{
  "type": "Feature",
  "properties": {
    "iso:country":"US",
    "sg:address":"1451 River Park Dr Ste 288",
    "sg:city":"Sacramento",
    "sg:classifiers":[
        {
            "category":"Banks & Credit Unions",
            "subcategory":"Bank",
            "type":"Services"
        },
        {
            "category":"Banks & Credit Unions",
            "subcategory":"Financial Services",
            "type":"Services"
        }
    ],
    "sg:phone":"+1 877 912 6858",
    "sg:postcode":"95815",
    "sg:province":"CA",
    "sg:tags":[
        "saving",
        "loan",
        "commercial",
        "banking",
        "internet"
    ],
    "sg:website":"https://www.bankofamerica.com/",
    "wof:name":"Bank of America",
    "wof:placetype":"venue"
},
  "geometry": {"coordinates":[-121.439781,38.597434],"type":"Point"}
}