{
  "type": "Feature",
  "properties": {
    "iso:country":"US",
    "sg:address":"2021 E 4th St",
    "sg:city":"Santa Ana",
    "sg:classifiers":[
        {
            "category":"Wholesale",
            "subcategory":"Electrical",
            "type":"Manufacturing & Wholesale Goods"
        }
    ],
    "sg:phone":"+1 714 547 3330",
    "sg:postcode":"92705",
    "sg:province":"CA",
    "sg:tags":[
        "conditioner",
        "parts",
        "appliance",
        "air"
    ],
    "wof:name":"Pacific Parts Sales Company",
    "wof:placetype":"venue"
},
  "geometry": {"coordinates":[-117.836645,33.748311],"type":"Point"}
}