{
  "type": "Feature",
  "properties": {
    "addr:full":"2257 Imperial Ave San Diego CA 92101",
    "addr:housenumber":"2257",
    "addr:postcode":"92101",
    "addr:street":"Imperial Ave",
    "iso:country":"US",
    "sg:address":"2257 Imperial Ave",
    "sg:city":"San Diego",
    "sg:classifiers":[
        {
            "category":"Retail",
            "subcategory":"Repair Shop",
            "type":"Services"
        }
    ],
    "sg:phone":"+1 619 696 9348",
    "sg:postcode":"92101",
    "sg:province":"CA",
    "sg:tags":[
        "welding"
    ],
    "wof:name":"Craftect Welding",
    "wof:placetype":"venue"
},
  "geometry": {"coordinates":[-117.142408,32.706317],"type":"Point"}
}