{
  "type": "Feature",
  "properties": {
    "addr:full":"1340 Pine St St Helena CA 94574",
    "addr:housenumber":"1340",
    "addr:postcode":"94574",
    "addr:street":"Pine St",
    "iso:country":"US",
    "sg:address":"1340 Pine St",
    "sg:city":"St Helena",
    "sg:classifiers":[
        {
            "category":"Building & Trades",
            "subcategory":"Electrical",
            "type":"Services"
        }
    ],
    "sg:phone":"+1 707 967 5529",
    "sg:postcode":"94574",
    "sg:province":"CA",
    "sg:tags":[
        "electric",
        "contractor"
    ],
    "wof:name":"BEI Construction Inc",
    "wof:placetype":"venue"
},
  "geometry": {"coordinates":[-122.47330700000001,38.505008],"type":"Point"}
}