{
  "type": "Feature",
  "properties": {
    "addr:full":"6614 Noble Ave Van Nuys CA 91405",
    "addr:housenumber":"6614",
    "addr:postcode":"91405",
    "addr:street":"Noble Ave",
    "iso:country":"US",
    "sg:address":"6614 Noble Ave",
    "sg:city":"Van Nuys",
    "sg:classifiers":[
        {
            "category":"Building & Trades",
            "subcategory":"Construction",
            "type":"Services"
        }
    ],
    "sg:phone":"+1 818 909 0375",
    "sg:postcode":"91405",
    "sg:province":"CA",
    "sg:tags":[
        "repairing",
        "remodeling",
        "contractor"
    ],
    "wof:name":"I M Electric & Remodeling Co",
    "wof:placetype":"venue"
},
  "geometry": {"coordinates":[-118.461743,34.191846],"type":"Point"}
}