{
  "type": "Feature",
  "properties": {
    "addr:full":"12338 Valley Blvd El Monte CA 91732",
    "addr:housenumber":"12338",
    "addr:postcode":"91732",
    "addr:street":"Valley Blvd",
    "iso:country":"US",
    "sg:address":"12338 Valley Blvd",
    "sg:city":"El Monte",
    "sg:classifiers":[
        {
            "category":"Professional",
            "subcategory":"Business Services",
            "type":"Services"
        },
        {
            "category":"Manufacturing",
            "subcategory":"Apparel",
            "type":"Manufacturing & Wholesale Goods"
        }
    ],
    "sg:phone":"+1 626 443 1337",
    "sg:postcode":"91732",
    "sg:province":"CA",
    "sg:tags":[
        "embroidery"
    ],
    "wof:name":"Rainbow Embroidery Inc",
    "wof:placetype":"venue"
},
  "geometry": {"coordinates":[-118.012547,34.05932],"type":"Point"}
}