{
  "type": "Feature",
  "properties": {
    "iso:country":"US",
    "sg:address":"7731 Katella Ave #D",
    "sg:city":"Stanton",
    "sg:classifiers":[
        {
            "category":"Personal",
            "subcategory":"Hair Removal",
            "type":"Services"
        }
    ],
    "sg:phone":"+1 714 797 3393",
    "sg:postcode":"90680",
    "sg:province":"CA",
    "wof:name":"Nisha's Threading",
    "wof:placetype":"venue"
},
  "geometry": {"coordinates":[-117.99786,33.803117],"type":"Point"}
}