{
  "type": "Feature",
  "properties": {
    "addr:full":"100 Universal City Universal City CA 91608",
    "addr:housenumber":"100",
    "addr:postcode":"91608",
    "addr:street":"Universal",
    "iso:country":"US",
    "sg:address":"100 Universal City",
    "sg:city":"Universal City",
    "sg:classifiers":[
        {
            "category":"Arts & Performance",
            "subcategory":"Arts Center",
            "type":"Entertainment"
        }
    ],
    "sg:phone":"+1 818 508 9600",
    "sg:postcode":"91608",
    "sg:province":"CA",
    "sg:website":"www.nbcuniversal.com",
    "wof:name":"NBC Universal Studios",
    "wof:placetype":"venue"
},
  "geometry": {"coordinates":[-118.359437,34.138328],"type":"Point"}
}