{
  "type": "Feature",
  "properties": {
    "addr:full":"5050 Del Mar Heights Rd San Diego CA 92130",
    "addr:housenumber":"5050",
    "addr:postcode":"92130",
    "addr:street":"Del Mar Heights Rd",
    "iso:country":"US",
    "sg:address":"5050 Del Mar Heights Rd",
    "sg:city":"San Diego",
    "sg:classifiers":[
        {
            "category":"Place Of Worship",
            "subcategory":"Synagogue",
            "type":"Public Place"
        }
    ],
    "sg:phone":"+1 858 481 2893",
    "sg:postcode":"92130",
    "sg:province":"CA",
    "wof:name":"Congregation Beth Am Preschool",
    "wof:placetype":"venue"
},
  "geometry": {"coordinates":[-117.20777,32.961686],"type":"Point"}
}