{
  "type": "Feature",
  "properties": {
    "iso:country":"US",
    "sg:address":"417 S Myrtle Ave",
    "sg:city":"Monrovia",
    "sg:classifiers":[
        {
            "category":"Shopping",
            "subcategory":"Clothing, Apparel, & Fashions",
            "type":"Retail Goods"
        }
    ],
    "sg:phone":"+1 626 358 9392",
    "sg:postcode":"91016",
    "sg:province":"CA",
    "sg:tags":[
        "children's",
        "clothing"
    ],
    "wof:name":"Little Sunshine",
    "wof:placetype":"venue"
},
  "geometry": {"coordinates":[-118.124061,34.147902],"type":"Point"}
}