{
  "type": "Feature",
  "properties": {
    "iso:country":"US",
    "sg:address":"11307 Hindry Ave",
    "sg:city":"Los Angeles",
    "sg:classifiers":[
        {
            "category":"Communications",
            "subcategory":"Film & Video Production",
            "type":"Services"
        }
    ],
    "sg:phone":"+1 310 670 8635",
    "sg:postcode":"90045",
    "sg:province":"CA",
    "sg:tags":[
        "motion",
        "picture",
        "studio",
        "producer"
    ],
    "wof:name":"Uncharted Territory",
    "wof:placetype":"venue"
},
  "geometry": {"coordinates":[-118.372426,33.933403],"type":"Point"}
}