{
  "type": "Feature",
  "properties": {
    "iso:country":"US",
    "sg:address":"2225 1st St",
    "sg:city":"Simi Valley",
    "sg:classifiers":[
        {
            "category":"Manufacturing",
            "subcategory":"Toys & Sporting Goods",
            "type":"Manufacturing & Wholesale Goods"
        }
    ],
    "sg:phone":"+1 805 306 0088",
    "sg:postcode":"93065",
    "sg:province":"CA",
    "sg:website":"www.gamesoftheheart.com",
    "wof:name":"Golden Sales",
    "wof:placetype":"venue"
},
  "geometry": {"coordinates":[-118.778971,34.27656],"type":"Point"}
}