{
  "type": "Feature",
  "properties": {
    "addr:full":"3841 E Sierra Madre Sierra Madre CA 91024",
    "addr:housenumber":"3841",
    "addr:postcode":"91024",
    "addr:street":"E Sierra Madre;Madre",
    "iso:country":"US",
    "sg:address":"3841 E Sierra Madre",
    "sg:city":"Sierra Madre",
    "sg:classifiers":[
        {
            "category":"Retail",
            "subcategory":"Portrait Studio",
            "type":"Services"
        },
        {
            "category":"Food & Beverages",
            "subcategory":"Groceries & Convenience Stores",
            "type":"Retail Goods"
        }
    ],
    "sg:phone":"+1 626 351 0076",
    "sg:postcode":"91024",
    "sg:province":"CA",
    "sg:tags":[
        "photography"
    ],
    "wof:name":"Albertson's Food & Drug",
    "wof:placetype":"venue"
},
  "geometry": {"coordinates":[-118.05300099999999,34.165001],"type":"Point"}
}