{
  "type": "Feature",
  "properties": {
    "addr:full":"878 Rose Blossom Dr Cupertino CA 95014",
    "addr:housenumber":"878",
    "addr:postcode":"95014",
    "addr:street":"Rose Blossom Dr",
    "iso:country":"US",
    "sg:address":"878 Rose Blossom Dr",
    "sg:city":"Cupertino",
    "sg:classifiers":[
        {
            "category":"Professional",
            "subcategory":"Printing & Photocopies",
            "type":"Services"
        }
    ],
    "sg:phone":"+1 310 933 3302",
    "sg:postcode":"95014",
    "sg:province":"CA",
    "sg:website":"www.ooshirts.com",
    "wof:name":"ooShirts",
    "wof:placetype":"venue"
},
  "geometry": {"coordinates":[-122.04367499999999,37.31339],"type":"Point"}
}