{
  "type": "Feature",
  "properties": {
    "addr:full":"746 Torreya Ct Palo Alto CA 94303",
    "addr:housenumber":"746",
    "addr:postcode":"94303",
    "addr:street":"Torreya Ct",
    "iso:country":"US",
    "sg:address":"746 Torreya Ct",
    "sg:city":"Palo Alto",
    "sg:classifiers":[
        {
            "category":"Health Services",
            "subcategory":"Health Practitioner",
            "type":"Services"
        }
    ],
    "sg:phone":"+1 650 424 1700",
    "sg:postcode":"94303",
    "sg:province":"CA",
    "sg:tags":[
        "psychologist"
    ],
    "wof:name":"Virginia A Price PHD",
    "wof:placetype":"venue"
},
  "geometry": {"coordinates":[-122.12050600000001,37.429469],"type":"Point"}
}