{
  "type": "Feature",
  "properties": {
    "addr:full":"4241 Jutland Dr San Diego CA 92117",
    "addr:housenumber":"4241",
    "addr:postcode":"92117",
    "addr:street":"Jutland Dr",
    "iso:country":"US",
    "sg:address":"4241 Jutland Dr",
    "sg:city":"San Diego",
    "sg:classifiers":[
        {
            "category":"Shopping",
            "subcategory":"Used Merchandise",
            "type":"Retail Goods"
        }
    ],
    "sg:phone":"+1 858 273 2925",
    "sg:postcode":"92117",
    "sg:province":"CA",
    "sg:tags":[
        "furniture"
    ],
    "wof:name":"Business Tech",
    "wof:placetype":"venue"
},
  "geometry": {"coordinates":[-117.227501,32.824475],"type":"Point"}
}