{
  "type": "Feature",
  "properties": {
    "iso:country":"US",
    "sg:address":"721 Nevada St Ste 402",
    "sg:city":"Redlands",
    "sg:classifiers":[
        {
            "category":"Sports & Exercise",
            "subcategory":"Gym",
            "type":"Entertainment"
        }
    ],
    "sg:phone":"+1 909 798 8989",
    "sg:postcode":"92373",
    "sg:province":"CA",
    "sg:tags":[
        "yoga"
    ],
    "wof:name":"Redlands Yoga",
    "wof:placetype":"venue"
},
  "geometry": {"coordinates":[-117.217628,34.196413],"type":"Point"}
}