{
  "type": "Feature",
  "properties": {
    "addr:full":"2021 Edwin Way Sacramento CA 95825",
    "addr:housenumber":"2021",
    "addr:postcode":"95825",
    "addr:street":"Edwin Way",
    "iso:country":"US",
    "sg:address":"2021 Edwin Way",
    "sg:city":"Sacramento",
    "sg:classifiers":[
        {
            "category":"Building & Trades",
            "subcategory":"Construction",
            "type":"Services"
        }
    ],
    "sg:phone":"+1 916 564 2671",
    "sg:postcode":"95825",
    "sg:province":"CA",
    "sg:tags":[
        "contractor",
        "mechanical"
    ],
    "wof:name":"Air Repair Mechanical Service",
    "wof:placetype":"venue"
},
  "geometry": {"coordinates":[-121.41962700000001,38.606187],"type":"Point"}
}