{
  "type": "Feature",
  "properties": {
    "addr:full":"4000 Irving St San Francisco CA 94122",
    "addr:housenumber":"4000",
    "addr:postcode":"94122",
    "addr:street":"Irving St",
    "iso:country":"US",
    "sg:address":"4000 Irving St",
    "sg:city":"San Francisco",
    "sg:classifiers":[
        {
            "category":"Building & Trades",
            "subcategory":"Construction",
            "type":"Services"
        }
    ],
    "sg:phone":"+1 415 564 9035",
    "sg:postcode":"94122",
    "sg:province":"CA",
    "sg:tags":[
        "project"
    ],
    "wof:name":"Cassidy Construction Inc",
    "wof:placetype":"venue"
},
  "geometry": {"coordinates":[-122.50176999999999,37.762474],"type":"Point"}
}