{
  "type": "Feature",
  "properties": {
    "addr:full":"4200 Ming Ave Bakersfield CA 93309",
    "addr:housenumber":"4200",
    "addr:postcode":"93309",
    "addr:street":"Ming Ave",
    "iso:country":"US",
    "sg:address":"4200 Ming Ave",
    "sg:city":"Bakersfield",
    "sg:classifiers":[
        {
            "category":"Shopping",
            "subcategory":"Department Store",
            "type":"Retail Goods"
        },
        {
            "category":"Shopping",
            "subcategory":"Discount & Variety Stores",
            "type":"Retail Goods"
        }
    ],
    "sg:phone":"+1 661 836 6699",
    "sg:postcode":"93309",
    "sg:province":"CA",
    "sg:website":"http://www.bargainw.com",
    "wof:name":"99 Cents Only Stores",
    "wof:placetype":"venue"
},
  "geometry": {"coordinates":[-119.049091,35.339635],"type":"Point"}
}