{
  "type": "Feature",
  "properties": {
    "addr:full":"99 N Milpitas Blvd Milpitas CA 95035",
    "addr:housenumber":"99",
    "addr:postcode":"95035",
    "addr:street":"N Milpitas Blvd",
    "iso:country":"US",
    "sg:address":"99 N Milpitas Blvd",
    "sg:city":"Milpitas",
    "sg:classifiers":[
        {
            "category":"Restaurant",
            "type":"Food & Drink"
        }
    ],
    "sg:menulink":"http://www.allmenus.com/ca/san-jose/216792-mcdonalds/menu/",
    "sg:postcode":"95035",
    "sg:province":"CA",
    "sg:tags":[
        "burger",
        "american"
    ],
    "wof:name":"McDonald's",
    "wof:placetype":"venue"
},
  "geometry": {"coordinates":[-121.901369,37.434444],"type":"Point"}
}