{
  "type": "Feature",
  "properties": {
    "addr:full":"944 McCourtney Rd Grass Valley CA 95949",
    "addr:housenumber":"944",
    "addr:postcode":"95949",
    "addr:street":"Mccourtney Rd",
    "iso:country":"US",
    "sg:address":"944 McCourtney Rd",
    "sg:city":"Grass Valley",
    "sg:classifiers":[
        {
            "category":"Building & Trades",
            "subcategory":"Construction",
            "type":"Services"
        }
    ],
    "sg:phone":"+1 530 477 1916",
    "sg:postcode":"95949",
    "sg:province":"CA",
    "sg:tags":[
        "paving",
        "contractor"
    ],
    "wof:name":"Franza Enterprises Inc",
    "wof:placetype":"venue"
},
  "geometry": {"coordinates":[-121.070089,39.209338],"type":"Point"}
}