{
  "type": "Feature",
  "properties": {
    "iso:country":"US",
    "sg:address":"12049 Paramount Blvd",
    "sg:city":"Downey",
    "sg:classifiers":[
        {
            "category":"Personal",
            "subcategory":"Beauty Salon",
            "type":"Services"
        }
    ],
    "sg:phone":"+1 562 927 2345",
    "sg:postcode":"90242",
    "sg:province":"CA",
    "wof:name":"Andrea's Hair Fashions",
    "wof:placetype":"venue"
},
  "geometry": {"coordinates":[-118.14651000000001,33.931365],"type":"Point"}
}