{
  "type": "Feature",
  "properties": {
    "addr:full":"1591 Misty Wood Dr Roseville CA 95747",
    "addr:housenumber":"1591",
    "addr:postcode":"95747",
    "addr:street":"Misty Wood Dr",
    "iso:country":"US",
    "sg:address":"1591 Misty Wood Dr",
    "sg:city":"Roseville",
    "sg:classifiers":[
        {
            "category":"Building & Trades",
            "subcategory":"Construction",
            "type":"Services"
        }
    ],
    "sg:phone":"+1 415 633 2212",
    "sg:postcode":"95747",
    "sg:province":"CA",
    "sg:tags":[
        "industrial",
        "deck",
        "altering",
        "builder",
        "contractor",
        "contractors-commercial",
        "remodeling"
    ],
    "wof:name":"SBC Contractors, Inc.",
    "wof:placetype":"venue"
},
  "geometry": {"coordinates":[-121.318443,38.779148],"type":"Point"}
}