{
  "type": "Feature",
  "properties": {
    "iso:country":"US",
    "sg:address":"17 Merion Cir",
    "sg:city":"Napa",
    "sg:classifiers":[
        {
            "category":"Professional",
            "subcategory":"Management & Consulting",
            "type":"Services"
        }
    ],
    "sg:phone":"+1 707 224 0112",
    "sg:postcode":"94558",
    "sg:province":"CA",
    "sg:tags":[
        "consultant",
        "business"
    ],
    "wof:name":"Bailly-Jacobs Consulting",
    "wof:placetype":"venue"
},
  "geometry": {"coordinates":[-122.25468,38.347728],"type":"Point"}
}