{
  "type": "Feature",
  "properties": {
    "acgov:api":"942.0",
    "acgov:type":"ES",
    "addr:full":"21201 Independent School Road Castro Valley CA",
    "wof:categories":[
        "education_and_religion:education=school"
    ],
    "wof:name":"Independent Elementary",
    "wof:placetype":"venue"
},
  "geometry": {"coordinates":[-122.04935528220079,37.69790926032088],"type":"Point"}
}