{
  "type": "Feature",
  "properties": {
    "addr:full":"331 D St Marysville CA 95901",
    "addr:housenumber":"331",
    "addr:postcode":"95901",
    "addr:street":"D St",
    "iso:country":"US",
    "sg:address":"331 D St",
    "sg:city":"Marysville",
    "sg:classifiers":[
        {
            "category":"Shopping",
            "subcategory":"Musical Instruments",
            "type":"Retail Goods"
        }
    ],
    "sg:phone":"+1 530 743 6466",
    "sg:postcode":"95901",
    "sg:province":"CA",
    "wof:name":"Marysville Music",
    "wof:placetype":"venue"
},
  "geometry": {"coordinates":[-121.58872599999999,39.138903],"type":"Point"}
}