{
  "type": "Feature",
  "properties": {
    "iso:country":"US",
    "sg:address":"13125 S Broadway",
    "sg:city":"Los Angeles",
    "sg:classifiers":[
        {
            "category":"Manufacturing",
            "subcategory":"Chemicals & Compounds",
            "type":"Manufacturing & Wholesale Goods"
        }
    ],
    "sg:phone":"+1 310 515 5260",
    "sg:postcode":"90061",
    "sg:province":"CA",
    "sg:tags":[
        "inorganic",
        "industrial",
        "mfg"
    ],
    "wof:name":"California Bionuclear Corp",
    "wof:placetype":"venue"
},
  "geometry": {"coordinates":[-118.278412,33.91256],"type":"Point"}
}