{
  "type": "Feature",
  "properties": {
    "iso:country":"US",
    "sg:address":"164 W Live Oak Ave",
    "sg:city":"Arcadia",
    "sg:classifiers":[
        {
            "category":"Wholesale",
            "subcategory":"Hardware",
            "type":"Manufacturing & Wholesale Goods"
        }
    ],
    "sg:phone":"+1 626 294 9888",
    "sg:postcode":"91007",
    "sg:province":"CA",
    "sg:tags":[
        "air",
        "parts",
        "conditioning",
        "supply"
    ],
    "wof:name":"T & L Air Conditioning Inc",
    "wof:placetype":"venue"
},
  "geometry": {"coordinates":[-118.036999,34.106413],"type":"Point"}
}