{
  "type": "Feature",
  "properties": {
    "addr:full":"17737 Sherman Way Reseda CA 91335",
    "addr:housenumber":"17737",
    "addr:postcode":"91335",
    "addr:street":"Sherman Way",
    "iso:country":"US",
    "sg:address":"17737 Sherman Way",
    "sg:city":"Reseda",
    "sg:classifiers":[
        {
            "category":"Shopping",
            "type":"Retail Goods"
        }
    ],
    "sg:phone":"+1 818 344 7665",
    "sg:postcode":"91335",
    "sg:province":"CA",
    "sg:tags":[
        "equipment",
        "pool",
        "swimming"
    ],
    "wof:name":"Swimming Pool Shop",
    "wof:placetype":"venue"
},
  "geometry": {"coordinates":[-118.52068800000001,34.201089],"type":"Point"}
}