{
  "type": "Feature",
  "properties": {
    "iso:country":"US",
    "sg:address":"1308 12th Ave",
    "sg:city":"Los Angeles",
    "sg:classifiers":[
        {
            "category":"Shopping",
            "subcategory":"Clothing, Apparel, & Fashions",
            "type":"Retail Goods"
        }
    ],
    "sg:phone":"+1 323 731 8266",
    "sg:postcode":"90019",
    "sg:province":"CA",
    "wof:name":"Mecca Clothing Design",
    "wof:placetype":"venue"
},
  "geometry": {"coordinates":[-118.326189,34.044068],"type":"Point"}
}