{
  "type": "Feature",
  "properties": {
    "addr:full":"570 Cherry Ave Los Altos CA 94022",
    "addr:housenumber":"570",
    "addr:postcode":"94022",
    "addr:street":"Cherry Ave",
    "iso:country":"US",
    "sg:address":"570 Cherry Ave",
    "sg:city":"Los Altos",
    "sg:classifiers":[
        {
            "category":"Travel",
            "subcategory":"Hotels & Motels",
            "type":"Entertainment"
        }
    ],
    "sg:phone":"+1 650 589 7500",
    "sg:postcode":"94022",
    "sg:province":"CA",
    "sg:tags":[
        "operation"
    ],
    "wof:name":"Comfort Inn",
    "wof:placetype":"venue"
},
  "geometry": {"coordinates":[-122.117548,37.391417],"type":"Point"}
}