{
  "type": "Feature",
  "properties": {
    "iso:country":"US",
    "sg:address":"9821 Catherine Ave",
    "sg:city":"Garden Grove",
    "sg:classifiers":[
        {
            "category":"Education",
            "subcategory":"School",
            "type":"Public Place"
        }
    ],
    "sg:phone":"+1 714 663 6556",
    "sg:postcode":"92841",
    "sg:province":"CA",
    "sg:tags":[
        "elementary"
    ],
    "sg:website":"www.ggusd.k12.ca.us",
    "wof:name":"Brookhurst Elementary School",
    "wof:placetype":"venue"
},
  "geometry": {"coordinates":[-117.959999,33.7836],"type":"Point"}
}