{
  "type": "Feature",
  "properties": {
    "addr:full":"3417 Hugo St San Diego CA 92106",
    "addr:housenumber":"3417",
    "addr:postcode":"92106",
    "addr:street":"Hugo St",
    "iso:country":"US",
    "sg:address":"3417 Hugo St",
    "sg:city":"San Diego",
    "sg:classifiers":[
        {
            "category":"Building & Trades",
            "subcategory":"Equipment Rental",
            "type":"Services"
        }
    ],
    "sg:phone":"+1 619 222 1984",
    "sg:postcode":"92106",
    "sg:province":"CA",
    "sg:tags":[
        "aircraft",
        "leasing"
    ],
    "wof:name":"Gustave Schwartz",
    "wof:placetype":"venue"
},
  "geometry": {"coordinates":[-117.232692,32.72902],"type":"Point"}
}