{
  "type": "Feature",
  "properties": {
    "iso:country":"US",
    "sg:address":"90 Diablo View Rd",
    "sg:city":"Orinda",
    "sg:classifiers":[
        {
            "category":"Professional",
            "type":"Services"
        }
    ],
    "sg:phone":"+1 925 253 0937",
    "sg:postcode":"94563",
    "sg:province":"CA",
    "wof:name":"Breznikar Family LLC",
    "wof:placetype":"venue"
},
  "geometry": {"coordinates":[-122.170235,37.906531],"type":"Point"}
}