{
  "type": "Feature",
  "properties": {
    "iso:country":"US",
    "sg:address":"11102 Songish St",
    "sg:city":"Garden Grove",
    "sg:classifiers":[
        {
            "category":"Autos & Motor Vehicles",
            "subcategory":"Automobile Sales",
            "type":"Retail Goods"
        }
    ],
    "sg:phone":"+1 714 530 5177",
    "sg:postcode":"92840",
    "sg:province":"CA",
    "sg:tags":[
        "limo"
    ],
    "wof:name":"Black Dog Limo",
    "wof:placetype":"venue"
},
  "geometry": {"coordinates":[-117.95509300000001,33.801713],"type":"Point"}
}