{
  "type": "Feature",
  "properties": {
    "iso:country":"US",
    "sg:address":"816 W Big Bear Blvd",
    "sg:city":"Big Bear City",
    "sg:classifiers":[
        {
            "category":"Health Services",
            "subcategory":"Clinic",
            "type":"Services"
        }
    ],
    "sg:phone":"+1 909 584 5261",
    "sg:postcode":"92314",
    "sg:province":"CA",
    "sg:tags":[
        "home",
        "care"
    ],
    "wof:name":"Nursefinders",
    "wof:placetype":"venue"
},
  "geometry": {"coordinates":[-116.859844,34.260382],"type":"Point"}
}