{
  "type": "Feature",
  "properties": {
    "iso:country":"US",
    "sg:address":"360 Oakdale Dr",
    "sg:city":"Claremont",
    "sg:classifiers":[
        {
            "category":"Wholesale",
            "subcategory":"Hardware",
            "type":"Manufacturing & Wholesale Goods"
        }
    ],
    "sg:phone":"+1 909 625 7264",
    "sg:postcode":"91711",
    "sg:province":"CA",
    "sg:tags":[
        "refrigeration"
    ],
    "wof:name":"Delta Refregeration",
    "wof:placetype":"venue"
},
  "geometry": {"coordinates":[-117.70786200000001,34.091477],"type":"Point"}
}