{
  "type": "Feature",
  "properties": {
    "addr:full":"10247 Macarthur Blvd Oakland CA 94605",
    "addr:housenumber":"10247",
    "addr:postcode":"94605",
    "addr:street":"Macarthur Blvd",
    "iso:country":"US",
    "sg:address":"10247 Macarthur Blvd",
    "sg:city":"Oakland",
    "sg:classifiers":[
        {
            "category":"Personal",
            "subcategory":"Beauty Salon",
            "type":"Services"
        }
    ],
    "sg:phone":"+1 510 635 8901",
    "sg:postcode":"94605",
    "sg:province":"CA",
    "wof:name":"Telegraph Beauty Supply & Sln",
    "wof:placetype":"venue"
},
  "geometry": {"coordinates":[-122.15428900000001,37.744555],"type":"Point"}
}