{
  "type": "Feature",
  "properties": {
    "addr:full":"595 Buckingham Way Ste 525 San Francisco CA 94132",
    "addr:housenumber":"595",
    "addr:postcode":"94132",
    "addr:street":"Buckingham Way Ste 525",
    "iso:country":"US",
    "sg:address":"595 Buckingham Way Ste 525",
    "sg:city":"San Francisco",
    "sg:classifiers":[
        {
            "category":"Health Services",
            "subcategory":"Doctor",
            "type":"Services"
        }
    ],
    "sg:phone":"+1 415 902 6248",
    "sg:postcode":"94132",
    "sg:province":"CA",
    "sg:tags":[
        "surgeon",
        "oral"
    ],
    "wof:name":"Dr. Cletus Chen, DDS",
    "wof:placetype":"venue"
},
  "geometry": {"coordinates":[-122.47954300000001,37.729561],"type":"Point"}
}