{
  "type": "Feature",
  "properties": {
    "addr:full":"1122 Missouri St Fairfield CA 94533",
    "addr:housenumber":"1122",
    "addr:postcode":"94533",
    "addr:street":"Missouri St",
    "iso:country":"US",
    "sg:address":"1122 Missouri St",
    "sg:city":"Fairfield",
    "sg:classifiers":[
        {
            "category":"Communications",
            "subcategory":"News Services",
            "type":"Services"
        },
        {
            "category":"Professional",
            "subcategory":"Printing & Photocopies",
            "type":"Services"
        },
        {
            "category":"Manufacturing",
            "subcategory":"Printing",
            "type":"Manufacturing & Wholesale Goods"
        }
    ],
    "sg:phone":"+1 707 426 2300",
    "sg:postcode":"94533",
    "sg:province":"CA",
    "sg:tags":[
        "fax",
        "form",
        "services-commercial",
        "duplicating",
        "printers-business",
        "imaging",
        "copying",
        "digital"
    ],
    "sg:website":"http://www.sirspeedy.com",
    "wof:name":"Sir Speedy",
    "wof:placetype":"venue"
},
  "geometry": {"coordinates":[-122.047515,38.248138],"type":"Point"}
}