{
  "type": "Feature",
  "properties": {
    "addr:full":"7415 Reservoir Rd Oroville CA 95966",
    "addr:housenumber":"7415",
    "addr:postcode":"95966",
    "addr:street":"Reservoir Rd",
    "iso:country":"US",
    "sg:address":"7415 Reservoir Rd",
    "sg:city":"Oroville",
    "sg:classifiers":[
        {
            "category":"Retail",
            "subcategory":"Repair Shop",
            "type":"Services"
        }
    ],
    "sg:phone":"+1 530 534 6466",
    "sg:postcode":"95966",
    "sg:province":"CA",
    "sg:tags":[
        "taxidermist"
    ],
    "wof:name":"Jack's Taxidermy",
    "wof:placetype":"venue"
},
  "geometry": {"coordinates":[-121.515013,39.429941],"type":"Point"}
}