{
  "type": "Feature",
  "properties": {
    "addr:full":"740 Ventura Blvd Camarillo CA 93010",
    "addr:housenumber":"740",
    "addr:postcode":"93010",
    "addr:street":"Ventura Blvd",
    "iso:country":"US",
    "sg:address":"740 Ventura Blvd",
    "sg:city":"Camarillo",
    "sg:classifiers":[
        {
            "category":"Manufacturing",
            "subcategory":"Apparel",
            "type":"Manufacturing & Wholesale Goods"
        },
        {
            "category":"Shopping",
            "subcategory":"Bicycles & Sporting Goods",
            "type":"Retail Goods"
        }
    ],
    "sg:phone":"+1 805 445 8229",
    "sg:postcode":"93010",
    "sg:province":"CA",
    "sg:tags":[
        "equipment",
        "clothing",
        "skateboard",
        "mfg"
    ],
    "wof:name":"Beach Bums Board Shop",
    "wof:placetype":"venue"
},
  "geometry": {"coordinates":[-119.058465,34.217809],"type":"Point"}
}