{
  "type": "Feature",
  "properties": {
    "iso:country":"US",
    "sg:address":"8339 State Rte 26",
    "sg:city":"Stockton",
    "sg:classifiers":[
        {
            "category":"Food & Beverages",
            "subcategory":"Groceries & Convenience Stores",
            "type":"Retail Goods"
        }
    ],
    "sg:phone":"+1 209 931 0517",
    "sg:postcode":"95215",
    "sg:province":"CA",
    "sg:tags":[
        "grocer"
    ],
    "wof:name":"Shop-N-Buy Market",
    "wof:placetype":"venue"
},
  "geometry": {"coordinates":[-121.208361,37.980215],"type":"Point"}
}