{
  "type": "Feature",
  "properties": {
    "addr:full":"3023 Longview Ln Santa Ynez CA 93460",
    "addr:housenumber":"3023",
    "addr:postcode":"93460",
    "addr:street":"Longview Ln",
    "iso:country":"US",
    "sg:address":"3023 Longview Ln",
    "sg:city":"Santa Ynez",
    "sg:classifiers":[
        {
            "category":"Wholesale",
            "subcategory":"Groceries",
            "type":"Manufacturing & Wholesale Goods"
        }
    ],
    "sg:phone":"+1 805 688 7850",
    "sg:postcode":"93460",
    "sg:province":"CA",
    "sg:tags":[
        "water",
        "coffee"
    ],
    "wof:name":"Tri Cities Water & Coffee Inc",
    "wof:placetype":"venue"
},
  "geometry": {"coordinates":[-120.095816,34.624832],"type":"Point"}
}