{
  "type": "Feature",
  "properties": {
    "iso:country":"US",
    "sg:address":"9690 Saluda Ave",
    "sg:city":"Tujunga",
    "sg:classifiers":[
        {
            "category":"Professional",
            "type":"Services"
        }
    ],
    "sg:phone":"+1 818 541 9155",
    "sg:postcode":"91042",
    "sg:province":"CA",
    "sg:tags":[
        "processing",
        "data"
    ],
    "wof:name":"Advanced Data Entry Consultants",
    "wof:placetype":"venue"
},
  "geometry": {"coordinates":[-118.268125,34.241997],"type":"Point"}
}