{
  "type": "Feature",
  "properties": {
    "addr:full":"4452 Ingraham St San Diego CA 92109",
    "addr:housenumber":"4452",
    "addr:postcode":"92109",
    "addr:street":"Ingraham St",
    "iso:country":"US",
    "sg:address":"4452 Ingraham St",
    "sg:city":"San Diego",
    "sg:classifiers":[
        {
            "category":"Restaurant",
            "type":"Food & Drink"
        }
    ],
    "sg:phone":"+1 858 581 2233",
    "sg:postcode":"92109",
    "sg:province":"CA",
    "sg:tags":[
        "shop",
        "coffee"
    ],
    "wof:name":"Caffe Veloce",
    "wof:placetype":"venue"
},
  "geometry": {"coordinates":[-117.240773,32.799276],"type":"Point"}
}