{
  "type": "Feature",
  "properties": {
    "addr:full":"1918 Don Lee Pl Escondido CA 92029",
    "addr:housenumber":"1918",
    "addr:postcode":"92029",
    "addr:street":"Don Lee Pl",
    "iso:country":"US",
    "sg:address":"1918 Don Lee Pl",
    "sg:city":"Escondido",
    "sg:classifiers":[
        {
            "category":"Manufacturing",
            "subcategory":"Tools & Machinery",
            "type":"Manufacturing & Wholesale Goods"
        }
    ],
    "sg:phone":"+1 760 432 4367",
    "sg:postcode":"92029",
    "sg:province":"CA",
    "sg:tags":[
        "machine",
        "shop"
    ],
    "wof:name":"Amer-Mex Mfg Inc",
    "wof:placetype":"venue"
},
  "geometry": {"coordinates":[-117.120862,33.128053],"type":"Point"}
}