{
  "type": "Feature",
  "properties": {
    "addr:full":"90 Soda Bay Rd Lakeport CA 95453",
    "addr:postcode":"95453",
    "addr:street":"Soda Bay Rd",
    "iso:country":"US",
    "sg:address":"90 Soda Bay Rd",
    "sg:city":"Lakeport",
    "sg:classifiers":[
        {
            "category":"Retail",
            "subcategory":"Repair Shop",
            "type":"Services"
        }
    ],
    "sg:phone":"+1 707 263 6494",
    "sg:postcode":"95453",
    "sg:province":"CA",
    "sg:tags":[
        "repairing",
        "saw"
    ],
    "wof:name":"Bill's Saw Shop",
    "wof:placetype":"venue"
},
  "geometry": {"coordinates":[-122.908254,39.011944],"type":"Point"}
}