{
  "type": "Feature",
  "properties": {
    "addr:full":"13058 Stanbridge Ave Downey CA 90242",
    "addr:postcode":"13058;90242",
    "addr:street":"Stanbridge Ave",
    "iso:country":"US",
    "sg:address":"13058 Stanbridge Ave",
    "sg:city":"Downey",
    "sg:classifiers":[
        {
            "category":"Health Services",
            "subcategory":"Doctor",
            "type":"Services"
        }
    ],
    "sg:phone":"+1 323 569 4461",
    "sg:postcode":"90242",
    "sg:province":"CA",
    "sg:tags":[
        "physician",
        "family",
        "practice",
        "surgeons",
        "medicine"
    ],
    "wof:name":"Your Family Doctor",
    "wof:placetype":"venue"
},
  "geometry": {"coordinates":[-118.127788,33.911893],"type":"Point"}
}