{
  "type": "Feature",
  "properties": {
    "iso:country":"US",
    "sg:address":"4482 Market St",
    "sg:city":"Ventura",
    "sg:classifiers":[
        {
            "category":"Real Estate",
            "subcategory":"Architect",
            "type":"Services"
        }
    ],
    "sg:phone":"+1 805 658 8054",
    "sg:postcode":"93003",
    "sg:province":"CA",
    "wof:name":"LTA Architect",
    "wof:placetype":"venue"
},
  "geometry": {"coordinates":[-119.23342,34.257287],"type":"Point"}
}