{
  "type": "Feature",
  "properties": {
    "addr:full":"7941 Fair Oaks Blvd Carmichael CA 95608",
    "addr:housenumber":"7941",
    "addr:postcode":"95608",
    "addr:street":"Fair Oaks Blvd",
    "iso:country":"US",
    "sg:address":"7941 Fair Oaks Blvd",
    "sg:city":"Carmichael",
    "sg:classifiers":[
        {
            "category":"Sports & Exercise",
            "subcategory":"Gym",
            "type":"Entertainment"
        },
        {
            "category":"Arena",
            "subcategory":"Sports Club",
            "type":"Entertainment"
        }
    ],
    "sg:phone":"+1 916 944 2900",
    "sg:postcode":"95608",
    "sg:province":"CA",
    "sg:tags":[
        "health",
        "gymnasium"
    ],
    "sg:website":"www.californiafamilyfitness.com/...",
    "wof:name":"California Family Health & Fitness",
    "wof:placetype":"venue"
},
  "geometry": {"coordinates":[-121.316002,38.636799],"type":"Point"}
}