{
  "type": "Feature",
  "properties": {
    "addr:full":"10800 Torre Ave Cupertino CA 95014",
    "addr:postcode":"10800;95014",
    "addr:street":"Torre Ave",
    "iso:country":"US",
    "sg:address":"10800 Torre Ave",
    "sg:city":"Cupertino",
    "sg:phone":"+1 408 446 1677",
    "sg:postcode":"95014",
    "sg:province":"CA",
    "sg:website":"http://www.sccoe.net",
    "wof:name":"Cupertino Library",
    "wof:placetype":"venue"
},
  "geometry": {"coordinates":[-122.029257,37.316432],"type":"Point"}
}