{
  "type": "Feature",
  "properties": {
    "iso:country":"US",
    "sg:address":"1148 W Hammer Ln",
    "sg:city":"Stockton",
    "sg:classifiers":[
        {
            "category":"Health Services",
            "subcategory":"Doctor",
            "type":"Services"
        }
    ],
    "sg:phone":"+1 209 952 9696",
    "sg:postcode":"95209",
    "sg:province":"CA",
    "sg:tags":[
        "physician",
        "surgeons",
        "manipulative",
        "osteopathic",
        "treatment",
        "surgeon"
    ],
    "wof:name":"Stockton Urgent Care Medical",
    "wof:placetype":"venue"
},
  "geometry": {"coordinates":[-121.325862,38.020939],"type":"Point"}
}