{
  "type": "Feature",
  "properties": {
    "iso:country":"US",
    "sg:address":"729 E 18th St",
    "sg:city":"Antioch",
    "sg:classifiers":[
        {
            "category":"Autos & Motor Vehicles",
            "subcategory":"Auto Supplies",
            "type":"Retail Goods"
        }
    ],
    "sg:phone":"+1 925 757 8324",
    "sg:postcode":"94509",
    "sg:province":"CA",
    "sg:tags":[
        "parts",
        "foreign"
    ],
    "wof:name":"Strictly Foreign Auto Parts",
    "wof:placetype":"venue"
},
  "geometry": {"coordinates":[-121.793132,38.004984],"type":"Point"}
}