{
  "type": "Feature",
  "properties": {
    "addr:full":"141 N Vallejo Way Upland CA 91786",
    "addr:housenumber":"141",
    "addr:postcode":"91786",
    "addr:street":"N Vallejo Way",
    "iso:country":"US",
    "sg:address":"141 N Vallejo Way",
    "sg:city":"Upland",
    "sg:classifiers":[
        {
            "category":"Building & Trades",
            "subcategory":"Construction",
            "type":"Services"
        }
    ],
    "sg:phone":"+1 951 880 5108",
    "sg:postcode":"91786",
    "sg:province":"CA",
    "sg:tags":[
        "system",
        "contractor",
        "air conditioning"
    ],
    "wof:name":"Affordable Air Repairs",
    "wof:placetype":"venue"
},
  "geometry": {"coordinates":[-117.66011399999999,34.095375],"type":"Point"}
}