{
  "type": "Feature",
  "properties": {
    "addr:full":"1111 el Camino Real Santa Clara CA 95050",
    "addr:housenumber":"1111",
    "addr:postcode":"95050",
    "addr:street":"El Camino Real",
    "iso:country":"US",
    "sg:address":"1111 el Camino Real",
    "sg:city":"Santa Clara",
    "sg:classifiers":[
        {
            "category":"Food & Beverages",
            "subcategory":"Groceries & Convenience Stores",
            "type":"Retail Goods"
        },
        {
            "category":"Farming",
            "subcategory":"Poultry Farm",
            "type":"Manufacturing & Wholesale Goods"
        }
    ],
    "sg:phone":"+1 408 248 2347",
    "sg:postcode":"95050",
    "sg:province":"CA",
    "sg:tags":[
        "grocer",
        "egg",
        "chicken"
    ],
    "wof:name":"S K S Enterprises Inc",
    "wof:placetype":"venue"
},
  "geometry": {"coordinates":[-121.94891200000001,37.353785],"type":"Point"}
}