{
  "type": "Feature",
  "properties": {
    "addr:full":"2895 3rd St San Francisco CA 94107",
    "addr:housenumber":"2895",
    "addr:postcode":"94107",
    "addr:street":"3Rd St",
    "iso:country":"US",
    "sg:address":"2895 3rd St",
    "sg:city":"San Francisco",
    "sg:classifiers":[
        {
            "category":"Wholesale",
            "subcategory":"Scrap",
            "type":"Manufacturing & Wholesale Goods"
        }
    ],
    "sg:phone":"+1 415 821 3100",
    "sg:postcode":"94107",
    "sg:province":"CA",
    "sg:tags":[
        "auto",
        "material",
        "parts",
        "used"
    ],
    "wof:name":"Ajax Auto Dismantlers Inc",
    "wof:placetype":"venue"
},
  "geometry": {"coordinates":[-122.387771,37.754115],"type":"Point"}
}