{
  "type": "Feature",
  "properties": {
    "addr:full":"427 Linden Ave South San Francisco CA 94080",
    "addr:housenumber":"427",
    "addr:postcode":"94080",
    "addr:street":"Linden Ave",
    "iso:country":"US",
    "sg:address":"427 Linden Ave",
    "sg:city":"South San Francisco",
    "sg:classifiers":[
        {
            "category":"Building & Trades",
            "subcategory":"Locksmith",
            "type":"Services"
        }
    ],
    "sg:phone":"+1 650 742 6437",
    "sg:postcode":"94080",
    "sg:province":"CA",
    "sg:tags":[
        "key"
    ],
    "wof:name":"A Emergency A Locksmith",
    "wof:placetype":"venue"
},
  "geometry": {"coordinates":[-122.410004,37.656399],"type":"Point"}
}