{
  "type": "Feature",
  "properties": {
    "addr:full":"5443 Stockton Blvd Sacramento CA 95820",
    "addr:housenumber":"5443",
    "addr:postcode":"95820",
    "addr:street":"Stockton Blvd",
    "iso:country":"US",
    "sg:address":"5443 Stockton Blvd",
    "sg:city":"Sacramento",
    "sg:classifiers":[
        {
            "category":"Retail",
            "subcategory":"Auto Rental",
            "type":"Services"
        }
    ],
    "sg:phone":"+1 916 457 4430",
    "sg:postcode":"95820",
    "sg:province":"CA",
    "sg:tags":[
        "renting",
        "truck",
        "leasing"
    ],
    "wof:name":"U-Haul Co",
    "wof:placetype":"venue"
},
  "geometry": {"coordinates":[-121.44301900000001,38.526389],"type":"Point"}
}