{
  "type": "Feature",
  "properties": {
    "addr:full":"120 E Valley Blvd San Gabriel CA 91776",
    "addr:housenumber":"120",
    "addr:postcode":"91776",
    "addr:street":"E Valley Blvd",
    "iso:country":"US",
    "sg:address":"120 E Valley Blvd",
    "sg:city":"San Gabriel",
    "sg:classifiers":[
        {
            "category":"Shopping",
            "subcategory":"Clothing, Apparel, & Fashions",
            "type":"Retail Goods"
        }
    ],
    "sg:phone":"+1 626 572 9866",
    "sg:postcode":"91776",
    "sg:province":"CA",
    "wof:name":"Marie's Clothing",
    "wof:placetype":"venue"
},
  "geometry": {"coordinates":[-118.099084,34.079702],"type":"Point"}
}