{
  "type": "Feature",
  "properties": {
    "addr:full":"1555 16th St Oroville CA 95965",
    "addr:housenumber":"1555",
    "addr:postcode":"95965",
    "addr:street":"16Th St",
    "iso:country":"US",
    "sg:address":"1555 16th St",
    "sg:city":"Oroville",
    "sg:classifiers":[
        {
            "category":"Shopping",
            "subcategory":"Catalog Store",
            "type":"Retail Goods"
        }
    ],
    "sg:phone":"+1 530 534 0665",
    "sg:postcode":"95965",
    "sg:province":"CA",
    "sg:tags":[
        "mail",
        "house"
    ],
    "wof:name":"Sacred Treasures",
    "wof:placetype":"venue"
},
  "geometry": {"coordinates":[-121.600472,39.509758],"type":"Point"}
}