{
  "type": "Feature",
  "properties": {
    "addr:full":"9716 6th St Rancho Cucamonga CA 91730",
    "addr:housenumber":"9716",
    "addr:postcode":"91730",
    "addr:street":"6Th St",
    "iso:country":"US",
    "sg:address":"9716 6th St",
    "sg:city":"Rancho Cucamonga",
    "sg:classifiers":[
        {
            "category":"Utilities",
            "subcategory":"Refuse",
            "type":"Services"
        }
    ],
    "sg:phone":"+1 909 481 2285",
    "sg:postcode":"91730",
    "sg:province":"CA",
    "sg:tags":[
        "disposal",
        "waste"
    ],
    "wof:name":"Crime Scene Steri-Clean",
    "wof:placetype":"venue"
},
  "geometry": {"coordinates":[-117.587022,34.084798],"type":"Point"}
}