{
  "type": "Feature",
  "properties": {
    "addr:full":"685 S Alvarado St Los Angeles CA 90057",
    "addr:housenumber":"685",
    "addr:postcode":"90057",
    "addr:street":"S Alvarado St",
    "iso:country":"US",
    "sg:address":"685 S Alvarado St",
    "sg:city":"Los Angeles",
    "sg:classifiers":[
        {
            "category":"Shopping",
            "type":"Retail Goods"
        }
    ],
    "sg:postcode":"90057",
    "sg:province":"CA",
    "wof:name":"Westlake Theatre Swapmeet",
    "wof:placetype":"venue"
},
  "geometry": {"coordinates":[-118.27654200000001,34.056908],"type":"Point"}
}