{
  "type": "Feature",
  "properties": {
    "iso:country":"US",
    "sg:address":"15315 Magnolia Blvd",
    "sg:city":"Sherman Oaks",
    "sg:classifiers":[
        {
            "category":"Building & Trades",
            "subcategory":"Construction",
            "type":"Services"
        }
    ],
    "sg:phone":"+1 818 907 6622",
    "sg:postcode":"91403",
    "sg:province":"CA",
    "wof:name":"Rm Building Maintenance",
    "wof:placetype":"venue"
},
  "geometry": {"coordinates":[-118.469285,34.164845],"type":"Point"}
}