{
  "type": "Feature",
  "properties": {
    "addr:full":"1779 E Main St Ventura CA 93001",
    "addr:housenumber":"1779",
    "addr:postcode":"93001",
    "addr:street":"E Main St",
    "iso:country":"US",
    "sg:address":"1779 E Main St",
    "sg:city":"Ventura",
    "sg:classifiers":[
        {
            "category":"Professional",
            "subcategory":"Lawyer & Legal Services",
            "type":"Services"
        }
    ],
    "sg:phone":"+1 805 641 5941",
    "sg:postcode":"93001",
    "sg:province":"CA",
    "sg:tags":[
        "attorney"
    ],
    "wof:name":"Sally F LA Macchia Law Office",
    "wof:placetype":"venue"
},
  "geometry": {"coordinates":[-119.27353100000001,34.27895],"type":"Point"}
}