{
  "type": "Feature",
  "properties": {
    "addr:full":"3614 State St Santa Barbara CA 93105",
    "addr:housenumber":"3614",
    "addr:postcode":"93105",
    "addr:street":"State St",
    "iso:country":"US",
    "sg:address":"3614 State St",
    "sg:city":"Santa Barbara",
    "sg:classifiers":[
        {
            "category":"Restaurant",
            "type":"Food & Drink"
        }
    ],
    "sg:menulink":"http://www.allmenus.com/ca/santa-barbara/8893-dennys/menu/",
    "sg:phone":"+1 805 898 4447",
    "sg:postcode":"93105",
    "sg:province":"CA",
    "sg:tags":[
        "american",
        "diner"
    ],
    "wof:name":"Denny's",
    "wof:placetype":"venue"
},
  "geometry": {"coordinates":[-119.740644,34.440499],"type":"Point"}
}