{
  "type": "Feature",
  "properties": {
    "addr:full":"12630 Carmenita Rd Santa Fe Springs CA 90670",
    "addr:housenumber":"12630",
    "addr:postcode":"90670",
    "addr:street":"Carmenita Rd",
    "iso:country":"US",
    "sg:address":"12630 Carmenita Rd",
    "sg:city":"Santa Fe Springs",
    "sg:classifiers":[
        {
            "category":"Retail",
            "subcategory":"Auto Repair",
            "type":"Services"
        }
    ],
    "sg:phone":"+1 562 926 8478",
    "sg:postcode":"90670",
    "sg:province":"CA",
    "sg:tags":[
        "repairing",
        "automobile"
    ],
    "wof:name":"Alfredo Body & Fender",
    "wof:placetype":"venue"
},
  "geometry": {"coordinates":[-118.046599,33.911747],"type":"Point"}
}