{
  "type": "Feature",
  "properties": {
    "iso:country":"US",
    "sg:address":"6455 Almaden Expressway",
    "sg:city":"San Jose",
    "sg:classifiers":[
        {
            "category":"Professional",
            "subcategory":"Accounting & Tax Preparation",
            "type":"Services"
        }
    ],
    "sg:phone":"+1 408 323 8505",
    "sg:postcode":"95120",
    "sg:province":"CA",
    "sg:tags":[
        "accountant"
    ],
    "wof:name":"Burriss & Company CPA",
    "wof:placetype":"venue"
},
  "geometry": {"coordinates":[-121.863157,37.222148],"type":"Point"}
}