{
  "type": "Feature",
  "properties": {
    "addr:full":"11237 Elliott Ave South El Monte CA 91733",
    "addr:housenumber":"11237",
    "addr:postcode":"91733",
    "addr:street":"Elliott Ave",
    "iso:country":"US",
    "sg:address":"11237 Elliott Ave",
    "sg:city":"South El Monte",
    "sg:classifiers":[
        {
            "category":"Wholesale",
            "subcategory":"Non-durable Goods",
            "type":"Manufacturing & Wholesale Goods"
        }
    ],
    "sg:phone":"+1 626 443 0289",
    "sg:postcode":"91733",
    "sg:province":"CA",
    "wof:name":"Memax Trading Inc",
    "wof:placetype":"venue"
},
  "geometry": {"coordinates":[-118.031266,34.058646],"type":"Point"}
}