{
  "type": "Feature",
  "properties": {
    "iso:country":"US",
    "sg:address":"1623 W 6th St",
    "sg:city":"Los Angeles",
    "sg:classifiers":[
        {
            "category":"Food & Beverages",
            "subcategory":"Meat & Fish",
            "type":"Retail Goods"
        }
    ],
    "sg:phone":"+1 213 484 9727",
    "sg:postcode":"90017",
    "sg:province":"CA",
    "sg:tags":[
        "shop"
    ],
    "wof:name":"Chino's Carniceria",
    "wof:placetype":"venue"
},
  "geometry": {"coordinates":[-118.269997,34.056999],"type":"Point"}
}