{
  "type": "Feature",
  "properties": {
    "addr:full":"1311 Whitley Ave Corcoran CA 93212",
    "addr:housenumber":"1311",
    "addr:postcode":"93212",
    "addr:street":"Whitley Ave",
    "iso:country":"US",
    "sg:address":"1311 Whitley Ave",
    "sg:city":"Corcoran",
    "sg:classifiers":[
        {
            "category":"Education",
            "subcategory":"Special Training",
            "type":"Public Place"
        }
    ],
    "sg:phone":"+1 559 992 8008",
    "sg:postcode":"93212",
    "sg:province":"CA",
    "sg:tags":[
        "boat"
    ],
    "wof:name":"Literacy Center",
    "wof:placetype":"venue"
},
  "geometry": {"coordinates":[-119.56367400000001,36.097969],"type":"Point"}
}