{
  "type": "Feature",
  "properties": {
    "iso:country":"US",
    "sg:address":"8632 S Sepulveda Blvd Ste 203",
    "sg:city":"Los Angeles",
    "sg:classifiers":[
        {
            "category":"Professional",
            "subcategory":"Computer Services",
            "type":"Services"
        }
    ],
    "sg:phone":"+1 310 215 1776",
    "sg:postcode":"90045",
    "sg:province":"CA",
    "sg:tags":[
        "repair"
    ],
    "wof:name":"1776 Inc",
    "wof:placetype":"venue"
},
  "geometry": {"coordinates":[-118.396004,33.9594],"type":"Point"}
}