{
  "type": "Feature",
  "properties": {
    "addr:full":"2301 Saint Pauls Way Modesto CA 95355",
    "addr:housenumber":"2301",
    "addr:postcode":"ca 95355",
    "addr:street":"Saint Pauls Way",
    "iso:country":"US",
    "sg:address":"2301 Saint Pauls Way",
    "sg:city":"Modesto",
    "sg:classifiers":[
        {
            "category":"Health Services",
            "subcategory":"Doctor",
            "type":"Services"
        }
    ],
    "sg:phone":"+1 209 578 4153",
    "sg:postcode":"95355",
    "sg:province":"CA",
    "sg:tags":[
        "dentist"
    ],
    "sg:website":"www.modestoperio.com",
    "wof:name":"Rena Bains DDS",
    "wof:placetype":"venue"
},
  "geometry": {"coordinates":[-120.954803,37.665492],"type":"Point"}
}