{
  "type": "Feature",
  "properties": {
    "addr:full":"South Coast Plaza 3333 Bear St Costa Mesa CA 92628",
    "addr:housenumber":"3333",
    "addr:postcode":"92628",
    "addr:street":"South;Bear St",
    "iso:country":"US",
    "sg:address":"South Coast Plaza 3333 Bear St",
    "sg:city":"Costa Mesa",
    "sg:classifiers":[
        {
            "category":"Shopping",
            "subcategory":"Clothing, Apparel, & Fashions",
            "type":"Retail Goods"
        }
    ],
    "sg:phone":"+1 714 966 1745",
    "sg:postcode":"92628",
    "sg:province":"CA",
    "sg:website":"www.hm.com",
    "wof:name":"H&M",
    "wof:placetype":"venue"
},
  "geometry": {"coordinates":[-117.893214,33.691183],"type":"Point"}
}