{
  "type": "Feature",
  "properties": {
    "addr:full":"4103 E Morada Ln Stockton CA 95212",
    "addr:housenumber":"4103",
    "addr:postcode":"95212",
    "addr:street":"E Morada Ln",
    "iso:country":"US",
    "sg:address":"4103 E Morada Ln",
    "sg:city":"Stockton",
    "sg:classifiers":[
        {
            "category":"Fast Food",
            "type":"Food & Drink"
        },
        {
            "category":"Restaurant",
            "type":"Food & Drink"
        }
    ],
    "sg:phone":"+1 209 474 8831",
    "sg:postcode":"95212",
    "sg:province":"CA",
    "sg:tags":[
        "take",
        "chinese"
    ],
    "sg:website":"http://www.pandaexpress.com",
    "wof:name":"Panda Express",
    "wof:placetype":"venue"
},
  "geometry": {"coordinates":[-121.256788,38.037319],"type":"Point"}
}