{
  "type": "Feature",
  "properties": {
    "addr:full":"5103 Marina Pacifica Dr Long Beach CA 90803",
    "addr:housenumber":"5103",
    "addr:postcode":"90803",
    "addr:street":"Marina Pacifica Dr",
    "iso:country":"US",
    "sg:address":"5103 Marina Pacifica Dr",
    "sg:city":"Long Beach",
    "sg:classifiers":[
        {
            "category":"Professional",
            "type":"Services"
        }
    ],
    "sg:phone":"+1 562 430 4971",
    "sg:postcode":"90803",
    "sg:province":"CA",
    "wof:name":"Tedi Cantalupo Inc",
    "wof:placetype":"venue"
},
  "geometry": {"coordinates":[-118.118619,33.761079],"type":"Point"}
}