{
  "type": "Feature",
  "properties": {
    "iso:country":"US",
    "sg:address":"5046 Commercial Cir",
    "sg:city":"Concord",
    "sg:classifiers":[
        {
            "category":"Building & Trades",
            "subcategory":"Plumbing",
            "type":"Services"
        }
    ],
    "sg:phone":"+1 925 827 0578",
    "sg:postcode":"94520",
    "sg:province":"CA",
    "sg:tags":[
        "conditioning",
        "air",
        "system",
        "contractor"
    ],
    "wof:name":"Conditioned Air Mechanical",
    "wof:placetype":"venue"
},
  "geometry": {"coordinates":[-122.030407,38.019847],"type":"Point"}
}