{
  "type": "Feature",
  "properties": {
    "addr:full":"17639 Cindy Ln Grass Valley CA 95945",
    "addr:housenumber":"17639",
    "addr:postcode":"95945",
    "addr:street":"Cindy Ln",
    "iso:country":"US",
    "sg:address":"17639 Cindy Ln",
    "sg:city":"Grass Valley",
    "sg:classifiers":[
        {
            "category":"Shopping",
            "subcategory":"Bicycles & Sporting Goods",
            "type":"Retail Goods"
        }
    ],
    "sg:phone":"+1 530 273 6876",
    "sg:postcode":"95945",
    "sg:province":"CA",
    "wof:name":"Cathyworks",
    "wof:placetype":"venue"
},
  "geometry": {"coordinates":[-120.963703,39.165183],"type":"Point"}
}