{
  "type": "Feature",
  "properties": {
    "iso:country":"US",
    "sg:address":"6512 San Fernando Rd",
    "sg:city":"Glendale",
    "sg:classifiers":[
        {
            "category":"Professional",
            "subcategory":"Employment Agencies",
            "type":"Services"
        },
        {
            "category":"Organizations",
            "subcategory":"Community Association",
            "type":"Services"
        }
    ],
    "sg:phone":"+1 818 242 2434",
    "sg:postcode":"91201",
    "sg:province":"CA",
    "sg:tags":[
        "employer"
    ],
    "wof:name":"Glendale Association For The Retarded Services",
    "wof:placetype":"venue"
},
  "geometry": {"coordinates":[-118.290722,34.16773],"type":"Point"}
}