{
  "type": "Feature",
  "properties": {
    "iso:country":"US",
    "sg:address":"8168 Garvey Ave",
    "sg:city":"Rosemead",
    "sg:classifiers":[
        {
            "category":"Banks & Credit Unions",
            "subcategory":"Bank",
            "type":"Services"
        }
    ],
    "sg:phone":"+1 626 572 4633",
    "sg:postcode":"91770",
    "sg:province":"CA",
    "sg:website":"www.eastwestbank.com",
    "wof:name":"East West Bank",
    "wof:placetype":"venue"
},
  "geometry": {"coordinates":[-118.091003,34.062698],"type":"Point"}
}