{
  "type": "Feature",
  "properties": {
    "iso:country":"US",
    "sg:address":"22749 Myrtle St",
    "sg:city":"Hayward",
    "sg:classifiers":[
        {
            "category":"Wholesale",
            "subcategory":"Toys & Hobbies",
            "type":"Manufacturing & Wholesale Goods"
        }
    ],
    "sg:phone":"+1 510 881 8169",
    "sg:postcode":"94541",
    "sg:province":"CA",
    "wof:name":"Marys Games",
    "wof:placetype":"venue"
},
  "geometry": {"coordinates":[-122.092157,37.666798],"type":"Point"}
}