{
  "type": "Feature",
  "properties": {
    "addr:full":"2537 N Ontario St Burbank CA 91504",
    "addr:housenumber":"2537",
    "addr:postcode":"91504",
    "addr:street":"N Ontario St",
    "iso:country":"US",
    "sg:address":"2537 N Ontario St",
    "sg:city":"Burbank",
    "sg:classifiers":[
        {
            "category":"Manufacturing",
            "subcategory":"Retail Goods",
            "type":"Manufacturing & Wholesale Goods"
        }
    ],
    "sg:phone":"+1 818 846 4491",
    "sg:postcode":"91504",
    "sg:province":"CA",
    "sg:tags":[
        "manufacturer"
    ],
    "sg:website":"www.adbco.com",
    "wof:name":"Adb Industries",
    "wof:placetype":"venue"
},
  "geometry": {"coordinates":[-118.34451199999999,34.198284],"type":"Point"}
}