{
  "type": "Feature",
  "properties": {
    "iso:country":"US",
    "sg:address":"710 Lakeway Dr",
    "sg:city":"Sunnyvale",
    "sg:classifiers":[
        {
            "category":"Travel",
            "subcategory":"Travel Agent",
            "type":"Entertainment"
        }
    ],
    "sg:phone":"+1 408 991 2288",
    "sg:postcode":"94085",
    "sg:province":"CA",
    "sg:tags":[
        "agency"
    ],
    "wof:name":"American Express",
    "wof:placetype":"venue"
},
  "geometry": {"coordinates":[-121.98821,37.387],"type":"Point"}
}