{
  "type": "Feature",
  "properties": {
    "addr:full":"745 Palmer Rd Walnut Creek CA 94596",
    "addr:housenumber":"745",
    "addr:postcode":"94596",
    "addr:street":"Palmer Rd",
    "iso:country":"US",
    "sg:address":"745 Palmer Rd",
    "sg:city":"Walnut Creek",
    "sg:classifiers":[
        {
            "category":"Building & Trades",
            "subcategory":"Construction",
            "type":"Services"
        }
    ],
    "sg:phone":"+1 925 935 4446",
    "sg:postcode":"94596",
    "sg:province":"CA",
    "sg:tags":[
        "contractor"
    ],
    "wof:name":"DDA Construction",
    "wof:placetype":"venue"
},
  "geometry": {"coordinates":[-122.032858,37.885783],"type":"Point"}
}