{
  "type": "Feature",
  "properties": {
    "iso:country":"US",
    "sg:address":"215 E Orangethorpe Ave",
    "sg:city":"Fullerton",
    "sg:classifiers":[
        {
            "category":"Professional",
            "subcategory":"Lawyer & Legal Services",
            "type":"Services"
        }
    ],
    "sg:phone":"+1 714 738 3724",
    "sg:postcode":"92832",
    "sg:province":"CA",
    "sg:tags":[
        "notary"
    ],
    "wof:name":"AAA Xpress Ship & Notary",
    "wof:placetype":"venue"
},
  "geometry": {"coordinates":[-117.921685,33.859677],"type":"Point"}
}