{
  "type": "Feature",
  "properties": {
    "iso:country":"US",
    "sg:address":"2967 Michelson Dr",
    "sg:city":"Irvine",
    "sg:classifiers":[
        {
            "category":"Wholesale",
            "subcategory":"Stationery",
            "type":"Manufacturing & Wholesale Goods"
        }
    ],
    "sg:phone":"+1 714 742 8260",
    "sg:postcode":"92612",
    "sg:province":"CA",
    "sg:tags":[
        "industry",
        "rep",
        "paper",
        "agency"
    ],
    "wof:name":"Innovative Paper Marketing LLC",
    "wof:placetype":"venue"
},
  "geometry": {"coordinates":[-117.84280800000001,33.670556],"type":"Point"}
}