{
  "type": "Feature",
  "properties": {
    "iso:country":"US",
    "sg:address":"44940 Silver Valley Rd",
    "sg:city":"Newberry Springs",
    "sg:classifiers":[
        {
            "category":"Organizations",
            "subcategory":"Religious Organization",
            "type":"Services"
        }
    ],
    "sg:phone":"+1 760 257 4191",
    "sg:postcode":"92365",
    "sg:province":"CA",
    "sg:tags":[
        "church"
    ],
    "wof:name":"Iglesia Evangelica Hespanic",
    "wof:placetype":"venue"
},
  "geometry": {"coordinates":[-116.674958,34.865638],"type":"Point"}
}