{
  "type": "Feature",
  "properties": {
    "iso:country":"US",
    "sg:address":"30139 Industrial Pkwy SW",
    "sg:city":"Hayward",
    "sg:classifiers":[
        {
            "category":"Place Of Worship",
            "type":"Public Place"
        },
        {
            "category":"Organizations",
            "subcategory":"Religious Organization",
            "type":"Services"
        }
    ],
    "sg:phone":"+1 510 489 2233",
    "sg:postcode":"94544",
    "sg:province":"CA",
    "sg:tags":[
        "church"
    ],
    "wof:name":"Purple Lotus Society of USA",
    "wof:placetype":"venue"
},
  "geometry": {"coordinates":[-122.066947,37.610566],"type":"Point"}
}