{
  "type": "Feature",
  "properties": {
    "addr:full":"5170 Orange Ave San Diego CA 92115",
    "addr:housenumber":"5170",
    "addr:postcode":"92115",
    "addr:street":"Orange Ave",
    "iso:country":"US",
    "sg:address":"5170 Orange Ave",
    "sg:city":"San Diego",
    "sg:classifiers":[
        {
            "category":"Professional",
            "subcategory":"Engineering",
            "type":"Services"
        }
    ],
    "sg:phone":"+1 619 563 8878",
    "sg:postcode":"92115",
    "sg:province":"CA",
    "sg:tags":[
        "engineer"
    ],
    "wof:name":"Building Experts Inc",
    "wof:placetype":"venue"
},
  "geometry": {"coordinates":[-117.083885,32.75312],"type":"Point"}
}