{
  "type": "Feature",
  "properties": {
    "addr:full":"38 Oakmont Dr Rancho Mirage CA 92270",
    "addr:housenumber":"38",
    "addr:postcode":"92270",
    "addr:street":"Oakmont Dr",
    "iso:country":"US",
    "sg:address":"38 Oakmont Dr",
    "sg:city":"Rancho Mirage",
    "sg:classifiers":[
        {
            "category":"Home & Garden",
            "subcategory":"Home Furnishings",
            "type":"Retail Goods"
        }
    ],
    "sg:phone":"+1 760 288 4885",
    "sg:postcode":"92270",
    "sg:province":"CA",
    "wof:name":"Angelo J Bragato",
    "wof:placetype":"venue"
},
  "geometry": {"coordinates":[-116.419104,33.787638],"type":"Point"}
}