{
  "type": "Feature",
  "properties": {
    "iso:country":"US",
    "sg:address":"6850 Five Star Blvd",
    "sg:city":"Rocklin",
    "sg:classifiers":[
        {
            "category":"Shopping",
            "type":"Retail Goods"
        }
    ],
    "sg:phone":"+1 916 788 1010",
    "sg:postcode":"95677",
    "sg:province":"CA",
    "sg:tags":[
        "spa",
        "hot",
        "tub"
    ],
    "wof:name":"Your Home Resort",
    "wof:placetype":"venue"
},
  "geometry": {"coordinates":[-121.26646,38.78189],"type":"Point"}
}