{
  "type": "Feature",
  "properties": {
    "iso:country":"US",
    "sg:address":"540 Delancey St",
    "sg:city":"San Francisco",
    "sg:classifiers":[
        {
            "category":"Professional",
            "subcategory":"Art Services",
            "type":"Services"
        }
    ],
    "sg:phone":"+1 415 227 4700",
    "sg:postcode":"94107",
    "sg:province":"CA",
    "sg:tags":[
        "graphic",
        "designer"
    ],
    "wof:name":"Hybrid Design",
    "wof:placetype":"venue"
},
  "geometry": {"coordinates":[-122.39122,37.784801],"type":"Point"}
}