{
  "type": "Feature",
  "properties": {
    "iso:country":"US",
    "sg:address":"12482 Washington Blvd",
    "sg:city":"Whittier",
    "sg:classifiers":[
        {
            "category":"Health Services",
            "subcategory":"Doctor",
            "type":"Services"
        }
    ],
    "sg:phone":"+1 562 698 2202",
    "sg:postcode":"90602",
    "sg:province":"CA",
    "sg:tags":[
        "physician",
        "surgeon"
    ],
    "wof:name":"B K Misto Inc",
    "wof:placetype":"venue"
},
  "geometry": {"coordinates":[-118.045366,33.967748],"type":"Point"}
}