{
  "type": "Feature",
  "properties": {
    "addr:full":"1814 E Front St Selma CA 93662",
    "addr:housenumber":"1814",
    "addr:postcode":"93662",
    "addr:street":"E Front St",
    "iso:country":"US",
    "sg:address":"1814 E Front St",
    "sg:city":"Selma",
    "sg:classifiers":[
        {
            "category":"Professional",
            "subcategory":"Lawyer & Legal Services",
            "type":"Services"
        }
    ],
    "sg:phone":"+1 559 896 2111",
    "sg:postcode":"93662",
    "sg:province":"CA",
    "sg:tags":[
        "attorney"
    ],
    "wof:name":"Shepard Shepard & Janian",
    "wof:placetype":"venue"
},
  "geometry": {"coordinates":[-119.611204,36.566695],"type":"Point"}
}