{
  "type": "Feature",
  "properties": {
    "addr:full":"2725 El Camino Real Santa Clara CA 95051",
    "addr:housenumber":"2725",
    "addr:postcode":"95051",
    "addr:street":"El Camino Real",
    "iso:country":"US",
    "sg:address":"2725 El Camino Real",
    "sg:city":"Santa Clara",
    "sg:classifiers":[
        {
            "category":"Personal",
            "subcategory":"Beauty Salon",
            "type":"Services"
        }
    ],
    "sg:phone":"+1 408 241 6411",
    "sg:postcode":"95051",
    "sg:province":"CA",
    "sg:tags":[
        "hair"
    ],
    "sg:website":"www.hairdesignsbykimberly.com",
    "wof:name":"Hair Designs by Kimberly",
    "wof:placetype":"venue"
},
  "geometry": {"coordinates":[-121.97583,37.352475],"type":"Point"}
}