{
  "type": "Feature",
  "properties": {
    "iso:country":"US",
    "sg:address":"800 Kennedy St",
    "sg:city":"Oakland",
    "sg:classifiers":[
        {
            "category":"Professional",
            "subcategory":"Advertising",
            "type":"Services"
        },
        {
            "category":"Professional",
            "subcategory":"Art Services",
            "type":"Services"
        },
        {
            "category":"Professional",
            "subcategory":"Printing & Photocopies",
            "type":"Services"
        }
    ],
    "sg:phone":"+1 510 533 5452",
    "sg:postcode":"94606",
    "sg:province":"CA",
    "sg:tags":[
        "graphic",
        "artist",
        "services-commercial",
        "commercial",
        "direct",
        "designer",
        "mail"
    ],
    "sg:website":"http://www.holtgraphicarts.com",
    "wof:name":"Holt Graphic Arts Inc.",
    "wof:placetype":"venue"
},
  "geometry": {"coordinates":[-122.23778799999999,37.778105],"type":"Point"}
}