{
  "type": "Feature",
  "properties": {
    "addr:full":"4939 E Andersen Ave Fresno CA 93727",
    "addr:housenumber":"4939",
    "addr:postcode":"93727",
    "addr:street":"E Andersen Ave",
    "iso:country":"US",
    "sg:address":"4939 E Andersen Ave",
    "sg:city":"Fresno",
    "sg:classifiers":[
        {
            "category":"Airline",
            "type":"Transportation"
        }
    ],
    "sg:phone":"+1 559 456 0543",
    "sg:postcode":"93727",
    "sg:province":"CA",
    "sg:tags":[
        "courier",
        "air"
    ],
    "wof:name":"Air Cargo Carriers Inc",
    "wof:placetype":"venue"
},
  "geometry": {"coordinates":[-119.728212,36.775907],"type":"Point"}
}