{
  "type": "Feature",
  "properties": {
    "iso:country":"US",
    "sg:address":"1933 S Broadway Ste 1053 at LA Mart",
    "sg:city":"Los Angeles",
    "sg:classifiers":[
        {
            "category":"Home & Garden",
            "subcategory":"Home Furnishings",
            "type":"Retail Goods"
        },
        {
            "category":"Building & Trades",
            "subcategory":"Construction",
            "type":"Services"
        },
        {
            "category":"Home & Garden",
            "subcategory":"Furniture",
            "type":"Retail Goods"
        }
    ],
    "sg:phone":"+1 213 748 8324",
    "sg:postcode":"90007",
    "sg:province":"CA",
    "sg:tags":[
        "interior",
        "decor",
        "design",
        "store"
    ],
    "sg:website":"www.rosenberggroup.net",
    "wof:name":"Rosenberg Group",
    "wof:placetype":"venue"
},
  "geometry": {"coordinates":[-118.266853,34.030805],"type":"Point"}
}