{
  "type": "Feature",
  "properties": {
    "addr:full":"504 Tamalpais Dr Corte Madera CA 94925",
    "addr:housenumber":"504",
    "addr:postcode":"94925",
    "addr:street":"Tamalpais Dr",
    "iso:country":"US",
    "sg:address":"504 Tamalpais Dr",
    "sg:city":"Corte Madera",
    "sg:classifiers":[
        {
            "category":"Professional",
            "subcategory":"Computer Services",
            "type":"Services"
        }
    ],
    "sg:phone":"+1 415 924 0308",
    "sg:postcode":"94925",
    "sg:province":"CA",
    "sg:tags":[
        "repair"
    ],
    "wof:name":"Mobile Tech",
    "wof:placetype":"venue"
},
  "geometry": {"coordinates":[-122.526465,37.925599],"type":"Point"}
}