{
  "type": "Feature",
  "properties": {
    "addr:full":"2917 Arabis Ct Antelope CA 95843",
    "addr:housenumber":"2917",
    "addr:postcode":"95843",
    "addr:street":"Arabis Ct",
    "iso:country":"US",
    "sg:address":"2917 Arabis Ct",
    "sg:city":"Antelope",
    "sg:classifiers":[
        {
            "category":"Utilities",
            "subcategory":"Telephone",
            "type":"Services"
        }
    ],
    "sg:phone":"+1 916 331 2178",
    "sg:postcode":"95843",
    "sg:province":"CA",
    "sg:tags":[
        "telecommunication"
    ],
    "wof:name":"Samsung Telcommunication",
    "wof:placetype":"venue"
},
  "geometry": {"coordinates":[-121.394942,38.722762],"type":"Point"}
}