{
  "type": "Feature",
  "properties": {
    "addr:full":"3800 Barham Boulevard Los Angeles CA 90068",
    "addr:housenumber":"3800",
    "addr:postcode":"90068",
    "addr:street":"Barham Boulevard",
    "iso:country":"US",
    "sg:address":"3800 Barham Boulevard",
    "sg:city":"Los Angeles",
    "sg:classifiers":[
        {
            "category":"Education",
            "subcategory":"University",
            "type":"Public Place"
        }
    ],
    "sg:phone":"+1 323 512 0096",
    "sg:postcode":"90068",
    "sg:province":"CA",
    "sg:tags":[
        "college"
    ],
    "wof:name":"University of Texas At Austin Los Angeles Center",
    "wof:placetype":"venue"
},
  "geometry": {"coordinates":[-118.341205,34.143669],"type":"Point"}
}