{
  "type": "Feature",
  "properties": {
    "iso:country":"US",
    "sg:address":"2222 Michelson Dr",
    "sg:city":"Irvine",
    "sg:classifiers":[
        {
            "category":"Restaurant",
            "type":"Food & Drink"
        }
    ],
    "sg:menulink":"http://www.allmenus.com/ca/central-coast/62354-taro/menu/",
    "sg:phone":"+1 949 261 9124",
    "sg:postcode":"92612",
    "sg:province":"CA",
    "sg:tags":[
        "japanese",
        "asian"
    ],
    "wof:name":"Taro",
    "wof:placetype":"venue"
},
  "geometry": {"coordinates":[-117.857477,33.676852],"type":"Point"}
}