{
  "type": "Feature",
  "properties": {
    "addr:full":"24529 State Hwy 88 Pioneer CA 95666",
    "addr:housenumber":"24529",
    "addr:postcode":"95666",
    "addr:street":"State Hwy 88",
    "iso:country":"US",
    "sg:address":"24529 State Hwy 88",
    "sg:city":"Pioneer",
    "sg:classifiers":[
        {
            "category":"Retail",
            "subcategory":"Repair Shop",
            "type":"Services"
        }
    ],
    "sg:phone":"+1 209 295 4407",
    "sg:postcode":"95666",
    "sg:province":"CA",
    "sg:tags":[
        "upholsterer"
    ],
    "wof:name":"Recovery Shop",
    "wof:placetype":"venue"
},
  "geometry": {"coordinates":[-120.562359,38.433423],"type":"Point"}
}