{
  "type": "Feature",
  "properties": {
    "addr:full":"311 California Street San Francisco CA 94104",
    "addr:housenumber":"311",
    "addr:postcode":"94104",
    "addr:street":"California Street",
    "iso:country":"US",
    "sg:address":"311 California Street",
    "sg:city":"San Francisco",
    "sg:classifiers":[
        {
            "category":"Professional",
            "subcategory":"Lawyer & Legal Services",
            "type":"Services"
        }
    ],
    "sg:phone":"+1 415 956 2828",
    "sg:postcode":"94104",
    "sg:province":"CA",
    "wof:name":"Prather Edwin K Atty",
    "wof:placetype":"venue"
},
  "geometry": {"coordinates":[-122.40003900000001,37.793264],"type":"Point"}
}