{
  "type": "Feature",
  "properties": {
    "addr:full":"2638 S Western Ave Los Angeles CA 90018",
    "addr:housenumber":"2638",
    "addr:postcode":"90018",
    "addr:street":"S Western Ave",
    "iso:country":"US",
    "sg:address":"2638 S Western Ave",
    "sg:city":"Los Angeles",
    "sg:classifiers":[
        {
            "category":"Organizations",
            "subcategory":"Religious Organization",
            "type":"Services"
        }
    ],
    "sg:phone":"+1 323 735 5110",
    "sg:postcode":"90018",
    "sg:province":"CA",
    "sg:tags":[
        "church"
    ],
    "wof:name":"Miracle Center Apostolic Chr",
    "wof:placetype":"venue"
},
  "geometry": {"coordinates":[-118.308869,34.031573],"type":"Point"}
}