{
  "type": "Feature",
  "properties": {
    "iso:country":"US",
    "sg:address":"16901 Main St",
    "sg:city":"Hesperia",
    "sg:phone":"+1 800 394 3064",
    "sg:postcode":"92345",
    "sg:province":"CA",
    "sg:website":"http://www.filitrac.com/Click.aspx?tid=BDEDC5D5EF8BAE3541B5938870DA3DDECE60F60FEE115906&FiliAff=15016&sid=99202&utm_source=YellowPages&utm_medium=ppc&utm_campaign=national&utm_term=92345",
    "wof:name":"Carpet Corral Carpet One Floor & Home",
    "wof:placetype":"venue"
},
  "geometry": {"coordinates":[-117.293499,34.42036],"type":"Point"}
}