{
  "type": "Feature",
  "properties": {
    "addr:full":"1345 Mission St San Francisco CA 94103",
    "addr:housenumber":"1345",
    "addr:postcode":"94103",
    "addr:street":"Mission St",
    "iso:country":"US",
    "sg:address":"1345 Mission St",
    "sg:city":"San Francisco",
    "sg:classifiers":[
        {
            "category":"Manufacturing",
            "subcategory":"Printing",
            "type":"Manufacturing & Wholesale Goods"
        }
    ],
    "sg:phone":"+1 415 626 2335",
    "sg:postcode":"94103",
    "sg:province":"CA",
    "sg:tags":[
        "commercial",
        "lithographic"
    ],
    "sg:website":"www.sfprintmasters.com",
    "wof:name":"Print Masters",
    "wof:placetype":"venue"
},
  "geometry": {"coordinates":[-122.415314,37.775672],"type":"Point"}
}