{
  "type": "Feature",
  "properties": {
    "addr:full":"9296 W Telephone Rd Ventura CA 93004",
    "addr:housenumber":"9296",
    "addr:postcode":"93004",
    "addr:street":"W Telephone Rd",
    "iso:country":"US",
    "sg:address":"9296 W Telephone Rd",
    "sg:city":"Ventura",
    "sg:classifiers":[
        {
            "category":"Retail",
            "subcategory":"Laundry & Dry Cleaning",
            "type":"Services"
        }
    ],
    "sg:phone":"+1 805 647 4744",
    "sg:postcode":"93004",
    "sg:province":"CA",
    "sg:tags":[
        "cleaners"
    ],
    "wof:name":"Paramount Cleaners",
    "wof:placetype":"venue"
},
  "geometry": {"coordinates":[-119.17384699999999,34.270888],"type":"Point"}
}