{
  "type": "Feature",
  "properties": {
    "addr:full":"10123 del Rio Rd Spring Valley CA 91977",
    "addr:housenumber":"10123",
    "addr:postcode":"91977",
    "addr:street":"Del Rio Rd",
    "iso:country":"US",
    "sg:address":"10123 del Rio Rd",
    "sg:city":"Spring Valley",
    "sg:classifiers":[
        {
            "category":"Social Services",
            "subcategory":"Adult Care",
            "type":"Services"
        }
    ],
    "sg:phone":"+1 619 670 2359",
    "sg:postcode":"91977",
    "sg:province":"CA",
    "sg:tags":[
        "home",
        "residential"
    ],
    "wof:name":"PAR Haven Retirement",
    "wof:placetype":"venue"
},
  "geometry": {"coordinates":[-116.97799500000001,32.742854],"type":"Point"}
}