{
  "type": "Feature",
  "properties": {
    "iso:country":"US",
    "sg:address":"1781 Junction Avenue",
    "sg:city":"San Jose",
    "sg:classifiers":[
        {
            "category":"Building & Trades",
            "subcategory":"Construction",
            "type":"Services"
        }
    ],
    "sg:phone":"+1 408 452 1615",
    "sg:postcode":"95112",
    "sg:province":"CA",
    "sg:tags":[
        "contractor"
    ],
    "sg:website":"www.marblecreationsinc.com",
    "wof:name":"Marble Creations",
    "wof:placetype":"venue"
},
  "geometry": {"coordinates":[-121.908691,37.379262],"type":"Point"}
}