{
  "type": "Feature",
  "properties": {
    "iso:country":"US",
    "sg:address":"48858 Sauvignon Ct",
    "sg:city":"Fremont",
    "sg:classifiers":[
        {
            "category":"Shopping",
            "subcategory":"Clothing, Apparel, & Fashions",
            "type":"Retail Goods"
        }
    ],
    "sg:phone":"+1 510 498 1999",
    "sg:postcode":"94539",
    "sg:province":"CA",
    "wof:name":"Aashiana Fashions",
    "wof:placetype":"venue"
},
  "geometry": {"coordinates":[-121.91224200000001,37.466612],"type":"Point"}
}