{
  "type": "Feature",
  "properties": {
    "iso:country":"US",
    "sg:address":"5800 Geary Blvd",
    "sg:city":"San Francisco",
    "sg:classifiers":[
        {
            "category":"Restaurant",
            "type":"Food & Drink"
        }
    ],
    "sg:phone":"+1 415 379 6720",
    "sg:postcode":"94121",
    "sg:province":"CA",
    "wof:name":"Socca Restaurant",
    "wof:placetype":"venue"
},
  "geometry": {"coordinates":[-122.482592,37.780189],"type":"Point"}
}