{
  "type": "Feature",
  "properties": {
    "addr:full":"408 E Valley Blvd Alhambra CA 91801",
    "addr:housenumber":"408",
    "addr:postcode":"91801",
    "addr:street":"E Valley Blvd",
    "iso:country":"US",
    "sg:address":"408 E Valley Blvd",
    "sg:city":"Alhambra",
    "sg:classifiers":[
        {
            "category":"Food & Beverages",
            "subcategory":"Groceries & Convenience Stores",
            "type":"Retail Goods"
        }
    ],
    "sg:phone":"+1 626 281 3678",
    "sg:postcode":"91801",
    "sg:province":"CA",
    "wof:name":"Wing's Market",
    "wof:placetype":"venue"
},
  "geometry": {"coordinates":[-118.11799600000001,34.0788],"type":"Point"}
}