{
  "type": "Feature",
  "properties": {
    "addr:full":"2189 Harbor Bay Pkwy Alameda CA 94502",
    "addr:housenumber":"2189",
    "addr:postcode":"94502",
    "addr:street":"Harbor Bay Pkwy",
    "iso:country":"US",
    "sg:address":"2189 Harbor Bay Pkwy",
    "sg:city":"Alameda",
    "sg:classifiers":[
        {
            "category":"Arena",
            "subcategory":"Sports Club",
            "type":"Entertainment"
        }
    ],
    "sg:phone":"+1 510 769 0939",
    "sg:postcode":"94502",
    "sg:province":"CA",
    "sg:tags":[
        "martial art"
    ],
    "sg:website":"www.alamedamartialarts.com",
    "wof:name":"Alameda Martial Arts",
    "wof:placetype":"venue"
},
  "geometry": {"coordinates":[-122.249607,37.730768],"type":"Point"}
}