{
  "type": "Feature",
  "properties": {
    "addr:full":"2500 Michelson Drive Irvine CA 92612",
    "addr:housenumber":"2500",
    "addr:postcode":"92612",
    "addr:street":"Michelson Drive",
    "iso:country":"US",
    "sg:address":"2500 Michelson Drive",
    "sg:city":"Irvine",
    "sg:classifiers":[
        {
            "category":"Education",
            "subcategory":"School",
            "type":"Public Place"
        }
    ],
    "sg:postcode":"92612",
    "sg:province":"CA",
    "sg:website":"www.berkeley-review.com",
    "wof:name":"Berkeley Review",
    "wof:placetype":"venue"
},
  "geometry": {"coordinates":[-117.85169500000001,33.674515],"type":"Point"}
}