{
  "type": "Feature",
  "properties": {
    "addr:full":"2199 Williams St San Leandro CA 94577",
    "addr:housenumber":"2199",
    "addr:postcode":"94577",
    "addr:street":"Williams St",
    "iso:country":"US",
    "sg:address":"2199 Williams St",
    "sg:city":"San Leandro",
    "sg:classifiers":[
        {
            "category":"Banks & Credit Unions",
            "subcategory":"Bank",
            "type":"Services"
        }
    ],
    "sg:phone":"+1 510 357 1298",
    "sg:postcode":"94577",
    "sg:province":"CA",
    "sg:tags":[
        "loan",
        "real estate"
    ],
    "wof:name":"Capitol Investments Inc",
    "wof:placetype":"venue"
},
  "geometry": {"coordinates":[-122.179739,37.709288],"type":"Point"}
}