{
  "type": "Feature",
  "properties": {
    "addr:full":"438 W 93rd St Los Angeles CA 90003",
    "addr:housenumber":"438",
    "addr:postcode":"90003",
    "addr:street":"W 93Rd St",
    "iso:country":"US",
    "sg:address":"438 W 93rd St",
    "sg:city":"Los Angeles",
    "sg:classifiers":[
        {
            "category":"Building & Trades",
            "subcategory":"Construction",
            "type":"Services"
        }
    ],
    "sg:phone":"+1 323 756 7755",
    "sg:postcode":"90003",
    "sg:province":"CA",
    "sg:tags":[
        "contractor"
    ],
    "wof:name":"Harpers Equipment",
    "wof:placetype":"venue"
},
  "geometry": {"coordinates":[-118.282023,33.951824],"type":"Point"}
}