{
  "type": "Feature",
  "properties": {
    "iso:country":"US",
    "sg:address":"12132 Ballantine Dr",
    "sg:city":"Los Alamitos",
    "sg:classifiers":[
        {
            "category":"Wholesale",
            "subcategory":"Non-durable Goods",
            "type":"Manufacturing & Wholesale Goods"
        }
    ],
    "sg:phone":"+1 562 431 0328",
    "sg:postcode":"90720",
    "sg:province":"CA",
    "wof:name":"Traders Line Inc",
    "wof:placetype":"venue"
},
  "geometry": {"coordinates":[-118.081783,33.78623],"type":"Point"}
}