{
  "type": "Feature",
  "properties": {
    "iso:country":"US",
    "sg:address":"2929 K St",
    "sg:city":"Sacramento",
    "sg:classifiers":[
        {
            "category":"Personal",
            "subcategory":"Beauty Salon",
            "type":"Services"
        }
    ],
    "sg:phone":"+1 916 440 1027",
    "sg:postcode":"95816",
    "sg:province":"CA",
    "wof:name":"Gloh",
    "wof:placetype":"venue"
},
  "geometry": {"coordinates":[-121.46804400000001,38.572402],"type":"Point"}
}