{
  "type": "Feature",
  "properties": {
    "addr:full":"1523 19th St Bakersfield CA 93301",
    "addr:housenumber":"1523",
    "addr:postcode":"93301",
    "addr:street":"19Th St",
    "iso:country":"US",
    "sg:address":"1523 19th St",
    "sg:city":"Bakersfield",
    "sg:classifiers":[
        {
            "category":"Bars & Pubs",
            "type":"Food & Drink"
        }
    ],
    "sg:phone":"+1 661 324 3268",
    "sg:postcode":"93301",
    "sg:province":"CA",
    "wof:name":"Riley's",
    "wof:placetype":"venue"
},
  "geometry": {"coordinates":[-119.019797,35.376154],"type":"Point"}
}