{
  "type": "Feature",
  "properties": {
    "addr:full":"634 E Simpson Ave Fresno CA 93704",
    "addr:housenumber":"634",
    "addr:postcode":"93704",
    "addr:street":"E Simpson Ave",
    "iso:country":"US",
    "sg:address":"634 E Simpson Ave",
    "sg:city":"Fresno",
    "sg:classifiers":[
        {
            "category":"Building & Trades",
            "subcategory":"Construction",
            "type":"Services"
        }
    ],
    "sg:phone":"+1 559 250 7364",
    "sg:postcode":"93704",
    "sg:province":"CA",
    "sg:tags":[
        "tennis",
        "court"
    ],
    "wof:name":"Sterling Surfacing",
    "wof:placetype":"venue"
},
  "geometry": {"coordinates":[-119.802283,36.778484],"type":"Point"}
}