{
  "type": "Feature",
  "properties": {
    "addr:full":"1836 Commercial St Escondido CA 92029",
    "addr:housenumber":"1836",
    "addr:postcode":"92029",
    "addr:street":"Commercial St",
    "iso:country":"US",
    "sg:address":"1836 Commercial St",
    "sg:city":"Escondido",
    "sg:classifiers":[
        {
            "category":"Autos & Motor Vehicles",
            "subcategory":"Recreational Vehicle Sales",
            "type":"Retail Goods"
        }
    ],
    "sg:phone":"+1 760 740 2421",
    "sg:postcode":"92029",
    "sg:province":"CA",
    "sg:tags":[
        "antique",
        "car",
        "classic"
    ],
    "wof:name":"North County Customs & Hot Rods",
    "wof:placetype":"venue"
},
  "geometry": {"coordinates":[-117.114951,33.123626],"type":"Point"}
}