{
  "type": "Feature",
  "properties": {
    "addr:full":"11070 White Rock Rd Rancho Cordova CA 95670",
    "addr:housenumber":"11070",
    "addr:postcode":"95670",
    "addr:street":"White Rock Rd",
    "iso:country":"US",
    "sg:address":"11070 White Rock Rd",
    "sg:city":"Rancho Cordova",
    "sg:classifiers":[
        {
            "category":"Real Estate",
            "subcategory":"Real Estate Agent",
            "type":"Services"
        }
    ],
    "sg:phone":"+1 916 635 1145",
    "sg:postcode":"95670",
    "sg:province":"CA",
    "sg:tags":[
        "management"
    ],
    "wof:name":"Hines Property Management",
    "wof:placetype":"venue"
},
  "geometry": {"coordinates":[-121.27278200000001,38.589626],"type":"Point"}
}