{
  "type": "Feature",
  "properties": {
    "iso:country":"US",
    "sg:address":"1115 W 37th Place",
    "sg:city":"Los Angeles",
    "sg:classifiers":[
        {
            "category":"Real Estate",
            "subcategory":"Real Estate Operator",
            "type":"Services"
        }
    ],
    "sg:phone":"+1 323 731 5050",
    "sg:postcode":"90007",
    "sg:province":"CA",
    "sg:tags":[
        "apartment"
    ],
    "wof:name":"Billy G Mills Manor",
    "wof:placetype":"venue"
},
  "geometry": {"coordinates":[-118.291947,34.019979],"type":"Point"}
}