{
  "type": "Feature",
  "properties": {
    "addr:full":"140 Colonel Durham St Seaside CA 93955",
    "addr:housenumber":"140",
    "addr:postcode":"93955",
    "addr:street":"Colonel Durham St",
    "iso:country":"US",
    "sg:address":"140 Colonel Durham St",
    "sg:city":"Seaside",
    "sg:classifiers":[
        {
            "category":"Government",
            "subcategory":"Office",
            "type":"Public Place"
        }
    ],
    "sg:phone":"+1 831 393 8412",
    "sg:postcode":"93955",
    "sg:province":"CA",
    "sg:tags":[
        "state",
        "security"
    ],
    "wof:name":"Army National Guard Recruiter",
    "wof:placetype":"venue"
},
  "geometry": {"coordinates":[-121.793454,36.646259],"type":"Point"}
}