{
  "type": "Feature",
  "properties": {
    "iso:country":"US",
    "sg:address":"88 Burlingame Ave",
    "sg:city":"Burlingame",
    "sg:classifiers":[
        {
            "category":"Professional",
            "subcategory":"Computer Services",
            "type":"Services"
        }
    ],
    "sg:postcode":"94010",
    "sg:province":"CA",
    "sg:tags":[
        "outsourcing"
    ],
    "sg:website":"http://www.optask.com",
    "wof:name":"Optask",
    "wof:placetype":"venue"
},
  "geometry": {"coordinates":[-122.33620999999999,37.586322],"type":"Point"}
}