{
  "type": "Feature",
  "properties": {
    "iso:country":"US",
    "sg:address":"24950 Fuhrman Rd",
    "sg:city":"Lodi",
    "sg:classifiers":[
        {
            "category":"Manufacturing",
            "subcategory":"Apparel",
            "type":"Manufacturing & Wholesale Goods"
        }
    ],
    "sg:phone":"+1 209 334 2513",
    "sg:postcode":"95220",
    "sg:province":"CA",
    "sg:tags":[
        "flag",
        "banner"
    ],
    "wof:name":"Reese's Installations",
    "wof:placetype":"venue"
},
  "geometry": {"coordinates":[-121.138685,38.217037],"type":"Point"}
}