{
  "type": "Feature",
  "properties": {
    "addr:full":"960 Overland Ct San Dimas CA 91773",
    "addr:housenumber":"960",
    "addr:postcode":"91773",
    "addr:street":"Overland Ct",
    "iso:country":"US",
    "sg:address":"960 Overland Ct",
    "sg:city":"San Dimas",
    "sg:classifiers":[
        {
            "category":"Manufacturing",
            "subcategory":"Tools & Machinery",
            "type":"Manufacturing & Wholesale Goods"
        }
    ],
    "sg:phone":"+1 909 394 5000",
    "sg:postcode":"91773",
    "sg:province":"CA",
    "sg:tags":[
        "search"
    ],
    "wof:name":"Thales Navigation Inc",
    "wof:placetype":"venue"
},
  "geometry": {"coordinates":[-117.82615300000001,34.109862],"type":"Point"}
}