{
  "type": "Feature",
  "properties": {
    "iso:country":"US",
    "sg:address":"8055 Elk Grove Florin Rd",
    "sg:city":"Sacramento",
    "sg:classifiers":[
        {
            "category":"Restaurant",
            "type":"Food & Drink"
        }
    ],
    "sg:phone":"+1 916 525 2405",
    "sg:postcode":"95829",
    "sg:province":"CA",
    "wof:name":"Annie's Fish & Chips",
    "wof:placetype":"venue"
},
  "geometry": {"coordinates":[-121.371869,38.465385],"type":"Point"}
}