{
  "type": "Feature",
  "properties": {
    "addr:full":"664 29th St San Francisco CA 94131",
    "addr:housenumber":"664",
    "addr:postcode":"94131",
    "addr:street":"29Th St",
    "iso:country":"US",
    "sg:address":"664 29th St",
    "sg:city":"San Francisco",
    "sg:classifiers":[
        {
            "category":"Retail",
            "subcategory":"Portrait Studio",
            "type":"Services"
        }
    ],
    "sg:phone":"+1 415 346 5595",
    "sg:postcode":"94131",
    "sg:province":"CA",
    "sg:tags":[
        "photographer"
    ],
    "wof:name":"Ann Hamilton Photography",
    "wof:placetype":"venue"
},
  "geometry": {"coordinates":[-122.435371,37.743251],"type":"Point"}
}