{
  "type": "Feature",
  "properties": {
    "addr:full":"452 Serra Dr Corona Del Mar CA 92625",
    "addr:housenumber":"452",
    "addr:postcode":"92625",
    "addr:street":"Serra Dr",
    "iso:country":"US",
    "sg:address":"452 Serra Dr",
    "sg:city":"Corona Del Mar",
    "sg:classifiers":[
        {
            "category":"Real Estate",
            "subcategory":"Real Estate Operator",
            "type":"Services"
        }
    ],
    "sg:phone":"+1 949 760 8217",
    "sg:postcode":"92625",
    "sg:province":"CA",
    "sg:tags":[
        "property",
        "lessor"
    ],
    "wof:name":"Sal Gottuso & Assoc",
    "wof:placetype":"venue"
},
  "geometry": {"coordinates":[-117.863866,33.594135],"type":"Point"}
}