{
  "type": "Feature",
  "properties": {
    "addr:full":"115 N Valley Oaks Dr # A Visalia CA 93292",
    "addr:housenumber":"115",
    "addr:postcode":"93292",
    "addr:street":"N Valley Oaks Dr # A",
    "iso:country":"US",
    "sg:address":"115 N Valley Oaks Dr # A",
    "sg:city":"Visalia",
    "sg:classifiers":[
        {
            "category":"Personal",
            "subcategory":"Beauty Salon",
            "type":"Services"
        }
    ],
    "sg:phone":"+1 559 625 9652",
    "sg:postcode":"93292",
    "sg:province":"CA",
    "wof:name":"Nacho's Salon",
    "wof:placetype":"venue"
},
  "geometry": {"coordinates":[-119.26491799999999,36.328534],"type":"Point"}
}