{
  "type": "Feature",
  "properties": {
    "iso:country":"US",
    "sg:address":"4025 N Fresno St",
    "sg:city":"Fresno",
    "sg:classifiers":[
        {
            "category":"Shopping",
            "subcategory":"Pharmacy",
            "type":"Retail Goods"
        }
    ],
    "sg:phone":"+1 559 226 0246",
    "sg:postcode":"93726",
    "sg:province":"CA",
    "wof:name":"Pharmacy Resolutions",
    "wof:placetype":"venue"
},
  "geometry": {"coordinates":[-119.781507,36.790961],"type":"Point"}
}