{
  "type": "Feature",
  "properties": {
    "iso:country":"US",
    "sg:address":"570 W Rancho Vista Blvd P",
    "sg:city":"Palmdale",
    "sg:classifiers":[
        {
            "category":"Fast Food",
            "type":"Food & Drink"
        },
        {
            "category":"Restaurant",
            "type":"Food & Drink"
        }
    ],
    "sg:phone":"+1 661 273 8261",
    "sg:postcode":"93551",
    "sg:province":"CA",
    "sg:tags":[
        "american",
        "hot",
        "hamburger",
        "dog"
    ],
    "sg:website":"http://www.jackinthebox.com",
    "wof:name":"Jack in the Box",
    "wof:placetype":"venue"
},
  "geometry": {"coordinates":[-118.14023,34.601721],"type":"Point"}
}