{
  "type": "Feature",
  "properties": {
    "addr:full":"1040 Heritage Rd San Diego CA 92154",
    "addr:housenumber":"1040",
    "addr:postcode":"92154",
    "addr:street":"Heritage Rd",
    "iso:country":"US",
    "sg:address":"1040 Heritage Rd",
    "sg:city":"San Diego",
    "sg:classifiers":[
        {
            "category":"Wholesale",
            "subcategory":"Auto Parts",
            "type":"Manufacturing & Wholesale Goods"
        }
    ],
    "sg:phone":"+1 619 661 1141",
    "sg:postcode":"92154",
    "sg:province":"CA",
    "sg:tags":[
        "wrecker"
    ],
    "wof:name":"Tokyo 2 Auto Wrecking",
    "wof:placetype":"venue"
},
  "geometry": {"coordinates":[-116.99668699999999,32.577507],"type":"Point"}
}