{
  "type": "Feature",
  "properties": {
    "addr:full":"21731 Lake Forest Dr Lake Forest CA 92630",
    "addr:housenumber":"21731",
    "addr:postcode":"92630",
    "addr:street":"Lake Forest Dr",
    "iso:country":"US",
    "sg:address":"21731 Lake Forest Dr",
    "sg:city":"Lake Forest",
    "sg:classifiers":[
        {
            "category":"Food & Beverages",
            "subcategory":"Candy",
            "type":"Retail Goods"
        }
    ],
    "sg:phone":"+1 949 458 7630",
    "sg:postcode":"92630",
    "sg:province":"CA",
    "sg:tags":[
        "confectionery"
    ],
    "wof:name":"Candy & Fancy",
    "wof:placetype":"venue"
},
  "geometry": {"coordinates":[-117.69556300000001,33.642721],"type":"Point"}
}