{
  "type": "Feature",
  "properties": {
    "addr:full":"50 Raleigh Ct Roseville CA 95678",
    "addr:housenumber":"50",
    "addr:postcode":"95678",
    "addr:street":"Raleigh Ct",
    "iso:country":"US",
    "sg:address":"50 Raleigh Ct",
    "sg:city":"Roseville",
    "sg:classifiers":[
        {
            "category":"Professional",
            "type":"Services"
        }
    ],
    "sg:phone":"+1 916 780 3977",
    "sg:postcode":"95678",
    "sg:province":"CA",
    "wof:name":"Adelbert E Schellenger",
    "wof:placetype":"venue"
},
  "geometry": {"coordinates":[-121.29906699999999,38.785962],"type":"Point"}
}