{
  "type": "Feature",
  "properties": {
    "iso:country":"US",
    "sg:address":"1845 S Sespe St",
    "sg:city":"Fillmore",
    "sg:classifiers":[
        {
            "category":"Wholesale",
            "subcategory":"Groceries",
            "type":"Manufacturing & Wholesale Goods"
        }
    ],
    "sg:phone":"+1 805 524 0775",
    "sg:postcode":"93015",
    "sg:province":"CA",
    "wof:name":"George Wise",
    "wof:placetype":"venue"
},
  "geometry": {"coordinates":[-118.94250099999999,34.36233],"type":"Point"}
}