{
  "type": "Feature",
  "properties": {
    "iso:country":"US",
    "sg:address":"6911 Katella Ave",
    "sg:city":"Cypress",
    "sg:classifiers":[
        {
            "category":"Shopping",
            "subcategory":"Mobile Phones",
            "type":"Retail Goods"
        }
    ],
    "sg:phone":"+1 714 527 0200",
    "sg:postcode":"90630",
    "sg:province":"CA",
    "wof:name":"Oceanview Wireless",
    "wof:placetype":"venue"
},
  "geometry": {"coordinates":[-118.28801,33.803089],"type":"Point"}
}