{
  "type": "Feature",
  "properties": {
    "addr:full":"111 W Dyer Rd Ste B Santa Ana CA 92707",
    "addr:housenumber":"111",
    "addr:postcode":"92707",
    "addr:street":"W Dyer Rd Ste B",
    "iso:country":"US",
    "sg:address":"111 W Dyer Rd Ste B",
    "sg:city":"Santa Ana",
    "sg:classifiers":[
        {
            "category":"Autos & Motor Vehicles",
            "subcategory":"Motorcycle Sales",
            "type":"Retail Goods"
        }
    ],
    "sg:phone":"+1 714 540 2920",
    "sg:postcode":"92707",
    "sg:province":"CA",
    "wof:name":"Up-Tite Husqvarna Cagiva C C M Motorcycles",
    "wof:placetype":"venue"
},
  "geometry": {"coordinates":[-117.86799600000001,33.708801],"type":"Point"}
}