{
  "type": "Feature",
  "properties": {
    "iso:country":"US",
    "sg:address":"6467 Hellman Ave",
    "sg:city":"Rancho Cucamonga",
    "sg:classifiers":[
        {
            "category":"Wholesale",
            "subcategory":"Home Furnishings",
            "type":"Manufacturing & Wholesale Goods"
        }
    ],
    "sg:phone":"+1 909 980 1461",
    "sg:postcode":"91701",
    "sg:province":"CA",
    "sg:tags":[
        "plate",
        "aluminum"
    ],
    "wof:name":"L H I Metal Inc",
    "wof:placetype":"venue"
},
  "geometry": {"coordinates":[-117.602729,34.138661],"type":"Point"}
}