{
  "type": "Feature",
  "properties": {
    "addr:full":"8602 Norwalk Blvd Whittier CA 90606",
    "addr:housenumber":"8602",
    "addr:postcode":"90606",
    "addr:street":"Norwalk Blvd",
    "iso:country":"US",
    "sg:address":"8602 Norwalk Blvd",
    "sg:city":"Whittier",
    "sg:classifiers":[
        {
            "category":"Manufacturing",
            "subcategory":"Printing",
            "type":"Manufacturing & Wholesale Goods"
        }
    ],
    "sg:phone":"+1 562 692 0888",
    "sg:postcode":"90606",
    "sg:province":"CA",
    "sg:tags":[
        "commercial"
    ],
    "wof:name":"Cello Printers Inc",
    "wof:placetype":"venue"
},
  "geometry": {"coordinates":[-118.070533,33.962262],"type":"Point"}
}