{
  "type": "Feature",
  "properties": {
    "addr:full":"19146 E Elberland St West Covina CA 91792",
    "addr:housenumber":"19146",
    "addr:postcode":"91792",
    "addr:street":"E Elberland St",
    "iso:country":"US",
    "sg:address":"19146 E Elberland St",
    "sg:city":"West Covina",
    "sg:classifiers":[
        {
            "category":"Professional",
            "subcategory":"Detective & Security Services",
            "type":"Services"
        }
    ],
    "sg:phone":"+1 626 241 5950",
    "sg:postcode":"91792",
    "sg:province":"CA",
    "sg:tags":[
        "company",
        "installation",
        "surveillance"
    ],
    "wof:name":"Revelations Integrated Svcs",
    "wof:placetype":"venue"
},
  "geometry": {"coordinates":[-117.88353600000001,34.009366],"type":"Point"}
}