{
  "type": "Feature",
  "properties": {
    "iso:country":"US",
    "sg:address":"1202 Mettler Rd",
    "sg:city":"Lodi",
    "sg:classifiers":[
        {
            "category":"Farming",
            "subcategory":"Crops",
            "type":"Manufacturing & Wholesale Goods"
        }
    ],
    "sg:phone":"+1 209 368 0305",
    "sg:postcode":"95242",
    "sg:province":"CA",
    "sg:tags":[
        "grove",
        "nut",
        "tree"
    ],
    "wof:name":"Walter Hofer",
    "wof:placetype":"venue"
},
  "geometry": {"coordinates":[-121.295987,38.07551],"type":"Point"}
}