{
  "type": "Feature",
  "properties": {
    "addr:full":"1350 45th ave # A Capitola CA 95010",
    "addr:housenumber":"1350",
    "addr:postcode":"95010",
    "addr:street":"45Th Ave # A",
    "iso:country":"US",
    "sg:address":"1350 45th ave # A",
    "sg:city":"Capitola",
    "sg:classifiers":[
        {
            "category":"Professional",
            "type":"Services"
        },
        {
            "category":"Building & Trades",
            "subcategory":"Construction",
            "type":"Services"
        }
    ],
    "sg:phone":"+1 831 419 3216",
    "sg:postcode":"95010",
    "sg:province":"CA",
    "sg:tags":[
        "interior",
        "design"
    ],
    "sg:website":"www.labrisdesigns.com/",
    "wof:name":"Labris Designs",
    "wof:placetype":"venue"
},
  "geometry": {"coordinates":[-121.959591,36.970573],"type":"Point"}
}