{
  "type": "Feature",
  "properties": {
    "iso:country":"US",
    "sg:address":"4855 Lindley Ave",
    "sg:city":"Tarzana",
    "sg:classifiers":[
        {
            "category":"Wholesale",
            "subcategory":"Electrical",
            "type":"Manufacturing & Wholesale Goods"
        }
    ],
    "sg:phone":"+1 818 401 0188",
    "sg:postcode":"91356",
    "sg:province":"CA",
    "sg:tags":[
        "equipment",
        "television",
        "studio"
    ],
    "wof:name":"United Broadcast Group",
    "wof:placetype":"venue"
},
  "geometry": {"coordinates":[-118.527328,34.158586],"type":"Point"}
}