{
  "type": "Feature",
  "properties": {
    "iso:country":"US",
    "sg:address":"811 W Clover Rd",
    "sg:city":"Tracy",
    "sg:classifiers":[
        {
            "category":"Travel",
            "subcategory":"Hotels & Motels",
            "type":"Entertainment"
        }
    ],
    "sg:phone":"+1 877 574 2464",
    "sg:postcode":"95376",
    "sg:province":"CA",
    "sg:tags":[
        "lodging"
    ],
    "sg:website":"http://book.bestwestern.com/bestwestern/priceAvail.do?propertyCode=05543&cm_mmc=IYP-_-YP-_-property-_-5543",
    "wof:name":"Best Western Luxury Inn",
    "wof:placetype":"venue"
},
  "geometry": {"coordinates":[-121.437321,37.761398],"type":"Point"}
}