{
  "type": "Feature",
  "properties": {
    "iso:country":"US",
    "sg:address":"5401 Woodmere Dr",
    "sg:city":"Bakersfield",
    "sg:classifiers":[
        {
            "category":"Utilities",
            "subcategory":"Telephone",
            "type":"Services"
        }
    ],
    "sg:phone":"+1 661 833 6361",
    "sg:postcode":"93313",
    "sg:province":"CA",
    "sg:tags":[
        "telecommunication"
    ],
    "sg:website":"www.commworldkc.com",
    "wof:name":"Commworld Of KERN County",
    "wof:placetype":"venue"
},
  "geometry": {"coordinates":[-119.064021,35.308417],"type":"Point"}
}