{
  "type": "Feature",
  "properties": {
    "addr:full":"10802 Norwalk Blvd Santa Fe Springs CA 90670",
    "addr:housenumber":"10802",
    "addr:postcode":"90670",
    "addr:street":"Norwalk Blvd",
    "iso:country":"US",
    "sg:address":"10802 Norwalk Blvd",
    "sg:city":"Santa Fe Springs",
    "sg:classifiers":[
        {
            "category":"Wholesale",
            "subcategory":"Electrical",
            "type":"Manufacturing & Wholesale Goods"
        }
    ],
    "sg:phone":"+1 562 903 9012",
    "sg:postcode":"90670",
    "sg:province":"CA",
    "sg:tags":[
        "alarm",
        "burglar",
        "system"
    ],
    "wof:name":"AAA Tech",
    "wof:placetype":"venue"
},
  "geometry": {"coordinates":[-118.07261099999999,33.933764],"type":"Point"}
}