{
  "type": "Feature",
  "properties": {
    "addr:full":"2144 W. Sunset Blvd Los Angeles CA 90026",
    "addr:housenumber":"2144",
    "addr:postcode":"90026",
    "addr:street":"W. Sunset Blvd",
    "iso:country":"US",
    "sg:address":"2144 W. Sunset Blvd",
    "sg:city":"Los Angeles",
    "sg:classifiers":[
        {
            "category":"Government",
            "subcategory":"City Hall",
            "type":"Public Place"
        }
    ],
    "sg:postcode":"90026",
    "sg:province":"CA",
    "wof:name":"Fire Station 20",
    "wof:placetype":"venue"
},
  "geometry": {"coordinates":[-118.265244,34.077435],"type":"Point"}
}