{
  "type": "Feature",
  "properties": {
    "addr:full":"15665 Los Gatos Blvd Los Gatos CA 95032",
    "addr:housenumber":"15665",
    "addr:postcode":"95032",
    "addr:street":"Los Gatos Blvd",
    "iso:country":"US",
    "sg:address":"15665 Los Gatos Blvd",
    "sg:city":"Los Gatos",
    "sg:classifiers":[
        {
            "category":"Food & Beverages",
            "subcategory":"Groceries & Convenience Stores",
            "type":"Retail Goods"
        }
    ],
    "sg:phone":"+1 408 356 4434",
    "sg:postcode":"95032",
    "sg:province":"CA",
    "wof:name":"Jiffy Market",
    "wof:placetype":"venue"
},
  "geometry": {"coordinates":[-121.960999,37.2407],"type":"Point"}
}