{
  "type": "Feature",
  "properties": {
    "addr:full":"16 Saint Josephs Avenue San Francisco CA 94115",
    "addr:housenumber":"16",
    "addr:postcode":"94115",
    "addr:street":"Saint Josephs Avenue",
    "iso:country":"US",
    "sg:address":"16 Saint Josephs Avenue",
    "sg:city":"San Francisco",
    "sg:classifiers":[
        {
            "category":"Personal",
            "type":"Services"
        }
    ],
    "sg:phone":"+1 415 673 6939",
    "sg:postcode":"94115",
    "sg:province":"CA",
    "sg:tags":[
        "local"
    ],
    "sg:website":"www.luke-a-tuke.com",
    "wof:name":"Luke-A-Tuke",
    "wof:placetype":"venue"
},
  "geometry": {"coordinates":[-122.441002,37.779598],"type":"Point"}
}