{
  "type": "Feature",
  "properties": {
    "iso:country":"US",
    "sg:address":"645 E Bidwell St",
    "sg:city":"Folsom",
    "sg:classifiers":[
        {
            "category":"Personal",
            "subcategory":"Beauty Salon",
            "type":"Services"
        }
    ],
    "sg:phone":"+1 916 983 3781",
    "sg:postcode":"95630",
    "sg:province":"CA",
    "wof:name":"Posey's Hair Design",
    "wof:placetype":"venue"
},
  "geometry": {"coordinates":[-121.157203,38.670627],"type":"Point"}
}