{
  "type": "Feature",
  "properties": {
    "iso:country":"US",
    "sg:address":"19220 Van Buren Blvd",
    "sg:city":"Riverside",
    "sg:classifiers":[
        {
            "category":"Autos & Motor Vehicles",
            "subcategory":"Fuel & Gas Station",
            "type":"Retail Goods"
        }
    ],
    "sg:phone":"+1 951 789 2040",
    "sg:postcode":"92508",
    "sg:province":"CA",
    "sg:tags":[
        "oil"
    ],
    "wof:name":"Chevron Stations Inc",
    "wof:placetype":"venue"
},
  "geometry": {"coordinates":[-117.32446,33.888461],"type":"Point"}
}