{
  "type": "Feature",
  "properties": {
    "iso:country":"US",
    "sg:address":"11306 Mountain View Ave",
    "sg:city":"Loma Linda",
    "sg:classifiers":[
        {
            "category":"Health Services",
            "subcategory":"Doctor",
            "type":"Services"
        }
    ],
    "sg:phone":"+1 909 796 0224",
    "sg:postcode":"92354",
    "sg:province":"CA",
    "sg:tags":[
        "physician",
        "surgeon"
    ],
    "wof:name":"Loma Linda Dermatology Medical",
    "wof:placetype":"venue"
},
  "geometry": {"coordinates":[-117.243707,34.044952],"type":"Point"}
}