{
  "type": "Feature",
  "properties": {
    "iso:country":"US",
    "sg:address":"9978 Scripps Ranch Blvd",
    "sg:city":"San Diego",
    "sg:classifiers":[
        {
            "category":"Restaurant",
            "type":"Food & Drink"
        }
    ],
    "sg:menulink":"http://www.allmenus.com/ca/san-diego/34060-chins-szechwan-cuisine/menu/",
    "sg:phone":"+1 858 566 0031",
    "sg:postcode":"92131",
    "sg:province":"CA",
    "sg:tags":[
        "asian",
        "chinese"
    ],
    "wof:name":"Chin's Szechwan Cuisine",
    "wof:placetype":"venue"
},
  "geometry": {"coordinates":[-117.098753,32.903238],"type":"Point"}
}