{
  "type": "Feature",
  "properties": {
    "addr:full":"15234 Sunburst St North Hills CA 91343",
    "addr:housenumber":"15234",
    "addr:postcode":"91343",
    "addr:street":"Sunburst St",
    "iso:country":"US",
    "sg:address":"15234 Sunburst St",
    "sg:city":"North Hills",
    "sg:classifiers":[
        {
            "category":"Shopping",
            "subcategory":"Clothing, Apparel, & Fashions",
            "type":"Retail Goods"
        }
    ],
    "sg:phone":"+1 818 895 2412",
    "sg:postcode":"91343",
    "sg:province":"CA",
    "sg:tags":[
        "family"
    ],
    "wof:name":"Devoir Clothing Lines",
    "wof:placetype":"venue"
},
  "geometry": {"coordinates":[-118.465075,34.234475],"type":"Point"}
}