{
  "type": "Feature",
  "properties": {
    "iso:country":"US",
    "sg:address":"10925 Osterman Ave",
    "sg:city":"Tustin",
    "sg:classifiers":[
        {
            "category":"Manufacturing",
            "subcategory":"Printing",
            "type":"Manufacturing & Wholesale Goods"
        }
    ],
    "sg:phone":"+1 714 838 5063",
    "sg:postcode":"92782",
    "sg:province":"CA",
    "sg:tags":[
        "lithographic",
        "commercial"
    ],
    "wof:name":"LL Print Consulting",
    "wof:placetype":"venue"
},
  "geometry": {"coordinates":[-117.769893,33.757027],"type":"Point"}
}