{
  "type": "Feature",
  "properties": {
    "addr:full":"2544 Navarra Dr Carlsbad CA 92009",
    "addr:housenumber":"2544",
    "addr:postcode":"92009",
    "addr:street":"Navarra Dr",
    "iso:country":"US",
    "sg:address":"2544 Navarra Dr",
    "sg:city":"Carlsbad",
    "sg:classifiers":[
        {
            "category":"Manufacturing",
            "subcategory":"Apparel",
            "type":"Manufacturing & Wholesale Goods"
        }
    ],
    "sg:phone":"+1 760 632 6992",
    "sg:postcode":"92009",
    "sg:province":"CA",
    "sg:tags":[
        "sportswear",
        "mfg"
    ],
    "wof:name":"Supa Dupa",
    "wof:placetype":"venue"
},
  "geometry": {"coordinates":[-117.249922,33.088946],"type":"Point"}
}