{
  "type": "Feature",
  "properties": {
    "iso:country":"US",
    "sg:address":"620 Kings Ct",
    "sg:city":"Ukiah",
    "sg:classifiers":[
        {
            "category":"Building & Trades",
            "subcategory":"Electrical",
            "type":"Services"
        }
    ],
    "sg:phone":"+1 707 463 3996",
    "sg:postcode":"95482",
    "sg:province":"CA",
    "sg:tags":[
        "electric",
        "contractor"
    ],
    "wof:name":"Bostwick Electric",
    "wof:placetype":"venue"
},
  "geometry": {"coordinates":[-123.197699,39.148166],"type":"Point"}
}