{
  "type": "Feature",
  "properties": {
    "addr:full":"140 E F St Dixon CA 95620",
    "addr:housenumber":"140",
    "addr:postcode":"95620",
    "addr:street":"E F St",
    "iso:country":"US",
    "sg:address":"140 E F St",
    "sg:city":"Dixon",
    "sg:classifiers":[
        {
            "category":"Retail",
            "subcategory":"Auto Repair",
            "type":"Services"
        }
    ],
    "sg:phone":"+1 707 693 9313",
    "sg:postcode":"95620",
    "sg:province":"CA",
    "sg:tags":[
        "repairing",
        "automobile"
    ],
    "wof:name":"Advanced Automotive",
    "wof:placetype":"venue"
},
  "geometry": {"coordinates":[-121.821698,38.450434],"type":"Point"}
}