{
  "type": "Feature",
  "properties": {
    "addr:full":"1530 Casitas Pass Rd Carpinteria CA 93013",
    "addr:housenumber":"1530",
    "addr:postcode":"93013",
    "addr:street":"Casitas Pass Rd",
    "iso:country":"US",
    "sg:address":"1530 Casitas Pass Rd",
    "sg:city":"Carpinteria",
    "sg:classifiers":[
        {
            "category":"Building & Trades",
            "subcategory":"Landscaping Services",
            "type":"Services"
        }
    ],
    "sg:phone":"+1 805 684 5552",
    "sg:postcode":"93013",
    "sg:province":"CA",
    "sg:tags":[
        "lawn"
    ],
    "wof:name":"Casitas Gardens Inc",
    "wof:placetype":"venue"
},
  "geometry": {"coordinates":[-119.505723,34.404748],"type":"Point"}
}