{
  "type": "Feature",
  "properties": {
    "addr:full":"7125 W Manchester Ave Los Angeles CA 90045",
    "addr:housenumber":"7125",
    "addr:postcode":"90045",
    "addr:street":"W Manchester Ave",
    "iso:country":"US",
    "sg:address":"7125 W Manchester Ave",
    "sg:city":"Los Angeles",
    "sg:classifiers":[
        {
            "category":"Personal",
            "subcategory":"Beauty Salon",
            "type":"Services"
        }
    ],
    "sg:phone":"+1 310 338 8727",
    "sg:postcode":"90045",
    "sg:province":"CA",
    "wof:name":"Avenue Hair Co",
    "wof:placetype":"venue"
},
  "geometry": {"coordinates":[-118.418318,33.959812],"type":"Point"}
}