{
  "type": "Feature",
  "properties": {
    "addr:full":"4436 Worth St Los Angeles CA 90063",
    "addr:housenumber":"4436",
    "addr:postcode":"90063",
    "addr:street":"Worth St",
    "iso:country":"US",
    "sg:address":"4436 Worth St",
    "sg:city":"Los Angeles",
    "sg:classifiers":[
        {
            "category":"Manufacturing",
            "subcategory":"Tools & Machinery",
            "type":"Manufacturing & Wholesale Goods"
        }
    ],
    "sg:phone":"+1 323 227 1921",
    "sg:postcode":"90063",
    "sg:province":"CA",
    "sg:tags":[
        "industrial",
        "truck"
    ],
    "sg:website":"www.davisbaconmh.com",
    "wof:name":"Davis Bacon Material Handling",
    "wof:placetype":"venue"
},
  "geometry": {"coordinates":[-118.188086,34.06226],"type":"Point"}
}