{
  "type": "Feature",
  "properties": {
    "iso:country":"US",
    "sg:address":"21321 Mission St",
    "sg:city":"Tehachapi",
    "sg:classifiers":[
        {
            "category":"Professional",
            "subcategory":"Management & Consulting",
            "type":"Services"
        }
    ],
    "sg:phone":"+1 661 823 0796",
    "sg:postcode":"93561",
    "sg:province":"CA",
    "sg:tags":[
        "consultant",
        "business"
    ],
    "wof:name":"M & M Management",
    "wof:placetype":"venue"
},
  "geometry": {"coordinates":[-118.493048,35.128749],"type":"Point"}
}