{
  "type": "Feature",
  "properties": {
    "iso:country":"US",
    "sg:address":"5663 E Fountain Way",
    "sg:city":"Fresno",
    "sg:classifiers":[
        {
            "category":"Food & Beverages",
            "subcategory":"Specialty",
            "type":"Retail Goods"
        }
    ],
    "sg:phone":"+1 559 291 0218",
    "sg:postcode":"93727",
    "sg:province":"CA",
    "sg:tags":[
        "spice"
    ],
    "sg:website":"www.pappyschoice.net",
    "wof:name":"Pappy's Fine Foods",
    "wof:placetype":"venue"
},
  "geometry": {"coordinates":[-119.69410999999999,36.78133],"type":"Point"}
}