{
  "type": "Feature",
  "properties": {
    "addr:full":"934 Escondido Ct Alamo CA 94507",
    "addr:housenumber":"934",
    "addr:postcode":"94507",
    "addr:street":"Escondido Ct",
    "iso:country":"US",
    "sg:address":"934 Escondido Ct",
    "sg:city":"Alamo",
    "sg:classifiers":[
        {
            "category":"Home & Garden",
            "subcategory":"Home Furnishings",
            "type":"Retail Goods"
        }
    ],
    "sg:phone":"+1 925 820 0856",
    "sg:postcode":"94507",
    "sg:province":"CA",
    "wof:name":"Kendall Designs",
    "wof:placetype":"venue"
},
  "geometry": {"coordinates":[-122.02265,37.834437],"type":"Point"}
}