{
  "type": "Feature",
  "properties": {
    "addr:full":"10215 Greenleaf Rd Spring Valley CA 91977",
    "addr:housenumber":"10215",
    "addr:postcode":"91977",
    "addr:street":"Greenleaf Rd",
    "iso:country":"US",
    "sg:address":"10215 Greenleaf Rd",
    "sg:city":"Spring Valley",
    "sg:classifiers":[
        {
            "category":"Manufacturing",
            "subcategory":"Apparel",
            "type":"Manufacturing & Wholesale Goods"
        }
    ],
    "sg:phone":"+1 619 670 3584",
    "sg:postcode":"91977",
    "sg:province":"CA",
    "sg:tags":[
        "embroidery",
        "mfg"
    ],
    "wof:name":"Rose Luceina Embroidery",
    "wof:placetype":"venue"
},
  "geometry": {"coordinates":[-116.980146,32.715165],"type":"Point"}
}