{
  "type": "Feature",
  "properties": {
    "iso:country":"US",
    "sg:address":"21021 Soledad Canyon Rd",
    "sg:city":"Santa Clarita",
    "sg:classifiers":[
        {
            "category":"Real Estate",
            "subcategory":"Real Estate Agent",
            "type":"Services"
        }
    ],
    "sg:phone":"+1 661 287 4480",
    "sg:postcode":"91351",
    "sg:province":"CA",
    "sg:tags":[
        "consultant"
    ],
    "wof:name":"Kellar Davis",
    "wof:placetype":"venue"
},
  "geometry": {"coordinates":[-118.50295800000001,34.420164],"type":"Point"}
}