{
  "type": "Feature",
  "properties": {
    "iso:country":"US",
    "sg:address":"Life West Health Center 25001 Industrial Blvd 2nd Fl",
    "sg:city":"Hayward",
    "sg:classifiers":[
        {
            "category":"Health Services",
            "subcategory":"Chiropractor",
            "type":"Services"
        }
    ],
    "sg:phone":"+1 510 780 4500",
    "sg:postcode":"94545",
    "sg:province":"CA",
    "sg:website":"www.lifewest.edu",
    "wof:name":"Bell Chiropractic",
    "wof:placetype":"venue"
},
  "geometry": {"coordinates":[-122.11797199999999,37.637956],"type":"Point"}
}