{
  "type": "Feature",
  "properties": {
    "iso:country":"US",
    "sg:address":"7988 Stromesa Ct",
    "sg:city":"San Diego",
    "sg:classifiers":[
        {
            "category":"Wholesale",
            "subcategory":"Vending Machines",
            "type":"Manufacturing & Wholesale Goods"
        }
    ],
    "sg:phone":"+1 858 530 1919",
    "sg:postcode":"92126",
    "sg:province":"CA",
    "wof:name":"Brec Vending",
    "wof:placetype":"venue"
},
  "geometry": {"coordinates":[-117.14798399999999,32.892701],"type":"Point"}
}