{
  "type": "Feature",
  "properties": {
    "iso:country":"US",
    "sg:address":"303 E Providencia Ave",
    "sg:city":"Burbank",
    "sg:classifiers":[
        {
            "category":"Building & Trades",
            "subcategory":"Construction",
            "type":"Services"
        }
    ],
    "sg:phone":"+1 818 846 5703",
    "sg:postcode":"91502",
    "sg:province":"CA",
    "sg:tags":[
        "painter"
    ],
    "wof:name":"Fischer Painting",
    "wof:placetype":"venue"
},
  "geometry": {"coordinates":[-118.301521,34.179581],"type":"Point"}
}