{
  "type": "Feature",
  "properties": {
    "iso:country":"US",
    "sg:address":"6557 S Western Ave",
    "sg:city":"Los Angeles",
    "sg:classifiers":[
        {
            "category":"Organizations",
            "subcategory":"Religious Organization",
            "type":"Services"
        }
    ],
    "sg:phone":"+1 323 778 1597",
    "sg:postcode":"90047",
    "sg:province":"CA",
    "sg:tags":[
        "church"
    ],
    "wof:name":"Greater Liberty Baptist Church",
    "wof:placetype":"venue"
},
  "geometry": {"coordinates":[-118.309031,33.979204],"type":"Point"}
}