{
  "type": "Feature",
  "properties": {
    "iso:country":"US",
    "sg:address":"698 Nebraska St",
    "sg:city":"Vallejo",
    "sg:classifiers":[
        {
            "category":"Place Of Worship",
            "subcategory":"Church",
            "type":"Public Place"
        }
    ],
    "sg:phone":"+1 707 647 1938",
    "sg:postcode":"94590",
    "sg:province":"CA",
    "sg:tags":[
        "churches-salvation",
        "army"
    ],
    "wof:name":"Hidden Treaures",
    "wof:placetype":"venue"
},
  "geometry": {"coordinates":[-122.24852,38.113659],"type":"Point"}
}