{
  "type": "Feature",
  "properties": {
    "iso:country":"US",
    "sg:address":"25 19th Ave",
    "sg:city":"Venice",
    "sg:classifiers":[
        {
            "category":"Arts & Performance",
            "subcategory":"Theater",
            "type":"Entertainment"
        }
    ],
    "sg:phone":"+1 310 305 7479",
    "sg:postcode":"90291",
    "sg:province":"CA",
    "sg:tags":[
        "bureau"
    ],
    "wof:name":"Stairway Music",
    "wof:placetype":"venue"
},
  "geometry": {"coordinates":[-118.471191,33.986013],"type":"Point"}
}