{
  "type": "Feature",
  "properties": {
    "addr:full":"267 N El Camino Real Ste H Encinitas CA 92024",
    "addr:housenumber":"267",
    "addr:postcode":"92024",
    "addr:street":"N El Camino Real Ste H",
    "iso:country":"US",
    "sg:address":"267 N El Camino Real Ste H",
    "sg:city":"Encinitas",
    "sg:classifiers":[
        {
            "category":"Health Services",
            "subcategory":"Chiropractor",
            "type":"Services"
        }
    ],
    "sg:phone":"+1 760 943 8500",
    "sg:postcode":"92024",
    "sg:province":"CA",
    "wof:name":"Accelerated Chiropractic Care",
    "wof:placetype":"venue"
},
  "geometry": {"coordinates":[-117.261002,33.052898],"type":"Point"}
}