{
  "type": "Feature",
  "properties": {
    "addr:full":"3190 Forest Hills Dr Redding CA 96002",
    "addr:housenumber":"3190",
    "addr:postcode":"96002",
    "addr:street":"Forest Hills Dr",
    "iso:country":"US",
    "sg:address":"3190 Forest Hills Dr",
    "sg:city":"Redding",
    "sg:classifiers":[
        {
            "category":"Building & Trades",
            "subcategory":"Landscaping Services",
            "type":"Services"
        }
    ],
    "sg:phone":"+1 530 222 2349",
    "sg:postcode":"96002",
    "sg:province":"CA",
    "sg:tags":[
        "lawn",
        "maintenance",
        "grounds"
    ],
    "wof:name":"Corey's Lawn Care",
    "wof:placetype":"venue"
},
  "geometry": {"coordinates":[-122.310031,40.557195],"type":"Point"}
}