{
  "type": "Feature",
  "properties": {
    "addr:full":"4101 S Main St Santa Ana CA 92707",
    "addr:housenumber":"4101",
    "addr:postcode":"92707",
    "addr:street":"S Main St",
    "iso:country":"US",
    "sg:address":"4101 S Main St",
    "sg:city":"Santa Ana",
    "sg:classifiers":[
        {
            "category":"Retail",
            "subcategory":"Auto Rental",
            "type":"Services"
        }
    ],
    "sg:phone":"+1 714 957 6521",
    "sg:postcode":"92707",
    "sg:province":"CA",
    "sg:tags":[
        "car"
    ],
    "sg:website":"www.avis.com",
    "wof:name":"Avis",
    "wof:placetype":"venue"
},
  "geometry": {"coordinates":[-117.86794999999999,33.693471],"type":"Point"}
}