{
  "type": "Feature",
  "properties": {
    "iso:country":"US",
    "sg:address":"844 California St Ste 4",
    "sg:city":"San Francisco",
    "sg:classifiers":[
        {
            "category":"Health Services",
            "subcategory":"Clinic",
            "type":"Services"
        }
    ],
    "sg:phone":"+1 415 362 8262",
    "sg:postcode":"94108",
    "sg:province":"CA",
    "sg:tags":[
        "counseling",
        "mental"
    ],
    "sg:website":"www.drjeffkaye.com",
    "wof:name":"Jeffrey S Kaye, PhD",
    "wof:placetype":"venue"
},
  "geometry": {"coordinates":[-122.408317,37.792166],"type":"Point"}
}