{
  "type": "Feature",
  "properties": {
    "iso:country":"US",
    "sg:address":"3927 Marriott Dr",
    "sg:city":"Bakersfield",
    "sg:classifiers":[
        {
            "category":"Travel",
            "subcategory":"Hotels & Motels",
            "type":"Entertainment"
        },
        {
            "category":"Retail",
            "subcategory":"Event Space",
            "type":"Services"
        },
        {
            "category":"Travel",
            "subcategory":"Resort",
            "type":"Entertainment"
        }
    ],
    "sg:phone":"+1 800 345 8082",
    "sg:postcode":"93308",
    "sg:province":"CA",
    "sg:tags":[
        "facility",
        "banquet",
        "reception",
        "lodging",
        "corporate",
        "hall"
    ],
    "sg:website":"http://ad.doubleclick.net/clk;223371278;47096201;d?http://www.holidayinn.com/redirect?path=hd&brandCode=hi&hotelCode=bkrrh&_PMID=99601036&cm_mmc=mdpr-_-yellowpages-_-hi-_-bkrrh",
    "wof:name":"Holiday Inn Hotel & Suites Bakersfield North",
    "wof:placetype":"venue"
},
  "geometry": {"coordinates":[-119.049359,35.380482],"type":"Point"}
}