{
  "type": "Feature",
  "properties": {
    "iso:country":"US",
    "sg:address":"936 Hermosa Ave",
    "sg:city":"Hermosa Beach",
    "sg:classifiers":[
        {
            "category":"Professional",
            "subcategory":"Business Services",
            "type":"Services"
        }
    ],
    "sg:phone":"+1 310 374 4355",
    "sg:postcode":"90254",
    "sg:province":"CA",
    "sg:tags":[
        "notary"
    ],
    "wof:name":"Advantage Accounting Systems",
    "wof:placetype":"venue"
},
  "geometry": {"coordinates":[-118.399525,33.860648],"type":"Point"}
}