{
  "type": "Feature",
  "properties": {
    "iso:country":"US",
    "sg:address":"11576 Morrison St",
    "sg:city":"North Hollywood",
    "sg:classifiers":[
        {
            "category":"Organizations",
            "subcategory":"Non-profit Organization",
            "type":"Services"
        }
    ],
    "sg:phone":"+1 818 906 8832",
    "sg:postcode":"91601",
    "sg:province":"CA",
    "sg:tags":[
        "suicide",
        "prevention"
    ],
    "wof:name":"Rosemarie S White",
    "wof:placetype":"venue"
},
  "geometry": {"coordinates":[-118.384414,34.160305],"type":"Point"}
}