{
  "type": "Feature",
  "properties": {
    "iso:country":"US",
    "sg:address":"420 S White Rd",
    "sg:city":"San Jose",
    "sg:classifiers":[
        {
            "category":"Insurance",
            "subcategory":"Insurance Agent",
            "type":"Services"
        }
    ],
    "sg:phone":"+1 408 347 3340",
    "sg:postcode":"95127",
    "sg:province":"CA",
    "wof:name":"Allstate",
    "wof:placetype":"venue"
},
  "geometry": {"coordinates":[-121.824382,37.36201],"type":"Point"}
}