{
  "type": "Feature",
  "properties": {
    "iso:country":"US",
    "sg:address":"7452 Monterey St",
    "sg:city":"Gilroy",
    "sg:classifiers":[
        {
            "category":"Personal",
            "subcategory":"Beauty Salon",
            "type":"Services"
        }
    ],
    "sg:phone":"+1 408 842 9991",
    "sg:postcode":"95020",
    "sg:province":"CA",
    "wof:name":"Kutz & Colors Hair Salon",
    "wof:placetype":"venue"
},
  "geometry": {"coordinates":[-121.56897499999999,37.007459],"type":"Point"}
}