{
  "type": "Feature",
  "properties": {
    "addr:full":"3848 E Chapman Ave Ste A-1 Orange CA 92869",
    "addr:housenumber":"3848",
    "addr:postcode":"92869",
    "addr:street":"E Chapman Ave Ste A-1",
    "iso:country":"US",
    "sg:address":"3848 E Chapman Ave Ste A-1",
    "sg:city":"Orange",
    "sg:classifiers":[
        {
            "category":"Restaurant",
            "type":"Food & Drink"
        }
    ],
    "sg:phone":"+1 714 628 9845",
    "sg:postcode":"92869",
    "sg:province":"CA",
    "sg:tags":[
        "mexican"
    ],
    "wof:name":"Dona Meche",
    "wof:placetype":"venue"
},
  "geometry": {"coordinates":[-117.81265,33.787775],"type":"Point"}
}