{
  "type": "Feature",
  "properties": {
    "addr:full":"104 Bronson St Ste 22 Santa Cruz CA 95062",
    "addr:housenumber":"104",
    "addr:postcode":"95062",
    "addr:street":"Bronson St Ste 22",
    "iso:country":"US",
    "sg:address":"104 Bronson St Ste 22",
    "sg:city":"Santa Cruz",
    "sg:classifiers":[
        {
            "category":"Shopping",
            "subcategory":"Bicycles & Sporting Goods",
            "type":"Retail Goods"
        }
    ],
    "sg:phone":"+1 831 459 7560",
    "sg:postcode":"95062",
    "sg:province":"CA",
    "sg:tags":[
        "bike"
    ],
    "wof:name":"Santa Cruz Mountain Bikes",
    "wof:placetype":"venue"
},
  "geometry": {"coordinates":[-122.00700399999999,36.967899],"type":"Point"}
}