{
  "type": "Feature",
  "properties": {
    "iso:country":"US",
    "sg:address":"19319 Ventura Blvd",
    "sg:city":"Tarzana",
    "sg:classifiers":[
        {
            "category":"Shopping",
            "subcategory":"Tobacco",
            "type":"Retail Goods"
        }
    ],
    "sg:phone":"+1 818 996 1110",
    "sg:postcode":"91356",
    "sg:province":"CA",
    "sg:tags":[
        "cigarette",
        "cigar",
        "dealer"
    ],
    "wof:name":"Lou's Tobacco Row LTD",
    "wof:placetype":"venue"
},
  "geometry": {"coordinates":[-118.554107,34.172741],"type":"Point"}
}