{
  "type": "Feature",
  "properties": {
    "addr:full":"11519 Lower Circle Dr Grass Valley CA 95949",
    "addr:housenumber":"11519",
    "addr:postcode":"95949",
    "addr:street":"Lower Circle Dr",
    "iso:country":"US",
    "sg:address":"11519 Lower Circle Dr",
    "sg:city":"Grass Valley",
    "sg:classifiers":[
        {
            "category":"Professional",
            "subcategory":"Engineering",
            "type":"Services"
        }
    ],
    "sg:phone":"+1 530 274 1617",
    "sg:postcode":"95949",
    "sg:province":"CA",
    "sg:tags":[
        "engineer"
    ],
    "wof:name":"Black Oak Engineering",
    "wof:placetype":"venue"
},
  "geometry": {"coordinates":[-121.04921899999999,39.140205],"type":"Point"}
}