{
  "type": "Feature",
  "properties": {
    "addr:full":"2222 Francisco Dr El Dorado Hills CA 95762",
    "addr:housenumber":"2222",
    "addr:postcode":"95762",
    "addr:street":"Francisco Dr",
    "iso:country":"US",
    "sg:address":"2222 Francisco Dr",
    "sg:city":"El Dorado Hills",
    "sg:classifiers":[
        {
            "category":"Social Services",
            "subcategory":"Child Care",
            "type":"Services"
        }
    ],
    "sg:phone":"+1 916 933 2420",
    "sg:postcode":"95762",
    "sg:province":"CA",
    "sg:tags":[
        "kindergarten",
        "academic",
        "school"
    ],
    "wof:name":"Montessori Manor",
    "wof:placetype":"venue"
},
  "geometry": {"coordinates":[-121.086118,38.712601],"type":"Point"}
}