{
  "type": "Feature",
  "properties": {
    "addr:full":"3565 Geary St San Francisco CA 94118",
    "addr:housenumber":"3565",
    "addr:postcode":"94118",
    "addr:street":"Geary St",
    "iso:country":"US",
    "sg:address":"3565 Geary St",
    "sg:city":"San Francisco",
    "sg:classifiers":[
        {
            "category":"Bars & Pubs",
            "type":"Food & Drink"
        }
    ],
    "sg:postcode":"94118",
    "sg:province":"CA",
    "wof:name":"PT Sports Bar",
    "wof:placetype":"venue"
},
  "geometry": {"coordinates":[-122.457241,37.781308],"type":"Point"}
}