{
  "type": "Feature",
  "properties": {
    "iso:country":"US",
    "sg:address":"3541 E Stapp Ave",
    "sg:city":"Visalia",
    "sg:classifiers":[
        {
            "category":"Wholesale",
            "subcategory":"Durable Goods & Equipment",
            "type":"Manufacturing & Wholesale Goods"
        }
    ],
    "sg:phone":"+1 559 625 5752",
    "sg:postcode":"93292",
    "sg:province":"CA",
    "sg:tags":[
        "importer"
    ],
    "wof:name":"South Valley Imports",
    "wof:placetype":"venue"
},
  "geometry": {"coordinates":[-119.253945,36.329778],"type":"Point"}
}