{
  "type": "Feature",
  "properties": {
    "iso:country":"US",
    "sg:address":"1822 W Kettleman Ln Ste 5",
    "sg:city":"Lodi",
    "sg:classifiers":[
        {
            "category":"Health Services",
            "subcategory":"Chiropractor",
            "type":"Services"
        }
    ],
    "sg:phone":"+1 209 368 1023",
    "sg:postcode":"95242",
    "sg:province":"CA",
    "sg:tags":[
        "chiropractic"
    ],
    "wof:name":"Glen C Schaefer Dc",
    "wof:placetype":"venue"
},
  "geometry": {"coordinates":[-121.29485099999999,38.115394],"type":"Point"}
}