{
  "type": "Feature",
  "properties": {
    "addr:full":"1041 Green Tree Ct Paradise CA 95969",
    "addr:housenumber":"1041",
    "addr:postcode":"95969",
    "addr:street":"Green Tree Ct",
    "iso:country":"US",
    "sg:address":"1041 Green Tree Ct",
    "sg:city":"Paradise",
    "sg:classifiers":[
        {
            "category":"Retail",
            "subcategory":"Auto Repair",
            "type":"Services"
        }
    ],
    "sg:phone":"+1 530 877 5000",
    "sg:postcode":"95969",
    "sg:province":"CA",
    "sg:tags":[
        "wrecker"
    ],
    "wof:name":"Dave's D J's Towing",
    "wof:placetype":"venue"
},
  "geometry": {"coordinates":[-121.609015,39.774781],"type":"Point"}
}