{
  "type": "Feature",
  "properties": {
    "iso:country":"US",
    "sg:address":"1670 15th St",
    "sg:city":"San Francisco",
    "sg:classifiers":[
        {
            "category":"Retail",
            "subcategory":"Auto Repair",
            "type":"Services"
        }
    ],
    "sg:phone":"+1 415 285 8141",
    "sg:postcode":"94102",
    "sg:province":"CA",
    "sg:tags":[
        "body",
        "shop",
        "painting",
        "automobile"
    ],
    "wof:name":"Americas Body Shop",
    "wof:placetype":"venue"
},
  "geometry": {"coordinates":[-122.421397,37.766798],"type":"Point"}
}