{
  "type": "Feature",
  "properties": {
    "addr:full":"14560 Calvert St Van Nuys CA 91411",
    "addr:housenumber":"14560",
    "addr:postcode":"91411",
    "addr:street":"Calvert St",
    "iso:country":"US",
    "sg:address":"14560 Calvert St",
    "sg:city":"Van Nuys",
    "sg:classifiers":[
        {
            "category":"Professional",
            "subcategory":"Business Services",
            "type":"Services"
        }
    ],
    "sg:phone":"+1 818 366 0493",
    "sg:postcode":"91411",
    "sg:province":"CA",
    "sg:tags":[
        "recording",
        "studio"
    ],
    "wof:name":"Khalifa Records",
    "wof:placetype":"venue"
},
  "geometry": {"coordinates":[-118.449789,34.181583],"type":"Point"}
}