{
  "type": "Feature",
  "properties": {
    "addr:full":"5525 N 10th St Fresno CA 93710",
    "addr:housenumber":"5525",
    "addr:postcode":"93710",
    "addr:street":"N 10Th St",
    "iso:country":"US",
    "sg:address":"5525 N 10th St",
    "sg:city":"Fresno",
    "sg:classifiers":[
        {
            "category":"Arts & Performance",
            "subcategory":"Theater",
            "type":"Entertainment"
        }
    ],
    "sg:phone":"+1 559 435 4833",
    "sg:postcode":"93710",
    "sg:province":"CA",
    "sg:tags":[
        "live",
        "music"
    ],
    "wof:name":"Silk Hat Productions",
    "wof:placetype":"venue"
},
  "geometry": {"coordinates":[-119.757042,36.819612],"type":"Point"}
}