{
  "type": "Feature",
  "properties": {
    "addr:full":"27000 Crown Valley Parkway San Juan Capistrano CA 92691",
    "addr:housenumber":"27000",
    "addr:postcode":"92691",
    "addr:street":"Crown Valley Parkway",
    "iso:country":"US",
    "sg:address":"27000 Crown Valley Parkway",
    "sg:city":"San Juan Capistrano",
    "sg:classifiers":[
        {
            "category":"Shopping",
            "subcategory":"Shoes",
            "type":"Retail Goods"
        }
    ],
    "sg:phone":"+1 949 364 7003",
    "sg:postcode":"92691",
    "sg:province":"CA",
    "sg:tags":[
        "store"
    ],
    "wof:name":"Walking Company",
    "wof:placetype":"venue"
},
  "geometry": {"coordinates":[-117.66971700000001,33.561624],"type":"Point"}
}