{
  "type": "Feature",
  "properties": {
    "iso:country":"US",
    "sg:address":"417 Ave Arboles",
    "sg:city":"San Jose",
    "sg:classifiers":[
        {
            "category":"Professional",
            "type":"Services"
        }
    ],
    "sg:phone":"+1 408 226 7397",
    "sg:postcode":"95123",
    "sg:province":"CA",
    "wof:name":"Becket & Company Incorporated",
    "wof:placetype":"venue"
},
  "geometry": {"coordinates":[-121.837605,37.255286],"type":"Point"}
}