{
  "type": "Feature",
  "properties": {
    "addr:full":"8358 W Sunset Blvd West Hollywood CA 90069",
    "addr:housenumber":"8358",
    "addr:postcode":"90069",
    "addr:street":"W Sunset Blvd",
    "iso:country":"US",
    "sg:address":"8358 W Sunset Blvd",
    "sg:city":"West Hollywood",
    "sg:classifiers":[
        {
            "category":"Travel",
            "subcategory":"Hotels & Motels",
            "type":"Entertainment"
        }
    ],
    "sg:phone":"+1 323 654 5381",
    "sg:postcode":"90069",
    "sg:province":"CA",
    "sg:website":"www.sunsettowerhotel.com",
    "wof:name":"Sunset Tower Hotel",
    "wof:placetype":"venue"
},
  "geometry": {"coordinates":[-118.372148,34.09505],"type":"Point"}
}