{
  "type": "Feature",
  "properties": {
    "iso:country":"US",
    "sg:address":"614 San Mateo Ave",
    "sg:city":"San Bruno",
    "sg:classifiers":[
        {
            "category":"Professional",
            "subcategory":"Business Services",
            "type":"Services"
        }
    ],
    "sg:phone":"+1 650 871 1313",
    "sg:postcode":"94066",
    "sg:province":"CA",
    "sg:tags":[
        "durable",
        "goo",
        "merchandise"
    ],
    "wof:name":"Fire Pro Extinguisher Company",
    "wof:placetype":"venue"
},
  "geometry": {"coordinates":[-122.411215,37.627404],"type":"Point"}
}