{
  "type": "Feature",
  "properties": {
    "addr:full":"617 N Irwin St Hanford CA 93230",
    "addr:housenumber":"617",
    "addr:postcode":"ca 93230",
    "addr:street":"N Irwin St",
    "iso:country":"US",
    "sg:address":"617 N Irwin St",
    "sg:city":"Hanford",
    "sg:classifiers":[
        {
            "category":"Shopping",
            "type":"Retail Goods"
        }
    ],
    "sg:phone":"+1 559 583 1700",
    "sg:postcode":"93230",
    "sg:province":"CA",
    "sg:tags":[
        "pet",
        "food",
        "supply"
    ],
    "sg:website":"www.petstophanford.com",
    "wof:name":"Pet Stop",
    "wof:placetype":"venue"
},
  "geometry": {"coordinates":[-119.647604,36.331559],"type":"Point"}
}