{
  "type": "Feature",
  "properties": {
    "iso:country":"US",
    "sg:address":"14531 Big Basin Way Ste 1",
    "sg:city":"Saratoga",
    "sg:classifiers":[
        {
            "category":"Shopping",
            "subcategory":"Beauty & Cosmetics",
            "type":"Retail Goods"
        }
    ],
    "sg:phone":"+1 408 867 7831",
    "sg:postcode":"95070",
    "sg:province":"CA",
    "sg:tags":[
        "supply"
    ],
    "wof:name":"Skin Prophecy Boutique",
    "wof:placetype":"venue"
},
  "geometry": {"coordinates":[-122.033997,37.257],"type":"Point"}
}