{
  "type": "Feature",
  "properties": {
    "iso:country":"US",
    "sg:address":"13363 Ventura Blvd",
    "sg:city":"Sherman Oaks",
    "sg:classifiers":[
        {
            "category":"Home & Garden",
            "subcategory":"Home Furnishings",
            "type":"Retail Goods"
        }
    ],
    "sg:phone":"+1 818 788 3400",
    "sg:postcode":"91423",
    "sg:province":"CA",
    "sg:tags":[
        "decor"
    ],
    "sg:website":"www.aumandgarden.com",
    "wof:name":"Aum & Garden",
    "wof:placetype":"venue"
},
  "geometry": {"coordinates":[-118.424533,34.146931],"type":"Point"}
}