{
  "type": "Feature",
  "properties": {
    "addr:full":"16970 Tulip Tree Way Lathrop CA 95330",
    "addr:housenumber":"16970",
    "addr:postcode":"95330",
    "addr:street":"Tulip Tree Way",
    "iso:country":"US",
    "sg:address":"16970 Tulip Tree Way",
    "sg:city":"Lathrop",
    "sg:classifiers":[
        {
            "category":"Professional",
            "subcategory":"Business Services",
            "type":"Services"
        }
    ],
    "sg:phone":"+1 209 983 1922",
    "sg:postcode":"95330",
    "sg:province":"CA",
    "sg:tags":[
        "organizing",
        "medical",
        "administration",
        "services-household"
    ],
    "wof:name":"Diva Inc Corporate",
    "wof:placetype":"venue"
},
  "geometry": {"coordinates":[-121.301714,37.806518],"type":"Point"}
}