{
  "type": "Feature",
  "properties": {
    "iso:country":"US",
    "sg:address":"707 N Broadway",
    "sg:city":"Santa Maria",
    "sg:classifiers":[
        {
            "category":"Shopping",
            "subcategory":"Pharmacy",
            "type":"Retail Goods"
        }
    ],
    "sg:phone":"+1 805 614 6127",
    "sg:postcode":"93454",
    "sg:province":"CA",
    "sg:website":"www.walgreens.com",
    "wof:name":"Walgreens",
    "wof:placetype":"venue"
},
  "geometry": {"coordinates":[-120.435886,34.960379],"type":"Point"}
}