{
  "type": "Feature",
  "properties": {
    "addr:full":"18523 Soledad Canyon Rd Canyon Country CA 91351",
    "addr:housenumber":"18523",
    "addr:postcode":"91351",
    "addr:street":"Soledad Canyon Rd",
    "iso:country":"US",
    "sg:address":"18523 Soledad Canyon Rd",
    "sg:city":"Canyon Country",
    "sg:classifiers":[
        {
            "category":"Home & Garden",
            "subcategory":"Mobile Homes",
            "type":"Retail Goods"
        }
    ],
    "sg:phone":"+1 661 298 3377",
    "sg:postcode":"91351",
    "sg:province":"CA",
    "sg:website":"www.lcmobilehomes.com",
    "wof:name":"Casa Blanca Homes",
    "wof:placetype":"venue"
},
  "geometry": {"coordinates":[-118.456301,34.416537],"type":"Point"}
}