{
  "type": "Feature",
  "properties": {
    "addr:full":"16932 Gothard Street Huntington Beach CA 92647",
    "addr:postcode":"16932;92647",
    "addr:street":"Gothard Street",
    "iso:country":"US",
    "sg:address":"16932 Gothard Street",
    "sg:city":"Huntington Beach",
    "sg:classifiers":[
        {
            "category":"Health Services",
            "subcategory":"Health Practitioner",
            "type":"Services"
        },
        {
            "category":"Insurance",
            "subcategory":"Health Insurance",
            "type":"Services"
        }
    ],
    "sg:phone":"+1 714 841 5349",
    "sg:postcode":"92647",
    "sg:province":"CA",
    "sg:tags":[
        "nutritionist",
        "market"
    ],
    "sg:website":"www.fernsnutrition.com",
    "wof:name":"Ferns Nutrition Center",
    "wof:placetype":"venue"
},
  "geometry": {"coordinates":[-118.000084,33.716336],"type":"Point"}
}