{
  "type": "Feature",
  "properties": {
    "addr:full":"15430 Cabrito Rd Van Nuys CA 91406",
    "addr:housenumber":"15430",
    "addr:postcode":"91406",
    "addr:street":"Cabrito Rd",
    "iso:country":"US",
    "sg:address":"15430 Cabrito Rd",
    "sg:city":"Van Nuys",
    "sg:classifiers":[
        {
            "category":"Retail",
            "subcategory":"Repair Shop",
            "type":"Services"
        }
    ],
    "sg:phone":"+1 818 908 0014",
    "sg:postcode":"91406",
    "sg:province":"CA",
    "sg:tags":[
        "ironwork"
    ],
    "wof:name":"Perez Iron Design",
    "wof:placetype":"venue"
},
  "geometry": {"coordinates":[-118.46849,34.216551],"type":"Point"}
}