{
  "type": "Feature",
  "properties": {
    "addr:full":"12016 Wilshire Blvd Los Angeles CA 90025",
    "addr:housenumber":"12016",
    "addr:postcode":"90025",
    "addr:street":"Wilshire Blvd",
    "iso:country":"US",
    "sg:address":"12016 Wilshire Blvd",
    "sg:city":"Los Angeles",
    "sg:classifiers":[
        {
            "category":"Insurance",
            "subcategory":"Insurance Agent",
            "type":"Services"
        }
    ],
    "sg:phone":"+1 310 207 6622",
    "sg:postcode":"90025",
    "sg:province":"CA",
    "wof:name":"Ted Oldemans Insurance Svc",
    "wof:placetype":"venue"
},
  "geometry": {"coordinates":[-118.46723,34.044233],"type":"Point"}
}