{
  "type": "Feature",
  "properties": {
    "iso:country":"US",
    "sg:address":"8601 Wilshire Blvd Ste 801",
    "sg:city":"Beverly Hills",
    "sg:classifiers":[
        {
            "category":"Professional",
            "subcategory":"Lawyer & Legal Services",
            "type":"Services"
        }
    ],
    "sg:phone":"+1 310 657 2492",
    "sg:postcode":"90211",
    "sg:province":"CA",
    "wof:name":"Levine Peter K Atty",
    "wof:placetype":"venue"
},
  "geometry": {"coordinates":[-118.384003,34.067101],"type":"Point"}
}