{
  "type": "Feature",
  "properties": {
    "iso:country":"US",
    "sg:address":"110 S B St",
    "sg:city":"San Mateo",
    "sg:classifiers":[
        {
            "category":"Shopping",
            "subcategory":"Jewelry",
            "type":"Retail Goods"
        }
    ],
    "sg:phone":"+1 650 558 0383",
    "sg:postcode":"94401",
    "sg:province":"CA",
    "sg:tags":[
        "jeweler"
    ],
    "wof:name":"Ditto",
    "wof:placetype":"venue"
},
  "geometry": {"coordinates":[-122.323369,37.566304],"type":"Point"}
}