{
  "type": "Feature",
  "properties": {
    "addr:full":"4953 el Cajon Blvd San Diego CA 92115",
    "addr:housenumber":"4953",
    "addr:postcode":"92115",
    "addr:street":"El Cajon Blvd",
    "iso:country":"US",
    "sg:address":"4953 el Cajon Blvd",
    "sg:city":"San Diego",
    "sg:classifiers":[
        {
            "category":"Restaurant",
            "type":"Food & Drink"
        }
    ],
    "sg:phone":"+1 619 265 0900",
    "sg:postcode":"92115",
    "sg:province":"CA",
    "sg:tags":[
        "caterer"
    ],
    "wof:name":"Consummate Catering",
    "wof:placetype":"venue"
},
  "geometry": {"coordinates":[-117.087391,32.756632],"type":"Point"}
}