{
  "type": "Feature",
  "properties": {
    "addr:full":"375 2nd Ave San Mateo CA 94401",
    "addr:housenumber":"375",
    "addr:postcode":"94401",
    "addr:street":"2Nd Ave",
    "iso:country":"US",
    "sg:address":"375 2nd Ave",
    "sg:city":"San Mateo",
    "sg:classifiers":[
        {
            "category":"Restaurant",
            "type":"Food & Drink"
        },
        {
            "category":"Ice Cream",
            "type":"Food & Drink"
        }
    ],
    "sg:menulink":"http://www.allmenus.com/ca/san-mateo/183988-cold-stone-creamery/menu/",
    "sg:phone":"+1 650 347 0500",
    "sg:postcode":"94401",
    "sg:province":"CA",
    "sg:tags":[
        "smoothy",
        "juice",
        "american",
        "ice",
        "cream"
    ],
    "wof:name":"Cold Stone Creamery",
    "wof:placetype":"venue"
},
  "geometry": {"coordinates":[-122.32271799999999,37.566639],"type":"Point"}
}