{
  "type": "Feature",
  "properties": {
    "addr:full":"8887 Folsom Blvd Sacramento CA 95826",
    "addr:housenumber":"8887",
    "addr:postcode":"95826",
    "addr:street":"Folsom Blvd",
    "iso:country":"US",
    "sg:address":"8887 Folsom Blvd",
    "sg:city":"Sacramento",
    "sg:classifiers":[
        {
            "category":"Sports & Exercise",
            "subcategory":"Gym",
            "type":"Entertainment"
        }
    ],
    "sg:phone":"+1 916 364 9913",
    "sg:postcode":"95826",
    "sg:province":"CA",
    "sg:tags":[
        "club",
        "health",
        "studio",
        "gymnasium"
    ],
    "wof:name":"Curves For Women",
    "wof:placetype":"venue"
},
  "geometry": {"coordinates":[-121.377104,38.55218],"type":"Point"}
}