{
  "type": "Feature",
  "properties": {
    "addr:full":"126 Cochrane Rd Morgan Hill CA 95037",
    "addr:housenumber":"126",
    "addr:postcode":"95037",
    "addr:street":"Cochrane Rd",
    "iso:country":"US",
    "sg:address":"126 Cochrane Rd",
    "sg:city":"Morgan Hill",
    "sg:classifiers":[
        {
            "category":"Shopping",
            "subcategory":"Clothing, Apparel, & Fashions",
            "type":"Retail Goods"
        }
    ],
    "sg:phone":"+1 408 779 5700",
    "sg:postcode":"95037",
    "sg:province":"CA",
    "sg:tags":[
        "furnishing"
    ],
    "sg:website":"www.anchorblue.com",
    "wof:name":"Miller's Outpost",
    "wof:placetype":"venue"
},
  "geometry": {"coordinates":[-121.661745,37.146868],"type":"Point"}
}