{
  "type": "Feature",
  "properties": {
    "addr:full":"355 W Alma Ave San Jose CA 95110",
    "addr:housenumber":"355",
    "addr:postcode":"95110",
    "addr:street":"W Alma Ave",
    "iso:country":"US",
    "sg:address":"355 W Alma Ave",
    "sg:city":"San Jose",
    "sg:classifiers":[
        {
            "category":"Restaurant",
            "type":"Food & Drink"
        }
    ],
    "sg:phone":"+1 408 292 1838",
    "sg:postcode":"95110",
    "sg:province":"CA",
    "wof:name":"Foodall",
    "wof:placetype":"venue"
},
  "geometry": {"coordinates":[-121.881624,37.311025],"type":"Point"}
}