{
  "type": "Feature",
  "properties": {
    "iso:country":"US",
    "sg:address":"433 Alisal Rd",
    "sg:city":"Solvang",
    "sg:classifiers":[
        {
            "category":"Professional",
            "subcategory":"Lawyer & Legal Services",
            "type":"Services"
        }
    ],
    "sg:phone":"+1 805 688 8075",
    "sg:postcode":"93463",
    "sg:province":"CA",
    "sg:tags":[
        "attorney"
    ],
    "wof:name":"Gateway LAW Forum",
    "wof:placetype":"venue"
},
  "geometry": {"coordinates":[-120.139256,34.593235],"type":"Point"}
}