{
  "type": "Feature",
  "properties": {
    "iso:country":"US",
    "sg:address":"3235 Associated Rd",
    "sg:city":"Fullerton",
    "sg:classifiers":[
        {
            "category":"Home & Garden",
            "subcategory":"Furniture",
            "type":"Retail Goods"
        }
    ],
    "sg:phone":"+1 714 255 0088",
    "sg:postcode":"92835",
    "sg:province":"CA",
    "sg:tags":[
        "store"
    ],
    "wof:name":"Futon Emporium",
    "wof:placetype":"venue"
},
  "geometry": {"coordinates":[-117.880522,33.90858],"type":"Point"}
}