{
  "type": "Feature",
  "properties": {
    "iso:country":"US",
    "sg:address":"855 Montague St",
    "sg:city":"San Leandro",
    "sg:phone":"+1 510 351 0560",
    "sg:postcode":"94577",
    "sg:province":"CA",
    "sg:tags":[
        "food",
        "equipment",
        "processing"
    ],
    "wof:name":"Ashlock Co",
    "wof:placetype":"venue"
},
  "geometry": {"coordinates":[-122.159977,37.709447],"type":"Point"}
}