{
  "type": "Feature",
  "properties": {
    "addr:full":"8684 Avenida De La Fuente San Diego CA 92154",
    "addr:housenumber":"8684",
    "addr:postcode":"92154",
    "addr:street":"Avenida De La Fuente",
    "iso:country":"US",
    "sg:address":"8684 Avenida De La Fuente",
    "sg:city":"San Diego",
    "sg:classifiers":[
        {
            "category":"Autos & Motor Vehicles",
            "subcategory":"Automobile Sales",
            "type":"Retail Goods"
        }
    ],
    "sg:phone":"+1 619 671 9776",
    "sg:postcode":"92154",
    "sg:province":"CA",
    "sg:tags":[
        "limo"
    ],
    "wof:name":"Silver Star Limousine",
    "wof:placetype":"venue"
},
  "geometry": {"coordinates":[-116.956041,32.556232],"type":"Point"}
}