{
  "type": "Feature",
  "properties": {
    "addr:full":"50 University Avenue Los Gatos CA 95030",
    "addr:housenumber":"50",
    "addr:postcode":"95030",
    "addr:street":"University Avenue",
    "iso:country":"US",
    "sg:address":"50 University Avenue",
    "sg:city":"Los Gatos",
    "sg:classifiers":[
        {
            "category":"Shopping",
            "subcategory":"Jewelry",
            "type":"Retail Goods"
        }
    ],
    "sg:phone":"+1 408 354 9988",
    "sg:postcode":"95030",
    "sg:province":"CA",
    "wof:name":"The Indian Store",
    "wof:placetype":"venue"
},
  "geometry": {"coordinates":[-121.98209,37.223161],"type":"Point"}
}