{
  "type": "Feature",
  "properties": {
    "iso:country":"US",
    "sg:address":"2100 Standiford Ave",
    "sg:city":"Modesto",
    "sg:classifiers":[
        {
            "category":"Recreation",
            "subcategory":"Amusement Park",
            "type":"Entertainment"
        }
    ],
    "sg:phone":"+1 209 526 0000",
    "sg:postcode":"95350",
    "sg:province":"CA",
    "wof:name":"Laser Quest",
    "wof:placetype":"venue"
},
  "geometry": {"coordinates":[-121.033327,37.689709],"type":"Point"}
}