{
  "type": "Feature",
  "properties": {
    "iso:country":"US",
    "sg:address":"5033 Corbin Ave",
    "sg:city":"San Jose",
    "sg:classifiers":[
        {
            "category":"Freight",
            "type":"Transportation"
        }
    ],
    "sg:phone":"+1 408 448 4125",
    "sg:postcode":"95118",
    "sg:province":"CA",
    "wof:name":"Reliable Electronic Transport",
    "wof:placetype":"venue"
},
  "geometry": {"coordinates":[-121.885672,37.256804],"type":"Point"}
}