{
  "type": "Feature",
  "properties": {
    "addr:full":"988 E el Camino Real Sunnyvale CA 94087",
    "addr:housenumber":"988",
    "addr:postcode":"94087",
    "addr:street":"E El Camino Real",
    "iso:country":"US",
    "sg:address":"988 E el Camino Real",
    "sg:city":"Sunnyvale",
    "sg:classifiers":[
        {
            "category":"Wholesale",
            "subcategory":"Groceries",
            "type":"Manufacturing & Wholesale Goods"
        }
    ],
    "sg:phone":"+1 408 774 1009",
    "sg:postcode":"94087",
    "sg:province":"CA",
    "wof:name":"Peale It Together",
    "wof:placetype":"venue"
},
  "geometry": {"coordinates":[-122.008202,37.352034],"type":"Point"}
}