{
  "type": "Feature",
  "properties": {
    "addr:full":"5000 Warehouse Way Sacramento CA 95826",
    "addr:housenumber":"5000",
    "addr:postcode":"95826",
    "addr:street":"Warehouse Way",
    "iso:country":"US",
    "sg:address":"5000 Warehouse Way",
    "sg:city":"Sacramento",
    "sg:classifiers":[
        {
            "category":"Manufacturing",
            "subcategory":"Chemicals & Compounds",
            "type":"Manufacturing & Wholesale Goods"
        }
    ],
    "sg:phone":"+1 916 381 7052",
    "sg:postcode":"95826",
    "sg:province":"CA",
    "sg:tags":[
        "chemicals-wholesale",
        "manufacturer"
    ],
    "wof:name":"Du Pont Liquid Packaging Systs",
    "wof:placetype":"venue"
},
  "geometry": {"coordinates":[-121.389056,38.531163],"type":"Point"}
}