{
  "type": "Feature",
  "properties": {
    "addr:full":"39120 Argonaut Way 362 Fremont CA 94538",
    "addr:housenumber":"39120;362",
    "addr:postcode":"94538",
    "addr:street":"Argonaut Way",
    "iso:country":"US",
    "sg:address":"39120 Argonaut Way 362",
    "sg:city":"Fremont",
    "sg:classifiers":[
        {
            "category":"Retail",
            "subcategory":"Auto Repair",
            "type":"Services"
        }
    ],
    "sg:phone":"+1 510 651 7698",
    "sg:postcode":"94538",
    "sg:province":"CA",
    "sg:tags":[
        "wheel",
        "automobile",
        "body",
        "servicing-automotive",
        "axle",
        "alignment-frame",
        "painting",
        "repairing"
    ],
    "wof:name":"Auto Mall Body & Frame Co",
    "wof:placetype":"venue"
},
  "geometry": {"coordinates":[-121.98912900000001,37.544534],"type":"Point"}
}