{
  "type": "Feature",
  "properties": {
    "addr:full":"1009 W Arrow Hwy San Dimas CA 91773",
    "addr:housenumber":"1009",
    "addr:postcode":"91773",
    "addr:street":"W Arrow Hwy",
    "iso:country":"US",
    "sg:address":"1009 W Arrow Hwy",
    "sg:city":"San Dimas",
    "sg:classifiers":[
        {
            "category":"Restaurant",
            "type":"Food & Drink"
        },
        {
            "category":"Ice Cream",
            "type":"Food & Drink"
        }
    ],
    "sg:menulink":"http://www.allmenus.com/ca/east-san-gabriel-valley/183976-cold-stone-creamery/menu/",
    "sg:phone":"+1 909 305 9368",
    "sg:postcode":"91773",
    "sg:province":"CA",
    "sg:tags":[
        "smoothy",
        "juice",
        "american",
        "ice",
        "cream"
    ],
    "wof:name":"Cold Stone Creamery",
    "wof:placetype":"venue"
},
  "geometry": {"coordinates":[-117.827371,34.106749],"type":"Point"}
}