{
  "type": "Feature",
  "properties": {
    "addr:full":"17705 Hale Ave Morgan Hill CA 95037",
    "addr:housenumber":"17705",
    "addr:postcode":"95037",
    "addr:street":"Hale Ave",
    "iso:country":"US",
    "sg:address":"17705 Hale Ave",
    "sg:city":"Morgan Hill",
    "sg:classifiers":[
        {
            "category":"Real Estate",
            "subcategory":"Architect",
            "type":"Services"
        }
    ],
    "sg:phone":"+1 408 778 7005",
    "sg:postcode":"95037",
    "sg:province":"CA",
    "sg:tags":[
        "building",
        "designer"
    ],
    "wof:name":"D & Z Design Assoc",
    "wof:placetype":"venue"
},
  "geometry": {"coordinates":[-121.66108,37.131307],"type":"Point"}
}