{
  "type": "Feature",
  "properties": {
    "addr:full":"330 2nd St Los Altos Hills CA 94022",
    "addr:housenumber":"330",
    "addr:postcode":"94022",
    "addr:street":"2Nd St",
    "iso:country":"US",
    "sg:address":"330 2nd St",
    "sg:city":"Los Altos Hills",
    "sg:classifiers":[
        {
            "category":"Shopping",
            "subcategory":"Used Merchandise",
            "type":"Retail Goods"
        }
    ],
    "sg:phone":"+1 650 949 1593",
    "sg:postcode":"94022",
    "sg:province":"CA",
    "sg:tags":[
        "book",
        "rare",
        "dealer"
    ],
    "wof:name":"Antiquarian Archive",
    "wof:placetype":"venue"
},
  "geometry": {"coordinates":[-122.114581,37.375501],"type":"Point"}
}