{
  "type": "Feature",
  "properties": {
    "addr:full":"17330 Pioneer Blvd Artesia CA 90701",
    "addr:housenumber":"17330",
    "addr:postcode":"90701",
    "addr:street":"Pioneer Blvd",
    "iso:country":"US",
    "sg:address":"17330 Pioneer Blvd",
    "sg:city":"Artesia",
    "sg:classifiers":[
        {
            "category":"Shopping",
            "subcategory":"Mobile Phones",
            "type":"Retail Goods"
        }
    ],
    "sg:phone":"+1 562 467 0111",
    "sg:postcode":"90701",
    "sg:province":"CA",
    "wof:name":"Skymax PCS",
    "wof:placetype":"venue"
},
  "geometry": {"coordinates":[-118.205282,33.873613],"type":"Point"}
}