{
  "type": "Feature",
  "properties": {
    "addr:full":"3796 Via Real Carpinteria CA 93013",
    "addr:housenumber":"3796",
    "addr:postcode":"93013",
    "addr:street":"Via Real",
    "iso:country":"US",
    "sg:address":"3796 Via Real",
    "sg:city":"Carpinteria",
    "sg:classifiers":[
        {
            "category":"Farming",
            "subcategory":"Nursery",
            "type":"Manufacturing & Wholesale Goods"
        }
    ],
    "sg:phone":"+1 805 684 2051",
    "sg:postcode":"93013",
    "sg:province":"CA",
    "sg:tags":[
        "grower",
        "nursery-wholesale"
    ],
    "wof:name":"Robert C King Nursery",
    "wof:placetype":"venue"
},
  "geometry": {"coordinates":[-119.546824,34.406873],"type":"Point"}
}