{
  "type": "Feature",
  "properties": {
    "addr:full":"5145 Stevens Creek Blvd Ste 140 Santa Clara CA 95051",
    "addr:housenumber":"5145",
    "addr:postcode":"95051",
    "addr:street":"Stevens Creek Blvd Ste 140",
    "iso:country":"US",
    "sg:address":"5145 Stevens Creek Blvd Ste 140",
    "sg:city":"Santa Clara",
    "sg:classifiers":[
        {
            "category":"Sports & Exercise",
            "subcategory":"Gym",
            "type":"Entertainment"
        }
    ],
    "sg:phone":"+1 408 241 0328",
    "sg:postcode":"95051",
    "sg:province":"CA",
    "sg:tags":[
        "yoga"
    ],
    "sg:website":"www.dahnyoga.com",
    "wof:name":"Dahn Yoga Center",
    "wof:placetype":"venue"
},
  "geometry": {"coordinates":[-121.99298,37.323455],"type":"Point"}
}