{
  "type": "Feature",
  "properties": {
    "iso:country":"US",
    "sg:address":"3604 The Barnyard",
    "sg:city":"Carmel",
    "sg:classifiers":[
        {
            "category":"Shopping",
            "subcategory":"Florist",
            "type":"Retail Goods"
        }
    ],
    "sg:phone":"+1 831 624 5395",
    "sg:postcode":"93923",
    "sg:province":"CA",
    "wof:name":"Tempel's Of Carmel Florist",
    "wof:placetype":"venue"
},
  "geometry": {"coordinates":[-121.907068,36.539847],"type":"Point"}
}