{
  "type": "Feature",
  "properties": {
    "iso:country":"US",
    "sg:address":"9826 Oak St",
    "sg:city":"Bellflower",
    "sg:classifiers":[
        {
            "category":"Taxi",
            "type":"Transportation"
        },
        {
            "category":"Local Transit",
            "type":"Transportation"
        }
    ],
    "sg:phone":"+1 562 920 2020",
    "sg:postcode":"90706",
    "sg:province":"CA",
    "sg:tags":[
        "public"
    ],
    "wof:name":"Yellow Cab",
    "wof:placetype":"venue"
},
  "geometry": {"coordinates":[-118.124081,33.88453],"type":"Point"}
}