{
  "type": "Feature",
  "properties": {
    "iso:country":"US",
    "sg:address":"3842 W Slauson Ave",
    "sg:city":"Los Angeles",
    "sg:classifiers":[
        {
            "category":"Banks & Credit Unions",
            "subcategory":"Financial Services",
            "type":"Services"
        }
    ],
    "sg:phone":"+1 323 508 2406",
    "sg:postcode":"90043",
    "sg:province":"CA",
    "sg:tags":[
        "broker",
        "mortgage"
    ],
    "wof:name":"Roger's Business Service",
    "wof:placetype":"venue"
},
  "geometry": {"coordinates":[-118.341003,33.989101],"type":"Point"}
}