{
  "type": "Feature",
  "properties": {
    "addr:full":"108 E Marshall Blvd San Bernardino CA 92404",
    "addr:housenumber":"108",
    "addr:postcode":"92404",
    "addr:street":"E Marshall Blvd",
    "iso:country":"US",
    "sg:address":"108 E Marshall Blvd",
    "sg:city":"San Bernardino",
    "sg:classifiers":[
        {
            "category":"Education",
            "subcategory":"Library",
            "type":"Public Place"
        }
    ],
    "sg:phone":"+1 909 883 3411",
    "sg:postcode":"92404",
    "sg:province":"CA",
    "sg:tags":[
        "executive"
    ],
    "sg:website":"www.sbpl.org",
    "wof:name":"Rowe Howard M Branch Library",
    "wof:placetype":"venue"
},
  "geometry": {"coordinates":[-117.284328,34.149567],"type":"Point"}
}