{
  "type": "Feature",
  "properties": {
    "addr:full":"11335 Magnolia Blvd Ste 1A North Hollywood CA 91601",
    "addr:housenumber":"11335",
    "addr:postcode":"91601",
    "addr:street":"Magnolia Blvd Ste 1A",
    "iso:country":"US",
    "sg:address":"11335 Magnolia Blvd Ste 1A",
    "sg:city":"North Hollywood",
    "sg:classifiers":[
        {
            "category":"Health Services",
            "subcategory":"Dentist",
            "type":"Services"
        }
    ],
    "sg:phone":"+1 818 755 1588",
    "sg:postcode":"91601",
    "sg:province":"CA",
    "sg:website":"www.a-dentalcenter.com",
    "wof:name":"A-Dental Center",
    "wof:placetype":"venue"
},
  "geometry": {"coordinates":[-118.378641,34.165082],"type":"Point"}
}