{
  "type": "Feature",
  "properties": {
    "addr:full":"4113 Radford Ave Studio City CA 91604",
    "addr:housenumber":"4113",
    "addr:postcode":"91604",
    "addr:street":"Radford Ave",
    "iso:country":"US",
    "sg:address":"4113 Radford Ave",
    "sg:city":"Studio City",
    "sg:classifiers":[
        {
            "category":"Arts & Performance",
            "subcategory":"Theater",
            "type":"Entertainment"
        }
    ],
    "sg:phone":"+1 818 754 5454",
    "sg:postcode":"91604",
    "sg:province":"CA",
    "sg:tags":[
        "bureau"
    ],
    "wof:name":"R C Entertainment Inc",
    "wof:placetype":"venue"
},
  "geometry": {"coordinates":[-118.39222700000001,34.146436],"type":"Point"}
}