{
  "type": "Feature",
  "properties": {
    "iso:country":"US",
    "sg:address":"100 N Garfield Ave",
    "sg:city":"Pasadena",
    "sg:classifiers":[
        {
            "category":"Government",
            "subcategory":"Office",
            "type":"Public Place"
        }
    ],
    "sg:phone":"+1 626 744 4000",
    "sg:postcode":"91199",
    "sg:province":"CA",
    "sg:tags":[
        "city"
    ],
    "sg:website":"www.ci.pasadena.ca.us/",
    "wof:name":"Pasadena City Hall",
    "wof:placetype":"venue"
},
  "geometry": {"coordinates":[-118.144283,34.147625],"type":"Point"}
}