{
  "type": "Feature",
  "properties": {
    "addr:full":"8770 Greenback Ln Orangevale CA 95662",
    "addr:housenumber":"8770",
    "addr:postcode":"95662",
    "addr:street":"Greenback Ln",
    "iso:country":"US",
    "sg:address":"8770 Greenback Ln",
    "sg:city":"Orangevale",
    "sg:classifiers":[
        {
            "category":"Banks & Credit Unions",
            "subcategory":"Bank",
            "type":"Services"
        }
    ],
    "sg:phone":"+1 916 257 0067",
    "sg:postcode":"95662",
    "sg:province":"CA",
    "sg:tags":[
        "broker",
        "mortgage"
    ],
    "wof:name":"Equity Real Estate & Loan Svcs",
    "wof:placetype":"venue"
},
  "geometry": {"coordinates":[-121.230706,38.678425],"type":"Point"}
}