{
  "type": "Feature",
  "properties": {
    "iso:country":"US",
    "sg:address":"543 N Puente Ave",
    "sg:city":"La Puente",
    "sg:classifiers":[
        {
            "category":"Cinema",
            "subcategory":"Movie Rental",
            "type":"Entertainment"
        }
    ],
    "sg:phone":"+1 626 333 7271",
    "sg:postcode":"91746",
    "sg:province":"CA",
    "sg:tags":[
        "leasing",
        "video",
        "disc",
        "tape"
    ],
    "wof:name":"Budget Video Plus",
    "wof:placetype":"venue"
},
  "geometry": {"coordinates":[-117.982701,34.04959],"type":"Point"}
}