{
  "type": "Feature",
  "properties": {
    "addr:full":"23737 Madison St Torrance CA 90505",
    "addr:housenumber":"23737",
    "addr:postcode":"90505",
    "addr:street":"Madison St",
    "iso:country":"US",
    "sg:address":"23737 Madison St",
    "sg:city":"Torrance",
    "sg:classifiers":[
        {
            "category":"Professional",
            "subcategory":"Business Services",
            "type":"Services"
        }
    ],
    "sg:phone":"+1 310 378 4353",
    "sg:postcode":"90505",
    "sg:province":"CA",
    "sg:tags":[
        "interior",
        "consultant",
        "design",
        "decorator"
    ],
    "wof:name":"J Teddy Kelly Interior Design",
    "wof:placetype":"venue"
},
  "geometry": {"coordinates":[-118.348935,33.80817],"type":"Point"}
}