{
  "type": "Feature",
  "properties": {
    "addr:full":"1701 Blue Spruce Way Milpitas CA 95035",
    "addr:housenumber":"1701",
    "addr:postcode":"95035",
    "addr:street":"Blue Spruce Way",
    "iso:country":"US",
    "sg:address":"1701 Blue Spruce Way",
    "sg:city":"Milpitas",
    "sg:classifiers":[
        {
            "category":"Communications",
            "type":"Services"
        }
    ],
    "sg:phone":"+1 510 747 3326",
    "sg:postcode":"95035",
    "sg:province":"CA",
    "sg:tags":[
        "communication"
    ],
    "wof:name":"Lucent Technologies Inc",
    "wof:placetype":"venue"
},
  "geometry": {"coordinates":[-121.907867,37.405739],"type":"Point"}
}