{
  "type": "Feature",
  "properties": {
    "addr:full":"3146 Midway Dr San Diego CA 92110",
    "addr:housenumber":"3146",
    "addr:postcode":"92110",
    "addr:street":"Midway Dr",
    "iso:country":"US",
    "sg:address":"3146 Midway Dr",
    "sg:city":"San Diego",
    "sg:classifiers":[
        {
            "category":"Food & Beverages",
            "subcategory":"Bakery",
            "type":"Retail Goods"
        }
    ],
    "sg:phone":"+1 619 523 0464",
    "sg:postcode":"92110",
    "sg:province":"CA",
    "wof:name":"Yum Yum Donut Shop",
    "wof:placetype":"venue"
},
  "geometry": {"coordinates":[-117.207965,32.750429],"type":"Point"}
}