{
  "type": "Feature",
  "properties": {
    "addr:full":"77622 Country Club Dr Palm Desert CA 92211",
    "addr:housenumber":"77622",
    "addr:postcode":"ca 92211",
    "addr:street":"Country Club Dr",
    "iso:country":"US",
    "sg:address":"77622 Country Club Dr",
    "sg:city":"Palm Desert",
    "sg:classifiers":[
        {
            "category":"Wholesale",
            "subcategory":"Chemicals & Plastics",
            "type":"Manufacturing & Wholesale Goods"
        }
    ],
    "sg:phone":"+1 760 360 6400",
    "sg:postcode":"92211",
    "sg:province":"CA",
    "wof:name":"Nittan USA Inc",
    "wof:placetype":"venue"
},
  "geometry": {"coordinates":[-116.310872,33.758241],"type":"Point"}
}