{
  "type": "Feature",
  "properties": {
    "addr:full":"2666 W Olympic Blvd Los Angeles CA 90006",
    "addr:housenumber":"2666",
    "addr:postcode":"90006",
    "addr:street":"W Olympic Blvd",
    "iso:country":"US",
    "sg:address":"2666 W Olympic Blvd",
    "sg:city":"Los Angeles",
    "sg:classifiers":[
        {
            "category":"Restaurant",
            "type":"Food & Drink"
        }
    ],
    "sg:phone":"+1 213 381 6524",
    "sg:postcode":"90006",
    "sg:province":"CA",
    "sg:tags":[
        "korean"
    ],
    "wof:name":"New Seoul Restaurant",
    "wof:placetype":"venue"
},
  "geometry": {"coordinates":[-118.29022999999999,34.051989],"type":"Point"}
}