{
  "type": "Feature",
  "properties": {
    "addr:full":"3594 Ridgeline Dr San Bernardino CA 92407",
    "addr:housenumber":"3594",
    "addr:postcode":"92407",
    "addr:street":"Ridgeline Dr",
    "iso:country":"US",
    "sg:address":"3594 Ridgeline Dr",
    "sg:city":"San Bernardino",
    "sg:classifiers":[
        {
            "category":"Professional",
            "type":"Services"
        }
    ],
    "sg:phone":"+1 909 886 0452",
    "sg:postcode":"92407",
    "sg:province":"CA",
    "wof:name":"Wiens Cellars LLC",
    "wof:placetype":"venue"
},
  "geometry": {"coordinates":[-117.299937,34.160623],"type":"Point"}
}