{
  "type": "Feature",
  "properties": {
    "addr:full":"2319 E Cesar E Chavez Ave Los Angeles CA 90033",
    "addr:housenumber":"2319",
    "addr:postcode":"90033",
    "addr:street":"E Cesar E Chavez Ave",
    "iso:country":"US",
    "sg:address":"2319 E Cesar E Chavez Ave",
    "sg:city":"Los Angeles",
    "sg:classifiers":[
        {
            "category":"Restaurant",
            "type":"Food & Drink"
        }
    ],
    "sg:phone":"+1 323 264 0041",
    "sg:postcode":"90033",
    "sg:province":"CA",
    "wof:name":"Pollo Bravo",
    "wof:placetype":"venue"
},
  "geometry": {"coordinates":[-118.20790100000001,34.046949],"type":"Point"}
}