{
  "type": "Feature",
  "properties": {
    "addr:full":"270 Divisadero St San Francisco CA 94117",
    "addr:housenumber":"270",
    "addr:postcode":"94117",
    "addr:street":"Divisadero St",
    "iso:country":"US",
    "sg:address":"270 Divisadero St",
    "sg:city":"San Francisco",
    "sg:classifiers":[
        {
            "category":"Education",
            "subcategory":"Vocational School",
            "type":"Public Place"
        }
    ],
    "sg:phone":"+1 415 503 4480",
    "sg:postcode":"94117",
    "sg:province":"CA",
    "wof:name":"Haight Ashbury Food Program",
    "wof:placetype":"venue"
},
  "geometry": {"coordinates":[-122.437048,37.771832],"type":"Point"}
}