{
  "type": "Feature",
  "properties": {
    "addr:full":"3907 Park Dr El Dorado Hills CA 95762",
    "addr:housenumber":"3907",
    "addr:postcode":"95762",
    "addr:street":"Park Dr",
    "iso:country":"US",
    "sg:address":"3907 Park Dr",
    "sg:city":"El Dorado Hills",
    "sg:classifiers":[
        {
            "category":"Health Services",
            "subcategory":"Doctor",
            "type":"Services"
        }
    ],
    "sg:phone":"+1 916 939 2330",
    "sg:postcode":"95762",
    "sg:province":"CA",
    "sg:tags":[
        "dentist"
    ],
    "wof:name":"David R Datwyler DDS",
    "wof:placetype":"venue"
},
  "geometry": {"coordinates":[-121.073857,38.659789],"type":"Point"}
}