{
  "type": "Feature",
  "properties": {
    "addr:full":"1036 Ashby Ave Berkeley CA 94710",
    "addr:housenumber":"1036",
    "addr:postcode":"94710",
    "addr:street":"Ashby Ave",
    "iso:country":"US",
    "sg:address":"1036 Ashby Ave",
    "sg:city":"Berkeley",
    "sg:classifiers":[
        {
            "category":"Restaurant",
            "type":"Food & Drink"
        }
    ],
    "sg:phone":"+1 510 540 8990",
    "sg:postcode":"94710",
    "sg:province":"CA",
    "sg:tags":[
        "banquet",
        "rooms"
    ],
    "wof:name":"Trader Vic's Wholesale",
    "wof:placetype":"venue"
},
  "geometry": {"coordinates":[-122.287155,37.852016],"type":"Point"}
}