{
  "type": "Feature",
  "properties": {
    "addr:full":"1093 Marsh Rd Redwood City CA 94063",
    "addr:housenumber":"1093",
    "addr:postcode":"94063",
    "addr:street":"Marsh Rd",
    "iso:country":"US",
    "sg:address":"1093 Marsh Rd",
    "sg:city":"Redwood City",
    "sg:classifiers":[
        {
            "category":"Building & Trades",
            "subcategory":"Cleaning & Sanitation",
            "type":"Services"
        }
    ],
    "sg:phone":"+1 650 367 7972",
    "sg:postcode":"94063",
    "sg:province":"CA",
    "sg:tags":[
        "window"
    ],
    "wof:name":"Vista Window Cleaning",
    "wof:placetype":"venue"
},
  "geometry": {"coordinates":[-122.184968,37.479935],"type":"Point"}
}