{
  "type": "Feature",
  "properties": {
    "addr:full":"5637 N Pershing Ave Stockton CA 95207",
    "addr:housenumber":"5637",
    "addr:postcode":"95207",
    "addr:street":"N Pershing Ave",
    "iso:country":"US",
    "sg:address":"5637 N Pershing Ave",
    "sg:city":"Stockton",
    "sg:classifiers":[
        {
            "category":"Building & Trades",
            "subcategory":"Construction",
            "type":"Services"
        }
    ],
    "sg:phone":"+1 209 951 8490",
    "sg:postcode":"95207",
    "sg:province":"CA",
    "sg:tags":[
        "contractor"
    ],
    "wof:name":"Magnum One Builders",
    "wof:placetype":"venue"
},
  "geometry": {"coordinates":[-121.326103,37.999751],"type":"Point"}
}