{
  "type": "Feature",
  "properties": {
    "addr:full":"142 Wyoming St Pleasanton CA 94566",
    "addr:housenumber":"142",
    "addr:postcode":"94566",
    "addr:street":"Wyoming St",
    "iso:country":"US",
    "sg:address":"142 Wyoming St",
    "sg:city":"Pleasanton",
    "sg:classifiers":[
        {
            "category":"Retail",
            "subcategory":"Auto Repair",
            "type":"Services"
        }
    ],
    "sg:phone":"+1 925 462 8491",
    "sg:postcode":"94566",
    "sg:province":"CA",
    "sg:tags":[
        "body",
        "automobile",
        "painting"
    ],
    "wof:name":"Bernard & Bob's Classic Auto",
    "wof:placetype":"venue"
},
  "geometry": {"coordinates":[-121.8592,37.667248],"type":"Point"}
}