{
  "type": "Feature",
  "properties": {
    "iso:country":"US",
    "sg:address":"4667 Macarthur Blvd",
    "sg:city":"Newport Beach",
    "sg:classifiers":[
        {
            "category":"Professional",
            "type":"Services"
        }
    ],
    "sg:phone":"+1 949 756 8308",
    "sg:postcode":"92660",
    "sg:province":"CA",
    "wof:name":"Steve Mader",
    "wof:placetype":"venue"
},
  "geometry": {"coordinates":[-117.86463,33.669657],"type":"Point"}
}