{
  "type": "Feature",
  "properties": {
    "iso:country":"US",
    "sg:address":"6331 E Spring St",
    "sg:city":"Long Beach",
    "sg:classifiers":[
        {
            "category":"Shopping",
            "subcategory":"Gifts & Souvenirs",
            "type":"Retail Goods"
        }
    ],
    "sg:phone":"+1 562 429 0792",
    "sg:postcode":"90808",
    "sg:province":"CA",
    "sg:tags":[
        "stationery",
        "shop",
        "card"
    ],
    "wof:name":"Dick's Hallmark Shop",
    "wof:placetype":"venue"
},
  "geometry": {"coordinates":[-118.10900100000001,33.8106],"type":"Point"}
}