{
  "type": "Feature",
  "properties": {
    "addr:full":"2301 W Whittier Blvd La Habra CA 90631",
    "addr:housenumber":"2301",
    "addr:postcode":"90631",
    "addr:street":"W Whittier Blvd",
    "iso:country":"US",
    "sg:address":"2301 W Whittier Blvd",
    "sg:city":"La Habra",
    "sg:classifiers":[
        {
            "category":"Wholesale",
            "subcategory":"Home Furnishings",
            "type":"Manufacturing & Wholesale Goods"
        }
    ],
    "sg:phone":"+1 562 694 4255",
    "sg:postcode":"90631",
    "sg:province":"CA",
    "sg:tags":[
        "blind",
        "shade"
    ],
    "wof:name":"La Habra Screen & Shade",
    "wof:placetype":"venue"
},
  "geometry": {"coordinates":[-117.97199999999999,33.9398],"type":"Point"}
}