{
  "type": "Feature",
  "properties": {
    "addr:full":"739 12th St Oakland CA 94607",
    "addr:housenumber":"739",
    "addr:postcode":"94607",
    "addr:street":"12Th St",
    "iso:country":"US",
    "sg:address":"739 12th St",
    "sg:city":"Oakland",
    "sg:classifiers":[
        {
            "category":"Food & Beverages",
            "subcategory":"Liquor & Beverages",
            "type":"Retail Goods"
        }
    ],
    "sg:phone":"+1 510 844 0451",
    "sg:postcode":"94607",
    "sg:province":"CA",
    "sg:tags":[
        "store"
    ],
    "wof:name":"Jackson Liq",
    "wof:placetype":"venue"
},
  "geometry": {"coordinates":[-122.279691,37.805923],"type":"Point"}
}