{
  "type": "Feature",
  "properties": {
    "addr:full":"5375 E 2nd St Long Beach CA 90803",
    "addr:housenumber":"5375",
    "addr:postcode":"90803",
    "addr:street":"E 2Nd St",
    "iso:country":"US",
    "sg:address":"5375 E 2nd St",
    "sg:city":"Long Beach",
    "sg:classifiers":[
        {
            "category":"Building & Trades",
            "subcategory":"Construction",
            "type":"Services"
        }
    ],
    "sg:phone":"+1 562 438 7999",
    "sg:postcode":"90803",
    "sg:province":"CA",
    "sg:tags":[
        "asbestos",
        "removal"
    ],
    "sg:website":"www.tenaska.com",
    "wof:name":"Environmental Construction Grp",
    "wof:placetype":"venue"
},
  "geometry": {"coordinates":[-118.13018099999999,33.758266],"type":"Point"}
}