{
  "type": "Feature",
  "properties": {
    "addr:full":"4932 Lankershim Blvd North Hollywood CA 91601",
    "addr:housenumber":"4932",
    "addr:postcode":"91601",
    "addr:street":"Lankershim Blvd",
    "iso:country":"US",
    "sg:address":"4932 Lankershim Blvd",
    "sg:city":"North Hollywood",
    "sg:classifiers":[
        {
            "category":"Professional",
            "subcategory":"Business Services",
            "type":"Services"
        }
    ],
    "sg:phone":"+1 818 508 6221",
    "sg:postcode":"91601",
    "sg:province":"CA",
    "sg:tags":[
        "recording",
        "rehearsal",
        "studio"
    ],
    "sg:website":"www.qpsound.com",
    "wof:name":"Q P Sound",
    "wof:placetype":"venue"
},
  "geometry": {"coordinates":[-118.37200199999999,34.160599],"type":"Point"}
}