{
  "type": "Feature",
  "properties": {
    "addr:full":"594 Almaden Walk Loop San Jose CA 95125",
    "addr:housenumber":"594",
    "addr:postcode":"95125",
    "addr:street":"Almaden Walk Loop",
    "iso:country":"US",
    "sg:address":"594 Almaden Walk Loop",
    "sg:city":"San Jose",
    "sg:classifiers":[
        {
            "category":"Autos & Motor Vehicles",
            "subcategory":"Fuel & Gas Station",
            "type":"Retail Goods"
        }
    ],
    "sg:phone":"+1 408 440 0095",
    "sg:postcode":"95125",
    "sg:province":"CA",
    "wof:name":"The Olson Company",
    "wof:placetype":"venue"
},
  "geometry": {"coordinates":[-121.879947,37.298124],"type":"Point"}
}