{
  "type": "Feature",
  "properties": {
    "iso:country":"US",
    "sg:address":"25 D St",
    "sg:city":"Chula Vista",
    "sg:classifiers":[
        {
            "category":"Building & Trades",
            "subcategory":"Landscaping Services",
            "type":"Services"
        }
    ],
    "sg:phone":"+1 619 426 0565",
    "sg:postcode":"91910",
    "sg:province":"CA",
    "sg:tags":[
        "landscape",
        "contractor"
    ],
    "wof:name":"Landscape Enterprises",
    "wof:placetype":"venue"
},
  "geometry": {"coordinates":[-117.071012,32.651542],"type":"Point"}
}