{
  "type": "Feature",
  "properties": {
    "addr:full":"1253 Lohrman Ln Petaluma CA 94952",
    "addr:housenumber":"1253",
    "addr:postcode":"94952",
    "addr:street":"Lohrman Ln",
    "iso:country":"US",
    "sg:address":"1253 Lohrman Ln",
    "sg:city":"Petaluma",
    "sg:classifiers":[
        {
            "category":"Wholesale",
            "subcategory":"Non-durable Goods",
            "type":"Manufacturing & Wholesale Goods"
        }
    ],
    "sg:phone":"+1 707 762 0215",
    "sg:postcode":"94952",
    "sg:province":"CA",
    "sg:tags":[
        "bag",
        "canvas",
        "cotton"
    ],
    "wof:name":"Lutz Bag Co",
    "wof:placetype":"venue"
},
  "geometry": {"coordinates":[-122.67016599999999,38.246199],"type":"Point"}
}