{
  "type": "Feature",
  "properties": {
    "iso:country":"US",
    "sg:address":"3537 Martin Luther King Jr Blvd",
    "sg:city":"Lynwood",
    "sg:classifiers":[
        {
            "category":"Fast Food",
            "type":"Food & Drink"
        }
    ],
    "sg:phone":"+1 323 213 2063",
    "sg:postcode":"90262",
    "sg:province":"CA",
    "sg:tags":[
        "chicken",
        "wing"
    ],
    "wof:name":"ROTISSERIE CHICKEN CAFE",
    "wof:placetype":"venue"
},
  "geometry": {"coordinates":[-118.207307,33.93633],"type":"Point"}
}