{
  "type": "Feature",
  "properties": {
    "iso:country":"US",
    "sg:address":"505 S Villa Real",
    "sg:city":"Anaheim",
    "sg:classifiers":[
        {
            "category":"Banks & Credit Unions",
            "subcategory":"Bank",
            "type":"Services"
        }
    ],
    "sg:phone":"+1 714 685 3366",
    "sg:postcode":"92807",
    "sg:province":"CA",
    "sg:tags":[
        "loan",
        "real estate"
    ],
    "sg:website":"www.scmeonline.com",
    "wof:name":"SCME Mortgage Bankers",
    "wof:placetype":"venue"
},
  "geometry": {"coordinates":[-117.822003,33.837302],"type":"Point"}
}