{
  "type": "Feature",
  "properties": {
    "iso:country":"US",
    "sg:address":"22016 Avalon Blvd",
    "sg:city":"Carson",
    "sg:classifiers":[
        {
            "category":"Personal",
            "subcategory":"Beauty Salon",
            "type":"Services"
        }
    ],
    "sg:phone":"+1 310 549 5506",
    "sg:postcode":"90745",
    "sg:province":"CA",
    "wof:name":"Sheer Elegance",
    "wof:placetype":"venue"
},
  "geometry": {"coordinates":[-118.263603,33.827656],"type":"Point"}
}