{
  "type": "Feature",
  "properties": {
    "iso:country":"US",
    "sg:address":"3366 W Pomona Blvd",
    "sg:city":"Pomona",
    "sg:classifiers":[
        {
            "category":"Manufacturing",
            "subcategory":"Textiles",
            "type":"Manufacturing & Wholesale Goods"
        }
    ],
    "sg:phone":"+1 909 598 1112",
    "sg:postcode":"91768",
    "sg:province":"CA",
    "sg:tags":[
        "mill",
        "piece",
        "fabric"
    ],
    "wof:name":"Orchid Art Flower Inc",
    "wof:placetype":"venue"
},
  "geometry": {"coordinates":[-117.809697,34.04794],"type":"Point"}
}