{
  "type": "Feature",
  "properties": {
    "iso:country":"US",
    "sg:address":"1841 23rd St",
    "sg:city":"San Pablo",
    "sg:classifiers":[
        {
            "category":"Restaurant",
            "type":"Food & Drink"
        }
    ],
    "sg:phone":"+1 510 235 4669",
    "sg:postcode":"94806",
    "sg:province":"CA",
    "sg:tags":[
        "eating"
    ],
    "wof:name":"China Express Restaurant",
    "wof:placetype":"venue"
},
  "geometry": {"coordinates":[-122.347032,37.958589],"type":"Point"}
}