{
  "type": "Feature",
  "properties": {
    "addr:full":"761 W Lambert Rd Brea CA 92821",
    "addr:housenumber":"761",
    "addr:postcode":"92821",
    "addr:street":"W Lambert Rd",
    "iso:country":"US",
    "sg:address":"761 W Lambert Rd",
    "sg:city":"Brea",
    "sg:classifiers":[
        {
            "category":"Shopping",
            "subcategory":"Stationery & Office Supplies",
            "type":"Retail Goods"
        },
        {
            "category":"Manufacturing",
            "subcategory":"Paper Products",
            "type":"Manufacturing & Wholesale Goods"
        }
    ],
    "sg:phone":"+1 714 529 5571",
    "sg:postcode":"92821",
    "sg:province":"CA",
    "sg:tags":[
        "stationery-wholesale",
        "store",
        "manufacturer"
    ],
    "wof:name":"Narsad Artworks",
    "wof:placetype":"venue"
},
  "geometry": {"coordinates":[-117.909032,33.924635],"type":"Point"}
}