{
  "type": "Feature",
  "properties": {
    "addr:full":"2041 Factory St Richmond CA 94801",
    "addr:housenumber":"2041",
    "addr:postcode":"94801",
    "addr:street":"Factory St",
    "iso:country":"US",
    "sg:address":"2041 Factory St",
    "sg:city":"Richmond",
    "sg:classifiers":[
        {
            "category":"Wholesale",
            "subcategory":"Meat",
            "type":"Manufacturing & Wholesale Goods"
        },
        {
            "category":"Food & Beverages",
            "subcategory":"Meat & Fish",
            "type":"Retail Goods"
        }
    ],
    "sg:phone":"+1 510 233 5113",
    "sg:postcode":"94801",
    "sg:province":"CA",
    "sg:tags":[
        "meat-wholesale",
        "packer",
        "market"
    ],
    "sg:website":"http://www.rwm.biz",
    "wof:name":"Richmond Wholesale Meat Co.",
    "wof:placetype":"venue"
},
  "geometry": {"coordinates":[-122.368888,37.947001],"type":"Point"}
}