{
  "type": "Feature",
  "properties": {
    "iso:country":"US",
    "sg:address":"32461 State Rte 20",
    "sg:city":"Fort Bragg",
    "sg:classifiers":[
        {
            "category":"Home & Garden",
            "subcategory":"Garden Supply",
            "type":"Retail Goods"
        }
    ],
    "sg:phone":"+1 707 964 4648",
    "sg:postcode":"95437",
    "sg:province":"CA",
    "sg:tags":[
        "nurseryman"
    ],
    "wof:name":"Hare Creek Nursery",
    "wof:placetype":"venue"
},
  "geometry": {"coordinates":[-123.797687,39.418932],"type":"Point"}
}