{
  "type": "Feature",
  "properties": {
    "addr:full":"6910 E Mckenzie Ave Fresno CA 93727",
    "addr:housenumber":"6910",
    "addr:postcode":"93727",
    "addr:street":"E Mckenzie Ave",
    "iso:country":"US",
    "sg:address":"6910 E Mckenzie Ave",
    "sg:city":"Fresno",
    "sg:classifiers":[
        {
            "category":"Building & Trades",
            "subcategory":"Landscaping Services",
            "type":"Services"
        }
    ],
    "sg:phone":"+1 559 341 7821",
    "sg:postcode":"93727",
    "sg:province":"CA",
    "sg:tags":[
        "lawn",
        "maintenance"
    ],
    "wof:name":"Almanza Lawn Service",
    "wof:placetype":"venue"
},
  "geometry": {"coordinates":[-119.664725,36.746987],"type":"Point"}
}