{
  "type": "Feature",
  "properties": {
    "addr:full":"1727 Main St Fortuna CA 95540",
    "addr:housenumber":"1727",
    "addr:postcode":"95540",
    "addr:street":"Main St",
    "iso:country":"US",
    "sg:address":"1727 Main St",
    "sg:city":"Fortuna",
    "sg:classifiers":[
        {
            "category":"Personal",
            "subcategory":"Beauty Salon",
            "type":"Services"
        }
    ],
    "sg:phone":"+1 707 726 9394",
    "sg:postcode":"95540",
    "sg:province":"CA",
    "wof:name":"Top Coat Nails Hair & More",
    "wof:placetype":"venue"
},
  "geometry": {"coordinates":[-124.14784299999999,40.597495],"type":"Point"}
}