{
  "type": "Feature",
  "properties": {
    "addr:full":"20 E Main St Apt 9 Los Gatos CA 95030",
    "addr:housenumber":"20",
    "addr:postcode":"95030",
    "addr:street":"E Main St Apt 9",
    "iso:country":"US",
    "sg:address":"20 E Main St Apt 9",
    "sg:city":"Los Gatos",
    "sg:classifiers":[
        {
            "category":"Real Estate",
            "subcategory":"Real Estate Operator",
            "type":"Services"
        }
    ],
    "sg:phone":"+1 408 354 3141",
    "sg:postcode":"95030",
    "sg:province":"CA",
    "sg:tags":[
        "apartment"
    ],
    "sg:website":"www.vasonamanagement.com",
    "wof:name":"El Gato Penthouse",
    "wof:placetype":"venue"
},
  "geometry": {"coordinates":[-121.98200199999999,37.221298],"type":"Point"}
}