{
  "type": "Feature",
  "properties": {
    "iso:country":"US",
    "sg:address":"275 E Douglas Ave Ste 102",
    "sg:city":"El Cajon",
    "sg:classifiers":[
        {
            "category":"Banks & Credit Unions",
            "subcategory":"Atm",
            "type":"Services"
        }
    ],
    "sg:phone":"+1 619 442 1114",
    "sg:postcode":"92020",
    "sg:province":"CA",
    "sg:tags":[
        "bankruptcy"
    ],
    "wof:name":"Attorney Randal C Leavitt",
    "wof:placetype":"venue"
},
  "geometry": {"coordinates":[-116.959,32.7938],"type":"Point"}
}