{
  "type": "Feature",
  "properties": {
    "addr:full":"2150 Main St Ste 6 Cambria CA 93428",
    "addr:housenumber":"2150",
    "addr:postcode":"93428",
    "addr:street":"Main St Ste 6",
    "iso:country":"US",
    "sg:address":"2150 Main St Ste 6",
    "sg:city":"Cambria",
    "sg:classifiers":[
        {
            "category":"Personal",
            "subcategory":"Skin Care",
            "type":"Services"
        },
        {
            "category":"Personal",
            "subcategory":"Day Spa",
            "type":"Services"
        }
    ],
    "sg:phone":"+1 805 927 5422",
    "sg:postcode":"93428",
    "sg:province":"CA",
    "wof:name":"Skin Care of Cambria",
    "wof:placetype":"venue"
},
  "geometry": {"coordinates":[-121.083393,35.563353],"type":"Point"}
}