{
  "type": "Feature",
  "properties": {
    "iso:country":"US",
    "sg:address":"1051 University Ave",
    "sg:city":"San Diego",
    "sg:classifiers":[
        {
            "category":"Bars & Pubs",
            "type":"Food & Drink"
        }
    ],
    "sg:phone":"+1 619 295 2195",
    "sg:postcode":"92103",
    "sg:province":"CA",
    "sg:tags":[
        "dance",
        "club",
        "night"
    ],
    "sg:website":"www.richssandiego.com/",
    "wof:name":"Rich's",
    "wof:placetype":"venue"
},
  "geometry": {"coordinates":[-117.154051,32.748398],"type":"Point"}
}