{
  "type": "Feature",
  "properties": {
    "iso:country":"US",
    "sg:address":"1409 E Cambridge Ave",
    "sg:city":"Fresno",
    "sg:classifiers":[
        {
            "category":"Real Estate",
            "subcategory":"Real Estate Operator",
            "type":"Services"
        }
    ],
    "sg:phone":"+1 661 872 2396",
    "sg:postcode":"93704",
    "sg:province":"CA",
    "sg:tags":[
        "apartment"
    ],
    "wof:name":"Kopper Rentals",
    "wof:placetype":"venue"
},
  "geometry": {"coordinates":[-119.79343900000001,36.769608],"type":"Point"}
}