{
  "type": "Feature",
  "properties": {
    "iso:country":"US",
    "sg:address":"903 San Ramon Valley Blvd",
    "sg:city":"Danville",
    "sg:classifiers":[
        {
            "category":"Health Services",
            "subcategory":"Doctor",
            "type":"Services"
        }
    ],
    "sg:phone":"+1 925 831 9217",
    "sg:postcode":"94526",
    "sg:province":"CA",
    "sg:tags":[
        "dentist"
    ],
    "wof:name":"Kain Farzaneh DDS Oral",
    "wof:placetype":"venue"
},
  "geometry": {"coordinates":[-121.991939,37.807611],"type":"Point"}
}