{
  "type": "Feature",
  "properties": {
    "iso:country":"US",
    "sg:address":"3233 Santa Rosa Ave",
    "sg:city":"Santa Rosa",
    "sg:classifiers":[
        {
            "category":"Retail",
            "subcategory":"Car Wash",
            "type":"Services"
        }
    ],
    "sg:phone":"+1 707 526 9268",
    "sg:postcode":"95407",
    "sg:province":"CA",
    "sg:tags":[
        "automobile",
        "detail",
        "clean"
    ],
    "wof:name":"American Auto Detailing",
    "wof:placetype":"venue"
},
  "geometry": {"coordinates":[-122.713575,38.397874],"type":"Point"}
}