{
  "type": "Feature",
  "properties": {
    "iso:country":"US",
    "sg:address":"27800 Medical Center Rd Ste 324",
    "sg:city":"Mission Viejo",
    "sg:classifiers":[
        {
            "category":"Health Services",
            "subcategory":"Doctor",
            "type":"Services"
        }
    ],
    "sg:phone":"+1 949 364 4361",
    "sg:postcode":"92691",
    "sg:province":"CA",
    "sg:tags":[
        "throat",
        "ear",
        "nose"
    ],
    "wof:name":"Orange County Physicians Hearing Associates",
    "wof:placetype":"venue"
},
  "geometry": {"coordinates":[-117.66799899999999,33.611198],"type":"Point"}
}