{
  "type": "Feature",
  "properties": {
    "iso:country":"US",
    "sg:address":"699 S C St",
    "sg:city":"Oxnard",
    "sg:classifiers":[
        {
            "category":"Personal",
            "subcategory":"Beauty Salon",
            "type":"Services"
        }
    ],
    "sg:phone":"+1 805 483 4994",
    "sg:postcode":"93030",
    "sg:province":"CA",
    "sg:tags":[
        "school"
    ],
    "wof:name":"Modern Beauty Academy",
    "wof:placetype":"venue"
},
  "geometry": {"coordinates":[-119.181116,34.196379],"type":"Point"}
}