{
  "type": "Feature",
  "properties": {
    "iso:country":"US",
    "sg:address":"2500 Hospital Dr",
    "sg:city":"Mountain View",
    "sg:classifiers":[
        {
            "category":"Building & Trades",
            "subcategory":"Construction",
            "type":"Services"
        }
    ],
    "sg:phone":"+1 650 968 8452",
    "sg:postcode":"94040",
    "sg:province":"CA",
    "sg:tags":[
        "painter"
    ],
    "wof:name":"Sunshine Painting",
    "wof:placetype":"venue"
},
  "geometry": {"coordinates":[-122.08199500000001,37.36871],"type":"Point"}
}