{
  "type": "Feature",
  "properties": {
    "addr:full":"6523 Pacific Blvd Huntington Park CA 90255",
    "addr:housenumber":"6523",
    "addr:postcode":"90255",
    "addr:street":"Pacific Blvd;Park",
    "iso:country":"US",
    "sg:address":"6523 Pacific Blvd",
    "sg:city":"Huntington Park",
    "sg:classifiers":[
        {
            "category":"Shopping",
            "subcategory":"Clothing, Apparel, & Fashions",
            "type":"Retail Goods"
        }
    ],
    "sg:phone":"+1 323 587 4140",
    "sg:postcode":"90255",
    "sg:province":"CA",
    "sg:tags":[
        "furnishing"
    ],
    "wof:name":"LA Mexicana",
    "wof:placetype":"venue"
},
  "geometry": {"coordinates":[-118.22525,33.980733],"type":"Point"}
}