{
  "type": "Feature",
  "properties": {
    "addr:full":"6504 Kaiser Dr Fremont CA 94555",
    "addr:housenumber":"6504",
    "addr:postcode":"94555",
    "addr:street":"Kaiser Dr",
    "iso:country":"US",
    "sg:address":"6504 Kaiser Dr",
    "sg:city":"Fremont",
    "sg:classifiers":[
        {
            "category":"Building & Trades",
            "subcategory":"Landscaping Services",
            "type":"Services"
        }
    ],
    "sg:phone":"+1 510 713 7770",
    "sg:postcode":"94555",
    "sg:province":"CA",
    "sg:tags":[
        "landscape",
        "contractor"
    ],
    "wof:name":"Trinity Landscape",
    "wof:placetype":"venue"
},
  "geometry": {"coordinates":[-122.067398,37.549227],"type":"Point"}
}