{
  "type": "Feature",
  "properties": {
    "iso:country":"US",
    "sg:address":"5567 Auckland Ave",
    "sg:city":"North Hollywood",
    "sg:classifiers":[
        {
            "category":"Wholesale",
            "subcategory":"Electrical",
            "type":"Manufacturing & Wholesale Goods"
        }
    ],
    "sg:phone":"+1 818 623 8190",
    "sg:postcode":"91601",
    "sg:province":"CA",
    "sg:tags":[
        "video",
        "disc",
        "tape"
    ],
    "wof:name":"Marina Pacific Corp",
    "wof:placetype":"venue"
},
  "geometry": {"coordinates":[-118.360536,34.170699],"type":"Point"}
}