{
  "type": "Feature",
  "properties": {
    "addr:full":"32757 Rd 160 Ivanhoe CA 93235",
    "addr:postcode":"32757;93235",
    "addr:street":"Rd 160",
    "iso:country":"US",
    "sg:address":"32757 Rd 160",
    "sg:city":"Ivanhoe",
    "sg:classifiers":[
        {
            "category":"Utilities",
            "subcategory":"Refuse",
            "type":"Services"
        }
    ],
    "sg:phone":"+1 559 798 4535",
    "sg:postcode":"93235",
    "sg:province":"CA",
    "sg:tags":[
        "system"
    ],
    "wof:name":"Recycle 4 Cash",
    "wof:placetype":"venue"
},
  "geometry": {"coordinates":[-119.215626,36.384519],"type":"Point"}
}