{
  "type": "Feature",
  "properties": {
    "addr:full":"9864 Dino Dr Elk Grove CA 95624",
    "addr:housenumber":"9864",
    "addr:postcode":"95624",
    "addr:street":"Dino Dr",
    "iso:country":"US",
    "sg:address":"9864 Dino Dr",
    "sg:city":"Elk Grove",
    "sg:classifiers":[
        {
            "category":"Manufacturing",
            "subcategory":"Printing",
            "type":"Manufacturing & Wholesale Goods"
        }
    ],
    "sg:phone":"+1 916 686 4404",
    "sg:postcode":"95624",
    "sg:province":"CA",
    "sg:tags":[
        "commercial"
    ],
    "wof:name":"Anderson Robinson & Associates",
    "wof:placetype":"venue"
},
  "geometry": {"coordinates":[-121.35692,38.40126],"type":"Point"}
}