{
  "type": "Feature",
  "properties": {
    "addr:full":"3601 Prescott Rd Modesto CA 95356",
    "addr:housenumber":"3601",
    "addr:postcode":"ca 95356",
    "addr:street":"Prescott Rd",
    "iso:country":"US",
    "sg:address":"3601 Prescott Rd",
    "sg:city":"Modesto",
    "sg:classifiers":[
        {
            "category":"Real Estate",
            "subcategory":"Real Estate Operator",
            "type":"Services"
        }
    ],
    "sg:phone":"+1 209 575 0276",
    "sg:postcode":"95356",
    "sg:province":"CA",
    "sg:tags":[
        "apartment"
    ],
    "wof:name":"Summerview Place",
    "wof:placetype":"venue"
},
  "geometry": {"coordinates":[-121.031553,37.691148],"type":"Point"}
}