{
  "type": "Feature",
  "properties": {
    "addr:full":"1617 S Cedar Ave Fresno CA 93702",
    "addr:housenumber":"1617",
    "addr:postcode":"93702",
    "addr:street":"S Cedar Ave",
    "iso:country":"US",
    "sg:address":"1617 S Cedar Ave",
    "sg:city":"Fresno",
    "sg:classifiers":[
        {
            "category":"Government",
            "subcategory":"Police Station",
            "type":"Public Place"
        }
    ],
    "sg:phone":"+1 559 621 6300",
    "sg:postcode":"93702",
    "sg:province":"CA",
    "sg:tags":[
        "department"
    ],
    "wof:name":"Fresno Police Dept",
    "wof:placetype":"venue"
},
  "geometry": {"coordinates":[-119.75457,36.727914],"type":"Point"}
}