{
  "type": "Feature",
  "properties": {
    "addr:full":"4773 Mountain Lakes Blvd Redding CA 96003",
    "addr:housenumber":"4773",
    "addr:postcode":"96003",
    "addr:street":"Mountain Lakes Blvd",
    "iso:country":"US",
    "sg:address":"4773 Mountain Lakes Blvd",
    "sg:city":"Redding",
    "sg:classifiers":[
        {
            "category":"Wholesale",
            "subcategory":"Electrical",
            "type":"Manufacturing & Wholesale Goods"
        }
    ],
    "sg:phone":"+1 530 241 7145",
    "sg:postcode":"96003",
    "sg:province":"CA",
    "sg:tags":[
        "electric",
        "motor"
    ],
    "wof:name":"Nor Cal Motor Rewinding",
    "wof:placetype":"venue"
},
  "geometry": {"coordinates":[-122.37697799999999,40.629895],"type":"Point"}
}