{
  "type": "Feature",
  "properties": {
    "addr:full":"655 Kennedy St Oakland CA 94606",
    "addr:housenumber":"655",
    "addr:postcode":"94606",
    "addr:street":"Kennedy St",
    "iso:country":"US",
    "sg:address":"655 Kennedy St",
    "sg:city":"Oakland",
    "sg:classifiers":[
        {
            "category":"Manufacturing",
            "subcategory":"Paper Products",
            "type":"Manufacturing & Wholesale Goods"
        }
    ],
    "sg:phone":"+1 510 534 1841",
    "sg:postcode":"94606",
    "sg:province":"CA",
    "wof:name":"Empire Paper Corp.",
    "wof:placetype":"venue"
},
  "geometry": {"coordinates":[-122.23757000000001,37.776503],"type":"Point"}
}