{
  "type": "Feature",
  "properties": {
    "addr:full":"901 Bay Shore Blvd San Francisco CA 94124",
    "addr:housenumber":"901",
    "addr:postcode":"94124",
    "addr:street":"Bay Shore Blvd",
    "iso:country":"US",
    "sg:address":"901 Bay Shore Blvd",
    "sg:city":"San Francisco",
    "sg:classifiers":[
        {
            "category":"Real Estate",
            "subcategory":"Real Estate Operator",
            "type":"Services"
        }
    ],
    "sg:phone":"+1 415 468 2152",
    "sg:postcode":"94124",
    "sg:province":"CA",
    "sg:tags":[
        "apartment"
    ],
    "wof:name":"San Francisco Native Builders",
    "wof:placetype":"venue"
},
  "geometry": {"coordinates":[-122.404212,37.732633],"type":"Point"}
}