{
  "type": "Feature",
  "properties": {
    "iso:country":"US",
    "sg:address":"1780 Placentia Ave Apt 20",
    "sg:city":"Costa Mesa",
    "sg:classifiers":[
        {
            "category":"Real Estate",
            "subcategory":"Real Estate Operator",
            "type":"Services"
        }
    ],
    "sg:phone":"+1 949 642 3790",
    "sg:postcode":"92627",
    "sg:province":"CA",
    "sg:tags":[
        "apartment"
    ],
    "wof:name":"Daisy Apartments the",
    "wof:placetype":"venue"
},
  "geometry": {"coordinates":[-117.931999,33.639],"type":"Point"}
}