{
  "type": "Feature",
  "properties": {
    "addr:full":"9367 Mountain Meadow Rd Shingletown CA 96088",
    "addr:housenumber":"9367",
    "addr:postcode":"96088",
    "addr:street":"Mountain Meadow Rd",
    "iso:country":"US",
    "sg:address":"9367 Mountain Meadow Rd",
    "sg:city":"Shingletown",
    "sg:classifiers":[
        {
            "category":"Utilities",
            "subcategory":"Water",
            "type":"Services"
        }
    ],
    "sg:phone":"+1 530 474 5120",
    "sg:postcode":"96088",
    "sg:province":"CA",
    "sg:tags":[
        "supply"
    ],
    "wof:name":"Lassen Pines Mutual Water Co",
    "wof:placetype":"venue"
},
  "geometry": {"coordinates":[-121.71544900000001,40.565909],"type":"Point"}
}