{
  "type": "Feature",
  "properties": {
    "addr:full":"901 Montague St San Leandro CA 94577",
    "addr:housenumber":"901",
    "addr:postcode":"94577",
    "addr:street":"Montague St",
    "iso:country":"US",
    "sg:address":"901 Montague St",
    "sg:city":"San Leandro",
    "sg:classifiers":[
        {
            "category":"Manufacturing",
            "subcategory":"Tools & Machinery",
            "type":"Manufacturing & Wholesale Goods"
        }
    ],
    "sg:phone":"+1 510 352 7600",
    "sg:postcode":"94577",
    "sg:province":"CA",
    "sg:tags":[
        "die",
        "cutting"
    ],
    "wof:name":"Alameda Die Cutting",
    "wof:placetype":"venue"
},
  "geometry": {"coordinates":[-122.159373,37.709671],"type":"Point"}
}