{
  "type": "Feature",
  "properties": {
    "addr:full":"824 Ellis Street San Francisco CA 94109",
    "addr:housenumber":"824",
    "addr:postcode":"94109",
    "addr:street":"Ellis Street",
    "iso:country":"US",
    "sg:address":"824 Ellis Street",
    "sg:city":"San Francisco",
    "sg:classifiers":[
        {
            "category":"Retail",
            "subcategory":"Auto Repair",
            "type":"Services"
        },
        {
            "category":"Government",
            "subcategory":"Office",
            "type":"Public Place"
        }
    ],
    "sg:phone":"+1 415 292 4840",
    "sg:postcode":"94109",
    "sg:province":"CA",
    "sg:tags":[
        "smog",
        "check"
    ],
    "sg:website":"www.sfautosport.com",
    "wof:name":"Ac Bmw-Mercedes-Saab-Jaguar Specialist",
    "wof:placetype":"venue"
},
  "geometry": {"coordinates":[-122.41999800000001,37.7841],"type":"Point"}
}