{
  "type": "Feature",
  "properties": {
    "iso:country":"US",
    "sg:address":"300 Calrsbad Village Dr",
    "sg:city":"Carlsbad",
    "sg:classifiers":[
        {
            "category":"Shopping Center",
            "type":"Public Place"
        }
    ],
    "sg:phone":"+1 805 965 1616",
    "sg:postcode":"92013",
    "sg:province":"CA",
    "sg:website":"www.shopvillagefaire.com",
    "wof:name":"Carlsbad Village Faire",
    "wof:placetype":"venue"
},
  "geometry": {"coordinates":[-117.351021,33.158283],"type":"Point"}
}