{
  "type": "Feature",
  "properties": {
    "iso:country":"US",
    "sg:address":"174 S O St",
    "sg:city":"Lincoln",
    "sg:phone":"+1 866 435 4962",
    "sg:postcode":"95648",
    "sg:province":"CA",
    "sg:website":"http://www.forrent.com/apartment-community-profile/1007386.php?cmp=CAC-CSearchProfile",
    "wof:name":"Auburn Creek Apts.",
    "wof:placetype":"venue"
},
  "geometry": {"coordinates":[-121.30290599999999,38.884479],"type":"Point"}
}