{
  "type": "Feature",
  "properties": {
    "iso:country":"US",
    "sg:address":"11400 N Ventura Ave",
    "sg:city":"Ojai",
    "sg:classifiers":[
        {
            "category":"Health Services",
            "subcategory":"Chiropractor",
            "type":"Services"
        }
    ],
    "sg:phone":"+1 805 649 9994",
    "sg:postcode":"93023",
    "sg:province":"CA",
    "wof:name":"Mid Valley Chiropractic",
    "wof:placetype":"venue"
},
  "geometry": {"coordinates":[-119.289185,34.424288],"type":"Point"}
}