{
  "type": "Feature",
  "properties": {
    "addr:full":"PO Box 92524 Long Beach CA 90809",
    "addr:housenumber":"po box 92524",
    "addr:postcode":"90809",
    "iso:country":"US",
    "sg:address":"PO Box 92524",
    "sg:city":"Long Beach",
    "sg:classifiers":[
        {
            "category":"Arts & Performance",
            "subcategory":"Arts Center",
            "type":"Entertainment"
        }
    ],
    "sg:phone":"+1 562 439 6919",
    "sg:postcode":"90809",
    "sg:province":"CA",
    "sg:tags":[
        "performing"
    ],
    "sg:website":"www.sccsingers.com",
    "wof:name":"South Coast Chorale",
    "wof:placetype":"venue"
},
  "geometry": {"coordinates":[-118.15100099999999,33.799099],"type":"Point"}
}