{
  "type": "Feature",
  "properties": {
    "iso:country":"US",
    "sg:address":"12450 Magnolia Blvd",
    "sg:city":"Valley Village",
    "sg:classifiers":[
        {
            "category":"Government",
            "subcategory":"Post Office",
            "type":"Public Place"
        }
    ],
    "sg:phone":"+1 818 762 4727",
    "sg:postcode":"91607",
    "sg:province":"CA",
    "wof:name":"Valley Village Station",
    "wof:placetype":"venue"
},
  "geometry": {"coordinates":[-118.404979,34.164796],"type":"Point"}
}