{
  "type": "Feature",
  "properties": {
    "iso:country":"US",
    "sg:address":"8204 E Oak Ridge Cir",
    "sg:city":"Anaheim",
    "sg:classifiers":[
        {
            "category":"Travel",
            "subcategory":"Travel Agent",
            "type":"Entertainment"
        }
    ],
    "sg:phone":"+1 714 282 2639",
    "sg:postcode":"92808",
    "sg:province":"CA",
    "sg:tags":[
        "operator",
        "tour"
    ],
    "wof:name":"Childrens Theatre Tour",
    "wof:placetype":"venue"
},
  "geometry": {"coordinates":[-117.737611,33.86282],"type":"Point"}
}