{
  "type": "Feature",
  "properties": {
    "iso:country":"US",
    "sg:address":"465 Fairchild Dr  Suite 130",
    "sg:city":"Mountain View",
    "sg:classifiers":[
        {
            "category":"Professional",
            "subcategory":"Computer Services",
            "type":"Services"
        }
    ],
    "sg:phone":"+1 650 351 6444",
    "sg:postcode":"94043",
    "sg:province":"CA",
    "sg:tags":[
        "interoperability",
        "interoperable",
        "communication",
        "software",
        "government",
        "contractor",
        "emergency-responders",
        "p25"
    ],
    "sg:website":"http://www.covialabs.com",
    "wof:name":"Covia Labs",
    "wof:placetype":"venue"
},
  "geometry": {"coordinates":[-122.0526,37.403737],"type":"Point"}
}