{
  "type": "Feature",
  "properties": {
    "addr:full":"14866 Cresent Dr Magalia CA 95954",
    "addr:housenumber":"14866",
    "addr:postcode":"95954",
    "addr:street":"Cresent Dr",
    "iso:country":"US",
    "sg:address":"14866 Cresent Dr",
    "sg:city":"Magalia",
    "sg:classifiers":[
        {
            "category":"Wholesale",
            "subcategory":"Construction Materials",
            "type":"Manufacturing & Wholesale Goods"
        },
        {
            "category":"Home & Garden",
            "subcategory":"Building Materials",
            "type":"Retail Goods"
        }
    ],
    "sg:phone":"+1 530 873 2500",
    "sg:postcode":"95954",
    "sg:province":"CA",
    "sg:tags":[
        "screen",
        "window"
    ],
    "wof:name":"Screenmobile The",
    "wof:placetype":"venue"
},
  "geometry": {"coordinates":[-121.597037,39.849096],"type":"Point"}
}