{
  "type": "Feature",
  "properties": {
    "iso:country":"US",
    "sg:address":"1008 Brioso Dr",
    "sg:city":"Costa Mesa",
    "sg:classifiers":[
        {
            "category":"Manufacturing",
            "subcategory":"Apparel",
            "type":"Manufacturing & Wholesale Goods"
        }
    ],
    "sg:phone":"+1 949 548 9095",
    "sg:postcode":"92627",
    "sg:province":"CA",
    "sg:tags":[
        "clothing"
    ],
    "sg:website":"www.truegrit.com",
    "wof:name":"Calour Group",
    "wof:placetype":"venue"
},
  "geometry": {"coordinates":[-117.943142,33.638347],"type":"Point"}
}