{
  "type": "Feature",
  "properties": {
    "addr:full":"610 Beaver St Santa Rosa CA 95404",
    "addr:housenumber":"610",
    "addr:postcode":"ca 95404",
    "addr:street":"Beaver St",
    "iso:country":"US",
    "sg:address":"610 Beaver St",
    "sg:city":"Santa Rosa",
    "sg:classifiers":[
        {
            "category":"Real Estate",
            "subcategory":"Developer",
            "type":"Services"
        }
    ],
    "sg:phone":"+1 707 545 3113",
    "sg:postcode":"95404",
    "sg:province":"CA",
    "wof:name":"Bess Knuthson Properties",
    "wof:placetype":"venue"
},
  "geometry": {"coordinates":[-122.71222299999999,38.445398],"type":"Point"}
}