{
  "type": "Feature",
  "properties": {
    "addr:full":"2009 W Garvey Ave N West Covina CA 91790",
    "addr:housenumber":"2009",
    "addr:postcode":"91790",
    "addr:street":"W Garvey Ave N",
    "iso:country":"US",
    "sg:address":"2009 W Garvey Ave N",
    "sg:city":"West Covina",
    "sg:classifiers":[
        {
            "category":"Social Services",
            "subcategory":"Child Care",
            "type":"Services"
        }
    ],
    "sg:phone":"+1 626 962 6972",
    "sg:postcode":"91790",
    "sg:province":"CA",
    "sg:tags":[
        "kindergarten",
        "academic",
        "school"
    ],
    "wof:name":"West Covina Education Ctr",
    "wof:placetype":"venue"
},
  "geometry": {"coordinates":[-117.946353,34.072583],"type":"Point"}
}