{
  "type": "Feature",
  "properties": {
    "iso:country":"US",
    "sg:address":"5933 W Century Blvd",
    "sg:city":"Los Angeles",
    "sg:classifiers":[
        {
            "category":"Insurance",
            "subcategory":"Insurance Agent",
            "type":"Services"
        }
    ],
    "sg:phone":"+1 310 216 2528",
    "sg:postcode":"90045",
    "sg:province":"CA",
    "wof:name":"Paul J White Insurance Agncy",
    "wof:placetype":"venue"
},
  "geometry": {"coordinates":[-118.383919,33.945636],"type":"Point"}
}