{
  "type": "Feature",
  "properties": {
    "iso:country":"US",
    "sg:address":"6568 Bradford Ct",
    "sg:city":"Rancho Cucamonga",
    "sg:classifiers":[
        {
            "category":"Local Transit",
            "type":"Transportation"
        }
    ],
    "sg:phone":"+1 909 466 0845",
    "sg:postcode":"91701",
    "sg:province":"CA",
    "wof:name":"Morrisons & Associates",
    "wof:placetype":"venue"
},
  "geometry": {"coordinates":[-117.559262,34.135275],"type":"Point"}
}