{
  "type": "Feature",
  "properties": {
    "addr:full":"3279 Applegate Rd Atwater CA 95301",
    "addr:housenumber":"3279",
    "addr:postcode":"95301",
    "addr:street":"Applegate Rd",
    "iso:country":"US",
    "sg:address":"3279 Applegate Rd",
    "sg:city":"Atwater",
    "sg:classifiers":[
        {
            "category":"Insurance",
            "subcategory":"Hazard Insurance",
            "type":"Services"
        }
    ],
    "sg:phone":"+1 209 358 7566",
    "sg:postcode":"95301",
    "sg:province":"CA",
    "sg:tags":[
        "bond"
    ],
    "wof:name":"Leroy's Bail Bonds",
    "wof:placetype":"venue"
},
  "geometry": {"coordinates":[-120.614546,37.331325],"type":"Point"}
}