{
  "type": "Feature",
  "properties": {
    "iso:country":"US",
    "sg:address":"2197 Gravenstein Hwy S",
    "sg:city":"Sebastopol",
    "sg:classifiers":[
        {
            "category":"Professional",
            "type":"Services"
        }
    ],
    "sg:phone":"+1 707 824 0828",
    "sg:postcode":"95472",
    "sg:province":"CA",
    "wof:name":"Legends 2000 Inc",
    "wof:placetype":"venue"
},
  "geometry": {"coordinates":[-122.798727,38.379336],"type":"Point"}
}