{
  "type": "Feature",
  "properties": {
    "addr:full":"5450 S Slauson Ave Culver City CA 90230",
    "addr:housenumber":"5450",
    "addr:postcode":"90230",
    "addr:street":"S Slauson Ave",
    "iso:country":"US",
    "sg:address":"5450 S Slauson Ave",
    "sg:city":"Culver City",
    "sg:classifiers":[
        {
            "category":"Building & Trades",
            "subcategory":"Plumbing",
            "type":"Services"
        }
    ],
    "sg:phone":"+1 310 288 6472",
    "sg:postcode":"90230",
    "sg:province":"CA",
    "sg:tags":[
        "contractor"
    ],
    "wof:name":"Electro-Air Company",
    "wof:placetype":"venue"
},
  "geometry": {"coordinates":[-118.401421,33.989553],"type":"Point"}
}