{
  "type": "Feature",
  "properties": {
    "addr:full":"3110 Camino Del Rio South Suite 311 San Diego CA 92108",
    "addr:housenumber":"3110",
    "addr:postcode":"92108",
    "addr:street":"Camino Del Rio South Suite 311",
    "iso:country":"US",
    "sg:address":"3110 Camino Del Rio South Suite 311",
    "sg:city":"San Diego",
    "sg:classifiers":[
        {
            "category":"Banks & Credit Unions",
            "subcategory":"Financial Services",
            "type":"Services"
        }
    ],
    "sg:phone":"+1 619 298 5626",
    "sg:postcode":"92108",
    "sg:province":"CA",
    "sg:tags":[
        "broker",
        "mortgage"
    ],
    "sg:website":"www.sapphirerealty.tv",
    "wof:name":"Emerald Mortgage",
    "wof:placetype":"venue"
},
  "geometry": {"coordinates":[-117.125378,32.773276],"type":"Point"}
}