{
  "type": "Feature",
  "properties": {
    "addr:full":"3467 W Shaw Ave Fresno CA 93711",
    "addr:housenumber":"3467",
    "addr:postcode":"93711",
    "addr:street":"W Shaw Ave",
    "iso:country":"US",
    "sg:address":"3467 W Shaw Ave",
    "sg:city":"Fresno",
    "sg:classifiers":[
        {
            "category":"Professional",
            "subcategory":"Art Services",
            "type":"Services"
        }
    ],
    "sg:phone":"+1 559 275 7386",
    "sg:postcode":"93711",
    "sg:province":"CA",
    "sg:tags":[
        "graphic",
        "designer"
    ],
    "sg:website":"www.zylkadesign.com",
    "wof:name":"Paul Zylka Design",
    "wof:placetype":"venue"
},
  "geometry": {"coordinates":[-119.852458,36.808193],"type":"Point"}
}