{
  "type": "Feature",
  "properties": {
    "iso:country":"US",
    "sg:address":"1425 Live Oak Blvd",
    "sg:city":"Yuba City",
    "sg:classifiers":[
        {
            "category":"Social Services",
            "subcategory":"Child Care",
            "type":"Services"
        }
    ],
    "sg:phone":"+1 530 674 3802",
    "sg:postcode":"95991",
    "sg:province":"CA",
    "sg:tags":[
        "kindergarten",
        "academic",
        "school"
    ],
    "wof:name":"New Adventures Pre School",
    "wof:placetype":"venue"
},
  "geometry": {"coordinates":[-121.620583,39.149784],"type":"Point"}
}