{
  "type": "Feature",
  "properties": {
    "addr:full":"PO Box 1092 Bonsall CA 92003",
    "addr:housenumber":"po",
    "addr:postcode":"92003",
    "addr:street":"Box 1092",
    "iso:country":"US",
    "sg:address":"PO Box 1092",
    "sg:city":"Bonsall",
    "sg:classifiers":[
        {
            "category":"Professional",
            "subcategory":"Computer Services",
            "type":"Services"
        }
    ],
    "sg:postcode":"92003",
    "sg:province":"CA",
    "sg:website":"http://www.monsteroffers.com",
    "wof:name":"Monster Offers",
    "wof:placetype":"venue"
},
  "geometry": {"coordinates":[-117.19410000000001,33.27616],"type":"Point"}
}