{
  "type": "Feature",
  "properties": {
    "addr:full":"2127 Research Dr Livermore CA 94550",
    "addr:housenumber":"2127",
    "addr:postcode":"94550",
    "addr:street":"Research Dr",
    "iso:country":"US",
    "sg:address":"2127 Research Dr",
    "sg:city":"Livermore",
    "sg:classifiers":[
        {
            "category":"Manufacturing",
            "subcategory":"Metals",
            "type":"Manufacturing & Wholesale Goods"
        }
    ],
    "sg:phone":"+1 925 371 1941",
    "sg:postcode":"94550",
    "sg:province":"CA",
    "sg:tags":[
        "industrial",
        "machinery",
        "mfg"
    ],
    "wof:name":"Controlled Precision",
    "wof:placetype":"venue"
},
  "geometry": {"coordinates":[-121.721277,37.678246],"type":"Point"}
}