{
  "type": "Feature",
  "properties": {
    "iso:country":"US",
    "sg:address":"3250 W Olympic Blvd",
    "sg:city":"Los Angeles",
    "sg:classifiers":[
        {
            "category":"Shopping",
            "subcategory":"Clothing, Apparel, & Fashions",
            "type":"Retail Goods"
        }
    ],
    "sg:phone":"+1 323 735 6363",
    "sg:postcode":"90006",
    "sg:province":"CA",
    "sg:tags":[
        "children's",
        "clothing"
    ],
    "wof:name":"Nene Kids",
    "wof:placetype":"venue"
},
  "geometry": {"coordinates":[-118.306999,34.052601],"type":"Point"}
}