{
  "type": "Feature",
  "properties": {
    "addr:full":"718 Philippine St Taft CA 93268",
    "addr:housenumber":"718",
    "addr:postcode":"93268",
    "addr:street":"Philippine St",
    "iso:country":"US",
    "sg:address":"718 Philippine St",
    "sg:city":"Taft",
    "sg:classifiers":[
        {
            "category":"Building & Trades",
            "subcategory":"Construction",
            "type":"Services"
        }
    ],
    "sg:phone":"+1 661 765 4377",
    "sg:postcode":"93268",
    "sg:province":"CA",
    "sg:tags":[
        "contractor"
    ],
    "wof:name":"Geiger Construction & Plumbing",
    "wof:placetype":"venue"
},
  "geometry": {"coordinates":[-119.47602000000001,35.13513],"type":"Point"}
}