{
  "type": "Feature",
  "properties": {
    "iso:country":"US",
    "sg:address":"3425 E 1st St",
    "sg:city":"Los Angeles",
    "sg:classifiers":[
        {
            "category":"Travel",
            "subcategory":"Travel Agent",
            "type":"Entertainment"
        }
    ],
    "sg:phone":"+1 323 268 3451",
    "sg:postcode":"90063",
    "sg:province":"CA",
    "sg:tags":[
        "information",
        "tourist"
    ],
    "wof:name":"El Mercado De Los Angeles",
    "wof:placetype":"venue"
},
  "geometry": {"coordinates":[-118.193782,34.036594],"type":"Point"}
}