{
  "type": "Feature",
  "properties": {
    "addr:full":"5545 Stearns St Long Beach CA 90815",
    "addr:housenumber":"5545",
    "addr:postcode":"90815",
    "addr:street":"Stearns St",
    "iso:country":"US",
    "sg:address":"5545 Stearns St",
    "sg:city":"Long Beach",
    "sg:classifiers":[
        {
            "category":"Shopping",
            "subcategory":"Pharmacy",
            "type":"Retail Goods"
        }
    ],
    "sg:phone":"+1 562 596 8690",
    "sg:postcode":"90815",
    "sg:province":"CA",
    "sg:tags":[
        "drugstore"
    ],
    "sg:website":"www.riteaid.com",
    "wof:name":"Rite Aid",
    "wof:placetype":"venue"
},
  "geometry": {"coordinates":[-118.123833,33.796102],"type":"Point"}
}