{
  "type": "Feature",
  "properties": {
    "addr:full":"574 S Chaparro Rd Covina CA 91724",
    "addr:housenumber":"574",
    "addr:postcode":"91724",
    "addr:street":"S Chaparro Rd",
    "iso:country":"US",
    "sg:address":"574 S Chaparro Rd",
    "sg:city":"Covina",
    "sg:classifiers":[
        {
            "category":"Wholesale",
            "subcategory":"Sporting Goods",
            "type":"Manufacturing & Wholesale Goods"
        }
    ],
    "sg:phone":"+1 626 339 5137",
    "sg:postcode":"91724",
    "sg:province":"CA",
    "wof:name":"Smith Ltd",
    "wof:placetype":"venue"
},
  "geometry": {"coordinates":[-117.86485999999999,34.075858],"type":"Point"}
}