{
  "type": "Feature",
  "properties": {
    "iso:country":"US",
    "sg:address":"2404 N Vagedes Ave",
    "sg:city":"Fresno",
    "sg:classifiers":[
        {
            "category":"Shopping",
            "subcategory":"Musical Instruments",
            "type":"Retail Goods"
        }
    ],
    "sg:phone":"+1 559 225 9981",
    "sg:postcode":"93705",
    "sg:province":"CA",
    "sg:tags":[
        "music",
        "dealer"
    ],
    "wof:name":"Jason Bentley Music Society",
    "wof:placetype":"venue"
},
  "geometry": {"coordinates":[-119.816389,36.773906],"type":"Point"}
}