{
  "type": "Feature",
  "properties": {
    "iso:country":"US",
    "sg:address":"2501 E Anaheim St",
    "sg:city":"Long Beach",
    "sg:classifiers":[
        {
            "category":"Shopping",
            "subcategory":"Clothing, Apparel, & Fashions",
            "type":"Retail Goods"
        }
    ],
    "sg:phone":"+1 562 434 9631",
    "sg:postcode":"90804",
    "sg:province":"CA",
    "sg:tags":[
        "accessory",
        "clothing",
        "women's"
    ],
    "wof:name":"B Fabulous",
    "wof:placetype":"venue"
},
  "geometry": {"coordinates":[-118.162229,33.782737],"type":"Point"}
}