{
  "type": "Feature",
  "properties": {
    "iso:country":"US",
    "sg:address":"3530 Auburn Blvd",
    "sg:city":"Sacramento",
    "sg:classifiers":[
        {
            "category":"Insurance",
            "subcategory":"Health Insurance",
            "type":"Services"
        }
    ],
    "sg:phone":"+1 916 483 4561",
    "sg:postcode":"95821",
    "sg:province":"CA",
    "sg:tags":[
        "plans-information",
        "referral"
    ],
    "wof:name":"Xuening Zhu",
    "wof:placetype":"venue"
},
  "geometry": {"coordinates":[-121.382256,38.637421],"type":"Point"}
}