{
  "type": "Feature",
  "properties": {
    "iso:country":"US",
    "sg:address":"239 Los Cerritos Mall",
    "sg:city":"Cerritos",
    "sg:classifiers":[
        {
            "category":"Shopping",
            "subcategory":"Clothing, Apparel, & Fashions",
            "type":"Retail Goods"
        }
    ],
    "sg:phone":"+1 562 809 2260",
    "sg:postcode":"90703",
    "sg:province":"CA",
    "wof:name":"Ann Taylor",
    "wof:placetype":"venue"
},
  "geometry": {"coordinates":[-118.09344900000001,33.859109],"type":"Point"}
}