{
  "type": "Feature",
  "properties": {
    "iso:country":"US",
    "sg:address":"1250 Bellflower Blvd. California State University",
    "sg:city":"Long Beach",
    "sg:classifiers":[
        {
            "category":"Coffee & Tea",
            "type":"Food & Drink"
        }
    ],
    "sg:phone":"+1 562 822 4603",
    "sg:postcode":"90815",
    "sg:province":"CA",
    "wof:name":"Starbucks",
    "wof:placetype":"venue"
},
  "geometry": {"coordinates":[-118.121181,33.78497],"type":"Point"}
}