{
  "type": "Feature",
  "properties": {
    "addr:full":"11712 W San Vicente Blvd, Los Angeles, CA, USA",
    "addr:housenumber":11712,
    "addr:phone":"310-481-7108",
    "addr:postcode":"90049",
    "addr:street":"W San Vicente Blvd",
    "addr:website":"http://pizzana.com/",
    "iso:country":"US",
    "name:eng_x_preferred":[
        "Pizzana"
    ],
    "wof:name":"Pizzana",
    "wof:placetype":"venue"
},
  "geometry": {"coordinates":[-118.46601099999999,34.053325],"type":"Point"}
}