{
  "type": "Feature",
  "properties": {
    "addr:full":"324 Avenida De La Estrell San Clemente CA 92672",
    "addr:housenumber":"324",
    "addr:postcode":"92672",
    "addr:street":"Avenida De La Estrell",
    "iso:country":"US",
    "sg:address":"324 Avenida De La Estrell",
    "sg:city":"San Clemente",
    "sg:classifiers":[
        {
            "category":"Professional",
            "subcategory":"Computer Services",
            "type":"Services"
        }
    ],
    "sg:phone":"+1 949 369 4688",
    "sg:postcode":"92672",
    "sg:province":"CA",
    "wof:name":"Ifes",
    "wof:placetype":"venue"
},
  "geometry": {"coordinates":[-117.61282,33.42848],"type":"Point"}
}