{
  "type": "Feature",
  "properties": {
    "addr:full":"1180 9th St Crescent City CA 95531",
    "addr:housenumber":"1180",
    "addr:postcode":"95531",
    "addr:street":"9Th St Crescent",
    "iso:country":"US",
    "sg:address":"1180 9th St",
    "sg:city":"Crescent City",
    "sg:classifiers":[
        {
            "category":"Shopping",
            "subcategory":"Department Store",
            "type":"Retail Goods"
        }
    ],
    "sg:phone":"+1 707 465 3884",
    "sg:postcode":"95531",
    "sg:province":"CA",
    "sg:tags":[
        "shop"
    ],
    "wof:name":"Dollar Tree",
    "wof:placetype":"venue"
},
  "geometry": {"coordinates":[-124.19841099999999,41.757988],"type":"Point"}
}