{
  "type": "Feature",
  "properties": {
    "addr:full":"15255 Texaco Ave Paramount CA 90723",
    "addr:housenumber":"15255",
    "addr:postcode":"90723",
    "addr:street":"Texaco Ave",
    "iso:country":"US",
    "sg:address":"15255 Texaco Ave",
    "sg:city":"Paramount",
    "sg:classifiers":[
        {
            "category":"Manufacturing",
            "subcategory":"Food",
            "type":"Manufacturing & Wholesale Goods"
        }
    ],
    "sg:phone":"+1 562 633 1581",
    "sg:postcode":"90723",
    "sg:province":"CA",
    "sg:tags":[
        "dessert",
        "mfg"
    ],
    "wof:name":"Margaritas Foods",
    "wof:placetype":"venue"
},
  "geometry": {"coordinates":[-118.17195100000001,33.895919],"type":"Point"}
}