{
  "type": "Feature",
  "properties": {
    "iso:country":"US",
    "sg:address":"900 Iliff St",
    "sg:city":"Pacific Plsds",
    "sg:classifiers":[
        {
            "category":"Professional",
            "subcategory":"Management & Consulting",
            "type":"Services"
        }
    ],
    "sg:phone":"+1 310 459 8852",
    "sg:postcode":"90272",
    "sg:province":"CA",
    "sg:tags":[
        "construction"
    ],
    "wof:name":"Gillespie & Assoc",
    "wof:placetype":"venue"
},
  "geometry": {"coordinates":[-118.519115,34.04766],"type":"Point"}
}