{
  "type": "Feature",
  "properties": {
    "iso:country":"US",
    "sg:address":"6194 Parallel Rd",
    "sg:city":"Anderson",
    "sg:classifiers":[
        {
            "category":"Autos & Motor Vehicles",
            "subcategory":"Automobile Sales",
            "type":"Retail Goods"
        }
    ],
    "sg:phone":"+1 530 365 1811",
    "sg:postcode":"96007",
    "sg:province":"CA",
    "sg:tags":[
        "car",
        "dealer"
    ],
    "wof:name":"Gibbons Auto Sales",
    "wof:placetype":"venue"
},
  "geometry": {"coordinates":[-122.327424,40.46785],"type":"Point"}
}