{
  "type": "Feature",
  "properties": {
    "iso:country":"US",
    "sg:address":"1200 Arden Way",
    "sg:city":"Sacramento",
    "sg:classifiers":[
        {
            "category":"Utilities",
            "subcategory":"Water",
            "type":"Services"
        },
        {
            "category":"Home & Garden",
            "subcategory":"Hardware",
            "type":"Retail Goods"
        }
    ],
    "sg:phone":"+1 916 927 5005",
    "sg:postcode":"95815",
    "sg:province":"CA",
    "sg:tags":[
        "filtration",
        "softening",
        "companies-bottled",
        "purification",
        "bulk",
        "equipment",
        "conditioning"
    ],
    "sg:website":"http://www.culligan.com",
    "wof:name":"Culligan Water Conditioning Of Sacramento",
    "wof:placetype":"venue"
},
  "geometry": {"coordinates":[-121.438158,38.605179],"type":"Point"}
}