{
  "type": "Feature",
  "properties": {
    "iso:country":"US",
    "sg:address":"6034 N McCaffrey Ave",
    "sg:city":"Fresno",
    "sg:classifiers":[
        {
            "category":"Building & Trades",
            "subcategory":"Construction",
            "type":"Services"
        }
    ],
    "sg:phone":"+1 559 940 2041",
    "sg:postcode":"93722",
    "sg:province":"CA",
    "sg:tags":[
        "handyman"
    ],
    "wof:name":"David W Ward Handyman",
    "wof:placetype":"venue"
},
  "geometry": {"coordinates":[-119.891386,36.822473],"type":"Point"}
}