{
  "type": "Feature",
  "properties": {
    "addr:full":"193 W Polk St Coalinga CA 93210",
    "addr:housenumber":"193",
    "addr:postcode":"93210",
    "addr:street":"W Polk St",
    "iso:country":"US",
    "sg:address":"193 W Polk St",
    "sg:city":"Coalinga",
    "sg:classifiers":[
        {
            "category":"Fast Food",
            "type":"Food & Drink"
        },
        {
            "category":"Restaurant",
            "type":"Food & Drink"
        },
        {
            "category":"Food & Beverages",
            "subcategory":"Groceries & Convenience Stores",
            "type":"Retail Goods"
        }
    ],
    "sg:phone":"+1 559 935 5656",
    "sg:postcode":"93210",
    "sg:province":"CA",
    "sg:tags":[
        "shop",
        "american",
        "sandwich",
        "take"
    ],
    "sg:website":"http://www.subway.com",
    "wof:name":"Subway",
    "wof:placetype":"venue"
},
  "geometry": {"coordinates":[-120.36543399999999,36.136509],"type":"Point"}
}