{
  "type": "Feature",
  "properties": {
    "addr:full":"San Jose, CA 95131, USA 1903 Concourse Dr. San Jose CA 95131",
    "addr:housenumber":"1903",
    "addr:postcode":"95131;95131",
    "addr:street":"Concourse Dr.",
    "iso:country":"US",
    "sg:address":"San Jose, CA 95131, USA 1903 Concourse Dr.",
    "sg:city":"San Jose",
    "sg:classifiers":[
        {
            "category":"Professional",
            "subcategory":"Computer Services",
            "type":"Services"
        }
    ],
    "sg:postcode":"95131",
    "sg:province":"CA",
    "sg:tags":[
        "outsource",
        "mobile-application-development",
        "crowdsource"
    ],
    "sg:website":"http://www.taskcity.com",
    "wof:name":"Taskcity",
    "wof:placetype":"venue"
},
  "geometry": {"coordinates":[-121.890934,37.397057],"type":"Point"}
}