{
  "type": "Feature",
  "properties": {
    "iso:country":"US",
    "sg:address":"531 el Retiro Ct",
    "sg:city":"Agoura Hills",
    "sg:classifiers":[
        {
            "category":"Building & Trades",
            "subcategory":"Construction",
            "type":"Services"
        }
    ],
    "sg:phone":"+1 818 706 0679",
    "sg:postcode":"91377",
    "sg:province":"CA",
    "sg:tags":[
        "residential",
        "contractor"
    ],
    "wof:name":"Smith Pat General Contractor",
    "wof:placetype":"venue"
},
  "geometry": {"coordinates":[-118.77969299999999,34.181772],"type":"Point"}
}