{
  "type": "Feature",
  "properties": {
    "iso:country":"US",
    "sg:address":"199 Stanford Shopping Center",
    "sg:city":"Palo Alto",
    "sg:classifiers":[
        {
            "category":"Restaurant",
            "type":"Food & Drink"
        }
    ],
    "sg:phone":"+1 650 327 7246",
    "sg:postcode":"94304",
    "sg:province":"CA",
    "wof:name":"Gourmet Franks",
    "wof:placetype":"venue"
},
  "geometry": {"coordinates":[-122.17034,37.44416],"type":"Point"}
}