{
  "type": "Feature",
  "properties": {
    "addr:full":"1814 Curtis St Berkeley CA 94702",
    "addr:housenumber":"1814",
    "addr:postcode":"94702",
    "addr:street":"Curtis St",
    "iso:country":"US",
    "sg:address":"1814 Curtis St",
    "sg:city":"Berkeley",
    "sg:classifiers":[
        {
            "category":"Manufacturing",
            "subcategory":"Apparel",
            "type":"Manufacturing & Wholesale Goods"
        }
    ],
    "sg:phone":"+1 510 526 7752",
    "sg:postcode":"94702",
    "sg:province":"CA",
    "sg:tags":[
        "household",
        "furnishing",
        "mfg"
    ],
    "wof:name":"Slips",
    "wof:placetype":"venue"
},
  "geometry": {"coordinates":[-122.289807,37.871038],"type":"Point"}
}