{
  "type": "Feature",
  "properties": {
    "addr:full":"920 Venice Blvd Venice CA 90291",
    "addr:housenumber":"920",
    "addr:postcode":"90291",
    "addr:street":"Venice Blvd",
    "iso:country":"US",
    "sg:address":"920 Venice Blvd",
    "sg:city":"Venice",
    "sg:classifiers":[
        {
            "category":"Shopping",
            "subcategory":"Gifts & Souvenirs",
            "type":"Retail Goods"
        }
    ],
    "sg:phone":"+1 310 301 3532",
    "sg:postcode":"90291",
    "sg:province":"CA",
    "sg:tags":[
        "cards",
        "greeting"
    ],
    "wof:name":"Dont Shoot The Messenger",
    "wof:placetype":"venue"
},
  "geometry": {"coordinates":[-118.454014,33.993129],"type":"Point"}
}