{
  "type": "Feature",
  "properties": {
    "iso:country":"US",
    "sg:address":"8400 Slauson Ave",
    "sg:city":"Pico Rivera",
    "sg:classifiers":[
        {
            "category":"Retail",
            "subcategory":"Auto Rental",
            "type":"Services"
        }
    ],
    "sg:phone":"+1 562 949 7961",
    "sg:postcode":"90660",
    "sg:province":"CA",
    "sg:tags":[
        "renting",
        "truck",
        "leasing"
    ],
    "wof:name":"J T Mc Kinney Co",
    "wof:placetype":"venue"
},
  "geometry": {"coordinates":[-118.112953,33.973431],"type":"Point"}
}