{
  "type": "Feature",
  "properties": {
    "addr:full":"910 W Center Ave Visalia CA 93291",
    "addr:housenumber":"910",
    "addr:postcode":"93291",
    "addr:street":"W Center Ave",
    "iso:country":"US",
    "sg:address":"910 W Center Ave",
    "sg:city":"Visalia",
    "sg:phone":"+1 559 732 1712",
    "sg:postcode":"93291",
    "sg:province":"CA",
    "wof:name":"Betty E Blanks",
    "wof:placetype":"venue"
},
  "geometry": {"coordinates":[-119.301221,36.331031],"type":"Point"}
}