{
  "type": "Feature",
  "properties": {
    "iso:country":"US",
    "sg:address":"1533 5th St",
    "sg:city":"Oakland",
    "sg:classifiers":[
        {
            "category":"Museum",
            "type":"Entertainment"
        }
    ],
    "sg:phone":"+1 415 244 8341",
    "sg:postcode":"94607",
    "sg:province":"CA",
    "wof:name":"Drum Machine Museum",
    "wof:placetype":"venue"
},
  "geometry": {"coordinates":[-122.297124,37.80452],"type":"Point"}
}