{
  "type": "Feature",
  "properties": {
    "addr:full":"400 S Atlantic Blvd Monterey Park CA 91754",
    "addr:housenumber":"400",
    "addr:postcode":"91754",
    "addr:street":"S Atlantic Blvd",
    "iso:country":"US",
    "sg:address":"400 S Atlantic Blvd",
    "sg:city":"Monterey Park",
    "sg:classifiers":[
        {
            "category":"Insurance",
            "subcategory":"Insurance Agent",
            "type":"Services"
        }
    ],
    "sg:phone":"+1 323 722 0071",
    "sg:postcode":"91754",
    "sg:province":"CA",
    "wof:name":"State Farm Insurance",
    "wof:placetype":"venue"
},
  "geometry": {"coordinates":[-118.134022,34.057953],"type":"Point"}
}