{
  "type": "Feature",
  "properties": {
    "iso:country":"US",
    "sg:address":"1400 Q St",
    "sg:city":"Bakersfield",
    "sg:classifiers":[
        {
            "category":"Building & Trades",
            "subcategory":"Construction",
            "type":"Services"
        }
    ],
    "sg:phone":"+1 661 859 1470",
    "sg:postcode":"93301",
    "sg:province":"CA",
    "sg:tags":[
        "nonresidential"
    ],
    "wof:name":"Omni Building Technology Inc",
    "wof:placetype":"venue"
},
  "geometry": {"coordinates":[-119.010532,35.371384],"type":"Point"}
}