{
  "type": "Feature",
  "properties": {
    "addr:full":"4801 E 3rd Street Los Angeles CA 90022",
    "addr:housenumber":"4801",
    "addr:postcode":"90022",
    "addr:street":"E 3Rd Street",
    "iso:country":"US",
    "sg:address":"4801 E 3rd Street",
    "sg:city":"Los Angeles",
    "sg:classifiers":[
        {
            "category":"Education",
            "subcategory":"Library",
            "type":"Public Place"
        }
    ],
    "sg:phone":"+1 323 263 5087",
    "sg:postcode":"90022",
    "sg:province":"CA",
    "sg:website":"planning.lacounty.gov",
    "wof:name":"Los Angeles County of",
    "wof:placetype":"venue"
},
  "geometry": {"coordinates":[-118.161677,34.033469],"type":"Point"}
}