{
  "type": "Feature",
  "properties": {
    "iso:country":"US",
    "sg:address":"205 E San Joaquin Ave",
    "sg:city":"Tulare",
    "sg:classifiers":[
        {
            "category":"Professional",
            "subcategory":"Business Services",
            "type":"Services"
        }
    ],
    "sg:phone":"+1 559 688 6666",
    "sg:postcode":"93274",
    "sg:province":"CA",
    "sg:tags":[
        "development"
    ],
    "wof:name":"Certified Dev Corp-Tulare Cty",
    "wof:placetype":"venue"
},
  "geometry": {"coordinates":[-119.346716,36.210601],"type":"Point"}
}