{
  "type": "Feature",
  "properties": {
    "iso:country":"US",
    "sg:address":"11568 Sorrento Valley Rd",
    "sg:city":"San Diego",
    "sg:classifiers":[
        {
            "category":"Manufacturing",
            "subcategory":"Tools & Machinery",
            "type":"Manufacturing & Wholesale Goods"
        }
    ],
    "sg:phone":"+1 858 847 0200",
    "sg:postcode":"92121",
    "sg:province":"CA",
    "sg:tags":[
        "laser",
        "for",
        "mfg",
        "devices",
        "can",
        "detecting"
    ],
    "wof:name":"Spectrascience  Inc",
    "wof:placetype":"venue"
},
  "geometry": {"coordinates":[-117.229023,32.90898],"type":"Point"}
}