{
  "type": "Feature",
  "properties": {
    "addr:full":"3607 W Pacific Ave Burbank CA 91505",
    "addr:housenumber":"3607",
    "addr:postcode":"91505",
    "addr:street":"W Pacific Ave",
    "iso:country":"US",
    "sg:address":"3607 W Pacific Ave",
    "sg:city":"Burbank",
    "sg:classifiers":[
        {
            "category":"Shopping",
            "subcategory":"Hobbies, Toys, & Games",
            "type":"Retail Goods"
        },
        {
            "category":"Professional",
            "subcategory":"Business Services",
            "type":"Services"
        }
    ],
    "sg:phone":"+1 818 557 0005",
    "sg:postcode":"91505",
    "sg:province":"CA",
    "sg:tags":[
        "import",
        "importer",
        "toy",
        "representative",
        "store"
    ],
    "sg:website":"www.funfactoryusa.net",
    "wof:name":"Funfactory Usa Inc",
    "wof:placetype":"venue"
},
  "geometry": {"coordinates":[-118.35025400000001,34.188517],"type":"Point"}
}