{
  "type": "Feature",
  "properties": {
    "addr:full":"1035 E Vista Way Vista CA 92084",
    "addr:housenumber":"1035",
    "addr:postcode":"92084",
    "addr:street":"E Vista Way",
    "iso:country":"US",
    "sg:address":"1035 E Vista Way",
    "sg:city":"Vista",
    "sg:classifiers":[
        {
            "category":"Retail",
            "subcategory":"Portrait Studio",
            "type":"Services"
        }
    ],
    "sg:phone":"+1 760 500 9707",
    "sg:postcode":"92084",
    "sg:province":"CA",
    "sg:tags":[
        "photographer"
    ],
    "wof:name":"A Third Eye Creative Photo",
    "wof:placetype":"venue"
},
  "geometry": {"coordinates":[-117.228678,33.212875],"type":"Point"}
}