{
  "type": "Feature",
  "properties": {
    "addr:full":"2568 Noriega St San Francisco CA 94122",
    "addr:housenumber":"2568",
    "addr:postcode":"94122",
    "addr:street":"Noriega St",
    "iso:country":"US",
    "sg:address":"2568 Noriega St",
    "sg:city":"San Francisco",
    "sg:classifiers":[
        {
            "category":"Professional",
            "type":"Services"
        }
    ],
    "sg:phone":"+1 415 661 1100",
    "sg:postcode":"94122",
    "sg:province":"CA",
    "sg:tags":[
        "establishment"
    ],
    "wof:name":"Arvik International Trade",
    "wof:placetype":"venue"
},
  "geometry": {"coordinates":[-122.49088999999999,37.753687],"type":"Point"}
}