{
  "type": "Feature",
  "properties": {
    "addr:full":"3031 Los Feliz Dr Thousand Oaks CA 91362",
    "addr:housenumber":"3031",
    "addr:postcode":"91362",
    "addr:street":"Los Feliz Dr",
    "iso:country":"US",
    "sg:address":"3031 Los Feliz Dr",
    "sg:city":"Thousand Oaks",
    "sg:classifiers":[
        {
            "category":"Building & Trades",
            "subcategory":"Plumbing",
            "type":"Services"
        }
    ],
    "sg:phone":"+1 818 889 8261",
    "sg:postcode":"91362",
    "sg:province":"CA",
    "sg:tags":[
        "conditioning",
        "air",
        "system",
        "contractor"
    ],
    "wof:name":"Len Air Conditioning & Htg",
    "wof:placetype":"venue"
},
  "geometry": {"coordinates":[-118.833859,34.170518],"type":"Point"}
}