{
  "type": "Feature",
  "properties": {
    "iso:country":"US",
    "sg:address":"2145 Mendocino Ave",
    "sg:city":"Santa Rosa",
    "sg:classifiers":[
        {
            "category":"Autos & Motor Vehicles",
            "subcategory":"Fuel & Gas Station",
            "type":"Retail Goods"
        }
    ],
    "sg:phone":"+1 707 526 6940",
    "sg:postcode":"95401",
    "sg:province":"CA",
    "sg:tags":[
        "oil"
    ],
    "wof:name":"Grand Gas",
    "wof:placetype":"venue"
},
  "geometry": {"coordinates":[-122.717218,38.459437],"type":"Point"}
}