{
  "type": "Feature",
  "properties": {
    "iso:country":"US",
    "sg:address":"1650 Gillette Rd",
    "sg:city":"Pomona",
    "sg:classifiers":[
        {
            "category":"Autos & Motor Vehicles",
            "subcategory":"Fuel & Gas Station",
            "type":"Retail Goods"
        }
    ],
    "sg:phone":"+1 909 629 2929",
    "sg:postcode":"91768",
    "sg:province":"CA",
    "sg:tags":[
        "oil"
    ],
    "wof:name":"Pomona Fuel",
    "wof:placetype":"venue"
},
  "geometry": {"coordinates":[-117.78406099999999,34.073466],"type":"Point"}
}