{
  "type": "Feature",
  "properties": {
    "addr:full":"3087 S Harbor Blvd Santa Ana CA 92704",
    "addr:housenumber":"3087",
    "addr:postcode":"92704",
    "addr:street":"S Harbor Blvd",
    "iso:country":"US",
    "sg:address":"3087 S Harbor Blvd",
    "sg:city":"Santa Ana",
    "sg:classifiers":[
        {
            "category":"Manufacturing",
            "subcategory":"Metals",
            "type":"Manufacturing & Wholesale Goods"
        }
    ],
    "sg:phone":"+1 714 427 0877",
    "sg:postcode":"92704",
    "sg:province":"CA",
    "sg:tags":[
        "industrial",
        "valve",
        "mfg"
    ],
    "wof:name":"Avco",
    "wof:placetype":"venue"
},
  "geometry": {"coordinates":[-117.91980100000001,33.706888],"type":"Point"}
}