{
  "type": "Feature",
  "properties": {
    "iso:country":"US",
    "sg:address":"3202 W Adams Blvd",
    "sg:city":"Los Angeles",
    "sg:classifiers":[
        {
            "category":"Education",
            "subcategory":"School",
            "type":"Public Place"
        }
    ],
    "sg:phone":"+1 323 373 2000",
    "sg:postcode":"90018",
    "sg:province":"CA",
    "sg:tags":[
        "high",
        "middle",
        "elementary"
    ],
    "sg:website":"www.lausd.k12.ca.us",
    "wof:name":"Community Harvest Charter School",
    "wof:placetype":"venue"
},
  "geometry": {"coordinates":[-118.319,34.0327],"type":"Point"}
}