{
  "type": "Feature",
  "properties": {
    "addr:full":"208 W Hueneme Rd Port Hueneme CA 93033",
    "addr:housenumber":"208",
    "addr:postcode":"93033",
    "addr:street":"W Hueneme Rd",
    "iso:country":"US",
    "sg:address":"208 W Hueneme Rd",
    "sg:city":"Port Hueneme",
    "sg:classifiers":[
        {
            "category":"Organizations",
            "subcategory":"Religious Organization",
            "type":"Services"
        }
    ],
    "sg:phone":"+1 805 986 5226",
    "sg:postcode":"93033",
    "sg:province":"CA",
    "wof:name":"Nacel Open Door Inc",
    "wof:placetype":"venue"
},
  "geometry": {"coordinates":[-119.183823,34.147561],"type":"Point"}
}