{
  "type": "Feature",
  "properties": {
    "addr:full":"14401 Sylvan St Ste 106 Van Nuys CA 91401",
    "addr:housenumber":"14401",
    "addr:postcode":"91401",
    "addr:street":"Sylvan St Ste 106",
    "iso:country":"US",
    "sg:address":"14401 Sylvan St Ste 106",
    "sg:city":"Van Nuys",
    "sg:classifiers":[
        {
            "category":"Professional",
            "subcategory":"Lawyer & Legal Services",
            "type":"Services"
        }
    ],
    "sg:phone":"+1 818 465 0222",
    "sg:postcode":"91401",
    "sg:province":"CA",
    "wof:name":"McNamara & McNamara",
    "wof:placetype":"venue"
},
  "geometry": {"coordinates":[-118.44650799999999,34.184787],"type":"Point"}
}