{
  "type": "Feature",
  "properties": {
    "addr:full":"310 N Akers St Visalia CA 93291",
    "addr:housenumber":"310",
    "addr:postcode":"93291",
    "addr:street":"N Akers St",
    "iso:country":"US",
    "sg:address":"310 N Akers St",
    "sg:city":"Visalia",
    "sg:classifiers":[
        {
            "category":"Education",
            "subcategory":"School",
            "type":"Public Place"
        }
    ],
    "sg:phone":"+1 559 730 7798",
    "sg:postcode":"93291",
    "sg:province":"CA",
    "wof:name":"Willow Glen Elementary School",
    "wof:placetype":"venue"
},
  "geometry": {"coordinates":[-119.349684,36.33299],"type":"Point"}
}