{
  "type": "Feature",
  "properties": {
    "iso:country":"US",
    "sg:address":"2425 S Norfolk St",
    "sg:city":"San Mateo",
    "sg:classifiers":[
        {
            "category":"Wholesale",
            "subcategory":"Vending Machines",
            "type":"Manufacturing & Wholesale Goods"
        }
    ],
    "sg:phone":"+1 650 573 0182",
    "sg:postcode":"94403",
    "sg:province":"CA",
    "wof:name":"Bay Vending",
    "wof:placetype":"venue"
},
  "geometry": {"coordinates":[-122.288146,37.549622],"type":"Point"}
}