{
  "type": "Feature",
  "properties": {
    "iso:country":"US",
    "sg:address":"1314 Barrington Way",
    "sg:city":"Glendale",
    "sg:classifiers":[
        {
            "category":"Home & Garden",
            "subcategory":"Carpets & Floor Coverings",
            "type":"Retail Goods"
        },
        {
            "category":"Building & Trades",
            "subcategory":"Construction",
            "type":"Services"
        },
        {
            "category":"Utilities",
            "type":"Services"
        }
    ],
    "sg:phone":"+1 818 934 0052",
    "sg:postcode":"91205",
    "sg:province":"CA",
    "sg:tags":[
        "contractor",
        "internet",
        "flooring",
        "provider"
    ],
    "sg:website":"www.kitchenbathremodelingpros.com",
    "wof:name":"Kitchen & Bath Remodeling Pros",
    "wof:placetype":"venue"
},
  "geometry": {"coordinates":[-118.23690499999999,34.147095],"type":"Point"}
}