{
  "type": "Feature",
  "properties": {
    "iso:country":"US",
    "sg:address":"9722 Alcott Street",
    "sg:city":"Los Angeles",
    "sg:classifiers":[
        {
            "category":"Education",
            "subcategory":"School",
            "type":"Public Place"
        }
    ],
    "sg:phone":"+1 310 277 7446",
    "sg:postcode":"90035",
    "sg:province":"CA",
    "wof:name":"Signshine",
    "wof:placetype":"venue"
},
  "geometry": {"coordinates":[-118.39955,34.053584],"type":"Point"}
}