{
  "type": "Feature",
  "properties": {
    "iso:country":"US",
    "sg:address":"916 E 8th St",
    "sg:city":"National City",
    "sg:classifiers":[
        {
            "category":"Retail",
            "subcategory":"Repair Shop",
            "type":"Services"
        }
    ],
    "sg:phone":"+1 619 474 8195",
    "sg:postcode":"91950",
    "sg:province":"CA",
    "sg:tags":[
        "jewelry"
    ],
    "wof:name":"Ginto ATBP Inc",
    "wof:placetype":"venue"
},
  "geometry": {"coordinates":[-117.09864,32.678065],"type":"Point"}
}