{
  "type": "Feature",
  "properties": {
    "addr:full":"233 Clark Ave Pomona CA 91767",
    "addr:housenumber":"233",
    "addr:postcode":"91767",
    "addr:street":"Clark Ave",
    "iso:country":"US",
    "sg:address":"233 Clark Ave",
    "sg:city":"Pomona",
    "sg:classifiers":[
        {
            "category":"Building & Trades",
            "subcategory":"Construction",
            "type":"Services"
        },
        {
            "category":"Manufacturing",
            "subcategory":"Tools & Machinery",
            "type":"Manufacturing & Wholesale Goods"
        }
    ],
    "sg:phone":"+1 909 469 0611",
    "sg:postcode":"91767",
    "sg:province":"CA",
    "sg:tags":[
        "lab",
        "cabinet",
        "maker",
        "cabin",
        "mfg"
    ],
    "wof:name":"Phil's Custom Cabinets",
    "wof:placetype":"venue"
},
  "geometry": {"coordinates":[-117.72936199999999,34.062604],"type":"Point"}
}