{
  "type": "Feature",
  "properties": {
    "addr:full":"4966 Elrod Dr Castro Valley CA 94546",
    "addr:housenumber":"4966",
    "addr:postcode":"94546",
    "addr:street":"Elrod Dr",
    "iso:country":"US",
    "sg:address":"4966 Elrod Dr",
    "sg:city":"Castro Valley",
    "sg:classifiers":[
        {
            "category":"Wholesale",
            "subcategory":"Home Furnishings",
            "type":"Manufacturing & Wholesale Goods"
        },
        {
            "category":"Home & Garden",
            "subcategory":"Home Furnishings",
            "type":"Retail Goods"
        }
    ],
    "sg:phone":"+1 510 582 4599",
    "sg:postcode":"94546",
    "sg:province":"CA",
    "sg:tags":[
        "table",
        "pad"
    ],
    "wof:name":"East Bay Table Pads Company",
    "wof:placetype":"venue"
},
  "geometry": {"coordinates":[-122.067825,37.711365],"type":"Point"}
}