{
  "type": "Feature",
  "properties": {
    "iso:country":"US",
    "sg:address":"195 Blue Ravine Rd",
    "sg:city":"Folsom",
    "sg:classifiers":[
        {
            "category":"Health Services",
            "subcategory":"Doctor",
            "type":"Services"
        }
    ],
    "sg:phone":"+1 916 404 3200",
    "sg:postcode":"95630",
    "sg:province":"CA",
    "sg:tags":[
        "dentist"
    ],
    "wof:name":"Blue Ravine Dental Group",
    "wof:placetype":"venue"
},
  "geometry": {"coordinates":[-121.184281,38.65273],"type":"Point"}
}