{
  "type": "Feature",
  "properties": {
    "addr:full":"4095 Harbor Dr Carlsbad CA 92008",
    "addr:housenumber":"4095",
    "addr:postcode":"92008",
    "addr:street":"Harbor Dr",
    "iso:country":"US",
    "sg:address":"4095 Harbor Dr",
    "sg:city":"Carlsbad",
    "sg:phone":"+1 800 793 3763",
    "sg:postcode":"92008",
    "sg:province":"CA",
    "sg:website":"http://WWW.FIRESAFECHIMNEYSWEEP.LIVEONATT.COM",
    "wof:name":"Fire Safe Chimney Sweep Co. & Repairs",
    "wof:placetype":"venue"
},
  "geometry": {"coordinates":[-117.33778700000001,33.148269],"type":"Point"}
}