{
  "type": "Feature",
  "properties": {
    "iso:country":"US",
    "sg:address":"1322 W Beverly Blvd",
    "sg:city":"Montebello",
    "sg:classifiers":[
        {
            "category":"Restaurant",
            "type":"Food & Drink"
        }
    ],
    "sg:menulink":"http://www.allmenus.com/ca/southwest-san-gabriel-valley/109235-village-inn/menu/",
    "sg:phone":"+1 323 722 6324",
    "sg:postcode":"90640",
    "sg:province":"CA",
    "sg:tags":[
        "new",
        "american"
    ],
    "wof:name":"Village Inn",
    "wof:placetype":"venue"
},
  "geometry": {"coordinates":[-118.11261399999999,34.018926],"type":"Point"}
}