{
  "type": "Feature",
  "properties": {
    "iso:country":"US",
    "sg:address":"11580 Niagara Dr",
    "sg:city":"Mira Loma",
    "sg:classifiers":[
        {
            "category":"Freight",
            "type":"Transportation"
        }
    ],
    "sg:phone":"+1 951 681 5252",
    "sg:postcode":"91752",
    "sg:province":"CA",
    "sg:tags":[
        "operator",
        "local",
        "trucking"
    ],
    "wof:name":"Tomatohead Studio Rentals",
    "wof:placetype":"venue"
},
  "geometry": {"coordinates":[-117.538132,33.978698],"type":"Point"}
}