{
  "type": "Feature",
  "properties": {
    "iso:country":"US",
    "sg:address":"3850 Ramada Dr",
    "sg:city":"Paso Robles",
    "sg:classifiers":[
        {
            "category":"Organizations",
            "subcategory":"Religious Organization",
            "type":"Services"
        }
    ],
    "sg:phone":"+1 805 434 3630",
    "sg:postcode":"93446",
    "sg:province":"CA",
    "sg:tags":[
        "church"
    ],
    "sg:website":"www.vineyardchurchofchrist.org",
    "wof:name":"Church Of Christ",
    "wof:placetype":"venue"
},
  "geometry": {"coordinates":[-120.699167,35.570099],"type":"Point"}
}