{
  "type": "Feature",
  "properties": {
    "addr:full":"11300 Hartland St North Hollywood CA 91605",
    "addr:housenumber":"11300",
    "addr:postcode":"91605",
    "addr:street":"Hartland St",
    "iso:country":"US",
    "sg:address":"11300 Hartland St",
    "sg:city":"North Hollywood",
    "sg:classifiers":[
        {
            "category":"Shopping",
            "subcategory":"Computers & Home Electronics",
            "type":"Retail Goods"
        }
    ],
    "sg:phone":"+1 818 760 4445",
    "sg:postcode":"91605",
    "sg:province":"CA",
    "sg:tags":[
        "repair",
        "equipment"
    ],
    "wof:name":"T S Computers",
    "wof:placetype":"venue"
},
  "geometry": {"coordinates":[-118.37799800000001,34.195301],"type":"Point"}
}