{
  "type": "Feature",
  "properties": {
    "iso:country":"US",
    "sg:address":"1894 Celeste Ave",
    "sg:city":"Clovis",
    "sg:classifiers":[
        {
            "category":"Building & Trades",
            "subcategory":"Construction",
            "type":"Services"
        }
    ],
    "sg:phone":"+1 559 322 7967",
    "sg:postcode":"93611",
    "sg:province":"CA",
    "sg:tags":[
        "carpenter"
    ],
    "wof:name":"Carpenter Appraisals, Inc.",
    "wof:placetype":"venue"
},
  "geometry": {"coordinates":[-119.67849,36.821172],"type":"Point"}
}