{
  "type": "Feature",
  "properties": {
    "iso:country":"US",
    "sg:address":"Bonita Rd",
    "sg:city":"Chula Vista",
    "sg:classifiers":[
        {
            "category":"Restaurant",
            "type":"Food & Drink"
        }
    ],
    "sg:postcode":"91911",
    "sg:province":"CA",
    "sg:tags":[
        "flavor",
        "local"
    ],
    "wof:name":"The Dinosaurs On Bonita Rd",
    "wof:placetype":"venue"
},
  "geometry": {"coordinates":[-117.057918,32.6479],"type":"Point"}
}