{
  "type": "Feature",
  "properties": {
    "iso:country":"US",
    "sg:address":"1111 Bayhill Dr",
    "sg:city":"San Bruno",
    "sg:classifiers":[
        {
            "category":"Shopping",
            "subcategory":"Catalog Store",
            "type":"Retail Goods"
        }
    ],
    "sg:phone":"+1 650 616 4670",
    "sg:postcode":"94066",
    "sg:province":"CA",
    "sg:tags":[
        "e"
    ],
    "sg:website":"www.rtimage.com",
    "wof:name":"Real Time Image",
    "wof:placetype":"venue"
},
  "geometry": {"coordinates":[-122.420265,37.62948],"type":"Point"}
}