{
  "type": "Feature",
  "properties": {
    "iso:country":"US",
    "sg:address":"3180 Colima Rd",
    "sg:city":"Hacienda Heights",
    "sg:classifiers":[
        {
            "category":"Health Services",
            "subcategory":"Doctor",
            "type":"Services"
        }
    ],
    "sg:phone":"+1 626 961 1644",
    "sg:postcode":"91745",
    "sg:province":"CA",
    "sg:tags":[
        "physician",
        "surgeon"
    ],
    "wof:name":"Care More Medical Group",
    "wof:placetype":"venue"
},
  "geometry": {"coordinates":[-117.974339,33.980908],"type":"Point"}
}