{
  "type": "Feature",
  "properties": {
    "addr:full":"28772 S Western Ave Rancho Pls Vrds CA 90275",
    "addr:housenumber":"28772",
    "addr:postcode":"90275",
    "addr:street":"S Western Ave",
    "iso:country":"US",
    "sg:address":"28772 S Western Ave",
    "sg:city":"Rancho Pls Vrds",
    "sg:classifiers":[
        {
            "category":"Recreation",
            "type":"Entertainment"
        }
    ],
    "sg:phone":"+1 310 221 6399",
    "sg:postcode":"90275",
    "sg:province":"CA",
    "sg:tags":[
        "instruction",
        "swimming"
    ],
    "wof:name":"Australian Swim School",
    "wof:placetype":"venue"
},
  "geometry": {"coordinates":[-118.311723,33.758009],"type":"Point"}
}