{
  "type": "Feature",
  "properties": {
    "iso:country":"US",
    "sg:address":"2423 W Florence Avenue",
    "sg:city":"Los Angeles",
    "sg:classifiers":[
        {
            "category":"Retail",
            "subcategory":"Auto Repair",
            "type":"Services"
        }
    ],
    "sg:phone":"+1 323 753 4651",
    "sg:postcode":"90043",
    "sg:province":"CA",
    "wof:name":"E Z Smog Auto Care",
    "wof:placetype":"venue"
},
  "geometry": {"coordinates":[-118.320553,33.974463],"type":"Point"}
}