{
  "type": "Feature",
  "properties": {
    "iso:country":"US",
    "sg:address":"7996 Armour St",
    "sg:city":"San Diego",
    "sg:classifiers":[
        {
            "category":"Autos & Motor Vehicles",
            "subcategory":"Automobile Sales",
            "type":"Retail Goods"
        }
    ],
    "sg:phone":"+1 858 541 2274",
    "sg:postcode":"92111",
    "sg:province":"CA",
    "sg:tags":[
        "car",
        "dealer"
    ],
    "wof:name":"Southwest Auto Sales",
    "wof:placetype":"venue"
},
  "geometry": {"coordinates":[-117.15083199999999,32.820037],"type":"Point"}
}