{
  "type": "Feature",
  "properties": {
    "iso:country":"US",
    "sg:address":"50 Lakeside Dr",
    "sg:city":"Corte Madera",
    "sg:classifiers":[
        {
            "category":"Education",
            "subcategory":"Special Training",
            "type":"Public Place"
        }
    ],
    "sg:phone":"+1 415 924 6602",
    "sg:postcode":"94925",
    "sg:province":"CA",
    "sg:tags":[
        "management"
    ],
    "wof:name":"Merger Managers",
    "wof:placetype":"venue"
},
  "geometry": {"coordinates":[-122.52076700000001,37.928319],"type":"Point"}
}