{
  "type": "Feature",
  "properties": {
    "iso:country":"US",
    "sg:address":"233 E 4th St",
    "sg:city":"Calexico",
    "sg:classifiers":[
        {
            "category":"Building & Trades",
            "subcategory":"Equipment Rental",
            "type":"Services"
        }
    ],
    "sg:phone":"+1 760 768 2115",
    "sg:postcode":"92231",
    "sg:province":"CA",
    "sg:tags":[
        "disabled",
        "person",
        "supply"
    ],
    "wof:name":"Calexico Transit Senior Svc",
    "wof:placetype":"venue"
},
  "geometry": {"coordinates":[-115.495851,32.668873],"type":"Point"}
}