{
  "type": "Feature",
  "properties": {
    "iso:country":"US",
    "sg:address":"40111 Highway 41 Ste 7",
    "sg:city":"Oakhurst",
    "sg:classifiers":[
        {
            "category":"Professional",
            "subcategory":"Lawyer & Legal Services",
            "type":"Services"
        }
    ],
    "sg:phone":"+1 559 642 6661",
    "sg:postcode":"93644",
    "sg:province":"CA",
    "sg:tags":[
        "attorney",
        "practice"
    ],
    "sg:website":"http://www.countrylawyer.biz",
    "wof:name":"James Mccallion Attorney",
    "wof:placetype":"venue"
},
  "geometry": {"coordinates":[-119.646145,37.335057],"type":"Point"}
}