{
  "type": "Feature",
  "properties": {
    "addr:full":"4128 Lincoln Blvd Marina Del Rey CA 90292",
    "addr:housenumber":"4128",
    "addr:postcode":"90292",
    "addr:street":"Lincoln Blvd",
    "iso:country":"US",
    "sg:address":"4128 Lincoln Blvd",
    "sg:city":"Marina Del Rey",
    "sg:classifiers":[
        {
            "category":"Autos & Motor Vehicles",
            "subcategory":"Automobile Sales",
            "type":"Retail Goods"
        }
    ],
    "sg:phone":"+1 310 827 8665",
    "sg:postcode":"90292",
    "sg:province":"CA",
    "sg:tags":[
        "car",
        "dealer"
    ],
    "sg:website":"www.chequeredflag.com",
    "wof:name":"Chequered Flag Wholesale",
    "wof:placetype":"venue"
},
  "geometry": {"coordinates":[-118.44618199999999,33.989268],"type":"Point"}
}