{
  "type": "Feature",
  "properties": {
    "addr:full":"5544 E Grant Ave Fresno CA 93727",
    "addr:housenumber":"5544",
    "addr:postcode":"93727",
    "addr:street":"E Grant Ave",
    "iso:country":"US",
    "sg:address":"5544 E Grant Ave",
    "sg:city":"Fresno",
    "sg:classifiers":[
        {
            "category":"Home & Garden",
            "subcategory":"Household Appliances",
            "type":"Retail Goods"
        }
    ],
    "sg:phone":"+1 559 255 8854",
    "sg:postcode":"93727",
    "sg:province":"CA",
    "wof:name":"In Home Appliance Care",
    "wof:placetype":"venue"
},
  "geometry": {"coordinates":[-119.704415,36.748527],"type":"Point"}
}