{
  "type": "Feature",
  "properties": {
    "addr:full":"17312 Foothill Blvd Fontana CA 92335",
    "addr:housenumber":"17312",
    "addr:postcode":"92335",
    "addr:street":"Foothill Blvd",
    "iso:country":"US",
    "sg:address":"17312 Foothill Blvd",
    "sg:city":"Fontana",
    "sg:classifiers":[
        {
            "category":"Autos & Motor Vehicles",
            "subcategory":"Fuel & Gas Station",
            "type":"Retail Goods"
        }
    ],
    "sg:phone":"+1 909 829 2833",
    "sg:postcode":"92335",
    "sg:province":"CA",
    "sg:tags":[
        "oil"
    ],
    "wof:name":"Price Saver Gasoline Station",
    "wof:placetype":"venue"
},
  "geometry": {"coordinates":[-117.42297000000001,34.106751],"type":"Point"}
}