{
  "type": "Feature",
  "properties": {
    "addr:full":"588 Roseland Ave Santa Rosa CA 95407",
    "addr:housenumber":"588",
    "addr:postcode":"95407",
    "addr:street":"Roseland Ave",
    "iso:country":"US",
    "sg:address":"588 Roseland Ave",
    "sg:city":"Santa Rosa",
    "sg:classifiers":[
        {
            "category":"Taxi",
            "type":"Transportation"
        }
    ],
    "sg:phone":"+1 707 544 4444",
    "sg:postcode":"95407",
    "sg:province":"CA",
    "sg:tags":[
        "taxicab"
    ],
    "wof:name":"Yellow Cab Co",
    "wof:placetype":"venue"
},
  "geometry": {"coordinates":[-122.73238499999999,38.429528],"type":"Point"}
}