{
  "type": "Feature",
  "properties": {
    "iso:country":"US",
    "sg:address":"4209 W Washington Boulevard",
    "sg:city":"Los Angeles",
    "sg:classifiers":[
        {
            "category":"Restaurant",
            "type":"Food & Drink"
        }
    ],
    "sg:phone":"+1 323 735 8786",
    "sg:postcode":"90016",
    "sg:province":"CA",
    "sg:tags":[
        "chinese"
    ],
    "wof:name":"Pacific Donut & Chinese Food",
    "wof:placetype":"venue"
},
  "geometry": {"coordinates":[-118.33282,34.036689],"type":"Point"}
}