{
  "type": "Feature",
  "properties": {
    "addr:full":"2154 E 51st St Los Angeles CA 90058",
    "addr:housenumber":"2154",
    "addr:postcode":"90058",
    "addr:street":"E 51St St",
    "iso:country":"US",
    "sg:address":"2154 E 51st St",
    "sg:city":"Los Angeles",
    "sg:classifiers":[
        {
            "category":"Manufacturing",
            "subcategory":"Motor Vehicles & Parts",
            "type":"Manufacturing & Wholesale Goods"
        }
    ],
    "sg:phone":"+1 323 234 2826",
    "sg:postcode":"90058",
    "sg:province":"CA",
    "sg:tags":[
        "car"
    ],
    "wof:name":"Team USA",
    "wof:placetype":"venue"
},
  "geometry": {"coordinates":[-118.232518,33.996663],"type":"Point"}
}