{
  "type": "Feature",
  "properties": {
    "addr:full":"1445 W Chapman Ave Orange CA 92868",
    "addr:housenumber":"1445",
    "addr:postcode":"92868",
    "addr:street":"W Chapman Ave",
    "iso:country":"US",
    "sg:address":"1445 W Chapman Ave",
    "sg:city":"Orange",
    "sg:classifiers":[
        {
            "category":"Shopping",
            "subcategory":"Music",
            "type":"Retail Goods"
        }
    ],
    "sg:phone":"+1 714 939 6563",
    "sg:postcode":"92868",
    "sg:province":"CA",
    "wof:name":"Video Mart",
    "wof:placetype":"venue"
},
  "geometry": {"coordinates":[-117.866961,33.787958],"type":"Point"}
}