{
  "type": "Feature",
  "properties": {
    "iso:country":"US",
    "sg:address":"2530 Main St",
    "sg:city":"Chula Vista",
    "sg:classifiers":[
        {
            "category":"Building & Trades",
            "subcategory":"Construction",
            "type":"Services"
        }
    ],
    "sg:phone":"+1 619 428 1908",
    "sg:postcode":"91911",
    "sg:province":"CA",
    "sg:tags":[
        "erectors",
        "machinery"
    ],
    "wof:name":"Sermaq Sa De Cv",
    "wof:placetype":"venue"
},
  "geometry": {"coordinates":[-117.07843699999999,32.594868],"type":"Point"}
}