{
  "type": "Feature",
  "properties": {
    "iso:country":"US",
    "sg:address":"840 The City Dr S Ste J",
    "sg:city":"Orange",
    "sg:classifiers":[
        {
            "category":"Coffee & Tea",
            "type":"Food & Drink"
        }
    ],
    "sg:phone":"+1 714 663 8144",
    "sg:postcode":"92868",
    "sg:province":"CA",
    "wof:name":"Choco-Latte",
    "wof:placetype":"venue"
},
  "geometry": {"coordinates":[-117.890879,33.774637],"type":"Point"}
}