{
  "type": "Feature",
  "properties": {
    "addr:full":"1308 E. Chapman Ave. Fullerton CA 92831",
    "addr:housenumber":"1308",
    "addr:postcode":"92831",
    "addr:street":"E. Chapman Ave.",
    "iso:country":"US",
    "sg:address":"1308 E. Chapman Ave.",
    "sg:city":"Fullerton",
    "sg:classifiers":[
        {
            "category":"Restaurant",
            "type":"Food & Drink"
        }
    ],
    "sg:phone":"+1 714 879 5588",
    "sg:postcode":"92831",
    "sg:province":"CA",
    "sg:tags":[
        "fusion",
        "asian"
    ],
    "wof:name":"Spicy Stix",
    "wof:placetype":"venue"
},
  "geometry": {"coordinates":[-117.90482799999999,33.874107],"type":"Point"}
}