{
  "type": "Feature",
  "properties": {
    "addr:full":"530 Water St Oakland CA 94607",
    "addr:housenumber":"530",
    "addr:postcode":"94607",
    "addr:street":"Water St",
    "iso:country":"US",
    "sg:address":"530 Water St",
    "sg:city":"Oakland",
    "sg:classifiers":[
        {
            "category":"Real Estate",
            "subcategory":"Real Estate Agent",
            "type":"Services"
        }
    ],
    "sg:phone":"+1 510 465 8000",
    "sg:postcode":"94607",
    "sg:province":"CA",
    "sg:tags":[
        "broker",
        "mortgage"
    ],
    "wof:name":"BT Commercial Real Estate",
    "wof:placetype":"venue"
},
  "geometry": {"coordinates":[-122.27895599999999,37.795466],"type":"Point"}
}