{
  "type": "Feature",
  "properties": {
    "iso:country":"US",
    "sg:address":"2170 Arrow Hwy",
    "sg:city":"La Verne",
    "sg:classifiers":[
        {
            "category":"Autos & Motor Vehicles",
            "subcategory":"Auto Supplies",
            "type":"Retail Goods"
        }
    ],
    "sg:phone":"+1 909 392 9144",
    "sg:postcode":"91750",
    "sg:province":"CA",
    "wof:name":"Blue Ribbon Performance",
    "wof:placetype":"venue"
},
  "geometry": {"coordinates":[-117.770617,34.097536],"type":"Point"}
}