{
  "type": "Feature",
  "properties": {
    "iso:country":"US",
    "sg:address":"4178 Chevy Chase Dr",
    "sg:city":"Los Angeles",
    "sg:classifiers":[
        {
            "category":"Manufacturing",
            "subcategory":"Printing",
            "type":"Manufacturing & Wholesale Goods"
        }
    ],
    "sg:phone":"+1 323 245 7118",
    "sg:postcode":"90039",
    "sg:province":"CA",
    "sg:tags":[
        "printer"
    ],
    "wof:name":"Systems Trade Printers",
    "wof:placetype":"venue"
},
  "geometry": {"coordinates":[-118.265561,34.133345],"type":"Point"}
}