{
  "type": "Feature",
  "properties": {
    "addr:full":"3755 Startouch Dr Pasadena CA 91107",
    "addr:housenumber":"3755",
    "addr:postcode":"91107",
    "addr:street":"Startouch Dr",
    "iso:country":"US",
    "sg:address":"3755 Startouch Dr",
    "sg:city":"Pasadena",
    "sg:classifiers":[
        {
            "category":"Wholesale",
            "subcategory":"Fruits & Vegetables",
            "type":"Manufacturing & Wholesale Goods"
        }
    ],
    "sg:phone":"+1 626 351 5511",
    "sg:postcode":"91107",
    "sg:province":"CA",
    "wof:name":"Star Produce Inc",
    "wof:placetype":"venue"
},
  "geometry": {"coordinates":[-118.069005,34.173658],"type":"Point"}
}