{
  "type": "Feature",
  "properties": {
    "iso:country":"US",
    "sg:address":"391 W 3rd St",
    "sg:city":"Buttonwillow",
    "sg:classifiers":[
        {
            "category":"Farming",
            "subcategory":"Farm",
            "type":"Manufacturing & Wholesale Goods"
        }
    ],
    "sg:phone":"+1 661 764 5388",
    "sg:postcode":"93206",
    "sg:province":"CA",
    "sg:tags":[
        "crop",
        "general"
    ],
    "wof:name":"Delfino & Son Farms",
    "wof:placetype":"venue"
},
  "geometry": {"coordinates":[-119.474695,35.402258],"type":"Point"}
}