{
  "type": "Feature",
  "properties": {
    "addr:full":"49 Overlook Ln El Sobrante CA 94803",
    "addr:housenumber":"49",
    "addr:postcode":"94803",
    "addr:street":"Overlook Ln",
    "iso:country":"US",
    "sg:address":"49 Overlook Ln",
    "sg:city":"El Sobrante",
    "sg:classifiers":[
        {
            "category":"Wholesale",
            "subcategory":"Machinery & Supplies",
            "type":"Manufacturing & Wholesale Goods"
        }
    ],
    "sg:phone":"+1 510 223 2611",
    "sg:postcode":"94803",
    "sg:province":"CA",
    "sg:tags":[
        "equipment",
        "establishment"
    ],
    "wof:name":"Es Janitorial Supply Co",
    "wof:placetype":"venue"
},
  "geometry": {"coordinates":[-122.310241,37.981942],"type":"Point"}
}