{
  "type": "Feature",
  "properties": {
    "iso:country":"US",
    "sg:address":"2108 Caroline Ct",
    "sg:city":"Rocklin",
    "sg:classifiers":[
        {
            "category":"Professional",
            "type":"Services"
        }
    ],
    "sg:phone":"+1 916 435 4289",
    "sg:postcode":"95765",
    "sg:province":"CA",
    "wof:name":"Mike Schoenberger",
    "wof:placetype":"venue"
},
  "geometry": {"coordinates":[-121.267432,38.820323],"type":"Point"}
}