{
  "type": "Feature",
  "properties": {
    "iso:country":"US",
    "sg:address":"46 Elm Ave",
    "sg:city":"San Anselmo",
    "sg:classifiers":[
        {
            "category":"Organizations",
            "subcategory":"Non-profit Organization",
            "type":"Services"
        }
    ],
    "sg:phone":"+1 415 456 3792",
    "sg:postcode":"94960",
    "sg:province":"CA",
    "wof:name":"Citizens For Safe Golden Gate",
    "wof:placetype":"venue"
},
  "geometry": {"coordinates":[-122.576616,37.980296],"type":"Point"}
}