{
  "type": "Feature",
  "properties": {
    "addr:full":"3185 de la Cruz Blvd Santa Clara CA 95054",
    "addr:housenumber":"3185",
    "addr:postcode":"95054",
    "addr:street":"De La Cruz Blvd",
    "iso:country":"US",
    "sg:address":"3185 de la Cruz Blvd",
    "sg:city":"Santa Clara",
    "sg:classifiers":[
        {
            "category":"Manufacturing",
            "subcategory":"Tools & Machinery",
            "type":"Manufacturing & Wholesale Goods"
        }
    ],
    "sg:phone":"+1 408 970 9460",
    "sg:postcode":"95054",
    "sg:province":"CA",
    "sg:tags":[
        "machine",
        "shop"
    ],
    "wof:name":"Excel CNC Machining",
    "wof:placetype":"venue"
},
  "geometry": {"coordinates":[-121.940341,37.380209],"type":"Point"}
}