{
  "type": "Feature",
  "properties": {
    "iso:country":"US",
    "sg:address":"228 N Garfield Ave",
    "sg:city":"Monterey Park",
    "sg:classifiers":[
        {
            "category":"Health Services",
            "subcategory":"Doctor",
            "type":"Services"
        }
    ],
    "sg:phone":"+1 626 571 1175",
    "sg:postcode":"91754",
    "sg:province":"CA",
    "wof:name":"Pang C N MD",
    "wof:placetype":"venue"
},
  "geometry": {"coordinates":[-118.123001,34.064602],"type":"Point"}
}