{
  "type": "Feature",
  "properties": {
    "addr:full":"1621 Bay St Alameda CA 94501",
    "addr:housenumber":"1621",
    "addr:postcode":"94501",
    "addr:street":"Bay St",
    "iso:country":"US",
    "sg:address":"1621 Bay St",
    "sg:city":"Alameda",
    "sg:classifiers":[
        {
            "category":"Insurance",
            "subcategory":"Insurance Agent",
            "type":"Services"
        }
    ],
    "sg:phone":"+1 510 814 9903",
    "sg:postcode":"94501",
    "sg:province":"CA",
    "wof:name":"McVay Risk Consulting LLC",
    "wof:placetype":"venue"
},
  "geometry": {"coordinates":[-122.264602,37.775771],"type":"Point"}
}