{
  "type": "Feature",
  "properties": {
    "iso:country":"US",
    "sg:address":"23 Garrett Way",
    "sg:city":"Cloverdale",
    "sg:classifiers":[
        {
            "category":"Retail",
            "subcategory":"Laundry & Dry Cleaning",
            "type":"Services"
        }
    ],
    "sg:phone":"+1 707 894 3193",
    "sg:postcode":"95425",
    "sg:province":"CA",
    "sg:tags":[
        "cleaners",
        "rug",
        "carpet"
    ],
    "wof:name":"Rudy's Carpet Cleaners",
    "wof:placetype":"venue"
},
  "geometry": {"coordinates":[-123.016142,38.799405],"type":"Point"}
}