{
  "type": "Feature",
  "properties": {
    "iso:country":"US",
    "sg:address":"2527 Cam Ramon",
    "sg:city":"San Ramon",
    "sg:classifiers":[
        {
            "category":"Professional",
            "subcategory":"Computer Services",
            "type":"Services"
        }
    ],
    "sg:phone":"+1 510 351 5201",
    "sg:postcode":"94583",
    "sg:province":"CA",
    "sg:tags":[
        "processing",
        "datum"
    ],
    "wof:name":"Advantage Payroll Svc",
    "wof:placetype":"venue"
},
  "geometry": {"coordinates":[-121.964861,37.774551],"type":"Point"}
}