{
  "type": "Feature",
  "properties": {
    "iso:country":"US",
    "sg:address":"824 Blair Ave",
    "sg:city":"Calexico",
    "sg:classifiers":[
        {
            "category":"Education",
            "subcategory":"School",
            "type":"Public Place"
        }
    ],
    "sg:phone":"+1 760 768 3955",
    "sg:postcode":"92231",
    "sg:province":"CA",
    "wof:name":"De Anza Junior High",
    "wof:placetype":"venue"
},
  "geometry": {"coordinates":[-115.490441,32.672872],"type":"Point"}
}