{
  "type": "Feature",
  "properties": {
    "iso:country":"US",
    "sg:address":"11160 Avalon Blvd",
    "sg:city":"Los Angeles",
    "sg:classifiers":[
        {
            "category":"Manufacturing",
            "subcategory":"Tools & Machinery",
            "type":"Manufacturing & Wholesale Goods"
        }
    ],
    "sg:phone":"+1 323 755 1931",
    "sg:postcode":"90061",
    "sg:province":"CA",
    "sg:tags":[
        "commercial",
        "laundry",
        "mach"
    ],
    "wof:name":"Pacific Laundry Machinery Co",
    "wof:placetype":"venue"
},
  "geometry": {"coordinates":[-118.26508,33.933175],"type":"Point"}
}