{
  "type": "Feature",
  "properties": {
    "addr:full":"743 E Chapman Ave Orange CA 92866",
    "addr:housenumber":"743",
    "addr:postcode":"92866",
    "addr:street":"E Chapman Ave",
    "iso:country":"US",
    "sg:address":"743 E Chapman Ave",
    "sg:city":"Orange",
    "sg:classifiers":[
        {
            "category":"Health Services",
            "subcategory":"Doctor",
            "type":"Services"
        }
    ],
    "sg:phone":"+1 714 997 5495",
    "sg:postcode":"92866",
    "sg:province":"CA",
    "sg:tags":[
        "surgeon",
        "oral"
    ],
    "wof:name":"Ronald T Krause DDS",
    "wof:placetype":"venue"
},
  "geometry": {"coordinates":[-117.845703,33.788145],"type":"Point"}
}