{
  "type": "Feature",
  "properties": {
    "addr:full":"3207 Manhattan Ave Hermosa Beach CA 90254",
    "addr:housenumber":"3207",
    "addr:postcode":"90254",
    "addr:street":"Manhattan Ave",
    "iso:country":"US",
    "sg:address":"3207 Manhattan Ave",
    "sg:city":"Hermosa Beach",
    "sg:classifiers":[
        {
            "category":"Home & Garden",
            "subcategory":"Home Furnishings",
            "type":"Retail Goods"
        }
    ],
    "sg:phone":"+1 310 374 7650",
    "sg:postcode":"90254",
    "sg:province":"CA",
    "sg:tags":[
        "interior"
    ],
    "wof:name":"Karen Wittich Designs",
    "wof:placetype":"venue"
},
  "geometry": {"coordinates":[-118.406132,33.875783],"type":"Point"}
}