{
  "type": "Feature",
  "properties": {
    "addr:full":"226228 E Foothill Blvd Arcadia CA 91006",
    "addr:housenumber":"226228",
    "addr:postcode":"91006",
    "addr:street":"E Foothill Blvd",
    "iso:country":"US",
    "sg:address":"226228 E Foothill Blvd",
    "sg:city":"Arcadia",
    "sg:classifiers":[
        {
            "category":"Health Services",
            "subcategory":"Chiropractor",
            "type":"Services"
        }
    ],
    "sg:phone":"+1 626 357 3232",
    "sg:postcode":"91006",
    "sg:province":"CA",
    "sg:tags":[
        "chiropractic"
    ],
    "wof:name":"Larry D Mellinger Dc Faco",
    "wof:placetype":"venue"
},
  "geometry": {"coordinates":[-118.031216,34.151026],"type":"Point"}
}