{
  "type": "Feature",
  "properties": {
    "iso:country":"US",
    "sg:address":"1701 E Edinger Ave",
    "sg:city":"Santa Ana",
    "sg:classifiers":[
        {
            "category":"Retail",
            "subcategory":"Laundry & Dry Cleaning",
            "type":"Services"
        }
    ],
    "sg:phone":"+1 714 541 2600",
    "sg:postcode":"92705",
    "sg:province":"CA",
    "wof:name":"Sears",
    "wof:placetype":"venue"
},
  "geometry": {"coordinates":[-117.84367,33.7268],"type":"Point"}
}