{
  "type": "Feature",
  "properties": {
    "iso:country":"US",
    "sg:address":"2042 S Fruit Ave",
    "sg:city":"Fresno",
    "sg:classifiers":[
        {
            "category":"Organizations",
            "subcategory":"Religious Organization",
            "type":"Services"
        }
    ],
    "sg:phone":"+1 559 237 0550",
    "sg:postcode":"93706",
    "sg:province":"CA",
    "sg:tags":[
        "church"
    ],
    "wof:name":"St John Victory Fellowship Chr",
    "wof:placetype":"venue"
},
  "geometry": {"coordinates":[-119.817763,36.721716],"type":"Point"}
}