{
  "type": "Feature",
  "properties": {
    "iso:country":"US",
    "sg:address":"1037 4th Ave",
    "sg:city":"San Diego",
    "sg:classifiers":[
        {
            "category":"Travel",
            "subcategory":"Hotels & Motels",
            "type":"Entertainment"
        }
    ],
    "sg:phone":"+1 619 233 8165",
    "sg:postcode":"92101",
    "sg:province":"CA",
    "wof:name":"Plaza Hotel",
    "wof:placetype":"venue"
},
  "geometry": {"coordinates":[-117.16100299999999,32.716],"type":"Point"}
}