{
  "type": "Feature",
  "properties": {
    "addr:full":"19915 Phoenix Lake Rd Sonora CA 95370",
    "addr:housenumber":"19915",
    "addr:postcode":"95370",
    "addr:street":"Phoenix Lake Rd",
    "iso:country":"US",
    "sg:address":"19915 Phoenix Lake Rd",
    "sg:city":"Sonora",
    "sg:classifiers":[
        {
            "category":"Organizations",
            "subcategory":"Professional Association",
            "type":"Services"
        }
    ],
    "sg:phone":"+1 209 532 4648",
    "sg:postcode":"95370",
    "sg:province":"CA",
    "sg:tags":[
        "business"
    ],
    "wof:name":"California State Grange",
    "wof:placetype":"venue"
},
  "geometry": {"coordinates":[-120.330369,37.985675],"type":"Point"}
}