{
  "type": "Feature",
  "properties": {
    "iso:country":"US",
    "sg:address":"263 N Lena Rd",
    "sg:city":"San Bernardino",
    "sg:classifiers":[
        {
            "category":"Shopping",
            "type":"Retail Goods"
        }
    ],
    "sg:phone":"+1 909 381 4144",
    "sg:postcode":"92408",
    "sg:province":"CA",
    "sg:tags":[
        "pet",
        "food",
        "supply"
    ],
    "sg:website":"www.birminghamind.com",
    "wof:name":"Birmingham Industries",
    "wof:placetype":"venue"
},
  "geometry": {"coordinates":[-117.267811,34.102735],"type":"Point"}
}