{
  "type": "Feature",
  "properties": {
    "iso:country":"US",
    "sg:address":"255 E Bradley Ave",
    "sg:city":"El Cajon",
    "sg:classifiers":[
        {
            "category":"Professional",
            "type":"Services"
        }
    ],
    "sg:phone":"+1 619 593 9014",
    "sg:postcode":"92021",
    "sg:province":"CA",
    "wof:name":"Norman F & Rendo Rendon",
    "wof:placetype":"venue"
},
  "geometry": {"coordinates":[-116.958372,32.819032],"type":"Point"}
}