{
  "type": "Feature",
  "properties": {
    "iso:country":"US",
    "sg:address":"355 S Mills Rd",
    "sg:city":"Ventura",
    "sg:classifiers":[
        {
            "category":"Restaurant",
            "type":"Food & Drink"
        }
    ],
    "sg:phone":"+1 805 639 0686",
    "sg:postcode":"93003",
    "sg:province":"CA",
    "wof:name":"Super Panda Buffet",
    "wof:placetype":"venue"
},
  "geometry": {"coordinates":[-119.246663,34.267748],"type":"Point"}
}