{
  "type": "Feature",
  "properties": {
    "iso:country":"US",
    "sg:address":"2406 S Main St",
    "sg:city":"Santa Ana",
    "sg:classifiers":[
        {
            "category":"Taxi",
            "type":"Transportation"
        }
    ],
    "sg:phone":"+1 714 638 2550",
    "sg:postcode":"92707",
    "sg:province":"CA",
    "wof:name":"White and Yellow Cab",
    "wof:placetype":"venue"
},
  "geometry": {"coordinates":[-117.86799600000001,33.715199],"type":"Point"}
}