{
  "type": "Feature",
  "properties": {
    "iso:country":"US",
    "sg:address":"1899 Clayton Rd",
    "sg:city":"Concord",
    "sg:classifiers":[
        {
            "category":"Government",
            "subcategory":"Office",
            "type":"Public Place"
        }
    ],
    "sg:phone":"+1 925 680 4526",
    "sg:postcode":"94520",
    "sg:province":"CA",
    "sg:tags":[
        "federal",
        "affairs",
        "govt",
        "admin"
    ],
    "wof:name":"Us Veterans Affairs Dept",
    "wof:placetype":"venue"
},
  "geometry": {"coordinates":[-122.03391999999999,37.974274],"type":"Point"}
}