{
  "type": "Feature",
  "properties": {
    "iso:country":"US",
    "sg:address":"4826 Whittier Blvd",
    "sg:city":"Los Angeles",
    "sg:classifiers":[
        {
            "category":"Banks & Credit Unions",
            "subcategory":"Bank",
            "type":"Services"
        }
    ],
    "sg:phone":"+1 323 263 2858",
    "sg:postcode":"90022",
    "sg:province":"CA",
    "sg:tags":[
        "money",
        "order"
    ],
    "wof:name":"Giromex",
    "wof:placetype":"venue"
},
  "geometry": {"coordinates":[-118.163662,34.021665],"type":"Point"}
}