{
  "type": "Feature",
  "properties": {
    "addr:full":"5242 Westside Rd Redding CA 96001",
    "addr:housenumber":"5242",
    "addr:postcode":"96001",
    "addr:street":"Westside Rd",
    "iso:country":"US",
    "sg:address":"5242 Westside Rd",
    "sg:city":"Redding",
    "sg:classifiers":[
        {
            "category":"Retail",
            "subcategory":"Auto Repair",
            "type":"Services"
        }
    ],
    "sg:phone":"+1 530 241 1592",
    "sg:postcode":"96001",
    "sg:province":"CA",
    "sg:tags":[
        "equipment",
        "industrial",
        "general"
    ],
    "wof:name":"Jerry Fairchild Industries",
    "wof:placetype":"venue"
},
  "geometry": {"coordinates":[-122.38638,40.543147],"type":"Point"}
}