{
  "type": "Feature",
  "properties": {
    "iso:country":"US",
    "sg:address":"969 Golf Course Dr",
    "sg:city":"Rohnert Park",
    "sg:classifiers":[
        {
            "category":"Restaurant",
            "type":"Food & Drink"
        }
    ],
    "sg:phone":"+1 707 584 4818",
    "sg:postcode":"94928",
    "sg:province":"CA",
    "sg:tags":[
        "shop",
        "coffee"
    ],
    "wof:name":"Starbucks",
    "wof:placetype":"venue"
},
  "geometry": {"coordinates":[-122.692268,38.363259],"type":"Point"}
}