{
  "type": "Feature",
  "properties": {
    "iso:country":"US",
    "sg:address":"11526 Kagel Canyon St",
    "sg:city":"Sylmar",
    "sg:classifiers":[
        {
            "category":"Building & Trades",
            "subcategory":"Construction",
            "type":"Services"
        }
    ],
    "sg:phone":"+1 818 266 8180",
    "sg:postcode":"91342",
    "sg:province":"CA",
    "sg:tags":[
        "hanging",
        "contractor"
    ],
    "wof:name":"Og Custom Painting & Dctg",
    "wof:placetype":"venue"
},
  "geometry": {"coordinates":[-118.38337799999999,34.278508],"type":"Point"}
}