{
  "type": "Feature",
  "properties": {
    "iso:country":"US",
    "sg:address":"3197 Rita Ct",
    "sg:city":"Napa",
    "sg:classifiers":[
        {
            "category":"Building & Trades",
            "subcategory":"Construction",
            "type":"Services"
        }
    ],
    "sg:phone":"+1 707 224 1406",
    "sg:postcode":"94558",
    "sg:province":"CA",
    "sg:tags":[
        "dry wall",
        "contractor"
    ],
    "wof:name":"Hole In The Wall Drywall",
    "wof:placetype":"venue"
},
  "geometry": {"coordinates":[-122.30342400000001,38.316591],"type":"Point"}
}