{
  "type": "Feature",
  "properties": {
    "iso:country":"US",
    "sg:address":"909 S Broadway",
    "sg:city":"Los Angeles",
    "sg:classifiers":[
        {
            "category":"Manufacturing",
            "subcategory":"Printing",
            "type":"Manufacturing & Wholesale Goods"
        }
    ],
    "sg:phone":"+1 213 622 9904",
    "sg:postcode":"90015",
    "sg:province":"CA",
    "sg:tags":[
        "print",
        "pattern",
        "fabric",
        "on"
    ],
    "wof:name":"Roshan Trading Inc",
    "wof:placetype":"venue"
},
  "geometry": {"coordinates":[-118.25737,34.041064],"type":"Point"}
}