{
  "type": "Feature",
  "properties": {
    "iso:country":"US",
    "sg:address":"3111 Fite Cir",
    "sg:city":"Sacramento",
    "sg:classifiers":[
        {
            "category":"Professional",
            "subcategory":"Management & Consulting",
            "type":"Services"
        }
    ],
    "sg:phone":"+1 916 366 7180",
    "sg:postcode":"95827",
    "sg:province":"CA",
    "sg:tags":[
        "consultant",
        "energy",
        "conservation"
    ],
    "wof:name":"Noresco",
    "wof:placetype":"venue"
},
  "geometry": {"coordinates":[-121.323629,38.573944],"type":"Point"}
}