{
  "type": "Feature",
  "properties": {
    "iso:country":"US",
    "sg:address":"5144 Colfax Ave",
    "sg:city":"North Hollywood",
    "sg:classifiers":[
        {
            "category":"Food & Beverages",
            "subcategory":"Groceries & Convenience Stores",
            "type":"Retail Goods"
        }
    ],
    "sg:phone":"+1 818 763 3336",
    "sg:postcode":"91601",
    "sg:province":"CA",
    "wof:name":"Jaby's Liquor Junior Mkt",
    "wof:placetype":"venue"
},
  "geometry": {"coordinates":[-118.38800000000001,34.1642],"type":"Point"}
}