{
  "type": "Feature",
  "properties": {
    "iso:country":"US",
    "sg:address":"1025 University Ave",
    "sg:city":"Berkeley",
    "sg:classifiers":[
        {
            "category":"Restaurant",
            "type":"Food & Drink"
        }
    ],
    "sg:menulink":"http://www.allmenus.com/ca/berkeley/3772-maharani/menu/",
    "sg:phone":"+1 510 848 7777",
    "sg:postcode":"94710",
    "sg:province":"CA",
    "sg:tags":[
        "indian",
        "asian"
    ],
    "wof:name":"Maharani",
    "wof:placetype":"venue"
},
  "geometry": {"coordinates":[-122.293211,37.868936],"type":"Point"}
}