{
  "type": "Feature",
  "properties": {
    "addr:full":"10353 Torre Ave Cupertino CA 95014",
    "addr:housenumber":"10353",
    "addr:postcode":"95014",
    "addr:street":"Torre Ave",
    "iso:country":"US",
    "sg:address":"10353 Torre Ave",
    "sg:city":"Cupertino",
    "sg:classifiers":[
        {
            "category":"Health Services",
            "subcategory":"Doctor",
            "type":"Services"
        }
    ],
    "sg:phone":"+1 408 257 4711",
    "sg:postcode":"95014",
    "sg:province":"CA",
    "sg:tags":[
        "physician",
        "surgeon"
    ],
    "wof:name":"Atul Sheth MEDICAL Corp",
    "wof:placetype":"venue"
},
  "geometry": {"coordinates":[-122.02929,37.316169],"type":"Point"}
}