{
  "type": "Feature",
  "properties": {
    "addr:full":"10947 Olson Dr Rancho Cordova CA 95670",
    "addr:housenumber":"10947",
    "addr:postcode":"95670",
    "addr:street":"Olson Dr",
    "iso:country":"US",
    "sg:address":"10947 Olson Dr",
    "sg:city":"Rancho Cordova",
    "sg:classifiers":[
        {
            "category":"Shopping",
            "subcategory":"Clothing, Apparel, & Fashions",
            "type":"Retail Goods"
        }
    ],
    "sg:phone":"+1 916 368 5302",
    "sg:postcode":"95670",
    "sg:province":"CA",
    "sg:tags":[
        "t"
    ],
    "wof:name":"Picture Me Novelties-Wearable",
    "wof:placetype":"venue"
},
  "geometry": {"coordinates":[-121.282011,38.595622],"type":"Point"}
}