{
  "type": "Feature",
  "properties": {
    "iso:country":"US",
    "sg:address":"4703 Tidewater Ave Ste B",
    "sg:city":"Oakland",
    "sg:classifiers":[
        {
            "category":"Professional",
            "subcategory":"Engineering",
            "type":"Services"
        },
        {
            "category":"Professional",
            "subcategory":"Business Services",
            "type":"Services"
        },
        {
            "category":"Building & Trades",
            "subcategory":"Electrical",
            "type":"Services"
        },
        {
            "category":"Professional",
            "subcategory":"Management & Consulting",
            "type":"Services"
        }
    ],
    "sg:phone":"+1 510 434 9200",
    "sg:postcode":"94601",
    "sg:province":"CA",
    "sg:tags":[
        "control",
        "product",
        "consultant",
        "system",
        "controls",
        "regulator",
        "environmental",
        "ecological",
        "engineer"
    ],
    "sg:website":"http://www.psiusa.com",
    "wof:name":"Psi",
    "wof:placetype":"venue"
},
  "geometry": {"coordinates":[-122.220911,37.76323],"type":"Point"}
}