{
  "type": "Feature",
  "properties": {
    "iso:country":"US",
    "sg:address":"555 W 5th St Ste 381",
    "sg:city":"Los Angeles",
    "sg:classifiers":[
        {
            "category":"Professional",
            "subcategory":"Lawyer & Legal Services",
            "type":"Services"
        }
    ],
    "sg:phone":"+1 213 260 9787",
    "sg:postcode":"90014",
    "sg:province":"CA",
    "sg:tags":[
        "divorce",
        "law",
        "family"
    ],
    "sg:website":"losangelasdivorceattorney.org/",
    "wof:name":"LA Los Angeles Divorce Law Firm",
    "wof:placetype":"venue"
},
  "geometry": {"coordinates":[-118.253494,34.05002],"type":"Point"}
}