{
  "type": "Feature",
  "properties": {
    "addr:full":"759 Barnegat Ln Redwood City CA 94065",
    "addr:housenumber":"759",
    "addr:postcode":"94065",
    "addr:street":"Barnegat Ln",
    "iso:country":"US",
    "sg:address":"759 Barnegat Ln",
    "sg:city":"Redwood City",
    "sg:classifiers":[
        {
            "category":"Professional",
            "subcategory":"Advertising",
            "type":"Services"
        }
    ],
    "sg:phone":"+1 650 802 9010",
    "sg:postcode":"94065",
    "sg:province":"CA",
    "sg:tags":[
        "publisher"
    ],
    "wof:name":"Ad Sales Assoc",
    "wof:placetype":"venue"
},
  "geometry": {"coordinates":[-122.245401,37.535558],"type":"Point"}
}