{
  "type": "Feature",
  "properties": {
    "addr:full":"927 N Ardmore Ave Los Angeles CA 90029",
    "addr:housenumber":"927",
    "addr:postcode":"90029",
    "addr:street":"N Ardmore Ave",
    "iso:country":"US",
    "sg:address":"927 N Ardmore Ave",
    "sg:city":"Los Angeles",
    "sg:classifiers":[
        {
            "category":"Retail",
            "subcategory":"Auto Repair",
            "type":"Services"
        }
    ],
    "sg:phone":"+1 323 662 8141",
    "sg:postcode":"90029",
    "sg:province":"CA",
    "sg:tags":[
        "automobile",
        "top",
        "upholstery"
    ],
    "wof:name":"Jj Sheepskin Seat Covers",
    "wof:placetype":"venue"
},
  "geometry": {"coordinates":[-118.301936,34.087927],"type":"Point"}
}