{
  "type": "Feature",
  "properties": {
    "addr:full":"2910 E Shady Forest Ln Orange CA 92867",
    "addr:housenumber":"2910",
    "addr:postcode":"92867",
    "addr:street":"E Shady Forest Ln",
    "iso:country":"US",
    "sg:address":"2910 E Shady Forest Ln",
    "sg:city":"Orange",
    "sg:classifiers":[
        {
            "category":"Banks & Credit Unions",
            "subcategory":"Financial Services",
            "type":"Services"
        }
    ],
    "sg:phone":"+1 714 998 0855",
    "sg:postcode":"92867",
    "sg:province":"CA",
    "sg:tags":[
        "trust",
        "management"
    ],
    "wof:name":"Schulze Family Trust 05 1",
    "wof:placetype":"venue"
},
  "geometry": {"coordinates":[-117.821793,33.827969],"type":"Point"}
}