{
  "type": "Feature",
  "properties": {
    "iso:country":"US",
    "sg:address":"511 Echandia St",
    "sg:city":"Los Angeles",
    "sg:classifiers":[
        {
            "category":"Social Services",
            "type":"Services"
        }
    ],
    "sg:phone":"+1 323 221 4000",
    "sg:postcode":"90033",
    "sg:province":"CA",
    "sg:tags":[
        "organization",
        "welfare"
    ],
    "wof:name":"Centro CSO",
    "wof:placetype":"venue"
},
  "geometry": {"coordinates":[-118.21835299999999,34.052592],"type":"Point"}
}