{
  "type": "Feature",
  "properties": {
    "addr:full":"775 N Virgil Ave Los Angeles CA 90029",
    "addr:housenumber":"775",
    "addr:postcode":"90029",
    "addr:street":"N Virgil Ave",
    "iso:country":"US",
    "sg:address":"775 N Virgil Ave",
    "sg:city":"Los Angeles",
    "sg:classifiers":[
        {
            "category":"Organizations",
            "subcategory":"Religious Organization",
            "type":"Services"
        }
    ],
    "sg:phone":"+1 323 663 8033",
    "sg:postcode":"90029",
    "sg:province":"CA",
    "sg:tags":[
        "church"
    ],
    "wof:name":"Iglesia De Dios Pentecostal",
    "wof:placetype":"venue"
},
  "geometry": {"coordinates":[-118.28692100000001,34.085124],"type":"Point"}
}