{
  "type": "Feature",
  "properties": {
    "addr:full":"756 Greenwood Ave San Bernardino CA 92407",
    "addr:housenumber":"756",
    "addr:postcode":"92407",
    "addr:street":"Greenwood Ave",
    "iso:country":"US",
    "sg:address":"756 Greenwood Ave",
    "sg:city":"San Bernardino",
    "sg:classifiers":[
        {
            "category":"Professional",
            "subcategory":"Engineering",
            "type":"Services"
        }
    ],
    "sg:phone":"+1 909 887 8448",
    "sg:postcode":"92407",
    "sg:province":"CA",
    "sg:tags":[
        "general",
        "contractor"
    ],
    "wof:name":"MDS Construction",
    "wof:placetype":"venue"
},
  "geometry": {"coordinates":[-117.420529,34.239311],"type":"Point"}
}