{
  "type": "Feature",
  "properties": {
    "addr:full":"11721 Westminster Ave Ste 1A Garden Grove CA 92843",
    "addr:housenumber":"11721",
    "addr:postcode":"92843",
    "addr:street":"Westminster Ave Ste 1A",
    "iso:country":"US",
    "sg:address":"11721 Westminster Ave Ste 1A",
    "sg:city":"Garden Grove",
    "sg:classifiers":[
        {
            "category":"Retail",
            "subcategory":"Auto Repair",
            "type":"Services"
        }
    ],
    "sg:phone":"+1 714 530 4430",
    "sg:postcode":"92843",
    "sg:province":"CA",
    "wof:name":"Tac Auto Rep",
    "wof:placetype":"venue"
},
  "geometry": {"coordinates":[-117.925003,33.759899],"type":"Point"}
}