{
  "type": "Feature",
  "properties": {
    "iso:country":"US",
    "sg:address":"6010 Little Creek Rd",
    "sg:city":"Yreka",
    "sg:classifiers":[
        {
            "category":"Farming",
            "subcategory":"Livestock Farm",
            "type":"Manufacturing & Wholesale Goods"
        }
    ],
    "sg:phone":"+1 530 842 3504",
    "sg:postcode":"96097",
    "sg:province":"CA",
    "sg:tags":[
        "specialty",
        "animal"
    ],
    "wof:name":"Eba Oaks Alpacas",
    "wof:placetype":"venue"
},
  "geometry": {"coordinates":[-122.622356,41.655589],"type":"Point"}
}