{
  "type": "Feature",
  "properties": {
    "addr:full":"4740 Bryson St Anaheim CA 92807",
    "addr:housenumber":"4740",
    "addr:postcode":"92807",
    "addr:street":"Bryson St",
    "iso:country":"US",
    "sg:address":"4740 Bryson St",
    "sg:city":"Anaheim",
    "sg:classifiers":[
        {
            "category":"Building & Trades",
            "subcategory":"Construction",
            "type":"Services"
        }
    ],
    "sg:phone":"+1 714 630 8894",
    "sg:postcode":"92807",
    "sg:province":"CA",
    "sg:tags":[
        "concrete",
        "contractor"
    ],
    "wof:name":"Loop Masters Inc",
    "wof:placetype":"venue"
},
  "geometry": {"coordinates":[-117.814925,33.862486],"type":"Point"}
}