{
  "type": "Feature",
  "properties": {
    "iso:country":"US",
    "sg:address":"1321 E Colorado St Ste C",
    "sg:city":"Glendale",
    "sg:classifiers":[
        {
            "category":"Restaurant",
            "type":"Food & Drink"
        }
    ],
    "sg:phone":"+1 818 247 5555",
    "sg:postcode":"91205",
    "sg:province":"CA",
    "sg:tags":[
        "pizza"
    ],
    "sg:website":"www.pizzaboy.us",
    "wof:name":"Pizza Boy",
    "wof:placetype":"venue"
},
  "geometry": {"coordinates":[-118.23666299999999,34.142685],"type":"Point"}
}