{
  "type": "Feature",
  "properties": {
    "iso:country":"US",
    "sg:address":"1610 Scott Street",
    "sg:city":"San Francisco",
    "sg:classifiers":[
        {
            "category":"Health Services",
            "subcategory":"Doctor",
            "type":"Services"
        }
    ],
    "sg:phone":"+1 415 929 0700",
    "sg:postcode":"94115",
    "sg:province":"CA",
    "sg:tags":[
        "psychiatrist"
    ],
    "wof:name":"Leary Jeanne M MD",
    "wof:placetype":"venue"
},
  "geometry": {"coordinates":[-122.43800400000001,37.785],"type":"Point"}
}