{
  "type": "Feature",
  "properties": {
    "iso:country":"US",
    "sg:address":"223 E 17th St",
    "sg:city":"Costa Mesa",
    "sg:classifiers":[
        {
            "category":"Shopping",
            "subcategory":"Jewelry",
            "type":"Retail Goods"
        }
    ],
    "sg:phone":"+1 949 650 1780",
    "sg:postcode":"92627",
    "sg:province":"CA",
    "sg:tags":[
        "jeweler"
    ],
    "wof:name":"Century Gems & Design",
    "wof:placetype":"venue"
},
  "geometry": {"coordinates":[-117.91776900000001,33.634705],"type":"Point"}
}