{
  "type": "Feature",
  "properties": {
    "addr:full":"791 Taft Ave Albany CA 94706",
    "addr:housenumber":"791",
    "addr:postcode":"94706",
    "addr:street":"Taft Ave",
    "iso:country":"US",
    "sg:address":"791 Taft Ave",
    "sg:city":"Albany",
    "sg:classifiers":[
        {
            "category":"Professional",
            "subcategory":"Management & Consulting",
            "type":"Services"
        },
        {
            "category":"Health Services",
            "subcategory":"Health Practitioner",
            "type":"Services"
        }
    ],
    "sg:phone":"+1 510 393 0437",
    "sg:postcode":"94706",
    "sg:province":"CA",
    "sg:tags":[
        "nutritionist",
        "life",
        "coach"
    ],
    "sg:website":"www.jamieliving.com",
    "wof:name":"Jamie G Dougherty",
    "wof:placetype":"venue"
},
  "geometry": {"coordinates":[-122.30335700000001,37.893572],"type":"Point"}
}