{
  "type": "Feature",
  "properties": {
    "addr:full":"24251 Rd 148 Tulare CA 93274",
    "addr:housenumber":"24251",
    "addr:postcode":"93274",
    "addr:street":"Rd 148",
    "iso:country":"US",
    "sg:address":"24251 Rd 148",
    "sg:city":"Tulare",
    "sg:phone":"+1 559 686 9424",
    "sg:postcode":"93274",
    "sg:province":"CA",
    "sg:tags":[
        "building",
        "field",
        "nonresidential",
        "farm",
        "corn",
        "crop",
        "opera"
    ],
    "wof:name":"Van Tol Farm",
    "wof:placetype":"venue"
},
  "geometry": {"coordinates":[-119.242519,36.239334],"type":"Point"}
}