{
  "type": "Feature",
  "properties": {
    "addr:full":"1757 Hayes St San Francisco CA 94117",
    "addr:housenumber":"1757",
    "addr:postcode":"94117",
    "addr:street":"Hayes St",
    "iso:country":"US",
    "sg:address":"1757 Hayes St",
    "sg:city":"San Francisco",
    "sg:classifiers":[
        {
            "category":"Professional",
            "type":"Services"
        }
    ],
    "sg:phone":"+1 415 931 8399",
    "sg:postcode":"94117",
    "sg:province":"CA",
    "wof:name":"Zulu Pacific",
    "wof:placetype":"venue"
},
  "geometry": {"coordinates":[-122.445318,37.773983],"type":"Point"}
}