{
  "type": "Feature",
  "properties": {
    "iso:country":"US",
    "sg:address":"1315 Ruberta Ave",
    "sg:city":"Glendale",
    "sg:classifiers":[
        {
            "category":"Professional",
            "subcategory":"Management & Consulting",
            "type":"Services"
        }
    ],
    "sg:phone":"+1 818 243 4864",
    "sg:postcode":"91201",
    "sg:province":"CA",
    "sg:tags":[
        "consultant",
        "business"
    ],
    "wof:name":"International Fieldworks Inc",
    "wof:placetype":"venue"
},
  "geometry": {"coordinates":[-118.28182099999999,34.173705],"type":"Point"}
}