{
  "type": "Feature",
  "properties": {
    "addr:full":"2020 Standiford Ave Modesto CA 95350",
    "addr:housenumber":"2020",
    "addr:postcode":"ca 95350",
    "addr:street":"Standiford Ave",
    "iso:country":"US",
    "sg:address":"2020 Standiford Ave",
    "sg:city":"Modesto",
    "sg:classifiers":[
        {
            "category":"Health Services",
            "subcategory":"Doctor",
            "type":"Services"
        }
    ],
    "sg:phone":"+1 209 529 1698",
    "sg:postcode":"95350",
    "sg:province":"CA",
    "sg:tags":[
        "dentist"
    ],
    "wof:name":"Lakeview Endodontics",
    "wof:placetype":"venue"
},
  "geometry": {"coordinates":[-121.03112,37.689546],"type":"Point"}
}