{
  "type": "Feature",
  "properties": {
    "iso:country":"US",
    "sg:address":"23733 la Salle Canyon Rd",
    "sg:city":"Newhall",
    "sg:classifiers":[
        {
            "category":"Insurance",
            "subcategory":"Insurance Agent",
            "type":"Services"
        }
    ],
    "sg:phone":"+1 661 290 2547",
    "sg:postcode":"91321",
    "sg:province":"CA",
    "sg:tags":[
        "adjuster"
    ],
    "wof:name":"Adjusters Unlimited",
    "wof:placetype":"venue"
},
  "geometry": {"coordinates":[-118.55189300000001,34.360786],"type":"Point"}
}