{
  "type": "Feature",
  "properties": {
    "addr:full":"10049 Campo Rd Spring Valley CA 91977",
    "addr:housenumber":"10049",
    "addr:postcode":"91977",
    "addr:street":"Campo Rd",
    "iso:country":"US",
    "sg:address":"10049 Campo Rd",
    "sg:city":"Spring Valley",
    "sg:classifiers":[
        {
            "category":"Food & Beverages",
            "subcategory":"Groceries & Convenience Stores",
            "type":"Retail Goods"
        }
    ],
    "sg:phone":"+1 619 670 7100",
    "sg:postcode":"91977",
    "sg:province":"CA",
    "wof:name":"7-Eleven",
    "wof:placetype":"venue"
},
  "geometry": {"coordinates":[-116.975713,32.745264],"type":"Point"}
}