{
  "type": "Feature",
  "properties": {
    "addr:full":"338 London St San Francisco CA 94112",
    "addr:housenumber":"338",
    "addr:postcode":"94112",
    "addr:street":"London St",
    "iso:country":"US",
    "sg:address":"338 London St",
    "sg:city":"San Francisco",
    "sg:classifiers":[
        {
            "category":"Organizations",
            "subcategory":"Professional Association",
            "type":"Services"
        }
    ],
    "sg:phone":"+1 415 585 6018",
    "sg:postcode":"94112",
    "sg:province":"CA",
    "wof:name":"National Association-Prchsng",
    "wof:placetype":"venue"
},
  "geometry": {"coordinates":[-122.434912,37.723404],"type":"Point"}
}