{
  "type": "Feature",
  "properties": {
    "iso:country":"US",
    "sg:address":"24201 Valencia Blvd Ste 145",
    "sg:city":"Santa Clarita",
    "sg:classifiers":[
        {
            "category":"Shopping",
            "subcategory":"Clothing, Apparel, & Fashions",
            "type":"Retail Goods"
        }
    ],
    "sg:phone":"+1 661 288 0363",
    "sg:postcode":"91355",
    "sg:province":"CA",
    "sg:tags":[
        "accessory",
        "clothing",
        "women's"
    ],
    "sg:website":"www.anntaylor.com",
    "wof:name":"Ann Taylor",
    "wof:placetype":"venue"
},
  "geometry": {"coordinates":[-118.557683,34.413351],"type":"Point"}
}