{
  "type": "Feature",
  "properties": {
    "addr:full":"2355 Westwood Blvd Los Angeles CA 90064",
    "addr:housenumber":"2355",
    "addr:postcode":"90064",
    "addr:street":"Westwood Blvd",
    "iso:country":"US",
    "sg:address":"2355 Westwood Blvd",
    "sg:city":"Los Angeles",
    "sg:classifiers":[
        {
            "category":"Real Estate",
            "subcategory":"Real Estate Services",
            "type":"Services"
        }
    ],
    "sg:phone":"+1 888 868 6156",
    "sg:postcode":"90064",
    "sg:province":"CA",
    "sg:website":"www.jrealty.org",
    "wof:name":"JRealty",
    "wof:placetype":"venue"
},
  "geometry": {"coordinates":[-118.429765,34.041082],"type":"Point"}
}