{
  "type": "Feature",
  "properties": {
    "addr:full":"3100 Lakeville Hwy Ste B Petaluma CA 94954",
    "addr:postcode":"3100;94954",
    "addr:street":"Lakeville Hwy Ste B",
    "iso:country":"US",
    "sg:address":"3100 Lakeville Hwy Ste B",
    "sg:city":"Petaluma",
    "sg:classifiers":[
        {
            "category":"Utilities",
            "subcategory":"Mobile Phone",
            "type":"Services"
        },
        {
            "category":"Coffee & Tea",
            "type":"Food & Drink"
        }
    ],
    "sg:phone":"+1 707 775 3708",
    "sg:postcode":"94954",
    "sg:province":"CA",
    "sg:tags":[
        "shop",
        "wi-fi",
        "espresso",
        "hotspot",
        "restaurant"
    ],
    "sg:website":"http://www.starbuckscoffee.com",
    "wof:name":"Starbucks Coffee",
    "wof:placetype":"venue"
},
  "geometry": {"coordinates":[-122.595933,38.23448],"type":"Point"}
}