{
  "type": "Feature",
  "properties": {
    "addr:full":"3637 Honeyglen Way Ontario CA 91761",
    "addr:housenumber":"3637",
    "addr:postcode":"91761",
    "addr:street":"Honeyglen Way",
    "iso:country":"US",
    "sg:address":"3637 Honeyglen Way",
    "sg:city":"Ontario",
    "sg:classifiers":[
        {
            "category":"Professional",
            "subcategory":"Management & Consulting",
            "type":"Services"
        }
    ],
    "sg:phone":"+1 909 947 4859",
    "sg:postcode":"91761",
    "sg:province":"CA",
    "sg:tags":[
        "environmental",
        "drilling"
    ],
    "wof:name":"SC Environmental Inc",
    "wof:placetype":"venue"
},
  "geometry": {"coordinates":[-117.572124,34.024992],"type":"Point"}
}