{
  "type": "Feature",
  "properties": {
    "iso:country":"US",
    "sg:address":"1027 76th Ave",
    "sg:city":"Oakland",
    "sg:classifiers":[
        {
            "category":"Wholesale",
            "subcategory":"Construction Materials",
            "type":"Manufacturing & Wholesale Goods"
        }
    ],
    "sg:phone":"+1 510 638 3721",
    "sg:postcode":"94621",
    "sg:province":"CA",
    "sg:tags":[
        "granite"
    ],
    "wof:name":"Galaxy Stone",
    "wof:placetype":"venue"
},
  "geometry": {"coordinates":[-122.189683,37.755066],"type":"Point"}
}