{
  "type": "Feature",
  "properties": {
    "iso:country":"US",
    "sg:address":"568 S Mathilda Ave",
    "sg:city":"Sunnyvale",
    "sg:classifiers":[
        {
            "category":"Professional",
            "subcategory":"Computer Services",
            "type":"Services"
        }
    ],
    "sg:phone":"+1 408 530 8324",
    "sg:postcode":"94086",
    "sg:province":"CA",
    "sg:tags":[
        "internet"
    ],
    "sg:website":"www.ubergeekmail.com",
    "wof:name":"Xeno Technology",
    "wof:placetype":"venue"
},
  "geometry": {"coordinates":[-122.036902,37.369438],"type":"Point"}
}