{
  "type": "Feature",
  "properties": {
    "addr:full":"179 Diza Rd San Diego CA 92173",
    "addr:housenumber":"179",
    "addr:postcode":"92173",
    "addr:street":"Diza Rd",
    "iso:country":"US",
    "sg:address":"179 Diza Rd",
    "sg:city":"San Diego",
    "sg:classifiers":[
        {
            "category":"Government",
            "subcategory":"Office",
            "type":"Public Place"
        }
    ],
    "sg:phone":"+1 619 424 0472",
    "sg:postcode":"92173",
    "sg:province":"CA",
    "sg:tags":[
        "village"
    ],
    "wof:name":"San Ysidro Activity Ctr",
    "wof:placetype":"venue"
},
  "geometry": {"coordinates":[-117.044758,32.564978],"type":"Point"}
}