{
  "type": "Feature",
  "properties": {
    "addr:full":"112 W Union Ave Fullerton CA 92832",
    "addr:housenumber":"112",
    "addr:postcode":"92832",
    "addr:street":"W Union Ave",
    "iso:country":"US",
    "sg:address":"112 W Union Ave",
    "sg:city":"Fullerton",
    "sg:classifiers":[
        {
            "category":"Wholesale",
            "subcategory":"Office Equipment",
            "type":"Manufacturing & Wholesale Goods"
        }
    ],
    "sg:phone":"+1 562 220 3715",
    "sg:postcode":"92832",
    "sg:province":"CA",
    "sg:tags":[
        "product",
        "mfr",
        "rep"
    ],
    "wof:name":"Specialty Office Products",
    "wof:placetype":"venue"
},
  "geometry": {"coordinates":[-117.92461299999999,33.877359],"type":"Point"}
}