{
  "type": "Feature",
  "properties": {
    "addr:full":"2675 Alderwood Dr San Jose CA 95132",
    "addr:housenumber":"2675",
    "addr:postcode":"95132",
    "addr:street":"Alderwood Dr",
    "iso:country":"US",
    "sg:address":"2675 Alderwood Dr",
    "sg:city":"San Jose",
    "sg:classifiers":[
        {
            "category":"Building & Trades",
            "subcategory":"Cleaning & Sanitation",
            "type":"Services"
        }
    ],
    "sg:phone":"+1 408 945 9764",
    "sg:postcode":"95132",
    "sg:province":"CA",
    "sg:tags":[
        "house"
    ],
    "wof:name":"Goldstar Cleaning Svc",
    "wof:placetype":"venue"
},
  "geometry": {"coordinates":[-121.885047,37.406338],"type":"Point"}
}