{
  "type": "Feature",
  "properties": {
    "iso:country":"US",
    "sg:address":"2107 N Broadway",
    "sg:city":"Santa Ana",
    "sg:classifiers":[
        {
            "category":"Professional",
            "subcategory":"Lawyer & Legal Services",
            "type":"Services"
        }
    ],
    "sg:phone":"+1 714 542 4300",
    "sg:postcode":"92706",
    "sg:province":"CA",
    "wof:name":"Morrison & LaRossa Attorneys",
    "wof:placetype":"venue"
},
  "geometry": {"coordinates":[-117.869392,33.764205],"type":"Point"}
}