{
  "type": "Feature",
  "properties": {
    "addr:full":"500 1st St Davis CA 95616",
    "addr:housenumber":"500",
    "addr:postcode":"95616",
    "addr:street":"1St St",
    "iso:country":"US",
    "sg:address":"500 1st St",
    "sg:city":"Davis",
    "sg:classifiers":[
        {
            "category":"Shopping",
            "subcategory":"Gifts & Souvenirs",
            "type":"Retail Goods"
        }
    ],
    "sg:phone":"+1 530 792 0100",
    "sg:postcode":"95616",
    "sg:province":"CA",
    "sg:tags":[
        "cards",
        "greeting"
    ],
    "wof:name":"Papyrus",
    "wof:placetype":"venue"
},
  "geometry": {"coordinates":[-121.740702,38.541949],"type":"Point"}
}