{
  "type": "Feature",
  "properties": {
    "addr:full":"1484 Pollard Rd Los Gatos CA 95032",
    "addr:housenumber":"1484",
    "addr:postcode":"95032",
    "addr:street":"Pollard Rd",
    "iso:country":"US",
    "sg:address":"1484 Pollard Rd",
    "sg:city":"Los Gatos",
    "sg:classifiers":[
        {
            "category":"Professional",
            "subcategory":"Lawyer & Legal Services",
            "type":"Services"
        }
    ],
    "sg:phone":"+1 408 374 9255",
    "sg:postcode":"95032",
    "sg:province":"CA",
    "sg:tags":[
        "notary"
    ],
    "wof:name":"PostalAnnex+",
    "wof:placetype":"venue"
},
  "geometry": {"coordinates":[-121.983116,37.26459],"type":"Point"}
}