{
  "type": "Feature",
  "properties": {
    "addr:full":"5153 W 134th Pl Hawthorne CA 90250",
    "addr:housenumber":"5153",
    "addr:postcode":"90250",
    "addr:street":"W 134Th Pl",
    "iso:country":"US",
    "sg:address":"5153 W 134th Pl",
    "sg:city":"Hawthorne",
    "sg:classifiers":[
        {
            "category":"Social Services",
            "subcategory":"Adult Care",
            "type":"Services"
        }
    ],
    "sg:phone":"+1 310 675 4366",
    "sg:postcode":"90250",
    "sg:province":"CA",
    "sg:tags":[
        "residential"
    ],
    "wof:name":"Sunshine Board and Care Fcilty",
    "wof:placetype":"venue"
},
  "geometry": {"coordinates":[-118.368458,33.910418],"type":"Point"}
}