{
  "type": "Feature",
  "properties": {
    "iso:country":"US",
    "sg:address":"3630 Modesto Dr",
    "sg:city":"San Bernardino",
    "sg:classifiers":[
        {
            "category":"Shopping",
            "subcategory":"Catalog Store",
            "type":"Retail Goods"
        }
    ],
    "sg:phone":"+1 909 886 9943",
    "sg:postcode":"92404",
    "sg:province":"CA",
    "sg:tags":[
        "show",
        "doll",
        "trade",
        "mail",
        "accessory",
        "order"
    ],
    "wof:name":"Pjs Dolls",
    "wof:placetype":"venue"
},
  "geometry": {"coordinates":[-117.26082100000001,34.156947],"type":"Point"}
}