{
  "type": "Feature",
  "properties": {
    "addr:full":"122 S Atlantic Blvd Monterey Park CA 91754",
    "addr:housenumber":"122",
    "addr:postcode":"91754",
    "addr:street":"S Atlantic Blvd",
    "iso:country":"US",
    "sg:address":"122 S Atlantic Blvd",
    "sg:city":"Monterey Park",
    "sg:classifiers":[
        {
            "category":"Restaurant",
            "type":"Food & Drink"
        },
        {
            "category":"Wholesale",
            "subcategory":"Home Furnishings",
            "type":"Manufacturing & Wholesale Goods"
        }
    ],
    "sg:phone":"+1 626 282 9829",
    "sg:postcode":"91754",
    "sg:province":"CA",
    "sg:tags":[
        "plate",
        "bar",
        "sushi",
        "fusion",
        "asian",
        "tapas/small"
    ],
    "wof:name":"The Open Door",
    "wof:placetype":"venue"
},
  "geometry": {"coordinates":[-118.134154,34.061591],"type":"Point"}
}