{
  "type": "Feature",
  "properties": {
    "addr:full":"7333 Coldwater Canyon Ave North Hollywood CA 91605",
    "addr:housenumber":"7333",
    "addr:postcode":"91605",
    "addr:street":"Coldwater Canyon Ave",
    "iso:country":"US",
    "sg:address":"7333 Coldwater Canyon Ave",
    "sg:city":"North Hollywood",
    "sg:classifiers":[
        {
            "category":"Manufacturing",
            "subcategory":"Metals",
            "type":"Manufacturing & Wholesale Goods"
        }
    ],
    "sg:phone":"+1 818 765 0163",
    "sg:postcode":"91605",
    "sg:province":"CA",
    "sg:tags":[
        "metalwork",
        "ornamental",
        "work",
        "architectural",
        "mfg"
    ],
    "wof:name":"Isaac Anaya",
    "wof:placetype":"venue"
},
  "geometry": {"coordinates":[-118.413866,34.203516],"type":"Point"}
}