{
  "type": "Feature",
  "properties": {
    "addr:full":"627 N San Gabriel Ave Azusa CA 91702",
    "addr:housenumber":"627",
    "addr:postcode":"91702",
    "addr:street":"N San Gabriel Ave",
    "iso:country":"US",
    "sg:address":"627 N San Gabriel Ave",
    "sg:city":"Azusa",
    "sg:classifiers":[
        {
            "category":"Real Estate",
            "subcategory":"Real Estate Services",
            "type":"Services"
        },
        {
            "category":"Real Estate",
            "subcategory":"Real Estate Agent",
            "type":"Services"
        }
    ],
    "sg:phone":"+1 626 633 0881",
    "sg:postcode":"91702",
    "sg:province":"CA",
    "sg:tags":[
        "buyer",
        "management",
        "broker"
    ],
    "wof:name":"California 2000 Realty",
    "wof:placetype":"venue"
},
  "geometry": {"coordinates":[-117.90882499999999,34.13214],"type":"Point"}
}