{
  "type": "Feature",
  "properties": {
    "addr:full":"490 Atascadero Rd Morro Bay CA 93442",
    "addr:housenumber":"490",
    "addr:postcode":"93442",
    "addr:street":"Atascadero Rd",
    "iso:country":"US",
    "sg:address":"490 Atascadero Rd",
    "sg:city":"Morro Bay",
    "sg:classifiers":[
        {
            "category":"Building & Trades",
            "subcategory":"Construction",
            "type":"Services"
        }
    ],
    "sg:phone":"+1 805 772 1613",
    "sg:postcode":"93442",
    "sg:province":"CA",
    "sg:tags":[
        "painter"
    ],
    "wof:name":"Stan Kraft Painting",
    "wof:placetype":"venue"
},
  "geometry": {"coordinates":[-120.85376599999999,35.380497],"type":"Point"}
}