{
  "type": "Feature",
  "properties": {
    "addr:full":"216 W Merced St Fowler CA 93625",
    "addr:housenumber":"216",
    "addr:postcode":"93625",
    "addr:street":"W Merced St",
    "iso:country":"US",
    "sg:address":"216 W Merced St",
    "sg:city":"Fowler",
    "sg:classifiers":[
        {
            "category":"Coffee & Tea",
            "type":"Food & Drink"
        }
    ],
    "sg:menulink":"http://www.allmenus.com/ca/fowler/110968-starbucks-coffee/menu/",
    "sg:phone":"+1 559 834 3206",
    "sg:postcode":"93625",
    "sg:province":"CA",
    "sg:tags":[
        "american"
    ],
    "wof:name":"Starbucks Coffee",
    "wof:placetype":"venue"
},
  "geometry": {"coordinates":[-119.68232999999999,36.628049],"type":"Point"}
}