{
  "type": "Feature",
  "properties": {
    "addr:full":"5493 Carlson Drive Suite B Sacramento CA 95819",
    "addr:housenumber":"5493",
    "addr:postcode":"95819",
    "addr:street":"Carlson Drive Suite B",
    "iso:country":"US",
    "sg:address":"5493 Carlson Drive Suite B",
    "sg:city":"Sacramento",
    "sg:classifiers":[
        {
            "category":"Personal",
            "subcategory":"Barber",
            "type":"Services"
        }
    ],
    "sg:phone":"+1 916 455 8326",
    "sg:postcode":"95819",
    "sg:province":"CA",
    "sg:website":"zeeandcompany.com/",
    "wof:name":"Mr Zee & Company",
    "wof:placetype":"venue"
},
  "geometry": {"coordinates":[-121.432389,38.572287],"type":"Point"}
}