{
  "type": "Feature",
  "properties": {
    "addr:full":"2210 S Loara St Apt E Anaheim CA 92802",
    "addr:housenumber":"2210",
    "addr:postcode":"92802",
    "addr:street":"S Loara St Apt E",
    "iso:country":"US",
    "sg:address":"2210 S Loara St Apt E",
    "sg:city":"Anaheim",
    "sg:classifiers":[
        {
            "category":"Communications",
            "type":"Services"
        }
    ],
    "sg:phone":"+1 714 537 2898",
    "sg:postcode":"92802",
    "sg:province":"CA",
    "sg:tags":[
        "consultant",
        "telecommunication"
    ],
    "wof:name":"Anacal Mlm",
    "wof:placetype":"venue"
},
  "geometry": {"coordinates":[-117.93692799999999,33.794472],"type":"Point"}
}