{
  "type": "Feature",
  "properties": {
    "addr:full":"1139 San Carlos Ave San Carlos CA 94070",
    "addr:housenumber":"1139",
    "addr:postcode":"94070",
    "addr:street":"San Carlos Ave",
    "iso:country":"US",
    "sg:address":"1139 San Carlos Ave",
    "sg:city":"San Carlos",
    "sg:classifiers":[
        {
            "category":"Health Services",
            "subcategory":"Hospital",
            "type":"Services"
        }
    ],
    "sg:phone":"+1 650 631 1139",
    "sg:postcode":"94070",
    "sg:province":"CA",
    "sg:tags":[
        "specialty"
    ],
    "wof:name":"Humrich Kiki",
    "wof:placetype":"venue"
},
  "geometry": {"coordinates":[-122.260835,37.506757],"type":"Point"}
}