{
  "type": "Feature",
  "properties": {
    "addr:full":"1029 N Azusa Ave Covina CA 91722",
    "addr:housenumber":"1029",
    "addr:postcode":"91722",
    "addr:street":"N Azusa Ave",
    "iso:country":"US",
    "sg:address":"1029 N Azusa Ave",
    "sg:city":"Covina",
    "sg:classifiers":[
        {
            "category":"Food & Beverages",
            "subcategory":"Liquor & Beverages",
            "type":"Retail Goods"
        }
    ],
    "sg:phone":"+1 626 332 6689",
    "sg:postcode":"91722",
    "sg:province":"CA",
    "sg:tags":[
        "alcoholic"
    ],
    "wof:name":"Starlite Liquor",
    "wof:placetype":"venue"
},
  "geometry": {"coordinates":[-117.907723,34.097007],"type":"Point"}
}