{
  "type": "Feature",
  "properties": {
    "iso:country":"US",
    "sg:address":"3602 Eagle Rock Blvd",
    "sg:city":"Los Angeles",
    "sg:classifiers":[
        {
            "category":"Education",
            "subcategory":"Preschool",
            "type":"Public Place"
        }
    ],
    "sg:phone":"+1 323 258 4525",
    "sg:postcode":"90065",
    "sg:province":"CA",
    "sg:website":"www.thegarden.la",
    "wof:name":"The Garden Cooperative Nursery School",
    "wof:placetype":"venue"
},
  "geometry": {"coordinates":[-118.234874,34.11667],"type":"Point"}
}