{
  "type": "Feature",
  "properties": {
    "iso:country":"US",
    "sg:address":"5275 W Washington Blvd",
    "sg:city":"Los Angeles",
    "sg:classifiers":[
        {
            "category":"Building & Trades",
            "subcategory":"Construction",
            "type":"Services"
        }
    ],
    "sg:phone":"+1 323 936 3603",
    "sg:postcode":"90016",
    "sg:province":"CA",
    "sg:tags":[
        "maker",
        "cabinet"
    ],
    "wof:name":"Martin & Carter Inc",
    "wof:placetype":"venue"
},
  "geometry": {"coordinates":[-118.357134,34.040878],"type":"Point"}
}