{
  "type": "Feature",
  "properties": {
    "addr:full":"4095 Avenida de la Plata Oceanside CA 92056",
    "addr:housenumber":"4095",
    "addr:postcode":"92056",
    "addr:street":"Avenida De La Plata",
    "iso:country":"US",
    "sg:address":"4095 Avenida de la Plata",
    "sg:city":"Oceanside",
    "sg:classifiers":[
        {
            "category":"Real Estate",
            "subcategory":"Real Estate Services",
            "type":"Services"
        },
        {
            "category":"Banks & Credit Unions",
            "subcategory":"Financial Services",
            "type":"Services"
        }
    ],
    "sg:phone":"+1 760 732 1200",
    "sg:postcode":"92056",
    "sg:province":"CA",
    "sg:tags":[
        "loan",
        "financing"
    ],
    "wof:name":"Hmc Funding",
    "wof:placetype":"venue"
},
  "geometry": {"coordinates":[-117.294371,33.208714],"type":"Point"}
}