{
  "type": "Feature",
  "properties": {
    "addr:full":"480 Old Newport Blvd Newport Beach CA 92663",
    "addr:housenumber":"480",
    "addr:postcode":"92663",
    "addr:street":"Old Newport Blvd",
    "iso:country":"US",
    "sg:address":"480 Old Newport Blvd",
    "sg:city":"Newport Beach",
    "sg:classifiers":[
        {
            "category":"Shopping",
            "subcategory":"Computers & Home Electronics",
            "type":"Retail Goods"
        }
    ],
    "sg:phone":"+1 949 650 4445",
    "sg:postcode":"92663",
    "sg:province":"CA",
    "sg:website":"www.newportav.com",
    "wof:name":"Newport Audio & Video",
    "wof:placetype":"venue"
},
  "geometry": {"coordinates":[-117.925583,33.62811],"type":"Point"}
}