{
  "type": "Feature",
  "properties": {
    "iso:country":"US",
    "sg:address":"79265 US Hwy 111",
    "sg:city":"La Quinta",
    "sg:classifiers":[
        {
            "category":"Autos & Motor Vehicles",
            "subcategory":"Auto Supplies",
            "type":"Retail Goods"
        }
    ],
    "sg:phone":"+1 760 564 5343",
    "sg:postcode":"92253",
    "sg:province":"CA",
    "sg:tags":[
        "tire"
    ],
    "wof:name":"Mt View Tire & Svc",
    "wof:placetype":"venue"
},
  "geometry": {"coordinates":[-116.281047,33.707522],"type":"Point"}
}