{
  "type": "Feature",
  "properties": {
    "iso:country":"US",
    "sg:address":"221 Kings St",
    "sg:city":"Salinas",
    "sg:classifiers":[
        {
            "category":"Organizations",
            "subcategory":"Religious Organization",
            "type":"Services"
        }
    ],
    "sg:phone":"+1 831 422 4419",
    "sg:postcode":"93905",
    "sg:province":"CA",
    "sg:tags":[
        "church"
    ],
    "wof:name":"New Hope Baptist Church",
    "wof:placetype":"venue"
},
  "geometry": {"coordinates":[-121.639101,36.676651],"type":"Point"}
}