{
  "type": "Feature",
  "properties": {
    "iso:country":"US",
    "sg:address":"5015 Boulder Ln",
    "sg:city":"Santa Rosa",
    "sg:classifiers":[
        {
            "category":"Building & Trades",
            "subcategory":"Electrical",
            "type":"Services"
        }
    ],
    "sg:phone":"+1 707 539 2408",
    "sg:postcode":"95405",
    "sg:province":"CA",
    "sg:tags":[
        "electric",
        "contractor"
    ],
    "sg:website":"www.laddersack.com",
    "wof:name":"Mannie Electric",
    "wof:placetype":"venue"
},
  "geometry": {"coordinates":[-122.658229,38.447216],"type":"Point"}
}