{
  "type": "Feature",
  "properties": {
    "addr:full":"5015 Boulder Ln Santa Rosa CA 95405",
    "addr:housenumber":"5015",
    "addr:postcode":"95405",
    "addr:street":"Boulder Ln",
    "iso:country":"US",
    "sg:address":"5015 Boulder Ln",
    "sg:city":"Santa Rosa",
    "sg:classifiers":[
        {
            "category":"Building & Trades",
            "subcategory":"Electrical",
            "type":"Services"
        }
    ],
    "sg:phone":"+1 707 539 2408",
    "sg:postcode":"95405",
    "sg:province":"CA",
    "sg:tags":[
        "electric",
        "contractor"
    ],
    "sg:website":"www.laddersack.com",
    "wof:name":"Mannie Electric",
    "wof:placetype":"venue"
},
  "geometry": {"coordinates":[-122.65822900000001,38.447216],"type":"Point"}
}