{
  "type": "Feature",
  "properties": {
    "addr:full":"568 Corona Mall Corona CA 92879",
    "addr:housenumber":"568",
    "addr:postcode":"92879",
    "addr:street":"Corona Mall",
    "iso:country":"US",
    "sg:address":"568 Corona Mall",
    "sg:city":"Corona",
    "sg:classifiers":[
        {
            "category":"Banks & Credit Unions",
            "subcategory":"Financial Services",
            "type":"Services"
        }
    ],
    "sg:phone":"+1 951 278 0712",
    "sg:postcode":"92879",
    "sg:province":"CA",
    "sg:tags":[
        "trust",
        "investment",
        "real estate"
    ],
    "wof:name":"Moonridge Realty Intl Inc",
    "wof:placetype":"venue"
},
  "geometry": {"coordinates":[-117.566688,33.876689],"type":"Point"}
}