{
  "type": "Feature",
  "properties": {
    "addr:full":"5910 South St Lakewood CA 90713",
    "addr:housenumber":"5910",
    "addr:postcode":"90713",
    "addr:street":"South St",
    "iso:country":"US",
    "sg:address":"5910 South St",
    "sg:city":"Lakewood",
    "sg:classifiers":[
        {
            "category":"Banks & Credit Unions",
            "subcategory":"Bank",
            "type":"Services"
        }
    ],
    "sg:phone":"+1 562 925 9941",
    "sg:postcode":"90713",
    "sg:province":"CA",
    "wof:name":"Union Bank of California",
    "wof:placetype":"venue"
},
  "geometry": {"coordinates":[-118.11799600000001,33.858398],"type":"Point"}
}