{
  "type": "Feature",
  "properties": {
    "addr:full":"1150 Burlingame Ave Burlingame CA 94010",
    "addr:housenumber":"1150",
    "addr:postcode":"94010",
    "addr:street":"Burlingame Ave",
    "iso:country":"US",
    "sg:address":"1150 Burlingame Ave",
    "sg:city":"Burlingame",
    "sg:classifiers":[
        {
            "category":"Recreation",
            "type":"Entertainment"
        }
    ],
    "sg:phone":"+1 650 343 8309",
    "sg:postcode":"94010",
    "sg:province":"CA",
    "sg:tags":[
        "psychic",
        "medium"
    ],
    "wof:name":"Psychic & Tarot Readings",
    "wof:placetype":"venue"
},
  "geometry": {"coordinates":[-122.34614500000001,37.579212],"type":"Point"}
}