{
  "type": "Feature",
  "properties": {
    "iso:country":"US",
    "sg:address":"4200 Gosford Rd Ste 103",
    "sg:city":"Bakersfield",
    "sg:classifiers":[
        {
            "category":"Insurance",
            "subcategory":"Hazard Insurance",
            "type":"Services"
        }
    ],
    "sg:phone":"+1 661 396 7961",
    "sg:postcode":"93313",
    "sg:province":"CA",
    "sg:website":"http://statefarm.mqgroup.com/url.asp?usr=551912",
    "wof:name":"State Farm Insurance Agent-Rosie Schweer",
    "wof:placetype":"venue"
},
  "geometry": {"coordinates":[-119.092072,35.318169],"type":"Point"}
}