{
  "type": "Feature",
  "properties": {
    "iso:country":"US",
    "sg:address":"1108 Faraday St",
    "sg:city":"Santa Ynez",
    "sg:classifiers":[
        {
            "category":"Manufacturing",
            "subcategory":"Printing",
            "type":"Manufacturing & Wholesale Goods"
        }
    ],
    "sg:phone":"+1 805 693 1498",
    "sg:postcode":"93460",
    "sg:province":"CA",
    "sg:tags":[
        "newspaper"
    ],
    "wof:name":"Santa Ynez Valley Journal",
    "wof:placetype":"venue"
},
  "geometry": {"coordinates":[-120.079931,34.613303],"type":"Point"}
}