{
  "type": "Feature",
  "properties": {
    "iso:country":"US",
    "sg:address":"5560 E Stearns St",
    "sg:city":"Long Beach",
    "sg:classifiers":[
        {
            "category":"Shopping",
            "subcategory":"Beauty & Cosmetics",
            "type":"Retail Goods"
        }
    ],
    "sg:phone":"+1 562 493 6061",
    "sg:postcode":"90815",
    "sg:province":"CA",
    "sg:tags":[
        "supply"
    ],
    "wof:name":"Cosmoprof",
    "wof:placetype":"venue"
},
  "geometry": {"coordinates":[-118.135036,33.796099],"type":"Point"}
}