{
  "type": "Feature",
  "properties": {
    "addr:full":"9849 Bace Ave Bakersfield CA 93307",
    "addr:housenumber":"9849",
    "addr:postcode":"93307",
    "addr:street":"Bace Ave",
    "iso:country":"US",
    "sg:address":"9849 Bace Ave",
    "sg:city":"Bakersfield",
    "sg:classifiers":[
        {
            "category":"Wholesale",
            "subcategory":"Farm Supplies",
            "type":"Manufacturing & Wholesale Goods"
        }
    ],
    "sg:phone":"+1 661 833 6827",
    "sg:postcode":"93307",
    "sg:province":"CA",
    "sg:tags":[
        "bulb",
        "seed"
    ],
    "wof:name":"Buys Seed Co",
    "wof:placetype":"venue"
},
  "geometry": {"coordinates":[-119.00448400000001,35.26631],"type":"Point"}
}