{
  "type": "Feature",
  "properties": {
    "addr:full":"7220 Eastern Ave Bell Gardens CA 90201",
    "addr:housenumber":"7220",
    "addr:postcode":"90201",
    "addr:street":"Eastern Ave",
    "iso:country":"US",
    "sg:address":"7220 Eastern Ave",
    "sg:city":"Bell Gardens",
    "sg:classifiers":[
        {
            "category":"Banks & Credit Unions",
            "subcategory":"Bank",
            "type":"Services"
        }
    ],
    "sg:phone":"+1 562 927 7387",
    "sg:postcode":"90201",
    "sg:province":"CA",
    "sg:website":"www.wamu.com",
    "wof:name":"WaMu",
    "wof:placetype":"venue"
},
  "geometry": {"coordinates":[-118.164523,33.967017],"type":"Point"}
}