{
  "type": "Feature",
  "properties": {
    "addr:full":"100 S McDowell Blvd Petaluma CA 94954",
    "addr:housenumber":"100",
    "addr:postcode":"94954",
    "addr:street":"S Mcdowell Blvd",
    "iso:country":"US",
    "sg:address":"100 S McDowell Blvd",
    "sg:city":"Petaluma",
    "sg:classifiers":[
        {
            "category":"Restaurant",
            "type":"Food & Drink"
        }
    ],
    "sg:phone":"+1 707 763 2646",
    "sg:postcode":"94954",
    "sg:province":"CA",
    "wof:name":"Carrows Restaurant",
    "wof:placetype":"venue"
},
  "geometry": {"coordinates":[-122.624512,38.248452],"type":"Point"}
}