{
  "type": "Feature",
  "properties": {
    "addr:full":"200 Clara Ave Ukiah CA 95482",
    "addr:housenumber":"200",
    "addr:postcode":"ca 95482",
    "addr:street":"Clara Ave",
    "iso:country":"US",
    "sg:address":"200 Clara Ave",
    "sg:city":"Ukiah",
    "sg:classifiers":[
        {
            "category":"Wholesale",
            "subcategory":"Groceries",
            "type":"Manufacturing & Wholesale Goods"
        }
    ],
    "sg:phone":"+1 707 462 6605",
    "sg:postcode":"95482",
    "sg:province":"CA",
    "sg:tags":[
        "baker"
    ],
    "wof:name":"Pamela's Product Inc",
    "wof:placetype":"venue"
},
  "geometry": {"coordinates":[-123.203903,39.155375],"type":"Point"}
}