{
  "type": "Feature",
  "properties": {
    "addr:full":"109 Mountain Valley St Oakland CA 94605",
    "addr:housenumber":"109",
    "addr:postcode":"94605",
    "addr:street":"Mountain Valley St",
    "iso:country":"US",
    "sg:address":"109 Mountain Valley St",
    "sg:city":"Oakland",
    "sg:classifiers":[
        {
            "category":"Professional",
            "subcategory":"Management & Consulting",
            "type":"Services"
        }
    ],
    "sg:phone":"+1 510 553 0188",
    "sg:postcode":"94605",
    "sg:province":"CA",
    "sg:tags":[
        "counselor",
        "public",
        "relations"
    ],
    "wof:name":"Sansone Public Relations",
    "wof:placetype":"venue"
},
  "geometry": {"coordinates":[-122.130951,37.769073],"type":"Point"}
}