{
  "type": "Feature",
  "properties": {
    "addr:full":"75 Aloha Ct Petaluma CA 94952",
    "addr:housenumber":"75",
    "addr:postcode":"94952",
    "addr:street":"Aloha Ct",
    "iso:country":"US",
    "sg:address":"75 Aloha Ct",
    "sg:city":"Petaluma",
    "sg:classifiers":[
        {
            "category":"Professional",
            "subcategory":"Art Services",
            "type":"Services"
        }
    ],
    "sg:phone":"+1 707 773 2949",
    "sg:postcode":"94952",
    "sg:province":"CA",
    "sg:tags":[
        "graphic",
        "designer"
    ],
    "wof:name":"Marcus Badgley Designs",
    "wof:placetype":"venue"
},
  "geometry": {"coordinates":[-122.662795,38.251758],"type":"Point"}
}