{
  "type": "Feature",
  "properties": {
    "iso:country":"US",
    "sg:address":"373 W Portal Ave",
    "sg:city":"San Francisco",
    "sg:classifiers":[
        {
            "category":"Shopping",
            "subcategory":"Clothing, Apparel, & Fashions",
            "type":"Retail Goods"
        }
    ],
    "sg:phone":"+1 415 564 8354",
    "sg:postcode":"94127",
    "sg:province":"CA",
    "sg:tags":[
        "dressmaker"
    ],
    "wof:name":"Lora Dukler Couture",
    "wof:placetype":"venue"
},
  "geometry": {"coordinates":[-122.46949,37.737551],"type":"Point"}
}