{
  "type": "Feature",
  "properties": {
    "iso:country":"US",
    "sg:address":"496 Montecito Dr",
    "sg:city":"Los Angeles",
    "sg:classifiers":[
        {
            "category":"Building & Trades",
            "subcategory":"Construction",
            "type":"Services"
        }
    ],
    "sg:phone":"+1 925 513 8734",
    "sg:postcode":"90031",
    "sg:province":"CA",
    "sg:tags":[
        "home",
        "builder"
    ],
    "wof:name":"Shea Homes",
    "wof:placetype":"venue"
},
  "geometry": {"coordinates":[-118.201748,34.095191],"type":"Point"}
}