{
  "type": "Feature",
  "properties": {
    "addr:full":"5560 Mccourtney Rd Lincoln CA 95648",
    "addr:housenumber":"5560",
    "addr:postcode":"95648",
    "addr:street":"Mccourtney Rd",
    "iso:country":"US",
    "sg:address":"5560 Mccourtney Rd",
    "sg:city":"Lincoln",
    "sg:classifiers":[
        {
            "category":"Farming",
            "subcategory":"Livestock Farm",
            "type":"Manufacturing & Wholesale Goods"
        }
    ],
    "sg:phone":"+1 916 645 8048",
    "sg:postcode":"95648",
    "sg:province":"CA",
    "sg:tags":[
        "feeding",
        "ranch"
    ],
    "wof:name":"Hanley Ranch",
    "wof:placetype":"venue"
},
  "geometry": {"coordinates":[-121.281865,38.979931],"type":"Point"}
}