{
  "type": "Feature",
  "properties": {
    "addr:full":"1344 Mangrove Ave Chico CA 95926",
    "addr:housenumber":"1344",
    "addr:postcode":"95926",
    "addr:street":"Mangrove Ave",
    "iso:country":"US",
    "sg:address":"1344 Mangrove Ave",
    "sg:city":"Chico",
    "sg:classifiers":[
        {
            "category":"Banks & Credit Unions",
            "subcategory":"Bank",
            "type":"Services"
        }
    ],
    "sg:phone":"+1 530 879 9500",
    "sg:postcode":"95926",
    "sg:province":"CA",
    "sg:tags":[
        "cashing",
        "check"
    ],
    "wof:name":"California Check Cashing",
    "wof:placetype":"venue"
},
  "geometry": {"coordinates":[-121.83938999999999,39.743523],"type":"Point"}
}