{
  "type": "Feature",
  "properties": {
    "addr:full":"4167 N Golden State Blvd Fresno CA 93722",
    "addr:housenumber":"4167",
    "addr:postcode":"93722",
    "addr:street":"N Golden State Blvd",
    "iso:country":"US",
    "sg:address":"4167 N Golden State Blvd",
    "sg:city":"Fresno",
    "sg:classifiers":[
        {
            "category":"Industrial Area",
            "type":"Public Place"
        }
    ],
    "sg:phone":"+1 800 439 0026",
    "sg:postcode":"93722",
    "sg:province":"CA",
    "sg:tags":[
        "floors-industrial"
    ],
    "wof:name":"American Exterior Coatings",
    "wof:placetype":"venue"
},
  "geometry": {"coordinates":[-119.86458,36.7964],"type":"Point"}
}