{
  "type": "Feature",
  "properties": {
    "iso:country":"US",
    "sg:address":"150 N Santa Anita Ave",
    "sg:city":"Arcadia",
    "sg:classifiers":[
        {
            "category":"Banks & Credit Unions",
            "subcategory":"Bank",
            "type":"Services"
        }
    ],
    "sg:phone":"+1 626 445 3408",
    "sg:postcode":"91006",
    "sg:province":"CA",
    "sg:tags":[
        "loan",
        "real estate"
    ],
    "sg:website":"www.poserinvestments.com",
    "wof:name":"Poser Investments Inc",
    "wof:placetype":"venue"
},
  "geometry": {"coordinates":[-118.03139,34.141801],"type":"Point"}
}