{
  "type": "Feature",
  "properties": {
    "iso:country":"US",
    "sg:address":"1520 S State Hwy 49",
    "sg:city":"Jackson",
    "sg:classifiers":[
        {
            "category":"Building & Trades",
            "subcategory":"Construction",
            "type":"Services"
        }
    ],
    "sg:phone":"+1 209 223 1332",
    "sg:postcode":"95642",
    "sg:province":"CA",
    "sg:tags":[
        "prefabricated",
        "contractor",
        "industrial",
        "bu"
    ],
    "wof:name":"Steel Building Systems Inc",
    "wof:placetype":"venue"
},
  "geometry": {"coordinates":[-120.758249,38.336351],"type":"Point"}
}