{
  "type": "Feature",
  "properties": {
    "addr:full":"18531 Roscoe Blvd 215A Northridge CA 91324",
    "addr:housenumber":"18531;215a",
    "addr:postcode":"91324",
    "addr:street":"Roscoe Blvd",
    "iso:country":"US",
    "sg:address":"18531 Roscoe Blvd 215A",
    "sg:city":"Northridge",
    "sg:classifiers":[
        {
            "category":"Social Services",
            "subcategory":"Job Training",
            "type":"Services"
        }
    ],
    "sg:phone":"+1 818 886 4315",
    "sg:postcode":"91324",
    "sg:province":"CA",
    "sg:tags":[
        "employment"
    ],
    "wof:name":"Advanced Pt. & Rehab.",
    "wof:placetype":"venue"
},
  "geometry": {"coordinates":[-118.537055,34.22073],"type":"Point"}
}