{
  "type": "Feature",
  "properties": {
    "addr:full":"1531 N Chester Ave Bakersfield CA 93308",
    "addr:housenumber":"1531",
    "addr:postcode":"93308",
    "addr:street":"N Chester Ave",
    "iso:country":"US",
    "sg:address":"1531 N Chester Ave",
    "sg:city":"Bakersfield",
    "sg:classifiers":[
        {
            "category":"Food & Beverages",
            "subcategory":"Bakery",
            "type":"Retail Goods"
        },
        {
            "category":"Bakery",
            "type":"Food & Drink"
        }
    ],
    "sg:menulink":"http://www.allmenus.com/ca/bakersfield/239489-winchells-doughnut-house/menu/",
    "sg:phone":"+1 805 399 8062",
    "sg:postcode":"93308",
    "sg:province":"CA",
    "sg:tags":[
        "smoothy",
        "juice",
        "american",
        "bakery",
        "pastry"
    ],
    "wof:name":"Winchell's Doughnut House",
    "wof:placetype":"venue"
},
  "geometry": {"coordinates":[-119.02154400000001,35.420267],"type":"Point"}
}