{
  "type": "Feature",
  "properties": {
    "addr:full":"253 Sutton Pl Santa Rosa CA 95407",
    "addr:housenumber":"253",
    "addr:postcode":"95407",
    "addr:street":"Sutton Pl",
    "iso:country":"US",
    "sg:address":"253 Sutton Pl",
    "sg:city":"Santa Rosa",
    "sg:classifiers":[
        {
            "category":"Recreation",
            "subcategory":"Marina",
            "type":"Entertainment"
        }
    ],
    "sg:phone":"+1 707 588 9100",
    "sg:postcode":"95407",
    "sg:province":"CA",
    "sg:tags":[
        "repairing",
        "boat"
    ],
    "wof:name":"Ace Marine",
    "wof:placetype":"venue"
},
  "geometry": {"coordinates":[-122.722356,38.390976],"type":"Point"}
}