{
  "type": "Feature",
  "properties": {
    "iso:country":"US",
    "sg:address":"12640 Kennedy Flat Rd",
    "sg:city":"Jackson",
    "sg:classifiers":[
        {
            "category":"Food & Beverages",
            "subcategory":"Meat & Fish",
            "type":"Retail Goods"
        }
    ],
    "sg:phone":"+1 209 223 0731",
    "sg:postcode":"95642",
    "sg:province":"CA",
    "wof:name":"Swingle Meat Co",
    "wof:placetype":"venue"
},
  "geometry": {"coordinates":[-120.792111,38.364793],"type":"Point"}
}