{
  "type": "Feature",
  "properties": {
    "addr:full":"1001 I St Sacramento CA 95814",
    "addr:housenumber":"1001",
    "addr:postcode":"95814",
    "addr:street":"I St",
    "iso:country":"US",
    "sg:address":"1001 I St",
    "sg:city":"Sacramento",
    "sg:classifiers":[
        {
            "category":"Building & Trades",
            "subcategory":"Construction",
            "type":"Services"
        }
    ],
    "sg:phone":"+1 916 322 0477",
    "sg:postcode":"95814",
    "sg:province":"CA",
    "sg:tags":[
        "pond",
        "supply"
    ],
    "wof:name":"Ca Environmental Agency",
    "wof:placetype":"venue"
},
  "geometry": {"coordinates":[-121.491646,38.581041],"type":"Point"}
}