{
  "type": "Feature",
  "properties": {
    "addr:full":"1070 N Cypress St La Habra CA 90631",
    "addr:housenumber":"1070",
    "addr:postcode":"90631",
    "addr:street":"N Cypress St",
    "iso:country":"US",
    "sg:address":"1070 N Cypress St",
    "sg:city":"La Habra",
    "sg:classifiers":[
        {
            "category":"Building & Trades",
            "subcategory":"Construction",
            "type":"Services"
        }
    ],
    "sg:phone":"+1 714 526 7463",
    "sg:postcode":"90631",
    "sg:province":"CA",
    "sg:tags":[
        "contractor"
    ],
    "wof:name":"Western Eagle Construction",
    "wof:placetype":"venue"
},
  "geometry": {"coordinates":[-117.941754,33.941871],"type":"Point"}
}