{
  "type": "Feature",
  "properties": {
    "iso:country":"US",
    "sg:address":"18921 Colima Rd",
    "sg:city":"Rowland Heights",
    "sg:classifiers":[
        {
            "category":"Personal",
            "subcategory":"Beauty Salon",
            "type":"Services"
        }
    ],
    "sg:phone":"+1 626 964 1042",
    "sg:postcode":"91748",
    "sg:province":"CA",
    "wof:name":"Susies Haircut & Barber Shop",
    "wof:placetype":"venue"
},
  "geometry": {"coordinates":[-117.890131,33.98762],"type":"Point"}
}