{
  "type": "Feature",
  "properties": {
    "iso:country":"US",
    "sg:address":"950 S Coast Drive",
    "sg:city":"Costa Mesa",
    "sg:classifiers":[
        {
            "category":"Banks & Credit Unions",
            "subcategory":"Financial Services",
            "type":"Services"
        }
    ],
    "sg:phone":"+1 714 424 0220",
    "sg:postcode":"92626",
    "sg:province":"CA",
    "sg:tags":[
        "broker",
        "mortgage"
    ],
    "wof:name":"4 Front Financial",
    "wof:placetype":"venue"
},
  "geometry": {"coordinates":[-117.89650399999999,33.689939],"type":"Point"}
}