{
  "type": "Feature",
  "properties": {
    "addr:full":"44032 Erie Ct Indian Wells CA 92210",
    "addr:housenumber":"44032",
    "addr:postcode":"92210",
    "addr:street":"Erie Ct",
    "iso:country":"US",
    "sg:address":"44032 Erie Ct",
    "sg:city":"Indian Wells",
    "sg:classifiers":[
        {
            "category":"Social Services",
            "type":"Services"
        }
    ],
    "sg:phone":"+1 760 346 1276",
    "sg:postcode":"92210",
    "sg:province":"CA",
    "sg:tags":[
        "senior",
        "citizen"
    ],
    "wof:name":"Palm Desert Senior Cup",
    "wof:placetype":"venue"
},
  "geometry": {"coordinates":[-116.357975,33.728188],"type":"Point"}
}