{
  "type": "Feature",
  "properties": {
    "iso:country":"US",
    "sg:address":"2396 US Hwy 86",
    "sg:city":"Imperial",
    "sg:classifiers":[
        {
            "category":"Building & Trades",
            "subcategory":"Equipment Rental",
            "type":"Services"
        }
    ],
    "sg:phone":"+1 760 353 0190",
    "sg:postcode":"92251",
    "sg:province":"CA",
    "sg:tags":[
        "yard"
    ],
    "sg:website":"www.nationsrent.com",
    "wof:name":"Nations Rent",
    "wof:placetype":"venue"
},
  "geometry": {"coordinates":[-115.56981,32.81854],"type":"Point"}
}