{
  "type": "Feature",
  "properties": {
    "iso:country":"US",
    "sg:address":"1216 Missouri St",
    "sg:city":"Fairfield",
    "sg:classifiers":[
        {
            "category":"Organizations",
            "subcategory":"Religious Organization",
            "type":"Services"
        }
    ],
    "sg:phone":"+1 707 426 6244",
    "sg:postcode":"94533",
    "sg:province":"CA",
    "sg:tags":[
        "church"
    ],
    "wof:name":"Salvation Army",
    "wof:placetype":"venue"
},
  "geometry": {"coordinates":[-122.049657,38.248228],"type":"Point"}
}