{
  "type": "Feature",
  "properties": {
    "addr:full":"1811 Fanwood Ave Long Beach CA 90815",
    "addr:housenumber":"1811",
    "addr:postcode":"90815",
    "addr:street":"Fanwood Ave",
    "iso:country":"US",
    "sg:address":"1811 Fanwood Ave",
    "sg:city":"Long Beach",
    "sg:classifiers":[
        {
            "category":"Professional",
            "subcategory":"Engineering",
            "type":"Services"
        }
    ],
    "sg:phone":"+1 858 756 6905",
    "sg:postcode":"90815",
    "sg:province":"CA",
    "sg:tags":[
        "engineer"
    ],
    "wof:name":"Omega Power Engineering",
    "wof:placetype":"venue"
},
  "geometry": {"coordinates":[-118.11626800000001,33.790775],"type":"Point"}
}