{
  "type": "Feature",
  "properties": {
    "acgov:api":"698.0",
    "acgov:type":"MS",
    "addr:full":"991 14th Street Oakland CA",
    "wof:categories":[
        "education_and_religion:education=school"
    ],
    "wof:name":"West Oakland Middle",
    "wof:placetype":"venue"
},
  "geometry": {"coordinates":[-122.28274733524472,37.80864278178863],"type":"Point"}
}