{
  "type": "Feature",
  "properties": {
    "iso:country":"US",
    "sg:address":"2418 Honolulu Ave Ste D",
    "sg:city":"La Crescenta-Montrose",
    "sg:classifiers":[
        {
            "category":"Health Services",
            "subcategory":"Chiropractor",
            "type":"Services"
        }
    ],
    "sg:phone":"+1 818 275 1014",
    "sg:postcode":"91020",
    "sg:province":"CA",
    "sg:website":"www.adjustedlife.net",
    "wof:name":"Adjusted Life Chiropractic",
    "wof:placetype":"venue"
},
  "geometry": {"coordinates":[-118.231301,34.206323],"type":"Point"}
}