{
  "type": "Feature",
  "properties": {
    "iso:country":"US",
    "sg:address":"5000 Van Nuys Blvd",
    "sg:city":"Sherman Oaks",
    "sg:classifiers":[
        {
            "category":"Professional",
            "type":"Services"
        }
    ],
    "sg:phone":"+1 818 501 0146",
    "sg:postcode":"91403",
    "sg:province":"CA",
    "wof:name":"Johnny M Roberson",
    "wof:placetype":"venue"
},
  "geometry": {"coordinates":[-118.448698,34.162135],"type":"Point"}
}