{
  "type": "Feature",
  "properties": {
    "iso:country":"US",
    "sg:address":"7720 Lorraine Ave",
    "sg:city":"Stockton",
    "sg:classifiers":[
        {
            "category":"Health Services",
            "subcategory":"Chiropractor",
            "type":"Services"
        }
    ],
    "sg:phone":"+1 209 474 8274",
    "sg:postcode":"95210",
    "sg:province":"CA",
    "wof:name":"All Injury Clinic",
    "wof:placetype":"venue"
},
  "geometry": {"coordinates":[-121.283292,38.019612],"type":"Point"}
}