{
  "type": "Feature",
  "properties": {
    "iso:country":"US",
    "sg:address":"1953 Niderer Rd",
    "sg:city":"Paso Robles",
    "sg:classifiers":[
        {
            "category":"Farming",
            "subcategory":"Vineyard",
            "type":"Manufacturing & Wholesale Goods"
        }
    ],
    "sg:phone":"+1 805 238 4763",
    "sg:postcode":"93446",
    "sg:province":"CA",
    "sg:tags":[
        "grape",
        "eating"
    ],
    "sg:website":"www.dunningvineyards.com",
    "wof:name":"Dunning Vineyards",
    "wof:placetype":"venue"
},
  "geometry": {"coordinates":[-120.772278,35.587524],"type":"Point"}
}