{
  "type": "Feature",
  "properties": {
    "addr:full":"3717 Camino Diablo Byron CA 94514",
    "addr:housenumber":"3717",
    "addr:postcode":"94514",
    "addr:street":"Camino Diablo",
    "iso:country":"US",
    "sg:address":"3717 Camino Diablo",
    "sg:city":"Byron",
    "sg:classifiers":[
        {
            "category":"Retail",
            "subcategory":"Pet Boarding",
            "type":"Services"
        }
    ],
    "sg:phone":"+1 925 634 1889",
    "sg:postcode":"94514",
    "sg:province":"CA",
    "sg:tags":[
        "boarding/pet",
        "sitting"
    ],
    "wof:name":"Shimer's Grooming & Boarding",
    "wof:placetype":"venue"
},
  "geometry": {"coordinates":[-121.60700199999999,37.895599],"type":"Point"}
}