{
  "type": "Feature",
  "properties": {
    "addr:full":"200 Plymouth Ave San Francisco CA 94112",
    "addr:housenumber":"200",
    "addr:postcode":"94112",
    "addr:street":"Plymouth Ave",
    "iso:country":"US",
    "sg:address":"200 Plymouth Ave",
    "sg:city":"San Francisco",
    "sg:classifiers":[
        {
            "category":"Education",
            "subcategory":"College",
            "type":"Public Place"
        }
    ],
    "sg:phone":"+1 415 585 6002",
    "sg:postcode":"94112",
    "sg:province":"CA",
    "sg:tags":[
        "academic",
        "school"
    ],
    "wof:name":"College Of Theology & Urban",
    "wof:placetype":"venue"
},
  "geometry": {"coordinates":[-122.456053,37.713194],"type":"Point"}
}