{
  "type": "Feature",
  "properties": {
    "addr:full":"316 12th St Oakland CA 94607",
    "addr:housenumber":"316",
    "addr:postcode":"94607",
    "addr:street":"12Th St",
    "iso:country":"US",
    "sg:address":"316 12th St",
    "sg:city":"Oakland",
    "sg:classifiers":[
        {
            "category":"Home & Garden",
            "subcategory":"Furniture",
            "type":"Retail Goods"
        }
    ],
    "sg:phone":"+1 510 835 2832",
    "sg:postcode":"94607",
    "sg:province":"CA",
    "sg:tags":[
        "store"
    ],
    "wof:name":"Shiu Fung Rosewood Furniture",
    "wof:placetype":"venue"
},
  "geometry": {"coordinates":[-122.268997,37.801899],"type":"Point"}
}