{
  "type": "Feature",
  "properties": {
    "iso:country":"US",
    "sg:address":"11814 Sheldon St",
    "sg:city":"Sun Valley",
    "sg:classifiers":[
        {
            "category":"Building & Trades",
            "subcategory":"Construction",
            "type":"Services"
        }
    ],
    "sg:phone":"+1 818 771 0014",
    "sg:postcode":"91352",
    "sg:province":"CA",
    "sg:tags":[
        "contractor"
    ],
    "wof:name":"Jim Jelinskis Tile In Style",
    "wof:placetype":"venue"
},
  "geometry": {"coordinates":[-118.388206,34.244013],"type":"Point"}
}