{
  "type": "Feature",
  "properties": {
    "iso:country":"US",
    "sg:address":"10056 Adams Ave",
    "sg:city":"Huntington Beach",
    "sg:classifiers":[
        {
            "category":"Manufacturing",
            "subcategory":"Food",
            "type":"Manufacturing & Wholesale Goods"
        }
    ],
    "sg:phone":"+1 714 378 0980",
    "sg:postcode":"92646",
    "sg:province":"CA",
    "sg:tags":[
        "donut",
        "product",
        "mfg"
    ],
    "wof:name":"Royal Donut & Bakery",
    "wof:placetype":"venue"
},
  "geometry": {"coordinates":[-117.952003,33.672199],"type":"Point"}
}