{
  "type": "Feature",
  "properties": {
    "addr:full":"4701 Natick Ave Sherman Oaks CA 91403",
    "addr:postcode":"4701;91403",
    "addr:street":"Natick Ave",
    "iso:country":"US",
    "sg:address":"4701 Natick Ave",
    "sg:city":"Sherman Oaks",
    "sg:classifiers":[
        {
            "category":"Real Estate",
            "subcategory":"Real Estate Operator",
            "type":"Services"
        }
    ],
    "sg:phone":"+1 818 906 3307",
    "sg:postcode":"91403",
    "sg:province":"CA",
    "sg:tags":[
        "apartment"
    ],
    "wof:name":"Natick Place",
    "wof:placetype":"venue"
},
  "geometry": {"coordinates":[-118.45422600000001,34.155336],"type":"Point"}
}