{
  "type": "Feature",
  "properties": {
    "iso:country":"US",
    "sg:address":"327 Main St",
    "sg:city":"Ferndale",
    "sg:classifiers":[
        {
            "category":"Personal",
            "subcategory":"Barber",
            "type":"Services"
        }
    ],
    "sg:phone":"+1 707 786 4310",
    "sg:postcode":"95536",
    "sg:province":"CA",
    "wof:name":"Ferndale Hair Designs",
    "wof:placetype":"venue"
},
  "geometry": {"coordinates":[-124.26418,40.576127],"type":"Point"}
}