{
  "type": "Feature",
  "properties": {
    "addr:full":"1813 Wilton Rd Encinitas CA 92024",
    "addr:housenumber":"1813",
    "addr:postcode":"92024",
    "addr:street":"Wilton Rd",
    "iso:country":"US",
    "sg:address":"1813 Wilton Rd",
    "sg:city":"Encinitas",
    "sg:classifiers":[
        {
            "category":"Shopping",
            "type":"Retail Goods"
        }
    ],
    "sg:phone":"+1 760 943 7140",
    "sg:postcode":"92024",
    "sg:province":"CA",
    "sg:tags":[
        "candle"
    ],
    "wof:name":"Candles By Connie",
    "wof:placetype":"venue"
},
  "geometry": {"coordinates":[-117.30945199999999,33.080209],"type":"Point"}
}