{
  "type": "Feature",
  "properties": {
    "iso:country":"US",
    "sg:address":"229 Commerce Dr",
    "sg:city":"Mammoth Lakes",
    "sg:classifiers":[
        {
            "category":"Building & Trades",
            "subcategory":"Plumbing",
            "type":"Services"
        }
    ],
    "sg:phone":"+1 760 934 8586",
    "sg:postcode":"93546",
    "sg:province":"CA",
    "sg:tags":[
        "conditioning",
        "air",
        "system",
        "contractor"
    ],
    "wof:name":"A-Plus Heating Air Cond Inc",
    "wof:placetype":"venue"
},
  "geometry": {"coordinates":[-118.95233,37.642966],"type":"Point"}
}