{
  "type": "Feature",
  "properties": {
    "iso:country":"US",
    "sg:address":"431 Columbus Ave",
    "sg:city":"San Francisco",
    "sg:classifiers":[
        {
            "category":"Restaurant",
            "type":"Food & Drink"
        }
    ],
    "sg:phone":"+1 415 591 0900",
    "sg:postcode":"94133",
    "sg:province":"CA",
    "wof:name":"Panta Rei Cafe Restaurant",
    "wof:placetype":"venue"
},
  "geometry": {"coordinates":[-122.40878600000001,37.799191],"type":"Point"}
}