{
  "type": "Feature",
  "properties": {
    "addr:full":"5727 Ravenspur Dr Apt 301 Rancho Palos Verdes CA 90275",
    "addr:housenumber":"5727;301",
    "addr:postcode":"90275",
    "addr:street":"Ravenspur Dr Apt",
    "iso:country":"US",
    "sg:address":"5727 Ravenspur Dr Apt 301",
    "sg:city":"Rancho Palos Verdes",
    "sg:classifiers":[
        {
            "category":"Real Estate",
            "subcategory":"Real Estate Operator",
            "type":"Services"
        }
    ],
    "sg:phone":"+1 310 541 2900",
    "sg:postcode":"90275",
    "sg:province":"CA",
    "sg:tags":[
        "apartment"
    ],
    "wof:name":"Peninsula Apartments",
    "wof:placetype":"venue"
},
  "geometry": {"coordinates":[-118.38099699999999,33.777802],"type":"Point"}
}