{
  "type": "Feature",
  "properties": {
    "addr:full":"11665 Gerald Ave Granada Hills CA 91344",
    "addr:housenumber":"11665",
    "addr:postcode":"91344",
    "addr:street":"Gerald Ave",
    "iso:country":"US",
    "sg:address":"11665 Gerald Ave",
    "sg:city":"Granada Hills",
    "sg:classifiers":[
        {
            "category":"Real Estate",
            "subcategory":"Real Estate Agent",
            "type":"Services"
        }
    ],
    "sg:phone":"+1 818 368 8528",
    "sg:postcode":"91344",
    "sg:province":"CA",
    "wof:name":"Tanaka Appraisal Service",
    "wof:placetype":"venue"
},
  "geometry": {"coordinates":[-118.494658,34.28213],"type":"Point"}
}