{
  "type": "Feature",
  "properties": {
    "addr:full":"26916 Baseline St Highland CA 92346",
    "addr:housenumber":"26916",
    "addr:postcode":"92346",
    "addr:street":"Baseline St",
    "iso:country":"US",
    "sg:address":"26916 Baseline St",
    "sg:city":"Highland",
    "sg:classifiers":[
        {
            "category":"Food & Beverages",
            "subcategory":"Groceries & Convenience Stores",
            "type":"Retail Goods"
        }
    ],
    "sg:phone":"+1 909 864 8634",
    "sg:postcode":"92346",
    "sg:province":"CA",
    "sg:tags":[
        "grocer"
    ],
    "wof:name":"Meadow Maid Dairy",
    "wof:placetype":"venue"
},
  "geometry": {"coordinates":[-117.215058,34.121342],"type":"Point"}
}