{
  "type": "Feature",
  "properties": {
    "addr:full":"2308 Tripaldi Way Hayward CA 94545",
    "addr:housenumber":"2308",
    "addr:postcode":"94545",
    "addr:street":"Tripaldi Way",
    "iso:country":"US",
    "sg:address":"2308 Tripaldi Way",
    "sg:city":"Hayward",
    "sg:classifiers":[
        {
            "category":"Retail",
            "subcategory":"Repair Shop",
            "type":"Services"
        }
    ],
    "sg:phone":"+1 510 783 7790",
    "sg:postcode":"94545",
    "sg:province":"CA",
    "sg:tags":[
        "lighting",
        "fixture"
    ],
    "wof:name":"Energy Management Technologies",
    "wof:placetype":"venue"
},
  "geometry": {"coordinates":[-122.083085,37.614409],"type":"Point"}
}