{
  "type": "Feature",
  "properties": {
    "iso:country":"US",
    "sg:address":"4477 Highland Springs Rd",
    "sg:city":"Lakeport",
    "sg:classifiers":[
        {
            "category":"Autos & Motor Vehicles",
            "subcategory":"Automobile Sales",
            "type":"Retail Goods"
        }
    ],
    "sg:phone":"+1 707 263 3145",
    "sg:postcode":"95453",
    "sg:province":"CA",
    "sg:tags":[
        "used"
    ],
    "wof:name":"Specialty Sales",
    "wof:placetype":"venue"
},
  "geometry": {"coordinates":[-122.894221,38.990785],"type":"Point"}
}