{
  "type": "Feature",
  "properties": {
    "iso:country":"US",
    "sg:address":"2777 Jefferson St Ste 101",
    "sg:city":"Carlsbad",
    "sg:classifiers":[
        {
            "category":"Professional",
            "subcategory":"Lawyer & Legal Services",
            "type":"Services"
        }
    ],
    "sg:phone":"+1 760 602 0660",
    "sg:postcode":"92008",
    "sg:province":"CA",
    "sg:website":"www.GregoryIbbetson.com",
    "wof:name":"Ibbetson Gregory",
    "wof:placetype":"venue"
},
  "geometry": {"coordinates":[-117.347757,33.163662],"type":"Point"}
}