{
  "type": "Feature",
  "properties": {
    "addr:full":"5138 Brooks St Montclair CA 91763",
    "addr:housenumber":"5138",
    "addr:postcode":"91763",
    "addr:street":"Brooks St",
    "iso:country":"US",
    "sg:address":"5138 Brooks St",
    "sg:city":"Montclair",
    "sg:classifiers":[
        {
            "category":"Manufacturing",
            "subcategory":"Apparel",
            "type":"Manufacturing & Wholesale Goods"
        }
    ],
    "sg:phone":"+1 909 625 3163",
    "sg:postcode":"91763",
    "sg:province":"CA",
    "sg:tags":[
        "sewing",
        "contractor"
    ],
    "wof:name":"C D Fashion",
    "wof:placetype":"venue"
},
  "geometry": {"coordinates":[-117.695379,34.061771],"type":"Point"}
}