{
  "type": "Feature",
  "properties": {
    "addr:full":"716 S Garfield Ave Alhambra CA 91801",
    "addr:housenumber":"716",
    "addr:postcode":"91801",
    "addr:street":"S Garfield Ave",
    "iso:country":"US",
    "sg:address":"716 S Garfield Ave",
    "sg:city":"Alhambra",
    "sg:classifiers":[
        {
            "category":"Travel",
            "subcategory":"Travel Agent",
            "type":"Entertainment"
        }
    ],
    "sg:phone":"+1 626 281 2988",
    "sg:postcode":"91801",
    "sg:province":"CA",
    "sg:tags":[
        "agency",
        "bureau"
    ],
    "wof:name":"Beneficial Travel Inc",
    "wof:placetype":"venue"
},
  "geometry": {"coordinates":[-118.122973,34.08761],"type":"Point"}
}