{
  "type": "Feature",
  "properties": {
    "addr:full":"4301 Valley Ave Pleasanton CA 94566",
    "addr:housenumber":"4301",
    "addr:postcode":"94566",
    "addr:street":"Valley Ave",
    "iso:country":"US",
    "sg:address":"4301 Valley Ave",
    "sg:city":"Pleasanton",
    "sg:classifiers":[
        {
            "category":"Food & Beverages",
            "subcategory":"Liquor & Beverages",
            "type":"Retail Goods"
        }
    ],
    "sg:phone":"+1 925 462 3800",
    "sg:postcode":"94566",
    "sg:province":"CA",
    "wof:name":"Perry's Liquors",
    "wof:placetype":"venue"
},
  "geometry": {"coordinates":[-121.875159,37.676736],"type":"Point"}
}