{
  "type": "Feature",
  "properties": {
    "addr:full":"2036 Hornblend St San Diego CA 92109",
    "addr:housenumber":"2036",
    "addr:postcode":"92109",
    "addr:street":"Hornblend St",
    "iso:country":"US",
    "sg:address":"2036 Hornblend St",
    "sg:city":"San Diego",
    "sg:classifiers":[
        {
            "category":"Health Services",
            "subcategory":"Medical Lab",
            "type":"Services"
        }
    ],
    "sg:phone":"+1 858 272 9650",
    "sg:postcode":"92109",
    "sg:province":"CA",
    "sg:tags":[
        "laboratory"
    ],
    "wof:name":"Futuramics Inc",
    "wof:placetype":"venue"
},
  "geometry": {"coordinates":[-117.232049,32.800798],"type":"Point"}
}