{
  "type": "Feature",
  "properties": {
    "iso:country":"US",
    "sg:address":"1142 East Grand Ave",
    "sg:city":"El Segundo",
    "sg:classifiers":[
        {
            "category":"Cinema",
            "subcategory":"Movie Theater",
            "type":"Entertainment"
        }
    ],
    "sg:phone":"+1 310 615 3070",
    "sg:postcode":"90245",
    "sg:province":"CA",
    "sg:website":"www.newmastersstudio.com",
    "wof:name":"New Masters Studio",
    "wof:placetype":"venue"
},
  "geometry": {"coordinates":[-118.404036,33.919155],"type":"Point"}
}