{
  "type": "Feature",
  "properties": {
    "iso:country":"US",
    "sg:address":"18990 State Rte 120",
    "sg:city":"Groveland",
    "sg:classifiers":[
        {
            "category":"Education",
            "subcategory":"Library",
            "type":"Public Place"
        }
    ],
    "sg:phone":"+1 209 962 6144",
    "sg:postcode":"95321",
    "sg:province":"CA",
    "wof:name":"Groveland Library",
    "wof:placetype":"venue"
},
  "geometry": {"coordinates":[-120.214669,37.835574],"type":"Point"}
}