{
  "type": "Feature",
  "properties": {
    "addr:full":"16002 Dearborn St Sepulveda CA 91343",
    "addr:housenumber":"16002",
    "addr:postcode":"91343",
    "addr:street":"Dearborn St",
    "iso:country":"US",
    "sg:address":"16002 Dearborn St",
    "sg:city":"Sepulveda",
    "sg:classifiers":[
        {
            "category":"Shopping",
            "subcategory":"Computers & Home Electronics",
            "type":"Retail Goods"
        }
    ],
    "sg:phone":"+1 818 894 9156",
    "sg:postcode":"91343",
    "sg:province":"CA",
    "sg:tags":[
        "software"
    ],
    "wof:name":"International Business Systems",
    "wof:placetype":"venue"
},
  "geometry": {"coordinates":[-118.48394500000001,34.237429],"type":"Point"}
}