{
  "type": "Feature",
  "properties": {
    "iso:country":"US",
    "sg:address":"16056 Valley Blvd",
    "sg:city":"Fontana",
    "sg:classifiers":[
        {
            "category":"Food & Beverages",
            "subcategory":"Liquor & Beverages",
            "type":"Retail Goods"
        }
    ],
    "sg:phone":"+1 909 823 6333",
    "sg:postcode":"92335",
    "sg:province":"CA",
    "wof:name":"Citrus Liquor & Market",
    "wof:placetype":"venue"
},
  "geometry": {"coordinates":[-117.456754,34.070369],"type":"Point"}
}