{
  "type": "Feature",
  "properties": {
    "addr:full":"14940 Camden Ave San Jose CA 95124",
    "addr:housenumber":"14940",
    "addr:postcode":"95124",
    "addr:street":"Camden Ave",
    "iso:country":"US",
    "sg:address":"14940 Camden Ave",
    "sg:city":"San Jose",
    "sg:classifiers":[
        {
            "category":"Restaurant",
            "type":"Food & Drink"
        }
    ],
    "sg:menulink":"http://www.allmenus.com/ca/san-jose/75376-round-table-pizza/menu/",
    "sg:phone":"+1 408 371 9550",
    "sg:postcode":"95124",
    "sg:province":"CA",
    "sg:tags":[
        "american",
        "pizza"
    ],
    "wof:name":"Round Table Pizza",
    "wof:placetype":"venue"
},
  "geometry": {"coordinates":[-121.92583399999999,37.261654],"type":"Point"}
}