{
  "type": "Feature",
  "properties": {
    "iso:country":"US",
    "sg:address":"14270 Chino Hills Pkwy",
    "sg:city":"Chino Hills",
    "sg:classifiers":[
        {
            "category":"Real Estate",
            "subcategory":"Real Estate Agent",
            "type":"Services"
        }
    ],
    "sg:phone":"+1 909 590 8853",
    "sg:postcode":"91709",
    "sg:province":"CA",
    "wof:name":"Century 21",
    "wof:placetype":"venue"
},
  "geometry": {"coordinates":[-117.758589,33.995608],"type":"Point"}
}