{
  "type": "Feature",
  "properties": {
    "iso:country":"US",
    "sg:address":"936 S Pacific St Apt 2",
    "sg:city":"Oceanside",
    "sg:classifiers":[
        {
            "category":"Communications",
            "subcategory":"Film & Video Production",
            "type":"Services"
        }
    ],
    "sg:phone":"+1 760 722 3225",
    "sg:postcode":"92054",
    "sg:province":"CA",
    "sg:tags":[
        "services-commercial"
    ],
    "wof:name":"Carlson Videographics",
    "wof:placetype":"venue"
},
  "geometry": {"coordinates":[-117.375334,33.184659],"type":"Point"}
}