{
  "type": "Feature",
  "properties": {
    "addr:full":"11300 Firestone Blvd Norwalk CA 90650",
    "addr:housenumber":"11300",
    "addr:postcode":"90650",
    "addr:street":"Firestone Blvd",
    "iso:country":"US",
    "sg:address":"11300 Firestone Blvd",
    "sg:city":"Norwalk",
    "sg:classifiers":[
        {
            "category":"Food & Beverages",
            "subcategory":"Groceries & Convenience Stores",
            "type":"Retail Goods"
        }
    ],
    "sg:phone":"+1 562 929 1878",
    "sg:postcode":"90650",
    "sg:province":"CA",
    "sg:tags":[
        "supermarket",
        "drug"
    ],
    "sg:website":"www.staterbros.com",
    "wof:name":"Stater Bros Markets",
    "wof:placetype":"venue"
},
  "geometry": {"coordinates":[-118.093172,33.9189],"type":"Point"}
}