{
  "type": "Feature",
  "properties": {
    "addr:full":"4370 24th St Sacramento CA 95822",
    "addr:housenumber":"4370",
    "addr:postcode":"95822",
    "addr:street":"24Th St",
    "iso:country":"US",
    "sg:address":"4370 24th St",
    "sg:city":"Sacramento",
    "sg:classifiers":[
        {
            "category":"Home & Garden",
            "subcategory":"Furniture",
            "type":"Retail Goods"
        }
    ],
    "sg:phone":"+1 916 451 5115",
    "sg:postcode":"95822",
    "sg:province":"CA",
    "sg:tags":[
        "futon"
    ],
    "wof:name":"American Futon",
    "wof:placetype":"venue"
},
  "geometry": {"coordinates":[-121.48374200000001,38.53695],"type":"Point"}
}