{
  "type": "Feature",
  "properties": {
    "iso:country":"US",
    "sg:address":"12204 Foothill Blvd",
    "sg:city":"Etiwanda",
    "sg:classifiers":[
        {
            "category":"Building & Trades",
            "subcategory":"Construction",
            "type":"Services"
        }
    ],
    "sg:phone":"+1 909 646 7761",
    "sg:postcode":"91739",
    "sg:province":"CA",
    "sg:tags":[
        "contractor"
    ],
    "wof:name":"Wl Butler Construction",
    "wof:placetype":"venue"
},
  "geometry": {"coordinates":[-117.538777,34.106434],"type":"Point"}
}