{
  "type": "Feature",
  "properties": {
    "addr:full":"1710 Pier B St Long Beach CA 90813",
    "addr:housenumber":"1710",
    "addr:postcode":"90813",
    "addr:street":"Pier B St",
    "iso:country":"US",
    "sg:address":"1710 Pier B St",
    "sg:city":"Long Beach",
    "sg:classifiers":[
        {
            "category":"Professional",
            "subcategory":"Advertising",
            "type":"Services"
        }
    ],
    "sg:phone":"+1 562 436 2271",
    "sg:postcode":"90813",
    "sg:province":"CA",
    "sg:tags":[
        "distribution"
    ],
    "sg:website":"www.jhbaxter.com",
    "wof:name":"J H Baxter & Co",
    "wof:placetype":"venue"
},
  "geometry": {"coordinates":[-118.223624,33.780704],"type":"Point"}
}