{
  "type": "Feature",
  "properties": {
    "addr:full":"155 N 2nd St Porterville CA 93257",
    "addr:housenumber":"155",
    "addr:postcode":"93257",
    "addr:street":"N 2Nd St",
    "iso:country":"US",
    "sg:address":"155 N 2nd St",
    "sg:city":"Porterville",
    "sg:classifiers":[
        {
            "category":"Shopping",
            "subcategory":"Computers & Home Electronics",
            "type":"Retail Goods"
        }
    ],
    "sg:phone":"+1 559 782 3409",
    "sg:postcode":"93257",
    "sg:province":"CA",
    "sg:tags":[
        "television",
        "radio"
    ],
    "sg:website":"www.dvs2000.com",
    "wof:name":"Don's TV Svc",
    "wof:placetype":"venue"
},
  "geometry": {"coordinates":[-119.015225,36.068656],"type":"Point"}
}