{
  "type": "Feature",
  "properties": {
    "iso:country":"US",
    "sg:address":"318 W 6th Street",
    "sg:city":"Los Angeles",
    "sg:classifiers":[
        {
            "category":"Shopping",
            "subcategory":"Jewelry",
            "type":"Retail Goods"
        }
    ],
    "sg:phone":"+1 213 624 8383",
    "sg:postcode":"90014",
    "sg:province":"CA",
    "sg:website":"www.orou.com",
    "wof:name":"Oro U",
    "wof:placetype":"venue"
},
  "geometry": {"coordinates":[-118.25266499999999,34.04708],"type":"Point"}
}