{
  "type": "Feature",
  "properties": {
    "addr:full":"2607 W 75th St Los Angeles CA 90043",
    "addr:housenumber":"2607",
    "addr:postcode":"90043",
    "addr:street":"W 75Th St",
    "iso:country":"US",
    "sg:address":"2607 W 75th St",
    "sg:city":"Los Angeles",
    "sg:classifiers":[
        {
            "category":"Building & Trades",
            "subcategory":"Plumbing",
            "type":"Services"
        }
    ],
    "sg:phone":"+1 323 753 5188",
    "sg:postcode":"90043",
    "sg:province":"CA",
    "sg:tags":[
        "plumbing",
        "consultant",
        "drain",
        "sewer"
    ],
    "wof:name":"Slater Plumbing",
    "wof:placetype":"venue"
},
  "geometry": {"coordinates":[-118.324253,33.971933],"type":"Point"}
}