{
  "type": "Feature",
  "properties": {
    "iso:country":"US",
    "sg:address":"3110 E Mckinley Ave",
    "sg:city":"Fresno",
    "sg:classifiers":[
        {
            "category":"Restaurant",
            "type":"Food & Drink"
        }
    ],
    "sg:menulink":"http://www.allmenus.com/ca/fresno/175027-popeyes-chicken--biscuits/menu/",
    "sg:phone":"+1 209 442 1789",
    "sg:postcode":"93703",
    "sg:province":"CA",
    "sg:tags":[
        "american",
        "wing"
    ],
    "wof:name":"Popeyes Chicken & Biscuits",
    "wof:placetype":"venue"
},
  "geometry": {"coordinates":[-119.77141899999999,36.764812],"type":"Point"}
}