{
  "type": "Feature",
  "properties": {
    "addr:full":"3870 Truxel Rd Sacramento CA 95857",
    "addr:postcode":"3870;95857",
    "addr:street":"Truxel Rd",
    "iso:country":"US",
    "sg:address":"3870 Truxel Rd",
    "sg:city":"Sacramento",
    "sg:classifiers":[
        {
            "category":"Restaurant",
            "type":"Food & Drink"
        }
    ],
    "sg:phone":"+1 916 285 8703",
    "sg:postcode":"95857",
    "sg:province":"CA",
    "sg:tags":[
        "traditional",
        "american",
        "tex-mex"
    ],
    "sg:website":"www.Chilis.com",
    "wof:name":"Chili's Grill & Bar",
    "wof:placetype":"venue"
},
  "geometry": {"coordinates":[-121.50381400000001,38.638481],"type":"Point"}
}