{
  "type": "Feature",
  "properties": {
    "iso:country":"US",
    "sg:address":"3210 W 54th St",
    "sg:city":"Los Angeles",
    "sg:classifiers":[
        {
            "category":"Shopping",
            "subcategory":"Crafts & Fabrics",
            "type":"Retail Goods"
        }
    ],
    "sg:phone":"+1 323 290 1434",
    "sg:postcode":"90043",
    "sg:province":"CA",
    "sg:tags":[
        "sewing"
    ],
    "wof:name":"Trimming Creation Source",
    "wof:placetype":"venue"
},
  "geometry": {"coordinates":[-118.329283,33.993057],"type":"Point"}
}