{
  "type": "Feature",
  "properties": {
    "addr:full":"735 S Figueroa St Los Angeles CA 90017",
    "addr:housenumber":"735",
    "addr:postcode":"90017",
    "addr:street":"S Figueroa St",
    "iso:country":"US",
    "sg:address":"735 S Figueroa St",
    "sg:city":"Los Angeles",
    "sg:classifiers":[
        {
            "category":"Personal",
            "type":"Services"
        }
    ],
    "sg:phone":"+1 213 624 6111",
    "sg:postcode":"90017",
    "sg:province":"CA",
    "sg:tags":[
        "local"
    ],
    "wof:name":"Authorized AT&T Store",
    "wof:placetype":"venue"
},
  "geometry": {"coordinates":[-118.260891,34.049602],"type":"Point"}
}