{
  "type": "Feature",
  "properties": {
    "addr:full":"3351 Centre Lake Dr Ontario CA 91761",
    "addr:housenumber":"3351",
    "addr:postcode":"91761",
    "addr:street":"Centre Lake Dr",
    "iso:country":"US",
    "sg:address":"3351 Centre Lake Dr",
    "sg:city":"Ontario",
    "sg:classifiers":[
        {
            "category":"Restaurant",
            "type":"Food & Drink"
        }
    ],
    "sg:menulink":"http://www.allmenus.com/ca/san-bernardino/75263-tgi-fridays/menu/",
    "sg:phone":"+1 909 390 0052",
    "sg:postcode":"91761",
    "sg:province":"CA",
    "sg:tags":[
        "american"
    ],
    "wof:name":"T.G.I. Friday's",
    "wof:placetype":"venue"
},
  "geometry": {"coordinates":[-117.57933199999999,34.066862],"type":"Point"}
}