{
  "type": "Feature",
  "properties": {
    "addr:full":"1128 Tasmania Way Modesto CA 95356",
    "addr:housenumber":"1128",
    "addr:postcode":"ca 95356",
    "addr:street":"Tasmania Way",
    "iso:country":"US",
    "sg:address":"1128 Tasmania Way",
    "sg:city":"Modesto",
    "sg:classifiers":[
        {
            "category":"Home & Garden",
            "subcategory":"Carpets & Floor Coverings",
            "type":"Retail Goods"
        }
    ],
    "sg:phone":"+1 209 527 1588",
    "sg:postcode":"95356",
    "sg:province":"CA",
    "wof:name":"Jim Maher Floor Covering",
    "wof:placetype":"venue"
},
  "geometry": {"coordinates":[-121.01079300000001,37.694437],"type":"Point"}
}