{
  "type": "Feature",
  "properties": {
    "iso:country":"US",
    "sg:address":"443 Webster St",
    "sg:city":"Monterey",
    "sg:classifiers":[
        {
            "category":"Sports & Exercise",
            "subcategory":"Gym",
            "type":"Entertainment"
        }
    ],
    "sg:phone":"+1 831 373 8446",
    "sg:postcode":"93940",
    "sg:province":"CA",
    "sg:tags":[
        "club",
        "health",
        "studio",
        "gymnasium"
    ],
    "wof:name":"Slender Lady Weight Loss/Fitns",
    "wof:placetype":"venue"
},
  "geometry": {"coordinates":[-121.891232,36.596934],"type":"Point"}
}