{
  "type": "Feature",
  "properties": {
    "iso:country":"US",
    "sg:address":"1840 Arrow Hwy",
    "sg:city":"La Verne",
    "sg:classifiers":[
        {
            "category":"Professional",
            "subcategory":"Art Services",
            "type":"Services"
        }
    ],
    "sg:phone":"+1 909 392 0213",
    "sg:postcode":"91750",
    "sg:province":"CA",
    "sg:tags":[
        "development",
        "package",
        "designing"
    ],
    "wof:name":"Legend International",
    "wof:placetype":"venue"
},
  "geometry": {"coordinates":[-117.775908,34.098925],"type":"Point"}
}