{
  "type": "Feature",
  "properties": {
    "addr:full":"1122 Golden Way Los Altos CA 94024",
    "addr:housenumber":"1122",
    "addr:postcode":"94024",
    "addr:street":"Golden Way",
    "iso:country":"US",
    "sg:address":"1122 Golden Way",
    "sg:city":"Los Altos",
    "sg:classifiers":[
        {
            "category":"Professional",
            "subcategory":"Art Services",
            "type":"Services"
        }
    ],
    "sg:phone":"+1 650 967 3811",
    "sg:postcode":"94024",
    "sg:province":"CA",
    "sg:tags":[
        "artist"
    ],
    "wof:name":"Jim Mc Guinness Design",
    "wof:placetype":"venue"
},
  "geometry": {"coordinates":[-122.090963,37.363669],"type":"Point"}
}