{
  "type": "Feature",
  "properties": {
    "iso:country":"US",
    "sg:address":"3855 W 111th Pl",
    "sg:city":"Inglewood",
    "sg:classifiers":[
        {
            "category":"Utilities",
            "type":"Services"
        }
    ],
    "sg:phone":"+1 310 671 4564",
    "sg:postcode":"90303",
    "sg:province":"CA",
    "sg:tags":[
        "sanitary"
    ],
    "wof:name":"Fitos Sweeping",
    "wof:placetype":"venue"
},
  "geometry": {"coordinates":[-118.34383800000001,33.933941],"type":"Point"}
}