{
  "type": "Feature",
  "properties": {
    "iso:country":"US",
    "sg:address":"18200 Yorba Linda Blvd",
    "sg:city":"Yorba Linda",
    "sg:classifiers":[
        {
            "category":"Health Services",
            "subcategory":"Clinic",
            "type":"Services"
        }
    ],
    "sg:phone":"+1 714 528 0100",
    "sg:postcode":"92886",
    "sg:province":"CA",
    "sg:tags":[
        "counseling",
        "mental"
    ],
    "sg:website":"www.drmichaelperrotti.com",
    "wof:name":"Perrotti Michael Dr PHD Inc",
    "wof:placetype":"venue"
},
  "geometry": {"coordinates":[-117.816002,33.888401],"type":"Point"}
}