{
  "type": "Feature",
  "properties": {
    "addr:full":"9155 Deschutes Rd Palo Cedro CA 96073",
    "addr:housenumber":"9155",
    "addr:postcode":"96073",
    "addr:street":"Deschutes Rd",
    "iso:country":"US",
    "sg:address":"9155 Deschutes Rd",
    "sg:city":"Palo Cedro",
    "sg:classifiers":[
        {
            "category":"Utilities",
            "subcategory":"Cable",
            "type":"Services"
        }
    ],
    "sg:phone":"+1 530 547 5438",
    "sg:postcode":"96073",
    "sg:province":"CA",
    "sg:tags":[
        "television"
    ],
    "wof:name":"Dca Cable Inc",
    "wof:placetype":"venue"
},
  "geometry": {"coordinates":[-122.23855500000001,40.561622],"type":"Point"}
}