{
  "type": "Feature",
  "properties": {
    "addr:full":"8736 Production Ave San Diego CA 92121",
    "addr:housenumber":"8736",
    "addr:postcode":"92121",
    "addr:street":"Production Ave",
    "iso:country":"US",
    "sg:address":"8736 Production Ave",
    "sg:city":"San Diego",
    "sg:classifiers":[
        {
            "category":"Professional",
            "subcategory":"Engineering",
            "type":"Services"
        }
    ],
    "sg:phone":"+1 858 566 8855",
    "sg:postcode":"92121",
    "sg:province":"CA",
    "sg:tags":[
        "engineer"
    ],
    "wof:name":"Delta Engineering Consulting",
    "wof:placetype":"venue"
},
  "geometry": {"coordinates":[-117.16591,32.882195],"type":"Point"}
}