{
  "type": "Feature",
  "properties": {
    "addr:full":"4839 Snowden Ave Lakewood CA 90713",
    "addr:housenumber":"4839",
    "addr:postcode":"90713",
    "addr:street":"Snowden Ave",
    "iso:country":"US",
    "sg:address":"4839 Snowden Ave",
    "sg:city":"Lakewood",
    "sg:classifiers":[
        {
            "category":"Utilities",
            "subcategory":"Telephone",
            "type":"Services"
        }
    ],
    "sg:phone":"+1 562 490 3514",
    "sg:postcode":"90713",
    "sg:province":"CA",
    "sg:tags":[
        "internet"
    ],
    "wof:name":"BNH Enterprises Inc",
    "wof:placetype":"venue"
},
  "geometry": {"coordinates":[-118.111428,33.844295],"type":"Point"}
}