{
  "type": "Feature",
  "properties": {
    "addr:full":"2127 University Ave Berkeley CA 94704",
    "addr:housenumber":"2127",
    "addr:postcode":"94704",
    "addr:street":"University Ave",
    "iso:country":"US",
    "sg:address":"2127 University Ave",
    "sg:city":"Berkeley",
    "sg:classifiers":[
        {
            "category":"Restaurant",
            "type":"Food & Drink"
        }
    ],
    "sg:menulink":"http://www.allmenus.com/ca/berkeley/17821-dominos-pizza/menu/",
    "sg:phone":"+1 510 849 9000",
    "sg:postcode":"94704",
    "sg:province":"CA",
    "sg:tags":[
        "american",
        "wing",
        "pizza"
    ],
    "wof:name":"Domino's Pizza",
    "wof:placetype":"venue"
},
  "geometry": {"coordinates":[-122.26746799999999,37.872321],"type":"Point"}
}