{
  "type": "Feature",
  "properties": {
    "addr:full":"1659 Branham Ln San Jose CA 95118",
    "addr:housenumber":"1659",
    "addr:postcode":"95118",
    "addr:street":"Branham Ln",
    "iso:country":"US",
    "sg:address":"1659 Branham Ln",
    "sg:city":"San Jose",
    "sg:classifiers":[
        {
            "category":"Insurance",
            "subcategory":"Insurance Agent",
            "type":"Services"
        }
    ],
    "sg:phone":"+1 408 979 2990",
    "sg:postcode":"95118",
    "sg:province":"CA",
    "wof:name":"Allstate Insurance",
    "wof:placetype":"venue"
},
  "geometry": {"coordinates":[-121.90504900000001,37.252625],"type":"Point"}
}