{
  "type": "Feature",
  "properties": {
    "addr:full":"270 Columbus Ave San Francisco CA 94133",
    "addr:housenumber":"270",
    "addr:postcode":"94133",
    "addr:street":"Columbus Ave",
    "iso:country":"US",
    "sg:address":"270 Columbus Ave",
    "sg:city":"San Francisco",
    "sg:classifiers":[
        {
            "category":"Bars & Pubs",
            "type":"Food & Drink"
        }
    ],
    "sg:phone":"+1 415 956 1112",
    "sg:postcode":"94133",
    "sg:province":"CA",
    "wof:name":"Star 67",
    "wof:placetype":"venue"
},
  "geometry": {"coordinates":[-122.406465,37.797787],"type":"Point"}
}