{
  "type": "Feature",
  "properties": {
    "addr:full":"5659 Lankershim Blvd North Hollywood CA 91601",
    "addr:housenumber":"5659",
    "addr:postcode":"91601",
    "addr:street":"Lankershim Blvd",
    "iso:country":"US",
    "sg:address":"5659 Lankershim Blvd",
    "sg:city":"North Hollywood",
    "sg:classifiers":[
        {
            "category":"Retail",
            "subcategory":"Repair Shop",
            "type":"Services"
        }
    ],
    "sg:phone":"+1 818 761 4107",
    "sg:postcode":"91601",
    "sg:province":"CA",
    "sg:tags":[
        "equipment",
        "conditioning",
        "air"
    ],
    "wof:name":"A & R Homes Svc",
    "wof:placetype":"venue"
},
  "geometry": {"coordinates":[-118.37964700000001,34.172864],"type":"Point"}
}