{
  "type": "Feature",
  "properties": {
    "addr:full":"10537 San Fernando Rd Pacoima CA 91331",
    "addr:housenumber":"10537",
    "addr:postcode":"91331",
    "addr:street":"San Fernando Rd",
    "iso:country":"US",
    "sg:address":"10537 San Fernando Rd",
    "sg:city":"Pacoima",
    "sg:classifiers":[
        {
            "category":"Manufacturing",
            "subcategory":"Metals",
            "type":"Manufacturing & Wholesale Goods"
        }
    ],
    "sg:phone":"+1 818 890 6095",
    "sg:postcode":"91331",
    "sg:province":"CA",
    "sg:tags":[
        "rod",
        "iron"
    ],
    "wof:name":"1-0-1 Iron Works",
    "wof:placetype":"venue"
},
  "geometry": {"coordinates":[-118.417683,34.261526],"type":"Point"}
}