{
  "type": "Feature",
  "properties": {
    "addr:full":"2108 16th Ave Sacramento CA 95822",
    "addr:housenumber":"2108",
    "addr:postcode":"95822",
    "addr:street":"16Th Ave",
    "iso:country":"US",
    "sg:address":"2108 16th Ave",
    "sg:city":"Sacramento",
    "sg:classifiers":[
        {
            "category":"Food & Beverages",
            "subcategory":"Groceries & Convenience Stores",
            "type":"Retail Goods"
        }
    ],
    "sg:phone":"+1 916 498 9378",
    "sg:postcode":"95822",
    "sg:province":"CA",
    "wof:name":"J & J Co.",
    "wof:placetype":"venue"
},
  "geometry": {"coordinates":[-121.490005,38.536457],"type":"Point"}
}