{
  "type": "Feature",
  "properties": {
    "iso:country":"US",
    "sg:address":"260 Oller St",
    "sg:city":"Mendota",
    "sg:classifiers":[
        {
            "category":"Restaurant",
            "type":"Food & Drink"
        }
    ],
    "sg:phone":"+1 559 655 4994",
    "sg:postcode":"93640",
    "sg:province":"CA",
    "wof:name":"Chvelas Mexican Food",
    "wof:placetype":"venue"
},
  "geometry": {"coordinates":[-120.385064,36.75934],"type":"Point"}
}