{
  "type": "Feature",
  "properties": {
    "addr:full":"416 Ignacio Blvd Novato CA 94949",
    "addr:housenumber":"416",
    "addr:postcode":"94949",
    "addr:street":"Ignacio Blvd",
    "iso:country":"US",
    "sg:address":"416 Ignacio Blvd",
    "sg:city":"Novato",
    "sg:classifiers":[
        {
            "category":"Personal",
            "type":"Services"
        }
    ],
    "sg:phone":"+1 415 382 0752",
    "sg:postcode":"94949",
    "sg:province":"CA",
    "sg:tags":[
        "sewing",
        "alteration"
    ],
    "wof:name":"Clothes Fit",
    "wof:placetype":"venue"
},
  "geometry": {"coordinates":[-122.542,38.624713],"type":"Point"}
}