{
  "type": "Feature",
  "properties": {
    "iso:country":"US",
    "sg:address":"2005 Court St",
    "sg:city":"Redding",
    "sg:classifiers":[
        {
            "category":"Health Services",
            "subcategory":"Chiropractor",
            "type":"Services"
        }
    ],
    "sg:phone":"+1 530 243 2300",
    "sg:postcode":"96001",
    "sg:province":"CA",
    "wof:name":"Carrino Chiropractic Inc",
    "wof:placetype":"venue"
},
  "geometry": {"coordinates":[-122.393345,40.577945],"type":"Point"}
}