{
  "type": "Feature",
  "properties": {
    "addr:full":"95831 Summit Dr Chilcoot CA 96105",
    "addr:housenumber":"95831",
    "addr:postcode":"96105",
    "addr:street":"Summit Dr",
    "iso:country":"US",
    "sg:address":"95831 Summit Dr",
    "sg:city":"Chilcoot",
    "sg:classifiers":[
        {
            "category":"Building & Trades",
            "subcategory":"Construction",
            "type":"Services"
        }
    ],
    "sg:phone":"+1 530 993 4522",
    "sg:postcode":"96105",
    "sg:province":"CA",
    "sg:tags":[
        "contractor"
    ],
    "wof:name":"Horizon Construction",
    "wof:placetype":"venue"
},
  "geometry": {"coordinates":[-120.131541,39.791366],"type":"Point"}
}