{
  "type": "Feature",
  "properties": {
    "addr:full":"2140 Fairlane Rd Yreka CA 96097",
    "addr:housenumber":"2140",
    "addr:postcode":"96097",
    "addr:street":"Fairlane Rd",
    "iso:country":"US",
    "sg:address":"2140 Fairlane Rd",
    "sg:city":"Yreka",
    "sg:classifiers":[
        {
            "category":"Retail",
            "subcategory":"Auto Repair",
            "type":"Services"
        }
    ],
    "sg:phone":"+1 530 842 0752",
    "sg:postcode":"96097",
    "sg:province":"CA",
    "sg:tags":[
        "repairing",
        "automobile"
    ],
    "wof:name":"Jasmer Automotive & Racing",
    "wof:placetype":"venue"
},
  "geometry": {"coordinates":[-122.639061,41.696476],"type":"Point"}
}