{
  "type": "Feature",
  "properties": {
    "iso:country":"US",
    "sg:address":"3820 S Hill St",
    "sg:city":"Los Angeles",
    "sg:classifiers":[
        {
            "category":"Wholesale",
            "subcategory":"Durable Goods & Equipment",
            "type":"Manufacturing & Wholesale Goods"
        }
    ],
    "sg:phone":"+1 323 235 4100",
    "sg:postcode":"90037",
    "sg:province":"CA",
    "sg:tags":[
        "importer"
    ],
    "wof:name":"Alliage Inc",
    "wof:placetype":"venue"
},
  "geometry": {"coordinates":[-118.278864,34.013376],"type":"Point"}
}