{
  "type": "Feature",
  "properties": {
    "addr:full":"28231 Marguerite Pkway Ste 4 Mission Viejo CA 92691",
    "addr:housenumber":"28231",
    "addr:postcode":"92691",
    "addr:street":"Marguerite Pkway Ste 4",
    "iso:country":"US",
    "sg:address":"28231 Marguerite Pkway Ste 4",
    "sg:city":"Mission Viejo",
    "sg:classifiers":[
        {
            "category":"Personal",
            "subcategory":"Beauty Salon",
            "type":"Services"
        }
    ],
    "sg:phone":"+1 949 413 0923",
    "sg:postcode":"92691",
    "sg:province":"CA",
    "sg:tags":[
        "hair"
    ],
    "sg:website":"www.dianeelizabethsalon.com",
    "wof:name":"Diane Elizabeth Salon & Day Spa",
    "wof:placetype":"venue"
},
  "geometry": {"coordinates":[-117.670503,33.553793],"type":"Point"}
}