{
  "type": "Feature",
  "properties": {
    "iso:country":"US",
    "sg:address":"930 Alhambra Blvd Ste 230",
    "sg:city":"Sacramento",
    "sg:classifiers":[
        {
            "category":"Professional",
            "subcategory":"Advertising",
            "type":"Services"
        }
    ],
    "sg:phone":"+1 916 551 1776",
    "sg:postcode":"95816",
    "sg:province":"CA",
    "sg:tags":[
        "agency"
    ],
    "wof:name":"Hanzlik Media Mgmt.",
    "wof:placetype":"venue"
},
  "geometry": {"coordinates":[-121.464915,38.573543],"type":"Point"}
}