{
  "type": "Feature",
  "properties": {
    "addr:full":"641 Norseman Dr Modesto CA 95357",
    "addr:housenumber":"641",
    "addr:postcode":"ca 95357",
    "addr:street":"Norseman Dr",
    "iso:country":"US",
    "sg:address":"641 Norseman Dr",
    "sg:city":"Modesto",
    "sg:classifiers":[
        {
            "category":"Education",
            "subcategory":"School",
            "type":"Public Place"
        }
    ],
    "sg:phone":"+1 209 576 4702",
    "sg:postcode":"95357",
    "sg:province":"CA",
    "sg:tags":[
        "high",
        "middle",
        "elementary"
    ],
    "wof:name":"Johansen Peter High School",
    "wof:placetype":"venue"
},
  "geometry": {"coordinates":[-120.917,37.644798],"type":"Point"}
}