{
  "type": "Feature",
  "properties": {
    "addr:full":"26814 Neff Ct Santa Clarita CA 91351",
    "addr:housenumber":"26814",
    "addr:postcode":"91351",
    "addr:street":"Neff Ct",
    "iso:country":"US",
    "sg:address":"26814 Neff Ct",
    "sg:city":"Santa Clarita",
    "sg:classifiers":[
        {
            "category":"Professional",
            "subcategory":"Art Services",
            "type":"Services"
        }
    ],
    "sg:phone":"+1 661 252 9756",
    "sg:postcode":"91351",
    "sg:province":"CA",
    "sg:tags":[
        "graphic",
        "designer"
    ],
    "wof:name":"Craycraft Creative",
    "wof:placetype":"venue"
},
  "geometry": {"coordinates":[-118.49018,34.414342],"type":"Point"}
}