{
  "type": "Feature",
  "properties": {
    "iso:country":"US",
    "sg:address":"181 Belvedere St",
    "sg:city":"San Francisco",
    "sg:classifiers":[
        {
            "category":"Social Services",
            "type":"Services"
        }
    ],
    "sg:phone":"+1 415 665 2539",
    "sg:postcode":"94117",
    "sg:province":"CA",
    "sg:tags":[
        "organization",
        "welfare"
    ],
    "wof:name":"Alfa Homes",
    "wof:placetype":"venue"
},
  "geometry": {"coordinates":[-122.449074,37.766872],"type":"Point"}
}