{
  "type": "Feature",
  "properties": {
    "iso:country":"US",
    "sg:address":"1818 Tully Rd",
    "sg:city":"San Jose",
    "sg:classifiers":[
        {
            "category":"Shopping",
            "subcategory":"Clothing, Apparel, & Fashions",
            "type":"Retail Goods"
        }
    ],
    "sg:phone":"+1 408 270 3809",
    "sg:postcode":"95122",
    "sg:province":"CA",
    "sg:tags":[
        "clothing",
        "women's"
    ],
    "wof:name":"L'mour Fashion",
    "wof:placetype":"venue"
},
  "geometry": {"coordinates":[-121.82468299999999,37.323073],"type":"Point"}
}