{
  "type": "Feature",
  "properties": {
    "addr:full":"4003 Lana Ter Fremont CA 94536",
    "addr:housenumber":"4003",
    "addr:postcode":"94536",
    "addr:street":"Lana Ter",
    "iso:country":"US",
    "sg:address":"4003 Lana Ter",
    "sg:city":"Fremont",
    "sg:classifiers":[
        {
            "category":"Real Estate",
            "subcategory":"Real Estate Agent",
            "type":"Services"
        }
    ],
    "sg:phone":"+1 510 793 8610",
    "sg:postcode":"94536",
    "sg:province":"CA",
    "sg:tags":[
        "inspection"
    ],
    "wof:name":"T Dragon Property Inspection",
    "wof:placetype":"venue"
},
  "geometry": {"coordinates":[-122.023882,37.566371],"type":"Point"}
}