{
  "type": "Feature",
  "properties": {
    "addr:full":"5775 Van Buren Blvd Riverside CA 92503",
    "addr:housenumber":"5775",
    "addr:postcode":"92503",
    "addr:street":"Van Buren Blvd",
    "iso:country":"US",
    "sg:address":"5775 Van Buren Blvd",
    "sg:city":"Riverside",
    "sg:classifiers":[
        {
            "category":"Restaurant",
            "type":"Food & Drink"
        }
    ],
    "sg:menulink":"http://www.allmenus.com/ca/riverside/164418-wienerschnitzel/menu/",
    "sg:phone":"+1 951 785 1788",
    "sg:postcode":"92503",
    "sg:province":"CA",
    "sg:tags":[
        "sandwich",
        "dog",
        "burger",
        "hot",
        "wrap",
        "american"
    ],
    "wof:name":"Wienerschnitzel",
    "wof:placetype":"venue"
},
  "geometry": {"coordinates":[-117.45351100000001,33.941103],"type":"Point"}
}