{
  "type": "Feature",
  "properties": {
    "addr:full":"8324 Cereus Way Antelope CA 95843",
    "addr:housenumber":"8324",
    "addr:postcode":"95843",
    "addr:street":"Cereus Way",
    "iso:country":"US",
    "sg:address":"8324 Cereus Way",
    "sg:city":"Antelope",
    "sg:classifiers":[
        {
            "category":"Wholesale",
            "subcategory":"Machinery & Supplies",
            "type":"Manufacturing & Wholesale Goods"
        }
    ],
    "sg:phone":"+1 916 212 8107",
    "sg:postcode":"95843",
    "sg:province":"CA",
    "sg:tags":[
        "printing"
    ],
    "wof:name":"ASAP Internet Marketing",
    "wof:placetype":"venue"
},
  "geometry": {"coordinates":[-121.353532,38.720937],"type":"Point"}
}