{
  "type": "Feature",
  "properties": {
    "iso:country":"US",
    "sg:address":"922 New York St",
    "sg:city":"Redlands",
    "sg:classifiers":[
        {
            "category":"Professional",
            "subcategory":"Printing & Photocopies",
            "type":"Services"
        }
    ],
    "sg:phone":"+1 909 792 3478",
    "sg:postcode":"92374",
    "sg:province":"CA",
    "sg:tags":[
        "blueprinting"
    ],
    "sg:website":"www.redlandsblueprint.com",
    "wof:name":"Redlands Blueprint & Coml",
    "wof:placetype":"venue"
},
  "geometry": {"coordinates":[-117.19548500000001,34.064439],"type":"Point"}
}