{
  "type": "Feature",
  "properties": {
    "iso:country":"US",
    "sg:address":"2140 Grand Ave",
    "sg:city":"Chino Hills",
    "sg:classifiers":[
        {
            "category":"Health Services",
            "subcategory":"Health Practitioner",
            "type":"Services"
        }
    ],
    "sg:phone":"+1 909 630 7878",
    "sg:postcode":"91709",
    "sg:province":"CA",
    "sg:tags":[
        "therapist",
        "physical"
    ],
    "wof:name":"Pomona Valley Hospital",
    "wof:placetype":"venue"
},
  "geometry": {"coordinates":[-117.75515799999999,33.99815],"type":"Point"}
}