{
  "type": "Feature",
  "properties": {
    "iso:country":"US",
    "sg:address":"4289 Dogwood Ave",
    "sg:city":"Seal Beach",
    "sg:classifiers":[
        {
            "category":"Personal",
            "subcategory":"Tanning Parlor",
            "type":"Services"
        }
    ],
    "sg:phone":"+1 714 454 4149",
    "sg:postcode":"92740",
    "sg:province":"CA",
    "wof:name":"Breanna's Mobile Spray Tan",
    "wof:placetype":"venue"
},
  "geometry": {"coordinates":[-118.056861,33.777565],"type":"Point"}
}