{
  "type": "Feature",
  "properties": {
    "iso:country":"US",
    "sg:address":"678 Mirada Ave",
    "sg:city":"Stanford",
    "sg:classifiers":[
        {
            "category":"Professional",
            "type":"Services"
        }
    ],
    "sg:phone":"+1 650 321 1436",
    "sg:postcode":"94305",
    "sg:province":"CA",
    "wof:name":"Patrick Suppes As Trustee",
    "wof:placetype":"venue"
},
  "geometry": {"coordinates":[-122.167655,37.41629],"type":"Point"}
}