{
  "type": "Feature",
  "properties": {
    "addr:full":"1320 Willow Rd Menlo Park CA 94025",
    "addr:housenumber":"1320",
    "addr:postcode":"94025",
    "addr:street":"Willow Rd",
    "iso:country":"US",
    "sg:address":"1320 Willow Rd",
    "sg:city":"Menlo Park",
    "sg:classifiers":[
        {
            "category":"Professional",
            "subcategory":"Detective & Security Services",
            "type":"Services"
        }
    ],
    "sg:phone":"+1 650 617 4548",
    "sg:postcode":"94025",
    "sg:province":"CA",
    "sg:tags":[
        "car",
        "armored"
    ],
    "wof:name":"Armor Transport Systems Inc",
    "wof:placetype":"venue"
},
  "geometry": {"coordinates":[-122.153217,37.475249],"type":"Point"}
}