{
  "type": "Feature",
  "properties": {
    "iso:country":"US",
    "sg:address":"6700 Independence Ave",
    "sg:city":"Canoga Park",
    "sg:classifiers":[
        {
            "category":"Local Transit",
            "type":"Transportation"
        }
    ],
    "sg:phone":"+1 818 262 4470",
    "sg:postcode":"91303",
    "sg:province":"CA",
    "sg:tags":[
        "limousine"
    ],
    "wof:name":"Raven Limousine Svc",
    "wof:placetype":"venue"
},
  "geometry": {"coordinates":[-118.590592,34.193773],"type":"Point"}
}