{
  "type": "Feature",
  "properties": {
    "iso:country":"US",
    "sg:address":"23300 Cinema Dr",
    "sg:city":"Santa Clarita",
    "sg:classifiers":[
        {
            "category":"Sports & Exercise",
            "subcategory":"Swimming Pool",
            "type":"Entertainment"
        }
    ],
    "sg:phone":"+1 661 255 1062",
    "sg:postcode":"91355",
    "sg:province":"CA",
    "sg:website":"www.tuscanypools.com",
    "wof:name":"Tuscany Pools",
    "wof:placetype":"venue"
},
  "geometry": {"coordinates":[-118.542034,34.419152],"type":"Point"}
}