{
  "type": "Feature",
  "properties": {
    "iso:country":"US",
    "sg:address":"5145 El Camino Real",
    "sg:city":"Atascadero",
    "sg:classifiers":[
        {
            "category":"Food & Beverages",
            "subcategory":"Liquor & Beverages",
            "type":"Retail Goods"
        }
    ],
    "sg:phone":"+1 805 461 9477",
    "sg:postcode":"93422",
    "sg:province":"CA",
    "sg:tags":[
        "store"
    ],
    "wof:name":"Stagecoach Liquor",
    "wof:placetype":"venue"
},
  "geometry": {"coordinates":[-120.67874999999999,35.494473],"type":"Point"}
}