{
  "type": "Feature",
  "properties": {
    "iso:country":"US",
    "sg:address":"6464 W Sunset Blvd",
    "sg:city":"Los Angeles",
    "sg:classifiers":[
        {
            "category":"Manufacturing",
            "subcategory":"Tools & Machinery",
            "type":"Manufacturing & Wholesale Goods"
        }
    ],
    "sg:phone":"+1 562 404 4262",
    "sg:postcode":"90028",
    "sg:province":"CA",
    "sg:tags":[
        "industrial",
        "mfg"
    ],
    "wof:name":"Beartech 2000 Inc",
    "wof:placetype":"venue"
},
  "geometry": {"coordinates":[-118.33156,34.097986],"type":"Point"}
}