{
  "type": "Feature",
  "properties": {
    "iso:country":"US",
    "sfac:artist":"Garza, Carmen Lomas",
    "sfac:created_at":"01/01/1970 12:33:19 AM +0000",
    "sfac:credit_line":"Commissioned for the San Francisco International Airport; Collection of the City and County of San Francisco",
    "sfac:display_dimensions":"16' H X 24' W",
    "sfac:location_description":"Airport : IT : Boarding Area G : Gate G93",
    "sfac:medium":"Copper and powder-coated steel.",
    "sfac:revision":"2-9a52e10df7926454038bcec2709d0fd7",
    "sfac:title":"Baile!",
    "wof:name":"Baile!",
    "wof:placetype":"venue"
},
  "geometry": {"coordinates":[-122.389979,37.615223],"type":"Point"}
}