{
  "type": "Feature",
  "properties": {
    "addr:full":"1990 Riverview Dr San Bernardino CA 92408",
    "addr:housenumber":"1990",
    "addr:postcode":"92408",
    "addr:street":"Riverview Dr",
    "iso:country":"US",
    "sg:address":"1990 Riverview Dr",
    "sg:city":"San Bernardino",
    "sg:classifiers":[
        {
            "category":"Manufacturing",
            "subcategory":"Tools & Machinery",
            "type":"Manufacturing & Wholesale Goods"
        }
    ],
    "sg:phone":"+1 909 799 8080",
    "sg:postcode":"92408",
    "sg:province":"CA",
    "sg:tags":[
        "machine",
        "shop"
    ],
    "wof:name":"Zwerner Industries",
    "wof:placetype":"venue"
},
  "geometry": {"coordinates":[-117.246002,34.081059],"type":"Point"}
}