{
  "type": "Feature",
  "properties": {
    "iso:country":"US",
    "sg:address":"2414 N Fruit Ave",
    "sg:city":"Fresno",
    "sg:classifiers":[
        {
            "category":"Food & Beverages",
            "subcategory":"Groceries & Convenience Stores",
            "type":"Retail Goods"
        }
    ],
    "sg:phone":"+1 559 224 7202",
    "sg:postcode":"93705",
    "sg:province":"CA",
    "sg:tags":[
        "grocer"
    ],
    "wof:name":"G & K Mini-Mart",
    "wof:placetype":"venue"
},
  "geometry": {"coordinates":[-119.817537,36.772852],"type":"Point"}
}