{
  "type": "Feature",
  "properties": {
    "iso:country":"US",
    "sg:address":"2325 3rd St",
    "sg:city":"San Francisco",
    "sg:classifiers":[
        {
            "category":"Shopping",
            "subcategory":"Clothing, Apparel, & Fashions",
            "type":"Retail Goods"
        }
    ],
    "sg:phone":"+1 415 621 6504",
    "sg:postcode":"94107",
    "sg:province":"CA",
    "sg:tags":[
        "baby",
        "accessory"
    ],
    "wof:name":"Little Forest",
    "wof:placetype":"venue"
},
  "geometry": {"coordinates":[-122.3882,37.758246],"type":"Point"}
}