{
  "type": "Feature",
  "properties": {
    "iso:country":"US",
    "sg:address":"1964 Westwood Blvd",
    "sg:city":"Los Angeles",
    "sg:classifiers":[
        {
            "category":"Health Services",
            "subcategory":"Health Practitioner",
            "type":"Services"
        }
    ],
    "sg:phone":"+1 310 470 6174",
    "sg:postcode":"90025",
    "sg:province":"CA",
    "sg:tags":[
        "psychotherapist"
    ],
    "wof:name":"Sherly Khodadad Mst",
    "wof:placetype":"venue"
},
  "geometry": {"coordinates":[-118.434787,34.047703],"type":"Point"}
}