{
  "type": "Feature",
  "properties": {
    "iso:country":"US",
    "sg:address":"5961 Kearny Villa Rd",
    "sg:city":"San Diego",
    "sg:classifiers":[
        {
            "category":"Professional",
            "subcategory":"Computer Services",
            "type":"Services"
        }
    ],
    "sg:phone":"+1 858 565 7224",
    "sg:postcode":"92123",
    "sg:province":"CA",
    "sg:tags":[
        "consultant",
        "designer"
    ],
    "sg:website":"www.rsft.com",
    "wof:name":"Rancho Santa Fe Technology",
    "wof:placetype":"venue"
},
  "geometry": {"coordinates":[-117.131561,32.839473],"type":"Point"}
}