{
  "type": "Feature",
  "properties": {
    "iso:country":"US",
    "sg:address":"7881 Greenback Ln",
    "sg:city":"Citrus Heights",
    "sg:classifiers":[
        {
            "category":"Shopping",
            "subcategory":"Tobacco",
            "type":"Retail Goods"
        },
        {
            "category":"Personal",
            "subcategory":"Tattoo Parlor",
            "type":"Services"
        },
        {
            "category":"Shopping",
            "subcategory":"Shoes",
            "type":"Retail Goods"
        },
        {
            "category":"Personal",
            "subcategory":"Piercing",
            "type":"Services"
        }
    ],
    "sg:phone":"+1 916 721 1128",
    "sg:postcode":"95610",
    "sg:province":"CA",
    "sg:tags":[
        "shop",
        "store"
    ],
    "wof:name":"Hair Creation-London Rock",
    "wof:placetype":"venue"
},
  "geometry": {"coordinates":[-121.272003,38.678501],"type":"Point"}
}