{
  "type": "Feature",
  "properties": {
    "addr:full":"870 Mitten Rd Burlingame CA 94010",
    "addr:housenumber":"870",
    "addr:postcode":"94010",
    "addr:street":"Mitten Rd",
    "iso:country":"US",
    "sg:address":"870 Mitten Rd",
    "sg:city":"Burlingame",
    "sg:classifiers":[
        {
            "category":"Professional",
            "type":"Services"
        }
    ],
    "sg:phone":"+1 650 259 9488",
    "sg:postcode":"94010",
    "sg:province":"CA",
    "sg:tags":[
        "establishment"
    ],
    "wof:name":"Callcomps",
    "wof:placetype":"venue"
},
  "geometry": {"coordinates":[-122.37343300000001,37.601901],"type":"Point"}
}