{
  "type": "Feature",
  "properties": {
    "addr:full":"5401 Bus Park S Bakersfield CA 93309",
    "addr:housenumber":"5401",
    "addr:postcode":"93309",
    "addr:street":"Bus Park S",
    "iso:country":"US",
    "sg:address":"5401 Bus Park S",
    "sg:city":"Bakersfield",
    "sg:classifiers":[
        {
            "category":"Insurance",
            "subcategory":"Insurance Agent",
            "type":"Services"
        }
    ],
    "sg:phone":"+1 661 327 3103",
    "sg:postcode":"93309",
    "sg:province":"CA",
    "sg:tags":[
        "processing"
    ],
    "wof:name":"Sds Claims Adjusting Co",
    "wof:placetype":"venue"
},
  "geometry": {"coordinates":[-119.06004900000001,35.357418],"type":"Point"}
}