{
  "type": "Feature",
  "properties": {
    "iso:country":"US",
    "sg:address":"455 University Ave # 270",
    "sg:city":"Sacramento",
    "sg:classifiers":[
        {
            "category":"Health Services",
            "subcategory":"Health Practitioner",
            "type":"Services"
        }
    ],
    "sg:phone":"+1 916 929 7737",
    "sg:postcode":"95825",
    "sg:province":"CA",
    "sg:tags":[
        "audiologists"
    ],
    "wof:name":"Hearing Advantage",
    "wof:placetype":"venue"
},
  "geometry": {"coordinates":[-121.418274,38.569092],"type":"Point"}
}