{
  "type": "Feature",
  "properties": {
    "addr:full":"518 Great Mall Drive Milpitas CA 95035",
    "addr:housenumber":"518",
    "addr:postcode":"95035",
    "addr:street":"Great Mall Drive",
    "iso:country":"US",
    "sg:address":"518 Great Mall Drive",
    "sg:city":"Milpitas",
    "sg:classifiers":[
        {
            "category":"Shopping",
            "subcategory":"Jewelry",
            "type":"Retail Goods"
        }
    ],
    "sg:phone":"+1 408 945 8423",
    "sg:postcode":"95035",
    "sg:province":"CA",
    "wof:name":"Bayside Watch",
    "wof:placetype":"venue"
},
  "geometry": {"coordinates":[-121.896112,37.419103],"type":"Point"}
}