{
  "type": "Feature",
  "properties": {
    "addr:full":"1741 Buchanan Street San Francisco CA 94115",
    "addr:housenumber":"1741",
    "addr:postcode":"94115",
    "addr:street":"Buchanan Street",
    "iso:country":"US",
    "sg:address":"1741 Buchanan Street",
    "sg:city":"San Francisco",
    "sg:classifiers":[
        {
            "category":"Professional",
            "subcategory":"Accounting & Tax Preparation",
            "type":"Services"
        }
    ],
    "sg:phone":"+1 415 922 8200",
    "sg:postcode":"94115",
    "sg:province":"CA",
    "sg:tags":[
        "accountant"
    ],
    "wof:name":"Moriguchi Mark CPA",
    "wof:placetype":"venue"
},
  "geometry": {"coordinates":[-122.43011,37.786369],"type":"Point"}
}