{
  "type": "Feature",
  "properties": {
    "addr:full":"2418 F St Bakersfield CA 93301",
    "addr:housenumber":"2418",
    "addr:postcode":"93301",
    "addr:street":"F St",
    "iso:country":"US",
    "sg:address":"2418 F St",
    "sg:city":"Bakersfield",
    "sg:classifiers":[
        {
            "category":"Professional",
            "type":"Services"
        }
    ],
    "sg:phone":"+1 661 325 4833",
    "sg:postcode":"93301",
    "sg:province":"CA",
    "sg:tags":[
        "establishment"
    ],
    "wof:name":"Valley Traffic School-Plus",
    "wof:placetype":"venue"
},
  "geometry": {"coordinates":[-119.023408,35.382749],"type":"Point"}
}