{
  "type": "Feature",
  "properties": {
    "addr:full":"2246 W Beverly Blvd Montebello CA 90640",
    "addr:housenumber":"2246",
    "addr:postcode":"90640",
    "addr:street":"W Beverly Blvd",
    "iso:country":"US",
    "sg:address":"2246 W Beverly Blvd",
    "sg:city":"Montebello",
    "sg:classifiers":[
        {
            "category":"Wholesale",
            "subcategory":"Medical Equipment & Supplies",
            "type":"Manufacturing & Wholesale Goods"
        }
    ],
    "sg:phone":"+1 323 721 0342",
    "sg:postcode":"90640",
    "sg:province":"CA",
    "sg:tags":[
        "physician",
        "surgeon"
    ],
    "wof:name":"Migun Montebello Ctr Inc",
    "wof:placetype":"venue"
},
  "geometry": {"coordinates":[-118.124207,34.021028],"type":"Point"}
}