{
  "type": "Feature",
  "properties": {
    "iso:country":"US",
    "sg:address":"200 W Cypress Rd",
    "sg:city":"Oakley",
    "sg:classifiers":[
        {
            "category":"Home & Garden",
            "subcategory":"Mobile Homes",
            "type":"Retail Goods"
        },
        {
            "category":"Autos & Motor Vehicles",
            "subcategory":"Recreational Vehicle Sales",
            "type":"Retail Goods"
        },
        {
            "category":"Recreation",
            "subcategory":"Campground",
            "type":"Entertainment"
        }
    ],
    "sg:phone":"+1 925 625 2238",
    "sg:postcode":"94561",
    "sg:province":"CA",
    "sg:tags":[
        "camper",
        "park"
    ],
    "wof:name":"Big Oak Mobile Home Park",
    "wof:placetype":"venue"
},
  "geometry": {"coordinates":[-121.698486,37.990582],"type":"Point"}
}