{
  "type": "Feature",
  "properties": {
    "addr:full":"900 Silver Spur Road Rolling Hills Estate CA 90274",
    "addr:housenumber":"900",
    "addr:postcode":"90274",
    "addr:street":"Silver Spur Road Rolling",
    "iso:country":"US",
    "sg:address":"900 Silver Spur Road",
    "sg:city":"Rolling Hills Estate",
    "sg:classifiers":[
        {
            "category":"Shopping",
            "subcategory":"Clothing, Apparel, & Fashions",
            "type":"Retail Goods"
        }
    ],
    "sg:phone":"+1 310 544 0885",
    "sg:postcode":"90274",
    "sg:province":"CA",
    "sg:tags":[
        "accessory",
        "clothing",
        "women's"
    ],
    "wof:name":"Christine Phillipe Company",
    "wof:placetype":"venue"
},
  "geometry": {"coordinates":[-118.36697100000001,33.770732],"type":"Point"}
}