{
  "type": "Feature",
  "properties": {
    "addr:full":"7126 Westminster Boulevard Westminster CA 92683",
    "addr:housenumber":"7126",
    "addr:postcode":"92683",
    "addr:street":"Westminster Boulevard",
    "iso:country":"US",
    "sg:address":"7126 Westminster Boulevard",
    "sg:city":"Westminster",
    "sg:classifiers":[
        {
            "category":"Food & Beverages",
            "subcategory":"Groceries & Convenience Stores",
            "type":"Retail Goods"
        }
    ],
    "sg:phone":"+1 714 892 2030",
    "sg:postcode":"92683",
    "sg:province":"CA",
    "wof:name":"99 Cent Outlet",
    "wof:placetype":"venue"
},
  "geometry": {"coordinates":[-118.004683,33.75902],"type":"Point"}
}