{
  "type": "Feature",
  "properties": {
    "iso:country":"US",
    "sg:address":"10401 Beach Blvd",
    "sg:city":"Stanton",
    "sg:classifiers":[
        {
            "category":"Shopping",
            "type":"Retail Goods"
        }
    ],
    "sg:phone":"+1 714 952 8703",
    "sg:postcode":"90680",
    "sg:province":"CA",
    "sg:tags":[
        "cosmetic",
        "perfume"
    ],
    "wof:name":"Jays Perfumes",
    "wof:placetype":"venue"
},
  "geometry": {"coordinates":[-117.993286,33.811735],"type":"Point"}
}