{
  "type": "Feature",
  "properties": {
    "iso:country":"US",
    "sg:address":"450 Sheridan Ave",
    "sg:city":"Palo Alto",
    "sg:classifiers":[
        {
            "category":"Banks & Credit Unions",
            "subcategory":"Financial Services",
            "type":"Services"
        }
    ],
    "sg:phone":"+1 650 324 1390",
    "sg:postcode":"94306",
    "sg:province":"CA",
    "sg:tags":[
        "program",
        "scholarship"
    ],
    "sg:website":"www.valleyscholars.org",
    "wof:name":"Valley Scholars",
    "wof:placetype":"venue"
},
  "geometry": {"coordinates":[-122.142366,37.424359],"type":"Point"}
}