{
  "type": "Feature",
  "properties": {
    "iso:country":"US",
    "sg:address":"6125 Pacific Boulevard",
    "sg:city":"Huntington Park",
    "sg:classifiers":[
        {
            "category":"Shopping",
            "subcategory":"Shoes",
            "type":"Retail Goods"
        }
    ],
    "sg:phone":"+1 323 587 2722",
    "sg:postcode":"90255",
    "sg:province":"CA",
    "sg:tags":[
        "store"
    ],
    "sg:website":"www.warehouseshoesale.com",
    "wof:name":"Warehouse Shoe Sale",
    "wof:placetype":"venue"
},
  "geometry": {"coordinates":[-118.225105,33.984733],"type":"Point"}
}