{
  "type": "Feature",
  "properties": {
    "addr:full":"247 F St Chula Vista CA 91910",
    "addr:housenumber":"247",
    "addr:postcode":"91910",
    "addr:street":"F St",
    "iso:country":"US",
    "sg:address":"247 F St",
    "sg:city":"Chula Vista",
    "sg:classifiers":[
        {
            "category":"Health Services",
            "subcategory":"Doctor",
            "type":"Services"
        }
    ],
    "sg:phone":"+1 619 422 5317",
    "sg:postcode":"91910",
    "sg:province":"CA",
    "sg:tags":[
        "dentist"
    ],
    "wof:name":"Wayne R Harrison DDS",
    "wof:placetype":"venue"
},
  "geometry": {"coordinates":[-117.07698000000001,32.642192],"type":"Point"}
}