{
  "type": "Feature",
  "properties": {
    "iso:country":"US",
    "sg:address":"3371 National Ave",
    "sg:city":"San Diego",
    "sg:classifiers":[
        {
            "category":"Restaurant",
            "type":"Food & Drink"
        }
    ],
    "sg:phone":"+1 619 696 7550",
    "sg:postcode":"92113",
    "sg:province":"CA",
    "sg:tags":[
        "seafood"
    ],
    "wof:name":"Shrimp Works",
    "wof:placetype":"venue"
},
  "geometry": {"coordinates":[-117.12200199999999,32.696098],"type":"Point"}
}