{
  "type": "Feature",
  "properties": {
    "addr:full":"4280 Katella Ave Los Alamitos CA 90720",
    "addr:housenumber":"4280",
    "addr:postcode":"90720",
    "addr:street":"Katella Ave",
    "iso:country":"US",
    "sg:address":"4280 Katella Ave",
    "sg:city":"Los Alamitos",
    "sg:classifiers":[
        {
            "category":"Restaurant",
            "type":"Food & Drink"
        }
    ],
    "sg:phone":"+1 562 430 9031",
    "sg:postcode":"90720",
    "sg:province":"CA",
    "wof:name":"City Sandwich Company",
    "wof:placetype":"venue"
},
  "geometry": {"coordinates":[-118.057999,33.802898],"type":"Point"}
}