{
  "type": "Feature",
  "properties": {
    "iso:country":"US",
    "sg:address":"356 Fairview Way",
    "sg:city":"Milpitas",
    "sg:classifiers":[
        {
            "category":"Professional",
            "subcategory":"Accounting & Tax Preparation",
            "type":"Services"
        },
        {
            "category":"Professional",
            "subcategory":"Management & Consulting",
            "type":"Services"
        },
        {
            "category":"Banks & Credit Unions",
            "subcategory":"Financial Services",
            "type":"Services"
        }
    ],
    "sg:phone":"+1 408 946 7700",
    "sg:postcode":"95035",
    "sg:province":"CA",
    "sg:tags":[
        "consultant",
        "financing",
        "planning",
        "return",
        "preparation-business"
    ],
    "wof:name":"Mirasol C Neufeld's Tax & Accounting Services",
    "wof:placetype":"venue"
},
  "geometry": {"coordinates":[-121.916421,37.446201],"type":"Point"}
}