{
  "type": "Feature",
  "properties": {
    "addr:full":"3111 Edison Hwy Bakersfield CA 93307",
    "addr:housenumber":"3111",
    "addr:postcode":"93307",
    "addr:street":"Edison Hwy",
    "iso:country":"US",
    "sg:address":"3111 Edison Hwy",
    "sg:city":"Bakersfield",
    "sg:classifiers":[
        {
            "category":"Autos & Motor Vehicles",
            "subcategory":"Auto Supplies",
            "type":"Retail Goods"
        },
        {
            "category":"Retail",
            "subcategory":"Auto Repair",
            "type":"Services"
        }
    ],
    "sg:phone":"+1 661 323 6557",
    "sg:postcode":"93307",
    "sg:province":"CA",
    "sg:tags":[
        "body",
        "lettering",
        "automobile",
        "dent",
        "truck",
        "removal",
        "painting",
        "repairing"
    ],
    "wof:name":"Trends Auto Body",
    "wof:placetype":"venue"
},
  "geometry": {"coordinates":[-118.948761,35.36655],"type":"Point"}
}