{
  "type": "Feature",
  "properties": {
    "iso:country":"US",
    "sg:address":"14 Denise Ct",
    "sg:city":"Novato",
    "sg:classifiers":[
        {
            "category":"Manufacturing",
            "subcategory":"Metals",
            "type":"Manufacturing & Wholesale Goods"
        },
        {
            "category":"Manufacturing",
            "subcategory":"Musical Instruments",
            "type":"Manufacturing & Wholesale Goods"
        }
    ],
    "sg:phone":"+1 415 897 0614",
    "sg:postcode":"94945",
    "sg:province":"CA",
    "sg:tags":[
        "steel",
        "mfg"
    ],
    "wof:name":"Sticks & Stands For Steel Pans",
    "wof:placetype":"venue"
},
  "geometry": {"coordinates":[-122.559842,38.107873],"type":"Point"}
}