{
  "type": "Feature",
  "properties": {
    "iso:country":"US",
    "sg:address":"1088 Country Club Dr",
    "sg:city":"Moraga",
    "sg:classifiers":[
        {
            "category":"Shopping",
            "subcategory":"Gifts & Souvenirs",
            "type":"Retail Goods"
        }
    ],
    "sg:phone":"+1 925 376 3552",
    "sg:postcode":"94556",
    "sg:province":"CA",
    "wof:name":"Gifts For You",
    "wof:placetype":"venue"
},
  "geometry": {"coordinates":[-122.126188,37.832338],"type":"Point"}
}