{
  "type": "Feature",
  "properties": {
    "iso:country":"US",
    "sg:address":"2719 San Pablo Ave",
    "sg:city":"Berkeley",
    "sg:classifiers":[
        {
            "category":"Travel",
            "subcategory":"Travel Agent",
            "type":"Entertainment"
        }
    ],
    "sg:phone":"+1 510 647 3455",
    "sg:postcode":"94702",
    "sg:province":"CA",
    "sg:tags":[
        "agency",
        "services-commercial"
    ],
    "wof:name":"J. O Travel & Cruises",
    "wof:placetype":"venue"
},
  "geometry": {"coordinates":[-122.288223,37.85685],"type":"Point"}
}