{
  "type": "Feature",
  "properties": {
    "addr:full":"20 Valley Vista Ct Fremont CA 94539",
    "addr:housenumber":"20",
    "addr:postcode":"94539",
    "addr:street":"Valley Vista Ct",
    "iso:country":"US",
    "sg:address":"20 Valley Vista Ct",
    "sg:city":"Fremont",
    "sg:classifiers":[
        {
            "category":"Wholesale",
            "subcategory":"Electrical",
            "type":"Manufacturing & Wholesale Goods"
        }
    ],
    "sg:phone":"+1 510 656 1224",
    "sg:postcode":"94539",
    "sg:province":"CA",
    "sg:tags":[
        "system",
        "power"
    ],
    "wof:name":"America Huaheng Systems Ctrl",
    "wof:placetype":"venue"
},
  "geometry": {"coordinates":[-121.91766800000001,37.524571],"type":"Point"}
}