{
  "type": "Feature",
  "properties": {
    "addr:full":"1625 W Redlands Blvd Redlands CA 92373",
    "addr:housenumber":"1625",
    "addr:postcode":"92373",
    "addr:street":"W Redlands Blvd",
    "iso:country":"US",
    "sg:address":"1625 W Redlands Blvd",
    "sg:city":"Redlands",
    "sg:classifiers":[
        {
            "category":"Autos & Motor Vehicles",
            "subcategory":"Auto Supplies",
            "type":"Retail Goods"
        }
    ],
    "sg:phone":"+1 909 335 1342",
    "sg:postcode":"92373",
    "sg:province":"CA",
    "sg:tags":[
        "tire"
    ],
    "sg:website":"www.sears.com/automotive",
    "wof:name":"Sears Auto Center",
    "wof:placetype":"venue"
},
  "geometry": {"coordinates":[-117.21002799999999,34.273493],"type":"Point"}
}