{
  "type": "Feature",
  "properties": {
    "addr:full":"948 Ramona Ave Clovis CA 93612",
    "addr:housenumber":"948",
    "addr:postcode":"93612",
    "addr:street":"Ramona Ave",
    "iso:country":"US",
    "sg:address":"948 Ramona Ave",
    "sg:city":"Clovis",
    "sg:classifiers":[
        {
            "category":"Travel",
            "subcategory":"Travel Agent",
            "type":"Entertainment"
        }
    ],
    "sg:phone":"+1 559 304 5760",
    "sg:postcode":"93612",
    "sg:province":"CA",
    "sg:tags":[
        "tours",
        "promoter"
    ],
    "wof:name":"India Tours",
    "wof:placetype":"venue"
},
  "geometry": {"coordinates":[-119.697464,36.785607],"type":"Point"}
}