{
  "type": "Feature",
  "properties": {
    "iso:country":"US",
    "sg:address":"143 N Harvard Ave",
    "sg:city":"Claremont",
    "sg:classifiers":[
        {
            "category":"Shopping",
            "subcategory":"Stationery & Office Supplies",
            "type":"Retail Goods"
        }
    ],
    "sg:phone":"+1 909 626 3479",
    "sg:postcode":"91711",
    "sg:province":"CA",
    "sg:tags":[
        "album",
        "scrapbook"
    ],
    "wof:name":"From The Heart",
    "wof:placetype":"venue"
},
  "geometry": {"coordinates":[-117.716478,34.095235],"type":"Point"}
}