{
  "type": "Feature",
  "properties": {
    "addr:full":"6041 Bolsa Ave Ste 10 Huntington Beach CA 92647",
    "addr:housenumber":"6041",
    "addr:postcode":"92647",
    "addr:street":"Bolsa Ave Ste 10",
    "iso:country":"US",
    "sg:address":"6041 Bolsa Ave Ste 10",
    "sg:city":"Huntington Beach",
    "sg:classifiers":[
        {
            "category":"Health Services",
            "subcategory":"Clinic",
            "type":"Services"
        }
    ],
    "sg:phone":"+1 714 799 5476",
    "sg:postcode":"92647",
    "sg:province":"CA",
    "sg:tags":[
        "spa",
        "medical"
    ],
    "sg:website":"www.Lipolaserandspa.com",
    "wof:name":"LipoLaser and Spa",
    "wof:placetype":"venue"
},
  "geometry": {"coordinates":[-118.023245,33.744845],"type":"Point"}
}