{
  "type": "Feature",
  "properties": {
    "iso:country":"US",
    "sg:address":"540 Ralston Ave",
    "sg:city":"Belmont",
    "sg:classifiers":[
        {
            "category":"Personal",
            "type":"Services"
        }
    ],
    "sg:phone":"+1 650 593 2299",
    "sg:postcode":"94002",
    "sg:province":"CA",
    "sg:tags":[
        "therapist",
        "massage"
    ],
    "wof:name":"Belmont Massage Therapy Group",
    "wof:placetype":"venue"
},
  "geometry": {"coordinates":[-122.273323,37.522712],"type":"Point"}
}