{
  "type": "Feature",
  "properties": {
    "addr:full":"926 Van Ness Ct Costa Mesa CA 92626",
    "addr:housenumber":"926",
    "addr:postcode":"92626",
    "addr:street":"Van Ness Ct",
    "iso:country":"US",
    "sg:address":"926 Van Ness Ct",
    "sg:city":"Costa Mesa",
    "sg:classifiers":[
        {
            "category":"Travel",
            "subcategory":"Travel Agent",
            "type":"Entertainment"
        }
    ],
    "sg:phone":"+1 714 742 2455",
    "sg:postcode":"92626",
    "sg:province":"CA",
    "sg:tags":[
        "agency"
    ],
    "wof:name":"Shari D S Traveling Notary Svc",
    "wof:placetype":"venue"
},
  "geometry": {"coordinates":[-117.89851,33.680775],"type":"Point"}
}