{
  "type": "Feature",
  "properties": {
    "addr:full":"1042 Woodbine Way San Jose CA 95117",
    "addr:housenumber":"1042",
    "addr:postcode":"95117",
    "addr:street":"Woodbine Way",
    "iso:country":"US",
    "sg:address":"1042 Woodbine Way",
    "sg:city":"San Jose",
    "sg:classifiers":[
        {
            "category":"Professional",
            "subcategory":"Computer Services",
            "type":"Services"
        }
    ],
    "sg:phone":"+1 408 410 4157",
    "sg:postcode":"95117",
    "sg:province":"CA",
    "sg:tags":[
        "repair"
    ],
    "wof:name":"New Millennium Computing",
    "wof:placetype":"venue"
},
  "geometry": {"coordinates":[-121.959856,37.306596],"type":"Point"}
}