{
  "type": "Feature",
  "properties": {
    "iso:country":"US",
    "sg:address":"6331 Woodley Ave",
    "sg:city":"Van Nuys",
    "sg:classifiers":[
        {
            "category":"Sports & Exercise",
            "subcategory":"Golf",
            "type":"Entertainment"
        }
    ],
    "sg:phone":"+1 818 780 6886",
    "sg:postcode":"91406",
    "sg:province":"CA",
    "sg:tags":[
        "course"
    ],
    "wof:name":"Woodley Lakes Golf Course",
    "wof:placetype":"venue"
},
  "geometry": {"coordinates":[-118.48372000000001,34.186507],"type":"Point"}
}