{
  "type": "Feature",
  "properties": {
    "addr:full":"4811 Keane Dr Carmichael CA 95608",
    "addr:housenumber":"4811",
    "addr:postcode":"95608",
    "addr:street":"Keane Dr",
    "iso:country":"US",
    "sg:address":"4811 Keane Dr",
    "sg:city":"Carmichael",
    "sg:classifiers":[
        {
            "category":"Shopping",
            "subcategory":"Catalog Store",
            "type":"Retail Goods"
        }
    ],
    "sg:phone":"+1 916 489 2990",
    "sg:postcode":"95608",
    "sg:province":"CA",
    "sg:tags":[
        "mail",
        "order",
        "online"
    ],
    "wof:name":"Curio House",
    "wof:placetype":"venue"
},
  "geometry": {"coordinates":[-121.34833999999999,38.585477],"type":"Point"}
}