{
  "type": "Feature",
  "properties": {
    "addr:full":"9447 Winter Gardens Blvd Lakeside CA 92040",
    "addr:housenumber":"9447",
    "addr:postcode":"92040",
    "addr:street":"Winter Gardens Blvd",
    "iso:country":"US",
    "sg:address":"9447 Winter Gardens Blvd",
    "sg:city":"Lakeside",
    "sg:classifiers":[
        {
            "category":"Health Services",
            "subcategory":"Doctor",
            "type":"Services"
        }
    ],
    "sg:phone":"+1 619 443 3948",
    "sg:postcode":"92040",
    "sg:province":"CA",
    "sg:tags":[
        "dentist"
    ],
    "wof:name":"John E Kramer DDS",
    "wof:placetype":"venue"
},
  "geometry": {"coordinates":[-116.93100200000001,32.848901],"type":"Point"}
}