{
  "type": "Feature",
  "properties": {
    "iso:country":"US",
    "sg:address":"1978 E Main St",
    "sg:city":"Ventura",
    "sg:phone":"+1 805 641 1892",
    "sg:postcode":"93001",
    "sg:province":"CA",
    "sg:website":"http://massagebypattib.com",
    "wof:name":"Massage by Patti",
    "wof:placetype":"venue"
},
  "geometry": {"coordinates":[-119.270529,34.278151],"type":"Point"}
}