{
  "type": "Feature",
  "properties": {
    "addr:full":"4614 Lincoln Ave Cypress CA 90630",
    "addr:housenumber":"4614",
    "addr:postcode":"90630",
    "addr:street":"Lincoln Ave",
    "iso:country":"US",
    "sg:address":"4614 Lincoln Ave",
    "sg:city":"Cypress",
    "sg:classifiers":[
        {
            "category":"Professional",
            "subcategory":"Accounting & Tax Preparation",
            "type":"Services"
        }
    ],
    "sg:phone":"+1 714 809 5808",
    "sg:postcode":"90630",
    "sg:province":"CA",
    "sg:tags":[
        "billing"
    ],
    "wof:name":"Independent Billing Solutions",
    "wof:placetype":"venue"
},
  "geometry": {"coordinates":[-118.04980999999999,33.831664],"type":"Point"}
}