{
  "type": "Feature",
  "properties": {
    "addr:full":"1944 Westmoreland Dr Brea CA 92821",
    "addr:housenumber":"1944",
    "addr:postcode":"92821",
    "addr:street":"Westmoreland Dr",
    "iso:country":"US",
    "sg:address":"1944 Westmoreland Dr",
    "sg:city":"Brea",
    "sg:classifiers":[
        {
            "category":"Professional",
            "subcategory":"Advertising",
            "type":"Services"
        }
    ],
    "sg:phone":"+1 714 529 6131",
    "sg:postcode":"92821",
    "sg:province":"CA",
    "sg:tags":[
        "agency",
        "public",
        "relations"
    ],
    "wof:name":"Creative Advertising",
    "wof:placetype":"venue"
},
  "geometry": {"coordinates":[-117.87608899999999,33.913013],"type":"Point"}
}