{
  "type": "Feature",
  "properties": {
    "iso:country":"US",
    "sg:address":"333 Culver Boulevard",
    "sg:city":"Los Angeles",
    "sg:classifiers":[
        {
            "category":"Building & Trades",
            "subcategory":"Construction",
            "type":"Services"
        }
    ],
    "sg:phone":"+1 310 974 8075",
    "sg:postcode":"90293",
    "sg:province":"CA",
    "sg:tags":[
        "contractor"
    ],
    "sg:website":"www.express-garage-doors.com",
    "wof:name":"Express Garage Doors In playa del rey",
    "wof:placetype":"venue"
},
  "geometry": {"coordinates":[-118.446955,33.960417],"type":"Point"}
}