{
  "type": "Feature",
  "properties": {
    "iso:country":"US",
    "sg:address":"2262 N Fresno St",
    "sg:city":"Fresno",
    "sg:classifiers":[
        {
            "category":"Professional",
            "subcategory":"Accounting & Tax Preparation",
            "type":"Services"
        }
    ],
    "sg:phone":"+1 559 268 9909",
    "sg:postcode":"93703",
    "sg:province":"CA",
    "sg:tags":[
        "return",
        "filing"
    ],
    "wof:name":"P & N Income Tax Svc",
    "wof:placetype":"venue"
},
  "geometry": {"coordinates":[-119.781439,36.77208],"type":"Point"}
}