{
  "type": "Feature",
  "properties": {
    "addr:full":"870 Market Street San Francisco CA 94102",
    "addr:housenumber":"870",
    "addr:postcode":"94102",
    "addr:street":"Market Street",
    "iso:country":"US",
    "sg:address":"870 Market Street",
    "sg:city":"San Francisco",
    "sg:classifiers":[
        {
            "category":"Professional",
            "subcategory":"Lawyer & Legal Services",
            "type":"Services"
        }
    ],
    "sg:phone":"+1 415 989 1476",
    "sg:postcode":"94102",
    "sg:province":"CA",
    "wof:name":"Agpaoa Anthony D Attorney At Law",
    "wof:placetype":"venue"
},
  "geometry": {"coordinates":[-122.406998,37.784698],"type":"Point"}
}