{
  "type": "Feature",
  "properties": {
    "iso:country":"US",
    "sg:address":"3836 State Rte 4",
    "sg:city":"Angels Camp",
    "sg:classifiers":[
        {
            "category":"Professional",
            "type":"Services"
        }
    ],
    "sg:phone":"+1 209 736 6394",
    "sg:postcode":"95222",
    "sg:province":"CA",
    "sg:tags":[
        "establishment"
    ],
    "wof:name":"Chalcedon",
    "wof:placetype":"venue"
},
  "geometry": {"coordinates":[-120.646512,38.046693],"type":"Point"}
}