{
  "type": "Feature",
  "properties": {
    "iso:country":"US",
    "sg:address":"1230 Montana Ave",
    "sg:city":"Santa Monica",
    "sg:classifiers":[
        {
            "category":"Shopping",
            "subcategory":"Clothing, Apparel, & Fashions",
            "type":"Retail Goods"
        }
    ],
    "sg:phone":"+1 310 393 0603",
    "sg:postcode":"90403",
    "sg:province":"CA",
    "sg:tags":[
        "handbag"
    ],
    "wof:name":"Alexander Zar New York",
    "wof:placetype":"venue"
},
  "geometry": {"coordinates":[-118.49679500000001,34.030759],"type":"Point"}
}