{
  "type": "Feature",
  "properties": {
    "iso:country":"US",
    "sg:address":"15710 Vanowen St",
    "sg:city":"Van Nuys",
    "sg:classifiers":[
        {
            "category":"Professional",
            "subcategory":"Management & Consulting",
            "type":"Services"
        }
    ],
    "sg:phone":"+1 818 780 6679",
    "sg:postcode":"91406",
    "sg:province":"CA",
    "sg:tags":[
        "retail",
        "direct",
        "sales"
    ],
    "wof:name":"Five Star Water Store",
    "wof:placetype":"venue"
},
  "geometry": {"coordinates":[-118.477019,34.193834],"type":"Point"}
}