{
  "type": "Feature",
  "properties": {
    "iso:country":"US",
    "sg:address":"3202 E Gage Ave",
    "sg:city":"Huntington Park",
    "sg:classifiers":[
        {
            "category":"Restaurant",
            "type":"Food & Drink"
        }
    ],
    "sg:phone":"+1 323 581 2383",
    "sg:postcode":"90255",
    "sg:province":"CA",
    "wof:name":"Yaya's Burgers No 2",
    "wof:placetype":"venue"
},
  "geometry": {"coordinates":[-118.209999,33.9804],"type":"Point"}
}