{
  "type": "Feature",
  "properties": {
    "iso:country":"US",
    "sg:address":"2521 Railroad Ave",
    "sg:city":"Ceres",
    "sg:classifiers":[
        {
            "category":"Retail",
            "subcategory":"Auto Repair",
            "type":"Services"
        }
    ],
    "sg:phone":"+1 209 534 9504",
    "sg:postcode":"95307",
    "sg:province":"CA",
    "sg:tags":[
        "body",
        "shop",
        "painting",
        "repairing",
        "automobile"
    ],
    "wof:name":"Concept Autobody",
    "wof:placetype":"venue"
},
  "geometry": {"coordinates":[-120.962535,37.594749],"type":"Point"}
}