{
  "type": "Feature",
  "properties": {
    "iso:country":"US",
    "sg:address":"541 Frederick St",
    "sg:city":"Santa Cruz",
    "sg:classifiers":[
        {
            "category":"Health Services",
            "subcategory":"Doctor",
            "type":"Services"
        }
    ],
    "sg:phone":"+1 831 457 2361",
    "sg:postcode":"95062",
    "sg:province":"CA",
    "sg:tags":[
        "physician",
        "surgeon"
    ],
    "wof:name":"John P Owens Pediatric Crdlgst",
    "wof:placetype":"venue"
},
  "geometry": {"coordinates":[-122.003996,36.977982],"type":"Point"}
}