{
  "type": "Feature",
  "properties": {
    "iso:country":"US",
    "sg:address":"40 Anderson Way",
    "sg:city":"Menlo Park",
    "sg:classifiers":[
        {
            "category":"Banks & Credit Unions",
            "subcategory":"Investment Brokerage",
            "type":"Services"
        }
    ],
    "sg:phone":"+1 650 233 9215",
    "sg:postcode":"94025",
    "sg:province":"CA",
    "sg:tags":[
        "advisory",
        "financial"
    ],
    "wof:name":"Quality Asset Management",
    "wof:placetype":"venue"
},
  "geometry": {"coordinates":[-122.193032,37.422151],"type":"Point"}
}