{
  "type": "Feature",
  "properties": {
    "addr:full":"41144 Roberts Ave Fremont CA 94538",
    "addr:housenumber":"41144",
    "addr:postcode":"94538",
    "addr:street":"Roberts Ave",
    "iso:country":"US",
    "sg:address":"41144 Roberts Ave",
    "sg:city":"Fremont",
    "sg:classifiers":[
        {
            "category":"Home & Garden",
            "subcategory":"Garden Supply",
            "type":"Retail Goods"
        }
    ],
    "sg:phone":"+1 510 656 5375",
    "sg:postcode":"94538",
    "sg:province":"CA",
    "sg:tags":[
        "lawn",
        "mower"
    ],
    "wof:name":"Schaa's Lawnmower Sales & Svc",
    "wof:placetype":"venue"
},
  "geometry": {"coordinates":[-121.956351,37.532004],"type":"Point"}
}