{
  "type": "Feature",
  "properties": {
    "addr:full":"430 State Hwy 49 Sutter Creek CA 95685",
    "addr:housenumber":"430",
    "addr:postcode":"95685",
    "addr:street":"State Hwy 49",
    "iso:country":"US",
    "sg:address":"430 State Hwy 49",
    "sg:city":"Sutter Creek",
    "sg:classifiers":[
        {
            "category":"Social Services",
            "type":"Services"
        }
    ],
    "sg:phone":"+1 209 267 0656",
    "sg:postcode":"95685",
    "sg:province":"CA",
    "sg:tags":[
        "counselor",
        "marriage",
        "family"
    ],
    "wof:name":"Samaritan Counseling Ctr",
    "wof:placetype":"venue"
},
  "geometry": {"coordinates":[-120.808995,38.399776],"type":"Point"}
}