{
  "type": "Feature",
  "properties": {
    "addr:full":"328 Nut Tree Rd Vacaville CA 95687",
    "addr:housenumber":"328",
    "addr:postcode":"95687",
    "addr:street":"Nut Tree Rd",
    "iso:country":"US",
    "sg:address":"328 Nut Tree Rd",
    "sg:city":"Vacaville",
    "sg:classifiers":[
        {
            "category":"Shopping",
            "subcategory":"Clothing, Apparel, & Fashions",
            "type":"Retail Goods"
        }
    ],
    "sg:phone":"+1 707 446 8292",
    "sg:postcode":"95687",
    "sg:province":"CA",
    "sg:tags":[
        "infant",
        "wear"
    ],
    "wof:name":"Little Me Retail Stores Of Ca",
    "wof:placetype":"venue"
},
  "geometry": {"coordinates":[-121.953219,38.365222],"type":"Point"}
}