{
  "type": "Feature",
  "properties": {
    "addr:full":"1140 W Branch St Arroyo Grande CA 93420",
    "addr:housenumber":"1140",
    "addr:postcode":"93420",
    "addr:street":"W Branch St",
    "iso:country":"US",
    "sg:address":"1140 W Branch St",
    "sg:city":"Arroyo Grande",
    "sg:classifiers":[
        {
            "category":"Retail",
            "subcategory":"Laundry & Dry Cleaning",
            "type":"Services"
        }
    ],
    "sg:phone":"+1 805 489 1188",
    "sg:postcode":"93420",
    "sg:province":"CA",
    "sg:tags":[
        "cleaners"
    ],
    "wof:name":"Kleanerette Dry Cleaners",
    "wof:placetype":"venue"
},
  "geometry": {"coordinates":[-120.599602,35.128036],"type":"Point"}
}