{
  "type": "Feature",
  "properties": {
    "iso:country":"US",
    "sg:address":"334 Ingalls St Ste C",
    "sg:city":"Santa Cruz",
    "sg:classifiers":[
        {
            "category":"Winery",
            "type":"Food & Drink"
        }
    ],
    "sg:phone":"+1 408 813 8384",
    "sg:postcode":"95060",
    "sg:province":"CA",
    "sg:website":"www.vino-tabi-wine.com",
    "wof:name":"Vino Tabi Winery",
    "wof:placetype":"venue"
},
  "geometry": {"coordinates":[-122.04725500000001,36.959143],"type":"Point"}
}