{
  "type": "Feature",
  "properties": {
    "addr:full":"8770 State Rte 25 Hollister CA 95023",
    "addr:housenumber":"8770",
    "addr:postcode":"hollister ca 95023",
    "addr:street":"State Rte 25",
    "iso:country":"US",
    "sg:address":"8770 State Rte 25",
    "sg:city":"Hollister",
    "sg:classifiers":[
        {
            "category":"Wholesale",
            "subcategory":"Chemicals & Plastics",
            "type":"Manufacturing & Wholesale Goods"
        }
    ],
    "sg:phone":"+1 831 637 1992",
    "sg:postcode":"95023",
    "sg:province":"CA",
    "wof:name":"Soil Chemical Corp",
    "wof:placetype":"venue"
},
  "geometry": {"coordinates":[-121.507559,36.946084],"type":"Point"}
}