{
  "type": "Feature",
  "properties": {
    "iso:country":"US",
    "sg:address":"2445 Fountain Oaks Dr",
    "sg:city":"Morgan Hill",
    "sg:classifiers":[
        {
            "category":"Building & Trades",
            "subcategory":"Construction",
            "type":"Services"
        }
    ],
    "sg:phone":"+1 408 779 1681",
    "sg:postcode":"95037",
    "sg:province":"CA",
    "sg:tags":[
        "painter"
    ],
    "wof:name":"Paradise Painting",
    "wof:placetype":"venue"
},
  "geometry": {"coordinates":[-121.607885,37.136756],"type":"Point"}
}