{
  "type": "Feature",
  "properties": {
    "addr:full":"541 Palisades Dr Pacific Palisades CA 90272",
    "addr:housenumber":"541",
    "addr:postcode":"90272",
    "addr:street":"Palisades Dr",
    "iso:country":"US",
    "sg:address":"541 Palisades Dr",
    "sg:city":"Pacific Palisades",
    "sg:classifiers":[
        {
            "category":"Professional",
            "type":"Services"
        }
    ],
    "sg:phone":"+1 310 459 7672",
    "sg:postcode":"90272",
    "sg:province":"CA",
    "wof:name":"Timothy Thelen",
    "wof:placetype":"venue"
},
  "geometry": {"coordinates":[-118.55283300000001,34.051338],"type":"Point"}
}