{
  "type": "Feature",
  "properties": {
    "iso:country":"US",
    "sg:address":"5260 E la Palma Ave",
    "sg:city":"Anaheim",
    "sg:classifiers":[
        {
            "category":"Professional",
            "type":"Services"
        },
        {
            "category":"Personal",
            "type":"Services"
        },
        {
            "category":"Retail",
            "subcategory":"Event Space",
            "type":"Services"
        },
        {
            "category":"Freight",
            "type":"Transportation"
        }
    ],
    "sg:phone":"+1 800 251 8879",
    "sg:postcode":"92807",
    "sg:province":"CA",
    "sg:tags":[
        "box",
        "full",
        "material",
        "storage",
        "trucking",
        "moving",
        "services-labor",
        "mover",
        "local"
    ],
    "sg:website":"http://www.bekins.com",
    "wof:name":"Bekins Van Lines",
    "wof:placetype":"venue"
},
  "geometry": {"coordinates":[-117.802347,33.859507],"type":"Point"}
}