{
  "type": "Feature",
  "properties": {
    "addr:full":"7619 Greenleaf Ave Whittier CA 90602",
    "addr:housenumber":"7619",
    "addr:postcode":"90602",
    "addr:street":"Greenleaf Ave",
    "iso:country":"US",
    "sg:address":"7619 Greenleaf Ave",
    "sg:city":"Whittier",
    "sg:classifiers":[
        {
            "category":"Shopping",
            "subcategory":"Used Merchandise",
            "type":"Retail Goods"
        }
    ],
    "sg:phone":"+1 562 907 0783",
    "sg:postcode":"90602",
    "sg:province":"CA",
    "wof:name":"Up Scale RE Sale",
    "wof:placetype":"venue"
},
  "geometry": {"coordinates":[-118.037443,33.972169],"type":"Point"}
}