{
  "type": "Feature",
  "properties": {
    "iso:country":"US",
    "sg:address":"1621 Creekside Dr",
    "sg:city":"Folsom",
    "sg:classifiers":[
        {
            "category":"Health Services",
            "subcategory":"Doctor",
            "type":"Services"
        }
    ],
    "sg:phone":"+1 916 984 7428",
    "sg:postcode":"95630",
    "sg:province":"CA",
    "sg:tags":[
        "physician",
        "surgeon"
    ],
    "wof:name":"Creekside Ob-Gyn Of Folsom",
    "wof:placetype":"venue"
},
  "geometry": {"coordinates":[-121.14286300000001,38.67237],"type":"Point"}
}