{
  "type": "Feature",
  "properties": {
    "iso:country":"US",
    "sg:address":"621 Ashlan Way",
    "sg:city":"Madera",
    "sg:classifiers":[
        {
            "category":"Building & Trades",
            "subcategory":"Construction",
            "type":"Services"
        }
    ],
    "sg:phone":"+1 559 661 5734",
    "sg:postcode":"93638",
    "sg:province":"CA",
    "sg:tags":[
        "handyman"
    ],
    "wof:name":"Lorzanos Handyman Svc",
    "wof:placetype":"venue"
},
  "geometry": {"coordinates":[-120.059821,36.979423],"type":"Point"}
}