{
  "type": "Feature",
  "properties": {
    "addr:full":"1943 Crows Landing Rd Modesto CA 95358",
    "addr:housenumber":"1943",
    "addr:postcode":"ca 95358",
    "addr:street":"Crows Landing Rd",
    "iso:country":"US",
    "sg:address":"1943 Crows Landing Rd",
    "sg:city":"Modesto",
    "sg:classifiers":[
        {
            "category":"Wholesale",
            "subcategory":"Machinery & Supplies",
            "type":"Manufacturing & Wholesale Goods"
        }
    ],
    "sg:phone":"+1 209 538 1555",
    "sg:postcode":"95358",
    "sg:province":"CA",
    "sg:tags":[
        "chains"
    ],
    "wof:name":"Sisco Wire Rope & Rigging",
    "wof:placetype":"venue"
},
  "geometry": {"coordinates":[-120.99359200000001,37.60132],"type":"Point"}
}