{
  "type": "Feature",
  "properties": {
    "iso:country":"US",
    "sg:address":"1681 Indian Hill Blvd",
    "sg:city":"Pomona",
    "sg:classifiers":[
        {
            "category":"Food & Beverages",
            "subcategory":"Bakery",
            "type":"Retail Goods"
        }
    ],
    "sg:phone":"+1 909 621 2354",
    "sg:postcode":"91767",
    "sg:province":"CA",
    "sg:tags":[
        "product",
        "mfg"
    ],
    "wof:name":"Sunshine Doughnuts",
    "wof:placetype":"venue"
},
  "geometry": {"coordinates":[-117.71932099999999,34.074575],"type":"Point"}
}