{
  "type": "Feature",
  "properties": {
    "iso:country":"US",
    "sg:address":"8800 Auburn Valley Rd",
    "sg:city":"Auburn",
    "sg:classifiers":[
        {
            "category":"Building & Trades",
            "subcategory":"Construction",
            "type":"Services"
        }
    ],
    "sg:phone":"+1 530 269 2600",
    "sg:postcode":"95602",
    "sg:province":"CA",
    "sg:tags":[
        "system",
        "specialty",
        "heating",
        "contractor",
        "air conditioning"
    ],
    "wof:name":"Kaiser Heating & Air Conditioning Co.",
    "wof:placetype":"venue"
},
  "geometry": {"coordinates":[-121.14904,39.003799],"type":"Point"}
}