{
  "type": "Feature",
  "properties": {
    "addr:full":"7964 Beach Blvd Buena Park CA 90620",
    "addr:housenumber":"7964",
    "addr:postcode":"90620",
    "addr:street":"Beach Blvd",
    "iso:country":"US",
    "sg:address":"7964 Beach Blvd",
    "sg:city":"Buena Park",
    "sg:classifiers":[
        {
            "category":"Banks & Credit Unions",
            "subcategory":"Bank",
            "type":"Services"
        },
        {
            "category":"Banks & Credit Unions",
            "subcategory":"Financial Services",
            "type":"Services"
        }
    ],
    "sg:phone":"+1 714 670 6743",
    "sg:postcode":"90620",
    "sg:province":"CA",
    "sg:tags":[
        "broker",
        "mortgage"
    ],
    "sg:website":"www.wamu.com",
    "wof:name":"Chase",
    "wof:placetype":"venue"
},
  "geometry": {"coordinates":[-117.998001,33.847],"type":"Point"}
}