{
  "type": "Feature",
  "properties": {
    "addr:full":"12317 Ventura Blvd Studio City CA 91604",
    "addr:housenumber":"12317",
    "addr:postcode":"91604",
    "addr:street":"Ventura Blvd",
    "iso:country":"US",
    "sg:address":"12317 Ventura Blvd",
    "sg:city":"Studio City",
    "sg:classifiers":[
        {
            "category":"Manufacturing",
            "subcategory":"Retail Goods",
            "type":"Manufacturing & Wholesale Goods"
        },
        {
            "category":"Professional",
            "type":"Services"
        }
    ],
    "sg:phone":"+1 818 766 7813",
    "sg:postcode":"91604",
    "sg:province":"CA",
    "sg:tags":[
        "buckle",
        "mfg"
    ],
    "wof:name":"Al Shelton Western Artist",
    "wof:placetype":"venue"
},
  "geometry": {"coordinates":[-118.402725,34.142983],"type":"Point"}
}