{
  "type": "Feature",
  "properties": {
    "addr:full":"15542 Elm Ave Patterson CA 95363",
    "addr:housenumber":"15542",
    "addr:postcode":"95363",
    "addr:street":"Elm Ave",
    "iso:country":"US",
    "sg:address":"15542 Elm Ave",
    "sg:city":"Patterson",
    "sg:phone":"+1 209 892 6083",
    "sg:postcode":"95363",
    "sg:province":"CA",
    "sg:tags":[
        "farm",
        "field",
        "crop"
    ],
    "wof:name":"Philip Carlson",
    "wof:placetype":"venue"
},
  "geometry": {"coordinates":[-121.095506,37.485254],"type":"Point"}
}