{
  "type": "Feature",
  "properties": {
    "addr:full":"2 Flagstone Ste 836 Irvine CA 92606",
    "addr:housenumber":"2",
    "addr:postcode":"92606",
    "addr:street":"Flagstone Ste 836",
    "iso:country":"US",
    "sg:address":"2 Flagstone Ste 836",
    "sg:city":"Irvine",
    "sg:classifiers":[
        {
            "category":"Building & Trades",
            "subcategory":"Plumbing",
            "type":"Services"
        },
        {
            "category":"Building & Trades",
            "subcategory":"Construction",
            "type":"Services"
        },
        {
            "category":"Building & Trades",
            "subcategory":"Electrical",
            "type":"Services"
        }
    ],
    "sg:phone":"+1 888 678 7261",
    "sg:postcode":"92606",
    "sg:province":"CA",
    "sg:tags":[
        "electrician",
        "contractor"
    ],
    "wof:name":"Sam Handyman",
    "wof:placetype":"venue"
},
  "geometry": {"coordinates":[-117.79574599999999,33.698156],"type":"Point"}
}