{
  "type": "Feature",
  "properties": {
    "iso:country":"US",
    "sg:address":"2966 Wilshire Boulevard",
    "sg:city":"Los Angeles",
    "sg:classifiers":[
        {
            "category":"Organizations",
            "subcategory":"Religious Organization",
            "type":"Services"
        }
    ],
    "sg:phone":"+1 213 736 6500",
    "sg:postcode":"90010",
    "sg:province":"CA",
    "wof:name":"The Reformed University of U S A",
    "wof:placetype":"venue"
},
  "geometry": {"coordinates":[-118.286161,34.061748],"type":"Point"}
}