{
  "type": "Feature",
  "properties": {
    "addr:full":"600 Bonita Ct Vallejo CA 94591",
    "addr:housenumber":"600",
    "addr:postcode":"94591",
    "addr:street":"Bonita Ct",
    "iso:country":"US",
    "sg:address":"600 Bonita Ct",
    "sg:city":"Vallejo",
    "sg:classifiers":[
        {
            "category":"Food & Beverages",
            "subcategory":"Groceries & Convenience Stores",
            "type":"Retail Goods"
        }
    ],
    "sg:phone":"+1 707 552 7164",
    "sg:postcode":"94591",
    "sg:province":"CA",
    "sg:tags":[
        "preserves",
        "jam",
        "jelly"
    ],
    "wof:name":"Rueber",
    "wof:placetype":"venue"
},
  "geometry": {"coordinates":[-122.22762299999999,38.09774],"type":"Point"}
}