{
  "type": "Feature",
  "properties": {
    "addr:full":"3559 W Ramsey St Banning CA 92220",
    "addr:housenumber":"3559",
    "addr:postcode":"92220",
    "addr:street":"W Ramsey St",
    "iso:country":"US",
    "sg:address":"3559 W Ramsey St",
    "sg:city":"Banning",
    "sg:classifiers":[
        {
            "category":"Shopping",
            "subcategory":"Gifts & Souvenirs",
            "type":"Retail Goods"
        }
    ],
    "sg:phone":"+1 951 849 5116",
    "sg:postcode":"92220",
    "sg:province":"CA",
    "sg:tags":[
        "shop"
    ],
    "sg:website":"http://www.tuzzymuzzy.com",
    "wof:name":"Tuzzy Muzzy",
    "wof:placetype":"venue"
},
  "geometry": {"coordinates":[-116.913939,33.926018],"type":"Point"}
}