{
  "type": "Feature",
  "properties": {
    "iso:country":"US",
    "sg:address":"12477 Angier Rd",
    "sg:city":"Lodi",
    "sg:classifiers":[
        {
            "category":"Wholesale",
            "subcategory":"Non-durable Goods",
            "type":"Manufacturing & Wholesale Goods"
        }
    ],
    "sg:phone":"+1 209 369 7533",
    "sg:postcode":"95240",
    "sg:province":"CA",
    "wof:name":"Camp Aviary",
    "wof:placetype":"venue"
},
  "geometry": {"coordinates":[-121.228967,38.092663],"type":"Point"}
}