{
  "type": "Feature",
  "properties": {
    "addr:full":"255 G St San Diego CA 92101",
    "addr:housenumber":"255",
    "addr:postcode":"92101",
    "addr:street":"G St",
    "iso:country":"US",
    "sg:address":"255 G St",
    "sg:city":"San Diego",
    "sg:classifiers":[
        {
            "category":"Wholesale",
            "subcategory":"Stationery",
            "type":"Manufacturing & Wholesale Goods"
        }
    ],
    "sg:phone":"+1 619 264 2157",
    "sg:postcode":"92101",
    "sg:province":"CA",
    "sg:tags":[
        "supply"
    ],
    "wof:name":"BP",
    "wof:placetype":"venue"
},
  "geometry": {"coordinates":[-117.162417,32.712474],"type":"Point"}
}