{
  "type": "Feature",
  "properties": {
    "iso:country":"US",
    "sg:address":"21255 Califa St",
    "sg:city":"Woodland Hills",
    "sg:classifiers":[
        {
            "category":"Banks & Credit Unions",
            "subcategory":"Bank",
            "type":"Services"
        }
    ],
    "sg:phone":"+1 818 703 0389",
    "sg:postcode":"91367",
    "sg:province":"CA",
    "wof:name":"Star Harbor Federal CU",
    "wof:placetype":"venue"
},
  "geometry": {"coordinates":[-118.594756,34.177194],"type":"Point"}
}