{
  "type": "Feature",
  "properties": {
    "addr:full":"375 S Rancho Santa Fe Rd San Marcos CA 92078",
    "addr:housenumber":"375",
    "addr:postcode":"92078",
    "addr:street":"S Rancho Santa Fe Rd",
    "iso:country":"US",
    "sg:address":"375 S Rancho Santa Fe Rd",
    "sg:city":"San Marcos",
    "sg:classifiers":[
        {
            "category":"Retail",
            "subcategory":"Auto Repair",
            "type":"Services"
        }
    ],
    "sg:phone":"+1 760 471 0770",
    "sg:postcode":"92078",
    "sg:province":"CA",
    "sg:tags":[
        "automobile",
        "smog"
    ],
    "wof:name":"Smog Central",
    "wof:placetype":"venue"
},
  "geometry": {"coordinates":[-117.20327,33.140264],"type":"Point"}
}