{
  "type": "Feature",
  "properties": {
    "iso:country":"US",
    "sg:address":"32 N Cluff Ave",
    "sg:city":"Lodi",
    "sg:classifiers":[
        {
            "category":"Manufacturing",
            "subcategory":"Metals",
            "type":"Manufacturing & Wholesale Goods"
        }
    ],
    "sg:phone":"+1 209 367 1940",
    "sg:postcode":"95240",
    "sg:province":"CA",
    "sg:tags":[
        "foundry",
        "iron"
    ],
    "wof:name":"South Bay Foundry",
    "wof:placetype":"venue"
},
  "geometry": {"coordinates":[-121.252434,38.135332],"type":"Point"}
}