{
  "type": "Feature",
  "properties": {
    "addr:full":"8534 Long Beach Boulevard South Gate CA 90280",
    "addr:housenumber":"8534",
    "addr:postcode":"90280",
    "addr:street":"Long Beach Boulevard;Gate",
    "iso:country":"US",
    "sg:address":"8534 Long Beach Boulevard",
    "sg:city":"South Gate",
    "sg:classifiers":[
        {
            "category":"Personal",
            "subcategory":"Nail Salon",
            "type":"Services"
        }
    ],
    "sg:phone":"+1 323 581 9709",
    "sg:postcode":"90280",
    "sg:province":"CA",
    "wof:name":"Vicky Nails",
    "wof:placetype":"venue"
},
  "geometry": {"coordinates":[-118.222764,33.959701],"type":"Point"}
}