{
  "type": "Feature",
  "properties": {
    "iso:country":"US",
    "sg:address":"200 Meadow Creek Ct",
    "sg:city":"Oakley",
    "sg:classifiers":[
        {
            "category":"Professional",
            "subcategory":"Business Services",
            "type":"Services"
        }
    ],
    "sg:phone":"+1 925 308 4059",
    "sg:postcode":"94561",
    "sg:province":"CA",
    "sg:tags":[
        "inspection"
    ],
    "wof:name":"Rob Bowlen Home Inspection Inc",
    "wof:placetype":"venue"
},
  "geometry": {"coordinates":[-121.69313,37.985081],"type":"Point"}
}