{
  "type": "Feature",
  "properties": {
    "iso:country":"US",
    "sg:address":"8045 Garfield Ave",
    "sg:city":"Bell Gardens",
    "sg:classifiers":[
        {
            "category":"Food & Beverages",
            "subcategory":"Meat & Fish",
            "type":"Retail Goods"
        }
    ],
    "sg:phone":"+1 562 928 0802",
    "sg:postcode":"90201",
    "sg:province":"CA",
    "wof:name":"Carniceria LA Yalalteca 2",
    "wof:placetype":"venue"
},
  "geometry": {"coordinates":[-118.15838599999999,33.958135],"type":"Point"}
}