{
  "type": "Feature",
  "properties": {
    "iso:country":"US",
    "sg:address":"13990 E 14th St",
    "sg:city":"San Leandro",
    "sg:classifiers":[
        {
            "category":"Retail",
            "subcategory":"Auto Repair",
            "type":"Services"
        }
    ],
    "sg:phone":"+1 510 351 8211",
    "sg:postcode":"94578",
    "sg:province":"CA",
    "sg:tags":[
        "body",
        "shop",
        "repairing",
        "automobile"
    ],
    "sg:website":"www.precisionautorepair.us/",
    "wof:name":"Precision Auto Care",
    "wof:placetype":"venue"
},
  "geometry": {"coordinates":[-122.139745,37.713515],"type":"Point"}
}