{
  "type": "Feature",
  "properties": {
    "iso:country":"US",
    "sg:address":"313 Kendal St",
    "sg:city":"Vacaville",
    "sg:classifiers":[
        {
            "category":"Health Services",
            "subcategory":"Health Practitioner",
            "type":"Services"
        }
    ],
    "sg:phone":"+1 707 455 7290",
    "sg:postcode":"95688",
    "sg:province":"CA",
    "sg:tags":[
        "acupuncture"
    ],
    "wof:name":"Edie Higgins",
    "wof:placetype":"venue"
},
  "geometry": {"coordinates":[-121.98882500000001,38.357583],"type":"Point"}
}