{
  "type": "Feature",
  "properties": {
    "addr:full":"381 Quintana Rd Morro Bay CA 93442",
    "addr:housenumber":"381",
    "addr:postcode":"93442",
    "addr:street":"Quintana Rd",
    "iso:country":"US",
    "sg:address":"381 Quintana Rd",
    "sg:city":"Morro Bay",
    "sg:classifiers":[
        {
            "category":"Home & Garden",
            "subcategory":"Furniture",
            "type":"Retail Goods"
        }
    ],
    "sg:phone":"+1 805 772 9740",
    "sg:postcode":"93442",
    "sg:province":"CA",
    "sg:tags":[
        "mattress"
    ],
    "wof:name":"Morro Bay Furniture",
    "wof:placetype":"venue"
},
  "geometry": {"coordinates":[-120.84899900000001,35.371201],"type":"Point"}
}