{
  "type": "Feature",
  "properties": {
    "iso:country":"US",
    "sg:address":"1677 Holly Ave",
    "sg:city":"San Bruno",
    "sg:classifiers":[
        {
            "category":"Arena",
            "subcategory":"Sports Club",
            "type":"Entertainment"
        }
    ],
    "sg:phone":"+1 650 873 2976",
    "sg:postcode":"94066",
    "sg:province":"CA",
    "sg:tags":[
        "soccer"
    ],
    "wof:name":"American Youth Soccer Orgnztn",
    "wof:placetype":"venue"
},
  "geometry": {"coordinates":[-122.424655,37.623335],"type":"Point"}
}