{
  "type": "Feature",
  "properties": {
    "iso:country":"US",
    "sg:address":"4743 Brooks St",
    "sg:city":"Montclair",
    "sg:classifiers":[
        {
            "category":"Retail",
            "subcategory":"Repair Shop",
            "type":"Services"
        }
    ],
    "sg:phone":"+1 909 447 1233",
    "sg:postcode":"91763",
    "sg:province":"CA",
    "sg:tags":[
        "ironwork"
    ],
    "wof:name":"Flores Wrought Iron",
    "wof:placetype":"venue"
},
  "geometry": {"coordinates":[-117.702966,34.061584],"type":"Point"}
}