{
  "type": "Feature",
  "properties": {
    "addr:full":"8 California Ave Pleasanton CA 94566",
    "addr:housenumber":"8",
    "addr:postcode":"94566",
    "addr:street":"California Ave",
    "iso:country":"US",
    "sg:address":"8 California Ave",
    "sg:city":"Pleasanton",
    "sg:classifiers":[
        {
            "category":"Autos & Motor Vehicles",
            "subcategory":"Automobile Sales",
            "type":"Retail Goods"
        }
    ],
    "sg:phone":"+1 925 426 1969",
    "sg:postcode":"94566",
    "sg:province":"CA",
    "sg:tags":[
        "classic"
    ],
    "wof:name":"Car Scene Inc",
    "wof:placetype":"venue"
},
  "geometry": {"coordinates":[-121.860966,37.666403],"type":"Point"}
}