{
  "type": "Feature",
  "properties": {
    "addr:full":"467 N Wilma Ave Ripon CA 95366",
    "addr:housenumber":"467",
    "addr:postcode":"ca 95366",
    "addr:street":"N Wilma Ave",
    "iso:country":"US",
    "sg:address":"467 N Wilma Ave",
    "sg:city":"Ripon",
    "sg:classifiers":[
        {
            "category":"Insurance",
            "subcategory":"Insurance Agent",
            "type":"Services"
        }
    ],
    "sg:phone":"+1 209 599 0707",
    "sg:postcode":"95366",
    "sg:province":"CA",
    "wof:name":"Morris Insurance",
    "wof:placetype":"venue"
},
  "geometry": {"coordinates":[-121.135559,37.743667],"type":"Point"}
}