{
  "type": "Feature",
  "properties": {
    "addr:full":"18210 Yorba Linda Blvd Yorba Linda CA 92886",
    "addr:housenumber":"18210",
    "addr:postcode":"92886",
    "addr:street":"Yorba Linda Blvd",
    "iso:country":"US",
    "sg:address":"18210 Yorba Linda Blvd",
    "sg:city":"Yorba Linda",
    "sg:classifiers":[
        {
            "category":"Real Estate",
            "subcategory":"Real Estate Agent",
            "type":"Services"
        }
    ],
    "sg:phone":"+1 714 524 4100",
    "sg:postcode":"92886",
    "sg:province":"CA",
    "wof:name":"Silvercrest Realty",
    "wof:placetype":"venue"
},
  "geometry": {"coordinates":[-117.81546899999999,33.888534],"type":"Point"}
}