{
  "type": "Feature",
  "properties": {
    "addr:full":"1028 W Westmont Ct Visalia CA 93277",
    "addr:housenumber":"1028",
    "addr:postcode":"93277",
    "addr:street":"W Westmont Ct",
    "iso:country":"US",
    "sg:address":"1028 W Westmont Ct",
    "sg:city":"Visalia",
    "sg:classifiers":[
        {
            "category":"Professional",
            "subcategory":"Business Services",
            "type":"Services"
        }
    ],
    "sg:phone":"+1 559 735 0397",
    "sg:postcode":"93277",
    "sg:province":"CA",
    "sg:tags":[
        "consultant",
        "coach"
    ],
    "wof:name":"Acedo Safety Consulting Group",
    "wof:placetype":"venue"
},
  "geometry": {"coordinates":[-119.302547,36.292726],"type":"Point"}
}