{
  "type": "Feature",
  "properties": {
    "addr:full":"Windermere Exclusive Properties 1905 Calle Barcelona Suite 230 Carlsbad CA 92009",
    "addr:housenumber":"1905",
    "addr:postcode":"92009",
    "addr:street":"Calle Barcelona Suite 230",
    "iso:country":"US",
    "sg:address":"Windermere Exclusive Properties 1905 Calle Barcelona Suite 230",
    "sg:city":"Carlsbad",
    "sg:classifiers":[
        {
            "category":"Real Estate",
            "subcategory":"Real Estate Agent",
            "type":"Services"
        }
    ],
    "sg:phone":"+1 858 945 6165",
    "sg:postcode":"92009",
    "sg:province":"CA",
    "sg:website":"www.carolmohan.com",
    "wof:name":"Carol Mohan",
    "wof:placetype":"venue"
},
  "geometry": {"coordinates":[-117.26701300000001,33.070738],"type":"Point"}
}