{
  "type": "Feature",
  "properties": {
    "addr:full":"8660 Gilman Dr La Jolla CA 92037",
    "addr:housenumber":"8660",
    "addr:postcode":"92037",
    "addr:street":"Gilman Dr",
    "iso:country":"US",
    "sg:address":"8660 Gilman Dr",
    "sg:city":"La Jolla",
    "sg:classifiers":[
        {
            "category":"Place Of Worship",
            "subcategory":"Synagogue",
            "type":"Public Place"
        }
    ],
    "sg:phone":"+1 858 452 1734",
    "sg:postcode":"92037",
    "sg:province":"CA",
    "wof:name":"Congregation Beth El",
    "wof:placetype":"venue"
},
  "geometry": {"coordinates":[-117.23699999999999,32.865799],"type":"Point"}
}