{
  "type": "Feature",
  "properties": {
    "addr:full":"2875 Middlefield Rd Palo Alto CA 94306",
    "addr:housenumber":"2875",
    "addr:postcode":"94306",
    "addr:street":"Middlefield Rd",
    "iso:country":"US",
    "sg:address":"2875 Middlefield Rd",
    "sg:city":"Palo Alto",
    "sg:classifiers":[
        {
            "category":"Health Services",
            "subcategory":"Chiropractor",
            "type":"Services"
        }
    ],
    "sg:phone":"+1 650 325 9200",
    "sg:postcode":"94306",
    "sg:province":"CA",
    "wof:name":"Midtown Chiropractic",
    "wof:placetype":"venue"
},
  "geometry": {"coordinates":[-122.127416,37.432203],"type":"Point"}
}