{
  "type": "Feature",
  "properties": {
    "iso:country":"US",
    "sg:address":"5531 Hemlock St",
    "sg:city":"Sacramento",
    "sg:classifiers":[
        {
            "category":"Organizations",
            "subcategory":"Religious Organization",
            "type":"Services"
        }
    ],
    "sg:phone":"+1 916 331 6532",
    "sg:postcode":"95841",
    "sg:province":"CA",
    "sg:tags":[
        "church"
    ],
    "wof:name":"Spirit Of Grace",
    "wof:placetype":"venue"
},
  "geometry": {"coordinates":[-121.341318,38.666829],"type":"Point"}
}