{
  "type": "Feature",
  "properties": {
    "iso:country":"US",
    "sg:address":"325 Page St",
    "sg:city":"San Jose",
    "sg:classifiers":[
        {
            "category":"Home & Garden",
            "subcategory":"Carpets & Floor Coverings",
            "type":"Retail Goods"
        }
    ],
    "sg:phone":"+1 408 813 8089",
    "sg:postcode":"95126",
    "sg:province":"CA",
    "sg:tags":[
        "dealer",
        "rug"
    ],
    "wof:name":"Carpets Star",
    "wof:placetype":"venue"
},
  "geometry": {"coordinates":[-121.915565,37.323024],"type":"Point"}
}