{
  "type": "Feature",
  "properties": {
    "addr:full":"3356 E Florence Ave Huntington Park CA 90255",
    "addr:housenumber":"3356",
    "addr:postcode":"90255",
    "addr:street":"E Florence Ave;Park",
    "iso:country":"US",
    "sg:address":"3356 E Florence Ave",
    "sg:city":"Huntington Park",
    "sg:classifiers":[
        {
            "category":"Retail",
            "subcategory":"Car Wash",
            "type":"Services"
        }
    ],
    "sg:phone":"+1 323 583 0088",
    "sg:postcode":"90255",
    "sg:province":"CA",
    "sg:tags":[
        "polishing",
        "washing"
    ],
    "wof:name":"Latinos Carwash",
    "wof:placetype":"venue"
},
  "geometry": {"coordinates":[-118.20626300000001,33.972168],"type":"Point"}
}