{
  "type": "Feature",
  "properties": {
    "iso:country":"US",
    "sg:address":"965 Olive Dr Ste F",
    "sg:city":"Davis",
    "sg:classifiers":[
        {
            "category":"Sports & Exercise",
            "subcategory":"Swimming Pool",
            "type":"Entertainment"
        }
    ],
    "sg:phone":"+1 530 758 1610",
    "sg:postcode":"95616",
    "sg:province":"CA",
    "wof:name":"Davis Pool Supply",
    "wof:placetype":"venue"
},
  "geometry": {"coordinates":[-121.739113,38.540324],"type":"Point"}
}