{
  "type": "Feature",
  "properties": {
    "addr:full":"315 G St Antioch CA 94509",
    "addr:housenumber":"315",
    "addr:postcode":"ca 94509",
    "addr:street":"G St",
    "iso:country":"US",
    "sg:address":"315 G St",
    "sg:city":"Antioch",
    "sg:classifiers":[
        {
            "category":"Manufacturing",
            "subcategory":"Apparel",
            "type":"Manufacturing & Wholesale Goods"
        }
    ],
    "sg:phone":"+1 925 706 1700",
    "sg:postcode":"94509",
    "sg:province":"CA",
    "sg:tags":[
        "product",
        "mfg"
    ],
    "wof:name":"Digital Canvas",
    "wof:placetype":"venue"
},
  "geometry": {"coordinates":[-121.813688,38.015569],"type":"Point"}
}