{
  "type": "Feature",
  "properties": {
    "addr:full":"12214 Riverside Dr Valley Village CA 91607",
    "addr:housenumber":"12214",
    "addr:postcode":"91607",
    "addr:street":"Riverside Dr",
    "iso:country":"US",
    "sg:address":"12214 Riverside Dr",
    "sg:city":"Valley Village",
    "sg:classifiers":[
        {
            "category":"Social Services",
            "type":"Services"
        }
    ],
    "sg:phone":"+1 818 508 0852",
    "sg:postcode":"91607",
    "sg:province":"CA",
    "sg:tags":[
        "counselor",
        "marriage",
        "family"
    ],
    "wof:name":"Jodie Levin MFT",
    "wof:placetype":"venue"
},
  "geometry": {"coordinates":[-118.399143,34.15754],"type":"Point"}
}