{
  "type": "Feature",
  "properties": {
    "iso:country":"US",
    "sg:address":"7 E Huntington Dr",
    "sg:city":"Arcadia",
    "sg:classifiers":[
        {
            "category":"Restaurant",
            "type":"Food & Drink"
        }
    ],
    "sg:menulink":"http://www.allmenus.com/ca/upper-san-gabriel-valley/8790-dennys/menu/",
    "sg:phone":"+1 626 446 3401",
    "sg:postcode":"91006",
    "sg:province":"CA",
    "sg:tags":[
        "american",
        "diner"
    ],
    "wof:name":"Denny's",
    "wof:placetype":"venue"
},
  "geometry": {"coordinates":[-118.024072,34.140198],"type":"Point"}
}