{
  "type": "Feature",
  "properties": {
    "addr:full":"1654 Lollie Ln El Centro CA 92243",
    "addr:housenumber":"1654",
    "addr:postcode":"92243",
    "addr:street":"Lollie Ln",
    "iso:country":"US",
    "sg:address":"1654 Lollie Ln",
    "sg:city":"El Centro",
    "sg:classifiers":[
        {
            "category":"Farming",
            "subcategory":"Farm",
            "type":"Manufacturing & Wholesale Goods"
        }
    ],
    "sg:phone":"+1 760 791 3408",
    "sg:postcode":"92243",
    "sg:province":"CA",
    "sg:tags":[
        "crop",
        "general"
    ],
    "wof:name":"Juan Munoz Farm Labor",
    "wof:placetype":"venue"
},
  "geometry": {"coordinates":[-115.50585700000001,32.770831],"type":"Point"}
}