{
  "type": "Feature",
  "properties": {
    "addr:full":"569 Constitution Ave Camarillo CA 93012",
    "addr:housenumber":"569",
    "addr:postcode":"93012",
    "addr:street":"Constitution Ave",
    "iso:country":"US",
    "sg:address":"569 Constitution Ave",
    "sg:city":"Camarillo",
    "sg:classifiers":[
        {
            "category":"Professional",
            "type":"Services"
        }
    ],
    "sg:phone":"+1 805 389 3401",
    "sg:postcode":"93012",
    "sg:province":"CA",
    "wof:name":"Silver State Bermuda Equity",
    "wof:placetype":"venue"
},
  "geometry": {"coordinates":[-119.031615,34.205958],"type":"Point"}
}