{
  "type": "Feature",
  "properties": {
    "addr:full":"1701 Lundy Ave San Jose CA 95131",
    "addr:housenumber":"1701",
    "addr:postcode":"95131",
    "addr:street":"Lundy Ave",
    "iso:country":"US",
    "sg:address":"1701 Lundy Ave",
    "sg:city":"San Jose",
    "sg:classifiers":[
        {
            "category":"Travel",
            "subcategory":"Travel Agent",
            "type":"Entertainment"
        }
    ],
    "sg:phone":"+1 408 436 8822",
    "sg:postcode":"95131",
    "sg:province":"CA",
    "sg:tags":[
        "agency",
        "bureau"
    ],
    "wof:name":"Van Vic Vacation",
    "wof:placetype":"venue"
},
  "geometry": {"coordinates":[-121.88722300000001,37.388449],"type":"Point"}
}