{
  "type": "Feature",
  "properties": {
    "iso:country":"US",
    "sg:address":"1189 E Main St",
    "sg:city":"El Cajon",
    "sg:classifiers":[
        {
            "category":"Autos & Motor Vehicles",
            "subcategory":"Auto Supplies",
            "type":"Retail Goods"
        }
    ],
    "sg:phone":"+1 619 593 0780",
    "sg:postcode":"92021",
    "sg:province":"CA",
    "sg:tags":[
        "tire"
    ],
    "wof:name":"Power Tires",
    "wof:placetype":"venue"
},
  "geometry": {"coordinates":[-116.940375,32.794844],"type":"Point"}
}