{
  "type": "Feature",
  "properties": {
    "iso:country":"US",
    "sg:address":"1551 N Miller St",
    "sg:city":"Anaheim",
    "sg:classifiers":[
        {
            "category":"Building & Trades",
            "subcategory":"Landscaping Services",
            "type":"Services"
        }
    ],
    "sg:phone":"+1 714 996 6045",
    "sg:postcode":"92806",
    "sg:province":"CA",
    "sg:tags":[
        "consultant",
        "designer",
        "landscape",
        "contractor"
    ],
    "wof:name":"Paradise Landscape Maintenance",
    "wof:placetype":"venue"
},
  "geometry": {"coordinates":[-117.851004,33.865053],"type":"Point"}
}