{
  "type": "Feature",
  "properties": {
    "addr:full":"9800 Variel Ave Chatsworth CA 91311",
    "addr:postcode":"9800;91311",
    "addr:street":"Variel Ave",
    "iso:country":"US",
    "sg:address":"9800 Variel Ave",
    "sg:city":"Chatsworth",
    "sg:classifiers":[
        {
            "category":"Communications",
            "type":"Services"
        }
    ],
    "sg:phone":"+1 818 998 2800",
    "sg:postcode":"91311",
    "sg:province":"CA",
    "wof:name":"Goodman Communications",
    "wof:placetype":"venue"
},
  "geometry": {"coordinates":[-118.592851,34.248146],"type":"Point"}
}