{
  "type": "Feature",
  "properties": {
    "addr:full":"2309 California St Stockton CA 95204",
    "addr:housenumber":"2309",
    "addr:postcode":"95204",
    "addr:street":"California St",
    "iso:country":"US",
    "sg:address":"2309 California St",
    "sg:city":"Stockton",
    "sg:classifiers":[
        {
            "category":"Wholesale",
            "subcategory":"Office Equipment",
            "type":"Manufacturing & Wholesale Goods"
        }
    ],
    "sg:phone":"+1 209 577 0233",
    "sg:postcode":"95204",
    "sg:province":"CA",
    "sg:tags":[
        "register",
        "cash",
        "supply"
    ],
    "wof:name":"Minimax Inc",
    "wof:placetype":"venue"
},
  "geometry": {"coordinates":[-121.29110900000001,37.975423],"type":"Point"}
}