{
  "type": "Feature",
  "properties": {
    "addr:full":"301 Howard St San Francisco CA 94105",
    "addr:housenumber":"301",
    "addr:postcode":"94105",
    "addr:street":"Howard St",
    "iso:country":"US",
    "sg:address":"301 Howard St",
    "sg:city":"San Francisco",
    "sg:classifiers":[
        {
            "category":"Manufacturing",
            "subcategory":"Printing",
            "type":"Manufacturing & Wholesale Goods"
        }
    ],
    "sg:phone":"+1 415 896 6882",
    "sg:postcode":"94105",
    "sg:province":"CA",
    "sg:tags":[
        "label"
    ],
    "wof:name":"SML Labels USA Inc",
    "wof:placetype":"venue"
},
  "geometry": {"coordinates":[-122.395151,37.789235],"type":"Point"}
}