{
  "type": "Feature",
  "properties": {
    "iso:country":"US",
    "sg:address":"14840 Highway 4",
    "sg:city":"Byron",
    "sg:classifiers":[
        {
            "category":"Banks & Credit Unions",
            "subcategory":"Bank",
            "type":"Services"
        }
    ],
    "sg:phone":"+1 925 513 2110",
    "sg:postcode":"94505",
    "sg:province":"CA",
    "sg:website":"www.usbank.com",
    "wof:name":"U.S. Bank",
    "wof:placetype":"venue"
},
  "geometry": {"coordinates":[-121.62157999999999,37.889524],"type":"Point"}
}