{
  "type": "Feature",
  "properties": {
    "addr:full":"1010 Northgate Dr San Rafael CA 94903",
    "addr:housenumber":"1010",
    "addr:postcode":"94903",
    "addr:street":"Northgate Dr",
    "iso:country":"US",
    "sg:address":"1010 Northgate Dr",
    "sg:city":"San Rafael",
    "sg:classifiers":[
        {
            "category":"Travel",
            "subcategory":"Hotels & Motels",
            "type":"Entertainment"
        }
    ],
    "sg:phone":"+1 415 479 8800",
    "sg:postcode":"94903",
    "sg:province":"CA",
    "wof:name":"Barcelo Hotel",
    "wof:placetype":"venue"
},
  "geometry": {"coordinates":[-122.54532,38.008891],"type":"Point"}
}