{
  "type": "Feature",
  "properties": {
    "addr:full":"44368 S Grimmer Blvd Fremont CA 94538",
    "addr:housenumber":"44368",
    "addr:postcode":"94538",
    "addr:street":"S Grimmer Blvd",
    "iso:country":"US",
    "sg:address":"44368 S Grimmer Blvd",
    "sg:city":"Fremont",
    "sg:classifiers":[
        {
            "category":"Shopping",
            "subcategory":"Computers & Home Electronics",
            "type":"Retail Goods"
        }
    ],
    "sg:phone":"+1 510 226 7031",
    "sg:postcode":"94538",
    "sg:province":"CA",
    "sg:tags":[
        "parts",
        "supply"
    ],
    "wof:name":"Rashmi Electronics Inc",
    "wof:placetype":"venue"
},
  "geometry": {"coordinates":[-121.955078,37.502734],"type":"Point"}
}