{
  "type": "Feature",
  "properties": {
    "addr:full":"555 W 5th St Ste 3000 Los Angeles CA 90013",
    "addr:housenumber":"555",
    "addr:postcode":"3000;90013",
    "addr:street":"W 5Th St Ste",
    "iso:country":"US",
    "sg:address":"555 W 5th St Ste 3000",
    "sg:city":"Los Angeles",
    "sg:classifiers":[
        {
            "category":"Banks & Credit Unions",
            "subcategory":"Financial Services",
            "type":"Services"
        }
    ],
    "sg:phone":"+1 213 996 8492",
    "sg:postcode":"90013",
    "sg:province":"CA",
    "sg:website":"us.hudson.com/legal/node.asp?kwd...",
    "wof:name":"Hudson Legal Staffing",
    "wof:placetype":"venue"
},
  "geometry": {"coordinates":[-118.253703,34.050046],"type":"Point"}
}