{
  "type": "Feature",
  "properties": {
    "iso:country":"US",
    "sg:address":"5780 Ave 296",
    "sg:city":"Visalia",
    "sg:classifiers":[
        {
            "category":"Restaurant",
            "type":"Food & Drink"
        }
    ],
    "sg:phone":"+1 559 651 1665",
    "sg:postcode":"93291",
    "sg:province":"CA",
    "sg:tags":[
        "caterer"
    ],
    "wof:name":"M & N Specialties Custom",
    "wof:placetype":"venue"
},
  "geometry": {"coordinates":[-119.44611999999999,36.327389],"type":"Point"}
}