{
  "type": "Feature",
  "properties": {
    "iso:country":"US",
    "sg:address":"1410 3rd St",
    "sg:city":"Riverside",
    "sg:classifiers":[
        {
            "category":"Real Estate",
            "subcategory":"Real Estate Agent",
            "type":"Services"
        }
    ],
    "sg:phone":"+1 951 786 3748",
    "sg:postcode":"92507",
    "sg:province":"CA",
    "wof:name":"New Century REI",
    "wof:placetype":"venue"
},
  "geometry": {"coordinates":[-117.34262,33.982954],"type":"Point"}
}