{
  "type": "Feature",
  "properties": {
    "addr:full":"1505 Solano Ave Berkeley CA 94707",
    "addr:housenumber":"1505",
    "addr:postcode":"94707",
    "addr:street":"Solano Ave",
    "iso:country":"US",
    "sg:address":"1505 Solano Ave",
    "sg:city":"Berkeley",
    "sg:classifiers":[
        {
            "category":"Professional",
            "subcategory":"Lawyer & Legal Services",
            "type":"Services"
        }
    ],
    "sg:phone":"+1 510 527 8454",
    "sg:postcode":"94707",
    "sg:province":"CA",
    "sg:tags":[
        "attorney"
    ],
    "wof:name":"Cheryl Law Offices",
    "wof:placetype":"venue"
},
  "geometry": {"coordinates":[-122.287272,37.890977],"type":"Point"}
}