{
  "type": "Feature",
  "properties": {
    "iso:country":"US",
    "sg:address":"3744 Mt Diablo Blvd",
    "sg:city":"Lafayette",
    "sg:classifiers":[
        {
            "category":"Insurance",
            "subcategory":"Insurance Agent",
            "type":"Services"
        }
    ],
    "sg:phone":"+1 925 299 3880",
    "sg:postcode":"94549",
    "sg:province":"CA",
    "wof:name":"Stephen Bundy Life Insurance",
    "wof:placetype":"venue"
},
  "geometry": {"coordinates":[-122.128283,37.890762],"type":"Point"}
}