{
  "type": "Feature",
  "properties": {
    "addr:full":"14508 Victory Blvd Van Nuys CA 91411",
    "addr:housenumber":"14508",
    "addr:postcode":"91411",
    "addr:street":"Victory Blvd",
    "iso:country":"US",
    "sg:address":"14508 Victory Blvd",
    "sg:city":"Van Nuys",
    "sg:classifiers":[
        {
            "category":"Restaurant",
            "type":"Food & Drink"
        }
    ],
    "sg:phone":"+1 818 787 3030",
    "sg:postcode":"91411",
    "sg:province":"CA",
    "sg:tags":[
        "pizza"
    ],
    "sg:website":"www.lapizzaloca.com",
    "wof:name":"La Pizza Loca",
    "wof:placetype":"venue"
},
  "geometry": {"coordinates":[-118.44899700000001,34.186798],"type":"Point"}
}