{
  "type": "Feature",
  "properties": {
    "iso:country":"US",
    "sg:address":"2750 E Main St",
    "sg:city":"Ventura",
    "sg:classifiers":[
        {
            "category":"Home & Garden",
            "subcategory":"Hardware",
            "type":"Retail Goods"
        },
        {
            "category":"Retail",
            "subcategory":"Repair Shop",
            "type":"Services"
        }
    ],
    "sg:phone":"+1 805 643 5397",
    "sg:postcode":"93003",
    "sg:province":"CA",
    "sg:tags":[
        "lock",
        "locksmith"
    ],
    "wof:name":"Sheryl's Keys",
    "wof:placetype":"venue"
},
  "geometry": {"coordinates":[-119.259713,34.273568],"type":"Point"}
}