{
  "type": "Feature",
  "properties": {
    "addr:full":"712 Clark Ave Encinitas CA 92024",
    "addr:housenumber":"712",
    "addr:postcode":"92024",
    "addr:street":"Clark Ave",
    "iso:country":"US",
    "sg:address":"712 Clark Ave",
    "sg:city":"Encinitas",
    "sg:classifiers":[
        {
            "category":"Wholesale",
            "subcategory":"Plants",
            "type":"Manufacturing & Wholesale Goods"
        }
    ],
    "sg:phone":"+1 760 753 4386",
    "sg:postcode":"92024",
    "sg:province":"CA",
    "sg:tags":[
        "supply"
    ],
    "wof:name":"L & E Nursery",
    "wof:placetype":"venue"
},
  "geometry": {"coordinates":[-117.289703,33.063159],"type":"Point"}
}