{
  "type": "Feature",
  "properties": {
    "iso:country":"US",
    "sg:address":"1339 Pine St",
    "sg:city":"Walnut Creek",
    "sg:classifiers":[
        {
            "category":"Local Transit",
            "type":"Transportation"
        },
        {
            "category":"Taxi",
            "type":"Transportation"
        }
    ],
    "sg:phone":"+1 925 933 6800",
    "sg:postcode":"94596",
    "sg:province":"CA",
    "sg:tags":[
        "taxicab"
    ],
    "wof:name":"A A Airport Transportation",
    "wof:placetype":"venue"
},
  "geometry": {"coordinates":[-122.060043,37.91073],"type":"Point"}
}