{
  "type": "Feature",
  "properties": {
    "addr:full":"1014 56th St San Diego CA 92114",
    "addr:housenumber":"1014",
    "addr:postcode":"92114",
    "addr:street":"56Th St",
    "iso:country":"US",
    "sg:address":"1014 56th St",
    "sg:city":"San Diego",
    "sg:classifiers":[
        {
            "category":"Building & Trades",
            "subcategory":"Construction",
            "type":"Services"
        }
    ],
    "sg:phone":"+1 619 262 6160",
    "sg:postcode":"92114",
    "sg:province":"CA",
    "sg:tags":[
        "general",
        "contractor"
    ],
    "wof:name":"American Professional Builders",
    "wof:placetype":"venue"
},
  "geometry": {"coordinates":[-117.075784,32.717895],"type":"Point"}
}