{
  "type": "Feature",
  "properties": {
    "addr:full":"7650 Windbridge Dr Sacramento CA 95831",
    "addr:housenumber":"7650",
    "addr:postcode":"95831",
    "addr:street":"Windbridge Dr",
    "iso:country":"US",
    "sg:address":"7650 Windbridge Dr",
    "sg:city":"Sacramento",
    "sg:classifiers":[
        {
            "category":"Real Estate",
            "subcategory":"Real Estate Operator",
            "type":"Services"
        }
    ],
    "sg:phone":"+1 916 429 1010",
    "sg:postcode":"95831",
    "sg:province":"CA",
    "sg:tags":[
        "apartment"
    ],
    "wof:name":"Waterford Cove Apartments",
    "wof:placetype":"venue"
},
  "geometry": {"coordinates":[-121.53574,38.482186],"type":"Point"}
}