{
  "type": "Feature",
  "properties": {
    "addr:full":"3821 Villa Glen Way San Jose CA 95136",
    "addr:housenumber":"3821",
    "addr:postcode":"95136",
    "addr:street":"Villa Glen Way",
    "iso:country":"US",
    "sg:address":"3821 Villa Glen Way",
    "sg:city":"San Jose",
    "sg:classifiers":[
        {
            "category":"Manufacturing",
            "subcategory":"Building Materials",
            "type":"Manufacturing & Wholesale Goods"
        }
    ],
    "sg:phone":"+1 408 205 6503",
    "sg:postcode":"95136",
    "sg:province":"CA",
    "sg:tags":[
        "mfg",
        "wood",
        "kitchen",
        "cabinet"
    ],
    "wof:name":"Heritage Wood Designs",
    "wof:placetype":"venue"
},
  "geometry": {"coordinates":[-121.873424,37.270036],"type":"Point"}
}