{
  "type": "Feature",
  "properties": {
    "addr:full":"1080 Blossom Hill Rd Ste A San Jose CA 95123",
    "addr:housenumber":"1080",
    "addr:postcode":"95123",
    "addr:street":"Blossom Hill Rd Ste A",
    "iso:country":"US",
    "sg:address":"1080 Blossom Hill Rd Ste A",
    "sg:city":"San Jose",
    "sg:classifiers":[
        {
            "category":"Sports & Exercise",
            "subcategory":"Gym",
            "type":"Entertainment"
        }
    ],
    "sg:phone":"+1 408 267 2440",
    "sg:postcode":"95123",
    "sg:province":"CA",
    "sg:tags":[
        "trainer"
    ],
    "wof:name":"Busy Body Home Fitness",
    "wof:placetype":"venue"
},
  "geometry": {"coordinates":[-121.87400100000001,37.250702],"type":"Point"}
}