{
  "type": "Feature",
  "properties": {
    "addr:full":"13376 Rue Montaigne Oregon House CA 95962",
    "addr:housenumber":"13376",
    "addr:postcode":"95962",
    "addr:street":"Rue Montaigne",
    "iso:country":"US",
    "sg:address":"13376 Rue Montaigne",
    "sg:city":"Oregon House",
    "sg:classifiers":[
        {
            "category":"Professional",
            "subcategory":"Engineering",
            "type":"Services"
        }
    ],
    "sg:phone":"+1 530 692 0140",
    "sg:postcode":"95962",
    "sg:province":"CA",
    "sg:tags":[
        "engineer"
    ],
    "wof:name":"Advanced Automotive Batteries",
    "wof:placetype":"venue"
},
  "geometry": {"coordinates":[-121.265933,39.348508],"type":"Point"}
}