{
  "type": "Feature",
  "properties": {
    "addr:full":"225 Vis del Mar San Rafael CA 94901",
    "addr:housenumber":"225",
    "addr:postcode":"94901",
    "addr:street":"Vis Del Mar",
    "iso:country":"US",
    "sg:address":"225 Vis del Mar",
    "sg:city":"San Rafael",
    "sg:classifiers":[
        {
            "category":"Professional",
            "type":"Services"
        }
    ],
    "sg:phone":"+1 415 485 0881",
    "sg:postcode":"94901",
    "sg:province":"CA",
    "wof:name":"Gigagraphics",
    "wof:placetype":"venue"
},
  "geometry": {"coordinates":[-122.50018,37.963252],"type":"Point"}
}