{
  "type": "Feature",
  "properties": {
    "addr:full":"7021 Monterey St Gilroy CA 95020",
    "addr:housenumber":"7021",
    "addr:postcode":"95020",
    "addr:street":"Monterey St",
    "iso:country":"US",
    "sg:address":"7021 Monterey St",
    "sg:city":"Gilroy",
    "sg:classifiers":[
        {
            "category":"Autos & Motor Vehicles",
            "subcategory":"Automobile Sales",
            "type":"Retail Goods"
        }
    ],
    "sg:phone":"+1 408 848 3058",
    "sg:postcode":"95020",
    "sg:province":"CA",
    "sg:tags":[
        "car",
        "dealer"
    ],
    "wof:name":"Campbell Auto Sales",
    "wof:placetype":"venue"
},
  "geometry": {"coordinates":[-121.56621800000001,37.000992],"type":"Point"}
}