{
  "type": "Feature",
  "properties": {
    "iso:country":"US",
    "sg:address":"1105 Coleman Ave",
    "sg:city":"San Jose",
    "sg:classifiers":[
        {
            "category":"Manufacturing",
            "subcategory":"Motor Vehicles & Parts",
            "type":"Manufacturing & Wholesale Goods"
        }
    ],
    "sg:phone":"+1 408 289 0111",
    "sg:postcode":"95110",
    "sg:province":"CA",
    "sg:tags":[
        "military",
        "mfg"
    ],
    "wof:name":"FMC Corporation",
    "wof:placetype":"venue"
},
  "geometry": {"coordinates":[-121.923937,37.352123],"type":"Point"}
}