{
  "type": "Feature",
  "properties": {
    "iso:country":"US",
    "sg:address":"4025 Spencer St",
    "sg:city":"Torrance",
    "sg:classifiers":[
        {
            "category":"Professional",
            "type":"Services"
        }
    ],
    "sg:phone":"+1 310 371 9874",
    "sg:postcode":"90503",
    "sg:province":"CA",
    "sg:tags":[
        "establishment"
    ],
    "wof:name":"Kokoa Associates",
    "wof:placetype":"venue"
},
  "geometry": {"coordinates":[-118.356998,33.845066],"type":"Point"}
}