{
  "type": "Feature",
  "properties": {
    "iso:country":"US",
    "sg:address":"7919 Cll San Felipe",
    "sg:city":"Carlsbad",
    "sg:classifiers":[
        {
            "category":"Professional",
            "subcategory":"Business Services",
            "type":"Services"
        }
    ],
    "sg:phone":"+1 760 436 7077",
    "sg:postcode":"92009",
    "sg:province":"CA",
    "sg:tags":[
        "appraiser"
    ],
    "wof:name":"Appraisal Trainee Svc",
    "wof:placetype":"venue"
},
  "geometry": {"coordinates":[-117.241124,33.071194],"type":"Point"}
}