{
  "type": "Feature",
  "properties": {
    "addr:full":"940 Hopper Ave Santa Rosa CA 95403",
    "addr:housenumber":"940",
    "addr:postcode":"95403",
    "addr:street":"Hopper Ave",
    "iso:country":"US",
    "sg:address":"940 Hopper Ave",
    "sg:city":"Santa Rosa",
    "sg:classifiers":[
        {
            "category":"Organizations",
            "subcategory":"Labor Organization",
            "type":"Services"
        }
    ],
    "sg:phone":"+1 707 546 1384",
    "sg:postcode":"95403",
    "sg:province":"CA",
    "wof:name":"United Food & Commercial Wrkrs",
    "wof:placetype":"venue"
},
  "geometry": {"coordinates":[-122.73628600000001,38.47963],"type":"Point"}
}