{
  "type": "Feature",
  "properties": {
    "addr:full":"220 N Palisade Dr Santa Maria CA 93454",
    "addr:housenumber":"220",
    "addr:postcode":"93454",
    "addr:street":"N Palisade Dr",
    "iso:country":"US",
    "sg:address":"220 N Palisade Dr",
    "sg:city":"Santa Maria",
    "sg:classifiers":[
        {
            "category":"Social Services",
            "type":"Services"
        }
    ],
    "sg:phone":"+1 805 925 4030",
    "sg:postcode":"93454",
    "sg:province":"CA",
    "sg:tags":[
        "counselor",
        "marriage",
        "family"
    ],
    "wof:name":"Peppertree Counseling",
    "wof:placetype":"venue"
},
  "geometry": {"coordinates":[-120.412138,34.954345],"type":"Point"}
}