{
  "type": "Feature",
  "properties": {
    "iso:country":"US",
    "sg:address":"8340 Clairemont Mesa Blvd",
    "sg:city":"San Diego",
    "sg:classifiers":[
        {
            "category":"Real Estate",
            "subcategory":"Real Estate Agent",
            "type":"Services"
        }
    ],
    "sg:phone":"+1 858 496 0009",
    "sg:postcode":"92117",
    "sg:province":"CA",
    "wof:name":"Denise E Matthis Financial Svc",
    "wof:placetype":"venue"
},
  "geometry": {"coordinates":[-117.14366099999999,32.832894],"type":"Point"}
}