{
  "type": "Feature",
  "properties": {
    "iso:country":"US",
    "sg:address":"3870 State Hwy 128",
    "sg:city":"Calistoga",
    "sg:classifiers":[
        {
            "category":"Manufacturing",
            "subcategory":"Food",
            "type":"Manufacturing & Wholesale Goods"
        }
    ],
    "sg:phone":"+1 707 942 4267",
    "sg:postcode":"94515",
    "sg:province":"CA",
    "sg:tags":[
        "winery"
    ],
    "wof:name":"Tom Eddy Wines",
    "wof:placetype":"venue"
},
  "geometry": {"coordinates":[-122.528457,38.554889],"type":"Point"}
}