{
  "type": "Feature",
  "properties": {
    "iso:country":"US",
    "sg:address":"585 W Sierra Madre Blvd",
    "sg:city":"Sierra Madre",
    "sg:classifiers":[
        {
            "category":"Professional",
            "type":"Services"
        }
    ],
    "sg:phone":"+1 626 355 3888",
    "sg:postcode":"91024",
    "sg:province":"CA",
    "wof:name":"Straps",
    "wof:placetype":"venue"
},
  "geometry": {"coordinates":[-118.067774,34.161872],"type":"Point"}
}