{
  "type": "Feature",
  "properties": {
    "addr:full":"1544 Washington Blvd Fremont CA 94539",
    "addr:housenumber":"1544",
    "addr:postcode":"94539",
    "addr:street":"Washington Blvd",
    "iso:country":"US",
    "sg:address":"1544 Washington Blvd",
    "sg:city":"Fremont",
    "sg:classifiers":[
        {
            "category":"Insurance",
            "subcategory":"Insurance Agent",
            "type":"Services"
        }
    ],
    "sg:phone":"+1 510 252 1765",
    "sg:postcode":"94539",
    "sg:province":"CA",
    "wof:name":"Allstate Insurance",
    "wof:placetype":"venue"
},
  "geometry": {"coordinates":[-121.93531,37.531328],"type":"Point"}
}