{
  "type": "Feature",
  "properties": {
    "addr:full":"1499 Marty Ave Mckinleyville CA 95519",
    "addr:housenumber":"1499",
    "addr:postcode":"95519",
    "addr:street":"Marty Ave",
    "iso:country":"US",
    "sg:address":"1499 Marty Ave",
    "sg:city":"Mckinleyville",
    "sg:classifiers":[
        {
            "category":"Wholesale",
            "subcategory":"Machinery & Supplies",
            "type":"Manufacturing & Wholesale Goods"
        }
    ],
    "sg:phone":"+1 707 839 0170",
    "sg:postcode":"95519",
    "sg:province":"CA",
    "sg:tags":[
        "farm",
        "equipment"
    ],
    "wof:name":"Alto Equipment",
    "wof:placetype":"venue"
},
  "geometry": {"coordinates":[-124.103298,40.935851],"type":"Point"}
}