{
  "type": "Feature",
  "properties": {
    "iso:country":"US",
    "sg:address":"3649 India St",
    "sg:city":"San Diego",
    "sg:classifiers":[
        {
            "category":"Retail",
            "subcategory":"Repair Shop",
            "type":"Services"
        }
    ],
    "sg:phone":"+1 619 297 9136",
    "sg:postcode":"92103",
    "sg:province":"CA",
    "sg:tags":[
        "instrument",
        "musical"
    ],
    "sg:website":"www.theblueguitar.com",
    "wof:name":"Blue Guitar",
    "wof:placetype":"venue"
},
  "geometry": {"coordinates":[-117.178966,32.740685],"type":"Point"}
}