{
  "type": "Feature",
  "properties": {
    "addr:full":"920 Silver Lake Blvd Los Angeles CA 90026",
    "addr:housenumber":"920",
    "addr:postcode":"90026",
    "addr:street":"Silver Lake Blvd",
    "iso:country":"US",
    "sg:address":"920 Silver Lake Blvd",
    "sg:city":"Los Angeles",
    "sg:classifiers":[
        {
            "category":"Personal",
            "subcategory":"Beauty Salon",
            "type":"Services"
        }
    ],
    "sg:phone":"+1 310 867 4925",
    "sg:postcode":"90026",
    "sg:province":"CA",
    "sg:tags":[
        "spa"
    ],
    "sg:website":"www.massageinla.com",
    "wof:name":"Massage In LA",
    "wof:placetype":"venue"
},
  "geometry": {"coordinates":[-118.273128,34.081716],"type":"Point"}
}