{
  "type": "Feature",
  "properties": {
    "addr:full":"3328 State St Santa Barbara CA 93105",
    "addr:housenumber":"3328",
    "addr:postcode":"93105",
    "addr:street":"State St",
    "iso:country":"US",
    "sg:address":"3328 State St",
    "sg:city":"Santa Barbara",
    "sg:classifiers":[
        {
            "category":"Shopping",
            "subcategory":"Musical Instruments",
            "type":"Retail Goods"
        }
    ],
    "sg:phone":"+1 805 569 5055",
    "sg:postcode":"93105",
    "sg:province":"CA",
    "wof:name":"Instrumental Music Co",
    "wof:placetype":"venue"
},
  "geometry": {"coordinates":[-119.735936,34.440469],"type":"Point"}
}