{
  "type": "Feature",
  "properties": {
    "addr:full":"302 Main St Los Altos CA 94022",
    "addr:housenumber":"302",
    "addr:postcode":"94022",
    "addr:street":"Main St",
    "iso:country":"US",
    "sg:address":"302 Main St",
    "sg:city":"Los Altos",
    "sg:classifiers":[
        {
            "category":"Real Estate",
            "subcategory":"Real Estate Agent",
            "type":"Services"
        }
    ],
    "sg:phone":"+1 650 941 9411",
    "sg:postcode":"94022",
    "sg:province":"CA",
    "wof:name":"Sasaki Investments",
    "wof:placetype":"venue"
},
  "geometry": {"coordinates":[-122.117734,37.377884],"type":"Point"}
}