{
  "type": "Feature",
  "properties": {
    "addr:full":"5931 1/2 Franklin Ave Hollywood CA 90028",
    "addr:housenumber":"5931 1 / 2",
    "addr:postcode":"90028",
    "addr:street":"Franklin Ave",
    "iso:country":"US",
    "sg:address":"5931 1/2 Franklin Ave",
    "sg:city":"Hollywood",
    "sg:classifiers":[
        {
            "category":"Communications",
            "subcategory":"Newspaper",
            "type":"Services"
        },
        {
            "category":"Wholesale",
            "subcategory":"Stationery",
            "type":"Manufacturing & Wholesale Goods"
        }
    ],
    "sg:phone":"+1 323 957 0061",
    "sg:postcode":"90028",
    "sg:province":"CA",
    "sg:tags":[
        "magazine",
        "card"
    ],
    "sg:website":"www.thedailyplanetbookstore.com",
    "wof:name":"The Daily Planet",
    "wof:placetype":"venue"
},
  "geometry": {"coordinates":[-118.32656799999999,34.105186],"type":"Point"}
}