{
  "type": "Feature",
  "properties": {
    "iso:country":"US",
    "sg:address":"1113 Douglas Ct",
    "sg:city":"Alamo",
    "sg:classifiers":[
        {
            "category":"Manufacturing",
            "subcategory":"Toys & Sporting Goods",
            "type":"Manufacturing & Wholesale Goods"
        }
    ],
    "sg:phone":"+1 925 256 1852",
    "sg:postcode":"94507",
    "sg:province":"CA",
    "sg:tags":[
        "mfg"
    ],
    "wof:name":"Sierra Lace",
    "wof:placetype":"venue"
},
  "geometry": {"coordinates":[-122.026678,37.865351],"type":"Point"}
}