{
  "type": "Feature",
  "properties": {
    "iso:country":"US",
    "sg:address":"3509 Bradshaw Rd",
    "sg:city":"Sacramento",
    "sg:classifiers":[
        {
            "category":"Banks & Credit Unions",
            "subcategory":"Bank",
            "type":"Services"
        },
        {
            "category":"Banks & Credit Unions",
            "subcategory":"Financial Services",
            "type":"Services"
        }
    ],
    "sg:phone":"+1 916 979 7233",
    "sg:postcode":"95827",
    "sg:province":"CA",
    "sg:tags":[
        "broker",
        "mortgage"
    ],
    "wof:name":"Safe Credit Union",
    "wof:placetype":"venue"
},
  "geometry": {"coordinates":[-121.335999,38.561699],"type":"Point"}
}