{
  "type": "Feature",
  "properties": {
    "addr:full":"533 White Ln Bakersfield CA 93307",
    "addr:housenumber":"533",
    "addr:postcode":"93307",
    "addr:street":"White Ln",
    "iso:country":"US",
    "sg:address":"533 White Ln",
    "sg:city":"Bakersfield",
    "sg:classifiers":[
        {
            "category":"Autos & Motor Vehicles",
            "subcategory":"Auto Supplies",
            "type":"Retail Goods"
        },
        {
            "category":"Retail",
            "subcategory":"Auto Repair",
            "type":"Services"
        }
    ],
    "sg:phone":"+1 661 832 6184",
    "sg:postcode":"93307",
    "sg:province":"CA",
    "sg:tags":[
        "wheel",
        "oil",
        "tire",
        "retread",
        "lube",
        "recap"
    ],
    "sg:website":"http://www.bigbrandtire.com",
    "wof:name":"Big Brand Tire & Service",
    "wof:placetype":"venue"
},
  "geometry": {"coordinates":[-119.007935,35.317621],"type":"Point"}
}