{
  "type": "Feature",
  "properties": {
    "iso:country":"US",
    "sg:address":"41440 Rd 128",
    "sg:city":"Orosi",
    "sg:classifiers":[
        {
            "category":"Food & Beverages",
            "subcategory":"Bakery",
            "type":"Retail Goods"
        },
        {
            "category":"Restaurant",
            "type":"Food & Drink"
        }
    ],
    "sg:phone":"+1 559 528 4936",
    "sg:postcode":"93647",
    "sg:province":"CA",
    "sg:tags":[
        "doughnut",
        "eating"
    ],
    "wof:name":"Kimbo's Donuts",
    "wof:placetype":"venue"
},
  "geometry": {"coordinates":[-119.28679,36.541306],"type":"Point"}
}