{
  "type": "Feature",
  "properties": {
    "acgov:api":"890.0",
    "acgov:type":"ES",
    "addr:full":"5200 Valpey Park Dr Fremont CA",
    "wof:categories":[
        "education_and_religion:education=school"
    ],
    "wof:name":"Steven Millard Elementary",
    "wof:placetype":"venue"
},
  "geometry": {"coordinates":[-121.97395612326426,37.51998739004419],"type":"Point"}
}