{
  "type": "Feature",
  "properties": {
    "iso:country":"US",
    "sg:address":"2941 Sunrise Blvd",
    "sg:city":"Rancho Cordova",
    "sg:classifiers":[
        {
            "category":"Arts & Performance",
            "subcategory":"Theater",
            "type":"Entertainment"
        }
    ],
    "sg:phone":"+1 916 631 4190",
    "sg:postcode":"95742",
    "sg:province":"CA",
    "sg:tags":[
        "bureau"
    ],
    "wof:name":"Hot Ticket Entertainment",
    "wof:placetype":"venue"
},
  "geometry": {"coordinates":[-121.265593,38.597776],"type":"Point"}
}