{
  "type": "Feature",
  "properties": {
    "iso:country":"US",
    "sg:address":"6633 Van Nuys Blvd",
    "sg:city":"Van Nuys",
    "sg:classifiers":[
        {
            "category":"Shopping",
            "subcategory":"Jewelry",
            "type":"Retail Goods"
        }
    ],
    "sg:phone":"+1 818 785 0560",
    "sg:postcode":"91405",
    "sg:province":"CA",
    "wof:name":"J B M Jewelers",
    "wof:placetype":"venue"
},
  "geometry": {"coordinates":[-118.44899700000001,34.191299],"type":"Point"}
}