{
  "type": "Feature",
  "properties": {
    "iso:country":"US",
    "sg:address":"2300 S Hope St",
    "sg:city":"Los Angeles",
    "sg:classifiers":[
        {
            "category":"Health Services",
            "subcategory":"Doctor",
            "type":"Services"
        }
    ],
    "sg:phone":"+1 213 742 9707",
    "sg:postcode":"90007",
    "sg:province":"CA",
    "sg:tags":[
        "physician",
        "surgeon"
    ],
    "wof:name":"West Coast Orthopaedics",
    "wof:placetype":"venue"
},
  "geometry": {"coordinates":[-118.273626,34.027083],"type":"Point"}
}