{
  "type": "Feature",
  "properties": {
    "addr:full":"6031 Babbitt Ave Encino CA 91316",
    "addr:housenumber":"6031",
    "addr:postcode":"91316",
    "addr:street":"Babbitt Ave",
    "iso:country":"US",
    "sg:address":"6031 Babbitt Ave",
    "sg:city":"Encino",
    "sg:classifiers":[
        {
            "category":"Retail",
            "subcategory":"Laundry & Dry Cleaning",
            "type":"Services"
        }
    ],
    "sg:phone":"+1 818 509 5963",
    "sg:postcode":"91316",
    "sg:province":"CA",
    "sg:tags":[
        "cleaners",
        "rug",
        "carpet"
    ],
    "wof:name":"Pacific Carpet Care",
    "wof:placetype":"venue"
},
  "geometry": {"coordinates":[-118.509339,34.177126],"type":"Point"}
}