{
  "type": "Feature",
  "properties": {
    "addr:full":"37 Commercial Blvd Novato CA 94949",
    "addr:housenumber":"37",
    "addr:postcode":"94949",
    "addr:street":"Commercial Blvd",
    "iso:country":"US",
    "sg:address":"37 Commercial Blvd",
    "sg:city":"Novato",
    "sg:classifiers":[
        {
            "category":"Wholesale",
            "subcategory":"Groceries",
            "type":"Manufacturing & Wholesale Goods"
        }
    ],
    "sg:phone":"+1 415 883 6781",
    "sg:postcode":"94949",
    "sg:province":"CA",
    "sg:tags":[
        "cocoa",
        "chocolate"
    ],
    "sg:website":"www.lebelgechocolatier.com",
    "wof:name":"Le Belge Chocolatier",
    "wof:placetype":"venue"
},
  "geometry": {"coordinates":[-122.530081,38.06807],"type":"Point"}
}