{
  "type": "Feature",
  "properties": {
    "addr:full":"17901 Pioneer Blvd Artesia CA 90701",
    "addr:housenumber":"17901",
    "addr:postcode":"90701",
    "addr:street":"Pioneer Blvd",
    "iso:country":"US",
    "sg:address":"17901 Pioneer Blvd",
    "sg:city":"Artesia",
    "sg:classifiers":[
        {
            "category":"Utilities",
            "subcategory":"Mobile Phone",
            "type":"Services"
        }
    ],
    "sg:phone":"+1 562 809 1695",
    "sg:postcode":"90701",
    "sg:province":"CA",
    "sg:tags":[
        "telephone",
        "cellular"
    ],
    "wof:name":"Cingular Wireless",
    "wof:placetype":"venue"
},
  "geometry": {"coordinates":[-118.08218599999999,33.865743],"type":"Point"}
}