{
  "type": "Feature",
  "properties": {
    "addr:full":"1510 Christy Ln Olympic Valley CA 96146",
    "addr:housenumber":"1510",
    "addr:postcode":"96146",
    "addr:street":"Christy Ln",
    "iso:country":"US",
    "sg:address":"1510 Christy Ln",
    "sg:city":"Olympic Valley",
    "sg:classifiers":[
        {
            "category":"Home & Garden",
            "subcategory":"Building Materials",
            "type":"Retail Goods"
        }
    ],
    "sg:phone":"+1 530 583 6725",
    "sg:postcode":"96146",
    "sg:province":"CA",
    "sg:tags":[
        "glass",
        "window",
        "plate"
    ],
    "wof:name":"Squaw Valley Glass",
    "wof:placetype":"venue"
},
  "geometry": {"coordinates":[-120.225953,39.201634],"type":"Point"}
}