{
  "type": "Feature",
  "properties": {
    "iso:country":"US",
    "sg:address":"3034 H St",
    "sg:city":"Eureka",
    "sg:classifiers":[
        {
            "category":"Banks & Credit Unions",
            "subcategory":"Investment Brokerage",
            "type":"Services"
        }
    ],
    "sg:phone":"+1 707 443 6884",
    "sg:postcode":"95501",
    "sg:province":"CA",
    "sg:tags":[
        "security"
    ],
    "wof:name":"Edward Jones Co",
    "wof:placetype":"venue"
},
  "geometry": {"coordinates":[-124.161362,40.780909],"type":"Point"}
}