{
  "type": "Feature",
  "properties": {
    "iso:country":"US",
    "sg:address":"13173 Van Nuys Blvd",
    "sg:city":"Pacoima",
    "sg:classifiers":[
        {
            "category":"Shopping",
            "subcategory":"Gifts & Souvenirs",
            "type":"Retail Goods"
        }
    ],
    "sg:phone":"+1 818 897 5787",
    "sg:postcode":"91331",
    "sg:province":"CA",
    "wof:name":"Black Moon Shop",
    "wof:placetype":"venue"
},
  "geometry": {"coordinates":[-118.41984100000001,34.267906],"type":"Point"}
}