{
  "type": "Feature",
  "properties": {
    "addr:full":"195 W Napa St Sonoma CA 95476",
    "addr:housenumber":"195",
    "addr:postcode":"95476",
    "addr:street":"W Napa St",
    "iso:country":"US",
    "sg:address":"195 W Napa St",
    "sg:city":"Sonoma",
    "sg:classifiers":[
        {
            "category":"Autos & Motor Vehicles",
            "subcategory":"Fuel & Gas Station",
            "type":"Retail Goods"
        }
    ],
    "sg:phone":"+1 707 996 3555",
    "sg:postcode":"95476",
    "sg:province":"CA",
    "sg:tags":[
        "oil"
    ],
    "wof:name":"Stu's 76",
    "wof:placetype":"venue"
},
  "geometry": {"coordinates":[-122.46106,38.292148],"type":"Point"}
}