{
  "type": "Feature",
  "properties": {
    "addr:full":"3500 West Olive Third Floor Burbank CA 91505",
    "addr:housenumber":"3500;floor",
    "addr:postcode":"91505",
    "addr:street":"West Olive Third",
    "iso:country":"US",
    "sg:address":"3500 West Olive Third Floor",
    "sg:city":"Burbank",
    "sg:classifiers":[
        {
            "category":"Professional",
            "subcategory":"Lawyer & Legal Services",
            "type":"Services"
        }
    ],
    "sg:phone":"+1 866 887 2836",
    "sg:postcode":"91505",
    "sg:province":"CA",
    "sg:website":"ThePatentOffice.com",
    "wof:name":"The Patent Office",
    "wof:placetype":"venue"
},
  "geometry": {"coordinates":[-118.33799999999999,34.152736],"type":"Point"}
}