{
  "type": "Feature",
  "properties": {
    "addr:full":"840 E St Eureka CA 95501",
    "addr:housenumber":"840",
    "addr:postcode":"95501",
    "addr:street":"E St",
    "iso:country":"US",
    "sg:address":"840 E St",
    "sg:city":"Eureka",
    "sg:classifiers":[
        {
            "category":"Organizations",
            "subcategory":"Labor Organization",
            "type":"Services"
        }
    ],
    "sg:phone":"+1 707 442 5284",
    "sg:postcode":"95501",
    "sg:province":"CA",
    "wof:name":"Painters & Allied Trades",
    "wof:placetype":"venue"
},
  "geometry": {"coordinates":[-124.166431,40.798972],"type":"Point"}
}