{
  "type": "Feature",
  "properties": {
    "addr:full":"18719 Omega Mine Rd Jamestown CA 95327",
    "addr:housenumber":"18719",
    "addr:postcode":"95327",
    "addr:street":"Omega Mine Rd",
    "iso:country":"US",
    "sg:address":"18719 Omega Mine Rd",
    "sg:city":"Jamestown",
    "sg:classifiers":[
        {
            "category":"Food & Beverages",
            "subcategory":"Meat & Fish",
            "type":"Retail Goods"
        }
    ],
    "sg:phone":"+1 209 984 5814",
    "sg:postcode":"95327",
    "sg:province":"CA",
    "sg:tags":[
        "cutting"
    ],
    "wof:name":"Rawhide Meat Processing",
    "wof:placetype":"venue"
},
  "geometry": {"coordinates":[-120.440398,37.963742],"type":"Point"}
}