{
  "type": "Feature",
  "properties": {
    "addr:full":"10641 Hidden Mesa Pl Monterey CA 93940",
    "addr:housenumber":"10641",
    "addr:postcode":"93940",
    "addr:street":"Hidden Mesa Pl",
    "iso:country":"US",
    "sg:address":"10641 Hidden Mesa Pl",
    "sg:city":"Monterey",
    "sg:classifiers":[
        {
            "category":"Shopping",
            "subcategory":"Shoes",
            "type":"Retail Goods"
        }
    ],
    "sg:phone":"+1 831 655 2585",
    "sg:postcode":"93940",
    "sg:province":"CA",
    "wof:name":"Happy Feet Inc",
    "wof:placetype":"venue"
},
  "geometry": {"coordinates":[-121.785984,36.563806],"type":"Point"}
}