{
  "type": "Feature",
  "properties": {
    "addr:full":"1260 Pine St Redding CA 96001",
    "addr:housenumber":"1260",
    "addr:postcode":"96001",
    "addr:street":"Pine St",
    "iso:country":"US",
    "sg:address":"1260 Pine St",
    "sg:city":"Redding",
    "sg:classifiers":[
        {
            "category":"Banks & Credit Unions",
            "subcategory":"Bank",
            "type":"Services"
        }
    ],
    "sg:phone":"+1 530 222 6060",
    "sg:postcode":"96001",
    "sg:province":"CA",
    "wof:name":"Members First Credit Union",
    "wof:placetype":"venue"
},
  "geometry": {"coordinates":[-122.39043599999999,40.58668],"type":"Point"}
}