{
  "type": "Feature",
  "properties": {
    "addr:full":"3819 Santa Rita Dr Concord CA 94519",
    "addr:housenumber":"3819",
    "addr:postcode":"94519",
    "addr:street":"Santa Rita Dr",
    "iso:country":"US",
    "sg:address":"3819 Santa Rita Dr",
    "sg:city":"Concord",
    "sg:classifiers":[
        {
            "category":"Shopping",
            "type":"Retail Goods"
        }
    ],
    "sg:phone":"+1 925 798 6238",
    "sg:postcode":"94519",
    "sg:province":"CA",
    "sg:tags":[
        "tropical",
        "fish"
    ],
    "wof:name":"Reef Aquatics",
    "wof:placetype":"venue"
},
  "geometry": {"coordinates":[-122.00588500000001,37.991141],"type":"Point"}
}