{
  "type": "Feature",
  "properties": {
    "iso:country":"US",
    "sg:address":"3819 Santa Rita Dr",
    "sg:city":"Concord",
    "sg:classifiers":[
        {
            "category":"Shopping",
            "type":"Retail Goods"
        }
    ],
    "sg:phone":"+1 925 798 6238",
    "sg:postcode":"94519",
    "sg:province":"CA",
    "sg:tags":[
        "tropical",
        "fish"
    ],
    "wof:name":"Reef Aquatics",
    "wof:placetype":"venue"
},
  "geometry": {"coordinates":[-122.005885,37.991141],"type":"Point"}
}