{
  "type": "Feature",
  "properties": {
    "addr:full":"39593 Long Ridge Dr Temecula CA 92591",
    "addr:housenumber":"39593",
    "addr:postcode":"92591",
    "addr:street":"Long Ridge Dr",
    "iso:country":"US",
    "sg:address":"39593 Long Ridge Dr",
    "sg:city":"Temecula",
    "sg:classifiers":[
        {
            "category":"Manufacturing",
            "subcategory":"Building Materials",
            "type":"Manufacturing & Wholesale Goods"
        },
        {
            "category":"Home & Garden",
            "subcategory":"Carpets & Floor Coverings",
            "type":"Retail Goods"
        }
    ],
    "sg:phone":"+1 800 236 6610",
    "sg:postcode":"92591",
    "sg:province":"CA",
    "sg:tags":[
        "materials-wholesale",
        "manufacturer"
    ],
    "wof:name":"Boardwalk Floors, Inc.",
    "wof:placetype":"venue"
},
  "geometry": {"coordinates":[-117.14636,33.544851],"type":"Point"}
}