{
  "type": "Feature",
  "properties": {
    "addr:full":"500 12th St Ste 36 Oakland CA 94607",
    "addr:housenumber":"500",
    "addr:postcode":"94607",
    "addr:street":"12Th St Ste 36",
    "iso:country":"US",
    "sg:address":"500 12th St Ste 36",
    "sg:city":"Oakland",
    "sg:classifiers":[
        {
            "category":"Shopping",
            "subcategory":"Florist",
            "type":"Retail Goods"
        }
    ],
    "sg:phone":"+1 510 836 6450",
    "sg:postcode":"94607",
    "sg:province":"CA",
    "wof:name":"Rossi & Rovetti",
    "wof:placetype":"venue"
},
  "geometry": {"coordinates":[-122.273279,37.803414],"type":"Point"}
}