{
  "type": "Feature",
  "properties": {
    "iso:country":"US",
    "sg:address":"1726 W 7th St",
    "sg:city":"Los Angeles",
    "sg:classifiers":[
        {
            "category":"Health Services",
            "subcategory":"Health Practitioner",
            "type":"Services"
        }
    ],
    "sg:phone":"+1 213 483 2213",
    "sg:postcode":"90017",
    "sg:province":"CA",
    "sg:tags":[
        "nutritionist"
    ],
    "wof:name":"Baby Melody Nutrition",
    "wof:placetype":"venue"
},
  "geometry": {"coordinates":[-118.273466,34.054861],"type":"Point"}
}