{
  "type": "Feature",
  "properties": {
    "iso:country":"US",
    "sg:address":"11327 Trade Center Dr Ste 335",
    "sg:city":"Rancho Cordova",
    "sg:classifiers":[
        {
            "category":"Building & Trades",
            "subcategory":"Cleaning & Sanitation",
            "type":"Services"
        },
        {
            "category":"Building & Trades",
            "subcategory":"Construction",
            "type":"Services"
        }
    ],
    "sg:phone":"+1 916 638 4100",
    "sg:postcode":"95742",
    "sg:province":"CA",
    "sg:tags":[
        "cleaner",
        "installation",
        "solar",
        "pool"
    ],
    "sg:website":"leisuretimepool.com",
    "wof:name":"Leisure Time Pool",
    "wof:placetype":"venue"
},
  "geometry": {"coordinates":[-121.263761,38.607202],"type":"Point"}
}