{
  "type": "Feature",
  "properties": {
    "iso:country":"US",
    "sg:address":"44707 Stonebridge Ln",
    "sg:city":"Lancaster",
    "sg:classifiers":[
        {
            "category":"Personal",
            "subcategory":"Beauty Salon",
            "type":"Services"
        }
    ],
    "sg:phone":"+1 661 942 8200",
    "sg:postcode":"93536",
    "sg:province":"CA",
    "wof:name":"Mykels Salon",
    "wof:placetype":"venue"
},
  "geometry": {"coordinates":[-118.176473,34.694733],"type":"Point"}
}