{
  "type": "Feature",
  "properties": {
    "addr:full":"1417 E Verness St West Covina CA 91791",
    "addr:housenumber":"1417",
    "addr:postcode":"91791",
    "addr:street":"E Verness St",
    "iso:country":"US",
    "sg:address":"1417 E Verness St",
    "sg:city":"West Covina",
    "sg:classifiers":[
        {
            "category":"Professional",
            "type":"Services"
        }
    ],
    "sg:phone":"+1 626 966 0955",
    "sg:postcode":"91791",
    "sg:province":"CA",
    "wof:name":"Fire Protection Systems",
    "wof:placetype":"venue"
},
  "geometry": {"coordinates":[-117.912442,34.076467],"type":"Point"}
}