{
  "type": "Feature",
  "properties": {
    "iso:country":"US",
    "sg:address":"1100 S. Coast Highway",
    "sg:city":"Laguna Beach",
    "sg:classifiers":[
        {
            "category":"Professional",
            "subcategory":"Computer Services",
            "type":"Services"
        }
    ],
    "sg:phone":"+1 949 715 0518",
    "sg:postcode":"92651",
    "sg:province":"CA",
    "sg:tags":[
        "recruiting-software",
        "applicant-tracking-system",
        "ats",
        "saas",
        "staffing",
        "job-post",
        "resume"
    ],
    "sg:website":"http://www.resuwe.com",
    "wof:name":"ResuWe",
    "wof:placetype":"venue"
},
  "geometry": {"coordinates":[-117.77758300000001,33.53504],"type":"Point"}
}