{
  "type": "Feature",
  "properties": {
    "iso:country":"US",
    "sg:address":"2900 Clayton Rd",
    "sg:city":"Concord",
    "sg:classifiers":[
        {
            "category":"Taxi",
            "type":"Transportation"
        }
    ],
    "sg:phone":"+1 925 609 7505",
    "sg:postcode":"94519",
    "sg:province":"CA",
    "sg:tags":[
        "taxicab"
    ],
    "wof:name":"Angel Cab",
    "wof:placetype":"venue"
},
  "geometry": {"coordinates":[-122.025452,37.974581],"type":"Point"}
}