{
  "type": "Feature",
  "properties": {
    "addr:full":"2122 Aaron St Los Angeles CA 90026",
    "addr:housenumber":"2122",
    "addr:postcode":"90026",
    "addr:street":"Aaron St",
    "iso:country":"US",
    "sg:address":"2122 Aaron St",
    "sg:city":"Los Angeles",
    "sg:classifiers":[
        {
            "category":"Manufacturing",
            "subcategory":"Metals",
            "type":"Manufacturing & Wholesale Goods"
        }
    ],
    "sg:phone":"+1 213 389 2391",
    "sg:postcode":"90026",
    "sg:province":"CA",
    "sg:tags":[
        "product",
        "wire",
        "fabricated"
    ],
    "sg:website":"www.arowire.com",
    "wof:name":"Aro Wire Products Inc",
    "wof:placetype":"venue"
},
  "geometry": {"coordinates":[-118.25949,34.086634],"type":"Point"}
}