{
  "type": "Feature",
  "properties": {
    "addr:full":"564 Tamarisk Ln San Marcos CA 92078",
    "addr:housenumber":"564",
    "addr:postcode":"92078",
    "addr:street":"Tamarisk Ln",
    "iso:country":"US",
    "sg:address":"564 Tamarisk Ln",
    "sg:city":"San Marcos",
    "sg:classifiers":[
        {
            "category":"Wholesale",
            "subcategory":"Toys & Hobbies",
            "type":"Manufacturing & Wholesale Goods"
        }
    ],
    "sg:phone":"+1 760 744 5506",
    "sg:postcode":"92078",
    "sg:province":"CA",
    "wof:name":"Connies Un Frog Get Able Crmc",
    "wof:placetype":"venue"
},
  "geometry": {"coordinates":[-117.19468000000001,33.132219],"type":"Point"}
}