{
  "type": "Feature",
  "properties": {
    "addr:full":"652 S Coast Hwy Laguna Beach CA 92651",
    "addr:housenumber":"652",
    "addr:postcode":"92651",
    "addr:street":"S Coast Hwy",
    "iso:country":"US",
    "sg:address":"652 S Coast Hwy",
    "sg:city":"Laguna Beach",
    "sg:classifiers":[
        {
            "category":"Manufacturing",
            "subcategory":"Jewelry",
            "type":"Manufacturing & Wholesale Goods"
        }
    ],
    "sg:phone":"+1 949 497 3279",
    "sg:postcode":"92651",
    "sg:province":"CA",
    "sg:tags":[
        "precious",
        "metal",
        "mfg"
    ],
    "wof:name":"Beres Donald Goldsmith",
    "wof:placetype":"venue"
},
  "geometry": {"coordinates":[-117.77988499999999,33.538189],"type":"Point"}
}