{
  "type": "Feature",
  "properties": {
    "addr:full":"18682 Beach Blvd Huntington Beach CA 92648",
    "addr:housenumber":"18682",
    "addr:postcode":"92648",
    "addr:street":"Beach Blvd",
    "iso:country":"US",
    "sg:address":"18682 Beach Blvd",
    "sg:city":"Huntington Beach",
    "sg:classifiers":[
        {
            "category":"Personal",
            "subcategory":"Massage",
            "type":"Services"
        }
    ],
    "sg:phone":"+1 714 965 5500",
    "sg:postcode":"92648",
    "sg:province":"CA",
    "sg:website":"www.relevantyellow.com/Massage-a...",
    "wof:name":"Revitalization Massage And Facial",
    "wof:placetype":"venue"
},
  "geometry": {"coordinates":[-117.98868899999999,33.691129],"type":"Point"}
}