{
  "type": "Feature",
  "properties": {
    "addr:full":"4525 Market Street San Diego CA 92102",
    "addr:housenumber":"4525",
    "addr:postcode":"92102",
    "addr:street":"Market Street",
    "iso:country":"US",
    "sg:address":"4525 Market Street",
    "sg:city":"San Diego",
    "sg:classifiers":[
        {
            "category":"Education",
            "subcategory":"School",
            "type":"Public Place"
        }
    ],
    "sg:phone":"+1 619 264 3113",
    "sg:postcode":"92102",
    "sg:province":"CA",
    "sg:tags":[
        "high",
        "middle",
        "elementary"
    ],
    "wof:name":"Chollas-Mead Elementary School",
    "wof:placetype":"venue"
},
  "geometry": {"coordinates":[-117.097871,32.71143],"type":"Point"}
}