{
  "type": "Feature",
  "properties": {
    "addr:full":"564 Rio Lindo Ave Chico CA 95926",
    "addr:housenumber":"564",
    "addr:postcode":"95926",
    "addr:street":"Rio Lindo Ave",
    "iso:country":"US",
    "sg:address":"564 Rio Lindo Ave",
    "sg:city":"Chico",
    "sg:classifiers":[
        {
            "category":"Social Services",
            "subcategory":"Job Training",
            "type":"Services"
        }
    ],
    "sg:phone":"+1 530 898 8326",
    "sg:postcode":"95926",
    "sg:province":"CA",
    "sg:tags":[
        "rehabilitation"
    ],
    "sg:website":"www.skywayhouse.org",
    "wof:name":"Skyway House Outpatient Svc",
    "wof:placetype":"venue"
},
  "geometry": {"coordinates":[-121.84745100000001,39.75337],"type":"Point"}
}