{
  "type": "Feature",
  "properties": {
    "addr:full":"701 N Euclid St La Habra CA 90631",
    "addr:housenumber":"701",
    "addr:postcode":"90631",
    "addr:street":"N Euclid St",
    "iso:country":"US",
    "sg:address":"701 N Euclid St",
    "sg:city":"La Habra",
    "sg:classifiers":[
        {
            "category":"Building & Trades",
            "subcategory":"Electrical",
            "type":"Services"
        }
    ],
    "sg:phone":"+1 562 905 3576",
    "sg:postcode":"90631",
    "sg:province":"CA",
    "sg:tags":[
        "electric",
        "contractor"
    ],
    "wof:name":"Golden State Electric",
    "wof:placetype":"venue"
},
  "geometry": {"coordinates":[-117.946161,33.938586],"type":"Point"}
}