{
  "type": "Feature",
  "properties": {
    "iso:country":"US",
    "sg:address":"9300 Valley Children's Pl",
    "sg:city":"Madera",
    "sg:classifiers":[
        {
            "category":"Health Services",
            "subcategory":"Doctor",
            "type":"Services"
        }
    ],
    "sg:phone":"+1 559 353 6425",
    "sg:postcode":"93638",
    "sg:province":"CA",
    "sg:tags":[
        "physician",
        "surgeon",
        "medical"
    ],
    "wof:name":"Charlie Mitchell Chld Clinic",
    "wof:placetype":"venue"
},
  "geometry": {"coordinates":[-119.806483,36.8837],"type":"Point"}
}