{
  "type": "Feature",
  "properties": {
    "iso:country":"US",
    "sg:address":"10675 Bryant St",
    "sg:city":"Yucaipa",
    "sg:classifiers":[
        {
            "category":"Real Estate",
            "subcategory":"Real Estate Operator",
            "type":"Services"
        }
    ],
    "sg:phone":"+1 909 797 5077",
    "sg:postcode":"92399",
    "sg:province":"CA",
    "sg:tags":[
        "mobile",
        "home",
        "community"
    ],
    "wof:name":"Northview Mobile Home Park",
    "wof:placetype":"venue"
},
  "geometry": {"coordinates":[-117.03437099999999,34.058375],"type":"Point"}
}