{
  "type": "Feature",
  "properties": {
    "iso:country":"US",
    "sg:address":"1003 W 6th St",
    "sg:city":"Corona",
    "sg:classifiers":[
        {
            "category":"Shopping",
            "subcategory":"Music",
            "type":"Retail Goods"
        }
    ],
    "sg:phone":"+1 951 737 1546",
    "sg:postcode":"92882",
    "sg:province":"CA",
    "sg:tags":[
        "video",
        "disc",
        "tape",
        "cassette"
    ],
    "wof:name":"Central Video",
    "wof:placetype":"venue"
},
  "geometry": {"coordinates":[-117.583217,33.877238],"type":"Point"}
}