{
  "type": "Feature",
  "properties": {
    "iso:country":"US",
    "sg:address":"16921 S Western Ave",
    "sg:city":"Gardena",
    "sg:classifiers":[
        {
            "category":"Health Services",
            "subcategory":"Medical Lab",
            "type":"Services"
        }
    ],
    "sg:phone":"+1 310 354 5968",
    "sg:postcode":"90247",
    "sg:province":"CA",
    "sg:tags":[
        "x",
        "laboratory"
    ],
    "wof:name":"Fairfax Group",
    "wof:placetype":"venue"
},
  "geometry": {"coordinates":[-118.309199,33.877602],"type":"Point"}
}