{
  "type": "Feature",
  "properties": {
    "addr:full":"939 S Broadway Los Angeles CA 90015",
    "addr:housenumber":"939",
    "addr:postcode":"90015",
    "addr:street":"S Broadway",
    "iso:country":"US",
    "sg:address":"939 S Broadway",
    "sg:city":"Los Angeles",
    "sg:classifiers":[
        {
            "category":"Professional",
            "type":"Services"
        }
    ],
    "sg:phone":"+1 213 683 1609",
    "sg:postcode":"90015",
    "sg:province":"CA",
    "wof:name":"Regency Line",
    "wof:placetype":"venue"
},
  "geometry": {"coordinates":[-118.25703,34.0415],"type":"Point"}
}