{
  "type": "Feature",
  "properties": {
    "addr:full":"13752 Foothill Blvd Sylmar CA 91342",
    "addr:housenumber":"13752",
    "addr:postcode":"91342",
    "addr:street":"Foothill Blvd",
    "iso:country":"US",
    "sg:address":"13752 Foothill Blvd",
    "sg:city":"Sylmar",
    "sg:classifiers":[
        {
            "category":"Retail",
            "subcategory":"Repair Shop",
            "type":"Services"
        }
    ],
    "sg:phone":"+1 818 833 7401",
    "sg:postcode":"91342",
    "sg:province":"CA",
    "sg:tags":[
        "picture",
        "framing"
    ],
    "wof:name":"Gonzalez Gallery",
    "wof:placetype":"venue"
},
  "geometry": {"coordinates":[-118.431731,34.308126],"type":"Point"}
}