{
  "type": "Feature",
  "properties": {
    "iso:country":"US",
    "sg:address":"588 1st St W",
    "sg:city":"Sonoma",
    "sg:classifiers":[
        {
            "category":"Personal",
            "subcategory":"Beauty Salon",
            "type":"Services"
        }
    ],
    "sg:phone":"+1 707 938 2405",
    "sg:postcode":"95476",
    "sg:province":"CA",
    "wof:name":"Strands Salon",
    "wof:placetype":"venue"
},
  "geometry": {"coordinates":[-122.459047,38.291054],"type":"Point"}
}