{
  "type": "Feature",
  "properties": {
    "addr:full":"500 Lander Ave Turlock CA 95380",
    "addr:housenumber":"500",
    "addr:postcode":"95380",
    "addr:street":"Lander Ave",
    "iso:country":"US",
    "sg:address":"500 Lander Ave",
    "sg:city":"Turlock",
    "sg:classifiers":[
        {
            "category":"Insurance",
            "subcategory":"Insurance Agent",
            "type":"Services"
        }
    ],
    "sg:phone":"+1 209 383 2002",
    "sg:postcode":"95380",
    "sg:province":"CA",
    "wof:name":"Central Valley Insurance Svc",
    "wof:placetype":"venue"
},
  "geometry": {"coordinates":[-120.848911,37.488149],"type":"Point"}
}