{
  "type": "Feature",
  "properties": {
    "addr:full":"4724 Renex Pl San Diego CA 92117",
    "addr:housenumber":"4724",
    "addr:postcode":"92117",
    "addr:street":"Renex Pl",
    "iso:country":"US",
    "sg:address":"4724 Renex Pl",
    "sg:city":"San Diego",
    "sg:classifiers":[
        {
            "category":"Manufacturing",
            "subcategory":"Watercraft",
            "type":"Manufacturing & Wholesale Goods"
        }
    ],
    "sg:phone":"+1 858 569 1395",
    "sg:postcode":"92117",
    "sg:province":"CA",
    "sg:tags":[
        "surf",
        "ski",
        "boat",
        "mfg"
    ],
    "wof:name":"Valhalla Surf Ski Products",
    "wof:placetype":"venue"
},
  "geometry": {"coordinates":[-117.18509299999999,32.831704],"type":"Point"}
}