{
  "type": "Feature",
  "properties": {
    "addr:full":"342 San Luis Ave Watsonville CA 95076",
    "addr:housenumber":"342",
    "addr:postcode":"95076",
    "addr:street":"San Luis Ave",
    "iso:country":"US",
    "sg:address":"342 San Luis Ave",
    "sg:city":"Watsonville",
    "sg:classifiers":[
        {
            "category":"Real Estate",
            "subcategory":"Real Estate Agent",
            "type":"Services"
        }
    ],
    "sg:phone":"+1 831 786 3900",
    "sg:postcode":"95076",
    "sg:province":"CA",
    "wof:name":"Royalty Real Estate",
    "wof:placetype":"venue"
},
  "geometry": {"coordinates":[-121.77283799999999,36.907445],"type":"Point"}
}