{
  "type": "Feature",
  "properties": {
    "iso:country":"US",
    "sg:address":"832 Abbie St",
    "sg:city":"Pleasanton",
    "sg:classifiers":[
        {
            "category":"Education",
            "subcategory":"Special Training",
            "type":"Public Place"
        }
    ],
    "sg:phone":"+1 925 846 4445",
    "sg:postcode":"94566",
    "sg:province":"CA",
    "sg:tags":[
        "educational"
    ],
    "wof:name":"A P Educational Svc",
    "wof:placetype":"venue"
},
  "geometry": {"coordinates":[-121.864999,37.653051],"type":"Point"}
}