{
  "type": "Feature",
  "properties": {
    "addr:full":"1839 Rotary Dr Los Angeles CA 90026",
    "addr:housenumber":"1839",
    "addr:postcode":"90026",
    "addr:street":"Rotary Dr",
    "iso:country":"US",
    "sg:address":"1839 Rotary Dr",
    "sg:city":"Los Angeles",
    "sg:classifiers":[
        {
            "category":"Retail",
            "subcategory":"Animal Services",
            "type":"Services"
        }
    ],
    "sg:phone":"+1 323 660 2162",
    "sg:postcode":"90026",
    "sg:province":"CA",
    "sg:tags":[
        "training",
        "dog"
    ],
    "wof:name":"Academy of Dog Obedience",
    "wof:placetype":"venue"
},
  "geometry": {"coordinates":[-118.270087,34.091065],"type":"Point"}
}