{
  "type": "Feature",
  "properties": {
    "addr:full":"9910 Mission Gorge Rd Santee CA 92071",
    "addr:housenumber":"9910",
    "addr:postcode":"92071",
    "addr:street":"Mission Gorge Rd",
    "iso:country":"US",
    "sg:address":"9910 Mission Gorge Rd",
    "sg:city":"Santee",
    "sg:classifiers":[
        {
            "category":"Manufacturing",
            "subcategory":"Printing",
            "type":"Manufacturing & Wholesale Goods"
        }
    ],
    "sg:phone":"+1 619 258 7575",
    "sg:postcode":"92071",
    "sg:province":"CA",
    "sg:tags":[
        "screen"
    ],
    "wof:name":"Instant Imprints",
    "wof:placetype":"venue"
},
  "geometry": {"coordinates":[-116.97946,32.838668],"type":"Point"}
}