{
  "type": "Feature",
  "properties": {
    "iso:country":"US",
    "sg:address":"871 S Harbor Blvd",
    "sg:city":"Anaheim",
    "sg:classifiers":[
        {
            "category":"Travel",
            "subcategory":"Hotels & Motels",
            "type":"Entertainment"
        }
    ],
    "sg:phone":"+1 714 535 7878",
    "sg:postcode":"92805",
    "sg:province":"CA",
    "sg:website":"www.econolodge.com",
    "wof:name":"Econo Lodge",
    "wof:placetype":"venue"
},
  "geometry": {"coordinates":[-117.916,33.8228],"type":"Point"}
}