{
  "type": "Feature",
  "properties": {
    "iso:country":"US",
    "sg:address":"1025 Crestview Dr",
    "sg:city":"Fullerton",
    "sg:classifiers":[
        {
            "category":"Building & Trades",
            "subcategory":"Pest Control",
            "type":"Services"
        }
    ],
    "sg:phone":"+1 714 773 5889",
    "sg:postcode":"92833",
    "sg:province":"CA",
    "wof:name":"Colby Pest Control Service",
    "wof:placetype":"venue"
},
  "geometry": {"coordinates":[-117.947998,33.883301],"type":"Point"}
}