{
  "type": "Feature",
  "properties": {
    "addr:full":"5184 Sonoma Blvd Vallejo CA 94589",
    "addr:housenumber":"5184",
    "addr:postcode":"94589",
    "addr:street":"Sonoma Blvd",
    "iso:country":"US",
    "sg:address":"5184 Sonoma Blvd",
    "sg:city":"Vallejo",
    "sg:classifiers":[
        {
            "category":"Food & Beverages",
            "subcategory":"Groceries & Convenience Stores",
            "type":"Retail Goods"
        }
    ],
    "sg:phone":"+1 707 552 0956",
    "sg:postcode":"94589",
    "sg:province":"CA",
    "wof:name":"Food 4 Less",
    "wof:placetype":"venue"
},
  "geometry": {"coordinates":[-122.254339,38.148465],"type":"Point"}
}