{
  "type": "Feature",
  "properties": {
    "iso:country":"US",
    "sg:address":"6072 Riverside Blvd",
    "sg:city":"Sacramento",
    "sg:classifiers":[
        {
            "category":"Wholesale",
            "subcategory":"Apparel",
            "type":"Manufacturing & Wholesale Goods"
        }
    ],
    "sg:phone":"+1 916 204 2712",
    "sg:postcode":"95831",
    "sg:province":"CA",
    "sg:tags":[
        "clothing"
    ],
    "wof:name":"Above Typical",
    "wof:placetype":"venue"
},
  "geometry": {"coordinates":[-121.526539,38.515128],"type":"Point"}
}