{
  "type": "Feature",
  "properties": {
    "addr:full":"9041 Central Ave Montclair CA 91763",
    "addr:postcode":"9041;91763",
    "addr:street":"Central Ave",
    "iso:country":"US",
    "sg:address":"9041 Central Ave",
    "sg:city":"Montclair",
    "sg:classifiers":[
        {
            "category":"Shopping",
            "subcategory":"Books",
            "type":"Retail Goods"
        }
    ],
    "sg:phone":"+1 909 621 5553",
    "sg:postcode":"91763",
    "sg:province":"CA",
    "sg:tags":[
        "dealer"
    ],
    "sg:website":"www.bn.com",
    "wof:name":"Barnes & Noble Booksellers",
    "wof:placetype":"venue"
},
  "geometry": {"coordinates":[-117.689544,34.090361],"type":"Point"}
}