{
  "type": "Feature",
  "properties": {
    "iso:country":"US",
    "sg:address":"520 E de la Guerra St",
    "sg:city":"Santa Barbara",
    "sg:classifiers":[
        {
            "category":"Building & Trades",
            "subcategory":"Plumbing",
            "type":"Services"
        }
    ],
    "sg:phone":"+1 805 963 8284",
    "sg:postcode":"93103",
    "sg:province":"CA",
    "sg:tags":[
        "ventilating",
        "contractor"
    ],
    "wof:name":"C & L Heating & Air",
    "wof:placetype":"venue"
},
  "geometry": {"coordinates":[-119.692672,34.425681],"type":"Point"}
}