{
  "type": "Feature",
  "properties": {
    "iso:country":"US",
    "sg:address":"1312 E Ontario Ave",
    "sg:city":"Corona",
    "sg:classifiers":[
        {
            "category":"Restaurant",
            "type":"Food & Drink"
        }
    ],
    "sg:phone":"+1 951 738 8888",
    "sg:postcode":"92881",
    "sg:province":"CA",
    "wof:name":"Golden Chopstix",
    "wof:placetype":"venue"
},
  "geometry": {"coordinates":[-117.539507,33.846571],"type":"Point"}
}