{
  "type": "Feature",
  "properties": {
    "iso:country":"US",
    "sg:address":"1020 Colorado Ave",
    "sg:city":"Chula Vista",
    "sg:classifiers":[
        {
            "category":"Building & Trades",
            "subcategory":"Plumbing",
            "type":"Services"
        }
    ],
    "sg:phone":"+1 619 409 9100",
    "sg:postcode":"91911",
    "sg:province":"CA",
    "sg:tags":[
        "conditioning",
        "air",
        "system",
        "contractor"
    ],
    "wof:name":"Able Heating & AC",
    "wof:placetype":"venue"
},
  "geometry": {"coordinates":[-117.087604,32.611199],"type":"Point"}
}