{
  "type": "Feature",
  "properties": {
    "iso:country":"US",
    "sg:address":"3731 Wilshire Blvd. #106",
    "sg:city":"Los Angeles",
    "sg:classifiers":[
        {
            "category":"Restaurant",
            "type":"Food & Drink"
        }
    ],
    "sg:phone":"+1 213 383 1477",
    "sg:postcode":"90010",
    "sg:province":"CA",
    "wof:name":"Colonnade Cafe",
    "wof:placetype":"venue"
},
  "geometry": {"coordinates":[-118.307543,34.062383],"type":"Point"}
}