{
  "type": "Feature",
  "properties": {
    "addr:full":"5030 Soquel Dr Soquel CA 95073",
    "addr:housenumber":"5030",
    "addr:postcode":"95073",
    "addr:street":"Soquel Dr",
    "iso:country":"US",
    "sg:address":"5030 Soquel Dr",
    "sg:city":"Soquel",
    "sg:classifiers":[
        {
            "category":"Social Services",
            "type":"Services"
        }
    ],
    "sg:phone":"+1 530 898 9393",
    "sg:postcode":"95073",
    "sg:province":"CA",
    "sg:tags":[
        "counselor",
        "marriage",
        "family"
    ],
    "wof:name":"Soquel Therapy Ctr",
    "wof:placetype":"venue"
},
  "geometry": {"coordinates":[-121.953058,36.988009],"type":"Point"}
}