{
  "type": "Feature",
  "properties": {
    "iso:country":"US",
    "sg:address":"737 3rd Ave",
    "sg:city":"Chula Vista",
    "sg:classifiers":[
        {
            "category":"Real Estate",
            "subcategory":"Real Estate Agent",
            "type":"Services"
        }
    ],
    "sg:phone":"+1 619 691 8200",
    "sg:postcode":"91910",
    "sg:province":"CA",
    "wof:name":"Liberty Properties",
    "wof:placetype":"venue"
},
  "geometry": {"coordinates":[-117.074207,32.627089],"type":"Point"}
}