{
  "type": "Feature",
  "properties": {
    "iso:country":"US",
    "sg:address":"14889 W California Ave",
    "sg:city":"Kerman",
    "sg:classifiers":[
        {
            "category":"Retail",
            "subcategory":"Auto Repair",
            "type":"Services"
        }
    ],
    "sg:phone":"+1 559 846 9656",
    "sg:postcode":"93630",
    "sg:province":"CA",
    "sg:tags":[
        "body",
        "automobile",
        "painting"
    ],
    "wof:name":"Ramirez Custom Auto Body",
    "wof:placetype":"venue"
},
  "geometry": {"coordinates":[-120.05792099999999,36.720519],"type":"Point"}
}