{
  "type": "Feature",
  "properties": {
    "addr:full":"9803 Adams Ave Huntington Beach CA 92646",
    "addr:housenumber":"9803",
    "addr:postcode":"92646",
    "addr:street":"Adams Ave",
    "iso:country":"US",
    "sg:address":"9803 Adams Ave",
    "sg:city":"Huntington Beach",
    "sg:classifiers":[
        {
            "category":"Utilities",
            "subcategory":"Mobile Phone",
            "type":"Services"
        }
    ],
    "sg:phone":"+1 714 414 8865",
    "sg:postcode":"92646",
    "sg:province":"CA",
    "sg:tags":[
        "communication",
        "radiotelephone"
    ],
    "wof:name":"ABC Wireless",
    "wof:placetype":"venue"
},
  "geometry": {"coordinates":[-117.95460300000001,33.672386],"type":"Point"}
}