{
  "type": "Feature",
  "properties": {
    "iso:country":"US",
    "sg:address":"21250 Hawthorne Blvd",
    "sg:city":"Torrance",
    "sg:classifiers":[
        {
            "category":"Food & Beverages",
            "subcategory":"Meat & Fish",
            "type":"Retail Goods"
        }
    ],
    "sg:phone":"+1 310 792 7050",
    "sg:postcode":"90503",
    "sg:province":"CA",
    "sg:tags":[
        "seafood-wholesale"
    ],
    "sg:website":"http://www.hamilton-standard.com",
    "wof:name":"Kingston Foods Corporation",
    "wof:placetype":"venue"
},
  "geometry": {"coordinates":[-118.35332,33.836367],"type":"Point"}
}