{
  "type": "Feature",
  "properties": {
    "addr:full":"309 W Colombero Dr Mccloud CA 96057",
    "addr:housenumber":"309",
    "addr:postcode":"96057",
    "addr:street":"W Colombero Dr",
    "iso:country":"US",
    "sg:address":"309 W Colombero Dr",
    "sg:city":"Mccloud",
    "sg:classifiers":[
        {
            "category":"Travel",
            "subcategory":"Hotels & Motels",
            "type":"Entertainment"
        }
    ],
    "sg:phone":"+1 530 964 2300",
    "sg:postcode":"96057",
    "sg:province":"CA",
    "sg:tags":[
        "breakfast",
        "accommodation",
        "bed"
    ],
    "sg:website":"www.stoneybrookinn.com",
    "wof:name":"Stoney Brook Inn B & B",
    "wof:placetype":"venue"
},
  "geometry": {"coordinates":[-122.139048,41.256024],"type":"Point"}
}