{
  "type": "Feature",
  "properties": {
    "addr:full":"3313 Brookwood Rd Sacramento CA 95821",
    "addr:housenumber":"3313",
    "addr:postcode":"95821",
    "addr:street":"Brookwood Rd",
    "iso:country":"US",
    "sg:address":"3313 Brookwood Rd",
    "sg:city":"Sacramento",
    "sg:classifiers":[
        {
            "category":"Shopping",
            "subcategory":"Pets & Pet Supplies",
            "type":"Retail Goods"
        }
    ],
    "sg:phone":"+1 916 486 9086",
    "sg:postcode":"95821",
    "sg:province":"CA",
    "sg:tags":[
        "furnishing",
        "dog",
        "store",
        "cat"
    ],
    "wof:name":"Poopsies Waste Removal Service",
    "wof:placetype":"venue"
},
  "geometry": {"coordinates":[-121.374635,38.627132],"type":"Point"}
}