{
  "type": "Feature",
  "properties": {
    "addr:full":"16900 Burbank Blvd Encino CA 91316",
    "addr:housenumber":"16900",
    "addr:postcode":"91316",
    "addr:street":"Burbank Blvd",
    "iso:country":"US",
    "sg:address":"16900 Burbank Blvd",
    "sg:city":"Encino",
    "sg:phone":"+1 310 558 8190",
    "sg:postcode":"91316",
    "sg:province":"CA",
    "wof:name":"Contemporary Catering",
    "wof:placetype":"venue"
},
  "geometry": {"coordinates":[-118.50166299999999,34.172218],"type":"Point"}
}