{
  "type": "Feature",
  "properties": {
    "addr:full":"9021 Norris Ave Sun Valley CA 91352",
    "addr:housenumber":"9021",
    "addr:postcode":"91352",
    "addr:street":"Norris Ave",
    "iso:country":"US",
    "sg:address":"9021 Norris Ave",
    "sg:city":"Sun Valley",
    "sg:classifiers":[
        {
            "category":"Manufacturing",
            "subcategory":"Tools & Machinery",
            "type":"Manufacturing & Wholesale Goods"
        }
    ],
    "sg:phone":"+1 818 767 7223",
    "sg:postcode":"91352",
    "sg:province":"CA",
    "sg:tags":[
        "equipment",
        "refrigeration"
    ],
    "wof:name":"Refrigeration Hardware Supply",
    "wof:placetype":"venue"
},
  "geometry": {"coordinates":[-118.37814400000001,34.234233],"type":"Point"}
}