{
  "type": "Feature",
  "properties": {
    "addr:full":"18150 Rd 112 Tulare CA 93274",
    "addr:housenumber":"18150",
    "addr:postcode":"93274",
    "addr:street":"Rd 112",
    "iso:country":"US",
    "sg:address":"18150 Rd 112",
    "sg:city":"Tulare",
    "sg:classifiers":[
        {
            "category":"Farming",
            "subcategory":"Dairy Farm",
            "type":"Manufacturing & Wholesale Goods"
        }
    ],
    "sg:phone":"+1 559 688 6363",
    "sg:postcode":"93274",
    "sg:province":"CA",
    "wof:name":"Felipe C Ribeiro & Sons",
    "wof:placetype":"venue"
},
  "geometry": {"coordinates":[-119.321788,36.123491],"type":"Point"}
}