{
  "type": "Feature",
  "properties": {
    "addr:full":"4808 W 1st St Santa Ana CA 92703",
    "addr:housenumber":"4808",
    "addr:postcode":"92703",
    "addr:street":"W 1St St",
    "iso:country":"US",
    "sg:address":"4808 W 1st St",
    "sg:city":"Santa Ana",
    "sg:classifiers":[
        {
            "category":"Banks & Credit Unions",
            "subcategory":"Atm",
            "type":"Services"
        }
    ],
    "sg:phone":"+1 714 418 0260",
    "sg:postcode":"92703",
    "sg:province":"CA",
    "sg:tags":[
        "bankruptcy"
    ],
    "sg:website":"www.rjseo.com",
    "wof:name":"SEO RAYMOND J ATTORNEY AT LAW",
    "wof:placetype":"venue"
},
  "geometry": {"coordinates":[-117.932682,33.744942],"type":"Point"}
}