{
  "type": "Feature",
  "properties": {
    "addr:full":"1799 A St Fresno CA 93706",
    "addr:housenumber":"1799",
    "addr:postcode":"93706",
    "addr:street":"A St",
    "iso:country":"US",
    "sg:address":"1799 A St",
    "sg:city":"Fresno",
    "sg:classifiers":[
        {
            "category":"Restaurant",
            "type":"Food & Drink"
        }
    ],
    "sg:menulink":"http://www.allmenus.com/ca/fresno/59911-subway/menu/",
    "sg:phone":"+1 559 266 7827",
    "sg:postcode":"93706",
    "sg:province":"CA",
    "sg:tags":[
        "american",
        "sandwich"
    ],
    "wof:name":"Subway",
    "wof:placetype":"venue"
},
  "geometry": {"coordinates":[-119.808314,36.734354],"type":"Point"}
}