{
  "type": "Feature",
  "properties": {
    "addr:full":"1931 23rd St San Francisco CA 94107",
    "addr:housenumber":"1931",
    "addr:postcode":"94107",
    "addr:street":"23Rd St",
    "iso:country":"US",
    "sg:address":"1931 23rd St",
    "sg:city":"San Francisco",
    "sg:classifiers":[
        {
            "category":"Professional",
            "subcategory":"Art Services",
            "type":"Services"
        }
    ],
    "sg:phone":"+1 415 775 8944",
    "sg:postcode":"94107",
    "sg:province":"CA",
    "sg:tags":[
        "photographer"
    ],
    "sg:website":"www.elisaphoto.com/",
    "wof:name":"Elisa Cicinelli Photography",
    "wof:placetype":"venue"
},
  "geometry": {"coordinates":[-122.39929100000001,37.754481],"type":"Point"}
}