{
  "type": "Feature",
  "properties": {
    "addr:full":"838 W Dana St Mountain View CA 94041",
    "addr:housenumber":"838",
    "addr:postcode":"94041",
    "addr:street":"W Dana St",
    "iso:country":"US",
    "sg:address":"838 W Dana St",
    "sg:city":"Mountain View",
    "sg:classifiers":[
        {
            "category":"Professional",
            "subcategory":"Accounting & Tax Preparation",
            "type":"Services"
        }
    ],
    "sg:phone":"+1 650 964 2488",
    "sg:postcode":"94041",
    "sg:province":"CA",
    "sg:tags":[
        "return",
        "filing"
    ],
    "wof:name":"Flores Accounting Svc",
    "wof:placetype":"venue"
},
  "geometry": {"coordinates":[-122.079859,37.392677],"type":"Point"}
}