{
  "type": "Feature",
  "properties": {
    "iso:country":"US",
    "sg:address":"1675 Hilltop Dr",
    "sg:city":"Redding",
    "sg:classifiers":[
        {
            "category":"Restaurant",
            "type":"Food & Drink"
        }
    ],
    "sg:phone":"+1 530 222 8188",
    "sg:postcode":"96002",
    "sg:province":"CA",
    "sg:tags":[
        "asian",
        "chinese",
        "pan"
    ],
    "wof:name":"Express China Restaurant",
    "wof:placetype":"venue"
},
  "geometry": {"coordinates":[-122.357775,40.581964],"type":"Point"}
}