{
  "type": "Feature",
  "properties": {
    "iso:country":"US",
    "sg:address":"2025 W March Ln",
    "sg:city":"Stockton",
    "sg:classifiers":[
        {
            "category":"Wholesale",
            "subcategory":"Electrical",
            "type":"Manufacturing & Wholesale Goods"
        }
    ],
    "sg:phone":"+1 510 476 1700",
    "sg:postcode":"95207",
    "sg:province":"CA",
    "sg:tags":[
        "refrigerator",
        "freezer"
    ],
    "wof:name":"Cold Storage Mfg",
    "wof:placetype":"venue"
},
  "geometry": {"coordinates":[-121.33377299999999,37.986202],"type":"Point"}
}