{
  "type": "Feature",
  "properties": {
    "addr:full":"912 S Barrington Ave Los Angeles CA 90049",
    "addr:housenumber":"912",
    "addr:postcode":"90049",
    "addr:street":"S Barrington Ave",
    "iso:country":"US",
    "sg:address":"912 S Barrington Ave",
    "sg:city":"Los Angeles",
    "sg:classifiers":[
        {
            "category":"Food & Beverages",
            "subcategory":"Candy",
            "type":"Retail Goods"
        }
    ],
    "sg:phone":"+1 310 826 3380",
    "sg:postcode":"90049",
    "sg:province":"CA",
    "sg:tags":[
        "confectionery"
    ],
    "sg:website":"www.compartes.com",
    "wof:name":"Comparte's Of Ca Chocolate",
    "wof:placetype":"venue"
},
  "geometry": {"coordinates":[-118.46527500000001,34.053481],"type":"Point"}
}