{
  "type": "Feature",
  "properties": {
    "addr:full":"2035 Starfish Ct San Jose CA 95148",
    "addr:housenumber":"2035",
    "addr:postcode":"95148",
    "addr:street":"Starfish Ct",
    "iso:country":"US",
    "sg:address":"2035 Starfish Ct",
    "sg:city":"San Jose",
    "sg:classifiers":[
        {
            "category":"Taxi",
            "type":"Transportation"
        }
    ],
    "sg:phone":"+1 408 828 2957",
    "sg:postcode":"95148",
    "sg:province":"CA",
    "sg:tags":[
        "taxicab"
    ],
    "wof:name":"Singh Bara",
    "wof:placetype":"venue"
},
  "geometry": {"coordinates":[-121.80823100000001,37.341067],"type":"Point"}
}