{
  "type": "Feature",
  "properties": {
    "iso:country":"US",
    "sg:address":"387 Magnolia Ave",
    "sg:city":"Corona",
    "sg:classifiers":[
        {
            "category":"Autos & Motor Vehicles",
            "subcategory":"Auto Supplies",
            "type":"Retail Goods"
        }
    ],
    "sg:phone":"+1 951 898 8420",
    "sg:postcode":"92879",
    "sg:province":"CA",
    "sg:tags":[
        "automobile",
        "parts"
    ],
    "wof:name":"Jaguar Central",
    "wof:placetype":"venue"
},
  "geometry": {"coordinates":[-117.56037,33.855638],"type":"Point"}
}