{
  "type": "Feature",
  "properties": {
    "iso:country":"US",
    "sg:address":"305 Cam del Remedio",
    "sg:city":"Santa Barbara",
    "sg:classifiers":[
        {
            "category":"Government",
            "subcategory":"Office",
            "type":"Public Place"
        }
    ],
    "sg:phone":"+1 805 692 1730",
    "sg:postcode":"93110",
    "sg:province":"CA",
    "wof:name":"Santa Barbara County Co-Op Ext",
    "wof:placetype":"venue"
},
  "geometry": {"coordinates":[-119.779445,34.445506],"type":"Point"}
}