{
  "type": "Feature",
  "properties": {
    "iso:country":"US",
    "sg:address":"131 S Kellogg Ave",
    "sg:city":"Goleta",
    "sg:classifiers":[
        {
            "category":"Real Estate",
            "subcategory":"Real Estate Services",
            "type":"Services"
        },
        {
            "category":"Real Estate",
            "subcategory":"Real Estate Operator",
            "type":"Services"
        }
    ],
    "sg:phone":"+1 805 964 0353",
    "sg:postcode":"93117",
    "sg:province":"CA",
    "sg:tags":[
        "vacancy",
        "apartment",
        "rental",
        "listing"
    ],
    "wof:name":"Goleta Valley Housing Committee",
    "wof:placetype":"venue"
},
  "geometry": {"coordinates":[-119.820571,34.436713],"type":"Point"}
}