{
  "type": "Feature",
  "properties": {
    "addr:full":"332 Pile St Ramona CA 92065",
    "addr:housenumber":"332",
    "addr:postcode":"92065",
    "addr:street":"Pile St",
    "iso:country":"US",
    "sg:address":"332 Pile St",
    "sg:city":"Ramona",
    "sg:classifiers":[
        {
            "category":"Building & Trades",
            "subcategory":"Construction",
            "type":"Services"
        }
    ],
    "sg:phone":"+1 760 789 0542",
    "sg:postcode":"92065",
    "sg:province":"CA",
    "sg:tags":[
        "welder"
    ],
    "wof:name":"Browns Custom Welding",
    "wof:placetype":"venue"
},
  "geometry": {"coordinates":[-116.851839,33.069329],"type":"Point"}
}