{
  "type": "Feature",
  "properties": {
    "iso:country":"US",
    "sg:address":"14692 Parthenia St",
    "sg:city":"Panorama City",
    "sg:classifiers":[
        {
            "category":"Personal",
            "subcategory":"Beauty Salon",
            "type":"Services"
        }
    ],
    "sg:phone":"+1 818 891 2383",
    "sg:postcode":"91402",
    "sg:province":"CA",
    "wof:name":"Kim's D-Maculent Hair",
    "wof:placetype":"venue"
},
  "geometry": {"coordinates":[-118.451909,34.227788],"type":"Point"}
}