{
  "type": "Feature",
  "properties": {
    "addr:full":"34920 Summerwood Dr Yucaipa CA 92399",
    "addr:housenumber":"34920",
    "addr:postcode":"92399",
    "addr:street":"Summerwood Dr",
    "iso:country":"US",
    "sg:address":"34920 Summerwood Dr",
    "sg:city":"Yucaipa",
    "sg:classifiers":[
        {
            "category":"Health Services",
            "subcategory":"Nursing And Care Facility",
            "type":"Services"
        }
    ],
    "sg:phone":"+1 909 797 5989",
    "sg:postcode":"92399",
    "sg:province":"CA",
    "sg:tags":[
        "home",
        "rest"
    ],
    "wof:name":"Valley Home I & II",
    "wof:placetype":"venue"
},
  "geometry": {"coordinates":[-117.04267,34.055475],"type":"Point"}
}