{
  "type": "Feature",
  "properties": {
    "addr:full":"1950 E 25th St Vernon CA 90058",
    "addr:housenumber":"1950",
    "addr:postcode":"90058",
    "addr:street":"E 25Th St",
    "iso:country":"US",
    "sg:address":"1950 E 25th St",
    "sg:city":"Vernon",
    "sg:classifiers":[
        {
            "category":"Wholesale",
            "subcategory":"Durable Goods & Equipment",
            "type":"Manufacturing & Wholesale Goods"
        }
    ],
    "sg:phone":"+1 323 232 8688",
    "sg:postcode":"90058",
    "sg:province":"CA",
    "sg:tags":[
        "importer"
    ],
    "wof:name":"Jiao Guang Intl Trading Inc",
    "wof:placetype":"venue"
},
  "geometry": {"coordinates":[-118.234123,34.014702],"type":"Point"}
}