{
  "type": "Feature",
  "properties": {
    "iso:country":"US",
    "sg:address":"2389 E Colorado Blvd",
    "sg:city":"Pasadena",
    "sg:classifiers":[
        {
            "category":"Retail",
            "subcategory":"Laundry & Dry Cleaning",
            "type":"Services"
        }
    ],
    "sg:phone":"+1 626 356 0034",
    "sg:postcode":"91107",
    "sg:province":"CA",
    "wof:name":"Pansy Cleaners",
    "wof:placetype":"venue"
},
  "geometry": {"coordinates":[-118.100998,34.146198],"type":"Point"}
}