{
  "type": "Feature",
  "properties": {
    "iso:country":"US",
    "sg:address":"2951 28th St",
    "sg:city":"Santa Monica",
    "sg:classifiers":[
        {
            "category":"Professional",
            "subcategory":"Research",
            "type":"Services"
        }
    ],
    "sg:phone":"+1 310 392 7337",
    "sg:postcode":"90405",
    "sg:province":"CA",
    "sg:tags":[
        "market",
        "analysis"
    ],
    "sg:website":"www.murrayhillcenter.com",
    "wof:name":"Murray Hill Ctr West",
    "wof:placetype":"venue"
},
  "geometry": {"coordinates":[-118.453762,34.016857],"type":"Point"}
}