{
  "type": "Feature",
  "properties": {
    "iso:country":"US",
    "sg:address":"210 Estates Dr",
    "sg:city":"Roseville",
    "sg:classifiers":[
        {
            "category":"Banks & Credit Unions",
            "subcategory":"Financial Services",
            "type":"Services"
        }
    ],
    "sg:phone":"+1 916 781 2856",
    "sg:postcode":"95678",
    "sg:province":"CA",
    "sg:tags":[
        "franchising"
    ],
    "wof:name":"Franchise Management Corp",
    "wof:placetype":"venue"
},
  "geometry": {"coordinates":[-121.272108,38.747058],"type":"Point"}
}