{
  "type": "Feature",
  "properties": {
    "addr:full":"3976 Goldfinch St San Diego CA 92103",
    "addr:housenumber":"3976",
    "addr:postcode":"92103",
    "addr:street":"Goldfinch St",
    "iso:country":"US",
    "sg:address":"3976 Goldfinch St",
    "sg:city":"San Diego",
    "sg:classifiers":[
        {
            "category":"Personal",
            "subcategory":"Massage",
            "type":"Services"
        }
    ],
    "sg:phone":"+1 619 296 9888",
    "sg:postcode":"92103",
    "sg:province":"CA",
    "wof:name":"San Diego Shiatzu Ctr",
    "wof:placetype":"venue"
},
  "geometry": {"coordinates":[-117.171452,32.749354],"type":"Point"}
}