{
  "type": "Feature",
  "properties": {
    "addr:full":"10101 Slater Ave Fountain Valley CA 92708",
    "addr:housenumber":"10101",
    "addr:postcode":"92708",
    "addr:street":"Slater Ave",
    "iso:country":"US",
    "sg:address":"10101 Slater Ave",
    "sg:city":"Fountain Valley",
    "sg:classifiers":[
        {
            "category":"Professional",
            "subcategory":"Accounting & Tax Preparation",
            "type":"Services"
        }
    ],
    "sg:phone":"+1 714 378 9123",
    "sg:postcode":"92708",
    "sg:province":"CA",
    "sg:tags":[
        "accountant"
    ],
    "wof:name":"Vastar Sales Group",
    "wof:placetype":"venue"
},
  "geometry": {"coordinates":[-117.952003,33.709099],"type":"Point"}
}