{
  "type": "Feature",
  "properties": {
    "addr:full":"1357 W Shaw Ave Fresno CA 93711",
    "addr:housenumber":"1357",
    "addr:postcode":"93711",
    "addr:street":"W Shaw Ave",
    "iso:country":"US",
    "sg:address":"1357 W Shaw Ave",
    "sg:city":"Fresno",
    "sg:phone":"+1 559 226 3400",
    "sg:postcode":"93711",
    "sg:province":"CA",
    "wof:name":"Tsutsui, Larry M, Dc - Chiropractic Orthopedic Group",
    "wof:placetype":"venue"
},
  "geometry": {"coordinates":[-119.816464,36.808264],"type":"Point"}
}