{
  "type": "Feature",
  "properties": {
    "addr:full":"4134 175th St Torrance CA 90504",
    "addr:housenumber":"4134",
    "addr:postcode":"90504",
    "addr:street":"175Th St",
    "iso:country":"US",
    "sg:address":"4134 175th St",
    "sg:city":"Torrance",
    "sg:classifiers":[
        {
            "category":"Banks & Credit Unions",
            "subcategory":"Bank",
            "type":"Services"
        }
    ],
    "sg:phone":"+1 213 240 6159",
    "sg:postcode":"90504",
    "sg:province":"CA",
    "sg:tags":[
        "national",
        "commercial"
    ],
    "wof:name":"Bank of America",
    "wof:placetype":"venue"
},
  "geometry": {"coordinates":[-118.34493500000001,33.871963],"type":"Point"}
}