{
  "type": "Feature",
  "properties": {
    "iso:country":"US",
    "sg:address":"42127 50th St W",
    "sg:city":"Lancaster",
    "sg:classifiers":[
        {
            "category":"Shopping",
            "subcategory":"Used Merchandise",
            "type":"Retail Goods"
        }
    ],
    "sg:phone":"+1 661 722 0980",
    "sg:postcode":"93536",
    "sg:province":"CA",
    "sg:tags":[
        "antique"
    ],
    "wof:name":"Vintage Dreams",
    "wof:placetype":"venue"
},
  "geometry": {"coordinates":[-118.218551,34.648052],"type":"Point"}
}