{
  "type": "Feature",
  "properties": {
    "addr:full":"505 Porter St Glendale CA 91205",
    "addr:housenumber":"505",
    "addr:postcode":"91205",
    "addr:street":"Porter St",
    "iso:country":"US",
    "sg:address":"505 Porter St",
    "sg:city":"Glendale",
    "sg:classifiers":[
        {
            "category":"Professional",
            "type":"Services"
        }
    ],
    "sg:phone":"+1 818 662 9399",
    "sg:postcode":"91205",
    "sg:province":"CA",
    "sg:tags":[
        "caterer"
    ],
    "wof:name":"Ez Cater Inc",
    "wof:placetype":"venue"
},
  "geometry": {"coordinates":[-118.23699999999999,34.140598],"type":"Point"}
}