{
  "type": "Feature",
  "properties": {
    "iso:country":"US",
    "sg:address":"5951 Jetton Rd",
    "sg:city":"Loomis",
    "sg:classifiers":[
        {
            "category":"Manufacturing",
            "subcategory":"Printing",
            "type":"Manufacturing & Wholesale Goods"
        }
    ],
    "sg:phone":"+1 916 652 8171",
    "sg:postcode":"95650",
    "sg:province":"CA",
    "sg:tags":[
        "printer",
        "business",
        "form"
    ],
    "wof:name":"Trade Winds Printing",
    "wof:placetype":"venue"
},
  "geometry": {"coordinates":[-121.192372,38.832815],"type":"Point"}
}