{
  "type": "Feature",
  "properties": {
    "addr:full":"325 S 1st Street San Jose CA 95113",
    "addr:housenumber":"325",
    "addr:postcode":"95113",
    "addr:street":"S 1St Street",
    "iso:country":"US",
    "sg:address":"325 S 1st Street",
    "sg:city":"San Jose",
    "sg:classifiers":[
        {
            "category":"Real Estate",
            "subcategory":"Architect",
            "type":"Services"
        }
    ],
    "sg:phone":"+1 408 298 0611",
    "sg:postcode":"95113",
    "sg:province":"CA",
    "wof:name":"Aia Santa Clara Valley",
    "wof:placetype":"venue"
},
  "geometry": {"coordinates":[-121.88681,37.331144],"type":"Point"}
}