{
  "type": "Feature",
  "properties": {
    "addr:full":"250 S Beverly Drive Suite 201 Beverly Hills CA 90212",
    "addr:housenumber":"250",
    "addr:postcode":"90212",
    "addr:street":"S Beverly Drive Suite 201;Hills Ca",
    "iso:country":"US",
    "sg:address":"250 S Beverly Drive Suite 201",
    "sg:city":"Beverly Hills",
    "sg:classifiers":[
        {
            "category":"Professional",
            "subcategory":"Employment Agencies",
            "type":"Services"
        }
    ],
    "sg:phone":"+1 310 278 4470",
    "sg:postcode":"90212",
    "sg:province":"CA",
    "wof:name":"International Services Agency",
    "wof:placetype":"venue"
},
  "geometry": {"coordinates":[-118.399072,34.063579],"type":"Point"}
}