{
  "type": "Feature",
  "properties": {
    "addr:full":"48 Springstowne Ctr Vallejo CA 94591",
    "addr:housenumber":"48",
    "addr:postcode":"94591",
    "addr:street":"Springstowne Ctr",
    "iso:country":"US",
    "sg:address":"48 Springstowne Ctr",
    "sg:city":"Vallejo",
    "sg:classifiers":[
        {
            "category":"Personal",
            "subcategory":"Beauty Salon",
            "type":"Services"
        },
        {
            "category":"Personal",
            "subcategory":"Nail Salon",
            "type":"Services"
        }
    ],
    "sg:phone":"+1 707 645 9269",
    "sg:postcode":"94591",
    "sg:province":"CA",
    "wof:name":"Neda's Beauty Palace",
    "wof:placetype":"venue"
},
  "geometry": {"coordinates":[-122.21727,38.104796],"type":"Point"}
}