{
  "type": "Feature",
  "properties": {
    "addr:full":"5245 Don Pio Dr Woodland Hills CA 91364",
    "addr:housenumber":"5245",
    "addr:postcode":"91364",
    "addr:street":"Don Pio Dr",
    "iso:country":"US",
    "sg:address":"5245 Don Pio Dr",
    "sg:city":"Woodland Hills",
    "sg:classifiers":[
        {
            "category":"Professional",
            "subcategory":"Advertising",
            "type":"Services"
        }
    ],
    "sg:phone":"+1 310 795 1558",
    "sg:postcode":"91364",
    "sg:province":"CA",
    "sg:tags":[
        "marketing"
    ],
    "sg:website":"MadeliaMarketing.com",
    "wof:name":"Madelia Marketing",
    "wof:placetype":"venue"
},
  "geometry": {"coordinates":[-118.605006,34.165559],"type":"Point"}
}