{
  "type": "Feature",
  "properties": {
    "addr:full":"4431 Cerritos Ave Cypress CA 90630",
    "addr:housenumber":"4431",
    "addr:postcode":"90630",
    "addr:street":"Cerritos Ave",
    "iso:country":"US",
    "sg:address":"4431 Cerritos Ave",
    "sg:city":"Cypress",
    "sg:classifiers":[
        {
            "category":"Retail",
            "subcategory":"Laundry & Dry Cleaning",
            "type":"Services"
        }
    ],
    "sg:phone":"+1 714 827 0605",
    "sg:postcode":"90630",
    "sg:province":"CA",
    "wof:name":"Cypress Cleaners",
    "wof:placetype":"venue"
},
  "geometry": {"coordinates":[-118.056,33.810501],"type":"Point"}
}