{
  "type": "Feature",
  "properties": {
    "addr:full":"1032 Irving St San Francisco CA 94122",
    "addr:housenumber":"1032",
    "addr:postcode":"94122",
    "addr:street":"Irving St",
    "iso:country":"US",
    "sg:address":"1032 Irving St",
    "sg:city":"San Francisco",
    "sg:classifiers":[
        {
            "category":"Freight",
            "type":"Transportation"
        }
    ],
    "sg:phone":"+1 415 566 2660",
    "sg:postcode":"94122",
    "sg:province":"CA",
    "sg:tags":[
        "shipping"
    ],
    "sg:website":"www.upsstore.com",
    "wof:name":"The UPS Store",
    "wof:placetype":"venue"
},
  "geometry": {"coordinates":[-122.469133,37.764163],"type":"Point"}
}