{
  "type": "Feature",
  "properties": {
    "iso:country":"US",
    "sg:address":"14419 Sylvan St",
    "sg:city":"Van Nuys",
    "sg:classifiers":[
        {
            "category":"Social Services",
            "subcategory":"Child Care",
            "type":"Services"
        },
        {
            "category":"Education",
            "subcategory":"Preschool",
            "type":"Public Place"
        },
        {
            "category":"Education",
            "subcategory":"School",
            "type":"Public Place"
        }
    ],
    "sg:phone":"+1 818 242 8045",
    "sg:postcode":"91401",
    "sg:province":"CA",
    "sg:tags":[
        "high",
        "middle",
        "day",
        "elementary"
    ],
    "wof:name":"St Mark's Episcopal Church Glendale",
    "wof:placetype":"venue"
},
  "geometry": {"coordinates":[-118.44699900000001,34.184502],"type":"Point"}
}