{
  "type": "Feature",
  "properties": {
    "iso:country":"US",
    "sg:address":"15219 W Sunset Blvd",
    "sg:city":"Pacific Plsds",
    "sg:classifiers":[
        {
            "category":"Real Estate",
            "subcategory":"Architect",
            "type":"Services"
        }
    ],
    "sg:phone":"+1 310 454 4189",
    "sg:postcode":"90272",
    "sg:province":"CA",
    "wof:name":"Roger A Schultz",
    "wof:placetype":"venue"
},
  "geometry": {"coordinates":[-118.524762,34.046569],"type":"Point"}
}