{
  "type": "Feature",
  "properties": {
    "addr:full":"225 E Cypress Ave Redding CA 96002",
    "addr:housenumber":"225",
    "addr:postcode":"96002",
    "addr:street":"E Cypress Ave",
    "iso:country":"US",
    "sg:address":"225 E Cypress Ave",
    "sg:city":"Redding",
    "sg:classifiers":[
        {
            "category":"Autos & Motor Vehicles",
            "subcategory":"Fuel & Gas Station",
            "type":"Retail Goods"
        }
    ],
    "sg:phone":"+1 530 222 2613",
    "sg:postcode":"96002",
    "sg:province":"CA",
    "sg:tags":[
        "oil"
    ],
    "wof:name":"One Stop",
    "wof:placetype":"venue"
},
  "geometry": {"coordinates":[-122.369039,40.571082],"type":"Point"}
}