{
  "type": "Feature",
  "properties": {
    "iso:country":"US",
    "sg:address":"2700 Irving St",
    "sg:city":"Riverside",
    "sg:classifiers":[
        {
            "category":"Education",
            "subcategory":"School",
            "type":"Public Place"
        }
    ],
    "sg:phone":"+1 951 352 6716",
    "sg:postcode":"92504",
    "sg:province":"CA",
    "sg:website":"http://www.rusd.k12.ca.us",
    "wof:name":"Hawthorne Elementary School",
    "wof:placetype":"venue"
},
  "geometry": {"coordinates":[-117.422737,33.911129],"type":"Point"}
}