{
  "type": "Feature",
  "properties": {
    "addr:full":"44421 20th St W Lancaster CA 93534",
    "addr:housenumber":"44421",
    "addr:postcode":"93534",
    "addr:street":"20Th St W",
    "iso:country":"US",
    "sg:address":"44421 20th St W",
    "sg:city":"Lancaster",
    "sg:classifiers":[
        {
            "category":"Personal",
            "subcategory":"Beauty Salon",
            "type":"Services"
        }
    ],
    "sg:phone":"+1 661 726 9012",
    "sg:postcode":"93534",
    "sg:province":"CA",
    "sg:tags":[
        "manicuring"
    ],
    "wof:name":"Misa Nail & Spa",
    "wof:placetype":"venue"
},
  "geometry": {"coordinates":[-118.16555700000001,34.690297],"type":"Point"}
}