{
  "type": "Feature",
  "properties": {
    "iso:country":"US",
    "sg:address":"102 Carnelian Rd",
    "sg:city":"South San Francisco",
    "sg:classifiers":[
        {
            "category":"Professional",
            "subcategory":"Computer Services",
            "type":"Services"
        }
    ],
    "sg:phone":"+1 650 877 1577",
    "sg:postcode":"94080",
    "sg:province":"CA",
    "sg:tags":[
        "related"
    ],
    "wof:name":"Warm Research",
    "wof:placetype":"venue"
},
  "geometry": {"coordinates":[-122.42317,37.665121],"type":"Point"}
}