{
  "type": "Feature",
  "properties": {
    "iso:country":"US",
    "sg:address":"1710 Brandon St",
    "sg:city":"Oakland",
    "sg:classifiers":[
        {
            "category":"Taxi",
            "type":"Transportation"
        }
    ],
    "sg:phone":"+1 510 428 1700",
    "sg:postcode":"94611",
    "sg:province":"CA",
    "sg:tags":[
        "taxicab"
    ],
    "wof:name":"Friendly Pamer Cab Svc",
    "wof:placetype":"venue"
},
  "geometry": {"coordinates":[-122.245566,37.828311],"type":"Point"}
}