{
  "type": "Feature",
  "properties": {
    "addr:full":"6050 Teesdale Ave North Hollywood CA 91606",
    "addr:housenumber":"6050",
    "addr:postcode":"91606",
    "addr:street":"Teesdale Ave",
    "iso:country":"US",
    "sg:address":"6050 Teesdale Ave",
    "sg:city":"North Hollywood",
    "sg:classifiers":[
        {
            "category":"Building & Trades",
            "subcategory":"Construction",
            "type":"Services"
        }
    ],
    "sg:phone":"+1 818 506 5890",
    "sg:postcode":"91606",
    "sg:province":"CA",
    "sg:tags":[
        "contractor"
    ],
    "wof:name":"Jonathan Builders Inc",
    "wof:placetype":"venue"
},
  "geometry": {"coordinates":[-118.40832899999999,34.182358],"type":"Point"}
}