{
  "type": "Feature",
  "properties": {
    "iso:country":"US",
    "sg:address":"207 Idora Ave",
    "sg:city":"Vallejo",
    "sg:classifiers":[
        {
            "category":"Building & Trades",
            "subcategory":"Construction",
            "type":"Services"
        }
    ],
    "sg:phone":"+1 707 554 3554",
    "sg:postcode":"94591",
    "sg:province":"CA",
    "sg:tags":[
        "concrete",
        "contractor"
    ],
    "wof:name":"Javier Zarate Concrete Contr",
    "wof:placetype":"venue"
},
  "geometry": {"coordinates":[-122.226033,38.092826],"type":"Point"}
}