{
  "type": "Feature",
  "properties": {
    "addr:full":"1261 Lincoln Ave San Jose CA 95125",
    "addr:housenumber":"1261",
    "addr:postcode":"95125",
    "addr:street":"Lincoln Ave",
    "iso:country":"US",
    "sg:address":"1261 Lincoln Ave",
    "sg:city":"San Jose",
    "sg:classifiers":[
        {
            "category":"Real Estate",
            "subcategory":"Architect",
            "type":"Services"
        }
    ],
    "sg:phone":"+1 408 279 3097",
    "sg:postcode":"95125",
    "sg:province":"CA",
    "sg:tags":[
        "home",
        "planning",
        "design"
    ],
    "wof:name":"Bearington Studios",
    "wof:placetype":"venue"
},
  "geometry": {"coordinates":[-121.89912699999999,37.305592],"type":"Point"}
}