{
  "type": "Feature",
  "properties": {
    "iso:country":"US",
    "sg:address":"1968 Buena Vista St",
    "sg:city":"Duarte",
    "sg:classifiers":[
        {
            "category":"Farming",
            "subcategory":"Livestock Farm",
            "type":"Manufacturing & Wholesale Goods"
        }
    ],
    "sg:phone":"+1 626 359 5464",
    "sg:postcode":"91010",
    "sg:province":"CA",
    "sg:tags":[
        "equine"
    ],
    "wof:name":"Ricardo V Zamora",
    "wof:placetype":"venue"
},
  "geometry": {"coordinates":[-117.977559,34.129051],"type":"Point"}
}