{
  "type": "Feature",
  "properties": {
    "iso:country":"US",
    "sg:address":"820 Northridge Shopping Ctr",
    "sg:city":"Salinas",
    "sg:classifiers":[
        {
            "category":"Shopping Center",
            "type":"Public Place"
        }
    ],
    "sg:phone":"+1 831 449 7281",
    "sg:postcode":"93906",
    "sg:province":"CA",
    "wof:name":"Northridge Mall",
    "wof:placetype":"venue"
},
  "geometry": {"coordinates":[-121.65682,36.721183],"type":"Point"}
}