{
  "type": "Feature",
  "properties": {
    "addr:full":"411 Western Dr Richmond CA 94801",
    "addr:housenumber":"411",
    "addr:postcode":"94801",
    "addr:street":"Western Dr",
    "iso:country":"US",
    "sg:address":"411 Western Dr",
    "sg:city":"Richmond",
    "sg:classifiers":[
        {
            "category":"Manufacturing",
            "subcategory":"Buildings",
            "type":"Manufacturing & Wholesale Goods"
        },
        {
            "category":"Building & Trades",
            "subcategory":"Construction",
            "type":"Services"
        }
    ],
    "sg:phone":"+1 510 232 4232",
    "sg:postcode":"94801",
    "sg:province":"CA",
    "sg:tags":[
        "home",
        "builder",
        "industrial",
        "contractors-commercial",
        "contractor"
    ],
    "wof:name":"Mbm",
    "wof:placetype":"venue"
},
  "geometry": {"coordinates":[-122.39077899999999,37.925682],"type":"Point"}
}