{
  "type": "Feature",
  "properties": {
    "iso:country":"US",
    "sg:address":"2115 W Florida Ave",
    "sg:city":"Hemet",
    "sg:classifiers":[
        {
            "category":"Home & Garden",
            "subcategory":"Furniture",
            "type":"Retail Goods"
        }
    ],
    "sg:phone":"+1 951 766 4614",
    "sg:postcode":"92545",
    "sg:province":"CA",
    "sg:tags":[
        "mattress"
    ],
    "wof:name":"Mattress Stop",
    "wof:placetype":"venue"
},
  "geometry": {"coordinates":[-116.99357500000001,33.747365],"type":"Point"}
}