{
  "type": "Feature",
  "properties": {
    "addr:full":"8021 Ridgegrove Way Fair Oaks CA 95628",
    "addr:housenumber":"8021",
    "addr:postcode":"95628",
    "addr:street":"Ridgegrove Way",
    "iso:country":"US",
    "sg:address":"8021 Ridgegrove Way",
    "sg:city":"Fair Oaks",
    "sg:classifiers":[
        {
            "category":"Building & Trades",
            "subcategory":"Construction",
            "type":"Services"
        }
    ],
    "sg:phone":"+1 916 967 4861",
    "sg:postcode":"95628",
    "sg:province":"CA",
    "sg:tags":[
        "contractor"
    ],
    "wof:name":"John Tragarz Construction",
    "wof:placetype":"venue"
},
  "geometry": {"coordinates":[-121.266211,38.657675],"type":"Point"}
}