{
  "type": "Feature",
  "properties": {
    "iso:country":"US",
    "sg:address":"515 S Fairfax Ave",
    "sg:city":"Los Angeles",
    "sg:classifiers":[
        {
            "category":"Shopping",
            "subcategory":"Clothing, Apparel, & Fashions",
            "type":"Retail Goods"
        }
    ],
    "sg:phone":"+1 323 938 7311",
    "sg:postcode":"90036",
    "sg:province":"CA",
    "sg:tags":[
        "clothing",
        "women's"
    ],
    "sg:website":"www.myspace.com/katelosangeles",
    "wof:name":"Kate Los Angeles",
    "wof:placetype":"venue"
},
  "geometry": {"coordinates":[-118.361684,34.066962],"type":"Point"}
}