{
  "type": "Feature",
  "properties": {
    "iso:country":"US",
    "sg:address":"1000 E Victoria St",
    "sg:city":"Carson",
    "sg:classifiers":[
        {
            "category":"Education",
            "subcategory":"University",
            "type":"Public Place"
        }
    ],
    "sg:phone":"+1 310 243 2025",
    "sg:postcode":"90747",
    "sg:province":"CA",
    "sg:tags":[
        "college"
    ],
    "sg:website":"www.lbusd.k12.ca.us",
    "wof:name":"Long Beach Unified School District",
    "wof:placetype":"venue"
},
  "geometry": {"coordinates":[-118.25900300000001,33.8671],"type":"Point"}
}