{
  "type": "Feature",
  "properties": {
    "addr:full":"11450 Elks Cir Rancho Cordova CA 95742",
    "addr:housenumber":"11450",
    "addr:postcode":"95742",
    "addr:street":"Elks Cir",
    "iso:country":"US",
    "sg:address":"11450 Elks Cir",
    "sg:city":"Rancho Cordova",
    "sg:classifiers":[
        {
            "category":"Building & Trades",
            "subcategory":"Construction",
            "type":"Services"
        }
    ],
    "sg:phone":"+1 916 635 1212",
    "sg:postcode":"95742",
    "sg:province":"CA",
    "sg:tags":[
        "maker",
        "cabinet"
    ],
    "wof:name":"Precision Woodworks",
    "wof:placetype":"venue"
},
  "geometry": {"coordinates":[-121.253787,38.564007],"type":"Point"}
}