{
  "type": "Feature",
  "properties": {
    "addr:full":"839 Phillips Ct Vista CA 92083",
    "addr:housenumber":"839",
    "addr:postcode":"92083",
    "addr:street":"Phillips Ct",
    "iso:country":"US",
    "sg:address":"839 Phillips Ct",
    "sg:city":"Vista",
    "sg:classifiers":[
        {
            "category":"Home & Garden",
            "subcategory":"Hardware",
            "type":"Retail Goods"
        }
    ],
    "sg:phone":"+1 760 630 4995",
    "sg:postcode":"92083",
    "sg:province":"CA",
    "wof:name":"Carlos & Sara Tools",
    "wof:placetype":"venue"
},
  "geometry": {"coordinates":[-117.237565,33.189437],"type":"Point"}
}