{
  "type": "Feature",
  "properties": {
    "addr:full":"180 Ford Rd Ukiah CA 95482",
    "addr:housenumber":"180",
    "addr:postcode":"ca 95482",
    "addr:street":"Ford Rd",
    "iso:country":"US",
    "sg:address":"180 Ford Rd",
    "sg:city":"Ukiah",
    "sg:classifiers":[
        {
            "category":"Restaurant",
            "type":"Food & Drink"
        }
    ],
    "sg:menulink":"http://www.allmenus.com/ca/ukiah/88003-little-caesars-pizza/menu/",
    "sg:phone":"+1 707 462 7646",
    "sg:postcode":"95482",
    "sg:province":"CA",
    "sg:tags":[
        "american",
        "pizza"
    ],
    "wof:name":"Little Caesar's Pizza",
    "wof:placetype":"venue"
},
  "geometry": {"coordinates":[-123.20712399999999,39.167528],"type":"Point"}
}