{
  "type": "Feature",
  "properties": {
    "iso:country":"US",
    "sg:address":"24309 Narbonne Ave",
    "sg:city":"Lomita",
    "sg:phone":"+1 310 325 3930",
    "sg:postcode":"90717",
    "sg:province":"CA",
    "wof:name":"Marriage License Express",
    "wof:placetype":"venue"
},
  "geometry": {"coordinates":[-118.319901,33.8049],"type":"Point"}
}