{
  "type": "Feature",
  "properties": {
    "addr:full":"25 Silver Eagle Rd Sacramento CA 95838",
    "addr:housenumber":"25",
    "addr:postcode":"95838",
    "addr:street":"Silver Eagle Rd",
    "iso:country":"US",
    "sg:address":"25 Silver Eagle Rd",
    "sg:city":"Sacramento",
    "sg:classifiers":[
        {
            "category":"Food & Beverages",
            "subcategory":"Groceries & Convenience Stores",
            "type":"Retail Goods"
        }
    ],
    "sg:phone":"+1 916 921 0135",
    "sg:postcode":"95838",
    "sg:province":"CA",
    "sg:tags":[
        "market"
    ],
    "wof:name":"Silver Eagle Market",
    "wof:placetype":"venue"
},
  "geometry": {"coordinates":[-121.463346,38.630307],"type":"Point"}
}