{
  "type": "Feature",
  "properties": {
    "iso:country":"US",
    "sg:address":"341 Shipley Ave",
    "sg:city":"Daly City",
    "sg:classifiers":[
        {
            "category":"Professional",
            "type":"Services"
        }
    ],
    "sg:phone":"+1 650 754 1186",
    "sg:postcode":"94015",
    "sg:province":"CA",
    "wof:name":"Pixc",
    "wof:placetype":"venue"
},
  "geometry": {"coordinates":[-122.46745199999999,37.651656],"type":"Point"}
}