{
  "type": "Feature",
  "properties": {
    "addr:full":"2900 E 44th St Los Angeles CA 90058",
    "addr:housenumber":"2900",
    "addr:postcode":"90058",
    "addr:street":"E 44Th St",
    "iso:country":"US",
    "sg:address":"2900 E 44th St",
    "sg:city":"Los Angeles",
    "sg:classifiers":[
        {
            "category":"Banks & Credit Unions",
            "subcategory":"Investment Brokerage",
            "type":"Services"
        }
    ],
    "sg:phone":"+1 323 583 6746",
    "sg:postcode":"90058",
    "sg:province":"CA",
    "sg:tags":[
        "commodity"
    ],
    "wof:name":"Grand West Commodities Inc",
    "wof:placetype":"venue"
},
  "geometry": {"coordinates":[-118.215293,34.003673],"type":"Point"}
}