{
  "type": "Feature",
  "properties": {
    "addr:full":"127 Jewell St Santa Cruz CA 95060",
    "addr:housenumber":"127",
    "addr:postcode":"95060",
    "addr:street":"Jewell St",
    "iso:country":"US",
    "sg:address":"127 Jewell St",
    "sg:city":"Santa Cruz",
    "sg:classifiers":[
        {
            "category":"Professional",
            "subcategory":"Lawyer & Legal Services",
            "type":"Services"
        }
    ],
    "sg:phone":"+1 831 425 3711",
    "sg:postcode":"95060",
    "sg:province":"CA",
    "wof:name":"Salatich Anthony J Atty",
    "wof:placetype":"venue"
},
  "geometry": {"coordinates":[-122.02600099999999,36.988499],"type":"Point"}
}