{
  "type": "Feature",
  "properties": {
    "addr:full":"195 N Main St Sebastopol CA 95472",
    "addr:housenumber":"195",
    "addr:postcode":"95472",
    "addr:street":"N Main St",
    "iso:country":"US",
    "sg:address":"195 N Main St",
    "sg:city":"Sebastopol",
    "sg:classifiers":[
        {
            "category":"Shopping",
            "subcategory":"Bicycles & Sporting Goods",
            "type":"Retail Goods"
        }
    ],
    "sg:phone":"+1 707 829 1880",
    "sg:postcode":"95472",
    "sg:province":"CA",
    "wof:name":"Bicycle Factory",
    "wof:placetype":"venue"
},
  "geometry": {"coordinates":[-122.824878,38.403318],"type":"Point"}
}