{
  "type": "Feature",
  "properties": {
    "addr:full":"1843 Hotel Cir S San Diego CA 92108",
    "addr:housenumber":"1843",
    "addr:postcode":"92108",
    "addr:street":"Hotel Cir S",
    "iso:country":"US",
    "sg:address":"1843 Hotel Cir S",
    "sg:city":"San Diego",
    "sg:classifiers":[
        {
            "category":"Professional",
            "subcategory":"Engineering",
            "type":"Services"
        }
    ],
    "sg:phone":"+1 619 260 5570",
    "sg:postcode":"92108",
    "sg:province":"CA",
    "sg:tags":[
        "engineer"
    ],
    "wof:name":"Jacob Associates",
    "wof:placetype":"venue"
},
  "geometry": {"coordinates":[-117.180153,32.758986],"type":"Point"}
}