{
  "type": "Feature",
  "properties": {
    "addr:full":"5921 Sheila St Commerce CA 90040",
    "addr:postcode":"5921;90040",
    "addr:street":"Sheila St",
    "iso:country":"US",
    "sg:address":"5921 Sheila St",
    "sg:city":"Commerce",
    "sg:classifiers":[
        {
            "category":"Manufacturing",
            "subcategory":"Retail Goods",
            "type":"Manufacturing & Wholesale Goods"
        }
    ],
    "sg:phone":"+1 323 720 1114",
    "sg:postcode":"90040",
    "sg:province":"CA",
    "sg:tags":[
        "handbags-wholesale",
        "manufacturer"
    ],
    "wof:name":"Calion Inc.",
    "wof:placetype":"venue"
},
  "geometry": {"coordinates":[-118.151803,33.996657],"type":"Point"}
}