{
  "type": "Feature",
  "properties": {
    "iso:country":"US",
    "sg:address":"16490 Vineyard Blvd",
    "sg:city":"Morgan Hill",
    "sg:classifiers":[
        {
            "category":"Building & Trades",
            "subcategory":"Construction",
            "type":"Services"
        }
    ],
    "sg:phone":"+1 408 465 2270",
    "sg:postcode":"95037",
    "sg:province":"CA",
    "sg:tags":[
        "paving",
        "contractor"
    ],
    "sg:website":"www.spiritroadoils.com",
    "wof:name":"Spirit Road Oils",
    "wof:placetype":"venue"
},
  "geometry": {"coordinates":[-121.638316,37.115382],"type":"Point"}
}