{
  "type": "Feature",
  "properties": {
    "addr:full":"1949 S Norfolk St San Mateo CA 94403",
    "addr:housenumber":"1949",
    "addr:postcode":"94403",
    "addr:street":"S Norfolk St",
    "iso:country":"US",
    "sg:address":"1949 S Norfolk St",
    "sg:city":"San Mateo",
    "sg:classifiers":[
        {
            "category":"Freight",
            "type":"Transportation"
        }
    ],
    "sg:phone":"+1 650 341 9666",
    "sg:postcode":"94403",
    "sg:province":"CA",
    "sg:tags":[
        "commercial",
        "storage",
        "general"
    ],
    "wof:name":"Budget Mini Storage San Mateo",
    "wof:placetype":"venue"
},
  "geometry": {"coordinates":[-122.289778,37.552332],"type":"Point"}
}