{
  "type": "Feature",
  "properties": {
    "iso:country":"US",
    "sg:address":"490 Post St Ste 1701",
    "sg:city":"San Francisco",
    "sg:classifiers":[
        {
            "category":"Health Services",
            "subcategory":"Doctor",
            "type":"Services"
        }
    ],
    "sg:phone":"+1 415 800 8371",
    "sg:postcode":"94102",
    "sg:province":"CA",
    "sg:tags":[
        "surgeon",
        "cosmetic"
    ],
    "sg:website":"www.rfgmd.com",
    "wof:name":"Richard F Grossman, MD",
    "wof:placetype":"venue"
},
  "geometry": {"coordinates":[-122.40989500000001,37.788181],"type":"Point"}
}