{
  "type": "Feature",
  "properties": {
    "iso:country":"US",
    "sg:address":"1122 19th St",
    "sg:city":"Bakersfield",
    "sg:classifiers":[
        {
            "category":"Personal",
            "subcategory":"Barber",
            "type":"Services"
        }
    ],
    "sg:phone":"+1 661 638 0199",
    "sg:postcode":"93301",
    "sg:province":"CA",
    "wof:name":"Just Us Barber Shop",
    "wof:placetype":"venue"
},
  "geometry": {"coordinates":[-119.015256,35.376213],"type":"Point"}
}