{
  "type": "Feature",
  "properties": {
    "addr:full":"6624 Somerset Blvd Paramount CA 90723",
    "addr:housenumber":"6624",
    "addr:postcode":"90723",
    "addr:street":"Somerset Blvd",
    "iso:country":"US",
    "sg:address":"6624 Somerset Blvd",
    "sg:city":"Paramount",
    "sg:classifiers":[
        {
            "category":"Restaurant",
            "type":"Food & Drink"
        }
    ],
    "sg:phone":"+1 562 633 1781",
    "sg:postcode":"90723",
    "sg:province":"CA",
    "sg:tags":[
        "pizza"
    ],
    "wof:name":"Little Caesars",
    "wof:placetype":"venue"
},
  "geometry": {"coordinates":[-118.18095099999999,33.896202],"type":"Point"}
}