{
  "type": "Feature",
  "properties": {
    "iso:country":"US",
    "sg:address":"3301 S St",
    "sg:city":"Sacramento",
    "sg:classifiers":[
        {
            "category":"Professional",
            "subcategory":"Computer Services",
            "type":"Services"
        }
    ],
    "sg:phone":"+1 916 739 7640",
    "sg:postcode":"95816",
    "sg:province":"CA",
    "sg:tags":[
        "datum",
        "center"
    ],
    "wof:name":"Health Humn Svcs Agcy Data Ctr",
    "wof:placetype":"venue"
},
  "geometry": {"coordinates":[-121.466404,38.562143],"type":"Point"}
}