{
  "type": "Feature",
  "properties": {
    "addr:full":"1358 Vineland Ave Baldwin Park CA 91706",
    "addr:housenumber":"1358",
    "addr:postcode":"91706",
    "addr:street":"Vineland Ave",
    "iso:country":"US",
    "sg:address":"1358 Vineland Ave",
    "sg:city":"Baldwin Park",
    "sg:classifiers":[
        {
            "category":"Freight",
            "type":"Transportation"
        }
    ],
    "sg:phone":"+1 626 960 7284",
    "sg:postcode":"91706",
    "sg:province":"CA",
    "sg:tags":[
        "trucking"
    ],
    "wof:name":"ABF Fence Co",
    "wof:placetype":"venue"
},
  "geometry": {"coordinates":[-117.97501,34.065782],"type":"Point"}
}