{
  "type": "Feature",
  "properties": {
    "iso:country":"US",
    "sg:address":"132 S Main Ave",
    "sg:city":"Fallbrook",
    "sg:classifiers":[
        {
            "category":"Professional",
            "subcategory":"Printing & Photocopies",
            "type":"Services"
        }
    ],
    "sg:phone":"+1 760 731 7177",
    "sg:postcode":"92028",
    "sg:province":"CA",
    "sg:tags":[
        "duplicating",
        "copying"
    ],
    "wof:name":"Inadas Express Copy Cente",
    "wof:placetype":"venue"
},
  "geometry": {"coordinates":[-117.251999,33.381302],"type":"Point"}
}