{
  "type": "Feature",
  "properties": {
    "iso:country":"US",
    "sg:address":"3301 Saco St",
    "sg:city":"Vernon",
    "sg:classifiers":[
        {
            "category":"Manufacturing",
            "subcategory":"Metals",
            "type":"Manufacturing & Wholesale Goods"
        }
    ],
    "sg:phone":"+1 323 588 8474",
    "sg:postcode":"90058",
    "sg:province":"CA",
    "sg:tags":[
        "transfer",
        "heat",
        "material"
    ],
    "sg:website":"www.stantoncalprints.com",
    "wof:name":"Stanton Calprints Inc",
    "wof:placetype":"venue"
},
  "geometry": {"coordinates":[-118.234089,34.009209],"type":"Point"}
}