{
  "type": "Feature",
  "properties": {
    "addr:full":"1970 E Gladwick St Rancho Dominguez CA 90220",
    "addr:housenumber":"1970",
    "addr:postcode":"90220",
    "addr:street":"E Gladwick St",
    "iso:country":"US",
    "sg:address":"1970 E Gladwick St",
    "sg:city":"Rancho Dominguez",
    "sg:classifiers":[
        {
            "category":"Wholesale",
            "subcategory":"Electrical",
            "type":"Manufacturing & Wholesale Goods"
        }
    ],
    "sg:phone":"+1 310 608 1305",
    "sg:postcode":"90220",
    "sg:province":"CA",
    "sg:tags":[
        "cleaners",
        "vacuum"
    ],
    "wof:name":"G V Wholesale Distr",
    "wof:placetype":"venue"
},
  "geometry": {"coordinates":[-118.23305000000001,33.853246],"type":"Point"}
}