{
  "type": "Feature",
  "properties": {
    "addr:full":"1610 N Gower St Los Angeles CA 90028",
    "addr:housenumber":"1610",
    "addr:postcode":"90028",
    "addr:street":"N Gower St",
    "iso:country":"US",
    "sg:address":"1610 N Gower St",
    "sg:city":"Los Angeles",
    "sg:classifiers":[
        {
            "category":"Food & Beverages",
            "subcategory":"Liquor & Beverages",
            "type":"Retail Goods"
        }
    ],
    "sg:phone":"+1 323 469 9677",
    "sg:postcode":"90028",
    "sg:province":"CA",
    "wof:name":"Carlton Liquor",
    "wof:placetype":"venue"
},
  "geometry": {"coordinates":[-118.322233,34.099997],"type":"Point"}
}