{
  "type": "Feature",
  "properties": {
    "addr:full":"14900 Ventura Blvd Sherman Oaks CA 91403",
    "addr:housenumber":"14900",
    "addr:postcode":"91403",
    "addr:street":"Ventura Blvd",
    "iso:country":"US",
    "sg:address":"14900 Ventura Blvd",
    "sg:city":"Sherman Oaks",
    "sg:classifiers":[
        {
            "category":"Professional",
            "subcategory":"Advertising",
            "type":"Services"
        }
    ],
    "sg:phone":"+1 818 981 2221",
    "sg:postcode":"91403",
    "sg:province":"CA",
    "sg:tags":[
        "medium",
        "broker"
    ],
    "wof:name":"Mediaworks Corp Communications",
    "wof:placetype":"venue"
},
  "geometry": {"coordinates":[-118.459602,34.152722],"type":"Point"}
}