{
  "type": "Feature",
  "properties": {
    "addr:full":"25 San Anselmo Ave San Anselmo CA 94960",
    "addr:housenumber":"25",
    "addr:postcode":"94960",
    "addr:street":"San Anselmo Ave",
    "iso:country":"US",
    "sg:address":"25 San Anselmo Ave",
    "sg:city":"San Anselmo",
    "sg:classifiers":[
        {
            "category":"Social Services",
            "type":"Services"
        }
    ],
    "sg:phone":"+1 415 454 9525",
    "sg:postcode":"94960",
    "sg:province":"CA",
    "sg:tags":[
        "counselor",
        "marriage",
        "family"
    ],
    "wof:name":"Marian P Preston",
    "wof:placetype":"venue"
},
  "geometry": {"coordinates":[-122.561229,37.970203],"type":"Point"}
}