{
  "type": "Feature",
  "properties": {
    "iso:country":"US",
    "sg:address":"3231 Baker Rd",
    "sg:city":"Modesto",
    "sg:classifiers":[
        {
            "category":"Farming",
            "subcategory":"Dairy Farm",
            "type":"Manufacturing & Wholesale Goods"
        }
    ],
    "sg:phone":"+1 209 529 2841",
    "sg:postcode":"95358",
    "sg:province":"CA",
    "wof:name":"Frank Sozinhos Diary",
    "wof:placetype":"venue"
},
  "geometry": {"coordinates":[-121.094075,37.604951],"type":"Point"}
}