{
  "type": "Feature",
  "properties": {
    "iso:country":"US",
    "sg:address":"2353 Moonlight Way",
    "sg:city":"Santa Rosa",
    "sg:classifiers":[
        {
            "category":"Building & Trades",
            "subcategory":"Electrical",
            "type":"Services"
        }
    ],
    "sg:phone":"+1 707 573 0634",
    "sg:postcode":"95403",
    "sg:province":"CA",
    "sg:tags":[
        "electrical",
        "contractor"
    ],
    "wof:name":"Arrow Electric",
    "wof:placetype":"venue"
},
  "geometry": {"coordinates":[-122.763897,38.456605],"type":"Point"}
}