{
  "type": "Feature",
  "properties": {
    "iso:country":"US",
    "sg:address":"25536 Barton Rd",
    "sg:city":"Loma Linda",
    "sg:classifiers":[
        {
            "category":"Restaurant",
            "type":"Food & Drink"
        }
    ],
    "sg:menulink":"http://www.allmenus.com/ca/san-bernardino/171104-carls-jr/menu/",
    "sg:phone":"+1 909 478 9834",
    "sg:postcode":"92354",
    "sg:province":"CA",
    "sg:tags":[
        "burger",
        "american"
    ],
    "wof:name":"Carl's Jr.",
    "wof:placetype":"venue"
},
  "geometry": {"coordinates":[-117.24776900000001,34.048469],"type":"Point"}
}