{
  "type": "Feature",
  "properties": {
    "iso:country":"US",
    "sg:address":"3116 N E St",
    "sg:city":"San Bernardino",
    "sg:classifiers":[
        {
            "category":"Shopping",
            "type":"Retail Goods"
        }
    ],
    "sg:phone":"+1 909 881 2240",
    "sg:postcode":"92405",
    "sg:province":"CA",
    "sg:tags":[
        "ice"
    ],
    "wof:name":"Bear Ice Co",
    "wof:placetype":"venue"
},
  "geometry": {"coordinates":[-117.294171,34.149226],"type":"Point"}
}