{
  "type": "Feature",
  "properties": {
    "addr:full":"7812 Fruitvale Ave Bakersfield CA 93308",
    "addr:housenumber":"7812",
    "addr:postcode":"93308",
    "addr:street":"Fruitvale Ave",
    "iso:country":"US",
    "sg:address":"7812 Fruitvale Ave",
    "sg:city":"Bakersfield",
    "sg:classifiers":[
        {
            "category":"Professional",
            "type":"Services"
        }
    ],
    "sg:phone":"+1 805 829 6969",
    "sg:postcode":"93308",
    "sg:province":"CA",
    "wof:name":"Easlick Services",
    "wof:placetype":"venue"
},
  "geometry": {"coordinates":[-119.074454,35.4282],"type":"Point"}
}