{
  "type": "Feature",
  "properties": {
    "addr:full":"9163 Quail Brook Cir Elk Grove CA 95624",
    "addr:housenumber":"9163",
    "addr:postcode":"95624",
    "addr:street":"Quail Brook Cir",
    "iso:country":"US",
    "sg:address":"9163 Quail Brook Cir",
    "sg:city":"Elk Grove",
    "sg:classifiers":[
        {
            "category":"Wholesale",
            "subcategory":"Medical Equipment & Supplies",
            "type":"Manufacturing & Wholesale Goods"
        }
    ],
    "sg:phone":"+1 916 685 1760",
    "sg:postcode":"95624",
    "sg:province":"CA",
    "wof:name":"Hq Opthalmic Co",
    "wof:placetype":"venue"
},
  "geometry": {"coordinates":[-121.367171,38.42407],"type":"Point"}
}