{
  "type": "Feature",
  "properties": {
    "iso:country":"US",
    "sg:address":"1260 N Sunshine Way",
    "sg:city":"Anaheim",
    "sg:classifiers":[
        {
            "category":"Wholesale",
            "subcategory":"Machinery & Supplies",
            "type":"Manufacturing & Wholesale Goods"
        }
    ],
    "sg:phone":"+1 714 688 0808",
    "sg:postcode":"92806",
    "sg:province":"CA",
    "sg:tags":[
        "industrial",
        "mach"
    ],
    "wof:name":"Select Equipment Sales",
    "wof:placetype":"venue"
},
  "geometry": {"coordinates":[-117.878133,33.853278],"type":"Point"}
}