{
  "type": "Feature",
  "properties": {
    "addr:full":"15500 Whittier Blvd Whittier CA 90603",
    "addr:housenumber":"15500",
    "addr:postcode":"90603",
    "addr:street":"Whittier Blvd",
    "iso:country":"US",
    "sg:address":"15500 Whittier Blvd",
    "sg:city":"Whittier",
    "sg:classifiers":[
        {
            "category":"Restaurant",
            "type":"Food & Drink"
        }
    ],
    "sg:menulink":"http://www.allmenus.com/ca/whittier/233738-black-angus-steakhouse/menu/",
    "sg:phone":"+1 562 947 2200",
    "sg:postcode":"90603",
    "sg:province":"CA",
    "sg:tags":[
        "american",
        "steakhouse"
    ],
    "wof:name":"Black Angus Steakhouse",
    "wof:placetype":"venue"
},
  "geometry": {"coordinates":[-117.99702000000001,33.94568],"type":"Point"}
}