{
  "type": "Feature",
  "properties": {
    "iso:country":"US",
    "sg:address":"24917 Pico Canyon Rd",
    "sg:city":"Stevenson Ranch",
    "sg:classifiers":[
        {
            "category":"Restaurant",
            "type":"Food & Drink"
        }
    ],
    "sg:phone":"+1 661 799 0360",
    "sg:postcode":"91381",
    "sg:province":"CA",
    "sg:tags":[
        "pizza",
        "italian"
    ],
    "sg:website":"www.spumonistevenson.com",
    "wof:name":"Spumoni Italian Restaurant",
    "wof:placetype":"venue"
},
  "geometry": {"coordinates":[-118.571669,34.381952],"type":"Point"}
}