{
  "type": "Feature",
  "properties": {
    "iso:country":"US",
    "sg:address":"109 William Ave",
    "sg:city":"Larkspur",
    "sg:classifiers":[
        {
            "category":"Communications",
            "type":"Services"
        }
    ],
    "sg:phone":"+1 415 924 9020",
    "sg:postcode":"94939",
    "sg:province":"CA",
    "sg:tags":[
        "a",
        "satellite",
        "specifically",
        "station",
        "radio",
        "earth"
    ],
    "wof:name":"Dbs Industries Inc",
    "wof:placetype":"venue"
},
  "geometry": {"coordinates":[-122.535731,37.931949],"type":"Point"}
}