{
  "type": "Feature",
  "properties": {
    "iso:country":"US",
    "sg:address":"13611 Doty Ave",
    "sg:city":"Hawthorne",
    "sg:classifiers":[
        {
            "category":"Manufacturing",
            "subcategory":"Food",
            "type":"Manufacturing & Wholesale Goods"
        }
    ],
    "sg:phone":"+1 310 263 0476",
    "sg:postcode":"90250",
    "sg:province":"CA",
    "sg:tags":[
        "cake",
        "product",
        "related",
        "bread"
    ],
    "wof:name":"C&D Catering",
    "wof:placetype":"venue"
},
  "geometry": {"coordinates":[-118.33956499999999,33.907945],"type":"Point"}
}