{
  "type": "Feature",
  "properties": {
    "iso:country":"US",
    "sg:address":"1 Florida St",
    "sg:city":"Vallejo",
    "sg:classifiers":[
        {
            "category":"Utilities",
            "type":"Services"
        }
    ],
    "sg:phone":"+1 707 648 5633",
    "sg:postcode":"94590",
    "sg:province":"CA",
    "sg:tags":[
        "company",
        "electric"
    ],
    "wof:name":"Pacific Gas and Electric Co",
    "wof:placetype":"venue"
},
  "geometry": {"coordinates":[-122.264883,38.105188],"type":"Point"}
}