{
  "type": "Feature",
  "properties": {
    "iso:country":"US",
    "sg:address":"1637 3rd Ave",
    "sg:city":"Chula Vista",
    "sg:classifiers":[
        {
            "category":"Health Services",
            "subcategory":"Medical Lab",
            "type":"Services"
        }
    ],
    "sg:phone":"+1 619 476 7847",
    "sg:postcode":"91911",
    "sg:province":"CA",
    "sg:tags":[
        "laboratory"
    ],
    "wof:name":"Biodata Medical Laboratories",
    "wof:placetype":"venue"
},
  "geometry": {"coordinates":[-117.064461,32.596591],"type":"Point"}
}