{
  "type": "Feature",
  "properties": {
    "iso:country":"US",
    "sg:address":"5140 Crenshaw Blvd",
    "sg:city":"Los Angeles",
    "sg:classifiers":[
        {
            "category":"Professional",
            "type":"Services"
        }
    ],
    "sg:phone":"+1 323 938 8352",
    "sg:postcode":"90043",
    "sg:province":"CA",
    "sg:tags":[
        "bureau"
    ],
    "wof:name":"Jimmy Johnson Tax Svc",
    "wof:placetype":"venue"
},
  "geometry": {"coordinates":[-118.33060999999999,33.996268],"type":"Point"}
}