{
  "type": "Feature",
  "properties": {
    "addr:full":"1320 Los Osos Valley Rd Los Osos CA 93402",
    "addr:housenumber":"1320",
    "addr:postcode":"93402",
    "addr:street":"Los Osos Valley Rd",
    "iso:country":"US",
    "sg:address":"1320 Los Osos Valley Rd",
    "sg:city":"Los Osos",
    "sg:classifiers":[
        {
            "category":"Food & Beverages",
            "subcategory":"Groceries & Convenience Stores",
            "type":"Retail Goods"
        }
    ],
    "sg:phone":"+1 805 528 0112",
    "sg:postcode":"93402",
    "sg:province":"CA",
    "sg:tags":[
        "grocer"
    ],
    "wof:name":"Ralph's",
    "wof:placetype":"venue"
},
  "geometry": {"coordinates":[-120.827202,35.310617],"type":"Point"}
}