{
  "type": "Feature",
  "properties": {
    "iso:country":"US",
    "sg:address":"665 Laurel St",
    "sg:city":"San Carlos",
    "sg:classifiers":[
        {
            "category":"Shopping",
            "subcategory":"Clothing, Apparel, & Fashions",
            "type":"Retail Goods"
        }
    ],
    "sg:phone":"+1 650 593 4617",
    "sg:postcode":"94070",
    "sg:province":"CA",
    "sg:tags":[
        "alteration"
    ],
    "wof:name":"Siran's Alteration",
    "wof:placetype":"venue"
},
  "geometry": {"coordinates":[-122.26048,37.506138],"type":"Point"}
}