{
  "type": "Feature",
  "properties": {
    "iso:country":"US",
    "sg:address":"131 Southampton Ln",
    "sg:city":"Santa Cruz",
    "sg:classifiers":[
        {
            "category":"Professional",
            "subcategory":"Management & Consulting",
            "type":"Services"
        }
    ],
    "sg:phone":"+1 831 457 9695",
    "sg:postcode":"95062",
    "sg:province":"CA",
    "sg:tags":[
        "marketing",
        "consultant"
    ],
    "sg:website":"www.scottiesavers.com",
    "wof:name":"Caesar Marketing",
    "wof:placetype":"venue"
},
  "geometry": {"coordinates":[-122.002308,36.970895],"type":"Point"}
}