{
  "type": "Feature",
  "properties": {
    "iso:country":"US",
    "sg:address":"225 S Olive St",
    "sg:city":"Los Angeles",
    "sg:classifiers":[
        {
            "category":"Insurance",
            "subcategory":"Hazard Insurance",
            "type":"Services"
        },
        {
            "category":"Insurance",
            "subcategory":"Insurance Agent",
            "type":"Services"
        }
    ],
    "sg:phone":"+1 213 628 8287",
    "sg:postcode":"90012",
    "sg:province":"CA",
    "sg:tags":[
        "carrier"
    ],
    "wof:name":"Patten Marine Insurance Servic",
    "wof:placetype":"venue"
},
  "geometry": {"coordinates":[-118.249027,34.053501],"type":"Point"}
}