{
  "type": "Feature",
  "properties": {
    "addr:full":"3501 Coffee Rd Modesto CA 95355",
    "addr:housenumber":"3501",
    "addr:postcode":"ca 95355",
    "addr:street":"Coffee Rd",
    "iso:country":"US",
    "sg:address":"3501 Coffee Rd",
    "sg:city":"Modesto",
    "sg:classifiers":[
        {
            "category":"Banks & Credit Unions",
            "subcategory":"Bank",
            "type":"Services"
        }
    ],
    "sg:phone":"+1 209 593 5316",
    "sg:postcode":"95355",
    "sg:province":"CA",
    "sg:tags":[
        "loan",
        "real estate"
    ],
    "wof:name":"American Security Financial",
    "wof:placetype":"venue"
},
  "geometry": {"coordinates":[-120.976085,37.690475],"type":"Point"}
}