{
  "type": "Feature",
  "properties": {
    "addr:full":"20930 S Alameda St Long Beach CA 90810",
    "addr:housenumber":"20930",
    "addr:postcode":"90810",
    "addr:street":"S Alameda St",
    "iso:country":"US",
    "sg:address":"20930 S Alameda St",
    "sg:city":"Long Beach",
    "sg:classifiers":[
        {
            "category":"Wholesale",
            "subcategory":"Construction Materials",
            "type":"Manufacturing & Wholesale Goods"
        }
    ],
    "sg:phone":"+1 310 635 7931",
    "sg:postcode":"90810",
    "sg:province":"CA",
    "sg:tags":[
        "lumber"
    ],
    "wof:name":"Bohannon Lumber Company",
    "wof:placetype":"venue"
},
  "geometry": {"coordinates":[-118.222774,33.839501],"type":"Point"}
}