{
  "type": "Feature",
  "properties": {
    "iso:country":"US",
    "sg:address":"44360 Gordon Ln",
    "sg:city":"Mendocino",
    "sg:classifiers":[
        {
            "category":"Building & Trades",
            "subcategory":"Construction",
            "type":"Services"
        }
    ],
    "sg:phone":"+1 707 937 4316",
    "sg:postcode":"95460",
    "sg:province":"CA",
    "sg:tags":[
        "contractor"
    ],
    "wof:name":"Heyden Loudon Construction Inc",
    "wof:placetype":"venue"
},
  "geometry": {"coordinates":[-123.783441,39.285262],"type":"Point"}
}