{
  "type": "Feature",
  "properties": {
    "addr:full":"2120 Montana St Oakland CA 94602",
    "addr:housenumber":"2120",
    "addr:postcode":"94602",
    "addr:street":"Montana St",
    "iso:country":"US",
    "sg:address":"2120 Montana St",
    "sg:city":"Oakland",
    "sg:classifiers":[
        {
            "category":"Autos & Motor Vehicles",
            "subcategory":"Fuel & Gas Station",
            "type":"Retail Goods"
        }
    ],
    "sg:phone":"+1 510 530 9234",
    "sg:postcode":"94602",
    "sg:province":"CA",
    "sg:website":"www.shell.com",
    "wof:name":"Vickie's Shell",
    "wof:placetype":"venue"
},
  "geometry": {"coordinates":[-122.218002,37.799],"type":"Point"}
}