{
  "type": "Feature",
  "properties": {
    "addr:full":"13441 S Normandie Ave Gardena CA 90249",
    "addr:housenumber":"13441",
    "addr:postcode":"90249",
    "addr:street":"S Normandie Ave",
    "iso:country":"US",
    "sg:address":"13441 S Normandie Ave",
    "sg:city":"Gardena",
    "sg:classifiers":[
        {
            "category":"Wholesale",
            "subcategory":"Machinery & Supplies",
            "type":"Manufacturing & Wholesale Goods"
        }
    ],
    "sg:phone":"+1 310 769 0010",
    "sg:postcode":"90249",
    "sg:province":"CA",
    "sg:tags":[
        "equipment",
        "industrial"
    ],
    "wof:name":"A N Hydraulics",
    "wof:placetype":"venue"
},
  "geometry": {"coordinates":[-118.30044599999999,33.909838],"type":"Point"}
}