{
  "type": "Feature",
  "properties": {
    "addr:full":"16053 Victory Blvd Van Nuys CA 91406",
    "addr:housenumber":"16053",
    "addr:postcode":"91406",
    "addr:street":"Victory Blvd",
    "iso:country":"US",
    "sg:address":"16053 Victory Blvd",
    "sg:city":"Van Nuys",
    "sg:classifiers":[
        {
            "category":"Shopping",
            "subcategory":"Tobacco",
            "type":"Retail Goods"
        }
    ],
    "sg:phone":"+1 818 782 7929",
    "sg:postcode":"91406",
    "sg:province":"CA",
    "sg:tags":[
        "cigarette",
        "cigar",
        "dealer"
    ],
    "wof:name":"Tobacco USA",
    "wof:placetype":"venue"
},
  "geometry": {"coordinates":[-118.483335,34.186714],"type":"Point"}
}