{
  "type": "Feature",
  "properties": {
    "addr:full":"1855 Gateway Blvd Ste 630 Concord CA 94520",
    "addr:housenumber":"1855",
    "addr:postcode":"94520",
    "addr:street":"Gateway Blvd Ste 630",
    "iso:country":"US",
    "sg:address":"1855 Gateway Blvd Ste 630",
    "sg:city":"Concord",
    "sg:classifiers":[
        {
            "category":"Retail",
            "subcategory":"Event Space",
            "type":"Services"
        },
        {
            "category":"Arena",
            "subcategory":"Sports Club",
            "type":"Entertainment"
        }
    ],
    "sg:phone":"+1 925 671 4000",
    "sg:postcode":"94520",
    "sg:province":"CA",
    "sg:tags":[
        "ticket",
        "sale"
    ],
    "sg:website":"http://www.tickets.com",
    "wof:name":"Tickets.com Inc",
    "wof:placetype":"venue"
},
  "geometry": {"coordinates":[-122.04312400000001,37.971566],"type":"Point"}
}