{
  "type": "Feature",
  "properties": {
    "addr:full":"4805 Clinton Ave Kingsburg CA 93631",
    "addr:housenumber":"4805",
    "addr:postcode":"93631",
    "addr:street":"Clinton Ave",
    "iso:country":"US",
    "sg:address":"4805 Clinton Ave",
    "sg:city":"Kingsburg",
    "sg:classifiers":[
        {
            "category":"Wholesale",
            "subcategory":"Groceries",
            "type":"Manufacturing & Wholesale Goods"
        }
    ],
    "sg:phone":"+1 559 897 4826",
    "sg:postcode":"93631",
    "sg:province":"CA",
    "sg:tags":[
        "grocer"
    ],
    "wof:name":"Olson Family Farms",
    "wof:placetype":"venue"
},
  "geometry": {"coordinates":[-119.551095,36.452281],"type":"Point"}
}