{
  "type": "Feature",
  "properties": {
    "iso:country":"US",
    "sg:address":"12108 Monogram Ave",
    "sg:city":"Granada Hills",
    "sg:classifiers":[
        {
            "category":"Travel",
            "subcategory":"Travel Agent",
            "type":"Entertainment"
        }
    ],
    "sg:phone":"+1 818 366 4148",
    "sg:postcode":"91344",
    "sg:province":"CA",
    "sg:tags":[
        "agency"
    ],
    "wof:name":"Day By Day Trips",
    "wof:placetype":"venue"
},
  "geometry": {"coordinates":[-118.490786,34.289808],"type":"Point"}
}