{
  "type": "Feature",
  "properties": {
    "addr:full":"1761 W Romneya Dr Ste K Anaheim CA 92801",
    "addr:housenumber":"1761",
    "addr:postcode":"92801",
    "addr:street":"W Romneya Dr Ste K",
    "iso:country":"US",
    "sg:address":"1761 W Romneya Dr Ste K",
    "sg:city":"Anaheim",
    "sg:classifiers":[
        {
            "category":"Health Services",
            "subcategory":"Dentist",
            "type":"Services"
        }
    ],
    "sg:phone":"+1 714 502 6990",
    "sg:postcode":"92801",
    "sg:province":"CA",
    "wof:name":"Yun John S DMD",
    "wof:placetype":"venue"
},
  "geometry": {"coordinates":[-117.94405399999999,33.851654],"type":"Point"}
}