{
  "type": "Feature",
  "properties": {
    "iso:country":"US",
    "sg:address":"3561 S Maple Ave",
    "sg:city":"Fresno",
    "sg:classifiers":[
        {
            "category":"Utilities",
            "subcategory":"Refuse",
            "type":"Services"
        }
    ],
    "sg:phone":"+1 559 486 1960",
    "sg:postcode":"93725",
    "sg:province":"CA",
    "sg:tags":[
        "waste",
        "removal"
    ],
    "wof:name":"Safety Kleen",
    "wof:placetype":"venue"
},
  "geometry": {"coordinates":[-119.745744,36.684666],"type":"Point"}
}