{
  "type": "Feature",
  "properties": {
    "addr:full":"81709 Doctor Carreon Blvd Indio CA 92201",
    "addr:postcode":"81709;92201",
    "addr:street":"Doctor Carreon Blvd",
    "iso:country":"US",
    "sg:address":"81709 Doctor Carreon Blvd",
    "sg:city":"Indio",
    "sg:classifiers":[
        {
            "category":"Health Services",
            "subcategory":"Doctor",
            "type":"Services"
        }
    ],
    "sg:phone":"+1 760 863 1968",
    "sg:postcode":"92201",
    "sg:province":"CA",
    "sg:tags":[
        "physician",
        "surgeon"
    ],
    "wof:name":"Vascular & Interventional",
    "wof:placetype":"venue"
},
  "geometry": {"coordinates":[-116.24194,33.707096],"type":"Point"}
}