{
  "type": "Feature",
  "properties": {
    "addr:full":"18041 Carmela Ct Lake Elsinore CA 92532",
    "addr:postcode":"18041;92532",
    "addr:street":"Carmela Ct",
    "iso:country":"US",
    "sg:address":"18041 Carmela Ct",
    "sg:city":"Lake Elsinore",
    "sg:classifiers":[
        {
            "category":"Building & Trades",
            "subcategory":"Cleaning & Sanitation",
            "type":"Services"
        },
        {
            "category":"Home & Garden",
            "subcategory":"Carpets & Floor Coverings",
            "type":"Retail Goods"
        }
    ],
    "sg:phone":"+1 951 775 4051",
    "sg:postcode":"92532",
    "sg:province":"CA",
    "sg:tags":[
        "carpeting"
    ],
    "sg:website":"flintscarpetcleaning.com",
    "wof:name":"Flint's Carpet Cleaning & Restoration",
    "wof:placetype":"venue"
},
  "geometry": {"coordinates":[-117.34618399999999,33.702362],"type":"Point"}
}