{
  "type": "Feature",
  "properties": {
    "addr:full":"6355 Pacific Blvd Huntington Park CA 90255",
    "addr:housenumber":"6355",
    "addr:postcode":"90255",
    "addr:street":"Pacific Blvd;Park",
    "iso:country":"US",
    "sg:address":"6355 Pacific Blvd",
    "sg:city":"Huntington Park",
    "sg:classifiers":[
        {
            "category":"Professional",
            "type":"Services"
        }
    ],
    "sg:phone":"+1 323 589 6719",
    "sg:postcode":"90255",
    "sg:province":"CA",
    "wof:name":"Lucia Colmenares",
    "wof:placetype":"venue"
},
  "geometry": {"coordinates":[-118.22525,33.982684],"type":"Point"}
}