{
  "type": "Feature",
  "properties": {
    "iso:country":"US",
    "sg:address":"3475 Investment Blvd",
    "sg:city":"Hayward",
    "sg:classifiers":[
        {
            "category":"Building & Trades",
            "subcategory":"Construction",
            "type":"Services"
        }
    ],
    "sg:phone":"+1 510 784 0610",
    "sg:postcode":"94545",
    "sg:province":"CA",
    "sg:tags":[
        "home",
        "improvement"
    ],
    "wof:name":"America's Home Imprvmt Pro",
    "wof:placetype":"venue"
},
  "geometry": {"coordinates":[-122.120637,37.62486],"type":"Point"}
}