{
  "type": "Feature",
  "properties": {
    "iso:country":"US",
    "sg:address":"2358 E Main St",
    "sg:city":"Ventura",
    "sg:classifiers":[
        {
            "category":"Shopping",
            "subcategory":"Tobacco",
            "type":"Retail Goods"
        }
    ],
    "sg:phone":"+1 805 653 5914",
    "sg:postcode":"93003",
    "sg:province":"CA",
    "sg:tags":[
        "shop",
        "smoke",
        "supply"
    ],
    "wof:name":"Tony's Smokeshop",
    "wof:placetype":"venue"
},
  "geometry": {"coordinates":[-119.265083,34.276386],"type":"Point"}
}