{
  "type": "Feature",
  "properties": {
    "addr:full":"842 S Broadway Los Angeles CA 90014",
    "addr:housenumber":"842",
    "addr:postcode":"90014",
    "addr:street":"S Broadway",
    "iso:country":"US",
    "sg:address":"842 S Broadway",
    "sg:city":"Los Angeles",
    "sg:classifiers":[
        {
            "category":"Health Services",
            "subcategory":"Optometrist",
            "type":"Services"
        }
    ],
    "sg:phone":"+1 213 627 9771",
    "sg:postcode":"90014",
    "sg:province":"CA",
    "wof:name":"Dr Harold Ross",
    "wof:placetype":"venue"
},
  "geometry": {"coordinates":[-118.25552399999999,34.042853],"type":"Point"}
}