{
  "type": "Feature",
  "properties": {
    "iso:country":"US",
    "sg:address":"41002 County Center Dr",
    "sg:city":"Temecula",
    "sg:classifiers":[
        {
            "category":"Government",
            "subcategory":"Office",
            "type":"Public Place"
        }
    ],
    "sg:phone":"+1 951 600 6400",
    "sg:postcode":"92591",
    "sg:province":"CA",
    "wof:name":"Riverside County Superior Ct",
    "wof:placetype":"venue"
},
  "geometry": {"coordinates":[-117.161244,33.52774],"type":"Point"}
}