{
  "type": "Feature",
  "properties": {
    "addr:full":"1513 S Curtis Ave Alhambra CA 91803",
    "addr:housenumber":"1513",
    "addr:postcode":"91803",
    "addr:street":"S Curtis Ave",
    "iso:country":"US",
    "sg:address":"1513 S Curtis Ave",
    "sg:city":"Alhambra",
    "sg:classifiers":[
        {
            "category":"Shopping",
            "subcategory":"Computers & Home Electronics",
            "type":"Retail Goods"
        }
    ],
    "sg:phone":"+1 626 584 7810",
    "sg:postcode":"91803",
    "sg:province":"CA",
    "sg:tags":[
        "software"
    ],
    "wof:name":"E-Sim",
    "wof:placetype":"venue"
},
  "geometry": {"coordinates":[-118.137227,34.076397],"type":"Point"}
}