{
  "type": "Feature",
  "properties": {
    "iso:country":"US",
    "sg:address":"670 N Arrowhead Ave",
    "sg:city":"San Bernardino",
    "sg:classifiers":[
        {
            "category":"Banks & Credit Unions",
            "subcategory":"Bank",
            "type":"Services"
        }
    ],
    "sg:phone":"+1 909 885 6531",
    "sg:postcode":"92401",
    "sg:province":"CA",
    "sg:tags":[
        "escrow"
    ],
    "wof:name":"Escrow Funding Svc",
    "wof:placetype":"venue"
},
  "geometry": {"coordinates":[-117.28975,34.110734],"type":"Point"}
}