{
  "type": "Feature",
  "properties": {
    "iso:country":"US",
    "sg:address":"6045 N Palm Ave",
    "sg:city":"Fresno",
    "sg:classifiers":[
        {
            "category":"Shopping",
            "subcategory":"Bicycles & Sporting Goods",
            "type":"Retail Goods"
        }
    ],
    "sg:phone":"+1 559 432 9535",
    "sg:postcode":"93704",
    "sg:province":"CA",
    "sg:tags":[
        "equipment",
        "tennis",
        "supply"
    ],
    "wof:name":"Stringer",
    "wof:placetype":"venue"
},
  "geometry": {"coordinates":[-119.808397,36.823863],"type":"Point"}
}