{
  "type": "Feature",
  "properties": {
    "addr:full":"4600 Fairfax Ave Oakland CA 94601",
    "addr:housenumber":"4600",
    "addr:postcode":"94601",
    "addr:street":"Fairfax Ave",
    "iso:country":"US",
    "sg:address":"4600 Fairfax Ave",
    "sg:city":"Oakland",
    "sg:classifiers":[
        {
            "category":"Health Services",
            "subcategory":"Clinic",
            "type":"Services"
        }
    ],
    "sg:phone":"+1 510 533 3083",
    "sg:postcode":"94601",
    "sg:province":"CA",
    "sg:tags":[
        "medical"
    ],
    "sg:website":"EvergreenEldercare.com",
    "wof:name":"Evergreen Eldercare",
    "wof:placetype":"venue"
},
  "geometry": {"coordinates":[-122.20500199999999,37.7799],"type":"Point"}
}