{
  "type": "Feature",
  "properties": {
    "iso:country":"US",
    "sg:address":"22469 Eden Canyon Rd",
    "sg:city":"Castro Valley",
    "sg:classifiers":[
        {
            "category":"Building & Trades",
            "subcategory":"Electrical",
            "type":"Services"
        }
    ],
    "sg:phone":"+1 510 733 6690",
    "sg:postcode":"94552",
    "sg:province":"CA",
    "sg:tags":[
        "electric",
        "contractor"
    ],
    "wof:name":"Ran Electric",
    "wof:placetype":"venue"
},
  "geometry": {"coordinates":[-121.994946,37.73021],"type":"Point"}
}