{
  "type": "Feature",
  "properties": {
    "addr:full":"301 25th Ave San Francisco CA 94121",
    "addr:housenumber":"301",
    "addr:postcode":"94121",
    "addr:street":"25Th Ave",
    "iso:country":"US",
    "sg:address":"301 25th Ave",
    "sg:city":"San Francisco",
    "sg:classifiers":[
        {
            "category":"Retail",
            "subcategory":"Auto Repair",
            "type":"Services"
        }
    ],
    "sg:phone":"+1 415 668 5953",
    "sg:postcode":"94121",
    "sg:province":"CA",
    "wof:name":"Manuel's Auto Repair",
    "wof:placetype":"venue"
},
  "geometry": {"coordinates":[-122.485173,37.78387],"type":"Point"}
}