{
  "type": "Feature",
  "properties": {
    "addr:full":"5920 Oakport Street Oakland CA 94601",
    "addr:housenumber":"5920",
    "addr:postcode":"94601",
    "addr:street":"Oakport Street",
    "iso:country":"US",
    "sg:address":"5920 Oakport Street",
    "sg:city":"Oakland",
    "sg:classifiers":[
        {
            "category":"Home & Garden",
            "subcategory":"Garden Supply",
            "type":"Retail Goods"
        }
    ],
    "sg:phone":"+1 510 886 5369",
    "sg:postcode":"94601",
    "sg:province":"CA",
    "sg:tags":[
        "nursery",
        "gardening"
    ],
    "sg:website":"santascoliseum.com/",
    "wof:name":"Santa's Coliseum",
    "wof:placetype":"venue"
},
  "geometry": {"coordinates":[-122.21160500000001,37.757281],"type":"Point"}
}