{
  "type": "Feature",
  "properties": {
    "addr:full":"2363 Mariner Square Dr Ste 141 Alameda CA 94501",
    "addr:housenumber":"2363",
    "addr:postcode":"94501",
    "addr:street":"Mariner Square Dr Ste 141",
    "iso:country":"US",
    "sg:address":"2363 Mariner Square Dr Ste 141",
    "sg:city":"Alameda",
    "sg:classifiers":[
        {
            "category":"Banks & Credit Unions",
            "subcategory":"Financial Services",
            "type":"Services"
        }
    ],
    "sg:phone":"+1 510 521 0300",
    "sg:postcode":"94501",
    "sg:province":"CA",
    "sg:tags":[
        "broker",
        "mortgage"
    ],
    "sg:website":"calrealestatefinance.com",
    "wof:name":"California Real Estate Finance",
    "wof:placetype":"venue"
},
  "geometry": {"coordinates":[-122.276661,37.788488],"type":"Point"}
}