{
  "type": "Feature",
  "properties": {
    "iso:country":"US",
    "sg:address":"27550 Newhall Ranch Rd Ste 203",
    "sg:city":"Valencia",
    "sg:classifiers":[
        {
            "category":"Banks & Credit Unions",
            "subcategory":"Bank",
            "type":"Services"
        }
    ],
    "sg:postcode":"91355",
    "sg:province":"CA",
    "wof:name":"Premier America Credit Union",
    "wof:placetype":"venue"
},
  "geometry": {"coordinates":[-118.563253,34.436843],"type":"Point"}
}