{
  "type": "Feature",
  "properties": {
    "addr:full":"955 S 6th St Unit 3105 San Jose CA 95112",
    "addr:housenumber":"955;3105",
    "addr:postcode":"95112",
    "addr:street":"S 6Th St Unit",
    "iso:country":"US",
    "sg:address":"955 S 6th St Unit 3105",
    "sg:city":"San Jose",
    "sg:classifiers":[
        {
            "category":"Real Estate",
            "subcategory":"Real Estate Operator",
            "type":"Services"
        }
    ],
    "sg:phone":"+1 408 280 1520",
    "sg:postcode":"95112",
    "sg:province":"CA",
    "sg:tags":[
        "apartment"
    ],
    "wof:name":"Ca Real Estate Villa Torre Phase II",
    "wof:placetype":"venue"
},
  "geometry": {"coordinates":[-121.87400100000001,37.3242],"type":"Point"}
}