{
  "type": "Feature",
  "properties": {
    "addr:full":"14180 E Firestone Blvd Whittier CA 90601",
    "addr:housenumber":"14180",
    "addr:postcode":"90601",
    "addr:street":"E Firestone Blvd",
    "iso:country":"US",
    "sg:address":"14180 E Firestone Blvd",
    "sg:city":"Whittier",
    "sg:classifiers":[
        {
            "category":"Building & Trades",
            "subcategory":"Construction",
            "type":"Services"
        }
    ],
    "sg:phone":"+1 562 404 8686",
    "sg:postcode":"90601",
    "sg:province":"CA",
    "sg:tags":[
        "painter"
    ],
    "wof:name":"PS Painting",
    "wof:placetype":"venue"
},
  "geometry": {"coordinates":[-118.04499800000001,33.996201],"type":"Point"}
}