{
  "type": "Feature",
  "properties": {
    "addr:full":"7227 Whitsett Ave North Hollywood CA 91605",
    "addr:housenumber":"7227",
    "addr:postcode":"91605",
    "addr:street":"Whitsett Ave",
    "iso:country":"US",
    "sg:address":"7227 Whitsett Ave",
    "sg:city":"North Hollywood",
    "sg:classifiers":[
        {
            "category":"Home & Garden",
            "subcategory":"Carpets & Floor Coverings",
            "type":"Retail Goods"
        }
    ],
    "sg:phone":"+1 818 982 0485",
    "sg:postcode":"91605",
    "sg:province":"CA",
    "wof:name":"Big D Floor Covering Supplies",
    "wof:placetype":"venue"
},
  "geometry": {"coordinates":[-118.405168,34.201195],"type":"Point"}
}