{
  "type": "Feature",
  "properties": {
    "iso:country":"US",
    "sg:address":"537 N Western Ave",
    "sg:city":"Los Angeles",
    "sg:classifiers":[
        {
            "category":"Sports & Exercise",
            "subcategory":"Golf",
            "type":"Entertainment"
        }
    ],
    "sg:phone":"+1 323 466 1131",
    "sg:postcode":"90004",
    "sg:province":"CA",
    "sg:website":"www.facebook.com/pages/Los-Angel...",
    "wof:name":"Western Golf College & Driving Range",
    "wof:placetype":"venue"
},
  "geometry": {"coordinates":[-118.30950900000001,34.080945],"type":"Point"}
}