{
  "type": "Feature",
  "properties": {
    "addr:full":"9 China Aly Hanford CA 93230",
    "addr:housenumber":"9",
    "addr:postcode":"ca 93230",
    "addr:street":"China Aly",
    "iso:country":"US",
    "sg:address":"9 China Aly",
    "sg:city":"Hanford",
    "sg:classifiers":[
        {
            "category":"Health Services",
            "subcategory":"Doctor",
            "type":"Services"
        },
        {
            "category":"Health Services",
            "subcategory":"Health Practitioner",
            "type":"Services"
        }
    ],
    "sg:phone":"+1 559 584 8100",
    "sg:postcode":"93230",
    "sg:province":"CA",
    "sg:tags":[
        "physician",
        "surgeons",
        "drug",
        "abuse",
        "medicine",
        "addiction"
    ],
    "wof:name":"Westcare",
    "wof:placetype":"venue"
},
  "geometry": {"coordinates":[-119.640912,36.327694],"type":"Point"}
}