{
  "type": "Feature",
  "properties": {
    "addr:full":"911 Cll Angosta Thousand Oaks CA 91360",
    "addr:housenumber":"911",
    "addr:postcode":"91360",
    "addr:street":"Cll Angosta",
    "iso:country":"US",
    "sg:address":"911 Cll Angosta",
    "sg:city":"Thousand Oaks",
    "sg:classifiers":[
        {
            "category":"Manufacturing",
            "subcategory":"Food",
            "type":"Manufacturing & Wholesale Goods"
        }
    ],
    "sg:phone":"+1 805 492 4921",
    "sg:postcode":"91360",
    "sg:province":"CA",
    "sg:tags":[
        "frozen",
        "specialty",
        "mfg"
    ],
    "wof:name":"Specialty Brands",
    "wof:placetype":"venue"
},
  "geometry": {"coordinates":[-118.903133,34.203144],"type":"Point"}
}