{
  "type": "Feature",
  "properties": {
    "addr:full":"1231 W March Ln Stockton CA 95207",
    "addr:housenumber":"1231",
    "addr:postcode":"95207",
    "addr:street":"W March Ln",
    "iso:country":"US",
    "sg:address":"1231 W March Ln",
    "sg:city":"Stockton",
    "sg:classifiers":[
        {
            "category":"Restaurant",
            "type":"Food & Drink"
        }
    ],
    "sg:menulink":"http://www.allmenus.com/ca/stockton/54060-ho-ho-express/menu/",
    "sg:phone":"+1 209 474 2211",
    "sg:postcode":"95207",
    "sg:province":"CA",
    "sg:tags":[
        "asian",
        "chinese"
    ],
    "wof:name":"Ho Ho Express",
    "wof:placetype":"venue"
},
  "geometry": {"coordinates":[-121.31993,37.989582],"type":"Point"}
}