{
  "type": "Feature",
  "properties": {
    "iso:country":"US",
    "sg:address":"2400 Ridge Rd",
    "sg:city":"Berkeley",
    "sg:classifiers":[
        {
            "category":"Education",
            "subcategory":"University",
            "type":"Public Place"
        },
        {
            "category":"Organizations",
            "subcategory":"Religious Organization",
            "type":"Services"
        }
    ],
    "sg:phone":"+1 510 649 2500",
    "sg:postcode":"94709",
    "sg:province":"CA",
    "sg:tags":[
        "college"
    ],
    "sg:website":"www.gtu.edu",
    "wof:name":"Graduate Theological Union",
    "wof:placetype":"venue"
},
  "geometry": {"coordinates":[-122.262439,37.876236],"type":"Point"}
}