{
  "type": "Feature",
  "properties": {
    "iso:country":"US",
    "sg:address":"17536 Elizabeth Lake Rd",
    "sg:city":"Lake Hughes",
    "sg:classifiers":[
        {
            "category":"Real Estate",
            "subcategory":"Real Estate Agent",
            "type":"Services"
        }
    ],
    "sg:phone":"+1 661 724 2592",
    "sg:postcode":"93532",
    "sg:province":"CA",
    "sg:website":"www.pjdehaasproperties.com",
    "wof:name":"P J De Haas Properties",
    "wof:placetype":"venue"
},
  "geometry": {"coordinates":[-118.440333,34.674895],"type":"Point"}
}