{
  "type": "Feature",
  "properties": {
    "addr:full":"820 Veterans Blvd Redwood City CA 94063",
    "addr:housenumber":"820",
    "addr:postcode":"94063",
    "addr:street":"Veterans Blvd",
    "iso:country":"US",
    "sg:address":"820 Veterans Blvd",
    "sg:city":"Redwood City",
    "sg:classifiers":[
        {
            "category":"Restaurant",
            "type":"Food & Drink"
        }
    ],
    "sg:phone":"+1 650 364 7848",
    "sg:postcode":"94063",
    "sg:province":"CA",
    "wof:name":"El Molino Taqueria",
    "wof:placetype":"venue"
},
  "geometry": {"coordinates":[-122.22870500000001,37.490399],"type":"Point"}
}