{
  "type": "Feature",
  "properties": {
    "iso:country":"US",
    "sg:address":"1604 S Hacienda Blvd",
    "sg:city":"Hacienda Heights",
    "sg:classifiers":[
        {
            "category":"Wholesale",
            "subcategory":"Home Furnishings",
            "type":"Manufacturing & Wholesale Goods"
        }
    ],
    "sg:phone":"+1 626 968 2264",
    "sg:postcode":"91745",
    "sg:province":"CA",
    "wof:name":"Leisure Pacific",
    "wof:placetype":"venue"
},
  "geometry": {"coordinates":[-117.965785,34.002451],"type":"Point"}
}