{
  "type": "Feature",
  "properties": {
    "addr:full":"3708 Bayshore Blvd Brisbane CA 94005",
    "addr:housenumber":"3708",
    "addr:postcode":"94005",
    "addr:street":"Bayshore Blvd",
    "iso:country":"US",
    "sg:address":"3708 Bayshore Blvd",
    "sg:city":"Brisbane",
    "sg:classifiers":[
        {
            "category":"Building & Trades",
            "subcategory":"Construction",
            "type":"Services"
        }
    ],
    "sg:phone":"+1 415 467 9000",
    "sg:postcode":"94005",
    "sg:province":"CA",
    "sg:tags":[
        "restoration",
        "cleaning",
        "patio",
        "deck"
    ],
    "wof:name":"Fried Service Co",
    "wof:placetype":"venue"
},
  "geometry": {"coordinates":[-122.394593,37.681011],"type":"Point"}
}