{
  "type": "Feature",
  "properties": {
    "addr:full":"18071 Irvine Blvd Tustin CA 92780",
    "addr:housenumber":"18071",
    "addr:postcode":"92780",
    "addr:street":"Irvine Blvd",
    "iso:country":"US",
    "sg:address":"18071 Irvine Blvd",
    "sg:city":"Tustin",
    "sg:classifiers":[
        {
            "category":"Real Estate",
            "subcategory":"Architect",
            "type":"Services"
        }
    ],
    "sg:phone":"+1 714 832 5100",
    "sg:postcode":"92780",
    "sg:province":"CA",
    "sg:website":"www.pacificdesigngroup.com",
    "wof:name":"Pacific Design Group",
    "wof:placetype":"venue"
},
  "geometry": {"coordinates":[-117.818001,33.748402],"type":"Point"}
}