{
  "type": "Feature",
  "properties": {
    "addr:full":"2131 Cross St La Canada Flintridge CA 91011",
    "addr:housenumber":"2131",
    "addr:postcode":"91011",
    "addr:street":"Cross St",
    "iso:country":"US",
    "sg:address":"2131 Cross St",
    "sg:city":"La Canada Flintridge",
    "sg:classifiers":[
        {
            "category":"Building & Trades",
            "subcategory":"Construction",
            "type":"Services"
        }
    ],
    "sg:phone":"+1 818 249 1073",
    "sg:postcode":"91011",
    "sg:province":"CA",
    "sg:tags":[
        "contractor"
    ],
    "wof:name":"R P M Construction",
    "wof:placetype":"venue"
},
  "geometry": {"coordinates":[-118.223232,34.221566],"type":"Point"}
}