{
  "type": "Feature",
  "properties": {
    "iso:country":"US",
    "sg:address":"14549 Victory Blvd",
    "sg:city":"Van Nuys",
    "sg:classifiers":[
        {
            "category":"Shopping",
            "type":"Retail Goods"
        }
    ],
    "sg:phone":"+1 818 785 6026",
    "sg:postcode":"91411",
    "sg:province":"CA",
    "sg:tags":[
        "telephone",
        "cellular"
    ],
    "wof:name":"Simply Mobile",
    "wof:placetype":"venue"
},
  "geometry": {"coordinates":[-118.450014,34.186735],"type":"Point"}
}