{
  "type": "Feature",
  "properties": {
    "iso:country":"US",
    "sg:address":"579 Floresta Blvd Ste H",
    "sg:city":"San Leandro",
    "sg:classifiers":[
        {
            "category":"Personal",
            "subcategory":"Tanning Parlor",
            "type":"Services"
        }
    ],
    "sg:phone":"+1 510 346 8267",
    "sg:postcode":"94578",
    "sg:province":"CA",
    "sg:website":"www.goldandbare.com",
    "wof:name":"Gold & Bare Tanning",
    "wof:placetype":"venue"
},
  "geometry": {"coordinates":[-122.143833,37.701203],"type":"Point"}
}