{
  "type": "Feature",
  "properties": {
    "addr:full":"22665 Califa St Woodland Hills CA 91367",
    "addr:housenumber":"22665",
    "addr:postcode":"91367",
    "addr:street":"Califa St",
    "iso:country":"US",
    "sg:address":"22665 Califa St",
    "sg:city":"Woodland Hills",
    "sg:classifiers":[
        {
            "category":"Professional",
            "type":"Services"
        }
    ],
    "sg:phone":"+1 818 346 7260",
    "sg:postcode":"91367",
    "sg:province":"CA",
    "sg:tags":[
        "arts",
        "artist"
    ],
    "wof:name":"Lentz Designs",
    "wof:placetype":"venue"
},
  "geometry": {"coordinates":[-118.621472,34.177444],"type":"Point"}
}