{
  "type": "Feature",
  "properties": {
    "addr:full":"26490 Dustin Rd Acampo CA 95220",
    "addr:postcode":"26490;95220",
    "addr:street":"Dustin Rd",
    "iso:country":"US",
    "sg:address":"26490 Dustin Rd",
    "sg:city":"Acampo",
    "sg:classifiers":[
        {
            "category":"Farming",
            "subcategory":"Livestock Farm",
            "type":"Manufacturing & Wholesale Goods"
        }
    ],
    "sg:phone":"+1 209 369 6187",
    "sg:postcode":"95220",
    "sg:province":"CA",
    "sg:tags":[
        "animal",
        "general"
    ],
    "wof:name":"Sky Ranch",
    "wof:placetype":"venue"
},
  "geometry": {"coordinates":[-121.22662099999999,38.229887],"type":"Point"}
}