{
  "type": "Feature",
  "properties": {
    "addr:full":"22359 Meekland AVE Hayward CA 94541",
    "addr:postcode":"22359;94541",
    "addr:street":"Meekland Ave",
    "iso:country":"US",
    "sg:address":"22359 Meekland AVE",
    "sg:city":"Hayward",
    "sg:classifiers":[
        {
            "category":"Retail",
            "subcategory":"Auto Repair",
            "type":"Services"
        }
    ],
    "sg:phone":"+1 510 258 4505",
    "sg:postcode":"94541",
    "sg:province":"CA",
    "wof:name":"EJ'S Auto Repair",
    "wof:placetype":"venue"
},
  "geometry": {"coordinates":[-122.101209,37.668158],"type":"Point"}
}