{
  "type": "Feature",
  "properties": {
    "iso:country":"US",
    "sg:address":"502 Lincoln St",
    "sg:city":"Calexico",
    "sg:classifiers":[
        {
            "category":"Home & Garden",
            "subcategory":"Carpets & Floor Coverings",
            "type":"Retail Goods"
        }
    ],
    "sg:phone":"+1 760 357 7929",
    "sg:postcode":"92231",
    "sg:province":"CA",
    "sg:tags":[
        "dealer",
        "rug"
    ],
    "wof:name":"M D Carpets",
    "wof:placetype":"venue"
},
  "geometry": {"coordinates":[-115.507654,32.675105],"type":"Point"}
}