{
  "type": "Feature",
  "properties": {
    "addr:full":"9950 Bell Ranch Dr Santa Fe Springs CA 90670",
    "addr:housenumber":"9950",
    "addr:postcode":"90670",
    "addr:street":"Bell Ranch Dr",
    "iso:country":"US",
    "sg:address":"9950 Bell Ranch Dr",
    "sg:city":"Santa Fe Springs",
    "sg:classifiers":[
        {
            "category":"Bus Station",
            "type":"Transportation"
        }
    ],
    "sg:phone":"+1 562 944 5975",
    "sg:postcode":"90670",
    "sg:province":"CA",
    "sg:tags":[
        "shuttle",
        "maintenance"
    ],
    "wof:name":"Media Maintenance Inc",
    "wof:placetype":"venue"
},
  "geometry": {"coordinates":[-118.063912,33.94752],"type":"Point"}
}