{
  "type": "Feature",
  "properties": {
    "addr:full":"11919 Pioneer Blvd Norwalk CA 90650",
    "addr:housenumber":"11919",
    "addr:postcode":"90650",
    "addr:street":"Pioneer Blvd",
    "iso:country":"US",
    "sg:address":"11919 Pioneer Blvd",
    "sg:city":"Norwalk",
    "sg:classifiers":[
        {
            "category":"Real Estate",
            "subcategory":"Real Estate Operator",
            "type":"Services"
        }
    ],
    "sg:phone":"+1 562 863 1473",
    "sg:postcode":"90650",
    "sg:province":"CA",
    "sg:tags":[
        "apartment"
    ],
    "wof:name":"Green Meadow Apartments",
    "wof:placetype":"venue"
},
  "geometry": {"coordinates":[-118.081873,33.922849],"type":"Point"}
}