{
  "type": "Feature",
  "properties": {
    "addr:full":"4027 Medford St Los Angeles CA 90063",
    "addr:housenumber":"4027",
    "addr:postcode":"90063",
    "addr:street":"Medford St",
    "iso:country":"US",
    "sg:address":"4027 Medford St",
    "sg:city":"Los Angeles",
    "sg:classifiers":[
        {
            "category":"Retail",
            "subcategory":"Auto Repair",
            "type":"Services"
        }
    ],
    "sg:phone":"+1 323 262 6209",
    "sg:postcode":"90063",
    "sg:province":"CA",
    "sg:tags":[
        "body",
        "automobile",
        "painting"
    ],
    "wof:name":"Frank's Body Shop",
    "wof:placetype":"venue"
},
  "geometry": {"coordinates":[-118.179919,34.060899],"type":"Point"}
}