{
  "type": "Feature",
  "properties": {
    "addr:full":"527 Stevenson St Vacaville CA 95688",
    "addr:housenumber":"527",
    "addr:postcode":"95688",
    "addr:street":"Stevenson St",
    "iso:country":"US",
    "sg:address":"527 Stevenson St",
    "sg:city":"Vacaville",
    "sg:classifiers":[
        {
            "category":"Personal",
            "subcategory":"Tattoo Parlor",
            "type":"Services"
        }
    ],
    "sg:phone":"+1 707 446 1850",
    "sg:postcode":"95688",
    "sg:province":"CA",
    "sg:tags":[
        "tattooing"
    ],
    "wof:name":"Chris P Tooles Tattoo Inc",
    "wof:placetype":"venue"
},
  "geometry": {"coordinates":[-121.98660700000001,38.353981],"type":"Point"}
}