{
  "type": "Feature",
  "properties": {
    "iso:country":"US",
    "sg:address":"1247 Lincoln Blvd",
    "sg:city":"Santa Monica",
    "sg:classifiers":[
        {
            "category":"Professional",
            "subcategory":"Business Services",
            "type":"Services"
        }
    ],
    "sg:phone":"+1 310 656 7878",
    "sg:postcode":"90401",
    "sg:province":"CA",
    "sg:tags":[
        "messenger"
    ],
    "wof:name":"Excel Messenger",
    "wof:placetype":"venue"
},
  "geometry": {"coordinates":[-118.493543,34.021537],"type":"Point"}
}