{
  "type": "Feature",
  "properties": {
    "iso:country":"US",
    "sg:address":"10418 S Prairie Avenue",
    "sg:city":"Inglewood",
    "sg:classifiers":[
        {
            "category":"Shopping",
            "subcategory":"Mobile Phones",
            "type":"Retail Goods"
        }
    ],
    "sg:phone":"+1 310 674 6990",
    "sg:postcode":"90303",
    "sg:province":"CA",
    "wof:name":"A & G Cellular 2",
    "wof:placetype":"venue"
},
  "geometry": {"coordinates":[-118.331007,33.935799],"type":"Point"}
}