{
  "type": "Feature",
  "properties": {
    "addr:full":"425 S Flower St Orange CA 92868",
    "addr:housenumber":"425",
    "addr:postcode":"92868",
    "addr:street":"S Flower St",
    "iso:country":"US",
    "sg:address":"425 S Flower St",
    "sg:city":"Orange",
    "sg:classifiers":[
        {
            "category":"Professional",
            "subcategory":"Printing & Photocopies",
            "type":"Services"
        }
    ],
    "sg:phone":"+1 714 997 2350",
    "sg:postcode":"92868",
    "sg:province":"CA",
    "wof:name":"Orange Coast Copier",
    "wof:placetype":"venue"
},
  "geometry": {"coordinates":[-117.87599899999999,33.781799],"type":"Point"}
}