{
  "type": "Feature",
  "properties": {
    "iso:country":"US",
    "sg:address":"18628 Seneca Rd",
    "sg:city":"Apple Valley",
    "sg:classifiers":[
        {
            "category":"Organizations",
            "subcategory":"Religious Organization",
            "type":"Services"
        }
    ],
    "sg:phone":"+1 760 242 3191",
    "sg:postcode":"92307",
    "sg:province":"CA",
    "sg:tags":[
        "church"
    ],
    "sg:website":"www.fullgospelchurch.info",
    "wof:name":"Full Gospel Church",
    "wof:placetype":"venue"
},
  "geometry": {"coordinates":[-117.256548,34.514881],"type":"Point"}
}