{
  "type": "Feature",
  "properties": {
    "addr:full":"8442 Santa Monica Blvd West Hollywood CA 90069",
    "addr:housenumber":"8442",
    "addr:postcode":"90069",
    "addr:street":"Santa Monica Blvd",
    "iso:country":"US",
    "sg:address":"8442 Santa Monica Blvd",
    "sg:city":"West Hollywood",
    "sg:classifiers":[
        {
            "category":"Cinema",
            "subcategory":"Movie Rental",
            "type":"Entertainment"
        },
        {
            "category":"Animal Shelter",
            "type":"Public Place"
        }
    ],
    "sg:phone":"+1 323 848 6970",
    "sg:postcode":"90069",
    "sg:province":"CA",
    "sg:tags":[
        "game",
        "video",
        "adult"
    ],
    "sg:website":"www.grandopening.com",
    "wof:name":"Grand Opening!",
    "wof:placetype":"venue"
},
  "geometry": {"coordinates":[-118.375,34.0905],"type":"Point"}
}