{
  "type": "Feature",
  "properties": {
    "addr:full":"312 S Roselawn Ave Turlock CA 95380",
    "addr:housenumber":"312",
    "addr:postcode":"95380",
    "addr:street":"S Roselawn Ave",
    "iso:country":"US",
    "sg:address":"312 S Roselawn Ave",
    "sg:city":"Turlock",
    "sg:classifiers":[
        {
            "category":"Education",
            "subcategory":"School",
            "type":"Public Place"
        }
    ],
    "sg:phone":"+1 209 634 9311",
    "sg:postcode":"95380",
    "sg:province":"CA",
    "wof:name":"Roselawn High School",
    "wof:placetype":"venue"
},
  "geometry": {"coordinates":[-120.79868500000001,37.491261],"type":"Point"}
}