{
  "type": "Feature",
  "properties": {
    "addr:full":"5595 Winfield Blvd San Jose CA 95123",
    "addr:housenumber":"5595",
    "addr:postcode":"95123",
    "addr:street":"Winfield Blvd",
    "iso:country":"US",
    "sg:address":"5595 Winfield Blvd",
    "sg:city":"San Jose",
    "sg:classifiers":[
        {
            "category":"Professional",
            "subcategory":"Lawyer & Legal Services",
            "type":"Services"
        }
    ],
    "sg:phone":"+1 408 281 8909",
    "sg:postcode":"95123",
    "sg:province":"CA",
    "wof:name":"Pope John Attorney At Law",
    "wof:placetype":"venue"
},
  "geometry": {"coordinates":[-121.866997,37.253399],"type":"Point"}
}