{
  "type": "Feature",
  "properties": {
    "addr:full":"1111 Bailey Ave Needles CA 92363",
    "addr:housenumber":"1111",
    "addr:postcode":"92363",
    "addr:street":"Bailey Ave",
    "iso:country":"US",
    "sg:address":"1111 Bailey Ave",
    "sg:city":"Needles",
    "sg:classifiers":[
        {
            "category":"Social Services",
            "type":"Services"
        }
    ],
    "sg:phone":"+1 760 326 9244",
    "sg:postcode":"92363",
    "sg:province":"CA",
    "sg:tags":[
        "probation"
    ],
    "wof:name":"Probation Dept",
    "wof:placetype":"venue"
},
  "geometry": {"coordinates":[-114.618212,34.835612],"type":"Point"}
}