{
  "type": "Feature",
  "properties": {
    "addr:full":"616 W Cutting Blvd Richmond CA 94804",
    "addr:housenumber":"616",
    "addr:postcode":"94804",
    "addr:street":"W Cutting Blvd",
    "iso:country":"US",
    "sg:address":"616 W Cutting Blvd",
    "sg:city":"Richmond",
    "sg:classifiers":[
        {
            "category":"Recreation",
            "subcategory":"Marina",
            "type":"Entertainment"
        }
    ],
    "sg:phone":"+1 510 232 5800",
    "sg:postcode":"94804",
    "sg:province":"CA",
    "sg:tags":[
        "repairing",
        "boat"
    ],
    "sg:website":"www.kkmi.com",
    "wof:name":"Richmond Boat Works",
    "wof:placetype":"venue"
},
  "geometry": {"coordinates":[-122.374364,37.925193],"type":"Point"}
}