{
  "type": "Feature",
  "properties": {
    "addr:full":"341 N N St Lompoc CA 93436",
    "addr:housenumber":"341",
    "addr:postcode":"93436",
    "addr:street":"N N",
    "iso:country":"US",
    "sg:address":"341 N N St",
    "sg:city":"Lompoc",
    "sg:classifiers":[
        {
            "category":"Social Services",
            "subcategory":"Adult Care",
            "type":"Services"
        }
    ],
    "sg:phone":"+1 805 736 6669",
    "sg:postcode":"93436",
    "sg:province":"CA",
    "sg:tags":[
        "organization",
        "senior",
        "citizen"
    ],
    "wof:name":"Valley Of Flowers Half Century",
    "wof:placetype":"venue"
},
  "geometry": {"coordinates":[-120.46554399999999,34.642954],"type":"Point"}
}