{
  "type": "Feature",
  "properties": {
    "iso:country":"US",
    "sg:address":"3732 W Century Blvd",
    "sg:city":"Inglewood",
    "sg:classifiers":[
        {
            "category":"Wholesale",
            "subcategory":"Non-durable Goods",
            "type":"Manufacturing & Wholesale Goods"
        }
    ],
    "sg:phone":"+1 310 677 7688",
    "sg:postcode":"90303",
    "sg:province":"CA",
    "wof:name":"South Pacific Imports",
    "wof:placetype":"venue"
},
  "geometry": {"coordinates":[-118.33673,33.945389],"type":"Point"}
}