{
  "type": "Feature",
  "properties": {
    "addr:full":"21651 Sharp Rd Perris CA 92570",
    "addr:housenumber":"21651",
    "addr:postcode":"92570",
    "addr:street":"Sharp Rd",
    "iso:country":"US",
    "sg:address":"21651 Sharp Rd",
    "sg:city":"Perris",
    "sg:classifiers":[
        {
            "category":"Farming",
            "subcategory":"Farm",
            "type":"Manufacturing & Wholesale Goods"
        }
    ],
    "sg:phone":"+1 951 346 6996",
    "sg:postcode":"92570",
    "sg:province":"CA",
    "wof:name":"Rancho Los Pirules",
    "wof:placetype":"venue"
},
  "geometry": {"coordinates":[-117.281914,33.753534],"type":"Point"}
}