{
  "type": "Feature",
  "properties": {
    "iso:country":"US",
    "sg:address":"4850 Marshall Rd",
    "sg:city":"Garden Valley",
    "sg:classifiers":[
        {
            "category":"Government",
            "subcategory":"Post Office",
            "type":"Public Place"
        }
    ],
    "sg:phone":"+1 530 333 4828",
    "sg:postcode":"95633",
    "sg:province":"CA",
    "wof:name":"US Post Office",
    "wof:placetype":"venue"
},
  "geometry": {"coordinates":[-120.85560599999999,38.855575],"type":"Point"}
}