{
  "type": "Feature",
  "properties": {
    "iso:country":"US",
    "sg:address":"1030 E el Camino Real",
    "sg:city":"Sunnyvale",
    "sg:classifiers":[
        {
            "category":"Shopping",
            "subcategory":"Computers & Home Electronics",
            "type":"Retail Goods"
        }
    ],
    "sg:phone":"+1 408 523 9990",
    "sg:postcode":"94087",
    "sg:province":"CA",
    "sg:tags":[
        "software"
    ],
    "wof:name":"Crew Software Inc",
    "wof:placetype":"venue"
},
  "geometry": {"coordinates":[-122.007589,37.352031],"type":"Point"}
}