{
  "type": "Feature",
  "properties": {
    "iso:country":"US",
    "sg:address":"236 S Halcyon Rd",
    "sg:city":"Arroyo Grande",
    "sg:classifiers":[
        {
            "category":"Health Services",
            "subcategory":"Doctor",
            "type":"Services"
        }
    ],
    "sg:phone":"+1 805 489 1495",
    "sg:postcode":"93420",
    "sg:province":"CA",
    "sg:tags":[
        "dentist"
    ],
    "wof:name":"Jeffrey L Williams DDS",
    "wof:placetype":"venue"
},
  "geometry": {"coordinates":[-120.591641,35.115809],"type":"Point"}
}