{
  "type": "Feature",
  "properties": {
    "addr:full":"127 N Thesta St Fresno CA 93701",
    "addr:housenumber":"127",
    "addr:postcode":"93701",
    "addr:street":"N Thesta St",
    "iso:country":"US",
    "sg:address":"127 N Thesta St",
    "sg:city":"Fresno",
    "sg:classifiers":[
        {
            "category":"Health Services",
            "subcategory":"Medical Lab",
            "type":"Services"
        }
    ],
    "sg:phone":"+1 559 459 6059",
    "sg:postcode":"93701",
    "sg:province":"CA",
    "wof:name":"Community Regional Medica",
    "wof:placetype":"venue"
},
  "geometry": {"coordinates":[-119.783736,36.743777],"type":"Point"}
}