{
  "type": "Feature",
  "properties": {
    "addr:full":"245 San Bernadino Ct Pittsburg CA 94565",
    "addr:housenumber":"245",
    "addr:postcode":"94565",
    "addr:street":"San Bernadino Ct",
    "iso:country":"US",
    "sg:address":"245 San Bernadino Ct",
    "sg:city":"Pittsburg",
    "sg:classifiers":[
        {
            "category":"Freight",
            "type":"Transportation"
        }
    ],
    "sg:phone":"+1 925 458 0178",
    "sg:postcode":"94565",
    "sg:province":"CA",
    "sg:tags":[
        "operator",
        "local",
        "trucking"
    ],
    "wof:name":"Batres Trucking",
    "wof:placetype":"venue"
},
  "geometry": {"coordinates":[-121.96190199999999,38.028213],"type":"Point"}
}