{
  "type": "Feature",
  "properties": {
    "addr:full":"3375 Foothill Rd Unit 731 Carpinteria CA 93013",
    "addr:housenumber":"3375;731",
    "addr:postcode":"93013",
    "addr:street":"Foothill Rd Unit",
    "iso:country":"US",
    "sg:address":"3375 Foothill Rd Unit 731",
    "sg:city":"Carpinteria",
    "sg:classifiers":[
        {
            "category":"Manufacturing",
            "subcategory":"Rubber & Plastics",
            "type":"Manufacturing & Wholesale Goods"
        },
        {
            "category":"Autos & Motor Vehicles",
            "subcategory":"Auto Supplies",
            "type":"Retail Goods"
        }
    ],
    "sg:phone":"+1 805 566 6666",
    "sg:postcode":"93013",
    "sg:province":"CA",
    "sg:tags":[
        "tires-wholesale",
        "tire",
        "manufacturer"
    ],
    "wof:name":"Stratford & Associates Inc",
    "wof:placetype":"venue"
},
  "geometry": {"coordinates":[-119.560951,34.42046],"type":"Point"}
}