{
  "type": "Feature",
  "properties": {
    "iso:country":"US",
    "sg:address":"12241 10th St",
    "sg:city":"Yucaipa",
    "sg:classifiers":[
        {
            "category":"Professional",
            "subcategory":"Management & Consulting",
            "type":"Services"
        }
    ],
    "sg:phone":"+1 909 797 3098",
    "sg:postcode":"92399",
    "sg:province":"CA",
    "sg:tags":[
        "retail",
        "direct",
        "sales"
    ],
    "wof:name":"Mac Tools",
    "wof:placetype":"venue"
},
  "geometry": {"coordinates":[-117.077596,34.032387],"type":"Point"}
}