{
  "type": "Feature",
  "properties": {
    "iso:country":"US",
    "sg:address":"1680 Vine Street",
    "sg:city":"Los Angeles",
    "sg:classifiers":[
        {
            "category":"Professional",
            "subcategory":"Lawyer & Legal Services",
            "type":"Services"
        }
    ],
    "sg:phone":"+1 323 463 8355",
    "sg:postcode":"90028",
    "sg:province":"CA",
    "wof:name":"Schiowitz Connor Ankrum Wolf",
    "wof:placetype":"venue"
},
  "geometry": {"coordinates":[-118.326648,34.101174],"type":"Point"}
}