{
  "type": "Feature",
  "properties": {
    "iso:country":"US",
    "sg:address":"12726 Putnam St",
    "sg:city":"Whittier",
    "sg:classifiers":[
        {
            "category":"Building & Trades",
            "subcategory":"Pest Control",
            "type":"Services"
        }
    ],
    "sg:phone":"+1 562 698 7731",
    "sg:postcode":"90602",
    "sg:province":"CA",
    "wof:name":"San Martin Termite Control",
    "wof:placetype":"venue"
},
  "geometry": {"coordinates":[-118.041608,33.964943],"type":"Point"}
}