{
  "type": "Feature",
  "properties": {
    "addr:full":"252 N El Camino Real Ste 3 Encinitas CA 92024",
    "addr:housenumber":"252",
    "addr:postcode":"92024",
    "addr:street":"N El Camino Real Ste 3",
    "iso:country":"US",
    "sg:address":"252 N El Camino Real Ste 3",
    "sg:city":"Encinitas",
    "sg:classifiers":[
        {
            "category":"Retail",
            "subcategory":"Laundry & Dry Cleaning",
            "type":"Services"
        }
    ],
    "sg:phone":"+1 760 942 3425",
    "sg:postcode":"92024",
    "sg:province":"CA",
    "wof:name":"Plaza Cleaners",
    "wof:placetype":"venue"
},
  "geometry": {"coordinates":[-117.261002,33.051998],"type":"Point"}
}