{
  "type": "Feature",
  "properties": {
    "iso:country":"US",
    "sg:address":"7444 Florence Avenue",
    "sg:city":"Downey",
    "sg:classifiers":[
        {
            "category":"Real Estate",
            "subcategory":"Real Estate Services",
            "type":"Services"
        }
    ],
    "sg:phone":"+1 562 927 4404",
    "sg:postcode":"90240",
    "sg:province":"CA",
    "sg:tags":[
        "management",
        "property"
    ],
    "wof:name":"Tri Delta Management L P",
    "wof:placetype":"venue"
},
  "geometry": {"coordinates":[-118.11194999999999,33.944843],"type":"Point"}
}