{
  "type": "Feature",
  "properties": {
    "iso:country":"US",
    "sg:address":"700 Fair Oaks Ave",
    "sg:city":"South Pasadena",
    "sg:classifiers":[
        {
            "category":"Personal",
            "subcategory":"Nail Salon",
            "type":"Services"
        }
    ],
    "sg:phone":"+1 626 441 8141",
    "sg:postcode":"91030",
    "sg:province":"CA",
    "wof:name":"Krissy's Nails",
    "wof:placetype":"venue"
},
  "geometry": {"coordinates":[-118.150002,34.118301],"type":"Point"}
}