{
  "type": "Feature",
  "properties": {
    "iso:country":"US",
    "sg:address":"12625 High Bluff Dr",
    "sg:city":"San Diego",
    "sg:classifiers":[
        {
            "category":"Professional",
            "subcategory":"Lawyer & Legal Services",
            "type":"Services"
        }
    ],
    "sg:phone":"+1 858 720 8250",
    "sg:postcode":"92130",
    "sg:province":"CA",
    "sg:tags":[
        "attorney"
    ],
    "wof:name":"Myra Chack Law Offices",
    "wof:placetype":"venue"
},
  "geometry": {"coordinates":[-117.240526,32.945787],"type":"Point"}
}