{
  "type": "Feature",
  "properties": {
    "addr:full":"4594 University Pkwy Ste A San Bernardino CA 92407",
    "addr:housenumber":"4594",
    "addr:postcode":"92407",
    "addr:street":"University Pkwy Ste A",
    "iso:country":"US",
    "sg:address":"4594 University Pkwy Ste A",
    "sg:city":"San Bernardino",
    "sg:classifiers":[
        {
            "category":"Restaurant",
            "type":"Food & Drink"
        },
        {
            "category":"Food & Beverages",
            "subcategory":"Bakery",
            "type":"Retail Goods"
        }
    ],
    "sg:phone":"+1 909 887 2562",
    "sg:postcode":"92407",
    "sg:province":"CA",
    "sg:tags":[
        "sandwich",
        "vietnamese"
    ],
    "sg:website":"www.baguetteexpress.com",
    "wof:name":"Baguette Express",
    "wof:placetype":"venue"
},
  "geometry": {"coordinates":[-117.334549,34.170364],"type":"Point"}
}