{
  "type": "Feature",
  "properties": {
    "iso:country":"US",
    "sg:address":"24400 Tiner Ct",
    "sg:city":"Malibu",
    "sg:classifiers":[
        {
            "category":"Insurance",
            "subcategory":"Hazard Insurance",
            "type":"Services"
        }
    ],
    "sg:phone":"+1 310 506 4903",
    "sg:postcode":"90265",
    "sg:province":"CA",
    "wof:name":"Ronald F Phillips",
    "wof:placetype":"venue"
},
  "geometry": {"coordinates":[-118.705872,34.04232],"type":"Point"}
}