{
  "type": "Feature",
  "properties": {
    "iso:country":"US",
    "sg:address":"506 Chestnut Ave",
    "sg:city":"Redlands",
    "sg:classifiers":[
        {
            "category":"Personal",
            "subcategory":"Beauty Salon",
            "type":"Services"
        }
    ],
    "sg:phone":"+1 909 793 5507",
    "sg:postcode":"92373",
    "sg:province":"CA",
    "sg:tags":[
        "shop"
    ],
    "wof:name":"Hair By Sharon",
    "wof:placetype":"venue"
},
  "geometry": {"coordinates":[-117.18051,34.039443],"type":"Point"}
}