{
  "type": "Feature",
  "properties": {
    "iso:country":"US",
    "sg:address":"1290 E Lincoln Ave",
    "sg:city":"Anaheim",
    "sg:classifiers":[
        {
            "category":"Manufacturing",
            "subcategory":"Printing",
            "type":"Manufacturing & Wholesale Goods"
        }
    ],
    "sg:phone":"+1 714 635 6951",
    "sg:postcode":"92805",
    "sg:province":"CA",
    "sg:tags":[
        "lithographic",
        "commercial"
    ],
    "wof:name":"Armando S Diaz Promotions",
    "wof:placetype":"venue"
},
  "geometry": {"coordinates":[-117.899013,33.838821],"type":"Point"}
}