{
  "type": "Feature",
  "properties": {
    "addr:full":"5940 College Ave Oakland CA 94618",
    "addr:housenumber":"5940",
    "addr:postcode":"94618",
    "addr:street":"College Ave",
    "iso:country":"US",
    "sg:address":"5940 College Ave",
    "sg:city":"Oakland",
    "sg:classifiers":[
        {
            "category":"Bars & Pubs",
            "type":"Food & Drink"
        }
    ],
    "sg:phone":"+1 510 654 1650",
    "sg:postcode":"94618",
    "sg:province":"CA",
    "sg:website":"www.barclayspub.com",
    "wof:name":"Barclay's Restaurant & Pub",
    "wof:placetype":"venue"
},
  "geometry": {"coordinates":[-122.251999,37.846401],"type":"Point"}
}