{
  "type": "Feature",
  "properties": {
    "iso:country":"US",
    "sg:address":"2967 G St",
    "sg:city":"Merced",
    "sg:classifiers":[
        {
            "category":"Shopping",
            "subcategory":"Computers & Home Electronics",
            "type":"Retail Goods"
        }
    ],
    "sg:phone":"+1 209 381 0678",
    "sg:postcode":"95340",
    "sg:province":"CA",
    "sg:tags":[
        "equipment",
        "dealer"
    ],
    "wof:name":"Computer Bug",
    "wof:placetype":"venue"
},
  "geometry": {"coordinates":[-120.469467,37.313317],"type":"Point"}
}