{
  "type": "Feature",
  "properties": {
    "addr:full":"10615 Artrude St Sunland CA 91040",
    "addr:housenumber":"10615",
    "addr:postcode":"91040",
    "addr:street":"Artrude St",
    "iso:country":"US",
    "sg:address":"10615 Artrude St",
    "sg:city":"Sunland",
    "sg:classifiers":[
        {
            "category":"Shopping",
            "subcategory":"Beauty & Cosmetics",
            "type":"Retail Goods"
        }
    ],
    "sg:phone":"+1 818 293 1105",
    "sg:postcode":"91040",
    "sg:province":"CA",
    "sg:tags":[
        "merchandise"
    ],
    "wof:name":"Gioia Cosmetics",
    "wof:placetype":"venue"
},
  "geometry": {"coordinates":[-118.364814,34.247225],"type":"Point"}
}