{
  "type": "Feature",
  "properties": {
    "iso:country":"US",
    "sg:address":"12423 Gladstone Ave",
    "sg:city":"Sylmar",
    "sg:classifiers":[
        {
            "category":"Home & Garden",
            "subcategory":"Furniture",
            "type":"Retail Goods"
        }
    ],
    "sg:phone":"+1 818 361 7131",
    "sg:postcode":"91342",
    "sg:province":"CA",
    "sg:tags":[
        "cabinet"
    ],
    "wof:name":"Custom Cabinetry",
    "wof:placetype":"venue"
},
  "geometry": {"coordinates":[-118.41345200000001,34.297162],"type":"Point"}
}