{
  "type": "Feature",
  "properties": {
    "addr:full":"15731 S Western Ave Gardena CA 90247",
    "addr:housenumber":"15731",
    "addr:postcode":"90247",
    "addr:street":"S Western Ave",
    "iso:country":"US",
    "sg:address":"15731 S Western Ave",
    "sg:city":"Gardena",
    "sg:classifiers":[
        {
            "category":"Health Services",
            "subcategory":"Health Practitioner",
            "type":"Services"
        }
    ],
    "sg:phone":"+1 310 808 0199",
    "sg:postcode":"90247",
    "sg:province":"CA",
    "sg:tags":[
        "acupuncture"
    ],
    "wof:name":"Gardena Hong's Health Center",
    "wof:placetype":"venue"
},
  "geometry": {"coordinates":[-118.308998,33.8881],"type":"Point"}
}