{
  "type": "Feature",
  "properties": {
    "addr:full":"45666 Jeronimo St Temecula CA 92592",
    "addr:housenumber":"45666",
    "addr:postcode":"92592",
    "addr:street":"Jeronimo St",
    "iso:country":"US",
    "sg:address":"45666 Jeronimo St",
    "sg:city":"Temecula",
    "sg:classifiers":[
        {
            "category":"Professional",
            "subcategory":"Management & Consulting",
            "type":"Services"
        }
    ],
    "sg:phone":"+1 951 695 1055",
    "sg:postcode":"92592",
    "sg:province":"CA",
    "sg:tags":[
        "training",
        "sales"
    ],
    "wof:name":"MKH Assoc",
    "wof:placetype":"venue"
},
  "geometry": {"coordinates":[-117.112312,33.459452],"type":"Point"}
}