{
  "type": "Feature",
  "properties": {
    "iso:country":"US",
    "sg:address":"309 W Beverly Blvd",
    "sg:city":"Montebello",
    "sg:classifiers":[
        {
            "category":"Banks & Credit Unions",
            "subcategory":"Bank",
            "type":"Services"
        }
    ],
    "sg:phone":"+1 323 725 4330",
    "sg:postcode":"90640",
    "sg:province":"CA",
    "wof:name":"Rancho Federal Credit Union",
    "wof:placetype":"venue"
},
  "geometry": {"coordinates":[-118.101737,34.016205],"type":"Point"}
}