{
  "type": "Feature",
  "properties": {
    "iso:country":"US",
    "sg:address":"3633 Long Beach Blvd",
    "sg:city":"Long Beach",
    "sg:classifiers":[
        {
            "category":"Building & Trades",
            "subcategory":"Construction",
            "type":"Services"
        }
    ],
    "sg:phone":"+1 562 989 4050",
    "sg:postcode":"90807",
    "sg:province":"CA",
    "sg:tags":[
        "air",
        "heating",
        "conditioning/hvac"
    ],
    "wof:name":"N & S Heating and AIr Conditioning",
    "wof:placetype":"venue"
},
  "geometry": {"coordinates":[-118.189777,33.823343],"type":"Point"}
}