{
  "type": "Feature",
  "properties": {
    "iso:country":"US",
    "sg:address":"115 Hackberry Ave",
    "sg:city":"Modesto",
    "sg:classifiers":[
        {
            "category":"Building & Trades",
            "subcategory":"Electrical",
            "type":"Services"
        }
    ],
    "sg:phone":"+1 209 544 2203",
    "sg:postcode":"95354",
    "sg:province":"CA",
    "sg:tags":[
        "electrical",
        "contractor"
    ],
    "wof:name":"Keefe Electric & Plmbing",
    "wof:placetype":"venue"
},
  "geometry": {"coordinates":[-121.001582,37.647009],"type":"Point"}
}