{
  "type": "Feature",
  "properties": {
    "iso:country":"US",
    "sg:address":"577 S Forestdale Ave",
    "sg:city":"Covina",
    "sg:classifiers":[
        {
            "category":"Place Of Worship",
            "type":"Public Place"
        }
    ],
    "sg:phone":"+1 626 331 7164",
    "sg:postcode":"91723",
    "sg:province":"CA",
    "sg:tags":[
        "church"
    ],
    "wof:name":"Dalton Glen Barnes Memorial Scholarship",
    "wof:placetype":"venue"
},
  "geometry": {"coordinates":[-117.876442,34.079258],"type":"Point"}
}