{
  "type": "Feature",
  "properties": {
    "iso:country":"US",
    "sg:address":"5901 Waukesha Pl",
    "sg:city":"Rancho Palos Verdes",
    "sg:classifiers":[
        {
            "category":"Insurance",
            "subcategory":"Insurance Agent",
            "type":"Services"
        }
    ],
    "sg:phone":"+1 310 377 4885",
    "sg:postcode":"90275",
    "sg:province":"CA",
    "wof:name":"SM Campos Indep Agnt",
    "wof:placetype":"venue"
},
  "geometry": {"coordinates":[-118.384277,33.782609],"type":"Point"}
}