{
  "type": "Feature",
  "properties": {
    "addr:full":"23862 Sycamore Dr Mission Viejo CA 92691",
    "addr:housenumber":"23862",
    "addr:postcode":"92691",
    "addr:street":"Sycamore Dr",
    "iso:country":"US",
    "sg:address":"23862 Sycamore Dr",
    "sg:city":"Mission Viejo",
    "sg:classifiers":[
        {
            "category":"Professional",
            "type":"Services"
        }
    ],
    "sg:phone":"+1 949 588 1135",
    "sg:postcode":"92691",
    "sg:province":"CA",
    "wof:name":"Jonathan V Galaviz",
    "wof:placetype":"venue"
},
  "geometry": {"coordinates":[-117.688265,33.615498],"type":"Point"}
}