{
  "type": "Feature",
  "properties": {
    "addr:full":"8949 Kenamar Dr San Diego CA 92121",
    "addr:housenumber":"8949",
    "addr:postcode":"92121",
    "addr:street":"Kenamar Dr",
    "iso:country":"US",
    "sg:address":"8949 Kenamar Dr",
    "sg:city":"San Diego",
    "sg:classifiers":[
        {
            "category":"Wholesale",
            "subcategory":"Machinery & Supplies",
            "type":"Manufacturing & Wholesale Goods"
        }
    ],
    "sg:phone":"+1 858 566 3363",
    "sg:postcode":"92121",
    "sg:province":"CA",
    "sg:tags":[
        "automobile",
        "parts",
        "pa",
        "motorcycle"
    ],
    "wof:name":"Hot Products",
    "wof:placetype":"venue"
},
  "geometry": {"coordinates":[-117.15540900000001,32.885784],"type":"Point"}
}