{
  "type": "Feature",
  "properties": {
    "iso:country":"US",
    "sg:address":"19114 Halcon Crest Ct",
    "sg:city":"Grass Valley",
    "sg:classifiers":[
        {
            "category":"Professional",
            "subcategory":"Engineering",
            "type":"Services"
        }
    ],
    "sg:phone":"+1 530 268 7070",
    "sg:postcode":"95949",
    "sg:province":"CA",
    "sg:tags":[
        "engineer"
    ],
    "wof:name":"C K Consultants Environmental",
    "wof:placetype":"venue"
},
  "geometry": {"coordinates":[-121.08123,39.095337],"type":"Point"}
}