{
  "type": "Feature",
  "properties": {
    "iso:country":"US",
    "sg:address":"2171 Cowell Blvd Ste F",
    "sg:city":"Davis",
    "sg:classifiers":[
        {
            "category":"Bars & Pubs",
            "type":"Food & Drink"
        }
    ],
    "sg:phone":"+1 530 750 2150",
    "sg:postcode":"95618",
    "sg:province":"CA",
    "sg:tags":[
        "brew"
    ],
    "wof:name":"Duke S Sports Bar Grill",
    "wof:placetype":"venue"
},
  "geometry": {"coordinates":[-121.723674,38.540593],"type":"Point"}
}