{
  "type": "Feature",
  "properties": {
    "addr:full":"8344 Florence Avenue Downey CA 90240",
    "addr:housenumber":"8344",
    "addr:postcode":"90240",
    "addr:street":"Florence Avenue",
    "iso:country":"US",
    "sg:address":"8344 Florence Avenue",
    "sg:city":"Downey",
    "sg:classifiers":[
        {
            "category":"Banks & Credit Unions",
            "subcategory":"Financial Services",
            "type":"Services"
        }
    ],
    "sg:phone":"+1 562 904 9125",
    "sg:postcode":"90240",
    "sg:province":"CA",
    "sg:tags":[
        "broker",
        "mortgage"
    ],
    "wof:name":"Expert Funding",
    "wof:placetype":"venue"
},
  "geometry": {"coordinates":[-118.124876,33.951057],"type":"Point"}
}