{
  "type": "Feature",
  "properties": {
    "iso:country":"US",
    "sg:address":"1425 Coldwell Ave",
    "sg:city":"Modesto",
    "sg:classifiers":[
        {
            "category":"Retail",
            "subcategory":"Auto Repair",
            "type":"Services"
        }
    ],
    "sg:phone":"+1 209 521 8731",
    "sg:postcode":"95350",
    "sg:province":"CA",
    "sg:tags":[
        "repairing",
        "automobile"
    ],
    "wof:name":"Doug Foss Automotive",
    "wof:placetype":"venue"
},
  "geometry": {"coordinates":[-121.014377,37.653242],"type":"Point"}
}