{
  "type": "Feature",
  "properties": {
    "iso:country":"US",
    "sg:address":"310 Centinary Dr",
    "sg:city":"Walnut",
    "sg:classifiers":[
        {
            "category":"Professional",
            "type":"Services"
        }
    ],
    "sg:phone":"+1 909 839 0291",
    "sg:postcode":"91789",
    "sg:province":"CA",
    "wof:name":"Y & W Corporation",
    "wof:placetype":"venue"
},
  "geometry": {"coordinates":[-117.859428,34.020676],"type":"Point"}
}