{
  "type": "Feature",
  "properties": {
    "iso:country":"US",
    "sg:address":"33851 Plum Tree Ln",
    "sg:city":"Yucaipa",
    "sg:classifiers":[
        {
            "category":"Shopping",
            "subcategory":"Photographic Equipment",
            "type":"Retail Goods"
        }
    ],
    "sg:phone":"+1 909 795 6166",
    "sg:postcode":"92399",
    "sg:province":"CA",
    "sg:tags":[
        "photography",
        "store"
    ],
    "wof:name":"David Swanson",
    "wof:placetype":"venue"
},
  "geometry": {"coordinates":[-117.06644300000001,34.024299],"type":"Point"}
}