{
  "type": "Feature",
  "properties": {
    "addr:full":"1480 S Mercey Springs Rd Los Banos CA 93635",
    "addr:housenumber":"1480",
    "addr:postcode":"93635",
    "addr:street":"S Mercey Springs Rd",
    "iso:country":"US",
    "sg:address":"1480 S Mercey Springs Rd",
    "sg:city":"Los Banos",
    "sg:classifiers":[
        {
            "category":"Restaurant",
            "type":"Food & Drink"
        }
    ],
    "sg:menulink":"http://www.allmenus.com/ca/los-banos/216030-mcdonalds/menu/",
    "sg:postcode":"93635",
    "sg:province":"CA",
    "sg:tags":[
        "burger",
        "american"
    ],
    "wof:name":"McDonald's",
    "wof:placetype":"venue"
},
  "geometry": {"coordinates":[-120.834924,37.05648],"type":"Point"}
}