{
  "type": "Feature",
  "properties": {
    "iso:country":"US",
    "sg:address":"14690 Meadow Cove Ln",
    "sg:city":"Big Oak Valley",
    "sg:classifiers":[
        {
            "category":"Professional",
            "subcategory":"Business Services",
            "type":"Services"
        }
    ],
    "sg:phone":"+1 530 272 3300",
    "sg:postcode":"95946",
    "sg:province":"CA",
    "sg:tags":[
        "paging",
        "answering"
    ],
    "wof:name":"Sierra Communications",
    "wof:placetype":"venue"
},
  "geometry": {"coordinates":[-121.25477100000001,39.252477],"type":"Point"}
}