{
  "type": "Feature",
  "properties": {
    "addr:full":"217 Delmas Ave San Jose CA 95110",
    "addr:housenumber":"217",
    "addr:postcode":"95110",
    "addr:street":"Delmas Ave",
    "iso:country":"US",
    "sg:address":"217 Delmas Ave",
    "sg:city":"San Jose",
    "sg:classifiers":[
        {
            "category":"Organizations",
            "subcategory":"Religious Organization",
            "type":"Services"
        }
    ],
    "sg:phone":"+1 408 294 1206",
    "sg:postcode":"95110",
    "sg:province":"CA",
    "sg:tags":[
        "church"
    ],
    "wof:name":"Primeva Baptist Church",
    "wof:placetype":"venue"
},
  "geometry": {"coordinates":[-121.89584000000001,37.327639],"type":"Point"}
}