{
  "type": "Feature",
  "properties": {
    "iso:country":"US",
    "sg:address":"8970 Reseda Blvd",
    "sg:city":"Northridge",
    "sg:classifiers":[
        {
            "category":"Shopping",
            "subcategory":"Clothing, Apparel, & Fashions",
            "type":"Retail Goods"
        }
    ],
    "sg:phone":"+1 818 701 0603",
    "sg:postcode":"91324",
    "sg:province":"CA",
    "sg:tags":[
        "work"
    ],
    "wof:name":"Outlet 8",
    "wof:placetype":"venue"
},
  "geometry": {"coordinates":[-118.53601,34.234208],"type":"Point"}
}