{
  "type": "Feature",
  "properties": {
    "iso:country":"US",
    "sg:address":"1071 Peppertree Dr",
    "sg:city":"Fairfield",
    "sg:classifiers":[
        {
            "category":"Shopping",
            "subcategory":"Computers & Home Electronics",
            "type":"Retail Goods"
        }
    ],
    "sg:phone":"+1 707 427 3229",
    "sg:postcode":"94533",
    "sg:province":"CA",
    "sg:tags":[
        "related"
    ],
    "wof:name":"RWS Micro Tech",
    "wof:placetype":"venue"
},
  "geometry": {"coordinates":[-122.012286,38.276014],"type":"Point"}
}