{
  "type": "Feature",
  "properties": {
    "iso:country":"US",
    "sg:address":"25246 W Dorris Ave",
    "sg:city":"Coalinga",
    "sg:classifiers":[
        {
            "category":"Restaurant",
            "type":"Food & Drink"
        }
    ],
    "sg:menulink":"http://www.allmenus.com/ca/coalinga/172141-burger-king/menu/",
    "sg:phone":"+1 559 935 0739",
    "sg:postcode":"93210",
    "sg:province":"CA",
    "sg:tags":[
        "burger",
        "american"
    ],
    "wof:name":"Burger King",
    "wof:placetype":"venue"
},
  "geometry": {"coordinates":[-120.251721,36.254243],"type":"Point"}
}