{
  "type": "Feature",
  "properties": {
    "addr:full":"5490 Complex St San Diego CA 92123",
    "addr:housenumber":"5490",
    "addr:postcode":"92123",
    "addr:street":"Complex St",
    "iso:country":"US",
    "sg:address":"5490 Complex St",
    "sg:city":"San Diego",
    "sg:classifiers":[
        {
            "category":"Building & Trades",
            "subcategory":"Plumbing",
            "type":"Services"
        }
    ],
    "sg:phone":"+1 619 729 4326",
    "sg:postcode":"92123",
    "sg:province":"CA",
    "sg:tags":[
        "plumbing",
        "contractor"
    ],
    "sg:website":"www.myplumber.com",
    "wof:name":"My Plumber",
    "wof:placetype":"venue"
},
  "geometry": {"coordinates":[-117.134807,32.83149],"type":"Point"}
}