{
  "type": "Feature",
  "properties": {
    "iso:country":"US",
    "sg:address":"1110 S el Camino Real",
    "sg:city":"San Clemente",
    "sg:classifiers":[
        {
            "category":"Food & Beverages",
            "subcategory":"Bakery",
            "type":"Retail Goods"
        }
    ],
    "sg:phone":"+1 949 492 1249",
    "sg:postcode":"92672",
    "sg:province":"CA",
    "wof:name":"Surfin Donut",
    "wof:placetype":"venue"
},
  "geometry": {"coordinates":[-117.607828,33.420442],"type":"Point"}
}