{
  "type": "Feature",
  "properties": {
    "iso:country":"US",
    "sg:address":"1787 Pomona Rd Ste L",
    "sg:city":"Corona",
    "sg:classifiers":[
        {
            "category":"Insurance",
            "subcategory":"Hazard Insurance",
            "type":"Services"
        },
        {
            "category":"Insurance",
            "subcategory":"Insurance Agent",
            "type":"Services"
        },
        {
            "category":"Insurance",
            "subcategory":"Life Insurance",
            "type":"Services"
        }
    ],
    "sg:phone":"+1 951 847 1887",
    "sg:postcode":"92880",
    "sg:province":"CA",
    "sg:tags":[
        "fidelity",
        "surety",
        "bond"
    ],
    "wof:name":"Turning Point Debt Relief",
    "wof:placetype":"venue"
},
  "geometry": {"coordinates":[-117.60245399999999,33.882715],"type":"Point"}
}