{
  "type": "Feature",
  "properties": {
    "iso:country":"US",
    "sg:address":"19634 Ventura Blvd Ste 209",
    "sg:city":"Tarzana",
    "sg:classifiers":[
        {
            "category":"Professional",
            "subcategory":"Lawyer & Legal Services",
            "type":"Services"
        }
    ],
    "sg:phone":"+1 818 344 9944",
    "sg:postcode":"91356",
    "sg:province":"CA",
    "wof:name":"Law Offices of Nitza Ben-Yehuda",
    "wof:placetype":"venue"
},
  "geometry": {"coordinates":[-118.56127499999999,34.172065],"type":"Point"}
}