{
  "type": "Feature",
  "properties": {
    "addr:full":"980 Wildcat Canyon Rd Berkeley CA 94708",
    "addr:housenumber":"980",
    "addr:postcode":"94708",
    "addr:street":"Wildcat Canyon Rd",
    "iso:country":"US",
    "sg:address":"980 Wildcat Canyon Rd",
    "sg:city":"Berkeley",
    "sg:classifiers":[
        {
            "category":"Manufacturing",
            "subcategory":"Electronics",
            "type":"Manufacturing & Wholesale Goods"
        }
    ],
    "sg:phone":"+1 510 843 5253",
    "sg:postcode":"94708",
    "sg:province":"CA",
    "sg:tags":[
        "equipment",
        "mfg",
        "communication"
    ],
    "wof:name":"Pacific Coast Factors Inc",
    "wof:placetype":"venue"
},
  "geometry": {"coordinates":[-122.256249,37.898695],"type":"Point"}
}