{
  "type": "Feature",
  "properties": {
    "iso:country":"US",
    "sg:address":"11701 Wilshire Blvd",
    "sg:city":"Los Angeles",
    "sg:classifiers":[
        {
            "category":"Health Services",
            "subcategory":"Optometrist",
            "type":"Services"
        }
    ],
    "sg:phone":"+1 310 820 7866",
    "sg:postcode":"90025",
    "sg:province":"CA",
    "wof:name":"Optometrix",
    "wof:placetype":"venue"
},
  "geometry": {"coordinates":[-118.460921,34.049408],"type":"Point"}
}