{
  "type": "Feature",
  "properties": {
    "addr:full":"4426 E Waterloo Rd Stockton CA 95215",
    "addr:housenumber":"4426",
    "addr:postcode":"95215",
    "addr:street":"E Waterloo Rd",
    "iso:country":"US",
    "sg:address":"4426 E Waterloo Rd",
    "sg:city":"Stockton",
    "sg:classifiers":[
        {
            "category":"Banks & Credit Unions",
            "subcategory":"Investment Brokerage",
            "type":"Services"
        },
        {
            "category":"Banks & Credit Unions",
            "subcategory":"Bank",
            "type":"Services"
        },
        {
            "category":"Banks & Credit Unions",
            "subcategory":"Financial Services",
            "type":"Services"
        }
    ],
    "sg:phone":"+1 209 373 4300",
    "sg:postcode":"95215",
    "sg:province":"CA",
    "sg:tags":[
        "commercial",
        "financing",
        "trust",
        "saving"
    ],
    "sg:website":"http://www.cbsjbank.com",
    "wof:name":"Community Bank Of San Joaquin",
    "wof:placetype":"venue"
},
  "geometry": {"coordinates":[-121.24388500000001,37.98867],"type":"Point"}
}