{
  "type": "Feature",
  "properties": {
    "iso:country":"US",
    "sg:address":"599 Bonnie Dr",
    "sg:city":"El Cerrito",
    "sg:classifiers":[
        {
            "category":"Health Services",
            "subcategory":"Clinic",
            "type":"Services"
        }
    ],
    "sg:phone":"+1 510 717 5060",
    "sg:postcode":"94530",
    "sg:province":"CA",
    "sg:tags":[
        "medical"
    ],
    "sg:website":"sanctuaryleopi.com",
    "wof:name":"Leopi Nicola Sanderson-Edmunds, LM CPM",
    "wof:placetype":"venue"
},
  "geometry": {"coordinates":[-122.292441,37.908487],"type":"Point"}
}