{
  "type": "Feature",
  "properties": {
    "iso:country":"US",
    "sg:address":"214 E Grand Ave",
    "sg:city":"Escondido",
    "sg:classifiers":[
        {
            "category":"Manufacturing",
            "subcategory":"Pet Food",
            "type":"Manufacturing & Wholesale Goods"
        },
        {
            "category":"Shopping",
            "subcategory":"Pets & Pet Supplies",
            "type":"Retail Goods"
        }
    ],
    "sg:phone":"+1 760 735 8445",
    "sg:postcode":"92025",
    "sg:province":"CA",
    "sg:tags":[
        "dog",
        "specialty",
        "cat",
        "furnishing",
        "foods-wholesale",
        "store",
        "manufacturer"
    ],
    "sg:website":"http://www.lllreptile.com",
    "wof:name":"Lll Reptile & Supply Co",
    "wof:placetype":"venue"
},
  "geometry": {"coordinates":[-117.079885,33.122426],"type":"Point"}
}