{
  "type": "Feature",
  "properties": {
    "addr:full":"9727 S Figueroa St Los Angeles CA 90003",
    "addr:housenumber":"9727",
    "addr:postcode":"90003",
    "addr:street":"S Figueroa St",
    "iso:country":"US",
    "sg:address":"9727 S Figueroa St",
    "sg:city":"Los Angeles",
    "sg:classifiers":[
        {
            "category":"Food & Beverages",
            "subcategory":"Groceries & Convenience Stores",
            "type":"Retail Goods"
        }
    ],
    "sg:phone":"+1 323 242 9084",
    "sg:postcode":"90003",
    "sg:province":"CA",
    "wof:name":"98th OK Market",
    "wof:placetype":"venue"
},
  "geometry": {"coordinates":[-118.282822,33.948019],"type":"Point"}
}