{
  "type": "Feature",
  "properties": {
    "iso:country":"US",
    "sg:address":"9976 Sierra Ave",
    "sg:city":"Fontana",
    "sg:classifiers":[
        {
            "category":"Shopping",
            "subcategory":"Department Store",
            "type":"Retail Goods"
        }
    ],
    "sg:phone":"+1 909 574 6114",
    "sg:postcode":"92335",
    "sg:province":"CA",
    "sg:tags":[
        "shop"
    ],
    "wof:name":"Dollar Tree",
    "wof:placetype":"venue"
},
  "geometry": {"coordinates":[-117.435763,34.070391],"type":"Point"}
}