{
  "type": "Feature",
  "properties": {
    "iso:country":"US",
    "sg:address":"9055 Central Ave",
    "sg:city":"Montclair",
    "sg:classifiers":[
        {
            "category":"Wholesale",
            "subcategory":"Hardware",
            "type":"Manufacturing & Wholesale Goods"
        }
    ],
    "sg:phone":"+1 909 988 5858",
    "sg:postcode":"91763",
    "sg:province":"CA",
    "sg:tags":[
        "tool"
    ],
    "sg:website":"www.etoolsrus.com",
    "wof:name":"Tools R Us",
    "wof:placetype":"venue"
},
  "geometry": {"coordinates":[-117.689528,34.088767],"type":"Point"}
}