{
  "type": "Feature",
  "properties": {
    "addr:full":"3603 Ponderosa St Palmdale CA 93535",
    "addr:housenumber":"3603",
    "addr:postcode":"ca 93535",
    "addr:street":"Ponderosa St",
    "iso:country":"US",
    "sg:address":"3603 Ponderosa St",
    "sg:city":"Palmdale",
    "sg:classifiers":[
        {
            "category":"Building & Trades",
            "subcategory":"Plumbing",
            "type":"Services"
        }
    ],
    "sg:phone":"+1 661 533 3569",
    "sg:postcode":"93535",
    "sg:province":"CA",
    "sg:tags":[
        "plumbing",
        "contractor"
    ],
    "wof:name":"Master Flow Plumbing",
    "wof:placetype":"venue"
},
  "geometry": {"coordinates":[-118.09014000000001,34.675696],"type":"Point"}
}