{
  "type": "Feature",
  "properties": {
    "iso:country":"US",
    "sg:address":"2132 E Dominguez St",
    "sg:city":"Long Beach",
    "sg:classifiers":[
        {
            "category":"Freight",
            "type":"Transportation"
        }
    ],
    "sg:phone":"+1 310 830 0013",
    "sg:postcode":"90810",
    "sg:province":"CA",
    "sg:tags":[
        "trucking"
    ],
    "wof:name":"Elite Logistics Corp",
    "wof:placetype":"venue"
},
  "geometry": {"coordinates":[-118.235044,33.83912],"type":"Point"}
}