{
  "type": "Feature",
  "properties": {
    "iso:country":"US",
    "sg:address":"449 W Bay Street",
    "sg:city":"Costa Mesa",
    "sg:classifiers":[
        {
            "category":"Retail",
            "subcategory":"Auto Repair",
            "type":"Services"
        }
    ],
    "sg:phone":"+1 949 645 4641",
    "sg:postcode":"92627",
    "sg:province":"CA",
    "wof:name":"The Tune Up Shop",
    "wof:placetype":"venue"
},
  "geometry": {"coordinates":[-117.918542,33.648838],"type":"Point"}
}