{
  "type": "Feature",
  "properties": {
    "iso:country":"US",
    "sg:address":"2451 Irvine Ave",
    "sg:city":"Costa Mesa",
    "sg:classifiers":[
        {
            "category":"Building & Trades",
            "subcategory":"Construction",
            "type":"Services"
        }
    ],
    "sg:phone":"+1 949 400 8202",
    "sg:postcode":"92627",
    "sg:province":"CA",
    "sg:tags":[
        "painter"
    ],
    "wof:name":"Pacific Painting Co",
    "wof:placetype":"venue"
},
  "geometry": {"coordinates":[-117.89016700000001,33.652666],"type":"Point"}
}