{
  "type": "Feature",
  "properties": {
    "iso:country":"US",
    "sg:address":"222 Meigs Rd",
    "sg:city":"Santa Barbara",
    "sg:classifiers":[
        {
            "category":"Recreation",
            "type":"Entertainment"
        }
    ],
    "sg:phone":"+1 805 451 4571",
    "sg:postcode":"93109",
    "sg:province":"CA",
    "sg:tags":[
        "amusement"
    ],
    "wof:name":"Davey Smith Surf Academy",
    "wof:placetype":"venue"
},
  "geometry": {"coordinates":[-119.722387,34.39851],"type":"Point"}
}