{
  "type": "Feature",
  "properties": {
    "addr:full":"1616 E Hammer Ln Stockton CA 95210",
    "addr:housenumber":"1616",
    "addr:postcode":"95210",
    "addr:street":"E Hammer Ln",
    "iso:country":"US",
    "sg:address":"1616 E Hammer Ln",
    "sg:city":"Stockton",
    "sg:classifiers":[
        {
            "category":"Wholesale",
            "subcategory":"Non-durable Goods",
            "type":"Manufacturing & Wholesale Goods"
        },
        {
            "category":"Autos & Motor Vehicles",
            "subcategory":"Auto Supplies",
            "type":"Retail Goods"
        },
        {
            "category":"Structure",
            "subcategory":"Warehouse",
            "type":"Public Place"
        },
        {
            "category":"Food & Beverages",
            "subcategory":"Supermarket",
            "type":"Retail Goods"
        },
        {
            "category":"Shopping",
            "subcategory":"Florist",
            "type":"Retail Goods"
        }
    ],
    "sg:phone":"+1 209 478 5813",
    "sg:postcode":"95210",
    "sg:province":"CA",
    "sg:tags":[
        "super",
        "warehouses-merchandise",
        "store",
        "tire",
        "merchandise-wholesale"
    ],
    "sg:website":"http://www.costco.com",
    "wof:name":"Costco",
    "wof:placetype":"venue"
},
  "geometry": {"coordinates":[-121.292429,38.020852],"type":"Point"}
}