{
  "type": "Feature",
  "properties": {
    "addr:full":"1110 Dana Dr Redding CA 96003",
    "addr:housenumber":"1110",
    "addr:postcode":"96003",
    "addr:street":"Dana Dr",
    "iso:country":"US",
    "sg:address":"1110 Dana Dr",
    "sg:city":"Redding",
    "sg:classifiers":[
        {
            "category":"Banks & Credit Unions",
            "subcategory":"Bank",
            "type":"Services"
        }
    ],
    "sg:phone":"+1 530 223 2197",
    "sg:postcode":"96003",
    "sg:province":"CA",
    "sg:website":"www.usbank.com",
    "wof:name":"US Bank",
    "wof:placetype":"venue"
},
  "geometry": {"coordinates":[-122.35116499999999,40.586205],"type":"Point"}
}