{
  "type": "Feature",
  "properties": {
    "iso:country":"US",
    "sg:address":"6319 Montecito Dr",
    "sg:city":"Carlsbad",
    "sg:classifiers":[
        {
            "category":"Autos & Motor Vehicles",
            "subcategory":"Boat Sales",
            "type":"Retail Goods"
        }
    ],
    "sg:phone":"+1 619 474 1349",
    "sg:postcode":"92009",
    "sg:province":"CA",
    "wof:name":"All County Independent Marine",
    "wof:placetype":"venue"
},
  "geometry": {"coordinates":[-117.25284499999999,33.12386],"type":"Point"}
}