{
  "type": "Feature",
  "properties": {
    "iso:country":"US",
    "sg:address":"5925 Santa Monica Blvd",
    "sg:city":"Los Angeles",
    "sg:classifiers":[
        {
            "category":"Professional",
            "type":"Services"
        }
    ],
    "sg:phone":"+1 323 461 1610",
    "sg:postcode":"90038",
    "sg:province":"CA",
    "wof:name":"Arthur Aslanyan",
    "wof:placetype":"venue"
},
  "geometry": {"coordinates":[-118.318416,34.09083],"type":"Point"}
}