{
  "type": "Feature",
  "properties": {
    "iso:country":"US",
    "sg:address":"904 Sylvia Ave",
    "sg:city":"Ridgecrest",
    "sg:classifiers":[
        {
            "category":"Manufacturing",
            "subcategory":"Printing",
            "type":"Manufacturing & Wholesale Goods"
        }
    ],
    "sg:phone":"+1 760 446 4023",
    "sg:postcode":"93555",
    "sg:province":"CA",
    "sg:tags":[
        "book"
    ],
    "wof:name":"Ayers Inc",
    "wof:placetype":"venue"
},
  "geometry": {"coordinates":[-117.681832,35.638382],"type":"Point"}
}