{
  "type": "Feature",
  "properties": {
    "iso:country":"US",
    "sg:address":"6317 Wilshire Blvd",
    "sg:city":"Los Angeles",
    "sg:classifiers":[
        {
            "category":"Health Services",
            "subcategory":"Doctor",
            "type":"Services"
        }
    ],
    "sg:phone":"+1 323 651 3833",
    "sg:postcode":"90048",
    "sg:province":"CA",
    "sg:tags":[
        "dentist"
    ],
    "wof:name":"William A Stomel DDS",
    "wof:placetype":"venue"
},
  "geometry": {"coordinates":[-118.36787200000001,34.063767],"type":"Point"}
}