{
  "type": "Feature",
  "properties": {
    "iso:country":"US",
    "sg:address":"1712 Newport Cir",
    "sg:city":"Santa Ana",
    "sg:classifiers":[
        {
            "category":"Real Estate",
            "subcategory":"Real Estate Operator",
            "type":"Services"
        }
    ],
    "sg:phone":"+1 714 979 2020",
    "sg:postcode":"92705",
    "sg:province":"CA",
    "sg:tags":[
        "building",
        "nonresidential"
    ],
    "wof:name":"Newport Circle Business Park",
    "wof:placetype":"venue"
},
  "geometry": {"coordinates":[-117.842465,33.718548],"type":"Point"}
}