{
  "type": "Feature",
  "properties": {
    "iso:country":"US",
    "sg:address":"250 E L St",
    "sg:city":"Benicia",
    "sg:classifiers":[
        {
            "category":"Building & Trades",
            "subcategory":"Construction",
            "type":"Services"
        }
    ],
    "sg:phone":"+1 707 746 4240",
    "sg:postcode":"94510",
    "sg:province":"CA",
    "sg:tags":[
        "marking",
        "maintenance",
        "parking"
    ],
    "wof:name":"Benicia Public Works Dept",
    "wof:placetype":"venue"
},
  "geometry": {"coordinates":[-122.15239699999999,38.0524],"type":"Point"}
}