{
  "type": "Feature",
  "properties": {
    "addr:full":"24422 Ave de la Carlota Laguna Hills CA 92653",
    "addr:housenumber":"24422",
    "addr:postcode":"92653",
    "addr:street":"Ave De La Carlota",
    "iso:country":"US",
    "sg:address":"24422 Ave de la Carlota",
    "sg:city":"Laguna Hills",
    "sg:classifiers":[
        {
            "category":"Professional",
            "subcategory":"Lawyer & Legal Services",
            "type":"Services"
        }
    ],
    "sg:phone":"+1 949 837 1060",
    "sg:postcode":"92653",
    "sg:province":"CA",
    "sg:tags":[
        "attorney"
    ],
    "sg:website":"www.lglawyer.com",
    "wof:name":"Linda Gunderson Law Office",
    "wof:placetype":"venue"
},
  "geometry": {"coordinates":[-117.702899,33.610303],"type":"Point"}
}