{
  "type": "Feature",
  "properties": {
    "addr:full":"2860 Gateway Oaks Dr Ste 300 Sacramento CA 95833",
    "addr:housenumber":"2860",
    "addr:postcode":"95833",
    "addr:street":"Gateway Oaks Dr Ste 300",
    "iso:country":"US",
    "sg:address":"2860 Gateway Oaks Dr Ste 300",
    "sg:city":"Sacramento",
    "sg:classifiers":[
        {
            "category":"Manufacturing",
            "subcategory":"Buildings",
            "type":"Manufacturing & Wholesale Goods"
        },
        {
            "category":"Building & Trades",
            "subcategory":"Construction",
            "type":"Services"
        }
    ],
    "sg:phone":"+1 916 830 8000",
    "sg:postcode":"95833",
    "sg:province":"CA",
    "sg:tags":[
        "altering",
        "home",
        "builder",
        "remodeling",
        "contractor"
    ],
    "wof:name":"Sundt Construction Inc",
    "wof:placetype":"venue"
},
  "geometry": {"coordinates":[-121.519535,38.620552],"type":"Point"}
}