{
  "type": "Feature",
  "properties": {
    "addr:full":"10537 Stanford Ave Garden Grove CA 92840",
    "addr:housenumber":"10537",
    "addr:postcode":"92840",
    "addr:street":"Stanford Ave",
    "iso:country":"US",
    "sg:address":"10537 Stanford Ave",
    "sg:city":"Garden Grove",
    "sg:classifiers":[
        {
            "category":"Retail",
            "subcategory":"Auto Repair",
            "type":"Services"
        }
    ],
    "sg:phone":"+1 714 539 5057",
    "sg:postcode":"92840",
    "sg:province":"CA",
    "sg:tags":[
        "automobile",
        "electric"
    ],
    "wof:name":"Aaron's Auto Electric",
    "wof:placetype":"venue"
},
  "geometry": {"coordinates":[-117.947998,33.777901],"type":"Point"}
}