{
  "type": "Feature",
  "properties": {
    "iso:country":"US",
    "sg:address":"3206 Scott Blvd",
    "sg:city":"Santa Clara",
    "sg:classifiers":[
        {
            "category":"Professional",
            "subcategory":"Computer Services",
            "type":"Services"
        }
    ],
    "sg:phone":"+1 408 492 1100",
    "sg:postcode":"95050",
    "sg:province":"CA",
    "sg:tags":[
        "graphics"
    ],
    "wof:name":"Dowslake Microsystems Corp",
    "wof:placetype":"venue"
},
  "geometry": {"coordinates":[-121.96821300000001,37.379019],"type":"Point"}
}