{
  "type": "Feature",
  "properties": {
    "addr:full":"2728 5th Ave San Diego CA 92103",
    "addr:housenumber":"2728",
    "addr:postcode":"92103",
    "addr:street":"5Th Ave",
    "iso:country":"US",
    "sg:address":"2728 5th Ave",
    "sg:city":"San Diego",
    "sg:classifiers":[
        {
            "category":"Professional",
            "subcategory":"Lawyer & Legal Services",
            "type":"Services"
        }
    ],
    "sg:phone":"+1 619 296 1594",
    "sg:postcode":"92103",
    "sg:province":"CA",
    "sg:website":"www.viviano-law.com",
    "wof:name":"Lori Clark Viviano Attorney At Law Atty",
    "wof:placetype":"venue"
},
  "geometry": {"coordinates":[-117.160302,32.733814],"type":"Point"}
}