{
  "type": "Feature",
  "properties": {
    "iso:country":"US",
    "sg:address":"1220 2nd St",
    "sg:city":"Santa Monica",
    "sg:classifiers":[
        {
            "category":"Organizations",
            "subcategory":"Religious Organization",
            "type":"Services"
        }
    ],
    "sg:phone":"+1 310 451 1303",
    "sg:postcode":"90401",
    "sg:province":"CA",
    "sg:tags":[
        "church"
    ],
    "wof:name":"First Presbyterian Church",
    "wof:placetype":"venue"
},
  "geometry": {"coordinates":[-118.49896699999999,34.01644],"type":"Point"}
}