{
  "type": "Feature",
  "properties": {
    "addr:full":"20122 Scobey Ave Carson CA 90746",
    "addr:postcode":"20122;90746",
    "addr:street":"Scobey Ave",
    "iso:country":"US",
    "sg:address":"20122 Scobey Ave",
    "sg:city":"Carson",
    "sg:classifiers":[
        {
            "category":"Retail",
            "subcategory":"Auto Repair",
            "type":"Services"
        }
    ],
    "sg:phone":"+1 310 763 1396",
    "sg:postcode":"90746",
    "sg:province":"CA",
    "sg:tags":[
        "body",
        "automobile",
        "painting",
        "repairing"
    ],
    "wof:name":"Flawless Auto Detailing",
    "wof:placetype":"venue"
},
  "geometry": {"coordinates":[-118.25444400000001,33.84828],"type":"Point"}
}