{
  "type": "Feature",
  "properties": {
    "iso:country":"US",
    "sg:address":"713 Broadway",
    "sg:city":"Chula Vista",
    "sg:classifiers":[
        {
            "category":"Restaurant",
            "type":"Food & Drink"
        }
    ],
    "sg:phone":"+1 619 476 0581",
    "sg:postcode":"91910",
    "sg:province":"CA",
    "wof:name":"Maria's Restaurant Pizzeria",
    "wof:placetype":"venue"
},
  "geometry": {"coordinates":[-117.08548399999999,32.621055],"type":"Point"}
}