{
  "type": "Feature",
  "properties": {
    "addr:full":"17538 Tulsa St Granada Hills CA 91344",
    "addr:housenumber":"17538",
    "addr:postcode":"91344",
    "addr:street":"Tulsa St",
    "iso:country":"US",
    "sg:address":"17538 Tulsa St",
    "sg:city":"Granada Hills",
    "sg:classifiers":[
        {
            "category":"Professional",
            "subcategory":"Engineering",
            "type":"Services"
        },
        {
            "category":"Manufacturing",
            "subcategory":"Tools & Machinery",
            "type":"Manufacturing & Wholesale Goods"
        }
    ],
    "sg:phone":"+1 818 366 1200",
    "sg:postcode":"91344",
    "sg:province":"CA",
    "sg:tags":[
        "industrial",
        "mfg"
    ],
    "wof:name":"Engineering Services Inc",
    "wof:placetype":"venue"
},
  "geometry": {"coordinates":[-118.516828,34.268433],"type":"Point"}
}