{
  "type": "Feature",
  "properties": {
    "iso:country":"US",
    "sg:address":"756 S Rancho Santa Fe Rd",
    "sg:city":"San Marcos",
    "sg:classifiers":[
        {
            "category":"Manufacturing",
            "subcategory":"Printing",
            "type":"Manufacturing & Wholesale Goods"
        }
    ],
    "sg:phone":"+1 760 727 5085",
    "sg:postcode":"92078",
    "sg:province":"CA",
    "sg:tags":[
        "engraver",
        "wood"
    ],
    "wof:name":"Engraving Place",
    "wof:placetype":"venue"
},
  "geometry": {"coordinates":[-117.207196,33.13321],"type":"Point"}
}