{
  "type": "Feature",
  "properties": {
    "addr:full":"3806 W Magnolia Blvd Burbank CA 91505",
    "addr:housenumber":"3806",
    "addr:postcode":"91505",
    "addr:street":"W Magnolia Blvd",
    "iso:country":"US",
    "sg:address":"3806 W Magnolia Blvd",
    "sg:city":"Burbank",
    "sg:classifiers":[
        {
            "category":"Shopping",
            "type":"Retail Goods"
        }
    ],
    "sg:phone":"+1 818 845 1155",
    "sg:postcode":"91505",
    "sg:province":"CA",
    "sg:website":"www.8ballwebstore.com",
    "wof:name":"8 Ball",
    "wof:placetype":"venue"
},
  "geometry": {"coordinates":[-118.34807000000001,34.167526],"type":"Point"}
}