{
  "type": "Feature",
  "properties": {
    "addr:full":"1675 Alhambra Blvd Ste E Sacramento CA 95816",
    "addr:housenumber":"1675",
    "addr:postcode":"95816",
    "addr:street":"Alhambra Blvd Ste E",
    "iso:country":"US",
    "sg:address":"1675 Alhambra Blvd Ste E",
    "sg:city":"Sacramento",
    "sg:classifiers":[
        {
            "category":"Health Services",
            "subcategory":"Doctor",
            "type":"Services"
        },
        {
            "category":"Health Services",
            "subcategory":"Dentist",
            "type":"Services"
        }
    ],
    "sg:phone":"+1 916 393 9622",
    "sg:postcode":"95816",
    "sg:province":"CA",
    "wof:name":"Do Han K DDS",
    "wof:placetype":"venue"
},
  "geometry": {"coordinates":[-121.468289,38.565255],"type":"Point"}
}