{
  "type": "Feature",
  "properties": {
    "addr:full":"2333 Camino del Rio South Ste 240 San Diego CA 92108",
    "addr:housenumber":"2333",
    "addr:postcode":"92108",
    "addr:street":"Camino Del Rio South Ste 240",
    "iso:country":"US",
    "sg:address":"2333 Camino del Rio South Ste 240",
    "sg:city":"San Diego",
    "sg:classifiers":[
        {
            "category":"Education",
            "subcategory":"Special Training",
            "type":"Public Place"
        },
        {
            "category":"Sports & Exercise",
            "subcategory":"Gym",
            "type":"Entertainment"
        }
    ],
    "sg:postcode":"92108",
    "sg:province":"CA",
    "sg:tags":[
        "school",
        "yoga",
        "specialty"
    ],
    "sg:website":"www.yogawell.com",
    "wof:name":"YogaWell",
    "wof:placetype":"venue"
},
  "geometry": {"coordinates":[-117.14010500000001,32.767688],"type":"Point"}
}