{
  "type": "Feature",
  "properties": {
    "addr:full":"2780 Olive Hwy Oroville CA 95966",
    "addr:housenumber":"2780",
    "addr:postcode":"95966",
    "addr:street":"Olive Hwy",
    "iso:country":"US",
    "sg:address":"2780 Olive Hwy",
    "sg:city":"Oroville",
    "sg:classifiers":[
        {
            "category":"Home & Garden",
            "subcategory":"Carpets & Floor Coverings",
            "type":"Retail Goods"
        }
    ],
    "sg:phone":"+1 530 533 1469",
    "sg:postcode":"95966",
    "sg:province":"CA",
    "sg:tags":[
        "dealer",
        "rug"
    ],
    "wof:name":"Floors By Ray",
    "wof:placetype":"venue"
},
  "geometry": {"coordinates":[-121.542029,39.504308],"type":"Point"}
}