{
  "type": "Feature",
  "properties": {
    "addr:full":"1520 N Mountain Ave Ontario CA 91762",
    "addr:housenumber":"1520",
    "addr:postcode":"91762",
    "addr:street":"N Mountain Ave",
    "iso:country":"US",
    "sg:address":"1520 N Mountain Ave",
    "sg:city":"Ontario",
    "sg:classifiers":[
        {
            "category":"Personal",
            "subcategory":"Nail Salon",
            "type":"Services"
        }
    ],
    "sg:phone":"+1 909 984 6202",
    "sg:postcode":"91762",
    "sg:province":"CA",
    "wof:name":"Happiness Nails & Spa",
    "wof:placetype":"venue"
},
  "geometry": {"coordinates":[-117.670151,34.085482],"type":"Point"}
}