{
  "type": "Feature",
  "properties": {
    "addr:full":"2020 Chapala St Santa Barbara CA 93105",
    "addr:housenumber":"2020",
    "addr:postcode":"93105",
    "addr:street":"Chapala St",
    "iso:country":"US",
    "sg:address":"2020 Chapala St",
    "sg:city":"Santa Barbara",
    "sg:classifiers":[
        {
            "category":"Real Estate",
            "subcategory":"Architect",
            "type":"Services"
        }
    ],
    "sg:phone":"+1 805 898 3822",
    "sg:postcode":"93105",
    "sg:province":"CA",
    "wof:name":"Leifer & Assoc",
    "wof:placetype":"venue"
},
  "geometry": {"coordinates":[-119.71682800000001,34.430555],"type":"Point"}
}