{
  "type": "Feature",
  "properties": {
    "addr:full":"12335 World Trade Dr San Diego CA 92128",
    "addr:housenumber":"12335",
    "addr:postcode":"92128",
    "addr:street":"World Trade Dr",
    "iso:country":"US",
    "sg:address":"12335 World Trade Dr",
    "sg:city":"San Diego",
    "sg:classifiers":[
        {
            "category":"Wholesale",
            "subcategory":"Home Furnishings",
            "type":"Manufacturing & Wholesale Goods"
        }
    ],
    "sg:phone":"+1 858 592 2446",
    "sg:postcode":"92128",
    "sg:province":"CA",
    "sg:tags":[
        "closet",
        "accessory"
    ],
    "sg:website":"www.concretecanvas.com",
    "wof:name":"Advanced Coating Concepts",
    "wof:placetype":"venue"
},
  "geometry": {"coordinates":[-117.06994,32.987344],"type":"Point"}
}