{
  "type": "Feature",
  "properties": {
    "iso:country":"US",
    "sg:address":"3530 W Pico Blvd",
    "sg:city":"Los Angeles",
    "sg:classifiers":[
        {
            "category":"Wholesale",
            "subcategory":"Construction Materials",
            "type":"Manufacturing & Wholesale Goods"
        }
    ],
    "sg:phone":"+1 323 734 8250",
    "sg:postcode":"90019",
    "sg:province":"CA",
    "wof:name":"Glass Land",
    "wof:placetype":"venue"
},
  "geometry": {"coordinates":[-118.319799,34.047112],"type":"Point"}
}