{
  "type": "Feature",
  "properties": {
    "iso:country":"US",
    "sg:address":"4625 Hooper Avenue",
    "sg:city":"Los Angeles",
    "sg:classifiers":[
        {
            "category":"Food & Beverages",
            "subcategory":"Groceries & Convenience Stores",
            "type":"Retail Goods"
        }
    ],
    "sg:phone":"+1 323 233 5033",
    "sg:postcode":"90011",
    "sg:province":"CA",
    "wof:name":"Los Altos Liquor Store",
    "wof:placetype":"venue"
},
  "geometry": {"coordinates":[-118.251996,34.001195],"type":"Point"}
}