{
  "type": "Feature",
  "properties": {
    "iso:country":"US",
    "sg:address":"110 E 7th St",
    "sg:city":"Hanford",
    "sg:classifiers":[
        {
            "category":"Recreation",
            "type":"Entertainment"
        }
    ],
    "sg:phone":"+1 559 583 8937",
    "sg:postcode":"93230",
    "sg:province":"CA",
    "sg:tags":[
        "instruction",
        "yoga"
    ],
    "wof:name":"Both Hands Alternative Therapy",
    "wof:placetype":"venue"
},
  "geometry": {"coordinates":[-119.64423499999999,36.326906],"type":"Point"}
}