{
  "type": "Feature",
  "properties": {
    "addr:full":"6640 N Blackstone Ave Fresno CA 93710",
    "addr:housenumber":"6640",
    "addr:postcode":"93710",
    "addr:street":"N Blackstone Ave",
    "iso:country":"US",
    "sg:address":"6640 N Blackstone Ave",
    "sg:city":"Fresno",
    "sg:classifiers":[
        {
            "category":"Manufacturing",
            "subcategory":"Printing",
            "type":"Manufacturing & Wholesale Goods"
        }
    ],
    "sg:phone":"+1 559 447 1543",
    "sg:postcode":"93710",
    "sg:province":"CA",
    "sg:tags":[
        "publisher",
        "guide"
    ],
    "sg:website":"www.autotrader.com",
    "wof:name":"Auto Deals",
    "wof:placetype":"venue"
},
  "geometry": {"coordinates":[-119.790187,36.833847],"type":"Point"}
}