{
  "type": "Feature",
  "properties": {
    "addr:full":"459 Hamilton Ave Palo Alto CA 94301",
    "addr:housenumber":"459",
    "addr:postcode":"94301",
    "addr:street":"Hamilton Ave",
    "iso:country":"US",
    "sg:address":"459 Hamilton Ave",
    "sg:city":"Palo Alto",
    "sg:classifiers":[
        {
            "category":"Professional",
            "subcategory":"Management & Consulting",
            "type":"Services"
        }
    ],
    "sg:phone":"+1 650 329 1590",
    "sg:postcode":"94301",
    "sg:province":"CA",
    "sg:tags":[
        "counselor",
        "public",
        "relations"
    ],
    "sg:website":"www.u-o.com",
    "wof:name":"Ulevich & Orrange Inc",
    "wof:placetype":"venue"
},
  "geometry": {"coordinates":[-122.15866200000001,37.446832],"type":"Point"}
}