{
  "type": "Feature",
  "properties": {
    "addr:full":"247 S Union Ave Bakersfield CA 93307",
    "addr:housenumber":"247",
    "addr:postcode":"93307",
    "addr:street":"S Union Ave",
    "iso:country":"US",
    "sg:address":"247 S Union Ave",
    "sg:city":"Bakersfield",
    "sg:classifiers":[
        {
            "category":"Autos & Motor Vehicles",
            "subcategory":"Auto Supplies",
            "type":"Retail Goods"
        }
    ],
    "sg:phone":"+1 661 325 0286",
    "sg:postcode":"93307",
    "sg:province":"CA",
    "sg:tags":[
        "wheel",
        "cover"
    ],
    "wof:name":"Kalifornia Wheels & Tires",
    "wof:placetype":"venue"
},
  "geometry": {"coordinates":[-119.00307599999999,35.350642],"type":"Point"}
}