{
  "type": "Feature",
  "properties": {
    "addr:full":"1371 Wheaton Way Riverside CA 92507",
    "addr:housenumber":"1371",
    "addr:postcode":"92507",
    "addr:street":"Wheaton Way",
    "iso:country":"US",
    "sg:address":"1371 Wheaton Way",
    "sg:city":"Riverside",
    "sg:classifiers":[
        {
            "category":"Manufacturing",
            "subcategory":"Textiles",
            "type":"Manufacturing & Wholesale Goods"
        }
    ],
    "sg:phone":"+1 951 680 9085",
    "sg:postcode":"92507",
    "sg:province":"CA",
    "sg:tags":[
        "finishing",
        "plant",
        "cotton"
    ],
    "wof:name":"909 Unincorporated",
    "wof:placetype":"venue"
},
  "geometry": {"coordinates":[-117.341469,33.98992],"type":"Point"}
}