{
  "type": "Feature",
  "properties": {
    "iso:country":"US",
    "sg:address":"675 Paularino Ave",
    "sg:city":"Costa Mesa",
    "sg:classifiers":[
        {
            "category":"Recreation",
            "type":"Entertainment"
        }
    ],
    "sg:phone":"+1 310 268 8499",
    "sg:postcode":"92626",
    "sg:province":"CA",
    "sg:tags":[
        "ticket",
        "local"
    ],
    "sg:website":"www.barrystickets.com",
    "wof:name":"Barry's Tickets",
    "wof:placetype":"venue"
},
  "geometry": {"coordinates":[-117.88435200000001,33.682285],"type":"Point"}
}