{
  "type": "Feature",
  "properties": {
    "iso:country":"US",
    "sg:address":"10808 Santa Monica Blvd",
    "sg:city":"Los Angeles",
    "sg:classifiers":[
        {
            "category":"Organizations",
            "subcategory":"Non-profit Organization",
            "type":"Services"
        }
    ],
    "sg:phone":"+1 310 441 9361",
    "sg:postcode":"90025",
    "sg:province":"CA",
    "sg:tags":[
        "charitable",
        "institution"
    ],
    "wof:name":"Sephardic Educational",
    "wof:placetype":"venue"
},
  "geometry": {"coordinates":[-118.427274,34.055509],"type":"Point"}
}