{
  "type": "Feature",
  "properties": {
    "addr:full":"411 Cam del Rio S San Diego CA 92108",
    "addr:housenumber":"411",
    "addr:postcode":"92108",
    "addr:street":"Cam Del Rio S",
    "iso:country":"US",
    "sg:address":"411 Cam del Rio S",
    "sg:city":"San Diego",
    "sg:classifiers":[
        {
            "category":"Real Estate",
            "subcategory":"Real Estate Agent",
            "type":"Services"
        }
    ],
    "sg:phone":"+1 619 688 0410",
    "sg:postcode":"92108",
    "sg:province":"CA",
    "sg:website":"www.ericelegado.com",
    "wof:name":"Elegado Realty",
    "wof:placetype":"venue"
},
  "geometry": {"coordinates":[-117.154906,32.7642],"type":"Point"}
}