{
  "type": "Feature",
  "properties": {
    "addr:full":"12608 Del AMO Blvd Lakewood CA 90715",
    "addr:housenumber":"12608",
    "addr:postcode":"90715",
    "addr:street":"Del Amo Blvd",
    "iso:country":"US",
    "sg:address":"12608 Del AMO Blvd",
    "sg:city":"Lakewood",
    "sg:classifiers":[
        {
            "category":"Cinema",
            "subcategory":"Movie Rental",
            "type":"Entertainment"
        }
    ],
    "sg:phone":"+1 562 809 8996",
    "sg:postcode":"90715",
    "sg:province":"CA",
    "sg:tags":[
        "game",
        "video"
    ],
    "wof:name":"Thumbs Up Video",
    "wof:placetype":"venue"
},
  "geometry": {"coordinates":[-118.06300400000001,33.846001],"type":"Point"}
}