{
  "type": "Feature",
  "properties": {
    "addr:full":"6770 Magnolia Ave Riverside CA 92506",
    "addr:housenumber":"6770",
    "addr:postcode":"92506",
    "addr:street":"Magnolia Ave",
    "iso:country":"US",
    "sg:address":"6770 Magnolia Ave",
    "sg:city":"Riverside",
    "sg:classifiers":[
        {
            "category":"Health Services",
            "subcategory":"Chiropractor",
            "type":"Services"
        }
    ],
    "sg:phone":"+1 951 778 1113",
    "sg:postcode":"92506",
    "sg:province":"CA",
    "wof:name":"Inlamb Accident & Injury",
    "wof:placetype":"venue"
},
  "geometry": {"coordinates":[-117.397006,33.952501],"type":"Point"}
}