{
  "type": "Feature",
  "properties": {
    "addr:full":"5176 Arlington Ave Riverside CA 92504",
    "addr:housenumber":"5176",
    "addr:postcode":"92504",
    "addr:street":"Arlington Ave",
    "iso:country":"US",
    "sg:address":"5176 Arlington Ave",
    "sg:city":"Riverside",
    "sg:classifiers":[
        {
            "category":"Shopping",
            "subcategory":"Department Store",
            "type":"Retail Goods"
        }
    ],
    "sg:phone":"+1 951 637 8828",
    "sg:postcode":"92504",
    "sg:province":"CA",
    "sg:tags":[
        "shop"
    ],
    "wof:name":"Dollar Warehouse",
    "wof:placetype":"venue"
},
  "geometry": {"coordinates":[-117.41722799999999,33.945997],"type":"Point"}
}