{
  "type": "Feature",
  "properties": {
    "iso:country":"US",
    "sg:address":"12777 Knott St",
    "sg:city":"Garden Grove",
    "sg:classifiers":[
        {
            "category":"Personal",
            "type":"Services"
        },
        {
            "category":"Retail",
            "subcategory":"Event Space",
            "type":"Services"
        }
    ],
    "sg:phone":"+1 714 899 0626",
    "sg:postcode":"92841",
    "sg:province":"CA",
    "sg:tags":[
        "party",
        "planning",
        "venue"
    ],
    "sg:website":"www.gardenroomwedding.com",
    "wof:name":"The Garden Room",
    "wof:placetype":"venue"
},
  "geometry": {"coordinates":[-118.010588,33.777025],"type":"Point"}
}