{
  "type": "Feature",
  "properties": {
    "addr:full":"150 Wyoming St Pleasanton CA 94566",
    "addr:housenumber":"150",
    "addr:postcode":"94566",
    "addr:street":"Wyoming St",
    "iso:country":"US",
    "sg:address":"150 Wyoming St",
    "sg:city":"Pleasanton",
    "sg:classifiers":[
        {
            "category":"Building & Trades",
            "subcategory":"Plumbing",
            "type":"Services"
        }
    ],
    "sg:phone":"+1 925 846 1833",
    "sg:postcode":"94566",
    "sg:province":"CA",
    "sg:tags":[
        "contractor"
    ],
    "wof:name":"Canam Plumbing",
    "wof:placetype":"venue"
},
  "geometry": {"coordinates":[-121.859201,37.667157],"type":"Point"}
}