{
  "type": "Feature",
  "properties": {
    "iso:country":"US",
    "sg:address":"10068 Hirschdale Rd",
    "sg:city":"Truckee",
    "sg:classifiers":[
        {
            "category":"Food & Beverages",
            "subcategory":"Groceries & Convenience Stores",
            "type":"Retail Goods"
        }
    ],
    "sg:phone":"+1 530 587 8282",
    "sg:postcode":"96161",
    "sg:province":"CA",
    "wof:name":"United Trails General Store",
    "wof:placetype":"venue"
},
  "geometry": {"coordinates":[-120.081271,39.382444],"type":"Point"}
}