{
  "type": "Feature",
  "properties": {
    "addr:full":"15600 Devonshire St Granada Hills CA 91344",
    "addr:housenumber":"15600",
    "addr:postcode":"91344",
    "addr:street":"Devonshire St",
    "iso:country":"US",
    "sg:address":"15600 Devonshire St",
    "sg:city":"Granada Hills",
    "sg:classifiers":[
        {
            "category":"Professional",
            "subcategory":"Lawyer & Legal Services",
            "type":"Services"
        }
    ],
    "sg:phone":"+1 818 891 6106",
    "sg:postcode":"91344",
    "sg:province":"CA",
    "sg:tags":[
        "attorney"
    ],
    "wof:name":"Ronald Gue Family Law Ctr",
    "wof:placetype":"venue"
},
  "geometry": {"coordinates":[-118.471851,34.257321],"type":"Point"}
}