{
  "type": "Feature",
  "properties": {
    "iso:country":"US",
    "sg:address":"14120 Culver Dr Ste A-F",
    "sg:city":"Irvine",
    "sg:classifiers":[
        {
            "category":"Food & Beverages",
            "subcategory":"Ethnic Foods",
            "type":"Retail Goods"
        },
        {
            "category":"Food & Beverages",
            "subcategory":"Groceries & Convenience Stores",
            "type":"Retail Goods"
        }
    ],
    "sg:phone":"+1 949 552 8844",
    "sg:postcode":"92604",
    "sg:province":"CA",
    "sg:website":"www.crownvalleysuperirvinepersia...",
    "wof:name":"Super Irvine",
    "wof:placetype":"venue"
},
  "geometry": {"coordinates":[-117.784167,33.708142],"type":"Point"}
}