{
  "type": "Feature",
  "properties": {
    "addr:full":"5959 Topanga Canyon Blvd Woodland Hills CA 91367",
    "addr:housenumber":"5959",
    "addr:postcode":"91367",
    "addr:street":"Topanga Canyon Blvd",
    "iso:country":"US",
    "sg:address":"5959 Topanga Canyon Blvd",
    "sg:city":"Woodland Hills",
    "sg:classifiers":[
        {
            "category":"Manufacturing",
            "subcategory":"Electronics",
            "type":"Manufacturing & Wholesale Goods"
        }
    ],
    "sg:phone":"+1 818 884 9568",
    "sg:postcode":"91367",
    "sg:province":"CA",
    "sg:tags":[
        "equipment",
        "mfg",
        "communication"
    ],
    "wof:name":"Interntional Fnd For Telemetry",
    "wof:placetype":"venue"
},
  "geometry": {"coordinates":[-118.6049,34.177219],"type":"Point"}
}