{
  "type": "Feature",
  "properties": {
    "addr:full":"5835 el Dori Dr San Jose CA 95123",
    "addr:housenumber":"5835",
    "addr:postcode":"95123",
    "addr:street":"El Dori Dr",
    "iso:country":"US",
    "sg:address":"5835 el Dori Dr",
    "sg:city":"San Jose",
    "sg:classifiers":[
        {
            "category":"Social Services",
            "subcategory":"Child Care",
            "type":"Services"
        }
    ],
    "sg:phone":"+1 408 281 7855",
    "sg:postcode":"95123",
    "sg:province":"CA",
    "wof:name":"Precious Beginnings",
    "wof:placetype":"venue"
},
  "geometry": {"coordinates":[-121.863529,37.246824],"type":"Point"}
}