{
  "type": "Feature",
  "properties": {
    "addr:full":"4900 Irvine Boulevard Irvine CA 92620",
    "addr:housenumber":"4900",
    "addr:postcode":"92620",
    "addr:street":"Irvine Boulevard",
    "iso:country":"US",
    "sg:address":"4900 Irvine Boulevard",
    "sg:city":"Irvine",
    "sg:classifiers":[
        {
            "category":"Bakery",
            "type":"Food & Drink"
        }
    ],
    "sg:phone":"+1 714 730 5058",
    "sg:postcode":"92620",
    "sg:province":"CA",
    "wof:name":"Yale Bakery",
    "wof:placetype":"venue"
},
  "geometry": {"coordinates":[-117.758717,33.712682],"type":"Point"}
}