{
  "type": "Feature",
  "properties": {
    "addr:full":"5330 Carroll Canyon Rd, #210 San Diego CA 92121",
    "addr:housenumber":"5330",
    "addr:postcode":"92121",
    "addr:street":"Carroll Canyon Rd # 210",
    "iso:country":"US",
    "sg:address":"5330 Carroll Canyon Rd, #210",
    "sg:city":"San Diego",
    "sg:classifiers":[
        {
            "category":"Professional",
            "subcategory":"Computer Services",
            "type":"Services"
        }
    ],
    "sg:phone":"+1 88862376278",
    "sg:postcode":"92121",
    "sg:province":"CA",
    "sg:website":"http://www.smartmicros.com",
    "wof:name":"Smartmicros",
    "wof:placetype":"venue"
},
  "geometry": {"coordinates":[-117.192926,32.891711],"type":"Point"}
}