{
  "type": "Feature",
  "properties": {
    "addr:full":"5195 Brighton Dr Riverside CA 92504",
    "addr:housenumber":"5195",
    "addr:postcode":"92504",
    "addr:street":"Brighton Dr",
    "iso:country":"US",
    "sg:address":"5195 Brighton Dr",
    "sg:city":"Riverside",
    "sg:classifiers":[
        {
            "category":"Real Estate",
            "subcategory":"Real Estate Agent",
            "type":"Services"
        }
    ],
    "sg:phone":"+1 951 788 7090",
    "sg:postcode":"92504",
    "sg:province":"CA",
    "wof:name":"Wayne H Holcomb Realty",
    "wof:placetype":"venue"
},
  "geometry": {"coordinates":[-117.39915999999999,33.973397],"type":"Point"}
}