{
  "type": "Feature",
  "properties": {
    "addr:full":"33575 Yucaipa Blvd Ste 1 Yucaipa CA 92399",
    "addr:postcode":"33575;92399",
    "addr:street":"Yucaipa Blvd Ste 1",
    "iso:country":"US",
    "sg:address":"33575 Yucaipa Blvd Ste 1",
    "sg:city":"Yucaipa",
    "sg:classifiers":[
        {
            "category":"Home & Garden",
            "subcategory":"Carpets & Floor Coverings",
            "type":"Retail Goods"
        }
    ],
    "sg:phone":"+1 909 570 2805",
    "sg:postcode":"92399",
    "sg:province":"CA",
    "sg:tags":[
        "carpeting"
    ],
    "wof:name":"M & M Carpets",
    "wof:placetype":"venue"
},
  "geometry": {"coordinates":[-117.072998,34.033901],"type":"Point"}
}