{
  "type": "Feature",
  "properties": {
    "iso:country":"US",
    "sg:address":"146 W Cypress Ave",
    "sg:city":"Burbank",
    "sg:classifiers":[
        {
            "category":"Shopping",
            "type":"Retail Goods"
        }
    ],
    "sg:phone":"+1 818 972 2670",
    "sg:postcode":"91502",
    "sg:province":"CA",
    "sg:tags":[
        "picture",
        "frame"
    ],
    "wof:name":"Burbankframing Com",
    "wof:placetype":"venue"
},
  "geometry": {"coordinates":[-118.319085,34.17942],"type":"Point"}
}