{
  "type": "Feature",
  "properties": {
    "iso:country":"US",
    "sg:address":"4538 Wolsey Ct",
    "sg:city":"Westlake Village",
    "sg:classifiers":[
        {
            "category":"Professional",
            "type":"Services"
        }
    ],
    "sg:phone":"+1 818 706 2973",
    "sg:postcode":"91361",
    "sg:province":"CA",
    "wof:name":"Fourspancom LLC",
    "wof:placetype":"venue"
},
  "geometry": {"coordinates":[-118.818412,34.14753],"type":"Point"}
}