{
  "type": "Feature",
  "properties": {
    "addr:full":"6000 W Coast Hwy Newport Beach CA 92663",
    "addr:housenumber":"6000",
    "addr:postcode":"92663",
    "addr:street":"W Coast Hwy",
    "iso:country":"US",
    "sg:address":"6000 W Coast Hwy",
    "sg:city":"Newport Beach",
    "sg:classifiers":[
        {
            "category":"Personal",
            "subcategory":"Beauty Salon",
            "type":"Services"
        }
    ],
    "sg:phone":"+1 714 642 9446",
    "sg:postcode":"92663",
    "sg:province":"CA",
    "sg:tags":[
        "hair"
    ],
    "sg:website":"www.foxiehair.com",
    "wof:name":"Ali B Hair Lounge",
    "wof:placetype":"venue"
},
  "geometry": {"coordinates":[-117.947863,33.625703],"type":"Point"}
}