{
  "type": "Feature",
  "properties": {
    "addr:full":"4681 Convoy St San Diego CA 92111",
    "addr:housenumber":"4681",
    "addr:postcode":"92111",
    "addr:street":"Convoy St",
    "iso:country":"US",
    "sg:address":"4681 Convoy St",
    "sg:city":"San Diego",
    "sg:classifiers":[
        {
            "category":"Bars & Pubs",
            "type":"Food & Drink"
        },
        {
            "category":"Bars & Pubs",
            "subcategory":"Lounge",
            "type":"Food & Drink"
        }
    ],
    "sg:phone":"+1 858 569 6707",
    "sg:postcode":"92111",
    "sg:province":"CA",
    "sg:tags":[
        "karaoke"
    ],
    "wof:name":"Soju Town",
    "wof:placetype":"venue"
},
  "geometry": {"coordinates":[-117.15437,32.825651],"type":"Point"}
}