{
  "type": "Feature",
  "properties": {
    "addr:full":"23 Hurst Ct San Ramon CA 94583",
    "addr:housenumber":"23",
    "addr:postcode":"94583",
    "addr:street":"Hurst Ct",
    "iso:country":"US",
    "sg:address":"23 Hurst Ct",
    "sg:city":"San Ramon",
    "sg:classifiers":[
        {
            "category":"Freight",
            "type":"Transportation"
        }
    ],
    "sg:phone":"+1 925 838 0105",
    "sg:postcode":"94583",
    "sg:province":"CA",
    "wof:name":"GEP Intl Freight Forwarding",
    "wof:placetype":"venue"
},
  "geometry": {"coordinates":[-121.947553,37.729588],"type":"Point"}
}