{
  "type": "Feature",
  "properties": {
    "addr:full":"6341 Adobe Rd Twentynine Palms CA 92277",
    "addr:housenumber":"6341",
    "addr:postcode":"92277",
    "addr:street":"Adobe Rd",
    "iso:country":"US",
    "sg:address":"6341 Adobe Rd",
    "sg:city":"Twentynine Palms",
    "sg:classifiers":[
        {
            "category":"Restaurant",
            "type":"Food & Drink"
        }
    ],
    "sg:phone":"+1 760 367 9324",
    "sg:postcode":"92277",
    "sg:province":"CA",
    "sg:tags":[
        "delicatessen"
    ],
    "wof:name":"Yellow Ribbon Deli",
    "wof:placetype":"venue"
},
  "geometry": {"coordinates":[-116.054258,34.139405],"type":"Point"}
}