{
  "type": "Feature",
  "properties": {
    "addr:full":"1943 N Campus Ave Upland CA 91784",
    "addr:housenumber":"1943",
    "addr:postcode":"91784",
    "addr:street":"N Campus Ave",
    "iso:country":"US",
    "sg:address":"1943 N Campus Ave",
    "sg:city":"Upland",
    "sg:classifiers":[
        {
            "category":"Banks & Credit Unions",
            "subcategory":"Investment Brokerage",
            "type":"Services"
        },
        {
            "category":"Insurance",
            "subcategory":"Life Insurance",
            "type":"Services"
        },
        {
            "category":"Banks & Credit Unions",
            "subcategory":"Financial Services",
            "type":"Services"
        }
    ],
    "sg:phone":"+1 909 829 5475",
    "sg:postcode":"91784",
    "sg:province":"CA",
    "sg:tags":[
        "advisory",
        "retirement",
        "plan",
        "mortgage",
        "annuity"
    ],
    "wof:name":"401k Rollovers",
    "wof:placetype":"venue"
},
  "geometry": {"coordinates":[-117.637604,34.132832],"type":"Point"}
}