{
  "type": "Feature",
  "properties": {
    "addr:full":"6535 Pacific Boulevard Huntington Park CA 90255",
    "addr:housenumber":"6535",
    "addr:postcode":"90255",
    "addr:street":"Pacific Boulevard;Park",
    "iso:country":"US",
    "sg:address":"6535 Pacific Boulevard",
    "sg:city":"Huntington Park",
    "sg:classifiers":[
        {
            "category":"Shopping",
            "subcategory":"Shoes",
            "type":"Retail Goods"
        }
    ],
    "sg:phone":"+1 323 589 3141",
    "sg:postcode":"90255",
    "sg:province":"CA",
    "sg:tags":[
        "store"
    ],
    "wof:name":"Shoe Hut",
    "wof:placetype":"venue"
},
  "geometry": {"coordinates":[-118.225094,33.979654],"type":"Point"}
}