{
  "type": "Feature",
  "properties": {
    "addr:full":"3575 Stevens Creek Blvd Ste F San Jose CA 95117",
    "addr:housenumber":"3575",
    "addr:postcode":"95117",
    "addr:street":"Stevens Creek Blvd Ste F",
    "iso:country":"US",
    "sg:address":"3575 Stevens Creek Blvd Ste F",
    "sg:city":"San Jose",
    "sg:classifiers":[
        {
            "category":"Personal",
            "subcategory":"Beauty Salon",
            "type":"Services"
        },
        {
            "category":"Personal",
            "subcategory":"Nail Salon",
            "type":"Services"
        }
    ],
    "sg:phone":"+1 408 771 8181",
    "sg:postcode":"95117",
    "sg:province":"CA",
    "sg:tags":[
        "hair"
    ],
    "wof:name":"Face To Face Hair Salon",
    "wof:placetype":"venue"
},
  "geometry": {"coordinates":[-121.961781,37.323645],"type":"Point"}
}