{
  "type": "Feature",
  "properties": {
    "iso:country":"US",
    "sg:address":"1090 Park Blvd",
    "sg:city":"Orange Cove",
    "sg:classifiers":[
        {
            "category":"Wholesale",
            "subcategory":"Motor Vehicles",
            "type":"Manufacturing & Wholesale Goods"
        }
    ],
    "sg:phone":"+1 559 626 7410",
    "sg:postcode":"93646",
    "sg:province":"CA",
    "sg:tags":[
        "automobile",
        "truck",
        "broker"
    ],
    "wof:name":"Macias Auto Sales",
    "wof:placetype":"venue"
},
  "geometry": {"coordinates":[-119.317937,36.624677],"type":"Point"}
}