{
  "type": "Feature",
  "properties": {
    "iso:country":"US",
    "sg:address":"73315 Country Club Dr",
    "sg:city":"Palm Desert",
    "sg:classifiers":[
        {
            "category":"Real Estate",
            "subcategory":"Real Estate Operator",
            "type":"Services"
        }
    ],
    "sg:phone":"+1 760 773 9040",
    "sg:postcode":"92260",
    "sg:province":"CA",
    "sg:tags":[
        "apartment"
    ],
    "wof:name":"Las Serenas Apartments",
    "wof:placetype":"venue"
},
  "geometry": {"coordinates":[-116.37374699999999,33.757985],"type":"Point"}
}