{
  "type": "Feature",
  "properties": {
    "iso:country":"US",
    "sg:address":"1377 Caspian Ave",
    "sg:city":"Long Beach",
    "sg:classifiers":[
        {
            "category":"Government",
            "subcategory":"Office",
            "type":"Public Place"
        }
    ],
    "sg:phone":"+1 562 491 4665",
    "sg:postcode":"90813",
    "sg:province":"CA",
    "sg:tags":[
        "smog",
        "check"
    ],
    "wof:name":"Westside Auto",
    "wof:placetype":"venue"
},
  "geometry": {"coordinates":[-118.211998,33.7836],"type":"Point"}
}