{
  "type": "Feature",
  "properties": {
    "addr:full":"54 Chatsworth Ct Oakland CA 94611",
    "addr:housenumber":"54",
    "addr:postcode":"94611",
    "addr:street":"Chatsworth Ct",
    "iso:country":"US",
    "sg:address":"54 Chatsworth Ct",
    "sg:city":"Oakland",
    "sg:classifiers":[
        {
            "category":"Wholesale",
            "subcategory":"Wine & Distilled Alcoholic Beverages",
            "type":"Manufacturing & Wholesale Goods"
        }
    ],
    "sg:phone":"+1 510 530 1952",
    "sg:postcode":"94611",
    "sg:province":"CA",
    "sg:tags":[
        "broker"
    ],
    "wof:name":"Brand Builders Brokerage",
    "wof:placetype":"venue"
},
  "geometry": {"coordinates":[-122.198409,37.823013],"type":"Point"}
}