{
  "type": "Feature",
  "properties": {
    "iso:country":"US",
    "sg:address":"531 W Lockeford St",
    "sg:city":"Lodi",
    "sg:classifiers":[
        {
            "category":"Shopping",
            "subcategory":"Computers & Home Electronics",
            "type":"Retail Goods"
        }
    ],
    "sg:phone":"+1 209 368 4025",
    "sg:postcode":"95240",
    "sg:province":"CA",
    "sg:tags":[
        "equipment",
        "dealer"
    ],
    "wof:name":"Computer Works",
    "wof:placetype":"venue"
},
  "geometry": {"coordinates":[-121.280154,38.138141],"type":"Point"}
}