{
  "type": "Feature",
  "properties": {
    "addr:full":"14669 Aetna St Van Nuys CA 91411",
    "addr:postcode":"14669;91411",
    "addr:street":"Aetna St",
    "iso:country":"US",
    "sg:address":"14669 Aetna St",
    "sg:city":"Van Nuys",
    "sg:classifiers":[
        {
            "category":"Building & Trades",
            "subcategory":"Construction",
            "type":"Services"
        }
    ],
    "sg:phone":"+1 818 761 3760",
    "sg:postcode":"91411",
    "sg:province":"CA",
    "sg:tags":[
        "resurfacing",
        "laying",
        "refinishing",
        "floor"
    ],
    "wof:name":"Richards Floor Co Inc",
    "wof:placetype":"venue"
},
  "geometry": {"coordinates":[-118.451824,34.180207],"type":"Point"}
}