{
  "type": "Feature",
  "properties": {
    "addr:full":"3227 Scotland Dr Antelope CA 95843",
    "addr:housenumber":"3227",
    "addr:postcode":"95843",
    "addr:street":"Scotland Dr",
    "iso:country":"US",
    "sg:address":"3227 Scotland Dr",
    "sg:city":"Antelope",
    "sg:classifiers":[
        {
            "category":"Professional",
            "subcategory":"Accounting & Tax Preparation",
            "type":"Services"
        }
    ],
    "sg:phone":"+1 916 344 2604",
    "sg:postcode":"95843",
    "sg:province":"CA",
    "sg:tags":[
        "billing"
    ],
    "wof:name":"Claims Fever",
    "wof:placetype":"venue"
},
  "geometry": {"coordinates":[-121.38835899999999,38.70659],"type":"Point"}
}