{
  "type": "Feature",
  "properties": {
    "addr:full":"4630 Balboa St San Francisco CA 94121",
    "addr:housenumber":"4630",
    "addr:postcode":"94121",
    "addr:street":"Balboa St",
    "iso:country":"US",
    "sg:address":"4630 Balboa St",
    "sg:city":"San Francisco",
    "sg:classifiers":[
        {
            "category":"Professional",
            "type":"Services"
        },
        {
            "category":"Food & Beverages",
            "subcategory":"Specialty",
            "type":"Retail Goods"
        },
        {
            "category":"Education",
            "subcategory":"Vocational School",
            "type":"Public Place"
        }
    ],
    "sg:phone":"+1 415 242 4192",
    "sg:postcode":"94121",
    "sg:province":"CA",
    "sg:tags":[
        "cooking",
        "caterer"
    ],
    "sg:website":"www.theculinarydude.com",
    "wof:name":"The Culinary Dude",
    "wof:placetype":"venue"
},
  "geometry": {"coordinates":[-122.508578,37.775446],"type":"Point"}
}