{
  "type": "Feature",
  "properties": {
    "iso:country":"US",
    "sg:address":"11301 W Olympic Blvd",
    "sg:city":"Los Angeles",
    "sg:classifiers":[
        {
            "category":"Building & Trades",
            "subcategory":"Cleaning & Sanitation",
            "type":"Services"
        }
    ],
    "sg:phone":"+1 310 388 6378",
    "sg:postcode":"90064",
    "sg:province":"CA",
    "sg:tags":[
        "carpet"
    ],
    "wof:name":"Carpet Upholstery Rug & Air Duct Cleaning",
    "wof:placetype":"venue"
},
  "geometry": {"coordinates":[-118.441283,34.038197],"type":"Point"}
}