{
  "type": "Feature",
  "properties": {
    "addr:full":"4110 Alhambra Way Martinez CA 94553",
    "addr:housenumber":"4110",
    "addr:postcode":"94553",
    "addr:street":"Alhambra Way",
    "iso:country":"US",
    "sg:address":"4110 Alhambra Way",
    "sg:city":"Martinez",
    "sg:classifiers":[
        {
            "category":"Health Services",
            "subcategory":"Nursing And Care Facility",
            "type":"Services"
        }
    ],
    "sg:phone":"+1 925 228 8396",
    "sg:postcode":"94553",
    "sg:province":"CA",
    "sg:tags":[
        "home",
        "convalescent"
    ],
    "wof:name":"Thekkek Health Svc Inc",
    "wof:placetype":"venue"
},
  "geometry": {"coordinates":[-122.12872,37.994372],"type":"Point"}
}