{
  "type": "Feature",
  "properties": {
    "addr:full":"507 Tahos Rd Orinda CA 94563",
    "addr:housenumber":"507",
    "addr:postcode":"94563",
    "addr:street":"Tahos Rd",
    "iso:country":"US",
    "sg:address":"507 Tahos Rd",
    "sg:city":"Orinda",
    "sg:classifiers":[
        {
            "category":"Professional",
            "type":"Services"
        }
    ],
    "sg:phone":"+1 925 253 8581",
    "sg:postcode":"94563",
    "sg:province":"CA",
    "wof:name":"Qtca Inc",
    "wof:placetype":"venue"
},
  "geometry": {"coordinates":[-122.166753,37.886614],"type":"Point"}
}