{
  "type": "Feature",
  "properties": {
    "iso:country":"US",
    "sg:address":"420 N Varney St",
    "sg:city":"Burbank",
    "sg:classifiers":[
        {
            "category":"Manufacturing",
            "subcategory":"Tools & Machinery",
            "type":"Manufacturing & Wholesale Goods"
        }
    ],
    "sg:phone":"+1 818 843 6602",
    "sg:postcode":"91502",
    "sg:province":"CA",
    "sg:tags":[
        "mold"
    ],
    "wof:name":"American Drainage System",
    "wof:placetype":"venue"
},
  "geometry": {"coordinates":[-118.317353,34.180929],"type":"Point"}
}