{
  "type": "Feature",
  "properties": {
    "addr:full":"36039 Magellan Dr Fremont CA 94536",
    "addr:housenumber":"36039",
    "addr:postcode":"94536",
    "addr:street":"Magellan Dr",
    "iso:country":"US",
    "sg:address":"36039 Magellan Dr",
    "sg:city":"Fremont",
    "sg:classifiers":[
        {
            "category":"Home & Garden",
            "subcategory":"Building Materials",
            "type":"Retail Goods"
        }
    ],
    "sg:phone":"+1 510 794 8334",
    "sg:postcode":"94536",
    "sg:province":"CA",
    "sg:tags":[
        "shutter"
    ],
    "wof:name":"Carl's Installations",
    "wof:placetype":"venue"
},
  "geometry": {"coordinates":[-122.029077,37.557152],"type":"Point"}
}