{
  "type": "Feature",
  "properties": {
    "addr:full":"18456 Dearborn St Northridge CA 91324",
    "addr:housenumber":"18456",
    "addr:postcode":"91324",
    "addr:street":"Dearborn St",
    "iso:country":"US",
    "sg:address":"18456 Dearborn St",
    "sg:city":"Northridge",
    "sg:classifiers":[
        {
            "category":"Restaurant",
            "type":"Food & Drink"
        }
    ],
    "sg:phone":"+1 818 886 3688",
    "sg:postcode":"91324",
    "sg:province":"CA",
    "wof:name":"Subway Sandwiches & Salads",
    "wof:placetype":"venue"
},
  "geometry": {"coordinates":[-118.533901,34.237305],"type":"Point"}
}