{
  "type": "Feature",
  "properties": {
    "iso:country":"US",
    "sg:address":"1233 W Ave I",
    "sg:city":"Lancaster",
    "sg:classifiers":[
        {
            "category":"Shopping",
            "subcategory":"Jewelry",
            "type":"Retail Goods"
        }
    ],
    "sg:phone":"+1 661 942 4990",
    "sg:postcode":"93534",
    "sg:province":"CA",
    "sg:tags":[
        "jeweler"
    ],
    "wof:name":"B & E Pawn Shop",
    "wof:placetype":"venue"
},
  "geometry": {"coordinates":[-118.151813,34.704054],"type":"Point"}
}