{
  "type": "Feature",
  "properties": {
    "iso:country":"US",
    "sg:address":"9028 Winding Way",
    "sg:city":"Oregon House",
    "sg:classifiers":[
        {
            "category":"Manufacturing",
            "subcategory":"Food",
            "type":"Manufacturing & Wholesale Goods"
        }
    ],
    "sg:phone":"+1 530 692 2314",
    "sg:postcode":"95962",
    "sg:province":"CA",
    "sg:tags":[
        "olive",
        "oil"
    ],
    "wof:name":"Apollo Olive Oil",
    "wof:placetype":"venue"
},
  "geometry": {"coordinates":[-121.269264,39.320744],"type":"Point"}
}