{
  "type": "Feature",
  "properties": {
    "iso:country":"US",
    "sg:address":"952 Avocado Ave",
    "sg:city":"Newport Beach",
    "sg:classifiers":[
        {
            "category":"Restaurant",
            "type":"Food & Drink"
        }
    ],
    "sg:phone":"+1 949 640 9256",
    "sg:postcode":"92660",
    "sg:province":"CA",
    "sg:tags":[
        "dessert",
        "parlor",
        "ice",
        "cream"
    ],
    "sg:website":"www.gelatoparadiso.net/",
    "wof:name":"Gelato Paradiso",
    "wof:placetype":"venue"
},
  "geometry": {"coordinates":[-117.87482199999999,33.60669],"type":"Point"}
}