{
  "type": "Feature",
  "properties": {
    "iso:country":"US",
    "sg:address":"1023 Espee St",
    "sg:city":"Bakersfield",
    "sg:classifiers":[
        {
            "category":"Professional",
            "type":"Services"
        }
    ],
    "sg:phone":"+1 661 587 8468",
    "sg:postcode":"93301",
    "sg:province":"CA",
    "wof:name":"Tom M Armistead Inc",
    "wof:placetype":"venue"
},
  "geometry": {"coordinates":[-119.013375,35.385886],"type":"Point"}
}