{
  "type": "Feature",
  "properties": {
    "addr:full":"78 2nd St San Francisco CA 94105",
    "addr:housenumber":"78",
    "addr:postcode":"94105",
    "addr:street":"2Nd St",
    "iso:country":"US",
    "sg:address":"78 2nd St",
    "sg:city":"San Francisco",
    "sg:classifiers":[
        {
            "category":"Restaurant",
            "type":"Food & Drink"
        }
    ],
    "sg:phone":"+1 415 543 8226",
    "sg:postcode":"94105",
    "sg:province":"CA",
    "wof:name":"Si Senor",
    "wof:placetype":"venue"
},
  "geometry": {"coordinates":[-122.399975,37.788078],"type":"Point"}
}