{
  "type": "Feature",
  "properties": {
    "addr:full":"2072 Walsh Ave Santa Clara CA 95050",
    "addr:housenumber":"2072",
    "addr:postcode":"95050",
    "addr:street":"Walsh Ave",
    "iso:country":"US",
    "sg:address":"2072 Walsh Ave",
    "sg:city":"Santa Clara",
    "sg:classifiers":[
        {
            "category":"Wholesale",
            "subcategory":"Electrical",
            "type":"Manufacturing & Wholesale Goods"
        }
    ],
    "sg:phone":"+1 408 988 8588",
    "sg:postcode":"95050",
    "sg:province":"CA",
    "sg:tags":[
        "electronic",
        "representative"
    ],
    "wof:name":"Hyckers Valley Intl Corp",
    "wof:placetype":"venue"
},
  "geometry": {"coordinates":[-121.960728,37.36939],"type":"Point"}
}