{
  "type": "Feature",
  "properties": {
    "iso:country":"US",
    "sg:address":"14042 Central Ave",
    "sg:city":"Chino",
    "sg:classifiers":[
        {
            "category":"Wholesale",
            "subcategory":"Electrical",
            "type":"Manufacturing & Wholesale Goods"
        }
    ],
    "sg:phone":"+1 909 364 8517",
    "sg:postcode":"91710",
    "sg:province":"CA",
    "sg:tags":[
        "supply",
        "sign"
    ],
    "sg:website":"www.dencosales.com",
    "wof:name":"Denco Sales",
    "wof:placetype":"venue"
},
  "geometry": {"coordinates":[-117.689131,33.999806],"type":"Point"}
}