{
  "type": "Feature",
  "properties": {
    "iso:country":"US",
    "sg:address":"1562 Auburn Blvd",
    "sg:city":"Sacramento",
    "sg:classifiers":[
        {
            "category":"Retail",
            "subcategory":"Auto Repair",
            "type":"Services"
        }
    ],
    "sg:phone":"+1 916 925 4902",
    "sg:postcode":"95815",
    "sg:province":"CA",
    "sg:tags":[
        "body",
        "shop"
    ],
    "wof:name":"Vo-Tech Auto Body",
    "wof:placetype":"venue"
},
  "geometry": {"coordinates":[-121.431,38.614498],"type":"Point"}
}