{
  "type": "Feature",
  "properties": {
    "iso:country":"US",
    "sg:address":"946 Donax Ave",
    "sg:city":"Imperial Beach",
    "sg:classifiers":[
        {
            "category":"Government",
            "subcategory":"Post Office",
            "type":"Public Place"
        }
    ],
    "sg:phone":"+1 619 423 1677",
    "sg:postcode":"91932",
    "sg:province":"CA",
    "sg:tags":[
        "postal",
        "u"
    ],
    "sg:website":"www.usps.com",
    "wof:name":"US Post Office",
    "wof:placetype":"venue"
},
  "geometry": {"coordinates":[-117.11318199999999,32.582308],"type":"Point"}
}