{
  "type": "Feature",
  "properties": {
    "addr:full":"12000 Washington Pl Los Angeles CA 90066",
    "addr:housenumber":"12000",
    "addr:postcode":"90066",
    "addr:street":"Washington Pl",
    "iso:country":"US",
    "sg:address":"12000 Washington Pl",
    "sg:city":"Los Angeles",
    "sg:classifiers":[
        {
            "category":"Home & Garden",
            "subcategory":"Building Materials",
            "type":"Retail Goods"
        }
    ],
    "sg:phone":"+1 805 813 1625",
    "sg:postcode":"90066",
    "sg:province":"CA",
    "sg:tags":[
        "equipment",
        "fixture",
        "lighting"
    ],
    "wof:name":"Christmas Lights Installation",
    "wof:placetype":"venue"
},
  "geometry": {"coordinates":[-118.42541900000001,34.001582],"type":"Point"}
}