{
  "type": "Feature",
  "properties": {
    "iso:country":"US",
    "sg:address":"5944 Pennswood Ave",
    "sg:city":"Lakewood",
    "sg:classifiers":[
        {
            "category":"Health Services",
            "subcategory":"Doctor",
            "type":"Services"
        }
    ],
    "sg:phone":"+1 562 461 2168",
    "sg:postcode":"90712",
    "sg:province":"CA",
    "sg:tags":[
        "clinic"
    ],
    "wof:name":"DAU Medical",
    "wof:placetype":"venue"
},
  "geometry": {"coordinates":[-118.136505,33.863229],"type":"Point"}
}