{
  "type": "Feature",
  "properties": {
    "addr:full":"1540 Marine Ave Manhattan Beach CA 90266",
    "addr:housenumber":"1540",
    "addr:postcode":"90266",
    "addr:street":"Marine Ave",
    "iso:country":"US",
    "sg:address":"1540 Marine Ave",
    "sg:city":"Manhattan Beach",
    "sg:classifiers":[
        {
            "category":"Professional",
            "subcategory":"Management & Consulting",
            "type":"Services"
        }
    ],
    "sg:phone":"+1 310 546 5994",
    "sg:postcode":"90266",
    "sg:province":"CA",
    "sg:tags":[
        "counselor",
        "public",
        "relations"
    ],
    "wof:name":"Bob Benoit & Assoc",
    "wof:placetype":"venue"
},
  "geometry": {"coordinates":[-118.386836,33.894568],"type":"Point"}
}