{
  "type": "Feature",
  "properties": {
    "addr:full":"1222 Atwater Blvd Atwater CA 95301",
    "addr:housenumber":"1222",
    "addr:postcode":"95301",
    "addr:street":"Atwater Blvd",
    "iso:country":"US",
    "sg:address":"1222 Atwater Blvd",
    "sg:city":"Atwater",
    "sg:classifiers":[
        {
            "category":"Wholesale",
            "subcategory":"Farm Supplies",
            "type":"Manufacturing & Wholesale Goods"
        }
    ],
    "sg:phone":"+1 209 358 1840",
    "sg:postcode":"95301",
    "sg:province":"CA",
    "wof:name":"Atwater Feed",
    "wof:placetype":"venue"
},
  "geometry": {"coordinates":[-120.610191,37.346255],"type":"Point"}
}