{
  "type": "Feature",
  "properties": {
    "addr:full":"12801 Halldale Ave Gardena CA 90249",
    "addr:housenumber":"12801",
    "addr:postcode":"90249",
    "addr:street":"Halldale Ave",
    "iso:country":"US",
    "sg:address":"12801 Halldale Ave",
    "sg:city":"Gardena",
    "sg:classifiers":[
        {
            "category":"Professional",
            "subcategory":"Management & Consulting",
            "type":"Services"
        }
    ],
    "sg:phone":"+1 310 329 5790",
    "sg:postcode":"90249",
    "sg:province":"CA",
    "sg:tags":[
        "consultant",
        "construction"
    ],
    "wof:name":"Gene Mechanical Construction",
    "wof:placetype":"venue"
},
  "geometry": {"coordinates":[-118.302284,33.914545],"type":"Point"}
}