{
  "type": "Feature",
  "properties": {
    "iso:country":"US",
    "sg:address":"2159 Warwick Dr",
    "sg:city":"Benicia",
    "sg:classifiers":[
        {
            "category":"Personal",
            "type":"Services"
        }
    ],
    "sg:phone":"+1 707 746 0828",
    "sg:postcode":"94510",
    "sg:province":"CA",
    "sg:tags":[
        "color",
        "consultant"
    ],
    "wof:name":"Seasonality",
    "wof:placetype":"venue"
},
  "geometry": {"coordinates":[-122.15343799999999,38.063836],"type":"Point"}
}