{
  "type": "Feature",
  "properties": {
    "iso:country":"US",
    "sg:address":"20257 Modoc Rd",
    "sg:city":"Apple Valley",
    "sg:classifiers":[
        {
            "category":"Real Estate",
            "subcategory":"Real Estate Agent",
            "type":"Services"
        }
    ],
    "sg:phone":"+1 760 240 7704",
    "sg:postcode":"92308",
    "sg:province":"CA",
    "wof:name":"High Desert Realty & Invstmnt",
    "wof:placetype":"venue"
},
  "geometry": {"coordinates":[-117.22157300000001,34.487047],"type":"Point"}
}