{
  "type": "Feature",
  "properties": {
    "iso:country":"US",
    "sg:address":"4552 Portola Dr",
    "sg:city":"Fremont",
    "sg:classifiers":[
        {
            "category":"Professional",
            "type":"Services"
        }
    ],
    "sg:phone":"+1 510 742 5533",
    "sg:postcode":"94536",
    "sg:province":"CA",
    "wof:name":"At Home Secretary",
    "wof:placetype":"venue"
},
  "geometry": {"coordinates":[-122.019904,37.556765],"type":"Point"}
}