{
  "type": "Feature",
  "properties": {
    "addr:full":"9725 Mission Gorge Rd Santee CA 92071",
    "addr:housenumber":"9725",
    "addr:postcode":"92071",
    "addr:street":"Mission Gorge Rd",
    "iso:country":"US",
    "sg:address":"9725 Mission Gorge Rd",
    "sg:city":"Santee",
    "sg:classifiers":[
        {
            "category":"Professional",
            "type":"Services"
        }
    ],
    "sg:phone":"+1 619 258 9705",
    "sg:postcode":"92071",
    "sg:province":"CA",
    "wof:name":"Innovative Office Product",
    "wof:placetype":"venue"
},
  "geometry": {"coordinates":[-116.986581,32.838609],"type":"Point"}
}