{
  "type": "Feature",
  "properties": {
    "addr:full":"2151 de Anza Blvd San Mateo CA 94402",
    "addr:housenumber":"2151",
    "addr:postcode":"94402",
    "addr:street":"De Anza Blvd",
    "iso:country":"US",
    "sg:address":"2151 de Anza Blvd",
    "sg:city":"San Mateo",
    "sg:classifiers":[
        {
            "category":"Manufacturing",
            "subcategory":"Jewelry",
            "type":"Manufacturing & Wholesale Goods"
        }
    ],
    "sg:phone":"+1 650 224 4840",
    "sg:postcode":"94402",
    "sg:province":"CA",
    "sg:tags":[
        "costume",
        "mfg"
    ],
    "wof:name":"Catwerk Designs",
    "wof:placetype":"venue"
},
  "geometry": {"coordinates":[-122.336788,37.520467],"type":"Point"}
}