{
  "type": "Feature",
  "properties": {
    "iso:country":"US",
    "sg:address":"6160 Fairmount Ave",
    "sg:city":"San Diego",
    "sg:classifiers":[
        {
            "category":"Professional",
            "subcategory":"Research",
            "type":"Services"
        }
    ],
    "sg:phone":"+1 619 299 0033",
    "sg:postcode":"92120",
    "sg:province":"CA",
    "sg:tags":[
        "environmental",
        "ecological"
    ],
    "sg:website":"www.enecotech.com",
    "wof:name":"Eneco Tech Inc",
    "wof:placetype":"venue"
},
  "geometry": {"coordinates":[-117.101478,32.788255],"type":"Point"}
}