{
  "type": "Feature",
  "properties": {
    "addr:full":"401 Vine Ave Sebastopol CA 95472",
    "addr:housenumber":"401",
    "addr:postcode":"95472",
    "addr:street":"Vine Ave",
    "iso:country":"US",
    "sg:address":"401 Vine Ave",
    "sg:city":"Sebastopol",
    "sg:classifiers":[
        {
            "category":"Professional",
            "type":"Services"
        }
    ],
    "sg:phone":"+1 707 823 9445",
    "sg:postcode":"95472",
    "sg:province":"CA",
    "wof:name":"Zap Okinawa",
    "wof:placetype":"venue"
},
  "geometry": {"coordinates":[-122.823886,38.397216],"type":"Point"}
}