{
  "type": "Feature",
  "properties": {
    "addr:full":"3991 Ohio St San Diego CA 92104",
    "addr:housenumber":"3991",
    "addr:postcode":"92104",
    "addr:street":"Ohio St",
    "iso:country":"US",
    "sg:address":"3991 Ohio St",
    "sg:city":"San Diego",
    "sg:classifiers":[
        {
            "category":"Real Estate",
            "subcategory":"Real Estate Services",
            "type":"Services"
        }
    ],
    "sg:phone":"+1 619 291 1776",
    "sg:postcode":"92104",
    "sg:province":"CA",
    "sg:tags":[
        "management",
        "property"
    ],
    "wof:name":"Protax",
    "wof:placetype":"venue"
},
  "geometry": {"coordinates":[-117.128998,32.75],"type":"Point"}
}