{
  "type": "Feature",
  "properties": {
    "iso:country":"US",
    "sg:address":"3775 Beacon Ave",
    "sg:city":"Fremont",
    "sg:classifiers":[
        {
            "category":"Social Services",
            "subcategory":"Job Training",
            "type":"Services"
        }
    ],
    "sg:phone":"+1 510 794 5155",
    "sg:postcode":"94538",
    "sg:province":"CA",
    "sg:tags":[
        "career",
        "counseling",
        "rehabilitation",
        "vocational"
    ],
    "wof:name":"Center For Speech Language",
    "wof:placetype":"venue"
},
  "geometry": {"coordinates":[-121.982737,37.547959],"type":"Point"}
}