{
  "type": "Feature",
  "properties": {
    "iso:country":"US",
    "sg:address":"100 Sprig Ct",
    "sg:city":"Roseville",
    "sg:classifiers":[
        {
            "category":"Real Estate",
            "subcategory":"Real Estate Services",
            "type":"Services"
        },
        {
            "category":"Real Estate",
            "subcategory":"Real Estate Agent",
            "type":"Services"
        }
    ],
    "sg:phone":"+1 916 783 1181",
    "sg:postcode":"95678",
    "sg:province":"CA",
    "sg:tags":[
        "buyer",
        "broker"
    ],
    "wof:name":"Cristina Farinas Realtor",
    "wof:placetype":"venue"
},
  "geometry": {"coordinates":[-121.301498,38.77018],"type":"Point"}
}