{
  "type": "Feature",
  "properties": {
    "iso:country":"US",
    "sg:address":"3356 Roxanne Ave",
    "sg:city":"Long Beach",
    "sg:classifiers":[
        {
            "category":"Manufacturing",
            "subcategory":"Musical Instruments",
            "type":"Manufacturing & Wholesale Goods"
        }
    ],
    "sg:phone":"+1 562 420 7926",
    "sg:postcode":"90808",
    "sg:province":"CA",
    "sg:tags":[
        "mfg"
    ],
    "wof:name":"Rocellie",
    "wof:placetype":"venue"
},
  "geometry": {"coordinates":[-118.09633,33.81546],"type":"Point"}
}