{
  "type": "Feature",
  "properties": {
    "addr:full":"412 S Bon View Ave Ontario CA 91761",
    "addr:housenumber":"412",
    "addr:postcode":"91761",
    "addr:street":"S Bon View Ave",
    "iso:country":"US",
    "sg:address":"412 S Bon View Ave",
    "sg:city":"Ontario",
    "sg:classifiers":[
        {
            "category":"Retail",
            "subcategory":"Auto Repair",
            "type":"Services"
        }
    ],
    "sg:phone":"+1 909 467 0371",
    "sg:postcode":"91761",
    "sg:province":"CA",
    "sg:tags":[
        "repairing",
        "automobile"
    ],
    "wof:name":"Anglin's Garage",
    "wof:placetype":"venue"
},
  "geometry": {"coordinates":[-117.636709,34.059488],"type":"Point"}
}