{
  "type": "Feature",
  "properties": {
    "addr:full":"28 Centerpointe Dr La Palma CA 90623",
    "addr:housenumber":"28",
    "addr:postcode":"90623",
    "addr:street":"Centerpointe Dr",
    "iso:country":"US",
    "sg:address":"28 Centerpointe Dr",
    "sg:city":"La Palma",
    "sg:classifiers":[
        {
            "category":"Retail",
            "subcategory":"Repair Shop",
            "type":"Services"
        }
    ],
    "sg:phone":"+1 714 522 2257",
    "sg:postcode":"90623",
    "sg:province":"CA",
    "sg:tags":[
        "equipment",
        "medical"
    ],
    "sg:website":"www.gehealthcare.com",
    "wof:name":"Fibertech Medical",
    "wof:placetype":"venue"
},
  "geometry": {"coordinates":[-118.03182099999999,33.861417],"type":"Point"}
}