{
  "type": "Feature",
  "properties": {
    "iso:country":"US",
    "sg:address":"481 S Murphy Ave",
    "sg:city":"Sunnyvale",
    "sg:classifiers":[
        {
            "category":"Health Services",
            "subcategory":"Chiropractor",
            "type":"Services"
        }
    ],
    "sg:phone":"+1 408 736 7777",
    "sg:postcode":"94086",
    "sg:province":"CA",
    "sg:tags":[
        "chiropractic"
    ],
    "sg:website":"http://www.sunnyvalechiropractic.com",
    "wof:name":"Sunnyvale Chiropractic",
    "wof:placetype":"venue"
},
  "geometry": {"coordinates":[-122.031998,37.371399],"type":"Point"}
}