{
  "type": "Feature",
  "properties": {
    "addr:full":"8006 Van Nuys Blvd Van Nuys CA 91402",
    "addr:housenumber":"8006",
    "addr:postcode":"91402",
    "addr:street":"Van Nuys Blvd",
    "iso:country":"US",
    "sg:address":"8006 Van Nuys Blvd",
    "sg:city":"Van Nuys",
    "sg:classifiers":[
        {
            "category":"Banks & Credit Unions",
            "subcategory":"Bank",
            "type":"Services"
        }
    ],
    "sg:phone":"+1 818 374 9211",
    "sg:postcode":"91402",
    "sg:province":"CA",
    "sg:tags":[
        "cashing",
        "check"
    ],
    "wof:name":"Cash Plus",
    "wof:placetype":"venue"
},
  "geometry": {"coordinates":[-118.448611,34.215425],"type":"Point"}
}