{
  "type": "Feature",
  "properties": {
    "addr:full":"116 E 5th St Los Angeles CA 90013",
    "addr:housenumber":"116",
    "addr:postcode":"90013",
    "addr:street":"E 5Th St",
    "iso:country":"US",
    "sg:address":"116 E 5th St",
    "sg:city":"Los Angeles",
    "sg:classifiers":[
        {
            "category":"Food & Beverages",
            "subcategory":"Groceries & Convenience Stores",
            "type":"Retail Goods"
        }
    ],
    "sg:phone":"+1 213 628 1825",
    "sg:postcode":"90013",
    "sg:province":"CA",
    "sg:tags":[
        "grocer"
    ],
    "wof:name":"Fifth Street Mkt",
    "wof:placetype":"venue"
},
  "geometry": {"coordinates":[-118.248001,34.0462],"type":"Point"}
}