{
  "type": "Feature",
  "properties": {
    "iso:country":"US",
    "sg:address":"21101 Mission Blvd",
    "sg:city":"Hayward",
    "sg:classifiers":[
        {
            "category":"Shopping",
            "subcategory":"Gifts & Souvenirs",
            "type":"Retail Goods"
        }
    ],
    "sg:phone":"+1 510 651 2444",
    "sg:postcode":"94541",
    "sg:province":"CA",
    "sg:tags":[
        "shop"
    ],
    "wof:name":"Designer Express",
    "wof:placetype":"venue"
},
  "geometry": {"coordinates":[-122.09741200000001,37.68306],"type":"Point"}
}