{
  "type": "Feature",
  "properties": {
    "addr:full":"6839 Five Star Blvd Rocklin CA 95677",
    "addr:housenumber":"6839",
    "addr:postcode":"95677",
    "addr:street":"Five Star Blvd",
    "iso:country":"US",
    "sg:address":"6839 Five Star Blvd",
    "sg:city":"Rocklin",
    "sg:classifiers":[
        {
            "category":"Shopping",
            "subcategory":"Bicycles & Sporting Goods",
            "type":"Retail Goods"
        }
    ],
    "sg:phone":"+1 916 624 3483",
    "sg:postcode":"95677",
    "sg:province":"CA",
    "sg:tags":[
        "equipment",
        "diver",
        "supply"
    ],
    "wof:name":"Nautilus Diving & Sports Ctr",
    "wof:placetype":"venue"
},
  "geometry": {"coordinates":[-121.266599,38.781741],"type":"Point"}
}