{
  "type": "Feature",
  "properties": {
    "addr:full":"3421 Coach Ln Cameron Park CA 95682",
    "addr:housenumber":"3421",
    "addr:postcode":"95682",
    "addr:street":"Coach Ln",
    "iso:country":"US",
    "sg:address":"3421 Coach Ln",
    "sg:city":"Cameron Park",
    "sg:classifiers":[
        {
            "category":"Restaurant",
            "type":"Food & Drink"
        }
    ],
    "sg:phone":"+1 530 677 3611",
    "sg:postcode":"95682",
    "sg:province":"CA",
    "wof:name":"3 Brothers Restaurant",
    "wof:placetype":"venue"
},
  "geometry": {"coordinates":[-120.9682,38.658233],"type":"Point"}
}