{
  "type": "Feature",
  "properties": {
    "addr:full":"11311 Slater Ave Fountain Valley CA 92708",
    "addr:housenumber":"11311",
    "addr:postcode":"92708",
    "addr:street":"Slater Ave",
    "iso:country":"US",
    "sg:address":"11311 Slater Ave",
    "sg:city":"Fountain Valley",
    "sg:classifiers":[
        {
            "category":"Manufacturing",
            "subcategory":"Printing",
            "type":"Manufacturing & Wholesale Goods"
        }
    ],
    "sg:phone":"+1 714 546 3996",
    "sg:postcode":"92708",
    "sg:province":"CA",
    "sg:tags":[
        "commercial"
    ],
    "wof:name":"Freestyle Frames",
    "wof:placetype":"venue"
},
  "geometry": {"coordinates":[-117.935253,33.709221],"type":"Point"}
}