{
  "type": "Feature",
  "properties": {
    "iso:country":"US",
    "sg:address":"6416 Flotilla St",
    "sg:city":"Los Angeles",
    "sg:classifiers":[
        {
            "category":"Wholesale",
            "subcategory":"Groceries",
            "type":"Manufacturing & Wholesale Goods"
        }
    ],
    "sg:phone":"+1 323 725 1013",
    "sg:postcode":"90040",
    "sg:province":"CA",
    "sg:tags":[
        "confectionery"
    ],
    "wof:name":"Rodney Sour Co",
    "wof:placetype":"venue"
},
  "geometry": {"coordinates":[-118.13418900000001,34.005773],"type":"Point"}
}