{
  "type": "Feature",
  "properties": {
    "iso:country":"US",
    "sg:address":"8383 Wilshire Blvd",
    "sg:city":"Beverly Hills",
    "sg:classifiers":[
        {
            "category":"Travel",
            "subcategory":"Travel Agent",
            "type":"Entertainment"
        }
    ],
    "sg:phone":"+1 323 658 7188",
    "sg:postcode":"90211",
    "sg:province":"CA",
    "sg:tags":[
        "information",
        "tourist"
    ],
    "wof:name":"Tourist Office Of Spain",
    "wof:placetype":"venue"
},
  "geometry": {"coordinates":[-118.373314,34.064543],"type":"Point"}
}