{
  "type": "Feature",
  "properties": {
    "addr:full":"1001 E Charleston Rd Palo Alto CA 94303",
    "addr:housenumber":"1001",
    "addr:postcode":"94303",
    "addr:street":"E Charleston Rd",
    "iso:country":"US",
    "sg:address":"1001 E Charleston Rd",
    "sg:city":"Palo Alto",
    "sg:classifiers":[
        {
            "category":"Wholesale",
            "subcategory":"Machinery & Supplies",
            "type":"Manufacturing & Wholesale Goods"
        }
    ],
    "sg:phone":"+1 650 494 6606",
    "sg:postcode":"94303",
    "sg:province":"CA",
    "sg:tags":[
        "truck"
    ],
    "sg:website":"www.baycitiesforklift.com",
    "wof:name":"Bay Cities Forklift Co",
    "wof:placetype":"venue"
},
  "geometry": {"coordinates":[-122.09883000000001,37.42169],"type":"Point"}
}