{
  "type": "Feature",
  "properties": {
    "addr:full":"3500 Lomita Blvd Torrance CA 90505",
    "addr:housenumber":"3500",
    "addr:postcode":"90505",
    "addr:street":"Lomita Blvd",
    "iso:country":"US",
    "sg:address":"3500 Lomita Blvd",
    "sg:city":"Torrance",
    "sg:classifiers":[
        {
            "category":"Health Services",
            "subcategory":"Doctor",
            "type":"Services"
        }
    ],
    "sg:phone":"+1 310 534 8164",
    "sg:postcode":"90505",
    "sg:province":"CA",
    "wof:name":"Franco Consuelo MD",
    "wof:placetype":"venue"
},
  "geometry": {"coordinates":[-118.345714,33.813343],"type":"Point"}
}