{
  "type": "Feature",
  "properties": {
    "addr:full":"12060 Barranca Rd Camarillo CA 93012",
    "addr:housenumber":"12060",
    "addr:postcode":"93012",
    "addr:street":"Barranca Rd",
    "iso:country":"US",
    "sg:address":"12060 Barranca Rd",
    "sg:city":"Camarillo",
    "sg:classifiers":[
        {
            "category":"Mining & Drilling",
            "type":"Manufacturing & Wholesale Goods"
        }
    ],
    "sg:phone":"+1 805 495 3747",
    "sg:postcode":"93012",
    "sg:province":"CA",
    "sg:tags":[
        "crude",
        "production",
        "gas"
    ],
    "wof:name":"H L Hall & Sons",
    "wof:placetype":"venue"
},
  "geometry": {"coordinates":[-118.897451,34.249434],"type":"Point"}
}