{
  "type": "Feature",
  "properties": {
    "iso:country":"US",
    "sg:address":"323 S Rosemead Blvd",
    "sg:city":"Pasadena",
    "sg:classifiers":[
        {
            "category":"Building & Trades",
            "subcategory":"Construction",
            "type":"Services"
        }
    ],
    "sg:phone":"+1 626 287 9187",
    "sg:postcode":"91107",
    "sg:province":"CA",
    "sg:tags":[
        "general",
        "contractor"
    ],
    "wof:name":"M Newell Construction",
    "wof:placetype":"venue"
},
  "geometry": {"coordinates":[-118.0734,34.140978],"type":"Point"}
}