{
  "type": "Feature",
  "properties": {
    "addr:full":"700 E Main St Barstow CA 92311",
    "addr:housenumber":"700",
    "addr:postcode":"92311",
    "addr:street":"E Main St",
    "iso:country":"US",
    "sg:address":"700 E Main St",
    "sg:city":"Barstow",
    "sg:classifiers":[
        {
            "category":"Insurance",
            "subcategory":"Insurance Agent",
            "type":"Services"
        }
    ],
    "sg:phone":"+1 760 256 8374",
    "sg:postcode":"92311",
    "sg:province":"CA",
    "wof:name":"Northstar Pacific Insurance",
    "wof:placetype":"venue"
},
  "geometry": {"coordinates":[-117.016772,34.8987],"type":"Point"}
}