{
  "type": "Feature",
  "properties": {
    "iso:country":"US",
    "sg:address":"2086 Union St",
    "sg:city":"San Francisco",
    "sg:classifiers":[
        {
            "category":"Shopping",
            "subcategory":"Shoes",
            "type":"Retail Goods"
        }
    ],
    "sg:phone":"+1 415 929 0829",
    "sg:postcode":"94123",
    "sg:province":"CA",
    "wof:name":"Nine West",
    "wof:placetype":"venue"
},
  "geometry": {"coordinates":[-122.43272,37.797555],"type":"Point"}
}