{
  "type": "Feature",
  "properties": {
    "addr:full":"999 Sutter Street San Francisco CA 94109",
    "addr:housenumber":"999",
    "addr:postcode":"94109",
    "addr:street":"Sutter Street",
    "iso:country":"US",
    "sg:address":"999 Sutter Street",
    "sg:city":"San Francisco",
    "sg:classifiers":[
        {
            "category":"Health Services",
            "subcategory":"Clinic",
            "type":"Services"
        }
    ],
    "sg:phone":"+1 415 614 1231",
    "sg:postcode":"94109",
    "sg:province":"CA",
    "sg:tags":[
        "counseling",
        "mental"
    ],
    "wof:name":"Bay Area Psychotherapy Services",
    "wof:placetype":"venue"
},
  "geometry": {"coordinates":[-122.417,37.788101],"type":"Point"}
}