{
  "type": "Feature",
  "properties": {
    "iso:country":"US",
    "sg:address":"155 Matisse Cir",
    "sg:city":"Aliso Viejo",
    "sg:classifiers":[
        {
            "category":"Manufacturing",
            "subcategory":"Printing",
            "type":"Manufacturing & Wholesale Goods"
        }
    ],
    "sg:phone":"+1 949 338 2611",
    "sg:postcode":"92656",
    "sg:province":"CA",
    "sg:tags":[
        "periodical"
    ],
    "wof:name":"Bargain Hunter Coupon Magazine",
    "wof:placetype":"venue"
},
  "geometry": {"coordinates":[-117.721272,33.55891],"type":"Point"}
}