{
  "type": "Feature",
  "properties": {
    "iso:country":"US",
    "sg:address":"801 Ygnacio Valley Rd",
    "sg:city":"Walnut Creek",
    "sg:classifiers":[
        {
            "category":"Education",
            "subcategory":"College",
            "type":"Public Place"
        }
    ],
    "sg:phone":"+1 925 945 7132",
    "sg:postcode":"94596",
    "sg:province":"CA",
    "sg:tags":[
        "academic",
        "school"
    ],
    "wof:name":"Golden Gate University",
    "wof:placetype":"venue"
},
  "geometry": {"coordinates":[-122.057811,37.907083],"type":"Point"}
}