{
  "type": "Feature",
  "properties": {
    "iso:country":"US",
    "sg:address":"13690 Goldenwest Street",
    "sg:city":"Westminster",
    "sg:classifiers":[
        {
            "category":"Food & Beverages",
            "subcategory":"Liquor & Beverages",
            "type":"Retail Goods"
        }
    ],
    "sg:phone":"+1 714 893 5069",
    "sg:postcode":"92683",
    "sg:province":"CA",
    "sg:tags":[
        "beer",
        "spirit",
        "wine"
    ],
    "wof:name":"Quik Stop Liquor",
    "wof:placetype":"venue"
},
  "geometry": {"coordinates":[-118.007181,33.763208],"type":"Point"}
}