{
  "type": "Feature",
  "properties": {
    "addr:full":"402 14th St Huntington Beach CA 92648",
    "addr:housenumber":"402",
    "addr:postcode":"92648",
    "addr:street":"14Th St",
    "iso:country":"US",
    "sg:address":"402 14th St",
    "sg:city":"Huntington Beach",
    "sg:classifiers":[
        {
            "category":"Professional",
            "type":"Services"
        }
    ],
    "sg:phone":"+1 714 536 7939",
    "sg:postcode":"92648",
    "sg:province":"CA",
    "wof:name":"Mark W Jay",
    "wof:placetype":"venue"
},
  "geometry": {"coordinates":[-118.006449,33.666393],"type":"Point"}
}