{
  "type": "Feature",
  "properties": {
    "addr:full":"1415 L St Sacramento CA 95814",
    "addr:housenumber":"1415",
    "addr:postcode":"95814",
    "addr:street":"L St",
    "iso:country":"US",
    "sg:address":"1415 L St",
    "sg:city":"Sacramento",
    "sg:classifiers":[
        {
            "category":"Restaurant",
            "type":"Food & Drink"
        }
    ],
    "sg:phone":"+1 916 440 8888",
    "sg:postcode":"95814",
    "sg:province":"CA",
    "sg:website":"www.spatarorestaurant.com",
    "wof:name":"Spataro",
    "wof:placetype":"venue"
},
  "geometry": {"coordinates":[-121.488748,38.57668],"type":"Point"}
}