{
  "type": "Feature",
  "properties": {
    "addr:full":"2051 N Oxnard Blvd Oxnard CA 93036",
    "addr:housenumber":"2051",
    "addr:postcode":"93036",
    "addr:street":"N Oxnard Blvd",
    "iso:country":"US",
    "sg:address":"2051 N Oxnard Blvd",
    "sg:city":"Oxnard",
    "sg:classifiers":[
        {
            "category":"Cinema",
            "subcategory":"Movie Rental",
            "type":"Entertainment"
        }
    ],
    "sg:phone":"+1 805 981 0909",
    "sg:postcode":"93036",
    "sg:province":"CA",
    "sg:tags":[
        "leasing",
        "video",
        "disc",
        "tape"
    ],
    "sg:website":"www.blockbuster.com",
    "wof:name":"Blockbuster Video",
    "wof:placetype":"venue"
},
  "geometry": {"coordinates":[-119.177179,34.219458],"type":"Point"}
}