{
  "type": "Feature",
  "properties": {
    "iso:country":"US",
    "sg:address":"911 Athens St",
    "sg:city":"Altadena",
    "sg:classifiers":[
        {
            "category":"Wholesale",
            "subcategory":"Non-durable Goods",
            "type":"Manufacturing & Wholesale Goods"
        }
    ],
    "sg:phone":"+1 626 794 8190",
    "sg:postcode":"91001",
    "sg:province":"CA",
    "wof:name":"Delta Distributing",
    "wof:placetype":"venue"
},
  "geometry": {"coordinates":[-118.128552,34.197401],"type":"Point"}
}