{
  "type": "Feature",
  "properties": {
    "addr:full":"1636 S Main St Milpitas CA 95035",
    "addr:housenumber":"1636",
    "addr:postcode":"95035",
    "addr:street":"S Main St",
    "iso:country":"US",
    "sg:address":"1636 S Main St",
    "sg:city":"Milpitas",
    "sg:classifiers":[
        {
            "category":"Retail",
            "subcategory":"Auto Repair",
            "type":"Services"
        }
    ],
    "sg:phone":"+1 408 263 3500",
    "sg:postcode":"95035",
    "sg:province":"CA",
    "sg:tags":[
        "repairing",
        "automobile"
    ],
    "wof:name":"Stevens Auto Works",
    "wof:placetype":"venue"
},
  "geometry": {"coordinates":[-121.902839,37.406064],"type":"Point"}
}