{
  "type": "Feature",
  "properties": {
    "iso:country":"US",
    "sg:address":"38340 9th St E",
    "sg:city":"Palmdale",
    "sg:classifiers":[
        {
            "category":"Professional",
            "type":"Services"
        }
    ],
    "sg:phone":"+1 661 267 1588",
    "sg:postcode":"93550",
    "sg:province":"CA",
    "sg:tags":[
        "establishment"
    ],
    "wof:name":"D & D 100 Percent Hemp",
    "wof:placetype":"venue"
},
  "geometry": {"coordinates":[-118.114197,34.579395],"type":"Point"}
}