{
  "type": "Feature",
  "properties": {
    "iso:country":"US",
    "sg:address":"1520 Mitchell Rd",
    "sg:city":"Ceres",
    "sg:classifiers":[
        {
            "category":"Shopping",
            "subcategory":"Shoes",
            "type":"Retail Goods"
        }
    ],
    "sg:phone":"+1 209 581 0362",
    "sg:postcode":"95307",
    "sg:province":"CA",
    "sg:tags":[
        "store"
    ],
    "wof:name":"Payless ShoeSource",
    "wof:placetype":"venue"
},
  "geometry": {"coordinates":[-120.938485,37.605814],"type":"Point"}
}