{
  "type": "Feature",
  "properties": {
    "addr:full":"6872 Avenida Rotella San Jose CA 95119",
    "addr:housenumber":"6872",
    "addr:postcode":"95119",
    "addr:street":"Avenida Rotella",
    "iso:country":"US",
    "sg:address":"6872 Avenida Rotella",
    "sg:city":"San Jose",
    "sg:classifiers":[
        {
            "category":"Communications",
            "subcategory":"Film & Video Production",
            "type":"Services"
        }
    ],
    "sg:phone":"+1 408 505 0599",
    "sg:postcode":"95119",
    "sg:province":"CA",
    "sg:tags":[
        "video/film"
    ],
    "wof:name":"HD VIdeo INC.",
    "wof:placetype":"venue"
},
  "geometry": {"coordinates":[-121.771895,37.231431],"type":"Point"}
}