{
  "type": "Feature",
  "properties": {
    "addr:full":"5522 E La Palma Ave Anaheim CA 92807",
    "addr:housenumber":"5522",
    "addr:postcode":"92807",
    "addr:street":"E La Palma Ave",
    "iso:country":"US",
    "sg:address":"5522 E La Palma Ave",
    "sg:city":"Anaheim",
    "sg:classifiers":[
        {
            "category":"Personal",
            "type":"Services"
        }
    ],
    "sg:phone":"+1 714 777 9400",
    "sg:postcode":"92807",
    "sg:province":"CA",
    "sg:tags":[
        "local"
    ],
    "sg:website":"www.sannahpackagingsupplies.com",
    "wof:name":"Sannah Packaging Supplies",
    "wof:placetype":"venue"
},
  "geometry": {"coordinates":[-117.793952,33.859863],"type":"Point"}
}