{
  "type": "Feature",
  "properties": {
    "iso:country":"US",
    "sg:address":"1634 Cottage Glen Ct",
    "sg:city":"Encinitas",
    "sg:classifiers":[
        {
            "category":"Manufacturing",
            "subcategory":"Printing",
            "type":"Manufacturing & Wholesale Goods"
        }
    ],
    "sg:phone":"+1 760 944 3541",
    "sg:postcode":"92024",
    "sg:province":"CA",
    "sg:tags":[
        "lithographic",
        "commercial"
    ],
    "wof:name":"Lane Litho LLC",
    "wof:placetype":"venue"
},
  "geometry": {"coordinates":[-117.251272,33.05676],"type":"Point"}
}