{
  "type": "Feature",
  "properties": {
    "iso:country":"US",
    "sg:address":"1808 San Leandro Blvd",
    "sg:city":"San Leandro",
    "sg:classifiers":[
        {
            "category":"Social Services",
            "subcategory":"Child Care",
            "type":"Services"
        }
    ],
    "sg:phone":"+1 510 351 6894",
    "sg:postcode":"94577",
    "sg:province":"CA",
    "sg:tags":[
        "center"
    ],
    "wof:name":"One Stop Shuttle Svc",
    "wof:placetype":"venue"
},
  "geometry": {"coordinates":[-122.15672000000001,37.71795],"type":"Point"}
}