{
  "type": "Feature",
  "properties": {
    "addr:full":"12482 Putnam St. Whittier CA 90602",
    "addr:housenumber":"12482",
    "addr:postcode":"90602",
    "addr:street":"Putnam St.",
    "iso:country":"US",
    "sg:address":"12482 Putnam St.",
    "sg:city":"Whittier",
    "sg:classifiers":[
        {
            "category":"Building & Trades",
            "subcategory":"Construction",
            "type":"Services"
        }
    ],
    "sg:phone":"+1 949 207 7117",
    "sg:postcode":"90602",
    "sg:province":"CA",
    "sg:tags":[
        "contractor"
    ],
    "sg:website":"newvillagesolar.com",
    "wof:name":"New Village Solar",
    "wof:placetype":"venue"
},
  "geometry": {"coordinates":[-118.04599,33.969146],"type":"Point"}
}