{
  "type": "Feature",
  "properties": {
    "iso:country":"US",
    "sg:address":"257 E Campbell Avenue Suite 3",
    "sg:city":"Campbell",
    "sg:classifiers":[
        {
            "category":"Banks & Credit Unions",
            "subcategory":"Financial Services",
            "type":"Services"
        }
    ],
    "sg:phone":"+1 408 379 1274",
    "sg:postcode":"95008",
    "sg:province":"CA",
    "sg:tags":[
        "broker",
        "mortgage"
    ],
    "wof:name":"Community Properties.",
    "wof:placetype":"venue"
},
  "geometry": {"coordinates":[-121.945452,37.287076],"type":"Point"}
}