{
  "type": "Feature",
  "properties": {
    "addr:full":"3940 S Bristol St Ste 208 Santa Ana CA 92704",
    "addr:housenumber":"3940",
    "addr:postcode":"92704",
    "addr:street":"S Bristol St Ste 208",
    "iso:country":"US",
    "sg:address":"3940 S Bristol St Ste 208",
    "sg:city":"Santa Ana",
    "sg:classifiers":[
        {
            "category":"Professional",
            "subcategory":"Employment Agencies",
            "type":"Services"
        }
    ],
    "sg:phone":"+1 714 668 9065",
    "sg:postcode":"92704",
    "sg:province":"CA",
    "wof:name":"Appleone Temporary & Full-Time Employment Services",
    "wof:placetype":"venue"
},
  "geometry": {"coordinates":[-117.88596200000001,33.694664],"type":"Point"}
}