{
  "type": "Feature",
  "properties": {
    "addr:full":"3275 Williams Rd San Jose CA 95117",
    "addr:housenumber":"3275",
    "addr:postcode":"95117",
    "addr:street":"Williams Rd",
    "iso:country":"US",
    "sg:address":"3275 Williams Rd",
    "sg:city":"San Jose",
    "sg:classifiers":[
        {
            "category":"Education",
            "subcategory":"School",
            "type":"Public Place"
        }
    ],
    "sg:postcode":"95117",
    "sg:province":"CA",
    "sg:website":"www.southbayprep.org",
    "wof:name":"South Bay Preparatory School",
    "wof:placetype":"venue"
},
  "geometry": {"coordinates":[-121.955648,37.309716],"type":"Point"}
}