{
  "type": "Feature",
  "properties": {
    "addr:full":"13279 Monte Vista Ave Chino CA 91710",
    "addr:housenumber":"13279",
    "addr:postcode":"91710",
    "addr:street":"Monte Vista Ave",
    "iso:country":"US",
    "sg:address":"13279 Monte Vista Ave",
    "sg:city":"Chino",
    "sg:classifiers":[
        {
            "category":"Retail",
            "subcategory":"Repair Shop",
            "type":"Services"
        }
    ],
    "sg:phone":"+1 909 627 4211",
    "sg:postcode":"91710",
    "sg:province":"CA",
    "sg:tags":[
        "upholsterer"
    ],
    "wof:name":"Custom Furniture Designs",
    "wof:placetype":"venue"
},
  "geometry": {"coordinates":[-117.697908,34.011875],"type":"Point"}
}