{
  "type": "Feature",
  "properties": {
    "iso:country":"US",
    "sg:address":"116 Kenneth St",
    "sg:city":"Santa Cruz",
    "sg:classifiers":[
        {
            "category":"Shopping",
            "subcategory":"Jewelry",
            "type":"Retail Goods"
        }
    ],
    "sg:phone":"+1 831 426 5629",
    "sg:postcode":"95060",
    "sg:province":"CA",
    "sg:tags":[
        "designer"
    ],
    "wof:name":"Desert Sage Designs",
    "wof:placetype":"venue"
},
  "geometry": {"coordinates":[-122.045189,36.969297],"type":"Point"}
}