{
  "type": "Feature",
  "properties": {
    "addr:full":"1160 Battery St. San Francisco CA 94111",
    "addr:housenumber":"1160",
    "addr:postcode":"94111",
    "addr:street":"Battery St.",
    "iso:country":"US",
    "sg:address":"1160 Battery St.",
    "sg:city":"San Francisco",
    "sg:classifiers":[
        {
            "category":"Real Estate",
            "subcategory":"Real Estate Services",
            "type":"Services"
        }
    ],
    "sg:phone":"+1 415 874 5010",
    "sg:postcode":"94111",
    "sg:province":"CA",
    "sg:website":"www.johnroachsf.com",
    "wof:name":"John Roach - Paragon Real Estate Group",
    "wof:placetype":"venue"
},
  "geometry": {"coordinates":[-122.40111899999999,37.801917],"type":"Point"}
}