{
  "type": "Feature",
  "properties": {
    "addr:full":"6600 Schirra Ct Bakersfield CA 93313",
    "addr:housenumber":"6600",
    "addr:postcode":"93313",
    "addr:street":"Schirra Ct",
    "iso:country":"US",
    "sg:address":"6600 Schirra Ct",
    "sg:city":"Bakersfield",
    "sg:classifiers":[
        {
            "category":"Retail",
            "subcategory":"Auto Repair",
            "type":"Services"
        }
    ],
    "sg:phone":"+1 661 398 0305",
    "sg:postcode":"93313",
    "sg:province":"CA",
    "sg:tags":[
        "automobile",
        "smog"
    ],
    "wof:name":"Blue Ribbon Automotive",
    "wof:placetype":"venue"
},
  "geometry": {"coordinates":[-119.08162799999999,35.31661],"type":"Point"}
}