{
  "type": "Feature",
  "properties": {
    "addr:full":"725 N 10th St San Jose CA 95112",
    "addr:housenumber":"725",
    "addr:postcode":"95112",
    "addr:street":"N 10Th St",
    "iso:country":"US",
    "sg:address":"725 N 10th St",
    "sg:city":"San Jose",
    "sg:classifiers":[
        {
            "category":"Building & Trades",
            "subcategory":"Construction",
            "type":"Services"
        }
    ],
    "sg:phone":"+1 408 280 7228",
    "sg:postcode":"95112",
    "sg:province":"CA",
    "sg:tags":[
        "works",
        "public",
        "contractor"
    ],
    "wof:name":"Esr Construction Inc",
    "wof:placetype":"venue"
},
  "geometry": {"coordinates":[-121.891949,37.355195],"type":"Point"}
}