{
  "type": "Feature",
  "properties": {
    "iso:country":"US",
    "sg:address":"401 N Pacific Coast Hwy",
    "sg:city":"Redondo Beach",
    "sg:classifiers":[
        {
            "category":"Shopping",
            "subcategory":"Pharmacy",
            "type":"Retail Goods"
        }
    ],
    "sg:phone":"+1 310 372 9029",
    "sg:postcode":"90277",
    "sg:province":"CA",
    "wof:name":"Rite Aid Pharmacy",
    "wof:placetype":"venue"
},
  "geometry": {"coordinates":[-118.388525,33.849103],"type":"Point"}
}