{
  "type": "Feature",
  "properties": {
    "iso:country":"US",
    "sg:address":"19925 Stevens Creek Boulevard",
    "sg:city":"Cupertino",
    "sg:classifiers":[
        {
            "category":"Professional",
            "subcategory":"Employment Agencies",
            "type":"Services"
        }
    ],
    "sg:phone":"+1 408 266 8844",
    "sg:postcode":"95014",
    "sg:province":"CA",
    "wof:name":"Advantage Personnel",
    "wof:placetype":"venue"
},
  "geometry": {"coordinates":[-122.02143,37.323035],"type":"Point"}
}