{
  "type": "Feature",
  "properties": {
    "addr:full":"2820 Eastern Ave Sacramento CA 95821",
    "addr:housenumber":"2820",
    "addr:postcode":"95821",
    "addr:street":"Eastern Ave",
    "iso:country":"US",
    "sg:address":"2820 Eastern Ave",
    "sg:city":"Sacramento",
    "sg:classifiers":[
        {
            "category":"Social Services",
            "subcategory":"Child Care",
            "type":"Services"
        },
        {
            "category":"Education",
            "subcategory":"Preschool",
            "type":"Public Place"
        },
        {
            "category":"Education",
            "subcategory":"School",
            "type":"Public Place"
        }
    ],
    "sg:phone":"+1 916 485 0507",
    "sg:postcode":"95821",
    "sg:province":"CA",
    "sg:tags":[
        "elementary",
        "day"
    ],
    "sg:website":"merryhillschool.com",
    "wof:name":"Merryhill School",
    "wof:placetype":"venue"
},
  "geometry": {"coordinates":[-121.364287,38.616321],"type":"Point"}
}