{
  "type": "Feature",
  "properties": {
    "iso:country":"US",
    "sg:address":"4676 W Jacquelyn Ave",
    "sg:city":"Fresno",
    "sg:classifiers":[
        {
            "category":"Professional",
            "subcategory":"Business Services",
            "type":"Services"
        }
    ],
    "sg:phone":"+1 559 276 9191",
    "sg:postcode":"93722",
    "sg:province":"CA",
    "sg:tags":[
        "recording",
        "studio"
    ],
    "sg:website":"www.classicaudiovideo.net",
    "wof:name":"Classic Audio Video",
    "wof:placetype":"venue"
},
  "geometry": {"coordinates":[-119.877424,36.812653],"type":"Point"}
}