{
  "type": "Feature",
  "properties": {
    "addr:full":"1752 Oregon St Redding CA 96001",
    "addr:housenumber":"1752",
    "addr:postcode":"96001",
    "addr:street":"Oregon St",
    "iso:country":"US",
    "sg:address":"1752 Oregon St",
    "sg:city":"Redding",
    "sg:classifiers":[
        {
            "category":"Shopping",
            "subcategory":"Clothing, Apparel, & Fashions",
            "type":"Retail Goods"
        }
    ],
    "sg:phone":"+1 530 241 7377",
    "sg:postcode":"96001",
    "sg:province":"CA",
    "sg:tags":[
        "salvage",
        "surplus",
        "merchandise"
    ],
    "wof:name":"Morrison Warehouse",
    "wof:placetype":"venue"
},
  "geometry": {"coordinates":[-122.393398,40.580961],"type":"Point"}
}