{
  "type": "Feature",
  "properties": {
    "addr:full":"1229 Santee St Los Angeles CA 90015",
    "addr:housenumber":"1229",
    "addr:postcode":"90015",
    "addr:street":"Santee St",
    "iso:country":"US",
    "sg:address":"1229 Santee St",
    "sg:city":"Los Angeles",
    "sg:classifiers":[
        {
            "category":"Professional",
            "type":"Services"
        }
    ],
    "sg:phone":"+1 213 749 6202",
    "sg:postcode":"90015",
    "sg:province":"CA",
    "sg:tags":[
        "establishment"
    ],
    "wof:name":"Eclectics",
    "wof:placetype":"venue"
},
  "geometry": {"coordinates":[-118.25810799999999,34.035511],"type":"Point"}
}