{
  "type": "Feature",
  "properties": {
    "addr:full":"6665 Mission Gorge Rd San Diego CA 92120",
    "addr:housenumber":"6665",
    "addr:postcode":"92120",
    "addr:street":"Mission Gorge Rd",
    "iso:country":"US",
    "sg:address":"6665 Mission Gorge Rd",
    "sg:city":"San Diego",
    "sg:classifiers":[
        {
            "category":"Taxi",
            "type":"Transportation"
        }
    ],
    "sg:phone":"+1 619 284 2369",
    "sg:postcode":"92120",
    "sg:province":"CA",
    "sg:tags":[
        "taxicab"
    ],
    "wof:name":"Neelo Cab",
    "wof:placetype":"venue"
},
  "geometry": {"coordinates":[-117.095584,32.795344],"type":"Point"}
}