{
  "type": "Feature",
  "properties": {
    "iso:country":"US",
    "sg:address":"7032 Comstock Ave",
    "sg:city":"Whittier",
    "sg:classifiers":[
        {
            "category":"Wholesale",
            "subcategory":"Electrical",
            "type":"Manufacturing & Wholesale Goods"
        }
    ],
    "sg:phone":"+1 562 696 2500",
    "sg:postcode":"90602",
    "sg:province":"CA",
    "sg:tags":[
        "control",
        "security",
        "system"
    ],
    "wof:name":"Golden Home Security",
    "wof:placetype":"venue"
},
  "geometry": {"coordinates":[-118.038473,33.97757],"type":"Point"}
}