{
  "type": "Feature",
  "properties": {
    "addr:full":"22526 Ave Empresa Rancho Santa Margarita CA 92688",
    "addr:housenumber":"22526",
    "addr:postcode":"92688",
    "addr:street":"Ave Empresa",
    "iso:country":"US",
    "sg:address":"22526 Ave Empresa",
    "sg:city":"Rancho Santa Margarita",
    "sg:classifiers":[
        {
            "category":"Freight",
            "type":"Transportation"
        }
    ],
    "sg:phone":"+1 949 459 1001",
    "sg:postcode":"92688",
    "sg:province":"CA",
    "sg:tags":[
        "local",
        "storage",
        "trucking"
    ],
    "wof:name":"Terry Moving and Storage Inc",
    "wof:placetype":"venue"
},
  "geometry": {"coordinates":[-117.606979,33.63441],"type":"Point"}
}