{
  "type": "Feature",
  "properties": {
    "iso:country":"US",
    "sg:address":"14530 Lakeshore Dr",
    "sg:city":"Clearlake",
    "sg:phone":"+1 707 995 1004",
    "sg:postcode":"95422",
    "sg:province":"CA",
    "wof:name":"Burger Time",
    "wof:placetype":"venue"
},
  "geometry": {"coordinates":[-122.64132600000001,38.951373],"type":"Point"}
}