{
  "type": "Feature",
  "properties": {
    "iso:country":"US",
    "sg:address":"6021 Pacific Blvd",
    "sg:city":"Huntington Park",
    "sg:classifiers":[
        {
            "category":"Professional",
            "subcategory":"Employment Agencies",
            "type":"Services"
        }
    ],
    "sg:phone":"+1 323 589 0545",
    "sg:postcode":"90255",
    "sg:province":"CA",
    "sg:tags":[
        "help",
        "contractor"
    ],
    "wof:name":"Checkmate Staffing Inc",
    "wof:placetype":"venue"
},
  "geometry": {"coordinates":[-118.225255,33.985899],"type":"Point"}
}