{
  "type": "Feature",
  "properties": {
    "addr:full":"224 Jackson St San Jose CA 95112",
    "addr:housenumber":"224",
    "addr:postcode":"95112",
    "addr:street":"Jackson St",
    "iso:country":"US",
    "sg:address":"224 Jackson St",
    "sg:city":"San Jose",
    "sg:classifiers":[
        {
            "category":"Professional",
            "subcategory":"Lawyer & Legal Services",
            "type":"Services"
        }
    ],
    "sg:phone":"+1 408 295 5051",
    "sg:postcode":"95112",
    "sg:province":"CA",
    "sg:tags":[
        "attorney"
    ],
    "wof:name":"Charles F Cummins Jr",
    "wof:placetype":"venue"
},
  "geometry": {"coordinates":[-121.893698,37.349163],"type":"Point"}
}