{
  "type": "Feature",
  "properties": {
    "addr:full":"1007 S Victoria Ave Corona CA 92879",
    "addr:housenumber":"1007",
    "addr:postcode":"92879",
    "addr:street":"S Victoria Ave",
    "iso:country":"US",
    "sg:address":"1007 S Victoria Ave",
    "sg:city":"Corona",
    "sg:classifiers":[
        {
            "category":"Professional",
            "subcategory":"Lawyer & Legal Services",
            "type":"Services"
        }
    ],
    "sg:phone":"+1 951 737 3663",
    "sg:postcode":"92879",
    "sg:province":"CA",
    "sg:tags":[
        "attorney"
    ],
    "wof:name":"Kurt A Seidler",
    "wof:placetype":"venue"
},
  "geometry": {"coordinates":[-117.564638,33.87007],"type":"Point"}
}