{
  "type": "Feature",
  "properties": {
    "addr:full":"325 N Milpas St Santa Barbara CA 93103",
    "addr:housenumber":"325",
    "addr:postcode":"93103",
    "addr:street":"N Milpas St",
    "iso:country":"US",
    "sg:address":"325 N Milpas St",
    "sg:city":"Santa Barbara",
    "sg:classifiers":[
        {
            "category":"Retail",
            "subcategory":"Repair Shop",
            "type":"Services"
        }
    ],
    "sg:phone":"+1 805 962 8924",
    "sg:postcode":"93103",
    "sg:province":"CA",
    "sg:tags":[
        "upholsterer"
    ],
    "wof:name":"Frango's Upholstery",
    "wof:placetype":"venue"
},
  "geometry": {"coordinates":[-119.683832,34.42509],"type":"Point"}
}