{
  "type": "Feature",
  "properties": {
    "addr:full":"2341 Industrial Pkwy W Hayward CA 94545",
    "addr:housenumber":"2341",
    "addr:postcode":"94545",
    "addr:street":"Industrial Pkwy W",
    "iso:country":"US",
    "sg:address":"2341 Industrial Pkwy W",
    "sg:city":"Hayward",
    "sg:phone":"+1 510 782 1988",
    "sg:postcode":"94545",
    "sg:province":"CA",
    "sg:tags":[
        "fixture",
        "store"
    ],
    "wof:name":"Grand & Benedicts Store",
    "wof:placetype":"venue"
},
  "geometry": {"coordinates":[-122.07969799999999,37.617828],"type":"Point"}
}