{
  "type": "Feature",
  "properties": {
    "addr:full":"10343 Roselle St San Diego CA 92121",
    "addr:housenumber":"10343",
    "addr:postcode":"92121",
    "addr:street":"Roselle St",
    "iso:country":"US",
    "sg:address":"10343 Roselle St",
    "sg:city":"San Diego",
    "sg:classifiers":[
        {
            "category":"Organizations",
            "subcategory":"Membership Organization",
            "type":"Services"
        }
    ],
    "sg:phone":"+1 858 527 1686",
    "sg:postcode":"92121",
    "sg:province":"CA",
    "wof:name":"Las Patronas",
    "wof:placetype":"venue"
},
  "geometry": {"coordinates":[-117.21895600000001,32.894191],"type":"Point"}
}