{
  "type": "Feature",
  "properties": {
    "addr:full":"2086 Newpark Mall Newark CA 94560",
    "addr:housenumber":"2086",
    "addr:postcode":"94560",
    "addr:street":"Newpark Mall",
    "iso:country":"US",
    "sg:address":"2086 Newpark Mall",
    "sg:city":"Newark",
    "sg:classifiers":[
        {
            "category":"Utilities",
            "subcategory":"Mobile Phone",
            "type":"Services"
        }
    ],
    "sg:phone":"+1 510 744 1620",
    "sg:postcode":"94560",
    "sg:province":"CA",
    "sg:tags":[
        "telephone",
        "cellular"
    ],
    "wof:name":"Metro Pcs",
    "wof:placetype":"venue"
},
  "geometry": {"coordinates":[-122.00321,37.527708],"type":"Point"}
}