{
  "type": "Feature",
  "properties": {
    "addr:full":"1344 W Redondo Beach Blvd Gardena CA 90247",
    "addr:housenumber":"1344",
    "addr:postcode":"90247",
    "addr:street":"W Redondo Beach Blvd",
    "iso:country":"US",
    "sg:address":"1344 W Redondo Beach Blvd",
    "sg:city":"Gardena",
    "sg:classifiers":[
        {
            "category":"Shopping",
            "subcategory":"Pharmacy",
            "type":"Retail Goods"
        }
    ],
    "sg:phone":"+1 310 353 5726",
    "sg:postcode":"90247",
    "sg:province":"CA",
    "sg:tags":[
        "drugstore"
    ],
    "wof:name":"Walgreens",
    "wof:placetype":"venue"
},
  "geometry": {"coordinates":[-118.29956199999999,33.891098],"type":"Point"}
}