{
  "type": "Feature",
  "properties": {
    "addr:full":"208 Scott St Ukiah CA 95482",
    "addr:housenumber":"208",
    "addr:postcode":"ca 95482",
    "addr:street":"Scott St",
    "iso:country":"US",
    "sg:address":"208 Scott St",
    "sg:city":"Ukiah",
    "sg:classifiers":[
        {
            "category":"Health Services",
            "subcategory":"Nursing And Care Facility",
            "type":"Services"
        }
    ],
    "sg:phone":"+1 707 468 9329",
    "sg:postcode":"95482",
    "sg:province":"CA",
    "sg:tags":[
        "residential",
        "homes-elderly",
        "people"
    ],
    "wof:name":"Dalistan Care Home",
    "wof:placetype":"venue"
},
  "geometry": {"coordinates":[-123.209597,39.153617],"type":"Point"}
}