{
  "type": "Feature",
  "properties": {
    "addr:full":"524 Center Ave Martinez CA 94553",
    "addr:housenumber":"524",
    "addr:postcode":"94553",
    "addr:street":"Center Ave",
    "iso:country":"US",
    "sg:address":"524 Center Ave",
    "sg:city":"Martinez",
    "sg:classifiers":[
        {
            "category":"Shopping",
            "subcategory":"Tobacco",
            "type":"Retail Goods"
        }
    ],
    "sg:phone":"+1 925 228 5317",
    "sg:postcode":"94553",
    "sg:province":"CA",
    "sg:tags":[
        "cigarette",
        "product",
        "cigar"
    ],
    "wof:name":"Cigarettes 4 Less",
    "wof:placetype":"venue"
},
  "geometry": {"coordinates":[-122.11917099999999,37.993401],"type":"Point"}
}