{
  "type": "Feature",
  "properties": {
    "iso:country":"US",
    "sg:address":"4571 Lake Isabella Blvd",
    "sg:city":"Lake Isabella",
    "sg:classifiers":[
        {
            "category":"Home & Garden",
            "subcategory":"Building Materials",
            "type":"Retail Goods"
        }
    ],
    "sg:phone":"+1 760 379 1694",
    "sg:postcode":"93240",
    "sg:province":"CA",
    "sg:tags":[
        "glass",
        "window",
        "plate"
    ],
    "wof:name":"Greenhorn Mountain Glass",
    "wof:placetype":"venue"
},
  "geometry": {"coordinates":[-118.48610499999999,35.603865],"type":"Point"}
}