{
  "type": "Feature",
  "properties": {
    "iso:country":"US",
    "sg:address":"2555 Lafayette St",
    "sg:city":"Santa Clara",
    "sg:classifiers":[
        {
            "category":"Professional",
            "type":"Services"
        }
    ],
    "sg:phone":"+1 408 496 6969",
    "sg:postcode":"95050",
    "sg:province":"CA",
    "wof:name":"CTA Inc 32",
    "wof:placetype":"venue"
},
  "geometry": {"coordinates":[-121.95024100000001,37.367234],"type":"Point"}
}