{
  "type": "Feature",
  "properties": {
    "addr:full":"24879 Moontide Ln Moreno Valley CA 92557",
    "addr:postcode":"24879;92557",
    "addr:street":"Moontide Ln",
    "iso:country":"US",
    "sg:address":"24879 Moontide Ln",
    "sg:city":"Moreno Valley",
    "sg:classifiers":[
        {
            "category":"Retail",
            "subcategory":"Portrait Studio",
            "type":"Services"
        }
    ],
    "sg:phone":"+1 951 533 0000",
    "sg:postcode":"92557",
    "sg:province":"CA",
    "sg:tags":[
        "photographer",
        "wedding"
    ],
    "wof:name":"AVF Photography",
    "wof:placetype":"venue"
},
  "geometry": {"coordinates":[-117.23200900000001,33.955202],"type":"Point"}
}