{
  "type": "Feature",
  "properties": {
    "addr:full":"747 N Twin Oaks Valley Rd San Marcos CA 92069",
    "addr:housenumber":"747",
    "addr:postcode":"92069",
    "addr:street":"N Twin Oaks Valley Rd",
    "iso:country":"US",
    "sg:address":"747 N Twin Oaks Valley Rd",
    "sg:city":"San Marcos",
    "sg:classifiers":[
        {
            "category":"Freight",
            "type":"Transportation"
        }
    ],
    "sg:phone":"+1 760 744 1683",
    "sg:postcode":"92069",
    "sg:province":"CA",
    "sg:tags":[
        "operator",
        "trucking"
    ],
    "wof:name":"Preferred Movers Inc",
    "wof:placetype":"venue"
},
  "geometry": {"coordinates":[-117.16164000000001,33.15107],"type":"Point"}
}