{
  "type": "Feature",
  "properties": {
    "addr:full":"15545 Devonshire St Mission Hills CA 91345",
    "addr:housenumber":"15545",
    "addr:postcode":"91345",
    "addr:street":"Devonshire St",
    "iso:country":"US",
    "sg:address":"15545 Devonshire St",
    "sg:city":"Mission Hills",
    "sg:classifiers":[
        {
            "category":"Professional",
            "subcategory":"Accounting & Tax Preparation",
            "type":"Services"
        }
    ],
    "sg:phone":"+1 818 892 3090",
    "sg:postcode":"91345",
    "sg:province":"CA",
    "sg:tags":[
        "accountant"
    ],
    "wof:name":"Gregory O Smith Accntncy Corp",
    "wof:placetype":"venue"
},
  "geometry": {"coordinates":[-118.471154,34.257392],"type":"Point"}
}