{
  "type": "Feature",
  "properties": {
    "addr:full":"2100 Ravenna St Simi Valley CA 93065",
    "addr:housenumber":"2100",
    "addr:postcode":"93065",
    "addr:street":"Ravenna St",
    "iso:country":"US",
    "sg:address":"2100 Ravenna St",
    "sg:city":"Simi Valley",
    "sg:classifiers":[
        {
            "category":"Social Services",
            "subcategory":"Child Care",
            "type":"Services"
        }
    ],
    "sg:phone":"+1 805 527 9292",
    "sg:postcode":"93065",
    "sg:province":"CA",
    "sg:tags":[
        "kindergarten",
        "academic",
        "school"
    ],
    "wof:name":"Child Development Resources",
    "wof:placetype":"venue"
},
  "geometry": {"coordinates":[-118.74036099999999,34.277621],"type":"Point"}
}