{
  "type": "Feature",
  "properties": {
    "iso:country":"US",
    "sg:address":"2435 San Ramon Valley Blvd",
    "sg:city":"San Ramon",
    "sg:classifiers":[
        {
            "category":"Restaurant",
            "type":"Food & Drink"
        }
    ],
    "sg:phone":"+1 925 838 0101",
    "sg:postcode":"94583",
    "sg:province":"CA",
    "sg:tags":[
        "delicatessen"
    ],
    "wof:name":"Diablo Deli",
    "wof:placetype":"venue"
},
  "geometry": {"coordinates":[-121.97433100000001,37.772346],"type":"Point"}
}