{
  "type": "Feature",
  "properties": {
    "iso:country":"US",
    "sg:address":"873 Guadalupe St",
    "sg:city":"Guadalupe",
    "sg:classifiers":[
        {
            "category":"Organizations",
            "subcategory":"Community Association",
            "type":"Services"
        }
    ],
    "sg:phone":"+1 805 343 9194",
    "sg:postcode":"93434",
    "sg:province":"CA",
    "sg:tags":[
        "educational"
    ],
    "wof:name":"Community Connection",
    "wof:placetype":"venue"
},
  "geometry": {"coordinates":[-120.57390100000001,34.96924],"type":"Point"}
}