{
  "type": "Feature",
  "properties": {
    "addr:full":"2250 E Imperial Hwy Ste 200 El Segundo CA 90245",
    "addr:housenumber":"2250",
    "addr:postcode":"90245",
    "addr:street":"E Imperial Hwy Ste 200",
    "iso:country":"US",
    "sg:address":"2250 E Imperial Hwy Ste 200",
    "sg:city":"El Segundo",
    "sg:classifiers":[
        {
            "category":"Professional",
            "subcategory":"Employment Agencies",
            "type":"Services"
        }
    ],
    "sg:phone":"+1 310 563 2125",
    "sg:postcode":"90245",
    "sg:province":"CA",
    "wof:name":"Tesa",
    "wof:placetype":"venue"
},
  "geometry": {"coordinates":[-118.385002,33.930901],"type":"Point"}
}