{
  "type": "Feature",
  "properties": {
    "addr:full":"417 14th St Oakland CA 94612",
    "addr:housenumber":"417",
    "addr:postcode":"94612",
    "addr:street":"14Th St",
    "iso:country":"US",
    "sg:address":"417 14th St",
    "sg:city":"Oakland",
    "sg:classifiers":[
        {
            "category":"Shopping",
            "subcategory":"Tobacco",
            "type":"Retail Goods"
        }
    ],
    "sg:phone":"+1 510 465 5510",
    "sg:postcode":"94612",
    "sg:province":"CA",
    "sg:tags":[
        "shop",
        "cigarette",
        "cigar"
    ],
    "wof:name":"News City Plus",
    "wof:placetype":"venue"
},
  "geometry": {"coordinates":[-122.271004,37.8041],"type":"Point"}
}