{
  "type": "Feature",
  "properties": {
    "iso:country":"US",
    "sg:address":"12811 Coral Tree Place",
    "sg:city":"Los Angeles",
    "sg:classifiers":[
        {
            "category":"Sports & Exercise",
            "subcategory":"Gym",
            "type":"Entertainment"
        }
    ],
    "sg:phone":"+1 310 823 4803",
    "sg:postcode":"90066",
    "sg:province":"CA",
    "sg:tags":[
        "trainer"
    ],
    "wof:name":"Evolution 180 Fitness & Beyond",
    "wof:placetype":"venue"
},
  "geometry": {"coordinates":[-118.420497,33.978769],"type":"Point"}
}