{
  "type": "Feature",
  "properties": {
    "iso:country":"US",
    "sg:address":"2680 Middlefield Rd",
    "sg:city":"Palo Alto",
    "sg:classifiers":[
        {
            "category":"Cafe",
            "type":"Food & Drink"
        }
    ],
    "sg:menulink":"http://www.allmenus.com/ca/san-jose/53852-mikes-cafe-etc/menu/",
    "sg:phone":"+1 650 473 6453",
    "sg:postcode":"94306",
    "sg:province":"CA",
    "sg:tags":[
        "american"
    ],
    "wof:name":"Mike's Cafe Etc.",
    "wof:placetype":"venue"
},
  "geometry": {"coordinates":[-122.12975299999999,37.433676],"type":"Point"}
}