{
  "type": "Feature",
  "properties": {
    "addr:full":"3300 Leonis Blvd Los Angeles CA 90058",
    "addr:postcode":"3300;90058",
    "addr:street":"Leonis Blvd",
    "iso:country":"US",
    "sg:address":"3300 Leonis Blvd",
    "sg:city":"Los Angeles",
    "sg:classifiers":[
        {
            "category":"Professional",
            "subcategory":"Management & Consulting",
            "type":"Services"
        }
    ],
    "sg:phone":"+1 213 680 9963",
    "sg:postcode":"90058",
    "sg:province":"CA",
    "sg:tags":[
        "consultant",
        "trademark",
        "agent"
    ],
    "sg:website":"www.gotokworld.com",
    "wof:name":"K-World Trading",
    "wof:placetype":"venue"
},
  "geometry": {"coordinates":[-118.204748,34.000306],"type":"Point"}
}