{
  "type": "Feature",
  "properties": {
    "addr:full":"12035 Sherman Way North Hollywood CA 91605",
    "addr:housenumber":"12035",
    "addr:postcode":"91605",
    "addr:street":"Sherman Way",
    "iso:country":"US",
    "sg:address":"12035 Sherman Way",
    "sg:city":"North Hollywood",
    "sg:classifiers":[
        {
            "category":"Shopping",
            "subcategory":"Gifts & Souvenirs",
            "type":"Retail Goods"
        }
    ],
    "sg:phone":"+1 818 764 4800",
    "sg:postcode":"91605",
    "sg:province":"CA",
    "sg:tags":[
        "party",
        "supply"
    ],
    "wof:name":"Jump With Joy",
    "wof:placetype":"venue"
},
  "geometry": {"coordinates":[-118.395645,34.200607],"type":"Point"}
}