{
  "type": "Feature",
  "properties": {
    "iso:country":"US",
    "sg:address":"24875 Prielipp Rd",
    "sg:city":"Wildomar",
    "sg:classifiers":[
        {
            "category":"Building & Trades",
            "subcategory":"Construction",
            "type":"Services"
        }
    ],
    "sg:phone":"+1 951 461 3329",
    "sg:postcode":"92595",
    "sg:province":"CA",
    "sg:tags":[
        "contractor"
    ],
    "wof:name":"Inland Empire Builders",
    "wof:placetype":"venue"
},
  "geometry": {"coordinates":[-117.226418,33.590352],"type":"Point"}
}