{
  "type": "Feature",
  "properties": {
    "iso:country":"US",
    "sg:address":"4311 Wilshire Blvd",
    "sg:city":"Los Angeles",
    "sg:classifiers":[
        {
            "category":"Health Services",
            "subcategory":"Doctor",
            "type":"Services"
        }
    ],
    "sg:phone":"+1 323 965 1611",
    "sg:postcode":"90010",
    "sg:province":"CA",
    "wof:name":"Dediashvili Rusudan Chiropractic Corp",
    "wof:placetype":"venue"
},
  "geometry": {"coordinates":[-118.32167,34.192448],"type":"Point"}
}