{
  "type": "Feature",
  "properties": {
    "addr:full":"1201 Chestnut St Burbank CA 91506",
    "addr:housenumber":"1201",
    "addr:postcode":"91506",
    "addr:street":"Chestnut St",
    "iso:country":"US",
    "sg:address":"1201 Chestnut St",
    "sg:city":"Burbank",
    "sg:classifiers":[
        {
            "category":"Wholesale",
            "subcategory":"Durable Goods & Equipment",
            "type":"Manufacturing & Wholesale Goods"
        }
    ],
    "sg:phone":"+1 818 563 1247",
    "sg:postcode":"91506",
    "sg:province":"CA",
    "wof:name":"Big Stuff Inc",
    "wof:placetype":"venue"
},
  "geometry": {"coordinates":[-118.321932,34.181769],"type":"Point"}
}