{
  "type": "Feature",
  "properties": {
    "addr:full":"26755 Alessandro Blvd Moreno Valley CA 92555",
    "addr:housenumber":"26755",
    "addr:postcode":"92555",
    "addr:street":"Alessandro Blvd",
    "iso:country":"US",
    "sg:address":"26755 Alessandro Blvd",
    "sg:city":"Moreno Valley",
    "sg:classifiers":[
        {
            "category":"Organizations",
            "subcategory":"Religious Organization",
            "type":"Services"
        }
    ],
    "sg:phone":"+1 951 242 5683",
    "sg:postcode":"92555",
    "sg:province":"CA",
    "sg:tags":[
        "church"
    ],
    "sg:website":"www.vccbic.org",
    "wof:name":"Valley Christian Church & Acad",
    "wof:placetype":"venue"
},
  "geometry": {"coordinates":[-117.196031,33.917273],"type":"Point"}
}