{
  "type": "Feature",
  "properties": {
    "addr:full":"18517 Ventura Blvd Tarzana CA 91356",
    "addr:housenumber":"18517",
    "addr:postcode":"91356",
    "addr:street":"Ventura Blvd",
    "iso:country":"US",
    "sg:address":"18517 Ventura Blvd",
    "sg:city":"Tarzana",
    "sg:classifiers":[
        {
            "category":"Wholesale",
            "subcategory":"Machinery & Supplies",
            "type":"Manufacturing & Wholesale Goods"
        }
    ],
    "sg:phone":"+1 818 881 8393",
    "sg:postcode":"91356",
    "sg:province":"CA",
    "sg:tags":[
        "salon",
        "beauty"
    ],
    "wof:name":"Beauty Collection",
    "wof:placetype":"venue"
},
  "geometry": {"coordinates":[-118.53707900000001,34.169253],"type":"Point"}
}