{
  "type": "Feature",
  "properties": {
    "iso:country":"US",
    "sg:address":"13170 Central Ave",
    "sg:city":"Chino",
    "sg:classifiers":[
        {
            "category":"Government",
            "subcategory":"Office",
            "type":"Public Place"
        }
    ],
    "sg:phone":"+1 909 591 9836",
    "sg:postcode":"91710",
    "sg:province":"CA",
    "sg:tags":[
        "senior",
        "center"
    ],
    "wof:name":"Senior Center",
    "wof:placetype":"venue"
},
  "geometry": {"coordinates":[-117.689347,34.015001],"type":"Point"}
}