{
  "type": "Feature",
  "properties": {
    "iso:country":"US",
    "sg:address":"6550 Dumbarton Cir",
    "sg:city":"Fremont",
    "sg:classifiers":[
        {
            "category":"Manufacturing",
            "subcategory":"Tools & Machinery",
            "type":"Manufacturing & Wholesale Goods"
        }
    ],
    "sg:phone":"+1 510 608 3400",
    "sg:postcode":"94555",
    "sg:province":"CA",
    "sg:tags":[
        "control",
        "industrial",
        "mfg",
        "system",
        "automation",
        "equipment"
    ],
    "wof:name":"Scientific Technologies Inc",
    "wof:placetype":"venue"
},
  "geometry": {"coordinates":[-122.05958699999999,37.550625],"type":"Point"}
}