{
  "type": "Feature",
  "properties": {
    "iso:country":"US",
    "sg:address":"193 S Beverly Dr",
    "sg:city":"Beverly Hills",
    "sg:classifiers":[
        {
            "category":"Personal",
            "type":"Services"
        }
    ],
    "sg:phone":"+1 323 874 5556",
    "sg:postcode":"90212",
    "sg:province":"CA",
    "sg:tags":[
        "party",
        "planning",
        "event"
    ],
    "sg:website":"www.EntertainmentDesignEvents.com",
    "wof:name":"Entertainment Design",
    "wof:placetype":"venue"
},
  "geometry": {"coordinates":[-118.399132,34.065214],"type":"Point"}
}