{
  "type": "Feature",
  "properties": {
    "iso:country":"US",
    "sg:address":"401 W Los Feliz Rd",
    "sg:city":"Glendale",
    "sg:classifiers":[
        {
            "category":"Shopping",
            "subcategory":"Music",
            "type":"Retail Goods"
        }
    ],
    "sg:phone":"+1 818 241 2263",
    "sg:postcode":"91204",
    "sg:province":"CA",
    "sg:tags":[
        "video",
        "disc",
        "tape",
        "cassette"
    ],
    "wof:name":"Mundo Latino",
    "wof:placetype":"venue"
},
  "geometry": {"coordinates":[-118.260498,34.127769],"type":"Point"}
}