{
  "type": "Feature",
  "properties": {
    "iso:country":"US",
    "sg:address":"155 W Hedding St",
    "sg:city":"San Jose",
    "sg:classifiers":[
        {
            "category":"Professional",
            "type":"Services"
        }
    ],
    "sg:phone":"+1 408 295 2795",
    "sg:postcode":"95110",
    "sg:province":"CA",
    "sg:tags":[
        "establishment"
    ],
    "wof:name":"USARC Retention",
    "wof:placetype":"venue"
},
  "geometry": {"coordinates":[-121.906474,37.351958],"type":"Point"}
}