{
  "type": "Feature",
  "properties": {
    "addr:full":"23 Duane Irvine CA 92620",
    "addr:housenumber":"23",
    "addr:postcode":"92620",
    "addr:street":"Duane",
    "iso:country":"US",
    "sg:address":"23 Duane",
    "sg:city":"Irvine",
    "sg:classifiers":[
        {
            "category":"Wholesale",
            "subcategory":"Computers",
            "type":"Manufacturing & Wholesale Goods"
        }
    ],
    "sg:phone":"+1 949 653 6554",
    "sg:postcode":"92620",
    "sg:province":"CA",
    "sg:tags":[
        "terminal"
    ],
    "wof:name":"Infoland Enterprise",
    "wof:placetype":"venue"
},
  "geometry": {"coordinates":[-117.758421,33.705612],"type":"Point"}
}