{
  "type": "Feature",
  "properties": {
    "addr:full":"6335 N Fresno St Fresno CA 93710",
    "addr:housenumber":"6335",
    "addr:postcode":"93710",
    "addr:street":"N Fresno",
    "iso:country":"US",
    "sg:address":"6335 N Fresno St",
    "sg:city":"Fresno",
    "sg:classifiers":[
        {
            "category":"Health Services",
            "subcategory":"Chiropractor",
            "type":"Services"
        }
    ],
    "sg:phone":"+1 559 449 8055",
    "sg:postcode":"93710",
    "sg:province":"CA",
    "wof:name":"Chiropractic For Health",
    "wof:placetype":"venue"
},
  "geometry": {"coordinates":[-119.781381,36.827744],"type":"Point"}
}