{
  "type": "Feature",
  "properties": {
    "iso:country":"US",
    "sg:address":"5400 Ygnacio Valley Rd",
    "sg:city":"Concord",
    "sg:classifiers":[
        {
            "category":"Restaurant",
            "type":"Food & Drink"
        }
    ],
    "sg:phone":"+1 925 672 6363",
    "sg:postcode":"94598",
    "sg:province":"CA",
    "wof:name":"Aladino's Pizzeria",
    "wof:placetype":"venue"
},
  "geometry": {"coordinates":[-121.95734299999999,37.952109],"type":"Point"}
}