{
  "type": "Feature",
  "properties": {
    "addr:full":"1935 el Camino Real Aromas CA 95004",
    "addr:housenumber":"1935",
    "addr:postcode":"ca 95004",
    "addr:street":"El Camino Real",
    "iso:country":"US",
    "sg:address":"1935 el Camino Real",
    "sg:city":"Aromas",
    "sg:classifiers":[
        {
            "category":"Freight",
            "type":"Transportation"
        },
        {
            "category":"Utilities",
            "subcategory":"Water",
            "type":"Services"
        }
    ],
    "sg:phone":"+1 831 726 3903",
    "sg:postcode":"95004",
    "sg:province":"CA",
    "sg:tags":[
        "supply",
        "trucking"
    ],
    "wof:name":"Sala Brothers Water Truck Inc",
    "wof:placetype":"venue"
},
  "geometry": {"coordinates":[-121.633871,36.843353],"type":"Point"}
}