{
  "type": "Feature",
  "properties": {
    "iso:country":"US",
    "sg:address":"2373 Donna Dr",
    "sg:city":"Eureka",
    "sg:classifiers":[
        {
            "category":"Building & Trades",
            "subcategory":"Landscaping Services",
            "type":"Services"
        }
    ],
    "sg:phone":"+1 707 445 5757",
    "sg:postcode":"95503",
    "sg:province":"CA",
    "sg:tags":[
        "landscape"
    ],
    "wof:name":"Bill At Your Service",
    "wof:placetype":"venue"
},
  "geometry": {"coordinates":[-124.201353,40.71769],"type":"Point"}
}