{
  "type": "Feature",
  "properties": {
    "iso:country":"US",
    "sg:address":"25311 Madison Ave",
    "sg:city":"Murrieta",
    "sg:classifiers":[
        {
            "category":"Personal",
            "subcategory":"Beauty Salon",
            "type":"Services"
        }
    ],
    "sg:phone":"+1 951 304 9249",
    "sg:postcode":"92562",
    "sg:province":"CA",
    "sg:tags":[
        "manicuring"
    ],
    "wof:name":"Nails & Spa",
    "wof:placetype":"venue"
},
  "geometry": {"coordinates":[-117.200863,33.557742],"type":"Point"}
}