{
  "type": "Feature",
  "properties": {
    "addr:full":"2744 el Camino Real Santa Clara CA 95051",
    "addr:housenumber":"2744",
    "addr:postcode":"95051",
    "addr:street":"El Camino Real",
    "iso:country":"US",
    "sg:address":"2744 el Camino Real",
    "sg:city":"Santa Clara",
    "sg:classifiers":[
        {
            "category":"Professional",
            "subcategory":"Accounting & Tax Preparation",
            "type":"Services"
        }
    ],
    "sg:phone":"+1 408 985 1044",
    "sg:postcode":"95051",
    "sg:province":"CA",
    "sg:tags":[
        "return",
        "filing"
    ],
    "wof:name":"H & R Block Tax Svc",
    "wof:placetype":"venue"
},
  "geometry": {"coordinates":[-121.975542,37.352205],"type":"Point"}
}