{
  "type": "Feature",
  "properties": {
    "addr:full":"870 Market Street Ste 305 San Francisco CA 94102",
    "addr:housenumber":"870",
    "addr:postcode":"94102",
    "addr:street":"Market Street Ste 305",
    "iso:country":"US",
    "sg:address":"870 Market Street Ste 305",
    "sg:city":"San Francisco",
    "sg:classifiers":[
        {
            "category":"Personal",
            "type":"Services"
        }
    ],
    "sg:phone":"+1 415 677 9820",
    "sg:postcode":"94102",
    "sg:province":"CA",
    "sg:tags":[
        "sewing",
        "alteration"
    ],
    "wof:name":"David's Tailor Shop Tailors & Alterations",
    "wof:placetype":"venue"
},
  "geometry": {"coordinates":[-122.40737900000001,37.78507],"type":"Point"}
}