{
  "type": "Feature",
  "properties": {
    "addr:full":"1240 N Hacienda Blvd La Puente CA 91744",
    "addr:housenumber":"1240",
    "addr:postcode":"91744",
    "addr:street":"N Hacienda Blvd",
    "iso:country":"US",
    "sg:address":"1240 N Hacienda Blvd",
    "sg:city":"La Puente",
    "sg:classifiers":[
        {
            "category":"Education",
            "subcategory":"Special Training",
            "type":"Public Place"
        }
    ],
    "sg:phone":"+1 626 917 1766",
    "sg:postcode":"91744",
    "sg:province":"CA",
    "sg:tags":[
        "tutoring"
    ],
    "wof:name":"Jones Reading & Math Clinic",
    "wof:placetype":"venue"
},
  "geometry": {"coordinates":[-117.948908,34.045382],"type":"Point"}
}