{
  "type": "Feature",
  "properties": {
    "iso:country":"US",
    "sg:address":"320 W Lewis St",
    "sg:city":"Ventura",
    "sg:classifiers":[
        {
            "category":"Manufacturing",
            "subcategory":"Building Materials",
            "type":"Manufacturing & Wholesale Goods"
        }
    ],
    "sg:phone":"+1 805 648 6943",
    "sg:postcode":"93001",
    "sg:province":"CA",
    "sg:tags":[
        "mfg",
        "wood",
        "kitchen",
        "cabinet"
    ],
    "sg:website":"www.rubottomco.com",
    "wof:name":"W L Rubottom Co",
    "wof:placetype":"venue"
},
  "geometry": {"coordinates":[-119.300642,34.295598],"type":"Point"}
}