{
  "type": "Feature",
  "properties": {
    "addr:full":"50 Victoria Ave Suite 100 Millbrae CA 94030",
    "addr:housenumber":"50",
    "addr:postcode":"94030",
    "addr:street":"Victoria Ave Suite 100",
    "iso:country":"US",
    "sg:address":"50 Victoria Ave Suite 100",
    "sg:city":"Millbrae",
    "sg:classifiers":[
        {
            "category":"Insurance",
            "subcategory":"Hazard Insurance",
            "type":"Services"
        },
        {
            "category":"Insurance",
            "subcategory":"Health Insurance",
            "type":"Services"
        }
    ],
    "sg:phone":"+1 510 280 1687",
    "sg:postcode":"94030",
    "sg:province":"CA",
    "sg:tags":[
        "disability",
        "compensation",
        "commercial",
        "worker",
        "business"
    ],
    "sg:website":"http://www.bifs1.com",
    "wof:name":"Berkeley Insurance",
    "wof:placetype":"venue"
},
  "geometry": {"coordinates":[-122.39016700000001,37.600151],"type":"Point"}
}