{
  "type": "Feature",
  "properties": {
    "iso:country":"US",
    "sg:address":"4645 Van Nuys Blvd",
    "sg:city":"Sherman Oaks",
    "sg:classifiers":[
        {
            "category":"Education",
            "subcategory":"Special Training",
            "type":"Public Place"
        }
    ],
    "sg:phone":"+1 818 728 0260",
    "sg:postcode":"91403",
    "sg:province":"CA",
    "sg:tags":[
        "instruction",
        "music"
    ],
    "wof:name":"Vocal Image",
    "wof:placetype":"venue"
},
  "geometry": {"coordinates":[-118.44877,34.155466],"type":"Point"}
}