{
  "type": "Feature",
  "properties": {
    "addr:full":"1079 Sunrise Ave Roseville CA 95661",
    "addr:housenumber":"1079",
    "addr:postcode":"95661",
    "addr:street":"Sunrise Ave",
    "iso:country":"US",
    "sg:address":"1079 Sunrise Ave",
    "sg:city":"Roseville",
    "sg:classifiers":[
        {
            "category":"Travel",
            "subcategory":"Travel Agent",
            "type":"Entertainment"
        }
    ],
    "sg:phone":"+1 916 786 5101",
    "sg:postcode":"95661",
    "sg:province":"CA",
    "sg:tags":[
        "agency",
        "bureau"
    ],
    "wof:name":"Kyle Travel",
    "wof:placetype":"venue"
},
  "geometry": {"coordinates":[-121.271996,38.728078],"type":"Point"}
}