{
  "type": "Feature",
  "properties": {
    "addr:full":"302 Pasadera Dr Monterey CA 93940",
    "addr:housenumber":"302",
    "addr:postcode":"93940",
    "addr:street":"Pasadera Dr",
    "iso:country":"US",
    "sg:address":"302 Pasadera Dr",
    "sg:city":"Monterey",
    "sg:classifiers":[
        {
            "category":"Communications",
            "subcategory":"Radio Station",
            "type":"Services"
        }
    ],
    "sg:phone":"+1 831 375 3676",
    "sg:postcode":"93940",
    "sg:province":"CA",
    "sg:tags":[
        "broadcast"
    ],
    "wof:name":"First Yosemite Corporation",
    "wof:placetype":"venue"
},
  "geometry": {"coordinates":[-121.767888,36.575998],"type":"Point"}
}