{
  "type": "Feature",
  "properties": {
    "iso:country":"US",
    "sg:address":"5508 Greco Ln",
    "sg:city":"Salida",
    "sg:classifiers":[
        {
            "category":"Shopping",
            "subcategory":"Florist",
            "type":"Retail Goods"
        }
    ],
    "sg:phone":"+1 209 545 9400",
    "sg:postcode":"95368",
    "sg:province":"CA",
    "wof:name":"Floral Elegance",
    "wof:placetype":"venue"
},
  "geometry": {"coordinates":[-121.091184,37.718222],"type":"Point"}
}