{
  "type": "Feature",
  "properties": {
    "iso:country":"US",
    "sg:address":"301 E Ocean Blvd",
    "sg:city":"Long Beach",
    "sg:classifiers":[
        {
            "category":"Insurance",
            "subcategory":"Insurance Agent",
            "type":"Services"
        }
    ],
    "sg:phone":"+1 562 436 5777",
    "sg:postcode":"90802",
    "sg:province":"CA",
    "wof:name":"Individual & Corporate Benefit",
    "wof:placetype":"venue"
},
  "geometry": {"coordinates":[-118.189378,33.766925],"type":"Point"}
}