{
  "type": "Feature",
  "properties": {
    "iso:country":"US",
    "sg:address":"589 Juniper Ct",
    "sg:city":"Newbury Park",
    "sg:classifiers":[
        {
            "category":"Professional",
            "type":"Services"
        }
    ],
    "sg:phone":"+1 805 498 9321",
    "sg:postcode":"91320",
    "sg:province":"CA",
    "wof:name":"Audio Etc",
    "wof:placetype":"venue"
},
  "geometry": {"coordinates":[-118.942037,34.167407],"type":"Point"}
}