{
  "type": "Feature",
  "properties": {
    "iso:country":"US",
    "sg:address":"1009 Muirfield Dr",
    "sg:city":"Newport Beach",
    "sg:classifiers":[
        {
            "category":"Professional",
            "subcategory":"Business Services",
            "type":"Services"
        }
    ],
    "sg:phone":"+1 949 640 4499",
    "sg:postcode":"92660",
    "sg:province":"CA",
    "sg:tags":[
        "interior",
        "design"
    ],
    "wof:name":"Joan Kipper Design",
    "wof:placetype":"venue"
},
  "geometry": {"coordinates":[-117.862872,33.628468],"type":"Point"}
}