{
  "type": "Feature",
  "properties": {
    "addr:full":"24155 Laguna Hills Mall Ste 1690A Laguna Hills CA 92653",
    "addr:housenumber":"24155",
    "addr:postcode":"92653",
    "addr:street":"Laguna;Mall Ste 1690A",
    "iso:country":"US",
    "sg:address":"24155 Laguna Hills Mall Ste 1690A",
    "sg:city":"Laguna Hills",
    "sg:classifiers":[
        {
            "category":"Professional",
            "subcategory":"Art Services",
            "type":"Services"
        }
    ],
    "sg:phone":"+1 949 380 1884",
    "sg:postcode":"92653",
    "sg:province":"CA",
    "sg:tags":[
        "photographer"
    ],
    "sg:website":"www.fotograafe.zenfolio.com",
    "wof:name":"Fotograafe Photo Studio & Gallery",
    "wof:placetype":"venue"
},
  "geometry": {"coordinates":[-117.707774,33.610477],"type":"Point"}
}