{
  "type": "Feature",
  "properties": {
    "addr:full":"1900 Rocking Horse Dr Simi Valley CA 93065",
    "addr:housenumber":"1900",
    "addr:postcode":"93065",
    "addr:street":"Rocking Horse Dr",
    "iso:country":"US",
    "sg:address":"1900 Rocking Horse Dr",
    "sg:city":"Simi Valley",
    "sg:classifiers":[
        {
            "category":"Freight",
            "type":"Transportation"
        }
    ],
    "sg:phone":"+1 805 582 9875",
    "sg:postcode":"93065",
    "sg:province":"CA",
    "sg:tags":[
        "operator",
        "local",
        "trucking"
    ],
    "wof:name":"Albert Tiuo",
    "wof:placetype":"venue"
},
  "geometry": {"coordinates":[-118.759146,34.240822],"type":"Point"}
}