{
  "type": "Feature",
  "properties": {
    "iso:country":"US",
    "sg:address":"1261 W 7th St",
    "sg:city":"Upland",
    "sg:classifiers":[
        {
            "category":"Personal",
            "subcategory":"Beauty Salon",
            "type":"Services"
        }
    ],
    "sg:phone":"+1 909 931 2161",
    "sg:postcode":"91786",
    "sg:province":"CA",
    "wof:name":"Shekhryistyl",
    "wof:placetype":"venue"
},
  "geometry": {"coordinates":[-117.671324,34.088855],"type":"Point"}
}