{
  "type": "Feature",
  "properties": {
    "addr:full":"2197 Lake Tahoe Blvd South Lake Tahoe CA 96150",
    "addr:housenumber":"2197",
    "addr:postcode":"96150",
    "addr:street":"Lake Tahoe Blvd",
    "iso:country":"US",
    "sg:address":"2197 Lake Tahoe Blvd",
    "sg:city":"South Lake Tahoe",
    "sg:classifiers":[
        {
            "category":"Insurance",
            "subcategory":"Insurance Agent",
            "type":"Services"
        }
    ],
    "sg:phone":"+1 530 544 7046",
    "sg:postcode":"96150",
    "sg:province":"CA",
    "wof:name":"Allstate Insurance",
    "wof:placetype":"venue"
},
  "geometry": {"coordinates":[-119.99813899999999,38.917471],"type":"Point"}
}