{
  "type": "Feature",
  "properties": {
    "addr:full":"4343 Duquesne Ave Culver City CA 90232",
    "addr:housenumber":"4343",
    "addr:postcode":"90232",
    "addr:street":"Duquesne Ave",
    "iso:country":"US",
    "sg:address":"4343 Duquesne Ave",
    "sg:city":"Culver City",
    "sg:classifiers":[
        {
            "category":"Local Transit",
            "type":"Transportation"
        }
    ],
    "sg:phone":"+1 310 253 6510",
    "sg:postcode":"90232",
    "sg:province":"CA",
    "sg:tags":[
        "public"
    ],
    "sg:website":"www.culvercity.org/depts_bus.asp",
    "wof:name":"Culver City Bus",
    "wof:placetype":"venue"
},
  "geometry": {"coordinates":[-118.389503,34.017509],"type":"Point"}
}