{
  "type": "Feature",
  "properties": {
    "iso:country":"US",
    "sg:address":"16813 Prairie Ave",
    "sg:city":"Lawndale",
    "sg:classifiers":[
        {
            "category":"Professional",
            "subcategory":"Accounting & Tax Preparation",
            "type":"Services"
        }
    ],
    "sg:phone":"+1 310 921 0040",
    "sg:postcode":"90260",
    "sg:province":"CA",
    "sg:tags":[
        "consultant"
    ],
    "wof:name":"Management Consulting LLP",
    "wof:placetype":"venue"
},
  "geometry": {"coordinates":[-118.34377499999999,33.877566],"type":"Point"}
}