{
  "type": "Feature",
  "properties": {
    "iso:country":"US",
    "sg:address":"2311 Lee Ave Ste C",
    "sg:city":"South El Monte",
    "sg:classifiers":[
        {
            "category":"Food & Beverages",
            "subcategory":"Meat & Fish",
            "type":"Retail Goods"
        }
    ],
    "sg:phone":"+1 626 582 8188",
    "sg:postcode":"91733",
    "sg:province":"CA",
    "sg:tags":[
        "seafood",
        "market"
    ],
    "wof:name":"Ly North Star Seafood Inc",
    "wof:placetype":"venue"
},
  "geometry": {"coordinates":[-118.067001,34.054699],"type":"Point"}
}