{
  "type": "Feature",
  "properties": {
    "iso:country":"US",
    "sg:address":"2955 N Moorpark Rd",
    "sg:city":"Thousand Oaks",
    "sg:classifiers":[
        {
            "category":"Personal",
            "type":"Services"
        }
    ],
    "sg:phone":"+1 805 368 6824",
    "sg:postcode":"91360",
    "sg:province":"CA",
    "sg:tags":[
        "therapist",
        "massage"
    ],
    "wof:name":"Kentner Sabina",
    "wof:placetype":"venue"
},
  "geometry": {"coordinates":[-118.868326,34.219389],"type":"Point"}
}