{
  "type": "Feature",
  "properties": {
    "addr:full":"939 Koster St Eureka CA 95501",
    "addr:housenumber":"939",
    "addr:postcode":"95501",
    "addr:street":"Koster St",
    "iso:country":"US",
    "sg:address":"939 Koster St",
    "sg:city":"Eureka",
    "sg:classifiers":[
        {
            "category":"Wholesale",
            "subcategory":"Electrical",
            "type":"Manufacturing & Wholesale Goods"
        }
    ],
    "sg:phone":"+1 707 444 8031",
    "sg:postcode":"95501",
    "sg:province":"CA",
    "sg:tags":[
        "equipment",
        "electric",
        "supply"
    ],
    "wof:name":"Platt Electric Supply Inc",
    "wof:placetype":"venue"
},
  "geometry": {"coordinates":[-124.179062,40.797932],"type":"Point"}
}