{
  "type": "Feature",
  "properties": {
    "iso:country":"US",
    "sg:address":"2045 Royal Ave",
    "sg:city":"Simi Valley",
    "sg:classifiers":[
        {
            "category":"Recreation",
            "type":"Entertainment"
        }
    ],
    "sg:phone":"+1 805 578 9828",
    "sg:postcode":"93065",
    "sg:province":"CA",
    "sg:tags":[
        "instruction",
        "yoga"
    ],
    "wof:name":"Hatha Yoga Care",
    "wof:placetype":"venue"
},
  "geometry": {"coordinates":[-118.757091,34.260957],"type":"Point"}
}