{
  "type": "Feature",
  "properties": {
    "iso:country":"US",
    "sg:address":"16654 Cohasset St",
    "sg:city":"Van Nuys",
    "sg:classifiers":[
        {
            "category":"Building & Trades",
            "subcategory":"Construction",
            "type":"Services"
        }
    ],
    "sg:phone":"+1 818 781 6032",
    "sg:postcode":"91406",
    "sg:province":"CA",
    "sg:tags":[
        "painter"
    ],
    "wof:name":"Bill Owens Painting & Plaster",
    "wof:placetype":"venue"
},
  "geometry": {"coordinates":[-118.495763,34.206848],"type":"Point"}
}