{
  "type": "Feature",
  "properties": {
    "iso:country":"US",
    "sg:address":"1330 Highland Ave",
    "sg:city":"Duarte",
    "sg:classifiers":[
        {
            "category":"Organizations",
            "subcategory":"Religious Organization",
            "type":"Services"
        }
    ],
    "sg:phone":"+1 626 357 3540",
    "sg:postcode":"91010",
    "sg:province":"CA",
    "sg:tags":[
        "church"
    ],
    "wof:name":"Church Of Christ",
    "wof:placetype":"venue"
},
  "geometry": {"coordinates":[-117.966537,34.138054],"type":"Point"}
}