{
  "type": "Feature",
  "properties": {
    "addr:full":"15915 Main St La Puente CA 91744",
    "addr:housenumber":"15915",
    "addr:postcode":"91744",
    "addr:street":"Main St",
    "iso:country":"US",
    "sg:address":"15915 Main St",
    "sg:city":"La Puente",
    "sg:classifiers":[
        {
            "category":"Building & Trades",
            "subcategory":"Construction",
            "type":"Services"
        }
    ],
    "sg:phone":"+1 626 336 1913",
    "sg:postcode":"91744",
    "sg:province":"CA",
    "sg:tags":[
        "coping",
        "plastering",
        "tiling",
        "pool",
        "swimming"
    ],
    "wof:name":"A-1 Swimming Pool Svc",
    "wof:placetype":"venue"
},
  "geometry": {"coordinates":[-117.950729,34.020172],"type":"Point"}
}