{
  "type": "Feature",
  "properties": {
    "addr:full":"9631 Alondra Blvd Bellflower CA 90706",
    "addr:housenumber":"9631",
    "addr:postcode":"90706",
    "addr:street":"Alondra Blvd",
    "iso:country":"US",
    "sg:address":"9631 Alondra Blvd",
    "sg:city":"Bellflower",
    "sg:classifiers":[
        {
            "category":"Banks & Credit Unions",
            "subcategory":"Bank",
            "type":"Services"
        }
    ],
    "sg:phone":"+1 562 804 4909",
    "sg:postcode":"90706",
    "sg:province":"CA",
    "sg:tags":[
        "loan",
        "real estate"
    ],
    "wof:name":"Bormel Equity Lenders",
    "wof:placetype":"venue"
},
  "geometry": {"coordinates":[-118.129656,33.889421],"type":"Point"}
}