{
  "type": "Feature",
  "properties": {
    "iso:country":"US",
    "sg:address":"10924 Le Conte Avenue",
    "sg:city":"Los Angeles",
    "sg:classifiers":[
        {
            "category":"Professional",
            "subcategory":"Research",
            "type":"Services"
        }
    ],
    "sg:phone":"+1 310 824 9999",
    "sg:postcode":"90024",
    "sg:province":"CA",
    "sg:website":"http://www.kitepharma.com",
    "wof:name":"Kite Pharma",
    "wof:placetype":"venue"
},
  "geometry": {"coordinates":[-118.44534299999999,34.063675],"type":"Point"}
}