{
  "type": "Feature",
  "properties": {
    "addr:full":"10829 Olson Dr Rancho Cordova CA 95670",
    "addr:housenumber":"10829",
    "addr:postcode":"95670",
    "addr:street":"Olson Dr",
    "iso:country":"US",
    "sg:address":"10829 Olson Dr",
    "sg:city":"Rancho Cordova",
    "sg:classifiers":[
        {
            "category":"Restaurant",
            "type":"Food & Drink"
        }
    ],
    "sg:phone":"+1 916 858 2695",
    "sg:postcode":"95670",
    "sg:province":"CA",
    "wof:name":"Nippon Teriyaki Bowl",
    "wof:placetype":"venue"
},
  "geometry": {"coordinates":[-121.285004,38.5938],"type":"Point"}
}