{
  "type": "Feature",
  "properties": {
    "addr:full":"5160 Whittier Boulevard Los Angeles CA 90022",
    "addr:housenumber":"5160",
    "addr:postcode":"90022",
    "addr:street":"Whittier Boulevard",
    "iso:country":"US",
    "sg:address":"5160 Whittier Boulevard",
    "sg:city":"Los Angeles",
    "sg:classifiers":[
        {
            "category":"Shopping",
            "subcategory":"Shoes",
            "type":"Retail Goods"
        }
    ],
    "sg:phone":"+1 323 780 8870",
    "sg:postcode":"90022",
    "sg:province":"CA",
    "sg:tags":[
        "store"
    ],
    "wof:name":"Eurostar",
    "wof:placetype":"venue"
},
  "geometry": {"coordinates":[-118.158387,34.020534],"type":"Point"}
}