{
  "type": "Feature",
  "properties": {
    "iso:country":"US",
    "sg:address":"22336 Meekland Ave Ste A",
    "sg:city":"Hayward",
    "sg:classifiers":[
        {
            "category":"Retail",
            "subcategory":"Auto Repair",
            "type":"Services"
        }
    ],
    "sg:phone":"+1 510 885 9471",
    "sg:postcode":"94541",
    "sg:province":"CA",
    "sg:tags":[
        "motorcycle"
    ],
    "wof:name":"Metal Dragon",
    "wof:placetype":"venue"
},
  "geometry": {"coordinates":[-122.100793,37.669064],"type":"Point"}
}