{
  "type": "Feature",
  "properties": {
    "addr:full":"126 S Cloverdale Blvd Cloverdale CA 95425",
    "addr:housenumber":"126",
    "addr:postcode":"95425",
    "addr:street":"S Cloverdale Blvd",
    "iso:country":"US",
    "sg:address":"126 S Cloverdale Blvd",
    "sg:city":"Cloverdale",
    "sg:classifiers":[
        {
            "category":"Professional",
            "subcategory":"Employment Agencies",
            "type":"Services"
        }
    ],
    "sg:phone":"+1 707 894 4400",
    "sg:postcode":"95425",
    "sg:province":"CA",
    "sg:tags":[
        "opportunity"
    ],
    "sg:website":"www.norcaljobs.com",
    "wof:name":"Management Connections",
    "wof:placetype":"venue"
},
  "geometry": {"coordinates":[-123.016817,38.804946],"type":"Point"}
}