{
  "type": "Feature",
  "properties": {
    "addr:full":"415 W Carroll Ave Glendora CA 91741",
    "addr:housenumber":"415",
    "addr:postcode":"91741",
    "addr:street":"W Carroll Ave",
    "iso:country":"US",
    "sg:address":"415 W Carroll Ave",
    "sg:city":"Glendora",
    "sg:classifiers":[
        {
            "category":"Health Services",
            "subcategory":"Medical Lab",
            "type":"Services"
        }
    ],
    "sg:phone":"+1 626 650 0400",
    "sg:postcode":"91741",
    "sg:province":"CA",
    "sg:tags":[
        "laboratory"
    ],
    "wof:name":"Aesthetic Dental Studio",
    "wof:placetype":"venue"
},
  "geometry": {"coordinates":[-117.872258,34.134287],"type":"Point"}
}