{
  "type": "Feature",
  "properties": {
    "iso:country":"US",
    "sg:address":"2933 Alvarado St",
    "sg:city":"San Leandro",
    "sg:classifiers":[
        {
            "category":"Building & Trades",
            "subcategory":"Construction",
            "type":"Services"
        }
    ],
    "sg:phone":"+1 510 895 2200",
    "sg:postcode":"94577",
    "sg:province":"CA",
    "sg:tags":[
        "resurfacing",
        "laying",
        "refinishing",
        "floor"
    ],
    "wof:name":"House Of Floors",
    "wof:placetype":"venue"
},
  "geometry": {"coordinates":[-122.153548,37.707686],"type":"Point"}
}