{
  "type": "Feature",
  "properties": {
    "addr:full":"2141 Tully Rd San Jose CA 95111",
    "addr:housenumber":"2141",
    "addr:postcode":"95111",
    "addr:street":"Tully Rd",
    "iso:country":"US",
    "sg:address":"2141 Tully Rd",
    "sg:city":"San Jose",
    "sg:classifiers":[
        {
            "category":"Real Estate",
            "subcategory":"Real Estate Agent",
            "type":"Services"
        }
    ],
    "sg:phone":"+1 408 272 6865",
    "sg:postcode":"95111",
    "sg:province":"CA",
    "wof:name":"Carmen Munoz Real Estate",
    "wof:placetype":"venue"
},
  "geometry": {"coordinates":[-121.818628,37.327371],"type":"Point"}
}