{
  "type": "Feature",
  "properties": {
    "iso:country":"US",
    "sg:address":"505 Almanor St",
    "sg:city":"Petaluma",
    "sg:classifiers":[
        {
            "category":"Wholesale",
            "subcategory":"Apparel",
            "type":"Manufacturing & Wholesale Goods"
        }
    ],
    "sg:phone":"+1 707 773 3668",
    "sg:postcode":"94954",
    "sg:province":"CA",
    "sg:tags":[
        "shoes"
    ],
    "wof:name":"Gic International",
    "wof:placetype":"venue"
},
  "geometry": {"coordinates":[-122.629715,38.264545],"type":"Point"}
}