{
  "type": "Feature",
  "properties": {
    "addr:full":"10925 S Figueroa Street Los Angeles CA 90061",
    "addr:housenumber":"10925",
    "addr:postcode":"90061",
    "addr:street":"S Figueroa Street",
    "iso:country":"US",
    "sg:address":"10925 S Figueroa Street",
    "sg:city":"Los Angeles",
    "sg:classifiers":[
        {
            "category":"Restaurant",
            "type":"Food & Drink"
        }
    ],
    "sg:phone":"+1 323 418 8502",
    "sg:postcode":"90061",
    "sg:province":"CA",
    "wof:name":"Navarro Restaurant",
    "wof:placetype":"venue"
},
  "geometry": {"coordinates":[-118.282466,33.936879],"type":"Point"}
}