{
  "type": "Feature",
  "properties": {
    "addr:full":"73605 Jack Clark Ct Thousand Palms CA 92276",
    "addr:housenumber":"73605",
    "addr:postcode":"92276",
    "addr:street":"Jack Clark Ct",
    "iso:country":"US",
    "sg:address":"73605 Jack Clark Ct",
    "sg:city":"Thousand Palms",
    "sg:classifiers":[
        {
            "category":"Professional",
            "type":"Services"
        },
        {
            "category":"Building & Trades",
            "subcategory":"Construction",
            "type":"Services"
        }
    ],
    "sg:phone":"+1 760 343 5500",
    "sg:postcode":"92276",
    "sg:province":"CA",
    "sg:tags":[
        "contractor"
    ],
    "sg:website":"www.riclyn.com",
    "wof:name":"Riclyn Construction",
    "wof:placetype":"venue"
},
  "geometry": {"coordinates":[-116.37840199999999,33.828316],"type":"Point"}
}