{
  "type": "Feature",
  "properties": {
    "iso:country":"US",
    "sg:address":"227 N Jackson Ave",
    "sg:city":"San Jose",
    "sg:classifiers":[
        {
            "category":"Health Services",
            "subcategory":"Doctor",
            "type":"Services"
        }
    ],
    "sg:phone":"+1 408 347 2370",
    "sg:postcode":"95116",
    "sg:province":"CA",
    "sg:tags":[
        "physician",
        "surgeon"
    ],
    "wof:name":"Santa Fe Medical Group",
    "wof:placetype":"venue"
},
  "geometry": {"coordinates":[-121.846131,37.361149],"type":"Point"}
}