{
  "type": "Feature",
  "properties": {
    "iso:country":"US",
    "sg:address":"3056 Snowbird Dr",
    "sg:city":"Chico",
    "sg:classifiers":[
        {
            "category":"Social Services",
            "subcategory":"Child Care",
            "type":"Services"
        }
    ],
    "sg:phone":"+1 530 342 9141",
    "sg:postcode":"95973",
    "sg:province":"CA",
    "wof:name":"Koala-Tee Family Day Care",
    "wof:placetype":"venue"
},
  "geometry": {"coordinates":[-121.86729,39.768691],"type":"Point"}
}