{
  "type": "Feature",
  "properties": {
    "addr:full":"2161 India St San Diego CA 92101",
    "addr:housenumber":"2161",
    "addr:postcode":"92101",
    "addr:street":"India St",
    "iso:country":"US",
    "sg:address":"2161 India St",
    "sg:city":"San Diego",
    "sg:classifiers":[
        {
            "category":"Bars & Pubs",
            "subcategory":"Wine Bar",
            "type":"Food & Drink"
        }
    ],
    "sg:phone":"+1 619 564 7700",
    "sg:postcode":"92101",
    "sg:province":"CA",
    "sg:website":"www.tangowine.com",
    "wof:name":"Tango Wine Company",
    "wof:placetype":"venue"
},
  "geometry": {"coordinates":[-117.16967,32.726989],"type":"Point"}
}