{
  "type": "Feature",
  "properties": {
    "iso:country":"US",
    "sg:address":"23822 Valencia Blvd Ste 202",
    "sg:city":"Valencia",
    "sg:classifiers":[
        {
            "category":"Professional",
            "subcategory":"Accounting & Tax Preparation",
            "type":"Services"
        }
    ],
    "sg:phone":"+1 661 287 9596",
    "sg:postcode":"91355",
    "sg:province":"CA",
    "sg:tags":[
        "accountant"
    ],
    "wof:name":"Edwards & Sato Cpas",
    "wof:placetype":"venue"
},
  "geometry": {"coordinates":[-118.554001,34.412998],"type":"Point"}
}