{
  "type": "Feature",
  "properties": {
    "addr:full":"7550 Corbin Ave Reseda CA 91335",
    "addr:housenumber":"7550",
    "addr:postcode":"91335",
    "addr:street":"Corbin Ave",
    "iso:country":"US",
    "sg:address":"7550 Corbin Ave",
    "sg:city":"Reseda",
    "sg:classifiers":[
        {
            "category":"Banks & Credit Unions",
            "subcategory":"Bank",
            "type":"Services"
        }
    ],
    "sg:phone":"+1 818 993 3404",
    "sg:postcode":"91335",
    "sg:province":"CA",
    "sg:tags":[
        "feasibility",
        "consultant",
        "mortgage"
    ],
    "wof:name":"Rmg",
    "wof:placetype":"venue"
},
  "geometry": {"coordinates":[-118.562189,34.207123],"type":"Point"}
}