{
  "type": "Feature",
  "properties": {
    "addr:full":"1664 W Nebraska Ave Caruthers CA 93609",
    "addr:housenumber":"1664",
    "addr:postcode":"93609",
    "addr:street":"W Nebraska Ave",
    "iso:country":"US",
    "sg:address":"1664 W Nebraska Ave",
    "sg:city":"Caruthers",
    "sg:classifiers":[
        {
            "category":"Farming",
            "subcategory":"Vineyard",
            "type":"Manufacturing & Wholesale Goods"
        }
    ],
    "sg:phone":"+1 559 864 8720",
    "sg:postcode":"93609",
    "sg:province":"CA",
    "sg:tags":[
        "grape"
    ],
    "wof:name":"Fred E Jones",
    "wof:placetype":"venue"
},
  "geometry": {"coordinates":[-119.824134,36.561836],"type":"Point"}
}