{
  "type": "Feature",
  "properties": {
    "iso:country":"US",
    "sg:address":"949 Front St",
    "sg:city":"Novato",
    "sg:classifiers":[
        {
            "category":"Personal",
            "subcategory":"Beauty Salon",
            "type":"Services"
        },
        {
            "category":"Personal",
            "subcategory":"Nail Salon",
            "type":"Services"
        }
    ],
    "sg:phone":"+1 415 892 7825",
    "sg:postcode":"94945",
    "sg:province":"CA",
    "sg:website":"http://www.starnail.com",
    "wof:name":"Star Nails",
    "wof:placetype":"venue"
},
  "geometry": {"coordinates":[-122.57115899999999,38.105999],"type":"Point"}
}