{
  "type": "Feature",
  "properties": {
    "addr:full":"338 S Rosemead Blvd Pasadena CA 91107",
    "addr:housenumber":"338",
    "addr:postcode":"91107",
    "addr:street":"S Rosemead Blvd",
    "iso:country":"US",
    "sg:address":"338 S Rosemead Blvd",
    "sg:city":"Pasadena",
    "sg:classifiers":[
        {
            "category":"Professional",
            "subcategory":"Accounting & Tax Preparation",
            "type":"Services"
        }
    ],
    "sg:phone":"+1 626 793 4322",
    "sg:postcode":"91107",
    "sg:province":"CA",
    "sg:tags":[
        "accountant"
    ],
    "sg:website":"www.figco.com/",
    "wof:name":"Figuero & Company",
    "wof:placetype":"venue"
},
  "geometry": {"coordinates":[-118.07285,34.140655],"type":"Point"}
}