{
  "type": "Feature",
  "properties": {
    "iso:country":"US",
    "sg:address":"1319 S Main St",
    "sg:city":"Santa Ana",
    "sg:classifiers":[
        {
            "category":"Professional",
            "subcategory":"Computer Services",
            "type":"Services"
        }
    ],
    "sg:phone":"+1 714 557 2256",
    "sg:postcode":"92707",
    "sg:province":"CA",
    "sg:tags":[
        "repair"
    ],
    "wof:name":"Elvis Computer Com",
    "wof:placetype":"venue"
},
  "geometry": {"coordinates":[-117.86758500000001,33.731034],"type":"Point"}
}