{
  "type": "Feature",
  "properties": {
    "iso:country":"US",
    "sg:address":"77 Butterfly Ln",
    "sg:city":"Santa Barbara",
    "sg:classifiers":[
        {
            "category":"Shopping",
            "subcategory":"Musical Instruments",
            "type":"Retail Goods"
        }
    ],
    "sg:phone":"+1 805 969 4819",
    "sg:postcode":"93108",
    "sg:province":"CA",
    "wof:name":"Musicalhues",
    "wof:placetype":"venue"
},
  "geometry": {"coordinates":[-119.647976,34.419438],"type":"Point"}
}