{
  "type": "Feature",
  "properties": {
    "iso:country":"US",
    "sg:address":"15466 Los Gatos Boulevard",
    "sg:city":"Los Gatos",
    "sg:classifiers":[
        {
            "category":"Banks & Credit Unions",
            "subcategory":"Bank",
            "type":"Services"
        }
    ],
    "sg:phone":"+1 408 358 7444",
    "sg:postcode":"95032",
    "sg:province":"CA",
    "wof:name":"State Farm Insurance Companies",
    "wof:placetype":"venue"
},
  "geometry": {"coordinates":[-121.95886299999999,37.244191],"type":"Point"}
}