{
  "type": "Feature",
  "properties": {
    "iso:country":"US",
    "sg:address":"12723 Landmark Ave",
    "sg:city":"Victorville",
    "sg:classifiers":[
        {
            "category":"Professional",
            "subcategory":"Advertising",
            "type":"Services"
        }
    ],
    "sg:phone":"+1 760 955 1519",
    "sg:postcode":"92395",
    "sg:province":"CA",
    "sg:tags":[
        "distribution"
    ],
    "wof:name":"Elite Distribution",
    "wof:placetype":"venue"
},
  "geometry": {"coordinates":[-117.308724,34.482679],"type":"Point"}
}