{
  "type": "Feature",
  "properties": {
    "addr:full":"751 Sandoval Way Hayward CA 94544",
    "addr:housenumber":"751",
    "addr:postcode":"94544",
    "addr:street":"Sandoval Way",
    "iso:country":"US",
    "sg:address":"751 Sandoval Way",
    "sg:city":"Hayward",
    "sg:classifiers":[
        {
            "category":"Retail",
            "subcategory":"Auto Rental",
            "type":"Services"
        }
    ],
    "sg:phone":"+1 510 785 7154",
    "sg:postcode":"94544",
    "sg:province":"CA",
    "sg:tags":[
        "renting",
        "truck",
        "leasing"
    ],
    "sg:website":"www.pensketruckrental.com",
    "wof:name":"Penske Truck Leasing",
    "wof:placetype":"venue"
},
  "geometry": {"coordinates":[-122.053532,37.621645],"type":"Point"}
}