{
  "type": "Feature",
  "properties": {
    "iso:country":"US",
    "sg:address":"61 Main St",
    "sg:city":"Sutter Creek",
    "sg:classifiers":[
        {
            "category":"Shopping",
            "subcategory":"Used Merchandise",
            "type":"Retail Goods"
        }
    ],
    "sg:phone":"+1 209 267 0059",
    "sg:postcode":"95685",
    "sg:province":"CA",
    "sg:tags":[
        "antique"
    ],
    "wof:name":"Columbian Lady",
    "wof:placetype":"venue"
},
  "geometry": {"coordinates":[-120.801738,38.390102],"type":"Point"}
}