{
  "type": "Feature",
  "properties": {
    "addr:full":"4369 S Vermont Avenue Los Angeles CA 90037",
    "addr:housenumber":"4369",
    "addr:postcode":"90037",
    "addr:street":"S Vermont Avenue",
    "iso:country":"US",
    "sg:address":"4369 S Vermont Avenue",
    "sg:city":"Los Angeles",
    "sg:classifiers":[
        {
            "category":"Shopping",
            "subcategory":"Beauty & Cosmetics",
            "type":"Retail Goods"
        }
    ],
    "sg:phone":"+1 323 233 6775",
    "sg:postcode":"90037",
    "sg:province":"CA",
    "sg:tags":[
        "supply"
    ],
    "wof:name":"I M Beauty Supply",
    "wof:placetype":"venue"
},
  "geometry": {"coordinates":[-118.291416,34.004002],"type":"Point"}
}