{
  "type": "Feature",
  "properties": {
    "iso:country":"US",
    "sg:address":"470 S Rosemead Blvd",
    "sg:city":"Pasadena",
    "sg:classifiers":[
        {
            "category":"Restaurant",
            "type":"Food & Drink"
        }
    ],
    "sg:phone":"+1 626 792 7437",
    "sg:postcode":"91107",
    "sg:province":"CA",
    "sg:tags":[
        "traditional",
        "american",
        "italian"
    ],
    "sg:website":"www.nikkics.com",
    "wof:name":"Nikki C's",
    "wof:placetype":"venue"
},
  "geometry": {"coordinates":[-118.072823,34.138374],"type":"Point"}
}