{
  "type": "Feature",
  "properties": {
    "iso:country":"US",
    "sg:address":"9401 Wilshire Blvd",
    "sg:city":"Beverly Hills",
    "sg:classifiers":[
        {
            "category":"Professional",
            "subcategory":"Lawyer & Legal Services",
            "type":"Services"
        }
    ],
    "sg:phone":"+1 818 226 9840",
    "sg:postcode":"90212",
    "sg:province":"CA",
    "wof:name":"Goldberg and Goldberg",
    "wof:placetype":"venue"
},
  "geometry": {"coordinates":[-118.399002,34.0672],"type":"Point"}
}