{
  "type": "Feature",
  "properties": {
    "addr:full":"340 S Farrell Dr Palm Springs CA 92262",
    "addr:housenumber":"340",
    "addr:postcode":"92262",
    "addr:street":"S Farrell Dr",
    "iso:country":"US",
    "sg:address":"340 S Farrell Dr",
    "sg:city":"Palm Springs",
    "sg:classifiers":[
        {
            "category":"Health Services",
            "subcategory":"Doctor",
            "type":"Services"
        }
    ],
    "sg:phone":"+1 760 327 6225",
    "sg:postcode":"92262",
    "sg:province":"CA",
    "sg:tags":[
        "physician",
        "surgeon"
    ],
    "wof:name":"Southern California Desert",
    "wof:placetype":"venue"
},
  "geometry": {"coordinates":[-116.51798700000001,33.816685],"type":"Point"}
}