{
  "type": "Feature",
  "properties": {
    "addr:full":"3305 B St San Diego CA 92102",
    "addr:housenumber":"3305",
    "addr:postcode":"92102",
    "addr:street":"B St",
    "iso:country":"US",
    "sg:address":"3305 B St",
    "sg:city":"San Diego",
    "sg:classifiers":[
        {
            "category":"Real Estate",
            "subcategory":"Real Estate Agent",
            "type":"Services"
        }
    ],
    "sg:phone":"+1 619 227 2185",
    "sg:postcode":"92102",
    "sg:province":"CA",
    "sg:tags":[
        "appraiser"
    ],
    "wof:name":"A1 Appraisal Group",
    "wof:placetype":"venue"
},
  "geometry": {"coordinates":[-117.12110199999999,32.71792],"type":"Point"}
}