{
  "type": "Feature",
  "properties": {
    "addr:full":"3343 Industrial Dr Santa Rosa CA 95403",
    "addr:housenumber":"3343",
    "addr:postcode":"95403",
    "addr:street":"Industrial Dr",
    "iso:country":"US",
    "sg:address":"3343 Industrial Dr",
    "sg:city":"Santa Rosa",
    "sg:classifiers":[
        {
            "category":"Shopping",
            "subcategory":"Computers & Home Electronics",
            "type":"Retail Goods"
        }
    ],
    "sg:phone":"+1 707 528 2841",
    "sg:postcode":"95403",
    "sg:province":"CA",
    "sg:tags":[
        "equipment",
        "dealer"
    ],
    "sg:website":"www.mawson.com",
    "wof:name":"Mawson Computers",
    "wof:placetype":"venue"
},
  "geometry": {"coordinates":[-122.74001,38.476913],"type":"Point"}
}