{
  "type": "Feature",
  "properties": {
    "addr:full":"12950 Lakeland Rd Santa Fe Springs CA 90670",
    "addr:housenumber":"12950",
    "addr:postcode":"90670",
    "addr:street":"Lakeland Rd",
    "iso:country":"US",
    "sg:address":"12950 Lakeland Rd",
    "sg:city":"Santa Fe Springs",
    "sg:classifiers":[
        {
            "category":"Manufacturing",
            "subcategory":"Metals",
            "type":"Manufacturing & Wholesale Goods"
        }
    ],
    "sg:phone":"+1 562 941 4858",
    "sg:postcode":"90670",
    "sg:province":"CA",
    "sg:tags":[
        "production",
        "grinding"
    ],
    "wof:name":"Capital Grinding Inc",
    "wof:placetype":"venue"
},
  "geometry": {"coordinates":[-118.05560199999999,33.931653],"type":"Point"}
}