{
  "type": "Feature",
  "properties": {
    "addr:full":"360 Arneill Rd Camarillo CA 93010",
    "addr:housenumber":"360",
    "addr:postcode":"93010",
    "addr:street":"Arneill Rd",
    "iso:country":"US",
    "sg:address":"360 Arneill Rd",
    "sg:city":"Camarillo",
    "sg:classifiers":[
        {
            "category":"Building & Trades",
            "subcategory":"Construction",
            "type":"Services"
        }
    ],
    "sg:phone":"+1 805 388 8245",
    "sg:postcode":"93010",
    "sg:province":"CA",
    "sg:tags":[
        "tile",
        "dealer"
    ],
    "wof:name":"Moline Tile Inc",
    "wof:placetype":"venue"
},
  "geometry": {"coordinates":[-119.038994,34.221453],"type":"Point"}
}