{
  "type": "Feature",
  "properties": {
    "addr:full":"1646 Clementine St Anaheim CA 92802",
    "addr:postcode":"1646;92802",
    "addr:street":"Clementine St",
    "iso:country":"US",
    "sg:address":"1646 Clementine St",
    "sg:city":"Anaheim",
    "sg:classifiers":[
        {
            "category":"Retail",
            "subcategory":"Auto Rental",
            "type":"Services"
        }
    ],
    "sg:phone":"+1 714 997 3900",
    "sg:postcode":"92802",
    "sg:province":"CA",
    "sg:tags":[
        "car"
    ],
    "sg:website":"ez2rentacar.com/",
    "wof:name":"EZ Rent-A-Car",
    "wof:placetype":"venue"
},
  "geometry": {"coordinates":[-117.90998399999999,33.807981],"type":"Point"}
}