{
  "type": "Feature",
  "properties": {
    "addr:full":"2106 W Foothill Blvd Upland CA 91786",
    "addr:housenumber":"2106",
    "addr:postcode":"91786",
    "addr:street":"W Foothill Blvd",
    "iso:country":"US",
    "sg:address":"2106 W Foothill Blvd",
    "sg:city":"Upland",
    "sg:classifiers":[
        {
            "category":"Autos & Motor Vehicles",
            "subcategory":"Automobile Sales",
            "type":"Retail Goods"
        }
    ],
    "sg:phone":"+1 909 931 2180",
    "sg:postcode":"91786",
    "sg:province":"CA",
    "sg:tags":[
        "car",
        "dealer"
    ],
    "wof:name":"Auto Ready Inc",
    "wof:placetype":"venue"
},
  "geometry": {"coordinates":[-117.69358099999999,34.106725],"type":"Point"}
}