{
  "type": "Feature",
  "properties": {
    "addr:full":"1440 Broadway Ave Atwater CA 95301",
    "addr:housenumber":"1440",
    "addr:postcode":"95301",
    "addr:street":"Broadway Ave",
    "iso:country":"US",
    "sg:address":"1440 Broadway Ave",
    "sg:city":"Atwater",
    "sg:classifiers":[
        {
            "category":"Manufacturing",
            "subcategory":"Glass & Minerals",
            "type":"Manufacturing & Wholesale Goods"
        }
    ],
    "sg:phone":"+1 209 357 2075",
    "sg:postcode":"95301",
    "sg:province":"CA",
    "sg:tags":[
        "crystal",
        "glassware",
        "china"
    ],
    "wof:name":"China House",
    "wof:placetype":"venue"
},
  "geometry": {"coordinates":[-120.61121199999999,37.347684],"type":"Point"}
}