{
  "type": "Feature",
  "properties": {
    "addr:full":"2616 S Normandie Ave Los Angeles CA 90007",
    "addr:housenumber":"2616",
    "addr:postcode":"90007",
    "addr:street":"S Normandie Ave",
    "iso:country":"US",
    "sg:address":"2616 S Normandie Ave",
    "sg:city":"Los Angeles",
    "sg:classifiers":[
        {
            "category":"Freight",
            "type":"Transportation"
        }
    ],
    "sg:phone":"+1 323 735 2662",
    "sg:postcode":"90007",
    "sg:province":"CA",
    "sg:tags":[
        "arrangement"
    ],
    "wof:name":"Transportes Ulua Inc",
    "wof:placetype":"venue"
},
  "geometry": {"coordinates":[-118.300167,34.031198],"type":"Point"}
}