{
  "type": "Feature",
  "properties": {
    "iso:country":"US",
    "sg:address":"20151 Port Greenwich Ln",
    "sg:city":"Huntington Beach",
    "sg:classifiers":[
        {
            "category":"Manufacturing",
            "subcategory":"Printing",
            "type":"Manufacturing & Wholesale Goods"
        }
    ],
    "sg:phone":"+1 714 891 5006",
    "sg:postcode":"92646",
    "sg:province":"CA",
    "sg:tags":[
        "lithographic",
        "commercial"
    ],
    "wof:name":"Printmasters 88",
    "wof:placetype":"venue"
},
  "geometry": {"coordinates":[-117.981775,33.669882],"type":"Point"}
}