{
  "type": "Feature",
  "properties": {
    "iso:country":"US",
    "sg:address":"1042 E El Camino Real",
    "sg:city":"Sunnyvale",
    "sg:classifiers":[
        {
            "category":"Restaurant",
            "type":"Food & Drink"
        }
    ],
    "sg:phone":"+1 408 241 7292",
    "sg:postcode":"94087",
    "sg:province":"CA",
    "sg:tags":[
        "sushi",
        "bar",
        "japanese"
    ],
    "sg:website":"sawasushi.net",
    "wof:name":"Sawa Sushi",
    "wof:placetype":"venue"
},
  "geometry": {"coordinates":[-122.00453400000001,37.351546],"type":"Point"}
}