{
  "type": "Feature",
  "properties": {
    "iso:country":"US",
    "sg:address":"1700 Hillside Blvd",
    "sg:city":"Colma",
    "sg:classifiers":[
        {
            "category":"Community Center",
            "subcategory":"Social",
            "type":"Public Place"
        },
        {
            "category":"Casinos & Gambling",
            "type":"Entertainment"
        }
    ],
    "sg:phone":"+1 650 758 2237",
    "sg:postcode":"94014",
    "sg:province":"CA",
    "sg:tags":[
        "playing",
        "card",
        "room"
    ],
    "sg:website":"http://www.luckychances.com",
    "wof:name":"Lucky Chances Casino",
    "wof:placetype":"venue"
},
  "geometry": {"coordinates":[-122.452888,37.680721],"type":"Point"}
}