{
  "type": "Feature",
  "properties": {
    "iso:country":"US",
    "sg:address":"618 S 20th St",
    "sg:city":"Richmond",
    "sg:classifiers":[
        {
            "category":"Shopping",
            "subcategory":"Party Supplies",
            "type":"Retail Goods"
        }
    ],
    "sg:phone":"+1 510 575 1594",
    "sg:postcode":"94804",
    "sg:province":"CA",
    "wof:name":"CRAZY PARTY JUMPERS",
    "wof:placetype":"venue"
},
  "geometry": {"coordinates":[-122.35040600000001,37.923692],"type":"Point"}
}