{
  "type": "Feature",
  "properties": {
    "iso:country":"US",
    "sg:address":"10602 San Pablo Avenue",
    "sg:city":"El Cerrito",
    "sg:classifiers":[
        {
            "category":"Autos & Motor Vehicles",
            "subcategory":"Fuel & Gas Station",
            "type":"Retail Goods"
        }
    ],
    "sg:phone":"+1 510 559 8138",
    "sg:postcode":"94530",
    "sg:province":"CA",
    "wof:name":"Best Gas & Car Wash",
    "wof:placetype":"venue"
},
  "geometry": {"coordinates":[-122.308998,37.911598],"type":"Point"}
}