{
  "type": "Feature",
  "properties": {
    "iso:country":"US",
    "sg:address":"1611 Paramount Blvd",
    "sg:city":"Montebello",
    "sg:classifiers":[
        {
            "category":"Social Services",
            "type":"Services"
        }
    ],
    "sg:phone":"+1 323 889 1933",
    "sg:postcode":"90640",
    "sg:province":"CA",
    "sg:tags":[
        "organization",
        "welfare"
    ],
    "wof:name":"Arroyo Developmental Svc",
    "wof:placetype":"venue"
},
  "geometry": {"coordinates":[-118.093397,34.038336],"type":"Point"}
}