{
  "type": "Feature",
  "properties": {
    "iso:country":"US",
    "sg:address":"2411 W Olympic Blvd",
    "sg:city":"Los Angeles",
    "sg:classifiers":[
        {
            "category":"Shopping",
            "subcategory":"Clothing, Apparel, & Fashions",
            "type":"Retail Goods"
        }
    ],
    "sg:phone":"+1 213 383 0370",
    "sg:postcode":"90006",
    "sg:province":"CA",
    "sg:tags":[
        "maternity"
    ],
    "wof:name":"LA Ciguena",
    "wof:placetype":"venue"
},
  "geometry": {"coordinates":[-118.284132,34.052485],"type":"Point"}
}