{
  "type": "Feature",
  "properties": {
    "addr:full":"1409 4th St Coronado CA 92118",
    "addr:housenumber":"1409",
    "addr:postcode":"92118",
    "addr:street":"4Th St",
    "iso:country":"US",
    "sg:address":"1409 4th St",
    "sg:city":"Coronado",
    "sg:classifiers":[
        {
            "category":"Building & Trades",
            "subcategory":"Construction",
            "type":"Services"
        }
    ],
    "sg:phone":"+1 619 286 5071",
    "sg:postcode":"92118",
    "sg:province":"CA",
    "sg:tags":[
        "general",
        "contractor"
    ],
    "wof:name":"Coronado Island Construction",
    "wof:placetype":"venue"
},
  "geometry": {"coordinates":[-117.17110700000001,32.693013],"type":"Point"}
}