{
  "type": "Feature",
  "properties": {
    "iso:country":"US",
    "sg:address":"2005 San Elijo Ave",
    "sg:city":"Cardiff By The Sea",
    "sg:classifiers":[
        {
            "category":"Restaurant",
            "type":"Food & Drink"
        }
    ],
    "sg:menulink":"http://www.allmenus.com/ca/san-diego/30476-yogis/menu/",
    "sg:phone":"+1 760 943 9644",
    "sg:postcode":"92007",
    "sg:province":"CA",
    "sg:tags":[
        "american",
        "pub"
    ],
    "wof:name":"Yogi's",
    "wof:placetype":"venue"
},
  "geometry": {"coordinates":[-117.283305,33.022419],"type":"Point"}
}