{
  "type": "Feature",
  "properties": {
    "addr:full":"412 Olive Ave Huntington Beach CA 92648",
    "addr:housenumber":"412",
    "addr:postcode":"92648",
    "addr:street":"Olive Ave",
    "iso:country":"US",
    "sg:address":"412 Olive Ave",
    "sg:city":"Huntington Beach",
    "sg:classifiers":[
        {
            "category":"Building & Trades",
            "subcategory":"Cleaning & Sanitation",
            "type":"Services"
        }
    ],
    "sg:phone":"+1 714 677 2362",
    "sg:postcode":"92648",
    "sg:province":"CA",
    "sg:tags":[
        "home"
    ],
    "sg:website":"carpetcleaninginhuntingtonbeach....",
    "wof:name":"The Rug Scrubber",
    "wof:placetype":"venue"
},
  "geometry": {"coordinates":[-118.000298,33.658974],"type":"Point"}
}