{
  "type": "Feature",
  "properties": {
    "addr:full":"370 Hawthorne Ave Oakland CA 94609",
    "addr:housenumber":"370",
    "addr:postcode":"94609",
    "addr:street":"Hawthorne Ave",
    "iso:country":"US",
    "sg:address":"370 Hawthorne Ave",
    "sg:city":"Oakland",
    "sg:classifiers":[
        {
            "category":"Health Services",
            "subcategory":"Hospital",
            "type":"Services"
        }
    ],
    "sg:phone":"+1 510 655 4000",
    "sg:postcode":"94609",
    "sg:province":"CA",
    "wof:name":"Summit Medical Center",
    "wof:placetype":"venue"
},
  "geometry": {"coordinates":[-122.264,37.820999],"type":"Point"}
}