{
  "type": "Feature",
  "properties": {
    "iso:country":"US",
    "sg:address":"445 S Cataract Ave",
    "sg:city":"San Dimas",
    "sg:classifiers":[
        {
            "category":"Utilities",
            "subcategory":"Fuel Oil & Lpg",
            "type":"Services"
        }
    ],
    "sg:phone":"+1 909 592 4374",
    "sg:postcode":"91773",
    "sg:province":"CA",
    "sg:tags":[
        "petroleum",
        "gas"
    ],
    "wof:name":"Aeropres Corp",
    "wof:placetype":"venue"
},
  "geometry": {"coordinates":[-117.81146699999999,34.102952],"type":"Point"}
}