{
  "type": "Feature",
  "properties": {
    "addr:full":"10 Declaration Dr Chico CA 95973",
    "addr:housenumber":"10",
    "addr:postcode":"95973",
    "addr:street":"Declaration Dr",
    "iso:country":"US",
    "sg:address":"10 Declaration Dr",
    "sg:city":"Chico",
    "sg:classifiers":[
        {
            "category":"Real Estate",
            "subcategory":"Architect",
            "type":"Services"
        }
    ],
    "sg:phone":"+1 530 892 8008",
    "sg:postcode":"95973",
    "sg:province":"CA",
    "wof:name":"AEC Group",
    "wof:placetype":"venue"
},
  "geometry": {"coordinates":[-121.87410800000001,39.770697],"type":"Point"}
}