{
  "type": "Feature",
  "properties": {
    "addr:full":"5860 Silverado Trl Napa CA 94558",
    "addr:housenumber":"5860",
    "addr:postcode":"94558",
    "addr:street":"Silverado Trl",
    "iso:country":"US",
    "sg:address":"5860 Silverado Trl",
    "sg:city":"Napa",
    "sg:classifiers":[
        {
            "category":"Manufacturing",
            "subcategory":"Food",
            "type":"Manufacturing & Wholesale Goods"
        }
    ],
    "sg:phone":"+1 707 226 1796",
    "sg:postcode":"94558",
    "sg:province":"CA",
    "sg:tags":[
        "liquor",
        "mfg"
    ],
    "wof:name":"Kelly Martin Winery",
    "wof:placetype":"venue"
},
  "geometry": {"coordinates":[-122.336349,38.415114],"type":"Point"}
}