{
  "type": "Feature",
  "properties": {
    "addr:full":"8861 Jurupa Rd Riverside CA 92509",
    "addr:housenumber":"8861",
    "addr:postcode":"92509",
    "addr:street":"Jurupa Rd",
    "iso:country":"US",
    "sg:address":"8861 Jurupa Rd",
    "sg:city":"Riverside",
    "sg:classifiers":[
        {
            "category":"Building & Trades",
            "subcategory":"Construction",
            "type":"Services"
        }
    ],
    "sg:phone":"+1 951 685 2367",
    "sg:postcode":"92509",
    "sg:province":"CA",
    "sg:tags":[
        "paper",
        "painting",
        "hanging"
    ],
    "wof:name":"Alvarez Painting",
    "wof:placetype":"venue"
},
  "geometry": {"coordinates":[-117.482921,33.997797],"type":"Point"}
}