{
  "type": "Feature",
  "properties": {
    "iso:country":"US",
    "sg:address":"16 Cherokee Ln",
    "sg:city":"Lodi",
    "sg:classifiers":[
        {
            "category":"Shopping",
            "subcategory":"Hobbies, Toys, & Games",
            "type":"Retail Goods"
        }
    ],
    "sg:phone":"+1 209 727 3168",
    "sg:postcode":"95240",
    "sg:province":"CA",
    "wof:name":"Need For Speed",
    "wof:placetype":"venue"
},
  "geometry": {"coordinates":[-121.260555,38.134149],"type":"Point"}
}