{
  "type": "Feature",
  "properties": {
    "addr:full":"5961 Linda Vista Rd San Diego CA 92110",
    "addr:housenumber":"5961",
    "addr:postcode":"92110",
    "addr:street":"Linda Vista Rd",
    "iso:country":"US",
    "sg:address":"5961 Linda Vista Rd",
    "sg:city":"San Diego",
    "sg:classifiers":[
        {
            "category":"Education",
            "subcategory":"School",
            "type":"Public Place"
        }
    ],
    "sg:phone":"+1 619 298 8277",
    "sg:postcode":"92110",
    "sg:province":"CA",
    "wof:name":"University San Deigo High Schl",
    "wof:placetype":"venue"
},
  "geometry": {"coordinates":[-117.18711999999999,32.770637],"type":"Point"}
}