{
  "type": "Feature",
  "properties": {
    "iso:country":"US",
    "sg:address":"4173 Macarthur Blvd Ste 10",
    "sg:city":"Oakland",
    "sg:classifiers":[
        {
            "category":"Professional",
            "type":"Services"
        },
        {
            "category":"Food & Beverages",
            "subcategory":"Farmers Market",
            "type":"Retail Goods"
        },
        {
            "category":"Organizations",
            "subcategory":"Non-profit Organization",
            "type":"Services"
        }
    ],
    "sg:phone":"+1 510 482 1898",
    "sg:postcode":"94609",
    "sg:province":"CA",
    "sg:tags":[
        "service/non-profit",
        "community",
        "caterer"
    ],
    "sg:website":"www.foodcommunityculture.org",
    "wof:name":"Oakland Food Connection",
    "wof:placetype":"venue"
},
  "geometry": {"coordinates":[-122.196039,37.788735],"type":"Point"}
}