{
  "type": "Feature",
  "properties": {
    "iso:country":"US",
    "sg:address":"56070 State Hwy 371",
    "sg:city":"Anza",
    "sg:classifiers":[
        {
            "category":"Wholesale",
            "subcategory":"Machinery & Supplies",
            "type":"Manufacturing & Wholesale Goods"
        }
    ],
    "sg:phone":"+1 951 763 0033",
    "sg:postcode":"92539",
    "sg:province":"CA",
    "sg:tags":[
        "equipment",
        "veterinarian"
    ],
    "wof:name":"Ron's Veterinary Supply",
    "wof:placetype":"venue"
},
  "geometry": {"coordinates":[-116.682403,33.555224],"type":"Point"}
}