{
  "type": "Feature",
  "properties": {
    "addr:full":"6381 Rose Ln Carpinteria CA 93013",
    "addr:housenumber":"6381",
    "addr:postcode":"93013",
    "addr:street":"Rose Ln",
    "iso:country":"US",
    "sg:address":"6381 Rose Ln",
    "sg:city":"Carpinteria",
    "sg:classifiers":[
        {
            "category":"Communications",
            "type":"Services"
        }
    ],
    "sg:phone":"+1 714 633 2664",
    "sg:postcode":"93013",
    "sg:province":"CA",
    "wof:name":"Mc Kee Communications",
    "wof:placetype":"venue"
},
  "geometry": {"coordinates":[-119.48665800000001,34.388325],"type":"Point"}
}