{
  "type": "Feature",
  "properties": {
    "iso:country":"US",
    "sg:address":"6381 Rose Ln",
    "sg:city":"Carpinteria",
    "sg:classifiers":[
        {
            "category":"Communications",
            "type":"Services"
        }
    ],
    "sg:phone":"+1 714 633 2664",
    "sg:postcode":"93013",
    "sg:province":"CA",
    "wof:name":"Mc Kee Communications",
    "wof:placetype":"venue"
},
  "geometry": {"coordinates":[-119.486658,34.388325],"type":"Point"}
}