{
  "type": "Feature",
  "properties": {
    "addr:full":"2255 Oceanside Blvd Oceanside CA 92054",
    "addr:housenumber":"2255",
    "addr:postcode":"92054",
    "addr:street":"Oceanside Blvd",
    "iso:country":"US",
    "sg:address":"2255 Oceanside Blvd",
    "sg:city":"Oceanside",
    "sg:classifiers":[
        {
            "category":"Retail",
            "subcategory":"Auto Repair",
            "type":"Services"
        }
    ],
    "sg:phone":"+1 760 722 6718",
    "sg:postcode":"92054",
    "sg:province":"CA",
    "sg:tags":[
        "repairing",
        "automobile"
    ],
    "wof:name":"City Automotive",
    "wof:placetype":"venue"
},
  "geometry": {"coordinates":[-117.349998,33.198101],"type":"Point"}
}