{
  "type": "Feature",
  "properties": {
    "addr:full":"9039 Bolsa Ave #116a Westminster CA 92683",
    "addr:housenumber":"9039",
    "addr:postcode":"92683",
    "addr:street":"Bolsa Ave # 116A",
    "iso:country":"US",
    "sg:address":"9039 Bolsa Ave #116a",
    "sg:city":"Westminster",
    "sg:classifiers":[
        {
            "category":"Shopping",
            "subcategory":"Mobile Phones",
            "type":"Retail Goods"
        }
    ],
    "sg:phone":"+1 714 657 7420",
    "sg:postcode":"92683",
    "sg:province":"CA",
    "wof:name":"Premiere Mobile",
    "wof:placetype":"venue"
},
  "geometry": {"coordinates":[-117.971553,33.744921],"type":"Point"}
}