{
  "type": "Feature",
  "properties": {
    "iso:country":"US",
    "sg:address":"7525 Nelson St",
    "sg:city":"Sutter",
    "sg:classifiers":[
        {
            "category":"Retail",
            "subcategory":"Auto Rental",
            "type":"Services"
        }
    ],
    "sg:phone":"+1 530 674 1069",
    "sg:postcode":"95982",
    "sg:province":"CA",
    "sg:tags":[
        "renting",
        "truck",
        "leasing"
    ],
    "wof:name":"U-Haul Co",
    "wof:placetype":"venue"
},
  "geometry": {"coordinates":[-121.75044,39.159988],"type":"Point"}
}