{
  "type": "Feature",
  "properties": {
    "addr:full":"380 S Melrose Ave Vista CA 92081",
    "addr:housenumber":"380",
    "addr:postcode":"92081",
    "addr:street":"S Melrose Ave",
    "iso:country":"US",
    "sg:address":"380 S Melrose Ave",
    "sg:city":"Vista",
    "sg:classifiers":[
        {
            "category":"Banks & Credit Unions",
            "subcategory":"Atm",
            "type":"Services"
        }
    ],
    "sg:phone":"+1 760 643 4114",
    "sg:postcode":"92081",
    "sg:province":"CA",
    "sg:tags":[
        "bankruptcy"
    ],
    "sg:website":"www.northsandiegobankruptcy.com",
    "wof:name":"Beck Jonathan Attorney At Law",
    "wof:placetype":"venue"
},
  "geometry": {"coordinates":[-117.252861,33.19105],"type":"Point"}
}