{
  "type": "Feature",
  "properties": {
    "iso:country":"US",
    "sg:address":"20627 Golden Springs Dr Ste 2K",
    "sg:city":"Walnut",
    "sg:classifiers":[
        {
            "category":"Fast Food",
            "type":"Food & Drink"
        },
        {
            "category":"Restaurant",
            "type":"Food & Drink"
        }
    ],
    "sg:phone":"+1 909 869 7881",
    "sg:postcode":"91789",
    "sg:province":"CA",
    "sg:tags":[
        "asian",
        "japanese",
        "pan",
        "take"
    ],
    "wof:name":"Jubei Japanese Cuisine",
    "wof:placetype":"venue"
},
  "geometry": {"coordinates":[-117.855485,33.996459],"type":"Point"}
}