{
  "type": "Feature",
  "properties": {
    "addr:full":"4200 Park Blvd Ste 127 Oakland CA 94602",
    "addr:housenumber":"4200",
    "addr:postcode":"94602",
    "addr:street":"Park Blvd Ste 127",
    "iso:country":"US",
    "sg:address":"4200 Park Blvd Ste 127",
    "sg:city":"Oakland",
    "sg:classifiers":[
        {
            "category":"Community Center",
            "subcategory":"Senior",
            "type":"Public Place"
        },
        {
            "category":"Health Services",
            "subcategory":"Nursing And Care Facility",
            "type":"Services"
        },
        {
            "category":"Health Services",
            "subcategory":"Health Practitioner",
            "type":"Services"
        },
        {
            "category":"Social Services",
            "subcategory":"Adult Care",
            "type":"Services"
        },
        {
            "category":"Social Services",
            "subcategory":"Retirement Home",
            "type":"Services"
        }
    ],
    "sg:phone":"+1 510 482 8700",
    "sg:postcode":"94602",
    "sg:province":"CA",
    "sg:tags":[
        "living",
        "alzheimer's",
        "assisted",
        "elder",
        "convalescent",
        "citizen",
        "eldercare-home"
    ],
    "sg:website":"http://www.comfortkeepers.com",
    "wof:name":"Comfort Keepers",
    "wof:placetype":"venue"
},
  "geometry": {"coordinates":[-122.222641,37.807261],"type":"Point"}
}