{
  "type": "Feature",
  "properties": {
    "iso:country":"US",
    "sg:address":"1508 Eureka Rd",
    "sg:city":"Roseville",
    "sg:classifiers":[
        {
            "category":"Banks & Credit Unions",
            "subcategory":"Bank",
            "type":"Services"
        }
    ],
    "sg:phone":"+1 916 788 2660",
    "sg:postcode":"95661",
    "sg:province":"CA",
    "sg:tags":[
        "loan",
        "real estate"
    ],
    "wof:name":"American Home Mortgage",
    "wof:placetype":"venue"
},
  "geometry": {"coordinates":[-121.251478,38.751851],"type":"Point"}
}