{
  "type": "Feature",
  "properties": {
    "addr:full":"3407 W Olive Ave Burbank CA 91505",
    "addr:housenumber":"3407",
    "addr:postcode":"91505",
    "addr:street":"W Olive Ave",
    "iso:country":"US",
    "sg:address":"3407 W Olive Ave",
    "sg:city":"Burbank",
    "sg:classifiers":[
        {
            "category":"Building & Trades",
            "subcategory":"Construction",
            "type":"Services"
        }
    ],
    "sg:phone":"+1 818 842 5100",
    "sg:postcode":"91505",
    "sg:province":"CA",
    "sg:tags":[
        "contractor"
    ],
    "wof:name":"Cutter Construction",
    "wof:placetype":"venue"
},
  "geometry": {"coordinates":[-118.337323,34.153858],"type":"Point"}
}