{
  "type": "Feature",
  "properties": {
    "addr:full":"10625 W Chandler Blvd North Hollywood CA 91601",
    "addr:housenumber":"10625",
    "addr:postcode":"91601",
    "addr:street":"W Chandler Blvd",
    "iso:country":"US",
    "sg:address":"10625 W Chandler Blvd",
    "sg:city":"North Hollywood",
    "sg:classifiers":[
        {
            "category":"Communications",
            "subcategory":"Film & Video Production",
            "type":"Services"
        }
    ],
    "sg:phone":"+1 818 760 2319",
    "sg:postcode":"91601",
    "sg:province":"CA",
    "sg:tags":[
        "motion",
        "picture",
        "studio",
        "producer"
    ],
    "wof:name":"Motion Picture Placement",
    "wof:placetype":"venue"
},
  "geometry": {"coordinates":[-118.361863,34.168782],"type":"Point"}
}