{
  "type": "Feature",
  "properties": {
    "iso:country":"US",
    "sg:address":"3625 McLaughlin Ave",
    "sg:city":"Los Angeles",
    "sg:classifiers":[
        {
            "category":"Real Estate",
            "subcategory":"Real Estate Operator",
            "type":"Services"
        }
    ],
    "sg:phone":"+1 310 391 7818",
    "sg:postcode":"90066",
    "sg:province":"CA",
    "sg:tags":[
        "building",
        "apartment"
    ],
    "wof:name":"WRW Properties",
    "wof:placetype":"venue"
},
  "geometry": {"coordinates":[-118.42746200000001,34.012207],"type":"Point"}
}