{
  "type": "Feature",
  "properties": {
    "addr:full":"23123 Ventura Blvd Woodland Hills CA 91364",
    "addr:housenumber":"23123",
    "addr:postcode":"91364",
    "addr:street":"Ventura Blvd",
    "iso:country":"US",
    "sg:address":"23123 Ventura Blvd",
    "sg:city":"Woodland Hills",
    "sg:classifiers":[
        {
            "category":"Building & Trades",
            "subcategory":"Construction",
            "type":"Services"
        }
    ],
    "sg:phone":"+1 818 888 2044",
    "sg:postcode":"91364",
    "sg:province":"CA",
    "sg:tags":[
        "repairing",
        "remodeling",
        "contractor"
    ],
    "wof:name":"All Craft Construction",
    "wof:placetype":"venue"
},
  "geometry": {"coordinates":[-118.630172,34.163166],"type":"Point"}
}