{
  "type": "Feature",
  "properties": {
    "addr:full":"41535 Mayberry Ave Hemet CA 92544",
    "addr:postcode":"41535;92544",
    "addr:street":"Mayberry Ave",
    "iso:country":"US",
    "sg:address":"41535 Mayberry Ave",
    "sg:city":"Hemet",
    "sg:classifiers":[
        {
            "category":"Education",
            "subcategory":"School",
            "type":"Public Place"
        }
    ],
    "sg:phone":"+1 951 765 2550",
    "sg:postcode":"92544",
    "sg:province":"CA",
    "sg:tags":[
        "middle"
    ],
    "wof:name":"Dartmouth Middle School",
    "wof:placetype":"venue"
},
  "geometry": {"coordinates":[-116.936286,33.740447],"type":"Point"}
}