{
  "type": "Feature",
  "properties": {
    "addr:full":"1000 Kelsey Trl Crescent City CA 95531",
    "addr:housenumber":"1000",
    "addr:postcode":"95531",
    "addr:street":"Kelsey Trl Crescent",
    "iso:country":"US",
    "sg:address":"1000 Kelsey Trl",
    "sg:city":"Crescent City",
    "sg:classifiers":[
        {
            "category":"Building & Trades",
            "subcategory":"Construction",
            "type":"Services"
        }
    ],
    "sg:phone":"+1 707 458 3676",
    "sg:postcode":"95531",
    "sg:province":"CA",
    "sg:tags":[
        "house",
        "contractor"
    ],
    "wof:name":"Don Hartley Construction",
    "wof:placetype":"venue"
},
  "geometry": {"coordinates":[-124.102726,41.843701],"type":"Point"}
}