{
  "type": "Feature",
  "properties": {
    "addr:full":"2720 Gateway Oaks Drive Sacramento CA 95833",
    "addr:housenumber":"2720",
    "addr:postcode":"95833",
    "addr:street":"Gateway Oaks Drive",
    "iso:country":"US",
    "sg:address":"2720 Gateway Oaks Drive",
    "sg:city":"Sacramento",
    "sg:classifiers":[
        {
            "category":"Restaurant",
            "type":"Food & Drink"
        },
        {
            "category":"Deli",
            "type":"Food & Drink"
        },
        {
            "category":"Food & Beverages",
            "subcategory":"Bakery",
            "type":"Retail Goods"
        },
        {
            "category":"Coffee & Tea",
            "type":"Food & Drink"
        }
    ],
    "sg:phone":"+1 916 921 2489",
    "sg:postcode":"95833",
    "sg:province":"CA",
    "sg:tags":[
        "delicatessen",
        "sandwich",
        "espresso"
    ],
    "wof:name":"City Cafe'",
    "wof:placetype":"venue"
},
  "geometry": {"coordinates":[-121.51752,38.616479],"type":"Point"}
}