{
  "type": "Feature",
  "properties": {
    "iso:country":"US",
    "sg:address":"39761 Anza Trl W",
    "sg:city":"Anza",
    "sg:classifiers":[
        {
            "category":"Professional",
            "subcategory":"Detective & Security Services",
            "type":"Services"
        }
    ],
    "sg:phone":"+1 951 541 7976",
    "sg:postcode":"92539",
    "sg:province":"CA",
    "sg:tags":[
        "information",
        "bureau"
    ],
    "wof:name":"Whitegon, Drywall",
    "wof:placetype":"venue"
},
  "geometry": {"coordinates":[-116.721515,33.544334],"type":"Point"}
}