{
  "type": "Feature",
  "properties": {
    "iso:country":"US",
    "sg:address":"7454 Pine Blvd",
    "sg:city":"Pine Valley",
    "sg:classifiers":[
        {
            "category":"Education",
            "subcategory":"School",
            "type":"Public Place"
        }
    ],
    "sg:phone":"+1 619 473 8693",
    "sg:postcode":"91962",
    "sg:province":"CA",
    "wof:name":"Pine Valley Elementary School",
    "wof:placetype":"venue"
},
  "geometry": {"coordinates":[-116.525356,32.819771],"type":"Point"}
}