{
  "type": "Feature",
  "properties": {
    "addr:full":"75 Cristich Ln Campbell CA 95008",
    "addr:housenumber":"75",
    "addr:postcode":"95008",
    "addr:street":"Cristich Ln",
    "iso:country":"US",
    "sg:address":"75 Cristich Ln",
    "sg:city":"Campbell",
    "sg:classifiers":[
        {
            "category":"Building & Trades",
            "subcategory":"Pest Control",
            "type":"Services"
        }
    ],
    "sg:phone":"+1 408 262 3273",
    "sg:postcode":"95008",
    "sg:province":"CA",
    "sg:website":"www.a-propestcontrol.com",
    "wof:name":"A-Pro Pest Control Inc",
    "wof:placetype":"venue"
},
  "geometry": {"coordinates":[-121.945066,37.277191],"type":"Point"}
}