{
  "type": "Feature",
  "properties": {
    "iso:country":"US",
    "sg:address":"11343 La Mirada Blvd",
    "sg:city":"Whittier",
    "sg:classifiers":[
        {
            "category":"Restaurant",
            "type":"Food & Drink"
        }
    ],
    "sg:phone":"+1 562 633 3793",
    "sg:postcode":"90604",
    "sg:province":"CA",
    "sg:tags":[
        "pizza"
    ],
    "sg:website":"www.3alarmpizza.com",
    "wof:name":"3-Alarm Pizza Dept Headquarters",
    "wof:placetype":"venue"
},
  "geometry": {"coordinates":[-118.012001,33.928101],"type":"Point"}
}