{
  "type": "Feature",
  "properties": {
    "addr:full":"5201 Linda Vista Rd San Diego CA 92110",
    "addr:housenumber":"5201",
    "addr:postcode":"92110",
    "addr:street":"Linda Vista Rd",
    "iso:country":"US",
    "sg:address":"5201 Linda Vista Rd",
    "sg:city":"San Diego",
    "sg:classifiers":[
        {
            "category":"Sports & Exercise",
            "subcategory":"Gym",
            "type":"Entertainment"
        }
    ],
    "sg:phone":"+1 619 293 7678",
    "sg:postcode":"92110",
    "sg:province":"CA",
    "sg:tags":[
        "club",
        "health",
        "studio",
        "gymnasium"
    ],
    "wof:name":"Curves For Women",
    "wof:placetype":"venue"
},
  "geometry": {"coordinates":[-117.196341,32.766035],"type":"Point"}
}