{
  "type": "Feature",
  "properties": {
    "addr:full":"9574 Stone Oak Ct Salinas CA 93907",
    "addr:housenumber":"9574",
    "addr:postcode":"93907",
    "addr:street":"Stone Oak Ct",
    "iso:country":"US",
    "sg:address":"9574 Stone Oak Ct",
    "sg:city":"Salinas",
    "sg:classifiers":[
        {
            "category":"Shopping",
            "subcategory":"Antiques",
            "type":"Retail Goods"
        }
    ],
    "sg:phone":"+1 831 632 0965",
    "sg:postcode":"93907",
    "sg:province":"CA",
    "wof:name":"Bluebird Antiques & Collectables",
    "wof:placetype":"venue"
},
  "geometry": {"coordinates":[-121.71491,36.777492],"type":"Point"}
}