{
  "type": "Feature",
  "properties": {
    "addr:full":"19620 Ave 152 Porterville CA 93257",
    "addr:housenumber":"19620",
    "addr:postcode":"93257",
    "addr:street":"Ave 152",
    "iso:country":"US",
    "sg:address":"19620 Ave 152",
    "sg:city":"Porterville",
    "sg:classifiers":[
        {
            "category":"Farming",
            "subcategory":"Orchard",
            "type":"Manufacturing & Wholesale Goods"
        },
        {
            "category":"Farming",
            "subcategory":"Farm",
            "type":"Manufacturing & Wholesale Goods"
        }
    ],
    "sg:phone":"+1 559 781 4142",
    "sg:postcode":"93257",
    "sg:province":"CA",
    "wof:name":"Green Leaf Farms Inc",
    "wof:placetype":"venue"
},
  "geometry": {"coordinates":[-119.133864,36.065931],"type":"Point"}
}