{
  "type": "Feature",
  "properties": {
    "addr:full":"2508 Channing Way Berkeley CA 94704",
    "addr:housenumber":"2508",
    "addr:postcode":"94704",
    "addr:street":"Channing Way",
    "iso:country":"US",
    "sg:address":"2508 Channing Way",
    "sg:city":"Berkeley",
    "sg:classifiers":[
        {
            "category":"Food & Beverages",
            "subcategory":"Fruits & Vegetables",
            "type":"Retail Goods"
        }
    ],
    "sg:phone":"+1 510 644 3727",
    "sg:postcode":"94704",
    "sg:province":"CA",
    "sg:tags":[
        "herb"
    ],
    "wof:name":"The Happy High Herbs Shop",
    "wof:placetype":"venue"
},
  "geometry": {"coordinates":[-122.258301,37.86697],"type":"Point"}
}