{
  "type": "Feature",
  "properties": {
    "iso:country":"US",
    "sg:address":"4327 Gage Ave",
    "sg:city":"Bell",
    "sg:classifiers":[
        {
            "category":"Health Services",
            "subcategory":"Optometrist",
            "type":"Services"
        }
    ],
    "sg:phone":"+1 323 771 7477",
    "sg:postcode":"90201",
    "sg:province":"CA",
    "wof:name":"Vision Plus Optometry Center",
    "wof:placetype":"venue"
},
  "geometry": {"coordinates":[-118.190002,33.9785],"type":"Point"}
}