{
  "type": "Feature",
  "properties": {
    "addr:full":"4327 Gage Ave Bell CA 90201",
    "addr:housenumber":"4327",
    "addr:postcode":"90201",
    "addr:street":"Gage Ave",
    "iso:country":"US",
    "sg:address":"4327 Gage Ave",
    "sg:city":"Bell",
    "sg:classifiers":[
        {
            "category":"Health Services",
            "subcategory":"Optometrist",
            "type":"Services"
        }
    ],
    "sg:phone":"+1 323 771 7477",
    "sg:postcode":"90201",
    "sg:province":"CA",
    "wof:name":"Vision Plus Optometry Center",
    "wof:placetype":"venue"
},
  "geometry": {"coordinates":[-118.19000200000001,33.9785],"type":"Point"}
}