{
  "type": "Feature",
  "properties": {
    "addr:full":"144 N Claremont St San Mateo CA 94401",
    "addr:housenumber":"144",
    "addr:postcode":"94401",
    "addr:street":"N Claremont St",
    "iso:country":"US",
    "sg:address":"144 N Claremont St",
    "sg:city":"San Mateo",
    "sg:classifiers":[
        {
            "category":"Health Services",
            "subcategory":"Health Practitioner",
            "type":"Services"
        }
    ],
    "sg:phone":"+1 650 367 6049",
    "sg:postcode":"94401",
    "sg:province":"CA",
    "sg:tags":[
        "psychotherapist"
    ],
    "wof:name":"Alexandra Joulibert",
    "wof:placetype":"venue"
},
  "geometry": {"coordinates":[-122.32584900000001,37.571244],"type":"Point"}
}