{
  "type": "Feature",
  "properties": {
    "iso:country":"US",
    "sg:address":"6005 Lewis Ave",
    "sg:city":"Atascadero",
    "sg:classifiers":[
        {
            "category":"Government",
            "subcategory":"Fire Station",
            "type":"Public Place"
        }
    ],
    "sg:phone":"+1 805 461 5070",
    "sg:postcode":"93422",
    "sg:province":"CA",
    "sg:tags":[
        "department",
        "dept"
    ],
    "sg:website":"www.atascadero.org",
    "wof:name":"City Atascadero Fire Dept",
    "wof:placetype":"venue"
},
  "geometry": {"coordinates":[-120.669094,35.491279],"type":"Point"}
}