{
  "type": "Feature",
  "properties": {
    "addr:full":"8828 Complex Dr San Diego CA 92123",
    "addr:housenumber":"8828",
    "addr:postcode":"92123",
    "addr:street":"Complex Dr",
    "iso:country":"US",
    "sg:address":"8828 Complex Dr",
    "sg:city":"San Diego",
    "sg:classifiers":[
        {
            "category":"Home & Garden",
            "subcategory":"Carpets & Floor Coverings",
            "type":"Retail Goods"
        }
    ],
    "sg:phone":"+1 858 292 2575",
    "sg:postcode":"92123",
    "sg:province":"CA",
    "sg:tags":[
        "dealer",
        "rug"
    ],
    "wof:name":"DFS Flooring",
    "wof:placetype":"venue"
},
  "geometry": {"coordinates":[-117.136071,32.830094],"type":"Point"}
}