{
  "type": "Feature",
  "properties": {
    "iso:country":"US",
    "sg:address":"1973 N Palm Canyon Dr",
    "sg:city":"Palm Springs",
    "sg:classifiers":[
        {
            "category":"Restaurant",
            "type":"Food & Drink"
        }
    ],
    "sg:phone":"+1 760 416 0090",
    "sg:postcode":"92262",
    "sg:province":"CA",
    "sg:tags":[
        "diner"
    ],
    "wof:name":"Rick's Restaurant & Bakery",
    "wof:placetype":"venue"
},
  "geometry": {"coordinates":[-116.547997,33.847801],"type":"Point"}
}