{
  "type": "Feature",
  "properties": {
    "addr:full":"1119 Huntington St Huntington Beach CA 92648",
    "addr:housenumber":"1119",
    "addr:postcode":"92648",
    "addr:street":"Huntington St",
    "iso:country":"US",
    "sg:address":"1119 Huntington St",
    "sg:city":"Huntington Beach",
    "sg:classifiers":[
        {
            "category":"Professional",
            "type":"Services"
        }
    ],
    "sg:phone":"+1 714 342 5192",
    "sg:postcode":"92648",
    "sg:province":"CA",
    "sg:tags":[
        "establishment"
    ],
    "wof:name":"Angel In Waiting",
    "wof:placetype":"venue"
},
  "geometry": {"coordinates":[-117.995152,33.667423],"type":"Point"}
}