{
  "type": "Feature",
  "properties": {
    "addr:full":"8669 Research Dr Irvine CA 92618",
    "addr:housenumber":"8669",
    "addr:postcode":"92618",
    "addr:street":"Research Dr",
    "iso:country":"US",
    "sg:address":"8669 Research Dr",
    "sg:city":"Irvine",
    "sg:classifiers":[
        {
            "category":"Park",
            "type":"Public Place"
        }
    ],
    "sg:phone":"+1 949 450 0014",
    "sg:postcode":"92618",
    "sg:province":"CA",
    "wof:name":"Parks America",
    "wof:placetype":"venue"
},
  "geometry": {"coordinates":[-117.742155,33.64491],"type":"Point"}
}