{
  "type": "Feature",
  "properties": {
    "iso:country":"US",
    "sg:address":"8853 Hollywood Blvd",
    "sg:city":"West Hollywood",
    "sg:classifiers":[
        {
            "category":"Shopping",
            "subcategory":"Books",
            "type":"Retail Goods"
        }
    ],
    "sg:phone":"+1 310 659 6443",
    "sg:postcode":"90069",
    "sg:province":"CA",
    "sg:tags":[
        "dealer"
    ],
    "sg:website":"www.adifferentlightbooks.com",
    "wof:name":"Androgyny Books",
    "wof:placetype":"venue"
},
  "geometry": {"coordinates":[-118.379407,34.099809],"type":"Point"}
}