{
  "type": "Feature",
  "properties": {
    "addr:full":"1403 Montana Ave Santa Monica CA 90403",
    "addr:housenumber":"1403",
    "addr:postcode":"90403",
    "addr:street":"Montana Ave",
    "iso:country":"US",
    "sg:address":"1403 Montana Ave",
    "sg:city":"Santa Monica",
    "sg:classifiers":[
        {
            "category":"Shopping",
            "subcategory":"Clothing, Apparel, & Fashions",
            "type":"Retail Goods"
        }
    ],
    "sg:phone":"+1 310 576 4711",
    "sg:postcode":"90403",
    "sg:province":"CA",
    "wof:name":"M'Attias",
    "wof:placetype":"venue"
},
  "geometry": {"coordinates":[-118.494753,34.032624],"type":"Point"}
}