{
  "type": "Feature",
  "properties": {
    "iso:country":"US",
    "sg:address":"906 Boardwalk",
    "sg:city":"San Marcos",
    "sg:classifiers":[
        {
            "category":"Manufacturing",
            "subcategory":"Tools & Machinery",
            "type":"Manufacturing & Wholesale Goods"
        }
    ],
    "sg:phone":"+1 760 744 5083",
    "sg:postcode":"92078",
    "sg:province":"CA",
    "sg:tags":[
        "chiller"
    ],
    "sg:website":"www.hydromiser.com",
    "wof:name":"Applied Thermal Technologies",
    "wof:placetype":"venue"
},
  "geometry": {"coordinates":[-117.186199,33.136673],"type":"Point"}
}