{
  "type": "Feature",
  "properties": {
    "iso:country":"US",
    "sg:address":"10212 Rose Ave",
    "sg:city":"Montclair",
    "sg:classifiers":[
        {
            "category":"Utilities",
            "subcategory":"Refuse",
            "type":"Services"
        }
    ],
    "sg:phone":"+1 909 964 5328",
    "sg:postcode":"91763",
    "sg:province":"CA",
    "sg:tags":[
        "recycling",
        "material",
        "waste",
        "salvage"
    ],
    "wof:name":"Sandeez Salvage Inc",
    "wof:placetype":"venue"
},
  "geometry": {"coordinates":[-117.688517,34.067651],"type":"Point"}
}