{
  "type": "Feature",
  "properties": {
    "iso:country":"US",
    "sg:address":"27 Laguna Seca Ct",
    "sg:city":"St Helena",
    "sg:classifiers":[
        {
            "category":"Wholesale",
            "subcategory":"Groceries",
            "type":"Manufacturing & Wholesale Goods"
        }
    ],
    "sg:phone":"+1 707 967 8900",
    "sg:postcode":"94574",
    "sg:province":"CA",
    "sg:tags":[
        "food",
        "broker",
        "general"
    ],
    "wof:name":"Miller Sales & Marketing",
    "wof:placetype":"venue"
},
  "geometry": {"coordinates":[-122.460104,38.513789],"type":"Point"}
}