{
  "type": "Feature",
  "properties": {
    "iso:country":"US",
    "sg:address":"7643 Firestone Blvd",
    "sg:city":"Downey",
    "sg:classifiers":[
        {
            "category":"Bars & Pubs",
            "subcategory":"Nightclub",
            "type":"Food & Drink"
        }
    ],
    "sg:phone":"+1 562 928 5503",
    "sg:postcode":"90241",
    "sg:province":"CA",
    "sg:tags":[
        "nightlife"
    ],
    "wof:name":"Stardust Club the",
    "wof:placetype":"venue"
},
  "geometry": {"coordinates":[-118.143997,33.946098],"type":"Point"}
}