{
  "type": "Feature",
  "properties": {
    "iso:country":"US",
    "sg:address":"740 Paradiso Ct",
    "sg:city":"Soquel",
    "sg:classifiers":[
        {
            "category":"Banks & Credit Unions",
            "subcategory":"Financial Services",
            "type":"Services"
        }
    ],
    "sg:phone":"+1 408 229 9481",
    "sg:postcode":"95073",
    "sg:province":"CA",
    "sg:tags":[
        "broker",
        "mortgage"
    ],
    "sg:website":"www.linkedin.com/in/thehomeloanc...",
    "wof:name":"Home Loan Center the Dan Findrick",
    "wof:placetype":"venue"
},
  "geometry": {"coordinates":[-121.95634699999999,36.998632],"type":"Point"}
}