{
  "type": "Feature",
  "properties": {
    "addr:full":"2012 Bryant St San Francisco CA 94110",
    "addr:housenumber":"2012",
    "addr:postcode":"94110",
    "addr:street":"Bryant St",
    "iso:country":"US",
    "sg:address":"2012 Bryant St",
    "sg:city":"San Francisco",
    "sg:classifiers":[
        {
            "category":"Manufacturing",
            "subcategory":"Metals",
            "type":"Manufacturing & Wholesale Goods"
        }
    ],
    "sg:phone":"+1 415 282 1022",
    "sg:postcode":"94110",
    "sg:province":"CA",
    "sg:tags":[
        "ornamental",
        "work"
    ],
    "wof:name":"Security Service Iron Works",
    "wof:placetype":"venue"
},
  "geometry": {"coordinates":[-122.410084,37.760635],"type":"Point"}
}