{
  "type": "Feature",
  "properties": {
    "iso:country":"US",
    "sg:address":"5691 Telegraph Ave",
    "sg:city":"Oakland",
    "sg:classifiers":[
        {
            "category":"Personal",
            "subcategory":"Beauty Salon",
            "type":"Services"
        }
    ],
    "sg:phone":"+1 510 547 6364",
    "sg:postcode":"94609",
    "sg:province":"CA",
    "wof:name":"Barbara Hennessey Hair Design",
    "wof:placetype":"venue"
},
  "geometry": {"coordinates":[-122.261845,37.841975],"type":"Point"}
}