{
  "type": "Feature",
  "properties": {
    "addr:full":"14829 Hawthorne Blvd Lawndale CA 90260",
    "addr:housenumber":"14829",
    "addr:postcode":"ca 90260",
    "addr:street":"Hawthorne Blvd",
    "iso:country":"US",
    "sg:address":"14829 Hawthorne Blvd",
    "sg:city":"Lawndale",
    "sg:classifiers":[
        {
            "category":"Professional",
            "subcategory":"Accounting & Tax Preparation",
            "type":"Services"
        }
    ],
    "sg:phone":"+1 310 978 0567",
    "sg:postcode":"90260",
    "sg:province":"CA",
    "sg:tags":[
        "accountant",
        "bookkeeping"
    ],
    "wof:name":"A Plus Accounting & Text Svc",
    "wof:placetype":"venue"
},
  "geometry": {"coordinates":[-118.352997,33.897099],"type":"Point"}
}