{
  "type": "Feature",
  "properties": {
    "iso:country":"US",
    "sg:address":"21893 Barton Rd",
    "sg:city":"Grand Terrace",
    "sg:classifiers":[
        {
            "category":"Home & Garden",
            "subcategory":"Garden Supply",
            "type":"Retail Goods"
        }
    ],
    "sg:phone":"+1 909 783 2099",
    "sg:postcode":"92313",
    "sg:province":"CA",
    "sg:tags":[
        "lawn",
        "mower"
    ],
    "wof:name":"John's Lawn Mower Shop",
    "wof:placetype":"venue"
},
  "geometry": {"coordinates":[-117.325913,34.033887],"type":"Point"}
}