{
  "type": "Feature",
  "properties": {
    "addr:full":"1284 Forest Creek Dr Hollister CA 95023",
    "addr:housenumber":"1284",
    "addr:postcode":"hollister ca 95023",
    "addr:street":"Forest Creek Dr",
    "iso:country":"US",
    "sg:address":"1284 Forest Creek Dr",
    "sg:city":"Hollister",
    "sg:classifiers":[
        {
            "category":"Manufacturing",
            "subcategory":"Wood Products",
            "type":"Manufacturing & Wholesale Goods"
        }
    ],
    "sg:phone":"+1 831 635 0133",
    "sg:postcode":"95023",
    "sg:province":"CA",
    "sg:tags":[
        "mfg"
    ],
    "wof:name":"Pallet Exchange",
    "wof:placetype":"venue"
},
  "geometry": {"coordinates":[-121.381084,36.841127],"type":"Point"}
}