{
  "type": "Feature",
  "properties": {
    "addr:full":"6425 Hollywood Blvd Los Angeles CA 90028",
    "addr:housenumber":"6425",
    "addr:postcode":"90028",
    "addr:street":"Hollywood Blvd",
    "iso:country":"US",
    "sg:address":"6425 Hollywood Blvd",
    "sg:city":"Los Angeles",
    "sg:classifiers":[
        {
            "category":"Arts & Performance",
            "subcategory":"Theater",
            "type":"Entertainment"
        },
        {
            "category":"Wholesale",
            "subcategory":"Photographic Equipment",
            "type":"Manufacturing & Wholesale Goods"
        }
    ],
    "sg:phone":"+1 323 464 6790",
    "sg:postcode":"90028",
    "sg:province":"CA",
    "sg:tags":[
        "motion",
        "picture",
        "group",
        "supply"
    ],
    "wof:name":"Rydt Entertainment Systems Inc",
    "wof:placetype":"venue"
},
  "geometry": {"coordinates":[-118.330733,34.101671],"type":"Point"}
}