{
  "type": "Feature",
  "properties": {
    "addr:full":"1839 N E St San Bernardino CA 92405",
    "addr:housenumber":"1839",
    "addr:postcode":"92405",
    "addr:street":"N E St",
    "iso:country":"US",
    "sg:address":"1839 N E St",
    "sg:city":"San Bernardino",
    "sg:classifiers":[
        {
            "category":"Shopping",
            "subcategory":"Hobbies, Toys, & Games",
            "type":"Retail Goods"
        }
    ],
    "sg:phone":"+1 909 762 2425",
    "sg:postcode":"92405",
    "sg:province":"CA",
    "wof:name":"J S Hobbies",
    "wof:placetype":"venue"
},
  "geometry": {"coordinates":[-117.294107,34.131957],"type":"Point"}
}