{
  "type": "Feature",
  "properties": {
    "addr:full":"1145 San Julian St Los Angeles CA 90015",
    "addr:housenumber":"1145",
    "addr:postcode":"90015",
    "addr:street":"San Julian St",
    "iso:country":"US",
    "sg:address":"1145 San Julian St",
    "sg:city":"Los Angeles",
    "sg:classifiers":[
        {
            "category":"Manufacturing",
            "subcategory":"Retail Goods",
            "type":"Manufacturing & Wholesale Goods"
        }
    ],
    "sg:phone":"+1 213 747 7132",
    "sg:postcode":"90015",
    "sg:province":"CA",
    "sg:tags":[
        "manufacturer"
    ],
    "wof:name":"Durian Industry Hawaii In",
    "wof:placetype":"venue"
},
  "geometry": {"coordinates":[-118.253961,34.035075],"type":"Point"}
}