{
  "type": "Feature",
  "properties": {
    "addr:full":"1500 W El Camino Ave #219 Sacramento CA 95833",
    "addr:housenumber":"1500",
    "addr:postcode":"95833",
    "addr:street":"W El Camino Ave # 219",
    "iso:country":"US",
    "sg:address":"1500 W El Camino Ave #219",
    "sg:city":"Sacramento",
    "sg:classifiers":[
        {
            "category":"Professional",
            "type":"Services"
        }
    ],
    "sg:phone":"+1 916 856 6607",
    "sg:postcode":"95833",
    "sg:province":"CA",
    "sg:tags":[
        "caterer"
    ],
    "sg:website":"www.estheradeborahcatering.com",
    "wof:name":"Esther A. Deborah Delicacies & Catering",
    "wof:placetype":"venue"
},
  "geometry": {"coordinates":[-121.49539,38.612873],"type":"Point"}
}