{
  "type": "Feature",
  "properties": {
    "addr:full":"5410 Ave 384 Dinuba CA 93618",
    "addr:housenumber":"5410",
    "addr:postcode":"93618",
    "addr:street":"Ave 384",
    "iso:country":"US",
    "sg:address":"5410 Ave 384",
    "sg:city":"Dinuba",
    "sg:classifiers":[
        {
            "category":"Farming",
            "subcategory":"Farm",
            "type":"Manufacturing & Wholesale Goods"
        }
    ],
    "sg:phone":"+1 559 897 4632",
    "sg:postcode":"93618",
    "sg:province":"CA",
    "wof:name":"Top Soil Farms",
    "wof:placetype":"venue"
},
  "geometry": {"coordinates":[-119.453086,36.488537],"type":"Point"}
}