{
  "type": "Feature",
  "properties": {
    "iso:country":"US",
    "sg:address":"2187 Garfield Ave",
    "sg:city":"Los Angeles",
    "sg:classifiers":[
        {
            "category":"Banks & Credit Unions",
            "subcategory":"Investment Brokerage",
            "type":"Services"
        }
    ],
    "sg:phone":"+1 323 726 7220",
    "sg:postcode":"90040",
    "sg:province":"CA",
    "sg:tags":[
        "advisory",
        "financial"
    ],
    "wof:name":"United Commercial Credit",
    "wof:placetype":"venue"
},
  "geometry": {"coordinates":[-118.131315,34.005396],"type":"Point"}
}