{
  "type": "Feature",
  "properties": {
    "addr:full":"1500 Fashion Island Blvd Suite 103 San Mateo CA 94404",
    "addr:housenumber":"1500",
    "addr:postcode":"94404",
    "addr:street":"Fashion Island Blvd Suite 103",
    "iso:country":"US",
    "sg:address":"1500 Fashion Island Blvd Suite 103",
    "sg:city":"San Mateo",
    "sg:classifiers":[
        {
            "category":"Professional",
            "subcategory":"Computer Services",
            "type":"Services"
        }
    ],
    "sg:phone":"+1 800 695 6021",
    "sg:postcode":"94404",
    "sg:province":"CA",
    "sg:website":"http://www.ucirrus.com/",
    "wof:name":"uCirrus",
    "wof:placetype":"venue"
},
  "geometry": {"coordinates":[-122.287153,37.557832],"type":"Point"}
}