{
  "type": "Feature",
  "properties": {
    "addr:full":"24546 Hawthorne Blvd Torrance CA 90505",
    "addr:housenumber":"24546",
    "addr:postcode":"90505",
    "addr:street":"Hawthorne Blvd",
    "iso:country":"US",
    "sg:address":"24546 Hawthorne Blvd",
    "sg:city":"Torrance",
    "sg:classifiers":[
        {
            "category":"Food & Beverages",
            "subcategory":"Bakery",
            "type":"Retail Goods"
        }
    ],
    "sg:phone":"+1 310 373 1185",
    "sg:postcode":"90505",
    "sg:province":"CA",
    "sg:tags":[
        "baker"
    ],
    "wof:name":"Bridal Sweets",
    "wof:placetype":"venue"
},
  "geometry": {"coordinates":[-118.35085599999999,33.79861],"type":"Point"}
}