{
  "type": "Feature",
  "properties": {
    "iso:country":"US",
    "sg:address":"618 S Mansfield Ave",
    "sg:city":"Los Angeles",
    "sg:classifiers":[
        {
            "category":"Building & Trades",
            "subcategory":"Plumbing",
            "type":"Services"
        }
    ],
    "sg:phone":"+1 323 937 7920",
    "sg:postcode":"90036",
    "sg:province":"CA",
    "sg:tags":[
        "product",
        "management",
        "energy",
        "system"
    ],
    "wof:name":"Virtual Energy",
    "wof:placetype":"venue"
},
  "geometry": {"coordinates":[-118.340684,34.063361],"type":"Point"}
}