{
  "type": "Feature",
  "properties": {
    "addr:full":"1401 E Santa Clara St San Jose CA 95116",
    "addr:housenumber":"1401",
    "addr:postcode":"95116",
    "addr:street":"E Santa Clara St",
    "iso:country":"US",
    "sg:address":"1401 E Santa Clara St",
    "sg:city":"San Jose",
    "sg:classifiers":[
        {
            "category":"Recreation",
            "type":"Entertainment"
        }
    ],
    "sg:phone":"+1 408 294 6343",
    "sg:postcode":"95116",
    "sg:province":"CA",
    "sg:tags":[
        "space",
        "venue",
        "event",
        "hall",
        "auditorium"
    ],
    "wof:name":"Ies Hall",
    "wof:placetype":"venue"
},
  "geometry": {"coordinates":[-121.862999,37.349201],"type":"Point"}
}