{
  "type": "Feature",
  "properties": {
    "addr:full":"25056 Oakana Rd Ramona CA 92065",
    "addr:housenumber":"25056",
    "addr:postcode":"92065",
    "addr:street":"Oakana Rd",
    "iso:country":"US",
    "sg:address":"25056 Oakana Rd",
    "sg:city":"Ramona",
    "sg:classifiers":[
        {
            "category":"Utilities",
            "subcategory":"Electric",
            "type":"Services"
        },
        {
            "category":"Manufacturing",
            "subcategory":"Electronics",
            "type":"Manufacturing & Wholesale Goods"
        }
    ],
    "sg:phone":"+1 760 788 3258",
    "sg:postcode":"92065",
    "sg:province":"CA",
    "sg:tags":[
        "equipment-testing"
    ],
    "wof:name":"Maximus Supply Corp",
    "wof:placetype":"venue"
},
  "geometry": {"coordinates":[-116.790449,33.069049],"type":"Point"}
}