{
  "type": "Feature",
  "properties": {
    "addr:full":"2281 Las Palmas Dr Carlsbad CA 92009",
    "addr:housenumber":"2281",
    "addr:postcode":"92009",
    "addr:street":"Las Palmas Dr",
    "iso:country":"US",
    "sg:address":"2281 Las Palmas Dr",
    "sg:city":"Carlsbad",
    "sg:classifiers":[
        {
            "category":"Manufacturing",
            "subcategory":"Tools & Machinery",
            "type":"Manufacturing & Wholesale Goods"
        }
    ],
    "sg:phone":"+1 760 603 0631",
    "sg:postcode":"92009",
    "sg:province":"CA",
    "sg:tags":[
        "test",
        "equipment",
        "electric",
        "mfg"
    ],
    "wof:name":"Mpi",
    "wof:placetype":"venue"
},
  "geometry": {"coordinates":[-117.277102,33.117807],"type":"Point"}
}