{
  "type": "Feature",
  "properties": {
    "addr:full":"1414 Garnet Avenue San Diego CA 92109",
    "addr:housenumber":"1414",
    "addr:postcode":"92109",
    "addr:street":"Garnet Avenue",
    "iso:country":"US",
    "sg:address":"1414 Garnet Avenue",
    "sg:city":"San Diego",
    "sg:classifiers":[
        {
            "category":"Personal",
            "subcategory":"Beauty Salon",
            "type":"Services"
        }
    ],
    "sg:phone":"+1 858 490 1154",
    "sg:postcode":"92109",
    "sg:province":"CA",
    "sg:tags":[
        "spa"
    ],
    "sg:website":"ipsbmassagetherapy.com",
    "wof:name":"IPSB Massage Therapy Center",
    "wof:placetype":"venue"
},
  "geometry": {"coordinates":[-117.244203,32.799061],"type":"Point"}
}