{
  "type": "Feature",
  "properties": {
    "iso:country":"US",
    "sg:address":"4515 Vis Largo",
    "sg:city":"Torrance",
    "sg:classifiers":[
        {
            "category":"Manufacturing",
            "subcategory":"Toys & Sporting Goods",
            "type":"Manufacturing & Wholesale Goods"
        }
    ],
    "sg:phone":"+1 310 375 0039",
    "sg:postcode":"90505",
    "sg:province":"CA",
    "sg:tags":[
        "mfg"
    ],
    "wof:name":"Wisenet International Inc",
    "wof:placetype":"venue"
},
  "geometry": {"coordinates":[-118.360421,33.805763],"type":"Point"}
}