{
  "type": "Feature",
  "properties": {
    "addr:full":"2229 Lake Tahoe Blvd South Lake Tahoe CA 96150",
    "addr:housenumber":"2229",
    "addr:postcode":"96150",
    "addr:street":"Lake Tahoe Blvd",
    "iso:country":"US",
    "sg:address":"2229 Lake Tahoe Blvd",
    "sg:city":"South Lake Tahoe",
    "sg:classifiers":[
        {
            "category":"Personal",
            "subcategory":"Beauty Salon",
            "type":"Services"
        }
    ],
    "sg:phone":"+1 530 541 5501",
    "sg:postcode":"96150",
    "sg:province":"CA",
    "wof:name":"Tahoe Pam",
    "wof:placetype":"venue"
},
  "geometry": {"coordinates":[-119.99620400000001,38.918781],"type":"Point"}
}