{
  "type": "Feature",
  "properties": {
    "iso:country":"US",
    "sg:address":"7383 Beverly Blvd",
    "sg:city":"Los Angeles",
    "sg:classifiers":[
        {
            "category":"Shopping",
            "subcategory":"Clothing, Apparel, & Fashions",
            "type":"Retail Goods"
        },
        {
            "category":"Personal",
            "type":"Services"
        }
    ],
    "sg:phone":"+1 323 964 0080",
    "sg:postcode":"90036",
    "sg:province":"CA",
    "sg:tags":[
        "men's",
        "sewing",
        "clothing",
        "alteration",
        "women's"
    ],
    "sg:website":"htcamerica.tumblr.com",
    "wof:name":"Denim Doctors & Hollywood Trading Company",
    "wof:placetype":"venue"
},
  "geometry": {"coordinates":[-118.350683,34.076161],"type":"Point"}
}