{
  "type": "Feature",
  "properties": {
    "addr:full":"1175 N Kraemer Blvd Anaheim CA 92806",
    "addr:housenumber":"1175",
    "addr:postcode":"92806",
    "addr:street":"N Kraemer Blvd",
    "iso:country":"US",
    "sg:address":"1175 N Kraemer Blvd",
    "sg:city":"Anaheim",
    "sg:classifiers":[
        {
            "category":"Manufacturing",
            "subcategory":"Printing",
            "type":"Manufacturing & Wholesale Goods"
        }
    ],
    "sg:phone":"+1 714 630 3737",
    "sg:postcode":"92806",
    "sg:province":"CA",
    "sg:tags":[
        "lithographic",
        "commercial"
    ],
    "wof:name":"Jrt Enterprises",
    "wof:placetype":"venue"
},
  "geometry": {"coordinates":[-117.85779599999999,33.851958],"type":"Point"}
}