{
  "type": "Feature",
  "properties": {
    "iso:country":"US",
    "sg:address":"200 W Main St",
    "sg:city":"Turlock",
    "sg:classifiers":[
        {
            "category":"Restaurant",
            "type":"Food & Drink"
        }
    ],
    "sg:phone":"+1 209 667 9209",
    "sg:postcode":"95380",
    "sg:province":"CA",
    "sg:tags":[
        "shop",
        "coffee"
    ],
    "sg:website":"www.epicentercafe.com",
    "wof:name":"Epicenter Cafe",
    "wof:placetype":"venue"
},
  "geometry": {"coordinates":[-120.84898699999999,37.492743],"type":"Point"}
}