{
  "type": "Feature",
  "properties": {
    "iso:country":"US",
    "sg:address":"1255 96th Ave",
    "sg:city":"Oakland",
    "sg:classifiers":[
        {
            "category":"Retail",
            "subcategory":"Auto Rental",
            "type":"Services"
        }
    ],
    "sg:phone":"+1 415 871 8486",
    "sg:postcode":"94603",
    "sg:province":"CA",
    "sg:tags":[
        "car"
    ],
    "wof:name":"Black Car Net, Inc.",
    "wof:placetype":"venue"
},
  "geometry": {"coordinates":[-122.174026,37.744614],"type":"Point"}
}