{
  "type": "Feature",
  "properties": {
    "iso:country":"US",
    "sg:address":"8048 W 3rd St",
    "sg:city":"Los Angeles",
    "sg:classifiers":[
        {
            "category":"Fast Food",
            "type":"Food & Drink"
        },
        {
            "category":"Bars & Pubs",
            "type":"Food & Drink"
        }
    ],
    "sg:phone":"+1 323 944 0503",
    "sg:postcode":"90048",
    "sg:province":"CA",
    "sg:tags":[
        "burger",
        "gastropubs"
    ],
    "sg:website":"burgerkitchenla.com/",
    "wof:name":"Burger Kitchen",
    "wof:placetype":"venue"
},
  "geometry": {"coordinates":[-118.36571,34.071813],"type":"Point"}
}