{
  "type": "Feature",
  "properties": {
    "addr:full":"1164 Willow Ave Sunnyvale CA 94086",
    "addr:housenumber":"1164",
    "addr:postcode":"94086",
    "addr:street":"Willow Ave",
    "iso:country":"US",
    "sg:address":"1164 Willow Ave",
    "sg:city":"Sunnyvale",
    "sg:classifiers":[
        {
            "category":"Wholesale",
            "subcategory":"Machinery & Supplies",
            "type":"Manufacturing & Wholesale Goods"
        }
    ],
    "sg:phone":"+1 408 261 2191",
    "sg:postcode":"94086",
    "sg:province":"CA",
    "sg:tags":[
        "sprinkler"
    ],
    "wof:name":"Adanac Fire Protection Inc",
    "wof:placetype":"venue"
},
  "geometry": {"coordinates":[-121.997235,37.368025],"type":"Point"}
}