{
  "type": "Feature",
  "properties": {
    "iso:country":"US",
    "sg:address":"2932 N Wolters Ave",
    "sg:city":"Fresno",
    "sg:classifiers":[
        {
            "category":"Building & Trades",
            "subcategory":"Construction",
            "type":"Services"
        }
    ],
    "sg:phone":"+1 559 226 6411",
    "sg:postcode":"93703",
    "sg:province":"CA",
    "sg:tags":[
        "pipeline",
        "engineer"
    ],
    "wof:name":"Pacific Engineers",
    "wof:placetype":"venue"
},
  "geometry": {"coordinates":[-119.760029,36.779277],"type":"Point"}
}