{
  "type": "Feature",
  "properties": {
    "iso:country":"US",
    "sg:address":"22635 Benner Ave",
    "sg:city":"Torrance",
    "sg:classifiers":[
        {
            "category":"Organizations",
            "subcategory":"Community Association",
            "type":"Services"
        }
    ],
    "sg:phone":"+1 310 326 2774",
    "sg:postcode":"90505",
    "sg:province":"CA",
    "sg:tags":[
        "environmental",
        "org"
    ],
    "wof:name":"Friends Of Madrona Marsh",
    "wof:placetype":"venue"
},
  "geometry": {"coordinates":[-118.33771,33.819951],"type":"Point"}
}