{
  "type": "Feature",
  "properties": {
    "addr:full":"4545 Elwood Ave Palmdale CA 93552",
    "addr:housenumber":"4545",
    "addr:postcode":"ca 93552",
    "addr:street":"Elwood Ave",
    "iso:country":"US",
    "sg:address":"4545 Elwood Ave",
    "sg:city":"Palmdale",
    "sg:classifiers":[
        {
            "category":"Real Estate",
            "subcategory":"Real Estate Agent",
            "type":"Services"
        }
    ],
    "sg:phone":"+1 661 285 4048",
    "sg:postcode":"93552",
    "sg:province":"CA",
    "sg:tags":[
        "investment"
    ],
    "wof:name":"Royce Financial",
    "wof:placetype":"venue"
},
  "geometry": {"coordinates":[-118.047506,34.565999],"type":"Point"}
}