{
  "type": "Feature",
  "properties": {
    "addr:full":"5609 Bradd Way Sacramento CA 95822",
    "addr:housenumber":"5609",
    "addr:postcode":"95822",
    "addr:street":"Bradd Way",
    "iso:country":"US",
    "sg:address":"5609 Bradd Way",
    "sg:city":"Sacramento",
    "sg:classifiers":[
        {
            "category":"Wholesale",
            "subcategory":"Vending Machines",
            "type":"Manufacturing & Wholesale Goods"
        }
    ],
    "sg:phone":"+1 916 428 2431",
    "sg:postcode":"95822",
    "sg:province":"CA",
    "sg:tags":[
        "merchandise"
    ],
    "wof:name":"Golden Chinchilla Vending Mach",
    "wof:placetype":"venue"
},
  "geometry": {"coordinates":[-121.490182,38.524534],"type":"Point"}
}