{
  "type": "Feature",
  "properties": {
    "addr:full":"780 E 9th St San Bernardino CA 92410",
    "addr:housenumber":"780",
    "addr:postcode":"92410",
    "addr:street":"E 9Th St",
    "iso:country":"US",
    "sg:address":"780 E 9th St",
    "sg:city":"San Bernardino",
    "sg:classifiers":[
        {
            "category":"Real Estate",
            "subcategory":"Real Estate Operator",
            "type":"Services"
        }
    ],
    "sg:phone":"+1 909 889 1314",
    "sg:postcode":"92410",
    "sg:province":"CA",
    "sg:tags":[
        "mobile",
        "home",
        "community"
    ],
    "wof:name":"Ninth Street Mobile Home Park",
    "wof:placetype":"venue"
},
  "geometry": {"coordinates":[-117.270759,34.115867],"type":"Point"}
}