{
  "type": "Feature",
  "properties": {
    "addr:full":"920 Samoa Blvd Arcata CA 95521",
    "addr:housenumber":"920",
    "addr:postcode":"95521",
    "addr:street":"Samoa Blvd",
    "iso:country":"US",
    "sg:address":"920 Samoa Blvd",
    "sg:city":"Arcata",
    "sg:classifiers":[
        {
            "category":"Personal",
            "type":"Services"
        }
    ],
    "sg:phone":"+1 707 822 6277",
    "sg:postcode":"95521",
    "sg:province":"CA",
    "sg:tags":[
        "therapist",
        "massage"
    ],
    "wof:name":"Abrina Massage Artist",
    "wof:placetype":"venue"
},
  "geometry": {"coordinates":[-124.090174,40.865631],"type":"Point"}
}