{
  "type": "Feature",
  "properties": {
    "iso:country":"US",
    "sg:address":"7956 Beverly Boulevard",
    "sg:city":"Los Angeles",
    "sg:classifiers":[
        {
            "category":"Shopping",
            "subcategory":"Antiques",
            "type":"Retail Goods"
        }
    ],
    "sg:phone":"+1 323 651 5082",
    "sg:postcode":"90048",
    "sg:province":"CA",
    "wof:name":"Modern One",
    "wof:placetype":"venue"
},
  "geometry": {"coordinates":[-118.363169,34.076211],"type":"Point"}
}