{
  "type": "Feature",
  "properties": {
    "addr:full":"1633 Broadway Ste B Oakland CA 94612",
    "addr:housenumber":"1633",
    "addr:postcode":"94612",
    "addr:street":"Broadway Ste B",
    "iso:country":"US",
    "sg:address":"1633 Broadway Ste B",
    "sg:city":"Oakland",
    "sg:classifiers":[
        {
            "category":"Shopping",
            "subcategory":"Clothing, Apparel, & Fashions",
            "type":"Retail Goods"
        }
    ],
    "sg:phone":"+1 510 355 5768",
    "sg:postcode":"94612",
    "sg:province":"CA",
    "sg:tags":[
        "tailor"
    ],
    "wof:name":"Rags Like Riches",
    "wof:placetype":"venue"
},
  "geometry": {"coordinates":[-122.270025,37.806194],"type":"Point"}
}