{
  "type": "Feature",
  "properties": {
    "iso:country":"US",
    "sg:address":"5556 Centinela Ave",
    "sg:city":"Los Angeles",
    "sg:classifiers":[
        {
            "category":"Transit Center",
            "subcategory":"Passenger",
            "type":"Transportation"
        }
    ],
    "sg:phone":"+1 877 600 5777",
    "sg:postcode":"90066",
    "sg:province":"CA",
    "sg:website":"www.calimoservice.com",
    "wof:name":"Superior Limousine and Transportation",
    "wof:placetype":"venue"
},
  "geometry": {"coordinates":[-118.40941,33.981941],"type":"Point"}
}