{
  "type": "Feature",
  "properties": {
    "addr:full":"11633 Louise Ave Lynwood CA 90262",
    "addr:housenumber":"11633",
    "addr:postcode":"90262",
    "addr:street":"Louise Ave",
    "iso:country":"US",
    "sg:address":"11633 Louise Ave",
    "sg:city":"Lynwood",
    "sg:classifiers":[
        {
            "category":"Building & Trades",
            "subcategory":"Construction",
            "type":"Services"
        }
    ],
    "sg:phone":"+1 310 764 0061",
    "sg:postcode":"90262",
    "sg:province":"CA",
    "sg:tags":[
        "sandblasting"
    ],
    "wof:name":"J B Powder Coating",
    "wof:placetype":"venue"
},
  "geometry": {"coordinates":[-118.181839,33.915656],"type":"Point"}
}