{
  "type": "Feature",
  "properties": {
    "iso:country":"US",
    "sg:address":"23331 Moulton Pkwy",
    "sg:city":"Laguna Hills",
    "sg:classifiers":[
        {
            "category":"Place Of Worship",
            "subcategory":"Church",
            "type":"Public Place"
        }
    ],
    "sg:postcode":"92653",
    "sg:province":"CA",
    "sg:website":"www.AccessFoundations.com",
    "wof:name":"Foundations Young Adults Ministry",
    "wof:placetype":"venue"
},
  "geometry": {"coordinates":[-117.732816,33.625135],"type":"Point"}
}