{
  "type": "Feature",
  "properties": {
    "iso:country":"US",
    "sg:address":"1764 E Vernon Ave",
    "sg:city":"Los Angeles",
    "sg:classifiers":[
        {
            "category":"Wholesale",
            "subcategory":"Construction Materials",
            "type":"Manufacturing & Wholesale Goods"
        }
    ],
    "sg:phone":"+1 323 231 5590",
    "sg:postcode":"90058",
    "sg:province":"CA",
    "wof:name":"Juval ACC & Win Tinting",
    "wof:placetype":"venue"
},
  "geometry": {"coordinates":[-118.243045,34.003917],"type":"Point"}
}