{
  "type": "Feature",
  "properties": {
    "addr:full":"43 Walnut Tree Dr Colusa CA 95932",
    "addr:housenumber":"43",
    "addr:postcode":"95932",
    "addr:street":"Walnut Tree Dr",
    "iso:country":"US",
    "sg:address":"43 Walnut Tree Dr",
    "sg:city":"Colusa",
    "sg:classifiers":[
        {
            "category":"Professional",
            "subcategory":"Management & Consulting",
            "type":"Services"
        }
    ],
    "sg:phone":"+1 530 458 3860",
    "sg:postcode":"95932",
    "sg:province":"CA",
    "sg:tags":[
        "consultant"
    ],
    "wof:name":"Xfloats",
    "wof:placetype":"venue"
},
  "geometry": {"coordinates":[-122.011816,39.190063],"type":"Point"}
}