{
  "type": "Feature",
  "properties": {
    "addr:full":"12045 Central Ave Chino CA 91710",
    "addr:postcode":"12045;91710",
    "addr:street":"Central Ave",
    "iso:country":"US",
    "sg:address":"12045 Central Ave",
    "sg:city":"Chino",
    "sg:classifiers":[
        {
            "category":"Personal",
            "subcategory":"Beauty Salon",
            "type":"Services"
        }
    ],
    "sg:phone":"+1 909 628 8545",
    "sg:postcode":"91710",
    "sg:province":"CA",
    "sg:tags":[
        "manicuring"
    ],
    "wof:name":"Crystal Nail",
    "wof:placetype":"venue"
},
  "geometry": {"coordinates":[-117.68951300000001,34.031553],"type":"Point"}
}