{
  "type": "Feature",
  "properties": {
    "iso:country":"US",
    "sg:address":"116 Coralie Way",
    "sg:city":"Folsom",
    "sg:classifiers":[
        {
            "category":"Education",
            "subcategory":"Special Training",
            "type":"Public Place"
        }
    ],
    "sg:phone":"+1 916 983 6131",
    "sg:postcode":"95630",
    "sg:province":"CA",
    "sg:tags":[
        "tutoring"
    ],
    "wof:name":"Edsberg's Private School",
    "wof:placetype":"venue"
},
  "geometry": {"coordinates":[-121.15877399999999,38.674015],"type":"Point"}
}