{
  "type": "Feature",
  "properties": {
    "iso:country":"US",
    "sg:address":"158 Stirling Dr",
    "sg:city":"Vacaville",
    "sg:classifiers":[
        {
            "category":"Insurance",
            "subcategory":"Hazard Insurance",
            "type":"Services"
        }
    ],
    "sg:phone":"+1 707 448 3214",
    "sg:postcode":"95687",
    "sg:province":"CA",
    "sg:tags":[
        "commercial",
        "business"
    ],
    "wof:name":"Forethought Insurance",
    "wof:placetype":"venue"
},
  "geometry": {"coordinates":[-121.949966,38.343161],"type":"Point"}
}