{
  "type": "Feature",
  "properties": {
    "addr:full":"2226 Vicente St San Francisco CA 94116",
    "addr:housenumber":"2226",
    "addr:postcode":"94116",
    "addr:street":"Vicente St",
    "iso:country":"US",
    "sg:address":"2226 Vicente St",
    "sg:city":"San Francisco",
    "sg:classifiers":[
        {
            "category":"Real Estate",
            "subcategory":"Real Estate Operator",
            "type":"Services"
        }
    ],
    "sg:phone":"+1 415 731 6494",
    "sg:postcode":"94116",
    "sg:province":"CA",
    "sg:tags":[
        "building",
        "apartment",
        "operates"
    ],
    "wof:name":"Whitney Arms Inc",
    "wof:placetype":"venue"
},
  "geometry": {"coordinates":[-122.491299,37.738702],"type":"Point"}
}