{
  "type": "Feature",
  "properties": {
    "addr:full":"2844 Niles St Bakersfield CA 93306",
    "addr:housenumber":"2844",
    "addr:postcode":"93306",
    "addr:street":"Niles St",
    "iso:country":"US",
    "sg:address":"2844 Niles St",
    "sg:city":"Bakersfield",
    "sg:classifiers":[
        {
            "category":"Personal",
            "subcategory":"Barber",
            "type":"Services"
        }
    ],
    "sg:phone":"+1 661 873 0512",
    "sg:postcode":"93306",
    "sg:province":"CA",
    "sg:tags":[
        "school"
    ],
    "wof:name":"Bakersfield Barber College",
    "wof:placetype":"venue"
},
  "geometry": {"coordinates":[-118.954947,35.375981],"type":"Point"}
}