{
  "type": "Feature",
  "properties": {
    "addr:full":"444 Blume St Nipomo CA 93444",
    "addr:housenumber":"444",
    "addr:postcode":"93444",
    "addr:street":"Blume St",
    "iso:country":"US",
    "sg:address":"444 Blume St",
    "sg:city":"Nipomo",
    "sg:classifiers":[
        {
            "category":"Building & Trades",
            "subcategory":"Landscaping Services",
            "type":"Services"
        }
    ],
    "sg:phone":"+1 805 929 9020",
    "sg:postcode":"93444",
    "sg:province":"CA",
    "sg:tags":[
        "consulting",
        "tree"
    ],
    "wof:name":"Carolyn Leach Consulting L L C",
    "wof:placetype":"venue"
},
  "geometry": {"coordinates":[-120.48359600000001,35.027612],"type":"Point"}
}