{
  "type": "Feature",
  "properties": {
    "iso:country":"US",
    "sg:address":"10601 Walker St",
    "sg:city":"Cypress",
    "sg:classifiers":[
        {
            "category":"Health Services",
            "subcategory":"Health Practitioner",
            "type":"Services"
        }
    ],
    "sg:phone":"+1 714 527 1674",
    "sg:postcode":"90630",
    "sg:province":"CA",
    "sg:tags":[
        "medicine",
        "alternative"
    ],
    "wof:name":"Cypress Center For Family Medicine",
    "wof:placetype":"venue"
},
  "geometry": {"coordinates":[-118.03695399999999,33.808659],"type":"Point"}
}