{
  "type": "Feature",
  "properties": {
    "iso:country":"US",
    "sg:address":"2728 J St",
    "sg:city":"Sacramento",
    "sg:classifiers":[
        {
            "category":"Restaurant",
            "type":"Food & Drink"
        }
    ],
    "sg:postcode":"95814",
    "sg:province":"CA",
    "sg:tags":[
        "pizza"
    ],
    "sg:website":"www.myspace.com/papispizza",
    "wof:name":"Papi's Pizza",
    "wof:placetype":"venue"
},
  "geometry": {"coordinates":[-121.46968099999999,38.573613],"type":"Point"}
}