{
  "type": "Feature",
  "properties": {
    "iso:country":"US",
    "sg:address":"8415 Haven Ave",
    "sg:city":"Rancho Cucamonga",
    "sg:classifiers":[
        {
            "category":"Health Services",
            "subcategory":"Doctor",
            "type":"Services"
        }
    ],
    "sg:phone":"+1 909 980 2272",
    "sg:postcode":"91730",
    "sg:province":"CA",
    "sg:tags":[
        "dentist"
    ],
    "wof:name":"Tooth Shop",
    "wof:placetype":"venue"
},
  "geometry": {"coordinates":[-117.575745,34.100792],"type":"Point"}
}