{
  "type": "Feature",
  "properties": {
    "addr:full":"15900 Pioneer Blvd Norwalk CA 90650",
    "addr:housenumber":"15900",
    "addr:postcode":"90650",
    "addr:street":"Pioneer Blvd",
    "iso:country":"US",
    "sg:address":"15900 Pioneer Blvd",
    "sg:city":"Norwalk",
    "sg:classifiers":[
        {
            "category":"Donuts",
            "subcategory":"None",
            "type":"Food & Drink"
        }
    ],
    "sg:phone":"+1 562 229 1040",
    "sg:postcode":"90650",
    "sg:province":"CA",
    "sg:website":"yumyumdonuts.com",
    "wof:name":"Yum Yum Donut Shops",
    "wof:placetype":"venue"
},
  "geometry": {"coordinates":[-118.082472,33.887563],"type":"Point"}
}