{
  "type": "Feature",
  "properties": {
    "addr:full":"505 South Dr Mountain View CA 94040",
    "addr:housenumber":"505",
    "addr:postcode":"94040",
    "addr:street":"South Dr",
    "iso:country":"US",
    "sg:address":"505 South Dr",
    "sg:city":"Mountain View",
    "sg:classifiers":[
        {
            "category":"Health Services",
            "subcategory":"Dentist",
            "type":"Services"
        }
    ],
    "sg:phone":"+1 650 328 1860",
    "sg:postcode":"94040",
    "sg:province":"CA",
    "wof:name":"Shih",
    "wof:placetype":"venue"
},
  "geometry": {"coordinates":[-122.084,37.367298],"type":"Point"}
}