{
  "type": "Feature",
  "properties": {
    "addr:full":"4075 Evergreen Village Sq Ste 160 San Jose CA 95135",
    "addr:housenumber":"4075",
    "addr:postcode":"95135",
    "addr:street":"Evergreen Village Sq Ste 160",
    "iso:country":"US",
    "sg:address":"4075 Evergreen Village Sq Ste 160",
    "sg:city":"San Jose",
    "sg:classifiers":[
        {
            "category":"Professional",
            "type":"Services"
        }
    ],
    "sg:phone":"+1 888 883 4111",
    "sg:postcode":"95135",
    "sg:province":"CA",
    "sg:website":"www.tricia-allen.com",
    "wof:name":"Tricia Allen Photography",
    "wof:placetype":"venue"
},
  "geometry": {"coordinates":[-121.772937,37.314585],"type":"Point"}
}