{
  "type": "Feature",
  "properties": {
    "addr:full":"1235 Sutter St San Francisco CA 94109",
    "addr:housenumber":"1235",
    "addr:postcode":"94109",
    "addr:street":"Sutter St",
    "iso:country":"US",
    "sg:address":"1235 Sutter St",
    "sg:city":"San Francisco",
    "sg:classifiers":[
        {
            "category":"Wholesale",
            "subcategory":"Non-durable Goods",
            "type":"Manufacturing & Wholesale Goods"
        }
    ],
    "sg:phone":"+1 415 922 6688",
    "sg:postcode":"94109",
    "sg:province":"CA",
    "sg:tags":[
        "used",
        "merchandise"
    ],
    "wof:name":"Art De Asia",
    "wof:placetype":"venue"
},
  "geometry": {"coordinates":[-122.421296,37.787546],"type":"Point"}
}