{
  "type": "Feature",
  "properties": {
    "iso:country":"US",
    "sg:address":"6301 Sky Creek Dr",
    "sg:city":"Sacramento",
    "sg:classifiers":[
        {
            "category":"Home & Garden",
            "subcategory":"Furniture",
            "type":"Retail Goods"
        }
    ],
    "sg:phone":"+1 916 381 7337",
    "sg:postcode":"95828",
    "sg:province":"CA",
    "sg:tags":[
        "top",
        "counter"
    ],
    "sg:website":"www.interstone.biz",
    "wof:name":"Interstone",
    "wof:placetype":"venue"
},
  "geometry": {"coordinates":[-121.384828,38.513795],"type":"Point"}
}