{
  "type": "Feature",
  "properties": {
    "addr:full":"1516 Cotner Ave Los Angeles CA 90025",
    "addr:housenumber":"1516",
    "addr:postcode":"90025",
    "addr:street":"Cotner Ave",
    "iso:country":"US",
    "sg:address":"1516 Cotner Ave",
    "sg:city":"Los Angeles",
    "sg:classifiers":[
        {
            "category":"Health Services",
            "subcategory":"Doctor",
            "type":"Services"
        }
    ],
    "sg:phone":"+1 310 445 2843",
    "sg:postcode":"90025",
    "sg:province":"CA",
    "sg:tags":[
        "physician",
        "surgeon"
    ],
    "sg:website":"www.crues.com",
    "wof:name":"Radnet Management",
    "wof:placetype":"venue"
},
  "geometry": {"coordinates":[-118.44714399999999,34.048492],"type":"Point"}
}