{
  "type": "Feature",
  "properties": {
    "addr:full":"16893 Algonquin St Huntington Beach CA 92649",
    "addr:housenumber":"16893",
    "addr:postcode":"92649",
    "addr:street":"Algonquin St",
    "iso:country":"US",
    "sg:address":"16893 Algonquin St",
    "sg:city":"Huntington Beach",
    "sg:classifiers":[
        {
            "category":"Health Services",
            "subcategory":"Clinic",
            "type":"Services"
        }
    ],
    "sg:phone":"+1 714 846 1378",
    "sg:postcode":"92649",
    "sg:province":"CA",
    "sg:tags":[
        "veterinary",
        "animal"
    ],
    "wof:name":"Kuttel John",
    "wof:placetype":"venue"
},
  "geometry": {"coordinates":[-118.050155,33.71612],"type":"Point"}
}