{
  "type": "Feature",
  "properties": {
    "addr:full":"6881 Catamaran Dr Carlsbad CA 92011",
    "addr:housenumber":"6881",
    "addr:postcode":"92011",
    "addr:street":"Catamaran Dr",
    "iso:country":"US",
    "sg:address":"6881 Catamaran Dr",
    "sg:city":"Carlsbad",
    "sg:classifiers":[
        {
            "category":"Banks & Credit Unions",
            "subcategory":"Bank",
            "type":"Services"
        }
    ],
    "sg:phone":"+1 760 942 3065",
    "sg:postcode":"92011",
    "sg:province":"CA",
    "sg:tags":[
        "loan",
        "real estate"
    ],
    "wof:name":"GAF Investment Inc",
    "wof:placetype":"venue"
},
  "geometry": {"coordinates":[-117.31778300000001,33.104745],"type":"Point"}
}