{
  "type": "Feature",
  "properties": {
    "iso:country":"US",
    "sg:address":"6164 S Eastern Ave",
    "sg:city":"Los Angeles",
    "sg:classifiers":[
        {
            "category":"Home & Garden",
            "subcategory":"Home Furnishings",
            "type":"Retail Goods"
        }
    ],
    "sg:phone":"+1 323 728 2391",
    "sg:postcode":"90040",
    "sg:province":"CA",
    "sg:tags":[
        "lighting",
        "fixture"
    ],
    "wof:name":"Spring Lighting",
    "wof:placetype":"venue"
},
  "geometry": {"coordinates":[-118.16276000000001,33.980428],"type":"Point"}
}