{
  "type": "Feature",
  "properties": {
    "addr:full":"4635 Auburn Boulevard Sacramento CA 95841",
    "addr:housenumber":"4635",
    "addr:postcode":"95841",
    "addr:street":"Auburn Boulevard",
    "iso:country":"US",
    "sg:address":"4635 Auburn Boulevard",
    "sg:city":"Sacramento",
    "sg:classifiers":[
        {
            "category":"Autos & Motor Vehicles",
            "subcategory":"Motorcycle Sales",
            "type":"Retail Goods"
        }
    ],
    "sg:phone":"+1 916 972 8100",
    "sg:postcode":"95841",
    "sg:province":"CA",
    "wof:name":"National Cycle Discount Center",
    "wof:placetype":"venue"
},
  "geometry": {"coordinates":[-121.355255,38.653227],"type":"Point"}
}