{
  "type": "Feature",
  "properties": {
    "iso:country":"US",
    "sg:address":"2603 S Bristol St",
    "sg:city":"Santa Ana",
    "sg:classifiers":[
        {
            "category":"Autos & Motor Vehicles",
            "subcategory":"Automobile Sales",
            "type":"Retail Goods"
        }
    ],
    "sg:phone":"+1 714 957 0061",
    "sg:postcode":"92704",
    "sg:province":"CA",
    "sg:tags":[
        "automotive"
    ],
    "wof:name":"AutoZone",
    "wof:placetype":"venue"
},
  "geometry": {"coordinates":[-117.88491399999999,33.712359],"type":"Point"}
}