{
  "type": "Feature",
  "properties": {
    "iso:country":"US",
    "sg:address":"1994 E 7th St",
    "sg:city":"Long Beach",
    "sg:classifiers":[
        {
            "category":"Food & Beverages",
            "subcategory":"Groceries & Convenience Stores",
            "type":"Retail Goods"
        }
    ],
    "sg:phone":"+1 562 435 1212",
    "sg:postcode":"90813",
    "sg:province":"CA",
    "wof:name":"7-Eleven",
    "wof:placetype":"venue"
},
  "geometry": {"coordinates":[-118.168514,33.775266],"type":"Point"}
}