{
  "type": "Feature",
  "properties": {
    "iso:country":"US",
    "sg:address":"8950 W Olympic Blvd",
    "sg:city":"Beverly Hills",
    "sg:classifiers":[
        {
            "category":"Shopping",
            "subcategory":"Pharmacy",
            "type":"Retail Goods"
        }
    ],
    "sg:phone":"+1 310 274 8080",
    "sg:postcode":"90211",
    "sg:province":"CA",
    "sg:tags":[
        "drugstore"
    ],
    "wof:name":"United Drugs",
    "wof:placetype":"venue"
},
  "geometry": {"coordinates":[-118.387001,34.059399],"type":"Point"}
}