{
  "type": "Feature",
  "properties": {
    "addr:full":"3040 Totterdell St Oakland CA 94611",
    "addr:housenumber":"3040",
    "addr:postcode":"94611",
    "addr:street":"Totterdell St",
    "iso:country":"US",
    "sg:address":"3040 Totterdell St",
    "sg:city":"Oakland",
    "sg:classifiers":[
        {
            "category":"Professional",
            "subcategory":"Computer Services",
            "type":"Services"
        }
    ],
    "sg:phone":"+1 510 482 1475",
    "sg:postcode":"94611",
    "sg:province":"CA",
    "sg:tags":[
        "design",
        "system",
        "network"
    ],
    "wof:name":"Infrastructure Design Assoc",
    "wof:placetype":"venue"
},
  "geometry": {"coordinates":[-122.187614,37.822422],"type":"Point"}
}