{
  "type": "Feature",
  "properties": {
    "addr:full":"2295 Pso de Las Americas San Diego CA 92154",
    "addr:housenumber":"2295",
    "addr:postcode":"92154",
    "addr:street":"Pso De Las Americas",
    "iso:country":"US",
    "sg:address":"2295 Pso de Las Americas",
    "sg:city":"San Diego",
    "sg:classifiers":[
        {
            "category":"Building & Trades",
            "subcategory":"Electrical",
            "type":"Services"
        }
    ],
    "sg:phone":"+1 619 671 0570",
    "sg:postcode":"92154",
    "sg:province":"CA",
    "sg:tags":[
        "electric",
        "contractor"
    ],
    "wof:name":"California Electric & Ind Splr",
    "wof:placetype":"venue"
},
  "geometry": {"coordinates":[-116.93586999999999,32.558492],"type":"Point"}
}