{
  "type": "Feature",
  "properties": {
    "addr:full":"Westfield Shoppingtown Mall 400 S Baldwin Ave, Ste 435B Arcadia CA 91007",
    "addr:housenumber":"400",
    "addr:postcode":"91007",
    "addr:street":"S Baldwin Ave Ste 435B",
    "iso:country":"US",
    "sg:address":"Westfield Shoppingtown Mall 400 S Baldwin Ave, Ste 435B",
    "sg:city":"Arcadia",
    "sg:classifiers":[
        {
            "category":"Shopping",
            "subcategory":"Bicycles & Sporting Goods",
            "type":"Retail Goods"
        }
    ],
    "sg:phone":"+1 626 447 7025",
    "sg:postcode":"91007",
    "sg:province":"CA",
    "sg:website":"www.champssports.com",
    "wof:name":"Champs Sports",
    "wof:placetype":"venue"
},
  "geometry": {"coordinates":[-118.05030600000001,34.133512],"type":"Point"}
}