{
  "type": "Feature",
  "properties": {
    "iso:country":"US",
    "sg:address":"212 Brookside Ave",
    "sg:city":"Redlands",
    "sg:classifiers":[
        {
            "category":"Banks & Credit Unions",
            "subcategory":"Bank",
            "type":"Services"
        }
    ],
    "sg:phone":"+1 909 798 7626",
    "sg:postcode":"92373",
    "sg:province":"CA",
    "wof:name":"Redlands City Employees Federal Credit Union",
    "wof:placetype":"venue"
},
  "geometry": {"coordinates":[-117.18636600000001,34.055046],"type":"Point"}
}