{
  "type": "Feature",
  "properties": {
    "iso:country":"US",
    "sg:address":"639 E Alisal St",
    "sg:city":"Salinas",
    "sg:classifiers":[
        {
            "category":"Shopping",
            "subcategory":"Clothing, Apparel, & Fashions",
            "type":"Retail Goods"
        }
    ],
    "sg:phone":"+1 831 753 9812",
    "sg:postcode":"93905",
    "sg:province":"CA",
    "sg:tags":[
        "shop",
        "bridal"
    ],
    "wof:name":"Medina's Bridal Shop",
    "wof:placetype":"venue"
},
  "geometry": {"coordinates":[-121.632251,36.673409],"type":"Point"}
}