{
  "type": "Feature",
  "properties": {
    "iso:country":"US",
    "sg:address":"839 Meridian St",
    "sg:city":"Duarte",
    "sg:classifiers":[
        {
            "category":"Wholesale",
            "subcategory":"Machinery & Supplies",
            "type":"Manufacturing & Wholesale Goods"
        }
    ],
    "sg:phone":"+1 626 303 0650",
    "sg:postcode":"91010",
    "sg:province":"CA",
    "sg:tags":[
        "truck"
    ],
    "wof:name":"Smith Industrial Tires",
    "wof:placetype":"venue"
},
  "geometry": {"coordinates":[-117.986914,34.121376],"type":"Point"}
}