{
  "type": "Feature",
  "properties": {
    "addr:full":"2900 Adams St Riverside CA 92504",
    "addr:housenumber":"2900",
    "addr:postcode":"92504",
    "addr:street":"Adams St",
    "iso:country":"US",
    "sg:address":"2900 Adams St",
    "sg:city":"Riverside",
    "sg:classifiers":[
        {
            "category":"Organizations",
            "subcategory":"Religious Organization",
            "type":"Services"
        }
    ],
    "sg:phone":"+1 951 687 6395",
    "sg:postcode":"92504",
    "sg:province":"CA",
    "sg:tags":[
        "church"
    ],
    "wof:name":"New Jerusalem Christian Ctr",
    "wof:placetype":"venue"
},
  "geometry": {"coordinates":[-117.41676099999999,33.923822],"type":"Point"}
}