{
  "type": "Feature",
  "properties": {
    "addr:full":"301 W County Line Rd Calimesa CA 92320",
    "addr:housenumber":"301",
    "addr:postcode":"92320",
    "addr:street":"W County Line Rd",
    "iso:country":"US",
    "sg:address":"301 W County Line Rd",
    "sg:city":"Calimesa",
    "sg:classifiers":[
        {
            "category":"Food & Beverages",
            "subcategory":"Groceries & Convenience Stores",
            "type":"Retail Goods"
        }
    ],
    "sg:phone":"+1 909 795 6735",
    "sg:postcode":"92320",
    "sg:province":"CA",
    "sg:website":"www.7-eleven.com",
    "wof:name":"7-Eleven",
    "wof:placetype":"venue"
},
  "geometry": {"coordinates":[-117.047997,34.004398],"type":"Point"}
}