{
  "type": "Feature",
  "properties": {
    "addr:full":"333 Bryant St Ste 240 San Francisco CA 94107",
    "addr:housenumber":"333",
    "addr:postcode":"94107",
    "addr:street":"Bryant St Ste 240",
    "iso:country":"US",
    "sg:address":"333 Bryant St Ste 240",
    "sg:city":"San Francisco",
    "sg:classifiers":[
        {
            "category":"Real Estate",
            "subcategory":"Architect",
            "type":"Services"
        }
    ],
    "sg:phone":"+1 415 896 9500",
    "sg:postcode":"94107",
    "sg:province":"CA",
    "wof:name":"Remick Associates Architecture & Design",
    "wof:placetype":"venue"
},
  "geometry": {"coordinates":[-122.39206799999999,37.78407],"type":"Point"}
}