{
  "type": "Feature",
  "properties": {
    "iso:country":"US",
    "sg:address":"1154 Atascadero St",
    "sg:city":"San Luis Obispo",
    "sg:classifiers":[
        {
            "category":"Social Services",
            "subcategory":"Adult Care",
            "type":"Services"
        }
    ],
    "sg:phone":"+1 805 543 1100",
    "sg:postcode":"93405",
    "sg:province":"CA",
    "sg:tags":[
        "home",
        "residential"
    ],
    "wof:name":"Bascos Virgil & Co",
    "wof:placetype":"venue"
},
  "geometry": {"coordinates":[-120.686233,35.259461],"type":"Point"}
}