{
  "type": "Feature",
  "properties": {
    "iso:country":"US",
    "sg:address":"745 Independence Ave",
    "sg:city":"Mountain View",
    "sg:classifiers":[
        {
            "category":"Building & Trades",
            "subcategory":"Landscaping Services",
            "type":"Services"
        }
    ],
    "sg:phone":"+1 650 968 4004",
    "sg:postcode":"94043",
    "sg:province":"CA",
    "sg:tags":[
        "tree"
    ],
    "wof:name":"Liddicoat Tree Svc",
    "wof:placetype":"venue"
},
  "geometry": {"coordinates":[-122.097362,37.413863],"type":"Point"}
}