{
  "type": "Feature",
  "properties": {
    "iso:country":"US",
    "sg:address":"4795 Vineland Ave",
    "sg:city":"Los Angeles",
    "sg:classifiers":[
        {
            "category":"Professional",
            "type":"Services"
        },
        {
            "category":"Professional",
            "subcategory":"Printing & Photocopies",
            "type":"Services"
        }
    ],
    "sg:phone":"+1 818 755 4542",
    "sg:postcode":"91602",
    "sg:province":"CA",
    "wof:name":"NoHo Copy Center",
    "wof:placetype":"venue"
},
  "geometry": {"coordinates":[-118.371126,34.157356],"type":"Point"}
}