{
  "type": "Feature",
  "properties": {
    "addr:full":"7767 Colwyn Ave Highland CA 92346",
    "addr:housenumber":"7767",
    "addr:postcode":"92346",
    "addr:street":"Colwyn Ave",
    "iso:country":"US",
    "sg:address":"7767 Colwyn Ave",
    "sg:city":"Highland",
    "sg:classifiers":[
        {
            "category":"Building & Trades",
            "subcategory":"Pest Control",
            "type":"Services"
        }
    ],
    "sg:phone":"+1 909 862 9273",
    "sg:postcode":"92346",
    "sg:province":"CA",
    "wof:name":"Axiom Pest Svc",
    "wof:placetype":"venue"
},
  "geometry": {"coordinates":[-117.220102,34.112824],"type":"Point"}
}