{
  "type": "Feature",
  "properties": {
    "addr:full":"21057 Clivus Dr Grass Valley CA 95949",
    "addr:postcode":"21057;95949",
    "addr:street":"Clivus Dr",
    "iso:country":"US",
    "sg:address":"21057 Clivus Dr",
    "sg:city":"Grass Valley",
    "sg:classifiers":[
        {
            "category":"Building & Trades",
            "subcategory":"Pest Control",
            "type":"Services"
        }
    ],
    "sg:phone":"+1 530 268 3081",
    "sg:postcode":"95949",
    "sg:province":"CA",
    "wof:name":"Bug Doctor Pest Control",
    "wof:placetype":"venue"
},
  "geometry": {"coordinates":[-121.086175,39.065747],"type":"Point"}
}