{
  "type": "Feature",
  "properties": {
    "iso:country":"US",
    "sg:address":"5950 Santo Rd",
    "sg:city":"San Diego",
    "sg:classifiers":[
        {
            "category":"Health Services",
            "subcategory":"Health Practitioner",
            "type":"Services"
        }
    ],
    "sg:phone":"+1 858 715 3878",
    "sg:postcode":"92124",
    "sg:province":"CA",
    "sg:tags":[
        "therapist",
        "physical"
    ],
    "wof:name":"Adjust Physical Therapy",
    "wof:placetype":"venue"
},
  "geometry": {"coordinates":[-117.097311,32.840739],"type":"Point"}
}