{
  "type": "Feature",
  "properties": {
    "addr:full":"5411 S Broadway Los Angeles CA 90037",
    "addr:housenumber":"5411",
    "addr:postcode":"90037",
    "addr:street":"S Broadway",
    "iso:country":"US",
    "sg:address":"5411 S Broadway",
    "sg:city":"Los Angeles",
    "sg:classifiers":[
        {
            "category":"Organizations",
            "subcategory":"Religious Organization",
            "type":"Services"
        }
    ],
    "sg:phone":"+1 323 751 4642",
    "sg:postcode":"90037",
    "sg:province":"CA",
    "sg:tags":[
        "church"
    ],
    "wof:name":"Iglesia Betel Pentecoste",
    "wof:placetype":"venue"
},
  "geometry": {"coordinates":[-118.278374,33.992489],"type":"Point"}
}