{
  "type": "Feature",
  "properties": {
    "iso:country":"US",
    "sg:address":"1161 Richard Ave",
    "sg:city":"Santa Clara",
    "sg:classifiers":[
        {
            "category":"Manufacturing",
            "subcategory":"Metals",
            "type":"Manufacturing & Wholesale Goods"
        }
    ],
    "sg:phone":"+1 408 727 5776",
    "sg:postcode":"95050",
    "sg:province":"CA",
    "sg:tags":[
        "coating"
    ],
    "wof:name":"Swift Metal Finishing",
    "wof:placetype":"venue"
},
  "geometry": {"coordinates":[-121.950076,37.365035],"type":"Point"}
}