{
  "type": "Feature",
  "properties": {
    "iso:country":"US",
    "sg:address":"3375 Scott Blvd",
    "sg:city":"Santa Clara",
    "sg:classifiers":[
        {
            "category":"Professional",
            "subcategory":"Employment Agencies",
            "type":"Services"
        }
    ],
    "sg:phone":"+1 408 748 0245",
    "sg:postcode":"95054",
    "sg:province":"CA",
    "wof:name":"Pro Source",
    "wof:placetype":"venue"
},
  "geometry": {"coordinates":[-121.98474,37.380727],"type":"Point"}
}