{
  "type": "Feature",
  "properties": {
    "iso:country":"US",
    "sg:address":"17870 Sky Park Cir",
    "sg:city":"Irvine",
    "sg:classifiers":[
        {
            "category":"Banks & Credit Unions",
            "subcategory":"Investment Brokerage",
            "type":"Services"
        }
    ],
    "sg:phone":"+1 949 757 0357",
    "sg:postcode":"92614",
    "sg:province":"CA",
    "sg:tags":[
        "security"
    ],
    "wof:name":"Bernard Abrams Assoc",
    "wof:placetype":"venue"
},
  "geometry": {"coordinates":[-117.855877,33.691026],"type":"Point"}
}