{
  "type": "Feature",
  "properties": {
    "iso:country":"US",
    "sg:address":"1818 Loveridge Rd",
    "sg:city":"Pittsburg",
    "sg:classifiers":[
        {
            "category":"Building & Trades",
            "subcategory":"Construction",
            "type":"Services"
        }
    ],
    "sg:phone":"+1 925 432 4282",
    "sg:postcode":"94565",
    "sg:province":"CA",
    "sg:tags":[
        "water",
        "well",
        "drilling"
    ],
    "sg:website":"www.martellwatersystems.homestead.com",
    "wof:name":"Martell Water Systems Inc",
    "wof:placetype":"venue"
},
  "geometry": {"coordinates":[-121.863858,38.012934],"type":"Point"}
}