{
  "type": "Feature",
  "properties": {
    "addr:full":"10727 Pekolee Dr Grass Valley CA 95949",
    "addr:housenumber":"10727",
    "addr:postcode":"95949",
    "addr:street":"Pekolee Dr",
    "iso:country":"US",
    "sg:address":"10727 Pekolee Dr",
    "sg:city":"Grass Valley",
    "sg:classifiers":[
        {
            "category":"Professional",
            "subcategory":"Research",
            "type":"Services"
        }
    ],
    "sg:phone":"+1 530 274 9552",
    "sg:postcode":"95949",
    "sg:province":"CA",
    "sg:tags":[
        "development",
        "electronic"
    ],
    "wof:name":"Conragan Systems Co",
    "wof:placetype":"venue"
},
  "geometry": {"coordinates":[-121.071608,39.119772],"type":"Point"}
}