{
  "type": "Feature",
  "properties": {
    "addr:full":"5726 La Jolla Blvd Studio 105 La Jolla CA 92037",
    "addr:housenumber":"5726;105",
    "addr:postcode":"92037",
    "addr:street":"La Jolla Blvd Studio",
    "iso:country":"US",
    "sg:address":"5726 La Jolla Blvd Studio 105",
    "sg:city":"La Jolla",
    "sg:classifiers":[
        {
            "category":"Personal",
            "subcategory":"Beauty Salon",
            "type":"Services"
        }
    ],
    "sg:phone":"+1 619 920 4081",
    "sg:postcode":"92037",
    "sg:province":"CA",
    "sg:tags":[
        "hair"
    ],
    "sg:website":"www.minxsalonsd.com",
    "wof:name":"Minx",
    "wof:placetype":"venue"
},
  "geometry": {"coordinates":[-117.27130699999999,32.816403],"type":"Point"}
}