{
  "type": "Feature",
  "properties": {
    "iso:country":"US",
    "sg:address":"635 S Hill St",
    "sg:city":"Los Angeles",
    "sg:classifiers":[
        {
            "category":"Wholesale",
            "subcategory":"Jewelry",
            "type":"Manufacturing & Wholesale Goods"
        }
    ],
    "sg:phone":"+1 213 629 1898",
    "sg:postcode":"90014",
    "sg:province":"CA",
    "sg:tags":[
        "jeweler"
    ],
    "wof:name":"Ultima Gems Of California",
    "wof:placetype":"venue"
},
  "geometry": {"coordinates":[-118.254122,34.046453],"type":"Point"}
}