{
  "type": "Feature",
  "properties": {
    "addr:full":"628 W Sacramento Ave Chico CA 95926",
    "addr:housenumber":"628",
    "addr:postcode":"95926",
    "addr:street":"W Sacramento Ave",
    "iso:country":"US",
    "sg:address":"628 W Sacramento Ave",
    "sg:city":"Chico",
    "sg:classifiers":[
        {
            "category":"Restaurant",
            "type":"Food & Drink"
        }
    ],
    "sg:phone":"+1 530 345 7672",
    "sg:postcode":"95926",
    "sg:province":"CA",
    "wof:name":"Monstros Pizza & Subs",
    "wof:placetype":"venue"
},
  "geometry": {"coordinates":[-121.852912,39.733409],"type":"Point"}
}