{
  "type": "Feature",
  "properties": {
    "iso:country":"US",
    "sg:address":"455 Antelope Blvd",
    "sg:city":"Red Bluff",
    "sg:classifiers":[
        {
            "category":"Restaurant",
            "type":"Food & Drink"
        }
    ],
    "sg:phone":"+1 530 527 3320",
    "sg:postcode":"96080",
    "sg:province":"CA",
    "wof:name":"Bud's Jolly KONE",
    "wof:placetype":"venue"
},
  "geometry": {"coordinates":[-122.210403,40.186191],"type":"Point"}
}