{
  "type": "Feature",
  "properties": {
    "iso:country":"US",
    "sg:address":"29502 Via San Sebastian",
    "sg:city":"Laguna Niguel",
    "sg:classifiers":[
        {
            "category":"Building & Trades",
            "subcategory":"Landscaping Services",
            "type":"Services"
        }
    ],
    "sg:phone":"+1 949 495 3412",
    "sg:postcode":"92677",
    "sg:province":"CA",
    "sg:tags":[
        "landscape",
        "contractor"
    ],
    "wof:name":"Landscape Systems",
    "wof:placetype":"venue"
},
  "geometry": {"coordinates":[-117.699458,33.534621],"type":"Point"}
}