{
  "type": "Feature",
  "properties": {
    "iso:country":"US",
    "sg:address":"825 Riverside Ave",
    "sg:city":"Paso Robles",
    "sg:classifiers":[
        {
            "category":"Building & Trades",
            "subcategory":"Construction",
            "type":"Services"
        }
    ],
    "sg:phone":"+1 805 237 7934",
    "sg:postcode":"93446",
    "sg:province":"CA",
    "sg:tags":[
        "contractor"
    ],
    "wof:name":"Bella Vista Estates",
    "wof:placetype":"venue"
},
  "geometry": {"coordinates":[-120.686607,35.623368],"type":"Point"}
}