{
  "type": "Feature",
  "properties": {
    "addr:full":"655 4th Ave San Diego CA 92101",
    "addr:housenumber":"655",
    "addr:postcode":"92101",
    "addr:street":"4Th Ave",
    "iso:country":"US",
    "sg:address":"655 4th Ave",
    "sg:city":"San Diego",
    "sg:classifiers":[
        {
            "category":"Bars & Pubs",
            "type":"Food & Drink"
        },
        {
            "category":"Arts & Performance",
            "subcategory":"Music",
            "type":"Entertainment"
        }
    ],
    "sg:phone":"+1 619 231 6700",
    "sg:postcode":"92101",
    "sg:province":"CA",
    "sg:tags":[
        "venue"
    ],
    "sg:website":"www.theshouthouse.com",
    "wof:name":"The Shout House",
    "wof:placetype":"venue"
},
  "geometry": {"coordinates":[-117.16100299999999,32.712101],"type":"Point"}
}