{
  "type": "Feature",
  "properties": {
    "iso:country":"US",
    "sg:address":"425 State Pl",
    "sg:city":"Escondido",
    "sg:classifiers":[
        {
            "category":"Government",
            "subcategory":"Office",
            "type":"Public Place"
        }
    ],
    "sg:phone":"+1 760 737 2030",
    "sg:postcode":"92029",
    "sg:province":"CA",
    "sg:tags":[
        "state",
        "program",
        "health"
    ],
    "wof:name":"Escondido Community Health Ctr",
    "wof:placetype":"venue"
},
  "geometry": {"coordinates":[-117.111369,33.122394],"type":"Point"}
}