{
  "type": "Feature",
  "properties": {
    "addr:full":"25555 N Ave Stanford Valencia CA 91355",
    "addr:housenumber":"25555",
    "addr:postcode":"91355",
    "addr:street":"N Ave",
    "iso:country":"US",
    "sg:address":"25555 N Ave Stanford",
    "sg:city":"Valencia",
    "sg:classifiers":[
        {
            "category":"Manufacturing",
            "subcategory":"Tools & Machinery",
            "type":"Manufacturing & Wholesale Goods"
        }
    ],
    "sg:phone":"+1 661 257 6245",
    "sg:postcode":"91355",
    "sg:province":"CA",
    "sg:tags":[
        "water",
        "cooler",
        "mfg",
        "mechanical"
    ],
    "wof:name":"Oasis Corporation",
    "wof:placetype":"venue"
},
  "geometry": {"coordinates":[-118.587166,34.43276],"type":"Point"}
}