{
  "type": "Feature",
  "properties": {
    "addr:full":"665 15th St Oakland CA 94612",
    "addr:housenumber":"665",
    "addr:postcode":"94612",
    "addr:street":"15Th St",
    "iso:country":"US",
    "sg:address":"665 15th St",
    "sg:city":"Oakland",
    "sg:classifiers":[
        {
            "category":"Home & Garden",
            "subcategory":"Building Materials",
            "type":"Retail Goods"
        }
    ],
    "sg:phone":"+1 415 255 5966",
    "sg:postcode":"94612",
    "sg:province":"CA",
    "sg:tags":[
        "windows"
    ],
    "wof:name":"Great Window Washing",
    "wof:placetype":"venue"
},
  "geometry": {"coordinates":[-122.275565,37.806884],"type":"Point"}
}