{
  "type": "Feature",
  "properties": {
    "addr:full":"7970 Woodman Ave Van Nuys CA 91402",
    "addr:housenumber":"7970",
    "addr:postcode":"91402",
    "addr:street":"Woodman Ave",
    "iso:country":"US",
    "sg:address":"7970 Woodman Ave",
    "sg:city":"Van Nuys",
    "sg:classifiers":[
        {
            "category":"Professional",
            "type":"Services"
        }
    ],
    "sg:phone":"+1 818 781 5108",
    "sg:postcode":"91402",
    "sg:province":"CA",
    "sg:tags":[
        "establishment"
    ],
    "wof:name":"Ppa Assoc LP",
    "wof:placetype":"venue"
},
  "geometry": {"coordinates":[-118.430898,34.216937],"type":"Point"}
}