{
  "type": "Feature",
  "properties": {
    "addr:full":"227 Forest Ave Pacific Grove CA 93950",
    "addr:housenumber":"227",
    "addr:postcode":"93950",
    "addr:street":"Forest Ave",
    "iso:country":"US",
    "sg:address":"227 Forest Ave",
    "sg:city":"Pacific Grove",
    "sg:classifiers":[
        {
            "category":"Wholesale",
            "subcategory":"Hardware",
            "type":"Manufacturing & Wholesale Goods"
        }
    ],
    "sg:phone":"+1 831 333 1919",
    "sg:postcode":"93950",
    "sg:province":"CA",
    "sg:tags":[
        "equipment",
        "energy",
        "solar"
    ],
    "wof:name":"Applied Solar Energy",
    "wof:placetype":"venue"
},
  "geometry": {"coordinates":[-121.91816,36.620127],"type":"Point"}
}