{
  "type": "Feature",
  "properties": {
    "iso:country":"US",
    "sg:address":"7422 Melrose Ave",
    "sg:city":"Los Angeles",
    "sg:classifiers":[
        {
            "category":"Shopping",
            "subcategory":"Clothing, Apparel, & Fashions",
            "type":"Retail Goods"
        }
    ],
    "sg:phone":"+1 323 653 5591",
    "sg:postcode":"90046",
    "sg:province":"CA",
    "sg:tags":[
        "dressmaker"
    ],
    "sg:website":"www.ayumicollection.com",
    "wof:name":"Ayumi",
    "wof:placetype":"venue"
},
  "geometry": {"coordinates":[-118.351805,34.083525],"type":"Point"}
}