{
  "type": "Feature",
  "properties": {
    "iso:country":"US",
    "sg:address":"303 Cheshire Dr",
    "sg:city":"Brentwood",
    "sg:classifiers":[
        {
            "category":"Travel",
            "subcategory":"Travel Agent",
            "type":"Entertainment"
        }
    ],
    "sg:phone":"+1 925 240 5740",
    "sg:postcode":"94513",
    "sg:province":"CA",
    "sg:tags":[
        "agency"
    ],
    "wof:name":"Cruiseone 1117",
    "wof:placetype":"venue"
},
  "geometry": {"coordinates":[-121.714409,37.921539],"type":"Point"}
}