{
  "type": "Feature",
  "properties": {
    "addr:full":"16240 Foothill Blvd San Leandro CA 94577",
    "addr:housenumber":"16240",
    "addr:postcode":"94577",
    "addr:street":"Foothill Blvd",
    "iso:country":"US",
    "sg:address":"16240 Foothill Blvd",
    "sg:city":"San Leandro",
    "sg:classifiers":[
        {
            "category":"Restaurant",
            "type":"Food & Drink"
        }
    ],
    "sg:phone":"+1 510 481 7696",
    "sg:postcode":"94577",
    "sg:province":"CA",
    "sg:tags":[
        "pizza"
    ],
    "wof:name":"Foothill Pizza Restaurant",
    "wof:placetype":"venue"
},
  "geometry": {"coordinates":[-122.142995,37.738548],"type":"Point"}
}