{
  "type": "Feature",
  "properties": {
    "iso:country":"US",
    "sg:address":"4462 Park Arroyo",
    "sg:city":"Calabasas",
    "sg:classifiers":[
        {
            "category":"Real Estate",
            "subcategory":"Real Estate Services",
            "type":"Services"
        },
        {
            "category":"Real Estate",
            "subcategory":"Real Estate Agent",
            "type":"Services"
        }
    ],
    "sg:phone":"+1 818 222 7072",
    "sg:postcode":"91302",
    "sg:province":"CA",
    "sg:tags":[
        "management"
    ],
    "sg:website":"http://www.rioricofire.org",
    "wof:name":"Costa Oro Realty",
    "wof:placetype":"venue"
},
  "geometry": {"coordinates":[-118.630957,34.149827],"type":"Point"}
}