{
  "type": "Feature",
  "properties": {
    "addr:full":"14945 Tercer Verde Del Mar CA 92014",
    "addr:housenumber":"14945",
    "addr:postcode":"92014",
    "addr:street":"Tercer Verde",
    "iso:country":"US",
    "sg:address":"14945 Tercer Verde",
    "sg:city":"Del Mar",
    "sg:classifiers":[
        {
            "category":"Wholesale",
            "subcategory":"Electrical",
            "type":"Manufacturing & Wholesale Goods"
        }
    ],
    "sg:phone":"+1 858 481 8226",
    "sg:postcode":"92014",
    "sg:province":"CA",
    "sg:tags":[
        "equipment",
        "rep",
        "electronic",
        "mfg"
    ],
    "wof:name":"Blueback Enterprises Inc",
    "wof:placetype":"venue"
},
  "geometry": {"coordinates":[-117.245609,32.987047],"type":"Point"}
}