{
  "type": "Feature",
  "properties": {
    "iso:country":"US",
    "sg:address":"3990 Old Town Avenue",
    "sg:city":"San Diego",
    "sg:classifiers":[
        {
            "category":"Professional",
            "subcategory":"Lawyer & Legal Services",
            "type":"Services"
        }
    ],
    "sg:phone":"+1 619 297 8480",
    "sg:postcode":"92110",
    "sg:province":"CA",
    "wof:name":"Caputo Anthony J Law Offices of",
    "wof:placetype":"venue"
},
  "geometry": {"coordinates":[-117.19125099999999,32.750461],"type":"Point"}
}