{
  "type": "Feature",
  "properties": {
    "iso:country":"US",
    "sg:address":"4921 W Jefferson Blvd",
    "sg:city":"Los Angeles",
    "sg:classifiers":[
        {
            "category":"Wholesale",
            "subcategory":"Auto Parts",
            "type":"Manufacturing & Wholesale Goods"
        }
    ],
    "sg:phone":"+1 323 373 0460",
    "sg:postcode":"90016",
    "sg:province":"CA",
    "sg:tags":[
        "body",
        "automobile",
        "shop"
    ],
    "wof:name":"Jose L Rodriquez",
    "wof:placetype":"venue"
},
  "geometry": {"coordinates":[-118.351802,34.025593],"type":"Point"}
}