{
  "type": "Feature",
  "properties": {
    "addr:full":"2650 W Chanticleer Rd Anaheim CA 92804",
    "addr:housenumber":"2650",
    "addr:postcode":"92804",
    "addr:street":"W Chanticleer Rd",
    "iso:country":"US",
    "sg:address":"2650 W Chanticleer Rd",
    "sg:city":"Anaheim",
    "sg:classifiers":[
        {
            "category":"Shopping",
            "subcategory":"Gifts & Souvenirs",
            "type":"Retail Goods"
        }
    ],
    "sg:phone":"+1 714 220 2062",
    "sg:postcode":"92804",
    "sg:province":"CA",
    "wof:name":"Dream Maker Gift Baskets",
    "wof:placetype":"venue"
},
  "geometry": {"coordinates":[-117.97784299999999,33.812454],"type":"Point"}
}