{
  "type": "Feature",
  "properties": {
    "addr:full":"1295 Seville Dr. Pacifica, Ca 94044",
    "wof:categories":[
        "education_and_religion:education=school"
    ],
    "wof:name":"Alma Heights Christian Academy",
    "wof:placetype":"venue"
},
  "geometry": {"coordinates":[-122.49371082933435,37.58839663865899],"type":"Point"}
}