{
  "type": "Feature",
  "properties": {
    "iso:country":"US",
    "sg:address":"195 S 28th Street",
    "sg:city":"San Jose",
    "sg:classifiers":[
        {
            "category":"Food & Beverages",
            "subcategory":"Groceries & Convenience Stores",
            "type":"Retail Goods"
        }
    ],
    "sg:phone":"+1 408 293 0550",
    "sg:postcode":"95116",
    "sg:province":"CA",
    "wof:name":"Cal Foods",
    "wof:placetype":"venue"
},
  "geometry": {"coordinates":[-121.862146,37.346182],"type":"Point"}
}