{
  "type": "Feature",
  "properties": {
    "addr:full":"345 Sunol St San Jose CA 95126",
    "addr:housenumber":"345",
    "addr:postcode":"95126",
    "addr:street":"Sunol St",
    "iso:country":"US",
    "sg:address":"345 Sunol St",
    "sg:city":"San Jose",
    "sg:classifiers":[
        {
            "category":"Personal",
            "type":"Services"
        }
    ],
    "sg:phone":"+1 877 417 6060",
    "sg:postcode":"95126",
    "sg:province":"CA",
    "sg:tags":[
        "mover"
    ],
    "sg:website":"www.spartanmoving.com",
    "wof:name":"Spartan Moving Systems",
    "wof:placetype":"venue"
},
  "geometry": {"coordinates":[-121.90629,37.322312],"type":"Point"}
}