{
  "type": "Feature",
  "properties": {
    "iso:country":"US",
    "sg:address":"503 S Vincent Ave",
    "sg:city":"Azusa",
    "sg:classifiers":[
        {
            "category":"Professional",
            "type":"Services"
        }
    ],
    "sg:phone":"+1 626 334 1519",
    "sg:postcode":"91702",
    "sg:province":"CA",
    "sg:tags":[
        "establishment"
    ],
    "wof:name":"Kemac Technology Inc",
    "wof:placetype":"venue"
},
  "geometry": {"coordinates":[-117.925346,34.111693],"type":"Point"}
}