{
  "type": "Feature",
  "properties": {
    "iso:country":"US",
    "sg:address":"225 E Carrillo St",
    "sg:city":"Santa Barbara",
    "sg:classifiers":[
        {
            "category":"Banks & Credit Unions",
            "subcategory":"Investment Brokerage",
            "type":"Services"
        }
    ],
    "sg:phone":"+1 805 965 7955",
    "sg:postcode":"93101",
    "sg:province":"CA",
    "sg:tags":[
        "consultant",
        "planning",
        "financial"
    ],
    "wof:name":"Montecito Capital Management",
    "wof:placetype":"venue"
},
  "geometry": {"coordinates":[-119.698755,34.424455],"type":"Point"}
}