{
  "type": "Feature",
  "properties": {
    "addr:full":"1496 Valencia Ave Pasadena CA 91104",
    "addr:housenumber":"1496",
    "addr:postcode":"91104",
    "addr:street":"Valencia Ave",
    "iso:country":"US",
    "sg:address":"1496 Valencia Ave",
    "sg:city":"Pasadena",
    "sg:classifiers":[
        {
            "category":"Wholesale",
            "subcategory":"Machinery & Supplies",
            "type":"Manufacturing & Wholesale Goods"
        }
    ],
    "sg:phone":"+1 626 794 9120",
    "sg:postcode":"91104",
    "sg:province":"CA",
    "sg:tags":[
        "equipment",
        "printing"
    ],
    "wof:name":"Printing Industry Exchange",
    "wof:placetype":"venue"
},
  "geometry": {"coordinates":[-118.09935,34.17233],"type":"Point"}
}