{
  "type": "Feature",
  "properties": {
    "addr:full":"625 Cannery Row Monterey CA 93940",
    "addr:housenumber":"625",
    "addr:postcode":"93940",
    "addr:street":"Cannery Row",
    "iso:country":"US",
    "sg:address":"625 Cannery Row",
    "sg:city":"Monterey",
    "sg:classifiers":[
        {
            "category":"Shopping",
            "subcategory":"Clothing, Apparel, & Fashions",
            "type":"Retail Goods"
        }
    ],
    "sg:phone":"+1 831 375 8286",
    "sg:postcode":"93940",
    "sg:province":"CA",
    "wof:name":"Hai Sona Boutique",
    "wof:placetype":"venue"
},
  "geometry": {"coordinates":[-121.90018999999999,36.61569],"type":"Point"}
}