{
  "type": "Feature",
  "properties": {
    "addr:full":"835 W Ave J Lancaster CA 93534",
    "addr:housenumber":"835",
    "addr:postcode":"93534",
    "addr:street":"W Ave J",
    "iso:country":"US",
    "sg:address":"835 W Ave J",
    "sg:city":"Lancaster",
    "sg:classifiers":[
        {
            "category":"Professional",
            "type":"Services"
        }
    ],
    "sg:phone":"+1 661 948 7100",
    "sg:postcode":"93534",
    "sg:province":"CA",
    "wof:name":"Alord Foods",
    "wof:placetype":"venue"
},
  "geometry": {"coordinates":[-118.144527,34.689439],"type":"Point"}
}