{
  "type": "Feature",
  "properties": {
    "addr:full":"603 Bush St San Francisco CA 94108",
    "addr:housenumber":"603",
    "addr:postcode":"94108",
    "addr:street":"Bush St",
    "iso:country":"US",
    "sg:address":"603 Bush St",
    "sg:city":"San Francisco",
    "sg:classifiers":[
        {
            "category":"Bars & Pubs",
            "type":"Food & Drink"
        }
    ],
    "sg:menulink":"http://www.allmenus.com/ca/san-francisco/121294-bar-crudo/menu/",
    "sg:phone":"+1 415 956 0396",
    "sg:postcode":"94108",
    "sg:province":"CA",
    "sg:tags":[
        "seafood",
        "american"
    ],
    "wof:name":"Bar Crudo",
    "wof:placetype":"venue"
},
  "geometry": {"coordinates":[-122.40732300000001,37.790377],"type":"Point"}
}