{
  "type": "Feature",
  "properties": {
    "addr:full":"2901 Douglas St Anderson CA 96007",
    "addr:housenumber":"2901",
    "addr:postcode":"96007",
    "addr:street":"Douglas St",
    "iso:country":"US",
    "sg:address":"2901 Douglas St",
    "sg:city":"Anderson",
    "sg:classifiers":[
        {
            "category":"Wholesale",
            "subcategory":"Hardware",
            "type":"Manufacturing & Wholesale Goods"
        },
        {
            "category":"Home & Garden",
            "subcategory":"Garden Supply",
            "type":"Retail Goods"
        },
        {
            "category":"Wholesale",
            "subcategory":"Machinery & Supplies",
            "type":"Manufacturing & Wholesale Goods"
        },
        {
            "category":"Retail",
            "subcategory":"Repair Shop",
            "type":"Services"
        },
        {
            "category":"Manufacturing",
            "subcategory":"Tools & Machinery",
            "type":"Manufacturing & Wholesale Goods"
        }
    ],
    "sg:phone":"+1 530 365 8700",
    "sg:postcode":"96007",
    "sg:province":"CA",
    "sg:tags":[
        "renting",
        "repairing",
        "lawn",
        "outdoor",
        "saws-sharpen",
        "generator",
        "power",
        "landscaping",
        "mowers-sharpening",
        "saw",
        "mower",
        "equipment",
        "equipment-sales"
    ],
    "sg:website":"http://www.stihldealer.net/default-dealer-011214.aspx",
    "wof:name":"Quality Saw & Mower",
    "wof:placetype":"venue"
},
  "geometry": {"coordinates":[-122.299797,40.448429],"type":"Point"}
}