{
  "type": "Feature",
  "properties": {
    "addr:full":"1801 E Washington Boulevard Los Angeles CA 90021",
    "addr:housenumber":"1801",
    "addr:postcode":"90021",
    "addr:street":"E Washington Boulevard",
    "iso:country":"US",
    "sg:address":"1801 E Washington Boulevard",
    "sg:city":"Los Angeles",
    "sg:classifiers":[
        {
            "category":"Food & Beverages",
            "subcategory":"Groceries & Convenience Stores",
            "type":"Retail Goods"
        }
    ],
    "sg:phone":"+1 213 746 7535",
    "sg:postcode":"90021",
    "sg:province":"CA",
    "wof:name":"D P Trading",
    "wof:placetype":"venue"
},
  "geometry": {"coordinates":[-118.241131,34.02039],"type":"Point"}
}