{
  "type": "Feature",
  "properties": {
    "iso:country":"US",
    "sg:address":"11515 Knott Ave",
    "sg:city":"Cypress",
    "sg:classifiers":[
        {
            "category":"Bakery",
            "type":"Food & Drink"
        }
    ],
    "sg:phone":"+1 714 903 8193",
    "sg:postcode":"90630",
    "sg:province":"CA",
    "wof:name":"Amy's Donuts",
    "wof:placetype":"venue"
},
  "geometry": {"coordinates":[-118.014999,33.794102],"type":"Point"}
}