{
  "type": "Feature",
  "properties": {
    "iso:country":"US",
    "sg:address":"80457 Muirfield Dr",
    "sg:city":"Indio",
    "sg:classifiers":[
        {
            "category":"Manufacturing",
            "subcategory":"Metals",
            "type":"Manufacturing & Wholesale Goods"
        }
    ],
    "sg:phone":"+1 760 345 7229",
    "sg:postcode":"92201",
    "sg:province":"CA",
    "sg:tags":[
        "steel",
        "foundry"
    ],
    "wof:name":"Ahrens Micromill",
    "wof:placetype":"venue"
},
  "geometry": {"coordinates":[-116.261036,33.727156],"type":"Point"}
}