{
  "type": "Feature",
  "properties": {
    "iso:country":"US",
    "sg:address":"215 N Shakespeare St",
    "sg:city":"Fullerton",
    "sg:classifiers":[
        {
            "category":"Building & Trades",
            "subcategory":"Construction",
            "type":"Services"
        }
    ],
    "sg:phone":"+1 714 992 1258",
    "sg:postcode":"92831",
    "sg:province":"CA",
    "sg:tags":[
        "contractor"
    ],
    "sg:website":"www.Denkersgaragedoors.com",
    "wof:name":"Denkers Garage Doors",
    "wof:placetype":"venue"
},
  "geometry": {"coordinates":[-117.877076,33.84281],"type":"Point"}
}