{
  "type": "Feature",
  "properties": {
    "addr:full":"23162 Los Alisos Blvd Mission Viejo CA 92691",
    "addr:housenumber":"23162",
    "addr:postcode":"92691",
    "addr:street":"Los Alisos Blvd",
    "iso:country":"US",
    "sg:address":"23162 Los Alisos Blvd",
    "sg:city":"Mission Viejo",
    "sg:classifiers":[
        {
            "category":"Personal",
            "subcategory":"Beauty Salon",
            "type":"Services"
        }
    ],
    "sg:phone":"+1 949 380 0222",
    "sg:postcode":"92691",
    "sg:province":"CA",
    "sg:tags":[
        "hair"
    ],
    "sg:website":"femmechicsalon.com",
    "wof:name":"Femme Chic Salon",
    "wof:placetype":"venue"
},
  "geometry": {"coordinates":[-117.677419,33.626412],"type":"Point"}
}