{
  "type": "Feature",
  "properties": {
    "iso:country":"US",
    "sg:address":"2823 Cll Guadalajara",
    "sg:city":"San Clemente",
    "sg:classifiers":[
        {
            "category":"Banks & Credit Unions",
            "subcategory":"Bank",
            "type":"Services"
        }
    ],
    "sg:phone":"+1 949 361 5080",
    "sg:postcode":"92673",
    "sg:province":"CA",
    "sg:tags":[
        "loan",
        "real estate"
    ],
    "wof:name":"First Financial Svc",
    "wof:placetype":"venue"
},
  "geometry": {"coordinates":[-117.63443599999999,33.464318],"type":"Point"}
}