{
  "type": "Feature",
  "properties": {
    "iso:country":"US",
    "sg:address":"977 E Colorado Blvd",
    "sg:city":"Pasadena",
    "sg:classifiers":[
        {
            "category":"Recreation",
            "type":"Entertainment"
        }
    ],
    "sg:phone":"+1 626 792 5050",
    "sg:postcode":"91106",
    "sg:province":"CA",
    "sg:tags":[
        "martial art",
        "instruction"
    ],
    "sg:website":"rogermachado.com/",
    "wof:name":"RCJ Machado Jiu Jitsu",
    "wof:placetype":"venue"
},
  "geometry": {"coordinates":[-118.129997,34.146],"type":"Point"}
}