{
  "type": "Feature",
  "properties": {
    "iso:country":"US",
    "sg:address":"1982 Concord Ave",
    "sg:city":"Concord",
    "sg:classifiers":[
        {
            "category":"Real Estate",
            "subcategory":"Real Estate Agent",
            "type":"Services"
        }
    ],
    "sg:phone":"+1 925 680 6374",
    "sg:postcode":"94520",
    "sg:province":"CA",
    "wof:name":"Equity Share Plus",
    "wof:placetype":"venue"
},
  "geometry": {"coordinates":[-122.036135,37.97688],"type":"Point"}
}