{
  "type": "Feature",
  "properties": {
    "addr:full":"2156 Surrey Rd Sacramento CA 95815",
    "addr:housenumber":"2156",
    "addr:postcode":"95815",
    "addr:street":"Surrey Rd",
    "iso:country":"US",
    "sg:address":"2156 Surrey Rd",
    "sg:city":"Sacramento",
    "sg:classifiers":[
        {
            "category":"Building & Trades",
            "subcategory":"Construction",
            "type":"Services"
        }
    ],
    "sg:phone":"+1 916 646 4242",
    "sg:postcode":"95815",
    "sg:province":"CA",
    "wof:name":"Coffey & Sons Roofing Co",
    "wof:placetype":"venue"
},
  "geometry": {"coordinates":[-121.421566,38.603713],"type":"Point"}
}