{
  "type": "Feature",
  "properties": {
    "addr:full":"140 W Ontario Ave Suite 105 Corona CA 92882",
    "addr:housenumber":"140",
    "addr:postcode":"92882",
    "addr:street":"W Ontario Ave Suite 105",
    "iso:country":"US",
    "sg:address":"140 W Ontario Ave Suite 105",
    "sg:city":"Corona",
    "sg:classifiers":[
        {
            "category":"Health Services",
            "subcategory":"Dentist",
            "type":"Services"
        }
    ],
    "sg:phone":"+1 866 643 7971",
    "sg:postcode":"92882",
    "sg:province":"CA",
    "sg:tags":[
        "dentists-orthodontists",
        "dental",
        "clinic",
        "dentists-pediatric",
        "dentistry"
    ],
    "sg:website":"http://www-brightnow-com.netsolads.com/?_nsag=32894",
    "wof:name":"Bright Now Dental",
    "wof:placetype":"venue"
},
  "geometry": {"coordinates":[-117.569408,33.856356],"type":"Point"}
}