{
  "type": "Feature",
  "properties": {
    "iso:country":"US",
    "sg:address":"1720 W Highland Ave",
    "sg:city":"San Bernardino",
    "sg:classifiers":[
        {
            "category":"Home & Garden",
            "subcategory":"Carpets & Floor Coverings",
            "type":"Retail Goods"
        }
    ],
    "sg:phone":"+1 909 887 6008",
    "sg:postcode":"92411",
    "sg:province":"CA",
    "sg:tags":[
        "rug"
    ],
    "wof:name":"H & S Carpet Upholstery",
    "wof:placetype":"venue"
},
  "geometry": {"coordinates":[-117.324277,34.136215],"type":"Point"}
}