{
  "type": "Feature",
  "properties": {
    "addr:full":"2230 22nd Ave San Francisco CA 94116",
    "addr:housenumber":"2230",
    "addr:postcode":"94116",
    "addr:street":"22Nd Ave",
    "iso:country":"US",
    "sg:address":"2230 22nd Ave",
    "sg:city":"San Francisco",
    "sg:classifiers":[
        {
            "category":"Retail",
            "subcategory":"Auto Repair",
            "type":"Services"
        }
    ],
    "sg:phone":"+1 415 336 6604",
    "sg:postcode":"94116",
    "sg:province":"CA",
    "sg:tags":[
        "wrecker"
    ],
    "wof:name":"Emile's Towing",
    "wof:placetype":"venue"
},
  "geometry": {"coordinates":[-122.47899200000001,37.745349],"type":"Point"}
}