{
  "type": "Feature",
  "properties": {
    "iso:country":"US",
    "sg:address":"15179 Ave 280",
    "sg:city":"Visalia",
    "sg:classifiers":[
        {
            "category":"Building & Trades",
            "subcategory":"Construction",
            "type":"Services"
        }
    ],
    "sg:phone":"+1 559 747 0717",
    "sg:postcode":"93292",
    "sg:province":"CA",
    "wof:name":"S L Miller Inc",
    "wof:placetype":"venue"
},
  "geometry": {"coordinates":[-119.236349,36.298017],"type":"Point"}
}