{
  "type": "Feature",
  "properties": {
    "iso:country":"US",
    "sg:address":"1028 Crenshaw Blvd",
    "sg:city":"Torrance",
    "sg:classifiers":[
        {
            "category":"Health Services",
            "subcategory":"Chiropractor",
            "type":"Services"
        }
    ],
    "sg:phone":"+1 310 374 0771",
    "sg:postcode":"90501",
    "sg:province":"CA",
    "wof:name":"Danner Chiropractic",
    "wof:placetype":"venue"
},
  "geometry": {"coordinates":[-118.32859,33.836565],"type":"Point"}
}