{
  "type": "Feature",
  "properties": {
    "addr:full":"3215 Fulton Ave Sacramento CA 95821",
    "addr:housenumber":"3215",
    "addr:postcode":"95821",
    "addr:street":"Fulton Ave",
    "iso:country":"US",
    "sg:address":"3215 Fulton Ave",
    "sg:city":"Sacramento",
    "sg:classifiers":[
        {
            "category":"Autos & Motor Vehicles",
            "subcategory":"Automobile Sales",
            "type":"Retail Goods"
        }
    ],
    "sg:phone":"+1 916 979 9474",
    "sg:postcode":"95821",
    "sg:province":"CA",
    "sg:tags":[
        "used",
        "car",
        "dealers-used",
        "new",
        "cars-wholesale"
    ],
    "wof:name":"H & H Mirage Auto Sales",
    "wof:placetype":"venue"
},
  "geometry": {"coordinates":[-121.401454,38.624017],"type":"Point"}
}