{
  "type": "Feature",
  "properties": {
    "addr:full":"543 S McCall Ave Sanger CA 93657",
    "addr:housenumber":"543",
    "addr:postcode":"ca 93657",
    "addr:street":"S Mccall Ave",
    "iso:country":"US",
    "sg:address":"543 S McCall Ave",
    "sg:city":"Sanger",
    "sg:classifiers":[
        {
            "category":"Farming",
            "subcategory":"Farm",
            "type":"Manufacturing & Wholesale Goods"
        }
    ],
    "sg:phone":"+1 559 252 2203",
    "sg:postcode":"93657",
    "sg:province":"CA",
    "sg:tags":[
        "crop",
        "general"
    ],
    "wof:name":"Metzger Farms",
    "wof:placetype":"venue"
},
  "geometry": {"coordinates":[-119.61018199999999,36.722026],"type":"Point"}
}