{
  "type": "Feature",
  "properties": {
    "iso:country":"US",
    "sg:address":"22633 Normandie Ave",
    "sg:city":"Torrance",
    "sg:classifiers":[
        {
            "category":"Retail",
            "subcategory":"Auto Repair",
            "type":"Services"
        }
    ],
    "sg:phone":"+1 310 212 6644",
    "sg:postcode":"90501",
    "sg:province":"CA",
    "wof:name":"John's Auto Care",
    "wof:placetype":"venue"
},
  "geometry": {"coordinates":[-118.298621,33.820459],"type":"Point"}
}