{
  "type": "Feature",
  "properties": {
    "iso:country":"US",
    "sg:address":"1881 Walters Ct",
    "sg:city":"Fairfield",
    "sg:classifiers":[
        {
            "category":"Retail",
            "subcategory":"Auto Repair",
            "type":"Services"
        }
    ],
    "sg:phone":"+1 707 425 2007",
    "sg:postcode":"94533",
    "sg:province":"CA",
    "sg:tags":[
        "repairing",
        "automobile"
    ],
    "wof:name":"Smith Auto Svc",
    "wof:placetype":"venue"
},
  "geometry": {"coordinates":[-121.994353,38.269914],"type":"Point"}
}