{
  "type": "Feature",
  "properties": {
    "addr:full":"16547 Creekside Dr Sonora CA 95370",
    "addr:housenumber":"16547",
    "addr:postcode":"95370",
    "addr:street":"Creekside Dr",
    "iso:country":"US",
    "sg:address":"16547 Creekside Dr",
    "sg:city":"Sonora",
    "sg:classifiers":[
        {
            "category":"Utilities",
            "subcategory":"Water",
            "type":"Services"
        }
    ],
    "sg:phone":"+1 209 533 4787",
    "sg:postcode":"95370",
    "sg:province":"CA",
    "sg:tags":[
        "company",
        "sewage"
    ],
    "wof:name":"Sonora Meadows Mutual Water Co",
    "wof:placetype":"venue"
},
  "geometry": {"coordinates":[-120.273571,38.015588],"type":"Point"}
}