{
  "type": "Feature",
  "properties": {
    "addr:full":"550 E 8th St National City CA 91950",
    "addr:housenumber":"550",
    "addr:postcode":"91950",
    "addr:street":"E 8Th St",
    "iso:country":"US",
    "sg:address":"550 E 8th St",
    "sg:city":"National City",
    "sg:classifiers":[
        {
            "category":"Wholesale",
            "subcategory":"Machinery & Supplies",
            "type":"Manufacturing & Wholesale Goods"
        }
    ],
    "sg:phone":"+1 619 477 8891",
    "sg:postcode":"91950",
    "sg:province":"CA",
    "sg:tags":[
        "cargo",
        "container",
        "freight"
    ],
    "wof:name":"Atlas Shippers Intl Inc",
    "wof:placetype":"venue"
},
  "geometry": {"coordinates":[-117.101208,32.677338],"type":"Point"}
}