{
  "type": "Feature",
  "properties": {
    "addr:full":"16010 Via Este Sonora CA 95370",
    "addr:housenumber":"16010",
    "addr:postcode":"95370",
    "addr:street":"Via Este",
    "iso:country":"US",
    "sg:address":"16010 Via Este",
    "sg:city":"Sonora",
    "sg:classifiers":[
        {
            "category":"Shopping",
            "type":"Retail Goods"
        }
    ],
    "sg:phone":"+1 209 532 7724",
    "sg:postcode":"95370",
    "sg:province":"CA",
    "sg:tags":[
        "spa",
        "hot",
        "tub"
    ],
    "wof:name":"Spa & Pool Works",
    "wof:placetype":"venue"
},
  "geometry": {"coordinates":[-120.291963,37.983472],"type":"Point"}
}