{
  "type": "Feature",
  "properties": {
    "addr:full":"327 S Anaheim Blvd Anaheim CA 92805",
    "addr:housenumber":"327",
    "addr:postcode":"92805",
    "addr:street":"S Anaheim Blvd",
    "iso:country":"US",
    "sg:address":"327 S Anaheim Blvd",
    "sg:city":"Anaheim",
    "sg:classifiers":[
        {
            "category":"Restaurant",
            "type":"Food & Drink"
        }
    ],
    "sg:menulink":"http://www.allmenus.com/ca/anaheim-santa-ana-garden-grove/123648-quiznos-sub/menu/",
    "sg:phone":"+1 714 520 0600",
    "sg:postcode":"92805",
    "sg:province":"CA",
    "sg:tags":[
        "wrap",
        "american",
        "sandwich"
    ],
    "wof:name":"Quiznos Sub",
    "wof:placetype":"venue"
},
  "geometry": {"coordinates":[-117.913042,33.832858],"type":"Point"}
}