{
  "type": "Feature",
  "properties": {
    "addr:full":"1615 McAllister St San Francisco CA 94117",
    "addr:housenumber":"1615",
    "addr:postcode":"94117",
    "addr:street":"Mcallister St",
    "iso:country":"US",
    "sg:address":"1615 McAllister St",
    "sg:city":"San Francisco",
    "sg:classifiers":[
        {
            "category":"Personal",
            "subcategory":"Barber",
            "type":"Services"
        }
    ],
    "sg:phone":"+1 415 203 1125",
    "sg:postcode":"94117",
    "sg:province":"CA",
    "wof:name":"Ce's Place",
    "wof:placetype":"venue"
},
  "geometry": {"coordinates":[-122.43875,37.777751],"type":"Point"}
}