{
  "type": "Feature",
  "properties": {
    "iso:country":"US",
    "sg:address":"909 S Harbor Blvd",
    "sg:city":"Anaheim",
    "sg:classifiers":[
        {
            "category":"Travel",
            "subcategory":"Hotels & Motels",
            "type":"Entertainment"
        }
    ],
    "sg:phone":"+1 714 778 5770",
    "sg:postcode":"92805",
    "sg:province":"CA",
    "sg:tags":[
        "operation"
    ],
    "wof:name":"Classic Motel",
    "wof:placetype":"venue"
},
  "geometry": {"coordinates":[-117.915414,33.818187],"type":"Point"}
}