{
  "type": "Feature",
  "properties": {
    "addr:full":"2311 W Burbank Blvd Burbank CA 91506",
    "addr:housenumber":"2311",
    "addr:postcode":"91506",
    "addr:street":"W Burbank Blvd",
    "iso:country":"US",
    "sg:address":"2311 W Burbank Blvd",
    "sg:city":"Burbank",
    "sg:classifiers":[
        {
            "category":"Retail",
            "subcategory":"Repair Shop",
            "type":"Services"
        },
        {
            "category":"Professional",
            "subcategory":"Business Services",
            "type":"Services"
        }
    ],
    "sg:phone":"+1 818 846 0875",
    "sg:postcode":"91506",
    "sg:province":"CA",
    "sg:tags":[
        "sewing",
        "cleaners-wholesale",
        "cleaners-repair",
        "machines-service",
        "vacuum",
        "manufacturer"
    ],
    "sg:website":"http://coolvacuums.com",
    "wof:name":"Cool Vacuum & Sewing",
    "wof:placetype":"venue"
},
  "geometry": {"coordinates":[-118.33618,34.179386],"type":"Point"}
}