{
  "type": "Feature",
  "properties": {
    "iso:country":"US",
    "sg:address":"195 N Mooney Blvd",
    "sg:city":"Tulare",
    "sg:classifiers":[
        {
            "category":"Shopping",
            "subcategory":"Florist",
            "type":"Retail Goods"
        }
    ],
    "sg:phone":"+1 559 687 2809",
    "sg:postcode":"93274",
    "sg:province":"CA",
    "wof:name":"Fonsy's Flowers",
    "wof:placetype":"venue"
},
  "geometry": {"coordinates":[-119.313075,36.211523],"type":"Point"}
}