{
  "type": "Feature",
  "properties": {
    "iso:country":"US",
    "sg:address":"10080 United Pl",
    "sg:city":"Cupertino",
    "sg:classifiers":[
        {
            "category":"Wholesale",
            "subcategory":"Computers",
            "type":"Manufacturing & Wholesale Goods"
        }
    ],
    "sg:phone":"+1 408 626 9323",
    "sg:postcode":"95014",
    "sg:province":"CA",
    "sg:tags":[
        "equipment"
    ],
    "wof:name":"Etherlinx Communications Inc",
    "wof:placetype":"venue"
},
  "geometry": {"coordinates":[-122.04221099999999,37.324622],"type":"Point"}
}