{
  "type": "Feature",
  "properties": {
    "addr:full":"1903 S Cabrillo Ave San Pedro CA 90731",
    "addr:housenumber":"1903",
    "addr:postcode":"90731",
    "addr:street":"S Cabrillo Ave",
    "iso:country":"US",
    "sg:address":"1903 S Cabrillo Ave",
    "sg:city":"San Pedro",
    "sg:classifiers":[
        {
            "category":"Organizations",
            "subcategory":"Community Association",
            "type":"Services"
        }
    ],
    "sg:phone":"+1 310 831 3183",
    "sg:postcode":"90731",
    "sg:province":"CA",
    "sg:tags":[
        "club"
    ],
    "wof:name":"Italian American Club",
    "wof:placetype":"venue"
},
  "geometry": {"coordinates":[-118.294583,33.727895],"type":"Point"}
}