{
  "type": "Feature",
  "properties": {
    "addr:full":"7250 Elk Grove Florin Rd Sacramento CA 95829",
    "addr:housenumber":"7250",
    "addr:postcode":"95829",
    "addr:street":"Elk Grove Florin Rd",
    "iso:country":"US",
    "sg:address":"7250 Elk Grove Florin Rd",
    "sg:city":"Sacramento",
    "sg:classifiers":[
        {
            "category":"Government",
            "subcategory":"Post Office",
            "type":"Public Place"
        }
    ],
    "sg:phone":"+1 916 227 6510",
    "sg:postcode":"95829",
    "sg:province":"CA",
    "wof:name":"US Post Office",
    "wof:placetype":"venue"
},
  "geometry": {"coordinates":[-121.372107,38.489056],"type":"Point"}
}