{
  "type": "Feature",
  "properties": {
    "iso:country":"US",
    "sg:address":"8936 S Sepulveda Blvd",
    "sg:city":"Los Angeles",
    "sg:classifiers":[
        {
            "category":"Insurance",
            "subcategory":"Insurance Agent",
            "type":"Services"
        }
    ],
    "sg:phone":"+1 310 641 9600",
    "sg:postcode":"90045",
    "sg:province":"CA",
    "wof:name":"Anthony Henley Insurance",
    "wof:placetype":"venue"
},
  "geometry": {"coordinates":[-118.396049,33.957147],"type":"Point"}
}