{
  "type": "Feature",
  "properties": {
    "iso:country":"US",
    "sg:address":"4405 Manchester Ave",
    "sg:city":"Encinitas",
    "sg:classifiers":[
        {
            "category":"Building & Trades",
            "subcategory":"Construction",
            "type":"Services"
        }
    ],
    "sg:phone":"+1 760 436 1454",
    "sg:postcode":"92024",
    "sg:province":"CA",
    "sg:tags":[
        "residential"
    ],
    "wof:name":"Dolphin Communities LLC",
    "wof:placetype":"venue"
},
  "geometry": {"coordinates":[-117.238899,33.036512],"type":"Point"}
}