{
  "type": "Feature",
  "properties": {
    "addr:full":"3075 Citrus Cir Walnut Creek CA 94598",
    "addr:housenumber":"3075",
    "addr:postcode":"94598",
    "addr:street":"Citrus Cir",
    "iso:country":"US",
    "sg:address":"3075 Citrus Cir",
    "sg:city":"Walnut Creek",
    "sg:classifiers":[
        {
            "category":"Utilities",
            "subcategory":"Telephone",
            "type":"Services"
        }
    ],
    "sg:phone":"+1 925 935 1507",
    "sg:postcode":"94598",
    "sg:province":"CA",
    "sg:tags":[
        "telecommunication"
    ],
    "wof:name":"MCI",
    "wof:placetype":"venue"
},
  "geometry": {"coordinates":[-122.01478,37.92871],"type":"Point"}
}