{
  "type": "Feature",
  "properties": {
    "iso:country":"US",
    "sg:address":"2125 James St",
    "sg:city":"Martinez",
    "sg:classifiers":[
        {
            "category":"Professional",
            "type":"Services"
        }
    ],
    "sg:phone":"+1 925 228 0132",
    "sg:postcode":"94553",
    "sg:province":"CA",
    "wof:name":"Radioactive PC Systems",
    "wof:placetype":"venue"
},
  "geometry": {"coordinates":[-122.122691,38.004305],"type":"Point"}
}