{
  "type": "Feature",
  "properties": {
    "iso:country":"US",
    "sg:address":"2354 Pheasant Run Cir",
    "sg:city":"Stockton",
    "sg:classifiers":[
        {
            "category":"Building & Trades",
            "subcategory":"Construction",
            "type":"Services"
        }
    ],
    "sg:phone":"+1 209 478 7141",
    "sg:postcode":"95207",
    "sg:province":"CA",
    "sg:tags":[
        "contractor"
    ],
    "wof:name":"Bruce Salisbury Building Contr",
    "wof:placetype":"venue"
},
  "geometry": {"coordinates":[-121.33767899999999,37.99507],"type":"Point"}
}