{
  "type": "Feature",
  "properties": {
    "iso:country":"US",
    "sg:address":"2120 Robinson St",
    "sg:city":"Oroville",
    "sg:classifiers":[
        {
            "category":"Government",
            "subcategory":"Office",
            "type":"Public Place"
        }
    ],
    "sg:phone":"+1 530 538 7753",
    "sg:postcode":"95965",
    "sg:province":"CA",
    "wof:name":"Butte County Office Of Educ",
    "wof:placetype":"venue"
},
  "geometry": {"coordinates":[-121.552544,39.513108],"type":"Point"}
}