{
  "type": "Feature",
  "properties": {
    "addr:full":"901 San Bernardino Rd # 104 Upland CA 91786",
    "addr:housenumber":"901",
    "addr:postcode":"91786",
    "addr:street":"San Bernardino Rd # 104",
    "iso:country":"US",
    "sg:address":"901 San Bernardino Rd # 104",
    "sg:city":"Upland",
    "sg:classifiers":[
        {
            "category":"Health Services",
            "subcategory":"Doctor",
            "type":"Services"
        },
        {
            "category":"Health Services",
            "subcategory":"Clinic",
            "type":"Services"
        },
        {
            "category":"Health Services",
            "subcategory":"Podiatrist",
            "type":"Services"
        }
    ],
    "sg:phone":"+1 909 946 6643",
    "sg:postcode":"91786",
    "sg:province":"CA",
    "sg:tags":[
        "physician",
        "medical",
        "surgeons",
        "surgeon"
    ],
    "sg:website":"http://www.lisafox.com",
    "wof:name":"Carey Bledsoe Dpm",
    "wof:placetype":"venue"
},
  "geometry": {"coordinates":[-117.639038,34.100101],"type":"Point"}
}