{
  "type": "Feature",
  "properties": {
    "iso:country":"US",
    "sg:address":"2951 Union Ave",
    "sg:city":"San Jose",
    "sg:classifiers":[
        {
            "category":"Building & Trades",
            "subcategory":"Locksmith",
            "type":"Services"
        }
    ],
    "sg:phone":"+1 408 377 9210",
    "sg:postcode":"95124",
    "sg:province":"CA",
    "sg:tags":[
        "key"
    ],
    "sg:website":"www.bakers-locksmith.com/",
    "wof:name":"Baker's Lock & Key Service",
    "wof:placetype":"venue"
},
  "geometry": {"coordinates":[-121.931,37.268398],"type":"Point"}
}