{
  "type": "Feature",
  "properties": {
    "addr:full":"619 C Street San Diego CA 92101",
    "addr:housenumber":"619",
    "addr:postcode":"92101",
    "addr:street":"C Street",
    "iso:country":"US",
    "sg:address":"619 C Street",
    "sg:city":"San Diego",
    "sg:classifiers":[
        {
            "category":"Shopping",
            "subcategory":"Bicycles & Sporting Goods",
            "type":"Retail Goods"
        },
        {
            "category":"Sports & Exercise",
            "subcategory":"Bicycle Rental",
            "type":"Entertainment"
        }
    ],
    "sg:phone":"+1 619 237 1245",
    "sg:postcode":"92101",
    "sg:province":"CA",
    "sg:tags":[
        "bike"
    ],
    "sg:website":"www.sdbikeshop.com",
    "wof:name":"San Diego Bike Shop",
    "wof:placetype":"venue"
},
  "geometry": {"coordinates":[-117.158962,32.716575],"type":"Point"}
}