{
  "type": "Feature",
  "properties": {
    "iso:country":"US",
    "sg:address":"3530 Wilshire Blvd",
    "sg:city":"Los Angeles",
    "sg:classifiers":[
        {
            "category":"Insurance",
            "subcategory":"Health Insurance",
            "type":"Services"
        }
    ],
    "sg:phone":"+1 213 738 1968",
    "sg:postcode":"90010",
    "sg:province":"CA",
    "sg:tags":[
        "market"
    ],
    "wof:name":"M-Co USA",
    "wof:placetype":"venue"
},
  "geometry": {"coordinates":[-118.30100299999999,34.061699],"type":"Point"}
}