{
  "type": "Feature",
  "properties": {
    "iso:country":"US",
    "sg:address":"10181 Carriage Rd",
    "sg:city":"Grass Valley",
    "sg:classifiers":[
        {
            "category":"Farming",
            "subcategory":"Livestock Farm",
            "type":"Manufacturing & Wholesale Goods"
        }
    ],
    "sg:phone":"+1 530 268 7777",
    "sg:postcode":"95949",
    "sg:province":"CA",
    "sg:tags":[
        "animal",
        "general"
    ],
    "wof:name":"Carriage Ranch",
    "wof:placetype":"venue"
},
  "geometry": {"coordinates":[-121.083787,39.072746],"type":"Point"}
}