{
  "type": "Feature",
  "properties": {
    "iso:country":"US",
    "sg:address":"32295 Mission Trl",
    "sg:city":"Lake Elsinore",
    "sg:classifiers":[
        {
            "category":"Shopping",
            "subcategory":"Tobacco",
            "type":"Retail Goods"
        }
    ],
    "sg:phone":"+1 951 245 6277",
    "sg:postcode":"92530",
    "sg:province":"CA",
    "sg:tags":[
        "shop"
    ],
    "wof:name":"Tobacco Star",
    "wof:placetype":"venue"
},
  "geometry": {"coordinates":[-117.296997,33.652802],"type":"Point"}
}