{
  "type": "Feature",
  "properties": {
    "addr:full":"27401 Los Altos Mission Viejo CA 92691",
    "addr:housenumber":"27401",
    "addr:postcode":"92691",
    "addr:street":"Los Altos",
    "iso:country":"US",
    "sg:address":"27401 Los Altos",
    "sg:city":"Mission Viejo",
    "sg:classifiers":[
        {
            "category":"Health Services",
            "subcategory":"Chiropractor",
            "type":"Services"
        }
    ],
    "sg:phone":"+1 949 716 4141",
    "sg:postcode":"92691",
    "sg:province":"CA",
    "wof:name":"Veleas Darius D C DR",
    "wof:placetype":"venue"
},
  "geometry": {"coordinates":[-117.666377,33.565178],"type":"Point"}
}