{
  "type": "Feature",
  "properties": {
    "iso:country":"US",
    "sg:address":"871 Via Esteban",
    "sg:city":"San Luis Obispo",
    "sg:classifiers":[
        {
            "category":"Manufacturing",
            "subcategory":"Musical Instruments",
            "type":"Manufacturing & Wholesale Goods"
        }
    ],
    "sg:phone":"+1 805 546 8442",
    "sg:postcode":"93401",
    "sg:province":"CA",
    "sg:website":"www.nationalguitars.com",
    "wof:name":"National Reso-Phonic Guitars",
    "wof:placetype":"venue"
},
  "geometry": {"coordinates":[-120.64388700000001,35.258971],"type":"Point"}
}