{
  "type": "Feature",
  "properties": {
    "iso:country":"US",
    "sg:address":"1625 The Alameda Suite 510",
    "sg:city":"San Jose",
    "sg:classifiers":[
        {
            "category":"Professional",
            "subcategory":"Lawyer & Legal Services",
            "type":"Services"
        }
    ],
    "sg:phone":"+1 408 295 0151",
    "sg:postcode":"95126",
    "sg:province":"CA",
    "sg:tags":[
        "divorce",
        "law",
        "family"
    ],
    "wof:name":"Law Office of Merrill M Hirsch",
    "wof:placetype":"venue"
},
  "geometry": {"coordinates":[-121.917126,37.335665],"type":"Point"}
}