{
  "type": "Feature",
  "properties": {
    "iso:country":"US",
    "sg:address":"3980 E Ocean Blvd",
    "sg:city":"Long Beach",
    "sg:classifiers":[
        {
            "category":"Restaurant",
            "type":"Food & Drink"
        }
    ],
    "sg:menulink":"http://www.allmenus.com/ca/long-beach-lakewood/178072-jack-in-the-box/menu/",
    "sg:phone":"+1 562 439 6798",
    "sg:postcode":"90803",
    "sg:province":"CA",
    "sg:tags":[
        "burger",
        "american"
    ],
    "wof:name":"Jack in the Box",
    "wof:placetype":"venue"
},
  "geometry": {"coordinates":[-118.146308,33.759626],"type":"Point"}
}