{
  "type": "Feature",
  "properties": {
    "addr:full":"46211 Research Ave Fremont CA 94539",
    "addr:housenumber":"46211",
    "addr:postcode":"94539",
    "addr:street":"Research Ave",
    "iso:country":"US",
    "sg:address":"46211 Research Ave",
    "sg:city":"Fremont",
    "sg:classifiers":[
        {
            "category":"Manufacturing",
            "subcategory":"Textiles",
            "type":"Manufacturing & Wholesale Goods"
        },
        {
            "category":"Building & Trades",
            "subcategory":"Construction",
            "type":"Services"
        }
    ],
    "sg:phone":"+1 510 252 8500",
    "sg:postcode":"94539",
    "sg:province":"CA",
    "sg:tags":[
        "tile-wholesale",
        "manufacturer",
        "tile-contractors"
    ],
    "wof:name":"Ceramic Tech, Inc.",
    "wof:placetype":"venue"
},
  "geometry": {"coordinates":[-121.92562100000001,37.495935],"type":"Point"}
}