{
  "type": "Feature",
  "properties": {
    "addr:full":"1929 Francisco St Berkeley CA 94709",
    "addr:housenumber":"1929",
    "addr:postcode":"94709",
    "addr:street":"Francisco St",
    "iso:country":"US",
    "sg:address":"1929 Francisco St",
    "sg:city":"Berkeley",
    "sg:classifiers":[
        {
            "category":"Home & Garden",
            "subcategory":"Furniture",
            "type":"Retail Goods"
        },
        {
            "category":"Wholesale",
            "subcategory":"Home Furnishings",
            "type":"Manufacturing & Wholesale Goods"
        }
    ],
    "sg:phone":"+1 510 549 9600",
    "sg:postcode":"94709",
    "sg:province":"CA",
    "sg:tags":[
        "equipment-wholesale",
        "kitchen",
        "equipment-household",
        "manufacturer",
        "cabinet"
    ],
    "wof:name":"Caseys Custom Cabinets",
    "wof:placetype":"venue"
},
  "geometry": {"coordinates":[-122.272749,37.875193],"type":"Point"}
}