{
  "type": "Feature",
  "properties": {
    "addr:full":"8929 S Sepulveda Boulevard Los Angeles CA 90045",
    "addr:housenumber":"8929",
    "addr:postcode":"90045",
    "addr:street":"S Sepulveda Boulevard",
    "iso:country":"US",
    "sg:address":"8929 S Sepulveda Boulevard",
    "sg:city":"Los Angeles",
    "sg:classifiers":[
        {
            "category":"Professional",
            "subcategory":"Accounting & Tax Preparation",
            "type":"Services"
        }
    ],
    "sg:phone":"+1 310 215 3985",
    "sg:postcode":"90045",
    "sg:province":"CA",
    "sg:tags":[
        "accountant"
    ],
    "wof:name":"Hodges Jerry CPA",
    "wof:placetype":"venue"
},
  "geometry": {"coordinates":[-118.396227,33.955436],"type":"Point"}
}