{
  "type": "Feature",
  "properties": {
    "iso:country":"US",
    "sg:address":"11526 Burbank Blvd",
    "sg:city":"North Hollywood",
    "sg:classifiers":[
        {
            "category":"Professional",
            "subcategory":"Business Services",
            "type":"Services"
        }
    ],
    "sg:phone":"+1 818 754 0074",
    "sg:postcode":"91601",
    "sg:province":"CA",
    "sg:tags":[
        "broker",
        "merchandise"
    ],
    "wof:name":"Mexican Film Brokers LTD",
    "wof:placetype":"venue"
},
  "geometry": {"coordinates":[-118.382559,34.172079],"type":"Point"}
}