{
  "type": "Feature",
  "properties": {
    "addr:full":"4007 S San Pedro St Los Angeles CA 90011",
    "addr:housenumber":"4007",
    "addr:postcode":"90011",
    "addr:street":"S San Pedro St",
    "iso:country":"US",
    "sg:address":"4007 S San Pedro St",
    "sg:city":"Los Angeles",
    "sg:classifiers":[
        {
            "category":"Banks & Credit Unions",
            "subcategory":"Bank",
            "type":"Services"
        }
    ],
    "sg:phone":"+1 323 233 3120",
    "sg:postcode":"90011",
    "sg:province":"CA",
    "sg:tags":[
        "cashing",
        "check"
    ],
    "wof:name":"Mexico Check Cashing",
    "wof:placetype":"venue"
},
  "geometry": {"coordinates":[-118.26855500000001,34.010358],"type":"Point"}
}