{
  "type": "Feature",
  "properties": {
    "addr:full":"7050 Madden Ave Los Angeles CA 90043",
    "addr:housenumber":"7050",
    "addr:postcode":"90043",
    "addr:street":"Madden Ave",
    "iso:country":"US",
    "sg:address":"7050 Madden Ave",
    "sg:city":"Los Angeles",
    "sg:classifiers":[
        {
            "category":"Health Services",
            "subcategory":"Nursing And Care Facility",
            "type":"Services"
        }
    ],
    "sg:phone":"+1 323 751 7813",
    "sg:postcode":"90043",
    "sg:province":"CA",
    "sg:tags":[
        "skilled"
    ],
    "wof:name":"China Nursing Assoc",
    "wof:placetype":"venue"
},
  "geometry": {"coordinates":[-118.325469,33.975013],"type":"Point"}
}