{
  "type": "Feature",
  "properties": {
    "iso:country":"US",
    "sg:address":"5959 S Hoover St",
    "sg:city":"Los Angeles",
    "sg:classifiers":[
        {
            "category":"Home & Garden",
            "subcategory":"Furniture",
            "type":"Retail Goods"
        }
    ],
    "sg:phone":"+1 323 751 8800",
    "sg:postcode":"90044",
    "sg:province":"CA",
    "wof:name":"L K Furniture",
    "wof:placetype":"venue"
},
  "geometry": {"coordinates":[-118.287098,33.986181],"type":"Point"}
}