{
  "type": "Feature",
  "properties": {
    "iso:country":"US",
    "sg:address":"2050 Auto Park Way",
    "sg:city":"Escondido",
    "sg:classifiers":[
        {
            "category":"Manufacturing",
            "subcategory":"Rubber & Plastics",
            "type":"Manufacturing & Wholesale Goods"
        },
        {
            "category":"Autos & Motor Vehicles",
            "subcategory":"Auto Supplies",
            "type":"Retail Goods"
        }
    ],
    "sg:phone":"+1 760 737 7141",
    "sg:postcode":"92029",
    "sg:province":"CA",
    "sg:tags":[
        "tires-wholesale",
        "tire",
        "manufacturer"
    ],
    "wof:name":"Sd Tires",
    "wof:placetype":"venue"
},
  "geometry": {"coordinates":[-117.11146100000001,33.118272],"type":"Point"}
}