{
  "type": "Feature",
  "properties": {
    "iso:country":"US",
    "sg:address":"660 10th Avenue",
    "sg:city":"San Diego",
    "sg:classifiers":[
        {
            "category":"Shopping",
            "subcategory":"Stationery & Office Supplies",
            "type":"Retail Goods"
        }
    ],
    "sg:phone":"+1 619 234 3262",
    "sg:postcode":"92101",
    "sg:province":"CA",
    "sg:tags":[
        "equipment"
    ],
    "sg:website":"www.farkasstorefixtures.com",
    "wof:name":"Farkas Store Fixtures",
    "wof:placetype":"venue"
},
  "geometry": {"coordinates":[-117.155626,32.712302],"type":"Point"}
}