{
  "type": "Feature",
  "properties": {
    "iso:country":"US",
    "sg:address":"1911 Warmlands Ave",
    "sg:city":"Vista",
    "sg:classifiers":[
        {
            "category":"Professional",
            "subcategory":"Computer Services",
            "type":"Services"
        }
    ],
    "sg:phone":"+1 760 630 5104",
    "sg:postcode":"92084",
    "sg:province":"CA",
    "sg:tags":[
        "consultant",
        "designer"
    ],
    "wof:name":"J Sable Consultants",
    "wof:placetype":"venue"
},
  "geometry": {"coordinates":[-117.216553,33.229135],"type":"Point"}
}