{
  "type": "Feature",
  "properties": {
    "addr:full":"260 Castro St Mountain View CA 94041",
    "addr:housenumber":"260",
    "addr:postcode":"94041",
    "addr:street":"Castro St",
    "iso:country":"US",
    "sg:address":"260 Castro St",
    "sg:city":"Mountain View",
    "sg:classifiers":[
        {
            "category":"Ice Cream",
            "type":"Food & Drink"
        }
    ],
    "sg:postcode":"94041",
    "sg:province":"CA",
    "sg:tags":[
        "frozen",
        "yogurt"
    ],
    "wof:name":"Yoogl Yogurt Cafe",
    "wof:placetype":"venue"
},
  "geometry": {"coordinates":[-122.079465,37.393046],"type":"Point"}
}