{
  "type": "Feature",
  "properties": {
    "iso:country":"US",
    "sg:address":"2A Liberty",
    "sg:city":"Aliso Viejo",
    "sg:classifiers":[
        {
            "category":"Place Of Worship",
            "subcategory":"Synagogue",
            "type":"Public Place"
        }
    ],
    "sg:phone":"+1 949 362 3999",
    "sg:postcode":"92656",
    "sg:province":"CA",
    "wof:name":"Temple Beth El S O C",
    "wof:placetype":"venue"
},
  "geometry": {"coordinates":[-117.729789,33.560575],"type":"Point"}
}