{
  "type": "Feature",
  "properties": {
    "addr:full":"4130 Fremont Hub Fremont CA 94538",
    "addr:housenumber":"4130",
    "addr:postcode":"94538",
    "addr:street":"Fremont Hub",
    "iso:country":"US",
    "sg:address":"4130 Fremont Hub",
    "sg:city":"Fremont",
    "sg:classifiers":[
        {
            "category":"Shopping",
            "subcategory":"Bicycles & Sporting Goods",
            "type":"Retail Goods"
        }
    ],
    "sg:phone":"+1 510 794 1533",
    "sg:postcode":"94538",
    "sg:province":"CA",
    "sg:tags":[
        "equipment",
        "exercise"
    ],
    "wof:name":"Busybody Home Fitness",
    "wof:placetype":"venue"
},
  "geometry": {"coordinates":[-121.99079,37.545722],"type":"Point"}
}