{
  "type": "Feature",
  "properties": {
    "iso:country":"US",
    "sg:address":"6550 Covey Rd",
    "sg:city":"Forestville",
    "sg:classifiers":[
        {
            "category":"Social Services",
            "subcategory":"Adult Care",
            "type":"Services"
        }
    ],
    "sg:phone":"+1 707 887 1070",
    "sg:postcode":"95436",
    "sg:province":"CA",
    "sg:tags":[
        "organization",
        "senior",
        "citizen"
    ],
    "wof:name":"Council On Aging Sonoma County",
    "wof:placetype":"venue"
},
  "geometry": {"coordinates":[-122.890254,38.475044],"type":"Point"}
}