{
  "type": "Feature",
  "properties": {
    "addr:full":"3675 Mt Diablo Blvd Lafayette CA 94549",
    "addr:housenumber":"3675",
    "addr:postcode":"94549",
    "addr:street":"Mt Diablo Blvd",
    "iso:country":"US",
    "sg:address":"3675 Mt Diablo Blvd",
    "sg:city":"Lafayette",
    "sg:classifiers":[
        {
            "category":"Wholesale",
            "subcategory":"Machinery & Supplies",
            "type":"Manufacturing & Wholesale Goods"
        }
    ],
    "sg:phone":"+1 925 299 3259",
    "sg:postcode":"94549",
    "sg:province":"CA",
    "sg:tags":[
        "equipment",
        "establishment"
    ],
    "wof:name":"Lafyte Cty Wrks Maintenance",
    "wof:placetype":"venue"
},
  "geometry": {"coordinates":[-122.12760900000001,37.890746],"type":"Point"}
}