{
  "type": "Feature",
  "properties": {
    "iso:country":"US",
    "sg:address":"2303 Cam Ramon",
    "sg:city":"San Ramon",
    "sg:classifiers":[
        {
            "category":"Banks & Credit Unions",
            "subcategory":"Bank",
            "type":"Services"
        }
    ],
    "sg:phone":"+1 925 242 6000",
    "sg:postcode":"94583",
    "sg:province":"CA",
    "sg:tags":[
        "loan",
        "real estate"
    ],
    "sg:website":"www.broadstreetmortgage.com",
    "wof:name":"Broad Street Mortgage",
    "wof:placetype":"venue"
},
  "geometry": {"coordinates":[-121.967302,37.776957],"type":"Point"}
}