{
  "type": "Feature",
  "properties": {
    "addr:full":"2869 24th St San Francisco CA 94110",
    "addr:housenumber":"2869",
    "addr:postcode":"94110",
    "addr:street":"24Th St",
    "iso:country":"US",
    "sg:address":"2869 24th St",
    "sg:city":"San Francisco",
    "sg:classifiers":[
        {
            "category":"Personal",
            "subcategory":"Beauty Salon",
            "type":"Services"
        }
    ],
    "sg:phone":"+1 415 824 4415",
    "sg:postcode":"94110",
    "sg:province":"CA",
    "wof:name":"International Hair Designer",
    "wof:placetype":"venue"
},
  "geometry": {"coordinates":[-122.409783,37.752686],"type":"Point"}
}