{
  "type": "Feature",
  "properties": {
    "addr:full":"166 N Canon Dr Beverly Hills CA 90210",
    "addr:housenumber":"166",
    "addr:postcode":"90210",
    "addr:street":"N Canon Dr",
    "iso:country":"US",
    "sg:address":"166 N Canon Dr",
    "sg:city":"Beverly Hills",
    "sg:classifiers":[
        {
            "category":"Real Estate",
            "subcategory":"Real Estate Agent",
            "type":"Services"
        }
    ],
    "sg:phone":"+1 310 285 7584",
    "sg:postcode":"90210",
    "sg:province":"CA",
    "wof:name":"Irene Arathoon",
    "wof:placetype":"venue"
},
  "geometry": {"coordinates":[-118.397537,34.06736],"type":"Point"}
}