{
  "type": "Feature",
  "properties": {
    "addr:full":"893 Oak St Costa Mesa CA 92627",
    "addr:housenumber":"893",
    "addr:postcode":"92627",
    "addr:street":"Oak St",
    "iso:country":"US",
    "sg:address":"893 Oak St",
    "sg:city":"Costa Mesa",
    "sg:classifiers":[
        {
            "category":"Building & Trades",
            "subcategory":"Construction",
            "type":"Services"
        }
    ],
    "sg:phone":"+1 949 548 4856",
    "sg:postcode":"92627",
    "sg:province":"CA",
    "sg:tags":[
        "house"
    ],
    "wof:name":"R J Tanner Construction",
    "wof:placetype":"venue"
},
  "geometry": {"coordinates":[-117.93638300000001,33.650141],"type":"Point"}
}