{
  "type": "Feature",
  "properties": {
    "iso:country":"US",
    "sg:address":"645 E Shaw Ave",
    "sg:city":"Fresno",
    "sg:classifiers":[
        {
            "category":"Shopping",
            "subcategory":"Jewelry",
            "type":"Retail Goods"
        }
    ],
    "sg:phone":"+1 559 243 1353",
    "sg:postcode":"93710",
    "sg:province":"CA",
    "sg:tags":[
        "jeweler"
    ],
    "wof:name":"Silver Spot",
    "wof:placetype":"venue"
},
  "geometry": {"coordinates":[-119.772747,36.808484],"type":"Point"}
}