{
  "type": "Feature",
  "properties": {
    "addr:full":"1655 West St Concord CA 94521",
    "addr:housenumber":"1655",
    "addr:postcode":"94521",
    "addr:street":"West St",
    "iso:country":"US",
    "sg:address":"1655 West St",
    "sg:city":"Concord",
    "sg:classifiers":[
        {
            "category":"Organizations",
            "subcategory":"Religious Organization",
            "type":"Services"
        }
    ],
    "sg:phone":"+1 925 676 4111",
    "sg:postcode":"94521",
    "sg:province":"CA",
    "wof:name":"Concord SDA Church",
    "wof:placetype":"venue"
},
  "geometry": {"coordinates":[-121.995133,37.974089],"type":"Point"}
}