{
  "type": "Feature",
  "properties": {
    "addr:full":"1131 Lucinda Way Tustin CA 92780",
    "addr:housenumber":"1131",
    "addr:postcode":"92780",
    "addr:street":"Lucinda Way",
    "iso:country":"US",
    "sg:address":"1131 Lucinda Way",
    "sg:city":"Tustin",
    "sg:classifiers":[
        {
            "category":"Professional",
            "subcategory":"Management & Consulting",
            "type":"Services"
        },
        {
            "category":"Building & Trades",
            "subcategory":"Landscaping Services",
            "type":"Services"
        }
    ],
    "sg:phone":"+1 714 731 6240",
    "sg:postcode":"92780",
    "sg:province":"CA",
    "sg:tags":[
        "tree",
        "business"
    ],
    "wof:name":"Gregory W Applegate",
    "wof:placetype":"venue"
},
  "geometry": {"coordinates":[-117.800387,33.755254],"type":"Point"}
}