{
  "type": "Feature",
  "properties": {
    "iso:country":"US",
    "sg:address":"2940 Jamacha Rd",
    "sg:city":"El Cajon",
    "sg:classifiers":[
        {
            "category":"Personal",
            "subcategory":"Beauty Salon",
            "type":"Services"
        }
    ],
    "sg:phone":"+1 619 818 5326",
    "sg:postcode":"92019",
    "sg:province":"CA",
    "wof:name":"Steve Brundege",
    "wof:placetype":"venue"
},
  "geometry": {"coordinates":[-116.941077,32.739841],"type":"Point"}
}