{
  "type": "Feature",
  "properties": {
    "iso:country":"US",
    "sg:address":"38727 Tierra Subida Ave",
    "sg:city":"Palmdale",
    "sg:classifiers":[
        {
            "category":"Food & Beverages",
            "subcategory":"Groceries & Convenience Stores",
            "type":"Retail Goods"
        }
    ],
    "sg:phone":"+1 661 274 9557",
    "sg:postcode":"93551",
    "sg:province":"CA",
    "sg:tags":[
        "grocer"
    ],
    "wof:name":"Albertsons",
    "wof:placetype":"venue"
},
  "geometry": {"coordinates":[-118.147498,34.584025],"type":"Point"}
}