{
  "type": "Feature",
  "properties": {
    "addr:full":"148 Rudgear Dr Walnut Creek CA 94596",
    "addr:housenumber":"148",
    "addr:postcode":"94596",
    "addr:street":"Rudgear Dr",
    "iso:country":"US",
    "sg:address":"148 Rudgear Dr",
    "sg:city":"Walnut Creek",
    "sg:classifiers":[
        {
            "category":"Home & Garden",
            "subcategory":"Furniture",
            "type":"Retail Goods"
        }
    ],
    "sg:phone":"+1 925 256 1165",
    "sg:postcode":"94596",
    "sg:province":"CA",
    "wof:name":"Heatherstone Manor",
    "wof:placetype":"venue"
},
  "geometry": {"coordinates":[-122.041673,37.879451],"type":"Point"}
}