{
  "type": "Feature",
  "properties": {
    "iso:country":"US",
    "sg:address":"8732 Portafino Pl",
    "sg:city":"Whittier",
    "sg:classifiers":[
        {
            "category":"Professional",
            "subcategory":"Management & Consulting",
            "type":"Services"
        }
    ],
    "sg:phone":"+1 562 947 2777",
    "sg:postcode":"90603",
    "sg:province":"CA",
    "sg:tags":[
        "business"
    ],
    "wof:name":"Louise Coats Consultant",
    "wof:placetype":"venue"
},
  "geometry": {"coordinates":[-117.986363,33.96188],"type":"Point"}
}