{
  "type": "Feature",
  "properties": {
    "addr:full":"110 6th St Broderick CA 95605",
    "addr:housenumber":"110",
    "addr:postcode":"95605",
    "addr:street":"6Th St",
    "iso:country":"US",
    "sg:address":"110 6th St",
    "sg:city":"Broderick",
    "sg:classifiers":[
        {
            "category":"Social Services",
            "type":"Services"
        }
    ],
    "sg:phone":"+1 916 372 0200",
    "sg:postcode":"95605",
    "sg:province":"CA",
    "sg:tags":[
        "organization",
        "welfare"
    ],
    "wof:name":"Broderick Christian Ctr",
    "wof:placetype":"venue"
},
  "geometry": {"coordinates":[-121.51365699999999,38.591561],"type":"Point"}
}