{
  "type": "Feature",
  "properties": {
    "iso:country":"US",
    "sg:address":"13339 Margate St",
    "sg:city":"Van Nuys",
    "sg:classifiers":[
        {
            "category":"Professional",
            "type":"Services"
        }
    ],
    "sg:phone":"+1 818 789 6067",
    "sg:postcode":"91401",
    "sg:province":"CA",
    "wof:name":"Karp Family LLC",
    "wof:placetype":"venue"
},
  "geometry": {"coordinates":[-118.426562,34.167552],"type":"Point"}
}