{
  "type": "Feature",
  "properties": {
    "addr:full":"203 E Ross Rd El Centro CA 92243",
    "addr:housenumber":"203",
    "addr:postcode":"92243",
    "addr:street":"E Ross Rd",
    "iso:country":"US",
    "sg:address":"203 E Ross Rd",
    "sg:city":"El Centro",
    "sg:classifiers":[
        {
            "category":"Manufacturing",
            "subcategory":"Wood Products",
            "type":"Manufacturing & Wholesale Goods"
        }
    ],
    "sg:phone":"+1 760 337 8646",
    "sg:postcode":"92243",
    "sg:province":"CA",
    "sg:tags":[
        "mfg"
    ],
    "wof:name":"A & S Pallets",
    "wof:placetype":"venue"
},
  "geometry": {"coordinates":[-115.517645,32.781428],"type":"Point"}
}