{
  "type": "Feature",
  "properties": {
    "addr:full":"3322 Canonita Dr Fallbrook CA 92028",
    "addr:housenumber":"3322",
    "addr:postcode":"92028",
    "addr:street":"Canonita Dr",
    "iso:country":"US",
    "sg:address":"3322 Canonita Dr",
    "sg:city":"Fallbrook",
    "sg:classifiers":[
        {
            "category":"Banks & Credit Unions",
            "subcategory":"Financial Services",
            "type":"Services"
        }
    ],
    "sg:phone":"+1 760 723 8377",
    "sg:postcode":"92028",
    "sg:province":"CA",
    "sg:tags":[
        "trust",
        "management"
    ],
    "wof:name":"Hansford Family Trust",
    "wof:placetype":"venue"
},
  "geometry": {"coordinates":[-117.18753,33.356272],"type":"Point"}
}