{
  "type": "Feature",
  "properties": {
    "addr:full":"49950 Jefferson St Ste 130 Indio CA 92201",
    "addr:housenumber":"49950",
    "addr:postcode":"92201",
    "addr:street":"Jefferson St Ste 130",
    "iso:country":"US",
    "sg:address":"49950 Jefferson St Ste 130",
    "sg:city":"Indio",
    "sg:classifiers":[
        {
            "category":"Shopping",
            "type":"Retail Goods"
        },
        {
            "category":"Retail",
            "subcategory":"Pet Boarding",
            "type":"Services"
        },
        {
            "category":"Government",
            "subcategory":"Embassy",
            "type":"Public Place"
        },
        {
            "category":"Professional",
            "type":"Services"
        },
        {
            "category":"Professional",
            "subcategory":"Business Services",
            "type":"Services"
        },
        {
            "category":"Professional",
            "subcategory":"Printing & Photocopies",
            "type":"Services"
        },
        {
            "category":"Manufacturing",
            "subcategory":"Paper Products",
            "type":"Manufacturing & Wholesale Goods"
        },
        {
            "category":"Government",
            "subcategory":"Post Office",
            "type":"Public Place"
        }
    ],
    "sg:phone":"+1 760 771 4244",
    "sg:postcode":"92201",
    "sg:province":"CA",
    "sg:tags":[
        "information",
        "fiber",
        "passport",
        "packing",
        "photo",
        "material",
        "mailbox-rental",
        "shipping",
        "duplicating",
        "packaging",
        "boxes-corrugated",
        "crating",
        "copying",
        "notary",
        "mail",
        "receiving",
        "document",
        "visa",
        "destruction"
    ],
    "sg:website":"http://www.postalannex.com/storeindex.asp?storenum=407",
    "wof:name":"PostalAnnex+",
    "wof:placetype":"venue"
},
  "geometry": {"coordinates":[-116.268627,33.686674],"type":"Point"}
}