{
  "type": "Feature",
  "properties": {
    "addr:full":"1832 Wright St Santa Rosa CA 95404",
    "addr:housenumber":"1832",
    "addr:postcode":"ca 95404",
    "addr:street":"Wright St",
    "iso:country":"US",
    "sg:address":"1832 Wright St",
    "sg:city":"Santa Rosa",
    "sg:classifiers":[
        {
            "category":"Shopping",
            "subcategory":"Clothing, Apparel, & Fashions",
            "type":"Retail Goods"
        }
    ],
    "sg:phone":"+1 707 568 1197",
    "sg:postcode":"95404",
    "sg:province":"CA",
    "wof:name":"Barbaras Custom Dress",
    "wof:placetype":"venue"
},
  "geometry": {"coordinates":[-122.709355,38.457742],"type":"Point"}
}