{
  "type": "Feature",
  "properties": {
    "addr:full":"1262 W Foothill Blvd Upland CA 91786",
    "addr:housenumber":"1262",
    "addr:postcode":"91786",
    "addr:street":"W Foothill Blvd",
    "iso:country":"US",
    "sg:address":"1262 W Foothill Blvd",
    "sg:city":"Upland",
    "sg:classifiers":[
        {
            "category":"Restaurant",
            "type":"Food & Drink"
        }
    ],
    "sg:phone":"+1 909 946 9276",
    "sg:postcode":"91786",
    "sg:province":"CA",
    "wof:name":"Jarritos Mexican Restaurant",
    "wof:placetype":"venue"
},
  "geometry": {"coordinates":[-117.670648,34.10689],"type":"Point"}
}