{
  "type": "Feature",
  "properties": {
    "iso:country":"US",
    "sg:address":"3130 E. Colorado Blvd.",
    "sg:city":"Pasadena",
    "sg:classifiers":[
        {
            "category":"Home & Garden",
            "subcategory":"Carpets & Floor Coverings",
            "type":"Retail Goods"
        }
    ],
    "sg:phone":"+1 626 793 9111",
    "sg:postcode":"91107",
    "sg:province":"CA",
    "sg:tags":[
        "mattress"
    ],
    "sg:website":"www.orthomattress.com/",
    "wof:name":"Ortho Mattress",
    "wof:placetype":"venue"
},
  "geometry": {"coordinates":[-118.084869,34.145921],"type":"Point"}
}