{
  "type": "Feature",
  "properties": {
    "iso:country":"US",
    "sg:address":"139 S Beverly Dr",
    "sg:city":"Beverly Hills",
    "sg:classifiers":[
        {
            "category":"Real Estate",
            "subcategory":"Real Estate Agent",
            "type":"Services"
        }
    ],
    "sg:phone":"+1 310 275 1414",
    "sg:postcode":"90212",
    "sg:province":"CA",
    "wof:name":"Kenco Realty",
    "wof:placetype":"venue"
},
  "geometry": {"coordinates":[-118.399125,34.065785],"type":"Point"}
}