{
  "type": "Feature",
  "properties": {
    "iso:country":"US",
    "sg:address":"20301 Ventura Blvd",
    "sg:city":"Woodland Hills",
    "sg:classifiers":[
        {
            "category":"Insurance",
            "subcategory":"Health Insurance",
            "type":"Services"
        }
    ],
    "sg:phone":"+1 818 883 7052",
    "sg:postcode":"91364",
    "sg:province":"CA",
    "sg:tags":[
        "plan"
    ],
    "wof:name":"Time Employee Benefit",
    "wof:placetype":"venue"
},
  "geometry": {"coordinates":[-118.57745300000001,34.168591],"type":"Point"}
}