{
  "type": "Feature",
  "properties": {
    "iso:country":"US",
    "sg:address":"706 W Las Tunas Dr",
    "sg:city":"San Gabriel",
    "sg:classifiers":[
        {
            "category":"Manufacturing",
            "subcategory":"Printing",
            "type":"Manufacturing & Wholesale Goods"
        }
    ],
    "sg:phone":"+1 626 457 9181",
    "sg:postcode":"91776",
    "sg:province":"CA",
    "sg:tags":[
        "lithographic",
        "commercial"
    ],
    "wof:name":"Ultimate Printing & Copy",
    "wof:placetype":"venue"
},
  "geometry": {"coordinates":[-118.110056,34.10234],"type":"Point"}
}