{
  "type": "Feature",
  "properties": {
    "addr:full":"550 Front St Grover Beach CA 93433",
    "addr:housenumber":"550",
    "addr:postcode":"93433",
    "addr:street":"Front St",
    "iso:country":"US",
    "sg:address":"550 Front St",
    "sg:city":"Grover Beach",
    "sg:classifiers":[
        {
            "category":"Travel",
            "subcategory":"Hotels & Motels",
            "type":"Entertainment"
        }
    ],
    "sg:phone":"+1 805 627 1900",
    "sg:postcode":"93433",
    "sg:province":"CA",
    "wof:name":"Avila Lighthouse Suites",
    "wof:placetype":"venue"
},
  "geometry": {"coordinates":[-120.631119,35.127326],"type":"Point"}
}