{
  "type": "Feature",
  "properties": {
    "iso:country":"US",
    "sg:address":"9521 Old River Rd",
    "sg:city":"Bakersfield",
    "sg:phone":"+1 661 831 2722",
    "sg:postcode":"93311",
    "sg:province":"CA",
    "sg:tags":[
        "farm",
        "corn",
        "wheat",
        "cotton"
    ],
    "wof:name":"Frank Fugitt",
    "wof:placetype":"venue"
},
  "geometry": {"coordinates":[-119.109899,35.280133],"type":"Point"}
}