{
  "type": "Feature",
  "properties": {
    "iso:country":"US",
    "sg:address":"2515 Artesia Blvd Ste F",
    "sg:city":"Redondo Beach",
    "sg:classifiers":[
        {
            "category":"Restaurant",
            "type":"Food & Drink"
        }
    ],
    "sg:phone":"+1 424 247 7414",
    "sg:postcode":"90278",
    "sg:province":"CA",
    "sg:tags":[
        "seafood"
    ],
    "wof:name":"Blue Salt Fish Grill",
    "wof:placetype":"venue"
},
  "geometry": {"coordinates":[-118.365015,33.873169],"type":"Point"}
}