{
  "type": "Feature",
  "properties": {
    "addr:full":"2551 E Vineyard Ave Oxnard CA 93036",
    "addr:housenumber":"2551",
    "addr:postcode":"93036",
    "addr:street":"E Vineyard Ave",
    "iso:country":"US",
    "sg:address":"2551 E Vineyard Ave",
    "sg:city":"Oxnard",
    "sg:classifiers":[
        {
            "category":"Fast Food",
            "type":"Food & Drink"
        },
        {
            "category":"Restaurant",
            "type":"Food & Drink"
        }
    ],
    "sg:phone":"+1 805 485 3373",
    "sg:postcode":"93036",
    "sg:province":"CA",
    "sg:tags":[
        "american",
        "hot",
        "hamburger",
        "dog"
    ],
    "sg:website":"http://www.wendys.com",
    "wof:name":"Wendy's",
    "wof:placetype":"venue"
},
  "geometry": {"coordinates":[-119.171989,34.23357],"type":"Point"}
}