{
  "type": "Feature",
  "properties": {
    "addr:full":"563 E 2nd St San Jacinto CA 92583",
    "addr:housenumber":"563",
    "addr:postcode":"92583",
    "addr:street":"E 2Nd St",
    "iso:country":"US",
    "sg:address":"563 E 2nd St",
    "sg:city":"San Jacinto",
    "sg:classifiers":[
        {
            "category":"Manufacturing",
            "subcategory":"Electronics",
            "type":"Manufacturing & Wholesale Goods"
        }
    ],
    "sg:phone":"+1 951 487 1681",
    "sg:postcode":"92583",
    "sg:province":"CA",
    "sg:tags":[
        "equipment",
        "mfg",
        "communication"
    ],
    "wof:name":"A Satellite",
    "wof:placetype":"venue"
},
  "geometry": {"coordinates":[-116.951605,33.786141],"type":"Point"}
}