{
  "type": "Feature",
  "properties": {
    "addr:full":"9050 Tarmac Way Fair Oaks CA 95628",
    "addr:postcode":"9050;95628",
    "addr:street":"Tarmac Way",
    "iso:country":"US",
    "sg:address":"9050 Tarmac Way",
    "sg:city":"Fair Oaks",
    "sg:classifiers":[
        {
            "category":"Manufacturing",
            "subcategory":"Tools & Machinery",
            "type":"Manufacturing & Wholesale Goods"
        }
    ],
    "sg:phone":"+1 916 989 0333",
    "sg:postcode":"95628",
    "sg:province":"CA",
    "sg:tags":[
        "equipment",
        "lighting",
        "mfg"
    ],
    "wof:name":"Tanamerica",
    "wof:placetype":"venue"
},
  "geometry": {"coordinates":[-121.217619,38.658159],"type":"Point"}
}