{
  "type": "Feature",
  "properties": {
    "iso:country":"US",
    "sg:address":"1082 Stockton Ave",
    "sg:city":"San Jose",
    "sg:classifiers":[
        {
            "category":"Health Services",
            "subcategory":"Clinic",
            "type":"Services"
        }
    ],
    "sg:phone":"+1 408 247 0400",
    "sg:postcode":"95110",
    "sg:province":"CA",
    "sg:tags":[
        "cannabis"
    ],
    "sg:website":"sjcbc.org",
    "wof:name":"The San Jose Cannabis Buyers Collective",
    "wof:placetype":"venue"
},
  "geometry": {"coordinates":[-121.921167,37.348135],"type":"Point"}
}