{
  "type": "Feature",
  "properties": {
    "iso:country":"US",
    "sg:address":"431 Lakeview Ave",
    "sg:city":"San Francisco",
    "sg:classifiers":[
        {
            "category":"Manufacturing",
            "subcategory":"Printing",
            "type":"Manufacturing & Wholesale Goods"
        }
    ],
    "sg:phone":"+1 415 333 7075",
    "sg:postcode":"94112",
    "sg:province":"CA",
    "sg:tags":[
        "commercial"
    ],
    "wof:name":"Graphic Consultants",
    "wof:placetype":"venue"
},
  "geometry": {"coordinates":[-122.45396,37.717975],"type":"Point"}
}