{
  "type": "Feature",
  "properties": {
    "iso:country":"US",
    "sg:address":"9010 Venice Blvd",
    "sg:city":"Culver City",
    "sg:classifiers":[
        {
            "category":"Professional",
            "subcategory":"Computer Services",
            "type":"Services"
        }
    ],
    "sg:phone":"+1 310 287 1579",
    "sg:postcode":"90232",
    "sg:province":"CA",
    "sg:tags":[
        "repair"
    ],
    "wof:name":"P C Tech",
    "wof:placetype":"venue"
},
  "geometry": {"coordinates":[-118.392674,34.026294],"type":"Point"}
}