{
  "type": "Feature",
  "properties": {
    "addr:full":"826 S Catalina St Los Angeles CA 90005",
    "addr:housenumber":"826",
    "addr:postcode":"90005",
    "addr:street":"S Catalina St",
    "iso:country":"US",
    "sg:address":"826 S Catalina St",
    "sg:city":"Los Angeles",
    "sg:classifiers":[
        {
            "category":"Local Transit",
            "type":"Transportation"
        }
    ],
    "sg:phone":"+1 310 216 3400",
    "sg:postcode":"90005",
    "sg:province":"CA",
    "sg:tags":[
        "passenger"
    ],
    "wof:name":"EZ Tour & Rainbow W Limo",
    "wof:placetype":"venue"
},
  "geometry": {"coordinates":[-118.295311,34.056402],"type":"Point"}
}