{
  "type": "Feature",
  "properties": {
    "addr:full":"2589 N Lakewood Blvd Long Beach CA 90815",
    "addr:housenumber":"2589",
    "addr:postcode":"90815",
    "addr:street":"N Lakewood Blvd",
    "iso:country":"US",
    "sg:address":"2589 N Lakewood Blvd",
    "sg:city":"Long Beach",
    "sg:classifiers":[
        {
            "category":"Autos & Motor Vehicles",
            "subcategory":"Fuel & Gas Station",
            "type":"Retail Goods"
        }
    ],
    "sg:phone":"+1 562 597 4480",
    "sg:postcode":"90815",
    "sg:province":"CA",
    "wof:name":"Michael Shell Service",
    "wof:placetype":"venue"
},
  "geometry": {"coordinates":[-118.14299800000001,33.8032],"type":"Point"}
}