{
  "type": "Feature",
  "properties": {
    "iso:country":"US",
    "sg:address":"60 Technology Drive",
    "sg:city":"Irvine",
    "sg:classifiers":[
        {
            "category":"Professional",
            "subcategory":"Research",
            "type":"Services"
        }
    ],
    "sg:phone":"+1 949 916 1630",
    "sg:postcode":"92618",
    "sg:province":"CA",
    "sg:website":"http://www.neomend.com/",
    "wof:name":"Neomend",
    "wof:placetype":"venue"
},
  "geometry": {"coordinates":[-117.739424,33.656495],"type":"Point"}
}