{
  "type": "Feature",
  "properties": {
    "addr:full":"5423 W Hillsdale Ave Visalia CA 93291",
    "addr:housenumber":"5423",
    "addr:postcode":"93291",
    "addr:street":"W Hillsdale Ave",
    "iso:country":"US",
    "sg:address":"5423 W Hillsdale Ave",
    "sg:city":"Visalia",
    "sg:classifiers":[
        {
            "category":"Health Services",
            "subcategory":"Dentist",
            "type":"Services"
        }
    ],
    "sg:phone":"+1 559 625 2488",
    "sg:postcode":"93291",
    "sg:province":"CA",
    "sg:tags":[
        "product",
        "dentists-cosmetic",
        "teeth",
        "whitening",
        "dentistry",
        "dentists-orthodontists"
    ],
    "sg:website":"http://www.jphillipsdds.com",
    "wof:name":"James Phillips DDS",
    "wof:placetype":"venue"
},
  "geometry": {"coordinates":[-119.351133,36.329527],"type":"Point"}
}