{
  "type": "Feature",
  "properties": {
    "addr:full":"8578 Ave Costa Blanca San Diego CA 92173",
    "addr:housenumber":"8578",
    "addr:postcode":"92173",
    "addr:street":"Ave Costa",
    "iso:country":"US",
    "sg:address":"8578 Ave Costa Blanca",
    "sg:city":"San Diego",
    "sg:classifiers":[
        {
            "category":"Wholesale",
            "subcategory":"Fruits & Vegetables",
            "type":"Manufacturing & Wholesale Goods"
        }
    ],
    "sg:phone":"+1 619 690 7183",
    "sg:postcode":"92173",
    "sg:province":"CA",
    "wof:name":"EXS Sales",
    "wof:placetype":"venue"
},
  "geometry": {"coordinates":[-116.95503600000001,32.557648],"type":"Point"}
}