{
  "type": "Feature",
  "properties": {
    "iso:country":"US",
    "sg:address":"1123 J St",
    "sg:city":"Sacramento",
    "sg:classifiers":[
        {
            "category":"Organizations",
            "subcategory":"Membership Organization",
            "type":"Services"
        }
    ],
    "sg:phone":"+1 916 961 5543",
    "sg:postcode":"95814",
    "sg:province":"CA",
    "sg:tags":[
        "fraternal"
    ],
    "wof:name":"Kinghts Templar",
    "wof:placetype":"venue"
},
  "geometry": {"coordinates":[-121.49180699999999,38.579893],"type":"Point"}
}