{
  "type": "Feature",
  "properties": {
    "iso:country":"US",
    "sg:address":"508 Main St",
    "sg:city":"Red Bluff",
    "sg:classifiers":[
        {
            "category":"Health Services",
            "subcategory":"Optometrist",
            "type":"Services"
        }
    ],
    "sg:phone":"+1 530 527 9242",
    "sg:postcode":"96080",
    "sg:province":"CA",
    "wof:name":"Red Bluff Vision Ctr",
    "wof:placetype":"venue"
},
  "geometry": {"coordinates":[-122.234043,40.176569],"type":"Point"}
}