{
  "type": "Feature",
  "properties": {
    "addr:full":"790 W Main St Turlock CA 95380",
    "addr:housenumber":"790",
    "addr:postcode":"95380",
    "addr:street":"W Main St",
    "iso:country":"US",
    "sg:address":"790 W Main St",
    "sg:city":"Turlock",
    "sg:classifiers":[
        {
            "category":"Wholesale",
            "subcategory":"Auto Parts",
            "type":"Manufacturing & Wholesale Goods"
        }
    ],
    "sg:phone":"+1 209 667 7084",
    "sg:postcode":"95380",
    "sg:province":"CA",
    "sg:tags":[
        "tire"
    ],
    "wof:name":"Llantas Tire Svc & Wheels",
    "wof:placetype":"venue"
},
  "geometry": {"coordinates":[-120.857185,37.492669],"type":"Point"}
}