{
  "type": "Feature",
  "properties": {
    "addr:full":"209 N Pennsylvania Ave A Glendora CA 91741",
    "addr:housenumber":"209",
    "addr:postcode":"glendora;91741",
    "addr:street":"N Pennsylvania Ave A",
    "iso:country":"US",
    "sg:address":"209 N Pennsylvania Ave A",
    "sg:city":"Glendora",
    "sg:classifiers":[
        {
            "category":"Real Estate",
            "subcategory":"Real Estate Services",
            "type":"Services"
        },
        {
            "category":"Real Estate",
            "subcategory":"Real Estate Operator",
            "type":"Services"
        }
    ],
    "sg:phone":"+1 626 914 2880",
    "sg:postcode":"91741",
    "sg:province":"CA",
    "sg:tags":[
        "apartment",
        "vacancy",
        "listing",
        "rental",
        "finder"
    ],
    "wof:name":"Mountain Shadows Apartments",
    "wof:placetype":"venue"
},
  "geometry": {"coordinates":[-117.86805,34.138568],"type":"Point"}
}