{
  "type": "Feature",
  "properties": {
    "iso:country":"US",
    "sg:address":"23021 Brenford St",
    "sg:city":"Woodland Hills",
    "sg:classifiers":[
        {
            "category":"Professional",
            "subcategory":"Engineering",
            "type":"Services"
        }
    ],
    "sg:phone":"+1 818 591 2119",
    "sg:postcode":"91364",
    "sg:province":"CA",
    "sg:tags":[
        "engineer"
    ],
    "wof:name":"Piersol Engineering Co",
    "wof:placetype":"venue"
},
  "geometry": {"coordinates":[-118.629566,34.149145],"type":"Point"}
}