{
  "type": "Feature",
  "properties": {
    "addr:full":"150 W Iowa Avenue Sunnyvale CA 94086",
    "addr:housenumber":"150",
    "addr:postcode":"94086",
    "addr:street":"W Iowa Avenue",
    "iso:country":"US",
    "sg:address":"150 W Iowa Avenue",
    "sg:city":"Sunnyvale",
    "sg:classifiers":[
        {
            "category":"Banks & Credit Unions",
            "subcategory":"Bank",
            "type":"Services"
        }
    ],
    "sg:phone":"+1 408 736 4204",
    "sg:postcode":"94086",
    "sg:province":"CA",
    "wof:name":"Duport Judy Ins Agt",
    "wof:placetype":"venue"
},
  "geometry": {"coordinates":[-122.031513,37.372629],"type":"Point"}
}