{
  "type": "Feature",
  "properties": {
    "addr:full":"6592 Rostrata Ave Buena Park CA 90621",
    "addr:housenumber":"6592",
    "addr:postcode":"90621",
    "addr:street":"Rostrata Ave",
    "iso:country":"US",
    "sg:address":"6592 Rostrata Ave",
    "sg:city":"Buena Park",
    "sg:classifiers":[
        {
            "category":"Building & Trades",
            "subcategory":"Construction",
            "type":"Services"
        }
    ],
    "sg:phone":"+1 714 521 1523",
    "sg:postcode":"90621",
    "sg:province":"CA",
    "sg:tags":[
        "house"
    ],
    "wof:name":"Newest Age Custom Builders",
    "wof:placetype":"venue"
},
  "geometry": {"coordinates":[-118.004583,33.863161],"type":"Point"}
}