{
  "type": "Feature",
  "properties": {
    "addr:full":"4121 Power Inn Rd Sacramento CA 95826",
    "addr:housenumber":"4121",
    "addr:postcode":"95826",
    "addr:street":"Power Inn Rd",
    "iso:country":"US",
    "sg:address":"4121 Power Inn Rd",
    "sg:city":"Sacramento",
    "sg:classifiers":[
        {
            "category":"Manufacturing",
            "subcategory":"Apparel",
            "type":"Manufacturing & Wholesale Goods"
        }
    ],
    "sg:phone":"+1 916 455 2876",
    "sg:postcode":"95826",
    "sg:province":"CA",
    "sg:tags":[
        "clothing"
    ],
    "sg:website":"www.motowear.com",
    "wof:name":"Danoc Manufacturing",
    "wof:placetype":"venue"
},
  "geometry": {"coordinates":[-121.409074,38.53748],"type":"Point"}
}