{
  "type": "Feature",
  "properties": {
    "addr:full":"1772 E Ave de Los Arboles Thousand Oaks CA 91362",
    "addr:housenumber":"1772",
    "addr:postcode":"91362",
    "addr:street":"E Ave De Los Arboles",
    "iso:country":"US",
    "sg:address":"1772 E Ave de Los Arboles",
    "sg:city":"Thousand Oaks",
    "sg:classifiers":[
        {
            "category":"Shopping",
            "type":"Retail Goods"
        }
    ],
    "sg:phone":"+1 805 492 1700",
    "sg:postcode":"91362",
    "sg:province":"CA",
    "sg:tags":[
        "telephone",
        "cellular"
    ],
    "wof:name":"United Wireless Ctr",
    "wof:placetype":"venue"
},
  "geometry": {"coordinates":[-118.84627,34.21136],"type":"Point"}
}