{
  "type": "Feature",
  "properties": {
    "iso:country":"US",
    "sg:address":"456 E Grand Ave",
    "sg:city":"Escondido",
    "sg:classifiers":[
        {
            "category":"Insurance",
            "subcategory":"Hazard Insurance",
            "type":"Services"
        }
    ],
    "sg:phone":"+1 760 432 8169",
    "sg:postcode":"92025",
    "sg:province":"CA",
    "sg:tags":[
        "bond"
    ],
    "wof:name":"Escondido Bailbonds",
    "wof:placetype":"venue"
},
  "geometry": {"coordinates":[-117.075605,33.124303],"type":"Point"}
}