{
  "type": "Feature",
  "properties": {
    "addr:full":"Alonda Blvd & Pioneer Blvd Norwalk CA 90650",
    "addr:postcode":"90650",
    "addr:street":"Alonda Blvd & Pioneer Blvd",
    "iso:country":"US",
    "sg:address":"Alonda Blvd & Pioneer Blvd",
    "sg:city":"Norwalk",
    "sg:classifiers":[
        {
            "category":"Food & Beverages",
            "subcategory":"Farmers Market",
            "type":"Retail Goods"
        }
    ],
    "sg:postcode":"90650",
    "sg:province":"CA",
    "sg:website":"www.cafarmersmarkets.com",
    "wof:name":"Norwalk Certified Farmer's Market",
    "wof:placetype":"venue"
},
  "geometry": {"coordinates":[-118.082493,33.887681],"type":"Point"}
}