{
  "type": "Feature",
  "properties": {
    "addr:full":"19301 Saticoy St Reseda CA 91335",
    "addr:housenumber":"19301",
    "addr:postcode":"91335",
    "addr:street":"Saticoy St",
    "iso:country":"US",
    "sg:address":"19301 Saticoy St",
    "sg:city":"Reseda",
    "sg:classifiers":[
        {
            "category":"Restaurant",
            "type":"Food & Drink"
        }
    ],
    "sg:menulink":"http://www.allmenus.com/ca/san-fernando-valley/150300-subway/menu/",
    "sg:phone":"+1 818 349 2060",
    "sg:postcode":"91335",
    "sg:province":"CA",
    "sg:tags":[
        "american",
        "sandwich"
    ],
    "wof:name":"Subway",
    "wof:placetype":"venue"
},
  "geometry": {"coordinates":[-118.553748,34.208492],"type":"Point"}
}