{
  "type": "Feature",
  "properties": {
    "addr:full":"1019 E 8th St Los Angeles CA 90021",
    "addr:housenumber":"1019",
    "addr:postcode":"90021",
    "addr:street":"E 8Th St",
    "iso:country":"US",
    "sg:address":"1019 E 8th St",
    "sg:city":"Los Angeles",
    "sg:classifiers":[
        {
            "category":"Professional",
            "type":"Services"
        }
    ],
    "sg:phone":"+1 213 683 8542",
    "sg:postcode":"90021",
    "sg:province":"CA",
    "wof:name":"Eosarang USA Inc",
    "wof:placetype":"venue"
},
  "geometry": {"coordinates":[-118.245998,34.035977],"type":"Point"}
}