{
  "type": "Feature",
  "properties": {
    "iso:country":"US",
    "sg:address":"601 Civic Center Dr E",
    "sg:city":"Santa Ana",
    "sg:classifiers":[
        {
            "category":"Organizations",
            "subcategory":"Non-profit Organization",
            "type":"Services"
        }
    ],
    "sg:phone":"+1 714 541 1010",
    "sg:postcode":"92701",
    "sg:province":"CA",
    "wof:name":"Public Law Ctr",
    "wof:placetype":"venue"
},
  "geometry": {"coordinates":[-117.86095,33.75259],"type":"Point"}
}