{
  "type": "Feature",
  "properties": {
    "iso:country":"US",
    "sg:address":"1747 5th Ave",
    "sg:city":"San Diego",
    "sg:classifiers":[
        {
            "category":"Shopping",
            "subcategory":"Gifts & Souvenirs",
            "type":"Retail Goods"
        }
    ],
    "sg:phone":"+1 619 234 5651",
    "sg:postcode":"92101",
    "sg:province":"CA",
    "wof:name":"Crown House 3",
    "wof:placetype":"venue"
},
  "geometry": {"coordinates":[-117.160156,32.723727],"type":"Point"}
}