{
  "type": "Feature",
  "properties": {
    "addr:full":"1433 S Pso de Marcia Palm Springs CA 92264",
    "addr:housenumber":"1433",
    "addr:postcode":"92264",
    "addr:street":"S Pso De Marcia",
    "iso:country":"US",
    "sg:address":"1433 S Pso de Marcia",
    "sg:city":"Palm Springs",
    "sg:classifiers":[
        {
            "category":"Building & Trades",
            "subcategory":"Landscaping Services",
            "type":"Services"
        }
    ],
    "sg:phone":"+1 760 485 4826",
    "sg:postcode":"92264",
    "sg:province":"CA",
    "sg:tags":[
        "landscape",
        "contractor"
    ],
    "wof:name":"Nicholsky's Calscapes",
    "wof:placetype":"venue"
},
  "geometry": {"coordinates":[-116.531807,33.805495],"type":"Point"}
}