{
  "type": "Feature",
  "properties": {
    "addr:full":"16714 Marquez Ave Pacific Plsds CA 90272",
    "addr:housenumber":"16714",
    "addr:postcode":"90272",
    "addr:street":"Marquez Ave",
    "iso:country":"US",
    "sg:address":"16714 Marquez Ave",
    "sg:city":"Pacific Plsds",
    "sg:classifiers":[
        {
            "category":"Health Services",
            "subcategory":"Health Practitioner",
            "type":"Services"
        }
    ],
    "sg:phone":"+1 310 454 9998",
    "sg:postcode":"90272",
    "sg:province":"CA",
    "sg:tags":[
        "psychologist"
    ],
    "wof:name":"Sandra Kaler PHD",
    "wof:placetype":"venue"
},
  "geometry": {"coordinates":[-118.545272,34.047811],"type":"Point"}
}