{
  "type": "Feature",
  "properties": {
    "iso:country":"US",
    "sg:address":"34852 Yucaipa Blvd",
    "sg:city":"Yucaipa",
    "sg:classifiers":[
        {
            "category":"Restaurant",
            "type":"Food & Drink"
        }
    ],
    "sg:menulink":"http://www.allmenus.com/ca/yucaipa/164138-wienerschnitzel/menu/",
    "sg:phone":"+1 909 790 3799",
    "sg:postcode":"92399",
    "sg:province":"CA",
    "sg:tags":[
        "sandwich",
        "dog",
        "burger",
        "hot",
        "wrap",
        "american"
    ],
    "wof:name":"Wienerschnitzel",
    "wof:placetype":"venue"
},
  "geometry": {"coordinates":[-117.044186,34.033877],"type":"Point"}
}