{
  "type": "Feature",
  "properties": {
    "addr:full":"5353 Almaden Expy Unit F-90 San Jose CA 95118",
    "addr:housenumber":"5353",
    "addr:postcode":"95118",
    "addr:street":"Almaden Expy Unit F-90",
    "iso:country":"US",
    "sg:address":"5353 Almaden Expy Unit F-90",
    "sg:city":"San Jose",
    "sg:classifiers":[
        {
            "category":"Ice Cream",
            "type":"Food & Drink"
        }
    ],
    "sg:phone":"+1 408 266 6365",
    "sg:postcode":"95118",
    "sg:province":"CA",
    "sg:tags":[
        "frozen",
        "yogurt"
    ],
    "sg:website":"www.orangeleafyogurt.com/",
    "wof:name":"Orange Leaf",
    "wof:placetype":"venue"
},
  "geometry": {"coordinates":[-121.876949,37.251758],"type":"Point"}
}