{
  "type": "Feature",
  "properties": {
    "addr:full":"324 E Valley Pkwy Escondido CA 92025",
    "addr:housenumber":"324",
    "addr:postcode":"92025",
    "addr:street":"E Valley Pkwy",
    "iso:country":"US",
    "sg:address":"324 E Valley Pkwy",
    "sg:city":"Escondido",
    "sg:classifiers":[
        {
            "category":"Home & Garden",
            "subcategory":"Mobile Homes",
            "type":"Retail Goods"
        }
    ],
    "sg:phone":"+1 760 743 6556",
    "sg:postcode":"92025",
    "sg:province":"CA",
    "sg:tags":[
        "parts"
    ],
    "wof:name":"Aladdin Supply",
    "wof:placetype":"venue"
},
  "geometry": {"coordinates":[-117.07840400000001,33.124525],"type":"Point"}
}