{
  "type": "Feature",
  "properties": {
    "iso:country":"US",
    "sg:address":"121 San Jose Ave",
    "sg:city":"Capitola",
    "sg:classifiers":[
        {
            "category":"Arts & Performance",
            "subcategory":"Art Gallery",
            "type":"Entertainment"
        }
    ],
    "sg:phone":"+1 831 476 0970",
    "sg:postcode":"95010",
    "sg:province":"CA",
    "sg:website":"www.kinkadecapitola.com",
    "wof:name":"Thomas Kinkade Capitola Gallery",
    "wof:placetype":"venue"
},
  "geometry": {"coordinates":[-121.95149499999999,36.972561],"type":"Point"}
}