{
  "type": "Feature",
  "properties": {
    "addr:full":"10230 Paramount Blvd Downey CA 90241",
    "addr:housenumber":"10230",
    "addr:postcode":"90241",
    "addr:street":"Paramount Blvd",
    "iso:country":"US",
    "sg:address":"10230 Paramount Blvd",
    "sg:city":"Downey",
    "sg:classifiers":[
        {
            "category":"Banks & Credit Unions",
            "subcategory":"Bank",
            "type":"Services"
        }
    ],
    "sg:phone":"+1 562 928 3361",
    "sg:postcode":"90241",
    "sg:province":"CA",
    "wof:name":"Bank of the West Downey Office",
    "wof:placetype":"venue"
},
  "geometry": {"coordinates":[-118.13099699999999,33.952801],"type":"Point"}
}