{
  "type": "Feature",
  "properties": {
    "addr:full":"2725 State Hwy 32 Chico CA 95973",
    "addr:housenumber":"2725",
    "addr:postcode":"95973",
    "addr:street":"State Hwy 32",
    "iso:country":"US",
    "sg:address":"2725 State Hwy 32",
    "sg:city":"Chico",
    "sg:classifiers":[
        {
            "category":"Manufacturing",
            "subcategory":"Signs",
            "type":"Manufacturing & Wholesale Goods"
        }
    ],
    "sg:phone":"+1 530 879 9261",
    "sg:postcode":"95973",
    "sg:province":"CA",
    "wof:name":"LRT Graphics",
    "wof:placetype":"venue"
},
  "geometry": {"coordinates":[-121.89082000000001,39.745118],"type":"Point"}
}