{
  "type": "Feature",
  "properties": {
    "addr:full":"888 3rd St Santa Rosa CA 95404",
    "addr:housenumber":"888",
    "addr:postcode":"ca 95404",
    "addr:street":"3Rd St",
    "iso:country":"US",
    "sg:address":"888 3rd St",
    "sg:city":"Santa Rosa",
    "sg:classifiers":[
        {
            "category":"Social Services",
            "type":"Services"
        }
    ],
    "sg:phone":"+1 707 575 4203",
    "sg:postcode":"95404",
    "sg:province":"CA",
    "sg:tags":[
        "counselor",
        "marriage",
        "family"
    ],
    "wof:name":"David J Kest",
    "wof:placetype":"venue"
},
  "geometry": {"coordinates":[-122.708079,38.441914],"type":"Point"}
}