{
  "type": "Feature",
  "properties": {
    "iso:country":"US",
    "sg:address":"6601 Victoria Ave",
    "sg:city":"Highland",
    "sg:classifiers":[
        {
            "category":"Professional",
            "subcategory":"Detective & Security Services",
            "type":"Services"
        }
    ],
    "sg:phone":"+1 909 864 6302",
    "sg:postcode":"92346",
    "sg:province":"CA",
    "sg:tags":[
        "guard",
        "patrol"
    ],
    "wof:name":"Century Tech Security",
    "wof:placetype":"venue"
},
  "geometry": {"coordinates":[-117.22614400000001,34.135735],"type":"Point"}
}