{
  "type": "Feature",
  "properties": {
    "addr:full":"50 Mark West Springs Rd Santa Rosa CA 95403",
    "addr:housenumber":"50",
    "addr:postcode":"95403",
    "addr:street":"Mark West Springs Rd",
    "iso:country":"US",
    "sg:address":"50 Mark West Springs Rd",
    "sg:city":"Santa Rosa",
    "sg:classifiers":[
        {
            "category":"Organizations",
            "subcategory":"Religious Organization",
            "type":"Services"
        }
    ],
    "sg:phone":"+1 707 579 2314",
    "sg:postcode":"95403",
    "sg:province":"CA",
    "sg:tags":[
        "church"
    ],
    "wof:name":"Calvary Chapel Of Santa Rosa",
    "wof:placetype":"venue"
},
  "geometry": {"coordinates":[-122.752848,38.49622],"type":"Point"}
}