{
  "type": "Feature",
  "properties": {
    "iso:country":"US",
    "sg:address":"150 Brentwood Ave",
    "sg:city":"San Francisco",
    "sg:classifiers":[
        {
            "category":"Professional",
            "subcategory":"Engineering",
            "type":"Services"
        }
    ],
    "sg:phone":"+1 415 333 1549",
    "sg:postcode":"94127",
    "sg:province":"CA",
    "sg:tags":[
        "engineer"
    ],
    "wof:name":"LHJ & Assoc",
    "wof:placetype":"venue"
},
  "geometry": {"coordinates":[-122.457689,37.733844],"type":"Point"}
}