{
  "type": "Feature",
  "properties": {
    "iso:country":"US",
    "sg:address":"7472 de la Farge Dr",
    "sg:city":"Cupertino",
    "sg:classifiers":[
        {
            "category":"Travel",
            "subcategory":"Travel Agent",
            "type":"Entertainment"
        }
    ],
    "sg:phone":"+1 408 255 6789",
    "sg:postcode":"95014",
    "sg:province":"CA",
    "sg:tags":[
        "operator",
        "tour"
    ],
    "wof:name":"Classic Himalaya Travel",
    "wof:placetype":"venue"
},
  "geometry": {"coordinates":[-122.036579,37.309916],"type":"Point"}
}