{
  "type": "Feature",
  "properties": {
    "addr:full":"320 Miles Ave Santa Maria CA 93455",
    "addr:housenumber":"320",
    "addr:postcode":"93455",
    "addr:street":"Miles Ave",
    "iso:country":"US",
    "sg:address":"320 Miles Ave",
    "sg:city":"Santa Maria",
    "sg:classifiers":[
        {
            "category":"Shopping",
            "subcategory":"Used Merchandise",
            "type":"Retail Goods"
        }
    ],
    "sg:phone":"+1 805 938 9104",
    "sg:postcode":"93455",
    "sg:province":"CA",
    "wof:name":"Brady Moore",
    "wof:placetype":"venue"
},
  "geometry": {"coordinates":[-120.43185099999999,34.894971],"type":"Point"}
}