{
  "type": "Feature",
  "properties": {
    "iso:country":"US",
    "sg:address":"25124 Narbonne Ave",
    "sg:city":"Lomita",
    "sg:classifiers":[
        {
            "category":"Manufacturing",
            "subcategory":"Printing",
            "type":"Manufacturing & Wholesale Goods"
        }
    ],
    "sg:phone":"+1 310 326 4553",
    "sg:postcode":"90717",
    "sg:province":"CA",
    "sg:tags":[
        "commercial"
    ],
    "sg:website":"www.advancedprinting.net",
    "wof:name":"Advanced Printing",
    "wof:placetype":"venue"
},
  "geometry": {"coordinates":[-118.319877,33.797191],"type":"Point"}
}