{
  "type": "Feature",
  "properties": {
    "addr:full":"131 Hillcrest Rd Hollister CA 95023",
    "addr:housenumber":"131",
    "addr:postcode":"hollister ca 95023",
    "addr:street":"Hillcrest Rd",
    "iso:country":"US",
    "sg:address":"131 Hillcrest Rd",
    "sg:city":"Hollister",
    "sg:classifiers":[
        {
            "category":"Building & Trades",
            "subcategory":"Construction",
            "type":"Services"
        }
    ],
    "sg:phone":"+1 831 637 1113",
    "sg:postcode":"95023",
    "sg:province":"CA",
    "sg:tags":[
        "maker",
        "cabinet"
    ],
    "wof:name":"Orozcos Quality Cabinet",
    "wof:placetype":"venue"
},
  "geometry": {"coordinates":[-121.396299,36.848068],"type":"Point"}
}