{
  "type": "Feature",
  "properties": {
    "addr:full":"635 W Colorado St Glendale CA 91204",
    "addr:housenumber":"635",
    "addr:postcode":"91204",
    "addr:street":"W Colorado St",
    "iso:country":"US",
    "sg:address":"635 W Colorado St",
    "sg:city":"Glendale",
    "sg:classifiers":[
        {
            "category":"Communications",
            "subcategory":"Newspaper",
            "type":"Services"
        }
    ],
    "sg:phone":"+1 818 551 1735",
    "sg:postcode":"91204",
    "sg:province":"CA",
    "sg:tags":[
        "magazine"
    ],
    "wof:name":"Don Ray Media",
    "wof:placetype":"venue"
},
  "geometry": {"coordinates":[-118.268066,34.142624],"type":"Point"}
}