{
  "type": "Feature",
  "properties": {
    "iso:country":"US",
    "sg:address":"2618 S Leonard Ave",
    "sg:city":"Sanger",
    "sg:classifiers":[
        {
            "category":"Farming",
            "subcategory":"Vineyard",
            "type":"Manufacturing & Wholesale Goods"
        }
    ],
    "sg:phone":"+1 559 266 7314",
    "sg:postcode":"93657",
    "sg:province":"CA",
    "sg:tags":[
        "grape"
    ],
    "wof:name":"Kandarian Farm",
    "wof:placetype":"venue"
},
  "geometry": {"coordinates":[-119.636864,36.705617],"type":"Point"}
}