{
  "type": "Feature",
  "properties": {
    "addr:full":"917 W Ave J Lancaster CA 93534",
    "addr:housenumber":"917",
    "addr:postcode":"93534",
    "addr:street":"W Ave J",
    "iso:country":"US",
    "sg:address":"917 W Ave J",
    "sg:city":"Lancaster",
    "sg:classifiers":[
        {
            "category":"Professional",
            "type":"Services"
        }
    ],
    "sg:phone":"+1 661 949 8710",
    "sg:postcode":"93534",
    "sg:province":"CA",
    "sg:tags":[
        "establishment"
    ],
    "wof:name":"Sunrise Plaza",
    "wof:placetype":"venue"
},
  "geometry": {"coordinates":[-118.146091,34.689432],"type":"Point"}
}