{
  "type": "Feature",
  "properties": {
    "addr:full":"870 Hermosa Ave Sunnyvale CA 94085",
    "addr:housenumber":"870",
    "addr:postcode":"94085",
    "addr:street":"Hermosa Ave",
    "iso:country":"US",
    "sg:address":"870 Hermosa Ave",
    "sg:city":"Sunnyvale",
    "sg:classifiers":[
        {
            "category":"Professional",
            "subcategory":"Research",
            "type":"Services"
        }
    ],
    "sg:phone":"+1 408 636 2000",
    "sg:postcode":"94085",
    "sg:province":"CA",
    "sg:tags":[
        "stent",
        "drug-eluting",
        "cardiovscular",
        "bioresorbable"
    ],
    "sg:website":"http://elixirmedical.com/",
    "wof:name":"Elixir Medical",
    "wof:placetype":"venue"
},
  "geometry": {"coordinates":[-122.036541,37.386636],"type":"Point"}
}