{
  "type": "Feature",
  "properties": {
    "iso:country":"US",
    "sg:address":"2000 Mcgregor Dr Ste A",
    "sg:city":"Aptos",
    "sg:classifiers":[
        {
            "category":"Arts & Performance",
            "subcategory":"Dance",
            "type":"Entertainment"
        }
    ],
    "sg:phone":"+1 831 588 3605",
    "sg:postcode":"95003",
    "sg:province":"CA",
    "sg:tags":[
        "instruction",
        "dancing"
    ],
    "wof:name":"Sherry's Domestic Goddess",
    "wof:placetype":"venue"
},
  "geometry": {"coordinates":[-121.927818,36.983009],"type":"Point"}
}