{
  "type": "Feature",
  "properties": {
    "iso:country":"US",
    "sg:address":"716 W Cedar St",
    "sg:city":"Eureka",
    "sg:classifiers":[
        {
            "category":"Professional",
            "type":"Services"
        }
    ],
    "sg:phone":"+1 707 441 1904",
    "sg:postcode":"95501",
    "sg:province":"CA",
    "wof:name":"Precision Tool & Machine",
    "wof:placetype":"venue"
},
  "geometry": {"coordinates":[-124.176376,40.79495],"type":"Point"}
}