{
  "type": "Feature",
  "properties": {
    "addr:full":"8040 F Greenback Citrus Heights CA 95610",
    "addr:housenumber":"8040 f greenback",
    "addr:postcode":"95610",
    "iso:country":"US",
    "sg:address":"8040 F Greenback",
    "sg:city":"Citrus Heights",
    "sg:classifiers":[
        {
            "category":"Personal",
            "subcategory":"Massage",
            "type":"Services"
        },
        {
            "category":"Health Services",
            "subcategory":"Clinic",
            "type":"Services"
        },
        {
            "category":"Education",
            "subcategory":"School",
            "type":"Public Place"
        }
    ],
    "sg:phone":"+1 916 728 1300",
    "sg:postcode":"95610",
    "sg:province":"CA",
    "sg:tags":[
        "counseling",
        "mental"
    ],
    "sg:website":"www.bodyharmonyinstitute.com",
    "wof:name":"Body Harmony Institute",
    "wof:placetype":"venue"
},
  "geometry": {"coordinates":[-121.26340999999999,38.677928],"type":"Point"}
}