{
  "type": "Feature",
  "properties": {
    "iso:country":"US",
    "sg:address":"630 Broadway St",
    "sg:city":"King City",
    "sg:classifiers":[
        {
            "category":"Building & Trades",
            "subcategory":"Construction",
            "type":"Services"
        }
    ],
    "sg:phone":"+1 831 385 4308",
    "sg:postcode":"93930",
    "sg:province":"CA",
    "sg:tags":[
        "coping",
        "plastering",
        "tiling",
        "pool",
        "swimming"
    ],
    "wof:name":"Water Man",
    "wof:placetype":"venue"
},
  "geometry": {"coordinates":[-121.13125100000001,36.210096],"type":"Point"}
}