{
  "type": "Feature",
  "properties": {
    "iso:country":"US",
    "sg:address":"500 Sansome St",
    "sg:city":"San Francisco",
    "sg:classifiers":[
        {
            "category":"Insurance",
            "subcategory":"Hazard Insurance",
            "type":"Services"
        }
    ],
    "sg:phone":"+1 415 438 3400",
    "sg:postcode":"94111",
    "sg:province":"CA",
    "sg:tags":[
        "employee",
        "benefit",
        "compensation",
        "plan"
    ],
    "wof:name":"Presidio Pay Advisors Inc",
    "wof:placetype":"venue"
},
  "geometry": {"coordinates":[-122.401581,37.795306],"type":"Point"}
}