{
  "type": "Feature",
  "properties": {
    "iso:country":"US",
    "sg:address":"6920 Miramar Rd",
    "sg:city":"San Diego",
    "sg:classifiers":[
        {
            "category":"Professional",
            "subcategory":"Employment Agencies",
            "type":"Services"
        }
    ],
    "sg:phone":"+1 858 271 4227",
    "sg:postcode":"92121",
    "sg:province":"CA",
    "sg:tags":[
        "opportunity"
    ],
    "wof:name":"Career Finders Inc",
    "wof:placetype":"venue"
},
  "geometry": {"coordinates":[-117.167292,32.878348],"type":"Point"}
}