{
  "type": "Feature",
  "properties": {
    "addr:full":"310 Rose St Bishop CA 93514",
    "addr:housenumber":"310",
    "addr:postcode":"93514",
    "addr:street":"Rose St",
    "iso:country":"US",
    "sg:address":"310 Rose St",
    "sg:city":"Bishop",
    "sg:classifiers":[
        {
            "category":"Manufacturing",
            "subcategory":"Rubber & Plastics",
            "type":"Manufacturing & Wholesale Goods"
        }
    ],
    "sg:phone":"+1 760 872 1799",
    "sg:postcode":"93514",
    "sg:province":"CA",
    "sg:tags":[
        "supply"
    ],
    "wof:name":"B & J Rubber Products",
    "wof:placetype":"venue"
},
  "geometry": {"coordinates":[-118.394171,37.363495],"type":"Point"}
}