{
  "type": "Feature",
  "properties": {
    "iso:country":"US",
    "sg:address":"3620 W 3rd St",
    "sg:city":"Los Angeles",
    "sg:classifiers":[
        {
            "category":"Professional",
            "subcategory":"Accounting & Tax Preparation",
            "type":"Services"
        }
    ],
    "sg:phone":"+1 213 383 2071",
    "sg:postcode":"90020",
    "sg:province":"CA",
    "sg:tags":[
        "return",
        "filing"
    ],
    "wof:name":"J & J Tax Svc",
    "wof:placetype":"venue"
},
  "geometry": {"coordinates":[-118.294979,34.068964],"type":"Point"}
}