{
  "type": "Feature",
  "properties": {
    "addr:full":"225 Woodland Ave San Rafael CA 94901",
    "addr:housenumber":"225",
    "addr:postcode":"94901",
    "addr:street":"Woodland Ave",
    "iso:country":"US",
    "sg:address":"225 Woodland Ave",
    "sg:city":"San Rafael",
    "sg:classifiers":[
        {
            "category":"Education",
            "subcategory":"School",
            "type":"Public Place"
        }
    ],
    "sg:phone":"+1 415 485 2306",
    "sg:postcode":"94901",
    "sg:province":"CA",
    "wof:name":"San Rafael School District",
    "wof:placetype":"venue"
},
  "geometry": {"coordinates":[-122.52625,37.964311],"type":"Point"}
}