{
  "type": "Feature",
  "properties": {
    "iso:country":"US",
    "sg:address":"879 14th St",
    "sg:city":"San Francisco",
    "sg:classifiers":[
        {
            "category":"Health Services",
            "subcategory":"Health Practitioner",
            "type":"Services"
        }
    ],
    "sg:phone":"+1 415 255 8709",
    "sg:postcode":"94114",
    "sg:province":"CA",
    "sg:tags":[
        "psychotherapist"
    ],
    "wof:name":"Michael A Graves",
    "wof:placetype":"venue"
},
  "geometry": {"coordinates":[-122.432891,37.767425],"type":"Point"}
}