{
  "type": "Feature",
  "properties": {
    "iso:country":"US",
    "sg:address":"8761 Garden Grove Blvd",
    "sg:city":"Garden Grove",
    "sg:classifiers":[
        {
            "category":"Cinema",
            "subcategory":"Movie Rental",
            "type":"Entertainment"
        }
    ],
    "sg:phone":"+1 714 636 4647",
    "sg:postcode":"92844",
    "sg:province":"CA",
    "sg:tags":[
        "game",
        "video"
    ],
    "wof:name":"Sam's Video",
    "wof:placetype":"venue"
},
  "geometry": {"coordinates":[-117.980003,33.774101],"type":"Point"}
}