{
  "type": "Feature",
  "properties": {
    "iso:country":"US",
    "sg:address":"201 Pasadena Ave",
    "sg:city":"South Pasadena",
    "sg:classifiers":[
        {
            "category":"Travel",
            "subcategory":"Hotels & Motels",
            "type":"Entertainment"
        }
    ],
    "sg:phone":"+1 626 441 3535",
    "sg:postcode":"91030",
    "sg:province":"CA",
    "sg:tags":[
        "breakfast",
        "accommodation",
        "bed"
    ],
    "sg:website":"www.bissellhouse.com",
    "wof:name":"Bissell House Bed & Breakfast",
    "wof:placetype":"venue"
},
  "geometry": {"coordinates":[-118.169274,34.112207],"type":"Point"}
}