{
  "type": "Feature",
  "properties": {
    "addr:full":"1505 N San Fernando Blvd Burbank CA 91504",
    "addr:housenumber":"1505",
    "addr:postcode":"91504",
    "addr:street":"N San Fernando Blvd",
    "iso:country":"US",
    "sg:address":"1505 N San Fernando Blvd",
    "sg:city":"Burbank",
    "sg:classifiers":[
        {
            "category":"Professional",
            "subcategory":"Lawyer & Legal Services",
            "type":"Services"
        }
    ],
    "sg:phone":"+1 818 239 1582",
    "sg:postcode":"91504",
    "sg:province":"CA",
    "wof:name":"Fu John Law Offices Of",
    "wof:placetype":"venue"
},
  "geometry": {"coordinates":[-118.32273499999999,34.190963],"type":"Point"}
}