{
  "type": "Feature",
  "properties": {
    "addr:full":"2323 W La Palma Ave Anaheim CA 92801",
    "addr:housenumber":"2323",
    "addr:postcode":"92801",
    "addr:street":"W La Palma Ave",
    "iso:country":"US",
    "sg:address":"2323 W La Palma Ave",
    "sg:city":"Anaheim",
    "sg:classifiers":[
        {
            "category":"Personal",
            "type":"Services"
        }
    ],
    "sg:phone":"+1 714 687 1000",
    "sg:postcode":"92801",
    "sg:province":"CA",
    "sg:tags":[
        "mover"
    ],
    "wof:name":"Atlantic Relocation Systems",
    "wof:placetype":"venue"
},
  "geometry": {"coordinates":[-117.964996,33.846802],"type":"Point"}
}