{
  "type": "Feature",
  "properties": {
    "addr:full":"244 Arvin Ave Arvin CA 93203",
    "addr:housenumber":"244",
    "addr:postcode":"93203",
    "addr:street":"Arvin Ave",
    "iso:country":"US",
    "sg:address":"244 Arvin Ave",
    "sg:city":"Arvin",
    "sg:classifiers":[
        {
            "category":"Organizations",
            "subcategory":"Religious Organization",
            "type":"Services"
        }
    ],
    "sg:phone":"+1 661 854 0620",
    "sg:postcode":"93203",
    "sg:province":"CA",
    "sg:tags":[
        "church"
    ],
    "wof:name":"Primera Iglesia Bautista",
    "wof:placetype":"venue"
},
  "geometry": {"coordinates":[-118.826711,35.210161],"type":"Point"}
}