{
  "type": "Feature",
  "properties": {
    "addr:full":"310 Alabama St Redlands CA 92373",
    "addr:housenumber":"310",
    "addr:postcode":"92373",
    "addr:street":"Alabama St",
    "iso:country":"US",
    "sg:address":"310 Alabama St",
    "sg:city":"Redlands",
    "sg:classifiers":[
        {
            "category":"Professional",
            "type":"Services"
        },
        {
            "category":"Shopping",
            "subcategory":"Bicycles & Sporting Goods",
            "type":"Retail Goods"
        },
        {
            "category":"Personal",
            "subcategory":"Day Spa",
            "type":"Services"
        },
        {
            "category":"Sports & Exercise",
            "subcategory":"Swimming Pool",
            "type":"Entertainment"
        }
    ],
    "sg:phone":"+1 909 793 9082",
    "sg:postcode":"92373",
    "sg:province":"CA",
    "sg:tags":[
        "repair",
        "supply",
        "tubs-repair",
        "equipment",
        "hot",
        "tub"
    ],
    "sg:website":"http://www.redlandspool.com",
    "wof:name":"Redlands Pool & Spa Center",
    "wof:placetype":"venue"
},
  "geometry": {"coordinates":[-117.20877,34.056155],"type":"Point"}
}