{
  "type": "Feature",
  "properties": {
    "addr:full":"450 N G St San Bernardino CA 92410",
    "addr:housenumber":"450",
    "addr:postcode":"92410",
    "addr:street":"N G St",
    "iso:country":"US",
    "sg:address":"450 N G St",
    "sg:city":"San Bernardino",
    "sg:classifiers":[
        {
            "category":"Travel",
            "subcategory":"Hotels & Motels",
            "type":"Entertainment"
        }
    ],
    "sg:phone":"+1 909 885 0055",
    "sg:postcode":"92410",
    "sg:province":"CA",
    "wof:name":"Sunset Hotel",
    "wof:placetype":"venue"
},
  "geometry": {"coordinates":[-117.29874599999999,34.10665],"type":"Point"}
}