{
  "type": "Feature",
  "properties": {
    "iso:country":"US",
    "sg:address":"8705 Truxton Ave",
    "sg:city":"Los Angeles",
    "sg:classifiers":[
        {
            "category":"Wholesale",
            "subcategory":"Medical Equipment & Supplies",
            "type":"Manufacturing & Wholesale Goods"
        }
    ],
    "sg:phone":"+1 310 670 3155",
    "sg:postcode":"90045",
    "sg:province":"CA",
    "wof:name":"Millenium Medical Supplies",
    "wof:placetype":"venue"
},
  "geometry": {"coordinates":[-118.393227,33.958256],"type":"Point"}
}