{
  "type": "Feature",
  "properties": {
    "iso:country":"US",
    "sg:address":"1446 Cameo Dr",
    "sg:city":"Del Mar",
    "sg:classifiers":[
        {
            "category":"Shopping",
            "subcategory":"Clothing, Apparel, & Fashions",
            "type":"Retail Goods"
        }
    ],
    "sg:phone":"+1 858 755 6370",
    "sg:postcode":"92026",
    "sg:province":"CA",
    "wof:name":"LA Mariposa Boutique",
    "wof:placetype":"venue"
},
  "geometry": {"coordinates":[-117.086112,33.144895],"type":"Point"}
}