{
  "type": "Feature",
  "properties": {
    "iso:country":"US",
    "sg:address":"29145 Arnold Dr",
    "sg:city":"Sonoma",
    "sg:classifiers":[
        {
            "category":"Professional",
            "subcategory":"Art Services",
            "type":"Services"
        }
    ],
    "sg:phone":"+1 707 996 5688",
    "sg:postcode":"95476",
    "sg:province":"CA",
    "sg:tags":[
        "graphic",
        "designer"
    ],
    "wof:name":"Landmark Grafix",
    "wof:placetype":"venue"
},
  "geometry": {"coordinates":[-122.446131,38.178029],"type":"Point"}
}