{
  "type": "Feature",
  "properties": {
    "iso:country":"US",
    "sg:address":"305 S Los Angeles Street",
    "sg:city":"Los Angeles",
    "sg:classifiers":[
        {
            "category":"Shopping",
            "subcategory":"Optician",
            "type":"Retail Goods"
        }
    ],
    "sg:phone":"+1 213 613 0108",
    "sg:postcode":"90013",
    "sg:province":"CA",
    "sg:tags":[
        "eyewear"
    ],
    "wof:name":"K B Eyewear International Company",
    "wof:placetype":"venue"
},
  "geometry": {"coordinates":[-118.244822,34.04825],"type":"Point"}
}