{
  "type": "Feature",
  "properties": {
    "addr:full":"21543 Knoll Way Hayward CA 94546",
    "addr:housenumber":"21543",
    "addr:postcode":"94546",
    "addr:street":"Knoll Way",
    "iso:country":"US",
    "sg:address":"21543 Knoll Way",
    "sg:city":"Hayward",
    "sg:classifiers":[
        {
            "category":"Real Estate",
            "subcategory":"Real Estate Services",
            "type":"Services"
        }
    ],
    "sg:phone":"+1 510 886 1636",
    "sg:postcode":"94546",
    "sg:province":"CA",
    "sg:tags":[
        "home",
        "inspector"
    ],
    "wof:name":"Bullseye Home Inspection",
    "wof:placetype":"venue"
},
  "geometry": {"coordinates":[-122.087802,37.684969],"type":"Point"}
}