{
  "type": "Feature",
  "properties": {
    "iso:country":"US",
    "sg:address":"2859 Maryetta Ct",
    "sg:city":"Shingle Springs",
    "sg:classifiers":[
        {
            "category":"Autos & Motor Vehicles",
            "subcategory":"Automobile Sales",
            "type":"Retail Goods"
        }
    ],
    "sg:phone":"+1 530 677 5252",
    "sg:postcode":"95682",
    "sg:province":"CA",
    "wof:name":"Hunt Enterprises",
    "wof:placetype":"venue"
},
  "geometry": {"coordinates":[-120.996961,38.689094],"type":"Point"}
}