{
  "type": "Feature",
  "properties": {
    "iso:country":"US",
    "sg:address":"13516 Phantom St",
    "sg:city":"Victorville",
    "sg:classifiers":[
        {
            "category":"Airport",
            "type":"Transportation"
        }
    ],
    "sg:phone":"+1 760 246 1651",
    "sg:postcode":"92394",
    "sg:province":"CA",
    "wof:name":"Leading Edge Aviation",
    "wof:placetype":"venue"
},
  "geometry": {"coordinates":[-117.370621,34.589017],"type":"Point"}
}