{
  "type": "Feature",
  "properties": {
    "iso:country":"US",
    "sg:address":"2480 S Sepulveda Blvd",
    "sg:city":"Los Angeles",
    "sg:classifiers":[
        {
            "category":"Shopping",
            "subcategory":"Gifts & Souvenirs",
            "type":"Retail Goods"
        }
    ],
    "sg:phone":"+1 310 312 6050",
    "sg:postcode":"90064",
    "sg:province":"CA",
    "sg:tags":[
        "party",
        "supply"
    ],
    "sg:website":"www.partycity.com",
    "wof:name":"Party City",
    "wof:placetype":"venue"
},
  "geometry": {"coordinates":[-118.434151,34.035686],"type":"Point"}
}