{
  "type": "Feature",
  "properties": {
    "addr:full":"862 W I St Benicia CA 94510",
    "addr:housenumber":"862",
    "addr:postcode":"94510",
    "addr:street":"W I St",
    "iso:country":"US",
    "sg:address":"862 W I St",
    "sg:city":"Benicia",
    "sg:classifiers":[
        {
            "category":"Building & Trades",
            "subcategory":"Construction",
            "type":"Services"
        }
    ],
    "sg:phone":"+1 707 751 0204",
    "sg:postcode":"94510",
    "sg:province":"CA",
    "sg:tags":[
        "home",
        "builder"
    ],
    "wof:name":"Myles Homes",
    "wof:placetype":"venue"
},
  "geometry": {"coordinates":[-122.172513,38.058037],"type":"Point"}
}