{
  "type": "Feature",
  "properties": {
    "addr:full":"1901 Airport Rd South Lake Tahoe CA 96150",
    "addr:housenumber":"1901",
    "addr:postcode":"96150",
    "addr:street":"Airport Rd",
    "iso:country":"US",
    "sg:address":"1901 Airport Rd",
    "sg:city":"South Lake Tahoe",
    "sg:classifiers":[
        {
            "category":"Professional",
            "subcategory":"Computer Services",
            "type":"Services"
        }
    ],
    "sg:phone":"+1 530 544 7733",
    "sg:postcode":"96150",
    "sg:province":"CA",
    "sg:tags":[
        "consultant",
        "designer"
    ],
    "wof:name":"CDS Computerized Design Syst",
    "wof:placetype":"venue"
},
  "geometry": {"coordinates":[-119.999183,38.891168],"type":"Point"}
}