{
  "type": "Feature",
  "properties": {
    "iso:country":"US",
    "sg:address":"2 del Fiore",
    "sg:city":"Lake Elsinore",
    "sg:classifiers":[
        {
            "category":"Wholesale",
            "subcategory":"Jewelry",
            "type":"Manufacturing & Wholesale Goods"
        }
    ],
    "sg:phone":"+1 951 674 6434",
    "sg:postcode":"92532",
    "sg:province":"CA",
    "sg:tags":[
        "stone"
    ],
    "wof:name":"Tuscany Trading Company",
    "wof:placetype":"venue"
},
  "geometry": {"coordinates":[-117.287397,33.682382],"type":"Point"}
}