{
  "type": "Feature",
  "properties": {
    "addr:full":"7724 University Ave La Mesa CA 91941",
    "addr:housenumber":"7724",
    "addr:postcode":"91941",
    "addr:street":"University Ave",
    "iso:country":"US",
    "sg:address":"7724 University Ave",
    "sg:city":"La Mesa",
    "sg:classifiers":[
        {
            "category":"Retail",
            "subcategory":"Repair Shop",
            "type":"Services"
        }
    ],
    "sg:phone":"+1 818 708 1148",
    "sg:postcode":"91941",
    "sg:province":"CA",
    "sg:tags":[
        "equipment",
        "conditioning",
        "air"
    ],
    "wof:name":"Applifix",
    "wof:placetype":"venue"
},
  "geometry": {"coordinates":[-117.030962,32.761838],"type":"Point"}
}