{
  "type": "Feature",
  "properties": {
    "iso:country":"US",
    "sg:address":"9500 Micron Ave #128",
    "sg:city":"Sacramento",
    "sg:classifiers":[
        {
            "category":"Restaurant",
            "type":"Food & Drink"
        }
    ],
    "sg:phone":"+1 916 454 1908",
    "sg:postcode":"95827",
    "sg:province":"CA",
    "sg:tags":[
        "italian",
        "pizza"
    ],
    "sg:website":"www.stringspizzeria.com",
    "wof:name":"Strings Pizzeria",
    "wof:placetype":"venue"
},
  "geometry": {"coordinates":[-121.343045,38.561809],"type":"Point"}
}