{
  "type": "Feature",
  "properties": {
    "addr:full":"16805 Klee St Northridge CA 91343",
    "addr:postcode":"16805;91343",
    "addr:street":"Klee St",
    "iso:country":"US",
    "sg:address":"16805 Klee St",
    "sg:city":"Northridge",
    "sg:classifiers":[
        {
            "category":"Manufacturing",
            "subcategory":"Tools & Machinery",
            "type":"Manufacturing & Wholesale Goods"
        }
    ],
    "sg:phone":"+1 818 893 8731",
    "sg:postcode":"91343",
    "sg:province":"CA",
    "sg:tags":[
        "physician",
        "surgeon"
    ],
    "wof:name":"Sender-Care",
    "wof:placetype":"venue"
},
  "geometry": {"coordinates":[-118.499921,34.231051],"type":"Point"}
}