{
  "type": "Feature",
  "properties": {
    "iso:country":"US",
    "sg:address":"50 Cakebread Cir",
    "sg:city":"Sacramento",
    "sg:classifiers":[
        {
            "category":"Real Estate",
            "subcategory":"Architect",
            "type":"Services"
        }
    ],
    "sg:phone":"+1 916 359 6980",
    "sg:postcode":"95834",
    "sg:province":"CA",
    "wof:name":"Bullseye Marketing",
    "wof:placetype":"venue"
},
  "geometry": {"coordinates":[-121.53600299999999,38.637299],"type":"Point"}
}