{
  "type": "Feature",
  "properties": {
    "iso:country":"US",
    "sg:address":"363 Bell St",
    "sg:city":"Los Alamos",
    "sg:classifiers":[
        {
            "category":"Manufacturing",
            "subcategory":"Tools & Machinery",
            "type":"Manufacturing & Wholesale Goods"
        }
    ],
    "sg:phone":"+1 805 344 2271",
    "sg:postcode":"93440",
    "sg:province":"CA",
    "sg:tags":[
        "lighting",
        "fixture"
    ],
    "wof:name":"Wendelighting",
    "wof:placetype":"venue"
},
  "geometry": {"coordinates":[-120.280286,34.744048],"type":"Point"}
}