{
  "type": "Feature",
  "properties": {
    "iso:country":"US",
    "sg:address":"11335 Magnolia Blvd Ste 2D",
    "sg:city":"North Hollywood",
    "sg:classifiers":[
        {
            "category":"Health Services",
            "subcategory":"Clinic",
            "type":"Services"
        },
        {
            "category":"Personal",
            "type":"Services"
        }
    ],
    "sg:phone":"+1 818 505 8805",
    "sg:postcode":"91601",
    "sg:province":"CA",
    "sg:tags":[
        "cannabis",
        "local"
    ],
    "sg:website":"www.organicmc.com",
    "wof:name":"Organic Medirex Consultations",
    "wof:placetype":"venue"
},
  "geometry": {"coordinates":[-118.378641,34.165082],"type":"Point"}
}