{
  "type": "Feature",
  "properties": {
    "addr:full":"825 Trenton Dr Sunnyvale CA 94087",
    "addr:housenumber":"825",
    "addr:postcode":"94087",
    "addr:street":"Trenton Dr",
    "iso:country":"US",
    "sg:address":"825 Trenton Dr",
    "sg:city":"Sunnyvale",
    "sg:classifiers":[
        {
            "category":"Travel",
            "subcategory":"Travel Agent",
            "type":"Entertainment"
        }
    ],
    "sg:phone":"+1 408 739 1086",
    "sg:postcode":"94087",
    "sg:province":"CA",
    "sg:tags":[
        "operator",
        "tour"
    ],
    "wof:name":"JC Tours",
    "wof:placetype":"venue"
},
  "geometry": {"coordinates":[-122.047282,37.354369],"type":"Point"}
}