{
  "type": "Feature",
  "properties": {
    "addr:full":"2443 Fair Oaks Blvd Sacramento CA 95825",
    "addr:housenumber":"2443",
    "addr:postcode":"95825",
    "addr:street":"Fair Oaks Blvd",
    "iso:country":"US",
    "sg:address":"2443 Fair Oaks Blvd",
    "sg:city":"Sacramento",
    "sg:classifiers":[
        {
            "category":"Professional",
            "subcategory":"Art Services",
            "type":"Services"
        }
    ],
    "sg:phone":"+1 916 442 0737",
    "sg:postcode":"95825",
    "sg:province":"CA",
    "sg:tags":[
        "photographer"
    ],
    "wof:name":"John Swain Photography",
    "wof:placetype":"venue"
},
  "geometry": {"coordinates":[-121.406003,38.574201],"type":"Point"}
}