{
  "type": "Feature",
  "properties": {
    "addr:full":"1524 Jacob Ave San Jose CA 95118",
    "addr:housenumber":"1524",
    "addr:postcode":"95118",
    "addr:street":"Jacob Ave",
    "iso:country":"US",
    "sg:address":"1524 Jacob Ave",
    "sg:city":"San Jose",
    "sg:classifiers":[
        {
            "category":"Education",
            "subcategory":"School",
            "type":"Public Place"
        }
    ],
    "sg:phone":"+1 408 978 1078",
    "sg:postcode":"95118",
    "sg:province":"CA",
    "wof:name":"Emq Children Family Services",
    "wof:placetype":"venue"
},
  "geometry": {"coordinates":[-121.894997,37.264801],"type":"Point"}
}