{
  "type": "Feature",
  "properties": {
    "iso:country":"US",
    "sg:address":"627 N Azusa Ave",
    "sg:city":"Azusa",
    "sg:classifiers":[
        {
            "category":"Home & Garden",
            "subcategory":"Home Furnishings",
            "type":"Retail Goods"
        }
    ],
    "sg:phone":"+1 626 334 7422",
    "sg:postcode":"91702",
    "sg:province":"CA",
    "sg:tags":[
        "draperies",
        "window",
        "treatment",
        "curtain",
        "drapery",
        "trimming"
    ],
    "wof:name":"V&M Draperies & Carpet",
    "wof:placetype":"venue"
},
  "geometry": {"coordinates":[-117.907532,34.131767],"type":"Point"}
}