{
  "type": "Feature",
  "properties": {
    "addr:full":"5315 Yarmouth Ave # 112 Encino CA 91316",
    "addr:housenumber":"5315",
    "addr:postcode":"91316",
    "addr:street":"Yarmouth Ave # 112",
    "iso:country":"US",
    "sg:address":"5315 Yarmouth Ave # 112",
    "sg:city":"Encino",
    "sg:classifiers":[
        {
            "category":"Real Estate",
            "subcategory":"Real Estate Operator",
            "type":"Services"
        }
    ],
    "sg:phone":"+1 818 609 8767",
    "sg:postcode":"91316",
    "sg:province":"CA",
    "sg:tags":[
        "apartment"
    ],
    "wof:name":"Amarillo Tzinberg Apartments",
    "wof:placetype":"venue"
},
  "geometry": {"coordinates":[-118.52027200000001,34.167236],"type":"Point"}
}