{
  "type": "Feature",
  "properties": {
    "addr:full":"501 Gibson Rd Roseville CA 95695",
    "addr:housenumber":"501",
    "addr:postcode":"95695",
    "addr:street":"Gibson Rd",
    "iso:country":"US",
    "sg:address":"501 Gibson Rd",
    "sg:city":"Roseville",
    "sg:classifiers":[
        {
            "category":"Shopping",
            "subcategory":"Used Merchandise",
            "type":"Retail Goods"
        }
    ],
    "sg:phone":"+1 916 780 0804",
    "sg:postcode":"95695",
    "sg:province":"CA",
    "sg:tags":[
        "antique"
    ],
    "wof:name":"Rock Around The Clock",
    "wof:placetype":"venue"
},
  "geometry": {"coordinates":[-121.772463,38.662901],"type":"Point"}
}