{
  "type": "Feature",
  "properties": {
    "addr:full":"7985 Sewell Ct Sacramento CA 95828",
    "addr:housenumber":"7985",
    "addr:postcode":"95828",
    "addr:street":"Sewell Ct",
    "iso:country":"US",
    "sg:address":"7985 Sewell Ct",
    "sg:city":"Sacramento",
    "sg:classifiers":[
        {
            "category":"Shopping",
            "subcategory":"Gifts & Souvenirs",
            "type":"Retail Goods"
        }
    ],
    "sg:phone":"+1 916 688 5226",
    "sg:postcode":"95828",
    "sg:province":"CA",
    "sg:tags":[
        "shop"
    ],
    "wof:name":"Ultimate Gifts",
    "wof:placetype":"venue"
},
  "geometry": {"coordinates":[-121.403801,38.467518],"type":"Point"}
}