{
  "type": "Feature",
  "properties": {
    "addr:full":"16327 S Vermont Ave Gardena CA 90247",
    "addr:housenumber":"16327",
    "addr:postcode":"90247",
    "addr:street":"S Vermont Ave",
    "iso:country":"US",
    "sg:address":"16327 S Vermont Ave",
    "sg:city":"Gardena",
    "sg:classifiers":[
        {
            "category":"Retail",
            "subcategory":"Auto Repair",
            "type":"Services"
        }
    ],
    "sg:phone":"+1 310 323 1605",
    "sg:postcode":"90247",
    "sg:province":"CA",
    "sg:tags":[
        "repairing",
        "automobile"
    ],
    "wof:name":"Bob & George's Auto Service",
    "wof:placetype":"venue"
},
  "geometry": {"coordinates":[-118.291,33.883099],"type":"Point"}
}