{
  "type": "Feature",
  "properties": {
    "addr:full":"1426 Gina Dr Oxnard CA 93030",
    "addr:housenumber":"1426",
    "addr:postcode":"93030",
    "addr:street":"Gina Dr",
    "iso:country":"US",
    "sg:address":"1426 Gina Dr",
    "sg:city":"Oxnard",
    "sg:classifiers":[
        {
            "category":"Health Services",
            "subcategory":"Hospital",
            "type":"Services"
        }
    ],
    "sg:phone":"+1 805 982 6369",
    "sg:postcode":"93030",
    "sg:province":"CA",
    "sg:tags":[
        "general"
    ],
    "wof:name":"Navy Medical Center",
    "wof:placetype":"venue"
},
  "geometry": {"coordinates":[-119.19590599999999,34.215992],"type":"Point"}
}