{
  "type": "Feature",
  "properties": {
    "iso:country":"US",
    "sg:address":"1425 Yosemite Ave",
    "sg:city":"San Francisco",
    "sg:classifiers":[
        {
            "category":"Autos & Motor Vehicles",
            "subcategory":"Auto Supplies",
            "type":"Retail Goods"
        }
    ],
    "sg:phone":"+1 415 822 4450",
    "sg:postcode":"94124",
    "sg:province":"CA",
    "sg:tags":[
        "automotive",
        "part",
        "automobile"
    ],
    "wof:name":"Auto Row Repair Center",
    "wof:placetype":"venue"
},
  "geometry": {"coordinates":[-122.38867999999999,37.724848],"type":"Point"}
}