{
  "type": "Feature",
  "properties": {
    "iso:country":"US",
    "sg:address":"20124 Sherman Way",
    "sg:city":"Canoga Park",
    "sg:classifiers":[
        {
            "category":"Retail",
            "subcategory":"Auto Repair",
            "type":"Services"
        }
    ],
    "sg:phone":"+1 818 887 9489",
    "sg:postcode":"91306",
    "sg:province":"CA",
    "wof:name":"MeXico MUffler 1",
    "wof:placetype":"venue"
},
  "geometry": {"coordinates":[-118.571816,34.200862],"type":"Point"}
}