{
  "type": "Feature",
  "properties": {
    "iso:country":"US",
    "sg:address":"4020 el Camino Ave",
    "sg:city":"Sacramento",
    "sg:classifiers":[
        {
            "category":"Professional",
            "subcategory":"Business Services",
            "type":"Services"
        }
    ],
    "sg:phone":"+1 916 487 4801",
    "sg:postcode":"95821",
    "sg:province":"CA",
    "wof:name":"Muscolino Inventory Service",
    "wof:placetype":"venue"
},
  "geometry": {"coordinates":[-121.369077,38.610217],"type":"Point"}
}