{
  "type": "Feature",
  "properties": {
    "iso:country":"US",
    "sg:address":"17 Las Tunas Dr",
    "sg:city":"Arcadia",
    "sg:classifiers":[
        {
            "category":"Shopping",
            "subcategory":"Used Merchandise",
            "type":"Retail Goods"
        }
    ],
    "sg:phone":"+1 626 574 7625",
    "sg:postcode":"91007",
    "sg:province":"CA",
    "sg:tags":[
        "shop",
        "thrift"
    ],
    "wof:name":"Goodwill Industries",
    "wof:placetype":"venue"
},
  "geometry": {"coordinates":[-118.033653,34.107681],"type":"Point"}
}