{
  "type": "Feature",
  "properties": {
    "addr:full":"332 Pine St San Francisco CA 94104",
    "addr:housenumber":"332",
    "addr:postcode":"94104",
    "addr:street":"Pine St",
    "iso:country":"US",
    "sg:address":"332 Pine St",
    "sg:city":"San Francisco",
    "sg:classifiers":[
        {
            "category":"Banks & Credit Unions",
            "subcategory":"Investment Brokerage",
            "type":"Services"
        }
    ],
    "sg:phone":"+1 415 292 3446",
    "sg:postcode":"94104",
    "sg:province":"CA",
    "sg:tags":[
        "consultant",
        "planning",
        "financial"
    ],
    "wof:name":"Portsmouth Finicial Svc",
    "wof:placetype":"venue"
},
  "geometry": {"coordinates":[-122.401732,37.792082],"type":"Point"}
}