{
  "type": "Feature",
  "properties": {
    "addr:full":"10349 Balboa Blvd Granada Hills CA 91344",
    "addr:housenumber":"10349",
    "addr:postcode":"91344",
    "addr:street":"Balboa Blvd",
    "iso:country":"US",
    "sg:address":"10349 Balboa Blvd",
    "sg:city":"Granada Hills",
    "sg:classifiers":[
        {
            "category":"Health Services",
            "subcategory":"Clinic",
            "type":"Services"
        }
    ],
    "sg:phone":"+1 818 363 4649",
    "sg:postcode":"91344",
    "sg:province":"CA",
    "wof:name":"U S Health Care Consultants",
    "wof:placetype":"venue"
},
  "geometry": {"coordinates":[-118.502399,34.25833],"type":"Point"}
}