{
  "type": "Feature",
  "properties": {
    "addr:full":"4909 Felspar St Riverside CA 92509",
    "addr:housenumber":"4909",
    "addr:postcode":"92509",
    "addr:street":"Felspar St",
    "iso:country":"US",
    "sg:address":"4909 Felspar St",
    "sg:city":"Riverside",
    "sg:classifiers":[
        {
            "category":"Retail",
            "subcategory":"Storage",
            "type":"Services"
        },
        {
            "category":"Manufacturing",
            "subcategory":"Paper Products",
            "type":"Manufacturing & Wholesale Goods"
        }
    ],
    "sg:phone":"+1 951 681 2289",
    "sg:postcode":"92509",
    "sg:province":"CA",
    "sg:tags":[
        "fiber",
        "automobile",
        "household",
        "commercial",
        "boxes-corrugated",
        "self",
        "boat"
    ],
    "sg:website":"http://www.ustoreit.com/?utm_source=yellowpages&utm_medium=premium&utm_campaign=yp2010&phid=0270",
    "wof:name":"U-Store-It",
    "wof:placetype":"venue"
},
  "geometry": {"coordinates":[-117.484127,33.998609],"type":"Point"}
}