{
  "type": "Feature",
  "properties": {
    "addr:full":"3120 Meadows Ave Merced CA 95348",
    "addr:housenumber":"3120",
    "addr:postcode":"95348",
    "addr:street":"Meadows Ave",
    "iso:country":"US",
    "sg:address":"3120 Meadows Ave",
    "sg:city":"Merced",
    "sg:classifiers":[
        {
            "category":"Shopping",
            "subcategory":"Crafts & Fabrics",
            "type":"Retail Goods"
        }
    ],
    "sg:phone":"+1 209 723 7433",
    "sg:postcode":"95348",
    "sg:province":"CA",
    "sg:tags":[
        "shop"
    ],
    "wof:name":"Jo-Ann Fabrics & Crafts",
    "wof:placetype":"venue"
},
  "geometry": {"coordinates":[-120.49034899999999,37.319606],"type":"Point"}
}