{
  "type": "Feature",
  "properties": {
    "addr:full":"111 S Grand Ave Los Angeles CA 90012",
    "addr:housenumber":"111",
    "addr:postcode":"90012",
    "addr:street":"S Grand Ave",
    "iso:country":"US",
    "sg:address":"111 S Grand Ave",
    "sg:city":"Los Angeles",
    "sg:classifiers":[
        {
            "category":"Home & Garden",
            "subcategory":"Building Materials",
            "type":"Retail Goods"
        }
    ],
    "sg:phone":"+1 213 260 9798",
    "sg:postcode":"90012",
    "sg:province":"CA",
    "sg:tags":[
        "supply"
    ],
    "wof:name":"Custom Design Iron Works, Inc",
    "wof:placetype":"venue"
},
  "geometry": {"coordinates":[-118.24961,34.055051],"type":"Point"}
}