{
  "type": "Feature",
  "properties": {
    "iso:country":"US",
    "sg:address":"1625 G St",
    "sg:city":"Reedley",
    "sg:classifiers":[
        {
            "category":"Freight",
            "type":"Transportation"
        }
    ],
    "sg:phone":"+1 559 637 9999",
    "sg:postcode":"93654",
    "sg:province":"CA",
    "sg:tags":[
        "refrigeration"
    ],
    "wof:name":"Hamilton Cold Storage Inc",
    "wof:placetype":"venue"
},
  "geometry": {"coordinates":[-119.444632,36.590412],"type":"Point"}
}