{
  "type": "Feature",
  "properties": {
    "addr:full":"6450 Leland St Ventura CA 93003",
    "addr:housenumber":"6450",
    "addr:postcode":"93003",
    "addr:street":"Leland St",
    "iso:country":"US",
    "sg:address":"6450 Leland St",
    "sg:city":"Ventura",
    "sg:classifiers":[
        {
            "category":"Autos & Motor Vehicles",
            "subcategory":"Automobile Sales",
            "type":"Retail Goods"
        }
    ],
    "sg:phone":"+1 805 654 0066",
    "sg:postcode":"93003",
    "sg:province":"CA",
    "sg:tags":[
        "car",
        "dealer"
    ],
    "wof:name":"Vista Honda",
    "wof:placetype":"venue"
},
  "geometry": {"coordinates":[-119.198294,34.244925],"type":"Point"}
}