{
  "type": "Feature",
  "properties": {
    "iso:country":"US",
    "sg:address":"3603 California St",
    "sg:city":"Eureka",
    "sg:classifiers":[
        {
            "category":"Building & Trades",
            "subcategory":"Construction",
            "type":"Services"
        }
    ],
    "sg:phone":"+1 707 445 3350",
    "sg:postcode":"95503",
    "sg:province":"CA",
    "sg:tags":[
        "general",
        "contractor"
    ],
    "wof:name":"S & W Construction",
    "wof:placetype":"venue"
},
  "geometry": {"coordinates":[-124.171456,40.774806],"type":"Point"}
}