{
  "type": "Feature",
  "properties": {
    "addr:full":"1555 Camino Del Mar suite 115 Del Mar CA 92014",
    "addr:housenumber":"1555",
    "addr:postcode":"92014",
    "addr:street":"Camino Del Mar Suite 115",
    "iso:country":"US",
    "sg:address":"1555 Camino Del Mar suite 115",
    "sg:city":"Del Mar",
    "sg:classifiers":[
        {
            "category":"Shopping",
            "subcategory":"Clothing, Apparel, & Fashions",
            "type":"Retail Goods"
        },
        {
            "category":"Sports & Exercise",
            "subcategory":"Bicycle Rental",
            "type":"Entertainment"
        }
    ],
    "sg:phone":"+1 858 259 0473",
    "sg:postcode":"92014",
    "sg:province":"CA",
    "sg:tags":[
        "clothing",
        "wear",
        "women's"
    ],
    "sg:website":"www.sandiegobeachwear.com",
    "wof:name":"San Diego Beachwear",
    "wof:placetype":"venue"
},
  "geometry": {"coordinates":[-117.264999,32.960499],"type":"Point"}
}