{
  "type": "Feature",
  "properties": {
    "iso:country":"US",
    "sg:address":"434 Firebird Ln",
    "sg:city":"San Marcos",
    "sg:classifiers":[
        {
            "category":"Real Estate",
            "subcategory":"Real Estate Operator",
            "type":"Services"
        }
    ],
    "sg:phone":"+1 760 471 4908",
    "sg:postcode":"92069",
    "sg:province":"CA",
    "sg:tags":[
        "apartment"
    ],
    "wof:name":"Firebird Manor Apartments",
    "wof:placetype":"venue"
},
  "geometry": {"coordinates":[-117.16473999999999,33.145418],"type":"Point"}
}