{
  "type": "Feature",
  "properties": {
    "iso:country":"US",
    "sg:address":"8775 Production Ave",
    "sg:city":"San Diego",
    "sg:classifiers":[
        {
            "category":"Home & Garden",
            "subcategory":"Building Materials",
            "type":"Retail Goods"
        }
    ],
    "sg:phone":"+1 858 549 3667",
    "sg:postcode":"92121",
    "sg:province":"CA",
    "sg:tags":[
        "door"
    ],
    "wof:name":"Millennium Garage Doors",
    "wof:placetype":"venue"
},
  "geometry": {"coordinates":[-117.165733,32.881624],"type":"Point"}
}