{
  "type": "Feature",
  "properties": {
    "iso:country":"US",
    "sg:address":"7628 Crystal Blvd",
    "sg:city":"El Dorado",
    "sg:classifiers":[
        {
            "category":"Manufacturing",
            "subcategory":"Signs",
            "type":"Manufacturing & Wholesale Goods"
        }
    ],
    "sg:phone":"+1 530 620 1066",
    "sg:postcode":"95623",
    "sg:province":"CA",
    "wof:name":"Hubbard Sign Co",
    "wof:placetype":"venue"
},
  "geometry": {"coordinates":[-120.855349,38.586776],"type":"Point"}
}