{
  "type": "Feature",
  "properties": {
    "iso:country":"US",
    "sg:address":"5511 W Pico Blvd",
    "sg:city":"Los Angeles",
    "sg:classifiers":[
        {
            "category":"Manufacturing",
            "subcategory":"Printing",
            "type":"Manufacturing & Wholesale Goods"
        }
    ],
    "sg:phone":"+1 323 934 6511",
    "sg:postcode":"90019",
    "sg:province":"CA",
    "sg:tags":[
        "commercial",
        "lithographic"
    ],
    "wof:name":"Del Rey Printing",
    "wof:placetype":"venue"
},
  "geometry": {"coordinates":[-118.357467,34.048911],"type":"Point"}
}