{
  "type": "Feature",
  "properties": {
    "addr:full":"2000 Outlet Center Dr Oxnard CA 93036",
    "addr:housenumber":"2000",
    "addr:postcode":"93036",
    "addr:street":"Outlet Center Dr",
    "iso:country":"US",
    "sg:address":"2000 Outlet Center Dr",
    "sg:city":"Oxnard",
    "sg:classifiers":[
        {
            "category":"Manufacturing",
            "subcategory":"Electronics",
            "type":"Manufacturing & Wholesale Goods"
        },
        {
            "category":"Wholesale",
            "subcategory":"Electrical",
            "type":"Manufacturing & Wholesale Goods"
        }
    ],
    "sg:phone":"+1 805 485 4033",
    "sg:postcode":"93036",
    "sg:province":"CA",
    "sg:tags":[
        "equipment",
        "electronic",
        "supply"
    ],
    "wof:name":"Mar Vac Electronics",
    "wof:placetype":"venue"
},
  "geometry": {"coordinates":[-119.14838,34.221637],"type":"Point"}
}