{
  "type": "Feature",
  "properties": {
    "addr:full":"1135 E Santa Clara Street San Jose CA 95116",
    "addr:housenumber":"1135",
    "addr:postcode":"95116",
    "addr:street":"E Santa Clara Street",
    "iso:country":"US",
    "sg:address":"1135 E Santa Clara Street",
    "sg:city":"San Jose",
    "sg:classifiers":[
        {
            "category":"Shopping",
            "subcategory":"Computers & Home Electronics",
            "type":"Retail Goods"
        }
    ],
    "sg:phone":"+1 408 947 9999",
    "sg:postcode":"95116",
    "sg:province":"CA",
    "wof:name":"AA Satellite & Wireless",
    "wof:placetype":"venue"
},
  "geometry": {"coordinates":[-121.86827599999999,37.346851],"type":"Point"}
}