{
  "type": "Feature",
  "properties": {
    "iso:country":"US",
    "sg:address":"1366 Fitzuren Rd",
    "sg:city":"Antioch",
    "sg:classifiers":[
        {
            "category":"Food & Beverages",
            "subcategory":"Liquor & Beverages",
            "type":"Retail Goods"
        }
    ],
    "sg:phone":"+1 925 778 3061",
    "sg:postcode":"94509",
    "sg:province":"CA",
    "wof:name":"Bottom's Up Liquor & Market",
    "wof:placetype":"venue"
},
  "geometry": {"coordinates":[-121.817571,37.997946],"type":"Point"}
}