{
  "type": "Feature",
  "properties": {
    "iso:country":"US",
    "sg:address":"1400 Bristol St N Ste 100",
    "sg:city":"Newport Beach",
    "sg:classifiers":[
        {
            "category":"Health Services",
            "subcategory":"Doctor",
            "type":"Services"
        }
    ],
    "sg:phone":"+1 949 724 8956",
    "sg:postcode":"92660",
    "sg:province":"CA",
    "wof:name":"Mercer Patricia PHD",
    "wof:placetype":"venue"
},
  "geometry": {"coordinates":[-117.86900300000001,33.6591],"type":"Point"}
}