{
  "type": "Feature",
  "properties": {
    "iso:country":"US",
    "sg:address":"5632 Van Nuys Blvd",
    "sg:city":"Van Nuys",
    "sg:classifiers":[
        {
            "category":"Wholesale",
            "subcategory":"Non-durable Goods",
            "type":"Manufacturing & Wholesale Goods"
        }
    ],
    "sg:phone":"+1 818 464 3757",
    "sg:postcode":"91401",
    "sg:province":"CA",
    "wof:name":"Crestview Enterprises",
    "wof:placetype":"venue"
},
  "geometry": {"coordinates":[-118.448632,34.175158],"type":"Point"}
}