{
  "type": "Feature",
  "properties": {
    "addr:full":"2200 State Rte 66 Glendora CA 91740",
    "addr:housenumber":"2200",
    "addr:postcode":"91740",
    "addr:street":"State Rte 66",
    "iso:country":"US",
    "sg:address":"2200 State Rte 66",
    "sg:city":"Glendora",
    "sg:classifiers":[
        {
            "category":"Banks & Credit Unions",
            "subcategory":"Bank",
            "type":"Services"
        }
    ],
    "sg:phone":"+1 626 914 9899",
    "sg:postcode":"91740",
    "sg:province":"CA",
    "sg:tags":[
        "loan",
        "real estate"
    ],
    "wof:name":"Stonecreek Capital Mortgage",
    "wof:placetype":"venue"
},
  "geometry": {"coordinates":[-117.820662,34.126939],"type":"Point"}
}