{
  "type": "Feature",
  "properties": {
    "iso:country":"US",
    "sg:address":"8984 Brydon Way",
    "sg:city":"Sacramento",
    "sg:classifiers":[
        {
            "category":"Wholesale",
            "subcategory":"Jewelry",
            "type":"Manufacturing & Wholesale Goods"
        }
    ],
    "sg:phone":"+1 916 368 7239",
    "sg:postcode":"95826",
    "sg:province":"CA",
    "sg:tags":[
        "jeweler"
    ],
    "wof:name":"Charming Just Charming",
    "wof:placetype":"venue"
},
  "geometry": {"coordinates":[-121.36909,38.544905],"type":"Point"}
}