{
  "type": "Feature",
  "properties": {
    "addr:full":"1228 S Bascom Ave Unit B San Jose CA 95128",
    "addr:housenumber":"1228",
    "addr:postcode":"95128",
    "addr:street":"S Bascom Ave Unit B",
    "iso:country":"US",
    "sg:address":"1228 S Bascom Ave Unit B",
    "sg:city":"San Jose",
    "sg:classifiers":[
        {
            "category":"Building & Trades",
            "subcategory":"Construction",
            "type":"Services"
        },
        {
            "category":"Building & Trades",
            "subcategory":"Electrical",
            "type":"Services"
        }
    ],
    "sg:phone":"+1 408 293 1330",
    "sg:postcode":"95128",
    "sg:province":"CA",
    "sg:tags":[
        "interior",
        "design",
        "electrician",
        "contractor"
    ],
    "sg:website":"www.ModernTvOnline.com",
    "wof:name":"Modern TV Custom Home Theater",
    "wof:placetype":"venue"
},
  "geometry": {"coordinates":[-121.93099100000001,37.303343],"type":"Point"}
}