{
  "type": "Feature",
  "properties": {
    "addr:full":"104 S Myrtle Ave Monrovia CA 91016",
    "addr:housenumber":"104",
    "addr:postcode":"91016",
    "addr:street":"S Myrtle Ave",
    "iso:country":"US",
    "sg:address":"104 S Myrtle Ave",
    "sg:city":"Monrovia",
    "sg:classifiers":[
        {
            "category":"Restaurant",
            "type":"Food & Drink"
        }
    ],
    "sg:menulink":"http://www.allmenus.com/ca/upper-san-gabriel-valley/123232-quiznos-sub/menu/",
    "sg:phone":"+1 626 358 4111",
    "sg:postcode":"91016",
    "sg:province":"CA",
    "sg:tags":[
        "wrap",
        "american",
        "sandwich"
    ],
    "wof:name":"Quiznos Sub",
    "wof:placetype":"venue"
},
  "geometry": {"coordinates":[-118.001036,34.151284],"type":"Point"}
}