{
  "type": "Feature",
  "properties": {
    "iso:country":"US",
    "sg:address":"5742 Research Dr",
    "sg:city":"Huntington Beach",
    "sg:classifiers":[
        {
            "category":"Building & Trades",
            "subcategory":"Construction",
            "type":"Services"
        }
    ],
    "sg:phone":"+1 714 891 9791",
    "sg:postcode":"92649",
    "sg:province":"CA",
    "sg:tags":[
        "mobile",
        "house",
        "nonresidential",
        "home"
    ],
    "wof:name":"Almquist Mobile Home Service",
    "wof:placetype":"venue"
},
  "geometry": {"coordinates":[-118.02843,33.73406],"type":"Point"}
}