{
  "type": "Feature",
  "properties": {
    "addr:full":"San Francisco International Airport Terminal 1- Gate 42 San Francisco CA 94128",
    "addr:housenumber":"42",
    "addr:postcode":"94128",
    "addr:street":"Gate",
    "iso:country":"US",
    "sg:address":"San Francisco International Airport Terminal 1- Gate 42",
    "sg:city":"San Francisco",
    "sg:classifiers":[
        {
            "category":"Restaurant",
            "type":"Food & Drink"
        }
    ],
    "sg:phone":"+1 650 821 1037",
    "sg:postcode":"94128",
    "sg:province":"CA",
    "sg:tags":[
        "traditional",
        "american"
    ],
    "sg:website":"www.tastesonthefly.com",
    "wof:name":"Perry's",
    "wof:placetype":"venue"
},
  "geometry": {"coordinates":[-122.38554999999999,37.614707],"type":"Point"}
}