{
  "type": "Feature",
  "properties": {
    "addr:full":"1875 Wyandotte Ave Oroville CA 95966",
    "addr:housenumber":"1875",
    "addr:postcode":"95966",
    "addr:street":"Wyandotte Ave",
    "iso:country":"US",
    "sg:address":"1875 Wyandotte Ave",
    "sg:city":"Oroville",
    "sg:classifiers":[
        {
            "category":"Building & Trades",
            "subcategory":"Construction",
            "type":"Services"
        }
    ],
    "sg:phone":"+1 530 533 6393",
    "sg:postcode":"95966",
    "sg:province":"CA",
    "sg:tags":[
        "roofing",
        "contractor"
    ],
    "wof:name":"George Roofing",
    "wof:placetype":"venue"
},
  "geometry": {"coordinates":[-121.552289,39.50022],"type":"Point"}
}