{
  "type": "Feature",
  "properties": {
    "iso:country":"US",
    "sg:address":"302 Fresno St Ste 106",
    "sg:city":"Fresno",
    "sg:phone":"+1 559 268 7851",
    "sg:postcode":"93706",
    "sg:province":"CA",
    "wof:name":"Gail Mallard-Warren Inc",
    "wof:placetype":"venue"
},
  "geometry": {"coordinates":[-119.809382,36.723766],"type":"Point"}
}