{
  "type": "Feature",
  "properties": {
    "iso:country":"US",
    "sg:address":"2236 Mariner Square Dr",
    "sg:city":"Alameda",
    "sg:classifiers":[
        {
            "category":"Shopping",
            "subcategory":"Computers & Home Electronics",
            "type":"Retail Goods"
        }
    ],
    "sg:phone":"+1 510 748 6507",
    "sg:postcode":"94501",
    "sg:province":"CA",
    "wof:name":"DISH Network",
    "wof:placetype":"venue"
},
  "geometry": {"coordinates":[-122.27609099999999,37.785862],"type":"Point"}
}