{
  "type": "Feature",
  "properties": {
    "addr:full":"10123 Wolfe Rd Cupertino CA 95014",
    "addr:housenumber":"10123",
    "addr:postcode":"95014",
    "addr:street":"Wolfe Rd",
    "iso:country":"US",
    "sg:address":"10123 Wolfe Rd",
    "sg:city":"Cupertino",
    "sg:classifiers":[
        {
            "category":"Shopping",
            "subcategory":"Clothing, Apparel, & Fashions",
            "type":"Retail Goods"
        }
    ],
    "sg:postcode":"95014",
    "sg:province":"CA",
    "sg:website":"steveandbarrys.com",
    "wof:name":"Steve & Barry's",
    "wof:placetype":"venue"
},
  "geometry": {"coordinates":[-122.014402,37.326341],"type":"Point"}
}