{
  "type": "Feature",
  "properties": {
    "iso:country":"US",
    "sg:address":"242 N Hopper Rd",
    "sg:city":"Modesto",
    "sg:classifiers":[
        {
            "category":"Building & Trades",
            "subcategory":"Construction",
            "type":"Services"
        },
        {
            "category":"Wholesale",
            "subcategory":"Groceries",
            "type":"Manufacturing & Wholesale Goods"
        }
    ],
    "sg:phone":"+1 209 523 8839",
    "sg:postcode":"95357",
    "sg:province":"CA",
    "sg:tags":[
        "honey",
        "excavation",
        "contractor"
    ],
    "wof:name":"Duncans Honey",
    "wof:placetype":"venue"
},
  "geometry": {"coordinates":[-120.829373,37.644395],"type":"Point"}
}