{
  "type": "Feature",
  "properties": {
    "iso:country":"US",
    "sg:address":"1912 McGee Ave",
    "sg:city":"Berkeley",
    "sg:classifiers":[
        {
            "category":"Building & Trades",
            "subcategory":"Landscaping Services",
            "type":"Services"
        }
    ],
    "sg:phone":"+1 510 845 0633",
    "sg:postcode":"94703",
    "sg:province":"CA",
    "sg:tags":[
        "counseling",
        "planning",
        "landscape"
    ],
    "wof:name":"Landscape Architecture",
    "wof:placetype":"venue"
},
  "geometry": {"coordinates":[-122.27774599999999,37.872278],"type":"Point"}
}