{
  "type": "Feature",
  "properties": {
    "iso:country":"US",
    "sg:address":"1225 Santo Domingo Ave",
    "sg:city":"Duarte",
    "sg:classifiers":[
        {
            "category":"Wholesale",
            "subcategory":"Durable Goods & Equipment",
            "type":"Manufacturing & Wholesale Goods"
        }
    ],
    "sg:phone":"+1 626 359 1913",
    "sg:postcode":"91010",
    "sg:province":"CA",
    "sg:tags":[
        "importer"
    ],
    "wof:name":"Aguirre Tequila Imports",
    "wof:placetype":"venue"
},
  "geometry": {"coordinates":[-117.96448599999999,34.139459],"type":"Point"}
}