{
  "type": "Feature",
  "properties": {
    "addr:full":"101 Golf Course Dr Rohnert Park CA 94928",
    "addr:housenumber":"101",
    "addr:postcode":"94928",
    "addr:street":"Golf Course Dr",
    "iso:country":"US",
    "sg:address":"101 Golf Course Dr",
    "sg:city":"Rohnert Park",
    "sg:classifiers":[
        {
            "category":"Professional",
            "subcategory":"Lawyer & Legal Services",
            "type":"Services"
        }
    ],
    "sg:phone":"+1 707 578 5788",
    "sg:postcode":"94928",
    "sg:province":"CA",
    "sg:tags":[
        "attorney"
    ],
    "wof:name":"Sam Libicki & Assoc",
    "wof:placetype":"venue"
},
  "geometry": {"coordinates":[-122.70890199999999,38.362902],"type":"Point"}
}