{
  "type": "Feature",
  "properties": {
    "addr:full":"2865 Fidler Ave Long Beach CA 90815",
    "addr:housenumber":"2865",
    "addr:postcode":"90815",
    "addr:street":"Fidler Ave",
    "iso:country":"US",
    "sg:address":"2865 Fidler Ave",
    "sg:city":"Long Beach",
    "sg:classifiers":[
        {
            "category":"Professional",
            "subcategory":"Management & Consulting",
            "type":"Services"
        }
    ],
    "sg:phone":"+1 562 421 2826",
    "sg:postcode":"90815",
    "sg:province":"CA",
    "sg:tags":[
        "consultant"
    ],
    "wof:name":"Illarij Pictures",
    "wof:placetype":"venue"
},
  "geometry": {"coordinates":[-118.132046,33.808788],"type":"Point"}
}