{
  "type": "Feature",
  "properties": {
    "addr:full":"2400 E Katella Ave Anaheim CA 92805",
    "addr:housenumber":"2400",
    "addr:postcode":"92805",
    "addr:street":"E Katella Ave",
    "iso:country":"US",
    "sg:address":"2400 E Katella Ave",
    "sg:city":"Anaheim",
    "sg:classifiers":[
        {
            "category":"Utilities",
            "subcategory":"Telephone",
            "type":"Services"
        }
    ],
    "sg:phone":"+1 714 978 0930",
    "sg:postcode":"92805",
    "sg:province":"CA",
    "sg:tags":[
        "communications"
    ],
    "wof:name":"North American Communications",
    "wof:placetype":"venue"
},
  "geometry": {"coordinates":[-117.883043,33.805817],"type":"Point"}
}