{
  "type": "Feature",
  "properties": {
    "iso:country":"US",
    "sg:address":"3603 Verbena Dr",
    "sg:city":"Rialto",
    "sg:classifiers":[
        {
            "category":"Professional",
            "subcategory":"Management & Consulting",
            "type":"Services"
        }
    ],
    "sg:phone":"+1 909 355 1071",
    "sg:postcode":"92377",
    "sg:province":"CA",
    "sg:tags":[
        "consultant",
        "business"
    ],
    "wof:name":"Faxes R Us Inc",
    "wof:placetype":"venue"
},
  "geometry": {"coordinates":[-117.415578,34.164029],"type":"Point"}
}