{
  "type": "Feature",
  "properties": {
    "iso:country":"US",
    "sg:address":"1132 Corona Ln",
    "sg:city":"Costa Mesa",
    "sg:classifiers":[
        {
            "category":"Building & Trades",
            "subcategory":"Landscaping Services",
            "type":"Services"
        }
    ],
    "sg:phone":"+1 714 545 6083",
    "sg:postcode":"92626",
    "sg:province":"CA",
    "wof:name":"Kamikihara Tadashi",
    "wof:placetype":"venue"
},
  "geometry": {"coordinates":[-117.903398,33.675573],"type":"Point"}
}