{
  "type": "Feature",
  "properties": {
    "iso:country":"US",
    "sg:address":"4607 Willowcrest Ave",
    "sg:city":"Toluca Lake",
    "sg:classifiers":[
        {
            "category":"Social Services",
            "subcategory":"Adult Care",
            "type":"Services"
        },
        {
            "category":"Social Services",
            "type":"Services"
        }
    ],
    "sg:phone":"+1 818 766 2236",
    "sg:postcode":"91602",
    "sg:province":"CA",
    "sg:tags":[
        "organization",
        "senior",
        "citizen"
    ],
    "wof:name":"Choice Senior Care",
    "wof:placetype":"venue"
},
  "geometry": {"coordinates":[-118.362681,34.153907],"type":"Point"}
}