{
  "type": "Feature",
  "properties": {
    "iso:country":"US",
    "sg:address":"13822 Brookhurst St",
    "sg:city":"Garden Grove",
    "sg:classifiers":[
        {
            "category":"Wholesale",
            "subcategory":"Stationery",
            "type":"Manufacturing & Wholesale Goods"
        },
        {
            "category":"Shopping",
            "subcategory":"Pharmacy",
            "type":"Retail Goods"
        }
    ],
    "sg:phone":"+1 714 530 3136",
    "sg:postcode":"92843",
    "sg:province":"CA",
    "sg:tags":[
        "drugstore",
        "card"
    ],
    "wof:name":"Rite Aid",
    "wof:placetype":"venue"
},
  "geometry": {"coordinates":[-117.95500199999999,33.761501],"type":"Point"}
}