{
  "type": "Feature",
  "properties": {
    "addr:full":"801 S Ramona St San Gabriel CA 91776",
    "addr:housenumber":"801",
    "addr:postcode":"91776",
    "addr:street":"S Ramona St",
    "iso:country":"US",
    "sg:address":"801 S Ramona St",
    "sg:city":"San Gabriel",
    "sg:classifiers":[
        {
            "category":"Government",
            "subcategory":"Office",
            "type":"Public Place"
        }
    ],
    "sg:phone":"+1 626 308 2586",
    "sg:postcode":"91776",
    "sg:province":"CA",
    "sg:tags":[
        "village"
    ],
    "wof:name":"ROP Office",
    "wof:placetype":"venue"
},
  "geometry": {"coordinates":[-118.107978,34.094585],"type":"Point"}
}