{
  "type": "Feature",
  "properties": {
    "addr:full":"25 Dorian Newport Beach CA 92657",
    "addr:housenumber":"25",
    "addr:postcode":"92657",
    "addr:street":"Dorian",
    "iso:country":"US",
    "sg:address":"25 Dorian",
    "sg:city":"Newport Beach",
    "sg:classifiers":[
        {
            "category":"Manufacturing",
            "subcategory":"Paper Products",
            "type":"Manufacturing & Wholesale Goods"
        },
        {
            "category":"Shopping",
            "subcategory":"Gifts & Souvenirs",
            "type":"Retail Goods"
        }
    ],
    "sg:phone":"+1 949 644 0460",
    "sg:postcode":"92657",
    "sg:province":"CA",
    "sg:tags":[
        "stationery",
        "announcement",
        "invitation",
        "mfg"
    ],
    "wof:name":"Alison's Paperie",
    "wof:placetype":"venue"
},
  "geometry": {"coordinates":[-117.83040699999999,33.608276],"type":"Point"}
}