{
  "type": "Feature",
  "properties": {
    "iso:country":"US",
    "sg:address":"110 W Main St",
    "sg:city":"Turlock",
    "sg:classifiers":[
        {
            "category":"Utilities",
            "subcategory":"Telephone",
            "type":"Services"
        }
    ],
    "sg:phone":"+1 209 668 4462",
    "sg:postcode":"95380",
    "sg:province":"CA",
    "sg:tags":[
        "communications"
    ],
    "wof:name":"Vitual Java",
    "wof:placetype":"venue"
},
  "geometry": {"coordinates":[-120.846926,37.493811],"type":"Point"}
}