{
  "type": "Feature",
  "properties": {
    "iso:country":"US",
    "sg:address":"8166 Whitsett Ave",
    "sg:city":"North Hollywood",
    "sg:classifiers":[
        {
            "category":"Local Transit",
            "type":"Transportation"
        }
    ],
    "sg:phone":"+1 818 503 9969",
    "sg:postcode":"91605",
    "sg:province":"CA",
    "sg:tags":[
        "passenger"
    ],
    "wof:name":"Crystal Crown Limousine Svcs",
    "wof:placetype":"venue"
},
  "geometry": {"coordinates":[-118.40517800000001,34.219688],"type":"Point"}
}