{
  "type": "Feature",
  "properties": {
    "iso:country":"US",
    "sg:address":"1901 Westwood Blvd",
    "sg:city":"Los Angeles",
    "sg:classifiers":[
        {
            "category":"Insurance",
            "subcategory":"Health Insurance",
            "type":"Services"
        }
    ],
    "sg:phone":"+1 310 234 2718",
    "sg:postcode":"90025",
    "sg:province":"CA",
    "sg:tags":[
        "market"
    ],
    "sg:website":"www.vitaminshoppe.com",
    "wof:name":"The Vitamin Shoppe",
    "wof:placetype":"venue"
},
  "geometry": {"coordinates":[-118.435574,34.047819],"type":"Point"}
}