{
  "type": "Feature",
  "properties": {
    "addr:full":"38930 Blacow Rd Fremont CA 94536",
    "addr:postcode":"38930;94536",
    "addr:street":"Blacow Rd",
    "iso:country":"US",
    "sg:address":"38930 Blacow Rd",
    "sg:city":"Fremont",
    "sg:classifiers":[
        {
            "category":"Professional",
            "subcategory":"Accounting & Tax Preparation",
            "type":"Services"
        }
    ],
    "sg:phone":"+1 510 742 8400",
    "sg:postcode":"94536",
    "sg:province":"CA",
    "sg:tags":[
        "return",
        "filing"
    ],
    "wof:name":"UBS",
    "wof:placetype":"venue"
},
  "geometry": {"coordinates":[-121.999382,37.536946],"type":"Point"}
}