{
  "type": "Feature",
  "properties": {
    "iso:country":"US",
    "sg:address":"2144 Walnut St",
    "sg:city":"Sutter",
    "sg:classifiers":[
        {
            "category":"Building & Trades",
            "subcategory":"Landscaping Services",
            "type":"Services"
        }
    ],
    "sg:phone":"+1 530 674 3616",
    "sg:postcode":"95982",
    "sg:province":"CA",
    "sg:tags":[
        "landscape",
        "contractor"
    ],
    "wof:name":"Anthony's Irrigation Solutions",
    "wof:placetype":"venue"
},
  "geometry": {"coordinates":[-121.755081,39.159238],"type":"Point"}
}