{
  "type": "Feature",
  "properties": {
    "iso:country":"US",
    "sg:address":"2710 Arden Way",
    "sg:city":"Sacramento",
    "sg:classifiers":[
        {
            "category":"Shopping",
            "subcategory":"Hobbies, Toys, & Games",
            "type":"Retail Goods"
        }
    ],
    "sg:phone":"+1 916 487 2646",
    "sg:postcode":"95825",
    "sg:province":"CA",
    "sg:tags":[
        "shop",
        "hobby"
    ],
    "sg:website":"www.excelsiorcoingallery.com/",
    "wof:name":"Excelsior Coin Gallery",
    "wof:placetype":"venue"
},
  "geometry": {"coordinates":[-121.399416,38.595693],"type":"Point"}
}