{
  "type": "Feature",
  "properties": {
    "iso:country":"US",
    "sg:address":"9 Fishermans Wharf",
    "sg:city":"San Francisco",
    "sg:classifiers":[
        {
            "category":"Restaurant",
            "type":"Food & Drink"
        }
    ],
    "sg:menulink":"http://www.allmenus.com/ca/san-francisco/20892-fishermans-grotto/menu/",
    "sg:phone":"+1 415 673 7025",
    "sg:postcode":"94133",
    "sg:province":"CA",
    "sg:tags":[
        "seafood",
        "american"
    ],
    "wof:name":"Fisherman's Grotto",
    "wof:placetype":"venue"
},
  "geometry": {"coordinates":[-122.415954,37.808357],"type":"Point"}
}