{
  "type": "Feature",
  "properties": {
    "addr:full":"7410 Amador Valley Blvd Dublin CA 94568",
    "addr:housenumber":"7410",
    "addr:postcode":"94568",
    "addr:street":"Amador Valley Blvd",
    "iso:country":"US",
    "sg:address":"7410 Amador Valley Blvd",
    "sg:city":"Dublin",
    "sg:classifiers":[
        {
            "category":"Restaurant",
            "type":"Food & Drink"
        }
    ],
    "sg:phone":"+1 925 829 6855",
    "sg:postcode":"94568",
    "sg:province":"CA",
    "wof:name":"Lucky Pizza",
    "wof:placetype":"venue"
},
  "geometry": {"coordinates":[-121.92860899999999,37.709702],"type":"Point"}
}