{
  "type": "Feature",
  "properties": {
    "iso:country":"US",
    "sg:address":"1041 Santa Cruz Way",
    "sg:city":"Rohnert Park",
    "sg:classifiers":[
        {
            "category":"Food & Beverages",
            "subcategory":"Specialty",
            "type":"Retail Goods"
        }
    ],
    "sg:phone":"+1 707 584 9046",
    "sg:postcode":"94928",
    "sg:province":"CA",
    "sg:tags":[
        "herb"
    ],
    "wof:name":"Herbalife An Independent Distr",
    "wof:placetype":"venue"
},
  "geometry": {"coordinates":[-122.690116,38.34853],"type":"Point"}
}