{
  "type": "Feature",
  "properties": {
    "iso:country":"US",
    "sg:address":"323 Lola Ave",
    "sg:city":"Pasadena",
    "sg:classifiers":[
        {
            "category":"Professional",
            "type":"Services"
        }
    ],
    "sg:phone":"+1 626 796 0832",
    "sg:postcode":"91107",
    "sg:province":"CA",
    "wof:name":"David JP Kaloyanides A Proffes",
    "wof:placetype":"venue"
},
  "geometry": {"coordinates":[-118.104422,34.151384],"type":"Point"}
}