{
  "type": "Feature",
  "properties": {
    "addr:full":"6702 Foster Bridge Blvd Bell Gardens CA 90201",
    "addr:housenumber":"6702",
    "addr:postcode":"90201",
    "addr:street":"Foster Bridge Blvd",
    "iso:country":"US",
    "sg:address":"6702 Foster Bridge Blvd",
    "sg:city":"Bell Gardens",
    "sg:classifiers":[
        {
            "category":"Food & Beverages",
            "subcategory":"Groceries & Convenience Stores",
            "type":"Retail Goods"
        }
    ],
    "sg:phone":"+1 562 927 1842",
    "sg:postcode":"90201",
    "sg:province":"CA",
    "sg:tags":[
        "market"
    ],
    "wof:name":"Wilch Brothers Market",
    "wof:placetype":"venue"
},
  "geometry": {"coordinates":[-118.14097599999999,33.969597],"type":"Point"}
}