{
  "type": "Feature",
  "properties": {
    "addr:full":"8273 Azucena Ave Atascadero CA 93422",
    "addr:housenumber":"8273",
    "addr:postcode":"93422",
    "addr:street":"Azucena Ave",
    "iso:country":"US",
    "sg:address":"8273 Azucena Ave",
    "sg:city":"Atascadero",
    "sg:classifiers":[
        {
            "category":"Building & Trades",
            "subcategory":"Construction",
            "type":"Services"
        }
    ],
    "sg:phone":"+1 805 460 9000",
    "sg:postcode":"93422",
    "sg:province":"CA",
    "sg:tags":[
        "roofing",
        "contractor"
    ],
    "wof:name":"North County Roofing",
    "wof:placetype":"venue"
},
  "geometry": {"coordinates":[-120.66686,35.471935],"type":"Point"}
}