{
  "type": "Feature",
  "properties": {
    "addr:full":"1930 Monterey Hwy San Jose CA 95111",
    "addr:housenumber":"1930",
    "addr:postcode":"95111",
    "addr:street":"Monterey Hwy",
    "iso:country":"US",
    "sg:address":"1930 Monterey Hwy",
    "sg:city":"San Jose",
    "sg:classifiers":[
        {
            "category":"Building & Trades",
            "subcategory":"Construction",
            "type":"Services"
        }
    ],
    "sg:phone":"+1 408 275 8750",
    "sg:postcode":"95111",
    "sg:province":"CA",
    "sg:tags":[
        "demolition",
        "contractor"
    ],
    "wof:name":"Earth Moving & Demolition Inc",
    "wof:placetype":"venue"
},
  "geometry": {"coordinates":[-121.864486,37.307054],"type":"Point"}
}