{
  "type": "Feature",
  "properties": {
    "iso:country":"US",
    "sg:address":"1 Dole Dr",
    "sg:city":"Thousand Oaks",
    "sg:classifiers":[
        {
            "category":"Wholesale",
            "subcategory":"Fruits & Vegetables",
            "type":"Manufacturing & Wholesale Goods"
        }
    ],
    "sg:phone":"+1 818 879 6600",
    "sg:postcode":"91362",
    "sg:province":"CA",
    "sg:tags":[
        "fresh"
    ],
    "wof:name":"Dole",
    "wof:placetype":"venue"
},
  "geometry": {"coordinates":[-118.80511,34.151876],"type":"Point"}
}