{
  "type": "Feature",
  "properties": {
    "addr:full":"2722 Ming Ave Bakersfield CA 93304",
    "addr:housenumber":"2722",
    "addr:postcode":"93304",
    "addr:street":"Ming Ave",
    "iso:country":"US",
    "sg:address":"2722 Ming Ave",
    "sg:city":"Bakersfield",
    "sg:classifiers":[
        {
            "category":"Bars & Pubs",
            "type":"Food & Drink"
        }
    ],
    "sg:phone":"+1 661 837 2914",
    "sg:postcode":"93304",
    "sg:province":"CA",
    "sg:tags":[
        "discotheque"
    ],
    "wof:name":"Discoteca Gonzalez Numero Dos",
    "wof:placetype":"venue"
},
  "geometry": {"coordinates":[-119.031622,35.339532],"type":"Point"}
}