{
  "type": "Feature",
  "properties": {
    "addr:full":"3105 W Rosecrans Ave Hawthorne CA 90250",
    "addr:housenumber":"3105",
    "addr:postcode":"90250",
    "addr:street":"W Rosecrans Ave",
    "iso:country":"US",
    "sg:address":"3105 W Rosecrans Ave",
    "sg:city":"Hawthorne",
    "sg:classifiers":[
        {
            "category":"Food & Beverages",
            "subcategory":"Bakery",
            "type":"Retail Goods"
        }
    ],
    "sg:phone":"+1 310 644 9072",
    "sg:postcode":"90250",
    "sg:province":"CA",
    "sg:tags":[
        "doughnut"
    ],
    "wof:name":"J & M Donut",
    "wof:placetype":"venue"
},
  "geometry": {"coordinates":[-118.328581,33.902003],"type":"Point"}
}