{
  "type": "Feature",
  "properties": {
    "iso:country":"US",
    "sg:address":"3316 Maya Linda",
    "sg:city":"Camarillo",
    "sg:classifiers":[
        {
            "category":"Wholesale",
            "subcategory":"Machinery & Supplies",
            "type":"Manufacturing & Wholesale Goods"
        }
    ],
    "sg:phone":"+1 805 445 1410",
    "sg:postcode":"93012",
    "sg:province":"CA",
    "sg:tags":[
        "gage"
    ],
    "sg:website":"www.westerngage.com",
    "wof:name":"Western Gage Corp",
    "wof:placetype":"venue"
},
  "geometry": {"coordinates":[-119.02440199999999,34.224235],"type":"Point"}
}