{
  "type": "Feature",
  "properties": {
    "iso:country":"US",
    "sg:address":"2262 Chelsey Ct",
    "sg:city":"Camarillo",
    "sg:classifiers":[
        {
            "category":"Professional",
            "type":"Services"
        }
    ],
    "sg:phone":"+1 805 484 2383",
    "sg:postcode":"93010",
    "sg:province":"CA",
    "wof:name":"Double V LLC",
    "wof:placetype":"venue"
},
  "geometry": {"coordinates":[-119.05269800000001,34.239863],"type":"Point"}
}