{
  "type": "Feature",
  "properties": {
    "addr:full":"5768 Waltrip Ln San Jose CA 95118",
    "addr:housenumber":"5768",
    "addr:postcode":"95118",
    "addr:street":"Waltrip Ln",
    "iso:country":"US",
    "sg:address":"5768 Waltrip Ln",
    "sg:city":"San Jose",
    "sg:classifiers":[
        {
            "category":"Professional",
            "subcategory":"Management & Consulting",
            "type":"Services"
        }
    ],
    "sg:phone":"+1 408 269 4221",
    "sg:postcode":"95118",
    "sg:province":"CA",
    "sg:tags":[
        "retail",
        "direct",
        "sales"
    ],
    "wof:name":"Hossner Machinery Service",
    "wof:placetype":"venue"
},
  "geometry": {"coordinates":[-121.886478,37.240617],"type":"Point"}
}