{
  "type": "Feature",
  "properties": {
    "iso:country":"US",
    "sg:address":"910 Baywood Dr",
    "sg:city":"Petaluma",
    "sg:classifiers":[
        {
            "category":"Autos & Motor Vehicles",
            "subcategory":"Fuel & Gas Station",
            "type":"Retail Goods"
        }
    ],
    "sg:phone":"+1 707 763 7723",
    "sg:postcode":"94954",
    "sg:province":"CA",
    "sg:tags":[
        "oil"
    ],
    "wof:name":"Metron Super Gas",
    "wof:placetype":"venue"
},
  "geometry": {"coordinates":[-122.6139,38.235374],"type":"Point"}
}