{
  "type": "Feature",
  "properties": {
    "iso:country":"US",
    "sg:address":"9145 Charleville Blvd",
    "sg:city":"Beverly Hills",
    "sg:classifiers":[
        {
            "category":"Wholesale",
            "subcategory":"Medical Equipment & Supplies",
            "type":"Manufacturing & Wholesale Goods"
        }
    ],
    "sg:phone":"+1 310 247 8470",
    "sg:postcode":"90212",
    "sg:province":"CA",
    "sg:tags":[
        "physician",
        "surgeon"
    ],
    "wof:name":"HFK Enterprises",
    "wof:placetype":"venue"
},
  "geometry": {"coordinates":[-118.391034,34.065059],"type":"Point"}
}