{
  "type": "Feature",
  "properties": {
    "addr:full":"820 Manhattan Ave Ste 105 Manhattan Beach CA 90266",
    "addr:housenumber":"820",
    "addr:postcode":"90266",
    "addr:street":"Manhattan Ave Ste 105",
    "iso:country":"US",
    "sg:address":"820 Manhattan Ave Ste 105",
    "sg:city":"Manhattan Beach",
    "sg:classifiers":[
        {
            "category":"Restaurant",
            "type":"Food & Drink"
        }
    ],
    "sg:phone":"+1 310 374 6311",
    "sg:postcode":"90266",
    "sg:province":"CA",
    "sg:tags":[
        "sushi",
        "bar"
    ],
    "wof:name":"Penny Lane",
    "wof:placetype":"venue"
},
  "geometry": {"coordinates":[-118.40938800000001,33.882801],"type":"Point"}
}