{
  "type": "Feature",
  "properties": {
    "addr:full":"410 E Main St El Cajon CA 92020",
    "addr:housenumber":"410",
    "addr:postcode":"92020",
    "addr:street":"E Main St",
    "iso:country":"US",
    "sg:address":"410 E Main St",
    "sg:city":"El Cajon",
    "sg:classifiers":[
        {
            "category":"Food & Beverages",
            "subcategory":"Groceries & Convenience Stores",
            "type":"Retail Goods"
        }
    ],
    "sg:phone":"+1 619 440 7117",
    "sg:postcode":"92020",
    "sg:province":"CA",
    "wof:name":"7-Eleven",
    "wof:placetype":"venue"
},
  "geometry": {"coordinates":[-116.956497,32.795003],"type":"Point"}
}