{
  "type": "Feature",
  "properties": {
    "addr:full":"304 Paseo de Cristobal San Clemente CA 92672",
    "addr:housenumber":"304",
    "addr:postcode":"92672",
    "addr:street":"Paseo De Cristobal",
    "iso:country":"US",
    "sg:address":"304 Paseo de Cristobal",
    "sg:city":"San Clemente",
    "sg:classifiers":[
        {
            "category":"Professional",
            "subcategory":"Advertising",
            "type":"Services"
        }
    ],
    "sg:phone":"+1 925 451 1249",
    "sg:postcode":"92672",
    "sg:province":"CA",
    "sg:tags":[
        "social-media",
        "social",
        "marketing",
        "philanthropy",
        "cause",
        "social-enabling"
    ],
    "sg:website":"http://www.thegluenetwork.com",
    "wof:name":"The Glue Network",
    "wof:placetype":"venue"
},
  "geometry": {"coordinates":[-117.614076,33.41657],"type":"Point"}
}