{
  "type": "Feature",
  "properties": {
    "iso:country":"US",
    "sg:address":"3333 Dwight Way",
    "sg:city":"Berkeley",
    "sg:classifiers":[
        {
            "category":"Organizations",
            "subcategory":"Community Association",
            "type":"Services"
        }
    ],
    "sg:phone":"+1 510 500 4566",
    "sg:postcode":"94704",
    "sg:province":"CA",
    "sg:tags":[
        "program",
        "incentive"
    ],
    "wof:name":"Government Sourcing.Com",
    "wof:placetype":"venue"
},
  "geometry": {"coordinates":[-122.245435,37.868489],"type":"Point"}
}