{
  "type": "Feature",
  "properties": {
    "addr:full":"105 N Spring St Susanville CA 96130",
    "addr:housenumber":"105",
    "addr:postcode":"96130",
    "addr:street":"N Spring St",
    "iso:country":"US",
    "sg:address":"105 N Spring St",
    "sg:city":"Susanville",
    "sg:classifiers":[
        {
            "category":"Retail",
            "subcategory":"Auto Repair",
            "type":"Services"
        }
    ],
    "sg:phone":"+1 530 251 5300",
    "sg:postcode":"96130",
    "sg:province":"CA",
    "sg:tags":[
        "body",
        "automobile",
        "painting"
    ],
    "wof:name":"Bear's Repair",
    "wof:placetype":"venue"
},
  "geometry": {"coordinates":[-120.642802,40.414451],"type":"Point"}
}