{
  "type": "Feature",
  "properties": {
    "addr:full":"725 Marsolan Ave Solana Beach CA 92075",
    "addr:housenumber":"725",
    "addr:postcode":"92075",
    "addr:street":"Marsolan Ave",
    "iso:country":"US",
    "sg:address":"725 Marsolan Ave",
    "sg:city":"Solana Beach",
    "sg:classifiers":[
        {
            "category":"Banks & Credit Unions",
            "subcategory":"Financial Services",
            "type":"Services"
        }
    ],
    "sg:phone":"+1 858 755 1085",
    "sg:postcode":"92075",
    "sg:province":"CA",
    "sg:tags":[
        "trust",
        "management"
    ],
    "wof:name":"Hoggan Family Trust",
    "wof:placetype":"venue"
},
  "geometry": {"coordinates":[-117.26790699999999,32.984353],"type":"Point"}
}