{
  "type": "Feature",
  "properties": {
    "iso:country":"US",
    "sg:address":"4120 E Ocean Blvd",
    "sg:city":"Long Beach",
    "sg:classifiers":[
        {
            "category":"Restaurant",
            "type":"Food & Drink"
        }
    ],
    "sg:phone":"+1 562 433 9317",
    "sg:postcode":"90803",
    "sg:province":"CA",
    "wof:name":"Chuck's Coffee Shop",
    "wof:placetype":"venue"
},
  "geometry": {"coordinates":[-118.144915,33.759042],"type":"Point"}
}