{
  "type": "Feature",
  "properties": {
    "iso:country":"US",
    "sg:address":"391 Foster City Blvd",
    "sg:city":"Foster City",
    "sg:classifiers":[
        {
            "category":"Building & Trades",
            "subcategory":"Construction",
            "type":"Services"
        }
    ],
    "sg:phone":"+1 650 571 6680",
    "sg:postcode":"94404",
    "sg:province":"CA",
    "sg:tags":[
        "resurfacing",
        "laying",
        "refinishing",
        "floor"
    ],
    "wof:name":"Pacific Flooring Manufacture",
    "wof:placetype":"venue"
},
  "geometry": {"coordinates":[-122.27603499999999,37.56776],"type":"Point"}
}