{
  "type": "Feature",
  "properties": {
    "iso:country":"US",
    "sg:address":"4306 Melrose Avenue",
    "sg:city":"Los Angeles",
    "sg:classifiers":[
        {
            "category":"Arts & Performance",
            "subcategory":"Arts Center",
            "type":"Entertainment"
        },
        {
            "category":"Arts & Performance",
            "subcategory":"Music",
            "type":"Entertainment"
        },
        {
            "category":"Arts & Performance",
            "subcategory":"Art Gallery",
            "type":"Entertainment"
        }
    ],
    "sg:phone":"+1 323 284 8960",
    "sg:postcode":"90029",
    "sg:province":"CA",
    "sg:tags":[
        "performing",
        "venue"
    ],
    "sg:website":"www.syncspacela.com/",
    "wof:name":"Synchronicity Space",
    "wof:placetype":"venue"
},
  "geometry": {"coordinates":[-118.294658,34.083592],"type":"Point"}
}