{
  "type": "Feature",
  "properties": {
    "addr:full":"3004 16th St San Francisco CA 94103",
    "addr:housenumber":"3004",
    "addr:postcode":"94103",
    "addr:street":"16Th St",
    "iso:country":"US",
    "sg:address":"3004 16th St",
    "sg:city":"San Francisco",
    "sg:classifiers":[
        {
            "category":"Social Services",
            "subcategory":"Adult Care",
            "type":"Services"
        },
        {
            "category":"Professional",
            "subcategory":"Research",
            "type":"Services"
        }
    ],
    "sg:phone":"+1 415 522 5889",
    "sg:postcode":"94103",
    "sg:province":"CA",
    "sg:tags":[
        "residential"
    ],
    "wof:name":"Center For Community Research",
    "wof:placetype":"venue"
},
  "geometry": {"coordinates":[-122.420416,37.765081],"type":"Point"}
}