{
  "type": "Feature",
  "properties": {
    "addr:full":"16901 Aston Irvine CA 92606",
    "addr:housenumber":"16901",
    "addr:postcode":"92606",
    "addr:street":"Aston",
    "iso:country":"US",
    "sg:address":"16901 Aston",
    "sg:city":"Irvine",
    "sg:classifiers":[
        {
            "category":"Retail",
            "subcategory":"Laundry & Dry Cleaning",
            "type":"Services"
        }
    ],
    "sg:phone":"+1 949 250 1740",
    "sg:postcode":"92606",
    "sg:province":"CA",
    "sg:tags":[
        "launderer",
        "industrial",
        "linen",
        "supply"
    ],
    "wof:name":"Prudential Overall Supply",
    "wof:placetype":"venue"
},
  "geometry": {"coordinates":[-117.84532900000001,33.698714],"type":"Point"}
}