{
  "type": "Feature",
  "properties": {
    "iso:country":"US",
    "sg:address":"13572 Laurinda Wy",
    "sg:city":"Santa Ana",
    "sg:classifiers":[
        {
            "category":"Home & Garden",
            "subcategory":"Carpets & Floor Coverings",
            "type":"Retail Goods"
        }
    ],
    "sg:phone":"+1 714 795 8624",
    "sg:postcode":"92705",
    "sg:province":"CA",
    "sg:tags":[
        "carpeting"
    ],
    "sg:website":"www.paragonplumbinganddrain.com",
    "wof:name":"Paragon Plumbing & Drain",
    "wof:placetype":"venue"
},
  "geometry": {"coordinates":[-117.82187399999999,33.766044],"type":"Point"}
}