{
  "type": "Feature",
  "properties": {
    "addr:full":"722 E Manchester Ave Los Angeles CA 90001",
    "addr:housenumber":"722",
    "addr:postcode":"90001",
    "addr:street":"E Manchester Ave",
    "iso:country":"US",
    "sg:address":"722 E Manchester Ave",
    "sg:city":"Los Angeles",
    "sg:classifiers":[
        {
            "category":"Organizations",
            "subcategory":"Religious Organization",
            "type":"Services"
        }
    ],
    "sg:phone":"+1 323 752 4767",
    "sg:postcode":"90001",
    "sg:province":"CA",
    "sg:tags":[
        "church"
    ],
    "wof:name":"United Christian's Missionary",
    "wof:placetype":"venue"
},
  "geometry": {"coordinates":[-118.261438,33.960071],"type":"Point"}
}