{
  "type": "Feature",
  "properties": {
    "iso:country":"US",
    "sg:address":"622 Edgewater Blvd",
    "sg:city":"San Mateo",
    "sg:classifiers":[
        {
            "category":"Professional",
            "type":"Services"
        }
    ],
    "sg:phone":"+1 650 341 4022",
    "sg:postcode":"94404",
    "sg:province":"CA",
    "wof:name":"Hipay Co Inc",
    "wof:placetype":"venue"
},
  "geometry": {"coordinates":[-122.277996,37.552815],"type":"Point"}
}