{
  "type": "Feature",
  "properties": {
    "addr:full":"2638 E Florence Avenue Huntington Park CA 90255",
    "addr:housenumber":"2638",
    "addr:postcode":"90255",
    "addr:street":"E Florence Avenue;Park",
    "iso:country":"US",
    "sg:address":"2638 E Florence Avenue",
    "sg:city":"Huntington Park",
    "sg:classifiers":[
        {
            "category":"Health Services",
            "subcategory":"Doctor",
            "type":"Services"
        }
    ],
    "sg:phone":"+1 323 581 4665",
    "sg:postcode":"90255",
    "sg:province":"CA",
    "wof:name":"Lu-Wei King MD",
    "wof:placetype":"venue"
},
  "geometry": {"coordinates":[-118.223956,33.973979],"type":"Point"}
}