{
  "type": "Feature",
  "properties": {
    "addr:full":"2145 Bella Casa St Davis CA 95616",
    "addr:housenumber":"2145",
    "addr:postcode":"95616",
    "addr:street":"Bella Casa St",
    "iso:country":"US",
    "sg:address":"2145 Bella Casa St",
    "sg:city":"Davis",
    "sg:classifiers":[
        {
            "category":"Professional",
            "subcategory":"Accounting & Tax Preparation",
            "type":"Services"
        }
    ],
    "sg:phone":"+1 530 758 2130",
    "sg:postcode":"95616",
    "sg:province":"CA",
    "sg:tags":[
        "bookkeeping",
        "general"
    ],
    "wof:name":"Betsy La Noue",
    "wof:placetype":"venue"
},
  "geometry": {"coordinates":[-121.74923099999999,38.562855],"type":"Point"}
}