{
  "type": "Feature",
  "properties": {
    "addr:full":"130 E Ortega St Santa Barbara CA 93101",
    "addr:housenumber":"130",
    "addr:postcode":"93101",
    "addr:street":"E Ortega St",
    "iso:country":"US",
    "sg:address":"130 E Ortega St",
    "sg:city":"Santa Barbara",
    "sg:classifiers":[
        {
            "category":"Professional",
            "subcategory":"Employment Agencies",
            "type":"Services"
        }
    ],
    "sg:phone":"+1 805 963 8838",
    "sg:postcode":"93101",
    "sg:province":"CA",
    "sg:tags":[
        "opportunity"
    ],
    "wof:name":"Youth Employment Svc",
    "wof:placetype":"venue"
},
  "geometry": {"coordinates":[-119.69599599999999,34.420427],"type":"Point"}
}