{
  "type": "Feature",
  "properties": {
    "iso:country":"US",
    "sg:address":"1511 Pontius Ave",
    "sg:city":"Los Angeles",
    "sg:classifiers":[
        {
            "category":"Professional",
            "type":"Services"
        }
    ],
    "sg:phone":"+1 310 268 1700",
    "sg:postcode":"90025",
    "sg:province":"CA",
    "sg:tags":[
        "establishment"
    ],
    "wof:name":"Digital Farmhouse",
    "wof:placetype":"venue"
},
  "geometry": {"coordinates":[-118.446268,34.048896],"type":"Point"}
}