{
  "type": "Feature",
  "properties": {
    "addr:full":"406 9th Ave Ste 210 San Diego CA 92101",
    "addr:housenumber":"406",
    "addr:postcode":"92101",
    "addr:street":"9Th Ave Ste 210",
    "iso:country":"US",
    "sg:address":"406 9th Ave Ste 210",
    "sg:city":"San Diego",
    "sg:classifiers":[
        {
            "category":"Professional",
            "type":"Services"
        },
        {
            "category":"Real Estate",
            "subcategory":"Real Estate Services",
            "type":"Services"
        }
    ],
    "sg:phone":"+1 619 677 2650",
    "sg:postcode":"92101",
    "sg:province":"CA",
    "sg:website":"www.notarynearyou.com/",
    "wof:name":"Notary Near You, Inc.",
    "wof:placetype":"venue"
},
  "geometry": {"coordinates":[-117.156921,32.709641],"type":"Point"}
}