{
  "type": "Feature",
  "properties": {
    "iso:country":"US",
    "sg:address":"958 Postal Way",
    "sg:city":"Vista",
    "sg:classifiers":[
        {
            "category":"Real Estate",
            "subcategory":"Real Estate Agent",
            "type":"Services"
        }
    ],
    "sg:phone":"+1 760 732 1486",
    "sg:postcode":"92083",
    "sg:province":"CA",
    "sg:tags":[
        "management"
    ],
    "wof:name":"Central Enterprises Inc",
    "wof:placetype":"venue"
},
  "geometry": {"coordinates":[-117.235066,33.192678],"type":"Point"}
}