{
  "type": "Feature",
  "properties": {
    "addr:full":"200 Harbor Dr San Diego CA 92101",
    "addr:housenumber":"200",
    "addr:postcode":"92101",
    "addr:street":"Harbor Dr",
    "iso:country":"US",
    "sg:address":"200 Harbor Dr",
    "sg:city":"San Diego",
    "sg:classifiers":[
        {
            "category":"Retail",
            "subcategory":"Car Wash",
            "type":"Services"
        }
    ],
    "sg:phone":"+1 619 235 8390",
    "sg:postcode":"92101",
    "sg:province":"CA",
    "sg:tags":[
        "automobile",
        "detail",
        "clean"
    ],
    "wof:name":"Absolute Perfection Auto Spa",
    "wof:placetype":"venue"
},
  "geometry": {"coordinates":[-117.159049,32.705931],"type":"Point"}
}