{
  "type": "Feature",
  "properties": {
    "addr:full":"922 Industrial Way Lodi CA 95240",
    "addr:housenumber":"922",
    "addr:postcode":"95240",
    "addr:street":"Industrial Way",
    "iso:country":"US",
    "sg:address":"922 Industrial Way",
    "sg:city":"Lodi",
    "sg:classifiers":[
        {
            "category":"Insurance",
            "subcategory":"Insurance Agent",
            "type":"Services"
        },
        {
            "category":"Insurance",
            "subcategory":"Hazard Insurance",
            "type":"Services"
        },
        {
            "category":"Insurance",
            "subcategory":"Title Insurance",
            "type":"Services"
        },
        {
            "category":"Insurance",
            "subcategory":"Life Insurance",
            "type":"Services"
        }
    ],
    "sg:phone":"+1 209 334 9465",
    "sg:postcode":"95240",
    "sg:province":"CA",
    "sg:tags":[
        "auto",
        "commercial",
        "business",
        "homeowner"
    ],
    "sg:website":"http://www.farmersagent.com/bhenton/",
    "wof:name":"William Henton Insurance Agency Inc - Farmers Insurance",
    "wof:placetype":"venue"
},
  "geometry": {"coordinates":[-121.254389,38.12546],"type":"Point"}
}