{
  "type": "Feature",
  "properties": {
    "iso:country":"US",
    "sg:address":"494 Stanford Pl",
    "sg:city":"Santa Barbara",
    "sg:classifiers":[
        {
            "category":"Manufacturing",
            "subcategory":"Metals",
            "type":"Manufacturing & Wholesale Goods"
        }
    ],
    "sg:phone":"+1 805 681 7323",
    "sg:postcode":"93111",
    "sg:province":"CA",
    "sg:tags":[
        "burner"
    ],
    "wof:name":"North America Mfrs",
    "wof:placetype":"venue"
},
  "geometry": {"coordinates":[-119.810185,34.445944],"type":"Point"}
}