{
  "type": "Feature",
  "properties": {
    "addr:full":"814 Sycamore Valley Rd W Danville CA 94526",
    "addr:housenumber":"814",
    "addr:postcode":"94526",
    "addr:street":"Sycamore Valley Rd W",
    "iso:country":"US",
    "sg:address":"814 Sycamore Valley Rd W",
    "sg:city":"Danville",
    "sg:classifiers":[
        {
            "category":"Shopping",
            "subcategory":"Bicycles & Sporting Goods",
            "type":"Retail Goods"
        },
        {
            "category":"Sports & Exercise",
            "subcategory":"Golf",
            "type":"Entertainment"
        }
    ],
    "sg:phone":"+1 925 820 6800",
    "sg:postcode":"94526",
    "sg:province":"CA",
    "sg:tags":[
        "equipment",
        "course",
        "supply"
    ],
    "wof:name":"From Tee To Green",
    "wof:placetype":"venue"
},
  "geometry": {"coordinates":[-121.99749799999999,37.812062],"type":"Point"}
}