{
  "type": "Feature",
  "properties": {
    "iso:country":"US",
    "sg:address":"55 New Montgomery Ste 420",
    "sg:city":"San Francisco",
    "sg:classifiers":[
        {
            "category":"Health Services",
            "subcategory":"Clinic",
            "type":"Services"
        }
    ],
    "sg:phone":"+1 415 643 3393",
    "sg:postcode":"94105",
    "sg:province":"CA",
    "sg:tags":[
        "counseling",
        "mental"
    ],
    "wof:name":"Pearl B. Werfel, PhD",
    "wof:placetype":"venue"
},
  "geometry": {"coordinates":[-122.401203,37.78809],"type":"Point"}
}