{
  "type": "Feature",
  "properties": {
    "iso:country":"US",
    "sg:address":"26800 Cherry Hills Blvd",
    "sg:city":"Sun City",
    "sg:classifiers":[
        {
            "category":"Banks & Credit Unions",
            "subcategory":"Bank",
            "type":"Services"
        },
        {
            "category":"Banks & Credit Unions",
            "subcategory":"Financial Services",
            "type":"Services"
        }
    ],
    "sg:phone":"+1 951 723 1960",
    "sg:postcode":"92586",
    "sg:province":"CA",
    "sg:tags":[
        "broker",
        "mortgage"
    ],
    "sg:website":"www.bankofamerica.com",
    "wof:name":"Bank of America",
    "wof:placetype":"venue"
},
  "geometry": {"coordinates":[-117.193001,33.7099],"type":"Point"}
}