{
  "type": "Feature",
  "properties": {
    "addr:full":"12009 Rivera Rd Santa Fe Springs CA 90670",
    "addr:housenumber":"12009",
    "addr:postcode":"90670",
    "addr:street":"Rivera Rd",
    "iso:country":"US",
    "sg:address":"12009 Rivera Rd",
    "sg:city":"Santa Fe Springs",
    "sg:classifiers":[
        {
            "category":"Manufacturing",
            "subcategory":"Printing",
            "type":"Manufacturing & Wholesale Goods"
        }
    ],
    "sg:phone":"+1 562 320 1555",
    "sg:postcode":"90670",
    "sg:province":"CA",
    "sg:tags":[
        "commercial"
    ],
    "wof:name":"Serendipity Screen Printing",
    "wof:placetype":"venue"
},
  "geometry": {"coordinates":[-118.058125,33.965548],"type":"Point"}
}