{
  "type": "Feature",
  "properties": {
    "addr:full":"6758 Folsom Blvd Sacramento CA 95819",
    "addr:housenumber":"6758",
    "addr:postcode":"95819",
    "addr:street":"Folsom Blvd",
    "iso:country":"US",
    "sg:address":"6758 Folsom Blvd",
    "sg:city":"Sacramento",
    "sg:classifiers":[
        {
            "category":"Manufacturing",
            "subcategory":"Leather Goods",
            "type":"Manufacturing & Wholesale Goods"
        },
        {
            "category":"Autos & Motor Vehicles",
            "subcategory":"Motorcycle Sales",
            "type":"Retail Goods"
        }
    ],
    "sg:phone":"+1 916 454 3700",
    "sg:postcode":"95819",
    "sg:province":"CA",
    "wof:name":"Renegade Classics Outlet Store",
    "wof:placetype":"venue"
},
  "geometry": {"coordinates":[-121.425003,38.553398],"type":"Point"}
}