{
  "type": "Feature",
  "properties": {
    "addr:full":"3336 Lone Hill Ln Encinitas CA 92024",
    "addr:housenumber":"3336",
    "addr:postcode":"92024",
    "addr:street":"Lone Hill Ln",
    "iso:country":"US",
    "sg:address":"3336 Lone Hill Ln",
    "sg:city":"Encinitas",
    "sg:classifiers":[
        {
            "category":"Mining & Drilling",
            "type":"Manufacturing & Wholesale Goods"
        }
    ],
    "sg:phone":"+1 858 759 7532",
    "sg:postcode":"92024",
    "sg:province":"CA",
    "sg:tags":[
        "mineral",
        "nonmetallic",
        "contractor"
    ],
    "sg:website":"www.breckenridgelodge.com",
    "wof:name":"Solution Mining Research Inst",
    "wof:placetype":"venue"
},
  "geometry": {"coordinates":[-117.212542,33.069709],"type":"Point"}
}