{
  "type": "Feature",
  "properties": {
    "addr:full":"351 N Arrowhead Ave San Bernardino CA 92401",
    "addr:housenumber":"351",
    "addr:postcode":"92401",
    "addr:street":"N Arrowhead Ave",
    "iso:country":"US",
    "sg:address":"351 N Arrowhead Ave",
    "sg:city":"San Bernardino",
    "sg:classifiers":[
        {
            "category":"Government",
            "subcategory":"Office",
            "type":"Public Place"
        }
    ],
    "sg:phone":"+1 909 387 3820",
    "sg:postcode":"92401",
    "sg:province":"CA",
    "wof:name":"San Bernardino Grand Jury",
    "wof:placetype":"venue"
},
  "geometry": {"coordinates":[-117.28967400000001,34.106439],"type":"Point"}
}