{
  "type": "Feature",
  "properties": {
    "addr:full":"870 Main St Cambria CA 93428",
    "addr:housenumber":"870",
    "addr:postcode":"93428",
    "addr:street":"Main St",
    "iso:country":"US",
    "sg:address":"870 Main St",
    "sg:city":"Cambria",
    "sg:classifiers":[
        {
            "category":"Recreation",
            "type":"Entertainment"
        }
    ],
    "sg:phone":"+1 805 927 7776",
    "sg:postcode":"93428",
    "sg:province":"CA",
    "sg:tags":[
        "hall",
        "auditorium"
    ],
    "wof:name":"Community Center Of Cambria",
    "wof:placetype":"venue"
},
  "geometry": {"coordinates":[-121.096661,35.564884],"type":"Point"}
}