{
  "type": "Feature",
  "properties": {
    "addr:full":"385 Clinton St Costa Mesa CA 92626",
    "addr:housenumber":"385",
    "addr:postcode":"92626",
    "addr:street":"Clinton St",
    "iso:country":"US",
    "sg:address":"385 Clinton St",
    "sg:city":"Costa Mesa",
    "sg:classifiers":[
        {
            "category":"Manufacturing",
            "subcategory":"Furniture",
            "type":"Manufacturing & Wholesale Goods"
        }
    ],
    "sg:phone":"+1 714 641 0411",
    "sg:postcode":"92626",
    "sg:province":"CA",
    "sg:tags":[
        "industry",
        "household",
        "machinery",
        "mfg"
    ],
    "wof:name":"Kyowa America Corporation",
    "wof:placetype":"venue"
},
  "geometry": {"coordinates":[-117.87721999999999,33.66637],"type":"Point"}
}