{
  "type": "Feature",
  "properties": {
    "addr:full":"21009 Saticoy St Canoga Park CA 91304",
    "addr:postcode":"21009;91304",
    "addr:street":"Saticoy St",
    "iso:country":"US",
    "sg:address":"21009 Saticoy St",
    "sg:city":"Canoga Park",
    "sg:classifiers":[
        {
            "category":"Shopping",
            "subcategory":"Clothing, Apparel, & Fashions",
            "type":"Retail Goods"
        }
    ],
    "sg:phone":"+1 818 907 3351",
    "sg:postcode":"91304",
    "sg:province":"CA",
    "wof:name":"Egnes Exclusive Design",
    "wof:placetype":"venue"
},
  "geometry": {"coordinates":[-118.592699,34.208376],"type":"Point"}
}