{
  "type": "Feature",
  "properties": {
    "addr:full":"4451 Gateway Park Blvd # 226 Sacramento CA 95834",
    "addr:housenumber":"4451",
    "addr:postcode":"95834",
    "addr:street":"Gateway Park Blvd # 226",
    "iso:country":"US",
    "sg:address":"4451 Gateway Park Blvd # 226",
    "sg:city":"Sacramento",
    "sg:classifiers":[
        {
            "category":"Professional",
            "subcategory":"Advertising",
            "type":"Services"
        }
    ],
    "sg:phone":"+1 916 419 6410",
    "sg:postcode":"95834",
    "sg:province":"CA",
    "sg:tags":[
        "mail",
        "direct"
    ],
    "wof:name":"Legitimate Information",
    "wof:placetype":"venue"
},
  "geometry": {"coordinates":[-121.502657,38.652837],"type":"Point"}
}