{
  "type": "Feature",
  "properties": {
    "addr:full":"9901 San Leandro St Oakland CA 94603",
    "addr:housenumber":"9901",
    "addr:postcode":"94603",
    "addr:street":"San Leandro St",
    "iso:country":"US",
    "sg:address":"9901 San Leandro St",
    "sg:city":"Oakland",
    "sg:classifiers":[
        {
            "category":"Professional",
            "type":"Services"
        }
    ],
    "sg:phone":"+1 510 638 5082",
    "sg:postcode":"94603",
    "sg:province":"CA",
    "sg:tags":[
        "metal"
    ],
    "wof:name":"Excellent Metal Processing",
    "wof:placetype":"venue"
},
  "geometry": {"coordinates":[-122.179062,37.738602],"type":"Point"}
}