{
  "type": "Feature",
  "properties": {
    "iso:country":"US",
    "sg:address":"412 Fairway Dr",
    "sg:city":"Ione",
    "sg:classifiers":[
        {
            "category":"Professional",
            "subcategory":"Business Services",
            "type":"Services"
        }
    ],
    "sg:phone":"+1 209 274 4512",
    "sg:postcode":"95640",
    "sg:province":"CA",
    "sg:tags":[
        "interior",
        "consultant",
        "design",
        "decorator"
    ],
    "wof:name":"Jidona Interiors",
    "wof:placetype":"venue"
},
  "geometry": {"coordinates":[-120.954256,38.360903],"type":"Point"}
}