{
  "type": "Feature",
  "properties": {
    "iso:country":"US",
    "sg:address":"12230 El Camino Real",
    "sg:city":"San Diego",
    "sg:classifiers":[
        {
            "category":"Real Estate",
            "subcategory":"Real Estate Services",
            "type":"Services"
        }
    ],
    "sg:phone":"+1 858 794 5500",
    "sg:postcode":"92130",
    "sg:province":"CA",
    "sg:tags":[
        "home",
        "inspector"
    ],
    "wof:name":"Cresapartners",
    "wof:placetype":"venue"
},
  "geometry": {"coordinates":[-117.240332,32.939839],"type":"Point"}
}