{
  "type": "Feature",
  "properties": {
    "addr:full":"28202 Cabot Road Laguna Niguel CA 92677",
    "addr:housenumber":"28202",
    "addr:postcode":"92677",
    "addr:street":"Cabot Road",
    "iso:country":"US",
    "sg:address":"28202 Cabot Road",
    "sg:city":"Laguna Niguel",
    "sg:classifiers":[
        {
            "category":"Professional",
            "subcategory":"Lawyer & Legal Services",
            "type":"Services"
        }
    ],
    "sg:phone":"+1 949 365 9000",
    "sg:postcode":"92677",
    "sg:province":"CA",
    "wof:name":"Orange Coast Law Center",
    "wof:placetype":"venue"
},
  "geometry": {"coordinates":[-117.67894200000001,33.551937],"type":"Point"}
}