{
  "type": "Feature",
  "properties": {
    "iso:country":"US",
    "sg:address":"1000 North Alameda St Ste 224",
    "sg:city":"Los Angeles",
    "sg:classifiers":[
        {
            "category":"Organizations",
            "subcategory":"Non-profit Organization",
            "type":"Services"
        }
    ],
    "sg:phone":"+1 213 625 7701",
    "sg:postcode":"90012",
    "sg:province":"CA",
    "sg:tags":[
        "service/non-profit",
        "community"
    ],
    "sg:website":"www.taprootfoundation.org",
    "wof:name":"Taproot Foundation",
    "wof:placetype":"venue"
},
  "geometry": {"coordinates":[-118.236045,34.059328],"type":"Point"}
}