{
  "type": "Feature",
  "properties": {
    "addr:full":"223 Eureka Ave Lodi CA 95240",
    "addr:housenumber":"223",
    "addr:postcode":"95240",
    "addr:street":"Eureka Ave",
    "iso:country":"US",
    "sg:address":"223 Eureka Ave",
    "sg:city":"Lodi",
    "sg:classifiers":[
        {
            "category":"Professional",
            "subcategory":"Management & Consulting",
            "type":"Services"
        }
    ],
    "sg:phone":"+1 209 333 0846",
    "sg:postcode":"95240",
    "sg:province":"CA",
    "sg:tags":[
        "consultant",
        "business"
    ],
    "wof:name":"Vintage Consulting",
    "wof:placetype":"venue"
},
  "geometry": {"coordinates":[-121.276117,38.144397],"type":"Point"}
}