{
  "type": "Feature",
  "properties": {
    "addr:full":"2257 Concord Dr Pittsburg CA 94565",
    "addr:housenumber":"2257",
    "addr:postcode":"94565",
    "addr:street":"Concord Dr",
    "iso:country":"US",
    "sg:address":"2257 Concord Dr",
    "sg:city":"Pittsburg",
    "sg:classifiers":[
        {
            "category":"Organizations",
            "subcategory":"Non-profit Organization",
            "type":"Services"
        }
    ],
    "sg:phone":"+1 925 458 6704",
    "sg:postcode":"94565",
    "sg:province":"CA",
    "sg:tags":[
        "charity"
    ],
    "wof:name":"Nanas House",
    "wof:placetype":"venue"
},
  "geometry": {"coordinates":[-121.93015,38.011836],"type":"Point"}
}