{
  "type": "Feature",
  "properties": {
    "addr:full":"962 Cooper Ave Yuba City CA 95991",
    "addr:housenumber":"962",
    "addr:postcode":"95991",
    "addr:street":"Cooper Ave",
    "iso:country":"US",
    "sg:address":"962 Cooper Ave",
    "sg:city":"Yuba City",
    "sg:classifiers":[
        {
            "category":"Personal",
            "subcategory":"Beauty Salon",
            "type":"Services"
        }
    ],
    "sg:phone":"+1 530 673 4357",
    "sg:postcode":"95991",
    "sg:province":"CA",
    "wof:name":"Classy Cuts",
    "wof:placetype":"venue"
},
  "geometry": {"coordinates":[-121.623819,39.140577],"type":"Point"}
}