{
  "type": "Feature",
  "properties": {
    "addr:full":"Upper Park Road Santa Cruz CA 95067",
    "addr:postcode":"95067",
    "addr:street":"Upper Park Road",
    "iso:country":"US",
    "sg:address":"Upper Park Road",
    "sg:city":"Santa Cruz",
    "sg:classifiers":[
        {
            "category":"Arts & Performance",
            "subcategory":"Arts Center",
            "type":"Entertainment"
        },
        {
            "category":"Park",
            "type":"Public Place"
        },
        {
            "category":"Sports & Exercise",
            "subcategory":"Golf",
            "type":"Entertainment"
        }
    ],
    "sg:postcode":"95067",
    "sg:province":"CA",
    "sg:website":"www.delaveagadiscgolf.com",
    "wof:name":"De LaVeaga Disc Golf Course",
    "wof:placetype":"venue"
},
  "geometry": {"coordinates":[-121.99870799999999,36.999526],"type":"Point"}
}