{
  "type": "Feature",
  "properties": {
    "iso:country":"US",
    "sg:address":"5 W 18th St",
    "sg:city":"National City",
    "sg:classifiers":[
        {
            "category":"Autos & Motor Vehicles",
            "subcategory":"Automobile Sales",
            "type":"Retail Goods"
        }
    ],
    "sg:phone":"+1 619 477 5700",
    "sg:postcode":"91950",
    "sg:province":"CA",
    "sg:tags":[
        "car",
        "dealer"
    ],
    "wof:name":"Chief Auto Sales",
    "wof:placetype":"venue"
},
  "geometry": {"coordinates":[-117.104594,32.666989],"type":"Point"}
}