{
  "type": "Feature",
  "properties": {
    "addr:full":"8017 W Sunset Blvd West Hollywood CA 90046",
    "addr:housenumber":"8017",
    "addr:postcode":"90046",
    "addr:street":"W Sunset Blvd",
    "iso:country":"US",
    "sg:address":"8017 W Sunset Blvd",
    "sg:city":"West Hollywood",
    "sg:classifiers":[
        {
            "category":"Deli",
            "type":"Food & Drink"
        },
        {
            "category":"Food & Beverages",
            "subcategory":"Liquor & Beverages",
            "type":"Retail Goods"
        }
    ],
    "sg:phone":"+1 323 656 0606",
    "sg:postcode":"90046",
    "sg:province":"CA",
    "sg:tags":[
        "beer",
        "spirit",
        "wine"
    ],
    "sg:website":"www.greenblattsdeli.com",
    "wof:name":"Greenblatt's Delicatessen & Fine Wine Shop",
    "wof:placetype":"venue"
},
  "geometry": {"coordinates":[-118.36466799999999,34.098031],"type":"Point"}
}