{
  "type": "Feature",
  "properties": {
    "addr:full":"665 Redwood Dr Garberville CA 95542",
    "addr:housenumber":"665",
    "addr:postcode":"95542",
    "addr:street":"Redwood Dr",
    "iso:country":"US",
    "sg:address":"665 Redwood Dr",
    "sg:city":"Garberville",
    "sg:classifiers":[
        {
            "category":"Shopping",
            "type":"Retail Goods"
        }
    ],
    "sg:phone":"+1 707 923 2934",
    "sg:postcode":"95542",
    "sg:province":"CA",
    "sg:tags":[
        "equipment",
        "telephone",
        "supply"
    ],
    "wof:name":"Childs Play Electronic",
    "wof:placetype":"venue"
},
  "geometry": {"coordinates":[-123.79491,40.10205],"type":"Point"}
}