{
  "type": "Feature",
  "properties": {
    "addr:full":"19480 Colina Dr Walnut CA 91789",
    "addr:housenumber":"19480",
    "addr:postcode":"91789",
    "addr:street":"Colina Dr",
    "iso:country":"US",
    "sg:address":"19480 Colina Dr",
    "sg:city":"Walnut",
    "sg:classifiers":[
        {
            "category":"Real Estate",
            "subcategory":"Real Estate Agent",
            "type":"Services"
        }
    ],
    "sg:phone":"+1 626 810 5533",
    "sg:postcode":"91789",
    "sg:province":"CA",
    "wof:name":"Advance Golden Valley Realty",
    "wof:placetype":"venue"
},
  "geometry": {"coordinates":[-117.87705200000001,34.030068],"type":"Point"}
}