{
  "type": "Feature",
  "properties": {
    "addr:full":"7301 Medical Center Dr Canoga Park CA 91307",
    "addr:housenumber":"7301",
    "addr:postcode":"91307",
    "addr:street":"Medical Center Dr",
    "iso:country":"US",
    "sg:address":"7301 Medical Center Dr",
    "sg:city":"Canoga Park",
    "sg:classifiers":[
        {
            "category":"Real Estate",
            "subcategory":"Real Estate Agent",
            "type":"Services"
        },
        {
            "category":"Real Estate",
            "subcategory":"Real Estate Operator",
            "type":"Services"
        }
    ],
    "sg:phone":"+1 818 716 7575",
    "sg:postcode":"91307",
    "sg:province":"CA",
    "sg:tags":[
        "building",
        "parks"
    ],
    "wof:name":"Grand Toyoko USA Inc",
    "wof:placetype":"venue"
},
  "geometry": {"coordinates":[-118.629531,34.201148],"type":"Point"}
}