{
  "type": "Feature",
  "properties": {
    "addr:full":"7771 Garvey Ave Rosemead CA 91770",
    "addr:housenumber":"7771",
    "addr:postcode":"91770",
    "addr:street":"Garvey Ave",
    "iso:country":"US",
    "sg:address":"7771 Garvey Ave",
    "sg:city":"Rosemead",
    "sg:classifiers":[
        {
            "category":"Professional",
            "subcategory":"Business Services",
            "type":"Services"
        }
    ],
    "sg:phone":"+1 626 571 7071",
    "sg:postcode":"91770",
    "sg:province":"CA",
    "sg:tags":[
        "packaging"
    ],
    "wof:name":"Nc Shipping Inc",
    "wof:placetype":"venue"
},
  "geometry": {"coordinates":[-118.10010200000001,34.062697],"type":"Point"}
}