{
  "type": "Feature",
  "properties": {
    "addr:full":"1801 Mount Vernon Ave Pomona CA 91768",
    "addr:housenumber":"1801",
    "addr:postcode":"91768",
    "addr:street":"Mount Vernon Ave",
    "iso:country":"US",
    "sg:address":"1801 Mount Vernon Ave",
    "sg:city":"Pomona",
    "sg:classifiers":[
        {
            "category":"Wholesale",
            "subcategory":"Chemicals & Plastics",
            "type":"Manufacturing & Wholesale Goods"
        }
    ],
    "sg:phone":"+1 909 865 8963",
    "sg:postcode":"91768",
    "sg:province":"CA",
    "wof:name":"Jetway International",
    "wof:placetype":"venue"
},
  "geometry": {"coordinates":[-117.783119,34.058395],"type":"Point"}
}