{
  "type": "Feature",
  "properties": {
    "iso:country":"US",
    "sg:address":"11082 Night Shadow Ave",
    "sg:city":"Moreno Valley",
    "sg:classifiers":[
        {
            "category":"Personal",
            "type":"Services"
        }
    ],
    "sg:phone":"+1 951 247 3998",
    "sg:postcode":"92555",
    "sg:province":"CA",
    "sg:tags":[
        "pet",
        "exercising"
    ],
    "wof:name":"Porter D & K",
    "wof:placetype":"venue"
},
  "geometry": {"coordinates":[-117.16071700000001,33.959691],"type":"Point"}
}