{
  "type": "Feature",
  "properties": {
    "iso:country":"US",
    "sg:address":"Downtown Plaza 547 L St",
    "sg:city":"Sacramento",
    "sg:classifiers":[
        {
            "category":"Personal",
            "subcategory":"Massage",
            "type":"Services"
        }
    ],
    "sg:postcode":"95814",
    "sg:province":"CA",
    "wof:name":"Good Hand",
    "wof:placetype":"venue"
},
  "geometry": {"coordinates":[-121.500229,38.5797],"type":"Point"}
}