{
  "type": "Feature",
  "properties": {
    "iso:country":"US",
    "sg:address":"1185 E Rosewood Dr",
    "sg:city":"San Bernardino",
    "sg:classifiers":[
        {
            "category":"Restaurant",
            "type":"Food & Drink"
        }
    ],
    "sg:phone":"+1 909 796 7227",
    "sg:postcode":"92408",
    "sg:province":"CA",
    "wof:name":"Denny's",
    "wof:placetype":"venue"
},
  "geometry": {"coordinates":[-117.25813100000001,34.065737],"type":"Point"}
}