{
  "type": "Feature",
  "properties": {
    "iso:country":"US",
    "sg:address":"26661 Pepita Dr",
    "sg:city":"Mission Viejo",
    "sg:classifiers":[
        {
            "category":"Professional",
            "subcategory":"Art Services",
            "type":"Services"
        }
    ],
    "sg:phone":"+1 949 305 5605",
    "sg:postcode":"92691",
    "sg:province":"CA",
    "sg:tags":[
        "graphic",
        "designer"
    ],
    "wof:name":"Baugh Designs",
    "wof:placetype":"venue"
},
  "geometry": {"coordinates":[-117.664658,33.593621],"type":"Point"}
}