{
  "type": "Feature",
  "properties": {
    "iso:country":"US",
    "sg:address":"1440 N Harbor Blvd",
    "sg:city":"Fullerton",
    "sg:classifiers":[
        {
            "category":"Banks & Credit Unions",
            "subcategory":"Financial Services",
            "type":"Services"
        }
    ],
    "sg:phone":"+1 714 449 3300",
    "sg:postcode":"92835",
    "sg:province":"CA",
    "sg:tags":[
        "broker",
        "mortgage"
    ],
    "wof:name":"Mortgage & Escrow Co",
    "wof:placetype":"venue"
},
  "geometry": {"coordinates":[-117.925873,33.885186],"type":"Point"}
}