{
  "type": "Feature",
  "properties": {
    "addr:full":"937 Entrada Dr Oxnard CA 93030",
    "addr:housenumber":"937",
    "addr:postcode":"93030",
    "addr:street":"Entrada Dr",
    "iso:country":"US",
    "sg:address":"937 Entrada Dr",
    "sg:city":"Oxnard",
    "sg:classifiers":[
        {
            "category":"Real Estate",
            "subcategory":"Developer",
            "type":"Services"
        }
    ],
    "sg:phone":"+1 805 981 2152",
    "sg:postcode":"93030",
    "sg:province":"CA",
    "wof:name":"Capital Pacific Homes",
    "wof:placetype":"venue"
},
  "geometry": {"coordinates":[-119.17409600000001,34.211482],"type":"Point"}
}