{
  "type": "Feature",
  "properties": {
    "addr:full":"311 Placerville Dr Placerville CA 95667",
    "addr:housenumber":"311",
    "addr:postcode":"95667",
    "addr:street":"Placerville Dr",
    "iso:country":"US",
    "sg:address":"311 Placerville Dr",
    "sg:city":"Placerville",
    "sg:classifiers":[
        {
            "category":"Building & Trades",
            "subcategory":"Construction",
            "type":"Services"
        }
    ],
    "sg:phone":"+1 530 626 1393",
    "sg:postcode":"95667",
    "sg:province":"CA",
    "sg:tags":[
        "contractor"
    ],
    "wof:name":"Daniels Construction",
    "wof:placetype":"venue"
},
  "geometry": {"coordinates":[-120.830054,38.733477],"type":"Point"}
}