{
  "type": "Feature",
  "properties": {
    "iso:country":"US",
    "sg:address":"795 S 1st Street",
    "sg:city":"San Jose",
    "sg:classifiers":[
        {
            "category":"Personal",
            "subcategory":"Beauty Salon",
            "type":"Services"
        }
    ],
    "sg:phone":"+1 408 279 2536",
    "sg:postcode":"95113",
    "sg:province":"CA",
    "sg:tags":[
        "hair"
    ],
    "wof:name":"The Look Salon",
    "wof:placetype":"venue"
},
  "geometry": {"coordinates":[-121.886482,37.330758],"type":"Point"}
}