{
  "type": "Feature",
  "properties": {
    "addr:full":"2927 Lomita Blvd Torrance CA 90505",
    "addr:housenumber":"2927",
    "addr:postcode":"90505",
    "addr:street":"Lomita Blvd",
    "iso:country":"US",
    "sg:address":"2927 Lomita Blvd",
    "sg:city":"Torrance",
    "sg:classifiers":[
        {
            "category":"Manufacturing",
            "subcategory":"Rubber & Plastics",
            "type":"Manufacturing & Wholesale Goods"
        }
    ],
    "sg:phone":"+1 310 326 2028",
    "sg:postcode":"90505",
    "sg:province":"CA",
    "sg:tags":[
        "equipment",
        "product",
        "electrical",
        "mfg"
    ],
    "sg:website":"www.totexusa.com",
    "wof:name":"Totex Manufacturing Inc",
    "wof:placetype":"venue"
},
  "geometry": {"coordinates":[-118.338579,33.810441],"type":"Point"}
}