{
  "type": "Feature",
  "properties": {
    "addr:full":"5601 Bickett St Vernon CA 90058",
    "addr:housenumber":"5601",
    "addr:postcode":"90058",
    "addr:street":"Bickett St",
    "iso:country":"US",
    "sg:address":"5601 Bickett St",
    "sg:city":"Vernon",
    "sg:classifiers":[
        {
            "category":"Wholesale",
            "subcategory":"Apparel",
            "type":"Manufacturing & Wholesale Goods"
        }
    ],
    "sg:phone":"+1 323 587 5488",
    "sg:postcode":"90058",
    "sg:province":"CA",
    "wof:name":"Silver Fashion",
    "wof:placetype":"venue"
},
  "geometry": {"coordinates":[-118.216212,33.991986],"type":"Point"}
}