{
  "type": "Feature",
  "properties": {
    "addr:full":"11210 Cement Hill Rd Nevada City CA 95959",
    "addr:housenumber":"11210",
    "addr:postcode":"95959",
    "addr:street":"Cement Hill Rd",
    "iso:country":"US",
    "sg:address":"11210 Cement Hill Rd",
    "sg:city":"Nevada City",
    "sg:classifiers":[
        {
            "category":"Building & Trades",
            "subcategory":"Construction",
            "type":"Services"
        }
    ],
    "sg:phone":"+1 530 265 5254",
    "sg:postcode":"95959",
    "sg:province":"CA",
    "sg:tags":[
        "dry wall",
        "contractor"
    ],
    "wof:name":"Foster Dry Wall Inc",
    "wof:placetype":"venue"
},
  "geometry": {"coordinates":[-121.04409699999999,39.277408],"type":"Point"}
}