{
  "type": "Feature",
  "properties": {
    "addr:full":"4548 el Cajon Blvd San Diego CA 92115",
    "addr:housenumber":"4548",
    "addr:postcode":"92115",
    "addr:street":"El Cajon Blvd",
    "iso:country":"US",
    "sg:address":"4548 el Cajon Blvd",
    "sg:city":"San Diego",
    "sg:classifiers":[
        {
            "category":"Retail",
            "subcategory":"Auto Repair",
            "type":"Services"
        }
    ],
    "sg:phone":"+1 619 640 3410",
    "sg:postcode":"92115",
    "sg:province":"CA",
    "sg:tags":[
        "repairing",
        "automobile"
    ],
    "wof:name":"LA Auto Repair",
    "wof:placetype":"venue"
},
  "geometry": {"coordinates":[-117.09690999999999,32.755418],"type":"Point"}
}