{
  "type": "Feature",
  "properties": {
    "iso:country":"US",
    "sg:address":"1 Dr Carlton B Goodlett Pl",
    "sg:city":"San Francisco",
    "sg:classifiers":[
        {
            "category":"Landmark",
            "subcategory":"Historic",
            "type":"Public Place"
        }
    ],
    "sg:phone":"+1 415 701 2311",
    "sg:postcode":"94102",
    "sg:province":"CA",
    "sg:tags":[
        "building",
        "historical"
    ],
    "sg:website":"www.sfgov.org/site/cityhall_inde...",
    "wof:name":"City Hall",
    "wof:placetype":"venue"
},
  "geometry": {"coordinates":[-122.418616,37.77939],"type":"Point"}
}