{
  "type": "Feature",
  "properties": {
    "iso:country":"US",
    "sg:address":"388 9th St",
    "sg:city":"Oakland",
    "sg:classifiers":[
        {
            "category":"Health Services",
            "subcategory":"Doctor",
            "type":"Services"
        }
    ],
    "sg:phone":"+1 510 663 9518",
    "sg:postcode":"94607",
    "sg:province":"CA",
    "sg:tags":[
        "physician",
        "surgeon"
    ],
    "wof:name":"Bay Healthcare",
    "wof:placetype":"venue"
},
  "geometry": {"coordinates":[-122.27121200000001,37.80067],"type":"Point"}
}