{
  "type": "Feature",
  "properties": {
    "addr:full":"7533 Hollywood Blvd West Hollywood CA 90046",
    "addr:housenumber":"7533",
    "addr:postcode":"90046",
    "addr:street":"Hollywood Blvd",
    "iso:country":"US",
    "sg:address":"7533 Hollywood Blvd",
    "sg:city":"West Hollywood",
    "sg:classifiers":[
        {
            "category":"Home & Garden",
            "subcategory":"Household Appliances",
            "type":"Retail Goods"
        }
    ],
    "sg:phone":"+1 818 506 4400",
    "sg:postcode":"90046",
    "sg:province":"CA",
    "wof:name":"Appliance & AC SVC",
    "wof:placetype":"venue"
},
  "geometry": {"coordinates":[-118.353336,34.101723],"type":"Point"}
}