{
  "type": "Feature",
  "properties": {
    "addr:full":"230 N Maryland Ave Glendale CA 91206",
    "addr:housenumber":"230",
    "addr:postcode":"91206",
    "addr:street":"N Maryland Ave",
    "iso:country":"US",
    "sg:address":"230 N Maryland Ave",
    "sg:city":"Glendale",
    "sg:classifiers":[
        {
            "category":"Health Services",
            "subcategory":"Dentist",
            "type":"Services"
        }
    ],
    "sg:phone":"+1 818 547 2804",
    "sg:postcode":"91206",
    "sg:province":"CA",
    "wof:name":"Glendale Endodontics Group",
    "wof:placetype":"venue"
},
  "geometry": {"coordinates":[-118.253998,34.1479],"type":"Point"}
}