{
  "type": "Feature",
  "properties": {
    "iso:country":"US",
    "sg:address":"1882 Fulton Ave",
    "sg:city":"Sacramento",
    "sg:classifiers":[
        {
            "category":"Retail",
            "subcategory":"Animal Services",
            "type":"Services"
        }
    ],
    "sg:phone":"+1 916 972 7297",
    "sg:postcode":"95825",
    "sg:province":"CA",
    "sg:tags":[
        "pet",
        "grooming"
    ],
    "wof:name":"Animal Works Inc.",
    "wof:placetype":"venue"
},
  "geometry": {"coordinates":[-121.40149700000001,38.599583],"type":"Point"}
}