{
  "type": "Feature",
  "properties": {
    "addr:full":"11330 Lakeview Ave Lucerne Valley CA 92356",
    "addr:housenumber":"11330",
    "addr:postcode":"92356",
    "addr:street":"Lakeview Ave",
    "iso:country":"US",
    "sg:address":"11330 Lakeview Ave",
    "sg:city":"Lucerne Valley",
    "sg:classifiers":[
        {
            "category":"Building & Trades",
            "subcategory":"Construction",
            "type":"Services"
        }
    ],
    "sg:phone":"+1 760 248 2294",
    "sg:postcode":"92356",
    "sg:province":"CA",
    "sg:tags":[
        "handyman"
    ],
    "wof:name":"Rnl Residential & Commercial",
    "wof:placetype":"venue"
},
  "geometry": {"coordinates":[-116.827403,34.459055],"type":"Point"}
}