{
  "type": "Feature",
  "properties": {
    "iso:country":"US",
    "sg:address":"2325 30th St",
    "sg:city":"San Diego",
    "sg:classifiers":[
        {
            "category":"Organizations",
            "subcategory":"Non-profit Organization",
            "type":"Services"
        }
    ],
    "sg:phone":"+1 619 584 2825",
    "sg:postcode":"92104",
    "sg:province":"CA",
    "sg:tags":[
        "info",
        "addiction",
        "abuse",
        "treatment",
        "drug"
    ],
    "wof:name":"Bethesda Recovery Ctr",
    "wof:placetype":"venue"
},
  "geometry": {"coordinates":[-117.129458,32.730739],"type":"Point"}
}