{
  "type": "Feature",
  "properties": {
    "iso:country":"US",
    "sg:address":"3808 N Blackstone Ave",
    "sg:city":"Fresno",
    "sg:classifiers":[
        {
            "category":"Building & Trades",
            "subcategory":"Construction",
            "type":"Services"
        }
    ],
    "sg:phone":"+1 559 217 7110",
    "sg:postcode":"93726",
    "sg:province":"CA",
    "sg:tags":[
        "maintenance",
        "contractor"
    ],
    "wof:name":"QFS Svc Station Maintenance",
    "wof:placetype":"venue"
},
  "geometry": {"coordinates":[-119.790442,36.787034],"type":"Point"}
}