{
  "type": "Feature",
  "properties": {
    "addr:full":"5325 N Commerce Ave Moorpark CA 93021",
    "addr:housenumber":"5325",
    "addr:postcode":"ca 93021",
    "addr:street":"N Commerce Ave",
    "iso:country":"US",
    "sg:address":"5325 N Commerce Ave",
    "sg:city":"Moorpark",
    "sg:classifiers":[
        {
            "category":"Utilities",
            "type":"Services"
        }
    ],
    "sg:phone":"+1 805 532 1776",
    "sg:postcode":"93021",
    "sg:province":"CA",
    "sg:tags":[
        "locating"
    ],
    "sg:website":"www.floorboxes.com",
    "wof:name":"Combine Utilities Box System",
    "wof:placetype":"venue"
},
  "geometry": {"coordinates":[-118.89881699999999,34.281158],"type":"Point"}
}