{
  "type": "Feature",
  "properties": {
    "addr:full":"12222 New York Ranch Rd Jackson CA 95642",
    "addr:housenumber":"12222",
    "addr:postcode":"95642",
    "addr:street":"New;Ranch Rd",
    "iso:country":"US",
    "sg:address":"12222 New York Ranch Rd",
    "sg:city":"Jackson",
    "sg:classifiers":[
        {
            "category":"Restaurant",
            "type":"Food & Drink"
        }
    ],
    "sg:menulink":"http://www.allmenus.com/ca/jackson/34868-raging-river/menu/",
    "sg:phone":"+1 209 223 1677",
    "sg:postcode":"95642",
    "sg:province":"CA",
    "sg:tags":[
        "american"
    ],
    "wof:name":"Raging River",
    "wof:placetype":"venue"
},
  "geometry": {"coordinates":[-120.738911,38.38565],"type":"Point"}
}