{
  "type": "Feature",
  "properties": {
    "iso:country":"US",
    "sg:address":"13021 Century Blvd",
    "sg:city":"Garden Grove",
    "sg:classifiers":[
        {
            "category":"Autos & Motor Vehicles",
            "subcategory":"Auto Supplies",
            "type":"Retail Goods"
        }
    ],
    "sg:phone":"+1 714 638 8309",
    "sg:postcode":"92843",
    "sg:province":"CA",
    "sg:tags":[
        "tire"
    ],
    "wof:name":"Michigan Wheels",
    "wof:placetype":"venue"
},
  "geometry": {"coordinates":[-117.944971,33.773682],"type":"Point"}
}