{
  "type": "Feature",
  "properties": {
    "addr:full":"2121 N California Blvd Walnut Creek CA 94596",
    "addr:housenumber":"2121",
    "addr:postcode":"94596",
    "addr:street":"N California Blvd",
    "iso:country":"US",
    "sg:address":"2121 N California Blvd",
    "sg:city":"Walnut Creek",
    "sg:classifiers":[
        {
            "category":"Insurance",
            "subcategory":"Insurance Agent",
            "type":"Services"
        }
    ],
    "sg:phone":"+1 925 979 2300",
    "sg:postcode":"94596",
    "sg:province":"CA",
    "wof:name":"San Francisco Bay Area Agency",
    "wof:placetype":"venue"
},
  "geometry": {"coordinates":[-122.06632399999999,37.907711],"type":"Point"}
}