{
  "type": "Feature",
  "properties": {
    "addr:full":"2751 W Coast Hwy Newport Beach CA 92663",
    "addr:housenumber":"2751",
    "addr:postcode":"92663",
    "addr:street":"W Coast Hwy",
    "iso:country":"US",
    "sg:address":"2751 W Coast Hwy",
    "sg:city":"Newport Beach",
    "sg:classifiers":[
        {
            "category":"Restaurant",
            "type":"Food & Drink"
        }
    ],
    "sg:phone":"+1 949 722 1100",
    "sg:postcode":"92663",
    "sg:province":"CA",
    "sg:tags":[
        "seafood"
    ],
    "sg:website":"www.billys-at-the-beach.com",
    "wof:name":"Billys At the Beach",
    "wof:placetype":"venue"
},
  "geometry": {"coordinates":[-117.924004,33.620098],"type":"Point"}
}