{
  "type": "Feature",
  "properties": {
    "addr:full":"144 W D St Ste 15 Encinitas CA 92024",
    "addr:housenumber":"144",
    "addr:postcode":"92024",
    "addr:street":"W D St Ste 15",
    "iso:country":"US",
    "sg:address":"144 W D St Ste 15",
    "sg:city":"Encinitas",
    "sg:classifiers":[
        {
            "category":"Real Estate",
            "subcategory":"Real Estate Services",
            "type":"Services"
        }
    ],
    "sg:phone":"+1 760 940 4100",
    "sg:postcode":"92024",
    "sg:province":"CA",
    "wof:name":"Palomar Financial Realty & Mortgage",
    "wof:placetype":"venue"
},
  "geometry": {"coordinates":[-117.294532,33.046192],"type":"Point"}
}