{
  "type": "Feature",
  "properties": {
    "addr:full":"1108 E Walnut St Pasadena CA 91106",
    "addr:housenumber":"1108",
    "addr:postcode":"91106",
    "addr:street":"E Walnut St",
    "iso:country":"US",
    "sg:address":"1108 E Walnut St",
    "sg:city":"Pasadena",
    "sg:classifiers":[
        {
            "category":"Retail",
            "subcategory":"Repair Shop",
            "type":"Services"
        }
    ],
    "sg:phone":"+1 626 577 9275",
    "sg:postcode":"91106",
    "sg:province":"CA",
    "sg:tags":[
        "reupholstery",
        "furniture"
    ],
    "wof:name":"Pacific Design Upholstery",
    "wof:placetype":"venue"
},
  "geometry": {"coordinates":[-118.12799800000001,34.149502],"type":"Point"}
}