{
  "type": "Feature",
  "properties": {
    "iso:country":"US",
    "sg:address":"7056 Gerald Ave",
    "sg:city":"Van Nuys",
    "sg:classifiers":[
        {
            "category":"Retail",
            "subcategory":"Auto Repair",
            "type":"Services"
        }
    ],
    "sg:phone":"+1 818 781 1414",
    "sg:postcode":"91406",
    "sg:province":"CA",
    "sg:tags":[
        "carburetor"
    ],
    "wof:name":"J & R Auto Industries",
    "wof:placetype":"venue"
},
  "geometry": {"coordinates":[-118.493407,34.199134],"type":"Point"}
}