{
  "type": "Feature",
  "properties": {
    "iso:country":"US",
    "sg:address":"5310 Zelzah Ave",
    "sg:city":"Encino",
    "sg:classifiers":[
        {
            "category":"Education",
            "subcategory":"School",
            "type":"Public Place"
        }
    ],
    "sg:phone":"+1 818 708 9493",
    "sg:postcode":"91316",
    "sg:province":"CA",
    "wof:name":"Friendship Kids Academy Inc",
    "wof:placetype":"venue"
},
  "geometry": {"coordinates":[-118.52194799999999,34.166806],"type":"Point"}
}