{
  "type": "Feature",
  "properties": {
    "iso:country":"US",
    "sg:address":"846 S State College Blvd",
    "sg:city":"Anaheim",
    "sg:classifiers":[
        {
            "category":"Real Estate",
            "subcategory":"Architect",
            "type":"Services"
        }
    ],
    "sg:phone":"+1 714 992 2473",
    "sg:postcode":"92806",
    "sg:province":"CA",
    "wof:name":"Drummond Thomas & Associates",
    "wof:placetype":"venue"
},
  "geometry": {"coordinates":[-117.889,33.829399],"type":"Point"}
}