{
  "type": "Feature",
  "properties": {
    "addr:full":"19350 Ward St Huntington Beach CA 92646",
    "addr:housenumber":"19350",
    "addr:postcode":"92646",
    "addr:street":"Ward St",
    "iso:country":"US",
    "sg:address":"19350 Ward St",
    "sg:city":"Huntington Beach",
    "sg:classifiers":[
        {
            "category":"Real Estate",
            "subcategory":"Real Estate Operator",
            "type":"Services"
        }
    ],
    "sg:phone":"+1 714 968 0820",
    "sg:postcode":"92646",
    "sg:province":"CA",
    "sg:tags":[
        "mobile",
        "home",
        "site"
    ],
    "wof:name":"Mariners Pointe Mobile Home Pk",
    "wof:placetype":"venue"
},
  "geometry": {"coordinates":[-117.945172,33.679754],"type":"Point"}
}