{
  "type": "Feature",
  "properties": {
    "addr:full":"24911 Adelanto Dr Laguna Niguel CA 92677",
    "addr:postcode":"24911;92677",
    "addr:street":"Adelanto Dr",
    "iso:country":"US",
    "sg:address":"24911 Adelanto Dr",
    "sg:city":"Laguna Niguel",
    "sg:classifiers":[
        {
            "category":"Social Services",
            "subcategory":"Adult Care",
            "type":"Services"
        }
    ],
    "sg:phone":"+1 949 363 6122",
    "sg:postcode":"92677",
    "sg:province":"CA",
    "sg:tags":[
        "home",
        "residential"
    ],
    "wof:name":"Valley Residential Elder Care",
    "wof:placetype":"venue"
},
  "geometry": {"coordinates":[-117.695685,33.536686],"type":"Point"}
}