{
  "type": "Feature",
  "properties": {
    "addr:full":"2113 Kittredge St Berkeley CA 94704",
    "addr:housenumber":"2113",
    "addr:postcode":"94704",
    "addr:street":"Kittredge St",
    "iso:country":"US",
    "sg:address":"2113 Kittredge St",
    "sg:city":"Berkeley",
    "sg:classifiers":[
        {
            "category":"Cinema",
            "subcategory":"Movie Theater",
            "type":"Entertainment"
        }
    ],
    "sg:phone":"+1 510 848 0249",
    "sg:postcode":"94704",
    "sg:province":"CA",
    "sg:website":"http://www.landmarktheatres.com",
    "wof:name":"California Theatre",
    "wof:placetype":"venue"
},
  "geometry": {"coordinates":[-122.267611,37.868545],"type":"Point"}
}