{
  "type": "Feature",
  "properties": {
    "addr:full":"12838 Wible Rd Bakersfield CA 93313",
    "addr:postcode":"12838;93313",
    "addr:street":"Wible Rd",
    "iso:country":"US",
    "sg:address":"12838 Wible Rd",
    "sg:city":"Bakersfield",
    "sg:classifiers":[
        {
            "category":"Wholesale",
            "subcategory":"Farm Supplies",
            "type":"Manufacturing & Wholesale Goods"
        }
    ],
    "sg:phone":"+1 661 836 1497",
    "sg:postcode":"93313",
    "sg:province":"CA",
    "sg:tags":[
        "feed"
    ],
    "wof:name":"Martin Feed",
    "wof:placetype":"venue"
},
  "geometry": {"coordinates":[-119.039016,35.231531],"type":"Point"}
}