{
  "type": "Feature",
  "properties": {
    "addr:full":"1379 Spinnaker Dr Ventura CA 93001",
    "addr:housenumber":"1379",
    "addr:postcode":"93001",
    "addr:street":"Spinnaker Dr",
    "iso:country":"US",
    "sg:address":"1379 Spinnaker Dr",
    "sg:city":"Ventura",
    "sg:classifiers":[
        {
            "category":"Recreation",
            "subcategory":"Marina",
            "type":"Entertainment"
        },
        {
            "category":"Manufacturing",
            "subcategory":"Watercraft",
            "type":"Manufacturing & Wholesale Goods"
        }
    ],
    "sg:phone":"+1 805 654 1433",
    "sg:postcode":"93001",
    "sg:province":"CA",
    "sg:tags":[
        "operation",
        "part",
        "rebuilt",
        "boat"
    ],
    "wof:name":"Ventura Harbor Boatyard Inc",
    "wof:placetype":"venue"
},
  "geometry": {"coordinates":[-119.26117600000001,34.240302],"type":"Point"}
}