{
  "type": "Feature",
  "properties": {
    "addr:full":"531 S Berendo St Los Angeles CA 90020",
    "addr:housenumber":"531",
    "addr:postcode":"90020",
    "addr:street":"S Berendo St",
    "iso:country":"US",
    "sg:address":"531 S Berendo St",
    "sg:city":"Los Angeles",
    "sg:classifiers":[
        {
            "category":"Insurance",
            "subcategory":"Insurance Agent",
            "type":"Services"
        }
    ],
    "sg:phone":"+1 213 384 4010",
    "sg:postcode":"90020",
    "sg:province":"CA",
    "wof:name":"R L Meals Jr Insurance",
    "wof:placetype":"venue"
},
  "geometry": {"coordinates":[-118.294212,34.064154],"type":"Point"}
}