{
  "type": "Feature",
  "properties": {
    "addr:full":"3170 Cam de Aguas Carlsbad CA 92009",
    "addr:housenumber":"3170",
    "addr:postcode":"92009",
    "addr:street":"Cam De Aguas",
    "iso:country":"US",
    "sg:address":"3170 Cam de Aguas",
    "sg:city":"Carlsbad",
    "sg:classifiers":[
        {
            "category":"Professional",
            "subcategory":"Management & Consulting",
            "type":"Services"
        }
    ],
    "sg:phone":"+1 760 753 2224",
    "sg:postcode":"92009",
    "sg:province":"CA",
    "sg:tags":[
        "selling",
        "establishment",
        "direct"
    ],
    "wof:name":"Amway Distributors",
    "wof:placetype":"venue"
},
  "geometry": {"coordinates":[-117.23906100000001,33.0924],"type":"Point"}
}