{
  "type": "Feature",
  "properties": {
    "iso:country":"US",
    "sg:address":"11326 Polaris Dr",
    "sg:city":"San Diego",
    "sg:classifiers":[
        {
            "category":"Organizations",
            "subcategory":"Non-profit Organization",
            "type":"Services"
        }
    ],
    "sg:phone":"+1 858 693 8537",
    "sg:postcode":"92126",
    "sg:province":"CA",
    "sg:tags":[
        "handicapped"
    ],
    "wof:name":"Mercado Adult Residential Fac",
    "wof:placetype":"venue"
},
  "geometry": {"coordinates":[-117.127706,32.928573],"type":"Point"}
}