{
  "type": "Feature",
  "properties": {
    "addr:full":"539 N Glenoaks Blvd Ste 101 Burbank CA 91502",
    "addr:housenumber":"539",
    "addr:postcode":"91502",
    "addr:street":"N Glenoaks Blvd Ste 101",
    "iso:country":"US",
    "sg:address":"539 N Glenoaks Blvd Ste 101",
    "sg:city":"Burbank",
    "sg:classifiers":[
        {
            "category":"Real Estate",
            "subcategory":"Real Estate Services",
            "type":"Services"
        }
    ],
    "sg:phone":"+1 818 845 1565",
    "sg:postcode":"91502",
    "sg:province":"CA",
    "wof:name":"Phillip Beauregard Realtor",
    "wof:placetype":"venue"
},
  "geometry": {"coordinates":[-118.306999,34.179001],"type":"Point"}
}