{
  "type": "Feature",
  "properties": {
    "addr:full":"4407 Manchester Ave Encinitas CA 92024",
    "addr:housenumber":"4407",
    "addr:postcode":"92024",
    "addr:street":"Manchester Ave",
    "iso:country":"US",
    "sg:address":"4407 Manchester Ave",
    "sg:city":"Encinitas",
    "sg:classifiers":[
        {
            "category":"Professional",
            "type":"Services"
        }
    ],
    "sg:phone":"+1 760 436 2479",
    "sg:postcode":"92024",
    "sg:province":"CA",
    "sg:tags":[
        "establishment"
    ],
    "sg:website":"www.airxus.com",
    "wof:name":"Air-X",
    "wof:placetype":"venue"
},
  "geometry": {"coordinates":[-117.23890900000001,33.036474],"type":"Point"}
}