{
  "type": "Feature",
  "properties": {
    "addr:full":"2755 Auto Mall Dr Selma CA 93662",
    "addr:housenumber":"2755",
    "addr:postcode":"93662",
    "addr:street":"Auto Mall Dr",
    "iso:country":"US",
    "sg:address":"2755 Auto Mall Dr",
    "sg:city":"Selma",
    "sg:classifiers":[
        {
            "category":"Autos & Motor Vehicles",
            "subcategory":"Auto Supplies",
            "type":"Retail Goods"
        }
    ],
    "sg:phone":"+1 559 891 5111",
    "sg:postcode":"93662",
    "sg:province":"CA",
    "sg:tags":[
        "automobile",
        "parts"
    ],
    "wof:name":"Selma Honda",
    "wof:placetype":"venue"
},
  "geometry": {"coordinates":[-119.625007,36.571647],"type":"Point"}
}