{
  "type": "Feature",
  "properties": {
    "iso:country":"US",
    "sg:address":"1618 Copenhagen Dr",
    "sg:city":"Solvang",
    "sg:classifiers":[
        {
            "category":"Shopping",
            "type":"Retail Goods"
        }
    ],
    "sg:phone":"+1 805 688 2252",
    "sg:postcode":"93463",
    "sg:province":"CA",
    "sg:tags":[
        "merchandise"
    ],
    "wof:name":"Copenhagen Gallery",
    "wof:placetype":"venue"
},
  "geometry": {"coordinates":[-120.141228,34.595287],"type":"Point"}
}