{
  "type": "Feature",
  "properties": {
    "iso:country":"US",
    "sg:address":"93 Lind Ave",
    "sg:city":"Clovis",
    "sg:classifiers":[
        {
            "category":"Health Services",
            "subcategory":"Health Practitioner",
            "type":"Services"
        }
    ],
    "sg:phone":"+1 559 299 5540",
    "sg:postcode":"93612",
    "sg:province":"CA",
    "sg:tags":[
        "therapist",
        "physical"
    ],
    "wof:name":"Showers Physical Therapy",
    "wof:placetype":"venue"
},
  "geometry": {"coordinates":[-119.711584,36.82977],"type":"Point"}
}