{
  "type": "Feature",
  "properties": {
    "addr:full":"2031 Pioneer Ct San Mateo CA 94403",
    "addr:housenumber":"2031",
    "addr:postcode":"94403",
    "addr:street":"Pioneer Ct",
    "iso:country":"US",
    "sg:address":"2031 Pioneer Ct",
    "sg:city":"San Mateo",
    "sg:classifiers":[
        {
            "category":"Professional",
            "subcategory":"Engineering",
            "type":"Services"
        }
    ],
    "sg:phone":"+1 650 345 3554",
    "sg:postcode":"94403",
    "sg:province":"CA",
    "sg:tags":[
        "engineer"
    ],
    "wof:name":"Cecil H Wells Jr & Assoc",
    "wof:placetype":"venue"
},
  "geometry": {"coordinates":[-122.31181100000001,37.546711],"type":"Point"}
}