{
  "type": "Feature",
  "properties": {
    "addr:full":"1420 Harbor Bay Pkwy Alameda CA 94502",
    "addr:housenumber":"1420",
    "addr:postcode":"94502",
    "addr:street":"Harbor Bay Pkwy",
    "iso:country":"US",
    "sg:address":"1420 Harbor Bay Pkwy",
    "sg:city":"Alameda",
    "sg:classifiers":[
        {
            "category":"Shopping",
            "subcategory":"Gifts & Souvenirs",
            "type":"Retail Goods"
        }
    ],
    "sg:phone":"+1 510 814 9174",
    "sg:postcode":"94502",
    "sg:province":"CA",
    "sg:tags":[
        "party",
        "supply"
    ],
    "wof:name":"Associated Thrid Party Adminis",
    "wof:placetype":"venue"
},
  "geometry": {"coordinates":[-122.236723,37.725365],"type":"Point"}
}