{
  "type": "Feature",
  "properties": {
    "addr:full":"11891 Gladstone Dr Santa Ana CA 92705",
    "addr:housenumber":"11891",
    "addr:postcode":"92705",
    "addr:street":"Gladstone Dr",
    "iso:country":"US",
    "sg:address":"11891 Gladstone Dr",
    "sg:city":"Santa Ana",
    "sg:classifiers":[
        {
            "category":"Manufacturing",
            "subcategory":"Textiles",
            "type":"Manufacturing & Wholesale Goods"
        }
    ],
    "sg:phone":"+1 714 730 3627",
    "sg:postcode":"92705",
    "sg:province":"CA",
    "sg:tags":[
        "finishing",
        "plant",
        "mfg"
    ],
    "wof:name":"Black Sheep",
    "wof:placetype":"venue"
},
  "geometry": {"coordinates":[-117.79697,33.760558],"type":"Point"}
}