{
  "type": "Feature",
  "properties": {
    "addr:full":"260 Sheridan Avenue Suite 420 Palo Alto CA 94306",
    "addr:housenumber":"260",
    "addr:postcode":"94306",
    "addr:street":"Sheridan Avenue Suite 420",
    "iso:country":"US",
    "sg:address":"260 Sheridan Avenue Suite 420",
    "sg:city":"Palo Alto",
    "sg:classifiers":[
        {
            "category":"Professional",
            "subcategory":"Computer Services",
            "type":"Services"
        }
    ],
    "sg:phone":"+1 800 805 0828",
    "sg:postcode":"94306",
    "sg:province":"CA",
    "sg:tags":[
        "businessintelligence",
        "enterprise",
        "reporting",
        "analytics"
    ],
    "sg:website":"http://www.kapowtech.com",
    "wof:name":"Kapow Technologies",
    "wof:placetype":"venue"
},
  "geometry": {"coordinates":[-122.14064399999999,37.42657],"type":"Point"}
}