{
  "type": "Feature",
  "properties": {
    "addr:full":"3350 Wilshire Boulevard Suite 940 Los Angeles CA 90010",
    "addr:housenumber":"3350",
    "addr:postcode":"90010",
    "addr:street":"Wilshire Boulevard Suite 940",
    "iso:country":"US",
    "sg:address":"3350 Wilshire Boulevard Suite 940",
    "sg:city":"Los Angeles",
    "sg:classifiers":[
        {
            "category":"Health Services",
            "subcategory":"Clinic",
            "type":"Services"
        }
    ],
    "sg:phone":"+1 213 487 7052",
    "sg:postcode":"90010",
    "sg:province":"CA",
    "sg:tags":[
        "medical"
    ],
    "sg:website":"www.AffiliatedHomeHealth.com",
    "wof:name":"Affiliated Home Health Services, Inc.",
    "wof:placetype":"venue"
},
  "geometry": {"coordinates":[-118.29584,34.061721],"type":"Point"}
}