{
  "type": "Feature",
  "properties": {
    "iso:country":"US",
    "sg:address":"3939 Bernard St",
    "sg:city":"Bakersfield",
    "sg:classifiers":[
        {
            "category":"Professional",
            "subcategory":"Accounting & Tax Preparation",
            "type":"Services"
        }
    ],
    "sg:phone":"+1 661 872 1891",
    "sg:postcode":"93306",
    "sg:province":"CA",
    "sg:tags":[
        "bookkeeping",
        "general"
    ],
    "wof:name":"Highland Bookkeeping & Tax Svc",
    "wof:placetype":"venue"
},
  "geometry": {"coordinates":[-118.94873699999999,35.392472],"type":"Point"}
}