{
  "type": "Feature",
  "properties": {
    "addr:full":"220 W 21st St Los Angeles CA 90007",
    "addr:housenumber":"220",
    "addr:postcode":"90007",
    "addr:street":"W 21St St",
    "iso:country":"US",
    "sg:address":"220 W 21st St",
    "sg:city":"Los Angeles",
    "sg:classifiers":[
        {
            "category":"Professional",
            "subcategory":"Management & Consulting",
            "type":"Services"
        }
    ],
    "sg:phone":"+1 213 763 8030",
    "sg:postcode":"90007",
    "sg:province":"CA",
    "sg:tags":[
        "construction"
    ],
    "wof:name":"Tri-Gem Construction",
    "wof:placetype":"venue"
},
  "geometry": {"coordinates":[-118.268579,34.029971],"type":"Point"}
}