{
  "type": "Feature",
  "properties": {
    "addr:full":"3611 Cahuenga Blvd W Los Angeles CA 90068",
    "addr:housenumber":"3611",
    "addr:postcode":"90068",
    "addr:street":"Cahuenga Blvd W",
    "iso:country":"US",
    "sg:address":"3611 Cahuenga Blvd W",
    "sg:city":"Los Angeles",
    "sg:classifiers":[
        {
            "category":"Communications",
            "subcategory":"Film & Video Production",
            "type":"Services"
        }
    ],
    "sg:phone":"+1 323 876 1815",
    "sg:postcode":"90068",
    "sg:province":"CA",
    "sg:tags":[
        "post",
        "audio",
        "television",
        "for"
    ],
    "wof:name":"Track Designs",
    "wof:placetype":"venue"
},
  "geometry": {"coordinates":[-118.360894,34.134751],"type":"Point"}
}