{
  "type": "Feature",
  "properties": {
    "addr:full":"10554 San Pablo Ave El Cerrito CA 94530",
    "addr:housenumber":"10554",
    "addr:postcode":"94530",
    "addr:street":"San Pablo Ave",
    "iso:country":"US",
    "sg:address":"10554 San Pablo Ave",
    "sg:city":"El Cerrito",
    "sg:classifiers":[
        {
            "category":"Professional",
            "subcategory":"Accounting & Tax Preparation",
            "type":"Services"
        }
    ],
    "sg:phone":"+1 510 559 2030",
    "sg:postcode":"94530",
    "sg:province":"CA",
    "sg:tags":[
        "return",
        "filing"
    ],
    "wof:name":"Jackson & Hewitt",
    "wof:placetype":"venue"
},
  "geometry": {"coordinates":[-122.30762900000001,37.909972],"type":"Point"}
}