{
  "type": "Feature",
  "properties": {
    "iso:country":"US",
    "sg:address":"5020 Campus Drive",
    "sg:city":"Newport Beach",
    "sg:classifiers":[
        {
            "category":"Professional",
            "subcategory":"Accounting & Tax Preparation",
            "type":"Services"
        }
    ],
    "sg:phone":"+1 949 251 0910",
    "sg:postcode":"92660",
    "sg:province":"CA",
    "sg:tags":[
        "accountant"
    ],
    "wof:name":"Klein Robert CPA",
    "wof:placetype":"venue"
},
  "geometry": {"coordinates":[-117.85718300000001,33.667978],"type":"Point"}
}