{
  "type": "Feature",
  "properties": {
    "addr:full":"2497 American Ave Hayward CA 94545",
    "addr:housenumber":"2497",
    "addr:postcode":"94545",
    "addr:street":"American Ave",
    "iso:country":"US",
    "sg:address":"2497 American Ave",
    "sg:city":"Hayward",
    "sg:classifiers":[
        {
            "category":"Professional",
            "subcategory":"Business Services",
            "type":"Services"
        }
    ],
    "sg:phone":"+1 510 670 1017",
    "sg:postcode":"94545",
    "sg:province":"CA",
    "sg:tags":[
        "repairing",
        "sign"
    ],
    "wof:name":"Associated Sign Co",
    "wof:placetype":"venue"
},
  "geometry": {"coordinates":[-122.12851000000001,37.648654],"type":"Point"}
}