{
  "type": "Feature",
  "properties": {
    "addr:full":"25851 Hawthorne Blvd Rolling Hills Estates CA 90274",
    "addr:housenumber":"25851",
    "addr:postcode":"90274",
    "addr:street":"Hawthorne Blvd",
    "iso:country":"US",
    "sg:address":"25851 Hawthorne Blvd",
    "sg:city":"Rolling Hills Estates",
    "sg:classifiers":[
        {
            "category":"Sports & Exercise",
            "subcategory":"Stables",
            "type":"Entertainment"
        },
        {
            "category":"Park",
            "type":"Public Place"
        },
        {
            "category":"Sports & Exercise",
            "subcategory":"Tennis Court",
            "type":"Entertainment"
        }
    ],
    "sg:phone":"+1 310 541 4585",
    "sg:postcode":"90274",
    "sg:province":"CA",
    "sg:tags":[
        "riding",
        "horseback"
    ],
    "wof:name":"Ernie Howlett Park",
    "wof:placetype":"venue"
},
  "geometry": {"coordinates":[-118.354951,33.790316],"type":"Point"}
}