{
  "type": "Feature",
  "properties": {
    "addr:full":"2200 Stokes Canyon Rd Calabasas CA 91302",
    "addr:housenumber":"2200",
    "addr:postcode":"91302",
    "addr:street":"Stokes Canyon Rd",
    "iso:country":"US",
    "sg:address":"2200 Stokes Canyon Rd",
    "sg:city":"Calabasas",
    "sg:classifiers":[
        {
            "category":"Farming",
            "subcategory":"Livestock Farm",
            "type":"Manufacturing & Wholesale Goods"
        },
        {
            "category":"Retail",
            "subcategory":"Animal Services",
            "type":"Services"
        }
    ],
    "sg:phone":"+1 818 878 3071",
    "sg:postcode":"91302",
    "sg:province":"CA",
    "sg:tags":[
        "training",
        "horse"
    ],
    "sg:website":"http://www.apollofarmsinc.com",
    "wof:name":"Apollo Farms Inc",
    "wof:placetype":"venue"
},
  "geometry": {"coordinates":[-118.702911,34.104179],"type":"Point"}
}