{
  "type": "Feature",
  "properties": {
    "iso:country":"US",
    "sg:address":"1587 Franklin St",
    "sg:city":"Oakland",
    "sg:classifiers":[
        {
            "category":"Shopping",
            "subcategory":"Pets & Pet Supplies",
            "type":"Retail Goods"
        }
    ],
    "sg:phone":"+1 510 525 2547",
    "sg:postcode":"94612",
    "sg:province":"CA",
    "sg:tags":[
        "training"
    ],
    "sg:website":"http://www.dogtec.org",
    "wof:name":"dogTEC",
    "wof:placetype":"venue"
},
  "geometry": {"coordinates":[-122.268989,37.805409],"type":"Point"}
}