{
  "type": "Feature",
  "properties": {
    "iso:country":"US",
    "sg:address":"32230 Sage Rd",
    "sg:city":"Hemet",
    "sg:classifiers":[
        {
            "category":"Shopping",
            "type":"Retail Goods"
        }
    ],
    "sg:phone":"+1 951 767 0158",
    "sg:postcode":"92544",
    "sg:province":"CA",
    "sg:tags":[
        "feed",
        "farm",
        "merchandise",
        "supply"
    ],
    "wof:name":"Daimond Valley Markert",
    "wof:placetype":"venue"
},
  "geometry": {"coordinates":[-116.942195,33.653337],"type":"Point"}
}