{
  "type": "Feature",
  "properties": {
    "iso:country":"US",
    "sg:address":"4155 W Washington Blvd",
    "sg:city":"Los Angeles",
    "sg:classifiers":[
        {
            "category":"Wholesale",
            "subcategory":"Electrical",
            "type":"Manufacturing & Wholesale Goods"
        }
    ],
    "sg:phone":"+1 323 373 0200",
    "sg:postcode":"90018",
    "sg:province":"CA",
    "sg:tags":[
        "electric",
        "motor"
    ],
    "wof:name":"MIJU Motor",
    "wof:placetype":"venue"
},
  "geometry": {"coordinates":[-118.330962,34.039942],"type":"Point"}
}