{
  "type": "Feature",
  "properties": {
    "addr:full":"2215 Ocean Front Walk Venice CA 90291",
    "addr:housenumber":"2215",
    "addr:postcode":"90291",
    "addr:street":"Ocean Front Walk",
    "iso:country":"US",
    "sg:address":"2215 Ocean Front Walk",
    "sg:city":"Venice",
    "sg:classifiers":[
        {
            "category":"Communications",
            "subcategory":"Film & Video Production",
            "type":"Services"
        }
    ],
    "sg:phone":"+1 310 823 4790",
    "sg:postcode":"90291",
    "sg:province":"CA",
    "sg:tags":[
        "motion",
        "picture",
        "studio",
        "producer"
    ],
    "wof:name":"Zirius Film Productions",
    "wof:placetype":"venue"
},
  "geometry": {"coordinates":[-118.47042399999999,33.983324],"type":"Point"}
}