{
  "type": "Feature",
  "properties": {
    "addr:full":"2200 E Artesia Blvd Long Beach CA 90805",
    "addr:housenumber":"2200",
    "addr:postcode":"90805",
    "addr:street":"E Artesia Blvd",
    "iso:country":"US",
    "sg:address":"2200 E Artesia Blvd",
    "sg:city":"Long Beach",
    "sg:classifiers":[
        {
            "category":"Wholesale",
            "subcategory":"Home Furnishings",
            "type":"Manufacturing & Wholesale Goods"
        }
    ],
    "sg:phone":"+1 562 422 6992",
    "sg:postcode":"90805",
    "sg:province":"CA",
    "sg:tags":[
        "linoleum"
    ],
    "wof:name":"Compass Concepts",
    "wof:placetype":"venue"
},
  "geometry": {"coordinates":[-118.165634,33.874659],"type":"Point"}
}