{
  "type": "Feature",
  "properties": {
    "addr:full":"18 Crow Canyon Ct San Ramon CA 94583",
    "addr:housenumber":"18",
    "addr:postcode":"94583",
    "addr:street":"Crow Canyon Ct",
    "iso:country":"US",
    "sg:address":"18 Crow Canyon Ct",
    "sg:city":"San Ramon",
    "sg:classifiers":[
        {
            "category":"Professional",
            "subcategory":"Management & Consulting",
            "type":"Services"
        }
    ],
    "sg:phone":"+1 925 362 9730",
    "sg:postcode":"94583",
    "sg:province":"CA",
    "sg:tags":[
        "marketing",
        "consultant"
    ],
    "wof:name":"Next Marketing",
    "wof:placetype":"venue"
},
  "geometry": {"coordinates":[-121.981413,37.777229],"type":"Point"}
}