{
  "type": "Feature",
  "properties": {
    "addr:full":"16457 Ave 24 1/2 Chowchilla CA 93610",
    "addr:housenumber":"16457;1 / 2",
    "addr:postcode":"93610",
    "addr:street":"Ave 24",
    "iso:country":"US",
    "sg:address":"16457 Ave 24 1/2",
    "sg:city":"Chowchilla",
    "sg:classifiers":[
        {
            "category":"Professional",
            "type":"Services"
        }
    ],
    "sg:phone":"+1 559 665 7763",
    "sg:postcode":"93610",
    "sg:province":"CA",
    "sg:tags":[
        "establishment"
    ],
    "wof:name":"Chow II",
    "wof:placetype":"venue"
},
  "geometry": {"coordinates":[-120.11081900000001,37.083415],"type":"Point"}
}