{
  "type": "Feature",
  "properties": {
    "addr:full":"108 Bryant St Ojai CA 93023",
    "addr:housenumber":"108",
    "addr:postcode":"93023",
    "addr:street":"Bryant St",
    "iso:country":"US",
    "sg:address":"108 Bryant St",
    "sg:city":"Ojai",
    "sg:classifiers":[
        {
            "category":"Building & Trades",
            "subcategory":"Landscaping Services",
            "type":"Services"
        }
    ],
    "sg:phone":"+1 805 646 8498",
    "sg:postcode":"93023",
    "sg:province":"CA",
    "sg:tags":[
        "landscape",
        "contractor"
    ],
    "wof:name":"Full Spectrum Landscaping",
    "wof:placetype":"venue"
},
  "geometry": {"coordinates":[-119.236437,34.448339],"type":"Point"}
}