{
  "type": "Feature",
  "properties": {
    "iso:country":"US",
    "sg:address":"1040 Di Giulio Ave Ste 350",
    "sg:city":"Santa Clara",
    "sg:classifiers":[
        {
            "category":"Retail",
            "subcategory":"Auto Repair",
            "type":"Services"
        }
    ],
    "sg:phone":"+1 408 988 3619",
    "sg:postcode":"95050",
    "sg:province":"CA",
    "sg:website":"www.rearendspecialties.com",
    "wof:name":"Rearend Specialties",
    "wof:placetype":"venue"
},
  "geometry": {"coordinates":[-121.950755,37.360468],"type":"Point"}
}