{
  "type": "Feature",
  "properties": {
    "addr:full":"10672 Cassowary Ct San Diego CA 92131",
    "addr:housenumber":"10672",
    "addr:postcode":"92131",
    "addr:street":"Cassowary Ct",
    "iso:country":"US",
    "sg:address":"10672 Cassowary Ct",
    "sg:city":"San Diego",
    "sg:classifiers":[
        {
            "category":"Shopping",
            "type":"Retail Goods"
        }
    ],
    "sg:phone":"+1 619 206 1316",
    "sg:postcode":"92131",
    "sg:province":"CA",
    "sg:tags":[
        "merchandise"
    ],
    "wof:name":"Custom Automotive Installation",
    "wof:placetype":"venue"
},
  "geometry": {"coordinates":[-117.098274,32.932321],"type":"Point"}
}