{
  "type": "Feature",
  "properties": {
    "addr:full":"11739 Ayres Ave Los Angeles CA 90064",
    "addr:postcode":"11739;90064",
    "addr:street":"Ayres Ave",
    "iso:country":"US",
    "sg:address":"11739 Ayres Ave",
    "sg:city":"Los Angeles",
    "sg:classifiers":[
        {
            "category":"Wholesale",
            "subcategory":"Drugs",
            "type":"Manufacturing & Wholesale Goods"
        }
    ],
    "sg:phone":"+1 310 445 2000",
    "sg:postcode":"90064",
    "sg:province":"CA",
    "sg:tags":[
        "perfume"
    ],
    "wof:name":"Stacked Style",
    "wof:placetype":"venue"
},
  "geometry": {"coordinates":[-118.446958,34.030018],"type":"Point"}
}