{
  "type": "Feature",
  "properties": {
    "iso:country":"US",
    "sg:address":"4274 Telegraph Rd",
    "sg:city":"Ventura",
    "sg:classifiers":[
        {
            "category":"Government",
            "subcategory":"Office",
            "type":"Public Place"
        }
    ],
    "sg:phone":"+1 805 477 2000",
    "sg:postcode":"93003",
    "sg:province":"CA",
    "sg:tags":[
        "county",
        "resource"
    ],
    "wof:name":"Ventura County Human Svc Agcy",
    "wof:placetype":"venue"
},
  "geometry": {"coordinates":[-119.235483,34.274843],"type":"Point"}
}