{
  "type": "Feature",
  "properties": {
    "addr:full":"8285 Sierra Ave Fontana CA 92335",
    "addr:housenumber":"8285",
    "addr:postcode":"92335",
    "addr:street":"Sierra Ave",
    "iso:country":"US",
    "sg:address":"8285 Sierra Ave",
    "sg:city":"Fontana",
    "sg:classifiers":[
        {
            "category":"Real Estate",
            "subcategory":"Real Estate Agent",
            "type":"Services"
        }
    ],
    "sg:phone":"+1 909 434 0545",
    "sg:postcode":"92335",
    "sg:province":"CA",
    "wof:name":"Realty Casa & Estates",
    "wof:placetype":"venue"
},
  "geometry": {"coordinates":[-117.43571300000001,34.104557],"type":"Point"}
}