{
  "type": "Feature",
  "properties": {
    "addr:full":"18909 Sherman Way Ste 100 Reseda CA 91335",
    "addr:housenumber":"18909",
    "addr:postcode":"91335",
    "addr:street":"Sherman Way Ste 100",
    "iso:country":"US",
    "sg:address":"18909 Sherman Way Ste 100",
    "sg:city":"Reseda",
    "sg:classifiers":[
        {
            "category":"Health Services",
            "subcategory":"Clinic",
            "type":"Services"
        }
    ],
    "sg:phone":"+1 818 774 1616",
    "sg:postcode":"91335",
    "sg:province":"CA",
    "sg:tags":[
        "welfare"
    ],
    "wof:name":"Medical Solutions Podiatry, Inc.",
    "wof:placetype":"venue"
},
  "geometry": {"coordinates":[-118.544927,34.201172],"type":"Point"}
}