{
  "type": "Feature",
  "properties": {
    "iso:country":"US",
    "sg:address":"4484 Wilshire Blvd",
    "sg:city":"Los Angeles",
    "sg:classifiers":[
        {
            "category":"Professional",
            "subcategory":"Lawyer & Legal Services",
            "type":"Services"
        }
    ],
    "sg:phone":"+1 323 857 7175",
    "sg:postcode":"90010",
    "sg:province":"CA",
    "sg:tags":[
        "mercury",
        "attorney",
        "co",
        "for",
        "casualty"
    ],
    "wof:name":"Alsop Silva Clasen & Raffalow",
    "wof:placetype":"venue"
},
  "geometry": {"coordinates":[-118.326468,34.061813],"type":"Point"}
}