{
  "type": "Feature",
  "properties": {
    "addr:full":"829 27th Ave Ste E Oakland CA 94601",
    "addr:housenumber":"829",
    "addr:postcode":"94601",
    "addr:street":"27Th Ave Ste E",
    "iso:country":"US",
    "sg:address":"829 27th Ave Ste E",
    "sg:city":"Oakland",
    "sg:classifiers":[
        {
            "category":"Communications",
            "type":"Services"
        }
    ],
    "sg:phone":"+1 510 533 0880",
    "sg:postcode":"94601",
    "sg:province":"CA",
    "sg:tags":[
        "recording",
        "rehearsal",
        "studio"
    ],
    "wof:name":"Studio 880",
    "wof:placetype":"venue"
},
  "geometry": {"coordinates":[-122.236,37.777],"type":"Point"}
}