{
  "type": "Feature",
  "properties": {
    "addr:full":"104 Constitution Dr Menlo Park CA 94025",
    "addr:housenumber":"104",
    "addr:postcode":"94025",
    "addr:street":"Constitution Dr",
    "iso:country":"US",
    "sg:address":"104 Constitution Dr",
    "sg:city":"Menlo Park",
    "sg:classifiers":[
        {
            "category":"Manufacturing",
            "subcategory":"Tools & Machinery",
            "type":"Manufacturing & Wholesale Goods"
        },
        {
            "category":"Wholesale",
            "subcategory":"Durable Goods & Equipment",
            "type":"Manufacturing & Wholesale Goods"
        }
    ],
    "sg:phone":"+1 650 330 0118",
    "sg:postcode":"94025",
    "sg:province":"CA",
    "sg:tags":[
        "electrical",
        "laser",
        "mfg"
    ],
    "wof:name":"Laser Shop",
    "wof:placetype":"venue"
},
  "geometry": {"coordinates":[-122.17661,37.484915],"type":"Point"}
}