{
  "type": "Feature",
  "properties": {
    "iso:country":"US",
    "sg:address":"1741 W Glenoaks Blvd Ste B",
    "sg:city":"Glendale",
    "sg:classifiers":[
        {
            "category":"Health Services",
            "subcategory":"Dentist",
            "type":"Services"
        }
    ],
    "sg:phone":"+1 818 246 0109",
    "sg:postcode":"91201",
    "sg:province":"CA",
    "wof:name":"Kechechyan Anush Dntst",
    "wof:placetype":"venue"
},
  "geometry": {"coordinates":[-118.292,34.170601],"type":"Point"}
}