{
  "type": "Feature",
  "properties": {
    "addr:full":"21715 Placeritos Blvd Newhall CA 91321",
    "addr:housenumber":"21715",
    "addr:postcode":"91321",
    "addr:street":"Placeritos Blvd",
    "iso:country":"US",
    "sg:address":"21715 Placeritos Blvd",
    "sg:city":"Newhall",
    "sg:classifiers":[
        {
            "category":"Building & Trades",
            "subcategory":"Landscaping Services",
            "type":"Services"
        }
    ],
    "sg:phone":"+1 661 259 6927",
    "sg:postcode":"91321",
    "sg:province":"CA",
    "wof:name":"Green Tree Landscape Mngm",
    "wof:placetype":"venue"
},
  "geometry": {"coordinates":[-118.517397,34.38423],"type":"Point"}
}