{
  "type": "Feature",
  "properties": {
    "addr:full":"8902 Avalon Boulevard Los Angeles CA 90003",
    "addr:housenumber":"8902",
    "addr:postcode":"90003",
    "addr:street":"Avalon Boulevard",
    "iso:country":"US",
    "sg:address":"8902 Avalon Boulevard",
    "sg:city":"Los Angeles",
    "sg:classifiers":[
        {
            "category":"Food & Beverages",
            "subcategory":"Groceries & Convenience Stores",
            "type":"Retail Goods"
        }
    ],
    "sg:phone":"+1 323 750 0190",
    "sg:postcode":"90003",
    "sg:province":"CA",
    "wof:name":"Hernandez Market",
    "wof:placetype":"venue"
},
  "geometry": {"coordinates":[-118.26526800000001,33.955573],"type":"Point"}
}