{
  "type": "Feature",
  "properties": {
    "addr:full":"257 Myrtle Rd Burlingame CA 94010",
    "addr:housenumber":"257",
    "addr:postcode":"94010",
    "addr:street":"Myrtle Rd",
    "iso:country":"US",
    "sg:address":"257 Myrtle Rd",
    "sg:city":"Burlingame",
    "sg:classifiers":[
        {
            "category":"Retail",
            "subcategory":"Auto Repair",
            "type":"Services"
        }
    ],
    "sg:phone":"+1 650 343 0257",
    "sg:postcode":"94010",
    "sg:province":"CA",
    "sg:tags":[
        "body",
        "shop",
        "painting",
        "repairing",
        "automobile"
    ],
    "wof:name":"All Makes Auto Body Shop",
    "wof:placetype":"venue"
},
  "geometry": {"coordinates":[-122.343002,37.5807],"type":"Point"}
}