{
  "type": "Feature",
  "properties": {
    "iso:country":"US",
    "sg:address":"606 Foothill Rd",
    "sg:city":"Beverly Hills",
    "sg:classifiers":[
        {
            "category":"Professional",
            "type":"Services"
        }
    ],
    "sg:phone":"+1 310 273 0438",
    "sg:postcode":"90210",
    "sg:province":"CA",
    "wof:name":"Malin Hearty Water LLC",
    "wof:placetype":"venue"
},
  "geometry": {"coordinates":[-118.402475,34.08131],"type":"Point"}
}