{
  "type": "Feature",
  "properties": {
    "addr:full":"3401 Mandela Pkwy Oakland CA 94620",
    "addr:housenumber":"3401",
    "addr:postcode":"94620",
    "addr:street":"Mandela Pkwy",
    "iso:country":"US",
    "sg:address":"3401 Mandela Pkwy",
    "sg:city":"Oakland",
    "sg:classifiers":[
        {
            "category":"Home & Garden",
            "subcategory":"Home Furnishings",
            "type":"Retail Goods"
        },
        {
            "category":"Home & Garden",
            "subcategory":"Building Materials",
            "type":"Retail Goods"
        }
    ],
    "sg:phone":"+1 510 652 6898",
    "sg:postcode":"94620",
    "sg:province":"CA",
    "sg:tags":[
        "bath",
        "kitchen",
        "supply"
    ],
    "sg:website":"thegraniteexpo.com",
    "wof:name":"Granite Expo",
    "wof:placetype":"venue"
},
  "geometry": {"coordinates":[-122.289129,37.822993],"type":"Point"}
}