{
  "type": "Feature",
  "properties": {
    "addr:full":"1360 Tomol St Carpinteria CA 93013",
    "addr:housenumber":"1360",
    "addr:postcode":"93013",
    "addr:street":"Tomol St",
    "iso:country":"US",
    "sg:address":"1360 Tomol St",
    "sg:city":"Carpinteria",
    "sg:classifiers":[
        {
            "category":"Building & Trades",
            "subcategory":"Construction",
            "type":"Services"
        }
    ],
    "sg:phone":"+1 805 684 5712",
    "sg:postcode":"93013",
    "sg:province":"CA",
    "wof:name":"Richard Martin Hotchkiss",
    "wof:placetype":"venue"
},
  "geometry": {"coordinates":[-119.518787,34.404086],"type":"Point"}
}