{
  "type": "Feature",
  "properties": {
    "addr:full":"3961 Sepulveda Blvd Ste 206 Culver City CA 90230",
    "addr:housenumber":"3961",
    "addr:postcode":"90230",
    "addr:street":"Sepulveda Blvd Ste 206",
    "iso:country":"US",
    "sg:address":"3961 Sepulveda Blvd Ste 206",
    "sg:city":"Culver City",
    "sg:classifiers":[
        {
            "category":"Professional",
            "subcategory":"Employment Agencies",
            "type":"Services"
        }
    ],
    "sg:phone":"+1 310 482 3777",
    "sg:postcode":"90230",
    "sg:province":"CA",
    "sg:website":"culvercityca.expresspros.com/",
    "wof:name":"Express Employment Professionals",
    "wof:placetype":"venue"
},
  "geometry": {"coordinates":[-118.414647,34.009664],"type":"Point"}
}