{
  "type": "Feature",
  "properties": {
    "addr:full":"1457 Lincoln Ave Calistoga CA 94515",
    "addr:housenumber":"1457",
    "addr:postcode":"94515",
    "addr:street":"Lincoln Ave",
    "iso:country":"US",
    "sg:address":"1457 Lincoln Ave",
    "sg:city":"Calistoga",
    "sg:classifiers":[
        {
            "category":"Restaurant",
            "type":"Food & Drink"
        }
    ],
    "sg:phone":"+1 707 942 5938",
    "sg:postcode":"94515",
    "sg:province":"CA",
    "sg:tags":[
        "new",
        "american"
    ],
    "sg:website":"www.jolerestaurant.com",
    "wof:name":"JoLe",
    "wof:placetype":"venue"
},
  "geometry": {"coordinates":[-122.57905700000001,38.579729],"type":"Point"}
}