{
  "type": "Feature",
  "properties": {
    "iso:country":"US",
    "sg:address":"201 S Anita Dr",
    "sg:city":"Orange",
    "sg:classifiers":[
        {
            "category":"Professional",
            "type":"Services"
        }
    ],
    "sg:phone":"+1 714 456 9114",
    "sg:postcode":"92868",
    "sg:province":"CA",
    "wof:name":"Superior Sourcing Inc",
    "wof:placetype":"venue"
},
  "geometry": {"coordinates":[-117.88112599999999,33.785472],"type":"Point"}
}