{
  "type": "Feature",
  "properties": {
    "iso:country":"US",
    "sg:address":"18042 Ventura Blvd",
    "sg:city":"Encino",
    "sg:classifiers":[
        {
            "category":"Organizations",
            "subcategory":"Religious Organization",
            "type":"Services"
        }
    ],
    "sg:phone":"+1 818 344 8789",
    "sg:postcode":"91316",
    "sg:province":"CA",
    "sg:tags":[
        "synagogue"
    ],
    "wof:name":"Iranian Synagogue",
    "wof:placetype":"venue"
},
  "geometry": {"coordinates":[-118.52627200000001,34.16498],"type":"Point"}
}