{
  "type": "Feature",
  "properties": {
    "addr:full":"3203 W March Ln Stockton CA 95219",
    "addr:housenumber":"3203",
    "addr:postcode":"95219",
    "addr:street":"W March Ln",
    "iso:country":"US",
    "sg:address":"3203 W March Ln",
    "sg:city":"Stockton",
    "sg:classifiers":[
        {
            "category":"Banks & Credit Unions",
            "subcategory":"Bank",
            "type":"Services"
        }
    ],
    "sg:phone":"+1 209 951 4980",
    "sg:postcode":"95219",
    "sg:province":"CA",
    "sg:tags":[
        "loan"
    ],
    "wof:name":"Rabo Agri Finance",
    "wof:placetype":"venue"
},
  "geometry": {"coordinates":[-121.355121,37.983864],"type":"Point"}
}