{
  "type": "Feature",
  "properties": {
    "iso:country":"US",
    "sg:address":"1711 Jenks Dr Ste 101",
    "sg:city":"Corona",
    "sg:classifiers":[
        {
            "category":"Shopping",
            "subcategory":"Hobbies, Toys, & Games",
            "type":"Retail Goods"
        }
    ],
    "sg:phone":"+1 951 735 2451",
    "sg:postcode":"92880",
    "sg:province":"CA",
    "sg:tags":[
        "coin",
        "supply"
    ],
    "wof:name":"Insert Coin Amusement",
    "wof:placetype":"venue"
},
  "geometry": {"coordinates":[-117.59690500000001,33.889916],"type":"Point"}
}