{
  "type": "Feature",
  "properties": {
    "iso:country":"US",
    "sg:address":"373 South Airport Blvd",
    "sg:city":"San Francisco",
    "sg:classifiers":[
        {
            "category":"Travel",
            "subcategory":"Hotels & Motels",
            "type":"Entertainment"
        },
        {
            "category":"Retail",
            "subcategory":"Event Space",
            "type":"Services"
        }
    ],
    "sg:phone":"+1 650 589 0600",
    "sg:postcode":"94080",
    "sg:province":"CA",
    "sg:tags":[
        "venue"
    ],
    "sg:website":"www.holidayinnexpress.com",
    "wof:name":"Holiday Inn Express Hotel & Suites in San Francisco Airport",
    "wof:placetype":"venue"
},
  "geometry": {"coordinates":[-122.40349999999999,37.64438],"type":"Point"}
}