{
  "type": "Feature",
  "properties": {
    "iso:country":"US",
    "sg:address":"524 Hartz Ave",
    "sg:city":"Danville",
    "sg:classifiers":[
        {
            "category":"Manufacturing",
            "subcategory":"Printing",
            "type":"Manufacturing & Wholesale Goods"
        }
    ],
    "sg:phone":"+1 925 837 4267",
    "sg:postcode":"94526",
    "sg:province":"CA",
    "sg:tags":[
        "newspaper"
    ],
    "sg:website":"www.contracosta.com",
    "wof:name":"San Ramon Valley Times",
    "wof:placetype":"venue"
},
  "geometry": {"coordinates":[-121.997395,37.820195],"type":"Point"}
}