{
  "type": "Feature",
  "properties": {
    "addr:full":"1026 Maple Ave Los Angeles CA 90015",
    "addr:housenumber":"1026",
    "addr:postcode":"90015",
    "addr:street":"Maple Ave",
    "iso:country":"US",
    "sg:address":"1026 Maple Ave",
    "sg:city":"Los Angeles",
    "sg:classifiers":[
        {
            "category":"Wholesale",
            "subcategory":"Apparel",
            "type":"Manufacturing & Wholesale Goods"
        }
    ],
    "sg:phone":"+1 213 748 6769",
    "sg:postcode":"90015",
    "sg:province":"CA",
    "sg:tags":[
        "clothing"
    ],
    "wof:name":"Patri Collection",
    "wof:placetype":"venue"
},
  "geometry": {"coordinates":[-118.25484299999999,34.03743],"type":"Point"}
}