{
  "type": "Feature",
  "properties": {
    "iso:country":"US",
    "sg:address":"1026 Maple Ave",
    "sg:city":"Los Angeles",
    "sg:classifiers":[
        {
            "category":"Wholesale",
            "subcategory":"Apparel",
            "type":"Manufacturing & Wholesale Goods"
        }
    ],
    "sg:phone":"+1 213 748 6769",
    "sg:postcode":"90015",
    "sg:province":"CA",
    "sg:tags":[
        "clothing"
    ],
    "wof:name":"Patri Collection",
    "wof:placetype":"venue"
},
  "geometry": {"coordinates":[-118.254843,34.03743],"type":"Point"}
}