{
  "type": "Feature",
  "properties": {
    "addr:full":"1740 Ferrari Dr Felton CA 95018",
    "addr:housenumber":"1740",
    "addr:postcode":"95018",
    "addr:street":"Ferrari Dr",
    "iso:country":"US",
    "sg:address":"1740 Ferrari Dr",
    "sg:city":"Felton",
    "sg:classifiers":[
        {
            "category":"Building & Trades",
            "subcategory":"Construction",
            "type":"Services"
        }
    ],
    "sg:phone":"+1 831 335 4015",
    "sg:postcode":"95018",
    "sg:province":"CA",
    "sg:tags":[
        "nonresidential"
    ],
    "wof:name":"R F Amos Constructi",
    "wof:placetype":"venue"
},
  "geometry": {"coordinates":[-122.078433,37.029879],"type":"Point"}
}