{
  "type": "Feature",
  "properties": {
    "iso:country":"US",
    "sg:address":"17307 Franklin Rd",
    "sg:city":"Fort Bragg",
    "sg:classifiers":[
        {
            "category":"Utilities",
            "subcategory":"Telephone",
            "type":"Services"
        }
    ],
    "sg:phone":"+1 707 961 6057",
    "sg:postcode":"95437",
    "sg:province":"CA",
    "sg:tags":[
        "communications"
    ],
    "wof:name":"Catherine Bremer",
    "wof:placetype":"venue"
},
  "geometry": {"coordinates":[-123.771278,39.392903],"type":"Point"}
}