{
  "type": "Feature",
  "properties": {
    "addr:full":"141 W 60th St Los Angeles CA 90003",
    "addr:housenumber":"141",
    "addr:postcode":"90003",
    "addr:street":"W 60Th St",
    "iso:country":"US",
    "sg:address":"141 W 60th St",
    "sg:city":"Los Angeles",
    "sg:classifiers":[
        {
            "category":"Shopping",
            "subcategory":"Used Merchandise",
            "type":"Retail Goods"
        }
    ],
    "sg:phone":"+1 323 758 1506",
    "sg:postcode":"90003",
    "sg:province":"CA",
    "wof:name":"Ramirez Services",
    "wof:placetype":"venue"
},
  "geometry": {"coordinates":[-118.27746500000001,33.985196],"type":"Point"}
}