{
  "type": "Feature",
  "properties": {
    "addr:full":"15155 Califa St Van Nuys CA 91411",
    "addr:housenumber":"15155",
    "addr:postcode":"91411",
    "addr:street":"Califa St",
    "iso:country":"US",
    "sg:address":"15155 Califa St",
    "sg:city":"Van Nuys",
    "sg:classifiers":[
        {
            "category":"Building & Trades",
            "subcategory":"Construction",
            "type":"Services"
        }
    ],
    "sg:phone":"+1 818 779 7966",
    "sg:postcode":"91411",
    "sg:province":"CA",
    "sg:tags":[
        "maker",
        "cabinet"
    ],
    "wof:name":"Universal Craftsman Inc",
    "wof:placetype":"venue"
},
  "geometry": {"coordinates":[-118.463724,34.177625],"type":"Point"}
}