{
  "type": "Feature",
  "properties": {
    "addr:full":"36 W Gabilan St Salinas CA 93901",
    "addr:housenumber":"36",
    "addr:postcode":"93901",
    "addr:street":"W Gabilan St",
    "iso:country":"US",
    "sg:address":"36 W Gabilan St",
    "sg:city":"Salinas",
    "sg:phone":"+1 831 424 7553",
    "sg:postcode":"93901",
    "sg:province":"CA",
    "wof:name":"Kokoro Sushi",
    "wof:placetype":"venue"
},
  "geometry": {"coordinates":[-121.65696699999999,36.675383],"type":"Point"}
}