{
  "type": "Feature",
  "properties": {
    "iso:country":"US",
    "sg:address":"108 E 7th St",
    "sg:city":"Hanford",
    "sg:classifiers":[
        {
            "category":"Insurance",
            "subcategory":"Hazard Insurance",
            "type":"Services"
        }
    ],
    "sg:phone":"+1 559 587 9007",
    "sg:postcode":"93230",
    "sg:province":"CA",
    "sg:tags":[
        "commercial",
        "business"
    ],
    "wof:name":"Golden State Crop & Insurance Services",
    "wof:placetype":"venue"
},
  "geometry": {"coordinates":[-119.645552,36.32665],"type":"Point"}
}