{
  "type": "Feature",
  "properties": {
    "addr:full":"777 Campus Commons Rd Sacramento CA 95825",
    "addr:housenumber":"777",
    "addr:postcode":"95825",
    "addr:street":"Campus Commons Rd",
    "iso:country":"US",
    "sg:address":"777 Campus Commons Rd",
    "sg:city":"Sacramento",
    "sg:classifiers":[
        {
            "category":"Professional",
            "subcategory":"Computer Services",
            "type":"Services"
        }
    ],
    "sg:phone":"+1 916 565 7609",
    "sg:postcode":"95825",
    "sg:province":"CA",
    "sg:tags":[
        "consultant",
        "designer"
    ],
    "wof:name":"Setka Information Technology",
    "wof:placetype":"venue"
},
  "geometry": {"coordinates":[-121.415553,38.569148],"type":"Point"}
}