{
  "type": "Feature",
  "properties": {
    "iso:country":"US",
    "sg:address":"2716 el Pasado Dr",
    "sg:city":"Modesto",
    "sg:classifiers":[
        {
            "category":"Shopping",
            "subcategory":"Gifts & Souvenirs",
            "type":"Retail Goods"
        }
    ],
    "sg:phone":"+1 209 572 1470",
    "sg:postcode":"95354",
    "sg:province":"CA",
    "sg:tags":[
        "party",
        "supply"
    ],
    "wof:name":"Tweedledeedumpartyco",
    "wof:placetype":"venue"
},
  "geometry": {"coordinates":[-120.942876,37.644997],"type":"Point"}
}