{
  "type": "Feature",
  "properties": {
    "addr:full":"408 Bauchet St. Los Angeles CA 90012",
    "addr:housenumber":"408",
    "addr:postcode":"90012",
    "addr:street":"Bauchet St.",
    "iso:country":"US",
    "sg:address":"408 Bauchet St.",
    "sg:city":"Los Angeles",
    "sg:classifiers":[
        {
            "category":"Recreation",
            "type":"Entertainment"
        }
    ],
    "sg:phone":"+1 323 708 3633",
    "sg:postcode":"90012",
    "sg:province":"CA",
    "sg:tags":[
        "active",
        "life"
    ],
    "sg:website":"QI-X.com",
    "wof:name":"QI-X",
    "wof:placetype":"venue"
},
  "geometry": {"coordinates":[-118.23278999999999,34.058754],"type":"Point"}
}