{
  "type": "Feature",
  "properties": {
    "addr:full":"1132 Hyperion Ave Los Angeles CA 90029",
    "addr:housenumber":"1132",
    "addr:postcode":"90029",
    "addr:street":"Hyperion Ave",
    "iso:country":"US",
    "sg:address":"1132 Hyperion Ave",
    "sg:city":"Los Angeles",
    "sg:classifiers":[
        {
            "category":"Professional",
            "type":"Services"
        }
    ],
    "sg:phone":"+1 323 664 4423",
    "sg:postcode":"90029",
    "sg:province":"CA",
    "sg:tags":[
        "information",
        "bureau"
    ],
    "sg:website":"www.timelyinformation.com",
    "wof:name":"Timely Info",
    "wof:placetype":"venue"
},
  "geometry": {"coordinates":[-118.27864,34.093038],"type":"Point"}
}