{
  "type": "Feature",
  "properties": {
    "iso:country":"US",
    "sg:address":"5637 Norman Way",
    "sg:city":"Sacramento",
    "sg:classifiers":[
        {
            "category":"Building & Trades",
            "subcategory":"Plumbing",
            "type":"Services"
        }
    ],
    "sg:phone":"+1 916 392 8498",
    "sg:postcode":"95822",
    "sg:province":"CA",
    "sg:tags":[
        "contractor"
    ],
    "wof:name":"Handyman Plus Hvac",
    "wof:placetype":"venue"
},
  "geometry": {"coordinates":[-121.487501,38.524121],"type":"Point"}
}