{
  "type": "Feature",
  "properties": {
    "addr:full":"1041 E Main St Santa Maria CA 93454",
    "addr:housenumber":"1041",
    "addr:postcode":"93454",
    "addr:street":"E Main St",
    "iso:country":"US",
    "sg:address":"1041 E Main St",
    "sg:city":"Santa Maria",
    "sg:classifiers":[
        {
            "category":"Restaurant",
            "type":"Food & Drink"
        }
    ],
    "sg:menulink":"http://www.allmenus.com/ca/santa-maria-valley/178429-jack-in-the-box/menu/",
    "sg:phone":"+1 805 346 1190",
    "sg:postcode":"93454",
    "sg:province":"CA",
    "sg:tags":[
        "burger",
        "american"
    ],
    "wof:name":"Jack in the Box",
    "wof:placetype":"venue"
},
  "geometry": {"coordinates":[-120.41833,34.953543],"type":"Point"}
}