{
  "type": "Feature",
  "properties": {
    "addr:full":"13100 Hubbard St Sylmar CA 91342",
    "addr:housenumber":"13100",
    "addr:postcode":"91342",
    "addr:street":"Hubbard St",
    "iso:country":"US",
    "sg:address":"13100 Hubbard St",
    "sg:city":"Sylmar",
    "sg:classifiers":[
        {
            "category":"Social Services",
            "subcategory":"Child Care",
            "type":"Services"
        }
    ],
    "sg:phone":"+1 818 362 8140",
    "sg:postcode":"91342",
    "sg:province":"CA",
    "wof:name":"Latin American Civic",
    "wof:placetype":"venue"
},
  "geometry": {"coordinates":[-118.419815,34.316753],"type":"Point"}
}