{
  "type": "Feature",
  "properties": {
    "iso:country":"US",
    "sg:address":"2099 Bluejacket Way",
    "sg:city":"San Jose",
    "sg:classifiers":[
        {
            "category":"Utilities",
            "type":"Services"
        }
    ],
    "sg:phone":"+1 408 258 1934",
    "sg:postcode":"95133",
    "sg:province":"CA",
    "sg:tags":[
        "provider",
        "internet"
    ],
    "wof:name":"Internet Tv",
    "wof:placetype":"venue"
},
  "geometry": {"coordinates":[-121.864512,37.378601],"type":"Point"}
}