{
  "type": "Feature",
  "properties": {
    "addr:full":"3800 Watt Ave Sacramento CA 95821",
    "addr:housenumber":"3800",
    "addr:postcode":"95821",
    "addr:street":"Watt Ave",
    "iso:country":"US",
    "sg:address":"3800 Watt Ave",
    "sg:city":"Sacramento",
    "sg:classifiers":[
        {
            "category":"Banks & Credit Unions",
            "subcategory":"Bank",
            "type":"Services"
        }
    ],
    "sg:phone":"+1 916 483 5975",
    "sg:postcode":"95821",
    "sg:province":"CA",
    "sg:tags":[
        "loan",
        "real estate"
    ],
    "wof:name":"Gateway Bank",
    "wof:placetype":"venue"
},
  "geometry": {"coordinates":[-121.382931,38.635101],"type":"Point"}
}