{
  "type": "Feature",
  "properties": {
    "iso:country":"US",
    "sg:address":"17615 Castleton St",
    "sg:city":"Rowland Heights",
    "sg:classifiers":[
        {
            "category":"Restaurant",
            "type":"Food & Drink"
        }
    ],
    "sg:menulink":"http://www.allmenus.com/ca/east-san-gabriel-valley/233724-black-angus-steakhouse/menu/",
    "sg:phone":"+1 626 965 3488",
    "sg:postcode":"91748",
    "sg:province":"CA",
    "sg:tags":[
        "american",
        "steakhouse"
    ],
    "wof:name":"Black Angus Steakhouse",
    "wof:placetype":"venue"
},
  "geometry": {"coordinates":[-117.919202,33.993879],"type":"Point"}
}