{
  "type": "Feature",
  "properties": {
    "addr:full":"707 N La Brea Avenue Los Angeles CA 90038",
    "addr:housenumber":"707",
    "addr:postcode":"90038",
    "addr:street":"N La Brea Avenue",
    "iso:country":"US",
    "sg:address":"707 N La Brea Avenue",
    "sg:city":"Los Angeles",
    "sg:classifiers":[
        {
            "category":"Shopping",
            "subcategory":"Florist",
            "type":"Retail Goods"
        }
    ],
    "sg:phone":"+1 323 938 3911",
    "sg:postcode":"90038",
    "sg:province":"CA",
    "sg:website":"www.1800conroys.com",
    "wof:name":"Ftd Member Florists",
    "wof:placetype":"venue"
},
  "geometry": {"coordinates":[-118.34418100000001,34.083631],"type":"Point"}
}