{
  "type": "Feature",
  "properties": {
    "iso:country":"US",
    "sg:address":"1138 N 8th St",
    "sg:city":"Banning",
    "sg:classifiers":[
        {
            "category":"Personal",
            "subcategory":"Beauty Salon",
            "type":"Services"
        }
    ],
    "sg:phone":"+1 909 981 9898",
    "sg:postcode":"92220",
    "sg:province":"CA",
    "wof:name":"Beautiful Image Salon",
    "wof:placetype":"venue"
},
  "geometry": {"coordinates":[-116.885473,33.935636],"type":"Point"}
}