{
  "type": "Feature",
  "properties": {
    "addr:full":"4955 Lamia Way Oceanside CA 92056",
    "addr:housenumber":"4955",
    "addr:postcode":"92056",
    "addr:street":"Lamia Way",
    "iso:country":"US",
    "sg:address":"4955 Lamia Way",
    "sg:city":"Oceanside",
    "sg:classifiers":[
        {
            "category":"Professional",
            "subcategory":"Management & Consulting",
            "type":"Services"
        }
    ],
    "sg:phone":"+1 760 631 4460",
    "sg:postcode":"92056",
    "sg:province":"CA",
    "sg:tags":[
        "consultant",
        "business"
    ],
    "wof:name":"Robert A Field Co Inc",
    "wof:placetype":"venue"
},
  "geometry": {"coordinates":[-117.265165,33.156618],"type":"Point"}
}