{
  "type": "Feature",
  "properties": {
    "addr:full":"622 Mission St South Pasadena CA 91030",
    "addr:housenumber":"622",
    "addr:postcode":"91030",
    "addr:street":"Mission St",
    "iso:country":"US",
    "sg:address":"622 Mission St",
    "sg:city":"South Pasadena",
    "sg:classifiers":[
        {
            "category":"Personal",
            "subcategory":"Beauty Salon",
            "type":"Services"
        },
        {
            "category":"Personal",
            "subcategory":"Skin Care",
            "type":"Services"
        },
        {
            "category":"Personal",
            "subcategory":"Nail Salon",
            "type":"Services"
        }
    ],
    "sg:phone":"+1 626 799 0118",
    "sg:postcode":"91030",
    "sg:province":"CA",
    "sg:tags":[
        "hair"
    ],
    "sg:website":"www.salondumei.com",
    "wof:name":"Salon du Mei",
    "wof:placetype":"venue"
},
  "geometry": {"coordinates":[-118.16255200000001,34.115735],"type":"Point"}
}