{
  "type": "Feature",
  "properties": {
    "addr:full":"Lee, Lawless & Blyth 11 Embarcadero W Ste 145 Oakland CA 94607",
    "addr:housenumber":"11",
    "addr:postcode":"94607",
    "addr:street":"Embarcadero W Ste 145",
    "iso:country":"US",
    "sg:address":"Lee, Lawless & Blyth 11 Embarcadero W Ste 145",
    "sg:city":"Oakland",
    "sg:classifiers":[
        {
            "category":"Professional",
            "subcategory":"Lawyer & Legal Services",
            "type":"Services"
        }
    ],
    "sg:phone":"+1 510 272 0200",
    "sg:postcode":"94607",
    "sg:province":"CA",
    "sg:website":"www.leelawlessblyth.com",
    "wof:name":"Stan D. Blyth",
    "wof:placetype":"venue"
},
  "geometry": {"coordinates":[-122.26908299999999,37.791078],"type":"Point"}
}