{
  "type": "Feature",
  "properties": {
    "addr:full":"514 Bryant St Palo Alto CA 94301",
    "addr:housenumber":"514",
    "addr:postcode":"94301",
    "addr:street":"Bryant St",
    "iso:country":"US",
    "sg:address":"514 Bryant St",
    "sg:city":"Palo Alto",
    "sg:classifiers":[
        {
            "category":"Professional",
            "type":"Services"
        }
    ],
    "sg:phone":"+1 650 321 6314",
    "sg:postcode":"94301",
    "sg:province":"CA",
    "sg:tags":[
        "establishment"
    ],
    "wof:name":"Ragnarok Capital",
    "wof:placetype":"venue"
},
  "geometry": {"coordinates":[-122.160512,37.445138],"type":"Point"}
}