{
  "type": "Feature",
  "properties": {
    "addr:full":"314 Frankfort St Daly City CA 94014",
    "addr:housenumber":"314",
    "addr:postcode":"94014",
    "addr:street":"Frankfort St",
    "iso:country":"US",
    "sg:address":"314 Frankfort St",
    "sg:city":"Daly City",
    "sg:classifiers":[
        {
            "category":"Retail",
            "subcategory":"Portrait Studio",
            "type":"Services"
        }
    ],
    "sg:phone":"+1 415 587 7921",
    "sg:postcode":"94014",
    "sg:province":"CA",
    "sg:tags":[
        "photographer"
    ],
    "wof:name":"J P Photography",
    "wof:placetype":"venue"
},
  "geometry": {"coordinates":[-122.449776,37.704569],"type":"Point"}
}