{
  "type": "Feature",
  "properties": {
    "addr:full":"8301 Folsom Blvd Ste B Sacramento CA 95826",
    "addr:housenumber":"8301",
    "addr:postcode":"95826",
    "addr:street":"Folsom Blvd Ste B",
    "iso:country":"US",
    "sg:address":"8301 Folsom Blvd Ste B",
    "sg:city":"Sacramento",
    "sg:classifiers":[
        {
            "category":"Professional",
            "subcategory":"Management & Consulting",
            "type":"Services"
        },
        {
            "category":"Professional",
            "subcategory":"Business Services",
            "type":"Services"
        }
    ],
    "sg:phone":"+1 916 381 1801",
    "sg:postcode":"95826",
    "sg:province":"CA",
    "sg:tags":[
        "consultant",
        "coach"
    ],
    "wof:name":"Transtec Consulting",
    "wof:placetype":"venue"
},
  "geometry": {"coordinates":[-121.39980300000001,38.547081],"type":"Point"}
}