{
  "type": "Feature",
  "properties": {
    "addr:full":"372 Front St Buttonwillow CA 93215",
    "addr:housenumber":"372",
    "addr:postcode":"93215",
    "addr:street":"Front St",
    "iso:country":"US",
    "sg:address":"372 Front St",
    "sg:city":"Buttonwillow",
    "sg:classifiers":[
        {
            "category":"Personal",
            "subcategory":"Beauty Salon",
            "type":"Services"
        }
    ],
    "sg:phone":"+1 661 764 5777",
    "sg:postcode":"93215",
    "sg:province":"CA",
    "wof:name":"Cindy's Beauty Salon",
    "wof:placetype":"venue"
},
  "geometry": {"coordinates":[-119.243217,35.756538],"type":"Point"}
}