{
  "type": "Feature",
  "properties": {
    "iso:country":"US",
    "sg:address":"475 Industrial Way",
    "sg:city":"Benicia",
    "sg:classifiers":[
        {
            "category":"Manufacturing",
            "subcategory":"Electronics",
            "type":"Manufacturing & Wholesale Goods"
        }
    ],
    "sg:phone":"+1 707 748 5800",
    "sg:postcode":"94510",
    "sg:province":"CA",
    "sg:tags":[
        "equipment",
        "electronic",
        "supply"
    ],
    "sg:website":"www.teamindustrialservices.com",
    "wof:name":"COOPERHEAT-Mqs Inc",
    "wof:placetype":"venue"
},
  "geometry": {"coordinates":[-122.132068,38.073947],"type":"Point"}
}