{
  "type": "Feature",
  "properties": {
    "addr:full":"12631 Imperial Hwy Santa Fe Springs CA 90670",
    "addr:housenumber":"12631",
    "addr:postcode":"90670",
    "addr:street":"Imperial Hwy",
    "iso:country":"US",
    "sg:address":"12631 Imperial Hwy",
    "sg:city":"Santa Fe Springs",
    "sg:classifiers":[
        {
            "category":"Wholesale",
            "subcategory":"Durable Goods & Equipment",
            "type":"Manufacturing & Wholesale Goods"
        }
    ],
    "sg:phone":"+1 562 868 6970",
    "sg:postcode":"90670",
    "sg:province":"CA",
    "sg:tags":[
        "exporter"
    ],
    "sg:website":"www.songlincorp.com",
    "wof:name":"Songlin International Corp",
    "wof:placetype":"venue"
},
  "geometry": {"coordinates":[-118.060416,33.917094],"type":"Point"}
}