{
  "type": "Feature",
  "properties": {
    "iso:country":"US",
    "sg:address":"74361 Highway 111",
    "sg:city":"Palm Desert",
    "sg:classifiers":[
        {
            "category":"Building & Trades",
            "subcategory":"Construction",
            "type":"Services"
        }
    ],
    "sg:phone":"+1 760 340 4216",
    "sg:postcode":"92260",
    "sg:province":"CA",
    "sg:tags":[
        "contractor"
    ],
    "wof:name":"Par Development",
    "wof:placetype":"venue"
},
  "geometry": {"coordinates":[-116.366997,33.721199],"type":"Point"}
}