{
  "type": "Feature",
  "properties": {
    "iso:country":"US",
    "sg:address":"827 E Colorado Blvd",
    "sg:city":"Pasadena",
    "sg:classifiers":[
        {
            "category":"Retail",
            "subcategory":"Laundry & Dry Cleaning",
            "type":"Services"
        }
    ],
    "sg:phone":"+1 626 793 3919",
    "sg:postcode":"91101",
    "sg:province":"CA",
    "sg:website":"www.roundtheclockcleaners.com",
    "wof:name":"Around the Clock Cleaners Inc",
    "wof:placetype":"venue"
},
  "geometry": {"coordinates":[-118.133003,34.146],"type":"Point"}
}