{
  "type": "Feature",
  "properties": {
    "addr:full":"1403 Retherford St Tulare CA 93274",
    "addr:housenumber":"1403",
    "addr:postcode":"93274",
    "addr:street":"Retherford St",
    "iso:country":"US",
    "sg:address":"1403 Retherford St",
    "sg:city":"Tulare",
    "sg:classifiers":[
        {
            "category":"Bakery",
            "type":"Food & Drink"
        }
    ],
    "sg:menulink":"http://www.allmenus.com/ca/tulare/219786-auntie-annes-pretzels/menu/",
    "sg:phone":"+1 559 684 9408",
    "sg:postcode":"93274",
    "sg:province":"CA",
    "sg:tags":[
        "american",
        "pastry"
    ],
    "wof:name":"Auntie Anne's Pretzels",
    "wof:placetype":"venue"
},
  "geometry": {"coordinates":[-119.335396,36.230646],"type":"Point"}
}