{
  "type": "Feature",
  "properties": {
    "addr:full":"203 N Ash St Escondido CA 92027",
    "addr:housenumber":"203",
    "addr:postcode":"92027",
    "addr:street":"N Ash St",
    "iso:country":"US",
    "sg:address":"203 N Ash St",
    "sg:city":"Escondido",
    "sg:classifiers":[
        {
            "category":"Health Services",
            "subcategory":"Doctor",
            "type":"Services"
        }
    ],
    "sg:phone":"+1 760 480 8883",
    "sg:postcode":"92027",
    "sg:province":"CA",
    "sg:tags":[
        "dentist"
    ],
    "wof:name":"Ash Dental Arts",
    "wof:placetype":"venue"
},
  "geometry": {"coordinates":[-117.066238,33.128629],"type":"Point"}
}