{
  "type": "Feature",
  "properties": {
    "iso:country":"US",
    "sg:address":"541 N Azusa Ave",
    "sg:city":"La Puente",
    "sg:classifiers":[
        {
            "category":"Restaurant",
            "type":"Food & Drink"
        }
    ],
    "sg:phone":"+1 626 581 7141",
    "sg:postcode":"91744",
    "sg:province":"CA",
    "wof:name":"Mi Jacalito Restaurant",
    "wof:placetype":"venue"
},
  "geometry": {"coordinates":[-117.91663800000001,34.027312],"type":"Point"}
}