{
  "type": "Feature",
  "properties": {
    "iso:country":"US",
    "sg:address":"455 W Broadway",
    "sg:city":"Glendale",
    "sg:classifiers":[
        {
            "category":"Retail",
            "subcategory":"Laundry & Dry Cleaning",
            "type":"Services"
        }
    ],
    "sg:phone":"+1 818 543 0994",
    "sg:postcode":"91204",
    "sg:province":"CA",
    "sg:tags":[
        "cleaners"
    ],
    "wof:name":"Tiffany's Alteration & Dry",
    "wof:placetype":"venue"
},
  "geometry": {"coordinates":[-118.262665,34.146897],"type":"Point"}
}