{
  "type": "Feature",
  "properties": {
    "addr:full":"14640 San Bernardino Ave Fontana CA 92335",
    "addr:housenumber":"14640",
    "addr:postcode":"92335",
    "addr:street":"San Bernardino Ave",
    "iso:country":"US",
    "sg:address":"14640 San Bernardino Ave",
    "sg:city":"Fontana",
    "sg:classifiers":[
        {
            "category":"Professional",
            "subcategory":"Engineering",
            "type":"Services"
        }
    ],
    "sg:phone":"+1 909 427 9737",
    "sg:postcode":"92335",
    "sg:province":"CA",
    "sg:tags":[
        "engineer"
    ],
    "wof:name":"Icon Metal Works Inc",
    "wof:placetype":"venue"
},
  "geometry": {"coordinates":[-117.48713100000001,34.07748],"type":"Point"}
}