{
  "type": "Feature",
  "properties": {
    "iso:country":"US",
    "sg:address":"2021 S Archibald Ave",
    "sg:city":"Ontario",
    "sg:classifiers":[
        {
            "category":"Wholesale",
            "subcategory":"Electrical",
            "type":"Manufacturing & Wholesale Goods"
        }
    ],
    "sg:phone":"+1 909 923 1925",
    "sg:postcode":"91761",
    "sg:province":"CA",
    "sg:tags":[
        "equipment",
        "electronic",
        "supply"
    ],
    "sg:website":"www.lge.com",
    "wof:name":"L G ELECTRONICS Ontario Iqc",
    "wof:placetype":"venue"
},
  "geometry": {"coordinates":[-117.593131,34.03454],"type":"Point"}
}