{
  "type": "Feature",
  "properties": {
    "iso:country":"US",
    "sg:address":"22111 Windward Way",
    "sg:city":"Lake Forest",
    "sg:classifiers":[
        {
            "category":"Professional",
            "subcategory":"Business Services",
            "type":"Services"
        }
    ],
    "sg:phone":"+1 949 305 0862",
    "sg:postcode":"92630",
    "sg:province":"CA",
    "wof:name":"Redtoblack",
    "wof:placetype":"venue"
},
  "geometry": {"coordinates":[-117.69653599999999,33.641703],"type":"Point"}
}