{
  "type": "Feature",
  "properties": {
    "iso:country":"US",
    "sg:address":"301 E Colorado Blvd",
    "sg:city":"Pasadena",
    "sg:classifiers":[
        {
            "category":"Professional",
            "subcategory":"Accounting & Tax Preparation",
            "type":"Services"
        }
    ],
    "sg:phone":"+1 626 449 6262",
    "sg:postcode":"91106",
    "sg:province":"CA",
    "sg:tags":[
        "accountant"
    ],
    "wof:name":"Apodaca & Co",
    "wof:placetype":"venue"
},
  "geometry": {"coordinates":[-118.145093,34.145895],"type":"Point"}
}