{
  "type": "Feature",
  "properties": {
    "iso:country":"US",
    "sg:address":"2100 N Rancho Ave",
    "sg:city":"Colton",
    "sg:classifiers":[
        {
            "category":"Food & Beverages",
            "subcategory":"Bakery",
            "type":"Retail Goods"
        }
    ],
    "sg:phone":"+1 909 885 0842",
    "sg:postcode":"92324",
    "sg:province":"CA",
    "sg:tags":[
        "product",
        "doughnut",
        "mfg"
    ],
    "wof:name":"J & J Donut and Ice Cream",
    "wof:placetype":"venue"
},
  "geometry": {"coordinates":[-117.333584,34.093264],"type":"Point"}
}