{
  "type": "Feature",
  "properties": {
    "iso:country":"US",
    "sg:address":"160 Newport Center Drive Suite 112",
    "sg:city":"Newport Beach",
    "sg:classifiers":[
        {
            "category":"Insurance",
            "subcategory":"Hazard Insurance",
            "type":"Services"
        }
    ],
    "sg:phone":"+1 949 720 8115",
    "sg:postcode":"92660",
    "sg:province":"CA",
    "wof:name":"McM Financial Group",
    "wof:placetype":"venue"
},
  "geometry": {"coordinates":[-117.876015,33.612565],"type":"Point"}
}