{
  "type": "Feature",
  "properties": {
    "iso:country":"US",
    "sg:address":"6249 Langdon Ave",
    "sg:city":"Van Nuys",
    "sg:classifiers":[
        {
            "category":"Wholesale",
            "subcategory":"Electrical",
            "type":"Manufacturing & Wholesale Goods"
        },
        {
            "category":"Wholesale",
            "subcategory":"Chemicals & Plastics",
            "type":"Manufacturing & Wholesale Goods"
        }
    ],
    "sg:phone":"+1 818 782 6541",
    "sg:postcode":"91411",
    "sg:province":"CA",
    "sg:tags":[
        "distribute",
        "produce",
        "disc",
        "video",
        "tape",
        "film"
    ],
    "wof:name":"Leos Films",
    "wof:placetype":"venue"
},
  "geometry": {"coordinates":[-118.468506,34.18559],"type":"Point"}
}