{
  "type": "Feature",
  "properties": {
    "addr:full":"805 Via Alondra Camarillo CA 93012",
    "addr:housenumber":"805",
    "addr:postcode":"93012",
    "addr:street":"Via Alondra",
    "iso:country":"US",
    "sg:address":"805 Via Alondra",
    "sg:city":"Camarillo",
    "sg:classifiers":[
        {
            "category":"Autos & Motor Vehicles",
            "subcategory":"Auto Supplies",
            "type":"Retail Goods"
        }
    ],
    "sg:phone":"+1 805 484 5613",
    "sg:postcode":"93012",
    "sg:province":"CA",
    "sg:tags":[
        "tire"
    ],
    "wof:name":"Big Brand Tires",
    "wof:placetype":"venue"
},
  "geometry": {"coordinates":[-119.022567,34.226489],"type":"Point"}
}