{
  "type": "Feature",
  "properties": {
    "iso:country":"US",
    "sg:address":"510 Greenville Rd",
    "sg:city":"Livermore",
    "sg:classifiers":[
        {
            "category":"Building & Trades",
            "subcategory":"Plumbing",
            "type":"Services"
        }
    ],
    "sg:phone":"+1 925 447 1500",
    "sg:postcode":"94550",
    "sg:province":"CA",
    "sg:tags":[
        "conditioning",
        "air",
        "system",
        "contractor"
    ],
    "wof:name":"Analysystems",
    "wof:placetype":"venue"
},
  "geometry": {"coordinates":[-121.696944,37.70314],"type":"Point"}
}