{
  "type": "Feature",
  "properties": {
    "addr:full":"7290 Santa Barbara Ct Fontana CA 92336",
    "addr:housenumber":"7290",
    "addr:postcode":"92336",
    "addr:street":"Santa Barbara Ct",
    "iso:country":"US",
    "sg:address":"7290 Santa Barbara Ct",
    "sg:city":"Fontana",
    "sg:classifiers":[
        {
            "category":"Building & Trades",
            "subcategory":"Construction",
            "type":"Services"
        }
    ],
    "sg:phone":"+1 909 904 3807",
    "sg:postcode":"92336",
    "sg:province":"CA",
    "sg:tags":[
        "house"
    ],
    "wof:name":"American International Homes",
    "wof:placetype":"venue"
},
  "geometry": {"coordinates":[-117.507452,34.121502],"type":"Point"}
}