{
  "type": "Feature",
  "properties": {
    "addr:full":"564 Market St San Francisco CA 94104",
    "addr:housenumber":"564",
    "addr:postcode":"94104",
    "addr:street":"Market St",
    "iso:country":"US",
    "sg:address":"564 Market St",
    "sg:city":"San Francisco",
    "sg:classifiers":[
        {
            "category":"Real Estate",
            "subcategory":"Real Estate Operator",
            "type":"Services"
        },
        {
            "category":"Building & Trades",
            "subcategory":"Construction",
            "type":"Services"
        }
    ],
    "sg:phone":"+1 415 834 9110",
    "sg:postcode":"94104",
    "sg:province":"CA",
    "sg:tags":[
        "professional",
        "industrial",
        "park"
    ],
    "wof:name":"Chancery Building",
    "wof:placetype":"venue"
},
  "geometry": {"coordinates":[-122.40107399999999,37.789722],"type":"Point"}
}