{
  "type": "Feature",
  "properties": {
    "addr:full":"1014 W Beverly Blvd Montebello CA 90640",
    "addr:housenumber":"1014",
    "addr:postcode":"90640",
    "addr:street":"W Beverly Blvd",
    "iso:country":"US",
    "sg:address":"1014 W Beverly Blvd",
    "sg:city":"Montebello",
    "sg:classifiers":[
        {
            "category":"Health Services",
            "subcategory":"Doctor",
            "type":"Services"
        }
    ],
    "sg:phone":"+1 323 725 9999",
    "sg:postcode":"90640",
    "sg:province":"CA",
    "sg:tags":[
        "dentist"
    ],
    "wof:name":"Dino C Hernandez Inc",
    "wof:placetype":"venue"
},
  "geometry": {"coordinates":[-118.109572,34.017956],"type":"Point"}
}