{
  "type": "Feature",
  "properties": {
    "addr:full":"2045 W Rosecrans Ave Gardena CA 90249",
    "addr:housenumber":"2045",
    "addr:postcode":"90249",
    "addr:street":"W Rosecrans Ave",
    "iso:country":"US",
    "sg:address":"2045 W Rosecrans Ave",
    "sg:city":"Gardena",
    "sg:classifiers":[
        {
            "category":"Retail",
            "subcategory":"Storage",
            "type":"Services"
        }
    ],
    "sg:phone":"+1 310 225 2577",
    "sg:postcode":"90249",
    "sg:province":"CA",
    "sg:tags":[
        "self"
    ],
    "sg:website":"www.safkeep.com/self_storage/Gar...",
    "wof:name":"Saf Keep Storage",
    "wof:placetype":"venue"
},
  "geometry": {"coordinates":[-118.31500200000001,33.901798],"type":"Point"}
}