{
  "type": "Feature",
  "properties": {
    "addr:full":"12400 Perris Blvd Moreno Valley CA 92557",
    "addr:housenumber":"12400",
    "addr:postcode":"92557",
    "addr:street":"Perris Blvd",
    "iso:country":"US",
    "sg:address":"12400 Perris Blvd",
    "sg:city":"Moreno Valley",
    "sg:classifiers":[
        {
            "category":"Restaurant",
            "type":"Food & Drink"
        }
    ],
    "sg:phone":"+1 951 243 5507",
    "sg:postcode":"92557",
    "sg:province":"CA",
    "wof:name":"Don's Golden Chicken & Fish",
    "wof:placetype":"venue"
},
  "geometry": {"coordinates":[-117.226375,33.9398],"type":"Point"}
}