{
  "type": "Feature",
  "properties": {
    "iso:country":"US",
    "sg:address":"21311 Hawthorne Blvd Ste 325",
    "sg:city":"Torrance",
    "sg:classifiers":[
        {
            "category":"Organizations",
            "subcategory":"Non-profit Organization",
            "type":"Services"
        }
    ],
    "sg:phone":"+1 866 933 2181",
    "sg:postcode":"90503",
    "sg:province":"CA",
    "sg:tags":[
        "service/non-profit",
        "community"
    ],
    "sg:website":"alliancehumanoc.com",
    "wof:name":"Alliance Health & Human Services",
    "wof:placetype":"venue"
},
  "geometry": {"coordinates":[-118.35511200000001,33.835506],"type":"Point"}
}