{
  "type": "Feature",
  "properties": {
    "addr:full":"635 San Anselmo Ave San Anselmo CA 94960",
    "addr:housenumber":"635",
    "addr:postcode":"94960",
    "addr:street":"San Anselmo Ave",
    "iso:country":"US",
    "sg:address":"635 San Anselmo Ave",
    "sg:city":"San Anselmo",
    "sg:classifiers":[
        {
            "category":"Shopping",
            "type":"Retail Goods"
        }
    ],
    "sg:phone":"+1 415 454 9000",
    "sg:postcode":"94960",
    "sg:province":"CA",
    "sg:tags":[
        "art",
        "gallery",
        "dealer"
    ],
    "wof:name":"Ezra KATZ Gallery North",
    "wof:placetype":"venue"
},
  "geometry": {"coordinates":[-122.562838,37.975799],"type":"Point"}
}