{
  "type": "Feature",
  "properties": {
    "addr:full":"328 S State St Hemet CA 92543",
    "addr:housenumber":"328",
    "addr:postcode":"92543",
    "addr:street":"S State St",
    "iso:country":"US",
    "sg:address":"328 S State St",
    "sg:city":"Hemet",
    "sg:classifiers":[
        {
            "category":"Professional",
            "subcategory":"Business Services",
            "type":"Services"
        }
    ],
    "sg:phone":"+1 951 765 5000",
    "sg:postcode":"92543",
    "sg:province":"CA",
    "sg:tags":[
        "repossessing"
    ],
    "wof:name":"Night Owl Adjusters Inc",
    "wof:placetype":"venue"
},
  "geometry": {"coordinates":[-116.971541,33.742633],"type":"Point"}
}