{
  "type": "Feature",
  "properties": {
    "addr:full":"110 N Magnolia Ave El Cajon CA 92020",
    "addr:housenumber":"110",
    "addr:postcode":"92020",
    "addr:street":"N Magnolia Ave",
    "iso:country":"US",
    "sg:address":"110 N Magnolia Ave",
    "sg:city":"El Cajon",
    "sg:classifiers":[
        {
            "category":"Wholesale",
            "subcategory":"Toys & Hobbies",
            "type":"Manufacturing & Wholesale Goods"
        }
    ],
    "sg:phone":"+1 619 444 5329",
    "sg:postcode":"92020",
    "sg:province":"CA",
    "wof:name":"Game Crazy",
    "wof:placetype":"venue"
},
  "geometry": {"coordinates":[-116.96242100000001,32.795139],"type":"Point"}
}