{
  "type": "Feature",
  "properties": {
    "addr:full":"4180 Mesquite Springs Rd Twentynine Palms CA 92277",
    "addr:housenumber":"4180",
    "addr:postcode":"92277",
    "addr:street":"Mesquite Springs Rd",
    "iso:country":"US",
    "sg:address":"4180 Mesquite Springs Rd",
    "sg:city":"Twentynine Palms",
    "sg:classifiers":[
        {
            "category":"Wholesale",
            "subcategory":"Farm Supplies",
            "type":"Manufacturing & Wholesale Goods"
        }
    ],
    "sg:phone":"+1 760 361 0330",
    "sg:postcode":"92277",
    "sg:province":"CA",
    "sg:tags":[
        "feed"
    ],
    "wof:name":"Pioneer Feed & Livestock",
    "wof:placetype":"venue"
},
  "geometry": {"coordinates":[-116.071833,34.177729],"type":"Point"}
}