{
  "type": "Feature",
  "properties": {
    "addr:full":"3770 Rosemar Ave San Jose CA 95127",
    "addr:postcode":"3770;95127",
    "addr:street":"Rosemar Ave",
    "iso:country":"US",
    "sg:address":"3770 Rosemar Ave",
    "sg:city":"San Jose",
    "sg:classifiers":[
        {
            "category":"Insurance",
            "subcategory":"Insurance Agent",
            "type":"Services"
        }
    ],
    "sg:phone":"+1 408 926 1317",
    "sg:postcode":"95127",
    "sg:province":"CA",
    "wof:name":"IIST",
    "wof:placetype":"venue"
},
  "geometry": {"coordinates":[-121.804631,37.369753],"type":"Point"}
}