{
  "type": "Feature",
  "properties": {
    "addr:full":"9299 el Valle Ave Fountain Valley CA 92708",
    "addr:housenumber":"9299",
    "addr:postcode":"92708",
    "addr:street":"El Valle Ave",
    "iso:country":"US",
    "sg:address":"9299 el Valle Ave",
    "sg:city":"Fountain Valley",
    "sg:classifiers":[
        {
            "category":"Building & Trades",
            "subcategory":"Construction",
            "type":"Services"
        }
    ],
    "sg:phone":"+1 714 964 0389",
    "sg:postcode":"92708",
    "sg:province":"CA",
    "sg:tags":[
        "contractor"
    ],
    "wof:name":"Ideal Masonry",
    "wof:placetype":"venue"
},
  "geometry": {"coordinates":[-117.966306,33.708261],"type":"Point"}
}