{
  "type": "Feature",
  "properties": {
    "addr:full":"10252 Rosecrans Ave Bellflower CA 90706",
    "addr:housenumber":"10252",
    "addr:postcode":"90706",
    "addr:street":"Rosecrans Ave",
    "iso:country":"US",
    "sg:address":"10252 Rosecrans Ave",
    "sg:city":"Bellflower",
    "sg:classifiers":[
        {
            "category":"Shopping Center",
            "type":"Public Place"
        }
    ],
    "sg:phone":"+1 562 925 7707",
    "sg:postcode":"90706",
    "sg:province":"CA",
    "wof:name":"Rosewood Land Co",
    "wof:placetype":"venue"
},
  "geometry": {"coordinates":[-118.114998,33.901901],"type":"Point"}
}