{
  "type": "Feature",
  "properties": {
    "iso:country":"US",
    "sg:address":"244 S San Pedro St",
    "sg:city":"Los Angeles",
    "sg:classifiers":[
        {
            "category":"Arts & Performance",
            "subcategory":"Theater",
            "type":"Entertainment"
        }
    ],
    "sg:phone":"+1 213 268 4011",
    "sg:postcode":"90013",
    "sg:province":"CA",
    "sg:tags":[
        "educational",
        "performer"
    ],
    "sg:website":"www.jaccc.org",
    "wof:name":"Taikoproject",
    "wof:placetype":"venue"
},
  "geometry": {"coordinates":[-118.241795,34.049346],"type":"Point"}
}