{
  "type": "Feature",
  "properties": {
    "addr:full":"551 Birch St Lake Elsinore CA 92530",
    "addr:housenumber":"551",
    "addr:postcode":"92530",
    "addr:street":"Birch St",
    "iso:country":"US",
    "sg:address":"551 Birch St",
    "sg:city":"Lake Elsinore",
    "sg:classifiers":[
        {
            "category":"Manufacturing",
            "subcategory":"Glass & Minerals",
            "type":"Manufacturing & Wholesale Goods"
        }
    ],
    "sg:phone":"+1 951 245 4520",
    "sg:postcode":"92530",
    "sg:province":"CA",
    "sg:tags":[
        "concrete",
        "brick",
        "prod",
        "block"
    ],
    "sg:website":"www.earthshield.com",
    "wof:name":"Earth Shield",
    "wof:placetype":"venue"
},
  "geometry": {"coordinates":[-117.33726900000001,33.684569],"type":"Point"}
}