{
  "type": "Feature",
  "properties": {
    "addr:full":"1401 Avocado Ave Ste 703 Newport Beach CA 92660",
    "addr:housenumber":"1401",
    "addr:postcode":"92660",
    "addr:street":"Avocado Ave Ste 703",
    "iso:country":"US",
    "sg:address":"1401 Avocado Ave Ste 703",
    "sg:city":"Newport Beach",
    "sg:classifiers":[
        {
            "category":"Health Services",
            "subcategory":"Doctor",
            "type":"Services"
        }
    ],
    "sg:phone":"+1 949 640 7489",
    "sg:postcode":"92660",
    "sg:province":"CA",
    "wof:name":"Silverberg Surgical & Medical Group",
    "wof:placetype":"venue"
},
  "geometry": {"coordinates":[-117.871066,33.611986],"type":"Point"}
}