{
  "type": "Feature",
  "properties": {
    "addr:full":"1680 Vine Street Suite 309 Los Angeles CA 90028",
    "addr:housenumber":"1680",
    "addr:postcode":"90028",
    "addr:street":"Vine Street Suite 309",
    "iso:country":"US",
    "sg:address":"1680 Vine Street Suite 309",
    "sg:city":"Los Angeles",
    "sg:classifiers":[
        {
            "category":"Cinema",
            "subcategory":"Movie Theater",
            "type":"Entertainment"
        }
    ],
    "sg:phone":"+1 323 460 6924",
    "sg:postcode":"90028",
    "sg:province":"CA",
    "wof:name":"Key Cinema Club",
    "wof:placetype":"venue"
},
  "geometry": {"coordinates":[-118.32664800000001,34.101174],"type":"Point"}
}