{
  "type": "Feature",
  "properties": {
    "addr:full":"640 S San Vicente Blvd Los Angeles CA 90048",
    "addr:housenumber":"640",
    "addr:postcode":"90048",
    "addr:street":"S San Vicente Blvd",
    "iso:country":"US",
    "sg:address":"640 S San Vicente Blvd",
    "sg:city":"Los Angeles",
    "sg:classifiers":[
        {
            "category":"Restaurant",
            "type":"Food & Drink"
        }
    ],
    "sg:phone":"+1 323 653 6878",
    "sg:postcode":"90048",
    "sg:province":"CA",
    "wof:name":"Cafe Rico",
    "wof:placetype":"venue"
},
  "geometry": {"coordinates":[-118.373001,34.065899],"type":"Point"}
}