{
  "type": "Feature",
  "properties": {
    "addr:full":"1350 Gateway Blvd Fairfield CA 94533",
    "addr:housenumber":"1350",
    "addr:postcode":"94533",
    "addr:street":"Gateway Blvd",
    "iso:country":"US",
    "sg:address":"1350 Gateway Blvd",
    "sg:city":"Fairfield",
    "sg:classifiers":[
        {
            "category":"Personal",
            "subcategory":"Beauty Salon",
            "type":"Services"
        }
    ],
    "sg:phone":"+1 707 426 3447",
    "sg:postcode":"94533",
    "sg:province":"CA",
    "wof:name":"Fantastic Sams Of Fairfield",
    "wof:placetype":"venue"
},
  "geometry": {"coordinates":[-122.052082,38.263144],"type":"Point"}
}