{
  "type": "Feature",
  "properties": {
    "addr:full":"9730 Cuyamaca St Ste B Santee CA 92071",
    "addr:housenumber":"9730",
    "addr:postcode":"92071",
    "addr:street":"Cuyamaca St Ste B",
    "iso:country":"US",
    "sg:address":"9730 Cuyamaca St Ste B",
    "sg:city":"Santee",
    "sg:classifiers":[
        {
            "category":"Personal",
            "subcategory":"Nail Salon",
            "type":"Services"
        }
    ],
    "sg:phone":"+1 619 631 7171",
    "sg:postcode":"92071",
    "sg:province":"CA",
    "wof:name":"Nails by Jessica Stieler",
    "wof:placetype":"venue"
},
  "geometry": {"coordinates":[-116.983002,32.855],"type":"Point"}
}