{
  "type": "Feature",
  "properties": {
    "addr:full":"3199 Stonefield Dr Jamul CA 91935",
    "addr:housenumber":"3199",
    "addr:postcode":"91935",
    "addr:street":"Stonefield Dr",
    "iso:country":"US",
    "sg:address":"3199 Stonefield Dr",
    "sg:city":"Jamul",
    "sg:classifiers":[
        {
            "category":"Retail",
            "subcategory":"Event Space",
            "type":"Services"
        },
        {
            "category":"Sports & Exercise",
            "subcategory":"Golf",
            "type":"Entertainment"
        },
        {
            "category":"Sports & Exercise",
            "subcategory":"Sports Center",
            "type":"Entertainment"
        },
        {
            "category":"Arena",
            "subcategory":"Sports Club",
            "type":"Entertainment"
        }
    ],
    "sg:phone":"+1 619 441 6900",
    "sg:postcode":"91935",
    "sg:province":"CA",
    "sg:tags":[
        "facility",
        "instruction",
        "hall",
        "course",
        "courses-private",
        "reception",
        "banquet"
    ],
    "wof:name":"Steele Canyon Golf Club",
    "wof:placetype":"venue"
},
  "geometry": {"coordinates":[-116.89402,32.743149],"type":"Point"}
}