{
  "type": "Feature",
  "properties": {
    "iso:country":"US",
    "sg:address":"321 D St",
    "sg:city":"Marysville",
    "sg:classifiers":[
        {
            "category":"Home & Garden",
            "subcategory":"Building Materials",
            "type":"Retail Goods"
        }
    ],
    "sg:phone":"+1 530 743 1091",
    "sg:postcode":"95901",
    "sg:province":"CA",
    "sg:tags":[
        "energy",
        "conservation",
        "prod"
    ],
    "wof:name":"Tru-Brite",
    "wof:placetype":"venue"
},
  "geometry": {"coordinates":[-121.588739,39.139016],"type":"Point"}
}