{
  "type": "Feature",
  "properties": {
    "addr:full":"770 The City Dr S Orange CA 92868",
    "addr:housenumber":"770",
    "addr:postcode":"92868",
    "addr:street":"The City Dr S",
    "iso:country":"US",
    "sg:address":"770 The City Dr S",
    "sg:city":"Orange",
    "sg:classifiers":[
        {
            "category":"Insurance",
            "subcategory":"Insurance Agent",
            "type":"Services"
        }
    ],
    "sg:phone":"+1 714 740 0888",
    "sg:postcode":"92868",
    "sg:province":"CA",
    "wof:name":"Atlantic Mutual Co",
    "wof:placetype":"venue"
},
  "geometry": {"coordinates":[-117.88941800000001,33.777717],"type":"Point"}
}