{
  "type": "Feature",
  "properties": {
    "addr:full":"Pier 39 Ste K01 San Francisco CA 94124",
    "addr:postcode":"94124",
    "addr:street":"Ste K01",
    "iso:country":"US",
    "sg:address":"Pier 39 Ste K01",
    "sg:city":"San Francisco",
    "sg:classifiers":[
        {
            "category":"Food & Beverages",
            "subcategory":"Candy",
            "type":"Retail Goods"
        },
        {
            "category":"Restaurant",
            "type":"Food & Drink"
        }
    ],
    "sg:phone":"+1 415 397 8881",
    "sg:postcode":"94124",
    "sg:province":"CA",
    "sg:tags":[
        "dessert",
        "seafood"
    ],
    "wof:name":"Crabcakes & Sweets",
    "wof:placetype":"venue"
},
  "geometry": {"coordinates":[-122.410612,37.809852],"type":"Point"}
}