{
  "type": "Feature",
  "properties": {
    "iso:country":"US",
    "sg:address":"7140 Gladys Ave",
    "sg:city":"El Cerrito",
    "sg:classifiers":[
        {
            "category":"Recreation",
            "subcategory":"Playground",
            "type":"Entertainment"
        }
    ],
    "sg:postcode":"94530",
    "sg:province":"CA",
    "wof:name":"Cameron School Toddler Park",
    "wof:placetype":"venue"
},
  "geometry": {"coordinates":[-122.306878,37.922192],"type":"Point"}
}