{
  "type": "Feature",
  "properties": {
    "iso:country":"US",
    "sg:address":"1906 W 3rd St",
    "sg:city":"Los Angeles",
    "sg:classifiers":[
        {
            "category":"Travel",
            "subcategory":"Hotels & Motels",
            "type":"Entertainment"
        }
    ],
    "sg:phone":"+1 213 483 6681",
    "sg:postcode":"90057",
    "sg:province":"CA",
    "wof:name":"Nutel Hotel",
    "wof:placetype":"venue"
},
  "geometry": {"coordinates":[-118.269997,34.062099],"type":"Point"}
}