{
  "type": "Feature",
  "properties": {
    "addr:full":"607 W Front St Covina CA 91722",
    "addr:housenumber":"607",
    "addr:postcode":"91722",
    "addr:street":"W Front St",
    "iso:country":"US",
    "sg:address":"607 W Front St",
    "sg:city":"Covina",
    "sg:classifiers":[
        {
            "category":"Local Transit",
            "type":"Transportation"
        }
    ],
    "sg:phone":"+1 626 339 1494",
    "sg:postcode":"91722",
    "sg:province":"CA",
    "sg:tags":[
        "passenger"
    ],
    "wof:name":"Vega Transport",
    "wof:placetype":"venue"
},
  "geometry": {"coordinates":[-117.901646,34.091693],"type":"Point"}
}