{
  "type": "Feature",
  "properties": {
    "iso:country":"US",
    "sg:address":"11500 Acacia Ave",
    "sg:city":"Hawthorne",
    "sg:classifiers":[
        {
            "category":"Travel",
            "subcategory":"Hotels & Motels",
            "type":"Entertainment"
        }
    ],
    "sg:phone":"+1 310 973 3335",
    "sg:postcode":"90250",
    "sg:province":"CA",
    "sg:website":"www.choicehotels.com",
    "wof:name":"Comfort Inn",
    "wof:placetype":"venue"
},
  "geometry": {"coordinates":[-118.351204,33.929969],"type":"Point"}
}