{
  "type": "Feature",
  "properties": {
    "addr:full":"303 N Alameda Street Compton CA 90220",
    "addr:housenumber":"303",
    "addr:postcode":"90220",
    "addr:street":"N Alameda Street",
    "iso:country":"US",
    "sg:address":"303 N Alameda Street",
    "sg:city":"Compton",
    "sg:classifiers":[
        {
            "category":"Restaurant",
            "type":"Food & Drink"
        }
    ],
    "sg:phone":"+1 310 639 3045",
    "sg:postcode":"90220",
    "sg:province":"CA",
    "wof:name":"Tam's Burgers No 23",
    "wof:placetype":"venue"
},
  "geometry": {"coordinates":[-118.220766,33.897524],"type":"Point"}
}