{
  "type": "Feature",
  "properties": {
    "iso:country":"US",
    "sg:address":"4004 Florida St",
    "sg:city":"San Diego",
    "sg:classifiers":[
        {
            "category":"Food & Beverages",
            "subcategory":"Specialty",
            "type":"Retail Goods"
        },
        {
            "category":"Wholesale",
            "subcategory":"Groceries",
            "type":"Manufacturing & Wholesale Goods"
        }
    ],
    "sg:phone":"+1 619 291 4832",
    "sg:postcode":"92104",
    "sg:province":"CA",
    "sg:tags":[
        "tea"
    ],
    "wof:name":"Fleur-De-Tea",
    "wof:placetype":"venue"
},
  "geometry": {"coordinates":[-117.143835,32.752085],"type":"Point"}
}