{
  "type": "Feature",
  "properties": {
    "addr:full":"1030 3rd St San Rafael CA 94901",
    "addr:housenumber":"1030",
    "addr:postcode":"94901",
    "addr:street":"3Rd St",
    "iso:country":"US",
    "sg:address":"1030 3rd St",
    "sg:city":"San Rafael",
    "sg:classifiers":[
        {
            "category":"Banks & Credit Unions",
            "subcategory":"Bank",
            "type":"Services"
        }
    ],
    "sg:phone":"+1 415 456 6231",
    "sg:postcode":"94901",
    "sg:province":"CA",
    "sg:tags":[
        "savings",
        "loan",
        "association"
    ],
    "wof:name":"First Federal Savings & Loan",
    "wof:placetype":"venue"
},
  "geometry": {"coordinates":[-122.528128,37.97221],"type":"Point"}
}