{
  "type": "Feature",
  "properties": {
    "iso:country":"US",
    "sg:address":"1 Lemon Tree Cir",
    "sg:city":"Vacaville",
    "sg:classifiers":[
        {
            "category":"Real Estate",
            "subcategory":"Real Estate Operator",
            "type":"Services"
        }
    ],
    "sg:phone":"+1 707 448 0818",
    "sg:postcode":"95687",
    "sg:province":"CA",
    "sg:tags":[
        "mobile",
        "home",
        "park",
        "community"
    ],
    "wof:name":"Lemon Tree Mobile Home Park Inc",
    "wof:placetype":"venue"
},
  "geometry": {"coordinates":[-121.950649,38.37064],"type":"Point"}
}