{
  "type": "Feature",
  "properties": {
    "iso:country":"US",
    "sg:address":"1452 Gavilan Way",
    "sg:city":"Millbrae",
    "sg:classifiers":[
        {
            "category":"Professional",
            "type":"Services"
        }
    ],
    "sg:phone":"+1 650 697 0380",
    "sg:postcode":"94030",
    "sg:province":"CA",
    "wof:name":"Thomas Spencer",
    "wof:placetype":"venue"
},
  "geometry": {"coordinates":[-122.401301,37.583825],"type":"Point"}
}