{
  "type": "Feature",
  "properties": {
    "iso:country":"US",
    "sg:address":"9009 W Sunset Blvd",
    "sg:city":"West Hollywood",
    "sg:classifiers":[
        {
            "category":"Bars & Pubs",
            "type":"Food & Drink"
        }
    ],
    "sg:phone":"+1 310 278 9457",
    "sg:postcode":"90069",
    "sg:province":"CA",
    "sg:tags":[
        "club",
        "venue",
        "music",
        "night"
    ],
    "sg:website":"www.theroxyonsunset.com",
    "wof:name":"The Roxy Theatre",
    "wof:placetype":"venue"
},
  "geometry": {"coordinates":[-118.387901,34.090632],"type":"Point"}
}