{
  "type": "Feature",
  "properties": {
    "iso:country":"US",
    "sg:address":"80 W Easy St",
    "sg:city":"Simi Valley",
    "sg:classifiers":[
        {
            "category":"Manufacturing",
            "subcategory":"Tools & Machinery",
            "type":"Manufacturing & Wholesale Goods"
        }
    ],
    "sg:phone":"+1 805 583 0808",
    "sg:postcode":"93065",
    "sg:province":"CA",
    "sg:tags":[
        "instrument",
        "surveying"
    ],
    "sg:website":"www.meilaser.com",
    "wof:name":"MEI Survey Instruments",
    "wof:placetype":"venue"
},
  "geometry": {"coordinates":[-118.799833,34.278798],"type":"Point"}
}