{
  "type": "Feature",
  "properties": {
    "addr:full":"13756 Victory Blvd Van Nuys CA 91401",
    "addr:housenumber":"13756",
    "addr:postcode":"91401",
    "addr:street":"Victory Blvd",
    "iso:country":"US",
    "sg:address":"13756 Victory Blvd",
    "sg:city":"Van Nuys",
    "sg:classifiers":[
        {
            "category":"Shopping",
            "subcategory":"Jewelry",
            "type":"Retail Goods"
        }
    ],
    "sg:phone":"+1 818 902 1771",
    "sg:postcode":"91401",
    "sg:province":"CA",
    "wof:name":"Bijan Jewelry",
    "wof:placetype":"venue"
},
  "geometry": {"coordinates":[-118.432787,34.186532],"type":"Point"}
}