{
  "type": "Feature",
  "properties": {
    "addr:full":"2675 Irvine Ave Costa Mesa CA 92627",
    "addr:housenumber":"2675",
    "addr:postcode":"92627",
    "addr:street":"Irvine Ave",
    "iso:country":"US",
    "sg:address":"2675 Irvine Ave",
    "sg:city":"Costa Mesa",
    "sg:classifiers":[
        {
            "category":"Personal",
            "subcategory":"Day Spa",
            "type":"Services"
        }
    ],
    "sg:phone":"+1 949 646 1788",
    "sg:postcode":"92627",
    "sg:province":"CA",
    "wof:name":"Holiday Spa",
    "wof:placetype":"venue"
},
  "geometry": {"coordinates":[-117.885122,33.6582],"type":"Point"}
}