{
  "type": "Feature",
  "properties": {
    "addr:full":"5820 College Ave Oakland CA 94618",
    "addr:housenumber":"5820",
    "addr:postcode":"94618",
    "addr:street":"College Ave",
    "iso:country":"US",
    "sg:address":"5820 College Ave",
    "sg:city":"Oakland",
    "sg:classifiers":[
        {
            "category":"Arts & Performance",
            "subcategory":"Art Gallery",
            "type":"Entertainment"
        },
        {
            "category":"Manufacturing",
            "subcategory":"Wood Products",
            "type":"Manufacturing & Wholesale Goods"
        },
        {
            "category":"Retail",
            "subcategory":"Repair Shop",
            "type":"Services"
        },
        {
            "category":"Professional",
            "subcategory":"Art Services",
            "type":"Services"
        },
        {
            "category":"Farming",
            "subcategory":"Fish & Marine Products",
            "type":"Manufacturing & Wholesale Goods"
        }
    ],
    "sg:phone":"+1 510 501 3389",
    "sg:postcode":"94618",
    "sg:province":"CA",
    "sg:tags":[
        "picture",
        "frames-wholesale",
        "consultant",
        "frame",
        "galleries",
        "restoration",
        "framing",
        "manufacturer"
    ],
    "sg:website":"http://www.thegreatframeup.com",
    "wof:name":"The Great Frame Up",
    "wof:placetype":"venue"
},
  "geometry": {"coordinates":[-122.251999,37.845699],"type":"Point"}
}