{
  "type": "Feature",
  "properties": {
    "iso:country":"US",
    "sg:address":"5080 Bonita Rd Ste G",
    "sg:city":"Bonita",
    "sg:classifiers":[
        {
            "category":"Personal",
            "subcategory":"Beauty Salon",
            "type":"Services"
        }
    ],
    "sg:phone":"+1 619 479 8842",
    "sg:postcode":"91902",
    "sg:province":"CA",
    "sg:tags":[
        "hair"
    ],
    "wof:name":"Gonzales Gloria Hair Designer",
    "wof:placetype":"venue"
},
  "geometry": {"coordinates":[-117.023003,32.669498],"type":"Point"}
}