{
  "type": "Feature",
  "properties": {
    "addr:full":"6360 W Third St. Los Angeles CA 90036",
    "addr:housenumber":"6360",
    "addr:postcode":"90036",
    "addr:street":"W Third St.",
    "iso:country":"US",
    "sg:address":"6360 W Third St.",
    "sg:city":"Los Angeles",
    "sg:classifiers":[
        {
            "category":"Shopping",
            "subcategory":"Pharmacy",
            "type":"Retail Goods"
        }
    ],
    "sg:postcode":"90036",
    "sg:province":"CA",
    "sg:tags":[
        "drugstore"
    ],
    "wof:name":"Rite Aid",
    "wof:placetype":"venue"
},
  "geometry": {"coordinates":[-118.361,34.071301],"type":"Point"}
}