{
  "type": "Feature",
  "properties": {
    "iso:country":"US",
    "sg:address":"2906 W Main St",
    "sg:city":"Visalia",
    "sg:classifiers":[
        {
            "category":"Banks & Credit Unions",
            "subcategory":"Investment Brokerage",
            "type":"Services"
        }
    ],
    "sg:phone":"+1 559 732 9025",
    "sg:postcode":"93291",
    "sg:province":"CA",
    "sg:tags":[
        "security"
    ],
    "sg:website":"www.divsecs.com",
    "wof:name":"Richard G Clore-Stock Broker",
    "wof:placetype":"venue"
},
  "geometry": {"coordinates":[-119.322093,36.329616],"type":"Point"}
}