{
  "type": "Feature",
  "properties": {
    "addr:full":"26881 Jefferson Ave Murrieta CA 92562",
    "addr:housenumber":"26881",
    "addr:postcode":"92562",
    "addr:street":"Jefferson Ave",
    "iso:country":"US",
    "sg:address":"26881 Jefferson Ave",
    "sg:city":"Murrieta",
    "sg:classifiers":[
        {
            "category":"Home & Garden",
            "subcategory":"Building Materials",
            "type":"Retail Goods"
        }
    ],
    "sg:phone":"+1 951 304 0301",
    "sg:postcode":"92562",
    "sg:province":"CA",
    "sg:tags":[
        "glass",
        "window",
        "plate"
    ],
    "sg:website":"www.windshieldpros.com",
    "wof:name":"Windshield Pros",
    "wof:placetype":"venue"
},
  "geometry": {"coordinates":[-117.174306,33.528377],"type":"Point"}
}