{
  "type": "Feature",
  "properties": {
    "addr:full":"226 Elm Wood Ct Los Gatos CA 95032",
    "addr:housenumber":"226",
    "addr:postcode":"95032",
    "addr:street":"Elm Wood Ct",
    "iso:country":"US",
    "sg:address":"226 Elm Wood Ct",
    "sg:city":"Los Gatos",
    "sg:classifiers":[
        {
            "category":"Retail",
            "subcategory":"Portrait Studio",
            "type":"Services"
        }
    ],
    "sg:phone":"+1 408 315 2140",
    "sg:postcode":"95032",
    "sg:province":"CA",
    "wof:name":"Unique Moment Videography",
    "wof:placetype":"venue"
},
  "geometry": {"coordinates":[-121.97713400000001,37.264471],"type":"Point"}
}