{
  "type": "Feature",
  "properties": {
    "addr:full":"4858 Harbord Dr Oakland CA 94618",
    "addr:housenumber":"4858",
    "addr:postcode":"94618",
    "addr:street":"Harbord Dr",
    "iso:country":"US",
    "sg:address":"4858 Harbord Dr",
    "sg:city":"Oakland",
    "sg:classifiers":[
        {
            "category":"Professional",
            "subcategory":"Research",
            "type":"Services"
        }
    ],
    "sg:phone":"+1 510 599 1799",
    "sg:postcode":"94618",
    "sg:province":"CA",
    "sg:tags":[
        "environmental",
        "ecological"
    ],
    "sg:website":"www.fletcherconsultantsinc.com",
    "wof:name":"Fletcher Consultants Inc",
    "wof:placetype":"venue"
},
  "geometry": {"coordinates":[-122.22972799999999,37.836848],"type":"Point"}
}