{
  "type": "Feature",
  "properties": {
    "iso:country":"US",
    "sg:address":"4191 Carpinteria Ave",
    "sg:city":"Carpinteria",
    "sg:classifiers":[
        {
            "category":"Building & Trades",
            "subcategory":"Construction",
            "type":"Services"
        }
    ],
    "sg:phone":"+1 805 684 6381",
    "sg:postcode":"93013",
    "sg:province":"CA",
    "sg:tags":[
        "contractor"
    ],
    "wof:name":"Ejs Construction",
    "wof:placetype":"venue"
},
  "geometry": {"coordinates":[-119.532918,34.403678],"type":"Point"}
}