{
  "type": "Feature",
  "properties": {
    "addr:full":"12522 Brookhurst St Garden Grove CA 92840",
    "addr:housenumber":"12522",
    "addr:postcode":"92840",
    "addr:street":"Brookhurst St",
    "iso:country":"US",
    "sg:address":"12522 Brookhurst St",
    "sg:city":"Garden Grove",
    "sg:classifiers":[
        {
            "category":"Professional",
            "subcategory":"Accounting & Tax Preparation",
            "type":"Services"
        }
    ],
    "sg:phone":"+1 714 539 5661",
    "sg:postcode":"92840",
    "sg:province":"CA",
    "sg:tags":[
        "return",
        "filing"
    ],
    "wof:name":"B T Svc",
    "wof:placetype":"venue"
},
  "geometry": {"coordinates":[-117.958467,33.780695],"type":"Point"}
}