{
  "type": "Feature",
  "properties": {
    "addr:full":"1234 Callen St Vacaville CA 95688",
    "addr:housenumber":"1234",
    "addr:postcode":"95688",
    "addr:street":"Callen St",
    "iso:country":"US",
    "sg:address":"1234 Callen St",
    "sg:city":"Vacaville",
    "sg:classifiers":[
        {
            "category":"Retail",
            "subcategory":"Auto Repair",
            "type":"Services"
        }
    ],
    "sg:phone":"+1 707 453 0555",
    "sg:postcode":"95688",
    "sg:province":"CA",
    "sg:tags":[
        "muffler",
        "exhaust",
        "system"
    ],
    "wof:name":"California Classics & Custom",
    "wof:placetype":"venue"
},
  "geometry": {"coordinates":[-121.97490500000001,38.358921],"type":"Point"}
}