{
  "type": "Feature",
  "properties": {
    "iso:country":"US",
    "sg:address":"2641 Oak Rd",
    "sg:city":"Walnut Creek",
    "sg:classifiers":[
        {
            "category":"Organizations",
            "subcategory":"Professional Association",
            "type":"Services"
        }
    ],
    "sg:phone":"+1 925 256 0228",
    "sg:postcode":"94597",
    "sg:province":"CA",
    "wof:name":"Carriage Place Homowners Assoc",
    "wof:placetype":"venue"
},
  "geometry": {"coordinates":[-122.058361,37.921788],"type":"Point"}
}