{
  "type": "Feature",
  "properties": {
    "iso:country":"US",
    "sg:address":"1220 E Woodbury Rd",
    "sg:city":"Pasadena",
    "sg:classifiers":[
        {
            "category":"Professional",
            "subcategory":"Computer Services",
            "type":"Services"
        }
    ],
    "sg:phone":"+1 626 797 3462",
    "sg:postcode":"91104",
    "sg:province":"CA",
    "sg:tags":[
        "repair"
    ],
    "sg:website":"www.jsnpc.com",
    "wof:name":"JSN PROFESSIONAL COMPUTER CARE",
    "wof:placetype":"venue"
},
  "geometry": {"coordinates":[-118.125314,34.176383],"type":"Point"}
}