{
  "type": "Feature",
  "properties": {
    "iso:country":"US",
    "sg:address":"2650 21st Street",
    "sg:city":"Sacramento",
    "sg:classifiers":[
        {
            "category":"Health Services",
            "subcategory":"Dentist",
            "type":"Services"
        }
    ],
    "sg:phone":"+1 916 452 5231",
    "sg:postcode":"95818",
    "sg:province":"CA",
    "sg:tags":[
        "pediatric"
    ],
    "wof:name":"Craig B Hollingsworth DDS",
    "wof:placetype":"venue"
},
  "geometry": {"coordinates":[-121.486968,38.556846],"type":"Point"}
}