{
  "type": "Feature",
  "properties": {
    "iso:country":"US",
    "sg:address":"3853 Taylor Rd",
    "sg:city":"Loomis",
    "sg:classifiers":[
        {
            "category":"Real Estate",
            "subcategory":"Real Estate Agent",
            "type":"Services"
        }
    ],
    "sg:phone":"+1 916 660 0798",
    "sg:postcode":"95650",
    "sg:province":"CA",
    "sg:tags":[
        "appraiser"
    ],
    "wof:name":"John Ridley Real Est Appraiser",
    "wof:placetype":"venue"
},
  "geometry": {"coordinates":[-121.200904,38.814907],"type":"Point"}
}