{
  "type": "Feature",
  "properties": {
    "iso:country":"US",
    "sg:address":"1342 Jasper Ave",
    "sg:city":"Mentone",
    "sg:classifiers":[
        {
            "category":"Place Of Worship",
            "subcategory":"Church",
            "type":"Public Place"
        },
        {
            "category":"Place Of Worship",
            "type":"Public Place"
        },
        {
            "category":"Organizations",
            "subcategory":"Religious Organization",
            "type":"Services"
        }
    ],
    "sg:phone":"+1 909 794 4234",
    "sg:postcode":"92359",
    "sg:province":"CA",
    "sg:tags":[
        "churches-interdenominational",
        "denomination",
        "churches-various",
        "churches-non-denominational"
    ],
    "wof:name":"Avodah Fellowship",
    "wof:placetype":"venue"
},
  "geometry": {"coordinates":[-117.136224,34.073096],"type":"Point"}
}