{
  "type": "Feature",
  "properties": {
    "addr:full":"1515 Pico Way Walnut Creek CA 94597",
    "addr:housenumber":"1515",
    "addr:postcode":"94597",
    "addr:street":"Pico Way",
    "iso:country":"US",
    "sg:address":"1515 Pico Way",
    "sg:city":"Walnut Creek",
    "sg:classifiers":[
        {
            "category":"Local Transit",
            "type":"Transportation"
        }
    ],
    "sg:phone":"+1 925 934 2258",
    "sg:postcode":"94597",
    "sg:province":"CA",
    "sg:tags":[
        "passenger"
    ],
    "wof:name":"Pet Jet",
    "wof:placetype":"venue"
},
  "geometry": {"coordinates":[-122.088797,37.922862],"type":"Point"}
}