{
  "type": "Feature",
  "properties": {
    "iso:country":"US",
    "sg:address":"4617 Freeport Blvd Ste G",
    "sg:city":"Sacramento",
    "sg:classifiers":[
        {
            "category":"Professional",
            "subcategory":"Testing Lab",
            "type":"Services"
        },
        {
            "category":"Health Services",
            "subcategory":"Medical Lab",
            "type":"Services"
        }
    ],
    "sg:phone":"+1 916 456 5093",
    "sg:postcode":"95822",
    "sg:province":"CA",
    "sg:tags":[
        "laboratory",
        "dental"
    ],
    "wof:name":"Hamai Dental Lab",
    "wof:placetype":"venue"
},
  "geometry": {"coordinates":[-121.494348,38.53337],"type":"Point"}
}