{
  "type": "Feature",
  "properties": {
    "addr:full":"2895 Regal Ave Redding CA 96002",
    "addr:housenumber":"2895",
    "addr:postcode":"96002",
    "addr:street":"Regal Ave",
    "iso:country":"US",
    "sg:address":"2895 Regal Ave",
    "sg:city":"Redding",
    "sg:classifiers":[
        {
            "category":"Real Estate",
            "subcategory":"Surveying",
            "type":"Services"
        }
    ],
    "sg:phone":"+1 530 222 1736",
    "sg:postcode":"96002",
    "sg:province":"CA",
    "sg:tags":[
        "surveyor",
        "land",
        "engineer"
    ],
    "wof:name":"Riggins Land Surveying",
    "wof:placetype":"venue"
},
  "geometry": {"coordinates":[-122.34293599999999,40.564822],"type":"Point"}
}