{
  "type": "Feature",
  "properties": {
    "iso:country":"US",
    "sg:address":"1368 E Washington Blvd",
    "sg:city":"Los Angeles",
    "sg:classifiers":[
        {
            "category":"Retail",
            "subcategory":"Auto Repair",
            "type":"Services"
        }
    ],
    "sg:phone":"+1 213 749 4948",
    "sg:postcode":"90021",
    "sg:province":"CA",
    "sg:tags":[
        "spring"
    ],
    "wof:name":"A & M Truck & Auto Suspension",
    "wof:placetype":"venue"
},
  "geometry": {"coordinates":[-118.249522,34.023941],"type":"Point"}
}