{
  "type": "Feature",
  "properties": {
    "addr:full":"265 W Foothill Blvd San Dimas CA 91773",
    "addr:housenumber":"265",
    "addr:postcode":"91773",
    "addr:street":"W Foothill Blvd",
    "iso:country":"US",
    "sg:address":"265 W Foothill Blvd",
    "sg:city":"San Dimas",
    "sg:classifiers":[
        {
            "category":"Real Estate",
            "subcategory":"Real Estate Operator",
            "type":"Services"
        }
    ],
    "sg:phone":"+1 909 394 0333",
    "sg:postcode":"91773",
    "sg:province":"CA",
    "sg:tags":[
        "apartment"
    ],
    "wof:name":"Park San Dimas Senior Apts",
    "wof:placetype":"venue"
},
  "geometry": {"coordinates":[-117.810378,34.125097],"type":"Point"}
}