{
  "type": "Feature",
  "properties": {
    "addr:full":"12 Mason Ste A Irvine CA 92618",
    "addr:housenumber":"12",
    "addr:postcode":"92618",
    "addr:street":"Mason Ste A",
    "iso:country":"US",
    "sg:address":"12 Mason Ste A",
    "sg:city":"Irvine",
    "sg:classifiers":[
        {
            "category":"Health Services",
            "subcategory":"Doctor",
            "type":"Services"
        },
        {
            "category":"Community Center",
            "type":"Public Place"
        }
    ],
    "sg:phone":"+1 949 380 1552",
    "sg:postcode":"92618",
    "sg:province":"CA",
    "sg:tags":[
        "medical"
    ],
    "wof:name":"South Coast Medical Center",
    "wof:placetype":"venue"
},
  "geometry": {"coordinates":[-117.72315399999999,33.64346],"type":"Point"}
}