{
  "type": "Feature",
  "properties": {
    "addr:full":"5330 Power Inn Rd Ste F Sacramento CA 95820",
    "addr:housenumber":"5330",
    "addr:postcode":"95820",
    "addr:street":"Power Inn Rd Ste F",
    "iso:country":"US",
    "sg:address":"5330 Power Inn Rd Ste F",
    "sg:city":"Sacramento",
    "sg:classifiers":[
        {
            "category":"Shopping",
            "subcategory":"Computers & Home Electronics",
            "type":"Retail Goods"
        }
    ],
    "sg:phone":"+1 916 381 5011",
    "sg:postcode":"95820",
    "sg:province":"CA",
    "sg:tags":[
        "hardware",
        "supply"
    ],
    "wof:name":"Assistive Technology Ctr",
    "wof:placetype":"venue"
},
  "geometry": {"coordinates":[-121.409142,38.526968],"type":"Point"}
}