{
  "type": "Feature",
  "properties": {
    "addr:full":"188 10th St Oakland CA 94607",
    "addr:housenumber":"188",
    "addr:postcode":"94607",
    "addr:street":"10Th St",
    "iso:country":"US",
    "sg:address":"188 10th St",
    "sg:city":"Oakland",
    "sg:classifiers":[
        {
            "category":"Manufacturing",
            "subcategory":"Metals",
            "type":"Manufacturing & Wholesale Goods"
        }
    ],
    "sg:phone":"+1 510 832 1681",
    "sg:postcode":"94607",
    "sg:province":"CA",
    "sg:tags":[
        "tool",
        "mfg",
        "hand"
    ],
    "wof:name":"The Ox Tools Company",
    "wof:placetype":"venue"
},
  "geometry": {"coordinates":[-122.26617400000001,37.798936],"type":"Point"}
}