{
  "type": "Feature",
  "properties": {
    "addr:full":"465 4th St Orange Cove CA 93646",
    "addr:housenumber":"465",
    "addr:postcode":"93646",
    "addr:street":"4Th St",
    "iso:country":"US",
    "sg:address":"465 4th St",
    "sg:city":"Orange Cove",
    "sg:classifiers":[
        {
            "category":"Organizations",
            "subcategory":"Religious Organization",
            "type":"Services"
        }
    ],
    "sg:phone":"+1 559 626 6821",
    "sg:postcode":"93646",
    "sg:province":"CA",
    "sg:tags":[
        "church"
    ],
    "wof:name":"New Beginnings Christian",
    "wof:placetype":"venue"
},
  "geometry": {"coordinates":[-119.309713,36.626899],"type":"Point"}
}