{
  "type": "Feature",
  "properties": {
    "iso:country":"US",
    "sg:address":"6008 69th St",
    "sg:city":"Sacramento",
    "sg:classifiers":[
        {
            "category":"Communications",
            "subcategory":"Film & Video Production",
            "type":"Services"
        }
    ],
    "sg:phone":"+1 916 281 6063",
    "sg:postcode":"95824",
    "sg:province":"CA",
    "sg:tags":[
        "recording",
        "service-sound"
    ],
    "sg:website":"http://hstrial-vlupsa.homestead.com",
    "wof:name":"papos studio",
    "wof:placetype":"venue"
},
  "geometry": {"coordinates":[-121.42347700000001,38.517471],"type":"Point"}
}