{
  "type": "Feature",
  "properties": {
    "iso:country":"US",
    "sg:address":"16546 Russell Ct",
    "sg:city":"San Leandro",
    "sg:classifiers":[
        {
            "category":"Banks & Credit Unions",
            "subcategory":"Financial Services",
            "type":"Services"
        }
    ],
    "sg:phone":"+1 510 278 8133",
    "sg:postcode":"94578",
    "sg:province":"CA",
    "sg:tags":[
        "broker",
        "mortgage"
    ],
    "wof:name":"Interbiz",
    "wof:placetype":"venue"
},
  "geometry": {"coordinates":[-122.10313499999999,37.698945],"type":"Point"}
}