{
  "type": "Feature",
  "properties": {
    "addr:full":"2728 E Coast Hwy Corona Del Mar CA 92625",
    "addr:housenumber":"2728",
    "addr:postcode":"92625",
    "addr:street":"E Coast Hwy",
    "iso:country":"US",
    "sg:address":"2728 E Coast Hwy",
    "sg:city":"Corona Del Mar",
    "sg:classifiers":[
        {
            "category":"Building & Trades",
            "subcategory":"Landscaping Services",
            "type":"Services"
        }
    ],
    "sg:phone":"+1 949 760 0454",
    "sg:postcode":"92625",
    "sg:province":"CA",
    "sg:tags":[
        "architect",
        "landscape"
    ],
    "wof:name":"Katzmaier Newell Kehr",
    "wof:placetype":"venue"
},
  "geometry": {"coordinates":[-117.87294,33.601637],"type":"Point"}
}