{
  "type": "Feature",
  "properties": {
    "addr:full":"7017 Hughson Ave Hughson CA 95326",
    "addr:housenumber":"7017",
    "addr:postcode":"95326",
    "addr:street":"Hughson Ave",
    "iso:country":"US",
    "sg:address":"7017 Hughson Ave",
    "sg:city":"Hughson",
    "sg:classifiers":[
        {
            "category":"Health Services",
            "subcategory":"Health Practitioner",
            "type":"Services"
        }
    ],
    "sg:phone":"+1 209 883 1060",
    "sg:postcode":"95326",
    "sg:province":"CA",
    "sg:tags":[
        "nurse",
        "registry"
    ],
    "wof:name":"We Care Medical Staff Inc",
    "wof:placetype":"venue"
},
  "geometry": {"coordinates":[-120.864425,37.596865],"type":"Point"}
}