{
  "type": "Feature",
  "properties": {
    "iso:country":"US",
    "sg:address":"1111 W El Camino Real 2nd Fl",
    "sg:city":"Sunnyvale",
    "sg:classifiers":[
        {
            "category":"Arts & Performance",
            "subcategory":"Arts Center",
            "type":"Entertainment"
        },
        {
            "category":"Shopping",
            "subcategory":"Shoes",
            "type":"Retail Goods"
        }
    ],
    "sg:phone":"+1 408 773 8833",
    "sg:postcode":"94087",
    "sg:province":"CA",
    "sg:tags":[
        "performing",
        "store"
    ],
    "sg:website":"www.ballroom-connection.com",
    "wof:name":"Ballroom Connection",
    "wof:placetype":"venue"
},
  "geometry": {"coordinates":[-122.052763,37.373039],"type":"Point"}
}