{
  "type": "Feature",
  "properties": {
    "addr:full":"21393 Encina Rd Topanga CA 90290",
    "addr:housenumber":"21393",
    "addr:postcode":"90290",
    "addr:street":"Encina Rd",
    "iso:country":"US",
    "sg:address":"21393 Encina Rd",
    "sg:city":"Topanga",
    "sg:classifiers":[
        {
            "category":"Shopping",
            "type":"Retail Goods"
        }
    ],
    "sg:phone":"+1 310 455 1383",
    "sg:postcode":"90290",
    "sg:province":"CA",
    "sg:tags":[
        "merchandise"
    ],
    "wof:name":"Tadpole Productions",
    "wof:placetype":"venue"
},
  "geometry": {"coordinates":[-118.600105,34.092241],"type":"Point"}
}