{
  "type": "Feature",
  "properties": {
    "iso:country":"US",
    "sg:address":"9375 Archibald Ave",
    "sg:city":"Rancho Cucamonga",
    "sg:classifiers":[
        {
            "category":"Manufacturing",
            "subcategory":"Printing",
            "type":"Manufacturing & Wholesale Goods"
        }
    ],
    "sg:phone":"+1 909 481 0221",
    "sg:postcode":"91730",
    "sg:province":"CA",
    "sg:tags":[
        "printer",
        "offset"
    ],
    "wof:name":"Diverse Graphics",
    "wof:placetype":"venue"
},
  "geometry": {"coordinates":[-117.593321,34.081837],"type":"Point"}
}