{
  "type": "Feature",
  "properties": {
    "iso:country":"US",
    "sg:address":"451 W Holt Ave",
    "sg:city":"Pomona",
    "sg:classifiers":[
        {
            "category":"Retail",
            "subcategory":"Auto Repair",
            "type":"Services"
        }
    ],
    "sg:phone":"+1 909 629 1133",
    "sg:postcode":"91768",
    "sg:province":"CA",
    "sg:tags":[
        "repairing",
        "automobile"
    ],
    "wof:name":"Anderson's Automotive",
    "wof:placetype":"venue"
},
  "geometry": {"coordinates":[-117.755597,34.062323],"type":"Point"}
}