{
  "type": "Feature",
  "properties": {
    "iso:country":"US",
    "sg:address":"1313 Beverly Dr",
    "sg:city":"Modesto",
    "sg:classifiers":[
        {
            "category":"Government",
            "subcategory":"Fire Station",
            "type":"Public Place"
        }
    ],
    "sg:phone":"+1 209 523 1129",
    "sg:postcode":"95351",
    "sg:province":"CA",
    "sg:tags":[
        "protection"
    ],
    "wof:name":"Burbank Paradise Fire Dept ( )",
    "wof:placetype":"venue"
},
  "geometry": {"coordinates":[-121.027904,37.621685],"type":"Point"}
}