{
  "type": "Feature",
  "properties": {
    "addr:full":"1313 Beverly Dr Modesto CA 95351",
    "addr:housenumber":"1313",
    "addr:postcode":"ca 95351",
    "addr:street":"Beverly Dr",
    "iso:country":"US",
    "sg:address":"1313 Beverly Dr",
    "sg:city":"Modesto",
    "sg:classifiers":[
        {
            "category":"Government",
            "subcategory":"Fire Station",
            "type":"Public Place"
        }
    ],
    "sg:phone":"+1 209 523 1129",
    "sg:postcode":"95351",
    "sg:province":"CA",
    "sg:tags":[
        "protection"
    ],
    "wof:name":"Burbank Paradise Fire Dept ( )",
    "wof:placetype":"venue"
},
  "geometry": {"coordinates":[-121.02790400000001,37.621685],"type":"Point"}
}