{
  "type": "Feature",
  "properties": {
    "iso:country":"US",
    "sg:address":"15533 Bechard Ave",
    "sg:city":"Norwalk",
    "sg:classifiers":[
        {
            "category":"Retail",
            "subcategory":"Repair Shop",
            "type":"Services"
        }
    ],
    "sg:phone":"+1 562 802 2145",
    "sg:postcode":"90650",
    "sg:province":"CA",
    "sg:tags":[
        "equipment",
        "telephone",
        "system"
    ],
    "wof:name":"Unique Communications",
    "wof:placetype":"venue"
},
  "geometry": {"coordinates":[-118.062727,33.88917],"type":"Point"}
}