{
  "type": "Feature",
  "properties": {
    "addr:full":"362 Bell St Los Alamos CA 93440",
    "addr:housenumber":"362",
    "addr:postcode":"93440",
    "addr:street":"Bell St",
    "iso:country":"US",
    "sg:address":"362 Bell St",
    "sg:city":"Los Alamos",
    "sg:classifiers":[
        {
            "category":"Travel",
            "subcategory":"Hotels & Motels",
            "type":"Entertainment"
        }
    ],
    "sg:phone":"+1 805 344 2744",
    "sg:postcode":"93440",
    "sg:province":"CA",
    "wof:name":"1880 Union Hotel & Victorian",
    "wof:placetype":"venue"
},
  "geometry": {"coordinates":[-120.280304,34.744049],"type":"Point"}
}