{
  "type": "Feature",
  "properties": {
    "iso:country":"US",
    "sg:address":"478 Stockton Ave",
    "sg:city":"San Jose",
    "sg:classifiers":[
        {
            "category":"Shopping",
            "subcategory":"Clothing, Apparel, & Fashions",
            "type":"Retail Goods"
        }
    ],
    "sg:phone":"+1 408 947 1202",
    "sg:postcode":"95126",
    "sg:province":"CA",
    "sg:tags":[
        "uniform"
    ],
    "wof:name":"Between The Lines",
    "wof:placetype":"venue"
},
  "geometry": {"coordinates":[-121.909606,37.337188],"type":"Point"}
}