{
  "type": "Feature",
  "properties": {
    "iso:country":"US",
    "sg:address":"2185 E South St",
    "sg:city":"Long Beach",
    "sg:classifiers":[
        {
            "category":"Insurance",
            "subcategory":"Insurance Agent",
            "type":"Services"
        }
    ],
    "sg:phone":"+1 562 984 3000",
    "sg:postcode":"90805",
    "sg:province":"CA",
    "wof:name":"AIS",
    "wof:placetype":"venue"
},
  "geometry": {"coordinates":[-118.165927,33.860213],"type":"Point"}
}