{
  "type": "Feature",
  "properties": {
    "addr:full":"18992 Soledad Canyon Rd Canyon Country CA 91351",
    "addr:housenumber":"18992",
    "addr:postcode":"91351",
    "addr:street":"Soledad Canyon Rd",
    "iso:country":"US",
    "sg:address":"18992 Soledad Canyon Rd",
    "sg:city":"Canyon Country",
    "sg:classifiers":[
        {
            "category":"Professional",
            "subcategory":"Business Services",
            "type":"Services"
        }
    ],
    "sg:phone":"+1 661 251 7779",
    "sg:postcode":"91351",
    "sg:province":"CA",
    "wof:name":"Design Firm",
    "wof:placetype":"venue"
},
  "geometry": {"coordinates":[-118.467074,34.415585],"type":"Point"}
}