{
  "type": "Feature",
  "properties": {
    "iso:country":"US",
    "sg:address":"2631 Reservoir Ln",
    "sg:city":"Redding",
    "sg:classifiers":[
        {
            "category":"Organizations",
            "subcategory":"Religious Organization",
            "type":"Services"
        }
    ],
    "sg:phone":"+1 530 222 2148",
    "sg:postcode":"96002",
    "sg:province":"CA",
    "sg:tags":[
        "church"
    ],
    "wof:name":"Echoes Of Praise",
    "wof:placetype":"venue"
},
  "geometry": {"coordinates":[-122.345217,40.568168],"type":"Point"}
}