{
  "type": "Feature",
  "properties": {
    "addr:full":"202 E Main St San Jacinto CA 92583",
    "addr:housenumber":"202",
    "addr:postcode":"92583",
    "addr:street":"E Main St",
    "iso:country":"US",
    "sg:address":"202 E Main St",
    "sg:city":"San Jacinto",
    "sg:classifiers":[
        {
            "category":"Shopping",
            "subcategory":"Clothing, Apparel, & Fashions",
            "type":"Retail Goods"
        }
    ],
    "sg:phone":"+1 951 654 9877",
    "sg:postcode":"92583",
    "sg:province":"CA",
    "wof:name":"Mayra's Fashion",
    "wof:placetype":"venue"
},
  "geometry": {"coordinates":[-116.95662400000001,33.783851],"type":"Point"}
}