{
  "type": "Feature",
  "properties": {
    "iso:country":"US",
    "sg:address":"16801 Halsted St",
    "sg:city":"North Hills",
    "sg:classifiers":[
        {
            "category":"Wholesale",
            "subcategory":"Machinery & Supplies",
            "type":"Manufacturing & Wholesale Goods"
        }
    ],
    "sg:phone":"+1 818 894 3431",
    "sg:postcode":"91343",
    "sg:province":"CA",
    "sg:tags":[
        "equipment",
        "industrial"
    ],
    "wof:name":"California Wild Wear",
    "wof:placetype":"venue"
},
  "geometry": {"coordinates":[-118.499391,34.244628],"type":"Point"}
}