{
  "type": "Feature",
  "properties": {
    "iso:country":"US",
    "sg:address":"5079 N Maywood Ave",
    "sg:city":"Los Angeles",
    "sg:classifiers":[
        {
            "category":"Professional",
            "type":"Services"
        }
    ],
    "sg:phone":"+1 323 259 3050",
    "sg:postcode":"90041",
    "sg:province":"CA",
    "sg:tags":[
        "establishment"
    ],
    "wof:name":"V 8 Commercial Co Inc",
    "wof:placetype":"venue"
},
  "geometry": {"coordinates":[-118.211643,34.138557],"type":"Point"}
}