{
  "type": "Feature",
  "properties": {
    "iso:country":"US",
    "sg:address":"123 Grande Way Ste B",
    "sg:city":"Ridgecrest",
    "sg:classifiers":[
        {
            "category":"Personal",
            "subcategory":"Beauty Salon",
            "type":"Services"
        }
    ],
    "sg:phone":"+1 760 371 4849",
    "sg:postcode":"93555",
    "sg:province":"CA",
    "sg:tags":[
        "hair",
        "stylist"
    ],
    "wof:name":"Ladies Gentlemen",
    "wof:placetype":"venue"
},
  "geometry": {"coordinates":[-117.668779,35.621504],"type":"Point"}
}