{
  "type": "Feature",
  "properties": {
    "iso:country":"US",
    "sg:address":"2646 Palma Dr",
    "sg:city":"Ventura",
    "sg:classifiers":[
        {
            "category":"Manufacturing",
            "subcategory":"Printing",
            "type":"Manufacturing & Wholesale Goods"
        }
    ],
    "sg:phone":"+1 805 650 1787",
    "sg:postcode":"93003",
    "sg:province":"CA",
    "sg:tags":[
        "commercial"
    ],
    "wof:name":"Print Pros Promotional",
    "wof:placetype":"venue"
},
  "geometry": {"coordinates":[-119.227158,34.249637],"type":"Point"}
}