{
  "type": "Feature",
  "properties": {
    "addr:full":"13832 Meadowlark Ln Grass Valley CA 95945",
    "addr:housenumber":"13832",
    "addr:postcode":"95945",
    "addr:street":"Meadowlark Ln",
    "iso:country":"US",
    "sg:address":"13832 Meadowlark Ln",
    "sg:city":"Grass Valley",
    "sg:classifiers":[
        {
            "category":"Professional",
            "subcategory":"Management & Consulting",
            "type":"Services"
        }
    ],
    "sg:phone":"+1 530 272 7000",
    "sg:postcode":"95945",
    "sg:province":"CA",
    "sg:tags":[
        "consultant",
        "wine"
    ],
    "wof:name":"Stephen Burch Consulting",
    "wof:placetype":"venue"
},
  "geometry": {"coordinates":[-120.98519,39.194975],"type":"Point"}
}