{
  "type": "Feature",
  "properties": {
    "iso:country":"US",
    "sg:address":"1471 Holiday Ln",
    "sg:city":"Fairfield",
    "sg:classifiers":[
        {
            "category":"Sports & Exercise",
            "subcategory":"Gym",
            "type":"Entertainment"
        }
    ],
    "sg:phone":"+1 707 429 4363",
    "sg:postcode":"94534",
    "sg:province":"CA",
    "sg:tags":[
        "club",
        "health",
        "studio",
        "gymnasium"
    ],
    "sg:website":"www.solanoathleticclub.com",
    "wof:name":"Solano Athletic Clubs",
    "wof:placetype":"venue"
},
  "geometry": {"coordinates":[-122.065134,38.258538],"type":"Point"}
}