{
  "type": "Feature",
  "properties": {
    "addr:full":"856 4th St Santa Rosa CA 95404",
    "addr:housenumber":"856",
    "addr:postcode":"ca 95404",
    "addr:street":"4Th St",
    "iso:country":"US",
    "sg:address":"856 4th St",
    "sg:city":"Santa Rosa",
    "sg:classifiers":[
        {
            "category":"Professional",
            "subcategory":"Business Services",
            "type":"Services"
        }
    ],
    "sg:phone":"+1 707 546 6869",
    "sg:postcode":"95404",
    "sg:province":"CA",
    "sg:tags":[
        "translator",
        "interpreter"
    ],
    "wof:name":"Communique Interpreting Svc",
    "wof:placetype":"venue"
},
  "geometry": {"coordinates":[-122.70747,38.443442],"type":"Point"}
}