{
  "type": "Feature",
  "properties": {
    "iso:country":"US",
    "sg:address":"138 E 231st St",
    "sg:city":"Carson",
    "sg:classifiers":[
        {
            "category":"Professional",
            "subcategory":"Lawyer & Legal Services",
            "type":"Services"
        }
    ],
    "sg:phone":"+1 310 427 1774",
    "sg:postcode":"90745",
    "sg:province":"CA",
    "sg:tags":[
        "plan"
    ],
    "wof:name":"Small Claims Svc",
    "wof:placetype":"venue"
},
  "geometry": {"coordinates":[-118.270874,33.815752],"type":"Point"}
}