{
  "type": "Feature",
  "properties": {
    "addr:full":"4680 Mission St San Francisco CA 94112",
    "addr:housenumber":"4680",
    "addr:postcode":"94112",
    "addr:street":"Mission St",
    "iso:country":"US",
    "sg:address":"4680 Mission St",
    "sg:city":"San Francisco",
    "sg:classifiers":[
        {
            "category":"Professional",
            "subcategory":"Business Services",
            "type":"Services"
        }
    ],
    "sg:phone":"+1 415 254 3109",
    "sg:postcode":"94112",
    "sg:province":"CA",
    "sg:tags":[
        "consultant",
        "production",
        "music"
    ],
    "wof:name":"Sonic House",
    "wof:placetype":"venue"
},
  "geometry": {"coordinates":[-122.435672,37.723784],"type":"Point"}
}