{
  "type": "Feature",
  "properties": {
    "iso:country":"US",
    "sg:address":"3317 W Beverly Blvd",
    "sg:city":"Montebello",
    "sg:classifiers":[
        {
            "category":"Professional",
            "subcategory":"Management & Consulting",
            "type":"Services"
        }
    ],
    "sg:phone":"+1 323 724 4977",
    "sg:postcode":"90640",
    "sg:province":"CA",
    "sg:tags":[
        "consultant",
        "training"
    ],
    "wof:name":"Manna Truck Training",
    "wof:placetype":"venue"
},
  "geometry": {"coordinates":[-118.141301,34.024621],"type":"Point"}
}