{
  "type": "Feature",
  "properties": {
    "addr:full":"7819 Cll Lomas Carlsbad CA 92009",
    "addr:postcode":"7819;92009",
    "addr:street":"Cll Lomas",
    "iso:country":"US",
    "sg:address":"7819 Cll Lomas",
    "sg:city":"Carlsbad",
    "sg:classifiers":[
        {
            "category":"Manufacturing",
            "subcategory":"Metals",
            "type":"Manufacturing & Wholesale Goods"
        }
    ],
    "sg:phone":"+1 760 479 0505",
    "sg:postcode":"92009",
    "sg:province":"CA",
    "sg:tags":[
        "secondary",
        "producer",
        "nonferrous"
    ],
    "wof:name":"Big Bronze LLC",
    "wof:placetype":"venue"
},
  "geometry": {"coordinates":[-117.237813,33.076676],"type":"Point"}
}