{
  "type": "Feature",
  "properties": {
    "addr:full":"5175 Hollywood Blvd Los Angeles CA 90027",
    "addr:housenumber":"5175",
    "addr:postcode":"90027",
    "addr:street":"Hollywood Blvd",
    "iso:country":"US",
    "sg:address":"5175 Hollywood Blvd",
    "sg:city":"Los Angeles",
    "sg:classifiers":[
        {
            "category":"Manufacturing",
            "subcategory":"Leather Goods",
            "type":"Manufacturing & Wholesale Goods"
        }
    ],
    "sg:phone":"+1 323 665 2666",
    "sg:postcode":"90027",
    "sg:province":"CA",
    "sg:tags":[
        "custom",
        "insole",
        "shoe",
        "mfg"
    ],
    "wof:name":"Globus Foot Orthotics",
    "wof:placetype":"venue"
},
  "geometry": {"coordinates":[-118.302695,34.101828],"type":"Point"}
}