{
  "type": "Feature",
  "properties": {
    "iso:country":"US",
    "sg:address":"11784 Firestone Blvd",
    "sg:city":"Norwalk",
    "sg:classifiers":[
        {
            "category":"Health Services",
            "subcategory":"Doctor",
            "type":"Services"
        },
        {
            "category":"Education",
            "subcategory":"University",
            "type":"Public Place"
        }
    ],
    "sg:phone":"+1 562 462 9235",
    "sg:postcode":"90650",
    "sg:province":"CA",
    "sg:tags":[
        "college"
    ],
    "wof:name":"University Physicians",
    "wof:placetype":"venue"
},
  "geometry": {"coordinates":[-118.231163,33.912746],"type":"Point"}
}