{
  "type": "Feature",
  "properties": {
    "addr:full":"9901 Indiana Ave Riverside CA 92503",
    "addr:housenumber":"9901",
    "addr:postcode":"92503",
    "addr:street":"Indiana Ave",
    "iso:country":"US",
    "sg:address":"9901 Indiana Ave",
    "sg:city":"Riverside",
    "sg:classifiers":[
        {
            "category":"Utilities",
            "subcategory":"Mobile Phone",
            "type":"Services"
        }
    ],
    "sg:phone":"+1 951 353 2437",
    "sg:postcode":"92503",
    "sg:province":"CA",
    "sg:tags":[
        "paging",
        "pager"
    ],
    "wof:name":"Verizon",
    "wof:placetype":"venue"
},
  "geometry": {"coordinates":[-117.452398,33.907877],"type":"Point"}
}