{
  "type": "Feature",
  "properties": {
    "addr:full":"7970 Oak Ave Citrus Heights CA 95610",
    "addr:housenumber":"7970",
    "addr:postcode":"95610",
    "addr:street":"Oak Ave",
    "iso:country":"US",
    "sg:address":"7970 Oak Ave",
    "sg:city":"Citrus Heights",
    "sg:classifiers":[
        {
            "category":"Organizations",
            "subcategory":"Non-profit Organization",
            "type":"Services"
        }
    ],
    "sg:phone":"+1 916 721 9699",
    "sg:postcode":"95610",
    "sg:province":"CA",
    "sg:tags":[
        "information",
        "alcoholism",
        "treatment"
    ],
    "wof:name":"Oak House Inc",
    "wof:placetype":"venue"
},
  "geometry": {"coordinates":[-121.26774899999999,38.70026],"type":"Point"}
}