{
  "type": "Feature",
  "properties": {
    "iso:country":"US",
    "sg:address":"158 Eastridge Mall",
    "sg:city":"San Jose",
    "sg:classifiers":[
        {
            "category":"Shopping",
            "subcategory":"Gifts & Souvenirs",
            "type":"Retail Goods"
        }
    ],
    "sg:phone":"+1 408 270 3341",
    "sg:postcode":"95122",
    "sg:province":"CA",
    "sg:tags":[
        "shop"
    ],
    "wof:name":"Spencer Gifts",
    "wof:placetype":"venue"
},
  "geometry": {"coordinates":[-121.81281,37.329241],"type":"Point"}
}