{
  "type": "Feature",
  "properties": {
    "addr:full":"315 Arroyo Vis Fallbrook CA 92028",
    "addr:housenumber":"315",
    "addr:postcode":"92028",
    "addr:street":"Arroyo Vis",
    "iso:country":"US",
    "sg:address":"315 Arroyo Vis",
    "sg:city":"Fallbrook",
    "sg:classifiers":[
        {
            "category":"Shopping",
            "subcategory":"Optical Goods",
            "type":"Retail Goods"
        }
    ],
    "sg:phone":"+1 760 451 0256",
    "sg:postcode":"92028",
    "sg:province":"CA",
    "wof:name":"Details",
    "wof:placetype":"venue"
},
  "geometry": {"coordinates":[-117.23157,33.377733],"type":"Point"}
}