{
  "type": "Feature",
  "properties": {
    "addr:full":"5728 Merriewood Dr Oakland CA 94611",
    "addr:postcode":"5728;94611",
    "addr:street":"Merriewood Dr",
    "iso:country":"US",
    "sg:address":"5728 Merriewood Dr",
    "sg:city":"Oakland",
    "sg:classifiers":[
        {
            "category":"Wholesale",
            "subcategory":"Electrical",
            "type":"Manufacturing & Wholesale Goods"
        }
    ],
    "sg:phone":"+1 510 655 9085",
    "sg:postcode":"94611",
    "sg:province":"CA",
    "sg:tags":[
        "electronic"
    ],
    "wof:name":"Quick Silver Technology",
    "wof:placetype":"venue"
},
  "geometry": {"coordinates":[-122.21411000000001,37.835946],"type":"Point"}
}