{
  "type": "Feature",
  "properties": {
    "iso:country":"US",
    "sg:address":"750 E Green St Ste 201",
    "sg:city":"Pasadena",
    "sg:classifiers":[
        {
            "category":"Banks & Credit Unions",
            "subcategory":"Financial Services",
            "type":"Services"
        }
    ],
    "sg:phone":"+1 626 585 1331",
    "sg:postcode":"91101",
    "sg:province":"CA",
    "sg:tags":[
        "broker",
        "mortgage"
    ],
    "wof:name":"American Frontier Financial Group",
    "wof:placetype":"venue"
},
  "geometry": {"coordinates":[-118.135002,34.144501],"type":"Point"}
}