{
  "type": "Feature",
  "properties": {
    "iso:country":"US",
    "sg:address":"443 Gateway Dr",
    "sg:city":"Pacifica",
    "sg:classifiers":[
        {
            "category":"Professional",
            "type":"Services"
        }
    ],
    "sg:phone":"+1 415 333 8786",
    "sg:postcode":"94044",
    "sg:province":"CA",
    "sg:tags":[
        "art",
        "restoring"
    ],
    "wof:name":"Midwest Of Cannon Falls",
    "wof:placetype":"venue"
},
  "geometry": {"coordinates":[-122.47611999999999,37.657466],"type":"Point"}
}