{
  "type": "Feature",
  "properties": {
    "iso:country":"US",
    "sg:address":"23470 Olive Wood Plaza Dr",
    "sg:city":"Moreno Valley",
    "sg:classifiers":[
        {
            "category":"Education",
            "subcategory":"Special Training",
            "type":"Public Place"
        }
    ],
    "sg:phone":"+1 951 243 0543",
    "sg:postcode":"92553",
    "sg:province":"CA",
    "sg:tags":[
        "center"
    ],
    "wof:name":"Institute For American Edctn",
    "wof:placetype":"venue"
},
  "geometry": {"coordinates":[-117.255943,33.939359],"type":"Point"}
}