{
  "type": "Feature",
  "properties": {
    "addr:full":"5431 Radford Ave Valley Village CA 91607",
    "addr:housenumber":"5431",
    "addr:postcode":"91607",
    "addr:street":"Radford Ave",
    "iso:country":"US",
    "sg:address":"5431 Radford Ave",
    "sg:city":"Valley Village",
    "sg:classifiers":[
        {
            "category":"Building & Trades",
            "subcategory":"Landscaping Services",
            "type":"Services"
        }
    ],
    "sg:phone":"+1 818 509 9573",
    "sg:postcode":"91607",
    "sg:province":"CA",
    "sg:tags":[
        "landscape",
        "contractor"
    ],
    "wof:name":"Native Designs",
    "wof:placetype":"venue"
},
  "geometry": {"coordinates":[-118.392207,34.16982],"type":"Point"}
}