{
  "type": "Feature",
  "properties": {
    "addr:full":"1800 Fairburn Ave Ste 211 Los Angeles CA 90025",
    "addr:housenumber":"1800",
    "addr:postcode":"90025",
    "addr:street":"Fairburn Ave Ste 211",
    "iso:country":"US",
    "sg:address":"1800 Fairburn Ave Ste 211",
    "sg:city":"Los Angeles",
    "sg:classifiers":[
        {
            "category":"Health Services",
            "subcategory":"Doctor",
            "type":"Services"
        }
    ],
    "sg:phone":"+1 310 475 5532",
    "sg:postcode":"90025",
    "sg:province":"CA",
    "sg:tags":[
        "psychiatrist"
    ],
    "wof:name":"Haas Neil B MD",
    "wof:placetype":"venue"
},
  "geometry": {"coordinates":[-118.42800099999999,34.054798],"type":"Point"}
}