{
  "type": "Feature",
  "properties": {
    "addr:full":"699 Highland Dr Ojai CA 93023",
    "addr:housenumber":"699",
    "addr:postcode":"93023",
    "addr:street":"Highland Dr",
    "iso:country":"US",
    "sg:address":"699 Highland Dr",
    "sg:city":"Ojai",
    "sg:classifiers":[
        {
            "category":"Education",
            "subcategory":"Special Training",
            "type":"Public Place"
        }
    ],
    "sg:phone":"+1 805 649 5367",
    "sg:postcode":"93023",
    "sg:province":"CA",
    "sg:tags":[
        "self",
        "motivational",
        "improvement"
    ],
    "sg:website":"www.connectingup.com",
    "wof:name":"Gateways Fulfillment",
    "wof:placetype":"venue"
},
  "geometry": {"coordinates":[-119.291791,34.419984],"type":"Point"}
}