{
  "type": "Feature",
  "properties": {
    "iso:country":"US",
    "sg:address":"538 Jackson Ave",
    "sg:city":"Redwood City",
    "sg:classifiers":[
        {
            "category":"Manufacturing",
            "subcategory":"Printing",
            "type":"Manufacturing & Wholesale Goods"
        }
    ],
    "sg:phone":"+1 415 254 7321",
    "sg:postcode":"94061",
    "sg:province":"CA",
    "sg:tags":[
        "printer",
        "laser",
        "supply"
    ],
    "wof:name":"Print Smart",
    "wof:placetype":"venue"
},
  "geometry": {"coordinates":[-122.23381999999999,37.478517],"type":"Point"}
}