{
  "type": "Feature",
  "properties": {
    "iso:country":"US",
    "sg:address":"6877 Gloria St",
    "sg:city":"Chino",
    "sg:classifiers":[
        {
            "category":"Professional",
            "type":"Services"
        }
    ],
    "sg:phone":"+1 909 591 3709",
    "sg:postcode":"91710",
    "sg:province":"CA",
    "wof:name":"J and M Cattle LLC",
    "wof:placetype":"venue"
},
  "geometry": {"coordinates":[-117.654517,34.017057],"type":"Point"}
}