{
  "type": "Feature",
  "properties": {
    "iso:country":"US",
    "sg:address":"9621 Clearbrook Dr",
    "sg:city":"Huntington Beach",
    "sg:classifiers":[
        {
            "category":"Manufacturing",
            "subcategory":"Aerospace",
            "type":"Manufacturing & Wholesale Goods"
        }
    ],
    "sg:phone":"+1 714 841 5518",
    "sg:postcode":"92646",
    "sg:province":"CA",
    "sg:tags":[
        "equipment",
        "aircraft",
        "parts",
        "component",
        "mfg"
    ],
    "wof:name":"Calair International Inc",
    "wof:placetype":"venue"
},
  "geometry": {"coordinates":[-117.95947,33.649188],"type":"Point"}
}