{
  "type": "Feature",
  "properties": {
    "addr:full":"645 W Central Ave Lompoc CA 93436",
    "addr:housenumber":"645",
    "addr:postcode":"93436",
    "addr:street":"W Central Ave",
    "iso:country":"US",
    "sg:address":"645 W Central Ave",
    "sg:city":"Lompoc",
    "sg:classifiers":[
        {
            "category":"Banks & Credit Unions",
            "subcategory":"Bank",
            "type":"Services"
        }
    ],
    "sg:phone":"+1 805 736 8541",
    "sg:postcode":"93436",
    "sg:province":"CA",
    "sg:website":"www.wellsfargo.com",
    "wof:name":"Wells Fargo Bank",
    "wof:placetype":"venue"
},
  "geometry": {"coordinates":[-120.467795,34.661035],"type":"Point"}
}