{
  "type": "Feature",
  "properties": {
    "iso:country":"US",
    "sg:address":"1803 1/2 Lomita Blvd",
    "sg:city":"Lomita",
    "sg:classifiers":[
        {
            "category":"Personal",
            "subcategory":"Barber",
            "type":"Services"
        },
        {
            "category":"Personal",
            "subcategory":"Piercing",
            "type":"Services"
        }
    ],
    "sg:phone":"+1 310 530 0373",
    "sg:postcode":"90717",
    "sg:province":"CA",
    "wof:name":"Lucky Unisex Barber & Beauty Salon",
    "wof:placetype":"venue"
},
  "geometry": {"coordinates":[-118.309348,33.797958],"type":"Point"}
}