{
  "type": "Feature",
  "properties": {
    "iso:country":"US",
    "sg:address":"6812 San Juan St",
    "sg:city":"Paramount",
    "sg:classifiers":[
        {
            "category":"Building & Trades",
            "subcategory":"Construction",
            "type":"Services"
        }
    ],
    "sg:phone":"+1 562 602 0960",
    "sg:postcode":"90723",
    "sg:province":"CA",
    "sg:tags":[
        "concrete",
        "contractor"
    ],
    "wof:name":"Next Level Concrete Pumping",
    "wof:placetype":"venue"
},
  "geometry": {"coordinates":[-118.177633,33.901174],"type":"Point"}
}