{
  "type": "Feature",
  "properties": {
    "addr:full":"583 el Cajon Blvd El Cajon CA 92020",
    "addr:housenumber":"583",
    "addr:postcode":"92020",
    "addr:street":"El Cajon Blvd",
    "iso:country":"US",
    "sg:address":"583 el Cajon Blvd",
    "sg:city":"El Cajon",
    "sg:classifiers":[
        {
            "category":"Building & Trades",
            "subcategory":"Construction",
            "type":"Services"
        }
    ],
    "sg:phone":"+1 619 444 4329",
    "sg:postcode":"92020",
    "sg:province":"CA",
    "sg:tags":[
        "fence",
        "contractor"
    ],
    "wof:name":"Alpha Fence",
    "wof:placetype":"venue"
},
  "geometry": {"coordinates":[-116.972865,32.789663],"type":"Point"}
}