{
  "type": "Feature",
  "properties": {
    "iso:country":"US",
    "sg:address":"502 Giuseppe Ct",
    "sg:city":"Roseville",
    "sg:classifiers":[
        {
            "category":"Building & Trades",
            "subcategory":"Construction",
            "type":"Services"
        }
    ],
    "sg:phone":"+1 916 782 4664",
    "sg:postcode":"95678",
    "sg:province":"CA",
    "sg:tags":[
        "roofing",
        "contractor"
    ],
    "wof:name":"Summit Roofing",
    "wof:placetype":"venue"
},
  "geometry": {"coordinates":[-121.301253,38.730837],"type":"Point"}
}