{
  "type": "Feature",
  "properties": {
    "addr:full":"2570 Bodega Ave Petaluma CA 94952",
    "addr:housenumber":"2570",
    "addr:postcode":"94952",
    "addr:street":"Bodega Ave",
    "iso:country":"US",
    "sg:address":"2570 Bodega Ave",
    "sg:city":"Petaluma",
    "sg:classifiers":[
        {
            "category":"Manufacturing",
            "subcategory":"Signs",
            "type":"Manufacturing & Wholesale Goods"
        }
    ],
    "sg:phone":"+1 707 769 0639",
    "sg:postcode":"94952",
    "sg:province":"CA",
    "sg:tags":[
        "specialty",
        "mfg"
    ],
    "wof:name":"Percell Signs",
    "wof:placetype":"venue"
},
  "geometry": {"coordinates":[-122.673114,38.238404],"type":"Point"}
}