{
  "type": "Feature",
  "properties": {
    "addr:full":"900 Vernon Way # 101 El Cajon CA 92020",
    "addr:housenumber":"900",
    "addr:postcode":"92020",
    "addr:street":"Vernon Way # 101",
    "iso:country":"US",
    "sg:address":"900 Vernon Way # 101",
    "sg:city":"El Cajon",
    "sg:classifiers":[
        {
            "category":"Shopping",
            "subcategory":"Pets & Pet Supplies",
            "type":"Retail Goods"
        }
    ],
    "sg:phone":"+1 619 258 1914",
    "sg:postcode":"92020",
    "sg:province":"CA",
    "sg:website":"www.solidgoldhealth.com/",
    "wof:name":"Solid Gold Health Products",
    "wof:placetype":"venue"
},
  "geometry": {"coordinates":[-116.97399900000001,32.812],"type":"Point"}
}