{
  "type": "Feature",
  "properties": {
    "addr:full":"996 Minnesota Ave San Jose CA 95125",
    "addr:housenumber":"996",
    "addr:postcode":"95125",
    "addr:street":"Minnesota Ave",
    "iso:country":"US",
    "sg:address":"996 Minnesota Ave",
    "sg:city":"San Jose",
    "sg:classifiers":[
        {
            "category":"Professional",
            "type":"Services"
        }
    ],
    "sg:phone":"+1 408 280 7861",
    "sg:postcode":"95125",
    "sg:province":"CA",
    "wof:name":"Ray Branchflower",
    "wof:placetype":"venue"
},
  "geometry": {"coordinates":[-121.894317,37.305361],"type":"Point"}
}