{
  "type": "Feature",
  "properties": {
    "iso:country":"US",
    "sg:address":"156 S Broadway St",
    "sg:city":"Turlock",
    "sg:classifiers":[
        {
            "category":"Government",
            "subcategory":"Office",
            "type":"Public Place"
        }
    ],
    "sg:phone":"+1 209 668 5640",
    "sg:postcode":"95380",
    "sg:province":"CA",
    "sg:tags":[
        "village"
    ],
    "wof:name":"Turlock Planning Dept",
    "wof:placetype":"venue"
},
  "geometry": {"coordinates":[-120.846475,37.492222],"type":"Point"}
}