{
  "type": "Feature",
  "properties": {
    "addr:full":"327 Harsin Ln Santa Maria CA 93455",
    "addr:housenumber":"327",
    "addr:postcode":"93455",
    "addr:street":"Harsin Ln",
    "iso:country":"US",
    "sg:address":"327 Harsin Ln",
    "sg:city":"Santa Maria",
    "sg:classifiers":[
        {
            "category":"Building & Trades",
            "subcategory":"Plumbing",
            "type":"Services"
        }
    ],
    "sg:phone":"+1 805 937 9483",
    "sg:postcode":"93455",
    "sg:province":"CA",
    "sg:tags":[
        "plumbing",
        "contractor"
    ],
    "wof:name":"CB Plumbing Inc",
    "wof:placetype":"venue"
},
  "geometry": {"coordinates":[-120.43365,34.890204],"type":"Point"}
}