{
  "type": "Feature",
  "properties": {
    "iso:country":"US",
    "sg:address":"459 1/2 N Fairfax Ave",
    "sg:city":"Los Angeles",
    "sg:classifiers":[
        {
            "category":"Personal",
            "subcategory":"Beauty Salon",
            "type":"Services"
        },
        {
            "category":"Personal",
            "subcategory":"Barber",
            "type":"Services"
        }
    ],
    "sg:phone":"+1 323 653 1299",
    "sg:postcode":"90036",
    "sg:province":"CA",
    "sg:tags":[
        "hair",
        "makeup",
        "artist"
    ],
    "wof:name":"Goo Salon",
    "wof:placetype":"venue"
},
  "geometry": {"coordinates":[-118.361614,34.079889],"type":"Point"}
}