{
  "type": "Feature",
  "properties": {
    "iso:country":"US",
    "sg:address":"1015 E Oak St",
    "sg:city":"Stockton",
    "sg:classifiers":[
        {
            "category":"Manufacturing",
            "subcategory":"Retail Goods",
            "type":"Manufacturing & Wholesale Goods"
        }
    ],
    "sg:phone":"+1 209 464 0294",
    "sg:postcode":"95205",
    "sg:province":"CA",
    "sg:tags":[
        "product",
        "mfg"
    ],
    "wof:name":"Magic Eyes",
    "wof:placetype":"venue"
},
  "geometry": {"coordinates":[-121.279704,37.96075],"type":"Point"}
}