{
  "type": "Feature",
  "properties": {
    "iso:country":"US",
    "sg:address":"8555 W Sunset Blvd",
    "sg:city":"West Hollywood",
    "sg:classifiers":[
        {
            "category":"Restaurant",
            "type":"Food & Drink"
        }
    ],
    "sg:phone":"+1 310 652 7008",
    "sg:postcode":"90069",
    "sg:province":"CA",
    "sg:tags":[
        "mexican"
    ],
    "sg:website":"www.poquitomas.com/",
    "wof:name":"Poquito Mas",
    "wof:placetype":"venue"
},
  "geometry": {"coordinates":[-118.378282,34.093311],"type":"Point"}
}