{
  "type": "Feature",
  "properties": {
    "addr:full":"2515 S H St Bakersfield CA 93304",
    "addr:housenumber":"2515",
    "addr:postcode":"93304",
    "addr:street":"S H St",
    "iso:country":"US",
    "sg:address":"2515 S H St",
    "sg:city":"Bakersfield",
    "sg:classifiers":[
        {
            "category":"Restaurant",
            "type":"Food & Drink"
        }
    ],
    "sg:menulink":"http://www.allmenus.com/ca/bakersfield/87695-little-caesars-pizza/menu/",
    "sg:phone":"+1 661 397 5555",
    "sg:postcode":"93304",
    "sg:province":"CA",
    "sg:tags":[
        "american",
        "pizza"
    ],
    "wof:name":"Little Caesar's Pizza",
    "wof:placetype":"venue"
},
  "geometry": {"coordinates":[-119.021314,35.331373],"type":"Point"}
}