{
  "type": "Feature",
  "properties": {
    "addr:full":"1400 Shattuck Ave Berkeley CA 94709",
    "addr:housenumber":"1400",
    "addr:postcode":"94709",
    "addr:street":"Shattuck Ave",
    "iso:country":"US",
    "sg:address":"1400 Shattuck Ave",
    "sg:city":"Berkeley",
    "sg:classifiers":[
        {
            "category":"Insurance",
            "subcategory":"Title Insurance",
            "type":"Services"
        },
        {
            "category":"Real Estate",
            "subcategory":"Real Estate Services",
            "type":"Services"
        }
    ],
    "sg:phone":"+1 510 644 8088",
    "sg:postcode":"94709",
    "sg:province":"CA",
    "sg:tags":[
        "company",
        "carrier"
    ],
    "wof:name":"Placer Title Co",
    "wof:placetype":"venue"
},
  "geometry": {"coordinates":[-122.269367,37.881074],"type":"Point"}
}