{
  "type": "Feature",
  "properties": {
    "addr:full":"6205 Cazadero Hwy Cazadero CA 95421",
    "addr:housenumber":"6205",
    "addr:postcode":"95421",
    "addr:street":"Cazadero Hwy",
    "iso:country":"US",
    "sg:address":"6205 Cazadero Hwy",
    "sg:city":"Cazadero",
    "sg:classifiers":[
        {
            "category":"Organizations",
            "subcategory":"Religious Organization",
            "type":"Services"
        }
    ],
    "sg:phone":"+1 707 632 5798",
    "sg:postcode":"95421",
    "sg:province":"CA",
    "sg:tags":[
        "church"
    ],
    "wof:name":"Cazadero Community Church",
    "wof:placetype":"venue"
},
  "geometry": {"coordinates":[-123.088531,38.535955],"type":"Point"}
}