{
  "type": "Feature",
  "properties": {
    "iso:country":"US",
    "sg:address":"11552 Paloma Ave",
    "sg:city":"Garden Grove",
    "sg:classifiers":[
        {
            "category":"Manufacturing",
            "subcategory":"Retail Goods",
            "type":"Manufacturing & Wholesale Goods"
        }
    ],
    "sg:phone":"+1 714 530 0049",
    "sg:postcode":"92843",
    "sg:province":"CA",
    "sg:tags":[
        "product",
        "mfg"
    ],
    "wof:name":"Nothing But Beads",
    "wof:placetype":"venue"
},
  "geometry": {"coordinates":[-117.925114,33.770136],"type":"Point"}
}