{
  "type": "Feature",
  "properties": {
    "iso:country":"US",
    "sg:address":"1500 E Rosecrans Ave",
    "sg:city":"Compton",
    "sg:classifiers":[
        {
            "category":"Recreation",
            "type":"Entertainment"
        }
    ],
    "sg:phone":"+1 310 635 3484",
    "sg:postcode":"90221",
    "sg:province":"CA",
    "sg:tags":[
        "executive"
    ],
    "wof:name":"William Love Swimming Pool",
    "wof:placetype":"venue"
},
  "geometry": {"coordinates":[-118.205016,33.90349],"type":"Point"}
}