{
  "type": "Feature",
  "properties": {
    "addr:full":"5299 College Ave Ste C3 Oakland CA 94618",
    "addr:housenumber":"5299",
    "addr:postcode":"94618",
    "addr:street":"College Ave Ste C3",
    "iso:country":"US",
    "sg:address":"5299 College Ave Ste C3",
    "sg:city":"Oakland",
    "sg:classifiers":[
        {
            "category":"Manufacturing",
            "subcategory":"Buildings",
            "type":"Manufacturing & Wholesale Goods"
        },
        {
            "category":"Building & Trades",
            "subcategory":"Construction",
            "type":"Services"
        }
    ],
    "sg:phone":"+1 510 883 9099",
    "sg:postcode":"94618",
    "sg:province":"CA",
    "sg:tags":[
        "home",
        "builder",
        "contractor"
    ],
    "wof:name":"Ace Construction & Development Corporation",
    "wof:placetype":"venue"
},
  "geometry": {"coordinates":[-122.251296,37.837921],"type":"Point"}
}