{
  "type": "Feature",
  "properties": {
    "addr:full":"6995 Buzz Tail Rd El Dorado CA 95623",
    "addr:postcode":"6995;95623",
    "addr:street":"Buzz Tail Rd",
    "iso:country":"US",
    "sg:address":"6995 Buzz Tail Rd",
    "sg:city":"El Dorado",
    "sg:classifiers":[
        {
            "category":"Retail",
            "subcategory":"Animal Services",
            "type":"Services"
        }
    ],
    "sg:phone":"+1 530 295 3439",
    "sg:postcode":"95623",
    "sg:province":"CA",
    "sg:tags":[
        "training",
        "dog"
    ],
    "sg:website":"www.prok9.com",
    "wof:name":"Pro K-9",
    "wof:placetype":"venue"
},
  "geometry": {"coordinates":[-120.832144,38.647277],"type":"Point"}
}