{
  "type": "Feature",
  "properties": {
    "iso:country":"US",
    "sg:address":"915 Foothill Blvd",
    "sg:city":"La Canada Fltrdg",
    "sg:classifiers":[
        {
            "category":"Utilities",
            "subcategory":"Mobile Phone",
            "type":"Services"
        }
    ],
    "sg:phone":"+1 818 952 5222",
    "sg:postcode":"91011",
    "sg:province":"CA",
    "sg:tags":[
        "telephone",
        "cellular"
    ],
    "wof:name":"Wireless Studio",
    "wof:placetype":"venue"
},
  "geometry": {"coordinates":[-118.19861400000001,34.203707],"type":"Point"}
}