{
  "type": "Feature",
  "properties": {
    "iso:country":"US",
    "sg:address":"713 Main St",
    "sg:city":"Susanville",
    "sg:classifiers":[
        {
            "category":"Personal",
            "subcategory":"Beauty Salon",
            "type":"Services"
        }
    ],
    "sg:phone":"+1 530 257 5959",
    "sg:postcode":"96130",
    "sg:province":"CA",
    "wof:name":"Shear Elegance",
    "wof:placetype":"venue"
},
  "geometry": {"coordinates":[-120.661691,40.41858],"type":"Point"}
}