{
  "type": "Feature",
  "properties": {
    "iso:country":"US",
    "sg:address":"1500 Southgate Ave",
    "sg:city":"Daly City",
    "sg:classifiers":[
        {
            "category":"Health Services",
            "subcategory":"Doctor",
            "type":"Services"
        }
    ],
    "sg:phone":"+1 650 991 7374",
    "sg:postcode":"94015",
    "sg:province":"CA",
    "sg:tags":[
        "dentist"
    ],
    "wof:name":"Emegio G Beronilla DDS",
    "wof:placetype":"venue"
},
  "geometry": {"coordinates":[-122.473344,37.675826],"type":"Point"}
}