{
  "type": "Feature",
  "properties": {
    "addr:full":"24639 Foresthill Rd Foresthill CA 95631",
    "addr:postcode":"24639;95631",
    "addr:street":"Foresthill Rd",
    "iso:country":"US",
    "sg:address":"24639 Foresthill Rd",
    "sg:city":"Foresthill",
    "sg:classifiers":[
        {
            "category":"Building & Trades",
            "subcategory":"Pest Control",
            "type":"Services"
        }
    ],
    "sg:phone":"+1 530 367 4498",
    "sg:postcode":"95631",
    "sg:province":"CA",
    "wof:name":"Cedar Rose Pest Control",
    "wof:placetype":"venue"
},
  "geometry": {"coordinates":[-120.814627,39.020887],"type":"Point"}
}