{
  "type": "Feature",
  "properties": {
    "iso:country":"US",
    "sg:address":"980 de Soto Ln",
    "sg:city":"Foster City",
    "sg:classifiers":[
        {
            "category":"Real Estate",
            "subcategory":"Architect",
            "type":"Services"
        }
    ],
    "sg:phone":"+1 650 345 3828",
    "sg:postcode":"94404",
    "sg:province":"CA",
    "sg:tags":[
        "architectural"
    ],
    "wof:name":"Mark A Moritz & Assoc",
    "wof:placetype":"venue"
},
  "geometry": {"coordinates":[-122.269195,37.551227],"type":"Point"}
}