{
  "type": "Feature",
  "properties": {
    "addr:full":"4041 Davana Rd Sherman Oaks CA 91423",
    "addr:housenumber":"4041",
    "addr:postcode":"91423",
    "addr:street":"Davana Rd",
    "iso:country":"US",
    "sg:address":"4041 Davana Rd",
    "sg:city":"Sherman Oaks",
    "sg:classifiers":[
        {
            "category":"Manufacturing",
            "subcategory":"Paper Products",
            "type":"Manufacturing & Wholesale Goods"
        }
    ],
    "sg:phone":"+1 818 905 7665",
    "sg:postcode":"91423",
    "sg:province":"CA",
    "sg:tags":[
        "stationery"
    ],
    "wof:name":"Saltwater Inc",
    "wof:placetype":"venue"
},
  "geometry": {"coordinates":[-118.434006,34.142426],"type":"Point"}
}