{
  "type": "Feature",
  "properties": {
    "addr:full":"401 W La Veta Ave Apt 115 Orange CA 92866",
    "addr:housenumber":"401;115",
    "addr:postcode":"92866",
    "addr:street":"W La Veta Ave Apt",
    "iso:country":"US",
    "sg:address":"401 W La Veta Ave Apt 115",
    "sg:city":"Orange",
    "sg:classifiers":[
        {
            "category":"Real Estate",
            "subcategory":"Real Estate Operator",
            "type":"Services"
        }
    ],
    "sg:phone":"+1 714 997 0982",
    "sg:postcode":"92866",
    "sg:province":"CA",
    "sg:tags":[
        "apartment"
    ],
    "wof:name":"La Veta Grand Apartments",
    "wof:placetype":"venue"
},
  "geometry": {"coordinates":[-117.856003,33.780602],"type":"Point"}
}