{
  "type": "Feature",
  "properties": {
    "iso:country":"US",
    "sg:address":"4114 W Ave J",
    "sg:city":"Lancaster",
    "sg:classifiers":[
        {
            "category":"Professional",
            "type":"Services"
        }
    ],
    "sg:phone":"+1 661 718 0870",
    "sg:postcode":"93536",
    "sg:province":"CA",
    "sg:tags":[
        "establishment"
    ],
    "wof:name":"Arial Hathaway Enterprises",
    "wof:placetype":"venue"
},
  "geometry": {"coordinates":[-118.20281199999999,34.689232],"type":"Point"}
}