{
  "type": "Feature",
  "properties": {
    "addr:full":"5035 Firestone Pl South Gate CA 90280",
    "addr:housenumber":"5035",
    "addr:postcode":"90280",
    "addr:street":"Firestone Pl;Gate",
    "iso:country":"US",
    "sg:address":"5035 Firestone Pl",
    "sg:city":"South Gate",
    "sg:classifiers":[
        {
            "category":"Retail",
            "subcategory":"Auto Repair",
            "type":"Services"
        }
    ],
    "sg:phone":"+1 323 566 7000",
    "sg:postcode":"90280",
    "sg:province":"CA",
    "sg:website":"www.unitedengine.com",
    "wof:name":"United Engine",
    "wof:placetype":"venue"
},
  "geometry": {"coordinates":[-118.17800099999999,33.951599],"type":"Point"}
}