{
  "type": "Feature",
  "properties": {
    "addr:full":"235 E Broadway Long Beach CA 90802",
    "addr:housenumber":"235",
    "addr:postcode":"90802",
    "addr:street":"E Broadway",
    "iso:country":"US",
    "sg:address":"235 E Broadway",
    "sg:city":"Long Beach",
    "sg:classifiers":[
        {
            "category":"Banks & Credit Unions",
            "subcategory":"Bank",
            "type":"Services"
        }
    ],
    "sg:phone":"+1 562 590 3200",
    "sg:postcode":"90802",
    "sg:province":"CA",
    "wof:name":"ACI Automated Collection Inc",
    "wof:placetype":"venue"
},
  "geometry": {"coordinates":[-118.189492,33.769362],"type":"Point"}
}