{
  "type": "Feature",
  "properties": {
    "iso:country":"US",
    "sg:address":"25072 Castlewood",
    "sg:city":"Lake Forest",
    "sg:classifiers":[
        {
            "category":"Professional",
            "subcategory":"Computer Services",
            "type":"Services"
        }
    ],
    "sg:phone":"+1 949 455 0167",
    "sg:postcode":"92630",
    "sg:province":"CA",
    "sg:tags":[
        "communications",
        "telephone",
        "related"
    ],
    "wof:name":"Riptide Systems",
    "wof:placetype":"venue"
},
  "geometry": {"coordinates":[-117.693484,33.636977],"type":"Point"}
}