{
  "type": "Feature",
  "properties": {
    "iso:country":"US",
    "sg:address":"2461 Via Rancheros",
    "sg:city":"Fallbrook",
    "sg:classifiers":[
        {
            "category":"Farming",
            "subcategory":"Farm",
            "type":"Manufacturing & Wholesale Goods"
        }
    ],
    "sg:phone":"+1 760 728 1304",
    "sg:postcode":"92028",
    "sg:province":"CA",
    "sg:tags":[
        "general"
    ],
    "wof:name":"Ewing William Jr & Shirley",
    "wof:placetype":"venue"
},
  "geometry": {"coordinates":[-117.205571,33.341898],"type":"Point"}
}