{
  "type": "Feature",
  "properties": {
    "iso:country":"US",
    "sg:address":"222 N Fulton St",
    "sg:city":"Fresno",
    "sg:classifiers":[
        {
            "category":"Social Services",
            "subcategory":"Adult Care",
            "type":"Services"
        }
    ],
    "sg:phone":"+1 559 485 8493",
    "sg:postcode":"93701",
    "sg:province":"CA",
    "sg:tags":[
        "home",
        "residential"
    ],
    "wof:name":"Home Sweet Home",
    "wof:placetype":"venue"
},
  "geometry": {"coordinates":[-119.80024899999999,36.746988],"type":"Point"}
}