{
  "type": "Feature",
  "properties": {
    "addr:full":"840 N Patterson Ave Santa Barbara CA 93111",
    "addr:housenumber":"840",
    "addr:postcode":"93111",
    "addr:street":"N Patterson Ave",
    "iso:country":"US",
    "sg:address":"840 N Patterson Ave",
    "sg:city":"Santa Barbara",
    "sg:classifiers":[
        {
            "category":"Freight",
            "type":"Transportation"
        }
    ],
    "sg:phone":"+1 805 967 8303",
    "sg:postcode":"93111",
    "sg:province":"CA",
    "sg:tags":[
        "trucking"
    ],
    "wof:name":"Yankies Trucking",
    "wof:placetype":"venue"
},
  "geometry": {"coordinates":[-119.808111,34.450969],"type":"Point"}
}