{
  "type": "Feature",
  "properties": {
    "addr:full":"4160 Market St Ventura CA 93003",
    "addr:housenumber":"4160",
    "addr:postcode":"93003",
    "addr:street":"Market St",
    "iso:country":"US",
    "sg:address":"4160 Market St",
    "sg:city":"Ventura",
    "sg:classifiers":[
        {
            "category":"Manufacturing",
            "subcategory":"Printing",
            "type":"Manufacturing & Wholesale Goods"
        }
    ],
    "sg:phone":"+1 805 658 0585",
    "sg:postcode":"93003",
    "sg:province":"CA",
    "sg:tags":[
        "lithographic",
        "commercial"
    ],
    "wof:name":"Fletcher Offset Printing",
    "wof:placetype":"venue"
},
  "geometry": {"coordinates":[-119.23870100000001,34.258987],"type":"Point"}
}