{
  "type": "Feature",
  "properties": {
    "iso:country":"US",
    "sg:address":"5958 Vineland Ave Unit F",
    "sg:city":"North Hollywood",
    "sg:classifiers":[
        {
            "category":"Restaurant",
            "type":"Food & Drink"
        }
    ],
    "sg:phone":"+1 818 760 7060",
    "sg:postcode":"91601",
    "sg:province":"CA",
    "wof:name":"Papas & Tacos",
    "wof:placetype":"venue"
},
  "geometry": {"coordinates":[-118.369968,34.179109],"type":"Point"}
}