{
  "type": "Feature",
  "properties": {
    "addr:full":"1201 N Alvarado St Los Angeles CA 90026",
    "addr:housenumber":"1201",
    "addr:postcode":"90026",
    "addr:street":"N Alvarado St",
    "iso:country":"US",
    "sg:address":"1201 N Alvarado St",
    "sg:city":"Los Angeles",
    "sg:classifiers":[
        {
            "category":"Manufacturing",
            "subcategory":"Printing",
            "type":"Manufacturing & Wholesale Goods"
        }
    ],
    "sg:phone":"+1 213 413 5355",
    "sg:postcode":"90026",
    "sg:province":"CA",
    "sg:tags":[
        "printer"
    ],
    "wof:name":"Lyman Printing & Letter Shop",
    "wof:placetype":"venue"
},
  "geometry": {"coordinates":[-118.26259,34.079039],"type":"Point"}
}