{
  "type": "Feature",
  "properties": {
    "addr:full":"20861 Lassen St Chatsworth CA 91311",
    "addr:housenumber":"20861",
    "addr:postcode":"91311",
    "addr:street":"Lassen St",
    "iso:country":"US",
    "sg:address":"20861 Lassen St",
    "sg:city":"Chatsworth",
    "sg:classifiers":[
        {
            "category":"Wholesale",
            "subcategory":"Groceries",
            "type":"Manufacturing & Wholesale Goods"
        }
    ],
    "sg:phone":"+1 818 773 0708",
    "sg:postcode":"91311",
    "sg:province":"CA",
    "sg:tags":[
        "food",
        "product"
    ],
    "wof:name":"Cousins Subs",
    "wof:placetype":"venue"
},
  "geometry": {"coordinates":[-118.58634000000001,34.250057],"type":"Point"}
}