{
  "type": "Feature",
  "properties": {
    "iso:country":"US",
    "sg:address":"13758 Foothill Blvd",
    "sg:city":"Sylmar",
    "sg:classifiers":[
        {
            "category":"Restaurant",
            "type":"Food & Drink"
        }
    ],
    "sg:phone":"+1 818 362 9676",
    "sg:postcode":"91342",
    "sg:province":"CA",
    "sg:tags":[
        "sandwich"
    ],
    "wof:name":"Submarine Queen",
    "wof:placetype":"venue"
},
  "geometry": {"coordinates":[-118.43162700000001,34.30803],"type":"Point"}
}