{
  "type": "Feature",
  "properties": {
    "addr:full":"61770 Commercial St Joshua Tree CA 92252",
    "addr:housenumber":"61770",
    "addr:postcode":"92252",
    "addr:street":"Commercial St Joshua",
    "iso:country":"US",
    "sg:address":"61770 Commercial St",
    "sg:city":"Joshua Tree",
    "sg:classifiers":[
        {
            "category":"Retail",
            "subcategory":"Auto Repair",
            "type":"Services"
        }
    ],
    "sg:phone":"+1 760 366 1324",
    "sg:postcode":"92252",
    "sg:province":"CA",
    "sg:tags":[
        "repairing",
        "automobile"
    ],
    "wof:name":"J T Automotive",
    "wof:placetype":"venue"
},
  "geometry": {"coordinates":[-116.315592,34.135841],"type":"Point"}
}