{
  "type": "Feature",
  "properties": {
    "addr:full":"541 Ellis St San Francisco CA 94109",
    "addr:housenumber":"541",
    "addr:postcode":"94109",
    "addr:street":"Ellis St",
    "iso:country":"US",
    "sg:address":"541 Ellis St",
    "sg:city":"San Francisco",
    "sg:classifiers":[
        {
            "category":"Retail",
            "subcategory":"Auto Repair",
            "type":"Services"
        }
    ],
    "sg:phone":"+1 415 673 8626",
    "sg:postcode":"94109",
    "sg:province":"CA",
    "sg:tags":[
        "transmission"
    ],
    "wof:name":"Market Garage",
    "wof:placetype":"venue"
},
  "geometry": {"coordinates":[-122.416072,37.784448],"type":"Point"}
}