{
  "type": "Feature",
  "properties": {
    "addr:full":"345 W Cerritos Ave Glendale CA 91204",
    "addr:housenumber":"345",
    "addr:postcode":"91204",
    "addr:street":"W Cerritos Ave",
    "iso:country":"US",
    "sg:address":"345 W Cerritos Ave",
    "sg:city":"Glendale",
    "sg:classifiers":[
        {
            "category":"Shopping",
            "type":"Retail Goods"
        }
    ],
    "sg:phone":"+1 818 956 1804",
    "sg:postcode":"91204",
    "sg:province":"CA",
    "sg:tags":[
        "equipment",
        "merchandise"
    ],
    "wof:name":"Select Copy Systems",
    "wof:placetype":"venue"
},
  "geometry": {"coordinates":[-118.25781600000001,34.124625],"type":"Point"}
}