{
  "type": "Feature",
  "properties": {
    "addr:full":"503 Main St El Segundo CA 90245",
    "addr:housenumber":"503",
    "addr:postcode":"90245",
    "addr:street":"Main St",
    "iso:country":"US",
    "sg:address":"503 Main St",
    "sg:city":"El Segundo",
    "sg:classifiers":[
        {
            "category":"Coffee & Tea",
            "type":"Food & Drink"
        }
    ],
    "sg:phone":"+1 310 615 0847",
    "sg:postcode":"90245",
    "sg:province":"CA",
    "wof:name":"Our Daily Grind",
    "wof:placetype":"venue"
},
  "geometry": {"coordinates":[-118.416,33.9226],"type":"Point"}
}