{
  "type": "Feature",
  "properties": {
    "iso:country":"US",
    "sg:address":"1005 S Main Ave Ste A",
    "sg:city":"Fallbrook",
    "sg:classifiers":[
        {
            "category":"Restaurant",
            "type":"Food & Drink"
        }
    ],
    "sg:phone":"+1 760 723 0115",
    "sg:postcode":"92028",
    "sg:province":"CA",
    "wof:name":"Las Brisas Taqueria",
    "wof:placetype":"venue"
},
  "geometry": {"coordinates":[-117.25099899999999,33.373901],"type":"Point"}
}