{
  "type": "Feature",
  "properties": {
    "addr:full":"835 5th Ave Ste 202 San Diego CA 92101",
    "addr:housenumber":"835",
    "addr:postcode":"92101",
    "addr:street":"5Th Ave Ste 202",
    "iso:country":"US",
    "sg:address":"835 5th Ave Ste 202",
    "sg:city":"San Diego",
    "sg:classifiers":[
        {
            "category":"Professional",
            "subcategory":"Lawyer & Legal Services",
            "type":"Services"
        }
    ],
    "sg:phone":"+1 619 687 0137",
    "sg:postcode":"92101",
    "sg:province":"CA",
    "wof:name":"Dreher Law Firm",
    "wof:placetype":"venue"
},
  "geometry": {"coordinates":[-117.159963,32.713973],"type":"Point"}
}