{
  "type": "Feature",
  "properties": {
    "iso:country":"US",
    "sg:address":"331 C St",
    "sg:city":"San Rafael",
    "sg:classifiers":[
        {
            "category":"Utilities",
            "subcategory":"Telephone",
            "type":"Services"
        }
    ],
    "sg:phone":"+1 415 459 2189",
    "sg:postcode":"94901",
    "sg:province":"CA",
    "sg:tags":[
        "communications"
    ],
    "wof:name":"Lucid Communications",
    "wof:placetype":"venue"
},
  "geometry": {"coordinates":[-122.532134,37.965773],"type":"Point"}
}