{
  "type": "Feature",
  "properties": {
    "addr:full":"19619 Mac Mountain Way Nevada City CA 95959",
    "addr:housenumber":"19619",
    "addr:postcode":"95959",
    "addr:street":"Mac Mountain Way",
    "iso:country":"US",
    "sg:address":"19619 Mac Mountain Way",
    "sg:city":"Nevada City",
    "sg:classifiers":[
        {
            "category":"Building & Trades",
            "subcategory":"Construction",
            "type":"Services"
        }
    ],
    "sg:phone":"+1 530 265 2511",
    "sg:postcode":"95959",
    "sg:province":"CA",
    "sg:tags":[
        "excavating",
        "contractor"
    ],
    "wof:name":"S & P Excavating",
    "wof:placetype":"venue"
},
  "geometry": {"coordinates":[-120.95362900000001,39.293425],"type":"Point"}
}