{
  "type": "Feature",
  "properties": {
    "iso:country":"US",
    "sg:address":"2592 Market St.",
    "sg:city":"San Diego",
    "sg:classifiers":[
        {
            "category":"Retail",
            "subcategory":"Repair Shop",
            "type":"Services"
        }
    ],
    "sg:phone":"+1 619 297 7748",
    "sg:postcode":"92102",
    "sg:province":"CA",
    "sg:tags":[
        "reupholstery",
        "furniture"
    ],
    "sg:website":"www.missionupholstery.net",
    "wof:name":"Mission Upholstery",
    "wof:placetype":"venue"
},
  "geometry": {"coordinates":[-117.138322,32.711966],"type":"Point"}
}