{
  "type": "Feature",
  "properties": {
    "addr:full":"3220 Adams Ave San Diego CA 92116",
    "addr:housenumber":"3220",
    "addr:postcode":"92116",
    "addr:street":"Adams Ave",
    "iso:country":"US",
    "sg:address":"3220 Adams Ave",
    "sg:city":"San Diego",
    "sg:classifiers":[
        {
            "category":"Shopping",
            "subcategory":"Used Merchandise",
            "type":"Retail Goods"
        }
    ],
    "sg:phone":"+1 619 284 3999",
    "sg:postcode":"92116",
    "sg:province":"CA",
    "sg:tags":[
        "antique"
    ],
    "sg:website":"www.revivalsantiques.com",
    "wof:name":"Revivals Antiques",
    "wof:placetype":"venue"
},
  "geometry": {"coordinates":[-117.124319,32.763445],"type":"Point"}
}