{
  "type": "Feature",
  "properties": {
    "iso:country":"US",
    "sg:address":"434 N School St",
    "sg:city":"Lodi",
    "sg:classifiers":[
        {
            "category":"Wholesale",
            "subcategory":"Machinery & Supplies",
            "type":"Manufacturing & Wholesale Goods"
        }
    ],
    "sg:phone":"+1 209 333 2681",
    "sg:postcode":"95240",
    "sg:province":"CA",
    "sg:tags":[
        "equipment",
        "industrial"
    ],
    "wof:name":"Garage Connection",
    "wof:placetype":"venue"
},
  "geometry": {"coordinates":[-121.27322700000001,38.140937],"type":"Point"}
}