{
  "type": "Feature",
  "properties": {
    "iso:country":"US",
    "sg:address":"6161 Lincoln Ave Ste C-3",
    "sg:city":"Buena Park",
    "sg:classifiers":[
        {
            "category":"Sports & Exercise",
            "subcategory":"Gym",
            "type":"Entertainment"
        },
        {
            "category":"Arena",
            "subcategory":"Sports Club",
            "type":"Entertainment"
        }
    ],
    "sg:phone":"+1 877 707 1598",
    "sg:postcode":"90620",
    "sg:province":"CA",
    "sg:tags":[
        "trainer",
        "martial art"
    ],
    "sg:website":"www.allinmma.com",
    "wof:name":"All In MMA",
    "wof:placetype":"venue"
},
  "geometry": {"coordinates":[-118.02558000000001,33.832556],"type":"Point"}
}