{
  "type": "Feature",
  "properties": {
    "addr:full":"12660 Riverside Dr Ste 310 Valley Village CA 91607",
    "addr:housenumber":"12660",
    "addr:postcode":"91607",
    "addr:street":"Riverside Dr Ste 310",
    "iso:country":"US",
    "sg:address":"12660 Riverside Dr Ste 310",
    "sg:city":"Valley Village",
    "sg:classifiers":[
        {
            "category":"Health Services",
            "subcategory":"Doctor",
            "type":"Services"
        }
    ],
    "sg:phone":"+1 818 755 0391",
    "sg:postcode":"91607",
    "sg:province":"CA",
    "wof:name":"Karen Virley MD",
    "wof:placetype":"venue"
},
  "geometry": {"coordinates":[-118.409521,34.157246],"type":"Point"}
}