{
  "type": "Feature",
  "properties": {
    "addr:full":"44 Montgomery St San Francisco CA 94104",
    "addr:housenumber":"44",
    "addr:postcode":"94104",
    "addr:street":"Montgomery St",
    "iso:country":"US",
    "sg:address":"44 Montgomery St",
    "sg:city":"San Francisco",
    "sg:classifiers":[
        {
            "category":"Arts & Performance",
            "subcategory":"Theater",
            "type":"Entertainment"
        }
    ],
    "sg:phone":"+1 415 986 2147",
    "sg:postcode":"94104",
    "sg:province":"CA",
    "sg:tags":[
        "talent",
        "agency",
        "casting"
    ],
    "wof:name":"United Talent Agency Inc",
    "wof:placetype":"venue"
},
  "geometry": {"coordinates":[-122.40204900000001,37.789642],"type":"Point"}
}