{
  "type": "Feature",
  "properties": {
    "iso:country":"US",
    "sg:address":"601 Moorpark Ave",
    "sg:city":"Moorpark",
    "sg:classifiers":[
        {
            "category":"Home & Garden",
            "subcategory":"Carpets & Floor Coverings",
            "type":"Retail Goods"
        }
    ],
    "sg:phone":"+1 805 523 8242",
    "sg:postcode":"93021",
    "sg:province":"CA",
    "sg:tags":[
        "rug"
    ],
    "wof:name":"Caesar Carpets",
    "wof:placetype":"venue"
},
  "geometry": {"coordinates":[-118.882133,34.285389],"type":"Point"}
}