{
  "type": "Feature",
  "properties": {
    "iso:country":"US",
    "sg:address":"312 N 9th St",
    "sg:city":"Lompoc",
    "sg:classifiers":[
        {
            "category":"Organizations",
            "subcategory":"Religious Organization",
            "type":"Services"
        }
    ],
    "sg:phone":"+1 805 733 9345",
    "sg:postcode":"93436",
    "sg:province":"CA",
    "sg:tags":[
        "church"
    ],
    "wof:name":"Church Of Christ",
    "wof:placetype":"venue"
},
  "geometry": {"coordinates":[-120.43809,34.642683],"type":"Point"}
}