{
  "type": "Feature",
  "properties": {
    "iso:country":"US",
    "sg:address":"441 Marine Ave",
    "sg:city":"Manhattan Beach",
    "sg:classifiers":[
        {
            "category":"Shopping",
            "subcategory":"Florist",
            "type":"Retail Goods"
        }
    ],
    "sg:phone":"+1 310 939 0993",
    "sg:postcode":"90266",
    "sg:province":"CA",
    "wof:name":"Bloom Floral Design",
    "wof:placetype":"venue"
},
  "geometry": {"coordinates":[-118.41150399999999,33.892549],"type":"Point"}
}