{
  "type": "Feature",
  "properties": {
    "addr:full":"2060 Sawtelle Boulevard Los Angeles CA 90025",
    "addr:housenumber":"2060",
    "addr:postcode":"90025",
    "addr:street":"Sawtelle Boulevard",
    "iso:country":"US",
    "sg:address":"2060 Sawtelle Boulevard",
    "sg:city":"Los Angeles",
    "sg:classifiers":[
        {
            "category":"Personal",
            "type":"Services"
        }
    ],
    "sg:phone":"+1 310 479 1280",
    "sg:postcode":"90025",
    "sg:province":"CA",
    "sg:tags":[
        "home"
    ],
    "wof:name":"George's Hardware & Garden Supply",
    "wof:placetype":"venue"
},
  "geometry": {"coordinates":[-118.442989,34.039989],"type":"Point"}
}