{
  "type": "Feature",
  "properties": {
    "addr:full":"8853 Arcade Rd Atascadero CA 93422",
    "addr:housenumber":"8853",
    "addr:postcode":"93422",
    "addr:street":"Arcade Rd",
    "iso:country":"US",
    "sg:address":"8853 Arcade Rd",
    "sg:city":"Atascadero",
    "sg:classifiers":[
        {
            "category":"Manufacturing",
            "subcategory":"Lumber",
            "type":"Manufacturing & Wholesale Goods"
        }
    ],
    "sg:phone":"+1 805 466 1615",
    "sg:postcode":"93422",
    "sg:province":"CA",
    "sg:tags":[
        "equipment",
        "rental"
    ],
    "wof:name":"Donald L Pense",
    "wof:placetype":"venue"
},
  "geometry": {"coordinates":[-120.65192,35.475744],"type":"Point"}
}