{
  "type": "Feature",
  "properties": {
    "iso:country":"US",
    "sg:address":"435 High St",
    "sg:city":"Fort Jones",
    "sg:classifiers":[
        {
            "category":"Shopping",
            "subcategory":"Computers & Home Electronics",
            "type":"Retail Goods"
        }
    ],
    "sg:phone":"+1 530 468 2697",
    "sg:postcode":"96032",
    "sg:province":"CA",
    "sg:tags":[
        "software"
    ],
    "wof:name":"Micros Associates",
    "wof:placetype":"venue"
},
  "geometry": {"coordinates":[-122.83638000000001,41.607871],"type":"Point"}
}