{
  "type": "Feature",
  "properties": {
    "iso:country":"US",
    "sg:address":"206 S Spring Street",
    "sg:city":"Los Angeles",
    "sg:classifiers":[
        {
            "category":"Restaurant",
            "type":"Food & Drink"
        }
    ],
    "sg:phone":"+1 213 628 2868",
    "sg:postcode":"90012",
    "sg:province":"CA",
    "wof:name":"The Blue Cube",
    "wof:placetype":"venue"
},
  "geometry": {"coordinates":[-118.246182,34.051277],"type":"Point"}
}