{
  "type": "Feature",
  "properties": {
    "addr:full":"6552 Bright Ave Whittier CA 90601",
    "addr:housenumber":"6552",
    "addr:postcode":"90601",
    "addr:street":"Bright Ave",
    "iso:country":"US",
    "sg:address":"6552 Bright Ave",
    "sg:city":"Whittier",
    "sg:classifiers":[
        {
            "category":"Insurance",
            "subcategory":"Insurance Agent",
            "type":"Services"
        }
    ],
    "sg:phone":"+1 562 692 0401",
    "sg:postcode":"90601",
    "sg:province":"CA",
    "wof:name":"Marie Gamet Insurance",
    "wof:placetype":"venue"
},
  "geometry": {"coordinates":[-118.03608,33.981364],"type":"Point"}
}