{
  "type": "Feature",
  "properties": {
    "addr:full":"199 S Hudson Ave Pasadena CA 91101",
    "addr:housenumber":"199",
    "addr:postcode":"91101",
    "addr:street":"S Hudson Ave",
    "iso:country":"US",
    "sg:address":"199 S Hudson Ave",
    "sg:city":"Pasadena",
    "sg:classifiers":[
        {
            "category":"Professional",
            "subcategory":"Engineering",
            "type":"Services"
        }
    ],
    "sg:phone":"+1 626 796 6101",
    "sg:postcode":"91101",
    "sg:province":"CA",
    "sg:tags":[
        "bl",
        "industrial",
        "nonresidential"
    ],
    "wof:name":"EARL CORPORATION",
    "wof:placetype":"venue"
},
  "geometry": {"coordinates":[-118.133899,34.140483],"type":"Point"}
}