{
  "type": "Feature",
  "properties": {
    "iso:country":"US",
    "sg:address":"1110 Commerce Ave",
    "sg:city":"Atwater",
    "sg:classifiers":[
        {
            "category":"Shopping",
            "subcategory":"Clothing, Apparel, & Fashions",
            "type":"Retail Goods"
        }
    ],
    "sg:phone":"+1 209 357 2030",
    "sg:postcode":"95301",
    "sg:province":"CA",
    "sg:tags":[
        "apparel",
        "women's"
    ],
    "wof:name":"Affection",
    "wof:placetype":"venue"
},
  "geometry": {"coordinates":[-120.600674,37.339844],"type":"Point"}
}