{
  "type": "Feature",
  "properties": {
    "addr:full":"245 E 157th St Gardena CA 90248",
    "addr:housenumber":"245",
    "addr:postcode":"90248",
    "addr:street":"E 157Th St",
    "iso:country":"US",
    "sg:address":"245 E 157th St",
    "sg:city":"Gardena",
    "sg:classifiers":[
        {
            "category":"Manufacturing",
            "subcategory":"Pottery",
            "type":"Manufacturing & Wholesale Goods"
        }
    ],
    "sg:phone":"+1 310 516 9426",
    "sg:postcode":"90248",
    "sg:province":"CA",
    "wof:name":"Time For You Creations",
    "wof:placetype":"venue"
},
  "geometry": {"coordinates":[-118.27258,33.889483],"type":"Point"}
}