{
  "type": "Feature",
  "properties": {
    "iso:country":"US",
    "sg:address":"18400 Avalon Blvd",
    "sg:city":"Carson",
    "sg:classifiers":[
        {
            "category":"Sports & Exercise",
            "subcategory":"Sports Center",
            "type":"Entertainment"
        },
        {
            "category":"Arena",
            "subcategory":"Stadium",
            "type":"Entertainment"
        }
    ],
    "sg:postcode":"90746",
    "sg:province":"CA",
    "sg:tags":[
        "amateur",
        "team"
    ],
    "sg:website":"www.lavelodrome.org",
    "wof:name":"LA Velodrome",
    "wof:placetype":"venue"
},
  "geometry": {"coordinates":[-118.25520299999999,33.859495],"type":"Point"}
}