{
  "type": "Feature",
  "properties": {
    "iso:country":"US",
    "sg:address":"9235 Chesapeake Dr Ste G",
    "sg:city":"San Diego",
    "sg:classifiers":[
        {
            "category":"Shopping",
            "subcategory":"Bicycles & Sporting Goods",
            "type":"Retail Goods"
        },
        {
            "category":"Recreation",
            "type":"Entertainment"
        }
    ],
    "sg:phone":"+1 858 268 0842",
    "sg:postcode":"92123",
    "sg:province":"CA",
    "sg:tags":[
        "outdoor",
        "gear",
        "hiking"
    ],
    "sg:website":"www.searchgear.com",
    "wof:name":"Search Gear",
    "wof:placetype":"venue"
},
  "geometry": {"coordinates":[-117.12980899999999,32.837962],"type":"Point"}
}