{
  "type": "Feature",
  "properties": {
    "iso:country":"US",
    "sg:address":"13807 Carpenter Rd",
    "sg:city":"Crows Landing",
    "sg:classifiers":[
        {
            "category":"Farming",
            "subcategory":"Dairy Farm",
            "type":"Manufacturing & Wholesale Goods"
        }
    ],
    "sg:phone":"+1 209 632 1334",
    "sg:postcode":"95313",
    "sg:province":"CA",
    "wof:name":"Velasquez Dairy",
    "wof:placetype":"venue"
},
  "geometry": {"coordinates":[-121.019938,37.445129],"type":"Point"}
}