{
  "type": "Feature",
  "properties": {
    "addr:full":"755 E Alvarado St Fallbrook CA 92028",
    "addr:housenumber":"755",
    "addr:postcode":"92028",
    "addr:street":"E Alvarado St",
    "iso:country":"US",
    "sg:address":"755 E Alvarado St",
    "sg:city":"Fallbrook",
    "sg:classifiers":[
        {
            "category":"Building & Trades",
            "subcategory":"Pest Control",
            "type":"Services"
        }
    ],
    "sg:phone":"+1 760 731 1411",
    "sg:postcode":"92028",
    "sg:province":"CA",
    "sg:tags":[
        "bee",
        "removal"
    ],
    "wof:name":"A-Z Bee Removal",
    "wof:placetype":"venue"
},
  "geometry": {"coordinates":[-117.24376100000001,33.381918],"type":"Point"}
}