{
  "type": "Feature",
  "properties": {
    "iso:country":"US",
    "sg:address":"1104 E Colorado Blvd",
    "sg:city":"Pasadena",
    "sg:classifiers":[
        {
            "category":"Manufacturing",
            "subcategory":"Tools & Machinery",
            "type":"Manufacturing & Wholesale Goods"
        }
    ],
    "sg:phone":"+1 626 577 4294",
    "sg:postcode":"91106",
    "sg:province":"CA",
    "sg:tags":[
        "equipment",
        "mfg"
    ],
    "wof:name":"George Haney & Son",
    "wof:placetype":"venue"
},
  "geometry": {"coordinates":[-118.127006,34.146019],"type":"Point"}
}