{
  "type": "Feature",
  "properties": {
    "addr:full":"3675 Mt Diablo Blvd Lafayette CA 94549",
    "addr:housenumber":"3675",
    "addr:postcode":"94549",
    "addr:street":"Mt Diablo Blvd",
    "iso:country":"US",
    "sg:address":"3675 Mt Diablo Blvd",
    "sg:city":"Lafayette",
    "sg:classifiers":[
        {
            "category":"Manufacturing",
            "subcategory":"Motor Vehicles & Parts",
            "type":"Manufacturing & Wholesale Goods"
        }
    ],
    "sg:phone":"+1 925 283 9600",
    "sg:postcode":"94549",
    "sg:province":"CA",
    "sg:tags":[
        "bus",
        "transit",
        "public",
        "mfg"
    ],
    "wof:name":"Herrick Pacific Corporation",
    "wof:placetype":"venue"
},
  "geometry": {"coordinates":[-122.12760900000001,37.890746],"type":"Point"}
}