{
  "type": "Feature",
  "properties": {
    "addr:full":"415 S Anaheim Hills Rd Anaheim CA 92807",
    "addr:housenumber":"415",
    "addr:postcode":"92807",
    "addr:street":"S Anaheim Hills Rd",
    "iso:country":"US",
    "sg:address":"415 S Anaheim Hills Rd",
    "sg:city":"Anaheim",
    "sg:classifiers":[
        {
            "category":"Sports & Exercise",
            "subcategory":"Tennis Court",
            "type":"Entertainment"
        }
    ],
    "sg:phone":"+1 714 998 4000",
    "sg:postcode":"92807",
    "sg:province":"CA",
    "sg:website":"www.anaheimhillsracquetclub.com",
    "wof:name":"Anaheim Hills Racquet Club",
    "wof:placetype":"venue"
},
  "geometry": {"coordinates":[-117.778766,33.848021],"type":"Point"}
}