{
  "type": "Feature",
  "properties": {
    "addr:full":"555 W Redondo Beach Blvd Gardena CA 90248",
    "addr:housenumber":"555",
    "addr:postcode":"90248",
    "addr:street":"W Redondo Beach Blvd",
    "iso:country":"US",
    "sg:address":"555 W Redondo Beach Blvd",
    "sg:city":"Gardena",
    "sg:classifiers":[
        {
            "category":"Professional",
            "subcategory":"Accounting & Tax Preparation",
            "type":"Services"
        }
    ],
    "sg:phone":"+1 310 329 6557",
    "sg:postcode":"90248",
    "sg:province":"CA",
    "sg:tags":[
        "accountant"
    ],
    "wof:name":"Sheen & Associates",
    "wof:placetype":"venue"
},
  "geometry": {"coordinates":[-118.283997,33.8927],"type":"Point"}
}