{
  "type": "Feature",
  "properties": {
    "addr:full":"326 Broadway San Diego CA 92101",
    "addr:housenumber":"326",
    "addr:postcode":"92101",
    "addr:street":"Broadway",
    "iso:country":"US",
    "sg:address":"326 Broadway",
    "sg:city":"San Diego",
    "sg:classifiers":[
        {
            "category":"Travel",
            "subcategory":"Hotels & Motels",
            "type":"Entertainment"
        }
    ],
    "sg:phone":"+1 619 232 3121",
    "sg:postcode":"92101",
    "sg:province":"CA",
    "wof:name":"U S Grant A Wyndham Historic Hotel",
    "wof:placetype":"venue"
},
  "geometry": {"coordinates":[-117.162003,32.715698],"type":"Point"}
}