{
  "type": "Feature",
  "properties": {
    "addr:full":"1116 Pacific Ave Santa Cruz CA 95060",
    "addr:housenumber":"1116",
    "addr:postcode":"95060",
    "addr:street":"Pacific Ave",
    "iso:country":"US",
    "sg:address":"1116 Pacific Ave",
    "sg:city":"Santa Cruz",
    "sg:classifiers":[
        {
            "category":"Restaurant",
            "type":"Food & Drink"
        }
    ],
    "sg:menulink":"http://www.allmenus.com/ca/santa-cruz/18892-pizza-my-heart/menu/",
    "sg:phone":"+1 831 426 2511",
    "sg:postcode":"95060",
    "sg:province":"CA",
    "sg:tags":[
        "american",
        "pizza"
    ],
    "wof:name":"Pizza My Heart",
    "wof:placetype":"venue"
},
  "geometry": {"coordinates":[-122.025576,36.972219],"type":"Point"}
}