{
  "type": "Feature",
  "properties": {
    "iso:country":"US",
    "sg:address":"215 Stuyvesant Dr",
    "sg:city":"San Anselmo",
    "sg:classifiers":[
        {
            "category":"Professional",
            "subcategory":"Business Services",
            "type":"Services"
        }
    ],
    "sg:phone":"+1 415 459 8754",
    "sg:postcode":"94960",
    "sg:province":"CA",
    "sg:tags":[
        "residential",
        "construction"
    ],
    "wof:name":"Barton Design and Construction",
    "wof:placetype":"venue"
},
  "geometry": {"coordinates":[-122.585907,38.005868],"type":"Point"}
}