{
  "type": "Feature",
  "properties": {
    "iso:country":"US",
    "sg:address":"2500 S Central Avenue",
    "sg:city":"Los Angeles",
    "sg:classifiers":[
        {
            "category":"Food & Beverages",
            "subcategory":"Meat & Fish",
            "type":"Retail Goods"
        }
    ],
    "sg:phone":"+1 323 233 1524",
    "sg:postcode":"90011",
    "sg:province":"CA",
    "sg:tags":[
        "shop"
    ],
    "wof:name":"Angelica's Meat Market",
    "wof:placetype":"venue"
},
  "geometry": {"coordinates":[-118.25468100000001,34.019741],"type":"Point"}
}