{
  "type": "Feature",
  "properties": {
    "iso:country":"US",
    "sg:address":"2345 Thompson Way",
    "sg:city":"Santa Maria",
    "sg:classifiers":[
        {
            "category":"Wholesale",
            "subcategory":"Groceries",
            "type":"Manufacturing & Wholesale Goods"
        }
    ],
    "sg:phone":"+1 805 922 7807",
    "sg:postcode":"93455",
    "sg:province":"CA",
    "sg:tags":[
        "juice",
        "fruit"
    ],
    "wof:name":"Pepsi Cola",
    "wof:placetype":"venue"
},
  "geometry": {"coordinates":[-120.45751,34.918615],"type":"Point"}
}