{
  "type": "Feature",
  "properties": {
    "addr:full":"1581 Webster St San Francisco CA 94115",
    "addr:housenumber":"1581",
    "addr:postcode":"94115",
    "addr:street":"Webster St",
    "iso:country":"US",
    "sg:address":"1581 Webster St",
    "sg:city":"San Francisco",
    "sg:classifiers":[
        {
            "category":"Arts & Performance",
            "subcategory":"Art Gallery",
            "type":"Entertainment"
        }
    ],
    "sg:phone":"+1 415 567 4390",
    "sg:postcode":"94115",
    "sg:province":"CA",
    "sg:website":"www.tokaidoarts.com/home.html?re...",
    "wof:name":"Tokaido Arts",
    "wof:placetype":"venue"
},
  "geometry": {"coordinates":[-122.43144599999999,37.785241],"type":"Point"}
}