{
  "type": "Feature",
  "properties": {
    "iso:country":"US",
    "sg:address":"11530 W Eight Mile Rd",
    "sg:city":"Stockton",
    "sg:classifiers":[
        {
            "category":"Retail",
            "subcategory":"Portrait Studio",
            "type":"Services"
        }
    ],
    "sg:phone":"+1 209 952 1637",
    "sg:postcode":"95219",
    "sg:province":"CA",
    "sg:tags":[
        "photographer"
    ],
    "wof:name":"Glenn Williams Photography",
    "wof:placetype":"venue"
},
  "geometry": {"coordinates":[-121.45760300000001,38.059166],"type":"Point"}
}