{
  "type": "Feature",
  "properties": {
    "addr:full":"8203 Lake Knoll Dr Rosemead CA 91770",
    "addr:housenumber":"8203",
    "addr:postcode":"91770",
    "addr:street":"Lake Knoll Dr",
    "iso:country":"US",
    "sg:address":"8203 Lake Knoll Dr",
    "sg:city":"Rosemead",
    "sg:classifiers":[
        {
            "category":"Freight",
            "type":"Transportation"
        }
    ],
    "sg:phone":"+1 626 288 4347",
    "sg:postcode":"91770",
    "sg:province":"CA",
    "sg:tags":[
        "opera",
        "arrangement",
        "local",
        "trucking"
    ],
    "wof:name":"No-Mar Trucking Inc",
    "wof:placetype":"venue"
},
  "geometry": {"coordinates":[-118.089944,34.050852],"type":"Point"}
}