{
  "type": "Feature",
  "properties": {
    "addr:full":"29701 S Western Ave Ste 103 Rancho Palos Verdes CA 90275",
    "addr:housenumber":"29701",
    "addr:postcode":"90275",
    "addr:street":"S Western Ave Ste 103",
    "iso:country":"US",
    "sg:address":"29701 S Western Ave Ste 103",
    "sg:city":"Rancho Palos Verdes",
    "sg:classifiers":[
        {
            "category":"Restaurant",
            "type":"Food & Drink"
        }
    ],
    "sg:phone":"+1 310 832 1200",
    "sg:postcode":"90275",
    "sg:province":"CA",
    "sg:tags":[
        "pizza"
    ],
    "wof:name":"Pavich's Brick Oven Pizzafe",
    "wof:placetype":"venue"
},
  "geometry": {"coordinates":[-118.310019,33.747028],"type":"Point"}
}