{
  "type": "Feature",
  "properties": {
    "iso:country":"US",
    "sg:address":"10567 Jefferson Blvd",
    "sg:city":"Culver City",
    "sg:classifiers":[
        {
            "category":"Autos & Motor Vehicles",
            "subcategory":"Automobile Sales",
            "type":"Retail Goods"
        }
    ],
    "sg:phone":"+1 310 280 4000",
    "sg:postcode":"90232",
    "sg:province":"CA",
    "sg:tags":[
        "car",
        "dealer"
    ],
    "sg:website":"www.carsdirect.com",
    "wof:name":"CARSDIRECT.COM",
    "wof:placetype":"venue"
},
  "geometry": {"coordinates":[-118.392712,34.005673],"type":"Point"}
}