{
  "type": "Feature",
  "properties": {
    "iso:country":"US",
    "sg:address":"9144 Owensmouth Ave",
    "sg:city":"Chatsworth",
    "sg:classifiers":[
        {
            "category":"Health Services",
            "subcategory":"Doctor",
            "type":"Services"
        }
    ],
    "sg:phone":"+1 800 471 9917",
    "sg:postcode":"91311",
    "sg:province":"CA",
    "sg:tags":[
        "hair",
        "replacement"
    ],
    "sg:website":"http://pixel1226.everesttech.net/1226/rq/43/f930503bf294f4ffbb31ffd0c6230236/url=http%3A//restored.bosley.com/%3Fp%3D800-471-9917",
    "wof:name":"Bosley Medical Hair Restoration",
    "wof:placetype":"venue"
},
  "geometry": {"coordinates":[-118.601887,34.235698],"type":"Point"}
}