{
  "type": "Feature",
  "properties": {
    "iso:country":"US",
    "sg:address":"25385 E Trimmer Springs Rd",
    "sg:city":"Sanger",
    "sg:classifiers":[
        {
            "category":"Education",
            "subcategory":"Library",
            "type":"Public Place"
        }
    ],
    "sg:phone":"+1 559 787 3266",
    "sg:postcode":"93657",
    "sg:province":"CA",
    "wof:name":"Piedra Branch Library",
    "wof:placetype":"venue"
},
  "geometry": {"coordinates":[-119.38276,36.820933],"type":"Point"}
}