{
  "type": "Feature",
  "properties": {
    "addr:full":"612 F St San Diego CA 92101",
    "addr:housenumber":"612",
    "addr:postcode":"92101",
    "addr:street":"F St",
    "iso:country":"US",
    "sg:address":"612 F St",
    "sg:city":"San Diego",
    "sg:classifiers":[
        {
            "category":"Wholesale",
            "subcategory":"Chemicals & Plastics",
            "type":"Manufacturing & Wholesale Goods"
        }
    ],
    "sg:phone":"+1 619 702 6282",
    "sg:postcode":"92101",
    "sg:province":"CA",
    "sg:tags":[
        "oxygen"
    ],
    "wof:name":"Pure Oxygen Cafe",
    "wof:placetype":"venue"
},
  "geometry": {"coordinates":[-117.158424,32.713707],"type":"Point"}
}