{
  "type": "Feature",
  "properties": {
    "iso:country":"US",
    "sg:address":"23679 Calabasas Rd",
    "sg:city":"Calabasas",
    "sg:classifiers":[
        {
            "category":"Food & Beverages",
            "subcategory":"Bakery",
            "type":"Retail Goods"
        },
        {
            "category":"Restaurant",
            "type":"Food & Drink"
        },
        {
            "category":"Bakery",
            "type":"Food & Drink"
        }
    ],
    "sg:phone":"+1 818 825 1119",
    "sg:postcode":"91302",
    "sg:province":"CA",
    "sg:tags":[
        "style",
        "family",
        "pie",
        "lunch",
        "american",
        "brunch",
        "breakfast"
    ],
    "sg:website":"http://www.mariecallenders.com",
    "wof:name":"Marie Callendar's",
    "wof:placetype":"venue"
},
  "geometry": {"coordinates":[-118.64259300000001,34.156182],"type":"Point"}
}