{
  "type": "Feature",
  "properties": {
    "iso:country":"US",
    "sg:address":"10877 Wilshire Blvd",
    "sg:city":"Los Angeles",
    "sg:classifiers":[
        {
            "category":"Banks & Credit Unions",
            "subcategory":"Investment Brokerage",
            "type":"Services"
        }
    ],
    "sg:phone":"+1 310 824 1107",
    "sg:postcode":"90024",
    "sg:province":"CA",
    "sg:tags":[
        "management"
    ],
    "wof:name":"Julius Baer Investment Mgmt",
    "wof:placetype":"venue"
},
  "geometry": {"coordinates":[-118.44030100000001,34.059932],"type":"Point"}
}