{
  "type": "Feature",
  "properties": {
    "iso:country":"US",
    "sg:address":"902 N La Cienega Blvd",
    "sg:city":"West Hollywood",
    "sg:classifiers":[
        {
            "category":"Restaurant",
            "type":"Food & Drink"
        }
    ],
    "sg:menulink":"http://www.allmenus.com/ca/los-angeles/73844-dominos-pizza/menu/",
    "sg:phone":"+1 310 855 1899",
    "sg:postcode":"90069",
    "sg:province":"CA",
    "sg:tags":[
        "american",
        "wing",
        "pizza"
    ],
    "wof:name":"Domino's Pizza",
    "wof:placetype":"venue"
},
  "geometry": {"coordinates":[-118.376457,34.087217],"type":"Point"}
}