{
  "type": "Feature",
  "properties": {
    "iso:country":"US",
    "sg:address":"131 E Fig St",
    "sg:city":"Fallbrook",
    "sg:classifiers":[
        {
            "category":"Travel",
            "subcategory":"Travel Agent",
            "type":"Entertainment"
        }
    ],
    "sg:phone":"+1 760 451 1001",
    "sg:postcode":"92028",
    "sg:province":"CA",
    "sg:tags":[
        "wholesale",
        "tour",
        "package"
    ],
    "wof:name":"Trip N Tour Micronesia",
    "wof:placetype":"venue"
},
  "geometry": {"coordinates":[-117.25117,33.381086],"type":"Point"}
}