{
  "type": "Feature",
  "properties": {
    "iso:country":"US",
    "sg:address":"2791 Sycamore Canyon Rd",
    "sg:city":"Santa Barbara",
    "sg:classifiers":[
        {
            "category":"Professional",
            "type":"Services"
        }
    ],
    "sg:phone":"+1 805 969 6195",
    "sg:postcode":"93108",
    "sg:province":"CA",
    "wof:name":"Castrapnola Foundation",
    "wof:placetype":"venue"
},
  "geometry": {"coordinates":[-119.646383,34.434647],"type":"Point"}
}