{
  "type": "Feature",
  "properties": {
    "iso:country":"US",
    "sg:address":"883 Lakewood Dr",
    "sg:city":"Sunnyvale",
    "sg:classifiers":[
        {
            "category":"Professional",
            "subcategory":"Computer Services",
            "type":"Services"
        }
    ],
    "sg:phone":"+1 408 734 5910",
    "sg:postcode":"94089",
    "sg:province":"CA",
    "sg:tags":[
        "repair"
    ],
    "wof:name":"Mr Monitor Repair & Svc",
    "wof:placetype":"venue"
},
  "geometry": {"coordinates":[-122.000179,37.39321],"type":"Point"}
}