{
  "type": "Feature",
  "properties": {
    "iso:country":"US",
    "sg:address":"12051 8th Ave",
    "sg:city":"Hanford",
    "sg:classifiers":[
        {
            "category":"Farming",
            "subcategory":"Dairy Farm",
            "type":"Manufacturing & Wholesale Goods"
        }
    ],
    "sg:phone":"+1 559 582 5873",
    "sg:postcode":"93230",
    "sg:province":"CA",
    "wof:name":"Tony Andre",
    "wof:placetype":"venue"
},
  "geometry": {"coordinates":[-119.60066500000001,36.297765],"type":"Point"}
}