{
  "type": "Feature",
  "properties": {
    "iso:country":"US",
    "sg:address":"519 S 3rd Ave",
    "sg:city":"Arcadia",
    "sg:classifiers":[
        {
            "category":"Wholesale",
            "subcategory":"Durable Goods & Equipment",
            "type":"Manufacturing & Wholesale Goods"
        }
    ],
    "sg:phone":"+1 626 447 9881",
    "sg:postcode":"91006",
    "sg:province":"CA",
    "wof:name":"Tech Leader USA Inc",
    "wof:placetype":"venue"
},
  "geometry": {"coordinates":[-118.023568,34.13263],"type":"Point"}
}