{
  "type": "Feature",
  "properties": {
    "addr:full":"524 Philan Cir Lemoore CA 93245",
    "addr:housenumber":"524",
    "addr:postcode":"93245",
    "addr:street":"Philan Cir",
    "iso:country":"US",
    "sg:address":"524 Philan Cir",
    "sg:city":"Lemoore",
    "sg:classifiers":[
        {
            "category":"Farming",
            "subcategory":"Farm & Veterinary Services",
            "type":"Manufacturing & Wholesale Goods"
        }
    ],
    "sg:phone":"+1 559 924 5838",
    "sg:postcode":"93245",
    "sg:province":"CA",
    "sg:tags":[
        "crop",
        "harvesting"
    ],
    "wof:name":"Ferguson Harvesting Inc",
    "wof:placetype":"venue"
},
  "geometry": {"coordinates":[-119.777505,36.289966],"type":"Point"}
}