{
  "type": "Feature",
  "properties": {
    "iso:country":"US",
    "sg:address":"1920 E Hammer Ln",
    "sg:city":"Stockton",
    "sg:classifiers":[
        {
            "category":"Restaurant",
            "type":"Food & Drink"
        }
    ],
    "sg:phone":"+1 209 478 3400",
    "sg:postcode":"95210",
    "sg:province":"CA",
    "wof:name":"Pizza Hut",
    "wof:placetype":"venue"
},
  "geometry": {"coordinates":[-121.28545800000001,38.020933],"type":"Point"}
}