{
  "type": "Feature",
  "properties": {
    "iso:country":"US",
    "sg:address":"4171 Montgomery Dr",
    "sg:city":"Santa Rosa",
    "sg:classifiers":[
        {
            "category":"Building & Trades",
            "subcategory":"Construction",
            "type":"Services"
        }
    ],
    "sg:phone":"+1 707 544 1519",
    "sg:postcode":"95405",
    "sg:province":"CA",
    "sg:tags":[
        "concrete",
        "contractor"
    ],
    "wof:name":"Merga Foundations Inc",
    "wof:placetype":"venue"
},
  "geometry": {"coordinates":[-122.671708,38.45618],"type":"Point"}
}