{
  "type": "Feature",
  "properties": {
    "addr:full":"22600 Sunset Crossing Rd Diamond Bar CA 91765",
    "addr:housenumber":"22600",
    "addr:postcode":"91765",
    "addr:street":"Sunset Crossing Rd",
    "iso:country":"US",
    "sg:address":"22600 Sunset Crossing Rd",
    "sg:city":"Diamond Bar",
    "sg:classifiers":[
        {
            "category":"Organizations",
            "subcategory":"Professional Association",
            "type":"Services"
        }
    ],
    "sg:phone":"+1 909 860 9622",
    "sg:postcode":"91765",
    "sg:province":"CA",
    "wof:name":"YMCA",
    "wof:placetype":"venue"
},
  "geometry": {"coordinates":[-117.818461,34.030654],"type":"Point"}
}