{
  "type": "Feature",
  "properties": {
    "addr:full":"2631 S Riverside Ave Bloomington CA 92316",
    "addr:housenumber":"2631",
    "addr:postcode":"92316",
    "addr:street":"S Riverside Ave",
    "iso:country":"US",
    "sg:address":"2631 S Riverside Ave",
    "sg:city":"Bloomington",
    "sg:classifiers":[
        {
            "category":"Building & Trades",
            "subcategory":"Construction",
            "type":"Services"
        }
    ],
    "sg:phone":"+1 909 873 0909",
    "sg:postcode":"92316",
    "sg:province":"CA",
    "sg:tags":[
        "contractor"
    ],
    "wof:name":"CMC Construction Services",
    "wof:placetype":"venue"
},
  "geometry": {"coordinates":[-117.370064,34.292142],"type":"Point"}
}