{
  "type": "Feature",
  "properties": {
    "iso:country":"US",
    "sg:address":"6521 S Sepulveda Blvd",
    "sg:city":"Los Angeles",
    "sg:classifiers":[
        {
            "category":"Restaurant",
            "type":"Food & Drink"
        }
    ],
    "sg:phone":"+1 310 645 0456",
    "sg:postcode":"90045",
    "sg:province":"CA",
    "sg:tags":[
        "diner"
    ],
    "sg:website":"www.dinahsrestaurant.com",
    "wof:name":"Dinah's Family Restaurant",
    "wof:placetype":"venue"
},
  "geometry": {"coordinates":[-118.394997,33.980598],"type":"Point"}
}