{
  "type": "Feature",
  "properties": {
    "addr:full":"5316 Monterey Hwy San Jose CA 95111",
    "addr:housenumber":"5316",
    "addr:postcode":"95111",
    "addr:street":"Monterey Hwy",
    "iso:country":"US",
    "sg:address":"5316 Monterey Hwy",
    "sg:city":"San Jose",
    "sg:classifiers":[
        {
            "category":"Restaurant",
            "type":"Food & Drink"
        }
    ],
    "sg:phone":"+1 408 281 8288",
    "sg:postcode":"95111",
    "sg:province":"CA",
    "wof:name":"Ocean Palace Chinese Rstrnt",
    "wof:placetype":"venue"
},
  "geometry": {"coordinates":[-121.80455499999999,37.257071],"type":"Point"}
}