{
  "type": "Feature",
  "properties": {
    "iso:country":"US",
    "sg:address":"23037 Birch Glen Cir",
    "sg:city":"Santa Clarita",
    "sg:classifiers":[
        {
            "category":"Building & Trades",
            "subcategory":"Construction",
            "type":"Services"
        }
    ],
    "sg:phone":"+1 661 297 7813",
    "sg:postcode":"91354",
    "sg:province":"CA",
    "sg:tags":[
        "contractor"
    ],
    "wof:name":"A Time To Build",
    "wof:placetype":"venue"
},
  "geometry": {"coordinates":[-118.539005,34.452546],"type":"Point"}
}