{
  "type": "Feature",
  "properties": {
    "addr:full":"3618 Coffey Ln Santa Rosa CA 95403",
    "addr:housenumber":"3618",
    "addr:postcode":"95403",
    "addr:street":"Coffey Ln",
    "iso:country":"US",
    "sg:address":"3618 Coffey Ln",
    "sg:city":"Santa Rosa",
    "sg:classifiers":[
        {
            "category":"Building & Trades",
            "subcategory":"Landscaping Services",
            "type":"Services"
        }
    ],
    "sg:phone":"+1 707 568 1700",
    "sg:postcode":"95403",
    "sg:province":"CA",
    "sg:tags":[
        "tree"
    ],
    "wof:name":"J & R Tree Svc",
    "wof:placetype":"venue"
},
  "geometry": {"coordinates":[-122.747045,38.478621],"type":"Point"}
}