{
  "type": "Feature",
  "properties": {
    "iso:country":"US",
    "sg:address":"9311 Hildreth Avenue",
    "sg:city":"South Gate",
    "sg:classifiers":[
        {
            "category":"Banks & Credit Unions",
            "subcategory":"Financial Services",
            "type":"Services"
        }
    ],
    "sg:phone":"+1 323 569 5204",
    "sg:postcode":"90280",
    "sg:province":"CA",
    "sg:tags":[
        "broker",
        "mortgage"
    ],
    "wof:name":"Golden Dreams Mortgage",
    "wof:placetype":"venue"
},
  "geometry": {"coordinates":[-118.187486,33.948183],"type":"Point"}
}