{
  "type": "Feature",
  "properties": {
    "iso:country":"US",
    "sg:address":"8122 Bolsa Ave",
    "sg:city":"Midway City",
    "sg:classifiers":[
        {
            "category":"Autos & Motor Vehicles",
            "subcategory":"Automobile Sales",
            "type":"Retail Goods"
        }
    ],
    "sg:phone":"+1 714 894 0063",
    "sg:postcode":"92683",
    "sg:province":"CA",
    "sg:tags":[
        "car"
    ],
    "sg:website":"www.deluxeautodealer.com/",
    "wof:name":"Deluxe Auto Dealers",
    "wof:placetype":"venue"
},
  "geometry": {"coordinates":[-117.987088,33.744421],"type":"Point"}
}