{
  "type": "Feature",
  "properties": {
    "iso:country":"US",
    "sg:address":"3801 Atlantic Ave",
    "sg:city":"Long Beach",
    "sg:classifiers":[
        {
            "category":"Banks & Credit Unions",
            "subcategory":"Financial Services",
            "type":"Services"
        }
    ],
    "sg:phone":"+1 562 427 2222",
    "sg:postcode":"90807",
    "sg:province":"CA",
    "sg:tags":[
        "broker",
        "mortgage"
    ],
    "sg:website":"www.bixbyknollsmortgage.com",
    "wof:name":"Bixby Knolls Mortgage",
    "wof:placetype":"venue"
},
  "geometry": {"coordinates":[-118.184998,33.826801],"type":"Point"}
}