{
  "type": "Feature",
  "properties": {
    "addr:full":"5665 College Ave Oakland CA 94618",
    "addr:housenumber":"5665",
    "addr:postcode":"94618",
    "addr:street":"College Ave",
    "iso:country":"US",
    "sg:address":"5665 College Ave",
    "sg:city":"Oakland",
    "sg:classifiers":[
        {
            "category":"Professional",
            "type":"Services"
        }
    ],
    "sg:phone":"+1 510 595 3580",
    "sg:postcode":"94618",
    "sg:province":"CA",
    "sg:tags":[
        "literary",
        "writer",
        "agent"
    ],
    "wof:name":"Wong, Penelope",
    "wof:placetype":"venue"
},
  "geometry": {"coordinates":[-122.251698,37.843757],"type":"Point"}
}