{
  "type": "Feature",
  "properties": {
    "addr:full":"402 Grass Valley Hwy Auburn CA 95603",
    "addr:housenumber":"402",
    "addr:postcode":"ca 95603",
    "addr:street":"Grass Valley Hwy",
    "iso:country":"US",
    "sg:address":"402 Grass Valley Hwy",
    "sg:city":"Auburn",
    "sg:classifiers":[
        {
            "category":"Retail",
            "subcategory":"Emissions Testing",
            "type":"Services"
        },
        {
            "category":"Autos & Motor Vehicles",
            "subcategory":"Fuel & Gas Station",
            "type":"Retail Goods"
        },
        {
            "category":"Retail",
            "subcategory":"Auto Repair",
            "type":"Services"
        }
    ],
    "sg:phone":"+1 530 888 6543",
    "sg:postcode":"95603",
    "sg:province":"CA",
    "sg:tags":[
        "automobile",
        "diagnostic",
        "brake",
        "truck",
        "repair-automobile",
        "inspection"
    ],
    "wof:name":"Sierra Smog & Auto Repair",
    "wof:placetype":"venue"
},
  "geometry": {"coordinates":[-121.07635999999999,38.905077],"type":"Point"}
}