{
  "type": "Feature",
  "properties": {
    "addr:full":"5684 Almaden Expy San Jose CA 95120",
    "addr:housenumber":"5684",
    "addr:postcode":"95120",
    "addr:street":"Almaden Expy",
    "iso:country":"US",
    "sg:address":"5684 Almaden Expy",
    "sg:city":"San Jose",
    "sg:classifiers":[
        {
            "category":"Health Services",
            "subcategory":"Doctor",
            "type":"Services"
        }
    ],
    "sg:phone":"+1 408 978 6684",
    "sg:postcode":"95120",
    "sg:province":"CA",
    "sg:tags":[
        "dentist"
    ],
    "wof:name":"Gray & Syn",
    "wof:placetype":"venue"
},
  "geometry": {"coordinates":[-121.875389,37.250796],"type":"Point"}
}