{
  "type": "Feature",
  "properties": {
    "iso:country":"US",
    "sg:address":"1601 Sawtelle Boulevard Suite 27",
    "sg:city":"Los Angeles",
    "sg:classifiers":[
        {
            "category":"Building & Trades",
            "subcategory":"Construction",
            "type":"Services"
        }
    ],
    "sg:phone":"+1 310 312 6070",
    "sg:postcode":"90025",
    "sg:province":"CA",
    "sg:tags":[
        "contractor"
    ],
    "wof:name":"Moment Construction Company",
    "wof:placetype":"venue"
},
  "geometry": {"coordinates":[-118.448986,34.047112],"type":"Point"}
}