{
  "type": "Feature",
  "properties": {
    "iso:country":"US",
    "sg:address":"7777 Sunrise Blvd",
    "sg:city":"Citrus Heights",
    "sg:classifiers":[
        {
            "category":"Organizations",
            "subcategory":"Community Association",
            "type":"Services"
        }
    ],
    "sg:phone":"+1 916 728 4800",
    "sg:postcode":"95610",
    "sg:province":"CA",
    "sg:tags":[
        "club"
    ],
    "wof:name":"Hilltop Sports Club",
    "wof:placetype":"venue"
},
  "geometry": {"coordinates":[-121.271867,38.705224],"type":"Point"}
}