{
  "type": "Feature",
  "properties": {
    "addr:full":"507 E Citrus Ave Redlands CA 92373",
    "addr:housenumber":"507",
    "addr:postcode":"92373",
    "addr:street":"E Citrus Ave",
    "iso:country":"US",
    "sg:address":"507 E Citrus Ave",
    "sg:city":"Redlands",
    "sg:classifiers":[
        {
            "category":"Personal",
            "subcategory":"Beauty Salon",
            "type":"Services"
        }
    ],
    "sg:phone":"+1 909 793 4199",
    "sg:postcode":"92373",
    "sg:province":"CA",
    "sg:tags":[
        "hair",
        "stylist"
    ],
    "wof:name":"Salon Museum",
    "wof:placetype":"venue"
},
  "geometry": {"coordinates":[-117.176992,34.055527],"type":"Point"}
}