{
  "type": "Feature",
  "properties": {
    "iso:country":"US",
    "sg:address":"48 W Romie Ln",
    "sg:city":"Salinas",
    "sg:classifiers":[
        {
            "category":"Health Services",
            "subcategory":"Optometrist",
            "type":"Services"
        }
    ],
    "sg:phone":"+1 831 424 0834",
    "sg:postcode":"93901",
    "sg:province":"CA",
    "wof:name":"Romie Lane Optometric Ctr",
    "wof:placetype":"venue"
},
  "geometry": {"coordinates":[-121.660085,36.663519],"type":"Point"}
}