{
  "type": "Feature",
  "properties": {
    "addr:full":"7069 Elmsdale Dr San Jose CA 95120",
    "addr:housenumber":"7069",
    "addr:postcode":"95120",
    "addr:street":"Elmsdale Dr",
    "iso:country":"US",
    "sg:address":"7069 Elmsdale Dr",
    "sg:city":"San Jose",
    "sg:classifiers":[
        {
            "category":"Professional",
            "type":"Services"
        }
    ],
    "sg:phone":"+1 408 323 1055",
    "sg:postcode":"95120",
    "sg:province":"CA",
    "wof:name":"Applied Systems Technolog",
    "wof:placetype":"venue"
},
  "geometry": {"coordinates":[-121.838233,37.208739],"type":"Point"}
}