{
  "type": "Feature",
  "properties": {
    "iso:country":"US",
    "sg:address":"22222 Destello",
    "sg:city":"Mission Viejo",
    "sg:classifiers":[
        {
            "category":"Professional",
            "type":"Services"
        }
    ],
    "sg:phone":"+1 949 830 7015",
    "sg:postcode":"92691",
    "sg:province":"CA",
    "wof:name":"27297 Via Capri Ltd Partnr",
    "wof:placetype":"venue"
},
  "geometry": {"coordinates":[-117.66225799999999,33.637526],"type":"Point"}
}