{
  "type": "Feature",
  "properties": {
    "addr:full":"6225 Conejo Rd Atascadero CA 93422",
    "addr:housenumber":"6225",
    "addr:postcode":"93422",
    "addr:street":"Conejo Rd",
    "iso:country":"US",
    "sg:address":"6225 Conejo Rd",
    "sg:city":"Atascadero",
    "sg:classifiers":[
        {
            "category":"Communications",
            "subcategory":"Film & Video Production",
            "type":"Services"
        }
    ],
    "sg:phone":"+1 805 461 5167",
    "sg:postcode":"93422",
    "sg:province":"CA",
    "sg:tags":[
        "taping"
    ],
    "wof:name":"Localmotion Video Productions",
    "wof:placetype":"venue"
},
  "geometry": {"coordinates":[-120.698892,35.508877],"type":"Point"}
}