{
  "type": "Feature",
  "properties": {
    "iso:country":"US",
    "sg:address":"7060 Hazard Ave Ste A",
    "sg:city":"Westminster",
    "sg:classifiers":[
        {
            "category":"Retail",
            "subcategory":"Auto Repair",
            "type":"Services"
        }
    ],
    "sg:phone":"+1 714 899 1464",
    "sg:postcode":"92683",
    "sg:province":"CA",
    "wof:name":"Sunshine Auto Repair",
    "wof:placetype":"venue"
},
  "geometry": {"coordinates":[-118.00599699999999,33.7519],"type":"Point"}
}