{
  "type": "Feature",
  "properties": {
    "addr:full":"26765 Madison Ave Murrieta CA 92562",
    "addr:housenumber":"26765",
    "addr:postcode":"92562",
    "addr:street":"Madison Ave",
    "iso:country":"US",
    "sg:address":"26765 Madison Ave",
    "sg:city":"Murrieta",
    "sg:classifiers":[
        {
            "category":"Organizations",
            "subcategory":"Non-profit Organization",
            "type":"Services"
        }
    ],
    "sg:phone":"+1 951 304 9500",
    "sg:postcode":"92562",
    "sg:province":"CA",
    "wof:name":"Susan G Komen Inland Empire",
    "wof:placetype":"venue"
},
  "geometry": {"coordinates":[-117.173227,33.532102],"type":"Point"}
}