{
  "type": "Feature",
  "properties": {
    "iso:country":"US",
    "sg:address":"1451 Webster St",
    "sg:city":"Alameda",
    "sg:classifiers":[
        {
            "category":"Travel",
            "subcategory":"Travel Agent",
            "type":"Entertainment"
        }
    ],
    "sg:phone":"+1 510 799 0952",
    "sg:postcode":"94501",
    "sg:province":"CA",
    "sg:tags":[
        "agency",
        "bureau"
    ],
    "wof:name":"Rely-On Tour & Travel Agency",
    "wof:placetype":"venue"
},
  "geometry": {"coordinates":[-122.27694200000001,37.773001],"type":"Point"}
}