{
  "type": "Feature",
  "properties": {
    "addr:full":"2343 Cathay Way Sacramento CA 95864",
    "addr:housenumber":"2343",
    "addr:postcode":"95864",
    "addr:street":"Cathay Way",
    "iso:country":"US",
    "sg:address":"2343 Cathay Way",
    "sg:city":"Sacramento",
    "sg:classifiers":[
        {
            "category":"Personal",
            "subcategory":"Beauty Salon",
            "type":"Services"
        }
    ],
    "sg:phone":"+1 916 488 8688",
    "sg:postcode":"95864",
    "sg:province":"CA",
    "wof:name":"Anna Lynn's Modern Beauty Sln",
    "wof:placetype":"venue"
},
  "geometry": {"coordinates":[-121.36685,38.607881],"type":"Point"}
}