{
  "type": "Feature",
  "properties": {
    "addr:full":"7720 El Camino Real Carlsbad CA 92009",
    "addr:housenumber":"7720",
    "addr:postcode":"92009",
    "addr:street":"El Camino Real",
    "iso:country":"US",
    "sg:address":"7720 El Camino Real",
    "sg:city":"Carlsbad",
    "sg:classifiers":[
        {
            "category":"Retail",
            "subcategory":"Laundry & Dry Cleaning",
            "type":"Services"
        }
    ],
    "sg:phone":"+1 760 942 5773",
    "sg:postcode":"92009",
    "sg:province":"CA",
    "wof:name":"La Costa Real Cleaners",
    "wof:placetype":"venue"
},
  "geometry": {"coordinates":[-117.26300000000001,33.0797],"type":"Point"}
}