{
  "type": "Feature",
  "properties": {
    "addr:full":"2061 Wallace Avenue Costa Mesa CA 92627",
    "addr:housenumber":"2061",
    "addr:postcode":"92627",
    "addr:street":"Wallace Avenue",
    "iso:country":"US",
    "sg:address":"2061 Wallace Avenue",
    "sg:city":"Costa Mesa",
    "sg:classifiers":[
        {
            "category":"Real Estate",
            "subcategory":"Real Estate Services",
            "type":"Services"
        },
        {
            "category":"Real Estate",
            "subcategory":"Real Estate Operator",
            "type":"Services"
        }
    ],
    "sg:phone":"+1 949 631 7229",
    "sg:postcode":"92627",
    "sg:province":"CA",
    "sg:tags":[
        "apartment",
        "property",
        "management"
    ],
    "wof:name":"Woodhaven Apartments",
    "wof:placetype":"venue"
},
  "geometry": {"coordinates":[-117.92992599999999,33.649148],"type":"Point"}
}