{
  "type": "Feature",
  "properties": {
    "iso:country":"US",
    "sg:address":"5104 E Olympic Blvd",
    "sg:city":"Los Angeles",
    "sg:classifiers":[
        {
            "category":"Autos & Motor Vehicles",
            "subcategory":"Automobile Sales",
            "type":"Retail Goods"
        }
    ],
    "sg:phone":"+1 323 266 6851",
    "sg:postcode":"90022",
    "sg:province":"CA",
    "sg:tags":[
        "car",
        "dealer"
    ],
    "wof:name":"Jesse's Auto Sales",
    "wof:placetype":"venue"
},
  "geometry": {"coordinates":[-118.159624,34.016447],"type":"Point"}
}