{
  "type": "Feature",
  "properties": {
    "iso:country":"US",
    "sg:address":"6435 Crowley Ave",
    "sg:city":"Ventura",
    "sg:classifiers":[
        {
            "category":"Wholesale",
            "subcategory":"Machinery & Supplies",
            "type":"Manufacturing & Wholesale Goods"
        }
    ],
    "sg:phone":"+1 805 650 3888",
    "sg:postcode":"93003",
    "sg:province":"CA",
    "sg:tags":[
        "equipment",
        "industrial"
    ],
    "wof:name":"Foilmax Co",
    "wof:placetype":"venue"
},
  "geometry": {"coordinates":[-119.202752,34.256816],"type":"Point"}
}