{
  "type": "Feature",
  "properties": {
    "iso:country":"US",
    "sg:address":"7510 Hazeltine Ave",
    "sg:city":"Van Nuys",
    "sg:classifiers":[
        {
            "category":"Health Services",
            "subcategory":"Medical Lab",
            "type":"Services"
        }
    ],
    "sg:phone":"+1 818 374 4637",
    "sg:postcode":"91405",
    "sg:province":"CA",
    "sg:tags":[
        "laboratory"
    ],
    "wof:name":"Quest Diagnostics",
    "wof:placetype":"venue"
},
  "geometry": {"coordinates":[-118.439995,34.205729],"type":"Point"}
}