{
  "type": "Feature",
  "properties": {
    "addr:full":"518 Vernon St Roseville CA 95678",
    "addr:housenumber":"518",
    "addr:postcode":"95678",
    "addr:street":"Vernon St",
    "iso:country":"US",
    "sg:address":"518 Vernon St",
    "sg:city":"Roseville",
    "sg:classifiers":[
        {
            "category":"Recreation",
            "type":"Entertainment"
        }
    ],
    "sg:phone":"+1 916 716 2080",
    "sg:postcode":"95678",
    "sg:province":"CA",
    "sg:tags":[
        "martial",
        "arts",
        "instruction"
    ],
    "wof:name":"Brazilian Jiu-Jitsu Training",
    "wof:placetype":"venue"
},
  "geometry": {"coordinates":[-121.28748899999999,38.74641],"type":"Point"}
}