{
  "type": "Feature",
  "properties": {
    "iso:country":"US",
    "sg:address":"26460 Corporate Ave",
    "sg:city":"Hayward",
    "sg:classifiers":[
        {
            "category":"Manufacturing",
            "subcategory":"Tools & Machinery",
            "type":"Manufacturing & Wholesale Goods"
        }
    ],
    "sg:phone":"+1 510 783 9210",
    "sg:postcode":"94545",
    "sg:province":"CA",
    "sg:tags":[
        "semiconductor",
        "industry",
        "for",
        "mfg"
    ],
    "sg:website":"www.etec.com",
    "wof:name":"Etec Systems Inc",
    "wof:placetype":"venue"
},
  "geometry": {"coordinates":[-122.113518,37.6271],"type":"Point"}
}