{
  "type": "Feature",
  "properties": {
    "iso:country":"US",
    "sg:address":"26657 Mission Blvd",
    "sg:city":"Hayward",
    "sg:classifiers":[
        {
            "category":"Restaurant",
            "type":"Food & Drink"
        }
    ],
    "sg:phone":"+1 510 581 4003",
    "sg:postcode":"94544",
    "sg:province":"CA",
    "sg:tags":[
        "indian"
    ],
    "wof:name":"Curry Corner Takeaway",
    "wof:placetype":"venue"
},
  "geometry": {"coordinates":[-122.06416299999999,37.647487],"type":"Point"}
}