{
  "type": "Feature",
  "properties": {
    "addr:full":"1235 Marina Blvd San Leandro CA 94577",
    "addr:housenumber":"1235",
    "addr:postcode":"94577",
    "addr:street":"Marina Blvd",
    "iso:country":"US",
    "sg:address":"1235 Marina Blvd",
    "sg:city":"San Leandro",
    "sg:classifiers":[
        {
            "category":"Shopping",
            "subcategory":"Department Store",
            "type":"Retail Goods"
        }
    ],
    "sg:phone":"+1 510 614 1090",
    "sg:postcode":"94577",
    "sg:province":"CA",
    "sg:website":"www.talbots.com",
    "wof:name":"Talbots",
    "wof:placetype":"venue"
},
  "geometry": {"coordinates":[-122.163797,37.711458],"type":"Point"}
}