{
  "type": "Feature",
  "properties": {
    "addr:full":"31 N 2nd Street Suite 280 San Jose CA 95113",
    "addr:housenumber":"31",
    "addr:postcode":"95113",
    "addr:street":"N 2Nd Street Suite 280",
    "iso:country":"US",
    "sg:address":"31 N 2nd Street Suite 280",
    "sg:city":"San Jose",
    "sg:classifiers":[
        {
            "category":"Professional",
            "subcategory":"Lawyer & Legal Services",
            "type":"Services"
        }
    ],
    "sg:phone":"+1 408 275 6565",
    "sg:postcode":"95113",
    "sg:province":"CA",
    "wof:name":"Shanfield & Klein Llp",
    "wof:placetype":"venue"
},
  "geometry": {"coordinates":[-121.88982799999999,37.337138],"type":"Point"}
}