{
  "type": "Feature",
  "properties": {
    "addr:full":"1567 Penasco Rd El Cajon CA 92019",
    "addr:housenumber":"1567",
    "addr:postcode":"92019",
    "addr:street":"Penasco Rd",
    "iso:country":"US",
    "sg:address":"1567 Penasco Rd",
    "sg:city":"El Cajon",
    "sg:classifiers":[
        {
            "category":"Farming",
            "subcategory":"Nursery",
            "type":"Manufacturing & Wholesale Goods"
        }
    ],
    "sg:phone":"+1 619 588 7175",
    "sg:postcode":"92019",
    "sg:province":"CA",
    "wof:name":"Woodard Greenhouse Mfg",
    "wof:placetype":"venue"
},
  "geometry": {"coordinates":[-116.926095,32.770192],"type":"Point"}
}