{
  "type": "Feature",
  "properties": {
    "iso:country":"US",
    "sg:address":"3540 Granby Dr",
    "sg:city":"Sacramento",
    "sg:classifiers":[
        {
            "category":"Travel",
            "subcategory":"Travel Agent",
            "type":"Entertainment"
        }
    ],
    "sg:phone":"+1 916 361 3097",
    "sg:postcode":"95827",
    "sg:province":"CA",
    "wof:name":"Siewell Travels",
    "wof:placetype":"venue"
},
  "geometry": {"coordinates":[-121.32971000000001,38.560547],"type":"Point"}
}