{
  "type": "Feature",
  "properties": {
    "addr:full":"322 1st St Eureka CA 95501",
    "addr:housenumber":"322",
    "addr:postcode":"95501",
    "addr:street":"1St St",
    "iso:country":"US",
    "sg:address":"322 1st St",
    "sg:city":"Eureka",
    "sg:classifiers":[
        {
            "category":"Personal",
            "subcategory":"Beauty Salon",
            "type":"Services"
        }
    ],
    "sg:phone":"+1 707 445 3226",
    "sg:postcode":"95501",
    "sg:province":"CA",
    "wof:name":"Headlines",
    "wof:placetype":"venue"
},
  "geometry": {"coordinates":[-124.16798799999999,40.804978],"type":"Point"}
}