{
  "type": "Feature",
  "properties": {
    "addr:full":"2526 New Ave Rosemead CA 91770",
    "addr:housenumber":"2526",
    "addr:postcode":"91770",
    "addr:street":"New Ave",
    "iso:country":"US",
    "sg:address":"2526 New Ave",
    "sg:city":"Rosemead",
    "sg:classifiers":[
        {
            "category":"Social Services",
            "subcategory":"Adult Care",
            "type":"Services"
        }
    ],
    "sg:phone":"+1 626 572 4146",
    "sg:postcode":"91770",
    "sg:province":"CA",
    "sg:tags":[
        "home",
        "residential"
    ],
    "wof:name":"Springfield Manor",
    "wof:placetype":"venue"
},
  "geometry": {"coordinates":[-118.108076,34.058399],"type":"Point"}
}