{
  "type": "Feature",
  "properties": {
    "iso:country":"US",
    "sg:address":"501 N Santa Cruz Ave",
    "sg:city":"Los Gatos",
    "sg:classifiers":[
        {
            "category":"Professional",
            "subcategory":"Computer Services",
            "type":"Services"
        }
    ],
    "sg:phone":"+1 408 395 9665",
    "sg:postcode":"95030",
    "sg:province":"CA",
    "sg:tags":[
        "internet"
    ],
    "wof:name":"Global Community Experience",
    "wof:placetype":"venue"
},
  "geometry": {"coordinates":[-121.97896,37.23299],"type":"Point"}
}