{
  "type": "Feature",
  "properties": {
    "iso:country":"US",
    "sg:address":"11513 Acacia St",
    "sg:city":"Loma Linda",
    "sg:classifiers":[
        {
            "category":"Social Services",
            "subcategory":"Adult Care",
            "type":"Services"
        }
    ],
    "sg:phone":"+1 909 796 5508",
    "sg:postcode":"92354",
    "sg:province":"CA",
    "sg:tags":[
        "residential"
    ],
    "wof:name":"Gentle Care Guest Home",
    "wof:placetype":"venue"
},
  "geometry": {"coordinates":[-117.25853,34.043386],"type":"Point"}
}