{
  "type": "Feature",
  "properties": {
    "addr:full":"422 Heard St Arvin CA 93203",
    "addr:housenumber":"422",
    "addr:postcode":"93203",
    "addr:street":"Heard St",
    "iso:country":"US",
    "sg:address":"422 Heard St",
    "sg:city":"Arvin",
    "sg:classifiers":[
        {
            "category":"Restaurant",
            "type":"Food & Drink"
        }
    ],
    "sg:phone":"+1 661 854 4024",
    "sg:postcode":"93203",
    "sg:province":"CA",
    "sg:tags":[
        "mexican"
    ],
    "wof:name":"Federico Garcia",
    "wof:placetype":"venue"
},
  "geometry": {"coordinates":[-118.84084300000001,35.213546],"type":"Point"}
}