{
  "type": "Feature",
  "properties": {
    "iso:country":"US",
    "sg:address":"2302 Artesia Blvd",
    "sg:city":"Redondo Beach",
    "sg:classifiers":[
        {
            "category":"Freight",
            "type":"Transportation"
        }
    ],
    "sg:phone":"+1 310 379 4491",
    "sg:postcode":"90278",
    "sg:province":"CA",
    "sg:tags":[
        "shipping"
    ],
    "sg:website":"www.boxbros.com",
    "wof:name":"Box Brothers",
    "wof:placetype":"venue"
},
  "geometry": {"coordinates":[-118.370294,33.87232],"type":"Point"}
}