{
  "type": "Feature",
  "properties": {
    "addr:full":"45815 Desert Springs Dr Lancaster CA 93534",
    "addr:housenumber":"45815",
    "addr:postcode":"93534",
    "addr:street":"Desert Springs Dr",
    "iso:country":"US",
    "sg:address":"45815 Desert Springs Dr",
    "sg:city":"Lancaster",
    "sg:classifiers":[
        {
            "category":"Shopping",
            "subcategory":"Gifts & Souvenirs",
            "type":"Retail Goods"
        }
    ],
    "sg:phone":"+1 661 940 0023",
    "sg:postcode":"93534",
    "sg:province":"CA",
    "sg:tags":[
        "basket",
        "parcel"
    ],
    "wof:name":"Gift Baskets Galore",
    "wof:placetype":"venue"
},
  "geometry": {"coordinates":[-118.147779,34.71604],"type":"Point"}
}