{
  "type": "Feature",
  "properties": {
    "addr:full":"310 Crane Ave Turlock CA 95380",
    "addr:housenumber":"310",
    "addr:postcode":"95380",
    "addr:street":"Crane Ave",
    "iso:country":"US",
    "sg:address":"310 Crane Ave",
    "sg:city":"Turlock",
    "sg:classifiers":[
        {
            "category":"Retail",
            "subcategory":"Veterinary Services",
            "type":"Services"
        }
    ],
    "sg:phone":"+1 209 634 5851",
    "sg:postcode":"95380",
    "sg:province":"CA",
    "sg:website":"www.discoveryranch.com",
    "wof:name":"Community Veterinary Clinic",
    "wof:placetype":"venue"
},
  "geometry": {"coordinates":[-120.84330799999999,37.495047],"type":"Point"}
}