{
  "type": "Feature",
  "properties": {
    "iso:country":"US",
    "sg:address":"2275 De La Cruz Blvd",
    "sg:city":"Santa Clara",
    "sg:classifiers":[
        {
            "category":"Retail",
            "subcategory":"Auto Repair",
            "type":"Services"
        }
    ],
    "sg:phone":"+1 408 748 1231",
    "sg:postcode":"95050",
    "sg:province":"CA",
    "sg:website":"radiatorland.com/",
    "wof:name":"Radiatorland",
    "wof:placetype":"venue"
},
  "geometry": {"coordinates":[-121.94134200000001,37.362829],"type":"Point"}
}