{
  "type": "Feature",
  "properties": {
    "addr:full":"1860 E 1st Street Los Angeles CA 90033",
    "addr:housenumber":"1860",
    "addr:postcode":"90033",
    "addr:street":"E 1St Street",
    "iso:country":"US",
    "sg:address":"1860 E 1st Street",
    "sg:city":"Los Angeles",
    "sg:classifiers":[
        {
            "category":"Shopping",
            "subcategory":"Florist",
            "type":"Retail Goods"
        }
    ],
    "sg:phone":"+1 323 526 7045",
    "sg:postcode":"90033",
    "sg:province":"CA",
    "wof:name":"Mom's Gardens",
    "wof:placetype":"venue"
},
  "geometry": {"coordinates":[-118.217797,34.046574],"type":"Point"}
}