{
  "type": "Feature",
  "properties": {
    "addr:full":"9920 Westminster Ave Garden Grove CA 92844",
    "addr:housenumber":"9920",
    "addr:postcode":"92844",
    "addr:street":"Westminster Ave",
    "iso:country":"US",
    "sg:address":"9920 Westminster Ave",
    "sg:city":"Garden Grove",
    "sg:classifiers":[
        {
            "category":"Food & Beverages",
            "subcategory":"Groceries & Convenience Stores",
            "type":"Retail Goods"
        }
    ],
    "sg:phone":"+1 714 539 5999",
    "sg:postcode":"92844",
    "sg:province":"CA",
    "wof:name":"Ninety Nine Cents Only Store",
    "wof:placetype":"venue"
},
  "geometry": {"coordinates":[-117.95700100000001,33.759399],"type":"Point"}
}