{
  "type": "Feature",
  "properties": {
    "addr:full":"545 Main St Half Moon Bay CA 94019",
    "addr:housenumber":"545",
    "addr:postcode":"94019",
    "addr:street":"Main St",
    "iso:country":"US",
    "sg:address":"545 Main St",
    "sg:city":"Half Moon Bay",
    "sg:classifiers":[
        {
            "category":"Shopping",
            "subcategory":"Used Merchandise",
            "type":"Retail Goods"
        }
    ],
    "sg:phone":"+1 650 726 1320",
    "sg:postcode":"94019",
    "sg:province":"CA",
    "wof:name":"Bella Antique & Collectibles",
    "wof:placetype":"venue"
},
  "geometry": {"coordinates":[-122.429233,37.463633],"type":"Point"}
}