{
  "type": "Feature",
  "properties": {
    "iso:country":"US",
    "sg:address":"1015 N Dutton Ave",
    "sg:city":"Santa Rosa",
    "sg:classifiers":[
        {
            "category":"Retail",
            "subcategory":"Auto Repair",
            "type":"Services"
        }
    ],
    "sg:phone":"+1 707 545 7477",
    "sg:postcode":"95401",
    "sg:province":"CA",
    "sg:tags":[
        "muffler",
        "exhaust",
        "system"
    ],
    "wof:name":"Major Muffler",
    "wof:placetype":"venue"
},
  "geometry": {"coordinates":[-122.72927900000001,38.442758],"type":"Point"}
}