{
  "type": "Feature",
  "properties": {
    "iso:country":"US",
    "sg:address":"13519 Alma Ave",
    "sg:city":"Gardena",
    "sg:classifiers":[
        {
            "category":"Manufacturing",
            "subcategory":"Metals",
            "type":"Manufacturing & Wholesale Goods"
        }
    ],
    "sg:phone":"+1 310 538 2550",
    "sg:postcode":"90249",
    "sg:province":"CA",
    "sg:tags":[
        "product",
        "wire"
    ],
    "wof:name":"Ex-Tech Mfg Inc",
    "wof:placetype":"venue"
},
  "geometry": {"coordinates":[-118.30316999999999,33.906915],"type":"Point"}
}