{
  "type": "Feature",
  "properties": {
    "addr:full":"5530 Corbin Ave Tarzana CA 91356",
    "addr:housenumber":"5530",
    "addr:postcode":"91356",
    "addr:street":"Corbin Ave",
    "iso:country":"US",
    "sg:address":"5530 Corbin Ave",
    "sg:city":"Tarzana",
    "sg:classifiers":[
        {
            "category":"Shopping",
            "subcategory":"Catalog Store",
            "type":"Retail Goods"
        }
    ],
    "sg:phone":"+1 818 757 7080",
    "sg:postcode":"91356",
    "sg:province":"CA",
    "sg:tags":[
        "mail",
        "order"
    ],
    "wof:name":"H H Gold Inc",
    "wof:placetype":"venue"
},
  "geometry": {"coordinates":[-118.562124,34.172328],"type":"Point"}
}