{
  "type": "Feature",
  "properties": {
    "addr:full":"4125 Sisk Rd Modesto CA 95356",
    "addr:housenumber":"4125",
    "addr:postcode":"ca 95356",
    "addr:street":"Sisk Rd",
    "iso:country":"US",
    "sg:address":"4125 Sisk Rd",
    "sg:city":"Modesto",
    "sg:classifiers":[
        {
            "category":"Restaurant",
            "type":"Food & Drink"
        }
    ],
    "sg:menulink":"http://www.allmenus.com/ca/modesto/171205-carls-jr/menu/",
    "sg:phone":"+1 209 545 2796",
    "sg:postcode":"95356",
    "sg:province":"CA",
    "sg:tags":[
        "burger",
        "american"
    ],
    "wof:name":"Carl's Jr.",
    "wof:placetype":"venue"
},
  "geometry": {"coordinates":[-121.069053,37.698554],"type":"Point"}
}