{
  "type": "Feature",
  "properties": {
    "addr:full":"456 Montgomery Suite 400 San Francisco CA 94104",
    "addr:housenumber":"456;suite 400",
    "addr:postcode":"94104",
    "addr:street":"Montgomery",
    "iso:country":"US",
    "sg:address":"456 Montgomery Suite 400",
    "sg:city":"San Francisco",
    "sg:classifiers":[
        {
            "category":"Professional",
            "subcategory":"Computer Services",
            "type":"Services"
        }
    ],
    "sg:phone":"+1 415 593 2100",
    "sg:postcode":"94104",
    "sg:province":"CA",
    "wof:name":"Applied Identity",
    "wof:placetype":"venue"
},
  "geometry": {"coordinates":[-122.402767,37.792851],"type":"Point"}
}