{
  "type": "Feature",
  "properties": {
    "iso:country":"US",
    "sg:address":"881 Dover Dr Ste 260",
    "sg:city":"Newport Beach",
    "sg:classifiers":[
        {
            "category":"Health Services",
            "subcategory":"Health Practitioner",
            "type":"Services"
        }
    ],
    "sg:phone":"+1 949 574 0750",
    "sg:postcode":"92663",
    "sg:province":"CA",
    "sg:tags":[
        "home",
        "care"
    ],
    "wof:name":"Caring Companions At Home",
    "wof:placetype":"venue"
},
  "geometry": {"coordinates":[-117.906119,33.623835],"type":"Point"}
}