{
  "type": "Feature",
  "properties": {
    "addr:full":"7669 Canberra Way Riverside CA 92508",
    "addr:housenumber":"7669",
    "addr:postcode":"92508",
    "addr:street":"Canberra Way",
    "iso:country":"US",
    "sg:address":"7669 Canberra Way",
    "sg:city":"Riverside",
    "sg:classifiers":[
        {
            "category":"Professional",
            "subcategory":"Business Services",
            "type":"Services"
        }
    ],
    "sg:phone":"+1 951 707 3060",
    "sg:postcode":"92508",
    "sg:province":"CA",
    "sg:tags":[
        "notary",
        "public"
    ],
    "wof:name":"Gladys M Carter Notary",
    "wof:placetype":"venue"
},
  "geometry": {"coordinates":[-117.31909400000001,33.911461],"type":"Point"}
}