{
  "type": "Feature",
  "properties": {
    "iso:country":"US",
    "sg:address":"16441 Bernardo Oaks Dr",
    "sg:city":"San Diego",
    "sg:classifiers":[
        {
            "category":"Cafe",
            "type":"Food & Drink"
        }
    ],
    "sg:menulink":"http://www.allmenus.com/ca/san-diego/35432-spices-thai-cafe/menu/",
    "sg:phone":"+1 858 674 4665",
    "sg:postcode":"92128",
    "sg:province":"CA",
    "sg:tags":[
        "thai",
        "asian"
    ],
    "wof:name":"Spices Thai Cafe",
    "wof:placetype":"venue"
},
  "geometry": {"coordinates":[-117.064109,33.011769],"type":"Point"}
}