{
  "type": "Feature",
  "properties": {
    "iso:country":"US",
    "sg:address":"9904 Fair Oaks Blvd",
    "sg:city":"Fair Oaks",
    "sg:classifiers":[
        {
            "category":"Real Estate",
            "subcategory":"Real Estate Agent",
            "type":"Services"
        }
    ],
    "sg:phone":"+1 916 966 2500",
    "sg:postcode":"95628",
    "sg:province":"CA",
    "sg:tags":[
        "appraiser"
    ],
    "wof:name":"Appraisal Solutions",
    "wof:placetype":"venue"
},
  "geometry": {"coordinates":[-121.271611,38.640013],"type":"Point"}
}