{
  "type": "Feature",
  "properties": {
    "addr:full":"1095 E Champlain Dr Fresno CA 93720",
    "addr:housenumber":"1095",
    "addr:postcode":"93720",
    "addr:street":"E Champlain Dr",
    "iso:country":"US",
    "sg:address":"1095 E Champlain Dr",
    "sg:city":"Fresno",
    "sg:classifiers":[
        {
            "category":"Personal",
            "subcategory":"Beauty Salon",
            "type":"Services"
        }
    ],
    "sg:phone":"+1 559 433 0345",
    "sg:postcode":"93720",
    "sg:province":"CA",
    "sg:website":"www.supercuts.com",
    "wof:name":"Supercuts",
    "wof:placetype":"venue"
},
  "geometry": {"coordinates":[-119.764588,36.872051],"type":"Point"}
}