{
  "type": "Feature",
  "properties": {
    "addr:full":"1890 Pueblo Ave Napa CA 94558",
    "addr:housenumber":"1890",
    "addr:postcode":"94558",
    "addr:street":"Pueblo Ave",
    "iso:country":"US",
    "sg:address":"1890 Pueblo Ave",
    "sg:city":"Napa",
    "sg:classifiers":[
        {
            "category":"Recreation",
            "type":"Entertainment"
        }
    ],
    "sg:phone":"+1 415 777 1630",
    "sg:postcode":"94558",
    "sg:province":"CA",
    "sg:tags":[
        "charter",
        "boat"
    ],
    "sg:website":"www.adventurecat.com",
    "wof:name":"Adventure Cat Sailing Charters",
    "wof:placetype":"venue"
},
  "geometry": {"coordinates":[-122.30573699999999,38.314287],"type":"Point"}
}