{
  "type": "Feature",
  "properties": {
    "iso:country":"US",
    "sg:address":"1309 Shore St",
    "sg:city":"West Sacramento",
    "sg:classifiers":[
        {
            "category":"Building & Trades",
            "subcategory":"Plumbing",
            "type":"Services"
        }
    ],
    "sg:phone":"+1 916 372 5160",
    "sg:postcode":"95691",
    "sg:province":"CA",
    "sg:tags":[
        "conditioning",
        "air",
        "system",
        "contractor"
    ],
    "sg:website":"www.abm.com",
    "wof:name":"Comm Air Mechanical Svc",
    "wof:placetype":"venue"
},
  "geometry": {"coordinates":[-121.546098,38.569943],"type":"Point"}
}