{
  "type": "Feature",
  "properties": {
    "iso:country":"US",
    "sg:address":"1068 N El Camino Real",
    "sg:city":"Encinitas",
    "sg:classifiers":[
        {
            "category":"Restaurant",
            "type":"Food & Drink"
        }
    ],
    "sg:menulink":"http://www.allmenus.com/ca/san-diego/19944-el-torito/menu/",
    "sg:phone":"+1 760 479 0003",
    "sg:postcode":"92024",
    "sg:province":"CA",
    "sg:tags":[
        "mexican"
    ],
    "wof:name":"El Torito",
    "wof:placetype":"venue"
},
  "geometry": {"coordinates":[-117.262519,33.067184],"type":"Point"}
}