{
  "type": "Feature",
  "properties": {
    "iso:country":"US",
    "sg:address":"4341 Birch St",
    "sg:city":"Newport Beach",
    "sg:classifiers":[
        {
            "category":"Building & Trades",
            "subcategory":"Construction",
            "type":"Services"
        }
    ],
    "sg:phone":"+1 949 261 9599",
    "sg:postcode":"92660",
    "sg:province":"CA",
    "sg:tags":[
        "contractor"
    ],
    "wof:name":"R C Development",
    "wof:placetype":"venue"
},
  "geometry": {"coordinates":[-117.865149,33.669246],"type":"Point"}
}