{
  "type": "Feature",
  "properties": {
    "iso:country":"US",
    "sg:address":"3751 6th Ave",
    "sg:city":"San Diego",
    "sg:classifiers":[
        {
            "category":"Utilities",
            "subcategory":"Telephone",
            "type":"Services"
        }
    ],
    "sg:phone":"+1 619 688 0529",
    "sg:postcode":"92103",
    "sg:province":"CA",
    "sg:tags":[
        "company"
    ],
    "wof:name":"Access Jcn Telephone",
    "wof:placetype":"venue"
},
  "geometry": {"coordinates":[-117.159524,32.746971],"type":"Point"}
}