{
  "type": "Feature",
  "properties": {
    "iso:country":"US",
    "sg:address":"2416 Chestnut St",
    "sg:city":"San Francisco",
    "sg:classifiers":[
        {
            "category":"Retail",
            "subcategory":"Laundry & Dry Cleaning",
            "type":"Services"
        }
    ],
    "sg:postcode":"94123",
    "sg:province":"CA",
    "wof:name":"Rainwater Laundromat",
    "wof:placetype":"venue"
},
  "geometry": {"coordinates":[-122.44313099999999,37.799973],"type":"Point"}
}