{
  "type": "Feature",
  "properties": {
    "addr:full":"2100 Avalon St Rubidoux CA 92509",
    "addr:housenumber":"2100",
    "addr:postcode":"92509",
    "addr:street":"Avalon St",
    "iso:country":"US",
    "sg:address":"2100 Avalon St",
    "sg:city":"Rubidoux",
    "sg:classifiers":[
        {
            "category":"Wholesale",
            "subcategory":"Construction Materials",
            "type":"Manufacturing & Wholesale Goods"
        }
    ],
    "sg:phone":"+1 951 826 3000",
    "sg:postcode":"92509",
    "sg:province":"CA",
    "sg:tags":[
        "lumber"
    ],
    "wof:name":"Universal Forest Products Inc",
    "wof:placetype":"venue"
},
  "geometry": {"coordinates":[-117.392526,34.018062],"type":"Point"}
}