{
  "type": "Feature",
  "properties": {
    "addr:full":"300 College Ave Santa Rosa CA 95401",
    "addr:housenumber":"300",
    "addr:postcode":"95401",
    "addr:street":"College Ave",
    "iso:country":"US",
    "sg:address":"300 College Ave",
    "sg:city":"Santa Rosa",
    "sg:classifiers":[
        {
            "category":"Autos & Motor Vehicles",
            "subcategory":"Fuel & Gas Station",
            "type":"Retail Goods"
        }
    ],
    "sg:phone":"+1 707 575 0352",
    "sg:postcode":"95401",
    "sg:province":"CA",
    "sg:tags":[
        "oil"
    ],
    "wof:name":"Flyers",
    "wof:placetype":"venue"
},
  "geometry": {"coordinates":[-122.72039700000001,38.445719],"type":"Point"}
}