{
  "type": "Feature",
  "properties": {
    "addr:full":"4109 Cathann St Torrance CA 90503",
    "addr:housenumber":"4109",
    "addr:postcode":"90503",
    "addr:street":"Cathann St",
    "iso:country":"US",
    "sg:address":"4109 Cathann St",
    "sg:city":"Torrance",
    "sg:classifiers":[
        {
            "category":"Professional",
            "subcategory":"Business Services",
            "type":"Services"
        }
    ],
    "sg:phone":"+1 310 792 2333",
    "sg:postcode":"90503",
    "sg:province":"CA",
    "sg:tags":[
        "diver"
    ],
    "sg:website":"www.saintbrendan.com",
    "wof:name":"St Brendan Corp",
    "wof:placetype":"venue"
},
  "geometry": {"coordinates":[-118.355424,33.826788],"type":"Point"}
}