{
  "type": "Feature",
  "properties": {
    "addr:full":"15600 Los Gatos Blvd Los Gatos CA 95032",
    "addr:housenumber":"15600",
    "addr:postcode":"95032",
    "addr:street":"Los Gatos Blvd",
    "iso:country":"US",
    "sg:address":"15600 Los Gatos Blvd",
    "sg:city":"Los Gatos",
    "sg:classifiers":[
        {
            "category":"Autos & Motor Vehicles",
            "subcategory":"Automobile Sales",
            "type":"Retail Goods"
        }
    ],
    "sg:phone":"+1 408 356 6161",
    "sg:postcode":"95032",
    "sg:province":"CA",
    "sg:tags":[
        "car",
        "dealer"
    ],
    "sg:website":"www.1800anderson.com",
    "wof:name":"Anderson Chevrolet-Oldsmobile",
    "wof:placetype":"venue"
},
  "geometry": {"coordinates":[-121.95822800000001,37.245512],"type":"Point"}
}