{
  "type": "Feature",
  "properties": {
    "iso:country":"US",
    "sg:address":"323 Junipero St",
    "sg:city":"Pleasanton",
    "sg:classifiers":[
        {
            "category":"Professional",
            "type":"Services"
        }
    ],
    "sg:phone":"+1 925 462 9095",
    "sg:postcode":"94566",
    "sg:province":"CA",
    "wof:name":"C Files",
    "wof:placetype":"venue"
},
  "geometry": {"coordinates":[-121.876672,37.650279],"type":"Point"}
}