{
  "type": "Feature",
  "properties": {
    "iso:country":"US",
    "sg:address":"3299 Abdy Way",
    "sg:city":"Marina",
    "sg:classifiers":[
        {
            "category":"Retail",
            "subcategory":"Auto Repair",
            "type":"Services"
        }
    ],
    "sg:phone":"+1 831 384 6042",
    "sg:postcode":"93933",
    "sg:province":"CA",
    "sg:tags":[
        "body",
        "automobile",
        "painting"
    ],
    "wof:name":"Mustang Beginnings",
    "wof:placetype":"venue"
},
  "geometry": {"coordinates":[-121.79940499999999,36.697956],"type":"Point"}
}