{
  "type": "Feature",
  "properties": {
    "iso:country":"US",
    "sg:address":"2645 Foothill Blvd",
    "sg:city":"La Crescenta",
    "sg:classifiers":[
        {
            "category":"Wholesale",
            "subcategory":"Machinery & Supplies",
            "type":"Manufacturing & Wholesale Goods"
        }
    ],
    "sg:phone":"+1 818 248 7588",
    "sg:postcode":"91214",
    "sg:province":"CA",
    "sg:tags":[
        "salon",
        "cosmetic",
        "beauty"
    ],
    "wof:name":"Hans Beauty Store",
    "wof:placetype":"venue"
},
  "geometry": {"coordinates":[-118.23616699999999,34.221829],"type":"Point"}
}