{
  "type": "Feature",
  "properties": {
    "iso:country":"US",
    "sg:address":"19301 Pacific Gateway Dr",
    "sg:city":"Torrance",
    "sg:classifiers":[
        {
            "category":"Wholesale",
            "subcategory":"Durable Goods & Equipment",
            "type":"Manufacturing & Wholesale Goods"
        }
    ],
    "sg:phone":"+1 310 532 7407",
    "sg:postcode":"90502",
    "sg:province":"CA",
    "sg:tags":[
        "exporter"
    ],
    "wof:name":"Nishizawa USA Limited",
    "wof:placetype":"venue"
},
  "geometry": {"coordinates":[-118.295367,33.85585],"type":"Point"}
}