{
  "type": "Feature",
  "properties": {
    "iso:country":"US",
    "sg:address":"2150 N Fine Ave",
    "sg:city":"Fresno",
    "sg:classifiers":[
        {
            "category":"Professional",
            "subcategory":"Accounting & Tax Preparation",
            "type":"Services"
        }
    ],
    "sg:phone":"+1 559 251 9797",
    "sg:postcode":"93727",
    "sg:province":"CA",
    "sg:tags":[
        "accountant"
    ],
    "sg:website":"www.fresnocpa.com",
    "wof:name":"Gnagy & Jensen",
    "wof:placetype":"venue"
},
  "geometry": {"coordinates":[-119.726806,36.771249],"type":"Point"}
}