{
  "type": "Feature",
  "properties": {
    "addr:full":"1151 Triton Dr Foster City CA 94404",
    "addr:housenumber":"1151",
    "addr:postcode":"94404",
    "addr:street":"Triton Dr",
    "iso:country":"US",
    "sg:address":"1151 Triton Dr",
    "sg:city":"Foster City",
    "sg:classifiers":[
        {
            "category":"Wholesale",
            "subcategory":"Office Equipment",
            "type":"Manufacturing & Wholesale Goods"
        }
    ],
    "sg:phone":"+1 650 572 1013",
    "sg:postcode":"94404",
    "sg:province":"CA",
    "sg:tags":[
        "register",
        "cash",
        "supply"
    ],
    "wof:name":"Electronic Retail System Inc",
    "wof:placetype":"venue"
},
  "geometry": {"coordinates":[-122.270483,37.563877],"type":"Point"}
}