{
  "type": "Feature",
  "properties": {
    "addr:full":"1628 Hostetter Road Ste J San Jose CA 95131",
    "addr:housenumber":"1628",
    "addr:postcode":"95131",
    "addr:street":"Hostetter Road Ste J",
    "iso:country":"US",
    "sg:address":"1628 Hostetter Road Ste J",
    "sg:city":"San Jose",
    "sg:classifiers":[
        {
            "category":"Health Services",
            "subcategory":"Dentist",
            "type":"Services"
        }
    ],
    "sg:phone":"+1 408 436 8282",
    "sg:postcode":"95131",
    "sg:province":"CA",
    "wof:name":"Lee Stanley T DDS",
    "wof:placetype":"venue"
},
  "geometry": {"coordinates":[-121.88506,37.387577],"type":"Point"}
}