{
  "type": "Feature",
  "properties": {
    "iso:country":"US",
    "sg:address":"21300 Victory Blvd",
    "sg:city":"Woodland Hills",
    "sg:classifiers":[
        {
            "category":"Real Estate",
            "subcategory":"Real Estate Services",
            "type":"Services"
        }
    ],
    "sg:phone":"+1 818 999 9033",
    "sg:postcode":"91367",
    "sg:province":"CA",
    "sg:tags":[
        "management",
        "property"
    ],
    "wof:name":"Douglas Emmett",
    "wof:placetype":"venue"
},
  "geometry": {"coordinates":[-118.595726,34.188205],"type":"Point"}
}