{
  "type": "Feature",
  "properties": {
    "addr:full":"3219 Preble Ave Ventura CA 93003",
    "addr:housenumber":"3219",
    "addr:postcode":"93003",
    "addr:street":"Preble Ave",
    "iso:country":"US",
    "sg:address":"3219 Preble Ave",
    "sg:city":"Ventura",
    "sg:classifiers":[
        {
            "category":"Farming",
            "subcategory":"Aquatic Farm",
            "type":"Manufacturing & Wholesale Goods"
        }
    ],
    "sg:phone":"+1 805 644 6884",
    "sg:postcode":"93003",
    "sg:province":"CA",
    "wof:name":"Force Field Fish",
    "wof:placetype":"venue"
},
  "geometry": {"coordinates":[-119.25175900000001,34.26548],"type":"Point"}
}