{
  "type": "Feature",
  "properties": {
    "addr:full":"4325 Glencoe Ave Marina Del Rey CA 90292",
    "addr:housenumber":"4325",
    "addr:postcode":"90292",
    "addr:street":"Glencoe Ave",
    "iso:country":"US",
    "sg:address":"4325 Glencoe Ave",
    "sg:city":"Marina Del Rey",
    "sg:classifiers":[
        {
            "category":"Restaurant",
            "type":"Food & Drink"
        }
    ],
    "sg:phone":"+1 310 305 8100",
    "sg:postcode":"90292",
    "sg:province":"CA",
    "sg:tags":[
        "caterer"
    ],
    "wof:name":"Fuddruckers",
    "wof:placetype":"venue"
},
  "geometry": {"coordinates":[-118.439143,33.986131],"type":"Point"}
}