{
  "type": "Feature",
  "properties": {
    "iso:country":"US",
    "sg:address":"1087 Revere Ave",
    "sg:city":"San Francisco",
    "sg:classifiers":[
        {
            "category":"Home & Garden",
            "subcategory":"Building Materials",
            "type":"Retail Goods"
        }
    ],
    "sg:phone":"+1 415 564 5673",
    "sg:postcode":"94124",
    "sg:province":"CA",
    "sg:tags":[
        "hardwood"
    ],
    "wof:name":"B Axelrod & Co Teak Lumber",
    "wof:placetype":"venue"
},
  "geometry": {"coordinates":[-122.38029,37.726173],"type":"Point"}
}