{
  "type": "Feature",
  "properties": {
    "iso:country":"US",
    "sg:address":"116 Market Pl",
    "sg:city":"San Ramon",
    "sg:classifiers":[
        {
            "category":"Retail",
            "subcategory":"Laundry & Dry Cleaning",
            "type":"Services"
        }
    ],
    "sg:phone":"+1 925 355 1252",
    "sg:postcode":"94583",
    "sg:province":"CA",
    "sg:tags":[
        "cleaners"
    ],
    "wof:name":"Market Place Cleaner",
    "wof:placetype":"venue"
},
  "geometry": {"coordinates":[-121.949528,37.763797],"type":"Point"}
}