{
  "type": "Feature",
  "properties": {
    "iso:country":"US",
    "sg:address":"9828 Mission Gorge Rd",
    "sg:city":"Santee",
    "sg:classifiers":[
        {
            "category":"Cafe",
            "type":"Food & Drink"
        }
    ],
    "sg:menulink":"http://www.allmenus.com/ca/san-diego/6195-daphnes-greek-cafe/menu/",
    "sg:phone":"+1 619 596 1470",
    "sg:postcode":"92071",
    "sg:province":"CA",
    "sg:tags":[
        "greek"
    ],
    "wof:name":"Daphne's Greek Cafe",
    "wof:placetype":"venue"
},
  "geometry": {"coordinates":[-116.983289,32.838561],"type":"Point"}
}