{
  "type": "Feature",
  "properties": {
    "addr:full":"1755 W Martin Luther King Jr Blvd Los Angeles CA 90062",
    "addr:housenumber":"1755",
    "addr:postcode":"90062",
    "addr:street":"W Martin Luther King Jr Blvd",
    "iso:country":"US",
    "sg:address":"1755 W Martin Luther King Jr Blvd",
    "sg:city":"Los Angeles",
    "sg:classifiers":[
        {
            "category":"Home & Garden",
            "subcategory":"Hardware",
            "type":"Retail Goods"
        }
    ],
    "sg:phone":"+1 323 290 9785",
    "sg:postcode":"90062",
    "sg:province":"CA",
    "sg:tags":[
        "store"
    ],
    "wof:name":"J & J Ferreteria-Hardware",
    "wof:placetype":"venue"
},
  "geometry": {"coordinates":[-118.310087,34.099471],"type":"Point"}
}