{
  "type": "Feature",
  "properties": {
    "iso:country":"US",
    "sg:address":"1430 N Serrano Ave",
    "sg:city":"Los Angeles",
    "sg:classifiers":[
        {
            "category":"Wholesale",
            "subcategory":"Groceries",
            "type":"Manufacturing & Wholesale Goods"
        }
    ],
    "sg:phone":"+1 323 871 1396",
    "sg:postcode":"90027",
    "sg:province":"CA",
    "sg:tags":[
        "baker"
    ],
    "wof:name":"Hollywood Bakery",
    "wof:placetype":"venue"
},
  "geometry": {"coordinates":[-118.306966,34.096631],"type":"Point"}
}