{
  "type": "Feature",
  "properties": {
    "addr:full":"12641 Waynoka Rd Apple Valley CA 92308",
    "addr:housenumber":"12641",
    "addr:postcode":"92308",
    "addr:street":"Waynoka Rd",
    "iso:country":"US",
    "sg:address":"12641 Waynoka Rd",
    "sg:city":"Apple Valley",
    "sg:classifiers":[
        {
            "category":"Food & Beverages",
            "subcategory":"Groceries & Convenience Stores",
            "type":"Retail Goods"
        }
    ],
    "sg:phone":"+1 760 247 0690",
    "sg:postcode":"92308",
    "sg:province":"CA",
    "wof:name":"Apple Valley Market",
    "wof:placetype":"venue"
},
  "geometry": {"coordinates":[-117.198227,34.47992],"type":"Point"}
}