{
  "type": "Feature",
  "properties": {
    "iso:country":"US",
    "sg:address":"3894 Greenwood St",
    "sg:city":"Newbury Park",
    "sg:classifiers":[
        {
            "category":"Building & Trades",
            "subcategory":"Construction",
            "type":"Services"
        }
    ],
    "sg:phone":"+1 805 499 0972",
    "sg:postcode":"91320",
    "sg:province":"CA",
    "sg:tags":[
        "designer",
        "dealer",
        "pool",
        "swimming"
    ],
    "wof:name":"Aqua Blue Pool Svc",
    "wof:placetype":"venue"
},
  "geometry": {"coordinates":[-118.957662,34.161327],"type":"Point"}
}