{
  "type": "Feature",
  "properties": {
    "iso:country":"US",
    "sg:address":"301 N Garfield Ave",
    "sg:city":"Monterey Park",
    "sg:classifiers":[
        {
            "category":"Sports & Exercise",
            "subcategory":"Gym",
            "type":"Entertainment"
        }
    ],
    "sg:phone":"+1 626 282 0743",
    "sg:postcode":"91754",
    "sg:province":"CA",
    "sg:tags":[
        "trainer"
    ],
    "wof:name":"Curves",
    "wof:placetype":"venue"
},
  "geometry": {"coordinates":[-118.123015,34.06494],"type":"Point"}
}