{
  "type": "Feature",
  "properties": {
    "iso:country":"US",
    "sg:address":"1200 E Highland Ave",
    "sg:city":"San Bernardino",
    "sg:classifiers":[
        {
            "category":"Organizations",
            "subcategory":"Religious Organization",
            "type":"Services"
        }
    ],
    "sg:phone":"+1 909 475 9429",
    "sg:postcode":"92404",
    "sg:province":"CA",
    "sg:tags":[
        "church"
    ],
    "wof:name":"High Praises Worship Ctr",
    "wof:placetype":"venue"
},
  "geometry": {"coordinates":[-117.25839499999999,34.135868],"type":"Point"}
}