{
  "type": "Feature",
  "properties": {
    "addr:full":"13424 Mesa Terrace Drive Yucaipa CA 92399",
    "addr:housenumber":"13424",
    "addr:postcode":"92399",
    "addr:street":"Mesa Terrace Drive",
    "iso:country":"US",
    "sg:address":"13424 Mesa Terrace Drive",
    "sg:city":"Yucaipa",
    "sg:classifiers":[
        {
            "category":"Professional",
            "type":"Services"
        }
    ],
    "sg:phone":"+1 888 307 4697",
    "sg:postcode":"92399",
    "sg:province":"CA",
    "wof:name":"Vintage Shower Doors and More",
    "wof:placetype":"venue"
},
  "geometry": {"coordinates":[-117.01390600000001,34.009494],"type":"Point"}
}