{
  "type": "Feature",
  "properties": {
    "addr:full":"967 Cedar St Ramona CA 92065",
    "addr:housenumber":"967",
    "addr:postcode":"92065",
    "addr:street":"Cedar St",
    "iso:country":"US",
    "sg:address":"967 Cedar St",
    "sg:city":"Ramona",
    "sg:classifiers":[
        {
            "category":"Home & Garden",
            "subcategory":"Furniture",
            "type":"Retail Goods"
        }
    ],
    "sg:phone":"+1 800 510 8697",
    "sg:postcode":"92065",
    "sg:province":"CA",
    "sg:tags":[
        "store"
    ],
    "wof:name":"Castle Creek Educational Furniture & Toy Co.",
    "wof:placetype":"venue"
},
  "geometry": {"coordinates":[-116.87152500000001,33.054862],"type":"Point"}
}