{
  "type": "Feature",
  "properties": {
    "iso:country":"US",
    "sg:address":"2054 Terilyn Ave",
    "sg:city":"San Jose",
    "sg:classifiers":[
        {
            "category":"Building & Trades",
            "subcategory":"Cleaning & Sanitation",
            "type":"Services"
        }
    ],
    "sg:phone":"+1 408 937 4778",
    "sg:postcode":"95122",
    "sg:province":"CA",
    "sg:tags":[
        "house"
    ],
    "wof:name":"Residential Housekeeping",
    "wof:placetype":"venue"
},
  "geometry": {"coordinates":[-121.834904,37.324608],"type":"Point"}
}