{
  "type": "Feature",
  "properties": {
    "addr:full":"5756 Pacific Ave Stockton CA 95207",
    "addr:housenumber":"5756",
    "addr:postcode":"95207",
    "addr:street":"Pacific Ave",
    "iso:country":"US",
    "sg:address":"5756 Pacific Ave",
    "sg:city":"Stockton",
    "sg:classifiers":[
        {
            "category":"Wholesale",
            "subcategory":"Machinery & Supplies",
            "type":"Manufacturing & Wholesale Goods"
        }
    ],
    "sg:phone":"+1 209 952 7004",
    "sg:postcode":"95207",
    "sg:province":"CA",
    "sg:tags":[
        "salon",
        "beauty"
    ],
    "wof:name":"Sally Beauty Supply",
    "wof:placetype":"venue"
},
  "geometry": {"coordinates":[-121.316979,38.001983],"type":"Point"}
}