{
  "type": "Feature",
  "properties": {
    "iso:country":"US",
    "sg:address":"2750 N Locust Ave",
    "sg:city":"Rialto",
    "sg:classifiers":[
        {
            "category":"Wholesale",
            "subcategory":"Metals & Minerals",
            "type":"Manufacturing & Wholesale Goods"
        }
    ],
    "sg:phone":"+1 909 429 6900",
    "sg:postcode":"92377",
    "sg:province":"CA",
    "sg:tags":[
        "steel",
        "warehouse"
    ],
    "sg:website":"www.tubularsteel.com",
    "wof:name":"Tubular Steel Inc",
    "wof:placetype":"venue"
},
  "geometry": {"coordinates":[-117.409858,34.148664],"type":"Point"}
}