{
  "type": "Feature",
  "properties": {
    "iso:country":"US",
    "sg:address":"1631 Calathea Rd",
    "sg:city":"Hemet",
    "sg:classifiers":[
        {
            "category":"Real Estate",
            "subcategory":"Architect",
            "type":"Services"
        }
    ],
    "sg:phone":"+1 951 658 4423",
    "sg:postcode":"92545",
    "sg:province":"CA",
    "wof:name":"James E Calkins",
    "wof:placetype":"venue"
},
  "geometry": {"coordinates":[-117.01475600000001,33.719567],"type":"Point"}
}