{
  "type": "Feature",
  "properties": {
    "addr:full":"13122 W Washington Blvd Los Angeles CA 90066",
    "addr:housenumber":"13122",
    "addr:postcode":"90066",
    "addr:street":"W Washington Blvd",
    "iso:country":"US",
    "sg:address":"13122 W Washington Blvd",
    "sg:city":"Los Angeles",
    "sg:classifiers":[
        {
            "category":"Personal",
            "subcategory":"Beauty Salon",
            "type":"Services"
        },
        {
            "category":"Personal",
            "subcategory":"Skin Care",
            "type":"Services"
        }
    ],
    "sg:phone":"+1 310 827 8966",
    "sg:postcode":"90066",
    "sg:province":"CA",
    "sg:tags":[
        "hair"
    ],
    "wof:name":"Refinery Hair & Skin Salon",
    "wof:placetype":"venue"
},
  "geometry": {"coordinates":[-118.44117799999999,33.993434],"type":"Point"}
}