{
  "type": "Feature",
  "properties": {
    "addr:full":"24326 Mission Blvd Ste 3 Hayward CA 94544",
    "addr:housenumber":"24326",
    "addr:postcode":"94544",
    "addr:street":"Mission Blvd Ste 3",
    "iso:country":"US",
    "sg:address":"24326 Mission Blvd Ste 3",
    "sg:city":"Hayward",
    "sg:classifiers":[
        {
            "category":"Health Services",
            "subcategory":"Medical Lab",
            "type":"Services"
        }
    ],
    "sg:phone":"+1 510 733 5707",
    "sg:postcode":"94544",
    "sg:province":"CA",
    "sg:tags":[
        "testing",
        "drug"
    ],
    "wof:name":"Hoa Tang",
    "wof:placetype":"venue"
},
  "geometry": {"coordinates":[-122.07730599999999,37.664554],"type":"Point"}
}