{
  "type": "Feature",
  "properties": {
    "iso:country":"US",
    "sg:address":"1312 E Ontario Ave",
    "sg:city":"Corona",
    "sg:classifiers":[
        {
            "category":"Retail",
            "subcategory":"Laundry & Dry Cleaning",
            "type":"Services"
        }
    ],
    "sg:phone":"+1 951 520 9707",
    "sg:postcode":"92881",
    "sg:province":"CA",
    "sg:tags":[
        "cleaners"
    ],
    "wof:name":"Dry Clean Factory",
    "wof:placetype":"venue"
},
  "geometry": {"coordinates":[-117.539507,33.846571],"type":"Point"}
}