{
  "type": "Feature",
  "properties": {
    "addr:full":"401 W Orangewood Ave Ofc Anaheim CA 92802",
    "addr:housenumber":"401",
    "addr:postcode":"92802",
    "addr:street":"W Orangewood Ave",
    "iso:country":"US",
    "sg:address":"401 W Orangewood Ave Ofc",
    "sg:city":"Anaheim",
    "sg:classifiers":[
        {
            "category":"Real Estate",
            "subcategory":"Real Estate Operator",
            "type":"Services"
        }
    ],
    "sg:phone":"+1 714 750 2900",
    "sg:postcode":"92802",
    "sg:province":"CA",
    "sg:tags":[
        "apartment"
    ],
    "wof:name":"Parkewood Village Apartments",
    "wof:placetype":"venue"
},
  "geometry": {"coordinates":[-117.924004,33.807098],"type":"Point"}
}