{
  "type": "Feature",
  "properties": {
    "iso:country":"US",
    "sg:address":"29033 Avenue Sherman Ste 212",
    "sg:city":"Valencia",
    "sg:classifiers":[
        {
            "category":"Home & Garden",
            "subcategory":"Furniture",
            "type":"Retail Goods"
        }
    ],
    "sg:phone":"+1 661 257 8053",
    "sg:postcode":"91355",
    "sg:province":"CA",
    "sg:tags":[
        "store"
    ],
    "wof:name":"Fill Dan Custom Cabinets",
    "wof:placetype":"venue"
},
  "geometry": {"coordinates":[-118.633337,34.445741],"type":"Point"}
}