{
  "type": "Feature",
  "properties": {
    "addr:full":"13070 State Highway 33 At I-5 Gustine CA 95322",
    "addr:housenumber":"13070",
    "addr:postcode":"95322",
    "addr:street":"State Highway 33 At",
    "iso:country":"US",
    "sg:address":"13070 State Highway 33 At I-5",
    "sg:city":"Gustine",
    "sg:classifiers":[
        {
            "category":"Travel",
            "subcategory":"Hotels & Motels",
            "type":"Entertainment"
        },
        {
            "category":"Retail",
            "subcategory":"Event Space",
            "type":"Services"
        }
    ],
    "sg:phone":"+1 209 826 4444",
    "sg:postcode":"95322",
    "sg:province":"CA",
    "sg:tags":[
        "hall",
        "banquet",
        "reception",
        "facility"
    ],
    "sg:website":"http://www.ramada.com",
    "wof:name":"Ramada Inn Mission De Oro",
    "wof:placetype":"venue"
},
  "geometry": {"coordinates":[-121.015851,37.100027],"type":"Point"}
}