{
  "type": "Feature",
  "properties": {
    "addr:full":"320 Superior Ave Ste 240 Newport Beach CA 92663",
    "addr:housenumber":"320",
    "addr:postcode":"92663",
    "addr:street":"Superior Ave Ste 240",
    "iso:country":"US",
    "sg:address":"320 Superior Ave Ste 240",
    "sg:city":"Newport Beach",
    "sg:classifiers":[
        {
            "category":"Health Services",
            "subcategory":"Doctor",
            "type":"Services"
        }
    ],
    "sg:phone":"+1 949 548 5111",
    "sg:postcode":"92663",
    "sg:province":"CA",
    "wof:name":"Shukla Lakshmi S MD Fccp Inc",
    "wof:placetype":"venue"
},
  "geometry": {"coordinates":[-117.931,33.618301],"type":"Point"}
}