{
  "type": "Feature",
  "properties": {
    "iso:country":"US",
    "sg:address":"1860 Anaheim Ave",
    "sg:city":"Costa Mesa",
    "sg:classifiers":[
        {
            "category":"Building & Trades",
            "subcategory":"Construction",
            "type":"Services"
        }
    ],
    "sg:phone":"+1 949 453 2868",
    "sg:postcode":"92627",
    "sg:province":"CA",
    "sg:tags":[
        "coping",
        "plastering",
        "tiling",
        "pool",
        "swimming"
    ],
    "wof:name":"Swimming Pool Store",
    "wof:placetype":"venue"
},
  "geometry": {"coordinates":[-117.923284,33.641629],"type":"Point"}
}