{
  "type": "Feature",
  "properties": {
    "iso:country":"US",
    "sg:address":"8145 Enterprise Dr",
    "sg:city":"Newark",
    "sg:classifiers":[
        {
            "category":"Professional",
            "subcategory":"Business Services",
            "type":"Services"
        }
    ],
    "sg:phone":"+1 510 795 6160",
    "sg:postcode":"94560",
    "sg:province":"CA",
    "sg:tags":[
        "exporter",
        "export",
        "representative"
    ],
    "wof:name":"Coastal Overseas Export Corp",
    "wof:placetype":"venue"
},
  "geometry": {"coordinates":[-122.04600499999999,37.522745],"type":"Point"}
}