{
  "type": "Feature",
  "properties": {
    "addr:full":"10804 Norwalk Blvd Santa Fe Springs CA 90670",
    "addr:housenumber":"10804",
    "addr:postcode":"90670",
    "addr:street":"Norwalk Blvd",
    "iso:country":"US",
    "sg:address":"10804 Norwalk Blvd",
    "sg:city":"Santa Fe Springs",
    "sg:classifiers":[
        {
            "category":"Insurance",
            "subcategory":"Insurance Agent",
            "type":"Services"
        }
    ],
    "sg:phone":"+1 562 929 5075",
    "sg:postcode":"90670",
    "sg:province":"CA",
    "wof:name":"Top Gun Insurance",
    "wof:placetype":"venue"
},
  "geometry": {"coordinates":[-118.07261099999999,33.933794],"type":"Point"}
}