{
  "type": "Feature",
  "properties": {
    "addr:full":"17981 Dellglen Cir Huntington Beach CA 92647",
    "addr:postcode":"17981;92647",
    "addr:street":"Dellglen Cir",
    "iso:country":"US",
    "sg:address":"17981 Dellglen Cir",
    "sg:city":"Huntington Beach",
    "sg:classifiers":[
        {
            "category":"Building & Trades",
            "subcategory":"Landscaping Services",
            "type":"Services"
        }
    ],
    "sg:phone":"+1 714 842 0536",
    "sg:postcode":"92647",
    "sg:province":"CA",
    "wof:name":"Kohara Yoshihisa",
    "wof:placetype":"venue"
},
  "geometry": {"coordinates":[-118.02074,33.701263],"type":"Point"}
}