{
  "type": "Feature",
  "properties": {
    "addr:full":"919 E Hollyvale St Azusa CA 91702",
    "addr:housenumber":"919",
    "addr:postcode":"91702",
    "addr:street":"E Hollyvale St",
    "iso:country":"US",
    "sg:address":"919 E Hollyvale St",
    "sg:city":"Azusa",
    "sg:classifiers":[
        {
            "category":"Building & Trades",
            "subcategory":"Landscaping Services",
            "type":"Services"
        }
    ],
    "sg:phone":"+1 626 815 0278",
    "sg:postcode":"91702",
    "sg:province":"CA",
    "sg:tags":[
        "landscape",
        "contractor"
    ],
    "wof:name":"Leon Carlos Gardening",
    "wof:placetype":"venue"
},
  "geometry": {"coordinates":[-117.88900599999999,34.12662],"type":"Point"}
}