{
  "type": "Feature",
  "properties": {
    "addr:full":"203 Acadia St San Francisco CA 94131",
    "addr:housenumber":"203",
    "addr:postcode":"94131",
    "addr:street":"Acadia St",
    "iso:country":"US",
    "sg:address":"203 Acadia St",
    "sg:city":"San Francisco",
    "sg:classifiers":[
        {
            "category":"Manufacturing",
            "subcategory":"Toys & Sporting Goods",
            "type":"Manufacturing & Wholesale Goods"
        }
    ],
    "sg:phone":"+1 415 334 8885",
    "sg:postcode":"94131",
    "sg:province":"CA",
    "sg:tags":[
        "mfg"
    ],
    "wof:name":"Cultured Thread",
    "wof:placetype":"venue"
},
  "geometry": {"coordinates":[-122.43754,37.732925],"type":"Point"}
}