{
  "type": "Feature",
  "properties": {
    "addr:full":"275 W Rider St Perris CA 92571",
    "addr:housenumber":"275",
    "addr:postcode":"92571",
    "addr:street":"W Rider St",
    "iso:country":"US",
    "sg:address":"275 W Rider St",
    "sg:city":"Perris",
    "sg:classifiers":[
        {
            "category":"Manufacturing",
            "subcategory":"Rubber & Plastics",
            "type":"Manufacturing & Wholesale Goods"
        }
    ],
    "sg:phone":"+1 951 940 4556",
    "sg:postcode":"92571",
    "sg:province":"CA",
    "sg:tags":[
        "spa",
        "portable",
        "mfg"
    ],
    "wof:name":"Catalina Spas",
    "wof:placetype":"venue"
},
  "geometry": {"coordinates":[-117.23332000000001,33.830182],"type":"Point"}
}