{
  "type": "Feature",
  "properties": {
    "iso:country":"US",
    "sg:address":"1440 Lincoln Blvd",
    "sg:city":"Venice",
    "sg:classifiers":[
        {
            "category":"Health Services",
            "subcategory":"Doctor",
            "type":"Services"
        }
    ],
    "sg:phone":"+1 310 399 9900",
    "sg:postcode":"90291",
    "sg:province":"CA",
    "sg:tags":[
        "dentist"
    ],
    "wof:name":"Lincoln Dental Ctr",
    "wof:placetype":"venue"
},
  "geometry": {"coordinates":[-118.460255,33.997791],"type":"Point"}
}