{
  "type": "Feature",
  "properties": {
    "addr:full":"1926 Broderick Street San Francisco CA 94115",
    "addr:housenumber":"1926",
    "addr:postcode":"94115",
    "addr:street":"Broderick Street",
    "iso:country":"US",
    "sg:address":"1926 Broderick Street",
    "sg:city":"San Francisco",
    "sg:classifiers":[
        {
            "category":"Food & Beverages",
            "subcategory":"Liquor & Beverages",
            "type":"Retail Goods"
        },
        {
            "category":"Wholesale",
            "subcategory":"Fruits & Vegetables",
            "type":"Manufacturing & Wholesale Goods"
        },
        {
            "category":"Food & Beverages",
            "subcategory":"Groceries & Convenience Stores",
            "type":"Retail Goods"
        }
    ],
    "sg:phone":"+1 415 928 2867",
    "sg:postcode":"94115",
    "sg:province":"CA",
    "sg:tags":[
        "beer",
        "wine",
        "veggie",
        "spirit"
    ],
    "wof:name":"Christa Wonderful Market",
    "wof:placetype":"venue"
},
  "geometry": {"coordinates":[-122.442001,37.7882],"type":"Point"}
}