{
  "type": "Feature",
  "properties": {
    "iso:country":"US",
    "sg:address":"1121 11th Ave",
    "sg:city":"Oakland",
    "sg:classifiers":[
        {
            "category":"Manufacturing",
            "subcategory":"Buildings",
            "type":"Manufacturing & Wholesale Goods"
        },
        {
            "category":"Building & Trades",
            "subcategory":"Construction",
            "type":"Services"
        }
    ],
    "sg:phone":"+1 510 467 7838",
    "sg:postcode":"94606",
    "sg:province":"CA",
    "sg:tags":[
        "home",
        "builder",
        "contractor"
    ],
    "wof:name":"D T G Construction",
    "wof:placetype":"venue"
},
  "geometry": {"coordinates":[-122.24995,37.790555],"type":"Point"}
}