{
  "type": "Feature",
  "properties": {
    "iso:country":"US",
    "sg:address":"4513 N Sunnyside Ave",
    "sg:city":"Fresno",
    "sg:classifiers":[
        {
            "category":"Utilities",
            "subcategory":"Telephone",
            "type":"Services"
        }
    ],
    "sg:phone":"+1 559 347 9277",
    "sg:postcode":"93727",
    "sg:province":"CA",
    "sg:tags":[
        "communications"
    ],
    "wof:name":"Way Cool Reflections",
    "wof:placetype":"venue"
},
  "geometry": {"coordinates":[-119.69158,36.798565],"type":"Point"}
}