{
  "type": "Feature",
  "properties": {
    "addr:full":"305 Greenhorn Rd Yreka CA 96097",
    "addr:housenumber":"305",
    "addr:postcode":"96097",
    "addr:street":"Greenhorn Rd",
    "iso:country":"US",
    "sg:address":"305 Greenhorn Rd",
    "sg:city":"Yreka",
    "sg:classifiers":[
        {
            "category":"Freight",
            "type":"Transportation"
        }
    ],
    "sg:phone":"+1 530 841 1309",
    "sg:postcode":"96097",
    "sg:province":"CA",
    "sg:tags":[
        "commercial",
        "storage"
    ],
    "wof:name":"Park Mini Storage",
    "wof:placetype":"venue"
},
  "geometry": {"coordinates":[-122.648695,41.712007],"type":"Point"}
}