{
  "type": "Feature",
  "properties": {
    "iso:country":"US",
    "sg:address":"171 W 4th St",
    "sg:city":"Pomona",
    "sg:classifiers":[
        {
            "category":"Sports & Exercise",
            "subcategory":"Gym",
            "type":"Entertainment"
        }
    ],
    "sg:phone":"+1 909 623 7612",
    "sg:postcode":"91766",
    "sg:province":"CA",
    "sg:tags":[
        "club",
        "health",
        "studio",
        "gymnasium"
    ],
    "wof:name":"Curves For Women",
    "wof:placetype":"venue"
},
  "geometry": {"coordinates":[-117.750528,34.056098],"type":"Point"}
}