{
  "type": "Feature",
  "properties": {
    "iso:country":"US",
    "sg:address":"13752 S Ainsworth St",
    "sg:city":"Gardena",
    "sg:classifiers":[
        {
            "category":"Professional",
            "type":"Services"
        }
    ],
    "sg:phone":"+1 310 715 2953",
    "sg:postcode":"90247",
    "sg:province":"CA",
    "sg:tags":[
        "establishment"
    ],
    "wof:name":"Spot Free",
    "wof:placetype":"venue"
},
  "geometry": {"coordinates":[-118.29028,33.908598],"type":"Point"}
}