{
  "type": "Feature",
  "properties": {
    "addr:full":"260 S Cimmeron Trl Glendora CA 91741",
    "addr:housenumber":"260",
    "addr:postcode":"91741",
    "addr:street":"S Cimmeron Trl",
    "iso:country":"US",
    "sg:address":"260 S Cimmeron Trl",
    "sg:city":"Glendora",
    "sg:classifiers":[
        {
            "category":"Professional",
            "type":"Services"
        }
    ],
    "sg:phone":"+1 626 335 4122",
    "sg:postcode":"91741",
    "sg:province":"CA",
    "wof:name":"Barrett A French Inc",
    "wof:placetype":"venue"
},
  "geometry": {"coordinates":[-117.83085699999999,34.132983],"type":"Point"}
}