{
  "type": "Feature",
  "properties": {
    "addr:full":"9375 E 9th St Rancho Cucamonga CA 91730",
    "addr:housenumber":"9375",
    "addr:postcode":"91730",
    "addr:street":"E 9Th St",
    "iso:country":"US",
    "sg:address":"9375 E 9th St",
    "sg:city":"Rancho Cucamonga",
    "sg:classifiers":[
        {
            "category":"Education",
            "subcategory":"College",
            "type":"Public Place"
        }
    ],
    "sg:phone":"+1 909 477 8675",
    "sg:postcode":"91730",
    "sg:province":"CA",
    "sg:tags":[
        "academic",
        "school"
    ],
    "wof:name":"Chaffey College Learning Ctr",
    "wof:placetype":"venue"
},
  "geometry": {"coordinates":[-117.601489,34.095629],"type":"Point"}
}