{
  "type": "Feature",
  "properties": {
    "addr:full":"7235 Watt Ave North Highlands CA 95660",
    "addr:housenumber":"7235",
    "addr:postcode":"95660",
    "addr:street":"Watt Ave",
    "iso:country":"US",
    "sg:address":"7235 Watt Ave",
    "sg:city":"North Highlands",
    "sg:classifiers":[
        {
            "category":"Retail",
            "subcategory":"Auto Repair",
            "type":"Services"
        }
    ],
    "sg:phone":"+1 916 344 1444",
    "sg:postcode":"95660",
    "sg:province":"CA",
    "sg:tags":[
        "recreational",
        "vehicle"
    ],
    "wof:name":"Stevens Auto Repair",
    "wof:placetype":"venue"
},
  "geometry": {"coordinates":[-121.382891,38.698373],"type":"Point"}
}