{
  "type": "Feature",
  "properties": {
    "iso:country":"US",
    "sg:address":"4343 Stevens Creek Blvd",
    "sg:city":"Santa Clara",
    "sg:classifiers":[
        {
            "category":"Autos & Motor Vehicles",
            "subcategory":"Automobile Sales",
            "type":"Retail Goods"
        }
    ],
    "sg:phone":"+1 408 249 9070",
    "sg:postcode":"95051",
    "sg:province":"CA",
    "sg:tags":[
        "repair",
        "car"
    ],
    "sg:website":"www.stevenscreekbmw.com/",
    "wof:name":"Stevens Creek BMW",
    "wof:placetype":"venue"
},
  "geometry": {"coordinates":[-121.976997,37.323002],"type":"Point"}
}