{
  "type": "Feature",
  "properties": {
    "addr:full":"40 Sandy Creek Way Novato CA 94945",
    "addr:housenumber":"40",
    "addr:postcode":"94945",
    "addr:street":"Sandy Creek Way",
    "iso:country":"US",
    "sg:address":"40 Sandy Creek Way",
    "sg:city":"Novato",
    "sg:classifiers":[
        {
            "category":"Manufacturing",
            "subcategory":"Food",
            "type":"Manufacturing & Wholesale Goods"
        }
    ],
    "sg:phone":"+1 415 897 2468",
    "sg:postcode":"94945",
    "sg:province":"CA",
    "sg:tags":[
        "seafood",
        "product",
        "fish",
        "prepared"
    ],
    "wof:name":"Ocean Seafood Marketing Co",
    "wof:placetype":"venue"
},
  "geometry": {"coordinates":[-122.61444899999999,38.120299],"type":"Point"}
}