{
  "type": "Feature",
  "properties": {
    "iso:country":"US",
    "sg:address":"557 Hot Springs Rd",
    "sg:city":"Montecito",
    "sg:classifiers":[
        {
            "category":"Shopping",
            "type":"Retail Goods"
        }
    ],
    "sg:phone":"+1 805 969 5781",
    "sg:postcode":"93108",
    "sg:province":"CA",
    "sg:tags":[
        "art",
        "gallery",
        "dealer"
    ],
    "wof:name":"Easton Gallery",
    "wof:placetype":"venue"
},
  "geometry": {"coordinates":[-119.64186100000001,34.437714],"type":"Point"}
}