{
  "type": "Feature",
  "properties": {
    "addr:full":"40646 171st St E Lancaster CA 93535",
    "addr:housenumber":"40646",
    "addr:postcode":"93535",
    "addr:street":"171St St E",
    "iso:country":"US",
    "sg:address":"40646 171st St E",
    "sg:city":"Lancaster",
    "sg:classifiers":[
        {
            "category":"Farming",
            "subcategory":"Farm & Veterinary Services",
            "type":"Manufacturing & Wholesale Goods"
        }
    ],
    "sg:phone":"+1 661 264 4027",
    "sg:postcode":"93535",
    "sg:province":"CA",
    "sg:tags":[
        "poultry",
        "producer"
    ],
    "wof:name":"Frank Jackson",
    "wof:placetype":"venue"
},
  "geometry": {"coordinates":[-117.825695,34.620809],"type":"Point"}
}