{
  "type": "Feature",
  "properties": {
    "iso:country":"US",
    "sg:address":"17565 Valley Blvd",
    "sg:city":"Bloomington",
    "sg:classifiers":[
        {
            "category":"Shopping",
            "subcategory":"Pawn Shop",
            "type":"Retail Goods"
        }
    ],
    "sg:phone":"+1 909 465 3874",
    "sg:postcode":"92316",
    "sg:province":"CA",
    "sg:tags":[
        "pawnbroker"
    ],
    "sg:website":"http://www.chinocashforgold.com",
    "wof:name":"Fontana Cash for Gold",
    "wof:placetype":"venue"
},
  "geometry": {"coordinates":[-117.42115099999999,34.070426],"type":"Point"}
}