{
  "type": "Feature",
  "properties": {
    "addr:full":"1443 Danville Blvd Alamo CA 94507",
    "addr:housenumber":"1443",
    "addr:postcode":"94507",
    "addr:street":"Danville Blvd",
    "iso:country":"US",
    "sg:address":"1443 Danville Blvd",
    "sg:city":"Alamo",
    "sg:classifiers":[
        {
            "category":"Government",
            "subcategory":"Office",
            "type":"Public Place"
        }
    ],
    "sg:phone":"+1 925 838 6070",
    "sg:postcode":"94507",
    "sg:province":"CA",
    "sg:tags":[
        "educational",
        "program",
        "administrative",
        "insurance"
    ],
    "wof:name":"Beta Health Care Group",
    "wof:placetype":"venue"
},
  "geometry": {"coordinates":[-122.029554,37.845754],"type":"Point"}
}