{
  "type": "Feature",
  "properties": {
    "iso:country":"US",
    "sg:address":"36056 Firethorn Dr",
    "sg:city":"Palm Desert",
    "sg:classifiers":[
        {
            "category":"Wholesale",
            "subcategory":"Non-durable Goods",
            "type":"Manufacturing & Wholesale Goods"
        }
    ],
    "sg:phone":"+1 760 360 4166",
    "sg:postcode":"92211",
    "sg:province":"CA",
    "wof:name":"American Ad Specialties",
    "wof:placetype":"venue"
},
  "geometry": {"coordinates":[-116.293641,33.787408],"type":"Point"}
}