{
  "type": "Feature",
  "properties": {
    "addr:full":"The District at Tustin Legacy 2487 Park Ave Tustin CA 92782",
    "addr:housenumber":"2487",
    "addr:postcode":"92782",
    "addr:street":"Park Ave",
    "iso:country":"US",
    "sg:address":"The District at Tustin Legacy 2487 Park Ave",
    "sg:city":"Tustin",
    "sg:classifiers":[
        {
            "category":"Restaurant",
            "type":"Food & Drink"
        }
    ],
    "sg:phone":"+1 714 259 7738",
    "sg:postcode":"92782",
    "sg:province":"CA",
    "sg:tags":[
        "fusion",
        "asian",
        "vietnamese"
    ],
    "sg:website":"www.asianmint.net",
    "wof:name":"Asian Mint",
    "wof:placetype":"venue"
},
  "geometry": {"coordinates":[-117.826891,33.698279],"type":"Point"}
}