{
  "type": "Feature",
  "properties": {
    "iso:country":"US",
    "sg:address":"910 Highland Ave",
    "sg:city":"National City",
    "sg:classifiers":[
        {
            "category":"Retail",
            "subcategory":"Auto Repair",
            "type":"Services"
        }
    ],
    "sg:phone":"+1 619 474 4500",
    "sg:postcode":"91950",
    "sg:province":"CA",
    "sg:tags":[
        "brake"
    ],
    "wof:name":"Brake Depot",
    "wof:placetype":"venue"
},
  "geometry": {"coordinates":[-117.098457,32.677339],"type":"Point"}
}