{
  "type": "Feature",
  "properties": {
    "iso:country":"US",
    "sg:address":"217 E Alameda Ave Ste 301",
    "sg:city":"Burbank",
    "sg:classifiers":[
        {
            "category":"Communications",
            "subcategory":"Newspaper",
            "type":"Services"
        }
    ],
    "sg:phone":"+1 818 848 2957",
    "sg:postcode":"91502",
    "sg:province":"CA",
    "sg:tags":[
        "print",
        "medium"
    ],
    "wof:name":"McGee Publishers",
    "wof:placetype":"venue"
},
  "geometry": {"coordinates":[-118.300003,34.174702],"type":"Point"}
}