{
  "type": "Feature",
  "properties": {
    "iso:country":"US",
    "sg:address":"12722 Ave 416",
    "sg:city":"Orosi",
    "sg:classifiers":[
        {
            "category":"Shopping",
            "subcategory":"Clothing, Apparel, & Fashions",
            "type":"Retail Goods"
        }
    ],
    "sg:phone":"+1 559 626 8433",
    "sg:postcode":"93647",
    "sg:province":"CA",
    "wof:name":"Joyerea Y Boutique Teresita",
    "wof:placetype":"venue"
},
  "geometry": {"coordinates":[-119.28903,36.544908],"type":"Point"}
}