{
  "type": "Feature",
  "properties": {
    "iso:country":"US",
    "sg:address":"21795 Graham Rd",
    "sg:city":"Manton",
    "sg:classifiers":[
        {
            "category":"Farming",
            "subcategory":"Orchard",
            "type":"Manufacturing & Wholesale Goods"
        }
    ],
    "sg:phone":"+1 530 474 5191",
    "sg:postcode":"96059",
    "sg:province":"CA",
    "sg:tags":[
        "fruit",
        "tree"
    ],
    "wof:name":"Dove Acres",
    "wof:placetype":"venue"
},
  "geometry": {"coordinates":[-121.838459,40.424483],"type":"Point"}
}