{
  "type": "Feature",
  "properties": {
    "iso:country":"US",
    "sg:address":"1750 Timothy Dr",
    "sg:city":"San Leandro",
    "sg:classifiers":[
        {
            "category":"Wholesale",
            "subcategory":"Groceries",
            "type":"Manufacturing & Wholesale Goods"
        }
    ],
    "sg:phone":"+1 510 483 6642",
    "sg:postcode":"94577",
    "sg:province":"CA",
    "sg:tags":[
        "general"
    ],
    "wof:name":"Ramos Distributors",
    "wof:placetype":"venue"
},
  "geometry": {"coordinates":[-122.173621,37.715214],"type":"Point"}
}