{
  "type": "Feature",
  "properties": {
    "addr:full":"5665 N Fresno St Fresno CA 93710",
    "addr:housenumber":"5665",
    "addr:postcode":"93710",
    "addr:street":"N Fresno",
    "iso:country":"US",
    "sg:address":"5665 N Fresno St",
    "sg:city":"Fresno",
    "sg:classifiers":[
        {
            "category":"Shopping",
            "subcategory":"Computers & Home Electronics",
            "type":"Retail Goods"
        }
    ],
    "sg:phone":"+1 209 967 2954",
    "sg:postcode":"93710",
    "sg:province":"CA",
    "sg:tags":[
        "equipment",
        "dealer"
    ],
    "wof:name":"Virtual Vision",
    "wof:placetype":"venue"
},
  "geometry": {"coordinates":[-119.78139400000001,36.821801],"type":"Point"}
}