{
  "type": "Feature",
  "properties": {
    "addr:full":"4412 Ming Ave Bakersfield CA 93309",
    "addr:housenumber":"4412",
    "addr:postcode":"93309",
    "addr:street":"Ming Ave",
    "iso:country":"US",
    "sg:address":"4412 Ming Ave",
    "sg:city":"Bakersfield",
    "sg:classifiers":[
        {
            "category":"Restaurant",
            "type":"Food & Drink"
        }
    ],
    "sg:phone":"+1 661 398 0608",
    "sg:postcode":"93309",
    "sg:province":"CA",
    "wof:name":"Izumo Sushi",
    "wof:placetype":"venue"
},
  "geometry": {"coordinates":[-119.051846,35.339654],"type":"Point"}
}