{
  "type": "Feature",
  "properties": {
    "iso:country":"US",
    "sg:address":"501 Valley Blvd",
    "sg:city":"Big Bear City",
    "sg:classifiers":[
        {
            "category":"Restaurant",
            "type":"Food & Drink"
        }
    ],
    "sg:phone":"+1 909 585 1818",
    "sg:postcode":"92314",
    "sg:province":"CA",
    "wof:name":"Mandarin Garden",
    "wof:placetype":"venue"
},
  "geometry": {"coordinates":[-116.853084,34.261114],"type":"Point"}
}