{
  "type": "Feature",
  "properties": {
    "addr:full":"9265 Dowdy Dr San Diego CA 92126",
    "addr:housenumber":"9265",
    "addr:postcode":"92126",
    "addr:street":"Dowdy Dr",
    "iso:country":"US",
    "sg:address":"9265 Dowdy Dr",
    "sg:city":"San Diego",
    "sg:classifiers":[
        {
            "category":"Utilities",
            "subcategory":"Cable",
            "type":"Services"
        }
    ],
    "sg:phone":"+1 858 527 1091",
    "sg:postcode":"92126",
    "sg:province":"CA",
    "sg:tags":[
        "television"
    ],
    "wof:name":"Pacific States Cable Svc Inc",
    "wof:placetype":"venue"
},
  "geometry": {"coordinates":[-117.145742,32.88868],"type":"Point"}
}