{
  "type": "Feature",
  "properties": {
    "iso:country":"US",
    "sg:address":"2409 Merced Ave",
    "sg:city":"South El Monte",
    "sg:classifiers":[
        {
            "category":"Shopping",
            "subcategory":"Clothing, Apparel, & Fashions",
            "type":"Retail Goods"
        }
    ],
    "sg:phone":"+1 626 448 3480",
    "sg:postcode":"91733",
    "sg:province":"CA",
    "wof:name":"J M Garment Inc",
    "wof:placetype":"venue"
},
  "geometry": {"coordinates":[-118.051367,34.058953],"type":"Point"}
}