{
  "type": "Feature",
  "properties": {
    "iso:country":"US",
    "sg:address":"650 N Priscilla Ln",
    "sg:city":"Burbank",
    "sg:classifiers":[
        {
            "category":"Professional",
            "type":"Services"
        }
    ],
    "sg:phone":"+1 818 843 7739",
    "sg:postcode":"91505",
    "sg:province":"CA",
    "wof:name":"Applied Information Sciences I",
    "wof:placetype":"venue"
},
  "geometry": {"coordinates":[-118.35048999999999,34.161729],"type":"Point"}
}