{
  "type": "Feature",
  "properties": {
    "iso:country":"US",
    "sg:address":"37471 Fremont Blvd",
    "sg:city":"Fremont",
    "sg:classifiers":[
        {
            "category":"Personal",
            "subcategory":"Beauty Salon",
            "type":"Services"
        }
    ],
    "sg:phone":"+1 510 792 6849",
    "sg:postcode":"94536",
    "sg:province":"CA",
    "wof:name":"Cutting Edge Salon",
    "wof:placetype":"venue"
},
  "geometry": {"coordinates":[-122.006201,37.557688],"type":"Point"}
}