{
  "type": "Feature",
  "properties": {
    "iso:country":"US",
    "sg:address":"919 Manhattan Ave Ste A",
    "sg:city":"Manhattan Beach",
    "sg:classifiers":[
        {
            "category":"Shopping",
            "subcategory":"Gifts & Souvenirs",
            "type":"Retail Goods"
        },
        {
            "category":"Home & Garden",
            "subcategory":"Home Furnishings",
            "type":"Retail Goods"
        }
    ],
    "sg:phone":"+1 310 318 3385",
    "sg:postcode":"90266",
    "sg:province":"CA",
    "sg:tags":[
        "decor",
        "flower"
    ],
    "sg:website":"www.tabularasaessentials.com",
    "wof:name":"Tabula Rasa Essentials",
    "wof:placetype":"venue"
},
  "geometry": {"coordinates":[-118.40986,33.883157],"type":"Point"}
}