{
  "type": "Feature",
  "properties": {
    "addr:full":"36th Avenue & Hacien San Mateo CA 94401",
    "addr:postcode":"94401",
    "addr:street":"36Th Avenue & Hacien",
    "iso:country":"US",
    "sg:address":"36th Avenue & Hacien",
    "sg:city":"San Mateo",
    "sg:classifiers":[
        {
            "category":"Education",
            "subcategory":"Preschool",
            "type":"Public Place"
        },
        {
            "category":"Education",
            "subcategory":"School",
            "type":"Public Place"
        }
    ],
    "sg:phone":"+1 650 570 6196",
    "sg:postcode":"94401",
    "sg:province":"CA",
    "sg:tags":[
        "elementary"
    ],
    "wof:name":"Childrens School Hillsdale United Methodist Church",
    "wof:placetype":"venue"
},
  "geometry": {"coordinates":[-122.321634,37.571445],"type":"Point"}
}