{
  "type": "Feature",
  "properties": {
    "addr:full":"1964 Pacific Coast Hwy Lomita CA 90717",
    "addr:housenumber":"1964",
    "addr:postcode":"90717",
    "addr:street":"Pacific Coast Hwy",
    "iso:country":"US",
    "sg:address":"1964 Pacific Coast Hwy",
    "sg:city":"Lomita",
    "sg:classifiers":[
        {
            "category":"Personal",
            "subcategory":"Barber",
            "type":"Services"
        }
    ],
    "sg:phone":"+1 310 325 3243",
    "sg:postcode":"90717",
    "sg:province":"CA",
    "wof:name":"Don's Barber Room",
    "wof:placetype":"venue"
},
  "geometry": {"coordinates":[-118.314003,33.7896],"type":"Point"}
}