{
  "type": "Feature",
  "properties": {
    "iso:country":"US",
    "sg:address":"5768 Paradise Dr",
    "sg:city":"Corte Madera",
    "sg:classifiers":[
        {
            "category":"Recreation",
            "type":"Entertainment"
        }
    ],
    "sg:phone":"+1 415 927 0899",
    "sg:postcode":"94925",
    "sg:province":"CA",
    "sg:tags":[
        "martial",
        "arts",
        "instruction"
    ],
    "wof:name":"Marin Karate Kids",
    "wof:placetype":"venue"
},
  "geometry": {"coordinates":[-122.511976,37.927326],"type":"Point"}
}