{
  "type": "Feature",
  "properties": {
    "iso:country":"US",
    "sg:address":"1901 Westcliff Dr Ste 2",
    "sg:city":"Newport Beach",
    "sg:classifiers":[
        {
            "category":"Health Services",
            "subcategory":"Doctor",
            "type":"Services"
        }
    ],
    "sg:phone":"+1 949 631 4890",
    "sg:postcode":"92660",
    "sg:province":"CA",
    "wof:name":"Hurwitz Michael MD",
    "wof:placetype":"venue"
},
  "geometry": {"coordinates":[-117.905998,33.626701],"type":"Point"}
}