{
  "type": "Feature",
  "properties": {
    "iso:country":"US",
    "sg:address":"611 Manwell Blvd",
    "sg:city":"Bakersfield",
    "sg:classifiers":[
        {
            "category":"Wholesale",
            "subcategory":"Machinery & Supplies",
            "type":"Manufacturing & Wholesale Goods"
        }
    ],
    "sg:phone":"+1 661 364 0161",
    "sg:postcode":"93307",
    "sg:province":"CA",
    "sg:tags":[
        "truck"
    ],
    "wof:name":"All-Lift Equipment Inc",
    "wof:placetype":"venue"
},
  "geometry": {"coordinates":[-118.915973,35.350176],"type":"Point"}
}