{
  "type": "Feature",
  "properties": {
    "addr:full":"120 S Spalding Dr Beverly Hills CA 90212",
    "addr:housenumber":"120",
    "addr:postcode":"90212",
    "addr:street":"S Spalding Dr",
    "iso:country":"US",
    "sg:address":"120 S Spalding Dr",
    "sg:city":"Beverly Hills",
    "sg:classifiers":[
        {
            "category":"Health Services",
            "subcategory":"Doctor",
            "type":"Services"
        }
    ],
    "sg:phone":"+1 310 275 2467",
    "sg:postcode":"90212",
    "sg:province":"CA",
    "sg:tags":[
        "physician",
        "surgeon"
    ],
    "sg:website":"www.spaldingplasticsurgery.com",
    "wof:name":"Spalding Drive Cosmetic Surgry",
    "wof:placetype":"venue"
},
  "geometry": {"coordinates":[-118.408812,34.065402],"type":"Point"}
}