{
  "type": "Feature",
  "properties": {
    "iso:country":"US",
    "sg:address":"860 el Camino Ave",
    "sg:city":"Vacaville",
    "sg:classifiers":[
        {
            "category":"Real Estate",
            "subcategory":"Real Estate Operator",
            "type":"Services"
        }
    ],
    "sg:phone":"+1 707 453 0933",
    "sg:postcode":"95688",
    "sg:province":"CA",
    "sg:tags":[
        "apartment"
    ],
    "wof:name":"Montgomery Apartments",
    "wof:placetype":"venue"
},
  "geometry": {"coordinates":[-122.00058799999999,38.348911],"type":"Point"}
}