{
  "type": "Feature",
  "properties": {
    "addr:full":"1801 Bayshore Hwy Burlingame CA 94010",
    "addr:housenumber":"1801",
    "addr:postcode":"94010",
    "addr:street":"Bayshore Hwy",
    "iso:country":"US",
    "sg:address":"1801 Bayshore Hwy",
    "sg:city":"Burlingame",
    "sg:classifiers":[
        {
            "category":"Airline",
            "type":"Transportation"
        }
    ],
    "sg:phone":"+1 650 777 9910",
    "sg:postcode":"94010",
    "sg:province":"CA",
    "sg:tags":[
        "courier",
        "air"
    ],
    "sg:website":"www.wcground.com",
    "wof:name":"World Courier",
    "wof:placetype":"venue"
},
  "geometry": {"coordinates":[-122.373605,37.603329],"type":"Point"}
}