{
  "type": "Feature",
  "properties": {
    "iso:country":"US",
    "sg:address":"1049 Magnolia Ave",
    "sg:city":"Long Beach",
    "sg:classifiers":[
        {
            "category":"Home & Garden",
            "subcategory":"Building Materials",
            "type":"Retail Goods"
        }
    ],
    "sg:phone":"+1 562 436 2616",
    "sg:postcode":"90813",
    "sg:province":"CA",
    "sg:tags":[
        "glass",
        "window",
        "plate"
    ],
    "wof:name":"J C Glass & Mirrors",
    "wof:placetype":"venue"
},
  "geometry": {"coordinates":[-118.198097,33.779583],"type":"Point"}
}