{
  "type": "Feature",
  "properties": {
    "addr:full":"4949 Great America Pkwy Santa Clara CA 95054",
    "addr:housenumber":"4949",
    "addr:postcode":"95054",
    "addr:street":"Great America Pkwy",
    "iso:country":"US",
    "sg:address":"4949 Great America Pkwy",
    "sg:city":"Santa Clara",
    "sg:classifiers":[
        {
            "category":"Travel",
            "subcategory":"Hotels & Motels",
            "type":"Entertainment"
        }
    ],
    "sg:phone":"+1 408 330 0001",
    "sg:postcode":"95054",
    "sg:province":"CA",
    "sg:website":"www.santaclara.hilton.com",
    "wof:name":"Hilton Santa Clara",
    "wof:placetype":"venue"
},
  "geometry": {"coordinates":[-121.976778,37.402546],"type":"Point"}
}