{
  "type": "Feature",
  "properties": {
    "iso:country":"US",
    "sg:address":"12167 Ave 400",
    "sg:city":"Cutler",
    "sg:classifiers":[
        {
            "category":"Manufacturing",
            "subcategory":"Retail Goods",
            "type":"Manufacturing & Wholesale Goods"
        }
    ],
    "sg:phone":"+1 559 528 0800",
    "sg:postcode":"93615",
    "sg:province":"CA",
    "sg:tags":[
        "manufacturer"
    ],
    "wof:name":"Eagle Manufacturing",
    "wof:placetype":"venue"
},
  "geometry": {"coordinates":[-119.298991,36.515756],"type":"Point"}
}