{
  "type": "Feature",
  "properties": {
    "addr:full":"4 N Tower Sq Tulare CA 93274",
    "addr:housenumber":"4",
    "addr:postcode":"93274",
    "addr:street":"N Tower Sq",
    "iso:country":"US",
    "sg:address":"4 N Tower Sq",
    "sg:city":"Tulare",
    "sg:classifiers":[
        {
            "category":"Personal",
            "subcategory":"Beauty Salon",
            "type":"Services"
        }
    ],
    "sg:phone":"+1 559 688 5222",
    "sg:postcode":"93274",
    "sg:province":"CA",
    "wof:name":"L J's Salon",
    "wof:placetype":"venue"
},
  "geometry": {"coordinates":[-119.347528,36.209216],"type":"Point"}
}