{
  "type": "Feature",
  "properties": {
    "iso:country":"US",
    "sg:address":"306 E Alton Ave",
    "sg:city":"Santa Ana",
    "sg:classifiers":[
        {
            "category":"Home & Garden",
            "subcategory":"Building Materials",
            "type":"Retail Goods"
        }
    ],
    "sg:phone":"+1 714 557 7212",
    "sg:postcode":"92707",
    "sg:province":"CA",
    "sg:tags":[
        "glass",
        "window",
        "plate"
    ],
    "sg:website":"www.goldcoastglass.com",
    "wof:name":"Gold Coast Glass Co",
    "wof:placetype":"venue"
},
  "geometry": {"coordinates":[-117.86379100000001,33.704969],"type":"Point"}
}