{
  "type": "Feature",
  "properties": {
    "addr:full":"13851 E 14th St San Leandro CA 94578",
    "addr:housenumber":"13851",
    "addr:postcode":"94578",
    "addr:street":"E 14Th St",
    "iso:country":"US",
    "sg:address":"13851 E 14th St",
    "sg:city":"San Leandro",
    "sg:classifiers":[
        {
            "category":"Health Services",
            "subcategory":"Doctor",
            "type":"Services"
        }
    ],
    "sg:phone":"+1 510 483 9007",
    "sg:postcode":"94578",
    "sg:province":"CA",
    "sg:tags":[
        "physician",
        "surgeon"
    ],
    "wof:name":"Stanley I Hegg MD",
    "wof:placetype":"venue"
},
  "geometry": {"coordinates":[-122.14243999999999,37.71507],"type":"Point"}
}