{
  "type": "Feature",
  "properties": {
    "iso:country":"US",
    "sg:address":"1309 Camino Del Mar",
    "sg:city":"Del Mar",
    "sg:classifiers":[
        {
            "category":"Education",
            "subcategory":"Library",
            "type":"Public Place"
        }
    ],
    "sg:phone":"+1 858 755 1666",
    "sg:postcode":"92014",
    "sg:province":"CA",
    "sg:website":"www.sdcl.org/locations_DM.html#s...",
    "wof:name":"Del Mar Library",
    "wof:placetype":"venue"
},
  "geometry": {"coordinates":[-117.26435600000001,32.957802],"type":"Point"}
}