{
  "type": "Feature",
  "properties": {
    "addr:full":"3951 Alemany Blvd San Francisco CA 94132",
    "addr:housenumber":"3951",
    "addr:postcode":"94132",
    "addr:street":"Alemany Blvd",
    "iso:country":"US",
    "sg:address":"3951 Alemany Blvd",
    "sg:city":"San Francisco",
    "sg:classifiers":[
        {
            "category":"Sports & Exercise",
            "subcategory":"Gym",
            "type":"Entertainment"
        }
    ],
    "sg:phone":"+1 650 985 2400",
    "sg:postcode":"94132",
    "sg:province":"CA",
    "sg:website":"www.ballyfitness.com",
    "wof:name":"Bally Total Fitness",
    "wof:placetype":"venue"
},
  "geometry": {"coordinates":[-122.46853299999999,37.710832],"type":"Point"}
}