{
  "type": "Feature",
  "properties": {
    "iso:country":"US",
    "sg:address":"299 Fair Ln",
    "sg:city":"Placerville",
    "sg:classifiers":[
        {
            "category":"Social Services",
            "subcategory":"Adult Care",
            "type":"Services"
        },
        {
            "category":"Government",
            "subcategory":"Office",
            "type":"Public Place"
        }
    ],
    "sg:phone":"+1 530 621 5589",
    "sg:postcode":"95667",
    "sg:province":"CA",
    "sg:tags":[
        "residential",
        "executive"
    ],
    "sg:website":"www.eldoradocounty.net",
    "wof:name":"El Dorado County Juvenile Hall",
    "wof:placetype":"venue"
},
  "geometry": {"coordinates":[-120.82832500000001,38.724024],"type":"Point"}
}