{
  "type": "Feature",
  "properties": {
    "addr:full":"316 N 7th St San Jose CA 95112",
    "addr:housenumber":"316",
    "addr:postcode":"95112",
    "addr:street":"N 7Th St",
    "iso:country":"US",
    "sg:address":"316 N 7th St",
    "sg:city":"San Jose",
    "sg:classifiers":[
        {
            "category":"Personal",
            "type":"Services"
        }
    ],
    "sg:phone":"+1 408 885 0222",
    "sg:postcode":"95112",
    "sg:province":"CA",
    "sg:tags":[
        "towing"
    ],
    "wof:name":"All American Towing",
    "wof:placetype":"venue"
},
  "geometry": {"coordinates":[-121.88800000000001,37.344101],"type":"Point"}
}