{
  "type": "Feature",
  "properties": {
    "iso:country":"US",
    "sg:address":"17330 Halsted St",
    "sg:city":"Northridge",
    "sg:classifiers":[
        {
            "category":"Recreation",
            "type":"Entertainment"
        }
    ],
    "sg:phone":"+1 818 993 6793",
    "sg:postcode":"91325",
    "sg:province":"CA",
    "sg:tags":[
        "club",
        "membership"
    ],
    "wof:name":"Valley Rv Club",
    "wof:placetype":"venue"
},
  "geometry": {"coordinates":[-118.513969,34.244725],"type":"Point"}
}