{
  "type": "Feature",
  "properties": {
    "addr:full":"16919 Donna Ynez Ln Pacific Plsds CA 90272",
    "addr:housenumber":"16919",
    "addr:postcode":"90272",
    "addr:street":"Donna Ynez Ln",
    "iso:country":"US",
    "sg:address":"16919 Donna Ynez Ln",
    "sg:city":"Pacific Plsds",
    "sg:classifiers":[
        {
            "category":"Professional",
            "subcategory":"Management & Consulting",
            "type":"Services"
        }
    ],
    "sg:phone":"+1 310 454 8082",
    "sg:postcode":"90272",
    "sg:province":"CA",
    "sg:tags":[
        "consultant",
        "business"
    ],
    "wof:name":"Telemedia Solutions",
    "wof:placetype":"venue"
},
  "geometry": {"coordinates":[-118.54973,34.047928],"type":"Point"}
}