{
  "type": "Feature",
  "properties": {
    "addr:full":"1659 Scott Blvd Santa Clara CA 95050",
    "addr:housenumber":"1659",
    "addr:postcode":"95050",
    "addr:street":"Scott Blvd",
    "iso:country":"US",
    "sg:address":"1659 Scott Blvd",
    "sg:city":"Santa Clara",
    "sg:classifiers":[
        {
            "category":"Health Services",
            "subcategory":"Doctor",
            "type":"Services"
        }
    ],
    "sg:phone":"+1 408 879 0110",
    "sg:postcode":"95050",
    "sg:province":"CA",
    "sg:tags":[
        "dentist"
    ],
    "wof:name":"Dentistry In Motion",
    "wof:placetype":"venue"
},
  "geometry": {"coordinates":[-121.959362,37.354113],"type":"Point"}
}