{
  "type": "Feature",
  "properties": {
    "addr:full":"13434 Lincoln Way Auburn CA 95603",
    "addr:housenumber":"13434",
    "addr:postcode":"ca 95603",
    "addr:street":"Lincoln Way",
    "iso:country":"US",
    "sg:address":"13434 Lincoln Way",
    "sg:city":"Auburn",
    "sg:classifiers":[
        {
            "category":"Restaurant",
            "type":"Food & Drink"
        }
    ],
    "sg:phone":"+1 530 888 7145",
    "sg:postcode":"95603",
    "sg:province":"CA",
    "wof:name":"Hanford's",
    "wof:placetype":"venue"
},
  "geometry": {"coordinates":[-121.056167,38.925658],"type":"Point"}
}