{
  "type": "Feature",
  "properties": {
    "iso:country":"US",
    "sg:address":"6749 Los Gatos Rd",
    "sg:city":"Atascadero",
    "sg:classifiers":[
        {
            "category":"Building & Trades",
            "subcategory":"Electrical",
            "type":"Services"
        }
    ],
    "sg:phone":"+1 805 466 4700",
    "sg:postcode":"93422",
    "sg:province":"CA",
    "sg:tags":[
        "electric",
        "contractor"
    ],
    "wof:name":"Pierson Electric",
    "wof:placetype":"venue"
},
  "geometry": {"coordinates":[-120.68460899999999,35.477396],"type":"Point"}
}