{
  "type": "Feature",
  "properties": {
    "addr:full":"8536 S Gate Ave South Gate CA 90280",
    "addr:housenumber":"8536",
    "addr:postcode":"90280",
    "addr:street":"S Gate Ave;Gate",
    "iso:country":"US",
    "sg:address":"8536 S Gate Ave",
    "sg:city":"South Gate",
    "sg:classifiers":[
        {
            "category":"Food & Beverages",
            "subcategory":"Bakery",
            "type":"Retail Goods"
        },
        {
            "category":"Restaurant",
            "type":"Food & Drink"
        }
    ],
    "sg:phone":"+1 323 583 0650",
    "sg:postcode":"90280",
    "sg:province":"CA",
    "sg:tags":[
        "doughnut",
        "eating"
    ],
    "wof:name":"Rainbow Donuts",
    "wof:placetype":"venue"
},
  "geometry": {"coordinates":[-118.213742,33.959554],"type":"Point"}
}