{
  "type": "Feature",
  "properties": {
    "addr:full":"1127 Wilshire Blvd Los Angeles CA 90017",
    "addr:housenumber":"1127",
    "addr:postcode":"90017",
    "addr:street":"Wilshire Blvd",
    "iso:country":"US",
    "sg:address":"1127 Wilshire Blvd",
    "sg:city":"Los Angeles",
    "sg:classifiers":[
        {
            "category":"Health Services",
            "subcategory":"Health Practitioner",
            "type":"Services"
        }
    ],
    "sg:phone":"+1 213 481 1295",
    "sg:postcode":"90017",
    "sg:province":"CA",
    "sg:tags":[
        "audiologists"
    ],
    "sg:website":"www.sonus.com",
    "wof:name":"Sonus USA Inc",
    "wof:placetype":"venue"
},
  "geometry": {"coordinates":[-118.26448499999999,34.052886],"type":"Point"}
}