{
  "type": "Feature",
  "properties": {
    "iso:country":"US",
    "sg:address":"2201 E La Palma Ave",
    "sg:city":"Anaheim",
    "sg:classifiers":[
        {
            "category":"Real Estate",
            "subcategory":"Real Estate Operator",
            "type":"Services"
        }
    ],
    "sg:phone":"+1 714 758 8084",
    "sg:postcode":"92806",
    "sg:province":"CA",
    "sg:tags":[
        "apartment"
    ],
    "wof:name":"Summerhill Village Apartments",
    "wof:placetype":"venue"
},
  "geometry": {"coordinates":[-117.885002,33.847301],"type":"Point"}
}