{
  "type": "Feature",
  "properties": {
    "iso:country":"US",
    "sg:address":"240 Church St",
    "sg:city":"Salinas",
    "sg:classifiers":[
        {
            "category":"Government",
            "subcategory":"Office",
            "type":"Public Place"
        }
    ],
    "sg:phone":"+1 831 647 7600",
    "sg:postcode":"93901",
    "sg:province":"CA",
    "wof:name":"Monterey Cnty Supervisor Clerk",
    "wof:placetype":"venue"
},
  "geometry": {"coordinates":[-121.658342,36.674984],"type":"Point"}
}