{
  "type": "Feature",
  "properties": {
    "iso:country":"US",
    "sg:address":"1800 W 11th St Ste A",
    "sg:city":"Upland",
    "sg:classifiers":[
        {
            "category":"Autos & Motor Vehicles",
            "subcategory":"Auto Supplies",
            "type":"Retail Goods"
        }
    ],
    "sg:phone":"+1 909 920 1122",
    "sg:postcode":"91786",
    "sg:province":"CA",
    "sg:tags":[
        "lettering",
        "painting",
        "truck"
    ],
    "wof:name":"Inland Valley Auto",
    "wof:placetype":"venue"
},
  "geometry": {"coordinates":[-117.685329,34.103238],"type":"Point"}
}