{
  "type": "Feature",
  "properties": {
    "iso:country":"US",
    "sg:address":"2650 Cameron Park Dr",
    "sg:city":"Cameron Park",
    "sg:classifiers":[
        {
            "category":"Shopping",
            "subcategory":"Discount & Variety Stores",
            "type":"Retail Goods"
        },
        {
            "category":"Shopping",
            "subcategory":"Used Merchandise",
            "type":"Retail Goods"
        }
    ],
    "sg:phone":"+1 530 676 2894",
    "sg:postcode":"95682",
    "sg:province":"CA",
    "wof:name":"Dollar Store Plus More",
    "wof:placetype":"venue"
},
  "geometry": {"coordinates":[-120.995381,38.69861],"type":"Point"}
}