{
  "type": "Feature",
  "properties": {
    "iso:country":"US",
    "sg:address":"2036 Rey Ave",
    "sg:city":"Redding",
    "sg:classifiers":[
        {
            "category":"Health Services",
            "subcategory":"Doctor",
            "type":"Services"
        }
    ],
    "sg:phone":"+1 530 225 8000",
    "sg:postcode":"96001",
    "sg:province":"CA",
    "sg:tags":[
        "physician",
        "surgeon"
    ],
    "wof:name":"Redding Pathologists Lab",
    "wof:placetype":"venue"
},
  "geometry": {"coordinates":[-122.396753,40.568594],"type":"Point"}
}