{
  "type": "Feature",
  "properties": {
    "addr:full":"16251 Main St Guerneville CA 95446",
    "addr:housenumber":"16251",
    "addr:postcode":"95446",
    "addr:street":"Main St",
    "iso:country":"US",
    "sg:address":"16251 Main St",
    "sg:city":"Guerneville",
    "sg:classifiers":[
        {
            "category":"Retail",
            "subcategory":"Portrait Studio",
            "type":"Services"
        },
        {
            "category":"Shopping",
            "subcategory":"Pharmacy",
            "type":"Retail Goods"
        }
    ],
    "sg:phone":"+1 707 869 9055",
    "sg:postcode":"95446",
    "sg:province":"CA",
    "sg:tags":[
        "photography",
        "drugstore",
        "store"
    ],
    "wof:name":"Lark Drugs Guerneville",
    "wof:placetype":"venue"
},
  "geometry": {"coordinates":[-123.00099899999999,38.502102],"type":"Point"}
}