{
  "type": "Feature",
  "properties": {
    "addr:full":"5420 Auburn Blvd Sacramento CA 95841",
    "addr:housenumber":"5420",
    "addr:postcode":"95841",
    "addr:street":"Auburn Blvd",
    "iso:country":"US",
    "sg:address":"5420 Auburn Blvd",
    "sg:city":"Sacramento",
    "sg:classifiers":[
        {
            "category":"Restaurant",
            "type":"Food & Drink"
        }
    ],
    "sg:phone":"+1 916 331 2564",
    "sg:postcode":"95841",
    "sg:province":"CA",
    "wof:name":"Bluewater Bar & Grill",
    "wof:placetype":"venue"
},
  "geometry": {"coordinates":[-121.334525,38.66902],"type":"Point"}
}