{
  "type": "Feature",
  "properties": {
    "addr:full":"2310 M L King St Calexico CA 92231",
    "addr:housenumber":"2310",
    "addr:postcode":"92231",
    "addr:street":"M L King St",
    "iso:country":"US",
    "sg:address":"2310 M L King St",
    "sg:city":"Calexico",
    "sg:classifiers":[
        {
            "category":"Building & Trades",
            "subcategory":"Cleaning & Sanitation",
            "type":"Services"
        }
    ],
    "sg:phone":"+1 760 768 1806",
    "sg:postcode":"92231",
    "sg:province":"CA",
    "sg:tags":[
        "chemical"
    ],
    "wof:name":"G & G Supply",
    "wof:placetype":"venue"
},
  "geometry": {"coordinates":[-115.49328300000001,32.68955],"type":"Point"}
}