{
  "type": "Feature",
  "properties": {
    "addr:full":"920 F St Fresno CA 93706",
    "addr:housenumber":"920",
    "addr:postcode":"93706",
    "addr:street":"F St",
    "iso:country":"US",
    "sg:address":"920 F St",
    "sg:city":"Fresno",
    "sg:classifiers":[
        {
            "category":"Food & Beverages",
            "subcategory":"Candy",
            "type":"Retail Goods"
        }
    ],
    "sg:phone":"+1 559 237 2670",
    "sg:postcode":"93706",
    "sg:province":"CA",
    "sg:tags":[
        "confectionery",
        "japanese"
    ],
    "wof:name":"Kogetsu Do Confectionery",
    "wof:placetype":"venue"
},
  "geometry": {"coordinates":[-119.794639,36.730311],"type":"Point"}
}