{
  "type": "Feature",
  "properties": {
    "iso:country":"US",
    "sg:address":"1233 W Rancho Vista Blvd # 327",
    "sg:city":"Palmdale",
    "sg:classifiers":[
        {
            "category":"Shopping",
            "subcategory":"Shoes",
            "type":"Retail Goods"
        }
    ],
    "sg:phone":"+1 661 267 2735",
    "sg:postcode":"93551",
    "sg:province":"CA",
    "sg:tags":[
        "store"
    ],
    "sg:website":"http://www.finishline.com",
    "wof:name":"Finish Line",
    "wof:placetype":"venue"
},
  "geometry": {"coordinates":[-118.14278899999999,34.547648],"type":"Point"}
}