{
  "type": "Feature",
  "properties": {
    "addr:full":"4229 Lozano Ln Fairfield CA 94585",
    "addr:housenumber":"4229",
    "addr:postcode":"94585",
    "addr:street":"Lozano Ln",
    "iso:country":"US",
    "sg:address":"4229 Lozano Ln",
    "sg:city":"Fairfield",
    "sg:classifiers":[
        {
            "category":"Wholesale",
            "subcategory":"Stationery",
            "type":"Manufacturing & Wholesale Goods"
        }
    ],
    "sg:phone":"+1 707 864 4100",
    "sg:postcode":"94585",
    "sg:province":"CA",
    "sg:tags":[
        "box",
        "fiber"
    ],
    "wof:name":"American Box & Container Co",
    "wof:placetype":"venue"
},
  "geometry": {"coordinates":[-122.07196999999999,38.249295],"type":"Point"}
}