{
  "type": "Feature",
  "properties": {
    "iso:country":"US",
    "sg:address":"300 E Grace St",
    "sg:city":"Barstow",
    "sg:classifiers":[
        {
            "category":"Wholesale",
            "subcategory":"Apparel",
            "type":"Manufacturing & Wholesale Goods"
        }
    ],
    "sg:phone":"+1 760 256 4404",
    "sg:postcode":"92311",
    "sg:province":"CA",
    "sg:tags":[
        "footwear"
    ],
    "wof:name":"Hydropedes Insoles",
    "wof:placetype":"venue"
},
  "geometry": {"coordinates":[-117.024869,34.887235],"type":"Point"}
}