{
  "type": "Feature",
  "properties": {
    "iso:country":"US",
    "sg:address":"23203 Iris Ave",
    "sg:city":"Torrance",
    "sg:classifiers":[
        {
            "category":"Professional",
            "type":"Services"
        }
    ],
    "sg:phone":"+1 310 534 1699",
    "sg:postcode":"90505",
    "sg:province":"CA",
    "wof:name":"Fun Time Parnt",
    "wof:placetype":"venue"
},
  "geometry": {"coordinates":[-118.33579,33.816388],"type":"Point"}
}