{
  "type": "Feature",
  "properties": {
    "addr:full":"1485 Park Ave San Jose CA 95126",
    "addr:housenumber":"1485",
    "addr:postcode":"95126",
    "addr:street":"Park Ave",
    "iso:country":"US",
    "sg:address":"1485 Park Ave",
    "sg:city":"San Jose",
    "sg:classifiers":[
        {
            "category":"Professional",
            "subcategory":"Lawyer & Legal Services",
            "type":"Services"
        }
    ],
    "sg:phone":"+1 408 971 7072",
    "sg:postcode":"95126",
    "sg:province":"CA",
    "sg:tags":[
        "attorney"
    ],
    "wof:name":"Jeffrey N Greenberg",
    "wof:placetype":"venue"
},
  "geometry": {"coordinates":[-121.919393,37.329981],"type":"Point"}
}