{
  "type": "Feature",
  "properties": {
    "iso:country":"US",
    "sg:address":"474 Whitney St",
    "sg:city":"San Leandro",
    "sg:classifiers":[
        {
            "category":"Wholesale",
            "subcategory":"Machinery & Supplies",
            "type":"Manufacturing & Wholesale Goods"
        }
    ],
    "sg:phone":"+1 510 568 8308",
    "sg:postcode":"94577",
    "sg:province":"CA",
    "sg:tags":[
        "equipment",
        "industrial"
    ],
    "wof:name":"Ancra",
    "wof:placetype":"venue"
},
  "geometry": {"coordinates":[-122.18926,37.722753],"type":"Point"}
}