{
  "type": "Feature",
  "properties": {
    "iso:country":"US",
    "sg:address":"3500 5th Ave Ste 203",
    "sg:city":"San Diego",
    "sg:classifiers":[
        {
            "category":"Health Services",
            "subcategory":"Clinic",
            "type":"Services"
        },
        {
            "category":"Education",
            "subcategory":"Special Training",
            "type":"Public Place"
        }
    ],
    "sg:phone":"+1 619 294 2192",
    "sg:postcode":"92103",
    "sg:province":"CA",
    "sg:tags":[
        "medical",
        "adult"
    ],
    "wof:name":"Family Health Services",
    "wof:placetype":"venue"
},
  "geometry": {"coordinates":[-117.16072699999999,32.741793],"type":"Point"}
}