{
  "type": "Feature",
  "properties": {
    "addr:full":"180 Dolores St San Francisco CA 94103",
    "addr:housenumber":"180",
    "addr:postcode":"94103",
    "addr:street":"Dolores St",
    "iso:country":"US",
    "sg:address":"180 Dolores St",
    "sg:city":"San Francisco",
    "sg:classifiers":[
        {
            "category":"Manufacturing",
            "subcategory":"Retail Goods",
            "type":"Manufacturing & Wholesale Goods"
        }
    ],
    "sg:phone":"+1 415 863 9423",
    "sg:postcode":"94103",
    "sg:province":"CA",
    "sg:tags":[
        "lead",
        "mfg"
    ],
    "wof:name":"Thomas Rohnacher",
    "wof:placetype":"venue"
},
  "geometry": {"coordinates":[-122.426739,37.766754],"type":"Point"}
}