{
  "type": "Feature",
  "properties": {
    "addr:full":"760 S Hill St Los Angeles CA 90014",
    "addr:housenumber":"760",
    "addr:postcode":"90014",
    "addr:street":"S Hill St",
    "iso:country":"US",
    "sg:address":"760 S Hill St",
    "sg:city":"Los Angeles",
    "sg:classifiers":[
        {
            "category":"Real Estate",
            "subcategory":"Real Estate Agent",
            "type":"Services"
        }
    ],
    "sg:phone":"+1 213 624 8600",
    "sg:postcode":"90014",
    "sg:province":"CA",
    "wof:name":"Heisman Co",
    "wof:placetype":"venue"
},
  "geometry": {"coordinates":[-118.255047,34.045305],"type":"Point"}
}