{
  "type": "Feature",
  "properties": {
    "addr:full":"1628 Hostetter Road San Jose CA 95131",
    "addr:housenumber":"1628",
    "addr:postcode":"95131",
    "addr:street":"Hostetter Road",
    "iso:country":"US",
    "sg:address":"1628 Hostetter Road",
    "sg:city":"San Jose",
    "sg:classifiers":[
        {
            "category":"Shopping",
            "subcategory":"Jewelry",
            "type":"Retail Goods"
        }
    ],
    "sg:phone":"+1 408 452 8050",
    "sg:postcode":"95131",
    "sg:province":"CA",
    "wof:name":"Fine Gems",
    "wof:placetype":"venue"
},
  "geometry": {"coordinates":[-121.8854,37.387549],"type":"Point"}
}