{
  "type": "Feature",
  "properties": {
    "iso:country":"US",
    "sg:address":"2203 A St",
    "sg:city":"Eureka",
    "sg:classifiers":[
        {
            "category":"Professional",
            "subcategory":"Business Services",
            "type":"Services"
        }
    ],
    "sg:phone":"+1 707 444 3041",
    "sg:postcode":"95501",
    "sg:province":"CA",
    "wof:name":"Hamanaka Legal Document Svc",
    "wof:placetype":"venue"
},
  "geometry": {"coordinates":[-124.17017,40.787816],"type":"Point"}
}