{
  "type": "Feature",
  "properties": {
    "addr:full":"639 Front Street 1st Floor San Francisco CA 94111",
    "addr:housenumber":"639",
    "addr:postcode":"94111",
    "addr:street":"Front Street 1St Floor",
    "iso:country":"US",
    "sg:address":"639 Front Street 1st Floor",
    "sg:city":"San Francisco",
    "sg:classifiers":[
        {
            "category":"Professional",
            "subcategory":"Computer Services",
            "type":"Services"
        }
    ],
    "sg:phone":"+1 415 706 1705",
    "sg:postcode":"94111",
    "sg:province":"CA",
    "sg:website":"http://www.headmix.com",
    "wof:name":"HeadMix",
    "wof:placetype":"venue"
},
  "geometry": {"coordinates":[-122.399705,37.797453],"type":"Point"}
}