{
  "type": "Feature",
  "properties": {
    "addr:full":"1132 Ballena Blvd Alameda CA 94501",
    "addr:housenumber":"1132",
    "addr:postcode":"94501",
    "addr:street":"Ballena Blvd",
    "iso:country":"US",
    "sg:address":"1132 Ballena Blvd",
    "sg:city":"Alameda",
    "sg:classifiers":[
        {
            "category":"Fast Food",
            "type":"Food & Drink"
        },
        {
            "category":"Coffee & Tea",
            "type":"Food & Drink"
        },
        {
            "category":"Food Court",
            "type":"Food & Drink"
        },
        {
            "category":"Restaurant",
            "type":"Food & Drink"
        }
    ],
    "sg:phone":"+1 510 769 2132",
    "sg:postcode":"94501",
    "sg:province":"CA",
    "sg:tags":[
        "box",
        "espresso",
        "take",
        "lunch"
    ],
    "wof:name":"Good & Plenty Cafe De Ballena",
    "wof:placetype":"venue"
},
  "geometry": {"coordinates":[-122.28800200000001,37.766201],"type":"Point"}
}