{
  "type": "Feature",
  "properties": {
    "addr:full":"208 Elm St Red Bluff CA 96080",
    "addr:housenumber":"208",
    "addr:postcode":"96080",
    "addr:street":"Elm St",
    "iso:country":"US",
    "sg:address":"208 Elm St",
    "sg:city":"Red Bluff",
    "sg:classifiers":[
        {
            "category":"Home & Garden",
            "subcategory":"Home Furnishings",
            "type":"Retail Goods"
        }
    ],
    "sg:phone":"+1 530 529 1436",
    "sg:postcode":"96080",
    "sg:province":"CA",
    "sg:tags":[
        "blanket"
    ],
    "sg:website":"www.institchesinredbluff.com",
    "wof:name":"In Stitches",
    "wof:placetype":"venue"
},
  "geometry": {"coordinates":[-122.23251,40.176266],"type":"Point"}
}