{
  "type": "Feature",
  "properties": {
    "addr:full":"4631 W Rosecrans Ave Hawthorne CA 90250",
    "addr:housenumber":"4631",
    "addr:postcode":"90250",
    "addr:street":"W Rosecrans Ave",
    "iso:country":"US",
    "sg:address":"4631 W Rosecrans Ave",
    "sg:city":"Hawthorne",
    "sg:classifiers":[
        {
            "category":"Retail",
            "subcategory":"Auto Repair",
            "type":"Services"
        }
    ],
    "sg:phone":"+1 310 676 7770",
    "sg:postcode":"90250",
    "sg:province":"CA",
    "sg:tags":[
        "repairing",
        "automobile"
    ],
    "wof:name":"Bob's Auto Repair",
    "wof:placetype":"venue"
},
  "geometry": {"coordinates":[-118.358002,33.901798],"type":"Point"}
}