{
  "type": "Feature",
  "properties": {
    "addr:full":"218 Lento Ln El Cajon CA 92021",
    "addr:housenumber":"218",
    "addr:postcode":"92021",
    "addr:street":"Lento Ln",
    "iso:country":"US",
    "sg:address":"218 Lento Ln",
    "sg:city":"El Cajon",
    "sg:classifiers":[
        {
            "category":"Professional",
            "type":"Services"
        }
    ],
    "sg:phone":"+1 619 442 4089",
    "sg:postcode":"92021",
    "sg:province":"CA",
    "sg:tags":[
        "establishment"
    ],
    "wof:name":"Cathy T Riley Marketing Svc",
    "wof:placetype":"venue"
},
  "geometry": {"coordinates":[-116.868115,32.805874],"type":"Point"}
}