{
  "type": "Feature",
  "properties": {
    "iso:country":"US",
    "sg:address":"3962 Cerritos Ave",
    "sg:city":"Los Alamitos",
    "sg:classifiers":[
        {
            "category":"Building & Trades",
            "subcategory":"Construction",
            "type":"Services"
        }
    ],
    "sg:phone":"+1 562 253 3689",
    "sg:postcode":"90720",
    "sg:province":"CA",
    "sg:tags":[
        "interior",
        "design"
    ],
    "sg:website":"www.joespremiumpainting.com",
    "wof:name":"Joe's Premium Painting",
    "wof:placetype":"venue"
},
  "geometry": {"coordinates":[-118.06327899999999,33.810271],"type":"Point"}
}