{
  "type": "Feature",
  "properties": {
    "addr:full":"4181 Mission St San Francisco CA 94132",
    "addr:housenumber":"4181",
    "addr:postcode":"94132",
    "addr:street":"Mission St",
    "iso:country":"US",
    "sg:address":"4181 Mission St",
    "sg:city":"San Francisco",
    "sg:classifiers":[
        {
            "category":"Real Estate",
            "subcategory":"Real Estate Agent",
            "type":"Services"
        }
    ],
    "sg:phone":"+1 650 206 8508",
    "sg:postcode":"94132",
    "sg:province":"CA",
    "sg:website":"carealestatechoice.info",
    "wof:name":"Daly City Quality Real Estate",
    "wof:placetype":"venue"
},
  "geometry": {"coordinates":[-122.429528,37.730486],"type":"Point"}
}