{
  "type": "Feature",
  "properties": {
    "addr:full":"5581 Toyon Bay Long Beach CA 90803",
    "addr:housenumber":"5581",
    "addr:postcode":"90803",
    "addr:street":"Toyon Bay",
    "iso:country":"US",
    "sg:address":"5581 Toyon Bay",
    "sg:city":"Long Beach",
    "sg:classifiers":[
        {
            "category":"Wholesale",
            "subcategory":"Electrical",
            "type":"Manufacturing & Wholesale Goods"
        }
    ],
    "sg:phone":"+1 562 498 7134",
    "sg:postcode":"90803",
    "sg:province":"CA",
    "sg:tags":[
        "appliance",
        "representative",
        "kitchen"
    ],
    "wof:name":"Products For Industry LLC",
    "wof:placetype":"venue"
},
  "geometry": {"coordinates":[-118.12463099999999,33.766364],"type":"Point"}
}