{
  "type": "Feature",
  "properties": {
    "addr:full":"2734 Loker Ave W Carlsbad CA 92008",
    "addr:housenumber":"2734",
    "addr:postcode":"92008",
    "addr:street":"Loker Ave W",
    "iso:country":"US",
    "sg:address":"2734 Loker Ave W",
    "sg:city":"Carlsbad",
    "sg:classifiers":[
        {
            "category":"Manufacturing",
            "subcategory":"Printing",
            "type":"Manufacturing & Wholesale Goods"
        }
    ],
    "sg:phone":"+1 760 431 2889",
    "sg:postcode":"92008",
    "sg:province":"CA",
    "sg:tags":[
        "printer"
    ],
    "wof:name":"Real Printing",
    "wof:placetype":"venue"
},
  "geometry": {"coordinates":[-117.254086,33.131462],"type":"Point"}
}