{
  "type": "Feature",
  "properties": {
    "addr:full":"4 Jeannette Prandi Way San Rafael CA 94903",
    "addr:housenumber":"4",
    "addr:postcode":"94903",
    "addr:street":"Jeannette Prandi Way",
    "iso:country":"US",
    "sg:address":"4 Jeannette Prandi Way",
    "sg:city":"San Rafael",
    "sg:classifiers":[
        {
            "category":"Government",
            "subcategory":"Office",
            "type":"Public Place"
        }
    ],
    "sg:phone":"+1 415 499 6659",
    "sg:postcode":"94903",
    "sg:province":"CA",
    "wof:name":"Marin County Juvenile Svc Ctr",
    "wof:placetype":"venue"
},
  "geometry": {"coordinates":[-122.56854300000001,38.026843],"type":"Point"}
}