{
  "type": "Feature",
  "properties": {
    "addr:full":"2461 N Long Beach Blvd Long Beach CA 90806",
    "addr:housenumber":"2461",
    "addr:postcode":"90806",
    "addr:street":"N Long Beach Blvd",
    "iso:country":"US",
    "sg:address":"2461 N Long Beach Blvd",
    "sg:city":"Long Beach",
    "sg:classifiers":[
        {
            "category":"Retail",
            "subcategory":"Auto Repair",
            "type":"Services"
        }
    ],
    "sg:phone":"+1 562 290 8083",
    "sg:postcode":"90806",
    "sg:province":"CA",
    "sg:tags":[
        "repairing",
        "automobile"
    ],
    "wof:name":"Jessie's Auto Repair",
    "wof:placetype":"venue"
},
  "geometry": {"coordinates":[-118.189432,33.802452],"type":"Point"}
}