{
  "type": "Feature",
  "properties": {
    "iso:country":"US",
    "sg:address":"435 Camino Real St",
    "sg:city":"Duarte",
    "sg:classifiers":[
        {
            "category":"Building & Trades",
            "subcategory":"Construction",
            "type":"Services"
        },
        {
            "category":"Manufacturing",
            "subcategory":"Glass & Minerals",
            "type":"Manufacturing & Wholesale Goods"
        },
        {
            "category":"Manufacturing",
            "subcategory":"Building Materials",
            "type":"Manufacturing & Wholesale Goods"
        },
        {
            "category":"Utilities",
            "type":"Services"
        }
    ],
    "sg:phone":"+1 626 401 0225",
    "sg:postcode":"91010",
    "sg:province":"CA",
    "sg:tags":[
        "plate",
        "glassware-repair",
        "door",
        "window",
        "shower",
        "glass-auto",
        "china",
        "board",
        "enclosure"
    ],
    "wof:name":"Diego's Glass",
    "wof:placetype":"venue"
},
  "geometry": {"coordinates":[-117.996973,34.121172],"type":"Point"}
}