{
  "type": "Feature",
  "properties": {
    "iso:country":"US",
    "sg:address":"10086 Baffin Dr",
    "sg:city":"San Diego",
    "sg:classifiers":[
        {
            "category":"Freight",
            "type":"Transportation"
        }
    ],
    "sg:phone":"+1 858 586 0234",
    "sg:postcode":"92126",
    "sg:province":"CA",
    "wof:name":"West CST Moving",
    "wof:placetype":"venue"
},
  "geometry": {"coordinates":[-117.15433299999999,32.900004],"type":"Point"}
}