{
  "type": "Feature",
  "properties": {
    "addr:full":"7343 Paseo Capuchina Carlsbad CA 92009",
    "addr:housenumber":"7343",
    "addr:postcode":"92009",
    "addr:street":"Paseo Capuchina",
    "iso:country":"US",
    "sg:address":"7343 Paseo Capuchina",
    "sg:city":"Carlsbad",
    "sg:classifiers":[
        {
            "category":"Banks & Credit Unions",
            "subcategory":"Bank",
            "type":"Services"
        }
    ],
    "sg:phone":"+1 760 634 2457",
    "sg:postcode":"92009",
    "sg:province":"CA",
    "wof:name":"First Regional Bank",
    "wof:placetype":"venue"
},
  "geometry": {"coordinates":[-117.2287,33.683478],"type":"Point"}
}