{
  "type": "Feature",
  "properties": {
    "addr:full":"1135 Prospect St La Jolla CA 92037",
    "addr:housenumber":"1135",
    "addr:postcode":"92037",
    "addr:street":"Prospect St",
    "iso:country":"US",
    "sg:address":"1135 Prospect St",
    "sg:city":"La Jolla",
    "sg:classifiers":[
        {
            "category":"Shopping",
            "subcategory":"Jewelry",
            "type":"Retail Goods"
        }
    ],
    "sg:phone":"+1 858 454 5390",
    "sg:postcode":"92037",
    "sg:province":"CA",
    "sg:tags":[
        "watch"
    ],
    "sg:website":"www.cjcharles.com/",
    "wof:name":"C J Charles Jewelers",
    "wof:placetype":"venue"
},
  "geometry": {"coordinates":[-117.273003,32.848598],"type":"Point"}
}