{
  "type": "Feature",
  "properties": {
    "iso:country":"US",
    "sg:address":"1801 Avenue of the Stars",
    "sg:city":"Los Angeles",
    "sg:classifiers":[
        {
            "category":"Professional",
            "subcategory":"Employment Agencies",
            "type":"Services"
        }
    ],
    "sg:phone":"+1 310 282 8559",
    "sg:postcode":"90067",
    "sg:province":"CA",
    "sg:website":"www.talentr.com",
    "wof:name":"Talent Resources",
    "wof:placetype":"venue"
},
  "geometry": {"coordinates":[-118.418538,34.095433],"type":"Point"}
}