{
  "type": "Feature",
  "properties": {
    "iso:country":"US",
    "sg:address":"220 E 17th St",
    "sg:city":"Costa Mesa",
    "sg:classifiers":[
        {
            "category":"Shopping",
            "subcategory":"Bicycles & Sporting Goods",
            "type":"Retail Goods"
        }
    ],
    "sg:phone":"+1 949 646 7330",
    "sg:postcode":"92627",
    "sg:province":"CA",
    "sg:tags":[
        "equipment",
        "racquetball",
        "supply"
    ],
    "sg:website":"www.devinsproshop.com",
    "wof:name":"Devin's Pro Shop",
    "wof:placetype":"venue"
},
  "geometry": {"coordinates":[-117.917615,33.634772],"type":"Point"}
}