{
  "type": "Feature",
  "properties": {
    "addr:full":"350 E Tasman Dr Cisco Bldg 11 1st Fl San Jose CA 95134",
    "addr:housenumber":"350;11 1st fl",
    "addr:postcode":"95134",
    "addr:street":"E Tasman Dr",
    "iso:country":"US",
    "sg:address":"350 E Tasman Dr Cisco Bldg 11 1st Fl",
    "sg:city":"San Jose",
    "sg:classifiers":[
        {
            "category":"Restaurant",
            "type":"Food & Drink"
        }
    ],
    "sg:postcode":"95134",
    "sg:province":"CA",
    "wof:name":"Market Cafe",
    "wof:placetype":"venue"
},
  "geometry": {"coordinates":[-121.930368,37.412497],"type":"Point"}
}