{
  "type": "Feature",
  "properties": {
    "iso:country":"US",
    "sg:address":"7076 Convoy Ct",
    "sg:city":"San Diego",
    "sg:classifiers":[
        {
            "category":"Wholesale",
            "subcategory":"Construction Materials",
            "type":"Manufacturing & Wholesale Goods"
        }
    ],
    "sg:phone":"+1 858 573 9124",
    "sg:postcode":"92117",
    "sg:province":"CA",
    "sg:tags":[
        "equipment",
        "caulking"
    ],
    "wof:name":"Smalley & Co",
    "wof:placetype":"venue"
},
  "geometry": {"coordinates":[-117.167958,32.834707],"type":"Point"}
}