{
  "type": "Feature",
  "properties": {
    "addr:full":"3765 Grass Valley Hwy Auburn CA 95602",
    "addr:housenumber":"3765",
    "addr:postcode":"ca 95602",
    "addr:street":"Grass Valley Hwy",
    "iso:country":"US",
    "sg:address":"3765 Grass Valley Hwy",
    "sg:city":"Auburn",
    "sg:classifiers":[
        {
            "category":"Real Estate",
            "subcategory":"Real Estate Operator",
            "type":"Services"
        }
    ],
    "sg:phone":"+1 530 885 0141",
    "sg:postcode":"95602",
    "sg:province":"CA",
    "sg:tags":[
        "mobile",
        "home",
        "community"
    ],
    "wof:name":"Rock Creek Mobile Home Park",
    "wof:placetype":"venue"
},
  "geometry": {"coordinates":[-121.100421,38.95181],"type":"Point"}
}