{
  "type": "Feature",
  "properties": {
    "iso:country":"US",
    "sg:address":"4943 McConnell Ave",
    "sg:city":"Los Angeles",
    "sg:classifiers":[
        {
            "category":"Professional",
            "subcategory":"Art Services",
            "type":"Services"
        }
    ],
    "sg:phone":"+1 310 301 0537",
    "sg:postcode":"90066",
    "sg:province":"CA",
    "sg:tags":[
        "photographer"
    ],
    "wof:name":"Wendi Marafino Photography",
    "wof:placetype":"venue"
},
  "geometry": {"coordinates":[-118.424562,33.984582],"type":"Point"}
}