{
  "type": "Feature",
  "properties": {
    "iso:country":"US",
    "sg:address":"6255 W Sunset Boulevard",
    "sg:city":"Los Angeles",
    "sg:classifiers":[
        {
            "category":"Education",
            "subcategory":"University",
            "type":"Public Place"
        }
    ],
    "sg:phone":"+1 323 469 0525",
    "sg:postcode":"90028",
    "sg:province":"CA",
    "sg:tags":[
        "college"
    ],
    "wof:name":"Columbia College Chicago",
    "wof:placetype":"venue"
},
  "geometry": {"coordinates":[-118.325414,34.098029],"type":"Point"}
}