{
  "type": "Feature",
  "properties": {
    "iso:country":"US",
    "sg:address":"1131 18th St",
    "sg:city":"Manhattan Beach",
    "sg:classifiers":[
        {
            "category":"Real Estate",
            "subcategory":"Real Estate Agent",
            "type":"Services"
        }
    ],
    "sg:phone":"+1 310 546 8799",
    "sg:postcode":"90266",
    "sg:province":"CA",
    "wof:name":"Property Solutions A Real Est",
    "wof:placetype":"venue"
},
  "geometry": {"coordinates":[-118.393716,33.891533],"type":"Point"}
}