{
  "type": "Feature",
  "properties": {
    "iso:country":"US",
    "sg:address":"14259 Don Julian Rd",
    "sg:city":"City Of Industry",
    "sg:classifiers":[
        {
            "category":"Wholesale",
            "subcategory":"Computers",
            "type":"Manufacturing & Wholesale Goods"
        }
    ],
    "sg:phone":"+1 626 961 2255",
    "sg:postcode":"91746",
    "sg:province":"CA",
    "wof:name":"Rexus Corp",
    "wof:placetype":"venue"
},
  "geometry": {"coordinates":[-117.985879,34.032857],"type":"Point"}
}