{
  "type": "Feature",
  "properties": {
    "addr:full":"245 Fischer Ave Costa Mesa CA 92626",
    "addr:housenumber":"245",
    "addr:postcode":"92626",
    "addr:street":"Fischer Ave",
    "iso:country":"US",
    "sg:address":"245 Fischer Ave",
    "sg:city":"Costa Mesa",
    "sg:classifiers":[
        {
            "category":"Professional",
            "subcategory":"Lawyer & Legal Services",
            "type":"Services"
        }
    ],
    "sg:phone":"+1 714 540 1820",
    "sg:postcode":"92626",
    "sg:province":"CA",
    "wof:name":"Leach Mc Greevy & Leach",
    "wof:placetype":"venue"
},
  "geometry": {"coordinates":[-117.879997,33.6759],"type":"Point"}
}