{
  "type": "Feature",
  "properties": {
    "iso:country":"US",
    "sg:address":"14 N Santa Cruz Avenue",
    "sg:city":"Los Gatos",
    "sg:classifiers":[
        {
            "category":"Personal",
            "type":"Services"
        },
        {
            "category":"Shopping",
            "subcategory":"Florist",
            "type":"Retail Goods"
        }
    ],
    "sg:phone":"+1 408 395 5451",
    "sg:postcode":"95030",
    "sg:province":"CA",
    "sg:tags":[
        "planning",
        "wedding"
    ],
    "sg:website":"buncheslosgatos.com",
    "wof:name":"Bunches",
    "wof:placetype":"venue"
},
  "geometry": {"coordinates":[-121.98367399999999,37.22292],"type":"Point"}
}