{
  "type": "Feature",
  "properties": {
    "addr:full":"9819 Thermal St Oakland CA 94605",
    "addr:housenumber":"9819",
    "addr:postcode":"94605",
    "addr:street":"Thermal St",
    "iso:country":"US",
    "sg:address":"9819 Thermal St",
    "sg:city":"Oakland",
    "sg:classifiers":[
        {
            "category":"Travel",
            "subcategory":"Travel Agent",
            "type":"Entertainment"
        }
    ],
    "sg:phone":"+1 510 638 6756",
    "sg:postcode":"94605",
    "sg:province":"CA",
    "sg:tags":[
        "agency"
    ],
    "wof:name":"Noremac Travel Services",
    "wof:placetype":"venue"
},
  "geometry": {"coordinates":[-122.157275,37.749253],"type":"Point"}
}