{
  "type": "Feature",
  "properties": {
    "iso:country":"US",
    "sg:address":"2483 W Middlefield Rd",
    "sg:city":"Mountain View",
    "sg:classifiers":[
        {
            "category":"Professional",
            "subcategory":"Engineering",
            "type":"Services"
        }
    ],
    "sg:phone":"+1 650 962 0207",
    "sg:postcode":"94043",
    "sg:province":"CA",
    "sg:tags":[
        "engineer"
    ],
    "wof:name":"Harlan Tait Assoc",
    "wof:placetype":"venue"
},
  "geometry": {"coordinates":[-122.099123,37.412859],"type":"Point"}
}