{
  "type": "Feature",
  "properties": {
    "iso:country":"US",
    "sg:address":"2020 Milvia Street",
    "sg:city":"Berkeley",
    "sg:classifiers":[
        {
            "category":"Education",
            "subcategory":"University",
            "type":"Public Place"
        }
    ],
    "sg:phone":"+1 510 981 2800",
    "sg:postcode":"94704",
    "sg:province":"CA",
    "sg:tags":[
        "college"
    ],
    "wof:name":"Vista Community College",
    "wof:placetype":"venue"
},
  "geometry": {"coordinates":[-122.271004,37.871498],"type":"Point"}
}