{
  "type": "Feature",
  "properties": {
    "iso:country":"US",
    "sg:address":"1165 Mulberry Ln",
    "sg:city":"Dixon",
    "sg:classifiers":[
        {
            "category":"Building & Trades",
            "subcategory":"Construction",
            "type":"Services"
        }
    ],
    "sg:phone":"+1 707 678 2043",
    "sg:postcode":"95620",
    "sg:province":"CA",
    "sg:tags":[
        "excavating",
        "contractor"
    ],
    "wof:name":"Hull Construction",
    "wof:placetype":"venue"
},
  "geometry": {"coordinates":[-121.837256,38.445093],"type":"Point"}
}