{
  "type": "Feature",
  "properties": {
    "iso:country":"US",
    "sg:address":"410 E Chapman Ave Ste C",
    "sg:city":"Fullerton",
    "sg:classifiers":[
        {
            "category":"Restaurant",
            "type":"Food & Drink"
        },
        {
            "category":"Bars & Pubs",
            "subcategory":"Nightclub",
            "type":"Food & Drink"
        }
    ],
    "sg:phone":"+1 714 871 0491",
    "sg:postcode":"92832",
    "sg:province":"CA",
    "sg:tags":[
        "nightlife"
    ],
    "wof:name":"Chicago Harv's",
    "wof:placetype":"venue"
},
  "geometry": {"coordinates":[-117.91719399999999,33.873623],"type":"Point"}
}