{
  "type": "Feature",
  "properties": {
    "addr:full":"11203 1/4 National Blvd Los Angeles CA 90232",
    "addr:housenumber":"11203 1 / 4",
    "addr:postcode":"90232",
    "addr:street":"National Blvd",
    "iso:country":"US",
    "sg:address":"11203 1/4 National Blvd",
    "sg:city":"Los Angeles",
    "sg:classifiers":[
        {
            "category":"Personal",
            "subcategory":"Beauty Salon",
            "type":"Services"
        }
    ],
    "sg:phone":"+1 310 916 8478",
    "sg:postcode":"90232",
    "sg:province":"CA",
    "sg:tags":[
        "hair"
    ],
    "sg:website":"susanaharo.com",
    "wof:name":"Celebrity Hair Extensions",
    "wof:placetype":"venue"
},
  "geometry": {"coordinates":[-118.42891299999999,34.027286],"type":"Point"}
}