{
  "type": "Feature",
  "properties": {
    "iso:country":"US",
    "sg:address":"2200 Giffen Ave",
    "sg:city":"Santa Rosa",
    "sg:classifiers":[
        {
            "category":"Organizations",
            "subcategory":"Religious Organization",
            "type":"Services"
        }
    ],
    "sg:phone":"+1 707 545 3863",
    "sg:postcode":"95407",
    "sg:province":"CA",
    "sg:tags":[
        "church"
    ],
    "wof:name":"First United Methodist Church",
    "wof:placetype":"venue"
},
  "geometry": {"coordinates":[-122.743802,38.417854],"type":"Point"}
}