{
  "type": "Feature",
  "properties": {
    "addr:full":"8805 Research Drive Suite # 100 Irvine CA 92618",
    "addr:housenumber":"8805",
    "addr:postcode":"92618",
    "addr:street":"Research Drive Suite # 100",
    "iso:country":"US",
    "sg:address":"8805 Research Drive Suite # 100",
    "sg:city":"Irvine",
    "sg:classifiers":[
        {
            "category":"Professional",
            "subcategory":"Management & Consulting",
            "type":"Services"
        }
    ],
    "sg:phone":"+1 888 696 9283",
    "sg:postcode":"92618",
    "sg:province":"CA",
    "sg:website":"http://www.waveimaging.com",
    "wof:name":"Wave Technology Solutions",
    "wof:placetype":"venue"
},
  "geometry": {"coordinates":[-117.744685,33.644285],"type":"Point"}
}