{
  "type": "Feature",
  "properties": {
    "addr:full":"3811 Malcolm Ave Oakland CA 94605",
    "addr:housenumber":"3811",
    "addr:postcode":"94605",
    "addr:street":"Malcolm Ave",
    "iso:country":"US",
    "sg:address":"3811 Malcolm Ave",
    "sg:city":"Oakland",
    "sg:classifiers":[
        {
            "category":"Building & Trades",
            "subcategory":"Plumbing",
            "type":"Services"
        }
    ],
    "sg:phone":"+1 510 253 9425",
    "sg:postcode":"94605",
    "sg:province":"CA",
    "sg:tags":[
        "plumber",
        "industrial",
        "contractors-commercial"
    ],
    "wof:name":"Richardson Plumbing",
    "wof:placetype":"venue"
},
  "geometry": {"coordinates":[-122.13621999999999,37.748944],"type":"Point"}
}