{
  "type": "Feature",
  "properties": {
    "iso:country":"US",
    "sg:address":"1108 E 17th St",
    "sg:city":"Santa Ana",
    "sg:classifiers":[
        {
            "category":"Banks & Credit Unions",
            "subcategory":"Bank",
            "type":"Services"
        }
    ],
    "sg:phone":"+1 714 569 0300",
    "sg:postcode":"92701",
    "sg:province":"CA",
    "sg:tags":[
        "cashing",
        "check"
    ],
    "wof:name":"Continental Currency Svc Inc",
    "wof:placetype":"venue"
},
  "geometry": {"coordinates":[-117.852071,33.759863],"type":"Point"}
}