{
  "type": "Feature",
  "properties": {
    "addr:full":"11155 Mountain View Ave Loma Linda CA 92354",
    "addr:housenumber":"11155",
    "addr:postcode":"92354",
    "addr:street":"Mountain View Ave",
    "iso:country":"US",
    "sg:address":"11155 Mountain View Ave",
    "sg:city":"Loma Linda",
    "sg:classifiers":[
        {
            "category":"Insurance",
            "subcategory":"Insurance Agent",
            "type":"Services"
        }
    ],
    "sg:phone":"+1 909 796 7514",
    "sg:postcode":"92354",
    "sg:province":"CA",
    "wof:name":"State Farm Insurance",
    "wof:placetype":"venue"
},
  "geometry": {"coordinates":[-117.24359200000001,34.051532],"type":"Point"}
}