{
  "type": "Feature",
  "properties": {
    "addr:full":"9131 Valley Blvd Rosemead CA 91770",
    "addr:housenumber":"9131",
    "addr:postcode":"91770",
    "addr:street":"Valley Blvd",
    "iso:country":"US",
    "sg:address":"9131 Valley Blvd",
    "sg:city":"Rosemead",
    "sg:classifiers":[
        {
            "category":"Shopping",
            "subcategory":"Music",
            "type":"Retail Goods"
        }
    ],
    "sg:phone":"+1 626 309 2997",
    "sg:postcode":"91770",
    "sg:province":"CA",
    "sg:tags":[
        "video",
        "disc",
        "tape",
        "cassette"
    ],
    "wof:name":"Nyein Chan Myanmar",
    "wof:placetype":"venue"
},
  "geometry": {"coordinates":[-118.07184100000001,34.080944],"type":"Point"}
}