{
  "type": "Feature",
  "properties": {
    "addr:full":"936 S Glendora Ave West Covina CA 91790",
    "addr:housenumber":"936",
    "addr:postcode":"91790",
    "addr:street":"S Glendora Ave",
    "iso:country":"US",
    "sg:address":"936 S Glendora Ave",
    "sg:city":"West Covina",
    "sg:classifiers":[
        {
            "category":"Retail",
            "subcategory":"Auto Repair",
            "type":"Services"
        }
    ],
    "sg:phone":"+1 626 472 6033",
    "sg:postcode":"91790",
    "sg:province":"CA",
    "sg:tags":[
        "repairing",
        "automobile"
    ],
    "wof:name":"Sure 2 Stop",
    "wof:placetype":"venue"
},
  "geometry": {"coordinates":[-117.934867,34.058583],"type":"Point"}
}