{
  "type": "Feature",
  "properties": {
    "iso:country":"US",
    "sg:address":"3077 Wiljan Ct",
    "sg:city":"Santa Rosa",
    "sg:classifiers":[
        {
            "category":"Wholesale",
            "subcategory":"Auto Parts",
            "type":"Manufacturing & Wholesale Goods"
        }
    ],
    "sg:phone":"+1 707 545 8969",
    "sg:postcode":"95407",
    "sg:province":"CA",
    "wof:name":"Elliott Auto Supply Co Inc",
    "wof:placetype":"venue"
},
  "geometry": {"coordinates":[-122.71986099999999,38.40278],"type":"Point"}
}