{
  "type": "Feature",
  "properties": {
    "addr:full":"3444 Kearny Villa Rd San Diego CA 92123",
    "addr:housenumber":"3444",
    "addr:postcode":"92123",
    "addr:street":"Kearny Villa Rd",
    "iso:country":"US",
    "sg:address":"3444 Kearny Villa Rd",
    "sg:city":"San Diego",
    "sg:classifiers":[
        {
            "category":"Health Services",
            "subcategory":"Doctor",
            "type":"Services"
        }
    ],
    "sg:phone":"+1 858 874 0033",
    "sg:postcode":"92123",
    "sg:province":"CA",
    "sg:tags":[
        "physician",
        "surgeon"
    ],
    "wof:name":"Sam Maywood MD",
    "wof:placetype":"venue"
},
  "geometry": {"coordinates":[-117.151338,32.809263],"type":"Point"}
}