{
  "type": "Feature",
  "properties": {
    "addr:full":"17510 N Tretheway Rd Lockeford CA 95237",
    "addr:housenumber":"17510",
    "addr:postcode":"95237",
    "addr:street":"N Tretheway Rd",
    "iso:country":"US",
    "sg:address":"17510 N Tretheway Rd",
    "sg:city":"Lockeford",
    "sg:classifiers":[
        {
            "category":"Professional",
            "type":"Services"
        }
    ],
    "sg:phone":"+1 209 369 3700",
    "sg:postcode":"95237",
    "sg:province":"CA",
    "wof:name":"Judgement Asset Recovery",
    "wof:placetype":"venue"
},
  "geometry": {"coordinates":[-121.17829399999999,38.14371],"type":"Point"}
}