{
  "type": "Feature",
  "properties": {
    "addr:full":"2203 E 28th St Long Beach CA 90755",
    "addr:housenumber":"2203",
    "addr:postcode":"90755",
    "addr:street":"E 28Th St",
    "iso:country":"US",
    "sg:address":"2203 E 28th St",
    "sg:city":"Long Beach",
    "sg:classifiers":[
        {
            "category":"Manufacturing",
            "subcategory":"Metals",
            "type":"Manufacturing & Wholesale Goods"
        },
        {
            "category":"Manufacturing",
            "subcategory":"Tools & Machinery",
            "type":"Manufacturing & Wholesale Goods"
        }
    ],
    "sg:phone":"+1 562 424 8615",
    "sg:postcode":"90755",
    "sg:province":"CA",
    "sg:tags":[
        "oil",
        "retailer",
        "valve"
    ],
    "wof:name":"M C Bowers Co",
    "wof:placetype":"venue"
},
  "geometry": {"coordinates":[-118.16435799999999,33.808098],"type":"Point"}
}