{
  "type": "Feature",
  "properties": {
    "addr:full":"1649 Fremont Ave Simi Valley CA 93065",
    "addr:housenumber":"1649",
    "addr:postcode":"93065",
    "addr:street":"Fremont Ave",
    "iso:country":"US",
    "sg:address":"1649 Fremont Ave",
    "sg:city":"Simi Valley",
    "sg:classifiers":[
        {
            "category":"Wholesale",
            "subcategory":"Groceries",
            "type":"Manufacturing & Wholesale Goods"
        }
    ],
    "sg:phone":"+1 805 582 2770",
    "sg:postcode":"93065",
    "sg:province":"CA",
    "wof:name":"Cookie Clones",
    "wof:placetype":"venue"
},
  "geometry": {"coordinates":[-118.76817200000001,34.260896],"type":"Point"}
}