{
  "type": "Feature",
  "properties": {
    "addr:full":"15749 California Ave Paramount CA 90723",
    "addr:housenumber":"15749",
    "addr:postcode":"90723",
    "addr:street":"California Ave",
    "iso:country":"US",
    "sg:address":"15749 California Ave",
    "sg:city":"Paramount",
    "sg:classifiers":[
        {
            "category":"Professional",
            "subcategory":"Employment Agencies",
            "type":"Services"
        }
    ],
    "sg:phone":"+1 562 232 0240",
    "sg:postcode":"90723",
    "sg:province":"CA",
    "wof:name":"Rally Staffing",
    "wof:placetype":"venue"
},
  "geometry": {"coordinates":[-118.15888,33.889705],"type":"Point"}
}