{
  "type": "Feature",
  "properties": {
    "iso:country":"US",
    "sg:address":"258 Lancaster Dr",
    "sg:city":"Manteca",
    "sg:classifiers":[
        {
            "category":"Real Estate",
            "subcategory":"Real Estate Operator",
            "type":"Services"
        }
    ],
    "sg:phone":"+1 209 823 4588",
    "sg:postcode":"95336",
    "sg:province":"CA",
    "sg:tags":[
        "apartment"
    ],
    "wof:name":"Colony North Apartments",
    "wof:placetype":"venue"
},
  "geometry": {"coordinates":[-121.215305,37.814076],"type":"Point"}
}