{
  "type": "Feature",
  "properties": {
    "iso:country":"US",
    "sg:address":"27600 Bouquet Canyon Rd",
    "sg:city":"Santa Clarita",
    "sg:classifiers":[
        {
            "category":"Communications",
            "subcategory":"Radio Station",
            "type":"Services"
        }
    ],
    "sg:phone":"+1 661 263 0585",
    "sg:postcode":"91350",
    "sg:province":"CA",
    "sg:tags":[
        "broadcast"
    ],
    "wof:name":"Clear Channel Santa Clarita",
    "wof:placetype":"venue"
},
  "geometry": {"coordinates":[-118.510288,34.443176],"type":"Point"}
}