{
  "type": "Feature",
  "properties": {
    "iso:country":"US",
    "sg:address":"44909 Golf Center Pkwy",
    "sg:city":"Indio",
    "sg:classifiers":[
        {
            "category":"Building & Trades",
            "subcategory":"Construction",
            "type":"Services"
        }
    ],
    "sg:phone":"+1 760 775 4500",
    "sg:postcode":"92201",
    "sg:province":"CA",
    "sg:tags":[
        "equipment",
        "rooms",
        "clean"
    ],
    "wof:name":"Purus International Inc",
    "wof:placetype":"venue"
},
  "geometry": {"coordinates":[-116.204266,33.724133],"type":"Point"}
}