{
  "type": "Feature",
  "properties": {
    "iso:country":"US",
    "sg:address":"21465 Palomar St",
    "sg:city":"Wildomar",
    "sg:classifiers":[
        {
            "category":"Food & Beverages",
            "subcategory":"Groceries & Convenience Stores",
            "type":"Retail Goods"
        }
    ],
    "sg:phone":"+1 951 678 6110",
    "sg:postcode":"92595",
    "sg:province":"CA",
    "sg:tags":[
        "market"
    ],
    "wof:name":"J & S Market",
    "wof:placetype":"venue"
},
  "geometry": {"coordinates":[-117.274002,33.604599],"type":"Point"}
}