{
  "type": "Feature",
  "properties": {
    "iso:country":"US",
    "sg:address":"1633 S Robertson Blvd",
    "sg:city":"Los Angeles",
    "sg:classifiers":[
        {
            "category":"Retail",
            "subcategory":"Auto Repair",
            "type":"Services"
        }
    ],
    "sg:phone":"+1 310 556 1606",
    "sg:postcode":"90035",
    "sg:province":"CA",
    "sg:website":"www.brownbrosautobody.com/index....",
    "wof:name":"Brown Bros. Auto Body & Paint Shop",
    "wof:placetype":"venue"
},
  "geometry": {"coordinates":[-118.385446,34.04955],"type":"Point"}
}