{
  "type": "Feature",
  "properties": {
    "addr:full":"360 S Milliken Ave Ontario CA 91761",
    "addr:housenumber":"360",
    "addr:postcode":"91761",
    "addr:street":"S Milliken Ave",
    "iso:country":"US",
    "sg:address":"360 S Milliken Ave",
    "sg:city":"Ontario",
    "sg:classifiers":[
        {
            "category":"Communications",
            "type":"Services"
        }
    ],
    "sg:phone":"+1 951 727 5000",
    "sg:postcode":"91761",
    "sg:province":"CA",
    "sg:website":"www.linkline.com",
    "wof:name":"Linkline Communication",
    "wof:placetype":"venue"
},
  "geometry": {"coordinates":[-117.55820900000001,34.061887],"type":"Point"}
}