{
  "type": "Feature",
  "properties": {
    "iso:country":"US",
    "sg:address":"360 S Milliken Ave",
    "sg:city":"Ontario",
    "sg:classifiers":[
        {
            "category":"Communications",
            "type":"Services"
        }
    ],
    "sg:phone":"+1 951 727 5000",
    "sg:postcode":"91761",
    "sg:province":"CA",
    "sg:website":"www.linkline.com",
    "wof:name":"Linkline Communication",
    "wof:placetype":"venue"
},
  "geometry": {"coordinates":[-117.558209,34.061887],"type":"Point"}
}