{
  "type": "Feature",
  "properties": {
    "addr:full":"2482 Newport Blvd Costa Mesa CA 92627",
    "addr:housenumber":"2482",
    "addr:postcode":"92627",
    "addr:street":"Newport Blvd Costa",
    "iso:country":"US",
    "sg:address":"2482 Newport Blvd",
    "sg:city":"Costa Mesa",
    "sg:classifiers":[
        {
            "category":"Building & Trades",
            "subcategory":"Construction",
            "type":"Services"
        }
    ],
    "sg:phone":"+1 949 515 7440",
    "sg:postcode":"92627",
    "sg:province":"CA",
    "sg:tags":[
        "resurfacing",
        "laying",
        "refinishing",
        "floor"
    ],
    "wof:name":"Hardwood Floor Store",
    "wof:placetype":"venue"
},
  "geometry": {"coordinates":[-117.90188999999999,33.658695],"type":"Point"}
}