{
  "type": "Feature",
  "properties": {
    "addr:full":"851 Irwin St San Rafael CA 94901",
    "addr:housenumber":"851",
    "addr:postcode":"94901",
    "addr:street":"Irwin St",
    "iso:country":"US",
    "sg:address":"851 Irwin St",
    "sg:city":"San Rafael",
    "sg:classifiers":[
        {
            "category":"Professional",
            "subcategory":"Accounting & Tax Preparation",
            "type":"Services"
        }
    ],
    "sg:phone":"+1 415 259 0112",
    "sg:postcode":"94901",
    "sg:province":"CA",
    "sg:tags":[
        "accountant"
    ],
    "wof:name":"Harrington Group",
    "wof:placetype":"venue"
},
  "geometry": {"coordinates":[-122.521123,37.970854],"type":"Point"}
}