{
  "type": "Feature",
  "properties": {
    "addr:full":"6330 State Hwy 193 Georgetown CA 95634",
    "addr:housenumber":"6330",
    "addr:postcode":"95634",
    "addr:street":"State Hwy 193",
    "iso:country":"US",
    "sg:address":"6330 State Hwy 193",
    "sg:city":"Georgetown",
    "sg:classifiers":[
        {
            "category":"Professional",
            "subcategory":"Lawyer & Legal Services",
            "type":"Services"
        }
    ],
    "sg:phone":"+1 530 333 4014",
    "sg:postcode":"95634",
    "sg:province":"CA",
    "sg:tags":[
        "attorney"
    ],
    "wof:name":"Abigail L Roseman",
    "wof:placetype":"venue"
},
  "geometry": {"coordinates":[-120.83573,38.902554],"type":"Point"}
}