{
  "type": "Feature",
  "properties": {
    "iso:country":"US",
    "sg:address":"3299 Mission St",
    "sg:city":"San Francisco",
    "sg:classifiers":[
        {
            "category":"Restaurant",
            "type":"Food & Drink"
        }
    ],
    "sg:phone":"+1 415 920 9430",
    "sg:postcode":"94110",
    "sg:province":"CA",
    "wof:name":"Stray Fish",
    "wof:placetype":"venue"
},
  "geometry": {"coordinates":[-122.420019,37.745388],"type":"Point"}
}