{
  "type": "Feature",
  "properties": {
    "iso:country":"US",
    "sg:address":"7727 River Landing Dr",
    "sg:city":"Sacramento",
    "sg:classifiers":[
        {
            "category":"Wholesale",
            "subcategory":"Toys & Hobbies",
            "type":"Manufacturing & Wholesale Goods"
        }
    ],
    "sg:phone":"+1 916 395 2133",
    "sg:postcode":"95831",
    "sg:province":"CA",
    "sg:tags":[
        "whole"
    ],
    "wof:name":"Tl Trading Company",
    "wof:placetype":"venue"
},
  "geometry": {"coordinates":[-121.537856,38.476265],"type":"Point"}
}