{
  "type": "Feature",
  "properties": {
    "addr:full":"1810 Parnell Ave Los Angeles CA 90025",
    "addr:housenumber":"1810",
    "addr:postcode":"90025",
    "addr:street":"Parnell Ave",
    "iso:country":"US",
    "sg:address":"1810 Parnell Ave",
    "sg:city":"Los Angeles",
    "sg:classifiers":[
        {
            "category":"Professional",
            "type":"Services"
        }
    ],
    "sg:phone":"+1 310 470 0404",
    "sg:postcode":"90025",
    "sg:province":"CA",
    "wof:name":"Gorge Collections",
    "wof:placetype":"venue"
},
  "geometry": {"coordinates":[-118.42923500000001,34.052052],"type":"Point"}
}