{
  "type": "Feature",
  "properties": {
    "iso:country":"US",
    "sg:address":"3227 Lakeshore Ave",
    "sg:city":"Oakland",
    "sg:classifiers":[
        {
            "category":"Personal",
            "subcategory":"Beauty Salon",
            "type":"Services"
        },
        {
            "category":"Personal",
            "subcategory":"Barber",
            "type":"Services"
        },
        {
            "category":"Personal",
            "subcategory":"Skin Care",
            "type":"Services"
        },
        {
            "category":"Shopping",
            "subcategory":"Beauty & Cosmetics",
            "type":"Retail Goods"
        }
    ],
    "sg:phone":"+1 510 465 9552",
    "sg:postcode":"94610",
    "sg:province":"CA",
    "sg:tags":[
        "supply"
    ],
    "wof:name":"Center Stage West Salon",
    "wof:placetype":"venue"
},
  "geometry": {"coordinates":[-122.245003,37.810699],"type":"Point"}
}