{
  "type": "Feature",
  "properties": {
    "addr:full":"226 Airport Parkway San Jose CA 95110",
    "addr:housenumber":"226",
    "addr:postcode":"95110",
    "addr:street":"Airport Parkway",
    "iso:country":"US",
    "sg:address":"226 Airport Parkway",
    "sg:city":"San Jose",
    "sg:classifiers":[
        {
            "category":"Communications",
            "subcategory":"Newspaper",
            "type":"Services"
        },
        {
            "category":"Real Estate",
            "subcategory":"Architect",
            "type":"Services"
        }
    ],
    "sg:phone":"+1 408 453 8300",
    "sg:postcode":"95110",
    "sg:province":"CA",
    "sg:tags":[
        "print",
        "medium"
    ],
    "wof:name":"Networking Architechs",
    "wof:placetype":"venue"
},
  "geometry": {"coordinates":[-121.92250900000001,37.369255],"type":"Point"}
}