{
  "type": "Feature",
  "properties": {
    "addr:full":"4130 Ming Ave Bakersfield CA 93309",
    "addr:housenumber":"4130",
    "addr:postcode":"93309",
    "addr:street":"Ming Ave",
    "iso:country":"US",
    "sg:address":"4130 Ming Ave",
    "sg:city":"Bakersfield",
    "sg:classifiers":[
        {
            "category":"Social Services",
            "type":"Services"
        }
    ],
    "sg:phone":"+1 661 835 0337",
    "sg:postcode":"93309",
    "sg:province":"CA",
    "sg:tags":[
        "organization",
        "welfare"
    ],
    "wof:name":"Salvation Army",
    "wof:placetype":"venue"
},
  "geometry": {"coordinates":[-119.049514,35.339631],"type":"Point"}
}