{
  "type": "Feature",
  "properties": {
    "addr:full":"1805 E Bayshore Rd Palo Alto CA 94303",
    "addr:housenumber":"1805",
    "addr:postcode":"94303",
    "addr:street":"E Bayshore Rd",
    "iso:country":"US",
    "sg:address":"1805 E Bayshore Rd",
    "sg:city":"Palo Alto",
    "sg:classifiers":[
        {
            "category":"Professional",
            "type":"Services"
        }
    ],
    "sg:phone":"+1 650 853 0420",
    "sg:postcode":"94303",
    "sg:province":"CA",
    "wof:name":"Thomas Ladonnis",
    "wof:placetype":"venue"
},
  "geometry": {"coordinates":[-122.129987,37.454482],"type":"Point"}
}