{
  "type": "Feature",
  "properties": {
    "iso:country":"US",
    "sg:address":"15924 S Orchard Ave",
    "sg:city":"Gardena",
    "sg:classifiers":[
        {
            "category":"Building & Trades",
            "subcategory":"Landscaping Services",
            "type":"Services"
        }
    ],
    "sg:phone":"+1 310 327 1926",
    "sg:postcode":"90247",
    "sg:province":"CA",
    "sg:tags":[
        "tree",
        "landscape",
        "contractor"
    ],
    "wof:name":"General Tree Service",
    "wof:placetype":"venue"
},
  "geometry": {"coordinates":[-118.288282,33.886894],"type":"Point"}
}