{
  "type": "Feature",
  "properties": {
    "addr:full":"7801 Shoup Ave Canoga Park CA 91304",
    "addr:housenumber":"7801",
    "addr:postcode":"91304",
    "addr:street":"Shoup Ave",
    "iso:country":"US",
    "sg:address":"7801 Shoup Ave",
    "sg:city":"Canoga Park",
    "sg:classifiers":[
        {
            "category":"Building & Trades",
            "subcategory":"Electrical",
            "type":"Services"
        }
    ],
    "sg:phone":"+1 818 704 1532",
    "sg:postcode":"91304",
    "sg:province":"CA",
    "sg:tags":[
        "electric",
        "contractor"
    ],
    "wof:name":"Pacific Coast Electrical Cont",
    "wof:placetype":"venue"
},
  "geometry": {"coordinates":[-118.61470799999999,34.215519],"type":"Point"}
}