{
  "type": "Feature",
  "properties": {
    "addr:full":"16105 Main St Volcano CA 95689",
    "addr:housenumber":"16105",
    "addr:postcode":"95689",
    "addr:street":"Main St",
    "iso:country":"US",
    "sg:address":"16105 Main St",
    "sg:city":"Volcano",
    "sg:classifiers":[
        {
            "category":"Shopping",
            "type":"Retail Goods"
        }
    ],
    "sg:phone":"+1 209 296 3334",
    "sg:postcode":"95689",
    "sg:province":"CA",
    "sg:tags":[
        "art",
        "gallery",
        "dealer"
    ],
    "wof:name":"Volcano Gallery",
    "wof:placetype":"venue"
},
  "geometry": {"coordinates":[-120.630781,38.441895],"type":"Point"}
}