{
  "type": "Feature",
  "properties": {
    "addr:full":"3144 El Camino Real Carlsbad CA 92008",
    "addr:housenumber":"3144",
    "addr:postcode":"92008",
    "addr:street":"El Camino Real",
    "iso:country":"US",
    "sg:address":"3144 El Camino Real",
    "sg:city":"Carlsbad",
    "sg:classifiers":[
        {
            "category":"Health Services",
            "subcategory":"Dentist",
            "type":"Services"
        }
    ],
    "sg:phone":"+1 760 720 7372",
    "sg:postcode":"92008",
    "sg:province":"CA",
    "wof:name":"William J Cho DDS",
    "wof:placetype":"venue"
},
  "geometry": {"coordinates":[-117.32340600000001,33.17317],"type":"Point"}
}