{
  "type": "Feature",
  "properties": {
    "iso:country":"US",
    "sg:address":"1921 E Deere Ave",
    "sg:city":"Santa Ana",
    "sg:classifiers":[
        {
            "category":"Shopping",
            "subcategory":"Stationery & Office Supplies",
            "type":"Retail Goods"
        }
    ],
    "sg:phone":"+1 949 250 3101",
    "sg:postcode":"92705",
    "sg:province":"CA",
    "sg:tags":[
        "equipment"
    ],
    "sg:website":"www.regalbp.com",
    "wof:name":"Regal Business Products",
    "wof:placetype":"venue"
},
  "geometry": {"coordinates":[-117.84899900000001,33.7048],"type":"Point"}
}