{
  "type": "Feature",
  "properties": {
    "addr:full":"435 Beaver St Santa Rosa CA 95404",
    "addr:housenumber":"435",
    "addr:postcode":"ca 95404",
    "addr:street":"Beaver St",
    "iso:country":"US",
    "sg:address":"435 Beaver St",
    "sg:city":"Santa Rosa",
    "sg:classifiers":[
        {
            "category":"Real Estate",
            "subcategory":"Developer",
            "type":"Services"
        }
    ],
    "sg:phone":"+1 707 568 3482",
    "sg:postcode":"95404",
    "sg:province":"CA",
    "wof:name":"Hugh Futrell",
    "wof:placetype":"venue"
},
  "geometry": {"coordinates":[-122.712175,38.442845],"type":"Point"}
}