{
  "type": "Feature",
  "properties": {
    "addr:full":"449 W Imperial Hwy Los Angeles CA 90061",
    "addr:housenumber":"449",
    "addr:postcode":"90061",
    "addr:street":"W Imperial Hwy",
    "iso:country":"US",
    "sg:address":"449 W Imperial Hwy",
    "sg:city":"Los Angeles",
    "sg:classifiers":[
        {
            "category":"Professional",
            "type":"Services"
        }
    ],
    "sg:phone":"+1 323 756 1006",
    "sg:postcode":"90061",
    "sg:province":"CA",
    "sg:tags":[
        "gas"
    ],
    "wof:name":"South City Gas",
    "wof:placetype":"venue"
},
  "geometry": {"coordinates":[-118.28217100000001,33.930878],"type":"Point"}
}