{
  "type": "Feature",
  "properties": {
    "iso:country":"US",
    "sg:address":"17300 Roscoe Blvd",
    "sg:city":"Northridge",
    "sg:classifiers":[
        {
            "category":"Health Services",
            "subcategory":"Nursing And Care Facility",
            "type":"Services"
        }
    ],
    "sg:phone":"+1 818 881 1475",
    "sg:postcode":"91325",
    "sg:province":"CA",
    "sg:tags":[
        "home",
        "retirement",
        "community"
    ],
    "wof:name":"Northridge Point",
    "wof:placetype":"venue"
},
  "geometry": {"coordinates":[-118.510848,34.221094],"type":"Point"}
}