{
  "type": "Feature",
  "properties": {
    "addr:full":"4590 MacArthur Boulevard Newport Beach CA 92660",
    "addr:housenumber":"4590",
    "addr:postcode":"92660",
    "addr:street":"Macarthur Boulevard",
    "iso:country":"US",
    "sg:address":"4590 MacArthur Boulevard",
    "sg:city":"Newport Beach",
    "sg:classifiers":[
        {
            "category":"Professional",
            "subcategory":"Lawyer & Legal Services",
            "type":"Services"
        }
    ],
    "sg:phone":"+1 949 851 2115",
    "sg:postcode":"92660",
    "sg:province":"CA",
    "wof:name":"Reedy M Alan Attorney At Law",
    "wof:placetype":"venue"
},
  "geometry": {"coordinates":[-117.86439300000001,33.668543],"type":"Point"}
}