{
  "type": "Feature",
  "properties": {
    "iso:country":"US",
    "sg:address":"5308 Pacific Ave",
    "sg:city":"Stockton",
    "sg:classifiers":[
        {
            "category":"Shopping",
            "subcategory":"Clothing, Apparel, & Fashions",
            "type":"Retail Goods"
        }
    ],
    "sg:phone":"+1 209 955 1164",
    "sg:postcode":"95207",
    "sg:province":"CA",
    "sg:tags":[
        "sportswear"
    ],
    "wof:name":"Shirtique",
    "wof:placetype":"venue"
},
  "geometry": {"coordinates":[-121.315957,37.999529],"type":"Point"}
}