{
  "type": "Feature",
  "properties": {
    "iso:country":"US",
    "sg:address":"2029 Yosemite Blvd",
    "sg:city":"Modesto",
    "sg:classifiers":[
        {
            "category":"Shopping",
            "subcategory":"Florist",
            "type":"Retail Goods"
        }
    ],
    "sg:phone":"+1 209 544 9677",
    "sg:postcode":"95354",
    "sg:province":"CA",
    "wof:name":"Say It With Flowers",
    "wof:placetype":"venue"
},
  "geometry": {"coordinates":[-120.960087,37.638253],"type":"Point"}
}