{
  "type": "Feature",
  "properties": {
    "addr:full":"912 N Eastern Ave Los Angeles CA 90063",
    "addr:housenumber":"912",
    "addr:postcode":"90063",
    "addr:street":"N Eastern Ave",
    "iso:country":"US",
    "sg:address":"912 N Eastern Ave",
    "sg:city":"Los Angeles",
    "sg:classifiers":[
        {
            "category":"Utilities",
            "subcategory":"Cable",
            "type":"Services"
        }
    ],
    "sg:phone":"+1 323 264 0371",
    "sg:postcode":"90063",
    "sg:province":"CA",
    "sg:tags":[
        "television"
    ],
    "wof:name":"Komtech",
    "wof:placetype":"venue"
},
  "geometry": {"coordinates":[-118.17410700000001,34.0466],"type":"Point"}
}