{
  "type": "Feature",
  "properties": {
    "iso:country":"US",
    "sg:address":"23322 Madero",
    "sg:city":"Mission Viejo",
    "sg:classifiers":[
        {
            "category":"Professional",
            "type":"Services"
        }
    ],
    "sg:phone":"+1 949 380 4380",
    "sg:postcode":"92691",
    "sg:province":"CA",
    "wof:name":"Inventions-Plus Inc",
    "wof:placetype":"venue"
},
  "geometry": {"coordinates":[-117.677556,33.623035],"type":"Point"}
}