{
  "type": "Feature",
  "properties": {
    "addr:full":"202 Bicknell Ave Santa Monica CA 90405",
    "addr:housenumber":"202",
    "addr:postcode":"90405",
    "addr:street":"Bicknell Ave",
    "iso:country":"US",
    "sg:address":"202 Bicknell Ave",
    "sg:city":"Santa Monica",
    "sg:classifiers":[
        {
            "category":"Professional",
            "subcategory":"Art Services",
            "type":"Services"
        }
    ],
    "sg:phone":"+1 310 392 8786",
    "sg:postcode":"90405",
    "sg:province":"CA",
    "sg:tags":[
        "commercial",
        "design"
    ],
    "wof:name":"American Contrs Connection",
    "wof:placetype":"venue"
},
  "geometry": {"coordinates":[-118.486542,34.00739],"type":"Point"}
}