{
  "type": "Feature",
  "properties": {
    "addr:full":"505 San Marin Dr Novato CA 94945",
    "addr:housenumber":"505",
    "addr:postcode":"94945",
    "addr:street":"San Marin Dr",
    "iso:country":"US",
    "sg:address":"505 San Marin Dr",
    "sg:city":"Novato",
    "sg:classifiers":[
        {
            "category":"Real Estate",
            "subcategory":"Real Estate Agent",
            "type":"Services"
        }
    ],
    "sg:phone":"+1 415 899 8484",
    "sg:postcode":"94945",
    "sg:province":"CA",
    "wof:name":"Kelley Forest",
    "wof:placetype":"venue"
},
  "geometry": {"coordinates":[-122.584756,38.121607],"type":"Point"}
}