{
  "type": "Feature",
  "properties": {
    "addr:full":"41213 Highway 41 Oakhurst CA 93644",
    "addr:housenumber":"41213",
    "addr:postcode":"93644",
    "addr:street":"Highway 41",
    "iso:country":"US",
    "sg:address":"41213 Highway 41",
    "sg:city":"Oakhurst",
    "sg:classifiers":[
        {
            "category":"Banks & Credit Unions",
            "subcategory":"Investment Brokerage",
            "type":"Services"
        },
        {
            "category":"Banks & Credit Unions",
            "subcategory":"Financial Services",
            "type":"Services"
        }
    ],
    "sg:phone":"+1 559 658 5110",
    "sg:postcode":"93644",
    "sg:province":"CA",
    "sg:tags":[
        "advisory",
        "management"
    ],
    "wof:name":"Ashby & Teague Investments Lp",
    "wof:placetype":"venue"
},
  "geometry": {"coordinates":[-119.630042,37.371545],"type":"Point"}
}