{
  "type": "Feature",
  "properties": {
    "iso:country":"US",
    "sg:address":"7888 Wren Ave",
    "sg:city":"Gilroy",
    "sg:classifiers":[
        {
            "category":"Health Services",
            "subcategory":"Doctor",
            "type":"Services"
        }
    ],
    "sg:phone":"+1 408 848 5522",
    "sg:postcode":"95020",
    "sg:province":"CA",
    "sg:tags":[
        "physician",
        "surgeon"
    ],
    "wof:name":"K K Bhatia MD",
    "wof:placetype":"venue"
},
  "geometry": {"coordinates":[-121.58666599999999,37.011972],"type":"Point"}
}