{
  "type": "Feature",
  "properties": {
    "addr:full":"2990 State St Carlsbad CA 92008",
    "addr:housenumber":"2990",
    "addr:postcode":"92008",
    "addr:street":"State St",
    "iso:country":"US",
    "sg:address":"2990 State St",
    "sg:city":"Carlsbad",
    "sg:classifiers":[
        {
            "category":"Bars & Pubs",
            "subcategory":"Nightclub",
            "type":"Food & Drink"
        }
    ],
    "sg:phone":"+1 760 434 2114",
    "sg:postcode":"92008",
    "sg:province":"CA",
    "sg:tags":[
        "nightlife"
    ],
    "wof:name":"Village Pub the",
    "wof:placetype":"venue"
},
  "geometry": {"coordinates":[-117.34899900000001,33.159698],"type":"Point"}
}