{
  "type": "Feature",
  "properties": {
    "iso:country":"US",
    "sg:address":"2970 Hilltop Mall Rd",
    "sg:city":"San Pablo",
    "sg:classifiers":[
        {
            "category":"Health Services",
            "subcategory":"Doctor",
            "type":"Services"
        }
    ],
    "sg:phone":"+1 510 222 5290",
    "sg:postcode":"94806",
    "sg:province":"CA",
    "sg:tags":[
        "clinic",
        "medical",
        "outpatient",
        "specialty"
    ],
    "wof:name":"Planned Prnthod Shasta-Diablo",
    "wof:placetype":"venue"
},
  "geometry": {"coordinates":[-122.331894,37.979033],"type":"Point"}
}