{
  "type": "Feature",
  "properties": {
    "iso:country":"US",
    "sg:address":"2087 Santa Barbara St",
    "sg:city":"San Luis Obispo",
    "sg:classifiers":[
        {
            "category":"Home & Garden",
            "subcategory":"Furniture",
            "type":"Retail Goods"
        }
    ],
    "sg:phone":"+1 805 544 2505",
    "sg:postcode":"93401",
    "sg:province":"CA",
    "wof:name":"Brooks Woodcraft",
    "wof:placetype":"venue"
},
  "geometry": {"coordinates":[-120.656298,35.271594],"type":"Point"}
}