{
  "type": "Feature",
  "properties": {
    "addr:full":"752 Broadway Sonoma CA 95476",
    "addr:housenumber":"752",
    "addr:postcode":"95476",
    "addr:street":"Broadway",
    "iso:country":"US",
    "sg:address":"752 Broadway",
    "sg:city":"Sonoma",
    "sg:classifiers":[
        {
            "category":"Manufacturing",
            "subcategory":"Printing",
            "type":"Manufacturing & Wholesale Goods"
        }
    ],
    "sg:phone":"+1 707 996 9529",
    "sg:postcode":"95476",
    "sg:province":"CA",
    "sg:tags":[
        "book",
        "publishing"
    ],
    "wof:name":"Arcus Publishing",
    "wof:placetype":"venue"
},
  "geometry": {"coordinates":[-122.45846,38.287383],"type":"Point"}
}