{
  "type": "Feature",
  "properties": {
    "iso:country":"US",
    "sg:address":"8967 Atlantic Ave",
    "sg:city":"South Gate",
    "sg:classifiers":[
        {
            "category":"Travel",
            "subcategory":"Hotels & Motels",
            "type":"Entertainment"
        }
    ],
    "sg:phone":"+1 323 564 2176",
    "sg:postcode":"90280",
    "sg:province":"CA",
    "wof:name":"Villa Motel",
    "wof:placetype":"venue"
},
  "geometry": {"coordinates":[-118.181999,33.950199],"type":"Point"}
}