{
  "type": "Feature",
  "properties": {
    "iso:country":"US",
    "sg:address":"1802 Santa Fe Rd",
    "sg:city":"South Lake Tahoe",
    "sg:classifiers":[
        {
            "category":"Building & Trades",
            "subcategory":"Construction",
            "type":"Services"
        }
    ],
    "sg:phone":"+1 530 577 5628",
    "sg:postcode":"96150",
    "sg:province":"CA",
    "sg:tags":[
        "maker",
        "cabinet"
    ],
    "wof:name":"Mountain High Cabinets",
    "wof:placetype":"venue"
},
  "geometry": {"coordinates":[-120.014171,38.859042],"type":"Point"}
}