{
  "type": "Feature",
  "properties": {
    "iso:country":"US",
    "sg:address":"2218 Alpine Blvd",
    "sg:city":"Alpine",
    "sg:classifiers":[
        {
            "category":"Professional",
            "subcategory":"Management & Consulting",
            "type":"Services"
        }
    ],
    "sg:phone":"+1 619 445 9236",
    "sg:postcode":"91901",
    "sg:province":"CA",
    "sg:tags":[
        "consultant",
        "educational"
    ],
    "wof:name":"Southern California American",
    "wof:placetype":"venue"
},
  "geometry": {"coordinates":[-116.76587,32.83555],"type":"Point"}
}