{
  "type": "Feature",
  "properties": {
    "addr:full":"18730 Roberts Rd Riverside CA 92508",
    "addr:housenumber":"18730",
    "addr:postcode":"92508",
    "addr:street":"Roberts Rd",
    "iso:country":"US",
    "sg:address":"18730 Roberts Rd",
    "sg:city":"Riverside",
    "sg:classifiers":[
        {
            "category":"Building & Trades",
            "subcategory":"Equipment Rental",
            "type":"Services"
        }
    ],
    "sg:phone":"+1 951 780 5900",
    "sg:postcode":"92508",
    "sg:province":"CA",
    "sg:tags":[
        "contractor"
    ],
    "wof:name":"M E Murphy Excavating",
    "wof:placetype":"venue"
},
  "geometry": {"coordinates":[-117.33520799999999,33.900083],"type":"Point"}
}