{
  "type": "Feature",
  "properties": {
    "iso:country":"US",
    "sg:address":"940 S Coast Dr",
    "sg:city":"Costa Mesa",
    "sg:classifiers":[
        {
            "category":"Wholesale",
            "subcategory":"Electrical",
            "type":"Manufacturing & Wholesale Goods"
        }
    ],
    "sg:phone":"+1 714 641 3937",
    "sg:postcode":"92626",
    "sg:province":"CA",
    "sg:tags":[
        "equipment",
        "electronic",
        "supply"
    ],
    "wof:name":"Analog Devices Inc",
    "wof:placetype":"venue"
},
  "geometry": {"coordinates":[-117.89542,33.68991],"type":"Point"}
}