{
  "type": "Feature",
  "properties": {
    "iso:country":"US",
    "sg:address":"15442 Newport Ave",
    "sg:city":"Tustin",
    "sg:classifiers":[
        {
            "category":"Banks & Credit Unions",
            "subcategory":"Bank",
            "type":"Services"
        }
    ],
    "sg:phone":"+1 800 462 8328",
    "sg:postcode":"92780",
    "sg:province":"CA",
    "sg:website":"www.schoolsfirstfcu.org",
    "wof:name":"SchoolsFirst Federal Credit Union",
    "wof:placetype":"venue"
},
  "geometry": {"coordinates":[-117.835212,33.720189],"type":"Point"}
}