{
  "type": "Feature",
  "properties": {
    "iso:country":"US",
    "sg:address":"3 Hazel St",
    "sg:city":"Hollister",
    "sg:classifiers":[
        {
            "category":"Home & Garden",
            "subcategory":"Building Materials",
            "type":"Retail Goods"
        }
    ],
    "sg:phone":"+1 831 630 0406",
    "sg:postcode":"95023",
    "sg:province":"CA",
    "sg:tags":[
        "glass",
        "window",
        "plate"
    ],
    "wof:name":"Golden State Glass",
    "wof:placetype":"venue"
},
  "geometry": {"coordinates":[-121.399657,36.847425],"type":"Point"}
}