{
  "type": "Feature",
  "properties": {
    "addr:full":"332 E Cedar St Oxnard CA 93033",
    "addr:housenumber":"332",
    "addr:postcode":"93033",
    "addr:street":"E Cedar St",
    "iso:country":"US",
    "sg:address":"332 E Cedar St",
    "sg:city":"Oxnard",
    "sg:classifiers":[
        {
            "category":"Professional",
            "type":"Services"
        }
    ],
    "sg:phone":"+1 805 487 3508",
    "sg:postcode":"93033",
    "sg:province":"CA",
    "wof:name":"Margarita Cruz",
    "wof:placetype":"venue"
},
  "geometry": {"coordinates":[-119.17528,34.184403],"type":"Point"}
}