{
  "type": "Feature",
  "properties": {
    "addr:full":"3500 W 8th Street Los Angeles CA 90005",
    "addr:housenumber":"3500",
    "addr:postcode":"90005",
    "addr:street":"W 8Th Street",
    "iso:country":"US",
    "sg:address":"3500 W 8th Street",
    "sg:city":"Los Angeles",
    "sg:classifiers":[
        {
            "category":"Shopping",
            "subcategory":"Comic Books",
            "type":"Retail Goods"
        }
    ],
    "sg:phone":"+1 213 383 5250",
    "sg:postcode":"90005",
    "sg:province":"CA",
    "wof:name":"Orange Comics",
    "wof:placetype":"venue"
},
  "geometry": {"coordinates":[-118.306652,34.057778],"type":"Point"}
}