{
  "type": "Feature",
  "properties": {
    "iso:country":"US",
    "sg:address":"4046 Chestnut St",
    "sg:city":"Riverside",
    "sg:classifiers":[
        {
            "category":"Professional",
            "subcategory":"Lawyer & Legal Services",
            "type":"Services"
        }
    ],
    "sg:phone":"+1 714 748 0430",
    "sg:postcode":"92501",
    "sg:province":"CA",
    "sg:tags":[
        "attorney"
    ],
    "wof:name":"Randolph K Driggs",
    "wof:placetype":"venue"
},
  "geometry": {"coordinates":[-117.37965199999999,33.98111],"type":"Point"}
}