{
  "type": "Feature",
  "properties": {
    "iso:country":"US",
    "sg:address":"85 N B St Ste 4",
    "sg:city":"San Mateo",
    "sg:classifiers":[
        {
            "category":"Restaurant",
            "type":"Food & Drink"
        }
    ],
    "sg:phone":"+1 650 347 8760",
    "sg:postcode":"94401",
    "sg:province":"CA",
    "sg:tags":[
        "mexican"
    ],
    "wof:name":"Los Primos Taqueria",
    "wof:placetype":"venue"
},
  "geometry": {"coordinates":[-122.324997,37.5681],"type":"Point"}
}