{
  "type": "Feature",
  "properties": {
    "addr:full":"305 N Harbor Blvd Ste 124 Fullerton CA 92832",
    "addr:housenumber":"305",
    "addr:postcode":"92832",
    "addr:street":"N Harbor Blvd Ste 124",
    "iso:country":"US",
    "sg:address":"305 N Harbor Blvd Ste 124",
    "sg:city":"Fullerton",
    "sg:classifiers":[
        {
            "category":"Food & Beverages",
            "subcategory":"Specialty",
            "type":"Retail Goods"
        }
    ],
    "sg:phone":"+1 714 738 0229",
    "sg:postcode":"92832",
    "sg:province":"CA",
    "sg:website":"www.thebritishgrocer.com/",
    "wof:name":"British Grocer",
    "wof:placetype":"venue"
},
  "geometry": {"coordinates":[-117.924708,33.87288],"type":"Point"}
}