{
  "type": "Feature",
  "properties": {
    "addr:full":"2100 Broadway St San Pablo CA 94806",
    "addr:housenumber":"2100",
    "addr:postcode":"94806",
    "addr:street":"Broadway St",
    "iso:country":"US",
    "sg:address":"2100 Broadway St",
    "sg:city":"San Pablo",
    "sg:classifiers":[
        {
            "category":"Organizations",
            "subcategory":"Religious Organization",
            "type":"Services"
        }
    ],
    "sg:phone":"+1 510 234 4388",
    "sg:postcode":"94806",
    "sg:province":"CA",
    "sg:tags":[
        "church"
    ],
    "wof:name":"Word Of Faith Church",
    "wof:placetype":"venue"
},
  "geometry": {"coordinates":[-122.344696,37.967915],"type":"Point"}
}