{
  "type": "Feature",
  "properties": {
    "iso:country":"US",
    "sg:address":"23221 Haskell Vista Ln",
    "sg:city":"Newhall",
    "sg:classifiers":[
        {
            "category":"Professional",
            "type":"Services"
        }
    ],
    "sg:phone":"+1 661 255 2169",
    "sg:postcode":"91321",
    "sg:province":"CA",
    "wof:name":"Wake Masters",
    "wof:placetype":"venue"
},
  "geometry": {"coordinates":[-118.534506,34.366971],"type":"Point"}
}