{
  "type": "Feature",
  "properties": {
    "addr:full":"23221 Haskell Vista Ln Newhall CA 91321",
    "addr:housenumber":"23221",
    "addr:postcode":"91321",
    "addr:street":"Haskell Vista Ln",
    "iso:country":"US",
    "sg:address":"23221 Haskell Vista Ln",
    "sg:city":"Newhall",
    "sg:classifiers":[
        {
            "category":"Professional",
            "type":"Services"
        }
    ],
    "sg:phone":"+1 661 255 2169",
    "sg:postcode":"91321",
    "sg:province":"CA",
    "wof:name":"Wake Masters",
    "wof:placetype":"venue"
},
  "geometry": {"coordinates":[-118.53450599999999,34.366971],"type":"Point"}
}