{
  "type": "Feature",
  "properties": {
    "addr:full":"15408 Doolittle Rd Grass Valley CA 95949",
    "addr:housenumber":"15408",
    "addr:postcode":"95949",
    "addr:street":"Doolittle Rd",
    "iso:country":"US",
    "sg:address":"15408 Doolittle Rd",
    "sg:city":"Grass Valley",
    "sg:classifiers":[
        {
            "category":"Home & Garden",
            "subcategory":"Furniture",
            "type":"Retail Goods"
        }
    ],
    "sg:phone":"+1 530 272 8005",
    "sg:postcode":"95949",
    "sg:province":"CA",
    "wof:name":"MJB Assoc",
    "wof:placetype":"venue"
},
  "geometry": {"coordinates":[-121.149118,39.09984],"type":"Point"}
}