{
  "type": "Feature",
  "properties": {
    "addr:full":"5605 Gage Avenue Bell Gardens CA 90201",
    "addr:housenumber":"5605",
    "addr:postcode":"90201",
    "addr:street":"Gage Avenue",
    "iso:country":"US",
    "sg:address":"5605 Gage Avenue",
    "sg:city":"Bell Gardens",
    "sg:classifiers":[
        {
            "category":"Food & Beverages",
            "subcategory":"Groceries & Convenience Stores",
            "type":"Retail Goods"
        }
    ],
    "sg:phone":"+1 323 773 2001",
    "sg:postcode":"90201",
    "sg:province":"CA",
    "wof:name":"Villa Latina Market",
    "wof:placetype":"venue"
},
  "geometry": {"coordinates":[-118.164655,33.975768],"type":"Point"}
}