{
  "type": "Feature",
  "properties": {
    "addr:full":"989 Waverly Heights Dr Thousand Oaks CA 91360",
    "addr:housenumber":"989",
    "addr:postcode":"91360",
    "addr:street":"Waverly Heights Dr",
    "iso:country":"US",
    "sg:address":"989 Waverly Heights Dr",
    "sg:city":"Thousand Oaks",
    "sg:classifiers":[
        {
            "category":"Building & Trades",
            "subcategory":"Plumbing",
            "type":"Services"
        }
    ],
    "sg:phone":"+1 805 495 4916",
    "sg:postcode":"91360",
    "sg:province":"CA",
    "sg:tags":[
        "plumbing",
        "contractor"
    ],
    "wof:name":"Henry Plumbing",
    "wof:placetype":"venue"
},
  "geometry": {"coordinates":[-118.862138,34.200041],"type":"Point"}
}