{
  "type": "Feature",
  "properties": {
    "addr:full":"947 Enterprise Dr Ste 17 Sacramento CA 95825",
    "addr:housenumber":"947",
    "addr:postcode":"95825",
    "addr:street":"Enterprise Dr Ste 17",
    "iso:country":"US",
    "sg:address":"947 Enterprise Dr Ste 17",
    "sg:city":"Sacramento",
    "sg:classifiers":[
        {
            "category":"Personal",
            "subcategory":"Beauty Salon",
            "type":"Services"
        }
    ],
    "sg:phone":"+1 916 802 9956",
    "sg:postcode":"95825",
    "sg:province":"CA",
    "sg:tags":[
        "hair",
        "makeup",
        "artist"
    ],
    "wof:name":"Melissa Moreno",
    "wof:placetype":"venue"
},
  "geometry": {"coordinates":[-121.417123,38.583691],"type":"Point"}
}