{
  "type": "Feature",
  "properties": {
    "iso:country":"US",
    "sg:address":"4650 Cushing Pkwy",
    "sg:city":"Fremont",
    "sg:classifiers":[
        {
            "category":"Wholesale",
            "subcategory":"Machinery & Supplies",
            "type":"Manufacturing & Wholesale Goods"
        }
    ],
    "sg:phone":"+1 510 572 0200",
    "sg:postcode":"94538",
    "sg:province":"CA",
    "sg:tags":[
        "used",
        "machinery-new",
        "specially",
        "designed"
    ],
    "sg:website":"http://www.lamrc.com",
    "wof:name":"Lam Research Corporation",
    "wof:placetype":"venue"
},
  "geometry": {"coordinates":[-121.956338,37.4895],"type":"Point"}
}