{
  "type": "Feature",
  "properties": {
    "iso:country":"US",
    "sg:address":"2609 Florida St",
    "sg:city":"Huntington Beach",
    "sg:classifiers":[
        {
            "category":"Building & Trades",
            "subcategory":"Electrical",
            "type":"Services"
        }
    ],
    "sg:phone":"+1 714 969 4277",
    "sg:postcode":"92648",
    "sg:province":"CA",
    "sg:tags":[
        "electric",
        "contractor"
    ],
    "wof:name":"A 3D Corp",
    "wof:placetype":"venue"
},
  "geometry": {"coordinates":[-117.990995,33.681572],"type":"Point"}
}