{
  "type": "Feature",
  "properties": {
    "addr:full":"1408 W Rosecrans Avenue Gardena CA 90249",
    "addr:housenumber":"1408",
    "addr:postcode":"90249",
    "addr:street":"W Rosecrans Avenue",
    "iso:country":"US",
    "sg:address":"1408 W Rosecrans Avenue",
    "sg:city":"Gardena",
    "sg:classifiers":[
        {
            "category":"Autos & Motor Vehicles",
            "subcategory":"Fuel & Gas Station",
            "type":"Retail Goods"
        },
        {
            "category":"Food & Beverages",
            "subcategory":"Groceries & Convenience Stores",
            "type":"Retail Goods"
        }
    ],
    "sg:phone":"+1 310 538 5477",
    "sg:postcode":"90249",
    "sg:province":"CA",
    "wof:name":"Star Oil Company",
    "wof:placetype":"venue"
},
  "geometry": {"coordinates":[-118.300954,33.902029],"type":"Point"}
}