{
  "type": "Feature",
  "properties": {
    "addr:full":"29976 Margale Ln Vista CA 92084",
    "addr:housenumber":"29976",
    "addr:postcode":"92084",
    "addr:street":"Margale Ln",
    "iso:country":"US",
    "sg:address":"29976 Margale Ln",
    "sg:city":"Vista",
    "sg:classifiers":[
        {
            "category":"Retail",
            "subcategory":"Animal Services",
            "type":"Services"
        }
    ],
    "sg:phone":"+1 760 726 3391",
    "sg:postcode":"92084",
    "sg:province":"CA",
    "sg:tags":[
        "pet",
        "boarding",
        "sitting"
    ],
    "wof:name":"Margale Kennels",
    "wof:placetype":"venue"
},
  "geometry": {"coordinates":[-117.17912,33.257946],"type":"Point"}
}