{
  "type": "Feature",
  "properties": {
    "iso:country":"US",
    "sg:address":"881 Alma Real Dr",
    "sg:city":"Pacific Plsds",
    "sg:classifiers":[
        {
            "category":"Health Services",
            "subcategory":"Doctor",
            "type":"Services"
        }
    ],
    "sg:phone":"+1 310 454 3111",
    "sg:postcode":"90272",
    "sg:province":"CA",
    "sg:tags":[
        "dentist"
    ],
    "wof:name":"Dental Spa",
    "wof:placetype":"venue"
},
  "geometry": {"coordinates":[-118.524887,34.044368],"type":"Point"}
}