{
  "type": "Feature",
  "properties": {
    "addr:full":"6141 Katella Avenue Cypress CA 90630",
    "addr:housenumber":"6141",
    "addr:postcode":"90630",
    "addr:street":"Katella Avenue",
    "iso:country":"US",
    "sg:address":"6141 Katella Avenue",
    "sg:city":"Cypress",
    "sg:classifiers":[
        {
            "category":"Professional",
            "subcategory":"Computer Services",
            "type":"Services"
        }
    ],
    "sg:phone":"+1 714 503 4200",
    "sg:postcode":"90630",
    "sg:province":"CA",
    "sg:website":"http://www.cdgnow.com",
    "wof:name":"CDG",
    "wof:placetype":"venue"
},
  "geometry": {"coordinates":[-118.026624,33.803093],"type":"Point"}
}