{
  "type": "Feature",
  "properties": {
    "iso:country":"US",
    "sg:address":"11015 1/2 Alondra Blvd",
    "sg:city":"Norwalk",
    "sg:classifiers":[
        {
            "category":"Personal",
            "subcategory":"Beauty Salon",
            "type":"Services"
        }
    ],
    "sg:phone":"+1 562 864 4751",
    "sg:postcode":"90650",
    "sg:province":"CA",
    "sg:tags":[
        "hair"
    ],
    "wof:name":"Elwyn's Beauty Salon",
    "wof:placetype":"venue"
},
  "geometry": {"coordinates":[-118.099554,33.887621],"type":"Point"}
}