{
  "type": "Feature",
  "properties": {
    "addr:full":"8816 Limonite Ave Riverside CA 92509",
    "addr:housenumber":"8816",
    "addr:postcode":"92509",
    "addr:street":"Limonite Ave",
    "iso:country":"US",
    "sg:address":"8816 Limonite Ave",
    "sg:city":"Riverside",
    "sg:classifiers":[
        {
            "category":"Restaurant",
            "type":"Food & Drink"
        }
    ],
    "sg:phone":"+1 951 685 8663",
    "sg:postcode":"92509",
    "sg:province":"CA",
    "wof:name":"Juan Pollo",
    "wof:placetype":"venue"
},
  "geometry": {"coordinates":[-117.475651,33.975744],"type":"Point"}
}