{
  "type": "Feature",
  "properties": {
    "addr:full":"295 McCreary Ave Hanford CA 93230",
    "addr:housenumber":"295",
    "addr:postcode":"ca 93230",
    "addr:street":"Mccreary Ave",
    "iso:country":"US",
    "sg:address":"295 McCreary Ave",
    "sg:city":"Hanford",
    "sg:classifiers":[
        {
            "category":"Manufacturing",
            "subcategory":"Food",
            "type":"Manufacturing & Wholesale Goods"
        }
    ],
    "sg:phone":"+1 559 584 6289",
    "sg:postcode":"93230",
    "sg:province":"CA",
    "sg:tags":[
        "mfg"
    ],
    "wof:name":"Yumi Stuff",
    "wof:placetype":"venue"
},
  "geometry": {"coordinates":[-119.648318,36.343821],"type":"Point"}
}