{
  "type": "Feature",
  "properties": {
    "iso:country":"US",
    "sg:address":"9101 Brabham Drive",
    "sg:city":"Huntington Beach",
    "sg:classifiers":[
        {
            "category":"Education",
            "subcategory":"School",
            "type":"Public Place"
        }
    ],
    "sg:phone":"+1 714 378 4220",
    "sg:postcode":"92646",
    "sg:province":"CA",
    "sg:tags":[
        "high",
        "middle",
        "elementary"
    ],
    "wof:name":"Fountain Valley School District",
    "wof:placetype":"venue"
},
  "geometry": {"coordinates":[-117.96922499999999,33.680806],"type":"Point"}
}