{
  "type": "Feature",
  "properties": {
    "iso:country":"US",
    "sg:address":"155 W Washington Blvd",
    "sg:city":"Los Angeles",
    "sg:classifiers":[
        {
            "category":"Retail",
            "subcategory":"Portrait Studio",
            "type":"Services"
        },
        {
            "category":"Professional",
            "subcategory":"Art Services",
            "type":"Services"
        }
    ],
    "sg:phone":"+1 213 765 0594",
    "sg:postcode":"90015",
    "sg:province":"CA",
    "sg:tags":[
        "photographer",
        "photography",
        "store"
    ],
    "wof:name":"Nicolas Melillo Photographer",
    "wof:placetype":"venue"
},
  "geometry": {"coordinates":[-118.265943,34.187297],"type":"Point"}
}