{
  "type": "Feature",
  "properties": {
    "addr:full":"2852 Walnut Ave Tustin CA 92780",
    "addr:housenumber":"2852",
    "addr:postcode":"92780",
    "addr:street":"Walnut Ave",
    "iso:country":"US",
    "sg:address":"2852 Walnut Ave",
    "sg:city":"Tustin",
    "sg:classifiers":[
        {
            "category":"Wholesale",
            "subcategory":"Construction Materials",
            "type":"Manufacturing & Wholesale Goods"
        }
    ],
    "sg:phone":"+1 714 368 1023",
    "sg:postcode":"92780",
    "sg:province":"CA",
    "sg:tags":[
        "tile"
    ],
    "wof:name":"Art & Stone",
    "wof:placetype":"venue"
},
  "geometry": {"coordinates":[-117.80495999999999,33.713568],"type":"Point"}
}