{
  "type": "Feature",
  "properties": {
    "iso:country":"US",
    "sg:address":"3415 Riverdale Way",
    "sg:city":"Carmichael",
    "sg:classifiers":[
        {
            "category":"Building & Trades",
            "subcategory":"Cleaning & Sanitation",
            "type":"Services"
        }
    ],
    "sg:phone":"+1 916 876 0266",
    "sg:postcode":"95608",
    "sg:province":"CA",
    "sg:tags":[
        "carpet"
    ],
    "wof:name":"Stevenson's Carpet Care",
    "wof:placetype":"venue"
},
  "geometry": {"coordinates":[-121.30673299999999,38.626224],"type":"Point"}
}