{
  "type": "Feature",
  "properties": {
    "addr:full":"13658 Hawthorne Blvd Ste 215 Hawthorne CA 90250",
    "addr:housenumber":"13658",
    "addr:postcode":"90250",
    "addr:street":"Hawthorne Blvd Ste 215",
    "iso:country":"US",
    "sg:address":"13658 Hawthorne Blvd Ste 215",
    "sg:city":"Hawthorne",
    "sg:classifiers":[
        {
            "category":"Banks & Credit Unions",
            "subcategory":"Investment Brokerage",
            "type":"Services"
        }
    ],
    "sg:phone":"+1 310 856 2888",
    "sg:postcode":"90250",
    "sg:province":"CA",
    "sg:tags":[
        "investing"
    ],
    "wof:name":"Royal Pelican",
    "wof:placetype":"venue"
},
  "geometry": {"coordinates":[-118.351997,33.907799],"type":"Point"}
}