{
  "type": "Feature",
  "properties": {
    "addr:full":"411 Silver Spur Rd Rolling Hls Ests CA 90274",
    "addr:housenumber":"411",
    "addr:postcode":"90274",
    "addr:street":"Silver Spur Rd",
    "iso:country":"US",
    "sg:address":"411 Silver Spur Rd",
    "sg:city":"Rolling Hls Ests",
    "sg:classifiers":[
        {
            "category":"Personal",
            "subcategory":"Beauty Salon",
            "type":"Services"
        }
    ],
    "sg:phone":"+1 310 544 4416",
    "sg:postcode":"90274",
    "sg:province":"CA",
    "wof:name":"Fantastic Sam's",
    "wof:placetype":"venue"
},
  "geometry": {"coordinates":[-118.37341600000001,33.773082],"type":"Point"}
}