{
  "type": "Feature",
  "properties": {
    "iso:country":"US",
    "sg:address":"4675 Stevens Creek Blvd",
    "sg:city":"Santa Clara",
    "sg:classifiers":[
        {
            "category":"Professional",
            "type":"Services"
        }
    ],
    "sg:phone":"+1 408 244 6606",
    "sg:postcode":"95051",
    "sg:province":"CA",
    "wof:name":"Xoomsys",
    "wof:placetype":"venue"
},
  "geometry": {"coordinates":[-121.982626,37.323111],"type":"Point"}
}