{
  "type": "Feature",
  "properties": {
    "addr:full":"152 S Brand Blvd Glendale CA 91205",
    "addr:housenumber":"152",
    "addr:postcode":"91205",
    "addr:street":"S Brand Blvd",
    "iso:country":"US",
    "sg:address":"152 S Brand Blvd",
    "sg:city":"Glendale",
    "sg:classifiers":[
        {
            "category":"Restaurant",
            "type":"Food & Drink"
        }
    ],
    "sg:phone":"+1 818 553 3888",
    "sg:postcode":"91205",
    "sg:province":"CA",
    "wof:name":"Pho Citi",
    "wof:placetype":"venue"
},
  "geometry": {"coordinates":[-118.254901,34.144666],"type":"Point"}
}