{
  "type": "Feature",
  "properties": {
    "addr:full":"201 Baker St Bakersfield CA 93305",
    "addr:housenumber":"201",
    "addr:postcode":"93305",
    "addr:street":"Baker St",
    "iso:country":"US",
    "sg:address":"201 Baker St",
    "sg:city":"Bakersfield",
    "sg:classifiers":[
        {
            "category":"Building & Trades",
            "subcategory":"Landscaping Services",
            "type":"Services"
        }
    ],
    "sg:phone":"+1 661 326 1020",
    "sg:postcode":"93305",
    "sg:province":"CA",
    "wof:name":"Gonzales Gardening Service",
    "wof:placetype":"venue"
},
  "geometry": {"coordinates":[-118.995138,35.370576],"type":"Point"}
}