{
  "type": "Feature",
  "properties": {
    "addr:full":"22301 State Rte 107 Torrance CA 90505",
    "addr:housenumber":"22301",
    "addr:postcode":"90505",
    "addr:street":"State Rte 107",
    "iso:country":"US",
    "sg:address":"22301 State Rte 107",
    "sg:city":"Torrance",
    "sg:classifiers":[
        {
            "category":"Shopping",
            "subcategory":"Computers & Home Electronics",
            "type":"Retail Goods"
        }
    ],
    "sg:phone":"+1 310 787 1589",
    "sg:postcode":"90505",
    "sg:province":"CA",
    "wof:name":"Susteen Inc Corporate Office",
    "wof:placetype":"venue"
},
  "geometry": {"coordinates":[-118.35117,33.824704],"type":"Point"}
}