{
  "type": "Feature",
  "properties": {
    "addr:full":"226 S Bedford Dr Beverly Hills CA 90212",
    "addr:housenumber":"226",
    "addr:postcode":"90212",
    "addr:street":"S Bedford Dr",
    "iso:country":"US",
    "sg:address":"226 S Bedford Dr",
    "sg:city":"Beverly Hills",
    "sg:classifiers":[
        {
            "category":"Wholesale",
            "subcategory":"Plants",
            "type":"Manufacturing & Wholesale Goods"
        }
    ],
    "sg:phone":"+1 310 277 3197",
    "sg:postcode":"90212",
    "sg:province":"CA",
    "sg:tags":[
        "florist"
    ],
    "wof:name":"L & K Wholesale Florists Inc",
    "wof:placetype":"venue"
},
  "geometry": {"coordinates":[-118.40445,34.062964],"type":"Point"}
}