{
  "type": "Feature",
  "properties": {
    "iso:country":"US",
    "sg:address":"1 Kaiser Plz Ste 1101",
    "sg:city":"Oakland",
    "sg:classifiers":[
        {
            "category":"Banks & Credit Unions",
            "subcategory":"Investment Brokerage",
            "type":"Services"
        },
        {
            "category":"Insurance",
            "subcategory":"Hazard Insurance",
            "type":"Services"
        }
    ],
    "sg:phone":"+1 510 452 0458",
    "sg:postcode":"94612",
    "sg:province":"CA",
    "sg:tags":[
        "commercial",
        "agent",
        "business",
        "resume"
    ],
    "wof:name":"Sitzmann, Morris & Lavis Insurance Agency, Inc.",
    "wof:placetype":"venue"
},
  "geometry": {"coordinates":[-122.264641,37.809608],"type":"Point"}
}