{
  "type": "Feature",
  "properties": {
    "addr:full":"4841 Meadow Pass Way Antelope CA 95843",
    "addr:housenumber":"4841",
    "addr:postcode":"95843",
    "addr:street":"Meadow Pass Way",
    "iso:country":"US",
    "sg:address":"4841 Meadow Pass Way",
    "sg:city":"Antelope",
    "sg:classifiers":[
        {
            "category":"Shopping",
            "subcategory":"Computers & Home Electronics",
            "type":"Retail Goods"
        }
    ],
    "sg:phone":"+1 916 202 2800",
    "sg:postcode":"95843",
    "sg:province":"CA",
    "wof:name":"Car Stereo Superstore",
    "wof:placetype":"venue"
},
  "geometry": {"coordinates":[-121.349574,38.722689],"type":"Point"}
}