{
  "type": "Feature",
  "properties": {
    "iso:country":"US",
    "sg:address":"16112 Sweetleaf St",
    "sg:city":"Fountain Valley",
    "sg:classifiers":[
        {
            "category":"Real Estate",
            "subcategory":"Real Estate Operator",
            "type":"Services"
        }
    ],
    "sg:phone":"+1 714 839 6741",
    "sg:postcode":"92708",
    "sg:province":"CA",
    "sg:tags":[
        "building",
        "nonresidential"
    ],
    "wof:name":"Dang Properties",
    "wof:placetype":"venue"
},
  "geometry": {"coordinates":[-117.967102,33.728958],"type":"Point"}
}