{
  "type": "Feature",
  "properties": {
    "iso:country":"US",
    "sg:address":"1015 Sunrise Ave",
    "sg:city":"Roseville",
    "sg:classifiers":[
        {
            "category":"Travel",
            "subcategory":"Travel Agent",
            "type":"Entertainment"
        }
    ],
    "sg:phone":"+1 916 786 2772",
    "sg:postcode":"95661",
    "sg:province":"CA",
    "sg:tags":[
        "passenger",
        "transportation",
        "arrangement"
    ],
    "wof:name":"Patterson Travel-American Ex",
    "wof:placetype":"venue"
},
  "geometry": {"coordinates":[-121.271994,38.727322],"type":"Point"}
}