{
  "type": "Feature",
  "properties": {
    "iso:country":"US",
    "sg:address":"28715 Los Alisos Blvd",
    "sg:city":"Mission Viejo",
    "sg:classifiers":[
        {
            "category":"Building & Trades",
            "subcategory":"Construction",
            "type":"Services"
        }
    ],
    "sg:phone":"+1 949 284 4036",
    "sg:postcode":"92692",
    "sg:province":"CA",
    "sg:tags":[
        "air",
        "heating",
        "conditioning/hvac"
    ],
    "sg:website":"www.missionviejoairconditioning.net",
    "wof:name":"Mission Viejo Air Conditioning",
    "wof:placetype":"venue"
},
  "geometry": {"coordinates":[-117.629898,33.655173],"type":"Point"}
}