{
  "type": "Feature",
  "properties": {
    "iso:country":"US",
    "sg:address":"13055 Poway Rd",
    "sg:city":"Poway",
    "sg:classifiers":[
        {
            "category":"Banks & Credit Unions",
            "subcategory":"Bank",
            "type":"Services"
        }
    ],
    "sg:phone":"+1 858 748 9894",
    "sg:postcode":"92064",
    "sg:province":"CA",
    "sg:tags":[
        "loan",
        "real estate"
    ],
    "wof:name":"Belcan Mortgage",
    "wof:placetype":"venue"
},
  "geometry": {"coordinates":[-117.049124,32.956475],"type":"Point"}
}