{
  "type": "Feature",
  "properties": {
    "addr:full":"13055 Poway Rd Poway CA 92064",
    "addr:housenumber":"13055",
    "addr:postcode":"ca 92064",
    "addr:street":"Poway Rd",
    "iso:country":"US",
    "sg:address":"13055 Poway Rd",
    "sg:city":"Poway",
    "sg:classifiers":[
        {
            "category":"Banks & Credit Unions",
            "subcategory":"Bank",
            "type":"Services"
        }
    ],
    "sg:phone":"+1 858 748 9894",
    "sg:postcode":"92064",
    "sg:province":"CA",
    "sg:tags":[
        "loan",
        "real estate"
    ],
    "wof:name":"Belcan Mortgage",
    "wof:placetype":"venue"
},
  "geometry": {"coordinates":[-117.04912400000001,32.956475],"type":"Point"}
}