{
  "type": "Feature",
  "properties": {
    "addr:full":"448 Valley View Rd El Sobrante CA 94803",
    "addr:housenumber":"448",
    "addr:postcode":"94803",
    "addr:street":"Valley View Rd",
    "iso:country":"US",
    "sg:address":"448 Valley View Rd",
    "sg:city":"El Sobrante",
    "sg:classifiers":[
        {
            "category":"Sports & Exercise",
            "subcategory":"Gym",
            "type":"Entertainment"
        }
    ],
    "sg:phone":"+1 510 222 4845",
    "sg:postcode":"94803",
    "sg:province":"CA",
    "sg:tags":[
        "club",
        "health",
        "studio",
        "gymnasium"
    ],
    "wof:name":"Image Health & Wellness",
    "wof:placetype":"venue"
},
  "geometry": {"coordinates":[-122.293756,37.977797],"type":"Point"}
}