{
  "type": "Feature",
  "properties": {
    "addr:full":"117 N E St Madera CA 93638",
    "addr:housenumber":"117",
    "addr:postcode":"93638",
    "addr:street":"N E St",
    "iso:country":"US",
    "sg:address":"117 N E St",
    "sg:city":"Madera",
    "sg:classifiers":[
        {
            "category":"Organizations",
            "subcategory":"Religious Organization",
            "type":"Services"
        }
    ],
    "sg:phone":"+1 559 661 1411",
    "sg:postcode":"93638",
    "sg:province":"CA",
    "sg:tags":[
        "church"
    ],
    "wof:name":"Believers Church Of Madera",
    "wof:placetype":"venue"
},
  "geometry": {"coordinates":[-120.060316,36.962737],"type":"Point"}
}