{
  "type": "Feature",
  "properties": {
    "addr:full":"1209 Dakota Ave San Mateo CA 94401",
    "addr:housenumber":"1209",
    "addr:postcode":"94401",
    "addr:street":"Dakota Ave",
    "iso:country":"US",
    "sg:address":"1209 Dakota Ave",
    "sg:city":"San Mateo",
    "sg:classifiers":[
        {
            "category":"Social Services",
            "subcategory":"Adult Care",
            "type":"Services"
        }
    ],
    "sg:phone":"+1 650 401 6196",
    "sg:postcode":"94401",
    "sg:province":"CA",
    "sg:tags":[
        "home",
        "residential"
    ],
    "wof:name":"American Star Homes",
    "wof:placetype":"venue"
},
  "geometry": {"coordinates":[-122.310695,37.569048],"type":"Point"}
}