{
  "type": "Feature",
  "properties": {
    "iso:country":"US",
    "sg:address":"15590 Hesperian Blvd",
    "sg:city":"San Lorenzo",
    "sg:classifiers":[
        {
            "category":"Shopping",
            "subcategory":"Music",
            "type":"Retail Goods"
        }
    ],
    "sg:phone":"+1 800 350 8700",
    "sg:postcode":"94580",
    "sg:province":"CA",
    "sg:tags":[
        "dvd's"
    ],
    "sg:website":"rasputinmusic.com",
    "wof:name":"Rasputin Music",
    "wof:placetype":"venue"
},
  "geometry": {"coordinates":[-122.129997,37.687],"type":"Point"}
}