{
  "type": "Feature",
  "properties": {
    "addr:full":"340 Lakewood Center Mall Lakewood CA 90712",
    "addr:housenumber":"340",
    "addr:postcode":"90712",
    "addr:street":"Lakewood;Mall",
    "iso:country":"US",
    "sg:address":"340 Lakewood Center Mall",
    "sg:city":"Lakewood",
    "sg:classifiers":[
        {
            "category":"Health Services",
            "subcategory":"Optometrist",
            "type":"Services"
        }
    ],
    "sg:phone":"+1 562 602 6100",
    "sg:postcode":"90712",
    "sg:province":"CA",
    "wof:name":"Greg Pearl & Associates",
    "wof:placetype":"venue"
},
  "geometry": {"coordinates":[-118.137829,33.85211],"type":"Point"}
}