{
  "type": "Feature",
  "properties": {
    "addr:full":"1700 Danbury Rd Claremont CA 91711",
    "addr:housenumber":"1700",
    "addr:postcode":"91711",
    "addr:street":"Danbury Rd",
    "iso:country":"US",
    "sg:address":"1700 Danbury Rd",
    "sg:city":"Claremont",
    "sg:classifiers":[
        {
            "category":"Government",
            "subcategory":"Office",
            "type":"Public Place"
        }
    ],
    "sg:phone":"+1 909 399 5490",
    "sg:postcode":"91711",
    "sg:province":"CA",
    "sg:tags":[
        "city",
        "resource",
        "human"
    ],
    "wof:name":"Claremont Human Svc Dept",
    "wof:placetype":"venue"
},
  "geometry": {"coordinates":[-117.733796,34.115614],"type":"Point"}
}