{
  "type": "Feature",
  "properties": {
    "addr:full":"3400 16th St San Francisco CA 94114",
    "addr:housenumber":"3400",
    "addr:postcode":"94114",
    "addr:street":"16Th St",
    "iso:country":"US",
    "sg:address":"3400 16th St",
    "sg:city":"San Francisco",
    "sg:classifiers":[
        {
            "category":"Real Estate",
            "subcategory":"Real Estate Operator",
            "type":"Services"
        }
    ],
    "sg:phone":"+1 415 621 4454",
    "sg:postcode":"94114",
    "sg:province":"CA",
    "sg:tags":[
        "apartment"
    ],
    "wof:name":"Padre Palou Community",
    "wof:placetype":"venue"
},
  "geometry": {"coordinates":[-122.429428,37.764461],"type":"Point"}
}