{
  "type": "Feature",
  "properties": {
    "iso:country":"US",
    "sg:address":"304 Sutton Pl",
    "sg:city":"Santa Rosa",
    "sg:classifiers":[
        {
            "category":"Banks & Credit Unions",
            "subcategory":"Bank",
            "type":"Services"
        }
    ],
    "sg:phone":"+1 707 584 0384",
    "sg:postcode":"95407",
    "sg:province":"CA",
    "wof:name":"Sonoma County Grange CU",
    "wof:placetype":"venue"
},
  "geometry": {"coordinates":[-122.724763,38.390821],"type":"Point"}
}