{
  "type": "Feature",
  "properties": {
    "iso:country":"US",
    "sg:address":"462 Mendocino Ave",
    "sg:city":"Santa Rosa",
    "sg:classifiers":[
        {
            "category":"Shopping",
            "subcategory":"Gifts & Souvenirs",
            "type":"Retail Goods"
        }
    ],
    "sg:phone":"+1 707 544 4493",
    "sg:postcode":"95401",
    "sg:province":"CA",
    "sg:tags":[
        "collectible"
    ],
    "sg:website":"www.thetoytrader.com",
    "wof:name":"Toy Trader",
    "wof:placetype":"venue"
},
  "geometry": {"coordinates":[-122.71558400000001,38.442739],"type":"Point"}
}