{
  "type": "Feature",
  "properties": {
    "iso:country":"US",
    "sg:address":"644 Westchester Dr",
    "sg:city":"Folsom",
    "sg:classifiers":[
        {
            "category":"Building & Trades",
            "subcategory":"Plumbing",
            "type":"Services"
        }
    ],
    "sg:phone":"+1 916 371 1920",
    "sg:postcode":"95630",
    "sg:province":"CA",
    "sg:tags":[
        "conditioning",
        "air",
        "system",
        "contractor"
    ],
    "wof:name":"Knoll Systems Corp",
    "wof:placetype":"venue"
},
  "geometry": {"coordinates":[-121.112578,38.662138],"type":"Point"}
}