{
  "type": "Feature",
  "properties": {
    "iso:country":"US",
    "sg:address":"18430 Ventura Blvd",
    "sg:city":"Tarzana",
    "sg:classifiers":[
        {
            "category":"Retail",
            "subcategory":"Animal Services",
            "type":"Services"
        }
    ],
    "sg:phone":"+1 818 705 7476",
    "sg:postcode":"91356",
    "sg:province":"CA",
    "wof:name":"Barking Lot",
    "wof:placetype":"venue"
},
  "geometry": {"coordinates":[-118.534797,34.168142],"type":"Point"}
}