{
  "type": "Feature",
  "properties": {
    "addr:full":"16015 Phoenix Dr City Of Industry CA 91745",
    "addr:housenumber":"16015",
    "addr:postcode":"91745",
    "addr:street":"Phoenix Dr",
    "iso:country":"US",
    "sg:address":"16015 Phoenix Dr",
    "sg:city":"City Of Industry",
    "sg:classifiers":[
        {
            "category":"Manufacturing",
            "subcategory":"Food",
            "type":"Manufacturing & Wholesale Goods"
        },
        {
            "category":"Wholesale",
            "subcategory":"Meat",
            "type":"Manufacturing & Wholesale Goods"
        }
    ],
    "sg:phone":"+1 626 333 8812",
    "sg:postcode":"91745",
    "sg:province":"CA",
    "sg:tags":[
        "poultry",
        "product",
        "manufacturer"
    ],
    "wof:name":"Leyen Foods Inc",
    "wof:placetype":"venue"
},
  "geometry": {"coordinates":[-117.955438,34.011184],"type":"Point"}
}