{
  "type": "Feature",
  "properties": {
    "addr:full":"110 1st St Los Altos CA 94022",
    "addr:housenumber":"110",
    "addr:postcode":"94022",
    "addr:street":"1St St",
    "iso:country":"US",
    "sg:address":"110 1st St",
    "sg:city":"Los Altos",
    "sg:classifiers":[
        {
            "category":"Real Estate",
            "subcategory":"Real Estate Agent",
            "type":"Services"
        }
    ],
    "sg:phone":"+1 650 948 0456",
    "sg:postcode":"94022",
    "sg:province":"CA",
    "sg:website":"www.californiamoves.com",
    "wof:name":"Coldwell Banker",
    "wof:placetype":"venue"
},
  "geometry": {"coordinates":[-122.1183,37.378479],"type":"Point"}
}