{
  "type": "Feature",
  "properties": {
    "addr:full":"169 W Java Dr Sunnyvale CA 94089",
    "addr:housenumber":"169",
    "addr:postcode":"94089",
    "addr:street":"W Java Dr",
    "iso:country":"US",
    "sg:address":"169 W Java Dr",
    "sg:city":"Sunnyvale",
    "sg:classifiers":[
        {
            "category":"Manufacturing",
            "subcategory":"Electronics",
            "type":"Manufacturing & Wholesale Goods"
        }
    ],
    "sg:phone":"+1 408 744 1800",
    "sg:postcode":"94089",
    "sg:province":"CA",
    "sg:tags":[
        "engineering",
        "devices",
        "mfg"
    ],
    "wof:name":"Flextronics Semiconductor Inc",
    "wof:placetype":"venue"
},
  "geometry": {"coordinates":[-122.019655,37.41222],"type":"Point"}
}