{
  "type": "Feature",
  "properties": {
    "addr:full":"575 Arastradero Rd Palo Alto CA 94306",
    "addr:housenumber":"575",
    "addr:postcode":"94306",
    "addr:street":"Arastradero Rd",
    "iso:country":"US",
    "sg:address":"575 Arastradero Rd",
    "sg:city":"Palo Alto",
    "sg:classifiers":[
        {
            "category":"Banks & Credit Unions",
            "subcategory":"Bank",
            "type":"Services"
        }
    ],
    "sg:phone":"+1 650 424 1637",
    "sg:postcode":"94306",
    "sg:province":"CA",
    "sg:tags":[
        "loan",
        "real estate"
    ],
    "sg:website":"www.opesventures.com",
    "wof:name":"Opes Ventures",
    "wof:placetype":"venue"
},
  "geometry": {"coordinates":[-122.124911,37.408021],"type":"Point"}
}