{
  "type": "Feature",
  "properties": {
    "addr:full":"1201 N Pershing Ave Stockton CA 95203",
    "addr:housenumber":"1201",
    "addr:postcode":"95203",
    "addr:street":"N Pershing Ave",
    "iso:country":"US",
    "sg:address":"1201 N Pershing Ave",
    "sg:city":"Stockton",
    "sg:classifiers":[
        {
            "category":"Education",
            "subcategory":"Library",
            "type":"Public Place"
        }
    ],
    "sg:phone":"+1 209 462 4116",
    "sg:postcode":"95203",
    "sg:province":"CA",
    "sg:tags":[
        "special",
        "interest"
    ],
    "wof:name":"Petzinger Library Of Ca",
    "wof:placetype":"venue"
},
  "geometry": {"coordinates":[-121.312681,37.961745],"type":"Point"}
}