{
  "type": "Feature",
  "properties": {
    "addr:full":"1327 S Juanita St San Jacinto CA 92583",
    "addr:housenumber":"1327",
    "addr:postcode":"92583",
    "addr:street":"S Juanita St",
    "iso:country":"US",
    "sg:address":"1327 S Juanita St",
    "sg:city":"San Jacinto",
    "sg:classifiers":[
        {
            "category":"Retail",
            "subcategory":"Auto Repair",
            "type":"Services"
        }
    ],
    "sg:phone":"+1 951 654 9461",
    "sg:postcode":"92583",
    "sg:province":"CA",
    "sg:tags":[
        "body",
        "automobile",
        "painting"
    ],
    "wof:name":"Valley Foreign Auto Body",
    "wof:placetype":"venue"
},
  "geometry": {"coordinates":[-116.968521,33.769526],"type":"Point"}
}