{
  "type": "Feature",
  "properties": {
    "addr:full":"3202 E Foothill Blvd Pasadena CA 91107",
    "addr:housenumber":"3202",
    "addr:postcode":"91107",
    "addr:street":"E Foothill Blvd",
    "iso:country":"US",
    "sg:address":"3202 E Foothill Blvd",
    "sg:city":"Pasadena",
    "sg:classifiers":[
        {
            "category":"Autos & Motor Vehicles",
            "subcategory":"Automobile Sales",
            "type":"Retail Goods"
        },
        {
            "category":"Retail",
            "subcategory":"Auto Rental",
            "type":"Services"
        },
        {
            "category":"Building & Trades",
            "subcategory":"Equipment Rental",
            "type":"Services"
        }
    ],
    "sg:phone":"+1 626 792 1740",
    "sg:postcode":"91107",
    "sg:province":"CA",
    "sg:tags":[
        "truck",
        "used",
        "moving"
    ],
    "sg:website":"http://budgettruck.com/IYP_tl",
    "wof:name":"Shamos Truck Rental DBA/Budget Truck Rental",
    "wof:placetype":"venue"
},
  "geometry": {"coordinates":[-118.08425699999999,34.150054],"type":"Point"}
}