{
  "type": "Feature",
  "properties": {
    "addr:full":"18141 Beach Blvd Suite 320 Huntington Beach CA 92648",
    "addr:housenumber":"18141",
    "addr:postcode":"92648",
    "addr:street":"Beach Blvd Suite 320",
    "iso:country":"US",
    "sg:address":"18141 Beach Blvd Suite 320",
    "sg:city":"Huntington Beach",
    "sg:classifiers":[
        {
            "category":"Health Services",
            "subcategory":"Health Practitioner",
            "type":"Services"
        },
        {
            "category":"Health Services",
            "subcategory":"Chiropractor",
            "type":"Services"
        }
    ],
    "sg:phone":"+1 714 375 0313",
    "sg:postcode":"92648",
    "sg:province":"CA",
    "sg:tags":[
        "acupuncture"
    ],
    "sg:website":"www.optimumcentre.com",
    "wof:name":"Optimum Health & Wellness Centre",
    "wof:placetype":"venue"
},
  "geometry": {"coordinates":[-117.990284,33.699014],"type":"Point"}
}