{
  "type": "Feature",
  "properties": {
    "iso:country":"US",
    "sg:address":"13701 Riverside Dr",
    "sg:city":"Sherman Oaks",
    "sg:classifiers":[
        {
            "category":"Health Services",
            "subcategory":"Doctor",
            "type":"Services"
        },
        {
            "category":"Health Services",
            "subcategory":"Clinic",
            "type":"Services"
        }
    ],
    "sg:phone":"+1 818 788 7580",
    "sg:postcode":"91423",
    "sg:province":"CA",
    "sg:tags":[
        "counseling",
        "mental"
    ],
    "wof:name":"Korchmarev Alex MD",
    "wof:placetype":"venue"
},
  "geometry": {"coordinates":[-118.431,34.1576],"type":"Point"}
}