{
  "type": "Feature",
  "properties": {
    "addr:full":"15858 Monterey St Morgan Hill CA 95037",
    "addr:housenumber":"15858",
    "addr:postcode":"95037",
    "addr:street":"Monterey St",
    "iso:country":"US",
    "sg:address":"15858 Monterey St",
    "sg:city":"Morgan Hill",
    "sg:classifiers":[
        {
            "category":"Professional",
            "type":"Services"
        }
    ],
    "sg:phone":"+1 408 778 8226",
    "sg:postcode":"95037",
    "sg:province":"CA",
    "sg:tags":[
        "establishment"
    ],
    "wof:name":"Young's Togo",
    "wof:placetype":"venue"
},
  "geometry": {"coordinates":[-121.641148,37.111355],"type":"Point"}
}