{
  "type": "Feature",
  "properties": {
    "iso:country":"US",
    "sg:address":"16640 Bellflower Blvd",
    "sg:city":"Bellflower",
    "sg:classifiers":[
        {
            "category":"Shopping",
            "subcategory":"Beauty & Cosmetics",
            "type":"Retail Goods"
        }
    ],
    "sg:phone":"+1 562 461 2972",
    "sg:postcode":"90706",
    "sg:province":"CA",
    "sg:tags":[
        "supply"
    ],
    "wof:name":"Salon Equipment Internatl",
    "wof:placetype":"venue"
},
  "geometry": {"coordinates":[-118.125,33.883202],"type":"Point"}
}