{
  "type": "Feature",
  "properties": {
    "iso:country":"US",
    "sg:address":"1041 Grand Ave",
    "sg:city":"San Marcos",
    "sg:classifiers":[
        {
            "category":"Wholesale",
            "subcategory":"Electrical",
            "type":"Manufacturing & Wholesale Goods"
        }
    ],
    "sg:phone":"+1 760 744 9646",
    "sg:postcode":"92069",
    "sg:province":"CA",
    "sg:tags":[
        "electric",
        "motor"
    ],
    "wof:name":"California Air Compressor Co N",
    "wof:placetype":"venue"
},
  "geometry": {"coordinates":[-117.187432,33.141337],"type":"Point"}
}