{
  "type": "Feature",
  "properties": {
    "addr:full":"2356 Sutter St. 7th Fl San Francisco CA 94115",
    "addr:housenumber":"2356",
    "addr:postcode":"94115",
    "addr:street":"Sutter St.",
    "iso:country":"US",
    "sg:address":"2356 Sutter St. 7th Fl",
    "sg:city":"San Francisco",
    "sg:classifiers":[
        {
            "category":"Health Services",
            "subcategory":"Doctor",
            "type":"Services"
        }
    ],
    "sg:phone":"+1 415 353 7475",
    "sg:postcode":"94115",
    "sg:province":"CA",
    "sg:website":"www.ucsfivf.org",
    "wof:name":"UCSF Center For Reproductive Health",
    "wof:placetype":"venue"
},
  "geometry": {"coordinates":[-122.43933199999999,37.785794],"type":"Point"}
}