{
  "type": "Feature",
  "properties": {
    "iso:country":"US",
    "sg:address":"5277 Vincent Ave",
    "sg:city":"Baldwin Park",
    "sg:classifiers":[
        {
            "category":"Wholesale",
            "subcategory":"Medical Equipment & Supplies",
            "type":"Manufacturing & Wholesale Goods"
        }
    ],
    "sg:phone":"+1 626 812 9850",
    "sg:postcode":"91706",
    "sg:province":"CA",
    "sg:tags":[
        "physician",
        "surgeon"
    ],
    "wof:name":"Bedan Medical Supls & Eqpt Inc",
    "wof:placetype":"venue"
},
  "geometry": {"coordinates":[-117.925414,34.10874],"type":"Point"}
}