{
  "type": "Feature",
  "properties": {
    "addr:full":"3597 Shadow Grove Rd Pasadena CA 91107",
    "addr:housenumber":"3597",
    "addr:postcode":"91107",
    "addr:street":"Shadow Grove Rd",
    "iso:country":"US",
    "sg:address":"3597 Shadow Grove Rd",
    "sg:city":"Pasadena",
    "sg:classifiers":[
        {
            "category":"Professional",
            "subcategory":"Business Services",
            "type":"Services"
        }
    ],
    "sg:phone":"+1 626 351 7400",
    "sg:postcode":"91107",
    "sg:province":"CA",
    "sg:tags":[
        "bus"
    ],
    "wof:name":"Quality Cleaning Service",
    "wof:placetype":"venue"
},
  "geometry": {"coordinates":[-118.07509899999999,34.157902],"type":"Point"}
}