{
  "type": "Feature",
  "properties": {
    "addr:full":"17216 Saticoy St Van Nuys CA 91406",
    "addr:housenumber":"17216",
    "addr:postcode":"91406",
    "addr:street":"Saticoy St",
    "iso:country":"US",
    "sg:address":"17216 Saticoy St",
    "sg:city":"Van Nuys",
    "sg:classifiers":[
        {
            "category":"Recreation",
            "type":"Entertainment"
        }
    ],
    "sg:phone":"+1 818 345 5155",
    "sg:postcode":"91406",
    "sg:province":"CA",
    "sg:tags":[
        "club",
        "membership"
    ],
    "wof:name":"Valley Raiders Track Club",
    "wof:placetype":"venue"
},
  "geometry": {"coordinates":[-118.507749,34.208339],"type":"Point"}
}