{
  "type": "Feature",
  "properties": {
    "addr:full":"1569 Fairway Dr Walnut CA 91789",
    "addr:housenumber":"1569",
    "addr:postcode":"91789",
    "addr:street":"Fairway Dr",
    "iso:country":"US",
    "sg:address":"1569 Fairway Dr",
    "sg:city":"Walnut",
    "sg:classifiers":[
        {
            "category":"Personal",
            "subcategory":"Beauty Salon",
            "type":"Services"
        }
    ],
    "sg:phone":"+1 909 594 8282",
    "sg:postcode":"91789",
    "sg:province":"CA",
    "wof:name":"Beverly Hills Salon",
    "wof:placetype":"venue"
},
  "geometry": {"coordinates":[-117.86998199999999,33.987147],"type":"Point"}
}