{
  "type": "Feature",
  "properties": {
    "addr:full":"1962 N Glassell St Orange CA 92865",
    "addr:housenumber":"1962",
    "addr:postcode":"92865",
    "addr:street":"N Glassell St",
    "iso:country":"US",
    "sg:address":"1962 N Glassell St",
    "sg:city":"Orange",
    "sg:classifiers":[
        {
            "category":"Retail",
            "subcategory":"Auto Repair",
            "type":"Services"
        }
    ],
    "sg:phone":"+1 714 974 4949",
    "sg:postcode":"92865",
    "sg:province":"CA",
    "sg:tags":[
        "engine",
        "diesel",
        "parts",
        "truck"
    ],
    "wof:name":"Ricks Truck Works",
    "wof:placetype":"venue"
},
  "geometry": {"coordinates":[-117.853335,33.81939],"type":"Point"}
}