{
  "type": "Feature",
  "properties": {
    "iso:country":"US",
    "sg:address":"2024 S Central Ave",
    "sg:city":"Los Angeles",
    "sg:classifiers":[
        {
            "category":"Shopping",
            "subcategory":"Clothing, Apparel, & Fashions",
            "type":"Retail Goods"
        }
    ],
    "sg:phone":"+1 213 741 0291",
    "sg:postcode":"90011",
    "sg:province":"CA",
    "sg:tags":[
        "shop",
        "bridal"
    ],
    "wof:name":"Avi's Bridal Shop",
    "wof:placetype":"venue"
},
  "geometry": {"coordinates":[-118.252309,34.022416],"type":"Point"}
}