{
  "type": "Feature",
  "properties": {
    "addr:full":"1989 Old Hernandez Rd Paicines CA 95043",
    "addr:housenumber":"1989",
    "addr:postcode":"paicines ca 95043",
    "addr:street":"Old Hernandez Rd",
    "iso:country":"US",
    "sg:address":"1989 Old Hernandez Rd",
    "sg:city":"Paicines",
    "sg:classifiers":[
        {
            "category":"Farming",
            "subcategory":"Livestock Farm",
            "type":"Manufacturing & Wholesale Goods"
        }
    ],
    "sg:phone":"+1 831 389 4392",
    "sg:postcode":"95043",
    "sg:province":"CA",
    "sg:tags":[
        "ranch"
    ],
    "wof:name":"J & L Ranch",
    "wof:placetype":"venue"
},
  "geometry": {"coordinates":[-121.05207900000001,36.508139],"type":"Point"}
}