{
  "type": "Feature",
  "properties": {
    "addr:full":"986 Walsh Ave Santa Clara CA 95050",
    "addr:housenumber":"986",
    "addr:postcode":"95050",
    "addr:street":"Walsh Ave",
    "iso:country":"US",
    "sg:address":"986 Walsh Ave",
    "sg:city":"Santa Clara",
    "sg:classifiers":[
        {
            "category":"Shopping",
            "subcategory":"Mobile Phones",
            "type":"Retail Goods"
        }
    ],
    "sg:phone":"+1 408 748 9522",
    "sg:postcode":"95050",
    "sg:province":"CA",
    "wof:name":"Sprint",
    "wof:placetype":"venue"
},
  "geometry": {"coordinates":[-121.952935,37.369656],"type":"Point"}
}