{
  "type": "Feature",
  "properties": {
    "iso:country":"US",
    "sg:address":"8501 Reseda Blvd",
    "sg:city":"Northridge",
    "sg:classifiers":[
        {
            "category":"Restaurant",
            "type":"Food & Drink"
        }
    ],
    "sg:phone":"+1 818 885 8916",
    "sg:postcode":"91324",
    "sg:province":"CA",
    "wof:name":"L A Lasagna Co",
    "wof:placetype":"venue"
},
  "geometry": {"coordinates":[-118.53608,34.225514],"type":"Point"}
}