{
  "type": "Feature",
  "properties": {
    "addr:full":"2015 Edgewood Drive Palo Alto CA 94303",
    "addr:housenumber":"2015",
    "addr:postcode":"94303",
    "addr:street":"Edgewood Drive",
    "iso:country":"US",
    "sg:address":"2015 Edgewood Drive",
    "sg:city":"Palo Alto",
    "sg:classifiers":[
        {
            "category":"Professional",
            "subcategory":"Computer Services",
            "type":"Services"
        }
    ],
    "sg:postcode":"94303",
    "sg:province":"CA",
    "sg:tags":[
        "startup",
        "founder",
        "hacker",
        "events",
        "technology",
        "media",
        "entrepreneurship",
        "jobs",
        "tech",
        "news",
        "curated"
    ],
    "sg:website":"http://www.startupdigest.com",
    "wof:name":"StartupDigest",
    "wof:placetype":"venue"
},
  "geometry": {"coordinates":[-122.12812099999999,37.451391],"type":"Point"}
}