{
  "type": "Feature",
  "properties": {
    "addr:full":"7023 Pacific Blvd Huntington Park CA 90255",
    "addr:housenumber":"7023",
    "addr:postcode":"90255",
    "addr:street":"Pacific Blvd;Park",
    "iso:country":"US",
    "sg:address":"7023 Pacific Blvd",
    "sg:city":"Huntington Park",
    "sg:classifiers":[
        {
            "category":"Real Estate",
            "subcategory":"Real Estate Agent",
            "type":"Services"
        }
    ],
    "sg:phone":"+1 323 585 7537",
    "sg:postcode":"90255",
    "sg:province":"CA",
    "wof:name":"Pacific",
    "wof:placetype":"venue"
},
  "geometry": {"coordinates":[-118.225255,33.975308],"type":"Point"}
}