{
  "type": "Feature",
  "properties": {
    "iso:country":"US",
    "sg:address":"4 N Euclid Ave",
    "sg:city":"National City",
    "sg:classifiers":[
        {
            "category":"Manufacturing",
            "subcategory":"Motor Vehicles & Parts",
            "type":"Manufacturing & Wholesale Goods"
        }
    ],
    "sg:phone":"+1 619 327 0899",
    "sg:postcode":"91950",
    "sg:province":"CA",
    "sg:tags":[
        "bearing"
    ],
    "wof:name":"Gold Comb Hair Gallery",
    "wof:placetype":"venue"
},
  "geometry": {"coordinates":[-117.085213,32.690911],"type":"Point"}
}