{
  "type": "Feature",
  "properties": {
    "addr:full":"535 Pajaro Ct Sacramento CA 95864",
    "addr:housenumber":"535",
    "addr:postcode":"95864",
    "addr:street":"Pajaro Ct",
    "iso:country":"US",
    "sg:address":"535 Pajaro Ct",
    "sg:city":"Sacramento",
    "sg:classifiers":[
        {
            "category":"Real Estate",
            "subcategory":"Real Estate Agent",
            "type":"Services"
        }
    ],
    "sg:phone":"+1 916 974 3460",
    "sg:postcode":"95864",
    "sg:province":"CA",
    "sg:tags":[
        "appraising",
        "consultation",
        "appraiser"
    ],
    "wof:name":"Thomas Clark Company Inc",
    "wof:placetype":"venue"
},
  "geometry": {"coordinates":[-121.37655100000001,38.575326],"type":"Point"}
}