{
  "type": "Feature",
  "properties": {
    "iso:country":"US",
    "sg:address":"2000 E 3rd Ave",
    "sg:city":"Foster City",
    "sg:classifiers":[
        {
            "category":"Home & Garden",
            "subcategory":"Carpets & Floor Coverings",
            "type":"Retail Goods"
        }
    ],
    "sg:phone":"+1 650 591 3822",
    "sg:postcode":"94404",
    "sg:province":"CA",
    "sg:tags":[
        "dealer",
        "rug"
    ],
    "wof:name":"Access Floor & Window Covering",
    "wof:placetype":"venue"
},
  "geometry": {"coordinates":[-122.28949,37.570478],"type":"Point"}
}