{
  "type": "Feature",
  "properties": {
    "iso:country":"US",
    "sg:address":"6450 20th Street",
    "sg:city":"Rio Linda",
    "sg:classifiers":[
        {
            "category":"Education",
            "subcategory":"School",
            "type":"Public Place"
        }
    ],
    "sg:phone":"+1 916 992 9033",
    "sg:postcode":"95673",
    "sg:province":"CA",
    "sg:tags":[
        "high",
        "middle",
        "elementary"
    ],
    "wof:name":"Heritage Peak Charter School",
    "wof:placetype":"venue"
},
  "geometry": {"coordinates":[-121.419872,38.683502],"type":"Point"}
}