{
  "type": "Feature",
  "properties": {
    "iso:country":"US",
    "sg:address":"555 Oakdale St",
    "sg:city":"Folsom",
    "sg:classifiers":[
        {
            "category":"Health Services",
            "subcategory":"Health Practitioner",
            "type":"Services"
        }
    ],
    "sg:phone":"+1 916 396 7415",
    "sg:postcode":"95630",
    "sg:province":"CA",
    "sg:tags":[
        "therapist",
        "physical"
    ],
    "wof:name":"Peak Sports Medicine & Phys",
    "wof:placetype":"venue"
},
  "geometry": {"coordinates":[-121.18123300000001,38.672307],"type":"Point"}
}