{
  "type": "Feature",
  "properties": {
    "iso:country":"US",
    "sg:address":"130 Calle Magdalena",
    "sg:city":"Encinitas",
    "sg:classifiers":[
        {
            "category":"Fast Food",
            "type":"Food & Drink"
        },
        {
            "category":"Restaurant",
            "type":"Food & Drink"
        }
    ],
    "sg:phone":"+1 760 753 5119",
    "sg:postcode":"92024",
    "sg:province":"CA",
    "sg:tags":[
        "tex-mex"
    ],
    "sg:website":"www.deltaco.com",
    "wof:name":"Del Taco",
    "wof:placetype":"venue"
},
  "geometry": {"coordinates":[-117.285004,33.047901],"type":"Point"}
}