{
  "type": "Feature",
  "properties": {
    "iso:country":"US",
    "sg:address":"67 E Live Oak Ave",
    "sg:city":"Arcadia",
    "sg:classifiers":[
        {
            "category":"Wholesale",
            "subcategory":"Non-durable Goods",
            "type":"Manufacturing & Wholesale Goods"
        }
    ],
    "sg:phone":"+1 626 446 5607",
    "sg:postcode":"91006",
    "sg:province":"CA",
    "wof:name":"S E C C USA Corp",
    "wof:placetype":"venue"
},
  "geometry": {"coordinates":[-118.027693,34.10783],"type":"Point"}
}