{
  "type": "Feature",
  "properties": {
    "iso:country":"US",
    "sg:address":"1701 S Elena Ave",
    "sg:city":"Redondo Beach",
    "sg:classifiers":[
        {
            "category":"Banks & Credit Unions",
            "subcategory":"Bank",
            "type":"Services"
        }
    ],
    "sg:phone":"+1 310 540 0043",
    "sg:postcode":"90277",
    "sg:province":"CA",
    "sg:website":"www.wellsfargo.com",
    "wof:name":"Wells Fargo Bank",
    "wof:placetype":"venue"
},
  "geometry": {"coordinates":[-118.38544400000001,33.818036],"type":"Point"}
}