{
  "type": "Feature",
  "properties": {
    "iso:country":"US",
    "sg:address":"223 Main St",
    "sg:city":"Huntington Beach",
    "sg:classifiers":[
        {
            "category":"Communications",
            "subcategory":"Television Station",
            "type":"Services"
        }
    ],
    "sg:phone":"+1 714 274 7435",
    "sg:postcode":"92648",
    "sg:province":"CA",
    "sg:tags":[
        "provider"
    ],
    "sg:website":"www.dishnetwork.com",
    "wof:name":"Dish Network",
    "wof:placetype":"venue"
},
  "geometry": {"coordinates":[-118.00037500000001,33.658759],"type":"Point"}
}