{
  "type": "Feature",
  "properties": {
    "iso:country":"US",
    "sg:address":"3190 S Bascom Ave Ste 150",
    "sg:city":"San Jose",
    "sg:classifiers":[
        {
            "category":"Health Services",
            "subcategory":"Doctor",
            "type":"Services"
        }
    ],
    "sg:phone":"+1 408 377 9877",
    "sg:postcode":"95124",
    "sg:province":"CA",
    "wof:name":"Medical Dimensions Inc",
    "wof:placetype":"venue"
},
  "geometry": {"coordinates":[-121.941002,37.265598],"type":"Point"}
}