{
  "type": "Feature",
  "properties": {
    "addr:full":"12728 Julian Ave Lakeside CA 92040",
    "addr:housenumber":"12728",
    "addr:postcode":"92040",
    "addr:street":"Julian Ave",
    "iso:country":"US",
    "sg:address":"12728 Julian Ave",
    "sg:city":"Lakeside",
    "sg:classifiers":[
        {
            "category":"Professional",
            "subcategory":"Accounting & Tax Preparation",
            "type":"Services"
        }
    ],
    "sg:phone":"+1 619 561 3539",
    "sg:postcode":"92040",
    "sg:province":"CA",
    "sg:tags":[
        "billing"
    ],
    "wof:name":"Dreaming Tiger Inc",
    "wof:placetype":"venue"
},
  "geometry": {"coordinates":[-116.917717,32.855573],"type":"Point"}
}