{
  "type": "Feature",
  "properties": {
    "iso:country":"US",
    "sg:address":"10631 International Blvd",
    "sg:city":"Oakland",
    "sg:classifiers":[
        {
            "category":"Personal",
            "subcategory":"Beauty Salon",
            "type":"Services"
        }
    ],
    "sg:phone":"+1 510 638 9071",
    "sg:postcode":"94603",
    "sg:province":"CA",
    "wof:name":"Studio 107",
    "wof:placetype":"venue"
},
  "geometry": {"coordinates":[-122.165941,37.738234],"type":"Point"}
}