{
  "type": "Feature",
  "properties": {
    "addr:full":"1040 Los Osos Valley Rd Los Osos CA 93402",
    "addr:housenumber":"1040",
    "addr:postcode":"93402",
    "addr:street":"Los Osos Valley Rd",
    "iso:country":"US",
    "sg:address":"1040 Los Osos Valley Rd",
    "sg:city":"Los Osos",
    "sg:classifiers":[
        {
            "category":"Professional",
            "subcategory":"Computer Services",
            "type":"Services"
        }
    ],
    "sg:phone":"+1 805 528 5514",
    "sg:postcode":"93402",
    "sg:province":"CA",
    "sg:tags":[
        "consultant",
        "designer"
    ],
    "sg:website":"www.realworldcomputers.com",
    "wof:name":"Realworld Onsite Computer Spec",
    "wof:placetype":"venue"
},
  "geometry": {"coordinates":[-120.831676,35.311044],"type":"Point"}
}