{
  "type": "Feature",
  "properties": {
    "addr:full":"29 Yolano Dr Woodland CA 95776",
    "addr:housenumber":"29",
    "addr:postcode":"95776",
    "addr:street":"Yolano Dr",
    "iso:country":"US",
    "sg:address":"29 Yolano Dr",
    "sg:city":"Woodland",
    "sg:classifiers":[
        {
            "category":"Building & Trades",
            "subcategory":"Landscaping Services",
            "type":"Services"
        }
    ],
    "sg:phone":"+1 530 315 2990",
    "sg:postcode":"95776",
    "sg:province":"CA",
    "sg:tags":[
        "landscape"
    ],
    "wof:name":"Manuel Barragan & Son Ldscpg",
    "wof:placetype":"venue"
},
  "geometry": {"coordinates":[-121.76378800000001,38.680109],"type":"Point"}
}