{
  "type": "Feature",
  "properties": {
    "addr:full":"6772 Clark Ave Newark CA 94560",
    "addr:housenumber":"6772",
    "addr:postcode":"94560",
    "addr:street":"Clark Ave",
    "iso:country":"US",
    "sg:address":"6772 Clark Ave",
    "sg:city":"Newark",
    "sg:classifiers":[
        {
            "category":"Retail",
            "subcategory":"Repair Shop",
            "type":"Services"
        }
    ],
    "sg:phone":"+1 510 793 8447",
    "sg:postcode":"94560",
    "sg:province":"CA",
    "sg:tags":[
        "compactors"
    ],
    "wof:name":"Checkmark Compactor Svc",
    "wof:placetype":"venue"
},
  "geometry": {"coordinates":[-122.028662,37.529079],"type":"Point"}
}