{
  "type": "Feature",
  "properties": {
    "addr:full":"225 Kings Pl Newport Beach CA 92663",
    "addr:housenumber":"225",
    "addr:postcode":"92663",
    "addr:street":"Kings Pl",
    "iso:country":"US",
    "sg:address":"225 Kings Pl",
    "sg:city":"Newport Beach",
    "sg:classifiers":[
        {
            "category":"Professional",
            "type":"Services"
        }
    ],
    "sg:phone":"+1 949 650 5593",
    "sg:postcode":"92663",
    "sg:province":"CA",
    "wof:name":"Reloader Research Inc",
    "wof:placetype":"venue"
},
  "geometry": {"coordinates":[-117.908012,33.617497],"type":"Point"}
}