{
  "type": "Feature",
  "properties": {
    "addr:full":"1666 Garnet Ave San Diego CA 92109",
    "addr:housenumber":"1666",
    "addr:postcode":"92109",
    "addr:street":"Garnet Ave",
    "iso:country":"US",
    "sg:address":"1666 Garnet Ave",
    "sg:city":"San Diego",
    "sg:classifiers":[
        {
            "category":"Professional",
            "subcategory":"Accounting & Tax Preparation",
            "type":"Services"
        }
    ],
    "sg:phone":"+1 858 483 3336",
    "sg:postcode":"92109",
    "sg:province":"CA",
    "sg:tags":[
        "calculating"
    ],
    "wof:name":"Accustat Inc",
    "wof:placetype":"venue"
},
  "geometry": {"coordinates":[-117.24012399999999,32.799997],"type":"Point"}
}