{
  "type": "Feature",
  "properties": {
    "iso:country":"US",
    "sg:address":"2201 Pine St",
    "sg:city":"Napa",
    "sg:classifiers":[
        {
            "category":"Organizations",
            "subcategory":"Community Association",
            "type":"Services"
        }
    ],
    "sg:phone":"+1 707 257 9023",
    "sg:postcode":"94559",
    "sg:province":"CA",
    "sg:tags":[
        "club"
    ],
    "wof:name":"Portoino Club",
    "wof:placetype":"venue"
},
  "geometry": {"coordinates":[-122.299601,38.291117],"type":"Point"}
}