{
  "type": "Feature",
  "properties": {
    "addr:full":"17077 San Mateo St Fountain Valley CA 92708",
    "addr:housenumber":"17077",
    "addr:postcode":"92708",
    "addr:street":"San Mateo St",
    "iso:country":"US",
    "sg:address":"17077 San Mateo St",
    "sg:city":"Fountain Valley",
    "sg:classifiers":[
        {
            "category":"Health Services",
            "subcategory":"Nursing And Care Facility",
            "type":"Services"
        },
        {
            "category":"Real Estate",
            "subcategory":"Real Estate Operator",
            "type":"Services"
        }
    ],
    "sg:phone":"+1 714 962 6667",
    "sg:postcode":"92708",
    "sg:province":"CA",
    "sg:tags":[
        "building",
        "retirement",
        "apartment",
        "community",
        "home"
    ],
    "wof:name":"Carmel Village Retirement",
    "wof:placetype":"venue"
},
  "geometry": {"coordinates":[-117.951753,33.714624],"type":"Point"}
}