{
  "type": "Feature",
  "properties": {
    "addr:full":"401 Geneva Ave San Francisco CA 94112",
    "addr:housenumber":"401",
    "addr:postcode":"94112",
    "addr:street":"Geneva Ave",
    "iso:country":"US",
    "sg:address":"401 Geneva Ave",
    "sg:city":"San Francisco",
    "sg:classifiers":[
        {
            "category":"Local Transit",
            "type":"Transportation"
        }
    ],
    "sg:postcode":"94112",
    "sg:province":"CA",
    "sg:tags":[
        "public"
    ],
    "sg:website":"www.bart.gov",
    "wof:name":"BART Station - Balboa Park",
    "wof:placetype":"venue"
},
  "geometry": {"coordinates":[-122.447703,37.721214],"type":"Point"}
}