{
  "type": "Feature",
  "properties": {
    "addr:full":"20321 SW Birch St Newport Beach CA 92660",
    "addr:housenumber":"20321",
    "addr:postcode":"92660",
    "addr:street":"Sw Birch St",
    "iso:country":"US",
    "sg:address":"20321 SW Birch St",
    "sg:city":"Newport Beach",
    "sg:classifiers":[
        {
            "category":"Insurance",
            "subcategory":"Insurance Agent",
            "type":"Services"
        }
    ],
    "sg:phone":"+1 949 250 9910",
    "sg:postcode":"92660",
    "sg:province":"CA",
    "sg:tags":[
        "broker"
    ],
    "wof:name":"Voyager Insurance Services",
    "wof:placetype":"venue"
},
  "geometry": {"coordinates":[-117.87782900000001,33.656774],"type":"Point"}
}