{
  "type": "Feature",
  "properties": {
    "iso:country":"US",
    "sg:address":"20321 SW Birch St",
    "sg:city":"Newport Beach",
    "sg:classifiers":[
        {
            "category":"Insurance",
            "subcategory":"Insurance Agent",
            "type":"Services"
        }
    ],
    "sg:phone":"+1 949 250 9910",
    "sg:postcode":"92660",
    "sg:province":"CA",
    "sg:tags":[
        "broker"
    ],
    "wof:name":"Voyager Insurance Services",
    "wof:placetype":"venue"
},
  "geometry": {"coordinates":[-117.877829,33.656774],"type":"Point"}
}