{
  "type": "Feature",
  "properties": {
    "iso:country":"US",
    "sg:address":"904 S Fortuna Blvd",
    "sg:city":"Fortuna",
    "sg:classifiers":[
        {
            "category":"Restaurant",
            "type":"Food & Drink"
        }
    ],
    "sg:phone":"+1 707 725 2361",
    "sg:postcode":"95540",
    "sg:province":"CA",
    "wof:name":"Hot Brew",
    "wof:placetype":"venue"
},
  "geometry": {"coordinates":[-124.14675099999999,40.581928],"type":"Point"}
}