{
  "type": "Feature",
  "properties": {
    "iso:country":"US",
    "sg:address":"610 Frieda Dr",
    "sg:city":"Suisun City",
    "sg:classifiers":[
        {
            "category":"Social Services",
            "type":"Services"
        }
    ],
    "sg:phone":"+1 707 399 0722",
    "sg:postcode":"94585",
    "sg:province":"CA",
    "sg:tags":[
        "care",
        "center",
        "day"
    ],
    "wof:name":"In Kymberlee's Care",
    "wof:placetype":"venue"
},
  "geometry": {"coordinates":[-122.00735,38.257496],"type":"Point"}
}