{
  "type": "Feature",
  "properties": {
    "iso:country":"US",
    "sg:address":"1407 Paloma St",
    "sg:city":"Los Angeles",
    "sg:classifiers":[
        {
            "category":"Professional",
            "type":"Services"
        }
    ],
    "sg:phone":"+1 213 745 6841",
    "sg:postcode":"90021",
    "sg:province":"CA",
    "wof:name":"Faramo",
    "wof:placetype":"venue"
},
  "geometry": {"coordinates":[-118.249774,34.028708],"type":"Point"}
}