{
  "type": "Feature",
  "properties": {
    "addr:full":"1221 E Dyer Rd Santa Ana CA 92705",
    "addr:housenumber":"1221",
    "addr:postcode":"92705",
    "addr:street":"E Dyer Rd",
    "iso:country":"US",
    "sg:address":"1221 E Dyer Rd",
    "sg:city":"Santa Ana",
    "sg:classifiers":[
        {
            "category":"Government",
            "subcategory":"Office",
            "type":"Public Place"
        }
    ],
    "sg:phone":"+1 714 662 6030",
    "sg:postcode":"92705",
    "sg:province":"CA",
    "sg:tags":[
        "health"
    ],
    "wof:name":"Rehabilitation California Dept",
    "wof:placetype":"venue"
},
  "geometry": {"coordinates":[-117.854698,33.708604],"type":"Point"}
}