{
  "type": "Feature",
  "properties": {
    "addr:full":"1471 Alta Vista Dr Hollister CA 95023",
    "addr:housenumber":"1471",
    "addr:postcode":"hollister ca 95023",
    "addr:street":"Alta Vista Dr",
    "iso:country":"US",
    "sg:address":"1471 Alta Vista Dr",
    "sg:city":"Hollister",
    "sg:classifiers":[
        {
            "category":"Building & Trades",
            "subcategory":"Landscaping Services",
            "type":"Services"
        }
    ],
    "sg:phone":"+1 831 637 8873",
    "sg:postcode":"95023",
    "sg:province":"CA",
    "sg:tags":[
        "lawn",
        "maintenance",
        "grounds"
    ],
    "wof:name":"Garden & Turf Management",
    "wof:placetype":"venue"
},
  "geometry": {"coordinates":[-121.376065,36.833383],"type":"Point"}
}