{
  "type": "Feature",
  "properties": {
    "iso:country":"US",
    "sg:address":"1951 Bard Ct",
    "sg:city":"Claremont",
    "sg:classifiers":[
        {
            "category":"Professional",
            "subcategory":"Accounting & Tax Preparation",
            "type":"Services"
        }
    ],
    "sg:phone":"+1 909 626 4511",
    "sg:postcode":"91711",
    "sg:province":"CA",
    "sg:tags":[
        "accountant"
    ],
    "wof:name":"Louis Motisi Jr CPA",
    "wof:placetype":"venue"
},
  "geometry": {"coordinates":[-117.726873,34.119041],"type":"Point"}
}