{
  "type": "Feature",
  "properties": {
    "iso:country":"US",
    "sg:address":"2101 Forest Ave",
    "sg:city":"San Jose",
    "sg:classifiers":[
        {
            "category":"Health Services",
            "subcategory":"Doctor",
            "type":"Services"
        }
    ],
    "sg:phone":"+1 408 286 3222",
    "sg:postcode":"95128",
    "sg:province":"CA",
    "wof:name":"Yu Andy S MD",
    "wof:placetype":"venue"
},
  "geometry": {"coordinates":[-121.937162,37.327146],"type":"Point"}
}