{
  "type": "Feature",
  "properties": {
    "addr:full":"6080 Center Dr Los Angeles CA 90045",
    "addr:housenumber":"6080",
    "addr:postcode":"90045",
    "addr:street":"Center Dr",
    "iso:country":"US",
    "sg:address":"6080 Center Dr",
    "sg:city":"Los Angeles",
    "sg:classifiers":[
        {
            "category":"Real Estate",
            "subcategory":"Real Estate Services",
            "type":"Services"
        }
    ],
    "sg:phone":"+1 310 417 5330",
    "sg:postcode":"90045",
    "sg:province":"CA",
    "sg:tags":[
        "management",
        "property"
    ],
    "wof:name":"Arden Realty Inc",
    "wof:placetype":"venue"
},
  "geometry": {"coordinates":[-118.39299800000001,33.978001],"type":"Point"}
}