{
  "type": "Feature",
  "properties": {
    "addr:full":"2180 1st St Simi Valley CA 93065",
    "addr:housenumber":"2180",
    "addr:postcode":"93065",
    "addr:street":"1St St",
    "iso:country":"US",
    "sg:address":"2180 1st St",
    "sg:city":"Simi Valley",
    "sg:classifiers":[
        {
            "category":"Retail",
            "subcategory":"Auto Repair",
            "type":"Services"
        }
    ],
    "sg:phone":"+1 805 522 8476",
    "sg:postcode":"93065",
    "sg:province":"CA",
    "sg:tags":[
        "repairing",
        "automobile"
    ],
    "wof:name":"WCPB Inc",
    "wof:placetype":"venue"
},
  "geometry": {"coordinates":[-118.778811,34.273865],"type":"Point"}
}