{
  "type": "Feature",
  "properties": {
    "addr:full":"11310 S Alameda St Lynwood CA 90262",
    "addr:housenumber":"11310",
    "addr:postcode":"90262",
    "addr:street":"S Alameda St",
    "iso:country":"US",
    "sg:address":"11310 S Alameda St",
    "sg:city":"Lynwood",
    "sg:classifiers":[
        {
            "category":"Retail",
            "subcategory":"Auto Repair",
            "type":"Services"
        }
    ],
    "sg:phone":"+1 310 608 1728",
    "sg:postcode":"90262",
    "sg:province":"CA",
    "sg:tags":[
        "body",
        "automobile",
        "painting"
    ],
    "wof:name":"Fast Bumpers",
    "wof:placetype":"venue"
},
  "geometry": {"coordinates":[-118.225511,33.932592],"type":"Point"}
}