{
  "type": "Feature",
  "properties": {
    "iso:country":"US",
    "sg:address":"815 Indianapolis Ave",
    "sg:city":"Huntington Beach",
    "sg:classifiers":[
        {
            "category":"Food & Beverages",
            "subcategory":"Liquor & Beverages",
            "type":"Retail Goods"
        }
    ],
    "sg:phone":"+1 714 536 6275",
    "sg:postcode":"92648",
    "sg:province":"CA",
    "sg:tags":[
        "beer",
        "spirit",
        "wine"
    ],
    "wof:name":"Hilltop Liquor",
    "wof:placetype":"venue"
},
  "geometry": {"coordinates":[-117.988998,33.664902],"type":"Point"}
}