{
  "type": "Feature",
  "properties": {
    "addr:full":"10848 Foothill Blvd Rancho Cucamonga CA 91730",
    "addr:housenumber":"10848",
    "addr:postcode":"91730",
    "addr:street":"Foothill Blvd",
    "iso:country":"US",
    "sg:address":"10848 Foothill Blvd",
    "sg:city":"Rancho Cucamonga",
    "sg:classifiers":[
        {
            "category":"Home & Garden",
            "subcategory":"Furniture",
            "type":"Retail Goods"
        }
    ],
    "sg:phone":"+1 909 476 2801",
    "sg:postcode":"91730",
    "sg:province":"CA",
    "wof:name":"Home Design Furniture",
    "wof:placetype":"venue"
},
  "geometry": {"coordinates":[-117.569866,34.106573],"type":"Point"}
}