{
  "type": "Feature",
  "properties": {
    "addr:full":"295 E St Arcata CA 95521",
    "addr:housenumber":"295",
    "addr:postcode":"95521",
    "addr:street":"E St",
    "iso:country":"US",
    "sg:address":"295 E St",
    "sg:city":"Arcata",
    "sg:classifiers":[
        {
            "category":"Shopping",
            "subcategory":"Clothing, Apparel, & Fashions",
            "type":"Retail Goods"
        }
    ],
    "sg:phone":"+1 707 822 0261",
    "sg:postcode":"95521",
    "sg:province":"CA",
    "wof:name":"Provolt Design",
    "wof:placetype":"venue"
},
  "geometry": {"coordinates":[-124.085697,40.863021],"type":"Point"}
}