{
  "type": "Feature",
  "properties": {
    "iso:country":"US",
    "sg:address":"1221 State St",
    "sg:city":"Santa Barbara",
    "sg:classifiers":[
        {
            "category":"Health Services",
            "subcategory":"Chiropractor",
            "type":"Services"
        }
    ],
    "sg:phone":"+1 805 966 1550",
    "sg:postcode":"93101",
    "sg:province":"CA",
    "wof:name":"Progessive Health Ctr",
    "wof:placetype":"venue"
},
  "geometry": {"coordinates":[-119.70556000000001,34.424045],"type":"Point"}
}