{
  "type": "Feature",
  "properties": {
    "iso:country":"US",
    "sg:address":"1067 C St",
    "sg:city":"Galt",
    "sg:classifiers":[
        {
            "category":"Health Services",
            "subcategory":"Health Practitioner",
            "type":"Services"
        }
    ],
    "sg:phone":"+1 209 745 5802",
    "sg:postcode":"95632",
    "sg:province":"CA",
    "sg:tags":[
        "therapist",
        "physical"
    ],
    "wof:name":"Delta Physical Therapy",
    "wof:placetype":"venue"
},
  "geometry": {"coordinates":[-121.297182,38.253205],"type":"Point"}
}