{
  "type": "Feature",
  "properties": {
    "addr:full":"6441 Jefferson St Anaheim CA 92807",
    "addr:housenumber":"6441",
    "addr:postcode":"92807",
    "addr:street":"Jefferson St",
    "iso:country":"US",
    "sg:address":"6441 Jefferson St",
    "sg:city":"Anaheim",
    "sg:phone":"+1 714 993 2110",
    "sg:postcode":"92807",
    "sg:province":"CA",
    "sg:website":"http://www.ford.com",
    "wof:name":"All Ford Auto Salvage Inc.",
    "wof:placetype":"venue"
},
  "geometry": {"coordinates":[-117.837484,33.858102],"type":"Point"}
}