{
  "type": "Feature",
  "properties": {
    "addr:full":"851 W Ave I Lancaster CA 93534",
    "addr:housenumber":"851",
    "addr:postcode":"93534",
    "addr:street":"W Ave I",
    "iso:country":"US",
    "sg:address":"851 W Ave I",
    "sg:city":"Lancaster",
    "sg:classifiers":[
        {
            "category":"Personal",
            "subcategory":"Beauty Salon",
            "type":"Services"
        }
    ],
    "sg:phone":"+1 661 723 9507",
    "sg:postcode":"93534",
    "sg:province":"CA",
    "wof:name":"Friend's Beauty Salon",
    "wof:placetype":"venue"
},
  "geometry": {"coordinates":[-118.146728,34.704035],"type":"Point"}
}