{
  "type": "Feature",
  "properties": {
    "iso:country":"US",
    "sg:address":"12824 Rosecrans Ave",
    "sg:city":"Norwalk",
    "sg:classifiers":[
        {
            "category":"Retail",
            "subcategory":"Auto Repair",
            "type":"Services"
        }
    ],
    "sg:phone":"+1 562 867 8062",
    "sg:postcode":"90650",
    "sg:province":"CA",
    "sg:tags":[
        "body",
        "automobile",
        "painting"
    ],
    "wof:name":"Balcaceres Bro's Tow",
    "wof:placetype":"venue"
},
  "geometry": {"coordinates":[-118.05976099999999,33.902201],"type":"Point"}
}