{
  "type": "Feature",
  "properties": {
    "addr:full":"250 E 17th St Costa Mesa CA 92627",
    "addr:housenumber":"250",
    "addr:postcode":"92627",
    "addr:street":"E 17Th St",
    "iso:country":"US",
    "sg:address":"250 E 17th St",
    "sg:city":"Costa Mesa",
    "sg:classifiers":[
        {
            "category":"Insurance",
            "subcategory":"Insurance Agent",
            "type":"Services"
        }
    ],
    "sg:phone":"+1 949 646 2209",
    "sg:postcode":"92627",
    "sg:province":"CA",
    "wof:name":"Ca Four Star Ins Svc Club Inc",
    "wof:placetype":"venue"
},
  "geometry": {"coordinates":[-117.91536000000001,33.633072],"type":"Point"}
}