{
  "type": "Feature",
  "properties": {
    "iso:country":"US",
    "sg:address":"14821 Aetna St",
    "sg:city":"Van Nuys",
    "sg:classifiers":[
        {
            "category":"Home & Garden",
            "subcategory":"Furniture",
            "type":"Retail Goods"
        }
    ],
    "sg:phone":"+1 818 787 8655",
    "sg:postcode":"91411",
    "sg:province":"CA",
    "sg:tags":[
        "carpentry",
        "contractor"
    ],
    "wof:name":"West End",
    "wof:placetype":"venue"
},
  "geometry": {"coordinates":[-118.455253,34.1802],"type":"Point"}
}