{
  "type": "Feature",
  "properties": {
    "addr:full":"28041 Hawthorne Blvd Rancho Pls Vrds CA 90275",
    "addr:housenumber":"28041",
    "addr:postcode":"90275",
    "addr:street":"Hawthorne Blvd",
    "iso:country":"US",
    "sg:address":"28041 Hawthorne Blvd",
    "sg:city":"Rancho Pls Vrds",
    "sg:classifiers":[
        {
            "category":"Professional",
            "subcategory":"Computer Services",
            "type":"Services"
        }
    ],
    "sg:phone":"+1 310 541 2015",
    "sg:postcode":"90275",
    "sg:province":"CA",
    "sg:tags":[
        "repair"
    ],
    "wof:name":"Far Pacific Intl",
    "wof:placetype":"venue"
},
  "geometry": {"coordinates":[-118.389121,33.77932],"type":"Point"}
}