{
  "type": "Feature",
  "properties": {
    "iso:country":"US",
    "sg:address":"420 N Santa Anita Ave",
    "sg:city":"Arcadia",
    "sg:classifiers":[
        {
            "category":"Fast Food",
            "type":"Food & Drink"
        },
        {
            "category":"Restaurant",
            "type":"Food & Drink"
        }
    ],
    "sg:phone":"+1 626 287 4377",
    "sg:postcode":"91006",
    "sg:province":"CA",
    "sg:tags":[
        "style",
        "hamburger",
        "family",
        "dog",
        "hot",
        "take"
    ],
    "wof:name":"In & Out Burger",
    "wof:placetype":"venue"
},
  "geometry": {"coordinates":[-118.03146700000001,34.144663],"type":"Point"}
}