{
  "type": "Feature",
  "properties": {
    "iso:country":"US",
    "sg:address":"2579 Willo Ln",
    "sg:city":"Costa Mesa",
    "sg:classifiers":[
        {
            "category":"Wholesale",
            "subcategory":"Jewelry",
            "type":"Manufacturing & Wholesale Goods"
        }
    ],
    "sg:phone":"+1 949 642 9600",
    "sg:postcode":"92627",
    "sg:province":"CA",
    "sg:tags":[
        "stone"
    ],
    "wof:name":"Milagros By Teresa Pattererson",
    "wof:placetype":"venue"
},
  "geometry": {"coordinates":[-117.889061,33.655878],"type":"Point"}
}