{
  "type": "Feature",
  "properties": {
    "addr:full":"4035 Clipper Ct Fremont CA 94538",
    "addr:housenumber":"4035",
    "addr:postcode":"94538",
    "addr:street":"Clipper Ct",
    "iso:country":"US",
    "sg:address":"4035 Clipper Ct",
    "sg:city":"Fremont",
    "sg:classifiers":[
        {
            "category":"Wholesale",
            "subcategory":"Computers",
            "type":"Manufacturing & Wholesale Goods"
        }
    ],
    "sg:phone":"+1 510 824 0888",
    "sg:postcode":"94538",
    "sg:province":"CA",
    "wof:name":"Selectcool LLC",
    "wof:placetype":"venue"
},
  "geometry": {"coordinates":[-121.947306,37.479344],"type":"Point"}
}