{
  "type": "Feature",
  "properties": {
    "iso:country":"US",
    "sg:address":"2510 Middlefield Rd",
    "sg:city":"Redwood City",
    "sg:classifiers":[
        {
            "category":"Education",
            "subcategory":"Library",
            "type":"Public Place"
        }
    ],
    "sg:phone":"+1 650 780 7261",
    "sg:postcode":"94063",
    "sg:province":"CA",
    "sg:tags":[
        "executive"
    ],
    "wof:name":"Fair Oaks Branch Library",
    "wof:placetype":"venue"
},
  "geometry": {"coordinates":[-122.21338,37.47813],"type":"Point"}
}