{
  "type": "Feature",
  "properties": {
    "iso:country":"US",
    "sg:address":"6254 N Paramount Blvd",
    "sg:city":"Long Beach",
    "sg:classifiers":[
        {
            "category":"Freight",
            "type":"Transportation"
        }
    ],
    "sg:phone":"+1 562 860 3000",
    "sg:postcode":"90805",
    "sg:province":"CA",
    "sg:tags":[
        "garbage",
        "collection",
        "transport"
    ],
    "wof:name":"B-Z Disposal",
    "wof:placetype":"venue"
},
  "geometry": {"coordinates":[-118.159842,33.86438],"type":"Point"}
}