{
  "type": "Feature",
  "properties": {
    "addr:full":"4440 Industrial St Simi Valley CA 93063",
    "addr:housenumber":"4440",
    "addr:postcode":"93063",
    "addr:street":"Industrial St",
    "iso:country":"US",
    "sg:address":"4440 Industrial St",
    "sg:city":"Simi Valley",
    "sg:classifiers":[
        {
            "category":"Wholesale",
            "subcategory":"Office Equipment",
            "type":"Manufacturing & Wholesale Goods"
        }
    ],
    "sg:phone":"+1 805 526 5443",
    "sg:postcode":"93063",
    "sg:province":"CA",
    "sg:tags":[
        "vault",
        "safe"
    ],
    "sg:website":"www.jrbozarthsafeco.com",
    "wof:name":"J R Bozarth Safe Co",
    "wof:placetype":"venue"
},
  "geometry": {"coordinates":[-118.701806,34.273184],"type":"Point"}
}