{
  "type": "Feature",
  "properties": {
    "addr:full":"1135 Old Bayshore Hwy San Jose CA 95112",
    "addr:housenumber":"1135",
    "addr:postcode":"95112",
    "addr:street":"Old Bayshore Hwy",
    "iso:country":"US",
    "sg:address":"1135 Old Bayshore Hwy",
    "sg:city":"San Jose",
    "sg:classifiers":[
        {
            "category":"Retail",
            "subcategory":"Auto Repair",
            "type":"Services"
        }
    ],
    "sg:phone":"+1 408 299 0508",
    "sg:postcode":"95112",
    "sg:province":"CA",
    "sg:tags":[
        "motorcycle"
    ],
    "sg:website":"www.advcycles.com/",
    "wof:name":"Advanced Cycle Service",
    "wof:placetype":"venue"
},
  "geometry": {"coordinates":[-121.897498,37.365193],"type":"Point"}
}