{
  "type": "Feature",
  "properties": {
    "iso:country":"US",
    "sg:address":"3152 Pacific Coast Hwy",
    "sg:city":"Torrance",
    "sg:classifiers":[
        {
            "category":"Real Estate",
            "subcategory":"Real Estate Agent",
            "type":"Services"
        }
    ],
    "sg:phone":"+1 310 325 3007",
    "sg:postcode":"90505",
    "sg:province":"CA",
    "sg:tags":[
        "management",
        "property"
    ],
    "sg:website":"www.era.com",
    "wof:name":"Home Partners Inc",
    "wof:placetype":"venue"
},
  "geometry": {"coordinates":[-118.341087,33.797988],"type":"Point"}
}