{
  "type": "Feature",
  "properties": {
    "addr:full":"432 5th St Gustine CA 95322",
    "addr:housenumber":"432",
    "addr:postcode":"95322",
    "addr:street":"5Th St",
    "iso:country":"US",
    "sg:address":"432 5th St",
    "sg:city":"Gustine",
    "sg:classifiers":[
        {
            "category":"Home & Garden",
            "subcategory":"Furniture",
            "type":"Retail Goods"
        }
    ],
    "sg:phone":"+1 209 854 2381",
    "sg:postcode":"95322",
    "sg:province":"CA",
    "wof:name":"Ruby's Furniture",
    "wof:placetype":"venue"
},
  "geometry": {"coordinates":[-120.99918599999999,37.255182],"type":"Point"}
}