{
  "type": "Feature",
  "properties": {
    "iso:country":"US",
    "sg:address":"4040 Sorrento Valley Blvd",
    "sg:city":"San Diego",
    "sg:classifiers":[
        {
            "category":"Professional",
            "type":"Services"
        }
    ],
    "sg:phone":"+1 858 546 0019",
    "sg:postcode":"92121",
    "sg:province":"CA",
    "wof:name":"Nirwana",
    "wof:placetype":"venue"
},
  "geometry": {"coordinates":[-117.215633,32.904026],"type":"Point"}
}