{
  "type": "Feature",
  "properties": {
    "addr:full":"271 Opportunity St Sacramento CA 95838",
    "addr:housenumber":"271",
    "addr:postcode":"95838",
    "addr:street":"Opportunity St",
    "iso:country":"US",
    "sg:address":"271 Opportunity St",
    "sg:city":"Sacramento",
    "sg:classifiers":[
        {
            "category":"Building & Trades",
            "subcategory":"Plumbing",
            "type":"Services"
        }
    ],
    "sg:phone":"+1 916 924 0494",
    "sg:postcode":"95838",
    "sg:province":"CA",
    "sg:tags":[
        "sheet",
        "work",
        "metal",
        "contractor"
    ],
    "wof:name":"California Sheet Metal",
    "wof:placetype":"venue"
},
  "geometry": {"coordinates":[-121.459436,38.640252],"type":"Point"}
}