{
  "type": "Feature",
  "properties": {
    "addr:full":"3333 Bristol Street Suite 2805 Costa Mesa CA 92626",
    "addr:housenumber":"3333",
    "addr:postcode":"92626",
    "addr:street":"Bristol Street Suite 2805",
    "iso:country":"US",
    "sg:address":"3333 Bristol Street Suite 2805",
    "sg:city":"Costa Mesa",
    "sg:classifiers":[
        {
            "category":"Shopping",
            "subcategory":"Shoes",
            "type":"Retail Goods"
        }
    ],
    "sg:phone":"+1 714 557 0259",
    "sg:postcode":"92626",
    "sg:province":"CA",
    "sg:tags":[
        "store"
    ],
    "wof:name":"Nine West",
    "wof:placetype":"venue"
},
  "geometry": {"coordinates":[-117.88564100000001,33.690289],"type":"Point"}
}