{
  "type": "Feature",
  "properties": {
    "iso:country":"US",
    "sg:address":"2945 Harding St",
    "sg:city":"Carlsbad",
    "sg:classifiers":[
        {
            "category":"Banks & Credit Unions",
            "subcategory":"Bank",
            "type":"Services"
        }
    ],
    "sg:phone":"+1 760 720 2462",
    "sg:postcode":"92008",
    "sg:province":"CA",
    "sg:tags":[
        "loan",
        "real estate"
    ],
    "wof:name":"Midland Loan Svc",
    "wof:placetype":"venue"
},
  "geometry": {"coordinates":[-117.345038,33.1624],"type":"Point"}
}