{
  "type": "Feature",
  "properties": {
    "addr:full":"4161 Ingot St Fremont CA 94538",
    "addr:housenumber":"4161",
    "addr:postcode":"94538",
    "addr:street":"Ingot St",
    "iso:country":"US",
    "sg:address":"4161 Ingot St",
    "sg:city":"Fremont",
    "sg:classifiers":[
        {
            "category":"Professional",
            "subcategory":"Computer Services",
            "type":"Services"
        }
    ],
    "sg:phone":"+1 510 687 1233",
    "sg:postcode":"94538",
    "sg:province":"CA",
    "sg:tags":[
        "consultant",
        "designer"
    ],
    "wof:name":"Techaspect Solutions",
    "wof:placetype":"venue"
},
  "geometry": {"coordinates":[-121.949732,37.498691],"type":"Point"}
}