{
  "type": "Feature",
  "properties": {
    "iso:country":"US",
    "sg:address":"1300 Chesapeake Ter",
    "sg:city":"Sunnyvale",
    "sg:classifiers":[
        {
            "category":"Travel",
            "subcategory":"Hotels & Motels",
            "type":"Entertainment"
        },
        {
            "category":"Travel",
            "subcategory":"Bed & Breakfast",
            "type":"Entertainment"
        }
    ],
    "sg:phone":"+1 408 747 0999",
    "sg:postcode":"94089",
    "sg:province":"CA",
    "sg:tags":[
        "inn",
        "lodging"
    ],
    "sg:website":"http://www.countryinns.com/sunnyvaleca",
    "wof:name":"Country Inn & Suites By Carlson",
    "wof:placetype":"venue"
},
  "geometry": {"coordinates":[-122.002146,37.4101],"type":"Point"}
}