{
  "type": "Feature",
  "properties": {
    "addr:full":"95 S Market St # 300 San Jose CA 95101",
    "addr:housenumber":"95",
    "addr:postcode":"95101",
    "addr:street":"S Market St # 300",
    "iso:country":"US",
    "sg:address":"95 S Market St # 300",
    "sg:city":"San Jose",
    "sg:classifiers":[
        {
            "category":"Professional",
            "subcategory":"Lawyer & Legal Services",
            "type":"Services"
        }
    ],
    "sg:phone":"+1 408 446 5879",
    "sg:postcode":"95101",
    "sg:province":"CA",
    "sg:tags":[
        "personal",
        "injury"
    ],
    "sg:website":"www.18004injury.com/",
    "wof:name":"Kuvara Law Firm",
    "wof:placetype":"venue"
},
  "geometry": {"coordinates":[-121.891328,37.333752],"type":"Point"}
}