{
  "type": "Feature",
  "properties": {
    "addr:full":"633 E 97th St Los Angeles CA 90002",
    "addr:housenumber":"633",
    "addr:postcode":"90002",
    "addr:street":"E 97Th St",
    "iso:country":"US",
    "sg:address":"633 E 97th St",
    "sg:city":"Los Angeles",
    "sg:classifiers":[
        {
            "category":"Building & Trades",
            "subcategory":"Electrical",
            "type":"Services"
        }
    ],
    "sg:phone":"+1 323 755 3641",
    "sg:postcode":"90002",
    "sg:province":"CA",
    "sg:tags":[
        "electrician"
    ],
    "wof:name":"Bert's Electrical Service",
    "wof:placetype":"venue"
},
  "geometry": {"coordinates":[-118.264,33.948399],"type":"Point"}
}