{
  "type": "Feature",
  "properties": {
    "addr:full":"307 Franci St Livingston CA 95334",
    "addr:housenumber":"307",
    "addr:postcode":"95334",
    "addr:street":"Franci St",
    "iso:country":"US",
    "sg:address":"307 Franci St",
    "sg:city":"Livingston",
    "sg:classifiers":[
        {
            "category":"Manufacturing",
            "subcategory":"Tools & Machinery",
            "type":"Manufacturing & Wholesale Goods"
        }
    ],
    "sg:phone":"+1 209 394 8084",
    "sg:postcode":"95334",
    "sg:province":"CA",
    "sg:tags":[
        "industry",
        "mfg"
    ],
    "wof:name":"Ultra Pure Inc",
    "wof:placetype":"venue"
},
  "geometry": {"coordinates":[-120.71896700000001,37.389369],"type":"Point"}
}