{
  "type": "Feature",
  "properties": {
    "addr:full":"99 N La Cienega Boulevard Suite 104 Beverly Hills CA 90211",
    "addr:housenumber":"99",
    "addr:postcode":"90211",
    "addr:street":"N La Cienega Boulevard Suite 104;Hills Ca",
    "iso:country":"US",
    "sg:address":"99 N La Cienega Boulevard Suite 104",
    "sg:city":"Beverly Hills",
    "sg:classifiers":[
        {
            "category":"Shopping",
            "subcategory":"Pharmacy",
            "type":"Retail Goods"
        }
    ],
    "sg:phone":"+1 310 360 9969",
    "sg:postcode":"90211",
    "sg:province":"CA",
    "sg:tags":[
        "drugstore"
    ],
    "wof:name":"Cienega Pharmacy United Drugs",
    "wof:placetype":"venue"
},
  "geometry": {"coordinates":[-118.376301,34.066476],"type":"Point"}
}