{
  "type": "Feature",
  "properties": {
    "iso:country":"US",
    "sg:address":"806 L St",
    "sg:city":"Sacramento",
    "sg:classifiers":[
        {
            "category":"Building & Trades",
            "subcategory":"Locksmith",
            "type":"Services"
        }
    ],
    "sg:phone":"+1 916 403 1355",
    "sg:postcode":"95814",
    "sg:province":"CA",
    "sg:tags":[
        "lock",
        "industrial",
        "key",
        "locksmiths-commercial"
    ],
    "wof:name":"Aarons Lock and Key of Sacramento",
    "wof:placetype":"venue"
},
  "geometry": {"coordinates":[-121.49699699999999,38.578817],"type":"Point"}
}