{
  "type": "Feature",
  "properties": {
    "addr:full":"14 Linden Dr Santa Clara CA 95050",
    "addr:housenumber":"14",
    "addr:postcode":"95050",
    "addr:street":"Linden Dr",
    "iso:country":"US",
    "sg:address":"14 Linden Dr",
    "sg:city":"Santa Clara",
    "sg:classifiers":[
        {
            "category":"Shopping",
            "subcategory":"Florist",
            "type":"Retail Goods"
        }
    ],
    "sg:phone":"+1 408 985 5370",
    "sg:postcode":"95050",
    "sg:province":"CA",
    "wof:name":"Wiggling Twiggs Partys & Thing",
    "wof:placetype":"venue"
},
  "geometry": {"coordinates":[-121.935936,37.338523],"type":"Point"}
}