{
  "type": "Feature",
  "properties": {
    "iso:country":"US",
    "sg:address":"620 Mcmurray Rd",
    "sg:city":"Buellton",
    "sg:classifiers":[
        {
            "category":"Bars & Pubs",
            "type":"Food & Drink"
        },
        {
            "category":"Food & Beverages",
            "subcategory":"Liquor & Beverages",
            "type":"Retail Goods"
        }
    ],
    "sg:phone":"+1 805 686 1557",
    "sg:postcode":"93427",
    "sg:province":"CA",
    "sg:tags":[
        "brew",
        "beer",
        "ale",
        "store"
    ],
    "sg:website":"http://www.firestonewalker.com",
    "wof:name":"Firestone Walker Brewing Co",
    "wof:placetype":"venue"
},
  "geometry": {"coordinates":[-120.187865,34.618705],"type":"Point"}
}