{
  "type": "Feature",
  "properties": {
    "iso:country":"US",
    "sg:address":"3009 Deer Valley Ave",
    "sg:city":"Newbury Park",
    "sg:classifiers":[
        {
            "category":"Building & Trades",
            "subcategory":"Landscaping Services",
            "type":"Services"
        }
    ],
    "sg:phone":"+1 805 498 1730",
    "sg:postcode":"91320",
    "sg:province":"CA",
    "sg:tags":[
        "landscape"
    ],
    "wof:name":"Ramirez Landscaping",
    "wof:placetype":"venue"
},
  "geometry": {"coordinates":[-118.942787,34.159959],"type":"Point"}
}