{
  "type": "Feature",
  "properties": {
    "iso:country":"US",
    "sg:address":"11039 Cantara St",
    "sg:city":"Sun Valley",
    "sg:classifiers":[
        {
            "category":"Organizations",
            "subcategory":"Religious Organization",
            "type":"Services"
        }
    ],
    "sg:phone":"+1 818 767 7619",
    "sg:postcode":"91352",
    "sg:province":"CA",
    "sg:tags":[
        "church"
    ],
    "wof:name":"Aposento Alto Foursquare Chr",
    "wof:placetype":"venue"
},
  "geometry": {"coordinates":[-118.37244099999999,34.219399],"type":"Point"}
}