{
  "type": "Feature",
  "properties": {
    "iso:country":"US",
    "sg:address":"2830 Auburn Blvd",
    "sg:city":"Sacramento",
    "sg:classifiers":[
        {
            "category":"Personal",
            "subcategory":"Beauty Salon",
            "type":"Services"
        }
    ],
    "sg:phone":"+1 916 483 0296",
    "sg:postcode":"95821",
    "sg:province":"CA",
    "wof:name":"Hair Lair",
    "wof:placetype":"venue"
},
  "geometry": {"coordinates":[-121.396274,38.631913],"type":"Point"}
}