{
  "type": "Feature",
  "properties": {
    "addr:full":"520 S Magnolia Ave El Cajon CA 92020",
    "addr:housenumber":"520",
    "addr:postcode":"92020",
    "addr:street":"S Magnolia Ave",
    "iso:country":"US",
    "sg:address":"520 S Magnolia Ave",
    "sg:city":"El Cajon",
    "sg:classifiers":[
        {
            "category":"Organizations",
            "subcategory":"Religious Organization",
            "type":"Services"
        }
    ],
    "sg:phone":"+1 619 401 7371",
    "sg:postcode":"92020",
    "sg:province":"CA",
    "sg:tags":[
        "church"
    ],
    "wof:name":"Eastside Community Church",
    "wof:placetype":"venue"
},
  "geometry": {"coordinates":[-116.962394,32.789537],"type":"Point"}
}