{
  "type": "Feature",
  "properties": {
    "addr:full":"12385 Rue Fontainebleau San Diego CA 92131",
    "addr:housenumber":"12385",
    "addr:postcode":"92131",
    "addr:street":"Rue Fontainebleau",
    "iso:country":"US",
    "sg:address":"12385 Rue Fontainebleau",
    "sg:city":"San Diego",
    "sg:classifiers":[
        {
            "category":"Professional",
            "type":"Services"
        }
    ],
    "sg:phone":"+1 858 578 7074",
    "sg:postcode":"92131",
    "sg:province":"CA",
    "wof:name":"Steelcomm",
    "wof:placetype":"venue"
},
  "geometry": {"coordinates":[-117.073121,32.907178],"type":"Point"}
}