{
  "type": "Feature",
  "properties": {
    "addr:full":"1400 Midvale Ave Los Angeles CA 90024",
    "addr:housenumber":"1400",
    "addr:postcode":"90024",
    "addr:street":"Midvale Ave",
    "iso:country":"US",
    "sg:address":"1400 Midvale Ave",
    "sg:city":"Los Angeles",
    "sg:classifiers":[
        {
            "category":"Professional",
            "subcategory":"Advertising",
            "type":"Services"
        }
    ],
    "sg:phone":"+1 310 452 9072",
    "sg:postcode":"90024",
    "sg:province":"CA",
    "wof:name":"Los Angeles Actors Guide",
    "wof:placetype":"venue"
},
  "geometry": {"coordinates":[-118.44155000000001,34.053565],"type":"Point"}
}