{
  "type": "Feature",
  "properties": {
    "iso:country":"US",
    "sg:address":"162 W 10th St",
    "sg:city":"Gilroy",
    "sg:classifiers":[
        {
            "category":"Food & Beverages",
            "subcategory":"Groceries & Convenience Stores",
            "type":"Retail Goods"
        }
    ],
    "sg:phone":"+1 408 842 8648",
    "sg:postcode":"95020",
    "sg:province":"CA",
    "wof:name":"7-Eleven",
    "wof:placetype":"venue"
},
  "geometry": {"coordinates":[-121.56817,36.99962],"type":"Point"}
}