{
  "type": "Feature",
  "properties": {
    "iso:country":"US",
    "sg:address":"5409 Central Ave",
    "sg:city":"Newark",
    "sg:classifiers":[
        {
            "category":"Home & Garden",
            "subcategory":"Building Materials",
            "type":"Retail Goods"
        }
    ],
    "sg:phone":"+1 510 795 8484",
    "sg:postcode":"94560",
    "sg:province":"CA",
    "sg:tags":[
        "paint"
    ],
    "wof:name":"California Carcolor",
    "wof:placetype":"venue"
},
  "geometry": {"coordinates":[-122.017348,37.539132],"type":"Point"}
}