{
  "type": "Feature",
  "properties": {
    "iso:country":"US",
    "sg:address":"29266 Elba Dr",
    "sg:city":"Laguna Niguel",
    "sg:classifiers":[
        {
            "category":"Professional",
            "type":"Services"
        }
    ],
    "sg:phone":"+1 949 495 8813",
    "sg:postcode":"92677",
    "sg:province":"CA",
    "wof:name":"Mason H B R",
    "wof:placetype":"venue"
},
  "geometry": {"coordinates":[-117.724614,33.53752],"type":"Point"}
}