{
  "type": "Feature",
  "properties": {
    "iso:country":"US",
    "sg:address":"22530 3rd St",
    "sg:city":"Hayward",
    "sg:classifiers":[
        {
            "category":"Health Services",
            "subcategory":"Hospital",
            "type":"Services"
        }
    ],
    "sg:phone":"+1 510 889 7463",
    "sg:postcode":"94541",
    "sg:province":"CA",
    "sg:tags":[
        "mental"
    ],
    "wof:name":"Bruce E Massarsky",
    "wof:placetype":"venue"
},
  "geometry": {"coordinates":[-122.07787999999999,37.676785],"type":"Point"}
}