{
  "type": "Feature",
  "properties": {
    "addr:full":"17550 Serene Dr Morgan Hill CA 95037",
    "addr:housenumber":"17550",
    "addr:postcode":"95037",
    "addr:street":"Serene Dr",
    "iso:country":"US",
    "sg:address":"17550 Serene Dr",
    "sg:city":"Morgan Hill",
    "sg:classifiers":[
        {
            "category":"Shopping",
            "subcategory":"Computers & Home Electronics",
            "type":"Retail Goods"
        }
    ],
    "sg:phone":"+1 408 776 0280",
    "sg:postcode":"95037",
    "sg:province":"CA",
    "sg:tags":[
        "software"
    ],
    "wof:name":"KCS Enterprises",
    "wof:placetype":"venue"
},
  "geometry": {"coordinates":[-121.64263,37.13875],"type":"Point"}
}