{
  "type": "Feature",
  "properties": {
    "addr:full":"520 Cortez Rd Arcadia CA 91007",
    "addr:housenumber":"520",
    "addr:postcode":"91007",
    "addr:street":"Cortez Rd",
    "iso:country":"US",
    "sg:address":"520 Cortez Rd",
    "sg:city":"Arcadia",
    "sg:classifiers":[
        {
            "category":"Home & Garden",
            "subcategory":"Furniture",
            "type":"Retail Goods"
        }
    ],
    "sg:phone":"+1 626 447 9540",
    "sg:postcode":"91007",
    "sg:province":"CA",
    "wof:name":"Sweet Pea Designs",
    "wof:placetype":"venue"
},
  "geometry": {"coordinates":[-118.0655,34.135375],"type":"Point"}
}