{
  "type": "Feature",
  "properties": {
    "addr:full":"1412 S Madera Ave Madera CA 93637",
    "addr:housenumber":"1412",
    "addr:postcode":"93637",
    "addr:street":"S Madera Ave",
    "iso:country":"US",
    "sg:address":"1412 S Madera Ave",
    "sg:city":"Madera",
    "sg:classifiers":[
        {
            "category":"Restaurant",
            "type":"Food & Drink"
        }
    ],
    "sg:phone":"+1 559 661 0200",
    "sg:postcode":"93637",
    "sg:province":"CA",
    "wof:name":"Subway Sandwiches & Salads",
    "wof:placetype":"venue"
},
  "geometry": {"coordinates":[-120.056099,36.946992],"type":"Point"}
}