{
  "type": "Feature",
  "properties": {
    "addr:full":"2545 Crenshaw Blvd Los Angeles CA 90189",
    "addr:housenumber":"2545",
    "addr:postcode":"90189",
    "addr:street":"Crenshaw Blvd",
    "iso:country":"US",
    "sg:address":"2545 Crenshaw Blvd",
    "sg:city":"Los Angeles",
    "sg:classifiers":[
        {
            "category":"Autos & Motor Vehicles",
            "subcategory":"Fuel & Gas Station",
            "type":"Retail Goods"
        }
    ],
    "sg:postcode":"90189",
    "sg:province":"CA",
    "wof:name":"Valero Gas Station",
    "wof:placetype":"venue"
},
  "geometry": {"coordinates":[-118.33479800000001,34.03313],"type":"Point"}
}