{
  "type": "Feature",
  "properties": {
    "iso:country":"US",
    "sg:address":"901 Shorepoint Ct",
    "sg:city":"Alameda",
    "sg:classifiers":[
        {
            "category":"Real Estate",
            "subcategory":"Real Estate Operator",
            "type":"Services"
        }
    ],
    "sg:phone":"+1 510 521 2801",
    "sg:postcode":"94501",
    "sg:province":"CA",
    "sg:tags":[
        "apartment"
    ],
    "wof:name":"South Shore Beach & Tennis Club",
    "wof:placetype":"venue"
},
  "geometry": {"coordinates":[-122.26953399999999,37.763124],"type":"Point"}
}