{
  "type": "Feature",
  "properties": {
    "iso:country":"US",
    "sg:address":"3182 Old Tunnel Rd Ste C",
    "sg:city":"Lafayette",
    "sg:classifiers":[
        {
            "category":"Professional",
            "subcategory":"Lawyer & Legal Services",
            "type":"Services"
        }
    ],
    "sg:phone":"+1 925 938 1200",
    "sg:postcode":"94549",
    "sg:province":"CA",
    "sg:tags":[
        "attorney",
        "practice"
    ],
    "wof:name":"F William Dorband",
    "wof:placetype":"venue"
},
  "geometry": {"coordinates":[-122.093386,37.895624],"type":"Point"}
}