{
  "type": "Feature",
  "properties": {
    "addr:full":"728 Alabama St San Francisco CA 94110",
    "addr:housenumber":"728",
    "addr:postcode":"94110",
    "addr:street":"Alabama St",
    "iso:country":"US",
    "sg:address":"728 Alabama St",
    "sg:city":"San Francisco",
    "sg:classifiers":[
        {
            "category":"Professional",
            "subcategory":"Advertising",
            "type":"Services"
        }
    ],
    "sg:phone":"+1 415 641 1565",
    "sg:postcode":"94110",
    "sg:province":"CA",
    "sg:tags":[
        "counselor"
    ],
    "wof:name":"Addict Inc",
    "wof:placetype":"venue"
},
  "geometry": {"coordinates":[-122.411683,37.759449],"type":"Point"}
}