{
  "type": "Feature",
  "properties": {
    "iso:country":"US",
    "sg:address":"30619 Romero Canyon Rd",
    "sg:city":"Castaic",
    "sg:classifiers":[
        {
            "category":"Building & Trades",
            "subcategory":"Plumbing",
            "type":"Services"
        }
    ],
    "sg:phone":"+1 661 296 1486",
    "sg:postcode":"91384",
    "sg:province":"CA",
    "wof:name":"Service Pro Plumbing & Heating",
    "wof:placetype":"venue"
},
  "geometry": {"coordinates":[-118.660527,34.473613],"type":"Point"}
}