{
  "type": "Feature",
  "properties": {
    "iso:country":"US",
    "sg:address":"9410 Topanga Canyon Blvd",
    "sg:city":"Chatsworth",
    "sg:classifiers":[
        {
            "category":"Manufacturing",
            "subcategory":"Electronics",
            "type":"Manufacturing & Wholesale Goods"
        }
    ],
    "sg:phone":"+1 818 718 4100",
    "sg:postcode":"91311",
    "sg:province":"CA",
    "sg:tags":[
        "equipment",
        "electronic",
        "supply"
    ],
    "wof:name":"Stock Point",
    "wof:placetype":"venue"
},
  "geometry": {"coordinates":[-118.60593,34.239872],"type":"Point"}
}