{
  "type": "Feature",
  "properties": {
    "iso:country":"US",
    "sg:address":"120 E Remington Drive",
    "sg:city":"Sunnyvale",
    "sg:classifiers":[
        {
            "category":"Real Estate",
            "subcategory":"Real Estate Operator",
            "type":"Services"
        }
    ],
    "sg:phone":"+1 408 738 1114",
    "sg:postcode":"94087",
    "sg:province":"CA",
    "sg:tags":[
        "apartment"
    ],
    "wof:name":"Remington Arms Apartments",
    "wof:placetype":"venue"
},
  "geometry": {"coordinates":[-122.029854,37.349254],"type":"Point"}
}