{
  "type": "Feature",
  "properties": {
    "addr:full":"513 Baypointe Dr Newport Beach CA 92660",
    "addr:housenumber":"513",
    "addr:postcode":"92660",
    "addr:street":"Baypointe Dr",
    "iso:country":"US",
    "sg:address":"513 Baypointe Dr",
    "sg:city":"Newport Beach",
    "sg:classifiers":[
        {
            "category":"Shopping",
            "subcategory":"Catalog Store",
            "type":"Retail Goods"
        }
    ],
    "sg:phone":"+1 949 706 9383",
    "sg:postcode":"92660",
    "sg:province":"CA",
    "sg:tags":[
        "e"
    ],
    "wof:name":"Razor Reef",
    "wof:placetype":"venue"
},
  "geometry": {"coordinates":[-117.86448,33.649632],"type":"Point"}
}