{
  "type": "Feature",
  "properties": {
    "iso:country":"US",
    "sg:address":"627 Broadway St",
    "sg:city":"Chico",
    "sg:classifiers":[
        {
            "category":"Building & Trades",
            "subcategory":"Landscaping Services",
            "type":"Services"
        }
    ],
    "sg:phone":"+1 530 899 1913",
    "sg:postcode":"95928",
    "sg:province":"CA",
    "sg:tags":[
        "architect",
        "landscape"
    ],
    "wof:name":"Land Image Ldscp Architects",
    "wof:placetype":"venue"
},
  "geometry": {"coordinates":[-121.83749899999999,39.726512],"type":"Point"}
}