{
  "type": "Feature",
  "properties": {
    "iso:country":"US",
    "sg:address":"5750 Ramirez Canyon Rd",
    "sg:city":"Malibu",
    "sg:classifiers":[
        {
            "category":"Recreation",
            "type":"Entertainment"
        }
    ],
    "sg:phone":"+1 310 589 3200",
    "sg:postcode":"90265",
    "sg:province":"CA",
    "sg:tags":[
        "parks"
    ],
    "wof:name":"Santa Monica Mountains",
    "wof:placetype":"venue"
},
  "geometry": {"coordinates":[-118.793233,34.036255],"type":"Point"}
}