{
  "type": "Feature",
  "properties": {
    "addr:full":"9833 Blue Larkspur Ln Monterey CA 93940",
    "addr:housenumber":"9833",
    "addr:postcode":"93940",
    "addr:street":"Blue Larkspur Ln",
    "iso:country":"US",
    "sg:address":"9833 Blue Larkspur Ln",
    "sg:city":"Monterey",
    "sg:classifiers":[
        {
            "category":"Health Services",
            "subcategory":"Doctor",
            "type":"Services"
        },
        {
            "category":"Banks & Credit Unions",
            "subcategory":"Investment Brokerage",
            "type":"Services"
        }
    ],
    "sg:phone":"+1 877 733 4483",
    "sg:postcode":"93940",
    "sg:province":"CA",
    "sg:tags":[
        "physician",
        "infertility",
        "reproductive",
        "endocrinology",
        "surgeons",
        "counseling",
        "surgeon"
    ],
    "sg:website":"http://www.montereybayivf.com",
    "wof:name":"Fertility & Gynecology Center - Monterey Bay IVF",
    "wof:placetype":"venue"
},
  "geometry": {"coordinates":[-121.802465,36.571173],"type":"Point"}
}