{
  "type": "Feature",
  "properties": {
    "addr:full":"451 W Foothill Blvd Glendora CA 91741",
    "addr:housenumber":"451",
    "addr:postcode":"91741",
    "addr:street":"W Foothill Blvd",
    "iso:country":"US",
    "sg:address":"451 W Foothill Blvd",
    "sg:city":"Glendora",
    "sg:classifiers":[
        {
            "category":"Personal",
            "subcategory":"Beauty Salon",
            "type":"Services"
        }
    ],
    "sg:phone":"+1 626 914 5879",
    "sg:postcode":"91741",
    "sg:province":"CA",
    "wof:name":"Rothman's Salon",
    "wof:placetype":"venue"
},
  "geometry": {"coordinates":[-117.8719,34.136031],"type":"Point"}
}