{
  "type": "Feature",
  "properties": {
    "addr:full":"17047 Zachary Rd Bakersfield CA 93308",
    "addr:housenumber":"17047",
    "addr:postcode":"93308",
    "addr:street":"Zachary Rd",
    "iso:country":"US",
    "sg:address":"17047 Zachary Rd",
    "sg:city":"Bakersfield",
    "sg:classifiers":[
        {
            "category":"Restaurant",
            "type":"Food & Drink"
        }
    ],
    "sg:phone":"+1 661 393 1990",
    "sg:postcode":"93308",
    "sg:province":"CA",
    "wof:name":"Denny's Restaurant 8571",
    "wof:placetype":"venue"
},
  "geometry": {"coordinates":[-119.186829,35.535925],"type":"Point"}
}