{
  "type": "Feature",
  "properties": {
    "iso:country":"US",
    "sg:address":"500 Cagney Ln",
    "sg:city":"Newport Beach",
    "sg:classifiers":[
        {
            "category":"Manufacturing",
            "subcategory":"Signs",
            "type":"Manufacturing & Wholesale Goods"
        }
    ],
    "sg:phone":"+1 949 645 6806",
    "sg:postcode":"92663",
    "sg:province":"CA",
    "sg:tags":[
        "specialty",
        "mfg"
    ],
    "wof:name":"Think Big Signs",
    "wof:placetype":"venue"
},
  "geometry": {"coordinates":[-117.933547,33.624883],"type":"Point"}
}