{
  "type": "Feature",
  "properties": {
    "addr:full":"210 Greenbush Ave Folsom CA 95630",
    "addr:housenumber":"210",
    "addr:postcode":"95630",
    "addr:street":"Greenbush Ave",
    "iso:country":"US",
    "sg:address":"210 Greenbush Ave",
    "sg:city":"Folsom",
    "sg:classifiers":[
        {
            "category":"Professional",
            "type":"Services"
        }
    ],
    "sg:phone":"+1 916 983 4284",
    "sg:postcode":"95630",
    "sg:province":"CA",
    "wof:name":"Katherine A Mettler",
    "wof:placetype":"venue"
},
  "geometry": {"coordinates":[-121.119027,38.673561],"type":"Point"}
}