{
  "type": "Feature",
  "properties": {
    "addr:full":"1843 34th Ave Oakland CA 94601",
    "addr:housenumber":"1843",
    "addr:postcode":"94601",
    "addr:street":"34Th Ave",
    "iso:country":"US",
    "sg:address":"1843 34th Ave",
    "sg:city":"Oakland",
    "sg:classifiers":[
        {
            "category":"Building & Trades",
            "subcategory":"Construction",
            "type":"Services"
        }
    ],
    "sg:phone":"+1 510 708 0441",
    "sg:postcode":"94601",
    "sg:province":"CA",
    "sg:tags":[
        "painter"
    ],
    "wof:name":"Rivera-Perez Painting",
    "wof:placetype":"venue"
},
  "geometry": {"coordinates":[-122.221062,37.782222],"type":"Point"}
}