{
  "type": "Feature",
  "properties": {
    "iso:country":"US",
    "sg:address":"238 Hospital Dr",
    "sg:city":"Ukiah",
    "sg:classifiers":[
        {
            "category":"Health Services",
            "subcategory":"Podiatrist",
            "type":"Services"
        }
    ],
    "sg:phone":"+1 707 463 3668",
    "sg:postcode":"95482",
    "sg:province":"CA",
    "wof:name":"Michael R Cosenza DPM",
    "wof:placetype":"venue"
},
  "geometry": {"coordinates":[-123.203875,39.152969],"type":"Point"}
}