{
  "type": "Feature",
  "properties": {
    "addr:full":"9171 Dalton Cir Westminster CA 92683",
    "addr:housenumber":"9171",
    "addr:postcode":"92683",
    "addr:street":"Dalton Cir",
    "iso:country":"US",
    "sg:address":"9171 Dalton Cir",
    "sg:city":"Westminster",
    "sg:classifiers":[
        {
            "category":"Shopping",
            "subcategory":"Gifts & Souvenirs",
            "type":"Retail Goods"
        }
    ],
    "sg:phone":"+1 714 914 0983",
    "sg:postcode":"92683",
    "sg:province":"CA",
    "wof:name":"Tus Gifts & Novelties",
    "wof:placetype":"venue"
},
  "geometry": {"coordinates":[-117.969127,33.738135],"type":"Point"}
}