{
  "type": "Feature",
  "properties": {
    "iso:country":"US",
    "sg:address":"33333 Lewis St",
    "sg:city":"Union City",
    "sg:classifiers":[
        {
            "category":"Building & Trades",
            "subcategory":"Construction",
            "type":"Services"
        }
    ],
    "sg:phone":"+1 510 475 9840",
    "sg:postcode":"94587",
    "sg:province":"CA",
    "sg:tags":[
        "fabricator",
        "metal"
    ],
    "wof:name":"Millspec Industries",
    "wof:placetype":"venue"
},
  "geometry": {"coordinates":[-122.03138800000001,37.600483],"type":"Point"}
}