{
  "type": "Feature",
  "properties": {
    "addr:full":"687 Dolphin Dr Danville CA 94526",
    "addr:housenumber":"687",
    "addr:postcode":"94526",
    "addr:street":"Dolphin Dr",
    "iso:country":"US",
    "sg:address":"687 Dolphin Dr",
    "sg:city":"Danville",
    "sg:classifiers":[
        {
            "category":"Real Estate",
            "subcategory":"Architect",
            "type":"Services"
        }
    ],
    "sg:phone":"+1 925 855 9164",
    "sg:postcode":"94526",
    "sg:province":"CA",
    "sg:tags":[
        "architects'",
        "specification",
        "builders'",
        "construction",
        "architectural",
        "engineer"
    ],
    "wof:name":"Steve Grote Architect",
    "wof:placetype":"venue"
},
  "geometry": {"coordinates":[-121.99615799999999,37.833483],"type":"Point"}
}