{
  "type": "Feature",
  "properties": {
    "addr:full":"1231 8th St Modesto CA 95354",
    "addr:housenumber":"1231",
    "addr:postcode":"ca 95354",
    "addr:street":"8Th St",
    "iso:country":"US",
    "sg:address":"1231 8th St",
    "sg:city":"Modesto",
    "sg:classifiers":[
        {
            "category":"Freight",
            "type":"Transportation"
        }
    ],
    "sg:phone":"+1 209 529 0294",
    "sg:postcode":"95354",
    "sg:province":"CA",
    "sg:tags":[
        "company",
        "moving"
    ],
    "wof:name":"Jensens Van & Storage",
    "wof:placetype":"venue"
},
  "geometry": {"coordinates":[-121.00540100000001,37.6416],"type":"Point"}
}