{
  "type": "Feature",
  "properties": {
    "addr:full":"8257 E Santa Ana Canyon Rd Anaheim CA 92808",
    "addr:housenumber":"8257",
    "addr:postcode":"92808",
    "addr:street":"E Santa Ana Canyon Rd",
    "iso:country":"US",
    "sg:address":"8257 E Santa Ana Canyon Rd",
    "sg:city":"Anaheim",
    "sg:classifiers":[
        {
            "category":"Restaurant",
            "type":"Food & Drink"
        }
    ],
    "sg:phone":"+1 714 283 3300",
    "sg:postcode":"92808",
    "sg:province":"CA",
    "sg:tags":[
        "sushi",
        "bar",
        "japanese"
    ],
    "wof:name":"House of Teriyaki",
    "wof:placetype":"venue"
},
  "geometry": {"coordinates":[-117.74511800000001,33.867283],"type":"Point"}
}