{
  "type": "Feature",
  "properties": {
    "addr:full":"8581 Santa Monica Blvd Ste 107 West Hollywood CA 90069",
    "addr:housenumber":"8581",
    "addr:postcode":"90069",
    "addr:street":"Santa Monica Blvd Ste 107",
    "iso:country":"US",
    "sg:address":"8581 Santa Monica Blvd Ste 107",
    "sg:city":"West Hollywood",
    "sg:classifiers":[
        {
            "category":"Personal",
            "type":"Services"
        }
    ],
    "sg:phone":"+1 877 465 5668",
    "sg:postcode":"90069",
    "sg:province":"CA",
    "sg:tags":[
        "mover"
    ],
    "sg:website":"www.pinkmoving.com",
    "wof:name":"Pink Moving",
    "wof:placetype":"venue"
},
  "geometry": {"coordinates":[-118.37823899999999,34.088526],"type":"Point"}
}