{
  "type": "Feature",
  "properties": {
    "addr:full":"4373 Convoy Street San Diego CA 92111",
    "addr:housenumber":"4373",
    "addr:postcode":"92111",
    "addr:street":"Convoy Street",
    "iso:country":"US",
    "sg:address":"4373 Convoy Street",
    "sg:city":"San Diego",
    "sg:classifiers":[
        {
            "category":"Restaurant",
            "type":"Food & Drink"
        }
    ],
    "sg:phone":"+1 858 268 0835",
    "sg:postcode":"92111",
    "sg:province":"CA",
    "wof:name":"Go Ba Woo Restaurant",
    "wof:placetype":"venue"
},
  "geometry": {"coordinates":[-117.155169,32.819709],"type":"Point"}
}