{
  "type": "Feature",
  "properties": {
    "addr:full":"16 Morning Sun Ave Mill Valley CA 94941",
    "addr:housenumber":"16",
    "addr:postcode":"94941",
    "addr:street":"Morning Sun Ave",
    "iso:country":"US",
    "sg:address":"16 Morning Sun Ave",
    "sg:city":"Mill Valley",
    "sg:classifiers":[
        {
            "category":"Personal",
            "type":"Services"
        }
    ],
    "sg:phone":"+1 415 388 4922",
    "sg:postcode":"94941",
    "sg:province":"CA",
    "sg:tags":[
        "control",
        "weight"
    ],
    "wof:name":"4 Life Research Indpndnt Distr",
    "wof:placetype":"venue"
},
  "geometry": {"coordinates":[-122.53316100000001,37.890539],"type":"Point"}
}