{
  "type": "Feature",
  "properties": {
    "addr:full":"572 N Lincoln Ave Fullerton CA 92831",
    "addr:housenumber":"572",
    "addr:postcode":"92831",
    "addr:street":"N Lincoln Ave",
    "iso:country":"US",
    "sg:address":"572 N Lincoln Ave",
    "sg:city":"Fullerton",
    "sg:classifiers":[
        {
            "category":"Professional",
            "subcategory":"Management & Consulting",
            "type":"Services"
        }
    ],
    "sg:phone":"+1 714 871 3644",
    "sg:postcode":"92831",
    "sg:province":"CA",
    "sg:tags":[
        "educational"
    ],
    "wof:name":"Edgar J Elliston",
    "wof:placetype":"venue"
},
  "geometry": {"coordinates":[-117.910881,33.875328],"type":"Point"}
}