{
  "type": "Feature",
  "properties": {
    "iso:country":"US",
    "sg:address":"5116 E Beverly Boulevard",
    "sg:city":"Los Angeles",
    "sg:classifiers":[
        {
            "category":"Restaurant",
            "type":"Food & Drink"
        }
    ],
    "sg:phone":"+1 323 268 9893",
    "sg:postcode":"90022",
    "sg:province":"CA",
    "wof:name":"Los Molcajetes",
    "wof:placetype":"venue"
},
  "geometry": {"coordinates":[-118.155244,34.032929],"type":"Point"}
}