{
  "type": "Feature",
  "properties": {
    "iso:country":"US",
    "sg:address":"22837 Ventura Blvd Ste 300",
    "sg:city":"Woodland Hills",
    "sg:classifiers":[
        {
            "category":"Real Estate",
            "subcategory":"Real Estate Services",
            "type":"Services"
        }
    ],
    "sg:phone":"+1 818 225 5800",
    "sg:postcode":"91364",
    "sg:province":"CA",
    "sg:website":"www.panorexcommercial.com",
    "wof:name":"Panorex Commercial",
    "wof:placetype":"venue"
},
  "geometry": {"coordinates":[-118.624602,34.165945],"type":"Point"}
}