{
  "type": "Feature",
  "properties": {
    "iso:country":"US",
    "sg:address":"830 S Hill St",
    "sg:city":"Los Angeles",
    "sg:classifiers":[
        {
            "category":"Wholesale",
            "subcategory":"Apparel",
            "type":"Manufacturing & Wholesale Goods"
        }
    ],
    "sg:phone":"+1 213 614 0832",
    "sg:postcode":"90014",
    "sg:province":"CA",
    "wof:name":"Sunny Fashion Inc",
    "wof:placetype":"venue"
},
  "geometry": {"coordinates":[-118.256726,34.04342],"type":"Point"}
}