{
  "type": "Feature",
  "properties": {
    "addr:full":"636 Emory St Imperial Beach CA 91932",
    "addr:housenumber":"636",
    "addr:postcode":"91932",
    "addr:street":"Emory St",
    "iso:country":"US",
    "sg:address":"636 Emory St",
    "sg:city":"Imperial Beach",
    "sg:classifiers":[
        {
            "category":"Real Estate",
            "subcategory":"Real Estate Agent",
            "type":"Services"
        }
    ],
    "sg:phone":"+1 619 423 6760",
    "sg:postcode":"91932",
    "sg:province":"CA",
    "wof:name":"Scheck Realty Inc",
    "wof:placetype":"venue"
},
  "geometry": {"coordinates":[-117.113141,32.583962],"type":"Point"}
}