{
  "type": "Feature",
  "properties": {
    "iso:country":"US",
    "sg:address":"2902 N Pacific Ave",
    "sg:city":"Stockton",
    "sg:classifiers":[
        {
            "category":"Professional",
            "subcategory":"Advertising",
            "type":"Services"
        }
    ],
    "sg:phone":"+1 209 948 4343",
    "sg:postcode":"95204",
    "sg:province":"CA",
    "sg:tags":[
        "counselor"
    ],
    "sg:website":"www.fernandesadvertising.com",
    "wof:name":"Fernandes Advertising & Design",
    "wof:placetype":"venue"
},
  "geometry": {"coordinates":[-121.303845,37.976389],"type":"Point"}
}