{
  "type": "Feature",
  "properties": {
    "iso:country":"US",
    "sg:address":"114 E de la Guerra St",
    "sg:city":"Santa Barbara",
    "sg:classifiers":[
        {
            "category":"Professional",
            "subcategory":"Lawyer & Legal Services",
            "type":"Services"
        }
    ],
    "sg:phone":"+1 805 882 0026",
    "sg:postcode":"93101",
    "sg:province":"CA",
    "sg:tags":[
        "attorney"
    ],
    "wof:name":"Norma Bishop",
    "wof:placetype":"venue"
},
  "geometry": {"coordinates":[-119.69769599999999,34.421282],"type":"Point"}
}