{
  "type": "Feature",
  "properties": {
    "iso:country":"US",
    "sg:address":"288 Atlantic Ave",
    "sg:city":"Pittsburg",
    "sg:classifiers":[
        {
            "category":"Shopping",
            "subcategory":"Clothing, Apparel, & Fashions",
            "type":"Retail Goods"
        }
    ],
    "sg:phone":"+1 925 427 5276",
    "sg:postcode":"94565",
    "sg:province":"CA",
    "wof:name":"Rene's Fashion",
    "wof:placetype":"venue"
},
  "geometry": {"coordinates":[-121.890045,38.007661],"type":"Point"}
}