{
  "type": "Feature",
  "properties": {
    "iso:country":"US",
    "sg:address":"2367 High Mesa Dr",
    "sg:city":"Duarte",
    "sg:classifiers":[
        {
            "category":"Wholesale",
            "subcategory":"Furniture",
            "type":"Manufacturing & Wholesale Goods"
        }
    ],
    "sg:phone":"+1 626 359 7637",
    "sg:postcode":"91008",
    "sg:province":"CA",
    "wof:name":"V S Seating & Assoc",
    "wof:placetype":"venue"
},
  "geometry": {"coordinates":[-117.955055,34.154741],"type":"Point"}
}