{
  "type": "Feature",
  "properties": {
    "iso:country":"US",
    "sg:address":"812 Foxglove Ct",
    "sg:city":"Newman",
    "sg:classifiers":[
        {
            "category":"Building & Trades",
            "subcategory":"Construction",
            "type":"Services"
        }
    ],
    "sg:phone":"+1 209 862 0267",
    "sg:postcode":"95360",
    "sg:province":"CA",
    "sg:tags":[
        "drywall",
        "contractor"
    ],
    "wof:name":"Advance Drywall",
    "wof:placetype":"venue"
},
  "geometry": {"coordinates":[-121.020853,37.31982],"type":"Point"}
}