{
  "type": "Feature",
  "properties": {
    "addr:full":"72601 Thrush Dr Palm Desert CA 92260",
    "addr:postcode":"72601;ca 92260",
    "addr:street":"Thrush Dr",
    "iso:country":"US",
    "sg:address":"72601 Thrush Dr",
    "sg:city":"Palm Desert",
    "sg:classifiers":[
        {
            "category":"Professional",
            "type":"Services"
        }
    ],
    "sg:phone":"+1 760 346 6467",
    "sg:postcode":"92260",
    "sg:province":"CA",
    "wof:name":"Agua Fera",
    "wof:placetype":"venue"
},
  "geometry": {"coordinates":[-116.396725,33.705536],"type":"Point"}
}