{
  "type": "Feature",
  "properties": {
    "iso:country":"US",
    "sg:address":"85 Moreland Rd",
    "sg:city":"Simi Valley",
    "sg:classifiers":[
        {
            "category":"Wholesale",
            "subcategory":"Electrical",
            "type":"Manufacturing & Wholesale Goods"
        }
    ],
    "sg:phone":"+1 650 583 5290",
    "sg:postcode":"93065",
    "sg:province":"CA",
    "sg:tags":[
        "equipment",
        "testing",
        "electronic"
    ],
    "wof:name":"Credence Systems Corp",
    "wof:placetype":"venue"
},
  "geometry": {"coordinates":[-118.797302,34.276546],"type":"Point"}
}