{
  "type": "Feature",
  "properties": {
    "addr:full":"1100 Clement Street San Francisco CA 94118",
    "addr:housenumber":"1100",
    "addr:postcode":"94118",
    "addr:street":"Clement Street",
    "iso:country":"US",
    "sg:address":"1100 Clement Street",
    "sg:city":"San Francisco",
    "sg:classifiers":[
        {
            "category":"Personal",
            "subcategory":"Beauty Salon",
            "type":"Services"
        }
    ],
    "sg:phone":"+1 415 387 2727",
    "sg:postcode":"94118",
    "sg:province":"CA",
    "sg:tags":[
        "hair"
    ],
    "wof:name":"Montage Hair Salon",
    "wof:placetype":"venue"
},
  "geometry": {"coordinates":[-122.471001,37.7827],"type":"Point"}
}