{
  "type": "Feature",
  "properties": {
    "iso:country":"US",
    "sg:address":"3100 Summit St",
    "sg:city":"Oakland",
    "sg:classifiers":[
        {
            "category":"Health Services",
            "subcategory":"Optometrist",
            "type":"Services"
        },
        {
            "category":"Shopping",
            "subcategory":"Optician",
            "type":"Retail Goods"
        },
        {
            "category":"Shopping",
            "subcategory":"Pharmacy",
            "type":"Retail Goods"
        }
    ],
    "sg:phone":"+1 510 893 3832",
    "sg:postcode":"94609",
    "sg:province":"CA",
    "sg:tags":[
        "drugstore",
        "eyewear"
    ],
    "sg:website":"www.pharmacare.com/SPECIALTY/",
    "wof:name":"Careplus Cvs pharmacy",
    "wof:placetype":"venue"
},
  "geometry": {"coordinates":[-122.264234,37.819933],"type":"Point"}
}