{
  "type": "Feature",
  "properties": {
    "addr:full":"701 17th Ave Santa Cruz CA 95062",
    "addr:housenumber":"701",
    "addr:postcode":"95062",
    "addr:street":"17Th Ave",
    "iso:country":"US",
    "sg:address":"701 17th Ave",
    "sg:city":"Santa Cruz",
    "sg:classifiers":[
        {
            "category":"Arts & Performance",
            "subcategory":"Theater",
            "type":"Entertainment"
        }
    ],
    "sg:phone":"+1 831 419 1135",
    "sg:postcode":"95062",
    "sg:province":"CA",
    "sg:tags":[
        "bureau"
    ],
    "wof:name":"Adventure Entertainment",
    "wof:placetype":"venue"
},
  "geometry": {"coordinates":[-121.986144,36.965811],"type":"Point"}
}