{
  "type": "Feature",
  "properties": {
    "iso:country":"US",
    "sg:address":"800 Jones St",
    "sg:city":"Berkeley",
    "sg:classifiers":[
        {
            "category":"Professional",
            "subcategory":"Computer Services",
            "type":"Services"
        }
    ],
    "sg:phone":"+1 510 559 8592",
    "sg:postcode":"94710",
    "sg:province":"CA",
    "sg:tags":[
        "prepackaged",
        "software",
        "custom"
    ],
    "wof:name":"Researchsoft",
    "wof:placetype":"venue"
},
  "geometry": {"coordinates":[-122.300066,37.875229],"type":"Point"}
}