{
  "type": "Feature",
  "properties": {
    "iso:country":"US",
    "sg:address":"836 N Ave 67",
    "sg:city":"Los Angeles",
    "sg:classifiers":[
        {
            "category":"Retail",
            "subcategory":"Animal Services",
            "type":"Services"
        }
    ],
    "sg:phone":"+1 323 255 1522",
    "sg:postcode":"90042",
    "sg:province":"CA",
    "wof:name":"Canines Best Behavior",
    "wof:placetype":"venue"
},
  "geometry": {"coordinates":[-118.17110700000001,34.120276],"type":"Point"}
}