{
  "type": "Feature",
  "properties": {
    "addr:full":"657 4th Ave San Francisco CA 94118",
    "addr:housenumber":"657",
    "addr:postcode":"94118",
    "addr:street":"4Th Ave",
    "iso:country":"US",
    "sg:address":"657 4th Ave",
    "sg:city":"San Francisco",
    "sg:classifiers":[
        {
            "category":"Professional",
            "type":"Services"
        }
    ],
    "sg:phone":"+1 415 876 3304",
    "sg:postcode":"94118",
    "sg:province":"CA",
    "wof:name":"Arnew Foundation",
    "wof:placetype":"venue"
},
  "geometry": {"coordinates":[-122.46186899999999,37.776528],"type":"Point"}
}