{
  "type": "Feature",
  "properties": {
    "iso:country":"US",
    "sg:address":"2335 Geysers Rd",
    "sg:city":"Geyserville",
    "sg:classifiers":[
        {
            "category":"Farming",
            "subcategory":"Livestock Farm",
            "type":"Manufacturing & Wholesale Goods"
        }
    ],
    "sg:phone":"+1 707 433 1294",
    "sg:postcode":"95441",
    "sg:province":"CA",
    "sg:tags":[
        "management",
        "animal",
        "general"
    ],
    "wof:name":"Garden Creek Ranch",
    "wof:placetype":"venue"
},
  "geometry": {"coordinates":[-122.83215800000001,38.695285],"type":"Point"}
}