{
  "type": "Feature",
  "properties": {
    "iso:country":"US",
    "sg:address":"51 Bresciani Ln",
    "sg:city":"Quincy",
    "sg:classifiers":[
        {
            "category":"Building & Trades",
            "subcategory":"Electrical",
            "type":"Services"
        },
        {
            "category":"Retail",
            "subcategory":"Auto Repair",
            "type":"Services"
        }
    ],
    "sg:phone":"+1 530 283 5555",
    "sg:postcode":"95971",
    "sg:province":"CA",
    "sg:tags":[
        "truck",
        "automobile",
        "electrician",
        "electric"
    ],
    "wof:name":"John's Automotive Electrical",
    "wof:placetype":"venue"
},
  "geometry": {"coordinates":[-120.914869,39.944086],"type":"Point"}
}