{
  "type": "Feature",
  "properties": {
    "iso:country":"US",
    "sg:address":"8960 Beech Ave",
    "sg:city":"Fontana",
    "sg:classifiers":[
        {
            "category":"Manufacturing",
            "subcategory":"Metals",
            "type":"Manufacturing & Wholesale Goods"
        }
    ],
    "sg:phone":"+1 909 823 6791",
    "sg:postcode":"92335",
    "sg:province":"CA",
    "sg:tags":[
        "wire",
        "mfg"
    ],
    "wof:name":"Wire Tech",
    "wof:placetype":"venue"
},
  "geometry": {"coordinates":[-117.47122,34.091582],"type":"Point"}
}