{
  "type": "Feature",
  "properties": {
    "addr:full":"5049 Blacksand Rd Fremont CA 94538",
    "addr:housenumber":"5049",
    "addr:postcode":"94538",
    "addr:street":"Blacksand Rd",
    "iso:country":"US",
    "sg:address":"5049 Blacksand Rd",
    "sg:city":"Fremont",
    "sg:classifiers":[
        {
            "category":"Taxi",
            "type":"Transportation"
        }
    ],
    "sg:phone":"+1 510 440 9999",
    "sg:postcode":"94538",
    "sg:province":"CA",
    "sg:tags":[
        "taxicab"
    ],
    "wof:name":"Yellow Cab",
    "wof:placetype":"venue"
},
  "geometry": {"coordinates":[-121.995535,37.532926],"type":"Point"}
}