{
  "type": "Feature",
  "properties": {
    "addr:full":"3630 Wilshire Blvd Los Angeles CA 90010",
    "addr:housenumber":"3630",
    "addr:postcode":"90010",
    "addr:street":"Wilshire Blvd",
    "iso:country":"US",
    "sg:address":"3630 Wilshire Blvd",
    "sg:city":"Los Angeles",
    "sg:classifiers":[
        {
            "category":"Restaurant",
            "type":"Food & Drink"
        }
    ],
    "sg:phone":"+1 213 385 7789",
    "sg:postcode":"90010",
    "sg:province":"CA",
    "sg:tags":[
        "korean"
    ],
    "wof:name":"Myung Dong Kyoja",
    "wof:placetype":"venue"
},
  "geometry": {"coordinates":[-118.304354,34.061321],"type":"Point"}
}