{
  "type": "Feature",
  "properties": {
    "iso:country":"US",
    "sg:address":"230 S Orange Ave",
    "sg:city":"Brea",
    "sg:classifiers":[
        {
            "category":"Health Services",
            "subcategory":"Dentist",
            "type":"Services"
        }
    ],
    "sg:phone":"+1 714 990 5414",
    "sg:postcode":"92821",
    "sg:province":"CA",
    "sg:tags":[
        "dentists-orthodontists"
    ],
    "sg:website":"http://www.breasmiles.com",
    "wof:name":"Tagawa & Curtis Orthodontics",
    "wof:placetype":"venue"
},
  "geometry": {"coordinates":[-117.89861000000001,33.917275],"type":"Point"}
}