{
  "type": "Feature",
  "properties": {
    "iso:country":"US",
    "sg:address":"4170 Eve Rd",
    "sg:city":"Simi Valley",
    "sg:classifiers":[
        {
            "category":"Building & Trades",
            "subcategory":"Landscaping Services",
            "type":"Services"
        }
    ],
    "sg:phone":"+1 805 526 0581",
    "sg:postcode":"93063",
    "sg:province":"CA",
    "wof:name":"Dka Landscape Constructio",
    "wof:placetype":"venue"
},
  "geometry": {"coordinates":[-118.709987,34.282525],"type":"Point"}
}