{
  "type": "Feature",
  "properties": {
    "iso:country":"US",
    "sg:address":"615 E Mariposa St",
    "sg:city":"Altadena",
    "sg:classifiers":[
        {
            "category":"Travel",
            "subcategory":"Campground",
            "type":"Entertainment"
        }
    ],
    "sg:phone":"+1 626 797 8312",
    "sg:postcode":"91001",
    "sg:province":"CA",
    "sg:tags":[
        "camp"
    ],
    "wof:name":"Girl Scouts",
    "wof:placetype":"venue"
},
  "geometry": {"coordinates":[-118.137066,34.189698],"type":"Point"}
}