{
  "type": "Feature",
  "properties": {
    "iso:country":"US",
    "sg:address":"38526 25th St E",
    "sg:city":"Palmdale",
    "sg:classifiers":[
        {
            "category":"Retail",
            "subcategory":"Animal Services",
            "type":"Services"
        }
    ],
    "sg:phone":"+1 661 618 9109",
    "sg:postcode":"93550",
    "sg:province":"CA",
    "sg:tags":[
        "pet",
        "grooming",
        "washing"
    ],
    "wof:name":"Kerri Green Pet Grooming",
    "wof:placetype":"venue"
},
  "geometry": {"coordinates":[-118.08506199999999,34.582312],"type":"Point"}
}