{
  "type": "Feature",
  "properties": {
    "addr:full":"5520 Scotts Valley Dr Scotts Valley CA 95066",
    "addr:housenumber":"5520",
    "addr:postcode":"95066",
    "addr:street":"Scotts Valley Dr",
    "iso:country":"US",
    "sg:address":"5520 Scotts Valley Dr",
    "sg:city":"Scotts Valley",
    "sg:classifiers":[
        {
            "category":"Restaurant",
            "type":"Food & Drink"
        }
    ],
    "sg:phone":"+1 831 461 0500",
    "sg:postcode":"95066",
    "sg:province":"CA",
    "sg:tags":[
        "caterer"
    ],
    "wof:name":"Bella's Catering",
    "wof:placetype":"venue"
},
  "geometry": {"coordinates":[-122.008651,37.060452],"type":"Point"}
}