{
  "type": "Feature",
  "properties": {
    "addr:full":"1060 Valley View Dr Quincy CA 95971",
    "addr:housenumber":"1060",
    "addr:postcode":"95971",
    "addr:street":"Valley View Dr",
    "iso:country":"US",
    "sg:address":"1060 Valley View Dr",
    "sg:city":"Quincy",
    "sg:classifiers":[
        {
            "category":"Health Services",
            "subcategory":"Hospital",
            "type":"Services"
        }
    ],
    "sg:phone":"+1 530 283 1322",
    "sg:postcode":"95971",
    "sg:province":"CA",
    "wof:name":"Plumas District Hospital",
    "wof:placetype":"venue"
},
  "geometry": {"coordinates":[-120.961071,39.940447],"type":"Point"}
}