{
  "type": "Feature",
  "properties": {
    "addr:full":"1560 Commerce St Corona CA 92880",
    "addr:housenumber":"1560",
    "addr:postcode":"92880",
    "addr:street":"Commerce St",
    "iso:country":"US",
    "sg:address":"1560 Commerce St",
    "sg:city":"Corona",
    "sg:classifiers":[
        {
            "category":"Wholesale",
            "subcategory":"Electrical",
            "type":"Manufacturing & Wholesale Goods"
        }
    ],
    "sg:phone":"+1 951 736 3530",
    "sg:postcode":"92880",
    "sg:province":"CA",
    "sg:tags":[
        "battery",
        "equipment",
        "primary",
        "mfg"
    ],
    "sg:website":"www.odysseybatteries.com",
    "wof:name":"West Coast Batteries",
    "wof:placetype":"venue"
},
  "geometry": {"coordinates":[-117.595461,33.885359],"type":"Point"}
}