{
  "type": "Feature",
  "properties": {
    "addr:full":"8300 Station Village Ln Ste 8 San Diego CA 92108",
    "addr:housenumber":"8300",
    "addr:postcode":"92108",
    "addr:street":"Station Village Ln Ste 8",
    "iso:country":"US",
    "sg:address":"8300 Station Village Ln Ste 8",
    "sg:city":"San Diego",
    "sg:classifiers":[
        {
            "category":"Real Estate",
            "subcategory":"Real Estate Services",
            "type":"Services"
        }
    ],
    "sg:phone":"+1 619 726 7185",
    "sg:postcode":"92108",
    "sg:province":"CA",
    "sg:tags":[
        "management",
        "property"
    ],
    "sg:website":"www.MissionCenterProperties.com",
    "wof:name":"Mission Center Property Management",
    "wof:placetype":"venue"
},
  "geometry": {"coordinates":[-117.145886,32.773923],"type":"Point"}
}