{
  "type": "Feature",
  "properties": {
    "iso:country":"US",
    "sg:address":"1681 Shattuck Ave",
    "sg:city":"Berkeley",
    "sg:classifiers":[
        {
            "category":"Travel",
            "subcategory":"Campground",
            "type":"Entertainment"
        }
    ],
    "sg:phone":"+1 510 548 4800",
    "sg:postcode":"94709",
    "sg:province":"CA",
    "sg:tags":[
        "camp"
    ],
    "sg:website":"www.educationunlimited.com",
    "wof:name":"National Forensic Consortium",
    "wof:placetype":"venue"
},
  "geometry": {"coordinates":[-122.268982,37.877239],"type":"Point"}
}