{
  "type": "Feature",
  "properties": {
    "addr:full":"643 E University Dr Carson CA 90746",
    "addr:housenumber":"643",
    "addr:postcode":"90746",
    "addr:street":"E University Dr",
    "iso:country":"US",
    "sg:address":"643 E University Dr",
    "sg:city":"Carson",
    "sg:classifiers":[
        {
            "category":"Shopping",
            "subcategory":"Tobacco",
            "type":"Retail Goods"
        }
    ],
    "sg:phone":"+1 310 327 2317",
    "sg:postcode":"90746",
    "sg:province":"CA",
    "sg:tags":[
        "shop"
    ],
    "wof:name":"Cheap Tobacco",
    "wof:placetype":"venue"
},
  "geometry": {"coordinates":[-118.263645,33.858271],"type":"Point"}
}