{
  "type": "Feature",
  "properties": {
    "addr:full":"2705 Union Ave San Jose CA 95124",
    "addr:housenumber":"2705",
    "addr:postcode":"95124",
    "addr:street":"Union Ave",
    "iso:country":"US",
    "sg:address":"2705 Union Ave",
    "sg:city":"San Jose",
    "sg:classifiers":[
        {
            "category":"Bars & Pubs",
            "subcategory":"Sports Bar",
            "type":"Food & Drink"
        }
    ],
    "sg:phone":"+1 408 559 0904",
    "sg:postcode":"95124",
    "sg:province":"CA",
    "sg:website":"www.steviesbarandgrill.com",
    "wof:name":"Stevie's Bar and Grill",
    "wof:placetype":"venue"
},
  "geometry": {"coordinates":[-121.93284199999999,37.272322],"type":"Point"}
}