{
  "type": "Feature",
  "properties": {
    "addr:full":"1575 Gladstone Way Rohnert Park CA 94928",
    "addr:housenumber":"1575",
    "addr:postcode":"94928",
    "addr:street":"Gladstone Way",
    "iso:country":"US",
    "sg:address":"1575 Gladstone Way",
    "sg:city":"Rohnert Park",
    "sg:classifiers":[
        {
            "category":"Shopping",
            "subcategory":"Gifts & Souvenirs",
            "type":"Retail Goods"
        }
    ],
    "sg:phone":"+1 707 584 8144",
    "sg:postcode":"94928",
    "sg:province":"CA",
    "sg:tags":[
        "party",
        "supply"
    ],
    "wof:name":"Cosmo Jump",
    "wof:placetype":"venue"
},
  "geometry": {"coordinates":[-122.67837299999999,38.371906],"type":"Point"}
}