{
  "type": "Feature",
  "properties": {
    "addr:full":"1600 Rosecrans Ave Bldg 5A, Ste 100 Manhattan Beach CA 90266",
    "addr:housenumber":"1600;5a ste 100",
    "addr:postcode":"90266",
    "addr:street":"Rosecrans Ave Bldg",
    "iso:country":"US",
    "sg:address":"1600 Rosecrans Ave Bldg 5A, Ste 100",
    "sg:city":"Manhattan Beach",
    "sg:classifiers":[
        {
            "category":"Communications",
            "subcategory":"Film & Video Production",
            "type":"Services"
        }
    ],
    "sg:phone":"+1 310 727 2760",
    "sg:postcode":"90266",
    "sg:province":"CA",
    "sg:tags":[
        "video/film"
    ],
    "sg:website":"www.blueroompost.com",
    "wof:name":"Blue Room Post",
    "wof:placetype":"venue"
},
  "geometry": {"coordinates":[-118.383715,33.898828],"type":"Point"}
}