{
  "type": "Feature",
  "properties": {
    "iso:country":"US",
    "sg:address":"3214 W Slauson Ave",
    "sg:city":"Los Angeles",
    "sg:classifiers":[
        {
            "category":"Shopping",
            "subcategory":"Mobile Phones",
            "type":"Retail Goods"
        }
    ],
    "sg:phone":"+1 323 293 8310",
    "sg:postcode":"90043",
    "sg:province":"CA",
    "wof:name":"Boost Up Wireless Solutions",
    "wof:placetype":"venue"
},
  "geometry": {"coordinates":[-118.328542,33.988882],"type":"Point"}
}