{
  "type": "Feature",
  "properties": {
    "addr:full":"7375 Greenbush Ave North Hollywood CA 91605",
    "addr:housenumber":"7375",
    "addr:postcode":"91605",
    "addr:street":"Greenbush Ave",
    "iso:country":"US",
    "sg:address":"7375 Greenbush Ave",
    "sg:city":"North Hollywood",
    "sg:classifiers":[
        {
            "category":"Wholesale",
            "subcategory":"Durable Goods & Equipment",
            "type":"Manufacturing & Wholesale Goods"
        }
    ],
    "sg:phone":"+1 818 764 1449",
    "sg:postcode":"91605",
    "sg:province":"CA",
    "sg:tags":[
        "specialty",
        "mfg"
    ],
    "wof:name":"Golden State Neon",
    "wof:placetype":"venue"
},
  "geometry": {"coordinates":[-118.42632500000001,34.20539],"type":"Point"}
}