{
  "type": "Feature",
  "properties": {
    "addr:full":"1650 Zanker Rd San Jose CA 95134",
    "addr:housenumber":"1650",
    "addr:postcode":"95134",
    "addr:street":"Zanker Rd",
    "iso:country":"US",
    "sg:address":"1650 Zanker Rd",
    "sg:city":"San Jose",
    "sg:classifiers":[
        {
            "category":"Arts & Performance",
            "subcategory":"Theater",
            "type":"Entertainment"
        }
    ],
    "sg:phone":"+1 408 254 1014",
    "sg:postcode":"95134",
    "sg:province":"CA",
    "sg:tags":[
        "musician"
    ],
    "wof:name":"Promovenus",
    "wof:placetype":"venue"
},
  "geometry": {"coordinates":[-121.912024,37.372673],"type":"Point"}
}