{
  "type": "Feature",
  "properties": {
    "iso:country":"US",
    "sg:address":"494 Hawthorne Ave",
    "sg:city":"Oakland",
    "sg:classifiers":[
        {
            "category":"Health Services",
            "subcategory":"Chiropractor",
            "type":"Services"
        }
    ],
    "sg:phone":"+1 510 724 7799",
    "sg:postcode":"94609",
    "sg:province":"CA",
    "wof:name":"Horowitz Chiropractic",
    "wof:placetype":"venue"
},
  "geometry": {"coordinates":[-122.266998,37.821301],"type":"Point"}
}