{
  "type": "Feature",
  "properties": {
    "addr:full":"621 Los Robles Ct Danville CA 94526",
    "addr:housenumber":"621",
    "addr:postcode":"94526",
    "addr:street":"Los Robles Ct",
    "iso:country":"US",
    "sg:address":"621 Los Robles Ct",
    "sg:city":"Danville",
    "sg:classifiers":[
        {
            "category":"Banks & Credit Unions",
            "subcategory":"Bank",
            "type":"Services"
        }
    ],
    "sg:phone":"+1 925 743 4470",
    "sg:postcode":"94526",
    "sg:province":"CA",
    "sg:tags":[
        "loan",
        "real estate"
    ],
    "wof:name":"Valley Home Loans",
    "wof:placetype":"venue"
},
  "geometry": {"coordinates":[-121.960078,37.792628],"type":"Point"}
}