{
  "type": "Feature",
  "properties": {
    "addr:full":"414 N 12th St San Jose CA 95112",
    "addr:housenumber":"414",
    "addr:postcode":"95112",
    "addr:street":"N 12Th St",
    "iso:country":"US",
    "sg:address":"414 N 12th St",
    "sg:city":"San Jose",
    "sg:classifiers":[
        {
            "category":"Real Estate",
            "subcategory":"Real Estate Agent",
            "type":"Services"
        }
    ],
    "sg:phone":"+1 408 295 8111",
    "sg:postcode":"95112",
    "sg:province":"CA",
    "wof:name":"Rembrandt Realty",
    "wof:placetype":"venue"
},
  "geometry": {"coordinates":[-121.88524099999999,37.350008],"type":"Point"}
}