{
  "type": "Feature",
  "properties": {
    "iso:country":"US",
    "sg:address":"1103 Sutton Way",
    "sg:city":"Grass Valley",
    "sg:classifiers":[
        {
            "category":"Insurance",
            "subcategory":"Title Insurance",
            "type":"Services"
        }
    ],
    "sg:phone":"+1 530 272 2283",
    "sg:postcode":"95945",
    "sg:province":"CA",
    "sg:website":"www.firstam.com",
    "wof:name":"First American Title Co",
    "wof:placetype":"venue"
},
  "geometry": {"coordinates":[-121.034296,39.226153],"type":"Point"}
}