{
  "type": "Feature",
  "properties": {
    "iso:country":"US",
    "sg:address":"6545 Sunrise Blvd",
    "sg:city":"Citrus Heights",
    "sg:classifiers":[
        {
            "category":"Professional",
            "subcategory":"Management & Consulting",
            "type":"Services"
        }
    ],
    "sg:phone":"+1 916 669 0508",
    "sg:postcode":"95610",
    "sg:province":"CA",
    "sg:tags":[
        "personnel",
        "consultant"
    ],
    "wof:name":"Valley Health Care Systems",
    "wof:placetype":"venue"
},
  "geometry": {"coordinates":[-121.2717,38.685152],"type":"Point"}
}