{
  "type": "Feature",
  "properties": {
    "iso:country":"US",
    "sg:address":"5897 Butler Rd",
    "sg:city":"Penryn",
    "sg:classifiers":[
        {
            "category":"Building & Trades",
            "subcategory":"Construction",
            "type":"Services"
        }
    ],
    "sg:phone":"+1 916 663 4741",
    "sg:postcode":"95663",
    "sg:province":"CA",
    "sg:tags":[
        "concrete",
        "contractor"
    ],
    "wof:name":"Allied West Construction",
    "wof:placetype":"venue"
},
  "geometry": {"coordinates":[-121.197455,38.859538],"type":"Point"}
}