{
  "type": "Feature",
  "properties": {
    "addr:full":"723 Bluebonnet Ct Thousand Oaks CA 91360",
    "addr:housenumber":"723",
    "addr:postcode":"91360",
    "addr:street":"Bluebonnet Ct",
    "iso:country":"US",
    "sg:address":"723 Bluebonnet Ct",
    "sg:city":"Thousand Oaks",
    "sg:classifiers":[
        {
            "category":"Real Estate",
            "subcategory":"Real Estate Agent",
            "type":"Services"
        }
    ],
    "sg:phone":"+1 805 492 5991",
    "sg:postcode":"91360",
    "sg:province":"CA",
    "wof:name":"Thousand Oaks Properties",
    "wof:placetype":"venue"
},
  "geometry": {"coordinates":[-118.892179,34.221605],"type":"Point"}
}