{
  "type": "Feature",
  "properties": {
    "addr:full":"1820 Solano Ave Ste C2 Berkeley CA 94707",
    "addr:housenumber":"1820",
    "addr:postcode":"94707",
    "addr:street":"Solano Ave Ste C2",
    "iso:country":"US",
    "sg:address":"1820 Solano Ave Ste C2",
    "sg:city":"Berkeley",
    "sg:classifiers":[
        {
            "category":"Shopping",
            "subcategory":"Jewelry",
            "type":"Retail Goods"
        },
        {
            "category":"Home & Garden",
            "subcategory":"Home Furnishings",
            "type":"Retail Goods"
        },
        {
            "category":"Shopping",
            "subcategory":"Antiques",
            "type":"Retail Goods"
        }
    ],
    "sg:phone":"+1 510 559 3229",
    "sg:postcode":"94707",
    "sg:province":"CA",
    "sg:tags":[
        "decor"
    ],
    "sg:website":"www.harmoniquehome.com",
    "wof:name":"Harmonique Home",
    "wof:placetype":"venue"
},
  "geometry": {"coordinates":[-122.2795,37.891343],"type":"Point"}
}