{
  "type": "Feature",
  "properties": {
    "iso:country":"US",
    "sg:address":"696 Crows Landing Rd",
    "sg:city":"Modesto",
    "sg:classifiers":[
        {
            "category":"Retail",
            "subcategory":"Auto Repair",
            "type":"Services"
        }
    ],
    "sg:phone":"+1 209 522 9996",
    "sg:postcode":"95351",
    "sg:province":"CA",
    "sg:tags":[
        "body",
        "shop",
        "painting",
        "automobile"
    ],
    "wof:name":"Federal Collision Center",
    "wof:placetype":"venue"
},
  "geometry": {"coordinates":[-120.99400300000001,37.620201],"type":"Point"}
}