{
  "type": "Feature",
  "properties": {
    "addr:full":"2203 S Bascom Ave Campbell CA 95008",
    "addr:housenumber":"2203",
    "addr:postcode":"95008",
    "addr:street":"S Bascom Ave",
    "iso:country":"US",
    "sg:address":"2203 S Bascom Ave",
    "sg:city":"Campbell",
    "sg:classifiers":[
        {
            "category":"Personal",
            "subcategory":"Barber",
            "type":"Services"
        }
    ],
    "sg:phone":"+1 408 879 9649",
    "sg:postcode":"95008",
    "sg:province":"CA",
    "wof:name":"Blackwell Forest Barbers",
    "wof:placetype":"venue"
},
  "geometry": {"coordinates":[-121.931769,37.282671],"type":"Point"}
}