{
  "type": "Feature",
  "properties": {
    "iso:country":"US",
    "sg:address":"15304 W Sunset Blvd",
    "sg:city":"Pacific Plsds",
    "sg:classifiers":[
        {
            "category":"Personal",
            "type":"Services"
        }
    ],
    "sg:phone":"+1 310 459 9394",
    "sg:postcode":"90272",
    "sg:province":"CA",
    "sg:tags":[
        "consultant",
        "program",
        "health",
        "fitness"
    ],
    "wof:name":"Body Aligned",
    "wof:placetype":"venue"
},
  "geometry": {"coordinates":[-118.526848,34.047933],"type":"Point"}
}