{
  "type": "Feature",
  "properties": {
    "iso:country":"US",
    "sg:address":"1500 Adams Ave",
    "sg:city":"Costa Mesa",
    "sg:classifiers":[
        {
            "category":"Health Services",
            "subcategory":"Clinic",
            "type":"Services"
        }
    ],
    "sg:phone":"+1 714 966 0770",
    "sg:postcode":"92626",
    "sg:province":"CA",
    "sg:tags":[
        "information",
        "dentist",
        "bureau"
    ],
    "wof:name":"Associated Group Dental Prctcs",
    "wof:placetype":"venue"
},
  "geometry": {"coordinates":[-117.92010999999999,33.67332],"type":"Point"}
}