{
  "type": "Feature",
  "properties": {
    "addr:full":"27540 Sierra Hwy Santa Clarita CA 91351",
    "addr:housenumber":"27540",
    "addr:postcode":"91351",
    "addr:street":"Sierra Hwy",
    "iso:country":"US",
    "sg:address":"27540 Sierra Hwy",
    "sg:city":"Santa Clarita",
    "sg:classifiers":[
        {
            "category":"Restaurant",
            "type":"Food & Drink"
        }
    ],
    "sg:phone":"+1 661 250 0029",
    "sg:postcode":"91351",
    "sg:province":"CA",
    "sg:tags":[
        "korean"
    ],
    "wof:name":"Tokyo Korean BBQ",
    "wof:placetype":"venue"
},
  "geometry": {"coordinates":[-118.456422,34.415005],"type":"Point"}
}