{
  "type": "Feature",
  "properties": {
    "iso:country":"US",
    "sg:address":"20409 Santa Maria Ave",
    "sg:city":"Castro Valley",
    "sg:classifiers":[
        {
            "category":"Shopping",
            "subcategory":"Books",
            "type":"Retail Goods"
        }
    ],
    "sg:phone":"+1 510 582 3311",
    "sg:postcode":"94546",
    "sg:province":"CA",
    "sg:tags":[
        "bookstore"
    ],
    "wof:name":"Avalon Books",
    "wof:placetype":"venue"
},
  "geometry": {"coordinates":[-122.078003,37.6968],"type":"Point"}
}