{
  "type": "Feature",
  "properties": {
    "addr:full":"107 S H St Lompoc CA 93436",
    "addr:housenumber":"107",
    "addr:postcode":"93436",
    "addr:street":"S H St",
    "iso:country":"US",
    "sg:address":"107 S H St",
    "sg:city":"Lompoc",
    "sg:classifiers":[
        {
            "category":"Shopping",
            "subcategory":"Books",
            "type":"Retail Goods"
        }
    ],
    "sg:phone":"+1 805 736 0797",
    "sg:postcode":"93436",
    "sg:province":"CA",
    "sg:tags":[
        "dealer"
    ],
    "wof:name":"Printed Matter Bookstore",
    "wof:placetype":"venue"
},
  "geometry": {"coordinates":[-120.45805,34.638504],"type":"Point"}
}