{
  "type": "Feature",
  "properties": {
    "addr:full":"931 Cll Negocio San Clemente CA 92673",
    "addr:housenumber":"931",
    "addr:postcode":"92673",
    "addr:street":"Cll Negocio",
    "iso:country":"US",
    "sg:address":"931 Cll Negocio",
    "sg:city":"San Clemente",
    "sg:classifiers":[
        {
            "category":"Manufacturing",
            "subcategory":"Motor Vehicles & Parts",
            "type":"Manufacturing & Wholesale Goods"
        }
    ],
    "sg:phone":"+1 949 492 2255",
    "sg:postcode":"92673",
    "sg:province":"CA",
    "sg:tags":[
        "fabricator",
        "bicycle"
    ],
    "wof:name":"Tri All 3 Sports",
    "wof:placetype":"venue"
},
  "geometry": {"coordinates":[-117.603708,33.453048],"type":"Point"}
}