{
  "type": "Feature",
  "properties": {
    "iso:country":"US",
    "sg:address":"525 Beamer St",
    "sg:city":"Woodland",
    "sg:classifiers":[
        {
            "category":"Education",
            "subcategory":"School",
            "type":"Public Place"
        }
    ],
    "sg:phone":"+1 530 662 1769",
    "sg:postcode":"95695",
    "sg:province":"CA",
    "wof:name":"Beamer Elementary School",
    "wof:placetype":"venue"
},
  "geometry": {"coordinates":[-121.774145,38.684784],"type":"Point"}
}