{
  "type": "Feature",
  "properties": {
    "addr:full":"3947 E Palm Ave Anaheim CA 92869",
    "addr:housenumber":"3947",
    "addr:postcode":"92869",
    "addr:street":"E Palm Ave",
    "iso:country":"US",
    "sg:address":"3947 E Palm Ave",
    "sg:city":"Anaheim",
    "sg:classifiers":[
        {
            "category":"Organizations",
            "subcategory":"Non-profit Organization",
            "type":"Services"
        }
    ],
    "sg:phone":"+1 714 632 9005",
    "sg:postcode":"92869",
    "sg:province":"CA",
    "sg:website":"www.miraclecenter.org",
    "wof:name":"Miracle Distribution Ctr",
    "wof:placetype":"venue"
},
  "geometry": {"coordinates":[-117.81438,33.792301],"type":"Point"}
}