{
  "type": "Feature",
  "properties": {
    "addr:full":"18918 Norwalk Blvd Artesia CA 90701",
    "addr:housenumber":"18918",
    "addr:postcode":"90701",
    "addr:street":"Norwalk Blvd",
    "iso:country":"US",
    "sg:address":"18918 Norwalk Blvd",
    "sg:city":"Artesia",
    "sg:classifiers":[
        {
            "category":"Restaurant",
            "type":"Food & Drink"
        }
    ],
    "sg:phone":"+1 562 468 1413",
    "sg:postcode":"90701",
    "sg:province":"CA",
    "wof:name":"Burger King",
    "wof:placetype":"venue"
},
  "geometry": {"coordinates":[-118.07199900000001,33.858799],"type":"Point"}
}