{
  "type": "Feature",
  "properties": {
    "iso:country":"US",
    "sg:address":"2170 S El Camino Real",
    "sg:city":"Oceanside",
    "sg:classifiers":[
        {
            "category":"Professional",
            "subcategory":"Lawyer & Legal Services",
            "type":"Services"
        }
    ],
    "sg:phone":"+1 760 721 4625",
    "sg:postcode":"92054",
    "sg:province":"CA",
    "sg:tags":[
        "divorce",
        "law",
        "family"
    ],
    "wof:name":"Marchant Kari M Attorney At Law",
    "wof:placetype":"venue"
},
  "geometry": {"coordinates":[-117.328003,33.187099],"type":"Point"}
}