{
  "type": "Feature",
  "properties": {
    "iso:country":"US",
    "sg:address":"19450 Plummer St",
    "sg:city":"Northridge",
    "sg:classifiers":[
        {
            "category":"Banks & Credit Unions",
            "subcategory":"Bank",
            "type":"Services"
        }
    ],
    "sg:phone":"+1 818 000 1111",
    "sg:postcode":"91324",
    "sg:province":"CA",
    "wof:name":"Cal National Bank",
    "wof:placetype":"venue"
},
  "geometry": {"coordinates":[-118.555204,34.242667],"type":"Point"}
}