{
  "type": "Feature",
  "properties": {
    "iso:country":"US",
    "sg:address":"303 Twin Dolphin Drive Suite 500",
    "sg:city":"Redwood City",
    "sg:classifiers":[
        {
            "category":"Professional",
            "subcategory":"Computer Services",
            "type":"Services"
        }
    ],
    "sg:phone":"+1 650 631 9800",
    "sg:postcode":"94065",
    "sg:province":"CA",
    "sg:website":"http://www.trionworlds.com",
    "wof:name":"Trion Worlds",
    "wof:placetype":"venue"
},
  "geometry": {"coordinates":[-122.259075,37.522038],"type":"Point"}
}