{
  "type": "Feature",
  "properties": {
    "addr:full":"53 Glen Rd Novato CA 94945",
    "addr:housenumber":"53",
    "addr:postcode":"94945",
    "addr:street":"Glen Rd",
    "iso:country":"US",
    "sg:address":"53 Glen Rd",
    "sg:city":"Novato",
    "sg:classifiers":[
        {
            "category":"Real Estate",
            "subcategory":"Real Estate Agent",
            "type":"Services"
        }
    ],
    "sg:phone":"+1 415 892 6544",
    "sg:postcode":"94945",
    "sg:province":"CA",
    "wof:name":"Tobin Real Estate",
    "wof:placetype":"venue"
},
  "geometry": {"coordinates":[-122.511149,38.109115],"type":"Point"}
}