{
  "type": "Feature",
  "properties": {
    "addr:full":"2000 Artesia Blvd Redondo Beach CA 90278",
    "addr:housenumber":"2000",
    "addr:postcode":"90278",
    "addr:street":"Artesia Blvd",
    "iso:country":"US",
    "sg:address":"2000 Artesia Blvd",
    "sg:city":"Redondo Beach",
    "sg:classifiers":[
        {
            "category":"Government",
            "subcategory":"Office",
            "type":"Public Place"
        }
    ],
    "sg:phone":"+1 310 318 0610",
    "sg:postcode":"90278",
    "sg:province":"CA",
    "sg:tags":[
        "village"
    ],
    "wof:name":"David K Hayward Ctr",
    "wof:placetype":"venue"
},
  "geometry": {"coordinates":[-118.374832,33.872831],"type":"Point"}
}