{
  "type": "Feature",
  "properties": {
    "iso:country":"US",
    "sg:address":"5460 College Ave",
    "sg:city":"Oakland",
    "sg:classifiers":[
        {
            "category":"Banks & Credit Unions",
            "subcategory":"Investment Brokerage",
            "type":"Services"
        }
    ],
    "sg:phone":"+1 510 658 2640",
    "sg:postcode":"94618",
    "sg:province":"CA",
    "sg:tags":[
        "accounting",
        "financial",
        "advisory"
    ],
    "sg:website":"http://www.calmuni.com",
    "wof:name":"California Municipal Statistics",
    "wof:placetype":"venue"
},
  "geometry": {"coordinates":[-122.25145000000001,37.841367],"type":"Point"}
}