{
  "type": "Feature",
  "properties": {
    "addr:full":"1445 Grand Ave Grover Beach CA 93433",
    "addr:housenumber":"1445",
    "addr:postcode":"93433",
    "addr:street":"Grand Ave",
    "iso:country":"US",
    "sg:address":"1445 Grand Ave",
    "sg:city":"Grover Beach",
    "sg:classifiers":[
        {
            "category":"Professional",
            "subcategory":"Engineering",
            "type":"Services"
        }
    ],
    "sg:phone":"+1 805 489 5268",
    "sg:postcode":"93433",
    "sg:province":"CA",
    "sg:tags":[
        "engineer"
    ],
    "wof:name":"Alan K Chesnutt Civil Engineer",
    "wof:placetype":"venue"
},
  "geometry": {"coordinates":[-120.61363299999999,35.121267],"type":"Point"}
}