{
  "type": "Feature",
  "properties": {
    "addr:full":"60 W Daily Dr Camarillo CA 93010",
    "addr:housenumber":"60",
    "addr:postcode":"93010",
    "addr:street":"W Daily Dr",
    "iso:country":"US",
    "sg:address":"60 W Daily Dr",
    "sg:city":"Camarillo",
    "sg:classifiers":[
        {
            "category":"Restaurant",
            "type":"Food & Drink"
        }
    ],
    "sg:menulink":"http://www.allmenus.com/ca/camarillo/216573-mcdonalds/menu/",
    "sg:postcode":"93010",
    "sg:province":"CA",
    "sg:tags":[
        "burger",
        "american"
    ],
    "wof:name":"McDonald's",
    "wof:placetype":"venue"
},
  "geometry": {"coordinates":[-119.07092,34.221433],"type":"Point"}
}