{
  "type": "Feature",
  "properties": {
    "iso:country":"US",
    "sg:address":"1313 E Pennsylvania Ave",
    "sg:city":"Redlands",
    "sg:classifiers":[
        {
            "category":"Wholesale",
            "subcategory":"Machinery & Supplies",
            "type":"Manufacturing & Wholesale Goods"
        }
    ],
    "sg:phone":"+1 909 793 8880",
    "sg:postcode":"92374",
    "sg:province":"CA",
    "sg:tags":[
        "equipment",
        "plastic"
    ],
    "wof:name":"Mold-Masters Systems",
    "wof:placetype":"venue"
},
  "geometry": {"coordinates":[-117.159094,34.073774],"type":"Point"}
}