{
  "type": "Feature",
  "properties": {
    "iso:country":"US",
    "sg:address":"601 S Glenoaks Blvd",
    "sg:city":"Burbank",
    "sg:classifiers":[
        {
            "category":"Manufacturing",
            "subcategory":"Printing",
            "type":"Manufacturing & Wholesale Goods"
        }
    ],
    "sg:phone":"+1 818 569 4490",
    "sg:postcode":"91502",
    "sg:province":"CA",
    "sg:tags":[
        "bus",
        "manifold",
        "form"
    ],
    "wof:name":"Wallace",
    "wof:placetype":"venue"
},
  "geometry": {"coordinates":[-118.300388,34.17882],"type":"Point"}
}