{
  "type": "Feature",
  "properties": {
    "addr:full":"3204 Stine Rd Bakersfield CA 93309",
    "addr:housenumber":"3204",
    "addr:postcode":"93309",
    "addr:street":"Stine Rd",
    "iso:country":"US",
    "sg:address":"3204 Stine Rd",
    "sg:city":"Bakersfield",
    "sg:classifiers":[
        {
            "category":"Health Services",
            "subcategory":"Doctor",
            "type":"Services"
        }
    ],
    "sg:phone":"+1 661 836 8999",
    "sg:postcode":"93309",
    "sg:province":"CA",
    "sg:tags":[
        "physician",
        "surgeon"
    ],
    "wof:name":"Hwang, Dr Chiao",
    "wof:placetype":"venue"
},
  "geometry": {"coordinates":[-119.05658699999999,35.325914],"type":"Point"}
}