{
  "type": "Feature",
  "properties": {
    "iso:country":"US",
    "sg:address":"6263 Santa Monica Boulevard",
    "sg:city":"Los Angeles",
    "sg:classifiers":[
        {
            "category":"Shopping",
            "subcategory":"Shoes",
            "type":"Retail Goods"
        }
    ],
    "sg:phone":"+1 323 465 2197",
    "sg:postcode":"90038",
    "sg:province":"CA",
    "sg:tags":[
        "store"
    ],
    "wof:name":"Hollywood's Unique Boutique",
    "wof:placetype":"venue"
},
  "geometry": {"coordinates":[-118.326362,34.090651],"type":"Point"}
}