{
  "type": "Feature",
  "properties": {
    "addr:full":"53 E Walker St Orland CA 95963",
    "addr:housenumber":"53",
    "addr:postcode":"95963",
    "addr:street":"E Walker St",
    "iso:country":"US",
    "sg:address":"53 E Walker St",
    "sg:city":"Orland",
    "sg:classifiers":[
        {
            "category":"Restaurant",
            "type":"Food & Drink"
        }
    ],
    "sg:phone":"+1 530 865 1838",
    "sg:postcode":"95963",
    "sg:province":"CA",
    "wof:name":"Maple's Garden No 2",
    "wof:placetype":"venue"
},
  "geometry": {"coordinates":[-122.18617399999999,39.747463],"type":"Point"}
}