{
  "type": "Feature",
  "properties": {
    "addr:full":"2004 Rosemead Blvd South El Monte CA 91733",
    "addr:housenumber":"2004",
    "addr:postcode":"91733",
    "addr:street":"Rosemead Blvd",
    "iso:country":"US",
    "sg:address":"2004 Rosemead Blvd",
    "sg:city":"South El Monte",
    "sg:classifiers":[
        {
            "category":"Autos & Motor Vehicles",
            "subcategory":"Fuel & Gas Station",
            "type":"Retail Goods"
        }
    ],
    "sg:phone":"+1 626 444 0546",
    "sg:postcode":"91733",
    "sg:province":"CA",
    "wof:name":"ampm",
    "wof:placetype":"venue"
},
  "geometry": {"coordinates":[-118.403448,34.184638],"type":"Point"}
}