{
  "type": "Feature",
  "properties": {
    "iso:country":"US",
    "sg:address":"11698 San Marino Dr",
    "sg:city":"Rancho Cucamonga",
    "sg:classifiers":[
        {
            "category":"Wholesale",
            "subcategory":"Drugs",
            "type":"Manufacturing & Wholesale Goods"
        }
    ],
    "sg:phone":"+1 909 484 1400",
    "sg:postcode":"91730",
    "sg:province":"CA",
    "sg:tags":[
        "pharmaceutical",
        "product"
    ],
    "sg:website":"www.livingstonusa.com",
    "wof:name":"Ups Supply Chain",
    "wof:placetype":"venue"
},
  "geometry": {"coordinates":[-117.54603400000001,34.083368],"type":"Point"}
}