{
  "type": "Feature",
  "properties": {
    "iso:country":"US",
    "sg:address":"2039 S Janette Ln",
    "sg:city":"Anaheim",
    "sg:classifiers":[
        {
            "category":"Professional",
            "type":"Services"
        }
    ],
    "sg:phone":"+1 714 638 2567",
    "sg:postcode":"92802",
    "sg:province":"CA",
    "wof:name":"Graham 4u",
    "wof:placetype":"venue"
},
  "geometry": {"coordinates":[-117.928799,33.797186],"type":"Point"}
}