{
  "type": "Feature",
  "properties": {
    "addr:full":"4407 S Broadway Los Angeles CA 90037",
    "addr:housenumber":"4407",
    "addr:postcode":"90037",
    "addr:street":"S Broadway",
    "iso:country":"US",
    "sg:address":"4407 S Broadway",
    "sg:city":"Los Angeles",
    "sg:classifiers":[
        {
            "category":"Shopping",
            "subcategory":"Clothing, Apparel, & Fashions",
            "type":"Retail Goods"
        }
    ],
    "sg:phone":"+1 323 846 0124",
    "sg:postcode":"90037",
    "sg:province":"CA",
    "sg:tags":[
        "infant",
        "wear"
    ],
    "wof:name":"Cyndy's Gift Shop",
    "wof:placetype":"venue"
},
  "geometry": {"coordinates":[-118.27841100000001,34.002941],"type":"Point"}
}