{
  "type": "Feature",
  "properties": {
    "addr:full":"101 Bernal Rd San Jose CA 95119",
    "addr:housenumber":"101",
    "addr:postcode":"95119",
    "addr:street":"Bernal Rd",
    "iso:country":"US",
    "sg:address":"101 Bernal Rd",
    "sg:city":"San Jose",
    "sg:classifiers":[
        {
            "category":"Autos & Motor Vehicles",
            "subcategory":"Fuel & Gas Station",
            "type":"Retail Goods"
        }
    ],
    "sg:phone":"+1 408 629 1849",
    "sg:postcode":"95119",
    "sg:province":"CA",
    "sg:tags":[
        "oil"
    ],
    "wof:name":"101 Bernal Shell Carwash",
    "wof:placetype":"venue"
},
  "geometry": {"coordinates":[-121.773737,37.230217],"type":"Point"}
}