{
  "type": "Feature",
  "properties": {
    "iso:country":"US",
    "sg:address":"456 Elm Ave",
    "sg:city":"Long Beach",
    "sg:classifiers":[
        {
            "category":"Bakery",
            "type":"Food & Drink"
        }
    ],
    "sg:phone":"+1 888 490 6688",
    "sg:postcode":"90802",
    "sg:province":"CA",
    "sg:website":"www.villagecookieshoppe.com",
    "wof:name":"Village Cookie Shoppe",
    "wof:placetype":"venue"
},
  "geometry": {"coordinates":[-118.187288,33.772744],"type":"Point"}
}