{
  "type": "Feature",
  "properties": {
    "addr:full":"57 S Oak St Ventura CA 93001",
    "addr:housenumber":"57",
    "addr:postcode":"93001",
    "addr:street":"S Oak St",
    "iso:country":"US",
    "sg:address":"57 S Oak St",
    "sg:city":"Ventura",
    "sg:classifiers":[
        {
            "category":"Travel",
            "subcategory":"Travel Agent",
            "type":"Entertainment"
        }
    ],
    "sg:phone":"+1 805 653 1911",
    "sg:postcode":"93001",
    "sg:province":"CA",
    "sg:tags":[
        "tour",
        "agency",
        "tours",
        "company",
        "promoter"
    ],
    "wof:name":"Lambert's Tours & Travel",
    "wof:placetype":"venue"
},
  "geometry": {"coordinates":[-119.29473299999999,34.280259],"type":"Point"}
}