{
  "type": "Feature",
  "properties": {
    "iso:country":"US",
    "sg:address":"17384 Colima Rd",
    "sg:city":"Rowland Heights",
    "sg:classifiers":[
        {
            "category":"Wholesale",
            "subcategory":"Jewelry",
            "type":"Manufacturing & Wholesale Goods"
        }
    ],
    "sg:phone":"+1 626 912 1929",
    "sg:postcode":"91748",
    "sg:province":"CA",
    "sg:tags":[
        "stone"
    ],
    "wof:name":"Castle Gems Company Inc",
    "wof:placetype":"venue"
},
  "geometry": {"coordinates":[-117.92483,33.990416],"type":"Point"}
}