{
  "type": "Feature",
  "properties": {
    "iso:country":"US",
    "sg:address":"20835 Nordhoff St",
    "sg:city":"Chatsworth",
    "sg:classifiers":[
        {
            "category":"Retail",
            "subcategory":"Auto Repair",
            "type":"Services"
        }
    ],
    "sg:phone":"+1 818 773 9636",
    "sg:postcode":"91311",
    "sg:province":"CA",
    "sg:tags":[
        "body",
        "automobile",
        "painting",
        "repairing"
    ],
    "wof:name":"Fusion Motorsports",
    "wof:placetype":"venue"
},
  "geometry": {"coordinates":[-118.58753900000001,34.235475],"type":"Point"}
}