{
  "type": "Feature",
  "properties": {
    "iso:country":"US",
    "sg:address":"89 Davis Rd",
    "sg:city":"Orinda",
    "sg:classifiers":[
        {
            "category":"Real Estate",
            "subcategory":"Real Estate Agent",
            "type":"Services"
        }
    ],
    "sg:phone":"+1 925 253 7000",
    "sg:postcode":"94563",
    "sg:province":"CA",
    "wof:name":"Intero Real Estate Svc",
    "wof:placetype":"venue"
},
  "geometry": {"coordinates":[-122.181687,37.879976],"type":"Point"}
}