{
  "type": "Feature",
  "properties": {
    "addr:full":"2400 Cement Hill Rd Fairfield CA 94533",
    "addr:housenumber":"2400",
    "addr:postcode":"94533",
    "addr:street":"Cement Hill Rd",
    "iso:country":"US",
    "sg:address":"2400 Cement Hill Rd",
    "sg:city":"Fairfield",
    "sg:classifiers":[
        {
            "category":"Retail",
            "subcategory":"Auto Repair",
            "type":"Services"
        }
    ],
    "sg:phone":"+1 707 437 5860",
    "sg:postcode":"94533",
    "sg:province":"CA",
    "sg:tags":[
        "wrecker"
    ],
    "wof:name":"A & D Towing Car Carrier",
    "wof:placetype":"venue"
},
  "geometry": {"coordinates":[-121.975076,38.287088],"type":"Point"}
}