{
  "type": "Feature",
  "properties": {
    "iso:country":"US",
    "sg:address":"2916 San Jose Ave",
    "sg:city":"Alameda",
    "sg:classifiers":[
        {
            "category":"Health Services",
            "subcategory":"Health Practitioner",
            "type":"Services"
        },
        {
            "category":"Communications",
            "type":"Services"
        }
    ],
    "sg:phone":"+1 510 814 0555",
    "sg:postcode":"94501",
    "sg:province":"CA",
    "sg:tags":[
        "pathologist",
        "speech-language",
        "myofunctional",
        "therapy"
    ],
    "sg:website":"http://www.diamondlanguage.com",
    "wof:name":"Susan Diamond Ma Ccc Slp",
    "wof:placetype":"venue"
},
  "geometry": {"coordinates":[-122.237595,37.756614],"type":"Point"}
}