{
  "type": "Feature",
  "properties": {
    "iso:country":"US",
    "sg:address":"13572 Carroll Way",
    "sg:city":"Tustin",
    "sg:classifiers":[
        {
            "category":"Real Estate",
            "subcategory":"Real Estate Operator",
            "type":"Services"
        }
    ],
    "sg:phone":"+1 714 838 4726",
    "sg:postcode":"92780",
    "sg:province":"CA",
    "sg:tags":[
        "apartment"
    ],
    "wof:name":"Gilbert Manors Apts",
    "wof:placetype":"venue"
},
  "geometry": {"coordinates":[-117.829672,33.766148],"type":"Point"}
}