{
  "type": "Feature",
  "properties": {
    "iso:country":"US",
    "sg:address":"700 Mill St",
    "sg:city":"Half Moon Bay",
    "sg:classifiers":[
        {
            "category":"Professional",
            "subcategory":"Management & Consulting",
            "type":"Services"
        }
    ],
    "sg:phone":"+1 650 726 3297",
    "sg:postcode":"94019",
    "sg:province":"CA",
    "sg:tags":[
        "marketing",
        "consultant"
    ],
    "sg:website":"www.cookingfearlessly.com",
    "wof:name":"Harter Communications",
    "wof:placetype":"venue"
},
  "geometry": {"coordinates":[-122.428159,37.464556],"type":"Point"}
}