{
  "type": "Feature",
  "properties": {
    "addr:full":"11824 1/2 Artesia Blvd Artesia CA 90701",
    "addr:housenumber":"11824 1 / 2",
    "addr:postcode":"90701",
    "addr:street":"Artesia Blvd",
    "iso:country":"US",
    "sg:address":"11824 1/2 Artesia Blvd",
    "sg:city":"Artesia",
    "sg:classifiers":[
        {
            "category":"Restaurant",
            "type":"Food & Drink"
        }
    ],
    "sg:phone":"+1 562 916 7849",
    "sg:postcode":"90701",
    "sg:province":"CA",
    "sg:tags":[
        "korean"
    ],
    "wof:name":"Arae Korean Restaurant",
    "wof:placetype":"venue"
},
  "geometry": {"coordinates":[-118.081502,33.872995],"type":"Point"}
}