{
  "type": "Feature",
  "properties": {
    "addr:full":"3460 Edward Ave Santa Clara CA 95054",
    "addr:housenumber":"3460",
    "addr:postcode":"95054",
    "addr:street":"Edward Ave",
    "iso:country":"US",
    "sg:address":"3460 Edward Ave",
    "sg:city":"Santa Clara",
    "sg:classifiers":[
        {
            "category":"Real Estate",
            "subcategory":"Developer",
            "type":"Services"
        }
    ],
    "sg:phone":"+1 408 330 0801",
    "sg:postcode":"95054",
    "sg:province":"CA",
    "sg:website":"www.geo-max.net",
    "wof:name":"Geomax",
    "wof:placetype":"venue"
},
  "geometry": {"coordinates":[-121.94241700000001,37.386994],"type":"Point"}
}