{
  "type": "Feature",
  "properties": {
    "addr:full":"4252 Tosca Rd Woodland Hills CA 91364",
    "addr:housenumber":"4252",
    "addr:postcode":"91364",
    "addr:street":"Tosca Rd",
    "iso:country":"US",
    "sg:address":"4252 Tosca Rd",
    "sg:city":"Woodland Hills",
    "sg:classifiers":[
        {
            "category":"Professional",
            "subcategory":"Lawyer & Legal Services",
            "type":"Services"
        }
    ],
    "sg:phone":"+1 818 702 0814",
    "sg:postcode":"91364",
    "sg:province":"CA",
    "sg:tags":[
        "attorney"
    ],
    "wof:name":"David E Frank",
    "wof:placetype":"venue"
},
  "geometry": {"coordinates":[-118.591207,34.147299],"type":"Point"}
}