{
  "type": "Feature",
  "properties": {
    "addr:full":"2996 Hyperion Ave Los Angeles CA 90027",
    "addr:housenumber":"2996",
    "addr:postcode":"90027",
    "addr:street":"Hyperion Ave",
    "iso:country":"US",
    "sg:address":"2996 Hyperion Ave",
    "sg:city":"Los Angeles",
    "sg:classifiers":[
        {
            "category":"Professional",
            "subcategory":"Secretarial Services",
            "type":"Services"
        }
    ],
    "sg:phone":"+1 310 275 2887",
    "sg:postcode":"90027",
    "sg:province":"CA",
    "sg:tags":[
        "editing"
    ],
    "wof:name":"Razor Edits",
    "wof:placetype":"venue"
},
  "geometry": {"coordinates":[-118.27005800000001,34.110544],"type":"Point"}
}