{
  "type": "Feature",
  "properties": {
    "addr:full":"20201 Charlanne Dr Redding CA 96002",
    "addr:housenumber":"20201",
    "addr:postcode":"96002",
    "addr:street":"Charlanne Dr",
    "iso:country":"US",
    "sg:address":"20201 Charlanne Dr",
    "sg:city":"Redding",
    "sg:classifiers":[
        {
            "category":"Wholesale",
            "subcategory":"Wine & Distilled Alcoholic Beverages",
            "type":"Manufacturing & Wholesale Goods"
        }
    ],
    "sg:phone":"+1 530 224 2221",
    "sg:postcode":"96002",
    "sg:province":"CA",
    "sg:tags":[
        "liquor"
    ],
    "wof:name":"Young's Market Co",
    "wof:placetype":"venue"
},
  "geometry": {"coordinates":[-122.30312499999999,40.54593],"type":"Point"}
}