{
  "type": "Feature",
  "properties": {
    "addr:full":"8857 Lubao Ave Northridge CA 91324",
    "addr:housenumber":"8857",
    "addr:postcode":"91324",
    "addr:street":"Lubao Ave",
    "iso:country":"US",
    "sg:address":"8857 Lubao Ave",
    "sg:city":"Northridge",
    "sg:classifiers":[
        {
            "category":"Building & Trades",
            "subcategory":"Construction",
            "type":"Services"
        }
    ],
    "sg:phone":"+1 818 885 7772",
    "sg:postcode":"91324",
    "sg:province":"CA",
    "sg:tags":[
        "contractor"
    ],
    "wof:name":"Interior & Exterior Remodeling",
    "wof:placetype":"venue"
},
  "geometry": {"coordinates":[-118.567899,34.231136],"type":"Point"}
}