{
  "type": "Feature",
  "properties": {
    "iso:country":"US",
    "sg:address":"170 E 17th Street Suite 214",
    "sg:city":"Costa Mesa",
    "sg:classifiers":[
        {
            "category":"Sports & Exercise",
            "subcategory":"Gym",
            "type":"Entertainment"
        }
    ],
    "sg:phone":"+1 949 642 7180",
    "sg:postcode":"92627",
    "sg:province":"CA",
    "sg:tags":[
        "trainer",
        "pilate"
    ],
    "wof:name":"Bodies In Balance",
    "wof:placetype":"venue"
},
  "geometry": {"coordinates":[-117.919905,33.636225],"type":"Point"}
}