{
  "type": "Feature",
  "properties": {
    "addr:full":"3429 Longview Dr Sacramento CA 95821",
    "addr:housenumber":"3429",
    "addr:postcode":"95821",
    "addr:street":"Longview Dr",
    "iso:country":"US",
    "sg:address":"3429 Longview Dr",
    "sg:city":"Sacramento",
    "sg:classifiers":[
        {
            "category":"Shopping",
            "type":"Retail Goods"
        }
    ],
    "sg:phone":"+1 916 485 8111",
    "sg:postcode":"95821",
    "sg:province":"CA",
    "sg:tags":[
        "equipment",
        "supply"
    ],
    "wof:name":"Delta Restaurant-Bar Equipment",
    "wof:placetype":"venue"
},
  "geometry": {"coordinates":[-121.383405,38.642293],"type":"Point"}
}