{
  "type": "Feature",
  "properties": {
    "iso:country":"US",
    "sg:address":"523 E Banning St",
    "sg:city":"Compton",
    "sg:classifiers":[
        {
            "category":"Manufacturing",
            "subcategory":"Wood Products",
            "type":"Manufacturing & Wholesale Goods"
        }
    ],
    "sg:phone":"+1 310 635 2664",
    "sg:postcode":"90222",
    "sg:province":"CA",
    "sg:tags":[
        "pallet",
        "skid"
    ],
    "wof:name":"S & M Pallet Inc",
    "wof:placetype":"venue"
},
  "geometry": {"coordinates":[-118.220525,33.918359],"type":"Point"}
}