{
  "type": "Feature",
  "properties": {
    "addr:full":"1398 Munras Ave Monterey CA 93940",
    "addr:housenumber":"1398",
    "addr:postcode":"93940",
    "addr:street":"Munras Ave",
    "iso:country":"US",
    "sg:address":"1398 Munras Ave",
    "sg:city":"Monterey",
    "sg:classifiers":[
        {
            "category":"Health Services",
            "subcategory":"Chiropractor",
            "type":"Services"
        }
    ],
    "sg:phone":"+1 831 375 2238",
    "sg:postcode":"93940",
    "sg:province":"CA",
    "sg:tags":[
        "chiropractic"
    ],
    "wof:name":"Randal Johnson Chiropractic",
    "wof:placetype":"venue"
},
  "geometry": {"coordinates":[-121.901779,36.583469],"type":"Point"}
}