{
  "type": "Feature",
  "properties": {
    "iso:country":"US",
    "sg:address":"300 West St",
    "sg:city":"Hollister",
    "sg:classifiers":[
        {
            "category":"Recreation",
            "type":"Entertainment"
        }
    ],
    "sg:phone":"+1 831 636 4390",
    "sg:postcode":"95023",
    "sg:province":"CA",
    "sg:tags":[
        "center"
    ],
    "wof:name":"Hollister City Recreation Dept",
    "wof:placetype":"venue"
},
  "geometry": {"coordinates":[-121.40562,36.853583],"type":"Point"}
}