{
  "type": "Feature",
  "properties": {
    "addr:full":"6450 E Parkcrest St Long Beach CA 90808",
    "addr:housenumber":"6450",
    "addr:postcode":"90808",
    "addr:street":"E;St",
    "iso:country":"US",
    "sg:address":"6450 E Parkcrest St",
    "sg:city":"Long Beach",
    "sg:classifiers":[
        {
            "category":"Professional",
            "type":"Services"
        }
    ],
    "sg:phone":"+1 562 421 0808",
    "sg:postcode":"90808",
    "sg:province":"CA",
    "sg:tags":[
        "establishment"
    ],
    "wof:name":"MSPS Novitiate",
    "wof:placetype":"venue"
},
  "geometry": {"coordinates":[-118.106272,33.830063],"type":"Point"}
}