{
  "type": "Feature",
  "properties": {
    "iso:country":"US",
    "sg:address":"542 Santa Fe Dr",
    "sg:city":"Encinitas",
    "sg:classifiers":[
        {
            "category":"Wholesale",
            "subcategory":"Fruits & Vegetables",
            "type":"Manufacturing & Wholesale Goods"
        }
    ],
    "sg:phone":"+1 760 783 0129",
    "sg:postcode":"92024",
    "sg:province":"CA",
    "sg:tags":[
        "veggie"
    ],
    "wof:name":"Encinitas 99C Plus Produce",
    "wof:placetype":"venue"
},
  "geometry": {"coordinates":[-117.279999,33.036098],"type":"Point"}
}