{
  "type": "Feature",
  "properties": {
    "iso:country":"US",
    "sg:address":"3800 Oceanic Dr # 101",
    "sg:city":"Oceanside",
    "sg:classifiers":[
        {
            "category":"Science Facility",
            "type":"Public Place"
        }
    ],
    "sg:phone":"+1 760 757 9739",
    "sg:postcode":"92056",
    "sg:province":"CA",
    "sg:tags":[
        "development",
        "laboratories-research"
    ],
    "wof:name":"Atomica",
    "wof:placetype":"venue"
},
  "geometry": {"coordinates":[-117.305328,33.205841],"type":"Point"}
}