{
  "type": "Feature",
  "properties": {
    "iso:country":"US",
    "sg:address":"895 B St",
    "sg:city":"Hayward",
    "sg:classifiers":[
        {
            "category":"Professional",
            "subcategory":"Advertising",
            "type":"Services"
        }
    ],
    "sg:phone":"+1 510 690 0200",
    "sg:postcode":"94541",
    "sg:province":"CA",
    "sg:tags":[
        "mailing",
        "shipping"
    ],
    "wof:name":"UPS Store",
    "wof:placetype":"venue"
},
  "geometry": {"coordinates":[-122.083878,37.672061],"type":"Point"}
}