{
  "type": "Feature",
  "properties": {
    "iso:country":"US",
    "sg:address":"1395 Broadway",
    "sg:city":"Sonoma",
    "sg:classifiers":[
        {
            "category":"Professional",
            "type":"Services"
        }
    ],
    "sg:phone":"+1 707 996 5407",
    "sg:postcode":"95476",
    "sg:province":"CA",
    "sg:tags":[
        "merchandise"
    ],
    "wof:name":"Brennie Brackett Studios",
    "wof:placetype":"venue"
},
  "geometry": {"coordinates":[-122.46017399999999,38.277017],"type":"Point"}
}