{
  "type": "Feature",
  "properties": {
    "addr:full":"530 S Santa Cruz Ave Modesto CA 95354",
    "addr:housenumber":"530",
    "addr:postcode":"ca 95354",
    "addr:street":"S Santa Cruz Ave",
    "iso:country":"US",
    "sg:address":"530 S Santa Cruz Ave",
    "sg:city":"Modesto",
    "sg:classifiers":[
        {
            "category":"Government",
            "subcategory":"Police Station",
            "type":"Public Place"
        }
    ],
    "sg:phone":"+1 209 558 8930",
    "sg:postcode":"95354",
    "sg:province":"CA",
    "sg:tags":[
        "sheriff"
    ],
    "wof:name":"Stanislaus County Sheriff Dept",
    "wof:placetype":"venue"
},
  "geometry": {"coordinates":[-120.974655,37.63155],"type":"Point"}
}