{
  "type": "Feature",
  "properties": {
    "addr:full":"6355 Peach Ave Van Nuys CA 91411",
    "addr:housenumber":"6355",
    "addr:postcode":"91411",
    "addr:street":"Peach Ave",
    "iso:country":"US",
    "sg:address":"6355 Peach Ave",
    "sg:city":"Van Nuys",
    "sg:classifiers":[
        {
            "category":"Professional",
            "type":"Services"
        }
    ],
    "sg:phone":"+1 818 906 9801",
    "sg:postcode":"91411",
    "sg:province":"CA",
    "wof:name":"Vera Armando",
    "wof:placetype":"venue"
},
  "geometry": {"coordinates":[-118.467555,34.183615],"type":"Point"}
}