{
  "type": "Feature",
  "properties": {
    "addr:full":"1468 Sun Manor Paradise CA 95969",
    "addr:housenumber":"1468",
    "addr:postcode":"95969",
    "addr:street":"Sun Manor",
    "iso:country":"US",
    "sg:address":"1468 Sun Manor",
    "sg:city":"Paradise",
    "sg:classifiers":[
        {
            "category":"Social Services",
            "subcategory":"Adult Care",
            "type":"Services"
        }
    ],
    "sg:phone":"+1 530 877 3363",
    "sg:postcode":"95969",
    "sg:province":"CA",
    "sg:tags":[
        "home",
        "residential"
    ],
    "wof:name":"Sunshine Cottage",
    "wof:placetype":"venue"
},
  "geometry": {"coordinates":[-121.590321,39.746988],"type":"Point"}
}