{
  "type": "Feature",
  "properties": {
    "addr:full":"3452 Corte Clarita Carlsbad CA 92009",
    "addr:housenumber":"3452",
    "addr:postcode":"92009",
    "addr:street":"Corte Clarita",
    "iso:country":"US",
    "sg:address":"3452 Corte Clarita",
    "sg:city":"Carlsbad",
    "sg:classifiers":[
        {
            "category":"Building & Trades",
            "subcategory":"Construction",
            "type":"Services"
        }
    ],
    "sg:phone":"+1 760 436 7931",
    "sg:postcode":"92009",
    "sg:province":"CA",
    "sg:tags":[
        "contractor"
    ],
    "wof:name":"Loyland Construction",
    "wof:placetype":"venue"
},
  "geometry": {"coordinates":[-117.230003,33.0676],"type":"Point"}
}