{
  "type": "Feature",
  "properties": {
    "iso:country":"US",
    "sg:address":"1591 24th Ave",
    "sg:city":"San Francisco",
    "sg:classifiers":[
        {
            "category":"Social Services",
            "subcategory":"Child Care",
            "type":"Services"
        }
    ],
    "sg:phone":"+1 415 731 7021",
    "sg:postcode":"94122",
    "sg:province":"CA",
    "sg:tags":[
        "day"
    ],
    "wof:name":"Family Day Care",
    "wof:placetype":"venue"
},
  "geometry": {"coordinates":[-122.48239100000001,37.757936],"type":"Point"}
}