{
  "type": "Feature",
  "properties": {
    "addr:full":"3425 S Bascom Ave Campbell CA 95008",
    "addr:housenumber":"3425",
    "addr:postcode":"95008",
    "addr:street":"S Bascom Ave",
    "iso:country":"US",
    "sg:address":"3425 S Bascom Ave",
    "sg:city":"Campbell",
    "sg:classifiers":[
        {
            "category":"Professional",
            "subcategory":"Art Services",
            "type":"Services"
        }
    ],
    "sg:phone":"+1 408 688 0400",
    "sg:postcode":"95008",
    "sg:province":"CA",
    "sg:tags":[
        "graphic",
        "designer"
    ],
    "wof:name":"Arlago Design & Communications",
    "wof:placetype":"venue"
},
  "geometry": {"coordinates":[-121.94395799999999,37.263066],"type":"Point"}
}