{
  "type": "Feature",
  "properties": {
    "addr:full":"427 Columbus Ave San Francisco CA 94133",
    "addr:housenumber":"427",
    "addr:postcode":"94133",
    "addr:street":"Columbus Ave",
    "iso:country":"US",
    "sg:address":"427 Columbus Ave",
    "sg:city":"San Francisco",
    "sg:classifiers":[
        {
            "category":"Home & Garden",
            "subcategory":"Home Furnishings",
            "type":"Retail Goods"
        }
    ],
    "sg:phone":"+1 415 982 7725",
    "sg:postcode":"94133",
    "sg:province":"CA",
    "sg:tags":[
        "cutlery"
    ],
    "wof:name":"Northbeach Cutlery",
    "wof:placetype":"venue"
},
  "geometry": {"coordinates":[-122.408823,37.799223],"type":"Point"}
}