{
  "type": "Feature",
  "properties": {
    "addr:full":"4582 Federal Blvd San Diego CA 92102",
    "addr:housenumber":"4582",
    "addr:postcode":"92102",
    "addr:street":"Federal Blvd",
    "iso:country":"US",
    "sg:address":"4582 Federal Blvd",
    "sg:city":"San Diego",
    "sg:classifiers":[
        {
            "category":"Shopping",
            "subcategory":"Beauty & Cosmetics",
            "type":"Retail Goods"
        },
        {
            "category":"Personal",
            "subcategory":"Beauty Salon",
            "type":"Services"
        }
    ],
    "sg:phone":"+1 619 253 8033",
    "sg:postcode":"92102",
    "sg:province":"CA",
    "sg:tags":[
        "aromatherapy"
    ],
    "wof:name":"Hot Toddies For The Body",
    "wof:placetype":"venue"
},
  "geometry": {"coordinates":[-117.09851999999999,32.721137],"type":"Point"}
}