{
  "type": "Feature",
  "properties": {
    "addr:full":"2969 Mesa Verde Dr E Costa Mesa CA 92626",
    "addr:housenumber":"2969",
    "addr:postcode":"92626",
    "addr:street":"Mesa Verde Dr E",
    "iso:country":"US",
    "sg:address":"2969 Mesa Verde Dr E",
    "sg:city":"Costa Mesa",
    "sg:classifiers":[
        {
            "category":"Education",
            "subcategory":"Library",
            "type":"Public Place"
        }
    ],
    "sg:phone":"+1 714 546 5274",
    "sg:postcode":"92626",
    "sg:province":"CA",
    "wof:name":"Public Library",
    "wof:placetype":"venue"
},
  "geometry": {"coordinates":[-117.92787300000001,33.678747],"type":"Point"}
}