{
  "type": "Feature",
  "properties": {
    "addr:full":"2570 Jason Ct Oceanside CA 92056",
    "addr:housenumber":"2570",
    "addr:postcode":"92056",
    "addr:street":"Jason Ct",
    "iso:country":"US",
    "sg:address":"2570 Jason Ct",
    "sg:city":"Oceanside",
    "sg:classifiers":[
        {
            "category":"Manufacturing",
            "subcategory":"Rubber & Plastics",
            "type":"Manufacturing & Wholesale Goods"
        }
    ],
    "sg:phone":"+1 760 940 6056",
    "sg:postcode":"92056",
    "sg:province":"CA",
    "wof:name":"Calpex Plastics Inc",
    "wof:placetype":"venue"
},
  "geometry": {"coordinates":[-117.265927,33.215904],"type":"Point"}
}