{
  "type": "Feature",
  "properties": {
    "addr:full":"5225 W Rosecrans Ave Hawthorne CA 90250",
    "addr:housenumber":"5225",
    "addr:postcode":"90250",
    "addr:street":"W Rosecrans Ave",
    "iso:country":"US",
    "sg:address":"5225 W Rosecrans Ave",
    "sg:city":"Hawthorne",
    "sg:classifiers":[
        {
            "category":"Arena",
            "subcategory":"Sports Club",
            "type":"Entertainment"
        }
    ],
    "sg:phone":"+1 310 536 9030",
    "sg:postcode":"90250",
    "sg:province":"CA",
    "sg:tags":[
        "martial art"
    ],
    "sg:website":"www.gbmanhattanbeach.com",
    "wof:name":"Gracie Barra Manhattan Beach",
    "wof:placetype":"venue"
},
  "geometry": {"coordinates":[-118.370386,33.901913],"type":"Point"}
}