{
  "type": "Feature",
  "properties": {
    "addr:full":"2552 F Street San Diego CA 92102",
    "addr:housenumber":"2552",
    "addr:postcode":"92102",
    "addr:street":"F Street",
    "iso:country":"US",
    "sg:address":"2552 F Street",
    "sg:city":"San Diego",
    "sg:classifiers":[
        {
            "category":"Professional",
            "subcategory":"Lawyer & Legal Services",
            "type":"Services"
        }
    ],
    "sg:phone":"+1 619 338 0643",
    "sg:postcode":"92102",
    "sg:province":"CA",
    "wof:name":"Jordan Jonathan Law Offices of",
    "wof:placetype":"venue"
},
  "geometry": {"coordinates":[-117.138997,32.71364],"type":"Point"}
}