{
  "type": "Feature",
  "properties": {
    "addr:full":"28918 Hancock Pkwy Valencia CA 91355",
    "addr:housenumber":"28918",
    "addr:postcode":"91355",
    "addr:street":"Hancock Pkwy",
    "iso:country":"US",
    "sg:address":"28918 Hancock Pkwy",
    "sg:city":"Valencia",
    "sg:classifiers":[
        {
            "category":"Home & Garden",
            "subcategory":"Carpets & Floor Coverings",
            "type":"Retail Goods"
        }
    ],
    "sg:phone":"+1 661 775 1911",
    "sg:postcode":"91355",
    "sg:province":"CA",
    "sg:tags":[
        "flooring"
    ],
    "sg:website":"www.leonardscarpetservice.com",
    "wof:name":"Leonard's Carpet Service",
    "wof:placetype":"venue"
},
  "geometry": {"coordinates":[-118.612379,34.443746],"type":"Point"}
}