{
  "type": "Feature",
  "properties": {
    "iso:country":"US",
    "sg:address":"1615 Bonanza St",
    "sg:city":"Walnut Creek",
    "sg:classifiers":[
        {
            "category":"Professional",
            "subcategory":"Employment Agencies",
            "type":"Services"
        }
    ],
    "sg:phone":"+1 925 256 0635",
    "sg:postcode":"94596",
    "sg:province":"CA",
    "sg:tags":[
        "opportunity"
    ],
    "sg:website":"www.dssc.com",
    "wof:name":"Data Systems Search Consultant",
    "wof:placetype":"venue"
},
  "geometry": {"coordinates":[-122.063345,37.899256],"type":"Point"}
}