{
  "type": "Feature",
  "properties": {
    "addr:full":"67 Technology Dr Irvine CA 92618",
    "addr:housenumber":"67",
    "addr:postcode":"92618",
    "addr:street":"Technology Dr",
    "iso:country":"US",
    "sg:address":"67 Technology Dr",
    "sg:city":"Irvine",
    "sg:classifiers":[
        {
            "category":"Banks & Credit Unions",
            "subcategory":"Bank",
            "type":"Services"
        }
    ],
    "sg:phone":"+1 949 753 1154",
    "sg:postcode":"92618",
    "sg:province":"CA",
    "sg:tags":[
        "national",
        "commercial"
    ],
    "sg:website":"locators.bankofamerica.com",
    "wof:name":"Bank of America",
    "wof:placetype":"venue"
},
  "geometry": {"coordinates":[-117.73974699999999,33.657031],"type":"Point"}
}