{
  "type": "Feature",
  "properties": {
    "addr:full":"7551 Franklin Blvd Sacramento CA 95823",
    "addr:housenumber":"7551",
    "addr:postcode":"95823",
    "addr:street":"Franklin Blvd",
    "iso:country":"US",
    "sg:address":"7551 Franklin Blvd",
    "sg:city":"Sacramento",
    "sg:classifiers":[
        {
            "category":"Taxi",
            "type":"Transportation"
        }
    ],
    "sg:phone":"+1 916 869 3681",
    "sg:postcode":"95823",
    "sg:province":"CA",
    "sg:tags":[
        "taxicab"
    ],
    "wof:name":"HP Cab Company",
    "wof:placetype":"venue"
},
  "geometry": {"coordinates":[-121.453086,38.482303],"type":"Point"}
}