{
  "type": "Feature",
  "properties": {
    "addr:full":"5845 Old Hwy 53 Clearlake CA 95422",
    "addr:housenumber":"5845",
    "addr:postcode":"95422",
    "addr:street":"Old Hwy 53",
    "iso:country":"US",
    "sg:address":"5845 Old Hwy 53",
    "sg:city":"Clearlake",
    "sg:classifiers":[
        {
            "category":"Real Estate",
            "subcategory":"Real Estate Operator",
            "type":"Services"
        }
    ],
    "sg:phone":"+1 707 994 3500",
    "sg:postcode":"95422",
    "sg:province":"CA",
    "sg:tags":[
        "mobile",
        "home",
        "community"
    ],
    "wof:name":"Kingfisher Mobile Home Park",
    "wof:placetype":"venue"
},
  "geometry": {"coordinates":[-122.63149,38.941067],"type":"Point"}
}