{
  "type": "Feature",
  "properties": {
    "iso:country":"US",
    "sg:address":"840 Sovereign Way",
    "sg:city":"Redwood City",
    "sg:classifiers":[
        {
            "category":"Professional",
            "subcategory":"Secretarial Services",
            "type":"Services"
        }
    ],
    "sg:phone":"+1 650 631 8600",
    "sg:postcode":"94065",
    "sg:province":"CA",
    "sg:tags":[
        "reporting",
        "court"
    ],
    "sg:website":"www.cmora.com",
    "wof:name":"Cmora & Assoc",
    "wof:placetype":"venue"
},
  "geometry": {"coordinates":[-122.237549,37.537121],"type":"Point"}
}