{
  "type": "Feature",
  "properties": {
    "iso:country":"US",
    "sg:address":"7833 W Sunset Boulevard",
    "sg:city":"Los Angeles",
    "sg:classifiers":[
        {
            "category":"Cinema",
            "subcategory":"Movie Rental",
            "type":"Entertainment"
        }
    ],
    "sg:phone":"+1 323 851 2688",
    "sg:postcode":"90046",
    "sg:province":"CA",
    "sg:tags":[
        "game",
        "video"
    ],
    "wof:name":"Blockbuster Video",
    "wof:placetype":"venue"
},
  "geometry": {"coordinates":[-118.360246,34.097947],"type":"Point"}
}