{
  "type": "Feature",
  "properties": {
    "iso:country":"US",
    "sg:address":"14747 Artesia Blvd Ste 5V",
    "sg:city":"La Mirada",
    "sg:classifiers":[
        {
            "category":"Shopping",
            "subcategory":"Optician",
            "type":"Retail Goods"
        }
    ],
    "sg:phone":"+1 714 522 2567",
    "sg:postcode":"90638",
    "sg:province":"CA",
    "sg:tags":[
        "eyewear"
    ],
    "wof:name":"Kc Technology",
    "wof:placetype":"venue"
},
  "geometry": {"coordinates":[-118.016474,33.874242],"type":"Point"}
}