{
  "type": "Feature",
  "properties": {
    "addr:full":"4455 Sheila St Los Angeles CA 90023",
    "addr:housenumber":"4455",
    "addr:postcode":"90023",
    "addr:street":"Sheila St",
    "iso:country":"US",
    "sg:address":"4455 Sheila St",
    "sg:city":"Los Angeles",
    "sg:classifiers":[
        {
            "category":"Autos & Motor Vehicles",
            "subcategory":"Auto Supplies",
            "type":"Retail Goods"
        }
    ],
    "sg:phone":"+1 323 268 8382",
    "sg:postcode":"90023",
    "sg:province":"CA",
    "sg:tags":[
        "automobile",
        "parts"
    ],
    "sg:website":"www.spwusa.com",
    "wof:name":"SPW Inc",
    "wof:placetype":"venue"
},
  "geometry": {"coordinates":[-118.17667899999999,34.004474],"type":"Point"}
}