{
  "type": "Feature",
  "properties": {
    "iso:country":"US",
    "sg:address":"2919 Bellows Ct",
    "sg:city":"Davis",
    "sg:classifiers":[
        {
            "category":"Professional",
            "subcategory":"Computer Services",
            "type":"Services"
        }
    ],
    "sg:phone":"+1 530 297 7845",
    "sg:postcode":"95618",
    "sg:province":"CA",
    "sg:tags":[
        "web",
        "design",
        "hosting",
        "site"
    ],
    "sg:website":"http://www.clientready.com",
    "wof:name":"Big Stock Photo, Inc.",
    "wof:placetype":"venue"
},
  "geometry": {"coordinates":[-121.71455899999999,38.57014],"type":"Point"}
}