{
  "type": "Feature",
  "properties": {
    "iso:country":"US",
    "sg:address":"32257 Dunlap Blvd",
    "sg:city":"Yucaipa",
    "sg:classifiers":[
        {
            "category":"Professional",
            "subcategory":"Management & Consulting",
            "type":"Services"
        }
    ],
    "sg:phone":"+1 909 446 0654",
    "sg:postcode":"92399",
    "sg:province":"CA",
    "wof:name":"Usnet LLC",
    "wof:placetype":"venue"
},
  "geometry": {"coordinates":[-117.098147,34.019887],"type":"Point"}
}