{
  "type": "Feature",
  "properties": {
    "addr:full":"3622 Martin Luther King Jr Blvd Lynwood CA 90262",
    "addr:housenumber":"3622",
    "addr:postcode":"90262",
    "addr:street":"Martin Luther King Jr Blvd",
    "iso:country":"US",
    "sg:address":"3622 Martin Luther King Jr Blvd",
    "sg:city":"Lynwood",
    "sg:classifiers":[
        {
            "category":"Personal",
            "subcategory":"Nail Salon",
            "type":"Services"
        }
    ],
    "sg:phone":"+1 310 885 5523",
    "sg:postcode":"90262",
    "sg:province":"CA",
    "wof:name":"Lynwood Nails",
    "wof:placetype":"venue"
},
  "geometry": {"coordinates":[-118.203791,33.932172],"type":"Point"}
}