{
  "type": "Feature",
  "properties": {
    "addr:full":"149 Valle Verde Ct Danville CA 94526",
    "addr:housenumber":"149",
    "addr:postcode":"94526",
    "addr:street":"Valle Verde Ct",
    "iso:country":"US",
    "sg:address":"149 Valle Verde Ct",
    "sg:city":"Danville",
    "sg:classifiers":[
        {
            "category":"Professional",
            "subcategory":"Art Services",
            "type":"Services"
        }
    ],
    "sg:phone":"+1 925 743 9961",
    "sg:postcode":"94526",
    "sg:province":"CA",
    "sg:tags":[
        "graphic",
        "designer"
    ],
    "wof:name":"Andjelic Design",
    "wof:placetype":"venue"
},
  "geometry": {"coordinates":[-121.977069,37.839264],"type":"Point"}
}