{
  "type": "Feature",
  "properties": {
    "addr:full":"8365 Church St Gilroy CA 95020",
    "addr:housenumber":"8365",
    "addr:postcode":"95020",
    "addr:street":"Church St",
    "iso:country":"US",
    "sg:address":"8365 Church St",
    "sg:city":"Gilroy",
    "sg:classifiers":[
        {
            "category":"Shopping",
            "type":"Retail Goods"
        }
    ],
    "sg:phone":"+1 408 779 3091",
    "sg:postcode":"95020",
    "sg:province":"CA",
    "sg:tags":[
        "merchandise"
    ],
    "wof:name":"Miracle-Ear",
    "wof:placetype":"venue"
},
  "geometry": {"coordinates":[-121.57660300000001,37.017845],"type":"Point"}
}