{
  "type": "Feature",
  "properties": {
    "addr:full":"1035 E Valley Pkwy Escondido CA 92025",
    "addr:housenumber":"1035",
    "addr:postcode":"92025",
    "addr:street":"E Valley Pkwy",
    "iso:country":"US",
    "sg:address":"1035 E Valley Pkwy",
    "sg:city":"Escondido",
    "sg:classifiers":[
        {
            "category":"Social Services",
            "type":"Services"
        }
    ],
    "sg:phone":"+1 760 737 3990",
    "sg:postcode":"92025",
    "sg:province":"CA",
    "sg:tags":[
        "organization",
        "welfare"
    ],
    "wof:name":"Easter Seal Society",
    "wof:placetype":"venue"
},
  "geometry": {"coordinates":[-117.068845,33.129537],"type":"Point"}
}