{
  "type": "Feature",
  "properties": {
    "iso:country":"US",
    "sg:address":"854 Maple Ave",
    "sg:city":"Los Angeles",
    "sg:classifiers":[
        {
            "category":"Education",
            "subcategory":"School",
            "type":"Public Place"
        }
    ],
    "sg:phone":"+1 213 243 5858",
    "sg:postcode":"90014",
    "sg:province":"CA",
    "wof:name":"Yoyo",
    "wof:placetype":"venue"
},
  "geometry": {"coordinates":[-118.251858,34.000313],"type":"Point"}
}