{
  "type": "Feature",
  "properties": {
    "iso:country":"US",
    "sg:address":"108 E Matilija St",
    "sg:city":"Ojai",
    "sg:classifiers":[
        {
            "category":"Arts & Performance",
            "subcategory":"Theater",
            "type":"Entertainment"
        }
    ],
    "sg:phone":"+1 805 646 8433",
    "sg:postcode":"93023",
    "sg:province":"CA",
    "sg:tags":[
        "talent",
        "agency",
        "casting"
    ],
    "sg:website":"www.paradiseartists.com",
    "wof:name":"Paradise Artists",
    "wof:placetype":"venue"
},
  "geometry": {"coordinates":[-119.243101,34.448935],"type":"Point"}
}