{
  "type": "Feature",
  "properties": {
    "iso:country":"US",
    "sg:address":"9021 Grapevine Rd E",
    "sg:city":"Lebec",
    "sg:classifiers":[
        {
            "category":"Restaurant",
            "type":"Food & Drink"
        }
    ],
    "sg:phone":"+1 661 323 2121",
    "sg:postcode":"93243",
    "sg:province":"CA",
    "wof:name":"Ranch House Restaurant",
    "wof:placetype":"venue"
},
  "geometry": {"coordinates":[-118.927245,34.929718],"type":"Point"}
}