{
  "type": "Feature",
  "properties": {
    "iso:country":"US",
    "sg:address":"2480 Sand Hill Rd",
    "sg:city":"Menlo Park",
    "sg:classifiers":[
        {
            "category":"Banks & Credit Unions",
            "subcategory":"Financial Services",
            "type":"Services"
        }
    ],
    "sg:phone":"+1 650 854 8180",
    "sg:postcode":"94025",
    "sg:province":"CA",
    "sg:tags":[
        "company",
        "investor",
        "venture",
        "capital"
    ],
    "sg:website":"www.benchmark.com",
    "wof:name":"Benchmark Capital",
    "wof:placetype":"venue"
},
  "geometry": {"coordinates":[-122.19987999999999,37.421945],"type":"Point"}
}