{
  "type": "Feature",
  "properties": {
    "iso:country":"US",
    "sg:address":"780 Montague Expressway",
    "sg:city":"San Jose",
    "sg:classifiers":[
        {
            "category":"Wholesale",
            "subcategory":"Computers",
            "type":"Manufacturing & Wholesale Goods"
        }
    ],
    "sg:phone":"+1 408 432 8805",
    "sg:postcode":"95131",
    "sg:province":"CA",
    "wof:name":"Uniquest Corporation",
    "wof:placetype":"venue"
},
  "geometry": {"coordinates":[-121.913962,37.397072],"type":"Point"}
}