{
  "type": "Feature",
  "properties": {
    "iso:country":"US",
    "sg:address":"670 Quail Gardens Dr",
    "sg:city":"Encinitas",
    "sg:classifiers":[
        {
            "category":"Shopping",
            "subcategory":"Clothing, Apparel, & Fashions",
            "type":"Retail Goods"
        }
    ],
    "sg:phone":"+1 760 505 3343",
    "sg:postcode":"92024",
    "sg:province":"CA",
    "sg:tags":[
        "designer"
    ],
    "sg:website":"www.efhed.com",
    "wof:name":"Enlighted Designs",
    "wof:placetype":"venue"
},
  "geometry": {"coordinates":[-117.28001399999999,33.063085],"type":"Point"}
}