{
  "type": "Feature",
  "properties": {
    "addr:full":"4825 Finney Rd Salida CA 95368",
    "addr:housenumber":"4825",
    "addr:postcode":"95368",
    "addr:street":"Finney Rd",
    "iso:country":"US",
    "sg:address":"4825 Finney Rd",
    "sg:city":"Salida",
    "sg:classifiers":[
        {
            "category":"Organizations",
            "subcategory":"Labor Organization",
            "type":"Services"
        }
    ],
    "sg:phone":"+1 209 545 3278",
    "sg:postcode":"95368",
    "sg:province":"CA",
    "wof:name":"Alfaro Farm Labor",
    "wof:placetype":"venue"
},
  "geometry": {"coordinates":[-121.086753,37.70893],"type":"Point"}
}