{
  "type": "Feature",
  "properties": {
    "addr:full":"625 E Home Ave Fresno CA 93728",
    "addr:housenumber":"625",
    "addr:postcode":"93728",
    "addr:street":"E Home Ave",
    "iso:country":"US",
    "sg:address":"625 E Home Ave",
    "sg:city":"Fresno",
    "sg:classifiers":[
        {
            "category":"Real Estate",
            "subcategory":"Real Estate Agent",
            "type":"Services"
        }
    ],
    "sg:phone":"+1 559 486 1448",
    "sg:postcode":"93728",
    "sg:province":"CA",
    "sg:tags":[
        "appraiser"
    ],
    "wof:name":"Viking Appraisal Svc",
    "wof:placetype":"venue"
},
  "geometry": {"coordinates":[-119.803226,36.76333],"type":"Point"}
}