{
  "type": "Feature",
  "properties": {
    "iso:country":"US",
    "sg:address":"132 Wikiup Dr",
    "sg:city":"Santa Rosa",
    "sg:classifiers":[
        {
            "category":"Professional",
            "subcategory":"Business Services",
            "type":"Services"
        }
    ],
    "sg:phone":"+1 707 544 3488",
    "sg:postcode":"95403",
    "sg:province":"CA",
    "wof:name":"RNF Assoc",
    "wof:placetype":"venue"
},
  "geometry": {"coordinates":[-122.758039,38.508361],"type":"Point"}
}