{
  "type": "Feature",
  "properties": {
    "addr:full":"2782 Patterson Rd Riverbank CA 95367",
    "addr:housenumber":"2782",
    "addr:postcode":"95367",
    "addr:street":"Patterson Rd",
    "iso:country":"US",
    "sg:address":"2782 Patterson Rd",
    "sg:city":"Riverbank",
    "sg:classifiers":[
        {
            "category":"Home & Garden",
            "subcategory":"Building Materials",
            "type":"Retail Goods"
        }
    ],
    "sg:phone":"+1 209 869 1085",
    "sg:postcode":"95367",
    "sg:province":"CA",
    "wof:name":"Oakdale Building Supply",
    "wof:placetype":"venue"
},
  "geometry": {"coordinates":[-120.94610400000001,37.73263],"type":"Point"}
}