{
  "type": "Feature",
  "properties": {
    "addr:full":"1165 E Mountain St Pasadena CA 91104",
    "addr:housenumber":"1165",
    "addr:postcode":"91104",
    "addr:street":"E Mountain St",
    "iso:country":"US",
    "sg:address":"1165 E Mountain St",
    "sg:city":"Pasadena",
    "sg:classifiers":[
        {
            "category":"Retail",
            "subcategory":"Animal Services",
            "type":"Services"
        }
    ],
    "sg:phone":"+1 626 794 5863",
    "sg:postcode":"91104",
    "sg:province":"CA",
    "sg:tags":[
        "specialty"
    ],
    "wof:name":"On Spot Mobile Groomi",
    "wof:placetype":"venue"
},
  "geometry": {"coordinates":[-118.126064,34.161714],"type":"Point"}
}