{
  "type": "Feature",
  "properties": {
    "addr:full":"1506 Railroad St Glendale CA 91204",
    "addr:housenumber":"1506",
    "addr:postcode":"91204",
    "addr:street":"Railroad St",
    "iso:country":"US",
    "sg:address":"1506 Railroad St",
    "sg:city":"Glendale",
    "sg:classifiers":[
        {
            "category":"Personal",
            "subcategory":"Beauty Salon",
            "type":"Services"
        }
    ],
    "sg:phone":"+1 818 507 8906",
    "sg:postcode":"91204",
    "sg:province":"CA",
    "sg:tags":[
        "hair"
    ],
    "wof:name":"Kevis Rejuvenation Programs Inc",
    "wof:placetype":"venue"
},
  "geometry": {"coordinates":[-118.260597,34.126553],"type":"Point"}
}