{
  "type": "Feature",
  "properties": {
    "iso:country":"US",
    "sg:address":"145 John Glenn Dr",
    "sg:city":"Concord",
    "sg:classifiers":[
        {
            "category":"Retail",
            "subcategory":"Auto Rental",
            "type":"Services"
        }
    ],
    "sg:phone":"+1 925 691 0104",
    "sg:postcode":"94520",
    "sg:province":"CA",
    "sg:tags":[
        "renting",
        "automobile"
    ],
    "wof:name":"Hertz Rent A Car",
    "wof:placetype":"venue"
},
  "geometry": {"coordinates":[-122.055626,37.983042],"type":"Point"}
}