{
  "type": "Feature",
  "properties": {
    "iso:country":"US",
    "sg:address":"4680 Sierra St",
    "sg:city":"Riverside",
    "sg:classifiers":[
        {
            "category":"Food & Beverages",
            "subcategory":"Groceries & Convenience Stores",
            "type":"Retail Goods"
        }
    ],
    "sg:phone":"+1 951 351 0125",
    "sg:postcode":"92504",
    "sg:province":"CA",
    "sg:tags":[
        "supermarket"
    ],
    "wof:name":"Stater Bros Markets",
    "wof:placetype":"venue"
},
  "geometry": {"coordinates":[-117.40399499999999,33.949752],"type":"Point"}
}