{
  "type": "Feature",
  "properties": {
    "addr:full":"12584 Central Ave Chino CA 91710",
    "addr:housenumber":"12584",
    "addr:postcode":"91710",
    "addr:street":"Central Ave",
    "iso:country":"US",
    "sg:address":"12584 Central Ave",
    "sg:city":"Chino",
    "sg:classifiers":[
        {
            "category":"Health Services",
            "subcategory":"Chiropractor",
            "type":"Services"
        }
    ],
    "sg:phone":"+1 909 287 1800",
    "sg:postcode":"91710",
    "sg:province":"CA",
    "wof:name":"Chino Pediatrics",
    "wof:placetype":"venue"
},
  "geometry": {"coordinates":[-117.689474,34.025427],"type":"Point"}
}