{
  "type": "Feature",
  "properties": {
    "addr:full":"1425 W Artesia Blvd Gardena CA 90248",
    "addr:housenumber":"1425",
    "addr:postcode":"90248",
    "addr:street":"W Artesia Blvd",
    "iso:country":"US",
    "sg:address":"1425 W Artesia Blvd",
    "sg:city":"Gardena",
    "sg:classifiers":[
        {
            "category":"Bars & Pubs",
            "subcategory":"Nightclub",
            "type":"Food & Drink"
        }
    ],
    "sg:phone":"+1 310 715 2887",
    "sg:postcode":"90248",
    "sg:province":"CA",
    "sg:tags":[
        "nightlife"
    ],
    "wof:name":"Celeb",
    "wof:placetype":"venue"
},
  "geometry": {"coordinates":[-118.29988400000001,33.873157],"type":"Point"}
}