{
  "type": "Feature",
  "properties": {
    "iso:country":"US",
    "sg:address":"517 W Manchester Blvd",
    "sg:city":"Inglewood",
    "sg:classifiers":[
        {
            "category":"Professional",
            "subcategory":"Accounting & Tax Preparation",
            "type":"Services"
        }
    ],
    "sg:phone":"+1 310 677 9949",
    "sg:postcode":"90301",
    "sg:province":"CA",
    "sg:tags":[
        "return",
        "filing"
    ],
    "wof:name":"Ultimate Professional Svc",
    "wof:placetype":"venue"
},
  "geometry": {"coordinates":[-118.36582900000001,33.961632],"type":"Point"}
}