{
  "type": "Feature",
  "properties": {
    "addr:full":"13406 Saticoy St North Hollywood CA 91605",
    "addr:housenumber":"13406",
    "addr:postcode":"91605",
    "addr:street":"Saticoy St",
    "iso:country":"US",
    "sg:address":"13406 Saticoy St",
    "sg:city":"North Hollywood",
    "sg:classifiers":[
        {
            "category":"Home & Garden",
            "subcategory":"Carpets & Floor Coverings",
            "type":"Retail Goods"
        }
    ],
    "sg:phone":"+1 818 901 7411",
    "sg:postcode":"91605",
    "sg:province":"CA",
    "sg:tags":[
        "carpeting"
    ],
    "wof:name":"Amigo's Flooring Superwarehouse",
    "wof:placetype":"venue"
},
  "geometry": {"coordinates":[-118.425003,34.208801],"type":"Point"}
}