{
  "type": "Feature",
  "properties": {
    "iso:country":"US",
    "sg:address":"1700 E Thompson Blvd",
    "sg:city":"Ventura",
    "sg:classifiers":[
        {
            "category":"Professional",
            "type":"Services"
        }
    ],
    "sg:phone":"+1 805 653 2425",
    "sg:postcode":"93001",
    "sg:province":"CA",
    "wof:name":"Ventura Reality",
    "wof:placetype":"venue"
},
  "geometry": {"coordinates":[-119.274915,34.275199],"type":"Point"}
}