{
  "type": "Feature",
  "properties": {
    "addr:full":"1685 Sutter Rd Mckinleyville CA 95519",
    "addr:housenumber":"1685",
    "addr:postcode":"95519",
    "addr:street":"Sutter Rd",
    "iso:country":"US",
    "sg:address":"1685 Sutter Rd",
    "sg:city":"Mckinleyville",
    "sg:classifiers":[
        {
            "category":"Home & Garden",
            "subcategory":"Building Materials",
            "type":"Retail Goods"
        },
        {
            "category":"Building & Trades",
            "subcategory":"Construction",
            "type":"Services"
        },
        {
            "category":"Manufacturing",
            "subcategory":"Building Materials",
            "type":"Manufacturing & Wholesale Goods"
        }
    ],
    "sg:phone":"+1 707 443 5551",
    "sg:postcode":"95519",
    "sg:province":"CA",
    "sg:tags":[
        "cabinetmakers-commercial",
        "industrial",
        "maker",
        "cabinet"
    ],
    "wof:name":"Thomas Cabinets",
    "wof:placetype":"venue"
},
  "geometry": {"coordinates":[-124.09925800000001,40.936054],"type":"Point"}
}