{
  "type": "Feature",
  "properties": {
    "iso:country":"US",
    "sg:address":"3435 Shady Spring Ln",
    "sg:city":"Mountain View",
    "sg:classifiers":[
        {
            "category":"Insurance",
            "subcategory":"Insurance Agent",
            "type":"Services"
        }
    ],
    "sg:phone":"+1 650 968 5967",
    "sg:postcode":"94040",
    "sg:province":"CA",
    "wof:name":"Montang & Associates",
    "wof:placetype":"venue"
},
  "geometry": {"coordinates":[-122.071192,37.359305],"type":"Point"}
}