{
  "type": "Feature",
  "properties": {
    "addr:full":"27410 Walnut Bayou Ln Winters CA 95694",
    "addr:housenumber":"27410",
    "addr:postcode":"95694",
    "addr:street":"Walnut Bayou Ln",
    "iso:country":"US",
    "sg:address":"27410 Walnut Bayou Ln",
    "sg:city":"Winters",
    "sg:classifiers":[
        {
            "category":"Farming",
            "subcategory":"Orchard",
            "type":"Manufacturing & Wholesale Goods"
        }
    ],
    "sg:phone":"+1 530 795 2133",
    "sg:postcode":"95694",
    "sg:province":"CA",
    "sg:tags":[
        "farm",
        "almond",
        "prune",
        "walnut"
    ],
    "wof:name":"T & M Kato Farms Inc",
    "wof:placetype":"venue"
},
  "geometry": {"coordinates":[-121.904968,38.540195],"type":"Point"}
}