{
  "type": "Feature",
  "properties": {
    "addr:full":"250 E Antelope Ave Woodlake CA 93286",
    "addr:housenumber":"250",
    "addr:postcode":"93286",
    "addr:street":"E Antelope Ave",
    "iso:country":"US",
    "sg:address":"250 E Antelope Ave",
    "sg:city":"Woodlake",
    "sg:classifiers":[
        {
            "category":"Health Services",
            "subcategory":"Doctor",
            "type":"Services"
        }
    ],
    "sg:phone":"+1 559 564 8014",
    "sg:postcode":"93286",
    "sg:province":"CA",
    "sg:tags":[
        "dentist"
    ],
    "wof:name":"Family Dental Ctr",
    "wof:placetype":"venue"
},
  "geometry": {"coordinates":[-119.097008,36.415653],"type":"Point"}
}