{
  "type": "Feature",
  "properties": {
    "iso:country":"US",
    "sg:address":"220 S Indian Hill Blvd",
    "sg:city":"Claremont",
    "sg:classifiers":[
        {
            "category":"Real Estate",
            "subcategory":"Real Estate Services",
            "type":"Services"
        },
        {
            "category":"Real Estate",
            "subcategory":"Real Estate Agent",
            "type":"Services"
        }
    ],
    "sg:phone":"+1 909 626 8989",
    "sg:postcode":"91711",
    "sg:province":"CA",
    "sg:tags":[
        "buyer",
        "loan",
        "broker"
    ],
    "wof:name":"First Choice Funding Solutions, Inc",
    "wof:placetype":"venue"
},
  "geometry": {"coordinates":[-117.719281,34.091745],"type":"Point"}
}