{
  "type": "Feature",
  "properties": {
    "iso:country":"US",
    "sg:address":"605 E Mission Rd",
    "sg:city":"San Marcos",
    "sg:classifiers":[
        {
            "category":"Building & Trades",
            "subcategory":"Construction",
            "type":"Services"
        }
    ],
    "sg:phone":"+1 760 744 7191",
    "sg:postcode":"92069",
    "sg:province":"CA",
    "sg:tags":[
        "pumping",
        "contractor"
    ],
    "sg:website":"www.diamondprovides.com",
    "wof:name":"Diamond Environmental Svc",
    "wof:placetype":"venue"
},
  "geometry": {"coordinates":[-117.153341,33.143908],"type":"Point"}
}