{
  "type": "Feature",
  "properties": {
    "iso:country":"US",
    "sg:address":"649 Jones St",
    "sg:city":"San Francisco",
    "sg:classifiers":[
        {
            "category":"Travel",
            "subcategory":"Hotels & Motels",
            "type":"Entertainment"
        }
    ],
    "sg:phone":"+1 415 929 8033",
    "sg:postcode":"94102",
    "sg:province":"CA",
    "sg:website":"www.halcyonsf.com",
    "wof:name":"Halcyon Hotel",
    "wof:placetype":"venue"
},
  "geometry": {"coordinates":[-122.413302,37.787337],"type":"Point"}
}