{
  "type": "Feature",
  "properties": {
    "iso:country":"US",
    "sg:address":"5020 Long Beach Blvd",
    "sg:city":"Long Beach",
    "sg:classifiers":[
        {
            "category":"Fast Food",
            "type":"Food & Drink"
        }
    ],
    "sg:postcode":"90805",
    "sg:province":"CA",
    "sg:website":"www.mcdonalds.com",
    "wof:name":"McDonald's",
    "wof:placetype":"venue"
},
  "geometry": {"coordinates":[-118.193142,33.847118],"type":"Point"}
}