{
  "type": "Feature",
  "properties": {
    "iso:country":"US",
    "sg:address":"31364 Hampton Rd",
    "sg:city":"Yucaipa",
    "sg:classifiers":[
        {
            "category":"Restaurant",
            "type":"Food & Drink"
        }
    ],
    "sg:phone":"+1 909 794 8680",
    "sg:postcode":"92399",
    "sg:province":"CA",
    "sg:tags":[
        "japanese"
    ],
    "wof:name":"Teriyaki Plus Smoothies",
    "wof:placetype":"venue"
},
  "geometry": {"coordinates":[-117.118996,34.028487],"type":"Point"}
}