{
  "type": "Feature",
  "properties": {
    "addr:full":"2917 E Florence Ave Huntington Park CA 90255",
    "addr:housenumber":"2917",
    "addr:postcode":"90255",
    "addr:street":"E Florence Ave;Park",
    "iso:country":"US",
    "sg:address":"2917 E Florence Ave",
    "sg:city":"Huntington Park",
    "sg:classifiers":[
        {
            "category":"Professional",
            "type":"Services"
        }
    ],
    "sg:phone":"+1 323 587 8560",
    "sg:postcode":"90255",
    "sg:province":"CA",
    "sg:tags":[
        "establishment"
    ],
    "wof:name":"Wateria",
    "wof:placetype":"venue"
},
  "geometry": {"coordinates":[-118.21754300000001,33.973414],"type":"Point"}
}