{
  "type": "Feature",
  "properties": {
    "iso:country":"US",
    "sg:address":"2385 Carlos St",
    "sg:city":"Moss Beach",
    "sg:classifiers":[
        {
            "category":"Real Estate",
            "subcategory":"Real Estate Agent",
            "type":"Services"
        }
    ],
    "sg:phone":"+1 650 728 5200",
    "sg:postcode":"94038",
    "sg:province":"CA",
    "wof:name":"Re/Max",
    "wof:placetype":"venue"
},
  "geometry": {"coordinates":[-122.514298,37.52887],"type":"Point"}
}