{
  "type": "Feature",
  "properties": {
    "addr:full":"619 Commercial Ave Covina CA 91723",
    "addr:housenumber":"619",
    "addr:postcode":"91723",
    "addr:street":"Commercial Ave",
    "iso:country":"US",
    "sg:address":"619 Commercial Ave",
    "sg:city":"Covina",
    "sg:classifiers":[
        {
            "category":"Wholesale",
            "subcategory":"Machinery & Supplies",
            "type":"Manufacturing & Wholesale Goods"
        }
    ],
    "sg:phone":"+1 626 339 6673",
    "sg:postcode":"91723",
    "sg:province":"CA",
    "sg:tags":[
        "equipment",
        "transportation"
    ],
    "wof:name":"Seahorse",
    "wof:placetype":"venue"
},
  "geometry": {"coordinates":[-117.87778,34.09138],"type":"Point"}
}