{
  "type": "Feature",
  "properties": {
    "iso:country":"US",
    "sg:address":"890 Wisconsin St",
    "sg:city":"Chico",
    "sg:classifiers":[
        {
            "category":"Building & Trades",
            "subcategory":"Construction",
            "type":"Services"
        }
    ],
    "sg:phone":"+1 530 893 5130",
    "sg:postcode":"95928",
    "sg:province":"CA",
    "sg:tags":[
        "contractor"
    ],
    "wof:name":"Anglin Roofing",
    "wof:placetype":"venue"
},
  "geometry": {"coordinates":[-121.819885,39.730462],"type":"Point"}
}