{
  "type": "Feature",
  "properties": {
    "addr:full":"657 Shaw Ave Ferndale CA 95536",
    "addr:housenumber":"657",
    "addr:postcode":"95536",
    "addr:street":"Shaw Ave",
    "iso:country":"US",
    "sg:address":"657 Shaw Ave",
    "sg:city":"Ferndale",
    "sg:classifiers":[
        {
            "category":"Home & Garden",
            "subcategory":"Building Materials",
            "type":"Retail Goods"
        }
    ],
    "sg:phone":"+1 707 786 4011",
    "sg:postcode":"95536",
    "sg:province":"CA",
    "sg:tags":[
        "lumber"
    ],
    "wof:name":"Valley Lumber & Millwork",
    "wof:placetype":"venue"
},
  "geometry": {"coordinates":[-124.261745,40.57721],"type":"Point"}
}