{
  "type": "Feature",
  "properties": {
    "iso:country":"US",
    "sg:address":"881 Cocao Pl",
    "sg:city":"Brea",
    "sg:classifiers":[
        {
            "category":"Professional",
            "subcategory":"Detective & Security Services",
            "type":"Services"
        }
    ],
    "sg:phone":"+1 714 519 9627",
    "sg:postcode":"92821",
    "sg:province":"CA",
    "sg:tags":[
        "information",
        "bureau"
    ],
    "wof:name":"Petersen Construction Services",
    "wof:placetype":"venue"
},
  "geometry": {"coordinates":[-117.884078,33.925528],"type":"Point"}
}