{
  "type": "Feature",
  "properties": {
    "addr:full":"5240 Arlington Ave Riverside CA 92504",
    "addr:housenumber":"5240",
    "addr:postcode":"92504",
    "addr:street":"Arlington Ave",
    "iso:country":"US",
    "sg:address":"5240 Arlington Ave",
    "sg:city":"Riverside",
    "sg:classifiers":[
        {
            "category":"Insurance",
            "subcategory":"Insurance Agent",
            "type":"Services"
        }
    ],
    "sg:phone":"+1 951 359 1130",
    "sg:postcode":"92504",
    "sg:province":"CA",
    "wof:name":"Romar Insurance",
    "wof:placetype":"venue"
},
  "geometry": {"coordinates":[-117.416214,33.946003],"type":"Point"}
}