{
  "type": "Feature",
  "properties": {
    "addr:full":"24032 Hesperian Blvd Hayward CA 94545",
    "addr:housenumber":"24032",
    "addr:postcode":"94545",
    "addr:street":"Hesperian Blvd",
    "iso:country":"US",
    "sg:address":"24032 Hesperian Blvd",
    "sg:city":"Hayward",
    "sg:classifiers":[
        {
            "category":"Shopping",
            "subcategory":"Photographic Equipment",
            "type":"Retail Goods"
        }
    ],
    "sg:phone":"+1 510 782 1506",
    "sg:postcode":"94545",
    "sg:province":"CA",
    "sg:tags":[
        "supply"
    ],
    "wof:name":"Negative Space Photography",
    "wof:placetype":"venue"
},
  "geometry": {"coordinates":[-122.10917000000001,37.651231],"type":"Point"}
}