{
  "type": "Feature",
  "properties": {
    "addr:full":"26441 Broken Bit Ln Laguna Hills CA 92653",
    "addr:housenumber":"26441",
    "addr:postcode":"92653",
    "addr:street":"Broken Bit Ln",
    "iso:country":"US",
    "sg:address":"26441 Broken Bit Ln",
    "sg:city":"Laguna Hills",
    "sg:classifiers":[
        {
            "category":"Professional",
            "type":"Services"
        }
    ],
    "sg:phone":"+1 949 360 1251",
    "sg:postcode":"92653",
    "sg:province":"CA",
    "wof:name":"Richard Sloan",
    "wof:placetype":"venue"
},
  "geometry": {"coordinates":[-117.690601,33.57807],"type":"Point"}
}