{
  "type": "Feature",
  "properties": {
    "addr:full":"915 Highland Pointe Dr Roseville CA 95678",
    "addr:housenumber":"915",
    "addr:postcode":"95678",
    "addr:street":"Highland Pointe Dr",
    "iso:country":"US",
    "sg:address":"915 Highland Pointe Dr",
    "sg:city":"Roseville",
    "sg:classifiers":[
        {
            "category":"Professional",
            "subcategory":"Accounting & Tax Preparation",
            "type":"Services"
        },
        {
            "category":"Professional",
            "subcategory":"Lawyer & Legal Services",
            "type":"Services"
        }
    ],
    "sg:phone":"+1 800 896 5536",
    "sg:postcode":"95678",
    "sg:province":"CA",
    "sg:tags":[
        "attorney",
        "return",
        "representative",
        "taxes-consultants"
    ],
    "sg:website":"http://www.jkharris.com/?ml_source=yellowpages",
    "wof:name":"JK Harris & Company",
    "wof:placetype":"venue"
},
  "geometry": {"coordinates":[-121.285141,38.783031],"type":"Point"}
}