{
  "type": "Feature",
  "properties": {
    "addr:full":"6925 Canby Ave Reseda CA 91335",
    "addr:housenumber":"6925",
    "addr:postcode":"91335",
    "addr:street":"Canby Ave",
    "iso:country":"US",
    "sg:address":"6925 Canby Ave",
    "sg:city":"Reseda",
    "sg:classifiers":[
        {
            "category":"Wholesale",
            "subcategory":"Office Equipment",
            "type":"Manufacturing & Wholesale Goods"
        }
    ],
    "sg:phone":"+1 818 757 0066",
    "sg:postcode":"91335",
    "sg:province":"CA",
    "sg:tags":[
        "machine",
        "duplicating",
        "copying"
    ],
    "sg:website":"www.offir.net",
    "wof:name":"Offir Office Systems",
    "wof:placetype":"venue"
},
  "geometry": {"coordinates":[-118.5348,34.195991],"type":"Point"}
}