{
  "type": "Feature",
  "properties": {
    "addr:full":"6955 Fernhill Dr Malibu CA 90265",
    "addr:housenumber":"6955",
    "addr:postcode":"90265",
    "addr:street":"Fernhill Dr",
    "iso:country":"US",
    "sg:address":"6955 Fernhill Dr",
    "sg:city":"Malibu",
    "sg:classifiers":[
        {
            "category":"Recreation",
            "type":"Entertainment"
        }
    ],
    "sg:phone":"+1 310 589 5529",
    "sg:postcode":"90265",
    "sg:province":"CA",
    "sg:tags":[
        "martial",
        "arts",
        "instruction"
    ],
    "wof:name":"Lampson Martial Arts Assn",
    "wof:placetype":"venue"
},
  "geometry": {"coordinates":[-118.801075,34.010825],"type":"Point"}
}