{
  "type": "Feature",
  "properties": {
    "addr:full":"9812 Bolsa Ave Westminster CA 92683",
    "addr:housenumber":"9812",
    "addr:postcode":"92683",
    "addr:street":"Bolsa Ave",
    "iso:country":"US",
    "sg:address":"9812 Bolsa Ave",
    "sg:city":"Westminster",
    "sg:classifiers":[
        {
            "category":"Retail",
            "subcategory":"Laundry & Dry Cleaning",
            "type":"Services"
        }
    ],
    "sg:phone":"+1 714 775 1231",
    "sg:postcode":"92683",
    "sg:province":"CA",
    "wof:name":"L T Cleaner & Alteration",
    "wof:placetype":"venue"
},
  "geometry": {"coordinates":[-117.959648,33.744692],"type":"Point"}
}