{
  "type": "Feature",
  "properties": {
    "addr:full":"1192 6th St Norco CA 92860",
    "addr:housenumber":"1192",
    "addr:postcode":"92860",
    "addr:street":"6Th St",
    "iso:country":"US",
    "sg:address":"1192 6th St",
    "sg:city":"Norco",
    "sg:classifiers":[
        {
            "category":"Shopping",
            "subcategory":"Bicycles & Sporting Goods",
            "type":"Retail Goods"
        }
    ],
    "sg:phone":"+1 951 735 7256",
    "sg:postcode":"92860",
    "sg:province":"CA",
    "sg:tags":[
        "horse",
        "furnishing"
    ],
    "wof:name":"Horse Clothesline",
    "wof:placetype":"venue"
},
  "geometry": {"coordinates":[-117.54801999999999,33.938336],"type":"Point"}
}