{
  "type": "Feature",
  "properties": {
    "iso:country":"US",
    "sg:address":"1443A Noriega St",
    "sg:city":"San Francisco",
    "sg:classifiers":[
        {
            "category":"Education",
            "subcategory":"Special Training",
            "type":"Public Place"
        }
    ],
    "sg:phone":"+1 415 661 1225",
    "sg:postcode":"94122",
    "sg:province":"CA",
    "sg:tags":[
        "tutoring"
    ],
    "sg:website":"www.upgradeteaching.com",
    "wof:name":"Up!Grade Learning Center",
    "wof:placetype":"venue"
},
  "geometry": {"coordinates":[-122.47910899999999,37.754119],"type":"Point"}
}