{
  "type": "Feature",
  "properties": {
    "addr:full":"2610 S. Croddy Way Suite H Santa Ana CA 92704",
    "addr:housenumber":"2610",
    "addr:postcode":"92704",
    "addr:street":"S. Croddy Way Suite H",
    "iso:country":"US",
    "sg:address":"2610 S. Croddy Way Suite H",
    "sg:city":"Santa Ana",
    "sg:classifiers":[
        {
            "category":"Professional",
            "subcategory":"Printing & Photocopies",
            "type":"Services"
        }
    ],
    "sg:phone":"+1 877 846 8711",
    "sg:postcode":"92704",
    "sg:province":"CA",
    "sg:website":"www.IndependentSigns.com",
    "wof:name":"Independent Signs",
    "wof:placetype":"venue"
},
  "geometry": {"coordinates":[-117.92102800000001,33.71256],"type":"Point"}
}