{
  "type": "Feature",
  "properties": {
    "addr:full":"30815 E Thousand Oaks Blvd Westlake Village CA 91362",
    "addr:housenumber":"30815",
    "addr:postcode":"91362",
    "addr:street":"E Thousand Oaks Blvd",
    "iso:country":"US",
    "sg:address":"30815 E Thousand Oaks Blvd",
    "sg:city":"Westlake Village",
    "sg:classifiers":[
        {
            "category":"Shopping",
            "type":"Retail Goods"
        }
    ],
    "sg:phone":"+1 818 879 0566",
    "sg:postcode":"91362",
    "sg:province":"CA",
    "sg:tags":[
        "bird"
    ],
    "wof:name":"Pets Stop",
    "wof:placetype":"venue"
},
  "geometry": {"coordinates":[-118.791202,34.154757],"type":"Point"}
}