{
  "type": "Feature",
  "properties": {
    "addr:full":"5092 W Knoll Dr Yorba Linda CA 92886",
    "addr:housenumber":"5092",
    "addr:postcode":"92886",
    "addr:street":"W Knoll Dr",
    "iso:country":"US",
    "sg:address":"5092 W Knoll Dr",
    "sg:city":"Yorba Linda",
    "sg:classifiers":[
        {
            "category":"Utilities",
            "subcategory":"Telephone",
            "type":"Services"
        }
    ],
    "sg:phone":"+1 714 693 2533",
    "sg:postcode":"92886",
    "sg:province":"CA",
    "sg:tags":[
        "cards",
        "phone",
        "dist",
        "prepaid"
    ],
    "wof:name":"Just Cds Inc",
    "wof:placetype":"venue"
},
  "geometry": {"coordinates":[-117.79673,33.886233],"type":"Point"}
}