{
  "type": "Feature",
  "properties": {
    "addr:full":"135 12th St Oakland CA 94607",
    "addr:housenumber":"135",
    "addr:postcode":"94607",
    "addr:street":"12Th St",
    "iso:country":"US",
    "sg:address":"135 12th St",
    "sg:city":"Oakland",
    "sg:classifiers":[
        {
            "category":"Restaurant",
            "type":"Food & Drink"
        }
    ],
    "sg:phone":"+1 510 763 0404",
    "sg:postcode":"94607",
    "sg:province":"CA",
    "sg:tags":[
        "dance",
        "club"
    ],
    "wof:name":"Oasis Restaurant & Bar",
    "wof:placetype":"venue"
},
  "geometry": {"coordinates":[-122.264681,37.79978],"type":"Point"}
}