{
  "type": "Feature",
  "properties": {
    "addr:full":"9685 Wilshire Blvd Beverly Hills CA 90212",
    "addr:housenumber":"9685",
    "addr:postcode":"90212",
    "addr:street":"Wilshire Blvd",
    "iso:country":"US",
    "sg:address":"9685 Wilshire Blvd",
    "sg:city":"Beverly Hills",
    "sg:classifiers":[
        {
            "category":"Personal",
            "subcategory":"Beauty Salon",
            "type":"Services"
        }
    ],
    "sg:phone":"+1 310 278 3881",
    "sg:postcode":"90212",
    "sg:province":"CA",
    "sg:tags":[
        "nail",
        "manicuring"
    ],
    "wof:name":"Nail Designs",
    "wof:placetype":"venue"
},
  "geometry": {"coordinates":[-118.405295,34.067097],"type":"Point"}
}