{
  "type": "Feature",
  "properties": {
    "addr:full":"5151 Lafayette St Santa Clara CA 95054",
    "addr:housenumber":"5151",
    "addr:postcode":"95054",
    "addr:street":"Lafayette St",
    "iso:country":"US",
    "sg:address":"5151 Lafayette St",
    "sg:city":"Santa Clara",
    "sg:classifiers":[
        {
            "category":"Recreation",
            "type":"Entertainment"
        }
    ],
    "sg:phone":"+1 408 727 3144",
    "sg:postcode":"95054",
    "sg:province":"CA",
    "sg:tags":[
        "paint",
        "ball",
        "sport"
    ],
    "wof:name":"Real Action Paintball",
    "wof:placetype":"venue"
},
  "geometry": {"coordinates":[-121.96702500000001,37.407268],"type":"Point"}
}