{
  "type": "Feature",
  "properties": {
    "iso:country":"US",
    "sg:address":"35 Ford Rd",
    "sg:city":"Carmel Valley",
    "sg:classifiers":[
        {
            "category":"Education",
            "subcategory":"School",
            "type":"Public Place"
        }
    ],
    "sg:phone":"+1 831 659 2276",
    "sg:postcode":"93924",
    "sg:province":"CA",
    "wof:name":"Tularcitos Elementary School",
    "wof:placetype":"venue"
},
  "geometry": {"coordinates":[-121.736336,36.48366],"type":"Point"}
}