{
  "type": "Feature",
  "properties": {
    "iso:country":"US",
    "sg:address":"5731 Watt Ave",
    "sg:city":"North Highlands",
    "sg:classifiers":[
        {
            "category":"Shopping",
            "subcategory":"Discount & Variety Stores",
            "type":"Retail Goods"
        }
    ],
    "sg:phone":"+1 916 338 2438",
    "sg:postcode":"95660",
    "sg:province":"CA",
    "wof:name":"DE1 Dollar Queen Superstore",
    "wof:placetype":"venue"
},
  "geometry": {"coordinates":[-121.382957,38.670722],"type":"Point"}
}