{
  "type": "Feature",
  "properties": {
    "iso:country":"US",
    "sg:address":"1667 Royal Ave",
    "sg:city":"Simi Valley",
    "sg:classifiers":[
        {
            "category":"Building & Trades",
            "subcategory":"Electrical",
            "type":"Services"
        }
    ],
    "sg:phone":"+1 805 520 3723",
    "sg:postcode":"93065",
    "sg:province":"CA",
    "sg:tags":[
        "electrical",
        "contractor"
    ],
    "wof:name":"Quality Service Electric",
    "wof:placetype":"venue"
},
  "geometry": {"coordinates":[-118.76660699999999,34.264546],"type":"Point"}
}