{
  "type": "Feature",
  "properties": {
    "addr:full":"600 K St Bakersfield CA 93304",
    "addr:housenumber":"600",
    "addr:postcode":"93304",
    "addr:street":"K St",
    "iso:country":"US",
    "sg:address":"600 K St",
    "sg:city":"Bakersfield",
    "sg:classifiers":[
        {
            "category":"Building & Trades",
            "subcategory":"Landscaping Services",
            "type":"Services"
        }
    ],
    "sg:phone":"+1 661 319 3674",
    "sg:postcode":"93304",
    "sg:province":"CA",
    "wof:name":"Juan Morales Gardening",
    "wof:placetype":"venue"
},
  "geometry": {"coordinates":[-119.01764900000001,35.36365],"type":"Point"}
}