{
  "type": "Feature",
  "properties": {
    "addr:full":"45277 Corte Progresso Temecula CA 92592",
    "addr:housenumber":"45277",
    "addr:postcode":"92592",
    "addr:street":"Corte Progresso",
    "iso:country":"US",
    "sg:address":"45277 Corte Progresso",
    "sg:city":"Temecula",
    "sg:classifiers":[
        {
            "category":"Professional",
            "subcategory":"Computer Services",
            "type":"Services"
        }
    ],
    "sg:phone":"+1 951 303 1423",
    "sg:postcode":"92592",
    "sg:province":"CA",
    "wof:name":"Computer 4 Help Svc",
    "wof:placetype":"venue"
},
  "geometry": {"coordinates":[-117.10203300000001,33.46958],"type":"Point"}
}