{
  "type": "Feature",
  "properties": {
    "addr:full":"842 Elizabeth Street San Francisco CA 94114",
    "addr:housenumber":"842",
    "addr:postcode":"94114",
    "addr:street":"Elizabeth Street",
    "iso:country":"US",
    "sg:address":"842 Elizabeth Street",
    "sg:city":"San Francisco",
    "sg:classifiers":[
        {
            "category":"Health Services",
            "subcategory":"Clinic",
            "type":"Services"
        }
    ],
    "sg:phone":"+1 415 282 2200",
    "sg:postcode":"94114",
    "sg:province":"CA",
    "sg:tags":[
        "counseling",
        "mental"
    ],
    "sg:website":"www.cheryldeaner.com",
    "wof:name":"Cheryl Deaner, LMFT",
    "wof:placetype":"venue"
},
  "geometry": {"coordinates":[-122.439498,37.751788],"type":"Point"}
}