{
  "type": "Feature",
  "properties": {
    "addr:full":"10170 Croydon Way Sacramento CA 95827",
    "addr:housenumber":"10170",
    "addr:postcode":"95827",
    "addr:street":"Croydon Way",
    "iso:country":"US",
    "sg:address":"10170 Croydon Way",
    "sg:city":"Sacramento",
    "sg:classifiers":[
        {
            "category":"Retail",
            "subcategory":"Auto Repair",
            "type":"Services"
        }
    ],
    "sg:phone":"+1 916 366 0330",
    "sg:postcode":"95827",
    "sg:province":"CA",
    "sg:website":"www.sportscarslimited.net/",
    "wof:name":"Sportscars Limited",
    "wof:placetype":"venue"
},
  "geometry": {"coordinates":[-121.312365,38.582045],"type":"Point"}
}