{
  "type": "Feature",
  "properties": {
    "iso:country":"US",
    "sg:address":"29770 Bradley Rd Unit J",
    "sg:city":"Sun City",
    "sg:classifiers":[
        {
            "category":"Government",
            "subcategory":"Office",
            "type":"Public Place"
        }
    ],
    "sg:phone":"+1 951 672 1311",
    "sg:postcode":"92586",
    "sg:province":"CA",
    "sg:tags":[
        "smog",
        "check"
    ],
    "sg:website":"www.testforsmog.com",
    "wof:name":"Tri-City Smog",
    "wof:placetype":"venue"
},
  "geometry": {"coordinates":[-117.18859999999999,33.688445],"type":"Point"}
}