{
  "type": "Feature",
  "properties": {
    "iso:country":"US",
    "sg:address":"186 El Camino Real",
    "sg:city":"Millbrae",
    "sg:classifiers":[
        {
            "category":"Building & Trades",
            "subcategory":"Plumbing",
            "type":"Services"
        },
        {
            "category":"Home & Garden",
            "subcategory":"Building Materials",
            "type":"Retail Goods"
        }
    ],
    "sg:phone":"+1 650 697 1325",
    "sg:postcode":"94030",
    "sg:province":"CA",
    "sg:tags":[
        "supply"
    ],
    "wof:name":"Wellgo Construction Supply Inc",
    "wof:placetype":"venue"
},
  "geometry": {"coordinates":[-122.389,37.600498],"type":"Point"}
}