{
  "type": "Feature",
  "properties": {
    "iso:country":"US",
    "sg:address":"1941 Noriega St Ste 3",
    "sg:city":"San Francisco",
    "sg:classifiers":[
        {
            "category":"Professional",
            "subcategory":"Art Services",
            "type":"Services"
        }
    ],
    "sg:phone":"+1 415 939 5877",
    "sg:postcode":"94122",
    "sg:province":"CA",
    "sg:tags":[
        "photographer"
    ],
    "sg:website":"www.iqphoto.com/cityhall",
    "wof:name":"IQ Photo",
    "wof:placetype":"venue"
},
  "geometry": {"coordinates":[-122.48474400000001,37.753681],"type":"Point"}
}