{
  "type": "Feature",
  "properties": {
    "addr:full":"445 North Whisman Road Suite 300 Mountain View CA 94303",
    "addr:housenumber":"445",
    "addr:postcode":"94303",
    "addr:street":"North Whisman Road Suite 300",
    "iso:country":"US",
    "sg:address":"445 North Whisman Road Suite 300",
    "sg:city":"Mountain View",
    "sg:classifiers":[
        {
            "category":"Personal",
            "type":"Services"
        },
        {
            "category":"Real Estate",
            "subcategory":"Architect",
            "type":"Services"
        }
    ],
    "sg:phone":"+1 650 318 0211",
    "sg:postcode":"94303",
    "sg:province":"CA",
    "sg:tags":[
        "home"
    ],
    "sg:website":"www.MetropolisArchitecture.com",
    "wof:name":"Metropolis Architecture",
    "wof:placetype":"venue"
},
  "geometry": {"coordinates":[-122.05853500000001,37.400074],"type":"Point"}
}