{
  "type": "Feature",
  "properties": {
    "iso:country":"US",
    "sg:address":"1210 Indiana Ct",
    "sg:city":"Redlands",
    "sg:classifiers":[
        {
            "category":"Health Services",
            "subcategory":"Doctor",
            "type":"Services"
        }
    ],
    "sg:phone":"+1 909 793 7500",
    "sg:postcode":"92374",
    "sg:province":"CA",
    "sg:tags":[
        "physician",
        "surgeon"
    ],
    "wof:name":"Inland Nephrology",
    "wof:placetype":"venue"
},
  "geometry": {"coordinates":[-117.205732,34.068215],"type":"Point"}
}