{
  "type": "Feature",
  "properties": {
    "iso:country":"US",
    "sg:address":"11208 Florindo Rd",
    "sg:city":"San Diego",
    "sg:classifiers":[
        {
            "category":"Travel",
            "subcategory":"Travel Agent",
            "type":"Entertainment"
        }
    ],
    "sg:phone":"+1 858 672 4533",
    "sg:postcode":"92127",
    "sg:province":"CA",
    "sg:tags":[
        "operator",
        "tour"
    ],
    "wof:name":"Galpagos Tours & Cruises",
    "wof:placetype":"venue"
},
  "geometry": {"coordinates":[-117.088072,33.026648],"type":"Point"}
}