{
  "type": "Feature",
  "properties": {
    "iso:country":"US",
    "sg:address":"2690 Via de la Valle",
    "sg:city":"Del Mar",
    "sg:classifiers":[
        {
            "category":"Home & Garden",
            "subcategory":"Home Furnishings",
            "type":"Retail Goods"
        }
    ],
    "sg:phone":"+1 858 481 6710",
    "sg:postcode":"92014",
    "sg:province":"CA",
    "sg:tags":[
        "glassware",
        "chinaware"
    ],
    "sg:website":"www.silverskillet.net",
    "wof:name":"Silver Skillet",
    "wof:placetype":"venue"
},
  "geometry": {"coordinates":[-117.24748599999999,32.981156],"type":"Point"}
}