{
  "type": "Feature",
  "properties": {
    "iso:country":"US",
    "sg:address":"402 14th St",
    "sg:city":"Ramona",
    "sg:classifiers":[
        {
            "category":"Retail",
            "subcategory":"Auto Repair",
            "type":"Services"
        }
    ],
    "sg:phone":"+1 760 789 5509",
    "sg:postcode":"92065",
    "sg:province":"CA",
    "sg:tags":[
        "repairing",
        "automobile"
    ],
    "wof:name":"Charlie's Garage",
    "wof:placetype":"venue"
},
  "geometry": {"coordinates":[-116.874111,33.037627],"type":"Point"}
}