{
  "type": "Feature",
  "properties": {
    "addr:full":"6265 Auto Center Dr Buena Park CA 90621",
    "addr:housenumber":"6265",
    "addr:postcode":"90621",
    "addr:street":"Auto Center Dr",
    "iso:country":"US",
    "sg:address":"6265 Auto Center Dr",
    "sg:city":"Buena Park",
    "sg:classifiers":[
        {
            "category":"Food & Beverages",
            "subcategory":"Liquor & Beverages",
            "type":"Retail Goods"
        }
    ],
    "sg:phone":"+1 714 523 0323",
    "sg:postcode":"90621",
    "sg:province":"CA",
    "sg:tags":[
        "beer",
        "spirit",
        "wine"
    ],
    "wof:name":"Rome In Liquor",
    "wof:placetype":"venue"
},
  "geometry": {"coordinates":[-118.001555,33.869005],"type":"Point"}
}