{
  "type": "Feature",
  "properties": {
    "addr:full":"303 Los Gatos Saratoga Rd Los Gatos CA 95030",
    "addr:housenumber":"303",
    "addr:postcode":"95030",
    "addr:street":"Los Gatos Saratoga Rd",
    "iso:country":"US",
    "sg:address":"303 Los Gatos Saratoga Rd",
    "sg:city":"Los Gatos",
    "sg:classifiers":[
        {
            "category":"Banks & Credit Unions",
            "subcategory":"Investment Brokerage",
            "type":"Services"
        }
    ],
    "sg:phone":"+1 408 402 5387",
    "sg:postcode":"95030",
    "sg:province":"CA",
    "sg:tags":[
        "investing"
    ],
    "wof:name":"Executive Edge",
    "wof:placetype":"venue"
},
  "geometry": {"coordinates":[-121.98343800000001,37.230322],"type":"Point"}
}