{
  "type": "Feature",
  "properties": {
    "iso:country":"US",
    "sg:address":"423 Main St",
    "sg:city":"Placerville",
    "sg:classifiers":[
        {
            "category":"Restaurant",
            "type":"Food & Drink"
        }
    ],
    "sg:phone":"+1 530 626 4431",
    "sg:postcode":"95667",
    "sg:province":"CA",
    "wof:name":"Hangtown Grill",
    "wof:placetype":"venue"
},
  "geometry": {"coordinates":[-120.800212,38.729498],"type":"Point"}
}