{
  "type": "Feature",
  "properties": {
    "addr:full":"23434 Bristol Way Murrieta CA 92562",
    "addr:housenumber":"23434",
    "addr:postcode":"92562",
    "addr:street":"Bristol Way",
    "iso:country":"US",
    "sg:address":"23434 Bristol Way",
    "sg:city":"Murrieta",
    "sg:classifiers":[
        {
            "category":"Building & Trades",
            "subcategory":"Construction",
            "type":"Services"
        }
    ],
    "sg:phone":"+1 951 698 7189",
    "sg:postcode":"92562",
    "sg:province":"CA",
    "sg:tags":[
        "steel",
        "erectors"
    ],
    "wof:name":"S & K Construction",
    "wof:placetype":"venue"
},
  "geometry": {"coordinates":[-117.24924900000001,33.570694],"type":"Point"}
}