{
  "type": "Feature",
  "properties": {
    "iso:country":"US",
    "sg:address":"895 Sycamore St",
    "sg:city":"Gridley",
    "sg:classifiers":[
        {
            "category":"Government",
            "subcategory":"Office",
            "type":"Public Place"
        }
    ],
    "sg:phone":"+1 530 000 1111",
    "sg:postcode":"95948",
    "sg:province":"CA",
    "sg:tags":[
        "village"
    ],
    "wof:name":"Gridley Animal Shelter",
    "wof:placetype":"venue"
},
  "geometry": {"coordinates":[-121.696281,39.363518],"type":"Point"}
}