{
  "type": "Feature",
  "properties": {
    "iso:country":"US",
    "sg:address":"495 Gaven St",
    "sg:city":"San Francisco",
    "sg:classifiers":[
        {
            "category":"Building & Trades",
            "subcategory":"Construction",
            "type":"Services"
        }
    ],
    "sg:phone":"+1 415 333 1046",
    "sg:postcode":"94134",
    "sg:province":"CA",
    "sg:tags":[
        "general",
        "contractor"
    ],
    "wof:name":"NTK Construction Inc",
    "wof:placetype":"venue"
},
  "geometry": {"coordinates":[-122.41353599999999,37.732028],"type":"Point"}
}