{
  "type": "Feature",
  "properties": {
    "addr:full":"835 1st St Gilroy CA 95020",
    "addr:housenumber":"835",
    "addr:postcode":"95020",
    "addr:street":"1St St",
    "iso:country":"US",
    "sg:address":"835 1st St",
    "sg:city":"Gilroy",
    "sg:classifiers":[
        {
            "category":"Shopping",
            "subcategory":"Department Store",
            "type":"Retail Goods"
        }
    ],
    "sg:phone":"+1 408 847 0505",
    "sg:postcode":"95020",
    "sg:province":"CA",
    "wof:name":"Sears Roebuck & Co",
    "wof:placetype":"venue"
},
  "geometry": {"coordinates":[-121.58253000000001,37.013483],"type":"Point"}
}