{
  "type": "Feature",
  "properties": {
    "iso:country":"US",
    "sg:address":"16065 Via Olinda",
    "sg:city":"San Lorenzo",
    "sg:classifiers":[
        {
            "category":"Home & Garden",
            "subcategory":"Building Materials",
            "type":"Retail Goods"
        }
    ],
    "sg:phone":"+1 510 276 3060",
    "sg:postcode":"94580",
    "sg:province":"CA",
    "sg:tags":[
        "screen",
        "window"
    ],
    "wof:name":"May's Aluminum Windows",
    "wof:placetype":"venue"
},
  "geometry": {"coordinates":[-122.133111,37.675063],"type":"Point"}
}