{
  "type": "Feature",
  "properties": {
    "addr:full":"10722 Arrow Blvd Rancho Cucamonga CA 91730",
    "addr:housenumber":"10722",
    "addr:postcode":"91730",
    "addr:street":"Arrow Blvd",
    "iso:country":"US",
    "sg:address":"10722 Arrow Blvd",
    "sg:city":"Rancho Cucamonga",
    "sg:classifiers":[
        {
            "category":"Professional",
            "subcategory":"Business Services",
            "type":"Services"
        }
    ],
    "sg:phone":"+1 909 483 5725",
    "sg:postcode":"91730",
    "sg:province":"CA",
    "sg:tags":[
        "broker"
    ],
    "wof:name":"American Business",
    "wof:placetype":"venue"
},
  "geometry": {"coordinates":[-117.569532,34.099213],"type":"Point"}
}