{
  "type": "Feature",
  "properties": {
    "addr:full":"519 S State St Ukiah CA 95482",
    "addr:housenumber":"519",
    "addr:postcode":"ca 95482",
    "addr:street":"S State St",
    "iso:country":"US",
    "sg:address":"519 S State St",
    "sg:city":"Ukiah",
    "sg:classifiers":[
        {
            "category":"Shopping",
            "subcategory":"Music",
            "type":"Retail Goods"
        }
    ],
    "sg:phone":"+1 707 472 0455",
    "sg:postcode":"95482",
    "sg:province":"CA",
    "sg:tags":[
        "compact",
        "record",
        "disc",
        "tape"
    ],
    "wof:name":"D J Pinoy Music",
    "wof:placetype":"venue"
},
  "geometry": {"coordinates":[-123.20684900000001,39.147102],"type":"Point"}
}