{
  "type": "Feature",
  "properties": {
    "addr:full":"16155 W 1st St Baldwin Park CA 91706",
    "addr:housenumber":"16155",
    "addr:postcode":"91706",
    "addr:street":"W 1St St",
    "iso:country":"US",
    "sg:address":"16155 W 1st St",
    "sg:city":"Baldwin Park",
    "sg:classifiers":[
        {
            "category":"Freight",
            "type":"Transportation"
        }
    ],
    "sg:phone":"+1 626 815 8771",
    "sg:postcode":"91706",
    "sg:province":"CA",
    "sg:tags":[
        "operator",
        "local",
        "trucking"
    ],
    "wof:name":"G O Rodriguez Trucking",
    "wof:placetype":"venue"
},
  "geometry": {"coordinates":[-117.93573000000001,34.121687],"type":"Point"}
}