{
  "type": "Feature",
  "properties": {
    "addr:full":"774 W California Ave Glendale CA 91203",
    "addr:housenumber":"774",
    "addr:postcode":"91203",
    "addr:street":"W California Ave",
    "iso:country":"US",
    "sg:address":"774 W California Ave",
    "sg:city":"Glendale",
    "sg:classifiers":[
        {
            "category":"Autos & Motor Vehicles",
            "subcategory":"Auto Supplies",
            "type":"Retail Goods"
        }
    ],
    "sg:phone":"+1 818 240 3344",
    "sg:postcode":"91203",
    "sg:province":"CA",
    "sg:tags":[
        "alternator",
        "generator"
    ],
    "wof:name":"So Cal Alternater & Starter",
    "wof:placetype":"venue"
},
  "geometry": {"coordinates":[-118.272171,34.149902],"type":"Point"}
}