{
  "type": "Feature",
  "properties": {
    "iso:country":"US",
    "sg:address":"1 Blackfield Dr",
    "sg:city":"Belvedere Tiburon",
    "sg:classifiers":[
        {
            "category":"Mining & Drilling",
            "type":"Manufacturing & Wholesale Goods"
        }
    ],
    "sg:phone":"+1 415 389 8012",
    "sg:postcode":"94920",
    "sg:province":"CA",
    "sg:tags":[
        "sand",
        "industrial"
    ],
    "wof:name":"Bbi Sand & Gravel",
    "wof:placetype":"venue"
},
  "geometry": {"coordinates":[-122.500794,37.900114],"type":"Point"}
}