{
  "type": "Feature",
  "properties": {
    "addr:full":"60 Tehama St San Francisco CA 94105",
    "addr:housenumber":"60",
    "addr:postcode":"94105",
    "addr:street":"Tehama St",
    "iso:country":"US",
    "sg:address":"60 Tehama St",
    "sg:city":"San Francisco",
    "sg:classifiers":[
        {
            "category":"Shopping",
            "subcategory":"Computers & Home Electronics",
            "type":"Retail Goods"
        }
    ],
    "sg:phone":"+1 415 512 2093",
    "sg:postcode":"94105",
    "sg:province":"CA",
    "sg:tags":[
        "software"
    ],
    "sg:website":"www.fontshop.com",
    "wof:name":"Font Shop San Francisco",
    "wof:placetype":"venue"
},
  "geometry": {"coordinates":[-122.396871,37.787133],"type":"Point"}
}