{
  "type": "Feature",
  "properties": {
    "addr:full":"181 N E St San Bernardino CA 92401",
    "addr:housenumber":"181",
    "addr:postcode":"92401",
    "addr:street":"N E St",
    "iso:country":"US",
    "sg:address":"181 N E St",
    "sg:city":"San Bernardino",
    "sg:classifiers":[
        {
            "category":"Building & Trades",
            "subcategory":"Landscaping Services",
            "type":"Services"
        }
    ],
    "sg:phone":"+1 909 888 5568",
    "sg:postcode":"92401",
    "sg:province":"CA",
    "sg:tags":[
        "designer",
        "landscape"
    ],
    "wof:name":"Richard Pope & Associates",
    "wof:placetype":"venue"
},
  "geometry": {"coordinates":[-117.29407500000001,34.104396],"type":"Point"}
}