{
  "type": "Feature",
  "properties": {
    "addr:full":"1804 S La Cienega Blvd Los Angeles CA 90035",
    "addr:housenumber":"1804",
    "addr:postcode":"90035",
    "addr:street":"S La Cienega Blvd",
    "iso:country":"US",
    "sg:address":"1804 S La Cienega Blvd",
    "sg:city":"Los Angeles",
    "sg:classifiers":[
        {
            "category":"Professional",
            "type":"Services"
        }
    ],
    "sg:phone":"+1 310 838 3263",
    "sg:postcode":"90035",
    "sg:province":"CA",
    "sg:tags":[
        "caterer"
    ],
    "wof:name":"Juan Moreno Catering",
    "wof:placetype":"venue"
},
  "geometry": {"coordinates":[-118.376634,34.443818],"type":"Point"}
}