{
  "type": "Feature",
  "properties": {
    "iso:country":"US",
    "sg:address":"50 Center St",
    "sg:city":"Rio Dell",
    "sg:classifiers":[
        {
            "category":"Government",
            "subcategory":"Fire Station",
            "type":"Public Place"
        }
    ],
    "sg:phone":"+1 707 764 3329",
    "sg:postcode":"95562",
    "sg:province":"CA",
    "sg:tags":[
        "department"
    ],
    "wof:name":"Rio Dell Fire Protection Dst",
    "wof:placetype":"venue"
},
  "geometry": {"coordinates":[-124.10612399999999,40.50171],"type":"Point"}
}