{
  "type": "Feature",
  "properties": {
    "addr:full":"3138 Roosevelt St Carlsbad CA 92008",
    "addr:housenumber":"3138",
    "addr:postcode":"92008",
    "addr:street":"Roosevelt St",
    "iso:country":"US",
    "sg:address":"3138 Roosevelt St",
    "sg:city":"Carlsbad",
    "sg:classifiers":[
        {
            "category":"Shopping",
            "subcategory":"Computers & Home Electronics",
            "type":"Retail Goods"
        }
    ],
    "sg:phone":"+1 760 434 4101",
    "sg:postcode":"92008",
    "sg:province":"CA",
    "sg:tags":[
        "software"
    ],
    "sg:website":"www.compumove.com",
    "wof:name":"Compu Move Systems",
    "wof:placetype":"venue"
},
  "geometry": {"coordinates":[-117.346144,33.158458],"type":"Point"}
}