{
  "type": "Feature",
  "properties": {
    "addr:full":"2750 Dawson Ave Long Beach CA 90755",
    "addr:housenumber":"2750",
    "addr:postcode":"90755",
    "addr:street":"Dawson Ave",
    "iso:country":"US",
    "sg:address":"2750 Dawson Ave",
    "sg:city":"Long Beach",
    "sg:classifiers":[
        {
            "category":"Wholesale",
            "subcategory":"Machinery & Supplies",
            "type":"Manufacturing & Wholesale Goods"
        }
    ],
    "sg:phone":"+1 562 490 0030",
    "sg:postcode":"90755",
    "sg:province":"CA",
    "sg:tags":[
        "industrial",
        "tank"
    ],
    "wof:name":"Western Pacific Products Inc",
    "wof:placetype":"venue"
},
  "geometry": {"coordinates":[-118.16534,33.807102],"type":"Point"}
}