{
  "type": "Feature",
  "properties": {
    "iso:country":"US",
    "sg:address":"6611 Haskell Ave",
    "sg:city":"Van Nuys",
    "sg:classifiers":[
        {
            "category":"Real Estate",
            "subcategory":"Real Estate Operator",
            "type":"Services"
        }
    ],
    "sg:phone":"+1 818 787 5651",
    "sg:postcode":"91406",
    "sg:province":"CA",
    "sg:tags":[
        "apartment"
    ],
    "wof:name":"Haskell Granada Apartments",
    "wof:placetype":"venue"
},
  "geometry": {"coordinates":[-118.474992,34.191144],"type":"Point"}
}