{
  "type": "Feature",
  "properties": {
    "addr:full":"3499 Hiatt Dr Redding CA 96003",
    "addr:housenumber":"3499",
    "addr:postcode":"96003",
    "addr:street":"Hiatt Dr",
    "iso:country":"US",
    "sg:address":"3499 Hiatt Dr",
    "sg:city":"Redding",
    "sg:classifiers":[
        {
            "category":"Government",
            "subcategory":"Office",
            "type":"Public Place"
        }
    ],
    "sg:phone":"+1 530 225 5574",
    "sg:postcode":"96003",
    "sg:province":"CA",
    "sg:tags":[
        "county"
    ],
    "wof:name":"Department of Human Services",
    "wof:placetype":"venue"
},
  "geometry": {"coordinates":[-122.403971,40.631008],"type":"Point"}
}