{
  "type": "Feature",
  "properties": {
    "addr:full":"3250 W Olympic Blvd Los Angeles CA 90006",
    "addr:housenumber":"3250",
    "addr:postcode":"90006",
    "addr:street":"W Olympic Blvd",
    "iso:country":"US",
    "sg:address":"3250 W Olympic Blvd",
    "sg:city":"Los Angeles",
    "sg:classifiers":[
        {
            "category":"Shopping",
            "subcategory":"Music",
            "type":"Retail Goods"
        }
    ],
    "sg:phone":"+1 323 525 0477",
    "sg:postcode":"90006",
    "sg:province":"CA",
    "sg:tags":[
        "m"
    ],
    "wof:name":"Chois Records",
    "wof:placetype":"venue"
},
  "geometry": {"coordinates":[-118.308683,34.052561],"type":"Point"}
}