{
  "type": "Feature",
  "properties": {
    "addr:full":"5716 E Jensen Ave Fresno CA 93725",
    "addr:housenumber":"5716",
    "addr:postcode":"93725",
    "addr:street":"E Jensen Ave",
    "iso:country":"US",
    "sg:address":"5716 E Jensen Ave",
    "sg:city":"Fresno",
    "sg:classifiers":[
        {
            "category":"Farming",
            "subcategory":"Vineyard",
            "type":"Manufacturing & Wholesale Goods"
        }
    ],
    "sg:phone":"+1 559 486 3947",
    "sg:postcode":"93725",
    "sg:province":"CA",
    "sg:tags":[
        "grape"
    ],
    "wof:name":"Mansmann Vineyards",
    "wof:placetype":"venue"
},
  "geometry": {"coordinates":[-119.694401,36.707384],"type":"Point"}
}