{
  "type": "Feature",
  "properties": {
    "addr:full":"7838 Clybourn Ave Sun Valley CA 91352",
    "addr:housenumber":"7838",
    "addr:postcode":"91352",
    "addr:street":"Clybourn Ave",
    "iso:country":"US",
    "sg:address":"7838 Clybourn Ave",
    "sg:city":"Sun Valley",
    "sg:classifiers":[
        {
            "category":"Wholesale",
            "subcategory":"Photographic Equipment",
            "type":"Manufacturing & Wholesale Goods"
        }
    ],
    "sg:phone":"+1 818 771 1281",
    "sg:postcode":"91352",
    "sg:province":"CA",
    "sg:tags":[
        "motion",
        "picture",
        "supply"
    ],
    "sg:website":"www.bmlighting.com",
    "wof:name":"Bardwell & Mc Alister Inc",
    "wof:placetype":"venue"
},
  "geometry": {"coordinates":[-118.363964,34.213773],"type":"Point"}
}