{
  "type": "Feature",
  "properties": {
    "iso:country":"US",
    "sg:address":"3045 Rosecrans St",
    "sg:city":"San Diego",
    "sg:classifiers":[
        {
            "category":"Professional",
            "subcategory":"Lawyer & Legal Services",
            "type":"Services"
        }
    ],
    "sg:phone":"+1 619 225 0739",
    "sg:postcode":"92110",
    "sg:province":"CA",
    "sg:tags":[
        "attorney"
    ],
    "wof:name":"D J Fontilla",
    "wof:placetype":"venue"
},
  "geometry": {"coordinates":[-117.211006,32.745779],"type":"Point"}
}