{
  "type": "Feature",
  "properties": {
    "addr:full":"1038 W Main St Santa Maria CA 93458",
    "addr:housenumber":"1038",
    "addr:postcode":"93458",
    "addr:street":"W Main St",
    "iso:country":"US",
    "sg:address":"1038 W Main St",
    "sg:city":"Santa Maria",
    "sg:classifiers":[
        {
            "category":"Health Services",
            "subcategory":"Doctor",
            "type":"Services"
        }
    ],
    "sg:phone":"+1 805 925 9091",
    "sg:postcode":"93458",
    "sg:province":"CA",
    "sg:tags":[
        "dentist"
    ],
    "wof:name":"Abdallah Al-Harazneh DDS",
    "wof:placetype":"venue"
},
  "geometry": {"coordinates":[-120.450018,34.953129],"type":"Point"}
}