{
  "type": "Feature",
  "properties": {
    "addr:full":"3790 Red Oak Way Redwood City, Ca 94061",
    "wof:categories":[
        "education_and_religion:education=school"
    ],
    "wof:name":"Roy Cloud Elementary School",
    "wof:placetype":"venue"
},
  "geometry": {"coordinates":[-122.25622626565544,37.45860494606643],"type":"Point"}
}