{
  "type": "Feature",
  "properties": {
    "iso:country":"US",
    "sg:address":"2074 2nd St",
    "sg:city":"Livermore",
    "sg:classifiers":[
        {
            "category":"Shopping",
            "subcategory":"Florist",
            "type":"Retail Goods"
        }
    ],
    "sg:phone":"+1 925 447 0803",
    "sg:postcode":"94550",
    "sg:province":"CA",
    "wof:name":"Knodt's Flowers",
    "wof:placetype":"venue"
},
  "geometry": {"coordinates":[-121.770443,37.680336],"type":"Point"}
}