{
  "type": "Feature",
  "properties": {
    "iso:country":"US",
    "sg:address":"305 N Ash St",
    "sg:city":"Escondido",
    "sg:classifiers":[
        {
            "category":"Food & Beverages",
            "subcategory":"Liquor & Beverages",
            "type":"Retail Goods"
        }
    ],
    "sg:phone":"+1 760 747 2828",
    "sg:postcode":"92027",
    "sg:province":"CA",
    "wof:name":"S C Liquor Mart",
    "wof:placetype":"venue"
},
  "geometry": {"coordinates":[-117.066759,33.129731],"type":"Point"}
}