{
  "type": "Feature",
  "properties": {
    "iso:country":"US",
    "sg:address":"2615 Davis St",
    "sg:city":"San Leandro",
    "sg:classifiers":[
        {
            "category":"Utilities",
            "subcategory":"Refuse",
            "type":"Services"
        }
    ],
    "sg:phone":"+1 510 638 2303",
    "sg:postcode":"94577",
    "sg:province":"CA",
    "sg:tags":[
        "material",
        "system"
    ],
    "wof:name":"Waste Management",
    "wof:placetype":"venue"
},
  "geometry": {"coordinates":[-122.18942,37.715623],"type":"Point"}
}