{
  "type": "Feature",
  "properties": {
    "iso:country":"US",
    "sg:address":"76 Lee St",
    "sg:city":"Mill Valley",
    "sg:classifiers":[
        {
            "category":"Organizations",
            "subcategory":"Community Association",
            "type":"Services"
        }
    ],
    "sg:phone":"+1 415 383 6130",
    "sg:postcode":"94941",
    "sg:province":"CA",
    "sg:tags":[
        "environmental",
        "org"
    ],
    "sg:website":"www.butterflylodge.org",
    "wof:name":"Health & Habitat",
    "wof:placetype":"venue"
},
  "geometry": {"coordinates":[-122.55394,37.921023],"type":"Point"}
}