{
  "type": "Feature",
  "properties": {
    "iso:country":"US",
    "sg:address":"1733 Monrovia Ave",
    "sg:city":"Costa Mesa",
    "sg:classifiers":[
        {
            "category":"Wholesale",
            "subcategory":"Sporting Goods",
            "type":"Manufacturing & Wholesale Goods"
        },
        {
            "category":"Shopping",
            "subcategory":"Bicycles & Sporting Goods",
            "type":"Retail Goods"
        }
    ],
    "sg:phone":"+1 949 642 6484",
    "sg:postcode":"92627",
    "sg:province":"CA",
    "sg:tags":[
        "equipment",
        "golf",
        "supply"
    ],
    "sg:website":"www.ironfinders.com",
    "wof:name":"Ironfinder",
    "wof:placetype":"venue"
},
  "geometry": {"coordinates":[-117.93632100000001,33.637363],"type":"Point"}
}