{
  "type": "Feature",
  "properties": {
    "iso:country":"US",
    "sg:address":"1330 N Broadway  Ste 200H",
    "sg:city":"Walnut Creek",
    "sg:classifiers":[
        {
            "category":"Professional",
            "subcategory":"Computer Services",
            "type":"Services"
        }
    ],
    "sg:phone":"+1 415 944 9090",
    "sg:postcode":"94596",
    "sg:province":"CA",
    "sg:website":"http://www.parkcirca.com",
    "wof:name":"Park Circa",
    "wof:placetype":"venue"
},
  "geometry": {"coordinates":[-122.060253,37.900622],"type":"Point"}
}