{
  "type": "Feature",
  "properties": {
    "addr:full":"130 Cremona Dr Goleta CA 93117",
    "addr:housenumber":"130",
    "addr:postcode":"93117",
    "addr:street":"Cremona Dr",
    "iso:country":"US",
    "sg:address":"130 Cremona Dr",
    "sg:city":"Goleta",
    "sg:classifiers":[
        {
            "category":"Government",
            "subcategory":"Office",
            "type":"Public Place"
        }
    ],
    "sg:phone":"+1 805 961 7500",
    "sg:postcode":"93117",
    "sg:province":"CA",
    "sg:tags":[
        "town",
        "city"
    ],
    "wof:name":"City of Goleta",
    "wof:placetype":"venue"
},
  "geometry": {"coordinates":[-119.85661,34.432261],"type":"Point"}
}