{
  "type": "Feature",
  "properties": {
    "addr:full":"1031 National City Blvd National City CA 91950",
    "addr:housenumber":"1031",
    "addr:postcode":"91950",
    "addr:street":"National City Blvd",
    "iso:country":"US",
    "sg:address":"1031 National City Blvd",
    "sg:city":"National City",
    "sg:classifiers":[
        {
            "category":"Wholesale",
            "subcategory":"Auto Parts",
            "type":"Manufacturing & Wholesale Goods"
        }
    ],
    "sg:phone":"+1 619 474 2408",
    "sg:postcode":"91950",
    "sg:province":"CA",
    "sg:tags":[
        "shaft",
        "drive"
    ],
    "wof:name":"Shaft Master",
    "wof:placetype":"venue"
},
  "geometry": {"coordinates":[-117.105936,32.673522],"type":"Point"}
}