{
  "type": "Feature",
  "properties": {
    "addr:full":"263 Speith Way Riverside CA 92507",
    "addr:housenumber":"263",
    "addr:postcode":"92507",
    "addr:street":"Speith Way",
    "iso:country":"US",
    "sg:address":"263 Speith Way",
    "sg:city":"Riverside",
    "sg:classifiers":[
        {
            "category":"Professional",
            "subcategory":"Management & Consulting",
            "type":"Services"
        }
    ],
    "sg:phone":"+1 951 781 7386",
    "sg:postcode":"92507",
    "sg:province":"CA",
    "sg:tags":[
        "fuel"
    ],
    "wof:name":"Water Management Group",
    "wof:placetype":"venue"
},
  "geometry": {"coordinates":[-117.316868,33.977298],"type":"Point"}
}