{
  "type": "Feature",
  "properties": {
    "addr:full":"1233 W Rancho Vista Blvd P Palmdale CA 93551",
    "addr:housenumber":"1233",
    "addr:postcode":"93551",
    "addr:street":"W Rancho Vista Blvd P Palmdale",
    "iso:country":"US",
    "sg:address":"1233 W Rancho Vista Blvd P",
    "sg:city":"Palmdale",
    "sg:classifiers":[
        {
            "category":"Fast Food",
            "type":"Food & Drink"
        },
        {
            "category":"Restaurant",
            "type":"Food & Drink"
        },
        {
            "category":"Food & Beverages",
            "subcategory":"Groceries & Convenience Stores",
            "type":"Retail Goods"
        }
    ],
    "sg:phone":"+1 661 265 1690",
    "sg:postcode":"93551",
    "sg:province":"CA",
    "sg:tags":[
        "shop",
        "american",
        "sandwich",
        "take"
    ],
    "sg:website":"http://www.subway.com",
    "wof:name":"Subway",
    "wof:placetype":"venue"
},
  "geometry": {"coordinates":[-118.15302699999999,34.601841],"type":"Point"}
}