{
  "type": "Feature",
  "properties": {
    "addr:full":"19541 Richwood Dr Cupertino CA 95014",
    "addr:housenumber":"19541",
    "addr:postcode":"95014",
    "addr:street":"Richwood Dr",
    "iso:country":"US",
    "sg:address":"19541 Richwood Dr",
    "sg:city":"Cupertino",
    "sg:classifiers":[
        {
            "category":"Restaurant",
            "type":"Food & Drink"
        }
    ],
    "sg:phone":"+1 408 873 1444",
    "sg:postcode":"95014",
    "sg:province":"CA",
    "sg:tags":[
        "sushi",
        "bar",
        "japanese"
    ],
    "sg:website":"kitshosushi.com",
    "wof:name":"Kitsho",
    "wof:placetype":"venue"
},
  "geometry": {"coordinates":[-122.014837,37.321945],"type":"Point"}
}