{
  "type": "Feature",
  "properties": {
    "iso:country":"US",
    "sg:address":"1227 Buena Vista St",
    "sg:city":"Duarte",
    "sg:classifiers":[
        {
            "category":"Health Services",
            "subcategory":"Chiropractor",
            "type":"Services"
        }
    ],
    "sg:phone":"+1 626 303 4988",
    "sg:postcode":"91010",
    "sg:province":"CA",
    "wof:name":"Buena Vista Chiropractic",
    "wof:placetype":"venue"
},
  "geometry": {"coordinates":[-117.977631,34.138599],"type":"Point"}
}