{
  "type": "Feature",
  "properties": {
    "addr:full":"11819 Imperial Hwy Norwalk CA 90650",
    "addr:housenumber":"11819",
    "addr:postcode":"90650",
    "addr:street":"Imperial Hwy",
    "iso:country":"US",
    "sg:address":"11819 Imperial Hwy",
    "sg:city":"Norwalk",
    "sg:classifiers":[
        {
            "category":"Wholesale",
            "subcategory":"Computers",
            "type":"Manufacturing & Wholesale Goods"
        },
        {
            "category":"Professional",
            "subcategory":"Computer Services",
            "type":"Services"
        }
    ],
    "sg:phone":"+1 562 651 2345",
    "sg:postcode":"90650",
    "sg:province":"CA",
    "sg:tags":[
        "repair"
    ],
    "wof:name":"Mail Stop Computers",
    "wof:placetype":"venue"
},
  "geometry": {"coordinates":[-118.081001,33.917301],"type":"Point"}
}