{
  "type": "Feature",
  "properties": {
    "addr:full":"19900 Beach Blvd Ste F1 Huntington Beach CA 92648",
    "addr:housenumber":"19900",
    "addr:postcode":"92648",
    "addr:street":"Beach Blvd Ste F1",
    "iso:country":"US",
    "sg:address":"19900 Beach Blvd Ste F1",
    "sg:city":"Huntington Beach",
    "sg:classifiers":[
        {
            "category":"Banks & Credit Unions",
            "subcategory":"Financial Services",
            "type":"Services"
        }
    ],
    "sg:phone":"+1 714 968 7963",
    "sg:postcode":"92648",
    "sg:province":"CA",
    "sg:tags":[
        "broker",
        "mortgage"
    ],
    "wof:name":"Manhathan Mortgage Corporation",
    "wof:placetype":"venue"
},
  "geometry": {"coordinates":[-117.988298,33.673509],"type":"Point"}
}