{
  "type": "Feature",
  "properties": {
    "addr:full":"55 Cyril Magnin St San Francisco CA 94102",
    "addr:housenumber":"55",
    "addr:postcode":"94102",
    "addr:street":"Cyril Magnin St",
    "iso:country":"US",
    "sg:address":"55 Cyril Magnin St",
    "sg:city":"San Francisco",
    "sg:classifiers":[
        {
            "category":"Retail",
            "subcategory":"Auto Rental",
            "type":"Services"
        }
    ],
    "sg:phone":"+1 415 986 2319",
    "sg:postcode":"94102",
    "sg:province":"CA",
    "sg:tags":[
        "car"
    ],
    "wof:name":"Hertz",
    "wof:placetype":"venue"
},
  "geometry": {"coordinates":[-122.40863299999999,37.784914],"type":"Point"}
}