{
  "type": "Feature",
  "properties": {
    "addr:full":"5288 Hanover Dr Cypress CA 90630",
    "addr:housenumber":"5288",
    "addr:postcode":"90630",
    "addr:street":"Hanover Dr",
    "iso:country":"US",
    "sg:address":"5288 Hanover Dr",
    "sg:city":"Cypress",
    "sg:classifiers":[
        {
            "category":"Manufacturing",
            "subcategory":"Tools & Machinery",
            "type":"Manufacturing & Wholesale Goods"
        }
    ],
    "sg:phone":"+1 714 827 0733",
    "sg:postcode":"90630",
    "sg:province":"CA",
    "sg:tags":[
        "industrial",
        "mfg"
    ],
    "wof:name":"G&M Precision Machine Works",
    "wof:placetype":"venue"
},
  "geometry": {"coordinates":[-118.03930800000001,33.821553],"type":"Point"}
}