{
  "type": "Feature",
  "properties": {
    "iso:country":"US",
    "sg:address":"1173 Forest Ave",
    "sg:city":"Pacific Grove",
    "sg:classifiers":[
        {
            "category":"Shopping",
            "subcategory":"Bicycles & Sporting Goods",
            "type":"Retail Goods"
        }
    ],
    "sg:phone":"+1 831 648 3300",
    "sg:postcode":"93950",
    "sg:province":"CA",
    "sg:tags":[
        "equipment",
        "skateboard"
    ],
    "wof:name":"68 Skate",
    "wof:placetype":"venue"
},
  "geometry": {"coordinates":[-121.92163,36.606359],"type":"Point"}
}