{
  "type": "Feature",
  "properties": {
    "iso:country":"US",
    "sg:address":"333 Sunset Ave",
    "sg:city":"Suisun City",
    "sg:classifiers":[
        {
            "category":"Government",
            "subcategory":"Office",
            "type":"Public Place"
        }
    ],
    "sg:phone":"+1 707 428 2041",
    "sg:postcode":"94585",
    "sg:province":"CA",
    "sg:tags":[
        "state",
        "inspection"
    ],
    "wof:name":"Equalization Board",
    "wof:placetype":"venue"
},
  "geometry": {"coordinates":[-122.020629,38.25052],"type":"Point"}
}