{
  "type": "Feature",
  "properties": {
    "addr:full":"900 E Stanley Blvd Livermore CA 94550",
    "addr:housenumber":"900",
    "addr:postcode":"94550",
    "addr:street":"E Stanley Blvd",
    "iso:country":"US",
    "sg:address":"900 E Stanley Blvd",
    "sg:city":"Livermore",
    "sg:classifiers":[
        {
            "category":"Health Services",
            "subcategory":"Nursing And Care Facility",
            "type":"Services"
        }
    ],
    "sg:phone":"+1 925 373 3636",
    "sg:postcode":"94550",
    "sg:province":"CA",
    "sg:tags":[
        "home",
        "retirement",
        "community"
    ],
    "wof:name":"Heritage Estates",
    "wof:placetype":"venue"
},
  "geometry": {"coordinates":[-121.78595199999999,37.67835],"type":"Point"}
}