{
  "type": "Feature",
  "properties": {
    "addr:full":"2019 Venice Blvd Los Angeles CA 90006",
    "addr:housenumber":"2019",
    "addr:postcode":"90006",
    "addr:street":"Venice Blvd",
    "iso:country":"US",
    "sg:address":"2019 Venice Blvd",
    "sg:city":"Los Angeles",
    "sg:classifiers":[
        {
            "category":"Restaurant",
            "type":"Food & Drink"
        }
    ],
    "sg:phone":"+1 323 735 6276",
    "sg:postcode":"90006",
    "sg:province":"CA",
    "wof:name":"Comedor Nicaraguense Camacho",
    "wof:placetype":"venue"
},
  "geometry": {"coordinates":[-118.30098599999999,34.043775],"type":"Point"}
}