{
  "type": "Feature",
  "properties": {
    "iso:country":"US",
    "sg:address":"270 E 17th St",
    "sg:city":"Costa Mesa",
    "sg:classifiers":[
        {
            "category":"Professional",
            "type":"Services"
        }
    ],
    "sg:phone":"+1 949 646 4144",
    "sg:postcode":"92627",
    "sg:province":"CA",
    "sg:tags":[
        "establishment"
    ],
    "wof:name":"Bedroom",
    "wof:placetype":"venue"
},
  "geometry": {"coordinates":[-117.91594600000001,33.633612],"type":"Point"}
}