{
  "type": "Feature",
  "properties": {
    "iso:country":"US",
    "sg:address":"660 Las Alturas Rd",
    "sg:city":"Santa Barbara",
    "sg:classifiers":[
        {
            "category":"Building & Trades",
            "subcategory":"Landscaping Services",
            "type":"Services"
        }
    ],
    "sg:phone":"+1 805 962 2323",
    "sg:postcode":"93103",
    "sg:province":"CA",
    "sg:tags":[
        "landscape",
        "contractor"
    ],
    "wof:name":"Help U Scape",
    "wof:placetype":"venue"
},
  "geometry": {"coordinates":[-119.6814,34.438209],"type":"Point"}
}