{
  "type": "Feature",
  "properties": {
    "iso:country":"US",
    "sg:address":"445 El Cerrito Plaza",
    "sg:city":"El Cerrito",
    "sg:classifiers":[
        {
            "category":"Shopping",
            "subcategory":"Clothing, Apparel, & Fashions",
            "type":"Retail Goods"
        }
    ],
    "sg:phone":"+1 510 526 3528",
    "sg:postcode":"94530",
    "sg:province":"CA",
    "sg:tags":[
        "accessory",
        "clothing",
        "women's"
    ],
    "sg:website":"www.dressbarn.com",
    "wof:name":"Dress Barn",
    "wof:placetype":"venue"
},
  "geometry": {"coordinates":[-122.299004,37.8997],"type":"Point"}
}