{
  "type": "Feature",
  "properties": {
    "iso:country":"US",
    "sg:address":"889 Redbud Pl",
    "sg:city":"Chula Vista",
    "sg:classifiers":[
        {
            "category":"Professional",
            "type":"Services"
        }
    ],
    "sg:phone":"+1 619 216 4804",
    "sg:postcode":"91910",
    "sg:province":"CA",
    "wof:name":"Jack H Wendy C Meng",
    "wof:placetype":"venue"
},
  "geometry": {"coordinates":[-117.026213,32.632288],"type":"Point"}
}