{
  "type": "Feature",
  "properties": {
    "iso:country":"US",
    "sg:address":"5930 Sutter Ave",
    "sg:city":"Carmichael",
    "sg:classifiers":[
        {
            "category":"Real Estate",
            "subcategory":"Real Estate Operator",
            "type":"Services"
        }
    ],
    "sg:phone":"+1 916 489 5014",
    "sg:postcode":"95608",
    "sg:province":"CA",
    "sg:tags":[
        "apartment"
    ],
    "wof:name":"Sutter Court Apartments",
    "wof:placetype":"venue"
},
  "geometry": {"coordinates":[-121.327003,38.633301],"type":"Point"}
}