{
  "type": "Feature",
  "properties": {
    "iso:country":"US",
    "sg:address":"3 Hopkins St",
    "sg:city":"Irvine",
    "sg:classifiers":[
        {
            "category":"Wholesale",
            "subcategory":"Non-durable Goods",
            "type":"Manufacturing & Wholesale Goods"
        }
    ],
    "sg:phone":"+1 714 836 1770",
    "sg:postcode":"92612",
    "sg:province":"CA",
    "wof:name":"Pacific Contact Corporation",
    "wof:placetype":"venue"
},
  "geometry": {"coordinates":[-117.82579699999999,33.665711],"type":"Point"}
}