{
  "type": "Feature",
  "properties": {
    "addr:full":"4122 Philadelphia St Chino CA 91710",
    "addr:housenumber":"4122",
    "addr:postcode":"91710",
    "addr:street":"Philadelphia St",
    "iso:country":"US",
    "sg:address":"4122 Philadelphia St",
    "sg:city":"Chino",
    "sg:classifiers":[
        {
            "category":"Autos & Motor Vehicles",
            "subcategory":"Automobile Sales",
            "type":"Retail Goods"
        },
        {
            "category":"Autos & Motor Vehicles",
            "subcategory":"Auto Supplies",
            "type":"Retail Goods"
        },
        {
            "category":"Retail",
            "subcategory":"Auto Repair",
            "type":"Services"
        }
    ],
    "sg:phone":"+1 909 465 9867",
    "sg:postcode":"91710",
    "sg:province":"CA",
    "sg:tags":[
        "car",
        "used",
        "brake",
        "tire"
    ],
    "wof:name":"Tires Up",
    "wof:placetype":"venue"
},
  "geometry": {"coordinates":[-117.715079,34.033412],"type":"Point"}
}