{
  "type": "Feature",
  "properties": {
    "addr:full":"2350 Athens Ave Redding CA 96001",
    "addr:housenumber":"2350",
    "addr:postcode":"96001",
    "addr:street":"Athens Ave",
    "iso:country":"US",
    "sg:address":"2350 Athens Ave",
    "sg:city":"Redding",
    "sg:classifiers":[
        {
            "category":"Home & Garden",
            "subcategory":"Furniture",
            "type":"Retail Goods"
        }
    ],
    "sg:phone":"+1 530 243 4535",
    "sg:postcode":"96001",
    "sg:province":"CA",
    "sg:tags":[
        "store"
    ],
    "sg:website":"www.mcmahans-furniture.com",
    "wof:name":"Mcmahans Furniture & Appls",
    "wof:placetype":"venue"
},
  "geometry": {"coordinates":[-122.375878,40.57673],"type":"Point"}
}