{
  "type": "Feature",
  "properties": {
    "iso:country":"US",
    "sg:address":"1647 Solano Ave",
    "sg:city":"Berkeley",
    "sg:phone":"+1 510 526 3700",
    "sg:postcode":"94707",
    "sg:province":"CA",
    "wof:name":"Bendean",
    "wof:placetype":"venue"
},
  "geometry": {"coordinates":[-122.28349300000001,37.89114],"type":"Point"}
}