{
  "type": "Feature",
  "properties": {
    "iso:country":"US",
    "sg:address":"4094 Glencoe Avenue Unit A, Marina del Rey, CA",
    "sg:classifiers":[
        {
            "category":"Professional",
            "subcategory":"Computer Services",
            "type":"Services"
        }
    ],
    "sg:phone":"+1 203 054 2200",
    "sg:postcode":"90292",
    "sg:province":"CA",
    "sg:website":"http://www.neilsoft.com",
    "wof:name":"Neilsoft Ltd",
    "wof:placetype":"venue"
},
  "geometry": {"coordinates":[-118.443032,33.990158],"type":"Point"}
}