{
  "type": "Feature",
  "properties": {
    "addr:full":"20556 Powder Horn Rd Hidden Valley Lk CA 95467",
    "addr:housenumber":"20556",
    "addr:postcode":"95467",
    "addr:street":"Powder Horn Rd",
    "iso:country":"US",
    "sg:address":"20556 Powder Horn Rd",
    "sg:city":"Hidden Valley Lk",
    "sg:classifiers":[
        {
            "category":"Shopping",
            "subcategory":"Hobbies, Toys, & Games",
            "type":"Retail Goods"
        }
    ],
    "sg:phone":"+1 707 987 2408",
    "sg:postcode":"95467",
    "sg:province":"CA",
    "sg:tags":[
        "doll"
    ],
    "wof:name":"J Hule",
    "wof:placetype":"venue"
},
  "geometry": {"coordinates":[-122.53661099999999,38.787638],"type":"Point"}
}