{
  "type": "Feature",
  "properties": {
    "addr:full":"4201 Macdonald Ave Richmond CA 94805",
    "addr:housenumber":"4201",
    "addr:postcode":"94805",
    "addr:street":"Macdonald Ave",
    "iso:country":"US",
    "sg:address":"4201 Macdonald Ave",
    "sg:city":"Richmond",
    "sg:classifiers":[
        {
            "category":"Autos & Motor Vehicles",
            "subcategory":"Automobile Sales",
            "type":"Retail Goods"
        }
    ],
    "sg:phone":"+1 510 232 8202",
    "sg:postcode":"94805",
    "sg:province":"CA",
    "sg:tags":[
        "car",
        "dealer"
    ],
    "wof:name":"Pars Auto",
    "wof:placetype":"venue"
},
  "geometry": {"coordinates":[-122.32904600000001,37.93304],"type":"Point"}
}