{
  "type": "Feature",
  "properties": {
    "addr:full":"820 N Hobson Ave Broderick CA 95605",
    "addr:housenumber":"820",
    "addr:postcode":"95605",
    "addr:street":"N Hobson Ave",
    "iso:country":"US",
    "sg:address":"820 N Hobson Ave",
    "sg:city":"Broderick",
    "sg:classifiers":[
        {
            "category":"Building & Trades",
            "subcategory":"Landscaping Services",
            "type":"Services"
        }
    ],
    "sg:phone":"+1 916 372 8021",
    "sg:postcode":"95605",
    "sg:province":"CA",
    "sg:tags":[
        "landscape",
        "contractor"
    ],
    "wof:name":"Paul's Year Round Landscaping",
    "wof:placetype":"venue"
},
  "geometry": {"coordinates":[-121.54285299999999,38.59329],"type":"Point"}
}