{
  "type": "Feature",
  "properties": {
    "addr:full":"1727 Sweetwater Rd National City CA 91950",
    "addr:housenumber":"1727",
    "addr:postcode":"91950",
    "addr:street":"Sweetwater Rd",
    "iso:country":"US",
    "sg:address":"1727 Sweetwater Rd",
    "sg:city":"National City",
    "sg:classifiers":[
        {
            "category":"Health Services",
            "subcategory":"Doctor",
            "type":"Services"
        }
    ],
    "sg:phone":"+1 619 477 0045",
    "sg:postcode":"91950",
    "sg:province":"CA",
    "sg:tags":[
        "dentist"
    ],
    "wof:name":"Family Dentistry",
    "wof:placetype":"venue"
},
  "geometry": {"coordinates":[-117.08125099999999,32.661666],"type":"Point"}
}