{
  "type": "Feature",
  "properties": {
    "iso:country":"US",
    "sg:address":"2172 Railroad Ave",
    "sg:city":"Livermore",
    "sg:classifiers":[
        {
            "category":"Manufacturing",
            "subcategory":"Glass & Minerals",
            "type":"Manufacturing & Wholesale Goods"
        },
        {
            "category":"Retail",
            "subcategory":"Auto Repair",
            "type":"Services"
        }
    ],
    "sg:phone":"+1 925 606 9600",
    "sg:postcode":"94550",
    "sg:province":"CA",
    "sg:tags":[
        "plate",
        "glass-auto",
        "glass-wholesale",
        "window",
        "windshield",
        "manufacturer"
    ],
    "wof:name":"Lowest Price Auto Glass",
    "wof:placetype":"venue"
},
  "geometry": {"coordinates":[-121.76988,37.683332],"type":"Point"}
}