{
  "type": "Feature",
  "properties": {
    "iso:country":"US",
    "sg:address":"7733 N 1st St",
    "sg:city":"Fresno",
    "sg:classifiers":[
        {
            "category":"Food & Beverages",
            "subcategory":"Groceries & Convenience Stores",
            "type":"Retail Goods"
        }
    ],
    "sg:phone":"+1 559 439 4179",
    "sg:postcode":"93720",
    "sg:province":"CA",
    "sg:tags":[
        "grocer"
    ],
    "sg:website":"www.vons.com",
    "wof:name":"Vons Co",
    "wof:placetype":"venue"
},
  "geometry": {"coordinates":[-119.774621,36.850743],"type":"Point"}
}