{
  "type": "Feature",
  "properties": {
    "iso:country":"US",
    "sg:address":"1956 Fulton Avenue",
    "sg:city":"Sacramento",
    "sg:classifiers":[
        {
            "category":"Autos & Motor Vehicles",
            "subcategory":"Auto Supplies",
            "type":"Retail Goods"
        }
    ],
    "sg:phone":"+1 916 482 1000",
    "sg:postcode":"95825",
    "sg:province":"CA",
    "sg:tags":[
        "glass"
    ],
    "sg:website":"www.mikesmobileglass.com",
    "wof:name":"Mike's Mobile Glass",
    "wof:placetype":"venue"
},
  "geometry": {"coordinates":[-121.401268,38.600254],"type":"Point"}
}