{
  "type": "Feature",
  "properties": {
    "iso:country":"US",
    "sg:address":"46537 Mission Blvd.",
    "sg:city":"Fremont",
    "sg:classifiers":[
        {
            "category":"Shopping",
            "subcategory":"Mobile Phones",
            "type":"Retail Goods"
        }
    ],
    "sg:phone":"+1 510 438 8977",
    "sg:postcode":"94539",
    "sg:province":"CA",
    "sg:website":"celltowns.com",
    "wof:name":"Cell towns of Fremont",
    "wof:placetype":"venue"
},
  "geometry": {"coordinates":[-121.928156,37.491043],"type":"Point"}
}