{
  "type": "Feature",
  "properties": {
    "iso:country":"US",
    "sg:address":"301 4th St",
    "sg:city":"Marysville",
    "sg:classifiers":[
        {
            "category":"Social Services",
            "type":"Services"
        }
    ],
    "sg:phone":"+1 530 742 5483",
    "sg:postcode":"95901",
    "sg:province":"CA",
    "sg:tags":[
        "youth",
        "organization",
        "center"
    ],
    "wof:name":"Friday Night Live",
    "wof:placetype":"venue"
},
  "geometry": {"coordinates":[-121.58806199999999,39.139286],"type":"Point"}
}