{
  "type": "Feature",
  "properties": {
    "iso:country":"US",
    "sg:address":"14423 Spring Crest Dr",
    "sg:city":"Chino Hills",
    "sg:classifiers":[
        {
            "category":"Wholesale",
            "subcategory":"Electrical",
            "type":"Manufacturing & Wholesale Goods"
        }
    ],
    "sg:phone":"+1 909 590 4404",
    "sg:postcode":"91709",
    "sg:province":"CA",
    "sg:tags":[
        "semiconductor",
        "devices"
    ],
    "wof:name":"Semtech Corp",
    "wof:placetype":"venue"
},
  "geometry": {"coordinates":[-117.75146599999999,33.990294],"type":"Point"}
}