{
  "type": "Feature",
  "properties": {
    "iso:country":"US",
    "sg:address":"6247 Ross Ave",
    "sg:city":"Carmichael",
    "sg:classifiers":[
        {
            "category":"Home & Garden",
            "subcategory":"Building Materials",
            "type":"Retail Goods"
        }
    ],
    "sg:phone":"+1 916 944 7179",
    "sg:postcode":"95608",
    "sg:province":"CA",
    "sg:tags":[
        "front",
        "glass",
        "window",
        "store",
        "plate"
    ],
    "sg:website":"http://www.centralglass1.com",
    "wof:name":"Central Glass",
    "wof:placetype":"venue"
},
  "geometry": {"coordinates":[-121.320043,38.635822],"type":"Point"}
}