{
  "type": "Feature",
  "properties": {
    "iso:country":"US",
    "sg:address":"6362 Amy Ave",
    "sg:city":"Garden Grove",
    "sg:classifiers":[
        {
            "category":"Professional",
            "type":"Services"
        }
    ],
    "sg:phone":"+1 714 271 6210",
    "sg:postcode":"92845",
    "sg:province":"CA",
    "wof:name":"Winspray Co",
    "wof:placetype":"venue"
},
  "geometry": {"coordinates":[-118.021728,33.786743],"type":"Point"}
}