{
  "type": "Feature",
  "properties": {
    "addr:full":"6922 26th St Rio Linda CA 95673",
    "addr:housenumber":"6922",
    "addr:postcode":"95673",
    "addr:street":"26Th St",
    "iso:country":"US",
    "sg:address":"6922 26th St",
    "sg:city":"Rio Linda",
    "sg:classifiers":[
        {
            "category":"Retail",
            "subcategory":"Auto Rental",
            "type":"Services"
        }
    ],
    "sg:phone":"+1 916 991 3058",
    "sg:postcode":"95673",
    "sg:province":"CA",
    "sg:tags":[
        "recreational",
        "leasing",
        "vehicle"
    ],
    "wof:name":"California Rv Rentals & Rprs",
    "wof:placetype":"venue"
},
  "geometry": {"coordinates":[-121.40588700000001,38.695598],"type":"Point"}
}