{
  "type": "Feature",
  "properties": {
    "addr:full":"1227 W Valley Blvd Alhambra CA 91803",
    "addr:housenumber":"1227",
    "addr:postcode":"91803",
    "addr:street":"W Valley Blvd",
    "iso:country":"US",
    "sg:address":"1227 W Valley Blvd",
    "sg:city":"Alhambra",
    "sg:classifiers":[
        {
            "category":"Personal",
            "subcategory":"Beauty Salon",
            "type":"Services"
        }
    ],
    "sg:phone":"+1 626 576 4117",
    "sg:postcode":"91803",
    "sg:province":"CA",
    "wof:name":"Seven Beauty & Facial Salon",
    "wof:placetype":"venue"
},
  "geometry": {"coordinates":[-118.13690800000001,34.077846],"type":"Point"}
}