{
  "type": "Feature",
  "properties": {
    "addr:full":"440 19th St Bakersfield CA 93301",
    "addr:housenumber":"440",
    "addr:postcode":"93301",
    "addr:street":"19Th St",
    "iso:country":"US",
    "sg:address":"440 19th St",
    "sg:city":"Bakersfield",
    "sg:classifiers":[
        {
            "category":"Retail",
            "subcategory":"Auto Repair",
            "type":"Services"
        }
    ],
    "sg:phone":"+1 661 322 7408",
    "sg:postcode":"93301",
    "sg:province":"CA",
    "sg:tags":[
        "automobile",
        "top",
        "upholstery"
    ],
    "wof:name":"Auto Upholstery By Aquiles",
    "wof:placetype":"venue"
},
  "geometry": {"coordinates":[-119.006657,35.376264],"type":"Point"}
}