{
  "type": "Feature",
  "properties": {
    "iso:country":"US",
    "sg:address":"1800 Logan Ave",
    "sg:city":"San Diego",
    "sg:classifiers":[
        {
            "category":"Shopping",
            "subcategory":"Bicycles & Sporting Goods",
            "type":"Retail Goods"
        }
    ],
    "sg:phone":"+1 619 237 1800",
    "sg:postcode":"92113",
    "sg:province":"CA",
    "sg:tags":[
        "equipment",
        "diver",
        "supply"
    ],
    "sg:website":"www.divecenter.com",
    "wof:name":"Aqua Tech Dive Ctr",
    "wof:placetype":"venue"
},
  "geometry": {"coordinates":[-117.144303,32.701473],"type":"Point"}
}