{
  "type": "Feature",
  "properties": {
    "addr:full":"1236 30th Ave Oakland CA 94601",
    "addr:housenumber":"1236",
    "addr:postcode":"94601",
    "addr:street":"30Th Ave",
    "iso:country":"US",
    "sg:address":"1236 30th Ave",
    "sg:city":"Oakland",
    "sg:classifiers":[
        {
            "category":"Insurance",
            "subcategory":"Insurance Agent",
            "type":"Services"
        }
    ],
    "sg:phone":"+1 510 533 9712",
    "sg:postcode":"94601",
    "sg:province":"CA",
    "wof:name":"State Farm Insurance",
    "wof:placetype":"venue"
},
  "geometry": {"coordinates":[-122.22837,37.778004],"type":"Point"}
}