{
  "type": "Feature",
  "properties": {
    "addr:full":"12607 Perris Blvd Moreno Valley CA 92553",
    "addr:housenumber":"12607",
    "addr:postcode":"92553",
    "addr:street":"Perris Blvd",
    "iso:country":"US",
    "sg:address":"12607 Perris Blvd",
    "sg:city":"Moreno Valley",
    "sg:classifiers":[
        {
            "category":"Wholesale",
            "subcategory":"Farm Supplies",
            "type":"Manufacturing & Wholesale Goods"
        },
        {
            "category":"Professional",
            "type":"Services"
        }
    ],
    "sg:phone":"+1 951 486 0441",
    "sg:postcode":"92553",
    "sg:province":"CA",
    "sg:tags":[
        "plant",
        "seed",
        "establishment"
    ],
    "wof:name":"Northstar Impex Corporation",
    "wof:placetype":"venue"
},
  "geometry": {"coordinates":[-117.226399,33.937416],"type":"Point"}
}