{
  "type": "Feature",
  "properties": {
    "iso:country":"US",
    "sg:address":"522 W Holt Ave",
    "sg:city":"Pomona",
    "sg:classifiers":[
        {
            "category":"Professional",
            "subcategory":"Lawyer & Legal Services",
            "type":"Services"
        }
    ],
    "sg:phone":"+1 909 622 1071",
    "sg:postcode":"91768",
    "sg:province":"CA",
    "sg:tags":[
        "attorney"
    ],
    "wof:name":"Ramon Otero Inc",
    "wof:placetype":"venue"
},
  "geometry": {"coordinates":[-117.757056,34.062136],"type":"Point"}
}