{
  "type": "Feature",
  "properties": {
    "iso:country":"US",
    "sg:address":"6363 Regent St",
    "sg:city":"Huntington Park",
    "sg:classifiers":[
        {
            "category":"Professional",
            "type":"Services"
        }
    ],
    "sg:phone":"+1 323 581 7988",
    "sg:postcode":"90255",
    "sg:province":"CA",
    "sg:tags":[
        "establishment"
    ],
    "wof:name":"Regent Seating Designs",
    "wof:placetype":"venue"
},
  "geometry": {"coordinates":[-118.234934,33.982849],"type":"Point"}
}