{
  "type": "Feature",
  "properties": {
    "iso:country":"US",
    "sg:address":"10481 Gold Flat Rd",
    "sg:city":"Nevada City",
    "sg:classifiers":[
        {
            "category":"Wholesale",
            "subcategory":"Machinery & Supplies",
            "type":"Manufacturing & Wholesale Goods"
        }
    ],
    "sg:phone":"+1 530 478 0226",
    "sg:postcode":"95959",
    "sg:province":"CA",
    "sg:tags":[
        "equipment",
        "industrial"
    ],
    "wof:name":"Harris Industrial Gases",
    "wof:placetype":"venue"
},
  "geometry": {"coordinates":[-121.020875,39.246742],"type":"Point"}
}