{
  "type": "Feature",
  "properties": {
    "iso:country":"US",
    "sg:address":"13443 Mulberry Dr",
    "sg:city":"Whittier",
    "sg:classifiers":[
        {
            "category":"Real Estate",
            "subcategory":"Real Estate Agent",
            "type":"Services"
        }
    ],
    "sg:phone":"+1 562 698 3028",
    "sg:postcode":"90605",
    "sg:province":"CA",
    "sg:tags":[
        "finding",
        "apartment",
        "rental"
    ],
    "wof:name":"Mulberry Gardens",
    "wof:placetype":"venue"
},
  "geometry": {"coordinates":[-118.042,33.952999],"type":"Point"}
}