{
  "type": "Feature",
  "properties": {
    "addr:full":"575 Polk St San Francisco CA 94102",
    "addr:housenumber":"575",
    "addr:postcode":"94102",
    "addr:street":"Polk St",
    "iso:country":"US",
    "sg:address":"575 Polk St",
    "sg:city":"San Francisco",
    "sg:classifiers":[
        {
            "category":"Government",
            "subcategory":"Court House",
            "type":"Public Place"
        }
    ],
    "sg:phone":"+1 415 551 3634",
    "sg:postcode":"94102",
    "sg:province":"CA",
    "sg:tags":[
        "city"
    ],
    "wof:name":"San Francisco Juvenile Court",
    "wof:placetype":"venue"
},
  "geometry": {"coordinates":[-122.41902399999999,37.781884],"type":"Point"}
}