{
  "type": "Feature",
  "properties": {
    "iso:country":"US",
    "sg:address":"8540 S Sepulveda Blvd Ste 808",
    "sg:city":"Los Angeles",
    "sg:classifiers":[
        {
            "category":"Health Services",
            "subcategory":"Dentist",
            "type":"Services"
        }
    ],
    "sg:phone":"+1 310 670 0659",
    "sg:postcode":"90045",
    "sg:province":"CA",
    "sg:tags":[
        "cosmetic"
    ],
    "sg:website":"www.southbaysmiles.com",
    "wof:name":"Bradley S Matthew, \u00a0DDS",
    "wof:placetype":"venue"
},
  "geometry": {"coordinates":[-118.395712,33.960199],"type":"Point"}
}