{
  "type": "Feature",
  "properties": {
    "addr:full":"1121 N Cosby Way Anaheim CA 92806",
    "addr:housenumber":"1121",
    "addr:postcode":"92806",
    "addr:street":"N Cosby Way",
    "iso:country":"US",
    "sg:address":"1121 N Cosby Way",
    "sg:city":"Anaheim",
    "sg:classifiers":[
        {
            "category":"Manufacturing",
            "subcategory":"Tools & Machinery",
            "type":"Manufacturing & Wholesale Goods"
        }
    ],
    "sg:phone":"+1 714 630 8360",
    "sg:postcode":"92806",
    "sg:province":"CA",
    "sg:tags":[
        "machine",
        "shop"
    ],
    "wof:name":"R Davis EDM",
    "wof:placetype":"venue"
},
  "geometry": {"coordinates":[-117.845147,33.855425],"type":"Point"}
}