{
  "type": "Feature",
  "properties": {
    "iso:country":"US",
    "sg:address":"4500 Rosemead Blvd",
    "sg:city":"Pico Rivera",
    "sg:classifiers":[
        {
            "category":"Restaurant",
            "type":"Food & Drink"
        }
    ],
    "sg:menulink":"http://www.allmenus.com/ca/whittier/73882-dominos-pizza/menu/",
    "sg:phone":"+1 562 692 9591",
    "sg:postcode":"90660",
    "sg:province":"CA",
    "sg:tags":[
        "american",
        "wing",
        "pizza"
    ],
    "wof:name":"Domino's Pizza",
    "wof:placetype":"venue"
},
  "geometry": {"coordinates":[-118.080727,34.009342],"type":"Point"}
}