{
  "type": "Feature",
  "properties": {
    "iso:country":"US",
    "sg:address":"13911 Old Harbor Ln",
    "sg:city":"Marina Del Rey",
    "sg:classifiers":[
        {
            "category":"Manufacturing",
            "subcategory":"Apparel",
            "type":"Manufacturing & Wholesale Goods"
        }
    ],
    "sg:phone":"+1 310 821 5441",
    "sg:postcode":"90292",
    "sg:province":"CA",
    "sg:tags":[
        "cards",
        "greeting",
        "sportswear",
        "mfg"
    ],
    "wof:name":"Gillette Sportswear",
    "wof:placetype":"venue"
},
  "geometry": {"coordinates":[-118.451566,33.968859],"type":"Point"}
}