{
  "type": "Feature",
  "properties": {
    "addr:full":"4336 Watt Avenue Sacramento CA 95821",
    "addr:housenumber":"4336",
    "addr:postcode":"95821",
    "addr:street":"Watt Avenue",
    "iso:country":"US",
    "sg:address":"4336 Watt Avenue",
    "sg:city":"Sacramento",
    "sg:classifiers":[
        {
            "category":"Restaurant",
            "type":"Food & Drink"
        }
    ],
    "sg:phone":"+1 916 488 1922",
    "sg:postcode":"95821",
    "sg:province":"CA",
    "wof:name":"Denny's Restaurant",
    "wof:placetype":"venue"
},
  "geometry": {"coordinates":[-121.38297799999999,38.644445],"type":"Point"}
}