{
  "type": "Feature",
  "properties": {
    "iso:country":"US",
    "sg:address":"89 Davis Road Suite 100",
    "sg:city":"Orinda",
    "sg:classifiers":[
        {
            "category":"Real Estate",
            "subcategory":"Real Estate Agent",
            "type":"Services"
        }
    ],
    "sg:phone":"+1 925 330 6108",
    "sg:postcode":"94563",
    "sg:province":"CA",
    "sg:website":"www.lamorindahome.com/",
    "wof:name":"Lily Wescott - J Rockcliff Realtors",
    "wof:placetype":"venue"
},
  "geometry": {"coordinates":[-122.18102500000001,37.879791],"type":"Point"}
}