{
  "type": "Feature",
  "properties": {
    "iso:country":"US",
    "sg:address":"14562 Goldenwest St",
    "sg:city":"Westminster",
    "sg:classifiers":[
        {
            "category":"Freight",
            "type":"Transportation"
        }
    ],
    "sg:phone":"+1 714 373 2461",
    "sg:postcode":"92683",
    "sg:province":"CA",
    "sg:tags":[
        "operator",
        "local",
        "trucking"
    ],
    "wof:name":"Lorena Waste Tire Haulers",
    "wof:placetype":"venue"
},
  "geometry": {"coordinates":[-118.00700500000001,33.751213],"type":"Point"}
}