{
  "type": "Feature",
  "properties": {
    "addr:full":"420 Cassia St Redwood City CA 94063",
    "addr:housenumber":"420",
    "addr:postcode":"94063",
    "addr:street":"Cassia St",
    "iso:country":"US",
    "sg:address":"420 Cassia St",
    "sg:city":"Redwood City",
    "sg:classifiers":[
        {
            "category":"Social Services",
            "subcategory":"Adult Care",
            "type":"Services"
        }
    ],
    "sg:phone":"+1 650 363 8125",
    "sg:postcode":"94063",
    "sg:province":"CA",
    "sg:tags":[
        "home",
        "residential"
    ],
    "wof:name":"Mateo Lodge",
    "wof:placetype":"venue"
},
  "geometry": {"coordinates":[-122.224864,37.483417],"type":"Point"}
}