{
  "type": "Feature",
  "properties": {
    "iso:country":"US",
    "sg:address":"2205 Artesia Blvd",
    "sg:city":"Redondo Beach",
    "sg:classifiers":[
        {
            "category":"Education",
            "subcategory":"Vocational School",
            "type":"Public Place"
        }
    ],
    "sg:phone":"+1 310 370 7464",
    "sg:postcode":"90278",
    "sg:province":"CA",
    "sg:tags":[
        "cosmetology"
    ],
    "wof:name":"Redondo Beach Flavio Beauty College",
    "wof:placetype":"venue"
},
  "geometry": {"coordinates":[-118.373001,33.873001],"type":"Point"}
}