{
  "type": "Feature",
  "properties": {
    "iso:country":"US",
    "sg:address":"429 Texas St",
    "sg:city":"Redlands",
    "sg:classifiers":[
        {
            "category":"Building & Trades",
            "subcategory":"Plumbing",
            "type":"Services"
        }
    ],
    "sg:phone":"+1 909 793 8461",
    "sg:postcode":"92374",
    "sg:province":"CA",
    "sg:tags":[
        "contractor"
    ],
    "wof:name":"Air Cndtioning Htg By Redlands",
    "wof:placetype":"venue"
},
  "geometry": {"coordinates":[-117.191445,34.058659],"type":"Point"}
}