{
  "type": "Feature",
  "properties": {
    "addr:full":"1429 E Miner Ave Stockton CA 95205",
    "addr:housenumber":"1429",
    "addr:postcode":"95205",
    "addr:street":"E Miner Ave",
    "iso:country":"US",
    "sg:address":"1429 E Miner Ave",
    "sg:city":"Stockton",
    "sg:classifiers":[
        {
            "category":"Autos & Motor Vehicles",
            "subcategory":"Automobile Sales",
            "type":"Retail Goods"
        }
    ],
    "sg:phone":"+1 209 403 9890",
    "sg:postcode":"95205",
    "sg:province":"CA",
    "sg:tags":[
        "car",
        "dealer"
    ],
    "wof:name":"Lucky Auto Sales Inc",
    "wof:placetype":"venue"
},
  "geometry": {"coordinates":[-121.272696,37.958795],"type":"Point"}
}