{
  "type": "Feature",
  "properties": {
    "iso:country":"US",
    "sg:address":"915 W Foothill Blvd Ste C",
    "sg:city":"Claremont",
    "sg:classifiers":[
        {
            "category":"Personal",
            "type":"Services"
        }
    ],
    "sg:phone":"+1 909 626 7706",
    "sg:postcode":"91711",
    "sg:province":"CA",
    "sg:tags":[
        "assistant"
    ],
    "wof:name":"Isabel Christina Garcia",
    "wof:placetype":"venue"
},
  "geometry": {"coordinates":[-117.732775,34.107101],"type":"Point"}
}