{
  "type": "Feature",
  "properties": {
    "addr:full":"25462 Villa Real Lake Forest CA 92630",
    "addr:housenumber":"25462",
    "addr:postcode":"92630",
    "addr:street":"Villa Real",
    "iso:country":"US",
    "sg:address":"25462 Villa Real",
    "sg:city":"Lake Forest",
    "sg:classifiers":[
        {
            "category":"Real Estate",
            "subcategory":"Real Estate Agent",
            "type":"Services"
        }
    ],
    "sg:phone":"+1 949 470 3829",
    "sg:postcode":"92630",
    "sg:province":"CA",
    "wof:name":"Delaware Arien Inc",
    "wof:placetype":"venue"
},
  "geometry": {"coordinates":[-117.686347,33.656763],"type":"Point"}
}