{
  "type": "Feature",
  "properties": {
    "iso:country":"US",
    "sg:address":"2575 Coit Dr",
    "sg:city":"San Jose",
    "sg:classifiers":[
        {
            "category":"Social Services",
            "subcategory":"Child Care",
            "type":"Services"
        }
    ],
    "sg:phone":"+1 408 371 4222",
    "sg:postcode":"95124",
    "sg:province":"CA",
    "wof:name":"Neighborhood Christian Pre-Sch",
    "wof:placetype":"venue"
},
  "geometry": {"coordinates":[-121.924116,37.275103],"type":"Point"}
}