{
  "type": "Feature",
  "properties": {
    "addr:full":"2320 Pso de Las Americas San Diego CA 92154",
    "addr:housenumber":"2320",
    "addr:postcode":"92154",
    "addr:street":"Pso De Las Americas",
    "iso:country":"US",
    "sg:address":"2320 Pso de Las Americas",
    "sg:city":"San Diego",
    "sg:classifiers":[
        {
            "category":"Professional",
            "type":"Services"
        }
    ],
    "sg:phone":"+1 858 715 7200",
    "sg:postcode":"92154",
    "sg:province":"CA",
    "sg:tags":[
        "establishment"
    ],
    "wof:name":"Crydom Co",
    "wof:placetype":"venue"
},
  "geometry": {"coordinates":[-116.935979,32.554879],"type":"Point"}
}