{
  "type": "Feature",
  "properties": {
    "iso:country":"US",
    "sg:address":"20988 Bake Pkwy",
    "sg:city":"Lake Forest",
    "sg:classifiers":[
        {
            "category":"Professional",
            "subcategory":"Detective & Security Services",
            "type":"Services"
        }
    ],
    "sg:phone":"+1 949 609 0156",
    "sg:postcode":"92630",
    "sg:province":"CA",
    "sg:tags":[
        "investigator"
    ],
    "wof:name":"Accurate Background Checks",
    "wof:placetype":"venue"
},
  "geometry": {"coordinates":[-117.702782,33.655132],"type":"Point"}
}