{
  "type": "Feature",
  "properties": {
    "addr:full":"1150 Kentucky St Fairfield CA 94533",
    "addr:housenumber":"1150",
    "addr:postcode":"94533",
    "addr:street":"Kentucky St",
    "iso:country":"US",
    "sg:address":"1150 Kentucky St",
    "sg:city":"Fairfield",
    "sg:classifiers":[
        {
            "category":"Shopping",
            "subcategory":"Used Merchandise",
            "type":"Retail Goods"
        }
    ],
    "sg:phone":"+1 707 434 9434",
    "sg:postcode":"94533",
    "sg:province":"CA",
    "sg:tags":[
        "book",
        "rare",
        "dealer"
    ],
    "wof:name":"Friends Of The Fairfield Lbry",
    "wof:placetype":"venue"
},
  "geometry": {"coordinates":[-122.04800400000001,38.251517],"type":"Point"}
}