{
  "type": "Feature",
  "properties": {
    "iso:country":"US",
    "sg:address":"300 E Orangethorpe Ave",
    "sg:city":"Anaheim",
    "sg:classifiers":[
        {
            "category":"Manufacturing",
            "subcategory":"Apparel",
            "type":"Manufacturing & Wholesale Goods"
        }
    ],
    "sg:phone":"+1 714 879 6810",
    "sg:postcode":"92801",
    "sg:province":"CA",
    "sg:tags":[
        "sportswear"
    ],
    "wof:name":"American Sporting Goods",
    "wof:placetype":"venue"
},
  "geometry": {"coordinates":[-117.917265,33.859426],"type":"Point"}
}