{
  "type": "Feature",
  "properties": {
    "addr:full":"2383 Via Segundo San Ysidro CA 92173",
    "addr:housenumber":"2383",
    "addr:postcode":"92173",
    "addr:street":"Via Segundo",
    "iso:country":"US",
    "sg:address":"2383 Via Segundo",
    "sg:city":"San Ysidro",
    "sg:classifiers":[
        {
            "category":"Professional",
            "subcategory":"Management & Consulting",
            "type":"Services"
        }
    ],
    "sg:phone":"+1 619 395 6690",
    "sg:postcode":"92173",
    "sg:province":"CA",
    "sg:tags":[
        "retail",
        "direct",
        "sales"
    ],
    "wof:name":"Javier & Garcia",
    "wof:placetype":"venue"
},
  "geometry": {"coordinates":[-117.05309099999999,32.554319],"type":"Point"}
}