{
  "type": "Feature",
  "properties": {
    "iso:country":"US",
    "sg:address":"4079 Huerfano Ave",
    "sg:city":"San Diego",
    "sg:classifiers":[
        {
            "category":"Freight",
            "type":"Transportation"
        }
    ],
    "sg:phone":"+1 858 344 2568",
    "sg:postcode":"92117",
    "sg:province":"CA",
    "sg:tags":[
        "water"
    ],
    "wof:name":"Douglas Watson Studios",
    "wof:placetype":"venue"
},
  "geometry": {"coordinates":[-117.218193,32.81992],"type":"Point"}
}