{
  "type": "Feature",
  "properties": {
    "iso:country":"US",
    "sg:address":"9701 Lakewood Blvd",
    "sg:city":"Downey",
    "sg:classifiers":[
        {
            "category":"Professional",
            "subcategory":"Lawyer & Legal Services",
            "type":"Services"
        }
    ],
    "sg:phone":"+1 562 862 7541",
    "sg:postcode":"90240",
    "sg:province":"CA",
    "sg:tags":[
        "attorney"
    ],
    "wof:name":"Eugene M Siegel Law Office",
    "wof:placetype":"venue"
},
  "geometry": {"coordinates":[-118.114953,33.951567],"type":"Point"}
}