{
  "type": "Feature",
  "properties": {
    "addr:full":"1200 9th Ave San Francisco CA 94122",
    "addr:housenumber":"1200",
    "addr:postcode":"94122",
    "addr:street":"9Th Ave",
    "iso:country":"US",
    "sg:address":"1200 9th Ave",
    "sg:city":"San Francisco",
    "sg:classifiers":[
        {
            "category":"Shopping",
            "type":"Retail Goods"
        }
    ],
    "sg:phone":"+1 415 504 0070",
    "sg:postcode":"94122",
    "sg:province":"CA",
    "sg:tags":[
        "art",
        "gallery",
        "dealer"
    ],
    "wof:name":"Canvas Gallery",
    "wof:placetype":"venue"
},
  "geometry": {"coordinates":[-122.46630999999999,37.764036],"type":"Point"}
}