{
  "type": "Feature",
  "properties": {
    "iso:country":"US",
    "sg:address":"1888 Geneva Ave",
    "sg:city":"San Francisco",
    "sg:classifiers":[
        {
            "category":"Real Estate",
            "subcategory":"Real Estate Operator",
            "type":"Services"
        }
    ],
    "sg:phone":"+1 415 859 1335",
    "sg:postcode":"94134",
    "sg:province":"CA",
    "sg:tags":[
        "apartment"
    ],
    "wof:name":"1888 Geneva Ave Apts LLC",
    "wof:placetype":"venue"
},
  "geometry": {"coordinates":[-122.423079,37.709091],"type":"Point"}
}