{
  "type": "Feature",
  "properties": {
    "iso:country":"US",
    "sg:address":"33635 Honeysuckle Ln",
    "sg:city":"Murrieta",
    "sg:classifiers":[
        {
            "category":"Real Estate",
            "subcategory":"Real Estate Services",
            "type":"Services"
        },
        {
            "category":"Real Estate",
            "subcategory":"Surveying",
            "type":"Services"
        }
    ],
    "sg:phone":"+1 951 679 9557",
    "sg:postcode":"92563",
    "sg:province":"CA",
    "sg:tags":[
        "industrial",
        "appraisers-commercial",
        "appraiser"
    ],
    "wof:name":"Perfect Balance Appraisals",
    "wof:placetype":"venue"
},
  "geometry": {"coordinates":[-117.16264,33.632157],"type":"Point"}
}