{
  "type": "Feature",
  "properties": {
    "iso:country":"US",
    "sg:address":"10968 Broadway Rd",
    "sg:city":"Moorpark",
    "sg:classifiers":[
        {
            "category":"Farming",
            "subcategory":"Orchard",
            "type":"Manufacturing & Wholesale Goods"
        }
    ],
    "sg:phone":"+1 805 529 9365",
    "sg:postcode":"93021",
    "sg:province":"CA",
    "sg:tags":[
        "citrus",
        "grove",
        "fruit"
    ],
    "wof:name":"Daryl Smith",
    "wof:placetype":"venue"
},
  "geometry": {"coordinates":[-118.915902,34.315133],"type":"Point"}
}