{
  "type": "Feature",
  "properties": {
    "iso:country":"US",
    "sg:address":"37312 Fremont Blvd",
    "sg:city":"Fremont",
    "sg:classifiers":[
        {
            "category":"Shopping",
            "subcategory":"Computers & Home Electronics",
            "type":"Retail Goods"
        }
    ],
    "sg:phone":"+1 510 794 7722",
    "sg:postcode":"94536",
    "sg:province":"CA",
    "sg:tags":[
        "software"
    ],
    "wof:name":"Video Com Ctr",
    "wof:placetype":"venue"
},
  "geometry": {"coordinates":[-122.007598,37.558562],"type":"Point"}
}