{
  "type": "Feature",
  "properties": {
    "addr:full":"1530 Highridge Rd Spring Valley CA 91977",
    "addr:housenumber":"1530",
    "addr:postcode":"91977",
    "addr:street":"Highridge Rd",
    "iso:country":"US",
    "sg:address":"1530 Highridge Rd",
    "sg:city":"Spring Valley",
    "sg:classifiers":[
        {
            "category":"Wholesale",
            "subcategory":"Apparel",
            "type":"Manufacturing & Wholesale Goods"
        }
    ],
    "sg:phone":"+1 619 520 5014",
    "sg:postcode":"91977",
    "sg:province":"CA",
    "sg:tags":[
        "clothing"
    ],
    "wof:name":"Ivy Lee Co",
    "wof:placetype":"venue"
},
  "geometry": {"coordinates":[-116.977051,32.718546],"type":"Point"}
}