{
  "type": "Feature",
  "properties": {
    "addr:full":"900 S Victory Blvd Burbank CA 91502",
    "addr:housenumber":"900",
    "addr:postcode":"91502",
    "addr:street":"S Victory Blvd",
    "iso:country":"US",
    "sg:address":"900 S Victory Blvd",
    "sg:city":"Burbank",
    "sg:classifiers":[
        {
            "category":"Manufacturing",
            "subcategory":"Tools & Machinery",
            "type":"Manufacturing & Wholesale Goods"
        }
    ],
    "sg:phone":"+1 818 846 2504",
    "sg:postcode":"91502",
    "sg:province":"CA",
    "sg:tags":[
        "machine",
        "shop",
        "industrial",
        "mfg"
    ],
    "wof:name":"Dean Engineering & Mfg Inc",
    "wof:placetype":"venue"
},
  "geometry": {"coordinates":[-118.307941,34.1668],"type":"Point"}
}