{
  "type": "Feature",
  "properties": {
    "addr:full":"1358 5th St Santa Monica CA 90401",
    "addr:housenumber":"1358",
    "addr:postcode":"90401",
    "addr:street":"5Th St",
    "iso:country":"US",
    "sg:address":"1358 5th St",
    "sg:city":"Santa Monica",
    "sg:classifiers":[
        {
            "category":"Arts & Performance",
            "subcategory":"Theater",
            "type":"Entertainment"
        }
    ],
    "sg:phone":"+1 310 587 1124",
    "sg:postcode":"90401",
    "sg:province":"CA",
    "sg:tags":[
        "musician"
    ],
    "wof:name":"PJK Music",
    "wof:placetype":"venue"
},
  "geometry": {"coordinates":[-118.495133,34.017916],"type":"Point"}
}