{
  "type": "Feature",
  "properties": {
    "iso:country":"US",
    "sg:address":"1301 Auto Center Dr",
    "sg:city":"Ontario",
    "sg:classifiers":[
        {
            "category":"Autos & Motor Vehicles",
            "subcategory":"Automobile Sales",
            "type":"Retail Goods"
        }
    ],
    "sg:phone":"+1 909 390 7888",
    "sg:postcode":"91761",
    "sg:province":"CA",
    "sg:tags":[
        "car",
        "dealership",
        "dealer"
    ],
    "sg:website":"www.savagebmw.com",
    "wof:name":"Savage BMW Inc",
    "wof:placetype":"venue"
},
  "geometry": {"coordinates":[-117.544678,34.0515],"type":"Point"}
}