{
  "type": "Feature",
  "properties": {
    "iso:country":"US",
    "sg:address":"1717 S Country Club Ln",
    "sg:city":"Fresno",
    "sg:classifiers":[
        {
            "category":"Building & Trades",
            "subcategory":"Plumbing",
            "type":"Services"
        }
    ],
    "sg:phone":"+1 559 497 5121",
    "sg:postcode":"93727",
    "sg:province":"CA",
    "sg:tags":[
        "plumbing",
        "contractor"
    ],
    "wof:name":"Plumbline Plumbing",
    "wof:placetype":"venue"
},
  "geometry": {"coordinates":[-119.696952,36.724445],"type":"Point"}
}