{
  "type": "Feature",
  "properties": {
    "addr:full":"465 S Beverly Dr Beverly Hills CA 90212",
    "addr:housenumber":"465",
    "addr:postcode":"90212",
    "addr:street":"S Beverly Dr",
    "iso:country":"US",
    "sg:address":"465 S Beverly Dr",
    "sg:city":"Beverly Hills",
    "sg:classifiers":[
        {
            "category":"Manufacturing",
            "subcategory":"Printing",
            "type":"Manufacturing & Wholesale Goods"
        }
    ],
    "sg:phone":"+1 310 551 3095",
    "sg:postcode":"90212",
    "sg:province":"CA",
    "sg:tags":[
        "publisher"
    ],
    "wof:name":"A2Z Publishing",
    "wof:placetype":"venue"
},
  "geometry": {"coordinates":[-118.39825999999999,34.059126],"type":"Point"}
}