{
  "type": "Feature",
  "properties": {
    "addr:full":"1440 Crestmont Dr Bakersfield CA 93306",
    "addr:housenumber":"1440",
    "addr:postcode":"93306",
    "addr:street":"Crestmont Dr",
    "iso:country":"US",
    "sg:address":"1440 Crestmont Dr",
    "sg:city":"Bakersfield",
    "sg:classifiers":[
        {
            "category":"Personal",
            "subcategory":"Beauty Salon",
            "type":"Services"
        }
    ],
    "sg:phone":"+1 661 873 7337",
    "sg:postcode":"93306",
    "sg:province":"CA",
    "wof:name":"Sassy Solutions For-Total Look",
    "wof:placetype":"venue"
},
  "geometry": {"coordinates":[-118.954193,35.376968],"type":"Point"}
}