{
  "type": "Feature",
  "properties": {
    "iso:country":"US",
    "sg:address":"2848 E 208th St",
    "sg:city":"Carson",
    "sg:classifiers":[
        {
            "category":"Manufacturing",
            "subcategory":"Aerospace",
            "type":"Manufacturing & Wholesale Goods"
        }
    ],
    "sg:phone":"+1 310 632 6353",
    "sg:postcode":"90810",
    "sg:province":"CA",
    "sg:tags":[
        "equipment",
        "aircraft",
        "parts",
        "d",
        "mfg"
    ],
    "sg:website":"www.hydroformusa.com",
    "wof:name":"Hydroform USA Inc",
    "wof:placetype":"venue"
},
  "geometry": {"coordinates":[-118.207353,33.83942],"type":"Point"}
}