{
  "type": "Feature",
  "properties": {
    "iso:country":"US",
    "sg:address":"881 Embarcadero Dr",
    "sg:city":"El Dorado Hills",
    "sg:classifiers":[
        {
            "category":"Professional",
            "type":"Services"
        }
    ],
    "sg:phone":"+1 916 939 0406",
    "sg:postcode":"95762",
    "sg:province":"CA",
    "wof:name":"Piel Esthetics",
    "wof:placetype":"venue"
},
  "geometry": {"coordinates":[-121.084395,38.708525],"type":"Point"}
}