{
  "type": "Feature",
  "properties": {
    "addr:full":"11682 W Olympic Blvd Los Angeles CA 90064",
    "addr:housenumber":"11682",
    "addr:postcode":"90064",
    "addr:street":"W Olympic Blvd",
    "iso:country":"US",
    "sg:address":"11682 W Olympic Blvd",
    "sg:city":"Los Angeles",
    "sg:classifiers":[
        {
            "category":"Retail",
            "subcategory":"Laundry & Dry Cleaning",
            "type":"Services"
        }
    ],
    "sg:phone":"+1 310 478 8358",
    "sg:postcode":"90064",
    "sg:province":"CA",
    "wof:name":"$1 Cleaners - Joan Inc.",
    "wof:placetype":"venue"
},
  "geometry": {"coordinates":[-118.447632,34.03441],"type":"Point"}
}