{
  "type": "Feature",
  "properties": {
    "iso:country":"US",
    "sg:address":"1011 S Los Angeles Street",
    "sg:city":"Los Angeles",
    "sg:classifiers":[
        {
            "category":"Real Estate",
            "subcategory":"Real Estate Operator",
            "type":"Services"
        }
    ],
    "sg:phone":"+1 213 746 4205",
    "sg:postcode":"90015",
    "sg:province":"CA",
    "sg:tags":[
        "apartment"
    ],
    "wof:name":"Moshe Aflalo",
    "wof:placetype":"venue"
},
  "geometry": {"coordinates":[-118.25599,34.039457],"type":"Point"}
}