{
  "type": "Feature",
  "properties": {
    "iso:country":"US",
    "sg:address":"2730 E Washington Blvd",
    "sg:city":"Los Angeles",
    "sg:classifiers":[
        {
            "category":"Manufacturing",
            "subcategory":"Glass & Minerals",
            "type":"Manufacturing & Wholesale Goods"
        }
    ],
    "sg:phone":"+1 323 260 5350",
    "sg:postcode":"90023",
    "sg:province":"CA",
    "sg:tags":[
        "ready",
        "concrete",
        "delivers",
        "mfg"
    ],
    "wof:name":"Associated Ready Mix Concrete",
    "wof:placetype":"venue"
},
  "geometry": {"coordinates":[-118.222223,34.017278],"type":"Point"}
}