{
  "type": "Feature",
  "properties": {
    "addr:full":"3665 S Western Ave Los Angeles CA 90018",
    "addr:housenumber":"3665",
    "addr:postcode":"90018",
    "addr:street":"S Western Ave",
    "iso:country":"US",
    "sg:address":"3665 S Western Ave",
    "sg:city":"Los Angeles",
    "sg:classifiers":[
        {
            "category":"Home & Garden",
            "subcategory":"Building Materials",
            "type":"Retail Goods"
        }
    ],
    "sg:phone":"+1 323 731 7313",
    "sg:postcode":"90018",
    "sg:province":"CA",
    "sg:tags":[
        "mixed",
        "concrete"
    ],
    "wof:name":"Western Equipment Rentals Inc",
    "wof:placetype":"venue"
},
  "geometry": {"coordinates":[-118.308967,34.021368],"type":"Point"}
}