{
  "type": "Feature",
  "properties": {
    "iso:country":"US",
    "sg:address":"3431 Via Oporto",
    "sg:city":"Newport Beach",
    "sg:classifiers":[
        {
            "category":"Shopping",
            "subcategory":"Jewelry",
            "type":"Retail Goods"
        }
    ],
    "sg:phone":"+1 949 675 1585",
    "sg:postcode":"92663",
    "sg:province":"CA",
    "wof:name":"World Estate Jewelry",
    "wof:placetype":"venue"
},
  "geometry": {"coordinates":[-117.92833,33.618284],"type":"Point"}
}