{
  "type": "Feature",
  "properties": {
    "addr:full":"330 Cordova St Pasadena CA 91101",
    "addr:housenumber":"330",
    "addr:postcode":"91101",
    "addr:street":"Cordova St",
    "iso:country":"US",
    "sg:address":"330 Cordova St",
    "sg:city":"Pasadena",
    "sg:classifiers":[
        {
            "category":"Farming",
            "subcategory":"Farm",
            "type":"Manufacturing & Wholesale Goods"
        }
    ],
    "sg:phone":"+1 626 564 0755",
    "sg:postcode":"91101",
    "sg:province":"CA",
    "sg:tags":[
        "crop",
        "general"
    ],
    "wof:name":"Schoonhoven Farms",
    "wof:placetype":"venue"
},
  "geometry": {"coordinates":[-118.145218,34.142165],"type":"Point"}
}