{
  "type": "Feature",
  "properties": {
    "addr:full":"4135 Cass St San Diego CA 92109",
    "addr:housenumber":"4135",
    "addr:postcode":"92109",
    "addr:street":"Cass St",
    "iso:country":"US",
    "sg:address":"4135 Cass St",
    "sg:city":"San Diego",
    "sg:classifiers":[
        {
            "category":"Professional",
            "type":"Services"
        }
    ],
    "sg:phone":"+1 858 274 8169",
    "sg:postcode":"92109",
    "sg:province":"CA",
    "wof:name":"Jc1 Interactive",
    "wof:placetype":"venue"
},
  "geometry": {"coordinates":[-117.250058,32.791868],"type":"Point"}
}