{
  "type": "Feature",
  "properties": {
    "addr:full":"11725 Goldring Rd Ste 1 Arcadia CA 91006",
    "addr:postcode":"11725;91006",
    "addr:street":"Goldring Rd Ste 1",
    "iso:country":"US",
    "sg:address":"11725 Goldring Rd Ste 1",
    "sg:city":"Arcadia",
    "sg:classifiers":[
        {
            "category":"Building & Trades",
            "subcategory":"Construction",
            "type":"Services"
        }
    ],
    "sg:phone":"+1 626 445 3002",
    "sg:postcode":"91006",
    "sg:province":"CA",
    "sg:tags":[
        "contractor"
    ],
    "sg:website":"www.rrcco.net",
    "wof:name":"READ RICHARD CONSTRUCTION CO",
    "wof:placetype":"venue"
},
  "geometry": {"coordinates":[-118.722256,34.101074],"type":"Point"}
}