{
  "type": "Feature",
  "properties": {
    "addr:full":"328 Macdonald Ave Richmond CA 94801",
    "addr:housenumber":"328",
    "addr:postcode":"94801",
    "addr:street":"Macdonald Ave",
    "iso:country":"US",
    "sg:address":"328 Macdonald Ave",
    "sg:city":"Richmond",
    "sg:classifiers":[
        {
            "category":"Organizations",
            "subcategory":"Religious Organization",
            "type":"Services"
        }
    ],
    "sg:phone":"+1 510 215 7332",
    "sg:postcode":"94801",
    "sg:province":"CA",
    "sg:tags":[
        "church"
    ],
    "wof:name":"Ark Of The Covenant Church",
    "wof:placetype":"venue"
},
  "geometry": {"coordinates":[-122.365933,37.935622],"type":"Point"}
}