{
  "type": "Feature",
  "properties": {
    "iso:country":"US",
    "sg:address":"5520 Ekwill St",
    "sg:city":"Santa Barbara",
    "sg:classifiers":[
        {
            "category":"Government",
            "subcategory":"Office",
            "type":"Public Place"
        }
    ],
    "sg:phone":"+1 805 681 2447",
    "sg:postcode":"93111",
    "sg:province":"CA",
    "sg:tags":[
        "national",
        "security"
    ],
    "wof:name":"Bechtel Nevada",
    "wof:placetype":"venue"
},
  "geometry": {"coordinates":[-119.821124,34.430151],"type":"Point"}
}