{
  "type": "Feature",
  "properties": {
    "iso:country":"US",
    "sg:address":"777 N California Ave",
    "sg:city":"Palo Alto",
    "sg:classifiers":[
        {
            "category":"Real Estate",
            "subcategory":"Real Estate Agent",
            "type":"Services"
        }
    ],
    "sg:phone":"+1 650 856 2900",
    "sg:postcode":"94303",
    "sg:province":"CA",
    "wof:name":"Sovereign Investment",
    "wof:placetype":"venue"
},
  "geometry": {"coordinates":[-122.135819,37.438262],"type":"Point"}
}