{
  "type": "Feature",
  "properties": {
    "addr:full":"308 Park Ave Capitola CA 95010",
    "addr:housenumber":"308",
    "addr:postcode":"95010",
    "addr:street":"Park Ave",
    "iso:country":"US",
    "sg:address":"308 Park Ave",
    "sg:city":"Capitola",
    "sg:classifiers":[
        {
            "category":"Building & Trades",
            "subcategory":"Cleaning & Sanitation",
            "type":"Services"
        }
    ],
    "sg:phone":"+1 831 476 4309",
    "sg:postcode":"95010",
    "sg:province":"CA",
    "sg:tags":[
        "window"
    ],
    "wof:name":"Real Clean Window Co",
    "wof:placetype":"venue"
},
  "geometry": {"coordinates":[-121.947012,36.976427],"type":"Point"}
}