{
  "type": "Feature",
  "properties": {
    "addr:full":"31887 Corydon Rd Lake Elsinore CA 92530",
    "addr:housenumber":"31887",
    "addr:postcode":"92530",
    "addr:street":"Corydon Rd",
    "iso:country":"US",
    "sg:address":"31887 Corydon Rd",
    "sg:city":"Lake Elsinore",
    "sg:classifiers":[
        {
            "category":"Professional",
            "subcategory":"Advertising",
            "type":"Services"
        }
    ],
    "sg:phone":"+1 951 471 8500",
    "sg:postcode":"92530",
    "sg:province":"CA",
    "sg:tags":[
        "distribution"
    ],
    "wof:name":"S L Faria Ind Supply",
    "wof:placetype":"venue"
},
  "geometry": {"coordinates":[-117.294673,33.628981],"type":"Point"}
}