{
  "type": "Feature",
  "properties": {
    "iso:country":"US",
    "sg:address":"6868 McKinley Ave",
    "sg:city":"Sebastopol",
    "sg:classifiers":[
        {
            "category":"Cinema",
            "subcategory":"Movie Theater",
            "type":"Entertainment"
        }
    ],
    "sg:phone":"+1 707 829 3456",
    "sg:postcode":"95472",
    "sg:province":"CA",
    "wof:name":"Sebastopol Cinemas",
    "wof:placetype":"venue"
},
  "geometry": {"coordinates":[-122.822846,38.403743],"type":"Point"}
}