{
  "type": "Feature",
  "properties": {
    "addr:full":"701 Wallis Ave Gustine CA 95322",
    "addr:housenumber":"701",
    "addr:postcode":"95322",
    "addr:street":"Wallis Ave",
    "iso:country":"US",
    "sg:address":"701 Wallis Ave",
    "sg:city":"Gustine",
    "sg:classifiers":[
        {
            "category":"Education",
            "subcategory":"School",
            "type":"Public Place"
        }
    ],
    "sg:phone":"+1 209 854 6071",
    "sg:postcode":"95322",
    "sg:province":"CA",
    "wof:name":"Gustine Unified School District",
    "wof:placetype":"venue"
},
  "geometry": {"coordinates":[-121.00129699999999,37.251209],"type":"Point"}
}