{
  "type": "Feature",
  "properties": {
    "addr:full":"5700 Van Buren Blvd Riverside CA 92503",
    "addr:housenumber":"5700",
    "addr:postcode":"92503",
    "addr:street":"Van Buren Blvd",
    "iso:country":"US",
    "sg:address":"5700 Van Buren Blvd",
    "sg:city":"Riverside",
    "sg:classifiers":[
        {
            "category":"Shopping",
            "subcategory":"Shoes",
            "type":"Retail Goods"
        }
    ],
    "sg:phone":"+1 951 687 2174",
    "sg:postcode":"92503",
    "sg:province":"CA",
    "wof:name":"Family Shoe Store",
    "wof:placetype":"venue"
},
  "geometry": {"coordinates":[-117.45401699999999,33.940269],"type":"Point"}
}