{
  "type": "Feature",
  "properties": {
    "iso:country":"US",
    "sg:address":"35 Lakewood Center Mall",
    "sg:city":"Lakewood",
    "sg:classifiers":[
        {
            "category":"Health Services",
            "subcategory":"Health Practitioner",
            "type":"Services"
        }
    ],
    "sg:phone":"+1 562 602 2988",
    "sg:postcode":"90712",
    "sg:province":"CA",
    "sg:tags":[
        "surgery",
        "laser"
    ],
    "wof:name":"Nuvo International Laser Skin",
    "wof:placetype":"venue"
},
  "geometry": {"coordinates":[-118.14058300000001,33.848553],"type":"Point"}
}