{
  "type": "Feature",
  "properties": {
    "iso:country":"US",
    "sg:address":"675 N 1st St",
    "sg:city":"San Jose",
    "sg:classifiers":[
        {
            "category":"Travel",
            "subcategory":"Hotels & Motels",
            "type":"Entertainment"
        }
    ],
    "sg:phone":"+1 925 939 7669",
    "sg:postcode":"95112",
    "sg:province":"CA",
    "sg:tags":[
        "resort"
    ],
    "wof:name":"Kirkwood Resort",
    "wof:placetype":"venue"
},
  "geometry": {"coordinates":[-121.899868,37.348417],"type":"Point"}
}