{
  "type": "Feature",
  "properties": {
    "iso:country":"US",
    "sg:address":"4091 Riverside Dr",
    "sg:city":"Chino",
    "sg:classifiers":[
        {
            "category":"Shopping",
            "type":"Retail Goods"
        }
    ],
    "sg:phone":"+1 909 628 0833",
    "sg:postcode":"91710",
    "sg:province":"CA",
    "sg:tags":[
        "religious"
    ],
    "wof:name":"Harvest Time Intl",
    "wof:placetype":"venue"
},
  "geometry": {"coordinates":[-117.719531,34.018829],"type":"Point"}
}