{
  "type": "Feature",
  "properties": {
    "addr:full":"492 23rd St Oakland CA 94612",
    "addr:housenumber":"492",
    "addr:postcode":"94612",
    "addr:street":"23Rd St",
    "iso:country":"US",
    "sg:address":"492 23rd St",
    "sg:city":"Oakland",
    "sg:classifiers":[
        {
            "category":"Arts & Performance",
            "subcategory":"Art Gallery",
            "type":"Entertainment"
        }
    ],
    "sg:phone":"+1 510 879 7382",
    "sg:postcode":"94612",
    "sg:province":"CA",
    "sg:website":"www.hatchgallery.org",
    "wof:name":"Hatch Gallery",
    "wof:placetype":"venue"
},
  "geometry": {"coordinates":[-122.268657,37.812561],"type":"Point"}
}