{
  "type": "Feature",
  "properties": {
    "iso:country":"US",
    "sg:address":"215 Maple St",
    "sg:city":"Auburn",
    "sg:classifiers":[
        {
            "category":"Personal",
            "subcategory":"Beauty Salon",
            "type":"Services"
        },
        {
            "category":"Personal",
            "subcategory":"Day Spa",
            "type":"Services"
        }
    ],
    "sg:phone":"+1 530 885 5323",
    "sg:postcode":"95603",
    "sg:province":"CA",
    "wof:name":"Tiamo Salon & Spa",
    "wof:placetype":"venue"
},
  "geometry": {"coordinates":[-121.078261,38.89672],"type":"Point"}
}