{
  "type": "Feature",
  "properties": {
    "addr:full":"1155 Meridian Ave San Jose CA 95125",
    "addr:housenumber":"1155",
    "addr:postcode":"95125",
    "addr:street":"Meridian Ave",
    "iso:country":"US",
    "sg:address":"1155 Meridian Ave",
    "sg:city":"San Jose",
    "sg:classifiers":[
        {
            "category":"Banks & Credit Unions",
            "subcategory":"Investment Brokerage",
            "type":"Services"
        }
    ],
    "sg:phone":"+1 408 978 1400",
    "sg:postcode":"95125",
    "sg:province":"CA",
    "sg:tags":[
        "advisory",
        "financial"
    ],
    "wof:name":"SOL Financial Svc",
    "wof:placetype":"venue"
},
  "geometry": {"coordinates":[-121.913675,37.303352],"type":"Point"}
}