{
  "type": "Feature",
  "properties": {
    "iso:country":"US",
    "sg:address":"19290 Desiree Ct",
    "sg:city":"Cottonwood",
    "sg:classifiers":[
        {
            "category":"Manufacturing",
            "subcategory":"Metals",
            "type":"Manufacturing & Wholesale Goods"
        }
    ],
    "sg:phone":"+1 530 243 7266",
    "sg:postcode":"96022",
    "sg:province":"CA",
    "sg:tags":[
        "tool",
        "mfg"
    ],
    "wof:name":"Snap-On Tools",
    "wof:placetype":"venue"
},
  "geometry": {"coordinates":[-122.32904600000001,40.353736],"type":"Point"}
}