{
  "type": "Feature",
  "properties": {
    "addr:full":"23 W 6th St Antioch CA 94509",
    "addr:housenumber":"23",
    "addr:postcode":"ca 94509",
    "addr:street":"W 6Th St",
    "iso:country":"US",
    "sg:address":"23 W 6th St",
    "sg:city":"Antioch",
    "sg:classifiers":[
        {
            "category":"Professional",
            "subcategory":"Accounting & Tax Preparation",
            "type":"Services"
        }
    ],
    "sg:phone":"+1 925 753 1986",
    "sg:postcode":"94509",
    "sg:province":"CA",
    "sg:tags":[
        "billing"
    ],
    "wof:name":"Delta Medical Svc",
    "wof:placetype":"venue"
},
  "geometry": {"coordinates":[-121.807258,38.013958],"type":"Point"}
}