{
  "type": "Feature",
  "properties": {
    "iso:country":"US",
    "sg:address":"196 Solana Point Cir",
    "sg:city":"Solana Beach",
    "sg:classifiers":[
        {
            "category":"Banks & Credit Unions",
            "subcategory":"Bank",
            "type":"Services"
        }
    ],
    "sg:phone":"+1 858 793 4666",
    "sg:postcode":"92075",
    "sg:province":"CA",
    "sg:tags":[
        "company"
    ],
    "wof:name":"Campbell River Co",
    "wof:placetype":"venue"
},
  "geometry": {"coordinates":[-117.272626,33.003745],"type":"Point"}
}