{
  "type": "Feature",
  "properties": {
    "addr:full":"24831 Narbonne Ave Lomita CA 90717",
    "addr:postcode":"24831;90717",
    "addr:street":"Narbonne Ave",
    "iso:country":"US",
    "sg:address":"24831 Narbonne Ave",
    "sg:city":"Lomita",
    "sg:classifiers":[
        {
            "category":"Arena",
            "subcategory":"Sports Club",
            "type":"Entertainment"
        }
    ],
    "sg:phone":"+1 310 929 0834",
    "sg:postcode":"90717",
    "sg:province":"CA",
    "sg:tags":[
        "martial art"
    ],
    "sg:website":"www.cjjusa.com",
    "wof:name":"Caique Jiu Jitsu",
    "wof:placetype":"venue"
},
  "geometry": {"coordinates":[-118.319969,33.798677],"type":"Point"}
}