{
  "type": "Feature",
  "properties": {
    "addr:full":"4477 Shadow Hills Blvd S Santa Barbara CA 93105",
    "addr:housenumber":"4477",
    "addr:postcode":"93105",
    "addr:street":"Shadow Hills Blvd S Santa Barbara",
    "iso:country":"US",
    "sg:address":"4477 Shadow Hills Blvd S",
    "sg:city":"Santa Barbara",
    "sg:classifiers":[
        {
            "category":"Professional",
            "type":"Services"
        }
    ],
    "sg:phone":"+1 805 964 4283",
    "sg:postcode":"93105",
    "sg:province":"CA",
    "wof:name":"Asselins",
    "wof:placetype":"venue"
},
  "geometry": {"coordinates":[-119.774272,34.461237],"type":"Point"}
}