{
  "type": "Feature",
  "properties": {
    "iso:country":"US",
    "sg:address":"1345 Fillmore St",
    "sg:city":"San Francisco",
    "sg:classifiers":[
        {
            "category":"Parking",
            "type":"Transportation"
        }
    ],
    "sg:phone":"+1 415 921 1969",
    "sg:postcode":"94115",
    "sg:province":"CA",
    "sg:tags":[
        "garage"
    ],
    "wof:name":"Fillmore Center Garage",
    "wof:placetype":"venue"
},
  "geometry": {"coordinates":[-122.43325,37.781812],"type":"Point"}
}