{
  "type": "Feature",
  "properties": {
    "iso:country":"US",
    "sg:address":"5900 Cathy Ave",
    "sg:city":"Cypress",
    "sg:classifiers":[
        {
            "category":"Building & Trades",
            "subcategory":"Construction",
            "type":"Services"
        }
    ],
    "sg:phone":"+1 714 226 0699",
    "sg:postcode":"90630",
    "sg:province":"CA",
    "sg:tags":[
        "contractor"
    ],
    "wof:name":"Bernards Brothers",
    "wof:placetype":"venue"
},
  "geometry": {"coordinates":[-118.03367,33.811693],"type":"Point"}
}