{
  "type": "Feature",
  "properties": {
    "addr:full":"2020 Junction Avenue San Jose CA 95131",
    "addr:housenumber":"2020",
    "addr:postcode":"95131",
    "addr:street":"Junction Avenue",
    "iso:country":"US",
    "sg:address":"2020 Junction Avenue",
    "sg:city":"San Jose",
    "sg:classifiers":[
        {
            "category":"Government",
            "subcategory":"City Hall",
            "type":"Public Place"
        }
    ],
    "sg:phone":"+1 408 467 5400",
    "sg:postcode":"95131",
    "sg:province":"CA",
    "sg:website":"www.chp.ca.gov/",
    "wof:name":"California Highway Patrol",
    "wof:placetype":"venue"
},
  "geometry": {"coordinates":[-121.91319300000001,37.384137],"type":"Point"}
}