{
  "type": "Feature",
  "properties": {
    "addr:full":"21622 Figueroa St Carson CA 90745",
    "addr:housenumber":"21622",
    "addr:postcode":"90745",
    "addr:street":"Figueroa St",
    "iso:country":"US",
    "sg:address":"21622 Figueroa St",
    "sg:city":"Carson",
    "sg:classifiers":[
        {
            "category":"Personal",
            "subcategory":"Beauty Salon",
            "type":"Services"
        }
    ],
    "sg:phone":"+1 310 533 8911",
    "sg:postcode":"90745",
    "sg:province":"CA",
    "wof:name":"Webb's Ruth Beauty Salon",
    "wof:placetype":"venue"
},
  "geometry": {"coordinates":[-118.28598,33.832243],"type":"Point"}
}