{
  "type": "Feature",
  "properties": {
    "addr:full":"715 S Broadway Santa Maria CA 93454",
    "addr:housenumber":"715",
    "addr:postcode":"93454",
    "addr:street":"S Broadway",
    "iso:country":"US",
    "sg:address":"715 S Broadway",
    "sg:city":"Santa Maria",
    "sg:classifiers":[
        {
            "category":"Restaurant",
            "type":"Food & Drink"
        }
    ],
    "sg:phone":"+1 805 925 0212",
    "sg:postcode":"93454",
    "sg:province":"CA",
    "wof:name":"Quito's Mexican Food",
    "wof:placetype":"venue"
},
  "geometry": {"coordinates":[-120.436106,34.945654],"type":"Point"}
}