{
  "type": "Feature",
  "properties": {
    "addr:full":"10370 Overland Trl Cherry Valley CA 92223",
    "addr:housenumber":"10370",
    "addr:postcode":"92223",
    "addr:street":"Overland Trl",
    "iso:country":"US",
    "sg:address":"10370 Overland Trl",
    "sg:city":"Cherry Valley",
    "sg:classifiers":[
        {
            "category":"Organizations",
            "subcategory":"Professional Association",
            "type":"Services"
        }
    ],
    "sg:phone":"+1 951 845 5768",
    "sg:postcode":"92223",
    "sg:province":"CA",
    "wof:name":"Highland Springs Village Ownrs",
    "wof:placetype":"venue"
},
  "geometry": {"coordinates":[-116.946507,33.970361],"type":"Point"}
}