{
  "type": "Feature",
  "properties": {
    "iso:country":"US",
    "sg:address":"6822 El Cajon Blvd",
    "sg:city":"San Diego",
    "sg:classifiers":[
        {
            "category":"Professional",
            "subcategory":"Computer Services",
            "type":"Services"
        }
    ],
    "sg:phone":"+1 619 460 5600",
    "sg:postcode":"92115",
    "sg:province":"CA",
    "sg:tags":[
        "repair"
    ],
    "sg:website":"www.networx.com",
    "wof:name":"Networx",
    "wof:placetype":"venue"
},
  "geometry": {"coordinates":[-117.098609,32.768843],"type":"Point"}
}