{
  "type": "Feature",
  "properties": {
    "iso:country":"US",
    "sg:address":"7137 Owensmouth Ave",
    "sg:city":"Canoga Park",
    "sg:classifiers":[
        {
            "category":"Shopping",
            "subcategory":"Used Merchandise",
            "type":"Retail Goods"
        }
    ],
    "sg:phone":"+1 818 716 5737",
    "sg:postcode":"91303",
    "sg:province":"CA",
    "sg:tags":[
        "repair",
        "appliance"
    ],
    "wof:name":"J & R Appliances",
    "wof:placetype":"venue"
},
  "geometry": {"coordinates":[-118.601698,34.200311],"type":"Point"}
}