{
  "type": "Feature",
  "properties": {
    "addr:full":"2809 Olive Hwy Oroville CA 95966",
    "addr:housenumber":"2809",
    "addr:postcode":"95966",
    "addr:street":"Olive Hwy",
    "iso:country":"US",
    "sg:address":"2809 Olive Hwy",
    "sg:city":"Oroville",
    "sg:classifiers":[
        {
            "category":"Health Services",
            "subcategory":"Doctor",
            "type":"Services"
        }
    ],
    "sg:phone":"+1 530 532 8180",
    "sg:postcode":"95966",
    "sg:province":"CA",
    "sg:tags":[
        "physician",
        "surgeon"
    ],
    "wof:name":"Oroville Women's Health",
    "wof:placetype":"venue"
},
  "geometry": {"coordinates":[-121.54145200000001,39.504188],"type":"Point"}
}