{
  "type": "Feature",
  "properties": {
    "iso:country":"US",
    "sg:address":"10755 Mueller Ct",
    "sg:city":"Tustin",
    "sg:classifiers":[
        {
            "category":"Building & Trades",
            "subcategory":"Construction",
            "type":"Services"
        }
    ],
    "sg:phone":"+1 714 531 0377",
    "sg:postcode":"92782",
    "sg:province":"CA",
    "sg:tags":[
        "painter"
    ],
    "wof:name":"New World Painting",
    "wof:placetype":"venue"
},
  "geometry": {"coordinates":[-117.765154,33.759937],"type":"Point"}
}