{
  "type": "Feature",
  "properties": {
    "iso:country":"US",
    "sg:address":"150 Waverly Pl",
    "sg:city":"San Francisco",
    "sg:classifiers":[
        {
            "category":"Restaurant",
            "type":"Food & Drink"
        }
    ],
    "sg:phone":"+1 415 248 5323",
    "sg:postcode":"94108",
    "sg:province":"CA",
    "wof:name":"A Chinatown Tradition",
    "wof:placetype":"venue"
},
  "geometry": {"coordinates":[-122.406854,37.794641],"type":"Point"}
}