{
  "type": "Feature",
  "properties": {
    "addr:full":"812 S Maclay St San Fernando CA 91340",
    "addr:housenumber":"812",
    "addr:postcode":"91340",
    "addr:street":"S Maclay St",
    "iso:country":"US",
    "sg:address":"812 S Maclay St",
    "sg:city":"San Fernando",
    "sg:classifiers":[
        {
            "category":"Home & Garden",
            "subcategory":"Furniture",
            "type":"Retail Goods"
        }
    ],
    "sg:phone":"+1 818 365 6815",
    "sg:postcode":"91340",
    "sg:province":"CA",
    "wof:name":"Alfonso's Furn ELECTRONICS",
    "wof:placetype":"venue"
},
  "geometry": {"coordinates":[-118.448534,34.277945],"type":"Point"}
}