{
  "type": "Feature",
  "properties": {
    "iso:country":"US",
    "sg:address":"10115 Hole Ave",
    "sg:city":"Riverside",
    "sg:classifiers":[
        {
            "category":"Shopping",
            "subcategory":"Clothing, Apparel, & Fashions",
            "type":"Retail Goods"
        }
    ],
    "sg:phone":"+1 951 352 5868",
    "sg:postcode":"92503",
    "sg:province":"CA",
    "wof:name":"Dee-Lux",
    "wof:placetype":"venue"
},
  "geometry": {"coordinates":[-117.459613,33.914539],"type":"Point"}
}