{
  "type": "Feature",
  "properties": {
    "iso:country":"US",
    "sg:address":"10000 Beverly Blvd",
    "sg:city":"Pico Rivera",
    "sg:classifiers":[
        {
            "category":"Retail",
            "subcategory":"Storage",
            "type":"Services"
        }
    ],
    "sg:phone":"+1 562 695 8085",
    "sg:postcode":"90660",
    "sg:province":"CA",
    "sg:tags":[
        "self"
    ],
    "wof:name":"Beverly Rv Storage",
    "wof:placetype":"venue"
},
  "geometry": {"coordinates":[-118.066002,34.005699],"type":"Point"}
}