{
  "type": "Feature",
  "properties": {
    "iso:country":"US",
    "sg:address":"10753 River Rd",
    "sg:city":"Hood",
    "sg:classifiers":[
        {
            "category":"Restaurant",
            "type":"Food & Drink"
        }
    ],
    "sg:phone":"+1 916 775 0087",
    "sg:postcode":"95639",
    "sg:province":"CA",
    "wof:name":"Lai Yuen Restaurant",
    "wof:placetype":"venue"
},
  "geometry": {"coordinates":[-121.519905,38.369532],"type":"Point"}
}