{
  "type": "Feature",
  "properties": {
    "addr:full":"802 Orange St Yuba City CA 95991",
    "addr:housenumber":"802",
    "addr:postcode":"95991",
    "addr:street":"Orange St",
    "iso:country":"US",
    "sg:address":"802 Orange St",
    "sg:city":"Yuba City",
    "sg:classifiers":[
        {
            "category":"Wholesale",
            "subcategory":"Auto Parts",
            "type":"Manufacturing & Wholesale Goods"
        }
    ],
    "sg:phone":"+1 530 674 2993",
    "sg:postcode":"95991",
    "sg:province":"CA",
    "wof:name":"Guy Autoglass",
    "wof:placetype":"venue"
},
  "geometry": {"coordinates":[-121.622681,39.140139],"type":"Point"}
}