{
  "type": "Feature",
  "properties": {
    "iso:country":"US",
    "sg:address":"1095 McCoy Ln",
    "sg:city":"Santa Maria",
    "sg:classifiers":[
        {
            "category":"Professional",
            "subcategory":"Business Services",
            "type":"Services"
        }
    ],
    "sg:phone":"+1 805 348 1800",
    "sg:postcode":"93455",
    "sg:province":"CA",
    "wof:name":"McAllister Robert W Planners",
    "wof:placetype":"venue"
},
  "geometry": {"coordinates":[-120.451431,34.916873],"type":"Point"}
}