{
  "type": "Feature",
  "properties": {
    "addr:full":"175 E Front St Farmersville CA 93223",
    "addr:housenumber":"175",
    "addr:postcode":"93223",
    "addr:street":"E Front St",
    "iso:country":"US",
    "sg:address":"175 E Front St",
    "sg:city":"Farmersville",
    "sg:classifiers":[
        {
            "category":"Government",
            "subcategory":"Office",
            "type":"Public Place"
        }
    ],
    "sg:phone":"+1 559 747 0843",
    "sg:postcode":"93223",
    "sg:province":"CA",
    "sg:tags":[
        "program",
        "administrative"
    ],
    "wof:name":"Wic Department",
    "wof:placetype":"venue"
},
  "geometry": {"coordinates":[-119.206253,36.304575],"type":"Point"}
}