{
  "type": "Feature",
  "properties": {
    "iso:country":"US",
    "sg:address":"962 W Manchester Avenue",
    "sg:city":"Los Angeles",
    "sg:classifiers":[
        {
            "category":"Health Services",
            "subcategory":"Dentist",
            "type":"Services"
        }
    ],
    "sg:phone":"+1 323 753 2596",
    "sg:postcode":"90044",
    "sg:province":"CA",
    "wof:name":"Donnelly R L DDS",
    "wof:placetype":"venue"
},
  "geometry": {"coordinates":[-118.290999,33.960141],"type":"Point"}
}