{
  "type": "Feature",
  "properties": {
    "iso:country":"US",
    "sg:address":"37212 Santa Rosa Glen Dr",
    "sg:city":"Murrieta",
    "sg:classifiers":[
        {
            "category":"Retail",
            "subcategory":"Repair Shop",
            "type":"Services"
        }
    ],
    "sg:phone":"+1 951 696 1989",
    "sg:postcode":"92562",
    "sg:province":"CA",
    "sg:tags":[
        "equipment",
        "telecommunication",
        "telephone",
        "consultant",
        "system"
    ],
    "wof:name":"Progressive Electronics",
    "wof:placetype":"venue"
},
  "geometry": {"coordinates":[-117.254395,33.579106],"type":"Point"}
}