{
  "type": "Feature",
  "properties": {
    "iso:country":"US",
    "sg:address":"18 Sunnydale Ln",
    "sg:city":"Rcho Sta Marg",
    "sg:classifiers":[
        {
            "category":"Building & Trades",
            "subcategory":"Pest Control",
            "type":"Services"
        }
    ],
    "sg:phone":"+1 949 766 8330",
    "sg:postcode":"92688",
    "sg:province":"CA",
    "wof:name":"Apollo Termite Control",
    "wof:placetype":"venue"
},
  "geometry": {"coordinates":[-117.625863,33.586029],"type":"Point"}
}