{
  "type": "Feature",
  "properties": {
    "addr:full":"7018 Blair Rd Calipatria CA 92233",
    "addr:housenumber":"7018",
    "addr:postcode":"92233",
    "addr:street":"Blair Rd",
    "iso:country":"US",
    "sg:address":"7018 Blair Rd",
    "sg:city":"Calipatria",
    "sg:classifiers":[
        {
            "category":"Professional",
            "type":"Services"
        }
    ],
    "sg:phone":"+1 760 348 5323",
    "sg:postcode":"92233",
    "sg:province":"CA",
    "sg:tags":[
        "establishment"
    ],
    "wof:name":"Centerforce",
    "wof:placetype":"venue"
},
  "geometry": {"coordinates":[-115.49311299999999,33.167688],"type":"Point"}
}