{
  "type": "Feature",
  "properties": {
    "addr:full":"13312 Springdale St Westminster CA 92683",
    "addr:housenumber":"13312",
    "addr:postcode":"92683",
    "addr:street":"Springdale St",
    "iso:country":"US",
    "sg:address":"13312 Springdale St",
    "sg:city":"Westminster",
    "sg:classifiers":[
        {
            "category":"Building & Trades",
            "subcategory":"Plumbing",
            "type":"Services"
        }
    ],
    "sg:phone":"+1 714 892 1795",
    "sg:postcode":"92683",
    "sg:province":"CA",
    "sg:tags":[
        "contractor"
    ],
    "wof:name":"Mulligan Plumbing",
    "wof:placetype":"venue"
},
  "geometry": {"coordinates":[-118.025188,33.771045],"type":"Point"}
}