{
  "type": "Feature",
  "properties": {
    "addr:full":"5437 Laurel Canyon Blvd Valley Village CA 91607",
    "addr:housenumber":"5437",
    "addr:postcode":"91607",
    "addr:street":"Laurel Canyon Blvd",
    "iso:country":"US",
    "sg:address":"5437 Laurel Canyon Blvd",
    "sg:city":"Valley Village",
    "sg:classifiers":[
        {
            "category":"Manufacturing",
            "subcategory":"Signs",
            "type":"Manufacturing & Wholesale Goods"
        }
    ],
    "sg:phone":"+1 818 753 1748",
    "sg:postcode":"91607",
    "sg:province":"CA",
    "sg:tags":[
        "specialty",
        "mfg"
    ],
    "wof:name":"Sign Parade",
    "wof:placetype":"venue"
},
  "geometry": {"coordinates":[-118.396576,34.169712],"type":"Point"}
}