{
  "type": "Feature",
  "properties": {
    "addr:full":"640 Garfield Ave El Cajon CA 92020",
    "addr:housenumber":"640",
    "addr:postcode":"92020",
    "addr:street":"Garfield Ave",
    "iso:country":"US",
    "sg:address":"640 Garfield Ave",
    "sg:city":"El Cajon",
    "sg:classifiers":[
        {
            "category":"Retail",
            "subcategory":"Auto Repair",
            "type":"Services"
        }
    ],
    "sg:phone":"+1 619 464 4200",
    "sg:postcode":"92020",
    "sg:province":"CA",
    "sg:tags":[
        "repairing",
        "automobile"
    ],
    "wof:name":"Al & Don Automotive",
    "wof:placetype":"venue"
},
  "geometry": {"coordinates":[-116.997615,32.802616],"type":"Point"}
}