{
  "type": "Feature",
  "properties": {
    "addr:full":"675 Valley Rd Walnut Creek CA 94564",
    "addr:housenumber":"675",
    "addr:postcode":"94564",
    "addr:street":"Valley Rd",
    "iso:country":"US",
    "sg:address":"675 Valley Rd",
    "sg:city":"Walnut Creek",
    "sg:classifiers":[
        {
            "category":"Professional",
            "subcategory":"Accounting & Tax Preparation",
            "type":"Services"
        }
    ],
    "sg:phone":"+1 415 876 1120",
    "sg:postcode":"94564",
    "sg:province":"CA",
    "sg:tags":[
        "return",
        "filing"
    ],
    "wof:name":"Tax Care",
    "wof:placetype":"venue"
},
  "geometry": {"coordinates":[-122.289356,38.006995],"type":"Point"}
}