{
  "type": "Feature",
  "properties": {
    "addr:full":"115 Bonnie Ct Camino CA 95709",
    "addr:housenumber":"115",
    "addr:postcode":"95709",
    "addr:street":"Bonnie Ct Camino",
    "iso:country":"US",
    "sg:address":"115 Bonnie Ct",
    "sg:city":"Camino",
    "sg:classifiers":[
        {
            "category":"Professional",
            "subcategory":"Computer Services",
            "type":"Services"
        }
    ],
    "sg:phone":"+1 530 644 4909",
    "sg:postcode":"95709",
    "sg:province":"CA",
    "sg:tags":[
        "technical",
        "assistance",
        "support"
    ],
    "sg:website":"http://www.colormine.com",
    "wof:name":"Colormine Web Works",
    "wof:placetype":"venue"
},
  "geometry": {"coordinates":[-120.630589,38.750254],"type":"Point"}
}