{
  "type": "Feature",
  "properties": {
    "iso:country":"US",
    "sg:address":"1645 Beverly Blvd",
    "sg:city":"Los Angeles",
    "sg:classifiers":[
        {
            "category":"Professional",
            "subcategory":"Lawyer & Legal Services",
            "type":"Services"
        }
    ],
    "sg:phone":"+1 213 975 9091",
    "sg:postcode":"90026",
    "sg:province":"CA",
    "sg:tags":[
        "naturalization",
        "immigration"
    ],
    "wof:name":"Immigration Solution Ctr",
    "wof:placetype":"venue"
},
  "geometry": {"coordinates":[-118.265185,34.064418],"type":"Point"}
}