{
  "type": "Feature",
  "properties": {
    "iso:country":"US",
    "sg:address":"4320 Atlantic Ave",
    "sg:city":"Long Beach",
    "sg:classifiers":[
        {
            "category":"Wholesale",
            "subcategory":"Machinery & Supplies",
            "type":"Manufacturing & Wholesale Goods"
        }
    ],
    "sg:phone":"+1 562 981 5352",
    "sg:postcode":"90807",
    "sg:province":"CA",
    "sg:tags":[
        "equipment",
        "establishment"
    ],
    "wof:name":"D M Carpet & Flooring Co",
    "wof:placetype":"venue"
},
  "geometry": {"coordinates":[-118.184923,33.835256],"type":"Point"}
}