{
  "type": "Feature",
  "properties": {
    "iso:country":"US",
    "sg:address":"9770 Culver Blvd",
    "sg:city":"Culver City",
    "sg:classifiers":[
        {
            "category":"Government",
            "subcategory":"Office",
            "type":"Public Place"
        }
    ],
    "sg:phone":"+1 310 253 5800",
    "sg:postcode":"90232",
    "sg:province":"CA",
    "sg:tags":[
        "city",
        "inspection"
    ],
    "wof:name":"Culver City Building Permits",
    "wof:placetype":"venue"
},
  "geometry": {"coordinates":[-118.396182,34.021554],"type":"Point"}
}