{
  "type": "Feature",
  "properties": {
    "addr:full":"1359 E 4th St Ontario CA 91764",
    "addr:housenumber":"1359",
    "addr:postcode":"91764",
    "addr:street":"E 4Th St",
    "iso:country":"US",
    "sg:address":"1359 E 4th St",
    "sg:city":"Ontario",
    "sg:classifiers":[
        {
            "category":"Wholesale",
            "subcategory":"Electrical",
            "type":"Manufacturing & Wholesale Goods"
        },
        {
            "category":"Shopping",
            "subcategory":"Computers & Home Electronics",
            "type":"Retail Goods"
        }
    ],
    "sg:phone":"+1 909 988 9952",
    "sg:postcode":"91764",
    "sg:province":"CA",
    "sg:tags":[
        "equipment",
        "electronic",
        "supply"
    ],
    "wof:name":"Los Amaya Electronica Y Discot",
    "wof:placetype":"venue"
},
  "geometry": {"coordinates":[-117.627244,34.077725],"type":"Point"}
}