{
  "type": "Feature",
  "properties": {
    "addr:full":"265 E Drake Dr San Bernardino CA 92408",
    "addr:housenumber":"265",
    "addr:postcode":"92408",
    "addr:street":"E Drake Dr",
    "iso:country":"US",
    "sg:address":"265 E Drake Dr",
    "sg:city":"San Bernardino",
    "sg:classifiers":[
        {
            "category":"Wholesale",
            "subcategory":"Groceries",
            "type":"Manufacturing & Wholesale Goods"
        }
    ],
    "sg:phone":"+1 909 383 1520",
    "sg:postcode":"92408",
    "sg:province":"CA",
    "sg:tags":[
        "grocer"
    ],
    "wof:name":"Summit Cash & Carry",
    "wof:placetype":"venue"
},
  "geometry": {"coordinates":[-117.279415,34.089031],"type":"Point"}
}