{
  "type": "Feature",
  "properties": {
    "iso:country":"US",
    "sg:address":"625 Elm Ave",
    "sg:city":"Seaside",
    "sg:classifiers":[
        {
            "category":"Organizations",
            "subcategory":"Religious Organization",
            "type":"Services"
        }
    ],
    "sg:phone":"+1 831 899 2712",
    "sg:postcode":"93955",
    "sg:province":"CA",
    "sg:tags":[
        "church"
    ],
    "wof:name":"Hays CME Church",
    "wof:placetype":"venue"
},
  "geometry": {"coordinates":[-121.849379,36.607806],"type":"Point"}
}