{
  "type": "Feature",
  "properties": {
    "iso:country":"US",
    "sg:address":"2560 Dominic Dr",
    "sg:city":"Chico",
    "sg:classifiers":[
        {
            "category":"Home & Garden",
            "subcategory":"Carpets & Floor Coverings",
            "type":"Retail Goods"
        }
    ],
    "sg:phone":"+1 530 898 9977",
    "sg:postcode":"95928",
    "sg:province":"CA",
    "sg:tags":[
        "dealer",
        "rug"
    ],
    "wof:name":"Cal-Vada Flooring & Interiors",
    "wof:placetype":"venue"
},
  "geometry": {"coordinates":[-121.78836200000001,39.712524],"type":"Point"}
}