{
  "type": "Feature",
  "properties": {
    "iso:country":"US",
    "sg:address":"101 1st St",
    "sg:city":"Los Altos",
    "sg:classifiers":[
        {
            "category":"Shopping",
            "subcategory":"Catalog Store",
            "type":"Retail Goods"
        }
    ],
    "sg:phone":"+1 650 917 9141",
    "sg:postcode":"94022",
    "sg:province":"CA",
    "sg:tags":[
        "e"
    ],
    "wof:name":"Elateral",
    "wof:placetype":"venue"
},
  "geometry": {"coordinates":[-122.11867,37.37903],"type":"Point"}
}