{
  "type": "Feature",
  "properties": {
    "addr:full":"4200 Sonoma Hwy Santa Rosa CA 95409",
    "addr:housenumber":"4200",
    "addr:postcode":"95409",
    "addr:street":"Sonoma Hwy",
    "iso:country":"US",
    "sg:address":"4200 Sonoma Hwy",
    "sg:city":"Santa Rosa",
    "sg:classifiers":[
        {
            "category":"Retail",
            "subcategory":"Veterinary Services",
            "type":"Services"
        }
    ],
    "sg:phone":"+1 707 539 1262",
    "sg:postcode":"95409",
    "sg:province":"CA",
    "sg:tags":[
        "hospital",
        "animal"
    ],
    "wof:name":"Rincon Valley Animal Hospital",
    "wof:placetype":"venue"
},
  "geometry": {"coordinates":[-122.67823799999999,38.456389],"type":"Point"}
}