{
  "type": "Feature",
  "properties": {
    "addr:full":"In Line Chiropractic 2100 Lakeshore Ave Oakland CA 94606",
    "addr:housenumber":"2100",
    "addr:postcode":"94606",
    "addr:street":"In;Lakeshore Ave",
    "iso:country":"US",
    "sg:address":"In Line Chiropractic 2100 Lakeshore Ave",
    "sg:city":"Oakland",
    "sg:classifiers":[
        {
            "category":"Health Services",
            "subcategory":"Health Practitioner",
            "type":"Services"
        }
    ],
    "sg:phone":"+1 510 893 1577",
    "sg:postcode":"94606",
    "sg:province":"CA",
    "sg:tags":[
        "acupuncture"
    ],
    "sg:website":"www.inlinedc.com",
    "wof:name":"Charles Adamec, LAc",
    "wof:placetype":"venue"
},
  "geometry": {"coordinates":[-122.25102200000001,37.804368],"type":"Point"}
}