{
  "type": "Feature",
  "properties": {
    "iso:country":"US",
    "sg:address":"12061 Jefferson Blvd",
    "sg:city":"Culver City",
    "sg:classifiers":[
        {
            "category":"Organizations",
            "subcategory":"Non-profit Organization",
            "type":"Services"
        }
    ],
    "sg:phone":"+1 310 574 7800",
    "sg:postcode":"90230",
    "sg:province":"CA",
    "wof:name":"Ceramic Tile Institute-America",
    "wof:placetype":"venue"
},
  "geometry": {"coordinates":[-118.406594,33.983026],"type":"Point"}
}