{
  "type": "Feature",
  "properties": {
    "addr:full":"349 Eucalyptus Ave El Centro CA 92243",
    "addr:housenumber":"349",
    "addr:postcode":"92243",
    "addr:street":"Eucalyptus Ave",
    "iso:country":"US",
    "sg:address":"349 Eucalyptus Ave",
    "sg:city":"El Centro",
    "sg:classifiers":[
        {
            "category":"Food & Beverages",
            "subcategory":"Meat & Fish",
            "type":"Retail Goods"
        }
    ],
    "sg:phone":"+1 760 352 2689",
    "sg:postcode":"92243",
    "sg:province":"CA",
    "wof:name":"Sanders Sedalia",
    "wof:placetype":"venue"
},
  "geometry": {"coordinates":[-115.54879200000001,32.802644],"type":"Point"}
}