{
  "type": "Feature",
  "properties": {
    "addr:full":"1044 N Pass Ave Burbank CA 91505",
    "addr:housenumber":"1044",
    "addr:postcode":"91505",
    "addr:street":"N Pass Ave",
    "iso:country":"US",
    "sg:address":"1044 N Pass Ave",
    "sg:city":"Burbank",
    "sg:classifiers":[
        {
            "category":"Home & Garden",
            "subcategory":"Furniture",
            "type":"Retail Goods"
        }
    ],
    "sg:phone":"+1 818 846 5118",
    "sg:postcode":"91505",
    "sg:province":"CA",
    "sg:tags":[
        "bedding"
    ],
    "sg:website":"www.colorsofafrica.com",
    "wof:name":"Colors Of Africa",
    "wof:placetype":"venue"
},
  "geometry": {"coordinates":[-118.35247099999999,34.169607],"type":"Point"}
}