{
  "type": "Feature",
  "properties": {
    "iso:country":"US",
    "sg:address":"33 Surrey Ct",
    "sg:city":"Daly City",
    "sg:classifiers":[
        {
            "category":"Professional",
            "type":"Services"
        }
    ],
    "sg:phone":"+1 650 878 1276",
    "sg:postcode":"94015",
    "sg:province":"CA",
    "sg:tags":[
        "establishment"
    ],
    "wof:name":"LA Mirada Intl",
    "wof:placetype":"venue"
},
  "geometry": {"coordinates":[-122.46699099999999,37.661376],"type":"Point"}
}