{
  "type": "Feature",
  "properties": {
    "iso:country":"US",
    "sg:address":"24882 Apple St",
    "sg:city":"Newhall",
    "sg:classifiers":[
        {
            "category":"Retail",
            "subcategory":"Veterinary Services",
            "type":"Services"
        }
    ],
    "sg:phone":"+1 661 254 6680",
    "sg:postcode":"91321",
    "sg:province":"CA",
    "sg:tags":[
        "veterinarian"
    ],
    "wof:name":"Valley Lyons Pet Clinic",
    "wof:placetype":"venue"
},
  "geometry": {"coordinates":[-118.542,34.379101],"type":"Point"}
}