{
  "type": "Feature",
  "properties": {
    "addr:full":"4850 Jackson St Riverside CA 92503",
    "addr:housenumber":"4850",
    "addr:postcode":"92503",
    "addr:street":"Jackson St",
    "iso:country":"US",
    "sg:address":"4850 Jackson St",
    "sg:city":"Riverside",
    "sg:classifiers":[
        {
            "category":"Cinema",
            "subcategory":"Movie Rental",
            "type":"Entertainment"
        }
    ],
    "sg:phone":"+1 951 354 6508",
    "sg:postcode":"92503",
    "sg:province":"CA",
    "sg:tags":[
        "leasing",
        "video",
        "disc",
        "tape"
    ],
    "wof:name":"Video Plus",
    "wof:placetype":"venue"
},
  "geometry": {"coordinates":[-117.45289,33.942091],"type":"Point"}
}