{
  "type": "Feature",
  "properties": {
    "iso:country":"US",
    "sg:address":"709 Brea Canyon Rd",
    "sg:city":"Walnut",
    "sg:classifiers":[
        {
            "category":"Shopping",
            "subcategory":"Computers & Home Electronics",
            "type":"Retail Goods"
        }
    ],
    "sg:phone":"+1 909 595 1799",
    "sg:postcode":"91789",
    "sg:province":"CA",
    "sg:tags":[
        "equipment",
        "dealer"
    ],
    "wof:name":"Techwell Solutions",
    "wof:placetype":"venue"
},
  "geometry": {"coordinates":[-117.846502,34.006481],"type":"Point"}
}