{
  "type": "Feature",
  "properties": {
    "iso:country":"US",
    "sg:address":"1 Hubbard St",
    "sg:city":"Sylmar",
    "sg:classifiers":[
        {
            "category":"Travel",
            "subcategory":"Travel Agent",
            "type":"Entertainment"
        }
    ],
    "sg:phone":"+1 818 367 0921",
    "sg:postcode":"91342",
    "sg:province":"CA",
    "sg:tags":[
        "agency"
    ],
    "wof:name":"Caravel Tours & Travel",
    "wof:placetype":"venue"
},
  "geometry": {"coordinates":[-118.449006,34.290741],"type":"Point"}
}