{
  "type": "Feature",
  "properties": {
    "addr:full":"101 Bayshore Boulevard San Francisco CA 94124",
    "addr:housenumber":"101",
    "addr:postcode":"94124",
    "addr:street":"Bayshore Boulevard",
    "iso:country":"US",
    "sg:address":"101 Bayshore Boulevard",
    "sg:city":"San Francisco",
    "sg:classifiers":[
        {
            "category":"Retail",
            "subcategory":"Auto Repair",
            "type":"Services"
        }
    ],
    "sg:phone":"+1 415 826 7290",
    "sg:postcode":"94124",
    "sg:province":"CA",
    "wof:name":"Patricks Chevron Service",
    "wof:placetype":"venue"
},
  "geometry": {"coordinates":[-122.40355599999999,37.746749],"type":"Point"}
}