{
  "type": "Feature",
  "properties": {
    "addr:full":"77 Asilomar Blvd Pacific Grove CA 93950",
    "addr:housenumber":"77",
    "addr:postcode":"93950",
    "addr:street":"Asilomar Blvd",
    "iso:country":"US",
    "sg:address":"77 Asilomar Blvd",
    "sg:city":"Pacific Grove",
    "sg:classifiers":[
        {
            "category":"Sports & Exercise",
            "subcategory":"Golf",
            "type":"Entertainment"
        }
    ],
    "sg:phone":"+1 831 648 5775",
    "sg:postcode":"93950",
    "sg:province":"CA",
    "sg:tags":[
        "course"
    ],
    "wof:name":"Pevita Inc",
    "wof:placetype":"venue"
},
  "geometry": {"coordinates":[-121.93203,36.633204],"type":"Point"}
}