{
  "type": "Feature",
  "properties": {
    "addr:full":"11834 Sandy Knoll Court Rancho Cordova CA 95742",
    "addr:housenumber":"11834",
    "addr:postcode":"95742",
    "addr:street":"Sandy Knoll Court",
    "iso:country":"US",
    "sg:address":"11834 Sandy Knoll Court",
    "sg:city":"Rancho Cordova",
    "sg:classifiers":[
        {
            "category":"Sports & Exercise",
            "subcategory":"Playing Field",
            "type":"Entertainment"
        }
    ],
    "sg:phone":"+1 916 355 8774",
    "sg:postcode":"95742",
    "sg:province":"CA",
    "sg:tags":[
        "instruction",
        "fitness"
    ],
    "wof:name":"Anatolia \u00a0Family Taekwondoe",
    "wof:placetype":"venue"
},
  "geometry": {"coordinates":[-121.23631899999999,38.550016],"type":"Point"}
}