{
  "type": "Feature",
  "properties": {
    "addr:full":"17752 Beach Boulevard Suite 305 Huntington Beach CA 92647",
    "addr:housenumber":"17752",
    "addr:postcode":"92647",
    "addr:street":"Beach Boulevard Suite 305",
    "iso:country":"US",
    "sg:address":"17752 Beach Boulevard Suite 305",
    "sg:city":"Huntington Beach",
    "sg:classifiers":[
        {
            "category":"Health Services",
            "subcategory":"Doctor",
            "type":"Services"
        }
    ],
    "sg:phone":"+1 714 841 6529",
    "sg:postcode":"92647",
    "sg:province":"CA",
    "sg:tags":[
        "dermatologist"
    ],
    "wof:name":"Manzini Joseph A MD",
    "wof:placetype":"venue"
},
  "geometry": {"coordinates":[-117.98906700000001,33.704551],"type":"Point"}
}