{
  "type": "Feature",
  "properties": {
    "addr:full":"740 W Rosewood Ct Ontario CA 91762",
    "addr:housenumber":"740",
    "addr:postcode":"91762",
    "addr:street":"W Rosewood Ct",
    "iso:country":"US",
    "sg:address":"740 W Rosewood Ct",
    "sg:city":"Ontario",
    "sg:classifiers":[
        {
            "category":"Home & Garden",
            "subcategory":"Building Materials",
            "type":"Retail Goods"
        }
    ],
    "sg:phone":"+1 909 984 7536",
    "sg:postcode":"91762",
    "sg:province":"CA",
    "sg:tags":[
        "equipment",
        "electric",
        "supply"
    ],
    "wof:name":"Reyes Electrical Supply",
    "wof:placetype":"venue"
},
  "geometry": {"coordinates":[-117.662426,34.077066],"type":"Point"}
}