{
  "type": "Feature",
  "properties": {
    "addr:full":"14711 Princeton Ave Ste 2 Moorpark CA 93021",
    "addr:housenumber":"14711",
    "addr:postcode":"ca 93021",
    "addr:street":"Princeton Ave Ste 2",
    "iso:country":"US",
    "sg:address":"14711 Princeton Ave Ste 2",
    "sg:city":"Moorpark",
    "sg:classifiers":[
        {
            "category":"Health Services",
            "subcategory":"Doctor",
            "type":"Services"
        }
    ],
    "sg:phone":"+1 805 532 2841",
    "sg:postcode":"93021",
    "sg:province":"CA",
    "sg:tags":[
        "physician",
        "pediatrics",
        "family",
        "practice",
        "surgeons",
        "manipulative",
        "osteopathic",
        "treatment",
        "medicine",
        "surgeon"
    ],
    "wof:name":"Moorpark Comprehensive Medical Group",
    "wof:placetype":"venue"
},
  "geometry": {"coordinates":[-118.857277,34.295158],"type":"Point"}
}