{
  "type": "Feature",
  "properties": {
    "iso:country":"US",
    "sg:address":"1680 S Melrose Dr Ste 108",
    "sg:city":"Vista",
    "sg:classifiers":[
        {
            "category":"Professional",
            "subcategory":"Management & Consulting",
            "type":"Services"
        }
    ],
    "sg:phone":"+1 760 727 3552",
    "sg:postcode":"92081",
    "sg:province":"CA",
    "sg:tags":[
        "consultant"
    ],
    "wof:name":"M&J Management",
    "wof:placetype":"venue"
},
  "geometry": {"coordinates":[-117.245823,33.165107],"type":"Point"}
}