{
  "type": "Feature",
  "properties": {
    "iso:country":"US",
    "sg:address":"3886 Industrial Way",
    "sg:city":"Benicia",
    "sg:classifiers":[
        {
            "category":"Wholesale",
            "subcategory":"Painting Supplies",
            "type":"Manufacturing & Wholesale Goods"
        }
    ],
    "sg:phone":"+1 707 745 6882",
    "sg:postcode":"94510",
    "sg:province":"CA",
    "sg:tags":[
        "finishing",
        "product",
        "wood",
        "distribution"
    ],
    "wof:name":"Chemical Coating Supply",
    "wof:placetype":"venue"
},
  "geometry": {"coordinates":[-122.122822,38.067637],"type":"Point"}
}