{
  "type": "Feature",
  "properties": {
    "iso:country":"US",
    "sg:address":"161 N Fairview Ave",
    "sg:city":"Goleta",
    "sg:classifiers":[
        {
            "category":"Manufacturing",
            "subcategory":"Chemicals & Compounds",
            "type":"Manufacturing & Wholesale Goods"
        }
    ],
    "sg:phone":"+1 805 964 8435",
    "sg:postcode":"93117",
    "sg:province":"CA",
    "sg:tags":[
        "preparation",
        "toilet",
        "mfg"
    ],
    "wof:name":"Nails By Lara",
    "wof:placetype":"venue"
},
  "geometry": {"coordinates":[-119.830664,34.444058],"type":"Point"}
}