{
  "type": "Feature",
  "properties": {
    "addr:full":"34274 State Hwy 16 Woodland CA 95695",
    "addr:housenumber":"34274",
    "addr:postcode":"95695",
    "addr:street":"State Hwy 16",
    "iso:country":"US",
    "sg:address":"34274 State Hwy 16",
    "sg:city":"Woodland",
    "sg:classifiers":[
        {
            "category":"Wholesale",
            "subcategory":"Machinery & Supplies",
            "type":"Manufacturing & Wholesale Goods"
        }
    ],
    "sg:phone":"+1 530 662 0265",
    "sg:postcode":"95695",
    "sg:province":"CA",
    "sg:tags":[
        "equipment",
        "irrigation",
        "system"
    ],
    "sg:website":"www.ycfcwcd.org",
    "wof:name":"Yolo County Flood Control",
    "wof:placetype":"venue"
},
  "geometry": {"coordinates":[-121.871385,38.66926],"type":"Point"}
}