{
  "type": "Feature",
  "properties": {
    "addr:full":"7950 Cherry Ave 110 Fontana CA 92336",
    "addr:housenumber":"7950;110",
    "addr:postcode":"92336",
    "addr:street":"Cherry Ave",
    "iso:country":"US",
    "sg:address":"7950 Cherry Ave 110",
    "sg:city":"Fontana",
    "sg:classifiers":[
        {
            "category":"Insurance",
            "subcategory":"Insurance Agent",
            "type":"Services"
        }
    ],
    "sg:phone":"+1 909 357 6700",
    "sg:postcode":"92336",
    "sg:province":"CA",
    "sg:tags":[
        "auto"
    ],
    "sg:website":"http://clickserve.dartsearch.net/link/click?lid=43000000277021190",
    "wof:name":"Allstate Insurance Company - Caren Adams",
    "wof:placetype":"venue"
},
  "geometry": {"coordinates":[-117.48872299999999,34.108567],"type":"Point"}
}