{
  "type": "Feature",
  "properties": {
    "addr:full":"8 Packsaddle Rd W Rolling Hills CA 90274",
    "addr:housenumber":"8",
    "addr:postcode":"90274",
    "addr:street":"Packsaddle Rd W",
    "iso:country":"US",
    "sg:address":"8 Packsaddle Rd W",
    "sg:city":"Rolling Hills",
    "sg:classifiers":[
        {
            "category":"Real Estate",
            "subcategory":"Real Estate Agent",
            "type":"Services"
        }
    ],
    "sg:phone":"+1 310 544 3946",
    "sg:postcode":"90274",
    "sg:province":"CA",
    "sg:tags":[
        "management"
    ],
    "wof:name":"One To One Properties",
    "wof:placetype":"venue"
},
  "geometry": {"coordinates":[-118.349227,33.745208],"type":"Point"}
}