{
  "type": "Feature",
  "properties": {
    "iso:country":"US",
    "sg:address":"2030 Industrial Way",
    "sg:city":"Ceres",
    "sg:classifiers":[
        {
            "category":"Food & Beverages",
            "subcategory":"Groceries & Convenience Stores",
            "type":"Retail Goods"
        }
    ],
    "sg:phone":"+1 209 538 8477",
    "sg:postcode":"95307",
    "sg:province":"CA",
    "sg:tags":[
        "grocer"
    ],
    "wof:name":"Industrial Market",
    "wof:placetype":"venue"
},
  "geometry": {"coordinates":[-120.95700100000001,37.585701],"type":"Point"}
}