{
  "type": "Feature",
  "properties": {
    "iso:country":"US",
    "sg:address":"4447 Mieko Way",
    "sg:city":"Sacramento",
    "sg:classifiers":[
        {
            "category":"Building & Trades",
            "subcategory":"Cleaning & Sanitation",
            "type":"Services"
        }
    ],
    "sg:phone":"+1 916 348 7018",
    "sg:postcode":"95841",
    "sg:province":"CA",
    "sg:tags":[
        "carpet"
    ],
    "sg:website":"www.TheCarpetSpecialists.com",
    "wof:name":"The Specialists",
    "wof:placetype":"venue"
},
  "geometry": {"coordinates":[-121.36005299999999,38.656302],"type":"Point"}
}