{
  "type": "Feature",
  "properties": {
    "addr:full":"901 Starcrest Dr Glendora CA 91740",
    "addr:housenumber":"901",
    "addr:postcode":"91740",
    "addr:street":"Starcrest Dr",
    "iso:country":"US",
    "sg:address":"901 Starcrest Dr",
    "sg:city":"Glendora",
    "sg:classifiers":[
        {
            "category":"Freight",
            "type":"Transportation"
        }
    ],
    "sg:phone":"+1 626 914 7668",
    "sg:postcode":"91740",
    "sg:province":"CA",
    "sg:tags":[
        "courier"
    ],
    "wof:name":"Federal Express Corporation",
    "wof:placetype":"venue"
},
  "geometry": {"coordinates":[-117.877837,34.124308],"type":"Point"}
}