{
  "type": "Feature",
  "properties": {
    "addr:full":"5620 Pso del Norte Carlsbad CA 92008",
    "addr:housenumber":"5620",
    "addr:postcode":"92008",
    "addr:street":"Pso Del Norte",
    "iso:country":"US",
    "sg:address":"5620 Pso del Norte",
    "sg:city":"Carlsbad",
    "sg:classifiers":[
        {
            "category":"Personal",
            "type":"Services"
        }
    ],
    "sg:phone":"+1 760 804 9760",
    "sg:postcode":"92008",
    "sg:province":"CA",
    "sg:tags":[
        "mail",
        "receiving"
    ],
    "wof:name":"Postal Annex",
    "wof:placetype":"venue"
},
  "geometry": {"coordinates":[-117.162406,33.331505],"type":"Point"}
}