{
  "type": "Feature",
  "properties": {
    "iso:country":"US",
    "sg:address":"14210 Culver Dr. Ste A",
    "sg:city":"Irvine",
    "sg:classifiers":[
        {
            "category":"Insurance",
            "subcategory":"Hazard Insurance",
            "type":"Services"
        }
    ],
    "sg:phone":"+1 949 559 8866",
    "sg:postcode":"92604",
    "sg:province":"CA",
    "sg:website":"www.richardtay.com",
    "wof:name":"Richard Tay - State Farm Insurance",
    "wof:placetype":"venue"
},
  "geometry": {"coordinates":[-117.784386,33.707937],"type":"Point"}
}