{
  "type": "Feature",
  "properties": {
    "iso:country":"US",
    "sg:address":"57 Longview Dr",
    "sg:city":"Daly City",
    "sg:classifiers":[
        {
            "category":"Professional",
            "subcategory":"Management & Consulting",
            "type":"Services"
        }
    ],
    "sg:phone":"+1 650 756 4805",
    "sg:postcode":"94015",
    "sg:province":"CA",
    "sg:tags":[
        "marketing",
        "consultant"
    ],
    "wof:name":"Pacific Marketing",
    "wof:placetype":"venue"
},
  "geometry": {"coordinates":[-122.48932499999999,37.665365],"type":"Point"}
}