{
  "type": "Feature",
  "properties": {
    "addr:full":"4500 Campus Drive Suite 103 Newport Beach CA 92660",
    "addr:housenumber":"4500",
    "addr:postcode":"92660",
    "addr:street":"Campus Drive Suite 103",
    "iso:country":"US",
    "sg:address":"4500 Campus Drive Suite 103",
    "sg:city":"Newport Beach",
    "sg:classifiers":[
        {
            "category":"Education",
            "subcategory":"Special Training",
            "type":"Public Place"
        }
    ],
    "sg:phone":"+1 949 252 8088",
    "sg:postcode":"92660",
    "sg:province":"CA",
    "sg:tags":[
        "school",
        "language"
    ],
    "wof:name":"The P S Language Institute",
    "wof:placetype":"venue"
},
  "geometry": {"coordinates":[-117.87948900000001,33.632027],"type":"Point"}
}