{
  "type": "Feature",
  "properties": {
    "addr:full":"2534 Durant Ave Berkeley CA 94704",
    "addr:housenumber":"2534",
    "addr:postcode":"94704",
    "addr:street":"Durant Ave",
    "iso:country":"US",
    "sg:address":"2534 Durant Ave",
    "sg:city":"Berkeley",
    "sg:classifiers":[
        {
            "category":"Restaurant",
            "type":"Food & Drink"
        }
    ],
    "sg:phone":"+1 510 843 5967",
    "sg:postcode":"94704",
    "sg:province":"CA",
    "sg:tags":[
        "hot",
        "dog"
    ],
    "sg:website":"www.topdoghotdogs.com",
    "wof:name":"Top Dog",
    "wof:placetype":"venue"
},
  "geometry": {"coordinates":[-122.258222,37.867962],"type":"Point"}
}