{
  "type": "Feature",
  "properties": {
    "addr:full":"10254 Mull Ave Riverside CA 92503",
    "addr:housenumber":"10254",
    "addr:postcode":"92503",
    "addr:street":"Mull Ave",
    "iso:country":"US",
    "sg:address":"10254 Mull Ave",
    "sg:city":"Riverside",
    "sg:classifiers":[
        {
            "category":"Building & Trades",
            "subcategory":"Landscaping Services",
            "type":"Services"
        }
    ],
    "sg:phone":"+1 951 354 8911",
    "sg:postcode":"92503",
    "sg:province":"CA",
    "wof:name":"Cruz Landscape Services",
    "wof:placetype":"venue"
},
  "geometry": {"coordinates":[-117.471536,33.927467],"type":"Point"}
}