{
  "type": "Feature",
  "properties": {
    "addr:full":"8332 Regents Rd San Diego CA 92122",
    "addr:housenumber":"8332",
    "addr:postcode":"92122",
    "addr:street":"Regents Rd",
    "iso:country":"US",
    "sg:address":"8332 Regents Rd",
    "sg:city":"San Diego",
    "sg:classifiers":[
        {
            "category":"Freight",
            "type":"Transportation"
        }
    ],
    "sg:phone":"+1 619 688 1234",
    "sg:postcode":"92122",
    "sg:province":"CA",
    "wof:name":"Aventine Transportation",
    "wof:placetype":"venue"
},
  "geometry": {"coordinates":[-117.219239,32.867481],"type":"Point"}
}