{
  "type": "Feature",
  "properties": {
    "iso:country":"US",
    "sg:address":"1150 E Edna Pl",
    "sg:city":"Covina",
    "sg:classifiers":[
        {
            "category":"Manufacturing",
            "subcategory":"Metals",
            "type":"Manufacturing & Wholesale Goods"
        }
    ],
    "sg:phone":"+1 626 339 9091",
    "sg:postcode":"91724",
    "sg:province":"CA",
    "sg:tags":[
        "plating"
    ],
    "wof:name":"Stabile Plating Co",
    "wof:placetype":"venue"
},
  "geometry": {"coordinates":[-117.865137,34.095403],"type":"Point"}
}