{
  "type": "Feature",
  "properties": {
    "addr:full":"1263 Firestone Blvd Los Angeles CA 90001",
    "addr:housenumber":"1263",
    "addr:postcode":"90001",
    "addr:street":"Firestone Blvd",
    "iso:country":"US",
    "sg:address":"1263 Firestone Blvd",
    "sg:city":"Los Angeles",
    "sg:classifiers":[
        {
            "category":"Education",
            "subcategory":"School",
            "type":"Public Place"
        }
    ],
    "sg:phone":"+1 323 582 7247",
    "sg:postcode":"90001",
    "sg:province":"CA",
    "sg:tags":[
        "elementary"
    ],
    "sg:website":"www.lausd.k12.ca.us",
    "wof:name":"Russell Elementary School",
    "wof:placetype":"venue"
},
  "geometry": {"coordinates":[-118.251999,33.9603],"type":"Point"}
}