{
  "type": "Feature",
  "properties": {
    "iso:country":"US",
    "sg:address":"157 Main St",
    "sg:city":"Woodland",
    "sg:classifiers":[
        {
            "category":"Food & Beverages",
            "subcategory":"Groceries & Convenience Stores",
            "type":"Retail Goods"
        }
    ],
    "sg:phone":"+1 530 662 5479",
    "sg:postcode":"95695",
    "sg:province":"CA",
    "sg:tags":[
        "grocer"
    ],
    "wof:name":"Nugget Markets",
    "wof:placetype":"venue"
},
  "geometry": {"coordinates":[-121.780974,38.677603],"type":"Point"}
}