{
  "type": "Feature",
  "properties": {
    "iso:country":"US",
    "sg:address":"2804 Brittan Ave",
    "sg:city":"San Carlos",
    "sg:classifiers":[
        {
            "category":"Professional",
            "subcategory":"Engineering",
            "type":"Services"
        }
    ],
    "sg:phone":"+1 650 537 1198",
    "sg:postcode":"94070",
    "sg:province":"CA",
    "wof:name":"Don Cook Engineering Inc",
    "wof:placetype":"venue"
},
  "geometry": {"coordinates":[-122.2702,37.487971],"type":"Point"}
}