{
  "type": "Feature",
  "properties": {
    "addr:full":"1777 Metz Rd Soledad CA 93960",
    "addr:housenumber":"1777",
    "addr:postcode":"93960",
    "addr:street":"Metz Rd",
    "iso:country":"US",
    "sg:address":"1777 Metz Rd",
    "sg:city":"Soledad",
    "sg:classifiers":[
        {
            "category":"Manufacturing",
            "subcategory":"Food",
            "type":"Manufacturing & Wholesale Goods"
        }
    ],
    "sg:phone":"+1 831 678 3991",
    "sg:postcode":"93960",
    "sg:province":"CA",
    "sg:tags":[
        "vineyard",
        "grape",
        "winery",
        "mfg"
    ],
    "wof:name":"Golden State Vintners Inc",
    "wof:placetype":"venue"
},
  "geometry": {"coordinates":[-121.31087599999999,36.425872],"type":"Point"}
}