{
  "type": "Feature",
  "properties": {
    "addr:full":"2112 Main Street Julian CA 92036",
    "addr:housenumber":"2112",
    "addr:postcode":"92036",
    "addr:street":"Main Street",
    "iso:country":"US",
    "sg:address":"2112 Main Street",
    "sg:city":"Julian",
    "sg:classifiers":[
        {
            "category":"Coffee & Tea",
            "type":"Food & Drink"
        },
        {
            "category":"Restaurant",
            "type":"Food & Drink"
        },
        {
            "category":"Bakery",
            "type":"Food & Drink"
        }
    ],
    "sg:phone":"+1 760 765 2712",
    "sg:postcode":"92036",
    "sg:province":"CA",
    "sg:tags":[
        "espresso"
    ],
    "wof:name":"Julian Cafe",
    "wof:placetype":"venue"
},
  "geometry": {"coordinates":[-116.601602,33.078325],"type":"Point"}
}