{
  "type": "Feature",
  "properties": {
    "addr:full":"16501 Halsted St Sepulveda CA 91343",
    "addr:housenumber":"16501",
    "addr:postcode":"91343",
    "addr:street":"Halsted St",
    "iso:country":"US",
    "sg:address":"16501 Halsted St",
    "sg:city":"Sepulveda",
    "sg:classifiers":[
        {
            "category":"Arts & Performance",
            "subcategory":"Theater",
            "type":"Entertainment"
        }
    ],
    "sg:phone":"+1 818 894 3232",
    "sg:postcode":"91343",
    "sg:province":"CA",
    "sg:tags":[
        "bureau"
    ],
    "sg:website":"www.enloeproductions.com",
    "wof:name":"Enloe Productions",
    "wof:placetype":"venue"
},
  "geometry": {"coordinates":[-118.491749,34.244698],"type":"Point"}
}