{
  "type": "Feature",
  "properties": {
    "addr:full":"3853 Ingraham St San Diego CA 92109",
    "addr:housenumber":"3853",
    "addr:postcode":"92109",
    "addr:street":"Ingraham St",
    "iso:country":"US",
    "sg:address":"3853 Ingraham St",
    "sg:city":"San Diego",
    "sg:classifiers":[
        {
            "category":"Professional",
            "subcategory":"Management & Consulting",
            "type":"Services"
        }
    ],
    "sg:phone":"+1 858 272 8876",
    "sg:postcode":"92109",
    "sg:province":"CA",
    "wof:name":"M Moda Marketing Inc",
    "wof:placetype":"venue"
},
  "geometry": {"coordinates":[-117.23825600000001,32.791413],"type":"Point"}
}