{
  "type": "Feature",
  "properties": {
    "iso:country":"US",
    "sg:address":"3853 Ingraham St",
    "sg:city":"San Diego",
    "sg:classifiers":[
        {
            "category":"Professional",
            "subcategory":"Management & Consulting",
            "type":"Services"
        }
    ],
    "sg:phone":"+1 858 272 8876",
    "sg:postcode":"92109",
    "sg:province":"CA",
    "wof:name":"M Moda Marketing Inc",
    "wof:placetype":"venue"
},
  "geometry": {"coordinates":[-117.238256,32.791413],"type":"Point"}
}