{
  "type": "Feature",
  "properties": {
    "addr:full":"17 Woodford Dr Moraga CA 94556",
    "addr:housenumber":"17",
    "addr:postcode":"94556",
    "addr:street":"Woodford Dr",
    "iso:country":"US",
    "sg:address":"17 Woodford Dr",
    "sg:city":"Moraga",
    "sg:classifiers":[
        {
            "category":"Real Estate",
            "subcategory":"Real Estate Services",
            "type":"Services"
        },
        {
            "category":"Real Estate",
            "subcategory":"Real Estate Agent",
            "type":"Services"
        }
    ],
    "sg:phone":"+1 925 376 1015",
    "sg:postcode":"94556",
    "sg:province":"CA",
    "sg:tags":[
        "buyer",
        "broker"
    ],
    "wof:name":"Gerold Real Estate",
    "wof:placetype":"venue"
},
  "geometry": {"coordinates":[-122.122528,37.86594],"type":"Point"}
}