{
  "type": "Feature",
  "properties": {
    "addr:full":"4313 Valley Fair St Simi Valley CA 93063",
    "addr:housenumber":"4313",
    "addr:postcode":"93063",
    "addr:street":"Valley Fair St",
    "iso:country":"US",
    "sg:address":"4313 Valley Fair St",
    "sg:city":"Simi Valley",
    "sg:classifiers":[
        {
            "category":"Communications",
            "subcategory":"Film & Video Production",
            "type":"Services"
        }
    ],
    "sg:phone":"+1 805 526 7101",
    "sg:postcode":"93063",
    "sg:province":"CA",
    "sg:tags":[
        "audio"
    ],
    "wof:name":"August Again Productions",
    "wof:placetype":"venue"
},
  "geometry": {"coordinates":[-118.709159,34.272634],"type":"Point"}
}