{
  "type": "Feature",
  "properties": {
    "iso:country":"US",
    "sg:address":"8508 Saint Helena Rd",
    "sg:city":"Santa Rosa",
    "sg:classifiers":[
        {
            "category":"Building & Trades",
            "subcategory":"Landscaping Services",
            "type":"Services"
        }
    ],
    "sg:phone":"+1 707 928 5470",
    "sg:postcode":"95404",
    "sg:province":"CA",
    "sg:tags":[
        "horticultural",
        "consultant"
    ],
    "wof:name":"Gro-Rose-Bru",
    "wof:placetype":"venue"
},
  "geometry": {"coordinates":[-122.596293,38.519619],"type":"Point"}
}