{
  "type": "Feature",
  "properties": {
    "addr:full":"37 E del Mar Blvd Pasadena CA 91105",
    "addr:housenumber":"37",
    "addr:postcode":"91105",
    "addr:street":"E Del Mar Blvd",
    "iso:country":"US",
    "sg:address":"37 E del Mar Blvd",
    "sg:city":"Pasadena",
    "sg:phone":"+1 626 792 3148",
    "sg:postcode":"91105",
    "sg:province":"CA",
    "sg:website":"http://www.elcentropasadena.org",
    "wof:name":"El Centro De Acci?n Social",
    "wof:placetype":"venue"
},
  "geometry": {"coordinates":[-118.149828,34.140576],"type":"Point"}
}