{
  "type": "Feature",
  "properties": {
    "iso:country":"US",
    "sg:address":"251 W Compton Blvd",
    "sg:city":"Compton",
    "sg:classifiers":[
        {
            "category":"Banks & Credit Unions",
            "subcategory":"Financial Services",
            "type":"Services"
        }
    ],
    "sg:phone":"+1 310 638 1288",
    "sg:postcode":"90220",
    "sg:province":"CA",
    "sg:website":"www.offthechainbailagency.com",
    "wof:name":"Off The Chain Bail Bonds",
    "wof:placetype":"venue"
},
  "geometry": {"coordinates":[-118.226083,33.895995],"type":"Point"}
}