{
  "type": "Feature",
  "properties": {
    "iso:country":"US",
    "sg:address":"11404 Cardiff Ln",
    "sg:city":"Loma Linda",
    "sg:classifiers":[
        {
            "category":"Social Services",
            "subcategory":"Adult Care",
            "type":"Services"
        }
    ],
    "sg:phone":"+1 909 799 3561",
    "sg:postcode":"92354",
    "sg:province":"CA",
    "sg:tags":[
        "home"
    ],
    "wof:name":"Peace Of Mind Adult Rsdntl",
    "wof:placetype":"venue"
},
  "geometry": {"coordinates":[-117.232707,34.046649],"type":"Point"}
}