{
  "type": "Feature",
  "properties": {
    "iso:country":"US",
    "sg:address":"5741 W Adams Blvd",
    "sg:city":"Los Angeles",
    "sg:classifiers":[
        {
            "category":"Building & Trades",
            "subcategory":"Construction",
            "type":"Services"
        }
    ],
    "sg:phone":"+1 323 930 1311",
    "sg:postcode":"90016",
    "sg:province":"CA",
    "sg:tags":[
        "roofing",
        "contractor"
    ],
    "wof:name":"Culver City Roofing Co",
    "wof:placetype":"venue"
},
  "geometry": {"coordinates":[-118.368673,34.032525],"type":"Point"}
}