{
  "type": "Feature",
  "properties": {
    "iso:country":"US",
    "sg:address":"18224 Prairie Ave",
    "sg:city":"Torrance",
    "sg:classifiers":[
        {
            "category":"Personal",
            "subcategory":"Beauty Salon",
            "type":"Services"
        }
    ],
    "sg:phone":"+1 310 329 8078",
    "sg:postcode":"90504",
    "sg:province":"CA",
    "sg:tags":[
        "nail",
        "manicuring"
    ],
    "wof:name":"2000 Nails",
    "wof:placetype":"venue"
},
  "geometry": {"coordinates":[-118.344002,33.865002],"type":"Point"}
}