{
  "type": "Feature",
  "properties": {
    "iso:country":"US",
    "sg:address":"320 Pine Ave",
    "sg:city":"Long Beach",
    "sg:classifiers":[
        {
            "category":"Freight",
            "type":"Transportation"
        }
    ],
    "sg:phone":"+1 562 590 6255",
    "sg:postcode":"90813",
    "sg:province":"CA",
    "sg:tags":[
        "operator",
        "trucking"
    ],
    "wof:name":"Allied Appraisals",
    "wof:placetype":"venue"
},
  "geometry": {"coordinates":[-118.192306,33.770552],"type":"Point"}
}