{
  "type": "Feature",
  "properties": {
    "addr:full":"8120 Timberlake Way Sacramento CA 95823",
    "addr:housenumber":"8120",
    "addr:postcode":"95823",
    "addr:street":"Timberlake Way",
    "iso:country":"US",
    "sg:address":"8120 Timberlake Way",
    "sg:city":"Sacramento",
    "sg:classifiers":[
        {
            "category":"Health Services",
            "subcategory":"Optometrist",
            "type":"Services"
        }
    ],
    "sg:phone":"+1 916 423 2134",
    "sg:postcode":"95823",
    "sg:province":"CA",
    "wof:name":"Wang Michael Od",
    "wof:placetype":"venue"
},
  "geometry": {"coordinates":[-121.41376,38.462774],"type":"Point"}
}