{
  "type": "Feature",
  "properties": {
    "iso:country":"US",
    "sg:address":"1345 E Thousand Oaks Blvd",
    "sg:city":"Thousand Oaks",
    "sg:classifiers":[
        {
            "category":"Restaurant",
            "type":"Food & Drink"
        }
    ],
    "sg:phone":"+1 805 379 6767",
    "sg:postcode":"91362",
    "sg:province":"CA",
    "wof:name":"Roxy's Famous Deli",
    "wof:placetype":"venue"
},
  "geometry": {"coordinates":[-118.855626,34.178172],"type":"Point"}
}