{
  "type": "Feature",
  "properties": {
    "addr:full":"13841 Tustin East Dr # 206 Tustin CA 92780",
    "addr:housenumber":"13841",
    "addr:postcode":"92780",
    "addr:street":"Tustin East Dr # 206",
    "iso:country":"US",
    "sg:address":"13841 Tustin East Dr # 206",
    "sg:city":"Tustin",
    "sg:classifiers":[
        {
            "category":"Place Of Worship",
            "type":"Public Place"
        }
    ],
    "sg:phone":"+1 714 914 3172",
    "sg:postcode":"92780",
    "sg:province":"CA",
    "sg:tags":[
        "church"
    ],
    "wof:name":"Shri Enterprises",
    "wof:placetype":"venue"
},
  "geometry": {"coordinates":[-117.81144500000001,33.733216],"type":"Point"}
}