{
  "type": "Feature",
  "properties": {
    "addr:full":"246 Inverness Pl Glendora CA 91741",
    "addr:housenumber":"246",
    "addr:postcode":"91741",
    "addr:street":"Inverness Pl",
    "iso:country":"US",
    "sg:address":"246 Inverness Pl",
    "sg:city":"Glendora",
    "sg:classifiers":[
        {
            "category":"Professional",
            "type":"Services"
        }
    ],
    "sg:phone":"+1 626 963 5484",
    "sg:postcode":"91741",
    "sg:province":"CA",
    "wof:name":"Childers Family Ltd Partnr",
    "wof:placetype":"venue"
},
  "geometry": {"coordinates":[-117.82325,34.13379],"type":"Point"}
}