{
  "type": "Feature",
  "properties": {
    "iso:country":"US",
    "sg:address":"17842 Irvine Blvd",
    "sg:city":"Tustin",
    "sg:classifiers":[
        {
            "category":"Retail",
            "subcategory":"Portrait Studio",
            "type":"Services"
        }
    ],
    "sg:phone":"+1 714 730 8200",
    "sg:postcode":"92780",
    "sg:province":"CA",
    "sg:tags":[
        "photographer"
    ],
    "wof:name":"Anmaria Brandt Photography",
    "wof:placetype":"venue"
},
  "geometry": {"coordinates":[-117.82034,33.748368],"type":"Point"}
}