{
  "type": "Feature",
  "properties": {
    "iso:country":"US",
    "sg:address":"1926 Modoc St",
    "sg:city":"Madera",
    "sg:classifiers":[
        {
            "category":"Retail",
            "subcategory":"Auto Repair",
            "type":"Services"
        }
    ],
    "sg:phone":"+1 559 662 1801",
    "sg:postcode":"93637",
    "sg:province":"CA",
    "sg:tags":[
        "exchanging",
        "engine"
    ],
    "wof:name":"Advanced Engines",
    "wof:placetype":"venue"
},
  "geometry": {"coordinates":[-120.081121,36.951547],"type":"Point"}
}