{
  "type": "Feature",
  "properties": {
    "iso:country":"US",
    "sg:address":"210 S B Street",
    "sg:city":"San Mateo",
    "sg:classifiers":[
        {
            "category":"Professional",
            "subcategory":"Computer Services",
            "type":"Services"
        }
    ],
    "sg:phone":"+1 650 340 8696",
    "sg:postcode":"94401",
    "sg:province":"CA",
    "sg:website":"http://www.smalltown.com",
    "wof:name":"Smalltown",
    "wof:placetype":"venue"
},
  "geometry": {"coordinates":[-122.32253,37.565536],"type":"Point"}
}