{
  "type": "Feature",
  "properties": {
    "addr:full":"1041 W 18th St Costa Mesa CA 92627",
    "addr:housenumber":"1041",
    "addr:postcode":"92627",
    "addr:street":"W 18Th St",
    "iso:country":"US",
    "sg:address":"1041 W 18th St",
    "sg:city":"Costa Mesa",
    "sg:classifiers":[
        {
            "category":"Professional",
            "subcategory":"Management & Consulting",
            "type":"Services"
        }
    ],
    "sg:phone":"+1 949 631 7056",
    "sg:postcode":"92627",
    "sg:province":"CA",
    "sg:tags":[
        "consultant",
        "business"
    ],
    "wof:name":"Rocky Mountain Energy Exchange",
    "wof:placetype":"venue"
},
  "geometry": {"coordinates":[-117.942142,33.639579],"type":"Point"}
}