{
  "type": "Feature",
  "properties": {
    "iso:country":"US",
    "sg:address":"1357 Century Ave",
    "sg:city":"Riverside",
    "sg:classifiers":[
        {
            "category":"Professional",
            "type":"Services"
        }
    ],
    "sg:phone":"+1 951 789 8879",
    "sg:postcode":"92506",
    "sg:province":"CA",
    "wof:name":"Max Chao",
    "wof:placetype":"venue"
},
  "geometry": {"coordinates":[-117.343953,33.935854],"type":"Point"}
}