{
  "type": "Feature",
  "properties": {
    "addr:full":"3768 W 242nd St Torrance CA 90505",
    "addr:housenumber":"3768",
    "addr:postcode":"90505",
    "addr:street":"W 242Nd St",
    "iso:country":"US",
    "sg:address":"3768 W 242nd St",
    "sg:city":"Torrance",
    "sg:classifiers":[
        {
            "category":"Restaurant",
            "type":"Food & Drink"
        }
    ],
    "sg:phone":"+1 310 375 1600",
    "sg:postcode":"90505",
    "sg:province":"CA",
    "sg:tags":[
        "middle",
        "eastern",
        "mediterranean",
        "greek"
    ],
    "sg:website":"aristocafe.com/",
    "wof:name":"Aristo Cafe",
    "wof:placetype":"venue"
},
  "geometry": {"coordinates":[-118.351997,33.804298],"type":"Point"}
}