{
  "type": "Feature",
  "properties": {
    "addr:full":"639 W Ave J Lancaster CA 93534",
    "addr:housenumber":"639",
    "addr:postcode":"93534",
    "addr:street":"W Ave J",
    "iso:country":"US",
    "sg:address":"639 W Ave J",
    "sg:city":"Lancaster",
    "sg:classifiers":[
        {
            "category":"Shopping",
            "type":"Retail Goods"
        }
    ],
    "sg:phone":"+1 661 949 7677",
    "sg:postcode":"93534",
    "sg:province":"CA",
    "sg:tags":[
        "stamp",
        "collector",
        "for"
    ],
    "wof:name":"Stamps For The Collector",
    "wof:placetype":"venue"
},
  "geometry": {"coordinates":[-118.139404,34.689389],"type":"Point"}
}