{
  "type": "Feature",
  "properties": {
    "iso:country":"US",
    "sg:address":"5143 Barry St",
    "sg:city":"Oceanside",
    "sg:classifiers":[
        {
            "category":"Travel",
            "subcategory":"Travel Agent",
            "type":"Entertainment"
        }
    ],
    "sg:phone":"+1 760 433 0855",
    "sg:postcode":"92057",
    "sg:province":"CA",
    "sg:tags":[
        "agency"
    ],
    "wof:name":"Sunshine Tours & Travel",
    "wof:placetype":"venue"
},
  "geometry": {"coordinates":[-117.291619,33.258526],"type":"Point"}
}