{
  "type": "Feature",
  "properties": {
    "iso:country":"US",
    "sg:address":"5077 Bullion St",
    "sg:city":"Mariposa",
    "sg:classifiers":[
        {
            "category":"Professional",
            "subcategory":"Engineering",
            "type":"Services"
        }
    ],
    "sg:phone":"+1 209 966 3801",
    "sg:postcode":"95338",
    "sg:province":"CA",
    "sg:tags":[
        "engineer"
    ],
    "wof:name":"Roger Stephens Engineering",
    "wof:placetype":"venue"
},
  "geometry": {"coordinates":[-119.965193,37.486112],"type":"Point"}
}