{
  "type": "Feature",
  "properties": {
    "iso:country":"US",
    "sg:address":"3336 Grand Ave",
    "sg:city":"Oakland",
    "sg:classifiers":[
        {
            "category":"Restaurant",
            "type":"Food & Drink"
        }
    ],
    "sg:phone":"+1 510 419 0601",
    "sg:postcode":"94610",
    "sg:province":"CA",
    "sg:tags":[
        "sushi",
        "bar"
    ],
    "wof:name":"Samurai Sushi Boat",
    "wof:placetype":"venue"
},
  "geometry": {"coordinates":[-122.24646300000001,37.813211],"type":"Point"}
}