{
  "type": "Feature",
  "properties": {
    "addr:full":"11756 Valley Blvd El Monte CA 91731",
    "addr:housenumber":"11756",
    "addr:postcode":"91731",
    "addr:street":"Valley Blvd",
    "iso:country":"US",
    "sg:address":"11756 Valley Blvd",
    "sg:city":"El Monte",
    "sg:classifiers":[
        {
            "category":"Insurance",
            "subcategory":"Hazard Insurance",
            "type":"Services"
        }
    ],
    "sg:phone":"+1 888 826 1904",
    "sg:postcode":"91731",
    "sg:province":"CA",
    "wof:name":"Capitol West Insurance",
    "wof:placetype":"venue"
},
  "geometry": {"coordinates":[-118.042984,34.07631],"type":"Point"}
}