{
  "type": "Feature",
  "properties": {
    "addr:full":"4626 W Caldwell Ave Visalia CA 93277",
    "addr:housenumber":"4626",
    "addr:postcode":"93277",
    "addr:street":"W Caldwell Ave",
    "iso:country":"US",
    "sg:address":"4626 W Caldwell Ave",
    "sg:city":"Visalia",
    "sg:classifiers":[
        {
            "category":"Real Estate",
            "subcategory":"Real Estate Services",
            "type":"Services"
        },
        {
            "category":"Real Estate",
            "subcategory":"Real Estate Operator",
            "type":"Services"
        }
    ],
    "sg:phone":"+1 559 733 3213",
    "sg:postcode":"93277",
    "sg:province":"CA",
    "sg:tags":[
        "vacancy",
        "apartment",
        "rental",
        "listing"
    ],
    "sg:website":"http://www.pacificviewcompanies.com",
    "wof:name":"Oak View Apartments",
    "wof:placetype":"venue"
},
  "geometry": {"coordinates":[-119.340929,36.298258],"type":"Point"}
}