{
  "type": "Feature",
  "properties": {
    "addr:full":"517 Silver Oak Ln Danville CA 94506",
    "addr:housenumber":"517",
    "addr:postcode":"94506",
    "addr:street":"Silver Oak Ln",
    "iso:country":"US",
    "sg:address":"517 Silver Oak Ln",
    "sg:city":"Danville",
    "sg:classifiers":[
        {
            "category":"Professional",
            "type":"Services"
        }
    ],
    "sg:phone":"+1 925 964 9393",
    "sg:postcode":"94506",
    "sg:province":"CA",
    "sg:tags":[
        "establishment"
    ],
    "wof:name":"Pro Systems",
    "wof:placetype":"venue"
},
  "geometry": {"coordinates":[-121.922877,37.801346],"type":"Point"}
}