{
  "type": "Feature",
  "properties": {
    "addr:full":"1582 Radar Rd San Diego CA 92154",
    "addr:housenumber":"1582",
    "addr:postcode":"92154",
    "addr:street":"Radar Rd",
    "iso:country":"US",
    "sg:address":"1582 Radar Rd",
    "sg:city":"San Diego",
    "sg:classifiers":[
        {
            "category":"Freight",
            "type":"Transportation"
        }
    ],
    "sg:phone":"+1 619 661 5411",
    "sg:postcode":"92154",
    "sg:province":"CA",
    "sg:tags":[
        "operator",
        "trucking"
    ],
    "wof:name":"Van Richards & Storage Inc",
    "wof:placetype":"venue"
},
  "geometry": {"coordinates":[-116.960165,32.569431],"type":"Point"}
}