{
  "type": "Feature",
  "properties": {
    "addr:full":"1705 O St Sanger CA 93657",
    "addr:housenumber":"1705",
    "addr:postcode":"ca 93657",
    "addr:street":"O St",
    "iso:country":"US",
    "sg:address":"1705 O St",
    "sg:city":"Sanger",
    "sg:classifiers":[
        {
            "category":"Personal",
            "subcategory":"Beauty Salon",
            "type":"Services"
        }
    ],
    "sg:phone":"+1 559 875 6518",
    "sg:postcode":"93657",
    "sg:province":"CA",
    "wof:name":"Gloria's Perms & Cuts",
    "wof:placetype":"venue"
},
  "geometry": {"coordinates":[-119.556757,36.693283],"type":"Point"}
}