{
  "type": "Feature",
  "properties": {
    "addr:full":"605 Valley Blvd Big Bear City CA 92314",
    "addr:housenumber":"605",
    "addr:postcode":"92314",
    "addr:street":"Valley Blvd",
    "iso:country":"US",
    "sg:address":"605 Valley Blvd",
    "sg:city":"Big Bear City",
    "sg:classifiers":[
        {
            "category":"Wholesale",
            "subcategory":"Electrical",
            "type":"Manufacturing & Wholesale Goods"
        }
    ],
    "sg:phone":"+1 909 584 8208",
    "sg:postcode":"92314",
    "sg:province":"CA",
    "sg:tags":[
        "cutting",
        "laser"
    ],
    "wof:name":"Howard Sign House",
    "wof:placetype":"venue"
},
  "geometry": {"coordinates":[-116.85524100000001,34.261183],"type":"Point"}
}