{
  "type": "Feature",
  "properties": {
    "addr:full":"2220 Revere Avenue San Francisco CA 94124",
    "addr:housenumber":"2220",
    "addr:postcode":"94124",
    "addr:street":"Revere Avenue",
    "iso:country":"US",
    "sg:address":"2220 Revere Avenue",
    "sg:city":"San Francisco",
    "sg:classifiers":[
        {
            "category":"Retail",
            "subcategory":"Auto Repair",
            "type":"Services"
        }
    ],
    "sg:phone":"+1 415 647 2118",
    "sg:postcode":"94124",
    "sg:province":"CA",
    "wof:name":"Winson Auto",
    "wof:placetype":"venue"
},
  "geometry": {"coordinates":[-122.402,37.738201],"type":"Point"}
}