{
  "type": "Feature",
  "properties": {
    "addr:full":"26751 Portola Parkway Foothill Ranch CA 92610",
    "addr:housenumber":"26751",
    "addr:postcode":"92610",
    "addr:street":"Portola Parkway",
    "iso:country":"US",
    "sg:address":"26751 Portola Parkway",
    "sg:city":"Foothill Ranch",
    "sg:classifiers":[
        {
            "category":"Food & Beverages",
            "subcategory":"Groceries & Convenience Stores",
            "type":"Retail Goods"
        }
    ],
    "sg:phone":"+1 949 457 9349",
    "sg:postcode":"92610",
    "sg:province":"CA",
    "wof:name":"Ralphs Grocery Company",
    "wof:placetype":"venue"
},
  "geometry": {"coordinates":[-117.663489,33.679272],"type":"Point"}
}