{
  "type": "Feature",
  "properties": {
    "iso:country":"US",
    "sg:address":"224 W Main St",
    "sg:city":"Santa Maria",
    "sg:classifiers":[
        {
            "category":"Professional",
            "subcategory":"Employment Agencies",
            "type":"Services"
        }
    ],
    "sg:phone":"+1 805 346 6083",
    "sg:postcode":"93458",
    "sg:province":"CA",
    "sg:tags":[
        "help",
        "contractor"
    ],
    "wof:name":"Labor Finders",
    "wof:placetype":"venue"
},
  "geometry": {"coordinates":[-120.437684,34.953009],"type":"Point"}
}