{
  "type": "Feature",
  "properties": {
    "iso:country":"US",
    "sg:address":"2039 10th Ave",
    "sg:city":"San Francisco",
    "sg:classifiers":[
        {
            "category":"Shopping",
            "subcategory":"Computers & Home Electronics",
            "type":"Retail Goods"
        }
    ],
    "sg:phone":"+1 415 596 8010",
    "sg:postcode":"94116",
    "sg:province":"CA",
    "wof:name":"Dynamix Car Audio & More",
    "wof:placetype":"venue"
},
  "geometry": {"coordinates":[-122.466452,37.749793],"type":"Point"}
}