{
  "type": "Feature",
  "properties": {
    "addr:full":"6860 Lexington Ave Los Angeles CA 90038",
    "addr:housenumber":"6860",
    "addr:postcode":"90038",
    "addr:street":"Lexington Ave",
    "iso:country":"US",
    "sg:address":"6860 Lexington Ave",
    "sg:city":"Los Angeles",
    "sg:classifiers":[
        {
            "category":"Professional",
            "subcategory":"Business Services",
            "type":"Services"
        }
    ],
    "sg:phone":"+1 323 790 1700",
    "sg:postcode":"90038",
    "sg:province":"CA",
    "sg:tags":[
        "fund",
        "promotion",
        "raising"
    ],
    "wof:name":"Blink",
    "wof:placetype":"venue"
},
  "geometry": {"coordinates":[-118.340334,34.092498],"type":"Point"}
}