{
  "type": "Feature",
  "properties": {
    "iso:country":"US",
    "sg:address":"24405 Amador St",
    "sg:city":"Hayward",
    "sg:classifiers":[
        {
            "category":"Professional",
            "subcategory":"Lawyer & Legal Services",
            "type":"Services"
        }
    ],
    "sg:phone":"+1 510 670 5100",
    "sg:postcode":"94544",
    "sg:province":"CA",
    "wof:name":"District Attorney",
    "wof:placetype":"venue"
},
  "geometry": {"coordinates":[-122.09442799999999,37.658291],"type":"Point"}
}