{
  "type": "Feature",
  "properties": {
    "iso:country":"US",
    "sg:address":"4856 Santa Monica Ave",
    "sg:city":"San Diego",
    "sg:classifiers":[
        {
            "category":"Health Services",
            "subcategory":"Chiropractor",
            "type":"Services"
        }
    ],
    "sg:phone":"+1 619 224 2041",
    "sg:postcode":"92107",
    "sg:province":"CA",
    "wof:name":"Jon B Ambert DC",
    "wof:placetype":"venue"
},
  "geometry": {"coordinates":[-117.247663,32.746086],"type":"Point"}
}