{
  "type": "Feature",
  "properties": {
    "addr:full":"445 W Garfield Ave Glendale CA 91204",
    "addr:housenumber":"445",
    "addr:postcode":"91204",
    "addr:street":"W Garfield Ave",
    "iso:country":"US",
    "sg:address":"445 W Garfield Ave",
    "sg:city":"Glendale",
    "sg:classifiers":[
        {
            "category":"Building & Trades",
            "subcategory":"Construction",
            "type":"Services"
        }
    ],
    "sg:phone":"+1 818 500 0067",
    "sg:postcode":"91204",
    "sg:province":"CA",
    "sg:tags":[
        "material",
        "contractor"
    ],
    "wof:name":"Screenmobile The",
    "wof:placetype":"venue"
},
  "geometry": {"coordinates":[-118.262434,34.135412],"type":"Point"}
}