{
  "type": "Feature",
  "properties": {
    "addr:full":"235 Hill St Santa Monica CA 90405",
    "addr:housenumber":"235",
    "addr:postcode":"90405",
    "addr:street":"Hill St",
    "iso:country":"US",
    "sg:address":"235 Hill St",
    "sg:city":"Santa Monica",
    "sg:classifiers":[
        {
            "category":"Organizations",
            "subcategory":"Non-profit Organization",
            "type":"Services"
        }
    ],
    "sg:phone":"+1 310 392 9700",
    "sg:postcode":"90405",
    "sg:province":"CA",
    "sg:tags":[
        "action",
        "agency",
        "community"
    ],
    "wof:name":"Parents Organized For Westside",
    "wof:placetype":"venue"
},
  "geometry": {"coordinates":[-118.48169,34.001601],"type":"Point"}
}