{
  "type": "Feature",
  "properties": {
    "iso:country":"US",
    "sg:address":"315 E 75th St",
    "sg:city":"Los Angeles",
    "sg:classifiers":[
        {
            "category":"Professional",
            "type":"Services"
        }
    ],
    "sg:phone":"+1 323 750 1081",
    "sg:postcode":"90003",
    "sg:province":"CA",
    "wof:name":"Johnson Ruteleious",
    "wof:placetype":"venue"
},
  "geometry": {"coordinates":[-118.2676,33.972237],"type":"Point"}
}