{
  "type": "Feature",
  "properties": {
    "addr:full":"2333 Courage Dr Fairfield CA 94533",
    "addr:housenumber":"2333",
    "addr:postcode":"94533",
    "addr:street":"Courage Dr",
    "iso:country":"US",
    "sg:address":"2333 Courage Dr",
    "sg:city":"Fairfield",
    "sg:classifiers":[
        {
            "category":"Government",
            "subcategory":"Jail",
            "type":"Public Place"
        }
    ],
    "sg:phone":"+1 707 428 2016",
    "sg:postcode":"94533",
    "sg:province":"CA",
    "sg:tags":[
        "correctional",
        "institution"
    ],
    "wof:name":"Fairfield Parole Sub-Unit",
    "wof:placetype":"venue"
},
  "geometry": {"coordinates":[-122.07623,38.23456],"type":"Point"}
}