{
  "type": "Feature",
  "properties": {
    "iso:country":"US",
    "sg:address":"1695 Curtiss Ct",
    "sg:city":"La Verne",
    "sg:classifiers":[
        {
            "category":"Health Services",
            "subcategory":"Doctor",
            "type":"Services"
        }
    ],
    "sg:phone":"+1 909 392 0882",
    "sg:postcode":"91750",
    "sg:province":"CA",
    "sg:tags":[
        "physician",
        "surgeon"
    ],
    "sg:website":"www.zimmer.com",
    "wof:name":"Intermed Orthopedics Inc",
    "wof:placetype":"venue"
},
  "geometry": {"coordinates":[-117.779963,34.09617],"type":"Point"}
}