{
  "type": "Feature",
  "properties": {
    "iso:country":"US",
    "sg:address":"30110 Crown Valley Pkwy",
    "sg:city":"Laguna Niguel",
    "sg:classifiers":[
        {
            "category":"Building & Trades",
            "subcategory":"Cleaning & Sanitation",
            "type":"Services"
        }
    ],
    "sg:phone":"+1 949 632 1691",
    "sg:postcode":"92677",
    "sg:province":"CA",
    "sg:tags":[
        "janitor"
    ],
    "wof:name":"ACS Building Maintance",
    "wof:placetype":"venue"
},
  "geometry": {"coordinates":[-117.714488,33.523902],"type":"Point"}
}