{
  "type": "Feature",
  "properties": {
    "iso:country":"US",
    "sg:address":"451 Lewis St",
    "sg:city":"Gilroy",
    "sg:classifiers":[
        {
            "category":"Social Services",
            "type":"Services"
        }
    ],
    "sg:phone":"+1 408 847 2425",
    "sg:postcode":"95020",
    "sg:province":"CA",
    "sg:tags":[
        "youth",
        "organization",
        "center"
    ],
    "wof:name":"Macsa All Capital",
    "wof:placetype":"venue"
},
  "geometry": {"coordinates":[-121.56436,37.011308],"type":"Point"}
}