{
  "type": "Feature",
  "properties": {
    "addr:full":"1641 E Slauson Ave Los Angeles CA 90011",
    "addr:housenumber":"1641",
    "addr:postcode":"90011",
    "addr:street":"E Slauson Ave",
    "iso:country":"US",
    "sg:address":"1641 E Slauson Ave",
    "sg:city":"Los Angeles",
    "sg:classifiers":[
        {
            "category":"Building & Trades",
            "subcategory":"Construction",
            "type":"Services"
        }
    ],
    "sg:phone":"+1 323 589 7782",
    "sg:postcode":"90011",
    "sg:province":"CA",
    "sg:tags":[
        "contractor"
    ],
    "wof:name":"Century Welding & Ironwork",
    "wof:placetype":"venue"
},
  "geometry": {"coordinates":[-118.24409300000001,33.989363],"type":"Point"}
}