{
  "type": "Feature",
  "properties": {
    "iso:country":"US",
    "sg:address":"2730 Bryant St",
    "sg:city":"San Francisco",
    "sg:classifiers":[
        {
            "category":"Government",
            "subcategory":"Office",
            "type":"Public Place"
        }
    ],
    "sg:phone":"+1 415 920 7192",
    "sg:postcode":"94110",
    "sg:province":"CA",
    "sg:tags":[
        "city",
        "program",
        "health"
    ],
    "wof:name":"San Francisco Health Clinic",
    "wof:placetype":"venue"
},
  "geometry": {"coordinates":[-122.408937,37.750085],"type":"Point"}
}