{
  "type": "Feature",
  "properties": {
    "iso:country":"US",
    "sg:address":"3281 College Pl",
    "sg:city":"Lemon Grove",
    "sg:classifiers":[
        {
            "category":"Shopping",
            "subcategory":"Gifts & Souvenirs",
            "type":"Retail Goods"
        }
    ],
    "sg:phone":"+1 619 461 0181",
    "sg:postcode":"91945",
    "sg:province":"CA",
    "sg:tags":[
        "shop",
        "novelty"
    ],
    "wof:name":"JMh Gifts N More",
    "wof:placetype":"venue"
},
  "geometry": {"coordinates":[-117.048743,32.740465],"type":"Point"}
}