{
  "type": "Feature",
  "properties": {
    "iso:country":"US",
    "sg:address":"3998 Vista Way",
    "sg:city":"Oceanside",
    "sg:classifiers":[
        {
            "category":"Health Services",
            "subcategory":"Doctor",
            "type":"Services"
        }
    ],
    "sg:phone":"+1 760 758 5340",
    "sg:postcode":"92056",
    "sg:province":"CA",
    "sg:tags":[
        "dermatologist"
    ],
    "wof:name":"Leshaw Steven M MD-Dermtlgst",
    "wof:placetype":"venue"
},
  "geometry": {"coordinates":[-117.290001,33.183899],"type":"Point"}
}