{
  "type": "Feature",
  "properties": {
    "iso:country":"US",
    "sg:address":"3885 N Madera Ave",
    "sg:city":"Kerman",
    "sg:classifiers":[
        {
            "category":"Home & Garden",
            "subcategory":"Garden Supply",
            "type":"Retail Goods"
        }
    ],
    "sg:phone":"+1 559 846 9306",
    "sg:postcode":"93630",
    "sg:province":"CA",
    "sg:tags":[
        "fertilizer"
    ],
    "wof:name":"Rasco Inc",
    "wof:placetype":"venue"
},
  "geometry": {"coordinates":[-120.060425,36.792384],"type":"Point"}
}