{
  "type": "Feature",
  "properties": {
    "addr:full":"1446 4th St San Rafael CA 94901",
    "addr:housenumber":"1446",
    "addr:postcode":"94901",
    "addr:street":"4Th St",
    "iso:country":"US",
    "sg:address":"1446 4th St",
    "sg:city":"San Rafael",
    "sg:classifiers":[
        {
            "category":"Manufacturing",
            "subcategory":"Musical Instruments",
            "type":"Manufacturing & Wholesale Goods"
        }
    ],
    "sg:phone":"+1 415 459 2525",
    "sg:postcode":"94901",
    "sg:province":"CA",
    "sg:tags":[
        "mfg"
    ],
    "wof:name":"Eguitars",
    "wof:placetype":"venue"
},
  "geometry": {"coordinates":[-122.532737,37.973665],"type":"Point"}
}