{
  "type": "Feature",
  "properties": {
    "addr:full":"909 N Estates Dr Brentwood CA 94513",
    "addr:housenumber":"909",
    "addr:postcode":"ca 94513",
    "addr:street":"N Estates Dr",
    "iso:country":"US",
    "sg:address":"909 N Estates Dr",
    "sg:city":"Brentwood",
    "sg:classifiers":[
        {
            "category":"Building & Trades",
            "subcategory":"Electrical",
            "type":"Services"
        }
    ],
    "sg:phone":"+1 925 634 8401",
    "sg:postcode":"94513",
    "sg:province":"CA",
    "sg:tags":[
        "installation"
    ],
    "wof:name":"A Plus Water Heaters",
    "wof:placetype":"venue"
},
  "geometry": {"coordinates":[-121.708141,37.934656],"type":"Point"}
}