{
  "type": "Feature",
  "properties": {
    "addr:full":"501 Beaumont Ave Beaumont CA 92223",
    "addr:housenumber":"501",
    "addr:postcode":"92223",
    "addr:street":"Beaumont Ave",
    "iso:country":"US",
    "sg:address":"501 Beaumont Ave",
    "sg:city":"Beaumont",
    "sg:classifiers":[
        {
            "category":"Restaurant",
            "type":"Food & Drink"
        }
    ],
    "sg:phone":"+1 951 769 3949",
    "sg:postcode":"92223",
    "sg:province":"CA",
    "sg:website":"www.mcdonalds.com",
    "wof:name":"McDonald's",
    "wof:placetype":"venue"
},
  "geometry": {"coordinates":[-116.976997,33.928398],"type":"Point"}
}