{
  "type": "Feature",
  "properties": {
    "addr:full":"1825 N Ross St Santa Ana CA 92706",
    "addr:housenumber":"1825",
    "addr:postcode":"92706",
    "addr:street":"N Ross St",
    "iso:country":"US",
    "sg:address":"1825 N Ross St",
    "sg:city":"Santa Ana",
    "sg:classifiers":[
        {
            "category":"Professional",
            "type":"Services"
        }
    ],
    "sg:phone":"+1 714 974 7458",
    "sg:postcode":"92706",
    "sg:province":"CA",
    "wof:name":"Brad Harkins Pool & Spa Servic",
    "wof:placetype":"venue"
},
  "geometry": {"coordinates":[-117.87248599999999,33.760686],"type":"Point"}
}