{
  "type": "Feature",
  "properties": {
    "addr:full":"7678 N Fork Rd Highland CA 92346",
    "addr:housenumber":"7678",
    "addr:postcode":"92346",
    "addr:street":"N Fork Rd",
    "iso:country":"US",
    "sg:address":"7678 N Fork Rd",
    "sg:city":"Highland",
    "sg:classifiers":[
        {
            "category":"Professional",
            "subcategory":"Management & Consulting",
            "type":"Services"
        }
    ],
    "sg:phone":"+1 909 863 0990",
    "sg:postcode":"92346",
    "sg:province":"CA",
    "sg:tags":[
        "consultant"
    ],
    "wof:name":"Gunn Biggi",
    "wof:placetype":"venue"
},
  "geometry": {"coordinates":[-117.153871,34.113723],"type":"Point"}
}