{
  "type": "Feature",
  "properties": {
    "addr:full":"22338 Alexandria Ave Torrance CA 90502",
    "addr:housenumber":"22338",
    "addr:postcode":"90502",
    "addr:street":"Alexandria Ave",
    "iso:country":"US",
    "sg:address":"22338 Alexandria Ave",
    "sg:city":"Torrance",
    "sg:classifiers":[
        {
            "category":"Utilities",
            "subcategory":"Telephone",
            "type":"Services"
        }
    ],
    "sg:phone":"+1 310 212 6908",
    "sg:postcode":"90502",
    "sg:province":"CA",
    "sg:tags":[
        "communications"
    ],
    "wof:name":"Datacore Communications Netwrk",
    "wof:placetype":"venue"
},
  "geometry": {"coordinates":[-118.29639299999999,33.823231],"type":"Point"}
}