{
  "type": "Feature",
  "properties": {
    "addr:full":"6381 Yale Cir Huntington Beach CA 92647",
    "addr:housenumber":"6381",
    "addr:postcode":"92647",
    "addr:street":"Yale Cir",
    "iso:country":"US",
    "sg:address":"6381 Yale Cir",
    "sg:city":"Huntington Beach",
    "sg:classifiers":[
        {
            "category":"Health Services",
            "subcategory":"Clinic",
            "type":"Services"
        }
    ],
    "sg:phone":"+1 888 492 3386",
    "sg:postcode":"92647",
    "sg:province":"CA",
    "sg:tags":[
        "counseling",
        "mental"
    ],
    "wof:name":"WestCoast Detox Service",
    "wof:placetype":"venue"
},
  "geometry": {"coordinates":[-118.017363,33.742471],"type":"Point"}
}