{
  "type": "Feature",
  "properties": {
    "iso:country":"US",
    "sg:address":"3047 W Valley Blvd",
    "sg:city":"Alhambra",
    "sg:classifiers":[
        {
            "category":"Wholesale",
            "subcategory":"Apparel",
            "type":"Manufacturing & Wholesale Goods"
        }
    ],
    "sg:phone":"+1 626 806 0007",
    "sg:postcode":"91803",
    "sg:province":"CA",
    "sg:tags":[
        "import"
    ],
    "wof:name":"U-Chin Inc",
    "wof:placetype":"venue"
},
  "geometry": {"coordinates":[-118.15935399999999,34.075972],"type":"Point"}
}