{
  "type": "Feature",
  "properties": {
    "addr:full":"250 E Rincon St Corona CA 92879",
    "addr:housenumber":"250",
    "addr:postcode":"92879",
    "addr:street":"E Rincon St",
    "iso:country":"US",
    "sg:address":"250 E Rincon St",
    "sg:city":"Corona",
    "sg:classifiers":[
        {
            "category":"Wholesale",
            "subcategory":"Fruits & Vegetables",
            "type":"Manufacturing & Wholesale Goods"
        }
    ],
    "sg:phone":"+1 951 734 8333",
    "sg:postcode":"92879",
    "sg:province":"CA",
    "sg:tags":[
        "produce"
    ],
    "wof:name":"Antelope Distributing Inc",
    "wof:placetype":"venue"
},
  "geometry": {"coordinates":[-117.56000899999999,33.886096],"type":"Point"}
}