{
  "type": "Feature",
  "properties": {
    "iso:country":"US",
    "sg:address":"4623 Telescope Ave",
    "sg:city":"Carlsbad",
    "sg:classifiers":[
        {
            "category":"Shopping",
            "subcategory":"Beauty & Cosmetics",
            "type":"Retail Goods"
        }
    ],
    "sg:phone":"+1 760 729 6708",
    "sg:postcode":"92008",
    "sg:province":"CA",
    "sg:tags":[
        "merchandise"
    ],
    "wof:name":"June Bessert",
    "wof:placetype":"venue"
},
  "geometry": {"coordinates":[-117.31731600000001,33.153036],"type":"Point"}
}