{
  "type": "Feature",
  "properties": {
    "addr:full":"359 S Parallel Ave Ripon CA 95366",
    "addr:housenumber":"359",
    "addr:postcode":"ca 95366",
    "addr:street":"S Parallel Ave",
    "iso:country":"US",
    "sg:address":"359 S Parallel Ave",
    "sg:city":"Ripon",
    "sg:classifiers":[
        {
            "category":"Travel",
            "subcategory":"Hotels & Motels",
            "type":"Entertainment"
        }
    ],
    "sg:phone":"+1 209 599 4577",
    "sg:postcode":"95366",
    "sg:province":"CA",
    "wof:name":"Ripon Motel",
    "wof:placetype":"venue"
},
  "geometry": {"coordinates":[-121.11666099999999,37.736278],"type":"Point"}
}