{
  "type": "Feature",
  "properties": {
    "addr:full":"1001 Mariposa St San Francisco CA 94107",
    "addr:housenumber":"1001",
    "addr:postcode":"94107",
    "addr:street":"Mariposa St",
    "iso:country":"US",
    "sg:address":"1001 Mariposa St",
    "sg:city":"San Francisco",
    "sg:classifiers":[
        {
            "category":"Professional",
            "subcategory":"Advertising",
            "type":"Services"
        }
    ],
    "sg:phone":"+1 415 249 1700",
    "sg:postcode":"94107",
    "sg:province":"CA",
    "sg:tags":[
        "counselor"
    ],
    "wof:name":"Melville Silver",
    "wof:placetype":"venue"
},
  "geometry": {"coordinates":[-122.39470900000001,37.763964],"type":"Point"}
}