{
  "type": "Feature",
  "properties": {
    "addr:full":"1621 Monument Blvd Unit B Concord CA 94520",
    "addr:housenumber":"1621",
    "addr:postcode":"94520",
    "addr:street":"Monument Blvd Unit B",
    "iso:country":"US",
    "sg:address":"1621 Monument Blvd Unit B",
    "sg:city":"Concord",
    "sg:classifiers":[
        {
            "category":"Autos & Motor Vehicles",
            "subcategory":"Auto Supplies",
            "type":"Retail Goods"
        },
        {
            "category":"Wholesale",
            "subcategory":"Machinery & Supplies",
            "type":"Manufacturing & Wholesale Goods"
        }
    ],
    "sg:phone":"+1 925 256 8468",
    "sg:postcode":"94520",
    "sg:province":"CA",
    "sg:tags":[
        "industrial",
        "glass",
        "coating",
        "tinting",
        "equipment",
        "window"
    ],
    "sg:website":"http://discoverytint.liveonatt.com",
    "wof:name":"Discovery Tint",
    "wof:placetype":"venue"
},
  "geometry": {"coordinates":[-122.042885,37.953632],"type":"Point"}
}