{
  "type": "Feature",
  "properties": {
    "addr:full":"991 Alamo Dr Vacaville CA 95687",
    "addr:housenumber":"991",
    "addr:postcode":"95687",
    "addr:street":"Alamo Dr",
    "iso:country":"US",
    "sg:address":"991 Alamo Dr",
    "sg:city":"Vacaville",
    "sg:classifiers":[
        {
            "category":"Shopping",
            "subcategory":"Department Store",
            "type":"Retail Goods"
        }
    ],
    "sg:phone":"+1 707 446 9898",
    "sg:postcode":"95687",
    "sg:province":"CA",
    "sg:tags":[
        "shop"
    ],
    "wof:name":"Dollar Tree",
    "wof:placetype":"venue"
},
  "geometry": {"coordinates":[-121.996115,38.344078],"type":"Point"}
}