{
  "type": "Feature",
  "properties": {
    "iso:country":"US",
    "sg:address":"331 J St",
    "sg:city":"Sacramento",
    "sg:classifiers":[
        {
            "category":"Professional",
            "subcategory":"Lawyer & Legal Services",
            "type":"Services"
        }
    ],
    "sg:phone":"+1 916 446 1516",
    "sg:postcode":"95814",
    "sg:province":"CA",
    "sg:tags":[
        "attorney"
    ],
    "wof:name":"Geoffrey Sutliff Atty At Law",
    "wof:placetype":"venue"
},
  "geometry": {"coordinates":[-121.501874,38.582667],"type":"Point"}
}