{
  "type": "Feature",
  "properties": {
    "iso:country":"US",
    "sg:address":"9889 Alondra Blvd",
    "sg:city":"Bellflower",
    "sg:classifiers":[
        {
            "category":"Food & Beverages",
            "subcategory":"Bakery",
            "type":"Retail Goods"
        }
    ],
    "sg:phone":"+1 562 920 6524",
    "sg:postcode":"90706",
    "sg:province":"CA",
    "sg:tags":[
        "donut",
        "eating"
    ],
    "wof:name":"J P Donuts",
    "wof:placetype":"venue"
},
  "geometry": {"coordinates":[-118.123001,33.8895],"type":"Point"}
}