{
  "type": "Feature",
  "properties": {
    "iso:country":"US",
    "sg:address":"486 Michigan Ave",
    "sg:city":"Berkeley",
    "sg:classifiers":[
        {
            "category":"Manufacturing",
            "subcategory":"Buildings",
            "type":"Manufacturing & Wholesale Goods"
        },
        {
            "category":"Building & Trades",
            "subcategory":"Construction",
            "type":"Services"
        }
    ],
    "sg:phone":"+1 510 883 1818",
    "sg:postcode":"94707",
    "sg:province":"CA",
    "sg:tags":[
        "altering",
        "consultant",
        "builder",
        "contractor",
        "home",
        "remodeling"
    ],
    "wof:name":"Landmark Improvement & Construction &",
    "wof:placetype":"venue"
},
  "geometry": {"coordinates":[-122.270867,37.901024],"type":"Point"}
}