{
  "type": "Feature",
  "properties": {
    "iso:country":"US",
    "sg:address":"1574 E Walnut St",
    "sg:city":"Pasadena",
    "sg:classifiers":[
        {
            "category":"Retail",
            "subcategory":"Repair Shop",
            "type":"Services"
        }
    ],
    "sg:phone":"+1 626 792 0537",
    "sg:postcode":"91106",
    "sg:province":"CA",
    "sg:tags":[
        "reupholstery",
        "furniture"
    ],
    "wof:name":"Al's Refinishing",
    "wof:placetype":"venue"
},
  "geometry": {"coordinates":[-118.118021,34.149405],"type":"Point"}
}