{
  "type": "Feature",
  "properties": {
    "iso:country":"US",
    "sg:address":"21317 Thomas Dr",
    "sg:city":"Carson",
    "sg:classifiers":[
        {
            "category":"Health Services",
            "subcategory":"Clinic",
            "type":"Services"
        }
    ],
    "sg:phone":"+1 310 533 1224",
    "sg:postcode":"90745",
    "sg:province":"CA",
    "sg:tags":[
        "home"
    ],
    "wof:name":"Vantage Home Health Care",
    "wof:placetype":"venue"
},
  "geometry": {"coordinates":[-118.254581,33.83527],"type":"Point"}
}