{
  "type": "Feature",
  "properties": {
    "addr:full":"3126 W 8th St Los Angeles CA 90005",
    "addr:housenumber":"3126",
    "addr:postcode":"90005",
    "addr:street":"W 8Th St",
    "iso:country":"US",
    "sg:address":"3126 W 8th St",
    "sg:city":"Los Angeles",
    "sg:classifiers":[
        {
            "category":"Restaurant",
            "type":"Food & Drink"
        }
    ],
    "sg:phone":"+1 213 381 7077",
    "sg:postcode":"90005",
    "sg:province":"CA",
    "sg:tags":[
        "korean"
    ],
    "wof:name":"Ohmajip",
    "wof:placetype":"venue"
},
  "geometry": {"coordinates":[-118.295265,34.057732],"type":"Point"}
}