{
  "type": "Feature",
  "properties": {
    "addr:full":"2418 Ponderosa St South Lake Tahoe CA 96150",
    "addr:housenumber":"2418",
    "addr:postcode":"96150",
    "addr:street":"Ponderosa St",
    "iso:country":"US",
    "sg:address":"2418 Ponderosa St",
    "sg:city":"South Lake Tahoe",
    "sg:classifiers":[
        {
            "category":"Health Services",
            "subcategory":"Clinic",
            "type":"Services"
        }
    ],
    "sg:phone":"+1 530 541 3751",
    "sg:postcode":"96150",
    "sg:province":"CA",
    "sg:tags":[
        "hypnotherapy"
    ],
    "wof:name":"Mary A Avila",
    "wof:placetype":"venue"
},
  "geometry": {"coordinates":[-119.99135200000001,38.923624],"type":"Point"}
}