{
  "type": "Feature",
  "properties": {
    "addr:full":"810 W 9th St San Pedro CA 90731",
    "addr:housenumber":"810",
    "addr:postcode":"90731",
    "addr:street":"W 9Th St",
    "iso:country":"US",
    "sg:address":"810 W 9th St",
    "sg:city":"San Pedro",
    "sg:classifiers":[
        {
            "category":"Banks & Credit Unions",
            "subcategory":"Investment Brokerage",
            "type":"Services"
        }
    ],
    "sg:phone":"+1 310 833 9780",
    "sg:postcode":"90731",
    "sg:province":"CA",
    "wof:name":"Synergy Investment Group",
    "wof:placetype":"venue"
},
  "geometry": {"coordinates":[-118.29667499999999,33.736141],"type":"Point"}
}