{
  "type": "Feature",
  "properties": {
    "iso:country":"US",
    "sg:address":"1525 Alum Rock Ave",
    "sg:city":"San Jose",
    "sg:classifiers":[
        {
            "category":"Home & Garden",
            "subcategory":"Building Materials",
            "type":"Retail Goods"
        }
    ],
    "sg:phone":"+1 408 926 4500",
    "sg:postcode":"95116",
    "sg:province":"CA",
    "sg:tags":[
        "center"
    ],
    "wof:name":"European Home & Garden",
    "wof:placetype":"venue"
},
  "geometry": {"coordinates":[-121.861125,37.350225],"type":"Point"}
}