{
  "type": "Feature",
  "properties": {
    "iso:country":"US",
    "sg:address":"321 N Sacramento St",
    "sg:city":"Lodi",
    "sg:classifiers":[
        {
            "category":"Building & Trades",
            "subcategory":"Construction",
            "type":"Services"
        }
    ],
    "sg:phone":"+1 209 367 1986",
    "sg:postcode":"95240",
    "sg:province":"CA",
    "sg:tags":[
        "dry wall",
        "contractor"
    ],
    "wof:name":"G Miller Drywall",
    "wof:placetype":"venue"
},
  "geometry": {"coordinates":[-121.271957,38.13858],"type":"Point"}
}