{
  "type": "Feature",
  "properties": {
    "iso:country":"US",
    "sg:address":"512 Civic Center Dr",
    "sg:city":"Oceanside",
    "sg:classifiers":[
        {
            "category":"Building & Trades",
            "subcategory":"Landscaping Services",
            "type":"Services"
        }
    ],
    "sg:phone":"+1 760 721 9912",
    "sg:postcode":"92054",
    "sg:province":"CA",
    "sg:tags":[
        "landscape",
        "contractor"
    ],
    "wof:name":"Oceanside Construction Co",
    "wof:placetype":"venue"
},
  "geometry": {"coordinates":[-117.380704,33.197859],"type":"Point"}
}