{
  "type": "Feature",
  "properties": {
    "addr:full":"701 Texas St Fairfield CA 94533",
    "addr:housenumber":"701",
    "addr:postcode":"94533",
    "addr:street":"Texas St",
    "iso:country":"US",
    "sg:address":"701 Texas St",
    "sg:city":"Fairfield",
    "sg:classifiers":[
        {
            "category":"Government",
            "subcategory":"Court House",
            "type":"Public Place"
        }
    ],
    "sg:phone":"+1 707 421 6290",
    "sg:postcode":"94533",
    "sg:province":"CA",
    "sg:tags":[
        "recorder"
    ],
    "wof:name":"Recorders Office County",
    "wof:placetype":"venue"
},
  "geometry": {"coordinates":[-122.043244,38.249227],"type":"Point"}
}