{
  "type": "Feature",
  "properties": {
    "addr:full":"2355 E Dominguez St Carson CA 90810",
    "addr:housenumber":"2355",
    "addr:postcode":"90810",
    "addr:street":"E Dominguez St",
    "iso:country":"US",
    "sg:address":"2355 E Dominguez St",
    "sg:city":"Carson",
    "sg:classifiers":[
        {
            "category":"Building & Trades",
            "subcategory":"Equipment Rental",
            "type":"Services"
        }
    ],
    "sg:phone":"+1 310 638 0401",
    "sg:postcode":"90810",
    "sg:province":"CA",
    "sg:tags":[
        "yard"
    ],
    "wof:name":"Rusmar High Lift Equipment",
    "wof:placetype":"venue"
},
  "geometry": {"coordinates":[-118.22743699999999,33.839269],"type":"Point"}
}