{
  "type": "Feature",
  "properties": {
    "addr:full":"4623 York Blvd Los Angeles CA 90041",
    "addr:housenumber":"4623",
    "addr:postcode":"90041",
    "addr:street":"York Blvd",
    "iso:country":"US",
    "sg:address":"4623 York Blvd",
    "sg:city":"Los Angeles",
    "sg:classifiers":[
        {
            "category":"Education",
            "subcategory":"School",
            "type":"Public Place"
        }
    ],
    "sg:phone":"+1 323 344 7375",
    "sg:postcode":"90041",
    "sg:province":"CA",
    "wof:name":"Julio Training School",
    "wof:placetype":"venue"
},
  "geometry": {"coordinates":[-118.215408,34.123204],"type":"Point"}
}