{
  "type": "Feature",
  "properties": {
    "addr:full":"7027 Dublin Blvd Dublin CA 94568",
    "addr:housenumber":"7027",
    "addr:postcode":"94568",
    "addr:street":"Dublin Blvd",
    "iso:country":"US",
    "sg:address":"7027 Dublin Blvd",
    "sg:city":"Dublin",
    "sg:classifiers":[
        {
            "category":"Professional",
            "subcategory":"Lawyer & Legal Services",
            "type":"Services"
        }
    ],
    "sg:phone":"+1 925 803 8081",
    "sg:postcode":"94568",
    "sg:province":"CA",
    "sg:tags":[
        "attorney"
    ],
    "wof:name":"Susie Larsen",
    "wof:placetype":"venue"
},
  "geometry": {"coordinates":[-121.91833800000001,37.705012],"type":"Point"}
}