{
  "type": "Feature",
  "properties": {
    "addr:full":"44409 Fig Ave Lancaster CA 93534",
    "addr:housenumber":"44409",
    "addr:postcode":"93534",
    "addr:street":"Fig Ave",
    "iso:country":"US",
    "sg:address":"44409 Fig Ave",
    "sg:city":"Lancaster",
    "sg:classifiers":[
        {
            "category":"Social Services",
            "subcategory":"Child Care",
            "type":"Services"
        }
    ],
    "sg:phone":"+1 661 945 8804",
    "sg:postcode":"93534",
    "sg:province":"CA",
    "wof:name":"Heavenly ACE Academy",
    "wof:placetype":"venue"
},
  "geometry": {"coordinates":[-118.142045,34.689486],"type":"Point"}
}