{
  "type": "Feature",
  "properties": {
    "addr:full":"1820 Pennebaker Way Manteca CA 95336",
    "addr:housenumber":"1820",
    "addr:postcode":"95336",
    "addr:street":"Pennebaker Way",
    "iso:country":"US",
    "sg:address":"1820 Pennebaker Way",
    "sg:city":"Manteca",
    "sg:classifiers":[
        {
            "category":"Real Estate",
            "subcategory":"Real Estate Operator",
            "type":"Services"
        }
    ],
    "sg:phone":"+1 209 239 1367",
    "sg:postcode":"95336",
    "sg:province":"CA",
    "sg:tags":[
        "apartment"
    ],
    "wof:name":"Sandpiper Village Apartments",
    "wof:placetype":"venue"
},
  "geometry": {"coordinates":[-121.186823,37.800695],"type":"Point"}
}