{
  "type": "Feature",
  "properties": {
    "iso:country":"US",
    "sg:address":"11162 Palm Terrace Ln",
    "sg:city":"Riverside",
    "sg:classifiers":[
        {
            "category":"Health Services",
            "subcategory":"Nursing And Care Facility",
            "type":"Services"
        }
    ],
    "sg:phone":"+1 951 687 7330",
    "sg:postcode":"92505",
    "sg:province":"CA",
    "sg:tags":[
        "home",
        "convalescent"
    ],
    "wof:name":"Palm Terrace Care Ctr",
    "wof:placetype":"venue"
},
  "geometry": {"coordinates":[-117.497276,33.935907],"type":"Point"}
}