{
  "type": "Feature",
  "properties": {
    "addr:full":"144 N Mountain Ave Upland CA 91786",
    "addr:housenumber":"144",
    "addr:postcode":"91786",
    "addr:street":"N Mountain Ave",
    "iso:country":"US",
    "sg:address":"144 N Mountain Ave",
    "sg:city":"Upland",
    "sg:classifiers":[
        {
            "category":"Home & Garden",
            "subcategory":"Carpets & Floor Coverings",
            "type":"Retail Goods"
        }
    ],
    "sg:phone":"+1 909 981 0437",
    "sg:postcode":"91786",
    "sg:province":"CA",
    "sg:tags":[
        "dealer",
        "rug"
    ],
    "wof:name":"Carpet One Of Upland",
    "wof:placetype":"venue"
},
  "geometry": {"coordinates":[-117.67007700000001,34.094847],"type":"Point"}
}