{
  "type": "Feature",
  "properties": {
    "iso:country":"US",
    "sg:address":"448 Georgia St",
    "sg:city":"Vallejo",
    "sg:classifiers":[
        {
            "category":"Home & Garden",
            "subcategory":"Garden Supply",
            "type":"Retail Goods"
        }
    ],
    "sg:phone":"+1 707 647 0774",
    "sg:postcode":"94590",
    "sg:province":"CA",
    "sg:tags":[
        "equipment",
        "hydroponics"
    ],
    "sg:website":"http://www.northbayhydroponics.com",
    "wof:name":"Everything Green Hydroponics",
    "wof:placetype":"venue"
},
  "geometry": {"coordinates":[-122.255363,38.101088],"type":"Point"}
}