{
  "type": "Feature",
  "properties": {
    "iso:country":"US",
    "sg:address":"17912 Lincoln St",
    "sg:city":"Villa Park",
    "sg:classifiers":[
        {
            "category":"Health Services",
            "subcategory":"Nursing And Care Facility",
            "type":"Services"
        }
    ],
    "sg:phone":"+1 714 639 5885",
    "sg:postcode":"92861",
    "sg:province":"CA",
    "sg:tags":[
        "home",
        "convalescent"
    ],
    "wof:name":"Best Elderly Care",
    "wof:placetype":"venue"
},
  "geometry": {"coordinates":[-117.819704,33.807711],"type":"Point"}
}