{
  "type": "Feature",
  "properties": {
    "addr:full":"6900 8th St Buena Park CA 90620",
    "addr:housenumber":"6900",
    "addr:postcode":"90620",
    "addr:street":"8Th St",
    "iso:country":"US",
    "sg:address":"6900 8th St",
    "sg:city":"Buena Park",
    "sg:classifiers":[
        {
            "category":"Wholesale",
            "subcategory":"Metals & Minerals",
            "type":"Manufacturing & Wholesale Goods"
        }
    ],
    "sg:phone":"+1 714 562 0996",
    "sg:postcode":"90620",
    "sg:province":"CA",
    "sg:tags":[
        "product",
        "wire"
    ],
    "sg:website":"www.dwfinc.com",
    "wof:name":"Distributor's Wire & Fittings",
    "wof:placetype":"venue"
},
  "geometry": {"coordinates":[-118.013536,33.867148],"type":"Point"}
}