{
  "type": "Feature",
  "properties": {
    "iso:country":"US",
    "sg:address":"825 W San Marcos Blvd",
    "sg:city":"San Marcos",
    "sg:classifiers":[
        {
            "category":"Health Services",
            "subcategory":"Doctor",
            "type":"Services"
        }
    ],
    "sg:phone":"+1 760 471 2261",
    "sg:postcode":"92078",
    "sg:province":"CA",
    "sg:tags":[
        "dentist"
    ],
    "wof:name":"Family Dentistry",
    "wof:placetype":"venue"
},
  "geometry": {"coordinates":[-117.182919,33.136066],"type":"Point"}
}