{
  "type": "Feature",
  "properties": {
    "addr:full":"15 Rowland Way Novato CA 94945",
    "addr:housenumber":"15",
    "addr:postcode":"94945",
    "addr:street":"Rowland Way",
    "iso:country":"US",
    "sg:address":"15 Rowland Way",
    "sg:city":"Novato",
    "sg:classifiers":[
        {
            "category":"Restaurant",
            "type":"Food & Drink"
        }
    ],
    "sg:menulink":"http://www.allmenus.com/ca/northeast-marin/51731-moylans-brewing-co/menu/",
    "sg:phone":"+1 415 898 4677",
    "sg:postcode":"94945",
    "sg:province":"CA",
    "sg:tags":[
        "american"
    ],
    "wof:name":"Moylan's Brewing Co.",
    "wof:placetype":"venue"
},
  "geometry": {"coordinates":[-122.55649,38.094257],"type":"Point"}
}