{
  "type": "Feature",
  "properties": {
    "iso:country":"US",
    "sg:address":"830 W 16th St",
    "sg:city":"Costa Mesa",
    "sg:classifiers":[
        {
            "category":"Manufacturing",
            "subcategory":"Tools & Machinery",
            "type":"Manufacturing & Wholesale Goods"
        }
    ],
    "sg:phone":"+1 949 642 9491",
    "sg:postcode":"92627",
    "sg:province":"CA",
    "sg:tags":[
        "model",
        "maker"
    ],
    "wof:name":"Sharp Marine Industries Inc",
    "wof:placetype":"venue"
},
  "geometry": {"coordinates":[-117.932815,33.632553],"type":"Point"}
}