{
  "type": "Feature",
  "properties": {
    "addr:full":"16 Romero Ct Novato CA 94945",
    "addr:housenumber":"16",
    "addr:postcode":"94945",
    "addr:street":"Romero Ct",
    "iso:country":"US",
    "sg:address":"16 Romero Ct",
    "sg:city":"Novato",
    "sg:classifiers":[
        {
            "category":"Professional",
            "type":"Services"
        }
    ],
    "sg:phone":"+1 415 898 8946",
    "sg:postcode":"94945",
    "sg:province":"CA",
    "sg:tags":[
        "establishment"
    ],
    "wof:name":"Victor Master & Co",
    "wof:placetype":"venue"
},
  "geometry": {"coordinates":[-122.59469199999999,38.122174],"type":"Point"}
}