{
  "type": "Feature",
  "properties": {
    "iso:country":"US",
    "sg:address":"540 Spectrum Cir",
    "sg:city":"Oxnard",
    "sg:classifiers":[
        {
            "category":"Manufacturing",
            "subcategory":"Metals",
            "type":"Manufacturing & Wholesale Goods"
        }
    ],
    "sg:phone":"+1 805 983 4320",
    "sg:postcode":"93030",
    "sg:province":"CA",
    "sg:tags":[
        "finisher"
    ],
    "wof:name":"Elite Metal Finishing",
    "wof:placetype":"venue"
},
  "geometry": {"coordinates":[-119.125309,34.206645],"type":"Point"}
}