{
  "type": "Feature",
  "properties": {
    "addr:full":"2105 Foothill Blvd La Verne CA 91750",
    "addr:housenumber":"2105",
    "addr:postcode":"91750",
    "addr:street":"Foothill Blvd",
    "iso:country":"US",
    "sg:address":"2105 Foothill Blvd",
    "sg:city":"La Verne",
    "sg:classifiers":[
        {
            "category":"Food & Beverages",
            "subcategory":"Bakery",
            "type":"Retail Goods"
        }
    ],
    "sg:phone":"+1 909 392 3841",
    "sg:postcode":"91750",
    "sg:province":"CA",
    "sg:tags":[
        "baker"
    ],
    "wof:name":"Truffles Patisserie",
    "wof:placetype":"venue"
},
  "geometry": {"coordinates":[-117.763098,34.112683],"type":"Point"}
}