{
  "type": "Feature",
  "properties": {
    "addr:full":"2262 State Rte 66 Glendora CA 91740",
    "addr:housenumber":"2262",
    "addr:postcode":"91740",
    "addr:street":"State Rte 66",
    "iso:country":"US",
    "sg:address":"2262 State Rte 66",
    "sg:city":"Glendora",
    "sg:classifiers":[
        {
            "category":"Retail",
            "subcategory":"Animal Services",
            "type":"Services"
        }
    ],
    "sg:phone":"+1 626 914 6564",
    "sg:postcode":"91740",
    "sg:province":"CA",
    "sg:tags":[
        "pet",
        "grooming",
        "washing"
    ],
    "wof:name":"American Pet Grooming",
    "wof:placetype":"venue"
},
  "geometry": {"coordinates":[-117.821926,34.127154],"type":"Point"}
}