{
  "type": "Feature",
  "properties": {
    "iso:country":"US",
    "sg:address":"874 Cherry Way",
    "sg:city":"Hayward",
    "sg:classifiers":[
        {
            "category":"Professional",
            "type":"Services"
        }
    ],
    "sg:phone":"+1 510 287 6777",
    "sg:postcode":"94541",
    "sg:province":"CA",
    "sg:website":"www.cherrywaydocprep.com",
    "wof:name":"Cherry Way Document Preparation Services",
    "wof:placetype":"venue"
},
  "geometry": {"coordinates":[-122.098855,37.682249],"type":"Point"}
}