{
  "type": "Feature",
  "properties": {
    "iso:country":"US",
    "sg:address":"3549 Willis Dr",
    "sg:city":"Napa",
    "sg:classifiers":[
        {
            "category":"Building & Trades",
            "subcategory":"Landscaping Services",
            "type":"Services"
        }
    ],
    "sg:phone":"+1 707 253 8054",
    "sg:postcode":"94558",
    "sg:province":"CA",
    "sg:tags":[
        "landscape",
        "contractor"
    ],
    "wof:name":"Jake A Ruygt Garden Mntnc",
    "wof:placetype":"venue"
},
  "geometry": {"coordinates":[-122.29976000000001,38.326792],"type":"Point"}
}