{
  "type": "Feature",
  "properties": {
    "addr:full":"4100 Easton Dr Bakersfield CA 93309",
    "addr:housenumber":"4100",
    "addr:postcode":"93309",
    "addr:street":"Easton Dr",
    "iso:country":"US",
    "sg:address":"4100 Easton Dr",
    "sg:city":"Bakersfield",
    "sg:classifiers":[
        {
            "category":"Retail",
            "subcategory":"Repair Shop",
            "type":"Services"
        }
    ],
    "sg:phone":"+1 661 332 8959",
    "sg:postcode":"93309",
    "sg:province":"CA",
    "sg:tags":[
        "upholsterer"
    ],
    "wof:name":"David Oroz Upholstery",
    "wof:placetype":"venue"
},
  "geometry": {"coordinates":[-119.053684,35.36567],"type":"Point"}
}