{
  "type": "Feature",
  "properties": {
    "iso:country":"US",
    "sg:address":"2041 Nicklaus Cir",
    "sg:city":"Roseville",
    "sg:classifiers":[
        {
            "category":"Shopping",
            "subcategory":"Used Merchandise",
            "type":"Retail Goods"
        }
    ],
    "sg:phone":"+1 916 782 3453",
    "sg:postcode":"95678",
    "sg:province":"CA",
    "wof:name":"C&C Antiques & Collectibl",
    "wof:placetype":"venue"
},
  "geometry": {"coordinates":[-121.28053300000001,38.76684],"type":"Point"}
}