{
  "type": "Feature",
  "properties": {
    "iso:country":"US",
    "sg:address":"11158 Carriage Ave",
    "sg:city":"Montclair",
    "sg:classifiers":[
        {
            "category":"Home & Garden",
            "subcategory":"Building Materials",
            "type":"Retail Goods"
        }
    ],
    "sg:phone":"+1 626 960 1682",
    "sg:postcode":"91763",
    "sg:province":"CA",
    "sg:tags":[
        "door"
    ],
    "wof:name":"Door Doctor Svc",
    "wof:placetype":"venue"
},
  "geometry": {"coordinates":[-117.70302599999999,34.050678],"type":"Point"}
}