{
  "type": "Feature",
  "properties": {
    "addr:full":"1104 Buchanan Rd Antioch CA 94509",
    "addr:housenumber":"1104",
    "addr:postcode":"ca 94509",
    "addr:street":"Buchanan Rd",
    "iso:country":"US",
    "sg:address":"1104 Buchanan Rd",
    "sg:city":"Antioch",
    "sg:classifiers":[
        {
            "category":"Professional",
            "subcategory":"Accounting & Tax Preparation",
            "type":"Services"
        }
    ],
    "sg:phone":"+1 510 754 0103",
    "sg:postcode":"94509",
    "sg:province":"CA",
    "sg:tags":[
        "return",
        "filing"
    ],
    "wof:name":"Shirley Magana Bkpg & Tax Svc",
    "wof:placetype":"venue"
},
  "geometry": {"coordinates":[-121.823431,37.998819],"type":"Point"}
}