{
  "type": "Feature",
  "properties": {
    "iso:country":"US",
    "sg:address":"3636 N Hazel Ave",
    "sg:city":"Fresno",
    "sg:classifiers":[
        {
            "category":"Retail",
            "subcategory":"Auto Repair",
            "type":"Services"
        }
    ],
    "sg:phone":"+1 559 442 4577",
    "sg:postcode":"93722",
    "sg:province":"CA",
    "sg:tags":[
        "automobile",
        "customizing"
    ],
    "wof:name":"Hoover Auto & Custom",
    "wof:placetype":"venue"
},
  "geometry": {"coordinates":[-119.849858,36.790484],"type":"Point"}
}