{
  "type": "Feature",
  "properties": {
    "addr:full":"1701 Lundy Ave Ste 120 San Jose CA 95131",
    "addr:housenumber":"1701",
    "addr:postcode":"95131",
    "addr:street":"Lundy Ave Ste 120",
    "iso:country":"US",
    "sg:address":"1701 Lundy Ave Ste 120",
    "sg:city":"San Jose",
    "sg:classifiers":[
        {
            "category":"Health Services",
            "subcategory":"Optometrist",
            "type":"Services"
        }
    ],
    "sg:phone":"+1 408 453 9988",
    "sg:postcode":"95131",
    "sg:province":"CA",
    "sg:website":"jenniferkaood.com",
    "wof:name":"Jennifer Kao, OD",
    "wof:placetype":"venue"
},
  "geometry": {"coordinates":[-121.908592,37.387156],"type":"Point"}
}