{
  "type": "Feature",
  "properties": {
    "iso:country":"US",
    "sg:address":"2429 N Beachwood Dr",
    "sg:city":"Los Angeles",
    "sg:classifiers":[
        {
            "category":"Professional",
            "subcategory":"Lawyer & Legal Services",
            "type":"Services"
        }
    ],
    "sg:phone":"+1 310 201 7900",
    "sg:postcode":"90068",
    "sg:province":"CA",
    "wof:name":"Gelles Peter Attorney At Law",
    "wof:placetype":"venue"
},
  "geometry": {"coordinates":[-118.321779,34.113955],"type":"Point"}
}