{
  "type": "Feature",
  "properties": {
    "addr:full":"1547 Venice Blvd Los Angeles CA 90006",
    "addr:housenumber":"1547",
    "addr:postcode":"90006",
    "addr:street":"Venice Blvd",
    "iso:country":"US",
    "sg:address":"1547 Venice Blvd",
    "sg:city":"Los Angeles",
    "sg:classifiers":[
        {
            "category":"Professional",
            "subcategory":"Accounting & Tax Preparation",
            "type":"Services"
        }
    ],
    "sg:phone":"+1 213 386 5010",
    "sg:postcode":"90006",
    "sg:province":"CA",
    "sg:tags":[
        "return",
        "filing"
    ],
    "wof:name":"El Mundo",
    "wof:placetype":"venue"
},
  "geometry": {"coordinates":[-118.287693,34.044324],"type":"Point"}
}