{
  "type": "Feature",
  "properties": {
    "addr:full":"374 E Santa Clara St San Jose CA 95113",
    "addr:housenumber":"374",
    "addr:postcode":"95113",
    "addr:street":"E Santa Clara St",
    "iso:country":"US",
    "sg:address":"374 E Santa Clara St",
    "sg:city":"San Jose",
    "sg:classifiers":[
        {
            "category":"Restaurant",
            "type":"Food & Drink"
        }
    ],
    "sg:phone":"+1 408 297 7994",
    "sg:postcode":"95113",
    "sg:province":"CA",
    "sg:tags":[
        "vietnamese"
    ],
    "sg:website":"www.onyxrestaurantsj.com",
    "wof:name":"Onyx Restaurant",
    "wof:placetype":"venue"
},
  "geometry": {"coordinates":[-121.89756199999999,37.331924],"type":"Point"}
}