{
  "type": "Feature",
  "properties": {
    "iso:country":"US",
    "sg:address":"789 S San Gabriel Blvd",
    "sg:city":"San Gabriel",
    "sg:classifiers":[
        {
            "category":"Health Services",
            "subcategory":"Doctor",
            "type":"Services"
        }
    ],
    "sg:phone":"+1 626 309 1313",
    "sg:postcode":"91776",
    "sg:province":"CA",
    "sg:tags":[
        "dentist"
    ],
    "wof:name":"Herbert Lin DDS",
    "wof:placetype":"venue"
},
  "geometry": {"coordinates":[-118.09096099999999,34.094108],"type":"Point"}
}