{
  "type": "Feature",
  "properties": {
    "iso:country":"US",
    "sg:address":"23569 Sunnymead Ranch Pkwy",
    "sg:city":"Moreno Valley",
    "sg:classifiers":[
        {
            "category":"Banks & Credit Unions",
            "subcategory":"Investment Brokerage",
            "type":"Services"
        }
    ],
    "sg:phone":"+1 951 488 9033",
    "sg:postcode":"92557",
    "sg:province":"CA",
    "sg:tags":[
        "security"
    ],
    "wof:name":"Edward Jones Co",
    "wof:placetype":"venue"
},
  "geometry": {"coordinates":[-117.252654,33.969037],"type":"Point"}
}