{
  "type": "Feature",
  "properties": {
    "iso:country":"US",
    "sg:address":"355 E Redondo Beach Blvd",
    "sg:city":"Gardena",
    "sg:classifiers":[
        {
            "category":"Utilities",
            "subcategory":"Refuse",
            "type":"Services"
        }
    ],
    "sg:phone":"+1 310 532 6732",
    "sg:postcode":"90248",
    "sg:province":"CA",
    "sg:tags":[
        "garbage",
        "collection"
    ],
    "wof:name":"West Coast Roll Off",
    "wof:placetype":"venue"
},
  "geometry": {"coordinates":[-118.270574,33.893162],"type":"Point"}
}