{
  "type": "Feature",
  "properties": {
    "addr:full":"1601 W Capitol Ave West Sacramento CA 95691",
    "addr:housenumber":"1601",
    "addr:postcode":"95691",
    "addr:street":"W Capitol Ave",
    "iso:country":"US",
    "sg:address":"1601 W Capitol Ave",
    "sg:city":"West Sacramento",
    "sg:classifiers":[
        {
            "category":"Shopping",
            "subcategory":"Pharmacy",
            "type":"Retail Goods"
        }
    ],
    "sg:phone":"+1 916 372 3111",
    "sg:postcode":"95691",
    "sg:province":"CA",
    "sg:tags":[
        "drugstore"
    ],
    "wof:name":"Raley's and Bel Air",
    "wof:placetype":"venue"
},
  "geometry": {"coordinates":[-121.529999,38.5802],"type":"Point"}
}