{
  "type": "Feature",
  "properties": {
    "iso:country":"US",
    "sg:address":"13891 Newport Ave",
    "sg:city":"Tustin",
    "sg:classifiers":[
        {
            "category":"Professional",
            "subcategory":"Business Services",
            "type":"Services"
        }
    ],
    "sg:phone":"+1 714 258 3016",
    "sg:postcode":"92780",
    "sg:province":"CA",
    "sg:tags":[
        "fund",
        "promotion",
        "raising"
    ],
    "sg:website":"www.geiger.com",
    "wof:name":"Geiger Brothers",
    "wof:placetype":"venue"
},
  "geometry": {"coordinates":[-117.820885,33.739522],"type":"Point"}
}