{
  "type": "Feature",
  "properties": {
    "iso:country":"US",
    "sg:address":"1404 Esplanade",
    "sg:city":"Redondo Beach",
    "sg:classifiers":[
        {
            "category":"Professional",
            "type":"Services"
        }
    ],
    "sg:phone":"+1 310 781 8647",
    "sg:postcode":"90277",
    "sg:province":"CA",
    "wof:name":"Joy M Greenberg",
    "wof:placetype":"venue"
},
  "geometry": {"coordinates":[-118.38969299999999,33.821383],"type":"Point"}
}