{
  "type": "Feature",
  "properties": {
    "iso:country":"US",
    "sg:address":"6536 Clara Way",
    "sg:city":"North Highlands",
    "sg:classifiers":[
        {
            "category":"Personal",
            "subcategory":"Shoe Repair & Shine",
            "type":"Services"
        }
    ],
    "sg:phone":"+1 916 339 9404",
    "sg:postcode":"95660",
    "sg:province":"CA",
    "sg:tags":[
        "repairing",
        "boot"
    ],
    "wof:name":"A-1 Shoe Repair",
    "wof:placetype":"venue"
},
  "geometry": {"coordinates":[-121.382338,38.683877],"type":"Point"}
}