{
  "type": "Feature",
  "properties": {
    "iso:country":"US",
    "sg:address":"16210 Inglewood Avenue",
    "sg:city":"Lawndale",
    "sg:classifiers":[
        {
            "category":"Food & Beverages",
            "subcategory":"Liquor & Beverages",
            "type":"Retail Goods"
        }
    ],
    "sg:phone":"+1 310 370 7591",
    "sg:postcode":"90260",
    "sg:province":"CA",
    "sg:tags":[
        "beer",
        "spirit",
        "wine"
    ],
    "wof:name":"B & K Liquor",
    "wof:placetype":"venue"
},
  "geometry": {"coordinates":[-118.35236,33.887972],"type":"Point"}
}