{
  "type": "Feature",
  "properties": {
    "iso:country":"US",
    "sg:address":"135 E Tulare St",
    "sg:city":"Dinuba",
    "sg:classifiers":[
        {
            "category":"Restaurant",
            "type":"Food & Drink"
        }
    ],
    "sg:phone":"+1 559 591 0125",
    "sg:postcode":"93618",
    "sg:province":"CA",
    "wof:name":"Amalia's Restaurant",
    "wof:placetype":"venue"
},
  "geometry": {"coordinates":[-119.390127,36.54103],"type":"Point"}
}