{
  "type": "Feature",
  "properties": {
    "addr:full":"24253 San Fernando Rd Santa Clarita CA 91321",
    "addr:housenumber":"24253",
    "addr:postcode":"91321",
    "addr:street":"San Fernando Rd",
    "iso:country":"US",
    "sg:address":"24253 San Fernando Rd",
    "sg:city":"Santa Clarita",
    "sg:classifiers":[
        {
            "category":"Social Services",
            "type":"Services"
        }
    ],
    "sg:phone":"+1 661 254 8904",
    "sg:postcode":"91321",
    "sg:province":"CA",
    "sg:tags":[
        "organization",
        "welfare"
    ],
    "wof:name":"Operation School Bell",
    "wof:placetype":"venue"
},
  "geometry": {"coordinates":[-118.527215,34.377818],"type":"Point"}
}