{
  "type": "Feature",
  "properties": {
    "iso:country":"US",
    "sg:address":"3012 Bear Valley Pkwy S",
    "sg:city":"Escondido",
    "sg:classifiers":[
        {
            "category":"Health Services",
            "subcategory":"Nursing And Care Facility",
            "type":"Services"
        }
    ],
    "sg:phone":"+1 760 735 8084",
    "sg:postcode":"92025",
    "sg:province":"CA",
    "sg:tags":[
        "home",
        "retirement",
        "community"
    ],
    "sg:website":"www.aegisal.com",
    "wof:name":"Aegis Senior Living",
    "wof:placetype":"venue"
},
  "geometry": {"coordinates":[-117.056403,33.081974],"type":"Point"}
}