{
  "type": "Feature",
  "properties": {
    "addr:full":"475 Klug Cir Corona CA 92880",
    "addr:housenumber":"475",
    "addr:postcode":"92880",
    "addr:street":"Klug Cir",
    "iso:country":"US",
    "sg:address":"475 Klug Cir",
    "sg:city":"Corona",
    "sg:classifiers":[
        {
            "category":"Wholesale",
            "subcategory":"Hardware",
            "type":"Manufacturing & Wholesale Goods"
        }
    ],
    "sg:phone":"+1 951 280 4488",
    "sg:postcode":"92880",
    "sg:province":"CA",
    "sg:tags":[
        "fastener"
    ],
    "sg:website":"www.tripaconline.com",
    "wof:name":"Tri Pac Fasteners",
    "wof:placetype":"venue"
},
  "geometry": {"coordinates":[-117.610901,33.889611],"type":"Point"}
}