{
  "type": "Feature",
  "properties": {
    "addr:full":"6134 Camino Verde Drive Suite E San Jose CA 95119",
    "addr:housenumber":"6134",
    "addr:postcode":"95119",
    "addr:street":"Camino Verde Drive Suite E",
    "iso:country":"US",
    "sg:address":"6134 Camino Verde Drive Suite E",
    "sg:city":"San Jose",
    "sg:classifiers":[
        {
            "category":"Health Services",
            "subcategory":"Dentist",
            "type":"Services"
        }
    ],
    "sg:phone":"+1 408 227 4010",
    "sg:postcode":"95119",
    "sg:province":"CA",
    "wof:name":"Ott James R DDS",
    "wof:placetype":"venue"
},
  "geometry": {"coordinates":[-121.80104799999999,37.236007],"type":"Point"}
}