{
  "type": "Feature",
  "properties": {
    "iso:country":"US",
    "sg:address":"12110 Tech Center Dr",
    "sg:city":"Poway",
    "sg:classifiers":[
        {
            "category":"Government",
            "subcategory":"Office",
            "type":"Public Place"
        }
    ],
    "sg:phone":"+1 858 679 4015",
    "sg:postcode":"92064",
    "sg:province":"CA",
    "sg:tags":[
        "survey",
        "geological"
    ],
    "wof:name":"Poway Field Office",
    "wof:placetype":"venue"
},
  "geometry": {"coordinates":[-117.036597,32.935206],"type":"Point"}
}