{
  "type": "Feature",
  "properties": {
    "addr:full":"24012 Calle De La Plata Laguna Hills CA 92653",
    "addr:housenumber":"24012",
    "addr:postcode":"92653",
    "addr:street":"Calle De La Plata",
    "iso:country":"US",
    "sg:address":"24012 Calle De La Plata",
    "sg:city":"Laguna Hills",
    "sg:classifiers":[
        {
            "category":"Banks & Credit Unions",
            "subcategory":"Financial Services",
            "type":"Services"
        }
    ],
    "sg:phone":"+1 949 583 7388",
    "sg:postcode":"92653",
    "sg:province":"CA",
    "sg:tags":[
        "broker",
        "mortgage"
    ],
    "wof:name":"Southern California Funding",
    "wof:placetype":"venue"
},
  "geometry": {"coordinates":[-117.712057,33.610041],"type":"Point"}
}