{
  "type": "Feature",
  "properties": {
    "addr:full":"145 Main St Half Moon Bay CA 94019",
    "addr:housenumber":"145",
    "addr:postcode":"94019",
    "addr:street":"Main St",
    "iso:country":"US",
    "sg:address":"145 Main St",
    "sg:city":"Half Moon Bay",
    "sg:classifiers":[
        {
            "category":"Retail",
            "subcategory":"Laundry & Dry Cleaning",
            "type":"Services"
        }
    ],
    "sg:phone":"+1 650 726 6676",
    "sg:postcode":"94019",
    "sg:province":"CA",
    "sg:tags":[
        "cleaners",
        "rug",
        "carpet"
    ],
    "wof:name":"Coastside Carpet Cleaners",
    "wof:placetype":"venue"
},
  "geometry": {"coordinates":[-122.43006,37.468005],"type":"Point"}
}