{
  "type": "Feature",
  "properties": {
    "addr:full":"42301 Zevo Dr Temecula CA 92590",
    "addr:postcode":"42301;92590",
    "addr:street":"Zevo Dr",
    "iso:country":"US",
    "sg:address":"42301 Zevo Dr",
    "sg:city":"Temecula",
    "sg:classifiers":[
        {
            "category":"Professional",
            "subcategory":"Business Services",
            "type":"Services"
        }
    ],
    "sg:phone":"+1 951 587 9004",
    "sg:postcode":"92590",
    "sg:province":"CA",
    "sg:tags":[
        "interior",
        "consultant",
        "design",
        "decorator"
    ],
    "wof:name":"Creative Touch Interiors",
    "wof:placetype":"venue"
},
  "geometry": {"coordinates":[-117.178983,33.511322],"type":"Point"}
}