{
  "type": "Feature",
  "properties": {
    "addr:full":"103 Sandholm Ln Cloverdale CA 95425",
    "addr:housenumber":"103",
    "addr:postcode":"95425",
    "addr:street":"Sandholm Ln",
    "iso:country":"US",
    "sg:address":"103 Sandholm Ln",
    "sg:city":"Cloverdale",
    "sg:classifiers":[
        {
            "category":"Retail",
            "subcategory":"Auto Repair",
            "type":"Services"
        }
    ],
    "sg:phone":"+1 707 894 7494",
    "sg:postcode":"95425",
    "sg:province":"CA",
    "sg:tags":[
        "body",
        "automobile",
        "painting"
    ],
    "wof:name":"Roux Body & Paint",
    "wof:placetype":"venue"
},
  "geometry": {"coordinates":[-123.009986,38.781967],"type":"Point"}
}