{
  "type": "Feature",
  "properties": {
    "iso:country":"US",
    "sg:address":"5920 Whitsett Ave Apt 6",
    "sg:city":"North Hollywood",
    "sg:classifiers":[
        {
            "category":"Professional",
            "subcategory":"Computer Services",
            "type":"Services"
        }
    ],
    "sg:phone":"+1 818 755 0149",
    "sg:postcode":"91607",
    "sg:province":"CA",
    "sg:tags":[
        "repair"
    ],
    "wof:name":"Esirco Master Inc",
    "wof:placetype":"venue"
},
  "geometry": {"coordinates":[-118.405081,34.177913],"type":"Point"}
}