{
  "type": "Feature",
  "properties": {
    "addr:full":"8490 Beverly Blvd Los Angeles CA 90048",
    "addr:housenumber":"8490",
    "addr:postcode":"90048",
    "addr:street":"Beverly Blvd",
    "iso:country":"US",
    "sg:address":"8490 Beverly Blvd",
    "sg:city":"Los Angeles",
    "sg:classifiers":[
        {
            "category":"Shopping",
            "subcategory":"Pharmacy",
            "type":"Retail Goods"
        }
    ],
    "sg:phone":"+1 323 653 4616",
    "sg:postcode":"90048",
    "sg:province":"CA",
    "wof:name":"Prescripton Department",
    "wof:placetype":"venue"
},
  "geometry": {"coordinates":[-118.37578999999999,34.075967],"type":"Point"}
}