{
  "type": "Feature",
  "properties": {
    "addr:full":"5825 Reseda Blvd Tarzana CA 91356",
    "addr:housenumber":"5825",
    "addr:postcode":"91356",
    "addr:street":"Reseda Blvd",
    "iso:country":"US",
    "sg:address":"5825 Reseda Blvd",
    "sg:city":"Tarzana",
    "sg:classifiers":[
        {
            "category":"Real Estate",
            "subcategory":"Real Estate Operator",
            "type":"Services"
        }
    ],
    "sg:phone":"+1 818 881 5253",
    "sg:postcode":"91356",
    "sg:province":"CA",
    "sg:tags":[
        "apartment"
    ],
    "wof:name":"Tarzana Springs",
    "wof:placetype":"venue"
},
  "geometry": {"coordinates":[-118.536007,34.176694],"type":"Point"}
}