{
  "type": "Feature",
  "properties": {
    "iso:country":"US",
    "sg:address":"9911 W Pico Blvd",
    "sg:city":"Los Angeles",
    "sg:classifiers":[
        {
            "category":"Health Services",
            "subcategory":"Doctor",
            "type":"Services"
        }
    ],
    "sg:phone":"+1 310 556 5446",
    "sg:postcode":"90035",
    "sg:province":"CA",
    "sg:tags":[
        "physician",
        "surgeon"
    ],
    "wof:name":"Terry V Eagan MD",
    "wof:placetype":"venue"
},
  "geometry": {"coordinates":[-118.404588,34.053257],"type":"Point"}
}