{
  "type": "Feature",
  "properties": {
    "addr:full":"714 N Michigan Ave Pasadena CA 91104",
    "addr:housenumber":"714",
    "addr:postcode":"91104",
    "addr:street":"N Michigan Ave",
    "iso:country":"US",
    "sg:address":"714 N Michigan Ave",
    "sg:city":"Pasadena",
    "sg:classifiers":[
        {
            "category":"Building & Trades",
            "subcategory":"Construction",
            "type":"Services"
        }
    ],
    "sg:phone":"+1 323 359 3827",
    "sg:postcode":"91104",
    "sg:province":"CA",
    "sg:tags":[
        "contractor"
    ],
    "wof:name":"Splinters Construction, Inc.",
    "wof:placetype":"venue"
},
  "geometry": {"coordinates":[-118.12520000000001,34.158339],"type":"Point"}
}