{
  "type": "Feature",
  "properties": {
    "iso:country":"US",
    "sg:address":"114 N Gateway Dr",
    "sg:city":"Madera",
    "sg:classifiers":[
        {
            "category":"Banks & Credit Unions",
            "subcategory":"Financial Services",
            "type":"Services"
        }
    ],
    "sg:phone":"+1 559 479 8260",
    "sg:postcode":"93637",
    "sg:province":"CA",
    "sg:tags":[
        "cashing",
        "check"
    ],
    "wof:name":"Mexpress",
    "wof:placetype":"venue"
},
  "geometry": {"coordinates":[-120.060697,36.96139],"type":"Point"}
}