{
  "type": "Feature",
  "properties": {
    "iso:country":"US",
    "sg:address":"1168 Phoenix Ave",
    "sg:city":"Seaside",
    "sg:classifiers":[
        {
            "category":"Food & Beverages",
            "subcategory":"Meat & Fish",
            "type":"Retail Goods"
        }
    ],
    "sg:phone":"+1 831 394 4961",
    "sg:postcode":"93955",
    "sg:province":"CA",
    "sg:tags":[
        "seafood"
    ],
    "wof:name":"Monterey Koi",
    "wof:placetype":"venue"
},
  "geometry": {"coordinates":[-121.84191199999999,36.613044],"type":"Point"}
}