{
  "type": "Feature",
  "properties": {
    "iso:country":"US",
    "sg:address":"22600-C Lambert St",
    "sg:city":"Lake Forest",
    "sg:classifiers":[
        {
            "category":"Shopping",
            "subcategory":"Crafts & Fabrics",
            "type":"Retail Goods"
        }
    ],
    "sg:phone":"+1 949 583 9336",
    "sg:postcode":"92630",
    "sg:province":"CA",
    "sg:tags":[
        "store"
    ],
    "sg:website":"sacredmoondance.com/",
    "wof:name":"Sacred Moondance",
    "wof:placetype":"venue"
},
  "geometry": {"coordinates":[-117.715379,33.635123],"type":"Point"}
}