{
  "type": "Feature",
  "properties": {
    "iso:country":"US",
    "sg:address":"2207 Candlewood Pl",
    "sg:city":"Riverbank",
    "sg:classifiers":[
        {
            "category":"Wholesale",
            "subcategory":"Machinery & Supplies",
            "type":"Manufacturing & Wholesale Goods"
        }
    ],
    "sg:phone":"+1 209 869 2062",
    "sg:postcode":"95367",
    "sg:province":"CA",
    "sg:tags":[
        "equipment",
        "establishment"
    ],
    "wof:name":"Rays Janitorial Supply",
    "wof:placetype":"venue"
},
  "geometry": {"coordinates":[-120.95657,37.735995],"type":"Point"}
}