{
  "type": "Feature",
  "properties": {
    "iso:country":"US",
    "sg:address":"9175 de Soto Ave",
    "sg:city":"Chatsworth",
    "sg:classifiers":[
        {
            "category":"Sports & Exercise",
            "subcategory":"Bowling",
            "type":"Entertainment"
        }
    ],
    "sg:phone":"+1 818 718 0193",
    "sg:postcode":"91311",
    "sg:province":"CA",
    "sg:tags":[
        "center"
    ],
    "wof:name":"San Fernando Bowling Assn",
    "wof:placetype":"venue"
},
  "geometry": {"coordinates":[-118.588611,34.23784],"type":"Point"}
}