{
  "type": "Feature",
  "properties": {
    "iso:country":"US",
    "sg:address":"1805 Central Ave",
    "sg:city":"Mckinleyville",
    "sg:classifiers":[
        {
            "category":"Professional",
            "subcategory":"Lawyer & Legal Services",
            "type":"Services"
        }
    ],
    "sg:phone":"+1 707 840 0909",
    "sg:postcode":"95519",
    "sg:province":"CA",
    "sg:tags":[
        "attorney"
    ],
    "wof:name":"Jason Garlick Attorney At Law",
    "wof:placetype":"venue"
},
  "geometry": {"coordinates":[-124.100774,40.937697],"type":"Point"}
}