{
  "type": "Feature",
  "properties": {
    "addr:full":"423 Whidbey St Morro Bay CA 93442",
    "addr:housenumber":"423",
    "addr:postcode":"93442",
    "addr:street":"Whidbey St",
    "iso:country":"US",
    "sg:address":"423 Whidbey St",
    "sg:city":"Morro Bay",
    "sg:classifiers":[
        {
            "category":"Retail",
            "subcategory":"Repair Shop",
            "type":"Services"
        }
    ],
    "sg:phone":"+1 805 637 2511",
    "sg:postcode":"93442",
    "sg:province":"CA",
    "sg:tags":[
        "cleaning",
        "boat"
    ],
    "wof:name":"Russell Burkman",
    "wof:placetype":"venue"
},
  "geometry": {"coordinates":[-120.86606399999999,35.405196],"type":"Point"}
}