{
  "type": "Feature",
  "properties": {
    "addr:full":"19036 Saratoga Glen Pl Saratoga CA 95070",
    "addr:housenumber":"19036",
    "addr:postcode":"95070",
    "addr:street":"Saratoga Glen Pl",
    "iso:country":"US",
    "sg:address":"19036 Saratoga Glen Pl",
    "sg:city":"Saratoga",
    "sg:classifiers":[
        {
            "category":"Shopping",
            "type":"Retail Goods"
        }
    ],
    "sg:phone":"+1 408 446 5286",
    "sg:postcode":"95070",
    "sg:province":"CA",
    "sg:tags":[
        "merchandise"
    ],
    "wof:name":"Bay Vent Medical",
    "wof:placetype":"venue"
},
  "geometry": {"coordinates":[-122.00214,37.282562],"type":"Point"}
}