{
  "type": "Feature",
  "properties": {
    "iso:country":"US",
    "sg:address":"571 E Perkins St",
    "sg:city":"Ukiah",
    "sg:classifiers":[
        {
            "category":"Professional",
            "subcategory":"Detective & Security Services",
            "type":"Services"
        }
    ],
    "sg:phone":"+1 707 489 7948",
    "sg:postcode":"95482",
    "sg:province":"CA",
    "sg:tags":[
        "investigator"
    ],
    "wof:name":"Mc Bride Truth Verification",
    "wof:placetype":"venue"
},
  "geometry": {"coordinates":[-123.199093,39.151401],"type":"Point"}
}