{
  "type": "Feature",
  "properties": {
    "addr:full":"1050 Kettner Blvd San Diego CA 92101",
    "addr:housenumber":"1050",
    "addr:postcode":"92101",
    "addr:street":"Kettner Blvd",
    "iso:country":"US",
    "sg:address":"1050 Kettner Blvd",
    "sg:city":"San Diego",
    "sg:classifiers":[
        {
            "category":"Local Transit",
            "type":"Transportation"
        }
    ],
    "sg:phone":"+1 619 239 4664",
    "sg:postcode":"92101",
    "sg:province":"CA",
    "sg:tags":[
        "management"
    ],
    "wof:name":"Amtrak",
    "wof:placetype":"venue"
},
  "geometry": {"coordinates":[-117.169242,32.715905],"type":"Point"}
}