{
  "type": "Feature",
  "properties": {
    "addr:full":"9830 Reseda Blvd Northridge CA 91324",
    "addr:housenumber":"9830",
    "addr:postcode":"91324",
    "addr:street":"Reseda Blvd",
    "iso:country":"US",
    "sg:address":"9830 Reseda Blvd",
    "sg:city":"Northridge",
    "sg:classifiers":[
        {
            "category":"Real Estate",
            "subcategory":"Real Estate Operator",
            "type":"Services"
        }
    ],
    "sg:phone":"+1 818 349 6682",
    "sg:postcode":"91324",
    "sg:province":"CA",
    "sg:tags":[
        "apartment"
    ],
    "wof:name":"Candlewood North Apartments",
    "wof:placetype":"venue"
},
  "geometry": {"coordinates":[-118.536091,34.248597],"type":"Point"}
}