{
  "type": "Feature",
  "properties": {
    "addr:full":"5950 Harrison Ave Corona CA 92880",
    "addr:housenumber":"5950",
    "addr:postcode":"92880",
    "addr:street":"Harrison Ave",
    "iso:country":"US",
    "sg:address":"5950 Harrison Ave",
    "sg:city":"Corona",
    "sg:classifiers":[
        {
            "category":"Farming",
            "subcategory":"Dairy Farm",
            "type":"Manufacturing & Wholesale Goods"
        }
    ],
    "sg:phone":"+1 909 947 3826",
    "sg:postcode":"92880",
    "sg:province":"CA",
    "wof:name":"Brothers Three Dairy",
    "wof:placetype":"venue"
},
  "geometry": {"coordinates":[-117.584273,33.976071],"type":"Point"}
}