{
  "type": "Feature",
  "properties": {
    "iso:country":"US",
    "sg:address":"861 N Vine St",
    "sg:city":"Los Angeles",
    "sg:classifiers":[
        {
            "category":"Shopping",
            "subcategory":"Pharmacy",
            "type":"Retail Goods"
        }
    ],
    "sg:phone":"+1 323 466 7300",
    "sg:postcode":"90038",
    "sg:province":"CA",
    "sg:tags":[
        "drugstore"
    ],
    "sg:website":"www.cvs.com",
    "wof:name":"CVS",
    "wof:placetype":"venue"
},
  "geometry": {"coordinates":[-118.326634,34.086382],"type":"Point"}
}