{
  "type": "Feature",
  "properties": {
    "iso:country":"US",
    "sg:address":"841 Chautauqua Blvd",
    "sg:city":"Pacific Plsds",
    "sg:classifiers":[
        {
            "category":"Real Estate",
            "subcategory":"Architect",
            "type":"Services"
        }
    ],
    "sg:phone":"+1 310 230 3378",
    "sg:postcode":"90272",
    "sg:province":"CA",
    "wof:name":"James L Tyler Architects Inc",
    "wof:placetype":"venue"
},
  "geometry": {"coordinates":[-118.517386,34.044105],"type":"Point"}
}