{
  "type": "Feature",
  "properties": {
    "iso:country":"US",
    "sg:address":"225 McMurray Rd",
    "sg:city":"Buellton",
    "sg:classifiers":[
        {
            "category":"Restaurant",
            "type":"Food & Drink"
        }
    ],
    "sg:phone":"+1 805 686 9001",
    "sg:postcode":"93427",
    "sg:province":"CA",
    "wof:name":"ARU Japanese Restaurant",
    "wof:placetype":"venue"
},
  "geometry": {"coordinates":[-120.188912,34.611593],"type":"Point"}
}