{
  "type": "Feature",
  "properties": {
    "iso:country":"US",
    "sg:address":"2137 E Wilson Ave",
    "sg:city":"Orange",
    "sg:classifiers":[
        {
            "category":"Building & Trades",
            "subcategory":"Construction",
            "type":"Services"
        }
    ],
    "sg:phone":"+1 714 628 9425",
    "sg:postcode":"92867",
    "sg:province":"CA",
    "sg:tags":[
        "contractor"
    ],
    "wof:name":"Mattson & Mattson Construction Inc",
    "wof:placetype":"venue"
},
  "geometry": {"coordinates":[-117.83011500000001,33.8076],"type":"Point"}
}