{
  "type": "Feature",
  "properties": {
    "iso:country":"US",
    "sg:address":"220 S Spruce Ave",
    "sg:city":"S San Francisco",
    "sg:classifiers":[
        {
            "category":"Professional",
            "subcategory":"Management & Consulting",
            "type":"Services"
        }
    ],
    "sg:phone":"+1 650 872 8318",
    "sg:postcode":"94080",
    "sg:province":"CA",
    "sg:tags":[
        "facility"
    ],
    "wof:name":"One Source",
    "wof:placetype":"venue"
},
  "geometry": {"coordinates":[-122.419041,37.648199],"type":"Point"}
}