{
  "type": "Feature",
  "properties": {
    "iso:country":"US",
    "sg:address":"938 W 50th St",
    "sg:city":"Los Angeles",
    "sg:classifiers":[
        {
            "category":"Building & Trades",
            "subcategory":"Locksmith",
            "type":"Services"
        }
    ],
    "sg:phone":"+1 323 752 1105",
    "sg:postcode":"90037",
    "sg:province":"CA",
    "sg:tags":[
        "key"
    ],
    "wof:name":"Immediate Locksmith Service",
    "wof:placetype":"venue"
},
  "geometry": {"coordinates":[-118.290492,33.997594],"type":"Point"}
}