{
  "type": "Feature",
  "properties": {
    "iso:country":"US",
    "sg:address":"541 S Yucca Ave",
    "sg:city":"Rialto",
    "sg:classifiers":[
        {
            "category":"Shopping",
            "subcategory":"Computers & Home Electronics",
            "type":"Retail Goods"
        }
    ],
    "sg:phone":"+1 909 728 0744",
    "sg:postcode":"92376",
    "sg:province":"CA",
    "sg:tags":[
        "equipment",
        "electronic",
        "supply"
    ],
    "wof:name":"Fun-Tastic Electronics",
    "wof:placetype":"venue"
},
  "geometry": {"coordinates":[-117.382743,34.091461],"type":"Point"}
}