{
  "type": "Feature",
  "properties": {
    "addr:full":"2001 2nd St Davis CA 95618",
    "addr:housenumber":"2001",
    "addr:postcode":"95618",
    "addr:street":"2Nd St",
    "iso:country":"US",
    "sg:address":"2001 2nd St",
    "sg:city":"Davis",
    "sg:classifiers":[
        {
            "category":"Government",
            "subcategory":"Office",
            "type":"Public Place"
        }
    ],
    "sg:phone":"+1 530 750 0135",
    "sg:postcode":"95618",
    "sg:province":"CA",
    "sg:tags":[
        "educational",
        "program",
        "administrative"
    ],
    "wof:name":"Association Efcnt Envrmntal",
    "wof:placetype":"venue"
},
  "geometry": {"coordinates":[-121.720024,38.54794],"type":"Point"}
}