{
  "type": "Feature",
  "properties": {
    "iso:country":"US",
    "sg:address":"100 Ponderosa Ct",
    "sg:city":"Folsom",
    "sg:classifiers":[
        {
            "category":"Home & Garden",
            "subcategory":"Furniture",
            "type":"Retail Goods"
        }
    ],
    "sg:phone":"+1 916 628 5112",
    "sg:postcode":"95630",
    "sg:province":"CA",
    "sg:tags":[
        "equipment",
        "kitchen",
        "cabinet"
    ],
    "wof:name":"Kitchens Made New",
    "wof:placetype":"venue"
},
  "geometry": {"coordinates":[-121.140986,38.679442],"type":"Point"}
}