{
  "type": "Feature",
  "properties": {
    "addr:full":"7 N Ridgewood Rd Kentfield CA 94904",
    "addr:housenumber":"7",
    "addr:postcode":"94904",
    "addr:street":"N Ridgewood Rd",
    "iso:country":"US",
    "sg:address":"7 N Ridgewood Rd",
    "sg:city":"Kentfield",
    "sg:classifiers":[
        {
            "category":"Real Estate",
            "subcategory":"Real Estate Agent",
            "type":"Services"
        }
    ],
    "sg:phone":"+1 415 461 7194",
    "sg:postcode":"94904",
    "sg:province":"CA",
    "wof:name":"Margie Smith Real Estate",
    "wof:placetype":"venue"
},
  "geometry": {"coordinates":[-122.558412,37.949687],"type":"Point"}
}