{
  "type": "Feature",
  "properties": {
    "addr:full":"6921 Roseville Rd Sacramento CA 95842",
    "addr:housenumber":"6921",
    "addr:postcode":"95842",
    "addr:street":"Roseville Rd",
    "iso:country":"US",
    "sg:address":"6921 Roseville Rd",
    "sg:city":"Sacramento",
    "sg:classifiers":[
        {
            "category":"Professional",
            "type":"Services"
        }
    ],
    "sg:phone":"+1 916 834 2233",
    "sg:postcode":"95842",
    "sg:province":"CA",
    "sg:website":"www.icadd.com",
    "wof:name":"Professional CADD Services",
    "wof:placetype":"venue"
},
  "geometry": {"coordinates":[-121.343835,38.69331],"type":"Point"}
}