{
  "type": "Feature",
  "properties": {
    "addr:full":"14985 W Whitesbridge Ave Kerman CA 93630",
    "addr:housenumber":"14985",
    "addr:postcode":"93630",
    "addr:street":"W Whitesbridge Ave",
    "iso:country":"US",
    "sg:address":"14985 W Whitesbridge Ave",
    "sg:city":"Kerman",
    "sg:classifiers":[
        {
            "category":"Autos & Motor Vehicles",
            "subcategory":"Fuel & Gas Station",
            "type":"Retail Goods"
        }
    ],
    "sg:phone":"+1 559 846 9569",
    "sg:postcode":"93630",
    "sg:province":"CA",
    "sg:tags":[
        "oil"
    ],
    "wof:name":"George's Beacon Svc Station",
    "wof:placetype":"venue"
},
  "geometry": {"coordinates":[-120.058318,36.734857],"type":"Point"}
}