{
  "type": "Feature",
  "properties": {
    "iso:country":"US",
    "sg:address":"1208 W Shields Ave",
    "sg:city":"Fresno",
    "sg:classifiers":[
        {
            "category":"Shopping",
            "subcategory":"Party Supplies",
            "type":"Retail Goods"
        },
        {
            "category":"Shopping",
            "subcategory":"Bridal",
            "type":"Retail Goods"
        }
    ],
    "sg:phone":"+1 559 227 4318",
    "sg:postcode":"93705",
    "sg:province":"CA",
    "sg:tags":[
        "shop",
        "wedding"
    ],
    "wof:name":"Glamourous Bridal Shop",
    "wof:placetype":"venue"
},
  "geometry": {"coordinates":[-119.82550500000001,36.779319],"type":"Point"}
}