{
  "type": "Feature",
  "properties": {
    "addr:full":"4801 Fair Ave Oakland CA 94619",
    "addr:housenumber":"4801",
    "addr:postcode":"94619",
    "addr:street":"Fair Ave",
    "iso:country":"US",
    "sg:address":"4801 Fair Ave",
    "sg:city":"Oakland",
    "sg:classifiers":[
        {
            "category":"Building & Trades",
            "subcategory":"Landscaping Services",
            "type":"Services"
        }
    ],
    "sg:phone":"+1 510 530 8749",
    "sg:postcode":"94619",
    "sg:province":"CA",
    "wof:name":"D J Tree Service",
    "wof:placetype":"venue"
},
  "geometry": {"coordinates":[-122.183216,37.784818],"type":"Point"}
}