{
  "type": "Feature",
  "properties": {
    "iso:country":"US",
    "sg:address":"9530 Owensmouth Ave",
    "sg:city":"Chatsworth",
    "sg:classifiers":[
        {
            "category":"Wholesale",
            "subcategory":"Machinery & Supplies",
            "type":"Manufacturing & Wholesale Goods"
        },
        {
            "category":"Wholesale",
            "subcategory":"Durable Goods & Equipment",
            "type":"Manufacturing & Wholesale Goods"
        }
    ],
    "sg:phone":"+1 818 717 3035",
    "sg:postcode":"91311",
    "sg:province":"CA",
    "sg:tags":[
        "janitor"
    ],
    "wof:name":"Econoline Industrial Supplies",
    "wof:placetype":"venue"
},
  "geometry": {"coordinates":[-118.601591,34.246989],"type":"Point"}
}