{
  "type": "Feature",
  "properties": {
    "iso:country":"US",
    "sg:address":"1415 Innes Pl",
    "sg:city":"Venice",
    "sg:classifiers":[
        {
            "category":"Professional",
            "subcategory":"Business Services",
            "type":"Services"
        }
    ],
    "sg:phone":"+1 310 779 4697",
    "sg:postcode":"90291",
    "sg:province":"CA",
    "wof:name":"Earthtone Sound",
    "wof:placetype":"venue"
},
  "geometry": {"coordinates":[-118.472224,33.988696],"type":"Point"}
}