{
  "type": "Feature",
  "properties": {
    "addr:full":"3608 Arden Dr El Monte CA 91731",
    "addr:housenumber":"3608",
    "addr:postcode":"91731",
    "addr:street":"Arden Dr",
    "iso:country":"US",
    "sg:address":"3608 Arden Dr",
    "sg:city":"El Monte",
    "sg:classifiers":[
        {
            "category":"Wholesale",
            "subcategory":"Durable Goods & Equipment",
            "type":"Manufacturing & Wholesale Goods"
        }
    ],
    "sg:phone":"+1 626 350 6982",
    "sg:postcode":"91731",
    "sg:province":"CA",
    "sg:tags":[
        "importer"
    ],
    "sg:website":"www.tmcusa.com",
    "wof:name":"TMC Trading Inc",
    "wof:placetype":"venue"
},
  "geometry": {"coordinates":[-118.046722,34.07407],"type":"Point"}
}