{
  "type": "Feature",
  "properties": {
    "iso:country":"US",
    "sg:address":"24811 San Fernando Rd",
    "sg:city":"Newhall",
    "sg:classifiers":[
        {
            "category":"Professional",
            "type":"Services"
        },
        {
            "category":"Shopping",
            "subcategory":"Florist",
            "type":"Retail Goods"
        }
    ],
    "sg:phone":"+1 661 254 5777",
    "sg:postcode":"91321",
    "sg:province":"CA",
    "wof:name":"Bloomin' Quick",
    "wof:placetype":"venue"
},
  "geometry": {"coordinates":[-118.532397,34.38608],"type":"Point"}
}