{
  "type": "Feature",
  "properties": {
    "iso:country":"US",
    "sg:address":"12511 San Mateo Rd",
    "sg:city":"Half Moon Bay",
    "sg:classifiers":[
        {
            "category":"Wholesale",
            "subcategory":"Plants",
            "type":"Manufacturing & Wholesale Goods"
        }
    ],
    "sg:phone":"+1 650 726 4000",
    "sg:postcode":"94019",
    "sg:province":"CA",
    "sg:tags":[
        "florist"
    ],
    "wof:name":"Pastorino & Sons Nursery",
    "wof:placetype":"venue"
},
  "geometry": {"coordinates":[-122.38661399999999,37.491999],"type":"Point"}
}