{
  "type": "Feature",
  "properties": {
    "addr:full":"4667 N Blythe Ave Fresno CA 93722",
    "addr:housenumber":"4667",
    "addr:postcode":"93722",
    "addr:street":"N Blythe Ave",
    "iso:country":"US",
    "sg:address":"4667 N Blythe Ave",
    "sg:city":"Fresno",
    "sg:classifiers":[
        {
            "category":"Building & Trades",
            "subcategory":"Pest Control",
            "type":"Services"
        }
    ],
    "sg:phone":"+1 559 237 1560",
    "sg:postcode":"93722",
    "sg:province":"CA",
    "wof:name":"Tanner Fumigation Specialists",
    "wof:placetype":"venue"
},
  "geometry": {"coordinates":[-119.872703,36.806106],"type":"Point"}
}