{
  "type": "Feature",
  "properties": {
    "addr:full":"101 Pacifica Irvine CA 92618",
    "addr:housenumber":"101",
    "addr:postcode":"92618",
    "addr:street":"Pacifica",
    "iso:country":"US",
    "sg:address":"101 Pacifica",
    "sg:city":"Irvine",
    "sg:classifiers":[
        {
            "category":"Professional",
            "subcategory":"Lawyer & Legal Services",
            "type":"Services"
        }
    ],
    "sg:phone":"+1 949 753 7538",
    "sg:postcode":"92618",
    "sg:province":"CA",
    "wof:name":"Nyman & Demattia",
    "wof:placetype":"venue"
},
  "geometry": {"coordinates":[-117.754997,33.658401],"type":"Point"}
}