{
  "type": "Feature",
  "properties": {
    "addr:full":"951 Pacific Ave Long Beach CA 90813",
    "addr:housenumber":"951",
    "addr:postcode":"90813",
    "addr:street":"Pacific Ave",
    "iso:country":"US",
    "sg:address":"951 Pacific Ave",
    "sg:city":"Long Beach",
    "sg:classifiers":[
        {
            "category":"Real Estate",
            "subcategory":"Real Estate Operator",
            "type":"Services"
        }
    ],
    "sg:phone":"+1 562 432 1793",
    "sg:postcode":"90813",
    "sg:province":"CA",
    "sg:tags":[
        "apartment"
    ],
    "wof:name":"Rob-Ho Properties Service",
    "wof:placetype":"venue"
},
  "geometry": {"coordinates":[-118.194,33.7789],"type":"Point"}
}