{
  "type": "Feature",
  "properties": {
    "addr:full":"6364 Hollywood Blvd Los Angeles CA 90028",
    "addr:housenumber":"6364",
    "addr:postcode":"90028",
    "addr:street":"Hollywood Blvd",
    "iso:country":"US",
    "sg:address":"6364 Hollywood Blvd",
    "sg:city":"Los Angeles",
    "sg:classifiers":[
        {
            "category":"Recreation",
            "subcategory":"Dance Hall",
            "type":"Entertainment"
        }
    ],
    "sg:postcode":"90028",
    "sg:province":"CA",
    "sg:tags":[
        "club"
    ],
    "sg:website":"www.vicehollywood.com",
    "wof:name":"Vice",
    "wof:placetype":"venue"
},
  "geometry": {"coordinates":[-118.328706,34.101594],"type":"Point"}
}