{
  "type": "Feature",
  "properties": {
    "addr:full":"5423 Central Ave Newark CA 94560",
    "addr:housenumber":"5423",
    "addr:postcode":"94560",
    "addr:street":"Central Ave",
    "iso:country":"US",
    "sg:address":"5423 Central Ave",
    "sg:city":"Newark",
    "sg:classifiers":[
        {
            "category":"Food & Beverages",
            "subcategory":"Specialty",
            "type":"Retail Goods"
        },
        {
            "category":"Manufacturing",
            "subcategory":"Food",
            "type":"Manufacturing & Wholesale Goods"
        }
    ],
    "sg:phone":"+1 510 894 4746",
    "sg:postcode":"94560",
    "sg:province":"CA",
    "sg:tags":[
        "spices-wholesale",
        "spice",
        "manufacturer"
    ],
    "wof:name":"Saaed Enterprises",
    "wof:placetype":"venue"
},
  "geometry": {"coordinates":[-122.01736,37.539241],"type":"Point"}
}