{
  "type": "Feature",
  "properties": {
    "iso:country":"US",
    "sg:address":"11 Wiltshire Ave",
    "sg:city":"Larkspur",
    "sg:classifiers":[
        {
            "category":"Professional",
            "type":"Services"
        }
    ],
    "sg:phone":"+1 415 927 3478",
    "sg:postcode":"94939",
    "sg:province":"CA",
    "wof:name":"Virginia Desin",
    "wof:placetype":"venue"
},
  "geometry": {"coordinates":[-122.533233,37.928322],"type":"Point"}
}