{
  "type": "Feature",
  "properties": {
    "addr:full":"20 S Ocean Ave Cayucos CA 93430",
    "addr:housenumber":"20",
    "addr:postcode":"93430",
    "addr:street":"S Ocean Ave",
    "iso:country":"US",
    "sg:address":"20 S Ocean Ave",
    "sg:city":"Cayucos",
    "sg:classifiers":[
        {
            "category":"Travel",
            "subcategory":"Hotels & Motels",
            "type":"Entertainment"
        }
    ],
    "sg:phone":"+1 805 995 3670",
    "sg:postcode":"93430",
    "sg:province":"CA",
    "sg:website":"www.cayucosmotel.com",
    "wof:name":"Cayucos Motel",
    "wof:placetype":"venue"
},
  "geometry": {"coordinates":[-120.90300000000001,35.447899],"type":"Point"}
}