{
  "type": "Feature",
  "properties": {
    "iso:country":"US",
    "sg:address":"3301 E Coast Hwy",
    "sg:city":"Corona Del Mar",
    "sg:classifiers":[
        {
            "category":"Real Estate",
            "subcategory":"Real Estate Agent",
            "type":"Services"
        }
    ],
    "sg:phone":"+1 949 723 7080",
    "sg:postcode":"92625",
    "sg:province":"CA",
    "wof:name":"Prudential",
    "wof:placetype":"venue"
},
  "geometry": {"coordinates":[-117.87013899999999,33.595701],"type":"Point"}
}