{
  "type": "Feature",
  "properties": {
    "addr:full":"4542 Sunnyslope Ave Sherman Oaks CA 91423",
    "addr:housenumber":"4542",
    "addr:postcode":"91423",
    "addr:street":"Sunnyslope Ave",
    "iso:country":"US",
    "sg:address":"4542 Sunnyslope Ave",
    "sg:city":"Sherman Oaks",
    "sg:classifiers":[
        {
            "category":"Professional",
            "subcategory":"Accounting & Tax Preparation",
            "type":"Services"
        }
    ],
    "sg:phone":"+1 818 907 6190",
    "sg:postcode":"91423",
    "sg:province":"CA",
    "sg:tags":[
        "accountant"
    ],
    "wof:name":"Borsuk Robert M CPA",
    "wof:placetype":"venue"
},
  "geometry": {"coordinates":[-118.427002,34.153099],"type":"Point"}
}