{
  "type": "Feature",
  "properties": {
    "addr:full":"341 S Lincoln Ave Corona CA 92882",
    "addr:housenumber":"341",
    "addr:postcode":"92882",
    "addr:street":"S Lincoln Ave",
    "iso:country":"US",
    "sg:address":"341 S Lincoln Ave",
    "sg:city":"Corona",
    "sg:classifiers":[
        {
            "category":"Health Services",
            "subcategory":"Doctor",
            "type":"Services"
        }
    ],
    "sg:phone":"+1 951 520 8221",
    "sg:postcode":"92882",
    "sg:province":"CA",
    "sg:tags":[
        "dentist"
    ],
    "wof:name":"Susan H Lee DDS",
    "wof:placetype":"venue"
},
  "geometry": {"coordinates":[-117.582903,33.878643],"type":"Point"}
}