{
  "type": "Feature",
  "properties": {
    "iso:country":"US",
    "sg:address":"29 E 16th St",
    "sg:city":"Merced",
    "sg:classifiers":[
        {
            "category":"Wholesale",
            "subcategory":"Jewelry",
            "type":"Manufacturing & Wholesale Goods"
        }
    ],
    "sg:phone":"+1 209 726 4680",
    "sg:postcode":"95340",
    "sg:province":"CA",
    "sg:tags":[
        "stone",
        "jeweler"
    ],
    "wof:name":"Olivia's Fine Jewelry",
    "wof:placetype":"venue"
},
  "geometry": {"coordinates":[-120.47581,37.297512],"type":"Point"}
}