{
  "type": "Feature",
  "properties": {
    "iso:country":"US",
    "sg:address":"8950 Villa La Jolla Dr Ste C225",
    "sg:city":"La Jolla",
    "sg:classifiers":[
        {
            "category":"Education",
            "subcategory":"University",
            "type":"Public Place"
        }
    ],
    "sg:phone":"+1 858 534 8638",
    "sg:postcode":"92037",
    "sg:province":"CA",
    "sg:tags":[
        "college"
    ],
    "wof:name":"San Diego Dialogue",
    "wof:placetype":"venue"
},
  "geometry": {"coordinates":[-117.234061,32.871117],"type":"Point"}
}