{
  "type": "Feature",
  "properties": {
    "addr:full":"8701 S Broadway Los Angeles CA 90003",
    "addr:housenumber":"8701",
    "addr:postcode":"90003",
    "addr:street":"S Broadway",
    "iso:country":"US",
    "sg:address":"8701 S Broadway",
    "sg:city":"Los Angeles",
    "sg:classifiers":[
        {
            "category":"Shopping",
            "subcategory":"Clothing, Apparel, & Fashions",
            "type":"Retail Goods"
        }
    ],
    "sg:phone":"+1 323 752 1290",
    "sg:postcode":"90003",
    "sg:province":"CA",
    "sg:tags":[
        "furnishing"
    ],
    "wof:name":"Gottawear",
    "wof:placetype":"venue"
},
  "geometry": {"coordinates":[-118.27821,33.958622],"type":"Point"}
}