{
  "type": "Feature",
  "properties": {
    "addr:full":"2398 Fair Oaks Boulevard Suite 8 Sacramento CA 95825",
    "addr:housenumber":"2398",
    "addr:postcode":"95825",
    "addr:street":"Fair Oaks Boulevard Suite 8",
    "iso:country":"US",
    "sg:address":"2398 Fair Oaks Boulevard Suite 8",
    "sg:city":"Sacramento",
    "sg:classifiers":[
        {
            "category":"Professional",
            "subcategory":"Lawyer & Legal Services",
            "type":"Services"
        }
    ],
    "sg:phone":"+1 916 923 2900",
    "sg:postcode":"95825",
    "sg:province":"CA",
    "sg:tags":[
        "divorce",
        "law",
        "family"
    ],
    "sg:website":"harmslaw.net",
    "wof:name":"Harms Carla D Atty",
    "wof:placetype":"venue"
},
  "geometry": {"coordinates":[-121.405968,38.573751],"type":"Point"}
}