{
  "type": "Feature",
  "properties": {
    "addr:full":"3303 Hillview Ave Palo Alto CA 94304",
    "addr:housenumber":"3303",
    "addr:postcode":"94304",
    "addr:street":"Hillview Ave",
    "iso:country":"US",
    "sg:address":"3303 Hillview Ave",
    "sg:city":"Palo Alto",
    "sg:classifiers":[
        {
            "category":"Professional",
            "subcategory":"Computer Services",
            "type":"Services"
        }
    ],
    "sg:phone":"+1 650 846 1000",
    "sg:postcode":"94304",
    "sg:province":"CA",
    "sg:tags":[
        "design",
        "system",
        "programing",
        "custom"
    ],
    "wof:name":"Tibco",
    "wof:placetype":"venue"
},
  "geometry": {"coordinates":[-122.145749,37.404821],"type":"Point"}
}