{
  "type": "Feature",
  "properties": {
    "iso:country":"US",
    "sg:address":"28150 Ave Crocker",
    "sg:city":"Santa Clarita",
    "sg:classifiers":[
        {
            "category":"Food & Beverages",
            "subcategory":"Groceries & Convenience Stores",
            "type":"Retail Goods"
        },
        {
            "category":"Manufacturing",
            "subcategory":"Food",
            "type":"Manufacturing & Wholesale Goods"
        }
    ],
    "sg:phone":"+1 661 257 2273",
    "sg:postcode":"91355",
    "sg:province":"CA",
    "sg:tags":[
        "product",
        "mfg"
    ],
    "wof:name":"Leyao Food",
    "wof:placetype":"venue"
},
  "geometry": {"coordinates":[-118.587081,34.437024],"type":"Point"}
}