{
  "type": "Feature",
  "properties": {
    "addr:full":"200 Valley Blvd Tehachapi CA 93561",
    "addr:housenumber":"200",
    "addr:postcode":"93561",
    "addr:street":"Valley Blvd",
    "iso:country":"US",
    "sg:address":"200 Valley Blvd",
    "sg:city":"Tehachapi",
    "sg:classifiers":[
        {
            "category":"Real Estate",
            "subcategory":"Real Estate Agent",
            "type":"Services"
        }
    ],
    "sg:phone":"+1 661 822 9769",
    "sg:postcode":"93561",
    "sg:province":"CA",
    "wof:name":"Tehachapi Homebuyers Ctr",
    "wof:placetype":"venue"
},
  "geometry": {"coordinates":[-118.45161,35.124313],"type":"Point"}
}