{
  "type": "Feature",
  "properties": {
    "addr:full":"6469 University Avenue San Diego CA 92115",
    "addr:housenumber":"6469",
    "addr:postcode":"92115",
    "addr:street":"University Avenue",
    "iso:country":"US",
    "sg:address":"6469 University Avenue",
    "sg:city":"San Diego",
    "sg:classifiers":[
        {
            "category":"Retail",
            "subcategory":"Laundry & Dry Cleaning",
            "type":"Services"
        }
    ],
    "sg:phone":"+1 619 286 3284",
    "sg:postcode":"92115",
    "sg:province":"CA",
    "wof:name":"University Cleaners",
    "wof:placetype":"venue"
},
  "geometry": {"coordinates":[-117.056388,32.755366],"type":"Point"}
}