{
  "type": "Feature",
  "properties": {
    "iso:country":"US",
    "sg:address":"4700 Lang Ave",
    "sg:city":"Mcclellan",
    "sg:classifiers":[
        {
            "category":"Wholesale",
            "subcategory":"Machinery & Supplies",
            "type":"Manufacturing & Wholesale Goods"
        }
    ],
    "sg:phone":"+1 916 568 1500",
    "sg:postcode":"95652",
    "sg:province":"CA",
    "sg:tags":[
        "industrial",
        "machinery-new",
        "equipment",
        "used",
        "supplies-wholesale"
    ],
    "sg:website":"http://www.scottmachinery.com",
    "wof:name":"Scott Machinery",
    "wof:placetype":"venue"
},
  "geometry": {"coordinates":[-121.42134299999999,38.652759],"type":"Point"}
}