{
  "type": "Feature",
  "properties": {
    "addr:full":"48451 Harrison St Coachella CA 92236",
    "addr:housenumber":"48451",
    "addr:postcode":"92236",
    "addr:street":"Harrison St",
    "iso:country":"US",
    "sg:address":"48451 Harrison St",
    "sg:city":"Coachella",
    "sg:classifiers":[
        {
            "category":"Wholesale",
            "subcategory":"Scrap",
            "type":"Manufacturing & Wholesale Goods"
        }
    ],
    "sg:phone":"+1 760 398 0106",
    "sg:postcode":"92236",
    "sg:province":"CA",
    "sg:tags":[
        "auto",
        "material",
        "parts",
        "used"
    ],
    "wof:name":"Desert Truck & Auto Parts",
    "wof:placetype":"venue"
},
  "geometry": {"coordinates":[-116.181631,33.698509],"type":"Point"}
}