{
  "type": "Feature",
  "properties": {
    "addr:full":"6288 Sheridan Way Buena Park CA 90620",
    "addr:housenumber":"6288",
    "addr:postcode":"90620",
    "addr:street":"Sheridan Way",
    "iso:country":"US",
    "sg:address":"6288 Sheridan Way",
    "sg:city":"Buena Park",
    "sg:classifiers":[
        {
            "category":"Autos & Motor Vehicles",
            "subcategory":"Auto Supplies",
            "type":"Retail Goods"
        }
    ],
    "sg:phone":"+1 714 523 1409",
    "sg:postcode":"90620",
    "sg:province":"CA",
    "sg:tags":[
        "glass"
    ],
    "wof:name":"Cypress Auto Glass",
    "wof:placetype":"venue"
},
  "geometry": {"coordinates":[-118.343357,33.855082],"type":"Point"}
}