{
  "type": "Feature",
  "properties": {
    "iso:country":"US",
    "sg:address":"1311 Orleans Drive",
    "sg:city":"Sunnyvale",
    "sg:classifiers":[
        {
            "category":"Professional",
            "subcategory":"Research",
            "type":"Services"
        }
    ],
    "sg:phone":"+1 800 635 5577",
    "sg:postcode":"94089",
    "sg:province":"CA",
    "sg:tags":[
        "bioanalytical",
        "analytical",
        "systems",
        "solutions",
        "instruments",
        "software",
        "reagents",
        "equipment"
    ],
    "sg:website":"http://www.moleculardevices.com/",
    "wof:name":"Molecular Devices",
    "wof:placetype":"venue"
},
  "geometry": {"coordinates":[-122.008077,37.407515],"type":"Point"}
}