{
  "type": "Feature",
  "properties": {
    "iso:country":"US",
    "sg:address":"759 W Main St",
    "sg:city":"El Centro",
    "sg:classifiers":[
        {
            "category":"Insurance",
            "subcategory":"Insurance Agent",
            "type":"Services"
        }
    ],
    "sg:phone":"+1 760 352 9676",
    "sg:postcode":"92243",
    "sg:province":"CA",
    "wof:name":"Mortgage Protection Insur Svcs",
    "wof:placetype":"venue"
},
  "geometry": {"coordinates":[-115.559882,32.792762],"type":"Point"}
}