{
  "type": "Feature",
  "properties": {
    "iso:country":"US",
    "sg:address":"1819 Yettford Rd",
    "sg:city":"Vista",
    "sg:classifiers":[
        {
            "category":"Banks & Credit Unions",
            "subcategory":"Financial Services",
            "type":"Services"
        }
    ],
    "sg:phone":"+1 760 941 5796",
    "sg:postcode":"92083",
    "sg:province":"CA",
    "sg:tags":[
        "trust",
        "management"
    ],
    "wof:name":"Cadenhead Family Trust",
    "wof:placetype":"venue"
},
  "geometry": {"coordinates":[-117.21951900000001,33.174082],"type":"Point"}
}