{
  "type": "Feature",
  "properties": {
    "addr:full":"530 N Coast Hwy 101 Encinitas CA 92024",
    "addr:housenumber":"530",
    "addr:postcode":"92024",
    "addr:street":"N Coast Hwy 101",
    "iso:country":"US",
    "sg:address":"530 N Coast Hwy 101",
    "sg:city":"Encinitas",
    "sg:classifiers":[
        {
            "category":"Shopping",
            "subcategory":"Clothing, Apparel, & Fashions",
            "type":"Retail Goods"
        },
        {
            "category":"Shopping",
            "subcategory":"Jewelry",
            "type":"Retail Goods"
        }
    ],
    "sg:phone":"+1 760 753 4822",
    "sg:postcode":"92024",
    "sg:province":"CA",
    "sg:tags":[
        "clothing",
        "women's"
    ],
    "wof:name":"Lorielle Apparel & Gifts",
    "wof:placetype":"venue"
},
  "geometry": {"coordinates":[-117.29993399999999,33.05888],"type":"Point"}
}