{
  "type": "Feature",
  "properties": {
    "iso:country":"US",
    "sg:address":"1629 Pollasky Ave",
    "sg:city":"Clovis",
    "sg:classifiers":[
        {
            "category":"Professional",
            "subcategory":"Business Services",
            "type":"Services"
        }
    ],
    "sg:phone":"+1 559 297 7775",
    "sg:postcode":"93612",
    "sg:province":"CA",
    "wof:name":"Williams Robert",
    "wof:placetype":"venue"
},
  "geometry": {"coordinates":[-119.701952,36.811793],"type":"Point"}
}