{
  "type": "Feature",
  "properties": {
    "iso:country":"US",
    "sg:address":"3142 Talbot Ave",
    "sg:city":"Riverbank",
    "sg:classifiers":[
        {
            "category":"Shopping",
            "type":"Retail Goods"
        }
    ],
    "sg:phone":"+1 209 869 9012",
    "sg:postcode":"95367",
    "sg:province":"CA",
    "sg:tags":[
        "art",
        "gallery",
        "dealer"
    ],
    "wof:name":"Santa Fe Trails Art Gallery",
    "wof:placetype":"venue"
},
  "geometry": {"coordinates":[-120.938075,37.726186],"type":"Point"}
}