{
  "type": "Feature",
  "properties": {
    "addr:full":"309 N Martel Ave Los Angeles CA 90036",
    "addr:housenumber":"309",
    "addr:postcode":"90036",
    "addr:street":"N Martel Ave",
    "iso:country":"US",
    "sg:address":"309 N Martel Ave",
    "sg:city":"Los Angeles",
    "sg:classifiers":[
        {
            "category":"Personal",
            "subcategory":"Beauty Salon",
            "type":"Services"
        },
        {
            "category":"Personal",
            "subcategory":"Hair Removal",
            "type":"Services"
        }
    ],
    "sg:phone":"+1 323 936 3600",
    "sg:postcode":"90036",
    "sg:province":"CA",
    "sg:website":"www.salonthree.com",
    "wof:name":"Salon Three",
    "wof:placetype":"venue"
},
  "geometry": {"coordinates":[-118.35113,34.076286],"type":"Point"}
}