{
  "type": "Feature",
  "properties": {
    "addr:full":"17860 Wards Ferry Rd Sonora CA 95370",
    "addr:housenumber":"17860",
    "addr:postcode":"95370",
    "addr:street":"Wards Ferry Rd",
    "iso:country":"US",
    "sg:address":"17860 Wards Ferry Rd",
    "sg:city":"Sonora",
    "sg:classifiers":[
        {
            "category":"Health Services",
            "subcategory":"Doctor",
            "type":"Services"
        }
    ],
    "sg:phone":"+1 209 532 7110",
    "sg:postcode":"95370",
    "sg:province":"CA",
    "sg:tags":[
        "physician",
        "family",
        "practice",
        "surgeons",
        "medicine"
    ],
    "wof:name":"Charles L Edwards Md",
    "wof:placetype":"venue"
},
  "geometry": {"coordinates":[-120.328563,37.945071],"type":"Point"}
}