{
  "type": "Feature",
  "properties": {
    "iso:country":"US",
    "sg:address":"11516 Downey Ave",
    "sg:city":"Downey",
    "sg:classifiers":[
        {
            "category":"Professional",
            "subcategory":"Management & Consulting",
            "type":"Services"
        }
    ],
    "sg:phone":"+1 562 622 9009",
    "sg:postcode":"90241",
    "sg:province":"CA",
    "sg:tags":[
        "consultant",
        "energy",
        "conservation"
    ],
    "sg:website":"www.nova-systems.net",
    "wof:name":"Nova Facilty Management System",
    "wof:placetype":"venue"
},
  "geometry": {"coordinates":[-118.134591,33.937754],"type":"Point"}
}