{
  "type": "Feature",
  "properties": {
    "addr:full":"101 California Street San Francisco CA 94111",
    "addr:housenumber":"101",
    "addr:postcode":"94111",
    "addr:street":"California Street",
    "iso:country":"US",
    "sg:address":"101 California Street",
    "sg:city":"San Francisco",
    "sg:classifiers":[
        {
            "category":"Professional",
            "subcategory":"Lawyer & Legal Services",
            "type":"Services"
        }
    ],
    "sg:phone":"+1 415 392 9200",
    "sg:postcode":"94111",
    "sg:province":"CA",
    "wof:name":"Berenson Phyllis G Atty",
    "wof:placetype":"venue"
},
  "geometry": {"coordinates":[-122.398003,37.793499],"type":"Point"}
}