{
  "type": "Feature",
  "properties": {
    "addr:full":"1888 Century Park E Los Angeles CA 90067",
    "addr:housenumber":"1888",
    "addr:postcode":"90067",
    "addr:street":"Century Park E",
    "iso:country":"US",
    "sg:address":"1888 Century Park E",
    "sg:city":"Los Angeles",
    "sg:classifiers":[
        {
            "category":"Professional",
            "subcategory":"Accounting & Tax Preparation",
            "type":"Services"
        }
    ],
    "sg:phone":"+1 310 553 3716",
    "sg:postcode":"90067",
    "sg:province":"CA",
    "sg:tags":[
        "accountant"
    ],
    "sg:website":"www.hzmcpas.com",
    "wof:name":"Horowitz Zaron Mc Mahon Cpas",
    "wof:placetype":"venue"
},
  "geometry": {"coordinates":[-118.414368,34.061235],"type":"Point"}
}