{
  "type": "Feature",
  "properties": {
    "iso:country":"US",
    "sg:address":"988 N Hill St Ste 103",
    "sg:city":"Los Angeles",
    "sg:classifiers":[
        {
            "category":"Shopping",
            "subcategory":"Clothing, Apparel, & Fashions",
            "type":"Retail Goods"
        },
        {
            "category":"Shopping",
            "subcategory":"Hobbies, Toys, & Games",
            "type":"Retail Goods"
        },
        {
            "category":"Shopping",
            "subcategory":"Antiques",
            "type":"Retail Goods"
        },
        {
            "category":"Shopping",
            "subcategory":"Crafts & Fabrics",
            "type":"Retail Goods"
        },
        {
            "category":"Shopping Center",
            "type":"Public Place"
        },
        {
            "category":"Restaurant",
            "type":"Food & Drink"
        }
    ],
    "sg:phone":"+1 213 680 0968",
    "sg:postcode":"90012",
    "sg:province":"CA",
    "sg:tags":[
        "dim",
        "sum",
        "toy",
        "art",
        "store"
    ],
    "wof:name":"Bamboo Plaza",
    "wof:placetype":"venue"
},
  "geometry": {"coordinates":[-118.237438,34.066739],"type":"Point"}
}