{
  "type": "Feature",
  "properties": {
    "addr:full":"1114 Brace Ave San Jose CA 95125",
    "addr:housenumber":"1114",
    "addr:postcode":"95125",
    "addr:street":"Brace Ave",
    "iso:country":"US",
    "sg:address":"1114 Brace Ave",
    "sg:city":"San Jose",
    "sg:classifiers":[
        {
            "category":"Professional",
            "type":"Services"
        }
    ],
    "sg:phone":"+1 408 594 1074",
    "sg:postcode":"95125",
    "sg:province":"CA",
    "wof:name":"Advatar Inc",
    "wof:placetype":"venue"
},
  "geometry": {"coordinates":[-121.899208,37.3046],"type":"Point"}
}