{
  "type": "Feature",
  "properties": {
    "iso:country":"US",
    "sg:address":"6620 Coyle Avenue Suite 301",
    "sg:city":"Carmichael",
    "sg:classifiers":[
        {
            "category":"Health Services",
            "subcategory":"Doctor",
            "type":"Services"
        }
    ],
    "sg:phone":"+1 916 965 6560",
    "sg:postcode":"95608",
    "sg:province":"CA",
    "wof:name":"Cohan Matthew MD",
    "wof:placetype":"venue"
},
  "geometry": {"coordinates":[-121.31019999999999,38.668088],"type":"Point"}
}