{
  "type": "Feature",
  "properties": {
    "addr:full":"302 Hollister St San Diego CA 92154",
    "addr:housenumber":"302",
    "addr:postcode":"92154",
    "addr:street":"Hollister St",
    "iso:country":"US",
    "sg:address":"302 Hollister St",
    "sg:city":"San Diego",
    "sg:classifiers":[
        {
            "category":"Wholesale",
            "subcategory":"Plants",
            "type":"Manufacturing & Wholesale Goods"
        }
    ],
    "sg:phone":"+1 619 575 2244",
    "sg:postcode":"92154",
    "sg:province":"CA",
    "sg:tags":[
        "supply"
    ],
    "wof:name":"El Sembrador Nursery",
    "wof:placetype":"venue"
},
  "geometry": {"coordinates":[-117.08415599999999,32.59122],"type":"Point"}
}