{
  "type": "Feature",
  "properties": {
    "iso:country":"US",
    "sg:address":"473 Soscol Ave",
    "sg:city":"Napa",
    "sg:classifiers":[
        {
            "category":"Retail",
            "subcategory":"Auto Rental",
            "type":"Services"
        }
    ],
    "sg:phone":"+1 707 257 1911",
    "sg:postcode":"94559",
    "sg:province":"CA",
    "sg:tags":[
        "renting",
        "automobile"
    ],
    "wof:name":"Affordable Auto Rentals",
    "wof:placetype":"venue"
},
  "geometry": {"coordinates":[-122.276124,38.289592],"type":"Point"}
}