{
  "type": "Feature",
  "properties": {
    "iso:country":"US",
    "sg:address":"5772 E Los Angeles Ave",
    "sg:city":"Simi Valley",
    "sg:classifiers":[
        {
            "category":"Restaurant",
            "type":"Food & Drink"
        }
    ],
    "sg:phone":"+1 805 522 0667",
    "sg:postcode":"93063",
    "sg:province":"CA",
    "wof:name":"Imperial Chinese Restaurant",
    "wof:placetype":"venue"
},
  "geometry": {"coordinates":[-118.680412,34.271655],"type":"Point"}
}