{
  "type": "Feature",
  "properties": {
    "addr:full":"2828 W Magnolia Blvd Burbank CA 91506",
    "addr:housenumber":"2828",
    "addr:postcode":"91506",
    "addr:street":"W Magnolia Blvd",
    "iso:country":"US",
    "sg:address":"2828 W Magnolia Blvd",
    "sg:city":"Burbank",
    "sg:classifiers":[
        {
            "category":"Organizations",
            "subcategory":"Religious Organization",
            "type":"Services"
        }
    ],
    "sg:phone":"+1 818 846 2866",
    "sg:postcode":"91506",
    "sg:province":"CA",
    "sg:tags":[
        "church"
    ],
    "wof:name":"Magnolia Park United Methodist",
    "wof:placetype":"venue"
},
  "geometry": {"coordinates":[-118.338593,34.170596],"type":"Point"}
}