{
  "type": "Feature",
  "properties": {
    "addr:full":"6055 San Vicente Boulevard Los Angeles CA 90036",
    "addr:housenumber":"6055",
    "addr:postcode":"90036",
    "addr:street":"San Vicente Boulevard",
    "iso:country":"US",
    "sg:address":"6055 San Vicente Boulevard",
    "sg:city":"Los Angeles",
    "sg:classifiers":[
        {
            "category":"Health Services",
            "subcategory":"Dentist",
            "type":"Services"
        }
    ],
    "sg:phone":"+1 323 933 9002",
    "sg:postcode":"90036",
    "sg:province":"CA",
    "wof:name":"Vinarsky Maya DDS",
    "wof:placetype":"venue"
},
  "geometry": {"coordinates":[-118.363585,34.058564],"type":"Point"}
}