{
  "type": "Feature",
  "properties": {
    "addr:full":"13348 Telegraph Rd Santa Fe Springs CA 90670",
    "addr:housenumber":"13348",
    "addr:postcode":"90670",
    "addr:street":"Telegraph Rd",
    "iso:country":"US",
    "sg:address":"13348 Telegraph Rd",
    "sg:city":"Santa Fe Springs",
    "sg:classifiers":[
        {
            "category":"Shopping",
            "subcategory":"Jewelry",
            "type":"Retail Goods"
        }
    ],
    "sg:phone":"+1 562 777 0085",
    "sg:postcode":"90670",
    "sg:province":"CA",
    "wof:name":"Don Roberto Jewelers Inc",
    "wof:placetype":"venue"
},
  "geometry": {"coordinates":[-118.047997,33.940899],"type":"Point"}
}