{
  "type": "Feature",
  "properties": {
    "iso:country":"US",
    "sg:address":"6300 Wilshire Blvd",
    "sg:city":"Los Angeles",
    "sg:classifiers":[
        {
            "category":"Personal",
            "subcategory":"Beauty Salon",
            "type":"Services"
        }
    ],
    "sg:phone":"+1 323 782 9300",
    "sg:postcode":"90048",
    "sg:province":"CA",
    "wof:name":"Hair Designs On Wilshire",
    "wof:placetype":"venue"
},
  "geometry": {"coordinates":[-118.36825899999999,34.063744],"type":"Point"}
}