{
  "type": "Feature",
  "properties": {
    "addr:full":"55 River St Santa Cruz CA 95060",
    "addr:housenumber":"55",
    "addr:postcode":"95060",
    "addr:street":"River St",
    "iso:country":"US",
    "sg:address":"55 River St",
    "sg:city":"Santa Cruz",
    "sg:classifiers":[
        {
            "category":"Professional",
            "subcategory":"Lawyer & Legal Services",
            "type":"Services"
        }
    ],
    "sg:phone":"+1 831 420 3500",
    "sg:postcode":"95060",
    "sg:province":"CA",
    "sg:tags":[
        "attorney"
    ],
    "wof:name":"Vilma Guerrero",
    "wof:placetype":"venue"
},
  "geometry": {"coordinates":[-122.025638,36.975939],"type":"Point"}
}