{
  "type": "Feature",
  "properties": {
    "iso:country":"US",
    "sg:address":"10 Joubert Rd",
    "sg:city":"Camptonville",
    "sg:classifiers":[
        {
            "category":"Wholesale",
            "subcategory":"Books, Periodicals, & Newspapers",
            "type":"Manufacturing & Wholesale Goods"
        }
    ],
    "sg:phone":"+1 530 289 3317",
    "sg:postcode":"95922",
    "sg:province":"CA",
    "sg:tags":[
        "distributor",
        "publisher",
        "maps-designers"
    ],
    "wof:name":"Sleighville Map & Print",
    "wof:placetype":"venue"
},
  "geometry": {"coordinates":[-120.934245,39.510448],"type":"Point"}
}