{
  "type": "Feature",
  "properties": {
    "iso:country":"US",
    "sg:address":"Berkeley Faculty Club University of California",
    "sg:city":"Berkeley",
    "sg:classifiers":[
        {
            "category":"Education",
            "subcategory":"Special Training",
            "type":"Public Place"
        }
    ],
    "sg:postcode":"94701",
    "sg:province":"CA",
    "sg:tags":[
        "tutoring"
    ],
    "sg:website":"www.testmasters.net/gre",
    "wof:name":"TestMasters",
    "wof:placetype":"venue"
},
  "geometry": {"coordinates":[-122.252869,37.871044],"type":"Point"}
}