{
  "type": "Feature",
  "properties": {
    "addr:full":"10056 Green St Temple City CA 91780",
    "addr:housenumber":"10056",
    "addr:postcode":"91780",
    "addr:street":"Green St",
    "iso:country":"US",
    "sg:address":"10056 Green St",
    "sg:city":"Temple City",
    "sg:classifiers":[
        {
            "category":"Wholesale",
            "subcategory":"Durable Goods & Equipment",
            "type":"Manufacturing & Wholesale Goods"
        }
    ],
    "sg:phone":"+1 626 575 5935",
    "sg:postcode":"91780",
    "sg:province":"CA",
    "wof:name":"Supplies Unlimited Co",
    "wof:placetype":"venue"
},
  "geometry": {"coordinates":[-118.048948,34.09651],"type":"Point"}
}