{
  "type": "Feature",
  "properties": {
    "addr:full":"3390 Gateway Blvd Fremont CA 94538",
    "addr:housenumber":"3390",
    "addr:postcode":"94538",
    "addr:street":"Gateway Blvd",
    "iso:country":"US",
    "sg:address":"3390 Gateway Blvd",
    "sg:city":"Fremont",
    "sg:classifiers":[
        {
            "category":"Retail",
            "subcategory":"Portrait Studio",
            "type":"Services"
        }
    ],
    "sg:phone":"+1 510 490 9930",
    "sg:postcode":"94538",
    "sg:province":"CA",
    "sg:tags":[
        "photographer"
    ],
    "wof:name":"Advanced Integrated Photonics",
    "wof:placetype":"venue"
},
  "geometry": {"coordinates":[-121.938524,37.475298],"type":"Point"}
}