{
  "type": "Feature",
  "properties": {
    "addr:full":"104 Sunset Ave Suisun City CA 94585",
    "addr:housenumber":"104",
    "addr:postcode":"94585",
    "addr:street":"Sunset Ave",
    "iso:country":"US",
    "sg:address":"104 Sunset Ave",
    "sg:city":"Suisun City",
    "sg:classifiers":[
        {
            "category":"Restaurant",
            "type":"Food & Drink"
        }
    ],
    "sg:phone":"+1 707 422 3390",
    "sg:postcode":"94585",
    "sg:province":"CA",
    "wof:name":"Taqueria Las Brisas",
    "wof:placetype":"venue"
},
  "geometry": {"coordinates":[-122.020224,38.244995],"type":"Point"}
}