{
  "type": "Feature",
  "properties": {
    "addr:full":"4463 Birch St Newport Beach CA 92660",
    "addr:housenumber":"4463",
    "addr:postcode":"92660",
    "addr:street":"Birch St",
    "iso:country":"US",
    "sg:address":"4463 Birch St",
    "sg:city":"Newport Beach",
    "sg:classifiers":[
        {
            "category":"Health Services",
            "subcategory":"Doctor",
            "type":"Services"
        }
    ],
    "sg:phone":"+1 714 477 9091",
    "sg:postcode":"92660",
    "sg:province":"CA",
    "sg:tags":[
        "physician",
        "surgeon"
    ],
    "wof:name":"Birch Outpatient Surgery Ctr",
    "wof:placetype":"venue"
},
  "geometry": {"coordinates":[-117.866252,33.668258],"type":"Point"}
}