{
  "type": "Feature",
  "properties": {
    "iso:country":"US",
    "sg:address":"331 Whitney Pl",
    "sg:city":"Fremont",
    "sg:classifiers":[
        {
            "category":"Wholesale",
            "subcategory":"Electrical",
            "type":"Manufacturing & Wholesale Goods"
        }
    ],
    "sg:phone":"+1 510 687 9960",
    "sg:postcode":"94539",
    "sg:province":"CA",
    "sg:tags":[
        "semiconductor"
    ],
    "wof:name":"Cal Semi",
    "wof:placetype":"venue"
},
  "geometry": {"coordinates":[-121.919302,37.469973],"type":"Point"}
}