{
  "type": "Feature",
  "properties": {
    "iso:country":"US",
    "sg:address":"965 Arnele Ave",
    "sg:city":"El Cajon",
    "sg:classifiers":[
        {
            "category":"Autos & Motor Vehicles",
            "subcategory":"Automobile Sales",
            "type":"Retail Goods"
        },
        {
            "category":"Retail",
            "subcategory":"Auto Rental",
            "type":"Services"
        },
        {
            "category":"Retail",
            "subcategory":"Auto Repair",
            "type":"Services"
        }
    ],
    "sg:phone":"+1 619 270 3000",
    "sg:postcode":"92020",
    "sg:province":"CA",
    "sg:tags":[
        "car"
    ],
    "sg:website":"www.toyotaofelcajon.com",
    "wof:name":"Toyota of El Cajon",
    "wof:placetype":"venue"
},
  "geometry": {"coordinates":[-116.974602,32.802674],"type":"Point"}
}