{
  "type": "Feature",
  "properties": {
    "iso:country":"US",
    "sg:address":"1359 N Lake Ave",
    "sg:city":"Pasadena",
    "sg:classifiers":[
        {
            "category":"Shopping",
            "type":"Retail Goods"
        }
    ],
    "sg:phone":"+1 626 296 6993",
    "sg:postcode":"91104",
    "sg:province":"CA",
    "sg:tags":[
        "ready",
        "picture",
        "frame"
    ],
    "wof:name":"Juans Art Work & Rugs",
    "wof:placetype":"venue"
},
  "geometry": {"coordinates":[-118.132263,34.169958],"type":"Point"}
}