{
  "type": "Feature",
  "properties": {
    "addr:full":"147 Golden Hind Psge Corte Madera CA 94925",
    "addr:housenumber":"147",
    "addr:postcode":"94925",
    "addr:street":"Golden Hind Psge",
    "iso:country":"US",
    "sg:address":"147 Golden Hind Psge",
    "sg:city":"Corte Madera",
    "sg:classifiers":[
        {
            "category":"Shopping",
            "subcategory":"Gifts & Souvenirs",
            "type":"Retail Goods"
        }
    ],
    "sg:phone":"+1 415 927 8155",
    "sg:postcode":"94925",
    "sg:province":"CA",
    "sg:tags":[
        "shop"
    ],
    "wof:name":"Still Life Inc",
    "wof:placetype":"venue"
},
  "geometry": {"coordinates":[-122.502346,37.92215],"type":"Point"}
}