{
  "type": "Feature",
  "properties": {
    "addr:full":"140 W Valley Blvd #118B San Gabriel CA 91776",
    "addr:housenumber":"140",
    "addr:postcode":"91776",
    "addr:street":"W Valley Blvd # 118B",
    "iso:country":"US",
    "sg:address":"140 W Valley Blvd #118B",
    "sg:city":"San Gabriel",
    "sg:classifiers":[
        {
            "category":"Coffee & Tea",
            "type":"Food & Drink"
        }
    ],
    "sg:phone":"+1 626 288 5658",
    "sg:postcode":"91776",
    "sg:province":"CA",
    "sg:website":"www.tapiocaexpress.com",
    "wof:name":"Tapioca Express",
    "wof:placetype":"venue"
},
  "geometry": {"coordinates":[-118.101788,34.079514],"type":"Point"}
}