{
  "type": "Feature",
  "properties": {
    "iso:country":"US",
    "sg:address":"1370 Foothill Blvd Ste 200",
    "sg:city":"La Canada Flintridge",
    "sg:classifiers":[
        {
            "category":"Health Services",
            "subcategory":"Doctor",
            "type":"Services"
        }
    ],
    "sg:phone":"+1 818 952 8183",
    "sg:postcode":"91011",
    "sg:province":"CA",
    "sg:tags":[
        "surgeon",
        "oral"
    ],
    "sg:website":"www.foothilldentalimplants.com",
    "wof:name":"Lytle Tate & Stamper",
    "wof:placetype":"venue"
},
  "geometry": {"coordinates":[-118.208173,34.207768],"type":"Point"}
}