{
  "type": "Feature",
  "properties": {
    "iso:country":"US",
    "sg:address":"18016 Ventura Blvd",
    "sg:city":"Encino",
    "sg:classifiers":[
        {
            "category":"Utilities",
            "subcategory":"Mobile Phone",
            "type":"Services"
        }
    ],
    "sg:phone":"+1 818 376 1090",
    "sg:postcode":"91316",
    "sg:province":"CA",
    "sg:tags":[
        "telephone",
        "cellular"
    ],
    "wof:name":"DHN Communications",
    "wof:placetype":"venue"
},
  "geometry": {"coordinates":[-118.526904,34.16522],"type":"Point"}
}