{
  "type": "Feature",
  "properties": {
    "iso:country":"US",
    "sg:address":"1437 W Badillo St",
    "sg:city":"West Covina",
    "sg:classifiers":[
        {
            "category":"Organizations",
            "subcategory":"Religious Organization",
            "type":"Services"
        }
    ],
    "sg:phone":"+1 626 962 2740",
    "sg:postcode":"91790",
    "sg:province":"CA",
    "sg:tags":[
        "church"
    ],
    "wof:name":"Church Of The Nazarene",
    "wof:placetype":"venue"
},
  "geometry": {"coordinates":[-117.936143,34.086777],"type":"Point"}
}