{
  "type": "Feature",
  "properties": {
    "iso:country":"US",
    "sg:address":"205 S Willowbrook Ave",
    "sg:city":"Compton",
    "sg:classifiers":[
        {
            "category":"Government",
            "subcategory":"Office",
            "type":"Public Place"
        }
    ],
    "sg:phone":"+1 310 605 5524",
    "sg:postcode":"90220",
    "sg:province":"CA",
    "sg:tags":[
        "govt",
        "city"
    ],
    "wof:name":"Compton Municipal Water Dept",
    "wof:placetype":"venue"
},
  "geometry": {"coordinates":[-118.224422,33.895558],"type":"Point"}
}