{
  "type": "Feature",
  "properties": {
    "addr:full":"8122 Katella Ave Stanton CA 90680",
    "addr:housenumber":"8122",
    "addr:postcode":"ca 90680",
    "addr:street":"Katella Ave",
    "iso:country":"US",
    "sg:address":"8122 Katella Ave",
    "sg:city":"Stanton",
    "sg:classifiers":[
        {
            "category":"Government",
            "subcategory":"Office",
            "type":"Public Place"
        }
    ],
    "sg:phone":"+1 714 527 3371",
    "sg:postcode":"90680",
    "sg:province":"CA",
    "sg:tags":[
        "construction"
    ],
    "wof:name":"Transportation California Dept",
    "wof:placetype":"venue"
},
  "geometry": {"coordinates":[-117.991665,33.802856],"type":"Point"}
}