{
  "type": "Feature",
  "properties": {
    "addr:full":"18414 S Santa Fe Ave Compton CA 90221",
    "addr:housenumber":"18414",
    "addr:postcode":"90221",
    "addr:street":"S Santa Fe Ave",
    "iso:country":"US",
    "sg:address":"18414 S Santa Fe Ave",
    "sg:city":"Compton",
    "sg:classifiers":[
        {
            "category":"Freight",
            "type":"Transportation"
        }
    ],
    "sg:phone":"+1 310 763 1423",
    "sg:postcode":"90221",
    "sg:province":"CA",
    "sg:tags":[
        "refuse",
        "system",
        "trucking",
        "operator",
        "sanitary",
        "local"
    ],
    "wof:name":"A C T I",
    "wof:placetype":"venue"
},
  "geometry": {"coordinates":[-118.213385,33.863156],"type":"Point"}
}