{
  "type": "Feature",
  "properties": {
    "addr:full":"1410 Beaumont Ave Beaumont CA 92223",
    "addr:housenumber":"1410",
    "addr:postcode":"92223",
    "addr:street":"Beaumont Ave",
    "iso:country":"US",
    "sg:address":"1410 Beaumont Ave",
    "sg:city":"Beaumont",
    "sg:classifiers":[
        {
            "category":"Restaurant",
            "type":"Food & Drink"
        }
    ],
    "sg:phone":"+1 951 769 5800",
    "sg:postcode":"92223",
    "sg:province":"CA",
    "sg:tags":[
        "mexican"
    ],
    "wof:name":"El Mariachi",
    "wof:placetype":"venue"
},
  "geometry": {"coordinates":[-116.977237,33.947355],"type":"Point"}
}