{
  "type": "Feature",
  "properties": {
    "iso:country":"US",
    "sg:address":"954 N Lake Ave",
    "sg:city":"Pasadena",
    "sg:classifiers":[
        {
            "category":"Retail",
            "subcategory":"Laundry & Dry Cleaning",
            "type":"Services"
        }
    ],
    "sg:phone":"+1 626 797 8040",
    "sg:postcode":"91104",
    "sg:province":"CA",
    "wof:name":"Sisi Cleaners",
    "wof:placetype":"venue"
},
  "geometry": {"coordinates":[-118.132501,34.162201],"type":"Point"}
}