{
  "type": "Feature",
  "properties": {
    "addr:full":"4410 N Pershing Ave Stockton CA 95207",
    "addr:housenumber":"4410",
    "addr:postcode":"95207",
    "addr:street":"N Pershing Ave",
    "iso:country":"US",
    "sg:address":"4410 N Pershing Ave",
    "sg:city":"Stockton",
    "sg:classifiers":[
        {
            "category":"Professional",
            "subcategory":"Lawyer & Legal Services",
            "type":"Services"
        }
    ],
    "sg:phone":"+1 209 957 2251",
    "sg:postcode":"95207",
    "sg:province":"CA",
    "sg:tags":[
        "attorney"
    ],
    "wof:name":"Harold Sullivan Law Office",
    "wof:placetype":"venue"
},
  "geometry": {"coordinates":[-121.32011,37.984756],"type":"Point"}
}