{
  "type": "Feature",
  "properties": {
    "addr:full":"903 Dell Ave Campbell CA 95008",
    "addr:housenumber":"903",
    "addr:postcode":"95008",
    "addr:street":"Dell Ave",
    "iso:country":"US",
    "sg:address":"903 Dell Ave",
    "sg:city":"Campbell",
    "sg:classifiers":[
        {
            "category":"Wholesale",
            "subcategory":"Electrical",
            "type":"Manufacturing & Wholesale Goods"
        }
    ],
    "sg:phone":"+1 408 874 0800",
    "sg:postcode":"95008",
    "sg:province":"CA",
    "sg:tags":[
        "battery"
    ],
    "wof:name":"IMC Tempest Batteries",
    "wof:placetype":"venue"
},
  "geometry": {"coordinates":[-121.950453,37.274323],"type":"Point"}
}