{
  "type": "Feature",
  "properties": {
    "addr:full":"8301 Utica Ave Rancho Cucamonga CA 91730",
    "addr:housenumber":"8301",
    "addr:postcode":"91730",
    "addr:street":"Utica Ave",
    "iso:country":"US",
    "sg:address":"8301 Utica Ave",
    "sg:city":"Rancho Cucamonga",
    "sg:classifiers":[
        {
            "category":"Banks & Credit Unions",
            "subcategory":"Bank",
            "type":"Services"
        }
    ],
    "sg:phone":"+1 909 944 7900",
    "sg:postcode":"91730",
    "sg:province":"CA",
    "sg:tags":[
        "loan",
        "real estate"
    ],
    "wof:name":"Mortgage Solutions",
    "wof:placetype":"venue"
},
  "geometry": {"coordinates":[-117.57054100000001,34.103218],"type":"Point"}
}