{
  "type": "Feature",
  "properties": {
    "addr:full":"340 N Westlake Blvd Thousand Oaks CA 91362",
    "addr:housenumber":"340",
    "addr:postcode":"91362",
    "addr:street":"N Westlake Blvd",
    "iso:country":"US",
    "sg:address":"340 N Westlake Blvd",
    "sg:city":"Thousand Oaks",
    "sg:classifiers":[
        {
            "category":"Professional",
            "type":"Services"
        }
    ],
    "sg:phone":"+1 805 495 0700",
    "sg:postcode":"91362",
    "sg:province":"CA",
    "wof:name":"Ecure Corp",
    "wof:placetype":"venue"
},
  "geometry": {"coordinates":[-118.822343,34.166672],"type":"Point"}
}