{
  "type": "Feature",
  "properties": {
    "addr:full":"501 W Broadway San Diego CA 92101",
    "addr:housenumber":"501",
    "addr:postcode":"92101",
    "addr:street":"W Broadway",
    "iso:country":"US",
    "sg:address":"501 W Broadway",
    "sg:city":"San Diego",
    "sg:classifiers":[
        {
            "category":"Professional",
            "subcategory":"Management & Consulting",
            "type":"Services"
        }
    ],
    "sg:phone":"+1 619 670 5071",
    "sg:postcode":"92101",
    "sg:province":"CA",
    "sg:tags":[
        "consultant",
        "business"
    ],
    "wof:name":"Safari Group",
    "wof:placetype":"venue"
},
  "geometry": {"coordinates":[-117.168279,32.715716],"type":"Point"}
}