{
  "type": "Feature",
  "properties": {
    "iso:country":"US",
    "sg:address":"465 W 2nd St",
    "sg:city":"Calexico",
    "sg:classifiers":[
        {
            "category":"Parking",
            "type":"Transportation"
        }
    ],
    "sg:phone":"+1 760 357 2477",
    "sg:postcode":"92231",
    "sg:province":"CA",
    "sg:tags":[
        "garage"
    ],
    "wof:name":"Calexico Parking & Storage",
    "wof:placetype":"venue"
},
  "geometry": {"coordinates":[-115.502787,32.666277],"type":"Point"}
}