{
  "type": "Feature",
  "properties": {
    "addr:full":"428 Main St # 102 Huntington Beach CA 92648",
    "addr:housenumber":"428",
    "addr:postcode":"92648",
    "addr:street":"Main St # 102",
    "iso:country":"US",
    "sg:address":"428 Main St # 102",
    "sg:city":"Huntington Beach",
    "sg:classifiers":[
        {
            "category":"Personal",
            "subcategory":"Beauty Salon",
            "type":"Services"
        }
    ],
    "sg:phone":"+1 714 960 4012",
    "sg:postcode":"92648",
    "sg:province":"CA",
    "sg:tags":[
        "hair"
    ],
    "sg:website":"www.salonhq.net",
    "wof:name":"Salon HQ",
    "wof:placetype":"venue"
},
  "geometry": {"coordinates":[-117.998576,33.66057],"type":"Point"}
}