{
  "type": "Feature",
  "properties": {
    "addr:full":"542 Vera Ave Ripon CA 95366",
    "addr:housenumber":"542",
    "addr:postcode":"ca 95366",
    "addr:street":"Vera Ave",
    "iso:country":"US",
    "sg:address":"542 Vera Ave",
    "sg:city":"Ripon",
    "sg:classifiers":[
        {
            "category":"Wholesale",
            "subcategory":"Machinery & Supplies",
            "type":"Manufacturing & Wholesale Goods"
        }
    ],
    "sg:phone":"+1 209 599 6507",
    "sg:postcode":"95366",
    "sg:province":"CA",
    "sg:tags":[
        "equipment",
        "ride",
        "park",
        "amusement"
    ],
    "wof:name":"Dykstra De Vries Inc",
    "wof:placetype":"venue"
},
  "geometry": {"coordinates":[-121.13295100000001,37.735345],"type":"Point"}
}