{
  "type": "Feature",
  "properties": {
    "addr:full":"423 Washington St San Francisco CA 94111",
    "addr:housenumber":"423",
    "addr:postcode":"94111",
    "addr:street":"Washington St",
    "iso:country":"US",
    "sg:address":"423 Washington St",
    "sg:city":"San Francisco",
    "sg:classifiers":[
        {
            "category":"Professional",
            "subcategory":"Research",
            "type":"Services"
        }
    ],
    "sg:phone":"+1 415 273 7733",
    "sg:postcode":"94111",
    "sg:province":"CA",
    "sg:tags":[
        "consulting",
        "commercial",
        "business",
        "physical"
    ],
    "wof:name":"Battelle San Frncsco Oprations",
    "wof:placetype":"venue"
},
  "geometry": {"coordinates":[-122.40087200000001,37.795756],"type":"Point"}
}