{
  "type": "Feature",
  "properties": {
    "addr:full":"517 4th Ave San Diego CA 92101",
    "addr:housenumber":"517",
    "addr:postcode":"92101",
    "addr:street":"4Th Ave",
    "iso:country":"US",
    "sg:address":"517 4th Ave",
    "sg:city":"San Diego",
    "sg:classifiers":[
        {
            "category":"Shopping",
            "subcategory":"Hobbies, Toys, & Games",
            "type":"Retail Goods"
        }
    ],
    "sg:phone":"+1 619 231 9902",
    "sg:postcode":"92101",
    "sg:province":"CA",
    "sg:tags":[
        "product",
        "ceramic"
    ],
    "wof:name":"Ptah",
    "wof:placetype":"venue"
},
  "geometry": {"coordinates":[-117.160961,32.711309],"type":"Point"}
}