{
  "type": "Feature",
  "properties": {
    "addr:full":"25775 McBean Pkwy Valencia CA 91355",
    "addr:postcode":"25775;91355",
    "addr:street":"Mcbean Pkwy",
    "iso:country":"US",
    "sg:address":"25775 McBean Pkwy",
    "sg:city":"Valencia",
    "sg:classifiers":[
        {
            "category":"Health Services",
            "subcategory":"Dentist",
            "type":"Services"
        }
    ],
    "sg:phone":"+1 661 222 7724",
    "sg:postcode":"91355",
    "sg:province":"CA",
    "sg:tags":[
        "orthodontist"
    ],
    "wof:name":"Snow Orthodontics",
    "wof:placetype":"venue"
},
  "geometry": {"coordinates":[-118.55500000000001,34.406799],"type":"Point"}
}