{
  "type": "Feature",
  "properties": {
    "addr:full":"330 Green Valley Rd El Dorado Hills CA 95762",
    "addr:housenumber":"330",
    "addr:postcode":"95762",
    "addr:street":"Green Valley Rd;Dorado",
    "iso:country":"US",
    "sg:address":"330 Green Valley Rd",
    "sg:city":"El Dorado Hills",
    "sg:classifiers":[
        {
            "category":"Restaurant",
            "type":"Food & Drink"
        }
    ],
    "sg:phone":"+1 916 941 7892",
    "sg:postcode":"95762",
    "sg:province":"CA",
    "wof:name":"Mad City Take N' Bake Pizza",
    "wof:placetype":"venue"
},
  "geometry": {"coordinates":[-121.109588,38.700693],"type":"Point"}
}