{
  "type": "Feature",
  "properties": {
    "iso:country":"US",
    "sg:address":"99 Escuela Dr",
    "sg:city":"Daly City",
    "sg:classifiers":[
        {
            "category":"Shopping",
            "subcategory":"Pharmacy",
            "type":"Retail Goods"
        }
    ],
    "sg:phone":"+1 650 994 6900",
    "sg:postcode":"94015",
    "sg:province":"CA",
    "wof:name":"Pharmaceutical Svc Pharmacy",
    "wof:placetype":"venue"
},
  "geometry": {"coordinates":[-122.475567,37.674392],"type":"Point"}
}