{
  "type": "Feature",
  "properties": {
    "iso:country":"US",
    "sg:address":"1481 E Success Dr",
    "sg:city":"Porterville",
    "sg:classifiers":[
        {
            "category":"Organizations",
            "subcategory":"Religious Organization",
            "type":"Services"
        }
    ],
    "sg:phone":"+1 559 781 4238",
    "sg:postcode":"93257",
    "sg:province":"CA",
    "sg:tags":[
        "church"
    ],
    "wof:name":"Porterville Praise Fellowship",
    "wof:placetype":"venue"
},
  "geometry": {"coordinates":[-118.984601,36.05738],"type":"Point"}
}