{
  "type": "Feature",
  "properties": {
    "iso:country":"US",
    "sg:address":"27645 Ynez Rd",
    "sg:city":"Temecula",
    "sg:classifiers":[
        {
            "category":"Restaurant",
            "type":"Food & Drink"
        }
    ],
    "sg:menulink":"http://www.allmenus.com/ca/murrieta/109895-chilis/menu/",
    "sg:phone":"+1 951 694 0099",
    "sg:postcode":"92591",
    "sg:province":"CA",
    "sg:tags":[
        "burger",
        "american",
        "sandwich",
        "tex-mex",
        "soup"
    ],
    "wof:name":"Chili's",
    "wof:placetype":"venue"
},
  "geometry": {"coordinates":[-117.14997,33.502675],"type":"Point"}
}