{
  "type": "Feature",
  "properties": {
    "addr:full":"756 E Thompson Blvd Ventura CA 93001",
    "addr:housenumber":"756",
    "addr:postcode":"93001",
    "addr:street":"E Thompson Blvd",
    "iso:country":"US",
    "sg:address":"756 E Thompson Blvd",
    "sg:city":"Ventura",
    "sg:classifiers":[
        {
            "category":"Travel",
            "subcategory":"Hotels & Motels",
            "type":"Entertainment"
        }
    ],
    "sg:phone":"+1 805 648 5371",
    "sg:postcode":"93001",
    "sg:province":"CA",
    "sg:website":"http://www.vagabondinns.com",
    "wof:name":"Vagabond Inn",
    "wof:placetype":"venue"
},
  "geometry": {"coordinates":[-119.289148,34.278278],"type":"Point"}
}