{
  "type": "Feature",
  "properties": {
    "iso:country":"US",
    "sg:address":"14760 E 14th St",
    "sg:city":"San Leandro",
    "sg:classifiers":[
        {
            "category":"Food & Beverages",
            "subcategory":"Bakery",
            "type":"Retail Goods"
        }
    ],
    "sg:phone":"+1 510 352 8785",
    "sg:postcode":"94578",
    "sg:province":"CA",
    "sg:tags":[
        "baker"
    ],
    "wof:name":"Bakery LA Mejor",
    "wof:placetype":"venue"
},
  "geometry": {"coordinates":[-122.133684,37.709032],"type":"Point"}
}