{
  "type": "Feature",
  "properties": {
    "addr:full":"2961 W MacArthur Blvd Santa Ana CA 92704",
    "addr:housenumber":"2961",
    "addr:postcode":"92704",
    "addr:street":"W Macarthur Blvd",
    "iso:country":"US",
    "sg:address":"2961 W MacArthur Blvd",
    "sg:city":"Santa Ana",
    "sg:classifiers":[
        {
            "category":"Banks & Credit Unions",
            "subcategory":"Bank",
            "type":"Services"
        }
    ],
    "sg:phone":"+1 714 557 3344",
    "sg:postcode":"92704",
    "sg:province":"CA",
    "wof:name":"Nelson Diane Ins",
    "wof:placetype":"venue"
},
  "geometry": {"coordinates":[-117.908997,33.700001],"type":"Point"}
}