{
  "type": "Feature",
  "properties": {
    "addr:full":"4448 Eagle Rock Boulevard Los Angeles CA 90041",
    "addr:housenumber":"4448",
    "addr:postcode":"90041",
    "addr:street":"Eagle Rock Boulevard",
    "iso:country":"US",
    "sg:address":"4448 Eagle Rock Boulevard",
    "sg:city":"Los Angeles",
    "sg:classifiers":[
        {
            "category":"Real Estate",
            "subcategory":"Real Estate Services",
            "type":"Services"
        }
    ],
    "sg:phone":"+1 323 259 1714",
    "sg:postcode":"90041",
    "sg:province":"CA",
    "sg:tags":[
        "management",
        "property"
    ],
    "wof:name":"Great American Management",
    "wof:placetype":"venue"
},
  "geometry": {"coordinates":[-118.21946699999999,34.125392],"type":"Point"}
}