{
  "type": "Feature",
  "properties": {
    "iso:country":"US",
    "sg:address":"315 W Fyffe St",
    "sg:city":"Stockton",
    "sg:classifiers":[
        {
            "category":"Wholesale",
            "subcategory":"Hardware",
            "type":"Manufacturing & Wholesale Goods"
        },
        {
            "category":"Professional",
            "subcategory":"Advertising",
            "type":"Services"
        }
    ],
    "sg:phone":"+1 209 462 3500",
    "sg:postcode":"95203",
    "sg:province":"CA",
    "sg:tags":[
        "distribution",
        "product",
        "steam"
    ],
    "wof:name":"California Steam Specialties",
    "wof:placetype":"venue"
},
  "geometry": {"coordinates":[-121.348416,37.948943],"type":"Point"}
}