{
  "type": "Feature",
  "properties": {
    "iso:country":"US",
    "sg:address":"6540 Lusk Blvd",
    "sg:city":"San Diego",
    "sg:classifiers":[
        {
            "category":"Professional",
            "subcategory":"Employment Agencies",
            "type":"Services"
        }
    ],
    "sg:phone":"+1 858 202 1700",
    "sg:postcode":"92121",
    "sg:province":"CA",
    "sg:tags":[
        "opportunity"
    ],
    "sg:website":"www.scitechrecruiters.com",
    "wof:name":"Scitech Recruiters",
    "wof:placetype":"venue"
},
  "geometry": {"coordinates":[-117.202632,32.901527],"type":"Point"}
}