{
  "type": "Feature",
  "properties": {
    "addr:full":"3414 Cromwell Pl San Diego CA 92116",
    "addr:housenumber":"3414",
    "addr:postcode":"92116",
    "addr:street":"Cromwell Pl",
    "iso:country":"US",
    "sg:address":"3414 Cromwell Pl",
    "sg:city":"San Diego",
    "sg:classifiers":[
        {
            "category":"Real Estate",
            "subcategory":"Real Estate Operator",
            "type":"Services"
        }
    ],
    "sg:phone":"+1 619 284 2640",
    "sg:postcode":"92116",
    "sg:province":"CA",
    "sg:tags":[
        "property",
        "lessor"
    ],
    "wof:name":"Connie J Laipple",
    "wof:placetype":"venue"
},
  "geometry": {"coordinates":[-117.11965499999999,32.77408],"type":"Point"}
}