{
  "type": "Feature",
  "properties": {
    "iso:country":"US",
    "sg:address":"235 S 2nd St",
    "sg:city":"Richmond",
    "sg:classifiers":[
        {
            "category":"Wholesale",
            "subcategory":"Machinery & Supplies",
            "type":"Manufacturing & Wholesale Goods"
        }
    ],
    "sg:phone":"+1 510 232 0999",
    "sg:postcode":"94804",
    "sg:province":"CA",
    "sg:tags":[
        "salon",
        "cosmetic",
        "beauty",
        "salons-equipment"
    ],
    "wof:name":"Le Chat Nail Product",
    "wof:placetype":"venue"
},
  "geometry": {"coordinates":[-122.36799600000001,37.928902],"type":"Point"}
}