{
  "type": "Feature",
  "properties": {
    "iso:country":"US",
    "sg:address":"696 San Ramon Valley Blvd",
    "sg:city":"Danville",
    "sg:classifiers":[
        {
            "category":"Wholesale",
            "subcategory":"Medical Equipment & Supplies",
            "type":"Manufacturing & Wholesale Goods"
        }
    ],
    "sg:phone":"+1 925 855 1915",
    "sg:postcode":"94526",
    "sg:province":"CA",
    "sg:tags":[
        "laboratory"
    ],
    "sg:website":"http://www.facilities.com",
    "wof:name":"Bionique Lab Svc Inc",
    "wof:placetype":"venue"
},
  "geometry": {"coordinates":[-121.995529,37.812431],"type":"Point"}
}