{
  "type": "Feature",
  "properties": {
    "addr:full":"333 N Santa Anita Ave Ste 7 Arcadia CA 91006",
    "addr:housenumber":"333",
    "addr:postcode":"91006",
    "addr:street":"N Santa Anita Ave Ste 7",
    "iso:country":"US",
    "sg:address":"333 N Santa Anita Ave Ste 7",
    "sg:city":"Arcadia",
    "sg:classifiers":[
        {
            "category":"Wholesale",
            "subcategory":"Computers",
            "type":"Manufacturing & Wholesale Goods"
        }
    ],
    "sg:phone":"+1 626 821 9306",
    "sg:postcode":"91006",
    "sg:province":"CA",
    "sg:website":"www.digigearinc.com",
    "wof:name":"Digigear Inc",
    "wof:placetype":"venue"
},
  "geometry": {"coordinates":[-118.175566,34.144437],"type":"Point"}
}