{
  "type": "Feature",
  "properties": {
    "iso:country":"US",
    "sg:address":"1068 N Hacienda Blvd",
    "sg:city":"La Puente",
    "sg:classifiers":[
        {
            "category":"Personal",
            "subcategory":"Beauty Salon",
            "type":"Services"
        }
    ],
    "sg:phone":"+1 626 918 6242",
    "sg:postcode":"91744",
    "sg:province":"CA",
    "wof:name":"Gladys Hair Studio",
    "wof:placetype":"venue"
},
  "geometry": {"coordinates":[-117.949636,34.039394],"type":"Point"}
}