{
  "type": "Feature",
  "properties": {
    "addr:full":"2213 S Hickory Pl Ontario CA 91762",
    "addr:housenumber":"2213",
    "addr:postcode":"91762",
    "addr:street":"S Hickory Pl",
    "iso:country":"US",
    "sg:address":"2213 S Hickory Pl",
    "sg:city":"Ontario",
    "sg:classifiers":[
        {
            "category":"Professional",
            "subcategory":"Art Services",
            "type":"Services"
        }
    ],
    "sg:phone":"+1 909 395 0708",
    "sg:postcode":"91762",
    "sg:province":"CA",
    "sg:tags":[
        "interior",
        "designer",
        "decorator"
    ],
    "wof:name":"Susys Greenery Interior",
    "wof:placetype":"venue"
},
  "geometry": {"coordinates":[-117.66136299999999,34.033031],"type":"Point"}
}