{
  "type": "Feature",
  "properties": {
    "iso:country":"US",
    "sg:address":"711 E Balboa Boulevard",
    "sg:city":"Newport Beach",
    "sg:classifiers":[
        {
            "category":"Coffee & Tea",
            "type":"Food & Drink"
        },
        {
            "category":"Restaurant",
            "type":"Food & Drink"
        }
    ],
    "sg:phone":"+1 949 675 2675",
    "sg:postcode":"92661",
    "sg:province":"CA",
    "sg:tags":[
        "traditional",
        "american",
        "brunch",
        "breakfast"
    ],
    "wof:name":"Miaafe Newport Beach",
    "wof:placetype":"venue"
},
  "geometry": {"coordinates":[-117.899477,33.602127],"type":"Point"}
}