{
  "type": "Feature",
  "properties": {
    "iso:country":"US",
    "sg:address":"9192 Kapaa Dr",
    "sg:city":"Huntington Beach",
    "sg:classifiers":[
        {
            "category":"Manufacturing",
            "subcategory":"Chemicals & Compounds",
            "type":"Manufacturing & Wholesale Goods"
        }
    ],
    "sg:phone":"+1 714 968 6825",
    "sg:postcode":"92646",
    "sg:province":"CA",
    "sg:tags":[
        "product",
        "mfg"
    ],
    "wof:name":"Precision Coatings",
    "wof:placetype":"venue"
},
  "geometry": {"coordinates":[-117.9701,33.644335],"type":"Point"}
}