{
  "type": "Feature",
  "properties": {
    "iso:country":"US",
    "sg:address":"8733 N Magnolia Ave",
    "sg:city":"Santee",
    "sg:classifiers":[
        {
            "category":"Wholesale",
            "subcategory":"Hardware",
            "type":"Manufacturing & Wholesale Goods"
        }
    ],
    "sg:phone":"+1 619 258 4259",
    "sg:postcode":"92071",
    "sg:province":"CA",
    "sg:tags":[
        "heater"
    ],
    "wof:name":"L E Schoonmaker Heating & Air",
    "wof:placetype":"venue"
},
  "geometry": {"coordinates":[-116.964815,32.834067],"type":"Point"}
}