{
  "type": "Feature",
  "properties": {
    "addr:full":"25865 San Fernando Rd Saugus CA 91350",
    "addr:housenumber":"25865",
    "addr:postcode":"91350",
    "addr:street":"San Fernando Rd",
    "iso:country":"US",
    "sg:address":"25865 San Fernando Rd",
    "sg:city":"Saugus",
    "sg:classifiers":[
        {
            "category":"Food & Beverages",
            "subcategory":"Groceries & Convenience Stores",
            "type":"Retail Goods"
        }
    ],
    "sg:phone":"+1 661 259 0223",
    "sg:postcode":"91350",
    "sg:province":"CA",
    "sg:tags":[
        "grocer"
    ],
    "wof:name":"Saugus Superette",
    "wof:placetype":"venue"
},
  "geometry": {"coordinates":[-118.540791,34.412142],"type":"Point"}
}