{
  "type": "Feature",
  "properties": {
    "iso:country":"US",
    "sg:address":"2501 Harbor Blvd",
    "sg:city":"Costa Mesa",
    "sg:classifiers":[
        {
            "category":"Farming",
            "subcategory":"Farm",
            "type":"Manufacturing & Wholesale Goods"
        }
    ],
    "sg:phone":"+1 714 708 1662",
    "sg:postcode":"92626",
    "sg:province":"CA",
    "wof:name":"Foxpoint Farms",
    "wof:placetype":"venue"
},
  "geometry": {"coordinates":[-117.91928,33.66383],"type":"Point"}
}