{
  "type": "Feature",
  "properties": {
    "addr:full":"120 Avram Ave Rohnert Park CA 94928",
    "addr:housenumber":"120",
    "addr:postcode":"94928",
    "addr:street":"Avram Ave",
    "iso:country":"US",
    "sg:address":"120 Avram Ave",
    "sg:city":"Rohnert Park",
    "sg:classifiers":[
        {
            "category":"Manufacturing",
            "subcategory":"Printing",
            "type":"Manufacturing & Wholesale Goods"
        }
    ],
    "sg:phone":"+1 707 792 6971",
    "sg:postcode":"94928",
    "sg:province":"CA",
    "sg:tags":[
        "publisher",
        "software"
    ],
    "wof:name":"S 2 Games",
    "wof:placetype":"venue"
},
  "geometry": {"coordinates":[-122.710264,38.342505],"type":"Point"}
}