{
  "type": "Feature",
  "properties": {
    "addr:full":"25078 Peachland Ave Ste B Santa Clarita CA 91321",
    "addr:postcode":"25078;91321",
    "addr:street":"Peachland Ave Ste B",
    "iso:country":"US",
    "sg:address":"25078 Peachland Ave Ste B",
    "sg:city":"Santa Clarita",
    "sg:classifiers":[
        {
            "category":"Health Services",
            "subcategory":"Health Practitioner",
            "type":"Services"
        }
    ],
    "sg:phone":"+1 661 310 7373",
    "sg:postcode":"91321",
    "sg:province":"CA",
    "sg:tags":[
        "nutritionist"
    ],
    "wof:name":"Women's Health Advantage LLC",
    "wof:placetype":"venue"
},
  "geometry": {"coordinates":[-118.546736,34.378806],"type":"Point"}
}