{
  "type": "Feature",
  "properties": {
    "iso:country":"US",
    "sg:address":"22501 Crenshaw Blvd #200",
    "sg:city":"Torrance",
    "sg:classifiers":[
        {
            "category":"Coffee & Tea",
            "type":"Food & Drink"
        }
    ],
    "sg:phone":"+1 310 325 1279",
    "sg:postcode":"90505",
    "sg:province":"CA",
    "sg:website":"www.boba-loca.com",
    "wof:name":"Boba Loca",
    "wof:placetype":"venue"
},
  "geometry": {"coordinates":[-118.329002,33.8218],"type":"Point"}
}