{
  "type": "Feature",
  "properties": {
    "iso:country":"US",
    "sg:address":"3824 Chester Ave",
    "sg:city":"Bakersfield",
    "sg:classifiers":[
        {
            "category":"Shopping",
            "subcategory":"Hobbies, Toys, & Games",
            "type":"Retail Goods"
        }
    ],
    "sg:phone":"+1 661 328 1481",
    "sg:postcode":"93301",
    "sg:province":"CA",
    "sg:tags":[
        "model",
        "supply"
    ],
    "wof:name":"Showtime RC Speedway",
    "wof:placetype":"venue"
},
  "geometry": {"coordinates":[-119.018633,35.395993],"type":"Point"}
}