{
  "type": "Feature",
  "properties": {
    "addr:full":"2531 S San Pedro Street Los Angeles CA 90011",
    "addr:housenumber":"2531",
    "addr:postcode":"90011",
    "addr:street":"S San Pedro Street",
    "iso:country":"US",
    "sg:address":"2531 S San Pedro Street",
    "sg:city":"Los Angeles",
    "sg:classifiers":[
        {
            "category":"Restaurant",
            "type":"Food & Drink"
        }
    ],
    "sg:phone":"+1 213 748 6118",
    "sg:postcode":"90011",
    "sg:province":"CA",
    "wof:name":"Chinatown Express",
    "wof:placetype":"venue"
},
  "geometry": {"coordinates":[-118.26109099999999,34.021684],"type":"Point"}
}