{
  "type": "Feature",
  "properties": {
    "iso:country":"US",
    "sg:address":"2730 State St",
    "sg:city":"Carlsbad",
    "sg:classifiers":[
        {
            "category":"Retail",
            "subcategory":"Auto Repair",
            "type":"Services"
        }
    ],
    "sg:phone":"+1 760 729 9323",
    "sg:postcode":"92008",
    "sg:province":"CA",
    "wof:name":"Ignition Interlock Systems of California",
    "wof:placetype":"venue"
},
  "geometry": {"coordinates":[-117.350998,33.162201],"type":"Point"}
}