{
  "type": "Feature",
  "properties": {
    "iso:country":"US",
    "sg:address":"12500 Riverside Dr Ste 201-C",
    "sg:city":"Valley Village",
    "sg:classifiers":[
        {
            "category":"Banks & Credit Unions",
            "subcategory":"Financial Services",
            "type":"Services"
        }
    ],
    "sg:phone":"+1 818 761 9102",
    "sg:postcode":"91607",
    "sg:province":"CA",
    "sg:website":"www.moneyfortitle.com",
    "wof:name":"Discount Title Loans",
    "wof:placetype":"venue"
},
  "geometry": {"coordinates":[-118.405659,34.157265],"type":"Point"}
}