{
  "type": "Feature",
  "properties": {
    "iso:country":"US",
    "sg:address":"18430 Bandilier Cir",
    "sg:city":"Fountain Valley",
    "sg:classifiers":[
        {
            "category":"Building & Trades",
            "subcategory":"Construction",
            "type":"Services"
        }
    ],
    "sg:phone":"+1 714 963 0011",
    "sg:postcode":"92708",
    "sg:province":"CA",
    "sg:tags":[
        "interior",
        "design"
    ],
    "sg:website":"www.canvasinteriordesign.com",
    "wof:name":"Canvas Interior Design",
    "wof:placetype":"venue"
},
  "geometry": {"coordinates":[-117.940265,33.694638],"type":"Point"}
}