{
  "type": "Feature",
  "properties": {
    "iso:country":"US",
    "sg:address":"268 Ruby Ave",
    "sg:city":"San Carlos",
    "sg:classifiers":[
        {
            "category":"Shopping",
            "subcategory":"Computers & Home Electronics",
            "type":"Retail Goods"
        }
    ],
    "sg:phone":"+1 650 594 9058",
    "sg:postcode":"94070",
    "sg:province":"CA",
    "sg:tags":[
        "software"
    ],
    "wof:name":"Consultech",
    "wof:placetype":"venue"
},
  "geometry": {"coordinates":[-122.255808,37.486124],"type":"Point"}
}