{
  "type": "Feature",
  "properties": {
    "addr:full":"6986 El Camino Real Carlsbad CA 92009",
    "addr:housenumber":"6986",
    "addr:postcode":"92009",
    "addr:street":"El Camino Real",
    "iso:country":"US",
    "sg:address":"6986 El Camino Real",
    "sg:city":"Carlsbad",
    "sg:classifiers":[
        {
            "category":"Health Services",
            "subcategory":"Chiropractor",
            "type":"Services"
        }
    ],
    "sg:phone":"+1 760 438 9548",
    "sg:postcode":"92009",
    "sg:province":"CA",
    "sg:website":"www.lacostachiropractic.com",
    "wof:name":"Miller James R DC",
    "wof:placetype":"venue"
},
  "geometry": {"coordinates":[-117.26599899999999,33.102402],"type":"Point"}
}