{
  "type": "Feature",
  "properties": {
    "addr:full":"18650 Farragut Ln Los Gatos CA 95030",
    "addr:housenumber":"18650",
    "addr:postcode":"95030",
    "addr:street":"Farragut Ln",
    "iso:country":"US",
    "sg:address":"18650 Farragut Ln",
    "sg:city":"Los Gatos",
    "sg:classifiers":[
        {
            "category":"Real Estate",
            "subcategory":"Real Estate Operator",
            "type":"Services"
        }
    ],
    "sg:phone":"+1 408 354 9586",
    "sg:postcode":"95030",
    "sg:province":"CA",
    "sg:tags":[
        "building",
        "nonresidential"
    ],
    "wof:name":"J L & Associates",
    "wof:placetype":"venue"
},
  "geometry": {"coordinates":[-121.997343,37.23774],"type":"Point"}
}