{
  "type": "Feature",
  "properties": {
    "addr:full":"26962 St Julian Cir Murrieta CA 92563",
    "addr:housenumber":"26962",
    "addr:postcode":"92563",
    "addr:street":"St Julian Cir",
    "iso:country":"US",
    "sg:address":"26962 St Julian Cir",
    "sg:city":"Murrieta",
    "sg:classifiers":[
        {
            "category":"Bakery",
            "type":"Food & Drink"
        }
    ],
    "sg:phone":"+1 951 415 1380",
    "sg:postcode":"92563",
    "sg:province":"CA",
    "wof:name":"S&T Bakery",
    "wof:placetype":"venue"
},
  "geometry": {"coordinates":[-117.14546,33.549151],"type":"Point"}
}