{
  "type": "Feature",
  "properties": {
    "iso:country":"US",
    "sg:address":"118 N Mott St",
    "sg:city":"Los Angeles",
    "sg:classifiers":[
        {
            "category":"Place Of Worship",
            "subcategory":"Temple",
            "type":"Public Place"
        }
    ],
    "sg:phone":"+1 323 269 4741",
    "sg:postcode":"90033",
    "sg:province":"CA",
    "sg:tags":[
        "buddhist"
    ],
    "wof:name":"Rissho Kosei Kai Buddhist Church",
    "wof:placetype":"venue"
},
  "geometry": {"coordinates":[-118.205002,34.0429],"type":"Point"}
}