{
  "type": "Feature",
  "properties": {
    "iso:country":"US",
    "sg:address":"2525 El Camino Real",
    "sg:city":"Redwood City",
    "sg:classifiers":[
        {
            "category":"Professional",
            "type":"Services"
        },
        {
            "category":"Restaurant",
            "type":"Food & Drink"
        }
    ],
    "sg:menulink":"http://www.allmenus.com/ca/san-mateo/51922-sichuan-delight/menu/",
    "sg:phone":"+1 650 701 0814",
    "sg:postcode":"94061",
    "sg:province":"CA",
    "sg:tags":[
        "asian",
        "chinese"
    ],
    "wof:name":"Sichuan Delight",
    "wof:placetype":"venue"
},
  "geometry": {"coordinates":[-122.21826299999999,37.473819],"type":"Point"}
}