{
  "type": "Feature",
  "properties": {
    "addr:full":"7008 Llama St Carlsbad CA 92009",
    "addr:housenumber":"7008",
    "addr:postcode":"92009",
    "addr:street":"Llama St",
    "iso:country":"US",
    "sg:address":"7008 Llama St",
    "sg:city":"Carlsbad",
    "sg:classifiers":[
        {
            "category":"Wholesale",
            "subcategory":"Groceries",
            "type":"Manufacturing & Wholesale Goods"
        }
    ],
    "sg:phone":"+1 760 929 0216",
    "sg:postcode":"92009",
    "sg:province":"CA",
    "sg:tags":[
        "food",
        "product"
    ],
    "wof:name":"Devinor",
    "wof:placetype":"venue"
},
  "geometry": {"coordinates":[-117.242316,33.10214],"type":"Point"}
}