{
  "type": "Feature",
  "properties": {
    "iso:country":"US",
    "sg:address":"2275 Torrance Blvd",
    "sg:city":"Torrance",
    "sg:classifiers":[
        {
            "category":"Education",
            "subcategory":"Special Training",
            "type":"Public Place"
        }
    ],
    "sg:phone":"+1 310 533 1335",
    "sg:postcode":"90501",
    "sg:province":"CA",
    "sg:tags":[
        "elementary",
        "school",
        "tutoring"
    ],
    "wof:name":"Skills For School",
    "wof:placetype":"venue"
},
  "geometry": {"coordinates":[-118.322998,33.836399],"type":"Point"}
}