{
  "type": "Feature",
  "properties": {
    "addr:full":"13851 Fremont Pines Ln Los Altos Hills CA 94022",
    "addr:housenumber":"13851",
    "addr:postcode":"94022",
    "addr:street":"Fremont Pines Ln",
    "iso:country":"US",
    "sg:address":"13851 Fremont Pines Ln",
    "sg:city":"Los Altos Hills",
    "sg:classifiers":[
        {
            "category":"Shopping",
            "subcategory":"Computers & Home Electronics",
            "type":"Retail Goods"
        }
    ],
    "sg:phone":"+1 650 949 0942",
    "sg:postcode":"94022",
    "sg:province":"CA",
    "sg:tags":[
        "software"
    ],
    "sg:website":"www.inet-sciences.com",
    "wof:name":"Internet Software Sciences",
    "wof:placetype":"venue"
},
  "geometry": {"coordinates":[-122.131446,37.381776],"type":"Point"}
}