{
  "type": "Feature",
  "properties": {
    "addr:full":"1132 Santee St Los Angeles CA 90015",
    "addr:housenumber":"1132",
    "addr:postcode":"90015",
    "addr:street":"Santee St",
    "iso:country":"US",
    "sg:address":"1132 Santee St",
    "sg:city":"Los Angeles",
    "sg:classifiers":[
        {
            "category":"Wholesale",
            "subcategory":"Apparel",
            "type":"Manufacturing & Wholesale Goods"
        },
        {
            "category":"Shopping",
            "subcategory":"Clothing, Apparel, & Fashions",
            "type":"Retail Goods"
        }
    ],
    "sg:phone":"+1 213 746 7363",
    "sg:postcode":"90015",
    "sg:province":"CA",
    "sg:tags":[
        "work",
        "w"
    ],
    "wof:name":"Crazy Jeans Fashion",
    "wof:placetype":"venue"
},
  "geometry": {"coordinates":[-118.256942,34.036734],"type":"Point"}
}