{
  "type": "Feature",
  "properties": {
    "addr:full":"29851 Aventura Rancho Santa Margarita CA 92688",
    "addr:housenumber":"29851",
    "addr:postcode":"92688",
    "addr:street":"Aventura",
    "iso:country":"US",
    "sg:address":"29851 Aventura",
    "sg:city":"Rancho Santa Margarita",
    "sg:classifiers":[
        {
            "category":"Manufacturing",
            "subcategory":"Food",
            "type":"Manufacturing & Wholesale Goods"
        }
    ],
    "sg:phone":"+1 949 459 5677",
    "sg:postcode":"92688",
    "sg:province":"CA",
    "sg:tags":[
        "malt",
        "beverage",
        "mfg"
    ],
    "wof:name":"Saddleback Brewery",
    "wof:placetype":"venue"
},
  "geometry": {"coordinates":[-117.611474,33.635916],"type":"Point"}
}