{
  "type": "Feature",
  "properties": {
    "addr:full":"4246 W Ashlan Ave Fresno CA 93722",
    "addr:housenumber":"4246",
    "addr:postcode":"93722",
    "addr:street":"W Ashlan Ave",
    "iso:country":"US",
    "sg:address":"4246 W Ashlan Ave",
    "sg:city":"Fresno",
    "sg:classifiers":[
        {
            "category":"Food & Beverages",
            "subcategory":"Groceries & Convenience Stores",
            "type":"Retail Goods"
        }
    ],
    "sg:phone":"+1 559 275 6970",
    "sg:postcode":"93722",
    "sg:province":"CA",
    "wof:name":"7-Eleven",
    "wof:placetype":"venue"
},
  "geometry": {"coordinates":[-119.866074,36.793693],"type":"Point"}
}