{
  "type": "Feature",
  "properties": {
    "iso:country":"US",
    "sg:address":"2181 Logan Ave",
    "sg:city":"San Diego",
    "sg:classifiers":[
        {
            "category":"Personal",
            "subcategory":"Barber",
            "type":"Services"
        },
        {
            "category":"Coffee & Tea",
            "type":"Food & Drink"
        },
        {
            "category":"Personal",
            "subcategory":"Tattoo Parlor",
            "type":"Services"
        }
    ],
    "sg:phone":"+1 619 702 4822",
    "sg:postcode":"92113",
    "sg:province":"CA",
    "sg:website":"www.tworosesinc.com",
    "wof:name":"Two Roses Tattoo",
    "wof:placetype":"venue"
},
  "geometry": {"coordinates":[-117.1396,32.698244],"type":"Point"}
}