{
  "type": "Feature",
  "properties": {
    "addr:full":"3237 Grand Ave Oakland CA 94610",
    "addr:housenumber":"3237",
    "addr:postcode":"94610",
    "addr:street":"Grand Ave",
    "iso:country":"US",
    "sg:address":"3237 Grand Ave",
    "sg:city":"Oakland",
    "sg:classifiers":[
        {
            "category":"Shopping",
            "subcategory":"Bicycles & Sporting Goods",
            "type":"Retail Goods"
        }
    ],
    "sg:phone":"+1 510 444 2459",
    "sg:postcode":"94610",
    "sg:province":"CA",
    "wof:name":"Recycle Sports",
    "wof:placetype":"venue"
},
  "geometry": {"coordinates":[-122.246915,37.813378],"type":"Point"}
}