{
  "type": "Feature",
  "properties": {
    "addr:full":"5309 Carrington Cir Stockton CA 95210",
    "addr:housenumber":"5309",
    "addr:postcode":"95210",
    "addr:street":"Carrington Cir",
    "iso:country":"US",
    "sg:address":"5309 Carrington Cir",
    "sg:city":"Stockton",
    "sg:classifiers":[
        {
            "category":"Health Services",
            "subcategory":"Doctor",
            "type":"Services"
        }
    ],
    "sg:phone":"+1 209 951 4100",
    "sg:postcode":"95210",
    "sg:province":"CA",
    "sg:tags":[
        "physician",
        "surgeon"
    ],
    "wof:name":"Dennis W Del Paine Inc",
    "wof:placetype":"venue"
},
  "geometry": {"coordinates":[-121.29331500000001,38.005121],"type":"Point"}
}