{
  "type": "Feature",
  "properties": {
    "iso:country":"US",
    "sg:address":"3020 Oceanside Blvd Apt 1",
    "sg:city":"Oceanside",
    "sg:phone":"+1 760 721 9332",
    "sg:postcode":"92054",
    "sg:province":"CA",
    "sg:website":"http://www.buccaneeraptsga.com",
    "wof:name":"Creekwood Villas",
    "wof:placetype":"venue"
},
  "geometry": {"coordinates":[-117.336342,33.203072],"type":"Point"}
}