{
  "type": "Feature",
  "properties": {
    "iso:country":"US",
    "sg:address":"1567 Pioneer Way",
    "sg:city":"El Cajon",
    "sg:classifiers":[
        {
            "category":"Professional",
            "subcategory":"Art Services",
            "type":"Services"
        }
    ],
    "sg:phone":"+1 619 401 8929",
    "sg:postcode":"92020",
    "sg:province":"CA",
    "sg:tags":[
        "graphic",
        "designer"
    ],
    "wof:name":"Prevail Productions",
    "wof:placetype":"venue"
},
  "geometry": {"coordinates":[-116.967679,32.813326],"type":"Point"}
}