{
  "type": "Feature",
  "properties": {
    "addr:full":"26732 Crown Valley Parkway Mission Viejo CA 92691",
    "addr:housenumber":"26732",
    "addr:postcode":"92691",
    "addr:street":"Crown Valley Parkway",
    "iso:country":"US",
    "sg:address":"26732 Crown Valley Parkway",
    "sg:city":"Mission Viejo",
    "sg:classifiers":[
        {
            "category":"Health Services",
            "subcategory":"Dentist",
            "type":"Services"
        }
    ],
    "sg:phone":"+1 949 364 5127",
    "sg:postcode":"92691",
    "sg:province":"CA",
    "sg:website":"www.missionendo.com",
    "wof:name":"Buoncristiani John R DDS",
    "wof:placetype":"venue"
},
  "geometry": {"coordinates":[-117.664734,33.563756],"type":"Point"}
}