{
  "type": "Feature",
  "properties": {
    "addr:full":"153 Verdugo Ave Glendora CA 91741",
    "addr:housenumber":"153",
    "addr:postcode":"91741",
    "addr:street":"Verdugo Ave",
    "iso:country":"US",
    "sg:address":"153 Verdugo Ave",
    "sg:city":"Glendora",
    "sg:classifiers":[
        {
            "category":"Insurance",
            "subcategory":"Insurance Agent",
            "type":"Services"
        }
    ],
    "sg:phone":"+1 626 963 7384",
    "sg:postcode":"91741",
    "sg:province":"CA",
    "wof:name":"Donohoe Mallie",
    "wof:placetype":"venue"
},
  "geometry": {"coordinates":[-117.830692,34.136307],"type":"Point"}
}