{
  "type": "Feature",
  "properties": {
    "addr:full":"20524 Wisteria St Castro Valley CA 94546",
    "addr:housenumber":"20524",
    "addr:postcode":"94546",
    "addr:street":"Wisteria St",
    "iso:country":"US",
    "sg:address":"20524 Wisteria St",
    "sg:city":"Castro Valley",
    "sg:classifiers":[
        {
            "category":"Health Services",
            "subcategory":"Nursing And Care Facility",
            "type":"Services"
        }
    ],
    "sg:phone":"+1 510 727 9169",
    "sg:postcode":"94546",
    "sg:province":"CA",
    "sg:tags":[
        "home",
        "convalescent"
    ],
    "wof:name":"Wisteria Care Ctr",
    "wof:placetype":"venue"
},
  "geometry": {"coordinates":[-122.085043,37.695828],"type":"Point"}
}