{
  "type": "Feature",
  "properties": {
    "iso:country":"US",
    "sg:address":"649 Gayley Ave Ste 21",
    "sg:city":"Los Angeles",
    "sg:classifiers":[
        {
            "category":"Real Estate",
            "subcategory":"Real Estate Services",
            "type":"Services"
        }
    ],
    "sg:phone":"+1 310 824 0931",
    "sg:postcode":"90024",
    "sg:province":"CA",
    "sg:tags":[
        "management",
        "property"
    ],
    "sg:website":"www.bnbwestwood.com",
    "wof:name":"B & B Management",
    "wof:placetype":"venue"
},
  "geometry": {"coordinates":[-118.448055,34.066733],"type":"Point"}
}