{
  "type": "Feature",
  "properties": {
    "addr:full":"481 Pleasant Valley Rd Port Hueneme CA 93041",
    "addr:housenumber":"481",
    "addr:postcode":"93041",
    "addr:street":"Pleasant Valley Rd",
    "iso:country":"US",
    "sg:address":"481 Pleasant Valley Rd",
    "sg:city":"Port Hueneme",
    "sg:classifiers":[
        {
            "category":"Personal",
            "subcategory":"Beauty Salon",
            "type":"Services"
        }
    ],
    "sg:phone":"+1 805 487 8708",
    "sg:postcode":"93041",
    "sg:province":"CA",
    "wof:name":"Virginia LA Forteza Hair Ctr",
    "wof:placetype":"venue"
},
  "geometry": {"coordinates":[-119.19376099999999,34.15486],"type":"Point"}
}