{
  "type": "Feature",
  "properties": {
    "iso:country":"US",
    "sg:address":"524 E Washington Boulevard",
    "sg:city":"Los Angeles",
    "sg:classifiers":[
        {
            "category":"Building & Trades",
            "subcategory":"Locksmith",
            "type":"Services"
        }
    ],
    "sg:phone":"+1 323 924 6741",
    "sg:postcode":"90015",
    "sg:province":"CA",
    "sg:tags":[
        "key"
    ],
    "wof:name":"Locksmith",
    "wof:placetype":"venue"
},
  "geometry": {"coordinates":[-118.258522,34.029341],"type":"Point"}
}