{
  "type": "Feature",
  "properties": {
    "addr:full":"45541 Northport Loop W Fremont CA 94538",
    "addr:housenumber":"45541",
    "addr:postcode":"94538",
    "addr:street":"Northport Loop W",
    "iso:country":"US",
    "sg:address":"45541 Northport Loop W",
    "sg:city":"Fremont",
    "sg:classifiers":[
        {
            "category":"Wholesale",
            "subcategory":"Stationery",
            "type":"Manufacturing & Wholesale Goods"
        }
    ],
    "sg:phone":"+1 510 770 3500",
    "sg:postcode":"94538",
    "sg:province":"CA",
    "sg:tags":[
        "packaging",
        "professional",
        "material",
        "paper"
    ],
    "sg:website":"www.stephengould.com",
    "wof:name":"Stephen Gould of California",
    "wof:placetype":"venue"
},
  "geometry": {"coordinates":[-121.956001,37.492298],"type":"Point"}
}