{
  "type": "Feature",
  "properties": {
    "addr:full":"200 W Arbor Dr Dept 8656 San Diego CA 92103",
    "addr:housenumber":"200",
    "addr:postcode":"8656;92103",
    "addr:street":"W Arbor Dr",
    "iso:country":"US",
    "sg:address":"200 W Arbor Dr Dept 8656",
    "sg:city":"San Diego",
    "sg:classifiers":[
        {
            "category":"Education",
            "subcategory":"University",
            "type":"Public Place"
        }
    ],
    "sg:phone":"+1 858 569 1866",
    "sg:postcode":"92103",
    "sg:province":"CA",
    "sg:tags":[
        "college"
    ],
    "wof:name":"University of California San Diego",
    "wof:placetype":"venue"
},
  "geometry": {"coordinates":[-117.164969,32.753917],"type":"Point"}
}