{
  "type": "Feature",
  "properties": {
    "addr:full":"13295 Spring Valley Pkwy Victorville CA 92395",
    "addr:housenumber":"13295",
    "addr:postcode":"92395",
    "addr:street":"Spring Valley Pkwy",
    "iso:country":"US",
    "sg:address":"13295 Spring Valley Pkwy",
    "sg:city":"Victorville",
    "sg:classifiers":[
        {
            "category":"Insurance",
            "subcategory":"Insurance Agent",
            "type":"Services"
        }
    ],
    "sg:phone":"+1 760 241 2257",
    "sg:postcode":"92395",
    "sg:province":"CA",
    "sg:tags":[
        "accident"
    ],
    "wof:name":"Senior Planning Advisors",
    "wof:placetype":"venue"
},
  "geometry": {"coordinates":[-117.26979,34.494522],"type":"Point"}
}