{
  "type": "Feature",
  "properties": {
    "iso:country":"US",
    "sg:address":"10801 Olson Dr",
    "sg:city":"Rancho Cordova",
    "sg:classifiers":[
        {
            "category":"Shopping",
            "subcategory":"Department Store",
            "type":"Retail Goods"
        }
    ],
    "sg:phone":"+1 916 635 9735",
    "sg:postcode":"95670",
    "sg:province":"CA",
    "sg:tags":[
        "shop"
    ],
    "wof:name":"Pier 1 Imports",
    "wof:placetype":"venue"
},
  "geometry": {"coordinates":[-121.28138300000001,38.598331],"type":"Point"}
}