{
  "type": "Feature",
  "properties": {
    "addr:full":"880 E Merritt Ave Tulare CA 93274",
    "addr:housenumber":"880",
    "addr:postcode":"93274",
    "addr:street":"E Merritt Ave",
    "iso:country":"US",
    "sg:address":"880 E Merritt Ave",
    "sg:city":"Tulare",
    "sg:classifiers":[
        {
            "category":"Health Services",
            "subcategory":"Medical Lab",
            "type":"Services"
        }
    ],
    "sg:phone":"+1 559 688 7500",
    "sg:postcode":"93274",
    "sg:province":"CA",
    "sg:tags":[
        "x",
        "laboratory"
    ],
    "wof:name":"Family X-Ray Ctr Of Tulare",
    "wof:placetype":"venue"
},
  "geometry": {"coordinates":[-119.333558,36.222073],"type":"Point"}
}