{
  "type": "Feature",
  "properties": {
    "iso:country":"US",
    "sg:address":"1225 Division St",
    "sg:city":"Napa",
    "sg:classifiers":[
        {
            "category":"Retail",
            "subcategory":"Portrait Studio",
            "type":"Services"
        }
    ],
    "sg:phone":"+1 707 257 1166",
    "sg:postcode":"94559",
    "sg:province":"CA",
    "sg:tags":[
        "photographer"
    ],
    "sg:website":"www.artclarity.com",
    "wof:name":"Art & Clarity",
    "wof:placetype":"venue"
},
  "geometry": {"coordinates":[-122.285456,38.294987],"type":"Point"}
}