{
  "type": "Feature",
  "properties": {
    "addr:full":"4371 Vale St Irvine CA 92604",
    "addr:housenumber":"4371",
    "addr:postcode":"92604",
    "addr:street":"Vale St",
    "iso:country":"US",
    "sg:address":"4371 Vale St",
    "sg:city":"Irvine",
    "sg:classifiers":[
        {
            "category":"Professional",
            "type":"Services"
        }
    ],
    "sg:phone":"+1 949 651 1382",
    "sg:postcode":"92604",
    "sg:province":"CA",
    "wof:name":"Lamb Oil Inc",
    "wof:placetype":"venue"
},
  "geometry": {"coordinates":[-117.785231,33.700663],"type":"Point"}
}