{
  "type": "Feature",
  "properties": {
    "addr:full":"6700 Sepulveda Blvd Van Nuys CA 91411",
    "addr:housenumber":"6700",
    "addr:postcode":"91411",
    "addr:street":"Sepulveda Blvd",
    "iso:country":"US",
    "sg:address":"6700 Sepulveda Blvd",
    "sg:city":"Van Nuys",
    "sg:classifiers":[
        {
            "category":"Health Services",
            "subcategory":"Nursing And Care Facility",
            "type":"Services"
        }
    ],
    "sg:phone":"+1 818 373 5429",
    "sg:postcode":"91411",
    "sg:province":"CA",
    "sg:tags":[
        "home",
        "convalescent"
    ],
    "wof:name":"California Healthcare",
    "wof:placetype":"venue"
},
  "geometry": {"coordinates":[-118.46618599999999,34.193009],"type":"Point"}
}