{
  "type": "Feature",
  "properties": {
    "iso:country":"US",
    "sg:address":"3802 Rosecrans St",
    "sg:city":"San Diego",
    "sg:classifiers":[
        {
            "category":"Building & Trades",
            "subcategory":"Construction",
            "type":"Services"
        }
    ],
    "sg:phone":"+1 619 559 4414",
    "sg:postcode":"92110",
    "sg:province":"CA",
    "sg:tags":[
        "hanging",
        "contractor"
    ],
    "wof:name":"Paint Deco",
    "wof:placetype":"venue"
},
  "geometry": {"coordinates":[-117.202952,32.753451],"type":"Point"}
}