{
  "type": "Feature",
  "properties": {
    "iso:country":"US",
    "sg:address":"2256 Tokaj Rd",
    "sg:city":"Spring Valley",
    "sg:classifiers":[
        {
            "category":"Banks & Credit Unions",
            "subcategory":"Investment Brokerage",
            "type":"Services"
        }
    ],
    "sg:phone":"+1 619 825 6763",
    "sg:postcode":"91977",
    "sg:province":"CA",
    "sg:tags":[
        "advisory",
        "financial"
    ],
    "wof:name":"Coast Capital Group",
    "wof:placetype":"venue"
},
  "geometry": {"coordinates":[-117.002578,32.727117],"type":"Point"}
}