{
  "type": "Feature",
  "properties": {
    "iso:country":"US",
    "sg:address":"22600 Lambert St",
    "sg:city":"Lake Forest",
    "sg:classifiers":[
        {
            "category":"Wholesale",
            "subcategory":"Machinery & Supplies",
            "type":"Manufacturing & Wholesale Goods"
        }
    ],
    "sg:phone":"+1 949 699 1626",
    "sg:postcode":"92630",
    "sg:province":"CA",
    "sg:tags":[
        "product",
        "health",
        "beauty",
        "aide"
    ],
    "wof:name":"Molecule 2000 Inc",
    "wof:placetype":"venue"
},
  "geometry": {"coordinates":[-117.71473,33.634319],"type":"Point"}
}