{
  "type": "Feature",
  "properties": {
    "addr:full":"1174 N Gordon St Pomona CA 91768",
    "addr:housenumber":"1174",
    "addr:postcode":"91768",
    "addr:street":"N Gordon St",
    "iso:country":"US",
    "sg:address":"1174 N Gordon St",
    "sg:city":"Pomona",
    "sg:classifiers":[
        {
            "category":"Personal",
            "type":"Services"
        }
    ],
    "sg:phone":"+1 909 865 0465",
    "sg:postcode":"91768",
    "sg:province":"CA",
    "sg:tags":[
        "wedding",
        "chapel"
    ],
    "wof:name":"Johnny Hernandez",
    "wof:placetype":"venue"
},
  "geometry": {"coordinates":[-117.753612,34.067953],"type":"Point"}
}