{
  "type": "Feature",
  "properties": {
    "iso:country":"US",
    "sg:address":"10017 Davis Rd",
    "sg:city":"Wilton",
    "sg:classifiers":[
        {
            "category":"Social Services",
            "type":"Services"
        }
    ],
    "sg:phone":"+1 916 687 6794",
    "sg:postcode":"95693",
    "sg:province":"CA",
    "wof:name":"Horizon Children's Charities",
    "wof:placetype":"venue"
},
  "geometry": {"coordinates":[-121.260628,38.393582],"type":"Point"}
}