{
  "type": "Feature",
  "properties": {
    "addr:full":"1390 Market St San Francisco CA 94102",
    "addr:housenumber":"1390",
    "addr:postcode":"94102",
    "addr:street":"Market St",
    "iso:country":"US",
    "sg:address":"1390 Market St",
    "sg:city":"San Francisco",
    "sg:classifiers":[
        {
            "category":"Professional",
            "subcategory":"Lawyer & Legal Services",
            "type":"Services"
        }
    ],
    "sg:phone":"+1 415 626 5400",
    "sg:postcode":"94102",
    "sg:province":"CA",
    "sg:tags":[
        "attorney"
    ],
    "wof:name":"Michael Mandel Law Offices",
    "wof:placetype":"venue"
},
  "geometry": {"coordinates":[-122.416567,37.777502],"type":"Point"}
}