{
  "type": "Feature",
  "properties": {
    "iso:country":"US",
    "sg:address":"8873 Katella Ave",
    "sg:city":"Anaheim",
    "sg:classifiers":[
        {
            "category":"Manufacturing",
            "subcategory":"Tools & Machinery",
            "type":"Manufacturing & Wholesale Goods"
        }
    ],
    "sg:phone":"+1 714 827 5565",
    "sg:postcode":"92804",
    "sg:province":"CA",
    "sg:tags":[
        "measuring",
        "instrument",
        "electrical",
        "mfg"
    ],
    "wof:name":"World View Satelite",
    "wof:placetype":"venue"
},
  "geometry": {"coordinates":[-117.977701,33.80312],"type":"Point"}
}