{
  "type": "Feature",
  "properties": {
    "iso:country":"US",
    "sg:address":"3050 Shattuck Avenue",
    "sg:city":"Berkeley",
    "sg:classifiers":[
        {
            "category":"Professional",
            "subcategory":"Lawyer & Legal Services",
            "type":"Services"
        }
    ],
    "sg:phone":"+1 510 848 4752",
    "sg:postcode":"94705",
    "sg:province":"CA",
    "sg:tags":[
        "divorce",
        "law",
        "family"
    ],
    "wof:name":"Kaplan Jane R Atty",
    "wof:placetype":"venue"
},
  "geometry": {"coordinates":[-122.26599899999999,37.853298],"type":"Point"}
}