{
  "type": "Feature",
  "properties": {
    "addr:full":"19717 Wells Dr Woodland Hills CA 91364",
    "addr:housenumber":"19717",
    "addr:postcode":"91364",
    "addr:street":"Wells Dr",
    "iso:country":"US",
    "sg:address":"19717 Wells Dr",
    "sg:city":"Woodland Hills",
    "sg:classifiers":[
        {
            "category":"Arts & Performance",
            "subcategory":"Arts Center",
            "type":"Entertainment"
        }
    ],
    "sg:phone":"+1 818 888 2360",
    "sg:postcode":"91364",
    "sg:province":"CA",
    "sg:tags":[
        "performing"
    ],
    "wof:name":"Marvelous Entertainment Inc",
    "wof:placetype":"venue"
},
  "geometry": {"coordinates":[-118.56223799999999,34.163227],"type":"Point"}
}