{
  "type": "Feature",
  "properties": {
    "iso:country":"US",
    "sg:address":"2498 Roll Dr",
    "sg:city":"San Diego",
    "sg:classifiers":[
        {
            "category":"Freight",
            "type":"Transportation"
        }
    ],
    "sg:phone":"+1 619 710 4818",
    "sg:postcode":"92154",
    "sg:province":"CA",
    "sg:tags":[
        "logistics",
        "warehousing"
    ],
    "wof:name":"US Logistics Corporation",
    "wof:placetype":"venue"
},
  "geometry": {"coordinates":[-116.937699,32.556589],"type":"Point"}
}