{
  "type": "Feature",
  "properties": {
    "addr:full":"12463 Beach Blvd Stanton CA 92841",
    "addr:housenumber":"12463",
    "addr:postcode":"ca 92841",
    "addr:street":"Beach Blvd",
    "iso:country":"US",
    "sg:address":"12463 Beach Blvd",
    "sg:city":"Stanton",
    "sg:classifiers":[
        {
            "category":"Shopping",
            "subcategory":"Bicycles & Sporting Goods",
            "type":"Retail Goods"
        }
    ],
    "sg:phone":"+1 714 894 4021",
    "sg:postcode":"92841",
    "sg:province":"CA",
    "sg:tags":[
        "equipment",
        "arts",
        "supply",
        "martial"
    ],
    "wof:name":"Musashi Martial Arts Supplies",
    "wof:placetype":"venue"
},
  "geometry": {"coordinates":[-117.99294999999999,33.783253],"type":"Point"}
}