{
  "type": "Feature",
  "properties": {
    "iso:country":"US",
    "sg:address":"14518 Best Ave",
    "sg:city":"Santa Fe Springs",
    "sg:classifiers":[
        {
            "category":"Freight",
            "type":"Transportation"
        }
    ],
    "sg:phone":"+1 562 802 9177",
    "sg:postcode":"90670",
    "sg:province":"CA",
    "sg:tags":[
        "mover"
    ],
    "wof:name":"Mc Collister's Moving & Strg",
    "wof:placetype":"venue"
},
  "geometry": {"coordinates":[-118.044293,33.899668],"type":"Point"}
}