{
  "type": "Feature",
  "properties": {
    "addr:full":"227 7th St San Francisco CA 94103",
    "addr:housenumber":"227",
    "addr:postcode":"94103",
    "addr:street":"7Th St",
    "iso:country":"US",
    "sg:address":"227 7th St",
    "sg:city":"San Francisco",
    "sg:classifiers":[
        {
            "category":"Professional",
            "subcategory":"Computer Services",
            "type":"Services"
        }
    ],
    "sg:phone":"+1 415 651 4236",
    "sg:postcode":"94103",
    "sg:province":"CA",
    "sg:tags":[
        "consultant",
        "designer"
    ],
    "wof:name":"Rocket Science Consulting",
    "wof:placetype":"venue"
},
  "geometry": {"coordinates":[-122.408113,37.777125],"type":"Point"}
}