{
  "type": "Feature",
  "properties": {
    "iso:country":"US",
    "sg:address":"1320 S Mary Ave",
    "sg:city":"Sunnyvale",
    "sg:classifiers":[
        {
            "category":"Government",
            "subcategory":"Office",
            "type":"Public Place"
        }
    ],
    "sg:phone":"+1 408 733 2910",
    "sg:postcode":"94087",
    "sg:province":"CA",
    "sg:tags":[
        "national",
        "security"
    ],
    "wof:name":"US Recruiting Marine Corps",
    "wof:placetype":"venue"
},
  "geometry": {"coordinates":[-122.050466,37.350276],"type":"Point"}
}