{
  "type": "Feature",
  "properties": {
    "addr:full":"2028 Lake Ave Altadena CA 91001",
    "addr:housenumber":"2028",
    "addr:postcode":"91001",
    "addr:street":"Lake Ave",
    "iso:country":"US",
    "sg:address":"2028 Lake Ave",
    "sg:city":"Altadena",
    "sg:classifiers":[
        {
            "category":"Health Services",
            "subcategory":"Dentist",
            "type":"Services"
        }
    ],
    "sg:phone":"+1 626 797 7551",
    "sg:postcode":"91001",
    "sg:province":"CA",
    "wof:name":"Albert M Malouf Inc., Dentistry",
    "wof:placetype":"venue"
},
  "geometry": {"coordinates":[-118.131699,34.180758],"type":"Point"}
}