{
  "type": "Feature",
  "properties": {
    "iso:country":"US",
    "sg:address":"246 W College St",
    "sg:city":"Covina",
    "sg:classifiers":[
        {
            "category":"Shopping",
            "subcategory":"Pharmacy",
            "type":"Retail Goods"
        }
    ],
    "sg:phone":"+1 626 967 2641",
    "sg:postcode":"91723",
    "sg:province":"CA",
    "wof:name":"Omega Pharmacy",
    "wof:placetype":"venue"
},
  "geometry": {"coordinates":[-117.893646,34.087401],"type":"Point"}
}