{
  "type": "Feature",
  "properties": {
    "addr:full":"302 Broderick St San Francisco CA 94117",
    "addr:housenumber":"302",
    "addr:postcode":"94117",
    "addr:street":"Broderick St",
    "iso:country":"US",
    "sg:address":"302 Broderick St",
    "sg:city":"San Francisco",
    "sg:classifiers":[
        {
            "category":"Bakery",
            "type":"Food & Drink"
        }
    ],
    "sg:menulink":"http://www.allmenus.com/ca/san-francisco/137853-delessio-bakery/menu/",
    "sg:phone":"+1 415 552 5559",
    "sg:postcode":"94117",
    "sg:province":"CA",
    "sg:tags":[
        "american",
        "pastry"
    ],
    "wof:name":"Delessio Bakery",
    "wof:placetype":"venue"
},
  "geometry": {"coordinates":[-122.43914100000001,37.773082],"type":"Point"}
}