{
  "type": "Feature",
  "properties": {
    "addr:full":"8591 Elk Grove Blvd Elk Grove CA 95624",
    "addr:housenumber":"8591",
    "addr:postcode":"95624",
    "addr:street":"Elk Grove Blvd",
    "iso:country":"US",
    "sg:address":"8591 Elk Grove Blvd",
    "sg:city":"Elk Grove",
    "sg:classifiers":[
        {
            "category":"Restaurant",
            "type":"Food & Drink"
        }
    ],
    "sg:phone":"+1 916 685 1560",
    "sg:postcode":"95624",
    "sg:province":"CA",
    "sg:tags":[
        "pizza"
    ],
    "wof:name":"Pizza Bell",
    "wof:placetype":"venue"
},
  "geometry": {"coordinates":[-121.386803,38.40925],"type":"Point"}
}