{
  "type": "Feature",
  "properties": {
    "iso:country":"US",
    "sg:address":"2519 4th Ave",
    "sg:city":"San Diego",
    "sg:classifiers":[
        {
            "category":"Manufacturing",
            "subcategory":"Printing",
            "type":"Manufacturing & Wholesale Goods"
        }
    ],
    "sg:phone":"+1 619 234 6206",
    "sg:postcode":"92103",
    "sg:province":"CA",
    "sg:tags":[
        "printer"
    ],
    "wof:name":"Copy Shoppe Printing Inc",
    "wof:placetype":"venue"
},
  "geometry": {"coordinates":[-117.161131,32.732234],"type":"Point"}
}