{
  "type": "Feature",
  "properties": {
    "iso:country":"US",
    "sg:address":"2570 Jensen Ave Ste 105",
    "sg:city":"Sanger",
    "sg:classifiers":[
        {
            "category":"Health Services",
            "subcategory":"Doctor",
            "type":"Services"
        }
    ],
    "sg:phone":"+1 559 875 2000",
    "sg:postcode":"93657",
    "sg:province":"CA",
    "sg:tags":[
        "physician",
        "surgeon"
    ],
    "wof:name":"Banihashemi, Ali R Md",
    "wof:placetype":"venue"
},
  "geometry": {"coordinates":[-119.57262299999999,36.70679],"type":"Point"}
}