{
  "type": "Feature",
  "properties": {
    "iso:country":"US",
    "sg:address":"6108 Avenida Encinas Ste D",
    "sg:city":"Carlsbad",
    "sg:classifiers":[
        {
            "category":"Shopping",
            "subcategory":"Hobbies, Toys, & Games",
            "type":"Retail Goods"
        }
    ],
    "sg:phone":"+1 760 431 4794",
    "sg:postcode":"92011",
    "sg:province":"CA",
    "sg:tags":[
        "toy",
        "store"
    ],
    "wof:name":"UCC Distributing Inc",
    "wof:placetype":"venue"
},
  "geometry": {"coordinates":[-117.322503,33.117381],"type":"Point"}
}