{
  "type": "Feature",
  "properties": {
    "iso:country":"US",
    "sg:address":"5455 Wilshire Blvd",
    "sg:city":"Los Angeles",
    "sg:classifiers":[
        {
            "category":"Health Services",
            "subcategory":"Optometrist",
            "type":"Services"
        }
    ],
    "sg:phone":"+1 323 937 2269",
    "sg:postcode":"90036",
    "sg:province":"CA",
    "sg:tags":[
        "ophthalmologist"
    ],
    "sg:website":"www.kaganinstitute.com",
    "wof:name":"Kagan Arkady MD",
    "wof:placetype":"venue"
},
  "geometry": {"coordinates":[-118.347576,34.06267],"type":"Point"}
}