{
  "type": "Feature",
  "properties": {
    "addr:full":"1771 W 36th Street Los Angeles CA 90018",
    "addr:housenumber":"1771",
    "addr:postcode":"90018",
    "addr:street":"W 36Th Street",
    "iso:country":"US",
    "sg:address":"1771 W 36th Street",
    "sg:city":"Los Angeles",
    "sg:classifiers":[
        {
            "category":"Education",
            "subcategory":"School",
            "type":"Public Place"
        }
    ],
    "sg:phone":"+1 323 733 1178",
    "sg:postcode":"90018",
    "sg:province":"CA",
    "sg:tags":[
        "high",
        "middle",
        "elementary"
    ],
    "sg:website":"www.lausd.k12.ca.us",
    "wof:name":"Bright Elementary School",
    "wof:placetype":"venue"
},
  "geometry": {"coordinates":[-118.311156,34.022711],"type":"Point"}
}