{
  "type": "Feature",
  "properties": {
    "addr:full":"1111 Melrose Way Vista CA 92081",
    "addr:housenumber":"1111",
    "addr:postcode":"92081",
    "addr:street":"Melrose Way",
    "iso:country":"US",
    "sg:address":"1111 Melrose Way",
    "sg:city":"Vista",
    "sg:classifiers":[
        {
            "category":"Education",
            "subcategory":"School",
            "type":"Public Place"
        }
    ],
    "sg:phone":"+1 760 945 2373",
    "sg:postcode":"92081",
    "sg:province":"CA",
    "sg:tags":[
        "high",
        "middle",
        "elementary"
    ],
    "wof:name":"Breeze Hill Elementary School",
    "wof:placetype":"venue"
},
  "geometry": {"coordinates":[-117.25599699999999,33.184399],"type":"Point"}
}