{
  "type": "Feature",
  "properties": {
    "iso:country":"US",
    "sg:address":"1518 Eaton Ave",
    "sg:city":"San Carlos",
    "sg:classifiers":[
        {
            "category":"Building & Trades",
            "subcategory":"Construction",
            "type":"Services"
        }
    ],
    "sg:phone":"+1 650 593 3099",
    "sg:postcode":"94070",
    "sg:province":"CA",
    "sg:tags":[
        "painter"
    ],
    "wof:name":"Global Painting",
    "wof:placetype":"venue"
},
  "geometry": {"coordinates":[-122.248193,37.490992],"type":"Point"}
}