{
  "type": "Feature",
  "properties": {
    "addr:full":"3250 Pine Valley Rd San Ramon CA 94583",
    "addr:housenumber":"3250",
    "addr:postcode":"ca 94583",
    "addr:street":"Pine Valley Rd",
    "iso:country":"US",
    "sg:address":"3250 Pine Valley Rd",
    "sg:city":"San Ramon",
    "sg:classifiers":[
        {
            "category":"Social Services",
            "subcategory":"Child Care",
            "type":"Services"
        }
    ],
    "sg:phone":"+1 925 829 5221",
    "sg:postcode":"94583",
    "sg:province":"CA",
    "wof:name":"Kid's Country Child Care",
    "wof:placetype":"venue"
},
  "geometry": {"coordinates":[-121.93342199999999,37.742468],"type":"Point"}
}