{
  "type": "Feature",
  "properties": {
    "iso:country":"US",
    "sg:address":"800 School St",
    "sg:city":"Napa",
    "sg:classifiers":[
        {
            "category":"Building & Trades",
            "subcategory":"Construction",
            "type":"Services"
        }
    ],
    "sg:phone":"+1 707 255 5501",
    "sg:postcode":"94559",
    "sg:province":"CA",
    "sg:tags":[
        "woodworker"
    ],
    "wof:name":"Hebbbuilt",
    "wof:placetype":"venue"
},
  "geometry": {"coordinates":[-122.28881199999999,38.29651],"type":"Point"}
}