{
  "type": "Feature",
  "properties": {
    "iso:country":"US",
    "sg:address":"621 N Palm Canyon",
    "sg:city":"Palm Springs",
    "sg:classifiers":[
        {
            "category":"Restaurant",
            "type":"Food & Drink"
        }
    ],
    "sg:phone":"+1 760 327 9555",
    "sg:postcode":"92262",
    "sg:province":"CA",
    "sg:tags":[
        "new",
        "american"
    ],
    "sg:website":"www.copleyspalmsprings.com",
    "wof:name":"Copley's",
    "wof:placetype":"venue"
},
  "geometry": {"coordinates":[-116.546808,33.832179],"type":"Point"}
}