{
  "type": "Feature",
  "properties": {
    "addr:full":"2621 Prescott Rd Modesto CA 95350",
    "addr:housenumber":"2621",
    "addr:postcode":"ca 95350",
    "addr:street":"Prescott Rd",
    "iso:country":"US",
    "sg:address":"2621 Prescott Rd",
    "sg:city":"Modesto",
    "sg:classifiers":[
        {
            "category":"Government",
            "subcategory":"Office",
            "type":"Public Place"
        }
    ],
    "sg:phone":"+1 209 524 3030",
    "sg:postcode":"95350",
    "sg:province":"CA",
    "sg:tags":[
        "township",
        "government-city",
        "village"
    ],
    "wof:name":"Friendly Vlg Aptarment Medesto",
    "wof:placetype":"venue"
},
  "geometry": {"coordinates":[-121.031403,37.679642],"type":"Point"}
}