{
  "type": "Feature",
  "properties": {
    "addr:full":"4772 Whittier Blvd Los Angeles CA 90022",
    "addr:housenumber":"4772",
    "addr:postcode":"90022",
    "addr:street":"Whittier Blvd",
    "iso:country":"US",
    "sg:address":"4772 Whittier Blvd",
    "sg:city":"Los Angeles",
    "sg:classifiers":[
        {
            "category":"Shopping",
            "subcategory":"Shoes",
            "type":"Retail Goods"
        }
    ],
    "sg:phone":"+1 323 261 2320",
    "sg:postcode":"90022",
    "sg:province":"CA",
    "wof:name":"Pj's Shoes W608",
    "wof:placetype":"venue"
},
  "geometry": {"coordinates":[-118.165015,34.021966],"type":"Point"}
}