{
  "type": "Feature",
  "properties": {
    "addr:full":"131 Metropole Ave Avalon CA 90704",
    "addr:housenumber":"131",
    "addr:postcode":"90704",
    "addr:street":"Metropole Ave",
    "iso:country":"US",
    "sg:address":"131 Metropole Ave",
    "sg:city":"Avalon",
    "sg:classifiers":[
        {
            "category":"Travel",
            "subcategory":"Hotels & Motels",
            "type":"Entertainment"
        }
    ],
    "sg:phone":"+1 310 510 1010",
    "sg:postcode":"90704",
    "sg:province":"CA",
    "wof:name":"Hermosa Hotel",
    "wof:placetype":"venue"
},
  "geometry": {"coordinates":[-118.326499,33.343972],"type":"Point"}
}