{
  "type": "Feature",
  "properties": {
    "addr:full":"3801 22nd Ave Sacramento CA 95820",
    "addr:housenumber":"3801",
    "addr:postcode":"95820",
    "addr:street":"22Nd Ave",
    "iso:country":"US",
    "sg:address":"3801 22nd Ave",
    "sg:city":"Sacramento",
    "sg:classifiers":[
        {
            "category":"Building & Trades",
            "subcategory":"Landscaping Services",
            "type":"Services"
        }
    ],
    "sg:phone":"+1 916 452 2419",
    "sg:postcode":"95820",
    "sg:province":"CA",
    "sg:tags":[
        "gardener"
    ],
    "wof:name":"Vasquez Gardening Svcs",
    "wof:placetype":"venue"
},
  "geometry": {"coordinates":[-121.465851,38.532711],"type":"Point"}
}