{
  "type": "Feature",
  "properties": {
    "addr:full":"1650 Oregon St Redding CA 96001",
    "addr:housenumber":"1650",
    "addr:postcode":"96001",
    "addr:street":"Oregon St",
    "iso:country":"US",
    "sg:address":"1650 Oregon St",
    "sg:city":"Redding",
    "sg:classifiers":[
        {
            "category":"Professional",
            "subcategory":"Business Services",
            "type":"Services"
        }
    ],
    "sg:phone":"+1 530 242 8720",
    "sg:postcode":"96001",
    "sg:province":"CA",
    "sg:tags":[
        "notary"
    ],
    "wof:name":"Quality Document Preparation",
    "wof:placetype":"venue"
},
  "geometry": {"coordinates":[-122.393823,40.581952],"type":"Point"}
}