{
  "type": "Feature",
  "properties": {
    "addr:full":"1215 Truxtun Ave Bakersfield CA 93301",
    "addr:housenumber":"1215",
    "addr:postcode":"93301",
    "addr:street":"Truxtun Ave",
    "iso:country":"US",
    "sg:address":"1215 Truxtun Ave",
    "sg:city":"Bakersfield",
    "sg:classifiers":[
        {
            "category":"Government",
            "subcategory":"Court House",
            "type":"Public Place"
        }
    ],
    "sg:phone":"+1 661 861 2411",
    "sg:postcode":"93301",
    "sg:province":"CA",
    "sg:tags":[
        "state",
        "system"
    ],
    "wof:name":"Kern Cnty Superior Crt Metor",
    "wof:placetype":"venue"
},
  "geometry": {"coordinates":[-119.01629200000001,35.373252],"type":"Point"}
}