{
  "type": "Feature",
  "properties": {
    "addr:full":"1300 Golden Rule Ln Lake Arrowhead CA 92352",
    "addr:housenumber":"1300",
    "addr:postcode":"92352",
    "addr:street":"Golden Rule Ln",
    "iso:country":"US",
    "sg:address":"1300 Golden Rule Ln",
    "sg:city":"Lake Arrowhead",
    "sg:classifiers":[
        {
            "category":"Education",
            "subcategory":"School",
            "type":"Public Place"
        }
    ],
    "sg:phone":"+1 909 336 0387",
    "sg:postcode":"92352",
    "sg:province":"CA",
    "sg:website":"www.rimsd.k12.ca.us",
    "wof:name":"Lake Arrowhead Elem School",
    "wof:placetype":"venue"
},
  "geometry": {"coordinates":[-117.178372,34.273261],"type":"Point"}
}