{
  "type": "Feature",
  "properties": {
    "iso:country":"US",
    "sg:address":"26926 Cherry Hills Blvd",
    "sg:city":"Sun City",
    "sg:classifiers":[
        {
            "category":"Health Services",
            "subcategory":"Doctor",
            "type":"Services"
        }
    ],
    "sg:phone":"+1 951 301 9188",
    "sg:postcode":"92586",
    "sg:province":"CA",
    "sg:tags":[
        "physician",
        "surgeon"
    ],
    "wof:name":"Menifee Valley Medical Assoc",
    "wof:placetype":"venue"
},
  "geometry": {"coordinates":[-117.191696,33.71032],"type":"Point"}
}