{
  "type": "Feature",
  "properties": {
    "addr:full":"2913 University Ave San Diego CA 92104",
    "addr:housenumber":"2913",
    "addr:postcode":"92104",
    "addr:street":"University Ave",
    "iso:country":"US",
    "sg:address":"2913 University Ave",
    "sg:city":"San Diego",
    "sg:classifiers":[
        {
            "category":"Personal",
            "subcategory":"Tattoo Parlor",
            "type":"Services"
        },
        {
            "category":"Personal",
            "subcategory":"Piercing",
            "type":"Services"
        }
    ],
    "sg:phone":"+1 619 299 4868",
    "sg:postcode":"92104",
    "sg:province":"CA",
    "sg:website":"www.tat2inc.com",
    "wof:name":"Big City Tattoo Incorporated",
    "wof:placetype":"venue"
},
  "geometry": {"coordinates":[-117.130933,32.748452],"type":"Point"}
}