{
  "type": "Feature",
  "properties": {
    "iso:country":"US",
    "sg:address":"550 Mill St",
    "sg:city":"Grass Valley",
    "sg:classifiers":[
        {
            "category":"Restaurant",
            "type":"Food & Drink"
        }
    ],
    "sg:phone":"+1 530 477 0609",
    "sg:postcode":"95945",
    "sg:province":"CA",
    "wof:name":"Paco's Tacos",
    "wof:placetype":"venue"
},
  "geometry": {"coordinates":[-121.069183,39.210672],"type":"Point"}
}