{
  "type": "Feature",
  "properties": {
    "addr:full":"83655 Date Ave Indio CA 92201",
    "addr:housenumber":"83655",
    "addr:postcode":"92201",
    "addr:street":"Date Ave",
    "iso:country":"US",
    "sg:address":"83655 Date Ave",
    "sg:city":"Indio",
    "sg:classifiers":[
        {
            "category":"Freight",
            "type":"Transportation"
        }
    ],
    "sg:phone":"+1 760 863 0999",
    "sg:postcode":"92201",
    "sg:province":"CA",
    "sg:tags":[
        "general"
    ],
    "sg:website":"www.adobemissionstorage.com",
    "wof:name":"Adobe Mission Self Storage",
    "wof:placetype":"venue"
},
  "geometry": {"coordinates":[-116.20529000000001,33.711282],"type":"Point"}
}