{
  "type": "Feature",
  "properties": {
    "addr:full":"10225 Glenoaks Blvd Pacoima CA 91331",
    "addr:housenumber":"10225",
    "addr:postcode":"91331",
    "addr:street":"Glenoaks Blvd",
    "iso:country":"US",
    "sg:address":"10225 Glenoaks Blvd",
    "sg:city":"Pacoima",
    "sg:classifiers":[
        {
            "category":"Manufacturing",
            "subcategory":"Metals",
            "type":"Manufacturing & Wholesale Goods"
        }
    ],
    "sg:phone":"+1 818 896 2465",
    "sg:postcode":"91331",
    "sg:province":"CA",
    "sg:tags":[
        "machine",
        "screw",
        "product"
    ],
    "sg:website":"www.anwright.com",
    "wof:name":"An Wright Corp",
    "wof:placetype":"venue"
},
  "geometry": {"coordinates":[-118.39590800000001,34.258249],"type":"Point"}
}