{
  "type": "Feature",
  "properties": {
    "addr:full":"9519 Harvey Rd Galt CA 95632",
    "addr:housenumber":"9519",
    "addr:postcode":"95632",
    "addr:street":"Harvey Rd",
    "iso:country":"US",
    "sg:address":"9519 Harvey Rd",
    "sg:city":"Galt",
    "sg:classifiers":[
        {
            "category":"Professional",
            "type":"Services"
        }
    ],
    "sg:phone":"+1 209 745 2281",
    "sg:postcode":"95632",
    "sg:province":"CA",
    "wof:name":"Timtam Dairy Goats",
    "wof:placetype":"venue"
},
  "geometry": {"coordinates":[-121.34569399999999,38.254601],"type":"Point"}
}