{
  "type": "Feature",
  "properties": {
    "iso:country":"US",
    "sg:address":"1905 E 17th St",
    "sg:city":"Santa Ana",
    "sg:classifiers":[
        {
            "category":"Local Transit",
            "type":"Transportation"
        }
    ],
    "sg:phone":"+1 714 338 2423",
    "sg:postcode":"92705",
    "sg:province":"CA",
    "sg:tags":[
        "public"
    ],
    "wof:name":"Diversified Monotoring Systems",
    "wof:placetype":"venue"
},
  "geometry": {"coordinates":[-117.83942500000001,33.760088],"type":"Point"}
}