{
  "type": "Feature",
  "properties": {
    "addr:full":"5360 Jackson Dr La Mesa CA 91942",
    "addr:housenumber":"5360",
    "addr:postcode":"91942",
    "addr:street":"Jackson Dr",
    "iso:country":"US",
    "sg:address":"5360 Jackson Dr",
    "sg:city":"La Mesa",
    "sg:classifiers":[
        {
            "category":"Banks & Credit Unions",
            "subcategory":"Bank",
            "type":"Services"
        }
    ],
    "sg:phone":"+1 619 433 3629",
    "sg:postcode":"91942",
    "sg:province":"CA",
    "sg:tags":[
        "loan",
        "real estate"
    ],
    "wof:name":"Express Funding",
    "wof:placetype":"venue"
},
  "geometry": {"coordinates":[-117.015961,32.776347],"type":"Point"}
}