{
  "type": "Feature",
  "properties": {
    "addr:full":"17885 Railroad Ave Sonoma CA 95476",
    "addr:housenumber":"17885",
    "addr:postcode":"95476",
    "addr:street":"Railroad Ave",
    "iso:country":"US",
    "sg:address":"17885 Railroad Ave",
    "sg:city":"Sonoma",
    "sg:classifiers":[
        {
            "category":"Manufacturing",
            "subcategory":"Metals",
            "type":"Manufacturing & Wholesale Goods"
        }
    ],
    "sg:phone":"+1 707 996 5744",
    "sg:postcode":"95476",
    "sg:province":"CA",
    "sg:tags":[
        "fabrication",
        "structural"
    ],
    "wof:name":"Eyeball Engineering",
    "wof:placetype":"venue"
},
  "geometry": {"coordinates":[-122.494086,38.314696],"type":"Point"}
}