{
  "type": "Feature",
  "properties": {
    "addr:full":"17833 Chatsworth St Granada Hills CA 91344",
    "addr:housenumber":"17833",
    "addr:postcode":"91344",
    "addr:street":"Chatsworth St",
    "iso:country":"US",
    "sg:address":"17833 Chatsworth St",
    "sg:city":"Granada Hills",
    "sg:classifiers":[
        {
            "category":"Home & Garden",
            "subcategory":"Carpets & Floor Coverings",
            "type":"Retail Goods"
        }
    ],
    "sg:phone":"+1 818 363 6665",
    "sg:postcode":"91344",
    "sg:province":"CA",
    "sg:tags":[
        "dealer",
        "rug"
    ],
    "wof:name":"Carpet Show",
    "wof:placetype":"venue"
},
  "geometry": {"coordinates":[-118.522897,34.264976],"type":"Point"}
}