{
  "type": "Feature",
  "properties": {
    "iso:country":"US",
    "sg:address":"1502 W Yale Ave",
    "sg:city":"Orange",
    "sg:classifiers":[
        {
            "category":"Wholesale",
            "subcategory":"Computers",
            "type":"Manufacturing & Wholesale Goods"
        }
    ],
    "sg:phone":"+1 714 674 7920",
    "sg:postcode":"92867",
    "sg:province":"CA",
    "wof:name":"Lafan Corp",
    "wof:placetype":"venue"
},
  "geometry": {"coordinates":[-117.86824900000001,33.813296],"type":"Point"}
}