{
  "type": "Feature",
  "properties": {
    "addr:full":"113 W Orangethorpe Ave Fullerton CA 92832",
    "addr:housenumber":"113",
    "addr:postcode":"92832",
    "addr:street":"W Orangethorpe Ave",
    "iso:country":"US",
    "sg:address":"113 W Orangethorpe Ave",
    "sg:city":"Fullerton",
    "sg:classifiers":[
        {
            "category":"Shopping",
            "subcategory":"Mobile Phones",
            "type":"Retail Goods"
        }
    ],
    "sg:phone":"+1 714 446 9901",
    "sg:postcode":"92832",
    "sg:province":"CA",
    "wof:name":"Pcszone",
    "wof:placetype":"venue"
},
  "geometry": {"coordinates":[-117.924622,33.859605],"type":"Point"}
}