{
  "type": "Feature",
  "properties": {
    "iso:country":"US",
    "sg:address":"575 Birch Ct Ste G",
    "sg:city":"Colton",
    "sg:classifiers":[
        {
            "category":"Autos & Motor Vehicles",
            "subcategory":"Automobile Sales",
            "type":"Retail Goods"
        }
    ],
    "sg:phone":"+1 909 824 2687",
    "sg:postcode":"92324",
    "sg:province":"CA",
    "sg:tags":[
        "used",
        "car",
        "broker",
        "dealers-used",
        "truck",
        "new",
        "cars-wholesale"
    ],
    "sg:website":"http://walkerwholesale1.com",
    "wof:name":"Walker Wholesale",
    "wof:placetype":"venue"
},
  "geometry": {"coordinates":[-117.333344,34.06023],"type":"Point"}
}