{
  "type": "Feature",
  "properties": {
    "iso:country":"US",
    "sg:address":"7400 E Slauson Ave",
    "sg:city":"Commerce",
    "sg:classifiers":[
        {
            "category":"Home & Garden",
            "subcategory":"Furniture",
            "type":"Retail Goods"
        }
    ],
    "sg:phone":"+1 323 727 9088",
    "sg:postcode":"90040",
    "sg:province":"CA",
    "sg:tags":[
        "store"
    ],
    "wof:name":"S Fiscal Furniture",
    "wof:placetype":"venue"
},
  "geometry": {"coordinates":[-118.132007,33.977953],"type":"Point"}
}