{
  "type": "Feature",
  "properties": {
    "addr:full":"12804 Loma Rica Dr Grass Valley CA 95945",
    "addr:housenumber":"12804",
    "addr:postcode":"95945",
    "addr:street":"Loma Rica Dr",
    "iso:country":"US",
    "sg:address":"12804 Loma Rica Dr",
    "sg:city":"Grass Valley",
    "sg:classifiers":[
        {
            "category":"Manufacturing",
            "subcategory":"Metals",
            "type":"Manufacturing & Wholesale Goods"
        }
    ],
    "sg:phone":"+1 530 477 0140",
    "sg:postcode":"95945",
    "sg:province":"CA",
    "sg:tags":[
        "fabrication",
        "structural"
    ],
    "wof:name":"Four X Four Labs",
    "wof:placetype":"venue"
},
  "geometry": {"coordinates":[-121.00821999999999,39.221444],"type":"Point"}
}