{
  "type": "Feature",
  "properties": {
    "iso:country":"US",
    "sg:address":"3709 Northcrest Ct",
    "sg:city":"Simi Valley",
    "sg:classifiers":[
        {
            "category":"Professional",
            "type":"Services"
        }
    ],
    "sg:phone":"+1 805 527 9249",
    "sg:postcode":"93063",
    "sg:province":"CA",
    "wof:name":"Wirts Hoggenbrau",
    "wof:placetype":"venue"
},
  "geometry": {"coordinates":[-118.72255800000001,34.285208],"type":"Point"}
}