{
  "type": "Feature",
  "properties": {
    "iso:country":"US",
    "sg:address":"9369 Dowdy Dr",
    "sg:city":"San Diego",
    "sg:classifiers":[
        {
            "category":"Home & Garden",
            "subcategory":"Furniture",
            "type":"Retail Goods"
        }
    ],
    "sg:phone":"+1 858 578 1889",
    "sg:postcode":"92126",
    "sg:province":"CA",
    "sg:tags":[
        "top",
        "counter"
    ],
    "wof:name":"Picasso Counter Top & Cabinet",
    "wof:placetype":"venue"
},
  "geometry": {"coordinates":[-117.145482,32.888345],"type":"Point"}
}