{
  "type": "Feature",
  "properties": {
    "addr:full":"1187 Crenshaw Blvd Los Angeles CA 90019",
    "addr:housenumber":"1187",
    "addr:postcode":"90019",
    "addr:street":"Crenshaw Blvd",
    "iso:country":"US",
    "sg:address":"1187 Crenshaw Blvd",
    "sg:city":"Los Angeles",
    "sg:classifiers":[
        {
            "category":"Organizations",
            "subcategory":"Religious Organization",
            "type":"Services"
        }
    ],
    "sg:phone":"+1 323 939 9191",
    "sg:postcode":"90019",
    "sg:province":"CA",
    "wof:name":"Ca Bible Baptist Church",
    "wof:placetype":"venue"
},
  "geometry": {"coordinates":[-118.325249,34.084809],"type":"Point"}
}