{
  "type": "Feature",
  "properties": {
    "addr:full":"11561 Circle Way Dublin CA 94568",
    "addr:housenumber":"11561",
    "addr:postcode":"94568",
    "addr:street":"Circle Way",
    "iso:country":"US",
    "sg:address":"11561 Circle Way",
    "sg:city":"Dublin",
    "sg:classifiers":[
        {
            "category":"Professional",
            "subcategory":"Secretarial Services",
            "type":"Services"
        }
    ],
    "sg:phone":"+1 925 829 8389",
    "sg:postcode":"94568",
    "sg:province":"CA",
    "sg:tags":[
        "reporting",
        "court"
    ],
    "wof:name":"Medi Transportation Svc",
    "wof:placetype":"venue"
},
  "geometry": {"coordinates":[-121.944177,37.701551],"type":"Point"}
}