{
  "type": "Feature",
  "properties": {
    "addr:full":"126 Cherrybrook Ln Irvine CA 92618",
    "addr:housenumber":"126",
    "addr:postcode":"92618",
    "addr:street":"Cherrybrook Ln",
    "iso:country":"US",
    "sg:address":"126 Cherrybrook Ln",
    "sg:city":"Irvine",
    "sg:classifiers":[
        {
            "category":"Professional",
            "subcategory":"Management & Consulting",
            "type":"Services"
        }
    ],
    "sg:phone":"+1 949 726 0986",
    "sg:postcode":"92618",
    "sg:province":"CA",
    "sg:tags":[
        "marketing",
        "advertising"
    ],
    "wof:name":"Owen and Whitehurst Inc",
    "wof:placetype":"venue"
},
  "geometry": {"coordinates":[-117.786449,33.668647],"type":"Point"}
}