{
  "type": "Feature",
  "properties": {
    "addr:full":"164 Leonard Ave Quincy CA 95971",
    "addr:housenumber":"164",
    "addr:postcode":"95971",
    "addr:street":"Leonard Ave",
    "iso:country":"US",
    "sg:address":"164 Leonard Ave",
    "sg:city":"Quincy",
    "sg:classifiers":[
        {
            "category":"Building & Trades",
            "subcategory":"Plumbing",
            "type":"Services"
        }
    ],
    "sg:phone":"+1 530 283 2445",
    "sg:postcode":"95971",
    "sg:province":"CA",
    "sg:tags":[
        "plumbing",
        "contractor"
    ],
    "wof:name":"Mc Lean's Plumbing",
    "wof:placetype":"venue"
},
  "geometry": {"coordinates":[-120.94707200000001,39.93894],"type":"Point"}
}