{
  "type": "Feature",
  "properties": {
    "iso:country":"US",
    "sg:address":"2850 W Pico Blvd",
    "sg:city":"Los Angeles",
    "sg:classifiers":[
        {
            "category":"Retail",
            "subcategory":"Auto Repair",
            "type":"Services"
        }
    ],
    "sg:phone":"+1 323 373 1648",
    "sg:postcode":"90006",
    "sg:province":"CA",
    "sg:tags":[
        "automobile",
        "electric"
    ],
    "wof:name":"Zorros Auto Electric",
    "wof:placetype":"venue"
},
  "geometry": {"coordinates":[-118.301345,34.047148],"type":"Point"}
}