{
  "type": "Feature",
  "properties": {
    "addr:full":"217 S B St San Mateo CA 94401",
    "addr:housenumber":"217",
    "addr:postcode":"94401",
    "addr:street":"S B St",
    "iso:country":"US",
    "sg:address":"217 S B St",
    "sg:city":"San Mateo",
    "sg:classifiers":[
        {
            "category":"Professional",
            "subcategory":"Computer Services",
            "type":"Services"
        }
    ],
    "sg:postcode":"94401",
    "sg:province":"CA",
    "sg:website":"http://uloop.com",
    "wof:name":"Uloop",
    "wof:placetype":"venue"
},
  "geometry": {"coordinates":[-122.322457,37.565682],"type":"Point"}
}