{
  "type": "Feature",
  "properties": {
    "iso:country":"US",
    "sg:address":"4169 Cushing Pkwy",
    "sg:city":"Fremont",
    "sg:classifiers":[
        {
            "category":"Restaurant",
            "type":"Food & Drink"
        }
    ],
    "sg:phone":"+1 510 651 5223",
    "sg:postcode":"94538",
    "sg:province":"CA",
    "wof:name":"Maple Chinese Restaurant",
    "wof:placetype":"venue"
},
  "geometry": {"coordinates":[-121.951808,37.490153],"type":"Point"}
}