{
  "type": "Feature",
  "properties": {
    "iso:country":"US",
    "sg:address":"500 Third St. Suite 455",
    "sg:city":"San Francisco",
    "sg:classifiers":[
        {
            "category":"Professional",
            "subcategory":"Computer Services",
            "type":"Services"
        }
    ],
    "sg:postcode":"94107",
    "sg:province":"CA",
    "sg:tags":[
        "mobile",
        "security",
        "backup"
    ],
    "sg:website":"http://www.mylookout.com",
    "wof:name":"Lookout",
    "wof:placetype":"venue"
},
  "geometry": {"coordinates":[-122.39972400000001,37.76046],"type":"Point"}
}