{
  "type": "Feature",
  "properties": {
    "addr:full":"4150 Power Inn Road Sacramento CA 95826",
    "addr:housenumber":"4150",
    "addr:postcode":"95826",
    "addr:street":"Power Inn Road",
    "iso:country":"US",
    "sg:address":"4150 Power Inn Road",
    "sg:city":"Sacramento",
    "sg:classifiers":[
        {
            "category":"Home & Garden",
            "subcategory":"Hardware",
            "type":"Retail Goods"
        }
    ],
    "sg:phone":"+1 916 452 2222",
    "sg:postcode":"95826",
    "sg:province":"CA",
    "sg:tags":[
        "store"
    ],
    "wof:name":"Warehouse Paint",
    "wof:placetype":"venue"
},
  "geometry": {"coordinates":[-121.368025,38.556695],"type":"Point"}
}