{
  "type": "Feature",
  "properties": {
    "iso:country":"US",
    "sg:address":"1900 Lincoln Ct",
    "sg:city":"Oxnard",
    "sg:classifiers":[
        {
            "category":"Professional",
            "type":"Services"
        }
    ],
    "sg:phone":"+1 805 488 3923",
    "sg:postcode":"93033",
    "sg:province":"CA",
    "sg:tags":[
        "establishment"
    ],
    "wof:name":"C H I S",
    "wof:placetype":"venue"
},
  "geometry": {"coordinates":[-119.15688900000001,34.158456],"type":"Point"}
}