{
  "type": "Feature",
  "properties": {
    "iso:country":"US",
    "sg:address":"4211 Norwood Ave",
    "sg:city":"Sacramento",
    "sg:classifiers":[
        {
            "category":"Retail",
            "subcategory":"Self-service Laundry",
            "type":"Services"
        }
    ],
    "sg:phone":"+1 916 927 7508",
    "sg:postcode":"95838",
    "sg:province":"CA",
    "wof:name":"Norwood Center Launderland",
    "wof:placetype":"venue"
},
  "geometry": {"coordinates":[-121.456973,38.646424],"type":"Point"}
}