{
  "type": "Feature",
  "properties": {
    "addr:full":"700 Frederick St Santa Cruz CA 95062",
    "addr:housenumber":"700",
    "addr:postcode":"95062",
    "addr:street":"Frederick St",
    "iso:country":"US",
    "sg:address":"700 Frederick St",
    "sg:city":"Santa Cruz",
    "sg:classifiers":[
        {
            "category":"Social Services",
            "type":"Services"
        }
    ],
    "sg:phone":"+1 831 425 7067",
    "sg:postcode":"95062",
    "sg:province":"CA",
    "sg:tags":[
        "counselor",
        "marriage",
        "family"
    ],
    "wof:name":"Xander Abrams PHD",
    "wof:placetype":"venue"
},
  "geometry": {"coordinates":[-122.004786,36.981489],"type":"Point"}
}