{
  "type": "Feature",
  "properties": {
    "addr:full":"7351 Heil Ave Huntington Beach CA 92647",
    "addr:housenumber":"7351",
    "addr:postcode":"92647",
    "addr:street":"Heil Ave",
    "iso:country":"US",
    "sg:address":"7351 Heil Ave",
    "sg:city":"Huntington Beach",
    "sg:classifiers":[
        {
            "category":"Manufacturing",
            "subcategory":"Printing",
            "type":"Manufacturing & Wholesale Goods"
        }
    ],
    "sg:phone":"+1 562 424 7294",
    "sg:postcode":"92647",
    "sg:province":"CA",
    "sg:tags":[
        "publishing"
    ],
    "wof:name":"Monterey Publications Enterpri",
    "wof:placetype":"venue"
},
  "geometry": {"coordinates":[-118.001149,33.722952],"type":"Point"}
}