{
  "type": "Feature",
  "properties": {
    "addr:full":"1400 Main St Ste C Ferndale CA 95536",
    "addr:housenumber":"1400",
    "addr:postcode":"95536",
    "addr:street":"Main St Ste C",
    "iso:country":"US",
    "sg:address":"1400 Main St Ste C",
    "sg:city":"Ferndale",
    "sg:classifiers":[
        {
            "category":"Fast Food",
            "type":"Food & Drink"
        },
        {
            "category":"Restaurant",
            "type":"Food & Drink"
        }
    ],
    "sg:phone":"+1 707 786 9474",
    "sg:postcode":"95536",
    "sg:province":"CA",
    "sg:tags":[
        "hot",
        "hamburger",
        "dog"
    ],
    "wof:name":"No Brand Burger Stand",
    "wof:placetype":"venue"
},
  "geometry": {"coordinates":[-124.258156,40.58662],"type":"Point"}
}