{
  "type": "Feature",
  "properties": {
    "addr:full":"10990 California Ave Lynwood CA 90262",
    "addr:housenumber":"10990",
    "addr:postcode":"90262",
    "addr:street":"California Ave",
    "iso:country":"US",
    "sg:address":"10990 California Ave",
    "sg:city":"Lynwood",
    "sg:classifiers":[
        {
            "category":"Education",
            "subcategory":"School",
            "type":"Public Place"
        }
    ],
    "sg:phone":"+1 310 537 2709",
    "sg:postcode":"90262",
    "sg:province":"CA",
    "wof:name":"Reads Learning Ctr",
    "wof:placetype":"venue"
},
  "geometry": {"coordinates":[-118.208366,33.933576],"type":"Point"}
}