{
  "type": "Feature",
  "properties": {
    "iso:country":"US",
    "sg:address":"431 W California St",
    "sg:city":"Ontario",
    "sg:classifiers":[
        {
            "category":"Food & Beverages",
            "subcategory":"Groceries & Convenience Stores",
            "type":"Retail Goods"
        }
    ],
    "sg:phone":"+1 909 984 5812",
    "sg:postcode":"91762",
    "sg:province":"CA",
    "sg:tags":[
        "market"
    ],
    "wof:name":"Cal-Vine Market",
    "wof:placetype":"venue"
},
  "geometry": {"coordinates":[-117.655555,34.055666],"type":"Point"}
}