{
  "type": "Feature",
  "properties": {
    "addr:full":"1100 Yosemite Blvd Modesto CA 95354",
    "addr:housenumber":"1100",
    "addr:postcode":"ca 95354",
    "addr:street":"Yosemite Blvd",
    "iso:country":"US",
    "sg:address":"1100 Yosemite Blvd",
    "sg:city":"Modesto",
    "sg:classifiers":[
        {
            "category":"Autos & Motor Vehicles",
            "subcategory":"Automobile Sales",
            "type":"Retail Goods"
        }
    ],
    "sg:phone":"+1 209 527 8488",
    "sg:postcode":"95354",
    "sg:province":"CA",
    "sg:tags":[
        "car",
        "dealer"
    ],
    "wof:name":"Thompson's Auto Sales",
    "wof:placetype":"venue"
},
  "geometry": {"coordinates":[-120.975393,37.638208],"type":"Point"}
}