{
  "type": "Feature",
  "properties": {
    "iso:country":"US",
    "sg:address":"847 Acacia Dr",
    "sg:city":"Burlingame",
    "sg:classifiers":[
        {
            "category":"Wholesale",
            "subcategory":"Stationery",
            "type":"Manufacturing & Wholesale Goods"
        }
    ],
    "sg:phone":"+1 650 558 8020",
    "sg:postcode":"94010",
    "sg:province":"CA",
    "sg:tags":[
        "business",
        "form",
        "system"
    ],
    "wof:name":"Safeguard Business Systems",
    "wof:placetype":"venue"
},
  "geometry": {"coordinates":[-122.357439,37.582217],"type":"Point"}
}