{
  "type": "Feature",
  "properties": {
    "iso:country":"US",
    "sg:address":"371 W 14th St",
    "sg:city":"San Bernardino",
    "sg:classifiers":[
        {
            "category":"Organizations",
            "subcategory":"Labor Organization",
            "type":"Services"
        }
    ],
    "sg:phone":"+1 909 888 3511",
    "sg:postcode":"92405",
    "sg:province":"CA",
    "wof:name":"San Bernardino Fire Fighters",
    "wof:placetype":"venue"
},
  "geometry": {"coordinates":[-117.29053,34.125722],"type":"Point"}
}