{
  "type": "Feature",
  "properties": {
    "iso:country":"US",
    "sg:address":"18737 Alfred Ave",
    "sg:city":"Cerritos",
    "sg:classifiers":[
        {
            "category":"Professional",
            "subcategory":"Computer Services",
            "type":"Services"
        }
    ],
    "sg:phone":"+1 562 402 9658",
    "sg:postcode":"90703",
    "sg:province":"CA",
    "sg:tags":[
        "website",
        "design"
    ],
    "sg:website":"www.jcncom.net",
    "wof:name":"Jcn Communications Inc",
    "wof:placetype":"venue"
},
  "geometry": {"coordinates":[-118.058936,33.859521],"type":"Point"}
}