{
  "type": "Feature",
  "properties": {
    "addr:full":"6523 Comanche Ave Winnetka CA 91306",
    "addr:housenumber":"6523",
    "addr:postcode":"91306",
    "addr:street":"Comanche Ave",
    "iso:country":"US",
    "sg:address":"6523 Comanche Ave",
    "sg:city":"Winnetka",
    "sg:classifiers":[
        {
            "category":"Building & Trades",
            "subcategory":"Landscaping Services",
            "type":"Services"
        }
    ],
    "sg:phone":"+1 818 887 2594",
    "sg:postcode":"91306",
    "sg:province":"CA",
    "sg:tags":[
        "gardener"
    ],
    "wof:name":"AA Ruiz Garden Services",
    "wof:placetype":"venue"
},
  "geometry": {"coordinates":[-118.57199900000001,34.188301],"type":"Point"}
}