{
  "type": "Feature",
  "properties": {
    "addr:full":"457 Cabrillo Ave Salinas CA 93906",
    "addr:housenumber":"457",
    "addr:postcode":"93906",
    "addr:street":"Cabrillo Ave",
    "iso:country":"US",
    "sg:address":"457 Cabrillo Ave",
    "sg:city":"Salinas",
    "sg:classifiers":[
        {
            "category":"Building & Trades",
            "subcategory":"Construction",
            "type":"Services"
        }
    ],
    "sg:phone":"+1 831 449 2503",
    "sg:postcode":"93906",
    "sg:province":"CA",
    "sg:tags":[
        "wallcoverings-installation",
        "wallpaper",
        "painting",
        "contractor"
    ],
    "wof:name":"Mcgarry Painting",
    "wof:placetype":"venue"
},
  "geometry": {"coordinates":[-121.64101700000001,36.698375],"type":"Point"}
}