{
  "type": "Feature",
  "properties": {
    "iso:country":"US",
    "sg:address":"8314 2nd St",
    "sg:city":"Downey",
    "sg:classifiers":[
        {
            "category":"Health Services",
            "subcategory":"Doctor",
            "type":"Services"
        }
    ],
    "sg:phone":"+1 562 862 1092",
    "sg:postcode":"90241",
    "sg:province":"CA",
    "wof:name":"Aesthetically You Plastic Surgery Center",
    "wof:placetype":"venue"
},
  "geometry": {"coordinates":[-118.13200399999999,33.940601],"type":"Point"}
}