{
  "type": "Feature",
  "properties": {
    "addr:full":"800 14th St Modesto CA 95354",
    "addr:housenumber":"800",
    "addr:postcode":"ca 95354",
    "addr:street":"14Th St",
    "iso:country":"US",
    "sg:address":"800 14th St",
    "sg:city":"Modesto",
    "sg:classifiers":[
        {
            "category":"Health Services",
            "subcategory":"Doctor",
            "type":"Services"
        }
    ],
    "sg:phone":"+1 209 521 8490",
    "sg:postcode":"95354",
    "sg:province":"CA",
    "sg:tags":[
        "physician",
        "surgeon"
    ],
    "wof:name":"Thomas Kaschak Records Ins",
    "wof:placetype":"venue"
},
  "geometry": {"coordinates":[-120.99531899999999,37.642405],"type":"Point"}
}