{
  "type": "Feature",
  "properties": {
    "addr:full":"243 Acalanes Dr #3 Sunnyvale CA 94086",
    "addr:housenumber":"243",
    "addr:postcode":"94086",
    "addr:street":"Acalanes Dr # 3",
    "iso:country":"US",
    "sg:address":"243 Acalanes Dr #3",
    "sg:city":"Sunnyvale",
    "sg:classifiers":[
        {
            "category":"Professional",
            "subcategory":"Art Services",
            "type":"Services"
        }
    ],
    "sg:postcode":"94086",
    "sg:province":"CA",
    "sg:tags":[
        "photographer"
    ],
    "sg:website":"www.wingedpower.com",
    "wof:name":"Winged Power Photography",
    "wof:placetype":"venue"
},
  "geometry": {"coordinates":[-122.057917,37.380322],"type":"Point"}
}