{
  "type": "Feature",
  "properties": {
    "iso:country":"US",
    "sg:address":"1300 Mason St",
    "sg:city":"San Francisco",
    "sg:classifiers":[
        {
            "category":"Food & Beverages",
            "subcategory":"Bakery",
            "type":"Retail Goods"
        }
    ],
    "sg:phone":"+1 415 433 8881",
    "sg:postcode":"94133",
    "sg:province":"CA",
    "sg:tags":[
        "baker"
    ],
    "wof:name":"Eastern Bakery",
    "wof:placetype":"venue"
},
  "geometry": {"coordinates":[-122.411472,37.795581],"type":"Point"}
}