{
  "type": "Feature",
  "properties": {
    "iso:country":"US",
    "sg:address":"11705 Inglewood Ave",
    "sg:city":"Hawthorne",
    "sg:classifiers":[
        {
            "category":"Shopping",
            "subcategory":"Clothing, Apparel, & Fashions",
            "type":"Retail Goods"
        }
    ],
    "sg:phone":"+1 310 978 3873",
    "sg:postcode":"90250",
    "sg:province":"CA",
    "sg:tags":[
        "item",
        "boutique"
    ],
    "wof:name":"Mathew Hopkins & Co",
    "wof:placetype":"venue"
},
  "geometry": {"coordinates":[-118.361363,33.927342],"type":"Point"}
}