{
  "type": "Feature",
  "properties": {
    "iso:country":"US",
    "sg:address":"33517 Pacific Coast Hwy",
    "sg:city":"Malibu",
    "sg:classifiers":[
        {
            "category":"Wholesale",
            "subcategory":"Jewelry",
            "type":"Manufacturing & Wholesale Goods"
        }
    ],
    "sg:phone":"+1 310 457 1725",
    "sg:postcode":"90265",
    "sg:province":"CA",
    "sg:tags":[
        "textile",
        "import",
        "precious",
        "product",
        "gem"
    ],
    "wof:name":"Strickland Enterprises",
    "wof:placetype":"venue"
},
  "geometry": {"coordinates":[-118.903998,34.042854],"type":"Point"}
}