{
  "type": "Feature",
  "properties": {
    "iso:country":"US",
    "sg:address":"804 E Calle Circulo",
    "sg:city":"Camarillo",
    "sg:classifiers":[
        {
            "category":"Building & Trades",
            "subcategory":"Construction",
            "type":"Services"
        }
    ],
    "sg:phone":"+1 805 987 9186",
    "sg:postcode":"93010",
    "sg:province":"CA",
    "sg:tags":[
        "road",
        "contractor"
    ],
    "wof:name":"Jj Pop Enterprises",
    "wof:placetype":"venue"
},
  "geometry": {"coordinates":[-119.06401,34.224182],"type":"Point"}
}