{
  "type": "Feature",
  "properties": {
    "iso:country":"US",
    "sg:address":"111 Clement Street",
    "sg:city":"San Francisco",
    "sg:classifiers":[
        {
            "category":"Personal",
            "subcategory":"Beauty Salon",
            "type":"Services"
        },
        {
            "category":"Personal",
            "subcategory":"Barber",
            "type":"Services"
        }
    ],
    "sg:phone":"+1 415 876 2838",
    "sg:postcode":"94118",
    "sg:province":"CA",
    "sg:tags":[
        "hair"
    ],
    "wof:name":"New Natural Beauty House",
    "wof:placetype":"venue"
},
  "geometry": {"coordinates":[-122.459999,37.7831],"type":"Point"}
}