{
  "type": "Feature",
  "properties": {
    "iso:country":"US",
    "sg:address":"7000 Soquel Ave",
    "sg:city":"Santa Cruz",
    "sg:classifiers":[
        {
            "category":"Retail",
            "subcategory":"Auto Repair",
            "type":"Services"
        }
    ],
    "sg:phone":"+1 831 476 2477",
    "sg:postcode":"95062",
    "sg:province":"CA",
    "sg:website":"www.pearceeuropean.com",
    "wof:name":"Saab Pearce European & Japanese",
    "wof:placetype":"venue"
},
  "geometry": {"coordinates":[-121.968709,36.982314],"type":"Point"}
}