{
  "type": "Feature",
  "properties": {
    "addr:full":"1611 Douglas Blvd Roseville CA 95661",
    "addr:housenumber":"1611",
    "addr:postcode":"95661",
    "addr:street":"Douglas Blvd",
    "iso:country":"US",
    "sg:address":"1611 Douglas Blvd",
    "sg:city":"Roseville",
    "sg:classifiers":[
        {
            "category":"Shopping",
            "type":"Retail Goods"
        }
    ],
    "sg:phone":"+1 916 789 2095",
    "sg:postcode":"95661",
    "sg:province":"CA",
    "sg:tags":[
        "equipment",
        "pool",
        "swimming"
    ],
    "wof:name":"Leslie's Swimming Pool Supply",
    "wof:placetype":"venue"
},
  "geometry": {"coordinates":[-121.260685,38.744276],"type":"Point"}
}