{
  "type": "Feature",
  "properties": {
    "iso:country":"US",
    "sg:address":"6728 Franklin Blvd",
    "sg:city":"Sacramento",
    "sg:classifiers":[
        {
            "category":"Retail",
            "subcategory":"Auto Repair",
            "type":"Services"
        }
    ],
    "sg:phone":"+1 916 421 9300",
    "sg:postcode":"95823",
    "sg:province":"CA",
    "sg:tags":[
        "repairing",
        "automobile"
    ],
    "wof:name":"Atlas Muffler",
    "wof:placetype":"venue"
},
  "geometry": {"coordinates":[-121.46399700000001,38.505199],"type":"Point"}
}