{
  "type": "Feature",
  "properties": {
    "iso:country":"US",
    "sg:address":"3150 Bear St",
    "sg:city":"Costa Mesa",
    "sg:classifiers":[
        {
            "category":"Organizations",
            "subcategory":"Religious Organization",
            "type":"Services"
        }
    ],
    "sg:phone":"+1 714 708 5404",
    "sg:postcode":"92626",
    "sg:province":"CA",
    "wof:name":"Trinity Christian Center International",
    "wof:placetype":"venue"
},
  "geometry": {"coordinates":[-117.89109999999999,33.686963],"type":"Point"}
}