{
  "type": "Feature",
  "properties": {
    "iso:country":"US",
    "sg:address":"16585 Von Karman Ave",
    "sg:city":"Irvine",
    "sg:classifiers":[
        {
            "category":"Wholesale",
            "subcategory":"Computers",
            "type":"Manufacturing & Wholesale Goods"
        }
    ],
    "sg:phone":"+1 949 760 7075",
    "sg:postcode":"92606",
    "sg:province":"CA",
    "sg:tags":[
        "commercial"
    ],
    "wof:name":"Multigraphics Group",
    "wof:placetype":"venue"
},
  "geometry": {"coordinates":[-117.838003,33.694086],"type":"Point"}
}