{
  "type": "Feature",
  "properties": {
    "addr:full":"2240 S Garey Ave Pomona CA 91766",
    "addr:housenumber":"2240",
    "addr:postcode":"91766",
    "addr:street":"S Garey Ave",
    "iso:country":"US",
    "sg:address":"2240 S Garey Ave",
    "sg:city":"Pomona",
    "sg:classifiers":[
        {
            "category":"Insurance",
            "subcategory":"Insurance Agent",
            "type":"Services"
        },
        {
            "category":"Insurance",
            "subcategory":"Hazard Insurance",
            "type":"Services"
        },
        {
            "category":"Insurance",
            "subcategory":"Title Insurance",
            "type":"Services"
        },
        {
            "category":"Insurance",
            "subcategory":"Life Insurance",
            "type":"Services"
        }
    ],
    "sg:phone":"+1 909 628 1034",
    "sg:postcode":"91766",
    "sg:province":"CA",
    "sg:tags":[
        "business",
        "auto",
        "commercial",
        "homeowner",
        "motorcycle",
        "renter"
    ],
    "wof:name":"Allstate Insurance Company - Jesse Diaz",
    "wof:placetype":"venue"
},
  "geometry": {"coordinates":[-117.749104,34.030603],"type":"Point"}
}