{
  "type": "Feature",
  "properties": {
    "addr:full":"2940 San Jose Ave San Francisco CA 94112",
    "addr:housenumber":"2940",
    "addr:postcode":"94112",
    "addr:street":"San Jose Ave",
    "iso:country":"US",
    "sg:address":"2940 San Jose Ave",
    "sg:city":"San Francisco",
    "sg:classifiers":[
        {
            "category":"Building & Trades",
            "subcategory":"Construction",
            "type":"Services"
        }
    ],
    "sg:phone":"+1 415 584 9575",
    "sg:postcode":"94112",
    "sg:province":"CA",
    "sg:tags":[
        "roofing",
        "contractor"
    ],
    "sg:website":"www.andersonroofingcompany.com",
    "wof:name":"Anderson Roofing & Sheet Metal",
    "wof:placetype":"venue"
},
  "geometry": {"coordinates":[-122.455626,37.71155],"type":"Point"}
}