{
  "type": "Feature",
  "properties": {
    "addr:full":"4339 Fruitland Ave Los Angeles CA 90058",
    "addr:housenumber":"4339",
    "addr:postcode":"90058",
    "addr:street":"Fruitland Ave",
    "iso:country":"US",
    "sg:address":"4339 Fruitland Ave",
    "sg:city":"Los Angeles",
    "sg:classifiers":[
        {
            "category":"Freight",
            "type":"Transportation"
        }
    ],
    "sg:phone":"+1 323 585 5111",
    "sg:postcode":"90058",
    "sg:province":"CA",
    "sg:tags":[
        "arrangement"
    ],
    "wof:name":"Unicold Corporation",
    "wof:placetype":"venue"
},
  "geometry": {"coordinates":[-118.202023,33.996604],"type":"Point"}
}