{
  "type": "Feature",
  "properties": {
    "iso:country":"US",
    "sg:address":"2104 E Main St",
    "sg:city":"Ventura",
    "sg:classifiers":[
        {
            "category":"Manufacturing",
            "subcategory":"Textiles",
            "type":"Manufacturing & Wholesale Goods"
        }
    ],
    "sg:phone":"+1 246 420 9300",
    "sg:postcode":"93001",
    "sg:province":"CA",
    "sg:tags":[
        "mfg",
        "household",
        "retailing",
        "furnishing",
        "primarily",
        "silk"
    ],
    "wof:name":"Ann Gish Inc",
    "wof:placetype":"venue"
},
  "geometry": {"coordinates":[-119.268327,34.277527],"type":"Point"}
}