{
  "type": "Feature",
  "properties": {
    "iso:country":"US",
    "sg:address":"27240 Turnberry Lane Suite 200",
    "sg:city":"Valencia",
    "sg:classifiers":[
        {
            "category":"Professional",
            "subcategory":"Lawyer & Legal Services",
            "type":"Services"
        }
    ],
    "sg:phone":"+1 661 362 0805",
    "sg:postcode":"91355",
    "sg:province":"CA",
    "sg:tags":[
        "personal",
        "injury"
    ],
    "sg:website":"www.scvlawcenter.com",
    "wof:name":"The Mason Law Firm",
    "wof:placetype":"venue"
},
  "geometry": {"coordinates":[-118.579348,34.421398],"type":"Point"}
}