{
  "type": "Feature",
  "properties": {
    "iso:country":"US",
    "sg:address":"40089 Mission Blvd",
    "sg:city":"Fremont",
    "sg:classifiers":[
        {
            "category":"Education",
            "subcategory":"Special Training",
            "type":"Public Place"
        }
    ],
    "sg:phone":"+1 510 252 1601",
    "sg:postcode":"94539",
    "sg:province":"CA",
    "sg:tags":[
        "tutoring"
    ],
    "wof:name":"Tutoring Club",
    "wof:placetype":"venue"
},
  "geometry": {"coordinates":[-121.950597,37.556734],"type":"Point"}
}