{
  "type": "Feature",
  "properties": {
    "addr:full":"7215 Garden Grove Blvd Garden Grove CA 92841",
    "addr:housenumber":"7215",
    "addr:postcode":"92841",
    "addr:street":"Garden Grove Blvd",
    "iso:country":"US",
    "sg:address":"7215 Garden Grove Blvd",
    "sg:city":"Garden Grove",
    "sg:classifiers":[
        {
            "category":"Shopping",
            "subcategory":"Gifts & Souvenirs",
            "type":"Retail Goods"
        }
    ],
    "sg:phone":"+1 714 903 9083",
    "sg:postcode":"92841",
    "sg:province":"CA",
    "sg:tags":[
        "collectible"
    ],
    "wof:name":"Julio's Collectibles",
    "wof:placetype":"venue"
},
  "geometry": {"coordinates":[-118.005168,33.773787],"type":"Point"}
}