{
  "type": "Feature",
  "properties": {
    "addr:full":"2001 Old Tim Bell Rd Waterford CA 95386",
    "addr:housenumber":"2001",
    "addr:postcode":"95386",
    "addr:street":"Old Tim Bell Rd",
    "iso:country":"US",
    "sg:address":"2001 Old Tim Bell Rd",
    "sg:city":"Waterford",
    "sg:phone":"+1 209 874 2447",
    "sg:postcode":"95386",
    "sg:province":"CA",
    "sg:tags":[
        "farm",
        "nut",
        "tree",
        "cash",
        "grove",
        "grain"
    ],
    "wof:name":"L Bar 4 Ranch",
    "wof:placetype":"venue"
},
  "geometry": {"coordinates":[-120.754762,37.669779],"type":"Point"}
}