{
  "type": "Feature",
  "properties": {
    "addr:full":"680 Rio Lindo Ave Chico CA 95926",
    "addr:housenumber":"680",
    "addr:postcode":"95926",
    "addr:street":"Rio Lindo Ave",
    "iso:country":"US",
    "sg:address":"680 Rio Lindo Ave",
    "sg:city":"Chico",
    "sg:classifiers":[
        {
            "category":"Personal",
            "subcategory":"Beauty Salon",
            "type":"Services"
        }
    ],
    "sg:phone":"+1 530 898 1948",
    "sg:postcode":"95926",
    "sg:province":"CA",
    "wof:name":"Wake Up With Make Up Skin",
    "wof:placetype":"venue"
},
  "geometry": {"coordinates":[-121.84922899999999,39.755405],"type":"Point"}
}