{
  "type": "Feature",
  "properties": {
    "addr:full":"1601 Linwood Dr Modesto CA 95350",
    "addr:housenumber":"1601",
    "addr:postcode":"ca 95350",
    "addr:street":"Linwood Dr",
    "iso:country":"US",
    "sg:address":"1601 Linwood Dr",
    "sg:city":"Modesto",
    "sg:classifiers":[
        {
            "category":"Building & Trades",
            "subcategory":"Landscaping Services",
            "type":"Services"
        }
    ],
    "sg:phone":"+1 209 527 7417",
    "sg:postcode":"95350",
    "sg:province":"CA",
    "wof:name":"Louis Landscape Maintenance",
    "wof:placetype":"venue"
},
  "geometry": {"coordinates":[-121.016283,37.668416],"type":"Point"}
}