{
  "type": "Feature",
  "properties": {
    "addr:full":"172 Starlite St South San Francisco CA 94080",
    "addr:housenumber":"172",
    "addr:postcode":"94080",
    "addr:street":"Starlite St",
    "iso:country":"US",
    "sg:address":"172 Starlite St",
    "sg:city":"South San Francisco",
    "sg:classifiers":[
        {
            "category":"Bakery",
            "type":"Food & Drink"
        }
    ],
    "sg:phone":"+1 650 588 5868",
    "sg:postcode":"94080",
    "sg:province":"CA",
    "sg:website":"www.raymondsbread.com/",
    "wof:name":"Raymond's Sourdough Bread",
    "wof:placetype":"venue"
},
  "geometry": {"coordinates":[-122.418176,37.649641],"type":"Point"}
}