{
  "type": "Feature",
  "properties": {
    "addr:full":"410 E Yosemite Ave Madera CA 93638",
    "addr:housenumber":"410",
    "addr:postcode":"93638",
    "addr:street":"E Yosemite Ave",
    "iso:country":"US",
    "sg:address":"410 E Yosemite Ave",
    "sg:city":"Madera",
    "sg:classifiers":[
        {
            "category":"Health Services",
            "subcategory":"Medical Lab",
            "type":"Services"
        }
    ],
    "sg:phone":"+1 559 675 7071",
    "sg:postcode":"93638",
    "sg:province":"CA",
    "sg:tags":[
        "laboratory"
    ],
    "wof:name":"Lab Man Dental Lab",
    "wof:placetype":"venue"
},
  "geometry": {"coordinates":[-120.05536600000001,36.964592],"type":"Point"}
}