{
  "type": "Feature",
  "properties": {
    "iso:country":"US",
    "sg:address":"San Francisco International Airport Gates 26-31 100 Upper International Loop",
    "sg:city":"San Francisco",
    "sg:classifiers":[
        {
            "category":"Coffee & Tea",
            "type":"Food & Drink"
        },
        {
            "category":"Restaurant",
            "type":"Food & Drink"
        }
    ],
    "sg:phone":"+1 650 821 0608",
    "sg:postcode":"94128",
    "sg:province":"CA",
    "wof:name":"Peet's Coffee & Tea",
    "wof:placetype":"venue"
},
  "geometry": {"coordinates":[-122.257082,37.798651],"type":"Point"}
}