{
  "type": "Feature",
  "properties": {
    "addr:full":"1236 W I St Oakdale CA 95361",
    "addr:housenumber":"1236",
    "addr:postcode":"95361",
    "addr:street":"W I St",
    "iso:country":"US",
    "sg:address":"1236 W I St",
    "sg:city":"Oakdale",
    "sg:classifiers":[
        {
            "category":"Personal",
            "subcategory":"Beauty Salon",
            "type":"Services"
        }
    ],
    "sg:phone":"+1 209 847 0466",
    "sg:postcode":"95361",
    "sg:province":"CA",
    "sg:tags":[
        "manicuring"
    ],
    "wof:name":"Simply Stylish",
    "wof:placetype":"venue"
},
  "geometry": {"coordinates":[-120.859701,37.758245],"type":"Point"}
}