{
  "type": "Feature",
  "properties": {
    "addr:full":"5756 Pacific Ave Stockton CA 95207",
    "addr:housenumber":"5756",
    "addr:postcode":"95207",
    "addr:street":"Pacific Ave",
    "iso:country":"US",
    "sg:address":"5756 Pacific Ave",
    "sg:city":"Stockton",
    "sg:classifiers":[
        {
            "category":"Food & Beverages",
            "subcategory":"Groceries & Convenience Stores",
            "type":"Retail Goods"
        }
    ],
    "sg:phone":"+1 209 473 4335",
    "sg:postcode":"95207",
    "sg:province":"CA",
    "sg:tags":[
        "grocer"
    ],
    "wof:name":"Castus Low Carb Superstores",
    "wof:placetype":"venue"
},
  "geometry": {"coordinates":[-121.316979,38.001983],"type":"Point"}
}