{
  "type": "Feature",
  "properties": {
    "addr:full":"1645 Almaden Rd San Jose CA 95101",
    "addr:housenumber":"1645",
    "addr:postcode":"95101",
    "addr:street":"Almaden Rd",
    "iso:country":"US",
    "sg:address":"1645 Almaden Rd",
    "sg:city":"San Jose",
    "sg:classifiers":[
        {
            "category":"Building & Trades",
            "subcategory":"Plumbing",
            "type":"Services"
        },
        {
            "category":"Building & Trades",
            "subcategory":"Construction",
            "type":"Services"
        },
        {
            "category":"Building & Trades",
            "subcategory":"Electrical",
            "type":"Services"
        }
    ],
    "sg:phone":"+1 408 287 2877",
    "sg:postcode":"95101",
    "sg:province":"CA",
    "sg:tags":[
        "electrician",
        "contractor"
    ],
    "wof:name":"Burr Plumbing, Pumping & Electric",
    "wof:placetype":"venue"
},
  "geometry": {"coordinates":[-121.878809,37.306138],"type":"Point"}
}