{
  "type": "Feature",
  "properties": {
    "iso:country":"US",
    "sg:address":"101 California Ave",
    "sg:city":"Santa Monica",
    "sg:classifiers":[
        {
            "category":"Professional",
            "subcategory":"Management & Consulting",
            "type":"Services"
        }
    ],
    "sg:phone":"+1 310 395 3534",
    "sg:postcode":"90403",
    "sg:province":"CA",
    "wof:name":"Shaktman Associates",
    "wof:placetype":"venue"
},
  "geometry": {"coordinates":[-118.50176500000001,34.01893],"type":"Point"}
}