{
  "type": "Feature",
  "properties": {
    "addr:full":"990 W Fremont Ave Suite A Sunnyvale CA 94087",
    "addr:housenumber":"990",
    "addr:postcode":"94087",
    "addr:street":"W Fremont Ave Suite A",
    "iso:country":"US",
    "sg:address":"990 W Fremont Ave Suite A",
    "sg:city":"Sunnyvale",
    "sg:classifiers":[
        {
            "category":"Health Services",
            "subcategory":"Clinic",
            "type":"Services"
        }
    ],
    "sg:phone":"+1 650 380 5787",
    "sg:postcode":"94087",
    "sg:province":"CA",
    "sg:tags":[
        "medical"
    ],
    "wof:name":"Carol Pacheco, DDS",
    "wof:placetype":"venue"
},
  "geometry": {"coordinates":[-122.054317,37.351074],"type":"Point"}
}