{
  "type": "Feature",
  "properties": {
    "addr:full":"1515 Palisades Drive Pacific Palisades CA 90272",
    "addr:housenumber":"1515",
    "addr:postcode":"90272",
    "addr:street":"Palisades Drive",
    "iso:country":"US",
    "sg:address":"1515 Palisades Drive",
    "sg:city":"Pacific Palisades",
    "sg:classifiers":[
        {
            "category":"Personal",
            "subcategory":"Skin Care",
            "type":"Services"
        }
    ],
    "sg:phone":"+1 310 454 5302",
    "sg:postcode":"90272",
    "sg:province":"CA",
    "sg:website":"www.spadmarie.com",
    "wof:name":"Spa D'marie",
    "wof:placetype":"venue"
},
  "geometry": {"coordinates":[-118.565213,34.075731],"type":"Point"}
}