{
  "type": "Feature",
  "properties": {
    "iso:country":"US",
    "sg:address":"9820 Willow Creek Rd",
    "sg:city":"San Diego",
    "sg:classifiers":[
        {
            "category":"Health Services",
            "subcategory":"Health Practitioner",
            "type":"Services"
        }
    ],
    "sg:phone":"+1 858 689 1335",
    "sg:postcode":"92131",
    "sg:province":"CA",
    "sg:tags":[
        "acupuncture"
    ],
    "wof:name":"Harmony Acupunture & Oriental",
    "wof:placetype":"venue"
},
  "geometry": {"coordinates":[-117.11392499999999,32.901317],"type":"Point"}
}