{
  "type": "Feature",
  "properties": {
    "addr:full":"475 Fawn Dr San Anselmo CA 94960",
    "addr:housenumber":"475",
    "addr:postcode":"94960",
    "addr:street":"Fawn Dr",
    "iso:country":"US",
    "sg:address":"475 Fawn Dr",
    "sg:city":"San Anselmo",
    "sg:classifiers":[
        {
            "category":"Professional",
            "subcategory":"Engineering",
            "type":"Services"
        }
    ],
    "sg:phone":"+1 415 453 6436",
    "sg:postcode":"94960",
    "sg:province":"CA",
    "sg:tags":[
        "engineer"
    ],
    "wof:name":"Robinson Merrit & Robin",
    "wof:placetype":"venue"
},
  "geometry": {"coordinates":[-122.568269,38.002115],"type":"Point"}
}