{
  "type": "Feature",
  "properties": {
    "iso:country":"US",
    "sg:address":"1492 Santa Fe Dr",
    "sg:city":"Tustin",
    "sg:classifiers":[
        {
            "category":"Wholesale",
            "subcategory":"Non-durable Goods",
            "type":"Manufacturing & Wholesale Goods"
        }
    ],
    "sg:phone":"+1 714 259 8068",
    "sg:postcode":"92780",
    "sg:province":"CA",
    "wof:name":"Worldwide Sourcing Inc",
    "wof:placetype":"venue"
},
  "geometry": {"coordinates":[-117.832492,33.720088],"type":"Point"}
}