{
  "type": "Feature",
  "properties": {
    "iso:country":"US",
    "sg:address":"2211 Palm Ave",
    "sg:city":"San Mateo",
    "sg:classifiers":[
        {
            "category":"Health Services",
            "subcategory":"Clinic",
            "type":"Services"
        }
    ],
    "sg:phone":"+1 800 967 7526",
    "sg:postcode":"94401",
    "sg:province":"CA",
    "sg:tags":[
        "counseling",
        "mental"
    ],
    "sg:website":"www.ggch.org",
    "wof:name":"Gollden Gate Community Health",
    "wof:placetype":"venue"
},
  "geometry": {"coordinates":[-122.30610799999999,37.546697],"type":"Point"}
}