{
  "type": "Feature",
  "properties": {
    "iso:country":"US",
    "sg:address":"16547 Boyle Ave",
    "sg:city":"Fontana",
    "sg:classifiers":[
        {
            "category":"Building & Trades",
            "subcategory":"Landscaping Services",
            "type":"Services"
        }
    ],
    "sg:phone":"+1 909 355 3852",
    "sg:postcode":"92337",
    "sg:province":"CA",
    "sg:tags":[
        "landscape"
    ],
    "wof:name":"Farmers Landscaping",
    "wof:placetype":"venue"
},
  "geometry": {"coordinates":[-117.44353599999999,34.064865],"type":"Point"}
}