{
  "type": "Feature",
  "properties": {
    "addr:full":"20700 Spence Rd Salinas CA 93908",
    "addr:housenumber":"20700",
    "addr:postcode":"93908",
    "addr:street":"Spence Rd",
    "iso:country":"US",
    "sg:address":"20700 Spence Rd",
    "sg:city":"Salinas",
    "sg:classifiers":[
        {
            "category":"Wholesale",
            "subcategory":"Fruits & Vegetables",
            "type":"Manufacturing & Wholesale Goods"
        }
    ],
    "sg:phone":"+1 831 757 4171",
    "sg:postcode":"93908",
    "sg:province":"CA",
    "sg:tags":[
        "shipper"
    ],
    "wof:name":"Fanciful Co",
    "wof:placetype":"venue"
},
  "geometry": {"coordinates":[-121.553293,36.62146],"type":"Point"}
}