{
  "type": "Feature",
  "properties": {
    "addr:full":"5131 Tweedy Blvd South Gate CA 90280",
    "addr:housenumber":"5131",
    "addr:postcode":"90280",
    "addr:street":"Tweedy Blvd;Gate",
    "iso:country":"US",
    "sg:address":"5131 Tweedy Blvd",
    "sg:city":"South Gate",
    "sg:classifiers":[
        {
            "category":"Food & Beverages",
            "subcategory":"Groceries & Convenience Stores",
            "type":"Retail Goods"
        }
    ],
    "sg:phone":"+1 323 569 8551",
    "sg:postcode":"90280",
    "sg:province":"CA",
    "wof:name":"Calderon Tire Service",
    "wof:placetype":"venue"
},
  "geometry": {"coordinates":[-118.181,33.941601],"type":"Point"}
}