{
  "type": "Feature",
  "properties": {
    "addr:full":"4035 E Castro Valley Blvd Castro Valley CA 94552",
    "addr:housenumber":"4035",
    "addr:postcode":"94552",
    "addr:street":"E Castro Valley Blvd",
    "iso:country":"US",
    "sg:address":"4035 E Castro Valley Blvd",
    "sg:city":"Castro Valley",
    "sg:classifiers":[
        {
            "category":"Health Services",
            "subcategory":"Chiropractor",
            "type":"Services"
        }
    ],
    "sg:phone":"+1 510 727 0121",
    "sg:postcode":"94552",
    "sg:province":"CA",
    "wof:name":"Katona Chiropractic",
    "wof:placetype":"venue"
},
  "geometry": {"coordinates":[-122.051075,37.695644],"type":"Point"}
}