{
  "type": "Feature",
  "properties": {
    "iso:country":"US",
    "sg:address":"14044 Ventura Blvd",
    "sg:city":"Sherman Oaks",
    "sg:classifiers":[
        {
            "category":"Building & Trades",
            "subcategory":"Construction",
            "type":"Services"
        }
    ],
    "sg:phone":"+1 818 995 6415",
    "sg:postcode":"91423",
    "sg:province":"CA",
    "sg:tags":[
        "contractor"
    ],
    "wof:name":"Prudential Home Remodeling",
    "wof:placetype":"venue"
},
  "geometry": {"coordinates":[-118.43800400000001,34.1492],"type":"Point"}
}