{
  "type": "Feature",
  "properties": {
    "iso:country":"US",
    "sg:address":"727 Sapphire St., #410",
    "sg:city":"San Diego",
    "sg:classifiers":[
        {
            "category":"Professional",
            "type":"Services"
        }
    ],
    "sg:phone":"+1 800 557 9047",
    "sg:postcode":"92109",
    "sg:province":"CA",
    "sg:website":"www.ehospitalitymarketing.com",
    "wof:name":"eHospitalityMarketing",
    "wof:placetype":"venue"
},
  "geometry": {"coordinates":[-117.260137,32.807294],"type":"Point"}
}