{
  "type": "Feature",
  "properties": {
    "iso:country":"US",
    "sg:address":"930 N Van Ness Ave",
    "sg:city":"Fresno",
    "sg:classifiers":[
        {
            "category":"Organizations",
            "subcategory":"Community Association",
            "type":"Services"
        }
    ],
    "sg:phone":"+1 559 486 2216",
    "sg:postcode":"93728",
    "sg:province":"CA",
    "sg:tags":[
        "club"
    ],
    "wof:name":"Central California Pride Network",
    "wof:placetype":"venue"
},
  "geometry": {"coordinates":[-119.79888200000001,36.754505],"type":"Point"}
}