{
  "type": "Feature",
  "properties": {
    "iso:country":"US",
    "sg:address":"8928 Santa Monica Blvd",
    "sg:city":"West Hollywood",
    "sg:classifiers":[
        {
            "category":"Restaurant",
            "type":"Food & Drink"
        }
    ],
    "sg:phone":"+1 310 855 1888",
    "sg:postcode":"90069",
    "sg:province":"CA",
    "sg:tags":[
        "vietnamese"
    ],
    "sg:website":"www.phociti.com",
    "wof:name":"Pho Citi",
    "wof:placetype":"venue"
},
  "geometry": {"coordinates":[-118.384689,34.084042],"type":"Point"}
}