{
  "type": "Feature",
  "properties": {
    "iso:country":"US",
    "sg:address":"24954 Taft St",
    "sg:city":"Los Molinos",
    "sg:classifiers":[
        {
            "category":"Building & Trades",
            "subcategory":"Construction",
            "type":"Services"
        }
    ],
    "sg:phone":"+1 530 384 2624",
    "sg:postcode":"96055",
    "sg:province":"CA",
    "sg:tags":[
        "bulldozing"
    ],
    "wof:name":"Bulldozer Service",
    "wof:placetype":"venue"
},
  "geometry": {"coordinates":[-122.104874,40.047589],"type":"Point"}
}