{
  "type": "Feature",
  "properties": {
    "addr:full":"8687 Melrose Avenue West Hollywood CA 90069",
    "addr:housenumber":"8687",
    "addr:postcode":"90069",
    "addr:street":"Melrose Avenue",
    "iso:country":"US",
    "sg:address":"8687 Melrose Avenue",
    "sg:city":"West Hollywood",
    "sg:classifiers":[
        {
            "category":"Shopping",
            "subcategory":"Stationery & Office Supplies",
            "type":"Retail Goods"
        }
    ],
    "sg:phone":"+1 310 652 4060",
    "sg:postcode":"90069",
    "sg:province":"CA",
    "sg:tags":[
        "equipment"
    ],
    "wof:name":"Paston-Rawleigh-Everett",
    "wof:placetype":"venue"
},
  "geometry": {"coordinates":[-118.382807,34.081528],"type":"Point"}
}