{
  "type": "Feature",
  "properties": {
    "addr:full":"2471 E. Bayshore Rd #525 Palo Alto  CA 94303",
    "addr:housenumber":"2471",
    "addr:postcode":"94303",
    "addr:street":"E. Bayshore Rd # 525",
    "iso:country":"US",
    "sg:address":"2471 E. Bayshore Rd #525",
    "sg:city":"Palo Alto ",
    "sg:classifiers":[
        {
            "category":"Professional",
            "subcategory":"Management & Consulting",
            "type":"Services"
        }
    ],
    "sg:phone":"+1 650 493 0223",
    "sg:postcode":"94303",
    "sg:province":"CA",
    "sg:website":"http://www.wehire.com",
    "wof:name":"Palo Alto Staffing Services",
    "wof:placetype":"venue"
},
  "geometry": {"coordinates":[-122.11841099999999,37.44663],"type":"Point"}
}