{
  "type": "Feature",
  "properties": {
    "iso:country":"US",
    "sg:address":"19815 Hamilton Ave",
    "sg:city":"Torrance",
    "sg:classifiers":[
        {
            "category":"Shopping",
            "subcategory":"Bicycles & Sporting Goods",
            "type":"Retail Goods"
        }
    ],
    "sg:phone":"+1 310 462 9991",
    "sg:postcode":"90502",
    "sg:province":"CA",
    "sg:website":"stokedskateboards.com/",
    "wof:name":"Stoked Skateboards",
    "wof:placetype":"venue"
},
  "geometry": {"coordinates":[-118.286066,33.850878],"type":"Point"}
}