{
  "type": "Feature",
  "properties": {
    "addr:full":"2564 Merrychase Dr Cameron Park CA 95682",
    "addr:housenumber":"2564",
    "addr:postcode":"95682",
    "addr:street":"Merrychase Dr",
    "iso:country":"US",
    "sg:address":"2564 Merrychase Dr",
    "sg:city":"Cameron Park",
    "sg:classifiers":[
        {
            "category":"Retail",
            "subcategory":"Auto Repair",
            "type":"Services"
        }
    ],
    "sg:phone":"+1 530 672 1750",
    "sg:postcode":"95682",
    "sg:province":"CA",
    "sg:tags":[
        "repairing",
        "automobile"
    ],
    "wof:name":"S & D Automotive",
    "wof:placetype":"venue"
},
  "geometry": {"coordinates":[-121.000936,38.657253],"type":"Point"}
}