{
  "type": "Feature",
  "properties": {
    "iso:country":"US",
    "sg:address":"6626 Valley Hi Dr",
    "sg:city":"Sacramento",
    "sg:classifiers":[
        {
            "category":"Banks & Credit Unions",
            "subcategory":"Bank",
            "type":"Services"
        },
        {
            "category":"Shopping",
            "subcategory":"Used Merchandise",
            "type":"Retail Goods"
        }
    ],
    "sg:phone":"+1 916 689 7671",
    "sg:postcode":"95823",
    "sg:province":"CA",
    "sg:tags":[
        "resale",
        "shop",
        "second",
        "hand"
    ],
    "wof:name":"Family Tree Thrift Shoppe",
    "wof:placetype":"venue"
},
  "geometry": {"coordinates":[-121.427145,38.471384],"type":"Point"}
}