{
  "type": "Feature",
  "properties": {
    "addr:full":"105 W F St San Diego CA 92101",
    "addr:housenumber":"105",
    "addr:postcode":"92101",
    "addr:street":"W F St",
    "iso:country":"US",
    "sg:address":"105 W F St",
    "sg:city":"San Diego",
    "sg:classifiers":[
        {
            "category":"Professional",
            "subcategory":"Lawyer & Legal Services",
            "type":"Services"
        }
    ],
    "sg:phone":"+1 619 232 2588",
    "sg:postcode":"92101",
    "sg:province":"CA",
    "sg:tags":[
        "attorney"
    ],
    "wof:name":"Guadalupe Valencia Law Offices of",
    "wof:placetype":"venue"
},
  "geometry": {"coordinates":[-117.164001,32.7136],"type":"Point"}
}