{
  "type": "Feature",
  "properties": {
    "addr:full":"1307 Harrison St Oakland CA 94612",
    "addr:housenumber":"1307",
    "addr:postcode":"94612",
    "addr:street":"Harrison St",
    "iso:country":"US",
    "sg:address":"1307 Harrison St",
    "sg:city":"Oakland",
    "sg:classifiers":[
        {
            "category":"Manufacturing",
            "subcategory":"Apparel",
            "type":"Manufacturing & Wholesale Goods"
        }
    ],
    "sg:phone":"+1 510 834 7493",
    "sg:postcode":"94612",
    "sg:province":"CA",
    "sg:tags":[
        "sewing",
        "contractor"
    ],
    "wof:name":"Hin Fai Sewing Co",
    "wof:placetype":"venue"
},
  "geometry": {"coordinates":[-122.267735,37.80289],"type":"Point"}
}