{
  "type": "Feature",
  "properties": {
    "addr:full":"547 L Street Sacramento CA 95814",
    "addr:housenumber":"547",
    "addr:postcode":"95814",
    "addr:street":"L Street",
    "iso:country":"US",
    "sg:address":"547 L Street",
    "sg:city":"Sacramento",
    "sg:classifiers":[
        {
            "category":"Shopping",
            "subcategory":"Clothing, Apparel, & Fashions",
            "type":"Retail Goods"
        }
    ],
    "sg:phone":"+1 916 498 9830",
    "sg:postcode":"95814",
    "sg:province":"CA",
    "sg:tags":[
        "men's",
        "clothing",
        "women's"
    ],
    "sg:website":"www.ikonboutique.com",
    "wof:name":"Ikon Boutique",
    "wof:placetype":"venue"
},
  "geometry": {"coordinates":[-121.500229,38.5797],"type":"Point"}
}