{
  "type": "Feature",
  "properties": {
    "addr:full":"8701 Beverly Blvd Los Angeles CA 90048",
    "addr:housenumber":"8701",
    "addr:postcode":"90048",
    "addr:street":"Beverly Blvd",
    "iso:country":"US",
    "sg:address":"8701 Beverly Blvd",
    "sg:city":"Los Angeles",
    "sg:classifiers":[
        {
            "category":"Deli",
            "type":"Food & Drink"
        },
        {
            "category":"Restaurant",
            "type":"Food & Drink"
        }
    ],
    "sg:menulink":"http://www.allmenus.com/ca/los-angeles/228666-jerrys-famous-deli/menu/",
    "sg:phone":"+1 310 289 1811",
    "sg:postcode":"90048",
    "sg:province":"CA",
    "sg:tags":[
        "deli",
        "american"
    ],
    "wof:name":"Jerry's Famous Deli",
    "wof:placetype":"venue"
},
  "geometry": {"coordinates":[-118.380655,34.077158],"type":"Point"}
}