{
  "type": "Feature",
  "properties": {
    "addr:full":"1601 Hemlock St Chico CA 95928",
    "addr:housenumber":"1601",
    "addr:postcode":"95928",
    "addr:street":"Hemlock St",
    "iso:country":"US",
    "sg:address":"1601 Hemlock St",
    "sg:city":"Chico",
    "sg:classifiers":[
        {
            "category":"Organizations",
            "subcategory":"Religious Organization",
            "type":"Services"
        }
    ],
    "sg:phone":"+1 530 342 3164",
    "sg:postcode":"95928",
    "sg:province":"CA",
    "wof:name":"Prayer House",
    "wof:placetype":"venue"
},
  "geometry": {"coordinates":[-121.82468,39.722522],"type":"Point"}
}