{
  "type": "Feature",
  "properties": {
    "iso:country":"US",
    "sg:address":"1226 Harter Ave",
    "sg:city":"Woodland",
    "sg:classifiers":[
        {
            "category":"Home & Garden",
            "subcategory":"Household Appliances",
            "type":"Retail Goods"
        }
    ],
    "sg:phone":"+1 530 662 3996",
    "sg:postcode":"95776",
    "sg:province":"CA",
    "wof:name":"A-1 Appliance",
    "wof:placetype":"venue"
},
  "geometry": {"coordinates":[-121.76434399999999,38.693367],"type":"Point"}
}