{
  "type": "Feature",
  "properties": {
    "iso:country":"US",
    "sg:address":"1518 19th St",
    "sg:city":"Bakersfield",
    "sg:classifiers":[
        {
            "category":"Shopping",
            "subcategory":"Music",
            "type":"Retail Goods"
        }
    ],
    "sg:phone":"+1 661 324 5235",
    "sg:postcode":"93301",
    "sg:province":"CA",
    "sg:tags":[
        "compact",
        "record",
        "disc",
        "tape"
    ],
    "wof:name":"Downtown Records",
    "wof:placetype":"venue"
},
  "geometry": {"coordinates":[-119.019837,35.376304],"type":"Point"}
}