{
  "type": "Feature",
  "properties": {
    "iso:country":"US",
    "sg:address":"22526 Dolores St",
    "sg:city":"Carson",
    "sg:classifiers":[
        {
            "category":"Education",
            "subcategory":"School",
            "type":"Public Place"
        }
    ],
    "sg:phone":"+1 310 834 2565",
    "sg:postcode":"90745",
    "sg:province":"CA",
    "sg:tags":[
        "elementary"
    ],
    "sg:website":"www.lausd.k12.ca.us",
    "wof:name":"Dolores Street Elementary School",
    "wof:placetype":"venue"
},
  "geometry": {"coordinates":[-118.272003,33.821701],"type":"Point"}
}