{
  "type": "Feature",
  "properties": {
    "addr:full":"323 W Canal Dr Turlock CA 95380",
    "addr:housenumber":"323",
    "addr:postcode":"95380",
    "addr:street":"W Canal Dr",
    "iso:country":"US",
    "sg:address":"323 W Canal Dr",
    "sg:city":"Turlock",
    "sg:classifiers":[
        {
            "category":"Shopping",
            "type":"Retail Goods"
        }
    ],
    "sg:phone":"+1 209 667 2600",
    "sg:postcode":"95380",
    "sg:province":"CA",
    "sg:tags":[
        "trophy",
        "medal",
        "award"
    ],
    "wof:name":"Forever Impressed",
    "wof:placetype":"venue"
},
  "geometry": {"coordinates":[-120.85257300000001,37.500659],"type":"Point"}
}