{
  "type": "Feature",
  "properties": {
    "addr:full":"768 N Ave 50 Los Angeles CA 90042",
    "addr:housenumber":"768;50",
    "addr:postcode":"90042",
    "addr:street":"N Ave",
    "iso:country":"US",
    "sg:address":"768 N Ave 50",
    "sg:city":"Los Angeles",
    "sg:classifiers":[
        {
            "category":"Building & Trades",
            "subcategory":"Construction",
            "type":"Services"
        }
    ],
    "sg:phone":"+1 323 256 0129",
    "sg:postcode":"90042",
    "sg:province":"CA",
    "sg:tags":[
        "product",
        "asphalt"
    ],
    "wof:name":"Pioneer Paving & Landscaping",
    "wof:placetype":"venue"
},
  "geometry": {"coordinates":[-118.207894,34.112615],"type":"Point"}
}