{
  "type": "Feature",
  "properties": {
    "addr:full":"1346 W Alluvial Ave Fresno CA 93711",
    "addr:housenumber":"1346",
    "addr:postcode":"93711",
    "addr:street":"W Alluvial Ave",
    "iso:country":"US",
    "sg:address":"1346 W Alluvial Ave",
    "sg:city":"Fresno",
    "sg:classifiers":[
        {
            "category":"Wholesale",
            "subcategory":"Hardware",
            "type":"Manufacturing & Wholesale Goods"
        }
    ],
    "sg:phone":"+1 559 432 6043",
    "sg:postcode":"93711",
    "sg:province":"CA",
    "sg:tags":[
        "leak",
        "detecting",
        "instrument"
    ],
    "sg:website":"www.visualcheck.com",
    "wof:name":"Visual Check Intl",
    "wof:placetype":"venue"
},
  "geometry": {"coordinates":[-119.816773,36.846004],"type":"Point"}
}