{
  "type": "Feature",
  "properties": {
    "iso:country":"US",
    "sg:address":"16538 Clear Creek Rd",
    "sg:city":"Redding",
    "sg:classifiers":[
        {
            "category":"Wholesale",
            "subcategory":"Electrical",
            "type":"Manufacturing & Wholesale Goods"
        }
    ],
    "sg:phone":"+1 530 242 6762",
    "sg:postcode":"96001",
    "sg:province":"CA",
    "sg:tags":[
        "insulation",
        "material"
    ],
    "wof:name":"Quality Insulation Fabricator",
    "wof:placetype":"venue"
},
  "geometry": {"coordinates":[-122.450379,40.501575],"type":"Point"}
}