{
  "type": "Feature",
  "properties": {
    "iso:country":"US",
    "sg:address":"5628 Kenneth Ave",
    "sg:city":"Carmichael",
    "sg:classifiers":[
        {
            "category":"Organizations",
            "subcategory":"Religious Organization",
            "type":"Services"
        }
    ],
    "sg:phone":"+1 916 483 3949",
    "sg:postcode":"95608",
    "sg:province":"CA",
    "sg:tags":[
        "church"
    ],
    "wof:name":"Jehovah's Witnesses Hall",
    "wof:placetype":"venue"
},
  "geometry": {"coordinates":[-121.332768,38.613579],"type":"Point"}
}