{
  "type": "Feature",
  "properties": {
    "iso:country":"US",
    "sg:address":"25466 Lane St",
    "sg:city":"Loma Linda",
    "sg:classifiers":[
        {
            "category":"Social Services",
            "subcategory":"Child Care",
            "type":"Services"
        }
    ],
    "sg:phone":"+1 909 799 0543",
    "sg:postcode":"92354",
    "sg:province":"CA",
    "wof:name":"Gadea Family Day Care",
    "wof:placetype":"venue"
},
  "geometry": {"coordinates":[-117.25102800000001,34.05706],"type":"Point"}
}