{
  "type": "Feature",
  "properties": {
    "addr:full":"3151 Airway Ave Costa Mesa CA 92626",
    "addr:housenumber":"3151",
    "addr:postcode":"92626",
    "addr:street":"Airway Ave",
    "iso:country":"US",
    "sg:address":"3151 Airway Ave",
    "sg:city":"Costa Mesa",
    "sg:classifiers":[
        {
            "category":"Travel",
            "subcategory":"Travel Agent",
            "type":"Entertainment"
        }
    ],
    "sg:phone":"+1 714 435 1122",
    "sg:postcode":"92626",
    "sg:province":"CA",
    "sg:tags":[
        "agency"
    ],
    "wof:name":"Uniglobe Way To Go Travel",
    "wof:placetype":"venue"
},
  "geometry": {"coordinates":[-117.8706,33.68015],"type":"Point"}
}