{
  "type": "Feature",
  "properties": {
    "iso:country":"US",
    "sg:address":"23286 Westwood St",
    "sg:city":"Grand Terrace",
    "sg:classifiers":[
        {
            "category":"Professional",
            "subcategory":"Management & Consulting",
            "type":"Services"
        }
    ],
    "sg:phone":"+1 909 824 6696",
    "sg:postcode":"92313",
    "sg:province":"CA",
    "sg:tags":[
        "promotion",
        "sales"
    ],
    "wof:name":"Discount Distributors",
    "wof:placetype":"venue"
},
  "geometry": {"coordinates":[-117.298463,34.037394],"type":"Point"}
}