{
  "type": "Feature",
  "properties": {
    "iso:country":"US",
    "sg:address":"7500 Lake Amador Dr",
    "sg:city":"Ione",
    "sg:classifiers":[
        {
            "category":"Travel",
            "subcategory":"Hotels & Motels",
            "type":"Entertainment"
        }
    ],
    "sg:phone":"+1 209 274 4739",
    "sg:postcode":"95646",
    "sg:province":"CA",
    "sg:tags":[
        "resort"
    ],
    "sg:website":"www.lakeamador.com",
    "wof:name":"Lake Amador Resort",
    "wof:placetype":"venue"
},
  "geometry": {"coordinates":[-120.89251,38.30475],"type":"Point"}
}