{
  "type": "Feature",
  "properties": {
    "addr:full":"4928 Florence Ave Bell CA 90201",
    "addr:housenumber":"4928",
    "addr:postcode":"90201",
    "addr:street":"Florence Ave",
    "iso:country":"US",
    "sg:address":"4928 Florence Ave",
    "sg:city":"Bell",
    "sg:classifiers":[
        {
            "category":"Manufacturing",
            "subcategory":"Retail Goods",
            "type":"Manufacturing & Wholesale Goods"
        }
    ],
    "sg:phone":"+1 323 771 2391",
    "sg:postcode":"90201",
    "sg:province":"CA",
    "sg:tags":[
        "assembly",
        "fabricating"
    ],
    "wof:name":"Sik Fabrications",
    "wof:placetype":"venue"
},
  "geometry": {"coordinates":[-118.17959,33.96937],"type":"Point"}
}