{
  "type": "Feature",
  "properties": {
    "iso:country":"US",
    "sg:address":"1441 Gardena Ave",
    "sg:city":"Glendale",
    "sg:classifiers":[
        {
            "category":"Organizations",
            "subcategory":"Non-profit Organization",
            "type":"Services"
        }
    ],
    "sg:phone":"+1 818 254 0200",
    "sg:postcode":"91204",
    "sg:province":"CA",
    "sg:tags":[
        "social"
    ],
    "wof:name":"Padres Contra El Cancer",
    "wof:placetype":"venue"
},
  "geometry": {"coordinates":[-118.259348,34.126243],"type":"Point"}
}