{
  "type": "Feature",
  "properties": {
    "iso:country":"US",
    "sg:address":"30867 Rd 400",
    "sg:city":"Coarsegold",
    "sg:classifiers":[
        {
            "category":"Freight",
            "type":"Transportation"
        }
    ],
    "sg:phone":"+1 559 658 2777",
    "sg:postcode":"93614",
    "sg:province":"CA",
    "sg:tags":[
        "truck"
    ],
    "wof:name":"Kenli Truck Licensing",
    "wof:placetype":"venue"
},
  "geometry": {"coordinates":[-119.824983,37.18503],"type":"Point"}
}