{
  "type": "Feature",
  "properties": {
    "addr:full":"1832 Tribute Rd. Suite #E Sacramento CA 95815",
    "addr:housenumber":"1832",
    "addr:postcode":"95815",
    "addr:street":"Tribute Rd. Suite # E",
    "iso:country":"US",
    "sg:address":"1832 Tribute Rd. Suite #E",
    "sg:city":"Sacramento",
    "sg:classifiers":[
        {
            "category":"Health Services",
            "subcategory":"Clinic",
            "type":"Services"
        },
        {
            "category":"Shopping",
            "type":"Retail Goods"
        },
        {
            "category":"Community Center",
            "type":"Public Place"
        },
        {
            "category":"Recreation",
            "type":"Entertainment"
        }
    ],
    "sg:phone":"+1 916 564 1824",
    "sg:postcode":"95815",
    "sg:province":"CA",
    "sg:tags":[
        "life",
        "medical",
        "cannabis",
        "active",
        "merchandise"
    ],
    "sg:website":"www.unitynpc.org",
    "wof:name":"Unity Non Profit Collective",
    "wof:placetype":"venue"
},
  "geometry": {"coordinates":[-121.44640699999999,38.598696],"type":"Point"}
}