{
  "type": "Feature",
  "properties": {
    "iso:country":"US",
    "sg:address":"4931 N Montpelier Rd",
    "sg:city":"Denair",
    "sg:classifiers":[
        {
            "category":"Farming",
            "subcategory":"Orchard",
            "type":"Manufacturing & Wholesale Goods"
        }
    ],
    "sg:phone":"+1 209 874 5126",
    "sg:postcode":"95316",
    "sg:province":"CA",
    "sg:tags":[
        "fruit",
        "tree"
    ],
    "wof:name":"Montpelier Nut Co",
    "wof:placetype":"venue"
},
  "geometry": {"coordinates":[-120.69538,37.535575],"type":"Point"}
}