{
  "type": "Feature",
  "properties": {
    "addr:full":"430 3rd St Woodland CA 95695",
    "addr:housenumber":"430",
    "addr:postcode":"95695",
    "addr:street":"3Rd St",
    "iso:country":"US",
    "sg:address":"430 3rd St",
    "sg:city":"Woodland",
    "sg:classifiers":[
        {
            "category":"Professional",
            "subcategory":"Lawyer & Legal Services",
            "type":"Services"
        }
    ],
    "sg:phone":"+1 530 662 9140",
    "sg:postcode":"95695",
    "sg:province":"CA",
    "sg:tags":[
        "attorney"
    ],
    "wof:name":"Thomas A Purtell",
    "wof:placetype":"venue"
},
  "geometry": {"coordinates":[-121.77071100000001,38.676173],"type":"Point"}
}