{
  "type": "Feature",
  "properties": {
    "iso:country":"US",
    "sg:address":"420 N Capitol Ave",
    "sg:city":"San Jose",
    "sg:classifiers":[
        {
            "category":"Shopping",
            "subcategory":"Clothing, Apparel, & Fashions",
            "type":"Retail Goods"
        }
    ],
    "sg:phone":"+1 408 873 8898",
    "sg:postcode":"95133",
    "sg:province":"CA",
    "sg:tags":[
        "shop",
        "bridal"
    ],
    "wof:name":"Susan's Bridals",
    "wof:placetype":"venue"
},
  "geometry": {"coordinates":[-121.844413,37.371494],"type":"Point"}
}