{
  "type": "Feature",
  "properties": {
    "iso:country":"US",
    "sg:address":"460 Tilia Ct",
    "sg:city":"Chula Vista",
    "sg:classifiers":[
        {
            "category":"Home & Garden",
            "subcategory":"Carpets & Floor Coverings",
            "type":"Retail Goods"
        }
    ],
    "sg:phone":"+1 619 421 2726",
    "sg:postcode":"91911",
    "sg:province":"CA",
    "sg:tags":[
        "dealer",
        "rug"
    ],
    "wof:name":"Rick Hamrick's Carpet Cleaning",
    "wof:placetype":"venue"
},
  "geometry": {"coordinates":[-117.03492900000001,32.599642],"type":"Point"}
}