{
  "type": "Feature",
  "properties": {
    "addr:full":"1500 Vine St Los Angeles CA 90028",
    "addr:housenumber":"1500",
    "addr:postcode":"90028",
    "addr:street":"Vine St",
    "iso:country":"US",
    "sg:address":"1500 Vine St",
    "sg:city":"Los Angeles",
    "sg:classifiers":[
        {
            "category":"Organizations",
            "subcategory":"Professional Association",
            "type":"Services"
        }
    ],
    "sg:phone":"+1 323 461 2121",
    "sg:postcode":"90028",
    "sg:province":"CA",
    "wof:name":"Pacific Pioneer Broadcasters",
    "wof:placetype":"venue"
},
  "geometry": {"coordinates":[-118.326668,34.099792],"type":"Point"}
}