{
  "type": "Feature",
  "properties": {
    "iso:country":"US",
    "sg:address":"4350 Gill Village Way",
    "sg:city":"San Diego",
    "sg:classifiers":[
        {
            "category":"Wholesale",
            "subcategory":"Apparel",
            "type":"Manufacturing & Wholesale Goods"
        }
    ],
    "sg:phone":"+1 858 546 4455",
    "sg:postcode":"92108",
    "sg:province":"CA",
    "sg:tags":[
        "piece"
    ],
    "wof:name":"Owens Corning",
    "wof:placetype":"venue"
},
  "geometry": {"coordinates":[-117.14702,32.774975],"type":"Point"}
}