{
  "type": "Feature",
  "properties": {
    "addr:full":"51 Porter Dr Watsonville CA 95076",
    "addr:housenumber":"51",
    "addr:postcode":"95076",
    "addr:street":"Porter Dr",
    "iso:country":"US",
    "sg:address":"51 Porter Dr",
    "sg:city":"Watsonville",
    "sg:classifiers":[
        {
            "category":"Wholesale",
            "subcategory":"Fruits & Vegetables",
            "type":"Manufacturing & Wholesale Goods"
        }
    ],
    "sg:phone":"+1 831 728 2919",
    "sg:postcode":"95076",
    "sg:province":"CA",
    "wof:name":"Leo's Produce & Market",
    "wof:placetype":"venue"
},
  "geometry": {"coordinates":[-121.750534,36.904735],"type":"Point"}
}