{
  "type": "Feature",
  "properties": {
    "iso:country":"US",
    "sg:address":"13117 Hadley St",
    "sg:city":"Whittier",
    "sg:classifiers":[
        {
            "category":"Banks & Credit Unions",
            "subcategory":"Bank",
            "type":"Services"
        }
    ],
    "sg:phone":"+1 562 698 9515",
    "sg:postcode":"90601",
    "sg:province":"CA",
    "sg:tags":[
        "escrow"
    ],
    "wof:name":"Adobe Escrow Corp",
    "wof:placetype":"venue"
},
  "geometry": {"coordinates":[-118.035712,33.982795],"type":"Point"}
}