{
  "type": "Feature",
  "properties": {
    "addr:full":"2741 Plz del Amo Torrance CA 90503",
    "addr:postcode":"2741;90503",
    "addr:street":"Plz Del",
    "iso:country":"US",
    "sg:address":"2741 Plz del Amo",
    "sg:city":"Torrance",
    "sg:classifiers":[
        {
            "category":"Wholesale",
            "subcategory":"Non-durable Goods",
            "type":"Manufacturing & Wholesale Goods"
        }
    ],
    "sg:phone":"+1 310 212 3259",
    "sg:postcode":"90503",
    "sg:province":"CA",
    "wof:name":"Round Up Trading Inc",
    "wof:placetype":"venue"
},
  "geometry": {"coordinates":[-118.210348,33.846406],"type":"Point"}
}