{
  "type": "Feature",
  "properties": {
    "addr:full":"14487 Griffith St San Leandro CA 94577",
    "addr:housenumber":"14487",
    "addr:postcode":"94577",
    "addr:street":"Griffith St",
    "iso:country":"US",
    "sg:address":"14487 Griffith St",
    "sg:city":"San Leandro",
    "sg:classifiers":[
        {
            "category":"Wholesale",
            "subcategory":"Hardware",
            "type":"Manufacturing & Wholesale Goods"
        }
    ],
    "sg:phone":"+1 510 352 4680",
    "sg:postcode":"94577",
    "sg:province":"CA",
    "sg:tags":[
        "air",
        "refrigeration",
        "conditioning",
        "supply"
    ],
    "wof:name":"Allied Refrigeration Inc",
    "wof:placetype":"venue"
},
  "geometry": {"coordinates":[-122.169757,37.697111],"type":"Point"}
}