{
  "type": "Feature",
  "properties": {
    "iso:country":"US",
    "sg:address":"11025 Alondra Blvd",
    "sg:city":"Norwalk",
    "sg:classifiers":[
        {
            "category":"Restaurant",
            "type":"Food & Drink"
        }
    ],
    "sg:phone":"+1 562 863 5252",
    "sg:postcode":"90650",
    "sg:province":"CA",
    "wof:name":"El Marinero Family Restaurant",
    "wof:placetype":"venue"
},
  "geometry": {"coordinates":[-118.09899900000001,33.887699],"type":"Point"}
}