{
  "type": "Feature",
  "properties": {
    "iso:country":"US",
    "sg:address":"2213 Sastre Ave",
    "sg:city":"South El Monte",
    "sg:classifiers":[
        {
            "category":"Manufacturing",
            "subcategory":"Signs",
            "type":"Manufacturing & Wholesale Goods"
        }
    ],
    "sg:phone":"+1 626 442 8690",
    "sg:postcode":"91733",
    "sg:province":"CA",
    "sg:tags":[
        "mfg"
    ],
    "wof:name":"Fargo Advertising",
    "wof:placetype":"venue"
},
  "geometry": {"coordinates":[-118.054261,34.054566],"type":"Point"}
}