{
  "type": "Feature",
  "properties": {
    "addr:full":"4730 Davis Dr Lakeport CA 95453",
    "addr:housenumber":"4730",
    "addr:postcode":"95453",
    "addr:street":"Davis Dr",
    "iso:country":"US",
    "sg:address":"4730 Davis Dr",
    "sg:city":"Lakeport",
    "sg:classifiers":[
        {
            "category":"Professional",
            "subcategory":"Management & Consulting",
            "type":"Services"
        }
    ],
    "sg:phone":"+1 707 263 1572",
    "sg:postcode":"95453",
    "sg:province":"CA",
    "sg:tags":[
        "agricultural",
        "consultant"
    ],
    "wof:name":"B V Svc",
    "wof:placetype":"venue"
},
  "geometry": {"coordinates":[-122.88254000000001,38.988415],"type":"Point"}
}