{
  "type": "Feature",
  "properties": {
    "addr:full":"2620 W Burbank Blvd Burbank CA 91505",
    "addr:housenumber":"2620",
    "addr:postcode":"91505",
    "addr:street":"W Burbank Blvd",
    "iso:country":"US",
    "sg:address":"2620 W Burbank Blvd",
    "sg:city":"Burbank",
    "sg:classifiers":[
        {
            "category":"Real Estate",
            "subcategory":"Real Estate Agent",
            "type":"Services"
        }
    ],
    "sg:phone":"+1 818 842 8100",
    "sg:postcode":"91505",
    "sg:province":"CA",
    "sg:tags":[
        "management",
        "property"
    ],
    "sg:website":"www.barryburnett.net",
    "wof:name":"Burnett Realty Inc",
    "wof:placetype":"venue"
},
  "geometry": {"coordinates":[-118.339996,34.178398],"type":"Point"}
}