{
  "type": "Feature",
  "properties": {
    "addr:full":"22347 El Toro Rd Lake Forest CA 92630",
    "addr:housenumber":"22347",
    "addr:postcode":"92630",
    "addr:street":"El Toro Rd",
    "iso:country":"US",
    "sg:address":"22347 El Toro Rd",
    "sg:city":"Lake Forest",
    "sg:classifiers":[
        {
            "category":"Personal",
            "subcategory":"Beauty Salon",
            "type":"Services"
        }
    ],
    "sg:phone":"+1 949 472 8510",
    "sg:postcode":"92630",
    "sg:province":"CA",
    "sg:tags":[
        "hair"
    ],
    "sg:website":"www.fantasticsams.com",
    "wof:name":"Fantastic Sams",
    "wof:placetype":"venue"
},
  "geometry": {"coordinates":[-117.678797,33.638023],"type":"Point"}
}