{
  "type": "Feature",
  "properties": {
    "iso:country":"US",
    "sg:address":"905 Orange Ave",
    "sg:city":"Long Beach",
    "sg:classifiers":[
        {
            "category":"Organizations",
            "subcategory":"Religious Organization",
            "type":"Services"
        }
    ],
    "sg:phone":"+1 562 599 5100",
    "sg:postcode":"90813",
    "sg:province":"CA",
    "sg:tags":[
        "church"
    ],
    "wof:name":"Buddhist Congregation Chr",
    "wof:placetype":"venue"
},
  "geometry": {"coordinates":[-118.17641,33.777969],"type":"Point"}
}