{
  "type": "Feature",
  "properties": {
    "addr:full":"1172 N Humboldt Ave Kerman CA 93630",
    "addr:housenumber":"1172",
    "addr:postcode":"93630",
    "addr:street":"N Humboldt Ave",
    "iso:country":"US",
    "sg:address":"1172 N Humboldt Ave",
    "sg:city":"Kerman",
    "sg:classifiers":[
        {
            "category":"Professional",
            "type":"Services"
        }
    ],
    "sg:phone":"+1 559 846 9685",
    "sg:postcode":"93630",
    "sg:province":"CA",
    "wof:name":"Mike W Slivkoff",
    "wof:placetype":"venue"
},
  "geometry": {"coordinates":[-120.123217,36.755722],"type":"Point"}
}