{
  "type": "Feature",
  "properties": {
    "addr:full":"10924 Kearney Ct Alta Loma CA 91701",
    "addr:housenumber":"10924",
    "addr:postcode":"91701",
    "addr:street":"Kearney Ct",
    "iso:country":"US",
    "sg:address":"10924 Kearney Ct",
    "sg:city":"Alta Loma",
    "sg:classifiers":[
        {
            "category":"Building & Trades",
            "subcategory":"Construction",
            "type":"Services"
        }
    ],
    "sg:phone":"+1 951 440 5267",
    "sg:postcode":"91701",
    "sg:province":"CA",
    "sg:tags":[
        "concrete",
        "pumping"
    ],
    "wof:name":"West Coast Concrete Pumping",
    "wof:placetype":"venue"
},
  "geometry": {"coordinates":[-117.566177,34.129547],"type":"Point"}
}