{
  "type": "Feature",
  "properties": {
    "addr:full":"930 Alhambra Blvd Ste 210 Sacramento CA 95816",
    "addr:housenumber":"930",
    "addr:postcode":"95816",
    "addr:street":"Alhambra Blvd Ste 210",
    "iso:country":"US",
    "sg:address":"930 Alhambra Blvd Ste 210",
    "sg:city":"Sacramento",
    "sg:classifiers":[
        {
            "category":"Health Services",
            "subcategory":"Doctor",
            "type":"Services"
        }
    ],
    "sg:postcode":"95816",
    "sg:province":"CA",
    "sg:tags":[
        "obstetrician",
        "gynecologist"
    ],
    "sg:website":"www.svpregnancyclinic.com/index.php",
    "wof:name":"Sac Valley Pregnancy Clinic",
    "wof:placetype":"venue"
},
  "geometry": {"coordinates":[-121.465479,38.573193],"type":"Point"}
}