{
  "type": "Feature",
  "properties": {
    "iso:country":"US",
    "sg:address":"11953 Inglewood Avenue",
    "sg:city":"Hawthorne",
    "sg:classifiers":[
        {
            "category":"Manufacturing",
            "subcategory":"Rubber & Plastics",
            "type":"Manufacturing & Wholesale Goods"
        },
        {
            "category":"Autos & Motor Vehicles",
            "subcategory":"Auto Supplies",
            "type":"Retail Goods"
        }
    ],
    "sg:phone":"+1 310 675 7488",
    "sg:postcode":"90250",
    "sg:province":"CA",
    "sg:tags":[
        "tires-wholesale",
        "tire",
        "manufacturer"
    ],
    "wof:name":"Baja Tires & Repair Services",
    "wof:placetype":"venue"
},
  "geometry": {"coordinates":[-118.361125,33.923882],"type":"Point"}
}