{
  "type": "Feature",
  "properties": {
    "iso:country":"US",
    "sg:address":"1115 Shore St",
    "sg:city":"West Sacramento",
    "sg:classifiers":[
        {
            "category":"Manufacturing",
            "subcategory":"Tools & Machinery",
            "type":"Manufacturing & Wholesale Goods"
        }
    ],
    "sg:phone":"+1 916 372 0657",
    "sg:postcode":"95691",
    "sg:province":"CA",
    "sg:tags":[
        "ink"
    ],
    "wof:name":"Ink Co",
    "wof:placetype":"venue"
},
  "geometry": {"coordinates":[-121.546074,38.572709],"type":"Point"}
}