{
  "type": "Feature",
  "properties": {
    "addr:full":"2480 N Quince Ave Rialto CA 92377",
    "addr:housenumber":"2480",
    "addr:postcode":"92377",
    "addr:street":"N Quince Ave",
    "iso:country":"US",
    "sg:address":"2480 N Quince Ave",
    "sg:city":"Rialto",
    "sg:classifiers":[
        {
            "category":"Building & Trades",
            "subcategory":"Construction",
            "type":"Services"
        }
    ],
    "sg:phone":"+1 909 875 6058",
    "sg:postcode":"92377",
    "sg:province":"CA",
    "sg:tags":[
        "contractor"
    ],
    "wof:name":"A C Prime Builders",
    "wof:placetype":"venue"
},
  "geometry": {"coordinates":[-117.396247,34.145458],"type":"Point"}
}