{
  "type": "Feature",
  "properties": {
    "addr:full":"2434 256th St Lomita CA 90717",
    "addr:housenumber":"2434",
    "addr:postcode":"90717",
    "addr:street":"256Th St",
    "iso:country":"US",
    "sg:address":"2434 256th St",
    "sg:city":"Lomita",
    "sg:classifiers":[
        {
            "category":"Building & Trades",
            "subcategory":"Plumbing",
            "type":"Services"
        }
    ],
    "sg:phone":"+1 310 530 5748",
    "sg:postcode":"90717",
    "sg:province":"CA",
    "sg:tags":[
        "contractor"
    ],
    "wof:name":"Ram Brothers Plumbing Inc",
    "wof:placetype":"venue"
},
  "geometry": {"coordinates":[-118.326634,33.790932],"type":"Point"}
}