{
  "type": "Feature",
  "properties": {
    "addr:full":"123 E Main St El Cajon CA 92020",
    "addr:housenumber":"123",
    "addr:postcode":"92020",
    "addr:street":"E Main St",
    "iso:country":"US",
    "sg:address":"123 E Main St",
    "sg:city":"El Cajon",
    "sg:classifiers":[
        {
            "category":"Shopping",
            "subcategory":"Clothing, Apparel, & Fashions",
            "type":"Retail Goods"
        },
        {
            "category":"Home & Garden",
            "subcategory":"Furniture",
            "type":"Retail Goods"
        },
        {
            "category":"Home & Garden",
            "subcategory":"Carpets & Floor Coverings",
            "type":"Retail Goods"
        }
    ],
    "sg:phone":"+1 619 440 1422",
    "sg:postcode":"92020",
    "sg:province":"CA",
    "sg:tags":[
        "children's",
        "clothing",
        "store",
        "mattress"
    ],
    "wof:name":"Moe's Children Furniture",
    "wof:placetype":"venue"
},
  "geometry": {"coordinates":[-116.96199799999999,32.794998],"type":"Point"}
}