{
  "type": "Feature",
  "properties": {
    "iso:country":"US",
    "sg:address":"3427 Foothill Blvd",
    "sg:city":"La Crescenta",
    "sg:classifiers":[
        {
            "category":"Personal",
            "subcategory":"Barber",
            "type":"Services"
        }
    ],
    "sg:phone":"+1 818 248 5588",
    "sg:postcode":"91214",
    "sg:province":"CA",
    "wof:name":"Hair & Now",
    "wof:placetype":"venue"
},
  "geometry": {"coordinates":[-118.25375,34.232831],"type":"Point"}
}