{
  "type": "Feature",
  "properties": {
    "iso:country":"US",
    "sg:address":"5255 Stevens Creek Blvd",
    "sg:city":"Santa Clara",
    "sg:classifiers":[
        {
            "category":"Professional",
            "subcategory":"Advertising",
            "type":"Services"
        }
    ],
    "sg:phone":"+1 408 727 6075",
    "sg:postcode":"95051",
    "sg:province":"CA",
    "sg:tags":[
        "mailing",
        "shipping"
    ],
    "wof:name":"American Mail Well Envelope Co",
    "wof:placetype":"venue"
},
  "geometry": {"coordinates":[-121.995625,37.323014],"type":"Point"}
}