{
  "type": "Feature",
  "properties": {
    "iso:country":"US",
    "sg:address":"801 N Brand Blvd",
    "sg:city":"Glendale",
    "sg:classifiers":[
        {
            "category":"Banks & Credit Unions",
            "subcategory":"Investment Brokerage",
            "type":"Services"
        }
    ],
    "sg:phone":"+1 818 545 3762",
    "sg:postcode":"91203",
    "sg:province":"CA",
    "sg:tags":[
        "advisory"
    ],
    "sg:website":"www.americanreal.com",
    "wof:name":"American Realty Advisors",
    "wof:placetype":"venue"
},
  "geometry": {"coordinates":[-118.255152,34.158462],"type":"Point"}
}