{
  "type": "Feature",
  "properties": {
    "iso:country":"US",
    "sg:address":"1030 Hemingway Ln",
    "sg:city":"Templeton",
    "sg:classifiers":[
        {
            "category":"Building & Trades",
            "subcategory":"Construction",
            "type":"Services"
        }
    ],
    "sg:phone":"+1 805 434 1346",
    "sg:postcode":"93465",
    "sg:province":"CA",
    "sg:tags":[
        "contractor",
        "utility"
    ],
    "wof:name":"Lm Cable Construction",
    "wof:placetype":"venue"
},
  "geometry": {"coordinates":[-120.722129,35.541458],"type":"Point"}
}