{
  "type": "Feature",
  "properties": {
    "iso:country":"US",
    "sg:address":"550 Vallombrosa Ave",
    "sg:city":"Chico",
    "sg:classifiers":[
        {
            "category":"Government",
            "subcategory":"Post Office",
            "type":"Public Place"
        }
    ],
    "sg:phone":"+1 530 343 2068",
    "sg:postcode":"95926",
    "sg:province":"CA",
    "wof:name":"US Post Office",
    "wof:placetype":"venue"
},
  "geometry": {"coordinates":[-121.83375700000001,39.734656],"type":"Point"}
}