{
  "type": "Feature",
  "properties": {
    "addr:full":"821 W Jefferson Blvd Los Angeles CA 90007",
    "addr:housenumber":"821",
    "addr:postcode":"90007",
    "addr:street":"W Jefferson Blvd",
    "iso:country":"US",
    "sg:address":"821 W Jefferson Blvd",
    "sg:city":"Los Angeles",
    "sg:classifiers":[
        {
            "category":"Restaurant",
            "type":"Food & Drink"
        }
    ],
    "sg:phone":"+1 213 748 8458",
    "sg:postcode":"90007",
    "sg:province":"CA",
    "sg:tags":[
        "breakfast",
        "brunch",
        "diner"
    ],
    "sg:website":"www.dennys.com",
    "wof:name":"Denny's",
    "wof:placetype":"venue"
},
  "geometry": {"coordinates":[-118.283997,34.023899],"type":"Point"}
}