{
  "type": "Feature",
  "properties": {
    "addr:full":"1111 Taraval St San Francisco CA 94116",
    "addr:housenumber":"1111",
    "addr:postcode":"94116",
    "addr:street":"Taraval St",
    "iso:country":"US",
    "sg:address":"1111 Taraval St",
    "sg:city":"San Francisco",
    "sg:classifiers":[
        {
            "category":"Retail",
            "subcategory":"Self-service Laundry",
            "type":"Services"
        }
    ],
    "sg:phone":"+1 415 731 6568",
    "sg:postcode":"94116",
    "sg:province":"CA",
    "wof:name":"Ocean Laundry & Dry Cleaners",
    "wof:placetype":"venue"
},
  "geometry": {"coordinates":[-122.478815,37.742839],"type":"Point"}
}