{
  "type": "Feature",
  "properties": {
    "addr:full":"1980 N Main St Los Angeles CA 90031",
    "addr:housenumber":"1980",
    "addr:postcode":"90031",
    "addr:street":"N Main St",
    "iso:country":"US",
    "sg:address":"1980 N Main St",
    "sg:city":"Los Angeles",
    "sg:classifiers":[
        {
            "category":"Shopping",
            "subcategory":"Antiques",
            "type":"Retail Goods"
        }
    ],
    "sg:phone":"+1 323 221 8411",
    "sg:postcode":"90031",
    "sg:province":"CA",
    "sg:website":"www.arteunico.net",
    "wof:name":"Arte Unico",
    "wof:placetype":"venue"
},
  "geometry": {"coordinates":[-118.21700300000001,34.065899],"type":"Point"}
}