{
  "type": "Feature",
  "properties": {
    "iso:country":"US",
    "sg:address":"2554 Main St",
    "sg:city":"Riverside",
    "sg:classifiers":[
        {
            "category":"Wholesale",
            "subcategory":"Auto Parts",
            "type":"Manufacturing & Wholesale Goods"
        }
    ],
    "sg:phone":"+1 951 276 8268",
    "sg:postcode":"92501",
    "sg:province":"CA",
    "sg:tags":[
        "used"
    ],
    "wof:name":"A & A Alternators & Starters",
    "wof:placetype":"venue"
},
  "geometry": {"coordinates":[-117.36695,33.993153],"type":"Point"}
}