{
  "type": "Feature",
  "properties": {
    "iso:country":"US",
    "sg:address":"445 N State St",
    "sg:city":"Ukiah",
    "sg:classifiers":[
        {
            "category":"Manufacturing",
            "subcategory":"Printing",
            "type":"Manufacturing & Wholesale Goods"
        }
    ],
    "sg:phone":"+1 707 462 6470",
    "sg:postcode":"95482",
    "sg:province":"CA",
    "sg:tags":[
        "newspaper"
    ],
    "wof:name":"Ukiah News Bureau",
    "wof:placetype":"venue"
},
  "geometry": {"coordinates":[-123.207966,39.152531],"type":"Point"}
}