{
  "type": "Feature",
  "properties": {
    "addr:full":"402 S Marengo Ave Pasadena CA 91101",
    "addr:housenumber":"402",
    "addr:postcode":"91101",
    "addr:street":"S Marengo Ave",
    "iso:country":"US",
    "sg:address":"402 S Marengo Ave",
    "sg:city":"Pasadena",
    "sg:classifiers":[
        {
            "category":"Organizations",
            "subcategory":"Religious Organization",
            "type":"Services"
        }
    ],
    "sg:phone":"+1 626 432 5680",
    "sg:postcode":"91101",
    "sg:province":"CA",
    "wof:name":"Holy Family Svc",
    "wof:placetype":"venue"
},
  "geometry": {"coordinates":[-118.145798,34.138063],"type":"Point"}
}