{
  "type": "Feature",
  "properties": {
    "iso:country":"US",
    "sg:address":"137 S Prospect Ave",
    "sg:city":"Tustin",
    "sg:classifiers":[
        {
            "category":"Professional",
            "subcategory":"Engineering",
            "type":"Services"
        }
    ],
    "sg:phone":"+1 714 730 6414",
    "sg:postcode":"92780",
    "sg:province":"CA",
    "sg:tags":[
        "engineer"
    ],
    "wof:name":"Dollar Engineering",
    "wof:placetype":"venue"
},
  "geometry": {"coordinates":[-117.822408,33.744715],"type":"Point"}
}