{
  "type": "Feature",
  "properties": {
    "iso:country":"US",
    "sg:address":"3309 W Magnolia Blvd",
    "sg:city":"Burbank",
    "sg:classifiers":[
        {
            "category":"Shopping",
            "subcategory":"Pharmacy",
            "type":"Retail Goods"
        }
    ],
    "sg:phone":"+1 818 843 6600",
    "sg:postcode":"91505",
    "sg:province":"CA",
    "sg:tags":[
        "drugstore"
    ],
    "wof:name":"Harmony RX Drug",
    "wof:placetype":"venue"
},
  "geometry": {"coordinates":[-118.343048,34.169331],"type":"Point"}
}