{
  "type": "Feature",
  "properties": {
    "iso:country":"US",
    "sg:address":"405 W Evans Reimer Rd",
    "sg:city":"Gridley",
    "sg:classifiers":[
        {
            "category":"Farming",
            "subcategory":"Orchard",
            "type":"Manufacturing & Wholesale Goods"
        }
    ],
    "sg:phone":"+1 530 846 4206",
    "sg:postcode":"95948",
    "sg:province":"CA",
    "sg:tags":[
        "fruit",
        "tree"
    ],
    "wof:name":"Khan Asrar",
    "wof:placetype":"venue"
},
  "geometry": {"coordinates":[-121.707809,39.333789],"type":"Point"}
}