{
  "type": "Feature",
  "properties": {
    "addr:full":"370 Highland Ave Piedmont CA 94611",
    "addr:housenumber":"370",
    "addr:postcode":"94611",
    "addr:street":"Highland Ave",
    "iso:country":"US",
    "sg:address":"370 Highland Ave",
    "sg:city":"Piedmont",
    "sg:classifiers":[
        {
            "category":"Personal",
            "subcategory":"Barber",
            "type":"Services"
        }
    ],
    "sg:phone":"+1 510 655 3358",
    "sg:postcode":"94611",
    "sg:province":"CA",
    "wof:name":"Chaparral Barber Shop",
    "wof:placetype":"venue"
},
  "geometry": {"coordinates":[-122.23200199999999,37.824501],"type":"Point"}
}