{
  "type": "Feature",
  "properties": {
    "addr:full":"3700 Midas Ave Rocklin CA 95677",
    "addr:housenumber":"3700",
    "addr:postcode":"95677",
    "addr:street":"Midas Ave",
    "iso:country":"US",
    "sg:address":"3700 Midas Ave",
    "sg:city":"Rocklin",
    "sg:classifiers":[
        {
            "category":"Shopping",
            "subcategory":"Pets & Pet Supplies",
            "type":"Retail Goods"
        },
        {
            "category":"Retail",
            "subcategory":"Animal Services",
            "type":"Services"
        }
    ],
    "sg:phone":"+1 916 624 2262",
    "sg:postcode":"95677",
    "sg:province":"CA",
    "sg:tags":[
        "grooming",
        "dog",
        "cat"
    ],
    "sg:website":"http://www.rocklinwagstoriches.com",
    "wof:name":"Wags To Riches Dog & Cat Grooming",
    "wof:placetype":"venue"
},
  "geometry": {"coordinates":[-121.234131,38.795811],"type":"Point"}
}