{
  "type": "Feature",
  "properties": {
    "addr:full":"2700 Imperial Ave San Diego CA 92102",
    "addr:housenumber":"2700",
    "addr:postcode":"92102",
    "addr:street":"Imperial Ave",
    "iso:country":"US",
    "sg:address":"2700 Imperial Ave",
    "sg:city":"San Diego",
    "sg:classifiers":[
        {
            "category":"Autos & Motor Vehicles",
            "subcategory":"Automobile Sales",
            "type":"Retail Goods"
        }
    ],
    "sg:phone":"+1 619 237 1827",
    "sg:postcode":"92102",
    "sg:province":"CA",
    "sg:tags":[
        "car",
        "dealer"
    ],
    "wof:name":"Lupita's Auto Sales",
    "wof:placetype":"venue"
},
  "geometry": {"coordinates":[-117.135465,32.706369],"type":"Point"}
}