{
  "type": "Feature",
  "properties": {
    "addr:full":"1912 N Broadway Santa Ana CA 92706",
    "addr:housenumber":"1912",
    "addr:postcode":"92706",
    "addr:street":"N Broadway",
    "iso:country":"US",
    "sg:address":"1912 N Broadway",
    "sg:city":"Santa Ana",
    "sg:classifiers":[
        {
            "category":"Professional",
            "subcategory":"Lawyer & Legal Services",
            "type":"Services"
        }
    ],
    "sg:phone":"+1 714 543 2266",
    "sg:postcode":"92706",
    "sg:province":"CA",
    "wof:name":"Hartmann Robert M Atty At Law",
    "wof:placetype":"venue"
},
  "geometry": {"coordinates":[-117.870003,33.761902],"type":"Point"}
}