{
  "type": "Feature",
  "properties": {
    "iso:country":"US",
    "sg:address":"550 W Aviation Rd",
    "sg:city":"Fallbrook",
    "sg:classifiers":[
        {
            "category":"Retail",
            "subcategory":"Storage",
            "type":"Services"
        }
    ],
    "sg:phone":"+1 760 728 6114",
    "sg:postcode":"92028",
    "sg:province":"CA",
    "sg:tags":[
        "self"
    ],
    "wof:name":"Fallbrook Mini Storage",
    "wof:placetype":"venue"
},
  "geometry": {"coordinates":[-117.25700399999999,33.373001],"type":"Point"}
}