{
  "type": "Feature",
  "properties": {
    "iso:country":"US",
    "sg:address":"795 Fernandez Ave",
    "sg:city":"Pinole",
    "sg:classifiers":[
        {
            "category":"Banks & Credit Unions",
            "subcategory":"Bank",
            "type":"Services"
        }
    ],
    "sg:phone":"+1 510 262 7282",
    "sg:postcode":"94564",
    "sg:province":"CA",
    "wof:name":"Mechanics Bank",
    "wof:placetype":"venue"
},
  "geometry": {"coordinates":[-122.290391,38.006822],"type":"Point"}
}