{
  "type": "Feature",
  "properties": {
    "addr:full":"957 Jackson St Oakland CA 94607",
    "addr:housenumber":"957",
    "addr:postcode":"94607",
    "addr:street":"Jackson St",
    "iso:country":"US",
    "sg:address":"957 Jackson St",
    "sg:city":"Oakland",
    "sg:classifiers":[
        {
            "category":"Insurance",
            "subcategory":"Insurance Agent",
            "type":"Services"
        }
    ],
    "sg:phone":"+1 510 465 7841",
    "sg:postcode":"94607",
    "sg:province":"CA",
    "wof:name":"Equitable Life Assurance Soc",
    "wof:placetype":"venue"
},
  "geometry": {"coordinates":[-122.267264,37.798884],"type":"Point"}
}