{
  "type": "Feature",
  "properties": {
    "addr:full":"149 Pearwood Ln Corona CA 92882",
    "addr:housenumber":"149",
    "addr:postcode":"92882",
    "addr:street":"Pearwood Ln",
    "iso:country":"US",
    "sg:address":"149 Pearwood Ln",
    "sg:city":"Corona",
    "sg:classifiers":[
        {
            "category":"Building & Trades",
            "subcategory":"Electrical",
            "type":"Services"
        }
    ],
    "sg:phone":"+1 951 735 7004",
    "sg:postcode":"92882",
    "sg:province":"CA",
    "sg:tags":[
        "electrician"
    ],
    "wof:name":"Dc Electric",
    "wof:placetype":"venue"
},
  "geometry": {"coordinates":[-117.571243,33.84832],"type":"Point"}
}