{
  "type": "Feature",
  "properties": {
    "iso:country":"US",
    "sg:address":"1022 Santa Rosa Ave",
    "sg:city":"Santa Rosa",
    "sg:classifiers":[
        {
            "category":"Building & Trades",
            "subcategory":"Construction",
            "type":"Services"
        }
    ],
    "sg:phone":"+1 707 545 8468",
    "sg:postcode":"95404",
    "sg:province":"CA",
    "sg:tags":[
        "contractor"
    ],
    "wof:name":"Sun Tint",
    "wof:placetype":"venue"
},
  "geometry": {"coordinates":[-122.71186899999999,38.428901],"type":"Point"}
}