{
  "type": "Feature",
  "properties": {
    "iso:country":"US",
    "sg:address":"6801 Burdett Way",
    "sg:city":"Sacramento",
    "sg:classifiers":[
        {
            "category":"Retail",
            "subcategory":"Auto Repair",
            "type":"Services"
        }
    ],
    "sg:phone":"+1 916 391 5165",
    "sg:postcode":"95823",
    "sg:province":"CA",
    "sg:tags":[
        "body"
    ],
    "wof:name":"Grammas Workshop",
    "wof:placetype":"venue"
},
  "geometry": {"coordinates":[-121.438014,38.503571],"type":"Point"}
}