{
  "type": "Feature",
  "properties": {
    "iso:country":"US",
    "sg:address":"235 E Broadway",
    "sg:city":"Long Beach",
    "sg:classifiers":[
        {
            "category":"Manufacturing",
            "subcategory":"Food",
            "type":"Manufacturing & Wholesale Goods"
        }
    ],
    "sg:phone":"+1 562 624 2311",
    "sg:postcode":"90802",
    "sg:province":"CA",
    "sg:tags":[
        "product",
        "manufacturer"
    ],
    "wof:name":"Marketing Sales & Svc",
    "wof:placetype":"venue"
},
  "geometry": {"coordinates":[-118.189492,33.769362],"type":"Point"}
}