{
  "type": "Feature",
  "properties": {
    "addr:full":"1461 N A St Perris CA 92570",
    "addr:housenumber":"1461",
    "addr:postcode":"92570",
    "addr:street":"N A St",
    "iso:country":"US",
    "sg:address":"1461 N A St",
    "sg:city":"Perris",
    "sg:classifiers":[
        {
            "category":"Education",
            "subcategory":"School",
            "type":"Public Place"
        }
    ],
    "sg:phone":"+1 951 657 0728",
    "sg:postcode":"92570",
    "sg:province":"CA",
    "sg:website":"www.perris.k12.ca.us",
    "wof:name":"Nan Sanders Elementary School",
    "wof:placetype":"venue"
},
  "geometry": {"coordinates":[-117.23472599999999,33.798984],"type":"Point"}
}