{
  "type": "Feature",
  "properties": {
    "iso:country":"US",
    "sg:address":"962 S 1st St",
    "sg:city":"San Jose",
    "sg:classifiers":[
        {
            "category":"Personal",
            "subcategory":"Barber",
            "type":"Services"
        }
    ],
    "sg:phone":"+1 408 288 5066",
    "sg:postcode":"95110",
    "sg:province":"CA",
    "sg:website":"www.myspace.com/premiumcutzbarbe...",
    "wof:name":"Premium Cutz",
    "wof:placetype":"venue"
},
  "geometry": {"coordinates":[-121.879283,37.321885],"type":"Point"}
}