{
  "type": "Feature",
  "properties": {
    "addr:full":"1100 Center St Redding CA 96001",
    "addr:housenumber":"1100",
    "addr:postcode":"96001",
    "addr:street":"Center St",
    "iso:country":"US",
    "sg:address":"1100 Center St",
    "sg:city":"Redding",
    "sg:classifiers":[
        {
            "category":"Restaurant",
            "type":"Food & Drink"
        }
    ],
    "sg:phone":"+1 530 244 7663",
    "sg:postcode":"96001",
    "sg:province":"CA",
    "sg:website":"www.girondas.com",
    "wof:name":"Gironda's Restaurant",
    "wof:placetype":"venue"
},
  "geometry": {"coordinates":[-122.394863,40.587047],"type":"Point"}
}