{
  "type": "Feature",
  "properties": {
    "addr:full":"4307 Foothill Way Pittsburg CA 94565",
    "addr:housenumber":"4307",
    "addr:postcode":"94565",
    "addr:street":"Foothill Way",
    "iso:country":"US",
    "sg:address":"4307 Foothill Way",
    "sg:city":"Pittsburg",
    "sg:classifiers":[
        {
            "category":"Professional",
            "subcategory":"Research",
            "type":"Services"
        }
    ],
    "sg:phone":"+1 925 709 1944",
    "sg:postcode":"94565",
    "sg:province":"CA",
    "sg:tags":[
        "environmental",
        "ecological"
    ],
    "wof:name":"General Environmental Mgmt Svc",
    "wof:placetype":"venue"
},
  "geometry": {"coordinates":[-121.879846,37.992962],"type":"Point"}
}