{
  "type": "Feature",
  "properties": {
    "addr:full":"575 W College Ave Santa Rosa CA 95401",
    "addr:housenumber":"575",
    "addr:postcode":"95401",
    "addr:street":"W College Ave",
    "iso:country":"US",
    "sg:address":"575 W College Ave",
    "sg:city":"Santa Rosa",
    "sg:classifiers":[
        {
            "category":"Professional",
            "subcategory":"Management & Consulting",
            "type":"Services"
        }
    ],
    "sg:phone":"+1 707 544 2348",
    "sg:postcode":"95401",
    "sg:province":"CA",
    "sg:tags":[
        "communications",
        "consultant"
    ],
    "wof:name":"Organization By Design",
    "wof:placetype":"venue"
},
  "geometry": {"coordinates":[-122.73527,38.445672],"type":"Point"}
}