{
  "type": "Feature",
  "properties": {
    "iso:country":"US",
    "sg:address":"825 Van Ness Avenue",
    "sg:city":"San Francisco",
    "sg:classifiers":[
        {
            "category":"Professional",
            "subcategory":"Lawyer & Legal Services",
            "type":"Services"
        }
    ],
    "sg:phone":"+1 415 440 3102",
    "sg:postcode":"94109",
    "sg:province":"CA",
    "wof:name":"Mosley & Gearinger",
    "wof:placetype":"venue"
},
  "geometry": {"coordinates":[-122.420998,37.783199],"type":"Point"}
}