{
  "type": "Feature",
  "properties": {
    "addr:full":"1819 1/2 Pacific Coast Hwy Lomita CA 90717",
    "addr:housenumber":"1819 1 / 2",
    "addr:postcode":"90717",
    "addr:street":"Pacific Coast Hwy",
    "iso:country":"US",
    "sg:address":"1819 1/2 Pacific Coast Hwy",
    "sg:city":"Lomita",
    "sg:classifiers":[
        {
            "category":"Real Estate",
            "subcategory":"Real Estate Services",
            "type":"Services"
        }
    ],
    "sg:phone":"+1 310 325 5177",
    "sg:postcode":"90717",
    "sg:province":"CA",
    "wof:name":"Alexander Real Estate",
    "wof:placetype":"venue"
},
  "geometry": {"coordinates":[-118.310219,33.789495],"type":"Point"}
}