{
  "type": "Feature",
  "properties": {
    "addr:full":"2505 Hilltop Dr Redding CA 96002",
    "addr:housenumber":"2505",
    "addr:postcode":"96002",
    "addr:street":"Hilltop Dr",
    "iso:country":"US",
    "sg:address":"2505 Hilltop Dr",
    "sg:city":"Redding",
    "sg:classifiers":[
        {
            "category":"Retail",
            "subcategory":"Veterinary Services",
            "type":"Services"
        },
        {
            "category":"Retail",
            "subcategory":"Animal Services",
            "type":"Services"
        }
    ],
    "sg:phone":"+1 530 410 0690",
    "sg:postcode":"96002",
    "sg:province":"CA",
    "sg:tags":[
        "pet",
        "hospital",
        "veterinarian",
        "clinic"
    ],
    "sg:website":"http://ad.doubleclick.net/clk;226007916;49913701;g?http://www.vcahospitals.com/main/offer?utm_source=iyp&utm_medium=iyp&utm_campaign=yellowpages",
    "wof:name":"VCA Asher Animal Hospital",
    "wof:placetype":"venue"
},
  "geometry": {"coordinates":[-122.35803300000001,40.572],"type":"Point"}
}