{
  "type": "Feature",
  "properties": {
    "iso:country":"US",
    "sg:address":"14548 Baseline Ave",
    "sg:city":"Fontana",
    "sg:classifiers":[
        {
            "category":"Restaurant",
            "type":"Food & Drink"
        }
    ],
    "sg:phone":"+1 909 350 0910",
    "sg:postcode":"92336",
    "sg:province":"CA",
    "sg:tags":[
        "shop",
        "coffee"
    ],
    "wof:name":"Sonrise Coffee House",
    "wof:placetype":"venue"
},
  "geometry": {"coordinates":[-117.485233,34.121506],"type":"Point"}
}