{
  "type": "Feature",
  "properties": {
    "addr:full":"14548 Baseline Ave Fontana CA 92336",
    "addr:housenumber":"14548",
    "addr:postcode":"92336",
    "addr:street":"Baseline Ave",
    "iso:country":"US",
    "sg:address":"14548 Baseline Ave",
    "sg:city":"Fontana",
    "sg:classifiers":[
        {
            "category":"Restaurant",
            "type":"Food & Drink"
        }
    ],
    "sg:phone":"+1 909 350 0910",
    "sg:postcode":"92336",
    "sg:province":"CA",
    "sg:tags":[
        "shop",
        "coffee"
    ],
    "wof:name":"Sonrise Coffee House",
    "wof:placetype":"venue"
},
  "geometry": {"coordinates":[-117.48523299999999,34.121506],"type":"Point"}
}