{
  "type": "Feature",
  "properties": {
    "iso:country":"US",
    "sg:address":"1270 Arroyo Way",
    "sg:city":"Walnut Creek",
    "sg:classifiers":[
        {
            "category":"Health Services",
            "subcategory":"Doctor",
            "type":"Services"
        }
    ],
    "sg:phone":"+1 925 283 2366",
    "sg:postcode":"94596",
    "sg:province":"CA",
    "sg:tags":[
        "physician",
        "surgeon"
    ],
    "wof:name":"Fischman Occupational Med Grp",
    "wof:placetype":"venue"
},
  "geometry": {"coordinates":[-122.059835,37.905116],"type":"Point"}
}