{
  "type": "Feature",
  "properties": {
    "iso:country":"US",
    "sg:address":"22 Woodland Ave",
    "sg:city":"San Rafael",
    "sg:classifiers":[
        {
            "category":"Retail",
            "subcategory":"Auto Repair",
            "type":"Services"
        }
    ],
    "sg:phone":"+1 415 459 3309",
    "sg:postcode":"94901",
    "sg:province":"CA",
    "sg:tags":[
        "repairing",
        "automobile"
    ],
    "wof:name":"Askims' Auto Works",
    "wof:placetype":"venue"
},
  "geometry": {"coordinates":[-122.51534100000001,37.962077],"type":"Point"}
}