{
  "type": "Feature",
  "properties": {
    "addr:full":"2687 E Portland Ave Fresno CA 93720",
    "addr:housenumber":"2687",
    "addr:postcode":"93720",
    "addr:street":"E Portland Ave",
    "iso:country":"US",
    "sg:address":"2687 E Portland Ave",
    "sg:city":"Fresno",
    "sg:classifiers":[
        {
            "category":"Professional",
            "type":"Services"
        }
    ],
    "sg:phone":"+1 559 323 1210",
    "sg:postcode":"93720",
    "sg:province":"CA",
    "sg:tags":[
        "establishment"
    ],
    "wof:name":"Carr Beverly",
    "wof:placetype":"venue"
},
  "geometry": {"coordinates":[-119.742169,36.856025],"type":"Point"}
}