{
  "type": "Feature",
  "properties": {
    "addr:full":"16516 Bernardo Center Dr San Diego CA 92128",
    "addr:housenumber":"16516",
    "addr:postcode":"92128",
    "addr:street":"Bernardo Center Dr",
    "iso:country":"US",
    "sg:address":"16516 Bernardo Center Dr",
    "sg:city":"San Diego",
    "sg:classifiers":[
        {
            "category":"Utilities",
            "subcategory":"Mobile Phone",
            "type":"Services"
        }
    ],
    "sg:phone":"+1 858 487 3224",
    "sg:postcode":"92128",
    "sg:province":"CA",
    "sg:tags":[
        "communication",
        "radiotelephone"
    ],
    "wof:name":"Comm A 6 Solutions",
    "wof:placetype":"venue"
},
  "geometry": {"coordinates":[-117.078051,33.013376],"type":"Point"}
}