{
  "type": "Feature",
  "properties": {
    "addr:full":"1125 W Avenue O M14 M14 Ste A Palmdale CA 93551",
    "addr:housenumber":"1125;m14 m14 ste a",
    "addr:postcode":"ca 93551",
    "addr:street":"W Avenue O",
    "iso:country":"US",
    "sg:address":"1125 W Avenue O M14 M14 Ste A",
    "sg:city":"Palmdale",
    "sg:classifiers":[
        {
            "category":"Professional",
            "subcategory":"Lawyer & Legal Services",
            "type":"Services"
        }
    ],
    "sg:phone":"+1 661 273 1780",
    "sg:postcode":"93551",
    "sg:province":"CA",
    "sg:tags":[
        "attorney",
        "practice"
    ],
    "wof:name":"Ashton, David W",
    "wof:placetype":"venue"
},
  "geometry": {"coordinates":[-118.15140100000001,34.616581],"type":"Point"}
}