{
  "type": "Feature",
  "properties": {
    "iso:country":"US",
    "sg:address":"642 Martin Ave",
    "sg:city":"Rohnert Park",
    "sg:classifiers":[
        {
            "category":"Retail",
            "subcategory":"Laundry & Dry Cleaning",
            "type":"Services"
        }
    ],
    "sg:phone":"+1 707 795 1001",
    "sg:postcode":"94928",
    "sg:province":"CA",
    "sg:tags":[
        "cleaners",
        "rug",
        "carpet"
    ],
    "wof:name":"Stanley Steemer Carpet Cleaner",
    "wof:placetype":"venue"
},
  "geometry": {"coordinates":[-122.724047,38.351841],"type":"Point"}
}