{
  "type": "Feature",
  "properties": {
    "addr:full":"1418 Grizzly Ct Yreka CA 96097",
    "addr:housenumber":"1418",
    "addr:postcode":"96097",
    "addr:street":"Grizzly Ct",
    "iso:country":"US",
    "sg:address":"1418 Grizzly Ct",
    "sg:city":"Yreka",
    "sg:classifiers":[
        {
            "category":"Social Services",
            "type":"Services"
        }
    ],
    "sg:phone":"+1 530 842 2701",
    "sg:postcode":"96097",
    "sg:province":"CA",
    "sg:tags":[
        "youth",
        "organization",
        "center"
    ],
    "wof:name":"Youth Specialties",
    "wof:placetype":"venue"
},
  "geometry": {"coordinates":[-122.658916,41.739576],"type":"Point"}
}