{
  "type": "Feature",
  "properties": {
    "iso:country":"US",
    "sg:address":"330 E Manchester Blvd",
    "sg:city":"Inglewood",
    "sg:classifiers":[
        {
            "category":"Organizations",
            "subcategory":"Non-profit Organization",
            "type":"Services"
        }
    ],
    "sg:phone":"+1 310 693 6550",
    "sg:postcode":"90301",
    "sg:province":"CA",
    "sg:tags":[
        "service/non-profit",
        "community"
    ],
    "sg:website":"www.broadspectrum.org",
    "wof:name":"Broad Spectrum CDC",
    "wof:placetype":"venue"
},
  "geometry": {"coordinates":[-118.35146400000001,33.961805],"type":"Point"}
}