{
  "type": "Feature",
  "properties": {
    "addr:full":"1175 W Carson St Torrance CA 90502",
    "addr:housenumber":"1175",
    "addr:postcode":"90502",
    "addr:street":"W Carson St",
    "iso:country":"US",
    "sg:address":"1175 W Carson St",
    "sg:city":"Torrance",
    "sg:classifiers":[
        {
            "category":"Wholesale",
            "subcategory":"Computers",
            "type":"Manufacturing & Wholesale Goods"
        },
        {
            "category":"Professional",
            "subcategory":"Computer Services",
            "type":"Services"
        }
    ],
    "sg:phone":"+1 310 516 2098",
    "sg:postcode":"90502",
    "sg:province":"CA",
    "sg:tags":[
        "repair"
    ],
    "wof:name":"PC Warehouse",
    "wof:placetype":"venue"
},
  "geometry": {"coordinates":[-118.29619,33.831585],"type":"Point"}
}