{
  "type": "Feature",
  "properties": {
    "iso:country":"US",
    "sg:address":"133 Jackson St",
    "sg:city":"Hayward",
    "sg:classifiers":[
        {
            "category":"Retail",
            "subcategory":"Car Wash",
            "type":"Services"
        }
    ],
    "sg:phone":"+1 510 733 0588",
    "sg:postcode":"94544",
    "sg:province":"CA",
    "sg:tags":[
        "automobile",
        "detail",
        "clean"
    ],
    "sg:website":"haywardcarwash.com/",
    "wof:name":"Hayward Touchless Car Wash",
    "wof:placetype":"venue"
},
  "geometry": {"coordinates":[-122.08654,37.658173],"type":"Point"}
}