{
  "type": "Feature",
  "properties": {
    "iso:country":"US",
    "sg:address":"1190 E Walnut St",
    "sg:city":"Pasadena",
    "sg:classifiers":[
        {
            "category":"Shopping",
            "type":"Retail Goods"
        }
    ],
    "sg:phone":"+1 626 792 6240",
    "sg:postcode":"91106",
    "sg:province":"CA",
    "sg:tags":[
        "antique",
        "coin",
        "supply"
    ],
    "wof:name":"Universal Coin Galleries",
    "wof:placetype":"venue"
},
  "geometry": {"coordinates":[-118.12586899999999,34.149551],"type":"Point"}
}