{
  "type": "Feature",
  "properties": {
    "addr:full":"1335 Bell St Apt 103 Sacramento CA 95825",
    "addr:housenumber":"1335;103",
    "addr:postcode":"95825",
    "addr:street":"Bell St Apt",
    "iso:country":"US",
    "sg:address":"1335 Bell St Apt 103",
    "sg:city":"Sacramento",
    "sg:classifiers":[
        {
            "category":"Shopping",
            "subcategory":"Computers & Home Electronics",
            "type":"Retail Goods"
        }
    ],
    "sg:phone":"+1 916 226 5989",
    "sg:postcode":"95825",
    "sg:province":"CA",
    "sg:tags":[
        "theater",
        "consumer",
        "system"
    ],
    "wof:name":"Mh Electronics",
    "wof:placetype":"venue"
},
  "geometry": {"coordinates":[-121.410715,38.590132],"type":"Point"}
}