{
  "type": "Feature",
  "properties": {
    "iso:country":"US",
    "sg:address":"3160 Danville Blvd",
    "sg:city":"Alamo",
    "sg:classifiers":[
        {
            "category":"Restaurant",
            "type":"Food & Drink"
        }
    ],
    "sg:phone":"+1 925 362 1520",
    "sg:postcode":"94507",
    "sg:province":"CA",
    "wof:name":"Subway Sandwiches & Salads",
    "wof:placetype":"venue"
},
  "geometry": {"coordinates":[-122.045556,37.871141],"type":"Point"}
}