{
  "type": "Feature",
  "properties": {
    "iso:country":"US",
    "sg:address":"24012 Lyons Ave",
    "sg:city":"Newhall",
    "sg:classifiers":[
        {
            "category":"Food & Beverages",
            "subcategory":"Specialty",
            "type":"Retail Goods"
        }
    ],
    "sg:phone":"+1 661 259 5657",
    "sg:postcode":"91321",
    "sg:province":"CA",
    "sg:tags":[
        "water",
        "bulk",
        "company"
    ],
    "wof:name":"Safe H2o",
    "wof:placetype":"venue"
},
  "geometry": {"coordinates":[-118.554454,34.378828],"type":"Point"}
}