{
  "type": "Feature",
  "properties": {
    "addr:full":"14671 Byron Hwy Byron CA 94514",
    "addr:housenumber":"14671",
    "addr:postcode":"94514",
    "addr:street":"Byron Hwy",
    "iso:country":"US",
    "sg:address":"14671 Byron Hwy",
    "sg:city":"Byron",
    "sg:classifiers":[
        {
            "category":"Organizations",
            "subcategory":"Religious Organization",
            "type":"Services"
        }
    ],
    "sg:phone":"+1 925 634 1411",
    "sg:postcode":"94514",
    "sg:province":"CA",
    "sg:tags":[
        "church"
    ],
    "wof:name":"Byron United Methodist Church",
    "wof:placetype":"venue"
},
  "geometry": {"coordinates":[-121.619315,37.846491],"type":"Point"}
}