{
  "type": "Feature",
  "properties": {
    "iso:country":"US",
    "sg:address":"2139 Freedom Blvd",
    "sg:city":"Freedom",
    "sg:classifiers":[
        {
            "category":"Food & Beverages",
            "subcategory":"Liquor & Beverages",
            "type":"Retail Goods"
        }
    ],
    "sg:phone":"+1 831 724 8559",
    "sg:postcode":"95019",
    "sg:province":"CA",
    "wof:name":"Dale's Liquors & Grocery",
    "wof:placetype":"venue"
},
  "geometry": {"coordinates":[-121.781224,36.940153],"type":"Point"}
}