{
  "type": "Feature",
  "properties": {
    "addr:full":"8230 Commercial St La Mesa CA 91942",
    "addr:housenumber":"8230",
    "addr:postcode":"91942",
    "addr:street":"Commercial St",
    "iso:country":"US",
    "sg:address":"8230 Commercial St",
    "sg:city":"La Mesa",
    "sg:classifiers":[
        {
            "category":"Autos & Motor Vehicles",
            "subcategory":"Automobile Sales",
            "type":"Retail Goods"
        }
    ],
    "sg:phone":"+1 619 697 7200",
    "sg:postcode":"91942",
    "sg:province":"CA",
    "sg:tags":[
        "car",
        "dealer"
    ],
    "wof:name":"PAW Auto Svc",
    "wof:placetype":"venue"
},
  "geometry": {"coordinates":[-117.01946700000001,32.772861],"type":"Point"}
}