{
  "type": "Feature",
  "properties": {
    "addr:full":"5185 Buck Rd Brawley CA 92227",
    "addr:housenumber":"5185",
    "addr:postcode":"92227",
    "addr:street":"Buck Rd",
    "iso:country":"US",
    "sg:address":"5185 Buck Rd",
    "sg:city":"Brawley",
    "sg:classifiers":[
        {
            "category":"Farming",
            "subcategory":"Livestock Farm",
            "type":"Manufacturing & Wholesale Goods"
        }
    ],
    "sg:phone":"+1 760 344 7649",
    "sg:postcode":"92227",
    "sg:province":"CA",
    "sg:tags":[
        "specialty",
        "animal"
    ],
    "wof:name":"Lowrie Pollation",
    "wof:placetype":"venue"
},
  "geometry": {"coordinates":[-115.692821,33.025291],"type":"Point"}
}