{
  "type": "Feature",
  "properties": {
    "iso:country":"US",
    "sg:address":"3442 Lake Tahoe Blvd",
    "sg:city":"South Lake Tahoe",
    "sg:classifiers":[
        {
            "category":"Personal",
            "subcategory":"Barber",
            "type":"Services"
        }
    ],
    "sg:phone":"+1 530 541 2230",
    "sg:postcode":"96150",
    "sg:province":"CA",
    "wof:name":"Rich",
    "wof:placetype":"venue"
},
  "geometry": {"coordinates":[-119.966841,38.945494],"type":"Point"}
}