{
  "type": "Feature",
  "properties": {
    "iso:country":"US",
    "sg:address":"1832 Stone Ave",
    "sg:city":"San Jose",
    "sg:classifiers":[
        {
            "category":"Wholesale",
            "subcategory":"Auto Parts",
            "type":"Manufacturing & Wholesale Goods"
        }
    ],
    "sg:phone":"+1 408 275 9540",
    "sg:postcode":"95125",
    "sg:province":"CA",
    "sg:tags":[
        "equipment",
        "truck"
    ],
    "wof:name":"Quest Transportation Products",
    "wof:placetype":"venue"
},
  "geometry": {"coordinates":[-121.876165,37.306149],"type":"Point"}
}