{
  "type": "Feature",
  "properties": {
    "iso:country":"US",
    "sg:address":"95 Scripps Drive",
    "sg:city":"Sacramento",
    "sg:classifiers":[
        {
            "category":"Health Services",
            "subcategory":"Doctor",
            "type":"Services"
        },
        {
            "category":"Personal",
            "subcategory":"Hair Removal",
            "type":"Services"
        }
    ],
    "sg:phone":"+1 916 929 1833",
    "sg:postcode":"95825",
    "sg:province":"CA",
    "wof:name":"Yamahata Wayne I MD",
    "wof:placetype":"venue"
},
  "geometry": {"coordinates":[-121.409727,38.571758],"type":"Point"}
}