{
  "type": "Feature",
  "properties": {
    "addr:full":"14260 Garden Rd Poway CA 92064",
    "addr:housenumber":"14260",
    "addr:postcode":"ca 92064",
    "addr:street":"Garden Rd",
    "iso:country":"US",
    "sg:address":"14260 Garden Rd",
    "sg:city":"Poway",
    "sg:classifiers":[
        {
            "category":"Banks & Credit Unions",
            "subcategory":"Investment Brokerage",
            "type":"Services"
        }
    ],
    "sg:phone":"+1 858 748 8444",
    "sg:postcode":"92064",
    "sg:province":"CA",
    "sg:tags":[
        "stock",
        "bond"
    ],
    "wof:name":"J K Financial Svc Inc",
    "wof:placetype":"venue"
},
  "geometry": {"coordinates":[-117.023129,32.956332],"type":"Point"}
}