{
  "type": "Feature",
  "properties": {
    "iso:country":"US",
    "sg:address":"5775 E Los Angeles Ave",
    "sg:city":"Simi Valley",
    "sg:classifiers":[
        {
            "category":"Shopping",
            "subcategory":"Clothing, Apparel, & Fashions",
            "type":"Retail Goods"
        }
    ],
    "sg:phone":"+1 805 526 1175",
    "sg:postcode":"93063",
    "sg:province":"CA",
    "wof:name":"Tribex Adrenaline Wear",
    "wof:placetype":"venue"
},
  "geometry": {"coordinates":[-118.679949,34.271805],"type":"Point"}
}