{
  "type": "Feature",
  "properties": {
    "iso:country":"US",
    "sg:address":"10800 W Pico Blvd",
    "sg:city":"Los Angeles",
    "sg:classifiers":[
        {
            "category":"Shopping",
            "subcategory":"Clothing, Apparel, & Fashions",
            "type":"Retail Goods"
        }
    ],
    "sg:phone":"+1 310 441 1050",
    "sg:postcode":"90064",
    "sg:province":"CA",
    "wof:name":"Windsor Fashions",
    "wof:placetype":"venue"
},
  "geometry": {"coordinates":[-118.428488,34.040116],"type":"Point"}
}