{
  "type": "Feature",
  "properties": {
    "iso:country":"US",
    "sg:address":"1200 Mount Diablo Blvd",
    "sg:city":"Walnut Creek",
    "sg:classifiers":[
        {
            "category":"Professional",
            "subcategory":"Employment Agencies",
            "type":"Services"
        }
    ],
    "sg:phone":"+1 408 369 9500",
    "sg:postcode":"94596",
    "sg:province":"CA",
    "sg:tags":[
        "opportunity"
    ],
    "wof:name":"Essential Solutions Inc",
    "wof:placetype":"venue"
},
  "geometry": {"coordinates":[-122.056471,37.898832],"type":"Point"}
}