{
  "type": "Feature",
  "properties": {
    "iso:country":"US",
    "sg:address":"1064 Barstow Ave",
    "sg:city":"Clovis",
    "sg:classifiers":[
        {
            "category":"Building & Trades",
            "subcategory":"Plumbing",
            "type":"Services"
        }
    ],
    "sg:phone":"+1 559 299 2529",
    "sg:postcode":"93612",
    "sg:province":"CA",
    "sg:tags":[
        "plumbing",
        "contractor"
    ],
    "wof:name":"Pinnacle Plumbing Inc",
    "wof:placetype":"venue"
},
  "geometry": {"coordinates":[-119.697247,36.815698],"type":"Point"}
}