{
  "type": "Feature",
  "properties": {
    "addr:full":"1175 Elko Dr Sunnyvale CA 94089",
    "addr:housenumber":"1175",
    "addr:postcode":"94089",
    "addr:street":"Elko Dr",
    "iso:country":"US",
    "sg:address":"1175 Elko Dr",
    "sg:city":"Sunnyvale",
    "sg:classifiers":[
        {
            "category":"Manufacturing",
            "subcategory":"Electronics",
            "type":"Manufacturing & Wholesale Goods"
        }
    ],
    "sg:phone":"+1 408 747 0550",
    "sg:postcode":"94089",
    "sg:province":"CA",
    "sg:tags":[
        "equipment",
        "electronic",
        "supply"
    ],
    "sg:website":"www.idec.com",
    "wof:name":"IDEC Corp",
    "wof:placetype":"venue"
},
  "geometry": {"coordinates":[-121.993082,37.406434],"type":"Point"}
}