{
  "type": "Feature",
  "properties": {
    "addr:full":"234 Carroll St Sunnyvale CA 94086",
    "addr:housenumber":"234",
    "addr:postcode":"94086",
    "addr:street":"Carroll St",
    "iso:country":"US",
    "sg:address":"234 Carroll St",
    "sg:city":"Sunnyvale",
    "sg:classifiers":[
        {
            "category":"Utilities",
            "type":"Services"
        }
    ],
    "sg:phone":"+1 408 980 0090",
    "sg:postcode":"94086",
    "sg:province":"CA",
    "sg:tags":[
        "provider",
        "internet"
    ],
    "sg:website":"www.quantum.com",
    "wof:name":"Quantum Intelligence",
    "wof:placetype":"venue"
},
  "geometry": {"coordinates":[-122.028037,37.374633],"type":"Point"}
}