{
  "type": "Feature",
  "properties": {
    "iso:country":"US",
    "sg:address":"26393 Riverside Pl",
    "sg:city":"Carmel",
    "sg:classifiers":[
        {
            "category":"Professional",
            "type":"Services"
        }
    ],
    "sg:phone":"+1 831 625 0376",
    "sg:postcode":"93923",
    "sg:province":"CA",
    "wof:name":"Pacific Miwa Corp",
    "wof:placetype":"venue"
},
  "geometry": {"coordinates":[-121.916854,36.540561],"type":"Point"}
}