{
  "type": "Feature",
  "properties": {
    "iso:country":"US",
    "sg:address":"5l Serramonte Ctr",
    "sg:city":"Daly City",
    "sg:classifiers":[
        {
            "category":"Restaurant",
            "type":"Food & Drink"
        }
    ],
    "sg:menulink":"http://www.allmenus.com/ca/south-san-francisco/214204-taco-bell/menu/",
    "sg:phone":"+1 650 991 7431",
    "sg:postcode":"94015",
    "sg:province":"CA",
    "sg:tags":[
        "mexican"
    ],
    "wof:name":"Taco Bell",
    "wof:placetype":"venue"
},
  "geometry": {"coordinates":[-122.470719,37.674019],"type":"Point"}
}