{
  "type": "Feature",
  "properties": {
    "iso:country":"US",
    "sg:address":"20841 Prairie St",
    "sg:city":"Chatsworth",
    "sg:classifiers":[
        {
            "category":"Shopping",
            "subcategory":"Computers & Home Electronics",
            "type":"Retail Goods"
        }
    ],
    "sg:phone":"+1 818 341 4488",
    "sg:postcode":"91311",
    "sg:province":"CA",
    "sg:tags":[
        "high",
        "fidelity",
        "stereophonic"
    ],
    "wof:name":"Anthony Gallo Acoustics",
    "wof:placetype":"venue"
},
  "geometry": {"coordinates":[-118.587802,34.240981],"type":"Point"}
}