{
  "type": "Feature",
  "properties": {
    "iso:country":"US",
    "sg:address":"424 N Quarantina St",
    "sg:city":"Santa Barbara",
    "sg:classifiers":[
        {
            "category":"Retail",
            "subcategory":"Auto Repair",
            "type":"Services"
        }
    ],
    "sg:phone":"+1 805 962 1613",
    "sg:postcode":"93103",
    "sg:province":"CA",
    "sg:tags":[
        "repairing",
        "automobile"
    ],
    "wof:name":"Muller & Goss",
    "wof:placetype":"venue"
},
  "geometry": {"coordinates":[-119.68644,34.423382],"type":"Point"}
}