{
  "type": "Feature",
  "properties": {
    "iso:country":"US",
    "sg:address":"3122 Kashiwa St",
    "sg:city":"Torrance",
    "sg:classifiers":[
        {
            "category":"Manufacturing",
            "subcategory":"Tools & Machinery",
            "type":"Manufacturing & Wholesale Goods"
        }
    ],
    "sg:phone":"+1 310 530 1093",
    "sg:postcode":"90505",
    "sg:province":"CA",
    "sg:tags":[
        "machine",
        "shop"
    ],
    "wof:name":"Tri Models",
    "wof:placetype":"venue"
},
  "geometry": {"coordinates":[-118.342316,33.816112],"type":"Point"}
}