{
  "type": "Feature",
  "properties": {
    "addr:full":"3260 Santa Rosa Ave Santa Rosa CA 95407",
    "addr:housenumber":"3260",
    "addr:postcode":"95407",
    "addr:street":"Santa Rosa Ave",
    "iso:country":"US",
    "sg:address":"3260 Santa Rosa Ave",
    "sg:city":"Santa Rosa",
    "sg:classifiers":[
        {
            "category":"Autos & Motor Vehicles",
            "subcategory":"Auto Supplies",
            "type":"Retail Goods"
        }
    ],
    "sg:phone":"+1 707 578 1115",
    "sg:postcode":"95407",
    "sg:province":"CA",
    "sg:tags":[
        "automobile",
        "parts"
    ],
    "sg:website":"www.papolaoffroad.com",
    "wof:name":"Papola Off Road",
    "wof:placetype":"venue"
},
  "geometry": {"coordinates":[-122.713408,38.40032],"type":"Point"}
}