{
  "type": "Feature",
  "properties": {
    "addr:full":"16988 S Harlan Rd Lathrop CA 95330",
    "addr:housenumber":"16988",
    "addr:postcode":"95330",
    "addr:street":"S Harlan Rd",
    "iso:country":"US",
    "sg:address":"16988 S Harlan Rd",
    "sg:city":"Lathrop",
    "sg:classifiers":[
        {
            "category":"Shopping",
            "subcategory":"Computers & Home Electronics",
            "type":"Retail Goods"
        }
    ],
    "sg:phone":"+1 209 858 1776",
    "sg:postcode":"95330",
    "sg:province":"CA",
    "sg:tags":[
        "software"
    ],
    "sg:website":"www.extendag.com",
    "wof:name":"John Deere Food Origins",
    "wof:placetype":"venue"
},
  "geometry": {"coordinates":[-121.296463,37.807254],"type":"Point"}
}