{
  "type": "Feature",
  "properties": {
    "addr:full":"2511 W Via Palma Anaheim CA 92801",
    "addr:housenumber":"2511",
    "addr:postcode":"92801",
    "addr:street":"W Via Palma",
    "iso:country":"US",
    "sg:address":"2511 W Via Palma",
    "sg:city":"Anaheim",
    "sg:classifiers":[
        {
            "category":"Manufacturing",
            "subcategory":"Tools & Machinery",
            "type":"Manufacturing & Wholesale Goods"
        }
    ],
    "sg:phone":"+1 714 821 3336",
    "sg:postcode":"92801",
    "sg:province":"CA",
    "sg:tags":[
        "machine",
        "industrial",
        "mfg"
    ],
    "wof:name":"C V Engineering",
    "wof:placetype":"venue"
},
  "geometry": {"coordinates":[-117.975842,33.847943],"type":"Point"}
}