{
  "type": "Feature",
  "properties": {
    "addr:full":"3001 Bayshore Rd Benicia CA 94510",
    "addr:housenumber":"3001",
    "addr:postcode":"94510",
    "addr:street":"Bayshore Rd",
    "iso:country":"US",
    "sg:address":"3001 Bayshore Rd",
    "sg:city":"Benicia",
    "sg:classifiers":[
        {
            "category":"Professional",
            "subcategory":"Detective & Security Services",
            "type":"Services"
        }
    ],
    "sg:phone":"+1 707 745 1922",
    "sg:postcode":"94510",
    "sg:province":"CA",
    "sg:tags":[
        "investigator"
    ],
    "wof:name":"Patten Investigations",
    "wof:placetype":"venue"
},
  "geometry": {"coordinates":[-122.12821099999999,38.061102],"type":"Point"}
}