{
  "type": "Feature",
  "properties": {
    "iso:country":"US",
    "sg:address":"2127 Colorado Blvd",
    "sg:city":"Los Angeles",
    "sg:classifiers":[
        {
            "category":"Wholesale",
            "subcategory":"Scrap",
            "type":"Manufacturing & Wholesale Goods"
        }
    ],
    "sg:phone":"+1 323 254 4814",
    "sg:postcode":"90041",
    "sg:province":"CA",
    "sg:tags":[
        "salvage",
        "surplus",
        "merchandise"
    ],
    "wof:name":"L A Army Navy Supply",
    "wof:placetype":"venue"
},
  "geometry": {"coordinates":[-118.212118,34.13933],"type":"Point"}
}