{
  "type": "Feature",
  "properties": {
    "addr:full":"629 Trancas St Napa CA 94558",
    "addr:housenumber":"629",
    "addr:postcode":"94558",
    "addr:street":"Trancas St",
    "iso:country":"US",
    "sg:address":"629 Trancas St",
    "sg:city":"Napa",
    "sg:classifiers":[
        {
            "category":"Retail",
            "subcategory":"Laundry & Dry Cleaning",
            "type":"Services"
        }
    ],
    "sg:phone":"+1 707 224 2060",
    "sg:postcode":"94558",
    "sg:province":"CA",
    "sg:tags":[
        "cleaners"
    ],
    "wof:name":"Country Club Cleaners",
    "wof:placetype":"venue"
},
  "geometry": {"coordinates":[-122.287852,38.324743],"type":"Point"}
}