{
  "type": "Feature",
  "properties": {
    "iso:country":"US",
    "sg:address":"4912 Fountain Avenue",
    "sg:city":"Los Angeles",
    "sg:classifiers":[
        {
            "category":"Shopping",
            "subcategory":"Tobacco",
            "type":"Retail Goods"
        }
    ],
    "sg:phone":"+1 323 669 1537",
    "sg:postcode":"90029",
    "sg:province":"CA",
    "sg:tags":[
        "shop"
    ],
    "wof:name":"Sal's Tobacco",
    "wof:placetype":"venue"
},
  "geometry": {"coordinates":[-118.2968,34.095475],"type":"Point"}
}