{
  "type": "Feature",
  "properties": {
    "iso:country":"US",
    "sg:address":"20370 Town Center Lane  Suite 208",
    "sg:city":"Cupertino",
    "sg:classifiers":[
        {
            "category":"Professional",
            "subcategory":"Computer Services",
            "type":"Services"
        }
    ],
    "sg:phone":"+1 866 240 2812",
    "sg:postcode":"95014 ",
    "sg:province":"CA",
    "sg:website":"http://www.sli-systems.com",
    "wof:name":"SLI Systems",
    "wof:placetype":"venue"
},
  "geometry": {"coordinates":[-122.02945200000001,37.318468],"type":"Point"}
}