{
  "type": "Feature",
  "properties": {
    "iso:country":"US",
    "sg:address":"229 N Central Ave Ste 103",
    "sg:city":"Glendale",
    "sg:classifiers":[
        {
            "category":"Health Services",
            "subcategory":"Doctor",
            "type":"Services"
        }
    ],
    "sg:phone":"+1 323 245 1155",
    "sg:postcode":"91203",
    "sg:province":"CA",
    "sg:tags":[
        "podiatrist"
    ],
    "sg:website":"www.drfindel.com",
    "wof:name":"Findel Murray J DPM",
    "wof:placetype":"venue"
},
  "geometry": {"coordinates":[-118.258003,34.148998],"type":"Point"}
}