{
  "type": "Feature",
  "properties": {
    "iso:country":"US",
    "sg:address":"1202 E Walnut St",
    "sg:city":"Santa Ana",
    "sg:classifiers":[
        {
            "category":"Building & Trades",
            "subcategory":"Construction",
            "type":"Services"
        }
    ],
    "sg:phone":"+1 714 558 2410",
    "sg:postcode":"92701",
    "sg:province":"CA",
    "sg:tags":[
        "sewer",
        "contractor"
    ],
    "wof:name":"Diana Fashions",
    "wof:placetype":"venue"
},
  "geometry": {"coordinates":[-117.852763,33.744356],"type":"Point"}
}