{
  "type": "Feature",
  "properties": {
    "addr:full":"3732 W Century Blvd Inglewood CA 90303",
    "addr:housenumber":"3732",
    "addr:postcode":"90303",
    "addr:street":"W Century Blvd",
    "iso:country":"US",
    "sg:address":"3732 W Century Blvd",
    "sg:city":"Inglewood",
    "sg:phone":"+1 310 671 8880",
    "sg:postcode":"90303",
    "sg:province":"CA",
    "wof:name":"Mega Pacific",
    "wof:placetype":"venue"
},
  "geometry": {"coordinates":[-118.339806,33.945461],"type":"Point"}
}