{
  "type": "Feature",
  "properties": {
    "iso:country":"US",
    "sg:address":"66700 Pierson Blvd",
    "sg:city":"Desert Hot Spgs",
    "sg:classifiers":[
        {
            "category":"Organizations",
            "subcategory":"Non-profit Organization",
            "type":"Services"
        }
    ],
    "sg:phone":"+1 760 251 8482",
    "sg:postcode":"92240",
    "sg:province":"CA",
    "sg:tags":[
        "charitable",
        "institution"
    ],
    "wof:name":"Catholic Charities",
    "wof:placetype":"venue"
},
  "geometry": {"coordinates":[-116.49796600000001,33.961547],"type":"Point"}
}