{
  "type": "Feature",
  "properties": {
    "addr:full":"16306 Blanco St San Leandro CA 94578",
    "addr:housenumber":"16306",
    "addr:postcode":"94578",
    "addr:street":"Blanco St",
    "iso:country":"US",
    "sg:address":"16306 Blanco St",
    "sg:city":"San Leandro",
    "sg:classifiers":[
        {
            "category":"Professional",
            "type":"Services"
        }
    ],
    "sg:phone":"+1 510 317 8519",
    "sg:postcode":"94578",
    "sg:province":"CA",
    "sg:tags":[
        "establishment"
    ],
    "wof:name":"Y & S Assoc",
    "wof:placetype":"venue"
},
  "geometry": {"coordinates":[-122.112813,37.695611],"type":"Point"}
}