{
  "type": "Feature",
  "properties": {
    "addr:full":"193 Culver Blvd Playa Del Rey CA 90293",
    "addr:housenumber":"193",
    "addr:postcode":"90293",
    "addr:street":"Culver Blvd",
    "iso:country":"US",
    "sg:address":"193 Culver Blvd",
    "sg:city":"Playa Del Rey",
    "sg:classifiers":[
        {
            "category":"Restaurant",
            "type":"Food & Drink"
        }
    ],
    "sg:phone":"+1 310 821 0018",
    "sg:postcode":"90293",
    "sg:province":"CA",
    "sg:tags":[
        "pizza",
        "italian"
    ],
    "sg:website":"www.salernobeach.com",
    "wof:name":"Cantalini's Salerno Beach Restaurant",
    "wof:placetype":"venue"
},
  "geometry": {"coordinates":[-118.448533,33.958789],"type":"Point"}
}