{
  "type": "Feature",
  "properties": {
    "addr:full":"301 Madre St Pasadena CA 91107",
    "addr:housenumber":"301",
    "addr:postcode":"91107",
    "addr:street":"Madre St",
    "iso:country":"US",
    "sg:address":"301 Madre St",
    "sg:city":"Pasadena",
    "sg:classifiers":[
        {
            "category":"Education",
            "subcategory":"School",
            "type":"Public Place"
        }
    ],
    "sg:phone":"+1 626 793 6163",
    "sg:postcode":"91107",
    "sg:province":"CA",
    "sg:tags":[
        "high",
        "middle",
        "elementary"
    ],
    "sg:website":"www.pasadena.k12.ca.us",
    "wof:name":"Willard Elementary School",
    "wof:placetype":"venue"
},
  "geometry": {"coordinates":[-118.081001,34.1418],"type":"Point"}
}