{
  "type": "Feature",
  "properties": {
    "addr:full":"7633 Paramount Blvd Pico Rivera CA 90660",
    "addr:housenumber":"7633",
    "addr:postcode":"90660",
    "addr:street":"Paramount Blvd",
    "iso:country":"US",
    "sg:address":"7633 Paramount Blvd",
    "sg:city":"Pico Rivera",
    "sg:classifiers":[
        {
            "category":"Manufacturing",
            "subcategory":"Furniture",
            "type":"Manufacturing & Wholesale Goods"
        }
    ],
    "sg:phone":"+1 562 949 1088",
    "sg:postcode":"90660",
    "sg:province":"CA",
    "sg:tags":[
        "mfg"
    ],
    "wof:name":"Golden Mattress Co",
    "wof:placetype":"venue"
},
  "geometry": {"coordinates":[-118.110618,33.977986],"type":"Point"}
}