{
  "type": "Feature",
  "properties": {
    "addr:full":"910 Cinnabar St San Jose CA 95126",
    "addr:housenumber":"910",
    "addr:postcode":"95126",
    "addr:street":"Cinnabar St",
    "iso:country":"US",
    "sg:address":"910 Cinnabar St",
    "sg:city":"San Jose",
    "sg:classifiers":[
        {
            "category":"Health Services",
            "subcategory":"Clinic",
            "type":"Services"
        },
        {
            "category":"Community Center",
            "type":"Public Place"
        }
    ],
    "sg:phone":"+1 408 295 0420",
    "sg:postcode":"95126",
    "sg:province":"CA",
    "sg:tags":[
        "cannabis",
        "medical"
    ],
    "sg:website":"www.cinnabarhealth.com/",
    "wof:name":"Cinnabar Health Collective",
    "wof:placetype":"venue"
},
  "geometry": {"coordinates":[-121.90938300000001,37.33437],"type":"Point"}
}