{
  "type": "Feature",
  "properties": {
    "iso:country":"US",
    "sg:address":"11602 Ventura Blvd.",
    "sg:city":"Los Angeles",
    "sg:classifiers":[
        {
            "category":"Education",
            "subcategory":"Special Training",
            "type":"Public Place"
        }
    ],
    "sg:phone":"+1 818 985 9357",
    "sg:postcode":"91604",
    "sg:province":"CA",
    "sg:tags":[
        "school",
        "art"
    ],
    "sg:website":"www.thevillageartproject.com",
    "wof:name":"The Village Art Project",
    "wof:placetype":"venue"
},
  "geometry": {"coordinates":[-118.38494300000001,34.140313],"type":"Point"}
}