{
  "type": "Feature",
  "properties": {
    "iso:country":"US",
    "sg:address":"701 Airport Blvd",
    "sg:city":"South San Francisco",
    "sg:classifiers":[
        {
            "category":"Travel",
            "subcategory":"Hotels & Motels",
            "type":"Entertainment"
        }
    ],
    "sg:phone":"+1 650 952 2505",
    "sg:postcode":"94080",
    "sg:province":"CA",
    "wof:name":"Hojo Inn by Howard Johnson",
    "wof:placetype":"venue"
},
  "geometry": {"coordinates":[-122.40300000000001,37.662102],"type":"Point"}
}