{
  "type": "Feature",
  "properties": {
    "iso:country":"US",
    "sg:address":"9464 Charleville Blvd",
    "sg:city":"Beverly Hills",
    "sg:classifiers":[
        {
            "category":"Food & Beverages",
            "subcategory":"Bakery",
            "type":"Retail Goods"
        }
    ],
    "sg:phone":"+1 310 860 9004",
    "sg:postcode":"90212",
    "sg:province":"CA",
    "sg:tags":[
        "sandwich"
    ],
    "sg:website":"www.thehoodcafe.com",
    "wof:name":"neighborHOOD Cafe",
    "wof:placetype":"venue"
},
  "geometry": {"coordinates":[-118.39919500000001,34.064972],"type":"Point"}
}