{
  "type": "Feature",
  "properties": {
    "addr:full":"14601 S Bascom Ave Los Gatos CA 95032",
    "addr:housenumber":"14601",
    "addr:postcode":"95032",
    "addr:street":"S Bascom Ave",
    "iso:country":"US",
    "sg:address":"14601 S Bascom Ave",
    "sg:city":"Los Gatos",
    "sg:classifiers":[
        {
            "category":"Health Services",
            "subcategory":"Doctor",
            "type":"Services"
        }
    ],
    "sg:phone":"+1 408 356 0464",
    "sg:postcode":"95032",
    "sg:province":"CA",
    "sg:tags":[
        "physician",
        "surgeon"
    ],
    "wof:name":"Ronald Joseph Inc",
    "wof:placetype":"venue"
},
  "geometry": {"coordinates":[-121.949521,37.256666],"type":"Point"}
}