{
  "type": "Feature",
  "properties": {
    "addr:full":"9253 Hermosa Ave Rancho Cucamonga CA 91730",
    "addr:housenumber":"9253",
    "addr:postcode":"91730",
    "addr:street":"Hermosa Ave",
    "iso:country":"US",
    "sg:address":"9253 Hermosa Ave",
    "sg:city":"Rancho Cucamonga",
    "sg:classifiers":[
        {
            "category":"Professional",
            "subcategory":"Printing & Photocopies",
            "type":"Services"
        }
    ],
    "sg:phone":"+1 909 941 0587",
    "sg:postcode":"91730",
    "sg:province":"CA",
    "sg:tags":[
        "blueprinting"
    ],
    "wof:name":"Mission Reprographics",
    "wof:placetype":"venue"
},
  "geometry": {"coordinates":[-117.58454,34.085682],"type":"Point"}
}