{
  "type": "Feature",
  "properties": {
    "iso:country":"US",
    "sg:address":"2744 Aiello Dr",
    "sg:city":"San Jose",
    "sg:classifiers":[
        {
            "category":"Personal",
            "type":"Services"
        }
    ],
    "sg:phone":"+1 408 839 7233",
    "sg:postcode":"95109",
    "sg:province":"CA",
    "sg:tags":[
        "mover"
    ],
    "sg:website":"www.allsafemove.com",
    "wof:name":"All Safe Move Inc.",
    "wof:placetype":"venue"
},
  "geometry": {"coordinates":[-121.847595,37.29484],"type":"Point"}
}