{
  "type": "Feature",
  "properties": {
    "addr:full":"19 37th Ave San Mateo CA 94403",
    "addr:housenumber":"19",
    "addr:postcode":"94403",
    "addr:street":"37Th Ave",
    "iso:country":"US",
    "sg:address":"19 37th Ave",
    "sg:city":"San Mateo",
    "sg:classifiers":[
        {
            "category":"Personal",
            "subcategory":"Barber",
            "type":"Services"
        }
    ],
    "sg:phone":"+1 650 341 4647",
    "sg:postcode":"94403",
    "sg:province":"CA",
    "wof:name":"Star Image",
    "wof:placetype":"venue"
},
  "geometry": {"coordinates":[-122.29602199999999,37.533706],"type":"Point"}
}