{
  "type": "Feature",
  "properties": {
    "iso:country":"US",
    "sg:address":"2243 Barry Avenue",
    "sg:city":"Los Angeles",
    "sg:classifiers":[
        {
            "category":"Building & Trades",
            "subcategory":"Landscaping Services",
            "type":"Services"
        }
    ],
    "sg:phone":"+1 310 473 7705",
    "sg:postcode":"90064",
    "sg:province":"CA",
    "sg:tags":[
        "tree"
    ],
    "wof:name":"Newhouse Tree Serv",
    "wof:placetype":"venue"
},
  "geometry": {"coordinates":[-118.445933,34.033896],"type":"Point"}
}