{
  "type": "Feature",
  "properties": {
    "iso:country":"US",
    "sg:address":"18505 Linnet St",
    "sg:city":"Tarzana",
    "sg:classifiers":[
        {
            "category":"Wholesale",
            "subcategory":"Apparel",
            "type":"Manufacturing & Wholesale Goods"
        }
    ],
    "sg:phone":"+1 818 705 8376",
    "sg:postcode":"91356",
    "sg:province":"CA",
    "sg:tags":[
        "piece"
    ],
    "wof:name":"Manila Textiles",
    "wof:placetype":"venue"
},
  "geometry": {"coordinates":[-118.537375,34.165805],"type":"Point"}
}