{
  "type": "Feature",
  "properties": {
    "iso:country":"US",
    "sg:address":"2363 Van Ness Ave Apt 401",
    "sg:city":"San Francisco",
    "sg:classifiers":[
        {
            "category":"Professional",
            "subcategory":"Computer Services",
            "type":"Services"
        }
    ],
    "sg:phone":"+1 415 861 6800",
    "sg:postcode":"94109",
    "sg:province":"CA",
    "sg:tags":[
        "repair"
    ],
    "wof:name":"Kasman Squillante LLC",
    "wof:placetype":"venue"
},
  "geometry": {"coordinates":[-122.42396100000001,37.797241],"type":"Point"}
}