{
  "type": "Feature",
  "properties": {
    "iso:country":"US",
    "sg:address":"15708 Golden Star Ave",
    "sg:city":"Riverside",
    "sg:classifiers":[
        {
            "category":"Personal",
            "subcategory":"Beauty Salon",
            "type":"Services"
        }
    ],
    "sg:phone":"+1 951 347 4253",
    "sg:postcode":"92506",
    "sg:province":"CA",
    "wof:name":"Styles By Vonny",
    "wof:placetype":"venue"
},
  "geometry": {"coordinates":[-117.36871600000001,33.891548],"type":"Point"}
}