{
  "type": "Feature",
  "properties": {
    "addr:full":"35126 Yucaipa Blvd. Yucaipa CA 92399",
    "addr:postcode":"35126;92399",
    "addr:street":"Yucaipa Blvd.",
    "iso:country":"US",
    "sg:address":"35126 Yucaipa Blvd.",
    "sg:city":"Yucaipa",
    "sg:classifiers":[
        {
            "category":"Autos & Motor Vehicles",
            "subcategory":"Automobile Sales",
            "type":"Retail Goods"
        }
    ],
    "sg:phone":"+1 909 790 0015",
    "sg:postcode":"92399",
    "sg:province":"CA",
    "sg:tags":[
        "automotive"
    ],
    "sg:website":"www.oilcanhenrys.com",
    "wof:name":"Oil Can Henry's",
    "wof:placetype":"venue"
},
  "geometry": {"coordinates":[-117.038313,34.033898],"type":"Point"}
}