{
  "type": "Feature",
  "properties": {
    "addr:full":"206 N Jackson St Glendale CA 91206",
    "addr:housenumber":"206",
    "addr:postcode":"91206",
    "addr:street":"N Jackson St",
    "iso:country":"US",
    "sg:address":"206 N Jackson St",
    "sg:city":"Glendale",
    "sg:classifiers":[
        {
            "category":"Health Services",
            "subcategory":"Doctor",
            "type":"Services"
        }
    ],
    "sg:phone":"+1 818 846 5526",
    "sg:postcode":"91206",
    "sg:province":"CA",
    "sg:tags":[
        "dentist"
    ],
    "wof:name":"Nishan Matossian DDS",
    "wof:placetype":"venue"
},
  "geometry": {"coordinates":[-118.25003,34.149191],"type":"Point"}
}