{
  "type": "Feature",
  "properties": {
    "iso:country":"US",
    "sg:address":"953 N Citrus Ave",
    "sg:city":"Covina",
    "sg:classifiers":[
        {
            "category":"Autos & Motor Vehicles",
            "subcategory":"Automobile Sales",
            "type":"Retail Goods"
        }
    ],
    "sg:phone":"+1 626 966 3858",
    "sg:postcode":"91722",
    "sg:province":"CA",
    "sg:tags":[
        "car",
        "dealer"
    ],
    "wof:name":"California Motor Cars",
    "wof:placetype":"venue"
},
  "geometry": {"coordinates":[-117.890266,34.096381],"type":"Point"}
}