{
  "type": "Feature",
  "properties": {
    "addr:full":"23342 Valencia Blvd Valencia CA 91355",
    "addr:housenumber":"23342",
    "addr:postcode":"91355",
    "addr:street":"Valencia Blvd",
    "iso:country":"US",
    "sg:address":"23342 Valencia Blvd",
    "sg:city":"Valencia",
    "sg:classifiers":[
        {
            "category":"Food & Beverages",
            "subcategory":"Groceries & Convenience Stores",
            "type":"Retail Goods"
        }
    ],
    "sg:phone":"+1 661 254 6874",
    "sg:postcode":"91355",
    "sg:province":"CA",
    "sg:website":"www.7-eleven.com/",
    "wof:name":"7-Eleven",
    "wof:placetype":"venue"
},
  "geometry": {"coordinates":[-118.54664200000001,34.421933],"type":"Point"}
}