{
  "type": "Feature",
  "properties": {
    "iso:country":"US",
    "sg:address":"5550 E Atherton St",
    "sg:city":"Long Beach",
    "sg:classifiers":[
        {
            "category":"Education",
            "subcategory":"Preschool",
            "type":"Public Place"
        },
        {
            "category":"Organizations",
            "subcategory":"Religious Organization",
            "type":"Services"
        }
    ],
    "sg:phone":"+1 562 596 2108",
    "sg:postcode":"90815",
    "sg:province":"CA",
    "sg:website":"www.discoverylaucc.com",
    "wof:name":"Discovery Preschool at LAUCC",
    "wof:placetype":"venue"
},
  "geometry": {"coordinates":[-118.123001,33.788502],"type":"Point"}
}