{
  "type": "Feature",
  "properties": {
    "addr:full":"1239 Myrtle Ave San Diego CA 92103",
    "addr:housenumber":"1239",
    "addr:postcode":"92103",
    "addr:street":"Myrtle Ave",
    "iso:country":"US",
    "sg:address":"1239 Myrtle Ave",
    "sg:city":"San Diego",
    "sg:classifiers":[
        {
            "category":"Shopping",
            "subcategory":"Computers & Home Electronics",
            "type":"Retail Goods"
        }
    ],
    "sg:phone":"+1 619 298 9349",
    "sg:postcode":"92103",
    "sg:province":"CA",
    "sg:tags":[
        "software"
    ],
    "sg:website":"www.goldenbow.com",
    "wof:name":"Golden Bow Systems",
    "wof:placetype":"venue"
},
  "geometry": {"coordinates":[-117.15154099999999,32.742169],"type":"Point"}
}