{
  "type": "Feature",
  "properties": {
    "addr:full":"12201 Skyline Blvd Oakland CA 94619",
    "addr:housenumber":"12201",
    "addr:postcode":"94619",
    "addr:street":"Skyline Blvd",
    "iso:country":"US",
    "sg:address":"12201 Skyline Blvd",
    "sg:city":"Oakland",
    "sg:classifiers":[
        {
            "category":"Retail",
            "subcategory":"Repair Shop",
            "type":"Services"
        }
    ],
    "sg:phone":"+1 510 531 2388",
    "sg:postcode":"94619",
    "sg:province":"CA",
    "sg:tags":[
        "lock",
        "locksmith"
    ],
    "wof:name":"Roland's Locksmithing",
    "wof:placetype":"venue"
},
  "geometry": {"coordinates":[-122.170068,37.79886],"type":"Point"}
}