{
  "type": "Feature",
  "properties": {
    "iso:country":"US",
    "sg:address":"16224 Garfield Ave",
    "sg:city":"Paramount",
    "sg:classifiers":[
        {
            "category":"Retail",
            "subcategory":"Auto Repair",
            "type":"Services"
        }
    ],
    "sg:phone":"+1 562 633 2660",
    "sg:postcode":"90723",
    "sg:province":"CA",
    "sg:tags":[
        "repairing",
        "automobile"
    ],
    "wof:name":"Vaughan's Industrial Repair",
    "wof:placetype":"venue"
},
  "geometry": {"coordinates":[-118.168656,33.886648],"type":"Point"}
}