{
  "type": "Feature",
  "properties": {
    "addr:full":"3502 24th St San Francisco CA 94110",
    "addr:housenumber":"3502",
    "addr:postcode":"94110",
    "addr:street":"24Th St",
    "iso:country":"US",
    "sg:address":"3502 24th St",
    "sg:city":"San Francisco",
    "sg:classifiers":[
        {
            "category":"Professional",
            "type":"Services"
        }
    ],
    "sg:phone":"+1 415 474 0222",
    "sg:postcode":"94110",
    "sg:province":"CA",
    "wof:name":"Unwirenow Inc",
    "wof:placetype":"venue"
},
  "geometry": {"coordinates":[-122.422864,37.752047],"type":"Point"}
}