{
  "type": "Feature",
  "properties": {
    "iso:country":"US",
    "sg:address":"2171 S el Camino Real",
    "sg:city":"Oceanside",
    "sg:classifiers":[
        {
            "category":"Banks & Credit Unions",
            "subcategory":"Bank",
            "type":"Services"
        }
    ],
    "sg:phone":"+1 760 231 7839",
    "sg:postcode":"92054",
    "sg:province":"CA",
    "sg:tags":[
        "loan",
        "real estate"
    ],
    "wof:name":"Marvel Realty & Mortgage",
    "wof:placetype":"venue"
},
  "geometry": {"coordinates":[-117.328255,33.189697],"type":"Point"}
}