{
  "type": "Feature",
  "properties": {
    "iso:country":"US",
    "sg:address":"473 Front St",
    "sg:city":"Salinas",
    "sg:classifiers":[
        {
            "category":"Health Services",
            "subcategory":"Clinic",
            "type":"Services"
        }
    ],
    "sg:phone":"+1 831 422 8700",
    "sg:postcode":"93901",
    "sg:province":"CA",
    "wof:name":"Health Sensation Inc",
    "wof:placetype":"venue"
},
  "geometry": {"coordinates":[-121.648443,36.669639],"type":"Point"}
}