{
  "type": "Feature",
  "properties": {
    "iso:country":"US",
    "sg:address":"18727 Soledad Canyon Rd",
    "sg:city":"Santa Clarita",
    "sg:classifiers":[
        {
            "category":"Retail",
            "subcategory":"Car Wash",
            "type":"Services"
        }
    ],
    "sg:phone":"+1 661 250 0399",
    "sg:postcode":"91351",
    "sg:province":"CA",
    "wof:name":"Canyon Car Wash",
    "wof:placetype":"venue"
},
  "geometry": {"coordinates":[-118.46191399999999,34.416105],"type":"Point"}
}