{
  "type": "Feature",
  "properties": {
    "addr:full":"2330 Vehicle Dr Rancho Cordova CA 95670",
    "addr:postcode":"2330;95670",
    "addr:street":"Vehicle Dr",
    "iso:country":"US",
    "sg:address":"2330 Vehicle Dr",
    "sg:city":"Rancho Cordova",
    "sg:classifiers":[
        {
            "category":"Professional",
            "type":"Services"
        }
    ],
    "sg:phone":"+1 916 501 1045",
    "sg:postcode":"95670",
    "sg:province":"CA",
    "wof:name":"Mobile Notary Biz",
    "wof:placetype":"venue"
},
  "geometry": {"coordinates":[-121.273183,38.614409],"type":"Point"}
}