{
  "type": "Feature",
  "properties": {
    "iso:country":"US",
    "sg:address":"616 N 20th St",
    "sg:city":"Montebello",
    "sg:classifiers":[
        {
            "category":"Shopping",
            "subcategory":"Florist",
            "type":"Retail Goods"
        }
    ],
    "sg:phone":"+1 323 721 3606",
    "sg:postcode":"90640",
    "sg:province":"CA",
    "wof:name":"Beverly Flowers",
    "wof:placetype":"venue"
},
  "geometry": {"coordinates":[-118.119161,34.023401],"type":"Point"}
}