{
  "type": "Feature",
  "properties": {
    "iso:country":"US",
    "sg:address":"821 S Maple Ave",
    "sg:city":"Montebello",
    "sg:classifiers":[
        {
            "category":"Personal",
            "type":"Services"
        }
    ],
    "sg:phone":"+1 323 726 3232",
    "sg:postcode":"90640",
    "sg:province":"CA",
    "sg:tags":[
        "towing"
    ],
    "wof:name":"Petra Towing Services",
    "wof:placetype":"venue"
},
  "geometry": {"coordinates":[-118.121002,34.000599],"type":"Point"}
}