{
  "type": "Feature",
  "properties": {
    "iso:country":"US",
    "sg:address":"1379 Donna St",
    "sg:city":"Novato",
    "sg:classifiers":[
        {
            "category":"Professional",
            "type":"Services"
        }
    ],
    "sg:phone":"+1 415 897 1394",
    "sg:postcode":"94947",
    "sg:province":"CA",
    "wof:name":"Pat Pidge",
    "wof:placetype":"venue"
},
  "geometry": {"coordinates":[-122.56410200000001,38.088935],"type":"Point"}
}