{
  "type": "Feature",
  "properties": {
    "iso:country":"US",
    "sg:address":"2644 S Desert Forest Ave",
    "sg:city":"Ontario",
    "sg:classifiers":[
        {
            "category":"Freight",
            "type":"Transportation"
        }
    ],
    "sg:phone":"+1 909 917 1806",
    "sg:postcode":"91761",
    "sg:province":"CA",
    "sg:tags":[
        "delivery"
    ],
    "wof:name":"Swift Delivery Svc",
    "wof:placetype":"venue"
},
  "geometry": {"coordinates":[-117.58959400000001,34.023626],"type":"Point"}
}