{
  "type": "Feature",
  "properties": {
    "addr:full":"10769 Woodside Ave Santee CA 92071",
    "addr:housenumber":"10769",
    "addr:postcode":"92071",
    "addr:street":"Woodside Ave",
    "iso:country":"US",
    "sg:address":"10769 Woodside Ave",
    "sg:city":"Santee",
    "sg:classifiers":[
        {
            "category":"Insurance",
            "subcategory":"Insurance Agent",
            "type":"Services"
        }
    ],
    "sg:phone":"+1 619 631 8588",
    "sg:postcode":"92071",
    "sg:province":"CA",
    "wof:name":"Jasak Agency",
    "wof:placetype":"venue"
},
  "geometry": {"coordinates":[-116.96314,32.840992],"type":"Point"}
}