{
  "type": "Feature",
  "properties": {
    "iso:country":"US",
    "sg:address":"77899 Wolf Rd",
    "sg:city":"Palm Desert",
    "sg:classifiers":[
        {
            "category":"Wholesale",
            "subcategory":"Computers",
            "type":"Manufacturing & Wholesale Goods"
        }
    ],
    "sg:phone":"+1 760 360 9561",
    "sg:postcode":"92211",
    "sg:province":"CA",
    "sg:tags":[
        "communications",
        "datum"
    ],
    "wof:name":"Lomac Information Systems",
    "wof:placetype":"venue"
},
  "geometry": {"coordinates":[-116.305958,33.764119],"type":"Point"}
}