{
  "type": "Feature",
  "properties": {
    "iso:country":"US",
    "sg:address":"8295 Bradshaw Rd",
    "sg:city":"Sacramento",
    "sg:classifiers":[
        {
            "category":"Retail",
            "subcategory":"Auto Repair",
            "type":"Services"
        }
    ],
    "sg:phone":"+1 916 688 9797",
    "sg:postcode":"95829",
    "sg:province":"CA",
    "sg:tags":[
        "scooters-repairing",
        "motorcycle",
        "motor"
    ],
    "wof:name":"Olray Motorcycle And Tennis Co",
    "wof:placetype":"venue"
},
  "geometry": {"coordinates":[-121.33474699999999,38.457169],"type":"Point"}
}