{
  "type": "Feature",
  "properties": {
    "addr:full":"5110 Fairhill Ct Oakland CA 94605",
    "addr:housenumber":"5110",
    "addr:postcode":"94605",
    "addr:street":"Fairhill Ct",
    "iso:country":"US",
    "sg:address":"5110 Fairhill Ct",
    "sg:city":"Oakland",
    "sg:classifiers":[
        {
            "category":"Utilities",
            "subcategory":"Natural Gas",
            "type":"Services"
        }
    ],
    "sg:phone":"+1 510 569 4140",
    "sg:postcode":"94605",
    "sg:province":"CA",
    "sg:tags":[
        "transmission"
    ],
    "wof:name":"Williams Companies Inc",
    "wof:placetype":"venue"
},
  "geometry": {"coordinates":[-122.148499,37.774435],"type":"Point"}
}