{
  "type": "Feature",
  "properties": {
    "iso:country":"US",
    "sg:address":"6590 Commerce Blvd",
    "sg:city":"Rohnert Park",
    "sg:classifiers":[
        {
            "category":"Shopping",
            "type":"Retail Goods"
        }
    ],
    "sg:phone":"+1 707 588 8050",
    "sg:postcode":"94928",
    "sg:province":"CA",
    "sg:tags":[
        "spa",
        "hot",
        "tub"
    ],
    "wof:name":"Hot Tub Store",
    "wof:placetype":"venue"
},
  "geometry": {"coordinates":[-122.711912,38.344763],"type":"Point"}
}