{
  "type": "Feature",
  "properties": {
    "iso:country":"US",
    "sg:address":"333 H St Ste 6000",
    "sg:city":"Chula Vista",
    "sg:classifiers":[
        {
            "category":"Real Estate",
            "subcategory":"Real Estate Services",
            "type":"Services"
        }
    ],
    "sg:phone":"+1 619 422 1493",
    "sg:postcode":"91910",
    "sg:province":"CA",
    "wof:name":"Mountain West Real Estate",
    "wof:placetype":"venue"
},
  "geometry": {"coordinates":[-117.078558,32.634023],"type":"Point"}
}