{
  "type": "Feature",
  "properties": {
    "iso:country":"US",
    "sg:address":"229 Clark Ave",
    "sg:city":"Yuba City",
    "sg:classifiers":[
        {
            "category":"Shopping",
            "subcategory":"Clothing, Apparel, & Fashions",
            "type":"Retail Goods"
        }
    ],
    "sg:phone":"+1 530 755 4282",
    "sg:postcode":"95991",
    "sg:province":"CA",
    "wof:name":"Always Elegant Bridal & Formal",
    "wof:placetype":"venue"
},
  "geometry": {"coordinates":[-121.624722,39.122278],"type":"Point"}
}