{
  "type": "Feature",
  "properties": {
    "iso:country":"US",
    "sg:address":"1316 S Meadow Ln",
    "sg:city":"Colton",
    "sg:classifiers":[
        {
            "category":"Freight",
            "type":"Transportation"
        }
    ],
    "sg:phone":"+1 909 824 1928",
    "sg:postcode":"92324",
    "sg:province":"CA",
    "sg:tags":[
        "operator",
        "local",
        "trucking"
    ],
    "wof:name":"Tht Trucking Co",
    "wof:placetype":"venue"
},
  "geometry": {"coordinates":[-117.299597,34.045942],"type":"Point"}
}