{
  "type": "Feature",
  "properties": {
    "addr:full":"1316 S Meadow Ln Colton CA 92324",
    "addr:housenumber":"1316",
    "addr:postcode":"92324",
    "addr:street":"S Meadow Ln",
    "iso:country":"US",
    "sg:address":"1316 S Meadow Ln",
    "sg:city":"Colton",
    "sg:classifiers":[
        {
            "category":"Freight",
            "type":"Transportation"
        }
    ],
    "sg:phone":"+1 909 824 1928",
    "sg:postcode":"92324",
    "sg:province":"CA",
    "sg:tags":[
        "operator",
        "local",
        "trucking"
    ],
    "wof:name":"Tht Trucking Co",
    "wof:placetype":"venue"
},
  "geometry": {"coordinates":[-117.29959700000001,34.045942],"type":"Point"}
}