{
  "type": "Feature",
  "properties": {
    "iso:country":"US",
    "sg:address":"1324 Wilshire Blvd",
    "sg:city":"Los Angeles",
    "sg:classifiers":[
        {
            "category":"Wholesale",
            "subcategory":"Non-durable Goods",
            "type":"Manufacturing & Wholesale Goods"
        }
    ],
    "sg:phone":"+1 213 484 0388",
    "sg:postcode":"90017",
    "sg:province":"CA",
    "wof:name":"Lito Color",
    "wof:placetype":"venue"
},
  "geometry": {"coordinates":[-118.268233,34.054421],"type":"Point"}
}