{
  "type": "Feature",
  "properties": {
    "addr:full":"207 Terrace Ave San Rafael CA 94901",
    "addr:housenumber":"207",
    "addr:postcode":"94901",
    "addr:street":"Terrace Ave",
    "iso:country":"US",
    "sg:address":"207 Terrace Ave",
    "sg:city":"San Rafael",
    "sg:classifiers":[
        {
            "category":"Manufacturing",
            "subcategory":"Tools & Machinery",
            "type":"Manufacturing & Wholesale Goods"
        }
    ],
    "sg:phone":"+1 415 459 0362",
    "sg:postcode":"94901",
    "sg:province":"CA",
    "sg:tags":[
        "computer",
        "electronic",
        "mfg"
    ],
    "wof:name":"Time Now",
    "wof:placetype":"venue"
},
  "geometry": {"coordinates":[-122.546404,37.973797],"type":"Point"}
}