{
  "type": "Feature",
  "properties": {
    "iso:country":"US",
    "sg:address":"Park Victoria and Kennedy",
    "sg:city":"Milpitas",
    "sg:classifiers":[
        {
            "category":"Park",
            "type":"Public Place"
        }
    ],
    "sg:postcode":"95035",
    "sg:province":"CA",
    "wof:name":"Cardoza Park",
    "wof:placetype":"venue"
},
  "geometry": {"coordinates":[-121.886002,37.441898],"type":"Point"}
}