{
  "type": "Feature",
  "properties": {
    "iso:country":"US",
    "sg:address":"325 E Arrow Hwy",
    "sg:city":"San Dimas",
    "sg:classifiers":[
        {
            "category":"Wholesale",
            "subcategory":"Medical Equipment & Supplies",
            "type":"Manufacturing & Wholesale Goods"
        }
    ],
    "sg:phone":"+1 909 394 0012",
    "sg:postcode":"91773",
    "sg:province":"CA",
    "sg:tags":[
        "physician",
        "surgeon"
    ],
    "wof:name":"Optimal Rehab",
    "wof:placetype":"venue"
},
  "geometry": {"coordinates":[-117.800368,34.103027],"type":"Point"}
}