{
  "type": "Feature",
  "properties": {
    "addr:full":"430 Hot Springs Rd Montecito CA 93108",
    "addr:housenumber":"430",
    "addr:postcode":"93108",
    "addr:street":"Hot Springs Rd",
    "iso:country":"US",
    "sg:address":"430 Hot Springs Rd",
    "sg:city":"Montecito",
    "sg:classifiers":[
        {
            "category":"Social Services",
            "subcategory":"Adult Care",
            "type":"Services"
        }
    ],
    "sg:phone":"+1 805 451 2222",
    "sg:postcode":"93108",
    "sg:province":"CA",
    "sg:tags":[
        "info",
        "life",
        "retirement"
    ],
    "wof:name":"Pepper's Estate",
    "wof:placetype":"venue"
},
  "geometry": {"coordinates":[-119.64115200000001,34.434536],"type":"Point"}
}