{
  "type": "Feature",
  "properties": {
    "addr:full":"747 Warehouse St Los Angeles CA 90021",
    "addr:housenumber":"747",
    "addr:postcode":"90021",
    "addr:street":"Warehouse St",
    "iso:country":"US",
    "sg:address":"747 Warehouse St",
    "sg:city":"Los Angeles",
    "sg:classifiers":[
        {
            "category":"Manufacturing",
            "subcategory":"Apparel",
            "type":"Manufacturing & Wholesale Goods"
        }
    ],
    "sg:phone":"+1 213 272 9490",
    "sg:postcode":"90021",
    "sg:province":"CA",
    "sg:tags":[
        "manufacturer"
    ],
    "wof:name":"Prince Activewear LLC",
    "wof:placetype":"venue"
},
  "geometry": {"coordinates":[-118.239147,34.035048],"type":"Point"}
}