{
  "type": "Feature",
  "properties": {
    "iso:country":"US",
    "sg:address":"27984 Hwy 189",
    "sg:city":"Lake Arrowhead",
    "sg:classifiers":[
        {
            "category":"Restaurant",
            "type":"Food & Drink"
        }
    ],
    "sg:phone":"+1 909 336 1511",
    "sg:postcode":"92352",
    "sg:province":"CA",
    "sg:website":"www.laresort.com/lars/bin189.htm",
    "wof:name":"Bin 189",
    "wof:placetype":"venue"
},
  "geometry": {"coordinates":[-117.11359,34.265641],"type":"Point"}
}