{
  "type": "Feature",
  "properties": {
    "addr:full":"405 Lone Tree Rd Oroville CA 95965",
    "addr:housenumber":"405",
    "addr:postcode":"95965",
    "addr:street":"Lone Tree Rd",
    "iso:country":"US",
    "sg:address":"405 Lone Tree Rd",
    "sg:city":"Oroville",
    "sg:classifiers":[
        {
            "category":"Manufacturing",
            "subcategory":"Buildings",
            "type":"Manufacturing & Wholesale Goods"
        },
        {
            "category":"Building & Trades",
            "subcategory":"Construction",
            "type":"Services"
        }
    ],
    "sg:phone":"+1 530 228 9489",
    "sg:postcode":"95965",
    "sg:province":"CA",
    "sg:tags":[
        "home",
        "builder",
        "contractor"
    ],
    "wof:name":"Abken Construction",
    "wof:placetype":"venue"
},
  "geometry": {"coordinates":[-121.576882,39.44683],"type":"Point"}
}