{
  "type": "Feature",
  "properties": {
    "addr:full":"2006 Niles St Bakersfield CA 93305",
    "addr:housenumber":"2006",
    "addr:postcode":"93305",
    "addr:street":"Niles St",
    "iso:country":"US",
    "sg:address":"2006 Niles St",
    "sg:city":"Bakersfield",
    "sg:classifiers":[
        {
            "category":"Professional",
            "type":"Services"
        }
    ],
    "sg:phone":"+1 661 852 0903",
    "sg:postcode":"93305",
    "sg:province":"CA",
    "wof:name":"MB Products",
    "wof:placetype":"venue"
},
  "geometry": {"coordinates":[-118.96753200000001,35.376468],"type":"Point"}
}