{
  "type": "Feature",
  "properties": {
    "addr:full":"600 W I St Los Banos CA 93635",
    "addr:housenumber":"600",
    "addr:postcode":"93635",
    "addr:street":"W I St",
    "iso:country":"US",
    "sg:address":"600 W I St",
    "sg:city":"Los Banos",
    "sg:classifiers":[
        {
            "category":"Health Services",
            "subcategory":"Doctor",
            "type":"Services"
        }
    ],
    "sg:phone":"+1 209 826 4666",
    "sg:postcode":"93635",
    "sg:province":"CA",
    "sg:tags":[
        "physician",
        "surgeon"
    ],
    "wof:name":"Central Valley Allergy Assoc",
    "wof:placetype":"venue"
},
  "geometry": {"coordinates":[-120.86084099999999,37.063127],"type":"Point"}
}