{
  "type": "Feature",
  "properties": {
    "addr:full":"17441 Valley Blvd Bloomington CA 92316",
    "addr:housenumber":"17441",
    "addr:postcode":"92316",
    "addr:street":"Valley Blvd",
    "iso:country":"US",
    "sg:address":"17441 Valley Blvd",
    "sg:city":"Bloomington",
    "sg:classifiers":[
        {
            "category":"Retail",
            "subcategory":"Repair Shop",
            "type":"Services"
        }
    ],
    "sg:phone":"+1 909 350 4965",
    "sg:postcode":"92316",
    "sg:province":"CA",
    "sg:tags":[
        "welding"
    ],
    "wof:name":"Lemco Engineering",
    "wof:placetype":"venue"
},
  "geometry": {"coordinates":[-117.42558099999999,34.070326],"type":"Point"}
}