{
  "type": "Feature",
  "properties": {
    "iso:country":"US",
    "sg:address":"1333 Webster St",
    "sg:city":"Alameda",
    "sg:classifiers":[
        {
            "category":"Real Estate",
            "subcategory":"Real Estate Operator",
            "type":"Services"
        }
    ],
    "sg:phone":"+1 510 523 9232",
    "sg:postcode":"94501",
    "sg:province":"CA",
    "sg:tags":[
        "management",
        "condominium"
    ],
    "wof:name":"Park Webster Condos",
    "wof:placetype":"venue"
},
  "geometry": {"coordinates":[-122.276848,37.771066],"type":"Point"}
}