{
  "type": "Feature",
  "properties": {
    "iso:country":"US",
    "sg:address":"810 College Ave",
    "sg:city":"Kentfield",
    "sg:classifiers":[
        {
            "category":"Real Estate",
            "subcategory":"Real Estate Agent",
            "type":"Services"
        }
    ],
    "sg:phone":"+1 800 326 9129",
    "sg:postcode":"94904",
    "sg:province":"CA",
    "wof:name":"Relo Intl. Relocation Service",
    "wof:placetype":"venue"
},
  "geometry": {"coordinates":[-122.549649,37.951858],"type":"Point"}
}