{
  "type": "Feature",
  "properties": {
    "iso:country":"US",
    "sg:address":"2725 E Monte Vista Ave",
    "sg:city":"Denair",
    "sg:classifiers":[
        {
            "category":"Professional",
            "type":"Services"
        }
    ],
    "sg:phone":"+1 209 656 1309",
    "sg:postcode":"95316",
    "sg:province":"CA",
    "wof:name":"Twilas Wallen Statuary & Gard",
    "wof:placetype":"venue"
},
  "geometry": {"coordinates":[-120.815058,37.521771],"type":"Point"}
}