{
  "type": "Feature",
  "properties": {
    "addr:full":"2725 E Monte Vista Ave Denair CA 95316",
    "addr:housenumber":"2725",
    "addr:postcode":"95316",
    "addr:street":"E Monte Vista Ave",
    "iso:country":"US",
    "sg:address":"2725 E Monte Vista Ave",
    "sg:city":"Denair",
    "sg:classifiers":[
        {
            "category":"Professional",
            "type":"Services"
        }
    ],
    "sg:phone":"+1 209 656 1309",
    "sg:postcode":"95316",
    "sg:province":"CA",
    "wof:name":"Twilas Wallen Statuary & Gard",
    "wof:placetype":"venue"
},
  "geometry": {"coordinates":[-120.81505799999999,37.521771],"type":"Point"}
}