{
  "type": "Feature",
  "properties": {
    "addr:full":"1017 Bayview Ave Oakland CA 94610",
    "addr:housenumber":"1017",
    "addr:postcode":"94610",
    "addr:street":"Bayview Ave",
    "iso:country":"US",
    "sg:address":"1017 Bayview Ave",
    "sg:city":"Oakland",
    "sg:classifiers":[
        {
            "category":"Wholesale",
            "subcategory":"Books, Periodicals, & Newspapers",
            "type":"Manufacturing & Wholesale Goods"
        }
    ],
    "sg:phone":"+1 510 532 7573",
    "sg:postcode":"94610",
    "sg:province":"CA",
    "sg:tags":[
        "publisher",
        "book"
    ],
    "wof:name":"Open Publishing",
    "wof:placetype":"venue"
},
  "geometry": {"coordinates":[-122.23684799999999,37.802078],"type":"Point"}
}