{
  "type": "Feature",
  "properties": {
    "iso:country":"US",
    "sg:address":"1016 E Cooley Dr",
    "sg:city":"Colton",
    "sg:classifiers":[
        {
            "category":"Professional",
            "type":"Services"
        }
    ],
    "sg:phone":"+1 909 484 5561",
    "sg:postcode":"92324",
    "sg:province":"CA",
    "sg:tags":[
        "establishment"
    ],
    "wof:name":"Horrigan Enterprises",
    "wof:placetype":"venue"
},
  "geometry": {"coordinates":[-117.309513,34.054676],"type":"Point"}
}