{
  "type": "Feature",
  "properties": {
    "iso:country":"US",
    "sg:address":"320 E H St",
    "sg:city":"Chula Vista",
    "sg:classifiers":[
        {
            "category":"Real Estate",
            "subcategory":"Real Estate Agent",
            "type":"Services"
        }
    ],
    "sg:phone":"+1 619 409 8533",
    "sg:postcode":"91910",
    "sg:province":"CA",
    "wof:name":"Betty Stoike Brocklehurst",
    "wof:placetype":"venue"
},
  "geometry": {"coordinates":[-117.054326,32.640719],"type":"Point"}
}