{
  "type": "Feature",
  "properties": {
    "iso:country":"US",
    "sg:address":"164 W Del Mar Blvd",
    "sg:city":"Pasadena",
    "sg:classifiers":[
        {
            "category":"Retail",
            "subcategory":"Laundry & Dry Cleaning",
            "type":"Services"
        }
    ],
    "sg:phone":"+1 626 792 3777",
    "sg:postcode":"91105",
    "sg:province":"CA",
    "wof:name":"Pasadena Cleaners",
    "wof:placetype":"venue"
},
  "geometry": {"coordinates":[-118.153999,34.1409],"type":"Point"}
}