{
  "type": "Feature",
  "properties": {
    "iso:country":"US",
    "sg:address":"2256 Colorado Boulevard",
    "sg:city":"Los Angeles",
    "sg:classifiers":[
        {
            "category":"Building & Trades",
            "subcategory":"Locksmith",
            "type":"Services"
        }
    ],
    "sg:phone":"+1 323 799 4315",
    "sg:postcode":"90041",
    "sg:province":"CA",
    "sg:tags":[
        "key"
    ],
    "wof:name":"7 Day 24 Hour Locks & Locksmith",
    "wof:placetype":"venue"
},
  "geometry": {"coordinates":[-118.215444,34.139347],"type":"Point"}
}