{
  "type": "Feature",
  "properties": {
    "addr:full":"18653 Ventura Blvd Ste 29 Tarzana CA 91356",
    "addr:housenumber":"18653",
    "addr:postcode":"91356",
    "addr:street":"Ventura Blvd Ste 29",
    "iso:country":"US",
    "sg:address":"18653 Ventura Blvd Ste 29",
    "sg:city":"Tarzana",
    "sg:classifiers":[
        {
            "category":"Professional",
            "subcategory":"Lawyer & Legal Services",
            "type":"Services"
        }
    ],
    "sg:phone":"+1 818 984 2131",
    "sg:postcode":"91356",
    "sg:province":"CA",
    "sg:tags":[
        "information",
        "attorney",
        "referral"
    ],
    "wof:name":"M Francesca Hannan",
    "wof:placetype":"venue"
},
  "geometry": {"coordinates":[-118.539912,34.170351],"type":"Point"}
}