{
  "type": "Feature",
  "properties": {
    "iso:country":"US",
    "sg:address":"1554 18th St",
    "sg:city":"Santa Monica",
    "sg:classifiers":[
        {
            "category":"Communications",
            "subcategory":"Film & Video Production",
            "type":"Services"
        }
    ],
    "sg:phone":"+1 310 315 4151",
    "sg:postcode":"90404",
    "sg:province":"CA",
    "sg:tags":[
        "motion",
        "picture",
        "duplication",
        "tape"
    ],
    "wof:name":"Copy Right Video LLC",
    "wof:placetype":"venue"
},
  "geometry": {"coordinates":[-118.47956499999999,34.025163],"type":"Point"}
}