{
  "type": "Feature",
  "properties": {
    "iso:country":"US",
    "sg:address":"541 W Bardsley Ave",
    "sg:city":"Tulare",
    "sg:classifiers":[
        {
            "category":"Food & Beverages",
            "subcategory":"Groceries & Convenience Stores",
            "type":"Retail Goods"
        }
    ],
    "sg:phone":"+1 559 685 1634",
    "sg:postcode":"93274",
    "sg:province":"CA",
    "sg:tags":[
        "grocer"
    ],
    "wof:name":"Mercado Sol Del Valle",
    "wof:placetype":"venue"
},
  "geometry": {"coordinates":[-119.357608,36.196305],"type":"Point"}
}