{
  "type": "Feature",
  "properties": {
    "iso:country":"US",
    "sg:address":"9632 Duke Dr",
    "sg:city":"Westminster",
    "sg:classifiers":[
        {
            "category":"Building & Trades",
            "subcategory":"Construction",
            "type":"Services"
        }
    ],
    "sg:phone":"+1 714 839 9804",
    "sg:postcode":"92683",
    "sg:province":"CA",
    "sg:tags":[
        "contractor"
    ],
    "wof:name":"L A Construction & Development",
    "wof:placetype":"venue"
},
  "geometry": {"coordinates":[-117.960965,33.734295],"type":"Point"}
}