{
  "type": "Feature",
  "properties": {
    "addr:full":"4727 Wilshire Blvd Los Angeles CA 90010",
    "addr:housenumber":"4727",
    "addr:postcode":"90010",
    "addr:street":"Wilshire Blvd",
    "iso:country":"US",
    "sg:address":"4727 Wilshire Blvd",
    "sg:city":"Los Angeles",
    "sg:classifiers":[
        {
            "category":"Professional",
            "subcategory":"Employment Agencies",
            "type":"Services"
        }
    ],
    "sg:phone":"+1 323 954 2263",
    "sg:postcode":"90010",
    "sg:province":"CA",
    "wof:name":"Acme Talent and Literary",
    "wof:placetype":"venue"
},
  "geometry": {"coordinates":[-118.332429,34.062067],"type":"Point"}
}