{
  "type": "Feature",
  "properties": {
    "iso:country":"US",
    "sg:address":"582 W Valley Blvd",
    "sg:city":"Colton",
    "sg:classifiers":[
        {
            "category":"Building & Trades",
            "subcategory":"Cleaning & Sanitation",
            "type":"Services"
        }
    ],
    "sg:phone":"+1 909 824 1010",
    "sg:postcode":"92324",
    "sg:province":"CA",
    "sg:tags":[
        "janitor"
    ],
    "wof:name":"Clean 4U",
    "wof:placetype":"venue"
},
  "geometry": {"coordinates":[-117.330842,34.067816],"type":"Point"}
}