{
  "type": "Feature",
  "properties": {
    "addr:full":"861 N Spring Street Suite 224 Los Angeles CA 90012",
    "addr:housenumber":"861",
    "addr:postcode":"90012",
    "addr:street":"N Spring Street Suite 224",
    "iso:country":"US",
    "sg:address":"861 N Spring Street Suite 224",
    "sg:city":"Los Angeles",
    "sg:classifiers":[
        {
            "category":"Shopping",
            "subcategory":"Shoes",
            "type":"Retail Goods"
        }
    ],
    "sg:phone":"+1 213 687 0438",
    "sg:postcode":"90012",
    "sg:province":"CA",
    "sg:tags":[
        "store"
    ],
    "wof:name":"World Plaza Shoe",
    "wof:placetype":"venue"
},
  "geometry": {"coordinates":[-118.236428,34.062998],"type":"Point"}
}