{
  "type": "Feature",
  "properties": {
    "iso:country":"US",
    "sg:address":"5407 S Central Ave",
    "sg:city":"Los Angeles",
    "sg:classifiers":[
        {
            "category":"Food & Beverages",
            "subcategory":"Meat & Fish",
            "type":"Retail Goods"
        }
    ],
    "sg:phone":"+1 323 231 0548",
    "sg:postcode":"90011",
    "sg:province":"CA",
    "sg:tags":[
        "grocery",
        "seafood",
        "market"
    ],
    "wof:name":"P & A Seafood",
    "wof:placetype":"venue"
},
  "geometry": {"coordinates":[-118.25599699999999,33.993198],"type":"Point"}
}