{
  "type": "Feature",
  "properties": {
    "addr:full":"2108 N 1st St San Jose CA 95131",
    "addr:housenumber":"2108",
    "addr:postcode":"95131",
    "addr:street":"N 1St St",
    "iso:country":"US",
    "sg:address":"2108 N 1st St",
    "sg:city":"San Jose",
    "sg:classifiers":[
        {
            "category":"Autos & Motor Vehicles",
            "subcategory":"Automobile Sales",
            "type":"Retail Goods"
        }
    ],
    "sg:phone":"+1 408 436 8678",
    "sg:postcode":"95131",
    "sg:province":"CA",
    "sg:tags":[
        "car"
    ],
    "wof:name":"Piercy Toyota Special Finance",
    "wof:placetype":"venue"
},
  "geometry": {"coordinates":[-121.918947,37.376406],"type":"Point"}
}