{
  "type": "Feature",
  "properties": {
    "addr:full":"1661 Mission Street San Francisco CA 94103",
    "addr:housenumber":"1661",
    "addr:postcode":"94103",
    "addr:street":"Mission Street",
    "iso:country":"US",
    "sg:address":"1661 Mission Street",
    "sg:city":"San Francisco",
    "sg:classifiers":[
        {
            "category":"Building & Trades",
            "subcategory":"Construction",
            "type":"Services"
        }
    ],
    "sg:phone":"+1 415 626 2320",
    "sg:postcode":"94103",
    "sg:province":"CA",
    "sg:tags":[
        "interior",
        "design"
    ],
    "wof:name":"Warren Sheets Design",
    "wof:placetype":"venue"
},
  "geometry": {"coordinates":[-122.418999,37.771099],"type":"Point"}
}