{
  "type": "Feature",
  "properties": {
    "addr:full":"3151 Los Feliz Blvd Los Angeles CA 90039",
    "addr:housenumber":"3151",
    "addr:postcode":"90039",
    "addr:street":"Los Feliz Blvd",
    "iso:country":"US",
    "sg:address":"3151 Los Feliz Blvd",
    "sg:city":"Los Angeles",
    "sg:classifiers":[
        {
            "category":"Shopping",
            "subcategory":"Books",
            "type":"Retail Goods"
        }
    ],
    "sg:phone":"+1 323 668 1212",
    "sg:postcode":"90039",
    "sg:province":"CA",
    "sg:tags":[
        "comic"
    ],
    "wof:name":"Mini Melt",
    "wof:placetype":"venue"
},
  "geometry": {"coordinates":[-118.268344,34.123676],"type":"Point"}
}