{
  "type": "Feature",
  "properties": {
    "addr:full":"198 E Ross Rd El Centro CA 92243",
    "addr:housenumber":"198",
    "addr:postcode":"92243",
    "addr:street":"E Ross Rd",
    "iso:country":"US",
    "sg:address":"198 E Ross Rd",
    "sg:city":"El Centro",
    "sg:classifiers":[
        {
            "category":"Manufacturing",
            "subcategory":"Tools & Machinery",
            "type":"Manufacturing & Wholesale Goods"
        }
    ],
    "sg:phone":"+1 760 352 4691",
    "sg:postcode":"92243",
    "sg:province":"CA",
    "sg:tags":[
        "equipment",
        "janitor",
        "supply"
    ],
    "wof:name":"Waxie Sanitary Supply",
    "wof:placetype":"venue"
},
  "geometry": {"coordinates":[-115.517731,32.781503],"type":"Point"}
}