{
  "type": "Feature",
  "properties": {
    "iso:country":"US",
    "sg:address":"1261 E Florence Avenue",
    "sg:city":"Los Angeles",
    "sg:classifiers":[
        {
            "category":"Food & Beverages",
            "subcategory":"Liquor & Beverages",
            "type":"Retail Goods"
        }
    ],
    "sg:phone":"+1 323 588 1322",
    "sg:postcode":"90001",
    "sg:province":"CA",
    "sg:tags":[
        "beer",
        "spirit",
        "wine"
    ],
    "wof:name":"Friendly Liquor",
    "wof:placetype":"venue"
},
  "geometry": {"coordinates":[-118.252162,33.974878],"type":"Point"}
}