{
  "type": "Feature",
  "properties": {
    "addr:full":"13215 Barton Cir Whittier CA 90605",
    "addr:housenumber":"13215",
    "addr:postcode":"90605",
    "addr:street":"Barton Cir",
    "iso:country":"US",
    "sg:address":"13215 Barton Cir",
    "sg:city":"Whittier",
    "sg:classifiers":[
        {
            "category":"Building & Trades",
            "subcategory":"Construction",
            "type":"Services"
        }
    ],
    "sg:phone":"+1 562 906 0062",
    "sg:postcode":"90605",
    "sg:province":"CA",
    "sg:tags":[
        "fabricator",
        "metal"
    ],
    "wof:name":"Carson Valley Metalworks",
    "wof:placetype":"venue"
},
  "geometry": {"coordinates":[-118.047746,33.946406],"type":"Point"}
}