{
  "type": "Feature",
  "properties": {
    "iso:country":"US",
    "sg:address":"4707 S Broadway",
    "sg:city":"Los Angeles",
    "sg:classifiers":[
        {
            "category":"Food & Beverages",
            "subcategory":"Groceries & Convenience Stores",
            "type":"Retail Goods"
        }
    ],
    "sg:phone":"+1 323 234 1228",
    "sg:postcode":"90037",
    "sg:province":"CA",
    "wof:name":"Super Discount",
    "wof:placetype":"venue"
},
  "geometry": {"coordinates":[-118.2782,34.000506],"type":"Point"}
}