{
  "type": "Feature",
  "properties": {
    "addr:full":"1953 Las Posas Rd Corona CA 92882",
    "addr:housenumber":"1953",
    "addr:postcode":"92882",
    "addr:street":"Las Posas Rd",
    "iso:country":"US",
    "sg:address":"1953 Las Posas Rd",
    "sg:city":"Corona",
    "sg:classifiers":[
        {
            "category":"Banks & Credit Unions",
            "subcategory":"Investment Brokerage",
            "type":"Services"
        }
    ],
    "sg:phone":"+1 951 817 9420",
    "sg:postcode":"92882",
    "sg:province":"CA",
    "sg:tags":[
        "consultant",
        "financing"
    ],
    "wof:name":"Alliance Group",
    "wof:placetype":"venue"
},
  "geometry": {"coordinates":[-117.611564,33.869689],"type":"Point"}
}