{
  "type": "Feature",
  "properties": {
    "iso:country":"US",
    "sg:address":"945 Lincoln Way",
    "sg:city":"Auburn",
    "sg:classifiers":[
        {
            "category":"Professional",
            "subcategory":"Computer Services",
            "type":"Services"
        }
    ],
    "sg:phone":"+1 530 887 0686",
    "sg:postcode":"95603",
    "sg:province":"CA",
    "sg:tags":[
        "publisher",
        "designer",
        "internet",
        "network",
        "repair",
        "consultant",
        "isp",
        "system",
        "design",
        "provider",
        "developer",
        "equipment-service",
        "software"
    ],
    "sg:website":"http://www.frommail.com",
    "wof:name":"Wizwire Communication Services",
    "wof:placetype":"venue"
},
  "geometry": {"coordinates":[-121.078869,38.896204],"type":"Point"}
}