{
  "type": "Feature",
  "properties": {
    "addr:full":"3525 Garfield Ave Los Angeles CA 90040",
    "addr:housenumber":"3525",
    "addr:postcode":"90040",
    "addr:street":"Garfield Ave",
    "iso:country":"US",
    "sg:address":"3525 Garfield Ave",
    "sg:city":"Los Angeles",
    "sg:classifiers":[
        {
            "category":"Home & Garden",
            "subcategory":"Building Materials",
            "type":"Retail Goods"
        }
    ],
    "sg:phone":"+1 323 560 1384",
    "sg:postcode":"90040",
    "sg:province":"CA",
    "sg:tags":[
        "paint"
    ],
    "sg:website":"www.dunnedwards.net",
    "wof:name":"Dunn-Edwards Paint & Wllcvrngs",
    "wof:placetype":"venue"
},
  "geometry": {"coordinates":[-118.141469,33.982467],"type":"Point"}
}