{
  "type": "Feature",
  "properties": {
    "addr:full":"6901 Woodley Ave Van Nuys CA 91406",
    "addr:housenumber":"6901",
    "addr:postcode":"91406",
    "addr:street":"Woodley Ave",
    "iso:country":"US",
    "sg:address":"6901 Woodley Ave",
    "sg:city":"Van Nuys",
    "sg:classifiers":[
        {
            "category":"Manufacturing",
            "subcategory":"Retail Goods",
            "type":"Manufacturing & Wholesale Goods"
        }
    ],
    "sg:phone":"+1 818 222 9200",
    "sg:postcode":"91406",
    "sg:province":"CA",
    "sg:tags":[
        "equipment",
        "engineering",
        "supply"
    ],
    "sg:website":"www.oesincorp.com",
    "wof:name":"Optimal Engineering Systems",
    "wof:placetype":"venue"
},
  "geometry": {"coordinates":[-118.483656,34.197533],"type":"Point"}
}