{
  "type": "Feature",
  "properties": {
    "iso:country":"US",
    "sg:address":"1050 Hermes Ave",
    "sg:city":"Encinitas",
    "sg:classifiers":[
        {
            "category":"Building & Trades",
            "subcategory":"Construction",
            "type":"Services"
        }
    ],
    "sg:phone":"+1 760 436 6080",
    "sg:postcode":"92024",
    "sg:province":"CA",
    "sg:tags":[
        "contractor"
    ],
    "wof:name":"Advantage Building",
    "wof:placetype":"venue"
},
  "geometry": {"coordinates":[-117.301498,33.068659],"type":"Point"}
}