{
  "type": "Feature",
  "properties": {
    "iso:country":"US",
    "sg:address":"127 Solana Rd",
    "sg:city":"Portola Valley",
    "sg:classifiers":[
        {
            "category":"Professional",
            "subcategory":"Management & Consulting",
            "type":"Services"
        }
    ],
    "sg:phone":"+1 650 851 4892",
    "sg:postcode":"94028",
    "sg:province":"CA",
    "sg:tags":[
        "support",
        "facility"
    ],
    "wof:name":"Edward Davis",
    "wof:placetype":"venue"
},
  "geometry": {"coordinates":[-122.221017,37.38967],"type":"Point"}
}