{
  "type": "Feature",
  "properties": {
    "addr:full":"250 Frank H Ogawa Plaza Suite 3330 Oakland CA 94612",
    "addr:housenumber":"250",
    "addr:postcode":"94612",
    "addr:street":"Frank H Ogawa Plaza Suite 3330",
    "iso:country":"US",
    "sg:address":"250 Frank H Ogawa Plaza Suite 3330",
    "sg:city":"Oakland",
    "sg:classifiers":[
        {
            "category":"Government",
            "subcategory":"City Hall",
            "type":"Public Place"
        }
    ],
    "sg:phone":"+1 510 238 3187",
    "sg:postcode":"94612",
    "sg:province":"CA",
    "sg:website":"www.oaklandnet.com/Parks",
    "wof:name":"City of Oakland Office of Parks and Recreation",
    "wof:placetype":"venue"
},
  "geometry": {"coordinates":[-122.27162300000001,37.805343],"type":"Point"}
}