{
  "type": "Feature",
  "properties": {
    "iso:country":"US",
    "sg:address":"23525 Civic Center Way",
    "sg:city":"Malibu",
    "sg:classifiers":[
        {
            "category":"Government",
            "subcategory":"Police Station",
            "type":"Public Place"
        }
    ],
    "sg:phone":"+1 310 317 1322",
    "sg:postcode":"90265",
    "sg:province":"CA",
    "sg:tags":[
        "sheriff"
    ],
    "wof:name":"Malibu Ct Sheriff's Office",
    "wof:placetype":"venue"
},
  "geometry": {"coordinates":[-118.68799300000001,34.036599],"type":"Point"}
}