{
  "type": "Feature",
  "properties": {
    "iso:country":"US",
    "sg:address":"13465 1/2 Pumice St",
    "sg:city":"Norwalk",
    "sg:classifiers":[
        {
            "category":"Utilities",
            "subcategory":"Telephone",
            "type":"Services"
        },
        {
            "category":"Communications",
            "type":"Services"
        }
    ],
    "sg:phone":"+1 562 404 1199",
    "sg:postcode":"90650",
    "sg:province":"CA",
    "sg:tags":[
        "equipment",
        "answering",
        "system",
        "systems-repair"
    ],
    "wof:name":"Union Telephone",
    "wof:placetype":"venue"
},
  "geometry": {"coordinates":[-118.04585299999999,33.897574],"type":"Point"}
}