{
  "type": "Feature",
  "properties": {
    "iso:country":"US",
    "sg:address":"14011 Park Ave",
    "sg:city":"Victorville",
    "sg:classifiers":[
        {
            "category":"Professional",
            "type":"Services"
        }
    ],
    "sg:phone":"+1 760 245 3330",
    "sg:postcode":"92392",
    "sg:province":"CA",
    "sg:tags":[
        "establishment"
    ],
    "wof:name":"Curriculum Networking Spec Inc",
    "wof:placetype":"venue"
},
  "geometry": {"coordinates":[-117.326462,34.505117],"type":"Point"}
}