{
  "type": "Feature",
  "properties": {
    "addr:full":"42263 Forsythia Dr Fremont CA 94539",
    "addr:postcode":"42263;94539",
    "addr:street":"Forsythia Dr",
    "iso:country":"US",
    "sg:address":"42263 Forsythia Dr",
    "sg:city":"Fremont",
    "sg:classifiers":[
        {
            "category":"Building & Trades",
            "subcategory":"Construction",
            "type":"Services"
        }
    ],
    "sg:phone":"+1 510 656 9180",
    "sg:postcode":"94539",
    "sg:province":"CA",
    "sg:tags":[
        "contractor"
    ],
    "wof:name":"C & S Construction",
    "wof:placetype":"venue"
},
  "geometry": {"coordinates":[-121.935073,37.539009],"type":"Point"}
}