{
  "type": "Feature",
  "properties": {
    "iso:country":"US",
    "sg:address":"4201 Wilshire Blvd",
    "sg:city":"Los Angeles",
    "sg:classifiers":[
        {
            "category":"Professional",
            "subcategory":"Computer Services",
            "type":"Services"
        }
    ],
    "sg:phone":"+1 323 934 4116",
    "sg:postcode":"90010",
    "sg:province":"CA",
    "sg:tags":[
        "website",
        "design"
    ],
    "wof:name":"Start In USA Inc",
    "wof:placetype":"venue"
},
  "geometry": {"coordinates":[-118.319952,34.061746],"type":"Point"}
}