{
  "type": "Feature",
  "properties": {
    "iso:country":"US",
    "sg:address":"1311 S Flower St",
    "sg:city":"Burbank",
    "sg:classifiers":[
        {
            "category":"Food & Beverages",
            "subcategory":"Meat & Fish",
            "type":"Retail Goods"
        }
    ],
    "sg:phone":"+1 818 848 2280",
    "sg:postcode":"91502",
    "sg:province":"CA",
    "wof:name":"Meat & Potatoes",
    "wof:placetype":"venue"
},
  "geometry": {"coordinates":[-118.299663,34.168946],"type":"Point"}
}