{
  "type": "Feature",
  "properties": {
    "iso:country":"US",
    "sg:address":"4562 E 2nd St",
    "sg:city":"Benicia",
    "sg:classifiers":[
        {
            "category":"Manufacturing",
            "subcategory":"Retail Goods",
            "type":"Manufacturing & Wholesale Goods"
        }
    ],
    "sg:phone":"+1 707 747 6918",
    "sg:postcode":"94510",
    "sg:province":"CA",
    "sg:tags":[
        "manufacture",
        "embellishment",
        "architectural"
    ],
    "wof:name":"Carving Workshop",
    "wof:placetype":"venue"
},
  "geometry": {"coordinates":[-122.12452,38.081081],"type":"Point"}
}