{
  "type": "Feature",
  "properties": {
    "addr:full":"4608 Meldon Ave Oakland CA 94619",
    "addr:housenumber":"4608",
    "addr:postcode":"94619",
    "addr:street":"Meldon Ave",
    "iso:country":"US",
    "sg:address":"4608 Meldon Ave",
    "sg:city":"Oakland",
    "sg:classifiers":[
        {
            "category":"Banks & Credit Unions",
            "subcategory":"Bank",
            "type":"Services"
        }
    ],
    "sg:phone":"+1 510 903 1456",
    "sg:postcode":"94619",
    "sg:province":"CA",
    "sg:tags":[
        "loan",
        "real estate"
    ],
    "wof:name":"Highland Mortgage",
    "wof:placetype":"venue"
},
  "geometry": {"coordinates":[-122.19399900000001,37.783519],"type":"Point"}
}