{
  "type": "Feature",
  "properties": {
    "addr:full":"8800 Coleraine Ct Bakersfield CA 93313",
    "addr:postcode":"8800;93313",
    "addr:street":"Coleraine Ct",
    "iso:country":"US",
    "sg:address":"8800 Coleraine Ct",
    "sg:city":"Bakersfield",
    "sg:classifiers":[
        {
            "category":"Wholesale",
            "subcategory":"Home Furnishings",
            "type":"Manufacturing & Wholesale Goods"
        }
    ],
    "sg:phone":"+1 661 397 7335",
    "sg:postcode":"93313",
    "sg:province":"CA",
    "wof:name":"California Garage Cabinets",
    "wof:placetype":"venue"
},
  "geometry": {"coordinates":[-119.04843099999999,35.275233],"type":"Point"}
}