{
  "type": "Feature",
  "properties": {
    "iso:country":"US",
    "sg:address":"13949 Dinard Ave",
    "sg:city":"Santa Fe Springs",
    "sg:classifiers":[
        {
            "category":"Manufacturing",
            "subcategory":"Tools & Machinery",
            "type":"Manufacturing & Wholesale Goods"
        }
    ],
    "sg:phone":"+1 562 802 0400",
    "sg:postcode":"90670",
    "sg:province":"CA",
    "sg:tags":[
        "metal",
        "shaping"
    ],
    "wof:name":"Hi Tech Curving Inc",
    "wof:placetype":"venue"
},
  "geometry": {"coordinates":[-118.050648,33.903578],"type":"Point"}
}