{
  "type": "Feature",
  "properties": {
    "iso:country":"US",
    "sg:address":"6120 Seville Ave",
    "sg:city":"Huntington Park",
    "sg:classifiers":[
        {
            "category":"Health Services",
            "subcategory":"Doctor",
            "type":"Services"
        }
    ],
    "sg:phone":"+1 323 587 5474",
    "sg:postcode":"90255",
    "sg:province":"CA",
    "sg:tags":[
        "physician",
        "surgeon"
    ],
    "wof:name":"Felix M Hinostroza MD",
    "wof:placetype":"venue"
},
  "geometry": {"coordinates":[-118.222532,33.984754],"type":"Point"}
}