{
  "type": "Feature",
  "properties": {
    "addr:full":"7007 Friars Road Suite 559 San Diego CA 92108",
    "addr:housenumber":"7007",
    "addr:postcode":"92108",
    "addr:street":"Friars Road Suite 559",
    "iso:country":"US",
    "sg:address":"7007 Friars Road Suite 559",
    "sg:city":"San Diego",
    "sg:classifiers":[
        {
            "category":"Shopping",
            "subcategory":"Shoes",
            "type":"Retail Goods"
        }
    ],
    "sg:phone":"+1 619 298 4433",
    "sg:postcode":"92108",
    "sg:province":"CA",
    "sg:tags":[
        "store"
    ],
    "wof:name":"Charles David",
    "wof:placetype":"venue"
},
  "geometry": {"coordinates":[-117.16854499999999,32.76954],"type":"Point"}
}