{
  "type": "Feature",
  "properties": {
    "iso:country":"US",
    "sg:address":"4531 Market St",
    "sg:city":"Ventura",
    "sg:classifiers":[
        {
            "category":"Social Services",
            "type":"Services"
        }
    ],
    "sg:phone":"+1 805 658 0475",
    "sg:postcode":"93003",
    "sg:province":"CA",
    "sg:tags":[
        "counselor",
        "marriage",
        "family"
    ],
    "wof:name":"Shores Counseling Ctr",
    "wof:placetype":"venue"
},
  "geometry": {"coordinates":[-119.232224,34.257174],"type":"Point"}
}