{
  "type": "Feature",
  "properties": {
    "addr:full":"23334 Lyons Ave Santa Clarita CA 91321",
    "addr:housenumber":"23334",
    "addr:postcode":"91321",
    "addr:street":"Lyons Ave",
    "iso:country":"US",
    "sg:address":"23334 Lyons Ave",
    "sg:city":"Santa Clarita",
    "sg:classifiers":[
        {
            "category":"Personal",
            "subcategory":"Beauty Salon",
            "type":"Services"
        },
        {
            "category":"Personal",
            "subcategory":"Nail Salon",
            "type":"Services"
        }
    ],
    "sg:phone":"+1 661 287 3895",
    "sg:postcode":"91321",
    "sg:province":"CA",
    "sg:tags":[
        "hair"
    ],
    "sg:website":"www.toddssalon.com",
    "wof:name":"Todd's Salon",
    "wof:placetype":"venue"
},
  "geometry": {"coordinates":[-118.541563,34.379672],"type":"Point"}
}