{
  "type": "Feature",
  "properties": {
    "iso:country":"US",
    "sg:address":"901 Hotel Cir S",
    "sg:city":"San Diego",
    "sg:classifiers":[
        {
            "category":"Personal",
            "subcategory":"Beauty Salon",
            "type":"Services"
        }
    ],
    "sg:phone":"+1 619 291 6434",
    "sg:postcode":"92108",
    "sg:province":"CA",
    "sg:tags":[
        "hair"
    ],
    "wof:name":"A Leap Ahead A Salon For Hair Nails Makeup and Skin Care",
    "wof:placetype":"venue"
},
  "geometry": {"coordinates":[-117.17099,32.75962],"type":"Point"}
}