{
  "type": "Feature",
  "properties": {
    "addr:full":"1215 E Middle Ave San Martin CA 95046",
    "addr:housenumber":"1215",
    "addr:postcode":"95046",
    "addr:street":"E Middle Ave",
    "iso:country":"US",
    "sg:address":"1215 E Middle Ave",
    "sg:city":"San Martin",
    "sg:classifiers":[
        {
            "category":"Farming",
            "subcategory":"Crops",
            "type":"Manufacturing & Wholesale Goods"
        }
    ],
    "sg:phone":"+1 408 779 2202",
    "sg:postcode":"95046",
    "sg:province":"CA",
    "sg:tags":[
        "grove",
        "nut",
        "tree"
    ],
    "wof:name":"Marfia Ciro",
    "wof:placetype":"venue"
},
  "geometry": {"coordinates":[-121.603382,37.107265],"type":"Point"}
}