{
  "type": "Feature",
  "properties": {
    "addr:full":"5951 Overholtzer Dr La Verne CA 91750",
    "addr:housenumber":"5951",
    "addr:postcode":"91750",
    "addr:street":"Overholtzer Dr",
    "iso:country":"US",
    "sg:address":"5951 Overholtzer Dr",
    "sg:city":"La Verne",
    "sg:classifiers":[
        {
            "category":"Manufacturing",
            "subcategory":"Toys & Sporting Goods",
            "type":"Manufacturing & Wholesale Goods"
        }
    ],
    "sg:phone":"+1 909 596 4000",
    "sg:postcode":"91750",
    "sg:province":"CA",
    "sg:tags":[
        "mfg"
    ],
    "wof:name":"Heirloom Dolls By Isabel",
    "wof:placetype":"venue"
},
  "geometry": {"coordinates":[-117.77551099999999,34.135],"type":"Point"}
}