{
  "type": "Feature",
  "properties": {
    "iso:country":"US",
    "sg:address":"5951 Overholtzer Dr",
    "sg:city":"La Verne",
    "sg:classifiers":[
        {
            "category":"Manufacturing",
            "subcategory":"Toys & Sporting Goods",
            "type":"Manufacturing & Wholesale Goods"
        }
    ],
    "sg:phone":"+1 909 596 4000",
    "sg:postcode":"91750",
    "sg:province":"CA",
    "sg:tags":[
        "mfg"
    ],
    "wof:name":"Heirloom Dolls By Isabel",
    "wof:placetype":"venue"
},
  "geometry": {"coordinates":[-117.775511,34.135],"type":"Point"}
}