{
  "type": "Feature",
  "properties": {
    "iso:country":"US",
    "sg:address":"815 Twelve Bridges Dr Suit 30",
    "sg:city":"Lincoln",
    "sg:classifiers":[
        {
            "category":"Restaurant",
            "type":"Food & Drink"
        }
    ],
    "sg:phone":"+1 916 253 3663",
    "sg:postcode":"95648",
    "sg:province":"CA",
    "wof:name":"Original Pete's",
    "wof:placetype":"venue"
},
  "geometry": {"coordinates":[-121.287447,38.851231],"type":"Point"}
}