{
  "type": "Feature",
  "properties": {
    "addr:full":"4845 Bucknall Road Campbell CA 95008",
    "addr:postcode":"4845;95008",
    "addr:street":"Bucknall Road",
    "iso:country":"US",
    "sg:address":"4845 Bucknall Road",
    "sg:city":"Campbell",
    "sg:classifiers":[
        {
            "category":"Education",
            "subcategory":"School",
            "type":"Public Place"
        }
    ],
    "sg:phone":"+1 408 874 3200",
    "sg:postcode":"95008",
    "sg:province":"CA",
    "sg:tags":[
        "high",
        "middle",
        "elementary"
    ],
    "sg:website":"www.moreland.k12.ca.us",
    "wof:name":"Moreland School District",
    "wof:placetype":"venue"
},
  "geometry": {"coordinates":[-121.95331299999999,37.278956],"type":"Point"}
}