{
  "type": "Feature",
  "properties": {
    "addr:full":"1112 Pratt Ave Saint Helena CA 94574",
    "addr:housenumber":"1112",
    "addr:postcode":"94574",
    "addr:street":"Pratt Ave",
    "iso:country":"US",
    "sg:address":"1112 Pratt Ave",
    "sg:city":"Saint Helena",
    "sg:classifiers":[
        {
            "category":"Farming",
            "subcategory":"Vineyard",
            "type":"Manufacturing & Wholesale Goods"
        }
    ],
    "sg:phone":"+1 707 963 2929",
    "sg:postcode":"94574",
    "sg:province":"CA",
    "sg:tags":[
        "grape"
    ],
    "wof:name":"Ray Quaglia",
    "wof:placetype":"venue"
},
  "geometry": {"coordinates":[-122.47787,38.509745],"type":"Point"}
}