{
  "type": "Feature",
  "properties": {
    "iso:country":"US",
    "sg:address":"935 N Avalon Blvd",
    "sg:city":"Wilmington",
    "sg:classifiers":[
        {
            "category":"Insurance",
            "subcategory":"Insurance Agent",
            "type":"Services"
        }
    ],
    "sg:phone":"+1 310 835 3373",
    "sg:postcode":"90744",
    "sg:province":"CA",
    "wof:name":"Arthur's Insurance Svc",
    "wof:placetype":"venue"
},
  "geometry": {"coordinates":[-118.262693,33.782303],"type":"Point"}
}