{
  "type": "Feature",
  "properties": {
    "addr:full":"1349 Rimrock Dr Escondido CA 92027",
    "addr:housenumber":"1349",
    "addr:postcode":"92027",
    "addr:street":"Rimrock Dr",
    "iso:country":"US",
    "sg:address":"1349 Rimrock Dr",
    "sg:city":"Escondido",
    "sg:classifiers":[
        {
            "category":"Professional",
            "subcategory":"Business Services",
            "type":"Services"
        }
    ],
    "sg:phone":"+1 760 743 6703",
    "sg:postcode":"92027",
    "sg:province":"CA",
    "sg:tags":[
        "interior",
        "consultant",
        "design",
        "decorator"
    ],
    "wof:name":"Joan Deddo Interiors",
    "wof:placetype":"venue"
},
  "geometry": {"coordinates":[-117.07077200000001,33.150396],"type":"Point"}
}