{
  "type": "Feature",
  "properties": {
    "addr:full":"424 N Lake Ave Pasadena CA 91101",
    "addr:housenumber":"424",
    "addr:postcode":"91101",
    "addr:street":"N Lake Ave",
    "iso:country":"US",
    "sg:address":"424 N Lake Ave",
    "sg:city":"Pasadena",
    "sg:classifiers":[
        {
            "category":"Health Services",
            "subcategory":"Chiropractor",
            "type":"Services"
        }
    ],
    "sg:phone":"+1 626 583 8243",
    "sg:postcode":"91101",
    "sg:province":"CA",
    "wof:name":"Gp Health Center",
    "wof:placetype":"venue"
},
  "geometry": {"coordinates":[-118.13200399999999,34.1534],"type":"Point"}
}