{
  "type": "Feature",
  "properties": {
    "iso:country":"US",
    "sg:address":"250 S Maple Ave",
    "sg:city":"South San Francisco",
    "sg:classifiers":[
        {
            "category":"Home & Garden",
            "subcategory":"Furniture",
            "type":"Retail Goods"
        }
    ],
    "sg:phone":"+1 650 837 9333",
    "sg:postcode":"94080",
    "sg:province":"CA",
    "sg:tags":[
        "store"
    ],
    "wof:name":"Wilsons & King Inc",
    "wof:placetype":"venue"
},
  "geometry": {"coordinates":[-122.416331,37.645028],"type":"Point"}
}