{
  "type": "Feature",
  "properties": {
    "iso:country":"US",
    "sg:address":"1842 4th St",
    "sg:city":"Berkeley",
    "sg:classifiers":[
        {
            "category":"Home & Garden",
            "subcategory":"Furniture",
            "type":"Retail Goods"
        }
    ],
    "sg:phone":"+1 510 540 8296",
    "sg:postcode":"94710",
    "sg:province":"CA",
    "wof:name":"Zinc Details",
    "wof:placetype":"venue"
},
  "geometry": {"coordinates":[-122.300745,37.869982],"type":"Point"}
}