{
  "type": "Feature",
  "properties": {
    "iso:country":"US",
    "sg:address":"1160 N East St",
    "sg:city":"Anaheim",
    "sg:classifiers":[
        {
            "category":"Health Services",
            "subcategory":"Dentist",
            "type":"Services"
        }
    ],
    "sg:phone":"+1 714 535 7373",
    "sg:postcode":"92805",
    "sg:province":"CA",
    "wof:name":"Sandoval Astrid DDS Inc",
    "wof:placetype":"venue"
},
  "geometry": {"coordinates":[-117.906471,33.850176],"type":"Point"}
}