{
  "type": "Feature",
  "properties": {
    "addr:full":"410 E Perkins Ave Mc Farland CA 93250",
    "addr:housenumber":"410",
    "addr:postcode":"93250",
    "addr:street":"E Perkins Ave Mc Farland",
    "iso:country":"US",
    "sg:address":"410 E Perkins Ave",
    "sg:city":"Mc Farland",
    "sg:classifiers":[
        {
            "category":"Education",
            "subcategory":"School",
            "type":"Public Place"
        }
    ],
    "sg:phone":"+1 661 792 2113",
    "sg:postcode":"93250",
    "sg:province":"CA",
    "wof:name":"Browning Road Elem School",
    "wof:placetype":"venue"
},
  "geometry": {"coordinates":[-119.223028,35.681771],"type":"Point"}
}