{
  "type": "Feature",
  "properties": {
    "iso:country":"US",
    "sg:address":"145 E Main St",
    "sg:city":"Tustin",
    "sg:classifiers":[
        {
            "category":"Professional",
            "subcategory":"Art Services",
            "type":"Services"
        }
    ],
    "sg:phone":"+1 714 730 8200",
    "sg:postcode":"92780",
    "sg:province":"CA",
    "sg:tags":[
        "photographer"
    ],
    "sg:website":"brandt11106.c3.cmdwebsites.com",
    "wof:name":"Anamaria Brandt Photography",
    "wof:placetype":"venue"
},
  "geometry": {"coordinates":[-117.82312899999999,33.742109],"type":"Point"}
}