{
  "type": "Feature",
  "properties": {
    "addr:full":"800 N. Alameda St. Los Angeles CA 90012",
    "addr:housenumber":"800",
    "addr:postcode":"90012",
    "addr:street":"N. Alameda St.",
    "iso:country":"US",
    "sg:address":"800 N. Alameda St.",
    "sg:city":"Los Angeles",
    "sg:classifiers":[
        {
            "category":"Transit Center",
            "subcategory":"Passenger",
            "type":"Transportation"
        }
    ],
    "sg:postcode":"90012",
    "sg:province":"CA",
    "sg:website":"www.amtrak.com",
    "wof:name":"Amtrak Pacific Surfliner",
    "wof:placetype":"venue"
},
  "geometry": {"coordinates":[-118.232759,34.055073],"type":"Point"}
}