{
  "type": "Feature",
  "properties": {
    "addr:full":"16820 S Vermont Ave Gardena CA 90247",
    "addr:housenumber":"16820",
    "addr:postcode":"90247",
    "addr:street":"S Vermont Ave",
    "iso:country":"US",
    "sg:address":"16820 S Vermont Ave",
    "sg:city":"Gardena",
    "sg:classifiers":[
        {
            "category":"Food & Beverages",
            "subcategory":"Specialty",
            "type":"Retail Goods"
        },
        {
            "category":"Professional",
            "subcategory":"Management & Consulting",
            "type":"Services"
        }
    ],
    "sg:phone":"+1 310 515 3998",
    "sg:postcode":"90247",
    "sg:province":"CA",
    "sg:tags":[
        "bulk",
        "water",
        "company",
        "direct",
        "sales"
    ],
    "wof:name":"Aqua Fine Water",
    "wof:placetype":"venue"
},
  "geometry": {"coordinates":[-118.29106899999999,33.878245],"type":"Point"}
}