{
  "type": "Feature",
  "properties": {
    "addr:full":"12401 Folsom Blvd Rancho Cordova CA 95742",
    "addr:housenumber":"12401",
    "addr:postcode":"95742",
    "addr:street":"Folsom Blvd",
    "iso:country":"US",
    "sg:address":"12401 Folsom Blvd",
    "sg:city":"Rancho Cordova",
    "sg:classifiers":[
        {
            "category":"Restaurant",
            "type":"Food & Drink"
        }
    ],
    "sg:phone":"+1 916 985 0822",
    "sg:postcode":"95742",
    "sg:province":"CA",
    "wof:name":"The Old Spaghetti Factory",
    "wof:placetype":"venue"
},
  "geometry": {"coordinates":[-121.230003,38.624001],"type":"Point"}
}