{
  "type": "Feature",
  "properties": {
    "iso:country":"US",
    "sg:address":"1515 Trousdale Dr",
    "sg:city":"Burlingame",
    "sg:classifiers":[
        {
            "category":"Health Services",
            "subcategory":"Doctor",
            "type":"Services"
        },
        {
            "category":"Health Services",
            "subcategory":"Dentist",
            "type":"Services"
        }
    ],
    "sg:phone":"+1 650 697 5367",
    "sg:postcode":"94010",
    "sg:province":"CA",
    "sg:tags":[
        "medicine",
        "internal"
    ],
    "wof:name":"Ho Steyer Coskey MDS",
    "wof:placetype":"venue"
},
  "geometry": {"coordinates":[-122.38400300000001,37.594101],"type":"Point"}
}