{
  "type": "Feature",
  "properties": {
    "addr:full":"515 G St Eureka CA 95501",
    "addr:housenumber":"515",
    "addr:postcode":"95501",
    "addr:street":"G St",
    "iso:country":"US",
    "sg:address":"515 G St",
    "sg:city":"Eureka",
    "sg:classifiers":[
        {
            "category":"Home & Garden",
            "subcategory":"Furniture",
            "type":"Retail Goods"
        }
    ],
    "sg:phone":"+1 707 445 5421",
    "sg:postcode":"95501",
    "sg:province":"CA",
    "wof:name":"Vern's Furniture",
    "wof:placetype":"venue"
},
  "geometry": {"coordinates":[-124.164778,40.801933],"type":"Point"}
}