{
  "type": "Feature",
  "properties": {
    "iso:country":"US",
    "sg:address":"8421 Wilshire Blvd",
    "sg:city":"Beverly Hills",
    "sg:classifiers":[
        {
            "category":"Sports & Exercise",
            "subcategory":"Gym",
            "type":"Entertainment"
        },
        {
            "category":"Insurance",
            "subcategory":"Health Insurance",
            "type":"Services"
        }
    ],
    "sg:phone":"+1 310 279 5300",
    "sg:postcode":"90211",
    "sg:province":"CA",
    "sg:tags":[
        "trainer",
        "market"
    ],
    "wof:name":"URI Health & Beauty",
    "wof:placetype":"venue"
},
  "geometry": {"coordinates":[-118.374652,34.495171],"type":"Point"}
}