{
  "type": "Feature",
  "properties": {
    "iso:country":"US",
    "sg:address":"4033 Chevy Chase Dr",
    "sg:city":"La Canada Flintridge",
    "sg:classifiers":[
        {
            "category":"Building & Trades",
            "subcategory":"Construction",
            "type":"Services"
        }
    ],
    "sg:phone":"+1 818 952 0103",
    "sg:postcode":"91011",
    "sg:province":"CA",
    "sg:tags":[
        "interior",
        "design"
    ],
    "wof:name":"Design Concepts",
    "wof:placetype":"venue"
},
  "geometry": {"coordinates":[-118.197998,34.188702],"type":"Point"}
}