{
  "type": "Feature",
  "properties": {
    "addr:full":"617 S Olive St Los Angeles CA 90014",
    "addr:housenumber":"617",
    "addr:postcode":"90014",
    "addr:street":"S Olive St",
    "iso:country":"US",
    "sg:address":"617 S Olive St",
    "sg:city":"Los Angeles",
    "sg:classifiers":[
        {
            "category":"Professional",
            "subcategory":"Lawyer & Legal Services",
            "type":"Services"
        }
    ],
    "sg:phone":"+1 213 614 1099",
    "sg:postcode":"90014",
    "sg:province":"CA",
    "wof:name":"Valinoti R James-Law Offices of",
    "wof:placetype":"venue"
},
  "geometry": {"coordinates":[-118.253998,34.047798],"type":"Point"}
}