{
  "type": "Feature",
  "properties": {
    "addr:full":"901 W Big Bear Blvd Big Bear City CA 92314",
    "addr:housenumber":"901",
    "addr:postcode":"92314",
    "addr:street":"W Big Bear Blvd",
    "iso:country":"US",
    "sg:address":"901 W Big Bear Blvd",
    "sg:city":"Big Bear City",
    "sg:classifiers":[
        {
            "category":"Building & Trades",
            "subcategory":"Construction",
            "type":"Services"
        }
    ],
    "sg:phone":"+1 909 866 3362",
    "sg:postcode":"92314",
    "sg:province":"CA",
    "sg:tags":[
        "fence",
        "contractor"
    ],
    "wof:name":"All Fence",
    "wof:placetype":"venue"
},
  "geometry": {"coordinates":[-116.86224,34.260455],"type":"Point"}
}