{
  "type": "Feature",
  "properties": {
    "addr:full":"2152 Dupont Dr Ste 101 Irvine CA 92612",
    "addr:housenumber":"2152",
    "addr:postcode":"92612",
    "addr:street":"Dupont Dr Ste 101",
    "iso:country":"US",
    "sg:address":"2152 Dupont Dr Ste 101",
    "sg:city":"Irvine",
    "sg:classifiers":[
        {
            "category":"Banks & Credit Unions",
            "subcategory":"Financial Services",
            "type":"Services"
        }
    ],
    "sg:phone":"+1 949 756 8865",
    "sg:postcode":"92612",
    "sg:province":"CA",
    "sg:tags":[
        "broker",
        "mortgage"
    ],
    "wof:name":"Premier Horizon",
    "wof:placetype":"venue"
},
  "geometry": {"coordinates":[-117.858137,33.676136],"type":"Point"}
}