{
  "type": "Feature",
  "properties": {
    "iso:country":"US",
    "sg:address":"5775 Chelton Dr",
    "sg:city":"Oakland",
    "sg:classifiers":[
        {
            "category":"Health Services",
            "subcategory":"Medical Lab",
            "type":"Services"
        }
    ],
    "sg:phone":"+1 510 530 6327",
    "sg:postcode":"94611",
    "sg:province":"CA",
    "sg:tags":[
        "laboratory",
        "dental"
    ],
    "wof:name":"Rickson Studio",
    "wof:placetype":"venue"
},
  "geometry": {"coordinates":[-122.199952,37.822835],"type":"Point"}
}