{
  "type": "Feature",
  "properties": {
    "addr:full":"1676 Guadalupe Ave San Jose CA 95125",
    "addr:housenumber":"1676",
    "addr:postcode":"95125",
    "addr:street":"Guadalupe Ave",
    "iso:country":"US",
    "sg:address":"1676 Guadalupe Ave",
    "sg:city":"San Jose",
    "sg:classifiers":[
        {
            "category":"Shopping",
            "subcategory":"Beauty & Cosmetics",
            "type":"Retail Goods"
        }
    ],
    "sg:phone":"+1 408 723 2306",
    "sg:postcode":"95125",
    "sg:province":"CA",
    "sg:tags":[
        "merchandise"
    ],
    "wof:name":"Angela Rooker",
    "wof:placetype":"venue"
},
  "geometry": {"coordinates":[-121.88090200000001,37.302355],"type":"Point"}
}