{
  "type": "Feature",
  "properties": {
    "iso:country":"US",
    "sg:address":"4959 E 6th St",
    "sg:city":"Los Angeles",
    "sg:classifiers":[
        {
            "category":"Shopping",
            "subcategory":"Florist",
            "type":"Retail Goods"
        }
    ],
    "sg:phone":"+1 323 262 2775",
    "sg:postcode":"90022",
    "sg:province":"CA",
    "wof:name":"Claudia's Flowers",
    "wof:placetype":"venue"
},
  "geometry": {"coordinates":[-118.159957,34.025807],"type":"Point"}
}