{
  "type": "Feature",
  "properties": {
    "addr:full":"2855 Stevens Creek Boulevard Santa Clara CA 95050",
    "addr:housenumber":"2855",
    "addr:postcode":"95050",
    "addr:street":"Stevens Creek Boulevard",
    "iso:country":"US",
    "sg:address":"2855 Stevens Creek Boulevard",
    "sg:city":"Santa Clara",
    "sg:classifiers":[
        {
            "category":"Cinema",
            "subcategory":"Movie Rental",
            "type":"Entertainment"
        }
    ],
    "sg:phone":"+1 408 248 3300",
    "sg:postcode":"95050",
    "sg:province":"CA",
    "sg:tags":[
        "game",
        "video"
    ],
    "wof:name":"Suncoast Motion Picture Co",
    "wof:placetype":"venue"
},
  "geometry": {"coordinates":[-121.945999,37.323502],"type":"Point"}
}