{
  "type": "Feature",
  "properties": {
    "iso:country":"US",
    "sg:address":"21300 Deering Ct",
    "sg:city":"Canoga Park",
    "sg:classifiers":[
        {
            "category":"Building & Trades",
            "subcategory":"Plumbing",
            "type":"Services"
        }
    ],
    "sg:phone":"+1 818 992 5700",
    "sg:postcode":"91304",
    "sg:province":"CA",
    "sg:tags":[
        "sheet",
        "work",
        "metal",
        "contractor"
    ],
    "sg:website":"www.wheelstud.com",
    "wof:name":"Design Deluxe Mfg",
    "wof:placetype":"venue"
},
  "geometry": {"coordinates":[-118.596511,34.215861],"type":"Point"}
}