{
  "type": "Feature",
  "properties": {
    "addr:full":"21834 Bear Valley Rd Apple Valley CA 92308",
    "addr:housenumber":"21834",
    "addr:postcode":"92308",
    "addr:street":"Bear Valley Rd",
    "iso:country":"US",
    "sg:address":"21834 Bear Valley Rd",
    "sg:city":"Apple Valley",
    "sg:classifiers":[
        {
            "category":"Building & Trades",
            "subcategory":"Construction",
            "type":"Services"
        }
    ],
    "sg:phone":"+1 760 961 8488",
    "sg:postcode":"92308",
    "sg:province":"CA",
    "sg:tags":[
        "excavating",
        "contractor"
    ],
    "wof:name":"Westech Industries Inc",
    "wof:placetype":"venue"
},
  "geometry": {"coordinates":[-117.187578,34.471603],"type":"Point"}
}