{
  "type": "Feature",
  "properties": {
    "addr:full":"405 S Glenwood Pl Burbank CA 91506",
    "addr:housenumber":"405",
    "addr:postcode":"91506",
    "addr:street":"S Glenwood Pl",
    "iso:country":"US",
    "sg:address":"405 S Glenwood Pl",
    "sg:city":"Burbank",
    "sg:classifiers":[
        {
            "category":"Building & Trades",
            "subcategory":"Construction",
            "type":"Services"
        }
    ],
    "sg:phone":"+1 818 569 4977",
    "sg:postcode":"91506",
    "sg:province":"CA",
    "sg:tags":[
        "roofing",
        "contractor"
    ],
    "wof:name":"Paul C Truskett Roofing",
    "wof:placetype":"venue"
},
  "geometry": {"coordinates":[-118.315045,34.167962],"type":"Point"}
}