{
  "type": "Feature",
  "properties": {
    "iso:country":"US",
    "sg:address":"6060 Sunrise Blvd",
    "sg:city":"Citrus Heights",
    "sg:classifiers":[
        {
            "category":"Organizations",
            "subcategory":"Non-profit Organization",
            "type":"Services"
        }
    ],
    "sg:phone":"+1 916 723 7222",
    "sg:postcode":"95610",
    "sg:province":"CA",
    "sg:tags":[
        "disability"
    ],
    "wof:name":"Rcca Svc",
    "wof:placetype":"venue"
},
  "geometry": {"coordinates":[-121.271434,38.674479],"type":"Point"}
}