{
  "type": "Feature",
  "properties": {
    "iso:country":"US",
    "sg:address":"1814 W 153rd St",
    "sg:city":"Gardena",
    "sg:classifiers":[
        {
            "category":"Shopping",
            "subcategory":"Florist",
            "type":"Retail Goods"
        }
    ],
    "sg:phone":"+1 310 329 9403",
    "sg:postcode":"90249",
    "sg:province":"CA",
    "wof:name":"Na Pua O'Hawaii",
    "wof:placetype":"venue"
},
  "geometry": {"coordinates":[-118.309376,33.892758],"type":"Point"}
}