{
  "type": "Feature",
  "properties": {
    "iso:country":"US",
    "sg:address":"18119 Avena Rd",
    "sg:city":"Escalon",
    "sg:phone":"+1 209 838 7464",
    "sg:postcode":"95320",
    "sg:province":"CA",
    "sg:tags":[
        "farm",
        "corn",
        "cash",
        "crop",
        "field",
        "grain"
    ],
    "wof:name":"Bruce E Mellor Inc",
    "wof:placetype":"venue"
},
  "geometry": {"coordinates":[-121.07208900000001,37.841923],"type":"Point"}
}