{
  "type": "Feature",
  "properties": {
    "addr:full":"14057 Milbank St Sherman Oaks CA 91423",
    "addr:postcode":"14057;91423",
    "addr:street":"St",
    "iso:country":"US",
    "sg:address":"14057 Milbank St",
    "sg:city":"Sherman Oaks",
    "sg:classifiers":[
        {
            "category":"Utilities",
            "subcategory":"Telephone",
            "type":"Services"
        }
    ],
    "sg:phone":"+1 818 385 0980",
    "sg:postcode":"91423",
    "sg:province":"CA",
    "sg:tags":[
        "communications"
    ],
    "wof:name":"Nextstep Broadband",
    "wof:placetype":"venue"
},
  "geometry": {"coordinates":[-118.43957399999999,34.153092],"type":"Point"}
}