{
  "type": "Feature",
  "properties": {
    "addr:full":"791 Arabian Cir Vacaville CA 95687",
    "addr:housenumber":"791",
    "addr:postcode":"95687",
    "addr:street":"Arabian Cir",
    "iso:country":"US",
    "sg:address":"791 Arabian Cir",
    "sg:city":"Vacaville",
    "sg:classifiers":[
        {
            "category":"Professional",
            "subcategory":"Detective & Security Services",
            "type":"Services"
        }
    ],
    "sg:phone":"+1 707 446 3510",
    "sg:postcode":"95687",
    "sg:province":"CA",
    "sg:tags":[
        "information",
        "bureau"
    ],
    "wof:name":"J. & M. Svc.",
    "wof:placetype":"venue"
},
  "geometry": {"coordinates":[-121.942009,38.354622],"type":"Point"}
}