{
  "type": "Feature",
  "properties": {
    "addr:full":"1922 E 7th Place Los Angeles CA 90021",
    "addr:housenumber":"1922",
    "addr:postcode":"90021",
    "addr:street":"E 7Th Place",
    "iso:country":"US",
    "sg:address":"1922 E 7th Place",
    "sg:city":"Los Angeles",
    "sg:classifiers":[
        {
            "category":"Shopping",
            "subcategory":"Clothing, Apparel, & Fashions",
            "type":"Retail Goods"
        }
    ],
    "sg:phone":"+1 213 624 2242",
    "sg:postcode":"90021",
    "sg:province":"CA",
    "sg:tags":[
        "clothing",
        "women's"
    ],
    "wof:name":"Papillon Eastern Imports",
    "wof:placetype":"venue"
},
  "geometry": {"coordinates":[-118.233114,34.033476],"type":"Point"}
}