{
  "type": "Feature",
  "properties": {
    "iso:country":"US",
    "sg:address":"151 E Evelyn Ave",
    "sg:city":"Mountain View",
    "sg:classifiers":[
        {
            "category":"Retail",
            "subcategory":"Auto Repair",
            "type":"Services"
        }
    ],
    "sg:phone":"+1 650 960 0755",
    "sg:postcode":"94041",
    "sg:province":"CA",
    "sg:tags":[
        "body",
        "shop"
    ],
    "sg:website":"www.evelynautobody.com",
    "wof:name":"Evelyn Auto Body",
    "wof:placetype":"venue"
},
  "geometry": {"coordinates":[-122.064843,37.389029],"type":"Point"}
}