{
  "type": "Feature",
  "properties": {
    "iso:country":"US",
    "sg:address":"127 E Main St Ste 1203",
    "sg:city":"Alhambra",
    "sg:classifiers":[
        {
            "category":"Shopping",
            "subcategory":"Clothing, Apparel, & Fashions",
            "type":"Retail Goods"
        }
    ],
    "sg:phone":"+1 213 489 4789",
    "sg:postcode":"91801",
    "sg:province":"CA",
    "sg:tags":[
        "clothing",
        "women's"
    ],
    "sg:website":"www.agenticonfashion.com",
    "wof:name":"Agent Icon Showroom",
    "wof:placetype":"venue"
},
  "geometry": {"coordinates":[-118.125122,34.096285],"type":"Point"}
}