{
  "type": "Feature",
  "properties": {
    "iso:country":"US",
    "sg:address":"220 Montgomery Street",
    "sg:city":"San Francisco",
    "sg:classifiers":[
        {
            "category":"Professional",
            "subcategory":"Lawyer & Legal Services",
            "type":"Services"
        }
    ],
    "sg:phone":"+1 415 291 0919",
    "sg:postcode":"94104",
    "sg:province":"CA",
    "wof:name":"Bosque Wm F Atty Jr",
    "wof:placetype":"venue"
},
  "geometry": {"coordinates":[-122.402393,37.791205],"type":"Point"}
}