{
  "type": "Feature",
  "properties": {
    "iso:country":"US",
    "sg:address":"634 Vernon St",
    "sg:city":"Roseville",
    "sg:classifiers":[
        {
            "category":"Wholesale",
            "subcategory":"Home Furnishings",
            "type":"Manufacturing & Wholesale Goods"
        }
    ],
    "sg:phone":"+1 916 786 2787",
    "sg:postcode":"95678",
    "sg:province":"CA",
    "sg:tags":[
        "picture",
        "frame"
    ],
    "wof:name":"Art Talks",
    "wof:placetype":"venue"
},
  "geometry": {"coordinates":[-121.288396,38.745719],"type":"Point"}
}