{
  "type": "Feature",
  "properties": {
    "addr:full":"8619 Avalon Blvd Los Angeles CA 90003",
    "addr:housenumber":"8619",
    "addr:postcode":"90003",
    "addr:street":"Avalon Blvd",
    "iso:country":"US",
    "sg:address":"8619 Avalon Blvd",
    "sg:city":"Los Angeles",
    "sg:classifiers":[
        {
            "category":"Organizations",
            "subcategory":"Religious Organization",
            "type":"Services"
        }
    ],
    "sg:phone":"+1 323 759 8271",
    "sg:postcode":"90003",
    "sg:province":"CA",
    "sg:tags":[
        "church"
    ],
    "wof:name":"St Paul Calvary",
    "wof:placetype":"venue"
},
  "geometry": {"coordinates":[-118.265196,33.95939],"type":"Point"}
}