{
  "type": "Feature",
  "properties": {
    "iso:country":"US",
    "sg:address":"33733 Yucaipa Blvd",
    "sg:city":"Yucaipa",
    "sg:classifiers":[
        {
            "category":"Health Services",
            "subcategory":"Chiropractor",
            "type":"Services"
        }
    ],
    "sg:phone":"+1 909 797 1705",
    "sg:postcode":"92399",
    "sg:province":"CA",
    "wof:name":"Wethey Dan DC",
    "wof:placetype":"venue"
},
  "geometry": {"coordinates":[-117.06864400000001,34.033456],"type":"Point"}
}