{
  "type": "Feature",
  "properties": {
    "iso:country":"US",
    "sg:address":"7955 Watt Ave",
    "sg:city":"Antelope",
    "sg:classifiers":[
        {
            "category":"Animal Shelter",
            "type":"Public Place"
        },
        {
            "category":"Retail",
            "subcategory":"Veterinary Services",
            "type":"Services"
        },
        {
            "category":"Retail",
            "subcategory":"Pet Boarding",
            "type":"Services"
        }
    ],
    "sg:phone":"+1 916 349 2755",
    "sg:postcode":"95843",
    "sg:province":"CA",
    "sg:tags":[
        "emergency",
        "hospital",
        "clinic",
        "veterinarian",
        "kennel"
    ],
    "sg:website":"http://www.cherrycreek.vetsuite.com",
    "wof:name":"Cherry Creek Veterinary Hospital",
    "wof:placetype":"venue"
},
  "geometry": {"coordinates":[-121.392157,38.713014],"type":"Point"}
}