{
  "type": "Feature",
  "properties": {
    "addr:full":"4868 Telegraph Ave Oakland CA 94609",
    "addr:housenumber":"4868",
    "addr:postcode":"94609",
    "addr:street":"Telegraph Ave",
    "iso:country":"US",
    "sg:address":"4868 Telegraph Ave",
    "sg:city":"Oakland",
    "sg:classifiers":[
        {
            "category":"Professional",
            "type":"Services"
        }
    ],
    "sg:phone":"+1 510 465 5155",
    "sg:postcode":"94609",
    "sg:province":"CA",
    "wof:name":"Ernie Pressman",
    "wof:placetype":"venue"
},
  "geometry": {"coordinates":[-122.26263400000001,37.835919],"type":"Point"}
}