{
  "type": "Feature",
  "properties": {
    "iso:country":"US",
    "sg:address":"1296 Fair Ave",
    "sg:city":"Santa Cruz",
    "sg:classifiers":[
        {
            "category":"Building & Trades",
            "subcategory":"Landscaping Services",
            "type":"Services"
        },
        {
            "category":"Building & Trades",
            "subcategory":"Construction",
            "type":"Services"
        }
    ],
    "sg:phone":"+1 831 234 7555",
    "sg:postcode":"95060",
    "sg:province":"CA",
    "sg:tags":[
        "interior",
        "design",
        "contractor"
    ],
    "sg:website":"www.counterbalanceart.com/projec...",
    "wof:name":"Counter Balance",
    "wof:placetype":"venue"
},
  "geometry": {"coordinates":[-122.046188,36.960515],"type":"Point"}
}