{
  "type": "Feature",
  "properties": {
    "addr:full":"9599 Garden Grove Blvd Garden Grove CA 92844",
    "addr:housenumber":"9599",
    "addr:postcode":"92844",
    "addr:street":"Garden Grove Blvd",
    "iso:country":"US",
    "sg:address":"9599 Garden Grove Blvd",
    "sg:city":"Garden Grove",
    "sg:classifiers":[
        {
            "category":"Manufacturing",
            "subcategory":"Printing",
            "type":"Manufacturing & Wholesale Goods"
        }
    ],
    "sg:phone":"+1 714 539 2068",
    "sg:postcode":"92844",
    "sg:province":"CA",
    "sg:tags":[
        "lithographic",
        "commercial"
    ],
    "wof:name":"US Speedy Printing",
    "wof:placetype":"venue"
},
  "geometry": {"coordinates":[-117.96510600000001,33.773906],"type":"Point"}
}