{
  "type": "Feature",
  "properties": {
    "addr:full":"801 Mira Grande Palm Springs CA 92262",
    "addr:housenumber":"801",
    "addr:postcode":"92262",
    "addr:street":"Mira Grande",
    "iso:country":"US",
    "sg:address":"801 Mira Grande",
    "sg:city":"Palm Springs",
    "sg:classifiers":[
        {
            "category":"Sports & Exercise",
            "subcategory":"Swimming Pool",
            "type":"Entertainment"
        }
    ],
    "sg:phone":"+1 760 218 4696",
    "sg:postcode":"92262",
    "sg:province":"CA",
    "wof:name":"Pool Care Solutions",
    "wof:placetype":"venue"
},
  "geometry": {"coordinates":[-116.557514,33.864644],"type":"Point"}
}