{
  "type": "Feature",
  "properties": {
    "addr:full":"21729 Vanowen St Canoga Park CA 91303",
    "addr:postcode":"21729;91303",
    "addr:street":"Vanowen St",
    "iso:country":"US",
    "sg:address":"21729 Vanowen St",
    "sg:city":"Canoga Park",
    "sg:classifiers":[
        {
            "category":"Home & Garden",
            "subcategory":"Building Materials",
            "type":"Retail Goods"
        }
    ],
    "sg:phone":"+1 818 673 1927",
    "sg:postcode":"91303",
    "sg:province":"CA",
    "sg:tags":[
        "windows"
    ],
    "wof:name":"Allbrand Windows",
    "wof:placetype":"venue"
},
  "geometry": {"coordinates":[-118.60253,34.193828],"type":"Point"}
}