{
  "type": "Feature",
  "properties": {
    "addr:full":"78321 US Hwy 111 La Quinta CA 92253",
    "addr:housenumber":"78321",
    "addr:postcode":"92253",
    "addr:street":"Us Hwy 111",
    "iso:country":"US",
    "sg:address":"78321 US Hwy 111",
    "sg:city":"La Quinta",
    "sg:classifiers":[
        {
            "category":"Food & Beverages",
            "subcategory":"Specialty",
            "type":"Retail Goods"
        }
    ],
    "sg:phone":"+1 760 564 5569",
    "sg:postcode":"92253",
    "sg:province":"CA",
    "sg:tags":[
        "health",
        "diet"
    ],
    "wof:name":"Lifestyles Nutrition Ctr",
    "wof:placetype":"venue"
},
  "geometry": {"coordinates":[-116.29595999999999,33.715541],"type":"Point"}
}