{
  "type": "Feature",
  "properties": {
    "addr:full":"4803 N Brightview Dr Covina CA 91722",
    "addr:housenumber":"4803",
    "addr:postcode":"91722",
    "addr:street":"N Brightview Dr",
    "iso:country":"US",
    "sg:address":"4803 N Brightview Dr",
    "sg:city":"Covina",
    "sg:classifiers":[
        {
            "category":"Building & Trades",
            "subcategory":"Landscaping Services",
            "type":"Services"
        }
    ],
    "sg:phone":"+1 626 858 9102",
    "sg:postcode":"91722",
    "sg:province":"CA",
    "wof:name":"Able Gardening",
    "wof:placetype":"venue"
},
  "geometry": {"coordinates":[-117.87567300000001,34.102868],"type":"Point"}
}