{
  "type": "Feature",
  "properties": {
    "iso:country":"US",
    "sg:address":"1565 El Camino Real",
    "sg:city":"South San Francisco",
    "sg:classifiers":[
        {
            "category":"Real Estate",
            "subcategory":"Real Estate Operator",
            "type":"Services"
        }
    ],
    "sg:phone":"+1 650 616 4570",
    "sg:postcode":"94080",
    "sg:province":"CA",
    "sg:tags":[
        "apartment"
    ],
    "wof:name":"Greenridge Apts",
    "wof:placetype":"venue"
},
  "geometry": {"coordinates":[-122.448318,37.663838],"type":"Point"}
}