{
  "type": "Feature",
  "properties": {
    "iso:country":"US",
    "sg:address":"8023 Naylor Ave",
    "sg:city":"Los Angeles",
    "sg:classifiers":[
        {
            "category":"Manufacturing",
            "subcategory":"Tools & Machinery",
            "type":"Manufacturing & Wholesale Goods"
        }
    ],
    "sg:phone":"+1 310 337 2929",
    "sg:postcode":"90045",
    "sg:province":"CA",
    "sg:tags":[
        "electrostatic",
        "shielding"
    ],
    "wof:name":"Miller Enterprises",
    "wof:placetype":"venue"
},
  "geometry": {"coordinates":[-118.395461,33.965272],"type":"Point"}
}