{
  "type": "Feature",
  "properties": {
    "iso:country":"US",
    "sg:address":"17 Pendegast St",
    "sg:city":"Woodland",
    "sg:classifiers":[
        {
            "category":"Building & Trades",
            "subcategory":"Construction",
            "type":"Services"
        }
    ],
    "sg:phone":"+1 530 908 7338",
    "sg:postcode":"95695",
    "sg:province":"CA",
    "sg:tags":[
        "handyman"
    ],
    "wof:name":"Brother's Home Repair",
    "wof:placetype":"venue"
},
  "geometry": {"coordinates":[-121.782022,38.670275],"type":"Point"}
}