{
  "type": "Feature",
  "properties": {
    "iso:country":"US",
    "sg:address":"2420 Sutter St",
    "sg:city":"San Francisco",
    "sg:classifiers":[
        {
            "category":"Health Services",
            "subcategory":"Doctor",
            "type":"Services"
        }
    ],
    "sg:phone":"+1 415 567 0100",
    "sg:postcode":"94115",
    "sg:province":"CA",
    "sg:tags":[
        "physician",
        "surgeon"
    ],
    "wof:name":"Morris D Brock MD",
    "wof:placetype":"venue"
},
  "geometry": {"coordinates":[-122.44128000000001,37.785153],"type":"Point"}
}