{
  "type": "Feature",
  "properties": {
    "iso:country":"US",
    "sg:address":"1111 E Ramon Rd",
    "sg:city":"Palm Springs",
    "sg:classifiers":[
        {
            "category":"Organizations",
            "subcategory":"Professional Association",
            "type":"Services"
        }
    ],
    "sg:phone":"+1 760 323 7703",
    "sg:postcode":"92264",
    "sg:province":"CA",
    "wof:name":"Ramona Villa Homeowners Assn",
    "wof:placetype":"venue"
},
  "geometry": {"coordinates":[-116.534485,33.815844],"type":"Point"}
}