{
  "type": "Feature",
  "properties": {
    "iso:country":"US",
    "sg:address":"1532 Chanslor Ave",
    "sg:city":"Richmond",
    "sg:classifiers":[
        {
            "category":"Banks & Credit Unions",
            "subcategory":"Bank",
            "type":"Services"
        }
    ],
    "sg:phone":"+1 510 236 2671",
    "sg:postcode":"94801",
    "sg:province":"CA",
    "sg:tags":[
        "loan",
        "real estate"
    ],
    "wof:name":"J B Mortgage Co",
    "wof:placetype":"venue"
},
  "geometry": {"coordinates":[-122.354548,37.932395],"type":"Point"}
}