{
  "type": "Feature",
  "properties": {
    "iso:country":"US",
    "sg:address":"606 S Olive St",
    "sg:city":"Los Angeles",
    "sg:classifiers":[
        {
            "category":"Wholesale",
            "subcategory":"Jewelry",
            "type":"Manufacturing & Wholesale Goods"
        }
    ],
    "sg:phone":"+1 213 488 3488",
    "sg:postcode":"90014",
    "sg:province":"CA",
    "sg:tags":[
        "diamond"
    ],
    "wof:name":"Nour Diamond Inc",
    "wof:placetype":"venue"
},
  "geometry": {"coordinates":[-118.25539499999999,34.046642],"type":"Point"}
}