{
  "type": "Feature",
  "properties": {
    "addr:full":"970 El Camino Ave Sacramento CA 95815",
    "addr:housenumber":"970",
    "addr:postcode":"95815",
    "addr:street":"El Camino Ave",
    "iso:country":"US",
    "sg:address":"970 El Camino Ave",
    "sg:city":"Sacramento",
    "sg:classifiers":[
        {
            "category":"Autos & Motor Vehicles",
            "subcategory":"Fuel & Gas Station",
            "type":"Retail Goods"
        }
    ],
    "sg:phone":"+1 800 255 8677",
    "sg:postcode":"95815",
    "sg:province":"CA",
    "wof:name":"Mobile Living Rv & Camper Shell Center",
    "wof:placetype":"venue"
},
  "geometry": {"coordinates":[-121.44454399999999,38.611114],"type":"Point"}
}