{
  "type": "Feature",
  "properties": {
    "addr:full":"2450 Venture Oaks Way Ste 100 Sacramento CA 95833",
    "addr:housenumber":"2450",
    "addr:postcode":"95833",
    "addr:street":"Venture Oaks Way Ste 100",
    "iso:country":"US",
    "sg:address":"2450 Venture Oaks Way Ste 100",
    "sg:city":"Sacramento",
    "sg:classifiers":[
        {
            "category":"Professional",
            "subcategory":"Business Services",
            "type":"Services"
        }
    ],
    "sg:phone":"+1 916 924 8092",
    "sg:postcode":"95833",
    "sg:province":"CA",
    "sg:tags":[
        "organizing",
        "medical",
        "administration",
        "services-household"
    ],
    "sg:website":"http://www.ehealthline.com",
    "wof:name":"Healthline Inc",
    "wof:placetype":"venue"
},
  "geometry": {"coordinates":[-121.512007,38.608244],"type":"Point"}
}