{
  "type": "Feature",
  "properties": {
    "iso:country":"US",
    "sg:address":"525 2nd St",
    "sg:city":"Eureka",
    "sg:classifiers":[
        {
            "category":"Banks & Credit Unions",
            "subcategory":"Investment Brokerage",
            "type":"Services"
        }
    ],
    "sg:phone":"+1 707 444 3420",
    "sg:postcode":"95501",
    "sg:province":"CA",
    "wof:name":"FKS Investments Co",
    "wof:placetype":"venue"
},
  "geometry": {"coordinates":[-124.165682,40.804569],"type":"Point"}
}