{
  "type": "Feature",
  "properties": {
    "addr:full":"7255 State Hwy 32 Orland CA 95963",
    "addr:housenumber":"7255",
    "addr:postcode":"95963",
    "addr:street":"State Hwy 32",
    "iso:country":"US",
    "sg:address":"7255 State Hwy 32",
    "sg:city":"Orland",
    "sg:classifiers":[
        {
            "category":"Building & Trades",
            "subcategory":"Plumbing",
            "type":"Services"
        }
    ],
    "sg:phone":"+1 530 865 3093",
    "sg:postcode":"95963",
    "sg:province":"CA",
    "sg:tags":[
        "conditioning",
        "air",
        "system",
        "contractor"
    ],
    "wof:name":"Air-Con Energy",
    "wof:placetype":"venue"
},
  "geometry": {"coordinates":[-122.11376199999999,39.746689],"type":"Point"}
}