{
  "type": "Feature",
  "properties": {
    "iso:country":"US",
    "sg:address":"820 W Pacheco Blvd",
    "sg:city":"Los Banos",
    "sg:classifiers":[
        {
            "category":"Retail",
            "subcategory":"Auto Repair",
            "type":"Services"
        }
    ],
    "sg:phone":"+1 209 827 6898",
    "sg:postcode":"93635",
    "sg:province":"CA",
    "sg:tags":[
        "repairing",
        "automobile"
    ],
    "wof:name":"Advance Auto Svc Ctr",
    "wof:placetype":"venue"
},
  "geometry": {"coordinates":[-120.863176,37.056947],"type":"Point"}
}