{
  "type": "Feature",
  "properties": {
    "addr:full":"384 Grand Ave Oakland CA 94610",
    "addr:housenumber":"384",
    "addr:postcode":"94610",
    "addr:street":"Grand Ave",
    "iso:country":"US",
    "sg:address":"384 Grand Ave",
    "sg:city":"Oakland",
    "sg:classifiers":[
        {
            "category":"Restaurant",
            "type":"Food & Drink"
        }
    ],
    "sg:menulink":"http://www.allmenus.com/ca/oakland/283179-grand-avenue-thai-cuisine/menu/",
    "sg:phone":"+1 510 444 1507",
    "sg:postcode":"94610",
    "sg:province":"CA",
    "sg:tags":[
        "thai",
        "asian"
    ],
    "wof:name":"Grand Avenue Thai Cuisine",
    "wof:placetype":"venue"
},
  "geometry": {"coordinates":[-122.25468499999999,37.808846],"type":"Point"}
}