{
  "type": "Feature",
  "properties": {
    "addr:full":"2537 W Coast Hwy Newport Beach CA 92663",
    "addr:housenumber":"2537",
    "addr:postcode":"92663",
    "addr:street":"W Coast Hwy",
    "iso:country":"US",
    "sg:address":"2537 W Coast Hwy",
    "sg:city":"Newport Beach",
    "sg:classifiers":[
        {
            "category":"Wholesale",
            "subcategory":"Electrical",
            "type":"Manufacturing & Wholesale Goods"
        }
    ],
    "sg:phone":"+1 949 631 8835",
    "sg:postcode":"92663",
    "sg:province":"CA",
    "sg:tags":[
        "communications",
        "equipment"
    ],
    "wof:name":"Phantom Marine",
    "wof:placetype":"venue"
},
  "geometry": {"coordinates":[-117.91283799999999,33.615874],"type":"Point"}
}