{
  "type": "Feature",
  "properties": {
    "addr:full":"501 W Weber Ave Stockton CA 95203",
    "addr:housenumber":"501",
    "addr:postcode":"95203",
    "addr:street":"W Weber Ave",
    "iso:country":"US",
    "sg:address":"501 W Weber Ave",
    "sg:city":"Stockton",
    "sg:classifiers":[
        {
            "category":"Professional",
            "subcategory":"Computer Services",
            "type":"Services"
        }
    ],
    "sg:phone":"+1 209 462 2791",
    "sg:postcode":"95203",
    "sg:province":"CA",
    "wof:name":"Quality Computer Svc Inc",
    "wof:placetype":"venue"
},
  "geometry": {"coordinates":[-121.29784100000001,37.952363],"type":"Point"}
}