{
  "type": "Feature",
  "properties": {
    "addr:full":"2187 Sampson Ave Corona CA 92879",
    "addr:housenumber":"2187",
    "addr:postcode":"92879",
    "addr:street":"Sampson Ave",
    "iso:country":"US",
    "sg:address":"2187 Sampson Ave",
    "sg:city":"Corona",
    "sg:classifiers":[
        {
            "category":"Retail",
            "subcategory":"Auto Repair",
            "type":"Services"
        }
    ],
    "sg:phone":"+1 951 736 1818",
    "sg:postcode":"92879",
    "sg:province":"CA",
    "sg:tags":[
        "truck"
    ],
    "wof:name":"One Way Transmission",
    "wof:placetype":"venue"
},
  "geometry": {"coordinates":[-117.518488,33.883528],"type":"Point"}
}