{
  "type": "Feature",
  "properties": {
    "addr:full":"6625 Santa Fe Avenue Huntington Park CA 90255",
    "addr:housenumber":"6625",
    "addr:postcode":"90255",
    "addr:street":"Santa Fe Avenue;Park",
    "iso:country":"US",
    "sg:address":"6625 Santa Fe Avenue",
    "sg:city":"Huntington Park",
    "sg:classifiers":[
        {
            "category":"Restaurant",
            "type":"Food & Drink"
        }
    ],
    "sg:phone":"+1 323 589 8988",
    "sg:postcode":"90255",
    "sg:province":"CA",
    "wof:name":"John's Drive Inn Hamburger",
    "wof:placetype":"venue"
},
  "geometry": {"coordinates":[-118.23012300000001,33.978855],"type":"Point"}
}