{
  "type": "Feature",
  "properties": {
    "addr:full":"401 E 7th St Los Angeles CA 90014",
    "addr:housenumber":"401",
    "addr:postcode":"90014",
    "addr:street":"E 7Th St",
    "iso:country":"US",
    "sg:address":"401 E 7th St",
    "sg:city":"Los Angeles",
    "sg:classifiers":[
        {
            "category":"Wholesale",
            "subcategory":"Apparel",
            "type":"Manufacturing & Wholesale Goods"
        }
    ],
    "sg:phone":"+1 213 689 7788",
    "sg:postcode":"90014",
    "sg:province":"CA",
    "sg:tags":[
        "clothing"
    ],
    "wof:name":"Sunnylon Inc",
    "wof:placetype":"venue"
},
  "geometry": {"coordinates":[-118.247474,34.0412],"type":"Point"}
}