{
  "type": "Feature",
  "properties": {
    "addr:full":"3333 Harding St Carlsbad CA 92008",
    "addr:housenumber":"3333",
    "addr:postcode":"92008",
    "addr:street":"Harding St",
    "iso:country":"US",
    "sg:address":"3333 Harding St",
    "sg:city":"Carlsbad",
    "sg:classifiers":[
        {
            "category":"Education",
            "subcategory":"Library",
            "type":"Public Place"
        }
    ],
    "sg:phone":"+1 760 729 6907",
    "sg:postcode":"92008",
    "sg:province":"CA",
    "wof:name":"Carlsbad Library",
    "wof:placetype":"venue"
},
  "geometry": {"coordinates":[-117.3426,33.159386],"type":"Point"}
}