{
  "type": "Feature",
  "properties": {
    "addr:full":"5215 E Beverly Blvd Los Angeles CA 90022",
    "addr:housenumber":"5215",
    "addr:postcode":"90022",
    "addr:street":"E Beverly Blvd",
    "iso:country":"US",
    "sg:address":"5215 E Beverly Blvd",
    "sg:city":"Los Angeles",
    "sg:classifiers":[
        {
            "category":"Professional",
            "subcategory":"Business Services",
            "type":"Services"
        }
    ],
    "sg:phone":"+1 323 728 2868",
    "sg:postcode":"90022",
    "sg:province":"CA",
    "sg:tags":[
        "license"
    ],
    "wof:name":"California Vehicle Registratin",
    "wof:placetype":"venue"
},
  "geometry": {"coordinates":[-118.15356199999999,34.032061],"type":"Point"}
}