{
  "type": "Feature",
  "properties": {
    "iso:country":"US",
    "sg:address":"881 Sunnyslope Rd",
    "sg:city":"Hollister",
    "sg:classifiers":[
        {
            "category":"Real Estate",
            "subcategory":"Real Estate Operator",
            "type":"Services"
        }
    ],
    "sg:phone":"+1 831 637 4609",
    "sg:postcode":"95023",
    "sg:province":"CA",
    "sg:tags":[
        "apartment"
    ],
    "wof:name":"Granada Court Apartments",
    "wof:placetype":"venue"
},
  "geometry": {"coordinates":[-121.386726,36.83913],"type":"Point"}
}