{
  "type": "Feature",
  "properties": {
    "addr:full":"906 Lake St Huntington Beach CA 92648",
    "addr:housenumber":"906",
    "addr:postcode":"92648",
    "addr:street":"Lake St",
    "iso:country":"US",
    "sg:address":"906 Lake St",
    "sg:city":"Huntington Beach",
    "sg:classifiers":[
        {
            "category":"Wholesale",
            "subcategory":"Jewelry",
            "type":"Manufacturing & Wholesale Goods"
        }
    ],
    "sg:phone":"+1 714 969 0200",
    "sg:postcode":"92648",
    "sg:province":"CA",
    "sg:tags":[
        "stone"
    ],
    "wof:name":"Wittya Yupin",
    "wof:placetype":"venue"
},
  "geometry": {"coordinates":[-117.99787999999999,33.66844],"type":"Point"}
}