{
  "type": "Feature",
  "properties": {
    "iso:country":"US",
    "sg:address":"1601 Hillhurst Ave",
    "sg:city":"Los Angeles",
    "sg:classifiers":[
        {
            "category":"Government",
            "subcategory":"Fire Station",
            "type":"Public Place"
        }
    ],
    "sg:phone":"+1 213 485 6235",
    "sg:postcode":"90027",
    "sg:province":"CA",
    "sg:tags":[
        "protection"
    ],
    "wof:name":"Fire Dept-Station 35",
    "wof:placetype":"venue"
},
  "geometry": {"coordinates":[-118.2874,34.100885],"type":"Point"}
}