{
  "type": "Feature",
  "properties": {
    "iso:country":"US",
    "sg:address":"1025 Holly Ln",
    "sg:city":"Carpinteria",
    "sg:classifiers":[
        {
            "category":"Personal",
            "type":"Services"
        },
        {
            "category":"Retail",
            "subcategory":"Storage",
            "type":"Services"
        }
    ],
    "sg:phone":"+1 805 684 3347",
    "sg:postcode":"93013",
    "sg:province":"CA",
    "sg:tags":[
        "mover",
        "self"
    ],
    "wof:name":"Budget Rent-A-Car System Inc",
    "wof:placetype":"venue"
},
  "geometry": {"coordinates":[-119.519997,34.4011],"type":"Point"}
}