{
  "type": "Feature",
  "properties": {
    "addr:full":"153 E 5th Ave San Mateo CA 94497",
    "addr:housenumber":"153",
    "addr:postcode":"94497",
    "addr:street":"E 5Th Ave",
    "iso:country":"US",
    "sg:address":"153 E 5th Ave",
    "sg:city":"San Mateo",
    "sg:classifiers":[
        {
            "category":"Personal",
            "subcategory":"Beauty Salon",
            "type":"Services"
        }
    ],
    "sg:phone":"+1 650 342 3211",
    "sg:postcode":"94497",
    "sg:province":"CA",
    "sg:tags":[
        "hair"
    ],
    "wof:name":"Renew Salon",
    "wof:placetype":"venue"
},
  "geometry": {"coordinates":[-122.322126,37.563525],"type":"Point"}
}