{
  "type": "Feature",
  "properties": {
    "iso:country":"US",
    "sg:address":"6080 Center Dr",
    "sg:city":"Los Angeles",
    "sg:classifiers":[
        {
            "category":"Professional",
            "subcategory":"Lawyer & Legal Services",
            "type":"Services"
        }
    ],
    "sg:phone":"+1 310 215 7509",
    "sg:postcode":"90045",
    "sg:province":"CA",
    "sg:website":"www.stanleygreenberg.com",
    "wof:name":"Greenberg Stanley I",
    "wof:placetype":"venue"
},
  "geometry": {"coordinates":[-118.392998,33.978001],"type":"Point"}
}