{
  "type": "Feature",
  "properties": {
    "addr:full":"449 Stony Point Rd Santa Rosa CA 95401",
    "addr:housenumber":"449",
    "addr:postcode":"95401",
    "addr:street":"Stony Point Rd",
    "iso:country":"US",
    "sg:address":"449 Stony Point Rd",
    "sg:city":"Santa Rosa",
    "sg:classifiers":[
        {
            "category":"Restaurant",
            "type":"Food & Drink"
        }
    ],
    "sg:menulink":"http://www.allmenus.com/ca/santa-rosa/74293-dominos-pizza/menu/",
    "sg:phone":"+1 707 545 8111",
    "sg:postcode":"95401",
    "sg:province":"CA",
    "sg:tags":[
        "american",
        "wing",
        "pizza"
    ],
    "wof:name":"Domino's Pizza",
    "wof:placetype":"venue"
},
  "geometry": {"coordinates":[-122.741846,38.431883],"type":"Point"}
}