{
  "type": "Feature",
  "properties": {
    "iso:country":"US",
    "sg:address":"4933 Durfee Ave",
    "sg:city":"Pico Rivera",
    "sg:classifiers":[
        {
            "category":"Freight",
            "type":"Transportation"
        }
    ],
    "sg:phone":"+1 562 692 5868",
    "sg:postcode":"90660",
    "sg:province":"CA",
    "sg:tags":[
        "water",
        "arr"
    ],
    "wof:name":"Amerasia Shipping Line Inc",
    "wof:placetype":"venue"
},
  "geometry": {"coordinates":[-118.079253,33.999853],"type":"Point"}
}