{
  "type": "Feature",
  "properties": {
    "addr:full":"7401 Jordan Ave Canoga Park CA 91303",
    "addr:housenumber":"7401",
    "addr:postcode":"91303",
    "addr:street":"Jordan Ave",
    "iso:country":"US",
    "sg:address":"7401 Jordan Ave",
    "sg:city":"Canoga Park",
    "sg:classifiers":[
        {
            "category":"Professional",
            "type":"Services"
        }
    ],
    "sg:phone":"+1 818 609 0310",
    "sg:postcode":"91303",
    "sg:province":"CA",
    "sg:tags":[
        "caterer"
    ],
    "sg:website":"www.belladonnacatering.com",
    "wof:name":"Bella Donna Halls & Catering",
    "wof:placetype":"venue"
},
  "geometry": {"coordinates":[-118.603025,34.204649],"type":"Point"}
}