{
  "type": "Feature",
  "properties": {
    "iso:country":"US",
    "sg:address":"3809 San Fernando Rd",
    "sg:city":"Glendale",
    "sg:classifiers":[
        {
            "category":"Retail",
            "subcategory":"Auto Rental",
            "type":"Services"
        }
    ],
    "sg:phone":"+1 818 243 3151",
    "sg:postcode":"91204",
    "sg:province":"CA",
    "sg:tags":[
        "renting",
        "truck",
        "leasing"
    ],
    "wof:name":"Suppose-U-Drive Truck Rental",
    "wof:placetype":"venue"
},
  "geometry": {"coordinates":[-118.25700000000001,34.125828],"type":"Point"}
}