{
  "type": "Feature",
  "properties": {
    "addr:full":"2845 W Pomona Blvd Pomona CA 91768",
    "addr:housenumber":"2845",
    "addr:postcode":"91768",
    "addr:street":"W Pomona Blvd",
    "iso:country":"US",
    "sg:address":"2845 W Pomona Blvd",
    "sg:city":"Pomona",
    "sg:classifiers":[
        {
            "category":"Wholesale",
            "subcategory":"Machinery & Supplies",
            "type":"Manufacturing & Wholesale Goods"
        }
    ],
    "sg:phone":"+1 909 718 0800",
    "sg:postcode":"91768",
    "sg:province":"CA",
    "sg:tags":[
        "hoist"
    ],
    "wof:name":"Trademark Hoist & Crane",
    "wof:placetype":"venue"
},
  "geometry": {"coordinates":[-117.802558,34.052944],"type":"Point"}
}