{
  "type": "Feature",
  "properties": {
    "iso:country":"US",
    "sg:address":"23861 McBean Pkwy",
    "sg:city":"Valencia",
    "sg:classifiers":[
        {
            "category":"Health Services",
            "subcategory":"Doctor",
            "type":"Services"
        }
    ],
    "sg:phone":"+1 661 222 7600",
    "sg:postcode":"91355",
    "sg:province":"CA",
    "sg:tags":[
        "physician",
        "surgeon"
    ],
    "wof:name":"Pacific West Dermatology",
    "wof:placetype":"venue"
},
  "geometry": {"coordinates":[-118.553141,34.396187],"type":"Point"}
}