{
  "type": "Feature",
  "properties": {
    "iso:country":"US",
    "sg:address":"580 N Rengstorff Ave",
    "sg:city":"Mountain View",
    "sg:classifiers":[
        {
            "category":"Food & Beverages",
            "subcategory":"Groceries & Convenience Stores",
            "type":"Retail Goods"
        }
    ],
    "sg:phone":"+1 650 966 8988",
    "sg:postcode":"94043",
    "sg:province":"CA",
    "sg:tags":[
        "grocer"
    ],
    "wof:name":"Golden Phoenix",
    "wof:placetype":"venue"
},
  "geometry": {"coordinates":[-122.092844,37.411053],"type":"Point"}
}