{
  "type": "Feature",
  "properties": {
    "iso:country":"US",
    "sg:address":"274 S Rampart Boulevard",
    "sg:city":"Los Angeles",
    "sg:classifiers":[
        {
            "category":"Health Services",
            "subcategory":"Dentist",
            "type":"Services"
        }
    ],
    "sg:phone":"+1 213 383 6656",
    "sg:postcode":"90057",
    "sg:province":"CA",
    "wof:name":"Satter Mohammed DDS",
    "wof:placetype":"venue"
},
  "geometry": {"coordinates":[-118.278862,34.066489],"type":"Point"}
}