{
  "type": "Feature",
  "properties": {
    "addr:full":"1364 Santa Paula Ave San Jose CA 95110",
    "addr:housenumber":"1364",
    "addr:postcode":"95110",
    "addr:street":"Santa Paula Ave",
    "iso:country":"US",
    "sg:address":"1364 Santa Paula Ave",
    "sg:city":"San Jose",
    "sg:classifiers":[
        {
            "category":"Shopping",
            "subcategory":"Musical Instruments",
            "type":"Retail Goods"
        }
    ],
    "sg:phone":"+1 408 452 8153",
    "sg:postcode":"95110",
    "sg:province":"CA",
    "wof:name":"Guitar Slim",
    "wof:placetype":"venue"
},
  "geometry": {"coordinates":[-121.912644,37.358865],"type":"Point"}
}