{
  "type": "Feature",
  "properties": {
    "iso:country":"US",
    "sg:address":"9595 Wilshire Blvd Ste 900",
    "sg:city":"Beverly Hills",
    "sg:classifiers":[
        {
            "category":"Professional",
            "subcategory":"Lawyer & Legal Services",
            "type":"Services"
        }
    ],
    "sg:phone":"+1 310 300 4021",
    "sg:postcode":"90212",
    "sg:province":"CA",
    "sg:tags":[
        "divorce",
        "law",
        "family"
    ],
    "sg:website":"www.cnortonlaw.com",
    "wof:name":"Law Office of Cathleen E. Norton",
    "wof:placetype":"venue"
},
  "geometry": {"coordinates":[-118.402597,34.067621],"type":"Point"}
}