{
  "type": "Feature",
  "properties": {
    "addr:full":"5449 Dudley Ct Pleasanton CA 94566",
    "addr:housenumber":"5449",
    "addr:postcode":"94566",
    "addr:street":"Dudley Ct",
    "iso:country":"US",
    "sg:address":"5449 Dudley Ct",
    "sg:city":"Pleasanton",
    "sg:classifiers":[
        {
            "category":"Travel",
            "subcategory":"Travel Agent",
            "type":"Entertainment"
        }
    ],
    "sg:phone":"+1 925 462 8753",
    "sg:postcode":"94566",
    "sg:province":"CA",
    "sg:tags":[
        "agency"
    ],
    "wof:name":"Dynasty Travel Agency",
    "wof:placetype":"venue"
},
  "geometry": {"coordinates":[-121.888818,37.671273],"type":"Point"}
}