{
  "type": "Feature",
  "properties": {
    "addr:full":"40469 Murrieta Hot Springs Rd Murrieta CA 92563",
    "addr:housenumber":"40469",
    "addr:postcode":"92563",
    "addr:street":"Murrieta Hot Springs Rd",
    "iso:country":"US",
    "sg:address":"40469 Murrieta Hot Springs Rd",
    "sg:city":"Murrieta",
    "sg:classifiers":[
        {
            "category":"Restaurant",
            "type":"Food & Drink"
        }
    ],
    "sg:phone":"+1 951 696 7570",
    "sg:postcode":"92563",
    "sg:province":"CA",
    "wof:name":"Hot Wok",
    "wof:placetype":"venue"
},
  "geometry": {"coordinates":[-117.17885200000001,33.556455],"type":"Point"}
}