{
  "type": "Feature",
  "properties": {
    "addr:full":"5009 Yosemite Blvd Modesto CA 95357",
    "addr:housenumber":"5009",
    "addr:postcode":"ca 95357",
    "addr:street":"Yosemite Blvd",
    "iso:country":"US",
    "sg:address":"5009 Yosemite Blvd",
    "sg:city":"Modesto",
    "sg:classifiers":[
        {
            "category":"Food & Beverages",
            "subcategory":"Groceries & Convenience Stores",
            "type":"Retail Goods"
        }
    ],
    "sg:phone":"+1 209 527 2070",
    "sg:postcode":"95357",
    "sg:province":"CA",
    "wof:name":"Cicero's Market",
    "wof:placetype":"venue"
},
  "geometry": {"coordinates":[-120.912003,37.6493],"type":"Point"}
}