{
  "type": "Feature",
  "properties": {
    "iso:country":"US",
    "sg:address":"8747 N Magnolia Ave",
    "sg:city":"Santee",
    "sg:classifiers":[
        {
            "category":"Home & Garden",
            "subcategory":"Furniture",
            "type":"Retail Goods"
        }
    ],
    "sg:phone":"+1 619 590 1141",
    "sg:postcode":"92071",
    "sg:province":"CA",
    "sg:tags":[
        "store"
    ],
    "wof:name":"Anthony Lauren & Co Inc",
    "wof:placetype":"venue"
},
  "geometry": {"coordinates":[-116.964598,32.834216],"type":"Point"}
}