{
  "type": "Feature",
  "properties": {
    "iso:country":"US",
    "sg:address":"3502 W Orange Ave",
    "sg:city":"Anaheim",
    "sg:classifiers":[
        {
            "category":"Sports & Exercise",
            "subcategory":"Golf",
            "type":"Entertainment"
        }
    ],
    "sg:phone":"+1 714 522 2273",
    "sg:postcode":"92804",
    "sg:province":"CA",
    "wof:name":"Tasei Construction Los Coyotes Country Club",
    "wof:placetype":"venue"
},
  "geometry": {"coordinates":[-118.00900300000001,33.824699],"type":"Point"}
}