{
  "type": "Feature",
  "properties": {
    "iso:country":"US",
    "sg:address":"2795 W Lincoln Ave Ste H",
    "sg:city":"Anaheim",
    "sg:classifiers":[
        {
            "category":"Shopping",
            "subcategory":"Pets & Pet Supplies",
            "type":"Retail Goods"
        }
    ],
    "sg:phone":"+1 714 527 7779",
    "sg:postcode":"92801",
    "sg:province":"CA",
    "sg:tags":[
        "store",
        "groomers"
    ],
    "wof:name":"K-9 Karousel",
    "wof:placetype":"venue"
},
  "geometry": {"coordinates":[-117.985001,33.832199],"type":"Point"}
}