{
  "type": "Feature",
  "properties": {
    "iso:country":"US",
    "sg:address":"211 Keystone Way",
    "sg:city":"Santa Cruz",
    "sg:classifiers":[
        {
            "category":"Organizations",
            "subcategory":"Non-profit Organization",
            "type":"Services"
        }
    ],
    "sg:phone":"+1 831 423 1530",
    "sg:postcode":"95060",
    "sg:province":"CA",
    "wof:name":"Paradise Pk Masonic Club Inc",
    "wof:placetype":"venue"
},
  "geometry": {"coordinates":[-122.04429,37.010729],"type":"Point"}
}