{
  "type": "Feature",
  "properties": {
    "iso:country":"US",
    "sg:address":"5340 E Walkerton St",
    "sg:city":"Long Beach",
    "sg:classifiers":[
        {
            "category":"Shopping",
            "subcategory":"Clothing, Apparel, & Fashions",
            "type":"Retail Goods"
        }
    ],
    "sg:phone":"+1 562 429 1856",
    "sg:postcode":"90808",
    "sg:province":"CA",
    "wof:name":"Buck Hull",
    "wof:placetype":"venue"
},
  "geometry": {"coordinates":[-118.128012,33.826549],"type":"Point"}
}