{
  "type": "Feature",
  "properties": {
    "addr:full":"585 Victoria Ct San Leandro CA 94577",
    "addr:housenumber":"585",
    "addr:postcode":"94577",
    "addr:street":"Victoria Ct",
    "iso:country":"US",
    "sg:address":"585 Victoria Ct",
    "sg:city":"San Leandro",
    "sg:classifiers":[
        {
            "category":"Restaurant",
            "type":"Food & Drink"
        }
    ],
    "sg:phone":"+1 510 569 8111",
    "sg:postcode":"94577",
    "sg:province":"CA",
    "sg:tags":[
        "caterer"
    ],
    "wof:name":"Blue Dish Catering & Wrap",
    "wof:placetype":"venue"
},
  "geometry": {"coordinates":[-122.153474,37.736297],"type":"Point"}
}