{
  "type": "Feature",
  "properties": {
    "addr:full":"19 Heron St San Francisco CA 94103",
    "addr:housenumber":"19",
    "addr:postcode":"94103",
    "addr:street":"Heron St",
    "iso:country":"US",
    "sg:address":"19 Heron St",
    "sg:city":"San Francisco",
    "sg:classifiers":[
        {
            "category":"Arts & Performance",
            "subcategory":"Dance",
            "type":"Entertainment"
        }
    ],
    "sg:phone":"+1 415 701 1300",
    "sg:postcode":"94103",
    "sg:province":"CA",
    "sg:tags":[
        "school"
    ],
    "sg:website":"www.studiogracia.com",
    "wof:name":"Studio Gracia",
    "wof:placetype":"venue"
},
  "geometry": {"coordinates":[-122.40799699999999,37.774502],"type":"Point"}
}