{
  "type": "Feature",
  "properties": {
    "iso:country":"US",
    "sg:address":"64 Railway Avenue",
    "sg:city":"Campbell",
    "sg:classifiers":[
        {
            "category":"Retail",
            "subcategory":"Auto Repair",
            "type":"Services"
        }
    ],
    "sg:phone":"+1 408 378 6466",
    "sg:postcode":"95008",
    "sg:province":"CA",
    "wof:name":"F & J Auto Imports",
    "wof:placetype":"venue"
},
  "geometry": {"coordinates":[-121.942544,37.286217],"type":"Point"}
}