{
  "type": "Feature",
  "properties": {
    "iso:country":"US",
    "sg:address":"825 Delbon Ave",
    "sg:city":"Turlock",
    "sg:classifiers":[
        {
            "category":"Health Services",
            "subcategory":"Doctor",
            "type":"Services"
        }
    ],
    "sg:phone":"+1 209 667 4200",
    "sg:postcode":"95382",
    "sg:province":"CA",
    "sg:tags":[
        "physician",
        "surgeon"
    ],
    "sg:website":"http://www.emanuelmedicalcenter.org",
    "wof:name":"Brandel Manor Of Emanuel",
    "wof:placetype":"venue"
},
  "geometry": {"coordinates":[-120.839793,37.51048],"type":"Point"}
}