{
  "type": "Feature",
  "properties": {
    "addr:full":"826 S Winchester Blvd San Jose CA 95128",
    "addr:housenumber":"826",
    "addr:postcode":"95128",
    "addr:street":"S Winchester Blvd",
    "iso:country":"US",
    "sg:address":"826 S Winchester Blvd",
    "sg:city":"San Jose",
    "sg:classifiers":[
        {
            "category":"Restaurant",
            "type":"Food & Drink"
        }
    ],
    "sg:menulink":"http://www.allmenus.com/ca/san-jose/89135-cajun-crab-house/menu/",
    "sg:phone":"+1 408 244 2528",
    "sg:postcode":"95128",
    "sg:province":"CA",
    "sg:tags":[
        "american",
        "creole",
        "cajun"
    ],
    "wof:name":"Cajun Crab House",
    "wof:placetype":"venue"
},
  "geometry": {"coordinates":[-121.94993100000001,37.312526],"type":"Point"}
}