{
  "type": "Feature",
  "properties": {
    "iso:country":"US",
    "sg:address":"14382 State Hwy 20",
    "sg:city":"Clearlake Oaks",
    "sg:classifiers":[
        {
            "category":"Wholesale",
            "subcategory":"Construction Materials",
            "type":"Manufacturing & Wholesale Goods"
        }
    ],
    "sg:phone":"+1 707 998 3346",
    "sg:postcode":"95423",
    "sg:province":"CA",
    "sg:tags":[
        "rock"
    ],
    "wof:name":"Clearlake Cinderchip",
    "wof:placetype":"venue"
},
  "geometry": {"coordinates":[-122.639157,39.015121],"type":"Point"}
}