{
  "type": "Feature",
  "properties": {
    "iso:country":"US",
    "sg:address":"430 E Foothill Blvd",
    "sg:city":"San Dimas",
    "sg:classifiers":[
        {
            "category":"Insurance",
            "subcategory":"Insurance Agent",
            "type":"Services"
        }
    ],
    "sg:phone":"+1 909 599 5131",
    "sg:postcode":"91773",
    "sg:province":"CA",
    "wof:name":"Farmers Insurance Group",
    "wof:placetype":"venue"
},
  "geometry": {"coordinates":[-117.798953,34.123213],"type":"Point"}
}