{
  "type": "Feature",
  "properties": {
    "addr:full":"5724 E Los Angeles Ave Simi Valley CA 93063",
    "addr:housenumber":"5724",
    "addr:postcode":"93063",
    "addr:street":"E Los Angeles Ave",
    "iso:country":"US",
    "sg:address":"5724 E Los Angeles Ave",
    "sg:city":"Simi Valley",
    "sg:classifiers":[
        {
            "category":"Shopping",
            "subcategory":"Used Merchandise",
            "type":"Retail Goods"
        }
    ],
    "sg:phone":"+1 805 526 1029",
    "sg:postcode":"93063",
    "sg:province":"CA",
    "sg:tags":[
        "shop",
        "consignment"
    ],
    "wof:name":"Hidden Treasures Corp",
    "wof:placetype":"venue"
},
  "geometry": {"coordinates":[-118.67952200000001,34.271655],"type":"Point"}
}