{
  "type": "Feature",
  "properties": {
    "addr:full":"16595 Marshall Ave Lake Elsinore CA 92530",
    "addr:housenumber":"16595",
    "addr:postcode":"92530",
    "addr:street":"Marshall Ave",
    "iso:country":"US",
    "sg:address":"16595 Marshall Ave",
    "sg:city":"Lake Elsinore",
    "sg:classifiers":[
        {
            "category":"Real Estate",
            "subcategory":"Real Estate Agent",
            "type":"Services"
        }
    ],
    "sg:phone":"+1 951 245 2608",
    "sg:postcode":"92530",
    "sg:province":"CA",
    "sg:tags":[
        "inspection"
    ],
    "wof:name":"Brett's Home Inspection Svc",
    "wof:placetype":"venue"
},
  "geometry": {"coordinates":[-117.368596,33.694825],"type":"Point"}
}