{
  "type": "Feature",
  "properties": {
    "iso:country":"US",
    "sg:address":"25250 Cabot Rd",
    "sg:city":"Laguna Hills",
    "sg:classifiers":[
        {
            "category":"Retail",
            "subcategory":"Laundry & Dry Cleaning",
            "type":"Services"
        }
    ],
    "sg:phone":"+1 949 581 3900",
    "sg:postcode":"92653",
    "sg:province":"CA",
    "wof:name":"Toro Cleaners",
    "wof:placetype":"venue"
},
  "geometry": {"coordinates":[-117.675822,33.595346],"type":"Point"}
}