{
  "type": "Feature",
  "properties": {
    "iso:country":"US",
    "sg:address":"735 S Figueroa St",
    "sg:city":"Los Angeles",
    "sg:classifiers":[
        {
            "category":"Restaurant",
            "type":"Food & Drink"
        }
    ],
    "sg:phone":"+1 213 624 1131",
    "sg:postcode":"90017",
    "sg:province":"CA",
    "sg:tags":[
        "chinese"
    ],
    "wof:name":"Panda Express",
    "wof:placetype":"venue"
},
  "geometry": {"coordinates":[-118.260002,34.048901],"type":"Point"}
}