{
  "type": "Feature",
  "properties": {
    "addr:full":"18502 Hesperian Blvd San Lorenzo CA 94541",
    "addr:housenumber":"18502",
    "addr:postcode":"94541",
    "addr:street":"Hesperian Blvd",
    "iso:country":"US",
    "sg:address":"18502 Hesperian Blvd",
    "sg:city":"San Lorenzo",
    "sg:classifiers":[
        {
            "category":"Restaurant",
            "type":"Food & Drink"
        }
    ],
    "sg:phone":"+1 510 856 0304",
    "sg:postcode":"94541",
    "sg:province":"CA",
    "sg:tags":[
        "mexican"
    ],
    "sg:website":"www.tacobell.com/",
    "wof:name":"Taco Bell",
    "wof:placetype":"venue"
},
  "geometry": {"coordinates":[-122.12179399999999,37.671812],"type":"Point"}
}