{
  "type": "Feature",
  "properties": {
    "iso:country":"US",
    "sg:address":"13685 Sage Mountain Ln",
    "sg:city":"Jamul",
    "sg:classifiers":[
        {
            "category":"Professional",
            "type":"Services"
        }
    ],
    "sg:phone":"+1 619 669 6924",
    "sg:postcode":"91935",
    "sg:province":"CA",
    "wof:name":"Kenners Leather & Vinyl Repair",
    "wof:placetype":"venue"
},
  "geometry": {"coordinates":[-116.89099400000001,32.713709],"type":"Point"}
}