{
  "type": "Feature",
  "properties": {
    "addr:full":"314 Chatsworth Dr San Fernando CA 91340",
    "addr:housenumber":"314",
    "addr:postcode":"91340",
    "addr:street":"Chatsworth Dr",
    "iso:country":"US",
    "sg:address":"314 Chatsworth Dr",
    "sg:city":"San Fernando",
    "sg:classifiers":[
        {
            "category":"Building & Trades",
            "subcategory":"Landscaping Services",
            "type":"Services"
        }
    ],
    "sg:phone":"+1 818 898 7287",
    "sg:postcode":"91340",
    "sg:province":"CA",
    "wof:name":"Omega Landscape Design",
    "wof:placetype":"venue"
},
  "geometry": {"coordinates":[-118.440443,34.279733],"type":"Point"}
}