{
  "type": "Feature",
  "properties": {
    "iso:country":"US",
    "sg:address":"5365 Alton Pkwy Ste A2",
    "sg:city":"Irvine",
    "sg:classifiers":[
        {
            "category":"Bagels",
            "subcategory":"None",
            "type":"Food & Drink"
        }
    ],
    "sg:phone":"+1 949 559 9196",
    "sg:postcode":"92604",
    "sg:province":"CA",
    "wof:name":"Big City Bagels",
    "wof:placetype":"venue"
},
  "geometry": {"coordinates":[-117.78851899999999,33.686246],"type":"Point"}
}