{
  "type": "Feature",
  "properties": {
    "iso:country":"US",
    "sg:address":"625 Randolph St",
    "sg:city":"Napa",
    "sg:classifiers":[
        {
            "category":"Organizations",
            "subcategory":"Religious Organization",
            "type":"Services"
        }
    ],
    "sg:phone":"+1 707 253 1411",
    "sg:postcode":"94559",
    "sg:province":"CA",
    "sg:tags":[
        "church"
    ],
    "sg:website":"www.napaumc.org",
    "wof:name":"United Methodist Church",
    "wof:placetype":"venue"
},
  "geometry": {"coordinates":[-122.285664,38.29521],"type":"Point"}
}