{
  "type": "Feature",
  "properties": {
    "addr:full":"2225 Plaza Pkwy Modesto CA 95350",
    "addr:housenumber":"2225",
    "addr:postcode":"ca 95350",
    "addr:street":"Plaza Pkwy",
    "iso:country":"US",
    "sg:address":"2225 Plaza Pkwy",
    "sg:city":"Modesto",
    "sg:classifiers":[
        {
            "category":"Shopping",
            "subcategory":"Clothing, Apparel, & Fashions",
            "type":"Retail Goods"
        }
    ],
    "sg:phone":"+1 209 577 1701",
    "sg:postcode":"95350",
    "sg:province":"CA",
    "sg:tags":[
        "accessory",
        "clothing",
        "women's"
    ],
    "sg:website":"fashionbug.charmingshoppes.com",
    "wof:name":"Fashion Bug",
    "wof:placetype":"venue"
},
  "geometry": {"coordinates":[-121.03299699999999,37.6717],"type":"Point"}
}