{
  "type": "Feature",
  "properties": {
    "addr:full":"1855 Winchester Blvd Campbell CA 95008",
    "addr:housenumber":"1855",
    "addr:postcode":"95008",
    "addr:street":"Winchester Blvd",
    "iso:country":"US",
    "sg:address":"1855 Winchester Blvd",
    "sg:city":"Campbell",
    "sg:classifiers":[
        {
            "category":"Organizations",
            "subcategory":"Religious Organization",
            "type":"Services"
        }
    ],
    "sg:phone":"+1 408 871 7201",
    "sg:postcode":"95008",
    "sg:province":"CA",
    "sg:tags":[
        "church"
    ],
    "sg:website":"www.guidepost-church.org",
    "wof:name":"Guide Post Gospel Church",
    "wof:placetype":"venue"
},
  "geometry": {"coordinates":[-121.949854,37.290612],"type":"Point"}
}