{
  "type": "Feature",
  "properties": {
    "addr:full":"3545 Cadillac Ave Costa Mesa CA 92626",
    "addr:housenumber":"3545",
    "addr:postcode":"92626",
    "addr:street":"Cadillac Ave",
    "iso:country":"US",
    "sg:address":"3545 Cadillac Ave",
    "sg:city":"Costa Mesa",
    "sg:classifiers":[
        {
            "category":"Manufacturing",
            "subcategory":"Electronics",
            "type":"Manufacturing & Wholesale Goods"
        }
    ],
    "sg:phone":"+1 714 433 1200",
    "sg:postcode":"92626",
    "sg:province":"CA",
    "sg:tags":[
        "component",
        "meas",
        "parts",
        "electronic",
        "mfg"
    ],
    "wof:name":"Ecliptek Inc",
    "wof:placetype":"venue"
},
  "geometry": {"coordinates":[-117.93079,33.695942],"type":"Point"}
}