{
  "type": "Feature",
  "properties": {
    "addr:full":"6684 Bancroft Ave Oakland CA 94605",
    "addr:housenumber":"6684",
    "addr:postcode":"94605",
    "addr:street":"Bancroft Ave",
    "iso:country":"US",
    "sg:address":"6684 Bancroft Ave",
    "sg:city":"Oakland",
    "sg:classifiers":[
        {
            "category":"Professional",
            "type":"Services"
        }
    ],
    "sg:phone":"+1 510 777 1516",
    "sg:postcode":"94605",
    "sg:province":"CA",
    "wof:name":"Nerdy J Feelings",
    "wof:placetype":"venue"
},
  "geometry": {"coordinates":[-122.181528,37.769598],"type":"Point"}
}