{
  "type": "Feature",
  "properties": {
    "addr:full":"2151 Johnson Ct Torrance CA 90504",
    "addr:housenumber":"2151",
    "addr:postcode":"90504",
    "addr:street":"Johnson Ct",
    "iso:country":"US",
    "sg:address":"2151 Johnson Ct",
    "sg:city":"Torrance",
    "sg:classifiers":[
        {
            "category":"Social Services",
            "type":"Services"
        }
    ],
    "sg:phone":"+1 310 538 1979",
    "sg:postcode":"90504",
    "sg:province":"CA",
    "sg:tags":[
        "organization",
        "welfare"
    ],
    "wof:name":"Health Systems Educators",
    "wof:placetype":"venue"
},
  "geometry": {"coordinates":[-118.31762999999999,33.87945],"type":"Point"}
}