{
  "type": "Feature",
  "properties": {
    "iso:country":"US",
    "sg:address":"605 S Auburn St",
    "sg:city":"Grass Valley",
    "sg:classifiers":[
        {
            "category":"Health Services",
            "subcategory":"Medical Lab",
            "type":"Services"
        }
    ],
    "sg:phone":"+1 530 272 9100",
    "sg:postcode":"95945",
    "sg:province":"CA",
    "sg:tags":[
        "x",
        "laboratory"
    ],
    "wof:name":"Gold Country Dental X-Ray Lab",
    "wof:placetype":"venue"
},
  "geometry": {"coordinates":[-121.06195,39.208942],"type":"Point"}
}