{
  "type": "Feature",
  "properties": {
    "iso:country":"US",
    "sg:address":"1495 Railroad Ave",
    "sg:city":"Clovis",
    "sg:classifiers":[
        {
            "category":"Autos & Motor Vehicles",
            "subcategory":"Automobile Sales",
            "type":"Retail Goods"
        }
    ],
    "sg:phone":"+1 559 297 8476",
    "sg:postcode":"93612",
    "sg:province":"CA",
    "sg:tags":[
        "car",
        "dealer"
    ],
    "wof:name":"Auto Buyers Svc-Sales",
    "wof:placetype":"venue"
},
  "geometry": {"coordinates":[-119.699685,36.813004],"type":"Point"}
}