{
  "type": "Feature",
  "properties": {
    "addr:full":"390 W Main St El Cajon CA 92020",
    "addr:housenumber":"390",
    "addr:postcode":"92020",
    "addr:street":"W Main St",
    "iso:country":"US",
    "sg:address":"390 W Main St",
    "sg:city":"El Cajon",
    "sg:classifiers":[
        {
            "category":"Restaurant",
            "type":"Food & Drink"
        }
    ],
    "sg:phone":"+1 619 441 6477",
    "sg:postcode":"92020",
    "sg:province":"CA",
    "sg:tags":[
        "buffet"
    ],
    "sg:website":"www.hometownbuffet.com",
    "wof:name":"Hometown Buffet",
    "wof:placetype":"venue"
},
  "geometry": {"coordinates":[-116.966003,32.795101],"type":"Point"}
}