{
  "type": "Feature",
  "properties": {
    "addr:full":"21691 Kimberly Rd Anderson CA 96007",
    "addr:housenumber":"21691",
    "addr:postcode":"96007",
    "addr:street":"Kimberly Rd",
    "iso:country":"US",
    "sg:address":"21691 Kimberly Rd",
    "sg:city":"Anderson",
    "sg:classifiers":[
        {
            "category":"Building & Trades",
            "subcategory":"Landscaping Services",
            "type":"Services"
        }
    ],
    "sg:phone":"+1 530 356 0435",
    "sg:postcode":"96007",
    "sg:province":"CA",
    "sg:tags":[
        "lawn",
        "maintenance",
        "grounds"
    ],
    "wof:name":"High Country Lawn & Tree Svc",
    "wof:placetype":"venue"
},
  "geometry": {"coordinates":[-122.249934,40.429708],"type":"Point"}
}