{
  "type": "Feature",
  "properties": {
    "iso:country":"US",
    "sg:address":"13611 Yukon Avenue",
    "sg:city":"Hawthorne",
    "sg:classifiers":[
        {
            "category":"Real Estate",
            "subcategory":"Real Estate Operator",
            "type":"Services"
        }
    ],
    "sg:phone":"+1 310 644 4170",
    "sg:postcode":"90250",
    "sg:province":"CA",
    "sg:tags":[
        "apartment"
    ],
    "wof:name":"Villa Fiorita",
    "wof:placetype":"venue"
},
  "geometry": {"coordinates":[-118.335155,33.908182],"type":"Point"}
}