{
  "type": "Feature",
  "properties": {
    "iso:country":"US",
    "sg:address":"1725 23rd St Ste 200",
    "sg:city":"Sacramento",
    "sg:classifiers":[
        {
            "category":"Autos & Motor Vehicles",
            "subcategory":"Automobile Sales",
            "type":"Retail Goods"
        }
    ],
    "sg:phone":"+1 916 324 6588",
    "sg:postcode":"95816",
    "sg:province":"CA",
    "sg:tags":[
        "new",
        "used",
        "car"
    ],
    "wof:name":"Off-Highway Motor Vehicle Recreatio",
    "wof:placetype":"venue"
},
  "geometry": {"coordinates":[-121.479355,38.567622],"type":"Point"}
}