{
  "type": "Feature",
  "properties": {
    "iso:country":"US",
    "sg:address":"545 Sutter St",
    "sg:city":"San Francisco",
    "sg:classifiers":[
        {
            "category":"Professional",
            "type":"Services"
        }
    ],
    "sg:phone":"+1 415 362 5343",
    "sg:postcode":"94102",
    "sg:province":"CA",
    "sg:tags":[
        "arts",
        "artist"
    ],
    "wof:name":"Daniel Kilpatrick Studio",
    "wof:placetype":"venue"
},
  "geometry": {"coordinates":[-122.409645,37.789036],"type":"Point"}
}