{
  "type": "Feature",
  "properties": {
    "addr:full":"844 E Mission Rd San Gabriel CA 91776",
    "addr:housenumber":"844",
    "addr:postcode":"91776",
    "addr:street":"E Mission Rd",
    "iso:country":"US",
    "sg:address":"844 E Mission Rd",
    "sg:city":"San Gabriel",
    "sg:classifiers":[
        {
            "category":"Real Estate",
            "subcategory":"Real Estate Agent",
            "type":"Services"
        }
    ],
    "sg:phone":"+1 626 292 1199",
    "sg:postcode":"91776",
    "sg:province":"CA",
    "wof:name":"Kotai Realty San Gabriel",
    "wof:placetype":"venue"
},
  "geometry": {"coordinates":[-118.088555,34.090054],"type":"Point"}
}