{
  "type": "Feature",
  "properties": {
    "addr:full":"3085 21st St San Francisco CA 94110",
    "addr:housenumber":"3085",
    "addr:postcode":"94110",
    "addr:street":"21St St",
    "iso:country":"US",
    "sg:address":"3085 21st St",
    "sg:city":"San Francisco",
    "sg:classifiers":[
        {
            "category":"Shopping",
            "subcategory":"Bicycles & Sporting Goods",
            "type":"Retail Goods"
        }
    ],
    "sg:phone":"+1 415 641 1264",
    "sg:postcode":"94110",
    "sg:province":"CA",
    "wof:name":"Pedal Revolution",
    "wof:placetype":"venue"
},
  "geometry": {"coordinates":[-122.416102,37.757137],"type":"Point"}
}