{
  "type": "Feature",
  "properties": {
    "iso:country":"US",
    "sg:address":"919 N Manhattan Ave",
    "sg:city":"Manhattan Beach",
    "sg:classifiers":[
        {
            "category":"Organizations",
            "subcategory":"Community Association",
            "type":"Services"
        }
    ],
    "sg:phone":"+1 310 374 8212",
    "sg:postcode":"90266",
    "sg:province":"CA",
    "sg:tags":[
        "environmental",
        "org"
    ],
    "wof:name":"Environmental Communication",
    "wof:placetype":"venue"
},
  "geometry": {"coordinates":[-118.410093,33.883406],"type":"Point"}
}