{
  "type": "Feature",
  "properties": {
    "addr:full":"235 W Inyo Ave Tulare CA 93274",
    "addr:housenumber":"235",
    "addr:postcode":"93274",
    "addr:street":"W Inyo Ave",
    "iso:country":"US",
    "sg:address":"235 W Inyo Ave",
    "sg:city":"Tulare",
    "sg:classifiers":[
        {
            "category":"Restaurant",
            "type":"Food & Drink"
        }
    ],
    "sg:phone":"+1 559 686 8226",
    "sg:postcode":"93274",
    "sg:province":"CA",
    "wof:name":"Taco Riendo",
    "wof:placetype":"venue"
},
  "geometry": {"coordinates":[-119.35014700000001,36.204722],"type":"Point"}
}