{
  "type": "Feature",
  "properties": {
    "iso:country":"US",
    "sg:address":"3751 Katella Ave",
    "sg:city":"Los Alamitos",
    "sg:classifiers":[
        {
            "category":"Health Services",
            "subcategory":"Hospital",
            "type":"Services"
        }
    ],
    "sg:phone":"+1 562 799 3234",
    "sg:postcode":"90720",
    "sg:province":"CA",
    "wof:name":"Institute of Geropsychtry At Ls Almts Mdcl Ctr the",
    "wof:placetype":"venue"
},
  "geometry": {"coordinates":[-118.067001,33.803299],"type":"Point"}
}