{
  "type": "Feature",
  "properties": {
    "iso:country":"US",
    "sg:address":"60 Narcissa Drive",
    "sg:city":"Rancho Palos Verdes",
    "sg:classifiers":[
        {
            "category":"Building & Trades",
            "subcategory":"Construction",
            "type":"Services"
        }
    ],
    "sg:phone":"+1 310 377 7269",
    "sg:postcode":"90275",
    "sg:province":"CA",
    "sg:tags":[
        "contractor"
    ],
    "wof:name":"C W R Corporation",
    "wof:placetype":"venue"
},
  "geometry": {"coordinates":[-118.370822,33.748693],"type":"Point"}
}