{
  "type": "Feature",
  "properties": {
    "addr:full":"140 S Mountain Ave Upland CA 91786",
    "addr:housenumber":"140",
    "addr:postcode":"91786",
    "addr:street":"S Mountain Ave",
    "iso:country":"US",
    "sg:address":"140 S Mountain Ave",
    "sg:city":"Upland",
    "sg:classifiers":[
        {
            "category":"Restaurant",
            "type":"Food & Drink"
        }
    ],
    "sg:menulink":"http://www.allmenus.com/ca/ontario/7501-rubios/menu/",
    "sg:phone":"+1 909 946 8555",
    "sg:postcode":"91786",
    "sg:province":"CA",
    "sg:tags":[
        "seafood",
        "mexican",
        "american"
    ],
    "wof:name":"Rubio's",
    "wof:placetype":"venue"
},
  "geometry": {"coordinates":[-117.67008199999999,34.093005],"type":"Point"}
}