{
  "type": "Feature",
  "properties": {
    "addr:full":"980 E Tahquitz Canyon Way Palm Springs CA 92262",
    "addr:housenumber":"980",
    "addr:postcode":"92262",
    "addr:street":"E Tahquitz Canyon Way",
    "iso:country":"US",
    "sg:address":"980 E Tahquitz Canyon Way",
    "sg:city":"Palm Springs",
    "sg:classifiers":[
        {
            "category":"Government",
            "subcategory":"Office",
            "type":"Public Place"
        }
    ],
    "sg:phone":"+1 760 322 5134",
    "sg:postcode":"92262",
    "sg:province":"CA",
    "sg:tags":[
        "policy"
    ],
    "wof:name":"Palm Springs Office",
    "wof:placetype":"venue"
},
  "geometry": {"coordinates":[-116.53919500000001,33.823217],"type":"Point"}
}