{
  "type": "Feature",
  "properties": {
    "addr:full":"7300 Central Ave Newark CA 94560",
    "addr:housenumber":"7300",
    "addr:postcode":"94560",
    "addr:street":"Central Ave",
    "iso:country":"US",
    "sg:address":"7300 Central Ave",
    "sg:city":"Newark",
    "sg:classifiers":[
        {
            "category":"Manufacturing",
            "subcategory":"Chemicals & Compounds",
            "type":"Manufacturing & Wholesale Goods"
        }
    ],
    "sg:phone":"+1 510 713 9961",
    "sg:postcode":"94560",
    "sg:province":"CA",
    "sg:tags":[
        "product",
        "vitamin"
    ],
    "wof:name":"Bioformx",
    "wof:placetype":"venue"
},
  "geometry": {"coordinates":[-122.034436,37.521405],"type":"Point"}
}