{
  "type": "Feature",
  "properties": {
    "iso:country":"US",
    "sg:address":"311 N Montgomery St",
    "sg:city":"Ojai",
    "sg:classifiers":[
        {
            "category":"Shopping",
            "subcategory":"Gifts & Souvenirs",
            "type":"Retail Goods"
        }
    ],
    "sg:phone":"+1 805 640 3679",
    "sg:postcode":"93023",
    "sg:province":"CA",
    "wof:name":"Soul Centered Inc",
    "wof:placetype":"venue"
},
  "geometry": {"coordinates":[-119.243083,34.450887],"type":"Point"}
}