{
  "type": "Feature",
  "properties": {
    "addr:full":"32525 State Hwy 18 Lucerne Valley CA 92356",
    "addr:housenumber":"32525",
    "addr:postcode":"92356",
    "addr:street":"State Hwy 18 Lucerne",
    "iso:country":"US",
    "sg:address":"32525 State Hwy 18",
    "sg:city":"Lucerne Valley",
    "sg:classifiers":[
        {
            "category":"Organizations",
            "subcategory":"Religious Organization",
            "type":"Services"
        }
    ],
    "sg:phone":"+1 760 248 7039",
    "sg:postcode":"92356",
    "sg:province":"CA",
    "sg:tags":[
        "church"
    ],
    "wof:name":"Crossroads Chapel Church",
    "wof:placetype":"venue"
},
  "geometry": {"coordinates":[-116.954415,34.443774],"type":"Point"}
}