{
  "type": "Feature",
  "properties": {
    "addr:full":"1611 Borel Place, Suite 2 San Mateo CA 94402",
    "addr:housenumber":"1611",
    "addr:postcode":"94402",
    "addr:street":"Borel Place Suite 2",
    "iso:country":"US",
    "sg:address":"1611 Borel Place, Suite 2",
    "sg:city":"San Mateo",
    "sg:classifiers":[
        {
            "category":"Professional",
            "subcategory":"Computer Services",
            "type":"Services"
        }
    ],
    "sg:phone":"+1 650 571 5255",
    "sg:postcode":"94402",
    "sg:province":"CA",
    "sg:tags":[
        "budgeting-and-forecasting",
        "collecting-and-tracking",
        "financial-reporting",
        "ftes",
        "life-sciences",
        "process-optimizations",
        "time-collection",
        "grants",
        "collaborations",
        "planning-and-tracking",
        "analyzing-actuals",
        "consolidation",
        "reporting"
    ],
    "sg:website":"http://www.rdlogic.com",
    "wof:name":"R&D Logic",
    "wof:placetype":"venue"
},
  "geometry": {"coordinates":[-122.317921,37.548582],"type":"Point"}
}