{
  "type": "Feature",
  "properties": {
    "iso:country":"US",
    "sg:address":"865 N Palm Canyon Dr",
    "sg:city":"Palm Springs",
    "sg:classifiers":[
        {
            "category":"Shopping",
            "subcategory":"Antiques",
            "type":"Retail Goods"
        }
    ],
    "sg:phone":"+1 760 320 2411",
    "sg:postcode":"92262",
    "sg:province":"CA",
    "wof:name":"Las Palmas Antiques",
    "wof:placetype":"venue"
},
  "geometry": {"coordinates":[-116.546997,33.834599],"type":"Point"}
}