{
  "type": "Feature",
  "properties": {
    "iso:country":"US",
    "sg:address":"1106 Carmelita Ave",
    "sg:city":"Sacramento",
    "sg:classifiers":[
        {
            "category":"Professional",
            "subcategory":"Management & Consulting",
            "type":"Services"
        }
    ],
    "sg:phone":"+1 916 920 0067",
    "sg:postcode":"95838",
    "sg:province":"CA",
    "sg:tags":[
        "promotion",
        "sales"
    ],
    "wof:name":"Sabanoh Enterprises",
    "wof:placetype":"venue"
},
  "geometry": {"coordinates":[-121.44032900000001,38.630914],"type":"Point"}
}