{
  "type": "Feature",
  "properties": {
    "iso:country":"US",
    "sg:address":"5822 W 3rd St",
    "sg:city":"Los Angeles",
    "sg:classifiers":[
        {
            "category":"Education",
            "subcategory":"College",
            "type":"Public Place"
        }
    ],
    "sg:phone":"+1 323 938 5196",
    "sg:postcode":"90036",
    "sg:province":"CA",
    "wof:name":"Bais Yaakov Maalot",
    "wof:placetype":"venue"
},
  "geometry": {"coordinates":[-118.346746,34.068996],"type":"Point"}
}