{
  "type": "Feature",
  "properties": {
    "iso:country":"US",
    "sg:address":"27515 Jefferson Ave",
    "sg:city":"Temecula",
    "sg:classifiers":[
        {
            "category":"Real Estate",
            "subcategory":"Real Estate Agent",
            "type":"Services"
        }
    ],
    "sg:phone":"+1 951 694 0111",
    "sg:postcode":"92562",
    "sg:province":"CA",
    "wof:name":"All-Star Real Estate",
    "wof:placetype":"venue"
},
  "geometry": {"coordinates":[-117.163302,33.51873],"type":"Point"}
}