{
  "type": "Feature",
  "properties": {
    "iso:country":"US",
    "sg:address":"1180 S Beverly Dr",
    "sg:city":"Los Angeles",
    "sg:classifiers":[
        {
            "category":"Health Services",
            "subcategory":"Doctor",
            "type":"Services"
        }
    ],
    "sg:phone":"+1 310 859 8563",
    "sg:postcode":"90035",
    "sg:province":"CA",
    "sg:tags":[
        "dentist"
    ],
    "wof:name":"Dentaland",
    "wof:placetype":"venue"
},
  "geometry": {"coordinates":[-118.395787,34.056037],"type":"Point"}
}