{
  "type": "Feature",
  "properties": {
    "addr:full":"6209 Lake Isabella Blvd Lake Isabella CA 93240",
    "addr:housenumber":"6209",
    "addr:postcode":"93240",
    "addr:street":"Lake Isabella Blvd",
    "iso:country":"US",
    "sg:address":"6209 Lake Isabella Blvd",
    "sg:city":"Lake Isabella",
    "sg:classifiers":[
        {
            "category":"Food & Beverages",
            "subcategory":"Groceries & Convenience Stores",
            "type":"Retail Goods"
        }
    ],
    "sg:phone":"+1 760 379 8170",
    "sg:postcode":"93240",
    "sg:province":"CA",
    "wof:name":"Crossroads Mini Mart",
    "wof:placetype":"venue"
},
  "geometry": {"coordinates":[-118.473821,35.627931],"type":"Point"}
}