{
  "type": "Feature",
  "properties": {
    "addr:full":"1815 Santa Rosa Ave Santa Rosa CA 95407",
    "addr:housenumber":"1815",
    "addr:postcode":"95407",
    "addr:street":"Santa Rosa Ave",
    "iso:country":"US",
    "sg:address":"1815 Santa Rosa Ave",
    "sg:city":"Santa Rosa",
    "sg:classifiers":[
        {
            "category":"Travel",
            "subcategory":"Hotels & Motels",
            "type":"Entertainment"
        }
    ],
    "sg:phone":"+1 707 542 3472",
    "sg:postcode":"95407",
    "sg:province":"CA",
    "wof:name":"Vineyard Lodge",
    "wof:placetype":"venue"
},
  "geometry": {"coordinates":[-122.71357999999999,38.417715],"type":"Point"}
}