{
  "type": "Feature",
  "properties": {
    "addr:full":"6 Cielo Vista Pl Monterey CA 93940",
    "addr:housenumber":"6",
    "addr:postcode":"93940",
    "addr:street":"Cielo Vista Pl",
    "iso:country":"US",
    "sg:address":"6 Cielo Vista Pl",
    "sg:city":"Monterey",
    "sg:classifiers":[
        {
            "category":"Travel",
            "subcategory":"Travel Agent",
            "type":"Entertainment"
        }
    ],
    "sg:phone":"+1 831 655 6450",
    "sg:postcode":"93940",
    "sg:province":"CA",
    "sg:tags":[
        "agency",
        "services-commercial"
    ],
    "wof:name":"Visit Usa",
    "wof:placetype":"venue"
},
  "geometry": {"coordinates":[-121.90633200000001,36.580943],"type":"Point"}
}