{
  "type": "Feature",
  "properties": {
    "addr:full":"4969 Westhaven St Los Angeles CA 90016",
    "addr:housenumber":"4969",
    "addr:postcode":"90016",
    "addr:street":"Westhaven St",
    "iso:country":"US",
    "sg:address":"4969 Westhaven St",
    "sg:city":"Los Angeles",
    "sg:classifiers":[
        {
            "category":"Building & Trades",
            "subcategory":"Landscaping Services",
            "type":"Services"
        }
    ],
    "sg:phone":"+1 323 731 1632",
    "sg:postcode":"90016",
    "sg:province":"CA",
    "sg:tags":[
        "landscape"
    ],
    "wof:name":"Porfirio P Perez",
    "wof:placetype":"venue"
},
  "geometry": {"coordinates":[-118.35226299999999,34.028656],"type":"Point"}
}