{
  "type": "Feature",
  "properties": {
    "addr:full":"4280 Pell Dr Sacramento CA 95838",
    "addr:housenumber":"4280",
    "addr:postcode":"95838",
    "addr:street":"Pell Dr",
    "iso:country":"US",
    "sg:address":"4280 Pell Dr",
    "sg:city":"Sacramento",
    "sg:classifiers":[
        {
            "category":"Retail",
            "subcategory":"Auto Repair",
            "type":"Services"
        }
    ],
    "sg:phone":"+1 916 922 9546",
    "sg:postcode":"95838",
    "sg:province":"CA",
    "sg:website":"swimsautorepairandtowing.com",
    "wof:name":"Swim's Enterprises",
    "wof:placetype":"venue"
},
  "geometry": {"coordinates":[-121.468261,38.646021],"type":"Point"}
}