{
  "type": "Feature",
  "properties": {
    "iso:country":"US",
    "sfac:artist":"Happersberger, Frank",
    "sfac:created_at":"01/01/1970 12:31:34 AM +0000",
    "sfac:credit_line":"Gift of James Lick",
    "sfac:display_dimensions":"Figure: 10' H; Pedestal: 30' H",
    "sfac:location_description":"Public Display : District 6 : McAllister St., between Asian Art Museum and Libra",
    "sfac:medium":"Bronze and granite",
    "sfac:revision":"2-e00831bbb5e5b04b865b9311c51132be",
    "sfac:title":"Pioneer Monument  (James Lick Monument)",
    "wof:name":"Pioneer Monument  (James Lick Monument)",
    "wof:placetype":"venue"
},
  "geometry": {"coordinates":[-122.4194155,37.7749295],"type":"Point"}
}