{
  "type": "Feature",
  "properties": {
    "iso:country":"US",
    "sg:address":"20707 Anza Ave",
    "sg:city":"Torrance",
    "sg:classifiers":[
        {
            "category":"Professional",
            "subcategory":"Computer Services",
            "type":"Services"
        }
    ],
    "sg:phone":"+1 310 320 5570",
    "sg:postcode":"90503",
    "sg:province":"CA",
    "sg:tags":[
        "developer"
    ],
    "wof:name":"Nuks Jain Inc",
    "wof:placetype":"venue"
},
  "geometry": {"coordinates":[-118.362428,33.842321],"type":"Point"}
}