{
  "type": "Feature",
  "properties": {
    "iso:country":"US",
    "sg:address":"2261 W Pico Blvd",
    "sg:city":"Los Angeles",
    "sg:classifiers":[
        {
            "category":"Retail",
            "subcategory":"Auto Repair",
            "type":"Services"
        }
    ],
    "sg:phone":"+1 213 384 4080",
    "sg:postcode":"90006",
    "sg:province":"CA",
    "sg:tags":[
        "automobile",
        "top",
        "upholstery"
    ],
    "wof:name":"Y & K USA",
    "wof:placetype":"venue"
},
  "geometry": {"coordinates":[-118.28630200000001,34.047351],"type":"Point"}
}