{
  "type": "Feature",
  "properties": {
    "iso:country":"US",
    "sg:address":"1215 Borregas Ave",
    "sg:city":"Sunnyvale",
    "sg:classifiers":[
        {
            "category":"Professional",
            "type":"Services"
        }
    ],
    "sg:phone":"+1 408 734 5521",
    "sg:postcode":"94089",
    "sg:province":"CA",
    "sg:tags":[
        "establishment"
    ],
    "wof:name":"Keencom",
    "wof:placetype":"venue"
},
  "geometry": {"coordinates":[-122.01859,37.409829],"type":"Point"}
}