{
  "type": "Feature",
  "properties": {
    "addr:full":"1601 W Kenneth Rd Glendale CA 91201",
    "addr:housenumber":"1601",
    "addr:postcode":"91201",
    "addr:street":"W Kenneth Rd",
    "iso:country":"US",
    "sg:address":"1601 W Kenneth Rd",
    "sg:city":"Glendale",
    "sg:classifiers":[
        {
            "category":"Building & Trades",
            "subcategory":"Construction",
            "type":"Services"
        }
    ],
    "sg:phone":"+1 818 244 8283",
    "sg:postcode":"91201",
    "sg:province":"CA",
    "sg:tags":[
        "waterproofing",
        "contractor"
    ],
    "wof:name":"H A Just Waterproofing Co",
    "wof:placetype":"venue"
},
  "geometry": {"coordinates":[-118.283833,34.175031],"type":"Point"}
}