{
  "type": "Feature",
  "properties": {
    "iso:country":"US",
    "sg:address":"2390 Michael Faraday Dr",
    "sg:city":"San Diego",
    "sg:classifiers":[
        {
            "category":"Freight",
            "type":"Transportation"
        }
    ],
    "sg:phone":"+1 619 710 4982",
    "sg:postcode":"92154",
    "sg:province":"CA",
    "sg:tags":[
        "consultant",
        "customs"
    ],
    "wof:name":"Especializacion En Servicios",
    "wof:placetype":"venue"
},
  "geometry": {"coordinates":[-116.931916,32.55661],"type":"Point"}
}