{
  "type": "Feature",
  "properties": {
    "iso:country":"US",
    "sg:address":"1050 Florin Rd",
    "sg:city":"Sacramento",
    "sg:classifiers":[
        {
            "category":"Utilities",
            "subcategory":"Mobile Phone",
            "type":"Services"
        }
    ],
    "sg:phone":"+1 916 231 9858",
    "sg:postcode":"95831",
    "sg:province":"CA",
    "sg:tags":[
        "telephone",
        "cellular"
    ],
    "wof:name":"Advanced Wireless Communications",
    "wof:placetype":"venue"
},
  "geometry": {"coordinates":[-121.521902,38.495544],"type":"Point"}
}