{
  "type": "Feature",
  "properties": {
    "addr:full":"1215 Laguna St San Francisco CA 94115",
    "addr:housenumber":"1215",
    "addr:postcode":"94115",
    "addr:street":"Laguna St",
    "iso:country":"US",
    "sg:address":"1215 Laguna St",
    "sg:city":"San Francisco",
    "sg:classifiers":[
        {
            "category":"Communications",
            "type":"Services"
        }
    ],
    "sg:phone":"+1 415 286 4700",
    "sg:postcode":"94115",
    "sg:province":"CA",
    "sg:tags":[
        "web",
        "design"
    ],
    "sg:website":"www.zoltanplus.com",
    "wof:name":"ZOLTAN+",
    "wof:placetype":"venue"
},
  "geometry": {"coordinates":[-122.427481,37.782368],"type":"Point"}
}