{
  "type": "Feature",
  "properties": {
    "iso:country":"US",
    "sg:address":"13570 Benson Ave",
    "sg:city":"Chino",
    "sg:classifiers":[
        {
            "category":"Building & Trades",
            "subcategory":"Construction",
            "type":"Services"
        }
    ],
    "sg:phone":"+1 909 591 3931",
    "sg:postcode":"91710",
    "sg:province":"CA",
    "sg:tags":[
        "contractor"
    ],
    "wof:name":"REC Equipment Corp",
    "wof:placetype":"venue"
},
  "geometry": {"coordinates":[-117.680546,34.007717],"type":"Point"}
}