{
  "type": "Feature",
  "properties": {
    "addr:full":"13570 Benson Ave Chino CA 91710",
    "addr:housenumber":"13570",
    "addr:postcode":"91710",
    "addr:street":"Benson Ave",
    "iso:country":"US",
    "sg:address":"13570 Benson Ave",
    "sg:city":"Chino",
    "sg:classifiers":[
        {
            "category":"Building & Trades",
            "subcategory":"Construction",
            "type":"Services"
        }
    ],
    "sg:phone":"+1 909 591 3931",
    "sg:postcode":"91710",
    "sg:province":"CA",
    "sg:tags":[
        "contractor"
    ],
    "wof:name":"REC Equipment Corp",
    "wof:placetype":"venue"
},
  "geometry": {"coordinates":[-117.68054600000001,34.007717],"type":"Point"}
}