{
  "type": "Feature",
  "properties": {
    "addr:full":"9880 Sierra Ave Fontana CA 92335",
    "addr:housenumber":"9880",
    "addr:postcode":"92335",
    "addr:street":"Sierra Ave",
    "iso:country":"US",
    "sg:address":"9880 Sierra Ave",
    "sg:city":"Fontana",
    "sg:classifiers":[
        {
            "category":"Shopping",
            "subcategory":"Gifts & Souvenirs",
            "type":"Retail Goods"
        }
    ],
    "sg:phone":"+1 909 823 7515",
    "sg:postcode":"92335",
    "sg:province":"CA",
    "sg:tags":[
        "party",
        "supply"
    ],
    "wof:name":"Andrea's Party Supply",
    "wof:placetype":"venue"
},
  "geometry": {"coordinates":[-117.435759,34.077265],"type":"Point"}
}