{
  "type": "Feature",
  "properties": {
    "iso:country":"US",
    "sg:address":"1237 Midas Way",
    "sg:city":"Sunnyvale",
    "sg:classifiers":[
        {
            "category":"Manufacturing",
            "subcategory":"Electronics",
            "type":"Manufacturing & Wholesale Goods"
        }
    ],
    "sg:phone":"+1 408 738 1452",
    "sg:postcode":"94085",
    "sg:province":"CA",
    "sg:tags":[
        "semiconductor",
        "related",
        "devices",
        "mfg"
    ],
    "wof:name":"Tdk Semiconductor Corp",
    "wof:placetype":"venue"
},
  "geometry": {"coordinates":[-121.992034,37.385265],"type":"Point"}
}