{
  "type": "Feature",
  "properties": {
    "iso:country":"US",
    "sg:address":"8370 Wilshire Blvd",
    "sg:city":"Beverly Hills",
    "sg:classifiers":[
        {
            "category":"Sports & Exercise",
            "subcategory":"Gym",
            "type":"Entertainment"
        }
    ],
    "sg:phone":"+1 323 665 6898",
    "sg:postcode":"90211",
    "sg:province":"CA",
    "sg:tags":[
        "yoga"
    ],
    "sg:website":"www.yogimindandbody.com",
    "wof:name":"Yogimind And Body",
    "wof:placetype":"venue"
},
  "geometry": {"coordinates":[-118.37378099999999,34.444312],"type":"Point"}
}