{
  "type": "Feature",
  "properties": {
    "addr:full":"6390 Dominica Ave Cypress CA 90630",
    "addr:housenumber":"6390",
    "addr:postcode":"90630",
    "addr:street":"Dominica Ave",
    "iso:country":"US",
    "sg:address":"6390 Dominica Ave",
    "sg:city":"Cypress",
    "sg:classifiers":[
        {
            "category":"Professional",
            "subcategory":"Art Services",
            "type":"Services"
        }
    ],
    "sg:phone":"+1 714 895 2648",
    "sg:postcode":"90630",
    "sg:province":"CA",
    "sg:tags":[
        "calligrapher"
    ],
    "wof:name":"Calligraphy By Linda",
    "wof:placetype":"venue"
},
  "geometry": {"coordinates":[-118.02081200000001,33.796053],"type":"Point"}
}