{
  "type": "Feature",
  "properties": {
    "addr:full":"4287 W Swift Ave Fresno CA 93722",
    "addr:housenumber":"4287",
    "addr:postcode":"93722",
    "addr:street":"W Swift Ave",
    "iso:country":"US",
    "sg:address":"4287 W Swift Ave",
    "sg:city":"Fresno",
    "sg:classifiers":[
        {
            "category":"Shopping",
            "subcategory":"Used Merchandise",
            "type":"Retail Goods"
        }
    ],
    "sg:phone":"+1 559 276 8790",
    "sg:postcode":"93722",
    "sg:province":"CA",
    "sg:tags":[
        "shop",
        "consignment"
    ],
    "wof:name":"E-Z Bay Store",
    "wof:placetype":"venue"
},
  "geometry": {"coordinates":[-119.865165,36.795229],"type":"Point"}
}