{
  "type": "Feature",
  "properties": {
    "addr:full":"725 Washington St Oakland CA 94607",
    "addr:housenumber":"725",
    "addr:postcode":"94607",
    "addr:street":"Washington St",
    "iso:country":"US",
    "sg:address":"725 Washington St",
    "sg:city":"Oakland",
    "sg:classifiers":[
        {
            "category":"Professional",
            "type":"Services"
        }
    ],
    "sg:phone":"+1 510 272 0700",
    "sg:postcode":"94607",
    "sg:province":"CA",
    "wof:name":"Bryant H Paul",
    "wof:placetype":"venue"
},
  "geometry": {"coordinates":[-122.275198,37.800542],"type":"Point"}
}