{
  "type": "Feature",
  "properties": {
    "addr:full":"2556 Somersville Rd # 58 Antioch CA 94509",
    "addr:housenumber":"2556;58",
    "addr:postcode":"ca 94509",
    "addr:street":"Somersville Rd #",
    "iso:country":"US",
    "sg:address":"2556 Somersville Rd # 58",
    "sg:city":"Antioch",
    "sg:classifiers":[
        {
            "category":"Restaurant",
            "type":"Food & Drink"
        },
        {
            "category":"Food & Beverages",
            "subcategory":"Dairy",
            "type":"Retail Goods"
        }
    ],
    "sg:phone":"+1 925 754 6245",
    "sg:postcode":"94509",
    "sg:province":"CA",
    "sg:tags":[
        "yogurt",
        "dessert"
    ],
    "wof:name":"Yougart Oasis",
    "wof:placetype":"venue"
},
  "geometry": {"coordinates":[-121.841179,38.000545],"type":"Point"}
}