{
  "type": "Feature",
  "properties": {
    "addr:full":"3150 Almaden Expy Ste 203 San Jose CA 95118",
    "addr:housenumber":"3150",
    "addr:postcode":"95118",
    "addr:street":"Almaden Expy Ste 203",
    "iso:country":"US",
    "sg:address":"3150 Almaden Expy Ste 203",
    "sg:city":"San Jose",
    "sg:classifiers":[
        {
            "category":"Insurance",
            "subcategory":"Hazard Insurance",
            "type":"Services"
        }
    ],
    "sg:phone":"+1 408 421 5555",
    "sg:postcode":"95118",
    "sg:province":"CA",
    "sg:website":"www.brauerinsurance.com",
    "wof:name":"Brauer Insurance Services",
    "wof:placetype":"venue"
},
  "geometry": {"coordinates":[-121.878345,37.276358],"type":"Point"}
}