{
  "type": "Feature",
  "properties": {
    "addr:full":"11410 Deerfield Dr Truckee CA 96161",
    "addr:housenumber":"11410",
    "addr:postcode":"96161",
    "addr:street":"Deerfield Dr",
    "iso:country":"US",
    "sg:address":"11410 Deerfield Dr",
    "sg:city":"Truckee",
    "sg:classifiers":[
        {
            "category":"Autos & Motor Vehicles",
            "subcategory":"Auto Supplies",
            "type":"Retail Goods"
        }
    ],
    "sg:phone":"+1 530 587 7107",
    "sg:postcode":"96161",
    "sg:province":"CA",
    "sg:tags":[
        "tire"
    ],
    "wof:name":"Stone's Country Tire & Auto",
    "wof:placetype":"venue"
},
  "geometry": {"coordinates":[-120.208635,39.320471],"type":"Point"}
}