{
  "type": "Feature",
  "properties": {
    "iso:country":"US",
    "sg:address":"331 Soquel Avenue",
    "sg:city":"Santa Cruz",
    "sg:classifiers":[
        {
            "category":"Professional",
            "subcategory":"Lawyer & Legal Services",
            "type":"Services"
        }
    ],
    "sg:phone":"+1 831 466 3203",
    "sg:postcode":"95062",
    "sg:province":"CA",
    "wof:name":"Law Office of Andrew J Lynch",
    "wof:placetype":"venue"
},
  "geometry": {"coordinates":[-122.02067,36.97408],"type":"Point"}
}