{
  "type": "Feature",
  "properties": {
    "iso:country":"US",
    "sg:address":"1945 E 55th St",
    "sg:city":"Los Angeles",
    "sg:classifiers":[
        {
            "category":"Freight",
            "type":"Transportation"
        }
    ],
    "sg:phone":"+1 323 589 8479",
    "sg:postcode":"90058",
    "sg:province":"CA",
    "sg:tags":[
        "arrangement"
    ],
    "wof:name":"Mountain America",
    "wof:placetype":"venue"
},
  "geometry": {"coordinates":[-118.230816,33.993012],"type":"Point"}
}