{
  "type": "Feature",
  "properties": {
    "iso:country":"US",
    "sg:address":"801 Crescent Way",
    "sg:city":"Arcata",
    "sg:classifiers":[
        {
            "category":"Health Services",
            "subcategory":"Health Practitioner",
            "type":"Services"
        }
    ],
    "sg:phone":"+1 707 825 0800",
    "sg:postcode":"95521",
    "sg:province":"CA",
    "sg:tags":[
        "therapist",
        "physical"
    ],
    "wof:name":"Spine Center",
    "wof:placetype":"venue"
},
  "geometry": {"coordinates":[-124.07392,40.858988],"type":"Point"}
}