{
  "type": "Feature",
  "properties": {
    "addr:full":"8425 N Star Way Orangevale CA 95662",
    "addr:housenumber":"8425",
    "addr:postcode":"95662",
    "addr:street":"N Star Way",
    "iso:country":"US",
    "sg:address":"8425 N Star Way",
    "sg:city":"Orangevale",
    "sg:classifiers":[
        {
            "category":"Real Estate",
            "subcategory":"Real Estate Agent",
            "type":"Services"
        }
    ],
    "sg:phone":"+1 916 725 5220",
    "sg:postcode":"95662",
    "sg:province":"CA",
    "wof:name":"Cleanlist",
    "wof:placetype":"venue"
},
  "geometry": {"coordinates":[-121.247776,38.68014],"type":"Point"}
}