{
  "type": "Feature",
  "properties": {
    "addr:full":"1760 Bay Rd East Palo Alto CA 94303",
    "addr:housenumber":"1760",
    "addr:postcode":"94303",
    "addr:street":"Bay Rd",
    "iso:country":"US",
    "sg:address":"1760 Bay Rd",
    "sg:city":"East Palo Alto",
    "sg:classifiers":[
        {
            "category":"Real Estate",
            "subcategory":"Real Estate Operator",
            "type":"Services"
        }
    ],
    "sg:phone":"+1 650 329 9605",
    "sg:postcode":"94303",
    "sg:province":"CA",
    "sg:tags":[
        "apartment"
    ],
    "wof:name":"Prodesse Property Group",
    "wof:placetype":"venue"
},
  "geometry": {"coordinates":[-122.13521299999999,37.471808],"type":"Point"}
}