{
  "type": "Feature",
  "properties": {
    "addr:full":"3810 Katella Ave Los Alamitos CA 90720",
    "addr:housenumber":"3810",
    "addr:postcode":"90720",
    "addr:street":"Katella Ave",
    "iso:country":"US",
    "sg:address":"3810 Katella Ave",
    "sg:city":"Los Alamitos",
    "sg:classifiers":[
        {
            "category":"Health Services",
            "subcategory":"Doctor",
            "type":"Services"
        }
    ],
    "sg:phone":"+1 562 598 9527",
    "sg:postcode":"90720",
    "sg:province":"CA",
    "sg:website":"www.azermd.com",
    "wof:name":"Los Alamitos Hemodialysis Center",
    "wof:placetype":"venue"
},
  "geometry": {"coordinates":[-118.066002,33.802898],"type":"Point"}
}