{
  "type": "Feature",
  "properties": {
    "addr:full":"2301 Fulkerth Rd Turlock CA 95380",
    "addr:housenumber":"2301",
    "addr:postcode":"95380",
    "addr:street":"Fulkerth Rd",
    "iso:country":"US",
    "sg:address":"2301 Fulkerth Rd",
    "sg:city":"Turlock",
    "sg:classifiers":[
        {
            "category":"Autos & Motor Vehicles",
            "subcategory":"Fuel & Gas Station",
            "type":"Retail Goods"
        }
    ],
    "sg:phone":"+1 209 668 8048",
    "sg:postcode":"95380",
    "sg:province":"CA",
    "sg:tags":[
        "oil"
    ],
    "wof:name":"Countryside Shell",
    "wof:placetype":"venue"
},
  "geometry": {"coordinates":[-120.87373100000001,37.507341],"type":"Point"}
}