{
  "type": "Feature",
  "properties": {
    "addr:full":"12067 Foothill Blvd Sylmar CA 91342",
    "addr:housenumber":"12067",
    "addr:postcode":"91342",
    "addr:street":"Foothill Blvd",
    "iso:country":"US",
    "sg:address":"12067 Foothill Blvd",
    "sg:city":"Sylmar",
    "sg:classifiers":[
        {
            "category":"Autos & Motor Vehicles",
            "subcategory":"Auto Supplies",
            "type":"Retail Goods"
        }
    ],
    "sg:phone":"+1 818 897 0195",
    "sg:postcode":"91342",
    "sg:province":"CA",
    "wof:name":"McGills Truckers Mart",
    "wof:placetype":"venue"
},
  "geometry": {"coordinates":[-118.396441,34.275441],"type":"Point"}
}