{
  "type": "Feature",
  "properties": {
    "addr:full":"5126 Stevens Creek Blvd San Jose CA 95129",
    "addr:housenumber":"5126",
    "addr:postcode":"95129",
    "addr:street":"Stevens Creek Blvd",
    "iso:country":"US",
    "sg:address":"5126 Stevens Creek Blvd",
    "sg:city":"San Jose",
    "sg:classifiers":[
        {
            "category":"Freight",
            "type":"Transportation"
        },
        {
            "category":"Professional",
            "subcategory":"Lawyer & Legal Services",
            "type":"Services"
        },
        {
            "category":"Professional",
            "subcategory":"Printing & Photocopies",
            "type":"Services"
        }
    ],
    "sg:phone":"+1 408 246 8005",
    "sg:postcode":"95129",
    "sg:province":"CA",
    "sg:tags":[
        "notary",
        "shipping"
    ],
    "wof:name":"Postnet",
    "wof:placetype":"venue"
},
  "geometry": {"coordinates":[-121.992729,37.322946],"type":"Point"}
}