{
  "type": "Feature",
  "properties": {
    "iso:country":"US",
    "sg:address":"347 Bell Ave",
    "sg:city":"Sacramento",
    "sg:classifiers":[
        {
            "category":"Shopping",
            "subcategory":"Clothing, Apparel, & Fashions",
            "type":"Retail Goods"
        }
    ],
    "sg:phone":"+1 916 971 1233",
    "sg:postcode":"95838",
    "sg:province":"CA",
    "sg:tags":[
        "maternity"
    ],
    "wof:name":"Mother-2-Bee",
    "wof:placetype":"venue"
},
  "geometry": {"coordinates":[-121.457777,38.64776],"type":"Point"}
}