{
  "type": "Feature",
  "properties": {
    "iso:country":"US",
    "sg:address":"5333 Mission Center Rd",
    "sg:city":"San Diego",
    "sg:classifiers":[
        {
            "category":"Health Services",
            "subcategory":"Doctor",
            "type":"Services"
        }
    ],
    "sg:phone":"+1 619 295 3355",
    "sg:postcode":"92108",
    "sg:province":"CA",
    "sg:tags":[
        "clinic"
    ],
    "sg:website":"www.missionvalleymedical.com",
    "wof:name":"Mission Valley Medical Clinic",
    "wof:placetype":"venue"
},
  "geometry": {"coordinates":[-117.154183,32.77331],"type":"Point"}
}