{
  "type": "Feature",
  "properties": {
    "iso:country":"US",
    "sg:address":"7200 Johnson Dr",
    "sg:city":"Pleasanton",
    "sg:classifiers":[
        {
            "category":"Professional",
            "subcategory":"Research",
            "type":"Services"
        }
    ],
    "sg:phone":"+1 925 425 6100",
    "sg:postcode":"94588",
    "sg:province":"CA",
    "sg:tags":[
        "commercial",
        "physical"
    ],
    "wof:name":"Clorox Technical Ctr",
    "wof:placetype":"venue"
},
  "geometry": {"coordinates":[-121.916551,37.691693],"type":"Point"}
}