{
  "type": "Feature",
  "properties": {
    "iso:country":"US",
    "sg:address":"499 14th St",
    "sg:city":"Oakland",
    "sg:classifiers":[
        {
            "category":"Professional",
            "subcategory":"Lawyer & Legal Services",
            "type":"Services"
        }
    ],
    "sg:phone":"+1 510 832 6200",
    "sg:postcode":"94612",
    "sg:province":"CA",
    "wof:name":"Isherwood J Scott Law Offices Of",
    "wof:placetype":"venue"
},
  "geometry": {"coordinates":[-122.27365500000001,37.805163],"type":"Point"}
}