{
  "type": "Feature",
  "properties": {
    "addr:full":"631 Cass St Monterey CA 93940",
    "addr:housenumber":"631",
    "addr:postcode":"93940",
    "addr:street":"Cass St",
    "iso:country":"US",
    "sg:address":"631 Cass St",
    "sg:city":"Monterey",
    "sg:classifiers":[
        {
            "category":"Personal",
            "subcategory":"Beauty Salon",
            "type":"Services"
        }
    ],
    "sg:phone":"+1 831 375 1500",
    "sg:postcode":"93940",
    "sg:province":"CA",
    "wof:name":"Creative Hair Design",
    "wof:placetype":"venue"
},
  "geometry": {"coordinates":[-121.894571,36.595677],"type":"Point"}
}