{
  "type": "Feature",
  "properties": {
    "addr:full":"1250 Keystone Way Vista CA 92081",
    "addr:housenumber":"1250",
    "addr:postcode":"92081",
    "addr:street":"Keystone Way",
    "iso:country":"US",
    "sg:address":"1250 Keystone Way",
    "sg:city":"Vista",
    "sg:classifiers":[
        {
            "category":"Manufacturing",
            "subcategory":"Printing",
            "type":"Manufacturing & Wholesale Goods"
        }
    ],
    "sg:phone":"+1 760 598 0092",
    "sg:postcode":"92081",
    "sg:province":"CA",
    "sg:tags":[
        "screen"
    ],
    "wof:name":"DC5 Silk Screen",
    "wof:placetype":"venue"
},
  "geometry": {"coordinates":[-117.23130399999999,33.13605],"type":"Point"}
}