{
  "type": "Feature",
  "properties": {
    "addr:full":"2350 E Vineyard Ave Oxnard CA 93036",
    "addr:housenumber":"2350",
    "addr:postcode":"93036",
    "addr:street":"E Vineyard Ave",
    "iso:country":"US",
    "sg:address":"2350 E Vineyard Ave",
    "sg:city":"Oxnard",
    "sg:classifiers":[
        {
            "category":"Manufacturing",
            "subcategory":"Printing",
            "type":"Manufacturing & Wholesale Goods"
        }
    ],
    "sg:phone":"+1 805 983 6006",
    "sg:postcode":"93036",
    "sg:province":"CA",
    "sg:tags":[
        "printer"
    ],
    "wof:name":"Fed Ex Kinko's Ofc & Print Ctr",
    "wof:placetype":"venue"
},
  "geometry": {"coordinates":[-119.175647,34.228476],"type":"Point"}
}