{
  "type": "Feature",
  "properties": {
    "iso:country":"US",
    "sg:address":"200 S Garfield Ave",
    "sg:city":"Alhambra",
    "sg:classifiers":[
        {
            "category":"Travel",
            "subcategory":"Travel Agent",
            "type":"Entertainment"
        }
    ],
    "sg:phone":"+1 626 570 9559",
    "sg:postcode":"91801",
    "sg:province":"CA",
    "sg:tags":[
        "agency",
        "bureau"
    ],
    "wof:name":"E-Z Holidays",
    "wof:placetype":"venue"
},
  "geometry": {"coordinates":[-118.124746,34.092132],"type":"Point"}
}