{
  "type": "Feature",
  "properties": {
    "addr:full":"1939 Arnold Ave Costa Mesa CA 92627",
    "addr:housenumber":"1939",
    "addr:postcode":"92627",
    "addr:street":"Arnold Ave",
    "iso:country":"US",
    "sg:address":"1939 Arnold Ave",
    "sg:city":"Costa Mesa",
    "sg:classifiers":[
        {
            "category":"Retail",
            "subcategory":"Laundry & Dry Cleaning",
            "type":"Services"
        }
    ],
    "sg:phone":"+1 949 631 1133",
    "sg:postcode":"92627",
    "sg:province":"CA",
    "sg:tags":[
        "cleaners",
        "rug",
        "carpet"
    ],
    "wof:name":"We Care Carpet Cleaners",
    "wof:placetype":"venue"
},
  "geometry": {"coordinates":[-117.926732,33.644813],"type":"Point"}
}