{
  "type": "Feature",
  "properties": {
    "addr:full":"818 W Front St Covina CA 91722",
    "addr:housenumber":"818",
    "addr:postcode":"91722",
    "addr:street":"W Front St",
    "iso:country":"US",
    "sg:address":"818 W Front St",
    "sg:city":"Covina",
    "sg:phone":"+1 626 332 1142",
    "sg:postcode":"91722",
    "sg:province":"CA",
    "sg:website":"http://www.tuckertirecompany.com",
    "wof:name":"Tucker Tire Company, Inc.",
    "wof:placetype":"venue"
},
  "geometry": {"coordinates":[-117.906249,34.091511],"type":"Point"}
}