{
  "type": "Feature",
  "properties": {
    "addr:full":"6455 Van Nuys Blvd Van Nuys CA 91401",
    "addr:housenumber":"6455",
    "addr:postcode":"91401",
    "addr:street":"Van Nuys Blvd",
    "iso:country":"US",
    "sg:address":"6455 Van Nuys Blvd",
    "sg:city":"Van Nuys",
    "sg:classifiers":[
        {
            "category":"Shopping",
            "type":"Retail Goods"
        }
    ],
    "sg:phone":"+1 818 909 6814",
    "sg:postcode":"91401",
    "sg:province":"CA",
    "sg:tags":[
        "bird",
        "merchandise"
    ],
    "wof:name":"Helen's Bird Shop",
    "wof:placetype":"venue"
},
  "geometry": {"coordinates":[-118.44879,34.188581],"type":"Point"}
}