{
  "type": "Feature",
  "properties": {
    "addr:full":"15A Sumner St San Francisco CA 94103",
    "addr:housenumber":"15a",
    "addr:postcode":"94103",
    "addr:street":"Sumner St",
    "iso:country":"US",
    "sg:address":"15A Sumner St",
    "sg:city":"San Francisco",
    "sg:classifiers":[
        {
            "category":"Travel",
            "subcategory":"Hotels & Motels",
            "type":"Entertainment"
        }
    ],
    "sg:phone":"+1 408 621 2249",
    "sg:postcode":"94103",
    "sg:province":"CA",
    "sg:tags":[
        "house",
        "guest"
    ],
    "sg:website":"www.sumnerhousesf.com",
    "wof:name":"Sumner House SF",
    "wof:placetype":"venue"
},
  "geometry": {"coordinates":[-122.410444,37.776252],"type":"Point"}
}