{
  "type": "Feature",
  "properties": {
    "addr:full":"2040 Armacost Ave Los Angeles CA 90025",
    "addr:housenumber":"2040",
    "addr:postcode":"90025",
    "addr:street":"Armacost Ave",
    "iso:country":"US",
    "sg:address":"2040 Armacost Ave",
    "sg:city":"Los Angeles",
    "sg:classifiers":[
        {
            "category":"Professional",
            "subcategory":"Engineering",
            "type":"Services"
        }
    ],
    "sg:phone":"+1 310 207 6638",
    "sg:postcode":"90025",
    "sg:province":"CA",
    "sg:tags":[
        "engineer"
    ],
    "wof:name":"Brian Cochran & Assoc",
    "wof:placetype":"venue"
},
  "geometry": {"coordinates":[-118.453192,34.033969],"type":"Point"}
}