{
  "type": "Feature",
  "properties": {
    "addr:full":"2331 Carmel Dr Palo Alto CA 94303",
    "addr:housenumber":"2331",
    "addr:postcode":"94303",
    "addr:street":"Carmel Dr",
    "iso:country":"US",
    "sg:address":"2331 Carmel Dr",
    "sg:city":"Palo Alto",
    "sg:classifiers":[
        {
            "category":"Building & Trades",
            "subcategory":"Construction",
            "type":"Services"
        }
    ],
    "sg:phone":"+1 650 857 9020",
    "sg:postcode":"94303",
    "sg:province":"CA",
    "sg:tags":[
        "house"
    ],
    "wof:name":"Groshart Construction Co",
    "wof:placetype":"venue"
},
  "geometry": {"coordinates":[-122.124272,37.445324],"type":"Point"}
}