{
  "type": "Feature",
  "properties": {
    "addr:full":"12155 Mora Dr Santa Fe Springs CA 90670",
    "addr:housenumber":"12155",
    "addr:postcode":"90670",
    "addr:street":"Mora Dr",
    "iso:country":"US",
    "sg:address":"12155 Mora Dr",
    "sg:city":"Santa Fe Springs",
    "sg:classifiers":[
        {
            "category":"Insurance",
            "subcategory":"Insurance Agent",
            "type":"Services"
        }
    ],
    "sg:phone":"+1 562 903 9831",
    "sg:postcode":"90670",
    "sg:province":"CA",
    "wof:name":"Farmers Insurance Group",
    "wof:placetype":"venue"
},
  "geometry": {"coordinates":[-118.07418,33.940053],"type":"Point"}
}