{
  "type": "Feature",
  "properties": {
    "iso:country":"US",
    "sg:address":"816 Maple Avenue",
    "sg:city":"Los Angeles",
    "sg:classifiers":[
        {
            "category":"Shopping",
            "subcategory":"Clothing, Apparel, & Fashions",
            "type":"Retail Goods"
        }
    ],
    "sg:phone":"+1 213 623 3510",
    "sg:postcode":"90014",
    "sg:province":"CA",
    "sg:tags":[
        "lingerie"
    ],
    "wof:name":"Lucky Lingerie Plus",
    "wof:placetype":"venue"
},
  "geometry": {"coordinates":[-118.25148799999999,34.04071],"type":"Point"}
}