{
  "type": "Feature",
  "properties": {
    "addr:full":"5176 State Rte 49 Mariposa CA 95338",
    "addr:housenumber":"5176",
    "addr:postcode":"95338",
    "addr:street":"State Rte 49",
    "iso:country":"US",
    "sg:address":"5176 State Rte 49",
    "sg:city":"Mariposa",
    "sg:classifiers":[
        {
            "category":"Retail",
            "subcategory":"Car Wash",
            "type":"Services"
        }
    ],
    "sg:phone":"+1 209 742 4418",
    "sg:postcode":"95338",
    "sg:province":"CA",
    "sg:tags":[
        "automobile",
        "detail",
        "clean"
    ],
    "wof:name":"Dave's Mountain Detail & Tint",
    "wof:placetype":"venue"
},
  "geometry": {"coordinates":[-119.97443800000001,37.492969],"type":"Point"}
}