{
  "type": "Feature",
  "properties": {
    "iso:country":"US",
    "sg:address":"3909 Clay St",
    "sg:city":"Sacramento",
    "sg:classifiers":[
        {
            "category":"Building & Trades",
            "subcategory":"Construction",
            "type":"Services"
        }
    ],
    "sg:phone":"+1 916 628 0130",
    "sg:postcode":"95838",
    "sg:province":"CA",
    "sg:tags":[
        "handyman"
    ],
    "wof:name":"Generations Handyman Svc",
    "wof:placetype":"venue"
},
  "geometry": {"coordinates":[-121.4396,38.640075],"type":"Point"}
}