{
  "type": "Feature",
  "properties": {
    "addr:full":"200 3rd St Los Altos CA 94022",
    "addr:housenumber":"200",
    "addr:postcode":"94022",
    "addr:street":"3Rd St",
    "iso:country":"US",
    "sg:address":"200 3rd St",
    "sg:city":"Los Altos",
    "sg:classifiers":[
        {
            "category":"Personal",
            "subcategory":"Beauty Salon",
            "type":"Services"
        }
    ],
    "sg:phone":"+1 650 941 8892",
    "sg:postcode":"94022",
    "sg:province":"CA",
    "wof:name":"L'Image Salon",
    "wof:placetype":"venue"
},
  "geometry": {"coordinates":[-122.11538,37.378479],"type":"Point"}
}