{
  "type": "Feature",
  "properties": {
    "iso:country":"US",
    "sg:address":"2730 State St",
    "sg:city":"Carlsbad",
    "sg:classifiers":[
        {
            "category":"Retail",
            "subcategory":"Auto Repair",
            "type":"Services"
        }
    ],
    "sg:phone":"+1 760 434 7903",
    "sg:postcode":"92008",
    "sg:province":"CA",
    "sg:tags":[
        "repairing",
        "automobile"
    ],
    "wof:name":"Autohaus Frankfurt LLC",
    "wof:placetype":"venue"
},
  "geometry": {"coordinates":[-117.350293,33.161652],"type":"Point"}
}