{
  "type": "Feature",
  "properties": {
    "iso:country":"US",
    "sg:address":"2099 E North Ave",
    "sg:city":"Fresno",
    "sg:classifiers":[
        {
            "category":"Wholesale",
            "subcategory":"Groceries",
            "type":"Manufacturing & Wholesale Goods"
        }
    ],
    "sg:phone":"+1 559 237 5500",
    "sg:postcode":"93725",
    "sg:province":"CA",
    "sg:tags":[
        "beverage"
    ],
    "wof:name":"R K Jones Enterprises",
    "wof:placetype":"venue"
},
  "geometry": {"coordinates":[-119.75096000000001,36.692305],"type":"Point"}
}