{
  "type": "Feature",
  "properties": {
    "addr:full":"1255 10th St Santa Monica CA 90401",
    "addr:housenumber":"1255",
    "addr:postcode":"90401",
    "addr:street":"10Th St",
    "iso:country":"US",
    "sg:address":"1255 10th St",
    "sg:city":"Santa Monica",
    "sg:classifiers":[
        {
            "category":"Building & Trades",
            "subcategory":"Construction",
            "type":"Services"
        }
    ],
    "sg:phone":"+1 310 393 9054",
    "sg:postcode":"90401",
    "sg:province":"CA",
    "sg:tags":[
        "coping",
        "plastering",
        "tiling",
        "pool",
        "swimming"
    ],
    "wof:name":"Manny's Pool & Spa",
    "wof:placetype":"venue"
},
  "geometry": {"coordinates":[-118.491789,34.023156],"type":"Point"}
}