{
  "type": "Feature",
  "properties": {
    "addr:full":"3435 Chestnut Ave Concord CA 94519",
    "addr:housenumber":"3435",
    "addr:postcode":"94519",
    "addr:street":"Chestnut Ave",
    "iso:country":"US",
    "sg:address":"3435 Chestnut Ave",
    "sg:city":"Concord",
    "sg:classifiers":[
        {
            "category":"Health Services",
            "subcategory":"Doctor",
            "type":"Services"
        }
    ],
    "sg:phone":"+1 925 685 8994",
    "sg:postcode":"94519",
    "sg:province":"CA",
    "sg:tags":[
        "dentist"
    ],
    "wof:name":"Daniel L Howlett Inc",
    "wof:placetype":"venue"
},
  "geometry": {"coordinates":[-122.010739,37.971752],"type":"Point"}
}