{
  "type": "Feature",
  "properties": {
    "iso:country":"US",
    "sg:address":"9150 W Olympic Blvd",
    "sg:city":"Beverly Hills",
    "sg:classifiers":[
        {
            "category":"Utilities",
            "subcategory":"Mobile Phone",
            "type":"Services"
        }
    ],
    "sg:phone":"+1 310 858 0100",
    "sg:postcode":"90212",
    "sg:province":"CA",
    "sg:tags":[
        "telephone",
        "cellular"
    ],
    "wof:name":"T Mobile",
    "wof:placetype":"venue"
},
  "geometry": {"coordinates":[-118.391001,34.059318],"type":"Point"}
}