{
  "type": "Feature",
  "properties": {
    "addr:full":"3235 N San Fernando Road Los Angeles CA 90065",
    "addr:housenumber":"3235",
    "addr:postcode":"90065",
    "addr:street":"N San Fernando Road",
    "iso:country":"US",
    "sg:address":"3235 N San Fernando Road",
    "sg:city":"Los Angeles",
    "sg:classifiers":[
        {
            "category":"Shopping",
            "subcategory":"Stationery & Office Supplies",
            "type":"Retail Goods"
        }
    ],
    "sg:phone":"+1 323 982 0969",
    "sg:postcode":"90065",
    "sg:province":"CA",
    "sg:tags":[
        "equipment"
    ],
    "wof:name":"Oasis Business Supply Corporation",
    "wof:placetype":"venue"
},
  "geometry": {"coordinates":[-118.248058,34.11716],"type":"Point"}
}