{
  "type": "Feature",
  "properties": {
    "iso:country":"US",
    "sg:address":"5703 Oberlin Dr",
    "sg:city":"San Diego",
    "sg:classifiers":[
        {
            "category":"Banks & Credit Unions",
            "subcategory":"Bank",
            "type":"Services"
        }
    ],
    "sg:phone":"+1 858 623 9102",
    "sg:postcode":"92121",
    "sg:province":"CA",
    "sg:tags":[
        "loan",
        "real estate"
    ],
    "wof:name":"Premier Mortgage Funding",
    "wof:placetype":"venue"
},
  "geometry": {"coordinates":[-117.193104,32.896202],"type":"Point"}
}