{
  "type": "Feature",
  "properties": {
    "addr:full":"12116 Severn Way Riverside CA 92503",
    "addr:housenumber":"12116",
    "addr:postcode":"92503",
    "addr:street":"Severn Way",
    "iso:country":"US",
    "sg:address":"12116 Severn Way",
    "sg:city":"Riverside",
    "sg:classifiers":[
        {
            "category":"Communications",
            "subcategory":"Television Station",
            "type":"Services"
        }
    ],
    "sg:phone":"+1 951 279 0418",
    "sg:postcode":"92503",
    "sg:province":"CA",
    "sg:tags":[
        "network"
    ],
    "wof:name":"Connex Communications",
    "wof:placetype":"venue"
},
  "geometry": {"coordinates":[-117.49906,33.896805],"type":"Point"}
}