{
  "type": "Feature",
  "properties": {
    "iso:country":"US",
    "sg:address":"17127 Pomona Rincon Rd",
    "sg:city":"Chino",
    "sg:classifiers":[
        {
            "category":"Museum",
            "type":"Entertainment"
        }
    ],
    "sg:phone":"+1 909 795 3485",
    "sg:postcode":"91708",
    "sg:province":"CA",
    "sg:tags":[
        "executive",
        "gallery"
    ],
    "wof:name":"Museums",
    "wof:placetype":"venue"
},
  "geometry": {"coordinates":[-117.66871,33.946867],"type":"Point"}
}