{
  "type": "Feature",
  "properties": {
    "iso:country":"US",
    "sg:address":"2107 W Commonwealth Ave",
    "sg:city":"Alhambra",
    "sg:classifiers":[
        {
            "category":"Food & Beverages",
            "subcategory":"Bakery",
            "type":"Retail Goods"
        }
    ],
    "sg:phone":"+1 626 300 8668",
    "sg:postcode":"91803",
    "sg:province":"CA",
    "sg:tags":[
        "sandwich"
    ],
    "wof:name":"Sub Station II",
    "wof:placetype":"venue"
},
  "geometry": {"coordinates":[-118.14299800000001,34.0755],"type":"Point"}
}