{
  "type": "Feature",
  "properties": {
    "iso:country":"US",
    "sg:address":"611 Bridgeway",
    "sg:city":"Sausalito",
    "sg:classifiers":[
        {
            "category":"Winery",
            "type":"Food & Drink"
        }
    ],
    "sg:phone":"+1 415 332 0105",
    "sg:postcode":"94965",
    "sg:province":"CA",
    "sg:website":"www.realnapa.com",
    "wof:name":"Real Napa",
    "wof:placetype":"venue"
},
  "geometry": {"coordinates":[-122.47897500000001,37.85447],"type":"Point"}
}