{
  "type": "Feature",
  "properties": {
    "addr:full":"6040 Telegraph Rd Ventura CA 93003",
    "addr:housenumber":"6040",
    "addr:postcode":"93003",
    "addr:street":"Telegraph Rd",
    "iso:country":"US",
    "sg:address":"6040 Telegraph Rd",
    "sg:city":"Ventura",
    "sg:classifiers":[
        {
            "category":"Food & Beverages",
            "subcategory":"Groceries & Convenience Stores",
            "type":"Retail Goods"
        }
    ],
    "sg:phone":"+1 805 650 2150",
    "sg:postcode":"93003",
    "sg:province":"CA",
    "sg:tags":[
        "grocer"
    ],
    "wof:name":"Vons Co",
    "wof:placetype":"venue"
},
  "geometry": {"coordinates":[-119.212964,34.278135],"type":"Point"}
}