{
  "type": "Feature",
  "properties": {
    "iso:country":"US",
    "sg:address":"701 Highland Springs Ave",
    "sg:city":"Beaumont",
    "sg:classifiers":[
        {
            "category":"Health Services",
            "subcategory":"Doctor",
            "type":"Services"
        }
    ],
    "sg:phone":"+1 951 845 4822",
    "sg:postcode":"92223",
    "sg:province":"CA",
    "sg:tags":[
        "dentist"
    ],
    "wof:name":"Steve Loper Inc",
    "wof:placetype":"venue"
},
  "geometry": {"coordinates":[-116.946915,33.936976],"type":"Point"}
}