{
  "type": "Feature",
  "properties": {
    "iso:country":"US",
    "sg:address":"2001 21st St",
    "sg:city":"Sacramento",
    "sg:classifiers":[
        {
            "category":"Professional",
            "subcategory":"Detective & Security Services",
            "type":"Services"
        }
    ],
    "sg:phone":"+1 916 454 4642",
    "sg:postcode":"95818",
    "sg:province":"CA",
    "sg:tags":[
        "investigator"
    ],
    "wof:name":"Sunrise Investigative Svc",
    "wof:placetype":"venue"
},
  "geometry": {"coordinates":[-121.483571,38.564766],"type":"Point"}
}