{
  "type": "Feature",
  "properties": {
    "addr:full":"3337 Michelson Dr Ste Cn-720 Irvine CA 92612",
    "addr:housenumber":"3337",
    "addr:postcode":"92612",
    "addr:street":"Michelson Dr Ste Cn-720",
    "iso:country":"US",
    "sg:address":"3337 Michelson Dr Ste Cn-720",
    "sg:city":"Irvine",
    "sg:classifiers":[
        {
            "category":"Real Estate",
            "subcategory":"Real Estate Services",
            "type":"Services"
        },
        {
            "category":"Real Estate",
            "subcategory":"Real Estate Agent",
            "type":"Services"
        }
    ],
    "sg:phone":"+1 949 748 3962",
    "sg:postcode":"92612",
    "sg:province":"CA",
    "sg:tags":[
        "buyer",
        "management",
        "broker"
    ],
    "wof:name":"Maguire Properties Inc",
    "wof:placetype":"venue"
},
  "geometry": {"coordinates":[-117.84048300000001,33.670435],"type":"Point"}
}