{
  "type": "Feature",
  "properties": {
    "addr:full":"4814 N Vecino Dr Covina CA 91722",
    "addr:housenumber":"4814",
    "addr:postcode":"91722",
    "addr:street":"N Vecino Dr",
    "iso:country":"US",
    "sg:address":"4814 N Vecino Dr",
    "sg:city":"Covina",
    "sg:classifiers":[
        {
            "category":"Banks & Credit Unions",
            "subcategory":"Investment Brokerage",
            "type":"Services"
        }
    ],
    "sg:phone":"+1 626 332 8417",
    "sg:postcode":"91722",
    "sg:province":"CA",
    "sg:tags":[
        "trust"
    ],
    "wof:name":"Russell Family Trust 04 1",
    "wof:placetype":"venue"
},
  "geometry": {"coordinates":[-117.876645,34.099785],"type":"Point"}
}