{
  "type": "Feature",
  "properties": {
    "addr:full":"250 Elm Street San Mateo CA 94401",
    "addr:housenumber":"250",
    "addr:postcode":"94401",
    "addr:street":"Elm Street",
    "iso:country":"US",
    "sg:address":"250 Elm Street",
    "sg:city":"San Mateo",
    "sg:classifiers":[
        {
            "category":"Real Estate",
            "subcategory":"Real Estate Operator",
            "type":"Services"
        }
    ],
    "sg:phone":"+1 650 342 4477",
    "sg:postcode":"94401",
    "sg:province":"CA",
    "sg:tags":[
        "apartment"
    ],
    "wof:name":"Royal Arms Apartments",
    "wof:placetype":"venue"
},
  "geometry": {"coordinates":[-122.331416,37.569558],"type":"Point"}
}