{
  "type": "Feature",
  "properties": {
    "addr:full":"33 3rd St San Francisco CA 94103",
    "addr:housenumber":"33",
    "addr:postcode":"94103",
    "addr:street":"3Rd St",
    "iso:country":"US",
    "sg:address":"33 3rd St",
    "sg:city":"San Francisco",
    "sg:classifiers":[
        {
            "category":"Shopping",
            "subcategory":"Stationery & Office Supplies",
            "type":"Retail Goods"
        }
    ],
    "sg:phone":"+1 415 777 1728",
    "sg:postcode":"94103",
    "sg:province":"CA",
    "sg:tags":[
        "printing"
    ],
    "wof:name":"Office Depot",
    "wof:placetype":"venue"
},
  "geometry": {"coordinates":[-122.402905,37.786989],"type":"Point"}
}