{
  "type": "Feature",
  "properties": {
    "addr:full":"5455 S Fresno Rd Le Grand CA 95333",
    "addr:housenumber":"5455",
    "addr:postcode":"95333",
    "addr:street":"S Fresno Rd",
    "iso:country":"US",
    "sg:address":"5455 S Fresno Rd",
    "sg:city":"Le Grand",
    "sg:classifiers":[
        {
            "category":"Wholesale",
            "subcategory":"Electrical",
            "type":"Manufacturing & Wholesale Goods"
        }
    ],
    "sg:phone":"+1 209 389 4400",
    "sg:postcode":"95333",
    "sg:province":"CA",
    "sg:tags":[
        "alarm",
        "burglar",
        "system"
    ],
    "wof:name":"Matson Alarm Co Inc",
    "wof:placetype":"venue"
},
  "geometry": {"coordinates":[-120.243792,37.207868],"type":"Point"}
}