{
  "type": "Feature",
  "properties": {
    "addr:full":"2920 Arden Way Sacramento CA 95825",
    "addr:housenumber":"2920",
    "addr:postcode":"95825",
    "addr:street":"Arden Way",
    "iso:country":"US",
    "sg:address":"2920 Arden Way",
    "sg:city":"Sacramento",
    "sg:classifiers":[
        {
            "category":"Personal",
            "subcategory":"Beauty Salon",
            "type":"Services"
        }
    ],
    "sg:phone":"+1 916 489 5462",
    "sg:postcode":"95825",
    "sg:province":"CA",
    "sg:tags":[
        "hair"
    ],
    "wof:name":"Lima Salon & Spa",
    "wof:placetype":"venue"
},
  "geometry": {"coordinates":[-121.396135,38.595893],"type":"Point"}
}