{
  "type": "Feature",
  "properties": {
    "addr:full":"40857 Sierra Dr Three Rivers CA 93271",
    "addr:housenumber":"40857",
    "addr:postcode":"93271",
    "addr:street":"Sierra Dr",
    "iso:country":"US",
    "sg:address":"40857 Sierra Dr",
    "sg:city":"Three Rivers",
    "sg:classifiers":[
        {
            "category":"Government",
            "subcategory":"Post Office",
            "type":"Public Place"
        }
    ],
    "sg:phone":"+1 559 561 4261",
    "sg:postcode":"93271",
    "sg:province":"CA",
    "wof:name":"US Post Office",
    "wof:placetype":"venue"
},
  "geometry": {"coordinates":[-118.916454,36.422094],"type":"Point"}
}