{
  "type": "Feature",
  "properties": {
    "addr:full":"16805 Montgomery Ave Fontana CA 92336",
    "addr:housenumber":"16805",
    "addr:postcode":"92336",
    "addr:street":"Montgomery Ave",
    "iso:country":"US",
    "sg:address":"16805 Montgomery Ave",
    "sg:city":"Fontana",
    "sg:classifiers":[
        {
            "category":"Shopping",
            "subcategory":"Catalog Store",
            "type":"Retail Goods"
        }
    ],
    "sg:phone":"+1 909 574 9090",
    "sg:postcode":"92336",
    "sg:province":"CA",
    "sg:tags":[
        "mail",
        "order"
    ],
    "wof:name":"H & I Giftz",
    "wof:placetype":"venue"
},
  "geometry": {"coordinates":[-117.438183,34.119326],"type":"Point"}
}