{
  "type": "Feature",
  "properties": {
    "iso:country":"US",
    "sg:address":"1362 N Quince Ave",
    "sg:city":"Upland",
    "sg:classifiers":[
        {
            "category":"Freight",
            "type":"Transportation"
        }
    ],
    "sg:phone":"+1 909 579 0450",
    "sg:postcode":"91786",
    "sg:province":"CA",
    "sg:tags":[
        "consultant"
    ],
    "wof:name":"Independent Freight Surveys",
    "wof:placetype":"venue"
},
  "geometry": {"coordinates":[-117.654517,34.111917],"type":"Point"}
}