{
  "type": "Feature",
  "properties": {
    "addr:full":"520 Mendocino Ave Santa Rosa CA 95401",
    "addr:housenumber":"520",
    "addr:postcode":"95401",
    "addr:street":"Mendocino Ave",
    "iso:country":"US",
    "sg:address":"520 Mendocino Ave",
    "sg:city":"Santa Rosa",
    "sg:classifiers":[
        {
            "category":"Social Services",
            "subcategory":"Job Training",
            "type":"Services"
        }
    ],
    "sg:phone":"+1 707 823 7889",
    "sg:postcode":"95401",
    "sg:province":"CA",
    "sg:tags":[
        "career",
        "counseling",
        "vocational"
    ],
    "wof:name":"Work Wise",
    "wof:placetype":"venue"
},
  "geometry": {"coordinates":[-122.715932,38.443206],"type":"Point"}
}