{
  "type": "Feature",
  "properties": {
    "addr:full":"893 Monarch Dr Corona CA 92879",
    "addr:housenumber":"893",
    "addr:postcode":"92879",
    "addr:street":"Monarch Dr",
    "iso:country":"US",
    "sg:address":"893 Monarch Dr",
    "sg:city":"Corona",
    "sg:classifiers":[
        {
            "category":"Professional",
            "type":"Services"
        }
    ],
    "sg:phone":"+1 951 279 1843",
    "sg:postcode":"92879",
    "sg:province":"CA",
    "wof:name":"Darwin Price",
    "wof:placetype":"venue"
},
  "geometry": {"coordinates":[-117.55123500000001,33.855234],"type":"Point"}
}