{
  "type": "Feature",
  "properties": {
    "iso:country":"US",
    "sg:address":"893 Monarch Dr",
    "sg:city":"Corona",
    "sg:classifiers":[
        {
            "category":"Professional",
            "type":"Services"
        }
    ],
    "sg:phone":"+1 951 279 1843",
    "sg:postcode":"92879",
    "sg:province":"CA",
    "wof:name":"Darwin Price",
    "wof:placetype":"venue"
},
  "geometry": {"coordinates":[-117.551235,33.855234],"type":"Point"}
}