{
  "type": "Feature",
  "properties": {
    "addr:full":"44590 Cam Gonzales Temecula CA 92592",
    "addr:housenumber":"44590",
    "addr:postcode":"92592",
    "addr:street":"Cam Gonzales",
    "iso:country":"US",
    "sg:address":"44590 Cam Gonzales",
    "sg:city":"Temecula",
    "sg:classifiers":[
        {
            "category":"Professional",
            "subcategory":"Computer Services",
            "type":"Services"
        }
    ],
    "sg:phone":"+1 951 303 0355",
    "sg:postcode":"92592",
    "sg:province":"CA",
    "sg:tags":[
        "repair"
    ],
    "wof:name":"Pacific Pharmacy Computers Inc",
    "wof:placetype":"venue"
},
  "geometry": {"coordinates":[-117.07441300000001,33.478683],"type":"Point"}
}