{
  "type": "Feature",
  "properties": {
    "addr:full":"4222 N Sierra Way San Bernardino CA 92407",
    "addr:housenumber":"4222",
    "addr:postcode":"92407",
    "addr:street":"N Sierra Way",
    "iso:country":"US",
    "sg:address":"4222 N Sierra Way",
    "sg:city":"San Bernardino",
    "sg:classifiers":[
        {
            "category":"Shopping",
            "subcategory":"Bicycles & Sporting Goods",
            "type":"Retail Goods"
        }
    ],
    "sg:phone":"+1 909 881 5166",
    "sg:postcode":"92407",
    "sg:province":"CA",
    "sg:tags":[
        "repair",
        "gun",
        "gunsmith"
    ],
    "wof:name":"Gordon's Gun Shop",
    "wof:placetype":"venue"
},
  "geometry": {"coordinates":[-117.2851,34.165382],"type":"Point"}
}