{
  "type": "Feature",
  "properties": {
    "addr:full":"4916 Venice Boulevard Los Angeles CA 90019",
    "addr:housenumber":"4916",
    "addr:postcode":"90019",
    "addr:street":"Venice Boulevard",
    "iso:country":"US",
    "sg:address":"4916 Venice Boulevard",
    "sg:city":"Los Angeles",
    "sg:classifiers":[
        {
            "category":"Retail",
            "subcategory":"Auto Repair",
            "type":"Services"
        }
    ],
    "sg:phone":"+1 323 937 1329",
    "sg:postcode":"90019",
    "sg:province":"CA",
    "wof:name":"Cnl International",
    "wof:placetype":"venue"
},
  "geometry": {"coordinates":[-118.344185,34.046038],"type":"Point"}
}