{
  "type": "Feature",
  "properties": {
    "addr:full":"1265 Tavistock Ln Lincoln CA 95648",
    "addr:housenumber":"1265",
    "addr:postcode":"95648",
    "addr:street":"Tavistock Ln",
    "iso:country":"US",
    "sg:address":"1265 Tavistock Ln",
    "sg:city":"Lincoln",
    "sg:classifiers":[
        {
            "category":"Building & Trades",
            "subcategory":"Construction",
            "type":"Services"
        }
    ],
    "sg:phone":"+1 916 543 4386",
    "sg:postcode":"95648",
    "sg:province":"CA",
    "sg:tags":[
        "wallcoverings-installation",
        "wallpaper",
        "painting",
        "contractor"
    ],
    "wof:name":"Cook's Custom Painting",
    "wof:placetype":"venue"
},
  "geometry": {"coordinates":[-121.304496,38.860419],"type":"Point"}
}