{
  "type": "Feature",
  "properties": {
    "iso:country":"US",
    "sg:address":"6424 Pacific Blvd",
    "sg:city":"Huntington Park",
    "sg:classifiers":[
        {
            "category":"Shopping",
            "subcategory":"Mobile Phones",
            "type":"Retail Goods"
        }
    ],
    "sg:phone":"+1 323 588 1480",
    "sg:postcode":"90255",
    "sg:province":"CA",
    "wof:name":"Boost Mobile Retailer",
    "wof:placetype":"venue"
},
  "geometry": {"coordinates":[-118.224959,33.98135],"type":"Point"}
}