{
  "type": "Feature",
  "properties": {
    "iso:country":"US",
    "sg:address":"2238 el Camino Real",
    "sg:city":"Santa Clara",
    "sg:classifiers":[
        {
            "category":"Health Services",
            "subcategory":"Chiropractor",
            "type":"Services"
        }
    ],
    "sg:phone":"+1 408 735 7028",
    "sg:postcode":"95050",
    "sg:province":"CA",
    "wof:name":"Bostock Chiropractic Offices",
    "wof:placetype":"venue"
},
  "geometry": {"coordinates":[-121.9649,37.35227],"type":"Point"}
}