{
  "type": "Feature",
  "properties": {
    "iso:country":"US",
    "sg:address":"1315 Woodcreek Way",
    "sg:city":"Stockton",
    "sg:classifiers":[
        {
            "category":"Education",
            "subcategory":"School",
            "type":"Public Place"
        }
    ],
    "sg:phone":"+1 209 953 8125",
    "sg:postcode":"95209",
    "sg:province":"CA",
    "wof:name":"Head Start Child Development",
    "wof:placetype":"venue"
},
  "geometry": {"coordinates":[-121.32930899999999,38.033967],"type":"Point"}
}