{
  "type": "Feature",
  "properties": {
    "addr:city":"Oakland",
    "addr:full":"540 Water St Oakland, Ca 94607",
    "addr:house_number":"540",
    "addr:housenumber":"540",
    "addr:phone":"+1 510-627-1215",
    "addr:postcode":"94607",
    "addr:road":"Water St",
    "addr:state":"CA",
    "addr:street":"Water St",
    "iso:country":"US",
    "sg:address":"540 Water St",
    "sg:city":"Oakland",
    "sg:classifiers":[
        {
            "category":"Museum",
            "type":"Entertainment"
        }
    ],
    "sg:phone":"+1 510 627 1502",
    "sg:postcode":"94607",
    "sg:province":"CA",
    "sg:website":"www.usspotomac.org",
    "wof:airports":[
        102527513,
        102531041,
        102532543
    ],
    "wof:name":"Uss Potomac",
    "wof:placetype":"venue"
},
  "geometry": {"coordinates":[-122.27504,37.79387],"type":"Point"}
}