{
  "type": "Feature",
  "properties": {
    "iso:country":"US",
    "sg:address":"540 Water St",
    "sg:city":"Oakland",
    "sg:classifiers":[
        {
            "category":"Museum",
            "type":"Entertainment"
        }
    ],
    "sg:phone":"+1 510 627 1502",
    "sg:postcode":"94607",
    "sg:province":"CA",
    "sg:website":"www.usspotomac.org",
    "wof:name":"USS Potomac",
    "wof:placetype":"venue"
},
  "geometry": {"coordinates":[-122.27952399999999,37.795672],"type":"Point"}
}