{
  "type": "Feature",
  "properties": {
    "iso:country":"US",
    "sg:address":"120 Fishermans Wharf",
    "sg:city":"Redondo Beach",
    "sg:classifiers":[
        {
            "category":"Professional",
            "subcategory":"Detective & Security Services",
            "type":"Services"
        }
    ],
    "sg:phone":"+1 310 798 8976",
    "sg:postcode":"90277",
    "sg:province":"CA",
    "sg:tags":[
        "investigator"
    ],
    "wof:name":"Thomas Romero Investigations",
    "wof:placetype":"venue"
},
  "geometry": {"coordinates":[-118.38936099999999,33.838492],"type":"Point"}
}