{
  "type": "Feature",
  "properties": {
    "addr:full":"15112 Rattlesnake Creek Rd Fort Jones CA 96032",
    "addr:postcode":"15112;96032",
    "addr:street":"Rattlesnake Creek Rd",
    "iso:country":"US",
    "sg:address":"15112 Rattlesnake Creek Rd",
    "sg:city":"Fort Jones",
    "sg:classifiers":[
        {
            "category":"Building & Trades",
            "subcategory":"Construction",
            "type":"Services"
        }
    ],
    "sg:phone":"+1 530 468 5742",
    "sg:postcode":"96032",
    "sg:province":"CA",
    "sg:tags":[
        "grading",
        "contractor"
    ],
    "wof:name":"G F Whilock Grading & Excavate",
    "wof:placetype":"venue"
},
  "geometry": {"coordinates":[-122.89013199999999,41.670806],"type":"Point"}
}