{
  "type": "Feature",
  "properties": {
    "iso:country":"US",
    "sg:address":"742 N Mansfield Ave",
    "sg:city":"Los Angeles",
    "sg:classifiers":[
        {
            "category":"Building & Trades",
            "subcategory":"Plumbing",
            "type":"Services"
        }
    ],
    "sg:phone":"+1 323 939 7272",
    "sg:postcode":"90038",
    "sg:province":"CA",
    "sg:tags":[
        "conditioning",
        "air",
        "system",
        "contractor"
    ],
    "wof:name":"Ward's Heating & Air",
    "wof:placetype":"venue"
},
  "geometry": {"coordinates":[-118.340546,34.08449],"type":"Point"}
}