{
  "type": "Feature",
  "properties": {
    "addr:full":"409 Borrego Ct San Dimas CA 91773",
    "addr:housenumber":"409",
    "addr:postcode":"91773",
    "addr:street":"Borrego Ct",
    "iso:country":"US",
    "sg:address":"409 Borrego Ct",
    "sg:city":"San Dimas",
    "sg:classifiers":[
        {
            "category":"Professional",
            "subcategory":"Business Services",
            "type":"Services"
        }
    ],
    "sg:phone":"+1 909 592 0612",
    "sg:postcode":"91773",
    "sg:province":"CA",
    "sg:tags":[
        "embroidery"
    ],
    "wof:name":"Paradise Co",
    "wof:placetype":"venue"
},
  "geometry": {"coordinates":[-117.81692200000001,34.101889],"type":"Point"}
}