{
  "type": "Feature",
  "properties": {
    "addr:full":"12 S 1st Street San Jose CA 95113",
    "addr:housenumber":"12",
    "addr:postcode":"95113",
    "addr:street":"S 1St Street",
    "iso:country":"US",
    "sg:address":"12 S 1st Street",
    "sg:city":"San Jose",
    "sg:classifiers":[
        {
            "category":"Professional",
            "type":"Services"
        }
    ],
    "sg:phone":"+1 408 295 1563",
    "sg:postcode":"95113",
    "sg:province":"CA",
    "sg:tags":[
        "caterer"
    ],
    "wof:name":"Catered Too Sales Office",
    "wof:placetype":"venue"
},
  "geometry": {"coordinates":[-121.890342,37.335978],"type":"Point"}
}