{
  "type": "Feature",
  "properties": {
    "iso:country":"US",
    "sg:address":"44600 Indian Wells Ln",
    "sg:city":"Indian Wells",
    "sg:classifiers":[
        {
            "category":"Restaurant",
            "type":"Food & Drink"
        }
    ],
    "sg:phone":"+1 760 674 4165",
    "sg:postcode":"92210",
    "sg:province":"CA",
    "wof:name":"Santa Rosa Grille",
    "wof:placetype":"venue"
},
  "geometry": {"coordinates":[-116.330083,33.723301],"type":"Point"}
}