{
  "type": "Feature",
  "properties": {
    "addr:full":"6519 S. Sepulveda Blvd Los Angeles CA 90045",
    "addr:housenumber":"6519",
    "addr:postcode":"90045",
    "addr:street":"S. Sepulveda Blvd",
    "iso:country":"US",
    "sg:address":"6519 S. Sepulveda Blvd",
    "sg:city":"Los Angeles",
    "sg:classifiers":[
        {
            "category":"Banks & Credit Unions",
            "subcategory":"Financial Services",
            "type":"Services"
        }
    ],
    "sg:phone":"+1 310 641 9724",
    "sg:postcode":"90045",
    "sg:province":"CA",
    "sg:tags":[
        "broker",
        "mortgage"
    ],
    "wof:name":"HomeLendingStore.net",
    "wof:placetype":"venue"
},
  "geometry": {"coordinates":[-118.39463499999999,33.980476],"type":"Point"}
}