{
  "type": "Feature",
  "properties": {
    "addr:full":"51600 Tyler St Apt 38 Coachella CA 92236",
    "addr:housenumber":"51600",
    "addr:postcode":"92236",
    "addr:street":"Tyler St Apt 38",
    "iso:country":"US",
    "sg:address":"51600 Tyler St Apt 38",
    "sg:city":"Coachella",
    "sg:classifiers":[
        {
            "category":"Real Estate",
            "subcategory":"Real Estate Services",
            "type":"Services"
        },
        {
            "category":"Real Estate",
            "subcategory":"Real Estate Agent",
            "type":"Services"
        },
        {
            "category":"Real Estate",
            "subcategory":"Real Estate Operator",
            "type":"Services"
        }
    ],
    "sg:phone":"+1 760 398 2820",
    "sg:postcode":"92236",
    "sg:province":"CA",
    "sg:tags":[
        "management",
        "vacancy",
        "apartment",
        "listing",
        "rental",
        "finder"
    ],
    "wof:name":"Las Casas Apartments",
    "wof:placetype":"venue"
},
  "geometry": {"coordinates":[-116.16386199999999,33.673826],"type":"Point"}
}