{
  "type": "Feature",
  "properties": {
    "iso:country":"US",
    "sg:address":"1344 Seabright Ave",
    "sg:city":"Long Beach",
    "sg:classifiers":[
        {
            "category":"Food & Beverages",
            "subcategory":"Groceries & Convenience Stores",
            "type":"Retail Goods"
        }
    ],
    "sg:phone":"+1 562 435 1106",
    "sg:postcode":"90813",
    "sg:province":"CA",
    "sg:tags":[
        "product"
    ],
    "wof:name":"Joy Processed Foods",
    "wof:placetype":"venue"
},
  "geometry": {"coordinates":[-118.21756499999999,33.784103],"type":"Point"}
}