{
  "type": "Feature",
  "properties": {
    "addr:full":"17035 Road 26 Ste B Madera CA 93638",
    "addr:housenumber":"17035",
    "addr:postcode":"93638",
    "addr:street":"Road 26 Ste B",
    "iso:country":"US",
    "sg:address":"17035 Road 26 Ste B",
    "sg:city":"Madera",
    "sg:classifiers":[
        {
            "category":"Real Estate",
            "subcategory":"Real Estate Services",
            "type":"Services"
        },
        {
            "category":"Professional",
            "subcategory":"Business Services",
            "type":"Services"
        },
        {
            "category":"Real Estate",
            "subcategory":"Surveying",
            "type":"Services"
        }
    ],
    "sg:phone":"+1 559 674 3120",
    "sg:postcode":"93638",
    "sg:province":"CA",
    "sg:tags":[
        "appraisers-business",
        "industrial",
        "appraisers-commercial",
        "commercial",
        "broker",
        "buyer",
        "appraiser"
    ],
    "wof:name":"Johnson Appraisal Service",
    "wof:placetype":"venue"
},
  "geometry": {"coordinates":[-120.07426,36.996794],"type":"Point"}
}