{
  "type": "Feature",
  "properties": {
    "addr:full":"1041 S Main St Burbank CA 91506",
    "addr:housenumber":"1041",
    "addr:postcode":"91506",
    "addr:street":"S Main St",
    "iso:country":"US",
    "sg:address":"1041 S Main St",
    "sg:city":"Burbank",
    "sg:classifiers":[
        {
            "category":"Health Services",
            "subcategory":"Nursing And Care Facility",
            "type":"Services"
        }
    ],
    "sg:phone":"+1 818 843 2330",
    "sg:postcode":"91506",
    "sg:province":"CA",
    "sg:tags":[
        "home",
        "convalescent"
    ],
    "wof:name":"Burbank Healthcare",
    "wof:placetype":"venue"
},
  "geometry": {"coordinates":[-118.310749,34.161538],"type":"Point"}
}