{
  "type": "Feature",
  "properties": {
    "addr:full":"2005 Cindee Ln Redding CA 96001",
    "addr:housenumber":"2005",
    "addr:postcode":"96001",
    "addr:street":"Cindee Ln",
    "iso:country":"US",
    "sg:address":"2005 Cindee Ln",
    "sg:city":"Redding",
    "sg:classifiers":[
        {
            "category":"Health Services",
            "subcategory":"Doctor",
            "type":"Services"
        }
    ],
    "sg:phone":"+1 530 241 7987",
    "sg:postcode":"96001",
    "sg:province":"CA",
    "sg:tags":[
        "dr"
    ],
    "wof:name":"Cedarwood Medical Group",
    "wof:placetype":"venue"
},
  "geometry": {"coordinates":[-122.469936,40.5783],"type":"Point"}
}