{
  "type": "Feature",
  "properties": {
    "addr:full":"2320 Sutter Street Suite 203 San Francisco CA 94115",
    "addr:housenumber":"2320",
    "addr:postcode":"94115",
    "addr:street":"Sutter Street Suite 203",
    "iso:country":"US",
    "sg:address":"2320 Sutter Street Suite 203",
    "sg:city":"San Francisco",
    "sg:classifiers":[
        {
            "category":"Health Services",
            "subcategory":"Chiropractor",
            "type":"Services"
        }
    ],
    "sg:phone":"+1 415 673 2225",
    "sg:postcode":"94115",
    "sg:province":"CA",
    "wof:name":"Grimes Peter H DC",
    "wof:placetype":"venue"
},
  "geometry": {"coordinates":[-122.439003,37.7855],"type":"Point"}
}