{
  "type": "Feature",
  "properties": {
    "iso:country":"US",
    "sg:address":"8449 Ranchita Way",
    "sg:city":"Fair Oaks",
    "sg:classifiers":[
        {
            "category":"Home & Garden",
            "subcategory":"Building Materials",
            "type":"Retail Goods"
        }
    ],
    "sg:phone":"+1 916 966 1600",
    "sg:postcode":"95628",
    "sg:province":"CA",
    "sg:tags":[
        "mixed",
        "concrete"
    ],
    "wof:name":"Made Rite Concrete",
    "wof:placetype":"venue"
},
  "geometry": {"coordinates":[-121.24654,38.648143],"type":"Point"}
}