{
  "type": "Feature",
  "properties": {
    "addr:full":"2045 Dairy Ave Corcoran CA 93212",
    "addr:housenumber":"2045",
    "addr:postcode":"93212",
    "addr:street":"Dairy Ave",
    "iso:country":"US",
    "sg:address":"2045 Dairy Ave",
    "sg:city":"Corcoran",
    "sg:classifiers":[
        {
            "category":"Restaurant",
            "type":"Food & Drink"
        }
    ],
    "sg:phone":"+1 559 992 4241",
    "sg:postcode":"93212",
    "sg:province":"CA",
    "sg:tags":[
        "eating"
    ],
    "wof:name":"La Perlita Restaurant",
    "wof:placetype":"venue"
},
  "geometry": {"coordinates":[-119.57201499999999,36.086322],"type":"Point"}
}