{
  "type": "Feature",
  "properties": {
    "addr:full":"29373 Rancho California Rd Temecula CA 92591",
    "addr:housenumber":"29373",
    "addr:postcode":"92591",
    "addr:street":"Rancho California Rd",
    "iso:country":"US",
    "sg:address":"29373 Rancho California Rd",
    "sg:city":"Temecula",
    "sg:classifiers":[
        {
            "category":"Health Services",
            "subcategory":"Doctor",
            "type":"Services"
        }
    ],
    "sg:phone":"+1 951 699 4472",
    "sg:postcode":"92591",
    "sg:province":"CA",
    "sg:tags":[
        "physician",
        "surgeon"
    ],
    "wof:name":"Rancho Valley Orthopaedic Surg",
    "wof:placetype":"venue"
},
  "geometry": {"coordinates":[-117.14543,33.504962],"type":"Point"}
}