{
  "type": "Feature",
  "properties": {
    "addr:full":"449 W 6th St Beaumont CA 92223",
    "addr:housenumber":"449",
    "addr:postcode":"92223",
    "addr:street":"W 6Th St",
    "iso:country":"US",
    "sg:address":"449 W 6th St",
    "sg:city":"Beaumont",
    "sg:classifiers":[
        {
            "category":"Freight",
            "type":"Transportation"
        }
    ],
    "sg:phone":"+1 951 845 1497",
    "sg:postcode":"92223",
    "sg:province":"CA",
    "sg:tags":[
        "operator",
        "trucking"
    ],
    "wof:name":"Dick Davis Trucking",
    "wof:placetype":"venue"
},
  "geometry": {"coordinates":[-116.983597,33.930567],"type":"Point"}
}