{
  "type": "Feature",
  "properties": {
    "addr:full":"1583 21st Ave San Francisco CA 94122",
    "addr:housenumber":"1583",
    "addr:postcode":"94122",
    "addr:street":"21St Ave",
    "iso:country":"US",
    "sg:address":"1583 21st Ave",
    "sg:city":"San Francisco",
    "sg:classifiers":[
        {
            "category":"Real Estate",
            "subcategory":"Real Estate Agent",
            "type":"Services"
        }
    ],
    "sg:phone":"+1 415 681 9230",
    "sg:postcode":"94122",
    "sg:province":"CA",
    "wof:name":"Paul Young Appraisals",
    "wof:placetype":"venue"
},
  "geometry": {"coordinates":[-122.47903599999999,37.759429],"type":"Point"}
}