{
  "type": "Feature",
  "properties": {
    "acgov:api":"0.0",
    "acgov:type":"Juvenile Court Schools",
    "addr:full":"2500 Fairmont Ave. San Leandro CA",
    "wof:categories":[
        "education_and_religion:education=school"
    ],
    "wof:name":"Alameda County Juvenile Hall/Court",
    "wof:placetype":"venue"
},
  "geometry": {"coordinates":[-122.11203802764301,37.71283800600728],"type":"Point"}
}