{
  "type": "Feature",
  "properties": {
    "iso:country":"US",
    "sg:address":"434 N Camden Dr",
    "sg:city":"Beverly Hills",
    "sg:classifiers":[
        {
            "category":"Coffee & Tea",
            "type":"Food & Drink"
        }
    ],
    "sg:phone":"+1 310 246 9182",
    "sg:postcode":"90210",
    "sg:province":"CA",
    "wof:name":"Coffee Seletto",
    "wof:placetype":"venue"
},
  "geometry": {"coordinates":[-118.404655,34.069213],"type":"Point"}
}