{
  "type": "Feature",
  "properties": {
    "addr:full":"18545 Gresham St Northridge CA 91324",
    "addr:housenumber":"18545",
    "addr:postcode":"91324",
    "addr:street":"Gresham St",
    "iso:country":"US",
    "sg:address":"18545 Gresham St",
    "sg:city":"Northridge",
    "sg:classifiers":[
        {
            "category":"Retail",
            "subcategory":"Auto Repair",
            "type":"Services"
        }
    ],
    "sg:phone":"+1 818 772 7870",
    "sg:postcode":"91324",
    "sg:province":"CA",
    "sg:tags":[
        "repairing",
        "automobile"
    ],
    "wof:name":"Gary's Automotive Repair",
    "wof:placetype":"venue"
},
  "geometry": {"coordinates":[-118.53639200000001,34.230839],"type":"Point"}
}