{
  "type": "Feature",
  "properties": {
    "iso:country":"US",
    "sg:address":"2521 Stockton Boulevard",
    "sg:city":"Sacramento",
    "sg:classifiers":[
        {
            "category":"Health Services",
            "subcategory":"Doctor",
            "type":"Services"
        }
    ],
    "sg:phone":"+1 916 734 5429",
    "sg:postcode":"95817",
    "sg:province":"CA",
    "sg:tags":[
        "cardiologist"
    ],
    "sg:website":"www.ucdmc.ucdavis.edu/otolaryngo...",
    "wof:name":"Uc Davis Medical Group",
    "wof:placetype":"venue"
},
  "geometry": {"coordinates":[-121.455761,38.552236],"type":"Point"}
}