{
  "type": "Feature",
  "properties": {
    "addr:full":"23263 2nd St Mc Kittrick CA 93251",
    "addr:housenumber":"23263",
    "addr:postcode":"93251",
    "addr:street":"2Nd St",
    "iso:country":"US",
    "sg:address":"23263 2nd St",
    "sg:city":"Mc Kittrick",
    "sg:classifiers":[
        {
            "category":"Government",
            "subcategory":"Post Office",
            "type":"Public Place"
        }
    ],
    "sg:phone":"+1 661 762 7544",
    "sg:postcode":"93251",
    "sg:province":"CA",
    "wof:name":"Mc Kittrick Main Office",
    "wof:placetype":"venue"
},
  "geometry": {"coordinates":[-119.624298,35.301204],"type":"Point"}
}