{
  "type": "Feature",
  "properties": {
    "iso:country":"US",
    "sg:address":"13510 S Normandie Ave",
    "sg:city":"Gardena",
    "sg:classifiers":[
        {
            "category":"Manufacturing",
            "subcategory":"Tools & Machinery",
            "type":"Manufacturing & Wholesale Goods"
        }
    ],
    "sg:phone":"+1 310 327 2033",
    "sg:postcode":"90249",
    "sg:province":"CA",
    "sg:tags":[
        "equipment",
        "station"
    ],
    "wof:name":"California Nozzle Specialists",
    "wof:placetype":"venue"
},
  "geometry": {"coordinates":[-118.300304,33.907449],"type":"Point"}
}