{
  "type": "Feature",
  "properties": {
    "addr:full":"28222 Silverado Canyon Rd Silverado CA 92676",
    "addr:housenumber":"28222",
    "addr:postcode":"92676",
    "addr:street":"Silverado Canyon Rd",
    "iso:country":"US",
    "sg:address":"28222 Silverado Canyon Rd",
    "sg:city":"Silverado",
    "sg:classifiers":[
        {
            "category":"Restaurant",
            "type":"Food & Drink"
        }
    ],
    "sg:phone":"+1 714 649 3200",
    "sg:postcode":"92676",
    "sg:province":"CA",
    "wof:name":"Buck's Roadhouse",
    "wof:placetype":"venue"
},
  "geometry": {"coordinates":[-117.638335,33.747342],"type":"Point"}
}