{
  "type": "Feature",
  "properties": {
    "iso:country":"US",
    "sg:address":"1301 K St Ste H",
    "sg:city":"Modesto",
    "sg:classifiers":[
        {
            "category":"Professional",
            "subcategory":"Lawyer & Legal Services",
            "type":"Services"
        }
    ],
    "sg:phone":"+1 209 574 9447",
    "sg:postcode":"95354",
    "sg:province":"CA",
    "wof:name":"Niermeyer Lawrence T",
    "wof:placetype":"venue"
},
  "geometry": {"coordinates":[-120.998566,37.644033],"type":"Point"}
}