{
  "type": "Feature",
  "properties": {
    "iso:country":"US",
    "sg:address":"12480 Ladd Ln",
    "sg:city":"Auburn",
    "sg:classifiers":[
        {
            "category":"Manufacturing",
            "subcategory":"Motor Vehicles & Parts",
            "type":"Manufacturing & Wholesale Goods"
        }
    ],
    "sg:phone":"+1 530 885 0172",
    "sg:postcode":"95603",
    "sg:province":"CA",
    "sg:tags":[
        "mfg"
    ],
    "wof:name":"Culcam Products",
    "wof:placetype":"venue"
},
  "geometry": {"coordinates":[-121.08804499999999,38.937665],"type":"Point"}
}