{
  "type": "Feature",
  "properties": {
    "addr:full":"7510 W Sunset Blvd Los Angeles CA 90046",
    "addr:housenumber":"7510",
    "addr:postcode":"90046",
    "addr:street":"W Sunset Blvd",
    "iso:country":"US",
    "sg:address":"7510 W Sunset Blvd",
    "sg:city":"Los Angeles",
    "sg:classifiers":[
        {
            "category":"Shopping",
            "subcategory":"Musical Instruments",
            "type":"Retail Goods"
        }
    ],
    "sg:phone":"+1 818 241 4435",
    "sg:postcode":"90046",
    "sg:province":"CA",
    "sg:tags":[
        "music",
        "dealer"
    ],
    "wof:name":"Musicsource",
    "wof:placetype":"venue"
},
  "geometry": {"coordinates":[-118.353735,34.097954],"type":"Point"}
}