{
  "type": "Feature",
  "properties": {
    "iso:country":"US",
    "sg:address":"4420 E Mariposa Rd",
    "sg:city":"Stockton",
    "sg:classifiers":[
        {
            "category":"Wholesale",
            "subcategory":"Construction Materials",
            "type":"Manufacturing & Wholesale Goods"
        }
    ],
    "sg:phone":"+1 415 383 4514",
    "sg:postcode":"95215",
    "sg:province":"CA",
    "sg:tags":[
        "concrete",
        "form"
    ],
    "wof:name":"W/G Construction Enterprises",
    "wof:placetype":"venue"
},
  "geometry": {"coordinates":[-121.218119,37.928602],"type":"Point"}
}