{
  "type": "Feature",
  "properties": {
    "iso:country":"US",
    "sg:address":"5627 Sepulveda Blvd",
    "sg:city":"Van Nuys",
    "sg:classifiers":[
        {
            "category":"Wholesale",
            "subcategory":"Motor Vehicles",
            "type":"Manufacturing & Wholesale Goods"
        }
    ],
    "sg:phone":"+1 818 988 8881",
    "sg:postcode":"91411",
    "sg:province":"CA",
    "sg:tags":[
        "auction",
        "automobile"
    ],
    "wof:name":"Frontline Auto Mart",
    "wof:placetype":"venue"
},
  "geometry": {"coordinates":[-118.466245,34.175258],"type":"Point"}
}