{
  "type": "Feature",
  "properties": {
    "addr:full":"8895 Towne Center Dr Ste 105 San Diego CA 92122",
    "addr:housenumber":"8895",
    "addr:postcode":"92122",
    "addr:street":"Towne Center Dr Ste 105",
    "iso:country":"US",
    "sg:address":"8895 Towne Center Dr Ste 105",
    "sg:city":"San Diego",
    "sg:classifiers":[
        {
            "category":"Social Services",
            "subcategory":"Child Care",
            "type":"Services"
        },
        {
            "category":"Health Services",
            "subcategory":"Health Practitioner",
            "type":"Services"
        }
    ],
    "sg:phone":"+1 858 228 5584",
    "sg:postcode":"92122",
    "sg:province":"CA",
    "sg:tags":[
        "home",
        "day"
    ],
    "sg:website":"www.crunchcare.com",
    "wof:name":"CrunchCare",
    "wof:placetype":"venue"
},
  "geometry": {"coordinates":[-117.206186,32.867398],"type":"Point"}
}