{
  "type": "Feature",
  "properties": {
    "iso:country":"US",
    "sg:address":"5445 Madison Ave",
    "sg:city":"Sacramento",
    "sg:classifiers":[
        {
            "category":"Travel",
            "subcategory":"Travel Agent",
            "type":"Entertainment"
        }
    ],
    "sg:phone":"+1 916 334 4990",
    "sg:postcode":"95841",
    "sg:province":"CA",
    "sg:tags":[
        "agency",
        "bureau"
    ],
    "wof:name":"Trans Global Travel",
    "wof:placetype":"venue"
},
  "geometry": {"coordinates":[-121.340023,38.660756],"type":"Point"}
}