{
  "type": "Feature",
  "properties": {
    "iso:country":"US",
    "sg:address":"1 N Cll Cesar Chavez",
    "sg:city":"Santa Barbara",
    "sg:classifiers":[
        {
            "category":"Building & Trades",
            "subcategory":"Plumbing",
            "type":"Services"
        }
    ],
    "sg:phone":"+1 805 965 3460",
    "sg:postcode":"93103",
    "sg:province":"CA",
    "sg:tags":[
        "contractor"
    ],
    "wof:name":"Arias Plumbing",
    "wof:placetype":"venue"
},
  "geometry": {"coordinates":[-119.683556,34.419371],"type":"Point"}
}