{
  "type": "Feature",
  "properties": {
    "iso:country":"US",
    "sg:address":"4500 Campus Drive",
    "sg:city":"Newport Beach",
    "sg:classifiers":[
        {
            "category":"Real Estate",
            "subcategory":"Real Estate Services",
            "type":"Services"
        }
    ],
    "sg:phone":"+1 866 996 9976",
    "sg:postcode":"92627",
    "sg:province":"CA",
    "wof:name":"American Law Firm",
    "wof:placetype":"venue"
},
  "geometry": {"coordinates":[-117.867006,33.66979],"type":"Point"}
}