{
  "type": "Feature",
  "properties": {
    "addr:full":"226 Hillcrest St Anaheim CA 92807",
    "addr:housenumber":"226",
    "addr:postcode":"92807",
    "addr:street":"Hillcrest St",
    "iso:country":"US",
    "sg:address":"226 Hillcrest St",
    "sg:city":"Anaheim",
    "sg:classifiers":[
        {
            "category":"Professional",
            "subcategory":"Business Services",
            "type":"Services"
        }
    ],
    "sg:phone":"+1 714 974 8800",
    "sg:postcode":"92807",
    "sg:province":"CA",
    "sg:tags":[
        "water",
        "treatment"
    ],
    "wof:name":"J R Fleming Co",
    "wof:placetype":"venue"
},
  "geometry": {"coordinates":[-117.780265,33.848743],"type":"Point"}
}