{
  "type": "Feature",
  "properties": {
    "iso:country":"US",
    "sg:address":"7837 Sepulveda Blvd",
    "sg:city":"Van Nuys",
    "sg:classifiers":[
        {
            "category":"Manufacturing",
            "subcategory":"Signs",
            "type":"Manufacturing & Wholesale Goods"
        }
    ],
    "sg:phone":"+1 818 782 5858",
    "sg:postcode":"91405",
    "sg:province":"CA",
    "sg:tags":[
        "specialty",
        "mfg"
    ],
    "wof:name":"Moriarty Sign Company",
    "wof:placetype":"venue"
},
  "geometry": {"coordinates":[-118.466278,34.212539],"type":"Point"}
}