{
  "type": "Feature",
  "properties": {
    "iso:country":"US",
    "sg:address":"738 W San Marcos Blvd",
    "sg:city":"San Marcos",
    "sg:classifiers":[
        {
            "category":"Retail",
            "subcategory":"Auto Repair",
            "type":"Services"
        }
    ],
    "sg:phone":"+1 760 591 3644",
    "sg:postcode":"92078",
    "sg:province":"CA",
    "sg:tags":[
        "transmission"
    ],
    "wof:name":"San Marcos Transmissions",
    "wof:placetype":"venue"
},
  "geometry": {"coordinates":[-117.17769699999999,33.137631],"type":"Point"}
}