{
  "type": "Feature",
  "properties": {
    "addr:full":"14739 Catalina St San Leandro CA 94577",
    "addr:housenumber":"14739",
    "addr:postcode":"94577",
    "addr:street":"Catalina St",
    "iso:country":"US",
    "sg:address":"14739 Catalina St",
    "sg:city":"San Leandro",
    "sg:classifiers":[
        {
            "category":"Professional",
            "subcategory":"Printing & Photocopies",
            "type":"Services"
        }
    ],
    "sg:phone":"+1 510 357 1400",
    "sg:postcode":"94577",
    "sg:province":"CA",
    "sg:tags":[
        "duplicating",
        "copying"
    ],
    "wof:name":"Profitability Of Hawaii Inc",
    "wof:placetype":"venue"
},
  "geometry": {"coordinates":[-122.171561,37.692349],"type":"Point"}
}