{
  "type": "Feature",
  "properties": {
    "iso:country":"US",
    "sg:address":"1710 N Vermont Avenue",
    "sg:city":"Los Angeles",
    "sg:classifiers":[
        {
            "category":"Professional",
            "subcategory":"Lawyer & Legal Services",
            "type":"Services"
        }
    ],
    "sg:phone":"+1 323 666 0515",
    "sg:postcode":"90027",
    "sg:province":"CA",
    "wof:name":"Robert Sarno Atty",
    "wof:placetype":"venue"
},
  "geometry": {"coordinates":[-118.29178,34.102019],"type":"Point"}
}