{
  "type": "Feature",
  "properties": {
    "addr:full":"1434 3rd St Napa CA 94559",
    "addr:housenumber":"1434",
    "addr:postcode":"94559",
    "addr:street":"3Rd St",
    "iso:country":"US",
    "sg:address":"1434 3rd St",
    "sg:city":"Napa",
    "sg:classifiers":[
        {
            "category":"Social Services",
            "type":"Services"
        }
    ],
    "sg:phone":"+1 707 258 9586",
    "sg:postcode":"94559",
    "sg:province":"CA",
    "sg:tags":[
        "counselor",
        "marriage",
        "family"
    ],
    "wof:name":"Holly Seaton PHD",
    "wof:placetype":"venue"
},
  "geometry": {"coordinates":[-122.288084,38.296008],"type":"Point"}
}