{
  "type": "Feature",
  "properties": {
    "iso:country":"US",
    "sg:address":"324 E Broadway",
    "sg:city":"Glendale",
    "sg:classifiers":[
        {
            "category":"Shopping",
            "subcategory":"Beauty & Cosmetics",
            "type":"Retail Goods"
        }
    ],
    "sg:phone":"+1 818 243 7396",
    "sg:postcode":"91205",
    "sg:province":"CA",
    "sg:tags":[
        "supply"
    ],
    "wof:name":"Anita Vartani Hair Studio",
    "wof:placetype":"venue"
},
  "geometry": {"coordinates":[-118.25099899999999,34.146198],"type":"Point"}
}