{
  "type": "Feature",
  "properties": {
    "addr:full":"27732 Torija Mission Viejo CA 92691",
    "addr:postcode":"27732;92691",
    "iso:country":"US",
    "sg:address":"27732 Torija",
    "sg:city":"Mission Viejo",
    "sg:classifiers":[
        {
            "category":"Wholesale",
            "subcategory":"Electrical",
            "type":"Manufacturing & Wholesale Goods"
        }
    ],
    "sg:phone":"+1 949 470 9750",
    "sg:postcode":"92691",
    "sg:province":"CA",
    "sg:tags":[
        "electronic"
    ],
    "wof:name":"P C Professional Group",
    "wof:placetype":"venue"
},
  "geometry": {"coordinates":[-117.64743799999999,33.644233],"type":"Point"}
}