{
  "type": "Feature",
  "properties": {
    "addr:full":"7813 S Broadway Los Angeles CA 90003",
    "addr:housenumber":"7813",
    "addr:postcode":"90003",
    "addr:street":"S Broadway",
    "iso:country":"US",
    "sg:address":"7813 S Broadway",
    "sg:city":"Los Angeles",
    "sg:classifiers":[
        {
            "category":"Retail",
            "subcategory":"Auto Repair",
            "type":"Services"
        }
    ],
    "sg:phone":"+1 323 758 7225",
    "sg:postcode":"90003",
    "sg:province":"CA",
    "sg:tags":[
        "body",
        "shop",
        "painting",
        "automobile"
    ],
    "wof:name":"Polo's Body & Paint",
    "wof:placetype":"venue"
},
  "geometry": {"coordinates":[-118.27800000000001,33.968498],"type":"Point"}
}