{
  "type": "Feature",
  "properties": {
    "addr:full":"1005 Elwell Ct Palo Alto CA 94303",
    "addr:housenumber":"1005",
    "addr:postcode":"94303",
    "addr:street":"Elwell Ct",
    "iso:country":"US",
    "sg:address":"1005 Elwell Ct",
    "sg:city":"Palo Alto",
    "sg:classifiers":[
        {
            "category":"Shopping",
            "subcategory":"Computers & Home Electronics",
            "type":"Retail Goods"
        }
    ],
    "sg:phone":"+1 650 404 9900",
    "sg:postcode":"94303",
    "sg:province":"CA",
    "sg:tags":[
        "software"
    ],
    "wof:name":"Active Reasoning",
    "wof:placetype":"venue"
},
  "geometry": {"coordinates":[-122.10320299999999,37.433525],"type":"Point"}
}