{
  "type": "Feature",
  "properties": {
    "addr:full":"5845 College Ave Ste 8 Oakland CA 94618",
    "addr:housenumber":"5845",
    "addr:postcode":"94618",
    "addr:street":"College Ave Ste 8",
    "iso:country":"US",
    "sg:address":"5845 College Ave Ste 8",
    "sg:city":"Oakland",
    "sg:classifiers":[
        {
            "category":"Health Services",
            "subcategory":"Health Practitioner",
            "type":"Services"
        }
    ],
    "sg:phone":"+1 510 654 6202",
    "sg:postcode":"94618",
    "sg:province":"CA",
    "sg:tags":[
        "therapy",
        "physical"
    ],
    "wof:name":"Rueben Lisa",
    "wof:placetype":"venue"
},
  "geometry": {"coordinates":[-122.252156,37.8466],"type":"Point"}
}