{
  "type": "Feature",
  "properties": {
    "iso:country":"US",
    "sg:address":"5001 E Commerce Center Dr",
    "sg:city":"Bakersfield",
    "sg:classifiers":[
        {
            "category":"Professional",
            "subcategory":"Accounting & Tax Preparation",
            "type":"Services"
        }
    ],
    "sg:phone":"+1 661 633 2272",
    "sg:postcode":"93309",
    "sg:province":"CA",
    "sg:tags":[
        "accountant"
    ],
    "wof:name":"John P Dover CPA",
    "wof:placetype":"venue"
},
  "geometry": {"coordinates":[-119.059679,35.363344],"type":"Point"}
}