{
  "type": "Feature",
  "properties": {
    "addr:full":"4 Tarragon Ct Petaluma CA 94954",
    "addr:housenumber":"4",
    "addr:postcode":"94954",
    "addr:street":"Tarragon Ct",
    "iso:country":"US",
    "sg:address":"4 Tarragon Ct",
    "sg:city":"Petaluma",
    "sg:classifiers":[
        {
            "category":"Professional",
            "type":"Services"
        }
    ],
    "sg:phone":"+1 707 658 2300",
    "sg:postcode":"94954",
    "sg:province":"CA",
    "wof:name":"Mary Judd",
    "wof:placetype":"venue"
},
  "geometry": {"coordinates":[-122.60311299999999,38.252576],"type":"Point"}
}