{
  "type": "Feature",
  "properties": {
    "iso:country":"US",
    "sg:address":"2925 Root Ave",
    "sg:city":"Carmichael",
    "sg:classifiers":[
        {
            "category":"Social Services",
            "subcategory":"Child Care",
            "type":"Services"
        }
    ],
    "sg:phone":"+1 916 483 8888",
    "sg:postcode":"95608",
    "sg:province":"CA",
    "wof:name":"Wild Kingdom Learning Ctr",
    "wof:placetype":"venue"
},
  "geometry": {"coordinates":[-121.35071499999999,38.617679],"type":"Point"}
}