{
  "type": "Feature",
  "properties": {
    "iso:country":"US",
    "sg:address":"73658 Old Dale Rd",
    "sg:city":"Twentynine Palms",
    "sg:classifiers":[
        {
            "category":"Communications",
            "subcategory":"Television Station",
            "type":"Services"
        }
    ],
    "sg:phone":"+1 760 367 1833",
    "sg:postcode":"92277",
    "sg:province":"CA",
    "sg:tags":[
        "translator",
        "broadcasting",
        "co"
    ],
    "wof:name":"County Service Area 70 TV-5",
    "wof:placetype":"venue"
},
  "geometry": {"coordinates":[-116.054503,34.132107],"type":"Point"}
}