{
  "type": "Feature",
  "properties": {
    "addr:full":"700 Court St Susanville CA 96130",
    "addr:housenumber":"700",
    "addr:postcode":"96130",
    "addr:street":"Court St",
    "iso:country":"US",
    "sg:address":"700 Court St",
    "sg:city":"Susanville",
    "sg:classifiers":[
        {
            "category":"Professional",
            "subcategory":"Lawyer & Legal Services",
            "type":"Services"
        }
    ],
    "sg:phone":"+1 530 257 7704",
    "sg:postcode":"96130",
    "sg:province":"CA",
    "sg:tags":[
        "attorney"
    ],
    "wof:name":"Kathleen R Lazard",
    "wof:placetype":"venue"
},
  "geometry": {"coordinates":[-120.663083,40.415693],"type":"Point"}
}