{
  "type": "Feature",
  "properties": {
    "addr:full":"1637 Ocean Ave San Francisco CA 94112",
    "addr:housenumber":"1637",
    "addr:postcode":"94112",
    "addr:street":"Ocean Ave",
    "iso:country":"US",
    "sg:address":"1637 Ocean Ave",
    "sg:city":"San Francisco",
    "sg:classifiers":[
        {
            "category":"Sports & Exercise",
            "subcategory":"Gym",
            "type":"Entertainment"
        }
    ],
    "sg:phone":"+1 415 225 5182",
    "sg:postcode":"94112",
    "sg:province":"CA",
    "sg:tags":[
        "yoga"
    ],
    "sg:website":"www.hotyogaoceanave.com",
    "wof:name":"Hot Yoga Ocean Ave",
    "wof:placetype":"venue"
},
  "geometry": {"coordinates":[-122.45990399999999,37.724514],"type":"Point"}
}