{
  "type": "Feature",
  "properties": {
    "iso:country":"US",
    "sg:address":"11770 Bernardo Plaza Ct",
    "sg:city":"San Diego",
    "sg:classifiers":[
        {
            "category":"Health Services",
            "subcategory":"Hospital",
            "type":"Services"
        },
        {
            "category":"Health Services",
            "subcategory":"Doctor",
            "type":"Services"
        }
    ],
    "sg:phone":"+1 858 487 9050",
    "sg:postcode":"92128",
    "sg:province":"CA",
    "sg:tags":[
        "physician",
        "surgeon"
    ],
    "wof:name":"Children's Hospital & Hlth Ctr",
    "wof:placetype":"venue"
},
  "geometry": {"coordinates":[-117.075193,33.020425],"type":"Point"}
}