{
  "type": "Feature",
  "properties": {
    "iso:country":"US",
    "sg:address":"2701 Arden Way",
    "sg:city":"Sacramento",
    "sg:classifiers":[
        {
            "category":"Autos & Motor Vehicles",
            "subcategory":"Automobile Sales",
            "type":"Retail Goods"
        }
    ],
    "sg:phone":"+1 916 482 5790",
    "sg:postcode":"95825",
    "sg:province":"CA",
    "sg:tags":[
        "car",
        "repair"
    ],
    "sg:website":"vw.niello.com",
    "wof:name":"Niello Volkswagen",
    "wof:placetype":"venue"
},
  "geometry": {"coordinates":[-121.400966,38.596017],"type":"Point"}
}