{
  "type": "Feature",
  "properties": {
    "addr:full":"1700 Union St San Francisco CA 94123",
    "addr:housenumber":"1700",
    "addr:postcode":"94123",
    "addr:street":"Union St",
    "iso:country":"US",
    "sg:address":"1700 Union St",
    "sg:city":"San Francisco",
    "sg:classifiers":[
        {
            "category":"Personal",
            "subcategory":"Massage",
            "type":"Services"
        },
        {
            "category":"Health Services",
            "subcategory":"Health Practitioner",
            "type":"Services"
        }
    ],
    "sg:phone":"+1 415 377 6022",
    "sg:postcode":"94123",
    "sg:province":"CA",
    "sg:tags":[
        "acupuncture"
    ],
    "sg:website":"steveacupuncture.com/",
    "wof:name":"Stephen Coleman, L.Ac., CMT",
    "wof:placetype":"venue"
},
  "geometry": {"coordinates":[-122.427487,37.798355],"type":"Point"}
}