{
  "type": "Feature",
  "properties": {
    "addr:full":"4563 State St Montclair CA 91763",
    "addr:housenumber":"4563",
    "addr:postcode":"91763",
    "addr:street":"State St",
    "iso:country":"US",
    "sg:address":"4563 State St",
    "sg:city":"Montclair",
    "sg:classifiers":[
        {
            "category":"Utilities",
            "subcategory":"Electric",
            "type":"Services"
        },
        {
            "category":"Building & Trades",
            "subcategory":"Electrical",
            "type":"Services"
        }
    ],
    "sg:phone":"+1 909 628 1256",
    "sg:postcode":"91763",
    "sg:province":"CA",
    "sg:tags":[
        "transformer",
        "industrial",
        "electrician",
        "contractors-commercial"
    ],
    "wof:name":"Hampton Tedder Technical Services, Inc.",
    "wof:placetype":"venue"
},
  "geometry": {"coordinates":[-117.706796,34.059683],"type":"Point"}
}