{
  "type": "Feature",
  "properties": {
    "iso:country":"US",
    "sg:address":"1910 University Ave",
    "sg:city":"Berkeley",
    "sg:classifiers":[
        {
            "category":"Health Services",
            "subcategory":"Clinic",
            "type":"Services"
        }
    ],
    "sg:phone":"+1 415 223 3111",
    "sg:postcode":"94704",
    "sg:province":"CA",
    "sg:tags":[
        "counseling",
        "mental"
    ],
    "sg:website":"loriopal.com",
    "wof:name":"Lori E. Opal, MFT",
    "wof:placetype":"venue"
},
  "geometry": {"coordinates":[-122.272671,37.871536],"type":"Point"}
}