{
  "type": "Feature",
  "properties": {
    "addr:full":"1100-1300 Franklin Mall Santa Clara CA 95050",
    "addr:housenumber":"1100-1300",
    "addr:postcode":"95050",
    "addr:street":"Franklin Mall",
    "iso:country":"US",
    "sg:address":"1100-1300 Franklin Mall",
    "sg:city":"Santa Clara",
    "sg:classifiers":[
        {
            "category":"Shopping Center",
            "type":"Public Place"
        }
    ],
    "sg:postcode":"95050",
    "sg:province":"CA",
    "wof:name":"Franklin Square",
    "wof:placetype":"venue"
},
  "geometry": {"coordinates":[-121.947529,37.349242],"type":"Point"}
}