{
  "type": "Feature",
  "properties": {
    "iso:country":"US",
    "sg:address":"28110 Harrison Pkwy",
    "sg:city":"Valencia",
    "sg:classifiers":[
        {
            "category":"Autos & Motor Vehicles",
            "subcategory":"Automobile Sales",
            "type":"Retail Goods"
        },
        {
            "category":"Building & Trades",
            "subcategory":"Construction",
            "type":"Services"
        }
    ],
    "sg:phone":"+1 661 257 3000",
    "sg:postcode":"91355",
    "sg:province":"CA",
    "sg:tags":[
        "supply",
        "mfg",
        "p",
        "contractor",
        "equipment",
        "aircraft",
        "parts",
        "special"
    ],
    "wof:name":"Regent Aerospace Corporation",
    "wof:placetype":"venue"
},
  "geometry": {"coordinates":[-118.625969,34.440302],"type":"Point"}
}