{
  "type": "Feature",
  "properties": {
    "iso:country":"US",
    "sg:address":"2915 Red Hill Avenue",
    "sg:city":"Costa Mesa",
    "sg:classifiers":[
        {
            "category":"Shopping",
            "subcategory":"Stationery & Office Supplies",
            "type":"Retail Goods"
        }
    ],
    "sg:phone":"+1 714 800 1780",
    "sg:postcode":"92626",
    "sg:province":"CA",
    "sg:tags":[
        "equipment"
    ],
    "sg:website":"www.maxonfurniture.com",
    "wof:name":"Maxon Furniture",
    "wof:placetype":"venue"
},
  "geometry": {"coordinates":[-117.880703,33.667948],"type":"Point"}
}