{
  "type": "Feature",
  "properties": {
    "iso:country":"US",
    "sg:address":"7900 Sausalito Ave",
    "sg:city":"Canoga Park",
    "sg:classifiers":[
        {
            "category":"Professional",
            "type":"Services"
        }
    ],
    "sg:phone":"+1 818 884 7821",
    "sg:postcode":"91304",
    "sg:province":"CA",
    "wof:name":"Franks For Memories",
    "wof:placetype":"venue"
},
  "geometry": {"coordinates":[-118.61563099999999,34.213686],"type":"Point"}
}