{
  "type": "Feature",
  "properties": {
    "iso:country":"US",
    "sg:address":"4220 Petaluma Blvd N",
    "sg:city":"Petaluma",
    "sg:classifiers":[
        {
            "category":"Autos & Motor Vehicles",
            "subcategory":"Auto Supplies",
            "type":"Retail Goods"
        }
    ],
    "sg:phone":"+1 707 283 4374",
    "sg:postcode":"94952",
    "sg:province":"CA",
    "sg:tags":[
        "equipment",
        "racing",
        "car",
        "automobile"
    ],
    "wof:name":"DPI",
    "wof:placetype":"venue"
},
  "geometry": {"coordinates":[-122.669574,38.265499],"type":"Point"}
}