{
  "type": "Feature",
  "properties": {
    "addr:full":"9340 Hazard Way San Diego CA 92123",
    "addr:housenumber":"9340",
    "addr:postcode":"92123",
    "addr:street":"Hazard Way",
    "iso:country":"US",
    "sg:address":"9340 Hazard Way",
    "sg:city":"San Diego",
    "sg:classifiers":[
        {
            "category":"Professional",
            "subcategory":"Employment Agencies",
            "type":"Services"
        }
    ],
    "sg:phone":"+1 858 292 6111",
    "sg:postcode":"92123",
    "sg:province":"CA",
    "wof:name":"Dial Resource Network",
    "wof:placetype":"venue"
},
  "geometry": {"coordinates":[-117.127617,32.835704],"type":"Point"}
}