{
  "type": "Feature",
  "properties": {
    "addr:full":"2250 Winchester Blvd Campbell CA 95008",
    "addr:housenumber":"2250",
    "addr:postcode":"95008",
    "addr:street":"Winchester Blvd",
    "iso:country":"US",
    "sg:address":"2250 Winchester Blvd",
    "sg:city":"Campbell",
    "sg:classifiers":[
        {
            "category":"Autos & Motor Vehicles",
            "subcategory":"Auto Supplies",
            "type":"Retail Goods"
        }
    ],
    "sg:phone":"+1 408 379 0300",
    "sg:postcode":"95008",
    "sg:province":"CA",
    "sg:tags":[
        "tire"
    ],
    "sg:website":"www.t-wmotorsports.com",
    "wof:name":"T W Motorsports",
    "wof:placetype":"venue"
},
  "geometry": {"coordinates":[-121.949635,37.28201],"type":"Point"}
}