{
  "type": "Feature",
  "properties": {
    "iso:country":"US",
    "sg:address":"2945 Randolph Ave",
    "sg:city":"Costa Mesa",
    "sg:classifiers":[
        {
            "category":"Retail",
            "subcategory":"Auto Repair",
            "type":"Services"
        }
    ],
    "sg:phone":"+1 949 642 8286",
    "sg:postcode":"92626",
    "sg:province":"CA",
    "sg:tags":[
        "automobile",
        "smog",
        "check",
        "diagnostic"
    ],
    "sg:website":"www.thecarbshop.com",
    "wof:name":"Carburetor Shop the",
    "wof:placetype":"venue"
},
  "geometry": {"coordinates":[-117.88800000000001,33.679401],"type":"Point"}
}