{
  "type": "Feature",
  "properties": {
    "addr:full":"600 S Napa Junction Rd American Canyon CA 94503",
    "addr:housenumber":"600",
    "addr:postcode":"94503",
    "addr:street":"S Napa Junction Rd American",
    "iso:country":"US",
    "sg:address":"600 S Napa Junction Rd",
    "sg:city":"American Canyon",
    "sg:classifiers":[
        {
            "category":"Professional",
            "subcategory":"Management & Consulting",
            "type":"Services"
        }
    ],
    "sg:phone":"+1 707 556 9145",
    "sg:postcode":"94503",
    "sg:province":"CA",
    "sg:tags":[
        "control",
        "builder"
    ],
    "wof:name":"Ghilotti Construction Co Inc",
    "wof:placetype":"venue"
},
  "geometry": {"coordinates":[-122.24888799999999,38.178445],"type":"Point"}
}