{
  "type": "Feature",
  "properties": {
    "addr:full":"1323 S Fairfax Rd Bakersfield CA 93307",
    "addr:housenumber":"1323",
    "addr:postcode":"93307",
    "addr:street":"S Fairfax Rd",
    "iso:country":"US",
    "sg:address":"1323 S Fairfax Rd",
    "sg:city":"Bakersfield",
    "sg:classifiers":[
        {
            "category":"Home & Garden",
            "subcategory":"Building Materials",
            "type":"Retail Goods"
        }
    ],
    "sg:phone":"+1 661 366 1270",
    "sg:postcode":"93307",
    "sg:province":"CA",
    "sg:tags":[
        "glass",
        "window",
        "plate"
    ],
    "wof:name":"American Windshield Repair",
    "wof:placetype":"venue"
},
  "geometry": {"coordinates":[-118.93209,35.342915],"type":"Point"}
}