{
  "type": "Feature",
  "properties": {
    "addr:full":"9686 W California Ave Fresno CA 93706",
    "addr:housenumber":"9686",
    "addr:postcode":"93706",
    "addr:street":"W California Ave",
    "iso:country":"US",
    "sg:address":"9686 W California Ave",
    "sg:city":"Fresno",
    "sg:classifiers":[
        {
            "category":"Wholesale",
            "subcategory":"Farm Supplies",
            "type":"Manufacturing & Wholesale Goods"
        }
    ],
    "sg:phone":"+1 559 266 2991",
    "sg:postcode":"93706",
    "sg:province":"CA",
    "sg:tags":[
        "vineyard",
        "grape",
        "livestock"
    ],
    "wof:name":"Americo J Foglio",
    "wof:placetype":"venue"
},
  "geometry": {"coordinates":[-119.964067,36.720592],"type":"Point"}
}