{
  "type": "Feature",
  "properties": {
    "addr:full":"568 Lighthouse Ave Pacific Grove CA 93950",
    "addr:housenumber":"568",
    "addr:postcode":"93950",
    "addr:street":"Lighthouse Ave",
    "iso:country":"US",
    "sg:address":"568 Lighthouse Ave",
    "sg:city":"Pacific Grove",
    "sg:classifiers":[
        {
            "category":"Arts & Performance",
            "subcategory":"Theater",
            "type":"Entertainment"
        }
    ],
    "sg:phone":"+1 831 372 0388",
    "sg:postcode":"93950",
    "sg:province":"CA",
    "sg:tags":[
        "dance",
        "company"
    ],
    "sg:website":"www.balletfantasque.org",
    "wof:name":"Ballet Fantasque",
    "wof:placetype":"venue"
},
  "geometry": {"coordinates":[-121.91745,36.621028],"type":"Point"}
}