{
  "type": "Feature",
  "properties": {
    "iso:country":"US",
    "sg:address":"1 Mills Cir",
    "sg:city":"Ontario",
    "sg:classifiers":[
        {
            "category":"Shopping",
            "subcategory":"Clothing, Apparel, & Fashions",
            "type":"Retail Goods"
        },
        {
            "category":"Shopping",
            "subcategory":"Baby Store",
            "type":"Retail Goods"
        },
        {
            "category":"Shopping",
            "subcategory":"Department Store",
            "type":"Retail Goods"
        }
    ],
    "sg:phone":"+1 909 987 5668",
    "sg:postcode":"91764",
    "sg:province":"CA",
    "sg:tags":[
        "infant",
        "vintage",
        "men's",
        "period",
        "accessory",
        "children's",
        "wear",
        "apparel",
        "girls'",
        "women's",
        "clothing",
        "boys'",
        "clothing-collectible"
    ],
    "sg:website":"http://www.gap.com",
    "wof:name":"Gap",
    "wof:placetype":"venue"
},
  "geometry": {"coordinates":[-117.556381,34.074471],"type":"Point"}
}