{
  "type": "Feature",
  "properties": {
    "iso:country":"US",
    "sg:address":"1524 N Effie St",
    "sg:city":"Fresno",
    "sg:classifiers":[
        {
            "category":"Retail",
            "subcategory":"Auto Repair",
            "type":"Services"
        }
    ],
    "sg:phone":"+1 559 237 0706",
    "sg:postcode":"93703",
    "sg:province":"CA",
    "sg:tags":[
        "repairing",
        "automobile"
    ],
    "wof:name":"T J's Auto Repair",
    "wof:placetype":"venue"
},
  "geometry": {"coordinates":[-119.788196,36.764556],"type":"Point"}
}