{
  "type": "Feature",
  "properties": {
    "addr:full":"10808 Foothill Blvd Rancho Cucamonga CA 91730",
    "addr:housenumber":"10808",
    "addr:postcode":"91730",
    "addr:street":"Foothill Blvd",
    "iso:country":"US",
    "sg:address":"10808 Foothill Blvd",
    "sg:city":"Rancho Cucamonga",
    "sg:classifiers":[
        {
            "category":"Insurance",
            "subcategory":"Hazard Insurance",
            "type":"Services"
        }
    ],
    "sg:phone":"+1 909 481 6869",
    "sg:postcode":"91730",
    "sg:province":"CA",
    "sg:tags":[
        "bond"
    ],
    "wof:name":"Gregory Phillips Bail Bonds",
    "wof:placetype":"venue"
},
  "geometry": {"coordinates":[-117.569136,34.106571],"type":"Point"}
}