{
  "type": "Feature",
  "properties": {
    "addr:full":"21001 San Ramon Valley Blvd San Ramon CA 94583",
    "addr:housenumber":"21001",
    "addr:postcode":"94583",
    "addr:street":"San Ramon Valley Blvd",
    "iso:country":"US",
    "sg:address":"21001 San Ramon Valley Blvd",
    "sg:city":"San Ramon",
    "sg:classifiers":[
        {
            "category":"Wholesale",
            "subcategory":"Machinery & Supplies",
            "type":"Manufacturing & Wholesale Goods"
        }
    ],
    "sg:phone":"+1 510 632 3000",
    "sg:postcode":"94583",
    "sg:province":"CA",
    "sg:tags":[
        "janitor"
    ],
    "sg:website":"www.keenesanitary.com",
    "wof:name":"Keene Sanitary Supply",
    "wof:placetype":"venue"
},
  "geometry": {"coordinates":[-121.94343000000001,37.726235],"type":"Point"}
}