{
  "type": "Feature",
  "properties": {
    "iso:country":"US",
    "sg:address":"1574 Callens Rd",
    "sg:city":"Ventura",
    "sg:classifiers":[
        {
            "category":"Retail",
            "subcategory":"Repair Shop",
            "type":"Services"
        }
    ],
    "sg:phone":"+1 805 654 0185",
    "sg:postcode":"93003",
    "sg:province":"CA",
    "sg:tags":[
        "scooter",
        "motorcycle",
        "motor"
    ],
    "wof:name":"West Coast Cycle",
    "wof:placetype":"venue"
},
  "geometry": {"coordinates":[-119.240233,34.26116],"type":"Point"}
}