{
  "type": "Feature",
  "properties": {
    "addr:full":"5793 Alton Pkwy Irvine CA 92604",
    "addr:housenumber":"5793",
    "addr:postcode":"92604",
    "addr:street":"Alton Pkwy",
    "iso:country":"US",
    "sg:address":"5793 Alton Pkwy",
    "sg:city":"Irvine",
    "sg:classifiers":[
        {
            "category":"Autos & Motor Vehicles",
            "subcategory":"Fuel & Gas Station",
            "type":"Retail Goods"
        },
        {
            "category":"Food & Beverages",
            "subcategory":"Groceries & Convenience Stores",
            "type":"Retail Goods"
        }
    ],
    "sg:phone":"+1 949 653 0596",
    "sg:postcode":"92604",
    "sg:province":"CA",
    "sg:website":"www.circlek.com",
    "wof:name":"Circle K \u00a0/ 76 Gas",
    "wof:placetype":"venue"
},
  "geometry": {"coordinates":[-117.78505199999999,33.668101],"type":"Point"}
}