{
  "type": "Feature",
  "properties": {
    "iso:country":"US",
    "sg:address":"2929 Fulton Ave",
    "sg:city":"Sacramento",
    "sg:classifiers":[
        {
            "category":"Manufacturing",
            "subcategory":"Printing",
            "type":"Manufacturing & Wholesale Goods"
        }
    ],
    "sg:phone":"+1 916 804 3340",
    "sg:postcode":"95821",
    "sg:province":"CA",
    "sg:tags":[
        "publisher"
    ],
    "wof:name":"Together Publishing",
    "wof:placetype":"venue"
},
  "geometry": {"coordinates":[-121.40148499999999,38.618635],"type":"Point"}
}