{
  "type": "Feature",
  "properties": {
    "iso:country":"US",
    "sg:address":"735 E 12th St",
    "sg:city":"Los Angeles",
    "sg:classifiers":[
        {
            "category":"Shopping",
            "subcategory":"Clothing, Apparel, & Fashions",
            "type":"Retail Goods"
        }
    ],
    "sg:phone":"+1 213 746 7727",
    "sg:postcode":"90021",
    "sg:province":"CA",
    "wof:name":"Jolie",
    "wof:placetype":"venue"
},
  "geometry": {"coordinates":[-118.252631,34.033535],"type":"Point"}
}