{
  "type": "Feature",
  "properties": {
    "iso:country":"US",
    "sg:address":"6262 Jarvis Ave",
    "sg:city":"Newark",
    "sg:classifiers":[
        {
            "category":"Professional",
            "subcategory":"Research",
            "type":"Services"
        }
    ],
    "sg:phone":"+1 510 794 5862",
    "sg:postcode":"94560",
    "sg:province":"CA",
    "sg:tags":[
        "educational"
    ],
    "wof:name":"National Technology",
    "wof:placetype":"venue"
},
  "geometry": {"coordinates":[-122.050566,37.54894],"type":"Point"}
}