{
  "type": "Feature",
  "properties": {
    "addr:full":"1656 N Main St Salinas CA 93906",
    "addr:housenumber":"1656",
    "addr:postcode":"93906",
    "addr:street":"N Main St",
    "iso:country":"US",
    "sg:address":"1656 N Main St",
    "sg:city":"Salinas",
    "sg:classifiers":[
        {
            "category":"Shopping",
            "subcategory":"Florist",
            "type":"Retail Goods"
        }
    ],
    "sg:phone":"+1 831 442 2210",
    "sg:postcode":"93906",
    "sg:province":"CA",
    "sg:website":"www.demetres.net",
    "wof:name":"Demetre's Flower Shoppe",
    "wof:placetype":"venue"
},
  "geometry": {"coordinates":[-121.65383799999999,36.710096],"type":"Point"}
}