{
  "type": "Feature",
  "properties": {
    "addr:full":"1115 Front St Ste 12 Sacramento CA 95814",
    "addr:housenumber":"1115",
    "addr:postcode":"95814",
    "addr:street":"Front St Ste 12",
    "iso:country":"US",
    "sg:address":"1115 Front St Ste 12",
    "sg:city":"Sacramento",
    "sg:classifiers":[
        {
            "category":"Personal",
            "type":"Services"
        },
        {
            "category":"Retail",
            "subcategory":"Laundry & Dry Cleaning",
            "type":"Services"
        }
    ],
    "sg:phone":"+1 916 448 2827",
    "sg:postcode":"95814",
    "sg:province":"CA",
    "sg:tags":[
        "sewing",
        "alteration"
    ],
    "wof:name":"Leather by Mary Terry",
    "wof:placetype":"venue"
},
  "geometry": {"coordinates":[-121.505798,38.581722],"type":"Point"}
}