{
  "type": "Feature",
  "properties": {
    "iso:country":"US",
    "sg:address":"3101 Santa Monica Blvd",
    "sg:city":"Santa Monica",
    "sg:classifiers":[
        {
            "category":"Shopping",
            "subcategory":"Bicycles & Sporting Goods",
            "type":"Retail Goods"
        }
    ],
    "sg:phone":"+1 310 828 3492",
    "sg:postcode":"90404",
    "sg:province":"CA",
    "sg:website":"www.docskihaus.com",
    "wof:name":"Doc's Ski Haus",
    "wof:placetype":"venue"
},
  "geometry": {"coordinates":[-118.46863999999999,34.037886],"type":"Point"}
}