{
  "type": "Feature",
  "properties": {
    "iso:country":"US",
    "sg:address":"1455 E Kentucky Ave",
    "sg:city":"Woodland",
    "sg:classifiers":[
        {
            "category":"Manufacturing",
            "subcategory":"Metals",
            "type":"Manufacturing & Wholesale Goods"
        }
    ],
    "sg:phone":"+1 530 662 0284",
    "sg:postcode":"95776",
    "sg:province":"CA",
    "sg:tags":[
        "steel"
    ],
    "sg:website":"www.gmc-w.com",
    "wof:name":"Gayle Manufacturing Co",
    "wof:placetype":"venue"
},
  "geometry": {"coordinates":[-121.747598,38.691853],"type":"Point"}
}