{
  "type": "Feature",
  "properties": {
    "addr:full":"2154 San Ramon Valley Blvd San Ramon CA 94583",
    "addr:housenumber":"2154",
    "addr:postcode":"94583",
    "addr:street":"San Ramon Valley Blvd",
    "iso:country":"US",
    "sg:address":"2154 San Ramon Valley Blvd",
    "sg:city":"San Ramon",
    "sg:classifiers":[
        {
            "category":"Restaurant",
            "type":"Food & Drink"
        }
    ],
    "sg:phone":"+1 925 837 2501",
    "sg:postcode":"94583",
    "sg:province":"CA",
    "sg:website":"www.brassdoor.com",
    "wof:name":"Brass Door",
    "wof:placetype":"venue"
},
  "geometry": {"coordinates":[-121.980026,37.784667],"type":"Point"}
}