{
  "type": "Feature",
  "properties": {
    "iso:country":"US",
    "sg:address":"608 W Beverly Blvd",
    "sg:city":"Montebello",
    "sg:classifiers":[
        {
            "category":"Health Services",
            "subcategory":"Chiropractor",
            "type":"Services"
        }
    ],
    "sg:phone":"+1 323 721 3297",
    "sg:postcode":"90640",
    "sg:province":"CA",
    "wof:name":"Penilla Chiropractic Inc",
    "wof:placetype":"venue"
},
  "geometry": {"coordinates":[-118.10433,34.016913],"type":"Point"}
}