{
  "type": "Feature",
  "properties": {
    "iso:country":"US",
    "sg:address":"7229 Stockton Blvd",
    "sg:city":"Sacramento",
    "sg:classifiers":[
        {
            "category":"Restaurant",
            "type":"Food & Drink"
        }
    ],
    "sg:menulink":"http://www.allmenus.com/ca/sacramento/175093-popeyes-chicken--biscuits/menu/",
    "sg:phone":"+1 916 392 0701",
    "sg:postcode":"95823",
    "sg:province":"CA",
    "sg:tags":[
        "american",
        "wing"
    ],
    "wof:name":"Popeyes Chicken & Biscuits",
    "wof:placetype":"venue"
},
  "geometry": {"coordinates":[-121.42783799999999,38.494429],"type":"Point"}
}