{
  "type": "Feature",
  "properties": {
    "addr:full":"3750 E Anaheim St Long Beach CA 90804",
    "addr:housenumber":"3750",
    "addr:postcode":"90804",
    "addr:street":"E Anaheim St",
    "iso:country":"US",
    "sg:address":"3750 E Anaheim St",
    "sg:city":"Long Beach",
    "sg:classifiers":[
        {
            "category":"Professional",
            "subcategory":"Advertising",
            "type":"Services"
        }
    ],
    "sg:phone":"+1 562 961 8545",
    "sg:postcode":"90804",
    "sg:province":"CA",
    "wof:name":"Spectrum Media",
    "wof:placetype":"venue"
},
  "geometry": {"coordinates":[-118.148082,33.78252],"type":"Point"}
}