{
  "type": "Feature",
  "properties": {
    "iso:country":"US",
    "sg:address":"14970 State Hwy 49",
    "sg:city":"Grass Valley",
    "sg:classifiers":[
        {
            "category":"Building & Trades",
            "subcategory":"Landscaping Services",
            "type":"Services"
        }
    ],
    "sg:phone":"+1 530 432 1980",
    "sg:postcode":"95949",
    "sg:province":"CA",
    "sg:tags":[
        "landscape",
        "contractor"
    ],
    "wof:name":"Brent Stuart",
    "wof:placetype":"venue"
},
  "geometry": {"coordinates":[-121.067396,39.151311],"type":"Point"}
}