{
  "type": "Feature",
  "properties": {
    "addr:full":"907 W Rialto Ave San Bernardino CA 92410",
    "addr:housenumber":"907",
    "addr:postcode":"92410",
    "addr:street":"W Rialto Ave",
    "iso:country":"US",
    "sg:address":"907 W Rialto Ave",
    "sg:city":"San Bernardino",
    "sg:classifiers":[
        {
            "category":"Organizations",
            "subcategory":"Non-profit Organization",
            "type":"Services"
        }
    ],
    "sg:phone":"+1 909 885 8804",
    "sg:postcode":"92410",
    "sg:province":"CA",
    "sg:tags":[
        "information",
        "alcoholism",
        "treatment"
    ],
    "wof:name":"VARP Inc",
    "wof:placetype":"venue"
},
  "geometry": {"coordinates":[-117.30368799999999,34.100769],"type":"Point"}
}