{
  "type": "Feature",
  "properties": {
    "iso:country":"US",
    "sg:address":"25 Circle Dr",
    "sg:city":"Belvedere Tibrn",
    "sg:classifiers":[
        {
            "category":"Real Estate",
            "subcategory":"Real Estate Operator",
            "type":"Services"
        }
    ],
    "sg:phone":"+1 415 383 2003",
    "sg:postcode":"94920",
    "sg:province":"CA",
    "sg:tags":[
        "apartment"
    ],
    "wof:name":"Tiburon View Apartments",
    "wof:placetype":"venue"
},
  "geometry": {"coordinates":[-122.497475,37.898092],"type":"Point"}
}