{
  "type": "Feature",
  "properties": {
    "iso:country":"US",
    "sg:address":"1455 Cherrywood Dr",
    "sg:city":"San Mateo",
    "sg:classifiers":[
        {
            "category":"Farming",
            "subcategory":"Livestock Farm",
            "type":"Manufacturing & Wholesale Goods"
        }
    ],
    "sg:phone":"+1 650 349 6875",
    "sg:postcode":"94403",
    "sg:province":"CA",
    "sg:tags":[
        "beef",
        "feedlot",
        "cattle"
    ],
    "wof:name":"Santa Cruz Island Co",
    "wof:placetype":"venue"
},
  "geometry": {"coordinates":[-122.328972,37.523374],"type":"Point"}
}