{
  "type": "Feature",
  "properties": {
    "iso:country":"US",
    "sg:address":"10524 Foothill Blvd",
    "sg:city":"Sylmar",
    "sg:classifiers":[
        {
            "category":"Building & Trades",
            "subcategory":"Landscaping Services",
            "type":"Services"
        }
    ],
    "sg:phone":"+1 818 420 0068",
    "sg:postcode":"91342",
    "sg:province":"CA",
    "sg:tags":[
        "tree"
    ],
    "wof:name":"Best Care Tree Service, Inc.",
    "wof:placetype":"venue"
},
  "geometry": {"coordinates":[-118.35964199999999,34.274241],"type":"Point"}
}