{
  "type": "Feature",
  "properties": {
    "addr:full":"1217 6th St Norco CA 92860",
    "addr:housenumber":"1217",
    "addr:postcode":"92860",
    "addr:street":"6Th St",
    "iso:country":"US",
    "sg:address":"1217 6th St",
    "sg:city":"Norco",
    "sg:classifiers":[
        {
            "category":"Professional",
            "subcategory":"Lawyer & Legal Services",
            "type":"Services"
        }
    ],
    "sg:phone":"+1 951 371 7951",
    "sg:postcode":"92860",
    "sg:province":"CA",
    "sg:tags":[
        "attorney"
    ],
    "wof:name":"Eduardo Lopez Law Offices",
    "wof:placetype":"venue"
},
  "geometry": {"coordinates":[-117.54758099999999,33.938485],"type":"Point"}
}