{
  "type": "Feature",
  "properties": {
    "addr:full":"3835 Cross Creek Rd Ste 2 Malibu CA 90265",
    "addr:housenumber":"3835",
    "addr:postcode":"90265",
    "addr:street":"Cross Creek Rd Ste 2",
    "iso:country":"US",
    "sg:address":"3835 Cross Creek Rd Ste 2",
    "sg:city":"Malibu",
    "sg:phone":"+1 310 456 1211",
    "sg:postcode":"90265",
    "sg:province":"CA",
    "wof:name":"Malibu Mutt",
    "wof:placetype":"venue"
},
  "geometry": {"coordinates":[-118.68552099999999,34.036592],"type":"Point"}
}