{
  "type": "Feature",
  "properties": {
    "iso:country":"US",
    "sg:address":"4190 E Tuolumne Rd",
    "sg:city":"Turlock",
    "sg:classifiers":[
        {
            "category":"Farming",
            "subcategory":"Dairy Farm",
            "type":"Manufacturing & Wholesale Goods"
        }
    ],
    "sg:phone":"+1 209 634 0245",
    "sg:postcode":"95382",
    "sg:province":"CA",
    "wof:name":"Cal Chris Holstins",
    "wof:placetype":"venue"
},
  "geometry": {"coordinates":[-120.800872,37.514336],"type":"Point"}
}