{
  "type": "Feature",
  "properties": {
    "addr:full":"555 Twin Dolphin Drive  Suite 200 Redwood City CA 94065",
    "addr:housenumber":"555",
    "addr:postcode":"94065",
    "addr:street":"Twin Dolphin Drive Suite 200",
    "iso:country":"US",
    "sg:address":"555 Twin Dolphin Drive  Suite 200",
    "sg:city":"Redwood City",
    "sg:classifiers":[
        {
            "category":"Professional",
            "subcategory":"Computer Services",
            "type":"Services"
        }
    ],
    "sg:phone":"+1 650 598 0300",
    "sg:postcode":"94065",
    "sg:province":"CA",
    "wof:name":"Celequest Corp",
    "wof:placetype":"venue"
},
  "geometry": {"coordinates":[-122.250941,37.518604],"type":"Point"}
}