{
  "type": "Feature",
  "properties": {
    "addr:full":"11025 Westminster Ave Garden Grove CA 92843",
    "addr:housenumber":"11025",
    "addr:postcode":"92843",
    "addr:street":"Westminster Ave",
    "iso:country":"US",
    "sg:address":"11025 Westminster Ave",
    "sg:city":"Garden Grove",
    "sg:classifiers":[
        {
            "category":"Manufacturing",
            "subcategory":"Food",
            "type":"Manufacturing & Wholesale Goods"
        }
    ],
    "sg:phone":"+1 714 894 6854",
    "sg:postcode":"92843",
    "sg:province":"CA",
    "sg:tags":[
        "organization",
        "religious",
        "mfg"
    ],
    "wof:name":"Kekos Foods",
    "wof:placetype":"venue"
},
  "geometry": {"coordinates":[-117.937118,33.759713],"type":"Point"}
}