{
  "type": "Feature",
  "properties": {
    "iso:country":"US",
    "sg:address":"14629 Main St",
    "sg:city":"Hesperia",
    "sg:classifiers":[
        {
            "category":"Professional",
            "subcategory":"Business Services",
            "type":"Services"
        }
    ],
    "sg:phone":"+1 760 947 9976",
    "sg:postcode":"92345",
    "sg:province":"CA",
    "sg:tags":[
        "inspection"
    ],
    "wof:name":"Rh Construction Services",
    "wof:placetype":"venue"
},
  "geometry": {"coordinates":[-117.345242,34.426804],"type":"Point"}
}