{
  "type": "Feature",
  "properties": {
    "iso:country":"US",
    "sg:address":"406 S Mansfield Ave",
    "sg:city":"Los Angeles",
    "sg:classifiers":[
        {
            "category":"Professional",
            "subcategory":"Lawyer & Legal Services",
            "type":"Services"
        }
    ],
    "sg:phone":"+1 323 939 1181",
    "sg:postcode":"90036",
    "sg:province":"CA",
    "wof:name":"Gss Communiqatios",
    "wof:placetype":"venue"
},
  "geometry": {"coordinates":[-118.340443,34.066594],"type":"Point"}
}