{
  "type": "Feature",
  "properties": {
    "iso:country":"US",
    "sg:address":"4260 Niblick Way",
    "sg:city":"Fair Oaks",
    "sg:classifiers":[
        {
            "category":"Building & Trades",
            "subcategory":"Cleaning & Sanitation",
            "type":"Services"
        }
    ],
    "sg:phone":"+1 916 967 3026",
    "sg:postcode":"95628",
    "sg:province":"CA",
    "sg:tags":[
        "house"
    ],
    "wof:name":"C & R Housekeeping",
    "wof:placetype":"venue"
},
  "geometry": {"coordinates":[-121.288944,38.642316],"type":"Point"}
}