{
  "type": "Feature",
  "properties": {
    "addr:full":"10559 Jefferson Blvd. Ste. C Culver City CA 90232",
    "addr:housenumber":"10559",
    "addr:postcode":"90232",
    "addr:street":"Jefferson Blvd. Ste. C",
    "iso:country":"US",
    "sg:address":"10559 Jefferson Blvd. Ste. C",
    "sg:city":"Culver City",
    "sg:classifiers":[
        {
            "category":"Professional",
            "subcategory":"Accounting & Tax Preparation",
            "type":"Services"
        },
        {
            "category":"Professional",
            "subcategory":"Lawyer & Legal Services",
            "type":"Services"
        }
    ],
    "sg:phone":"+1 310 401 6955",
    "sg:postcode":"90232",
    "sg:province":"CA",
    "sg:tags":[
        "accountant"
    ],
    "sg:website":"www.411TaxRelief.com",
    "wof:name":"411TaxRelief",
    "wof:placetype":"venue"
},
  "geometry": {"coordinates":[-118.392723,34.005854],"type":"Point"}
}