{
  "type": "Feature",
  "properties": {
    "addr:full":"14535 Arminta St Van Nuys CA 91402",
    "addr:housenumber":"14535",
    "addr:postcode":"91402",
    "addr:street":"Arminta St",
    "iso:country":"US",
    "sg:address":"14535 Arminta St",
    "sg:city":"Van Nuys",
    "sg:classifiers":[
        {
            "category":"Building & Trades",
            "subcategory":"Construction",
            "type":"Services"
        }
    ],
    "sg:phone":"+1 818 780 8192",
    "sg:postcode":"91402",
    "sg:province":"CA",
    "sg:tags":[
        "woodworker"
    ],
    "wof:name":"Rojas Custom Woodwork",
    "wof:placetype":"venue"
},
  "geometry": {"coordinates":[-118.453076,34.213465],"type":"Point"}
}