{
  "type": "Feature",
  "properties": {
    "addr:full":"1217 Sutter St San Francisco CA 94109",
    "addr:housenumber":"1217",
    "addr:postcode":"94109",
    "addr:street":"Sutter St",
    "iso:country":"US",
    "sg:address":"1217 Sutter St",
    "sg:city":"San Francisco",
    "sg:classifiers":[
        {
            "category":"Restaurant",
            "type":"Food & Drink"
        }
    ],
    "sg:phone":"+1 415 440 8838",
    "sg:postcode":"94109",
    "sg:province":"CA",
    "sg:website":"www.osakagrill.com",
    "wof:name":"Osaka Grill",
    "wof:placetype":"venue"
},
  "geometry": {"coordinates":[-122.42153399999999,37.787508],"type":"Point"}
}