{
  "type": "Feature",
  "properties": {
    "addr:full":"1700 Peppervilla Dr El Cajon CA 92021",
    "addr:housenumber":"1700",
    "addr:postcode":"92021",
    "addr:street":"Peppervilla Dr",
    "iso:country":"US",
    "sg:address":"1700 Peppervilla Dr",
    "sg:city":"El Cajon",
    "sg:classifiers":[
        {
            "category":"Retail",
            "subcategory":"Auto Repair",
            "type":"Services"
        }
    ],
    "sg:phone":"+1 619 442 0739",
    "sg:postcode":"92021",
    "sg:province":"CA",
    "sg:tags":[
        "repairing",
        "automobile"
    ],
    "wof:name":"Imported Car Care",
    "wof:placetype":"venue"
},
  "geometry": {"coordinates":[-116.948663,32.822652],"type":"Point"}
}