{
  "type": "Feature",
  "properties": {
    "iso:country":"US",
    "sg:address":"11042 Olinda St",
    "sg:city":"Sun Valley",
    "sg:classifiers":[
        {
            "category":"Manufacturing",
            "subcategory":"Glass & Minerals",
            "type":"Manufacturing & Wholesale Goods"
        }
    ],
    "sg:phone":"+1 818 768 9200",
    "sg:postcode":"91352",
    "sg:province":"CA",
    "sg:tags":[
        "abrasive",
        "product",
        "mfg"
    ],
    "wof:name":"Laurance Tile & Marble Design",
    "wof:placetype":"venue"
},
  "geometry": {"coordinates":[-118.37139000000001,34.223869],"type":"Point"}
}