{
  "type": "Feature",
  "properties": {
    "iso:country":"US",
    "sg:address":"1125 N Fig St",
    "sg:city":"Escondido",
    "sg:classifiers":[
        {
            "category":"Building & Trades",
            "subcategory":"Landscaping Services",
            "type":"Services"
        }
    ],
    "sg:phone":"+1 760 741 5274",
    "sg:postcode":"92026",
    "sg:province":"CA",
    "sg:tags":[
        "landscape"
    ],
    "wof:name":"Ledesma Lazaro Landscaping",
    "wof:placetype":"venue"
},
  "geometry": {"coordinates":[-117.080118,33.139222],"type":"Point"}
}