{
  "type": "Feature",
  "properties": {
    "iso:country":"US",
    "sg:address":"1955 36th St",
    "sg:city":"Sacramento",
    "sg:classifiers":[
        {
            "category":"Personal",
            "type":"Services"
        },
        {
            "category":"Professional",
            "subcategory":"Business Services",
            "type":"Services"
        },
        {
            "category":"Conference Center",
            "type":"Public Place"
        }
    ],
    "sg:phone":"+1 800 800 0230",
    "sg:postcode":"95816",
    "sg:province":"CA",
    "sg:tags":[
        "facility",
        "supply",
        "planning",
        "convention",
        "party",
        "event"
    ],
    "sg:website":"www.spectrumevents.com",
    "wof:name":"Spectrum Events",
    "wof:placetype":"venue"
},
  "geometry": {"coordinates":[-121.46355,38.560142],"type":"Point"}
}