{
  "type": "Feature",
  "properties": {
    "addr:full":"1056 Glenneyre St Laguna Beach CA 92651",
    "addr:housenumber":"1056",
    "addr:postcode":"92651",
    "addr:street":"Glenneyre St",
    "iso:country":"US",
    "sg:address":"1056 Glenneyre St",
    "sg:city":"Laguna Beach",
    "sg:classifiers":[
        {
            "category":"Professional",
            "subcategory":"Business Services",
            "type":"Services"
        }
    ],
    "sg:phone":"+1 949 376 5110",
    "sg:postcode":"92651",
    "sg:province":"CA",
    "sg:tags":[
        "interior",
        "consultant",
        "design",
        "decorator"
    ],
    "wof:name":"Cannery Exchange",
    "wof:placetype":"venue"
},
  "geometry": {"coordinates":[-117.776461,33.535096],"type":"Point"}
}