{
  "type": "Feature",
  "properties": {
    "addr:full":"901 Dover Dr Newport Beach CA 92660",
    "addr:housenumber":"901",
    "addr:postcode":"92660",
    "addr:street":"Dover Dr",
    "iso:country":"US",
    "sg:address":"901 Dover Dr",
    "sg:city":"Newport Beach",
    "sg:classifiers":[
        {
            "category":"Health Services",
            "subcategory":"Doctor",
            "type":"Services"
        }
    ],
    "sg:phone":"+1 949 646 4865",
    "sg:postcode":"92660",
    "sg:province":"CA",
    "sg:tags":[
        "physician",
        "surgeon"
    ],
    "wof:name":"Fred Galluccio MD",
    "wof:placetype":"venue"
},
  "geometry": {"coordinates":[-117.90408499999999,33.625105],"type":"Point"}
}