{
  "type": "Feature",
  "properties": {
    "addr:full":"489 Central Ave Upland CA 91786",
    "addr:housenumber":"489",
    "addr:postcode":"91786",
    "addr:street":"Central Ave",
    "iso:country":"US",
    "sg:address":"489 Central Ave",
    "sg:city":"Upland",
    "sg:classifiers":[
        {
            "category":"Professional",
            "subcategory":"Lawyer & Legal Services",
            "type":"Services"
        }
    ],
    "sg:phone":"+1 909 946 7270",
    "sg:postcode":"91786",
    "sg:province":"CA",
    "sg:tags":[
        "attorney"
    ],
    "wof:name":"Elizabeth F Courtney",
    "wof:placetype":"venue"
},
  "geometry": {"coordinates":[-117.689713,34.096991],"type":"Point"}
}