{
  "type": "Feature",
  "properties": {
    "iso:country":"US",
    "sg:address":"615 S Grand Avenue",
    "sg:city":"Los Angeles",
    "sg:classifiers":[
        {
            "category":"Utilities",
            "type":"Services"
        }
    ],
    "sg:phone":"+1 213 452 7024",
    "sg:postcode":"90017",
    "sg:province":"CA",
    "sg:tags":[
        "provider",
        "internet"
    ],
    "sg:website":"www.vertextelecom.com",
    "wof:name":"Vertex Group",
    "wof:placetype":"venue"
},
  "geometry": {"coordinates":[-118.25532,34.048482],"type":"Point"}
}