{
  "type": "Feature",
  "properties": {
    "iso:country":"US",
    "sg:address":"509 Saint Malo Ave",
    "sg:city":"La Puente",
    "sg:classifiers":[
        {
            "category":"Freight",
            "type":"Transportation"
        }
    ],
    "sg:phone":"+1 626 919 7668",
    "sg:postcode":"91744",
    "sg:province":"CA",
    "sg:tags":[
        "operator",
        "local",
        "trucking"
    ],
    "wof:name":"Rosealinda G Maxilom",
    "wof:placetype":"venue"
},
  "geometry": {"coordinates":[-117.962445,34.036095],"type":"Point"}
}