{
  "type": "Feature",
  "properties": {
    "iso:country":"US",
    "sg:address":"1560 E Chevy Chase Dr Ste 140",
    "sg:city":"Glendale",
    "sg:classifiers":[
        {
            "category":"Health Services",
            "subcategory":"Clinic",
            "type":"Services"
        }
    ],
    "sg:phone":"+1 818 254 1600",
    "sg:postcode":"91206",
    "sg:province":"CA",
    "sg:tags":[
        "medical"
    ],
    "sg:website":"www.cctstudy.com",
    "wof:name":"California Clinical Trials",
    "wof:placetype":"venue"
},
  "geometry": {"coordinates":[-118.230192,34.152805],"type":"Point"}
}