{
  "type": "Feature",
  "properties": {
    "iso:country":"US",
    "sg:address":"910 Via de la Paz",
    "sg:city":"Pacific Plsds",
    "sg:classifiers":[
        {
            "category":"Health Services",
            "subcategory":"Chiropractor",
            "type":"Services"
        }
    ],
    "sg:phone":"+1 310 230 2334",
    "sg:postcode":"90272",
    "sg:province":"CA",
    "wof:name":"Chiropractic Healthcare",
    "wof:placetype":"venue"
},
  "geometry": {"coordinates":[-118.526836,34.047907],"type":"Point"}
}