{
  "type": "Feature",
  "properties": {
    "iso:country":"US",
    "sg:address":"845 Marina Bay Pkwy",
    "sg:city":"Richmond",
    "sg:classifiers":[
        {
            "category":"Professional",
            "subcategory":"Business Services",
            "type":"Services"
        }
    ],
    "sg:phone":"+1 510 215 6380",
    "sg:postcode":"94804",
    "sg:province":"CA",
    "sg:tags":[
        "inspection"
    ],
    "wof:name":"Columbia Inspections Inc.",
    "wof:placetype":"venue"
},
  "geometry": {"coordinates":[-122.346493,37.919442],"type":"Point"}
}