{
  "type": "Feature",
  "properties": {
    "addr:full":"1340 S. De Anza Blvd. Suite #106 San Jose CA 95129",
    "addr:housenumber":"1340",
    "addr:postcode":"95129",
    "addr:street":"S. De Anza Blvd. Suite # 106",
    "iso:country":"US",
    "sg:address":"1340 S. De Anza Blvd. Suite #106",
    "sg:city":"San Jose",
    "sg:classifiers":[
        {
            "category":"Professional",
            "subcategory":"Computer Services",
            "type":"Services"
        }
    ],
    "sg:phone":"+1 408 872 3100",
    "sg:postcode":"95129",
    "sg:province":"CA",
    "sg:tags":[
        "lead-generation-software",
        "data-append-software",
        "candidate-sourcing-solutions",
        "internet-research-software"
    ],
    "sg:website":"http://www.egrabber.com",
    "wof:name":"eGrabber",
    "wof:placetype":"venue"
},
  "geometry": {"coordinates":[-122.03218,37.300013],"type":"Point"}
}