{
  "type": "Feature",
  "properties": {
    "iso:country":"US",
    "sg:address":"17048 Chatsworth St",
    "sg:city":"Granada Hills",
    "sg:classifiers":[
        {
            "category":"Real Estate",
            "subcategory":"Real Estate Agent",
            "type":"Services"
        }
    ],
    "sg:phone":"+1 818 366 4779",
    "sg:postcode":"91344",
    "sg:province":"CA",
    "wof:name":"Mickle Ardi & Assoc",
    "wof:placetype":"venue"
},
  "geometry": {"coordinates":[-118.50300799999999,34.264701],"type":"Point"}
}