{
  "type": "Feature",
  "properties": {
    "addr:full":"1005 Oxford St Berkeley CA 94707",
    "addr:housenumber":"1005",
    "addr:postcode":"94707",
    "addr:street":"Oxford St",
    "iso:country":"US",
    "sg:address":"1005 Oxford St",
    "sg:city":"Berkeley",
    "sg:classifiers":[
        {
            "category":"Professional",
            "type":"Services"
        }
    ],
    "sg:phone":"+1 415 465 5054",
    "sg:postcode":"94707",
    "sg:province":"CA",
    "wof:name":"Ana Forest",
    "wof:placetype":"venue"
},
  "geometry": {"coordinates":[-122.26826699999999,37.890662],"type":"Point"}
}