{
  "type": "Feature",
  "properties": {
    "iso:country":"US",
    "sg:address":"7438 Stanford Pl",
    "sg:city":"Cupertino",
    "sg:classifiers":[
        {
            "category":"Manufacturing",
            "subcategory":"Retail Goods",
            "type":"Manufacturing & Wholesale Goods"
        }
    ],
    "sg:phone":"+1 408 725 8485",
    "sg:postcode":"95014",
    "sg:province":"CA",
    "sg:tags":[
        "product",
        "mfg"
    ],
    "wof:name":"Bil-Jax Inc",
    "wof:placetype":"venue"
},
  "geometry": {"coordinates":[-122.036567,37.30689],"type":"Point"}
}