{
  "type": "Feature",
  "properties": {
    "addr:full":"2405 S Norfolk St San Mateo CA 94403",
    "addr:housenumber":"2405",
    "addr:postcode":"94403",
    "addr:street":"S Norfolk St",
    "iso:country":"US",
    "sg:address":"2405 S Norfolk St",
    "sg:city":"San Mateo",
    "sg:classifiers":[
        {
            "category":"Freight",
            "type":"Transportation"
        }
    ],
    "sg:phone":"+1 650 570 5737",
    "sg:postcode":"94403",
    "sg:province":"CA",
    "sg:tags":[
        "operator",
        "local",
        "trucking"
    ],
    "wof:name":"C B Trucking",
    "wof:placetype":"venue"
},
  "geometry": {"coordinates":[-122.288122,37.549591],"type":"Point"}
}