{
  "type": "Feature",
  "properties": {
    "addr:full":"130 S Hope Ave Santa Barbara CA 93105",
    "addr:housenumber":"130",
    "addr:postcode":"93105",
    "addr:street":"S Hope Ave",
    "iso:country":"US",
    "sg:address":"130 S Hope Ave",
    "sg:city":"Santa Barbara",
    "sg:classifiers":[
        {
            "category":"Shopping",
            "subcategory":"Clothing, Apparel, & Fashions",
            "type":"Retail Goods"
        }
    ],
    "sg:phone":"+1 805 569 7111",
    "sg:postcode":"93105",
    "sg:province":"CA",
    "sg:tags":[
        "lingerie"
    ],
    "sg:website":"www.victoriassecret.com",
    "wof:name":"Victoria Secret",
    "wof:placetype":"venue"
},
  "geometry": {"coordinates":[-119.746833,34.437218],"type":"Point"}
}