{
  "type": "Feature",
  "properties": {
    "iso:country":"US",
    "sg:address":"140 Town and Country Dr",
    "sg:city":"Danville",
    "sg:classifiers":[
        {
            "category":"Banks & Credit Unions",
            "subcategory":"Bank",
            "type":"Services"
        }
    ],
    "sg:phone":"+1 925 838 1121",
    "sg:postcode":"94526",
    "sg:province":"CA",
    "sg:tags":[
        "loan"
    ],
    "wof:name":"Town & Country Financial",
    "wof:placetype":"venue"
},
  "geometry": {"coordinates":[-121.997935,37.815121],"type":"Point"}
}