{
  "type": "Feature",
  "properties": {
    "iso:country":"US",
    "sg:address":"21722 Roscoe Blvd",
    "sg:city":"Canoga Park",
    "sg:classifiers":[
        {
            "category":"Manufacturing",
            "subcategory":"Printing",
            "type":"Manufacturing & Wholesale Goods"
        }
    ],
    "sg:phone":"+1 818 932 8950",
    "sg:postcode":"91304",
    "sg:province":"CA",
    "sg:tags":[
        "lithographic",
        "commercial"
    ],
    "wof:name":"Alfa Printing Supplies",
    "wof:placetype":"venue"
},
  "geometry": {"coordinates":[-118.605635,34.21959],"type":"Point"}
}