{
  "type": "Feature",
  "properties": {
    "iso:country":"US",
    "sg:address":"354 W Lancaster Blvd",
    "sg:city":"Lancaster",
    "sg:classifiers":[
        {
            "category":"Social Services",
            "subcategory":"Child Care",
            "type":"Services"
        }
    ],
    "sg:phone":"+1 661 942 5414",
    "sg:postcode":"93534",
    "sg:province":"CA",
    "sg:tags":[
        "kindergarten",
        "academic",
        "school"
    ],
    "wof:name":"Children's Corner",
    "wof:placetype":"venue"
},
  "geometry": {"coordinates":[-118.134271,34.698583],"type":"Point"}
}