{
  "type": "Feature",
  "properties": {
    "addr:full":"12700 Rosedale Hwy Bakersfield CA 93312",
    "addr:housenumber":"12700",
    "addr:postcode":"93312",
    "addr:street":"Rosedale Hwy",
    "iso:country":"US",
    "sg:address":"12700 Rosedale Hwy",
    "sg:city":"Bakersfield",
    "sg:classifiers":[
        {
            "category":"Professional",
            "subcategory":"Engineering",
            "type":"Services"
        }
    ],
    "sg:phone":"+1 661 587 4067",
    "sg:postcode":"93312",
    "sg:province":"CA",
    "sg:tags":[
        "general",
        "contractor"
    ],
    "wof:name":"Grijalva Contractors",
    "wof:placetype":"venue"
},
  "geometry": {"coordinates":[-119.142725,35.383641],"type":"Point"}
}