{
  "type": "Feature",
  "properties": {
    "addr:full":"1320 Gateway Dr Paso Robles CA 93446",
    "addr:housenumber":"1320",
    "addr:postcode":"93446",
    "addr:street":"Gateway Dr",
    "iso:country":"US",
    "sg:address":"1320 Gateway Dr",
    "sg:city":"Paso Robles",
    "sg:classifiers":[
        {
            "category":"Wholesale",
            "subcategory":"Stationery",
            "type":"Manufacturing & Wholesale Goods"
        }
    ],
    "sg:phone":"+1 805 239 7799",
    "sg:postcode":"93446",
    "sg:province":"CA",
    "sg:tags":[
        "school",
        "supply"
    ],
    "sg:website":"www.debcoschoolequipment.com",
    "wof:name":"Debco School Equipment",
    "wof:placetype":"venue"
},
  "geometry": {"coordinates":[-120.87099499999999,35.720543],"type":"Point"}
}