{
  "type": "Feature",
  "properties": {
    "iso:country":"US",
    "sg:address":"28400 Thermal Rd",
    "sg:city":"Sanger",
    "sg:classifiers":[
        {
            "category":"Utilities",
            "type":"Services"
        }
    ],
    "sg:phone":"+1 559 787 3571",
    "sg:postcode":"93657",
    "sg:province":"CA",
    "wof:name":"Dba",
    "wof:placetype":"venue"
},
  "geometry": {"coordinates":[-119.397941,36.757129],"type":"Point"}
}