{
  "type": "Feature",
  "properties": {
    "iso:country":"US",
    "sg:address":"3371 Arden Rd",
    "sg:city":"Hayward",
    "sg:classifiers":[
        {
            "category":"Wholesale",
            "subcategory":"Groceries",
            "type":"Manufacturing & Wholesale Goods"
        }
    ],
    "sg:phone":"+1 510 784 5919",
    "sg:postcode":"94545",
    "sg:province":"CA",
    "sg:tags":[
        "packaged"
    ],
    "wof:name":"Tree of Life West-Hayward",
    "wof:placetype":"venue"
},
  "geometry": {"coordinates":[-122.108734,37.620936],"type":"Point"}
}