{
  "type": "Feature",
  "properties": {
    "addr:full":"11511 Knott Ave Cypress CA 90630",
    "addr:housenumber":"11511",
    "addr:postcode":"90630",
    "addr:street":"Knott Ave",
    "iso:country":"US",
    "sg:address":"11511 Knott Ave",
    "sg:city":"Cypress",
    "sg:classifiers":[
        {
            "category":"Professional",
            "subcategory":"Printing & Photocopies",
            "type":"Services"
        }
    ],
    "sg:phone":"+1 714 896 0122",
    "sg:postcode":"90630",
    "sg:province":"CA",
    "sg:tags":[
        "duplicating",
        "copying"
    ],
    "wof:name":"122 Copy",
    "wof:placetype":"venue"
},
  "geometry": {"coordinates":[-118.010755,33.806442],"type":"Point"}
}