{
  "type": "Feature",
  "properties": {
    "addr:full":"7325 Bock Ave Stanton CA 90680",
    "addr:housenumber":"7325",
    "addr:postcode":"ca 90680",
    "addr:street":"Bock Ave",
    "iso:country":"US",
    "sg:address":"7325 Bock Ave",
    "sg:city":"Stanton",
    "sg:classifiers":[
        {
            "category":"Freight",
            "type":"Transportation"
        }
    ],
    "sg:phone":"+1 714 527 1774",
    "sg:postcode":"90680",
    "sg:province":"CA",
    "sg:tags":[
        "operator",
        "local",
        "trucking"
    ],
    "wof:name":"Donald Woodhouse Trucking",
    "wof:placetype":"venue"
},
  "geometry": {"coordinates":[-118.005284,33.806065],"type":"Point"}
}