{
  "type": "Feature",
  "properties": {
    "addr:full":"11782 Western Ave Garden Grove CA 90680",
    "addr:housenumber":"11782",
    "addr:postcode":"90680",
    "addr:street":"Western Ave",
    "iso:country":"US",
    "sg:address":"11782 Western Ave",
    "sg:city":"Garden Grove",
    "sg:classifiers":[
        {
            "category":"Retail",
            "subcategory":"Auto Repair",
            "type":"Services"
        }
    ],
    "sg:phone":"+1 714 891 7850",
    "sg:postcode":"90680",
    "sg:province":"CA",
    "wof:name":"Dean's Garage",
    "wof:placetype":"venue"
},
  "geometry": {"coordinates":[-118.000612,33.791299],"type":"Point"}
}