{
  "type": "Feature",
  "properties": {
    "iso:country":"US",
    "sg:address":"965 E Main St",
    "sg:city":"Santa Paula",
    "sg:classifiers":[
        {
            "category":"Professional",
            "subcategory":"Accounting & Tax Preparation",
            "type":"Services"
        }
    ],
    "sg:phone":"+1 805 525 5968",
    "sg:postcode":"93060",
    "sg:province":"CA",
    "sg:tags":[
        "return",
        "filing"
    ],
    "wof:name":"Gustavo Ramirez Income Tax Svc",
    "wof:placetype":"venue"
},
  "geometry": {"coordinates":[-119.06061099999999,34.353784],"type":"Point"}
}