{
  "type": "Feature",
  "properties": {
    "iso:country":"US",
    "sg:address":"3350 Macarthur Blvd",
    "sg:city":"Oakland",
    "sg:classifiers":[
        {
            "category":"Social Services",
            "type":"Services"
        }
    ],
    "sg:phone":"+1 510 482 1738",
    "sg:postcode":"94602",
    "sg:province":"CA",
    "sg:tags":[
        "youth",
        "organization",
        "center"
    ],
    "wof:name":"Project Reconnect",
    "wof:placetype":"venue"
},
  "geometry": {"coordinates":[-122.201713,37.794891],"type":"Point"}
}