{
  "type": "Feature",
  "properties": {
    "addr:full":"3200 Highland Ave National City CA 91950",
    "addr:housenumber":"3200",
    "addr:postcode":"91950",
    "addr:street":"Highland Ave",
    "iso:country":"US",
    "sg:address":"3200 Highland Ave",
    "sg:city":"National City",
    "sg:classifiers":[
        {
            "category":"Retail",
            "subcategory":"Repair Shop",
            "type":"Services"
        }
    ],
    "sg:phone":"+1 619 474 1977",
    "sg:postcode":"91950",
    "sg:province":"CA",
    "sg:tags":[
        "reupholstery",
        "furniture"
    ],
    "wof:name":"Classic Upholstery",
    "wof:placetype":"venue"
},
  "geometry": {"coordinates":[-117.091003,32.657398],"type":"Point"}
}