{
  "type": "Feature",
  "properties": {
    "iso:country":"US",
    "sg:address":"1000 E Bidwell St",
    "sg:city":"Folsom",
    "sg:classifiers":[
        {
            "category":"Restaurant",
            "type":"Food & Drink"
        }
    ],
    "sg:menulink":"http://www.allmenus.com/ca/folsom/69241-mountain-mikes-pizza/menu/",
    "sg:phone":"+1 916 983 3331",
    "sg:postcode":"95630",
    "sg:province":"CA",
    "sg:tags":[
        "american",
        "pizza"
    ],
    "wof:name":"Mountain Mike's Pizza",
    "wof:placetype":"venue"
},
  "geometry": {"coordinates":[-121.156412,38.670261],"type":"Point"}
}