{
  "type": "Feature",
  "properties": {
    "iso:country":"US",
    "sg:address":"20682 Scofield Dr",
    "sg:city":"Cupertino",
    "sg:classifiers":[
        {
            "category":"Farming",
            "subcategory":"Orchard",
            "type":"Manufacturing & Wholesale Goods"
        }
    ],
    "sg:phone":"+1 408 252 3874",
    "sg:postcode":"95014",
    "sg:province":"CA",
    "sg:tags":[
        "citrus",
        "grove",
        "fruit"
    ],
    "wof:name":"Frank Farran",
    "wof:placetype":"venue"
},
  "geometry": {"coordinates":[-122.033953,37.321002],"type":"Point"}
}