{
  "type": "Feature",
  "properties": {
    "addr:full":"17842 Bellflower Blvd Bellflower CA 90706",
    "addr:housenumber":"17842",
    "addr:postcode":"90706",
    "addr:street":"Bellflower Blvd",
    "iso:country":"US",
    "sg:address":"17842 Bellflower Blvd",
    "sg:city":"Bellflower",
    "sg:classifiers":[
        {
            "category":"Personal",
            "subcategory":"Nail Salon",
            "type":"Services"
        }
    ],
    "sg:phone":"+1 562 925 1259",
    "sg:postcode":"90706",
    "sg:province":"CA",
    "wof:name":"Spa Nail and Facial",
    "wof:placetype":"venue"
},
  "geometry": {"coordinates":[-118.12514,33.869998],"type":"Point"}
}