{
  "type": "Feature",
  "properties": {
    "addr:full":"2568 Elden Ave Costa Mesa CA 92627",
    "addr:housenumber":"2568",
    "addr:postcode":"92627",
    "addr:street":"Elden Ave",
    "iso:country":"US",
    "sg:address":"2568 Elden Ave",
    "sg:city":"Costa Mesa",
    "sg:classifiers":[
        {
            "category":"Retail",
            "subcategory":"Repair Shop",
            "type":"Services"
        }
    ],
    "sg:phone":"+1 949 650 1950",
    "sg:postcode":"92627",
    "sg:province":"CA",
    "sg:tags":[
        "equipment"
    ],
    "wof:name":"West Coast Beverage Company",
    "wof:placetype":"venue"
},
  "geometry": {"coordinates":[-117.89645,33.660422],"type":"Point"}
}