{
  "type": "Feature",
  "properties": {
    "addr:full":"3340 Gibraltar Dr Riverside CA 92506",
    "addr:housenumber":"3340",
    "addr:postcode":"92506",
    "addr:street":"Gibraltar Dr",
    "iso:country":"US",
    "sg:address":"3340 Gibraltar Dr",
    "sg:city":"Riverside",
    "sg:classifiers":[
        {
            "category":"Education",
            "subcategory":"Vocational School",
            "type":"Public Place"
        }
    ],
    "sg:phone":"+1 951 826 7936",
    "sg:postcode":"92506",
    "sg:province":"CA",
    "sg:tags":[
        "training",
        "computer"
    ],
    "wof:name":"Applied Training Ctr",
    "wof:placetype":"venue"
},
  "geometry": {"coordinates":[-117.381929,33.957137],"type":"Point"}
}