{
  "type": "Feature",
  "properties": {
    "addr:full":"602 N Flower St Santa Ana CA 92703",
    "addr:housenumber":"602",
    "addr:postcode":"92703",
    "addr:street":"N Flower St",
    "iso:country":"US",
    "sg:address":"602 N Flower St",
    "sg:city":"Santa Ana",
    "sg:classifiers":[
        {
            "category":"Fast Food",
            "type":"Food & Drink"
        }
    ],
    "sg:phone":"+1 714 656 2888",
    "sg:postcode":"92703",
    "sg:province":"CA",
    "sg:tags":[
        "burger"
    ],
    "sg:website":"www.downtownstadiumgrill.com",
    "wof:name":"Downtown Stadium Grill",
    "wof:placetype":"venue"
},
  "geometry": {"coordinates":[-117.87831199999999,33.750624],"type":"Point"}
}