{
  "type": "Feature",
  "properties": {
    "iso:country":"US",
    "sg:address":"468 N Camden Drive",
    "sg:city":"Beverly Hills",
    "sg:classifiers":[
        {
            "category":"Shopping",
            "subcategory":"Music",
            "type":"Retail Goods"
        }
    ],
    "sg:phone":"+1 310 860 4778",
    "sg:postcode":"90210",
    "sg:province":"CA",
    "sg:tags":[
        "dvd's"
    ],
    "wof:name":"Fxs Music",
    "wof:placetype":"venue"
},
  "geometry": {"coordinates":[-118.405181,34.06992],"type":"Point"}
}