{
  "type": "Feature",
  "properties": {
    "addr:full":"1836 E Colorado Blvd Pasadena CA 91107",
    "addr:housenumber":"1836",
    "addr:postcode":"91107",
    "addr:street":"E Colorado Blvd",
    "iso:country":"US",
    "sg:address":"1836 E Colorado Blvd",
    "sg:city":"Pasadena",
    "sg:classifiers":[
        {
            "category":"Shopping",
            "subcategory":"Shoes",
            "type":"Retail Goods"
        }
    ],
    "sg:phone":"+1 626 796 4971",
    "sg:postcode":"91107",
    "sg:province":"CA",
    "sg:tags":[
        "repair"
    ],
    "wof:name":"Novis Crrct & Cmvrt Shs",
    "wof:placetype":"venue"
},
  "geometry": {"coordinates":[-118.112364,34.145945],"type":"Point"}
}