{
  "type": "Feature",
  "properties": {
    "iso:country":"US",
    "sg:address":"1021 Austin St",
    "sg:city":"Madera",
    "sg:classifiers":[
        {
            "category":"Organizations",
            "subcategory":"Religious Organization",
            "type":"Services"
        }
    ],
    "sg:phone":"+1 559 674 0911",
    "sg:postcode":"93638",
    "sg:province":"CA",
    "sg:tags":[
        "church"
    ],
    "wof:name":"Church Of The Nazarene",
    "wof:placetype":"venue"
},
  "geometry": {"coordinates":[-120.059667,36.974198],"type":"Point"}
}