{
  "type": "Feature",
  "properties": {
    "iso:country":"US",
    "sg:address":"1140 Lincoln Ave",
    "sg:city":"San Jose",
    "sg:classifiers":[
        {
            "category":"Personal",
            "subcategory":"Beauty Salon",
            "type":"Services"
        }
    ],
    "sg:phone":"+1 408 920 0333",
    "sg:postcode":"95125",
    "sg:province":"CA",
    "wof:name":"Tippie Toes",
    "wof:placetype":"venue"
},
  "geometry": {"coordinates":[-121.900276,37.3075],"type":"Point"}
}