{
  "type": "Feature",
  "properties": {
    "addr:full":"101 2nd St San Francisco CA 94105",
    "addr:housenumber":"101",
    "addr:postcode":"94105",
    "addr:street":"2Nd St",
    "iso:country":"US",
    "sg:address":"101 2nd St",
    "sg:city":"San Francisco",
    "sg:classifiers":[
        {
            "category":"Banks & Credit Unions",
            "subcategory":"Investment Brokerage",
            "type":"Services"
        }
    ],
    "sg:phone":"+1 415 543 0733",
    "sg:postcode":"94105",
    "sg:province":"CA",
    "sg:tags":[
        "advisory",
        "referral"
    ],
    "wof:name":"Rockefeller Philanthropy Advsr",
    "wof:placetype":"venue"
},
  "geometry": {"coordinates":[-122.399255,37.787579],"type":"Point"}
}