{
  "type": "Feature",
  "properties": {
    "addr:full":"5241 Lincoln Ave Cypress CA 90630",
    "addr:housenumber":"5241",
    "addr:postcode":"90630",
    "addr:street":"Lincoln Ave",
    "iso:country":"US",
    "sg:address":"5241 Lincoln Ave",
    "sg:city":"Cypress",
    "sg:classifiers":[
        {
            "category":"Manufacturing",
            "subcategory":"Tools & Machinery",
            "type":"Manufacturing & Wholesale Goods"
        }
    ],
    "sg:phone":"+1 714 827 8811",
    "sg:postcode":"90630",
    "sg:province":"CA",
    "sg:tags":[
        "built",
        "industrial",
        "designed",
        "mfg"
    ],
    "wof:name":"Perfect Machinery",
    "wof:placetype":"venue"
},
  "geometry": {"coordinates":[-118.04468900000001,33.831859],"type":"Point"}
}