{
  "type": "Feature",
  "properties": {
    "addr:full":"2600 Michelson Dr Irvine CA 92612",
    "addr:housenumber":"2600",
    "addr:postcode":"92612",
    "addr:street":"Michelson Dr",
    "iso:country":"US",
    "sg:address":"2600 Michelson Dr",
    "sg:city":"Irvine",
    "sg:classifiers":[
        {
            "category":"Real Estate",
            "subcategory":"Real Estate Agent",
            "type":"Services"
        }
    ],
    "sg:phone":"+1 949 852 3650",
    "sg:postcode":"92612",
    "sg:province":"CA",
    "wof:name":"AMB Property Corp",
    "wof:placetype":"venue"
},
  "geometry": {"coordinates":[-117.852074,33.675479],"type":"Point"}
}