{
  "type": "Feature",
  "properties": {
    "addr:full":"405 E Branch St Arroyo Grande CA 93420",
    "addr:housenumber":"405",
    "addr:postcode":"93420",
    "addr:street":"E Branch St",
    "iso:country":"US",
    "sg:address":"405 E Branch St",
    "sg:city":"Arroyo Grande",
    "sg:classifiers":[
        {
            "category":"Real Estate",
            "subcategory":"Real Estate Agent",
            "type":"Services"
        }
    ],
    "sg:phone":"+1 805 489 7595",
    "sg:postcode":"93420",
    "sg:province":"CA",
    "wof:name":"Arroyo Grande Property Mgt",
    "wof:placetype":"venue"
},
  "geometry": {"coordinates":[-120.575266,35.125102],"type":"Point"}
}