{
  "type": "Feature",
  "properties": {
    "iso:country":"US",
    "sg:address":"3926 30th St",
    "sg:city":"San Diego",
    "sg:classifiers":[
        {
            "category":"Restaurant",
            "type":"Food & Drink"
        }
    ],
    "sg:phone":"+1 619 291 1859",
    "sg:postcode":"92104",
    "sg:province":"CA",
    "sg:tags":[
        "new",
        "american"
    ],
    "sg:website":"eltakeiteasy.com/",
    "wof:name":"El Take It Easy",
    "wof:placetype":"venue"
},
  "geometry": {"coordinates":[-117.130292,32.749038],"type":"Point"}
}