{
  "type": "Feature",
  "properties": {
    "iso:country":"US",
    "sg:address":"1297 W Hobsonway",
    "sg:city":"Blythe",
    "sg:classifiers":[
        {
            "category":"Health Services",
            "subcategory":"Doctor",
            "type":"Services"
        }
    ],
    "sg:phone":"+1 760 921 7870",
    "sg:postcode":"92225",
    "sg:province":"CA",
    "sg:tags":[
        "medical"
    ],
    "wof:name":"Mental Health Dept",
    "wof:placetype":"venue"
},
  "geometry": {"coordinates":[-114.60832,33.610234],"type":"Point"}
}