{
  "type": "Feature",
  "properties": {
    "iso:country":"US",
    "sg:address":"1621 N Placentia Ave",
    "sg:city":"Fullerton",
    "sg:classifiers":[
        {
            "category":"Food & Beverages",
            "subcategory":"Groceries & Convenience Stores",
            "type":"Retail Goods"
        }
    ],
    "sg:phone":"+1 714 993 9251",
    "sg:postcode":"92831",
    "sg:province":"CA",
    "sg:website":"www.7-eleven.com",
    "wof:name":"7-Eleven",
    "wof:placetype":"venue"
},
  "geometry": {"coordinates":[-117.875,33.887001],"type":"Point"}
}