{
  "type": "Feature",
  "properties": {
    "addr:full":"13464 Ave 152 Tipton CA 93272",
    "addr:housenumber":"13464",
    "addr:postcode":"93272",
    "addr:street":"Ave 152",
    "iso:country":"US",
    "sg:address":"13464 Ave 152",
    "sg:city":"Tipton",
    "sg:classifiers":[
        {
            "category":"Farming",
            "subcategory":"Dairy Farm",
            "type":"Manufacturing & Wholesale Goods"
        }
    ],
    "sg:phone":"+1 559 752 1100",
    "sg:postcode":"93272",
    "sg:province":"CA",
    "wof:name":"Pires Dairy",
    "wof:placetype":"venue"
},
  "geometry": {"coordinates":[-119.273949,36.065802],"type":"Point"}
}