{
  "type": "Feature",
  "properties": {
    "iso:country":"US",
    "sg:address":"6221 Metropolitan St",
    "sg:city":"Carlsbad",
    "sg:classifiers":[
        {
            "category":"Health Services",
            "subcategory":"Dentist",
            "type":"Services"
        }
    ],
    "sg:phone":"+1 760 438 1279",
    "sg:postcode":"92009",
    "sg:province":"CA",
    "sg:tags":[
        "pediatric"
    ],
    "wof:name":"Sheikh Cyrous DDS Ms",
    "wof:placetype":"venue"
},
  "geometry": {"coordinates":[-117.265615,33.123076],"type":"Point"}
}