{
  "type": "Feature",
  "properties": {
    "addr:full":"10809 Myrtle Ave Lamont CA 93241",
    "addr:housenumber":"10809",
    "addr:postcode":"93241",
    "addr:street":"Myrtle Ave",
    "iso:country":"US",
    "sg:address":"10809 Myrtle Ave",
    "sg:city":"Lamont",
    "sg:classifiers":[
        {
            "category":"Retail",
            "subcategory":"Laundry & Dry Cleaning",
            "type":"Services"
        },
        {
            "category":"Building & Trades",
            "subcategory":"Cleaning & Sanitation",
            "type":"Services"
        }
    ],
    "sg:phone":"+1 661 809 0548",
    "sg:postcode":"93241",
    "sg:province":"CA",
    "sg:tags":[
        "cleaner",
        "house"
    ],
    "wof:name":"Aztec Clean Ups",
    "wof:placetype":"venue"
},
  "geometry": {"coordinates":[-118.909806,35.256908],"type":"Point"}
}