{
  "type": "Feature",
  "properties": {
    "iso:country":"US",
    "sg:address":"19151 Yacht Ln",
    "sg:city":"Huntington Beach",
    "sg:classifiers":[
        {
            "category":"Professional",
            "subcategory":"Computer Services",
            "type":"Services"
        }
    ],
    "sg:phone":"+1 714 962 1242",
    "sg:postcode":"92646",
    "sg:province":"CA",
    "sg:tags":[
        "prepackaged",
        "software"
    ],
    "wof:name":"Micros Systems Inc",
    "wof:placetype":"venue"
},
  "geometry": {"coordinates":[-117.97963900000001,33.684489],"type":"Point"}
}