{
  "type": "Feature",
  "properties": {
    "addr:full":"2940 16th Street San Francisco CA 94103",
    "addr:housenumber":"2940",
    "addr:postcode":"94103",
    "addr:street":"16Th Street",
    "iso:country":"US",
    "sg:address":"2940 16th Street",
    "sg:city":"San Francisco",
    "sg:classifiers":[
        {
            "category":"Professional",
            "subcategory":"Employment Agencies",
            "type":"Services"
        }
    ],
    "sg:phone":"+1 415 252 9960",
    "sg:postcode":"94103",
    "sg:province":"CA",
    "wof:name":"Development Center For Children Youth and Their Families",
    "wof:placetype":"venue"
},
  "geometry": {"coordinates":[-122.418448,37.765189],"type":"Point"}
}