{
  "type": "Feature",
  "properties": {
    "iso:country":"US",
    "sg:address":"417 Beech Ave",
    "sg:city":"San Bruno",
    "sg:classifiers":[
        {
            "category":"Building & Trades",
            "subcategory":"Construction",
            "type":"Services"
        }
    ],
    "sg:phone":"+1 650 873 1631",
    "sg:postcode":"94066",
    "sg:province":"CA",
    "sg:tags":[
        "house"
    ],
    "wof:name":"Carrillo Construction Inc",
    "wof:placetype":"venue"
},
  "geometry": {"coordinates":[-122.418551,37.619832],"type":"Point"}
}