{
  "type": "Feature",
  "properties": {
    "addr:full":"8809 C Ave Hesperia CA 92345",
    "addr:housenumber":"8809",
    "addr:postcode":"92345",
    "addr:street":"C Ave",
    "iso:country":"US",
    "sg:address":"8809 C Ave",
    "sg:city":"Hesperia",
    "sg:classifiers":[
        {
            "category":"Professional",
            "type":"Services"
        }
    ],
    "sg:phone":"+1 760 244 6633",
    "sg:postcode":"92345",
    "sg:province":"CA",
    "wof:name":"Crossing At Hesperia",
    "wof:placetype":"venue"
},
  "geometry": {"coordinates":[-117.298636,34.411854],"type":"Point"}
}