{
  "type": "Feature",
  "properties": {
    "iso:country":"US",
    "sg:address":"465 Broadway",
    "sg:city":"Millbrae",
    "sg:classifiers":[
        {
            "category":"Restaurant",
            "type":"Food & Drink"
        }
    ],
    "sg:phone":"+1 650 697 7788",
    "sg:postcode":"94030",
    "sg:province":"CA",
    "sg:tags":[
        "chinese"
    ],
    "sg:website":"www.gourmetvillagerestaurant.com",
    "wof:name":"Gourmet Village",
    "wof:placetype":"venue"
},
  "geometry": {"coordinates":[-122.39371800000001,37.602112],"type":"Point"}
}