{
  "type": "Feature",
  "properties": {
    "iso:country":"US",
    "sg:address":"11278 Laurel Canyon Blvd",
    "sg:city":"San Fernando",
    "sg:classifiers":[
        {
            "category":"Autos & Motor Vehicles",
            "subcategory":"Fuel & Gas Station",
            "type":"Retail Goods"
        }
    ],
    "sg:phone":"+1 818 361 0411",
    "sg:postcode":"91340",
    "sg:province":"CA",
    "sg:tags":[
        "oil"
    ],
    "wof:name":"Laurel Canyon Shell",
    "wof:placetype":"venue"
},
  "geometry": {"coordinates":[-118.449738,34.275396],"type":"Point"}
}