{
  "type": "Feature",
  "properties": {
    "addr:full":"7606 E Chapman Ave Orange CA 92869",
    "addr:housenumber":"7606",
    "addr:postcode":"92869",
    "addr:street":"E Chapman Ave",
    "iso:country":"US",
    "sg:address":"7606 E Chapman Ave",
    "sg:city":"Orange",
    "sg:classifiers":[
        {
            "category":"Restaurant",
            "type":"Food & Drink"
        }
    ],
    "sg:phone":"+1 714 633 4161",
    "sg:postcode":"92869",
    "sg:province":"CA",
    "sg:tags":[
        "pizza"
    ],
    "wof:name":"Victoria's Pizza",
    "wof:placetype":"venue"
},
  "geometry": {"coordinates":[-117.772003,33.7952],"type":"Point"}
}