{
  "type": "Feature",
  "properties": {
    "iso:country":"US",
    "sg:address":"12502 Van Nuys Blvd",
    "sg:city":"Pacoima",
    "sg:classifiers":[
        {
            "category":"Social Services",
            "type":"Services"
        }
    ],
    "sg:phone":"+1 818 896 7776",
    "sg:postcode":"91331",
    "sg:province":"CA",
    "sg:tags":[
        "counselor",
        "marriage",
        "family"
    ],
    "sg:website":"www.elnidofamilycenters.org",
    "wof:name":"El Nido Svc",
    "wof:placetype":"venue"
},
  "geometry": {"coordinates":[-118.405882,34.277831],"type":"Point"}
}