{
  "type": "Feature",
  "properties": {
    "iso:country":"US",
    "sg:address":"1828 El Camino Real",
    "sg:city":"Burlingame",
    "sg:classifiers":[
        {
            "category":"Health Services",
            "subcategory":"Doctor",
            "type":"Services"
        }
    ],
    "sg:phone":"+1 650 259 8090",
    "sg:postcode":"94010",
    "sg:province":"CA",
    "wof:name":"Bulkin Bruce M DPM Facfas",
    "wof:placetype":"venue"
},
  "geometry": {"coordinates":[-122.38368800000001,37.595336],"type":"Point"}
}