{
  "type": "Feature",
  "properties": {
    "addr:full":"2027 Newcastle Ave Ste 501 Cardiff by the Sea CA 92007",
    "addr:housenumber":"2027",
    "addr:postcode":"92007",
    "addr:street":"Newcastle Ave Ste 501",
    "iso:country":"US",
    "sg:address":"2027 Newcastle Ave Ste 501",
    "sg:city":"Cardiff by the Sea",
    "sg:classifiers":[
        {
            "category":"Building & Trades",
            "subcategory":"Construction",
            "type":"Services"
        }
    ],
    "sg:phone":"+1 858 472 0988",
    "sg:postcode":"92007",
    "sg:province":"CA",
    "sg:tags":[
        "interior",
        "design"
    ],
    "sg:website":"www.Sensible-Chic.com",
    "wof:name":"Sensible Chic Interior Design",
    "wof:placetype":"venue"
},
  "geometry": {"coordinates":[-117.281971,33.022763],"type":"Point"}
}