{
  "type": "Feature",
  "properties": {
    "addr:full":"1252 Fesler St El Cajon CA 92020",
    "addr:housenumber":"1252",
    "addr:postcode":"92020",
    "addr:street":"Fesler St",
    "iso:country":"US",
    "sg:address":"1252 Fesler St",
    "sg:city":"El Cajon",
    "sg:classifiers":[
        {
            "category":"Retail",
            "subcategory":"Storage",
            "type":"Services"
        }
    ],
    "sg:phone":"+1 619 562 5689",
    "sg:postcode":"92020",
    "sg:province":"CA",
    "sg:tags":[
        "self"
    ],
    "wof:name":"Fort Knox Storage",
    "wof:placetype":"venue"
},
  "geometry": {"coordinates":[-116.978996,32.808899],"type":"Point"}
}