{
  "type": "Feature",
  "properties": {
    "addr:full":"9716 Elk Grove Florin Rd Elk Grove CA 95624",
    "addr:housenumber":"9716",
    "addr:postcode":"95624",
    "addr:street":"Elk Grove Florin Rd",
    "iso:country":"US",
    "sg:address":"9716 Elk Grove Florin Rd",
    "sg:city":"Elk Grove",
    "sg:classifiers":[
        {
            "category":"Home & Garden",
            "subcategory":"Building Materials",
            "type":"Retail Goods"
        }
    ],
    "sg:phone":"+1 916 686 6034",
    "sg:postcode":"95624",
    "sg:province":"CA",
    "sg:tags":[
        "paint"
    ],
    "wof:name":"Sherwin-Williams Paints",
    "wof:placetype":"venue"
},
  "geometry": {"coordinates":[-121.371604,38.405092],"type":"Point"}
}