{
  "type": "Feature",
  "properties": {
    "iso:country":"US",
    "sg:address":"507 Purisima St",
    "sg:city":"Half Moon Bay",
    "sg:classifiers":[
        {
            "category":"Professional",
            "subcategory":"Engineering",
            "type":"Services"
        }
    ],
    "sg:phone":"+1 650 726 9494",
    "sg:postcode":"94019",
    "sg:province":"CA",
    "sg:tags":[
        "engineer"
    ],
    "sg:website":"www.mcvicker.com",
    "wof:name":"Mc Vicker Associates Inc",
    "wof:placetype":"venue"
},
  "geometry": {"coordinates":[-122.43024200000001,37.462766],"type":"Point"}
}