{
  "type": "Feature",
  "properties": {
    "iso:country":"US",
    "sg:address":"601 San Gabriel Ave",
    "sg:city":"Albany",
    "sg:classifiers":[
        {
            "category":"Organizations",
            "subcategory":"Non-profit Organization",
            "type":"Services"
        }
    ],
    "sg:phone":"+1 510 525 7845",
    "sg:postcode":"94706",
    "sg:province":"CA",
    "wof:name":"Easter Seals Bay Area",
    "wof:placetype":"venue"
},
  "geometry": {"coordinates":[-122.29439499999999,37.894565],"type":"Point"}
}