{
  "type": "Feature",
  "properties": {
    "addr:full":"1035 Camellia Dr Alameda CA 94502",
    "addr:housenumber":"1035",
    "addr:postcode":"94502",
    "addr:street":"Camellia Dr",
    "iso:country":"US",
    "sg:address":"1035 Camellia Dr",
    "sg:city":"Alameda",
    "sg:classifiers":[
        {
            "category":"Health Services",
            "subcategory":"Doctor",
            "type":"Services"
        }
    ],
    "sg:phone":"+1 510 523 4151",
    "sg:postcode":"94502",
    "sg:province":"CA",
    "wof:name":"Center For Healthy Living And Family Medicine",
    "wof:placetype":"venue"
},
  "geometry": {"coordinates":[-122.238544,37.734097],"type":"Point"}
}