{
  "type": "Feature",
  "properties": {
    "iso:country":"US",
    "sg:address":"338 Garden Hwy",
    "sg:city":"Yuba City",
    "sg:classifiers":[
        {
            "category":"Organizations",
            "subcategory":"Community Association",
            "type":"Services"
        }
    ],
    "sg:phone":"+1 530 673 8693",
    "sg:postcode":"95991",
    "sg:province":"CA",
    "sg:tags":[
        "club"
    ],
    "wof:name":"Allstate Motor Club Emergency",
    "wof:placetype":"venue"
},
  "geometry": {"coordinates":[-121.610196,39.124298],"type":"Point"}
}