{
  "type": "Feature",
  "properties": {
    "iso:country":"US",
    "sg:address":"975 W 5th St",
    "sg:city":"San Pedro",
    "sg:classifiers":[
        {
            "category":"Government",
            "subcategory":"Court House",
            "type":"Public Place"
        }
    ],
    "sg:phone":"+1 562 491 6324",
    "sg:postcode":"90731",
    "sg:province":"CA",
    "sg:tags":[
        "legal"
    ],
    "wof:name":"Judy Office",
    "wof:placetype":"venue"
},
  "geometry": {"coordinates":[-118.297552,33.73958],"type":"Point"}
}