{
  "type": "Feature",
  "properties": {
    "iso:country":"US",
    "sg:address":"1403 Silver Oak Ct",
    "sg:city":"Pinole",
    "sg:classifiers":[
        {
            "category":"Travel",
            "subcategory":"Travel Agent",
            "type":"Entertainment"
        }
    ],
    "sg:phone":"+1 510 724 7020",
    "sg:postcode":"94564",
    "sg:province":"CA",
    "sg:tags":[
        "agency"
    ],
    "wof:name":"ABC World Travel",
    "wof:placetype":"venue"
},
  "geometry": {"coordinates":[-122.28894,37.998023],"type":"Point"}
}