{
  "type": "Feature",
  "properties": {
    "addr:full":"1320 Standiford Ave Modesto CA 95350",
    "addr:housenumber":"1320",
    "addr:postcode":"ca 95350",
    "addr:street":"Standiford Ave",
    "iso:country":"US",
    "sg:address":"1320 Standiford Ave",
    "sg:city":"Modesto",
    "sg:classifiers":[
        {
            "category":"Banks & Credit Unions",
            "subcategory":"Financial Services",
            "type":"Services"
        }
    ],
    "sg:phone":"+1 209 572 2900",
    "sg:postcode":"95350",
    "sg:province":"CA",
    "sg:tags":[
        "cashing",
        "loan",
        "payday",
        "alternative",
        "check"
    ],
    "sg:website":"http://www.acecashexpress.com",
    "wof:name":"ACE Cash Express",
    "wof:placetype":"venue"
},
  "geometry": {"coordinates":[-121.01298199999999,37.689343],"type":"Point"}
}