{
  "type": "Feature",
  "properties": {
    "iso:country":"US",
    "sg:address":"11 Cortez Ct",
    "sg:city":"Oakland",
    "sg:classifiers":[
        {
            "category":"Building & Trades",
            "subcategory":"Landscaping Services",
            "type":"Services"
        }
    ],
    "sg:phone":"+1 510 339 9798",
    "sg:postcode":"94611",
    "sg:province":"CA",
    "sg:tags":[
        "landscape"
    ],
    "wof:name":"Top Floor Designs LLC",
    "wof:placetype":"venue"
},
  "geometry": {"coordinates":[-122.20172100000001,37.830282],"type":"Point"}
}