{
  "type": "Feature",
  "properties": {
    "iso:country":"US",
    "sg:address":"6790 Top Gun St",
    "sg:city":"San Diego",
    "sg:classifiers":[
        {
            "category":"Building & Trades",
            "subcategory":"Plumbing",
            "type":"Services"
        }
    ],
    "sg:phone":"+1 858 535 9797",
    "sg:postcode":"92121",
    "sg:province":"CA",
    "sg:tags":[
        "plumbing",
        "contractor"
    ],
    "wof:name":"Pipeline Plumbing & Mechanical",
    "wof:placetype":"venue"
},
  "geometry": {"coordinates":[-117.172909,32.910536],"type":"Point"}
}