{
  "type": "Feature",
  "properties": {
    "iso:country":"US",
    "sg:address":"15 Knoll Ln",
    "sg:city":"Mill Valley",
    "sg:classifiers":[
        {
            "category":"Freight",
            "type":"Transportation"
        }
    ],
    "sg:phone":"+1 415 389 0995",
    "sg:postcode":"94941",
    "sg:province":"CA",
    "sg:tags":[
        "courier"
    ],
    "wof:name":"Stabler Socket Courier Service",
    "wof:placetype":"venue"
},
  "geometry": {"coordinates":[-122.51246999999999,37.901582],"type":"Point"}
}