{
  "type": "Feature",
  "properties": {
    "addr:full":"2236 Pacific Ave Costa Mesa CA 92627",
    "addr:housenumber":"2236",
    "addr:postcode":"92627",
    "addr:street":"Pacific Ave",
    "iso:country":"US",
    "sg:address":"2236 Pacific Ave",
    "sg:city":"Costa Mesa",
    "sg:classifiers":[
        {
            "category":"Professional",
            "subcategory":"Business Services",
            "type":"Services"
        }
    ],
    "sg:phone":"+1 949 574 5255",
    "sg:postcode":"92627",
    "sg:province":"CA",
    "sg:tags":[
        "recording",
        "studio"
    ],
    "wof:name":"Music Soul Nature Publishing",
    "wof:placetype":"venue"
},
  "geometry": {"coordinates":[-117.94462,33.654869],"type":"Point"}
}