{
  "type": "Feature",
  "properties": {
    "addr:full":"23901 Calabasas Rd Calabasas CA 91302",
    "addr:housenumber":"23901",
    "addr:postcode":"91302",
    "addr:street":"Calabasas Rd",
    "iso:country":"US",
    "sg:address":"23901 Calabasas Rd",
    "sg:city":"Calabasas",
    "sg:classifiers":[
        {
            "category":"Professional",
            "subcategory":"Accounting & Tax Preparation",
            "type":"Services"
        }
    ],
    "sg:phone":"+1 818 222 2000",
    "sg:postcode":"91302",
    "sg:province":"CA",
    "sg:tags":[
        "accountant"
    ],
    "sg:website":"www.taxsavrs.com",
    "wof:name":"Kendall & Assoc",
    "wof:placetype":"venue"
},
  "geometry": {"coordinates":[-118.64867599999999,34.153454],"type":"Point"}
}