{
  "type": "Feature",
  "properties": {
    "addr:full":"2008 Banjo St Santa Rosa CA 95407",
    "addr:housenumber":"2008",
    "addr:postcode":"ca 95407",
    "addr:street":"Banjo St",
    "iso:country":"US",
    "sg:address":"2008 Banjo St",
    "sg:city":"Santa Rosa",
    "sg:classifiers":[
        {
            "category":"Restaurant",
            "type":"Food & Drink"
        }
    ],
    "sg:phone":"+1 707 569 8163",
    "sg:postcode":"95407",
    "sg:province":"CA",
    "sg:tags":[
        "eating"
    ],
    "wof:name":"Casual Catering",
    "wof:placetype":"venue"
},
  "geometry": {"coordinates":[-122.732634,38.407459],"type":"Point"}
}