{
  "type": "Feature",
  "properties": {
    "addr:full":"3000 E Via Mondo Compton CA 90221",
    "addr:housenumber":"3000",
    "addr:postcode":"90221",
    "addr:street":"E Via Mondo",
    "iso:country":"US",
    "sg:address":"3000 E Via Mondo",
    "sg:city":"Compton",
    "sg:classifiers":[
        {
            "category":"Manufacturing",
            "subcategory":"Rubber & Plastics",
            "type":"Manufacturing & Wholesale Goods"
        }
    ],
    "sg:phone":"+1 310 537 1600",
    "sg:postcode":"90221",
    "sg:province":"CA",
    "sg:tags":[
        "product"
    ],
    "sg:website":"www.scholle.com",
    "wof:name":"Scholle Corp",
    "wof:placetype":"venue"
},
  "geometry": {"coordinates":[-118.210718,33.871914],"type":"Point"}
}