{
  "type": "Feature",
  "properties": {
    "addr:full":"17055 Gale Ave City Of Industry CA 91745",
    "addr:housenumber":"17055",
    "addr:postcode":"91745",
    "addr:street":"Gale Ave",
    "iso:country":"US",
    "sg:address":"17055 Gale Ave",
    "sg:city":"City Of Industry",
    "sg:classifiers":[
        {
            "category":"Manufacturing",
            "subcategory":"Tools & Machinery",
            "type":"Manufacturing & Wholesale Goods"
        }
    ],
    "sg:phone":"+1 626 965 1630",
    "sg:postcode":"91745",
    "sg:province":"CA",
    "sg:tags":[
        "shop",
        "machine",
        "industrial",
        "equipment",
        "mfg"
    ],
    "sg:website":"www.ralee.com",
    "wof:name":"Ralee Engineering Corp",
    "wof:placetype":"venue"
},
  "geometry": {"coordinates":[-117.93625,34.00118],"type":"Point"}
}