{
  "type": "Feature",
  "properties": {
    "addr:full":"1720 E Cesar E Chavez Ave Los Angeles CA 90033",
    "addr:housenumber":"1720",
    "addr:postcode":"90033",
    "addr:street":"E Cesar E Chavez Ave",
    "iso:country":"US",
    "sg:address":"1720 E Cesar E Chavez Ave",
    "sg:city":"Los Angeles",
    "sg:classifiers":[
        {
            "category":"Health Services",
            "subcategory":"Hospital",
            "type":"Services"
        }
    ],
    "sg:phone":"+1 323 268 5000",
    "sg:postcode":"90033",
    "sg:province":"CA",
    "wof:name":"White Memorial Medical Center",
    "wof:placetype":"venue"
},
  "geometry": {"coordinates":[-118.21700300000001,34.050701],"type":"Point"}
}