{
  "type": "Feature",
  "properties": {
    "iso:country":"US",
    "sg:address":"4751 17th St",
    "sg:city":"San Francisco",
    "sg:classifiers":[
        {
            "category":"Manufacturing",
            "subcategory":"Tools & Machinery",
            "type":"Manufacturing & Wholesale Goods"
        }
    ],
    "sg:phone":"+1 415 566 9978",
    "sg:postcode":"94117",
    "sg:province":"CA",
    "sg:tags":[
        "recording",
        "medium",
        "mfg"
    ],
    "wof:name":"Qmr Corp",
    "wof:placetype":"venue"
},
  "geometry": {"coordinates":[-122.448574,37.761612],"type":"Point"}
}