{
  "type": "Feature",
  "properties": {
    "iso:country":"US",
    "sg:address":"6059 Golden West Ave",
    "sg:city":"Temple City",
    "sg:classifiers":[
        {
            "category":"Building & Trades",
            "subcategory":"Construction",
            "type":"Services"
        }
    ],
    "sg:phone":"+1 626 286 0354",
    "sg:postcode":"91780",
    "sg:province":"CA",
    "sg:tags":[
        "painter"
    ],
    "wof:name":"Bemiller Painting",
    "wof:placetype":"venue"
},
  "geometry": {"coordinates":[-118.057138,34.109795],"type":"Point"}
}