{
  "type": "Feature",
  "properties": {
    "addr:full":"8981 Kendall Ave South Gate CA 90280",
    "addr:housenumber":"8981",
    "addr:postcode":"90280",
    "addr:street":"Kendall Ave;Gate",
    "iso:country":"US",
    "sg:address":"8981 Kendall Ave",
    "sg:city":"South Gate",
    "sg:classifiers":[
        {
            "category":"Personal",
            "type":"Services"
        }
    ],
    "sg:phone":"+1 323 563 3264",
    "sg:postcode":"90280",
    "sg:province":"CA",
    "sg:tags":[
        "mover"
    ],
    "wof:name":"Gil Moving & Storage",
    "wof:placetype":"venue"
},
  "geometry": {"coordinates":[-118.18000000000001,33.950401],"type":"Point"}
}