{
  "type": "Feature",
  "properties": {
    "addr:full":"6145 El Cajon Blvd #L San Diego CA 92115",
    "addr:housenumber":"6145",
    "addr:postcode":"92115",
    "addr:street":"El Cajon Blvd # L",
    "iso:country":"US",
    "sg:address":"6145 El Cajon Blvd #L",
    "sg:city":"San Diego",
    "sg:classifiers":[
        {
            "category":"Retail",
            "subcategory":"Laundry & Dry Cleaning",
            "type":"Services"
        }
    ],
    "sg:phone":"+1 619 287 3467",
    "sg:postcode":"92115",
    "sg:province":"CA",
    "wof:name":"Campus Plaza Coin Laundry",
    "wof:placetype":"venue"
},
  "geometry": {"coordinates":[-117.065872,32.76084],"type":"Point"}
}