{
  "type": "Feature",
  "properties": {
    "addr:full":"4020 W Magnolia Blvd Burbank CA 91505",
    "addr:housenumber":"4020",
    "addr:postcode":"91505",
    "addr:street":"W Magnolia Blvd",
    "iso:country":"US",
    "sg:address":"4020 W Magnolia Blvd",
    "sg:city":"Burbank",
    "sg:classifiers":[
        {
            "category":"Professional",
            "type":"Services"
        }
    ],
    "sg:phone":"+1 818 558 1144",
    "sg:postcode":"91505",
    "sg:province":"CA",
    "sg:tags":[
        "establishment"
    ],
    "wof:name":"Soundzone",
    "wof:placetype":"venue"
},
  "geometry": {"coordinates":[-118.350818,34.166513],"type":"Point"}
}