{
  "type": "Feature",
  "properties": {
    "iso:country":"US",
    "sg:address":"4772 Katella Ave",
    "sg:city":"Los Alamitos",
    "sg:classifiers":[
        {
            "category":"Wholesale",
            "subcategory":"Electrical",
            "type":"Manufacturing & Wholesale Goods"
        }
    ],
    "sg:phone":"+1 562 799 9909",
    "sg:postcode":"90720",
    "sg:province":"CA",
    "sg:tags":[
        "electronic"
    ],
    "wof:name":"R D H Associates",
    "wof:placetype":"venue"
},
  "geometry": {"coordinates":[-118.049219,33.803074],"type":"Point"}
}