{
  "type": "Feature",
  "properties": {
    "addr:full":"8109 S Denker Ave Los Angeles CA 90047",
    "addr:housenumber":"8109",
    "addr:postcode":"90047",
    "addr:street":"S Denker Ave",
    "iso:country":"US",
    "sg:address":"8109 S Denker Ave",
    "sg:city":"Los Angeles",
    "sg:classifiers":[
        {
            "category":"Wholesale",
            "subcategory":"Plants",
            "type":"Manufacturing & Wholesale Goods"
        }
    ],
    "sg:phone":"+1 323 541 0388",
    "sg:postcode":"90047",
    "sg:province":"CA",
    "sg:tags":[
        "supply"
    ],
    "wof:name":"Odell Flower Shop",
    "wof:placetype":"venue"
},
  "geometry": {"coordinates":[-118.304715,33.964654],"type":"Point"}
}