{
  "type": "Feature",
  "properties": {
    "addr:full":"6622 Freeport Blvd Sacramento CA 95822",
    "addr:housenumber":"6622",
    "addr:postcode":"95822",
    "addr:street":"Freeport Blvd",
    "iso:country":"US",
    "sg:address":"6622 Freeport Blvd",
    "sg:city":"Sacramento",
    "sg:classifiers":[
        {
            "category":"Building & Trades",
            "subcategory":"Landscaping Services",
            "type":"Services"
        }
    ],
    "sg:phone":"+1 916 427 7210",
    "sg:postcode":"95822",
    "sg:province":"CA",
    "wof:name":"Home Landscape And Nursery Co",
    "wof:placetype":"venue"
},
  "geometry": {"coordinates":[-121.504576,38.506588],"type":"Point"}
}