{
  "type": "Feature",
  "properties": {
    "iso:country":"US",
    "sg:address":"1819 S Catalina Ave",
    "sg:city":"Redondo Beach",
    "sg:classifiers":[
        {
            "category":"Restaurant",
            "type":"Food & Drink"
        }
    ],
    "sg:phone":"+1 310 373 6397",
    "sg:postcode":"90277",
    "sg:province":"CA",
    "wof:name":"Pedone Pizza",
    "wof:placetype":"venue"
},
  "geometry": {"coordinates":[-118.387173,33.816375],"type":"Point"}
}