{
  "type": "Feature",
  "properties": {
    "addr:full":"2761 Patterson Rd Riverbank CA 95367",
    "addr:housenumber":"2761",
    "addr:postcode":"95367",
    "addr:street":"Patterson Rd",
    "iso:country":"US",
    "sg:address":"2761 Patterson Rd",
    "sg:city":"Riverbank",
    "sg:classifiers":[
        {
            "category":"Restaurant",
            "type":"Food & Drink"
        }
    ],
    "sg:menulink":"http://www.allmenus.com/ca/modesto/150259-subway/menu/",
    "sg:phone":"+1 209 869 1883",
    "sg:postcode":"95367",
    "sg:province":"CA",
    "sg:tags":[
        "american",
        "sandwich"
    ],
    "wof:name":"Subway",
    "wof:placetype":"venue"
},
  "geometry": {"coordinates":[-120.946089,37.733134],"type":"Point"}
}