{
  "type": "Feature",
  "properties": {
    "iso:country":"US",
    "sg:address":"207 Palm Street",
    "sg:city":"Newport Beach",
    "sg:classifiers":[
        {
            "category":"Sports & Exercise",
            "subcategory":"Bicycle Rental",
            "type":"Entertainment"
        }
    ],
    "sg:phone":"+1 949 675 2999",
    "sg:postcode":"92661",
    "sg:province":"CA",
    "sg:tags":[
        "bike"
    ],
    "wof:name":"Balboa Beach Rentals",
    "wof:placetype":"venue"
},
  "geometry": {"coordinates":[-117.90114800000001,33.602618],"type":"Point"}
}