{
  "type": "Feature",
  "properties": {
    "addr:full":"9995 Carmel Mountain Rd San Diego CA 92129",
    "addr:housenumber":"9995",
    "addr:postcode":"92129",
    "addr:street":"Carmel Mountain Rd",
    "iso:country":"US",
    "sg:address":"9995 Carmel Mountain Rd",
    "sg:city":"San Diego",
    "sg:classifiers":[
        {
            "category":"Recreation",
            "type":"Entertainment"
        }
    ],
    "sg:phone":"+1 858 484 8808",
    "sg:postcode":"92129",
    "sg:province":"CA",
    "sg:tags":[
        "martial",
        "arts",
        "instruction"
    ],
    "wof:name":"Champion Taekwondo Academy",
    "wof:placetype":"venue"
},
  "geometry": {"coordinates":[-117.113311,32.960715],"type":"Point"}
}