{
  "type": "Feature",
  "properties": {
    "iso:country":"US",
    "sg:address":"1316 El Paseo De Saratoga",
    "sg:city":"San Jose",
    "sg:classifiers":[
        {
            "category":"Shopping",
            "subcategory":"Mobile Phones",
            "type":"Retail Goods"
        }
    ],
    "sg:phone":"+1 408 341 1540",
    "sg:postcode":"95130",
    "sg:province":"CA",
    "wof:name":"At & T",
    "wof:placetype":"venue"
},
  "geometry": {"coordinates":[-121.98200199999999,37.290001],"type":"Point"}
}