{
  "type": "Feature",
  "properties": {
    "iso:country":"US",
    "sg:address":"1344 E Thousand Oaks Blvd",
    "sg:city":"Thousand Oaks",
    "sg:classifiers":[
        {
            "category":"Retail",
            "subcategory":"Repair Shop",
            "type":"Services"
        },
        {
            "category":"Retail",
            "subcategory":"Auto Repair",
            "type":"Services"
        }
    ],
    "sg:phone":"+1 805 495 8185",
    "sg:postcode":"91362",
    "sg:province":"CA",
    "sg:tags":[
        "wrecker",
        "welding"
    ],
    "wof:name":"Thousand Oaks Welding",
    "wof:placetype":"venue"
},
  "geometry": {"coordinates":[-118.855683,34.17803],"type":"Point"}
}