{
  "type": "Feature",
  "properties": {
    "addr:full":"8600 Tujunga Ave Sun Valley CA 91352",
    "addr:housenumber":"8600",
    "addr:postcode":"91352",
    "addr:street":"Tujunga Ave",
    "iso:country":"US",
    "sg:address":"8600 Tujunga Ave",
    "sg:city":"Sun Valley",
    "sg:classifiers":[
        {
            "category":"Manufacturing",
            "subcategory":"Rubber & Plastics",
            "type":"Manufacturing & Wholesale Goods"
        }
    ],
    "sg:phone":"+1 818 768 4636",
    "sg:postcode":"91352",
    "sg:province":"CA",
    "sg:tags":[
        "product"
    ],
    "wof:name":"Joe's Tooling",
    "wof:placetype":"venue"
},
  "geometry": {"coordinates":[-118.380808,34.226155],"type":"Point"}
}