{
  "type": "Feature",
  "properties": {
    "iso:country":"US",
    "sg:address":"1460 Broadway Ave",
    "sg:city":"Atwater",
    "sg:classifiers":[
        {
            "category":"Shopping",
            "subcategory":"Department Store",
            "type":"Retail Goods"
        }
    ],
    "sg:phone":"+1 209 358 6727",
    "sg:postcode":"95301",
    "sg:province":"CA",
    "sg:tags":[
        "variety"
    ],
    "wof:name":"Ninety Nine Cent Plus",
    "wof:placetype":"venue"
},
  "geometry": {"coordinates":[-120.61136399999999,37.347742],"type":"Point"}
}