{
  "type": "Feature",
  "properties": {
    "addr:full":"2170 Paragon Dr San Jose CA 95131",
    "addr:housenumber":"2170",
    "addr:postcode":"95131",
    "addr:street":"Paragon Dr",
    "iso:country":"US",
    "sg:address":"2170 Paragon Dr",
    "sg:city":"San Jose",
    "sg:classifiers":[
        {
            "category":"Building & Trades",
            "subcategory":"Landscaping Services",
            "type":"Services"
        }
    ],
    "sg:phone":"+1 408 467 9453",
    "sg:postcode":"95131",
    "sg:province":"CA",
    "sg:tags":[
        "gardener"
    ],
    "sg:website":"www.ambius.com",
    "wof:name":"Ambius",
    "wof:placetype":"venue"
},
  "geometry": {"coordinates":[-121.908463,37.387409],"type":"Point"}
}