{
  "type": "Feature",
  "properties": {
    "addr:full":"801 N. Brand Boulevard Glendale CA 91203",
    "addr:housenumber":"801",
    "addr:postcode":"91203",
    "addr:street":"N. Brand Boulevard",
    "iso:country":"US",
    "sg:address":"801 N. Brand Boulevard",
    "sg:city":"Glendale",
    "sg:classifiers":[
        {
            "category":"Real Estate",
            "subcategory":"Real Estate Services",
            "type":"Services"
        }
    ],
    "sg:phone":"+1 818 334 1886",
    "sg:postcode":"91203",
    "sg:province":"CA",
    "sg:website":"www.cbcnco.com",
    "wof:name":"Coldwell Banker Commercial",
    "wof:placetype":"venue"
},
  "geometry": {"coordinates":[-118.255709,34.157823],"type":"Point"}
}