{
  "type": "Feature",
  "properties": {
    "iso:country":"US",
    "sg:address":"15089 Roxford Pl",
    "sg:city":"Sylmar",
    "sg:classifiers":[
        {
            "category":"Organizations",
            "subcategory":"Religious Organization",
            "type":"Services"
        }
    ],
    "sg:phone":"+1 818 367 2077",
    "sg:postcode":"91342",
    "sg:province":"CA",
    "sg:tags":[
        "church"
    ],
    "wof:name":"Valley Korean Community Chr",
    "wof:placetype":"venue"
},
  "geometry": {"coordinates":[-118.460089,34.321699],"type":"Point"}
}