{
  "type": "Feature",
  "properties": {
    "iso:country":"US",
    "sg:address":"215 S Coast Hwy Ste 205",
    "sg:city":"Oceanside",
    "sg:classifiers":[
        {
            "category":"Communications",
            "subcategory":"Newspaper",
            "type":"Services"
        },
        {
            "category":"Professional",
            "subcategory":"Lawyer & Legal Services",
            "type":"Services"
        }
    ],
    "sg:phone":"+1 760 757 3356",
    "sg:postcode":"92054",
    "sg:province":"CA",
    "sg:tags":[
        "print",
        "medium"
    ],
    "wof:name":"Wallenius-Margolis Rena Atty",
    "wof:placetype":"venue"
},
  "geometry": {"coordinates":[-117.36199999999999,33.210701],"type":"Point"}
}