{
  "type": "Feature",
  "properties": {
    "addr:full":"987 N San Antonio Rd Los Altos CA 94022",
    "addr:housenumber":"987",
    "addr:postcode":"94022",
    "addr:street":"N San Antonio Rd",
    "iso:country":"US",
    "sg:address":"987 N San Antonio Rd",
    "sg:city":"Los Altos",
    "sg:classifiers":[
        {
            "category":"Cafe",
            "type":"Food & Drink"
        }
    ],
    "sg:menulink":"http://www.allmenus.com/ca/san-jose/50739-second-cup-cafe/menu/",
    "sg:phone":"+1 650 948 1670",
    "sg:postcode":"94022",
    "sg:province":"CA",
    "sg:tags":[
        "american",
        "diner"
    ],
    "wof:name":"Second Cup Cafe",
    "wof:placetype":"venue"
},
  "geometry": {"coordinates":[-122.114227,37.399931],"type":"Point"}
}