{
  "type": "Feature",
  "properties": {
    "addr:full":"2 Flores Irvine CA 92612",
    "addr:housenumber":"2",
    "addr:postcode":"92612",
    "addr:street":"Flores",
    "iso:country":"US",
    "sg:address":"2 Flores",
    "sg:city":"Irvine",
    "sg:classifiers":[
        {
            "category":"Professional",
            "type":"Services"
        }
    ],
    "sg:phone":"+1 949 509 1700",
    "sg:postcode":"92612",
    "sg:province":"CA",
    "wof:name":"Lapin Company",
    "wof:placetype":"venue"
},
  "geometry": {"coordinates":[-117.835847,33.659663],"type":"Point"}
}