{
  "type": "Feature",
  "properties": {
    "addr:full":"542 Lisbon St Daly City CA 94014",
    "addr:housenumber":"542",
    "addr:postcode":"94014",
    "addr:street":"Lisbon St",
    "iso:country":"US",
    "sg:address":"542 Lisbon St",
    "sg:city":"Daly City",
    "sg:classifiers":[
        {
            "category":"Organizations",
            "subcategory":"Religious Organization",
            "type":"Services"
        }
    ],
    "sg:phone":"+1 650 992 0680",
    "sg:postcode":"94014",
    "sg:province":"CA",
    "sg:tags":[
        "church"
    ],
    "wof:name":"First Baptist Church Daly City",
    "wof:placetype":"venue"
},
  "geometry": {"coordinates":[-122.460452,37.689168],"type":"Point"}
}