{
  "type": "Feature",
  "properties": {
    "addr:full":"1634 Oakland Rd San Jose CA 95131",
    "addr:housenumber":"1634",
    "addr:postcode":"95131",
    "addr:street":"Oakland Rd",
    "iso:country":"US",
    "sg:address":"1634 Oakland Rd",
    "sg:city":"San Jose",
    "sg:classifiers":[
        {
            "category":"Real Estate",
            "subcategory":"Real Estate Agent",
            "type":"Services"
        }
    ],
    "sg:phone":"+1 408 451 5990",
    "sg:postcode":"95131",
    "sg:province":"CA",
    "wof:name":"Greenbay Realty Group LLC",
    "wof:placetype":"venue"
},
  "geometry": {"coordinates":[-121.895546,37.378629],"type":"Point"}
}