{
  "type": "Feature",
  "properties": {
    "addr:full":"6740 Reseda Blvd Reseda CA 91335",
    "addr:postcode":"6740;91335",
    "addr:street":"Reseda Blvd",
    "iso:country":"US",
    "sg:address":"6740 Reseda Blvd",
    "sg:city":"Reseda",
    "sg:classifiers":[
        {
            "category":"Restaurant",
            "type":"Food & Drink"
        }
    ],
    "sg:menulink":"http://www.allmenus.com/ca/san-fernando-valley/73923-dominos-pizza/menu/",
    "sg:phone":"+1 818 996 7996",
    "sg:postcode":"91335",
    "sg:province":"CA",
    "sg:tags":[
        "american",
        "wing",
        "pizza"
    ],
    "wof:name":"Domino's Pizza",
    "wof:placetype":"venue"
},
  "geometry": {"coordinates":[-118.535613,34.193478],"type":"Point"}
}