{
  "type": "Feature",
  "properties": {
    "iso:country":"US",
    "sg:address":"1711 Mossbrook Ave",
    "sg:city":"San Jose",
    "sg:classifiers":[
        {
            "category":"Building & Trades",
            "subcategory":"Cleaning & Sanitation",
            "type":"Services"
        }
    ],
    "sg:phone":"+1 408 374 5251",
    "sg:postcode":"95130",
    "sg:province":"CA",
    "sg:tags":[
        "house"
    ],
    "wof:name":"Markey's Maintenance",
    "wof:placetype":"venue"
},
  "geometry": {"coordinates":[-121.983093,37.290439],"type":"Point"}
}