{
  "type": "Feature",
  "properties": {
    "addr:full":"13735 Victory Blvd Van Nuys CA 91401",
    "addr:housenumber":"13735",
    "addr:postcode":"91401",
    "addr:street":"Victory Blvd",
    "iso:country":"US",
    "sg:address":"13735 Victory Blvd",
    "sg:city":"Van Nuys",
    "sg:classifiers":[
        {
            "category":"Banks & Credit Unions",
            "subcategory":"Bank",
            "type":"Services"
        }
    ],
    "sg:phone":"+1 818 997 6191",
    "sg:postcode":"91401",
    "sg:province":"CA",
    "sg:tags":[
        "cashing",
        "check"
    ],
    "wof:name":"V & Z Check Cashing",
    "wof:placetype":"venue"
},
  "geometry": {"coordinates":[-118.43124899999999,34.186667],"type":"Point"}
}