{
  "type": "Feature",
  "properties": {
    "iso:country":"US",
    "sg:address":"2640 Greenwich St",
    "sg:city":"San Francisco",
    "sg:classifiers":[
        {
            "category":"Recreation",
            "type":"Entertainment"
        }
    ],
    "sg:phone":"+1 415 921 1192",
    "sg:postcode":"94123",
    "sg:province":"CA",
    "sg:tags":[
        "astrologer"
    ],
    "wof:name":"Astro-Psychology Institute",
    "wof:placetype":"venue"
},
  "geometry": {"coordinates":[-122.443611,37.79806],"type":"Point"}
}