{
  "type": "Feature",
  "properties": {
    "iso:country":"US",
    "sg:address":"20983 Foothill Blvd",
    "sg:city":"Hayward",
    "sg:classifiers":[
        {
            "category":"Wholesale",
            "subcategory":"Non-durable Goods",
            "type":"Manufacturing & Wholesale Goods"
        },
        {
            "category":"Personal",
            "subcategory":"Beauty Salon",
            "type":"Services"
        }
    ],
    "sg:phone":"+1 510 940 2901",
    "sg:postcode":"94541",
    "sg:province":"CA",
    "sg:tags":[
        "supplies-wholesale",
        "salons-equipment",
        "manufacturer"
    ],
    "wof:name":"Thee Elegant Palace",
    "wof:placetype":"venue"
},
  "geometry": {"coordinates":[-122.094759,37.686906],"type":"Point"}
}