{
  "type": "Feature",
  "properties": {
    "iso:country":"US",
    "sg:address":"4811 Woodwind Way",
    "sg:city":"Anaheim",
    "sg:classifiers":[
        {
            "category":"Farming",
            "subcategory":"Farm",
            "type":"Manufacturing & Wholesale Goods"
        }
    ],
    "sg:phone":"+1 714 779 6656",
    "sg:postcode":"92807",
    "sg:province":"CA",
    "sg:tags":[
        "crop",
        "general"
    ],
    "wof:name":"Woodwind Farms",
    "wof:placetype":"venue"
},
  "geometry": {"coordinates":[-117.811104,33.867317],"type":"Point"}
}