{
  "type": "Feature",
  "properties": {
    "iso:country":"US",
    "sg:address":"13716 Ruette Le Parc",
    "sg:city":"Del Mar",
    "sg:classifiers":[
        {
            "category":"Professional",
            "subcategory":"Business Services",
            "type":"Services"
        }
    ],
    "sg:phone":"+1 858 350 0006",
    "sg:postcode":"92014",
    "sg:province":"CA",
    "sg:tags":[
        "interior",
        "consultant",
        "design",
        "decorator"
    ],
    "wof:name":"South Coast Interior",
    "wof:placetype":"venue"
},
  "geometry": {"coordinates":[-117.24531500000001,32.947842],"type":"Point"}
}