{
  "type": "Feature",
  "properties": {
    "addr:full":"6325 Marindustry Dr San Diego CA 92121",
    "addr:housenumber":"6325",
    "addr:postcode":"92121",
    "addr:street":"Marindustry Dr",
    "iso:country":"US",
    "sg:address":"6325 Marindustry Dr",
    "sg:city":"San Diego",
    "sg:classifiers":[
        {
            "category":"Manufacturing",
            "subcategory":"Printing",
            "type":"Manufacturing & Wholesale Goods"
        }
    ],
    "sg:phone":"+1 858 455 7102",
    "sg:postcode":"92121",
    "sg:province":"CA",
    "sg:tags":[
        "lithographic",
        "commercial"
    ],
    "wof:name":"Trade Color Graphics",
    "wof:placetype":"venue"
},
  "geometry": {"coordinates":[-117.177301,32.880046],"type":"Point"}
}