{
  "type": "Feature",
  "properties": {
    "iso:country":"US",
    "sg:address":"1614 Industrial Ave",
    "sg:city":"Norco",
    "sg:classifiers":[
        {
            "category":"Retail",
            "subcategory":"Repair Shop",
            "type":"Services"
        }
    ],
    "sg:phone":"+1 951 737 2195",
    "sg:postcode":"92860",
    "sg:province":"CA",
    "sg:tags":[
        "repairing",
        "saw"
    ],
    "wof:name":"Southern Counties Saw",
    "wof:placetype":"venue"
},
  "geometry": {"coordinates":[-117.563704,33.906385],"type":"Point"}
}