{
  "type": "Feature",
  "properties": {
    "iso:country":"US",
    "sg:address":"17853 Santiago Blvd Ste 107",
    "sg:city":"Villa Park",
    "sg:classifiers":[
        {
            "category":"Arts & Performance",
            "subcategory":"Arts Center",
            "type":"Entertainment"
        }
    ],
    "sg:phone":"+1 714 771 2499",
    "sg:postcode":"92861",
    "sg:province":"CA",
    "sg:tags":[
        "performing"
    ],
    "wof:name":"Imagination Machine The",
    "wof:placetype":"venue"
},
  "geometry": {"coordinates":[-117.82052299999999,33.814096],"type":"Point"}
}