{
  "type": "Feature",
  "properties": {
    "iso:country":"US",
    "sg:address":"1500 Quail St Ste 120",
    "sg:city":"Newport Beach",
    "sg:classifiers":[
        {
            "category":"Home & Garden",
            "subcategory":"Carpets & Floor Coverings",
            "type":"Retail Goods"
        }
    ],
    "sg:phone":"+1 949 250 1993",
    "sg:postcode":"92660",
    "sg:province":"CA",
    "sg:tags":[
        "flooring"
    ],
    "wof:name":"Jps Surface and Solutions",
    "wof:placetype":"venue"
},
  "geometry": {"coordinates":[-117.86799600000001,33.660801],"type":"Point"}
}