{
  "type": "Feature",
  "properties": {
    "iso:country":"US",
    "sg:address":"5885 Rickenbacker Rd",
    "sg:city":"Los Angeles",
    "sg:classifiers":[
        {
            "category":"Wholesale",
            "subcategory":"Apparel",
            "type":"Manufacturing & Wholesale Goods"
        }
    ],
    "sg:phone":"+1 323 887 1610",
    "sg:postcode":"90040",
    "sg:province":"CA",
    "sg:tags":[
        "textile"
    ],
    "wof:name":"C & L Textiles",
    "wof:placetype":"venue"
},
  "geometry": {"coordinates":[-118.158979,33.989519],"type":"Point"}
}