{
  "type": "Feature",
  "properties": {
    "iso:country":"US",
    "sg:address":"5058 Valley Blvd",
    "sg:city":"Los Angeles",
    "sg:classifiers":[
        {
            "category":"Autos & Motor Vehicles",
            "subcategory":"Auto Supplies",
            "type":"Retail Goods"
        }
    ],
    "sg:phone":"+1 323 222 2513",
    "sg:postcode":"90032",
    "sg:province":"CA",
    "sg:tags":[
        "tire"
    ],
    "wof:name":"Canos Tires",
    "wof:placetype":"venue"
},
  "geometry": {"coordinates":[-118.173683,34.056135],"type":"Point"}
}