{
  "type": "Feature",
  "properties": {
    "iso:country":"US",
    "sg:address":"107 W Pacheco Blvd",
    "sg:city":"Los Banos",
    "sg:classifiers":[
        {
            "category":"Restaurant",
            "type":"Food & Drink"
        }
    ],
    "sg:phone":"+1 209 826 1548",
    "sg:postcode":"93635",
    "sg:province":"CA",
    "wof:name":"Iris Taqueriea",
    "wof:placetype":"venue"
},
  "geometry": {"coordinates":[-120.855886,37.056804],"type":"Point"}
}