{
  "type": "Feature",
  "properties": {
    "addr:full":"1100 Quail St Newport Beach CA 92660",
    "addr:housenumber":"1100",
    "addr:postcode":"92660",
    "addr:street":"Quail St",
    "iso:country":"US",
    "sg:address":"1100 Quail St",
    "sg:city":"Newport Beach",
    "sg:classifiers":[
        {
            "category":"Banks & Credit Unions",
            "subcategory":"Investment Brokerage",
            "type":"Services"
        }
    ],
    "sg:phone":"+1 949 250 4254",
    "sg:postcode":"92660",
    "sg:province":"CA",
    "sg:tags":[
        "stock",
        "bond"
    ],
    "wof:name":"Gavel Capital Group",
    "wof:placetype":"venue"
},
  "geometry": {"coordinates":[-117.867085,33.659974],"type":"Point"}
}