{
  "type": "Feature",
  "properties": {
    "iso:country":"US",
    "sg:address":"2964 Arf Ave Ste 7",
    "sg:city":"Hayward",
    "sg:classifiers":[
        {
            "category":"Retail",
            "subcategory":"Auto Repair",
            "type":"Services"
        }
    ],
    "sg:phone":"+1 510 783 0500",
    "sg:postcode":"94545",
    "sg:province":"CA",
    "sg:tags":[
        "body",
        "shop"
    ],
    "sg:website":"www.gilbertsbodyandpaint.com",
    "wof:name":"Gilbert's Body & Paint",
    "wof:placetype":"venue"
},
  "geometry": {"coordinates":[-122.101997,37.6222],"type":"Point"}
}