{
  "type": "Feature",
  "properties": {
    "iso:country":"US",
    "sg:address":"277 Higuera St",
    "sg:city":"San Luis Obispo",
    "sg:classifiers":[
        {
            "category":"Wholesale",
            "subcategory":"Groceries",
            "type":"Manufacturing & Wholesale Goods"
        }
    ],
    "sg:phone":"+1 805 543 5341",
    "sg:postcode":"93401",
    "sg:province":"CA",
    "sg:tags":[
        "grocer"
    ],
    "sg:website":"www.smartandfinal.com",
    "wof:name":"Smart & Final",
    "wof:placetype":"venue"
},
  "geometry": {"coordinates":[-120.670204,35.269589],"type":"Point"}
}