{
  "type": "Feature",
  "properties": {
    "addr:full":"2026 University Ave Berkeley CA 94704",
    "addr:housenumber":"2026",
    "addr:postcode":"94704",
    "addr:street":"University Ave",
    "iso:country":"US",
    "sg:address":"2026 University Ave",
    "sg:city":"Berkeley",
    "sg:phone":"+1 510 841 0884",
    "sg:postcode":"94704",
    "sg:province":"CA",
    "wof:name":"Jayakarta Restaurant",
    "wof:placetype":"venue"
},
  "geometry": {"coordinates":[-122.270078,37.871938],"type":"Point"}
}