{
  "type": "Feature",
  "properties": {
    "addr:full":"18682 Beach Blvd Huntington Beach CA 92648",
    "addr:housenumber":"18682",
    "addr:postcode":"92648",
    "addr:street":"Beach Blvd",
    "iso:country":"US",
    "sg:address":"18682 Beach Blvd",
    "sg:city":"Huntington Beach",
    "sg:classifiers":[
        {
            "category":"Shopping",
            "subcategory":"Pharmacy",
            "type":"Retail Goods"
        }
    ],
    "sg:phone":"+1 949 678 6699",
    "sg:postcode":"92648",
    "sg:province":"CA",
    "wof:name":"Pacifica Pharmancy",
    "wof:placetype":"venue"
},
  "geometry": {"coordinates":[-117.98866,33.693098],"type":"Point"}
}