{
  "type": "Feature",
  "properties": {
    "iso:country":"US",
    "sg:address":"3008 McHenry Ave",
    "sg:city":"Modesto",
    "sg:classifiers":[
        {
            "category":"Restaurant",
            "type":"Food & Drink"
        }
    ],
    "sg:phone":"+1 209 527 3450",
    "sg:postcode":"95350",
    "sg:province":"CA",
    "wof:name":"Fisherman's Galley",
    "wof:placetype":"venue"
},
  "geometry": {"coordinates":[-120.994138,37.683846],"type":"Point"}
}