{
  "type": "Feature",
  "properties": {
    "addr:full":"218 Marine Ave Newport Beach CA 92662",
    "addr:housenumber":"218",
    "addr:postcode":"92662",
    "addr:street":"Marine Ave",
    "iso:country":"US",
    "sg:address":"218 Marine Ave",
    "sg:city":"Newport Beach",
    "sg:classifiers":[
        {
            "category":"Real Estate",
            "subcategory":"Real Estate Agent",
            "type":"Services"
        }
    ],
    "sg:phone":"+1 949 673 6511",
    "sg:postcode":"92662",
    "sg:province":"CA",
    "wof:name":"Beach Time Realty",
    "wof:placetype":"venue"
},
  "geometry": {"coordinates":[-117.889713,33.606744],"type":"Point"}
}