{
  "type": "Feature",
  "properties": {
    "addr:full":"1300 N Bristol St Newport Beach CA 92660",
    "addr:housenumber":"1300",
    "addr:postcode":"92660",
    "addr:street":"N Bristol St",
    "iso:country":"US",
    "sg:address":"1300 N Bristol St",
    "sg:city":"Newport Beach",
    "sg:classifiers":[
        {
            "category":"Manufacturing",
            "subcategory":"Printing",
            "type":"Manufacturing & Wholesale Goods"
        }
    ],
    "sg:phone":"+1 949 752 2585",
    "sg:postcode":"92660",
    "sg:province":"CA",
    "sg:tags":[
        "printer"
    ],
    "wof:name":"First Continental Printing",
    "wof:placetype":"venue"
},
  "geometry": {"coordinates":[-117.86806199999999,33.658346],"type":"Point"}
}