{
  "type": "Feature",
  "properties": {
    "iso:country":"US",
    "sg:address":"2110 Oak St",
    "sg:city":"Concord",
    "sg:classifiers":[
        {
            "category":"Real Estate",
            "subcategory":"Real Estate Agent",
            "type":"Services"
        }
    ],
    "sg:phone":"+1 925 284 7200",
    "sg:postcode":"94520",
    "sg:province":"CA",
    "sg:tags":[
        "management"
    ],
    "sg:website":"www.tenantfinders.com",
    "wof:name":"Tenant Finders",
    "wof:placetype":"venue"
},
  "geometry": {"coordinates":[-122.03026,37.97341],"type":"Point"}
}