{
  "type": "Feature",
  "properties": {
    "addr:full":"110 E 9th St Ste A905 Los Angeles CA 90079",
    "addr:housenumber":"110",
    "addr:postcode":"90079",
    "addr:street":"E 9Th St Ste A905",
    "iso:country":"US",
    "sg:address":"110 E 9th St Ste A905",
    "sg:city":"Los Angeles",
    "sg:classifiers":[
        {
            "category":"Shopping",
            "subcategory":"Jewelry",
            "type":"Retail Goods"
        }
    ],
    "sg:phone":"+1 213 623 7640",
    "sg:postcode":"90079",
    "sg:province":"CA",
    "sg:tags":[
        "watch"
    ],
    "sg:website":"www.swisswatchinc.com",
    "wof:name":"Swiss Watch Inc",
    "wof:placetype":"venue"
},
  "geometry": {"coordinates":[-118.255388,34.040588],"type":"Point"}
}