{
  "type": "Feature",
  "properties": {
    "addr:full":"1243 N Grand Ave Walnut CA 91789",
    "addr:housenumber":"1243",
    "addr:postcode":"91789",
    "addr:street":"N Grand Ave",
    "iso:country":"US",
    "sg:address":"1243 N Grand Ave",
    "sg:city":"Walnut",
    "sg:classifiers":[
        {
            "category":"Utilities",
            "subcategory":"Mobile Phone",
            "type":"Services"
        }
    ],
    "sg:phone":"+1 909 468 1880",
    "sg:postcode":"91789",
    "sg:province":"CA",
    "sg:tags":[
        "telephone",
        "cellular"
    ],
    "wof:name":"Pcs Hq Inc",
    "wof:placetype":"venue"
},
  "geometry": {"coordinates":[-117.84836,34.043805],"type":"Point"}
}