{
  "type": "Feature",
  "properties": {
    "addr:full":"2799 Middlefield Rd Palo Alto CA 94306",
    "addr:housenumber":"2799",
    "addr:postcode":"94306",
    "addr:street":"Middlefield Rd",
    "iso:country":"US",
    "sg:address":"2799 Middlefield Rd",
    "sg:city":"Palo Alto",
    "sg:classifiers":[
        {
            "category":"Professional",
            "subcategory":"Business Services",
            "type":"Services"
        }
    ],
    "sg:phone":"+1 650 322 2188",
    "sg:postcode":"94306",
    "sg:province":"CA",
    "wof:name":"Cmp Group Inc",
    "wof:placetype":"venue"
},
  "geometry": {"coordinates":[-122.12752999999999,37.432387],"type":"Point"}
}