{
  "type": "Feature",
  "properties": {
    "addr:full":"1 Deer Ct Sacramento CA 95823",
    "addr:housenumber":"1",
    "addr:postcode":"95823",
    "addr:street":"Deer Ct",
    "iso:country":"US",
    "sg:address":"1 Deer Ct",
    "sg:city":"Sacramento",
    "sg:classifiers":[
        {
            "category":"Freight",
            "type":"Transportation"
        }
    ],
    "sg:phone":"+1 916 422 7937",
    "sg:postcode":"95823",
    "sg:province":"CA",
    "sg:tags":[
        "courier"
    ],
    "wof:name":"Garfield's Specialized Carrier",
    "wof:placetype":"venue"
},
  "geometry": {"coordinates":[-121.453682,38.47399],"type":"Point"}
}