{
  "type": "Feature",
  "properties": {
    "iso:country":"US",
    "sg:address":"2700 W Magnolia Blvd",
    "sg:city":"Burbank",
    "sg:classifiers":[
        {
            "category":"Professional",
            "subcategory":"Business Services",
            "type":"Services"
        }
    ],
    "sg:phone":"+1 818 846 4640",
    "sg:postcode":"91506",
    "sg:province":"CA",
    "sg:tags":[
        "recording",
        "studio"
    ],
    "wof:name":"Monkeyland Audio NTR",
    "wof:placetype":"venue"
},
  "geometry": {"coordinates":[-118.33785,34.170908],"type":"Point"}
}