{
  "type": "Feature",
  "properties": {
    "iso:country":"US",
    "sg:address":"123 Lakewood Center Mall",
    "sg:city":"Lakewood",
    "sg:classifiers":[
        {
            "category":"Shopping",
            "subcategory":"Music",
            "type":"Retail Goods"
        }
    ],
    "sg:phone":"+1 562 531 3411",
    "sg:postcode":"90712",
    "sg:province":"CA",
    "sg:tags":[
        "compact",
        "record",
        "disc",
        "tape"
    ],
    "sg:website":"www.samgoody.com",
    "wof:name":"Sam Goody",
    "wof:placetype":"venue"
},
  "geometry": {"coordinates":[-118.140575,33.850013],"type":"Point"}
}