{
  "type": "Feature",
  "properties": {
    "iso:country":"US",
    "sg:address":"1762 Robertson Blvd",
    "sg:city":"Chowchilla",
    "sg:classifiers":[
        {
            "category":"Personal",
            "subcategory":"Nail Salon",
            "type":"Services"
        }
    ],
    "sg:phone":"+1 559 665 3830",
    "sg:postcode":"93610",
    "sg:province":"CA",
    "wof:name":"All About Nails",
    "wof:placetype":"venue"
},
  "geometry": {"coordinates":[-120.274266,37.110578],"type":"Point"}
}