{
  "type": "Feature",
  "properties": {
    "iso:country":"US",
    "sg:address":"1212 S Greenwood Ave",
    "sg:city":"Montebello",
    "sg:classifiers":[
        {
            "category":"Restaurant",
            "type":"Food & Drink"
        }
    ],
    "sg:phone":"+1 323 888 9099",
    "sg:postcode":"90640",
    "sg:province":"CA",
    "sg:tags":[
        "chinese"
    ],
    "wof:name":"Greenwood Chinese Food",
    "wof:placetype":"venue"
},
  "geometry": {"coordinates":[-118.12200199999999,33.9902],"type":"Point"}
}