{
  "type": "Feature",
  "properties": {
    "addr:full":"2320 Florin Rd Sacramento CA 95822",
    "addr:housenumber":"2320",
    "addr:postcode":"95822",
    "addr:street":"Florin Rd",
    "iso:country":"US",
    "sg:address":"2320 Florin Rd",
    "sg:city":"Sacramento",
    "sg:classifiers":[
        {
            "category":"Professional",
            "subcategory":"Business Services",
            "type":"Services"
        }
    ],
    "sg:phone":"+1 916 410 1641",
    "sg:postcode":"95822",
    "sg:province":"CA",
    "sg:tags":[
        "recording",
        "studio"
    ],
    "wof:name":"Grey Beard Studios",
    "wof:placetype":"venue"
},
  "geometry": {"coordinates":[-121.483221,38.495683],"type":"Point"}
}