{
  "type": "Feature",
  "properties": {
    "iso:country":"US",
    "sg:address":"206 Park Blvd",
    "sg:city":"San Diego",
    "sg:classifiers":[
        {
            "category":"Real Estate",
            "subcategory":"Real Estate Services",
            "type":"Services"
        },
        {
            "category":"Real Estate",
            "subcategory":"Real Estate Operator",
            "type":"Services"
        }
    ],
    "sg:phone":"+1 619 702 2533",
    "sg:postcode":"92101",
    "sg:province":"CA",
    "sg:tags":[
        "apartment",
        "property",
        "management"
    ],
    "wof:name":"San Diego Sunrise Management",
    "wof:placetype":"venue"
},
  "geometry": {"coordinates":[-117.15494099999999,32.707589],"type":"Point"}
}