{
  "type": "Feature",
  "properties": {
    "iso:country":"US",
    "sg:address":"12046 Emelita St",
    "sg:city":"Valley Village",
    "sg:classifiers":[
        {
            "category":"Professional",
            "type":"Services"
        }
    ],
    "sg:phone":"+1 818 766 8562",
    "sg:postcode":"91607",
    "sg:province":"CA",
    "wof:name":"Fine Colombian Emeralds",
    "wof:placetype":"venue"
},
  "geometry": {"coordinates":[-118.39566000000001,34.176219],"type":"Point"}
}