{
  "type": "Feature",
  "properties": {
    "iso:country":"US",
    "sg:address":"1 Autry",
    "sg:city":"Irvine",
    "sg:classifiers":[
        {
            "category":"Government",
            "subcategory":"Office",
            "type":"Public Place"
        }
    ],
    "sg:phone":"+1 949 795 6523",
    "sg:postcode":"92618",
    "sg:province":"CA",
    "sg:tags":[
        "smog",
        "check"
    ],
    "sg:website":"www.OrangeCountyPublicScales.com/",
    "wof:name":"Orange County Public Scales",
    "wof:placetype":"venue"
},
  "geometry": {"coordinates":[-117.716977,33.639801],"type":"Point"}
}