{
  "type": "Feature",
  "properties": {
    "addr:full":"27279 Industrial Blvd Hayward CA 94545",
    "addr:housenumber":"27279",
    "addr:postcode":"94545",
    "addr:street":"Industrial Blvd",
    "iso:country":"US",
    "sg:address":"27279 Industrial Blvd",
    "sg:city":"Hayward",
    "sg:classifiers":[
        {
            "category":"Food & Beverages",
            "subcategory":"Specialty",
            "type":"Retail Goods"
        }
    ],
    "sg:phone":"+1 650 872 1883",
    "sg:postcode":"94545",
    "sg:province":"CA",
    "sg:tags":[
        "gourmet",
        "shop"
    ],
    "wof:name":"Sun Foods Co",
    "wof:placetype":"venue"
},
  "geometry": {"coordinates":[-122.109088,37.629502],"type":"Point"}
}