{
  "type": "Feature",
  "properties": {
    "addr:full":"525 W State St Ontario CA 91762",
    "addr:housenumber":"525",
    "addr:postcode":"91762",
    "addr:street":"W State St",
    "iso:country":"US",
    "sg:address":"525 W State St",
    "sg:city":"Ontario",
    "sg:classifiers":[
        {
            "category":"Marine",
            "type":"Transportation"
        }
    ],
    "sg:phone":"+1 909 933 1107",
    "sg:postcode":"91762",
    "sg:province":"CA",
    "sg:website":"www.ourboyztow.com",
    "wof:name":"Our Boyz Towing",
    "wof:placetype":"venue"
},
  "geometry": {"coordinates":[-117.657719,34.059955],"type":"Point"}
}