{
  "type": "Feature",
  "properties": {
    "addr:full":"790 Lincoln St Santa Clara CA 95050",
    "addr:housenumber":"790",
    "addr:postcode":"95050",
    "addr:street":"Lincoln St",
    "iso:country":"US",
    "sg:address":"790 Lincoln St",
    "sg:city":"Santa Clara",
    "sg:classifiers":[
        {
            "category":"Personal",
            "subcategory":"Beauty Salon",
            "type":"Services"
        }
    ],
    "sg:phone":"+1 408 247 7785",
    "sg:postcode":"95050",
    "sg:province":"CA",
    "sg:tags":[
        "hair"
    ],
    "sg:website":"www.thesanctuarysalon.com",
    "wof:name":"Sanctuary Salon",
    "wof:placetype":"venue"
},
  "geometry": {"coordinates":[-121.950779,37.345113],"type":"Point"}
}