{
  "type": "Feature",
  "properties": {
    "iso:country":"US",
    "sg:address":"4475 Entrada Dr",
    "sg:city":"Pleasanton",
    "sg:classifiers":[
        {
            "category":"Health Services",
            "subcategory":"Clinic",
            "type":"Services"
        }
    ],
    "sg:phone":"+1 925 426 0439",
    "sg:postcode":"94566",
    "sg:province":"CA",
    "sg:tags":[
        "rehabilitation"
    ],
    "wof:name":"RehabCare",
    "wof:placetype":"venue"
},
  "geometry": {"coordinates":[-121.870058,37.657776],"type":"Point"}
}