{
  "type": "Feature",
  "properties": {
    "iso:country":"US",
    "sg:address":"3125 Sullivan Ave",
    "sg:city":"Rosemead",
    "sg:classifiers":[
        {
            "category":"Professional",
            "type":"Services"
        }
    ],
    "sg:phone":"+1 626 280 9149",
    "sg:postcode":"91770",
    "sg:province":"CA",
    "sg:tags":[
        "establishment"
    ],
    "wof:name":"Mao Liying",
    "wof:placetype":"venue"
},
  "geometry": {"coordinates":[-118.071844,34.06558],"type":"Point"}
}