{
  "type": "Feature",
  "properties": {
    "addr:full":"26885 Mulholland Hwy Calabasas CA 91302",
    "addr:housenumber":"26885",
    "addr:postcode":"91302",
    "addr:street":"Mulholland Hwy",
    "iso:country":"US",
    "sg:address":"26885 Mulholland Hwy",
    "sg:city":"Calabasas",
    "sg:classifiers":[
        {
            "category":"Professional",
            "subcategory":"Engineering",
            "type":"Services"
        }
    ],
    "sg:phone":"+1 818 878 9641",
    "sg:postcode":"91302",
    "sg:province":"CA",
    "sg:tags":[
        "engineer"
    ],
    "wof:name":"Boudreau Trust Of 1990",
    "wof:placetype":"venue"
},
  "geometry": {"coordinates":[-118.711175,34.104058],"type":"Point"}
}