{
  "type": "Feature",
  "properties": {
    "addr:full":"900 3rd St San Fernando CA 91340",
    "addr:housenumber":"900",
    "addr:postcode":"91340",
    "addr:street":"3Rd St",
    "iso:country":"US",
    "sg:address":"900 3rd St",
    "sg:city":"San Fernando",
    "sg:classifiers":[
        {
            "category":"Government",
            "subcategory":"Court House",
            "type":"Public Place"
        }
    ],
    "sg:phone":"+1 818 898 2401",
    "sg:postcode":"91340",
    "sg:province":"CA",
    "sg:tags":[
        "county"
    ],
    "sg:website":"www.lasuperiorcourt.org",
    "wof:name":"Los Angeles Superior Court",
    "wof:placetype":"venue"
},
  "geometry": {"coordinates":[-118.43674,34.284649],"type":"Point"}
}