{
  "type": "Feature",
  "properties": {
    "addr:full":"565 W Lambert Rd Brea CA 92821",
    "addr:housenumber":"565",
    "addr:postcode":"92821",
    "addr:street":"W Lambert Rd",
    "iso:country":"US",
    "sg:address":"565 W Lambert Rd",
    "sg:city":"Brea",
    "sg:classifiers":[
        {
            "category":"Building & Trades",
            "subcategory":"Landscaping Services",
            "type":"Services"
        }
    ],
    "sg:phone":"+1 714 529 1291",
    "sg:postcode":"92821",
    "sg:province":"CA",
    "sg:tags":[
        "design",
        "landscape",
        "maintenance",
        "contractor"
    ],
    "wof:name":"Segura Deutschman Associates",
    "wof:placetype":"venue"
},
  "geometry": {"coordinates":[-117.904753,33.924755],"type":"Point"}
}