{
  "type": "Feature",
  "properties": {
    "addr:full":"2185 Market St San Francisco CA 94114",
    "addr:housenumber":"2185",
    "addr:postcode":"94114",
    "addr:street":"Market St",
    "iso:country":"US",
    "sg:address":"2185 Market St",
    "sg:city":"San Francisco",
    "sg:classifiers":[
        {
            "category":"Manufacturing",
            "subcategory":"Printing",
            "type":"Manufacturing & Wholesale Goods"
        }
    ],
    "sg:phone":"+1 415 626 2416",
    "sg:postcode":"94114",
    "sg:province":"CA",
    "sg:tags":[
        "printer"
    ],
    "wof:name":"KWIK KOPY Printing",
    "wof:placetype":"venue"
},
  "geometry": {"coordinates":[-122.43102500000001,37.765868],"type":"Point"}
}