{
  "type": "Feature",
  "properties": {
    "iso:country":"US",
    "sg:address":"1520 Merritt Dr",
    "sg:city":"El Cajon",
    "sg:classifiers":[
        {
            "category":"Professional",
            "subcategory":"Engineering",
            "type":"Services"
        }
    ],
    "sg:phone":"+1 619 579 9333",
    "sg:postcode":"92020",
    "sg:province":"CA",
    "sg:tags":[
        "engineer"
    ],
    "wof:name":"Baker Engineering Inc",
    "wof:placetype":"venue"
},
  "geometry": {"coordinates":[-116.93705199999999,32.780902],"type":"Point"}
}