{
  "type": "Feature",
  "properties": {
    "iso:country":"US",
    "sg:address":"3033 5th Ave Ste 235",
    "sg:city":"San Diego",
    "sg:classifiers":[
        {
            "category":"Banks & Credit Unions",
            "subcategory":"Financial Services",
            "type":"Services"
        }
    ],
    "sg:phone":"+1 619 704 1090",
    "sg:postcode":"92103",
    "sg:province":"CA",
    "sg:tags":[
        "broker",
        "mortgage"
    ],
    "wof:name":"Action Foreclosure Services Inc",
    "wof:placetype":"venue"
},
  "geometry": {"coordinates":[-117.160146,32.736979],"type":"Point"}
}