{
  "type": "Feature",
  "properties": {
    "iso:country":"US",
    "sg:address":"1641 Camino Verdera",
    "sg:city":"Lincoln",
    "sg:classifiers":[
        {
            "category":"Professional",
            "subcategory":"Computer Services",
            "type":"Services"
        }
    ],
    "sg:phone":"+1 916 209 3900",
    "sg:postcode":"95648",
    "sg:province":"CA",
    "sg:tags":[
        "isp",
        "provider",
        "internet"
    ],
    "wof:name":"Archivability Inc",
    "wof:placetype":"venue"
},
  "geometry": {"coordinates":[-121.23160300000001,38.858776],"type":"Point"}
}