{
  "type": "Feature",
  "properties": {
    "iso:country":"US",
    "sg:address":"2418 Marine Ave",
    "sg:city":"Gardena",
    "sg:classifiers":[
        {
            "category":"Personal",
            "subcategory":"Beauty Salon",
            "type":"Services"
        }
    ],
    "sg:phone":"+1 310 354 9914",
    "sg:postcode":"90249",
    "sg:province":"CA",
    "wof:name":"Andres Hair Studio",
    "wof:placetype":"venue"
},
  "geometry": {"coordinates":[-118.321382,33.894596],"type":"Point"}
}