{
  "type": "Feature",
  "properties": {
    "iso:country":"US",
    "sg:address":"2201 Pillsbury Rd",
    "sg:city":"Chico",
    "sg:classifiers":[
        {
            "category":"Food & Beverages",
            "subcategory":"Specialty",
            "type":"Retail Goods"
        }
    ],
    "sg:phone":"+1 530 345 8600",
    "sg:postcode":"95926",
    "sg:province":"CA",
    "sg:tags":[
        "health",
        "diet"
    ],
    "wof:name":"Herb Store & Education Ctr",
    "wof:placetype":"venue"
},
  "geometry": {"coordinates":[-121.84930799999999,39.758604],"type":"Point"}
}