{
  "type": "Feature",
  "properties": {
    "addr:full":"2978 D St La Verne CA 91750",
    "addr:housenumber":"2978",
    "addr:postcode":"91750",
    "addr:street":"D St",
    "iso:country":"US",
    "sg:address":"2978 D St",
    "sg:city":"La Verne",
    "sg:classifiers":[
        {
            "category":"Building & Trades",
            "subcategory":"Construction",
            "type":"Services"
        }
    ],
    "sg:phone":"+1 909 593 4317",
    "sg:postcode":"91750",
    "sg:province":"CA",
    "sg:tags":[
        "maker",
        "cabinet"
    ],
    "wof:name":"Roman Finish",
    "wof:placetype":"venue"
},
  "geometry": {"coordinates":[-117.767796,34.106491],"type":"Point"}
}