{
  "type": "Feature",
  "properties": {
    "addr:full":"13331 Brookhurst St Garden Grove CA 92843",
    "addr:housenumber":"13331",
    "addr:postcode":"92843",
    "addr:street":"Brookhurst St",
    "iso:country":"US",
    "sg:address":"13331 Brookhurst St",
    "sg:city":"Garden Grove",
    "sg:classifiers":[
        {
            "category":"Autos & Motor Vehicles",
            "subcategory":"Auto Supplies",
            "type":"Retail Goods"
        }
    ],
    "sg:phone":"+1 714 590 1990",
    "sg:postcode":"92843",
    "sg:province":"CA",
    "sg:tags":[
        "glass"
    ],
    "wof:name":"U S Safety Auto Glass",
    "wof:placetype":"venue"
},
  "geometry": {"coordinates":[-117.95500199999999,33.769199],"type":"Point"}
}