{
  "type": "Feature",
  "properties": {
    "iso:country":"US",
    "sg:address":"24305 Sparrow St",
    "sg:city":"Lake Forest",
    "sg:classifiers":[
        {
            "category":"Professional",
            "type":"Services"
        }
    ],
    "sg:phone":"+1 949 306 6760",
    "sg:postcode":"92630",
    "sg:province":"CA",
    "wof:name":"Terrasurv Inc",
    "wof:placetype":"venue"
},
  "geometry": {"coordinates":[-117.70635799999999,33.640149],"type":"Point"}
}