{
  "type": "Feature",
  "properties": {
    "iso:country":"US",
    "sg:address":"1512 Barton Rd",
    "sg:city":"Redlands",
    "sg:classifiers":[
        {
            "category":"Wholesale",
            "subcategory":"Chemicals & Plastics",
            "type":"Manufacturing & Wholesale Goods"
        }
    ],
    "sg:phone":"+1 909 793 1601",
    "sg:postcode":"92373",
    "sg:province":"CA",
    "sg:tags":[
        "medic",
        "merchandise"
    ],
    "wof:name":"Redlands Medical Supplies",
    "wof:placetype":"venue"
},
  "geometry": {"coordinates":[-117.204295,34.046564],"type":"Point"}
}