{
  "type": "Feature",
  "properties": {
    "iso:country":"US",
    "sg:address":"2550 Treasure Dr",
    "sg:city":"Santa Barbara",
    "sg:classifiers":[
        {
            "category":"Health Services",
            "subcategory":"Nursing And Care Facility",
            "type":"Services"
        }
    ],
    "sg:phone":"+1 805 687 0701",
    "sg:postcode":"93105",
    "sg:province":"CA",
    "wof:name":"Samarkand Retirement Community",
    "wof:placetype":"venue"
},
  "geometry": {"coordinates":[-119.730904,34.430216],"type":"Point"}
}