{
  "type": "Feature",
  "properties": {
    "iso:country":"US",
    "sg:address":"1915 Salvio St",
    "sg:city":"Concord",
    "sg:classifiers":[
        {
            "category":"Retail",
            "subcategory":"Repair Shop",
            "type":"Services"
        }
    ],
    "sg:phone":"+1 925 682 1242",
    "sg:postcode":"94519",
    "sg:province":"CA",
    "sg:tags":[
        "watch"
    ],
    "wof:name":"Joe's Clock & Watch",
    "wof:placetype":"venue"
},
  "geometry": {"coordinates":[-122.036169,37.976843],"type":"Point"}
}