{
  "type": "Feature",
  "properties": {
    "addr:full":"321 W Katella Ave Level 1 - 152 Anaheim CA 92802",
    "addr:housenumber":"321;1",
    "addr:postcode":"152;92802",
    "addr:street":"W Katella Ave Level",
    "iso:country":"US",
    "sg:address":"321 W Katella Ave Level 1 - 152",
    "sg:city":"Anaheim",
    "sg:classifiers":[
        {
            "category":"Personal",
            "subcategory":"Beauty Salon",
            "type":"Services"
        },
        {
            "category":"Personal",
            "subcategory":"Day Spa",
            "type":"Services"
        }
    ],
    "sg:phone":"+1 714 778 3337",
    "sg:postcode":"92802",
    "sg:province":"CA",
    "sg:tags":[
        "hair"
    ],
    "sg:website":"www.luxsalon.info",
    "wof:name":"Lux Aveda Salon/Spa",
    "wof:placetype":"venue"
},
  "geometry": {"coordinates":[-117.911312,33.80376],"type":"Point"}
}