{
  "type": "Feature",
  "properties": {
    "iso:country":"US",
    "sg:address":"4673 Ave Rio del Oro",
    "sg:city":"Yorba Linda",
    "sg:classifiers":[
        {
            "category":"Building & Trades",
            "subcategory":"Plumbing",
            "type":"Services"
        }
    ],
    "sg:phone":"+1 714 970 1210",
    "sg:postcode":"92886",
    "sg:province":"CA",
    "sg:tags":[
        "contractor"
    ],
    "wof:name":"Vans Plumbing",
    "wof:placetype":"venue"
},
  "geometry": {"coordinates":[-117.783418,33.892889],"type":"Point"}
}