{
  "type": "Feature",
  "properties": {
    "addr:full":"7528 Etiwanda Ave Reseda CA 91335",
    "addr:housenumber":"7528",
    "addr:postcode":"91335",
    "addr:street":"Etiwanda Ave",
    "iso:country":"US",
    "sg:address":"7528 Etiwanda Ave",
    "sg:city":"Reseda",
    "sg:classifiers":[
        {
            "category":"Building & Trades",
            "subcategory":"Construction",
            "type":"Services"
        }
    ],
    "sg:phone":"+1 818 343 2621",
    "sg:postcode":"91335",
    "sg:province":"CA",
    "sg:tags":[
        "painter"
    ],
    "wof:name":"Ken Hansen Painting",
    "wof:placetype":"venue"
},
  "geometry": {"coordinates":[-118.531617,34.206044],"type":"Point"}
}