{
  "type": "Feature",
  "properties": {
    "iso:country":"US",
    "sg:address":"73030 El Paseo",
    "sg:city":"Palm Desert",
    "sg:classifiers":[
        {
            "category":"Restaurant",
            "type":"Food & Drink"
        }
    ],
    "sg:phone":"+1 760 776 1971",
    "sg:postcode":"92260",
    "sg:province":"CA",
    "wof:name":"Rib Co the",
    "wof:placetype":"venue"
},
  "geometry": {"coordinates":[-116.39099899999999,33.719799],"type":"Point"}
}