{
  "type": "Feature",
  "properties": {
    "addr:full":"9726 Alpine Rd Stockton CA 95212",
    "addr:housenumber":"9726",
    "addr:postcode":"95212",
    "addr:street":"Alpine Rd",
    "iso:country":"US",
    "sg:address":"9726 Alpine Rd",
    "sg:city":"Stockton",
    "sg:classifiers":[
        {
            "category":"Local Transit",
            "type":"Transportation"
        }
    ],
    "sg:phone":"+1 209 931 9047",
    "sg:postcode":"95212",
    "sg:province":"CA",
    "sg:tags":[
        "limousine"
    ],
    "wof:name":"A-One Limousine Svc",
    "wof:placetype":"venue"
},
  "geometry": {"coordinates":[-121.210179,38.055292],"type":"Point"}
}