{
  "type": "Feature",
  "properties": {
    "addr:full":"324 N Main St Fort Bragg CA 95437",
    "addr:housenumber":"324",
    "addr:postcode":"95437",
    "addr:street":"N Main St",
    "iso:country":"US",
    "sg:address":"324 N Main St",
    "sg:city":"Fort Bragg",
    "sg:classifiers":[
        {
            "category":"Shopping",
            "subcategory":"Used Merchandise",
            "type":"Retail Goods"
        }
    ],
    "sg:phone":"+1 707 964 2050",
    "sg:postcode":"95437",
    "sg:province":"CA",
    "sg:tags":[
        "book",
        "rare",
        "dealer"
    ],
    "sg:website":"www.windsongbooks.com",
    "wof:name":"Windsong Used Books & Records",
    "wof:placetype":"venue"
},
  "geometry": {"coordinates":[-123.805807,39.44517],"type":"Point"}
}