{
  "type": "Feature",
  "properties": {
    "addr:full":"510 Adriana Pl Auburn CA 95603",
    "addr:housenumber":"510",
    "addr:postcode":"ca 95603",
    "addr:street":"Adriana Pl",
    "iso:country":"US",
    "sg:address":"510 Adriana Pl",
    "sg:city":"Auburn",
    "sg:classifiers":[
        {
            "category":"Real Estate",
            "subcategory":"Developer",
            "type":"Services"
        }
    ],
    "sg:phone":"+1 530 885 4525",
    "sg:postcode":"95603",
    "sg:province":"CA",
    "wof:name":"Duff Investments",
    "wof:placetype":"venue"
},
  "geometry": {"coordinates":[-121.076318,38.87964],"type":"Point"}
}