{
  "type": "Feature",
  "properties": {
    "addr:full":"9211 Cripple Creek Ave Bakersfield CA 93312",
    "addr:housenumber":"9211",
    "addr:postcode":"93312",
    "addr:street":"Cripple Creek Ave",
    "iso:country":"US",
    "sg:address":"9211 Cripple Creek Ave",
    "sg:city":"Bakersfield",
    "sg:classifiers":[
        {
            "category":"Wholesale",
            "subcategory":"Machinery & Supplies",
            "type":"Manufacturing & Wholesale Goods"
        }
    ],
    "sg:phone":"+1 661 399 4940",
    "sg:postcode":"93312",
    "sg:province":"CA",
    "sg:tags":[
        "boring",
        "drilling"
    ],
    "wof:name":"3 D Energy Svc",
    "wof:placetype":"venue"
},
  "geometry": {"coordinates":[-119.104328,35.425285],"type":"Point"}
}