{
  "type": "Feature",
  "properties": {
    "iso:country":"US",
    "sg:address":"1549 Brentford Ave",
    "sg:city":"Westlake Village",
    "sg:classifiers":[
        {
            "category":"Wholesale",
            "subcategory":"Non-durable Goods",
            "type":"Manufacturing & Wholesale Goods"
        }
    ],
    "sg:phone":"+1 805 497 1377",
    "sg:postcode":"91361",
    "sg:province":"CA",
    "wof:name":"Wcb Import Co",
    "wof:placetype":"venue"
},
  "geometry": {"coordinates":[-118.84813,34.146637],"type":"Point"}
}