{
  "type": "Feature",
  "properties": {
    "iso:country":"US",
    "sg:address":"15404 S Hacienda Blvd",
    "sg:city":"Hacienda Heights",
    "sg:classifiers":[
        {
            "category":"Professional",
            "subcategory":"Detective & Security Services",
            "type":"Services"
        }
    ],
    "sg:phone":"+1 626 333 3337",
    "sg:postcode":"91745",
    "sg:province":"CA",
    "sg:tags":[
        "investigator"
    ],
    "wof:name":"Buhler Investigations",
    "wof:placetype":"venue"
},
  "geometry": {"coordinates":[-117.971025,33.986613],"type":"Point"}
}