{
  "type": "Feature",
  "properties": {
    "iso:country":"US",
    "sg:address":"1411 S State St",
    "sg:city":"Ukiah",
    "sg:classifiers":[
        {
            "category":"Retail",
            "subcategory":"Auto Rental",
            "type":"Services"
        }
    ],
    "sg:phone":"+1 707 463 2777",
    "sg:postcode":"95482",
    "sg:province":"CA",
    "sg:tags":[
        "renting",
        "automobile",
        "passenger",
        "car"
    ],
    "wof:name":"Enterprise Rent-A-Car",
    "wof:placetype":"venue"
},
  "geometry": {"coordinates":[-123.204492,39.128652],"type":"Point"}
}