{
  "type": "Feature",
  "properties": {
    "addr:full":"10636 Zelzah Ave Granada Hills CA 91344",
    "addr:housenumber":"10636",
    "addr:postcode":"91344",
    "addr:street":"Zelzah Ave",
    "iso:country":"US",
    "sg:address":"10636 Zelzah Ave",
    "sg:city":"Granada Hills",
    "sg:classifiers":[
        {
            "category":"Education",
            "subcategory":"Special Training",
            "type":"Public Place"
        }
    ],
    "sg:phone":"+1 818 366 5540",
    "sg:postcode":"91344",
    "sg:province":"CA",
    "sg:tags":[
        "instruction",
        "music"
    ],
    "wof:name":"Marina's School Of Music",
    "wof:placetype":"venue"
},
  "geometry": {"coordinates":[-118.52329899999999,34.262955],"type":"Point"}
}