{
  "type": "Feature",
  "properties": {
    "addr:full":"6885 Flanders Dr San Diego CA 92126",
    "addr:housenumber":"6885",
    "addr:postcode":"92126",
    "addr:street":"Flanders Dr",
    "iso:country":"US",
    "sg:address":"6885 Flanders Dr",
    "sg:city":"San Diego",
    "sg:classifiers":[
        {
            "category":"Professional",
            "subcategory":"Computer Services",
            "type":"Services"
        }
    ],
    "sg:phone":"+1 619 294 7372",
    "sg:postcode":"92126",
    "sg:province":"CA",
    "sg:tags":[
        "electronics"
    ],
    "sg:website":"www.sdrinc.com",
    "wof:name":"SDRC",
    "wof:placetype":"venue"
},
  "geometry": {"coordinates":[-117.17477599999999,32.903567],"type":"Point"}
}