{
  "type": "Feature",
  "properties": {
    "iso:country":"US",
    "sg:address":"1712 Broadway",
    "sg:city":"El Cajon",
    "sg:classifiers":[
        {
            "category":"Building & Trades",
            "subcategory":"Construction",
            "type":"Services"
        }
    ],
    "sg:phone":"+1 619 444 8879",
    "sg:postcode":"92021",
    "sg:province":"CA",
    "sg:tags":[
        "concrete",
        "pumping"
    ],
    "wof:name":"Heartland Concrete Pumping",
    "wof:placetype":"venue"
},
  "geometry": {"coordinates":[-116.919494,32.807708],"type":"Point"}
}