{
  "type": "Feature",
  "properties": {
    "iso:country":"US",
    "sg:address":"7225 E Southgate Dr",
    "sg:city":"Sacramento",
    "sg:classifiers":[
        {
            "category":"Organizations",
            "subcategory":"Non-profit Organization",
            "type":"Services"
        }
    ],
    "sg:phone":"+1 916 394 1000",
    "sg:postcode":"95823",
    "sg:province":"CA",
    "sg:tags":[
        "info",
        "addiction",
        "abuse",
        "treatment",
        "drug"
    ],
    "wof:name":"Center For Behavioral Health",
    "wof:placetype":"venue"
},
  "geometry": {"coordinates":[-121.43764299999999,38.493389],"type":"Point"}
}