{
  "type": "Feature",
  "properties": {
    "addr:full":"1280 Tuolumne Rd Millbrae CA 94030",
    "addr:housenumber":"1280",
    "addr:postcode":"94030",
    "addr:street":"Tuolumne Rd",
    "iso:country":"US",
    "sg:address":"1280 Tuolumne Rd",
    "sg:city":"Millbrae",
    "sg:classifiers":[
        {
            "category":"Building & Trades",
            "subcategory":"Construction",
            "type":"Services"
        }
    ],
    "sg:phone":"+1 650 692 6160",
    "sg:postcode":"94030",
    "sg:province":"CA",
    "sg:tags":[
        "contractor"
    ],
    "wof:name":"Calstate Roofing Inc",
    "wof:placetype":"venue"
},
  "geometry": {"coordinates":[-122.415199,37.596162],"type":"Point"}
}