{
  "type": "Feature",
  "properties": {
    "iso:country":"US",
    "sg:address":"1850 W Lacey Blvd",
    "sg:city":"Hanford",
    "sg:classifiers":[
        {
            "category":"Food & Beverages",
            "subcategory":"Groceries & Convenience Stores",
            "type":"Retail Goods"
        }
    ],
    "sg:phone":"+1 559 585 2080",
    "sg:postcode":"93230",
    "sg:province":"CA",
    "sg:tags":[
        "grocer"
    ],
    "wof:name":"Foods Co",
    "wof:placetype":"venue"
},
  "geometry": {"coordinates":[-119.669048,36.328079],"type":"Point"}
}