{
  "type": "Feature",
  "properties": {
    "addr:full":"1969 el Camino Real Aromas CA 95004",
    "addr:housenumber":"1969",
    "addr:postcode":"ca 95004",
    "addr:street":"El Camino Real",
    "iso:country":"US",
    "sg:address":"1969 el Camino Real",
    "sg:city":"Aromas",
    "sg:classifiers":[
        {
            "category":"Freight",
            "type":"Transportation"
        }
    ],
    "sg:phone":"+1 831 726 7146",
    "sg:postcode":"95004",
    "sg:province":"CA",
    "sg:tags":[
        "operator",
        "local",
        "trucking"
    ],
    "wof:name":"Lnl Trucking",
    "wof:placetype":"venue"
},
  "geometry": {"coordinates":[-121.634338,36.844304],"type":"Point"}
}