{
  "type": "Feature",
  "properties": {
    "iso:country":"US",
    "sg:address":"11324 Magnolia Blvd",
    "sg:city":"North Hollywood",
    "sg:classifiers":[
        {
            "category":"Education",
            "subcategory":"Special Training",
            "type":"Public Place"
        },
        {
            "category":"Health Services",
            "subcategory":"Health Practitioner",
            "type":"Services"
        }
    ],
    "sg:phone":"+1 818 760 8558",
    "sg:postcode":"91601",
    "sg:province":"CA",
    "sg:tags":[
        "acupuncture",
        "school",
        "specialty"
    ],
    "wof:name":"LY Acupuncture",
    "wof:placetype":"venue"
},
  "geometry": {"coordinates":[-118.37778900000001,34.164773],"type":"Point"}
}