{
  "type": "Feature",
  "properties": {
    "addr:full":"2652 Judah St San Francisco CA 94122",
    "addr:housenumber":"2652",
    "addr:postcode":"94122",
    "addr:street":"Judah St",
    "iso:country":"US",
    "sg:address":"2652 Judah St",
    "sg:city":"San Francisco",
    "sg:classifiers":[
        {
            "category":"Restaurant",
            "type":"Food & Drink"
        }
    ],
    "sg:phone":"+1 415 242 9900",
    "sg:postcode":"94122",
    "sg:province":"CA",
    "wof:name":"E KOMO Mai",
    "wof:placetype":"venue"
},
  "geometry": {"coordinates":[-122.490478,37.761187],"type":"Point"}
}