{
  "type": "Feature",
  "properties": {
    "iso:country":"US",
    "sg:address":"1808 W Commonwealth Ave",
    "sg:city":"Fullerton",
    "sg:classifiers":[
        {
            "category":"Retail",
            "subcategory":"Auto Repair",
            "type":"Services"
        }
    ],
    "sg:phone":"+1 714 526 0123",
    "sg:postcode":"92833",
    "sg:province":"CA",
    "wof:name":"Son's Auto Repair",
    "wof:placetype":"venue"
},
  "geometry": {"coordinates":[-117.959935,33.869588],"type":"Point"}
}