{
  "type": "Feature",
  "properties": {
    "addr:full":"833 N Humboldt St San Mateo CA 94401",
    "addr:housenumber":"833",
    "addr:postcode":"94401",
    "addr:street":"N Humboldt St",
    "iso:country":"US",
    "sg:address":"833 N Humboldt St",
    "sg:city":"San Mateo",
    "sg:classifiers":[
        {
            "category":"Health Services",
            "subcategory":"Health Practitioner",
            "type":"Services"
        }
    ],
    "sg:phone":"+1 650 558 0437",
    "sg:postcode":"94401",
    "sg:province":"CA",
    "sg:tags":[
        "hypnotist"
    ],
    "wof:name":"Transformational Hypnotherapy",
    "wof:placetype":"venue"
},
  "geometry": {"coordinates":[-122.32963599999999,37.581565],"type":"Point"}
}