{
  "type": "Feature",
  "properties": {
    "addr:full":"60 Main St Quincy CA 95971",
    "addr:housenumber":"60",
    "addr:postcode":"95971",
    "addr:street":"Main St",
    "iso:country":"US",
    "sg:address":"60 Main St",
    "sg:city":"Quincy",
    "sg:classifiers":[
        {
            "category":"Autos & Motor Vehicles",
            "subcategory":"Fuel & Gas Station",
            "type":"Retail Goods"
        }
    ],
    "sg:phone":"+1 530 283 2640",
    "sg:postcode":"95971",
    "sg:province":"CA",
    "sg:tags":[
        "oil"
    ],
    "wof:name":"Foley's Auto Svc",
    "wof:placetype":"venue"
},
  "geometry": {"coordinates":[-120.938496,39.937695],"type":"Point"}
}