{
  "type": "Feature",
  "properties": {
    "addr:full":"7658 N Blackstone Ave Fresno CA 93720",
    "addr:housenumber":"7658",
    "addr:postcode":"93720",
    "addr:street":"N Blackstone Ave",
    "iso:country":"US",
    "sg:address":"7658 N Blackstone Ave",
    "sg:city":"Fresno",
    "sg:classifiers":[
        {
            "category":"Coffee & Tea",
            "type":"Food & Drink"
        }
    ],
    "sg:menulink":"http://www.allmenus.com/ca/fresno/111008-starbucks-coffee/menu/",
    "sg:phone":"+1 559 261 2439",
    "sg:postcode":"93720",
    "sg:province":"CA",
    "sg:tags":[
        "american"
    ],
    "wof:name":"Starbucks Coffee",
    "wof:placetype":"venue"
},
  "geometry": {"coordinates":[-119.78990899999999,36.849648],"type":"Point"}
}