{
  "type": "Feature",
  "properties": {
    "addr:full":"2900 4th St Santa Monica CA 90405",
    "addr:housenumber":"2900",
    "addr:postcode":"90405",
    "addr:street":"4Th St",
    "iso:country":"US",
    "sg:address":"2900 4th St",
    "sg:city":"Santa Monica",
    "sg:classifiers":[
        {
            "category":"Professional",
            "type":"Services"
        }
    ],
    "sg:phone":"+1 310 452 6645",
    "sg:postcode":"90405",
    "sg:province":"CA",
    "wof:name":"C/O Area Madaras",
    "wof:placetype":"venue"
},
  "geometry": {"coordinates":[-118.477915,34.000465],"type":"Point"}
}