{
  "type": "Feature",
  "properties": {
    "iso:country":"US",
    "sg:address":"9331 Langley Rd",
    "sg:city":"Bakersfield",
    "sg:classifiers":[
        {
            "category":"Professional",
            "type":"Services"
        }
    ],
    "sg:phone":"+1 661 303 3739",
    "sg:postcode":"93312",
    "sg:province":"CA",
    "sg:tags":[
        "establishment"
    ],
    "wof:name":"Oil Tool Mktg",
    "wof:placetype":"venue"
},
  "geometry": {"coordinates":[-119.10651,35.376197],"type":"Point"}
}