{
  "type": "Feature",
  "properties": {
    "addr:full":"798 Morro Bay Blvd Morro Bay CA 93442",
    "addr:housenumber":"798",
    "addr:postcode":"93442",
    "addr:street":"Morro Bay Blvd",
    "iso:country":"US",
    "sg:address":"798 Morro Bay Blvd",
    "sg:city":"Morro Bay",
    "sg:classifiers":[
        {
            "category":"Insurance",
            "subcategory":"Insurance Agent",
            "type":"Services"
        }
    ],
    "sg:phone":"+1 805 772 1717",
    "sg:postcode":"93442",
    "sg:province":"CA",
    "wof:name":"Mike Goolsby & Daughters Ins",
    "wof:placetype":"venue"
},
  "geometry": {"coordinates":[-120.84343200000001,35.365956],"type":"Point"}
}