{
  "type": "Feature",
  "properties": {
    "addr:full":"252 State Hwy 45 Colusa CA 95932",
    "addr:housenumber":"252",
    "addr:postcode":"95932",
    "addr:street":"State Hwy 45",
    "iso:country":"US",
    "sg:address":"252 State Hwy 45",
    "sg:city":"Colusa",
    "sg:phone":"+1 530 458 4661",
    "sg:postcode":"95932",
    "sg:province":"CA",
    "sg:tags":[
        "farm",
        "rice"
    ],
    "wof:name":"Goddard Farms",
    "wof:placetype":"venue"
},
  "geometry": {"coordinates":[-122.004734,39.213352],"type":"Point"}
}