{
  "type": "Feature",
  "properties": {
    "iso:country":"US",
    "sg:address":"1382 Wickham Ct",
    "sg:city":"San Dimas",
    "sg:classifiers":[
        {
            "category":"Wholesale",
            "subcategory":"Medical Equipment & Supplies",
            "type":"Manufacturing & Wholesale Goods"
        }
    ],
    "sg:phone":"+1 909 208 7120",
    "sg:postcode":"91773",
    "sg:province":"CA",
    "sg:tags":[
        "physician",
        "surgeon"
    ],
    "wof:name":"IMED",
    "wof:placetype":"venue"
},
  "geometry": {"coordinates":[-117.83615399999999,34.095302],"type":"Point"}
}