{
  "type": "Feature",
  "properties": {
    "addr:full":"31705 Central St Wildomar CA 92595",
    "addr:postcode":"31705;92595",
    "addr:street":"Central St",
    "iso:country":"US",
    "sg:address":"31705 Central St",
    "sg:city":"Wildomar",
    "sg:classifiers":[
        {
            "category":"Home & Garden",
            "subcategory":"Building Materials",
            "type":"Retail Goods"
        }
    ],
    "sg:phone":"+1 951 609 3194",
    "sg:postcode":"92595",
    "sg:province":"CA",
    "sg:tags":[
        "supply"
    ],
    "wof:name":"M & M Landscape Supply",
    "wof:placetype":"venue"
},
  "geometry": {"coordinates":[-117.264999,33.612099],"type":"Point"}
}