{
  "type": "Feature",
  "properties": {
    "iso:country":"US",
    "sg:address":"924 E Ave Q",
    "sg:city":"Palmdale",
    "sg:classifiers":[
        {
            "category":"Autos & Motor Vehicles",
            "subcategory":"Auto Supplies",
            "type":"Retail Goods"
        }
    ],
    "sg:phone":"+1 661 947 3640",
    "sg:postcode":"93550",
    "sg:province":"CA",
    "sg:tags":[
        "tire"
    ],
    "wof:name":"Affordable Tire & Brake",
    "wof:placetype":"venue"
},
  "geometry": {"coordinates":[-118.113933,34.587229],"type":"Point"}
}