{
  "type": "Feature",
  "properties": {
    "iso:country":"US",
    "sg:address":"1920 T Street",
    "sg:city":"Sacramento",
    "sg:classifiers":[
        {
            "category":"Sports & Exercise",
            "subcategory":"Playing Field",
            "type":"Entertainment"
        }
    ],
    "sg:phone":"+1 916 448 7837",
    "sg:postcode":"95814",
    "sg:province":"CA",
    "sg:tags":[
        "instruction",
        "fitness"
    ],
    "sg:website":"www.step1danceandfitness.com/",
    "wof:name":"Step 1 Dance & Fitness",
    "wof:placetype":"venue"
},
  "geometry": {"coordinates":[-121.485018,38.565784],"type":"Point"}
}