{
  "type": "Feature",
  "properties": {
    "addr:full":"28 Precita Avenue San Francisco CA 94110",
    "addr:housenumber":"28",
    "addr:postcode":"94110",
    "addr:street":"Precita Avenue",
    "iso:country":"US",
    "sg:address":"28 Precita Avenue",
    "sg:city":"San Francisco",
    "sg:classifiers":[
        {
            "category":"Real Estate",
            "subcategory":"Architect",
            "type":"Services"
        }
    ],
    "sg:phone":"+1 415 648 4812",
    "sg:postcode":"94110",
    "sg:province":"CA",
    "wof:name":"Lisa Harvey Architect",
    "wof:placetype":"venue"
},
  "geometry": {"coordinates":[-122.41799899999999,37.7467],"type":"Point"}
}