{
  "type": "Feature",
  "properties": {
    "addr:full":"52 Golf Club Rd Pleasant Hill CA 94523",
    "addr:housenumber":"52",
    "addr:postcode":"94523",
    "addr:street":"Golf Club Rd",
    "iso:country":"US",
    "sg:address":"52 Golf Club Rd",
    "sg:city":"Pleasant Hill",
    "sg:classifiers":[
        {
            "category":"Home & Garden",
            "subcategory":"Carpets & Floor Coverings",
            "type":"Retail Goods"
        }
    ],
    "sg:phone":"+1 925 680 8220",
    "sg:postcode":"94523",
    "sg:province":"CA",
    "sg:tags":[
        "dealer",
        "rug"
    ],
    "wof:name":"Flooring City",
    "wof:placetype":"venue"
},
  "geometry": {"coordinates":[-122.06438300000001,37.971624],"type":"Point"}
}