{
  "type": "Feature",
  "properties": {
    "iso:country":"US",
    "sg:address":"23431 Pacific Coast Hwy",
    "sg:city":"Malibu",
    "sg:classifiers":[
        {
            "category":"Retail",
            "subcategory":"Veterinary Services",
            "type":"Services"
        }
    ],
    "sg:phone":"+1 310 317 4560",
    "sg:postcode":"90265",
    "sg:province":"CA",
    "sg:tags":[
        "veterinarian",
        "specialty"
    ],
    "wof:name":"Erengerg Victor DVM",
    "wof:placetype":"venue"
},
  "geometry": {"coordinates":[-118.685432,34.034353],"type":"Point"}
}