{
  "type": "Feature",
  "properties": {
    "addr:full":"23016 Terra Dr Laguna Hills CA 92653",
    "addr:housenumber":"23016",
    "addr:postcode":"92653",
    "addr:street":"Terra Dr",
    "iso:country":"US",
    "sg:address":"23016 Terra Dr",
    "sg:city":"Laguna Hills",
    "sg:classifiers":[
        {
            "category":"Manufacturing",
            "subcategory":"Chemicals & Compounds",
            "type":"Manufacturing & Wholesale Goods"
        }
    ],
    "sg:phone":"+1 949 458 8090",
    "sg:postcode":"92653",
    "sg:province":"CA",
    "sg:tags":[
        "plastic"
    ],
    "wof:name":"Cosmo-Co",
    "wof:placetype":"venue"
},
  "geometry": {"coordinates":[-117.728002,33.626626],"type":"Point"}
}