{
  "type": "Feature",
  "properties": {
    "addr:full":"3709 Globe Ave Los Angeles CA 90066",
    "addr:housenumber":"3709",
    "addr:postcode":"90066",
    "addr:street":"Globe Ave",
    "iso:country":"US",
    "sg:address":"3709 Globe Ave",
    "sg:city":"Los Angeles",
    "sg:classifiers":[
        {
            "category":"Building & Trades",
            "subcategory":"Construction",
            "type":"Services"
        }
    ],
    "sg:phone":"+1 310 397 5706",
    "sg:postcode":"90066",
    "sg:province":"CA",
    "sg:tags":[
        "house"
    ],
    "wof:name":"Klos Construction",
    "wof:placetype":"venue"
},
  "geometry": {"coordinates":[-118.41911899999999,34.012184],"type":"Point"}
}