{
  "type": "Feature",
  "properties": {
    "iso:country":"US",
    "sg:address":"600 Castro St",
    "sg:city":"San Francisco",
    "sg:classifiers":[
        {
            "category":"Personal",
            "type":"Services"
        },
        {
            "category":"Education",
            "subcategory":"School",
            "type":"Public Place"
        },
        {
            "category":"Shopping",
            "type":"Retail Goods"
        }
    ],
    "sg:phone":"+1 415 431 2200",
    "sg:postcode":"94114",
    "sg:province":"CA",
    "sg:tags":[
        "local"
    ],
    "sg:website":"shop.hrc.org/san-francisco-hrc-s...",
    "wof:name":"Human Rights Campaign Action Center and Store",
    "wof:placetype":"venue"
},
  "geometry": {"coordinates":[-122.434867,37.759278],"type":"Point"}
}