{
  "type": "Feature",
  "properties": {
    "addr:full":"10495 Bolsa Ave Westminster CA 92683",
    "addr:housenumber":"10495",
    "addr:postcode":"92683",
    "addr:street":"Bolsa Ave",
    "iso:country":"US",
    "sg:address":"10495 Bolsa Ave",
    "sg:city":"Westminster",
    "sg:classifiers":[
        {
            "category":"Professional",
            "subcategory":"Lawyer & Legal Services",
            "type":"Services"
        }
    ],
    "sg:phone":"+1 714 839 9293",
    "sg:postcode":"92683",
    "sg:province":"CA",
    "sg:tags":[
        "consultant",
        "naturalization",
        "immigration"
    ],
    "wof:name":"H V Immigration Services",
    "wof:placetype":"venue"
},
  "geometry": {"coordinates":[-117.94616499999999,33.745012],"type":"Point"}
}