{
  "type": "Feature",
  "properties": {
    "addr:full":"906 Dianthus Ln El Dorado Hills CA 95762",
    "addr:housenumber":"906",
    "addr:postcode":"95762",
    "addr:street":"Dianthus Ln",
    "iso:country":"US",
    "sg:address":"906 Dianthus Ln",
    "sg:city":"El Dorado Hills",
    "sg:classifiers":[
        {
            "category":"Building & Trades",
            "subcategory":"Construction",
            "type":"Services"
        }
    ],
    "sg:phone":"+1 916 225 5000",
    "sg:postcode":"95762",
    "sg:province":"CA",
    "sg:tags":[
        "contractor"
    ],
    "wof:name":"Best Design Builders",
    "wof:placetype":"venue"
},
  "geometry": {"coordinates":[-121.08382,38.714301],"type":"Point"}
}