{
  "type": "Feature",
  "properties": {
    "iso:country":"US",
    "sg:address":"110 Belvedere St",
    "sg:city":"San Rafael",
    "sg:classifiers":[
        {
            "category":"Building & Trades",
            "subcategory":"Construction",
            "type":"Services"
        }
    ],
    "sg:phone":"+1 415 457 2150",
    "sg:postcode":"94901",
    "sg:province":"CA",
    "sg:tags":[
        "contractor"
    ],
    "wof:name":"Thomas Mulvey & Assoc",
    "wof:placetype":"venue"
},
  "geometry": {"coordinates":[-122.50550200000001,37.963319],"type":"Point"}
}