{
  "type": "Feature",
  "properties": {
    "iso:country":"US",
    "sg:address":"7911 Cll Posada",
    "sg:city":"Carlsbad",
    "sg:classifiers":[
        {
            "category":"Shopping",
            "subcategory":"Used Merchandise",
            "type":"Retail Goods"
        },
        {
            "category":"Home & Garden",
            "subcategory":"Furniture",
            "type":"Retail Goods"
        }
    ],
    "sg:phone":"+1 760 635 2663",
    "sg:postcode":"92009",
    "sg:province":"CA",
    "sg:tags":[
        "cabinet"
    ],
    "wof:name":"Pull Out Shelf Co of San",
    "wof:placetype":"venue"
},
  "geometry": {"coordinates":[-117.24144800000001,33.069198],"type":"Point"}
}