{
  "type": "Feature",
  "properties": {
    "iso:country":"US",
    "sg:address":"20710 Manhattan Pl",
    "sg:city":"Torrance",
    "sg:classifiers":[
        {
            "category":"Professional",
            "subcategory":"Testing Lab",
            "type":"Services"
        }
    ],
    "sg:phone":"+1 310 320 6862",
    "sg:postcode":"90501",
    "sg:province":"CA",
    "sg:tags":[
        "laboratory"
    ],
    "wof:name":"Micro Connection",
    "wof:placetype":"venue"
},
  "geometry": {"coordinates":[-118.311279,33.84347],"type":"Point"}
}