{
  "type": "Feature",
  "properties": {
    "addr:full":"472 Jasmine St Laguna Beach CA 92651",
    "addr:housenumber":"472",
    "addr:postcode":"92651",
    "addr:street":"Jasmine St",
    "iso:country":"US",
    "sg:address":"472 Jasmine St",
    "sg:city":"Laguna Beach",
    "sg:classifiers":[
        {
            "category":"Food & Beverages",
            "subcategory":"Specialty",
            "type":"Retail Goods"
        }
    ],
    "sg:phone":"+1 949 494 8736",
    "sg:postcode":"92651",
    "sg:province":"CA",
    "sg:tags":[
        "health",
        "diet"
    ],
    "wof:name":"Eden East",
    "wof:placetype":"venue"
},
  "geometry": {"coordinates":[-117.78883999999999,33.547529],"type":"Point"}
}