{
  "type": "Feature",
  "properties": {
    "addr:full":"4942 Vineland Ave Ste 112 North Hollywood CA 91601",
    "addr:housenumber":"4942",
    "addr:postcode":"91601",
    "addr:street":"Vineland Ave Ste 112",
    "iso:country":"US",
    "sg:address":"4942 Vineland Ave Ste 112",
    "sg:city":"North Hollywood",
    "sg:classifiers":[
        {
            "category":"Health Services",
            "subcategory":"Clinic",
            "type":"Services"
        }
    ],
    "sg:phone":"+1 818 761 5467",
    "sg:postcode":"91601",
    "sg:province":"CA",
    "sg:tags":[
        "cannabis"
    ],
    "wof:name":"AZ Caregivers",
    "wof:placetype":"venue"
},
  "geometry": {"coordinates":[-118.369934,34.160656],"type":"Point"}
}