{
  "type": "Feature",
  "properties": {
    "iso:country":"US",
    "sg:address":"3191 Diablo Ave",
    "sg:city":"Hayward",
    "sg:classifiers":[
        {
            "category":"Professional",
            "subcategory":"Advertising",
            "type":"Services"
        }
    ],
    "sg:phone":"+1 510 782 2540",
    "sg:postcode":"94545",
    "sg:province":"CA",
    "wof:name":"Beachline",
    "wof:placetype":"venue"
},
  "geometry": {"coordinates":[-122.123355,37.635797],"type":"Point"}
}