{
  "type": "Feature",
  "properties": {
    "iso:country":"US",
    "sg:address":"617 Kent St",
    "sg:city":"Petaluma",
    "sg:classifiers":[
        {
            "category":"Professional",
            "subcategory":"Management & Consulting",
            "type":"Services"
        }
    ],
    "sg:phone":"+1 707 765 9121",
    "sg:postcode":"94952",
    "sg:province":"CA",
    "sg:tags":[
        "consultant",
        "business"
    ],
    "wof:name":"Scott R Stroud Acctg & Cnsltng",
    "wof:placetype":"venue"
},
  "geometry": {"coordinates":[-122.649469,38.237997],"type":"Point"}
}