{
  "type": "Feature",
  "properties": {
    "addr:full":"8575 Gibbs Dr San Diego CA 92123",
    "addr:housenumber":"8575",
    "addr:postcode":"92123",
    "addr:street":"Gibbs Dr",
    "iso:country":"US",
    "sg:address":"8575 Gibbs Dr",
    "sg:city":"San Diego",
    "sg:classifiers":[
        {
            "category":"Wholesale",
            "subcategory":"Electrical",
            "type":"Manufacturing & Wholesale Goods"
        }
    ],
    "sg:phone":"+1 858 268 9945",
    "sg:postcode":"92123",
    "sg:province":"CA",
    "sg:tags":[
        "lighting",
        "consumer",
        "market"
    ],
    "wof:name":"GE",
    "wof:placetype":"venue"
},
  "geometry": {"coordinates":[-117.14164599999999,32.81038],"type":"Point"}
}