{
  "type": "Feature",
  "properties": {
    "iso:country":"US",
    "sg:address":"725 W Anaheim St",
    "sg:city":"Long Beach",
    "sg:classifiers":[
        {
            "category":"Real Estate",
            "subcategory":"Developer",
            "type":"Services"
        }
    ],
    "sg:phone":"+1 562 436 8237",
    "sg:postcode":"90813",
    "sg:province":"CA",
    "wof:name":"Bechler Corp",
    "wof:placetype":"venue"
},
  "geometry": {"coordinates":[-118.202932,33.782699],"type":"Point"}
}