{
  "type": "Feature",
  "properties": {
    "iso:country":"US",
    "sg:address":"1405 S Sunkist St",
    "sg:city":"Anaheim",
    "sg:classifiers":[
        {
            "category":"Shopping",
            "subcategory":"Stationery & Office Supplies",
            "type":"Retail Goods"
        }
    ],
    "sg:phone":"+1 714 758 0936",
    "sg:postcode":"92806",
    "sg:province":"CA",
    "sg:tags":[
        "equipment"
    ],
    "sg:website":"www.kellypaper.com",
    "wof:name":"Kelly Paper",
    "wof:placetype":"venue"
},
  "geometry": {"coordinates":[-117.88258500000001,33.814072],"type":"Point"}
}