{
  "type": "Feature",
  "properties": {
    "addr:full":"676 W Slauson Ave Los Angeles CA 90044",
    "addr:housenumber":"676",
    "addr:postcode":"90044",
    "addr:street":"W Slauson Ave",
    "iso:country":"US",
    "sg:address":"676 W Slauson Ave",
    "sg:city":"Los Angeles",
    "sg:classifiers":[
        {
            "category":"Shopping",
            "subcategory":"Used Merchandise",
            "type":"Retail Goods"
        }
    ],
    "sg:phone":"+1 323 971 6159",
    "sg:postcode":"90044",
    "sg:province":"CA",
    "sg:tags":[
        "furniture"
    ],
    "wof:name":"Raul C Godoy",
    "wof:placetype":"venue"
},
  "geometry": {"coordinates":[-118.28545699999999,33.989055],"type":"Point"}
}