{
  "type": "Feature",
  "properties": {
    "addr:full":"5470 W Spruce Ave Fresno CA 93722",
    "addr:housenumber":"5470",
    "addr:postcode":"93722",
    "addr:street":"W Spruce Ave",
    "iso:country":"US",
    "sg:address":"5470 W Spruce Ave",
    "sg:city":"Fresno",
    "sg:classifiers":[
        {
            "category":"Professional",
            "subcategory":"Management & Consulting",
            "type":"Services"
        }
    ],
    "sg:phone":"+1 559 276 5742",
    "sg:postcode":"93722",
    "sg:province":"CA",
    "sg:tags":[
        "agricultural",
        "consultant"
    ],
    "wof:name":"Personal Ag Management Svc",
    "wof:placetype":"venue"
},
  "geometry": {"coordinates":[-119.888486,36.840516],"type":"Point"}
}