{
  "type": "Feature",
  "properties": {
    "iso:country":"US",
    "sg:address":"2945 Middlefield Rd",
    "sg:city":"Redwood City",
    "sg:classifiers":[
        {
            "category":"Wholesale",
            "subcategory":"Motor Vehicles",
            "type":"Manufacturing & Wholesale Goods"
        }
    ],
    "sg:phone":"+1 650 995 9595",
    "sg:postcode":"94063",
    "sg:province":"CA",
    "wof:name":"Mild To Wild Custom Paint",
    "wof:placetype":"venue"
},
  "geometry": {"coordinates":[-122.207706,37.474261],"type":"Point"}
}