{
  "type": "Feature",
  "properties": {
    "addr:full":"208 5th St Gustine CA 95322",
    "addr:housenumber":"208",
    "addr:postcode":"95322",
    "addr:street":"5Th St",
    "iso:country":"US",
    "sg:address":"208 5th St",
    "sg:city":"Gustine",
    "sg:classifiers":[
        {
            "category":"Banks & Credit Unions",
            "subcategory":"Bank",
            "type":"Services"
        },
        {
            "category":"Banks & Credit Unions",
            "subcategory":"Financial Services",
            "type":"Services"
        }
    ],
    "sg:phone":"+1 209 854 6476",
    "sg:postcode":"95322",
    "sg:province":"CA",
    "sg:tags":[
        "broker",
        "mortgage"
    ],
    "sg:website":"www.bankofamerica.com",
    "wof:name":"Bank of America",
    "wof:placetype":"venue"
},
  "geometry": {"coordinates":[-121.695221,37.258474],"type":"Point"}
}