{
  "type": "Feature",
  "properties": {
    "iso:country":"US",
    "sg:address":"5655 College Ave",
    "sg:city":"Oakland",
    "sg:classifiers":[
        {
            "category":"Banks & Credit Unions",
            "subcategory":"Investment Brokerage",
            "type":"Services"
        }
    ],
    "sg:phone":"+1 510 450 0882",
    "sg:postcode":"94618",
    "sg:province":"CA",
    "sg:tags":[
        "advisory"
    ],
    "wof:name":"Palomarin Capital Advisors",
    "wof:placetype":"venue"
},
  "geometry": {"coordinates":[-122.251693,37.843682],"type":"Point"}
}