{
  "type": "Feature",
  "properties": {
    "iso:country":"US",
    "sg:address":"17295 Armintrout Dr",
    "sg:city":"Riverside",
    "sg:classifiers":[
        {
            "category":"Retail",
            "subcategory":"Veterinary Services",
            "type":"Services"
        }
    ],
    "sg:phone":"+1 951 685 4477",
    "sg:postcode":"92504",
    "sg:province":"CA",
    "sg:tags":[
        "veterinarian"
    ],
    "wof:name":"Gary S Cash DVM",
    "wof:placetype":"venue"
},
  "geometry": {"coordinates":[-117.367409,33.872535],"type":"Point"}
}