{
  "type": "Feature",
  "properties": {
    "addr:full":"307 N Robertson Blvd Beverly Hills CA 90211",
    "addr:housenumber":"307",
    "addr:postcode":"90211",
    "addr:street":"N Robertson Blvd",
    "iso:country":"US",
    "sg:address":"307 N Robertson Blvd",
    "sg:city":"Beverly Hills",
    "sg:classifiers":[
        {
            "category":"Home & Garden",
            "subcategory":"Hardware",
            "type":"Retail Goods"
        }
    ],
    "sg:phone":"+1 310 550 8842",
    "sg:postcode":"90211",
    "sg:province":"CA",
    "sg:tags":[
        "store"
    ],
    "wof:name":"Elite Hardware Inc",
    "wof:placetype":"venue"
},
  "geometry": {"coordinates":[-118.38393499999999,34.086265],"type":"Point"}
}