{
  "type": "Feature",
  "properties": {
    "addr:full":"2430 Oak Way Chico CA 95973",
    "addr:housenumber":"2430",
    "addr:postcode":"95973",
    "addr:street":"Oak Way",
    "iso:country":"US",
    "sg:address":"2430 Oak Way",
    "sg:city":"Chico",
    "sg:classifiers":[
        {
            "category":"Farming",
            "subcategory":"Crops",
            "type":"Manufacturing & Wholesale Goods"
        }
    ],
    "sg:phone":"+1 530 345 1448",
    "sg:postcode":"95973",
    "sg:province":"CA",
    "sg:tags":[
        "grove",
        "nut",
        "tree"
    ],
    "wof:name":"Wayne Stai",
    "wof:placetype":"venue"
},
  "geometry": {"coordinates":[-121.902664,39.735626],"type":"Point"}
}