{
  "type": "Feature",
  "properties": {
    "iso:country":"US",
    "sg:address":"1811 State St",
    "sg:city":"Santa Barbara",
    "sg:classifiers":[
        {
            "category":"Personal",
            "type":"Services"
        }
    ],
    "sg:phone":"+1 805 686 9711",
    "sg:postcode":"93101",
    "sg:province":"CA",
    "sg:tags":[
        "therapist",
        "massage"
    ],
    "wof:name":"Fredd Dunham Medical Massage",
    "wof:placetype":"venue"
},
  "geometry": {"coordinates":[-119.713347,34.429752],"type":"Point"}
}