{
  "type": "Feature",
  "properties": {
    "addr:full":"3248 N Garey Ave Pomona CA 91767",
    "addr:housenumber":"3248",
    "addr:postcode":"91767",
    "addr:street":"N Garey Ave",
    "iso:country":"US",
    "sg:address":"3248 N Garey Ave",
    "sg:city":"Pomona",
    "sg:classifiers":[
        {
            "category":"Personal",
            "subcategory":"Barber",
            "type":"Services"
        }
    ],
    "sg:phone":"+1 909 593 9178",
    "sg:postcode":"91767",
    "sg:province":"CA",
    "wof:name":"Garey's Barber's Salon",
    "wof:placetype":"venue"
},
  "geometry": {"coordinates":[-117.74851700000001,34.10697],"type":"Point"}
}