{
  "type": "Feature",
  "properties": {
    "addr:full":"5431 Auburn Blvd Ste 397 Sacramento CA 95841",
    "addr:housenumber":"5431",
    "addr:postcode":"95841",
    "addr:street":"Auburn Blvd Ste 397",
    "iso:country":"US",
    "sg:address":"5431 Auburn Blvd Ste 397",
    "sg:city":"Sacramento",
    "sg:classifiers":[
        {
            "category":"Real Estate",
            "subcategory":"Real Estate Services",
            "type":"Services"
        },
        {
            "category":"Real Estate",
            "subcategory":"Real Estate Agent",
            "type":"Services"
        }
    ],
    "sg:phone":"+1 916 443 5353",
    "sg:postcode":"95841",
    "sg:province":"CA",
    "sg:tags":[
        "management"
    ],
    "wof:name":"Prime Plus Properties",
    "wof:placetype":"venue"
},
  "geometry": {"coordinates":[-121.338055,38.667833],"type":"Point"}
}