{
  "type": "Feature",
  "properties": {
    "addr:full":"860 Via de la Paz Pacific Plsds CA 90272",
    "addr:housenumber":"860",
    "addr:postcode":"90272",
    "addr:street":"Via De La Paz",
    "iso:country":"US",
    "sg:address":"860 Via de la Paz",
    "sg:city":"Pacific Plsds",
    "sg:classifiers":[
        {
            "category":"Professional",
            "subcategory":"Advertising",
            "type":"Services"
        }
    ],
    "sg:phone":"+1 310 573 0002",
    "sg:postcode":"90272",
    "sg:province":"CA",
    "sg:tags":[
        "counselor"
    ],
    "wof:name":"Two Car Garage",
    "wof:placetype":"venue"
},
  "geometry": {"coordinates":[-118.52733499999999,34.045669],"type":"Point"}
}