{
  "type": "Feature",
  "properties": {
    "addr:full":"16407 Mcallister St Riverside CA 92503",
    "addr:postcode":"16407;92503",
    "addr:street":"Mcallister St",
    "iso:country":"US",
    "sg:address":"16407 Mcallister St",
    "sg:city":"Riverside",
    "sg:classifiers":[
        {
            "category":"Manufacturing",
            "subcategory":"Buildings",
            "type":"Manufacturing & Wholesale Goods"
        },
        {
            "category":"Home & Garden",
            "subcategory":"Building Materials",
            "type":"Retail Goods"
        },
        {
            "category":"Building & Trades",
            "subcategory":"Construction",
            "type":"Services"
        }
    ],
    "sg:phone":"+1 951 359 0555",
    "sg:postcode":"92503",
    "sg:province":"CA",
    "sg:tags":[
        "foundation",
        "altering",
        "metal",
        "contractor",
        "concrete",
        "shape",
        "paving",
        "staining",
        "remodeling",
        "block"
    ],
    "sg:website":"http://www.concreteconstruction.com",
    "wof:name":"Van Holland Concrete",
    "wof:placetype":"venue"
},
  "geometry": {"coordinates":[-117.436718,33.881569],"type":"Point"}
}