{
  "type": "Feature",
  "properties": {
    "addr:full":"9393 Main St Plymouth CA 95669",
    "addr:housenumber":"9393",
    "addr:postcode":"95669",
    "addr:street":"Main St",
    "iso:country":"US",
    "sg:address":"9393 Main St",
    "sg:city":"Plymouth",
    "sg:classifiers":[
        {
            "category":"Restaurant",
            "type":"Food & Drink"
        }
    ],
    "sg:phone":"+1 209 245 3968",
    "sg:postcode":"95669",
    "sg:province":"CA",
    "sg:tags":[
        "caterer"
    ],
    "sg:website":"www.amadorvintagemarket.com",
    "wof:name":"Beth Sogaard Catering",
    "wof:placetype":"venue"
},
  "geometry": {"coordinates":[-120.847684,38.481205],"type":"Point"}
}