{
  "type": "Feature",
  "properties": {
    "iso:country":"US",
    "sg:address":"9880 N Magnolia Ave",
    "sg:city":"Santee",
    "sg:classifiers":[
        {
            "category":"Arts & Performance",
            "subcategory":"Theater",
            "type":"Entertainment"
        }
    ],
    "sg:phone":"+1 619 562 3434",
    "sg:postcode":"92071",
    "sg:province":"CA",
    "sg:tags":[
        "entertainer",
        "business"
    ],
    "wof:name":"Alakazam Entertainment",
    "wof:placetype":"venue"
},
  "geometry": {"coordinates":[-116.971123,32.856708],"type":"Point"}
}