{
  "type": "Feature",
  "properties": {
    "iso:country":"US",
    "sg:address":"17707 Gale Ave",
    "sg:city":"City Of Industry",
    "sg:classifiers":[
        {
            "category":"Home & Garden",
            "subcategory":"Furniture",
            "type":"Retail Goods"
        }
    ],
    "sg:phone":"+1 626 964 0548",
    "sg:postcode":"91748",
    "sg:province":"CA",
    "wof:name":"Jennifer Convertibles Inc",
    "wof:placetype":"venue"
},
  "geometry": {"coordinates":[-117.922898,33.99633],"type":"Point"}
}