{
  "type": "Feature",
  "properties": {
    "iso:country":"US",
    "sg:address":"5523 S Peach Ave",
    "sg:city":"Fresno",
    "sg:classifiers":[
        {
            "category":"Farming",
            "subcategory":"Farm & Veterinary Services",
            "type":"Manufacturing & Wholesale Goods"
        }
    ],
    "sg:phone":"+1 559 834 9009",
    "sg:postcode":"93725",
    "sg:province":"CA",
    "wof:name":"Valley Farm Svc",
    "wof:placetype":"venue"
},
  "geometry": {"coordinates":[-119.718014,36.649329],"type":"Point"}
}