{
  "type": "Feature",
  "properties": {
    "addr:full":"5200 Zoo Drive Los Angeles CA 90027",
    "addr:housenumber":"5200",
    "addr:postcode":"90027",
    "addr:street":"Zoo Drive",
    "iso:country":"US",
    "sg:address":"5200 Zoo Drive",
    "sg:city":"Los Angeles",
    "sg:classifiers":[
        {
            "category":"Recreation",
            "subcategory":"Amusement Park",
            "type":"Entertainment"
        },
        {
            "category":"Park",
            "type":"Public Place"
        }
    ],
    "sg:phone":"+1 323 662 9678",
    "sg:postcode":"90027",
    "sg:province":"CA",
    "wof:name":"Travel Town Railroad",
    "wof:placetype":"venue"
},
  "geometry": {"coordinates":[-118.30328900000001,34.155327],"type":"Point"}
}