{
  "type": "Feature",
  "properties": {
    "addr:full":"191 Santa Clara St Fillmore CA 93015",
    "addr:housenumber":"191",
    "addr:postcode":"93015",
    "addr:street":"Santa Clara St",
    "iso:country":"US",
    "sg:address":"191 Santa Clara St",
    "sg:city":"Fillmore",
    "sg:classifiers":[
        {
            "category":"Building & Trades",
            "subcategory":"Construction",
            "type":"Services"
        }
    ],
    "sg:phone":"+1 805 524 3217",
    "sg:postcode":"93015",
    "sg:province":"CA",
    "sg:tags":[
        "maker",
        "cabinet"
    ],
    "wof:name":"Hector's Woodworks",
    "wof:placetype":"venue"
},
  "geometry": {"coordinates":[-118.905545,34.399349],"type":"Point"}
}