{
  "type": "Feature",
  "properties": {
    "iso:country":"US",
    "sg:address":"12955 Washington Blvd",
    "sg:city":"Los Angeles",
    "sg:classifiers":[
        {
            "category":"Retail",
            "subcategory":"Auto Repair",
            "type":"Services"
        }
    ],
    "sg:phone":"+1 310 306 7875",
    "sg:postcode":"90066",
    "sg:province":"CA",
    "wof:name":"Quality Tire and Brake Service",
    "wof:placetype":"venue"
},
  "geometry": {"coordinates":[-118.439375,33.994978],"type":"Point"}
}