{
  "type": "Feature",
  "properties": {
    "addr:full":"11990 Heritage Oak Pl # 9 Auburn CA 95603",
    "addr:housenumber":"11990",
    "addr:postcode":"ca 95603",
    "addr:street":"Heritage Oak Pl # 9",
    "iso:country":"US",
    "sg:address":"11990 Heritage Oak Pl # 9",
    "sg:city":"Auburn",
    "sg:classifiers":[
        {
            "category":"Social Services",
            "type":"Services"
        }
    ],
    "sg:phone":"+1 530 887 3536",
    "sg:postcode":"95603",
    "sg:province":"CA",
    "wof:name":"Auburn Family Resource Center",
    "wof:placetype":"venue"
},
  "geometry": {"coordinates":[-121.098826,38.941022],"type":"Point"}
}