{
  "type": "Feature",
  "properties": {
    "addr:full":"2624 Fir St Live Oak CA 95953",
    "addr:housenumber":"2624",
    "addr:postcode":"95953",
    "addr:street":"Fir St",
    "iso:country":"US",
    "sg:address":"2624 Fir St",
    "sg:city":"Live Oak",
    "sg:classifiers":[
        {
            "category":"Organizations",
            "subcategory":"Professional Association",
            "type":"Services"
        }
    ],
    "sg:phone":"+1 530 695 1519",
    "sg:postcode":"95953",
    "sg:province":"CA",
    "sg:tags":[
        "chambers",
        "commerce"
    ],
    "wof:name":"Live Oak Dist Chamber-Commerce",
    "wof:placetype":"venue"
},
  "geometry": {"coordinates":[-121.662626,39.274071],"type":"Point"}
}