{
  "type": "Feature",
  "properties": {
    "addr:full":"206 4th St Santa Rosa CA 95401",
    "addr:housenumber":"206",
    "addr:postcode":"ca 95401",
    "addr:street":"4Th St",
    "iso:country":"US",
    "sg:address":"206 4th St",
    "sg:city":"Santa Rosa",
    "sg:classifiers":[
        {
            "category":"Freight",
            "type":"Transportation"
        }
    ],
    "sg:phone":"+1 707 575 9912",
    "sg:postcode":"95401",
    "sg:province":"CA",
    "sg:tags":[
        "general"
    ],
    "wof:name":"Warson & Schwindt Co Inc",
    "wof:placetype":"venue"
},
  "geometry": {"coordinates":[-122.718902,38.438187],"type":"Point"}
}