{
  "type": "Feature",
  "properties": {
    "iso:country":"US",
    "sg:address":"603 W 216th St",
    "sg:city":"Carson",
    "sg:classifiers":[
        {
            "category":"Shopping",
            "subcategory":"Shoes",
            "type":"Retail Goods"
        }
    ],
    "sg:phone":"+1 310 328 5734",
    "sg:postcode":"90745",
    "sg:province":"CA",
    "wof:name":"Gift & Shoes",
    "wof:placetype":"venue"
},
  "geometry": {"coordinates":[-118.286833,33.832509],"type":"Point"}
}