{
  "type": "Feature",
  "properties": {
    "iso:country":"US",
    "sg:address":"118 E Fremont St",
    "sg:city":"Stockton",
    "sg:classifiers":[
        {
            "category":"Manufacturing",
            "subcategory":"Tools & Machinery",
            "type":"Manufacturing & Wholesale Goods"
        }
    ],
    "sg:phone":"+1 209 466 4375",
    "sg:postcode":"95202",
    "sg:province":"CA",
    "sg:tags":[
        "engine",
        "internal",
        "combustion"
    ],
    "wof:name":"AAA Machine Shop",
    "wof:placetype":"venue"
},
  "geometry": {"coordinates":[-121.290008,37.957689],"type":"Point"}
}