{
  "type": "Feature",
  "properties": {
    "addr:full":"4020 Fabian Way Palo Alto CA 94303",
    "addr:housenumber":"4020",
    "addr:postcode":"94303",
    "addr:street":"Fabian Way",
    "iso:country":"US",
    "sg:address":"4020 Fabian Way",
    "sg:city":"Palo Alto",
    "sg:classifiers":[
        {
            "category":"Professional",
            "subcategory":"Computer Services",
            "type":"Services"
        }
    ],
    "sg:phone":"+1 650 320 8661",
    "sg:postcode":"94303",
    "sg:province":"CA",
    "sg:tags":[
        "repair"
    ],
    "wof:name":"Bass Way Intl",
    "wof:placetype":"venue"
},
  "geometry": {"coordinates":[-122.102439,37.42109],"type":"Point"}
}