{
  "type": "Feature",
  "properties": {
    "iso:country":"US",
    "sg:address":"1065 Kensington Way",
    "sg:city":"Salinas",
    "sg:classifiers":[
        {
            "category":"Shopping",
            "subcategory":"Used Merchandise",
            "type":"Retail Goods"
        }
    ],
    "sg:phone":"+1 831 443 3673",
    "sg:postcode":"93906",
    "sg:province":"CA",
    "wof:name":"American Indian Artifacts",
    "wof:placetype":"venue"
},
  "geometry": {"coordinates":[-121.616526,36.699895],"type":"Point"}
}