{
  "type": "Feature",
  "properties": {
    "addr:full":"523 S Main St Salinas CA 93901",
    "addr:housenumber":"523",
    "addr:postcode":"93901",
    "addr:street":"S Main St",
    "iso:country":"US",
    "sg:address":"523 S Main St",
    "sg:city":"Salinas",
    "sg:classifiers":[
        {
            "category":"Banks & Credit Unions",
            "subcategory":"Bank",
            "type":"Services"
        }
    ],
    "sg:phone":"+1 831 424 8000",
    "sg:postcode":"93901",
    "sg:province":"CA",
    "sg:tags":[
        "loan",
        "real estate"
    ],
    "wof:name":"Lighthouse Home Loans",
    "wof:placetype":"venue"
},
  "geometry": {"coordinates":[-121.65489700000001,36.670651],"type":"Point"}
}