{
  "type": "Feature",
  "properties": {
    "addr:full":"3975 Wattling St Oakland CA 94601",
    "addr:housenumber":"3975",
    "addr:postcode":"94601",
    "addr:street":"Wattling St",
    "iso:country":"US",
    "sg:address":"3975 Wattling St",
    "sg:city":"Oakland",
    "sg:classifiers":[
        {
            "category":"Freight",
            "type":"Transportation"
        }
    ],
    "sg:phone":"+1 510 534 0900",
    "sg:postcode":"94601",
    "sg:province":"CA",
    "sg:tags":[
        "commercial",
        "storage"
    ],
    "wof:name":"A-Accessible Storage",
    "wof:placetype":"venue"
},
  "geometry": {"coordinates":[-122.22099,37.771209],"type":"Point"}
}