{
  "type": "Feature",
  "properties": {
    "iso:country":"US",
    "sg:address":"6733 Lindbergh Dr Ste F",
    "sg:city":"Sacramento",
    "sg:classifiers":[
        {
            "category":"Professional",
            "subcategory":"Engineering",
            "type":"Services"
        },
        {
            "category":"Retail",
            "subcategory":"Repair Shop",
            "type":"Services"
        }
    ],
    "sg:phone":"+1 916 924 1982",
    "sg:postcode":"95837",
    "sg:province":"CA",
    "sg:tags":[
        "rebuilding",
        "aircraft",
        "maintenance"
    ],
    "sg:website":"http://www.asig.com",
    "wof:name":"Aircraft Service International Group, Inc",
    "wof:placetype":"venue"
},
  "geometry": {"coordinates":[-121.594673,38.686485],"type":"Point"}
}