{
  "type": "Feature",
  "properties": {
    "addr:full":"212 E Ojai Ave Ojai CA 93023",
    "addr:housenumber":"212",
    "addr:postcode":"93023",
    "addr:street":"E Ojai Ave",
    "iso:country":"US",
    "sg:address":"212 E Ojai Ave",
    "sg:city":"Ojai",
    "sg:classifiers":[
        {
            "category":"Shopping",
            "subcategory":"Jewelry",
            "type":"Retail Goods"
        },
        {
            "category":"Shopping",
            "subcategory":"Clothing, Apparel, & Fashions",
            "type":"Retail Goods"
        }
    ],
    "sg:phone":"+1 805 640 0994",
    "sg:postcode":"93023",
    "sg:province":"CA",
    "sg:tags":[
        "jeweler"
    ],
    "wof:name":"Calais & Co",
    "wof:placetype":"venue"
},
  "geometry": {"coordinates":[-119.24413699999999,34.448014],"type":"Point"}
}