{
  "type": "Feature",
  "properties": {
    "addr:full":"609 Poplar Ave South San Francisco CA 94080",
    "addr:housenumber":"609",
    "addr:postcode":"94080",
    "addr:street":"Poplar Ave",
    "iso:country":"US",
    "sg:address":"609 Poplar Ave",
    "sg:city":"South San Francisco",
    "sg:classifiers":[
        {
            "category":"Social Services",
            "subcategory":"Child Care",
            "type":"Services"
        }
    ],
    "sg:phone":"+1 650 273 1255",
    "sg:postcode":"94080",
    "sg:province":"CA",
    "sg:tags":[
        "day"
    ],
    "wof:name":"Little Foot Prints",
    "wof:placetype":"venue"
},
  "geometry": {"coordinates":[-122.419781,37.661395],"type":"Point"}
}