{
  "type": "Feature",
  "properties": {
    "iso:country":"US",
    "sg:address":"575 E Locust Ave Ste 201",
    "sg:city":"Fresno",
    "sg:classifiers":[
        {
            "category":"Building & Trades",
            "subcategory":"Plumbing",
            "type":"Services"
        }
    ],
    "sg:phone":"+1 559 841 3347",
    "sg:postcode":"93720",
    "sg:province":"CA",
    "sg:tags":[
        "plumber",
        "industrial",
        "contractors-commercial"
    ],
    "wof:name":"Headliner Plumbing Co Inc",
    "wof:placetype":"venue"
},
  "geometry": {"coordinates":[-119.77597799999999,36.83926],"type":"Point"}
}