{
  "type": "Feature",
  "properties": {
    "iso:country":"US",
    "sg:address":"722 E 9th Pl",
    "sg:city":"Los Angeles",
    "sg:classifiers":[
        {
            "category":"Shopping",
            "subcategory":"Clothing, Apparel, & Fashions",
            "type":"Retail Goods"
        }
    ],
    "sg:phone":"+1 213 629 5040",
    "sg:postcode":"90021",
    "sg:province":"CA",
    "wof:name":"Cefian Fashion Inc",
    "wof:placetype":"venue"
},
  "geometry": {"coordinates":[-118.25011,34.035739],"type":"Point"}
}