{
  "type": "Feature",
  "properties": {
    "iso:country":"US",
    "sg:address":"5721 W Slauson Ave Ste 200",
    "sg:city":"Culver City",
    "sg:classifiers":[
        {
            "category":"Real Estate",
            "subcategory":"Real Estate Services",
            "type":"Services"
        }
    ],
    "sg:phone":"+1 310 641 7155",
    "sg:postcode":"90230",
    "sg:province":"CA",
    "sg:tags":[
        "management",
        "property"
    ],
    "wof:name":"E & S Ring Management Corp",
    "wof:placetype":"venue"
},
  "geometry": {"coordinates":[-118.383003,33.989101],"type":"Point"}
}