{
  "type": "Feature",
  "properties": {
    "iso:country":"US",
    "sg:address":"131B Front Street",
    "sg:city":"Santa Cruz",
    "sg:classifiers":[
        {
            "category":"Arts & Performance",
            "subcategory":"Art Gallery",
            "type":"Entertainment"
        }
    ],
    "sg:phone":"+1 831 621 3939",
    "sg:postcode":"95062",
    "sg:province":"CA",
    "sg:website":"www.hidegallery.com",
    "wof:name":"Hide Gallery",
    "wof:placetype":"venue"
},
  "geometry": {"coordinates":[-122.023933,36.967178],"type":"Point"}
}