{
  "type": "Feature",
  "properties": {
    "iso:country":"US",
    "sg:address":"35225 Ave A",
    "sg:city":"Yucaipa",
    "sg:classifiers":[
        {
            "category":"Health Services",
            "subcategory":"Doctor",
            "type":"Services"
        }
    ],
    "sg:phone":"+1 909 790 1300",
    "sg:postcode":"92399",
    "sg:province":"CA",
    "sg:tags":[
        "clinic"
    ],
    "wof:name":"Valley Guidance Ctr",
    "wof:placetype":"venue"
},
  "geometry": {"coordinates":[-117.034982,34.032746],"type":"Point"}
}