{
  "type": "Feature",
  "properties": {
    "iso:country":"US",
    "sg:address":"415 Cedar St",
    "sg:city":"San Carlos",
    "sg:classifiers":[
        {
            "category":"Autos & Motor Vehicles",
            "subcategory":"Automobile Sales",
            "type":"Retail Goods"
        }
    ],
    "sg:phone":"+1 650 591 1234",
    "sg:postcode":"94070",
    "sg:province":"CA",
    "sg:tags":[
        "limo"
    ],
    "wof:name":"A Corporate Transportation Service",
    "wof:placetype":"venue"
},
  "geometry": {"coordinates":[-122.26673099999999,37.50516],"type":"Point"}
}