{
  "type": "Feature",
  "properties": {
    "addr:full":"811 S Euclid St Anaheim CA 92802",
    "addr:housenumber":"811",
    "addr:postcode":"92802",
    "addr:street":"S Euclid St",
    "iso:country":"US",
    "sg:address":"811 S Euclid St",
    "sg:city":"Anaheim",
    "sg:classifiers":[
        {
            "category":"Banks & Credit Unions",
            "subcategory":"Financial Services",
            "type":"Services"
        }
    ],
    "sg:phone":"+1 714 772 5275",
    "sg:postcode":"92802",
    "sg:province":"CA",
    "sg:tags":[
        "broker",
        "mortgage"
    ],
    "wof:name":"Housing Specialities",
    "wof:placetype":"venue"
},
  "geometry": {"coordinates":[-117.941605,33.821134],"type":"Point"}
}