{
  "type": "Feature",
  "properties": {
    "iso:country":"US",
    "sg:address":"13390 Lincoln Way",
    "sg:city":"Auburn",
    "sg:classifiers":[
        {
            "category":"Shopping",
            "subcategory":"Gifts & Souvenirs",
            "type":"Retail Goods"
        }
    ],
    "sg:phone":"+1 530 888 6033",
    "sg:postcode":"95603",
    "sg:province":"CA",
    "sg:tags":[
        "shop"
    ],
    "wof:name":"Dawn's Hallmark-Office Supply",
    "wof:placetype":"venue"
},
  "geometry": {"coordinates":[-121.05666,38.92218],"type":"Point"}
}