{
  "type": "Feature",
  "properties": {
    "addr:full":"837 S Los Angeles Street Los Angeles CA 90014",
    "addr:housenumber":"837",
    "addr:postcode":"90014",
    "addr:street":"S;Angeles Street",
    "iso:country":"US",
    "sg:address":"837 S Los Angeles Street",
    "sg:city":"Los Angeles",
    "sg:classifiers":[
        {
            "category":"Shopping",
            "subcategory":"Shoes",
            "type":"Retail Goods"
        }
    ],
    "sg:phone":"+1 213 624 2692",
    "sg:postcode":"90014",
    "sg:province":"CA",
    "sg:tags":[
        "store"
    ],
    "wof:name":"E Z Shoes",
    "wof:placetype":"venue"
},
  "geometry": {"coordinates":[-118.25390299999999,34.040718],"type":"Point"}
}