{
  "type": "Feature",
  "properties": {
    "addr:full":"3048 W Torrance Blvd Torrance CA 90503",
    "addr:housenumber":"3048",
    "addr:postcode":"90503",
    "addr:street":"W Torrance Blvd",
    "iso:country":"US",
    "sg:address":"3048 W Torrance Blvd",
    "sg:city":"Torrance",
    "sg:classifiers":[
        {
            "category":"Professional",
            "subcategory":"Lawyer & Legal Services",
            "type":"Services"
        }
    ],
    "sg:phone":"+1 310 671 0211",
    "sg:postcode":"90503",
    "sg:province":"CA",
    "sg:tags":[
        "personal",
        "injury"
    ],
    "sg:website":"www.bobcohenlaw.com",
    "wof:name":"Bob M. Cohen & Associates",
    "wof:placetype":"venue"
},
  "geometry": {"coordinates":[-118.34064100000001,33.836396],"type":"Point"}
}