{
  "type": "Feature",
  "properties": {
    "addr:full":"560 S Bascom Ave San Jose CA 95128",
    "addr:housenumber":"560",
    "addr:postcode":"95128",
    "addr:street":"S Bascom Ave",
    "iso:country":"US",
    "sg:address":"560 S Bascom Ave",
    "sg:city":"San Jose",
    "sg:classifiers":[
        {
            "category":"Retail",
            "subcategory":"Repair Shop",
            "type":"Services"
        }
    ],
    "sg:phone":"+1 408 292 6328",
    "sg:postcode":"95128",
    "sg:province":"CA",
    "sg:tags":[
        "equipment",
        "photographic"
    ],
    "wof:name":"A Able Repair Ctr",
    "wof:placetype":"venue"
},
  "geometry": {"coordinates":[-121.931853,37.318093],"type":"Point"}
}