{
  "type": "Feature",
  "properties": {
    "addr:full":"165 Borland Ave Auburn CA 95603",
    "addr:housenumber":"165",
    "addr:postcode":"ca 95603",
    "addr:street":"Borland Ave",
    "iso:country":"US",
    "sg:address":"165 Borland Ave",
    "sg:city":"Auburn",
    "sg:classifiers":[
        {
            "category":"Retail",
            "subcategory":"Auto Repair",
            "type":"Services"
        }
    ],
    "sg:phone":"+1 530 887 0800",
    "sg:postcode":"95603",
    "sg:province":"CA",
    "sg:tags":[
        "repairing",
        "automobile"
    ],
    "wof:name":"Renn Tech",
    "wof:placetype":"venue"
},
  "geometry": {"coordinates":[-121.064626,38.900575],"type":"Point"}
}