{
  "type": "Feature",
  "properties": {
    "iso:country":"US",
    "sg:address":"2027 Mission Ave",
    "sg:city":"Oceanside",
    "sg:classifiers":[
        {
            "category":"Shopping",
            "subcategory":"Music",
            "type":"Retail Goods"
        }
    ],
    "sg:phone":"+1 760 433 8311",
    "sg:postcode":"92058",
    "sg:province":"CA",
    "sg:tags":[
        "dvd's"
    ],
    "wof:name":"Discoteca Cuevas",
    "wof:placetype":"venue"
},
  "geometry": {"coordinates":[-117.36363299999999,33.204477],"type":"Point"}
}