{
  "type": "Feature",
  "properties": {
    "iso:country":"US",
    "sg:address":"517 S Broadway",
    "sg:city":"Los Angeles",
    "sg:classifiers":[
        {
            "category":"Professional",
            "type":"Services"
        }
    ],
    "sg:phone":"+1 213 624 6205",
    "sg:postcode":"90013",
    "sg:province":"CA",
    "sg:tags":[
        "establishment"
    ],
    "wof:name":"Dil8 Productions",
    "wof:placetype":"venue"
},
  "geometry": {"coordinates":[-118.251911,34.046927],"type":"Point"}
}