{
  "type": "Feature",
  "properties": {
    "addr:full":"5800 Paradise Dr Corte Madera CA 94925",
    "addr:housenumber":"5800",
    "addr:postcode":"94925",
    "addr:street":"Paradise Dr",
    "iso:country":"US",
    "sg:address":"5800 Paradise Dr",
    "sg:city":"Corte Madera",
    "sg:classifiers":[
        {
            "category":"Autos & Motor Vehicles",
            "subcategory":"Auto Supplies",
            "type":"Retail Goods"
        }
    ],
    "sg:phone":"+1 415 924 8810",
    "sg:postcode":"94925",
    "sg:province":"CA",
    "sg:tags":[
        "repair",
        "r",
        "general",
        "automotive"
    ],
    "wof:name":"Corte Madera Tire & Brake",
    "wof:placetype":"venue"
},
  "geometry": {"coordinates":[-122.51134,37.921107],"type":"Point"}
}