{
  "type": "Feature",
  "properties": {
    "iso:country":"US",
    "sg:address":"30600 Navarro Ridge Rd",
    "sg:city":"Albion",
    "sg:classifiers":[
        {
            "category":"Wholesale",
            "subcategory":"Machinery & Supplies",
            "type":"Manufacturing & Wholesale Goods"
        }
    ],
    "sg:phone":"+1 707 937 4652",
    "sg:postcode":"95410",
    "sg:province":"CA",
    "sg:tags":[
        "equipment",
        "industrial"
    ],
    "wof:name":"Yarman Studio",
    "wof:placetype":"venue"
},
  "geometry": {"coordinates":[-123.705882,39.186857],"type":"Point"}
}