{
  "type": "Feature",
  "properties": {
    "addr:full":"7748 Crossway Dr Pico Rivera CA 90660",
    "addr:housenumber":"7748",
    "addr:postcode":"90660",
    "addr:street":"Crossway Dr",
    "iso:country":"US",
    "sg:address":"7748 Crossway Dr",
    "sg:city":"Pico Rivera",
    "sg:classifiers":[
        {
            "category":"Utilities",
            "subcategory":"Refuse",
            "type":"Services"
        }
    ],
    "sg:phone":"+1 562 942 0712",
    "sg:postcode":"90660",
    "sg:province":"CA",
    "sg:tags":[
        "system"
    ],
    "wof:name":"CA Recycling Center",
    "wof:placetype":"venue"
},
  "geometry": {"coordinates":[-118.10810499999999,33.973519],"type":"Point"}
}