{
  "type": "Feature",
  "properties": {
    "addr:full":"35111 Newark Blvd Newark CA 94560",
    "addr:housenumber":"35111",
    "addr:postcode":"94560",
    "addr:street":"Newark Blvd",
    "iso:country":"US",
    "sg:address":"35111 Newark Blvd",
    "sg:city":"Newark",
    "sg:classifiers":[
        {
            "category":"Building & Trades",
            "subcategory":"Pest Control",
            "type":"Services"
        }
    ],
    "sg:phone":"+1 510 791 0649",
    "sg:postcode":"94560",
    "sg:province":"CA",
    "wof:name":"Windoms Pest Specialist",
    "wof:placetype":"venue"
},
  "geometry": {"coordinates":[-122.046097,37.548781],"type":"Point"}
}