{
  "type": "Feature",
  "properties": {
    "addr:full":"10625 Vanowen St Burbank CA 91605",
    "addr:housenumber":"10625",
    "addr:postcode":"91605",
    "addr:street":"Vanowen St",
    "iso:country":"US",
    "sg:address":"10625 Vanowen St",
    "sg:city":"Burbank",
    "sg:classifiers":[
        {
            "category":"Wholesale",
            "subcategory":"Auto Parts",
            "type":"Manufacturing & Wholesale Goods"
        }
    ],
    "sg:phone":"+1 818 506 4445",
    "sg:postcode":"91605",
    "sg:province":"CA",
    "sg:tags":[
        "equipment",
        "truck"
    ],
    "wof:name":"Fleet Pride Inc",
    "wof:placetype":"venue"
},
  "geometry": {"coordinates":[-118.362422,34.194033],"type":"Point"}
}