{
  "type": "Feature",
  "properties": {
    "addr:full":"963 Linden Ave Carpinteria CA 93013",
    "addr:housenumber":"963",
    "addr:postcode":"93013",
    "addr:street":"Linden Ave",
    "iso:country":"US",
    "sg:address":"963 Linden Ave",
    "sg:city":"Carpinteria",
    "sg:classifiers":[
        {
            "category":"Arts & Performance",
            "subcategory":"Art Gallery",
            "type":"Entertainment"
        }
    ],
    "sg:phone":"+1 805 220 6264",
    "sg:postcode":"93013",
    "sg:province":"CA",
    "wof:name":"Chalk Gallery",
    "wof:placetype":"venue"
},
  "geometry": {"coordinates":[-119.518738,34.398803],"type":"Point"}
}