{
  "type": "Feature",
  "properties": {
    "iso:country":"US",
    "sg:address":"260 S Imperial Ave",
    "sg:city":"Imperial",
    "sg:classifiers":[
        {
            "category":"Professional",
            "type":"Services"
        }
    ],
    "sg:phone":"+1 760 355 2476",
    "sg:postcode":"92251",
    "sg:province":"CA",
    "sg:tags":[
        "establishment"
    ],
    "wof:name":"Raspados Cuchis Imperial",
    "wof:placetype":"venue"
},
  "geometry": {"coordinates":[-115.56989299999999,32.84629],"type":"Point"}
}