{
  "type": "Feature",
  "properties": {
    "iso:country":"US",
    "sg:address":"12234 Hesperia Rd",
    "sg:city":"Victorville",
    "sg:classifiers":[
        {
            "category":"Recreation",
            "type":"Entertainment"
        }
    ],
    "sg:phone":"+1 760 245 2910",
    "sg:postcode":"92395",
    "sg:province":"CA",
    "sg:tags":[
        "bingo",
        "game"
    ],
    "wof:name":"Community Bingo Hall",
    "wof:placetype":"venue"
},
  "geometry": {"coordinates":[-117.291973,34.470954],"type":"Point"}
}