{
  "type": "Feature",
  "properties": {
    "addr:full":"39200 Fremont Blvd Fremont CA 94538",
    "addr:housenumber":"39200",
    "addr:postcode":"94538",
    "addr:street":"Fremont Blvd",
    "iso:country":"US",
    "sg:address":"39200 Fremont Blvd",
    "sg:city":"Fremont",
    "sg:classifiers":[
        {
            "category":"Restaurant",
            "type":"Food & Drink"
        }
    ],
    "sg:phone":"+1 510 713 0706",
    "sg:postcode":"94538",
    "sg:province":"CA",
    "wof:name":"Ancestros Mexican Bar & Grill",
    "wof:placetype":"venue"
},
  "geometry": {"coordinates":[-121.988179,37.548542],"type":"Point"}
}