{
  "type": "Feature",
  "properties": {
    "iso:country":"US",
    "sg:address":"2814 Rex Ave",
    "sg:city":"Bakersfield",
    "sg:classifiers":[
        {
            "category":"Home & Garden",
            "subcategory":"Garden Supply",
            "type":"Retail Goods"
        }
    ],
    "sg:phone":"+1 661 392 0800",
    "sg:postcode":"93304",
    "sg:province":"CA",
    "sg:tags":[
        "sprinkler"
    ],
    "wof:name":"Ron Dunham Enterprises",
    "wof:placetype":"venue"
},
  "geometry": {"coordinates":[-119.034024,35.326465],"type":"Point"}
}