{
  "type": "Feature",
  "properties": {
    "iso:country":"US",
    "sg:address":"7939 Silverton Ave",
    "sg:city":"San Diego",
    "sg:classifiers":[
        {
            "category":"Building & Trades",
            "subcategory":"Electrical",
            "type":"Services"
        }
    ],
    "sg:phone":"+1 858 695 3416",
    "sg:postcode":"92126",
    "sg:province":"CA",
    "sg:tags":[
        "electric",
        "contractor"
    ],
    "wof:name":"Allstate Electric",
    "wof:placetype":"venue"
},
  "geometry": {"coordinates":[-117.153288,32.890832],"type":"Point"}
}