{
  "type": "Feature",
  "properties": {
    "addr:full":"325 Boyd St Los Angeles CA 90013",
    "addr:housenumber":"325",
    "addr:postcode":"90013",
    "addr:street":"Boyd St",
    "iso:country":"US",
    "sg:address":"325 Boyd St",
    "sg:city":"Los Angeles",
    "sg:classifiers":[
        {
            "category":"Shopping",
            "subcategory":"Luggage & Leather Goods",
            "type":"Retail Goods"
        }
    ],
    "sg:phone":"+1 213 680 0021",
    "sg:postcode":"90013",
    "sg:province":"CA",
    "wof:name":"All Leather Imports",
    "wof:placetype":"venue"
},
  "geometry": {"coordinates":[-118.242994,34.046878],"type":"Point"}
}