{
  "type": "Feature",
  "properties": {
    "addr:full":"280 Hemsted Dr Redding CA 96002",
    "addr:housenumber":"280",
    "addr:postcode":"96002",
    "addr:street":"Hemsted Dr",
    "iso:country":"US",
    "sg:address":"280 Hemsted Dr",
    "sg:city":"Redding",
    "sg:classifiers":[
        {
            "category":"Real Estate",
            "subcategory":"Real Estate Services",
            "type":"Services"
        },
        {
            "category":"Banks & Credit Unions",
            "subcategory":"Financial Services",
            "type":"Services"
        }
    ],
    "sg:phone":"+1 530 226 1490",
    "sg:postcode":"96002",
    "sg:province":"CA",
    "sg:tags":[
        "financing",
        "loan",
        "mortgage"
    ],
    "wof:name":"Home Loan Experts",
    "wof:placetype":"venue"
},
  "geometry": {"coordinates":[-122.367637,40.572998],"type":"Point"}
}