{
  "type": "Feature",
  "properties": {
    "iso:country":"US",
    "sg:address":"122 Paul Dr",
    "sg:city":"San Rafael",
    "sg:classifiers":[
        {
            "category":"Retail",
            "subcategory":"Auto Repair",
            "type":"Services"
        }
    ],
    "sg:phone":"+1 415 472 2886",
    "sg:postcode":"94903",
    "sg:province":"CA",
    "sg:tags":[
        "repairing",
        "automobile"
    ],
    "wof:name":"Taylor Automotive",
    "wof:placetype":"venue"
},
  "geometry": {"coordinates":[-122.536813,38.019445],"type":"Point"}
}