{
  "type": "Feature",
  "properties": {
    "iso:country":"US",
    "sg:address":"22421 El Toro Rd",
    "sg:city":"Lake Forest",
    "sg:classifiers":[
        {
            "category":"Retail",
            "subcategory":"Veterinary Services",
            "type":"Services"
        }
    ],
    "sg:phone":"+1 949 581 6622",
    "sg:postcode":"92630",
    "sg:province":"CA",
    "sg:tags":[
        "veterinarian"
    ],
    "wof:name":"Bahou David DVM",
    "wof:placetype":"venue"
},
  "geometry": {"coordinates":[-117.672997,33.639],"type":"Point"}
}