{
  "type": "Feature",
  "properties": {
    "addr:full":"737 Diamond St San Francisco CA 94114",
    "addr:housenumber":"737",
    "addr:postcode":"94114",
    "addr:street":"Diamond St",
    "iso:country":"US",
    "sg:address":"737 Diamond St",
    "sg:city":"San Francisco",
    "sg:classifiers":[
        {
            "category":"Restaurant",
            "type":"Food & Drink"
        }
    ],
    "sg:menulink":"http://www.allmenus.com/ca/san-francisco/21092-bacco-ristorante/menu/",
    "sg:phone":"+1 415 282 4969",
    "sg:postcode":"94114",
    "sg:province":"CA",
    "sg:tags":[
        "italian"
    ],
    "wof:name":"Bacco Ristorante",
    "wof:placetype":"venue"
},
  "geometry": {"coordinates":[-122.43637099999999,37.751678],"type":"Point"}
}