{
  "type": "Feature",
  "properties": {
    "addr:full":"149 Bluxome St San Francisco CA 94107",
    "addr:postcode":"94107",
    "addr:street":"Bluxome St",
    "iso:country":"US",
    "sg:address":"149 Bluxome St",
    "sg:city":"San Francisco",
    "sg:classifiers":[
        {
            "category":"Manufacturing",
            "subcategory":"Apparel",
            "type":"Manufacturing & Wholesale Goods"
        }
    ],
    "sg:phone":"+1 415 241 9268",
    "sg:postcode":"94107",
    "sg:province":"CA",
    "sg:tags":[
        "sewing",
        "contractor"
    ],
    "wof:name":"Laurel Garment Factory",
    "wof:placetype":"venue"
},
  "geometry": {"coordinates":[-122.39929100000001,37.774996],"type":"Point"}
}