{
  "type": "Feature",
  "properties": {
    "iso:country":"US",
    "sg:address":"10564 Progress Way",
    "sg:city":"Cypress",
    "sg:classifiers":[
        {
            "category":"Restaurant",
            "type":"Food & Drink"
        }
    ],
    "sg:phone":"+1 714 827 3730",
    "sg:postcode":"90630",
    "sg:province":"CA",
    "sg:tags":[
        "eating"
    ],
    "wof:name":"McDonalds",
    "wof:placetype":"venue"
},
  "geometry": {"coordinates":[-118.035515,33.809564],"type":"Point"}
}