{
  "type": "Feature",
  "properties": {
    "addr:full":"930 San Benito St Hollister CA 95023",
    "addr:housenumber":"930",
    "addr:postcode":"hollister ca 95023",
    "addr:street":"San Benito St",
    "iso:country":"US",
    "sg:address":"930 San Benito St",
    "sg:city":"Hollister",
    "sg:classifiers":[
        {
            "category":"Professional",
            "subcategory":"Engineering",
            "type":"Services"
        }
    ],
    "sg:phone":"+1 831 638 9260",
    "sg:postcode":"95023",
    "sg:province":"CA",
    "sg:tags":[
        "engineer"
    ],
    "wof:name":"Pinnacle Traffic Engineering",
    "wof:placetype":"venue"
},
  "geometry": {"coordinates":[-121.402396,36.846041],"type":"Point"}
}