{
  "type": "Feature",
  "properties": {
    "addr:full":"41146 Elm St Murrieta CA 92562",
    "addr:housenumber":"41146",
    "addr:postcode":"92562",
    "addr:street":"Elm St",
    "iso:country":"US",
    "sg:address":"41146 Elm St",
    "sg:city":"Murrieta",
    "sg:classifiers":[
        {
            "category":"Building & Trades",
            "subcategory":"Construction",
            "type":"Services"
        }
    ],
    "sg:phone":"+1 951 696 5387",
    "sg:postcode":"92562",
    "sg:province":"CA",
    "sg:tags":[
        "general",
        "contractor"
    ],
    "wof:name":"David Breseden Construction",
    "wof:placetype":"venue"
},
  "geometry": {"coordinates":[-117.176922,33.53774],"type":"Point"}
}