{
  "type": "Feature",
  "properties": {
    "iso:country":"US",
    "sg:address":"18 Urbano Dr",
    "sg:city":"San Francisco",
    "sg:classifiers":[
        {
            "category":"Professional",
            "subcategory":"Business Services",
            "type":"Services"
        }
    ],
    "sg:phone":"+1 415 584 4000",
    "sg:postcode":"94127",
    "sg:province":"CA",
    "sg:tags":[
        "interior",
        "consultant",
        "design",
        "decorator"
    ],
    "wof:name":"Spirited Spaces Design Conslnt",
    "wof:placetype":"venue"
},
  "geometry": {"coordinates":[-122.463252,37.724635],"type":"Point"}
}