{
  "type": "Feature",
  "properties": {
    "addr:full":"11001 Chapman Ave Garden Grove CA 92840",
    "addr:housenumber":"11001",
    "addr:postcode":"92840",
    "addr:street":"Chapman Ave",
    "iso:country":"US",
    "sg:address":"11001 Chapman Ave",
    "sg:city":"Garden Grove",
    "sg:classifiers":[
        {
            "category":"Coffee & Tea",
            "type":"Food & Drink"
        }
    ],
    "sg:phone":"+1 714 638 1716",
    "sg:postcode":"92840",
    "sg:province":"CA",
    "sg:website":"www.starbucks.com",
    "wof:name":"Starbucks Coffee",
    "wof:placetype":"venue"
},
  "geometry": {"coordinates":[-117.931,33.784698],"type":"Point"}
}