{
  "type": "Feature",
  "properties": {
    "iso:country":"US",
    "sg:address":"5324 Wilshire Blvd",
    "sg:city":"Los Angeles",
    "sg:classifiers":[
        {
            "category":"Professional",
            "subcategory":"Lawyer & Legal Services",
            "type":"Services"
        }
    ],
    "sg:phone":"+1 323 937 2311",
    "sg:postcode":"90036",
    "sg:province":"CA",
    "sg:tags":[
        "divorce",
        "law",
        "family"
    ],
    "wof:name":"CottO Robert",
    "wof:placetype":"venue"
},
  "geometry": {"coordinates":[-118.344471,34.203919],"type":"Point"}
}