{
  "type": "Feature",
  "properties": {
    "addr:full":"628 N Market Blvd Sacramento CA 95834",
    "addr:housenumber":"628",
    "addr:postcode":"95834",
    "addr:street":"N Market Blvd",
    "iso:country":"US",
    "sg:address":"628 N Market Blvd",
    "sg:city":"Sacramento",
    "sg:classifiers":[
        {
            "category":"Social Services",
            "subcategory":"Job Training",
            "type":"Services"
        }
    ],
    "sg:phone":"+1 916 929 0134",
    "sg:postcode":"95834",
    "sg:province":"CA",
    "sg:tags":[
        "rehabilitation"
    ],
    "wof:name":"Mc Elroy Vocational Consul",
    "wof:placetype":"venue"
},
  "geometry": {"coordinates":[-121.476895,38.647244],"type":"Point"}
}