{
  "type": "Feature",
  "properties": {
    "iso:country":"US",
    "sg:address":"820 W A St",
    "sg:city":"Hayward",
    "sg:classifiers":[
        {
            "category":"Freight",
            "type":"Transportation"
        }
    ],
    "sg:phone":"+1 510 301 6974",
    "sg:postcode":"94541",
    "sg:province":"CA",
    "sg:tags":[
        "operator",
        "local",
        "trucking"
    ],
    "wof:name":"R&P Trucking",
    "wof:placetype":"venue"
},
  "geometry": {"coordinates":[-122.113742,37.665937],"type":"Point"}
}