{
  "type": "Feature",
  "properties": {
    "addr:full":"600 San Pablo Ave Albany CA 94706",
    "addr:housenumber":"600",
    "addr:postcode":"94706",
    "addr:street":"San Pablo Ave",
    "iso:country":"US",
    "sg:address":"600 San Pablo Ave",
    "sg:city":"Albany",
    "sg:classifiers":[
        {
            "category":"Professional",
            "subcategory":"Management & Consulting",
            "type":"Services"
        }
    ],
    "sg:phone":"+1 510 526 1860",
    "sg:postcode":"94706",
    "sg:province":"CA",
    "sg:tags":[
        "international",
        "business"
    ],
    "wof:name":"Sunrise International",
    "wof:placetype":"venue"
},
  "geometry": {"coordinates":[-122.30059300000001,37.895043],"type":"Point"}
}