{
  "type": "Feature",
  "properties": {
    "addr:full":"1320 Broadway Placerville CA 95667",
    "addr:housenumber":"1320",
    "addr:postcode":"95667",
    "addr:street":"Broadway",
    "iso:country":"US",
    "sg:address":"1320 Broadway",
    "sg:city":"Placerville",
    "sg:classifiers":[
        {
            "category":"Restaurant",
            "type":"Food & Drink"
        }
    ],
    "sg:phone":"+1 530 622 7125",
    "sg:postcode":"95667",
    "sg:province":"CA",
    "wof:name":"Shoestring",
    "wof:placetype":"venue"
},
  "geometry": {"coordinates":[-120.783704,38.731603],"type":"Point"}
}