{
  "type": "Feature",
  "properties": {
    "addr:full":"601 Coeur D Alene Ave Venice CA 90291",
    "addr:housenumber":"601",
    "addr:postcode":"90291",
    "addr:street":"Coeur D Alene Ave",
    "iso:country":"US",
    "sg:address":"601 Coeur D Alene Ave",
    "sg:city":"Venice",
    "sg:classifiers":[
        {
            "category":"Real Estate",
            "subcategory":"Real Estate Agent",
            "type":"Services"
        }
    ],
    "sg:phone":"+1 310 448 1894",
    "sg:postcode":"90291",
    "sg:province":"CA",
    "wof:name":"Southland Title Corp",
    "wof:placetype":"venue"
},
  "geometry": {"coordinates":[-118.453703,33.989747],"type":"Point"}
}