{
  "type": "Feature",
  "properties": {
    "addr:full":"1315 E Saint Andrew Pl Ste A Santa Ana CA 92705",
    "addr:housenumber":"1315",
    "addr:postcode":"92705",
    "addr:street":"E Saint Andrew Pl Ste A",
    "iso:country":"US",
    "sg:address":"1315 E Saint Andrew Pl Ste A",
    "sg:city":"Santa Ana",
    "sg:classifiers":[
        {
            "category":"Building & Trades",
            "subcategory":"Construction",
            "type":"Services"
        }
    ],
    "sg:phone":"+1 714 641 7380",
    "sg:postcode":"92705",
    "sg:province":"CA",
    "sg:tags":[
        "painter"
    ],
    "sg:website":"www.pacificrimcontractors.com",
    "wof:name":"Pacific Rim Contractors Inc",
    "wof:placetype":"venue"
},
  "geometry": {"coordinates":[-117.852997,33.723],"type":"Point"}
}