{
  "type": "Feature",
  "properties": {
    "addr:full":"23916 Lyons Ave Newhall CA 91321",
    "addr:housenumber":"23916",
    "addr:postcode":"91321",
    "addr:street":"Lyons Ave",
    "iso:country":"US",
    "sg:address":"23916 Lyons Ave",
    "sg:city":"Newhall",
    "sg:classifiers":[
        {
            "category":"Real Estate",
            "subcategory":"Real Estate Agent",
            "type":"Services"
        }
    ],
    "sg:phone":"+1 661 259 9723",
    "sg:postcode":"91321",
    "sg:province":"CA",
    "sg:tags":[
        "notary"
    ],
    "sg:website":"www.sellinghomes1-2-3.com",
    "wof:name":"Bob Boog Realty",
    "wof:placetype":"venue"
},
  "geometry": {"coordinates":[-118.552002,34.379101],"type":"Point"}
}