{
  "type": "Feature",
  "properties": {
    "iso:country":"US",
    "sg:address":"16209 Minnesota Ave",
    "sg:city":"Paramount",
    "sg:classifiers":[
        {
            "category":"Wholesale",
            "subcategory":"Machinery & Supplies",
            "type":"Manufacturing & Wholesale Goods"
        }
    ],
    "sg:phone":"+1 562 634 6425",
    "sg:postcode":"90723",
    "sg:province":"CA",
    "sg:tags":[
        "pipe",
        "fitting"
    ],
    "wof:name":"Columbia Specialty Co",
    "wof:placetype":"venue"
},
  "geometry": {"coordinates":[-118.166702,33.885466],"type":"Point"}
}