{
  "type": "Feature",
  "properties": {
    "addr:full":"43095 Whittenburg Rd Oakhurst CA 93644",
    "addr:postcode":"43095;93644",
    "addr:street":"Whittenburg Rd",
    "iso:country":"US",
    "sg:address":"43095 Whittenburg Rd",
    "sg:city":"Oakhurst",
    "sg:classifiers":[
        {
            "category":"Professional",
            "subcategory":"Management & Consulting",
            "type":"Services"
        }
    ],
    "sg:phone":"+1 559 658 2722",
    "sg:postcode":"93644",
    "sg:province":"CA",
    "wof:name":"Bmp Service",
    "wof:placetype":"venue"
},
  "geometry": {"coordinates":[-119.63698100000001,37.377036],"type":"Point"}
}