{
  "type": "Feature",
  "properties": {
    "addr:full":"27772 Homestead Rd Laguna Niguel CA 92677",
    "addr:housenumber":"27772",
    "addr:postcode":"92677",
    "addr:street":"Homestead Rd",
    "iso:country":"US",
    "sg:address":"27772 Homestead Rd",
    "sg:city":"Laguna Niguel",
    "sg:classifiers":[
        {
            "category":"Professional",
            "type":"Services"
        }
    ],
    "sg:phone":"+1 949 643 0991",
    "sg:postcode":"92677",
    "sg:province":"CA",
    "wof:name":"Amy C Schaefer",
    "wof:placetype":"venue"
},
  "geometry": {"coordinates":[-117.69839,33.563992],"type":"Point"}
}