{
  "type": "Feature",
  "properties": {
    "iso:country":"US",
    "sg:address":"19528 Ventura Blvd",
    "sg:city":"Tarzana",
    "sg:classifiers":[
        {
            "category":"Local Transit",
            "type":"Transportation"
        }
    ],
    "sg:phone":"+1 818 776 0815",
    "sg:postcode":"91356",
    "sg:province":"CA",
    "sg:tags":[
        "ambulance"
    ],
    "wof:name":"World Transport Non Emergency",
    "wof:placetype":"venue"
},
  "geometry": {"coordinates":[-118.559441,34.17273],"type":"Point"}
}