{
  "type": "Feature",
  "properties": {
    "iso:country":"US",
    "sg:address":"611 Cherry Creek Rd",
    "sg:city":"Cloverdale",
    "sg:classifiers":[
        {
            "category":"Social Services",
            "subcategory":"Adult Care",
            "type":"Services"
        }
    ],
    "sg:phone":"+1 707 894 4615",
    "sg:postcode":"95425",
    "sg:province":"CA",
    "sg:tags":[
        "home",
        "residential"
    ],
    "wof:name":"Clearwater Lodge",
    "wof:placetype":"venue"
},
  "geometry": {"coordinates":[-123.033941,38.797149],"type":"Point"}
}