{
  "type": "Feature",
  "properties": {
    "iso:country":"US",
    "sg:address":"750 N Broadway",
    "sg:city":"Los Angeles",
    "sg:classifiers":[
        {
            "category":"Wholesale",
            "subcategory":"Meat",
            "type":"Manufacturing & Wholesale Goods"
        }
    ],
    "sg:phone":"+1 213 628 7645",
    "sg:postcode":"90012",
    "sg:province":"CA",
    "sg:tags":[
        "poultry",
        "plant",
        "processing"
    ],
    "wof:name":"Superior Poultry Co",
    "wof:placetype":"venue"
},
  "geometry": {"coordinates":[-118.238663,34.061288],"type":"Point"}
}