{
  "type": "Feature",
  "properties": {
    "addr:full":"2191 Niles St Bakersfield CA 93305",
    "addr:housenumber":"2191",
    "addr:postcode":"93305",
    "addr:street":"Niles St",
    "iso:country":"US",
    "sg:address":"2191 Niles St",
    "sg:city":"Bakersfield",
    "sg:classifiers":[
        {
            "category":"Shopping",
            "subcategory":"Pharmacy",
            "type":"Retail Goods"
        }
    ],
    "sg:phone":"+1 661 327 4248",
    "sg:postcode":"93305",
    "sg:province":"CA",
    "wof:name":"United Drugs",
    "wof:placetype":"venue"
},
  "geometry": {"coordinates":[-118.967601,35.376415],"type":"Point"}
}