{
  "type": "Feature",
  "properties": {
    "addr:full":"3322 E Chapman Ave Orange CA 92869",
    "addr:housenumber":"3322",
    "addr:postcode":"92869",
    "addr:street":"E Chapman Ave",
    "iso:country":"US",
    "sg:address":"3322 E Chapman Ave",
    "sg:city":"Orange",
    "sg:classifiers":[
        {
            "category":"Restaurant",
            "type":"Food & Drink"
        }
    ],
    "sg:phone":"+1 714 221 8674",
    "sg:postcode":"92869",
    "sg:province":"CA",
    "sg:tags":[
        "breakfast",
        "brunch"
    ],
    "sg:website":"www.originalpancakehouse.com/",
    "wof:name":"The Original Pancake House",
    "wof:placetype":"venue"
},
  "geometry": {"coordinates":[-117.818063,33.787788],"type":"Point"}
}