{
  "type": "Feature",
  "properties": {
    "iso:country":"US",
    "sg:address":"2865 Mission St",
    "sg:city":"San Francisco",
    "sg:classifiers":[
        {
            "category":"Shopping",
            "subcategory":"Gifts & Souvenirs",
            "type":"Retail Goods"
        }
    ],
    "sg:phone":"+1 415 824 4188",
    "sg:postcode":"94110",
    "sg:province":"CA",
    "wof:name":"W & W Gift Shop",
    "wof:placetype":"venue"
},
  "geometry": {"coordinates":[-122.418294,37.751689],"type":"Point"}
}