{
  "type": "Feature",
  "properties": {
    "iso:country":"US",
    "sg:address":"1377 Kern St",
    "sg:city":"Taft",
    "sg:classifiers":[
        {
            "category":"Building & Trades",
            "subcategory":"Construction",
            "type":"Services"
        }
    ],
    "sg:phone":"+1 661 763 4187",
    "sg:postcode":"93268",
    "sg:province":"CA",
    "sg:tags":[
        "underground",
        "trenching",
        "contractor"
    ],
    "wof:name":"KERN Backhoe Svc Inc",
    "wof:placetype":"venue"
},
  "geometry": {"coordinates":[-119.469492,35.146211],"type":"Point"}
}