{
  "type": "Feature",
  "properties": {
    "iso:country":"US",
    "sg:address":"993 Center St",
    "sg:city":"Riverside",
    "sg:classifiers":[
        {
            "category":"Restaurant",
            "type":"Food & Drink"
        }
    ],
    "sg:phone":"+1 951 328 9331",
    "sg:postcode":"92507",
    "sg:province":"CA",
    "wof:name":"Mi Lindo Mihon",
    "wof:placetype":"venue"
},
  "geometry": {"coordinates":[-117.332933,34.015827],"type":"Point"}
}