{
  "type": "Feature",
  "properties": {
    "iso:country":"US",
    "sg:address":"1045 E South St",
    "sg:city":"Long Beach",
    "sg:classifiers":[
        {
            "category":"Food & Beverages",
            "subcategory":"Liquor & Beverages",
            "type":"Retail Goods"
        }
    ],
    "sg:phone":"+1 562 422 6299",
    "sg:postcode":"90805",
    "sg:province":"CA",
    "sg:tags":[
        "beer",
        "spirit",
        "wine"
    ],
    "wof:name":"Lucky Liquor Market",
    "wof:placetype":"venue"
},
  "geometry": {"coordinates":[-118.179917,33.860363],"type":"Point"}
}