{
  "type": "Feature",
  "properties": {
    "iso:country":"US",
    "sg:address":"295 Pine Breeze Dr",
    "sg:city":"Angwin",
    "sg:classifiers":[
        {
            "category":"Health Services",
            "subcategory":"Hospital",
            "type":"Services"
        }
    ],
    "sg:phone":"+1 707 965 2461",
    "sg:postcode":"94508",
    "sg:province":"CA",
    "sg:tags":[
        "mental"
    ],
    "wof:name":"Crestwood Center",
    "wof:placetype":"venue"
},
  "geometry": {"coordinates":[-122.455665,38.560907],"type":"Point"}
}