{
  "type": "Feature",
  "properties": {
    "addr:full":"27720 Jefferson Ave Temecula CA 92590",
    "addr:housenumber":"27720",
    "addr:postcode":"92590",
    "addr:street":"Jefferson Ave",
    "iso:country":"US",
    "sg:address":"27720 Jefferson Ave",
    "sg:city":"Temecula",
    "sg:classifiers":[
        {
            "category":"Real Estate",
            "subcategory":"Real Estate Agent",
            "type":"Services"
        }
    ],
    "sg:phone":"+1 951 695 0500",
    "sg:postcode":"92590",
    "sg:province":"CA",
    "sg:website":"www.lee-associates.com",
    "wof:name":"Lee & Assoc",
    "wof:placetype":"venue"
},
  "geometry": {"coordinates":[-117.157922,33.511269],"type":"Point"}
}