{
  "type": "Feature",
  "properties": {
    "addr:full":"54 Cam de Herrera San Anselmo CA 94960",
    "addr:housenumber":"54",
    "addr:postcode":"94960",
    "addr:street":"Cam De Herrera",
    "iso:country":"US",
    "sg:address":"54 Cam de Herrera",
    "sg:city":"San Anselmo",
    "sg:classifiers":[
        {
            "category":"Building & Trades",
            "subcategory":"Construction",
            "type":"Services"
        }
    ],
    "sg:phone":"+1 415 256 8373",
    "sg:postcode":"94960",
    "sg:province":"CA",
    "sg:tags":[
        "contractor"
    ],
    "wof:name":"Howes & Co",
    "wof:placetype":"venue"
},
  "geometry": {"coordinates":[-122.580748,37.991007],"type":"Point"}
}