{
  "type": "Feature",
  "properties": {
    "iso:country":"US",
    "sg:address":"631 W Pine St",
    "sg:city":"Bishop",
    "sg:classifiers":[
        {
            "category":"Building & Trades",
            "subcategory":"Construction",
            "type":"Services"
        }
    ],
    "sg:phone":"+1 760 873 3116",
    "sg:postcode":"93514",
    "sg:province":"CA",
    "sg:tags":[
        "excavation",
        "contractor"
    ],
    "wof:name":"Galvin Landscaping",
    "wof:placetype":"venue"
},
  "geometry": {"coordinates":[-118.401164,37.363848],"type":"Point"}
}