{
  "type": "Feature",
  "properties": {
    "addr:full":"609 40th St Sacramento CA 95819",
    "addr:housenumber":"609",
    "addr:postcode":"95819",
    "addr:street":"40Th St",
    "iso:country":"US",
    "sg:address":"609 40th St",
    "sg:city":"Sacramento",
    "sg:classifiers":[
        {
            "category":"Professional",
            "type":"Services"
        }
    ],
    "sg:phone":"+1 916 374 3695",
    "sg:postcode":"95819",
    "sg:province":"CA",
    "wof:name":"Susan L Brill Lehn",
    "wof:placetype":"venue"
},
  "geometry": {"coordinates":[-121.45102300000001,38.572724],"type":"Point"}
}