{
  "type": "Feature",
  "properties": {
    "iso:country":"US",
    "sg:address":"609 40th St",
    "sg:city":"Sacramento",
    "sg:classifiers":[
        {
            "category":"Professional",
            "type":"Services"
        }
    ],
    "sg:phone":"+1 916 374 3695",
    "sg:postcode":"95819",
    "sg:province":"CA",
    "wof:name":"Susan L Brill Lehn",
    "wof:placetype":"venue"
},
  "geometry": {"coordinates":[-121.451023,38.572724],"type":"Point"}
}