{
  "type": "Feature",
  "properties": {
    "iso:country":"US",
    "sg:address":"3765 Jurupa Ave",
    "sg:city":"Riverside",
    "sg:phone":"+1 951 684 7077",
    "sg:postcode":"92506",
    "sg:province":"CA",
    "wof:name":"Axis Business Solutions",
    "wof:placetype":"venue"
},
  "geometry": {"coordinates":[-117.39063299999999,33.960941],"type":"Point"}
}