{
  "type": "Feature",
  "properties": {
    "iso:country":"US",
    "sg:address":"5542 Buckingham Dr",
    "sg:city":"Huntington Beach",
    "sg:classifiers":[
        {
            "category":"Manufacturing",
            "subcategory":"Glass & Minerals",
            "type":"Manufacturing & Wholesale Goods"
        }
    ],
    "sg:phone":"+1 714 373 8305",
    "sg:postcode":"92649",
    "sg:province":"CA",
    "sg:tags":[
        "art"
    ],
    "wof:name":"August Art Co",
    "wof:placetype":"venue"
},
  "geometry": {"coordinates":[-118.032407,33.743471],"type":"Point"}
}