{
  "type": "Feature",
  "properties": {
    "addr:full":"8800 Long Beach Blvd South Gate CA 90280",
    "addr:housenumber":"8800",
    "addr:postcode":"90280",
    "addr:street":"Long Beach Blvd;Gate",
    "iso:country":"US",
    "sg:address":"8800 Long Beach Blvd",
    "sg:city":"South Gate",
    "sg:classifiers":[
        {
            "category":"Retail",
            "subcategory":"Car Wash",
            "type":"Services"
        }
    ],
    "sg:phone":"+1 323 569 0841",
    "sg:postcode":"90280",
    "sg:province":"CA",
    "wof:name":"Magic Wand Car Wash",
    "wof:placetype":"venue"
},
  "geometry": {"coordinates":[-118.221001,33.956299],"type":"Point"}
}