{
  "type": "Feature",
  "properties": {
    "iso:country":"US",
    "sg:address":"648 W Williamson Ave",
    "sg:city":"Fullerton",
    "sg:classifiers":[
        {
            "category":"Retail",
            "subcategory":"Auto Repair",
            "type":"Services"
        }
    ],
    "sg:phone":"+1 714 680 8809",
    "sg:postcode":"92832",
    "sg:province":"CA",
    "wof:name":"Sal's Auto Service",
    "wof:placetype":"venue"
},
  "geometry": {"coordinates":[-117.937539,33.869193],"type":"Point"}
}