{
  "type": "Feature",
  "properties": {
    "addr:full":"2527 Beverly Ave Clovis CA 93611",
    "addr:housenumber":"2527",
    "addr:postcode":"93611",
    "addr:street":"Beverly Ave",
    "iso:country":"US",
    "sg:address":"2527 Beverly Ave",
    "sg:city":"Clovis",
    "sg:classifiers":[
        {
            "category":"Building & Trades",
            "subcategory":"Construction",
            "type":"Services"
        }
    ],
    "sg:phone":"+1 559 297 4482",
    "sg:postcode":"93611",
    "sg:province":"CA",
    "sg:tags":[
        "tile",
        "dealer"
    ],
    "wof:name":"Barboza Tile Co",
    "wof:placetype":"venue"
},
  "geometry": {"coordinates":[-119.66522399999999,36.812592],"type":"Point"}
}