{
  "type": "Feature",
  "properties": {
    "addr:full":"276 S Atlantic Blvd Los Angeles CA 90022",
    "addr:housenumber":"276",
    "addr:postcode":"90022",
    "addr:street":"S Atlantic Blvd",
    "iso:country":"US",
    "sg:address":"276 S Atlantic Blvd",
    "sg:city":"Los Angeles",
    "sg:classifiers":[
        {
            "category":"Banks & Credit Unions",
            "subcategory":"Bank",
            "type":"Services"
        }
    ],
    "sg:phone":"+1 323 526 1000",
    "sg:postcode":"90022",
    "sg:province":"CA",
    "sg:tags":[
        "loan"
    ],
    "wof:name":"Z F Lending",
    "wof:placetype":"venue"
},
  "geometry": {"coordinates":[-118.152953,34.032819],"type":"Point"}
}