{
  "type": "Feature",
  "properties": {
    "iso:country":"US",
    "sg:address":"6916 Claire Ave",
    "sg:city":"Reseda",
    "sg:classifiers":[
        {
            "category":"Building & Trades",
            "subcategory":"Plumbing",
            "type":"Services"
        }
    ],
    "sg:phone":"+1 818 609 8912",
    "sg:postcode":"91335",
    "sg:province":"CA",
    "sg:tags":[
        "conditioning",
        "air",
        "system",
        "contractor"
    ],
    "wof:name":"Jon Abroghimoff",
    "wof:placetype":"venue"
},
  "geometry": {"coordinates":[-118.549995,34.196191],"type":"Point"}
}