{
  "type": "Feature",
  "properties": {
    "addr:full":"1424 N Vagedes Ave Fresno CA 93728",
    "addr:housenumber":"1424",
    "addr:postcode":"93728",
    "addr:street":"N Vagedes Ave",
    "iso:country":"US",
    "sg:address":"1424 N Vagedes Ave",
    "sg:city":"Fresno",
    "sg:classifiers":[
        {
            "category":"Wholesale",
            "subcategory":"Vending Machines",
            "type":"Manufacturing & Wholesale Goods"
        }
    ],
    "sg:phone":"+1 559 494 0470",
    "sg:postcode":"93728",
    "sg:province":"CA",
    "sg:tags":[
        "operator"
    ],
    "wof:name":"Johnsons Vending",
    "wof:placetype":"venue"
},
  "geometry": {"coordinates":[-119.81644799999999,36.762555],"type":"Point"}
}