{
  "type": "Feature",
  "properties": {
    "iso:country":"US",
    "sg:address":"266 S Martin Dr",
    "sg:city":"Zephyr Cove",
    "sg:classifiers":[
        {
            "category":"Building & Trades",
            "subcategory":"Construction",
            "type":"Services"
        }
    ],
    "sg:phone":"+1 775 588 8060",
    "sg:postcode":"89448",
    "sg:province":"CA",
    "sg:tags":[
        "handyman"
    ],
    "wof:name":"Mark Jackson Maintenance",
    "wof:placetype":"venue"
},
  "geometry": {"coordinates":[-119.950746,38.999931],"type":"Point"}
}