{
  "type": "Feature",
  "properties": {
    "addr:full":"4717 University Ave San Diego CA 92105",
    "addr:housenumber":"4717",
    "addr:postcode":"92105",
    "addr:street":"University Ave",
    "iso:country":"US",
    "sg:address":"4717 University Ave",
    "sg:city":"San Diego",
    "sg:classifiers":[
        {
            "category":"Restaurant",
            "type":"Food & Drink"
        }
    ],
    "sg:phone":"+1 619 285 9722",
    "sg:postcode":"92105",
    "sg:province":"CA",
    "sg:tags":[
        "ethiopian"
    ],
    "wof:name":"Red Sea Restaurant",
    "wof:placetype":"venue"
},
  "geometry": {"coordinates":[-117.093002,32.749699],"type":"Point"}
}