{
  "type": "Feature",
  "properties": {
    "iso:country":"US",
    "sg:address":"13762 Jamboree",
    "sg:city":"Irvine",
    "sg:classifiers":[
        {
            "category":"Home & Garden",
            "subcategory":"Furniture",
            "type":"Retail Goods"
        }
    ],
    "sg:phone":"+1 714 734 5777",
    "sg:postcode":"92604",
    "sg:province":"CA",
    "sg:tags":[
        "store"
    ],
    "sg:website":"www.la-z-boy.com/",
    "wof:name":"La-Z-Boy Furniture Galleries",
    "wof:placetype":"venue"
},
  "geometry": {"coordinates":[-117.788528,33.728383],"type":"Point"}
}