{
  "type": "Feature",
  "properties": {
    "addr:full":"2421 190th Street Redondo Beach CA 90278",
    "addr:housenumber":"2421",
    "addr:postcode":"90278",
    "addr:street":"190Th Street",
    "iso:country":"US",
    "sg:address":"2421 190th Street",
    "sg:city":"Redondo Beach",
    "sg:classifiers":[
        {
            "category":"Personal",
            "subcategory":"Nail Salon",
            "type":"Services"
        }
    ],
    "sg:phone":"+1 310 372 5252",
    "sg:postcode":"90278",
    "sg:province":"CA",
    "wof:name":"Sandys Hair Design",
    "wof:placetype":"venue"
},
  "geometry": {"coordinates":[-118.36752199999999,33.858437],"type":"Point"}
}