{
  "type": "Feature",
  "properties": {
    "addr:full":"17631 Sonora Rd Knights Ferry CA 95361",
    "addr:housenumber":"17631",
    "addr:postcode":"95361",
    "addr:street":"Sonora Rd",
    "iso:country":"US",
    "sg:address":"17631 Sonora Rd",
    "sg:city":"Knights Ferry",
    "sg:classifiers":[
        {
            "category":"Social Services",
            "subcategory":"Adult Care",
            "type":"Services"
        }
    ],
    "sg:phone":"+1 209 881 3535",
    "sg:postcode":"95361",
    "sg:province":"CA",
    "sg:tags":[
        "organization",
        "senior",
        "citizen"
    ],
    "wof:name":"Knights Ferry Senior Ctr",
    "wof:placetype":"venue"
},
  "geometry": {"coordinates":[-120.671513,37.819276],"type":"Point"}
}