{
  "type": "Feature",
  "properties": {
    "addr:full":"2931 W Central Ave Santa Ana CA 92704",
    "addr:housenumber":"2931",
    "addr:postcode":"92704",
    "addr:street":"W Central Ave",
    "iso:country":"US",
    "sg:address":"2931 W Central Ave",
    "sg:city":"Santa Ana",
    "sg:classifiers":[
        {
            "category":"Manufacturing",
            "subcategory":"Tools & Machinery",
            "type":"Manufacturing & Wholesale Goods"
        }
    ],
    "sg:phone":"+1 714 662 1550",
    "sg:postcode":"92704",
    "sg:province":"CA",
    "sg:tags":[
        "i",
        "engineering",
        "mfg"
    ],
    "wof:name":"Old Mans Machine Shop",
    "wof:placetype":"venue"
},
  "geometry": {"coordinates":[-117.90896600000001,33.71281],"type":"Point"}
}