{
  "type": "Feature",
  "properties": {
    "iso:country":"US",
    "sg:address":"210 N Avenue 55",
    "sg:city":"Los Angeles",
    "sg:classifiers":[
        {
            "category":"Real Estate",
            "subcategory":"Real Estate Operator",
            "type":"Services"
        }
    ],
    "sg:phone":"+1 323 254 9954",
    "sg:postcode":"90042",
    "sg:province":"CA",
    "sg:tags":[
        "apartment"
    ],
    "wof:name":"Highland Villas",
    "wof:placetype":"venue"
},
  "geometry": {"coordinates":[-118.195999,34.109501],"type":"Point"}
}