{
  "type": "Feature",
  "properties": {
    "addr:full":"4028 Dale Rd Modesto CA 95356",
    "addr:housenumber":"4028",
    "addr:postcode":"ca 95356",
    "addr:street":"Dale Rd",
    "iso:country":"US",
    "sg:address":"4028 Dale Rd",
    "sg:city":"Modesto",
    "sg:classifiers":[
        {
            "category":"Banks & Credit Unions",
            "subcategory":"Investment Brokerage",
            "type":"Services"
        }
    ],
    "sg:phone":"+1 209 545 9610",
    "sg:postcode":"95356",
    "sg:province":"CA",
    "sg:tags":[
        "advisory",
        "financial"
    ],
    "wof:name":"RMH Financial",
    "wof:placetype":"venue"
},
  "geometry": {"coordinates":[-121.049924,37.697225],"type":"Point"}
}