{
  "type": "Feature",
  "properties": {
    "addr:full":"5827 Mission Gorge Rd San Diego CA 92120",
    "addr:housenumber":"5827",
    "addr:postcode":"92120",
    "addr:street":"Mission Gorge Rd",
    "iso:country":"US",
    "sg:address":"5827 Mission Gorge Rd",
    "sg:city":"San Diego",
    "sg:classifiers":[
        {
            "category":"Manufacturing",
            "subcategory":"Printing",
            "type":"Manufacturing & Wholesale Goods"
        }
    ],
    "sg:phone":"+1 619 282 0270",
    "sg:postcode":"92120",
    "sg:province":"CA",
    "sg:tags":[
        "commercial"
    ],
    "wof:name":"Banners Etc",
    "wof:placetype":"venue"
},
  "geometry": {"coordinates":[-117.098879,32.782647],"type":"Point"}
}