{
  "type": "Feature",
  "properties": {
    "iso:country":"US",
    "sg:address":"14321 Imperial Hwy",
    "sg:city":"La Mirada",
    "sg:classifiers":[
        {
            "category":"Autos & Motor Vehicles",
            "subcategory":"Auto Supplies",
            "type":"Retail Goods"
        }
    ],
    "sg:phone":"+1 562 944 3330",
    "sg:postcode":"90638",
    "sg:province":"CA",
    "sg:tags":[
        "tire"
    ],
    "wof:name":"Tire Plus",
    "wof:placetype":"venue"
},
  "geometry": {"coordinates":[-118.024338,33.917139],"type":"Point"}
}