{
  "type": "Feature",
  "properties": {
    "addr:full":"7916 West Ln Stockton CA 95210",
    "addr:housenumber":"7916",
    "addr:postcode":"95210",
    "addr:street":"West Ln",
    "iso:country":"US",
    "sg:address":"7916 West Ln",
    "sg:city":"Stockton",
    "sg:classifiers":[
        {
            "category":"Restaurant",
            "type":"Food & Drink"
        }
    ],
    "sg:phone":"+1 209 957 8701",
    "sg:postcode":"95210",
    "sg:province":"CA",
    "sg:tags":[
        "banquet",
        "rooms"
    ],
    "wof:name":"China Buffet",
    "wof:placetype":"venue"
},
  "geometry": {"coordinates":[-121.294847,38.019292],"type":"Point"}
}