{
  "type": "Feature",
  "properties": {
    "iso:country":"US",
    "sg:address":"3685 Maple Ave",
    "sg:city":"Oakland",
    "sg:classifiers":[
        {
            "category":"Building & Trades",
            "subcategory":"Plumbing",
            "type":"Services"
        }
    ],
    "sg:phone":"+1 510 482 2595",
    "sg:postcode":"94602",
    "sg:province":"CA",
    "sg:tags":[
        "contractor"
    ],
    "wof:name":"AC Holdings",
    "wof:placetype":"venue"
},
  "geometry": {"coordinates":[-122.204232,37.798138],"type":"Point"}
}