{
  "type": "Feature",
  "properties": {
    "addr:full":"6206 Falmouth Dr La Mesa CA 91942",
    "addr:housenumber":"6206",
    "addr:postcode":"91942",
    "addr:street":"Falmouth Dr",
    "iso:country":"US",
    "sg:address":"6206 Falmouth Dr",
    "sg:city":"La Mesa",
    "sg:classifiers":[
        {
            "category":"Shopping",
            "subcategory":"Used Merchandise",
            "type":"Retail Goods"
        }
    ],
    "sg:phone":"+1 619 741 6941",
    "sg:postcode":"91942",
    "sg:province":"CA",
    "wof:name":"Career Mined Clothes",
    "wof:placetype":"venue"
},
  "geometry": {"coordinates":[-116.994114,32.791348],"type":"Point"}
}