{
  "type": "Feature",
  "properties": {
    "iso:country":"US",
    "sg:address":"3001 P St",
    "sg:city":"Sacramento",
    "sg:classifiers":[
        {
            "category":"Health Services",
            "subcategory":"Dentist",
            "type":"Services"
        }
    ],
    "sg:phone":"+1 916 736 6750",
    "sg:postcode":"95816",
    "sg:province":"CA",
    "sg:tags":[
        "orthodontist"
    ],
    "sg:website":"www.sutterterracedental.com",
    "wof:name":"Sutter Terrace Dental Group",
    "wof:placetype":"venue"
},
  "geometry": {"coordinates":[-121.46941700000001,38.566484],"type":"Point"}
}