{
  "type": "Feature",
  "properties": {
    "addr:full":"1446 Lazy Trail Dr Chico CA 95926",
    "addr:housenumber":"1446",
    "addr:postcode":"95926",
    "addr:street":"Lazy Trail Dr",
    "iso:country":"US",
    "sg:address":"1446 Lazy Trail Dr",
    "sg:city":"Chico",
    "sg:classifiers":[
        {
            "category":"Wholesale",
            "subcategory":"Durable Goods & Equipment",
            "type":"Manufacturing & Wholesale Goods"
        }
    ],
    "sg:phone":"+1 530 891 0161",
    "sg:postcode":"95926",
    "sg:province":"CA",
    "sg:tags":[
        "representative",
        "manufacturer"
    ],
    "wof:name":"M C Sport Reps",
    "wof:placetype":"venue"
},
  "geometry": {"coordinates":[-121.869553,39.728288],"type":"Point"}
}