{
  "type": "Feature",
  "properties": {
    "iso:country":"US",
    "sg:address":"1401 N Sepulveda Boulevard",
    "sg:city":"Manhattan Beach",
    "sg:classifiers":[
        {
            "category":"Retail",
            "subcategory":"Veterinary Services",
            "type":"Services"
        }
    ],
    "sg:phone":"+1 310 546 5731",
    "sg:postcode":"90266",
    "sg:province":"CA",
    "sg:tags":[
        "veterinarian"
    ],
    "wof:name":"Willauer Curtis Vmd Acvs",
    "wof:placetype":"venue"
},
  "geometry": {"coordinates":[-118.396213,33.889041],"type":"Point"}
}