{
  "type": "Feature",
  "properties": {
    "iso:country":"US",
    "sg:address":"2369 Barrett Ave",
    "sg:city":"Richmond",
    "sg:classifiers":[
        {
            "category":"Professional",
            "type":"Services"
        }
    ],
    "sg:phone":"+1 510 237 6778",
    "sg:postcode":"94804",
    "sg:province":"CA",
    "sg:tags":[
        "establishment"
    ],
    "wof:name":"Project Genesis",
    "wof:placetype":"venue"
},
  "geometry": {"coordinates":[-122.346114,37.938377],"type":"Point"}
}