{
  "type": "Feature",
  "properties": {
    "addr:full":"15451 Marty Dr Glen Ellen CA 95442",
    "addr:postcode":"15451;95442",
    "addr:street":"Marty Dr",
    "iso:country":"US",
    "sg:address":"15451 Marty Dr",
    "sg:city":"Glen Ellen",
    "sg:classifiers":[
        {
            "category":"Real Estate",
            "subcategory":"Real Estate Operator",
            "type":"Services"
        }
    ],
    "sg:phone":"+1 707 939 9895",
    "sg:postcode":"95442",
    "sg:province":"CA",
    "sg:tags":[
        "building",
        "apartment"
    ],
    "wof:name":"Madrone Apts",
    "wof:placetype":"venue"
},
  "geometry": {"coordinates":[-122.510621,38.340361],"type":"Point"}
}