{
  "type": "Feature",
  "properties": {
    "addr:full":"400 Capitol Mall Ste 1460 Sacramento CA 95814",
    "addr:housenumber":"400",
    "addr:postcode":"95814",
    "addr:street":"Capitol Mall Ste 1460",
    "iso:country":"US",
    "sg:address":"400 Capitol Mall Ste 1460",
    "sg:city":"Sacramento",
    "sg:classifiers":[
        {
            "category":"Professional",
            "subcategory":"Lawyer & Legal Services",
            "type":"Services"
        }
    ],
    "sg:phone":"+1 916 554 0240",
    "sg:postcode":"95814",
    "sg:province":"CA",
    "wof:name":"Locke Lord Bissell & Liddell Lip",
    "wof:placetype":"venue"
},
  "geometry": {"coordinates":[-121.50297999999999,38.578908],"type":"Point"}
}