{
  "type": "Feature",
  "properties": {
    "iso:country":"US",
    "sg:address":"2301 Herndon Ave",
    "sg:city":"Clovis",
    "sg:classifiers":[
        {
            "category":"Wholesale",
            "subcategory":"Machinery & Supplies",
            "type":"Manufacturing & Wholesale Goods"
        }
    ],
    "sg:phone":"+1 559 322 8047",
    "sg:postcode":"93611",
    "sg:province":"CA",
    "sg:tags":[
        "contractor"
    ],
    "wof:name":"Sierra Vista Cast-In-Place",
    "wof:placetype":"venue"
},
  "geometry": {"coordinates":[-119.673678,36.837307],"type":"Point"}
}