{
  "type": "Feature",
  "properties": {
    "iso:country":"US",
    "sg:address":"31285 State Rte 44",
    "sg:city":"Shingletown",
    "sg:classifiers":[
        {
            "category":"Manufacturing",
            "subcategory":"Printing",
            "type":"Manufacturing & Wholesale Goods"
        }
    ],
    "sg:phone":"+1 530 474 4192",
    "sg:postcode":"96088",
    "sg:province":"CA",
    "sg:tags":[
        "poster"
    ],
    "wof:name":"123 Posters",
    "wof:placetype":"venue"
},
  "geometry": {"coordinates":[-121.898577,40.490887],"type":"Point"}
}