{
  "type": "Feature",
  "properties": {
    "addr:full":"2200 Sunrise Ave Modesto CA 95350",
    "addr:housenumber":"2200",
    "addr:postcode":"ca 95350",
    "addr:street":"Sunrise Ave",
    "iso:country":"US",
    "sg:address":"2200 Sunrise Ave",
    "sg:city":"Modesto",
    "sg:classifiers":[
        {
            "category":"Education",
            "subcategory":"Special Training",
            "type":"Public Place"
        }
    ],
    "sg:phone":"+1 209 824 7719",
    "sg:postcode":"95350",
    "sg:province":"CA",
    "sg:tags":[
        "instruction",
        "music"
    ],
    "wof:name":"Kindermusik With Miss Carla",
    "wof:placetype":"venue"
},
  "geometry": {"coordinates":[-120.984816,37.674879],"type":"Point"}
}