{
  "type": "Feature",
  "properties": {
    "iso:country":"US",
    "sg:address":"2200 Sunrise Ave",
    "sg:city":"Modesto",
    "sg:classifiers":[
        {
            "category":"Education",
            "subcategory":"Special Training",
            "type":"Public Place"
        }
    ],
    "sg:phone":"+1 209 824 7719",
    "sg:postcode":"95350",
    "sg:province":"CA",
    "sg:tags":[
        "instruction",
        "music"
    ],
    "wof:name":"Kindermusik With Miss Carla",
    "wof:placetype":"venue"
},
  "geometry": {"coordinates":[-120.984816,37.674879],"type":"Point"}
}