{
  "type": "Feature",
  "properties": {
    "iso:country":"US",
    "sg:address":"1616 Capitol Ave",
    "sg:city":"Sacramento",
    "sg:classifiers":[
        {
            "category":"Real Estate",
            "subcategory":"Real Estate Operator",
            "type":"Services"
        }
    ],
    "sg:phone":"+1 916 445 3700",
    "sg:postcode":"95814",
    "sg:province":"CA",
    "sg:tags":[
        "building",
        "nonresidential"
    ],
    "wof:name":"Department of General Services",
    "wof:placetype":"venue"
},
  "geometry": {"coordinates":[-121.48551500000001,38.574417],"type":"Point"}
}