{
  "type": "Feature",
  "properties": {
    "addr:full":"1215 Quintara St San Francisco CA 94116",
    "addr:housenumber":"1215",
    "addr:postcode":"94116",
    "addr:street":"Quintara St",
    "iso:country":"US",
    "sg:address":"1215 Quintara St",
    "sg:city":"San Francisco",
    "sg:classifiers":[
        {
            "category":"Education",
            "subcategory":"School",
            "type":"Public Place"
        }
    ],
    "sg:phone":"+1 415 753 8920",
    "sg:postcode":"94116",
    "sg:province":"CA",
    "sg:tags":[
        "academic",
        "special"
    ],
    "wof:name":"California Summer Music",
    "wof:placetype":"venue"
},
  "geometry": {"coordinates":[-122.47917099999999,37.748436],"type":"Point"}
}