{
  "type": "Feature",
  "properties": {
    "addr:full":"1319 Stanley Ave Glendale CA 91206",
    "addr:housenumber":"1319",
    "addr:postcode":"91206",
    "addr:street":"Stanley Ave",
    "iso:country":"US",
    "sg:address":"1319 Stanley Ave",
    "sg:city":"Glendale",
    "sg:classifiers":[
        {
            "category":"Freight",
            "type":"Transportation"
        }
    ],
    "sg:phone":"+1 818 265 0153",
    "sg:postcode":"91206",
    "sg:province":"CA",
    "sg:tags":[
        "operator",
        "local",
        "trucking"
    ],
    "wof:name":"N & E Trucking",
    "wof:placetype":"venue"
},
  "geometry": {"coordinates":[-118.237435,34.149057],"type":"Point"}
}