{
  "type": "Feature",
  "properties": {
    "iso:country":"US",
    "sg:address":"10913 Orr and Day Rd",
    "sg:city":"Santa Fe Springs",
    "sg:classifiers":[
        {
            "category":"Retail",
            "subcategory":"Repair Shop",
            "type":"Services"
        }
    ],
    "sg:phone":"+1 562 868 2385",
    "sg:postcode":"90670",
    "sg:province":"CA",
    "sg:tags":[
        "upholsterer"
    ],
    "wof:name":"Vera's Upholstery",
    "wof:placetype":"venue"
},
  "geometry": {"coordinates":[-118.090604,33.933832],"type":"Point"}
}