{
  "type": "Feature",
  "properties": {
    "iso:country":"US",
    "sg:address":"402 W Broadway",
    "sg:city":"San Diego",
    "sg:classifiers":[
        {
            "category":"Professional",
            "subcategory":"Employment Agencies",
            "type":"Services"
        }
    ],
    "sg:phone":"+1 619 233 9158",
    "sg:postcode":"92101",
    "sg:province":"CA",
    "sg:tags":[
        "opportunity"
    ],
    "wof:name":"Accountancy At Remex Finaincial",
    "wof:placetype":"venue"
},
  "geometry": {"coordinates":[-117.167,32.715801],"type":"Point"}
}