{
  "type": "Feature",
  "properties": {
    "iso:country":"US",
    "sg:address":"4813 S Wilton Place",
    "sg:city":"Los Angeles",
    "sg:classifiers":[
        {
            "category":"Building & Trades",
            "subcategory":"Construction",
            "type":"Services"
        }
    ],
    "sg:phone":"+1 323 296 4884",
    "sg:postcode":"90062",
    "sg:province":"CA",
    "sg:tags":[
        "contractor"
    ],
    "wof:name":"Tucker M Construction",
    "wof:placetype":"venue"
},
  "geometry": {"coordinates":[-118.314792,33.999507],"type":"Point"}
}