{
  "type": "Feature",
  "properties": {
    "addr:full":"415 N Main St #6 Manteca CA 95336",
    "addr:housenumber":"415",
    "addr:postcode":"95336",
    "addr:street":"N Main St # 6",
    "iso:country":"US",
    "sg:address":"415 N Main St #6",
    "sg:city":"Manteca",
    "sg:classifiers":[
        {
            "category":"Insurance",
            "subcategory":"Insurance Agent",
            "type":"Services"
        },
        {
            "category":"Insurance",
            "subcategory":"Hazard Insurance",
            "type":"Services"
        }
    ],
    "sg:phone":"+1 209 239 7001",
    "sg:postcode":"95336",
    "sg:province":"CA",
    "sg:tags":[
        "auto",
        "recreational",
        "motorcycle",
        "vehicle",
        "marine",
        "boat"
    ],
    "wof:name":"JOHN RODRIGUEZ",
    "wof:placetype":"venue"
},
  "geometry": {"coordinates":[-121.216706,37.803073],"type":"Point"}
}