{
  "type": "Feature",
  "properties": {
    "addr:full":"1254 Chadwick Ct Modesto CA 95350",
    "addr:housenumber":"1254",
    "addr:postcode":"ca 95350",
    "addr:street":"Chadwick Ct",
    "iso:country":"US",
    "sg:address":"1254 Chadwick Ct",
    "sg:city":"Modesto",
    "sg:classifiers":[
        {
            "category":"Building & Trades",
            "subcategory":"Construction",
            "type":"Services"
        }
    ],
    "sg:phone":"+1 209 577 5522",
    "sg:postcode":"95350",
    "sg:province":"CA",
    "sg:tags":[
        "painter"
    ],
    "wof:name":"Murray & Son Painting",
    "wof:placetype":"venue"
},
  "geometry": {"coordinates":[-120.977191,37.655726],"type":"Point"}
}