{
  "type": "Feature",
  "properties": {
    "iso:country":"US",
    "sg:address":"2643 W Pomona Blvd",
    "sg:city":"Pomona",
    "sg:classifiers":[
        {
            "category":"Retail",
            "subcategory":"Laundry & Dry Cleaning",
            "type":"Services"
        }
    ],
    "sg:phone":"+1 909 598 1700",
    "sg:postcode":"91768",
    "sg:province":"CA",
    "sg:tags":[
        "cleaners",
        "rug",
        "carpet"
    ],
    "sg:website":"www.mcccarpet.com",
    "wof:name":"MCC Carpet Upholstery Clnrs",
    "wof:placetype":"venue"
},
  "geometry": {"coordinates":[-117.79845899999999,34.05572],"type":"Point"}
}