{
  "type": "Feature",
  "properties": {
    "addr:full":"1201 E Ocean Ave Lompoc CA 93436",
    "addr:housenumber":"1201",
    "addr:postcode":"93436",
    "addr:street":"E Ocean Ave",
    "iso:country":"US",
    "sg:address":"1201 E Ocean Ave",
    "sg:city":"Lompoc",
    "sg:classifiers":[
        {
            "category":"Health Services",
            "subcategory":"Doctor",
            "type":"Services"
        }
    ],
    "sg:phone":"+1 805 735 2702",
    "sg:postcode":"93436",
    "sg:province":"CA",
    "sg:tags":[
        "dentist"
    ],
    "wof:name":"Vincent K Siefe DDS",
    "wof:placetype":"venue"
},
  "geometry": {"coordinates":[-120.443792,34.638967],"type":"Point"}
}