{
  "type": "Feature",
  "properties": {
    "addr:full":"4040 Hancock St. # 2702 San Diego CA 92110",
    "addr:housenumber":"4040",
    "addr:postcode":"92110",
    "addr:street":"Hancock St. # 2702",
    "iso:country":"US",
    "sg:address":"4040 Hancock St. # 2702",
    "sg:city":"San Diego",
    "sg:classifiers":[
        {
            "category":"Building & Trades",
            "subcategory":"Cleaning & Sanitation",
            "type":"Services"
        }
    ],
    "sg:phone":"+1 619 665 8725",
    "sg:postcode":"92110",
    "sg:province":"CA",
    "sg:tags":[
        "carpet"
    ],
    "sg:website":"www.larryrugworks.com/carpet-cle...",
    "wof:name":"Larry's Rug Works",
    "wof:placetype":"venue"
},
  "geometry": {"coordinates":[-117.216292,32.757244],"type":"Point"}
}