{
  "type": "Feature",
  "properties": {
    "addr:full":"11664 National Blvd Los Angeles CA 90064",
    "addr:housenumber":"11664",
    "addr:postcode":"90064",
    "addr:street":"National Blvd",
    "iso:country":"US",
    "sg:address":"11664 National Blvd",
    "sg:city":"Los Angeles",
    "sg:classifiers":[
        {
            "category":"Building & Trades",
            "subcategory":"Construction",
            "type":"Services"
        }
    ],
    "sg:phone":"+1 310 454 5586",
    "sg:postcode":"90064",
    "sg:province":"CA",
    "sg:tags":[
        "planning",
        "remodeling",
        "kitchen"
    ],
    "wof:name":"Bobbie Allen Designs",
    "wof:placetype":"venue"
},
  "geometry": {"coordinates":[-118.437512,34.023276],"type":"Point"}
}