{
  "type": "Feature",
  "properties": {
    "iso:country":"US",
    "sg:address":"3635 Fashion Way",
    "sg:city":"Torrance",
    "sg:classifiers":[
        {
            "category":"Personal",
            "subcategory":"Beauty Salon",
            "type":"Services"
        }
    ],
    "sg:phone":"+1 310 543 1184",
    "sg:postcode":"90503",
    "sg:province":"CA",
    "wof:name":"Artistic Cut Etc",
    "wof:placetype":"venue"
},
  "geometry": {"coordinates":[-118.349643,33.835289],"type":"Point"}
}