{
  "type": "Feature",
  "properties": {
    "addr:full":"30100 Town Center Dr Laguna Niguel CA 92677",
    "addr:housenumber":"30100",
    "addr:postcode":"92677",
    "addr:street":"Town Center Dr",
    "iso:country":"US",
    "sg:address":"30100 Town Center Dr",
    "sg:city":"Laguna Niguel",
    "sg:classifiers":[
        {
            "category":"Manufacturing",
            "subcategory":"Metals",
            "type":"Manufacturing & Wholesale Goods"
        }
    ],
    "sg:phone":"+1 949 249 9057",
    "sg:postcode":"92677",
    "sg:province":"CA",
    "sg:tags":[
        "mfg",
        "forging"
    ],
    "wof:name":"Dill Engineering",
    "wof:placetype":"venue"
},
  "geometry": {"coordinates":[-117.714062,33.52575],"type":"Point"}
}