{
  "type": "Feature",
  "properties": {
    "addr:full":"628 Lancer Ln Corona CA 92879",
    "addr:housenumber":"628",
    "addr:postcode":"92879",
    "addr:street":"Lancer Ln",
    "iso:country":"US",
    "sg:address":"628 Lancer Ln",
    "sg:city":"Corona",
    "sg:classifiers":[
        {
            "category":"Professional",
            "type":"Services"
        }
    ],
    "sg:phone":"+1 951 371 7852",
    "sg:postcode":"92879",
    "sg:province":"CA",
    "wof:name":"Ign LLC",
    "wof:placetype":"venue"
},
  "geometry": {"coordinates":[-117.559737,33.868699],"type":"Point"}
}