{
  "type": "Feature",
  "properties": {
    "addr:full":"2009 San Pablo Avenue Berkeley CA 94702",
    "addr:housenumber":"2009",
    "addr:postcode":"94702",
    "addr:street":"San Pablo Avenue",
    "iso:country":"US",
    "sg:address":"2009 San Pablo Avenue",
    "sg:city":"Berkeley",
    "sg:classifiers":[
        {
            "category":"Shopping",
            "subcategory":"Clothing, Apparel, & Fashions",
            "type":"Retail Goods"
        }
    ],
    "sg:phone":"+1 510 649 7998",
    "sg:postcode":"94702",
    "sg:province":"CA",
    "sg:tags":[
        "accessory",
        "clothing",
        "women's"
    ],
    "wof:name":"India Fashion",
    "wof:placetype":"venue"
},
  "geometry": {"coordinates":[-122.292,37.8689],"type":"Point"}
}