{
  "type": "Feature",
  "properties": {
    "addr:full":"907 N Court St Visalia CA 93291",
    "addr:housenumber":"907",
    "addr:postcode":"93291",
    "addr:street":"N Court St",
    "iso:country":"US",
    "sg:address":"907 N Court St",
    "sg:city":"Visalia",
    "sg:classifiers":[
        {
            "category":"Restaurant",
            "type":"Food & Drink"
        }
    ],
    "sg:phone":"+1 559 625 2234",
    "sg:postcode":"93291",
    "sg:province":"CA",
    "wof:name":"Seven Seas",
    "wof:placetype":"venue"
},
  "geometry": {"coordinates":[-119.292542,36.338151],"type":"Point"}
}