{
  "type": "Feature",
  "properties": {
    "iso:country":"US",
    "sg:address":"1670 S Amphlett Blvd",
    "sg:city":"San Mateo",
    "sg:classifiers":[
        {
            "category":"Freight",
            "type":"Transportation"
        }
    ],
    "sg:phone":"+1 650 655 4065",
    "sg:postcode":"94402",
    "sg:province":"CA",
    "wof:name":"World Transportation Svc",
    "wof:placetype":"venue"
},
  "geometry": {"coordinates":[-122.300358,37.556911],"type":"Point"}
}