{
  "type": "Feature",
  "properties": {
    "addr:full":"8015 Cohasset Rd Chico CA 95973",
    "addr:housenumber":"8015",
    "addr:postcode":"95973",
    "addr:street":"Cohasset Rd",
    "iso:country":"US",
    "sg:address":"8015 Cohasset Rd",
    "sg:city":"Chico",
    "sg:classifiers":[
        {
            "category":"Building & Trades",
            "subcategory":"Construction",
            "type":"Services"
        }
    ],
    "sg:phone":"+1 530 343 0238",
    "sg:postcode":"95973",
    "sg:province":"CA",
    "sg:tags":[
        "water",
        "well",
        "drilling"
    ],
    "wof:name":"Watson Earl Well Drilling",
    "wof:placetype":"venue"
},
  "geometry": {"coordinates":[-121.798182,39.853263],"type":"Point"}
}