{
  "type": "Feature",
  "properties": {
    "iso:country":"US",
    "sg:address":"3611 W 5th St",
    "sg:city":"Oxnard",
    "sg:classifiers":[
        {
            "category":"Personal",
            "subcategory":"Beauty Salon",
            "type":"Services"
        }
    ],
    "sg:phone":"+1 805 984 0233",
    "sg:postcode":"93030",
    "sg:province":"CA",
    "sg:tags":[
        "manicuring"
    ],
    "wof:name":"Mandaley Nails",
    "wof:placetype":"venue"
},
  "geometry": {"coordinates":[-119.22445,34.19771],"type":"Point"}
}