{
  "type": "Feature",
  "properties": {
    "addr:full":"21840 Normandie Ave Torrance CA 90502",
    "addr:housenumber":"21840",
    "addr:postcode":"90502",
    "addr:street":"Normandie Ave",
    "iso:country":"US",
    "sg:address":"21840 Normandie Ave",
    "sg:city":"Torrance",
    "sg:classifiers":[
        {
            "category":"Health Services",
            "subcategory":"Doctor",
            "type":"Services"
        }
    ],
    "sg:phone":"+1 310 222 2345",
    "sg:postcode":"90502",
    "sg:province":"CA",
    "sg:tags":[
        "physician",
        "surgeon"
    ],
    "wof:name":"HARBOR-Ucla Physician",
    "wof:placetype":"venue"
},
  "geometry": {"coordinates":[-118.29919,33.828581],"type":"Point"}
}