{
  "type": "Feature",
  "properties": {
    "iso:country":"US",
    "sg:address":"10100 Santa Monica Blvd",
    "sg:city":"Los Angeles",
    "sg:classifiers":[
        {
            "category":"Professional",
            "subcategory":"Lawyer & Legal Services",
            "type":"Services"
        }
    ],
    "sg:phone":"+1 310 282 0553",
    "sg:postcode":"90067",
    "sg:province":"CA",
    "sg:tags":[
        "attorney"
    ],
    "wof:name":"Donald A Barton",
    "wof:placetype":"venue"
},
  "geometry": {"coordinates":[-118.41840500000001,34.06107],"type":"Point"}
}