{
  "type": "Feature",
  "properties": {
    "addr:full":"3939 Atlantic Ave Long Beach CA 90807",
    "addr:housenumber":"3939",
    "addr:postcode":"90807",
    "addr:street":"Atlantic Ave",
    "iso:country":"US",
    "sg:address":"3939 Atlantic Ave",
    "sg:city":"Long Beach",
    "sg:classifiers":[
        {
            "category":"Health Services",
            "subcategory":"Health Practitioner",
            "type":"Services"
        }
    ],
    "sg:phone":"+1 562 989 1700",
    "sg:postcode":"90807",
    "sg:province":"CA",
    "sg:tags":[
        "therapy",
        "physical"
    ],
    "sg:website":"www.sunsetphysicaltherapy.com",
    "wof:name":"SUNSET PHYSICAL THERAPY",
    "wof:placetype":"venue"
},
  "geometry": {"coordinates":[-118.185233,33.82984],"type":"Point"}
}