{
  "type": "Feature",
  "properties": {
    "addr:full":"27241 Borrasca Mission Viejo CA 92691",
    "addr:postcode":"27241;92691",
    "addr:street":"Borrasca",
    "iso:country":"US",
    "sg:address":"27241 Borrasca",
    "sg:city":"Mission Viejo",
    "sg:classifiers":[
        {
            "category":"Wholesale",
            "subcategory":"Electrical",
            "type":"Manufacturing & Wholesale Goods"
        }
    ],
    "sg:phone":"+1 949 855 6013",
    "sg:postcode":"92691",
    "sg:province":"CA",
    "sg:tags":[
        "electronic"
    ],
    "wof:name":"Jon Price & Associates",
    "wof:placetype":"venue"
},
  "geometry": {"coordinates":[-117.656412,33.622793],"type":"Point"}
}