{
  "type": "Feature",
  "properties": {
    "addr:full":"1199 Forest Ave Pacific Grove CA 93950",
    "addr:housenumber":"1199",
    "addr:postcode":"93950",
    "addr:street":"Forest Ave",
    "iso:country":"US",
    "sg:address":"1199 Forest Ave",
    "sg:city":"Pacific Grove",
    "sg:classifiers":[
        {
            "category":"Professional",
            "type":"Services"
        }
    ],
    "sg:phone":"+1 831 643 2355",
    "sg:postcode":"93950",
    "sg:province":"CA",
    "sg:tags":[
        "establishment"
    ],
    "wof:name":"Bell Mia",
    "wof:placetype":"venue"
},
  "geometry": {"coordinates":[-121.922219,36.60716],"type":"Point"}
}