{
  "type": "Feature",
  "properties": {
    "addr:full":"800 Asilomar Blvd Pacific Grove CA 93950",
    "addr:housenumber":"800",
    "addr:postcode":"93950",
    "addr:street":"Asilomar Blvd",
    "iso:country":"US",
    "sg:address":"800 Asilomar Blvd",
    "sg:city":"Pacific Grove",
    "sg:classifiers":[
        {
            "category":"Travel",
            "subcategory":"Hotels & Motels",
            "type":"Entertainment"
        }
    ],
    "sg:phone":"+1 831 372 8016",
    "sg:postcode":"93950",
    "sg:province":"CA",
    "wof:name":"Asilomar Conference Grounds",
    "wof:placetype":"venue"
},
  "geometry": {"coordinates":[-121.93619,36.616081],"type":"Point"}
}