{
  "type": "Feature",
  "properties": {
    "iso:country":"US",
    "sg:address":"325 W Gladstone St",
    "sg:city":"Glendora",
    "sg:classifiers":[
        {
            "category":"Social Services",
            "subcategory":"Child Care",
            "type":"Services"
        }
    ],
    "sg:phone":"+1 626 335 6705",
    "sg:postcode":"91740",
    "sg:province":"CA",
    "sg:tags":[
        "nursery",
        "day"
    ],
    "wof:name":"S C Child Care",
    "wof:placetype":"venue"
},
  "geometry": {"coordinates":[-117.868514,34.113945],"type":"Point"}
}