{
  "type": "Feature",
  "properties": {
    "addr:full":"1761 Hotel Cir S San Diego CA 92108",
    "addr:housenumber":"1761",
    "addr:postcode":"92108",
    "addr:street":"Hotel Cir S",
    "iso:country":"US",
    "sg:address":"1761 Hotel Cir S",
    "sg:city":"San Diego",
    "sg:classifiers":[
        {
            "category":"Utilities",
            "subcategory":"Mobile Phone",
            "type":"Services"
        }
    ],
    "sg:phone":"+1 619 294 3452",
    "sg:postcode":"92108",
    "sg:province":"CA",
    "sg:tags":[
        "communication",
        "radiotelephone"
    ],
    "wof:name":"Wireless E",
    "wof:placetype":"venue"
},
  "geometry": {"coordinates":[-117.181234,32.759015],"type":"Point"}
}