{
  "type": "Feature",
  "properties": {
    "iso:country":"US",
    "sg:address":"6100 Watt Ave",
    "sg:city":"North Highlands",
    "sg:classifiers":[
        {
            "category":"Shopping",
            "subcategory":"Clothing, Apparel, & Fashions",
            "type":"Retail Goods"
        }
    ],
    "sg:phone":"+1 916 339 3941",
    "sg:postcode":"95660",
    "sg:province":"CA",
    "sg:tags":[
        "western"
    ],
    "wof:name":"Durango Western Wear",
    "wof:placetype":"venue"
},
  "geometry": {"coordinates":[-121.38281600000001,38.676784],"type":"Point"}
}