{
  "type": "Feature",
  "properties": {
    "iso:country":"US",
    "sg:address":"2239 Cypress Ave",
    "sg:city":"Santa Ana",
    "sg:classifiers":[
        {
            "category":"Professional",
            "type":"Services"
        }
    ],
    "sg:phone":"+1 714 641 8209",
    "sg:postcode":"92707",
    "sg:province":"CA",
    "wof:name":"One Big Party",
    "wof:placetype":"venue"
},
  "geometry": {"coordinates":[-117.86654299999999,33.717489],"type":"Point"}
}