{
  "type": "Feature",
  "properties": {
    "iso:country":"US",
    "sg:address":"3274 Ross Rd",
    "sg:city":"Palo Alto",
    "sg:classifiers":[
        {
            "category":"Shopping",
            "subcategory":"Computers & Home Electronics",
            "type":"Retail Goods"
        }
    ],
    "sg:phone":"+1 650 494 6200",
    "sg:postcode":"94303",
    "sg:province":"CA",
    "sg:tags":[
        "software"
    ],
    "wof:name":"Posedge Inc",
    "wof:placetype":"venue"
},
  "geometry": {"coordinates":[-122.118209,37.430257],"type":"Point"}
}