{
  "type": "Feature",
  "properties": {
    "iso:country":"US",
    "sg:address":"6530 Northbrook Way",
    "sg:city":"Fair Oaks",
    "sg:classifiers":[
        {
            "category":"Professional",
            "type":"Services"
        }
    ],
    "sg:phone":"+1 916 967 4900",
    "sg:postcode":"95628",
    "sg:province":"CA",
    "wof:name":"Fotocollage",
    "wof:placetype":"venue"
},
  "geometry": {"coordinates":[-121.312045,38.670621],"type":"Point"}
}