{
  "type": "Feature",
  "properties": {
    "addr:full":"7499 Kickapoo Trl Yucca Valley CA 92284",
    "addr:housenumber":"7499",
    "addr:postcode":"92284",
    "addr:street":"Kickapoo Trl",
    "iso:country":"US",
    "sg:address":"7499 Kickapoo Trl",
    "sg:city":"Yucca Valley",
    "sg:classifiers":[
        {
            "category":"Restaurant",
            "type":"Food & Drink"
        }
    ],
    "sg:phone":"+1 760 365 3460",
    "sg:postcode":"92284",
    "sg:province":"CA",
    "wof:name":"Jerry's Restaurant & Lounge",
    "wof:placetype":"venue"
},
  "geometry": {"coordinates":[-116.457736,34.115838],"type":"Point"}
}