{
  "type": "Feature",
  "properties": {
    "addr:full":"1625 Terrace Way Santa Rosa CA 95404",
    "addr:housenumber":"1625",
    "addr:postcode":"95404",
    "addr:street":"Terrace Way",
    "iso:country":"US",
    "sg:address":"1625 Terrace Way",
    "sg:city":"Santa Rosa",
    "sg:classifiers":[
        {
            "category":"Personal",
            "subcategory":"Beauty Salon",
            "type":"Services"
        }
    ],
    "sg:phone":"+1 707 542 3223",
    "sg:postcode":"95404",
    "sg:province":"CA",
    "sg:tags":[
        "treatment",
        "skin"
    ],
    "wof:name":"Facially Yours",
    "wof:placetype":"venue"
},
  "geometry": {"coordinates":[-122.70291,38.456184],"type":"Point"}
}