{
  "type": "Feature",
  "properties": {
    "iso:country":"US",
    "sg:address":"2655 N Weber Ave",
    "sg:city":"Fresno",
    "sg:classifiers":[
        {
            "category":"Wholesale",
            "subcategory":"Metals & Minerals",
            "type":"Manufacturing & Wholesale Goods"
        }
    ],
    "sg:phone":"+1 559 266 0881",
    "sg:postcode":"93705",
    "sg:province":"CA",
    "sg:tags":[
        "steel",
        "warehouse"
    ],
    "wof:name":"American Metals Corp",
    "wof:placetype":"venue"
},
  "geometry": {"coordinates":[-119.837508,36.77516],"type":"Point"}
}