{
  "type": "Feature",
  "properties": {
    "addr:full":"11716 Carmenita Rd Whittier CA 90605",
    "addr:housenumber":"11716",
    "addr:postcode":"90605",
    "addr:street":"Carmenita Rd",
    "iso:country":"US",
    "sg:address":"11716 Carmenita Rd",
    "sg:city":"Whittier",
    "sg:classifiers":[
        {
            "category":"Shopping",
            "subcategory":"Books",
            "type":"Retail Goods"
        }
    ],
    "sg:phone":"+1 562 944 5180",
    "sg:postcode":"90605",
    "sg:province":"CA",
    "sg:tags":[
        "dealer"
    ],
    "wof:name":"Libreria Cristiana Aliento De",
    "wof:placetype":"venue"
},
  "geometry": {"coordinates":[-118.046345,33.924682],"type":"Point"}
}