{
  "type": "Feature",
  "properties": {
    "addr:full":"2856 Vail Ave Commerce CA 90040",
    "addr:housenumber":"2856",
    "addr:postcode":"90040",
    "addr:street":"Vail Ave",
    "iso:country":"US",
    "sg:address":"2856 Vail Ave",
    "sg:city":"Commerce",
    "sg:classifiers":[
        {
            "category":"Manufacturing",
            "subcategory":"Toys & Sporting Goods",
            "type":"Manufacturing & Wholesale Goods"
        }
    ],
    "sg:phone":"+1 323 888 8708",
    "sg:postcode":"90040",
    "sg:province":"CA",
    "sg:tags":[
        "toys-wholesale",
        "manufacturer"
    ],
    "wof:name":"Direct Distribution Services",
    "wof:placetype":"venue"
},
  "geometry": {"coordinates":[-118.13117200000001,33.990824],"type":"Point"}
}