{
  "type": "Feature",
  "properties": {
    "addr:full":"1239 Longbranch Ave Grover Beach CA 93433",
    "addr:housenumber":"1239",
    "addr:postcode":"93433",
    "addr:street":"Longbranch Ave",
    "iso:country":"US",
    "sg:address":"1239 Longbranch Ave",
    "sg:city":"Grover Beach",
    "sg:classifiers":[
        {
            "category":"Retail",
            "subcategory":"Funeral Services",
            "type":"Services"
        }
    ],
    "sg:phone":"+1 805 489 5552",
    "sg:postcode":"93433",
    "sg:province":"CA",
    "sg:tags":[
        "director"
    ],
    "wof:name":"Marshall-Spoo Sunset Funeral",
    "wof:placetype":"venue"
},
  "geometry": {"coordinates":[-120.61633,35.119272],"type":"Point"}
}