{
  "type": "Feature",
  "properties": {
    "iso:country":"US",
    "sg:address":"1569 W Carson St",
    "sg:city":"Torrance",
    "sg:classifiers":[
        {
            "category":"Building & Trades",
            "subcategory":"Landscaping Services",
            "type":"Services"
        }
    ],
    "sg:phone":"+1 310 782 9285",
    "sg:postcode":"90501",
    "sg:province":"CA",
    "wof:name":"Mendoza Gardening",
    "wof:placetype":"venue"
},
  "geometry": {"coordinates":[-118.30493800000001,33.831577],"type":"Point"}
}