{
  "type": "Feature",
  "properties": {
    "addr:full":"1760 California Ave Corona CA 92881",
    "addr:housenumber":"1760",
    "addr:postcode":"92881",
    "addr:street":"California Ave",
    "iso:country":"US",
    "sg:address":"1760 California Ave",
    "sg:city":"Corona",
    "sg:classifiers":[
        {
            "category":"Home & Garden",
            "subcategory":"Home Furnishings",
            "type":"Retail Goods"
        }
    ],
    "sg:phone":"+1 951 734 4205",
    "sg:postcode":"92881",
    "sg:province":"CA",
    "sg:tags":[
        "curtain",
        "made",
        "drapery"
    ],
    "wof:name":"R & D Custom Draperies",
    "wof:placetype":"venue"
},
  "geometry": {"coordinates":[-117.53909899999999,33.858877],"type":"Point"}
}