{
  "type": "Feature",
  "properties": {
    "iso:country":"US",
    "sg:address":"Clairemont Town Square Shopping Ceter 3962 Clairemont Mesa Blvd",
    "sg:city":"San Diego",
    "sg:classifiers":[
        {
            "category":"Shopping",
            "subcategory":"Department Store",
            "type":"Retail Goods"
        }
    ],
    "sg:phone":"+1 858 272 1893",
    "sg:postcode":"92117",
    "sg:province":"CA",
    "wof:name":"Baby Depot At Burlington Coat Factory",
    "wof:placetype":"venue"
},
  "geometry": {"coordinates":[-117.203232,32.827654],"type":"Point"}
}