{
  "type": "Feature",
  "properties": {
    "addr:full":"20450 Royal Ave Hayward CA 94541",
    "addr:housenumber":"20450",
    "addr:postcode":"94541",
    "addr:street":"Royal Ave",
    "iso:country":"US",
    "sg:address":"20450 Royal Ave",
    "sg:city":"Hayward",
    "sg:classifiers":[
        {
            "category":"Education",
            "subcategory":"School",
            "type":"Public Place"
        }
    ],
    "sg:phone":"+1 510 317 4400",
    "sg:postcode":"94541",
    "sg:province":"CA",
    "sg:tags":[
        "high",
        "middle"
    ],
    "wof:name":"San Lorenzo Unified School District",
    "wof:placetype":"venue"
},
  "geometry": {"coordinates":[-122.114998,37.6693],"type":"Point"}
}