{
  "type": "Feature",
  "properties": {
    "iso:country":"US",
    "sg:address":"911 Pacific Ave",
    "sg:city":"Crescent City",
    "sg:classifiers":[
        {
            "category":"Real Estate",
            "subcategory":"Real Estate Operator",
            "type":"Services"
        }
    ],
    "sg:phone":"+1 707 464 9768",
    "sg:postcode":"95531",
    "sg:province":"CA",
    "sg:tags":[
        "apartment"
    ],
    "wof:name":"Redwood Village Townhouse",
    "wof:placetype":"venue"
},
  "geometry": {"coordinates":[-124.212332,41.758156],"type":"Point"}
}