{
  "type": "Feature",
  "properties": {
    "addr:full":"3222 Airway Dr Santa Rosa CA 95403",
    "addr:housenumber":"3222",
    "addr:postcode":"95403",
    "addr:street":"Airway Dr",
    "iso:country":"US",
    "sg:address":"3222 Airway Dr",
    "sg:city":"Santa Rosa",
    "sg:classifiers":[
        {
            "category":"Wholesale",
            "subcategory":"Vending Machines",
            "type":"Manufacturing & Wholesale Goods"
        }
    ],
    "sg:phone":"+1 707 579 3618",
    "sg:postcode":"95403",
    "sg:province":"CA",
    "wof:name":"Minute Man Vending",
    "wof:placetype":"venue"
},
  "geometry": {"coordinates":[-122.73802499999999,38.473843],"type":"Point"}
}