{
  "type": "Feature",
  "properties": {
    "iso:country":"US",
    "sg:address":"1756 Landana Dr",
    "sg:city":"Concord",
    "sg:classifiers":[
        {
            "category":"Building & Trades",
            "subcategory":"Construction",
            "type":"Services"
        }
    ],
    "sg:phone":"+1 925 685 4195",
    "sg:postcode":"94519",
    "sg:province":"CA",
    "sg:tags":[
        "roofing",
        "contractor"
    ],
    "wof:name":"Joe Sullivan Roofing",
    "wof:placetype":"venue"
},
  "geometry": {"coordinates":[-121.996185,37.980264],"type":"Point"}
}