{
  "type": "Feature",
  "properties": {
    "addr:full":"175 S Fortuna Blvd Fortuna CA 95540",
    "addr:housenumber":"175",
    "addr:postcode":"95540",
    "addr:street":"S Fortuna Blvd",
    "iso:country":"US",
    "sg:address":"175 S Fortuna Blvd",
    "sg:city":"Fortuna",
    "sg:classifiers":[
        {
            "category":"Retail",
            "subcategory":"Laundry & Dry Cleaning",
            "type":"Services"
        }
    ],
    "sg:phone":"+1 707 725 6621",
    "sg:postcode":"95540",
    "sg:province":"CA",
    "wof:name":"Wash House",
    "wof:placetype":"venue"
},
  "geometry": {"coordinates":[-124.146575,40.591126],"type":"Point"}
}