{
  "type": "Feature",
  "properties": {
    "addr:full":"1020 Grand Ave Pacific Beach CA 92109",
    "addr:housenumber":"1020",
    "addr:postcode":"92109",
    "addr:street":"Grand Ave",
    "iso:country":"US",
    "sg:address":"1020 Grand Ave",
    "sg:city":"Pacific Beach",
    "sg:classifiers":[
        {
            "category":"Sports & Exercise",
            "subcategory":"Bicycle Rental",
            "type":"Entertainment"
        }
    ],
    "sg:phone":"+1 858 270 5425",
    "sg:postcode":"92109",
    "sg:province":"CA",
    "sg:tags":[
        "wear"
    ],
    "sg:website":"www.otmfightshop.com",
    "wof:name":"OTM Fight Shop",
    "wof:placetype":"venue"
},
  "geometry": {"coordinates":[-117.25082399999999,32.79591],"type":"Point"}
}