{
  "type": "Feature",
  "properties": {
    "addr:full":"940 N Highland Ave Los Angeles CA 90038",
    "addr:housenumber":"940",
    "addr:postcode":"90038",
    "addr:street":"N Highland Ave",
    "iso:country":"US",
    "sg:address":"940 N Highland Ave",
    "sg:city":"Los Angeles",
    "sg:classifiers":[
        {
            "category":"Retail",
            "subcategory":"Portrait Studio",
            "type":"Services"
        }
    ],
    "sg:phone":"+1 323 466 6630",
    "sg:postcode":"90038",
    "sg:province":"CA",
    "sg:tags":[
        "photography"
    ],
    "sg:website":"www.charleswilliambush.com",
    "wof:name":"Charles Bush Studios",
    "wof:placetype":"venue"
},
  "geometry": {"coordinates":[-118.338517,34.088165],"type":"Point"}
}