{
  "type": "Feature",
  "properties": {
    "addr:full":"33780 Briggs Rd Menifee CA 92584",
    "addr:housenumber":"33780",
    "addr:postcode":"92584",
    "addr:street":"Briggs Rd",
    "iso:country":"US",
    "sg:address":"33780 Briggs Rd",
    "sg:city":"Menifee",
    "sg:classifiers":[
        {
            "category":"Farming",
            "subcategory":"Livestock Farm",
            "type":"Manufacturing & Wholesale Goods"
        }
    ],
    "sg:phone":"+1 951 926 1634",
    "sg:postcode":"92584",
    "sg:province":"CA",
    "sg:tags":[
        "beef",
        "feedlot",
        "cattle"
    ],
    "wof:name":"Pinto Ranch",
    "wof:placetype":"venue"
},
  "geometry": {"coordinates":[-117.136672,33.627682],"type":"Point"}
}