{
  "type": "Feature",
  "properties": {
    "addr:full":"18034 S Western Ave Gardena CA 90248",
    "addr:housenumber":"18034",
    "addr:postcode":"90248",
    "addr:street":"S Western Ave",
    "iso:country":"US",
    "sg:address":"18034 S Western Ave",
    "sg:city":"Gardena",
    "sg:classifiers":[
        {
            "category":"Personal",
            "subcategory":"Day Spa",
            "type":"Services"
        }
    ],
    "sg:phone":"+1 310 768 2799",
    "sg:postcode":"90248",
    "sg:province":"CA",
    "wof:name":"Island Day Spa",
    "wof:placetype":"venue"
},
  "geometry": {"coordinates":[-118.308976,33.867125],"type":"Point"}
}