{
  "type": "Feature",
  "properties": {
    "addr:full":"1200 Pso Camarillo Camarillo CA 93010",
    "addr:housenumber":"1200",
    "addr:postcode":"93010",
    "addr:street":"Pso Camarillo",
    "iso:country":"US",
    "sg:address":"1200 Pso Camarillo",
    "sg:city":"Camarillo",
    "sg:classifiers":[
        {
            "category":"Professional",
            "subcategory":"Management & Consulting",
            "type":"Services"
        }
    ],
    "sg:phone":"+1 805 987 0872",
    "sg:postcode":"93010",
    "sg:province":"CA",
    "wof:name":"American Express",
    "wof:placetype":"venue"
},
  "geometry": {"coordinates":[-119.095938,34.22056],"type":"Point"}
}