{
  "type": "Feature",
  "properties": {
    "addr:full":"4951 N State St Ukiah CA 95482",
    "addr:housenumber":"4951",
    "addr:postcode":"ca 95482",
    "addr:street":"N State St",
    "iso:country":"US",
    "sg:address":"4951 N State St",
    "sg:city":"Ukiah",
    "sg:classifiers":[
        {
            "category":"Real Estate",
            "subcategory":"Real Estate Operator",
            "type":"Services"
        }
    ],
    "sg:phone":"+1 707 485 0994",
    "sg:postcode":"95482",
    "sg:province":"CA",
    "sg:tags":[
        "mobile",
        "home",
        "community"
    ],
    "wof:name":"Western Hills Mobile Home Park",
    "wof:placetype":"venue"
},
  "geometry": {"coordinates":[-123.205045,39.221533],"type":"Point"}
}