{
  "type": "Feature",
  "properties": {
    "iso:country":"US",
    "sg:address":"12040 Florence Ave",
    "sg:city":"Santa Fe Springs",
    "sg:classifiers":[
        {
            "category":"Manufacturing",
            "subcategory":"Tools & Machinery",
            "type":"Manufacturing & Wholesale Goods"
        }
    ],
    "sg:phone":"+1 562 906 0210",
    "sg:postcode":"90670",
    "sg:province":"CA",
    "sg:tags":[
        "water",
        "equipment",
        "treatment",
        "mfg"
    ],
    "wof:name":"Water Science Technologies",
    "wof:placetype":"venue"
},
  "geometry": {"coordinates":[-118.077162,33.935182],"type":"Point"}
}