{
  "type": "Feature",
  "properties": {
    "addr:full":"5201 Fruitridge Rd Sacramento CA 95820",
    "addr:housenumber":"5201",
    "addr:postcode":"95820",
    "addr:street":"Fruitridge Rd",
    "iso:country":"US",
    "sg:address":"5201 Fruitridge Rd",
    "sg:city":"Sacramento",
    "sg:classifiers":[
        {
            "category":"Travel",
            "subcategory":"Travel Agent",
            "type":"Entertainment"
        }
    ],
    "sg:phone":"+1 916 731 8723",
    "sg:postcode":"95820",
    "sg:province":"CA",
    "sg:tags":[
        "agency",
        "bureau"
    ],
    "wof:name":"Mundi Travel",
    "wof:placetype":"venue"
},
  "geometry": {"coordinates":[-121.445941,38.525015],"type":"Point"}
}