{
  "type": "Feature",
  "properties": {
    "addr:full":"3328 Coach Ln Cameron Park CA 95682",
    "addr:housenumber":"3328",
    "addr:postcode":"95682",
    "addr:street":"Coach Ln",
    "iso:country":"US",
    "sg:address":"3328 Coach Ln",
    "sg:city":"Cameron Park",
    "sg:classifiers":[
        {
            "category":"Retail",
            "subcategory":"Laundry & Dry Cleaning",
            "type":"Services"
        }
    ],
    "sg:phone":"+1 530 676 5679",
    "sg:postcode":"95682",
    "sg:province":"CA",
    "sg:tags":[
        "curtain",
        "drapery",
        "cleaners"
    ],
    "wof:name":"Cameron Park Cleaners",
    "wof:placetype":"venue"
},
  "geometry": {"coordinates":[-120.971672,38.658074],"type":"Point"}
}