{
  "type": "Feature",
  "properties": {
    "iso:country":"US",
    "sg:address":"9061 Bolsa Ave",
    "sg:city":"Westminster",
    "sg:classifiers":[
        {
            "category":"Insurance",
            "subcategory":"Insurance Agent",
            "type":"Services"
        }
    ],
    "sg:phone":"+1 714 901 7440",
    "sg:postcode":"92683",
    "sg:province":"CA",
    "sg:website":"www.baohiemxe.com",
    "wof:name":"Elite Insurance",
    "wof:placetype":"venue"
},
  "geometry": {"coordinates":[-117.971003,33.744829],"type":"Point"}
}