{
  "type": "Feature",
  "properties": {
    "addr:full":"4211 Business Dr Cameron Park CA 95682",
    "addr:housenumber":"4211",
    "addr:postcode":"95682",
    "addr:street":"Business Dr",
    "iso:country":"US",
    "sg:address":"4211 Business Dr",
    "sg:city":"Cameron Park",
    "sg:classifiers":[
        {
            "category":"Autos & Motor Vehicles",
            "subcategory":"Auto Supplies",
            "type":"Retail Goods"
        }
    ],
    "sg:phone":"+1 530 672 8864",
    "sg:postcode":"95682",
    "sg:province":"CA",
    "sg:tags":[
        "automobile",
        "stereo",
        "radio"
    ],
    "wof:name":"Elite Car Audio & Visual",
    "wof:placetype":"venue"
},
  "geometry": {"coordinates":[-120.952236,38.652991],"type":"Point"}
}