{
  "type": "Feature",
  "properties": {
    "addr:full":"14414 Oak St Saratoga CA 95070",
    "addr:housenumber":"14414",
    "addr:postcode":"95070",
    "addr:street":"Oak St",
    "iso:country":"US",
    "sg:address":"14414 Oak St",
    "sg:city":"Saratoga",
    "sg:classifiers":[
        {
            "category":"Shopping",
            "type":"Retail Goods"
        }
    ],
    "sg:phone":"+1 408 867 3278",
    "sg:postcode":"95070",
    "sg:province":"CA",
    "sg:tags":[
        "art",
        "gallery",
        "merchandise"
    ],
    "wof:name":"Oak Golden Gallery",
    "wof:placetype":"venue"
},
  "geometry": {"coordinates":[-122.031417,37.257996],"type":"Point"}
}