{
  "type": "Feature",
  "properties": {
    "iso:country":"US",
    "sg:address":"585 W Maple Ct",
    "sg:city":"Colton",
    "sg:classifiers":[
        {
            "category":"Building & Trades",
            "subcategory":"Construction",
            "type":"Services"
        }
    ],
    "sg:phone":"+1 909 514 0632",
    "sg:postcode":"92324",
    "sg:province":"CA",
    "sg:tags":[
        "tile",
        "dealer"
    ],
    "wof:name":"Petersen Tile Inc",
    "wof:placetype":"venue"
},
  "geometry": {"coordinates":[-117.333856,34.059329],"type":"Point"}
}