{
  "type": "Feature",
  "properties": {
    "iso:country":"US",
    "sg:address":"550 Irwin St",
    "sg:city":"San Rafael",
    "sg:classifiers":[
        {
            "category":"Wholesale",
            "subcategory":"Machinery & Supplies",
            "type":"Manufacturing & Wholesale Goods"
        },
        {
            "category":"Wholesale",
            "subcategory":"Hardware",
            "type":"Manufacturing & Wholesale Goods"
        }
    ],
    "sg:phone":"+1 415 457 9530",
    "sg:postcode":"94901",
    "sg:province":"CA",
    "sg:tags":[
        "plumbing",
        "equipment",
        "irrigation",
        "system",
        "sup"
    ],
    "wof:name":"Ewing Irrigation & Indus Pdts",
    "wof:placetype":"venue"
},
  "geometry": {"coordinates":[-122.521987,37.965185],"type":"Point"}
}