{
  "type": "Feature",
  "properties": {
    "addr:full":"3484 Gage Avenue Bell CA 90201",
    "addr:housenumber":"3484",
    "addr:postcode":"90201",
    "addr:street":"Gage Avenue",
    "iso:country":"US",
    "sg:address":"3484 Gage Avenue",
    "sg:city":"Bell",
    "sg:classifiers":[
        {
            "category":"Restaurant",
            "type":"Food & Drink"
        }
    ],
    "sg:phone":"+1 323 581 6277",
    "sg:postcode":"90201",
    "sg:province":"CA",
    "wof:name":"Tom's Burgers No 14",
    "wof:placetype":"venue"
},
  "geometry": {"coordinates":[-118.20346600000001,33.979693],"type":"Point"}
}