{
  "type": "Feature",
  "properties": {
    "addr:full":"793 North Ave Vista CA 92083",
    "addr:housenumber":"793",
    "addr:postcode":"92083",
    "addr:street":"North Ave",
    "iso:country":"US",
    "sg:address":"793 North Ave",
    "sg:city":"Vista",
    "sg:classifiers":[
        {
            "category":"Home & Garden",
            "subcategory":"Furniture",
            "type":"Retail Goods"
        }
    ],
    "sg:phone":"+1 760 630 1977",
    "sg:postcode":"92083",
    "sg:province":"CA",
    "wof:name":"John W Goff Furniture Maker",
    "wof:placetype":"venue"
},
  "geometry": {"coordinates":[-117.262443,33.215626],"type":"Point"}
}