{
  "type": "Feature",
  "properties": {
    "addr:full":"605 Glenshire Ct Roseville CA 95661",
    "addr:housenumber":"605",
    "addr:postcode":"95661",
    "addr:street":"Glenshire Ct",
    "iso:country":"US",
    "sg:address":"605 Glenshire Ct",
    "sg:city":"Roseville",
    "sg:classifiers":[
        {
            "category":"Building & Trades",
            "subcategory":"Equipment Rental",
            "type":"Services"
        }
    ],
    "sg:phone":"+1 916 600 3718",
    "sg:postcode":"95661",
    "sg:province":"CA",
    "sg:tags":[
        "leasing"
    ],
    "wof:name":"North City Financial",
    "wof:placetype":"venue"
},
  "geometry": {"coordinates":[-121.23325800000001,38.733892],"type":"Point"}
}