{
  "type": "Feature",
  "properties": {
    "addr:full":"5678 Cherry Ave Long Beach CA 90805",
    "addr:housenumber":"5678",
    "addr:postcode":"90805",
    "addr:street":"Cherry Ave",
    "iso:country":"US",
    "sg:address":"5678 Cherry Ave",
    "sg:city":"Long Beach",
    "sg:classifiers":[
        {
            "category":"Manufacturing",
            "subcategory":"Signs",
            "type":"Manufacturing & Wholesale Goods"
        }
    ],
    "sg:phone":"+1 562 423 5581",
    "sg:postcode":"90805",
    "sg:province":"CA",
    "sg:tags":[
        "specialty",
        "mfg"
    ],
    "wof:name":"James De Blois",
    "wof:placetype":"venue"
},
  "geometry": {"coordinates":[-118.16850599999999,33.859236],"type":"Point"}
}