{
  "type": "Feature",
  "properties": {
    "iso:country":"US",
    "sg:address":"1694 N D St",
    "sg:city":"San Bernardino",
    "sg:classifiers":[
        {
            "category":"Real Estate",
            "subcategory":"Real Estate Agent",
            "type":"Services"
        }
    ],
    "sg:phone":"+1 909 882 6937",
    "sg:postcode":"92405",
    "sg:province":"CA",
    "sg:tags":[
        "management"
    ],
    "wof:name":"Park West Group",
    "wof:placetype":"venue"
},
  "geometry": {"coordinates":[-117.292006,34.12883],"type":"Point"}
}