{
  "type": "Feature",
  "properties": {
    "addr:full":"4617 Morse Ave Sherman Oaks CA 91423",
    "addr:housenumber":"4617",
    "addr:postcode":"91423",
    "addr:street":"Morse Ave",
    "iso:country":"US",
    "sg:address":"4617 Morse Ave",
    "sg:city":"Sherman Oaks",
    "sg:classifiers":[
        {
            "category":"Building & Trades",
            "subcategory":"Construction",
            "type":"Services"
        }
    ],
    "sg:phone":"+1 818 986 2121",
    "sg:postcode":"91423",
    "sg:province":"CA",
    "sg:tags":[
        "painter"
    ],
    "wof:name":"Cliff Jones Painting Co",
    "wof:placetype":"venue"
},
  "geometry": {"coordinates":[-118.41606899999999,34.155505],"type":"Point"}
}