{
  "type": "Feature",
  "properties": {
    "iso:country":"US",
    "sg:address":"3720 Camino Del Rio W",
    "sg:city":"San Diego",
    "sg:classifiers":[
        {
            "category":"Restaurant",
            "type":"Food & Drink"
        }
    ],
    "sg:phone":"+1 619 543 0429",
    "sg:postcode":"92110",
    "sg:province":"CA",
    "sg:tags":[
        "mexican"
    ],
    "sg:website":"www.gotburritos.com",
    "wof:name":"Cotixan Mexican and Seafood",
    "wof:placetype":"venue"
},
  "geometry": {"coordinates":[-117.205392,32.75474],"type":"Point"}
}