{
  "type": "Feature",
  "properties": {
    "iso:country":"US",
    "sg:address":"11033 Harrell St",
    "sg:city":"Mira Loma",
    "sg:classifiers":[
        {
            "category":"Freight",
            "type":"Transportation"
        }
    ],
    "sg:phone":"+1 951 685 8352",
    "sg:postcode":"91752",
    "sg:province":"CA",
    "sg:tags":[
        "operator",
        "tank",
        "truck",
        "trucking"
    ],
    "wof:name":"Cal Southern Transport",
    "wof:placetype":"venue"
},
  "geometry": {"coordinates":[-117.526417,34.011493],"type":"Point"}
}