{
  "type": "Feature",
  "properties": {
    "addr:full":"45 Quail Ct Walnut Creek CA 94596",
    "addr:housenumber":"45",
    "addr:postcode":"94596",
    "addr:street":"Quail Ct",
    "iso:country":"US",
    "sg:address":"45 Quail Ct",
    "sg:city":"Walnut Creek",
    "sg:classifiers":[
        {
            "category":"Health Services",
            "subcategory":"Clinic",
            "type":"Services"
        }
    ],
    "sg:phone":"+1 925 945 6799",
    "sg:postcode":"94596",
    "sg:province":"CA",
    "sg:tags":[
        "specialty",
        "outpatient"
    ],
    "wof:name":"Kathleen Defronzo Mfcc",
    "wof:placetype":"venue"
},
  "geometry": {"coordinates":[-122.055144,37.887778],"type":"Point"}
}