{
  "type": "Feature",
  "properties": {
    "addr:full":"189 Stanford Ave Half Moon Bay CA 94038",
    "addr:housenumber":"189",
    "addr:postcode":"94038",
    "addr:street":"Stanford Ave",
    "iso:country":"US",
    "sg:address":"189 Stanford Ave",
    "sg:city":"Half Moon Bay",
    "sg:classifiers":[
        {
            "category":"Building & Trades",
            "subcategory":"Plumbing",
            "type":"Services"
        }
    ],
    "sg:phone":"+1 650 728 9403",
    "sg:postcode":"94038",
    "sg:province":"CA",
    "sg:tags":[
        "plumbing",
        "contractor"
    ],
    "wof:name":"Kensit Plumbing",
    "wof:placetype":"venue"
},
  "geometry": {"coordinates":[-122.492964,37.50499],"type":"Point"}
}