{
  "type": "Feature",
  "properties": {
    "iso:country":"US",
    "sg:address":"623 W Duarte Rd Ste 7",
    "sg:city":"Arcadia",
    "sg:classifiers":[
        {
            "category":"Health Services",
            "subcategory":"Doctor",
            "type":"Services"
        }
    ],
    "sg:phone":"+1 626 446 0599",
    "sg:postcode":"91007",
    "sg:province":"CA",
    "wof:name":"Shah Ramila MD",
    "wof:placetype":"venue"
},
  "geometry": {"coordinates":[-118.052002,34.1264],"type":"Point"}
}