{
  "type": "Feature",
  "properties": {
    "addr:full":"2940 Summit St Oakland CA 94609",
    "addr:housenumber":"2940",
    "addr:postcode":"94609",
    "addr:street":"Summit St",
    "iso:country":"US",
    "sg:address":"2940 Summit St",
    "sg:city":"Oakland",
    "sg:classifiers":[
        {
            "category":"Health Services",
            "subcategory":"Doctor",
            "type":"Services"
        }
    ],
    "sg:phone":"+1 510 444 9460",
    "sg:postcode":"94609",
    "sg:province":"CA",
    "sg:tags":[
        "practice",
        "family"
    ],
    "wof:name":"Westpoint Chiropractic",
    "wof:placetype":"venue"
},
  "geometry": {"coordinates":[-122.264999,37.818199],"type":"Point"}
}