{
  "type": "Feature",
  "properties": {
    "addr:full":"1572 Old Stage Rd Salinas CA 93908",
    "addr:housenumber":"1572",
    "addr:postcode":"93908",
    "addr:street":"Old Stage Rd",
    "iso:country":"US",
    "sg:address":"1572 Old Stage Rd",
    "sg:city":"Salinas",
    "sg:classifiers":[
        {
            "category":"Food & Beverages",
            "subcategory":"Fruits & Vegetables",
            "type":"Retail Goods"
        }
    ],
    "sg:phone":"+1 831 751 7967",
    "sg:postcode":"93908",
    "sg:province":"CA",
    "sg:tags":[
        "produce"
    ],
    "wof:name":"Rancho Tinajitos",
    "wof:placetype":"venue"
},
  "geometry": {"coordinates":[-121.531755,36.62709],"type":"Point"}
}