{
  "type": "Feature",
  "properties": {
    "iso:country":"US",
    "sg:address":"15618 Mule Mountain Pkwy",
    "sg:city":"Redding",
    "sg:classifiers":[
        {
            "category":"Banks & Credit Unions",
            "subcategory":"Bank",
            "type":"Services"
        }
    ],
    "sg:phone":"+1 530 243 3002",
    "sg:postcode":"96001",
    "sg:province":"CA",
    "sg:tags":[
        "loan",
        "broker"
    ],
    "wof:name":"Shasta Funding",
    "wof:placetype":"venue"
},
  "geometry": {"coordinates":[-122.480398,40.573996],"type":"Point"}
}