{
  "type": "Feature",
  "properties": {
    "addr:full":"4887 E Kings Canyon Rd Fresno CA 93727",
    "addr:housenumber":"4887",
    "addr:postcode":"93727",
    "addr:street":"E Kings Canyon Rd",
    "iso:country":"US",
    "sg:address":"4887 E Kings Canyon Rd",
    "sg:city":"Fresno",
    "sg:classifiers":[
        {
            "category":"Personal",
            "subcategory":"Beauty Salon",
            "type":"Services"
        }
    ],
    "sg:phone":"+1 559 251 5110",
    "sg:postcode":"93727",
    "sg:province":"CA",
    "wof:name":"MMP Magic Cut",
    "wof:placetype":"venue"
},
  "geometry": {"coordinates":[-119.733349,36.735996],"type":"Point"}
}