{
  "type": "Feature",
  "properties": {
    "addr:full":"2081 Bering Dr San Jose CA 95131",
    "addr:housenumber":"2081",
    "addr:postcode":"95131",
    "addr:street":"Bering Dr",
    "iso:country":"US",
    "sg:address":"2081 Bering Dr",
    "sg:city":"San Jose",
    "sg:classifiers":[
        {
            "category":"Cinema",
            "subcategory":"Movie Theater",
            "type":"Entertainment"
        }
    ],
    "sg:phone":"+1 408 288 7872",
    "sg:postcode":"95131",
    "sg:province":"CA",
    "wof:name":"Home Cinema Solutions",
    "wof:placetype":"venue"
},
  "geometry": {"coordinates":[-121.91798300000001,37.37674],"type":"Point"}
}