{
  "type": "Feature",
  "properties": {
    "addr:full":"1705 E San Marcus St Compton CA 90221",
    "addr:housenumber":"1705",
    "addr:postcode":"90221",
    "addr:street":"E San Marcus St",
    "iso:country":"US",
    "sg:address":"1705 E San Marcus St",
    "sg:city":"Compton",
    "sg:classifiers":[
        {
            "category":"Retail",
            "subcategory":"Laundry & Dry Cleaning",
            "type":"Services"
        }
    ],
    "sg:phone":"+1 310 762 2500",
    "sg:postcode":"90221",
    "sg:province":"CA",
    "sg:tags":[
        "cleaners",
        "rug",
        "carpet"
    ],
    "wof:name":"A 1 Carpet Cleaning",
    "wof:placetype":"venue"
},
  "geometry": {"coordinates":[-118.204584,33.897799],"type":"Point"}
}