{
  "type": "Feature",
  "properties": {
    "addr:full":"2031 San Bernardino Ave Redlands CA 92374",
    "addr:housenumber":"2031",
    "addr:postcode":"92374",
    "addr:street":"San Bernardino Ave",
    "iso:country":"US",
    "sg:address":"2031 San Bernardino Ave",
    "sg:city":"Redlands",
    "sg:classifiers":[
        {
            "category":"Professional",
            "subcategory":"Employment Agencies",
            "type":"Services"
        }
    ],
    "sg:phone":"+1 909 381 2251",
    "sg:postcode":"92374",
    "sg:province":"CA",
    "sg:tags":[
        "help",
        "supply"
    ],
    "wof:name":"Adecco Staffing",
    "wof:placetype":"venue"
},
  "geometry": {"coordinates":[-117.203579,34.077483],"type":"Point"}
}