{
  "type": "Feature",
  "properties": {
    "addr:full":"3161 Lucinda Ln Santa Barbara CA 93105",
    "addr:housenumber":"3161",
    "addr:postcode":"93105",
    "addr:street":"Lucinda Ln",
    "iso:country":"US",
    "sg:address":"3161 Lucinda Ln",
    "sg:city":"Santa Barbara",
    "sg:classifiers":[
        {
            "category":"Social Services",
            "type":"Services"
        }
    ],
    "sg:phone":"+1 805 687 3078",
    "sg:postcode":"93105",
    "sg:province":"CA",
    "sg:tags":[
        "counselor",
        "marriage",
        "family"
    ],
    "wof:name":"Robert L Peterson",
    "wof:placetype":"venue"
},
  "geometry": {"coordinates":[-119.728514,34.449597],"type":"Point"}
}