{
  "type": "Feature",
  "properties": {
    "iso:country":"US",
    "sg:address":"1855 W Main St",
    "sg:city":"El Centro",
    "sg:classifiers":[
        {
            "category":"Real Estate",
            "subcategory":"Real Estate Operator",
            "type":"Services"
        }
    ],
    "sg:phone":"+1 760 353 7316",
    "sg:postcode":"92243",
    "sg:province":"CA",
    "sg:tags":[
        "apartment"
    ],
    "wof:name":"Palm Gardens",
    "wof:placetype":"venue"
},
  "geometry": {"coordinates":[-115.576115,32.792766],"type":"Point"}
}