{
  "type": "Feature",
  "properties": {
    "iso:country":"US",
    "sg:address":"461 el Camino Real",
    "sg:city":"Salinas",
    "sg:classifiers":[
        {
            "category":"Farming",
            "subcategory":"Livestock Farm",
            "type":"Manufacturing & Wholesale Goods"
        }
    ],
    "sg:phone":"+1 831 422 6826",
    "sg:postcode":"93908",
    "sg:province":"CA",
    "sg:tags":[
        "ranch",
        "cattle"
    ],
    "wof:name":"Azevedo Cattle Co Inc",
    "wof:placetype":"venue"
},
  "geometry": {"coordinates":[-121.572531,36.616946],"type":"Point"}
}