{
  "type": "Feature",
  "properties": {
    "iso:country":"US",
    "sg:address":"12085 Central Ave",
    "sg:city":"Chino",
    "sg:classifiers":[
        {
            "category":"Recreation",
            "type":"Entertainment"
        }
    ],
    "sg:phone":"+1 909 627 6900",
    "sg:postcode":"91710",
    "sg:province":"CA",
    "sg:tags":[
        "martial",
        "arts",
        "instruction"
    ],
    "wof:name":"Young Kim's Tae KWON Do",
    "wof:placetype":"venue"
},
  "geometry": {"coordinates":[-117.689516,34.03189],"type":"Point"}
}