{
  "type": "Feature",
  "properties": {
    "addr:full":"1503 Abbot Kinney Blvd Venice CA 90291",
    "addr:housenumber":"1503",
    "addr:postcode":"90291",
    "addr:street":"Abbot Kinney Blvd",
    "iso:country":"US",
    "sg:address":"1503 Abbot Kinney Blvd",
    "sg:city":"Venice",
    "sg:classifiers":[
        {
            "category":"Communications",
            "subcategory":"Film & Video Production",
            "type":"Services"
        }
    ],
    "sg:phone":"+1 310 581 1555",
    "sg:postcode":"90291",
    "sg:province":"CA",
    "sg:tags":[
        "animated"
    ],
    "sg:website":"www.gmfx.com",
    "wof:name":"Gray Matter FX",
    "wof:placetype":"venue"
},
  "geometry": {"coordinates":[-118.463949,33.990115],"type":"Point"}
}