{
  "type": "Feature",
  "properties": {
    "addr:full":"6426 Hay Rd Vacaville CA 95687",
    "addr:housenumber":"6426",
    "addr:postcode":"95687",
    "addr:street":"Hay Rd",
    "iso:country":"US",
    "sg:address":"6426 Hay Rd",
    "sg:city":"Vacaville",
    "sg:classifiers":[
        {
            "category":"Utilities",
            "subcategory":"Refuse",
            "type":"Services"
        }
    ],
    "sg:phone":"+1 707 678 4196",
    "sg:postcode":"95687",
    "sg:province":"CA",
    "sg:tags":[
        "garbage",
        "collection"
    ],
    "wof:name":"B & J Landfill",
    "wof:placetype":"venue"
},
  "geometry": {"coordinates":[-121.830276,38.31498],"type":"Point"}
}