{
  "type": "Feature",
  "properties": {
    "iso:country":"US",
    "sg:address":"7880 Cll Juela",
    "sg:city":"La Jolla",
    "sg:classifiers":[
        {
            "category":"Shopping",
            "subcategory":"Gifts & Souvenirs",
            "type":"Retail Goods"
        }
    ],
    "sg:phone":"+1 858 456 8486",
    "sg:postcode":"92037",
    "sg:province":"CA",
    "sg:tags":[
        "shop"
    ],
    "wof:name":"Hawaiian Collection",
    "wof:placetype":"venue"
},
  "geometry": {"coordinates":[-117.255155,32.850139],"type":"Point"}
}