{
  "type": "Feature",
  "properties": {
    "addr:full":"16050 Church St Morgan Hill CA 95037",
    "addr:housenumber":"16050",
    "addr:postcode":"95037",
    "addr:street":"Church St",
    "iso:country":"US",
    "sg:address":"16050 Church St",
    "sg:city":"Morgan Hill",
    "sg:classifiers":[
        {
            "category":"Manufacturing",
            "subcategory":"Paper Products",
            "type":"Manufacturing & Wholesale Goods"
        }
    ],
    "sg:phone":"+1 408 776 3733",
    "sg:postcode":"95037",
    "sg:province":"CA",
    "sg:tags":[
        "converted",
        "mfg"
    ],
    "wof:name":"Vicious Venture Stuff",
    "wof:placetype":"venue"
},
  "geometry": {"coordinates":[-121.641351,37.11475],"type":"Point"}
}