{
  "type": "Feature",
  "properties": {
    "iso:country":"US",
    "sg:address":"350 Grand Ave",
    "sg:city":"Grover Beach",
    "sg:classifiers":[
        {
            "category":"Restaurant",
            "type":"Food & Drink"
        }
    ],
    "sg:phone":"+1 805 489 2816",
    "sg:postcode":"93433",
    "sg:province":"CA",
    "wof:name":"Speedy Burger",
    "wof:placetype":"venue"
},
  "geometry": {"coordinates":[-120.627152,35.121778],"type":"Point"}
}