{
  "type": "Feature",
  "properties": {
    "iso:country":"US",
    "sg:address":"7365 Carnelian St",
    "sg:city":"Rancho Cucamonga",
    "sg:classifiers":[
        {
            "category":"Professional",
            "subcategory":"Accounting & Tax Preparation",
            "type":"Services"
        }
    ],
    "sg:phone":"+1 909 945 5100",
    "sg:postcode":"91730",
    "sg:province":"CA",
    "sg:tags":[
        "return",
        "filing"
    ],
    "wof:name":"Olympus Financial",
    "wof:placetype":"venue"
},
  "geometry": {"coordinates":[-117.615975,34.119594],"type":"Point"}
}