{
  "type": "Feature",
  "properties": {
    "iso:country":"US",
    "sg:address":"3821 Main St",
    "sg:city":"Culver City",
    "sg:classifiers":[
        {
            "category":"Retail",
            "subcategory":"Repair Shop",
            "type":"Services"
        }
    ],
    "sg:phone":"+1 310 280 0184",
    "sg:postcode":"90232",
    "sg:province":"CA",
    "sg:tags":[
        "jewelry"
    ],
    "wof:name":"Milan Jewelers",
    "wof:placetype":"venue"
},
  "geometry": {"coordinates":[-118.394533,34.024694],"type":"Point"}
}