{
  "type": "Feature",
  "properties": {
    "addr:full":"4110 Saint Helena Hwy Napa CA 94558",
    "addr:housenumber":"4110",
    "addr:postcode":"94558",
    "addr:street":"Saint Helena Hwy",
    "iso:country":"US",
    "sg:address":"4110 Saint Helena Hwy",
    "sg:city":"Napa",
    "sg:classifiers":[
        {
            "category":"Restaurant",
            "type":"Food & Drink"
        }
    ],
    "sg:phone":"+1 707 224 3300",
    "sg:postcode":"94558",
    "sg:province":"CA",
    "sg:website":"www.bistrodongiovanni.com",
    "wof:name":"Bistro Don Giovanni",
    "wof:placetype":"venue"
},
  "geometry": {"coordinates":[-122.331326,38.353108],"type":"Point"}
}