{
  "type": "Feature",
  "properties": {
    "addr:full":"5760 Ayala Ave Baldwin Park CA 91706",
    "addr:housenumber":"5760",
    "addr:postcode":"91706",
    "addr:street":"Ayala Ave",
    "iso:country":"US",
    "sg:address":"5760 Ayala Ave",
    "sg:city":"Baldwin Park",
    "sg:classifiers":[
        {
            "category":"Shopping",
            "subcategory":"Clothing, Apparel, & Fashions",
            "type":"Retail Goods"
        }
    ],
    "sg:phone":"+1 626 812 9000",
    "sg:postcode":"91706",
    "sg:province":"CA",
    "sg:tags":[
        "sportswear"
    ],
    "wof:name":"Apache Sportswear",
    "wof:placetype":"venue"
},
  "geometry": {"coordinates":[-117.941203,34.120652],"type":"Point"}
}