{
  "type": "Feature",
  "properties": {
    "iso:country":"US",
    "sg:address":"1355 N Harbor Dr",
    "sg:city":"San Diego",
    "sg:classifiers":[
        {
            "category":"Parking",
            "type":"Transportation"
        }
    ],
    "sg:phone":"+1 619 544 8360",
    "sg:postcode":"92101",
    "sg:province":"CA",
    "sg:tags":[
        "garage"
    ],
    "wof:name":"Ace Parking",
    "wof:placetype":"venue"
},
  "geometry": {"coordinates":[-117.173027,32.718201],"type":"Point"}
}