{
  "type": "Feature",
  "properties": {
    "iso:country":"US",
    "sg:address":"490 N Harold St",
    "sg:city":"Fort Bragg",
    "sg:classifiers":[
        {
            "category":"Social Services",
            "subcategory":"Adult Care",
            "type":"Services"
        }
    ],
    "sg:phone":"+1 707 964 0443",
    "sg:postcode":"95437",
    "sg:province":"CA",
    "sg:tags":[
        "organization",
        "senior",
        "citizen"
    ],
    "wof:name":"Redwood Coast Seniors",
    "wof:placetype":"venue"
},
  "geometry": {"coordinates":[-123.79794,39.44557],"type":"Point"}
}