{
  "type": "Feature",
  "properties": {
    "iso:country":"US",
    "sg:address":"1425 University Ave",
    "sg:city":"San Diego",
    "sg:classifiers":[
        {
            "category":"Professional",
            "subcategory":"Computer Services",
            "type":"Services"
        }
    ],
    "sg:phone":"+1 619 291 3927",
    "sg:postcode":"92103",
    "sg:province":"CA",
    "sg:tags":[
        "home",
        "consulting",
        "page",
        "dev",
        "internet"
    ],
    "wof:name":"DZAP Design",
    "wof:placetype":"venue"
},
  "geometry": {"coordinates":[-117.150377,32.748425],"type":"Point"}
}