{
  "type": "Feature",
  "properties": {
    "addr:full":"505 S Pepper Ave Rialto CA 92376",
    "addr:housenumber":"505",
    "addr:postcode":"92376",
    "addr:street":"S Pepper Ave",
    "iso:country":"US",
    "sg:address":"505 S Pepper Ave",
    "sg:city":"Rialto",
    "sg:classifiers":[
        {
            "category":"Restaurant",
            "type":"Food & Drink"
        }
    ],
    "sg:phone":"+1 909 820 7567",
    "sg:postcode":"92376",
    "sg:province":"CA",
    "sg:tags":[
        "out"
    ],
    "wof:name":"Peppermill Charbroiled Burgers",
    "wof:placetype":"venue"
},
  "geometry": {"coordinates":[-117.35289,34.090268],"type":"Point"}
}