{
  "type": "Feature",
  "properties": {
    "iso:country":"US",
    "sg:address":"2230 4th St",
    "sg:city":"San Rafael",
    "sg:classifiers":[
        {
            "category":"Shopping",
            "type":"Retail Goods"
        }
    ],
    "sg:phone":"+1 415 454 8833",
    "sg:postcode":"94901",
    "sg:province":"CA",
    "sg:tags":[
        "pet",
        "food",
        "supply"
    ],
    "wof:name":"Elephant Walk Inc",
    "wof:placetype":"venue"
},
  "geometry": {"coordinates":[-122.550171,37.976335],"type":"Point"}
}