{
  "type": "Feature",
  "properties": {
    "iso:country":"US",
    "sg:address":"1037 S Ventura Rd",
    "sg:city":"Oxnard",
    "sg:classifiers":[
        {
            "category":"Shopping",
            "subcategory":"Bicycles & Sporting Goods",
            "type":"Retail Goods"
        },
        {
            "category":"Shopping",
            "subcategory":"Clothing, Apparel, & Fashions",
            "type":"Retail Goods"
        }
    ],
    "sg:phone":"+1 805 382 9345",
    "sg:postcode":"93030",
    "sg:province":"CA",
    "sg:tags":[
        "navy",
        "army"
    ],
    "wof:name":"P S Surplus Plus",
    "wof:placetype":"venue"
},
  "geometry": {"coordinates":[-119.194876,34.191727],"type":"Point"}
}