{
  "type": "Feature",
  "properties": {
    "addr:full":"9638 Mission Blvd Riverside CA 92509",
    "addr:housenumber":"9638",
    "addr:postcode":"92509",
    "addr:street":"Mission Blvd",
    "iso:country":"US",
    "sg:address":"9638 Mission Blvd",
    "sg:city":"Riverside",
    "sg:classifiers":[
        {
            "category":"Restaurant",
            "type":"Food & Drink"
        }
    ],
    "sg:phone":"+1 951 681 9707",
    "sg:postcode":"92509",
    "sg:province":"CA",
    "wof:name":"Casa Karlitas",
    "wof:placetype":"venue"
},
  "geometry": {"coordinates":[-117.49760499999999,34.011476],"type":"Point"}
}