{
  "type": "Feature",
  "properties": {
    "addr:full":"1050 Blossom Hill Rd Ste 100 San Jose CA 95123",
    "addr:housenumber":"1050",
    "addr:postcode":"95123",
    "addr:street":"Blossom Hill Rd Ste 100",
    "iso:country":"US",
    "sg:address":"1050 Blossom Hill Rd Ste 100",
    "sg:city":"San Jose",
    "sg:classifiers":[
        {
            "category":"Sports & Exercise",
            "subcategory":"Bicycle Rental",
            "type":"Entertainment"
        },
        {
            "category":"Insurance",
            "subcategory":"Health Insurance",
            "type":"Services"
        }
    ],
    "sg:phone":"+1 408 694 0631",
    "sg:postcode":"95123",
    "sg:province":"CA",
    "sg:tags":[
        "wear",
        "market"
    ],
    "sg:website":"www.maxmusclesanjose.com",
    "wof:name":"Max Muscle",
    "wof:placetype":"venue"
},
  "geometry": {"coordinates":[-121.872553,37.250564],"type":"Point"}
}