{
  "type": "Feature",
  "properties": {
    "addr:full":"5700 Lindero Canyon Rd Thousand Oaks CA 91362",
    "addr:housenumber":"5700",
    "addr:postcode":"91362",
    "addr:street":"Lindero Canyon Rd",
    "iso:country":"US",
    "sg:address":"5700 Lindero Canyon Rd",
    "sg:city":"Thousand Oaks",
    "sg:classifiers":[
        {
            "category":"Shopping",
            "subcategory":"Discount & Variety Stores",
            "type":"Retail Goods"
        }
    ],
    "sg:phone":"+1 818 597 3901",
    "sg:postcode":"91362",
    "sg:province":"CA",
    "sg:tags":[
        "club",
        "membership"
    ],
    "wof:name":"Costco",
    "wof:placetype":"venue"
},
  "geometry": {"coordinates":[-118.798289,34.15332],"type":"Point"}
}