{
  "type": "Feature",
  "properties": {
    "addr:full":"8919 Limonite Ave Riverside CA 92509",
    "addr:housenumber":"8919",
    "addr:postcode":"92509",
    "addr:street":"Limonite Ave",
    "iso:country":"US",
    "sg:address":"8919 Limonite Ave",
    "sg:city":"Riverside",
    "sg:classifiers":[
        {
            "category":"Restaurant",
            "type":"Food & Drink"
        }
    ],
    "sg:menulink":"http://www.allmenus.com/ca/jurupa/171382-carls-jr/menu/",
    "sg:phone":"+1 951 681 3970",
    "sg:postcode":"92509",
    "sg:province":"CA",
    "sg:tags":[
        "burger",
        "american"
    ],
    "wof:name":"Carl's Jr.",
    "wof:placetype":"venue"
},
  "geometry": {"coordinates":[-117.47842799999999,33.975534],"type":"Point"}
}