{
  "type": "Feature",
  "properties": {
    "addr:full":"1418 Main St Venice CA 90291",
    "addr:housenumber":"1418",
    "addr:postcode":"90291",
    "addr:street":"Main St",
    "iso:country":"US",
    "sg:address":"1418 Main St",
    "sg:city":"Venice",
    "sg:classifiers":[
        {
            "category":"Personal",
            "subcategory":"Beauty Salon",
            "type":"Services"
        }
    ],
    "sg:phone":"+1 310 452 8985",
    "sg:postcode":"90291",
    "sg:province":"CA",
    "wof:name":"Off The Top",
    "wof:placetype":"venue"
},
  "geometry": {"coordinates":[-118.471565,33.98872],"type":"Point"}
}