{
  "type": "Feature",
  "properties": {
    "addr:full":"2820 Sonoma Blvd Vallejo CA 94590",
    "addr:housenumber":"2820",
    "addr:postcode":"94590",
    "addr:street":"Sonoma Blvd",
    "iso:country":"US",
    "sg:address":"2820 Sonoma Blvd",
    "sg:city":"Vallejo",
    "sg:classifiers":[
        {
            "category":"Restaurant",
            "type":"Food & Drink"
        }
    ],
    "sg:menulink":"http://www.allmenus.com/ca/vallejo/74253-dominos-pizza/menu/",
    "sg:phone":"+1 707 554 6600",
    "sg:postcode":"94590",
    "sg:province":"CA",
    "sg:tags":[
        "american",
        "wing",
        "pizza"
    ],
    "wof:name":"Domino's Pizza",
    "wof:placetype":"venue"
},
  "geometry": {"coordinates":[-122.25436500000001,38.112672],"type":"Point"}
}