{
  "type": "Feature",
  "properties": {
    "iso:country":"US",
    "sg:address":"13085 Road 144",
    "sg:city":"Tipton",
    "sg:classifiers":[
        {
            "category":"Real Estate",
            "subcategory":"Real Estate Services",
            "type":"Services"
        },
        {
            "category":"Real Estate",
            "subcategory":"Real Estate Agent",
            "type":"Services"
        }
    ],
    "sg:phone":"+1 559 752 4364",
    "sg:postcode":"93272",
    "sg:province":"CA",
    "sg:tags":[
        "buyer",
        "broker"
    ],
    "wof:name":"Cotta Family Real Estate Ltd P",
    "wof:placetype":"venue"
},
  "geometry": {"coordinates":[-119.250478,36.024205],"type":"Point"}
}