{
  "type": "Feature",
  "properties": {
    "addr:full":"1111 Torrey Pines Rd La Jolla CA 92037",
    "addr:housenumber":"1111",
    "addr:postcode":"92037",
    "addr:street":"Torrey Pines Rd",
    "iso:country":"US",
    "sg:address":"1111 Torrey Pines Rd",
    "sg:city":"La Jolla",
    "sg:classifiers":[
        {
            "category":"Wholesale",
            "subcategory":"Computers",
            "type":"Manufacturing & Wholesale Goods"
        }
    ],
    "sg:phone":"+1 858 454 9765",
    "sg:postcode":"92037",
    "sg:province":"CA",
    "wof:name":"Education Systems Exchange",
    "wof:placetype":"venue"
},
  "geometry": {"coordinates":[-117.272003,32.842899],"type":"Point"}
}