{
  "type": "Feature",
  "properties": {
    "iso:country":"US",
    "sg:address":"13601 Purche Ave",
    "sg:city":"Gardena",
    "sg:classifiers":[
        {
            "category":"Place Of Worship",
            "subcategory":"Church",
            "type":"Public Place"
        },
        {
            "category":"Place Of Worship",
            "type":"Public Place"
        }
    ],
    "sg:phone":"+1 310 686 3342",
    "sg:postcode":"90249",
    "sg:province":"CA",
    "sg:tags":[
        "churches-catholic-traditional",
        "churches-catholic"
    ],
    "wof:name":"Providence Holy Cross Med",
    "wof:placetype":"venue"
},
  "geometry": {"coordinates":[-118.320637,33.908302],"type":"Point"}
}