{
  "type": "Feature",
  "properties": {
    "addr:full":"34372 Dunhill Dr Fremont CA 94555",
    "addr:housenumber":"34372",
    "addr:postcode":"94555",
    "addr:street":"Dunhill Dr",
    "iso:country":"US",
    "sg:address":"34372 Dunhill Dr",
    "sg:city":"Fremont",
    "sg:classifiers":[
        {
            "category":"Shopping",
            "subcategory":"Books",
            "type":"Retail Goods"
        }
    ],
    "sg:phone":"+1 510 790 1342",
    "sg:postcode":"94555",
    "sg:province":"CA",
    "wof:name":"Papyrus Books",
    "wof:placetype":"venue"
},
  "geometry": {"coordinates":[-122.05659199999999,37.557868],"type":"Point"}
}