{
  "type": "Feature",
  "properties": {
    "iso:country":"US",
    "sg:address":"34372 Dunhill Dr",
    "sg:city":"Fremont",
    "sg:classifiers":[
        {
            "category":"Shopping",
            "subcategory":"Books",
            "type":"Retail Goods"
        }
    ],
    "sg:phone":"+1 510 790 1342",
    "sg:postcode":"94555",
    "sg:province":"CA",
    "wof:name":"Papyrus Books",
    "wof:placetype":"venue"
},
  "geometry": {"coordinates":[-122.056592,37.557868],"type":"Point"}
}