{
  "type": "Feature",
  "properties": {
    "addr:full":"428 E Chestnut Ave Orange CA 92867",
    "addr:housenumber":"428",
    "addr:postcode":"92867",
    "addr:street":"E Chestnut Ave",
    "iso:country":"US",
    "sg:address":"428 E Chestnut Ave",
    "sg:city":"Orange",
    "sg:classifiers":[
        {
            "category":"Insurance",
            "subcategory":"Insurance Agent",
            "type":"Services"
        }
    ],
    "sg:phone":"+1 714 283 1286",
    "sg:postcode":"92867",
    "sg:province":"CA",
    "sg:tags":[
        "adjuster"
    ],
    "wof:name":"Frontier Adjusters Of Anaheim",
    "wof:placetype":"venue"
},
  "geometry": {"coordinates":[-117.85222,33.813635],"type":"Point"}
}