{
  "type": "Feature",
  "properties": {
    "addr:full":"985 E Main St El Cajon CA 92021",
    "addr:housenumber":"985",
    "addr:postcode":"92021",
    "addr:street":"E Main St",
    "iso:country":"US",
    "sg:address":"985 E Main St",
    "sg:city":"El Cajon",
    "sg:classifiers":[
        {
            "category":"Retail",
            "subcategory":"Auto Rental",
            "type":"Services"
        }
    ],
    "sg:phone":"+1 619 442 5777",
    "sg:postcode":"92021",
    "sg:province":"CA",
    "sg:tags":[
        "renting",
        "truck",
        "leasing"
    ],
    "wof:name":"Ryder",
    "wof:placetype":"venue"
},
  "geometry": {"coordinates":[-116.949206,32.794844],"type":"Point"}
}