{
  "type": "Feature",
  "properties": {
    "addr:full":"101 N Victory Blvd Burbank CA 91502",
    "addr:housenumber":"101",
    "addr:postcode":"91502",
    "addr:street":"N Victory Blvd",
    "iso:country":"US",
    "sg:address":"101 N Victory Blvd",
    "sg:city":"Burbank",
    "sg:classifiers":[
        {
            "category":"Food & Beverages",
            "subcategory":"Liquor & Beverages",
            "type":"Retail Goods"
        }
    ],
    "sg:phone":"+1 818 848 1812",
    "sg:postcode":"91502",
    "sg:province":"CA",
    "wof:name":"Prime Liquor Jr Market",
    "wof:placetype":"venue"
},
  "geometry": {"coordinates":[-118.316709,34.173987],"type":"Point"}
}