{
  "type": "Feature",
  "properties": {
    "iso:country":"US",
    "sg:address":"1622 W el Segundo Blvd",
    "sg:city":"Gardena",
    "sg:classifiers":[
        {
            "category":"Freight",
            "type":"Transportation"
        }
    ],
    "sg:phone":"+1 310 630 5835",
    "sg:postcode":"90249",
    "sg:province":"CA",
    "sg:tags":[
        "delivery"
    ],
    "wof:name":"D's Delivery Svc",
    "wof:placetype":"venue"
},
  "geometry": {"coordinates":[-118.305134,33.916369],"type":"Point"}
}