{
  "type": "Feature",
  "properties": {
    "addr:full":"21889 Sunset Ct Hayward CA 94541",
    "addr:housenumber":"21889",
    "addr:postcode":"94541",
    "addr:street":"Sunset Ct",
    "iso:country":"US",
    "sg:address":"21889 Sunset Ct",
    "sg:city":"Hayward",
    "sg:classifiers":[
        {
            "category":"Manufacturing",
            "subcategory":"Metals",
            "type":"Manufacturing & Wholesale Goods"
        }
    ],
    "sg:phone":"+1 510 537 4787",
    "sg:postcode":"94541",
    "sg:province":"CA",
    "sg:tags":[
        "steel",
        "erectors"
    ],
    "wof:name":"Superior Erectors Inc",
    "wof:placetype":"venue"
},
  "geometry": {"coordinates":[-122.10268000000001,37.672192],"type":"Point"}
}