{
  "type": "Feature",
  "properties": {
    "iso:country":"US",
    "sg:address":"907 Tennyson Ln",
    "sg:city":"San Jose",
    "sg:classifiers":[
        {
            "category":"Restaurant",
            "type":"Food & Drink"
        }
    ],
    "sg:phone":"+1 408 259 2715",
    "sg:postcode":"95116",
    "sg:province":"CA",
    "sg:tags":[
        "mexican"
    ],
    "wof:name":"Tacos al Gusto",
    "wof:placetype":"venue"
},
  "geometry": {"coordinates":[-121.84492400000001,37.342663],"type":"Point"}
}