{
  "type": "Feature",
  "properties": {
    "iso:country":"US",
    "sg:address":"2200 Newport Blvd",
    "sg:city":"Newport Beach",
    "sg:classifiers":[
        {
            "category":"Restaurant",
            "type":"Food & Drink"
        },
        {
            "category":"Food & Beverages",
            "subcategory":"Meat & Fish",
            "type":"Retail Goods"
        }
    ],
    "sg:phone":"+1 949 673 0100",
    "sg:postcode":"92663",
    "sg:province":"CA",
    "sg:tags":[
        "seafood",
        "market"
    ],
    "sg:website":"www.crabcooker.com",
    "wof:name":"The Crab Cooker",
    "wof:placetype":"venue"
},
  "geometry": {"coordinates":[-117.92800099999999,33.609901],"type":"Point"}
}