{
  "type": "Feature",
  "properties": {
    "iso:country":"US",
    "sg:address":"14929 Slover Ave",
    "sg:city":"Fontana",
    "sg:classifiers":[
        {
            "category":"Building & Trades",
            "subcategory":"Construction",
            "type":"Services"
        }
    ],
    "sg:phone":"+1 909 829 0505",
    "sg:postcode":"92337",
    "sg:province":"CA",
    "sg:tags":[
        "sealcoating",
        "asphalt",
        "paving"
    ],
    "wof:name":"Ergon Asphalt Emulsions I",
    "wof:placetype":"venue"
},
  "geometry": {"coordinates":[-117.47953800000001,34.062931],"type":"Point"}
}