{
  "type": "Feature",
  "properties": {
    "iso:country":"US",
    "sg:address":"1929 Truxtun Ave",
    "sg:city":"Bakersfield",
    "sg:classifiers":[
        {
            "category":"Personal",
            "subcategory":"Beauty Salon",
            "type":"Services"
        }
    ],
    "sg:phone":"+1 661 327 7546",
    "sg:postcode":"93301",
    "sg:province":"CA",
    "wof:name":"Absolute Skin Care",
    "wof:placetype":"venue"
},
  "geometry": {"coordinates":[-119.024427,35.373281],"type":"Point"}
}