{
  "type": "Feature",
  "properties": {
    "addr:full":"1442 Brockton Ave Los Angeles CA 90025",
    "addr:housenumber":"1442",
    "addr:postcode":"90025",
    "addr:street":"Brockton Ave",
    "iso:country":"US",
    "sg:address":"1442 Brockton Ave",
    "sg:city":"Los Angeles",
    "sg:classifiers":[
        {
            "category":"Professional",
            "type":"Services"
        }
    ],
    "sg:phone":"+1 310 473 9424",
    "sg:postcode":"90025",
    "sg:province":"CA",
    "wof:name":"David Enfield Res Custom",
    "wof:placetype":"venue"
},
  "geometry": {"coordinates":[-118.461777,34.042289],"type":"Point"}
}