{
  "type": "Feature",
  "properties": {
    "addr:full":"Alameda Town Center 2250 S Shore Dr Alameda CA 94501",
    "addr:housenumber":"2250",
    "addr:postcode":"94501",
    "addr:street":"Alameda Town;S Shore Dr",
    "iso:country":"US",
    "sg:address":"Alameda Town Center 2250 S Shore Dr",
    "sg:city":"Alameda",
    "sg:classifiers":[
        {
            "category":"Shopping",
            "subcategory":"Department Store",
            "type":"Retail Goods"
        }
    ],
    "sg:phone":"+1 510 749 8201",
    "sg:postcode":"94501",
    "sg:province":"CA",
    "sg:website":"www.tjmaxx.com",
    "wof:name":"TJ Maxx",
    "wof:placetype":"venue"
},
  "geometry": {"coordinates":[-122.25035800000001,37.757029],"type":"Point"}
}