{
  "type": "Feature",
  "properties": {
    "addr:full":"255 S Santa Fe Avenue Los Angeles CA 90012",
    "addr:housenumber":"255",
    "addr:postcode":"90012",
    "addr:street":"S Santa Fe Avenue",
    "iso:country":"US",
    "sg:address":"255 S Santa Fe Avenue",
    "sg:city":"Los Angeles",
    "sg:classifiers":[
        {
            "category":"Shopping",
            "subcategory":"Clothing, Apparel, & Fashions",
            "type":"Retail Goods"
        }
    ],
    "sg:phone":"+1 213 617 1458",
    "sg:postcode":"90012",
    "sg:province":"CA",
    "sg:tags":[
        "clothing",
        "women's"
    ],
    "wof:name":"Pdtw",
    "wof:placetype":"venue"
},
  "geometry": {"coordinates":[-118.23245300000001,34.046313],"type":"Point"}
}