{
  "type": "Feature",
  "properties": {
    "addr:full":"562 Lighthouse Ave Pacific Grove CA 93950",
    "addr:housenumber":"562",
    "addr:postcode":"93950",
    "addr:street":"Lighthouse Ave",
    "iso:country":"US",
    "sg:address":"562 Lighthouse Ave",
    "sg:city":"Pacific Grove",
    "sg:classifiers":[
        {
            "category":"Shopping",
            "subcategory":"Gifts & Souvenirs",
            "type":"Retail Goods"
        }
    ],
    "sg:phone":"+1 831 643 1250",
    "sg:postcode":"93950",
    "sg:province":"CA",
    "sg:tags":[
        "party",
        "supply"
    ],
    "sg:website":"www.firstnoel.com",
    "wof:name":"First Noel",
    "wof:placetype":"venue"
},
  "geometry": {"coordinates":[-121.917548,36.621082],"type":"Point"}
}