{
  "type": "Feature",
  "properties": {
    "addr:full":"18079 Conestoga Ln Chino Hills CA 91709",
    "addr:housenumber":"18079",
    "addr:postcode":"91709",
    "addr:street":"Conestoga Ln",
    "iso:country":"US",
    "sg:address":"18079 Conestoga Ln",
    "sg:city":"Chino Hills",
    "sg:classifiers":[
        {
            "category":"Professional",
            "type":"Services"
        }
    ],
    "sg:phone":"+1 909 393 7183",
    "sg:postcode":"91709",
    "sg:province":"CA",
    "wof:name":"Present Moments",
    "wof:placetype":"venue"
},
  "geometry": {"coordinates":[-117.664455,33.924668],"type":"Point"}
}