{
  "type": "Feature",
  "properties": {
    "iso:country":"US",
    "sg:address":"3598 Woodhill Canyon Rd",
    "sg:city":"Studio City",
    "sg:classifiers":[
        {
            "category":"Real Estate",
            "subcategory":"Architect",
            "type":"Services"
        }
    ],
    "sg:phone":"+1 818 506 3657",
    "sg:postcode":"91604",
    "sg:province":"CA",
    "wof:name":"Citi Studio Architects",
    "wof:placetype":"venue"
},
  "geometry": {"coordinates":[-118.397188,34.137089],"type":"Point"}
}