{
  "type": "Feature",
  "properties": {
    "iso:country":"US",
    "sg:address":"4908 N Rolinda Ave",
    "sg:city":"Fresno",
    "sg:classifiers":[
        {
            "category":"Manufacturing",
            "subcategory":"Motor Vehicles & Parts",
            "type":"Manufacturing & Wholesale Goods"
        },
        {
            "category":"Building & Trades",
            "subcategory":"Electrical",
            "type":"Services"
        }
    ],
    "sg:phone":"+1 559 275 3840",
    "sg:postcode":"93723",
    "sg:province":"CA",
    "sg:tags":[
        "electrician",
        "electric"
    ],
    "wof:name":"Van Dyke Harlin",
    "wof:placetype":"venue"
},
  "geometry": {"coordinates":[-119.96120500000001,36.800462],"type":"Point"}
}