{
  "type": "Feature",
  "properties": {
    "iso:country":"US",
    "sg:address":"14623 Hawthorne Blvd",
    "sg:city":"Lawndale",
    "sg:classifiers":[
        {
            "category":"Banks & Credit Unions",
            "subcategory":"Investment Brokerage",
            "type":"Services"
        }
    ],
    "sg:phone":"+1 310 676 6297",
    "sg:postcode":"90260",
    "sg:province":"CA",
    "sg:tags":[
        "advisory",
        "financial"
    ],
    "wof:name":"DTS Financial Svc Inc",
    "wof:placetype":"venue"
},
  "geometry": {"coordinates":[-118.352441,33.898558],"type":"Point"}
}