{
  "type": "Feature",
  "properties": {
    "addr:full":"1790 E Lugonia Ave Redlands CA 92374",
    "addr:housenumber":"1790",
    "addr:postcode":"92374",
    "addr:street":"E Lugonia Ave",
    "iso:country":"US",
    "sg:address":"1790 E Lugonia Ave",
    "sg:city":"Redlands",
    "sg:classifiers":[
        {
            "category":"Restaurant",
            "type":"Food & Drink"
        }
    ],
    "sg:phone":"+1 909 794 2125",
    "sg:postcode":"92374",
    "sg:province":"CA",
    "sg:tags":[
        "pizza"
    ],
    "wof:name":"Venezia Pizza",
    "wof:placetype":"venue"
},
  "geometry": {"coordinates":[-117.139,34.07],"type":"Point"}
}