{
  "type": "Feature",
  "properties": {
    "addr:full":"31760 S Grade Rd Pauma Valley CA 92061",
    "addr:housenumber":"31760",
    "addr:postcode":"92061",
    "addr:street":"S Grade Rd",
    "iso:country":"US",
    "sg:address":"31760 S Grade Rd",
    "sg:city":"Pauma Valley",
    "sg:classifiers":[
        {
            "category":"Utilities",
            "subcategory":"Fuel Oil & Lpg",
            "type":"Services"
        }
    ],
    "sg:phone":"+1 760 742 4467",
    "sg:postcode":"92061",
    "sg:province":"CA",
    "sg:tags":[
        "firewood"
    ],
    "wof:name":"Chris The Woodcutter",
    "wof:placetype":"venue"
},
  "geometry": {"coordinates":[-116.894841,33.294616],"type":"Point"}
}