{
  "type": "Feature",
  "properties": {
    "addr:full":"1601 28th St Sacramento CA 95816",
    "addr:housenumber":"1601",
    "addr:postcode":"95816",
    "addr:street":"28Th St",
    "iso:country":"US",
    "sg:address":"1601 28th St",
    "sg:city":"Sacramento",
    "sg:classifiers":[
        {
            "category":"Personal",
            "subcategory":"Beauty Salon",
            "type":"Services"
        }
    ],
    "sg:phone":"+1 916 454 2800",
    "sg:postcode":"95816",
    "sg:province":"CA",
    "sg:tags":[
        "hair"
    ],
    "wof:name":"Studio 28 Inc",
    "wof:placetype":"venue"
},
  "geometry": {"coordinates":[-121.47199999999999,38.567101],"type":"Point"}
}