{
  "type": "Feature",
  "properties": {
    "iso:country":"US",
    "sg:address":"8640 Auto Center Dr",
    "sg:city":"Buena Park",
    "sg:classifiers":[
        {
            "category":"Real Estate",
            "subcategory":"Real Estate Operator",
            "type":"Services"
        }
    ],
    "sg:phone":"+1 714 739 0998",
    "sg:postcode":"90621",
    "sg:province":"CA",
    "sg:tags":[
        "apartment"
    ],
    "wof:name":"Casitas Apartments",
    "wof:placetype":"venue"
},
  "geometry": {"coordinates":[-117.98506500000001,33.859596],"type":"Point"}
}