{
  "type": "Feature",
  "properties": {
    "iso:country":"US",
    "sg:address":"29250 State Rte 120",
    "sg:city":"Escalon",
    "sg:classifiers":[
        {
            "category":"Wholesale",
            "subcategory":"Farm Supplies",
            "type":"Manufacturing & Wholesale Goods"
        }
    ],
    "sg:phone":"+1 209 838 7550",
    "sg:postcode":"95320",
    "sg:province":"CA",
    "sg:tags":[
        "feed"
    ],
    "wof:name":"Ted Nuce Autos & Trailers",
    "wof:placetype":"venue"
},
  "geometry": {"coordinates":[-120.94315400000001,37.793718],"type":"Point"}
}