{
  "type": "Feature",
  "properties": {
    "iso:country":"US",
    "sg:address":"247 Holiday Hills Dr",
    "sg:city":"Martinez",
    "sg:classifiers":[
        {
            "category":"Professional",
            "subcategory":"Management & Consulting",
            "type":"Services"
        }
    ],
    "sg:phone":"+1 925 313 9194",
    "sg:postcode":"94553",
    "sg:province":"CA",
    "sg:tags":[
        "consultant",
        "safety"
    ],
    "wof:name":"Code 3 Safety Inc",
    "wof:placetype":"venue"
},
  "geometry": {"coordinates":[-122.091444,37.992552],"type":"Point"}
}