{
  "type": "Feature",
  "properties": {
    "addr:full":"4712 Woodhaven Dr Yorba Linda CA 92886",
    "addr:housenumber":"4712",
    "addr:postcode":"92886",
    "addr:street":"Woodhaven Dr",
    "iso:country":"US",
    "sg:address":"4712 Woodhaven Dr",
    "sg:city":"Yorba Linda",
    "sg:classifiers":[
        {
            "category":"Manufacturing",
            "subcategory":"Rubber & Plastics",
            "type":"Manufacturing & Wholesale Goods"
        }
    ],
    "sg:phone":"+1 714 996 3898",
    "sg:postcode":"92886",
    "sg:province":"CA",
    "sg:tags":[
        "organizer",
        "closet",
        "mfg"
    ],
    "wof:name":"Closet Shoelutions",
    "wof:placetype":"venue"
},
  "geometry": {"coordinates":[-117.822587,33.892956],"type":"Point"}
}