{
  "type": "Feature",
  "properties": {
    "iso:country":"US",
    "sg:address":"1255 Post St",
    "sg:city":"San Francisco",
    "sg:classifiers":[
        {
            "category":"Real Estate",
            "subcategory":"Developer",
            "type":"Services"
        }
    ],
    "sg:phone":"+1 415 928 3868",
    "sg:postcode":"94109",
    "sg:province":"CA",
    "wof:name":"Sunnybay Development Corp",
    "wof:placetype":"venue"
},
  "geometry": {"coordinates":[-122.422486,37.786447],"type":"Point"}
}