{
  "type": "Feature",
  "properties": {
    "addr:full":"550 Deep Valley Dr Rolling Hls Ests CA 90274",
    "addr:housenumber":"550",
    "addr:postcode":"90274",
    "addr:street":"Deep Valley Dr Rolling",
    "iso:country":"US",
    "sg:address":"550 Deep Valley Dr",
    "sg:city":"Rolling Hls Ests",
    "sg:classifiers":[
        {
            "category":"Shopping",
            "subcategory":"Gifts & Souvenirs",
            "type":"Retail Goods"
        }
    ],
    "sg:phone":"+1 310 544 1101",
    "sg:postcode":"90274",
    "sg:province":"CA",
    "sg:tags":[
        "shop"
    ],
    "wof:name":"Sharper Image",
    "wof:placetype":"venue"
},
  "geometry": {"coordinates":[-118.374668,33.772885],"type":"Point"}
}