{
  "type": "Feature",
  "properties": {
    "iso:country":"US",
    "sg:address":"3210 Mission Way",
    "sg:city":"Rocklin",
    "sg:classifiers":[
        {
            "category":"Health Services",
            "subcategory":"Chiropractor",
            "type":"Services"
        }
    ],
    "sg:phone":"+1 916 782 3141",
    "sg:postcode":"95677",
    "sg:province":"CA",
    "wof:name":"Kness Chiropractic",
    "wof:placetype":"venue"
},
  "geometry": {"coordinates":[-121.23895899999999,38.802107],"type":"Point"}
}