{
  "type": "Feature",
  "properties": {
    "iso:country":"US",
    "sg:address":"1938 Old Middlefield Way",
    "sg:city":"Mountain View",
    "sg:classifiers":[
        {
            "category":"Building & Trades",
            "subcategory":"Construction",
            "type":"Services"
        }
    ],
    "sg:phone":"+1 650 961 8922",
    "sg:postcode":"94043",
    "sg:province":"CA",
    "sg:tags":[
        "roofing",
        "contractor"
    ],
    "sg:website":"castoroofing.net",
    "wof:name":"Casto Roofing Inc",
    "wof:placetype":"venue"
},
  "geometry": {"coordinates":[-122.087997,37.414398],"type":"Point"}
}