{
  "type": "Feature",
  "properties": {
    "addr:full":"311 E Valley Blvd Colton CA 92324",
    "addr:housenumber":"311",
    "addr:postcode":"92324",
    "addr:street":"E Valley Blvd",
    "iso:country":"US",
    "sg:address":"311 E Valley Blvd",
    "sg:city":"Colton",
    "sg:classifiers":[
        {
            "category":"Autos & Motor Vehicles",
            "subcategory":"Auto Supplies",
            "type":"Retail Goods"
        }
    ],
    "sg:phone":"+1 909 825 3333",
    "sg:postcode":"92324",
    "sg:province":"CA",
    "sg:tags":[
        "automobile",
        "parts"
    ],
    "wof:name":"Genuine Auto Parts",
    "wof:placetype":"venue"
},
  "geometry": {"coordinates":[-117.321071,34.066546],"type":"Point"}
}