{
  "type": "Feature",
  "properties": {
    "addr:full":"2101 W Beverly Blvd Montebello CA 90640",
    "addr:housenumber":"2101",
    "addr:postcode":"90640",
    "addr:street":"W Beverly Blvd",
    "iso:country":"US",
    "sg:address":"2101 W Beverly Blvd",
    "sg:city":"Montebello",
    "sg:classifiers":[
        {
            "category":"Health Services",
            "subcategory":"Doctor",
            "type":"Services"
        }
    ],
    "sg:phone":"+1 323 725 6625",
    "sg:postcode":"90640",
    "sg:province":"CA",
    "wof:name":"Lin Peter S MD",
    "wof:placetype":"venue"
},
  "geometry": {"coordinates":[-118.121002,34.020401],"type":"Point"}
}