{
  "type": "Feature",
  "properties": {
    "addr:full":"1228 Main St Delano CA 93215",
    "addr:housenumber":"1228",
    "addr:postcode":"93215",
    "addr:street":"Main St",
    "iso:country":"US",
    "sg:address":"1228 Main St",
    "sg:city":"Delano",
    "sg:classifiers":[
        {
            "category":"Shopping",
            "subcategory":"Department Store",
            "type":"Retail Goods"
        },
        {
            "category":"Shopping",
            "subcategory":"Beauty & Cosmetics",
            "type":"Retail Goods"
        },
        {
            "category":"Home & Garden",
            "subcategory":"Home Furnishings",
            "type":"Retail Goods"
        },
        {
            "category":"Shopping",
            "type":"Retail Goods"
        },
        {
            "category":"Shopping",
            "subcategory":"Catalog Store",
            "type":"Retail Goods"
        },
        {
            "category":"Professional",
            "subcategory":"Art Services",
            "type":"Services"
        },
        {
            "category":"Shopping",
            "subcategory":"Shoes",
            "type":"Retail Goods"
        },
        {
            "category":"Shopping",
            "subcategory":"Jewelry",
            "type":"Retail Goods"
        }
    ],
    "sg:phone":"+1 800 222 6161",
    "sg:postcode":"93215",
    "sg:province":"CA",
    "sg:tags":[
        "draperies",
        "designer",
        "vertical",
        "supply",
        "merchandise",
        "blinds-venetian",
        "jeweler",
        "equipment",
        "window",
        "interior",
        "treatment",
        "housewares",
        "curtain",
        "showroom",
        "decorator"
    ],
    "sg:website":"http://www.jcpenney.com",
    "wof:name":"JCPenney",
    "wof:placetype":"venue"
},
  "geometry": {"coordinates":[-119.246347,35.772034],"type":"Point"}
}