{
  "type": "Feature",
  "properties": {
    "addr:full":"5422 W Sunset Boulevard Los Angeles CA 90027",
    "addr:housenumber":"5422",
    "addr:postcode":"90027",
    "addr:street":"W Sunset Boulevard",
    "iso:country":"US",
    "sg:address":"5422 W Sunset Boulevard",
    "sg:city":"Los Angeles",
    "sg:classifiers":[
        {
            "category":"Education",
            "subcategory":"University",
            "type":"Public Place"
        }
    ],
    "sg:phone":"+1 323 468 0402",
    "sg:postcode":"90027",
    "sg:province":"CA",
    "sg:tags":[
        "college"
    ],
    "wof:name":"Intrl Career Development Center",
    "wof:placetype":"venue"
},
  "geometry": {"coordinates":[-118.307451,34.098199],"type":"Point"}
}