{
  "type": "Feature",
  "properties": {
    "iso:country":"US",
    "sg:address":"18939 Magnolia St",
    "sg:city":"Fountain Valley",
    "sg:classifiers":[
        {
            "category":"Personal",
            "type":"Services"
        }
    ],
    "sg:phone":"+1 714 968 3173",
    "sg:postcode":"92708",
    "sg:province":"CA",
    "sg:tags":[
        "sewing",
        "alteration"
    ],
    "wof:name":"My Huong Tailor Shop",
    "wof:placetype":"venue"
},
  "geometry": {"coordinates":[-117.971001,33.687599],"type":"Point"}
}