{
  "type": "Feature",
  "properties": {
    "iso:country":"US",
    "sg:address":"420 N E St",
    "sg:city":"Porterville",
    "sg:classifiers":[
        {
            "category":"Social Services",
            "subcategory":"Child Care",
            "type":"Services"
        }
    ],
    "sg:phone":"+1 559 782 1234",
    "sg:postcode":"93257",
    "sg:province":"CA",
    "wof:name":"Krayola Korner",
    "wof:placetype":"venue"
},
  "geometry": {"coordinates":[-119.02009,36.074278],"type":"Point"}
}