{
  "type": "Feature",
  "properties": {
    "iso:country":"US",
    "sg:address":"2525 E Fremont St",
    "sg:city":"Stockton",
    "sg:classifiers":[
        {
            "category":"Shopping",
            "subcategory":"Pharmacy",
            "type":"Retail Goods"
        }
    ],
    "sg:phone":"+1 209 948 0546",
    "sg:postcode":"95205",
    "sg:province":"CA",
    "wof:name":"Fremont Center Pharmacy",
    "wof:placetype":"venue"
},
  "geometry": {"coordinates":[-121.254615,37.966234],"type":"Point"}
}