{
  "type": "Feature",
  "properties": {
    "addr:full":"3755 Avocado Blvd La Mesa CA 91941",
    "addr:housenumber":"3755",
    "addr:postcode":"91941",
    "addr:street":"Avocado Blvd",
    "iso:country":"US",
    "sg:address":"3755 Avocado Blvd",
    "sg:city":"La Mesa",
    "sg:classifiers":[
        {
            "category":"Shopping",
            "subcategory":"Stationery & Office Supplies",
            "type":"Retail Goods"
        }
    ],
    "sg:phone":"+1 619 660 7673",
    "sg:postcode":"91941",
    "sg:province":"CA",
    "sg:tags":[
        "equipment"
    ],
    "wof:name":"Rose Printed Products",
    "wof:placetype":"venue"
},
  "geometry": {"coordinates":[-116.961826,32.74758],"type":"Point"}
}