{
  "type": "Feature",
  "properties": {
    "addr:full":"491 Madonna Rd San Luis Obispo CA 93405",
    "addr:housenumber":"491",
    "addr:postcode":"93405",
    "addr:street":"Madonna Rd",
    "iso:country":"US",
    "sg:address":"491 Madonna Rd",
    "sg:city":"San Luis Obispo",
    "sg:classifiers":[
        {
            "category":"Utilities",
            "subcategory":"Mobile Phone",
            "type":"Services"
        }
    ],
    "sg:phone":"+1 805 546 1035",
    "sg:postcode":"93405",
    "sg:province":"CA",
    "sg:tags":[
        "telephone",
        "cellular"
    ],
    "wof:name":"Go Wireless",
    "wof:placetype":"venue"
},
  "geometry": {"coordinates":[-120.680004,35.261266],"type":"Point"}
}