{
  "type": "Feature",
  "properties": {
    "addr:full":"386 Grand Ave South San Francisco CA 94080",
    "addr:housenumber":"386",
    "addr:postcode":"94080",
    "addr:street":"Grand Ave",
    "iso:country":"US",
    "sg:address":"386 Grand Ave",
    "sg:city":"South San Francisco",
    "sg:classifiers":[
        {
            "category":"Retail",
            "subcategory":"Laundry & Dry Cleaning",
            "type":"Services"
        }
    ],
    "sg:phone":"+1 650 589 0821",
    "sg:postcode":"94080",
    "sg:province":"CA",
    "sg:website":"dvw.ssf.net/company_info.php?id=...",
    "wof:name":"Central Cleaners",
    "wof:placetype":"venue"
},
  "geometry": {"coordinates":[-122.412003,37.655701],"type":"Point"}
}