{
  "type": "Feature",
  "properties": {
    "addr:full":"1515 Ocean Ave Santa Monica CA 90401",
    "addr:housenumber":"1515",
    "addr:postcode":"90401",
    "addr:street":"Ocean Ave",
    "iso:country":"US",
    "sg:address":"1515 Ocean Ave",
    "sg:city":"Santa Monica",
    "sg:classifiers":[
        {
            "category":"Travel",
            "subcategory":"Hotels & Motels",
            "type":"Entertainment"
        }
    ],
    "sg:phone":"+1 310 395 6133",
    "sg:postcode":"90401",
    "sg:province":"CA",
    "wof:name":"Pacific Sands Motel",
    "wof:placetype":"venue"
},
  "geometry": {"coordinates":[-118.495026,34.011668],"type":"Point"}
}