{
  "type": "Feature",
  "properties": {
    "iso:country":"US",
    "sg:address":"16803 Mitchell Creek Dr",
    "sg:city":"Fort Bragg",
    "sg:classifiers":[
        {
            "category":"Building & Trades",
            "subcategory":"Cleaning & Sanitation",
            "type":"Services"
        }
    ],
    "sg:phone":"+1 707 462 0166",
    "sg:postcode":"95437",
    "sg:province":"CA",
    "sg:tags":[
        "venetian",
        "blind"
    ],
    "wof:name":"Mendo Shine-A-Blind",
    "wof:placetype":"venue"
},
  "geometry": {"coordinates":[-123.77428,39.392612],"type":"Point"}
}