{
  "type": "Feature",
  "properties": {
    "addr:full":"1028 N Davis Rd Salinas CA 93907",
    "addr:housenumber":"1028",
    "addr:postcode":"93907",
    "addr:street":"N Davis Rd",
    "iso:country":"US",
    "sg:address":"1028 N Davis Rd",
    "sg:city":"Salinas",
    "sg:classifiers":[
        {
            "category":"Personal",
            "subcategory":"Beauty Salon",
            "type":"Services"
        },
        {
            "category":"Personal",
            "subcategory":"Nail Salon",
            "type":"Services"
        }
    ],
    "sg:phone":"+1 831 422 3242",
    "sg:postcode":"93907",
    "sg:province":"CA",
    "wof:name":"10 Top Nails",
    "wof:placetype":"venue"
},
  "geometry": {"coordinates":[-121.668305,36.694367],"type":"Point"}
}