{
  "type": "Feature",
  "properties": {
    "iso:country":"US",
    "sg:address":"700 Arneill Rd",
    "sg:city":"Camarillo",
    "sg:classifiers":[
        {
            "category":"Autos & Motor Vehicles",
            "subcategory":"Fuel & Gas Station",
            "type":"Retail Goods"
        },
        {
            "category":"Autos & Motor Vehicles",
            "subcategory":"Auto Supplies",
            "type":"Retail Goods"
        },
        {
            "category":"Retail",
            "subcategory":"Auto Repair",
            "type":"Services"
        },
        {
            "category":"Government",
            "subcategory":"Office",
            "type":"Public Place"
        }
    ],
    "sg:phone":"+1 805 482 3465",
    "sg:postcode":"93010",
    "sg:province":"CA",
    "sg:tags":[
        "smog",
        "check",
        "tire"
    ],
    "wof:name":"Union 76 Central Plaza",
    "wof:placetype":"venue"
},
  "geometry": {"coordinates":[-119.039001,34.2248],"type":"Point"}
}