{
  "type": "Feature",
  "properties": {
    "iso:country":"US",
    "sg:address":"1325 Melrose Ave Ste C",
    "sg:city":"Modesto",
    "sg:classifiers":[
        {
            "category":"Health Services",
            "subcategory":"Doctor",
            "type":"Services"
        }
    ],
    "sg:phone":"+1 209 527 4585",
    "sg:postcode":"95350",
    "sg:province":"CA",
    "wof:name":"Bibi Salah MD",
    "wof:placetype":"venue"
},
  "geometry": {"coordinates":[-120.987644,37.662586],"type":"Point"}
}