{
  "type": "Feature",
  "properties": {
    "iso:country":"US",
    "sg:address":"1958 Tice Valley Blvd",
    "sg:city":"Walnut Creek",
    "sg:classifiers":[
        {
            "category":"Retail",
            "subcategory":"Laundry & Dry Cleaning",
            "type":"Services"
        }
    ],
    "sg:phone":"+1 925 939 8711",
    "sg:postcode":"94595",
    "sg:province":"CA",
    "sg:tags":[
        "cleaners"
    ],
    "wof:name":"Sparklizing Cleaners & Laundry",
    "wof:placetype":"venue"
},
  "geometry": {"coordinates":[-122.074012,37.877947],"type":"Point"}
}