{
  "type": "Feature",
  "properties": {
    "iso:country":"US",
    "sg:address":"15840 Ventura Blvd # 209",
    "sg:city":"Encino",
    "sg:classifiers":[
        {
            "category":"Professional",
            "subcategory":"Advertising",
            "type":"Services"
        }
    ],
    "sg:phone":"+1 818 995 6597",
    "sg:postcode":"91436",
    "sg:province":"CA",
    "sg:tags":[
        "advertising-broadcast",
        "film"
    ],
    "wof:name":"Art Ministry",
    "wof:placetype":"venue"
},
  "geometry": {"coordinates":[-118.47824,34.155606],"type":"Point"}
}