{
  "type": "Feature",
  "properties": {
    "addr:full":"6640 Linne Rd Paso Robles CA 93446",
    "addr:housenumber":"6640",
    "addr:postcode":"93446",
    "addr:street":"Linne Rd",
    "iso:country":"US",
    "sg:address":"6640 Linne Rd",
    "sg:city":"Paso Robles",
    "sg:classifiers":[
        {
            "category":"Manufacturing",
            "subcategory":"Electronics",
            "type":"Manufacturing & Wholesale Goods"
        }
    ],
    "sg:phone":"+1 805 239 8232",
    "sg:postcode":"93446",
    "sg:province":"CA",
    "sg:tags":[
        "equipment",
        "mfg",
        "communication"
    ],
    "wof:name":"Communications Plus",
    "wof:placetype":"venue"
},
  "geometry": {"coordinates":[-120.573137,35.597604],"type":"Point"}
}