{
  "type": "Feature",
  "properties": {
    "addr:full":"6310 San Vicente Boulevard Los Angeles CA 90048",
    "addr:housenumber":"6310",
    "addr:postcode":"90048",
    "addr:street":"San Vicente Boulevard",
    "iso:country":"US",
    "sg:address":"6310 San Vicente Boulevard",
    "sg:city":"Los Angeles",
    "sg:classifiers":[
        {
            "category":"Professional",
            "subcategory":"Lawyer & Legal Services",
            "type":"Services"
        }
    ],
    "sg:phone":"+1 323 549 6908",
    "sg:postcode":"90048",
    "sg:province":"CA",
    "sg:website":"www.bkwlegal.com",
    "wof:name":"Weissman Steven J",
    "wof:placetype":"venue"
},
  "geometry": {"coordinates":[-118.367305,34.060773],"type":"Point"}
}