{
  "type": "Feature",
  "properties": {
    "addr:full":"19925 Stevens Creek Blvd Cupertino CA 95014",
    "addr:housenumber":"19925",
    "addr:postcode":"95014",
    "addr:street":"Stevens Creek Blvd",
    "iso:country":"US",
    "sg:address":"19925 Stevens Creek Blvd",
    "sg:city":"Cupertino",
    "sg:classifiers":[
        {
            "category":"Banks & Credit Unions",
            "subcategory":"Bank",
            "type":"Services"
        }
    ],
    "sg:phone":"+1 408 997 9832",
    "sg:postcode":"95014",
    "sg:province":"CA",
    "sg:tags":[
        "loan",
        "real estate"
    ],
    "wof:name":"Los Gatos Lending Connection",
    "wof:placetype":"venue"
},
  "geometry": {"coordinates":[-122.022649,37.32292],"type":"Point"}
}