{
  "type": "Feature",
  "properties": {
    "iso:country":"US",
    "sg:address":"202 Ann St",
    "sg:city":"Greenville",
    "sg:classifiers":[
        {
            "category":"Utilities",
            "subcategory":"Water",
            "type":"Services"
        }
    ],
    "sg:phone":"+1 530 258 3063",
    "sg:postcode":"95947",
    "sg:province":"CA",
    "sg:tags":[
        "company",
        "sewage"
    ],
    "wof:name":"Indian Vly Cmnty Svc Dist",
    "wof:placetype":"venue"
},
  "geometry": {"coordinates":[-120.952639,40.140679],"type":"Point"}
}