{
  "type": "Feature",
  "properties": {
    "addr:full":"40 Wembley Dr Daly City CA 94015",
    "addr:housenumber":"40",
    "addr:postcode":"94015",
    "addr:street":"Wembley Dr",
    "iso:country":"US",
    "sg:address":"40 Wembley Dr",
    "sg:city":"Daly City",
    "sg:classifiers":[
        {
            "category":"Museum",
            "type":"Entertainment"
        }
    ],
    "sg:phone":"+1 650 755 5123",
    "sg:postcode":"94015",
    "sg:province":"CA",
    "wof:name":"Colma History Guild Museum",
    "wof:placetype":"venue"
},
  "geometry": {"coordinates":[-122.469514,37.66278],"type":"Point"}
}