{
  "type": "Feature",
  "properties": {
    "addr:full":"83680 Indio Blvd Indio CA 92201",
    "addr:housenumber":"83680",
    "addr:postcode":"92201",
    "addr:street":"Indio Blvd",
    "iso:country":"US",
    "sg:address":"83680 Indio Blvd",
    "sg:city":"Indio",
    "sg:classifiers":[
        {
            "category":"Autos & Motor Vehicles",
            "subcategory":"Auto Supplies",
            "type":"Retail Goods"
        }
    ],
    "sg:phone":"+1 760 342 1615",
    "sg:postcode":"92201",
    "sg:province":"CA",
    "sg:tags":[
        "trade",
        "contractor"
    ],
    "wof:name":"Window Tinting Masters",
    "wof:placetype":"venue"
},
  "geometry": {"coordinates":[-116.20316,33.712745],"type":"Point"}
}