{
  "type": "Feature",
  "properties": {
    "iso:country":"US",
    "sg:address":"30 Chestnut Avenue",
    "sg:city":"South San Francisco",
    "sg:classifiers":[
        {
            "category":"Food & Beverages",
            "subcategory":"Groceries & Convenience Stores",
            "type":"Retail Goods"
        }
    ],
    "sg:phone":"+1 650 952 8867",
    "sg:postcode":"94080",
    "sg:province":"CA",
    "sg:website":"safeway.com",
    "wof:name":"Safeway",
    "wof:placetype":"venue"
},
  "geometry": {"coordinates":[-122.432573,37.656],"type":"Point"}
}