{
  "type": "Feature",
  "properties": {
    "iso:country":"US",
    "sg:address":"2240 A St",
    "sg:city":"Santa Maria",
    "sg:classifiers":[
        {
            "category":"Building & Trades",
            "subcategory":"Construction",
            "type":"Services"
        }
    ],
    "sg:phone":"+1 805 928 0110",
    "sg:postcode":"93455",
    "sg:province":"CA",
    "sg:tags":[
        "maker",
        "cabinet"
    ],
    "wof:name":"Wood Concepts Unlimted Inc",
    "wof:placetype":"venue"
},
  "geometry": {"coordinates":[-120.464106,34.919136],"type":"Point"}
}