{
  "type": "Feature",
  "properties": {
    "iso:country":"US",
    "sg:address":"1795 Ofarrell St",
    "sg:city":"San Francisco",
    "sg:classifiers":[
        {
            "category":"Building & Trades",
            "subcategory":"Landscaping Services",
            "type":"Services"
        }
    ],
    "sg:phone":"+1 415 673 1561",
    "sg:postcode":"94115",
    "sg:province":"CA",
    "sg:tags":[
        "computer",
        "landscape",
        "related"
    ],
    "wof:name":"Englenton Consulting",
    "wof:placetype":"venue"
},
  "geometry": {"coordinates":[-122.433111,37.783187],"type":"Point"}
}