{
  "type": "Feature",
  "properties": {
    "addr:full":"1500 Vista Club Cir Santa Clara CA 95054",
    "addr:housenumber":"1500",
    "addr:postcode":"95054",
    "addr:street":"Vista Club Cir",
    "iso:country":"US",
    "sg:address":"1500 Vista Club Cir",
    "sg:city":"Santa Clara",
    "sg:classifiers":[
        {
            "category":"Real Estate",
            "subcategory":"Real Estate Operator",
            "type":"Services"
        }
    ],
    "sg:phone":"+1 408 496 6300",
    "sg:postcode":"95054",
    "sg:province":"CA",
    "sg:tags":[
        "apartment"
    ],
    "sg:website":"www.bellavista-apartments.com",
    "wof:name":"Bella Vista Apartments",
    "wof:placetype":"venue"
},
  "geometry": {"coordinates":[-121.95366799999999,37.402561],"type":"Point"}
}