{
  "type": "Feature",
  "properties": {
    "iso:country":"US",
    "sg:address":"31360 Turner Rd",
    "sg:city":"Fort Bragg",
    "sg:classifiers":[
        {
            "category":"Professional",
            "type":"Services"
        }
    ],
    "sg:phone":"+1 707 964 9352",
    "sg:postcode":"95437",
    "sg:province":"CA",
    "wof:name":"Richard S Hines",
    "wof:placetype":"venue"
},
  "geometry": {"coordinates":[-123.789461,39.384877],"type":"Point"}
}