{
  "type": "Feature",
  "properties": {
    "iso:country":"US",
    "sg:address":"1505 Soquel Drive",
    "sg:city":"Santa Cruz",
    "sg:classifiers":[
        {
            "category":"Health Services",
            "subcategory":"Doctor",
            "type":"Services"
        }
    ],
    "sg:phone":"+1 831 475 4024",
    "sg:postcode":"95065",
    "sg:province":"CA",
    "sg:tags":[
        "orthopedist"
    ],
    "sg:website":"www.santacruzortho.com",
    "wof:name":"Abidi Nicholas A MD",
    "wof:placetype":"venue"
},
  "geometry": {"coordinates":[-121.985198,36.987852],"type":"Point"}
}