{
  "type": "Feature",
  "properties": {
    "addr:full":"322 Cortland Ave San Francisco CA 94110",
    "addr:housenumber":"322",
    "addr:postcode":"94110",
    "addr:street":"Cortland Ave",
    "iso:country":"US",
    "sg:address":"322 Cortland Ave",
    "sg:city":"San Francisco",
    "sg:classifiers":[
        {
            "category":"Building & Trades",
            "subcategory":"Landscaping Services",
            "type":"Services"
        }
    ],
    "sg:phone":"+1 415 643 4705",
    "sg:postcode":"94110",
    "sg:province":"CA",
    "sg:tags":[
        "landscape"
    ],
    "wof:name":"Garden Route Co",
    "wof:placetype":"venue"
},
  "geometry": {"coordinates":[-122.417933,37.739127],"type":"Point"}
}