{
  "type": "Feature",
  "properties": {
    "iso:country":"US",
    "sg:address":"3400 Shelby St",
    "sg:city":"Ontario",
    "sg:classifiers":[
        {
            "category":"Travel",
            "subcategory":"Hotels & Motels",
            "type":"Entertainment"
        }
    ],
    "sg:phone":"+1 877 574 2464",
    "sg:postcode":"91764",
    "sg:province":"CA",
    "sg:tags":[
        "lodging"
    ],
    "sg:website":"http://book.bestwestern.com/bestwestern/priceAvail.do?propertyCode=05655&cm_mmc=IYP-_-YP-_-property-_-5655",
    "wof:name":"Best Western Innsuites Hotel & Suites Ontario",
    "wof:placetype":"venue"
},
  "geometry": {"coordinates":[-117.57785,34.07013],"type":"Point"}
}