{
  "type": "Feature",
  "properties": {
    "iso:country":"US",
    "sg:address":"3727 Park Mountain Dr",
    "sg:city":"Bakersfield",
    "sg:classifiers":[
        {
            "category":"Building & Trades",
            "subcategory":"Construction",
            "type":"Services"
        }
    ],
    "sg:phone":"+1 661 399 4700",
    "sg:postcode":"93308",
    "sg:province":"CA",
    "sg:tags":[
        "home",
        "builder"
    ],
    "wof:name":"Nader Development",
    "wof:placetype":"venue"
},
  "geometry": {"coordinates":[-119.027194,35.440054],"type":"Point"}
}