{
  "type": "Feature",
  "properties": {
    "addr:full":"14484 Penasquitos Dr San Diego CA 92129",
    "addr:housenumber":"14484",
    "addr:postcode":"92129",
    "addr:street":"Penasquitos Dr",
    "iso:country":"US",
    "sg:address":"14484 Penasquitos Dr",
    "sg:city":"San Diego",
    "sg:classifiers":[
        {
            "category":"Organizations",
            "subcategory":"Religious Organization",
            "type":"Services"
        }
    ],
    "sg:phone":"+1 858 672 3466",
    "sg:postcode":"92129",
    "sg:province":"CA",
    "sg:tags":[
        "church"
    ],
    "sg:website":"www.plc-church.org",
    "wof:name":"Penasquitos Lutheran Church",
    "wof:placetype":"venue"
},
  "geometry": {"coordinates":[-117.09145700000001,32.978129],"type":"Point"}
}