{
  "type": "Feature",
  "properties": {
    "addr:full":"245 Vista Village Dr Vista CA 92083",
    "addr:housenumber":"245",
    "addr:postcode":"92083",
    "addr:street":"Vista Village Dr",
    "iso:country":"US",
    "sg:address":"245 Vista Village Dr",
    "sg:city":"Vista",
    "sg:classifiers":[
        {
            "category":"Banks & Credit Unions",
            "subcategory":"Bank",
            "type":"Services"
        }
    ],
    "sg:phone":"+1 760 726 2122",
    "sg:postcode":"92083",
    "sg:province":"CA",
    "sg:website":"www.sdnb.com",
    "wof:name":"San Diego National Bank",
    "wof:placetype":"venue"
},
  "geometry": {"coordinates":[-117.248536,33.197424],"type":"Point"}
}