{
  "type": "Feature",
  "properties": {
    "addr:full":"19934 Keswick Ln Huntington Beach CA 92646",
    "addr:housenumber":"19934",
    "addr:postcode":"92646",
    "addr:street":"Keswick Ln",
    "iso:country":"US",
    "sg:address":"19934 Keswick Ln",
    "sg:city":"Huntington Beach",
    "sg:classifiers":[
        {
            "category":"Shopping",
            "subcategory":"Computers & Home Electronics",
            "type":"Retail Goods"
        }
    ],
    "sg:phone":"+1 714 963 1546",
    "sg:postcode":"92646",
    "sg:province":"CA",
    "wof:name":"Rmm Productions",
    "wof:placetype":"venue"
},
  "geometry": {"coordinates":[-117.957945,33.673351],"type":"Point"}
}