{
  "type": "Feature",
  "properties": {
    "addr:full":"1630 I St Modesto CA 95354",
    "addr:housenumber":"1630",
    "addr:postcode":"ca 95354",
    "addr:street":"I St",
    "iso:country":"US",
    "sg:address":"1630 I St",
    "sg:city":"Modesto",
    "sg:classifiers":[
        {
            "category":"Professional",
            "subcategory":"Lawyer & Legal Services",
            "type":"Services"
        }
    ],
    "sg:phone":"+1 209 524 4807",
    "sg:postcode":"95354",
    "sg:province":"CA",
    "wof:name":"ISAAC TERRI L ATTORNEY AT LAW",
    "wof:placetype":"venue"
},
  "geometry": {"coordinates":[-120.993039,37.643946],"type":"Point"}
}