{
  "type": "Feature",
  "properties": {
    "addr:full":"9247 Alden Dr Beverly Hills CA 90210",
    "addr:housenumber":"9247",
    "addr:postcode":"90210",
    "addr:street":"Alden Dr",
    "iso:country":"US",
    "sg:address":"9247 Alden Dr",
    "sg:city":"Beverly Hills",
    "sg:classifiers":[
        {
            "category":"Retail",
            "subcategory":"Portrait Studio",
            "type":"Services"
        }
    ],
    "sg:phone":"+1 310 888 2806",
    "sg:postcode":"90210",
    "sg:province":"CA",
    "sg:tags":[
        "photographer"
    ],
    "wof:name":"Concrete & Clay",
    "wof:placetype":"venue"
},
  "geometry": {"coordinates":[-118.39239000000001,34.075353],"type":"Point"}
}