{
  "type": "Feature",
  "properties": {
    "iso:country":"US",
    "sg:address":"10956 Klingerman St",
    "sg:city":"El Monte",
    "sg:classifiers":[
        {
            "category":"Wholesale",
            "subcategory":"Machinery & Supplies",
            "type":"Manufacturing & Wholesale Goods"
        }
    ],
    "sg:phone":"+1 626 452 8384",
    "sg:postcode":"91733",
    "sg:province":"CA",
    "sg:tags":[
        "baker"
    ],
    "wof:name":"Partybake Insighters Inc",
    "wof:placetype":"venue"
},
  "geometry": {"coordinates":[-118.035769,34.055957],"type":"Point"}
}