{
  "type": "Feature",
  "properties": {
    "iso:country":"US",
    "sg:address":"1343 Logan Ave",
    "sg:city":"Costa Mesa",
    "sg:classifiers":[
        {
            "category":"Retail",
            "subcategory":"Auto Repair",
            "type":"Services"
        }
    ],
    "sg:phone":"+1 949 673 3357",
    "sg:postcode":"92626",
    "sg:province":"CA",
    "sg:tags":[
        "body",
        "shop"
    ],
    "wof:name":"Euro Am",
    "wof:placetype":"venue"
},
  "geometry": {"coordinates":[-117.914001,33.678699],"type":"Point"}
}