{
  "type": "Feature",
  "properties": {
    "iso:country":"US",
    "sg:address":"1133 W Lomita Blvd",
    "sg:city":"Harbor City",
    "sg:classifiers":[
        {
            "category":"Retail",
            "subcategory":"Auto Repair",
            "type":"Services"
        }
    ],
    "sg:phone":"+1 310 530 3469",
    "sg:postcode":"90710",
    "sg:province":"CA",
    "sg:tags":[
        "repairing",
        "automobile"
    ],
    "wof:name":"Golden Impact Svc",
    "wof:placetype":"venue"
},
  "geometry": {"coordinates":[-118.296837,33.797863],"type":"Point"}
}