{
  "type": "Feature",
  "properties": {
    "iso:country":"US",
    "sg:address":"649 S Ridgeley Dr",
    "sg:city":"Los Angeles",
    "sg:classifiers":[
        {
            "category":"Communications",
            "subcategory":"Film & Video Production",
            "type":"Services"
        }
    ],
    "sg:phone":"+1 323 938 6338",
    "sg:postcode":"90036",
    "sg:province":"CA",
    "sg:tags":[
        "audio"
    ],
    "wof:name":"Lil Black Man Productions",
    "wof:placetype":"venue"
},
  "geometry": {"coordinates":[-118.35046,34.063698],"type":"Point"}
}