{
  "type": "Feature",
  "properties": {
    "addr:full":"16340 Perris Blvd Moreno Valley CA 92551",
    "addr:housenumber":"16340",
    "addr:postcode":"92551",
    "addr:street":"Perris Blvd",
    "iso:country":"US",
    "sg:address":"16340 Perris Blvd",
    "sg:city":"Moreno Valley",
    "sg:classifiers":[
        {
            "category":"Freight",
            "type":"Transportation"
        }
    ],
    "sg:phone":"+1 951 247 5555",
    "sg:postcode":"92551",
    "sg:province":"CA",
    "sg:tags":[
        "commercial",
        "storage"
    ],
    "wof:name":"Americas Self Storage",
    "wof:placetype":"venue"
},
  "geometry": {"coordinates":[-117.22610299999999,33.882758],"type":"Point"}
}