{
  "type": "Feature",
  "properties": {
    "addr:full":"9815 Topeka Dr Northridge CA 91324",
    "addr:housenumber":"9815",
    "addr:postcode":"91324",
    "addr:street":"Topeka Dr",
    "iso:country":"US",
    "sg:address":"9815 Topeka Dr",
    "sg:city":"Northridge",
    "sg:classifiers":[
        {
            "category":"Education",
            "subcategory":"School",
            "type":"Public Place"
        }
    ],
    "sg:phone":"+1 818 886 2266",
    "sg:postcode":"91324",
    "sg:province":"CA",
    "sg:tags":[
        "elementary"
    ],
    "wof:name":"Topeka Drive Elementary School",
    "wof:placetype":"venue"
},
  "geometry": {"coordinates":[-118.54577,34.248741],"type":"Point"}
}