{
  "type": "Feature",
  "properties": {
    "addr:full":"157 N Armstrong Ave Clovis CA 93611",
    "addr:housenumber":"157",
    "addr:postcode":"93611",
    "addr:street":"N Armstrong Ave",
    "iso:country":"US",
    "sg:address":"157 N Armstrong Ave",
    "sg:city":"Clovis",
    "sg:classifiers":[
        {
            "category":"Organizations",
            "subcategory":"Non-profit Organization",
            "type":"Services"
        }
    ],
    "sg:phone":"+1 559 323 5550",
    "sg:postcode":"93611",
    "sg:province":"CA",
    "sg:tags":[
        "disability"
    ],
    "wof:name":"Thongma Home",
    "wof:placetype":"venue"
},
  "geometry": {"coordinates":[-119.67285,36.828278],"type":"Point"}
}