{
  "type": "Feature",
  "properties": {
    "iso:country":"US",
    "sg:address":"1300 E Burnett St",
    "sg:city":"Signal Hill",
    "sg:classifiers":[
        {
            "category":"Building & Trades",
            "subcategory":"Construction",
            "type":"Services"
        }
    ],
    "sg:phone":"+1 562 595 1601",
    "sg:postcode":"90755",
    "sg:province":"CA",
    "sg:tags":[
        "excavating",
        "contractor"
    ],
    "sg:website":"www.lovcoconstruction.com",
    "wof:name":"Lovco Construction Inc",
    "wof:placetype":"venue"
},
  "geometry": {"coordinates":[-118.17415699999999,33.800751],"type":"Point"}
}