{
  "type": "Feature",
  "properties": {
    "addr:full":"2705 Divisadero St Fresno CA 93721",
    "addr:housenumber":"2705",
    "addr:postcode":"93721",
    "addr:street":"Divisadero St",
    "iso:country":"US",
    "sg:address":"2705 Divisadero St",
    "sg:city":"Fresno",
    "sg:classifiers":[
        {
            "category":"Banks & Credit Unions",
            "subcategory":"Bank",
            "type":"Services"
        }
    ],
    "sg:phone":"+1 559 264 4478",
    "sg:postcode":"93721",
    "sg:province":"CA",
    "wof:name":"County Bank",
    "wof:placetype":"venue"
},
  "geometry": {"coordinates":[-119.778403,36.743378],"type":"Point"}
}