{
  "type": "Feature",
  "properties": {
    "addr:full":"160 E El Camino Real Mountain View CA 94040",
    "addr:housenumber":"160",
    "addr:postcode":"94040",
    "addr:street":"E El Camino Real",
    "iso:country":"US",
    "sg:address":"160 E El Camino Real",
    "sg:city":"Mountain View",
    "sg:classifiers":[
        {
            "category":"Autos & Motor Vehicles",
            "subcategory":"Automobile Sales",
            "type":"Retail Goods"
        },
        {
            "category":"Retail",
            "subcategory":"Auto Repair",
            "type":"Services"
        }
    ],
    "sg:phone":"+1 650 567 9901",
    "sg:postcode":"94040",
    "sg:province":"CA",
    "sg:tags":[
        "car"
    ],
    "wof:name":"Mini of Mountain View",
    "wof:placetype":"venue"
},
  "geometry": {"coordinates":[-122.070999,37.379799],"type":"Point"}
}