{
  "type": "Feature",
  "properties": {
    "addr:full":"1100 Glendon Ave Los Angeles CA 90024",
    "addr:housenumber":"1100",
    "addr:postcode":"90024",
    "addr:street":"Glendon Ave",
    "iso:country":"US",
    "sg:address":"1100 Glendon Ave",
    "sg:city":"Los Angeles",
    "sg:classifiers":[
        {
            "category":"Museum",
            "subcategory":"Zoo",
            "type":"Entertainment"
        }
    ],
    "sg:phone":"+1 310 689 7400",
    "sg:postcode":"90024",
    "sg:province":"CA",
    "wof:name":"Zoo TV",
    "wof:placetype":"venue"
},
  "geometry": {"coordinates":[-118.44452800000001,34.06072],"type":"Point"}
}