{
  "type": "Feature",
  "properties": {
    "iso:country":"US",
    "sg:address":"7950 el Camino Real",
    "sg:city":"Atascadero",
    "sg:classifiers":[
        {
            "category":"Autos & Motor Vehicles",
            "subcategory":"Motorcycle Sales",
            "type":"Retail Goods"
        }
    ],
    "sg:phone":"+1 805 461 1818",
    "sg:postcode":"93422",
    "sg:province":"CA",
    "sg:tags":[
        "scooter"
    ],
    "wof:name":"Gary Bang Harley-Davidson",
    "wof:placetype":"venue"
},
  "geometry": {"coordinates":[-120.65674799999999,35.47791],"type":"Point"}
}