{
  "type": "Feature",
  "properties": {
    "addr:full":"2825 S Rodeo Gulch Rd Soquel CA 95073",
    "addr:housenumber":"2825",
    "addr:postcode":"95073",
    "addr:street":"S Rodeo Gulch Rd",
    "iso:country":"US",
    "sg:address":"2825 S Rodeo Gulch Rd",
    "sg:city":"Soquel",
    "sg:classifiers":[
        {
            "category":"Building & Trades",
            "subcategory":"Plumbing",
            "type":"Services"
        }
    ],
    "sg:phone":"+1 831 465 1083",
    "sg:postcode":"95073",
    "sg:province":"CA",
    "sg:tags":[
        "plumbing",
        "contractor"
    ],
    "wof:name":"D Ulery & Sons Plumbing",
    "wof:placetype":"venue"
},
  "geometry": {"coordinates":[-121.96965299999999,36.98747],"type":"Point"}
}