{
  "type": "Feature",
  "properties": {
    "iso:country":"US",
    "sg:address":"23000 Foresthill Rd",
    "sg:city":"Foresthill",
    "sg:classifiers":[
        {
            "category":"Health Services",
            "subcategory":"Doctor",
            "type":"Services"
        }
    ],
    "sg:phone":"+1 530 367 2229",
    "sg:postcode":"95631",
    "sg:province":"CA",
    "sg:tags":[
        "physician",
        "surgeon"
    ],
    "wof:name":"Foresthill Medical Ctr Inc",
    "wof:placetype":"venue"
},
  "geometry": {"coordinates":[-120.839941,39.012391],"type":"Point"}
}