{
  "type": "Feature",
  "properties": {
    "iso:country":"US",
    "sg:address":"2480 Erringer Rd",
    "sg:city":"Simi Valley",
    "sg:classifiers":[
        {
            "category":"Food & Beverages",
            "subcategory":"Groceries & Convenience Stores",
            "type":"Retail Goods"
        }
    ],
    "sg:phone":"+1 805 584 1663",
    "sg:postcode":"93065",
    "sg:province":"CA",
    "sg:tags":[
        "grocer"
    ],
    "wof:name":"Plaza Market",
    "wof:placetype":"venue"
},
  "geometry": {"coordinates":[-118.761287,34.280312],"type":"Point"}
}