{
  "type": "Feature",
  "properties": {
    "iso:country":"US",
    "sg:address":"742 W 133rd St",
    "sg:city":"Gardena",
    "sg:classifiers":[
        {
            "category":"Real Estate",
            "subcategory":"Real Estate Operator",
            "type":"Services"
        }
    ],
    "sg:phone":"+1 310 327 2009",
    "sg:postcode":"90247",
    "sg:province":"CA",
    "sg:tags":[
        "property",
        "lessor"
    ],
    "wof:name":"Kincaide Services",
    "wof:placetype":"venue"
},
  "geometry": {"coordinates":[-118.288588,33.911196],"type":"Point"}
}