{
  "type": "Feature",
  "properties": {
    "addr:full":"3141 Crow Canyon Pl San Ramon CA 94583",
    "addr:housenumber":"3141",
    "addr:postcode":"94583",
    "addr:street":"Crow Canyon Pl",
    "iso:country":"US",
    "sg:address":"3141 Crow Canyon Pl",
    "sg:city":"San Ramon",
    "sg:classifiers":[
        {
            "category":"Restaurant",
            "type":"Food & Drink"
        }
    ],
    "sg:menulink":"http://www.allmenus.com/ca/central-contra-costa/135691-jamba-juice/menu/",
    "sg:phone":"+1 925 275 6890",
    "sg:postcode":"94583",
    "sg:province":"CA",
    "sg:tags":[
        "smoothy",
        "juice",
        "american"
    ],
    "wof:name":"Jamba Juice",
    "wof:placetype":"venue"
},
  "geometry": {"coordinates":[-121.96872999999999,37.77847],"type":"Point"}
}