{
  "type": "Feature",
  "properties": {
    "addr:full":"8 W Court St Woodland CA 95695",
    "addr:housenumber":"8",
    "addr:postcode":"95695",
    "addr:street":"W Court St",
    "iso:country":"US",
    "sg:address":"8 W Court St",
    "sg:city":"Woodland",
    "sg:classifiers":[
        {
            "category":"Personal",
            "subcategory":"Beauty Salon",
            "type":"Services"
        }
    ],
    "sg:phone":"+1 530 662 0283",
    "sg:postcode":"95695",
    "sg:province":"CA",
    "wof:name":"Beauty Concepts",
    "wof:placetype":"venue"
},
  "geometry": {"coordinates":[-121.784328,38.678862],"type":"Point"}
}