{
  "type": "Feature",
  "properties": {
    "iso:country":"US",
    "sg:address":"2201 N Bellflower Blvd",
    "sg:city":"Long Beach",
    "sg:classifiers":[
        {
            "category":"Fast Food",
            "type":"Food & Drink"
        }
    ],
    "sg:phone":"+1 562 597 2822",
    "sg:postcode":"90815",
    "sg:province":"CA",
    "sg:tags":[
        "burger"
    ],
    "sg:website":"www.wendys.com",
    "wof:name":"Wendy's",
    "wof:placetype":"venue"
},
  "geometry": {"coordinates":[-118.125999,33.796299],"type":"Point"}
}