{
  "type": "Feature",
  "properties": {
    "iso:country":"US",
    "sg:address":"3512 W 79th Street",
    "sg:city":"Inglewood",
    "sg:classifiers":[
        {
            "category":"Retail",
            "subcategory":"Auto Repair",
            "type":"Services"
        }
    ],
    "sg:phone":"+1 323 759 1100",
    "sg:postcode":"90305",
    "sg:province":"CA",
    "wof:name":"Philthy Ragz",
    "wof:placetype":"venue"
},
  "geometry": {"coordinates":[-118.333666,33.967139],"type":"Point"}
}