{
  "type": "Feature",
  "properties": {
    "iso:country":"US",
    "sg:address":"3710 State St",
    "sg:city":"Santa Barbara",
    "sg:classifiers":[
        {
            "category":"Manufacturing",
            "subcategory":"Printing",
            "type":"Manufacturing & Wholesale Goods"
        }
    ],
    "sg:phone":"+1 805 563 3121",
    "sg:postcode":"93105",
    "sg:province":"CA",
    "sg:tags":[
        "cards",
        "greeting"
    ],
    "sg:website":"www.4yoursoul.com",
    "wof:name":"4YOURSOUL.COM",
    "wof:placetype":"venue"
},
  "geometry": {"coordinates":[-119.743405,34.440499],"type":"Point"}
}