{
  "type": "Feature",
  "properties": {
    "addr:full":"1605 Villa Ave Santa Barbara CA 93101",
    "addr:housenumber":"1605",
    "addr:postcode":"93101",
    "addr:street":"Villa Ave",
    "iso:country":"US",
    "sg:address":"1605 Villa Ave",
    "sg:city":"Santa Barbara",
    "sg:classifiers":[
        {
            "category":"Professional",
            "subcategory":"Art Services",
            "type":"Services"
        }
    ],
    "sg:phone":"+1 805 966 7559",
    "sg:postcode":"93101",
    "sg:province":"CA",
    "sg:tags":[
        "commercial",
        "design"
    ],
    "wof:name":"Moonlight Graphics",
    "wof:placetype":"venue"
},
  "geometry": {"coordinates":[-119.720406,34.418966],"type":"Point"}
}