{
  "type": "Feature",
  "properties": {
    "iso:country":"US",
    "sg:address":"3619 W Ave J",
    "sg:city":"Lancaster",
    "sg:classifiers":[
        {
            "category":"Manufacturing",
            "subcategory":"Retail Goods",
            "type":"Manufacturing & Wholesale Goods"
        }
    ],
    "sg:phone":"+1 661 723 7850",
    "sg:postcode":"93536",
    "sg:province":"CA",
    "sg:tags":[
        "product",
        "mfg"
    ],
    "wof:name":"Tiger Mfg",
    "wof:placetype":"venue"
},
  "geometry": {"coordinates":[-118.193676,34.689388],"type":"Point"}
}