{
  "type": "Feature",
  "properties": {
    "iso:country":"US",
    "sg:address":"20733 Londelius St",
    "sg:city":"Canoga Park",
    "sg:classifiers":[
        {
            "category":"Health Services",
            "subcategory":"Nursing And Care Facility",
            "type":"Services"
        }
    ],
    "sg:phone":"+1 818 717 0897",
    "sg:postcode":"91306",
    "sg:province":"CA",
    "sg:tags":[
        "home",
        "convalescent"
    ],
    "wof:name":"Homecare Manner Inc",
    "wof:placetype":"venue"
},
  "geometry": {"coordinates":[-118.586991,34.229193],"type":"Point"}
}