{
  "type": "Feature",
  "properties": {
    "addr:full":"2517 Daisy Ln Fallbrook CA 92028",
    "addr:housenumber":"2517",
    "addr:postcode":"92028",
    "addr:street":"Daisy Ln",
    "iso:country":"US",
    "sg:address":"2517 Daisy Ln",
    "sg:city":"Fallbrook",
    "sg:classifiers":[
        {
            "category":"Building & Trades",
            "subcategory":"Electrical",
            "type":"Services"
        }
    ],
    "sg:phone":"+1 760 731 9888",
    "sg:postcode":"92028",
    "sg:province":"CA",
    "sg:tags":[
        "electrical",
        "contractor"
    ],
    "wof:name":"Al Hodges Costruction",
    "wof:placetype":"venue"
},
  "geometry": {"coordinates":[-117.164596,33.345477],"type":"Point"}
}