{
  "type": "Feature",
  "properties": {
    "iso:country":"US",
    "sg:address":"444 Irving Dr",
    "sg:city":"Burbank",
    "sg:classifiers":[
        {
            "category":"Recreation",
            "type":"Entertainment"
        }
    ],
    "sg:phone":"+1 818 842 2881",
    "sg:postcode":"91504",
    "sg:province":"CA",
    "sg:tags":[
        "club",
        "a",
        "membership"
    ],
    "wof:name":"Burbank Squash Club",
    "wof:placetype":"venue"
},
  "geometry": {"coordinates":[-118.327705,34.199223],"type":"Point"}
}