{
  "type": "Feature",
  "properties": {
    "iso:country":"US",
    "sg:address":"17911 Sky Park Cir",
    "sg:city":"Irvine",
    "sg:classifiers":[
        {
            "category":"Professional",
            "type":"Services"
        }
    ],
    "sg:phone":"+1 949 225 6294",
    "sg:postcode":"92614",
    "sg:province":"CA",
    "wof:name":"Pennies 2 Dollars",
    "wof:placetype":"venue"
},
  "geometry": {"coordinates":[-117.86018,33.69118],"type":"Point"}
}