{
  "type": "Feature",
  "properties": {
    "addr:full":"2340 W Sepulveda Blvd Ste C Torrance CA 90501",
    "addr:housenumber":"2340",
    "addr:postcode":"90501",
    "addr:street":"W Sepulveda Blvd Ste C",
    "iso:country":"US",
    "sg:address":"2340 W Sepulveda Blvd Ste C",
    "sg:city":"Torrance",
    "sg:classifiers":[
        {
            "category":"Personal",
            "subcategory":"Hair Removal",
            "type":"Services"
        }
    ],
    "sg:phone":"+1 310 612 7402",
    "sg:postcode":"90501",
    "sg:province":"CA",
    "sg:website":"thebeautyden.com",
    "wof:name":"The Beauty Den",
    "wof:placetype":"venue"
},
  "geometry": {"coordinates":[-118.30292799999999,33.814894],"type":"Point"}
}