{
  "type": "Feature",
  "properties": {
    "addr:full":"509 el Mar Ct Suisun City CA 94585",
    "addr:housenumber":"509",
    "addr:postcode":"94585",
    "addr:street":"El Mar Ct",
    "iso:country":"US",
    "sg:address":"509 el Mar Ct",
    "sg:city":"Suisun City",
    "sg:classifiers":[
        {
            "category":"Wholesale",
            "subcategory":"Chemicals & Plastics",
            "type":"Manufacturing & Wholesale Goods"
        }
    ],
    "sg:phone":"+1 707 425 2417",
    "sg:postcode":"94585",
    "sg:province":"CA",
    "sg:tags":[
        "cleaning",
        "compound"
    ],
    "wof:name":"Terra Science",
    "wof:placetype":"venue"
},
  "geometry": {"coordinates":[-121.984544,38.246216],"type":"Point"}
}