{
  "type": "Feature",
  "properties": {
    "addr:full":"1410 2nd St Eureka CA 95501",
    "addr:housenumber":"1410",
    "addr:postcode":"95501",
    "addr:street":"2Nd St",
    "iso:country":"US",
    "sg:address":"1410 2nd St",
    "sg:city":"Eureka",
    "sg:classifiers":[
        {
            "category":"Manufacturing",
            "subcategory":"Lumber",
            "type":"Manufacturing & Wholesale Goods"
        }
    ],
    "sg:phone":"+1 707 445 4130",
    "sg:postcode":"95501",
    "sg:province":"CA",
    "sg:tags":[
        "logging"
    ],
    "wof:name":"Stover Logging Inc",
    "wof:placetype":"venue"
},
  "geometry": {"coordinates":[-124.156291,40.806257],"type":"Point"}
}