{
  "type": "Feature",
  "properties": {
    "iso:country":"US",
    "sg:address":"19850 Vanowen St",
    "sg:city":"Winnetka",
    "sg:classifiers":[
        {
            "category":"Professional",
            "subcategory":"Business Services",
            "type":"Services"
        }
    ],
    "sg:phone":"+1 818 884 8684",
    "sg:postcode":"91306",
    "sg:province":"CA",
    "sg:tags":[
        "delivery",
        "courier"
    ],
    "wof:name":"Totito Express",
    "wof:placetype":"venue"
},
  "geometry": {"coordinates":[-118.566002,34.193901],"type":"Point"}
}