{
  "type": "Feature",
  "properties": {
    "iso:country":"US",
    "sg:address":"6573 Shattuck Ave",
    "sg:city":"Oakland",
    "sg:classifiers":[
        {
            "category":"Building & Trades",
            "subcategory":"Construction",
            "type":"Services"
        }
    ],
    "sg:phone":"+1 510 420 8111",
    "sg:postcode":"94609",
    "sg:province":"CA",
    "sg:tags":[
        "contractor"
    ],
    "sg:website":"www.altmann-associates.com",
    "wof:name":"Altmann & Associates",
    "wof:placetype":"venue"
},
  "geometry": {"coordinates":[-122.26628100000001,37.85143],"type":"Point"}
}