{
  "type": "Feature",
  "properties": {
    "addr:full":"2445 5th Avenue San Diego CA 92101",
    "addr:housenumber":"2445",
    "addr:postcode":"92101",
    "addr:street":"5Th Avenue",
    "iso:country":"US",
    "sg:address":"2445 5th Avenue",
    "sg:city":"San Diego",
    "sg:classifiers":[
        {
            "category":"Professional",
            "subcategory":"Accounting & Tax Preparation",
            "type":"Services"
        }
    ],
    "sg:phone":"+1 619 233 1040",
    "sg:postcode":"92101",
    "sg:province":"CA",
    "sg:tags":[
        "accountant"
    ],
    "wof:name":"Digenan James D",
    "wof:placetype":"venue"
},
  "geometry": {"coordinates":[-117.160248,32.730796],"type":"Point"}
}