{
  "type": "Feature",
  "properties": {
    "addr:full":"18111 Saticoy St Reseda CA 91335",
    "addr:housenumber":"18111",
    "addr:postcode":"91335",
    "addr:street":"Saticoy St",
    "iso:country":"US",
    "sg:address":"18111 Saticoy St",
    "sg:city":"Reseda",
    "sg:classifiers":[
        {
            "category":"Restaurant",
            "type":"Food & Drink"
        }
    ],
    "sg:phone":"+1 818 776 9944",
    "sg:postcode":"91335",
    "sg:province":"CA",
    "wof:name":"Saramduel Choeun",
    "wof:placetype":"venue"
},
  "geometry": {"coordinates":[-118.527968,34.208468],"type":"Point"}
}