{
  "type": "Feature",
  "properties": {
    "iso:country":"US",
    "sg:address":"1480 Poplar St",
    "sg:city":"Oakdale",
    "sg:classifiers":[
        {
            "category":"Social Services",
            "subcategory":"Child Care",
            "type":"Services"
        }
    ],
    "sg:phone":"+1 209 847 4050",
    "sg:postcode":"95361",
    "sg:province":"CA",
    "wof:name":"Learning Tree Childrens Ctr",
    "wof:placetype":"venue"
},
  "geometry": {"coordinates":[-120.862731,37.76557],"type":"Point"}
}