{
  "type": "Feature",
  "properties": {
    "addr:full":"33091 Fairview St Lake Elsinore CA 92530",
    "addr:housenumber":"33091",
    "addr:postcode":"92530",
    "addr:street":"Fairview St",
    "iso:country":"US",
    "sg:address":"33091 Fairview St",
    "sg:city":"Lake Elsinore",
    "sg:classifiers":[
        {
            "category":"Manufacturing",
            "subcategory":"Retail Goods",
            "type":"Manufacturing & Wholesale Goods"
        }
    ],
    "sg:phone":"+1 951 678 1358",
    "sg:postcode":"92530",
    "sg:province":"CA",
    "sg:tags":[
        "distribution"
    ],
    "wof:name":"World Market Distribution",
    "wof:placetype":"venue"
},
  "geometry": {"coordinates":[-117.382715,33.660953],"type":"Point"}
}