{
  "type": "Feature",
  "properties": {
    "addr:full":"13350 W Park Ave Boulder Creek CA 95006",
    "addr:housenumber":"13350",
    "addr:postcode":"95006",
    "addr:street":"W Park Ave",
    "iso:country":"US",
    "sg:address":"13350 W Park Ave",
    "sg:city":"Boulder Creek",
    "sg:classifiers":[
        {
            "category":"Building & Trades",
            "subcategory":"Pest Control",
            "type":"Services"
        }
    ],
    "sg:phone":"+1 831 338 4800",
    "sg:postcode":"95006",
    "sg:province":"CA",
    "sg:website":"www.calamexterminator.com",
    "wof:name":"California American Extrmntg",
    "wof:placetype":"venue"
},
  "geometry": {"coordinates":[-122.12497399999999,37.127102],"type":"Point"}
}