{
  "type": "Feature",
  "properties": {
    "addr:full":"524 Houston St West Sacramento CA 95691",
    "addr:housenumber":"524",
    "addr:postcode":"95691",
    "addr:street":"Houston St",
    "iso:country":"US",
    "sg:address":"524 Houston St",
    "sg:city":"West Sacramento",
    "sg:classifiers":[
        {
            "category":"Real Estate",
            "subcategory":"Real Estate Agent",
            "type":"Services"
        }
    ],
    "sg:phone":"+1 916 372 4040",
    "sg:postcode":"95691",
    "sg:province":"CA",
    "wof:name":"Hefner Associates Realtors",
    "wof:placetype":"venue"
},
  "geometry": {"coordinates":[-121.55116200000001,38.580316],"type":"Point"}
}