{
  "type": "Feature",
  "properties": {
    "iso:country":"US",
    "sg:address":"305 Canyon Terrace Ln",
    "sg:city":"Folsom",
    "sg:classifiers":[
        {
            "category":"Professional",
            "subcategory":"Advertising",
            "type":"Services"
        }
    ],
    "sg:phone":"+1 877 692 1443",
    "sg:postcode":"95630",
    "sg:province":"CA",
    "sg:tags":[
        "marketing"
    ],
    "wof:name":"MJM Premier",
    "wof:placetype":"venue"
},
  "geometry": {"coordinates":[-121.19011,38.698071],"type":"Point"}
}