{
  "type": "Feature",
  "properties": {
    "iso:country":"US",
    "sg:address":"3755 Donald Ave",
    "sg:city":"Riverside",
    "sg:classifiers":[
        {
            "category":"Professional",
            "subcategory":"Accounting & Tax Preparation",
            "type":"Services"
        }
    ],
    "sg:phone":"+1 951 687 2292",
    "sg:postcode":"92503",
    "sg:province":"CA",
    "sg:tags":[
        "return",
        "filing"
    ],
    "wof:name":"Brown Guadalupe Tax Prepare",
    "wof:placetype":"venue"
},
  "geometry": {"coordinates":[-117.439999,33.922231],"type":"Point"}
}