{
  "type": "Feature",
  "properties": {
    "iso:country":"US",
    "sg:address":"6868 Santa Teresa Blvd",
    "sg:city":"San Jose",
    "sg:classifiers":[
        {
            "category":"Real Estate",
            "subcategory":"Architect",
            "type":"Services"
        }
    ],
    "sg:phone":"+1 408 779 5402",
    "sg:postcode":"95119",
    "sg:province":"CA",
    "wof:name":"Stotler Design Group",
    "wof:placetype":"venue"
},
  "geometry": {"coordinates":[-121.78703899999999,37.233059],"type":"Point"}
}