{
  "type": "Feature",
  "properties": {
    "iso:country":"US",
    "sg:address":"23419 Crestline Rd",
    "sg:city":"Crestline",
    "sg:classifiers":[
        {
            "category":"Building & Trades",
            "subcategory":"Construction",
            "type":"Services"
        }
    ],
    "sg:phone":"+1 909 338 7742",
    "sg:postcode":"92407",
    "sg:province":"CA",
    "sg:tags":[
        "contractor"
    ],
    "wof:name":"Kris Crudup Construction",
    "wof:placetype":"venue"
},
  "geometry": {"coordinates":[-117.29167700000001,34.237716],"type":"Point"}
}