{
  "type": "Feature",
  "properties": {
    "addr:full":"1046 N Hudson Ave Los Angeles CA 90038",
    "addr:housenumber":"1046",
    "addr:postcode":"90038",
    "addr:street":"N Hudson Ave",
    "iso:country":"US",
    "sg:address":"1046 N Hudson Ave",
    "sg:city":"Los Angeles",
    "sg:classifiers":[
        {
            "category":"Real Estate",
            "subcategory":"Architect",
            "type":"Services"
        }
    ],
    "sg:phone":"+1 323 467 6755",
    "sg:postcode":"90038",
    "sg:province":"CA",
    "sg:tags":[
        "estimate",
        "construction"
    ],
    "wof:name":"G R Universal Construction",
    "wof:placetype":"venue"
},
  "geometry": {"coordinates":[-118.332005,34.089879],"type":"Point"}
}