{
  "type": "Feature",
  "properties": {
    "addr:full":"8219 Avalon Blvd Los Angeles CA 90003",
    "addr:housenumber":"8219",
    "addr:postcode":"90003",
    "addr:street":"Avalon Blvd",
    "iso:country":"US",
    "sg:address":"8219 Avalon Blvd",
    "sg:city":"Los Angeles",
    "sg:classifiers":[
        {
            "category":"Utilities",
            "subcategory":"Mobile Phone",
            "type":"Services"
        }
    ],
    "sg:phone":"+1 323 753 2559",
    "sg:postcode":"90003",
    "sg:province":"CA",
    "sg:tags":[
        "communication",
        "radiotelephone"
    ],
    "wof:name":"Pager Express",
    "wof:placetype":"venue"
},
  "geometry": {"coordinates":[-118.26520499999999,33.963926],"type":"Point"}
}