{
  "type": "Feature",
  "properties": {
    "iso:country":"US",
    "sg:address":"425 W Los Feliz Rd",
    "sg:city":"Glendale",
    "sg:classifiers":[
        {
            "category":"Banks & Credit Unions",
            "subcategory":"Investment Brokerage",
            "type":"Services"
        }
    ],
    "sg:phone":"+1 818 545 8300",
    "sg:postcode":"91204",
    "sg:province":"CA",
    "sg:tags":[
        "trade",
        "barter",
        "exchange"
    ],
    "wof:name":"Consolidate International Ent",
    "wof:placetype":"venue"
},
  "geometry": {"coordinates":[-118.260077,34.128041],"type":"Point"}
}