{
  "type": "Feature",
  "properties": {
    "iso:country":"US",
    "sg:address":"1544 W Branch St",
    "sg:city":"Arroyo Grande",
    "sg:classifiers":[
        {
            "category":"Building & Trades",
            "subcategory":"Construction",
            "type":"Services"
        }
    ],
    "sg:phone":"+1 805 489 7378",
    "sg:postcode":"93420",
    "sg:province":"CA",
    "sg:tags":[
        "home",
        "builder"
    ],
    "wof:name":"Homes Advantage",
    "wof:placetype":"venue"
},
  "geometry": {"coordinates":[-120.602902,35.129352],"type":"Point"}
}