{
  "type": "Feature",
  "properties": {
    "iso:country":"US",
    "sg:address":"1811 S del Mar Ave",
    "sg:city":"San Gabriel",
    "sg:classifiers":[
        {
            "category":"Wholesale",
            "subcategory":"Electrical",
            "type":"Manufacturing & Wholesale Goods"
        }
    ],
    "sg:phone":"+1 626 288 2730",
    "sg:postcode":"91776",
    "sg:province":"CA",
    "sg:tags":[
        "electric",
        "motor"
    ],
    "wof:name":"JVL Motor Corp",
    "wof:placetype":"venue"
},
  "geometry": {"coordinates":[-118.09962299999999,34.075469],"type":"Point"}
}