{
  "type": "Feature",
  "properties": {
    "addr:full":"141 E Harvard Blvd Santa Paula CA 93060",
    "addr:housenumber":"141",
    "addr:postcode":"93060",
    "addr:street":"E Harvard Blvd",
    "iso:country":"US",
    "sg:address":"141 E Harvard Blvd",
    "sg:city":"Santa Paula",
    "sg:classifiers":[
        {
            "category":"Wholesale",
            "subcategory":"Machinery & Supplies",
            "type":"Manufacturing & Wholesale Goods"
        }
    ],
    "sg:phone":"+1 805 525 3990",
    "sg:postcode":"93060",
    "sg:province":"CA",
    "sg:tags":[
        "gage"
    ],
    "wof:name":"Michl Gauge Sales & Svc",
    "wof:placetype":"venue"
},
  "geometry": {"coordinates":[-119.070854,34.346616],"type":"Point"}
}