{
  "type": "Feature",
  "properties": {
    "iso:country":"US",
    "sg:address":"4150 Patricks Point Dr",
    "sg:city":"Trinidad",
    "sg:classifiers":[
        {
            "category":"Organizations",
            "subcategory":"Professional Association",
            "type":"Services"
        }
    ],
    "sg:phone":"+1 707 677 1945",
    "sg:postcode":"95570",
    "sg:province":"CA",
    "wof:name":"North Coast Redwood",
    "wof:placetype":"venue"
},
  "geometry": {"coordinates":[-124.152943,41.13357],"type":"Point"}
}