{
  "type": "Feature",
  "properties": {
    "iso:country":"US",
    "sg:address":"5989 Lake Crest Way",
    "sg:city":"Sacramento",
    "sg:classifiers":[
        {
            "category":"Building & Trades",
            "subcategory":"Construction",
            "type":"Services"
        }
    ],
    "sg:phone":"+1 916 427 3470",
    "sg:postcode":"95822",
    "sg:province":"CA",
    "sg:tags":[
        "dry wall",
        "contractor"
    ],
    "wof:name":"State Of The Art Drywall",
    "wof:placetype":"venue"
},
  "geometry": {"coordinates":[-121.51643,38.517572],"type":"Point"}
}