{
  "type": "Feature",
  "properties": {
    "addr:full":"6081 Center Dr Los Angeles CA 90045",
    "addr:housenumber":"6081",
    "addr:postcode":"90045",
    "addr:street":"Center Dr",
    "iso:country":"US",
    "sg:address":"6081 Center Dr",
    "sg:city":"Los Angeles",
    "sg:classifiers":[
        {
            "category":"Coffee & Tea",
            "type":"Food & Drink"
        },
        {
            "category":"Shopping",
            "subcategory":"Books",
            "type":"Retail Goods"
        }
    ],
    "sg:phone":"+1 310 215 3720",
    "sg:postcode":"90045",
    "sg:province":"CA",
    "sg:tags":[
        "mags",
        "video",
        "books",
        "music"
    ],
    "sg:website":"www.borders.com",
    "wof:name":"Borders",
    "wof:placetype":"venue"
},
  "geometry": {"coordinates":[-118.39299800000001,33.978199],"type":"Point"}
}