{
  "type": "Feature",
  "properties": {
    "addr:full":"1200 Main St Montara CA 94037",
    "addr:housenumber":"1200",
    "addr:postcode":"94037",
    "addr:street":"Main St",
    "iso:country":"US",
    "sg:address":"1200 Main St",
    "sg:city":"Montara",
    "sg:classifiers":[
        {
            "category":"Science Facility",
            "type":"Public Place"
        }
    ],
    "sg:phone":"+1 650 563 9943",
    "sg:postcode":"94037",
    "sg:province":"CA",
    "sg:tags":[
        "development",
        "laboratories-research"
    ],
    "wof:name":"Kramer Botanical",
    "wof:placetype":"venue"
},
  "geometry": {"coordinates":[-122.513519,37.544498],"type":"Point"}
}