{
  "type": "Feature",
  "properties": {
    "addr:full":"6200 Center St Clayton CA 94517",
    "addr:housenumber":"6200",
    "addr:postcode":"94517",
    "addr:street":"Center St",
    "iso:country":"US",
    "sg:address":"6200 Center St",
    "sg:city":"Clayton",
    "sg:classifiers":[
        {
            "category":"Professional",
            "subcategory":"Business Services",
            "type":"Services"
        }
    ],
    "sg:phone":"+1 925 672 0800",
    "sg:postcode":"94517",
    "sg:province":"CA",
    "sg:tags":[
        "drafting"
    ],
    "wof:name":"Hvac Cad Svc",
    "wof:placetype":"venue"
},
  "geometry": {"coordinates":[-121.93284800000001,37.940532],"type":"Point"}
}