{
  "type": "Feature",
  "properties": {
    "addr:full":"714 P St Sacramento CA 95814",
    "addr:housenumber":"714",
    "addr:postcode":"95814",
    "addr:street":"P St",
    "iso:country":"US",
    "sg:address":"714 P St",
    "sg:city":"Sacramento",
    "sg:classifiers":[
        {
            "category":"Professional",
            "subcategory":"Business Services",
            "type":"Services"
        }
    ],
    "sg:phone":"+1 916 650 6416",
    "sg:postcode":"95814",
    "sg:province":"CA",
    "sg:tags":[
        "medical",
        "administration"
    ],
    "sg:website":"http://www.calsurv.org",
    "wof:name":"California Department Of Health Care Services",
    "wof:placetype":"venue"
},
  "geometry": {"coordinates":[-121.50016100000001,38.574699],"type":"Point"}
}