{
  "type": "Feature",
  "properties": {
    "addr:full":"3201 Scott Blvd Santa Clara CA 95050",
    "addr:housenumber":"3201",
    "addr:postcode":"95050",
    "addr:street":"Scott Blvd",
    "iso:country":"US",
    "sg:address":"3201 Scott Blvd",
    "sg:city":"Santa Clara",
    "sg:classifiers":[
        {
            "category":"Professional",
            "subcategory":"Engineering",
            "type":"Services"
        },
        {
            "category":"Wholesale",
            "subcategory":"Electrical",
            "type":"Manufacturing & Wholesale Goods"
        }
    ],
    "sg:phone":"+1 408 988 7700",
    "sg:postcode":"95050",
    "sg:province":"CA",
    "sg:tags":[
        "company",
        "holding"
    ],
    "sg:website":"www.advantest-atec.com",
    "wof:name":"Advantest America Corp Del",
    "wof:placetype":"venue"
},
  "geometry": {"coordinates":[-121.96863399999999,37.379182],"type":"Point"}
}