{
  "type": "Feature",
  "properties": {
    "iso:country":"US",
    "sg:address":"1210 E North St",
    "sg:city":"Manteca",
    "sg:classifiers":[
        {
            "category":"Health Services",
            "subcategory":"Podiatrist",
            "type":"Services"
        }
    ],
    "sg:phone":"+1 209 823 9378",
    "sg:postcode":"95336",
    "sg:province":"CA",
    "wof:name":"Howard C Miller DPM",
    "wof:placetype":"venue"
},
  "geometry": {"coordinates":[-121.19639599999999,37.800981],"type":"Point"}
}