{
  "type": "Feature",
  "properties": {
    "addr:full":"10767 Woodside Ave Santee CA 92071",
    "addr:housenumber":"10767",
    "addr:postcode":"92071",
    "addr:street":"Woodside Ave",
    "iso:country":"US",
    "sg:address":"10767 Woodside Ave",
    "sg:city":"Santee",
    "sg:classifiers":[
        {
            "category":"Restaurant",
            "type":"Food & Drink"
        }
    ],
    "sg:phone":"+1 619 562 7878",
    "sg:postcode":"92071",
    "sg:province":"CA",
    "sg:tags":[
        "pizza",
        "italian"
    ],
    "sg:website":"www.realcheesepizza.com",
    "wof:name":"Filippi's Pizza Grotto",
    "wof:placetype":"venue"
},
  "geometry": {"coordinates":[-116.965039,32.839259],"type":"Point"}
}