{
  "type": "Feature",
  "properties": {
    "addr:full":"4126 D St Eureka CA 95503",
    "addr:housenumber":"4126",
    "addr:postcode":"95503",
    "addr:street":"D St",
    "iso:country":"US",
    "sg:address":"4126 D St",
    "sg:city":"Eureka",
    "sg:classifiers":[
        {
            "category":"Retail",
            "subcategory":"Auto Repair",
            "type":"Services"
        }
    ],
    "sg:phone":"+1 707 444 8160",
    "sg:postcode":"95503",
    "sg:province":"CA",
    "sg:tags":[
        "repairing",
        "automobile"
    ],
    "wof:name":"Eel Valley Motorsport",
    "wof:placetype":"venue"
},
  "geometry": {"coordinates":[-124.165918,40.767407],"type":"Point"}
}