{
  "type": "Feature",
  "properties": {
    "addr:full":"871 Willow St Redwood City CA 94063",
    "addr:housenumber":"871",
    "addr:postcode":"94063",
    "addr:street":"Willow St",
    "iso:country":"US",
    "sg:address":"871 Willow St",
    "sg:city":"Redwood City",
    "sg:classifiers":[
        {
            "category":"Freight",
            "type":"Transportation"
        }
    ],
    "sg:phone":"+1 650 368 3484",
    "sg:postcode":"94063",
    "sg:province":"CA",
    "sg:tags":[
        "facility"
    ],
    "wof:name":"Storage U S A",
    "wof:placetype":"venue"
},
  "geometry": {"coordinates":[-122.21413200000001,37.484148],"type":"Point"}
}