{
  "type": "Feature",
  "properties": {
    "addr:full":"1189 Rose Ave Mountain View CA 94040",
    "addr:housenumber":"1189",
    "addr:postcode":"94040",
    "addr:street":"Rose Ave",
    "iso:country":"US",
    "sg:address":"1189 Rose Ave",
    "sg:city":"Mountain View",
    "sg:classifiers":[
        {
            "category":"Building & Trades",
            "subcategory":"Construction",
            "type":"Services"
        }
    ],
    "sg:phone":"+1 650 964 1530",
    "sg:postcode":"94040",
    "sg:province":"CA",
    "sg:tags":[
        "coping",
        "plastering",
        "tiling",
        "pool",
        "swimming"
    ],
    "wof:name":"R S Pool Svc",
    "wof:placetype":"venue"
},
  "geometry": {"coordinates":[-122.08703,37.371289],"type":"Point"}
}