{
  "type": "Feature",
  "properties": {
    "iso:country":"US",
    "sg:address":"1693 Arbor Rd",
    "sg:city":"Paso Robles",
    "sg:classifiers":[
        {
            "category":"Farming",
            "subcategory":"Vineyard",
            "type":"Manufacturing & Wholesale Goods"
        }
    ],
    "sg:phone":"+1 805 239 1765",
    "sg:postcode":"93446",
    "sg:province":"CA",
    "sg:tags":[
        "grape"
    ],
    "wof:name":"Valhalla Vineyards",
    "wof:placetype":"venue"
},
  "geometry": {"coordinates":[-120.71284,35.590202],"type":"Point"}
}