{
  "type": "Feature",
  "properties": {
    "addr:full":"615 Irwin St San Rafael CA 94901",
    "addr:housenumber":"615",
    "addr:postcode":"94901",
    "addr:street":"Irwin St",
    "iso:country":"US",
    "sg:address":"615 Irwin St",
    "sg:city":"San Rafael",
    "sg:classifiers":[
        {
            "category":"Home & Garden",
            "subcategory":"Furniture",
            "type":"Retail Goods"
        }
    ],
    "sg:phone":"+1 650 344 0617",
    "sg:postcode":"94901",
    "sg:province":"CA",
    "sg:tags":[
        "equipment",
        "kitchen",
        "cabinet"
    ],
    "sg:website":"www.kitchenworks.com",
    "wof:name":"Home Works The Home Improvemnt",
    "wof:placetype":"venue"
},
  "geometry": {"coordinates":[-122.521961,37.96636],"type":"Point"}
}