{
  "type": "Feature",
  "properties": {
    "addr:full":"13380 Quapaw Rd Apple Valley CA 92308",
    "addr:housenumber":"13380",
    "addr:postcode":"92308",
    "addr:street":"Quapaw Rd",
    "iso:country":"US",
    "sg:address":"13380 Quapaw Rd",
    "sg:city":"Apple Valley",
    "sg:classifiers":[
        {
            "category":"Building & Trades",
            "subcategory":"Landscaping Services",
            "type":"Services"
        }
    ],
    "sg:phone":"+1 760 240 4742",
    "sg:postcode":"92308",
    "sg:province":"CA",
    "sg:tags":[
        "landscape"
    ],
    "wof:name":"Martinez Landscaping",
    "wof:placetype":"venue"
},
  "geometry": {"coordinates":[-117.217539,34.497095],"type":"Point"}
}