{
  "type": "Feature",
  "properties": {
    "iso:country":"US",
    "sg:address":"12310 Ave 368",
    "sg:city":"Visalia",
    "sg:classifiers":[
        {
            "category":"Professional",
            "type":"Services"
        }
    ],
    "sg:phone":"+1 559 627 4916",
    "sg:postcode":"93291",
    "sg:province":"CA",
    "sg:tags":[
        "establishment"
    ],
    "wof:name":"FMC Corp",
    "wof:placetype":"venue"
},
  "geometry": {"coordinates":[-119.29631999999999,36.457811],"type":"Point"}
}