{
  "type": "Feature",
  "properties": {
    "iso:country":"US",
    "sg:address":"2389 N Main St",
    "sg:city":"Walnut Creek",
    "sg:classifiers":[
        {
            "category":"Travel",
            "subcategory":"Hotels & Motels",
            "type":"Entertainment"
        }
    ],
    "sg:phone":"+1 925 935 4010",
    "sg:postcode":"94596",
    "sg:province":"CA",
    "wof:name":"Motel 6",
    "wof:placetype":"venue"
},
  "geometry": {"coordinates":[-122.065518,37.91295],"type":"Point"}
}