{
  "type": "Feature",
  "properties": {
    "iso:country":"US",
    "sg:address":"2319 Mountain View Rd",
    "sg:city":"El Monte",
    "sg:classifiers":[
        {
            "category":"Food & Beverages",
            "subcategory":"Groceries & Convenience Stores",
            "type":"Retail Goods"
        }
    ],
    "sg:phone":"+1 626 444 4394",
    "sg:postcode":"91733",
    "sg:province":"CA",
    "sg:tags":[
        "market"
    ],
    "wof:name":"Hong's Market",
    "wof:placetype":"venue"
},
  "geometry": {"coordinates":[-118.030767,34.055238],"type":"Point"}
}