{
  "type": "Feature",
  "properties": {
    "iso:country":"US",
    "sg:address":"2115 Glendale Galleria",
    "sg:city":"Glendale",
    "sg:classifiers":[
        {
            "category":"Shopping",
            "subcategory":"Jewelry",
            "type":"Retail Goods"
        }
    ],
    "sg:phone":"+1 818 637 2511",
    "sg:postcode":"91210",
    "sg:province":"CA",
    "wof:name":"Pan Dor Jeweler",
    "wof:placetype":"venue"
},
  "geometry": {"coordinates":[-118.25988,34.144895],"type":"Point"}
}