{
  "type": "Feature",
  "properties": {
    "iso:country":"US",
    "sg:address":"1736 Tehama St",
    "sg:city":"Redding",
    "sg:classifiers":[
        {
            "category":"Professional",
            "subcategory":"Lawyer & Legal Services",
            "type":"Services"
        }
    ],
    "sg:phone":"+1 530 243 8240",
    "sg:postcode":"96001",
    "sg:province":"CA",
    "sg:tags":[
        "attorney"
    ],
    "wof:name":"David L Morrow",
    "wof:placetype":"venue"
},
  "geometry": {"coordinates":[-122.395158,40.584519],"type":"Point"}
}