{
  "type": "Feature",
  "properties": {
    "iso:country":"US",
    "sg:address":"160 N Joy St",
    "sg:city":"Corona",
    "sg:classifiers":[
        {
            "category":"Building & Trades",
            "subcategory":"Construction",
            "type":"Services"
        }
    ],
    "sg:phone":"+1 951 738 9795",
    "sg:postcode":"92879",
    "sg:province":"CA",
    "sg:tags":[
        "asbestos",
        "removal",
        "contractor"
    ],
    "sg:website":"www.actee.com",
    "wof:name":"Action Environmental Entps Inc",
    "wof:placetype":"venue"
},
  "geometry": {"coordinates":[-117.560631,33.880442],"type":"Point"}
}