{
  "type": "Feature",
  "properties": {
    "iso:country":"US",
    "sg:address":"711 E Murray Ave",
    "sg:city":"Visalia",
    "sg:classifiers":[
        {
            "category":"Wholesale",
            "subcategory":"Electrical",
            "type":"Manufacturing & Wholesale Goods"
        }
    ],
    "sg:phone":"+1 559 734 9221",
    "sg:postcode":"93292",
    "sg:province":"CA",
    "sg:tags":[
        "equipment",
        "electric",
        "supply"
    ],
    "wof:name":"Consolidated Electrical Distr",
    "wof:placetype":"venue"
},
  "geometry": {"coordinates":[-119.285844,36.333734],"type":"Point"}
}