{
  "type": "Feature",
  "properties": {
    "addr:full":"4663 Riverside Dr Chino CA 91710",
    "addr:housenumber":"4663",
    "addr:postcode":"91710",
    "addr:street":"Riverside Dr",
    "iso:country":"US",
    "sg:address":"4663 Riverside Dr",
    "sg:city":"Chino",
    "sg:classifiers":[
        {
            "category":"Personal",
            "subcategory":"Beauty Salon",
            "type":"Services"
        }
    ],
    "sg:phone":"+1 909 364 9306",
    "sg:postcode":"91710",
    "sg:province":"CA",
    "sg:tags":[
        "hair",
        "stylist"
    ],
    "wof:name":"Hair Creations",
    "wof:placetype":"venue"
},
  "geometry": {"coordinates":[-117.703247,34.018978],"type":"Point"}
}