{
  "type": "Feature",
  "properties": {
    "addr:city":"San Francisco",
    "addr:full":"800 Chestnut St San Francisco, Ca 94133",
    "addr:house_number":"800",
    "addr:housenumber":"800",
    "addr:postcode":"94133",
    "addr:road":"Chestnut St",
    "addr:state":"CA",
    "addr:street":"Chestnut St",
    "iso:country":"US",
    "sg:address":"800 Chestnut St",
    "sg:city":"San Francisco",
    "sg:classifiers":[
        {
            "category":"Shopping",
            "type":"Retail Goods"
        }
    ],
    "sg:phone":"+1 415 749 4564",
    "sg:postcode":"94133",
    "sg:province":"CA",
    "sg:tags":[
        "art",
        "gallery",
        "dealer"
    ],
    "wof:airports":[
        102527513,
        102531041
    ],
    "wof:name":"Walter/ Mcbean Gallery",
    "wof:placetype":"venue"
},
  "geometry": {"coordinates":[-122.41652999999999,37.80343],"type":"Point"}
}