{
  "type": "Feature",
  "properties": {
    "addr:full":"800 Chestnut St San Francisco CA 94133",
    "addr:housenumber":"800",
    "addr:postcode":"94133",
    "addr:street":"Chestnut St",
    "iso:country":"US",
    "sg:address":"800 Chestnut St",
    "sg:city":"San Francisco",
    "sg:classifiers":[
        {
            "category":"Shopping",
            "type":"Retail Goods"
        }
    ],
    "sg:phone":"+1 415 749 4564",
    "sg:postcode":"94133",
    "sg:province":"CA",
    "sg:tags":[
        "art",
        "gallery",
        "dealer"
    ],
    "wof:name":"Walter & Mc Bean Galleries",
    "wof:placetype":"venue"
},
  "geometry": {"coordinates":[-122.41815099999999,37.803135],"type":"Point"}
}