{
  "type": "Feature",
  "properties": {
    "iso:country":"US",
    "sg:address":"285 N Hill Ave",
    "sg:city":"Pasadena",
    "sg:classifiers":[
        {
            "category":"Government",
            "subcategory":"Fire Station",
            "type":"Public Place"
        }
    ],
    "sg:phone":"+1 626 396 9010",
    "sg:postcode":"91106",
    "sg:province":"CA",
    "sg:tags":[
        "department"
    ],
    "wof:name":"Pasadena Fire Fighters 809",
    "wof:placetype":"venue"
},
  "geometry": {"coordinates":[-118.12146199999999,34.151484],"type":"Point"}
}