{
  "type": "Feature",
  "properties": {
    "addr:full":"6049 Claremont Ave Oakland CA 94618",
    "addr:housenumber":"6049",
    "addr:postcode":"94618",
    "addr:street":"Claremont Ave",
    "iso:country":"US",
    "sg:address":"6049 Claremont Ave",
    "sg:city":"Oakland",
    "sg:classifiers":[
        {
            "category":"Local Transit",
            "type":"Transportation"
        }
    ],
    "sg:phone":"+1 510 420 0233",
    "sg:postcode":"94618",
    "sg:province":"CA",
    "sg:tags":[
        "shuttle"
    ],
    "wof:name":"Eastbay Shuttle",
    "wof:placetype":"venue"
},
  "geometry": {"coordinates":[-122.253703,37.847676],"type":"Point"}
}