{
  "type": "Feature",
  "properties": {
    "addr:full":"172 W Main St Brawley CA 92227",
    "addr:housenumber":"172",
    "addr:postcode":"92227",
    "addr:street":"W Main St",
    "iso:country":"US",
    "sg:address":"172 W Main St",
    "sg:city":"Brawley",
    "sg:classifiers":[
        {
            "category":"Shopping",
            "type":"Retail Goods"
        }
    ],
    "sg:phone":"+1 760 344 6080",
    "sg:postcode":"92227",
    "sg:province":"CA",
    "sg:tags":[
        "merchandise"
    ],
    "wof:name":"Gilmore Racing Products",
    "wof:placetype":"venue"
},
  "geometry": {"coordinates":[-115.543148,32.97863],"type":"Point"}
}