{
  "type": "Feature",
  "properties": {
    "iso:country":"US",
    "sg:address":"4952 Warner Ave",
    "sg:city":"Huntington Beach",
    "sg:classifiers":[
        {
            "category":"Building & Trades",
            "subcategory":"Construction",
            "type":"Services"
        }
    ],
    "sg:phone":"+1 714 892 6516",
    "sg:postcode":"92649",
    "sg:province":"CA",
    "sg:tags":[
        "nonresidential"
    ],
    "wof:name":"Keanco Construction",
    "wof:placetype":"venue"
},
  "geometry": {"coordinates":[-118.042497,33.715185],"type":"Point"}
}