{
  "type": "Feature",
  "properties": {
    "addr:full":"3240 Lone Tree Way Antioch CA 94509",
    "addr:housenumber":"3240",
    "addr:postcode":"ca 94509",
    "addr:street":"Lone Tree Way",
    "iso:country":"US",
    "sg:address":"3240 Lone Tree Way",
    "sg:city":"Antioch",
    "sg:classifiers":[
        {
            "category":"Insurance",
            "subcategory":"Insurance Agent",
            "type":"Services"
        }
    ],
    "sg:phone":"+1 925 754 0500",
    "sg:postcode":"94509",
    "sg:province":"CA",
    "wof:name":"Farmers Insurance",
    "wof:placetype":"venue"
},
  "geometry": {"coordinates":[-121.793711,37.970523],"type":"Point"}
}