{
  "type": "Feature",
  "properties": {
    "iso:country":"US",
    "sg:address":"10400 Wilshire Blvd",
    "sg:city":"Los Angeles",
    "sg:classifiers":[
        {
            "category":"Education",
            "subcategory":"School",
            "type":"Public Place"
        }
    ],
    "sg:phone":"+1 310 481 3270",
    "sg:postcode":"90024",
    "sg:province":"CA",
    "sg:website":"www.sinaitemple.org",
    "wof:name":"Sinai Temple Preschool",
    "wof:placetype":"venue"
},
  "geometry": {"coordinates":[-118.429219,34.065739],"type":"Point"}
}