{
  "type": "Feature",
  "properties": {
    "addr:full":"4334 Atlantic Ave Long Beach CA 90807",
    "addr:housenumber":"4334",
    "addr:postcode":"90807",
    "addr:street":"Atlantic Ave",
    "iso:country":"US",
    "sg:address":"4334 Atlantic Ave",
    "sg:city":"Long Beach",
    "sg:classifiers":[
        {
            "category":"Home & Garden",
            "subcategory":"Carpets & Floor Coverings",
            "type":"Retail Goods"
        }
    ],
    "sg:phone":"+1 562 426 5548",
    "sg:postcode":"90807",
    "sg:province":"CA",
    "sg:tags":[
        "dealer",
        "rug"
    ],
    "wof:name":"Bixby Knolls Carpet",
    "wof:placetype":"venue"
},
  "geometry": {"coordinates":[-118.184923,33.834888],"type":"Point"}
}