{
  "type": "Feature",
  "properties": {
    "addr:full":"509 N Sepulveda Blvd Manhattan Beach CA 90266",
    "addr:housenumber":"509",
    "addr:postcode":"90266",
    "addr:street":"N Sepulveda Blvd",
    "iso:country":"US",
    "sg:address":"509 N Sepulveda Blvd",
    "sg:city":"Manhattan Beach",
    "sg:classifiers":[
        {
            "category":"Health Services",
            "subcategory":"Doctor",
            "type":"Services"
        }
    ],
    "sg:phone":"+1 310 543 0424",
    "sg:postcode":"90266",
    "sg:province":"CA",
    "wof:name":"Koo Martha Md",
    "wof:placetype":"venue"
},
  "geometry": {"coordinates":[-118.396221,33.882316],"type":"Point"}
}