{
  "type": "Feature",
  "properties": {
    "addr:full":"443 S Bascom Ave San Jose CA 95128",
    "addr:housenumber":"443",
    "addr:postcode":"95128",
    "addr:street":"S Bascom Ave",
    "iso:country":"US",
    "sg:address":"443 S Bascom Ave",
    "sg:city":"San Jose",
    "sg:classifiers":[
        {
            "category":"Home & Garden",
            "subcategory":"Household Appliances",
            "type":"Retail Goods"
        }
    ],
    "sg:phone":"+1 408 280 1044",
    "sg:postcode":"95128",
    "sg:province":"CA",
    "sg:tags":[
        "repair"
    ],
    "wof:name":"Bascom Appliances",
    "wof:placetype":"venue"
},
  "geometry": {"coordinates":[-121.931999,37.3209],"type":"Point"}
}