{
  "type": "Feature",
  "properties": {
    "iso:country":"US",
    "sg:address":"1011 Riley St",
    "sg:city":"Folsom",
    "sg:classifiers":[
        {
            "category":"Restaurant",
            "type":"Food & Drink"
        }
    ],
    "sg:menulink":"http://www.allmenus.com/ca/folsom/8394-red-robin/menu/",
    "sg:phone":"+1 916 983 1773",
    "sg:postcode":"95630",
    "sg:province":"CA",
    "sg:tags":[
        "american"
    ],
    "wof:name":"Red Robin",
    "wof:placetype":"venue"
},
  "geometry": {"coordinates":[-121.16924299999999,38.671069],"type":"Point"}
}