{
  "type": "Feature",
  "properties": {
    "iso:country":"US",
    "sg:address":"6045 Park Dr",
    "sg:city":"Wrightwood",
    "sg:classifiers":[
        {
            "category":"Real Estate",
            "subcategory":"Real Estate Agent",
            "type":"Services"
        }
    ],
    "sg:phone":"+1 760 249 6017",
    "sg:postcode":"92397",
    "sg:province":"CA",
    "wof:name":"Devlin Realty",
    "wof:placetype":"venue"
},
  "geometry": {"coordinates":[-117.633471,34.36038],"type":"Point"}
}