{
  "type": "Feature",
  "properties": {
    "iso:country":"US",
    "sg:address":"806 Manhattan Beach Boulevard",
    "sg:city":"Manhattan Beach",
    "sg:classifiers":[
        {
            "category":"Professional",
            "subcategory":"Art Services",
            "type":"Services"
        }
    ],
    "sg:phone":"+1 310 798 2711",
    "sg:postcode":"90266",
    "sg:province":"CA",
    "sg:tags":[
        "graphic",
        "design"
    ],
    "wof:name":"The Graphic Element",
    "wof:placetype":"venue"
},
  "geometry": {"coordinates":[-118.402984,33.887349],"type":"Point"}
}