{
  "type": "Feature",
  "properties": {
    "addr:full":"2409 Palermo Dr San Diego CA 92106",
    "addr:housenumber":"2409",
    "addr:postcode":"92106",
    "addr:street":"Palermo Dr",
    "iso:country":"US",
    "sg:address":"2409 Palermo Dr",
    "sg:city":"San Diego",
    "sg:classifiers":[
        {
            "category":"Professional",
            "subcategory":"Management & Consulting",
            "type":"Services"
        }
    ],
    "sg:phone":"+1 619 226 0351",
    "sg:postcode":"92106",
    "sg:province":"CA",
    "wof:name":"Tools For Transformation",
    "wof:placetype":"venue"
},
  "geometry": {"coordinates":[-117.226893,32.743212],"type":"Point"}
}