{
  "type": "Feature",
  "properties": {
    "iso:country":"US",
    "sg:address":"16485 Elm Haven Dr",
    "sg:city":"Hacienda Heights",
    "sg:classifiers":[
        {
            "category":"Wholesale",
            "subcategory":"Plants",
            "type":"Manufacturing & Wholesale Goods"
        }
    ],
    "sg:phone":"+1 626 336 9112",
    "sg:postcode":"91745",
    "sg:province":"CA",
    "sg:tags":[
        "supply"
    ],
    "wof:name":"Crysco Design & Gift Co",
    "wof:placetype":"venue"
},
  "geometry": {"coordinates":[-117.947462,33.993784],"type":"Point"}
}