{
  "type": "Feature",
  "properties": {
    "addr:full":"342 Carriage Dr Santa Clara CA 95050",
    "addr:housenumber":"342",
    "addr:postcode":"95050",
    "addr:street":"Carriage Dr",
    "iso:country":"US",
    "sg:address":"342 Carriage Dr",
    "sg:city":"Santa Clara",
    "sg:classifiers":[
        {
            "category":"Travel",
            "subcategory":"Travel Agent",
            "type":"Entertainment"
        }
    ],
    "sg:phone":"+1 408 247 7782",
    "sg:postcode":"95050",
    "sg:province":"CA",
    "sg:tags":[
        "tours",
        "promoter"
    ],
    "wof:name":"Toshali Tours & Cruises",
    "wof:placetype":"venue"
},
  "geometry": {"coordinates":[-121.954947,37.337469],"type":"Point"}
}