{
  "type": "Feature",
  "properties": {
    "addr:full":"226 Miller Avenue South San Francisco CA 94080",
    "addr:housenumber":"226",
    "addr:postcode":"94080",
    "addr:street":"Miller Avenue",
    "iso:country":"US",
    "sg:address":"226 Miller Avenue",
    "sg:city":"South San Francisco",
    "sg:classifiers":[
        {
            "category":"Shopping",
            "subcategory":"Discount & Variety Stores",
            "type":"Retail Goods"
        }
    ],
    "sg:phone":"+1 650 871 5707",
    "sg:postcode":"94080",
    "sg:province":"CA",
    "sg:website":"biotechequipmentsales.com/the-news",
    "wof:name":"Biotech Equipment Sales",
    "wof:placetype":"venue"
},
  "geometry": {"coordinates":[-122.409243,37.656317],"type":"Point"}
}