{
  "type": "Feature",
  "properties": {
    "addr:full":"528 N el Camino Real San Clemente CA 92672",
    "addr:housenumber":"528",
    "addr:postcode":"92672",
    "addr:street":"N El Camino Real",
    "iso:country":"US",
    "sg:address":"528 N el Camino Real",
    "sg:city":"San Clemente",
    "sg:classifiers":[
        {
            "category":"Building & Trades",
            "subcategory":"Plumbing",
            "type":"Services"
        }
    ],
    "sg:phone":"+1 949 492 1721",
    "sg:postcode":"92672",
    "sg:province":"CA",
    "sg:tags":[
        "plumbing",
        "contractor"
    ],
    "wof:name":"Greenwall Plumbing & Heat",
    "wof:placetype":"venue"
},
  "geometry": {"coordinates":[-117.616552,33.429862],"type":"Point"}
}