{
  "type": "Feature",
  "properties": {
    "iso:country":"US",
    "sg:address":"23 Colony Way",
    "sg:city":"Aliso Viejo",
    "sg:classifiers":[
        {
            "category":"Building & Trades",
            "subcategory":"Landscaping Services",
            "type":"Services"
        }
    ],
    "sg:phone":"+1 949 425 3643",
    "sg:postcode":"92656",
    "sg:province":"CA",
    "wof:name":"Damons Garden Care",
    "wof:placetype":"venue"
},
  "geometry": {"coordinates":[-117.72722,33.55191],"type":"Point"}
}