{
  "type": "Feature",
  "properties": {
    "iso:country":"US",
    "sg:address":"1680 Vine St",
    "sg:city":"Los Angeles",
    "sg:classifiers":[
        {
            "category":"Social Services",
            "type":"Services"
        }
    ],
    "sg:phone":"+1 323 468 0567",
    "sg:postcode":"90028",
    "sg:province":"CA",
    "sg:tags":[
        "organization",
        "welfare"
    ],
    "sg:website":"www.cultawarenessnetwork.org",
    "wof:name":"Cult Awareness Network",
    "wof:placetype":"venue"
},
  "geometry": {"coordinates":[-118.326597,34.100129],"type":"Point"}
}