{
  "type": "Feature",
  "properties": {
    "iso:country":"US",
    "sg:address":"391 Sutter St",
    "sg:city":"San Francisco",
    "sg:classifiers":[
        {
            "category":"Personal",
            "subcategory":"Beauty Salon",
            "type":"Services"
        }
    ],
    "sg:phone":"+1 415 982 4928",
    "sg:postcode":"94108",
    "sg:province":"CA",
    "wof:name":"Gerhard & Joseph Inc",
    "wof:placetype":"venue"
},
  "geometry": {"coordinates":[-122.40581400000001,37.789542],"type":"Point"}
}