{
  "type": "Feature",
  "properties": {
    "iso:country":"US",
    "sg:address":"112 S Cypress Ave",
    "sg:city":"Ontario",
    "sg:classifiers":[
        {
            "category":"Insurance",
            "subcategory":"Insurance Agent",
            "type":"Services"
        }
    ],
    "sg:phone":"+1 909 983 8111",
    "sg:postcode":"91762",
    "sg:province":"CA",
    "wof:name":"Quiroz Insurance Svc",
    "wof:placetype":"venue"
},
  "geometry": {"coordinates":[-117.661973,34.062487],"type":"Point"}
}