{
  "type": "Feature",
  "properties": {
    "addr:full":"8153 Gualala Ct Sacramento CA 95828",
    "addr:housenumber":"8153",
    "addr:postcode":"95828",
    "addr:street":"Gualala Ct",
    "iso:country":"US",
    "sg:address":"8153 Gualala Ct",
    "sg:city":"Sacramento",
    "sg:classifiers":[
        {
            "category":"Wholesale",
            "subcategory":"Non-durable Goods",
            "type":"Manufacturing & Wholesale Goods"
        }
    ],
    "sg:phone":"+1 916 849 1731",
    "sg:postcode":"95828",
    "sg:province":"CA",
    "wof:name":"Karosy Brand Imports",
    "wof:placetype":"venue"
},
  "geometry": {"coordinates":[-121.40431,38.457386],"type":"Point"}
}