{
  "type": "Feature",
  "properties": {
    "addr:full":"448 Balboa St San Francisco CA 94118",
    "addr:housenumber":"448",
    "addr:postcode":"94118",
    "addr:street":"Balboa St",
    "iso:country":"US",
    "sg:address":"448 Balboa St",
    "sg:city":"San Francisco",
    "sg:classifiers":[
        {
            "category":"Retail",
            "subcategory":"Repair Shop",
            "type":"Services"
        }
    ],
    "sg:phone":"+1 415 386 2178",
    "sg:postcode":"94118",
    "sg:province":"CA",
    "sg:tags":[
        "appliance"
    ],
    "wof:name":"San Yang Pai Co",
    "wof:placetype":"venue"
},
  "geometry": {"coordinates":[-122.463601,37.777333],"type":"Point"}
}