{
  "type": "Feature",
  "properties": {
    "iso:country":"US",
    "sg:address":"15819 Gramercy Pl",
    "sg:city":"Gardena",
    "sg:classifiers":[
        {
            "category":"Building & Trades",
            "subcategory":"Landscaping Services",
            "type":"Services"
        }
    ],
    "sg:phone":"+1 310 532 3929",
    "sg:postcode":"90247",
    "sg:province":"CA",
    "sg:tags":[
        "lawn",
        "maintenance",
        "grounds"
    ],
    "wof:name":"Sun Gardening Svc & Landscpg",
    "wof:placetype":"venue"
},
  "geometry": {"coordinates":[-118.313113,33.884733],"type":"Point"}
}