{
  "type": "Feature",
  "properties": {
    "iso:country":"US",
    "sg:address":"2112 W Whittier Blvd",
    "sg:city":"Montebello",
    "sg:classifiers":[
        {
            "category":"Real Estate",
            "subcategory":"Real Estate Agent",
            "type":"Services"
        }
    ],
    "sg:phone":"+1 323 721 1236",
    "sg:postcode":"90640",
    "sg:province":"CA",
    "wof:name":"Legacy Realty",
    "wof:placetype":"venue"
},
  "geometry": {"coordinates":[-118.123993,34.013388],"type":"Point"}
}