{
  "type": "Feature",
  "properties": {
    "iso:country":"US",
    "sg:address":"7311 E Avenue T",
    "sg:city":"Littlerock",
    "sg:classifiers":[
        {
            "category":"Building & Trades",
            "subcategory":"Construction",
            "type":"Services"
        },
        {
            "category":"Retail",
            "subcategory":"Storage",
            "type":"Services"
        }
    ],
    "sg:phone":"+1 661 533 2115",
    "sg:postcode":"93543",
    "sg:province":"CA",
    "sg:tags":[
        "shop",
        "rock",
        "brick-clay-common",
        "face"
    ],
    "wof:name":"Holliday Rock Company Inc.",
    "wof:placetype":"venue"
},
  "geometry": {"coordinates":[-117.99364300000001,34.542821],"type":"Point"}
}