{
  "type": "Feature",
  "properties": {
    "iso:country":"US",
    "sg:address":"737 Buena Vista Ave W",
    "sg:city":"San Francisco",
    "sg:classifiers":[
        {
            "category":"Shopping",
            "type":"Retail Goods"
        }
    ],
    "sg:phone":"+1 415 558 7179",
    "sg:postcode":"94117",
    "sg:province":"CA",
    "sg:tags":[
        "art",
        "gallery",
        "dealer"
    ],
    "wof:name":"Bomani Gallery",
    "wof:placetype":"venue"
},
  "geometry": {"coordinates":[-122.443576,37.768447],"type":"Point"}
}