{
  "type": "Feature",
  "properties": {
    "iso:country":"US",
    "sg:address":"136 Tea Ln",
    "sg:city":"Brea",
    "sg:classifiers":[
        {
            "category":"Manufacturing",
            "subcategory":"Printing",
            "type":"Manufacturing & Wholesale Goods"
        }
    ],
    "sg:phone":"+1 714 488 1930",
    "sg:postcode":"92821",
    "sg:province":"CA",
    "sg:tags":[
        "commercial"
    ],
    "wof:name":"Imagine Displays",
    "wof:placetype":"venue"
},
  "geometry": {"coordinates":[-117.901411,33.920648],"type":"Point"}
}