{
  "type": "Feature",
  "properties": {
    "iso:country":"US",
    "sg:address":"15987 Yarnell St",
    "sg:city":"Sylmar",
    "sg:classifiers":[
        {
            "category":"Personal",
            "subcategory":"Beauty Salon",
            "type":"Services"
        }
    ],
    "sg:phone":"+1 818 362 5811",
    "sg:postcode":"91342",
    "sg:province":"CA",
    "wof:name":"Barbara's Hair Co",
    "wof:placetype":"venue"
},
  "geometry": {"coordinates":[-118.479092,34.322576],"type":"Point"}
}