{
  "type": "Feature",
  "properties": {
    "addr:full":"9625 Bolsa Ave Westminster CA 92684",
    "addr:housenumber":"9625",
    "addr:postcode":"92684",
    "addr:street":"Bolsa Ave",
    "iso:country":"US",
    "sg:address":"9625 Bolsa Ave",
    "sg:city":"Westminster",
    "sg:classifiers":[
        {
            "category":"Restaurant",
            "type":"Food & Drink"
        }
    ],
    "sg:phone":"+1 714 839 9882",
    "sg:postcode":"92684",
    "sg:province":"CA",
    "sg:tags":[
        "vietnamese"
    ],
    "wof:name":"Pho Thanh",
    "wof:placetype":"venue"
},
  "geometry": {"coordinates":[-117.960999,33.745098],"type":"Point"}
}