{
  "type": "Feature",
  "properties": {
    "iso:country":"US",
    "sg:address":"10941 Firestone Blvd",
    "sg:city":"Norwalk",
    "sg:classifiers":[
        {
            "category":"Building & Trades",
            "subcategory":"Construction",
            "type":"Services"
        }
    ],
    "sg:phone":"+1 562 252 8714",
    "sg:postcode":"90650",
    "sg:province":"CA",
    "sg:tags":[
        "contractor"
    ],
    "sg:website":"bit.ly/dhnRJD",
    "wof:name":"UAC Contractors",
    "wof:placetype":"venue"
},
  "geometry": {"coordinates":[-118.101378,33.923358],"type":"Point"}
}