{
  "type": "Feature",
  "properties": {
    "addr:full":"2460 Carmichael Way Turlock CA 95382",
    "addr:housenumber":"2460",
    "addr:postcode":"95382",
    "addr:street":"Carmichael Way",
    "iso:country":"US",
    "sg:address":"2460 Carmichael Way",
    "sg:city":"Turlock",
    "sg:classifiers":[
        {
            "category":"Professional",
            "subcategory":"Business Services",
            "type":"Services"
        }
    ],
    "sg:phone":"+1 209 613 4605",
    "sg:postcode":"95382",
    "sg:province":"CA",
    "sg:tags":[
        "notary"
    ],
    "wof:name":"Notary On Wheels",
    "wof:placetype":"venue"
},
  "geometry": {"coordinates":[-120.828846,37.515031],"type":"Point"}
}