{
  "type": "Feature",
  "properties": {
    "iso:country":"US",
    "sg:address":"6291 N State St",
    "sg:city":"Ukiah",
    "sg:classifiers":[
        {
            "category":"Manufacturing",
            "subcategory":"Metals",
            "type":"Manufacturing & Wholesale Goods"
        }
    ],
    "sg:phone":"+1 707 485 0588",
    "sg:postcode":"95482",
    "sg:province":"CA",
    "sg:tags":[
        "equipment",
        "heating"
    ],
    "wof:name":"Advance Solar Hydro Wind Power",
    "wof:placetype":"venue"
},
  "geometry": {"coordinates":[-123.202282,39.23367],"type":"Point"}
}