{
  "type": "Feature",
  "properties": {
    "addr:full":"702 N San Joaquin St Stockton CA 95202",
    "addr:housenumber":"702",
    "addr:postcode":"95202",
    "addr:street":"N San Joaquin St",
    "iso:country":"US",
    "sg:address":"702 N San Joaquin St",
    "sg:city":"Stockton",
    "sg:classifiers":[
        {
            "category":"Health Services",
            "subcategory":"Nursing And Care Facility",
            "type":"Services"
        }
    ],
    "sg:phone":"+1 209 464 9212",
    "sg:postcode":"95202",
    "sg:province":"CA",
    "sg:tags":[
        "home",
        "retirement",
        "community"
    ],
    "wof:name":"Delta Plaza Senior Apartments",
    "wof:placetype":"venue"
},
  "geometry": {"coordinates":[-121.289261,37.961085],"type":"Point"}
}