{
  "type": "Feature",
  "properties": {
    "addr:full":"202 Hillcrest Ave San Bernardino CA 92408",
    "addr:housenumber":"202",
    "addr:postcode":"92408",
    "addr:street":"Hillcrest Ave",
    "iso:country":"US",
    "sg:address":"202 Hillcrest Ave",
    "sg:city":"San Bernardino",
    "sg:classifiers":[
        {
            "category":"Wholesale",
            "subcategory":"Machinery & Supplies",
            "type":"Manufacturing & Wholesale Goods"
        }
    ],
    "sg:phone":"+1 909 383 2316",
    "sg:postcode":"92408",
    "sg:province":"CA",
    "sg:tags":[
        "rubber",
        "product"
    ],
    "wof:name":"Industrial Rubber & Supply",
    "wof:placetype":"venue"
},
  "geometry": {"coordinates":[-117.28829500000001,34.082724],"type":"Point"}
}