{
  "type": "Feature",
  "properties": {
    "iso:country":"US",
    "sg:address":"7843 Sepulveda Blvd",
    "sg:city":"Van Nuys",
    "sg:classifiers":[
        {
            "category":"Restaurant",
            "type":"Food & Drink"
        }
    ],
    "sg:phone":"+1 818 989 2610",
    "sg:postcode":"91405",
    "sg:province":"CA",
    "wof:name":"Tijuana Grill",
    "wof:placetype":"venue"
},
  "geometry": {"coordinates":[-118.466278,34.212412],"type":"Point"}
}