{
  "type": "Feature",
  "properties": {
    "iso:country":"US",
    "sg:address":"4601 Wilshire Boulevard Suite 205",
    "sg:city":"Los Angeles",
    "sg:classifiers":[
        {
            "category":"Real Estate",
            "subcategory":"Real Estate Services",
            "type":"Services"
        }
    ],
    "sg:phone":"+1 323 933 5763",
    "sg:postcode":"90010",
    "sg:province":"CA",
    "sg:tags":[
        "management",
        "property"
    ],
    "wof:name":"F L M Enterprises",
    "wof:placetype":"venue"
},
  "geometry": {"coordinates":[-118.329134,34.061977],"type":"Point"}
}