{
  "type": "Feature",
  "properties": {
    "iso:country":"US",
    "sg:address":"1330 N Dutton Ave",
    "sg:city":"Santa Rosa",
    "sg:classifiers":[
        {
            "category":"Professional",
            "subcategory":"Computer Services",
            "type":"Services"
        }
    ],
    "sg:phone":"+1 707 524 6960",
    "sg:postcode":"95401",
    "sg:province":"CA",
    "sg:tags":[
        "development",
        "technology",
        "software"
    ],
    "wof:name":"Adobe Graphics",
    "wof:placetype":"venue"
},
  "geometry": {"coordinates":[-122.73288599999999,38.449133],"type":"Point"}
}