{
  "type": "Feature",
  "properties": {
    "iso:country":"US",
    "sg:address":"135 S Campus Ave",
    "sg:city":"Upland",
    "sg:classifiers":[
        {
            "category":"Personal",
            "type":"Services"
        },
        {
            "category":"Retail",
            "subcategory":"Auto Rental",
            "type":"Services"
        },
        {
            "category":"Retail",
            "subcategory":"Storage",
            "type":"Services"
        }
    ],
    "sg:phone":"+1 909 981 6903",
    "sg:postcode":"91786",
    "sg:province":"CA",
    "sg:tags":[
        "renting",
        "moving-self",
        "leasing",
        "automobile",
        "household",
        "recreational",
        "commercial",
        "truck",
        "trailer",
        "campers-storage",
        "vehicle",
        "mover",
        "self",
        "boat"
    ],
    "sg:website":"http://www.stor-king.com",
    "wof:name":"Stor-King",
    "wof:placetype":"venue"
},
  "geometry": {"coordinates":[-117.64144899999999,34.093113],"type":"Point"}
}