{
  "type": "Feature",
  "properties": {
    "iso:country":"US",
    "sg:address":"2132 Stone Valley Rd",
    "sg:city":"Alamo",
    "sg:classifiers":[
        {
            "category":"Farming",
            "subcategory":"Livestock Farm",
            "type":"Manufacturing & Wholesale Goods"
        }
    ],
    "sg:phone":"+1 707 279 4563",
    "sg:postcode":"94507",
    "sg:province":"CA",
    "sg:tags":[
        "ranch"
    ],
    "wof:name":"Cobb Valley Ranch & Developmen",
    "wof:placetype":"venue"
},
  "geometry": {"coordinates":[-122.013964,37.852434],"type":"Point"}
}