{
  "type": "Feature",
  "properties": {
    "iso:country":"US",
    "sg:address":"12267 Indian Country Dr",
    "sg:city":"Redding",
    "sg:classifiers":[
        {
            "category":"Shopping",
            "subcategory":"Gifts & Souvenirs",
            "type":"Retail Goods"
        }
    ],
    "sg:phone":"+1 530 275 3625",
    "sg:postcode":"96003",
    "sg:province":"CA",
    "sg:tags":[
        "indian"
    ],
    "wof:name":"United Native Indian Tribes",
    "wof:placetype":"venue"
},
  "geometry": {"coordinates":[-122.345054,40.646955],"type":"Point"}
}