{
  "type": "Feature",
  "properties": {
    "addr:full":"2232 Rutherford Rd Carlsbad CA 92008",
    "addr:housenumber":"2232",
    "addr:postcode":"92008",
    "addr:street":"Rutherford Rd",
    "iso:country":"US",
    "sg:address":"2232 Rutherford Rd",
    "sg:city":"Carlsbad",
    "sg:classifiers":[
        {
            "category":"Shopping",
            "subcategory":"Optician",
            "type":"Retail Goods"
        }
    ],
    "sg:phone":"+1 760 476 9410",
    "sg:postcode":"92008",
    "sg:province":"CA",
    "sg:tags":[
        "eyewear"
    ],
    "sg:website":"www.synergeyes.com",
    "wof:name":"Synergeyes Inc",
    "wof:placetype":"venue"
},
  "geometry": {"coordinates":[-117.279501,33.131822],"type":"Point"}
}