{
  "type": "Feature",
  "properties": {
    "addr:full":"16024 Broadway Ter Oakland CA 94611",
    "addr:housenumber":"16024",
    "addr:postcode":"94611",
    "addr:street":"Broadway Ter",
    "iso:country":"US",
    "sg:address":"16024 Broadway Ter",
    "sg:city":"Oakland",
    "sg:classifiers":[
        {
            "category":"Professional",
            "subcategory":"Lawyer & Legal Services",
            "type":"Services"
        }
    ],
    "sg:phone":"+1 510 594 1427",
    "sg:postcode":"94611",
    "sg:province":"CA",
    "sg:tags":[
        "attorney"
    ],
    "wof:name":"Skamser & Assoc",
    "wof:placetype":"venue"
},
  "geometry": {"coordinates":[-122.214336,37.846832],"type":"Point"}
}