{
  "type": "Feature",
  "properties": {
    "iso:country":"US",
    "sg:address":"1676 Grove Rd",
    "sg:city":"El Cajon",
    "sg:classifiers":[
        {
            "category":"Building & Trades",
            "subcategory":"Construction",
            "type":"Services"
        }
    ],
    "sg:phone":"+1 619 447 3416",
    "sg:postcode":"92020",
    "sg:province":"CA",
    "sg:tags":[
        "contractor"
    ],
    "wof:name":"Baggett Construction",
    "wof:placetype":"venue"
},
  "geometry": {"coordinates":[-116.93723300000001,32.774895],"type":"Point"}
}