{
  "type": "Feature",
  "properties": {
    "addr:full":"2155 Pfe Rd Roseville CA 95747",
    "addr:housenumber":"2155",
    "addr:postcode":"95747",
    "addr:street":"Pfe Rd",
    "iso:country":"US",
    "sg:address":"2155 Pfe Rd",
    "sg:city":"Roseville",
    "sg:classifiers":[
        {
            "category":"Manufacturing",
            "subcategory":"Tools & Machinery",
            "type":"Manufacturing & Wholesale Goods"
        }
    ],
    "sg:phone":"+1 916 782 8494",
    "sg:postcode":"95747",
    "sg:province":"CA",
    "sg:website":"www.kencoengineering.com",
    "wof:name":"Kenco Engineering Inc",
    "wof:placetype":"venue"
},
  "geometry": {"coordinates":[-121.320778,38.729166],"type":"Point"}
}