{
  "type": "Feature",
  "properties": {
    "iso:country":"US",
    "sg:address":"7325 Arleta Ct",
    "sg:city":"Sacramento",
    "sg:classifiers":[
        {
            "category":"Professional",
            "subcategory":"Advertising",
            "type":"Services"
        }
    ],
    "sg:phone":"+1 916 422 6042",
    "sg:postcode":"95823",
    "sg:province":"CA",
    "sg:tags":[
        "distribution"
    ],
    "wof:name":"BDS Distributing",
    "wof:placetype":"venue"
},
  "geometry": {"coordinates":[-121.440549,38.488819],"type":"Point"}
}