{
  "type": "Feature",
  "properties": {
    "addr:full":"7242 Valjean Ave Van Nuys CA 91406",
    "addr:housenumber":"7242",
    "addr:postcode":"91406",
    "addr:street":"Valjean Ave",
    "iso:country":"US",
    "sg:address":"7242 Valjean Ave",
    "sg:city":"Van Nuys",
    "sg:classifiers":[
        {
            "category":"Manufacturing",
            "subcategory":"Printing",
            "type":"Manufacturing & Wholesale Goods"
        }
    ],
    "sg:phone":"+1 818 782 5490",
    "sg:postcode":"91406",
    "sg:province":"CA",
    "sg:tags":[
        "printer"
    ],
    "sg:website":"www.printcnx.net",
    "wof:name":"Printing Connection",
    "wof:placetype":"venue"
},
  "geometry": {"coordinates":[-118.485803,34.202911],"type":"Point"}
}