{
  "type": "Feature",
  "properties": {
    "iso:country":"US",
    "sg:address":"12136 Santa Monica Blvd",
    "sg:city":"Los Angeles",
    "sg:classifiers":[
        {
            "category":"Food & Beverages",
            "subcategory":"Meat & Fish",
            "type":"Retail Goods"
        }
    ],
    "sg:phone":"+1 310 447 1612",
    "sg:postcode":"90025",
    "sg:province":"CA",
    "wof:name":"Star Kosher Meat Market",
    "wof:placetype":"venue"
},
  "geometry": {"coordinates":[-118.464027,34.040187],"type":"Point"}
}