{
  "type": "Feature",
  "properties": {
    "iso:country":"US",
    "sg:address":"515 9th Street",
    "sg:city":"Huntington Beach",
    "sg:classifiers":[
        {
            "category":"Building & Trades",
            "subcategory":"Construction",
            "type":"Services"
        }
    ],
    "sg:phone":"+1 714 536 8839",
    "sg:postcode":"92648",
    "sg:province":"CA",
    "sg:tags":[
        "contractor"
    ],
    "sg:website":"www.curecoinc.com",
    "wof:name":"Cureco",
    "wof:placetype":"venue"
},
  "geometry": {"coordinates":[-118.002128,33.664022],"type":"Point"}
}