{
  "type": "Feature",
  "properties": {
    "addr:full":"550 Lorabel Way Simi Valley CA 93065",
    "addr:housenumber":"550",
    "addr:postcode":"93065",
    "addr:street":"Lorabel Way",
    "iso:country":"US",
    "sg:address":"550 Lorabel Way",
    "sg:city":"Simi Valley",
    "sg:classifiers":[
        {
            "category":"Shopping",
            "subcategory":"Crafts & Fabrics",
            "type":"Retail Goods"
        }
    ],
    "sg:phone":"+1 805 577 0676",
    "sg:postcode":"93065",
    "sg:province":"CA",
    "sg:tags":[
        "sewing"
    ],
    "wof:name":"Sew Superior",
    "wof:placetype":"venue"
},
  "geometry": {"coordinates":[-118.80500499999999,34.22944],"type":"Point"}
}