{
  "type": "Feature",
  "properties": {
    "addr:full":"707 N. Coast Hwy Oceanside CA 92054",
    "addr:housenumber":"707",
    "addr:postcode":"92054",
    "addr:street":"N. Coast Hwy",
    "iso:country":"US",
    "sg:address":"707 N. Coast Hwy",
    "sg:city":"Oceanside",
    "sg:classifiers":[
        {
            "category":"Restaurant",
            "type":"Food & Drink"
        },
        {
            "category":"Food & Beverages",
            "subcategory":"Farmers Market",
            "type":"Retail Goods"
        }
    ],
    "sg:phone":"+1 760 805 4500",
    "sg:postcode":"92054",
    "sg:province":"CA",
    "sg:tags":[
        "barbeque"
    ],
    "sg:website":"www.ApeHangersGrill.com",
    "wof:name":"ApeHangers Grill",
    "wof:placetype":"venue"
},
  "geometry": {"coordinates":[-117.383201,33.200227],"type":"Point"}
}