{
  "type": "Feature",
  "properties": {
    "addr:full":"19570 San Jose Ave City Of Industry CA 91748",
    "addr:housenumber":"19570",
    "addr:postcode":"91748",
    "addr:street":"San Jose Ave",
    "iso:country":"US",
    "sg:address":"19570 San Jose Ave",
    "sg:city":"City Of Industry",
    "sg:classifiers":[
        {
            "category":"Manufacturing",
            "subcategory":"Paper Products",
            "type":"Manufacturing & Wholesale Goods"
        }
    ],
    "sg:phone":"+1 909 444 9454",
    "sg:postcode":"91748",
    "sg:province":"CA",
    "sg:tags":[
        "corrugated",
        "solid",
        "fiber",
        "box"
    ],
    "wof:name":"Hoover Containers",
    "wof:placetype":"venue"
},
  "geometry": {"coordinates":[-117.875539,33.999193],"type":"Point"}
}