{
  "type": "Feature",
  "properties": {
    "addr:full":"6800 Sierra Ct Dublin CA 94568",
    "addr:housenumber":"6800",
    "addr:postcode":"94568",
    "addr:street":"Sierra Ct",
    "iso:country":"US",
    "sg:address":"6800 Sierra Ct",
    "sg:city":"Dublin",
    "sg:classifiers":[
        {
            "category":"Wholesale",
            "subcategory":"Hardware",
            "type":"Manufacturing & Wholesale Goods"
        }
    ],
    "sg:phone":"+1 925 828 7012",
    "sg:postcode":"94568",
    "sg:province":"CA",
    "sg:tags":[
        "plumbing",
        "fixture",
        "supply"
    ],
    "wof:name":"Cal Steam-East Bay",
    "wof:placetype":"venue"
},
  "geometry": {"coordinates":[-121.915155,37.707004],"type":"Point"}
}