{
  "type": "Feature",
  "properties": {
    "iso:country":"US",
    "sg:address":"2368 Concord Blvd",
    "sg:city":"Concord",
    "sg:classifiers":[
        {
            "category":"Shopping",
            "type":"Retail Goods"
        }
    ],
    "sg:phone":"+1 925 685 0134",
    "sg:postcode":"94519",
    "sg:province":"CA",
    "sg:tags":[
        "merchandise"
    ],
    "wof:name":"Ead Surachai Fine Art",
    "wof:placetype":"venue"
},
  "geometry": {"coordinates":[-122.030575,37.976835],"type":"Point"}
}