{
  "type": "Feature",
  "properties": {
    "addr:full":"4921 Newport Ave San Diego CA 92107",
    "addr:housenumber":"4921",
    "addr:postcode":"92107",
    "addr:street":"Newport Ave",
    "iso:country":"US",
    "sg:address":"4921 Newport Ave",
    "sg:city":"San Diego",
    "sg:classifiers":[
        {
            "category":"Shopping",
            "subcategory":"Catalog Store",
            "type":"Retail Goods"
        }
    ],
    "sg:phone":"+1 619 223 5048",
    "sg:postcode":"92107",
    "sg:province":"CA",
    "sg:tags":[
        "house",
        "mail"
    ],
    "wof:name":"Theadams Attic",
    "wof:placetype":"venue"
},
  "geometry": {"coordinates":[-117.250755,32.746576],"type":"Point"}
}