{
  "type": "Feature",
  "properties": {
    "iso:country":"US",
    "sg:address":"1435 N Willow Ave",
    "sg:city":"Rialto",
    "sg:classifiers":[
        {
            "category":"Organizations",
            "subcategory":"Religious Organization",
            "type":"Services"
        }
    ],
    "sg:phone":"+1 909 874 2034",
    "sg:postcode":"92376",
    "sg:province":"CA",
    "sg:tags":[
        "church"
    ],
    "wof:name":"Church Of The Nazarene-Rialto",
    "wof:placetype":"venue"
},
  "geometry": {"coordinates":[-117.374737,34.126014],"type":"Point"}
}