{
  "type": "Feature",
  "properties": {
    "addr:full":"840 N Puente Ave La Puente CA 91746",
    "addr:housenumber":"840",
    "addr:postcode":"91746",
    "addr:street":"N Puente Ave",
    "iso:country":"US",
    "sg:address":"840 N Puente Ave",
    "sg:city":"La Puente",
    "sg:classifiers":[
        {
            "category":"Social Services",
            "subcategory":"Child Care",
            "type":"Services"
        }
    ],
    "sg:phone":"+1 626 918 2263",
    "sg:postcode":"91746",
    "sg:province":"CA",
    "wof:name":"Guzman Family Day Care",
    "wof:placetype":"venue"
},
  "geometry": {"coordinates":[-117.97756699999999,34.054839],"type":"Point"}
}