{
  "type": "Feature",
  "properties": {
    "addr:full":"1830 Vernon St Roseville CA 95678",
    "addr:housenumber":"1830",
    "addr:postcode":"95678",
    "addr:street":"Vernon St",
    "iso:country":"US",
    "sg:address":"1830 Vernon St",
    "sg:city":"Roseville",
    "sg:classifiers":[
        {
            "category":"Building & Trades",
            "subcategory":"Construction",
            "type":"Services"
        }
    ],
    "sg:phone":"+1 916 784 3388",
    "sg:postcode":"95678",
    "sg:province":"CA",
    "sg:tags":[
        "contractor"
    ],
    "wof:name":"Jones Construction",
    "wof:placetype":"venue"
},
  "geometry": {"coordinates":[-121.29980500000001,38.731413],"type":"Point"}
}