{
  "type": "Feature",
  "properties": {
    "addr:full":"3600 Harbor Blvd Oxnard CA 93035",
    "addr:housenumber":"3600",
    "addr:postcode":"93035",
    "addr:street":"Harbor Blvd",
    "iso:country":"US",
    "sg:address":"3600 Harbor Blvd",
    "sg:city":"Oxnard",
    "sg:classifiers":[
        {
            "category":"Autos & Motor Vehicles",
            "subcategory":"Boat Sales",
            "type":"Retail Goods"
        }
    ],
    "sg:phone":"+1 805 815 4520",
    "sg:postcode":"93035",
    "sg:province":"CA",
    "sg:tags":[
        "equipment",
        "supply"
    ],
    "sg:website":"www.coastchandlery.com",
    "wof:name":"Coast Chandlery",
    "wof:placetype":"venue"
},
  "geometry": {"coordinates":[-119.229388,34.167597],"type":"Point"}
}