{
  "type": "Feature",
  "properties": {
    "iso:country":"US",
    "sg:address":"35 Tierra Verde Ct",
    "sg:city":"Walnut Creek",
    "sg:classifiers":[
        {
            "category":"Professional",
            "subcategory":"Computer Services",
            "type":"Services"
        }
    ],
    "sg:phone":"+1 925 945 8863",
    "sg:postcode":"94598",
    "sg:province":"CA",
    "sg:tags":[
        "hardware",
        "provider",
        "internet",
        "software"
    ],
    "wof:name":"Oasis Tech Limited",
    "wof:placetype":"venue"
},
  "geometry": {"coordinates":[-122.035117,37.907124],"type":"Point"}
}