{
  "type": "Feature",
  "properties": {
    "iso:country":"US",
    "sg:address":"1750 Stokes Street Ofc",
    "sg:city":"San Jose",
    "sg:classifiers":[
        {
            "category":"Real Estate",
            "subcategory":"Real Estate Operator",
            "type":"Services"
        }
    ],
    "sg:phone":"+1 408 998 0300",
    "sg:postcode":"95126",
    "sg:province":"CA",
    "sg:tags":[
        "apartment"
    ],
    "wof:name":"Central Park Apartments",
    "wof:placetype":"venue"
},
  "geometry": {"coordinates":[-121.924813,37.301231],"type":"Point"}
}