{
  "type": "Feature",
  "properties": {
    "addr:full":"1050 N Pacific Ave San Pedro CA 90731",
    "addr:housenumber":"1050",
    "addr:postcode":"90731",
    "addr:street":"N Pacific Ave",
    "iso:country":"US",
    "sg:address":"1050 N Pacific Ave",
    "sg:city":"San Pedro",
    "sg:classifiers":[
        {
            "category":"Retail",
            "subcategory":"Auto Repair",
            "type":"Services"
        }
    ],
    "sg:phone":"+1 310 833 5977",
    "sg:postcode":"90731",
    "sg:province":"CA",
    "sg:tags":[
        "repairing",
        "automobile"
    ],
    "wof:name":"Tuneup Masters",
    "wof:placetype":"venue"
},
  "geometry": {"coordinates":[-118.290498,33.753831],"type":"Point"}
}