{
  "type": "Feature",
  "properties": {
    "iso:country":"US",
    "sg:address":"1756 Carmel Dr",
    "sg:city":"Walnut Creek",
    "sg:classifiers":[
        {
            "category":"Real Estate",
            "subcategory":"Real Estate Operator",
            "type":"Services"
        }
    ],
    "sg:phone":"+1 925 934 1537",
    "sg:postcode":"94596",
    "sg:province":"CA",
    "sg:tags":[
        "apartment"
    ],
    "wof:name":"Carmel House",
    "wof:placetype":"venue"
},
  "geometry": {"coordinates":[-122.058316,37.901984],"type":"Point"}
}