{
  "type": "Feature",
  "properties": {
    "iso:country":"US",
    "sg:address":"11300 Coloma Rd",
    "sg:city":"Gold River",
    "sg:classifiers":[
        {
            "category":"Insurance",
            "subcategory":"Insurance Agent",
            "type":"Services"
        }
    ],
    "sg:phone":"+1 916 861 0700",
    "sg:postcode":"95670",
    "sg:province":"CA",
    "wof:name":"Cheryl Y WEIS Insurance",
    "wof:placetype":"venue"
},
  "geometry": {"coordinates":[-121.260578,38.620965],"type":"Point"}
}