{
  "type": "Feature",
  "properties": {
    "addr:full":"205 E Clark Ave Santa Maria CA 93455",
    "addr:housenumber":"205",
    "addr:postcode":"93455",
    "addr:street":"E Clark Ave",
    "iso:country":"US",
    "sg:address":"205 E Clark Ave",
    "sg:city":"Santa Maria",
    "sg:classifiers":[
        {
            "category":"Shopping",
            "type":"Retail Goods"
        }
    ],
    "sg:phone":"+1 805 937 1058",
    "sg:postcode":"93455",
    "sg:province":"CA",
    "sg:tags":[
        "art",
        "gallery",
        "dealer"
    ],
    "wof:name":"David Ryan Gallery",
    "wof:placetype":"venue"
},
  "geometry": {"coordinates":[-120.444715,34.865251],"type":"Point"}
}