{
  "type": "Feature",
  "properties": {
    "iso:country":"US",
    "sg:address":"9885 Mesa Rim Rd",
    "sg:city":"San Diego",
    "sg:classifiers":[
        {
            "category":"Wholesale",
            "subcategory":"Groceries",
            "type":"Manufacturing & Wholesale Goods"
        }
    ],
    "sg:phone":"+1 858 625 9013",
    "sg:postcode":"92121",
    "sg:province":"CA",
    "sg:tags":[
        "chips",
        "potato"
    ],
    "wof:name":"Charles Chips",
    "wof:placetype":"venue"
},
  "geometry": {"coordinates":[-117.177379,32.901203],"type":"Point"}
}