{
  "type": "Feature",
  "properties": {
    "addr:full":"212 Fraxinella St Encinitas CA 92024",
    "addr:housenumber":"212",
    "addr:postcode":"92024",
    "addr:street":"Fraxinella St",
    "iso:country":"US",
    "sg:address":"212 Fraxinella St",
    "sg:city":"Encinitas",
    "sg:classifiers":[
        {
            "category":"Banks & Credit Unions",
            "subcategory":"Financial Services",
            "type":"Services"
        }
    ],
    "sg:phone":"+1 760 436 1383",
    "sg:postcode":"92024",
    "sg:province":"CA",
    "sg:tags":[
        "trust",
        "management"
    ],
    "wof:name":"Seymore Family Trust",
    "wof:placetype":"venue"
},
  "geometry": {"coordinates":[-117.273121,33.05118],"type":"Point"}
}