{
  "type": "Feature",
  "properties": {
    "addr:full":"340 S Pine Ave Long Beach CA 90802",
    "addr:housenumber":"340",
    "addr:postcode":"90802",
    "addr:street":"S Pine Ave",
    "iso:country":"US",
    "sg:address":"340 S Pine Ave",
    "sg:city":"Long Beach",
    "sg:classifiers":[
        {
            "category":"Restaurant",
            "type":"Food & Drink"
        }
    ],
    "sg:menulink":"http://www.allmenus.com/ca/long-beach-lakewood/6640-pf-changs/menu/",
    "sg:phone":"+1 562 308 1025",
    "sg:postcode":"90802",
    "sg:province":"CA",
    "sg:tags":[
        "japanese",
        "chinese",
        "asian"
    ],
    "wof:name":"P.F. Chang's",
    "wof:placetype":"venue"
},
  "geometry": {"coordinates":[-118.192956,33.762617],"type":"Point"}
}