{
  "type": "Feature",
  "properties": {
    "iso:country":"US",
    "sg:address":"47159 Youngs Ln",
    "sg:city":"Indio",
    "sg:classifiers":[
        {
            "category":"Professional",
            "subcategory":"Advertising",
            "type":"Services"
        }
    ],
    "sg:phone":"+1 760 775 3626",
    "sg:postcode":"92201",
    "sg:province":"CA",
    "sg:tags":[
        "counselor"
    ],
    "wof:name":"Eaton & KIRK Advertising",
    "wof:placetype":"venue"
},
  "geometry": {"coordinates":[-116.255805,33.70573],"type":"Point"}
}