{
  "type": "Feature",
  "properties": {
    "iso:country":"US",
    "sg:address":"3 del Amo Fashion Sq",
    "sg:city":"Torrance",
    "sg:classifiers":[
        {
            "category":"Professional",
            "type":"Services"
        }
    ],
    "sg:phone":"+1 310 214 9696",
    "sg:postcode":"90503",
    "sg:province":"CA",
    "wof:name":"Santas Treasure Chest",
    "wof:placetype":"venue"
},
  "geometry": {"coordinates":[-118.350677,33.828522],"type":"Point"}
}