{
  "type": "Feature",
  "properties": {
    "addr:full":"529 Hartnell St Monterey CA 93940",
    "addr:housenumber":"529",
    "addr:postcode":"93940",
    "addr:street":"Hartnell St",
    "iso:country":"US",
    "sg:address":"529 Hartnell St",
    "sg:city":"Monterey",
    "sg:classifiers":[
        {
            "category":"Travel",
            "subcategory":"Travel Agent",
            "type":"Entertainment"
        }
    ],
    "sg:phone":"+1 831 375 3100",
    "sg:postcode":"93940",
    "sg:province":"CA",
    "sg:tags":[
        "agency"
    ],
    "wof:name":"First World Travel",
    "wof:placetype":"venue"
},
  "geometry": {"coordinates":[-121.89598700000001,36.596864],"type":"Point"}
}