{
  "type": "Feature",
  "properties": {
    "addr:full":"3742 Mission St San Francisco CA 94110",
    "addr:housenumber":"3742",
    "addr:postcode":"94110",
    "addr:street":"Mission St",
    "iso:country":"US",
    "sg:address":"3742 Mission St",
    "sg:city":"San Francisco",
    "sg:classifiers":[
        {
            "category":"Freight",
            "type":"Transportation"
        },
        {
            "category":"Airline",
            "type":"Transportation"
        }
    ],
    "sg:phone":"+1 415 648 3535",
    "sg:postcode":"94110",
    "sg:province":"CA",
    "sg:tags":[
        "delivery",
        "courier",
        "air"
    ],
    "wof:name":"Transporte Nicaragua",
    "wof:placetype":"venue"
},
  "geometry": {"coordinates":[-122.424128,37.737329],"type":"Point"}
}