{
  "type": "Feature",
  "properties": {
    "addr:full":"726 Mendocino Ave Santa Rosa CA 95401",
    "addr:housenumber":"726",
    "addr:postcode":"95401",
    "addr:street":"Mendocino Ave",
    "iso:country":"US",
    "sg:address":"726 Mendocino Ave",
    "sg:city":"Santa Rosa",
    "sg:classifiers":[
        {
            "category":"Insurance",
            "subcategory":"Insurance Agent",
            "type":"Services"
        }
    ],
    "sg:phone":"+1 707 523 2994",
    "sg:postcode":"95401",
    "sg:province":"CA",
    "wof:name":"Farmers Insurance Group",
    "wof:placetype":"venue"
},
  "geometry": {"coordinates":[-122.717628,38.445667],"type":"Point"}
}