{
  "type": "Feature",
  "properties": {
    "iso:country":"US",
    "sg:address":"1710 Parker Polich Ct",
    "sg:city":"Tracy",
    "sg:classifiers":[
        {
            "category":"Building & Trades",
            "subcategory":"Construction",
            "type":"Services"
        }
    ],
    "sg:phone":"+1 209 835 9330",
    "sg:postcode":"95376",
    "sg:province":"CA",
    "sg:tags":[
        "marking",
        "maintenance",
        "parking"
    ],
    "wof:name":"A 1 Stripes & Stencils",
    "wof:placetype":"venue"
},
  "geometry": {"coordinates":[-121.44756,37.722593],"type":"Point"}
}