{
  "type": "Feature",
  "properties": {
    "iso:country":"US",
    "sg:address":"126 S Vineyard Ave",
    "sg:city":"Ontario",
    "sg:classifiers":[
        {
            "category":"Retail",
            "subcategory":"Auto Rental",
            "type":"Services"
        }
    ],
    "sg:phone":"+1 909 458 1198",
    "sg:postcode":"91761",
    "sg:province":"CA",
    "sg:tags":[
        "home",
        "leasing",
        "motor"
    ],
    "wof:name":"El Monte Rv",
    "wof:placetype":"venue"
},
  "geometry": {"coordinates":[-117.611048,34.063241],"type":"Point"}
}