{
  "type": "Feature",
  "properties": {
    "iso:country":"US",
    "sg:address":"4648 Mac Arthur Blvd",
    "sg:city":"Newport Beach",
    "sg:classifiers":[
        {
            "category":"Professional",
            "subcategory":"Lawyer & Legal Services",
            "type":"Services"
        },
        {
            "category":"Banks & Credit Unions",
            "subcategory":"Atm",
            "type":"Services"
        }
    ],
    "sg:phone":"+1 888 494 6481",
    "sg:postcode":"92660",
    "sg:province":"CA",
    "sg:tags":[
        "personal",
        "injury",
        "bankruptcy"
    ],
    "wof:name":"Law Offices of Craig Sturm",
    "wof:placetype":"venue"
},
  "geometry": {"coordinates":[-117.86437100000001,33.6697],"type":"Point"}
}