{
  "type": "Feature",
  "properties": {
    "addr:full":"3740 La Sierra Ave Riverside CA 92505",
    "addr:housenumber":"3740",
    "addr:postcode":"92505",
    "addr:street":"La Sierra Ave",
    "iso:country":"US",
    "sg:address":"3740 La Sierra Ave",
    "sg:city":"Riverside",
    "sg:classifiers":[
        {
            "category":"Restaurant",
            "type":"Food & Drink"
        }
    ],
    "sg:menulink":"http://www.allmenus.com/ca/riverside/168694-el-pollo-loco/menu/",
    "sg:phone":"+1 951 351 4242",
    "sg:postcode":"92505",
    "sg:province":"CA",
    "sg:tags":[
        "american",
        "mexican",
        "tex-mex"
    ],
    "wof:name":"El Pollo Loco",
    "wof:placetype":"venue"
},
  "geometry": {"coordinates":[-117.475803,33.902395],"type":"Point"}
}