{
  "type": "Feature",
  "properties": {
    "addr:full":"138 Golf Club Dr Santa Cruz CA 95060",
    "addr:housenumber":"138",
    "addr:postcode":"95060",
    "addr:street":"Golf Club Dr",
    "iso:country":"US",
    "sg:address":"138 Golf Club Dr",
    "sg:city":"Santa Cruz",
    "sg:classifiers":[
        {
            "category":"Local Transit",
            "type":"Transportation"
        }
    ],
    "sg:phone":"+1 831 429 5455",
    "sg:postcode":"95060",
    "sg:province":"CA",
    "sg:tags":[
        "bus"
    ],
    "wof:name":"Maintenance Dept",
    "wof:placetype":"venue"
},
  "geometry": {"coordinates":[-122.032585,36.989649],"type":"Point"}
}