{
  "type": "Feature",
  "properties": {
    "iso:country":"US",
    "sg:address":"13204 Arcturus Ave",
    "sg:city":"Gardena",
    "sg:classifiers":[
        {
            "category":"Place Of Worship",
            "type":"Public Place"
        }
    ],
    "sg:phone":"+1 310 538 1712",
    "sg:postcode":"90249",
    "sg:province":"CA",
    "sg:tags":[
        "church"
    ],
    "wof:name":"Los Angeles Church Of Faith And Delivera",
    "wof:placetype":"venue"
},
  "geometry": {"coordinates":[-118.321289,33.912602],"type":"Point"}
}