{
  "type": "Feature",
  "properties": {
    "addr:full":"4813 Greenleaf Ct Modesto CA 95356",
    "addr:housenumber":"4813",
    "addr:postcode":"ca 95356",
    "addr:street":"Greenleaf Ct",
    "iso:country":"US",
    "sg:address":"4813 Greenleaf Ct",
    "sg:city":"Modesto",
    "sg:classifiers":[
        {
            "category":"Manufacturing",
            "subcategory":"Textiles",
            "type":"Manufacturing & Wholesale Goods"
        },
        {
            "category":"Building & Trades",
            "subcategory":"Construction",
            "type":"Services"
        },
        {
            "category":"Manufacturing",
            "subcategory":"Building Materials",
            "type":"Manufacturing & Wholesale Goods"
        },
        {
            "category":"Home & Garden",
            "subcategory":"Carpets & Floor Coverings",
            "type":"Retail Goods"
        }
    ],
    "sg:phone":"+1 209 545 2000",
    "sg:postcode":"95356",
    "sg:province":"CA",
    "sg:tags":[
        "tile-wholesale",
        "materials-wholesale",
        "manufacturer",
        "tile-contractors"
    ],
    "sg:website":"http://www.bedrosians.com",
    "wof:name":"Bedrosians Tile & Stone",
    "wof:placetype":"venue"
},
  "geometry": {"coordinates":[-121.070651,37.702802],"type":"Point"}
}