{
  "type": "Feature",
  "properties": {
    "addr:full":"1568 W Foothill Blvd Rialto CA 92376",
    "addr:housenumber":"1568",
    "addr:postcode":"92376",
    "addr:street":"W Foothill Blvd",
    "iso:country":"US",
    "sg:address":"1568 W Foothill Blvd",
    "sg:city":"Rialto",
    "sg:classifiers":[
        {
            "category":"Autos & Motor Vehicles",
            "subcategory":"Automobile Sales",
            "type":"Retail Goods"
        }
    ],
    "sg:phone":"+1 909 427 1008",
    "sg:postcode":"92376",
    "sg:province":"CA",
    "sg:tags":[
        "car",
        "dealer"
    ],
    "wof:name":"Lobo Auto Sales",
    "wof:placetype":"venue"
},
  "geometry": {"coordinates":[-117.403904,34.106812],"type":"Point"}
}