{
  "type": "Feature",
  "properties": {
    "iso:country":"US",
    "sg:address":"13993 Boquita Dr",
    "sg:city":"Del Mar",
    "sg:classifiers":[
        {
            "category":"Home & Garden",
            "subcategory":"Building Materials",
            "type":"Retail Goods"
        }
    ],
    "sg:phone":"+1 858 793 1459",
    "sg:postcode":"92014",
    "sg:province":"CA",
    "sg:tags":[
        "shutter"
    ],
    "wof:name":"Golden West Shutters",
    "wof:placetype":"venue"
},
  "geometry": {"coordinates":[-117.249635,32.951556],"type":"Point"}
}