{
  "type": "Feature",
  "properties": {
    "iso:country":"US",
    "sg:address":"447 Great Mall Dr",
    "sg:city":"Milpitas",
    "sg:classifiers":[
        {
            "category":"Utilities",
            "subcategory":"Mobile Phone",
            "type":"Services"
        }
    ],
    "sg:phone":"+1 408 935 8640",
    "sg:postcode":"95035",
    "sg:province":"CA",
    "sg:tags":[
        "telephone",
        "cellular"
    ],
    "wof:name":"Bay Wireless Talk",
    "wof:placetype":"venue"
},
  "geometry": {"coordinates":[-121.895914,37.415197],"type":"Point"}
}