{
  "type": "Feature",
  "properties": {
    "addr:full":"1850 Natalie Rd Bakersfield CA 93307",
    "addr:housenumber":"1850",
    "addr:postcode":"93307",
    "addr:street":"Natalie Rd",
    "iso:country":"US",
    "sg:address":"1850 Natalie Rd",
    "sg:city":"Bakersfield",
    "sg:classifiers":[
        {
            "category":"Professional",
            "type":"Services"
        },
        {
            "category":"Farming",
            "subcategory":"Farm",
            "type":"Manufacturing & Wholesale Goods"
        }
    ],
    "sg:phone":"+1 661 858 6117",
    "sg:postcode":"93307",
    "sg:province":"CA",
    "sg:tags":[
        "establishment",
        "crop",
        "general"
    ],
    "wof:name":"Sun Pacific Farming Co",
    "wof:placetype":"venue"
},
  "geometry": {"coordinates":[-118.958045,35.069006],"type":"Point"}
}