{
  "type": "Feature",
  "properties": {
    "addr:full":"13669 California St Yucaipa CA 92399",
    "addr:housenumber":"13669",
    "addr:postcode":"92399",
    "addr:street":"California St",
    "iso:country":"US",
    "sg:address":"13669 California St",
    "sg:city":"Yucaipa",
    "sg:classifiers":[
        {
            "category":"Retail",
            "subcategory":"Event Space",
            "type":"Services"
        }
    ],
    "sg:phone":"+1 909 795 9070",
    "sg:postcode":"92399",
    "sg:province":"CA",
    "sg:tags":[
        "venue"
    ],
    "wof:name":"Yucaipa Masonic Hall Association",
    "wof:placetype":"venue"
},
  "geometry": {"coordinates":[-117.039001,34.0051],"type":"Point"}
}