{
  "type": "Feature",
  "properties": {
    "iso:country":"US",
    "sg:address":"1327 Crenshaw Boulevard",
    "sg:city":"Los Angeles",
    "sg:classifiers":[
        {
            "category":"Real Estate",
            "subcategory":"Real Estate Operator",
            "type":"Services"
        }
    ],
    "sg:phone":"+1 323 936 1812",
    "sg:postcode":"90019",
    "sg:province":"CA",
    "sg:tags":[
        "apartment"
    ],
    "wof:name":"Crenshaw Townhouse",
    "wof:placetype":"venue"
},
  "geometry": {"coordinates":[-118.32687199999999,34.047557],"type":"Point"}
}