{
  "type": "Feature",
  "properties": {
    "iso:country":"US",
    "sg:address":"5142 Waring Rd",
    "sg:city":"San Diego",
    "sg:classifiers":[
        {
            "category":"Personal",
            "subcategory":"Barber",
            "type":"Services"
        }
    ],
    "sg:phone":"+1 619 582 6842",
    "sg:postcode":"92120",
    "sg:province":"CA",
    "wof:name":"Allied Gardens Barber Shop",
    "wof:placetype":"venue"
},
  "geometry": {"coordinates":[-117.08200100000001,32.791],"type":"Point"}
}