{
  "type": "Feature",
  "properties": {
    "iso:country":"US",
    "sg:address":"400 Moffett Blvd",
    "sg:city":"Mountain View",
    "sg:classifiers":[
        {
            "category":"Professional",
            "subcategory":"Business Services",
            "type":"Services"
        }
    ],
    "sg:phone":"+1 650 967 0665",
    "sg:postcode":"94043",
    "sg:province":"CA",
    "sg:tags":[
        "food",
        "delivery"
    ],
    "wof:name":"Pure Valley Water of Mountain View",
    "wof:placetype":"venue"
},
  "geometry": {"coordinates":[-122.07501999999999,37.399667],"type":"Point"}
}