{
  "type": "Feature",
  "properties": {
    "addr:full":"1395 7th St Oakland CA 94607",
    "addr:housenumber":"1395",
    "addr:postcode":"94607",
    "addr:street":"7Th St",
    "iso:country":"US",
    "sg:address":"1395 7th St",
    "sg:city":"Oakland",
    "sg:classifiers":[
        {
            "category":"Autos & Motor Vehicles",
            "subcategory":"Fuel & Gas Station",
            "type":"Retail Goods"
        }
    ],
    "sg:phone":"+1 510 465 6569",
    "sg:postcode":"94607",
    "sg:province":"CA",
    "wof:name":"Trucker Fuel",
    "wof:placetype":"venue"
},
  "geometry": {"coordinates":[-122.29299899999999,37.804798],"type":"Point"}
}