{
  "type": "Feature",
  "properties": {
    "iso:country":"US",
    "sg:address":"2106 Main St",
    "sg:city":"Julian",
    "sg:classifiers":[
        {
            "category":"Shopping",
            "subcategory":"Gifts & Souvenirs",
            "type":"Retail Goods"
        }
    ],
    "sg:phone":"+1 760 765 2490",
    "sg:postcode":"92036",
    "sg:province":"CA",
    "sg:tags":[
        "shop"
    ],
    "wof:name":"Julian Imports",
    "wof:placetype":"venue"
},
  "geometry": {"coordinates":[-116.601495,33.078017],"type":"Point"}
}