{
  "type": "Feature",
  "properties": {
    "addr:full":"12631 Lewis St Garden Grove CA 92840",
    "addr:housenumber":"12631",
    "addr:postcode":"92840",
    "addr:street":"Lewis St",
    "iso:country":"US",
    "sg:address":"12631 Lewis St",
    "sg:city":"Garden Grove",
    "sg:classifiers":[
        {
            "category":"Communications",
            "subcategory":"Film & Video Production",
            "type":"Services"
        }
    ],
    "sg:phone":"+1 714 376 3146",
    "sg:postcode":"92840",
    "sg:province":"CA",
    "sg:tags":[
        "taping"
    ],
    "wof:name":"Affordable Video Productions",
    "wof:placetype":"venue"
},
  "geometry": {"coordinates":[-117.89746,33.781309],"type":"Point"}
}