{
  "type": "Feature",
  "properties": {
    "iso:country":"US",
    "sg:address":"30997 Huntwood Ave",
    "sg:city":"Hayward",
    "sg:classifiers":[
        {
            "category":"Professional",
            "subcategory":"Advertising",
            "type":"Services"
        }
    ],
    "sg:phone":"+1 510 487 8660",
    "sg:postcode":"94544",
    "sg:province":"CA",
    "sg:tags":[
        "counselor"
    ],
    "sg:website":"www.ovrstreet.com",
    "wof:name":"Overstreet & Assoc",
    "wof:placetype":"venue"
},
  "geometry": {"coordinates":[-122.054922,37.61687],"type":"Point"}
}