{
  "type": "Feature",
  "properties": {
    "iso:country":"US",
    "sg:address":"953 Tower Pl",
    "sg:city":"Santa Cruz",
    "sg:classifiers":[
        {
            "category":"Wholesale",
            "subcategory":"Machinery & Supplies",
            "type":"Manufacturing & Wholesale Goods"
        }
    ],
    "sg:phone":"+1 831 479 4803",
    "sg:postcode":"95062",
    "sg:province":"CA",
    "sg:tags":[
        "apparel",
        "fastener"
    ],
    "sg:website":"www.cannabisworks.com",
    "wof:name":"Pan World Traders",
    "wof:placetype":"venue"
},
  "geometry": {"coordinates":[-121.982229,36.967741],"type":"Point"}
}