{
  "type": "Feature",
  "properties": {
    "addr:full":"1225 Saviers Rd Oxnard CA 93033",
    "addr:housenumber":"1225",
    "addr:postcode":"93033",
    "addr:street":"Saviers Rd",
    "iso:country":"US",
    "sg:address":"1225 Saviers Rd",
    "sg:city":"Oxnard",
    "sg:classifiers":[
        {
            "category":"Autos & Motor Vehicles",
            "subcategory":"Automobile Sales",
            "type":"Retail Goods"
        }
    ],
    "sg:phone":"+1 805 240 9810",
    "sg:postcode":"93033",
    "sg:province":"CA",
    "sg:tags":[
        "sport",
        "trailer",
        "utility"
    ],
    "sg:website":"www.maddawgtrailers.com",
    "wof:name":"Maddawg Trailer Sales",
    "wof:placetype":"venue"
},
  "geometry": {"coordinates":[-119.177543,34.187016],"type":"Point"}
}