{
  "type": "Feature",
  "properties": {
    "iso:country":"US",
    "sg:address":"1475 W 139th St",
    "sg:city":"Gardena",
    "sg:classifiers":[
        {
            "category":"Wholesale",
            "subcategory":"Chemicals & Plastics",
            "type":"Manufacturing & Wholesale Goods"
        }
    ],
    "sg:phone":"+1 310 515 3680",
    "sg:postcode":"90249",
    "sg:province":"CA",
    "sg:tags":[
        "ind",
        "industrial"
    ],
    "sg:website":"www.oscarent.com",
    "wof:name":"Oscar Enterprises Inc",
    "wof:placetype":"venue"
},
  "geometry": {"coordinates":[-118.30199,33.905622],"type":"Point"}
}