{
  "type": "Feature",
  "properties": {
    "addr:full":"525 Henrietta St Martinez CA 94553",
    "addr:housenumber":"525",
    "addr:postcode":"94553",
    "addr:street":"Henrietta St",
    "iso:country":"US",
    "sg:address":"525 Henrietta St",
    "sg:city":"Martinez",
    "sg:classifiers":[
        {
            "category":"Government",
            "subcategory":"Office",
            "type":"Public Place"
        }
    ],
    "sg:phone":"+1 925 372 3504",
    "sg:postcode":"94553",
    "sg:province":"CA",
    "sg:tags":[
        "city",
        "taxation"
    ],
    "wof:name":"Martinez City Treasurer",
    "wof:placetype":"venue"
},
  "geometry": {"coordinates":[-122.13500500000001,38.014001],"type":"Point"}
}