{
  "type": "Feature",
  "properties": {
    "iso:country":"US",
    "sg:address":"3262 Airway Dr",
    "sg:city":"Santa Rosa",
    "sg:classifiers":[
        {
            "category":"Professional",
            "subcategory":"Advertising",
            "type":"Services"
        }
    ],
    "sg:phone":"+1 707 575 1320",
    "sg:postcode":"95403",
    "sg:province":"CA",
    "sg:tags":[
        "representative"
    ],
    "wof:name":"Cable One",
    "wof:placetype":"venue"
},
  "geometry": {"coordinates":[-122.738024,38.473576],"type":"Point"}
}