{
  "type": "Feature",
  "properties": {
    "iso:country":"US",
    "sg:address":"5741 Palmer Way",
    "sg:city":"Carlsbad",
    "sg:classifiers":[
        {
            "category":"Professional",
            "subcategory":"Engineering",
            "type":"Services"
        }
    ],
    "sg:phone":"+1 760 438 3155",
    "sg:postcode":"92010",
    "sg:province":"CA",
    "sg:tags":[
        "engineer"
    ],
    "sg:website":"www.geosoilsinc.com",
    "wof:name":"Geo Soils Inc",
    "wof:placetype":"venue"
},
  "geometry": {"coordinates":[-117.271832,33.137111],"type":"Point"}
}