{
  "type": "Feature",
  "properties": {
    "iso:country":"US",
    "sg:address":"1334 Berwick Dr",
    "sg:city":"Cambria",
    "sg:classifiers":[
        {
            "category":"Professional",
            "subcategory":"Computer Services",
            "type":"Services"
        }
    ],
    "sg:phone":"+1 805 927 0491",
    "sg:postcode":"93428",
    "sg:province":"CA",
    "sg:tags":[
        "datum"
    ],
    "wof:name":"Diversified Macintosh Service",
    "wof:placetype":"venue"
},
  "geometry": {"coordinates":[-121.08001899999999,35.546934],"type":"Point"}
}