{
  "type": "Feature",
  "properties": {
    "addr:full":"2383 Via Segundo San Diego CA 92173",
    "addr:housenumber":"2383",
    "addr:postcode":"92173",
    "addr:street":"Via Segundo",
    "iso:country":"US",
    "sg:address":"2383 Via Segundo",
    "sg:city":"San Diego",
    "sg:classifiers":[
        {
            "category":"Shopping",
            "subcategory":"Hobbies, Toys, & Games",
            "type":"Retail Goods"
        },
        {
            "category":"Shopping",
            "subcategory":"Gifts & Souvenirs",
            "type":"Retail Goods"
        }
    ],
    "sg:phone":"+1 619 662 3501",
    "sg:postcode":"92173",
    "sg:province":"CA",
    "sg:tags":[
        "product",
        "ceramic"
    ],
    "wof:name":"Ceramica Ruiz",
    "wof:placetype":"venue"
},
  "geometry": {"coordinates":[-117.05309099999999,32.554319],"type":"Point"}
}