{
  "type": "Feature",
  "properties": {
    "iso:country":"US",
    "sg:address":"6642 Clara St",
    "sg:city":"Bell Gardens",
    "sg:classifiers":[
        {
            "category":"Wholesale",
            "subcategory":"Meat",
            "type":"Manufacturing & Wholesale Goods"
        }
    ],
    "sg:phone":"+1 562 927 9523",
    "sg:postcode":"90201",
    "sg:province":"CA",
    "sg:tags":[
        "shop"
    ],
    "wof:name":"Franks A Lot",
    "wof:placetype":"venue"
},
  "geometry": {"coordinates":[-118.147003,33.961102],"type":"Point"}
}