{
  "type": "Feature",
  "properties": {
    "iso:country":"US",
    "sg:address":"302 N Brandon Rd",
    "sg:city":"Fallbrook",
    "sg:classifiers":[
        {
            "category":"Social Services",
            "type":"Services"
        }
    ],
    "sg:phone":"+1 760 723 9327",
    "sg:postcode":"92028",
    "sg:province":"CA",
    "sg:tags":[
        "youth",
        "organization",
        "center"
    ],
    "wof:name":"Nicppfallbrook Prevention Ofc",
    "wof:placetype":"venue"
},
  "geometry": {"coordinates":[-117.244764,33.381991],"type":"Point"}
}