{
  "type": "Feature",
  "properties": {
    "addr:full":"2030 Main St Irvine CA 92614",
    "addr:housenumber":"2030",
    "addr:postcode":"92614",
    "addr:street":"Main St",
    "iso:country":"US",
    "sg:address":"2030 Main St",
    "sg:city":"Irvine",
    "sg:classifiers":[
        {
            "category":"Banks & Credit Unions",
            "subcategory":"Investment Brokerage",
            "type":"Services"
        }
    ],
    "sg:phone":"+1 949 387 4900",
    "sg:postcode":"92614",
    "sg:province":"CA",
    "sg:tags":[
        "investing"
    ],
    "wof:name":"Mason Asset Management",
    "wof:placetype":"venue"
},
  "geometry": {"coordinates":[-117.85153200000001,33.684687],"type":"Point"}
}