{
  "type": "Feature",
  "properties": {
    "iso:country":"US",
    "sg:address":"26865 Durham Way",
    "sg:city":"Hayward",
    "sg:classifiers":[
        {
            "category":"Retail",
            "subcategory":"Auto Rental",
            "type":"Services"
        }
    ],
    "sg:phone":"+1 510 440 8000",
    "sg:postcode":"94542",
    "sg:province":"CA",
    "sg:tags":[
        "automobile",
        "leasing"
    ],
    "wof:name":"Felimar Co",
    "wof:placetype":"venue"
},
  "geometry": {"coordinates":[-122.032598,37.66417],"type":"Point"}
}