{
  "type": "Feature",
  "properties": {
    "iso:country":"US",
    "sg:address":"1280 Central Blvd",
    "sg:city":"Brentwood",
    "sg:classifiers":[
        {
            "category":"Real Estate",
            "subcategory":"Real Estate Services",
            "type":"Services"
        },
        {
            "category":"Real Estate",
            "subcategory":"Real Estate Agent",
            "type":"Services"
        }
    ],
    "sg:phone":"+1 925 626 3725",
    "sg:postcode":"94513",
    "sg:province":"CA",
    "sg:tags":[
        "buyer",
        "property",
        "management",
        "broker"
    ],
    "wof:name":"Independent Real Estate",
    "wof:placetype":"venue"
},
  "geometry": {"coordinates":[-121.697754,37.939382],"type":"Point"}
}