{
  "type": "Feature",
  "properties": {
    "addr:full":"2400 Ridgeview Dr Chino Hills CA 91709",
    "addr:housenumber":"2400",
    "addr:postcode":"91709",
    "addr:street":"Ridgeview Dr",
    "iso:country":"US",
    "sg:address":"2400 Ridgeview Dr",
    "sg:city":"Chino Hills",
    "sg:classifiers":[
        {
            "category":"Social Services",
            "subcategory":"Adult Care",
            "type":"Services"
        }
    ],
    "sg:phone":"+1 909 396 1203",
    "sg:postcode":"91709",
    "sg:province":"CA",
    "sg:tags":[
        "home",
        "residential"
    ],
    "wof:name":"A+ Country View",
    "wof:placetype":"venue"
},
  "geometry": {"coordinates":[-117.752015,33.983289],"type":"Point"}
}