{
  "type": "Feature",
  "properties": {
    "addr:full":"2295 Otay Lakes Rd Chula Vista CA 91915",
    "addr:housenumber":"2295",
    "addr:postcode":"91915",
    "addr:street":"Otay Lakes Rd",
    "iso:country":"US",
    "sg:address":"2295 Otay Lakes Rd",
    "sg:city":"Chula Vista",
    "sg:classifiers":[
        {
            "category":"Ice Cream",
            "type":"Food & Drink"
        }
    ],
    "sg:menulink":"http://www.allmenus.com/ca/san-diego/183796-cold-stone-creamery/menu/",
    "sg:phone":"+1 619 421 7172",
    "sg:postcode":"91915",
    "sg:province":"CA",
    "sg:tags":[
        "smoothy",
        "juice",
        "american"
    ],
    "wof:name":"Cold Stone Creamery",
    "wof:placetype":"venue"
},
  "geometry": {"coordinates":[-116.965676,32.648213],"type":"Point"}
}