{
  "type": "Feature",
  "properties": {
    "iso:country":"US",
    "sg:address":"1601 Myrtle St.",
    "sg:city":"Oakland",
    "sg:classifiers":[
        {
            "category":"Building & Trades",
            "subcategory":"Construction",
            "type":"Services"
        }
    ],
    "sg:phone":"+1 510 917 6089",
    "sg:postcode":"94607",
    "sg:province":"CA",
    "sg:tags":[
        "contractor"
    ],
    "wof:name":"Pacifica Construction",
    "wof:placetype":"venue"
},
  "geometry": {"coordinates":[-122.281414,37.810111],"type":"Point"}
}