{
  "type": "Feature",
  "properties": {
    "iso:country":"US",
    "sg:address":"1610 Oak St",
    "sg:city":"Solvang",
    "sg:classifiers":[
        {
            "category":"Building & Trades",
            "subcategory":"Construction",
            "type":"Services"
        }
    ],
    "sg:phone":"+1 805 688 3414",
    "sg:postcode":"93463",
    "sg:province":"CA",
    "sg:tags":[
        "commercial",
        "general",
        "shopping",
        "for",
        "contractor"
    ],
    "wof:name":"Baldacchino Construction Co",
    "wof:placetype":"venue"
},
  "geometry": {"coordinates":[-120.142211,34.593921],"type":"Point"}
}