{
  "type": "Feature",
  "properties": {
    "addr:full":"7561 Silverado Ln La Palma CA 90623",
    "addr:housenumber":"7561",
    "addr:postcode":"90623",
    "addr:street":"Silverado Ln",
    "iso:country":"US",
    "sg:address":"7561 Silverado Ln",
    "sg:city":"La Palma",
    "sg:classifiers":[
        {
            "category":"Professional",
            "type":"Services"
        }
    ],
    "sg:phone":"+1 714 865 0029",
    "sg:postcode":"90623",
    "sg:province":"CA",
    "wof:name":"Silverado Systems",
    "wof:placetype":"venue"
},
  "geometry": {"coordinates":[-118.046757,33.852493],"type":"Point"}
}