{
  "type": "Feature",
  "properties": {
    "iso:country":"US",
    "sg:address":"882 San Carrizo Way",
    "sg:city":"Mountain View",
    "sg:classifiers":[
        {
            "category":"Retail",
            "subcategory":"Animal Services",
            "type":"Services"
        }
    ],
    "sg:phone":"+1 650 965 2596",
    "sg:postcode":"94043",
    "sg:province":"CA",
    "wof:name":"Happy Tails To You Dog Tr",
    "wof:placetype":"venue"
},
  "geometry": {"coordinates":[-122.071145,37.40555],"type":"Point"}
}