{
  "type": "Feature",
  "properties": {
    "addr:full":"5978 Silver Creek Valley Road San Jose CA 95138",
    "addr:housenumber":"5978",
    "addr:postcode":"95138",
    "addr:street":"Silver Creek Valley Road",
    "iso:country":"US",
    "sg:address":"5978 Silver Creek Valley Road",
    "sg:city":"San Jose",
    "sg:classifiers":[
        {
            "category":"Juice Bar",
            "subcategory":"None",
            "type":"Food & Drink"
        }
    ],
    "sg:phone":"+1 408 224 6666",
    "sg:postcode":"95138",
    "sg:province":"CA",
    "sg:tags":[
        "smoothy"
    ],
    "sg:website":"smoothieking.com",
    "wof:name":"Smoothie King",
    "wof:placetype":"venue"
},
  "geometry": {"coordinates":[-121.787392,37.257335],"type":"Point"}
}