{
  "type": "Feature",
  "properties": {
    "addr:full":"619 S Vulcan Ave #213 Encinitas CA 92024",
    "addr:housenumber":"619",
    "addr:postcode":"92024",
    "addr:street":"S Vulcan Ave # 213",
    "iso:country":"US",
    "sg:address":"619 S Vulcan Ave #213",
    "sg:city":"Encinitas",
    "sg:classifiers":[
        {
            "category":"Communications",
            "type":"Services"
        }
    ],
    "sg:phone":"+1 619 244 4709",
    "sg:postcode":"92024",
    "sg:province":"CA",
    "sg:tags":[
        "web",
        "design"
    ],
    "wof:name":"VernettiArts",
    "wof:placetype":"venue"
},
  "geometry": {"coordinates":[-117.29208199999999,33.044392],"type":"Point"}
}