{
  "type": "Feature",
  "properties": {
    "iso:country":"US",
    "sg:address":"38780 Trade Center Dr G",
    "sg:city":"Palmdale",
    "sg:classifiers":[
        {
            "category":"Banks & Credit Unions",
            "subcategory":"Financial Services",
            "type":"Services"
        }
    ],
    "sg:phone":"+1 661 575 9301",
    "sg:postcode":"93551",
    "sg:province":"CA",
    "sg:tags":[
        "escrow"
    ],
    "wof:name":"Advantage Gold Escrow Inc",
    "wof:placetype":"venue"
},
  "geometry": {"coordinates":[-118.143271,34.586125],"type":"Point"}
}