{
  "type": "Feature",
  "properties": {
    "iso:country":"US",
    "sg:address":"21675 Redwood Rd",
    "sg:city":"Castro Valley",
    "sg:classifiers":[
        {
            "category":"Health Services",
            "subcategory":"Optometrist",
            "type":"Services"
        }
    ],
    "sg:phone":"+1 510 538 5252",
    "sg:postcode":"94546",
    "sg:province":"CA",
    "sg:tags":[
        "ophthalmologist"
    ],
    "wof:name":"Albracht Diane C MD Inc",
    "wof:placetype":"venue"
},
  "geometry": {"coordinates":[-122.07399700000001,37.689499],"type":"Point"}
}