{
  "type": "Feature",
  "properties": {
    "iso:country":"US",
    "sg:address":"2531 W 237th St",
    "sg:city":"Torrance",
    "sg:classifiers":[
        {
            "category":"Real Estate",
            "subcategory":"Real Estate Agent",
            "type":"Services"
        }
    ],
    "sg:phone":"+1 310 530 8457",
    "sg:postcode":"90505",
    "sg:province":"CA",
    "wof:name":"Maupin Development Inc",
    "wof:placetype":"venue"
},
  "geometry": {"coordinates":[-118.331282,33.811349],"type":"Point"}
}