{
  "type": "Feature",
  "properties": {
    "iso:country":"US",
    "sg:address":"7135 W Manchester Ave",
    "sg:city":"Los Angeles",
    "sg:classifiers":[
        {
            "category":"Organizations",
            "subcategory":"Religious Organization",
            "type":"Services"
        }
    ],
    "sg:phone":"+1 310 417 8730",
    "sg:postcode":"90045",
    "sg:province":"CA",
    "sg:tags":[
        "church"
    ],
    "wof:name":"Resurrection Life Fellowship",
    "wof:placetype":"venue"
},
  "geometry": {"coordinates":[-118.418144,33.959813],"type":"Point"}
}