{
  "type": "Feature",
  "properties": {
    "iso:country":"US",
    "sg:address":"4224 S Vermont Ave",
    "sg:city":"Los Angeles",
    "sg:classifiers":[
        {
            "category":"Organizations",
            "subcategory":"Religious Organization",
            "type":"Services"
        }
    ],
    "sg:phone":"+1 323 235 2120",
    "sg:postcode":"90037",
    "sg:province":"CA",
    "sg:tags":[
        "church"
    ],
    "wof:name":"Faro De Luz Pentecostes Inc",
    "wof:placetype":"venue"
},
  "geometry": {"coordinates":[-118.291465,34.006972],"type":"Point"}
}