{
  "type": "Feature",
  "properties": {
    "iso:country":"US",
    "sg:address":"345 S Locust St",
    "sg:city":"Pomona",
    "sg:classifiers":[
        {
            "category":"Banks & Credit Unions",
            "subcategory":"Financial Services",
            "type":"Services"
        }
    ],
    "sg:phone":"+1 909 865 6406",
    "sg:postcode":"91766",
    "sg:province":"CA",
    "sg:tags":[
        "company",
        "holding"
    ],
    "wof:name":"Arreguin Holdings Inc",
    "wof:placetype":"venue"
},
  "geometry": {"coordinates":[-117.749067,34.056452],"type":"Point"}
}