{
  "type": "Feature",
  "properties": {
    "addr:full":"301 W Las Tunas Dr San Gabriel CA 91776",
    "addr:housenumber":"301",
    "addr:postcode":"91776",
    "addr:street":"W Las Tunas Dr",
    "iso:country":"US",
    "sg:address":"301 W Las Tunas Dr",
    "sg:city":"San Gabriel",
    "sg:classifiers":[
        {
            "category":"Shopping",
            "subcategory":"Computers & Home Electronics",
            "type":"Retail Goods"
        }
    ],
    "sg:phone":"+1 626 285 2013",
    "sg:postcode":"91776",
    "sg:province":"CA",
    "wof:name":"DISH Network",
    "wof:placetype":"venue"
},
  "geometry": {"coordinates":[-118.10248199999999,34.102637],"type":"Point"}
}