{
  "type": "Feature",
  "properties": {
    "iso:country":"US",
    "sg:address":"3330 Pruneridge Ave",
    "sg:city":"Santa Clara",
    "sg:classifiers":[
        {
            "category":"Park",
            "type":"Public Place"
        },
        {
            "category":"Recreation",
            "subcategory":"Playground",
            "type":"Entertainment"
        }
    ],
    "sg:phone":"+1 408 615 2200",
    "sg:postcode":"95052",
    "sg:province":"CA",
    "sg:website":"www.ci.santa-clara.ca.us/park_re...",
    "wof:name":"Maywood Park",
    "wof:placetype":"venue"
},
  "geometry": {"coordinates":[-121.98870700000001,37.331202],"type":"Point"}
}