{
  "type": "Feature",
  "properties": {
    "addr:full":"3081 W Bullard Ave Fresno CA 93711",
    "addr:housenumber":"3081",
    "addr:postcode":"93711",
    "addr:street":"W Bullard Ave",
    "iso:country":"US",
    "sg:address":"3081 W Bullard Ave",
    "sg:city":"Fresno",
    "sg:classifiers":[
        {
            "category":"Recreation",
            "type":"Entertainment"
        }
    ],
    "sg:phone":"+1 559 432 5322",
    "sg:postcode":"93711",
    "sg:province":"CA",
    "sg:tags":[
        "martial",
        "arts",
        "instruction"
    ],
    "wof:name":"Way Of Japan",
    "wof:placetype":"venue"
},
  "geometry": {"coordinates":[-119.846485,36.822642],"type":"Point"}
}