{
  "type": "Feature",
  "properties": {
    "iso:country":"US",
    "sg:address":"1600 Parway Dr",
    "sg:city":"Glendale",
    "sg:classifiers":[
        {
            "category":"Real Estate",
            "subcategory":"Real Estate Agent",
            "type":"Services"
        }
    ],
    "sg:phone":"+1 818 241 1700",
    "sg:postcode":"91206",
    "sg:province":"CA",
    "wof:name":"Noel Igaune",
    "wof:placetype":"venue"
},
  "geometry": {"coordinates":[-118.205345,34.171765],"type":"Point"}
}