{
  "type": "Feature",
  "properties": {
    "addr:full":"1600 Parway Dr Glendale CA 91206",
    "addr:housenumber":"1600",
    "addr:postcode":"91206",
    "addr:street":"Parway Dr",
    "iso:country":"US",
    "sg:address":"1600 Parway Dr",
    "sg:city":"Glendale",
    "sg:classifiers":[
        {
            "category":"Real Estate",
            "subcategory":"Real Estate Agent",
            "type":"Services"
        }
    ],
    "sg:phone":"+1 818 241 1700",
    "sg:postcode":"91206",
    "sg:province":"CA",
    "wof:name":"Noel Igaune",
    "wof:placetype":"venue"
},
  "geometry": {"coordinates":[-118.20534499999999,34.171765],"type":"Point"}
}