{
  "type": "Feature",
  "properties": {
    "addr:full":"2121 Harrison St San Francisco CA 94110",
    "addr:housenumber":"2121",
    "addr:postcode":"94110",
    "addr:street":"Harrison St",
    "iso:country":"US",
    "sg:address":"2121 Harrison St",
    "sg:city":"San Francisco",
    "sg:classifiers":[
        {
            "category":"Retail",
            "subcategory":"Repair Shop",
            "type":"Services"
        }
    ],
    "sg:phone":"+1 415 864 6516",
    "sg:postcode":"94110",
    "sg:province":"CA",
    "sg:tags":[
        "reupholstery",
        "furniture"
    ],
    "sg:website":"www.trickeystudio.com",
    "wof:name":"Trickey Studio",
    "wof:placetype":"venue"
},
  "geometry": {"coordinates":[-122.41289399999999,37.76304],"type":"Point"}
}