{
  "type": "Feature",
  "properties": {
    "addr:full":"5040 W Spruce Ave Fresno CA 93722",
    "addr:housenumber":"5040",
    "addr:postcode":"93722",
    "addr:street":"W Spruce Ave",
    "iso:country":"US",
    "sg:address":"5040 W Spruce Ave",
    "sg:city":"Fresno",
    "sg:classifiers":[
        {
            "category":"Professional",
            "subcategory":"Art Services",
            "type":"Services"
        }
    ],
    "sg:phone":"+1 559 276 2526",
    "sg:postcode":"93722",
    "sg:province":"CA",
    "sg:tags":[
        "graphic",
        "commercial",
        "designer",
        "artist"
    ],
    "wof:name":"Klein S Innovative Dsgns",
    "wof:placetype":"venue"
},
  "geometry": {"coordinates":[-119.88261900000001,36.839965],"type":"Point"}
}