{
  "type": "Feature",
  "properties": {
    "iso:country":"US",
    "sg:address":"67 Georges Dr",
    "sg:city":"Hollister",
    "sg:phone":"+1 831 630 1550",
    "sg:postcode":"95023",
    "sg:province":"CA",
    "wof:name":"Gold Coast Electric",
    "wof:placetype":"venue"
},
  "geometry": {"coordinates":[-121.377692,36.815154],"type":"Point"}
}