{
  "type": "Feature",
  "properties": {
    "addr:full":"10053 E Valley Blvd Ste 15 El Monte CA 91731",
    "addr:housenumber":"10053",
    "addr:postcode":"91731",
    "addr:street":"E Valley Blvd Ste 15",
    "iso:country":"US",
    "sg:address":"10053 E Valley Blvd Ste 15",
    "sg:city":"El Monte",
    "sg:classifiers":[
        {
            "category":"Insurance",
            "subcategory":"Hazard Insurance",
            "type":"Services"
        }
    ],
    "sg:phone":"+1 888 313 6212",
    "sg:postcode":"91731",
    "sg:province":"CA",
    "wof:name":"Global Choice Insurance",
    "wof:placetype":"venue"
},
  "geometry": {"coordinates":[-118.050865,34.078725],"type":"Point"}
}