{
  "type": "Feature",
  "properties": {
    "iso:country":"US",
    "sg:address":"46200 Harrison St",
    "sg:city":"Coachella",
    "sg:classifiers":[
        {
            "category":"Arena",
            "subcategory":"Indoor Arena",
            "type":"Entertainment"
        },
        {
            "category":"Restaurant",
            "type":"Food & Drink"
        },
        {
            "category":"Retail",
            "subcategory":"Event Space",
            "type":"Services"
        },
        {
            "category":"Casinos & Gambling",
            "type":"Entertainment"
        }
    ],
    "sg:phone":"+1 760 775 5566",
    "sg:postcode":"92236",
    "sg:province":"CA",
    "sg:tags":[
        "bingo",
        "facility",
        "banquet",
        "reception",
        "hall"
    ],
    "sg:website":"http://www.spotlight29.com",
    "wof:name":"Spotlight 29 Total Casino",
    "wof:placetype":"venue"
},
  "geometry": {"coordinates":[-116.183182,33.710442],"type":"Point"}
}