{
  "type": "Feature",
  "properties": {
    "iso:country":"US",
    "sg:address":"7860 Mission Center Ct",
    "sg:city":"San Diego",
    "sg:classifiers":[
        {
            "category":"Shopping",
            "subcategory":"Computers & Home Electronics",
            "type":"Retail Goods"
        }
    ],
    "sg:phone":"+1 619 692 9075",
    "sg:postcode":"92108",
    "sg:province":"CA",
    "sg:tags":[
        "equipment",
        "satellite",
        "system"
    ],
    "wof:name":"Affordable Satellite",
    "wof:placetype":"venue"
},
  "geometry": {"coordinates":[-117.155281,32.773639],"type":"Point"}
}