{
  "type": "Feature",
  "properties": {
    "addr:full":"1542 S La Cienega Blvd Los Angeles CA 90035",
    "addr:housenumber":"1542",
    "addr:postcode":"90035",
    "addr:street":"S La Cienega Blvd",
    "iso:country":"US",
    "sg:address":"1542 S La Cienega Blvd",
    "sg:city":"Los Angeles",
    "sg:classifiers":[
        {
            "category":"Retail",
            "subcategory":"Laundry & Dry Cleaning",
            "type":"Services"
        }
    ],
    "sg:phone":"+1 310 360 0935",
    "sg:postcode":"90035",
    "sg:province":"CA",
    "wof:name":"Coin Laundry",
    "wof:placetype":"venue"
},
  "geometry": {"coordinates":[-118.37599899999999,34.0494],"type":"Point"}
}