{
  "type": "Feature",
  "properties": {
    "iso:country":"US",
    "sg:address":"477 S California Ave",
    "sg:city":"Palo Alto",
    "sg:classifiers":[
        {
            "category":"Food & Beverages",
            "subcategory":"Bakery",
            "type":"Retail Goods"
        }
    ],
    "sg:phone":"+1 650 329 0700",
    "sg:postcode":"94306",
    "sg:province":"CA",
    "sg:tags":[
        "bagel"
    ],
    "wof:name":"Izzy's Brooklyn Bagels",
    "wof:placetype":"venue"
},
  "geometry": {"coordinates":[-122.144902,37.426153],"type":"Point"}
}