{
  "type": "Feature",
  "properties": {
    "addr:full":"3421 Starside Dr Bakersfield CA 93312",
    "addr:housenumber":"3421",
    "addr:postcode":"93312",
    "addr:street":"Starside Dr",
    "iso:country":"US",
    "sg:address":"3421 Starside Dr",
    "sg:city":"Bakersfield",
    "sg:classifiers":[
        {
            "category":"Building & Trades",
            "subcategory":"Plumbing",
            "type":"Services"
        }
    ],
    "sg:phone":"+1 661 587 0533",
    "sg:postcode":"93312",
    "sg:province":"CA",
    "sg:tags":[
        "contractor"
    ],
    "wof:name":"Frost Heating & AC",
    "wof:placetype":"venue"
},
  "geometry": {"coordinates":[-119.104686,35.390825],"type":"Point"}
}