{
  "type": "Feature",
  "properties": {
    "addr:full":"56 Loma Media Rd Santa Barbara CA 93103",
    "addr:housenumber":"56",
    "addr:postcode":"93103",
    "addr:street":"Loma Media Rd",
    "iso:country":"US",
    "sg:address":"56 Loma Media Rd",
    "sg:city":"Santa Barbara",
    "sg:classifiers":[
        {
            "category":"Real Estate",
            "subcategory":"Real Estate Agent",
            "type":"Services"
        }
    ],
    "sg:phone":"+1 805 962 2240",
    "sg:postcode":"93103",
    "sg:province":"CA",
    "wof:name":"Optimo Property Svc",
    "wof:placetype":"venue"
},
  "geometry": {"coordinates":[-119.683616,34.436195],"type":"Point"}
}