{
  "type": "Feature",
  "properties": {
    "addr:full":"1425 Echo Park Ave Los Angeles CA 90026",
    "addr:housenumber":"1425",
    "addr:postcode":"90026",
    "addr:street":"Echo Park Ave",
    "iso:country":"US",
    "sg:address":"1425 Echo Park Ave",
    "sg:city":"Los Angeles",
    "sg:classifiers":[
        {
            "category":"Travel",
            "subcategory":"Travel Agent",
            "type":"Entertainment"
        }
    ],
    "sg:phone":"+1 213 250 8058",
    "sg:postcode":"90026",
    "sg:province":"CA",
    "sg:tags":[
        "agency",
        "bureau"
    ],
    "wof:name":"Skyline System Co",
    "wof:placetype":"venue"
},
  "geometry": {"coordinates":[-118.255576,34.079663],"type":"Point"}
}