{
  "type": "Feature",
  "properties": {
    "iso:country":"US",
    "sg:address":"1250 4th St",
    "sg:city":"Santa Monica",
    "sg:classifiers":[
        {
            "category":"Banks & Credit Unions",
            "subcategory":"Investment Brokerage",
            "type":"Services"
        }
    ],
    "sg:phone":"+1 310 434 9989",
    "sg:postcode":"90401",
    "sg:province":"CA",
    "wof:name":"AFA Management Partners",
    "wof:placetype":"venue"
},
  "geometry": {"coordinates":[-118.497527,34.018388],"type":"Point"}
}