{
  "type": "Feature",
  "properties": {
    "iso:country":"US",
    "sg:address":"209 Ave del Mar",
    "sg:city":"San Clemente",
    "sg:classifiers":[
        {
            "category":"Wholesale",
            "subcategory":"Groceries",
            "type":"Manufacturing & Wholesale Goods"
        }
    ],
    "sg:phone":"+1 949 498 2811",
    "sg:postcode":"92672",
    "sg:province":"CA",
    "sg:tags":[
        "general"
    ],
    "wof:name":"Hansen Marketing",
    "wof:placetype":"venue"
},
  "geometry": {"coordinates":[-117.61631,33.425093],"type":"Point"}
}