{
  "type": "Feature",
  "properties": {
    "addr:full":"451 West St Fort Bragg CA 95437",
    "addr:housenumber":"451",
    "addr:postcode":"95437",
    "addr:street":"West St",
    "iso:country":"US",
    "sg:address":"451 West St",
    "sg:city":"Fort Bragg",
    "sg:classifiers":[
        {
            "category":"Professional",
            "subcategory":"Detective & Security Services",
            "type":"Services"
        }
    ],
    "sg:phone":"+1 707 964 7194",
    "sg:postcode":"95437",
    "sg:province":"CA",
    "sg:tags":[
        "guard",
        "patrol"
    ],
    "wof:name":"Lee Geoble Security",
    "wof:placetype":"venue"
},
  "geometry": {"coordinates":[-123.80873,39.446117],"type":"Point"}
}