{
  "type": "Feature",
  "properties": {
    "iso:country":"US",
    "sg:address":"941 N Wilmington Blvd",
    "sg:city":"Wilmington",
    "sg:classifiers":[
        {
            "category":"Wholesale",
            "subcategory":"Motor Vehicles",
            "type":"Manufacturing & Wholesale Goods"
        }
    ],
    "sg:phone":"+1 310 830 2084",
    "sg:postcode":"90744",
    "sg:province":"CA",
    "wof:name":"Robert Bello",
    "wof:placetype":"venue"
},
  "geometry": {"coordinates":[-118.27444199999999,33.781638],"type":"Point"}
}