{
  "type": "Feature",
  "properties": {
    "iso:country":"US",
    "sg:address":"806 Vis del Monte",
    "sg:city":"Hemet",
    "sg:classifiers":[
        {
            "category":"Building & Trades",
            "subcategory":"Plumbing",
            "type":"Services"
        }
    ],
    "sg:phone":"+1 951 766 5579",
    "sg:postcode":"92543",
    "sg:province":"CA",
    "sg:tags":[
        "contractor"
    ],
    "wof:name":"Grangers Plumbing",
    "wof:placetype":"venue"
},
  "geometry": {"coordinates":[-116.963684,33.728071],"type":"Point"}
}