{
  "type": "Feature",
  "properties": {
    "iso:country":"US",
    "sg:address":"12215 Telegraph Rd Ste 112",
    "sg:city":"Santa Fe Springs",
    "sg:classifiers":[
        {
            "category":"Health Services",
            "subcategory":"Doctor",
            "type":"Services"
        }
    ],
    "sg:phone":"+1 562 864 2518",
    "sg:postcode":"90670",
    "sg:province":"CA",
    "wof:name":"SWANSON GERALD W MD MD",
    "wof:placetype":"venue"
},
  "geometry": {"coordinates":[-118.233387,33.942056],"type":"Point"}
}