{
  "type": "Feature",
  "properties": {
    "iso:country":"US",
    "sg:address":"2131 Westclif Dr Ste 110",
    "sg:city":"Newport Beach",
    "sg:classifiers":[
        {
            "category":"Health Services",
            "subcategory":"Clinic",
            "type":"Services"
        },
        {
            "category":"Personal",
            "subcategory":"Hair Removal",
            "type":"Services"
        }
    ],
    "sg:phone":"+1 949 631 2800",
    "sg:postcode":"92660",
    "sg:province":"CA",
    "sg:tags":[
        "loss",
        "medical",
        "laser",
        "weight",
        "spa"
    ],
    "sg:website":"www.newportbeachmedspa.com",
    "wof:name":"Newport Beach MedSpa",
    "wof:placetype":"venue"
},
  "geometry": {"coordinates":[-117.908438,33.627594],"type":"Point"}
}