{
  "type": "Feature",
  "properties": {
    "addr:full":"1031 S Broadway Los Angeles CA 90015",
    "addr:housenumber":"1031",
    "addr:postcode":"90015",
    "addr:street":"S Broadway",
    "iso:country":"US",
    "sg:address":"1031 S Broadway",
    "sg:city":"Los Angeles",
    "sg:classifiers":[
        {
            "category":"Professional",
            "subcategory":"Management & Consulting",
            "type":"Services"
        }
    ],
    "sg:phone":"+1 213 741 1867",
    "sg:postcode":"90015",
    "sg:province":"CA",
    "sg:tags":[
        "manufacture",
        "woman",
        "pro",
        "music",
        "child",
        "clothing"
    ],
    "wof:name":"Guerra Industries LLC",
    "wof:placetype":"venue"
},
  "geometry": {"coordinates":[-118.25862600000001,34.040068],"type":"Point"}
}