{
  "type": "Feature",
  "properties": {
    "addr:full":"1610 Solejar Dr La Habra Heights CA 90631",
    "addr:housenumber":"1610",
    "addr:postcode":"90631",
    "addr:street":"Solejar Dr",
    "iso:country":"US",
    "sg:address":"1610 Solejar Dr",
    "sg:city":"La Habra Heights",
    "sg:classifiers":[
        {
            "category":"Building & Trades",
            "subcategory":"Construction",
            "type":"Services"
        }
    ],
    "sg:phone":"+1 562 690 4304",
    "sg:postcode":"90631",
    "sg:province":"CA",
    "sg:tags":[
        "roofing",
        "contractor"
    ],
    "sg:website":"www.kabmgmt.com",
    "wof:name":"KAB Management",
    "wof:placetype":"venue"
},
  "geometry": {"coordinates":[-117.971636,33.954042],"type":"Point"}
}