{
  "type": "Feature",
  "properties": {
    "iso:country":"US",
    "sg:address":"1475 E del Amo Blvd",
    "sg:city":"Carson",
    "sg:classifiers":[
        {
            "category":"Professional",
            "type":"Services"
        }
    ],
    "sg:phone":"+1 310 639 7992",
    "sg:postcode":"90746",
    "sg:province":"CA",
    "wof:name":"Accu Back Inc",
    "wof:placetype":"venue"
},
  "geometry": {"coordinates":[-118.24538800000001,33.846817],"type":"Point"}
}