{
  "type": "Feature",
  "properties": {
    "iso:country":"US",
    "sg:address":"1318 Ross St",
    "sg:city":"Petaluma",
    "sg:classifiers":[
        {
            "category":"Professional",
            "subcategory":"Research",
            "type":"Services"
        }
    ],
    "sg:phone":"+1 707 775 2424",
    "sg:postcode":"94954",
    "sg:province":"CA",
    "wof:name":"Biochem Research",
    "wof:placetype":"venue"
},
  "geometry": {"coordinates":[-122.663878,38.26907],"type":"Point"}
}