{
  "type": "Feature",
  "properties": {
    "iso:country":"US",
    "sg:address":"4619 Lakeview Canyon Rd",
    "sg:city":"Westlake Village",
    "sg:classifiers":[
        {
            "category":"Shopping",
            "subcategory":"Gifts & Souvenirs",
            "type":"Retail Goods"
        }
    ],
    "sg:phone":"+1 818 707 2273",
    "sg:postcode":"91361",
    "sg:province":"CA",
    "sg:tags":[
        "cards",
        "trading",
        "memorabilia"
    ],
    "wof:name":"Baseball Crds-Mvie Cllectibles",
    "wof:placetype":"venue"
},
  "geometry": {"coordinates":[-118.819321,34.147901],"type":"Point"}
}