{
  "type": "Feature",
  "properties": {
    "addr:full":"1803 N Main St Los Angeles CA 90031",
    "addr:housenumber":"1803",
    "addr:postcode":"90031",
    "addr:street":"N Main St",
    "iso:country":"US",
    "sg:address":"1803 N Main St",
    "sg:city":"Los Angeles",
    "sg:classifiers":[
        {
            "category":"Food & Beverages",
            "subcategory":"Groceries & Convenience Stores",
            "type":"Retail Goods"
        }
    ],
    "sg:phone":"+1 323 225 8977",
    "sg:postcode":"90031",
    "sg:province":"CA",
    "sg:tags":[
        "grocer"
    ],
    "wof:name":"Lanza Brothers Market",
    "wof:placetype":"venue"
},
  "geometry": {"coordinates":[-118.221273,34.066729],"type":"Point"}
}