{
  "type": "Feature",
  "properties": {
    "addr:full":"455 S Lake Ave Pasadena CA 91101",
    "addr:housenumber":"455",
    "addr:postcode":"91101",
    "addr:street":"S Lake Ave",
    "iso:country":"US",
    "sg:address":"455 S Lake Ave",
    "sg:city":"Pasadena",
    "sg:classifiers":[
        {
            "category":"Manufacturing",
            "subcategory":"Apparel",
            "type":"Manufacturing & Wholesale Goods"
        }
    ],
    "sg:phone":"+1 626 578 1625",
    "sg:postcode":"91101",
    "sg:province":"CA",
    "sg:tags":[
        "accessory",
        "manufacturer"
    ],
    "wof:name":"Coldwater Creek Inc",
    "wof:placetype":"venue"
},
  "geometry": {"coordinates":[-118.13200399999999,34.137901],"type":"Point"}
}