{
  "type": "Feature",
  "properties": {
    "addr:full":"197 East Ave Chico CA 95926",
    "addr:housenumber":"197",
    "addr:postcode":"95926",
    "addr:street":"East Ave",
    "iso:country":"US",
    "sg:address":"197 East Ave",
    "sg:city":"Chico",
    "sg:classifiers":[
        {
            "category":"Personal",
            "type":"Services"
        }
    ],
    "sg:phone":"+1 530 521 0017",
    "sg:postcode":"95926",
    "sg:province":"CA",
    "sg:tags":[
        "therapist",
        "massage"
    ],
    "wof:name":"A Healing Knead",
    "wof:placetype":"venue"
},
  "geometry": {"coordinates":[-121.85898299999999,39.757987],"type":"Point"}
}