{
  "type": "Feature",
  "properties": {
    "addr:full":"3944 Center St Piru CA 93040",
    "addr:housenumber":"3944",
    "addr:postcode":"93040",
    "addr:street":"Center St",
    "iso:country":"US",
    "sg:address":"3944 Center St",
    "sg:city":"Piru",
    "sg:classifiers":[
        {
            "category":"Restaurant",
            "type":"Food & Drink"
        }
    ],
    "sg:phone":"+1 805 521 0694",
    "sg:postcode":"93040",
    "sg:province":"CA",
    "wof:name":"Poncho's Place",
    "wof:placetype":"venue"
},
  "geometry": {"coordinates":[-118.795593,34.415301],"type":"Point"}
}