{
  "type": "Feature",
  "properties": {
    "iso:country":"US",
    "sg:address":"26 Jordans Pl",
    "sg:city":"Chico",
    "sg:classifiers":[
        {
            "category":"Retail",
            "subcategory":"Auto Repair",
            "type":"Services"
        }
    ],
    "sg:phone":"+1 530 343 7071",
    "sg:postcode":"95973",
    "sg:province":"CA",
    "sg:tags":[
        "machine",
        "automobile",
        "shop"
    ],
    "wof:name":"B & M Automotive Machine Shop",
    "wof:placetype":"venue"
},
  "geometry": {"coordinates":[-121.890734,39.74667],"type":"Point"}
}