{
  "type": "Feature",
  "properties": {
    "addr:full":"739 S Workman St San Fernando CA 91340",
    "addr:housenumber":"739",
    "addr:postcode":"91340",
    "addr:street":"S Workman St",
    "iso:country":"US",
    "sg:address":"739 S Workman St",
    "sg:city":"San Fernando",
    "sg:classifiers":[
        {
            "category":"Professional",
            "subcategory":"Business Services",
            "type":"Services"
        }
    ],
    "sg:phone":"+1 818 898 7494",
    "sg:postcode":"91340",
    "sg:province":"CA",
    "wof:name":"C & C Legal Svc",
    "wof:placetype":"venue"
},
  "geometry": {"coordinates":[-118.450903,34.28267],"type":"Point"}
}