{
  "type": "Feature",
  "properties": {
    "addr:full":"1701 S Capitol Ave San Jose CA 95127",
    "addr:housenumber":"1701",
    "addr:postcode":"95127",
    "addr:street":"S Capitol Ave",
    "iso:country":"US",
    "sg:address":"1701 S Capitol Ave",
    "sg:city":"San Jose",
    "sg:classifiers":[
        {
            "category":"Professional",
            "type":"Services"
        }
    ],
    "sg:phone":"+1 408 729 1746",
    "sg:postcode":"95127",
    "sg:province":"CA",
    "wof:name":"Ruben Aceves Iniguez Et Al Ptr",
    "wof:placetype":"venue"
},
  "geometry": {"coordinates":[-121.82124399999999,37.342872],"type":"Point"}
}