{
  "type": "Feature",
  "properties": {
    "addr:full":"8243 La Mesa Blvd La Mesa CA 91941",
    "addr:housenumber":"8243",
    "addr:postcode":"91941",
    "addr:street":"La Mesa Blvd",
    "iso:country":"US",
    "sg:address":"8243 La Mesa Blvd",
    "sg:city":"La Mesa",
    "sg:classifiers":[
        {
            "category":"Shopping",
            "subcategory":"Used Merchandise",
            "type":"Retail Goods"
        }
    ],
    "sg:phone":"+1 619 698 2392",
    "sg:postcode":"91941",
    "sg:province":"CA",
    "sg:tags":[
        "vintage",
        "consignment"
    ],
    "wof:name":"Act II",
    "wof:placetype":"venue"
},
  "geometry": {"coordinates":[-117.021004,32.7644],"type":"Point"}
}