{
  "type": "Feature",
  "properties": {
    "iso:country":"US",
    "sg:address":"3301 E 12th St Ste 271",
    "sg:city":"Oakland",
    "sg:classifiers":[
        {
            "category":"Education",
            "subcategory":"Library",
            "type":"Public Place"
        }
    ],
    "sg:phone":"+1 510 535 5620",
    "sg:postcode":"94601",
    "sg:province":"CA",
    "sg:website":"www.oaklandlibrary.org/Branches/...",
    "wof:name":"C?sar E. Ch?vez Branch Library",
    "wof:placetype":"venue"
},
  "geometry": {"coordinates":[-122.224564,37.775262],"type":"Point"}
}