{
  "type": "Feature",
  "properties": {
    "iso:country":"US",
    "sg:address":"3233 N Cedar Ave",
    "sg:city":"Fresno",
    "sg:classifiers":[
        {
            "category":"Shopping",
            "subcategory":"Department Store",
            "type":"Retail Goods"
        },
        {
            "category":"Shopping",
            "subcategory":"Discount & Variety Stores",
            "type":"Retail Goods"
        },
        {
            "category":"Shopping",
            "type":"Retail Goods"
        }
    ],
    "sg:phone":"+1 559 840 2605",
    "sg:postcode":"93726",
    "sg:province":"CA",
    "sg:tags":[
        "merchandise"
    ],
    "wof:name":"Fresno Discount Center",
    "wof:placetype":"venue"
},
  "geometry": {"coordinates":[-119.75447,36.77997],"type":"Point"}
}