{
  "type": "Feature",
  "properties": {
    "addr:full":"242 Hale St San Francisco CA 94134",
    "addr:housenumber":"242",
    "addr:postcode":"94134",
    "addr:street":"Hale St",
    "iso:country":"US",
    "sg:address":"242 Hale St",
    "sg:city":"San Francisco",
    "sg:classifiers":[
        {
            "category":"Retail",
            "subcategory":"Laundry & Dry Cleaning",
            "type":"Services"
        }
    ],
    "sg:phone":"+1 408 354 1667",
    "sg:postcode":"94134",
    "sg:province":"CA",
    "wof:name":"1-800-DryClean",
    "wof:placetype":"venue"
},
  "geometry": {"coordinates":[-122.409943,37.731931],"type":"Point"}
}