{
  "type": "Feature",
  "properties": {
    "addr:full":"6363 Christie Ave Emeryville CA 94608",
    "addr:housenumber":"6363",
    "addr:postcode":"94608",
    "addr:street":"Christie Ave",
    "iso:country":"US",
    "sg:address":"6363 Christie Ave",
    "sg:city":"Emeryville",
    "sg:classifiers":[
        {
            "category":"Shopping",
            "type":"Retail Goods"
        }
    ],
    "sg:phone":"+1 415 391 3036",
    "sg:postcode":"94608",
    "sg:province":"CA",
    "sg:tags":[
        "wedding",
        "supply"
    ],
    "sg:website":"www.soundcraftproductions.com",
    "wof:name":"A-Sound Craft Productions",
    "wof:placetype":"venue"
},
  "geometry": {"coordinates":[-122.294972,37.839625],"type":"Point"}
}