{
  "type": "Feature",
  "properties": {
    "addr:full":"7752 North Ave Lemon Grove CA 91945",
    "addr:housenumber":"7752",
    "addr:postcode":"91945",
    "addr:street":"North Ave",
    "iso:country":"US",
    "sg:address":"7752 North Ave",
    "sg:city":"Lemon Grove",
    "sg:classifiers":[
        {
            "category":"Home & Garden",
            "subcategory":"Household Appliances",
            "type":"Retail Goods"
        }
    ],
    "sg:phone":"+1 619 463 9596",
    "sg:postcode":"91945",
    "sg:province":"CA",
    "sg:tags":[
        "repair"
    ],
    "wof:name":"Anthony's Appliances Sales",
    "wof:placetype":"venue"
},
  "geometry": {"coordinates":[-117.031412,32.74461],"type":"Point"}
}