{
  "type": "Feature",
  "properties": {
    "addr:full":"2941 Main St Santa Monica CA 90405",
    "addr:housenumber":"2941",
    "addr:postcode":"90405",
    "addr:street":"Main St",
    "iso:country":"US",
    "sg:address":"2941 Main St",
    "sg:city":"Santa Monica",
    "sg:classifiers":[
        {
            "category":"Bars & Pubs",
            "type":"Food & Drink"
        }
    ],
    "sg:phone":"+1 310 396 4725",
    "sg:postcode":"90405",
    "sg:province":"CA",
    "wof:name":"O'Brien's Pub",
    "wof:placetype":"venue"
},
  "geometry": {"coordinates":[-118.48014000000001,33.99871],"type":"Point"}
}