{
  "type": "Feature",
  "properties": {
    "iso:country":"US",
    "sg:address":"1133 W Sacramento Ave",
    "sg:city":"Chico",
    "sg:classifiers":[
        {
            "category":"Real Estate",
            "subcategory":"Real Estate Operator",
            "type":"Services"
        }
    ],
    "sg:phone":"+1 530 896 0969",
    "sg:postcode":"95926",
    "sg:province":"CA",
    "sg:tags":[
        "building",
        "apartment"
    ],
    "wof:name":"Nord West Apartments",
    "wof:placetype":"venue"
},
  "geometry": {"coordinates":[-121.86202299999999,39.730985],"type":"Point"}
}