{
  "type": "Feature",
  "properties": {
    "addr:full":"28465 Old Town Front St # 221 Temecula CA 92590",
    "addr:housenumber":"28465",
    "addr:postcode":"92590",
    "addr:street":"Old Town Front St # 221",
    "iso:country":"US",
    "sg:address":"28465 Old Town Front St # 221",
    "sg:city":"Temecula",
    "sg:classifiers":[
        {
            "category":"Insurance",
            "subcategory":"Hazard Insurance",
            "type":"Services"
        }
    ],
    "sg:phone":"+1 951 694 8070",
    "sg:postcode":"92590",
    "sg:province":"CA",
    "wof:name":"Creative Benefit Solutions",
    "wof:placetype":"venue"
},
  "geometry": {"coordinates":[-117.15137799999999,33.495488],"type":"Point"}
}