{
  "type": "Feature",
  "properties": {
    "iso:country":"US",
    "sg:address":"4308 F St",
    "sg:city":"Sacramento",
    "sg:classifiers":[
        {
            "category":"Restaurant",
            "type":"Food & Drink"
        }
    ],
    "sg:phone":"+1 916 737 1499",
    "sg:postcode":"95819",
    "sg:province":"CA",
    "sg:tags":[
        "pizza"
    ],
    "wof:name":"Domino Events",
    "wof:placetype":"venue"
},
  "geometry": {"coordinates":[-121.44733600000001,38.573176],"type":"Point"}
}