{
  "type": "Feature",
  "properties": {
    "addr:full":"16813 S Broadway Street Gardena CA 90248",
    "addr:housenumber":"16813",
    "addr:postcode":"90248",
    "addr:street":"S Broadway Street",
    "iso:country":"US",
    "sg:address":"16813 S Broadway Street",
    "sg:city":"Gardena",
    "sg:classifiers":[
        {
            "category":"Building & Trades",
            "subcategory":"Construction",
            "type":"Services"
        }
    ],
    "sg:phone":"+1 323 759 1153",
    "sg:postcode":"90248",
    "sg:province":"CA",
    "sg:tags":[
        "interior",
        "design"
    ],
    "wof:name":"American Shutter Company",
    "wof:placetype":"venue"
},
  "geometry": {"coordinates":[-118.277967,33.878519],"type":"Point"}
}