{
  "type": "Feature",
  "properties": {
    "iso:country":"US",
    "sg:address":"1929 Pontius Ave",
    "sg:city":"Los Angeles",
    "sg:classifiers":[
        {
            "category":"Freight",
            "type":"Transportation"
        }
    ],
    "sg:phone":"+1 310 231 6012",
    "sg:postcode":"90025",
    "sg:province":"CA",
    "sg:tags":[
        "operator",
        "local",
        "courier",
        "trucking"
    ],
    "wof:name":"National Delivery Service Inc",
    "wof:placetype":"venue"
},
  "geometry": {"coordinates":[-118.441226,34.043058],"type":"Point"}
}