{
  "type": "Feature",
  "properties": {
    "iso:country":"US",
    "sg:address":"2238 W Beverly Blvd",
    "sg:city":"Montebello",
    "sg:classifiers":[
        {
            "category":"Personal",
            "subcategory":"Beauty Salon",
            "type":"Services"
        }
    ],
    "sg:phone":"+1 323 722 5009",
    "sg:postcode":"90640",
    "sg:province":"CA",
    "wof:name":"Future Hair",
    "wof:placetype":"venue"
},
  "geometry": {"coordinates":[-118.12433299999999,34.02106],"type":"Point"}
}