{
  "type": "Feature",
  "properties": {
    "addr:full":"1443 N Highland Ave Hollywood CA 90028",
    "addr:housenumber":"1443",
    "addr:postcode":"90028",
    "addr:street":"N Highland Ave",
    "iso:country":"US",
    "sg:address":"1443 N Highland Ave",
    "sg:city":"Hollywood",
    "sg:classifiers":[
        {
            "category":"Shopping",
            "subcategory":"Clothing, Apparel, & Fashions",
            "type":"Retail Goods"
        },
        {
            "category":"Arts & Performance",
            "subcategory":"Art Gallery",
            "type":"Entertainment"
        },
        {
            "category":"Arts & Performance",
            "subcategory":"Music",
            "type":"Entertainment"
        }
    ],
    "sg:postcode":"90028",
    "sg:province":"CA",
    "sg:tags":[
        "venue"
    ],
    "wof:name":"Records Ad Nauseam",
    "wof:placetype":"venue"
},
  "geometry": {"coordinates":[-118.338678,34.09734],"type":"Point"}
}