{
  "type": "Feature",
  "properties": {
    "iso:country":"US",
    "sg:address":"727 Sutter St",
    "sg:city":"Folsom",
    "sg:classifiers":[
        {
            "category":"Wholesale",
            "subcategory":"Groceries",
            "type":"Manufacturing & Wholesale Goods"
        }
    ],
    "sg:phone":"+1 916 351 5844",
    "sg:postcode":"95630",
    "sg:province":"CA",
    "sg:tags":[
        "tea"
    ],
    "wof:name":"Partea Time",
    "wof:placetype":"venue"
},
  "geometry": {"coordinates":[-121.177411,38.677147],"type":"Point"}
}