{
  "type": "Feature",
  "properties": {
    "addr:full":"5804 Soto St Huntington Park CA 90255",
    "addr:housenumber":"5804",
    "addr:postcode":"90255",
    "addr:street":"Soto St;Park",
    "iso:country":"US",
    "sg:address":"5804 Soto St",
    "sg:city":"Huntington Park",
    "sg:classifiers":[
        {
            "category":"Wholesale",
            "subcategory":"Non-durable Goods",
            "type":"Manufacturing & Wholesale Goods"
        }
    ],
    "sg:phone":"+1 323 587 2300",
    "sg:postcode":"90255",
    "sg:province":"CA",
    "wof:name":"International Wholesale",
    "wof:placetype":"venue"
},
  "geometry": {"coordinates":[-118.219263,33.989742],"type":"Point"}
}