{
  "type": "Feature",
  "properties": {
    "iso:country":"US",
    "sg:address":"451 Airport Rd",
    "sg:city":"Novato",
    "sg:classifiers":[
        {
            "category":"Education",
            "subcategory":"Special Training",
            "type":"Public Place"
        }
    ],
    "sg:phone":"+1 415 898 7600",
    "sg:postcode":"94945",
    "sg:province":"CA",
    "sg:tags":[
        "aircraft",
        "flight",
        "school"
    ],
    "wof:name":"John Ward Flight Training",
    "wof:placetype":"venue"
},
  "geometry": {"coordinates":[-122.559498,38.140927],"type":"Point"}
}