{
  "type": "Feature",
  "properties": {
    "iso:country":"US",
    "sg:address":"620 W Leadora Ave",
    "sg:city":"Glendora",
    "sg:classifiers":[
        {
            "category":"Building & Trades",
            "subcategory":"Construction",
            "type":"Services"
        }
    ],
    "sg:phone":"+1 626 852 0262",
    "sg:postcode":"91741",
    "sg:province":"CA",
    "sg:tags":[
        "contractor"
    ],
    "wof:name":"Zuro Metz Building Contractors",
    "wof:placetype":"venue"
},
  "geometry": {"coordinates":[-117.87282,34.143271],"type":"Point"}
}