{
  "type": "Feature",
  "properties": {
    "iso:country":"US",
    "sg:address":"1201 Lincoln Ave",
    "sg:city":"Alameda",
    "sg:classifiers":[
        {
            "category":"Organizations",
            "subcategory":"Religious Organization",
            "type":"Services"
        }
    ],
    "sg:phone":"+1 510 522 2930",
    "sg:postcode":"94501",
    "sg:province":"CA",
    "sg:tags":[
        "church"
    ],
    "wof:name":"Christian Science Reading Room",
    "wof:placetype":"venue"
},
  "geometry": {"coordinates":[-122.263307,37.774715],"type":"Point"}
}