{
  "type": "Feature",
  "properties": {
    "addr:full":"673 S Cooley Dr W Colton CA 92324",
    "addr:housenumber":"673",
    "addr:postcode":"92324",
    "addr:street":"S Cooley Dr W",
    "iso:country":"US",
    "sg:address":"673 S Cooley Dr W",
    "sg:city":"Colton",
    "sg:classifiers":[
        {
            "category":"Wholesale",
            "subcategory":"Furniture",
            "type":"Manufacturing & Wholesale Goods"
        }
    ],
    "sg:phone":"+1 909 423 0300",
    "sg:postcode":"92324",
    "sg:province":"CA",
    "wof:name":"Furniture Guys",
    "wof:placetype":"venue"
},
  "geometry": {"coordinates":[-117.30422,34.059911],"type":"Point"}
}