{
  "type": "Feature",
  "properties": {
    "addr:full":"456 Elena St Apt 40 Morro Bay CA 93442",
    "addr:housenumber":"456;40",
    "addr:postcode":"93442",
    "addr:street":"Elena St Apt",
    "iso:country":"US",
    "sg:address":"456 Elena St Apt 40",
    "sg:city":"Morro Bay",
    "sg:classifiers":[
        {
            "category":"Real Estate",
            "subcategory":"Real Estate Operator",
            "type":"Services"
        }
    ],
    "sg:phone":"+1 805 772 1921",
    "sg:postcode":"93442",
    "sg:province":"CA",
    "sg:tags":[
        "apartment"
    ],
    "wof:name":"Ocean View Manor Apartments",
    "wof:placetype":"venue"
},
  "geometry": {"coordinates":[-120.85700199999999,35.3909],"type":"Point"}
}