{
  "type": "Feature",
  "properties": {
    "addr:full":"8920 Kenamar Dr San Diego CA 92121",
    "addr:housenumber":"8920",
    "addr:postcode":"92121",
    "addr:street":"Kenamar Dr",
    "iso:country":"US",
    "sg:address":"8920 Kenamar Dr",
    "sg:city":"San Diego",
    "sg:classifiers":[
        {
            "category":"Professional",
            "subcategory":"Business Services",
            "type":"Services"
        }
    ],
    "sg:phone":"+1 858 578 7757",
    "sg:postcode":"92121",
    "sg:province":"CA",
    "sg:tags":[
        "fund",
        "promotion",
        "raising"
    ],
    "wof:name":"Promotion Products",
    "wof:placetype":"venue"
},
  "geometry": {"coordinates":[-117.155629,32.885322],"type":"Point"}
}