{
  "type": "Feature",
  "properties": {
    "addr:full":"2440 Taraval St San Francisco CA 94116",
    "addr:housenumber":"2440",
    "addr:postcode":"94116",
    "addr:street":"Taraval St",
    "iso:country":"US",
    "sg:address":"2440 Taraval St",
    "sg:city":"San Francisco",
    "sg:classifiers":[
        {
            "category":"Professional",
            "subcategory":"Accounting & Tax Preparation",
            "type":"Services"
        }
    ],
    "sg:phone":"+1 415 661 5900",
    "sg:postcode":"94116",
    "sg:province":"CA",
    "sg:tags":[
        "return",
        "filing"
    ],
    "wof:name":"Stone & Mc Laughlin",
    "wof:placetype":"venue"
},
  "geometry": {"coordinates":[-122.492496,37.742389],"type":"Point"}
}