{
  "type": "Feature",
  "properties": {
    "addr:full":"534 Broadway St Chico CA 95928",
    "addr:housenumber":"534",
    "addr:postcode":"95928",
    "addr:street":"Broadway St",
    "iso:country":"US",
    "sg:address":"534 Broadway St",
    "sg:city":"Chico",
    "sg:classifiers":[
        {
            "category":"Shopping",
            "subcategory":"Used Merchandise",
            "type":"Retail Goods"
        }
    ],
    "sg:phone":"+1 530 345 4222",
    "sg:postcode":"95928",
    "sg:province":"CA",
    "sg:tags":[
        "pawnbroker"
    ],
    "wof:name":"Broadway Music Ctr",
    "wof:placetype":"venue"
},
  "geometry": {"coordinates":[-121.83843899999999,39.727181],"type":"Point"}
}