{
  "type": "Feature",
  "properties": {
    "iso:country":"US",
    "sg:address":"8038 Geary Blvd",
    "sg:city":"San Francisco",
    "sg:classifiers":[
        {
            "category":"Professional",
            "subcategory":"Business Services",
            "type":"Services"
        }
    ],
    "sg:phone":"+1 415 386 0348",
    "sg:postcode":"94121",
    "sg:province":"CA",
    "sg:tags":[
        "paging",
        "answering"
    ],
    "sg:website":"www.message.com",
    "wof:name":"Business Message Ctr",
    "wof:placetype":"venue"
},
  "geometry": {"coordinates":[-122.50584,37.779205],"type":"Point"}
}