{
  "type": "Feature",
  "properties": {
    "addr:full":"21026 Parkridge Dr Walnut CA 91789",
    "addr:housenumber":"21026",
    "addr:postcode":"91789",
    "addr:street":"Parkridge Dr",
    "iso:country":"US",
    "sg:address":"21026 Parkridge Dr",
    "sg:city":"Walnut",
    "sg:classifiers":[
        {
            "category":"Cinema",
            "subcategory":"Movie Rental",
            "type":"Entertainment"
        }
    ],
    "sg:phone":"+1 626 917 9833",
    "sg:postcode":"91789",
    "sg:province":"CA",
    "sg:tags":[
        "leasing",
        "video",
        "disc",
        "tape"
    ],
    "wof:name":"Budget Video Plus",
    "wof:placetype":"venue"
},
  "geometry": {"coordinates":[-117.84504099999999,34.018856],"type":"Point"}
}