{
  "type": "Feature",
  "properties": {
    "addr:full":"1130 Fremont Blvd Seaside CA 93955",
    "addr:housenumber":"1130",
    "addr:postcode":"93955",
    "addr:street":"Fremont Blvd",
    "iso:country":"US",
    "sg:address":"1130 Fremont Blvd",
    "sg:city":"Seaside",
    "sg:classifiers":[
        {
            "category":"Building & Trades",
            "subcategory":"Cleaning & Sanitation",
            "type":"Services"
        }
    ],
    "sg:phone":"+1 831 224 2677",
    "sg:postcode":"93955",
    "sg:province":"CA",
    "sg:tags":[
        "house"
    ],
    "wof:name":"Dirty Blinds Com",
    "wof:placetype":"venue"
},
  "geometry": {"coordinates":[-121.84921900000001,36.601277],"type":"Point"}
}