{
  "type": "Feature",
  "properties": {
    "addr:full":"14623 Victory Blvd Van Nuys CA 91411",
    "addr:housenumber":"14623",
    "addr:postcode":"91411",
    "addr:street":"Victory Blvd",
    "iso:country":"US",
    "sg:address":"14623 Victory Blvd",
    "sg:city":"Van Nuys",
    "sg:classifiers":[
        {
            "category":"Insurance",
            "subcategory":"Insurance Agent",
            "type":"Services"
        }
    ],
    "sg:phone":"+1 818 780 1515",
    "sg:postcode":"91411",
    "sg:province":"CA",
    "wof:name":"Echo Insurance Svc",
    "wof:placetype":"venue"
},
  "geometry": {"coordinates":[-118.452676,34.186733],"type":"Point"}
}