{
  "type": "Feature",
  "properties": {
    "addr:full":"906 N Harper Ave Los Angeles CA 90046",
    "addr:housenumber":"906",
    "addr:postcode":"90046",
    "addr:street":"N Harper Ave",
    "iso:country":"US",
    "sg:address":"906 N Harper Ave",
    "sg:city":"Los Angeles",
    "sg:classifiers":[
        {
            "category":"Travel",
            "subcategory":"Travel Agent",
            "type":"Entertainment"
        }
    ],
    "sg:phone":"+1 323 656 0743",
    "sg:postcode":"90046",
    "sg:province":"CA",
    "sg:tags":[
        "agency"
    ],
    "wof:name":"Embassy Travel Inc",
    "wof:placetype":"venue"
},
  "geometry": {"coordinates":[-118.369011,34.088584],"type":"Point"}
}