{
  "type": "Feature",
  "properties": {
    "addr:full":"515 Canyon del Rey Blvd Del Rey Oaks CA 93940",
    "addr:housenumber":"515",
    "addr:postcode":"93940",
    "addr:street":"Canyon Del Rey Blvd Del Rey Oaks",
    "iso:country":"US",
    "sg:address":"515 Canyon del Rey Blvd",
    "sg:city":"Del Rey Oaks",
    "sg:classifiers":[
        {
            "category":"Real Estate",
            "subcategory":"Real Estate Agent",
            "type":"Services"
        }
    ],
    "sg:phone":"+1 831 393 2402",
    "sg:postcode":"93940",
    "sg:province":"CA",
    "sg:tags":[
        "management"
    ],
    "wof:name":"Oaks Of Del Ray Hoa",
    "wof:placetype":"venue"
},
  "geometry": {"coordinates":[-121.83183099999999,36.588923],"type":"Point"}
}