{
  "type": "Feature",
  "properties": {
    "addr:full":"331 Carrera Dr Mill Valley CA 94941",
    "addr:housenumber":"331",
    "addr:postcode":"94941",
    "addr:street":"Carrera Dr",
    "iso:country":"US",
    "sg:address":"331 Carrera Dr",
    "sg:city":"Mill Valley",
    "sg:classifiers":[
        {
            "category":"Manufacturing",
            "subcategory":"Printing",
            "type":"Manufacturing & Wholesale Goods"
        }
    ],
    "sg:phone":"+1 415 381 3739",
    "sg:postcode":"94941",
    "sg:province":"CA",
    "sg:tags":[
        "publishing"
    ],
    "wof:name":"Tritone",
    "wof:placetype":"venue"
},
  "geometry": {"coordinates":[-122.529084,37.869782],"type":"Point"}
}