{
  "type": "Feature",
  "properties": {
    "addr:full":"26141 Marguerite Pkwy Ste A Mission Viejo CA 92692",
    "addr:housenumber":"26141",
    "addr:postcode":"92692",
    "addr:street":"Marguerite Pkwy Ste A",
    "iso:country":"US",
    "sg:address":"26141 Marguerite Pkwy Ste A",
    "sg:city":"Mission Viejo",
    "sg:classifiers":[
        {
            "category":"Building & Trades",
            "subcategory":"Construction",
            "type":"Services"
        }
    ],
    "sg:phone":"+1 949 362 0756",
    "sg:postcode":"92692",
    "sg:province":"CA",
    "sg:tags":[
        "contractor"
    ],
    "wof:name":"Sauers Construction",
    "wof:placetype":"venue"
},
  "geometry": {"coordinates":[-117.659282,33.58275],"type":"Point"}
}