{
  "type": "Feature",
  "properties": {
    "addr:full":"26886 Cll Hermosa Capistrano Beach CA 92624",
    "addr:postcode":"26886;92624",
    "addr:street":"Cll Hermosa",
    "iso:country":"US",
    "sg:address":"26886 Cll Hermosa",
    "sg:city":"Capistrano Beach",
    "sg:classifiers":[
        {
            "category":"Retail",
            "subcategory":"Animal Services",
            "type":"Services"
        }
    ],
    "sg:phone":"+1 949 496 2968",
    "sg:postcode":"92624",
    "sg:province":"CA",
    "wof:name":"Estrella Pet Grooming",
    "wof:placetype":"venue"
},
  "geometry": {"coordinates":[-117.661112,33.454305],"type":"Point"}
}