{
  "type": "Feature",
  "properties": {
    "addr:full":"830 E Dunne Ave Morgan Hill CA 95037",
    "addr:housenumber":"830",
    "addr:postcode":"95037",
    "addr:street":"E Dunne Ave",
    "iso:country":"US",
    "sg:address":"830 E Dunne Ave",
    "sg:city":"Morgan Hill",
    "sg:classifiers":[
        {
            "category":"Restaurant",
            "type":"Food & Drink"
        }
    ],
    "sg:menulink":"http://www.allmenus.com/ca/san-jose/171912-burger-king/menu/",
    "sg:phone":"+1 408 776 9221",
    "sg:postcode":"95037",
    "sg:province":"CA",
    "sg:tags":[
        "burger",
        "american"
    ],
    "wof:name":"Burger King",
    "wof:placetype":"venue"
},
  "geometry": {"coordinates":[-121.63730700000001,37.129132],"type":"Point"}
}