{
  "type": "Feature",
  "properties": {
    "iso:country":"US",
    "sg:address":"410 S San Gabriel Blvd",
    "sg:city":"San Gabriel",
    "sg:classifiers":[
        {
            "category":"Insurance",
            "subcategory":"Insurance Agent",
            "type":"Services"
        }
    ],
    "sg:phone":"+1 626 291 5110",
    "sg:postcode":"91776",
    "sg:province":"CA",
    "wof:name":"Allstate",
    "wof:placetype":"venue"
},
  "geometry": {"coordinates":[-118.090839,34.097018],"type":"Point"}
}