{
  "type": "Feature",
  "properties": {
    "addr:full":"2824 Red Pine Ct Pleasanton CA 94588",
    "addr:housenumber":"2824",
    "addr:postcode":"94588",
    "addr:street":"Red Pine Ct",
    "iso:country":"US",
    "sg:address":"2824 Red Pine Ct",
    "sg:city":"Pleasanton",
    "sg:classifiers":[
        {
            "category":"Building & Trades",
            "subcategory":"Landscaping Services",
            "type":"Services"
        }
    ],
    "sg:phone":"+1 925 580 1913",
    "sg:postcode":"94588",
    "sg:province":"CA",
    "sg:tags":[
        "landscape",
        "contractor"
    ],
    "wof:name":"Pacific Crest Landscape",
    "wof:placetype":"venue"
},
  "geometry": {"coordinates":[-121.862279,37.692759],"type":"Point"}
}