{
  "type": "Feature",
  "properties": {
    "iso:country":"US",
    "sg:address":"475 Douglas Ave",
    "sg:city":"Oakland",
    "sg:classifiers":[
        {
            "category":"Building & Trades",
            "subcategory":"Construction",
            "type":"Services"
        }
    ],
    "sg:phone":"+1 510 430 0226",
    "sg:postcode":"94603",
    "sg:province":"CA",
    "sg:tags":[
        "contractor"
    ],
    "wof:name":"ABC Home Improvement",
    "wof:placetype":"venue"
},
  "geometry": {"coordinates":[-122.18209299999999,37.730624],"type":"Point"}
}