{
  "type": "Feature",
  "properties": {
    "iso:country":"US",
    "sg:address":"20422 Beach Blvd",
    "sg:city":"Huntington Beach",
    "sg:classifiers":[
        {
            "category":"Professional",
            "subcategory":"Engineering",
            "type":"Services"
        }
    ],
    "sg:phone":"+1 714 960 7633",
    "sg:postcode":"92648",
    "sg:province":"CA",
    "sg:tags":[
        "engineer"
    ],
    "wof:name":"Envirocon Consulting Engineers",
    "wof:placetype":"venue"
},
  "geometry": {"coordinates":[-117.988286,33.665898],"type":"Point"}
}