{
  "type": "Feature",
  "properties": {
    "addr:full":"505 Shatto Pl Ste 302 Los Angeles CA 90020",
    "addr:housenumber":"505",
    "addr:postcode":"90020",
    "addr:street":"Shatto Pl Ste 302",
    "iso:country":"US",
    "sg:address":"505 Shatto Pl Ste 302",
    "sg:city":"Los Angeles",
    "sg:classifiers":[
        {
            "category":"Education",
            "subcategory":"University",
            "type":"Public Place"
        }
    ],
    "sg:phone":"+1 213 383 8040",
    "sg:postcode":"90020",
    "sg:province":"CA",
    "sg:tags":[
        "college"
    ],
    "wof:name":"Cas Academy",
    "wof:placetype":"venue"
},
  "geometry": {"coordinates":[-118.28999399999999,34.065022],"type":"Point"}
}