{
  "type": "Feature",
  "properties": {
    "iso:country":"US",
    "sg:address":"1641 Mountain View Ave",
    "sg:city":"Oxnard",
    "sg:classifiers":[
        {
            "category":"Wholesale",
            "subcategory":"Stationery",
            "type":"Manufacturing & Wholesale Goods"
        }
    ],
    "sg:phone":"+1 805 487 7529",
    "sg:postcode":"93030",
    "sg:province":"CA",
    "sg:tags":[
        "paper",
        "industrial",
        "supply"
    ],
    "sg:website":"www.calpinecontainers.com",
    "wof:name":"Calpine Containers Inc",
    "wof:placetype":"venue"
},
  "geometry": {"coordinates":[-119.161013,34.193514],"type":"Point"}
}