{
  "type": "Feature",
  "properties": {
    "addr:full":"8420 Wilshire Blvd Beverly Hills CA 90211",
    "addr:housenumber":"8420",
    "addr:postcode":"90211",
    "addr:street":"Wilshire Blvd",
    "iso:country":"US",
    "sg:address":"8420 Wilshire Blvd",
    "sg:city":"Beverly Hills",
    "sg:classifiers":[
        {
            "category":"Personal",
            "subcategory":"Skin Care",
            "type":"Services"
        }
    ],
    "sg:phone":"+1 310 728 0293",
    "sg:postcode":"90211",
    "sg:province":"CA",
    "wof:name":"Cindy's Skin Care & Spa",
    "wof:placetype":"venue"
},
  "geometry": {"coordinates":[-118.37441800000001,34.064801],"type":"Point"}
}