{
  "type": "Feature",
  "properties": {
    "addr:full":"20906 Higgins Ct Torrance CA 90501",
    "addr:housenumber":"20906",
    "addr:postcode":"90501",
    "addr:street":"Higgins Ct",
    "iso:country":"US",
    "sg:address":"20906 Higgins Ct",
    "sg:city":"Torrance",
    "sg:classifiers":[
        {
            "category":"Shopping",
            "subcategory":"Pharmacy",
            "type":"Retail Goods"
        }
    ],
    "sg:phone":"+1 310 212 5733",
    "sg:postcode":"90501",
    "sg:province":"CA",
    "sg:tags":[
        "sundries",
        "drug"
    ],
    "wof:name":"Valley Western Pharmacy Svc",
    "wof:placetype":"venue"
},
  "geometry": {"coordinates":[-118.310338,33.839994],"type":"Point"}
}