{
  "type": "Feature",
  "properties": {
    "addr:full":"8417 Fontana St Downey CA 90241",
    "addr:housenumber":"8417",
    "addr:postcode":"90241",
    "addr:street":"Fontana St",
    "iso:country":"US",
    "sg:address":"8417 Fontana St",
    "sg:city":"Downey",
    "sg:classifiers":[
        {
            "category":"Building & Trades",
            "subcategory":"Cleaning & Sanitation",
            "type":"Services"
        }
    ],
    "sg:phone":"+1 562 861 5041",
    "sg:postcode":"90241",
    "sg:province":"CA",
    "sg:tags":[
        "carpet"
    ],
    "sg:website":"www.aaronsinteriorcleaning.com",
    "wof:name":"Aaron's Interior Cleaning",
    "wof:placetype":"venue"
},
  "geometry": {"coordinates":[-118.136011,33.931716],"type":"Point"}
}