{
  "type": "Feature",
  "properties": {
    "addr:full":"13254 Woodruff Ave Downey CA 90242",
    "addr:housenumber":"13254",
    "addr:postcode":"90242",
    "addr:street":"Woodruff Ave",
    "iso:country":"US",
    "sg:address":"13254 Woodruff Ave",
    "sg:city":"Downey",
    "sg:classifiers":[
        {
            "category":"Food & Beverages",
            "subcategory":"Groceries & Convenience Stores",
            "type":"Retail Goods"
        }
    ],
    "sg:phone":"+1 562 922 8401",
    "sg:postcode":"90242",
    "sg:province":"CA",
    "wof:name":"98 Cents Store Plus Mart",
    "wof:placetype":"venue"
},
  "geometry": {"coordinates":[-118.116499,33.910565],"type":"Point"}
}