{
  "type": "Feature",
  "properties": {
    "addr:full":"1121 Zygmunt Dr St Helena CA 94574",
    "addr:housenumber":"1121",
    "addr:postcode":"94574",
    "addr:street":"Zygmunt Dr",
    "iso:country":"US",
    "sg:address":"1121 Zygmunt Dr",
    "sg:city":"St Helena",
    "sg:classifiers":[
        {
            "category":"Building & Trades",
            "subcategory":"Electrical",
            "type":"Services"
        }
    ],
    "sg:phone":"+1 707 963 8256",
    "sg:postcode":"94574",
    "sg:province":"CA",
    "sg:tags":[
        "electric",
        "contractor"
    ],
    "wof:name":"Hemken Electric",
    "wof:placetype":"venue"
},
  "geometry": {"coordinates":[-122.442092,38.484625],"type":"Point"}
}