{
  "type": "Feature",
  "properties": {
    "addr:full":"20991 Sharmila Lake Forest CA 92630",
    "addr:housenumber":"20991",
    "addr:postcode":"92630",
    "addr:street":"Sharmila",
    "iso:country":"US",
    "sg:address":"20991 Sharmila",
    "sg:city":"Lake Forest",
    "sg:classifiers":[
        {
            "category":"Building & Trades",
            "subcategory":"Electrical",
            "type":"Services"
        }
    ],
    "sg:phone":"+1 949 206 1002",
    "sg:postcode":"92630",
    "sg:province":"CA",
    "sg:tags":[
        "telecommunication",
        "contractor"
    ],
    "wof:name":"Telecommunications & Data Svc",
    "wof:placetype":"venue"
},
  "geometry": {"coordinates":[-117.67696100000001,33.658832],"type":"Point"}
}