{
  "type": "Feature",
  "properties": {
    "addr:full":"5605 N Figueroa St Los Angeles CA 90042",
    "addr:housenumber":"5605",
    "addr:postcode":"90042",
    "addr:street":"N Figueroa St",
    "iso:country":"US",
    "sg:address":"5605 N Figueroa St",
    "sg:city":"Los Angeles",
    "sg:classifiers":[
        {
            "category":"Professional",
            "subcategory":"Management & Consulting",
            "type":"Services"
        }
    ],
    "sg:phone":"+1 323 258 8003",
    "sg:postcode":"90042",
    "sg:province":"CA",
    "sg:tags":[
        "consultant",
        "training"
    ],
    "wof:name":"Los Angeles Indigenous Peoples",
    "wof:placetype":"venue"
},
  "geometry": {"coordinates":[-118.19293500000001,34.109604],"type":"Point"}
}