{
  "type": "Feature",
  "properties": {
    "iso:country":"US",
    "sg:address":"15004 Daffodil Ave",
    "sg:city":"Canyon Country",
    "sg:classifiers":[
        {
            "category":"Building & Trades",
            "subcategory":"Landscaping Services",
            "type":"Services"
        }
    ],
    "sg:phone":"+1 661 299 5383",
    "sg:postcode":"91387",
    "sg:province":"CA",
    "sg:tags":[
        "landscape"
    ],
    "wof:name":"Createmps",
    "wof:placetype":"venue"
},
  "geometry": {"coordinates":[-118.398258,34.445583],"type":"Point"}
}