{
  "type": "Feature",
  "properties": {
    "iso:country":"US",
    "sg:address":"2122 N Baywood Dr",
    "sg:city":"Fullerton",
    "sg:classifiers":[
        {
            "category":"Professional",
            "type":"Services"
        }
    ],
    "sg:phone":"+1 714 680 3541",
    "sg:postcode":"92833",
    "sg:province":"CA",
    "sg:tags":[
        "establishment"
    ],
    "wof:name":"Cyclone Air Systems",
    "wof:placetype":"venue"
},
  "geometry": {"coordinates":[-117.96636599999999,33.897611],"type":"Point"}
}