{
  "type": "Feature",
  "properties": {
    "addr:full":"3093 Sacramento St San Francisco CA 94115",
    "addr:housenumber":"3093",
    "addr:postcode":"94115",
    "addr:street":"Sacramento St",
    "iso:country":"US",
    "sg:address":"3093 Sacramento St",
    "sg:city":"San Francisco",
    "sg:classifiers":[
        {
            "category":"Health Services",
            "subcategory":"Health Practitioner",
            "type":"Services"
        }
    ],
    "sg:phone":"+1 415 931 3384",
    "sg:postcode":"94115",
    "sg:province":"CA",
    "sg:tags":[
        "psychologist"
    ],
    "wof:name":"Walter Beckman PHD",
    "wof:placetype":"venue"
},
  "geometry": {"coordinates":[-122.44270899999999,37.788694],"type":"Point"}
}