{
  "type": "Feature",
  "properties": {
    "iso:country":"US",
    "sg:address":"872 37th St",
    "sg:city":"Emeryville",
    "sg:classifiers":[
        {
            "category":"Professional",
            "type":"Services"
        }
    ],
    "sg:phone":"+1 510 569 4005",
    "sg:postcode":"94608",
    "sg:province":"CA",
    "wof:name":"Crochet 4 Play",
    "wof:placetype":"venue"
},
  "geometry": {"coordinates":[-122.27207799999999,37.826796],"type":"Point"}
}