{
  "type": "Feature",
  "properties": {
    "addr:full":"2421 W 205th St Torrance CA 90501",
    "addr:housenumber":"2421",
    "addr:postcode":"90501",
    "addr:street":"W 205Th St",
    "iso:country":"US",
    "sg:address":"2421 W 205th St",
    "sg:city":"Torrance",
    "sg:classifiers":[
        {
            "category":"Wholesale",
            "subcategory":"Durable Goods & Equipment",
            "type":"Manufacturing & Wholesale Goods"
        }
    ],
    "sg:phone":"+1 310 782 3555",
    "sg:postcode":"90501",
    "sg:province":"CA",
    "sg:tags":[
        "exporter"
    ],
    "wof:name":"Max Creation USA Inc",
    "wof:placetype":"venue"
},
  "geometry": {"coordinates":[-118.32455899999999,33.845405],"type":"Point"}
}