{
  "type": "Feature",
  "properties": {
    "iso:country":"US",
    "sg:address":"508 del Monte Ave",
    "sg:city":"Monterey",
    "sg:classifiers":[
        {
            "category":"Retail",
            "subcategory":"Laundry & Dry Cleaning",
            "type":"Services"
        }
    ],
    "sg:phone":"+1 831 375 9597",
    "sg:postcode":"93940",
    "sg:province":"CA",
    "wof:name":"Del Mar French Laundry",
    "wof:placetype":"venue"
},
  "geometry": {"coordinates":[-121.888916,36.600094],"type":"Point"}
}