{
  "type": "Feature",
  "properties": {
    "addr:full":"2362 Tractor St Paso Robles CA 93446",
    "addr:housenumber":"2362",
    "addr:postcode":"93446",
    "addr:street":"Tractor St",
    "iso:country":"US",
    "sg:address":"2362 Tractor St",
    "sg:city":"Paso Robles",
    "sg:classifiers":[
        {
            "category":"Retail",
            "subcategory":"Repair Shop",
            "type":"Services"
        }
    ],
    "sg:phone":"+1 805 238 2404",
    "sg:postcode":"93446",
    "sg:province":"CA",
    "sg:tags":[
        "welding"
    ],
    "wof:name":"Hank's Welding Svc",
    "wof:placetype":"venue"
},
  "geometry": {"coordinates":[-120.65351200000001,35.647475],"type":"Point"}
}