{
  "type": "Feature",
  "properties": {
    "addr:full":"22114 S Vermont Ave Torrance CA 90502",
    "addr:housenumber":"22114",
    "addr:postcode":"90502",
    "addr:street":"S Vermont Ave",
    "iso:country":"US",
    "sg:address":"22114 S Vermont Ave",
    "sg:city":"Torrance",
    "sg:classifiers":[
        {
            "category":"Professional",
            "type":"Services"
        },
        {
            "category":"Wholesale",
            "subcategory":"Sporting Goods",
            "type":"Manufacturing & Wholesale Goods"
        }
    ],
    "sg:phone":"+1 310 533 9113",
    "sg:postcode":"90502",
    "sg:province":"CA",
    "sg:tags":[
        "equipment",
        "billiard",
        "supply"
    ],
    "wof:name":"Beasley Creations Inc",
    "wof:placetype":"venue"
},
  "geometry": {"coordinates":[-118.29019,33.827631],"type":"Point"}
}