{
  "type": "Feature",
  "properties": {
    "iso:country":"US",
    "sg:address":"2135 Covillaud St",
    "sg:city":"Marysville",
    "sg:phone":"+1 530 674 1677",
    "sg:postcode":"95901",
    "sg:province":"CA",
    "sg:tags":[
        "farm",
        "rice"
    ],
    "wof:name":"Bell Farms",
    "wof:placetype":"venue"
},
  "geometry": {"coordinates":[-121.577988,39.159181],"type":"Point"}
}