{
  "type": "Feature",
  "properties": {
    "iso:country":"US",
    "sg:address":"11600 Bartlett Ave",
    "sg:city":"Adelanto",
    "sg:classifiers":[
        {
            "category":"Banks & Credit Unions",
            "subcategory":"Financial Services",
            "type":"Services"
        }
    ],
    "sg:phone":"+1 760 530 0537",
    "sg:postcode":"92301",
    "sg:province":"CA",
    "sg:tags":[
        "cashing",
        "check"
    ],
    "wof:name":"Money Stop Check Cashing",
    "wof:placetype":"venue"
},
  "geometry": {"coordinates":[-117.412041,34.579201],"type":"Point"}
}