{
  "type": "Feature",
  "properties": {
    "iso:country":"US",
    "sg:address":"636 Broadway",
    "sg:city":"San Diego",
    "sg:classifiers":[
        {
            "category":"Professional",
            "subcategory":"Testing Lab",
            "type":"Services"
        }
    ],
    "sg:phone":"+1 619 544 6819",
    "sg:postcode":"92101",
    "sg:province":"CA",
    "sg:tags":[
        "laboratory"
    ],
    "wof:name":"Interlab Inc",
    "wof:placetype":"venue"
},
  "geometry": {"coordinates":[-117.158654,32.715782],"type":"Point"}
}