{
  "type": "Feature",
  "properties": {
    "addr:full":"6025 Agee St San Diego CA 92122",
    "addr:housenumber":"6025",
    "addr:postcode":"92122",
    "addr:street":"Agee St",
    "iso:country":"US",
    "sg:address":"6025 Agee St",
    "sg:city":"San Diego",
    "sg:classifiers":[
        {
            "category":"Building & Trades",
            "subcategory":"Construction",
            "type":"Services"
        }
    ],
    "sg:phone":"+1 858 792 7747",
    "sg:postcode":"92122",
    "sg:province":"CA",
    "sg:tags":[
        "general",
        "contractor"
    ],
    "wof:name":"Remar Construction",
    "wof:placetype":"venue"
},
  "geometry": {"coordinates":[-117.201161,32.851069],"type":"Point"}
}