{
  "type": "Feature",
  "properties": {
    "addr:full":"4495 Clairemont Mesa Blvd San Diego CA 92117",
    "addr:housenumber":"4495",
    "addr:postcode":"92117",
    "addr:street":"Clairemont Mesa Blvd",
    "iso:country":"US",
    "sg:address":"4495 Clairemont Mesa Blvd",
    "sg:city":"San Diego",
    "sg:classifiers":[
        {
            "category":"Retail",
            "subcategory":"Auto Repair",
            "type":"Services"
        }
    ],
    "sg:phone":"+1 858 274 6566",
    "sg:postcode":"92117",
    "sg:province":"CA",
    "sg:tags":[
        "repairing",
        "automobile"
    ],
    "wof:name":"Clairemont Auto Care",
    "wof:placetype":"venue"
},
  "geometry": {"coordinates":[-117.197582,32.834368],"type":"Point"}
}