{
  "type": "Feature",
  "properties": {
    "iso:country":"US",
    "sg:address":"1096 S Coast Hwy",
    "sg:city":"Laguna Beach",
    "sg:classifiers":[
        {
            "category":"Real Estate",
            "subcategory":"Real Estate Agent",
            "type":"Services"
        }
    ],
    "sg:phone":"+1 949 494 8057",
    "sg:postcode":"92651",
    "sg:province":"CA",
    "wof:name":"Laguna Properties",
    "wof:placetype":"venue"
},
  "geometry": {"coordinates":[-117.77755500000001,33.53503],"type":"Point"}
}