{
  "type": "Feature",
  "properties": {
    "iso:country":"US",
    "sg:address":"5737 Thornhill Dr",
    "sg:city":"Oakland",
    "sg:classifiers":[
        {
            "category":"Professional",
            "type":"Services"
        }
    ],
    "sg:phone":"+1 530 432 5670",
    "sg:postcode":"94611",
    "sg:province":"CA",
    "sg:tags":[
        "establishment"
    ],
    "wof:name":"Denise Feinsod Database Dev",
    "wof:placetype":"venue"
},
  "geometry": {"coordinates":[-122.212968,37.834068],"type":"Point"}
}