{
  "type": "Feature",
  "properties": {
    "iso:country":"US",
    "sg:address":"14906 S Figueroa St",
    "sg:city":"Gardena",
    "sg:classifiers":[
        {
            "category":"Wholesale",
            "subcategory":"Durable Goods & Equipment",
            "type":"Manufacturing & Wholesale Goods"
        }
    ],
    "sg:phone":"+1 310 532 6666",
    "sg:postcode":"90248",
    "sg:province":"CA",
    "sg:tags":[
        "importer"
    ],
    "sg:website":"www.tridentautotech.com",
    "wof:name":"Trident Autotech",
    "wof:placetype":"venue"
},
  "geometry": {"coordinates":[-118.28312,33.897047],"type":"Point"}
}