{
  "type": "Feature",
  "properties": {
    "iso:country":"US",
    "sg:address":"2627 Buck Owens Blvd",
    "sg:city":"Bakersfield",
    "sg:classifiers":[
        {
            "category":"Restaurant",
            "type":"Food & Drink"
        }
    ],
    "sg:menulink":"http://www.allmenus.com/ca/bakersfield/8410-dennys/menu/",
    "sg:phone":"+1 661 395 3014",
    "sg:postcode":"93308",
    "sg:province":"CA",
    "sg:tags":[
        "american",
        "diner"
    ],
    "wof:name":"Denny's",
    "wof:placetype":"venue"
},
  "geometry": {"coordinates":[-119.043335,35.383399],"type":"Point"}
}