{
  "type": "Feature",
  "properties": {
    "iso:country":"US",
    "sg:address":"400 Visitacion Ave",
    "sg:city":"Brisbane",
    "sg:classifiers":[
        {
            "category":"Real Estate",
            "subcategory":"Real Estate Agent",
            "type":"Services"
        }
    ],
    "sg:phone":"+1 415 467 4000",
    "sg:postcode":"94005",
    "sg:province":"CA",
    "wof:name":"Ron Davis & Co Real Estate",
    "wof:placetype":"venue"
},
  "geometry": {"coordinates":[-122.403126,37.68088],"type":"Point"}
}