{
  "type": "Feature",
  "properties": {
    "iso:country":"US",
    "sg:address":"1907 Princeton Ct",
    "sg:city":"Salinas",
    "sg:classifiers":[
        {
            "category":"Professional",
            "type":"Services"
        }
    ],
    "sg:phone":"+1 831 771 9559",
    "sg:postcode":"93906",
    "sg:province":"CA",
    "wof:name":"JBA LLC",
    "wof:placetype":"venue"
},
  "geometry": {"coordinates":[-121.646095,36.717014],"type":"Point"}
}