{
  "type": "Feature",
  "properties": {
    "iso:country":"US",
    "sg:address":"12866 Main St",
    "sg:city":"Garden Grove",
    "sg:classifiers":[
        {
            "category":"Travel",
            "subcategory":"Travel Agent",
            "type":"Entertainment"
        }
    ],
    "sg:phone":"+1 714 638 2843",
    "sg:postcode":"92840",
    "sg:province":"CA",
    "sg:tags":[
        "agency"
    ],
    "wof:name":"Pacific Travel & Tours Intl",
    "wof:placetype":"venue"
},
  "geometry": {"coordinates":[-117.940866,33.774242],"type":"Point"}
}