{
  "type": "Feature",
  "properties": {
    "iso:country":"US",
    "sg:address":"3100 Milliken Ave",
    "sg:city":"Mira Loma",
    "sg:classifiers":[
        {
            "category":"Freight",
            "type":"Transportation"
        }
    ],
    "sg:phone":"+1 951 727 3200",
    "sg:postcode":"91752",
    "sg:province":"CA",
    "sg:tags":[
        "general"
    ],
    "wof:name":"Kmart",
    "wof:placetype":"venue"
},
  "geometry": {"coordinates":[-117.558374,34.027707],"type":"Point"}
}