{
  "type": "Feature",
  "properties": {
    "addr:full":"255 N el Cielo Rd Palm Springs CA 92262",
    "addr:housenumber":"255",
    "addr:postcode":"92262",
    "addr:street":"N El Cielo Rd",
    "iso:country":"US",
    "sg:address":"255 N el Cielo Rd",
    "sg:city":"Palm Springs",
    "sg:classifiers":[
        {
            "category":"Insurance",
            "subcategory":"Insurance Agent",
            "type":"Services"
        }
    ],
    "sg:phone":"+1 760 774 6355",
    "sg:postcode":"92262",
    "sg:province":"CA",
    "wof:name":"General Electric Long Term",
    "wof:placetype":"venue"
},
  "geometry": {"coordinates":[-116.510704,33.825721],"type":"Point"}
}