{
  "type": "Feature",
  "properties": {
    "iso:country":"US",
    "sg:address":"123 W B St",
    "sg:city":"Ontario",
    "sg:classifiers":[
        {
            "category":"Real Estate",
            "subcategory":"Real Estate Agent",
            "type":"Services"
        }
    ],
    "sg:phone":"+1 909 988 6700",
    "sg:postcode":"91762",
    "sg:province":"CA",
    "sg:tags":[
        "management"
    ],
    "wof:name":"First Management Properties",
    "wof:placetype":"venue"
},
  "geometry": {"coordinates":[-117.65209900000001,34.064509],"type":"Point"}
}