{
  "type": "Feature",
  "properties": {
    "iso:country":"US",
    "sg:address":"16660 Paramount Blvd Ste 211",
    "sg:city":"Paramount",
    "sg:classifiers":[
        {
            "category":"Health Services",
            "subcategory":"Doctor",
            "type":"Services"
        }
    ],
    "sg:phone":"+1 562 633 5438",
    "sg:postcode":"90723",
    "sg:province":"CA",
    "wof:name":"Deleon Jessie MD",
    "wof:placetype":"venue"
},
  "geometry": {"coordinates":[-118.160004,33.882401],"type":"Point"}
}