{
  "type": "Feature",
  "properties": {
    "addr:full":"3105 Chardonnay Dr Pleasanton CA 94566",
    "addr:housenumber":"3105",
    "addr:postcode":"94566",
    "addr:street":"Chardonnay Dr",
    "iso:country":"US",
    "sg:address":"3105 Chardonnay Dr",
    "sg:city":"Pleasanton",
    "sg:classifiers":[
        {
            "category":"Building & Trades",
            "subcategory":"Construction",
            "type":"Services"
        }
    ],
    "sg:phone":"+1 925 426 8047",
    "sg:postcode":"94566",
    "sg:province":"CA",
    "sg:tags":[
        "repairing",
        "remodeling",
        "contractor"
    ],
    "wof:name":"S P Evans Construction",
    "wof:placetype":"venue"
},
  "geometry": {"coordinates":[-121.849362,37.664371],"type":"Point"}
}