{
  "type": "Feature",
  "properties": {
    "iso:country":"US",
    "sg:address":"3440 Torrance Blvd",
    "sg:city":"Torrance",
    "sg:classifiers":[
        {
            "category":"Professional",
            "subcategory":"Lawyer & Legal Services",
            "type":"Services"
        }
    ],
    "sg:phone":"+1 310 543 9355",
    "sg:postcode":"90503",
    "sg:province":"CA",
    "wof:name":"Stennett Jack C Lawyer",
    "wof:placetype":"venue"
},
  "geometry": {"coordinates":[-118.346001,33.837502],"type":"Point"}
}