{
  "type": "Feature",
  "properties": {
    "addr:full":"14245 Monterey Hwy San Martin CA 95046",
    "addr:housenumber":"14245",
    "addr:postcode":"95046",
    "addr:street":"Monterey Hwy",
    "iso:country":"US",
    "sg:address":"14245 Monterey Hwy",
    "sg:city":"San Martin",
    "sg:classifiers":[
        {
            "category":"Professional",
            "subcategory":"Advertising",
            "type":"Services"
        }
    ],
    "sg:phone":"+1 408 779 8431",
    "sg:postcode":"95046",
    "sg:province":"CA",
    "sg:tags":[
        "distribution"
    ],
    "wof:name":"Lico Distributing",
    "wof:placetype":"venue"
},
  "geometry": {"coordinates":[-121.61684200000001,37.095622],"type":"Point"}
}