{
  "type": "Feature",
  "properties": {
    "addr:full":"528 Solano Ave Los Angeles CA 90012",
    "addr:housenumber":"528",
    "addr:postcode":"90012",
    "addr:street":"Solano Ave",
    "iso:country":"US",
    "sg:address":"528 Solano Ave",
    "sg:city":"Los Angeles",
    "sg:classifiers":[
        {
            "category":"Professional",
            "type":"Services"
        }
    ],
    "sg:phone":"+1 323 493 6715",
    "sg:postcode":"90012",
    "sg:province":"CA",
    "wof:name":"MI Unico Inc",
    "wof:placetype":"venue"
},
  "geometry": {"coordinates":[-118.231397,34.075674],"type":"Point"}
}