{
  "type": "Feature",
  "properties": {
    "iso:country":"US",
    "sg:address":"9130 Telegraph Road",
    "sg:city":"Downey",
    "sg:classifiers":[
        {
            "category":"Personal",
            "subcategory":"Massage",
            "type":"Services"
        }
    ],
    "sg:phone":"+1 562 861 6759",
    "sg:postcode":"90240",
    "sg:province":"CA",
    "wof:name":"All Seasons Health & Clinical",
    "wof:placetype":"venue"
},
  "geometry": {"coordinates":[-118.107676,33.959183],"type":"Point"}
}