{
  "type": "Feature",
  "properties": {
    "iso:country":"US",
    "sg:address":"2760 Oro Dam Blvd W",
    "sg:city":"Oroville",
    "sg:classifiers":[
        {
            "category":"Health Services",
            "subcategory":"Doctor",
            "type":"Services"
        }
    ],
    "sg:phone":"+1 530 533 4746",
    "sg:postcode":"95965",
    "sg:province":"CA",
    "sg:tags":[
        "dentist"
    ],
    "wof:name":"Hanosh Family Dentistry",
    "wof:placetype":"venue"
},
  "geometry": {"coordinates":[-121.628832,39.498154],"type":"Point"}
}