{
  "type": "Feature",
  "properties": {
    "addr:full":"1709 Sutter St Vallejo CA 94590",
    "addr:housenumber":"1709",
    "addr:postcode":"94590",
    "addr:street":"Sutter St",
    "iso:country":"US",
    "sg:address":"1709 Sutter St",
    "sg:city":"Vallejo",
    "sg:classifiers":[
        {
            "category":"Professional",
            "subcategory":"Engineering",
            "type":"Services"
        }
    ],
    "sg:phone":"+1 707 552 9111",
    "sg:postcode":"94590",
    "sg:province":"CA",
    "sg:tags":[
        "civil",
        "engineer"
    ],
    "wof:name":"Jordan Associates Inc",
    "wof:placetype":"venue"
},
  "geometry": {"coordinates":[-122.253057,38.110287],"type":"Point"}
}