{
  "type": "Feature",
  "properties": {
    "addr:full":"3637 Motor Ave Los Angeles CA 90034",
    "addr:housenumber":"3637",
    "addr:postcode":"90034",
    "addr:street":"Motor Ave",
    "iso:country":"US",
    "sg:address":"3637 Motor Ave",
    "sg:city":"Los Angeles",
    "sg:classifiers":[
        {
            "category":"Real Estate",
            "subcategory":"Real Estate Agent",
            "type":"Services"
        }
    ],
    "sg:phone":"+1 310 836 9708",
    "sg:postcode":"90034",
    "sg:province":"CA",
    "sg:tags":[
        "management"
    ],
    "sg:website":"www.auraassetgroup.com",
    "wof:name":"Aura Asset Group Inc",
    "wof:placetype":"venue"
},
  "geometry": {"coordinates":[-118.40625300000001,34.023477],"type":"Point"}
}