{
  "type": "Feature",
  "properties": {
    "addr:full":"3035 Moore St San Diego CA 92110",
    "addr:housenumber":"3035",
    "addr:postcode":"92110",
    "addr:street":"Moore St",
    "iso:country":"US",
    "sg:address":"3035 Moore St",
    "sg:city":"San Diego",
    "sg:classifiers":[
        {
            "category":"Travel",
            "subcategory":"Travel Agent",
            "type":"Entertainment"
        }
    ],
    "sg:phone":"+1 619 688 1022",
    "sg:postcode":"92110",
    "sg:province":"CA",
    "sg:tags":[
        "agency"
    ],
    "wof:name":"Grattan Robbi",
    "wof:placetype":"venue"
},
  "geometry": {"coordinates":[-117.20323999999999,32.754179],"type":"Point"}
}