{
  "type": "Feature",
  "properties": {
    "iso:country":"US",
    "sg:address":"2025 E Highland Ave",
    "sg:city":"San Bernardino",
    "sg:classifiers":[
        {
            "category":"Manufacturing",
            "subcategory":"Tools & Machinery",
            "type":"Manufacturing & Wholesale Goods"
        }
    ],
    "sg:phone":"+1 909 864 1170",
    "sg:postcode":"92404",
    "sg:province":"CA",
    "sg:tags":[
        "devices",
        "mfg"
    ],
    "wof:name":"Horizon Measured Inc",
    "wof:placetype":"venue"
},
  "geometry": {"coordinates":[-117.239745,34.135935],"type":"Point"}
}