{
  "type": "Feature",
  "properties": {
    "iso:country":"US",
    "sg:address":"1028 Summit Ave",
    "sg:city":"Napa",
    "sg:classifiers":[
        {
            "category":"Professional",
            "type":"Services"
        }
    ],
    "sg:phone":"+1 707 253 0204",
    "sg:postcode":"94559",
    "sg:province":"CA",
    "sg:tags":[
        "arts",
        "artist"
    ],
    "wof:name":"Napa Valley Art Studio",
    "wof:placetype":"venue"
},
  "geometry": {"coordinates":[-122.275414,38.30882],"type":"Point"}
}