{
  "type": "Feature",
  "properties": {
    "iso:country":"US",
    "sg:address":"2104 Monterey Blvd",
    "sg:city":"Hermosa Beach",
    "sg:classifiers":[
        {
            "category":"Utilities",
            "subcategory":"Telephone",
            "type":"Services"
        }
    ],
    "sg:phone":"+1 310 779 4471",
    "sg:postcode":"90254",
    "sg:province":"CA",
    "sg:tags":[
        "global",
        "outsourcing"
    ],
    "wof:name":"Giantpost",
    "wof:placetype":"venue"
},
  "geometry": {"coordinates":[-118.401608,33.870056],"type":"Point"}
}