{
  "type": "Feature",
  "properties": {
    "addr:full":"2930 E 23rd St Oakland CA 94601",
    "addr:housenumber":"2930",
    "addr:postcode":"94601",
    "addr:street":"E 23Rd St",
    "iso:country":"US",
    "sg:address":"2930 E 23rd St",
    "sg:city":"Oakland",
    "sg:classifiers":[
        {
            "category":"Social Services",
            "subcategory":"Child Care",
            "type":"Services"
        }
    ],
    "sg:phone":"+1 510 261 2005",
    "sg:postcode":"94601",
    "sg:province":"CA",
    "wof:name":"Like Home Daycare Ctr",
    "wof:placetype":"venue"
},
  "geometry": {"coordinates":[-122.222559,37.785909],"type":"Point"}
}