{
  "type": "Feature",
  "properties": {
    "addr:full":"10500 Gibbs Dr Oakdale CA 95361",
    "addr:housenumber":"10500",
    "addr:postcode":"95361",
    "addr:street":"Gibbs Dr",
    "iso:country":"US",
    "sg:address":"10500 Gibbs Dr",
    "sg:city":"Oakdale",
    "sg:classifiers":[
        {
            "category":"Wholesale",
            "subcategory":"Non-durable Goods",
            "type":"Manufacturing & Wholesale Goods"
        }
    ],
    "sg:phone":"+1 209 847 0247",
    "sg:postcode":"95361",
    "sg:province":"CA",
    "wof:name":"Elegant Creations",
    "wof:placetype":"venue"
},
  "geometry": {"coordinates":[-120.78966200000001,37.789609],"type":"Point"}
}