{
  "type": "Feature",
  "properties": {
    "iso:country":"US",
    "sg:address":"628 Wendy Way",
    "sg:city":"Paradise",
    "sg:classifiers":[
        {
            "category":"Building & Trades",
            "subcategory":"Construction",
            "type":"Services"
        }
    ],
    "sg:phone":"+1 530 877 3778",
    "sg:postcode":"95969",
    "sg:province":"CA",
    "sg:tags":[
        "house"
    ],
    "wof:name":"William Ruhl Prof Bldr",
    "wof:placetype":"venue"
},
  "geometry": {"coordinates":[-121.62747299999999,39.7456],"type":"Point"}
}