{
  "type": "Feature",
  "properties": {
    "addr:full":"121 S Hacienda Blvd City Of Industry CA 91745",
    "addr:housenumber":"121",
    "addr:postcode":"91745",
    "addr:street":"S Hacienda Blvd",
    "iso:country":"US",
    "sg:address":"121 S Hacienda Blvd",
    "sg:city":"City Of Industry",
    "sg:classifiers":[
        {
            "category":"Manufacturing",
            "subcategory":"Food",
            "type":"Manufacturing & Wholesale Goods"
        },
        {
            "category":"Food & Beverages",
            "subcategory":"Bakery",
            "type":"Retail Goods"
        }
    ],
    "sg:phone":"+1 626 330 1297",
    "sg:postcode":"91745",
    "sg:province":"CA",
    "sg:tags":[
        "product",
        "doughnut",
        "mfg"
    ],
    "wof:name":"Crown Donuts",
    "wof:placetype":"venue"
},
  "geometry": {"coordinates":[-117.959681,34.017573],"type":"Point"}
}