{
  "type": "Feature",
  "properties": {
    "iso:country":"US",
    "sg:address":"440 N 1st St",
    "sg:city":"San Jose",
    "sg:classifiers":[
        {
            "category":"Real Estate",
            "subcategory":"Real Estate Agent",
            "type":"Services"
        }
    ],
    "sg:phone":"+1 408 390 0323",
    "sg:postcode":"95112",
    "sg:province":"CA",
    "wof:name":"Wardenclyffe LP",
    "wof:placetype":"venue"
},
  "geometry": {"coordinates":[-121.895948,37.343489],"type":"Point"}
}