{
  "type": "Feature",
  "properties": {
    "iso:country":"US",
    "sg:address":"5401 Sunrise Blvd",
    "sg:city":"Citrus Heights",
    "sg:classifiers":[
        {
            "category":"Retail",
            "subcategory":"Photofinishing",
            "type":"Services"
        }
    ],
    "sg:phone":"+1 916 961 1119",
    "sg:postcode":"95610",
    "sg:province":"CA",
    "sg:tags":[
        "photo",
        "finishing"
    ],
    "wof:name":"Rainbow Photo",
    "wof:placetype":"venue"
},
  "geometry": {"coordinates":[-121.272174,38.666762],"type":"Point"}
}