{
  "type": "Feature",
  "properties": {
    "addr:full":"13711 Calimesa Blvd Yucaipa CA 92399",
    "addr:housenumber":"13711",
    "addr:postcode":"92399",
    "addr:street":"Calimesa Blvd",
    "iso:country":"US",
    "sg:address":"13711 Calimesa Blvd",
    "sg:city":"Yucaipa",
    "sg:classifiers":[
        {
            "category":"Food & Beverages",
            "subcategory":"Liquor & Beverages",
            "type":"Retail Goods"
        }
    ],
    "sg:phone":"+1 909 795 5519",
    "sg:postcode":"92399",
    "sg:province":"CA",
    "sg:tags":[
        "beer",
        "spirit",
        "wine"
    ],
    "wof:name":"C & H Liquors",
    "wof:placetype":"venue"
},
  "geometry": {"coordinates":[-117.08899700000001,34.015701],"type":"Point"}
}