{
  "type": "Feature",
  "properties": {
    "iso:country":"US",
    "sg:address":"16484 4th St",
    "sg:city":"Guerneville",
    "sg:classifiers":[
        {
            "category":"Travel",
            "subcategory":"Hotels & Motels",
            "type":"Entertainment"
        }
    ],
    "sg:phone":"+1 877 887 9218",
    "sg:postcode":"95446",
    "sg:province":"CA",
    "sg:website":"www.rrwoods.com",
    "wof:name":"The Woods Resort",
    "wof:placetype":"venue"
},
  "geometry": {"coordinates":[-123.001305,38.503177],"type":"Point"}
}