{
  "type": "Feature",
  "properties": {
    "addr:full":"11 Leabig Ln Martinez CA 94553",
    "addr:housenumber":"11",
    "addr:postcode":"94553",
    "addr:street":"Leabig Ln",
    "iso:country":"US",
    "sg:address":"11 Leabig Ln",
    "sg:city":"Martinez",
    "sg:classifiers":[
        {
            "category":"Building & Trades",
            "subcategory":"Plumbing",
            "type":"Services"
        }
    ],
    "sg:phone":"+1 925 938 2565",
    "sg:postcode":"94553",
    "sg:province":"CA",
    "sg:tags":[
        "plumbing",
        "contractor"
    ],
    "wof:name":"California Home Svc",
    "wof:placetype":"venue"
},
  "geometry": {"coordinates":[-122.086736,38.012375],"type":"Point"}
}