{
  "type": "Feature",
  "properties": {
    "iso:country":"US",
    "sg:address":"8065 Elk Grove Florin Rd",
    "sg:city":"Sacramento",
    "sg:classifiers":[
        {
            "category":"Food & Beverages",
            "subcategory":"Bakery",
            "type":"Retail Goods"
        }
    ],
    "sg:phone":"+1 916 689 2828",
    "sg:postcode":"95829",
    "sg:province":"CA",
    "sg:tags":[
        "doughnut"
    ],
    "wof:name":"Premium Donuts",
    "wof:placetype":"venue"
},
  "geometry": {"coordinates":[-121.371798,38.466116],"type":"Point"}
}