{
  "type": "Feature",
  "properties": {
    "addr:full":"Valencia Street Muscle 333 Valencia St Ste 100 San Francisco CA 94103",
    "addr:housenumber":"333",
    "addr:postcode":"94103",
    "addr:street":"Valencia Street;Valencia St Ste 100",
    "iso:country":"US",
    "sg:address":"Valencia Street Muscle 333 Valencia St Ste 100",
    "sg:city":"San Francisco",
    "sg:classifiers":[
        {
            "category":"Arena",
            "subcategory":"Sports Club",
            "type":"Entertainment"
        }
    ],
    "sg:phone":"+1 415 374 6790",
    "sg:postcode":"94103",
    "sg:province":"CA",
    "sg:tags":[
        "martial art"
    ],
    "sg:website":"www.capoeiramission.com",
    "wof:name":"Capoeira Mission",
    "wof:placetype":"venue"
},
  "geometry": {"coordinates":[-122.422112,37.76744],"type":"Point"}
}