{
  "type": "Feature",
  "properties": {
    "iso:country":"US",
    "sg:address":"10700 Katella Ave",
    "sg:city":"Anaheim",
    "sg:classifiers":[
        {
            "category":"Local Transit",
            "type":"Transportation"
        }
    ],
    "sg:phone":"+1 714 750 8087",
    "sg:postcode":"92804",
    "sg:province":"CA",
    "sg:tags":[
        "passenger"
    ],
    "wof:name":"All Taxis",
    "wof:placetype":"venue"
},
  "geometry": {"coordinates":[-117.949133,33.803135],"type":"Point"}
}