{
  "type": "Feature",
  "properties": {
    "iso:country":"US",
    "sg:address":"777 S Figueroa St",
    "sg:city":"Los Angeles",
    "sg:classifiers":[
        {
            "category":"Professional",
            "subcategory":"Lawyer & Legal Services",
            "type":"Services"
        }
    ],
    "sg:phone":"+1 213 892 4903",
    "sg:postcode":"90017",
    "sg:province":"CA",
    "wof:name":"Hallem Timi A",
    "wof:placetype":"venue"
},
  "geometry": {"coordinates":[-118.261002,34.048199],"type":"Point"}
}