{
  "type": "Feature",
  "properties": {
    "addr:full":"1302 Reamwood Ave Sunnyvale CA 94089",
    "addr:housenumber":"1302",
    "addr:postcode":"94089",
    "addr:street":"Reamwood Ave",
    "iso:country":"US",
    "sg:address":"1302 Reamwood Ave",
    "sg:city":"Sunnyvale",
    "sg:classifiers":[
        {
            "category":"Manufacturing",
            "subcategory":"Tools & Machinery",
            "type":"Manufacturing & Wholesale Goods"
        }
    ],
    "sg:phone":"+1 408 745 1100",
    "sg:postcode":"94089",
    "sg:province":"CA",
    "sg:tags":[
        "industry",
        "mfg"
    ],
    "wof:name":"Freylit USA Inc",
    "wof:placetype":"venue"
},
  "geometry": {"coordinates":[-121.988455,37.409207],"type":"Point"}
}