{
  "type": "Feature",
  "properties": {
    "iso:country":"US",
    "sg:address":"310 Nord Ave",
    "sg:city":"Chico",
    "sg:classifiers":[
        {
            "category":"Wholesale",
            "subcategory":"Petroleum",
            "type":"Manufacturing & Wholesale Goods"
        },
        {
            "category":"Manufacturing",
            "subcategory":"Petroleum Products",
            "type":"Manufacturing & Wholesale Goods"
        },
        {
            "category":"Utilities",
            "subcategory":"Fuel Oil & Lpg",
            "type":"Services"
        },
        {
            "category":"Utilities",
            "subcategory":"Natural Gas",
            "type":"Services"
        }
    ],
    "sg:phone":"+1 530 342 8376",
    "sg:postcode":"95926",
    "sg:province":"CA",
    "sg:tags":[
        "propane",
        "oils-fuel",
        "refiner",
        "gasoline-wholesale"
    ],
    "sg:website":"http://www.huntnsons.com",
    "wof:name":"Warner Petroleum Inc.",
    "wof:placetype":"venue"
},
  "geometry": {"coordinates":[-121.873955,39.738232],"type":"Point"}
}