{
  "type": "Feature",
  "properties": {
    "iso:country":"US",
    "sg:address":"660 J St",
    "sg:city":"Sacramento",
    "sg:classifiers":[
        {
            "category":"Professional",
            "subcategory":"Computer Services",
            "type":"Services"
        }
    ],
    "sg:phone":"+1 916 442 8358",
    "sg:postcode":"95814",
    "sg:province":"CA",
    "sg:tags":[
        "hardware",
        "software",
        "provider",
        "internet"
    ],
    "wof:name":"Project Arena",
    "wof:placetype":"venue"
},
  "geometry": {"coordinates":[-121.498056,38.581504],"type":"Point"}
}