{
  "type": "Feature",
  "properties": {
    "addr:full":"650 S Grand Ave Los Angeles CA 90017",
    "addr:housenumber":"650",
    "addr:postcode":"90017",
    "addr:street":"S Grand Ave",
    "iso:country":"US",
    "sg:address":"650 S Grand Ave",
    "sg:city":"Los Angeles",
    "sg:classifiers":[
        {
            "category":"Utilities",
            "subcategory":"Telephone",
            "type":"Services"
        }
    ],
    "sg:phone":"+1 213 683 8868",
    "sg:postcode":"90017",
    "sg:province":"CA",
    "sg:tags":[
        "company"
    ],
    "wof:name":"Teledirect Communications Inc",
    "wof:placetype":"venue"
},
  "geometry": {"coordinates":[-118.256405,34.047415],"type":"Point"}
}