{
  "type": "Feature",
  "properties": {
    "addr:full":"1809 Railroad Ave Livermore CA 94550",
    "addr:housenumber":"1809",
    "addr:postcode":"94550",
    "addr:street":"Railroad Ave",
    "iso:country":"US",
    "sg:address":"1809 Railroad Ave",
    "sg:city":"Livermore",
    "sg:classifiers":[
        {
            "category":"Real Estate",
            "subcategory":"Real Estate Operator",
            "type":"Services"
        }
    ],
    "sg:phone":"+1 925 373 7275",
    "sg:postcode":"94550",
    "sg:province":"CA",
    "sg:tags":[
        "apartment"
    ],
    "wof:name":"Mill Springs Park",
    "wof:placetype":"venue"
},
  "geometry": {"coordinates":[-121.77365,37.68205],"type":"Point"}
}