{
  "type": "Feature",
  "properties": {
    "iso:country":"US",
    "sg:address":"4824 W 120th St",
    "sg:city":"Hawthorne",
    "sg:classifiers":[
        {
            "category":"Building & Trades",
            "subcategory":"Cleaning & Sanitation",
            "type":"Services"
        }
    ],
    "sg:phone":"+1 310 675 0946",
    "sg:postcode":"90250",
    "sg:province":"CA",
    "sg:tags":[
        "home"
    ],
    "wof:name":"Angelica's Cleaning Service",
    "wof:placetype":"venue"
},
  "geometry": {"coordinates":[-118.36199999999999,33.923801],"type":"Point"}
}