{
  "type": "Feature",
  "properties": {
    "addr:full":"15126 Versailles St Lake Elsinore CA 92530",
    "addr:postcode":"15126;92530",
    "addr:street":"Versailles St",
    "iso:country":"US",
    "sg:address":"15126 Versailles St",
    "sg:city":"Lake Elsinore",
    "sg:classifiers":[
        {
            "category":"Manufacturing",
            "subcategory":"Retail Goods",
            "type":"Manufacturing & Wholesale Goods"
        }
    ],
    "sg:phone":"+1 951 471 3294",
    "sg:postcode":"92530",
    "sg:province":"CA",
    "sg:tags":[
        "manufacturer"
    ],
    "wof:name":"JWS Enterprises Co",
    "wof:placetype":"venue"
},
  "geometry": {"coordinates":[-117.38615799999999,33.686806],"type":"Point"}
}