{
  "type": "Feature",
  "properties": {
    "iso:country":"US",
    "sg:address":"15126 Versailles St",
    "sg:city":"Lake Elsinore",
    "sg:classifiers":[
        {
            "category":"Manufacturing",
            "subcategory":"Retail Goods",
            "type":"Manufacturing & Wholesale Goods"
        }
    ],
    "sg:phone":"+1 951 471 3294",
    "sg:postcode":"92530",
    "sg:province":"CA",
    "sg:tags":[
        "manufacturer"
    ],
    "wof:name":"JWS Enterprises Co",
    "wof:placetype":"venue"
},
  "geometry": {"coordinates":[-117.386158,33.686806],"type":"Point"}
}