{
  "type": "Feature",
  "properties": {
    "iso:country":"US",
    "sg:address":"510 S Lorena St",
    "sg:city":"Los Angeles",
    "sg:classifiers":[
        {
            "category":"Restaurant",
            "type":"Food & Drink"
        }
    ],
    "sg:phone":"+1 323 262 8858",
    "sg:postcode":"90063",
    "sg:province":"CA",
    "wof:name":"Salsa Chips",
    "wof:placetype":"venue"
},
  "geometry": {"coordinates":[-118.19826999999999,34.031921],"type":"Point"}
}