{
  "type": "Feature",
  "properties": {
    "addr:full":"539 W Fern Dr Fullerton CA 92832",
    "addr:housenumber":"539",
    "addr:postcode":"92832",
    "addr:street":"W Fern Dr",
    "iso:country":"US",
    "sg:address":"539 W Fern Dr",
    "sg:city":"Fullerton",
    "sg:classifiers":[
        {
            "category":"Insurance",
            "subcategory":"Insurance Agent",
            "type":"Services"
        }
    ],
    "sg:phone":"+1 714 447 1608",
    "sg:postcode":"92832",
    "sg:province":"CA",
    "wof:name":"4healthplanscom",
    "wof:placetype":"venue"
},
  "geometry": {"coordinates":[-117.93371399999999,33.880429],"type":"Point"}
}