{
  "type": "Feature",
  "properties": {
    "iso:country":"US",
    "sg:address":"9030 Kenamar Dr",
    "sg:city":"San Diego",
    "sg:classifiers":[
        {
            "category":"Manufacturing",
            "subcategory":"Chemicals & Compounds",
            "type":"Manufacturing & Wholesale Goods"
        }
    ],
    "sg:phone":"+1 858 536 2360",
    "sg:postcode":"92121",
    "sg:province":"CA",
    "sg:tags":[
        "preparation",
        "pharmaceutical"
    ],
    "wof:name":"Pharmessen Scientific",
    "wof:placetype":"venue"
},
  "geometry": {"coordinates":[-117.155534,32.887132],"type":"Point"}
}