{
  "type": "Feature",
  "properties": {
    "addr:full":"21074 S Lassen Ave Five Points CA 93624",
    "addr:housenumber":"21074",
    "addr:postcode":"93624",
    "addr:street":"S Lassen Ave",
    "iso:country":"US",
    "sg:address":"21074 S Lassen Ave",
    "sg:city":"Five Points",
    "sg:classifiers":[
        {
            "category":"Government",
            "subcategory":"Post Office",
            "type":"Public Place"
        }
    ],
    "sg:phone":"+1 559 884 2409",
    "sg:postcode":"93624",
    "sg:province":"CA",
    "wof:name":"US Post Office",
    "wof:placetype":"venue"
},
  "geometry": {"coordinates":[-120.103027,36.42823],"type":"Point"}
}