{
  "type": "Feature",
  "properties": {
    "addr:full":"73 Corsica Dr Newport Beach CA 92660",
    "addr:housenumber":"73",
    "addr:postcode":"92660",
    "addr:street":"Corsica Dr",
    "iso:country":"US",
    "sg:address":"73 Corsica Dr",
    "sg:city":"Newport Beach",
    "sg:classifiers":[
        {
            "category":"Shopping",
            "subcategory":"Bicycles & Sporting Goods",
            "type":"Retail Goods"
        }
    ],
    "sg:phone":"+1 949 713 3072",
    "sg:postcode":"92660",
    "sg:province":"CA",
    "wof:name":"G M Sports",
    "wof:placetype":"venue"
},
  "geometry": {"coordinates":[-117.864144,33.641152],"type":"Point"}
}