{
  "type": "Feature",
  "properties": {
    "addr:full":"12305 207th St Lakewood CA 90715",
    "addr:housenumber":"12305",
    "addr:postcode":"90715",
    "addr:street":"207Th St",
    "iso:country":"US",
    "sg:address":"12305 207th St",
    "sg:city":"Lakewood",
    "sg:classifiers":[
        {
            "category":"Park",
            "type":"Public Place"
        }
    ],
    "sg:phone":"+1 562 865 6414",
    "sg:postcode":"90715",
    "sg:province":"CA",
    "wof:name":"Palms Park Community Center",
    "wof:placetype":"venue"
},
  "geometry": {"coordinates":[-118.07011799999999,33.842349],"type":"Point"}
}