{
  "type": "Feature",
  "properties": {
    "addr:full":"2036 Livingston St Oakland CA 94606",
    "addr:housenumber":"2036",
    "addr:postcode":"94606",
    "addr:street":"Livingston St",
    "iso:country":"US",
    "sg:address":"2036 Livingston St",
    "sg:city":"Oakland",
    "sg:classifiers":[
        {
            "category":"Professional",
            "subcategory":"Advertising",
            "type":"Services"
        }
    ],
    "sg:phone":"+1 510 434 0300",
    "sg:postcode":"94606",
    "sg:province":"CA",
    "sg:tags":[
        "distribution"
    ],
    "wof:name":"Bayview Distributing Inc",
    "wof:placetype":"venue"
},
  "geometry": {"coordinates":[-122.23966,37.781005],"type":"Point"}
}