{
  "type": "Feature",
  "properties": {
    "addr:full":"15146 Downey Ave Paramount CA 90723",
    "addr:housenumber":"15146",
    "addr:postcode":"90723",
    "addr:street":"Downey Ave",
    "iso:country":"US",
    "sg:address":"15146 Downey Ave",
    "sg:city":"Paramount",
    "sg:classifiers":[
        {
            "category":"Autos & Motor Vehicles",
            "subcategory":"Motorcycle Sales",
            "type":"Retail Goods"
        }
    ],
    "sg:phone":"+1 562 531 6185",
    "sg:postcode":"90723",
    "sg:province":"CA",
    "sg:website":"www.ccseats.com",
    "wof:name":"C & C Motorcycle Seats",
    "wof:placetype":"venue"
},
  "geometry": {"coordinates":[-118.151184,33.896052],"type":"Point"}
}