{
  "type": "Feature",
  "properties": {
    "addr:full":"15495 Los Gatos Boulevard Los Gatos CA 95032",
    "addr:housenumber":"15495",
    "addr:postcode":"95032",
    "addr:street":"Los Gatos Boulevard",
    "iso:country":"US",
    "sg:address":"15495 Los Gatos Boulevard",
    "sg:city":"Los Gatos",
    "sg:classifiers":[
        {
            "category":"Professional",
            "subcategory":"Lawyer & Legal Services",
            "type":"Services"
        }
    ],
    "sg:phone":"+1 408 395 9202",
    "sg:postcode":"95032",
    "sg:province":"CA",
    "sg:tags":[
        "divorce",
        "law",
        "family"
    ],
    "wof:name":"Ostrow Judith Mfcc",
    "wof:placetype":"venue"
},
  "geometry": {"coordinates":[-121.95939799999999,37.24364],"type":"Point"}
}