{
  "type": "Feature",
  "properties": {
    "addr:full":"42220 Lake Hughes Rd Lake Hughes CA 93532",
    "addr:housenumber":"42220",
    "addr:postcode":"93532",
    "addr:street":"Lake Hughes Rd",
    "iso:country":"US",
    "sg:address":"42220 Lake Hughes Rd",
    "sg:city":"Lake Hughes",
    "sg:classifiers":[
        {
            "category":"Government",
            "subcategory":"Office",
            "type":"Public Place"
        }
    ],
    "sg:phone":"+1 661 724 1314",
    "sg:postcode":"93532",
    "sg:province":"CA",
    "sg:tags":[
        "county",
        "program"
    ],
    "wof:name":"Los Angeles Cnty Education Ofc",
    "wof:placetype":"venue"
},
  "geometry": {"coordinates":[-118.455265,34.665367],"type":"Point"}
}