{
  "type": "Feature",
  "properties": {
    "iso:country":"US",
    "sg:address":"2475 Balmoral St",
    "sg:city":"Union City",
    "sg:classifiers":[
        {
            "category":"Wholesale",
            "subcategory":"Groceries",
            "type":"Manufacturing & Wholesale Goods"
        }
    ],
    "sg:phone":"+1 510 489 2765",
    "sg:postcode":"94587",
    "sg:province":"CA",
    "sg:tags":[
        "extract",
        "spice"
    ],
    "wof:name":"Watkins Quality Products",
    "wof:placetype":"venue"
},
  "geometry": {"coordinates":[-122.057994,37.600583],"type":"Point"}
}