{
  "type": "Feature",
  "properties": {
    "addr:full":"918 Lander Ave Turlock CA 95380",
    "addr:housenumber":"918",
    "addr:postcode":"95380",
    "addr:street":"Lander Ave",
    "iso:country":"US",
    "sg:address":"918 Lander Ave",
    "sg:city":"Turlock",
    "sg:classifiers":[
        {
            "category":"Utilities",
            "subcategory":"Cable",
            "type":"Services"
        }
    ],
    "sg:phone":"+1 209 667 5003",
    "sg:postcode":"95380",
    "sg:province":"CA",
    "sg:tags":[
        "television"
    ],
    "wof:name":"Charter Cmmnctons Holdings LLC",
    "wof:placetype":"venue"
},
  "geometry": {"coordinates":[-120.848894,37.48449],"type":"Point"}
}