{
  "type": "Feature",
  "properties": {
    "addr:full":"9605 Artesia Blvd Bellflower CA 90706",
    "addr:housenumber":"9605",
    "addr:postcode":"90706",
    "addr:street":"Artesia Blvd",
    "iso:country":"US",
    "sg:address":"9605 Artesia Blvd",
    "sg:city":"Bellflower",
    "sg:classifiers":[
        {
            "category":"Retail",
            "subcategory":"Car Wash",
            "type":"Services"
        }
    ],
    "sg:phone":"+1 562 634 3107",
    "sg:postcode":"90706",
    "sg:province":"CA",
    "sg:tags":[
        "polishing",
        "washing"
    ],
    "wof:name":"Willie's Detail Shop",
    "wof:placetype":"venue"
},
  "geometry": {"coordinates":[-118.128998,33.875],"type":"Point"}
}