{
  "type": "Feature",
  "properties": {
    "iso:country":"US",
    "sg:address":"2822 Elm St",
    "sg:city":"Los Angeles",
    "sg:classifiers":[
        {
            "category":"Wholesale",
            "subcategory":"Non-durable Goods",
            "type":"Manufacturing & Wholesale Goods"
        }
    ],
    "sg:phone":"+1 323 221 4652",
    "sg:postcode":"90065",
    "sg:province":"CA",
    "wof:name":"J&V Trading Co",
    "wof:placetype":"venue"
},
  "geometry": {"coordinates":[-118.23219899999999,34.098265],"type":"Point"}
}