{
  "type": "Feature",
  "properties": {
    "iso:country":"US",
    "sg:address":"2928 Via San Carlo",
    "sg:city":"Montebello",
    "sg:classifiers":[
        {
            "category":"Professional",
            "type":"Services"
        }
    ],
    "sg:phone":"+1 323 722 8170",
    "sg:postcode":"90640",
    "sg:province":"CA",
    "wof:name":"Gayane Chevchian",
    "wof:placetype":"venue"
},
  "geometry": {"coordinates":[-118.134509,34.025338],"type":"Point"}
}