{
  "type": "Feature",
  "properties": {
    "addr:full":"2928 Via San Carlo Montebello CA 90640",
    "addr:housenumber":"2928",
    "addr:postcode":"90640",
    "addr:street":"Via San Carlo",
    "iso:country":"US",
    "sg:address":"2928 Via San Carlo",
    "sg:city":"Montebello",
    "sg:classifiers":[
        {
            "category":"Professional",
            "type":"Services"
        }
    ],
    "sg:phone":"+1 323 722 8170",
    "sg:postcode":"90640",
    "sg:province":"CA",
    "wof:name":"Gayane Chevchian",
    "wof:placetype":"venue"
},
  "geometry": {"coordinates":[-118.13450899999999,34.025338],"type":"Point"}
}