{
  "type": "Feature",
  "properties": {
    "addr:full":"1726 W Verdugo Ave Burbank CA 91506",
    "addr:housenumber":"1726",
    "addr:postcode":"91506",
    "addr:street":"W Verdugo Ave",
    "iso:country":"US",
    "sg:address":"1726 W Verdugo Ave",
    "sg:city":"Burbank",
    "sg:classifiers":[
        {
            "category":"Shopping",
            "subcategory":"Beauty & Cosmetics",
            "type":"Retail Goods"
        },
        {
            "category":"Personal",
            "subcategory":"Hair Removal",
            "type":"Services"
        },
        {
            "category":"Personal",
            "subcategory":"Nail Salon",
            "type":"Services"
        }
    ],
    "sg:phone":"+1 818 848 5038",
    "sg:postcode":"91506",
    "sg:province":"CA",
    "sg:tags":[
        "supply"
    ],
    "wof:name":"Cali Nails Facial Waxing Beauty Supply & Gift",
    "wof:placetype":"venue"
},
  "geometry": {"coordinates":[-118.32399700000001,34.167801],"type":"Point"}
}