{
  "type": "Feature",
  "properties": {
    "iso:country":"US",
    "sg:address":"37803 6th St E",
    "sg:city":"Palmdale",
    "sg:classifiers":[
        {
            "category":"Manufacturing",
            "subcategory":"Food",
            "type":"Manufacturing & Wholesale Goods"
        }
    ],
    "sg:phone":"+1 661 723 0714",
    "sg:postcode":"93550",
    "sg:province":"CA",
    "sg:tags":[
        "bottler"
    ],
    "wof:name":"Coca Cola Bottling Co",
    "wof:placetype":"venue"
},
  "geometry": {"coordinates":[-118.117054,34.569099],"type":"Point"}
}