{
  "type": "Feature",
  "properties": {
    "addr:full":"977 Linda Vista Dr San Marcos CA 92078",
    "addr:housenumber":"977",
    "addr:postcode":"92078",
    "addr:street":"Linda Vista Dr",
    "iso:country":"US",
    "sg:address":"977 Linda Vista Dr",
    "sg:city":"San Marcos",
    "sg:classifiers":[
        {
            "category":"Professional",
            "type":"Services"
        }
    ],
    "sg:phone":"+1 760 744 5566",
    "sg:postcode":"92078",
    "sg:province":"CA",
    "sg:tags":[
        "spraying",
        "metal"
    ],
    "wof:name":"Hues Metal Finishing",
    "wof:placetype":"venue"
},
  "geometry": {"coordinates":[-117.18722,33.138953],"type":"Point"}
}