{
  "type": "Feature",
  "properties": {
    "iso:country":"US",
    "sg:address":"12053 1/2 Ventura Pl",
    "sg:city":"Studio City",
    "sg:classifiers":[
        {
            "category":"Shopping",
            "subcategory":"Clothing, Apparel, & Fashions",
            "type":"Retail Goods"
        }
    ],
    "sg:phone":"+1 818 766 9177",
    "sg:postcode":"91604",
    "sg:province":"CA",
    "sg:tags":[
        "children's",
        "clothing"
    ],
    "sg:website":"entertainingelephants.com",
    "wof:name":"Entertaining Elephants",
    "wof:placetype":"venue"
},
  "geometry": {"coordinates":[-118.393649,34.144113],"type":"Point"}
}