{
  "type": "Feature",
  "properties": {
    "addr:full":"421 Grand Ave Ste A South San Francisco CA 94080",
    "addr:housenumber":"421",
    "addr:postcode":"94080",
    "addr:street":"Grand Ave Ste A",
    "iso:country":"US",
    "sg:address":"421 Grand Ave Ste A",
    "sg:city":"South San Francisco",
    "sg:classifiers":[
        {
            "category":"Professional",
            "subcategory":"Lawyer & Legal Services",
            "type":"Services"
        }
    ],
    "sg:phone":"+1 650 615 0117",
    "sg:postcode":"94080",
    "sg:province":"CA",
    "wof:name":"Gendelman Sherry Atty",
    "wof:placetype":"venue"
},
  "geometry": {"coordinates":[-122.413439,37.655591],"type":"Point"}
}