{
  "type": "Feature",
  "properties": {
    "addr:full":"53585 Dogwood Dr North Fork CA 93643",
    "addr:housenumber":"53585",
    "addr:postcode":"93643",
    "addr:street":"Dogwood Dr",
    "iso:country":"US",
    "sg:address":"53585 Dogwood Dr",
    "sg:city":"North Fork",
    "sg:classifiers":[
        {
            "category":"Government",
            "subcategory":"Office",
            "type":"Public Place"
        }
    ],
    "sg:phone":"+1 559 250 4813",
    "sg:postcode":"93643",
    "sg:province":"CA",
    "sg:tags":[
        "contracting"
    ],
    "wof:name":"Carol Desilva",
    "wof:placetype":"venue"
},
  "geometry": {"coordinates":[-119.56889200000001,37.194914],"type":"Point"}
}