{
  "type": "Feature",
  "properties": {
    "addr:full":"486 Marsh St San Luis Obispo CA 93401",
    "addr:housenumber":"486",
    "addr:postcode":"93401",
    "addr:street":"Marsh St",
    "iso:country":"US",
    "sg:address":"486 Marsh St",
    "sg:city":"San Luis Obispo",
    "sg:classifiers":[
        {
            "category":"Building & Trades",
            "subcategory":"Equipment Rental",
            "type":"Services"
        }
    ],
    "sg:phone":"+1 805 596 0511",
    "sg:postcode":"93401",
    "sg:province":"CA",
    "sg:tags":[
        "leasing"
    ],
    "wof:name":"Hurst Financial",
    "wof:placetype":"venue"
},
  "geometry": {"coordinates":[-120.66737999999999,35.275892],"type":"Point"}
}