{
  "type": "Feature",
  "properties": {
    "addr:full":"1721 Oxford Ave Clovis CA 93612",
    "addr:housenumber":"1721",
    "addr:postcode":"93612",
    "addr:street":"Oxford Ave",
    "iso:country":"US",
    "sg:address":"1721 Oxford Ave",
    "sg:city":"Clovis",
    "sg:classifiers":[
        {
            "category":"Retail",
            "subcategory":"Repair Shop",
            "type":"Services"
        }
    ],
    "sg:phone":"+1 559 299 5450",
    "sg:postcode":"93612",
    "sg:province":"CA",
    "sg:tags":[
        "plumbing",
        "drain",
        "cleaning",
        "sewer"
    ],
    "wof:name":"Rodeo Rooter",
    "wof:placetype":"venue"
},
  "geometry": {"coordinates":[-119.70689900000001,36.811403],"type":"Point"}
}