{
  "type": "Feature",
  "properties": {
    "iso:country":"US",
    "sg:address":"250 Newport Center Dr",
    "sg:city":"Newport Beach",
    "sg:classifiers":[
        {
            "category":"Real Estate",
            "subcategory":"Real Estate Agent",
            "type":"Services"
        }
    ],
    "sg:phone":"+1 949 833 2650",
    "sg:postcode":"92660",
    "sg:province":"CA",
    "wof:name":"Tarantello & Assoc",
    "wof:placetype":"venue"
},
  "geometry": {"coordinates":[-117.872984,33.613952],"type":"Point"}
}