{
  "type": "Feature",
  "properties": {
    "addr:full":"643 Arundel Rd Goleta CA 93117",
    "addr:housenumber":"643",
    "addr:postcode":"93117",
    "addr:street":"Arundel Rd",
    "iso:country":"US",
    "sg:address":"643 Arundel Rd",
    "sg:city":"Goleta",
    "sg:classifiers":[
        {
            "category":"Building & Trades",
            "subcategory":"Construction",
            "type":"Services"
        }
    ],
    "sg:phone":"+1 805 966 9991",
    "sg:postcode":"93117",
    "sg:province":"CA",
    "sg:tags":[
        "designer",
        "contractor",
        "merchandise",
        "dealer",
        "pool",
        "swimming"
    ],
    "wof:name":"Channel Islands Custom Pools",
    "wof:placetype":"venue"
},
  "geometry": {"coordinates":[-119.82490199999999,34.450194],"type":"Point"}
}