{
  "type": "Feature",
  "properties": {
    "iso:country":"US",
    "sg:address":"1655 N Texas St",
    "sg:city":"Fairfield",
    "sg:classifiers":[
        {
            "category":"Shopping",
            "subcategory":"Clothing, Apparel, & Fashions",
            "type":"Retail Goods"
        }
    ],
    "sg:phone":"+1 707 422 7060",
    "sg:postcode":"94533",
    "sg:province":"CA",
    "sg:tags":[
        "tailor"
    ],
    "wof:name":"Kwong's Tailor Shop",
    "wof:placetype":"venue"
},
  "geometry": {"coordinates":[-122.034219,38.259964],"type":"Point"}
}