{
  "type": "Feature",
  "properties": {
    "addr:full":"911 E 22nd St Los Angeles CA 90011",
    "addr:housenumber":"911",
    "addr:postcode":"90011",
    "addr:street":"E 22Nd St",
    "iso:country":"US",
    "sg:address":"911 E 22nd St",
    "sg:city":"Los Angeles",
    "sg:classifiers":[
        {
            "category":"Freight",
            "type":"Transportation"
        }
    ],
    "sg:phone":"+1 323 296 8491",
    "sg:postcode":"90011",
    "sg:province":"CA",
    "sg:tags":[
        "operator",
        "local",
        "trucking"
    ],
    "wof:name":"Jaf Trucking",
    "wof:placetype":"venue"
},
  "geometry": {"coordinates":[-118.255398,34.023307],"type":"Point"}
}