{
  "type": "Feature",
  "properties": {
    "addr:full":"5006 Mountain Lakes Blvd Redding CA 96003",
    "addr:housenumber":"5006",
    "addr:postcode":"96003",
    "addr:street":"Mountain Lakes Blvd",
    "iso:country":"US",
    "sg:address":"5006 Mountain Lakes Blvd",
    "sg:city":"Redding",
    "sg:classifiers":[
        {
            "category":"Wholesale",
            "subcategory":"Machinery & Supplies",
            "type":"Manufacturing & Wholesale Goods"
        }
    ],
    "sg:phone":"+1 530 243 6353",
    "sg:postcode":"96003",
    "sg:province":"CA",
    "sg:tags":[
        "equipment",
        "industrial"
    ],
    "wof:name":"Beckers Forklift Parts",
    "wof:placetype":"venue"
},
  "geometry": {"coordinates":[-122.381477,40.632341],"type":"Point"}
}