{
  "type": "Feature",
  "properties": {
    "addr:full":"130 Cambridge Ln San Bruno CA 94066",
    "addr:housenumber":"130",
    "addr:postcode":"94066",
    "addr:street":"Cambridge Ln",
    "iso:country":"US",
    "sg:address":"130 Cambridge Ln",
    "sg:city":"San Bruno",
    "sg:classifiers":[
        {
            "category":"Social Services",
            "subcategory":"Child Care",
            "type":"Services"
        }
    ],
    "sg:phone":"+1 650 876 1023",
    "sg:postcode":"94066",
    "sg:province":"CA",
    "wof:name":"Champions Program",
    "wof:placetype":"venue"
},
  "geometry": {"coordinates":[-122.435734,37.612849],"type":"Point"}
}