{
  "type": "Feature",
  "properties": {
    "iso:country":"US",
    "sg:address":"6042 Magnolia Ave",
    "sg:city":"Riverside",
    "sg:classifiers":[
        {
            "category":"Personal",
            "subcategory":"Beauty Salon",
            "type":"Services"
        },
        {
            "category":"Personal",
            "subcategory":"Nail Salon",
            "type":"Services"
        }
    ],
    "sg:phone":"+1 951 682 5598",
    "sg:postcode":"92506",
    "sg:province":"CA",
    "wof:name":"Julia's Premier Beauty Salon & Permanet Makeup",
    "wof:placetype":"venue"
},
  "geometry": {"coordinates":[-117.392163,33.960323],"type":"Point"}
}