{
  "type": "Feature",
  "properties": {
    "iso:country":"US",
    "sg:address":"10924 Weyburn Ave",
    "sg:city":"Los Angeles",
    "sg:classifiers":[
        {
            "category":"Freight",
            "type":"Transportation"
        },
        {
            "category":"Professional",
            "subcategory":"Printing & Photocopies",
            "type":"Services"
        }
    ],
    "sg:phone":"+1 310 443 5501",
    "sg:postcode":"90024",
    "sg:province":"CA",
    "sg:tags":[
        "shipping"
    ],
    "sg:website":"www.fedex.com/us/office/",
    "wof:name":"FedEx Office Print & Ship Center",
    "wof:placetype":"venue"
},
  "geometry": {"coordinates":[-118.446275,34.062334],"type":"Point"}
}