{
  "type": "Feature",
  "properties": {
    "iso:country":"US",
    "sg:address":"13383 Tall Oak Pl",
    "sg:city":"Nevada City",
    "sg:classifiers":[
        {
            "category":"Manufacturing",
            "subcategory":"Furniture",
            "type":"Manufacturing & Wholesale Goods"
        },
        {
            "category":"Home & Garden",
            "subcategory":"Home Furnishings",
            "type":"Retail Goods"
        }
    ],
    "sg:phone":"+1 530 533 5581",
    "sg:postcode":"95959",
    "sg:province":"CA",
    "sg:tags":[
        "venetian",
        "blind",
        "drapery",
        "mfg"
    ],
    "wof:name":"Howard's Shades",
    "wof:placetype":"venue"
},
  "geometry": {"coordinates":[-120.94002999999999,39.283326],"type":"Point"}
}