{
  "type": "Feature",
  "properties": {
    "iso:country":"US",
    "sg:address":"4201 Wilshire Blvd Ste 518",
    "sg:city":"Los Angeles",
    "sg:classifiers":[
        {
            "category":"Building & Trades",
            "subcategory":"Construction",
            "type":"Services"
        }
    ],
    "sg:phone":"+1 323 939 4540",
    "sg:postcode":"90010",
    "sg:province":"CA",
    "sg:tags":[
        "contractor"
    ],
    "wof:name":"Pacific Coast Home Improvement",
    "wof:placetype":"venue"
},
  "geometry": {"coordinates":[-118.319227,34.06219],"type":"Point"}
}