{
  "type": "Feature",
  "properties": {
    "addr:full":"135 S 5th Ave Oakdale CA 95361",
    "addr:housenumber":"135",
    "addr:postcode":"95361",
    "addr:street":"S 5Th Ave",
    "iso:country":"US",
    "sg:address":"135 S 5th Ave",
    "sg:city":"Oakdale",
    "sg:classifiers":[
        {
            "category":"Building & Trades",
            "subcategory":"Construction",
            "type":"Services"
        }
    ],
    "sg:phone":"+1 209 346 6728",
    "sg:postcode":"95361",
    "sg:province":"CA",
    "sg:tags":[
        "dry wall",
        "contractor"
    ],
    "wof:name":"Spray Rite",
    "wof:placetype":"venue"
},
  "geometry": {"coordinates":[-120.843711,37.767058],"type":"Point"}
}