{
  "type": "Feature",
  "properties": {
    "iso:country":"US",
    "sg:address":"711 W College St",
    "sg:city":"Los Angeles",
    "sg:classifiers":[
        {
            "category":"Health Services",
            "subcategory":"Doctor",
            "type":"Services"
        }
    ],
    "sg:phone":"+1 213 626 8338",
    "sg:postcode":"90012",
    "sg:province":"CA",
    "sg:tags":[
        "physician",
        "surgeon"
    ],
    "wof:name":"Osmund T Chan MD",
    "wof:placetype":"venue"
},
  "geometry": {"coordinates":[-118.241998,34.065646],"type":"Point"}
}