{
  "type": "Feature",
  "properties": {
    "iso:country":"US",
    "sg:address":"3082 Galveston St",
    "sg:city":"Simi Valley",
    "sg:classifiers":[
        {
            "category":"Building & Trades",
            "subcategory":"Plumbing",
            "type":"Services"
        }
    ],
    "sg:phone":"+1 818 599 8329",
    "sg:postcode":"93063",
    "sg:province":"CA",
    "sg:tags":[
        "mechanical",
        "contractor"
    ],
    "wof:name":"D & D Mechanical",
    "wof:placetype":"venue"
},
  "geometry": {"coordinates":[-118.706502,34.290379],"type":"Point"}
}