{
  "type": "Feature",
  "properties": {
    "iso:country":"US",
    "sg:address":"2281 Lake Ave",
    "sg:city":"Altadena",
    "sg:classifiers":[
        {
            "category":"Bakery",
            "type":"Food & Drink"
        }
    ],
    "sg:phone":"+1 626 794 3555",
    "sg:postcode":"91001",
    "sg:province":"CA",
    "wof:name":"Dutch Oven Bakery",
    "wof:placetype":"venue"
},
  "geometry": {"coordinates":[-118.13154400000001,34.185337],"type":"Point"}
}