{
  "type": "Feature",
  "properties": {
    "iso:country":"US",
    "sg:address":"2424 Parkwood Dr",
    "sg:city":"Sacramento",
    "sg:classifiers":[
        {
            "category":"Building & Trades",
            "subcategory":"Landscaping Services",
            "type":"Services"
        }
    ],
    "sg:phone":"+1 916 488 9313",
    "sg:postcode":"95825",
    "sg:province":"CA",
    "wof:name":"Bladerunner Lawn Care",
    "wof:placetype":"venue"
},
  "geometry": {"coordinates":[-121.398597,38.61024],"type":"Point"}
}