{
  "type": "Feature",
  "properties": {
    "iso:country":"US",
    "sg:address":"935 Riverside Ave",
    "sg:city":"Paso Robles",
    "sg:classifiers":[
        {
            "category":"Insurance",
            "subcategory":"Insurance Agent",
            "type":"Services"
        }
    ],
    "sg:phone":"+1 805 239 9066",
    "sg:postcode":"93446",
    "sg:province":"CA",
    "wof:name":"GSP Insurance",
    "wof:placetype":"venue"
},
  "geometry": {"coordinates":[-120.686691,35.624275],"type":"Point"}
}