{
  "type": "Feature",
  "properties": {
    "iso:country":"US",
    "sg:address":"2391 Telegraph Ave",
    "sg:city":"Berkeley",
    "sg:classifiers":[
        {
            "category":"Shopping",
            "subcategory":"Clothing, Apparel, & Fashions",
            "type":"Retail Goods"
        }
    ],
    "sg:phone":"+1 510 704 1363",
    "sg:postcode":"94704",
    "sg:province":"CA",
    "wof:name":"Royalty Couture",
    "wof:placetype":"venue"
},
  "geometry": {"coordinates":[-122.25885599999999,37.867125],"type":"Point"}
}