{
  "type": "Feature",
  "properties": {
    "iso:country":"US",
    "sg:address":"12206 Mulberry Ave",
    "sg:city":"Chino",
    "sg:classifiers":[
        {
            "category":"Building & Trades",
            "subcategory":"Construction",
            "type":"Services"
        }
    ],
    "sg:phone":"+1 909 983 8199",
    "sg:postcode":"91710",
    "sg:province":"CA",
    "sg:tags":[
        "steel",
        "erection",
        "structural"
    ],
    "wof:name":"Teague Construction",
    "wof:placetype":"venue"
},
  "geometry": {"coordinates":[-117.67469,34.031217],"type":"Point"}
}