{
  "type": "Feature",
  "properties": {
    "iso:country":"US",
    "sg:address":"484 Meadowlark St",
    "sg:city":"Livermore",
    "sg:classifiers":[
        {
            "category":"Retail",
            "subcategory":"Auto Repair",
            "type":"Services"
        }
    ],
    "sg:phone":"+1 925 443 8468",
    "sg:postcode":"94551",
    "sg:province":"CA",
    "sg:tags":[
        "glass",
        "coating",
        "tinting"
    ],
    "wof:name":"N Detail",
    "wof:placetype":"venue"
},
  "geometry": {"coordinates":[-121.78858200000001,37.683073],"type":"Point"}
}