{
  "type": "Feature",
  "properties": {
    "addr:full":"2001 S Main St Santa Ana CA 92707",
    "addr:housenumber":"2001",
    "addr:postcode":"92707",
    "addr:street":"S Main St",
    "iso:country":"US",
    "sg:address":"2001 S Main St",
    "sg:city":"Santa Ana",
    "sg:classifiers":[
        {
            "category":"Banks & Credit Unions",
            "subcategory":"Bank",
            "type":"Services"
        },
        {
            "category":"Banks & Credit Unions",
            "subcategory":"Financial Services",
            "type":"Services"
        }
    ],
    "sg:phone":"+1 714 708 6905",
    "sg:postcode":"92707",
    "sg:province":"CA",
    "sg:tags":[
        "broker",
        "mortgage"
    ],
    "sg:website":"www.bankofamerica.com",
    "wof:name":"Bank of America",
    "wof:placetype":"venue"
},
  "geometry": {"coordinates":[-117.86768499999999,33.722448],"type":"Point"}
}