{
  "type": "Feature",
  "properties": {
    "addr:full":"9852 Katella Ave Anaheim CA 92804",
    "addr:housenumber":"9852",
    "addr:postcode":"92804",
    "addr:street":"Katella Ave",
    "iso:country":"US",
    "sg:address":"9852 Katella Ave",
    "sg:city":"Anaheim",
    "sg:classifiers":[
        {
            "category":"Professional",
            "subcategory":"Computer Services",
            "type":"Services"
        }
    ],
    "sg:phone":"+1 714 537 3372",
    "sg:postcode":"92804",
    "sg:province":"CA",
    "sg:tags":[
        "related"
    ],
    "wof:name":"Calculus",
    "wof:placetype":"venue"
},
  "geometry": {"coordinates":[-117.96144099999999,33.803026],"type":"Point"}
}