{
  "type": "Feature",
  "properties": {
    "iso:country":"US",
    "sg:address":"3914 Murphy Canyon Rd",
    "sg:city":"San Diego",
    "sg:classifiers":[
        {
            "category":"Banks & Credit Unions",
            "subcategory":"Bank",
            "type":"Services"
        }
    ],
    "sg:phone":"+1 858 495 1888",
    "sg:postcode":"92123",
    "sg:province":"CA",
    "sg:tags":[
        "loan",
        "real estate"
    ],
    "sg:website":"www.sdloan.com",
    "wof:name":"Old Mission Mortgage Inc",
    "wof:placetype":"venue"
},
  "geometry": {"coordinates":[-117.11739,32.821312],"type":"Point"}
}