{
  "type": "Feature",
  "properties": {
    "iso:country":"US",
    "sg:address":"9107 Garfield Ave",
    "sg:city":"Fountain Valley",
    "sg:classifiers":[
        {
            "category":"Health Services",
            "subcategory":"Optometrist",
            "type":"Services"
        }
    ],
    "sg:phone":"+1 714 963 2020",
    "sg:postcode":"92708",
    "sg:province":"CA",
    "sg:tags":[
        "laser",
        "surgery/lasik",
        "eye",
        "ophthalmologist"
    ],
    "sg:website":"www.drgoldstone2020.com",
    "wof:name":"Dr. Goldstone Vision Centers",
    "wof:placetype":"venue"
},
  "geometry": {"coordinates":[-117.969297,33.686852],"type":"Point"}
}