{
  "type": "Feature",
  "properties": {
    "addr:full":"35300 State Hwy 41 Coarsegold CA 93614",
    "addr:housenumber":"35300",
    "addr:postcode":"93614",
    "addr:street":"State Hwy 41",
    "iso:country":"US",
    "sg:address":"35300 State Hwy 41",
    "sg:city":"Coarsegold",
    "sg:classifiers":[
        {
            "category":"Organizations",
            "subcategory":"Religious Organization",
            "type":"Services"
        }
    ],
    "sg:phone":"+1 559 658 8411",
    "sg:postcode":"93614",
    "sg:province":"CA",
    "sg:tags":[
        "church"
    ],
    "sg:website":"www.stoneycreekbaptistchurch.org",
    "wof:name":"Stoney Creek Baptist Church",
    "wof:placetype":"venue"
},
  "geometry": {"coordinates":[-119.701165,37.261428],"type":"Point"}
}