{
  "type": "Feature",
  "properties": {
    "iso:country":"US",
    "sg:address":"12333 S Van Ness Ave",
    "sg:city":"Hawthorne",
    "sg:classifiers":[
        {
            "category":"Freight",
            "type":"Transportation"
        }
    ],
    "sg:phone":"+1 323 754 8613",
    "sg:postcode":"90250",
    "sg:province":"CA",
    "sg:tags":[
        "forwarding",
        "arrangement"
    ],
    "sg:website":"http://www.cargoexpressi.com",
    "wof:name":"BTX Air Express",
    "wof:placetype":"venue"
},
  "geometry": {"coordinates":[-118.31783299999999,33.921255],"type":"Point"}
}