{
  "type": "Feature",
  "properties": {
    "iso:country":"US",
    "sg:address":"44439 17th St W",
    "sg:city":"Lancaster",
    "sg:classifiers":[
        {
            "category":"Health Services",
            "subcategory":"Health Practitioner",
            "type":"Services"
        }
    ],
    "sg:phone":"+1 661 948 0023",
    "sg:postcode":"93534",
    "sg:province":"CA",
    "sg:tags":[
        "acupuncture"
    ],
    "wof:name":"Oriental Health Care Svc",
    "wof:placetype":"venue"
},
  "geometry": {"coordinates":[-118.161334,34.69006],"type":"Point"}
}