{
  "type": "Feature",
  "properties": {
    "iso:country":"US",
    "sg:address":"161 Berth",
    "sg:city":"Wilmington",
    "sg:classifiers":[
        {
            "category":"Government",
            "subcategory":"Office",
            "type":"Public Place"
        }
    ],
    "sg:phone":"+1 310 732 3890",
    "sg:postcode":"90744",
    "sg:province":"CA",
    "sg:tags":[
        "village"
    ],
    "wof:name":"Purchasing Dept",
    "wof:placetype":"venue"
},
  "geometry": {"coordinates":[-118.26207100000001,33.761653],"type":"Point"}
}