{
  "type": "Feature",
  "properties": {
    "addr:full":"9835 Pearmain St Oakland CA 94603",
    "addr:housenumber":"9835",
    "addr:postcode":"94603",
    "addr:street":"Pearmain St",
    "iso:country":"US",
    "sg:address":"9835 Pearmain St",
    "sg:city":"Oakland",
    "sg:classifiers":[
        {
            "category":"Retail",
            "subcategory":"Auto Rental",
            "type":"Services"
        }
    ],
    "sg:phone":"+1 510 638 6877",
    "sg:postcode":"94603",
    "sg:province":"CA",
    "sg:tags":[
        "renting",
        "truck",
        "leasing"
    ],
    "wof:name":"U-Haul Co",
    "wof:placetype":"venue"
},
  "geometry": {"coordinates":[-122.180407,37.737788],"type":"Point"}
}