{
  "type": "Feature",
  "properties": {
    "iso:country":"US",
    "sg:address":"1607 Sepulveda Blvd",
    "sg:city":"Torrance",
    "sg:classifiers":[
        {
            "category":"Restaurant",
            "type":"Food & Drink"
        }
    ],
    "sg:phone":"+1 310 534 3480",
    "sg:postcode":"90510",
    "sg:province":"CA",
    "sg:tags":[
        "korean"
    ],
    "sg:website":"www.bcdtofu.com",
    "wof:name":"BCD Tofu House",
    "wof:placetype":"venue"
},
  "geometry": {"coordinates":[-118.306803,33.81636],"type":"Point"}
}