{
  "type": "Feature",
  "properties": {
    "iso:country":"US",
    "sg:address":"1718 Monrovia Ave",
    "sg:city":"Costa Mesa",
    "sg:classifiers":[
        {
            "category":"Organizations",
            "subcategory":"Non-profit Organization",
            "type":"Services"
        }
    ],
    "sg:phone":"+1 949 645 0075",
    "sg:postcode":"92627",
    "sg:province":"CA",
    "sg:tags":[
        "service/non-profit",
        "community"
    ],
    "sg:website":"www.mikacdc.org",
    "wof:name":"MIKA CDC",
    "wof:placetype":"venue"
},
  "geometry": {"coordinates":[-117.935186,33.636238],"type":"Point"}
}