{
  "type": "Feature",
  "properties": {
    "addr:full":"826 Main St Martinez CA 94553",
    "addr:housenumber":"826",
    "addr:postcode":"94553",
    "addr:street":"Main St",
    "iso:country":"US",
    "sg:address":"826 Main St",
    "sg:city":"Martinez",
    "sg:classifiers":[
        {
            "category":"Government",
            "subcategory":"Office",
            "type":"Public Place"
        }
    ],
    "sg:phone":"+1 925 646 2517",
    "sg:postcode":"94553",
    "sg:province":"CA",
    "wof:name":"Contra Costa Birth Certifcates",
    "wof:placetype":"venue"
},
  "geometry": {"coordinates":[-122.13509999999999,38.017954],"type":"Point"}
}