{
  "type": "Feature",
  "properties": {
    "addr:full":"1350 41st Ave Capitola CA 95010",
    "addr:housenumber":"1350",
    "addr:postcode":"95010",
    "addr:street":"41St Ave",
    "iso:country":"US",
    "sg:address":"1350 41st Ave",
    "sg:city":"Capitola",
    "sg:classifiers":[
        {
            "category":"Organizations",
            "subcategory":"Non-profit Organization",
            "type":"Services"
        }
    ],
    "sg:phone":"+1 831 423 8755",
    "sg:postcode":"95010",
    "sg:province":"CA",
    "wof:name":"Lighthouse Venture Forum",
    "wof:placetype":"venue"
},
  "geometry": {"coordinates":[-121.964825,36.97058],"type":"Point"}
}