{
  "type": "Feature",
  "properties": {
    "addr:full":"340 Merrill Rd San Juan Bautista CA 95045",
    "addr:housenumber":"340",
    "addr:postcode":"juan bautista ca 95045",
    "addr:street":"Merrill Rd",
    "iso:country":"US",
    "sg:address":"340 Merrill Rd",
    "sg:city":"San Juan Bautista",
    "sg:classifiers":[
        {
            "category":"Wholesale",
            "subcategory":"Durable Goods & Equipment",
            "type":"Manufacturing & Wholesale Goods"
        }
    ],
    "sg:phone":"+1 831 623 4572",
    "sg:postcode":"95045",
    "sg:province":"CA",
    "wof:name":"Heavenly Quilting & Supplies",
    "wof:placetype":"venue"
},
  "geometry": {"coordinates":[-121.585444,36.865364],"type":"Point"}
}