{
  "type": "Feature",
  "properties": {
    "iso:country":"US",
    "sg:address":"17915 Indian Peak Rd",
    "sg:city":"Cottonwood",
    "sg:classifiers":[
        {
            "category":"Professional",
            "type":"Services"
        }
    ],
    "sg:phone":"+1 530 347 5028",
    "sg:postcode":"96022",
    "sg:province":"CA",
    "wof:name":"Donna Boots",
    "wof:placetype":"venue"
},
  "geometry": {"coordinates":[-122.37051,40.286623],"type":"Point"}
}