{
  "type": "Feature",
  "properties": {
    "addr:full":"923 E 3rd St Ste 115 Los Angeles CA 90013",
    "addr:housenumber":"923",
    "addr:postcode":"90013",
    "addr:street":"E 3Rd St Ste 115",
    "iso:country":"US",
    "sg:address":"923 E 3rd St Ste 115",
    "sg:city":"Los Angeles",
    "sg:classifiers":[
        {
            "category":"Real Estate",
            "subcategory":"Architect",
            "type":"Services"
        }
    ],
    "sg:phone":"+1 213 625 1995",
    "sg:postcode":"90013",
    "sg:province":"CA",
    "wof:name":"Quatro Design Group",
    "wof:placetype":"venue"
},
  "geometry": {"coordinates":[-118.234111,34.046213],"type":"Point"}
}