{
  "type": "Feature",
  "properties": {
    "iso:country":"US",
    "sg:address":"210 N Palisade Dr",
    "sg:city":"Santa Maria",
    "sg:classifiers":[
        {
            "category":"Health Services",
            "subcategory":"Doctor",
            "type":"Services"
        }
    ],
    "sg:phone":"+1 805 928 5851",
    "sg:postcode":"93454",
    "sg:province":"CA",
    "sg:tags":[
        "physician",
        "surgeon"
    ],
    "wof:name":"Ram C Dandillaya MD",
    "wof:placetype":"venue"
},
  "geometry": {"coordinates":[-120.41213999999999,34.954233],"type":"Point"}
}