{
  "type": "Feature",
  "properties": {
    "iso:country":"US",
    "sg:address":"310 S Robertson Boulevard",
    "sg:city":"Los Angeles",
    "sg:classifiers":[
        {
            "category":"Building & Trades",
            "subcategory":"Locksmith",
            "type":"Services"
        }
    ],
    "sg:phone":"+1 310 405 6311",
    "sg:postcode":"90048",
    "sg:province":"CA",
    "sg:tags":[
        "key"
    ],
    "wof:name":"7 Day Emergency Locks and Locksmith",
    "wof:placetype":"venue"
},
  "geometry": {"coordinates":[-118.383906,34.072864],"type":"Point"}
}