{
  "type": "Feature",
  "properties": {
    "iso:country":"US",
    "sg:address":"927 Armory Rd",
    "sg:city":"Barstow",
    "sg:classifiers":[
        {
            "category":"Health Services",
            "subcategory":"Doctor",
            "type":"Services"
        }
    ],
    "sg:phone":"+1 760 252 4488",
    "sg:postcode":"92311",
    "sg:province":"CA",
    "sg:tags":[
        "dentist"
    ],
    "wof:name":"Asad Salman & Assoc",
    "wof:placetype":"venue"
},
  "geometry": {"coordinates":[-117.01454099999999,34.884121],"type":"Point"}
}