{
  "type": "Feature",
  "properties": {
    "addr:full":"432 Gilcrest Ave Vallejo CA 94591",
    "addr:housenumber":"432",
    "addr:postcode":"94591",
    "addr:street":"Gilcrest Ave",
    "iso:country":"US",
    "sg:address":"432 Gilcrest Ave",
    "sg:city":"Vallejo",
    "sg:classifiers":[
        {
            "category":"Social Services",
            "subcategory":"Adult Care",
            "type":"Services"
        }
    ],
    "sg:phone":"+1 707 644 6968",
    "sg:postcode":"94591",
    "sg:province":"CA",
    "sg:tags":[
        "residential",
        "intermediate",
        "facility"
    ],
    "wof:name":"Williams Board & Care Facility",
    "wof:placetype":"venue"
},
  "geometry": {"coordinates":[-122.21965299999999,38.082744],"type":"Point"}
}