{
  "type": "Feature",
  "properties": {
    "addr:full":"626 Cecil Ave Delano CA 93215",
    "addr:housenumber":"626",
    "addr:postcode":"93215",
    "addr:street":"Cecil Ave",
    "iso:country":"US",
    "sg:address":"626 Cecil Ave",
    "sg:city":"Delano",
    "sg:classifiers":[
        {
            "category":"Autos & Motor Vehicles",
            "subcategory":"Automobile Sales",
            "type":"Retail Goods"
        }
    ],
    "sg:phone":"+1 661 725 7701",
    "sg:postcode":"93215",
    "sg:province":"CA",
    "sg:tags":[
        "car",
        "dealer"
    ],
    "wof:name":"Family Chrysler Jeep Dodge",
    "wof:placetype":"venue"
},
  "geometry": {"coordinates":[-119.251105,35.775795],"type":"Point"}
}