{
  "type": "Feature",
  "properties": {
    "iso:country":"US",
    "sg:address":"13425 Glenoaks Blvd",
    "sg:city":"Sylmar",
    "sg:classifiers":[
        {
            "category":"Organizations",
            "subcategory":"Religious Organization",
            "type":"Services"
        }
    ],
    "sg:phone":"+1 818 362 7700",
    "sg:postcode":"91342",
    "sg:province":"CA",
    "sg:tags":[
        "church"
    ],
    "wof:name":"Church Of The Foothills",
    "wof:placetype":"venue"
},
  "geometry": {"coordinates":[-118.46332,34.317929],"type":"Point"}
}