{
  "type": "Feature",
  "properties": {
    "addr:full":"602 Hayes St San Francisco CA 94102",
    "addr:housenumber":"602",
    "addr:postcode":"94102",
    "addr:street":"Hayes St",
    "iso:country":"US",
    "sg:address":"602 Hayes St",
    "sg:city":"San Francisco",
    "sg:classifiers":[
        {
            "category":"Restaurant",
            "type":"Food & Drink"
        }
    ],
    "sg:phone":"+1 415 241 1900",
    "sg:postcode":"94102",
    "sg:province":"CA",
    "sg:website":"www.terrabrazilissf.com",
    "wof:name":"Tandoori Grill",
    "wof:placetype":"venue"
},
  "geometry": {"coordinates":[-122.427899,37.776332],"type":"Point"}
}