{
  "type": "Feature",
  "properties": {
    "iso:country":"US",
    "sg:address":"9631 de Soto Ave",
    "sg:city":"Chatsworth",
    "sg:classifiers":[
        {
            "category":"Manufacturing",
            "subcategory":"Tools & Machinery",
            "type":"Manufacturing & Wholesale Goods"
        }
    ],
    "sg:phone":"+1 818 885 5010",
    "sg:postcode":"91311",
    "sg:province":"CA",
    "sg:tags":[
        "lamp"
    ],
    "wof:name":"Hallmark Manufacturing",
    "wof:placetype":"venue"
},
  "geometry": {"coordinates":[-118.588622,34.245869],"type":"Point"}
}