{
  "type": "Feature",
  "properties": {
    "addr:full":"2560 Mission College Boulevard Santa Clara CA 95054",
    "addr:housenumber":"2560",
    "addr:postcode":"95054",
    "addr:street":"Mission College Boulevard",
    "iso:country":"US",
    "sg:address":"2560 Mission College Boulevard",
    "sg:city":"Santa Clara",
    "sg:classifiers":[
        {
            "category":"Banks & Credit Unions",
            "subcategory":"Financial Services",
            "type":"Services"
        }
    ],
    "sg:phone":"+1 408 452 2800",
    "sg:postcode":"95054",
    "sg:province":"CA",
    "sg:tags":[
        "broker",
        "mortgage"
    ],
    "wof:name":"Hcl Finance",
    "wof:placetype":"venue"
},
  "geometry": {"coordinates":[-121.970088,37.389027],"type":"Point"}
}