{
  "type": "Feature",
  "properties": {
    "iso:country":"US",
    "sg:address":"3801 Howe St 2nd floor",
    "sg:city":"Oakland",
    "sg:classifiers":[
        {
            "category":"Community Center",
            "type":"Public Place"
        }
    ],
    "sg:phone":"+1 510 752 6202",
    "sg:postcode":"94611",
    "sg:province":"CA",
    "sg:tags":[
        "medical"
    ],
    "sg:website":"mydoctor.kaiserpermanente.org/nc...",
    "wof:name":"Kaiser Oakland Injection Clinic",
    "wof:placetype":"venue"
},
  "geometry": {"coordinates":[-122.256013,37.824942],"type":"Point"}
}