{
  "type": "Feature",
  "properties": {
    "addr:full":"986 Airway Ct Santa Rosa CA 95403",
    "addr:housenumber":"986",
    "addr:postcode":"95403",
    "addr:street":"Airway Ct",
    "iso:country":"US",
    "sg:address":"986 Airway Ct",
    "sg:city":"Santa Rosa",
    "sg:classifiers":[
        {
            "category":"Wholesale",
            "subcategory":"Stationery",
            "type":"Manufacturing & Wholesale Goods"
        }
    ],
    "sg:phone":"+1 707 542 7012",
    "sg:postcode":"95403",
    "sg:province":"CA",
    "sg:tags":[
        "personal",
        "product",
        "industrial",
        "paper"
    ],
    "wof:name":"Paper Plus",
    "wof:placetype":"venue"
},
  "geometry": {"coordinates":[-122.737881,38.474468],"type":"Point"}
}