{
  "type": "Feature",
  "properties": {
    "addr:full":"119 E Broadway Vista CA 92084",
    "addr:housenumber":"119",
    "addr:postcode":"92084",
    "addr:street":"E Broadway",
    "iso:country":"US",
    "sg:address":"119 E Broadway",
    "sg:city":"Vista",
    "sg:classifiers":[
        {
            "category":"Bars & Pubs",
            "type":"Food & Drink"
        }
    ],
    "sg:phone":"+1 760 724 0510",
    "sg:postcode":"92084",
    "sg:province":"CA",
    "sg:tags":[
        "lounge",
        "cocktail"
    ],
    "wof:name":"Smitty's Downtown",
    "wof:placetype":"venue"
},
  "geometry": {"coordinates":[-117.24197599999999,33.201012],"type":"Point"}
}