{
  "type": "Feature",
  "properties": {
    "iso:country":"US",
    "sg:address":"3031 Lemon Grove Ave",
    "sg:city":"Lemon Grove",
    "sg:classifiers":[
        {
            "category":"Personal",
            "type":"Services"
        }
    ],
    "sg:phone":"+1 619 698 3344",
    "sg:postcode":"91945",
    "sg:province":"CA",
    "sg:tags":[
        "therapist",
        "massage"
    ],
    "wof:name":"Donald Eighmy",
    "wof:placetype":"venue"
},
  "geometry": {"coordinates":[-117.030687,32.738412],"type":"Point"}
}