{
  "type": "Feature",
  "properties": {
    "addr:full":"14513 7th St Victorville CA 92395",
    "addr:housenumber":"14513",
    "addr:postcode":"92395",
    "addr:street":"7Th St",
    "iso:country":"US",
    "sg:address":"14513 7th St",
    "sg:city":"Victorville",
    "sg:classifiers":[
        {
            "category":"Bars & Pubs",
            "type":"Food & Drink"
        }
    ],
    "sg:phone":"+1 760 245 8125",
    "sg:postcode":"92395",
    "sg:province":"CA",
    "wof:name":"Phantom Room",
    "wof:placetype":"venue"
},
  "geometry": {"coordinates":[-117.31279000000001,34.516666],"type":"Point"}
}