{
  "type": "Feature",
  "properties": {
    "iso:country":"US",
    "sg:address":"2038 W Lincoln Ave",
    "sg:city":"Anaheim",
    "sg:classifiers":[
        {
            "category":"Wholesale",
            "subcategory":"Home Furnishings",
            "type":"Manufacturing & Wholesale Goods"
        }
    ],
    "sg:phone":"+1 714 956 4006",
    "sg:postcode":"92801",
    "sg:province":"CA",
    "wof:name":"Super Estrellas Rena Ware Inte",
    "wof:placetype":"venue"
},
  "geometry": {"coordinates":[-117.95428099999999,33.832475],"type":"Point"}
}