{
  "type": "Feature",
  "properties": {
    "iso:country":"US",
    "sg:address":"5372 Packard St",
    "sg:city":"Los Angeles",
    "sg:classifiers":[
        {
            "category":"Personal",
            "type":"Services"
        }
    ],
    "sg:phone":"+1 323 782 1425",
    "sg:postcode":"90019",
    "sg:province":"CA",
    "sg:tags":[
        "home"
    ],
    "sg:website":"www.BrainworksArt.com",
    "wof:name":"Brainworks, Inc.",
    "wof:placetype":"venue"
},
  "geometry": {"coordinates":[-118.353793,34.050627],"type":"Point"}
}