{
  "type": "Feature",
  "properties": {
    "iso:country":"US",
    "sg:address":"1674 Mentone Ave",
    "sg:city":"Pasadena",
    "sg:classifiers":[
        {
            "category":"Health Services",
            "subcategory":"Nursing And Care Facility",
            "type":"Services"
        }
    ],
    "sg:phone":"+1 626 398 8837",
    "sg:postcode":"91103",
    "sg:province":"CA",
    "sg:tags":[
        "home",
        "convalescent"
    ],
    "wof:name":"Seniors Haven",
    "wof:placetype":"venue"
},
  "geometry": {"coordinates":[-118.157287,34.176767],"type":"Point"}
}