{
  "type": "Feature",
  "properties": {
    "iso:country":"US",
    "sg:address":"14895 E 14th St",
    "sg:city":"San Leandro",
    "sg:classifiers":[
        {
            "category":"Organizations",
            "subcategory":"Religious Organization",
            "type":"Services"
        }
    ],
    "sg:phone":"+1 510 357 0300",
    "sg:postcode":"94578",
    "sg:province":"CA",
    "sg:tags":[
        "church"
    ],
    "wof:name":"Millennium International",
    "wof:placetype":"venue"
},
  "geometry": {"coordinates":[-122.131692,37.707468],"type":"Point"}
}