{
  "type": "Feature",
  "properties": {
    "iso:country":"US",
    "sg:address":"9026 Los Cerritos Mall",
    "sg:city":"Cerritos",
    "sg:classifiers":[
        {
            "category":"Shopping",
            "subcategory":"Jewelry",
            "type":"Retail Goods"
        }
    ],
    "sg:phone":"+1 562 924 9205",
    "sg:postcode":"90703",
    "sg:province":"CA",
    "sg:tags":[
        "jeweler"
    ],
    "wof:name":"Piercing Pagoda",
    "wof:placetype":"venue"
},
  "geometry": {"coordinates":[-118.093715,33.864785],"type":"Point"}
}