{
  "type": "Feature",
  "properties": {
    "addr:full":"24754 E River Rd Escalon CA 95320",
    "addr:housenumber":"24754",
    "addr:postcode":"95320",
    "addr:street":"E River Rd",
    "iso:country":"US",
    "sg:address":"24754 E River Rd",
    "sg:city":"Escalon",
    "sg:classifiers":[
        {
            "category":"Home & Garden",
            "subcategory":"Garden Supply",
            "type":"Retail Goods"
        },
        {
            "category":"Wholesale",
            "subcategory":"Machinery & Supplies",
            "type":"Manufacturing & Wholesale Goods"
        },
        {
            "category":"Manufacturing",
            "subcategory":"Paper Products",
            "type":"Manufacturing & Wholesale Goods"
        }
    ],
    "sg:phone":"+1 209 838 2550",
    "sg:postcode":"95320",
    "sg:province":"CA",
    "sg:tags":[
        "equipment",
        "irrigation",
        "system",
        "bamboo"
    ],
    "sg:website":"http://www.morrill-industries.net",
    "wof:name":"Morrill Industries Inc",
    "wof:placetype":"venue"
},
  "geometry": {"coordinates":[-121.006556,37.758573],"type":"Point"}
}