{
  "type": "Feature",
  "properties": {
    "addr:full":"1631 E Capitol Expressway San Jose CA 95121",
    "addr:housenumber":"1631",
    "addr:postcode":"95121",
    "addr:street":"E Capitol Expressway",
    "iso:country":"US",
    "sg:address":"1631 E Capitol Expressway",
    "sg:city":"San Jose",
    "sg:classifiers":[
        {
            "category":"Personal",
            "subcategory":"Barber",
            "type":"Services"
        }
    ],
    "sg:phone":"+1 408 238 9533",
    "sg:postcode":"95121",
    "sg:province":"CA",
    "wof:name":"Clean Cuts",
    "wof:placetype":"venue"
},
  "geometry": {"coordinates":[-121.81206400000001,37.306286],"type":"Point"}
}