{
  "type": "Feature",
  "properties": {
    "iso:country":"US",
    "sg:address":"4530 S Minturn Rd",
    "sg:city":"Le Grand",
    "sg:classifiers":[
        {
            "category":"Professional",
            "type":"Services"
        }
    ],
    "sg:phone":"+1 209 389 4263",
    "sg:postcode":"95333",
    "sg:province":"CA",
    "wof:name":"Light Up Legrand Fund",
    "wof:placetype":"venue"
},
  "geometry": {"coordinates":[-120.270744,37.2207],"type":"Point"}
}