{
  "type": "Feature",
  "properties": {
    "addr:full":"4429 Cape May Ave San Diego CA 92107",
    "addr:housenumber":"4429",
    "addr:postcode":"92107",
    "addr:street":"Cape May Ave",
    "iso:country":"US",
    "sg:address":"4429 Cape May Ave",
    "sg:city":"San Diego",
    "sg:classifiers":[
        {
            "category":"Professional",
            "subcategory":"Lawyer & Legal Services",
            "type":"Services"
        }
    ],
    "sg:phone":"+1 619 291 6219",
    "sg:postcode":"92107",
    "sg:province":"CA",
    "wof:name":"Hilton Harvey M Attorney and Counselor At Law",
    "wof:placetype":"venue"
},
  "geometry": {"coordinates":[-117.239108,32.743001],"type":"Point"}
}