{
  "type": "Feature",
  "properties": {
    "iso:country":"US",
    "sg:address":"4939 Marine Ave Ste A",
    "sg:city":"Lawndale",
    "sg:classifiers":[
        {
            "category":"Retail",
            "subcategory":"Auto Repair",
            "type":"Services"
        }
    ],
    "sg:phone":"+1 310 318 1032",
    "sg:postcode":"90260",
    "sg:province":"CA",
    "wof:name":"Kishi Auto Repair",
    "wof:placetype":"venue"
},
  "geometry": {"coordinates":[-118.364998,33.894501],"type":"Point"}
}