{
  "type": "Feature",
  "properties": {
    "addr:full":"6594 Bose Ln San Jose CA 95120",
    "addr:housenumber":"6594",
    "addr:postcode":"95120",
    "addr:street":"Bose Ln",
    "iso:country":"US",
    "sg:address":"6594 Bose Ln",
    "sg:city":"San Jose",
    "sg:classifiers":[
        {
            "category":"Professional",
            "subcategory":"Art Services",
            "type":"Services"
        }
    ],
    "sg:phone":"+1 408 268 8651",
    "sg:postcode":"95120",
    "sg:province":"CA",
    "sg:tags":[
        "photographer"
    ],
    "wof:name":"James R Curtis Photography",
    "wof:placetype":"venue"
},
  "geometry": {"coordinates":[-121.867182,37.217775],"type":"Point"}
}