{
  "type": "Feature",
  "properties": {
    "addr:full":"8013 Norwalk Blvd Whittier CA 90606",
    "addr:housenumber":"8013",
    "addr:postcode":"90606",
    "addr:street":"Norwalk Blvd",
    "iso:country":"US",
    "sg:address":"8013 Norwalk Blvd",
    "sg:city":"Whittier",
    "sg:classifiers":[
        {
            "category":"Retail",
            "subcategory":"Laundry & Dry Cleaning",
            "type":"Services"
        }
    ],
    "sg:phone":"+1 562 692 8884",
    "sg:postcode":"90606",
    "sg:province":"CA",
    "wof:name":"Superior Laundry",
    "wof:placetype":"venue"
},
  "geometry": {"coordinates":[-118.073986,33.97181],"type":"Point"}
}