{
  "type": "Feature",
  "properties": {
    "iso:country":"US",
    "sg:address":"14240 Vai Brothers Dr",
    "sg:city":"Rancho Cucamonga",
    "sg:classifiers":[
        {
            "category":"Manufacturing",
            "subcategory":"Retail Goods",
            "type":"Manufacturing & Wholesale Goods"
        }
    ],
    "sg:phone":"+1 909 463 5938",
    "sg:postcode":"91739",
    "sg:province":"CA",
    "sg:tags":[
        "product",
        "mfg"
    ],
    "wof:name":"Unit Industries",
    "wof:placetype":"venue"
},
  "geometry": {"coordinates":[-117.497151,34.161407],"type":"Point"}
}