{
  "type": "Feature",
  "properties": {
    "iso:country":"US",
    "sg:address":"1611 Telegraph Ave",
    "sg:city":"Oakland",
    "sg:classifiers":[
        {
            "category":"Home & Garden",
            "subcategory":"Home Furnishings",
            "type":"Retail Goods"
        },
        {
            "category":"Real Estate",
            "subcategory":"Architect",
            "type":"Services"
        }
    ],
    "sg:phone":"+1 510 451 7007",
    "sg:postcode":"94612",
    "sg:province":"CA",
    "sg:tags":[
        "architects'",
        "specification",
        "builders'",
        "planning",
        "design",
        "architectural",
        "construction"
    ],
    "wof:name":"Town Green",
    "wof:placetype":"venue"
},
  "geometry": {"coordinates":[-122.270422,37.806182],"type":"Point"}
}