{
  "type": "Feature",
  "properties": {
    "iso:country":"US",
    "sg:address":"1941 A St",
    "sg:city":"La Verne",
    "sg:classifiers":[
        {
            "category":"Shopping",
            "subcategory":"Clothing, Apparel, & Fashions",
            "type":"Retail Goods"
        }
    ],
    "sg:phone":"+1 909 596 1170",
    "sg:postcode":"91750",
    "sg:province":"CA",
    "sg:tags":[
        "t"
    ],
    "wof:name":"T Shirt Mart",
    "wof:placetype":"venue"
},
  "geometry": {"coordinates":[-117.777496,34.098603],"type":"Point"}
}