{
  "type": "Feature",
  "properties": {
    "iso:country":"US",
    "sg:address":"160 W Main St",
    "sg:city":"El Centro",
    "sg:classifiers":[
        {
            "category":"Freight",
            "type":"Transportation"
        }
    ],
    "sg:phone":"+1 760 337 8250",
    "sg:postcode":"92243",
    "sg:province":"CA",
    "sg:tags":[
        "courier",
        "air"
    ],
    "wof:name":"UPS",
    "wof:placetype":"venue"
},
  "geometry": {"coordinates":[-115.545208,32.792903],"type":"Point"}
}