{
  "type": "Feature",
  "properties": {
    "iso:country":"US",
    "sg:address":"5 W Los Angeles Ave",
    "sg:city":"Moorpark",
    "sg:classifiers":[
        {
            "category":"Shopping",
            "subcategory":"Jewelry",
            "type":"Retail Goods"
        }
    ],
    "sg:phone":"+1 805 529 5844",
    "sg:postcode":"93021",
    "sg:province":"CA",
    "sg:tags":[
        "jeweler"
    ],
    "wof:name":"Anderson Jewelers",
    "wof:placetype":"venue"
},
  "geometry": {"coordinates":[-118.803339,34.28198],"type":"Point"}
}