{
  "type": "Feature",
  "properties": {
    "iso:country":"US",
    "sg:address":"366 San Miguel Dr",
    "sg:city":"Newport Beach",
    "sg:classifiers":[
        {
            "category":"Social Services",
            "type":"Services"
        }
    ],
    "sg:phone":"+1 949 718 1275",
    "sg:postcode":"92660",
    "sg:province":"CA",
    "sg:tags":[
        "crisis",
        "intervention"
    ],
    "wof:name":"Win Foundation",
    "wof:placetype":"venue"
},
  "geometry": {"coordinates":[-117.871685,33.612479],"type":"Point"}
}