{
  "type": "Feature",
  "properties": {
    "addr:full":"820 Beckman Rd Lodi CA 95240",
    "addr:housenumber":"820",
    "addr:postcode":"95240",
    "addr:street":"Beckman Rd",
    "iso:country":"US",
    "sg:address":"820 Beckman Rd",
    "sg:city":"Lodi",
    "sg:classifiers":[
        {
            "category":"Retail",
            "subcategory":"Auto Repair",
            "type":"Services"
        }
    ],
    "sg:phone":"+1 209 365 6747",
    "sg:postcode":"95240",
    "sg:province":"CA",
    "sg:tags":[
        "repairing",
        "automobile"
    ],
    "wof:name":"Gasoline Alley",
    "wof:placetype":"venue"
},
  "geometry": {"coordinates":[-121.259103,38.145549],"type":"Point"}
}