{
  "type": "Feature",
  "properties": {
    "addr:full":"2540 Sweet Creek Ln Rescue CA 95672",
    "addr:housenumber":"2540",
    "addr:postcode":"95672",
    "addr:street":"Sweet Creek Ln",
    "iso:country":"US",
    "sg:address":"2540 Sweet Creek Ln",
    "sg:city":"Rescue",
    "sg:classifiers":[
        {
            "category":"Building & Trades",
            "subcategory":"Electrical",
            "type":"Services"
        }
    ],
    "sg:phone":"+1 530 677 6204",
    "sg:postcode":"95672",
    "sg:province":"CA",
    "sg:tags":[
        "electrician"
    ],
    "wof:name":"Hal Duncan Electrical Co",
    "wof:placetype":"venue"
},
  "geometry": {"coordinates":[-120.975144,38.738413],"type":"Point"}
}