{
  "type": "Feature",
  "properties": {
    "iso:country":"US",
    "sg:address":"5460 Woodruff Ave",
    "sg:city":"Lakewood",
    "sg:classifiers":[
        {
            "category":"Shopping",
            "subcategory":"Tobacco",
            "type":"Retail Goods"
        }
    ],
    "sg:phone":"+1 562 867 7467",
    "sg:postcode":"90713",
    "sg:province":"CA",
    "sg:tags":[
        "shop"
    ],
    "wof:name":"Lakewood Smoke Shop",
    "wof:placetype":"venue"
},
  "geometry": {"coordinates":[-118.116997,33.855999],"type":"Point"}
}