{
  "type": "Feature",
  "properties": {
    "addr:full":"509 Humes Ave Aptos CA 95003",
    "addr:housenumber":"509",
    "addr:postcode":"ca 95003",
    "addr:street":"Humes Ave",
    "iso:country":"US",
    "sg:address":"509 Humes Ave",
    "sg:city":"Aptos",
    "sg:classifiers":[
        {
            "category":"Farming",
            "subcategory":"Farm",
            "type":"Manufacturing & Wholesale Goods"
        }
    ],
    "sg:phone":"+1 831 662 9413",
    "sg:postcode":"95003",
    "sg:province":"CA",
    "sg:tags":[
        "crop",
        "general"
    ],
    "wof:name":"Leo Moll",
    "wof:placetype":"venue"
},
  "geometry": {"coordinates":[-121.886011,36.969645],"type":"Point"}
}