{
  "type": "Feature",
  "properties": {
    "iso:country":"US",
    "sg:address":"1500 Willow Ave",
    "sg:city":"Burlingame",
    "sg:classifiers":[
        {
            "category":"Professional",
            "type":"Services"
        }
    ],
    "sg:phone":"+1 650 342 5985",
    "sg:postcode":"94010",
    "sg:province":"CA",
    "wof:name":"Polyar LLC",
    "wof:placetype":"venue"
},
  "geometry": {"coordinates":[-122.358586,37.579277],"type":"Point"}
}