{
  "type": "Feature",
  "properties": {
    "addr:full":"4050 Phelan Rd Phelan CA 92371",
    "addr:housenumber":"4050",
    "addr:postcode":"92371",
    "addr:street":"Phelan Rd",
    "iso:country":"US",
    "sg:address":"4050 Phelan Rd",
    "sg:city":"Phelan",
    "sg:classifiers":[
        {
            "category":"Restaurant",
            "type":"Food & Drink"
        }
    ],
    "sg:phone":"+1 760 868 4886",
    "sg:postcode":"92371",
    "sg:province":"CA",
    "wof:name":"Mama Maria Restaurant",
    "wof:placetype":"venue"
},
  "geometry": {"coordinates":[-117.573624,34.426315],"type":"Point"}
}