{
  "type": "Feature",
  "properties": {
    "iso:country":"US",
    "sg:address":"2414 Foothill Blvd",
    "sg:city":"La Crescenta",
    "sg:classifiers":[
        {
            "category":"Wholesale",
            "subcategory":"Electrical",
            "type":"Manufacturing & Wholesale Goods"
        }
    ],
    "sg:phone":"+1 818 957 2654",
    "sg:postcode":"91214",
    "sg:province":"CA",
    "sg:tags":[
        "equipment",
        "electronic",
        "supply"
    ],
    "wof:name":"Mulvin & Co Inc Sls Engnrs",
    "wof:placetype":"venue"
},
  "geometry": {"coordinates":[-118.232283,34.219412],"type":"Point"}
}