{
  "type": "Feature",
  "properties": {
    "iso:country":"US",
    "sg:address":"6300 Wilshire Blvd",
    "sg:city":"Los Angeles",
    "sg:classifiers":[
        {
            "category":"Restaurant",
            "type":"Food & Drink"
        }
    ],
    "sg:phone":"+1 323 951 0989",
    "sg:postcode":"90048",
    "sg:province":"CA",
    "wof:name":"Garden of Eating Cafe",
    "wof:placetype":"venue"
},
  "geometry": {"coordinates":[-118.366195,34.063352],"type":"Point"}
}