{
  "type": "Feature",
  "properties": {
    "iso:country":"US",
    "sg:address":"13311 Penn St",
    "sg:city":"Whittier",
    "sg:classifiers":[
        {
            "category":"Shopping",
            "subcategory":"Antiques",
            "type":"Retail Goods"
        }
    ],
    "sg:phone":"+1 562 789 9547",
    "sg:postcode":"90602",
    "sg:province":"CA",
    "sg:website":"www.wholesale-antiques.net",
    "wof:name":"Wholesale Antiques",
    "wof:placetype":"venue"
},
  "geometry": {"coordinates":[-118.34559,33.975571],"type":"Point"}
}