{
  "type": "Feature",
  "properties": {
    "addr:full":"1580 Cannon Road Carlsbad CA 92008",
    "addr:housenumber":"1580",
    "addr:postcode":"92008",
    "addr:street":"Cannon Road",
    "iso:country":"US",
    "sg:address":"1580 Cannon Road",
    "sg:city":"Carlsbad",
    "sg:classifiers":[
        {
            "category":"Government",
            "subcategory":"City Hall",
            "type":"Public Place"
        },
        {
            "category":"Recreation",
            "type":"Entertainment"
        }
    ],
    "sg:phone":"+1 760 804 1969",
    "sg:postcode":"92008",
    "sg:province":"CA",
    "sg:tags":[
        "active",
        "life"
    ],
    "sg:website":"www.aguahedionda.org/",
    "wof:name":"The Agua Hedionda Lagoon Discovery Center",
    "wof:placetype":"venue"
},
  "geometry": {"coordinates":[-117.3095,33.13744],"type":"Point"}
}