{
  "type": "Feature",
  "properties": {
    "addr:full":"5389 Turquoise Ave Rancho Cucamonga CA 91701",
    "addr:housenumber":"5389",
    "addr:postcode":"91701",
    "addr:street":"Turquoise Ave",
    "iso:country":"US",
    "sg:address":"5389 Turquoise Ave",
    "sg:city":"Rancho Cucamonga",
    "sg:classifiers":[
        {
            "category":"Manufacturing",
            "subcategory":"Printing",
            "type":"Manufacturing & Wholesale Goods"
        }
    ],
    "sg:phone":"+1 909 481 4318",
    "sg:postcode":"91701",
    "sg:province":"CA",
    "sg:tags":[
        "publisher",
        "magazine"
    ],
    "wof:name":"First Class Creations Inc",
    "wof:placetype":"venue"
},
  "geometry": {"coordinates":[-117.63435699999999,34.155474],"type":"Point"}
}