{
  "type": "Feature",
  "properties": {
    "iso:country":"US",
    "sg:address":"2 McClure Way",
    "sg:city":"Seaside",
    "sg:classifiers":[
        {
            "category":"Real Estate",
            "subcategory":"Developer",
            "type":"Services"
        }
    ],
    "sg:phone":"+1 831 392 1900",
    "sg:postcode":"93955",
    "sg:province":"CA",
    "wof:name":"Seaside Resort Development",
    "wof:placetype":"venue"
},
  "geometry": {"coordinates":[-121.814612,36.628132],"type":"Point"}
}