{
  "type": "Feature",
  "properties": {
    "iso:country":"US",
    "sg:address":"1301 Rand St",
    "sg:city":"Petaluma",
    "sg:classifiers":[
        {
            "category":"Professional",
            "subcategory":"Engineering",
            "type":"Services"
        }
    ],
    "sg:phone":"+1 707 769 5330",
    "sg:postcode":"94954",
    "sg:province":"CA",
    "sg:tags":[
        "engineer"
    ],
    "sg:website":"www.pavengr.com",
    "wof:name":"Pavement Engineering Inc",
    "wof:placetype":"venue"
},
  "geometry": {"coordinates":[-122.659544,38.268053],"type":"Point"}
}