{
  "type": "Feature",
  "properties": {
    "addr:full":"1901 Matson Dr Sacramento CA 95822",
    "addr:housenumber":"1901",
    "addr:postcode":"95822",
    "addr:street":"Matson Dr",
    "iso:country":"US",
    "sg:address":"1901 Matson Dr",
    "sg:city":"Sacramento",
    "sg:classifiers":[
        {
            "category":"Professional",
            "subcategory":"Detective & Security Services",
            "type":"Services"
        }
    ],
    "sg:phone":"+1 916 289 4444",
    "sg:postcode":"95822",
    "sg:province":"CA",
    "sg:tags":[
        "information",
        "bureau"
    ],
    "wof:name":"Liberty Janitorial Service",
    "wof:placetype":"venue"
},
  "geometry": {"coordinates":[-121.494614,38.484852],"type":"Point"}
}