{
  "type": "Feature",
  "properties": {
    "addr:full":"2842 Walnut Ave Ste B1 Tustin CA 92780",
    "addr:housenumber":"2842",
    "addr:postcode":"92780",
    "addr:street":"Walnut Ave Ste B1",
    "iso:country":"US",
    "sg:address":"2842 Walnut Ave Ste B1",
    "sg:city":"Tustin",
    "sg:classifiers":[
        {
            "category":"Building & Trades",
            "subcategory":"Cleaning & Sanitation",
            "type":"Services"
        }
    ],
    "sg:phone":"+1 714 544 4818",
    "sg:postcode":"92780",
    "sg:province":"CA",
    "wof:name":"Myers Building Service",
    "wof:placetype":"venue"
},
  "geometry": {"coordinates":[-117.80485,33.71316],"type":"Point"}
}