{
  "type": "Feature",
  "properties": {
    "iso:country":"US",
    "sg:address":"1775 Hancock St",
    "sg:city":"San Diego",
    "sg:classifiers":[
        {
            "category":"Insurance",
            "subcategory":"Insurance Agent",
            "type":"Services"
        }
    ],
    "sg:phone":"+1 858 573 1117",
    "sg:postcode":"92110",
    "sg:province":"CA",
    "wof:name":"Consolidated Administration",
    "wof:placetype":"venue"
},
  "geometry": {"coordinates":[-117.183385,32.741926],"type":"Point"}
}