{
  "type": "Feature",
  "properties": {
    "iso:country":"US",
    "sg:address":"3177 Austin Ave",
    "sg:city":"Simi Valley",
    "sg:classifiers":[
        {
            "category":"Building & Trades",
            "subcategory":"Electrical",
            "type":"Services"
        }
    ],
    "sg:phone":"+1 805 526 7989",
    "sg:postcode":"93063",
    "sg:province":"CA",
    "sg:tags":[
        "electrical",
        "contractor"
    ],
    "wof:name":"Waynes Electric",
    "wof:placetype":"venue"
},
  "geometry": {"coordinates":[-118.70580699999999,34.28951],"type":"Point"}
}