{
  "type": "Feature",
  "properties": {
    "addr:full":"20 Galway Ln San Rafael CA 94903",
    "addr:housenumber":"20",
    "addr:postcode":"94903",
    "addr:street":"Galway Ln",
    "iso:country":"US",
    "sg:address":"20 Galway Ln",
    "sg:city":"San Rafael",
    "sg:classifiers":[
        {
            "category":"Personal",
            "subcategory":"Beauty Salon",
            "type":"Services"
        }
    ],
    "sg:phone":"+1 415 451 0123",
    "sg:postcode":"94903",
    "sg:province":"CA",
    "sg:website":"www.pfbvanish.com",
    "wof:name":"Skin Care Technologies",
    "wof:placetype":"venue"
},
  "geometry": {"coordinates":[-122.563542,38.019015],"type":"Point"}
}