{
  "type": "Feature",
  "properties": {
    "iso:country":"US",
    "sg:address":"21021 Soledad Canyon Rd",
    "sg:city":"Canyon Country",
    "sg:classifiers":[
        {
            "category":"Banks & Credit Unions",
            "subcategory":"Bank",
            "type":"Services"
        }
    ],
    "sg:phone":"+1 661 362 6070",
    "sg:postcode":"91351",
    "sg:province":"CA",
    "sg:website":"www.bankofsantaclarita.com",
    "wof:name":"Bank of Santa Clarita",
    "wof:placetype":"venue"
},
  "geometry": {"coordinates":[-118.504447,34.4202],"type":"Point"}
}