{
  "type": "Feature",
  "properties": {
    "addr:full":"929 Alhambra Ave Martinez CA 94553",
    "addr:housenumber":"929",
    "addr:postcode":"94553",
    "addr:street":"Alhambra Ave",
    "iso:country":"US",
    "sg:address":"929 Alhambra Ave",
    "sg:city":"Martinez",
    "sg:classifiers":[
        {
            "category":"Autos & Motor Vehicles",
            "subcategory":"Motorcycle Sales",
            "type":"Retail Goods"
        }
    ],
    "sg:phone":"+1 925 229 5000",
    "sg:postcode":"94553",
    "sg:province":"CA",
    "sg:tags":[
        "scooter"
    ],
    "wof:name":"California Sport Touring",
    "wof:placetype":"venue"
},
  "geometry": {"coordinates":[-122.136651,38.014935],"type":"Point"}
}