{
  "type": "Feature",
  "properties": {
    "iso:country":"US",
    "sg:address":"8130 N Lake Blvd",
    "sg:city":"Kings Beach",
    "sg:classifiers":[
        {
            "category":"Real Estate",
            "subcategory":"Real Estate Agent",
            "type":"Services"
        }
    ],
    "sg:phone":"+1 530 546 3700",
    "sg:postcode":"96143",
    "sg:province":"CA",
    "wof:name":"Prudential California Realty",
    "wof:placetype":"venue"
},
  "geometry": {"coordinates":[-120.02860699999999,39.237488],"type":"Point"}
}