{
  "type": "Feature",
  "properties": {
    "addr:full":"1100 Le Conte Ave Montara 94037",
    "wof:categories":[
        "education_and_religion:education=school"
    ],
    "wof:name":"Farallone View Elementary School",
    "wof:placetype":"venue"
},
  "geometry": {"coordinates":[-122.50823877936784,37.54390090515697],"type":"Point"}
}