{
  "type": "Feature",
  "properties": {
    "addr:full":"30611 Rolling Hills Dr Valley Center CA 92082",
    "addr:housenumber":"30611",
    "addr:postcode":"92082",
    "addr:street":"Rolling Hills Dr",
    "iso:country":"US",
    "sg:address":"30611 Rolling Hills Dr",
    "sg:city":"Valley Center",
    "sg:classifiers":[
        {
            "category":"Professional",
            "type":"Services"
        }
    ],
    "sg:phone":"+1 760 751 0706",
    "sg:postcode":"92082",
    "sg:province":"CA",
    "wof:name":"Chlorco",
    "wof:placetype":"venue"
},
  "geometry": {"coordinates":[-117.08909199999999,33.266056],"type":"Point"}
}