{
  "type": "Feature",
  "properties": {
    "iso:country":"US",
    "sg:address":"30611 Rolling Hills Dr",
    "sg:city":"Valley Center",
    "sg:classifiers":[
        {
            "category":"Professional",
            "type":"Services"
        }
    ],
    "sg:phone":"+1 760 751 0706",
    "sg:postcode":"92082",
    "sg:province":"CA",
    "wof:name":"Chlorco",
    "wof:placetype":"venue"
},
  "geometry": {"coordinates":[-117.089092,33.266056],"type":"Point"}
}