{
  "type": "Feature",
  "properties": {
    "iso:country":"US",
    "sg:address":"619 E Blithedale Ave",
    "sg:city":"Mill Valley",
    "sg:classifiers":[
        {
            "category":"Health Services",
            "subcategory":"Health Practitioner",
            "type":"Services"
        }
    ],
    "sg:phone":"+1 415 388 5223",
    "sg:postcode":"94941",
    "sg:province":"CA",
    "sg:tags":[
        "therapist",
        "physical"
    ],
    "sg:website":"www.millvalleypt.com",
    "wof:name":"Mill Valley Physical Therapy",
    "wof:placetype":"venue"
},
  "geometry": {"coordinates":[-122.52912499999999,37.900854],"type":"Point"}
}