{
  "type": "Feature",
  "properties": {
    "iso:country":"US",
    "sg:address":"14400 Washington Ave",
    "sg:city":"San Leandro",
    "sg:classifiers":[
        {
            "category":"Restaurant",
            "type":"Food & Drink"
        }
    ],
    "sg:phone":"+1 510 357 8858",
    "sg:postcode":"94577",
    "sg:province":"CA",
    "wof:name":"Beijing Bowl",
    "wof:placetype":"venue"
},
  "geometry": {"coordinates":[-122.139889,37.701028],"type":"Point"}
}