{
  "type": "Feature",
  "properties": {
    "iso:country":"US",
    "sg:address":"573 W Vista Way",
    "sg:city":"Vista",
    "sg:classifiers":[
        {
            "category":"Personal",
            "subcategory":"Beauty Salon",
            "type":"Services"
        }
    ],
    "sg:phone":"+1 760 941 1250",
    "sg:postcode":"92083",
    "sg:province":"CA",
    "sg:tags":[
        "hair"
    ],
    "wof:name":"Shannon Beauty Salon",
    "wof:placetype":"venue"
},
  "geometry": {"coordinates":[-117.253998,33.195599],"type":"Point"}
}