{
  "type": "Feature",
  "properties": {
    "addr:full":"1717 Kathleen Ave Sacramento CA 95815",
    "addr:housenumber":"1717",
    "addr:postcode":"95815",
    "addr:street":"Kathleen Ave",
    "iso:country":"US",
    "sg:address":"1717 Kathleen Ave",
    "sg:city":"Sacramento",
    "sg:classifiers":[
        {
            "category":"Professional",
            "subcategory":"Art Services",
            "type":"Services"
        }
    ],
    "sg:phone":"+1 916 922 1518",
    "sg:postcode":"95815",
    "sg:province":"CA",
    "sg:tags":[
        "photographer"
    ],
    "wof:name":"Lau & Assoc",
    "wof:placetype":"venue"
},
  "geometry": {"coordinates":[-121.42555,38.622048],"type":"Point"}
}