{
  "type": "Feature",
  "properties": {
    "addr:full":"2543 Cordelia Rd Fairfield CA 94534",
    "addr:housenumber":"2543",
    "addr:postcode":"94534",
    "addr:street":"Cordelia Rd",
    "iso:country":"US",
    "sg:address":"2543 Cordelia Rd",
    "sg:city":"Fairfield",
    "sg:classifiers":[
        {
            "category":"Wholesale",
            "subcategory":"Durable Goods & Equipment",
            "type":"Manufacturing & Wholesale Goods"
        }
    ],
    "sg:phone":"+1 707 864 6161",
    "sg:postcode":"94534",
    "sg:province":"CA",
    "sg:tags":[
        "exporter"
    ],
    "wof:name":"Atlas Seeds Inc",
    "wof:placetype":"venue"
},
  "geometry": {"coordinates":[-122.109791,38.224241],"type":"Point"}
}