{
  "type": "Feature",
  "properties": {
    "iso:country":"US",
    "sg:address":"330 Golden Shore",
    "sg:city":"Long Beach",
    "sg:classifiers":[
        {
            "category":"Organizations",
            "subcategory":"Non-profit Organization",
            "type":"Services"
        }
    ],
    "sg:phone":"+1 562 256 7400",
    "sg:postcode":"90802",
    "sg:province":"CA",
    "sg:tags":[
        "service/non-profit",
        "community"
    ],
    "wof:name":"Children's Home Society Of California",
    "wof:placetype":"venue"
},
  "geometry": {"coordinates":[-118.198263,33.763716],"type":"Point"}
}