{
  "type": "Feature",
  "properties": {
    "iso:country":"US",
    "sg:address":"1428 Howe Ave",
    "sg:city":"Sacramento",
    "sg:classifiers":[
        {
            "category":"Government",
            "subcategory":"Office",
            "type":"Public Place"
        }
    ],
    "sg:phone":"+1 916 263 2595",
    "sg:postcode":"95825",
    "sg:province":"CA",
    "wof:name":"Dental Auxiliaries",
    "wof:placetype":"venue"
},
  "geometry": {"coordinates":[-121.41523,38.592928],"type":"Point"}
}