{
  "type": "Feature",
  "properties": {
    "addr:full":"45250 Fremont Blvd Fremont CA 94538",
    "addr:housenumber":"45250",
    "addr:postcode":"94538",
    "addr:street":"Fremont Blvd",
    "iso:country":"US",
    "sg:address":"45250 Fremont Blvd",
    "sg:city":"Fremont",
    "sg:classifiers":[
        {
            "category":"Retail",
            "subcategory":"Auto Repair",
            "type":"Services"
        }
    ],
    "sg:phone":"+1 510 498 7817",
    "sg:postcode":"94538",
    "sg:province":"CA",
    "sg:tags":[
        "automotive",
        "management"
    ],
    "wof:name":"Toyota Motor",
    "wof:placetype":"venue"
},
  "geometry": {"coordinates":[-121.94849499999999,37.49798],"type":"Point"}
}