{
  "type": "Feature",
  "properties": {
    "addr:full":"555 N 13th St Grover Beach CA 93433",
    "addr:housenumber":"555",
    "addr:postcode":"93433",
    "addr:street":"N 13Th St",
    "iso:country":"US",
    "sg:address":"555 N 13th St",
    "sg:city":"Grover Beach",
    "sg:classifiers":[
        {
            "category":"Shopping",
            "subcategory":"Computers & Home Electronics",
            "type":"Retail Goods"
        }
    ],
    "sg:phone":"+1 805 994 1040",
    "sg:postcode":"93433",
    "sg:province":"CA",
    "sg:tags":[
        "software"
    ],
    "sg:website":"www.moonvalley.com",
    "wof:name":"Moon Valley Software",
    "wof:placetype":"venue"
},
  "geometry": {"coordinates":[-120.61500700000001,35.126518],"type":"Point"}
}