{
  "type": "Feature",
  "properties": {
    "iso:country":"US",
    "sg:address":"4700 Stockdale Hwy",
    "sg:city":"Bakersfield",
    "sg:classifiers":[
        {
            "category":"Banks & Credit Unions",
            "subcategory":"Investment Brokerage",
            "type":"Services"
        }
    ],
    "sg:phone":"+1 661 631 4355",
    "sg:postcode":"93309",
    "sg:province":"CA",
    "sg:tags":[
        "stock",
        "bond"
    ],
    "sg:website":"www.calfinancial.com",
    "wof:name":"California Financial Network",
    "wof:placetype":"venue"
},
  "geometry": {"coordinates":[-119.056557,35.354217],"type":"Point"}
}