{
  "type": "Feature",
  "properties": {
    "addr:full":"7451 Dowdy St Gilroy CA 95020",
    "addr:housenumber":"7451",
    "addr:postcode":"95020",
    "addr:street":"Dowdy St",
    "iso:country":"US",
    "sg:address":"7451 Dowdy St",
    "sg:city":"Gilroy",
    "sg:classifiers":[
        {
            "category":"Professional",
            "subcategory":"Accounting & Tax Preparation",
            "type":"Services"
        }
    ],
    "sg:phone":"+1 408 842 7317",
    "sg:postcode":"95020",
    "sg:province":"CA",
    "sg:tags":[
        "bookkeeping",
        "general"
    ],
    "wof:name":"Morton Bookkeeping",
    "wof:placetype":"venue"
},
  "geometry": {"coordinates":[-121.575176,37.005795],"type":"Point"}
}