{
  "type": "Feature",
  "properties": {
    "iso:country":"US",
    "sg:address":"84651 State Rte 70",
    "sg:city":"Beckwourth",
    "sg:classifiers":[
        {
            "category":"Building & Trades",
            "subcategory":"Construction",
            "type":"Services"
        }
    ],
    "sg:phone":"+1 530 832 0525",
    "sg:postcode":"96129",
    "sg:province":"CA",
    "sg:tags":[
        "barn"
    ],
    "wof:name":"Sierra Valley Barns & Gazebos",
    "wof:placetype":"venue"
},
  "geometry": {"coordinates":[-120.315995,39.811509],"type":"Point"}
}