{
  "type": "Feature",
  "properties": {
    "addr:full":"820 N China Lake Blvd Ridgecrest CA 93555",
    "addr:housenumber":"820",
    "addr:postcode":"93555",
    "addr:street":"N China Lake Blvd",
    "iso:country":"US",
    "sg:address":"820 N China Lake Blvd",
    "sg:city":"Ridgecrest",
    "sg:classifiers":[
        {
            "category":"Retail",
            "subcategory":"Laundry & Dry Cleaning",
            "type":"Services"
        }
    ],
    "sg:phone":"+1 760 375 0234",
    "sg:postcode":"93555",
    "sg:province":"CA",
    "sg:tags":[
        "cleaners"
    ],
    "wof:name":"Towne Center 1-Hour Cleaners",
    "wof:placetype":"venue"
},
  "geometry": {"coordinates":[-117.66979499999999,35.635701],"type":"Point"}
}