{
  "type": "Feature",
  "properties": {
    "iso:country":"US",
    "sg:address":"990 Nolan Way",
    "sg:city":"Chula Vista",
    "sg:classifiers":[
        {
            "category":"Professional",
            "subcategory":"Testing Lab",
            "type":"Services"
        }
    ],
    "sg:phone":"+1 619 426 4202",
    "sg:postcode":"91911",
    "sg:province":"CA",
    "sg:tags":[
        "electrical",
        "system",
        "power"
    ],
    "sg:website":"www.fantester.com",
    "wof:name":"Airflow Measurement Systems",
    "wof:placetype":"venue"
},
  "geometry": {"coordinates":[-117.045998,32.62502],"type":"Point"}
}