{
  "type": "Feature",
  "properties": {
    "iso:country":"US",
    "sg:address":"6909 Mellodora Dr",
    "sg:city":"Orangevale",
    "sg:classifiers":[
        {
            "category":"Personal",
            "subcategory":"Beauty Salon",
            "type":"Services"
        }
    ],
    "sg:phone":"+1 916 728 4916",
    "sg:postcode":"95662",
    "sg:province":"CA",
    "wof:name":"Hair Sculptor Hair Design",
    "wof:placetype":"venue"
},
  "geometry": {"coordinates":[-121.250605,38.692928],"type":"Point"}
}