{
  "type": "Feature",
  "properties": {
    "iso:country":"US",
    "sg:address":"6678 Mallard St",
    "sg:city":"San Diego",
    "sg:classifiers":[
        {
            "category":"Wholesale",
            "subcategory":"Electrical",
            "type":"Manufacturing & Wholesale Goods"
        }
    ],
    "sg:phone":"+1 951 903 2771",
    "sg:postcode":"92114",
    "sg:province":"CA",
    "sg:tags":[
        "mobile",
        "dist",
        "agency",
        "talent"
    ],
    "wof:name":"A One Entrtnmnt/ Cmmunications",
    "wof:placetype":"venue"
},
  "geometry": {"coordinates":[-117.05314,32.729681],"type":"Point"}
}