{
  "type": "Feature",
  "properties": {
    "addr:full":"25401 Cabot Rd Laguna Hills CA 92653",
    "addr:housenumber":"25401",
    "addr:postcode":"92653",
    "addr:street":"Cabot Rd",
    "iso:country":"US",
    "sg:address":"25401 Cabot Rd",
    "sg:city":"Laguna Hills",
    "sg:classifiers":[
        {
            "category":"Mining & Drilling",
            "type":"Manufacturing & Wholesale Goods"
        }
    ],
    "sg:phone":"+1 949 859 2204",
    "sg:postcode":"92653",
    "sg:province":"CA",
    "wof:name":"H J Baker & Brother Inc",
    "wof:placetype":"venue"
},
  "geometry": {"coordinates":[-117.67466,33.592351],"type":"Point"}
}