{
  "type": "Feature",
  "properties": {
    "addr:full":"737 S Glendale Ave Glendale CA 91205",
    "addr:housenumber":"737",
    "addr:postcode":"91205",
    "addr:street":"S Glendale Ave",
    "iso:country":"US",
    "sg:address":"737 S Glendale Ave",
    "sg:city":"Glendale",
    "sg:classifiers":[
        {
            "category":"Wholesale",
            "subcategory":"Auto Parts",
            "type":"Manufacturing & Wholesale Goods"
        }
    ],
    "sg:phone":"+1 818 502 1836",
    "sg:postcode":"91205",
    "sg:province":"CA",
    "sg:tags":[
        "used"
    ],
    "wof:name":"A N J",
    "wof:placetype":"venue"
},
  "geometry": {"coordinates":[-118.251409,34.137301],"type":"Point"}
}