{
  "type": "Feature",
  "properties": {
    "addr:full":"149 N San Gorgonio Ave Banning CA 92220",
    "addr:housenumber":"149",
    "addr:postcode":"92220",
    "addr:street":"N San Gorgonio Ave",
    "iso:country":"US",
    "sg:address":"149 N San Gorgonio Ave",
    "sg:city":"Banning",
    "sg:classifiers":[
        {
            "category":"Professional",
            "subcategory":"Lawyer & Legal Services",
            "type":"Services"
        }
    ],
    "sg:phone":"+1 951 849 2913",
    "sg:postcode":"92220",
    "sg:province":"CA",
    "sg:tags":[
        "attorney",
        "planning",
        "estate"
    ],
    "wof:name":"Mc Clellan & Wilson",
    "wof:placetype":"venue"
},
  "geometry": {"coordinates":[-116.876739,33.926707],"type":"Point"}
}