{
  "type": "Feature",
  "properties": {
    "addr:full":"111 N Euclid St La Habra CA 90631",
    "addr:housenumber":"111",
    "addr:postcode":"90631",
    "addr:street":"N Euclid St",
    "iso:country":"US",
    "sg:address":"111 N Euclid St",
    "sg:city":"La Habra",
    "sg:classifiers":[
        {
            "category":"Health Services",
            "subcategory":"Doctor",
            "type":"Services"
        }
    ],
    "sg:phone":"+1 562 697 1229",
    "sg:postcode":"90631",
    "sg:province":"CA",
    "sg:tags":[
        "dentist"
    ],
    "wof:name":"George Arakelian Inc",
    "wof:placetype":"venue"
},
  "geometry": {"coordinates":[-117.946192,33.9322],"type":"Point"}
}