{
  "type": "Feature",
  "properties": {
    "addr:full":"6125 Enterprise Dr Diamond Springs CA 95619",
    "addr:housenumber":"6125",
    "addr:postcode":"ca 95619",
    "addr:street":"Enterprise Dr Diamond Springs",
    "iso:country":"US",
    "sg:address":"6125 Enterprise Dr",
    "sg:city":"Diamond Springs",
    "sg:classifiers":[
        {
            "category":"Wholesale",
            "subcategory":"Machinery & Supplies",
            "type":"Manufacturing & Wholesale Goods"
        },
        {
            "category":"Manufacturing",
            "subcategory":"Tools & Machinery",
            "type":"Manufacturing & Wholesale Goods"
        }
    ],
    "sg:phone":"+1 530 621 4088",
    "sg:postcode":"95619",
    "sg:province":"CA",
    "sg:tags":[
        "machine",
        "equipment",
        "industrial",
        "shop"
    ],
    "wof:name":"O R Tool Works",
    "wof:placetype":"venue"
},
  "geometry": {"coordinates":[-120.832095,38.693949],"type":"Point"}
}