{
  "type": "Feature",
  "properties": {
    "iso:country":"US",
    "sg:address":"85 E Colorado Blvd",
    "sg:city":"Pasadena",
    "sg:classifiers":[
        {
            "category":"Shopping",
            "subcategory":"Mobile Phones",
            "type":"Retail Goods"
        }
    ],
    "sg:phone":"+1 626 396 0100",
    "sg:postcode":"91105",
    "sg:province":"CA",
    "sg:website":"www.attwireless.com",
    "wof:name":"AT&T Wireless",
    "wof:placetype":"venue"
},
  "geometry": {"coordinates":[-118.149002,34.145901],"type":"Point"}
}