{
  "type": "Feature",
  "properties": {
    "iso:country":"US",
    "sg:address":"263 3rd St",
    "sg:city":"San Rafael",
    "sg:classifiers":[
        {
            "category":"Shopping",
            "subcategory":"Clothing, Apparel, & Fashions",
            "type":"Retail Goods"
        }
    ],
    "sg:phone":"+1 415 457 1835",
    "sg:postcode":"94901",
    "sg:province":"CA",
    "wof:name":"Three Wishes Fashion",
    "wof:placetype":"venue"
},
  "geometry": {"coordinates":[-122.51514899999999,37.969793],"type":"Point"}
}