{
  "type": "Feature",
  "properties": {
    "addr:full":"311 Laurent St Santa Cruz CA 95060",
    "addr:housenumber":"311",
    "addr:postcode":"95060",
    "addr:street":"Laurent St",
    "iso:country":"US",
    "sg:address":"311 Laurent St",
    "sg:city":"Santa Cruz",
    "sg:classifiers":[
        {
            "category":"Professional",
            "subcategory":"Engineering",
            "type":"Services"
        }
    ],
    "sg:phone":"+1 831 429 5018",
    "sg:postcode":"95060",
    "sg:province":"CA",
    "sg:tags":[
        "engineer"
    ],
    "wof:name":"Freitas Plus Freitas Conslnts",
    "wof:placetype":"venue"
},
  "geometry": {"coordinates":[-122.041771,36.969192],"type":"Point"}
}