{
  "type": "Feature",
  "properties": {
    "iso:country":"US",
    "sg:address":"1475 Echo Park Avenue",
    "sg:city":"Los Angeles",
    "sg:classifiers":[
        {
            "category":"Professional",
            "subcategory":"Lawyer & Legal Services",
            "type":"Services"
        }
    ],
    "sg:phone":"+1 213 250 5500",
    "sg:postcode":"90026",
    "sg:province":"CA",
    "sg:tags":[
        "divorce",
        "law",
        "family"
    ],
    "wof:name":"Working People's Law Center",
    "wof:placetype":"venue"
},
  "geometry": {"coordinates":[-118.25555799999999,34.079821],"type":"Point"}
}