{
  "type": "Feature",
  "properties": {
    "iso:country":"US",
    "sg:address":"863 Mission St",
    "sg:city":"San Francisco",
    "sg:classifiers":[
        {
            "category":"Arts & Performance",
            "subcategory":"Art Gallery",
            "type":"Entertainment"
        }
    ],
    "sg:phone":"+1 415 522 2440",
    "sg:postcode":"94199",
    "sg:province":"CA",
    "sg:website":"www.theartistsalley.com",
    "wof:name":"The Artists Alley",
    "wof:placetype":"venue"
},
  "geometry": {"coordinates":[-122.405682,37.78328],"type":"Point"}
}