{
  "type": "Feature",
  "properties": {
    "addr:full":"1019 L St Sacramento CA 95814",
    "addr:housenumber":"1019",
    "addr:postcode":"95814",
    "addr:street":"L St",
    "iso:country":"US",
    "sg:address":"1019 L St",
    "sg:city":"Sacramento",
    "sg:classifiers":[
        {
            "category":"Shopping",
            "subcategory":"Gifts & Souvenirs",
            "type":"Retail Goods"
        }
    ],
    "sg:phone":"+1 916 442 0207",
    "sg:postcode":"95814",
    "sg:province":"CA",
    "sg:tags":[
        "shop"
    ],
    "wof:name":"Joann's Elegant Gifts",
    "wof:placetype":"venue"
},
  "geometry": {"coordinates":[-121.493239,38.577883],"type":"Point"}
}