{
  "type": "Feature",
  "properties": {
    "addr:full":"1619 W 17th St Santa Ana CA 92706",
    "addr:housenumber":"1619",
    "addr:postcode":"92706",
    "addr:street":"W 17Th St",
    "iso:country":"US",
    "sg:address":"1619 W 17th St",
    "sg:city":"Santa Ana",
    "sg:classifiers":[
        {
            "category":"Shopping",
            "subcategory":"Gifts & Souvenirs",
            "type":"Retail Goods"
        }
    ],
    "sg:phone":"+1 714 571 0098",
    "sg:postcode":"92706",
    "sg:province":"CA",
    "sg:tags":[
        "party",
        "supply"
    ],
    "wof:name":"98 Cent Store",
    "wof:placetype":"venue"
},
  "geometry": {"coordinates":[-117.891839,33.759941],"type":"Point"}
}