{
  "type": "Feature",
  "properties": {
    "addr:full":"2215 S Bascom Ave Campbell CA 95008",
    "addr:housenumber":"2215",
    "addr:postcode":"95008",
    "addr:street":"S Bascom Ave",
    "iso:country":"US",
    "sg:address":"2215 S Bascom Ave",
    "sg:city":"Campbell",
    "sg:classifiers":[
        {
            "category":"Shopping",
            "subcategory":"Books",
            "type":"Retail Goods"
        }
    ],
    "sg:phone":"+1 408 377 9452",
    "sg:postcode":"95008",
    "sg:province":"CA",
    "sg:tags":[
        "bookstore"
    ],
    "wof:name":"Church of Jesus Christ of Latter-Day Saints the",
    "wof:placetype":"venue"
},
  "geometry": {"coordinates":[-121.93204799999999,37.283336],"type":"Point"}
}