{
  "type": "Feature",
  "properties": {
    "iso:country":"US",
    "sg:address":"25548 Novela Way",
    "sg:city":"Valencia",
    "sg:classifiers":[
        {
            "category":"Professional",
            "subcategory":"Management & Consulting",
            "type":"Services"
        }
    ],
    "sg:phone":"+1 661 255 8029",
    "sg:postcode":"91355",
    "sg:province":"CA",
    "sg:tags":[
        "retail",
        "direct",
        "sales"
    ],
    "wof:name":"Donna M Rice",
    "wof:placetype":"venue"
},
  "geometry": {"coordinates":[-118.552924,34.392517],"type":"Point"}
}