{
  "type": "Feature",
  "properties": {
    "addr:full":"11058 Limonite Ave Mira Loma CA 91752",
    "addr:housenumber":"11058",
    "addr:postcode":"91752",
    "addr:street":"Limonite Ave",
    "iso:country":"US",
    "sg:address":"11058 Limonite Ave",
    "sg:city":"Mira Loma",
    "sg:classifiers":[
        {
            "category":"Health Services",
            "subcategory":"Doctor",
            "type":"Services"
        }
    ],
    "sg:phone":"+1 951 737 6005",
    "sg:postcode":"91752",
    "sg:province":"CA",
    "sg:tags":[
        "dentist"
    ],
    "wof:name":"Mira Loma Dental Ctr",
    "wof:placetype":"venue"
},
  "geometry": {"coordinates":[-117.531058,33.975237],"type":"Point"}
}