{
  "type": "Feature",
  "properties": {
    "iso:country":"US",
    "sg:address":"901 Cedarcrest Dr",
    "sg:city":"Vacaville",
    "sg:classifiers":[
        {
            "category":"Retail",
            "subcategory":"Laundry & Dry Cleaning",
            "type":"Services"
        }
    ],
    "sg:phone":"+1 707 425 0144",
    "sg:postcode":"95687",
    "sg:province":"CA",
    "sg:tags":[
        "cleaners",
        "rug",
        "carpet"
    ],
    "wof:name":"Clean Sweep Carpet Care",
    "wof:placetype":"venue"
},
  "geometry": {"coordinates":[-121.956327,38.320244],"type":"Point"}
}