{
  "type": "Feature",
  "properties": {
    "iso:country":"US",
    "sg:address":"10721 White Rock Rd",
    "sg:city":"Rancho Cordova",
    "sg:classifiers":[
        {
            "category":"Travel",
            "subcategory":"Hotels & Motels",
            "type":"Entertainment"
        },
        {
            "category":"Real Estate",
            "subcategory":"Real Estate Operator",
            "type":"Services"
        }
    ],
    "sg:phone":"+1 916 635 2363",
    "sg:postcode":"95670",
    "sg:province":"CA",
    "sg:tags":[
        "apartment"
    ],
    "wof:name":"Extended Stayamerica",
    "wof:placetype":"venue"
},
  "geometry": {"coordinates":[-121.29499800000001,38.585602],"type":"Point"}
}