{
  "type": "Feature",
  "properties": {
    "iso:country":"US",
    "sg:address":"2570 Boeing Way",
    "sg:city":"Stockton",
    "sg:classifiers":[
        {
            "category":"Professional",
            "subcategory":"Management & Consulting",
            "type":"Services"
        }
    ],
    "sg:phone":"+1 209 983 8038",
    "sg:postcode":"95206",
    "sg:province":"CA",
    "sg:tags":[
        "logistics"
    ],
    "wof:name":"Carolina Logistics Svc",
    "wof:placetype":"venue"
},
  "geometry": {"coordinates":[-121.234373,37.910714],"type":"Point"}
}