{
  "type": "Feature",
  "properties": {
    "iso:country":"US",
    "sg:address":"5112 el Rivino Rd",
    "sg:city":"Riverside",
    "sg:classifiers":[
        {
            "category":"Manufacturing",
            "subcategory":"Tools & Machinery",
            "type":"Manufacturing & Wholesale Goods"
        }
    ],
    "sg:phone":"+1 951 276 1739",
    "sg:postcode":"92509",
    "sg:province":"CA",
    "sg:tags":[
        "operator",
        "equipment",
        "mfg",
        "trucking"
    ],
    "wof:name":"TNT Pilot Service",
    "wof:placetype":"venue"
},
  "geometry": {"coordinates":[-117.385371,34.03379],"type":"Point"}
}