{
  "type": "Feature",
  "properties": {
    "iso:country":"US",
    "sg:address":"1995 University Ave",
    "sg:city":"Berkeley",
    "sg:classifiers":[
        {
            "category":"Real Estate",
            "subcategory":"Real Estate Agent",
            "type":"Services"
        }
    ],
    "sg:phone":"+1 510 549 4510",
    "sg:postcode":"94704",
    "sg:province":"CA",
    "sg:tags":[
        "consultant"
    ],
    "sg:website":"www.rosenconsulting.com",
    "wof:name":"Rosen Consulting Group",
    "wof:placetype":"venue"
},
  "geometry": {"coordinates":[-122.27094700000001,37.871865],"type":"Point"}
}