{
  "type": "Feature",
  "properties": {
    "iso:country":"US",
    "sg:address":"1810 Gateway Dr",
    "sg:city":"Foster City",
    "sg:classifiers":[
        {
            "category":"Professional",
            "subcategory":"Employment Agencies",
            "type":"Services"
        }
    ],
    "sg:phone":"+1 650 356 1100",
    "sg:postcode":"94404",
    "sg:province":"CA",
    "sg:tags":[
        "opportunity"
    ],
    "wof:name":"Culver Careers",
    "wof:placetype":"venue"
},
  "geometry": {"coordinates":[-122.281189,37.555819],"type":"Point"}
}