{
  "type": "Feature",
  "properties": {
    "addr:full":"1139 San Julian Street Los Angeles CA 90015",
    "addr:housenumber":"1139",
    "addr:postcode":"90015",
    "addr:street":"San Julian Street",
    "iso:country":"US",
    "sg:address":"1139 San Julian Street",
    "sg:city":"Los Angeles",
    "sg:classifiers":[
        {
            "category":"Shopping",
            "subcategory":"Clothing, Apparel, & Fashions",
            "type":"Retail Goods"
        }
    ],
    "sg:phone":"+1 213 749 4636",
    "sg:postcode":"90015",
    "sg:province":"CA",
    "sg:tags":[
        "children's",
        "clothing",
        "women's"
    ],
    "wof:name":"Wonky Fashion",
    "wof:placetype":"venue"
},
  "geometry": {"coordinates":[-118.254105,34.034457],"type":"Point"}
}