{
  "type": "Feature",
  "properties": {
    "iso:country":"US",
    "sg:address":"10390 Commerce Center Dr",
    "sg:city":"Rancho Cucamonga",
    "sg:classifiers":[
        {
            "category":"Banks & Credit Unions",
            "subcategory":"Bank",
            "type":"Services"
        }
    ],
    "sg:phone":"+1 909 581 1099",
    "sg:postcode":"91730",
    "sg:province":"CA",
    "sg:tags":[
        "loan"
    ],
    "sg:website":"www.myloronline.com",
    "wof:name":"Mylor Financial",
    "wof:placetype":"venue"
},
  "geometry": {"coordinates":[-117.578227,34.078458],"type":"Point"}
}