{
  "type": "Feature",
  "properties": {
    "addr:full":"2736 Winfield Dr Mountain View CA 94040",
    "addr:housenumber":"2736",
    "addr:postcode":"94040",
    "addr:street":"Winfield Dr",
    "iso:country":"US",
    "sg:address":"2736 Winfield Dr",
    "sg:city":"Mountain View",
    "sg:classifiers":[
        {
            "category":"Professional",
            "subcategory":"Management & Consulting",
            "type":"Services"
        }
    ],
    "sg:phone":"+1 650 964 3974",
    "sg:postcode":"94040",
    "sg:province":"CA",
    "sg:tags":[
        "automobile",
        "used",
        "ev",
        "electric"
    ],
    "wof:name":"Evi",
    "wof:placetype":"venue"
},
  "geometry": {"coordinates":[-122.07550500000001,37.363697],"type":"Point"}
}