{
  "type": "Feature",
  "properties": {
    "iso:country":"US",
    "sg:address":"19545 E Cienega Ave",
    "sg:city":"Covina",
    "sg:classifiers":[
        {
            "category":"Social Services",
            "subcategory":"Child Care",
            "type":"Services"
        }
    ],
    "sg:phone":"+1 626 332 8519",
    "sg:postcode":"91724",
    "sg:province":"CA",
    "wof:name":"Cumorah Academy",
    "wof:placetype":"venue"
},
  "geometry": {"coordinates":[-117.872229,34.103135],"type":"Point"}
}