{
  "type": "Feature",
  "properties": {
    "iso:country":"US",
    "sg:address":"650 E Parkridge Ave",
    "sg:city":"Corona",
    "sg:classifiers":[
        {
            "category":"Wholesale",
            "subcategory":"Office Equipment",
            "type":"Manufacturing & Wholesale Goods"
        }
    ],
    "sg:phone":"+1 951 278 4955",
    "sg:postcode":"92879",
    "sg:province":"CA",
    "sg:tags":[
        "scanning",
        "code",
        "bar"
    ],
    "wof:name":"Bar Code Specialties",
    "wof:placetype":"venue"
},
  "geometry": {"coordinates":[-117.553471,33.884542],"type":"Point"}
}