{
  "type": "Feature",
  "properties": {
    "addr:full":"4155 Erbes Rd Thousand Oaks CA 91360",
    "addr:housenumber":"4155",
    "addr:postcode":"91360",
    "addr:street":"Erbes Rd",
    "iso:country":"US",
    "sg:address":"4155 Erbes Rd",
    "sg:city":"Thousand Oaks",
    "sg:classifiers":[
        {
            "category":"Recreation",
            "type":"Entertainment"
        }
    ],
    "sg:phone":"+1 805 495 6484",
    "sg:postcode":"91360",
    "sg:province":"CA",
    "sg:tags":[
        "course",
        "golf"
    ],
    "wof:name":"Sunset Hills Country Club",
    "wof:placetype":"venue"
},
  "geometry": {"coordinates":[-118.847926,34.238419],"type":"Point"}
}