{
  "type": "Feature",
  "properties": {
    "addr:full":"8439 Elk Grove Blvd Elk Grove CA 95758",
    "addr:housenumber":"8439",
    "addr:postcode":"95758",
    "addr:street":"Elk Grove Blvd",
    "iso:country":"US",
    "sg:address":"8439 Elk Grove Blvd",
    "sg:city":"Elk Grove",
    "sg:classifiers":[
        {
            "category":"Personal",
            "subcategory":"Beauty Salon",
            "type":"Services"
        }
    ],
    "sg:phone":"+1 916 681 9603",
    "sg:postcode":"95758",
    "sg:province":"CA",
    "wof:name":"Hair Obsession",
    "wof:placetype":"venue"
},
  "geometry": {"coordinates":[-121.390519,38.408991],"type":"Point"}
}