{
  "type": "Feature",
  "properties": {
    "iso:country":"US",
    "sg:address":"16211 Bear Valley Rd",
    "sg:city":"Hesperia",
    "sg:classifiers":[
        {
            "category":"Social Services",
            "subcategory":"Child Care",
            "type":"Services"
        }
    ],
    "sg:phone":"+1 760 956 6002",
    "sg:postcode":"92345",
    "sg:province":"CA",
    "wof:name":"Dream Tenders",
    "wof:placetype":"venue"
},
  "geometry": {"coordinates":[-117.31032399999999,34.470717],"type":"Point"}
}