{
  "type": "Feature",
  "properties": {
    "iso:country":"US",
    "sfac:artist":"Segal, George",
    "sfac:created_at":"01/01/1970 12:33:02 AM +0000",
    "sfac:credit_line":"Commissioned by the Mayor's Committee for a Memorial to the Six Million Victims of the Holocaust",
    "sfac:display_dimensions":"66 in. x 144 in. x 144 in.",
    "sfac:location_description":"Public Display : District 1 : Lincoln Park : Land's End",
    "sfac:medium":"Cast and painted bronze and wire",
    "sfac:revision":"2-e3c505f76ca69ec0e6b7ba1fc8b71368",
    "sfac:title":"The Holocaust",
    "wof:name":"The Holocaust",
    "wof:placetype":"venue"
},
  "geometry": {"coordinates":[-122.5056701,37.78773899999999],"type":"Point"}
}