{
  "type": "Feature",
  "properties": {
    "iso:country":"US",
    "sg:address":"129 E Central Ave",
    "sg:city":"Lompoc",
    "sg:classifiers":[
        {
            "category":"Social Services",
            "subcategory":"Job Training",
            "type":"Services"
        }
    ],
    "sg:phone":"+1 805 735 9400",
    "sg:postcode":"93436",
    "sg:province":"CA",
    "sg:tags":[
        "employment"
    ],
    "wof:name":"Atlas Computer Ctr",
    "wof:placetype":"venue"
},
  "geometry": {"coordinates":[-120.455269,34.660884],"type":"Point"}
}