{
  "type": "Feature",
  "properties": {
    "iso:country":"US",
    "sg:address":"26 S 3rd St",
    "sg:city":"Patterson",
    "sg:classifiers":[
        {
            "category":"Banks & Credit Unions",
            "subcategory":"Bank",
            "type":"Services"
        }
    ],
    "sg:phone":"+1 209 895 9400",
    "sg:postcode":"95363",
    "sg:province":"CA",
    "sg:tags":[
        "loan",
        "real estate"
    ],
    "wof:name":"Acceptance Capitol Mortgage",
    "wof:placetype":"venue"
},
  "geometry": {"coordinates":[-121.129199,37.470387],"type":"Point"}
}