{
  "type": "Feature",
  "properties": {
    "addr:full":"1816 Bonnie Way Sacramento CA 95825",
    "addr:housenumber":"1816",
    "addr:postcode":"95825",
    "addr:street":"Bonnie Way",
    "iso:country":"US",
    "sg:address":"1816 Bonnie Way",
    "sg:city":"Sacramento",
    "sg:classifiers":[
        {
            "category":"Building & Trades",
            "subcategory":"Landscaping Services",
            "type":"Services"
        }
    ],
    "sg:phone":"+1 916 489 3278",
    "sg:postcode":"95825",
    "sg:province":"CA",
    "sg:tags":[
        "landscape",
        "contractor"
    ],
    "wof:name":"River City Landscape",
    "wof:placetype":"venue"
},
  "geometry": {"coordinates":[-121.394392,38.599249],"type":"Point"}
}