{
  "type": "Feature",
  "properties": {
    "addr:full":"3878 Carlsbad Blvd Carlsbad CA 92008",
    "addr:housenumber":"3878",
    "addr:postcode":"92008",
    "addr:street":"Carlsbad Blvd",
    "iso:country":"US",
    "sg:address":"3878 Carlsbad Blvd",
    "sg:city":"Carlsbad",
    "sg:classifiers":[
        {
            "category":"Restaurant",
            "type":"Food & Drink"
        }
    ],
    "sg:phone":"+1 760 434 2580",
    "sg:postcode":"92008",
    "sg:province":"CA",
    "sg:tags":[
        "seafood",
        "steakhouse",
        "italian"
    ],
    "sg:website":"www.vigiluccis.com",
    "wof:name":"Vigilucci's Seafood & Steakhouse",
    "wof:placetype":"venue"
},
  "geometry": {"coordinates":[-117.345297,33.147966],"type":"Point"}
}