{
  "type": "Feature",
  "properties": {
    "iso:country":"US",
    "sg:address":"7 Toscany",
    "sg:city":"Irvine",
    "sg:classifiers":[
        {
            "category":"Professional",
            "type":"Services"
        }
    ],
    "sg:phone":"+1 949 724 1200",
    "sg:postcode":"92614",
    "sg:province":"CA",
    "wof:name":"Allen Allen USA",
    "wof:placetype":"venue"
},
  "geometry": {"coordinates":[-117.816625,33.680755],"type":"Point"}
}