{
  "type": "Feature",
  "properties": {
    "iso:country":"US",
    "sg:address":"10522 McFadden Ave",
    "sg:city":"Garden Grove",
    "sg:classifiers":[
        {
            "category":"Travel",
            "subcategory":"Travel Agent",
            "type":"Entertainment"
        }
    ],
    "sg:phone":"+1 714 531 6688",
    "sg:postcode":"92683",
    "sg:province":"CA",
    "sg:tags":[
        "agency"
    ],
    "wof:name":"Five Star World Travel",
    "wof:placetype":"venue"
},
  "geometry": {"coordinates":[-117.94402100000001,33.737972],"type":"Point"}
}