{
  "type": "Feature",
  "properties": {
    "addr:full":"5557 Rubion Cir Citrus Heights CA 95610",
    "addr:housenumber":"5557",
    "addr:postcode":"95610",
    "addr:street":"Rubion Cir",
    "iso:country":"US",
    "sg:address":"5557 Rubion Cir",
    "sg:city":"Citrus Heights",
    "sg:classifiers":[
        {
            "category":"Professional",
            "type":"Services"
        }
    ],
    "sg:phone":"+1 916 956 1196",
    "sg:postcode":"95610",
    "sg:province":"CA",
    "sg:tags":[
        "establishment"
    ],
    "wof:name":"Alternative Healing",
    "wof:placetype":"venue"
},
  "geometry": {"coordinates":[-121.267853,38.66553],"type":"Point"}
}