{
  "type": "Feature",
  "properties": {
    "iso:country":"US",
    "sg:address":"46164 Warm Springs Blvd",
    "sg:city":"Fremont",
    "sg:classifiers":[
        {
            "category":"Home & Garden",
            "subcategory":"Carpets & Floor Coverings",
            "type":"Retail Goods"
        }
    ],
    "sg:phone":"+1 510 498 8879",
    "sg:postcode":"94539",
    "sg:province":"CA",
    "sg:tags":[
        "flooring"
    ],
    "wof:name":"Dmca",
    "wof:placetype":"venue"
},
  "geometry": {"coordinates":[-121.93104099999999,37.492999],"type":"Point"}
}