{
  "type": "Feature",
  "properties": {
    "addr:full":"120 W Warner Ave Santa Ana CA 92707",
    "addr:housenumber":"120",
    "addr:postcode":"92707",
    "addr:street":"W Warner Ave",
    "iso:country":"US",
    "sg:address":"120 W Warner Ave",
    "sg:city":"Santa Ana",
    "sg:classifiers":[
        {
            "category":"Autos & Motor Vehicles",
            "subcategory":"Auto Supplies",
            "type":"Retail Goods"
        }
    ],
    "sg:phone":"+1 714 545 5818",
    "sg:postcode":"92707",
    "sg:province":"CA",
    "sg:tags":[
        "tire"
    ],
    "wof:name":"Pete's Road Service Inc",
    "wof:placetype":"venue"
},
  "geometry": {"coordinates":[-117.86900300000001,33.716099],"type":"Point"}
}