{
  "type": "Feature",
  "properties": {
    "addr:full":"1859 Sutter Ave Simi Valley CA 93065",
    "addr:housenumber":"1859",
    "addr:postcode":"93065",
    "addr:street":"Sutter Ave",
    "iso:country":"US",
    "sg:address":"1859 Sutter Ave",
    "sg:city":"Simi Valley",
    "sg:classifiers":[
        {
            "category":"Building & Trades",
            "subcategory":"Plumbing",
            "type":"Services"
        }
    ],
    "sg:phone":"+1 805 581 3881",
    "sg:postcode":"93065",
    "sg:province":"CA",
    "sg:tags":[
        "plumbing",
        "contractor"
    ],
    "wof:name":"Gen X Plumbing Co",
    "wof:placetype":"venue"
},
  "geometry": {"coordinates":[-118.76440100000001,34.263815],"type":"Point"}
}