{
  "type": "Feature",
  "properties": {
    "addr:full":"1059 South Alvarado Street Los Angeles CA 90006",
    "addr:housenumber":"1059",
    "addr:postcode":"90006",
    "addr:street":"South Alvarado Street",
    "iso:country":"US",
    "sg:address":"1059 South Alvarado Street",
    "sg:city":"Los Angeles",
    "sg:classifiers":[
        {
            "category":"Restaurant",
            "type":"Food & Drink"
        }
    ],
    "sg:phone":"+1 213 738 8814",
    "sg:postcode":"90006",
    "sg:province":"CA",
    "wof:name":"Pronto Pizza",
    "wof:placetype":"venue"
},
  "geometry": {"coordinates":[-118.28060600000001,34.050545],"type":"Point"}
}