{
  "type": "Feature",
  "properties": {
    "iso:country":"US",
    "sg:address":"96 Niblick Rd",
    "sg:city":"Paso Robles",
    "sg:classifiers":[
        {
            "category":"Restaurant",
            "type":"Food & Drink"
        }
    ],
    "sg:menulink":"http://www.allmenus.com/ca/paso-robles/135596-jamba-juice/menu/",
    "sg:phone":"+1 805 227 0826",
    "sg:postcode":"93446",
    "sg:province":"CA",
    "sg:tags":[
        "smoothy",
        "juice",
        "american"
    ],
    "wof:name":"Jamba Juice",
    "wof:placetype":"venue"
},
  "geometry": {"coordinates":[-120.689684,35.615227],"type":"Point"}
}