{
  "type": "Feature",
  "properties": {
    "addr:full":"1752 Mentone Blvd Fontana CA 92359",
    "addr:housenumber":"1752",
    "addr:postcode":"92359",
    "addr:street":"Mentone Blvd",
    "iso:country":"US",
    "sg:address":"1752 Mentone Blvd",
    "sg:city":"Fontana",
    "sg:classifiers":[
        {
            "category":"Shopping",
            "subcategory":"Florist",
            "type":"Retail Goods"
        }
    ],
    "sg:phone":"+1 909 864 4403",
    "sg:postcode":"92359",
    "sg:province":"CA",
    "wof:name":"Petals & Stems Florist",
    "wof:placetype":"venue"
},
  "geometry": {"coordinates":[-117.137164,34.070039],"type":"Point"}
}