{
  "type": "Feature",
  "properties": {
    "addr:full":"11816 Artesia Blvd Artesia CA 90701",
    "addr:housenumber":"11816",
    "addr:postcode":"90701",
    "addr:street":"Artesia Blvd",
    "iso:country":"US",
    "sg:address":"11816 Artesia Blvd",
    "sg:city":"Artesia",
    "sg:classifiers":[
        {
            "category":"Shopping",
            "subcategory":"Florist",
            "type":"Retail Goods"
        }
    ],
    "sg:phone":"+1 562 860 4226",
    "sg:postcode":"90701",
    "sg:province":"CA",
    "wof:name":"Ideal Florist",
    "wof:placetype":"venue"
},
  "geometry": {"coordinates":[-118.08200100000001,33.872898],"type":"Point"}
}