{
  "type": "Feature",
  "properties": {
    "addr:full":"7221 Garden Grove Blvd Garden Grove CA 92841",
    "addr:housenumber":"7221",
    "addr:postcode":"92841",
    "addr:street":"Garden Grove Blvd",
    "iso:country":"US",
    "sg:address":"7221 Garden Grove Blvd",
    "sg:city":"Garden Grove",
    "sg:classifiers":[
        {
            "category":"Wholesale",
            "subcategory":"Apparel",
            "type":"Manufacturing & Wholesale Goods"
        }
    ],
    "sg:phone":"+1 714 896 0008",
    "sg:postcode":"92841",
    "sg:province":"CA",
    "sg:tags":[
        "hosiery"
    ],
    "wof:name":"A B C Hosiery",
    "wof:placetype":"venue"
},
  "geometry": {"coordinates":[-118.005202,33.773787],"type":"Point"}
}