{
  "type": "Feature",
  "properties": {
    "addr:full":"20265 Ventura Blvd Woodland Hills CA 91364",
    "addr:housenumber":"20265",
    "addr:postcode":"91364",
    "addr:street":"Ventura Blvd",
    "iso:country":"US",
    "sg:address":"20265 Ventura Blvd",
    "sg:city":"Woodland Hills",
    "sg:classifiers":[
        {
            "category":"Arts & Performance",
            "subcategory":"Theater",
            "type":"Entertainment"
        }
    ],
    "sg:phone":"+1 818 713 9111",
    "sg:postcode":"91364",
    "sg:province":"CA",
    "sg:tags":[
        "band",
        "orchestra"
    ],
    "sg:website":"www.serenitysong.com",
    "wof:name":"Fifth Avenue Orchestras",
    "wof:placetype":"venue"
},
  "geometry": {"coordinates":[-118.572216,34.170776],"type":"Point"}
}