{
  "type": "Feature",
  "properties": {
    "iso:country":"US",
    "sg:address":"20575 Valley Blvd",
    "sg:city":"Walnut",
    "sg:classifiers":[
        {
            "category":"Professional",
            "subcategory":"Employment Agencies",
            "type":"Services"
        }
    ],
    "sg:phone":"+1 909 444 0484",
    "sg:postcode":"91789",
    "sg:province":"CA",
    "sg:tags":[
        "opportunity"
    ],
    "wof:name":"Select Personal",
    "wof:placetype":"venue"
},
  "geometry": {"coordinates":[-117.858496,34.010031],"type":"Point"}
}