{
  "type": "Feature",
  "properties": {
    "addr:full":"1601 Butano Dr Milpitas CA 95035",
    "addr:housenumber":"1601",
    "addr:postcode":"95035",
    "addr:street":"Butano Dr",
    "iso:country":"US",
    "sg:address":"1601 Butano Dr",
    "sg:city":"Milpitas",
    "sg:classifiers":[
        {
            "category":"Manufacturing",
            "subcategory":"Printing",
            "type":"Manufacturing & Wholesale Goods"
        }
    ],
    "sg:phone":"+1 408 945 3963",
    "sg:postcode":"95035",
    "sg:province":"CA",
    "sg:tags":[
        "publishing"
    ],
    "wof:name":"Gremost Publications",
    "wof:placetype":"venue"
},
  "geometry": {"coordinates":[-121.870373,37.419793],"type":"Point"}
}