{
  "type": "Feature",
  "properties": {
    "addr:full":"1100 Hastings Rd # B Ukiah CA 95482",
    "addr:housenumber":"1100",
    "addr:postcode":"ca 95482",
    "addr:street":"Hastings Rd # B",
    "iso:country":"US",
    "sg:address":"1100 Hastings Rd # B",
    "sg:city":"Ukiah",
    "sg:classifiers":[
        {
            "category":"Communications",
            "subcategory":"Radio Station",
            "type":"Services"
        }
    ],
    "sg:phone":"+1 707 462 1483",
    "sg:postcode":"95482",
    "sg:province":"CA",
    "sg:tags":[
        "broadcast"
    ],
    "wof:name":"KMKX",
    "wof:placetype":"venue"
},
  "geometry": {"coordinates":[-123.191582,39.136459],"type":"Point"}
}