{
  "type": "Feature",
  "properties": {
    "iso:country":"US",
    "sg:address":"1631 Montana Ave",
    "sg:city":"Santa Monica",
    "sg:classifiers":[
        {
            "category":"Shopping",
            "subcategory":"Pharmacy",
            "type":"Retail Goods"
        }
    ],
    "sg:phone":"+1 310 393 0761",
    "sg:postcode":"90403",
    "sg:province":"CA",
    "wof:name":"Regent Square Pharmacy",
    "wof:placetype":"venue"
},
  "geometry": {"coordinates":[-118.492617,34.034318],"type":"Point"}
}