{
  "type": "Feature",
  "properties": {
    "addr:full":"4605 Frazee Rd Oceanside CA 92049",
    "addr:housenumber":"4605",
    "addr:postcode":"92049",
    "addr:street":"Frazee Rd",
    "iso:country":"US",
    "sg:address":"4605 Frazee Rd",
    "sg:city":"Oceanside",
    "sg:classifiers":[
        {
            "category":"Fast Food",
            "type":"Food & Drink"
        }
    ],
    "sg:phone":"+1 800 786 1000",
    "sg:postcode":"92049",
    "sg:province":"CA",
    "sg:website":"www.in-n-out.com",
    "wof:name":"In-N-Out Burger",
    "wof:placetype":"venue"
},
  "geometry": {"coordinates":[-117.299206,33.237858],"type":"Point"}
}