{
  "type": "Feature",
  "properties": {
    "addr:full":"1333 Lincoln Ave Calistoga CA 94515",
    "addr:housenumber":"1333",
    "addr:postcode":"94515",
    "addr:street":"Lincoln Ave",
    "iso:country":"US",
    "sg:address":"1333 Lincoln Ave",
    "sg:city":"Calistoga",
    "sg:classifiers":[
        {
            "category":"Shopping",
            "subcategory":"Bicycles & Sporting Goods",
            "type":"Retail Goods"
        }
    ],
    "sg:phone":"+1 415 726 6524",
    "sg:postcode":"94515",
    "sg:province":"CA",
    "sg:tags":[
        "equipment",
        "outdoor",
        "accessory"
    ],
    "wof:name":"Mountain Where",
    "wof:placetype":"venue"
},
  "geometry": {"coordinates":[-122.579176,38.578356],"type":"Point"}
}