{
  "type": "Feature",
  "properties": {
    "addr:full":"504 Windcove Pl Bakersfield CA 93308",
    "addr:housenumber":"504",
    "addr:postcode":"93308",
    "addr:street":"Windcove Pl",
    "iso:country":"US",
    "sg:address":"504 Windcove Pl",
    "sg:city":"Bakersfield",
    "sg:classifiers":[
        {
            "category":"Manufacturing",
            "subcategory":"Metals",
            "type":"Manufacturing & Wholesale Goods"
        }
    ],
    "sg:phone":"+1 661 393 5115",
    "sg:postcode":"93308",
    "sg:province":"CA",
    "sg:tags":[
        "coating"
    ],
    "wof:name":"Custom Coatings Of Bakersfield",
    "wof:placetype":"venue"
},
  "geometry": {"coordinates":[-119.030612,35.431003],"type":"Point"}
}