{
  "type": "Feature",
  "properties": {
    "iso:country":"US",
    "sg:address":"22596 E Cliff Drive",
    "sg:city":"Santa Cruz",
    "sg:classifiers":[
        {
            "category":"Personal",
            "subcategory":"Beauty Salon",
            "type":"Services"
        }
    ],
    "sg:phone":"+1 831 475 2508",
    "sg:postcode":"95062",
    "sg:province":"CA",
    "sg:tags":[
        "hair"
    ],
    "wof:name":"Medusa Hair Salon",
    "wof:placetype":"venue"
},
  "geometry": {"coordinates":[-121.980833,36.958709],"type":"Point"}
}