{
  "type": "Feature",
  "properties": {
    "iso:country":"US",
    "sg:address":"870 Haddock St",
    "sg:city":"San Mateo",
    "sg:classifiers":[
        {
            "category":"Wholesale",
            "subcategory":"Computers",
            "type":"Manufacturing & Wholesale Goods"
        }
    ],
    "sg:phone":"+1 650 846 1140",
    "sg:postcode":"94404",
    "sg:province":"CA",
    "sg:tags":[
        "consulting"
    ],
    "wof:name":"Proper Connection Computers",
    "wof:placetype":"venue"
},
  "geometry": {"coordinates":[-122.250368,37.554959],"type":"Point"}
}