{
  "type": "Feature",
  "properties": {
    "iso:country":"US",
    "sg:address":"4418 S Broadway",
    "sg:city":"Los Angeles",
    "sg:classifiers":[
        {
            "category":"Personal",
            "subcategory":"Beauty Salon",
            "type":"Services"
        }
    ],
    "sg:phone":"+1 323 232 0751",
    "sg:postcode":"90037",
    "sg:province":"CA",
    "sg:tags":[
        "barber"
    ],
    "wof:name":"Delcy Beauty Salon",
    "wof:placetype":"venue"
},
  "geometry": {"coordinates":[-118.27847300000001,34.003563],"type":"Point"}
}