{
  "type": "Feature",
  "properties": {
    "addr:full":"19657 Ventura Blvd Tarzana CA 91356",
    "addr:housenumber":"19657",
    "addr:postcode":"91356",
    "addr:street":"Ventura Blvd",
    "iso:country":"US",
    "sg:address":"19657 Ventura Blvd",
    "sg:city":"Tarzana",
    "sg:classifiers":[
        {
            "category":"Home & Garden",
            "subcategory":"Carpets & Floor Coverings",
            "type":"Retail Goods"
        }
    ],
    "sg:phone":"+1 818 342 9777",
    "sg:postcode":"91356",
    "sg:province":"CA",
    "sg:tags":[
        "rug",
        "carpeting"
    ],
    "sg:website":"www.customblind.com",
    "wof:name":"Custom Blind & Carpet Co",
    "wof:placetype":"venue"
},
  "geometry": {"coordinates":[-118.560997,34.172699],"type":"Point"}
}