{
  "type": "Feature",
  "properties": {
    "addr:full":"1530 El Camino Ave Sacramento CA 95815",
    "addr:housenumber":"1530",
    "addr:postcode":"95815",
    "addr:street":"El Camino Ave",
    "iso:country":"US",
    "sg:address":"1530 El Camino Ave",
    "sg:city":"Sacramento",
    "sg:classifiers":[
        {
            "category":"Recreation",
            "type":"Entertainment"
        }
    ],
    "sg:phone":"+1 916 929 8188",
    "sg:postcode":"95815",
    "sg:province":"CA",
    "sg:tags":[
        "active",
        "life"
    ],
    "sg:website":"www.dolphinscuba.com",
    "wof:name":"Dolphin Scuba Center & Swim School",
    "wof:placetype":"venue"
},
  "geometry": {"coordinates":[-121.43118699999999,38.610922],"type":"Point"}
}