{
  "type": "Feature",
  "properties": {
    "addr:full":"1142 N Matthew Ave Farmersville CA 93223",
    "addr:housenumber":"1142",
    "addr:postcode":"93223",
    "addr:street":"N Matthew Ave",
    "iso:country":"US",
    "sg:address":"1142 N Matthew Ave",
    "sg:city":"Farmersville",
    "sg:classifiers":[
        {
            "category":"Wholesale",
            "subcategory":"Drugs",
            "type":"Manufacturing & Wholesale Goods"
        }
    ],
    "sg:phone":"+1 559 747 0560",
    "sg:postcode":"93223",
    "sg:province":"CA",
    "wof:name":"Rancho Medical Services",
    "wof:placetype":"venue"
},
  "geometry": {"coordinates":[-119.21245999999999,36.306216],"type":"Point"}
}