{
  "type": "Feature",
  "properties": {
    "iso:country":"US",
    "sg:address":"341 Lafayette St #106",
    "sg:city":"Santa Clara",
    "sg:classifiers":[
        {
            "category":"Sports & Exercise",
            "subcategory":"Gym",
            "type":"Entertainment"
        }
    ],
    "sg:phone":"+1 408 509 3497",
    "sg:postcode":"95050",
    "sg:province":"CA",
    "sg:tags":[
        "trainer"
    ],
    "sg:website":"www.FSTworkout.com",
    "wof:name":"Functional Strength Training",
    "wof:placetype":"venue"
},
  "geometry": {"coordinates":[-121.940901,37.344444],"type":"Point"}
}