{
  "type": "Feature",
  "properties": {
    "addr:full":"5137 E Truman Ave Fresno CA 93725",
    "addr:housenumber":"5137",
    "addr:postcode":"93725",
    "addr:street":"E Truman Ave",
    "iso:country":"US",
    "sg:address":"5137 E Truman Ave",
    "sg:city":"Fresno",
    "sg:classifiers":[
        {
            "category":"Building & Trades",
            "subcategory":"Cleaning & Sanitation",
            "type":"Services"
        }
    ],
    "sg:phone":"+1 559 251 3151",
    "sg:postcode":"93725",
    "sg:province":"CA",
    "sg:tags":[
        "janitorial"
    ],
    "wof:name":"Abc Janitorial Services",
    "wof:placetype":"venue"
},
  "geometry": {"coordinates":[-119.720084,36.717449],"type":"Point"}
}