{
  "type": "Feature",
  "properties": {
    "addr:full":"2660 Diamond St Rosamond CA 93560",
    "addr:housenumber":"2660",
    "addr:postcode":"93560",
    "addr:street":"Diamond St",
    "iso:country":"US",
    "sg:address":"2660 Diamond St",
    "sg:city":"Rosamond",
    "sg:classifiers":[
        {
            "category":"Real Estate",
            "subcategory":"Real Estate Agent",
            "type":"Services"
        }
    ],
    "sg:phone":"+1 661 256 4987",
    "sg:postcode":"93560",
    "sg:province":"CA",
    "wof:name":"Bona Real Estate",
    "wof:placetype":"venue"
},
  "geometry": {"coordinates":[-118.163836,34.859512],"type":"Point"}
}