{
  "type": "Feature",
  "properties": {
    "iso:country":"US",
    "sg:address":"5558 N Millbrook Ave",
    "sg:city":"Fresno",
    "sg:classifiers":[
        {
            "category":"Shopping",
            "subcategory":"Clothing, Apparel, & Fashions",
            "type":"Retail Goods"
        }
    ],
    "sg:phone":"+1 559 435 5324",
    "sg:postcode":"93710",
    "sg:province":"CA",
    "sg:tags":[
        "t"
    ],
    "wof:name":"Pacifico Hibiscus Blossom",
    "wof:placetype":"venue"
},
  "geometry": {"coordinates":[-119.762811,36.817603],"type":"Point"}
}