{
  "type": "Feature",
  "properties": {
    "iso:country":"US",
    "sg:address":"29000 Hesperian Blvd",
    "sg:city":"Hayward",
    "sg:classifiers":[
        {
            "category":"Restaurant",
            "type":"Food & Drink"
        }
    ],
    "sg:phone":"+1 510 781 3600",
    "sg:postcode":"94545",
    "sg:province":"CA",
    "sg:tags":[
        "new",
        "american"
    ],
    "wof:name":"Pepsi Bottling Group",
    "wof:placetype":"venue"
},
  "geometry": {"coordinates":[-122.087997,37.6171],"type":"Point"}
}