{
  "type": "Feature",
  "properties": {
    "addr:full":"2438 E 6th St Apt B Lakewood CA 90814",
    "addr:housenumber":"2438",
    "addr:postcode":"90814",
    "addr:street":"E 6Th St Apt B",
    "iso:country":"US",
    "sg:address":"2438 E 6th St Apt B",
    "sg:city":"Lakewood",
    "sg:classifiers":[
        {
            "category":"Shopping",
            "subcategory":"Computers & Home Electronics",
            "type":"Retail Goods"
        }
    ],
    "sg:phone":"+1 562 746 9063",
    "sg:postcode":"90814",
    "sg:province":"CA",
    "sg:tags":[
        "installation",
        "theatre"
    ],
    "wof:name":"Superior Pixel",
    "wof:placetype":"venue"
},
  "geometry": {"coordinates":[-118.162446,33.773503],"type":"Point"}
}