{
  "type": "Feature",
  "properties": {
    "addr:full":"1537 W McKinley Ave Azusa CA 91702",
    "addr:housenumber":"1537",
    "addr:postcode":"91702",
    "addr:street":"W Mckinley Ave",
    "iso:country":"US",
    "sg:address":"1537 W McKinley Ave",
    "sg:city":"Azusa",
    "sg:classifiers":[
        {
            "category":"Manufacturing",
            "subcategory":"Printing",
            "type":"Manufacturing & Wholesale Goods"
        }
    ],
    "sg:phone":"+1 626 969 3100",
    "sg:postcode":"91702",
    "sg:province":"CA",
    "sg:tags":[
        "printer"
    ],
    "wof:name":"Graphic Foils",
    "wof:placetype":"venue"
},
  "geometry": {"coordinates":[-117.93353500000001,34.119777],"type":"Point"}
}