{
  "type": "Feature",
  "properties": {
    "addr:full":"433 Delphine Pl Fullerton CA 92833",
    "addr:housenumber":"433",
    "addr:postcode":"92833",
    "addr:street":"Delphine Pl",
    "iso:country":"US",
    "sg:address":"433 Delphine Pl",
    "sg:city":"Fullerton",
    "sg:classifiers":[
        {
            "category":"Professional",
            "type":"Services"
        }
    ],
    "sg:phone":"+1 714 992 5598",
    "sg:postcode":"92833",
    "sg:province":"CA",
    "wof:name":"Mohamed A Simjee",
    "wof:placetype":"venue"
},
  "geometry": {"coordinates":[-117.954679,33.87488],"type":"Point"}
}