{
  "type": "Feature",
  "properties": {
    "addr:full":"8013 Wheatland Ave Sun Valley CA 91352",
    "addr:housenumber":"8013",
    "addr:postcode":"91352",
    "addr:street":"Wheatland Ave",
    "iso:country":"US",
    "sg:address":"8013 Wheatland Ave",
    "sg:city":"Sun Valley",
    "sg:classifiers":[
        {
            "category":"Building & Trades",
            "subcategory":"Construction",
            "type":"Services"
        }
    ],
    "sg:phone":"+1 818 768 9878",
    "sg:postcode":"91352",
    "sg:province":"CA",
    "sg:tags":[
        "concrete",
        "cutting",
        "breaking",
        "sawing"
    ],
    "wof:name":"J & J Concrete Cutting",
    "wof:placetype":"venue"
},
  "geometry": {"coordinates":[-118.361863,34.217333],"type":"Point"}
}