{
  "type": "Feature",
  "properties": {
    "addr:full":"16411 E 14th Street San Leandro CA 94578",
    "addr:housenumber":"16411",
    "addr:postcode":"94578",
    "addr:street":"E 14Th Street",
    "iso:country":"US",
    "sg:address":"16411 E 14th Street",
    "sg:city":"San Leandro",
    "sg:classifiers":[
        {
            "category":"Food & Beverages",
            "subcategory":"Ethnic Foods",
            "type":"Retail Goods"
        }
    ],
    "sg:phone":"+1 510 276 1224",
    "sg:postcode":"94578",
    "sg:province":"CA",
    "wof:name":"Supermercado La Raza",
    "wof:placetype":"venue"
},
  "geometry": {"coordinates":[-122.11346399999999,37.694563],"type":"Point"}
}