{
  "type": "Feature",
  "properties": {
    "iso:country":"US",
    "sg:address":"201 Bucksaw Ln",
    "sg:city":"West Point",
    "sg:classifiers":[
        {
            "category":"Manufacturing",
            "subcategory":"Printing",
            "type":"Manufacturing & Wholesale Goods"
        }
    ],
    "sg:phone":"+1 209 293 7800",
    "sg:postcode":"95255",
    "sg:province":"CA",
    "sg:tags":[
        "newspaper"
    ],
    "wof:name":"West Point News",
    "wof:placetype":"venue"
},
  "geometry": {"coordinates":[-120.525998,38.40849],"type":"Point"}
}