{
  "type": "Feature",
  "properties": {
    "addr:full":"350 S Beverly Dr Beverly Hills CA 90212",
    "addr:housenumber":"350",
    "addr:postcode":"90212",
    "addr:street":"S Beverly Dr",
    "iso:country":"US",
    "sg:address":"350 S Beverly Dr",
    "sg:city":"Beverly Hills",
    "sg:classifiers":[
        {
            "category":"Restaurant",
            "type":"Food & Drink"
        }
    ],
    "sg:menulink":"http://www.allmenus.com/ca/los-angeles/8303-islands/menu/",
    "sg:phone":"+1 310 556 1624",
    "sg:postcode":"90212",
    "sg:province":"CA",
    "sg:tags":[
        "burger",
        "american"
    ],
    "wof:name":"Islands Fine Burgers & Drinks",
    "wof:placetype":"venue"
},
  "geometry": {"coordinates":[-118.39910500000001,34.060596],"type":"Point"}
}