{
  "type": "Feature",
  "properties": {
    "addr:full":"1524 McHenry Ave Ste 515 Modesto CA 95350",
    "addr:housenumber":"1524",
    "addr:postcode":"ca 95350",
    "addr:street":"Mchenry Ave Ste 515",
    "iso:country":"US",
    "sg:address":"1524 McHenry Ave Ste 515",
    "sg:city":"Modesto",
    "sg:classifiers":[
        {
            "category":"Health Services",
            "subcategory":"Optometrist",
            "type":"Services"
        }
    ],
    "sg:phone":"+1 209 549 2002",
    "sg:postcode":"95350",
    "sg:province":"CA",
    "sg:tags":[
        "eye",
        "laser",
        "surgery/lasik"
    ],
    "sg:website":"www.mchenrylasik.com",
    "wof:name":"Northern California Laser Center",
    "wof:placetype":"venue"
},
  "geometry": {"coordinates":[-120.992735,37.666306],"type":"Point"}
}