{
  "type": "Feature",
  "properties": {
    "iso:country":"US",
    "sg:address":"520 Parkbrook St",
    "sg:city":"Spring Valley",
    "sg:classifiers":[
        {
            "category":"Building & Trades",
            "subcategory":"Construction",
            "type":"Services"
        }
    ],
    "sg:phone":"+1 619 470 0345",
    "sg:postcode":"91977",
    "sg:province":"CA",
    "sg:tags":[
        "contractor"
    ],
    "wof:name":"Haugen Roof Construction",
    "wof:placetype":"venue"
},
  "geometry": {"coordinates":[-117.01270100000001,32.705526],"type":"Point"}
}