{
  "type": "Feature",
  "properties": {
    "iso:country":"US",
    "sg:address":"509 W Tehachapi Blvd",
    "sg:city":"Tehachapi",
    "sg:classifiers":[
        {
            "category":"Retail",
            "subcategory":"Auto Repair",
            "type":"Services"
        }
    ],
    "sg:phone":"+1 800 800 2727",
    "sg:postcode":"93561",
    "sg:province":"CA",
    "sg:tags":[
        "glass",
        "replacement"
    ],
    "wof:name":"Safelite Autoglass",
    "wof:placetype":"venue"
},
  "geometry": {"coordinates":[-118.456659,35.132644],"type":"Point"}
}