{
  "type": "Feature",
  "properties": {
    "iso:country":"US",
    "sg:address":"5540 Ekwill St",
    "sg:city":"Santa Barbara",
    "sg:classifiers":[
        {
            "category":"Manufacturing",
            "subcategory":"Tools & Machinery",
            "type":"Manufacturing & Wholesale Goods"
        }
    ],
    "sg:phone":"+1 805 683 6761",
    "sg:postcode":"93111",
    "sg:province":"CA",
    "sg:tags":[
        "surgical",
        "component",
        "implant",
        "mfg"
    ],
    "wof:name":"Inamed Corporation",
    "wof:placetype":"venue"
},
  "geometry": {"coordinates":[-119.82064699999999,34.430124],"type":"Point"}
}