{
  "type": "Feature",
  "properties": {
    "addr:full":"2730 S Fairview St Santa Ana CA 92704",
    "addr:housenumber":"2730",
    "addr:postcode":"92704",
    "addr:street":"S Fairview St",
    "iso:country":"US",
    "sg:address":"2730 S Fairview St",
    "sg:city":"Santa Ana",
    "sg:classifiers":[
        {
            "category":"Retail",
            "subcategory":"Storage",
            "type":"Services"
        }
    ],
    "sg:phone":"+1 714 557 3700",
    "sg:postcode":"92704",
    "sg:province":"CA",
    "sg:tags":[
        "self"
    ],
    "sg:website":"www.storagewest.com/santa_ana.htm",
    "wof:name":"Storage West Self Storage Santa Ana",
    "wof:placetype":"venue"
},
  "geometry": {"coordinates":[-117.90799699999999,33.711102],"type":"Point"}
}