{
  "type": "Feature",
  "properties": {
    "iso:country":"US",
    "sg:address":"701 Kings Row",
    "sg:city":"San Jose",
    "sg:classifiers":[
        {
            "category":"Communications",
            "subcategory":"Film & Video Production",
            "type":"Services"
        }
    ],
    "sg:phone":"+1 408 294 1817",
    "sg:postcode":"95112",
    "sg:province":"CA",
    "sg:tags":[
        "motion"
    ],
    "wof:name":"Elegant Fox Production",
    "wof:placetype":"venue"
},
  "geometry": {"coordinates":[-121.89943,37.371769],"type":"Point"}
}