{
  "type": "Feature",
  "properties": {
    "addr:full":"429 E Tokay St Lodi CA 95240",
    "addr:housenumber":"429",
    "addr:postcode":"95240",
    "addr:street":"E Tokay St",
    "iso:country":"US",
    "sg:address":"429 E Tokay St",
    "sg:city":"Lodi",
    "sg:classifiers":[
        {
            "category":"Building & Trades",
            "subcategory":"Construction",
            "type":"Services"
        }
    ],
    "sg:phone":"+1 209 333 2606",
    "sg:postcode":"95240",
    "sg:province":"CA",
    "sg:tags":[
        "contractor"
    ],
    "wof:name":"D & M Construction",
    "wof:placetype":"venue"
},
  "geometry": {"coordinates":[-121.263336,38.126904],"type":"Point"}
}