{
  "type": "Feature",
  "properties": {
    "addr:full":"1425 Standiford Ave Modesto CA 95350",
    "addr:housenumber":"1425",
    "addr:postcode":"ca 95350",
    "addr:street":"Standiford Ave",
    "iso:country":"US",
    "sg:address":"1425 Standiford Ave",
    "sg:city":"Modesto",
    "sg:classifiers":[
        {
            "category":"Health Services",
            "subcategory":"Clinic",
            "type":"Services"
        }
    ],
    "sg:phone":"+1 209 577 2408",
    "sg:postcode":"95350",
    "sg:province":"CA",
    "sg:tags":[
        "ultrasound",
        "imaging"
    ],
    "wof:name":"Womb With A View",
    "wof:placetype":"venue"
},
  "geometry": {"coordinates":[-121.017275,37.689491],"type":"Point"}
}