{
  "type": "Feature",
  "properties": {
    "addr:full":"10600 Tembladera St Castroville CA 95012",
    "addr:housenumber":"10600",
    "addr:postcode":"95012",
    "addr:street":"Tembladera St",
    "iso:country":"US",
    "sg:address":"10600 Tembladera St",
    "sg:city":"Castroville",
    "sg:classifiers":[
        {
            "category":"Marine",
            "type":"Transportation"
        },
        {
            "category":"Retail",
            "subcategory":"Auto Repair",
            "type":"Services"
        }
    ],
    "sg:phone":"+1 831 633 3387",
    "sg:postcode":"95012",
    "sg:province":"CA",
    "sg:tags":[
        "wrecker",
        "towing",
        "salvaging"
    ],
    "wof:name":"Vessel Towing and Salvage",
    "wof:placetype":"venue"
},
  "geometry": {"coordinates":[-121.758858,36.765522],"type":"Point"}
}