{
  "type": "Feature",
  "properties": {
    "iso:country":"US",
    "sg:address":"24301 Devries Rd",
    "sg:city":"Lodi",
    "sg:classifiers":[
        {
            "category":"Farming",
            "subcategory":"Vineyard",
            "type":"Manufacturing & Wholesale Goods"
        }
    ],
    "sg:phone":"+1 209 368 7341",
    "sg:postcode":"95242",
    "sg:province":"CA",
    "sg:tags":[
        "grape"
    ],
    "wof:name":"Rudy Maggio Farms",
    "wof:placetype":"venue"
},
  "geometry": {"coordinates":[-121.35408200000001,38.192181],"type":"Point"}
}