{
  "type": "Feature",
  "properties": {
    "addr:full":"401 N Culver Ave Compton CA 90220",
    "addr:housenumber":"401",
    "addr:postcode":"90220",
    "addr:street":"N Culver Ave",
    "iso:country":"US",
    "sg:address":"401 N Culver Ave",
    "sg:city":"Compton",
    "sg:classifiers":[
        {
            "category":"Wholesale",
            "subcategory":"Chemicals & Plastics",
            "type":"Manufacturing & Wholesale Goods"
        }
    ],
    "sg:phone":"+1 310 637 7625",
    "sg:postcode":"90220",
    "sg:province":"CA",
    "sg:tags":[
        "distributor"
    ],
    "wof:name":"Amway Corporation",
    "wof:placetype":"venue"
},
  "geometry": {"coordinates":[-118.225691,33.899274],"type":"Point"}
}