{
  "type": "Feature",
  "properties": {
    "iso:country":"US",
    "sg:address":"8225 N Fresno St",
    "sg:city":"Fresno",
    "sg:classifiers":[
        {
            "category":"Manufacturing",
            "subcategory":"Textiles",
            "type":"Manufacturing & Wholesale Goods"
        }
    ],
    "sg:phone":"+1 559 447 1800",
    "sg:postcode":"93710",
    "sg:province":"CA",
    "sg:tags":[
        "cotton"
    ],
    "sg:website":"www.dunca-cotton.com",
    "wof:name":"Dunavant Of California",
    "wof:placetype":"venue"
},
  "geometry": {"coordinates":[-119.78507,36.857402],"type":"Point"}
}