{
  "type": "Feature",
  "properties": {
    "iso:country":"US",
    "sg:address":"2221 Orange Grove Pl",
    "sg:city":"Escondido",
    "sg:classifiers":[
        {
            "category":"Education",
            "subcategory":"Special Training",
            "type":"Public Place"
        }
    ],
    "sg:phone":"+1 858 268 2236",
    "sg:postcode":"92027",
    "sg:province":"CA",
    "sg:tags":[
        "management"
    ],
    "wof:name":"CEO Training Inc",
    "wof:placetype":"venue"
},
  "geometry": {"coordinates":[-117.011939,33.123325],"type":"Point"}
}