{
  "type": "Feature",
  "properties": {
    "iso:country":"US",
    "sg:address":"728 Ventura Pl",
    "sg:city":"San Diego",
    "sg:classifiers":[
        {
            "category":"Restaurant",
            "type":"Food & Drink"
        }
    ],
    "sg:menulink":"http://www.allmenus.com/ca/san-diego/35152-fat-boyz-pizza/menu/",
    "sg:phone":"+1 858 488 2699",
    "sg:postcode":"92109",
    "sg:province":"CA",
    "sg:tags":[
        "american",
        "pizza"
    ],
    "wof:name":"Fat Boyz Pizza",
    "wof:placetype":"venue"
},
  "geometry": {"coordinates":[-117.25221500000001,32.772037],"type":"Point"}
}