{
  "type": "Feature",
  "properties": {
    "iso:country":"US",
    "sg:address":"11629 Lower Azusa Rd",
    "sg:city":"El Monte",
    "sg:classifiers":[
        {
            "category":"Food & Beverages",
            "subcategory":"Bakery",
            "type":"Retail Goods"
        }
    ],
    "sg:phone":"+1 626 448 6238",
    "sg:postcode":"91732",
    "sg:province":"CA",
    "sg:tags":[
        "baker"
    ],
    "wof:name":"Happy Bakery",
    "wof:placetype":"venue"
},
  "geometry": {"coordinates":[-118.013465,34.090542],"type":"Point"}
}