{
  "type": "Feature",
  "properties": {
    "iso:country":"US",
    "sg:address":"40370 Ross Rd",
    "sg:city":"Fallbrook",
    "sg:classifiers":[
        {
            "category":"Building & Trades",
            "subcategory":"Electrical",
            "type":"Services"
        }
    ],
    "sg:phone":"+1 760 723 3193",
    "sg:postcode":"92028",
    "sg:province":"CA",
    "sg:tags":[
        "electric",
        "contractor"
    ],
    "wof:name":"G P Electrical",
    "wof:placetype":"venue"
},
  "geometry": {"coordinates":[-117.289205,33.443515],"type":"Point"}
}