{
  "type": "Feature",
  "properties": {
    "iso:country":"US",
    "sg:address":"14900 Central Ave",
    "sg:city":"Baldwin Park",
    "sg:classifiers":[
        {
            "category":"Organizations",
            "subcategory":"Religious Organization",
            "type":"Services"
        }
    ],
    "sg:phone":"+1 626 480 8454",
    "sg:postcode":"91706",
    "sg:province":"CA",
    "sg:tags":[
        "church"
    ],
    "wof:name":"Communida Cristiana Nueva",
    "wof:placetype":"venue"
},
  "geometry": {"coordinates":[-117.950834,34.081581],"type":"Point"}
}