{
  "type": "Feature",
  "properties": {
    "iso:country":"US",
    "sg:address":"2323 California Ave",
    "sg:city":"Santa Monica",
    "sg:classifiers":[
        {
            "category":"Professional",
            "type":"Services"
        }
    ],
    "sg:phone":"+1 310 453 8635",
    "sg:postcode":"90403",
    "sg:province":"CA",
    "wof:name":"80 Windward LLC A Cal Ltd LI",
    "wof:placetype":"venue"
},
  "geometry": {"coordinates":[-118.481679,34.035322],"type":"Point"}
}