{
  "type": "Feature",
  "properties": {
    "addr:full":"10350 Baseline Rd Alta Loma CA 91701",
    "addr:housenumber":"10350",
    "addr:postcode":"91701",
    "addr:street":"Baseline Rd",
    "iso:country":"US",
    "sg:address":"10350 Baseline Rd",
    "sg:city":"Alta Loma",
    "sg:classifiers":[
        {
            "category":"Building & Trades",
            "subcategory":"Cleaning & Sanitation",
            "type":"Services"
        }
    ],
    "sg:phone":"+1 909 481 4919",
    "sg:postcode":"91701",
    "sg:province":"CA",
    "sg:tags":[
        "window"
    ],
    "wof:name":"Bobby's Window Cleaning",
    "wof:placetype":"venue"
},
  "geometry": {"coordinates":[-117.57875799999999,34.121606],"type":"Point"}
}