{
  "type": "Feature",
  "properties": {
    "addr:full":"3242 W 153rd Street Gardena CA 90249",
    "addr:housenumber":"3242",
    "addr:postcode":"90249",
    "addr:street":"W 153Rd Street",
    "iso:country":"US",
    "sg:address":"3242 W 153rd Street",
    "sg:city":"Gardena",
    "sg:classifiers":[
        {
            "category":"Home & Garden",
            "subcategory":"Household Appliances",
            "type":"Retail Goods"
        },
        {
            "category":"Building & Trades",
            "subcategory":"Plumbing",
            "type":"Services"
        },
        {
            "category":"Building & Trades",
            "subcategory":"Construction",
            "type":"Services"
        }
    ],
    "sg:phone":"+1 310 355 0500",
    "sg:postcode":"90249",
    "sg:province":"CA",
    "sg:tags":[
        "major",
        "system",
        "appliances-small",
        "specialty",
        "heating",
        "contractor",
        "air conditioning"
    ],
    "wof:name":"Just N Time Heating & Air Conditioning",
    "wof:placetype":"venue"
},
  "geometry": {"coordinates":[-118.33031800000001,33.892349],"type":"Point"}
}