{
  "type": "Feature",
  "properties": {
    "addr:full":"28901 Sierra Peak Ln Trabuco Canyon CA 92679",
    "addr:housenumber":"28901",
    "addr:postcode":"92679",
    "addr:street":"Sierra Peak Ln",
    "iso:country":"US",
    "sg:address":"28901 Sierra Peak Ln",
    "sg:city":"Trabuco Canyon",
    "sg:classifiers":[
        {
            "category":"Manufacturing",
            "subcategory":"Tools & Machinery",
            "type":"Manufacturing & Wholesale Goods"
        }
    ],
    "sg:phone":"+1 949 735 1155",
    "sg:postcode":"92679",
    "sg:province":"CA",
    "sg:tags":[
        "metalworking",
        "mfg"
    ],
    "wof:name":"Swift Kik Fabrications",
    "wof:placetype":"venue"
},
  "geometry": {"coordinates":[-117.62693400000001,33.68157],"type":"Point"}
}