{
  "type": "Feature",
  "properties": {
    "iso:country":"US",
    "sg:address":"28901 Sierra Peak Ln",
    "sg:city":"Trabuco Canyon",
    "sg:classifiers":[
        {
            "category":"Manufacturing",
            "subcategory":"Tools & Machinery",
            "type":"Manufacturing & Wholesale Goods"
        }
    ],
    "sg:phone":"+1 949 735 1155",
    "sg:postcode":"92679",
    "sg:province":"CA",
    "sg:tags":[
        "metalworking",
        "mfg"
    ],
    "wof:name":"Swift Kik Fabrications",
    "wof:placetype":"venue"
},
  "geometry": {"coordinates":[-117.626934,33.68157],"type":"Point"}
}