{
  "type": "Feature",
  "properties": {
    "addr:full":"10745 Andy St Cerritos CA 90703",
    "addr:housenumber":"10745",
    "addr:postcode":"ca 90703",
    "addr:street":"Andy St",
    "iso:country":"US",
    "sg:address":"10745 Andy St",
    "sg:city":"Cerritos",
    "sg:classifiers":[
        {
            "category":"Wholesale",
            "subcategory":"Medical Equipment & Supplies",
            "type":"Manufacturing & Wholesale Goods"
        }
    ],
    "sg:phone":"+1 562 925 5267",
    "sg:postcode":"90703",
    "sg:province":"CA",
    "wof:name":"Dan Dallas Medical Supply",
    "wof:placetype":"venue"
},
  "geometry": {"coordinates":[-118.106246,33.862355],"type":"Point"}
}