{
  "type": "Feature",
  "properties": {
    "addr:full":"250 Walnut St Newport Beach CA 92663",
    "addr:housenumber":"250",
    "addr:postcode":"92663",
    "addr:street":"Walnut St",
    "iso:country":"US",
    "sg:address":"250 Walnut St",
    "sg:city":"Newport Beach",
    "sg:classifiers":[
        {
            "category":"Professional",
            "type":"Services"
        }
    ],
    "sg:phone":"+1 949 515 8815",
    "sg:postcode":"92663",
    "sg:province":"CA",
    "wof:name":"Beach Citys Guide",
    "wof:placetype":"venue"
},
  "geometry": {"coordinates":[-117.948638,33.629589],"type":"Point"}
}