{
  "type": "Feature",
  "properties": {
    "iso:country":"US",
    "sg:address":"2018 17th St",
    "sg:city":"Bakersfield",
    "sg:classifiers":[
        {
            "category":"Health Services",
            "subcategory":"Chiropractor",
            "type":"Services"
        }
    ],
    "sg:phone":"+1 661 321 0333",
    "sg:postcode":"93301",
    "sg:province":"CA",
    "sg:tags":[
        "chiropractic"
    ],
    "wof:name":"Signee Hoffman Dc",
    "wof:placetype":"venue"
},
  "geometry": {"coordinates":[-119.024877,35.37434],"type":"Point"}
}