{
  "type": "Feature",
  "properties": {
    "addr:full":"3318 Santa Fe St Riverbank CA 95367",
    "addr:housenumber":"3318",
    "addr:postcode":"95367",
    "addr:street":"Santa Fe St",
    "iso:country":"US",
    "sg:address":"3318 Santa Fe St",
    "sg:city":"Riverbank",
    "sg:classifiers":[
        {
            "category":"Shopping",
            "subcategory":"Clothing, Apparel, & Fashions",
            "type":"Retail Goods"
        }
    ],
    "sg:phone":"+1 209 869 0511",
    "sg:postcode":"95367",
    "sg:province":"CA",
    "sg:tags":[
        "western"
    ],
    "wof:name":"Rodeo's Men's Western",
    "wof:placetype":"venue"
},
  "geometry": {"coordinates":[-120.93429500000001,37.735942],"type":"Point"}
}