{
  "type": "Feature",
  "properties": {
    "addr:full":"5070 Redwood Dr Rohnert Park CA 94928",
    "addr:housenumber":"5070",
    "addr:postcode":"94928",
    "addr:street":"Redwood Dr",
    "iso:country":"US",
    "sg:address":"5070 Redwood Dr",
    "sg:city":"Rohnert Park",
    "sg:classifiers":[
        {
            "category":"Building & Trades",
            "subcategory":"Construction",
            "type":"Services"
        }
    ],
    "sg:phone":"+1 707 585 7400",
    "sg:postcode":"94928",
    "sg:province":"CA",
    "sg:tags":[
        "contractor"
    ],
    "wof:name":"Lucas & Lucas General Contr",
    "wof:placetype":"venue"
},
  "geometry": {"coordinates":[-122.713224,38.365621],"type":"Point"}
}