{
  "type": "Feature",
  "properties": {
    "addr:full":"1447 Ocean Ave Santa Monica CA 90401",
    "addr:housenumber":"1447",
    "addr:postcode":"90401",
    "addr:street":"Ocean Ave",
    "iso:country":"US",
    "sg:address":"1447 Ocean Ave",
    "sg:city":"Santa Monica",
    "sg:classifiers":[
        {
            "category":"Travel",
            "subcategory":"Hotels & Motels",
            "type":"Entertainment"
        }
    ],
    "sg:phone":"+1 310 458 4888",
    "sg:postcode":"90401",
    "sg:province":"CA",
    "sg:tags":[
        "operation"
    ],
    "sg:website":"www.bestwestern.com",
    "wof:name":"Best Western Ocean View Htl",
    "wof:placetype":"venue"
},
  "geometry": {"coordinates":[-118.497038,34.013418],"type":"Point"}
}