{
  "type": "Feature",
  "properties": {
    "addr:full":"186 Weathermark Ct Vallejo CA 94591",
    "addr:housenumber":"186",
    "addr:postcode":"94591",
    "addr:street":"Weathermark Ct",
    "iso:country":"US",
    "sg:address":"186 Weathermark Ct",
    "sg:city":"Vallejo",
    "sg:classifiers":[
        {
            "category":"Wholesale",
            "subcategory":"Toys & Hobbies",
            "type":"Manufacturing & Wholesale Goods"
        }
    ],
    "sg:phone":"+1 707 557 1058",
    "sg:postcode":"94591",
    "sg:province":"CA",
    "wof:name":"Famber",
    "wof:placetype":"venue"
},
  "geometry": {"coordinates":[-122.20031400000001,38.065444],"type":"Point"}
}