{
  "type": "Feature",
  "properties": {
    "addr:full":"2130 Railroad Ave Pittsburg CA 94565",
    "addr:housenumber":"2130",
    "addr:postcode":"94565",
    "addr:street":"Railroad Ave",
    "iso:country":"US",
    "sg:address":"2130 Railroad Ave",
    "sg:city":"Pittsburg",
    "sg:phone":"+1 925 439 9500",
    "sg:postcode":"94565",
    "sg:province":"CA",
    "sg:website":"http://www.togos.com/",
    "wof:name":"Togos Eatery",
    "wof:placetype":"venue"
},
  "geometry": {"coordinates":[-121.89014899999999,38.015224],"type":"Point"}
}