{
  "type": "Feature",
  "properties": {
    "addr:full":"11135 Weddington Ave Ste 113 North Hollywood CA 91601",
    "addr:housenumber":"11135",
    "addr:postcode":"91601",
    "addr:street":"Weddington Ave Ste 113",
    "iso:country":"US",
    "sg:address":"11135 Weddington Ave Ste 113",
    "sg:city":"North Hollywood",
    "sg:classifiers":[
        {
            "category":"Sports & Exercise",
            "subcategory":"Playing Field",
            "type":"Entertainment"
        }
    ],
    "sg:phone":"+1 818 985 4474",
    "sg:postcode":"91601",
    "sg:province":"CA",
    "sg:tags":[
        "instruction",
        "fitness"
    ],
    "sg:website":"www.xpolesitions.com",
    "wof:name":"X-Polesitions",
    "wof:placetype":"venue"
},
  "geometry": {"coordinates":[-118.37369,34.166999],"type":"Point"}
}