{
  "type": "Feature",
  "properties": {
    "iso:country":"US",
    "sg:address":"73585 el Paseo",
    "sg:city":"Palm Desert",
    "sg:classifiers":[
        {
            "category":"Shopping",
            "subcategory":"Clothing, Apparel, & Fashions",
            "type":"Retail Goods"
        }
    ],
    "sg:phone":"+1 760 346 8501",
    "sg:postcode":"92260",
    "sg:province":"CA",
    "sg:tags":[
        "furnishing"
    ],
    "wof:name":"Davinci",
    "wof:placetype":"venue"
},
  "geometry": {"coordinates":[-116.381358,33.7197],"type":"Point"}
}