{
  "type": "Feature",
  "properties": {
    "addr:full":"3331 Mt Diablo Blvd Lafayette CA 94549",
    "addr:housenumber":"3331",
    "addr:postcode":"94549",
    "addr:street":"Mt Diablo Blvd",
    "iso:country":"US",
    "sg:address":"3331 Mt Diablo Blvd",
    "sg:city":"Lafayette",
    "sg:classifiers":[
        {
            "category":"Retail",
            "subcategory":"Auto Repair",
            "type":"Services"
        }
    ],
    "sg:phone":"+1 925 283 2160",
    "sg:postcode":"94549",
    "sg:province":"CA",
    "sg:tags":[
        "body",
        "repairing",
        "painting",
        "automobile"
    ],
    "sg:website":"http://www.professionalautomotive.net",
    "wof:name":"Professional Automotive",
    "wof:placetype":"venue"
},
  "geometry": {"coordinates":[-122.10444699999999,37.895542],"type":"Point"}
}