{
  "type": "Feature",
  "properties": {
    "iso:country":"US",
    "sg:address":"210 San Benito St",
    "sg:city":"Hollister",
    "sg:classifiers":[
        {
            "category":"Real Estate",
            "subcategory":"Real Estate Agent",
            "type":"Services"
        }
    ],
    "sg:phone":"+1 831 636 8815",
    "sg:postcode":"95023",
    "sg:province":"CA",
    "wof:name":"Certified Appraisal Service",
    "wof:placetype":"venue"
},
  "geometry": {"coordinates":[-121.40212,36.85443],"type":"Point"}
}