{
  "type": "Feature",
  "properties": {
    "iso:country":"US",
    "sg:address":"21755 Ventura Blvd",
    "sg:city":"Woodland Hills",
    "sg:classifiers":[
        {
            "category":"Shopping",
            "type":"Retail Goods"
        }
    ],
    "sg:phone":"+1 818 222 0431",
    "sg:postcode":"91364",
    "sg:province":"CA",
    "sg:tags":[
        "cosmetic",
        "perfume"
    ],
    "wof:name":"Urban Cosmetics",
    "wof:placetype":"venue"
},
  "geometry": {"coordinates":[-118.601455,34.168408],"type":"Point"}
}