{
  "type": "Feature",
  "properties": {
    "iso:country":"US",
    "sg:address":"5524 Scotts Valley Dr",
    "sg:city":"Scotts Valley",
    "sg:classifiers":[
        {
            "category":"Professional",
            "subcategory":"Lawyer & Legal Services",
            "type":"Services"
        }
    ],
    "sg:phone":"+1 831 438 6614",
    "sg:postcode":"95066",
    "sg:province":"CA",
    "sg:tags":[
        "attorney"
    ],
    "wof:name":"Raymond M Haight",
    "wof:placetype":"venue"
},
  "geometry": {"coordinates":[-122.008611,37.060496],"type":"Point"}
}