{
  "type": "Feature",
  "properties": {
    "addr:full":"209 Palm St Newport Beach CA 92661",
    "addr:housenumber":"209",
    "addr:postcode":"92661",
    "addr:street":"Palm St",
    "iso:country":"US",
    "sg:address":"209 Palm St",
    "sg:city":"Newport Beach",
    "sg:classifiers":[
        {
            "category":"Bars & Pubs",
            "subcategory":"Nightclub",
            "type":"Food & Drink"
        }
    ],
    "sg:phone":"+1 949 675 5774",
    "sg:postcode":"92661",
    "sg:province":"CA",
    "sg:tags":[
        "nightlife"
    ],
    "wof:name":"Class of 47",
    "wof:placetype":"venue"
},
  "geometry": {"coordinates":[-117.90100099999999,33.6026],"type":"Point"}
}