{
  "type": "Feature",
  "properties": {
    "addr:full":"1409 Kuehner Dr Simi Valley CA 93063",
    "addr:housenumber":"1409",
    "addr:postcode":"93063",
    "addr:street":"Kuehner Dr",
    "iso:country":"US",
    "sg:address":"1409 Kuehner Dr",
    "sg:city":"Simi Valley",
    "sg:classifiers":[
        {
            "category":"Building & Trades",
            "subcategory":"Plumbing",
            "type":"Services"
        }
    ],
    "sg:phone":"+1 805 526 6717",
    "sg:postcode":"93063",
    "sg:province":"CA",
    "sg:tags":[
        "plumbing",
        "contractor"
    ],
    "wof:name":"Jeffrey Frankel Plumbing Inc",
    "wof:placetype":"venue"
},
  "geometry": {"coordinates":[-118.66153300000001,34.261882],"type":"Point"}
}