{
  "type": "Feature",
  "properties": {
    "addr:full":"860 Redwood Dr Garberville CA 95542",
    "addr:housenumber":"860",
    "addr:postcode":"95542",
    "addr:street":"Redwood Dr",
    "iso:country":"US",
    "sg:address":"860 Redwood Dr",
    "sg:city":"Garberville",
    "sg:classifiers":[
        {
            "category":"Autos & Motor Vehicles",
            "subcategory":"Fuel & Gas Station",
            "type":"Retail Goods"
        }
    ],
    "sg:phone":"+1 707 923 9144",
    "sg:postcode":"95542",
    "sg:province":"CA",
    "sg:tags":[
        "oil"
    ],
    "wof:name":"Garberville Shell",
    "wof:placetype":"venue"
},
  "geometry": {"coordinates":[-123.795142,40.0991],"type":"Point"}
}