{
  "type": "Feature",
  "properties": {
    "addr:full":"6069 Madera Dr Woodland Hills CA 91367",
    "addr:housenumber":"6069",
    "addr:postcode":"91367",
    "addr:street":"Madera Dr",
    "iso:country":"US",
    "sg:address":"6069 Madera Dr",
    "sg:city":"Woodland Hills",
    "sg:classifiers":[
        {
            "category":"Professional",
            "subcategory":"Lawyer & Legal Services",
            "type":"Services"
        }
    ],
    "sg:phone":"+1 818 347 0101",
    "sg:postcode":"91367",
    "sg:province":"CA",
    "sg:website":"www.professionallegalassistors.com",
    "wof:name":"Professional Legal Assistors",
    "wof:placetype":"venue"
},
  "geometry": {"coordinates":[-118.613507,34.18048],"type":"Point"}
}