{
  "type": "Feature",
  "properties": {
    "addr:full":"4900 N Figueroa St Los Angeles CA 90042",
    "addr:housenumber":"4900",
    "addr:postcode":"90042",
    "addr:street":"N Figueroa St",
    "iso:country":"US",
    "sg:address":"4900 N Figueroa St",
    "sg:city":"Los Angeles",
    "sg:classifiers":[
        {
            "category":"Organizations",
            "subcategory":"Religious Organization",
            "type":"Services"
        }
    ],
    "sg:phone":"+1 323 256 2411",
    "sg:postcode":"90042",
    "sg:province":"CA",
    "sg:tags":[
        "church"
    ],
    "wof:name":"Pillar Of Fire",
    "wof:placetype":"venue"
},
  "geometry": {"coordinates":[-118.202907,34.102408],"type":"Point"}
}