{
  "type": "Feature",
  "properties": {
    "iso:country":"US",
    "sg:address":"8737 Firestone Blvd",
    "sg:city":"Downey",
    "sg:classifiers":[
        {
            "category":"Insurance",
            "subcategory":"Insurance Agent",
            "type":"Services"
        }
    ],
    "sg:phone":"+1 562 923 8113",
    "sg:postcode":"90241",
    "sg:province":"CA",
    "wof:name":"Robert Roller Insurance",
    "wof:placetype":"venue"
},
  "geometry": {"coordinates":[-118.12416399999999,33.93575],"type":"Point"}
}