{
  "type": "Feature",
  "properties": {
    "addr:full":"2102 S Flower St Santa Ana CA 92707",
    "addr:housenumber":"2102",
    "addr:postcode":"92707",
    "addr:street":"S Flower St",
    "iso:country":"US",
    "sg:address":"2102 S Flower St",
    "sg:city":"Santa Ana",
    "sg:classifiers":[
        {
            "category":"Government",
            "subcategory":"City Hall",
            "type":"Public Place"
        }
    ],
    "sg:phone":"+1 714 571 4242",
    "sg:postcode":"92707",
    "sg:province":"CA",
    "wof:name":"Santa Ana City of",
    "wof:placetype":"venue"
},
  "geometry": {"coordinates":[-117.876999,33.7192],"type":"Point"}
}