{
  "type": "Feature",
  "properties": {
    "addr:full":"727 Brea Canyon Rd Walnut CA 91789",
    "addr:housenumber":"727",
    "addr:postcode":"91789",
    "addr:street":"Brea Canyon Rd",
    "iso:country":"US",
    "sg:address":"727 Brea Canyon Rd",
    "sg:city":"Walnut",
    "sg:classifiers":[
        {
            "category":"Utilities",
            "subcategory":"Telephone",
            "type":"Services"
        }
    ],
    "sg:phone":"+1 909 820 5168",
    "sg:postcode":"91789",
    "sg:province":"CA",
    "sg:tags":[
        "telecommunication"
    ],
    "wof:name":"ITT Worldcom Inc",
    "wof:placetype":"venue"
},
  "geometry": {"coordinates":[-117.84658399999999,34.004066],"type":"Point"}
}