{
  "type": "Feature",
  "properties": {
    "addr:full":"1221 Dodson Way Riverside CA 92507",
    "addr:housenumber":"1221",
    "addr:postcode":"92507",
    "addr:street":"Dodson Way",
    "iso:country":"US",
    "sg:address":"1221 Dodson Way",
    "sg:city":"Riverside",
    "sg:classifiers":[
        {
            "category":"Professional",
            "subcategory":"Computer Services",
            "type":"Services"
        }
    ],
    "sg:phone":"+1 951 684 6029",
    "sg:postcode":"92507",
    "sg:province":"CA",
    "sg:tags":[
        "isp",
        "provider",
        "internet"
    ],
    "wof:name":"Source Broadband Services",
    "wof:placetype":"venue"
},
  "geometry": {"coordinates":[-117.345125,34.000885],"type":"Point"}
}