{
  "type": "Feature",
  "properties": {
    "iso:country":"US",
    "sg:address":"235 W 27th St",
    "sg:city":"Los Angeles",
    "sg:classifiers":[
        {
            "category":"Wholesale",
            "subcategory":"Apparel",
            "type":"Manufacturing & Wholesale Goods"
        }
    ],
    "sg:phone":"+1 213 749 4106",
    "sg:postcode":"90007",
    "sg:province":"CA",
    "sg:tags":[
        "sportswear"
    ],
    "wof:name":"Na Young Fashion",
    "wof:placetype":"venue"
},
  "geometry": {"coordinates":[-118.272488,34.025271],"type":"Point"}
}