{
  "type": "Feature",
  "properties": {
    "addr:full":"1220 N St Ste 400 Sacramento CA 95814",
    "addr:housenumber":"1220",
    "addr:postcode":"95814",
    "addr:street":"N St Ste 400",
    "iso:country":"US",
    "sg:address":"1220 N St Ste 400",
    "sg:city":"Sacramento",
    "sg:classifiers":[
        {
            "category":"Government",
            "subcategory":"Office",
            "type":"Public Place"
        }
    ],
    "sg:phone":"+1 916 654 1447",
    "sg:postcode":"95814",
    "sg:province":"CA",
    "sg:tags":[
        "government-state"
    ],
    "wof:name":"State Veterinarian",
    "wof:placetype":"venue"
},
  "geometry": {"coordinates":[-121.492407,38.575091],"type":"Point"}
}