{
  "type": "Feature",
  "properties": {
    "addr:full":"1331 Kendall Dr Ste 4 San Bernardino CA 92407",
    "addr:housenumber":"1331",
    "addr:postcode":"92407",
    "addr:street":"Kendall Dr Ste 4",
    "iso:country":"US",
    "sg:address":"1331 Kendall Dr Ste 4",
    "sg:city":"San Bernardino",
    "sg:classifiers":[
        {
            "category":"Retail",
            "subcategory":"Laundry & Dry Cleaning",
            "type":"Services"
        }
    ],
    "sg:phone":"+1 909 880 8925",
    "sg:postcode":"92407",
    "sg:province":"CA",
    "wof:name":"El Dorado Saturn Cleaners",
    "wof:placetype":"venue"
},
  "geometry": {"coordinates":[-117.314003,34.168098],"type":"Point"}
}