{
  "type": "Feature",
  "properties": {
    "iso:country":"US",
    "sg:address":"20380 Stevens Creek Blvd",
    "sg:city":"Cupertino",
    "sg:classifiers":[
        {
            "category":"Real Estate",
            "subcategory":"Real Estate Operator",
            "type":"Services"
        }
    ],
    "sg:phone":"+1 408 255 4010",
    "sg:postcode":"95014",
    "sg:province":"CA",
    "sg:tags":[
        "apartment"
    ],
    "wof:name":"Verona",
    "wof:placetype":"venue"
},
  "geometry": {"coordinates":[-122.03058,37.320631],"type":"Point"}
}