{
  "type": "Feature",
  "properties": {
    "addr:full":"1901 Junipero Serra Blvd Daly City CA 94014",
    "addr:housenumber":"1901",
    "addr:postcode":"94014",
    "addr:street":"Junipero Serra Blvd",
    "iso:country":"US",
    "sg:address":"1901 Junipero Serra Blvd",
    "sg:city":"Daly City",
    "sg:classifiers":[
        {
            "category":"Ice Cream",
            "type":"Food & Drink"
        }
    ],
    "sg:phone":"+1 650 992 3889",
    "sg:postcode":"94014",
    "sg:province":"CA",
    "sg:tags":[
        "frozen",
        "yogurt"
    ],
    "sg:website":"www.coldstonecreamery.com",
    "wof:name":"Cold Stone Creamery",
    "wof:placetype":"venue"
},
  "geometry": {"coordinates":[-122.471001,37.7034],"type":"Point"}
}