{
  "type": "Feature",
  "properties": {
    "addr:full":"3081 W Lincoln Ave Anaheim CA 92801",
    "addr:housenumber":"3081",
    "addr:postcode":"92801",
    "addr:street":"W Lincoln Ave",
    "iso:country":"US",
    "sg:address":"3081 W Lincoln Ave",
    "sg:city":"Anaheim",
    "sg:classifiers":[
        {
            "category":"Retail",
            "subcategory":"Auto Repair",
            "type":"Services"
        }
    ],
    "sg:phone":"+1 714 995 4013",
    "sg:postcode":"92801",
    "sg:province":"CA",
    "sg:tags":[
        "repairing",
        "automobile"
    ],
    "wof:name":"Accurate Radiator & Air Cond",
    "wof:placetype":"venue"
},
  "geometry": {"coordinates":[-117.996222,33.832034],"type":"Point"}
}