{
  "type": "Feature",
  "properties": {
    "iso:country":"US",
    "sg:address":"1435 W 39th St",
    "sg:city":"Los Angeles",
    "sg:classifiers":[
        {
            "category":"Food & Beverages",
            "subcategory":"Groceries & Convenience Stores",
            "type":"Retail Goods"
        }
    ],
    "sg:phone":"+1 323 732 6018",
    "sg:postcode":"90062",
    "sg:province":"CA",
    "wof:name":"Inner City Mkt",
    "wof:placetype":"venue"
},
  "geometry": {"coordinates":[-118.304001,34.0154],"type":"Point"}
}