{
  "type": "Feature",
  "properties": {
    "iso:country":"US",
    "sg:address":"19722 8th St E",
    "sg:city":"Sonoma",
    "sg:classifiers":[
        {
            "category":"Building & Trades",
            "subcategory":"Construction",
            "type":"Services"
        }
    ],
    "sg:phone":"+1 707 938 2055",
    "sg:postcode":"95476",
    "sg:province":"CA",
    "sg:tags":[
        "grading",
        "contractor"
    ],
    "wof:name":"Road Maintenance Yards",
    "wof:placetype":"venue"
},
  "geometry": {"coordinates":[-122.43747500000001,38.278992],"type":"Point"}
}