{
  "type": "Feature",
  "properties": {
    "addr:full":"8921 S Sepulveda Boulevard Suite 121 Los Angeles CA 90045",
    "addr:housenumber":"8921",
    "addr:postcode":"90045",
    "addr:street":"S Sepulveda Boulevard Suite 121",
    "iso:country":"US",
    "sg:address":"8921 S Sepulveda Boulevard Suite 121",
    "sg:city":"Los Angeles",
    "sg:classifiers":[
        {
            "category":"Personal",
            "type":"Services"
        }
    ],
    "sg:phone":"+1 310 215 3667",
    "sg:postcode":"90045",
    "sg:province":"CA",
    "sg:tags":[
        "towing"
    ],
    "sg:website":"autoshippersdirectbylax.com/",
    "wof:name":"Auto Shippers Direct",
    "wof:placetype":"venue"
},
  "geometry": {"coordinates":[-118.39622900000001,33.955654],"type":"Point"}
}