{
  "type": "Feature",
  "properties": {
    "addr:full":"888 S Figueroa St Los Angeles CA 90017",
    "addr:housenumber":"888",
    "addr:postcode":"90017",
    "addr:street":"S Figueroa St",
    "iso:country":"US",
    "sg:address":"888 S Figueroa St",
    "sg:city":"Los Angeles",
    "sg:classifiers":[
        {
            "category":"Manufacturing",
            "subcategory":"Printing",
            "type":"Manufacturing & Wholesale Goods"
        }
    ],
    "sg:phone":"+1 213 599 4100",
    "sg:postcode":"90017",
    "sg:province":"CA",
    "sg:tags":[
        "periodical"
    ],
    "wof:name":"Weddingbells US",
    "wof:placetype":"venue"
},
  "geometry": {"coordinates":[-118.26282399999999,34.046186],"type":"Point"}
}