{
  "type": "Feature",
  "properties": {
    "iso:country":"US",
    "sg:address":"15046 E Nelson Ave",
    "sg:city":"City Of Industry",
    "sg:classifiers":[
        {
            "category":"Shopping",
            "subcategory":"Computers & Home Electronics",
            "type":"Retail Goods"
        }
    ],
    "sg:phone":"+1 626 336 3536",
    "sg:postcode":"91744",
    "sg:province":"CA",
    "sg:tags":[
        "high",
        "fidelity",
        "stereophonic"
    ],
    "wof:name":"GBS",
    "wof:placetype":"venue"
},
  "geometry": {"coordinates":[-117.96276899999999,34.030047],"type":"Point"}
}