{
  "type": "Feature",
  "properties": {
    "addr:full":"14241 Imperial Hwy Ste M La Mirada CA 90638",
    "addr:housenumber":"14241",
    "addr:postcode":"90638",
    "addr:street":"Imperial Hwy Ste M",
    "iso:country":"US",
    "sg:address":"14241 Imperial Hwy Ste M",
    "sg:city":"La Mirada",
    "sg:classifiers":[
        {
            "category":"Health Services",
            "subcategory":"Doctor",
            "type":"Services"
        }
    ],
    "sg:phone":"+1 562 941 2201",
    "sg:postcode":"90638",
    "sg:province":"CA",
    "sg:tags":[
        "surgeon",
        "oral"
    ],
    "wof:name":"Ozaki Mark M DDS",
    "wof:placetype":"venue"
},
  "geometry": {"coordinates":[-118.02800000000001,33.917198],"type":"Point"}
}