{
  "type": "Feature",
  "properties": {
    "addr:full":"921 E Garvey Ave Monterey Park CA 91755",
    "addr:housenumber":"921",
    "addr:postcode":"91755",
    "addr:street":"E Garvey Ave",
    "iso:country":"US",
    "sg:address":"921 E Garvey Ave",
    "sg:city":"Monterey Park",
    "sg:classifiers":[
        {
            "category":"Insurance",
            "subcategory":"Health Insurance",
            "type":"Services"
        }
    ],
    "sg:phone":"+1 626 288 4344",
    "sg:postcode":"91755",
    "sg:province":"CA",
    "sg:tags":[
        "market"
    ],
    "wof:name":"Weidner's Nutrition Center",
    "wof:placetype":"venue"
},
  "geometry": {"coordinates":[-118.11006,34.062834],"type":"Point"}
}