{
  "type": "Feature",
  "properties": {
    "iso:country":"US",
    "sg:address":"5725 Medallion Ct",
    "sg:city":"Castro Valley",
    "sg:classifiers":[
        {
            "category":"Professional",
            "subcategory":"Management & Consulting",
            "type":"Services"
        }
    ],
    "sg:phone":"+1 510 886 4898",
    "sg:postcode":"94552",
    "sg:province":"CA",
    "sg:tags":[
        "consultant",
        "safety"
    ],
    "wof:name":"Safety Facts",
    "wof:placetype":"venue"
},
  "geometry": {"coordinates":[-122.05679000000001,37.717533],"type":"Point"}
}