{
  "type": "Feature",
  "properties": {
    "iso:country":"US",
    "sg:address":"6032 Laguna Villa Way",
    "sg:city":"Elk Grove",
    "sg:classifiers":[
        {
            "category":"Building & Trades",
            "subcategory":"Construction",
            "type":"Services"
        }
    ],
    "sg:phone":"+1 916 524 6121",
    "sg:postcode":"95758",
    "sg:province":"CA",
    "wof:name":"Custom Sheds & More",
    "wof:placetype":"venue"
},
  "geometry": {"coordinates":[-121.43670299999999,38.420204],"type":"Point"}
}