{
  "type": "Feature",
  "properties": {
    "iso:country":"US",
    "sg:address":"11323 Idaho Ave",
    "sg:city":"Los Angeles",
    "sg:classifiers":[
        {
            "category":"Shopping",
            "subcategory":"Books",
            "type":"Retail Goods"
        }
    ],
    "sg:phone":"+1 310 428 4631",
    "sg:postcode":"90025",
    "sg:province":"CA",
    "sg:tags":[
        "bookstore"
    ],
    "wof:name":"Sideshow Rare Books, Art & Curiosties",
    "wof:placetype":"venue"
},
  "geometry": {"coordinates":[-118.448829,34.045764],"type":"Point"}
}