{
  "type": "Feature",
  "properties": {
    "iso:country":"US",
    "sg:address":"1249 E Deerfield Ct",
    "sg:city":"Ontario",
    "sg:classifiers":[
        {
            "category":"Wholesale",
            "subcategory":"Toys & Hobbies",
            "type":"Manufacturing & Wholesale Goods"
        }
    ],
    "sg:phone":"+1 909 947 6658",
    "sg:postcode":"91761",
    "sg:province":"CA",
    "sg:tags":[
        "wholesaler"
    ],
    "wof:name":"International Rack USA",
    "wof:placetype":"venue"
},
  "geometry": {"coordinates":[-117.626856,34.022766],"type":"Point"}
}