{
  "type": "Feature",
  "properties": {
    "addr:full":"13910 Struikman Rd Cerritos CA 90703",
    "addr:housenumber":"13910",
    "addr:postcode":"ca 90703",
    "addr:street":"Struikman Rd",
    "iso:country":"US",
    "sg:address":"13910 Struikman Rd",
    "sg:city":"Cerritos",
    "sg:phone":"+1 714 739 1003",
    "sg:postcode":"90703",
    "sg:province":"CA",
    "wof:name":"Lee's Marine Service",
    "wof:placetype":"venue"
},
  "geometry": {"coordinates":[-118.035962,33.875119],"type":"Point"}
}