{
  "type": "Feature",
  "properties": {
    "addr:full":"1732 Fillmore St San Francisco CA 94115",
    "addr:housenumber":"1732",
    "addr:postcode":"94115",
    "addr:street":"Fillmore St",
    "iso:country":"US",
    "sg:address":"1732 Fillmore St",
    "sg:city":"San Francisco",
    "sg:classifiers":[
        {
            "category":"Health Services",
            "subcategory":"Health Practitioner",
            "type":"Services"
        }
    ],
    "sg:phone":"+1 415 567 6230",
    "sg:postcode":"94115",
    "sg:province":"CA",
    "sg:tags":[
        "psychologist"
    ],
    "wof:name":"Marta Brody",
    "wof:placetype":"venue"
},
  "geometry": {"coordinates":[-122.433149,37.785792],"type":"Point"}
}