{
  "type": "Feature",
  "properties": {
    "iso:country":"US",
    "sg:address":"333 Hegenberger Rd",
    "sg:city":"Oakland",
    "sg:classifiers":[
        {
            "category":"Banks & Credit Unions",
            "subcategory":"Bank",
            "type":"Services"
        }
    ],
    "sg:phone":"+1 510 562 1894",
    "sg:postcode":"94621",
    "sg:province":"CA",
    "sg:tags":[
        "financing"
    ],
    "wof:name":"Persevere Financial & Assoc",
    "wof:placetype":"venue"
},
  "geometry": {"coordinates":[-122.19838900000001,37.733378],"type":"Point"}
}