{
  "type": "Feature",
  "properties": {
    "iso:country":"US",
    "sg:address":"1235 Pierre Way",
    "sg:city":"El Cajon",
    "sg:classifiers":[
        {
            "category":"Building & Trades",
            "subcategory":"Construction",
            "type":"Services"
        }
    ],
    "sg:phone":"+1 619 442 3754",
    "sg:postcode":"92021",
    "sg:province":"CA",
    "sg:tags":[
        "home",
        "improvement"
    ],
    "wof:name":"Complete Home Svc",
    "wof:placetype":"venue"
},
  "geometry": {"coordinates":[-116.952621,32.811469],"type":"Point"}
}