{
  "type": "Feature",
  "properties": {
    "addr:full":"20036 Ave 160 Porterville CA 93257",
    "addr:housenumber":"20036",
    "addr:postcode":"93257",
    "addr:street":"Ave 160",
    "iso:country":"US",
    "sg:address":"20036 Ave 160",
    "sg:city":"Porterville",
    "sg:classifiers":[
        {
            "category":"Farming",
            "subcategory":"Crops",
            "type":"Manufacturing & Wholesale Goods"
        }
    ],
    "sg:phone":"+1 559 784 9501",
    "sg:postcode":"93257",
    "sg:province":"CA",
    "sg:tags":[
        "grove",
        "nut",
        "tree"
    ],
    "wof:name":"Daniels Family Farm",
    "wof:placetype":"venue"
},
  "geometry": {"coordinates":[-119.121548,36.080403],"type":"Point"}
}