{
  "type": "Feature",
  "properties": {
    "iso:country":"US",
    "sg:address":"302 Main Street",
    "sg:city":"Newport Beach",
    "sg:classifiers":[
        {
            "category":"Sports & Exercise",
            "subcategory":"Bicycle Rental",
            "type":"Entertainment"
        }
    ],
    "sg:phone":"+1 949 675 9529",
    "sg:postcode":"92661",
    "sg:province":"CA",
    "sg:tags":[
        "wear"
    ],
    "wof:name":"Young & Restless",
    "wof:placetype":"venue"
},
  "geometry": {"coordinates":[-117.89909400000001,33.602217],"type":"Point"}
}