{
  "type": "Feature",
  "properties": {
    "iso:country":"US",
    "sg:address":"2225 Sepulveda Blvd",
    "sg:city":"Torrance",
    "sg:classifiers":[
        {
            "category":"Health Services",
            "subcategory":"Medical Lab",
            "type":"Services"
        }
    ],
    "sg:phone":"+1 310 320 7332",
    "sg:postcode":"90501",
    "sg:province":"CA",
    "sg:tags":[
        "laboratory"
    ],
    "wof:name":"Eldorado Dental Lab",
    "wof:placetype":"venue"
},
  "geometry": {"coordinates":[-118.32082800000001,33.820404],"type":"Point"}
}