{
  "type": "Feature",
  "properties": {
    "addr:full":"13271 Hwy 9 Boulder Creek CA 95006",
    "addr:housenumber":"13271",
    "addr:postcode":"95006",
    "addr:street":"Hwy 9",
    "iso:country":"US",
    "sg:address":"13271 Hwy 9",
    "sg:city":"Boulder Creek",
    "sg:classifiers":[
        {
            "category":"Restaurant",
            "type":"Food & Drink"
        }
    ],
    "sg:phone":"+1 831 338 2632",
    "sg:postcode":"95006",
    "sg:province":"CA",
    "wof:name":"Mama Goya's Mexican Food",
    "wof:placetype":"venue"
},
  "geometry": {"coordinates":[-122.122631,37.126401],"type":"Point"}
}