{
  "type": "Feature",
  "properties": {
    "iso:country":"US",
    "sg:address":"198 Bonifacio Pl",
    "sg:city":"Monterey",
    "sg:classifiers":[
        {
            "category":"Shopping",
            "subcategory":"Computers & Home Electronics",
            "type":"Retail Goods"
        }
    ],
    "sg:phone":"+1 831 655 8000",
    "sg:postcode":"93940",
    "sg:province":"CA",
    "sg:tags":[
        "system"
    ],
    "wof:name":"Home Theater Xcellence",
    "wof:placetype":"venue"
},
  "geometry": {"coordinates":[-121.894626,36.59896],"type":"Point"}
}