{
  "type": "Feature",
  "properties": {
    "iso:country":"US",
    "sg:address":"560 Broadway",
    "sg:city":"Chula Vista",
    "sg:classifiers":[
        {
            "category":"Restaurant",
            "type":"Food & Drink"
        }
    ],
    "sg:phone":"+1 619 420 8910",
    "sg:postcode":"91910",
    "sg:province":"CA",
    "wof:name":"Cafe Palacio De Oro",
    "wof:placetype":"venue"
},
  "geometry": {"coordinates":[-117.088947,32.629595],"type":"Point"}
}