{
  "type": "Feature",
  "properties": {
    "iso:country":"US",
    "sg:address":"1580 Sunflower Ave",
    "sg:city":"Costa Mesa",
    "sg:classifiers":[
        {
            "category":"Manufacturing",
            "subcategory":"Rubber & Plastics",
            "type":"Manufacturing & Wholesale Goods"
        }
    ],
    "sg:phone":"+1 714 434 4838",
    "sg:postcode":"92626",
    "sg:province":"CA",
    "sg:tags":[
        "wood",
        "product",
        "hard",
        "drapery",
        "mfg"
    ],
    "wof:name":"Heather Ann Creations",
    "wof:placetype":"venue"
},
  "geometry": {"coordinates":[-117.922821,33.695545],"type":"Point"}
}