{
  "type": "Feature",
  "properties": {
    "iso:country":"US",
    "sg:address":"108 E Clinton Ave",
    "sg:city":"Fresno",
    "sg:classifiers":[
        {
            "category":"Insurance",
            "subcategory":"Insurance Agent",
            "type":"Services"
        }
    ],
    "sg:phone":"+1 559 259 2079",
    "sg:postcode":"93704",
    "sg:province":"CA",
    "wof:name":"Berglund Insurance & Trust",
    "wof:placetype":"venue"
},
  "geometry": {"coordinates":[-119.8087,36.772045],"type":"Point"}
}