{
  "type": "Feature",
  "properties": {
    "addr:full":"17985 Sky Park Cir Irvine CA 92614",
    "addr:housenumber":"17985",
    "addr:postcode":"92614",
    "addr:street":"Sky Park Cir",
    "iso:country":"US",
    "sg:address":"17985 Sky Park Cir",
    "sg:city":"Irvine",
    "sg:classifiers":[
        {
            "category":"Shopping",
            "subcategory":"Florist",
            "type":"Retail Goods"
        }
    ],
    "sg:phone":"+1 949 833 1060",
    "sg:postcode":"92614",
    "sg:province":"CA",
    "sg:website":"www.chrislindsay.com",
    "wof:name":"Chris Lindsay Designs",
    "wof:placetype":"venue"
},
  "geometry": {"coordinates":[-117.859651,33.689301],"type":"Point"}
}