{
  "type": "Feature",
  "properties": {
    "addr:full":"351 Tres Pinos Rd Hollister CA 95023",
    "addr:housenumber":"351",
    "addr:postcode":"hollister ca 95023",
    "addr:street":"Tres Pinos Rd",
    "iso:country":"US",
    "sg:address":"351 Tres Pinos Rd",
    "sg:city":"Hollister",
    "sg:classifiers":[
        {
            "category":"Insurance",
            "subcategory":"Insurance Agent",
            "type":"Services"
        }
    ],
    "sg:phone":"+1 831 637 7457",
    "sg:postcode":"95023",
    "sg:province":"CA",
    "wof:name":"AAA Insurance",
    "wof:placetype":"venue"
},
  "geometry": {"coordinates":[-121.396365,36.839394],"type":"Point"}
}