{
  "type": "Feature",
  "properties": {
    "iso:country":"US",
    "sg:address":"675 S Rancho Santa Fe Rd",
    "sg:city":"San Marcos",
    "sg:classifiers":[
        {
            "category":"Banks & Credit Unions",
            "subcategory":"Bank",
            "type":"Services"
        }
    ],
    "sg:phone":"+1 760 727 6460",
    "sg:postcode":"92078",
    "sg:province":"CA",
    "sg:tags":[
        "savings",
        "loan",
        "association"
    ],
    "sg:website":"www.downeysavings.com",
    "wof:name":"Downey Savings & Loan Assn",
    "wof:placetype":"venue"
},
  "geometry": {"coordinates":[-117.207922,33.131796],"type":"Point"}
}