{
  "type": "Feature",
  "properties": {
    "iso:country":"US",
    "sg:address":"230 E Valley Blvd",
    "sg:city":"San Gabriel",
    "sg:classifiers":[
        {
            "category":"Shopping",
            "subcategory":"Clothing, Apparel, & Fashions",
            "type":"Retail Goods"
        }
    ],
    "sg:phone":"+1 626 280 2823",
    "sg:postcode":"91776",
    "sg:province":"CA",
    "sg:tags":[
        "item",
        "boutique"
    ],
    "wof:name":"Tulip Boutique",
    "wof:placetype":"venue"
},
  "geometry": {"coordinates":[-118.097026,34.079781],"type":"Point"}
}