{
  "type": "Feature",
  "properties": {
    "iso:country":"US",
    "sg:address":"14234 Bellflower Blvd",
    "sg:city":"Bellflower",
    "sg:classifiers":[
        {
            "category":"Personal",
            "subcategory":"Beauty Salon",
            "type":"Services"
        }
    ],
    "sg:phone":"+1 562 804 3880",
    "sg:postcode":"90706",
    "sg:province":"CA",
    "sg:tags":[
        "hair"
    ],
    "wof:name":"Americuts Beauty Salon",
    "wof:placetype":"venue"
},
  "geometry": {"coordinates":[-118.125326,33.902199],"type":"Point"}
}