{
  "type": "Feature",
  "properties": {
    "iso:country":"US",
    "sg:address":"590 Washington St",
    "sg:city":"San Francisco",
    "sg:classifiers":[
        {
            "category":"Cafe",
            "type":"Food & Drink"
        }
    ],
    "sg:menulink":"http://www.allmenus.com/ca/san-francisco/44870-tricolore-cafe/menu/",
    "sg:phone":"+1 415 391 0509",
    "sg:postcode":"94111",
    "sg:province":"CA",
    "sg:tags":[
        "italian"
    ],
    "wof:name":"Tricolore Cafe",
    "wof:placetype":"venue"
},
  "geometry": {"coordinates":[-122.403216,37.795587],"type":"Point"}
}