{
  "type": "Feature",
  "properties": {
    "addr:full":"2113 S San Pedro Street Los Angeles CA 90011",
    "addr:housenumber":"2113",
    "addr:postcode":"90011",
    "addr:street":"S San Pedro Street",
    "iso:country":"US",
    "sg:address":"2113 S San Pedro Street",
    "sg:city":"Los Angeles",
    "sg:classifiers":[
        {
            "category":"Building & Trades",
            "subcategory":"Locksmith",
            "type":"Services"
        }
    ],
    "sg:phone":"+1 213 746 2663",
    "sg:postcode":"90011",
    "sg:province":"CA",
    "sg:tags":[
        "key"
    ],
    "sg:website":"www.guskey.com",
    "wof:name":"Gus Lock & Key Locksmith",
    "wof:placetype":"venue"
},
  "geometry": {"coordinates":[-118.25893499999999,34.025069],"type":"Point"}
}