{
  "type": "Feature",
  "properties": {
    "addr:full":"16100 Red Bank Rd Red Bluff CA 96080",
    "addr:housenumber":"16100",
    "addr:postcode":"96080",
    "addr:street":"Red Bank Rd",
    "iso:country":"US",
    "sg:address":"16100 Red Bank Rd",
    "sg:city":"Red Bluff",
    "sg:classifiers":[
        {
            "category":"Farming",
            "subcategory":"Crops",
            "type":"Manufacturing & Wholesale Goods"
        }
    ],
    "sg:phone":"+1 530 529 5799",
    "sg:postcode":"96080",
    "sg:province":"CA",
    "sg:tags":[
        "grove",
        "nut",
        "tree"
    ],
    "wof:name":"Red Bank Ranch",
    "wof:placetype":"venue"
},
  "geometry": {"coordinates":[-122.445364,40.09352],"type":"Point"}
}