{
  "type": "Feature",
  "properties": {
    "addr:full":"1836 5th St Eureka CA 95501",
    "addr:housenumber":"1836",
    "addr:postcode":"95501",
    "addr:street":"5Th St",
    "iso:country":"US",
    "sg:address":"1836 5th St",
    "sg:city":"Eureka",
    "sg:classifiers":[
        {
            "category":"Restaurant",
            "type":"Food & Drink"
        }
    ],
    "sg:phone":"+1 707 444 8130",
    "sg:postcode":"95501",
    "sg:province":"CA",
    "sg:tags":[
        "shop",
        "coffee"
    ],
    "wof:name":"Jitter Bean Coffee Co",
    "wof:placetype":"venue"
},
  "geometry": {"coordinates":[-124.152241,40.803785],"type":"Point"}
}