{
  "type": "Feature",
  "properties": {
    "iso:country":"US",
    "sg:address":"629 Flint Ave",
    "sg:city":"Wilmington",
    "sg:classifiers":[
        {
            "category":"Wholesale",
            "subcategory":"Auto Parts",
            "type":"Manufacturing & Wholesale Goods"
        }
    ],
    "sg:phone":"+1 310 518 0210",
    "sg:postcode":"90744",
    "sg:province":"CA",
    "sg:tags":[
        "body",
        "automobile",
        "shop"
    ],
    "wof:name":"Adolfo R Rivera",
    "wof:placetype":"venue"
},
  "geometry": {"coordinates":[-118.249354,33.778805],"type":"Point"}
}