{
  "type": "Feature",
  "properties": {
    "addr:full":"7116 Eastern Avenue Bell Gardens CA 90201",
    "addr:housenumber":"7116",
    "addr:postcode":"90201",
    "addr:street":"Eastern Avenue",
    "iso:country":"US",
    "sg:address":"7116 Eastern Avenue",
    "sg:city":"Bell Gardens",
    "sg:classifiers":[
        {
            "category":"Restaurant",
            "type":"Food & Drink"
        }
    ],
    "sg:phone":"+1 323 562 6888",
    "sg:postcode":"90201",
    "sg:province":"CA",
    "wof:name":"Chinatownexpress No 55",
    "wof:placetype":"venue"
},
  "geometry": {"coordinates":[-118.164759,33.968231],"type":"Point"}
}