{
  "type": "Feature",
  "properties": {
    "addr:full":"2025 Telegraph Ave Oakland CA 94612",
    "addr:housenumber":"2025",
    "addr:postcode":"94612",
    "addr:street":"Telegraph Ave",
    "iso:country":"US",
    "sg:address":"2025 Telegraph Ave",
    "sg:city":"Oakland",
    "sg:classifiers":[
        {
            "category":"Manufacturing",
            "subcategory":"Printing",
            "type":"Manufacturing & Wholesale Goods"
        }
    ],
    "sg:phone":"+1 510 444 0220",
    "sg:postcode":"94612",
    "sg:province":"CA",
    "sg:tags":[
        "newspaper"
    ],
    "wof:name":"Korea Times Sf",
    "wof:placetype":"venue"
},
  "geometry": {"coordinates":[-122.269599,37.810164],"type":"Point"}
}