{
  "type": "Feature",
  "properties": {
    "addr:full":"1840 Tenth Ave San Francisco CA 94122",
    "addr:housenumber":"1840",
    "addr:postcode":"94122",
    "addr:street":"Tenth Ave",
    "iso:country":"US",
    "sg:address":"1840 Tenth Ave",
    "sg:city":"San Francisco",
    "sg:classifiers":[
        {
            "category":"Building & Trades",
            "subcategory":"Construction",
            "type":"Services"
        }
    ],
    "sg:phone":"+1 415 681 1655",
    "sg:postcode":"94122",
    "sg:province":"CA",
    "sg:tags":[
        "contractor"
    ],
    "sg:website":"www.rolloutshelves.com",
    "wof:name":"Roll Out Shelves",
    "wof:placetype":"venue"
},
  "geometry": {"coordinates":[-122.4667,37.75389],"type":"Point"}
}