{
  "type": "Feature",
  "properties": {
    "addr:full":"151 N Boulder Dr Redding CA 96003",
    "addr:housenumber":"151",
    "addr:postcode":"96003",
    "addr:street":"N Boulder Dr",
    "iso:country":"US",
    "sg:address":"151 N Boulder Dr",
    "sg:city":"Redding",
    "sg:classifiers":[
        {
            "category":"Recreation",
            "subcategory":"Amusement Park",
            "type":"Entertainment"
        }
    ],
    "sg:phone":"+1 530 246 9550",
    "sg:postcode":"96003",
    "sg:province":"CA",
    "sg:tags":[
        "theme",
        "aquatic",
        "park"
    ],
    "sg:website":"www.waterworkspark.com",
    "wof:name":"Waterworks Park",
    "wof:placetype":"venue"
},
  "geometry": {"coordinates":[-122.37017899999999,40.611486],"type":"Point"}
}