{
  "type": "Feature",
  "properties": {
    "addr:full":"23552 Silverhawk Pl Valencia CA 91354",
    "addr:housenumber":"23552",
    "addr:postcode":"91354",
    "addr:street":"Silverhawk Pl",
    "iso:country":"US",
    "sg:address":"23552 Silverhawk Pl",
    "sg:city":"Valencia",
    "sg:classifiers":[
        {
            "category":"Structure",
            "subcategory":"Office Building",
            "type":"Public Place"
        }
    ],
    "sg:phone":"+1 213 485 6276",
    "sg:postcode":"91354",
    "sg:province":"CA",
    "sg:tags":[
        "park"
    ],
    "wof:name":"City Of Los Angeles",
    "wof:placetype":"venue"
},
  "geometry": {"coordinates":[-118.548207,34.450132],"type":"Point"}
}