{
  "type": "Feature",
  "properties": {
    "addr:full":"217 Bell Canyon Rd Bell Canyon CA 91307",
    "addr:housenumber":"217",
    "addr:postcode":"91307",
    "addr:street":"Bell Canyon Rd Bell",
    "iso:country":"US",
    "sg:address":"217 Bell Canyon Rd",
    "sg:city":"Bell Canyon",
    "sg:classifiers":[
        {
            "category":"Professional",
            "type":"Services"
        }
    ],
    "sg:phone":"+1 818 888 5455",
    "sg:postcode":"91307",
    "sg:province":"CA",
    "sg:tags":[
        "establishment"
    ],
    "wof:name":"Mike Hoff Investigations",
    "wof:placetype":"venue"
},
  "geometry": {"coordinates":[-118.69410000000001,34.201105],"type":"Point"}
}