{
  "type": "Feature",
  "properties": {
    "addr:full":"333 S Alameda St Ste 202 Los Angeles CA 90013",
    "addr:housenumber":"333",
    "addr:postcode":"90013",
    "addr:street":"S Alameda St Ste 202",
    "iso:country":"US",
    "sg:address":"333 S Alameda St Ste 202",
    "sg:city":"Los Angeles",
    "sg:classifiers":[
        {
            "category":"Insurance",
            "subcategory":"Health Insurance",
            "type":"Services"
        }
    ],
    "sg:phone":"+1 408 252 3071",
    "sg:postcode":"90013",
    "sg:province":"CA",
    "sg:tags":[
        "market"
    ],
    "wof:name":"Super Health",
    "wof:placetype":"venue"
},
  "geometry": {"coordinates":[-118.237999,34.0448],"type":"Point"}
}