{
  "type": "Feature",
  "properties": {
    "addr:full":"2540 Rosemead Blvd South El Monte CA 91733",
    "addr:housenumber":"2540",
    "addr:postcode":"91733",
    "addr:street":"Rosemead Blvd",
    "iso:country":"US",
    "sg:address":"2540 Rosemead Blvd",
    "sg:city":"South El Monte",
    "sg:classifiers":[
        {
            "category":"Cinema",
            "subcategory":"Movie Theater",
            "type":"Entertainment"
        }
    ],
    "sg:phone":"+1 626 448 7631",
    "sg:postcode":"91733",
    "sg:province":"CA",
    "wof:name":"Rosemead Swap Meet",
    "wof:placetype":"venue"
},
  "geometry": {"coordinates":[-118.064003,34.057598],"type":"Point"}
}