{
  "type": "Feature",
  "properties": {
    "addr:full":"710 Pacific Cove Dr Port Hueneme CA 93041",
    "addr:housenumber":"710",
    "addr:postcode":"93041",
    "addr:street":"Pacific Cove Dr",
    "iso:country":"US",
    "sg:address":"710 Pacific Cove Dr",
    "sg:city":"Port Hueneme",
    "sg:classifiers":[
        {
            "category":"Retail",
            "subcategory":"Portrait Studio",
            "type":"Services"
        }
    ],
    "sg:phone":"+1 805 984 1372",
    "sg:postcode":"93041",
    "sg:province":"CA",
    "sg:tags":[
        "photographer"
    ],
    "wof:name":"Ernest Hazard Digital Imaging",
    "wof:placetype":"venue"
},
  "geometry": {"coordinates":[-119.219103,34.177693],"type":"Point"}
}