{
  "type": "Feature",
  "properties": {
    "iso:country":"US",
    "sg:address":"566 E Campbell Ave",
    "sg:city":"Campbell",
    "sg:classifiers":[
        {
            "category":"Wholesale",
            "subcategory":"Auto Parts",
            "type":"Manufacturing & Wholesale Goods"
        }
    ],
    "sg:phone":"+1 408 378 6713",
    "sg:postcode":"95008",
    "sg:province":"CA",
    "sg:tags":[
        "supply"
    ],
    "wof:name":"P D G",
    "wof:placetype":"venue"
},
  "geometry": {"coordinates":[-121.939848,37.286934],"type":"Point"}
}