{
  "type": "Feature",
  "properties": {
    "addr:full":"1060 W 13th St Merced CA 95341",
    "addr:housenumber":"1060",
    "addr:postcode":"95341",
    "addr:street":"W 13Th St",
    "iso:country":"US",
    "sg:address":"1060 W 13th St",
    "sg:city":"Merced",
    "sg:classifiers":[
        {
            "category":"Restaurant",
            "type":"Food & Drink"
        }
    ],
    "sg:phone":"+1 209 723 7030",
    "sg:postcode":"95341",
    "sg:province":"CA",
    "wof:name":"Mc Donald's",
    "wof:placetype":"venue"
},
  "geometry": {"coordinates":[-120.49417699999999,37.300051],"type":"Point"}
}