{
  "type": "Feature",
  "properties": {
    "iso:country":"US",
    "sg:address":"1512 Starr Dr",
    "sg:city":"Yuba City",
    "sg:classifiers":[
        {
            "category":"Professional",
            "subcategory":"Accounting & Tax Preparation",
            "type":"Services"
        }
    ],
    "sg:phone":"+1 530 674 1156",
    "sg:postcode":"95993",
    "sg:province":"CA",
    "sg:tags":[
        "bookkeeping",
        "general"
    ],
    "wof:name":"Meyer Bookkeeping & Tax Svc",
    "wof:placetype":"venue"
},
  "geometry": {"coordinates":[-121.641031,39.144301],"type":"Point"}
}