{
  "type": "Feature",
  "properties": {
    "iso:country":"US",
    "sg:address":"10900 Hayvenhurst Ave",
    "sg:city":"Granada Hills",
    "sg:classifiers":[
        {
            "category":"Social Services",
            "subcategory":"Child Care",
            "type":"Services"
        }
    ],
    "sg:phone":"+1 818 368 3231",
    "sg:postcode":"91344",
    "sg:province":"CA",
    "wof:name":"North Valley YMCA-Tulsa",
    "wof:placetype":"venue"
},
  "geometry": {"coordinates":[-118.493477,34.270132],"type":"Point"}
}