{
  "type": "Feature",
  "properties": {
    "addr:full":"1431 Grove St Healdsburg CA 95476",
    "addr:housenumber":"1431",
    "addr:postcode":"95476",
    "addr:street":"Grove St",
    "iso:country":"US",
    "sg:address":"1431 Grove St",
    "sg:city":"Healdsburg",
    "sg:classifiers":[
        {
            "category":"Building & Trades",
            "subcategory":"Construction",
            "type":"Services"
        }
    ],
    "sg:phone":"+1 707 433 3030",
    "sg:postcode":"95476",
    "sg:province":"CA",
    "sg:tags":[
        "planning",
        "remodeling",
        "kitchen"
    ],
    "wof:name":"Creative Kitchens",
    "wof:placetype":"venue"
},
  "geometry": {"coordinates":[-122.51294799999999,38.293279],"type":"Point"}
}