{
  "type": "Feature",
  "properties": {
    "addr:full":"8511 Lindley Ave Northridge CA 91325",
    "addr:housenumber":"8511",
    "addr:postcode":"91325",
    "addr:street":"Lindley Ave",
    "iso:country":"US",
    "sg:address":"8511 Lindley Ave",
    "sg:city":"Northridge",
    "sg:classifiers":[
        {
            "category":"Home & Garden",
            "subcategory":"Carpets & Floor Coverings",
            "type":"Retail Goods"
        }
    ],
    "sg:phone":"+1 818 576 9686",
    "sg:postcode":"91325",
    "sg:province":"CA",
    "sg:tags":[
        "laying",
        "contractor"
    ],
    "wof:name":"Toxtle Carpet Services",
    "wof:placetype":"venue"
},
  "geometry": {"coordinates":[-118.527421,34.22621],"type":"Point"}
}