{
  "type": "Feature",
  "properties": {
    "addr:full":"310 E Providencia Ave Burbank CA 91502",
    "addr:housenumber":"310",
    "addr:postcode":"91502",
    "addr:street":"E Providencia Ave",
    "iso:country":"US",
    "sg:address":"310 E Providencia Ave",
    "sg:city":"Burbank",
    "sg:classifiers":[
        {
            "category":"Building & Trades",
            "subcategory":"Equipment Rental",
            "type":"Services"
        }
    ],
    "sg:phone":"+1 818 845 5507",
    "sg:postcode":"91502",
    "sg:province":"CA",
    "sg:tags":[
        "crane"
    ],
    "wof:name":"High Crane Svc",
    "wof:placetype":"venue"
},
  "geometry": {"coordinates":[-118.301542,34.179327],"type":"Point"}
}