{
  "type": "Feature",
  "properties": {
    "iso:country":"US",
    "sg:address":"1142 W Broadway",
    "sg:city":"Anaheim",
    "sg:classifiers":[
        {
            "category":"Retail",
            "subcategory":"Repair Shop",
            "type":"Services"
        }
    ],
    "sg:phone":"+1 714 956 2463",
    "sg:postcode":"92805",
    "sg:province":"CA",
    "wof:name":"Campos Handyman & Cleaning Ser",
    "wof:placetype":"venue"
},
  "geometry": {"coordinates":[-117.926597,33.830153],"type":"Point"}
}