{
  "type": "Feature",
  "properties": {
    "iso:country":"US",
    "sg:address":"245 Ocean View Ave",
    "sg:city":"Santa Cruz",
    "sg:classifiers":[
        {
            "category":"Farming",
            "subcategory":"Livestock Farm",
            "type":"Manufacturing & Wholesale Goods"
        }
    ],
    "sg:phone":"+1 831 427 1743",
    "sg:postcode":"95062",
    "sg:province":"CA",
    "sg:tags":[
        "ranch"
    ],
    "wof:name":"Ocean View Ranch",
    "wof:placetype":"venue"
},
  "geometry": {"coordinates":[-122.014393,36.971269],"type":"Point"}
}