{
  "type": "Feature",
  "properties": {
    "iso:country":"US",
    "sg:address":"1615 Dry Creek Rd",
    "sg:city":"San Jose",
    "sg:classifiers":[
        {
            "category":"Social Services",
            "type":"Services"
        },
        {
            "category":"Organizations",
            "subcategory":"Community Association",
            "type":"Services"
        }
    ],
    "sg:phone":"+1 408 264 3058",
    "sg:postcode":"95125",
    "sg:province":"CA",
    "sg:tags":[
        "local",
        "welfare"
    ],
    "sg:website":"www.jlsj.org",
    "wof:name":"Junior League of San Jose",
    "wof:placetype":"venue"
},
  "geometry": {"coordinates":[-121.90779999999999,37.288478],"type":"Point"}
}