{
  "type": "Feature",
  "properties": {
    "iso:country":"US",
    "sg:address":"9216 Valley Blvd",
    "sg:city":"Rosemead",
    "sg:classifiers":[
        {
            "category":"Wholesale",
            "subcategory":"Machinery & Supplies",
            "type":"Manufacturing & Wholesale Goods"
        }
    ],
    "sg:phone":"+1 626 288 7891",
    "sg:postcode":"91770",
    "sg:province":"CA",
    "sg:tags":[
        "equipment",
        "cosmetic",
        "beauty",
        "salons-equipment"
    ],
    "sg:website":"http://www.spabeautysupply.com",
    "wof:name":"Spa Beauty Supply",
    "wof:placetype":"venue"
},
  "geometry": {"coordinates":[-118.069,34.080799],"type":"Point"}
}