{
  "type": "Feature",
  "properties": {
    "addr:full":"2300 N Park Blvd Pittsburg CA 94565",
    "addr:housenumber":"2300",
    "addr:postcode":"94565",
    "addr:street":"N Park Blvd",
    "iso:country":"US",
    "sg:address":"2300 N Park Blvd",
    "sg:city":"Pittsburg",
    "sg:classifiers":[
        {
            "category":"Home & Garden",
            "subcategory":"Building Materials",
            "type":"Retail Goods"
        }
    ],
    "sg:phone":"+1 925 473 1900",
    "sg:postcode":"94565",
    "sg:province":"CA",
    "sg:website":"www.homedepot.com",
    "wof:name":"Home Depot",
    "wof:placetype":"venue"
},
  "geometry": {"coordinates":[-121.856904,38.011094],"type":"Point"}
}