{
  "type": "Feature",
  "properties": {
    "addr:full":"1633 Cypress Ln Paradise CA 95969",
    "addr:housenumber":"1633",
    "addr:postcode":"95969",
    "addr:street":"Cypress Ln",
    "iso:country":"US",
    "sg:address":"1633 Cypress Ln",
    "sg:city":"Paradise",
    "sg:classifiers":[
        {
            "category":"Social Services",
            "subcategory":"Job Training",
            "type":"Services"
        }
    ],
    "sg:phone":"+1 530 877 6304",
    "sg:postcode":"95969",
    "sg:province":"CA",
    "sg:tags":[
        "rehabilitation"
    ],
    "wof:name":"Med Serv Rehabilitation Svc",
    "wof:placetype":"venue"
},
  "geometry": {"coordinates":[-121.585504,39.783871],"type":"Point"}
}