{
  "type": "Feature",
  "properties": {
    "addr:full":"3327 Royal Meadow Ln San Jose CA 95135",
    "addr:housenumber":"3327",
    "addr:postcode":"95135",
    "addr:street":"Royal Meadow Ln",
    "iso:country":"US",
    "sg:address":"3327 Royal Meadow Ln",
    "sg:city":"San Jose",
    "sg:classifiers":[
        {
            "category":"Building & Trades",
            "subcategory":"Construction",
            "type":"Services"
        }
    ],
    "sg:phone":"+1 408 223 0212",
    "sg:postcode":"95135",
    "sg:province":"CA",
    "sg:tags":[
        "painter"
    ],
    "wof:name":"M & M Painting",
    "wof:placetype":"venue"
},
  "geometry": {"coordinates":[-121.743689,37.282496],"type":"Point"}
}