{
  "type": "Feature",
  "properties": {
    "addr:full":"15017 Skyridge Rd Poway CA 92064",
    "addr:housenumber":"15017",
    "addr:postcode":"ca 92064",
    "addr:street":"Skyridge Rd",
    "iso:country":"US",
    "sg:address":"15017 Skyridge Rd",
    "sg:city":"Poway",
    "sg:classifiers":[
        {
            "category":"Professional",
            "subcategory":"Business Services",
            "type":"Services"
        }
    ],
    "sg:phone":"+1 858 513 9171",
    "sg:postcode":"92064",
    "sg:province":"CA",
    "sg:tags":[
        "interior",
        "consultant",
        "design",
        "decorator"
    ],
    "sg:website":"www.lisatappinteriordesign.com",
    "wof:name":"Lisa Tapp Interior Design",
    "wof:placetype":"venue"
},
  "geometry": {"coordinates":[-116.99708,32.99652],"type":"Point"}
}