{
  "type": "Feature",
  "properties": {
    "addr:full":"3439 Sacramento Street Suite 202 San Francisco CA 94118",
    "addr:housenumber":"3439",
    "addr:postcode":"94118",
    "addr:street":"Sacramento Street Suite 202",
    "iso:country":"US",
    "sg:address":"3439 Sacramento Street Suite 202",
    "sg:city":"San Francisco",
    "sg:classifiers":[
        {
            "category":"Professional",
            "subcategory":"Computer Services",
            "type":"Services"
        }
    ],
    "sg:phone":"+1 650 427 0502",
    "sg:postcode":"94118",
    "sg:province":"CA",
    "sg:tags":[
        "mobile-payment-network",
        "alternative-payment",
        "electronic-payment",
        "smartphone-payment",
        "person-to-person-payment",
        "software-based-nfc"
    ],
    "sg:website":"http://www.cimbal.com",
    "wof:name":"Cimbal",
    "wof:placetype":"venue"
},
  "geometry": {"coordinates":[-122.449786,37.787774],"type":"Point"}
}