{
  "type": "Feature",
  "properties": {
    "iso:country":"US",
    "sg:address":"1010 Wilshire Blvd Ste 804",
    "sg:city":"Los Angeles",
    "sg:classifiers":[
        {
            "category":"Communications",
            "subcategory":"Film & Video Production",
            "type":"Services"
        }
    ],
    "sg:phone":"+1 213 785 5230",
    "sg:postcode":"90017",
    "sg:province":"CA",
    "sg:tags":[
        "video/film"
    ],
    "sg:website":"www.rivetingentertainment.com",
    "wof:name":"Riveting Entertainment",
    "wof:placetype":"venue"
},
  "geometry": {"coordinates":[-118.262213,34.051505],"type":"Point"}
}