{
  "type": "Feature",
  "properties": {
    "iso:country":"US",
    "sg:address":"1369 Garden Hwy",
    "sg:city":"Sacramento",
    "sg:classifiers":[
        {
            "category":"Restaurant",
            "type":"Food & Drink"
        }
    ],
    "sg:phone":"+1 916 649 0390",
    "sg:postcode":"95833",
    "sg:province":"CA",
    "sg:tags":[
        "drinking",
        "eating"
    ],
    "wof:name":"Chevys Fresh Mex Restaurant",
    "wof:placetype":"venue"
},
  "geometry": {"coordinates":[-121.498924,38.60793],"type":"Point"}
}