{
  "type": "Feature",
  "properties": {
    "iso:country":"US",
    "sg:address":"10225 Telephone Rd",
    "sg:city":"Ventura",
    "sg:classifiers":[
        {
            "category":"Health Services",
            "subcategory":"Optometrist",
            "type":"Services"
        },
        {
            "category":"Shopping",
            "subcategory":"Optical Goods",
            "type":"Retail Goods"
        },
        {
            "category":"Shopping",
            "subcategory":"Optician",
            "type":"Retail Goods"
        }
    ],
    "sg:phone":"+1 805 647 4950",
    "sg:postcode":"93004",
    "sg:province":"CA",
    "sg:tags":[
        "lens",
        "contact"
    ],
    "sg:website":"http://www.frickoptometry.com",
    "wof:name":"Gary M. Frick OD",
    "wof:placetype":"venue"
},
  "geometry": {"coordinates":[-119.162002,34.277347],"type":"Point"}
}