{
  "type": "Feature",
  "properties": {
    "iso:country":"US",
    "sg:address":"25285 Madison Ave",
    "sg:city":"Murrieta",
    "sg:classifiers":[
        {
            "category":"Health Services",
            "subcategory":"Doctor",
            "type":"Services"
        }
    ],
    "sg:phone":"+1 951 698 3585",
    "sg:postcode":"92562",
    "sg:province":"CA",
    "sg:tags":[
        "dentist"
    ],
    "wof:name":"Madison Springs Dental",
    "wof:placetype":"venue"
},
  "geometry": {"coordinates":[-117.200706,33.557565],"type":"Point"}
}