{
  "type": "Feature",
  "properties": {
    "addr:full":"15341 Texaco Ave Paramount CA 90723",
    "addr:postcode":"15341;90723",
    "addr:street":"Texaco Ave",
    "iso:country":"US",
    "sg:address":"15341 Texaco Ave",
    "sg:city":"Paramount",
    "sg:classifiers":[
        {
            "category":"Wholesale",
            "subcategory":"Stationery",
            "type":"Manufacturing & Wholesale Goods"
        }
    ],
    "sg:phone":"+1 562 529 3686",
    "sg:postcode":"90723",
    "sg:province":"CA",
    "sg:tags":[
        "product",
        "paper"
    ],
    "sg:website":"www.brentpapertube.com",
    "wof:name":"Brent Paper Tube",
    "wof:placetype":"venue"
},
  "geometry": {"coordinates":[-118.171955,33.894475],"type":"Point"}
}