{
  "type": "Feature",
  "properties": {
    "addr:full":"5861 Stanford Ave Garden Grove CA 92845",
    "addr:housenumber":"5861",
    "addr:postcode":"92845",
    "addr:street":"Stanford Ave",
    "iso:country":"US",
    "sg:address":"5861 Stanford Ave",
    "sg:city":"Garden Grove",
    "sg:classifiers":[
        {
            "category":"Building & Trades",
            "subcategory":"Plumbing",
            "type":"Services"
        }
    ],
    "sg:phone":"+1 714 897 3499",
    "sg:postcode":"92845",
    "sg:province":"CA",
    "sg:tags":[
        "contractor"
    ],
    "wof:name":"Alva Plumbing",
    "wof:placetype":"venue"
},
  "geometry": {"coordinates":[-118.03027,33.778053],"type":"Point"}
}