{
  "type": "Feature",
  "properties": {
    "addr:full":"18691 Buena Vista Ave Yorba Linda CA 92886",
    "addr:housenumber":"18691",
    "addr:postcode":"92886",
    "addr:street":"Buena Vista Ave",
    "iso:country":"US",
    "sg:address":"18691 Buena Vista Ave",
    "sg:city":"Yorba Linda",
    "sg:classifiers":[
        {
            "category":"Building & Trades",
            "subcategory":"Construction",
            "type":"Services"
        }
    ],
    "sg:phone":"+1 714 970 5626",
    "sg:postcode":"92886",
    "sg:province":"CA",
    "sg:tags":[
        "excavation",
        "contractor"
    ],
    "wof:name":"Lee Verpooten & Sons",
    "wof:placetype":"venue"
},
  "geometry": {"coordinates":[-117.80405,33.88001],"type":"Point"}
}