{
  "type": "Feature",
  "properties": {
    "iso:country":"US",
    "sg:address":"5101 Crockett Pl",
    "sg:city":"Oakland",
    "sg:classifiers":[
        {
            "category":"Banks & Credit Unions",
            "subcategory":"Investment Brokerage",
            "type":"Services"
        }
    ],
    "sg:phone":"+1 510 336 2181",
    "sg:postcode":"94602",
    "sg:province":"CA",
    "sg:tags":[
        "consultant",
        "planning",
        "financial"
    ],
    "wof:name":"AIG Royal Alliance",
    "wof:placetype":"venue"
},
  "geometry": {"coordinates":[-122.181015,37.808659],"type":"Point"}
}