{
  "type": "Feature",
  "properties": {
    "addr:full":"3901 Broadway Oakland CA 94611",
    "addr:housenumber":"3901",
    "addr:postcode":"94611",
    "addr:street":"Broadway",
    "iso:country":"US",
    "sg:address":"3901 Broadway",
    "sg:city":"Oakland",
    "sg:classifiers":[
        {
            "category":"Health Services",
            "subcategory":"Clinic",
            "type":"Services"
        },
        {
            "category":"Organizations",
            "subcategory":"Non-profit Organization",
            "type":"Services"
        }
    ],
    "sg:phone":"+1 510 595 4400",
    "sg:postcode":"94611",
    "sg:province":"CA",
    "sg:tags":[
        "medical",
        "service/non-profit",
        "community"
    ],
    "sg:website":"www.redcrossbayarea.org",
    "wof:name":"American Red Cross Bay Area Chapter",
    "wof:placetype":"venue"
},
  "geometry": {"coordinates":[-122.257879,37.827037],"type":"Point"}
}