{
  "type": "Feature",
  "properties": {
    "iso:country":"US",
    "sg:address":"57 East St",
    "sg:city":"Hollister",
    "sg:classifiers":[
        {
            "category":"Home & Garden",
            "subcategory":"Building Materials",
            "type":"Retail Goods"
        }
    ],
    "sg:phone":"+1 831 637 4145",
    "sg:postcode":"95023",
    "sg:province":"CA",
    "sg:tags":[
        "paint"
    ],
    "wof:name":"Hollister Paint Store",
    "wof:placetype":"venue"
},
  "geometry": {"coordinates":[-121.40082,36.856045],"type":"Point"}
}