{
  "type": "Feature",
  "properties": {
    "iso:country":"US",
    "sg:address":"1364 Cam Real",
    "sg:city":"San Bernardino",
    "sg:classifiers":[
        {
            "category":"Autos & Motor Vehicles",
            "subcategory":"Motorcycle Sales",
            "type":"Retail Goods"
        }
    ],
    "sg:phone":"+1 951 237 8199",
    "sg:postcode":"92408",
    "sg:province":"CA",
    "sg:tags":[
        "scooter"
    ],
    "sg:website":"www.redlinedchoppers.com",
    "wof:name":"Redlined Choppers",
    "wof:placetype":"venue"
},
  "geometry": {"coordinates":[-117.29605,34.074589],"type":"Point"}
}