{
  "type": "Feature",
  "properties": {
    "iso:country":"US",
    "sg:address":"3665 S Broadway",
    "sg:city":"Los Angeles",
    "sg:classifiers":[
        {
            "category":"Shopping",
            "subcategory":"Clothing, Apparel, & Fashions",
            "type":"Retail Goods"
        }
    ],
    "sg:phone":"+1 323 234 0816",
    "sg:postcode":"90007",
    "sg:province":"CA",
    "sg:tags":[
        "garment",
        "lettering"
    ],
    "wof:name":"P J Max Inc Corp",
    "wof:placetype":"venue"
},
  "geometry": {"coordinates":[-118.275884,34.016016],"type":"Point"}
}