{
  "type": "Feature",
  "properties": {
    "addr:full":"12525 Ojai Santa Paula Rd Ojai CA 93023",
    "addr:housenumber":"12525",
    "addr:postcode":"93023",
    "addr:street":"Ojai Santa Paula Rd",
    "iso:country":"US",
    "sg:address":"12525 Ojai Santa Paula Rd",
    "sg:city":"Ojai",
    "sg:classifiers":[
        {
            "category":"Education",
            "subcategory":"School",
            "type":"Public Place"
        }
    ],
    "sg:phone":"+1 805 525 3038",
    "sg:postcode":"93023",
    "sg:province":"CA",
    "wof:name":"Summit Elementary School",
    "wof:placetype":"venue"
},
  "geometry": {"coordinates":[-119.138841,34.436564],"type":"Point"}
}