{
  "type": "Feature",
  "properties": {
    "iso:country":"US",
    "sg:address":"5314 Drybank Dr",
    "sg:city":"Rolling Hills Estates",
    "sg:classifiers":[
        {
            "category":"Food & Beverages",
            "subcategory":"Dairy",
            "type":"Retail Goods"
        }
    ],
    "sg:phone":"+1 310 377 0595",
    "sg:postcode":"90274",
    "sg:province":"CA",
    "sg:tags":[
        "frozen",
        "yogurt",
        "ice",
        "cream"
    ],
    "wof:name":"Yummy Yogurt",
    "wof:placetype":"venue"
},
  "geometry": {"coordinates":[-118.371906,33.771943],"type":"Point"}
}