{
  "type": "Feature",
  "properties": {
    "addr:full":"1500 Viking St Escalon CA 95320",
    "addr:housenumber":"1500",
    "addr:postcode":"95320",
    "addr:street":"Viking St",
    "iso:country":"US",
    "sg:address":"1500 Viking St",
    "sg:city":"Escalon",
    "sg:classifiers":[
        {
            "category":"Organizations",
            "subcategory":"Community Association",
            "type":"Services"
        }
    ],
    "sg:phone":"+1 209 838 0325",
    "sg:postcode":"95320",
    "sg:province":"CA",
    "sg:tags":[
        "fraternal"
    ],
    "wof:name":"Escalon Masonic Lodge",
    "wof:placetype":"venue"
},
  "geometry": {"coordinates":[-120.993583,37.796622],"type":"Point"}
}