{
  "type": "Feature",
  "properties": {
    "iso:country":"US",
    "sg:address":"1750 McHenry Ave",
    "sg:city":"Escalon",
    "sg:classifiers":[
        {
            "category":"Manufacturing",
            "subcategory":"Wood Products",
            "type":"Manufacturing & Wholesale Goods"
        }
    ],
    "sg:phone":"+1 209 838 7170",
    "sg:postcode":"95320",
    "sg:province":"CA",
    "sg:tags":[
        "mfg",
        "contractor",
        "carpentry"
    ],
    "wof:name":"Bills Woodwork",
    "wof:placetype":"venue"
},
  "geometry": {"coordinates":[-120.996549,37.793879],"type":"Point"}
}