{
  "type": "Feature",
  "properties": {
    "iso:country":"US",
    "sg:address":"7560 W Sunset Blvd",
    "sg:city":"Los Angeles",
    "sg:classifiers":[
        {
            "category":"Personal",
            "subcategory":"Tattoo Parlor",
            "type":"Services"
        }
    ],
    "sg:phone":"+1 323 882 8165",
    "sg:postcode":"90046",
    "sg:province":"CA",
    "sg:website":"www.purplepanthertattoos.com",
    "wof:name":"Purple Panther Tattoo",
    "wof:placetype":"venue"
},
  "geometry": {"coordinates":[-118.353996,34.098202],"type":"Point"}
}