{
  "type": "Feature",
  "properties": {
    "addr:full":"25636 N Ave Stanford Valencia CA 91355",
    "addr:housenumber":"25636",
    "addr:postcode":"91355",
    "addr:street":"N Ave",
    "iso:country":"US",
    "sg:address":"25636 N Ave Stanford",
    "sg:city":"Valencia",
    "sg:classifiers":[
        {
            "category":"Manufacturing",
            "subcategory":"Tools & Machinery",
            "type":"Manufacturing & Wholesale Goods"
        }
    ],
    "sg:phone":"+1 661 257 4060",
    "sg:postcode":"91355",
    "sg:province":"CA",
    "sg:tags":[
        "mfg",
        "mold",
        "marble",
        "cultured",
        "for"
    ],
    "wof:name":"Gruber Systems Inc",
    "wof:placetype":"venue"
},
  "geometry": {"coordinates":[-118.587503,34.432904],"type":"Point"}
}