{
  "type": "Feature",
  "properties": {
    "iso:country":"US",
    "sg:address":"6137 Watt Avenue",
    "sg:city":"North Highlands",
    "sg:classifiers":[
        {
            "category":"Health Services",
            "subcategory":"Doctor",
            "type":"Services"
        }
    ],
    "sg:phone":"+1 916 339 2229",
    "sg:postcode":"95660",
    "sg:province":"CA",
    "wof:name":"Sacramento Family Medical Clinic",
    "wof:placetype":"venue"
},
  "geometry": {"coordinates":[-121.38298899999999,38.678553],"type":"Point"}
}