{
  "type": "Feature",
  "properties": {
    "addr:full":"3501 S Mooney Blvd Visalia CA 93277",
    "addr:housenumber":"3501",
    "addr:postcode":"93277",
    "addr:street":"S Mooney Blvd",
    "iso:country":"US",
    "sg:address":"3501 S Mooney Blvd",
    "sg:city":"Visalia",
    "sg:classifiers":[
        {
            "category":"Shopping",
            "subcategory":"Optical Goods",
            "type":"Retail Goods"
        },
        {
            "category":"Shopping",
            "subcategory":"Optician",
            "type":"Retail Goods"
        },
        {
            "category":"Health Services",
            "subcategory":"Optometrist",
            "type":"Services"
        },
        {
            "category":"Personal",
            "subcategory":"Shoe Repair & Shine",
            "type":"Services"
        }
    ],
    "sg:phone":"+1 559 636 0737",
    "sg:postcode":"93277",
    "sg:province":"CA",
    "sg:tags":[
        "eyeglass",
        "sunglass"
    ],
    "sg:website":"http://",
    "wof:name":"Sears Optical",
    "wof:placetype":"venue"
},
  "geometry": {"coordinates":[-119.313759,36.299273],"type":"Point"}
}