{
  "type": "Feature",
  "properties": {
    "addr:full":"9666 Owensmouth Ave Chatsworth CA 91311",
    "addr:housenumber":"9666",
    "addr:postcode":"91311",
    "addr:street":"Owensmouth Ave",
    "iso:country":"US",
    "sg:address":"9666 Owensmouth Ave",
    "sg:city":"Chatsworth",
    "sg:classifiers":[
        {
            "category":"Retail",
            "subcategory":"Auto Repair",
            "type":"Services"
        }
    ],
    "sg:phone":"+1 818 882 0500",
    "sg:postcode":"91311",
    "sg:province":"CA",
    "sg:tags":[
        "machine",
        "automobile",
        "shop"
    ],
    "wof:name":"R D Machine",
    "wof:placetype":"venue"
},
  "geometry": {"coordinates":[-118.60242700000001,34.244386],"type":"Point"}
}