{
  "type": "Feature",
  "properties": {
    "addr:full":"2086 Placentia Ave Costa Mesa CA 92627",
    "addr:housenumber":"2086",
    "addr:postcode":"92627",
    "addr:street":"Placentia Ave",
    "iso:country":"US",
    "sg:address":"2086 Placentia Ave",
    "sg:city":"Costa Mesa",
    "sg:classifiers":[
        {
            "category":"Wholesale",
            "subcategory":"Construction Materials",
            "type":"Manufacturing & Wholesale Goods"
        }
    ],
    "sg:phone":"+1 949 650 8449",
    "sg:postcode":"92627",
    "sg:province":"CA",
    "sg:tags":[
        "concrete",
        "product"
    ],
    "wof:name":"Ocean Pacific Marine Products",
    "wof:placetype":"venue"
},
  "geometry": {"coordinates":[-117.931989,33.649931],"type":"Point"}
}