{
  "type": "Feature",
  "properties": {
    "iso:country":"US",
    "sg:address":"9736 Airport Vista Rd",
    "sg:city":"Santee",
    "sg:classifiers":[
        {
            "category":"Building & Trades",
            "subcategory":"Plumbing",
            "type":"Services"
        }
    ],
    "sg:phone":"+1 619 562 2000",
    "sg:postcode":"92071",
    "sg:province":"CA",
    "sg:tags":[
        "heating",
        "contractor"
    ],
    "wof:name":"Air Santee",
    "wof:placetype":"venue"
},
  "geometry": {"coordinates":[-116.98502000000001,32.834377],"type":"Point"}
}