{
  "type": "Feature",
  "properties": {
    "iso:country":"US",
    "sg:address":"28519 Meadow Glen Way W",
    "sg:city":"Escondido",
    "sg:classifiers":[
        {
            "category":"Wholesale",
            "subcategory":"Apparel",
            "type":"Manufacturing & Wholesale Goods"
        }
    ],
    "sg:phone":"+1 760 751 9737",
    "sg:postcode":"92026",
    "sg:province":"CA",
    "sg:tags":[
        "hair",
        "accessory"
    ],
    "wof:name":"Hairscate",
    "wof:placetype":"venue"
},
  "geometry": {"coordinates":[-117.11949,33.22416],"type":"Point"}
}