{
  "type": "Feature",
  "properties": {
    "addr:full":"3509 Iroquois Ave Long Beach CA 90808",
    "addr:housenumber":"3509",
    "addr:postcode":"90808",
    "addr:street":"Iroquois Ave",
    "iso:country":"US",
    "sg:address":"3509 Iroquois Ave",
    "sg:city":"Long Beach",
    "sg:classifiers":[
        {
            "category":"Professional",
            "subcategory":"Art Services",
            "type":"Services"
        }
    ],
    "sg:phone":"+1 562 429 8538",
    "sg:postcode":"90808",
    "sg:province":"CA",
    "sg:tags":[
        "graphic",
        "designer"
    ],
    "wof:name":"Snap Graphics",
    "wof:placetype":"venue"
},
  "geometry": {"coordinates":[-118.106465,33.82184],"type":"Point"}
}