{
  "type": "Feature",
  "properties": {
    "addr:full":"2077 20th St W Rosamond CA 93560",
    "addr:housenumber":"2077",
    "addr:postcode":"93560",
    "addr:street":"20Th St W",
    "iso:country":"US",
    "sg:address":"2077 20th St W",
    "sg:city":"Rosamond",
    "sg:classifiers":[
        {
            "category":"Manufacturing",
            "subcategory":"Printing",
            "type":"Manufacturing & Wholesale Goods"
        }
    ],
    "sg:phone":"+1 661 256 0121",
    "sg:postcode":"93560",
    "sg:province":"CA",
    "sg:tags":[
        "newspaper",
        "publishing"
    ],
    "wof:name":"Rosamond Tribune",
    "wof:placetype":"venue"
},
  "geometry": {"coordinates":[-118.16706499999999,34.851622],"type":"Point"}
}