{
  "type": "Feature",
  "properties": {
    "iso:country":"US",
    "sg:address":"44824 Cedar Ave",
    "sg:city":"Lancaster",
    "sg:classifiers":[
        {
            "category":"Banks & Credit Unions",
            "subcategory":"Investment Brokerage",
            "type":"Services"
        },
        {
            "category":"Insurance",
            "subcategory":"Hazard Insurance",
            "type":"Services"
        }
    ],
    "sg:phone":"+1 661 945 3494",
    "sg:postcode":"93534",
    "sg:province":"CA",
    "sg:tags":[
        "agent",
        "resume"
    ],
    "sg:website":"http://www.viscofinancial.com",
    "wof:name":"Visco Finaical Insurance",
    "wof:placetype":"venue"
},
  "geometry": {"coordinates":[-118.13930000000001,34.69671],"type":"Point"}
}