{
  "type": "Feature",
  "properties": {
    "iso:country":"US",
    "sg:address":"3187 Airway Ave",
    "sg:city":"Costa Mesa",
    "sg:classifiers":[
        {
            "category":"Wholesale",
            "subcategory":"Electrical",
            "type":"Manufacturing & Wholesale Goods"
        }
    ],
    "sg:phone":"+1 714 241 0362",
    "sg:postcode":"92626",
    "sg:province":"CA",
    "sg:tags":[
        "control"
    ],
    "sg:website":"www.amx.com",
    "wof:name":"AMX West",
    "wof:placetype":"venue"
},
  "geometry": {"coordinates":[-117.86903599999999,33.682598],"type":"Point"}
}