{
  "type": "Feature",
  "properties": {
    "iso:country":"US",
    "sg:address":"15108 del Gado Dr",
    "sg:city":"Sherman Oaks",
    "sg:classifiers":[
        {
            "category":"Building & Trades",
            "subcategory":"Electrical",
            "type":"Services"
        }
    ],
    "sg:phone":"+1 818 995 1898",
    "sg:postcode":"91403",
    "sg:province":"CA",
    "sg:tags":[
        "electric",
        "contractor"
    ],
    "wof:name":"Sigmond Electric Co",
    "wof:placetype":"venue"
},
  "geometry": {"coordinates":[-118.462323,34.147881],"type":"Point"}
}