{
  "type": "Feature",
  "properties": {
    "addr:full":"5260 Beach Blvd Buena Park CA 90621",
    "addr:housenumber":"5260",
    "addr:postcode":"90621",
    "addr:street":"Beach Blvd",
    "iso:country":"US",
    "sg:address":"5260 Beach Blvd",
    "sg:city":"Buena Park",
    "sg:classifiers":[
        {
            "category":"Retail",
            "subcategory":"Laundry & Dry Cleaning",
            "type":"Services"
        }
    ],
    "sg:phone":"+1 714 739 5533",
    "sg:postcode":"90621",
    "sg:province":"CA",
    "sg:tags":[
        "cleaners"
    ],
    "wof:name":"Best Cleaners",
    "wof:placetype":"venue"
},
  "geometry": {"coordinates":[-117.994488,33.885719],"type":"Point"}
}