{
  "type": "Feature",
  "properties": {
    "iso:country":"US",
    "sg:address":"129 S Linden Ave",
    "sg:city":"S San Francisco",
    "sg:classifiers":[
        {
            "category":"Retail",
            "subcategory":"Auto Repair",
            "type":"Services"
        }
    ],
    "sg:phone":"+1 650 877 0310",
    "sg:postcode":"94080",
    "sg:province":"CA",
    "sg:tags":[
        "repairing",
        "automobile"
    ],
    "sg:website":"www.apenterprise.com",
    "wof:name":"A P Enterprises",
    "wof:placetype":"venue"
},
  "geometry": {"coordinates":[-122.41414,37.643467],"type":"Point"}
}