{
  "type": "Feature",
  "properties": {
    "iso:country":"US",
    "sg:address":"800 Garden Hwy",
    "sg:city":"Yuba City",
    "sg:classifiers":[
        {
            "category":"Shopping",
            "subcategory":"Used Merchandise",
            "type":"Retail Goods"
        },
        {
            "category":"Wholesale",
            "subcategory":"Auto Parts",
            "type":"Manufacturing & Wholesale Goods"
        }
    ],
    "sg:phone":"+1 530 674 7721",
    "sg:postcode":"95991",
    "sg:province":"CA",
    "sg:tags":[
        "a",
        "automobile",
        "supply"
    ],
    "wof:name":"A C Auto Dismantling",
    "wof:placetype":"venue"
},
  "geometry": {"coordinates":[-121.61732499999999,39.113281],"type":"Point"}
}