{
  "type": "Feature",
  "properties": {
    "iso:country":"US",
    "sg:address":"840 S Meridian Rd",
    "sg:city":"Meridian",
    "sg:classifiers":[
        {
            "category":"Home & Garden",
            "subcategory":"Building Materials",
            "type":"Retail Goods"
        }
    ],
    "sg:phone":"+1 530 682 7679",
    "sg:postcode":"95957",
    "sg:province":"CA",
    "wof:name":"Duffey Property Chris Management",
    "wof:placetype":"venue"
},
  "geometry": {"coordinates":[-121.90719,39.119413],"type":"Point"}
}