{
  "type": "Feature",
  "properties": {
    "iso:country":"US",
    "sg:address":"2917 Santa Monica Blvd",
    "sg:city":"Santa Monica",
    "sg:classifiers":[
        {
            "category":"Shopping",
            "type":"Retail Goods"
        }
    ],
    "sg:phone":"+1 310 828 5031",
    "sg:postcode":"90404",
    "sg:province":"CA",
    "sg:tags":[
        "merchandise"
    ],
    "wof:name":"Tor Two Gallery",
    "wof:placetype":"venue"
},
  "geometry": {"coordinates":[-118.470705,34.03628],"type":"Point"}
}