{
  "type": "Feature",
  "properties": {
    "addr:full":"3009 1/2 C St Sacramento CA 95816",
    "addr:housenumber":"3009 1 / 2",
    "addr:postcode":"95816",
    "addr:street":"C St",
    "iso:country":"US",
    "sg:address":"3009 1/2 C St",
    "sg:city":"Sacramento",
    "sg:classifiers":[
        {
            "category":"Building & Trades",
            "subcategory":"Landscaping Services",
            "type":"Services"
        }
    ],
    "sg:phone":"+1 916 443 5500",
    "sg:postcode":"95816",
    "sg:province":"CA",
    "sg:tags":[
        "gardener"
    ],
    "sg:website":"www.davey.com",
    "wof:name":"Davey Tree & Shrub Care Experts",
    "wof:placetype":"venue"
},
  "geometry": {"coordinates":[-121.462507,38.58058],"type":"Point"}
}