{
  "type": "Feature",
  "properties": {
    "iso:country":"US",
    "sg:address":"18462 Beach Blvd",
    "sg:city":"Huntington Beach",
    "sg:classifiers":[
        {
            "category":"Restaurant",
            "type":"Food & Drink"
        }
    ],
    "sg:menulink":"http://www.allmenus.com/ca/north-coast/178686-jack-in-the-box/menu/",
    "sg:phone":"+1 714 841 2325",
    "sg:postcode":"92648",
    "sg:province":"CA",
    "sg:tags":[
        "burger",
        "american"
    ],
    "wof:name":"Jack in the Box",
    "wof:placetype":"venue"
},
  "geometry": {"coordinates":[-117.98850299999999,33.694259],"type":"Point"}
}