{
  "type": "Feature",
  "properties": {
    "addr:full":"529 Seabright Avenue Santa Cruz CA 95062",
    "addr:housenumber":"529",
    "addr:postcode":"95062",
    "addr:street":"Seabright Avenue",
    "iso:country":"US",
    "sg:address":"529 Seabright Avenue",
    "sg:city":"Santa Cruz",
    "sg:classifiers":[
        {
            "category":"Bars & Pubs",
            "subcategory":"Nightclub",
            "type":"Food & Drink"
        }
    ],
    "sg:phone":"+1 831 425 2900",
    "sg:postcode":"95062",
    "sg:province":"CA",
    "sg:tags":[
        "nightlife"
    ],
    "wof:name":"Cardiff Lounge",
    "wof:placetype":"venue"
},
  "geometry": {"coordinates":[-122.00799499999999,36.967811],"type":"Point"}
}