{
  "type": "Feature",
  "properties": {
    "iso:country":"US",
    "sg:address":"417 N Poinsettia Ave",
    "sg:city":"Compton",
    "sg:classifiers":[
        {
            "category":"Social Services",
            "subcategory":"Adult Care",
            "type":"Services"
        }
    ],
    "sg:phone":"+1 310 603 0921",
    "sg:postcode":"90221",
    "sg:province":"CA",
    "sg:tags":[
        "home",
        "residential"
    ],
    "wof:name":"MAP Homes",
    "wof:placetype":"venue"
},
  "geometry": {"coordinates":[-118.209746,33.900653],"type":"Point"}
}