{
  "type": "Feature",
  "properties": {
    "iso:country":"US",
    "sg:address":"19300 Robinson St",
    "sg:city":"Perris",
    "sg:classifiers":[
        {
            "category":"Transit Center",
            "subcategory":"Freight",
            "type":"Transportation"
        },
        {
            "category":"Freight",
            "type":"Transportation"
        }
    ],
    "sg:phone":"+1 951 722 4956",
    "sg:postcode":"92570",
    "sg:province":"CA",
    "sg:tags":[
        "local",
        "trucking-motor",
        "trucking"
    ],
    "wof:name":"Jose Maya",
    "wof:placetype":"venue"
},
  "geometry": {"coordinates":[-117.28183,33.83969],"type":"Point"}
}