{
  "type": "Feature",
  "properties": {
    "iso:country":"US",
    "sg:address":"1310 67th St",
    "sg:city":"Emeryville",
    "sg:classifiers":[
        {
            "category":"Restaurant",
            "type":"Food & Drink"
        }
    ],
    "sg:phone":"+1 510 595 4305",
    "sg:postcode":"94608",
    "sg:province":"CA",
    "sg:tags":[
        "delivery"
    ],
    "wof:name":"Cosmo Catering",
    "wof:placetype":"venue"
},
  "geometry": {"coordinates":[-122.29105199999999,37.849202],"type":"Point"}
}