{
  "type": "Feature",
  "properties": {
    "iso:country":"US",
    "sg:address":"6452 Rhea Ave",
    "sg:city":"Reseda",
    "sg:classifiers":[
        {
            "category":"Professional",
            "type":"Services"
        }
    ],
    "sg:phone":"+1 818 342 2790",
    "sg:postcode":"91335",
    "sg:province":"CA",
    "wof:name":"Seven Hearts Inc",
    "wof:placetype":"venue"
},
  "geometry": {"coordinates":[-118.541202,34.188752],"type":"Point"}
}