{
  "type": "Feature",
  "properties": {
    "iso:country":"US",
    "sg:address":"13 Lemon Hill Dr",
    "sg:city":"Oroville",
    "sg:classifiers":[
        {
            "category":"Real Estate",
            "subcategory":"Real Estate Agent",
            "type":"Services"
        }
    ],
    "sg:phone":"+1 530 533 5678",
    "sg:postcode":"95966",
    "sg:province":"CA",
    "sg:tags":[
        "appraiser"
    ],
    "wof:name":"2artier Insurance Svc",
    "wof:placetype":"venue"
},
  "geometry": {"coordinates":[-121.51837500000001,39.524107],"type":"Point"}
}