{
  "type": "Feature",
  "properties": {
    "iso:country":"US",
    "sg:address":"446 Southgate Ct",
    "sg:city":"Chico",
    "sg:classifiers":[
        {
            "category":"Farming",
            "subcategory":"Nursery",
            "type":"Manufacturing & Wholesale Goods"
        }
    ],
    "sg:phone":"+1 530 893 4718",
    "sg:postcode":"95928",
    "sg:province":"CA",
    "sg:tags":[
        "production",
        "seed"
    ],
    "wof:name":"Vaccaro Seed California Inc",
    "wof:placetype":"venue"
},
  "geometry": {"coordinates":[-121.780874,39.698519],"type":"Point"}
}