{
  "type": "Feature",
  "properties": {
    "addr:full":"300 S el Camino Real San Clemente CA 92672",
    "addr:housenumber":"300",
    "addr:postcode":"92672",
    "addr:street":"S El Camino Real",
    "iso:country":"US",
    "sg:address":"300 S el Camino Real",
    "sg:city":"San Clemente",
    "sg:classifiers":[
        {
            "category":"Professional",
            "type":"Services"
        }
    ],
    "sg:phone":"+1 949 369 4961",
    "sg:postcode":"92672",
    "sg:province":"CA",
    "wof:name":"Sohocollege Co",
    "wof:placetype":"venue"
},
  "geometry": {"coordinates":[-117.61127,33.426139],"type":"Point"}
}