{
  "type": "Feature",
  "properties": {
    "iso:country":"US",
    "sg:address":"1724 N Tustin Ave",
    "sg:city":"Orange",
    "sg:classifiers":[
        {
            "category":"Restaurant",
            "type":"Food & Drink"
        }
    ],
    "sg:phone":"+1 714 637 8226",
    "sg:postcode":"92865",
    "sg:province":"CA",
    "sg:tags":[
        "mexican"
    ],
    "wof:name":"O.C. Taco Joint",
    "wof:placetype":"venue"
},
  "geometry": {"coordinates":[-117.835967,33.816661],"type":"Point"}
}