{
  "type": "Feature",
  "properties": {
    "addr:full":"3124 W Rosecrans Ave Hawthorne CA 90250",
    "addr:housenumber":"3124",
    "addr:postcode":"90250",
    "addr:street":"W Rosecrans Ave",
    "iso:country":"US",
    "sg:address":"3124 W Rosecrans Ave",
    "sg:city":"Hawthorne",
    "sg:classifiers":[
        {
            "category":"Autos & Motor Vehicles",
            "subcategory":"Automobile Sales",
            "type":"Retail Goods"
        }
    ],
    "sg:phone":"+1 310 973 8828",
    "sg:postcode":"90250",
    "sg:province":"CA",
    "sg:tags":[
        "used"
    ],
    "wof:name":"Ace Auto Sales",
    "wof:placetype":"venue"
},
  "geometry": {"coordinates":[-118.328214,33.901856],"type":"Point"}
}