{
  "type": "Feature",
  "properties": {
    "addr:full":"1015 N Gower St Los Angeles CA 90038",
    "addr:housenumber":"1015",
    "addr:postcode":"90038",
    "addr:street":"N Gower St",
    "iso:country":"US",
    "sg:address":"1015 N Gower St",
    "sg:city":"Los Angeles",
    "sg:classifiers":[
        {
            "category":"Building & Trades",
            "subcategory":"Construction",
            "type":"Services"
        }
    ],
    "sg:phone":"+1 323 469 2981",
    "sg:postcode":"90038",
    "sg:province":"CA",
    "sg:tags":[
        "roofing",
        "contractor"
    ],
    "wof:name":"Supreme Roofing Co Inc",
    "wof:placetype":"venue"
},
  "geometry": {"coordinates":[-118.322344,34.089578],"type":"Point"}
}