{
  "type": "Feature",
  "properties": {
    "addr:full":"2044 Pine Hurst Ln Hawthorne CA 90250",
    "addr:housenumber":"2044",
    "addr:postcode":"90250",
    "addr:street":"Pine Hurst Ln",
    "iso:country":"US",
    "sg:address":"2044 Pine Hurst Ln",
    "sg:city":"Hawthorne",
    "sg:classifiers":[
        {
            "category":"Personal",
            "type":"Services"
        },
        {
            "category":"Retail",
            "subcategory":"Auto Repair",
            "type":"Services"
        }
    ],
    "sg:phone":"+1 800 974 4439",
    "sg:postcode":"90250",
    "sg:province":"CA",
    "sg:tags":[
        "body",
        "automobile",
        "dent",
        "towing",
        "removal",
        "painting",
        "repairing"
    ],
    "wof:name":"A Westside Road Service",
    "wof:placetype":"venue"
},
  "geometry": {"coordinates":[-118.31519,33.917649],"type":"Point"}
}