{
  "type": "Feature",
  "properties": {
    "addr:full":"1320 Commerce St Petaluma CA 94954",
    "addr:housenumber":"1320",
    "addr:postcode":"94954",
    "addr:street":"Commerce St",
    "iso:country":"US",
    "sg:address":"1320 Commerce St",
    "sg:city":"Petaluma",
    "sg:classifiers":[
        {
            "category":"Manufacturing",
            "subcategory":"Printing",
            "type":"Manufacturing & Wholesale Goods"
        }
    ],
    "sg:phone":"+1 707 775 4700",
    "sg:postcode":"94954",
    "sg:province":"CA",
    "sg:tags":[
        "commercial"
    ],
    "wof:name":"AC Label Company",
    "wof:placetype":"venue"
},
  "geometry": {"coordinates":[-122.641957,38.255978],"type":"Point"}
}