{
  "type": "Feature",
  "properties": {
    "addr:full":"918 S Bascom Ave San Jose CA 95128",
    "addr:housenumber":"918",
    "addr:postcode":"95128",
    "addr:street":"S Bascom Ave",
    "iso:country":"US",
    "sg:address":"918 S Bascom Ave",
    "sg:city":"San Jose",
    "sg:classifiers":[
        {
            "category":"Food & Beverages",
            "subcategory":"Specialty",
            "type":"Retail Goods"
        }
    ],
    "sg:phone":"+1 408 293 1330",
    "sg:postcode":"95128",
    "sg:province":"CA",
    "sg:tags":[
        "water",
        "bulk",
        "company"
    ],
    "wof:name":"Modern Pure Water",
    "wof:placetype":"venue"
},
  "geometry": {"coordinates":[-121.931708,37.309797],"type":"Point"}
}