{
  "type": "Feature",
  "properties": {
    "iso:country":"US",
    "sg:address":"6000 Shepherd Canyon Road",
    "sg:city":"Oakland",
    "sg:classifiers":[
        {
            "category":"Recreation",
            "type":"Entertainment"
        }
    ],
    "sg:postcode":"94611",
    "sg:province":"CA",
    "sg:tags":[
        "active",
        "life"
    ],
    "wof:name":"Montclair Railroad Trail",
    "wof:placetype":"venue"
},
  "geometry": {"coordinates":[-122.202558,37.82538],"type":"Point"}
}