{
  "type": "Feature",
  "properties": {
    "iso:country":"US",
    "sg:address":"7523 Fairmount Ave",
    "sg:city":"El Cerrito",
    "sg:classifiers":[
        {
            "category":"Shopping",
            "subcategory":"Pets & Pet Supplies",
            "type":"Retail Goods"
        }
    ],
    "sg:phone":"+1 510 356 4233",
    "sg:postcode":"94530",
    "sg:province":"CA",
    "sg:tags":[
        "store"
    ],
    "sg:website":"www.rabbitears.org",
    "wof:name":"RabbitEARS Pet Supply",
    "wof:placetype":"venue"
},
  "geometry": {"coordinates":[-122.291884,37.904105],"type":"Point"}
}