{
  "type": "Feature",
  "properties": {
    "addr:full":"3407 W 6th St Los Angeles CA 90020",
    "addr:housenumber":"3407",
    "addr:postcode":"90020",
    "addr:street":"W 6Th St",
    "iso:country":"US",
    "sg:address":"3407 W 6th St",
    "sg:city":"Los Angeles",
    "sg:classifiers":[
        {
            "category":"Manufacturing",
            "subcategory":"Printing",
            "type":"Manufacturing & Wholesale Goods"
        }
    ],
    "sg:phone":"+1 213 738 7406",
    "sg:postcode":"90020",
    "sg:province":"CA",
    "sg:tags":[
        "printer"
    ],
    "sg:website":"www.columbiaprinting.net",
    "wof:name":"Columbia Printing Inc",
    "wof:placetype":"venue"
},
  "geometry": {"coordinates":[-118.29650599999999,34.063665],"type":"Point"}
}