{
  "type": "Feature",
  "properties": {
    "addr:full":"1511 Rialto St Oxnard CA 93035",
    "addr:housenumber":"1511",
    "addr:postcode":"93035",
    "addr:street":"Rialto St",
    "iso:country":"US",
    "sg:address":"1511 Rialto St",
    "sg:city":"Oxnard",
    "sg:classifiers":[
        {
            "category":"Building & Trades",
            "subcategory":"Construction",
            "type":"Services"
        }
    ],
    "sg:phone":"+1 805 984 2122",
    "sg:postcode":"93035",
    "sg:province":"CA",
    "sg:tags":[
        "concrete",
        "contractor"
    ],
    "wof:name":"Randy Diaz & Sons Const Masnry",
    "wof:placetype":"venue"
},
  "geometry": {"coordinates":[-119.19779699999999,34.184634],"type":"Point"}
}