{
  "type": "Feature",
  "properties": {
    "iso:country":"US",
    "sg:address":"521 W Rosecrans Ave",
    "sg:city":"Gardena",
    "sg:classifiers":[
        {
            "category":"Wholesale",
            "subcategory":"Durable Goods & Equipment",
            "type":"Manufacturing & Wholesale Goods"
        }
    ],
    "sg:phone":"+1 310 539 0232",
    "sg:postcode":"90248",
    "sg:province":"CA",
    "sg:tags":[
        "ear",
        "piercing",
        "supply"
    ],
    "sg:website":"www.studex.com",
    "wof:name":"Studex Corp",
    "wof:placetype":"venue"
},
  "geometry": {"coordinates":[-118.28401100000001,33.901969],"type":"Point"}
}