{
  "type": "Feature",
  "properties": {
    "addr:full":"3978 W 6th St Los Angeles CA 90020",
    "addr:housenumber":"3978",
    "addr:postcode":"90020",
    "addr:street":"W 6Th St",
    "iso:country":"US",
    "sg:address":"3978 W 6th St",
    "sg:city":"Los Angeles",
    "sg:classifiers":[
        {
            "category":"Retail",
            "subcategory":"Portrait Studio",
            "type":"Services"
        }
    ],
    "sg:phone":"+1 213 738 1904",
    "sg:postcode":"90020",
    "sg:province":"CA",
    "sg:tags":[
        "photographer"
    ],
    "wof:name":"A Authorized Passport",
    "wof:placetype":"venue"
},
  "geometry": {"coordinates":[-118.30972,34.063441],"type":"Point"}
}