{
  "type": "Feature",
  "properties": {
    "addr:full":"2139 Sinclair St Pomona CA 91767",
    "addr:housenumber":"2139",
    "addr:postcode":"91767",
    "addr:street":"Sinclair St",
    "iso:country":"US",
    "sg:address":"2139 Sinclair St",
    "sg:city":"Pomona",
    "sg:classifiers":[
        {
            "category":"Organizations",
            "subcategory":"Professional Association",
            "type":"Services"
        }
    ],
    "sg:phone":"+1 909 620 7170",
    "sg:postcode":"91767",
    "sg:province":"CA",
    "wof:name":"Simba",
    "wof:placetype":"venue"
},
  "geometry": {"coordinates":[-117.74314,34.08374],"type":"Point"}
}