{
  "type": "Feature",
  "properties": {
    "addr:full":"1656 W 9th St Upland CA 91786",
    "addr:housenumber":"1656",
    "addr:postcode":"91786",
    "addr:street":"W 9Th St",
    "iso:country":"US",
    "sg:address":"1656 W 9th St",
    "sg:city":"Upland",
    "sg:classifiers":[
        {
            "category":"Retail",
            "subcategory":"Auto Repair",
            "type":"Services"
        },
        {
            "category":"Manufacturing",
            "subcategory":"Motor Vehicles & Parts",
            "type":"Manufacturing & Wholesale Goods"
        }
    ],
    "sg:phone":"+1 909 579 0750",
    "sg:postcode":"91786",
    "sg:province":"CA",
    "sg:tags":[
        "motorcycle",
        "mfg"
    ],
    "wof:name":"Cycleworks",
    "wof:placetype":"venue"
},
  "geometry": {"coordinates":[-117.682085,34.095838],"type":"Point"}
}