{
  "type": "Feature",
  "properties": {
    "addr:full":"2325 W Main St Visalia CA 93291",
    "addr:housenumber":"2325",
    "addr:postcode":"93291",
    "addr:street":"W Main St",
    "iso:country":"US",
    "sg:address":"2325 W Main St",
    "sg:city":"Visalia",
    "sg:classifiers":[
        {
            "category":"Government",
            "subcategory":"Office",
            "type":"Public Place"
        }
    ],
    "sg:phone":"+1 559 733 6013",
    "sg:postcode":"93291",
    "sg:province":"CA",
    "sg:tags":[
        "management"
    ],
    "wof:name":"Environmnt Health Visalia",
    "wof:placetype":"venue"
},
  "geometry": {"coordinates":[-119.318288,36.329543],"type":"Point"}
}