{
  "type": "Feature",
  "properties": {
    "addr:full":"8824 International Blvd Oakland CA 94621",
    "addr:housenumber":"8824",
    "addr:postcode":"94621",
    "addr:street":"International Blvd",
    "iso:country":"US",
    "sg:address":"8824 International Blvd",
    "sg:city":"Oakland",
    "sg:classifiers":[
        {
            "category":"Banks & Credit Unions",
            "subcategory":"Bank",
            "type":"Services"
        }
    ],
    "sg:phone":"+1 510 633 3048",
    "sg:postcode":"94621",
    "sg:province":"CA",
    "sg:tags":[
        "money",
        "order",
        "store",
        "variety"
    ],
    "sg:website":"http://www.dollar.com",
    "wof:name":"Dolex Dollar Express",
    "wof:placetype":"venue"
},
  "geometry": {"coordinates":[-122.175189,37.750813],"type":"Point"}
}