{
  "type": "Feature",
  "properties": {
    "addr:full":"6333 Woodman Ave Van Nuys CA 91401",
    "addr:housenumber":"6333",
    "addr:postcode":"91401",
    "addr:street":"Woodman Ave",
    "iso:country":"US",
    "sg:address":"6333 Woodman Ave",
    "sg:city":"Van Nuys",
    "sg:classifiers":[
        {
            "category":"Professional",
            "type":"Services"
        }
    ],
    "sg:phone":"+1 818 997 9243",
    "sg:postcode":"91401",
    "sg:province":"CA",
    "wof:name":"Joselyn Transportes",
    "wof:placetype":"venue"
},
  "geometry": {"coordinates":[-118.43132300000001,34.185133],"type":"Point"}
}