{
  "type": "Feature",
  "properties": {
    "iso:country":"US",
    "sg:address":"686 N Creekview Dr",
    "sg:city":"Orange",
    "sg:classifiers":[
        {
            "category":"Real Estate",
            "subcategory":"Architect",
            "type":"Services"
        }
    ],
    "sg:phone":"+1 714 538 2836",
    "sg:postcode":"92869",
    "sg:province":"CA",
    "sg:tags":[
        "residential",
        "designer"
    ],
    "wof:name":"Larry Willis",
    "wof:placetype":"venue"
},
  "geometry": {"coordinates":[-117.779454,33.799667],"type":"Point"}
}