{
  "type": "Feature",
  "properties": {
    "iso:country":"US",
    "sg:address":"5468 Bellevue Cir",
    "sg:city":"Dublin",
    "sg:classifiers":[
        {
            "category":"Farming",
            "subcategory":"Livestock Farm",
            "type":"Manufacturing & Wholesale Goods"
        }
    ],
    "sg:phone":"+1 925 829 7698",
    "sg:postcode":"94568",
    "sg:province":"CA",
    "sg:tags":[
        "ranch"
    ],
    "wof:name":"Dublin Ranch By Std Pacific Hm",
    "wof:placetype":"venue"
},
  "geometry": {"coordinates":[-121.87088,37.717254],"type":"Point"}
}