{
  "type": "Feature",
  "properties": {
    "iso:country":"US",
    "sg:address":"200 Healy Ave",
    "sg:city":"Marina",
    "sg:classifiers":[
        {
            "category":"Food & Beverages",
            "subcategory":"Dairy",
            "type":"Retail Goods"
        }
    ],
    "sg:phone":"+1 831 384 0164",
    "sg:postcode":"93933",
    "sg:province":"CA",
    "sg:tags":[
        "product"
    ],
    "wof:name":"Challenge Dairy Prods Inc",
    "wof:placetype":"venue"
},
  "geometry": {"coordinates":[-121.79651800000001,36.698382],"type":"Point"}
}