{
  "type": "Feature",
  "properties": {
    "addr:full":"17301 Beach Blvd Huntington Beach CA 92647",
    "addr:housenumber":"17301",
    "addr:postcode":"92647",
    "addr:street":"Beach Blvd",
    "iso:country":"US",
    "sg:address":"17301 Beach Blvd",
    "sg:city":"Huntington Beach",
    "sg:classifiers":[
        {
            "category":"Autos & Motor Vehicles",
            "subcategory":"Automobile Sales",
            "type":"Retail Goods"
        }
    ],
    "sg:phone":"+1 714 916 0570",
    "sg:postcode":"92647",
    "sg:province":"CA",
    "sg:tags":[
        "car"
    ],
    "sg:website":"MBZ4LESS.com",
    "wof:name":"MBZ 4 LESS",
    "wof:placetype":"venue"
},
  "geometry": {"coordinates":[-117.989754,33.711143],"type":"Point"}
}