{
  "type": "Feature",
  "properties": {
    "iso:country":"US",
    "sg:address":"555 University Ave",
    "sg:city":"Sacramento",
    "sg:classifiers":[
        {
            "category":"Professional",
            "subcategory":"Accounting & Tax Preparation",
            "type":"Services"
        }
    ],
    "sg:phone":"+1 916 922 9398",
    "sg:postcode":"95825",
    "sg:province":"CA",
    "sg:tags":[
        "accountant"
    ],
    "wof:name":"John Olekszulin CPA",
    "wof:placetype":"venue"
},
  "geometry": {"coordinates":[-121.419279,38.565262],"type":"Point"}
}