{
  "type": "Feature",
  "properties": {
    "iso:country":"US",
    "sg:address":"1024 Freedom Blvd",
    "sg:city":"Watsonville",
    "sg:classifiers":[
        {
            "category":"Manufacturing",
            "subcategory":"Printing",
            "type":"Manufacturing & Wholesale Goods"
        }
    ],
    "sg:phone":"+1 831 763 1000",
    "sg:postcode":"95076",
    "sg:province":"CA",
    "sg:tags":[
        "commercial"
    ],
    "wof:name":"T-Shirts",
    "wof:placetype":"venue"
},
  "geometry": {"coordinates":[-121.761195,36.921913],"type":"Point"}
}