{
  "type": "Feature",
  "properties": {
    "iso:country":"US",
    "sg:address":"8871 Fanita Dr",
    "sg:city":"Santee",
    "sg:classifiers":[
        {
            "category":"Retail",
            "subcategory":"Auto Repair",
            "type":"Services"
        }
    ],
    "sg:phone":"+1 619 258 1566",
    "sg:postcode":"92071",
    "sg:province":"CA",
    "sg:tags":[
        "repairing",
        "automobile"
    ],
    "wof:name":"Ban's Auto Repair",
    "wof:placetype":"venue"
},
  "geometry": {"coordinates":[-117.00066700000001,32.838051],"type":"Point"}
}