{
  "type": "Feature",
  "properties": {
    "addr:full":"10500 Flora Vista Street Bellflower CA 90706",
    "addr:housenumber":"10500",
    "addr:postcode":"90706",
    "addr:street":"Flora Vista Street",
    "iso:country":"US",
    "sg:address":"10500 Flora Vista Street",
    "sg:city":"Bellflower",
    "sg:classifiers":[
        {
            "category":"Park",
            "type":"Public Place"
        }
    ],
    "sg:phone":"+1 562 866 5684",
    "sg:postcode":"90706",
    "sg:province":"CA",
    "sg:website":"bellflower.org",
    "wof:name":"Ruth R. Caruthers Park",
    "wof:placetype":"venue"
},
  "geometry": {"coordinates":[-118.110088,33.878823],"type":"Point"}
}