{
  "type": "Feature",
  "properties": {
    "addr:full":"24301 Southland Dr Hayward CA 94545",
    "addr:housenumber":"24301",
    "addr:postcode":"94545",
    "addr:street":"Southland Dr",
    "iso:country":"US",
    "sg:address":"24301 Southland Dr",
    "sg:city":"Hayward",
    "sg:classifiers":[
        {
            "category":"Manufacturing",
            "subcategory":"Chemicals & Compounds",
            "type":"Manufacturing & Wholesale Goods"
        }
    ],
    "sg:phone":"+1 510 887 0555",
    "sg:postcode":"94545",
    "sg:province":"CA",
    "sg:tags":[
        "mfg"
    ],
    "wof:name":"Matthew P Duran",
    "wof:placetype":"venue"
},
  "geometry": {"coordinates":[-122.10513400000001,37.654247],"type":"Point"}
}