{
  "type": "Feature",
  "properties": {
    "iso:country":"US",
    "sg:address":"6245 Bristol Pkwy Ste 137",
    "sg:city":"Culver City",
    "sg:classifiers":[
        {
            "category":"Personal",
            "type":"Services"
        },
        {
            "category":"Professional",
            "subcategory":"Employment Agencies",
            "type":"Services"
        }
    ],
    "sg:phone":"+1 310 281 9795",
    "sg:postcode":"90230",
    "sg:province":"CA",
    "sg:tags":[
        "party",
        "planning",
        "event"
    ],
    "sg:website":"www.customstaffing2007.com",
    "wof:name":"Custom Staffing",
    "wof:placetype":"venue"
},
  "geometry": {"coordinates":[-118.39132499999999,33.982657],"type":"Point"}
}