{
  "type": "Feature",
  "properties": {
    "iso:country":"US",
    "sg:address":"275 Olympia Way",
    "sg:city":"San Francisco",
    "sg:classifiers":[
        {
            "category":"Organizations",
            "subcategory":"Religious Organization",
            "type":"Services"
        }
    ],
    "sg:phone":"+1 415 661 1142",
    "sg:postcode":"94131",
    "sg:province":"CA",
    "sg:tags":[
        "church"
    ],
    "sg:website":"www.sjarmenianchurch.org",
    "wof:name":"Armenian Apostolic Church",
    "wof:placetype":"venue"
},
  "geometry": {"coordinates":[-122.454971,37.751259],"type":"Point"}
}