{
  "type": "Feature",
  "properties": {
    "addr:full":"16760 Stagg St Van Nuys CA 91406",
    "addr:postcode":"16760;91406",
    "addr:street":"Stagg St",
    "iso:country":"US",
    "sg:address":"16760 Stagg St",
    "sg:city":"Van Nuys",
    "sg:classifiers":[
        {
            "category":"Arts & Performance",
            "subcategory":"Theater",
            "type":"Entertainment"
        }
    ],
    "sg:phone":"+1 818 786 4436",
    "sg:postcode":"91406",
    "sg:province":"CA",
    "sg:tags":[
        "equipment",
        "theatrical",
        "supply"
    ],
    "wof:name":"Halgo Specialties Co",
    "wof:placetype":"venue"
},
  "geometry": {"coordinates":[-118.49728500000001,34.213081],"type":"Point"}
}