{
  "type": "Feature",
  "properties": {
    "iso:country":"US",
    "sg:address":"611 S Catalina St",
    "sg:city":"Los Angeles",
    "sg:classifiers":[
        {
            "category":"Real Estate",
            "subcategory":"Real Estate Agent",
            "type":"Services"
        }
    ],
    "sg:phone":"+1 213 389 8694",
    "sg:postcode":"90005",
    "sg:province":"CA",
    "wof:name":"United Investment & Mortgage",
    "wof:placetype":"venue"
},
  "geometry": {"coordinates":[-118.29543700000001,34.062745],"type":"Point"}
}