{
  "type": "Feature",
  "properties": {
    "addr:full":"38 Nichols Ln Morgan Hill CA 95037",
    "addr:housenumber":"38",
    "addr:postcode":"95037",
    "addr:street":"Nichols Ln",
    "iso:country":"US",
    "sg:address":"38 Nichols Ln",
    "sg:city":"Morgan Hill",
    "sg:classifiers":[
        {
            "category":"Freight",
            "type":"Transportation"
        }
    ],
    "sg:phone":"+1 408 264 3170",
    "sg:postcode":"95037",
    "sg:province":"CA",
    "sg:tags":[
        "trucking"
    ],
    "wof:name":"Azzarello's Truck-N-Hoe",
    "wof:placetype":"venue"
},
  "geometry": {"coordinates":[-121.675257,37.165113],"type":"Point"}
}