{
  "type": "Feature",
  "properties": {
    "addr:full":"175 Robley Rd Salinas CA 93908",
    "addr:housenumber":"175",
    "addr:postcode":"93908",
    "addr:street":"Robley Rd",
    "iso:country":"US",
    "sg:address":"175 Robley Rd",
    "sg:city":"Salinas",
    "sg:classifiers":[
        {
            "category":"Freight",
            "type":"Transportation"
        }
    ],
    "sg:phone":"+1 831 484 2570",
    "sg:postcode":"93908",
    "sg:province":"CA",
    "sg:tags":[
        "operator",
        "local",
        "trucking"
    ],
    "wof:name":"John Pitta Trucking",
    "wof:placetype":"venue"
},
  "geometry": {"coordinates":[-121.74734100000001,36.55399],"type":"Point"}
}