{
  "type": "Feature",
  "properties": {
    "iso:country":"US",
    "sg:address":"930 Merchant St",
    "sg:city":"Redding",
    "sg:classifiers":[
        {
            "category":"Autos & Motor Vehicles",
            "subcategory":"Auto Supplies",
            "type":"Retail Goods"
        }
    ],
    "sg:phone":"+1 530 221 3980",
    "sg:postcode":"96002",
    "sg:province":"CA",
    "sg:tags":[
        "automobile",
        "accessory"
    ],
    "wof:name":"Auto Accessories Company",
    "wof:placetype":"venue"
},
  "geometry": {"coordinates":[-122.354688,40.573479],"type":"Point"}
}