{
  "type": "Feature",
  "properties": {
    "iso:country":"US",
    "sg:address":"2866 W Olympic Blvd",
    "sg:city":"Los Angeles",
    "sg:classifiers":[
        {
            "category":"Local Transit",
            "type":"Transportation"
        }
    ],
    "sg:phone":"+1 213 387 6800",
    "sg:postcode":"90006",
    "sg:province":"CA",
    "sg:tags":[
        "passenger"
    ],
    "wof:name":"CA Hanmi Limo and Tour Co",
    "wof:placetype":"venue"
},
  "geometry": {"coordinates":[-118.29622999999999,34.052568],"type":"Point"}
}