{
  "type": "Feature",
  "properties": {
    "iso:country":"US",
    "sg:address":"1201 W 5th St",
    "sg:city":"Los Angeles",
    "sg:classifiers":[
        {
            "category":"Cinema",
            "subcategory":"Movie Rental",
            "type":"Entertainment"
        }
    ],
    "sg:phone":"+1 213 534 3775",
    "sg:postcode":"90017",
    "sg:province":"CA",
    "sg:tags":[
        "leasing",
        "video",
        "disc",
        "tape"
    ],
    "wof:name":"Picture Car Warehouse",
    "wof:placetype":"venue"
},
  "geometry": {"coordinates":[-118.261429,34.054907],"type":"Point"}
}