{
  "type": "Feature",
  "properties": {
    "addr:full":"3440 W Warner Ave Santa Ana CA 92704",
    "addr:housenumber":"3440",
    "addr:postcode":"92704",
    "addr:street":"W Warner Ave",
    "iso:country":"US",
    "sg:address":"3440 W Warner Ave",
    "sg:city":"Santa Ana",
    "sg:classifiers":[
        {
            "category":"Wholesale",
            "subcategory":"Chemicals & Plastics",
            "type":"Manufacturing & Wholesale Goods"
        }
    ],
    "sg:phone":"+1 714 437 7770",
    "sg:postcode":"92704",
    "sg:province":"CA",
    "wof:name":"Pulmonaire",
    "wof:placetype":"venue"
},
  "geometry": {"coordinates":[-117.915271,33.713924],"type":"Point"}
}