{
  "type": "Feature",
  "properties": {
    "iso:country":"US",
    "sg:address":"929 Silverado St",
    "sg:city":"La Jolla",
    "sg:classifiers":[
        {
            "category":"Personal",
            "subcategory":"Shoe Repair & Shine",
            "type":"Services"
        }
    ],
    "sg:phone":"+1 858 454 0806",
    "sg:postcode":"92037",
    "sg:province":"CA",
    "wof:name":"Cinderella Shoe Clinic",
    "wof:placetype":"venue"
},
  "geometry": {"coordinates":[-117.275002,32.845001],"type":"Point"}
}