{
  "type": "Feature",
  "properties": {
    "iso:country":"US",
    "sg:address":"11947 Paramount Blvd",
    "sg:city":"Downey",
    "sg:classifiers":[
        {
            "category":"Shopping",
            "subcategory":"Bicycles & Sporting Goods",
            "type":"Retail Goods"
        }
    ],
    "sg:phone":"+1 562 869 5245",
    "sg:postcode":"90242",
    "sg:province":"CA",
    "sg:tags":[
        "equipment",
        "skateboard"
    ],
    "wof:name":"Downey Skate",
    "wof:placetype":"venue"
},
  "geometry": {"coordinates":[-118.144355,33.934162],"type":"Point"}
}