{
  "type": "Feature",
  "properties": {
    "addr:full":"219 Mount Hermon Rd Ste A2 Scotts Valley CA 95066",
    "addr:housenumber":"219",
    "addr:postcode":"95066",
    "addr:street":"Mount Hermon Rd Ste A2",
    "iso:country":"US",
    "sg:address":"219 Mount Hermon Rd Ste A2",
    "sg:city":"Scotts Valley",
    "sg:classifiers":[
        {
            "category":"Restaurant",
            "type":"Food & Drink"
        }
    ],
    "sg:phone":"+1 831 438 3406",
    "sg:postcode":"95066",
    "sg:province":"CA",
    "sg:tags":[
        "chinese"
    ],
    "wof:name":"ABC Chinese Restaurant",
    "wof:placetype":"venue"
},
  "geometry": {"coordinates":[-122.02600099999999,37.044201],"type":"Point"}
}