{
  "type": "Feature",
  "properties": {
    "iso:country":"US",
    "sg:address":"20111 Roscoe Blvd",
    "sg:city":"Winnetka",
    "sg:classifiers":[
        {
            "category":"Personal",
            "subcategory":"Nail Salon",
            "type":"Services"
        }
    ],
    "sg:phone":"+1 818 998 6999",
    "sg:postcode":"91306",
    "sg:province":"CA",
    "wof:name":"Violet Nails",
    "wof:placetype":"venue"
},
  "geometry": {"coordinates":[-118.570999,34.2201],"type":"Point"}
}