{
  "type": "Feature",
  "properties": {
    "addr:full":"40912 Rd 56 Reedley CA 93654",
    "addr:postcode":"40912;93654",
    "addr:street":"Rd 56",
    "iso:country":"US",
    "sg:address":"40912 Rd 56",
    "sg:city":"Reedley",
    "sg:classifiers":[
        {
            "category":"Real Estate",
            "subcategory":"Real Estate Agent",
            "type":"Services"
        }
    ],
    "sg:phone":"+1 559 638 5388",
    "sg:postcode":"93654",
    "sg:province":"CA",
    "sg:tags":[
        "appraiser"
    ],
    "wof:name":"Just Co Real Estate",
    "wof:placetype":"venue"
},
  "geometry": {"coordinates":[-119.448542,36.54425],"type":"Point"}
}