{
  "type": "Feature",
  "properties": {
    "iso:country":"US",
    "sg:address":"1215 W Laurel Ave",
    "sg:city":"Lompoc",
    "sg:classifiers":[
        {
            "category":"Manufacturing",
            "subcategory":"Retail Goods",
            "type":"Manufacturing & Wholesale Goods"
        }
    ],
    "sg:phone":"+1 805 735 6156",
    "sg:postcode":"93436",
    "sg:province":"CA",
    "sg:tags":[
        "manufacturer"
    ],
    "wof:name":"Southwest Chemical Co",
    "wof:placetype":"venue"
},
  "geometry": {"coordinates":[-120.474019,34.64403],"type":"Point"}
}