{
  "type": "Feature",
  "properties": {
    "iso:country":"US",
    "sg:address":"2388 Market Ave",
    "sg:city":"San Pablo",
    "sg:classifiers":[
        {
            "category":"Food & Beverages",
            "subcategory":"Groceries & Convenience Stores",
            "type":"Retail Goods"
        }
    ],
    "sg:phone":"+1 510 236 8864",
    "sg:postcode":"94806",
    "sg:province":"CA",
    "sg:tags":[
        "grocer"
    ],
    "wof:name":"Mc Kay's Market",
    "wof:placetype":"venue"
},
  "geometry": {"coordinates":[-122.345536,37.956382],"type":"Point"}
}