{
  "type": "Feature",
  "properties": {
    "addr:full":"1798 Mission Street San Francisco CA 94103",
    "addr:housenumber":"1798",
    "addr:postcode":"94103",
    "addr:street":"Mission Street",
    "iso:country":"US",
    "sg:address":"1798 Mission Street",
    "sg:city":"San Francisco",
    "sg:classifiers":[
        {
            "category":"Autos & Motor Vehicles",
            "subcategory":"Fuel & Gas Station",
            "type":"Retail Goods"
        }
    ],
    "sg:phone":"+1 415 437 1947",
    "sg:postcode":"94103",
    "sg:province":"CA",
    "wof:name":"Arco Gas Station",
    "wof:placetype":"venue"
},
  "geometry": {"coordinates":[-122.41999800000001,37.768398],"type":"Point"}
}