{
  "type": "Feature",
  "properties": {
    "iso:country":"US",
    "sg:address":"2907 W Sunset Boulevard",
    "sg:city":"Los Angeles",
    "sg:classifiers":[
        {
            "category":"Health Services",
            "subcategory":"Dentist",
            "type":"Services"
        }
    ],
    "sg:phone":"+1 323 663 2141",
    "sg:postcode":"90026",
    "sg:province":"CA",
    "wof:name":"Nguyen Thien DDS",
    "wof:placetype":"venue"
},
  "geometry": {"coordinates":[-118.27373,34.083151],"type":"Point"}
}