{
  "type": "Feature",
  "properties": {
    "iso:country":"US",
    "sg:address":"18701 Devonshire St",
    "sg:city":"Northridge",
    "sg:classifiers":[
        {
            "category":"Restaurant",
            "type":"Food & Drink"
        }
    ],
    "sg:phone":"+1 818 363 3459",
    "sg:postcode":"91324",
    "sg:province":"CA",
    "sg:tags":[
        "tea",
        "rooms"
    ],
    "wof:name":"Boba City Cafe",
    "wof:placetype":"venue"
},
  "geometry": {"coordinates":[-118.537388,34.257341],"type":"Point"}
}