{
  "type": "Feature",
  "properties": {
    "addr:full":"5455 Morgan Ave Riverside CA 92509",
    "addr:housenumber":"5455",
    "addr:postcode":"92509",
    "addr:street":"Morgan Ave",
    "iso:country":"US",
    "sg:address":"5455 Morgan Ave",
    "sg:city":"Riverside",
    "sg:classifiers":[
        {
            "category":"Professional",
            "subcategory":"Research",
            "type":"Services"
        }
    ],
    "sg:phone":"+1 951 681 4929",
    "sg:postcode":"92509",
    "sg:province":"CA",
    "sg:tags":[
        "environmental",
        "ecological"
    ],
    "wof:name":"L & L Environmental",
    "wof:placetype":"venue"
},
  "geometry": {"coordinates":[-117.445116,33.989704],"type":"Point"}
}