{
  "type": "Feature",
  "properties": {
    "addr:full":"600 21st Ave San Francisco CA 94121",
    "addr:housenumber":"600",
    "addr:postcode":"94121",
    "addr:street":"21St Ave",
    "iso:country":"US",
    "sg:address":"600 21st Ave",
    "sg:city":"San Francisco",
    "sg:classifiers":[
        {
            "category":"Education",
            "subcategory":"School",
            "type":"Public Place"
        }
    ],
    "sg:phone":"+1 415 668 3401",
    "sg:postcode":"94121",
    "sg:province":"CA",
    "wof:name":"Rosewood Center",
    "wof:placetype":"venue"
},
  "geometry": {"coordinates":[-122.48004,37.774632],"type":"Point"}
}