{
  "type": "Feature",
  "properties": {
    "iso:country":"US",
    "sg:address":"65 McBrown Rd",
    "sg:city":"Petaluma",
    "sg:classifiers":[
        {
            "category":"Building & Trades",
            "subcategory":"Landscaping Services",
            "type":"Services"
        }
    ],
    "sg:phone":"+1 707 762 1336",
    "sg:postcode":"94952",
    "sg:province":"CA",
    "sg:tags":[
        "installation",
        "landscape",
        "contractor"
    ],
    "wof:name":"Triad Landscaping",
    "wof:placetype":"venue"
},
  "geometry": {"coordinates":[-122.705644,38.266484],"type":"Point"}
}