{
  "type": "Feature",
  "properties": {
    "addr:full":"31952 Mission Trl Lake Elsinore CA 92530",
    "addr:housenumber":"31952",
    "addr:postcode":"92530",
    "addr:street":"Mission Trl",
    "iso:country":"US",
    "sg:address":"31952 Mission Trl",
    "sg:city":"Lake Elsinore",
    "sg:classifiers":[
        {
            "category":"Food & Beverages",
            "subcategory":"Groceries & Convenience Stores",
            "type":"Retail Goods"
        }
    ],
    "sg:phone":"+1 951 674 4837",
    "sg:postcode":"92530",
    "sg:province":"CA",
    "wof:name":"Stater Bros Mkt",
    "wof:placetype":"venue"
},
  "geometry": {"coordinates":[-117.29815499999999,33.657186],"type":"Point"}
}