{
  "type": "Feature",
  "properties": {
    "iso:country":"US",
    "sg:address":"3509 Chestnut Ave",
    "sg:city":"Concord",
    "sg:classifiers":[
        {
            "category":"Building & Trades",
            "subcategory":"Construction",
            "type":"Services"
        }
    ],
    "sg:phone":"+1 925 709 1870",
    "sg:postcode":"94519",
    "sg:province":"CA",
    "sg:tags":[
        "contractor"
    ],
    "wof:name":"Bay Area Roofing",
    "wof:placetype":"venue"
},
  "geometry": {"coordinates":[-122.01242499999999,37.971721],"type":"Point"}
}