{
  "type": "Feature",
  "properties": {
    "addr:full":"5031 Diamond Heights Blvd. San Francisco CA 94131",
    "addr:housenumber":"5031",
    "addr:postcode":"94131",
    "addr:street":"Diamond Heights Blvd.",
    "iso:country":"US",
    "sg:address":"5031 Diamond Heights Blvd.",
    "sg:city":"San Francisco",
    "sg:classifiers":[
        {
            "category":"Professional",
            "type":"Services"
        }
    ],
    "sg:phone":"+1 415 826 0445",
    "sg:postcode":"94131",
    "sg:province":"CA",
    "sg:website":"www.wordwc.com",
    "wof:name":"Wordwright Communications, Inc.",
    "wof:placetype":"venue"
},
  "geometry": {"coordinates":[-122.443147,37.746766],"type":"Point"}
}