{
  "type": "Feature",
  "properties": {
    "addr:full":"1500 Quivira Way San Diego CA 92109",
    "addr:housenumber":"1500",
    "addr:postcode":"92109",
    "addr:street":"Quivira Way",
    "iso:country":"US",
    "sg:address":"1500 Quivira Way",
    "sg:city":"San Diego",
    "sg:classifiers":[
        {
            "category":"Autos & Motor Vehicles",
            "subcategory":"Boat Sales",
            "type":"Retail Goods"
        }
    ],
    "sg:phone":"+1 619 221 8456",
    "sg:postcode":"92109",
    "sg:province":"CA",
    "sg:tags":[
        "yacht"
    ],
    "wof:name":"Driscoll Mission Bay",
    "wof:placetype":"venue"
},
  "geometry": {"coordinates":[-117.23292600000001,32.760732],"type":"Point"}
}