{
  "type": "Feature",
  "properties": {
    "addr:full":"1640 Camino Del Rio N San Diego CA 92108",
    "addr:housenumber":"1640",
    "addr:postcode":"92108",
    "addr:street":"Camino Del Rio N",
    "iso:country":"US",
    "sg:address":"1640 Camino Del Rio N",
    "sg:city":"San Diego",
    "sg:classifiers":[
        {
            "category":"Shopping",
            "subcategory":"Jewelry",
            "type":"Retail Goods"
        }
    ],
    "sg:phone":"+1 619 295 1074",
    "sg:postcode":"92108",
    "sg:province":"CA",
    "sg:tags":[
        "watch"
    ],
    "wof:name":"Valley Time",
    "wof:placetype":"venue"
},
  "geometry": {"coordinates":[-117.148003,32.7672],"type":"Point"}
}