{
  "type": "Feature",
  "properties": {
    "addr:full":"10851 Driver Rd Delano CA 93215",
    "addr:housenumber":"10851",
    "addr:postcode":"93215",
    "addr:street":"Driver Rd",
    "iso:country":"US",
    "sg:address":"10851 Driver Rd",
    "sg:city":"Delano",
    "sg:classifiers":[
        {
            "category":"Farming",
            "subcategory":"Farm",
            "type":"Manufacturing & Wholesale Goods"
        }
    ],
    "sg:phone":"+1 661 725 2833",
    "sg:postcode":"93215",
    "sg:province":"CA",
    "sg:tags":[
        "crop",
        "general"
    ],
    "wof:name":"Dayton Bean Farms",
    "wof:placetype":"venue"
},
  "geometry": {"coordinates":[-119.20529399999999,35.760049],"type":"Point"}
}