{
  "type": "Feature",
  "properties": {
    "iso:country":"US",
    "sg:address":"418 E 18th St",
    "sg:city":"Antioch",
    "sg:classifiers":[
        {
            "category":"Food & Beverages",
            "subcategory":"Liquor & Beverages",
            "type":"Retail Goods"
        }
    ],
    "sg:phone":"+1 925 754 3392",
    "sg:postcode":"94509",
    "sg:province":"CA",
    "wof:name":"Romi's Liquor & Food",
    "wof:placetype":"venue"
},
  "geometry": {"coordinates":[-121.797038,38.004821],"type":"Point"}
}