{
  "type": "Feature",
  "properties": {
    "iso:country":"US",
    "sg:address":"1333 Howard Ave",
    "sg:city":"Burlingame",
    "sg:classifiers":[
        {
            "category":"Home & Garden",
            "subcategory":"Household Appliances",
            "type":"Retail Goods"
        }
    ],
    "sg:phone":"+1 650 568 0281",
    "sg:postcode":"94010",
    "sg:province":"CA",
    "sg:tags":[
        "machine",
        "major",
        "dishwashing"
    ],
    "wof:name":"Michael C Giotinis",
    "wof:placetype":"venue"
},
  "geometry": {"coordinates":[-122.34600399999999,37.577018],"type":"Point"}
}