{
  "type": "Feature",
  "properties": {
    "addr:full":"3136 Story Rd San Jose CA 95127",
    "addr:housenumber":"3136",
    "addr:postcode":"95127",
    "addr:street":"Story Rd",
    "iso:country":"US",
    "sg:address":"3136 Story Rd",
    "sg:city":"San Jose",
    "sg:classifiers":[
        {
            "category":"Banks & Credit Unions",
            "subcategory":"Bank",
            "type":"Services"
        }
    ],
    "sg:phone":"+1 408 347 0200",
    "sg:postcode":"95127",
    "sg:province":"CA",
    "sg:tags":[
        "other",
        "plan",
        "card"
    ],
    "wof:name":"Credit Xpress",
    "wof:placetype":"venue"
},
  "geometry": {"coordinates":[-121.81817700000001,37.356602],"type":"Point"}
}