{
  "type": "Feature",
  "properties": {
    "addr:full":"19570 Ventura Blvd Tarzana CA 91356",
    "addr:housenumber":"19570",
    "addr:postcode":"91356",
    "addr:street":"Ventura Blvd",
    "iso:country":"US",
    "sg:address":"19570 Ventura Blvd",
    "sg:city":"Tarzana",
    "sg:classifiers":[
        {
            "category":"Personal",
            "subcategory":"Beauty Salon",
            "type":"Services"
        }
    ],
    "sg:phone":"+1 818 996 7575",
    "sg:postcode":"91356",
    "sg:province":"CA",
    "sg:tags":[
        "manicuring"
    ],
    "wof:name":"Nails By Lan",
    "wof:placetype":"venue"
},
  "geometry": {"coordinates":[-118.558667,34.172706],"type":"Point"}
}