{
  "type": "Feature",
  "properties": {
    "iso:country":"US",
    "sg:address":"7518 Melrose Ave",
    "sg:city":"Los Angeles",
    "sg:classifiers":[
        {
            "category":"Shopping",
            "subcategory":"Clothing, Apparel, & Fashions",
            "type":"Retail Goods"
        }
    ],
    "sg:phone":"+1 323 655 5750",
    "sg:postcode":"90036",
    "sg:province":"CA",
    "sg:tags":[
        "men's",
        "clothing"
    ],
    "sg:website":"www.moistwear.com/",
    "wof:name":"Moist Wear",
    "wof:placetype":"venue"
},
  "geometry": {"coordinates":[-118.354027,34.083389],"type":"Point"}
}