{
  "type": "Feature",
  "properties": {
    "addr:full":"108 View Dr Boulder Creek CA 95006",
    "addr:housenumber":"108",
    "addr:postcode":"95006",
    "addr:street":"View Dr",
    "iso:country":"US",
    "sg:address":"108 View Dr",
    "sg:city":"Boulder Creek",
    "sg:classifiers":[
        {
            "category":"Personal",
            "type":"Services"
        }
    ],
    "sg:phone":"+1 831 338 4698",
    "sg:postcode":"95006",
    "sg:province":"CA",
    "sg:tags":[
        "therapist",
        "massage"
    ],
    "wof:name":"On-Site Stress Relief",
    "wof:placetype":"venue"
},
  "geometry": {"coordinates":[-122.114627,37.129512],"type":"Point"}
}