{
  "type": "Feature",
  "properties": {
    "addr:full":"550 San Pablo Ave Rodeo CA 94572",
    "addr:housenumber":"550",
    "addr:postcode":"94572",
    "addr:street":"San Pablo Ave",
    "iso:country":"US",
    "sg:address":"550 San Pablo Ave",
    "sg:city":"Rodeo",
    "sg:classifiers":[
        {
            "category":"Retail",
            "subcategory":"Auto Repair",
            "type":"Services"
        }
    ],
    "sg:phone":"+1 510 799 4135",
    "sg:postcode":"94572",
    "sg:province":"CA",
    "sg:tags":[
        "body",
        "automobile",
        "painting",
        "repairing"
    ],
    "wof:name":"Auto Craft",
    "wof:placetype":"venue"
},
  "geometry": {"coordinates":[-122.268089,38.037979],"type":"Point"}
}