{
  "type": "Feature",
  "properties": {
    "iso:country":"US",
    "sg:address":"131 W Ball Rd",
    "sg:city":"Anaheim",
    "sg:classifiers":[
        {
            "category":"Restaurant",
            "type":"Food & Drink"
        }
    ],
    "sg:phone":"+1 714 635 8231",
    "sg:postcode":"92805",
    "sg:province":"CA",
    "wof:name":"Kfc",
    "wof:placetype":"venue"
},
  "geometry": {"coordinates":[-117.910004,33.818001],"type":"Point"}
}