{
  "type": "Feature",
  "properties": {
    "addr:full":"322 N El Camino Real Ste F Encinitas CA 92024",
    "addr:housenumber":"322",
    "addr:postcode":"92024",
    "addr:street":"N El Camino Real Ste F",
    "iso:country":"US",
    "sg:address":"322 N El Camino Real Ste F",
    "sg:city":"Encinitas",
    "sg:classifiers":[
        {
            "category":"Retail",
            "subcategory":"Repair Shop",
            "type":"Services"
        }
    ],
    "sg:phone":"+1 760 436 3889",
    "sg:postcode":"92024",
    "sg:province":"CA",
    "sg:tags":[
        "reupholstery",
        "furniture"
    ],
    "wof:name":"S & Brothers Upholstery",
    "wof:placetype":"venue"
},
  "geometry": {"coordinates":[-117.262001,33.054699],"type":"Point"}
}