{
  "type": "Feature",
  "properties": {
    "addr:full":"550 Marina Pkwy Chula Vista CA 91910",
    "addr:housenumber":"550",
    "addr:postcode":"91910",
    "addr:street":"Marina Pkwy",
    "iso:country":"US",
    "sg:address":"550 Marina Pkwy",
    "sg:city":"Chula Vista",
    "sg:classifiers":[
        {
            "category":"Restaurant",
            "type":"Food & Drink"
        }
    ],
    "sg:phone":"+1 619 422 5714",
    "sg:postcode":"91910",
    "sg:province":"CA",
    "sg:tags":[
        "new",
        "american",
        "brunch",
        "breakfast"
    ],
    "sg:website":"www.galleyatthemarina.com",
    "wof:name":"Galley At the Marina",
    "wof:placetype":"venue"
},
  "geometry": {"coordinates":[-117.10293799999999,32.624496],"type":"Point"}
}