{
  "type": "Feature",
  "properties": {
    "addr:full":"3104 Walnut Ave Carmichael CA 95608",
    "addr:housenumber":"3104",
    "addr:postcode":"95608",
    "addr:street":"Walnut Ave",
    "iso:country":"US",
    "sg:address":"3104 Walnut Ave",
    "sg:city":"Carmichael",
    "sg:classifiers":[
        {
            "category":"Home & Garden",
            "subcategory":"Building Materials",
            "type":"Retail Goods"
        }
    ],
    "sg:phone":"+1 916 973 1424",
    "sg:postcode":"95608",
    "sg:province":"CA",
    "wof:name":"Latham Truss Inc",
    "wof:placetype":"venue"
},
  "geometry": {"coordinates":[-121.34599300000001,38.621188],"type":"Point"}
}