{
  "type": "Feature",
  "properties": {
    "iso:country":"US",
    "sg:address":"8912 Golden State Hwy",
    "sg:city":"Bakersfield",
    "sg:classifiers":[
        {
            "category":"Freight",
            "type":"Transportation"
        },
        {
            "category":"Wholesale",
            "subcategory":"Auto Parts",
            "type":"Manufacturing & Wholesale Goods"
        }
    ],
    "sg:phone":"+1 661 399 3547",
    "sg:postcode":"93308",
    "sg:province":"CA",
    "sg:tags":[
        "trucking",
        "equipment",
        "refrigeration",
        "operator",
        "truck",
        "local"
    ],
    "wof:name":"Glenn's Refrigeration",
    "wof:placetype":"venue"
},
  "geometry": {"coordinates":[-119.063691,35.423642],"type":"Point"}
}