{
  "type": "Feature",
  "properties": {
    "addr:full":"1679 Tracy Dr Yuba City CA 95993",
    "addr:housenumber":"1679",
    "addr:postcode":"95993",
    "addr:street":"Tracy Dr",
    "iso:country":"US",
    "sg:address":"1679 Tracy Dr",
    "sg:city":"Yuba City",
    "sg:classifiers":[
        {
            "category":"Freight",
            "type":"Transportation"
        }
    ],
    "sg:phone":"+1 530 674 7662",
    "sg:postcode":"95993",
    "sg:province":"CA",
    "sg:tags":[
        "operator",
        "local",
        "trucking"
    ],
    "wof:name":"Quality Express",
    "wof:placetype":"venue"
},
  "geometry": {"coordinates":[-121.64462399999999,39.107409],"type":"Point"}
}