{
  "type": "Feature",
  "properties": {
    "addr:full":"107 W Napa St Sonoma CA 95476",
    "addr:housenumber":"107",
    "addr:postcode":"95476",
    "addr:street":"W Napa St",
    "iso:country":"US",
    "sg:address":"107 W Napa St",
    "sg:city":"Sonoma",
    "sg:classifiers":[
        {
            "category":"Home & Garden",
            "subcategory":"Furniture",
            "type":"Retail Goods"
        }
    ],
    "sg:phone":"+1 707 933 9044",
    "sg:postcode":"95476",
    "sg:province":"CA",
    "wof:name":"Harvest Home Stores Inc",
    "wof:placetype":"venue"
},
  "geometry": {"coordinates":[-122.45877,38.291938],"type":"Point"}
}