{
  "type": "Feature",
  "properties": {
    "iso:country":"US",
    "sg:address":"1747 Miramar Dr",
    "sg:city":"Newport Beach",
    "sg:classifiers":[
        {
            "category":"Wholesale",
            "subcategory":"Apparel",
            "type":"Manufacturing & Wholesale Goods"
        }
    ],
    "sg:phone":"+1 949 723 0739",
    "sg:postcode":"92661",
    "sg:province":"CA",
    "sg:tags":[
        "piece"
    ],
    "wof:name":"Worldwide Inch Master",
    "wof:placetype":"venue"
},
  "geometry": {"coordinates":[-117.887112,33.597423],"type":"Point"}
}