{
  "type": "Feature",
  "properties": {
    "addr:full":"2929 E 14th St Long Beach CA 90804",
    "addr:housenumber":"2929",
    "addr:postcode":"90804",
    "addr:street":"E 14Th St",
    "iso:country":"US",
    "sg:address":"2929 E 14th St",
    "sg:city":"Long Beach",
    "sg:classifiers":[
        {
            "category":"Retail",
            "subcategory":"Auto Repair",
            "type":"Services"
        }
    ],
    "sg:phone":"+1 562 599 0084",
    "sg:postcode":"90804",
    "sg:province":"CA",
    "sg:tags":[
        "body",
        "automobile",
        "painting"
    ],
    "wof:name":"Long Beach Collision Ctr",
    "wof:placetype":"venue"
},
  "geometry": {"coordinates":[-118.157268,33.784487],"type":"Point"}
}