{
  "type": "Feature",
  "properties": {
    "addr:full":"7145 Winnetka Ave Winnetka CA 91306",
    "addr:housenumber":"7145",
    "addr:postcode":"91306",
    "addr:street":"Winnetka Ave",
    "iso:country":"US",
    "sg:address":"7145 Winnetka Ave",
    "sg:city":"Winnetka",
    "sg:classifiers":[
        {
            "category":"Health Services",
            "subcategory":"Health Practitioner",
            "type":"Services"
        }
    ],
    "sg:phone":"+1 818 712 9138",
    "sg:postcode":"91306",
    "sg:province":"CA",
    "sg:tags":[
        "acupuncture"
    ],
    "wof:name":"Acupuncture Center",
    "wof:placetype":"venue"
},
  "geometry": {"coordinates":[-118.570999,34.199902],"type":"Point"}
}