{
  "type": "Feature",
  "properties": {
    "addr:full":"2552 Stuart Ave Clovis CA 93611",
    "addr:housenumber":"2552",
    "addr:postcode":"93611",
    "addr:street":"Stuart Ave",
    "iso:country":"US",
    "sg:address":"2552 Stuart Ave",
    "sg:city":"Clovis",
    "sg:classifiers":[
        {
            "category":"Building & Trades",
            "subcategory":"Construction",
            "type":"Services"
        }
    ],
    "sg:phone":"+1 559 323 9124",
    "sg:postcode":"93611",
    "sg:province":"CA",
    "sg:tags":[
        "system",
        "contractor",
        "air conditioning"
    ],
    "wof:name":"Jonathan E Mesple Air Conditioning",
    "wof:placetype":"venue"
},
  "geometry": {"coordinates":[-119.665818,36.82513],"type":"Point"}
}