{
  "type": "Feature",
  "properties": {
    "iso:country":"US",
    "sg:address":"663 Haight St",
    "sg:city":"San Francisco",
    "sg:classifiers":[
        {
            "category":"Restaurant",
            "type":"Food & Drink"
        },
        {
            "category":"Bagels",
            "subcategory":"None",
            "type":"Food & Drink"
        }
    ],
    "sg:phone":"+1 415 621 5183",
    "sg:postcode":"94117",
    "sg:province":"CA",
    "sg:tags":[
        "pizza"
    ],
    "wof:name":"Katz Bagels",
    "wof:placetype":"venue"
},
  "geometry": {"coordinates":[-122.433076,37.77152],"type":"Point"}
}