{
  "type": "Feature",
  "properties": {
    "addr:full":"3381 Durock Rd Cameron Park CA 95682",
    "addr:housenumber":"3381",
    "addr:postcode":"95682",
    "addr:street":"Durock Rd;Park",
    "iso:country":"US",
    "sg:address":"3381 Durock Rd",
    "sg:city":"Cameron Park",
    "sg:classifiers":[
        {
            "category":"Home & Garden",
            "subcategory":"Building Materials",
            "type":"Retail Goods"
        }
    ],
    "sg:phone":"+1 530 677 5781",
    "sg:postcode":"95682",
    "sg:province":"CA",
    "sg:tags":[
        "glass",
        "window",
        "plate"
    ],
    "wof:name":"Camerado Glass",
    "wof:placetype":"venue"
},
  "geometry": {"coordinates":[-120.966346,38.653041],"type":"Point"}
}