{
  "type": "Feature",
  "properties": {
    "iso:country":"US",
    "sg:address":"2518 Woolner Ave",
    "sg:city":"Fairfield",
    "sg:classifiers":[
        {
            "category":"Arts & Performance",
            "subcategory":"Theater",
            "type":"Entertainment"
        }
    ],
    "sg:phone":"+1 707 249 1135",
    "sg:postcode":"94533",
    "sg:province":"CA",
    "sg:tags":[
        "live",
        "music"
    ],
    "wof:name":"Center Stage Entertainment",
    "wof:placetype":"venue"
},
  "geometry": {"coordinates":[-122.076953,38.243561],"type":"Point"}
}