{
  "type": "Feature",
  "properties": {
    "iso:country":"US",
    "sg:address":"305 Broadway",
    "sg:city":"Millbrae",
    "sg:classifiers":[
        {
            "category":"Health Services",
            "subcategory":"Optometrist",
            "type":"Services"
        },
        {
            "category":"Health Services",
            "subcategory":"Doctor",
            "type":"Services"
        },
        {
            "category":"Shopping",
            "subcategory":"Optician",
            "type":"Retail Goods"
        }
    ],
    "sg:phone":"+1 650 697 2475",
    "sg:postcode":"94030",
    "sg:province":"CA",
    "sg:tags":[
        "physician",
        "surgeon",
        "eyewear"
    ],
    "wof:name":"Chang Patricia OD",
    "wof:placetype":"venue"
},
  "geometry": {"coordinates":[-122.391998,37.600899],"type":"Point"}
}