{
  "type": "Feature",
  "properties": {
    "iso:country":"US",
    "sg:address":"216 S Louise St",
    "sg:city":"Glendale",
    "sg:classifiers":[
        {
            "category":"Professional",
            "subcategory":"Credit Reporting & Collection",
            "type":"Services"
        }
    ],
    "sg:phone":"+1 818 502 1981",
    "sg:postcode":"91205",
    "sg:province":"CA",
    "sg:tags":[
        "agency"
    ],
    "sg:website":"www.fidelitycreditor.com",
    "wof:name":"Fidelity Creditor Svc",
    "wof:placetype":"venue"
},
  "geometry": {"coordinates":[-118.252511,34.142919],"type":"Point"}
}