{
  "type": "Feature",
  "properties": {
    "iso:country":"US",
    "sg:address":"125 Auburn Ct",
    "sg:city":"Westlake Village",
    "sg:classifiers":[
        {
            "category":"Autos & Motor Vehicles",
            "subcategory":"Auto Supplies",
            "type":"Retail Goods"
        }
    ],
    "sg:phone":"+1 805 373 5509",
    "sg:postcode":"91362",
    "sg:province":"CA",
    "sg:tags":[
        "tire"
    ],
    "wof:name":"America's Tire Co",
    "wof:placetype":"venue"
},
  "geometry": {"coordinates":[-118.83073,34.165694],"type":"Point"}
}