{
  "type": "Feature",
  "properties": {
    "addr:full":"5 Isadora Duncan Ln San Francisco CA 94102",
    "addr:housenumber":"5",
    "addr:postcode":"94102",
    "addr:street":"Isadora Duncan Ln",
    "iso:country":"US",
    "sg:address":"5 Isadora Duncan Ln",
    "sg:city":"San Francisco",
    "sg:classifiers":[
        {
            "category":"Building & Trades",
            "subcategory":"Landscaping Services",
            "type":"Services"
        }
    ],
    "sg:phone":"+1 415 626 8535",
    "sg:postcode":"94102",
    "sg:province":"CA",
    "sg:tags":[
        "tree"
    ],
    "wof:name":"City Trees",
    "wof:placetype":"venue"
},
  "geometry": {"coordinates":[-122.412198,37.787422],"type":"Point"}
}