{
  "type": "Feature",
  "properties": {
    "addr:full":"808 Gilman St Berkeley CA 94710",
    "addr:housenumber":"808",
    "addr:postcode":"94710",
    "addr:street":"Gilman St",
    "iso:country":"US",
    "sg:address":"808 Gilman St",
    "sg:city":"Berkeley",
    "sg:classifiers":[
        {
            "category":"Shopping",
            "subcategory":"Antiques",
            "type":"Retail Goods"
        }
    ],
    "sg:phone":"+1 510 524 5500",
    "sg:postcode":"94710",
    "sg:province":"CA",
    "wof:name":"Gilman Trading",
    "wof:placetype":"venue"
},
  "geometry": {"coordinates":[-122.301706,37.878432],"type":"Point"}
}