{
  "type": "Feature",
  "properties": {
    "iso:country":"US",
    "sg:address":"3161 Humbolt Ave",
    "sg:city":"Santa Clara",
    "sg:classifiers":[
        {
            "category":"Education",
            "subcategory":"Special Training",
            "type":"Public Place"
        }
    ],
    "sg:phone":"+1 408 985 2655",
    "sg:postcode":"95051",
    "sg:province":"CA",
    "sg:tags":[
        "school",
        "instruction",
        "art"
    ],
    "wof:name":"Creative Valley Art Ctr",
    "wof:placetype":"venue"
},
  "geometry": {"coordinates":[-121.984665,37.347475],"type":"Point"}
}