{
  "type": "Feature",
  "properties": {
    "iso:country":"US",
    "sg:address":"2045 Tasso St",
    "sg:city":"Palo Alto",
    "sg:classifiers":[
        {
            "category":"Professional",
            "type":"Services"
        }
    ],
    "sg:phone":"+1 650 324 2966",
    "sg:postcode":"94301",
    "sg:province":"CA",
    "wof:name":"Verhalen Brownstone Fmly Ptnrs",
    "wof:placetype":"venue"
},
  "geometry": {"coordinates":[-122.14021700000001,37.437581],"type":"Point"}
}