{
  "type": "Feature",
  "properties": {
    "iso:country":"US",
    "sg:address":"2225 N Euclid St",
    "sg:city":"Fullerton",
    "sg:classifiers":[
        {
            "category":"Organizations",
            "subcategory":"Religious Organization",
            "type":"Services"
        }
    ],
    "sg:phone":"+1 714 871 8804",
    "sg:postcode":"92835",
    "sg:province":"CA",
    "sg:tags":[
        "church"
    ],
    "wof:name":"LDS Church",
    "wof:placetype":"venue"
},
  "geometry": {"coordinates":[-117.94220199999999,33.898596],"type":"Point"}
}