{
  "type": "Feature",
  "properties": {
    "addr:full":"899 Northgate Dr Ste 302 San Rafael CA 94903",
    "addr:housenumber":"899",
    "addr:postcode":"94903",
    "addr:street":"Northgate Dr Ste 302",
    "iso:country":"US",
    "sg:address":"899 Northgate Dr Ste 302",
    "sg:city":"San Rafael",
    "sg:classifiers":[
        {
            "category":"Banks & Credit Unions",
            "subcategory":"Investment Brokerage",
            "type":"Services"
        }
    ],
    "sg:phone":"+1 707 525 1333",
    "sg:postcode":"94903",
    "sg:province":"CA",
    "sg:tags":[
        "investing"
    ],
    "wof:name":"Annadel Capital",
    "wof:placetype":"venue"
},
  "geometry": {"coordinates":[-122.54571,38.653106],"type":"Point"}
}