{
  "type": "Feature",
  "properties": {
    "iso:country":"US",
    "sg:address":"10675 Rush St",
    "sg:city":"South El Monte",
    "sg:classifiers":[
        {
            "category":"Wholesale",
            "subcategory":"Durable Goods & Equipment",
            "type":"Manufacturing & Wholesale Goods"
        }
    ],
    "sg:phone":"+1 626 279 5618",
    "sg:postcode":"91733",
    "sg:province":"CA",
    "sg:tags":[
        "importer"
    ],
    "wof:name":"ADI Sports",
    "wof:placetype":"venue"
},
  "geometry": {"coordinates":[-118.041605,34.051923],"type":"Point"}
}