{
  "type": "Feature",
  "properties": {
    "addr:full":"775 Palomar Ave Sunnyvale CA 94085",
    "addr:housenumber":"775",
    "addr:postcode":"94085",
    "addr:street":"Palomar Ave",
    "iso:country":"US",
    "sg:address":"775 Palomar Ave",
    "sg:city":"Sunnyvale",
    "sg:classifiers":[
        {
            "category":"Manufacturing",
            "subcategory":"Tools & Machinery",
            "type":"Manufacturing & Wholesale Goods"
        }
    ],
    "sg:phone":"+1 408 524 3500",
    "sg:postcode":"94085",
    "sg:province":"CA",
    "sg:tags":[
        "physician",
        "surgeon"
    ],
    "wof:name":"Revivant Corp",
    "wof:placetype":"venue"
},
  "geometry": {"coordinates":[-122.035128,37.393152],"type":"Point"}
}