{
  "type": "Feature",
  "properties": {
    "addr:full":"548 E Sepulveda Blvd Carson CA 90745",
    "addr:housenumber":"548",
    "addr:postcode":"90745",
    "addr:street":"E Sepulveda Blvd",
    "iso:country":"US",
    "sg:address":"548 E Sepulveda Blvd",
    "sg:city":"Carson",
    "sg:classifiers":[
        {
            "category":"Organizations",
            "subcategory":"Religious Organization",
            "type":"Services"
        }
    ],
    "sg:phone":"+1 310 835 0174",
    "sg:postcode":"90745",
    "sg:province":"CA",
    "sg:tags":[
        "church"
    ],
    "wof:name":"Apostolic Gates Of Praise",
    "wof:placetype":"venue"
},
  "geometry": {"coordinates":[-118.265153,33.808096],"type":"Point"}
}