{
  "type": "Feature",
  "properties": {
    "addr:full":"31 Beta Ct San Ramon CA 94583",
    "addr:housenumber":"31",
    "addr:postcode":"94583",
    "addr:street":"Beta Ct",
    "iso:country":"US",
    "sg:address":"31 Beta Ct",
    "sg:city":"San Ramon",
    "sg:classifiers":[
        {
            "category":"Organizations",
            "subcategory":"Non-profit Organization",
            "type":"Services"
        }
    ],
    "sg:phone":"+1 925 831 9630",
    "sg:postcode":"94583",
    "sg:province":"CA",
    "sg:tags":[
        "fund",
        "counselor",
        "raising"
    ],
    "wof:name":"Charity Works",
    "wof:placetype":"venue"
},
  "geometry": {"coordinates":[-121.98067,37.781037],"type":"Point"}
}