{
  "type": "Feature",
  "properties": {
    "iso:country":"US",
    "sg:address":"150 Coronado Ave",
    "sg:city":"Daly City",
    "sg:classifiers":[
        {
            "category":"Building & Trades",
            "subcategory":"Construction",
            "type":"Services"
        }
    ],
    "sg:phone":"+1 650 992 6386",
    "sg:postcode":"94015",
    "sg:province":"CA",
    "sg:tags":[
        "resurfacing",
        "laying",
        "refinishing",
        "floor"
    ],
    "wof:name":"Affordable Floors",
    "wof:placetype":"venue"
},
  "geometry": {"coordinates":[-122.485258,37.696876],"type":"Point"}
}