{
  "type": "Feature",
  "properties": {
    "iso:country":"US",
    "sg:address":"12405 Slauson Ave",
    "sg:city":"Whittier",
    "sg:classifiers":[
        {
            "category":"Manufacturing",
            "subcategory":"Tools & Machinery",
            "type":"Manufacturing & Wholesale Goods"
        }
    ],
    "sg:phone":"+1 562 696 2550",
    "sg:postcode":"90606",
    "sg:province":"CA",
    "sg:tags":[
        "machine",
        "shop",
        "industrial",
        "mfg"
    ],
    "wof:name":"ARS Engineering",
    "wof:placetype":"venue"
},
  "geometry": {"coordinates":[-118.05319799999999,33.960303],"type":"Point"}
}