{
  "type": "Feature",
  "properties": {
    "iso:country":"US",
    "sg:address":"10605 Balboa Blvd",
    "sg:city":"Granada Hills",
    "sg:classifiers":[
        {
            "category":"Health Services",
            "subcategory":"Clinic",
            "type":"Services"
        }
    ],
    "sg:phone":"+1 818 832 7200",
    "sg:postcode":"91344",
    "sg:province":"CA",
    "sg:tags":[
        "home"
    ],
    "sg:website":"www.kaiserpermanente.org",
    "wof:name":"Kaiser Permanente Medical Care",
    "wof:placetype":"venue"
},
  "geometry": {"coordinates":[-118.502354,34.263357],"type":"Point"}
}