{
  "type": "Feature",
  "properties": {
    "addr:full":"3701 Mountain View Rd Turlock CA 95382",
    "addr:housenumber":"3701",
    "addr:postcode":"95382",
    "addr:street":"Mountain View Rd",
    "iso:country":"US",
    "sg:address":"3701 Mountain View Rd",
    "sg:city":"Turlock",
    "sg:classifiers":[
        {
            "category":"Professional",
            "type":"Services"
        }
    ],
    "sg:phone":"+1 209 632 8623",
    "sg:postcode":"95382",
    "sg:province":"CA",
    "wof:name":"Dan E Layne",
    "wof:placetype":"venue"
},
  "geometry": {"coordinates":[-120.880787,37.526719],"type":"Point"}
}