{
  "type": "Feature",
  "properties": {
    "iso:country":"US",
    "sg:address":"6549 Pardall Rd",
    "sg:city":"Isla Vista",
    "sg:classifiers":[
        {
            "category":"Restaurant",
            "type":"Food & Drink"
        }
    ],
    "sg:phone":"+1 805 968 5768",
    "sg:postcode":"93117",
    "sg:province":"CA",
    "wof:name":"Menehumes Bar & Grill",
    "wof:placetype":"venue"
},
  "geometry": {"coordinates":[-119.85659699999999,34.413062],"type":"Point"}
}