{
  "type": "Feature",
  "properties": {
    "addr:full":"12102 Rideout Pl Whittier CA 90601",
    "addr:housenumber":"12102",
    "addr:postcode":"90601",
    "addr:street":"Rideout Pl",
    "iso:country":"US",
    "sg:address":"12102 Rideout Pl",
    "sg:city":"Whittier",
    "sg:classifiers":[
        {
            "category":"Building & Trades",
            "subcategory":"Construction",
            "type":"Services"
        }
    ],
    "sg:phone":"+1 562 695 6904",
    "sg:postcode":"90601",
    "sg:province":"CA",
    "sg:tags":[
        "coping",
        "plastering",
        "tiling",
        "pool",
        "swimming"
    ],
    "wof:name":"Andrew's Pool Care",
    "wof:placetype":"venue"
},
  "geometry": {"coordinates":[-118.046824,33.997005],"type":"Point"}
}