{
  "type": "Feature",
  "properties": {
    "addr:full":"2550 Willow Ln Westlake Village CA 91361",
    "addr:housenumber":"2550",
    "addr:postcode":"91361",
    "addr:street":"Willow Ln",
    "iso:country":"US",
    "sg:address":"2550 Willow Ln",
    "sg:city":"Westlake Village",
    "sg:classifiers":[
        {
            "category":"Freight",
            "type":"Transportation"
        }
    ],
    "sg:phone":"+1 805 494 8722",
    "sg:postcode":"91361",
    "sg:province":"CA",
    "sg:tags":[
        "general"
    ],
    "wof:name":"Westlake Self Storage Ltd",
    "wof:placetype":"venue"
},
  "geometry": {"coordinates":[-118.84601499999999,34.170915],"type":"Point"}
}