{
  "type": "Feature",
  "properties": {
    "addr:full":"266 Mount Hermon Rd Scotts Valley CA 95066",
    "addr:housenumber":"266",
    "addr:postcode":"95066",
    "addr:street":"Mount Hermon Rd",
    "iso:country":"US",
    "sg:address":"266 Mount Hermon Rd",
    "sg:city":"Scotts Valley",
    "sg:classifiers":[
        {
            "category":"Retail",
            "subcategory":"Auto Rental",
            "type":"Services"
        }
    ],
    "sg:phone":"+1 831 438 6776",
    "sg:postcode":"95066",
    "sg:province":"CA",
    "sg:tags":[
        "renting",
        "automobile"
    ],
    "wof:name":"Enterprise Rent-A-Car",
    "wof:placetype":"venue"
},
  "geometry": {"coordinates":[-122.03267099999999,37.047574],"type":"Point"}
}