{
  "type": "Feature",
  "properties": {
    "iso:country":"US",
    "sg:address":"7820 Enterprise Dr",
    "sg:city":"Newark",
    "sg:classifiers":[
        {
            "category":"Recreation",
            "type":"Entertainment"
        }
    ],
    "sg:phone":"+1 510 792 1965",
    "sg:postcode":"94560",
    "sg:province":"CA",
    "sg:tags":[
        "amusement"
    ],
    "wof:name":"Enterprise Motor Sports",
    "wof:placetype":"venue"
},
  "geometry": {"coordinates":[-122.046069,37.522662],"type":"Point"}
}