{
  "type": "Feature",
  "properties": {
    "iso:country":"US",
    "sg:address":"10636 Valle Vista Rd",
    "sg:city":"Lakeside",
    "sg:classifiers":[
        {
            "category":"Building & Trades",
            "subcategory":"Cleaning & Sanitation",
            "type":"Services"
        }
    ],
    "sg:phone":"+1 619 561 5502",
    "sg:postcode":"92040",
    "sg:province":"CA",
    "sg:tags":[
        "cleaners",
        "lot"
    ],
    "wof:name":"Dances With Weeds Landscape",
    "wof:placetype":"venue"
},
  "geometry": {"coordinates":[-116.933711,32.870976],"type":"Point"}
}