{
  "type": "Feature",
  "properties": {
    "iso:country":"US",
    "sg:address":"652 Stevens Ave",
    "sg:city":"Solana Beach",
    "sg:classifiers":[
        {
            "category":"Education",
            "subcategory":"Music School",
            "type":"Public Place"
        }
    ],
    "sg:phone":"+1 858 481 3069",
    "sg:postcode":"92075",
    "sg:province":"CA",
    "sg:tags":[
        "instrument",
        "teacher",
        "musical"
    ],
    "sg:website":"www.rhythmhousemusic.com",
    "wof:name":"Rhythm House Music",
    "wof:placetype":"venue"
},
  "geometry": {"coordinates":[-117.260002,32.987301],"type":"Point"}
}