{
  "type": "Feature",
  "properties": {
    "iso:country":"US",
    "sg:address":"7366 Beverly Blvd",
    "sg:city":"Los Angeles",
    "sg:classifiers":[
        {
            "category":"Shopping",
            "subcategory":"Used Merchandise",
            "type":"Retail Goods"
        }
    ],
    "sg:phone":"+1 323 934 1254",
    "sg:postcode":"90036",
    "sg:province":"CA",
    "sg:tags":[
        "antique"
    ],
    "wof:name":"Moderica",
    "wof:placetype":"venue"
},
  "geometry": {"coordinates":[-118.350734,34.076071],"type":"Point"}
}