{
  "type": "Feature",
  "properties": {
    "addr:full":"8502 E Chapman Ave Orange CA 92869",
    "addr:housenumber":"8502",
    "addr:postcode":"92869",
    "addr:street":"E Chapman Ave",
    "iso:country":"US",
    "sg:address":"8502 E Chapman Ave",
    "sg:city":"Orange",
    "sg:classifiers":[
        {
            "category":"Building & Trades",
            "subcategory":"Construction",
            "type":"Services"
        }
    ],
    "sg:phone":"+1 714 628 9755",
    "sg:postcode":"92869",
    "sg:province":"CA",
    "sg:tags":[
        "contractor"
    ],
    "wof:name":"Mel-Mar Construction Inc",
    "wof:placetype":"venue"
},
  "geometry": {"coordinates":[-117.762356,33.792341],"type":"Point"}
}