{
  "type": "Feature",
  "properties": {
    "iso:country":"US",
    "sg:address":"1717 I St",
    "sg:city":"Sacramento",
    "sg:classifiers":[
        {
            "category":"Banks & Credit Unions",
            "subcategory":"Investment Brokerage",
            "type":"Services"
        },
        {
            "category":"Banks & Credit Unions",
            "subcategory":"Financial Services",
            "type":"Services"
        }
    ],
    "sg:phone":"+1 916 448 8994",
    "sg:postcode":"95811",
    "sg:province":"CA",
    "sg:tags":[
        "advisory",
        "management",
        "planner"
    ],
    "wof:name":"Tbt Investments",
    "wof:placetype":"venue"
},
  "geometry": {"coordinates":[-121.48320699999999,38.578792],"type":"Point"}
}