{
  "type": "Feature",
  "properties": {
    "iso:country":"US",
    "sg:address":"670 Lawrence Dr",
    "sg:city":"Newbury Park",
    "sg:classifiers":[
        {
            "category":"Building & Trades",
            "subcategory":"Electrical",
            "type":"Services"
        }
    ],
    "sg:phone":"+1 805 480 9841",
    "sg:postcode":"91320",
    "sg:province":"CA",
    "sg:tags":[
        "electrical",
        "contractor"
    ],
    "wof:name":"Adelphia Headend",
    "wof:placetype":"venue"
},
  "geometry": {"coordinates":[-118.929782,34.188732],"type":"Point"}
}