{
  "type": "Feature",
  "properties": {
    "iso:country":"US",
    "sg:address":"6600 Topanga Canyon Blvd",
    "sg:city":"Canoga Park",
    "sg:classifiers":[
        {
            "category":"Restaurant",
            "type":"Food & Drink"
        }
    ],
    "sg:phone":"+1 818 610 8120",
    "sg:postcode":"91303",
    "sg:province":"CA",
    "wof:name":"Dilkash Cuisine Of India Inc",
    "wof:placetype":"venue"
},
  "geometry": {"coordinates":[-118.605739,34.187627],"type":"Point"}
}