{
  "type": "Feature",
  "properties": {
    "addr:full":"2474 W Pico Blvd Los Angeles CA 90006",
    "addr:housenumber":"2474",
    "addr:postcode":"90006",
    "addr:street":"W Pico Blvd",
    "iso:country":"US",
    "sg:address":"2474 W Pico Blvd",
    "sg:city":"Los Angeles",
    "sg:classifiers":[
        {
            "category":"Food & Beverages",
            "subcategory":"Groceries & Convenience Stores",
            "type":"Retail Goods"
        }
    ],
    "sg:phone":"+1 213 382 6886",
    "sg:postcode":"90006",
    "sg:province":"CA",
    "sg:tags":[
        "grocer"
    ],
    "wof:name":"Pico Discount Store",
    "wof:placetype":"venue"
},
  "geometry": {"coordinates":[-118.290499,34.047189],"type":"Point"}
}