{
  "type": "Feature",
  "properties": {
    "iso:country":"US",
    "sg:address":"74950 Hwy 111",
    "sg:city":"Indian Wells",
    "sg:classifiers":[
        {
            "category":"Banks & Credit Unions",
            "subcategory":"Investment Brokerage",
            "type":"Services"
        }
    ],
    "sg:phone":"+1 760 674 5858",
    "sg:postcode":"92210",
    "sg:province":"CA",
    "sg:tags":[
        "stock",
        "bond"
    ],
    "wof:name":"Scottrade Inc",
    "wof:placetype":"venue"
},
  "geometry": {"coordinates":[-116.357594,33.721468],"type":"Point"}
}