{
  "type": "Feature",
  "properties": {
    "iso:country":"US",
    "sg:address":"6926 Brockton Ave",
    "sg:city":"Riverside",
    "sg:classifiers":[
        {
            "category":"Personal",
            "type":"Services"
        }
    ],
    "sg:phone":"+1 951 781 1321",
    "sg:postcode":"92506",
    "sg:province":"CA",
    "sg:tags":[
        "therapist",
        "massage"
    ],
    "wof:name":"Somatherapy",
    "wof:placetype":"venue"
},
  "geometry": {"coordinates":[-117.396684,33.947937],"type":"Point"}
}