{
  "type": "Feature",
  "properties": {
    "addr:full":"429 Main St Quincy CA 95971",
    "addr:housenumber":"429",
    "addr:postcode":"95971",
    "addr:street":"Main St",
    "iso:country":"US",
    "sg:address":"429 Main St",
    "sg:city":"Quincy",
    "sg:classifiers":[
        {
            "category":"Social Services",
            "subcategory":"Child Care",
            "type":"Services"
        }
    ],
    "sg:phone":"+1 530 283 1242",
    "sg:postcode":"95971",
    "sg:province":"CA",
    "wof:name":"Sierra Cascade Head Start",
    "wof:placetype":"venue"
},
  "geometry": {"coordinates":[-120.947377,39.936789],"type":"Point"}
}