{
  "type": "Feature",
  "properties": {
    "addr:full":"4695 Leathers St San Diego CA 92117",
    "addr:housenumber":"4695",
    "addr:postcode":"92117",
    "addr:street":"Leathers St",
    "iso:country":"US",
    "sg:address":"4695 Leathers St",
    "sg:city":"San Diego",
    "sg:classifiers":[
        {
            "category":"Manufacturing",
            "subcategory":"Glass & Minerals",
            "type":"Manufacturing & Wholesale Goods"
        }
    ],
    "sg:phone":"+1 858 270 3925",
    "sg:postcode":"92117",
    "sg:province":"CA",
    "sg:tags":[
        "mfg"
    ],
    "wof:name":"Deborahs Art Glass",
    "wof:placetype":"venue"
},
  "geometry": {"coordinates":[-117.225976,32.827898],"type":"Point"}
}