{
  "type": "Feature",
  "properties": {
    "iso:country":"US",
    "sg:address":"1220 E F St Ste C1",
    "sg:city":"Oakdale",
    "sg:classifiers":[
        {
            "category":"Personal",
            "subcategory":"Nail Salon",
            "type":"Services"
        }
    ],
    "sg:phone":"+1 209 847 4054",
    "sg:postcode":"95361",
    "sg:province":"CA",
    "wof:name":"Panther Printing",
    "wof:placetype":"venue"
},
  "geometry": {"coordinates":[-120.837835,37.77004],"type":"Point"}
}