{
  "type": "Feature",
  "properties": {
    "iso:country":"US",
    "sg:address":"3300 Soscol Ave",
    "sg:city":"Napa",
    "sg:classifiers":[
        {
            "category":"Professional",
            "type":"Services"
        }
    ],
    "sg:phone":"+1 707 224 7955",
    "sg:postcode":"94558",
    "sg:province":"CA",
    "sg:tags":[
        "establishment"
    ],
    "wof:name":"IASCO",
    "wof:placetype":"venue"
},
  "geometry": {"coordinates":[-122.28507500000001,38.323763],"type":"Point"}
}