{
  "type": "Feature",
  "properties": {
    "addr:full":"14448 Union Ave San Jose CA 95124",
    "addr:housenumber":"14448",
    "addr:postcode":"95124",
    "addr:street":"Union Ave",
    "iso:country":"US",
    "sg:address":"14448 Union Ave",
    "sg:city":"San Jose",
    "sg:classifiers":[
        {
            "category":"Shopping",
            "subcategory":"Bicycles & Sporting Goods",
            "type":"Retail Goods"
        }
    ],
    "sg:phone":"+1 408 377 3577",
    "sg:postcode":"95124",
    "sg:province":"CA",
    "sg:tags":[
        "equipment",
        "skateboard"
    ],
    "wof:name":"Boarder Nation Inc",
    "wof:placetype":"venue"
},
  "geometry": {"coordinates":[-121.931265,37.259083],"type":"Point"}
}