{
  "type": "Feature",
  "properties": {
    "addr:full":"1236 Quarry Ln Pleasanton CA 94566",
    "addr:housenumber":"1236",
    "addr:postcode":"94566",
    "addr:street":"Quarry Ln",
    "iso:country":"US",
    "sg:address":"1236 Quarry Ln",
    "sg:city":"Pleasanton",
    "sg:classifiers":[
        {
            "category":"Building & Trades",
            "subcategory":"Construction",
            "type":"Services"
        }
    ],
    "sg:phone":"+1 925 353 0093",
    "sg:postcode":"94566",
    "sg:province":"CA",
    "sg:tags":[
        "maker",
        "cabinet"
    ],
    "wof:name":"Aloha Cabinetry",
    "wof:placetype":"venue"
},
  "geometry": {"coordinates":[-121.865734,37.673891],"type":"Point"}
}