{
  "type": "Feature",
  "properties": {
    "addr:full":"100 Main St Scotia CA 95565",
    "addr:housenumber":"100",
    "addr:postcode":"95565",
    "addr:street":"Main St",
    "iso:country":"US",
    "sg:address":"100 Main St",
    "sg:city":"Scotia",
    "sg:classifiers":[
        {
            "category":"Bars & Pubs",
            "type":"Food & Drink"
        },
        {
            "category":"Travel",
            "subcategory":"Bed & Breakfast",
            "type":"Entertainment"
        }
    ],
    "sg:phone":"+1 707 764 5338",
    "sg:postcode":"95565",
    "sg:province":"CA",
    "sg:tags":[
        "brew",
        "inn"
    ],
    "wof:name":"Scotia Inn",
    "wof:placetype":"venue"
},
  "geometry": {"coordinates":[-124.099159,40.48838],"type":"Point"}
}