{
  "type": "Feature",
  "properties": {
    "iso:country":"US",
    "sg:address":"1820 E 14th St",
    "sg:city":"Oakland",
    "sg:classifiers":[
        {
            "category":"Wholesale",
            "subcategory":"Durable Goods & Equipment",
            "type":"Manufacturing & Wholesale Goods"
        }
    ],
    "sg:phone":"+1 510 533 5191",
    "sg:postcode":"94606",
    "sg:province":"CA",
    "wof:name":"Safety Footwear",
    "wof:placetype":"venue"
},
  "geometry": {"coordinates":[-122.241044,37.786487],"type":"Point"}
}