{
  "type": "Feature",
  "properties": {
    "addr:full":"1820 E 14th St Oakland CA 94606",
    "addr:housenumber":"1820",
    "addr:postcode":"94606",
    "addr:street":"E 14Th St",
    "iso:country":"US",
    "sg:address":"1820 E 14th St",
    "sg:city":"Oakland",
    "sg:classifiers":[
        {
            "category":"Wholesale",
            "subcategory":"Durable Goods & Equipment",
            "type":"Manufacturing & Wholesale Goods"
        }
    ],
    "sg:phone":"+1 510 533 5191",
    "sg:postcode":"94606",
    "sg:province":"CA",
    "wof:name":"Safety Footwear",
    "wof:placetype":"venue"
},
  "geometry": {"coordinates":[-122.241044,37.786487],"type":"Point"}
}