{
  "type": "Feature",
  "properties": {
    "iso:country":"US",
    "sg:address":"1310 Berry St",
    "sg:city":"Calistoga",
    "sg:classifiers":[
        {
            "category":"Place Of Worship",
            "subcategory":"Church",
            "type":"Public Place"
        },
        {
            "category":"Place Of Worship",
            "type":"Public Place"
        },
        {
            "category":"Organizations",
            "subcategory":"Religious Organization",
            "type":"Services"
        }
    ],
    "sg:phone":"+1 707 942 5721",
    "sg:postcode":"94515",
    "sg:province":"CA",
    "sg:tags":[
        "churches-baptist-general",
        "churches-baptist-southern",
        "churches-baptist"
    ],
    "wof:name":"First Baptist Church",
    "wof:placetype":"venue"
},
  "geometry": {"coordinates":[-122.582915,38.578114],"type":"Point"}
}