{
  "type": "Feature",
  "properties": {
    "iso:country":"US",
    "sg:address":"22222 Sherman Way",
    "sg:city":"Canoga Park",
    "sg:classifiers":[
        {
            "category":"Professional",
            "subcategory":"Management & Consulting",
            "type":"Services"
        }
    ],
    "sg:phone":"+1 818 501 7676",
    "sg:postcode":"91303",
    "sg:province":"CA",
    "sg:tags":[
        "fuel"
    ],
    "wof:name":"Superior Management",
    "wof:placetype":"venue"
},
  "geometry": {"coordinates":[-118.611209,34.20093],"type":"Point"}
}