{
  "type": "Feature",
  "properties": {
    "addr:full":"1106 Alpine Oaks Dr Alpine CA 91901",
    "addr:housenumber":"1106",
    "addr:postcode":"91901",
    "addr:street":"Alpine Oaks Dr",
    "iso:country":"US",
    "sg:address":"1106 Alpine Oaks Dr",
    "sg:city":"Alpine",
    "sg:classifiers":[
        {
            "category":"Professional",
            "type":"Services"
        }
    ],
    "sg:phone":"+1 619 445 6346",
    "sg:postcode":"91901",
    "sg:province":"CA",
    "sg:tags":[
        "establishment"
    ],
    "wof:name":"Dunteman & Zolleweg",
    "wof:placetype":"venue"
},
  "geometry": {"coordinates":[-116.784825,32.815344],"type":"Point"}
}