{
  "type": "Feature",
  "properties": {
    "iso:country":"US",
    "sg:address":"22610 Weatherly Ct",
    "sg:city":"Wildomar",
    "sg:classifiers":[
        {
            "category":"Home & Garden",
            "subcategory":"Home Furnishings",
            "type":"Retail Goods"
        }
    ],
    "sg:phone":"+1 951 678 5610",
    "sg:postcode":"92595",
    "sg:province":"CA",
    "sg:tags":[
        "quilting"
    ],
    "wof:name":"Quality Machine Quilting",
    "wof:placetype":"venue"
},
  "geometry": {"coordinates":[-117.264511,33.604389],"type":"Point"}
}