{
  "type": "Feature",
  "properties": {
    "iso:country":"US",
    "sg:address":"11900 South St Ste 109",
    "sg:city":"Cerritos",
    "sg:classifiers":[
        {
            "category":"Banks & Credit Unions",
            "subcategory":"Bank",
            "type":"Services"
        }
    ],
    "sg:phone":"+1 562 924 0700",
    "sg:postcode":"90703",
    "sg:province":"CA",
    "wof:name":"California Korea Bank",
    "wof:placetype":"venue"
},
  "geometry": {"coordinates":[-118.087997,33.858398],"type":"Point"}
}