{
  "type": "Feature",
  "properties": {
    "addr:full":"419 1/4 N Larchmont Blvd Los Angeles CA 90004",
    "addr:housenumber":"419 1 / 4",
    "addr:postcode":"90004",
    "addr:street":"N Larchmont Blvd",
    "iso:country":"US",
    "sg:address":"419 1/4 N Larchmont Blvd",
    "sg:city":"Los Angeles",
    "sg:classifiers":[
        {
            "category":"Shopping",
            "subcategory":"Jewelry",
            "type":"Retail Goods"
        }
    ],
    "sg:phone":"+1 323 460 6183",
    "sg:postcode":"90004",
    "sg:province":"CA",
    "sg:website":"www.creationsbykrys.com",
    "wof:name":"Creations by Krys",
    "wof:placetype":"venue"
},
  "geometry": {"coordinates":[-118.32364699999999,34.078113],"type":"Point"}
}