{
  "type": "Feature",
  "properties": {
    "iso:country":"US",
    "sg:address":"2945 Ramona Avenue",
    "sg:city":"Sacramento",
    "sg:classifiers":[
        {
            "category":"Autos & Motor Vehicles",
            "subcategory":"Automobile Sales",
            "type":"Retail Goods"
        }
    ],
    "sg:phone":"+1 916 456 3960",
    "sg:postcode":"95826",
    "sg:province":"CA",
    "sg:tags":[
        "limo"
    ],
    "wof:name":"River City Automotive",
    "wof:placetype":"venue"
},
  "geometry": {"coordinates":[-121.41448699999999,38.545435],"type":"Point"}
}