{
  "type": "Feature",
  "properties": {
    "addr:full":"401 N Lincoln St Burbank CA 91506",
    "addr:housenumber":"401",
    "addr:postcode":"91506",
    "addr:street":"N Lincoln St",
    "iso:country":"US",
    "sg:address":"401 N Lincoln St",
    "sg:city":"Burbank",
    "sg:classifiers":[
        {
            "category":"Communications",
            "type":"Services"
        }
    ],
    "sg:phone":"+1 818 842 4453",
    "sg:postcode":"91506",
    "sg:province":"CA",
    "sg:tags":[
        "communication"
    ],
    "wof:name":"Geebs Technical Communications",
    "wof:placetype":"venue"
},
  "geometry": {"coordinates":[-118.330432,34.167862],"type":"Point"}
}