{
  "type": "Feature",
  "properties": {
    "addr:full":"699 Azule Ave San Jose CA 95123",
    "addr:housenumber":"699",
    "addr:postcode":"95123",
    "addr:street":"Azule Ave",
    "iso:country":"US",
    "sg:address":"699 Azule Ave",
    "sg:city":"San Jose",
    "sg:classifiers":[
        {
            "category":"Home & Garden",
            "subcategory":"Carpets & Floor Coverings",
            "type":"Retail Goods"
        }
    ],
    "sg:phone":"+1 408 947 0222",
    "sg:postcode":"95123",
    "sg:province":"CA",
    "wof:name":"Stephens Carpet & Uphl Clg",
    "wof:placetype":"venue"
},
  "geometry": {"coordinates":[-121.836195,37.241603],"type":"Point"}
}