{
  "type": "Feature",
  "properties": {
    "addr:full":"2810 Lone Tree Way Antioch CA 94509",
    "addr:housenumber":"2810",
    "addr:postcode":"ca 94509",
    "addr:street":"Lone Tree Way",
    "iso:country":"US",
    "sg:address":"2810 Lone Tree Way",
    "sg:city":"Antioch",
    "sg:classifiers":[
        {
            "category":"Banks & Credit Unions",
            "subcategory":"Bank",
            "type":"Services"
        }
    ],
    "sg:phone":"+1 925 706 0011",
    "sg:postcode":"94509",
    "sg:province":"CA",
    "sg:tags":[
        "mortgage"
    ],
    "wof:name":"Eagle Crest Home Loans",
    "wof:placetype":"venue"
},
  "geometry": {"coordinates":[-121.801158,37.975806],"type":"Point"}
}