{
  "type": "Feature",
  "properties": {
    "iso:country":"US",
    "sg:address":"804 10th Ave",
    "sg:city":"Delano",
    "sg:classifiers":[
        {
            "category":"Shopping",
            "subcategory":"Music",
            "type":"Retail Goods"
        }
    ],
    "sg:phone":"+1 661 725 3422",
    "sg:postcode":"93215",
    "sg:province":"CA",
    "sg:tags":[
        "video",
        "disc",
        "tape",
        "cassette"
    ],
    "wof:name":"Rosa's Video",
    "wof:placetype":"venue"
},
  "geometry": {"coordinates":[-119.245664,35.768994],"type":"Point"}
}