{
  "type": "Feature",
  "properties": {
    "iso:country":"US",
    "sg:address":"21212 Erwin St",
    "sg:city":"Woodland Hills",
    "sg:classifiers":[
        {
            "category":"Building & Trades",
            "subcategory":"Construction",
            "type":"Services"
        }
    ],
    "sg:phone":"+1 818 340 8050",
    "sg:postcode":"91367",
    "sg:province":"CA",
    "sg:tags":[
        "contractor"
    ],
    "wof:name":"Artner Construction",
    "wof:placetype":"venue"
},
  "geometry": {"coordinates":[-118.59594,34.182781],"type":"Point"}
}