{
  "type": "Feature",
  "properties": {
    "iso:country":"US",
    "sg:address":"2664 Newport Boulevard",
    "sg:city":"Costa Mesa",
    "sg:classifiers":[
        {
            "category":"Health Services",
            "subcategory":"Health Practitioner",
            "type":"Services"
        }
    ],
    "sg:phone":"+1 949 631 9009",
    "sg:postcode":"92627",
    "sg:province":"CA",
    "sg:tags":[
        "therapy",
        "physical"
    ],
    "wof:name":"Wellness by Design",
    "wof:placetype":"venue"
},
  "geometry": {"coordinates":[-117.89529,33.664645],"type":"Point"}
}