{
  "type": "Feature",
  "properties": {
    "iso:country":"US",
    "sg:address":"6100 Wilshire Blvd",
    "sg:city":"Los Angeles",
    "sg:classifiers":[
        {
            "category":"Professional",
            "subcategory":"Advertising",
            "type":"Services"
        }
    ],
    "sg:phone":"+1 323 937 7072",
    "sg:postcode":"90048",
    "sg:province":"CA",
    "wof:name":"Cass Communications Inc",
    "wof:placetype":"venue"
},
  "geometry": {"coordinates":[-118.363374,34.063193],"type":"Point"}
}