{
  "type": "Feature",
  "properties": {
    "addr:full":"1050 Murrieta Blvd Livermore CA 94550",
    "addr:housenumber":"1050",
    "addr:postcode":"94550",
    "addr:street":"Murrieta Blvd",
    "iso:country":"US",
    "sg:address":"1050 Murrieta Blvd",
    "sg:city":"Livermore",
    "sg:classifiers":[
        {
            "category":"Health Services",
            "subcategory":"Doctor",
            "type":"Services"
        }
    ],
    "sg:phone":"+1 925 443 3120",
    "sg:postcode":"94550",
    "sg:province":"CA",
    "sg:tags":[
        "physician",
        "surgeon"
    ],
    "wof:name":"Baijnath Saw MD",
    "wof:placetype":"venue"
},
  "geometry": {"coordinates":[-121.781913,37.676054],"type":"Point"}
}