{
  "type": "Feature",
  "properties": {
    "addr:full":"281 Magnolia Ave Goleta CA 93117",
    "addr:housenumber":"281",
    "addr:postcode":"93117",
    "addr:street":"Magnolia Ave",
    "iso:country":"US",
    "sg:address":"281 Magnolia Ave",
    "sg:city":"Goleta",
    "sg:classifiers":[
        {
            "category":"Manufacturing",
            "subcategory":"Printing",
            "type":"Manufacturing & Wholesale Goods"
        }
    ],
    "sg:phone":"+1 805 967 8015",
    "sg:postcode":"93117",
    "sg:province":"CA",
    "sg:tags":[
        "publisher"
    ],
    "sg:website":"www.academicinnovations.com",
    "wof:name":"Academic Innovations",
    "wof:placetype":"venue"
},
  "geometry": {"coordinates":[-119.827735,34.435684],"type":"Point"}
}