{
  "type": "Feature",
  "properties": {
    "addr:full":"2737 Velvet Way Walnut Creek CA 94596",
    "addr:housenumber":"2737",
    "addr:postcode":"94596",
    "addr:street":"Velvet Way",
    "iso:country":"US",
    "sg:address":"2737 Velvet Way",
    "sg:city":"Walnut Creek",
    "sg:classifiers":[
        {
            "category":"Real Estate",
            "subcategory":"Real Estate Agent",
            "type":"Services"
        }
    ],
    "sg:phone":"+1 925 932 3270",
    "sg:postcode":"94596",
    "sg:province":"CA",
    "wof:name":"Larry Holcomb Inc",
    "wof:placetype":"venue"
},
  "geometry": {"coordinates":[-122.020753,37.867443],"type":"Point"}
}