{
  "type": "Feature",
  "properties": {
    "iso:country":"US",
    "sg:address":"6920 Koll Center Parkway, Suite 215",
    "sg:city":"Pleasanton",
    "sg:classifiers":[
        {
            "category":"Professional",
            "subcategory":"Research",
            "type":"Services"
        }
    ],
    "sg:phone":"+1 925 461 1300",
    "sg:postcode":"94566",
    "sg:province":"CA",
    "sg:website":"http://www.arcxis.com",
    "wof:name":"Arcxis Biotechnologies",
    "wof:placetype":"venue"
},
  "geometry": {"coordinates":[-121.87233000000001,37.65715],"type":"Point"}
}