{
  "type": "Feature",
  "properties": {
    "addr:full":"21777 Ventura Blvd Ste 238 Woodland Hills CA 91364",
    "addr:housenumber":"21777",
    "addr:postcode":"91364",
    "addr:street":"Ventura Blvd Ste 238",
    "iso:country":"US",
    "sg:address":"21777 Ventura Blvd Ste 238",
    "sg:city":"Woodland Hills",
    "sg:classifiers":[
        {
            "category":"Building & Trades",
            "subcategory":"Construction",
            "type":"Services"
        }
    ],
    "sg:phone":"+1 818 704 7844",
    "sg:postcode":"91364",
    "sg:province":"CA",
    "sg:tags":[
        "contractor"
    ],
    "wof:name":"Rj Engineering & Construction",
    "wof:placetype":"venue"
},
  "geometry": {"coordinates":[-118.601997,34.1684],"type":"Point"}
}