{
  "type": "Feature",
  "properties": {
    "addr:full":"811 W 7th St Los Angeles CA 90017",
    "addr:housenumber":"811",
    "addr:postcode":"90017",
    "addr:street":"W 7Th St",
    "iso:country":"US",
    "sg:address":"811 W 7th St",
    "sg:city":"Los Angeles",
    "sg:classifiers":[
        {
            "category":"Parking",
            "type":"Transportation"
        }
    ],
    "sg:phone":"+1 213 627 5481",
    "sg:postcode":"90017",
    "sg:province":"CA",
    "sg:tags":[
        "lots"
    ],
    "wof:name":"Allright Parking Cal Inc",
    "wof:placetype":"venue"
},
  "geometry": {"coordinates":[-118.258976,34.048876],"type":"Point"}
}