{
  "type": "Feature",
  "properties": {
    "iso:country":"US",
    "sg:address":"1243 S Channing Ave",
    "sg:city":"Fresno",
    "sg:classifiers":[
        {
            "category":"Freight",
            "type":"Transportation"
        }
    ],
    "sg:phone":"+1 559 486 1870",
    "sg:postcode":"93706",
    "sg:province":"CA",
    "sg:tags":[
        "trucking"
    ],
    "wof:name":"JFT Inc",
    "wof:placetype":"venue"
},
  "geometry": {"coordinates":[-119.82431099999999,36.729334],"type":"Point"}
}