{
  "type": "Feature",
  "properties": {
    "iso:country":"US",
    "sg:address":"7555 Mexico Way",
    "sg:city":"Buena Park",
    "sg:classifiers":[
        {
            "category":"Retail",
            "subcategory":"Repair Shop",
            "type":"Services"
        }
    ],
    "sg:phone":"+1 714 670 1880",
    "sg:postcode":"90620",
    "sg:province":"CA",
    "sg:tags":[
        "welding"
    ],
    "wof:name":"B & P Portable Welding Svc",
    "wof:placetype":"venue"
},
  "geometry": {"coordinates":[-118.03429,33.85082],"type":"Point"}
}