{
  "type": "Feature",
  "properties": {
    "addr:full":"2222 E Lincoln Ave Anaheim CA 92806",
    "addr:housenumber":"2222",
    "addr:postcode":"92806",
    "addr:street":"E Lincoln Ave",
    "iso:country":"US",
    "sg:address":"2222 E Lincoln Ave",
    "sg:city":"Anaheim",
    "sg:classifiers":[
        {
            "category":"Shopping",
            "subcategory":"Department Store",
            "type":"Retail Goods"
        },
        {
            "category":"Shopping",
            "subcategory":"Pharmacy",
            "type":"Retail Goods"
        }
    ],
    "sg:phone":"+1 714 991 6111",
    "sg:postcode":"92806",
    "sg:province":"CA",
    "sg:tags":[
        "drugstore"
    ],
    "wof:name":"Kmart Stores",
    "wof:placetype":"venue"
},
  "geometry": {"coordinates":[-117.887001,33.8395],"type":"Point"}
}