{
  "type": "Feature",
  "properties": {
    "iso:country":"US",
    "sg:address":"828 W Taft Ave",
    "sg:city":"Orange",
    "sg:classifiers":[
        {
            "category":"Professional",
            "subcategory":"Computer Services",
            "type":"Services"
        }
    ],
    "sg:phone":"+1 714 282 6111",
    "sg:postcode":"92865",
    "sg:province":"CA",
    "sg:tags":[
        "hardware",
        "provider",
        "internet",
        "software"
    ],
    "sg:website":"www.8e6technologies.com",
    "wof:name":"8e6 Technologies",
    "wof:placetype":"venue"
},
  "geometry": {"coordinates":[-117.86148,33.815608],"type":"Point"}
}