{
  "type": "Feature",
  "properties": {
    "iso:country":"US",
    "sg:address":"42540 Washington St",
    "sg:city":"Bermuda Dunes",
    "sg:classifiers":[
        {
            "category":"Real Estate",
            "subcategory":"Real Estate Agent",
            "type":"Services"
        }
    ],
    "sg:phone":"+1 760 345 5668",
    "sg:postcode":"92203",
    "sg:province":"CA",
    "sg:tags":[
        "rental",
        "vacation"
    ],
    "wof:name":"LA Quinta Resort Leasing",
    "wof:placetype":"venue"
},
  "geometry": {"coordinates":[-116.303782,33.739835],"type":"Point"}
}