{
  "type": "Feature",
  "properties": {
    "addr:full":"5105 Laguna Blvd Elk Grove CA 95758",
    "addr:housenumber":"5105",
    "addr:postcode":"95758",
    "addr:street":"Laguna Blvd",
    "iso:country":"US",
    "sg:address":"5105 Laguna Blvd",
    "sg:city":"Elk Grove",
    "sg:classifiers":[
        {
            "category":"Health Services",
            "subcategory":"Doctor",
            "type":"Services"
        }
    ],
    "sg:phone":"+1 916 683 1400",
    "sg:postcode":"95758",
    "sg:province":"CA",
    "sg:tags":[
        "dentist"
    ],
    "wof:name":"Laguna Family Dental",
    "wof:placetype":"venue"
},
  "geometry": {"coordinates":[-121.444711,38.423365],"type":"Point"}
}