{
  "type": "Feature",
  "properties": {
    "iso:country":"US",
    "sg:address":"245 E St",
    "sg:city":"Brawley",
    "sg:classifiers":[
        {
            "category":"Building & Trades",
            "subcategory":"Landscaping Services",
            "type":"Services"
        }
    ],
    "sg:phone":"+1 760 351 1564",
    "sg:postcode":"92227",
    "sg:province":"CA",
    "sg:tags":[
        "tree"
    ],
    "wof:name":"Tres Amigos Tree Svc",
    "wof:placetype":"venue"
},
  "geometry": {"coordinates":[-115.538524,32.979841],"type":"Point"}
}