{
  "type": "Feature",
  "properties": {
    "addr:full":"17121 Hwy 116 Guerneville CA 95446",
    "addr:housenumber":"17121",
    "addr:postcode":"95446",
    "addr:street":"Hwy 116",
    "iso:country":"US",
    "sg:address":"17121 Hwy 116",
    "sg:city":"Guerneville",
    "sg:classifiers":[
        {
            "category":"Restaurant",
            "type":"Food & Drink"
        }
    ],
    "sg:phone":"+1 707 869 8286",
    "sg:postcode":"95446",
    "sg:province":"CA",
    "wof:name":"C K House Guerneville Chinese",
    "wof:placetype":"venue"
},
  "geometry": {"coordinates":[-123.008045,38.495626],"type":"Point"}
}