{
  "type": "Feature",
  "properties": {
    "addr:full":"16400 Sierra Hwy Santa Clarita CA 91351",
    "addr:housenumber":"16400",
    "addr:postcode":"91351",
    "addr:street":"Sierra Hwy",
    "iso:country":"US",
    "sg:address":"16400 Sierra Hwy",
    "sg:city":"Santa Clarita",
    "sg:classifiers":[
        {
            "category":"Social Services",
            "subcategory":"Child Care",
            "type":"Services"
        }
    ],
    "sg:phone":"+1 661 252 3804",
    "sg:postcode":"91351",
    "sg:province":"CA",
    "wof:name":"Sand Castles Schl Age Child Cr",
    "wof:placetype":"venue"
},
  "geometry": {"coordinates":[-118.422703,34.450652],"type":"Point"}
}