{
  "type": "Feature",
  "properties": {
    "addr:full":"2552 Mercantile Way Ste A Barstow CA 92311",
    "addr:housenumber":"2552",
    "addr:postcode":"92311",
    "addr:street":"Mercantile Way Ste A",
    "iso:country":"US",
    "sg:address":"2552 Mercantile Way Ste A",
    "sg:city":"Barstow",
    "sg:classifiers":[
        {
            "category":"Real Estate",
            "subcategory":"Real Estate Services",
            "type":"Services"
        },
        {
            "category":"Real Estate",
            "subcategory":"Real Estate Agent",
            "type":"Services"
        }
    ],
    "sg:phone":"+1 760 253 7342",
    "sg:postcode":"92311",
    "sg:province":"CA",
    "sg:tags":[
        "management"
    ],
    "sg:website":"http://www.newplanexcel.com",
    "wof:name":"Factory Merchantile Mall",
    "wof:placetype":"venue"
},
  "geometry": {"coordinates":[-117.08039100000001,34.848629],"type":"Point"}
}