{
  "type": "Feature",
  "properties": {
    "iso:country":"US",
    "sg:address":"560 Pine St",
    "sg:city":"San Francisco",
    "sg:classifiers":[
        {
            "category":"Professional",
            "subcategory":"Lawyer & Legal Services",
            "type":"Services"
        }
    ],
    "sg:phone":"+1 415 217 4757",
    "sg:postcode":"94108",
    "sg:province":"CA",
    "sg:tags":[
        "attorney"
    ],
    "wof:name":"Dennis Zaragoza Law Office",
    "wof:placetype":"venue"
},
  "geometry": {"coordinates":[-122.405742,37.791574],"type":"Point"}
}