{
  "type": "Feature",
  "properties": {
    "addr:full":"12 Shetland Ct. Oakland CA 94605",
    "addr:housenumber":"12",
    "addr:postcode":"94605",
    "addr:street":"Shetland Ct.",
    "iso:country":"US",
    "sg:address":"12 Shetland Ct.",
    "sg:city":"Oakland",
    "sg:classifiers":[
        {
            "category":"Sports & Exercise",
            "subcategory":"Gym",
            "type":"Entertainment"
        }
    ],
    "sg:phone":"+1 510 219 1851",
    "sg:postcode":"94605",
    "sg:province":"CA",
    "sg:tags":[
        "yoga"
    ],
    "sg:website":"www.theopener.com",
    "wof:name":"The Opener",
    "wof:placetype":"venue"
},
  "geometry": {"coordinates":[-122.119103,37.754162],"type":"Point"}
}