{
  "type": "Feature",
  "properties": {
    "addr:full":"6871 Katella Ave Cypress CA 90630",
    "addr:housenumber":"6871",
    "addr:postcode":"90630",
    "addr:street":"Katella Ave",
    "iso:country":"US",
    "sg:address":"6871 Katella Ave",
    "sg:city":"Cypress",
    "sg:classifiers":[
        {
            "category":"Insurance",
            "subcategory":"Health Insurance",
            "type":"Services"
        }
    ],
    "sg:phone":"+1 714 527 2246",
    "sg:postcode":"90630",
    "sg:province":"CA",
    "sg:tags":[
        "market"
    ],
    "wof:name":"Gnc",
    "wof:placetype":"venue"
},
  "geometry": {"coordinates":[-118.01300000000001,33.803101],"type":"Point"}
}