{
  "type": "Feature",
  "properties": {
    "addr:full":"466 France St Sonoma CA 95476",
    "addr:housenumber":"466",
    "addr:postcode":"95476",
    "addr:street":"France St",
    "iso:country":"US",
    "sg:address":"466 France St",
    "sg:city":"Sonoma",
    "sg:classifiers":[
        {
            "category":"Building & Trades",
            "subcategory":"Construction",
            "type":"Services"
        }
    ],
    "sg:phone":"+1 707 938 3629",
    "sg:postcode":"95476",
    "sg:province":"CA",
    "sg:tags":[
        "contractor"
    ],
    "wof:name":"Sonoma Valley Tile",
    "wof:placetype":"venue"
},
  "geometry": {"coordinates":[-122.450459,38.287632],"type":"Point"}
}