{
  "type": "Feature",
  "properties": {
    "iso:country":"US",
    "sg:address":"6480 Westminster Boulevard",
    "sg:city":"Westminster",
    "sg:classifiers":[
        {
            "category":"Shopping",
            "subcategory":"Tobacco",
            "type":"Retail Goods"
        }
    ],
    "sg:phone":"+1 714 379 1615",
    "sg:postcode":"92683",
    "sg:province":"CA",
    "sg:tags":[
        "shop"
    ],
    "wof:name":"Smoke & Gifts",
    "wof:placetype":"venue"
},
  "geometry": {"coordinates":[-118.016184,33.758915],"type":"Point"}
}