{
  "type": "Feature",
  "properties": {
    "iso:country":"US",
    "sg:address":"4311 Rosa Ln",
    "sg:city":"Shingle Springs",
    "sg:classifiers":[
        {
            "category":"Wholesale",
            "subcategory":"Groceries",
            "type":"Manufacturing & Wholesale Goods"
        }
    ],
    "sg:phone":"+1 530 677 7373",
    "sg:postcode":"95682",
    "sg:province":"CA",
    "wof:name":"Allium Acres",
    "wof:placetype":"venue"
},
  "geometry": {"coordinates":[-120.944845,38.707792],"type":"Point"}
}