{
  "type": "Feature",
  "properties": {
    "addr:full":"1522 W Manchester Avenue Los Angeles CA 90047",
    "addr:housenumber":"1522",
    "addr:postcode":"90047",
    "addr:street":"W Manchester Avenue",
    "iso:country":"US",
    "sg:address":"1522 W Manchester Avenue",
    "sg:city":"Los Angeles",
    "sg:classifiers":[
        {
            "category":"Professional",
            "subcategory":"Lawyer & Legal Services",
            "type":"Services"
        }
    ],
    "sg:phone":"+1 323 971 6063",
    "sg:postcode":"90047",
    "sg:province":"CA",
    "sg:tags":[
        "notary"
    ],
    "wof:name":"Rhynes Tax & Bookkeeping Service",
    "wof:placetype":"venue"
},
  "geometry": {"coordinates":[-118.30383500000001,33.960104],"type":"Point"}
}