{
  "type": "Feature",
  "properties": {
    "iso:country":"US",
    "sg:address":"8900 Walker St",
    "sg:city":"Cypress",
    "sg:classifiers":[
        {
            "category":"Retail",
            "subcategory":"Auto Repair",
            "type":"Services"
        }
    ],
    "sg:phone":"+1 714 952 9181",
    "sg:postcode":"90630",
    "sg:province":"CA",
    "sg:tags":[
        "body",
        "shop",
        "painting",
        "automobile"
    ],
    "wof:name":"Cypress Auto Body & Paint",
    "wof:placetype":"venue"
},
  "geometry": {"coordinates":[-118.037003,33.832901],"type":"Point"}
}