{
  "type": "Feature",
  "properties": {
    "addr:full":"1347 Highland Ct Milpitas CA 95035",
    "addr:housenumber":"1347",
    "addr:postcode":"95035",
    "addr:street":"Highland Ct",
    "iso:country":"US",
    "sg:address":"1347 Highland Ct",
    "sg:city":"Milpitas",
    "sg:classifiers":[
        {
            "category":"Manufacturing",
            "subcategory":"Tools & Machinery",
            "type":"Manufacturing & Wholesale Goods"
        }
    ],
    "sg:phone":"+1 408 263 4974",
    "sg:postcode":"95035",
    "sg:province":"CA",
    "sg:tags":[
        "mining",
        "mfg"
    ],
    "wof:name":"Paul Arpin Manufacturing",
    "wof:placetype":"venue"
},
  "geometry": {"coordinates":[-121.87034300000001,37.418289],"type":"Point"}
}