{
  "type": "Feature",
  "properties": {
    "addr:full":"4341 Macarthur Blvd Newport Beach CA 92660",
    "addr:housenumber":"4341",
    "addr:postcode":"92660",
    "addr:street":"Macarthur Blvd",
    "iso:country":"US",
    "sg:address":"4341 Macarthur Blvd",
    "sg:city":"Newport Beach",
    "sg:classifiers":[
        {
            "category":"Wholesale",
            "subcategory":"Hardware",
            "type":"Manufacturing & Wholesale Goods"
        }
    ],
    "sg:phone":"+1 949 975 1074",
    "sg:postcode":"92660",
    "sg:province":"CA",
    "sg:tags":[
        "equipment",
        "energy",
        "solar"
    ],
    "wof:name":"Infinity Tan",
    "wof:placetype":"venue"
},
  "geometry": {"coordinates":[-117.864628,33.6687],"type":"Point"}
}