{
  "type": "Feature",
  "properties": {
    "addr:full":"8055 Beverly Blvd Los Angeles CA 90048",
    "addr:housenumber":"8055",
    "addr:postcode":"90048",
    "addr:street":"Beverly Blvd",
    "iso:country":"US",
    "sg:address":"8055 Beverly Blvd",
    "sg:city":"Los Angeles",
    "sg:classifiers":[
        {
            "category":"Shopping",
            "type":"Retail Goods"
        }
    ],
    "sg:phone":"+1 323 658 6756",
    "sg:postcode":"90048",
    "sg:province":"CA",
    "sg:website":"www.inheritanceshop.com",
    "wof:name":"Inheritance",
    "wof:placetype":"venue"
},
  "geometry": {"coordinates":[-118.36507400000001,34.076082],"type":"Point"}
}