{
  "type": "Feature",
  "properties": {
    "iso:country":"US",
    "sg:address":"130 Battery St",
    "sg:city":"San Francisco",
    "sg:classifiers":[
        {
            "category":"Professional",
            "subcategory":"Advertising",
            "type":"Services"
        }
    ],
    "sg:phone":"+1 415 291 4999",
    "sg:postcode":"94111",
    "sg:province":"CA",
    "sg:tags":[
        "counselor"
    ],
    "sg:website":"www.aaaawest.org",
    "wof:name":"American Association-Advrtsng",
    "wof:placetype":"venue"
},
  "geometry": {"coordinates":[-122.399838,37.79293],"type":"Point"}
}