{
  "type": "Feature",
  "properties": {
    "addr:full":"7016 Cottontail St Ventura CA 93003",
    "addr:housenumber":"7016",
    "addr:postcode":"93003",
    "addr:street":"Cottontail St",
    "iso:country":"US",
    "sg:address":"7016 Cottontail St",
    "sg:city":"Ventura",
    "sg:classifiers":[
        {
            "category":"Professional",
            "subcategory":"Business Services",
            "type":"Services"
        }
    ],
    "sg:phone":"+1 805 659 4608",
    "sg:postcode":"93003",
    "sg:province":"CA",
    "sg:tags":[
        "interior",
        "consultant",
        "design",
        "decorator"
    ],
    "wof:name":"Keller Instincts",
    "wof:placetype":"venue"
},
  "geometry": {"coordinates":[-119.193901,34.253505],"type":"Point"}
}