{
  "type": "Feature",
  "properties": {
    "iso:country":"US",
    "sg:address":"529 E Manchester Blvd",
    "sg:city":"Inglewood",
    "sg:classifiers":[
        {
            "category":"Home & Garden",
            "subcategory":"Furniture",
            "type":"Retail Goods"
        }
    ],
    "sg:phone":"+1 310 672 6566",
    "sg:postcode":"90301",
    "sg:province":"CA",
    "sg:tags":[
        "store"
    ],
    "wof:name":"Mattress 4 Less",
    "wof:placetype":"venue"
},
  "geometry": {"coordinates":[-118.347,33.961102],"type":"Point"}
}