{
  "type": "Feature",
  "properties": {
    "iso:country":"US",
    "sg:address":"133 W Kern Ave",
    "sg:city":"Mc Farland",
    "sg:classifiers":[
        {
            "category":"Food & Beverages",
            "subcategory":"Candy",
            "type":"Retail Goods"
        }
    ],
    "sg:phone":"+1 661 792 3842",
    "sg:postcode":"93250",
    "sg:province":"CA",
    "sg:tags":[
        "confectionery"
    ],
    "wof:name":"Lopez Mexican Candy",
    "wof:placetype":"venue"
},
  "geometry": {"coordinates":[-119.229128,35.677961],"type":"Point"}
}