{
  "type": "Feature",
  "properties": {
    "iso:country":"US",
    "sg:address":"301 19th St",
    "sg:city":"Bakersfield",
    "sg:classifiers":[
        {
            "category":"Retail",
            "subcategory":"Auto Repair",
            "type":"Services"
        }
    ],
    "sg:phone":"+1 661 324 4863",
    "sg:postcode":"93301",
    "sg:province":"CA",
    "sg:tags":[
        "muffler",
        "exhaust",
        "system"
    ],
    "wof:name":"Bakersfield Muffler Svc",
    "wof:placetype":"venue"
},
  "geometry": {"coordinates":[-119.01502499999999,35.376137],"type":"Point"}
}