{
  "type": "Feature",
  "properties": {
    "addr:full":"479 N 41 St Banning CA 92220",
    "addr:housenumber":"479",
    "addr:postcode":"92220",
    "addr:street":"N 41 St",
    "iso:country":"US",
    "sg:address":"479 N 41 St",
    "sg:city":"Banning",
    "sg:classifiers":[
        {
            "category":"Shopping",
            "subcategory":"Computers & Home Electronics",
            "type":"Retail Goods"
        }
    ],
    "sg:phone":"+1 951 849 4910",
    "sg:postcode":"92220",
    "sg:province":"CA",
    "sg:tags":[
        "software"
    ],
    "wof:name":"Intelligent Health Systems",
    "wof:placetype":"venue"
},
  "geometry": {"coordinates":[-116.922245,33.928895],"type":"Point"}
}