{
  "type": "Feature",
  "properties": {
    "addr:full":"1224 Rossmoor Pkwy Walnut Creek CA 94595",
    "addr:housenumber":"1224",
    "addr:postcode":"94595",
    "addr:street":"Rossmoor Pkwy",
    "iso:country":"US",
    "sg:address":"1224 Rossmoor Pkwy",
    "sg:city":"Walnut Creek",
    "sg:classifiers":[
        {
            "category":"Personal",
            "subcategory":"Beauty Salon",
            "type":"Services"
        }
    ],
    "sg:phone":"+1 925 934 2120",
    "sg:postcode":"94595",
    "sg:province":"CA",
    "wof:name":"Betty's Beauty",
    "wof:placetype":"venue"
},
  "geometry": {"coordinates":[-122.06980799999999,37.879078],"type":"Point"}
}