{
  "type": "Feature",
  "properties": {
    "iso:country":"US",
    "sg:address":"8232 Tampa Ave",
    "sg:city":"Reseda",
    "sg:classifiers":[
        {
            "category":"Personal",
            "subcategory":"Beauty Salon",
            "type":"Services"
        }
    ],
    "sg:phone":"+1 818 773 0756",
    "sg:postcode":"91335",
    "sg:province":"CA",
    "sg:tags":[
        "manicuring"
    ],
    "wof:name":"Exquisite Nails",
    "wof:placetype":"venue"
},
  "geometry": {"coordinates":[-118.553477,34.219798],"type":"Point"}
}