{
  "type": "Feature",
  "properties": {
    "iso:country":"US",
    "sg:address":"300 Judah St",
    "sg:city":"Roseville",
    "sg:classifiers":[
        {
            "category":"Personal",
            "subcategory":"Massage",
            "type":"Services"
        },
        {
            "category":"Health Services",
            "subcategory":"Health Practitioner",
            "type":"Services"
        }
    ],
    "sg:phone":"+1 916 786 0695",
    "sg:postcode":"95678",
    "sg:province":"CA",
    "sg:tags":[
        "acupuncture",
        "medicine",
        "alternative",
        "therapist"
    ],
    "sg:website":"http://www.villageacupuncture.com",
    "wof:name":"Village Acupuncture",
    "wof:placetype":"venue"
},
  "geometry": {"coordinates":[-121.285599,38.744709],"type":"Point"}
}