{
  "type": "Feature",
  "properties": {
    "iso:country":"US",
    "sg:address":"903 Grant Avenue",
    "sg:city":"San Francisco",
    "sg:classifiers":[
        {
            "category":"Wholesale",
            "subcategory":"Stationery",
            "type":"Manufacturing & Wholesale Goods"
        }
    ],
    "sg:phone":"+1 415 982 1299",
    "sg:postcode":"94108",
    "sg:province":"CA",
    "sg:tags":[
        "card"
    ],
    "sg:website":"www.fatmingco.com",
    "wof:name":"Fat Ming Co.",
    "wof:placetype":"venue"
},
  "geometry": {"coordinates":[-122.406998,37.7952],"type":"Point"}
}