{
  "type": "Feature",
  "properties": {
    "iso:country":"US",
    "sg:address":"601 Broadway",
    "sg:city":"San Francisco",
    "sg:classifiers":[
        {
            "category":"Coffee & Tea",
            "type":"Food & Drink"
        }
    ],
    "sg:phone":"+1 415 398 2996",
    "sg:postcode":"94133",
    "sg:province":"CA",
    "wof:name":"Yoogo Corporation",
    "wof:placetype":"venue"
},
  "geometry": {"coordinates":[-122.406998,37.797798],"type":"Point"}
}