{
  "type": "Feature",
  "properties": {
    "addr:full":"101 Ave Miramar San Clemente CA 92672",
    "addr:housenumber":"101",
    "addr:postcode":"92672",
    "addr:street":"Ave",
    "iso:country":"US",
    "sg:address":"101 Ave Miramar",
    "sg:city":"San Clemente",
    "sg:classifiers":[
        {
            "category":"Shopping",
            "subcategory":"Jewelry",
            "type":"Retail Goods"
        }
    ],
    "sg:phone":"+1 949 361 0162",
    "sg:postcode":"92672",
    "sg:province":"CA",
    "sg:tags":[
        "used",
        "establish",
        "merchandise"
    ],
    "wof:name":"Precious Plum Antiques",
    "wof:placetype":"venue"
},
  "geometry": {"coordinates":[-117.6147,33.42895],"type":"Point"}
}