{
  "type": "Feature",
  "properties": {
    "iso:country":"US",
    "sg:address":"1840 4th Ave",
    "sg:city":"San Diego",
    "sg:classifiers":[
        {
            "category":"Travel",
            "subcategory":"Hotels & Motels",
            "type":"Entertainment"
        }
    ],
    "sg:phone":"+1 619 236 1600",
    "sg:postcode":"92101",
    "sg:province":"CA",
    "sg:website":"www.westparkinn.com",
    "wof:name":"West Park Inn",
    "wof:placetype":"venue"
},
  "geometry": {"coordinates":[-117.16144,32.72472],"type":"Point"}
}