{
  "type": "Feature",
  "properties": {
    "iso:country":"US",
    "sg:address":"1217 10th St",
    "sg:city":"Modesto",
    "sg:classifiers":[
        {
            "category":"Wholesale",
            "subcategory":"Groceries",
            "type":"Manufacturing & Wholesale Goods"
        }
    ],
    "sg:phone":"+1 209 526 3922",
    "sg:postcode":"95354",
    "sg:province":"CA",
    "sg:tags":[
        "grocer"
    ],
    "sg:website":"www.smartandfinal.com",
    "wof:name":"Cash & Carry",
    "wof:placetype":"venue"
},
  "geometry": {"coordinates":[-121.00299800000001,37.6427],"type":"Point"}
}