{
  "type": "Feature",
  "properties": {
    "addr:full":"643 Wild Oak Dr Windsor CA 95492",
    "addr:housenumber":"643",
    "addr:postcode":"95492",
    "addr:street":"Wild Oak Dr",
    "iso:country":"US",
    "sg:address":"643 Wild Oak Dr",
    "sg:city":"Windsor",
    "sg:classifiers":[
        {
            "category":"Wholesale",
            "subcategory":"Hardware",
            "type":"Manufacturing & Wholesale Goods"
        }
    ],
    "sg:phone":"+1 707 838 9567",
    "sg:postcode":"95492",
    "sg:province":"CA",
    "sg:tags":[
        "tool"
    ],
    "wof:name":"Snap-On Tools Co",
    "wof:placetype":"venue"
},
  "geometry": {"coordinates":[-122.819945,38.548338],"type":"Point"}
}