{
  "type": "Feature",
  "properties": {
    "iso:country":"US",
    "sg:address":"1210 S Sherbourne Dr",
    "sg:city":"Los Angeles",
    "sg:classifiers":[
        {
            "category":"Professional",
            "type":"Services"
        }
    ],
    "sg:phone":"+1 310 360 7537",
    "sg:postcode":"90035",
    "sg:province":"CA",
    "sg:tags":[
        "establishment"
    ],
    "wof:name":"Top USA",
    "wof:placetype":"venue"
},
  "geometry": {"coordinates":[-118.379364,34.055725],"type":"Point"}
}