{
  "type": "Feature",
  "properties": {
    "iso:country":"US",
    "sg:address":"5135 Laurel Canyon Blvd",
    "sg:city":"Valley Village",
    "sg:classifiers":[
        {
            "category":"Restaurant",
            "type":"Food & Drink"
        }
    ],
    "sg:menulink":"http://www.allmenus.com/ca/san-fernando-valley/164380-wienerschnitzel/menu/",
    "sg:phone":"+1 818 506 9086",
    "sg:postcode":"91607",
    "sg:province":"CA",
    "sg:tags":[
        "sandwich",
        "dog",
        "burger",
        "hot",
        "wrap",
        "american"
    ],
    "wof:name":"Wienerschnitzel",
    "wof:placetype":"venue"
},
  "geometry": {"coordinates":[-118.39684699999999,34.164121],"type":"Point"}
}