{
  "type": "Feature",
  "properties": {
    "iso:country":"US",
    "sg:address":"4028 Amelia Dr",
    "sg:city":"Mariposa",
    "sg:classifiers":[
        {
            "category":"Freight",
            "type":"Transportation"
        }
    ],
    "sg:phone":"+1 209 966 3344",
    "sg:postcode":"95338",
    "sg:province":"CA",
    "sg:tags":[
        "operator",
        "local",
        "trucking"
    ],
    "wof:name":"Belardes Butch Trucking",
    "wof:placetype":"venue"
},
  "geometry": {"coordinates":[-119.897907,37.465721],"type":"Point"}
}