{
  "type": "Feature",
  "properties": {
    "addr:full":"5612 Greenbrae Rd Sacramento CA 95822",
    "addr:housenumber":"5612",
    "addr:postcode":"95822",
    "addr:street":"Greenbrae Rd",
    "iso:country":"US",
    "sg:address":"5612 Greenbrae Rd",
    "sg:city":"Sacramento",
    "sg:classifiers":[
        {
            "category":"Retail",
            "subcategory":"Repair Shop",
            "type":"Services"
        }
    ],
    "sg:phone":"+1 916 447 5494",
    "sg:postcode":"95822",
    "sg:province":"CA",
    "sg:tags":[
        "repairing",
        "piano",
        "refinishing"
    ],
    "wof:name":"Mark Stivers Piano Svc",
    "wof:placetype":"venue"
},
  "geometry": {"coordinates":[-121.517875,38.523951],"type":"Point"}
}