{
  "type": "Feature",
  "properties": {
    "iso:country":"US",
    "sg:address":"68315 Kieley Rd",
    "sg:city":"Cathedral City",
    "sg:classifiers":[
        {
            "category":"Personal",
            "type":"Services"
        }
    ],
    "sg:phone":"+1 760 324 1414",
    "sg:postcode":"92234",
    "sg:province":"CA",
    "sg:tags":[
        "towing"
    ],
    "wof:name":"Mohica Towing",
    "wof:placetype":"venue"
},
  "geometry": {"coordinates":[-116.470001,33.7864],"type":"Point"}
}