{
  "type": "Feature",
  "properties": {
    "addr:full":"475 E Nicolet St Banning CA 92220",
    "addr:housenumber":"475",
    "addr:postcode":"92220",
    "addr:street":"E Nicolet St",
    "iso:country":"US",
    "sg:address":"475 E Nicolet St",
    "sg:city":"Banning",
    "sg:classifiers":[
        {
            "category":"Transit Center",
            "subcategory":"Freight",
            "type":"Transportation"
        },
        {
            "category":"Freight",
            "type":"Transportation"
        }
    ],
    "sg:phone":"+1 951 849 7617",
    "sg:postcode":"92220",
    "sg:province":"CA",
    "sg:tags":[
        "trucking-motor",
        "trucking"
    ],
    "wof:name":"One Family One Unit Trucking",
    "wof:placetype":"venue"
},
  "geometry": {"coordinates":[-116.87169299999999,33.928902],"type":"Point"}
}