{
  "type": "Feature",
  "properties": {
    "addr:full":"3242 E Willow St Long Beach CA 90755",
    "addr:housenumber":"3242",
    "addr:postcode":"90755",
    "addr:street":"E Willow St",
    "iso:country":"US",
    "sg:address":"3242 E Willow St",
    "sg:city":"Long Beach",
    "sg:classifiers":[
        {
            "category":"Autos & Motor Vehicles",
            "subcategory":"Auto Supplies",
            "type":"Retail Goods"
        },
        {
            "category":"Wholesale",
            "subcategory":"Auto Parts",
            "type":"Manufacturing & Wholesale Goods"
        }
    ],
    "sg:phone":"+1 562 426 3536",
    "sg:postcode":"90755",
    "sg:province":"CA",
    "sg:tags":[
        "automobile",
        "rebuilt"
    ],
    "wof:name":"Collier's Classics",
    "wof:placetype":"venue"
},
  "geometry": {"coordinates":[-118.15470999999999,33.804418],"type":"Point"}
}