{
  "type": "Feature",
  "properties": {
    "addr:full":"c/o ComMedia LLC 801 S. Grand Ave., #1511 Los Angeles CA 90017",
    "addr:housenumber":"801",
    "addr:postcode":"90017",
    "addr:street":"C;S. Grand Ave. # 1511",
    "iso:country":"US",
    "sg:address":"c/o ComMedia LLC 801 S. Grand Ave., #1511",
    "sg:city":"Los Angeles",
    "sg:classifiers":[
        {
            "category":"Arts & Performance",
            "subcategory":"Arts Center",
            "type":"Entertainment"
        }
    ],
    "sg:phone":"+1 310 499 4104",
    "sg:postcode":"90017",
    "sg:province":"CA",
    "sg:tags":[
        "performing"
    ],
    "sg:website":"www.YaleCabaretHollywood.com/",
    "wof:name":"Yale Cabaret Hollywood",
    "wof:placetype":"venue"
},
  "geometry": {"coordinates":[-118.258743,34.045564],"type":"Point"}
}