{
  "type": "Feature",
  "properties": {
    "addr:full":"1021 Pecten Ct Milpitas CA 95035",
    "addr:housenumber":"1021",
    "addr:postcode":"95035",
    "addr:street":"Pecten Ct",
    "iso:country":"US",
    "sg:address":"1021 Pecten Ct",
    "sg:city":"Milpitas",
    "sg:classifiers":[
        {
            "category":"Professional",
            "subcategory":"Engineering",
            "type":"Services"
        }
    ],
    "sg:phone":"+1 408 945 5997",
    "sg:postcode":"95035",
    "sg:province":"CA",
    "sg:tags":[
        "general",
        "contractor"
    ],
    "wof:name":"D & L Engineering Inc",
    "wof:placetype":"venue"
},
  "geometry": {"coordinates":[-121.883291,37.413076],"type":"Point"}
}