{
  "type": "Feature",
  "properties": {
    "iso:country":"US",
    "sg:address":"17905 Sky Park Cir",
    "sg:city":"Irvine",
    "sg:classifiers":[
        {
            "category":"Arts & Performance",
            "subcategory":"Theater",
            "type":"Entertainment"
        }
    ],
    "sg:phone":"+1 714 639 1007",
    "sg:postcode":"92614",
    "sg:province":"CA",
    "sg:tags":[
        "entertainer"
    ],
    "wof:name":"Stonebridge Productions",
    "wof:placetype":"venue"
},
  "geometry": {"coordinates":[-117.860512,33.691087],"type":"Point"}
}