{
  "type": "Feature",
  "properties": {
    "addr:full":"1527 Ashby Ave Berkeley CA 94703",
    "addr:housenumber":"1527",
    "addr:postcode":"94703",
    "addr:street":"Ashby Ave",
    "iso:country":"US",
    "sg:address":"1527 Ashby Ave",
    "sg:city":"Berkeley",
    "sg:classifiers":[
        {
            "category":"Real Estate",
            "subcategory":"Real Estate Services",
            "type":"Services"
        }
    ],
    "sg:phone":"+1 510 256 0519",
    "sg:postcode":"94703",
    "sg:province":"CA",
    "sg:tags":[
        "home",
        "inspector"
    ],
    "sg:website":"indoorrestore.net",
    "wof:name":"IndoorRestore Mold Removal and Remediation",
    "wof:placetype":"venue"
},
  "geometry": {"coordinates":[-122.277908,37.853698],"type":"Point"}
}