{
  "type": "Feature",
  "properties": {
    "addr:full":"1256 Simonson Ct San Jose CA 95121",
    "addr:housenumber":"1256",
    "addr:postcode":"95121",
    "addr:street":"Simonson Ct",
    "iso:country":"US",
    "sg:address":"1256 Simonson Ct",
    "sg:city":"San Jose",
    "sg:classifiers":[
        {
            "category":"Wholesale",
            "subcategory":"Non-durable Goods",
            "type":"Manufacturing & Wholesale Goods"
        }
    ],
    "sg:phone":"+1 408 362 4615",
    "sg:postcode":"95121",
    "sg:province":"CA",
    "wof:name":"Casa Bella Import & Export",
    "wof:placetype":"venue"
},
  "geometry": {"coordinates":[-121.830387,37.312916],"type":"Point"}
}