{
  "type": "Feature",
  "properties": {
    "iso:country":"US",
    "sg:address":"Silver Creek and Capitol",
    "sg:city":"San Jose",
    "sg:classifiers":[
        {
            "category":"Education",
            "subcategory":"Preschool",
            "type":"Public Place"
        }
    ],
    "sg:phone":"+1 408 532 8986",
    "sg:postcode":"95121",
    "sg:province":"CA",
    "sg:website":"www.bethanyspreschoolhome.com",
    "wof:name":"Bethany's Preschool Home and Daycare",
    "wof:placetype":"venue"
},
  "geometry": {"coordinates":[-121.81082600000001,37.307013],"type":"Point"}
}