{
  "type": "Feature",
  "properties": {
    "iso:country":"US",
    "sg:address":"1832 4th St",
    "sg:city":"Berkeley",
    "sg:classifiers":[
        {
            "category":"Shopping",
            "subcategory":"Clothing, Apparel, & Fashions",
            "type":"Retail Goods"
        }
    ],
    "sg:phone":"+1 510 540 8242",
    "sg:postcode":"94710",
    "sg:province":"CA",
    "wof:name":"Margaret O'Leary Inc",
    "wof:placetype":"venue"
},
  "geometry": {"coordinates":[-122.300683,37.869819],"type":"Point"}
}