{
  "type": "Feature",
  "properties": {
    "addr:full":"627 N Wilson Way Stockton CA 95205",
    "addr:housenumber":"627",
    "addr:postcode":"95205",
    "addr:street":"N Wilson Way",
    "iso:country":"US",
    "sg:address":"627 N Wilson Way",
    "sg:city":"Stockton",
    "sg:classifiers":[
        {
            "category":"Restaurant",
            "type":"Food & Drink"
        }
    ],
    "sg:phone":"+1 209 466 1328",
    "sg:postcode":"95205",
    "sg:province":"CA",
    "wof:name":"Taco Bell",
    "wof:placetype":"venue"
},
  "geometry": {"coordinates":[-121.273466,37.962501],"type":"Point"}
}