{
  "type": "Feature",
  "properties": {
    "iso:country":"US",
    "sg:address":"288 E Valley Blvd",
    "sg:city":"Alhambra",
    "sg:classifiers":[
        {
            "category":"Professional",
            "subcategory":"Business Services",
            "type":"Services"
        }
    ],
    "sg:phone":"+1 626 642 0167",
    "sg:postcode":"91801",
    "sg:province":"CA",
    "wof:name":"4 V Intl Network",
    "wof:placetype":"venue"
},
  "geometry": {"coordinates":[-118.120541,34.078623],"type":"Point"}
}