{
  "type": "Feature",
  "properties": {
    "iso:country":"US",
    "sg:address":"4301 Truxel Rd",
    "sg:city":"Sacramento",
    "sg:classifiers":[
        {
            "category":"Food & Beverages",
            "subcategory":"Meat & Fish",
            "type":"Retail Goods"
        }
    ],
    "sg:phone":"+1 916 285 0780",
    "sg:postcode":"95834",
    "sg:province":"CA",
    "sg:tags":[
        "seafood",
        "market"
    ],
    "wof:name":"Weng's Oriental Fish Market",
    "wof:placetype":"venue"
},
  "geometry": {"coordinates":[-121.510666,38.649862],"type":"Point"}
}