{
  "type": "Feature",
  "properties": {
    "iso:country":"US",
    "sg:address":"919 E Broadway",
    "sg:city":"Glendale",
    "sg:classifiers":[
        {
            "category":"Professional",
            "subcategory":"Lawyer & Legal Services",
            "type":"Services"
        }
    ],
    "sg:phone":"+1 818 500 7305",
    "sg:postcode":"91205",
    "sg:province":"CA",
    "sg:tags":[
        "attorney"
    ],
    "wof:name":"Lansangan Pio C Law Offices of",
    "wof:placetype":"venue"
},
  "geometry": {"coordinates":[-118.24400300000001,34.1464],"type":"Point"}
}