{
  "type": "Feature",
  "properties": {
    "iso:country":"US",
    "sg:address":"633 W 5th St",
    "sg:city":"Los Angeles",
    "sg:classifiers":[
        {
            "category":"Professional",
            "subcategory":"Lawyer & Legal Services",
            "type":"Services"
        }
    ],
    "sg:phone":"+1 213 896 2400",
    "sg:postcode":"90071",
    "sg:province":"CA",
    "sg:tags":[
        "firm",
        "attorney",
        "law"
    ],
    "sg:website":"www.hklaw.com",
    "wof:name":"Holland & Knight LLP",
    "wof:placetype":"venue"
},
  "geometry": {"coordinates":[-118.254613,34.050669],"type":"Point"}
}