{
  "type": "Feature",
  "properties": {
    "addr:full":"829 Gilman Street Berkeley CA 94710",
    "addr:housenumber":"829",
    "addr:postcode":"94710",
    "addr:street":"Gilman Street",
    "iso:country":"US",
    "sg:address":"829 Gilman Street",
    "sg:city":"Berkeley",
    "sg:classifiers":[
        {
            "category":"Retail",
            "subcategory":"Auto Repair",
            "type":"Services"
        }
    ],
    "sg:phone":"+1 510 843 2639",
    "sg:postcode":"94710",
    "sg:province":"CA",
    "wof:name":"Zephyr Auto Works",
    "wof:placetype":"venue"
},
  "geometry": {"coordinates":[-122.302002,37.879398],"type":"Point"}
}