{
  "type": "Feature",
  "properties": {
    "addr:full":"4045 N Blackstone Ave Fresno CA 93726",
    "addr:housenumber":"4045",
    "addr:postcode":"93726",
    "addr:street":"N Blackstone Ave",
    "iso:country":"US",
    "sg:address":"4045 N Blackstone Ave",
    "sg:city":"Fresno",
    "sg:classifiers":[
        {
            "category":"Banks & Credit Unions",
            "subcategory":"Bank",
            "type":"Services"
        }
    ],
    "sg:phone":"+1 559 241 0145",
    "sg:postcode":"93726",
    "sg:province":"CA",
    "sg:tags":[
        "financing"
    ],
    "wof:name":"Wells Fargo Financial Accptnce",
    "wof:placetype":"venue"
},
  "geometry": {"coordinates":[-119.79058499999999,36.793284],"type":"Point"}
}