{
  "type": "Feature",
  "properties": {
    "iso:country":"US",
    "sg:address":"2826 S Norton Ave",
    "sg:city":"Los Angeles",
    "sg:classifiers":[
        {
            "category":"Social Services",
            "subcategory":"Child Care",
            "type":"Services"
        }
    ],
    "sg:phone":"+1 323 737 4533",
    "sg:postcode":"90018",
    "sg:province":"CA",
    "wof:name":"Wooten Childcare",
    "wof:placetype":"venue"
},
  "geometry": {"coordinates":[-118.332649,34.029913],"type":"Point"}
}