{
  "type": "Feature",
  "properties": {
    "iso:country":"US",
    "sg:address":"9851 Santa Cruz Rd",
    "sg:city":"Desert Hot Spgs",
    "sg:classifiers":[
        {
            "category":"Building & Trades",
            "subcategory":"Construction",
            "type":"Services"
        }
    ],
    "sg:phone":"+1 760 251 6007",
    "sg:postcode":"92240",
    "sg:province":"CA",
    "sg:tags":[
        "contractor"
    ],
    "wof:name":"Shatz Construction Inc",
    "wof:placetype":"venue"
},
  "geometry": {"coordinates":[-116.504868,33.976909],"type":"Point"}
}