{
  "type": "Feature",
  "properties": {
    "iso:country":"US",
    "sg:address":"1754 Hudson Dr",
    "sg:city":"San Jose",
    "sg:classifiers":[
        {
            "category":"Arts & Performance",
            "subcategory":"Theater",
            "type":"Entertainment"
        }
    ],
    "sg:phone":"+1 408 978 9745",
    "sg:postcode":"95124",
    "sg:province":"CA",
    "sg:tags":[
        "musician"
    ],
    "wof:name":"Bagpipes-Bruce Cotter",
    "wof:placetype":"venue"
},
  "geometry": {"coordinates":[-121.914047,37.276475],"type":"Point"}
}