{
  "type": "Feature",
  "properties": {
    "iso:country":"US",
    "sg:address":"3512 E 1st St",
    "sg:city":"Los Angeles",
    "sg:classifiers":[
        {
            "category":"Shopping",
            "type":"Retail Goods"
        }
    ],
    "sg:phone":"+1 323 263 0696",
    "sg:postcode":"90063",
    "sg:province":"CA",
    "sg:tags":[
        "telephone",
        "cellular"
    ],
    "wof:name":"R V Communications",
    "wof:placetype":"venue"
},
  "geometry": {"coordinates":[-118.191712,34.035934],"type":"Point"}
}