{
  "type": "Feature",
  "properties": {
    "addr:full":"3650 W Martin Luther King J Suite 232 Los Angeles CA 90008",
    "addr:housenumber":"3650;j suite 232",
    "addr:postcode":"90008",
    "addr:street":"W Martin Luther King",
    "iso:country":"US",
    "sg:address":"3650 W Martin Luther King J Suite 232",
    "sg:city":"Los Angeles",
    "sg:classifiers":[
        {
            "category":"Personal",
            "subcategory":"Barber",
            "type":"Services"
        }
    ],
    "sg:phone":"+1 323 299 3577",
    "sg:postcode":"90008",
    "sg:province":"CA",
    "wof:name":"Hair Architects",
    "wof:placetype":"venue"
},
  "geometry": {"coordinates":[-118.336617,34.011537],"type":"Point"}
}