{
  "type": "Feature",
  "properties": {
    "addr:full":"505 Montgomery St San Francisco CA 94111",
    "addr:housenumber":"505",
    "addr:postcode":"94111",
    "addr:street":"Montgomery St",
    "iso:country":"US",
    "sg:address":"505 Montgomery St",
    "sg:city":"San Francisco",
    "sg:classifiers":[
        {
            "category":"Banks & Credit Unions",
            "subcategory":"Bank",
            "type":"Services"
        }
    ],
    "sg:phone":"+1 415 874 3111",
    "sg:postcode":"94111",
    "sg:province":"CA",
    "sg:tags":[
        "financing"
    ],
    "wof:name":"Intermodal Capital Corp",
    "wof:placetype":"venue"
},
  "geometry": {"coordinates":[-122.403115,37.794168],"type":"Point"}
}