{
  "type": "Feature",
  "properties": {
    "addr:full":"1603 Church St San Francisco CA 94131",
    "addr:housenumber":"1603",
    "addr:postcode":"94131",
    "addr:street":"Church St",
    "iso:country":"US",
    "sg:address":"1603 Church St",
    "sg:city":"San Francisco",
    "sg:classifiers":[
        {
            "category":"Social Services",
            "type":"Services"
        }
    ],
    "sg:phone":"+1 415 882 1161",
    "sg:postcode":"94131",
    "sg:province":"CA",
    "sg:tags":[
        "counselor",
        "marriage",
        "family"
    ],
    "wof:name":"Julie De Pinna Armer",
    "wof:placetype":"venue"
},
  "geometry": {"coordinates":[-122.42667400000001,37.744535],"type":"Point"}
}