{
  "type": "Feature",
  "properties": {
    "addr:full":"1055 Sherwood Rd San Marino CA 91108",
    "addr:housenumber":"1055",
    "addr:postcode":"91108",
    "addr:street":"Sherwood Rd",
    "iso:country":"US",
    "sg:address":"1055 Sherwood Rd",
    "sg:city":"San Marino",
    "sg:classifiers":[
        {
            "category":"Real Estate",
            "subcategory":"Real Estate Operator",
            "type":"Services"
        }
    ],
    "sg:phone":"+1 626 284 2053",
    "sg:postcode":"91108",
    "sg:province":"CA",
    "sg:tags":[
        "building",
        "nonresidential"
    ],
    "wof:name":"Peggy Hamlin",
    "wof:placetype":"venue"
},
  "geometry": {"coordinates":[-118.122276,34.110631],"type":"Point"}
}