{
  "type": "Feature",
  "properties": {
    "addr:full":"3833 Jurupa Ave Riverside CA 92506",
    "addr:housenumber":"3833",
    "addr:postcode":"92506",
    "addr:street":"Jurupa Ave",
    "iso:country":"US",
    "sg:address":"3833 Jurupa Ave",
    "sg:city":"Riverside",
    "sg:classifiers":[
        {
            "category":"Personal",
            "subcategory":"Beauty Salon",
            "type":"Services"
        }
    ],
    "sg:phone":"+1 951 684 5644",
    "sg:postcode":"92506",
    "sg:province":"CA",
    "wof:name":"Center Of New Concepts",
    "wof:placetype":"venue"
},
  "geometry": {"coordinates":[-117.39281699999999,33.961026],"type":"Point"}
}