{
  "type": "Feature",
  "properties": {
    "iso:country":"US",
    "sg:address":"3403 Calle Odessa",
    "sg:city":"Carlsbad",
    "sg:classifiers":[
        {
            "category":"Cinema",
            "subcategory":"Movie Theater",
            "type":"Entertainment"
        }
    ],
    "sg:phone":"+1 760 633 1130",
    "sg:postcode":"92009",
    "sg:province":"CA",
    "wof:name":"New Village Arts Theatre",
    "wof:placetype":"venue"
},
  "geometry": {"coordinates":[-117.23400100000001,33.078098],"type":"Point"}
}