{
  "type": "Feature",
  "properties": {
    "iso:country":"US",
    "sg:address":"1852 Mcgaw Ave",
    "sg:city":"Irvine",
    "sg:classifiers":[
        {
            "category":"Professional",
            "subcategory":"Printing & Photocopies",
            "type":"Services"
        }
    ],
    "sg:phone":"+1 800 600 1440",
    "sg:postcode":"92614",
    "sg:province":"CA",
    "sg:tags":[
        "medal",
        "plaque",
        "trophies"
    ],
    "wof:name":"Recognition Specialists",
    "wof:placetype":"venue"
},
  "geometry": {"coordinates":[-117.84664100000001,33.693888],"type":"Point"}
}