{
  "type": "Feature",
  "properties": {
    "addr:full":"821 Bay St Santa Monica CA 90405",
    "addr:housenumber":"821",
    "addr:postcode":"90405",
    "addr:street":"Bay St",
    "iso:country":"US",
    "sg:address":"821 Bay St",
    "sg:city":"Santa Monica",
    "sg:classifiers":[
        {
            "category":"Professional",
            "subcategory":"Management & Consulting",
            "type":"Services"
        }
    ],
    "sg:phone":"+1 310 452 6114",
    "sg:postcode":"90405",
    "sg:province":"CA",
    "sg:tags":[
        "counselor",
        "public",
        "relations"
    ],
    "wof:name":"Lili Ungar Public Relations",
    "wof:placetype":"venue"
},
  "geometry": {"coordinates":[-118.481832,34.011746],"type":"Point"}
}