{
  "type": "Feature",
  "properties": {
    "iso:country":"US",
    "sg:address":"25301 Alicia Pkwy",
    "sg:city":"Laguna Hills",
    "sg:classifiers":[
        {
            "category":"Retail",
            "subcategory":"Funeral Services",
            "type":"Services"
        }
    ],
    "sg:phone":"+1 949 581 4300",
    "sg:postcode":"92653",
    "sg:province":"CA",
    "sg:tags":[
        "cemetery"
    ],
    "sg:website":"www.oconnormortuary.com",
    "wof:name":"O'Connor Mortuary",
    "wof:placetype":"venue"
},
  "geometry": {"coordinates":[-117.699997,33.590801],"type":"Point"}
}