{
  "type": "Feature",
  "properties": {
    "addr:full":"113 W 8th Ave Chico CA 95926",
    "addr:housenumber":"113",
    "addr:postcode":"95926",
    "addr:street":"W 8Th Ave",
    "iso:country":"US",
    "sg:address":"113 W 8th Ave",
    "sg:city":"Chico",
    "sg:classifiers":[
        {
            "category":"Shopping",
            "subcategory":"Stationery & Office Supplies",
            "type":"Retail Goods"
        }
    ],
    "sg:phone":"+1 530 893 4253",
    "sg:postcode":"95926",
    "sg:province":"CA",
    "wof:name":"Laser Renew ZIT",
    "wof:placetype":"venue"
},
  "geometry": {"coordinates":[-121.85142999999999,39.744973],"type":"Point"}
}