{
  "type": "Feature",
  "properties": {
    "iso:country":"US",
    "sg:address":"8402 Monroe Ave",
    "sg:city":"Stanton",
    "sg:classifiers":[
        {
            "category":"Manufacturing",
            "subcategory":"Tools & Machinery",
            "type":"Manufacturing & Wholesale Goods"
        }
    ],
    "sg:phone":"+1 714 236 9110",
    "sg:postcode":"90680",
    "sg:province":"CA",
    "sg:tags":[
        "measuring",
        "industrial",
        "instr",
        "mfg",
        "instrument",
        "controlling"
    ],
    "wof:name":"Seymour Instruments Inc",
    "wof:placetype":"venue"
},
  "geometry": {"coordinates":[-117.986221,33.805454],"type":"Point"}
}