{
  "type": "Feature",
  "properties": {
    "addr:full":"1807 Foothill Blvd Calistoga CA 94515",
    "addr:housenumber":"1807",
    "addr:postcode":"94515",
    "addr:street":"Foothill Blvd",
    "iso:country":"US",
    "sg:address":"1807 Foothill Blvd",
    "sg:city":"Calistoga",
    "sg:classifiers":[
        {
            "category":"Travel",
            "subcategory":"Hotels & Motels",
            "type":"Entertainment"
        }
    ],
    "sg:phone":"+1 877 942 7700",
    "sg:postcode":"94515",
    "sg:province":"CA",
    "sg:tags":[
        "breakfast",
        "accommodation",
        "bed"
    ],
    "sg:website":"www.aurorapark.com",
    "wof:name":"Aurora Park Cottages",
    "wof:placetype":"venue"
},
  "geometry": {"coordinates":[-122.58899700000001,38.577999],"type":"Point"}
}