{
  "type": "Feature",
  "properties": {
    "addr:full":"1309 Rumrill Blvd San Pablo CA 94806",
    "addr:housenumber":"1309",
    "addr:postcode":"94806",
    "addr:street":"Rumrill Blvd",
    "iso:country":"US",
    "sg:address":"1309 Rumrill Blvd",
    "sg:city":"San Pablo",
    "sg:classifiers":[
        {
            "category":"Organizations",
            "subcategory":"Religious Organization",
            "type":"Services"
        }
    ],
    "sg:phone":"+1 510 799 4159",
    "sg:postcode":"94806",
    "sg:province":"CA",
    "sg:tags":[
        "church"
    ],
    "wof:name":"Iglesia Apospolica",
    "wof:placetype":"venue"
},
  "geometry": {"coordinates":[-122.357057,37.9533],"type":"Point"}
}