{
  "type": "Feature",
  "properties": {
    "iso:country":"US",
    "sg:address":"12500 Campus Dr",
    "sg:city":"Oakland",
    "sg:classifiers":[
        {
            "category":"Food & Beverages",
            "subcategory":"Meat & Fish",
            "type":"Retail Goods"
        }
    ],
    "sg:postcode":"94619",
    "sg:province":"CA",
    "sg:tags":[
        "hot",
        "dog"
    ],
    "wof:name":"Merritt College Hotdog Stand",
    "wof:placetype":"venue"
},
  "geometry": {"coordinates":[-122.167647,37.79132],"type":"Point"}
}