{
  "type": "Feature",
  "properties": {
    "iso:country":"US",
    "sg:address":"1133 E.Broadway Ave",
    "sg:city":"Glendale",
    "sg:classifiers":[
        {
            "category":"Restaurant",
            "type":"Food & Drink"
        }
    ],
    "sg:phone":"+1 818 247 7781",
    "sg:postcode":"91206",
    "sg:province":"CA",
    "sg:tags":[
        "flavor",
        "local"
    ],
    "wof:name":"7 Eleven",
    "wof:placetype":"venue"
},
  "geometry": {"coordinates":[-118.240307,34.146539],"type":"Point"}
}