{
  "type": "Feature",
  "properties": {
    "addr:full":"17326 Cam Brisa del Mar San Diego CA 92127",
    "addr:housenumber":"17326",
    "addr:postcode":"92127",
    "addr:street":"Cam Brisa Del Mar",
    "iso:country":"US",
    "sg:address":"17326 Cam Brisa del Mar",
    "sg:city":"San Diego",
    "sg:classifiers":[
        {
            "category":"Manufacturing",
            "subcategory":"Printing",
            "type":"Manufacturing & Wholesale Goods"
        }
    ],
    "sg:phone":"+1 858 759 8038",
    "sg:postcode":"92127",
    "sg:province":"CA",
    "sg:tags":[
        "newsletter",
        "publish"
    ],
    "wof:name":"Crystal Report",
    "wof:placetype":"venue"
},
  "geometry": {"coordinates":[-117.126918,33.030112],"type":"Point"}
}