{
  "type": "Feature",
  "properties": {
    "iso:country":"US",
    "sg:address":"2000 W Orange Ave",
    "sg:city":"Anaheim",
    "sg:classifiers":[
        {
            "category":"Organizations",
            "subcategory":"Religious Organization",
            "type":"Services"
        }
    ],
    "sg:phone":"+1 714 826 0950",
    "sg:postcode":"92804",
    "sg:province":"CA",
    "wof:name":"Corporation of President of Th",
    "wof:placetype":"venue"
},
  "geometry": {"coordinates":[-117.952788,33.8251],"type":"Point"}
}