{
  "type": "Feature",
  "properties": {
    "addr:full":"9906 Carmel Mountain Rd San Diego CA 92129",
    "addr:housenumber":"9906",
    "addr:postcode":"92129",
    "addr:street":"Carmel Mountain Rd",
    "iso:country":"US",
    "sg:address":"9906 Carmel Mountain Rd",
    "sg:city":"San Diego",
    "sg:classifiers":[
        {
            "category":"Real Estate",
            "subcategory":"Real Estate Agent",
            "type":"Services"
        }
    ],
    "sg:phone":"+1 858 484 2930",
    "sg:postcode":"92129",
    "sg:province":"CA",
    "wof:name":"ERA",
    "wof:placetype":"venue"
},
  "geometry": {"coordinates":[-117.11520299999999,32.959894],"type":"Point"}
}