{
  "type": "Feature",
  "properties": {
    "iso:country":"US",
    "sg:address":"1595 Soquel Dr Suite 310",
    "sg:city":"Santa Cruz",
    "sg:classifiers":[
        {
            "category":"Health Services",
            "subcategory":"Doctor",
            "type":"Services"
        }
    ],
    "sg:phone":"+1 831 476 2626",
    "sg:postcode":"95065",
    "sg:province":"CA",
    "sg:website":"www.urocentersc.com",
    "wof:name":"Rosen Mark A MD",
    "wof:placetype":"venue"
},
  "geometry": {"coordinates":[-121.983108,36.988648],"type":"Point"}
}