{
  "type": "Feature",
  "properties": {
    "iso:country":"US",
    "sg:address":"2846 W 8th St Ste 204",
    "sg:city":"Los Angeles",
    "sg:classifiers":[
        {
            "category":"Health Services",
            "subcategory":"Health Practitioner",
            "type":"Services"
        }
    ],
    "sg:phone":"+1 213 252 1985",
    "sg:postcode":"90005",
    "sg:province":"CA",
    "sg:tags":[
        "acupuncture"
    ],
    "wof:name":"Multicare Health Center",
    "wof:placetype":"venue"
},
  "geometry": {"coordinates":[-118.288082,34.057602],"type":"Point"}
}