{
  "type": "Feature",
  "properties": {
    "iso:country":"US",
    "sg:address":"478 Sandy Way",
    "sg:city":"Benicia",
    "sg:classifiers":[
        {
            "category":"Shopping",
            "subcategory":"Used Merchandise",
            "type":"Retail Goods"
        }
    ],
    "sg:phone":"+1 707 745 4446",
    "sg:postcode":"94510",
    "sg:province":"CA",
    "sg:tags":[
        "antique"
    ],
    "wof:name":"Snook's Nook Old Toys",
    "wof:placetype":"venue"
},
  "geometry": {"coordinates":[-122.16073900000001,38.060987],"type":"Point"}
}