{
  "type": "Feature",
  "properties": {
    "iso:country":"US",
    "sg:address":"10067 Byrne Avenue",
    "sg:city":"Cupertino",
    "sg:classifiers":[
        {
            "category":"Personal",
            "type":"Services"
        }
    ],
    "sg:phone":"+1 408 289 1642",
    "sg:postcode":"95014",
    "sg:province":"CA",
    "sg:tags":[
        "home"
    ],
    "wof:name":"J.M. Appliance",
    "wof:placetype":"venue"
},
  "geometry": {"coordinates":[-122.059,37.32183],"type":"Point"}
}