{
  "type": "Feature",
  "properties": {
    "addr:full":"4722 Slauson Avenue Maywood CA 90270",
    "addr:housenumber":"4722",
    "addr:postcode":"90270",
    "addr:street":"Slauson Avenue",
    "iso:country":"US",
    "sg:address":"4722 Slauson Avenue",
    "sg:city":"Maywood",
    "sg:classifiers":[
        {
            "category":"Restaurant",
            "type":"Food & Drink"
        }
    ],
    "sg:phone":"+1 323 560 2379",
    "sg:postcode":"90270",
    "sg:province":"CA",
    "wof:name":"Apollo Burgers",
    "wof:placetype":"venue"
},
  "geometry": {"coordinates":[-118.180302,33.986535],"type":"Point"}
}