{
  "type": "Feature",
  "properties": {
    "addr:full":"38510 Madrone Rd Carmel Valley CA 93924",
    "addr:housenumber":"38510",
    "addr:postcode":"93924",
    "addr:street":"Madrone Rd",
    "iso:country":"US",
    "sg:address":"38510 Madrone Rd",
    "sg:city":"Carmel Valley",
    "sg:classifiers":[
        {
            "category":"Retail",
            "subcategory":"Auto Repair",
            "type":"Services"
        }
    ],
    "sg:phone":"+1 831 659 1627",
    "sg:postcode":"93924",
    "sg:province":"CA",
    "sg:tags":[
        "repairing",
        "automobile"
    ],
    "wof:name":"Carmel Valley Pump & Backflow",
    "wof:placetype":"venue"
},
  "geometry": {"coordinates":[-121.599695,36.379033],"type":"Point"}
}