{
  "type": "Feature",
  "properties": {
    "iso:country":"US",
    "sg:address":"625 W Olive Ave",
    "sg:city":"Merced",
    "sg:classifiers":[
        {
            "category":"Banks & Credit Unions",
            "subcategory":"Investment Brokerage",
            "type":"Services"
        }
    ],
    "sg:phone":"+1 209 383 5019",
    "sg:postcode":"95348",
    "sg:province":"CA",
    "sg:tags":[
        "security"
    ],
    "wof:name":"Edward Jones Co",
    "wof:placetype":"venue"
},
  "geometry": {"coordinates":[-120.480716,37.319342],"type":"Point"}
}