{
  "type": "Feature",
  "properties": {
    "iso:country":"US",
    "sg:address":"1129 Industrial Ave",
    "sg:city":"Petaluma",
    "sg:classifiers":[
        {
            "category":"Professional",
            "subcategory":"Computer Services",
            "type":"Services"
        }
    ],
    "sg:phone":"+1 707 766 1745",
    "sg:postcode":"94952",
    "sg:province":"CA",
    "sg:tags":[
        "software"
    ],
    "wof:name":"Brightmetrics",
    "wof:placetype":"venue"
},
  "geometry": {"coordinates":[-122.663101,38.263672],"type":"Point"}
}