{
  "type": "Feature",
  "properties": {
    "addr:full":"529 W Spruce Ave Inglewood CA 90301",
    "addr:housenumber":"529",
    "addr:postcode":"90301",
    "addr:street":"W Spruce Ave",
    "iso:country":"US",
    "sg:address":"529 W Spruce Ave",
    "sg:city":"Inglewood",
    "sg:classifiers":[
        {
            "category":"Professional",
            "type":"Services"
        }
    ],
    "sg:phone":"+1 310 673 6837",
    "sg:postcode":"90301",
    "sg:province":"CA",
    "wof:name":"Ramon Gonzales",
    "wof:placetype":"venue"
},
  "geometry": {"coordinates":[-118.365454,33.955089],"type":"Point"}
}