{
  "type": "Feature",
  "properties": {
    "iso:country":"US",
    "sg:address":"5745 Tujunga Ave",
    "sg:city":"North Hollywood",
    "sg:classifiers":[
        {
            "category":"Food & Beverages",
            "subcategory":"Liquor & Beverages",
            "type":"Retail Goods"
        }
    ],
    "sg:phone":"+1 818 766 4921",
    "sg:postcode":"91601",
    "sg:province":"CA",
    "sg:tags":[
        "beer",
        "spirit",
        "wine"
    ],
    "wof:name":"A & S Liquor Store",
    "wof:placetype":"venue"
},
  "geometry": {"coordinates":[-118.378998,34.175701],"type":"Point"}
}