{
  "type": "Feature",
  "properties": {
    "addr:full":"3440 Del Lago Blvd Escondido CA 92029",
    "addr:housenumber":"3440",
    "addr:postcode":"92029",
    "addr:street":"Del Lago Blvd",
    "iso:country":"US",
    "sg:address":"3440 Del Lago Blvd",
    "sg:city":"Escondido",
    "sg:classifiers":[
        {
            "category":"Coffee & Tea",
            "type":"Food & Drink"
        }
    ],
    "sg:menulink":"http://www.allmenus.com/ca/oceanside-escondido/110914-starbucks-coffee/menu/",
    "sg:phone":"+1 760 489 6550",
    "sg:postcode":"92029",
    "sg:province":"CA",
    "sg:tags":[
        "american"
    ],
    "wof:name":"Starbucks Coffee",
    "wof:placetype":"venue"
},
  "geometry": {"coordinates":[-117.071361,33.07109],"type":"Point"}
}