{
  "type": "Feature",
  "properties": {
    "iso:country":"US",
    "sg:address":"1739 Berkeley St",
    "sg:city":"Santa Monica",
    "sg:classifiers":[
        {
            "category":"Professional",
            "type":"Services"
        }
    ],
    "sg:phone":"+1 310 829 6965",
    "sg:postcode":"90404",
    "sg:province":"CA",
    "sg:tags":[
        "establishment"
    ],
    "wof:name":"Rist Robbie",
    "wof:placetype":"venue"
},
  "geometry": {"coordinates":[-118.463602,34.032488],"type":"Point"}
}