{
  "type": "Feature",
  "properties": {
    "iso:country":"US",
    "sg:address":"27311 La Paz Rd",
    "sg:city":"Laguna Niguel",
    "sg:classifiers":[
        {
            "category":"Home & Garden",
            "subcategory":"Carpets & Floor Coverings",
            "type":"Retail Goods"
        }
    ],
    "sg:phone":"+1 949 425 5900",
    "sg:postcode":"92677",
    "sg:province":"CA",
    "sg:tags":[
        "carpeting"
    ],
    "wof:name":"Tompkins Flooring",
    "wof:placetype":"venue"
},
  "geometry": {"coordinates":[-117.708,33.568802],"type":"Point"}
}