{
  "type": "Feature",
  "properties": {
    "iso:country":"US",
    "sg:address":"328 S Hayden Dr",
    "sg:city":"Escondido",
    "sg:classifiers":[
        {
            "category":"Wholesale",
            "subcategory":"Machinery & Supplies",
            "type":"Manufacturing & Wholesale Goods"
        }
    ],
    "sg:phone":"+1 760 743 5780",
    "sg:postcode":"92027",
    "sg:province":"CA",
    "sg:tags":[
        "equipment",
        "industrial"
    ],
    "wof:name":"Bbs Truck And Equipment Inc",
    "wof:placetype":"venue"
},
  "geometry": {"coordinates":[-117.036125,33.137928],"type":"Point"}
}