{
  "type": "Feature",
  "properties": {
    "addr:full":"11655 Ferris Rd El Monte CA 91732",
    "addr:housenumber":"11655",
    "addr:postcode":"91732",
    "addr:street":"Ferris Rd",
    "iso:country":"US",
    "sg:address":"11655 Ferris Rd",
    "sg:city":"El Monte",
    "sg:classifiers":[
        {
            "category":"Professional",
            "type":"Services"
        }
    ],
    "sg:phone":"+1 626 350 5777",
    "sg:postcode":"91732",
    "sg:province":"CA",
    "wof:name":"Vite Han",
    "wof:placetype":"venue"
},
  "geometry": {"coordinates":[-118.020768,34.073481],"type":"Point"}
}