{
  "type": "Feature",
  "properties": {
    "iso:country":"US",
    "sg:address":"8301 La Mesa Blvd",
    "sg:city":"La Mesa",
    "sg:classifiers":[
        {
            "category":"Shopping",
            "subcategory":"Pharmacy",
            "type":"Retail Goods"
        }
    ],
    "sg:phone":"+1 619 466 3246",
    "sg:postcode":"91941",
    "sg:province":"CA",
    "sg:tags":[
        "drugstore"
    ],
    "wof:name":"La Mesa Pharmacy",
    "wof:placetype":"venue"
},
  "geometry": {"coordinates":[-117.018997,32.765099],"type":"Point"}
}