{
  "type": "Feature",
  "properties": {
    "iso:country":"US",
    "sg:address":"375 Alabama St",
    "sg:city":"San Francisco",
    "sg:classifiers":[
        {
            "category":"Utilities",
            "subcategory":"Telephone",
            "type":"Services"
        }
    ],
    "sg:phone":"+1 415 934 2700",
    "sg:postcode":"94110",
    "sg:province":"CA",
    "sg:tags":[
        "communication",
        "radio",
        "except"
    ],
    "wof:name":"Aol",
    "wof:placetype":"venue"
},
  "geometry": {"coordinates":[-122.412292,37.765178],"type":"Point"}
}