{
  "type": "Feature",
  "properties": {
    "addr:full":"8090 Parkway Dr La Mesa CA 91942",
    "addr:housenumber":"8090",
    "addr:postcode":"91942",
    "addr:street":"Parkway Dr",
    "iso:country":"US",
    "sg:address":"8090 Parkway Dr",
    "sg:city":"La Mesa",
    "sg:classifiers":[
        {
            "category":"Health Services",
            "subcategory":"Clinic",
            "type":"Services"
        }
    ],
    "sg:phone":"+1 619 697 0018",
    "sg:postcode":"91942",
    "sg:province":"CA",
    "wof:name":"Us Healthworks",
    "wof:placetype":"venue"
},
  "geometry": {"coordinates":[-117.02613700000001,32.774531],"type":"Point"}
}