{
  "type": "Feature",
  "properties": {
    "addr:full":"3140 Telegraph Rd Ventura CA 93003",
    "addr:housenumber":"3140",
    "addr:postcode":"93003",
    "addr:street":"Telegraph Rd",
    "iso:country":"US",
    "sg:address":"3140 Telegraph Rd",
    "sg:city":"Ventura",
    "sg:classifiers":[
        {
            "category":"Banks & Credit Unions",
            "subcategory":"Bank",
            "type":"Services"
        }
    ],
    "sg:phone":"+1 805 644 5525",
    "sg:postcode":"93003",
    "sg:province":"CA",
    "sg:tags":[
        "escrow"
    ],
    "wof:name":"Lawyers Title",
    "wof:placetype":"venue"
},
  "geometry": {"coordinates":[-119.25193299999999,34.2724],"type":"Point"}
}