{
  "type": "Feature",
  "properties": {
    "addr:full":"269 Chirco Ave Santa Cruz CA 95065",
    "addr:housenumber":"269",
    "addr:postcode":"95065",
    "addr:street":"Chirco Ave",
    "iso:country":"US",
    "sg:address":"269 Chirco Ave",
    "sg:city":"Santa Cruz",
    "sg:classifiers":[
        {
            "category":"Professional",
            "type":"Services"
        }
    ],
    "sg:phone":"+1 831 251 1779",
    "sg:postcode":"95065",
    "sg:province":"CA",
    "wof:name":"Moniqe's Personal Care Svc",
    "wof:placetype":"venue"
},
  "geometry": {"coordinates":[-121.97629499999999,36.998929],"type":"Point"}
}