{
  "type": "Feature",
  "properties": {
    "iso:country":"US",
    "sg:address":"7459 Reese Rd",
    "sg:city":"Sacramento",
    "sg:phone":"+1 916 387 6591",
    "sg:postcode":"95828",
    "sg:province":"CA",
    "sg:website":"http://kampspropane.com",
    "wof:name":"Kamps Propane",
    "wof:placetype":"venue"
},
  "geometry": {"coordinates":[-121.396812,38.487415],"type":"Point"}
}