{
  "type": "Feature",
  "properties": {
    "addr:full":"2382 Crenshaw Blvd Suite 5, Providence Little Company of Mary Institute Torrance CA 90501",
    "addr:housenumber":"2382",
    "addr:postcode":"90501",
    "addr:street":"Crenshaw Blvd Suite 5 Providence",
    "iso:country":"US",
    "sg:address":"2382 Crenshaw Blvd Suite 5, Providence Little Company of Mary Institute",
    "sg:city":"Torrance",
    "sg:classifiers":[
        {
            "category":"Health Services",
            "subcategory":"Doctor",
            "type":"Services"
        },
        {
            "category":"Health Services",
            "subcategory":"Hospital",
            "type":"Services"
        }
    ],
    "sg:phone":"+1 310 618 9200",
    "sg:postcode":"90501",
    "sg:province":"CA",
    "sg:tags":[
        "medicine",
        "urgent",
        "internal",
        "care"
    ],
    "sg:website":"www.lcmweb.org/index.html",
    "wof:name":"Farah Ahamed, DO",
    "wof:placetype":"venue"
},
  "geometry": {"coordinates":[-118.32834699999999,33.822687],"type":"Point"}
}