{
  "type": "Feature",
  "properties": {
    "iso:country":"US",
    "sg:address":"1669 S.Main St. Bldg #4 , Milpitas,ca 460 Revere Terrace , Fremont ,Ca 94539",
    "sg:city":"Milpitas",
    "sg:classifiers":[
        {
            "category":"Health Services",
            "subcategory":"Clinic",
            "type":"Services"
        }
    ],
    "sg:phone":"+1 408 262 3411",
    "sg:postcode":"95035",
    "sg:province":"CA",
    "sg:tags":[
        "loss",
        "weight"
    ],
    "wof:name":"weightwise MD clinic",
    "wof:placetype":"venue"
},
  "geometry": {"coordinates":[-121.903002,37.406318],"type":"Point"}
}