{
  "type": "Feature",
  "properties": {
    "addr:full":"16 E Olive Ave Redlands CA 92373",
    "addr:housenumber":"16",
    "addr:postcode":"92373",
    "addr:street":"E Olive Ave",
    "iso:country":"US",
    "sg:address":"16 E Olive Ave",
    "sg:city":"Redlands",
    "sg:classifiers":[
        {
            "category":"Professional",
            "subcategory":"Lawyer & Legal Services",
            "type":"Services"
        }
    ],
    "sg:phone":"+1 909 792 2762",
    "sg:postcode":"92373",
    "sg:province":"CA",
    "sg:tags":[
        "attorney",
        "referral"
    ],
    "wof:name":"Legal Aid Clinic Of Redlands",
    "wof:placetype":"venue"
},
  "geometry": {"coordinates":[-117.18026999999999,34.053885],"type":"Point"}
}