{
  "type": "Feature",
  "properties": {
    "iso:country":"US",
    "sg:address":"433 Estudillo Ave",
    "sg:city":"San Leandro",
    "sg:classifiers":[
        {
            "category":"Health Services",
            "subcategory":"Dentist",
            "type":"Services"
        }
    ],
    "sg:phone":"+1 510 346 2600",
    "sg:postcode":"94577",
    "sg:province":"CA",
    "wof:name":"Wayman Tang DDS",
    "wof:placetype":"venue"
},
  "geometry": {"coordinates":[-122.151494,37.726052],"type":"Point"}
}