{
  "type": "Feature",
  "properties": {
    "iso:country":"US",
    "sg:address":"1300 S. El Camino suite 310",
    "sg:city":"San Mateo",
    "sg:classifiers":[
        {
            "category":"Professional",
            "type":"Services"
        }
    ],
    "sg:phone":"+1 800 782 1746",
    "sg:postcode":"94402",
    "sg:province":"CA",
    "wof:name":"SolveITLabs",
    "wof:placetype":"venue"
},
  "geometry": {"coordinates":[-122.31705700000001,37.554785],"type":"Point"}
}