{
  "type": "Feature",
  "properties": {
    "addr:full":"593 Glendale Blvd Los Angeles CA 90026",
    "addr:housenumber":"593",
    "addr:postcode":"90026",
    "addr:street":"Glendale Blvd",
    "iso:country":"US",
    "sg:address":"593 Glendale Blvd",
    "sg:city":"Los Angeles",
    "sg:classifiers":[
        {
            "category":"Communications",
            "subcategory":"Film & Video Production",
            "type":"Services"
        }
    ],
    "sg:phone":"+1 213 413 1333",
    "sg:postcode":"90026",
    "sg:province":"CA",
    "sg:tags":[
        "motion",
        "picture",
        "studio",
        "producer"
    ],
    "wof:name":"Jesse Lerner",
    "wof:placetype":"venue"
},
  "geometry": {"coordinates":[-118.261404,34.070002],"type":"Point"}
}