{
  "type": "Feature",
  "properties": {
    "addr:full":"904 N A St Oxnard CA 93030",
    "addr:housenumber":"904",
    "addr:postcode":"93030",
    "addr:street":"N A St",
    "iso:country":"US",
    "sg:address":"904 N A St",
    "sg:city":"Oxnard",
    "sg:classifiers":[
        {
            "category":"Personal",
            "subcategory":"Beauty Salon",
            "type":"Services"
        }
    ],
    "sg:phone":"+1 805 278 9464",
    "sg:postcode":"93030",
    "sg:province":"CA",
    "wof:name":"A St Haircutters",
    "wof:placetype":"venue"
},
  "geometry": {"coordinates":[-119.17845199999999,34.210691],"type":"Point"}
}