{
  "type": "Feature",
  "properties": {
    "addr:full":"15 Aviara Ct Napa CA 94558",
    "addr:housenumber":"15",
    "addr:postcode":"94558",
    "addr:street":"Aviara Ct",
    "iso:country":"US",
    "sg:address":"15 Aviara Ct",
    "sg:city":"Napa",
    "sg:classifiers":[
        {
            "category":"Health Services",
            "subcategory":"Podiatrist",
            "type":"Services"
        }
    ],
    "sg:phone":"+1 707 265 6333",
    "sg:postcode":"94558",
    "sg:province":"CA",
    "sg:tags":[
        "physician",
        "surgeons"
    ],
    "wof:name":"Napa Clinical Workshop",
    "wof:placetype":"venue"
},
  "geometry": {"coordinates":[-122.254654,38.35336],"type":"Point"}
}