{
  "type": "Feature",
  "properties": {
    "addr:full":"15930 Hesperian Blvd San Lorenzo CA 94580",
    "addr:housenumber":"15930",
    "addr:postcode":"94580",
    "addr:street":"Hesperian Blvd",
    "iso:country":"US",
    "sg:address":"15930 Hesperian Blvd",
    "sg:city":"San Lorenzo",
    "sg:classifiers":[
        {
            "category":"Restaurant",
            "type":"Food & Drink"
        }
    ],
    "sg:menulink":"http://www.allmenus.com/ca/hayward/89142-fishermans-hut/menu/",
    "sg:phone":"+1 510 278 3868",
    "sg:postcode":"94580",
    "sg:province":"CA",
    "sg:tags":[
        "seafood",
        "american"
    ],
    "wof:name":"Fisherman's Hut",
    "wof:placetype":"venue"
},
  "geometry": {"coordinates":[-122.12718599999999,37.680225],"type":"Point"}
}