{
  "type": "Feature",
  "properties": {
    "iso:country":"US",
    "sg:address":"39985 Big Bear Blvd",
    "sg:city":"Big Bear Lake",
    "sg:classifiers":[
        {
            "category":"Building & Trades",
            "subcategory":"Construction",
            "type":"Services"
        }
    ],
    "sg:phone":"+1 909 866 4855",
    "sg:postcode":"92315",
    "sg:province":"CA",
    "sg:tags":[
        "handyman"
    ],
    "wof:name":"Dwayne Haygood Handyman",
    "wof:placetype":"venue"
},
  "geometry": {"coordinates":[-116.929892,34.240179],"type":"Point"}
}