{
  "type": "Feature",
  "properties": {
    "iso:country":"US",
    "sg:address":"24342 Cardinal Pl",
    "sg:city":"Lake Forest",
    "sg:classifiers":[
        {
            "category":"Building & Trades",
            "subcategory":"Construction",
            "type":"Services"
        }
    ],
    "sg:phone":"+1 949 837 9226",
    "sg:postcode":"92630",
    "sg:province":"CA",
    "sg:tags":[
        "steam",
        "cleaning"
    ],
    "sg:website":"www.cleanriteservices.com",
    "wof:name":"Clean Rite Svc",
    "wof:placetype":"venue"
},
  "geometry": {"coordinates":[-117.70647200000001,33.642453],"type":"Point"}
}