{
  "type": "Feature",
  "properties": {
    "addr:full":"7100 Convoy Ct San Diego CA 92117",
    "addr:housenumber":"7100",
    "addr:postcode":"92117",
    "addr:street":"Convoy Ct",
    "iso:country":"US",
    "sg:address":"7100 Convoy Ct",
    "sg:city":"San Diego",
    "sg:classifiers":[
        {
            "category":"Manufacturing",
            "subcategory":"Printing",
            "type":"Manufacturing & Wholesale Goods"
        }
    ],
    "sg:phone":"+1 858 278 0707",
    "sg:postcode":"92117",
    "sg:province":"CA",
    "sg:tags":[
        "printer"
    ],
    "wof:name":"Graphic Communications Inc",
    "wof:placetype":"venue"
},
  "geometry": {"coordinates":[-117.15925900000001,32.834705],"type":"Point"}
}