{
  "type": "Feature",
  "properties": {
    "addr:full":"2200 Chandler Dr Tustin CA 92782",
    "addr:housenumber":"2200",
    "addr:postcode":"92782",
    "addr:street":"Chandler Dr",
    "iso:country":"US",
    "sg:address":"2200 Chandler Dr",
    "sg:city":"Tustin",
    "sg:classifiers":[
        {
            "category":"Recreation",
            "type":"Entertainment"
        }
    ],
    "sg:phone":"+1 714 730 5665",
    "sg:postcode":"92782",
    "sg:province":"CA",
    "sg:tags":[
        "club",
        "membership"
    ],
    "wof:name":"Princess Club",
    "wof:placetype":"venue"
},
  "geometry": {"coordinates":[-117.78752,33.74406],"type":"Point"}
}