{
  "type": "Feature",
  "properties": {
    "addr:full":"2920 Selwyn Cir Santa Barbara CA 93105",
    "addr:housenumber":"2920",
    "addr:postcode":"93105",
    "addr:street":"Selwyn Cir",
    "iso:country":"US",
    "sg:address":"2920 Selwyn Cir",
    "sg:city":"Santa Barbara",
    "sg:classifiers":[
        {
            "category":"Professional",
            "subcategory":"Management & Consulting",
            "type":"Services"
        }
    ],
    "sg:phone":"+1 805 682 4579",
    "sg:postcode":"93105",
    "sg:province":"CA",
    "sg:tags":[
        "consultant",
        "business"
    ],
    "wof:name":"Renaissance Management Cnsltnt",
    "wof:placetype":"venue"
},
  "geometry": {"coordinates":[-119.722528,34.449104],"type":"Point"}
}