{
  "type": "Feature",
  "properties": {
    "iso:country":"US",
    "sg:address":"6601 Owens Dr",
    "sg:city":"Pleasanton",
    "sg:classifiers":[
        {
            "category":"Banks & Credit Unions",
            "subcategory":"Bank",
            "type":"Services"
        }
    ],
    "sg:phone":"+1 925 737 0277",
    "sg:postcode":"94588",
    "sg:province":"CA",
    "sg:tags":[
        "loan",
        "real estate"
    ],
    "wof:name":"Metrociti Mortgage",
    "wof:placetype":"venue"
},
  "geometry": {"coordinates":[-121.909469,37.697379],"type":"Point"}
}