{
  "type": "Feature",
  "properties": {
    "addr:full":"991 Lincoln Way Auburn CA 95603",
    "addr:housenumber":"991",
    "addr:postcode":"ca 95603",
    "addr:street":"Lincoln Way",
    "iso:country":"US",
    "sg:address":"991 Lincoln Way",
    "sg:city":"Auburn",
    "sg:classifiers":[
        {
            "category":"Social Services",
            "type":"Services"
        }
    ],
    "sg:phone":"+1 530 885 0441",
    "sg:postcode":"95603",
    "sg:province":"CA",
    "sg:tags":[
        "counselor",
        "marriage",
        "family"
    ],
    "sg:website":"www.sierrafamily.org",
    "wof:name":"Sierra Family Svc",
    "wof:placetype":"venue"
},
  "geometry": {"coordinates":[-121.071854,38.898373],"type":"Point"}
}