{
  "type": "Feature",
  "properties": {
    "iso:country":"US",
    "sg:address":"22678 Black Hawk Dr",
    "sg:city":"Twain Harte",
    "sg:classifiers":[
        {
            "category":"Travel",
            "subcategory":"Hotels & Motels",
            "type":"Entertainment"
        }
    ],
    "sg:phone":"+1 209 586 4479",
    "sg:postcode":"95383",
    "sg:province":"CA",
    "wof:name":"El Dorado Motel",
    "wof:placetype":"venue"
},
  "geometry": {"coordinates":[-120.230559,38.035443],"type":"Point"}
}