{
  "type": "Feature",
  "properties": {
    "iso:country":"US",
    "sg:address":"600 Sequoia Pacific Blvd",
    "sg:city":"Sacramento",
    "sg:classifiers":[
        {
            "category":"Manufacturing",
            "subcategory":"Motor Vehicles & Parts",
            "type":"Manufacturing & Wholesale Goods"
        }
    ],
    "sg:phone":"+1 916 446 4666",
    "sg:postcode":"95811",
    "sg:province":"CA",
    "sg:tags":[
        "automobile",
        "supply"
    ],
    "wof:name":"Auto Parts Wholesale",
    "wof:placetype":"venue"
},
  "geometry": {"coordinates":[-121.497426,38.597207],"type":"Point"}
}