{
  "type": "Feature",
  "properties": {
    "iso:country":"US",
    "sg:address":"731 Howard St",
    "sg:city":"Marina Del Rey",
    "sg:classifiers":[
        {
            "category":"Professional",
            "subcategory":"Business Services",
            "type":"Services"
        }
    ],
    "sg:phone":"+1 310 306 0632",
    "sg:postcode":"90292",
    "sg:province":"CA",
    "sg:tags":[
        "fixed",
        "motor",
        "freight",
        "facility"
    ],
    "wof:name":"Apple Home Inspection",
    "wof:placetype":"venue"
},
  "geometry": {"coordinates":[-118.452471,33.986889],"type":"Point"}
}