{
  "type": "Feature",
  "properties": {
    "addr:full":"4451 California Ave Bakersfield CA 93309",
    "addr:housenumber":"4451",
    "addr:postcode":"93309",
    "addr:street":"California Ave",
    "iso:country":"US",
    "sg:address":"4451 California Ave",
    "sg:city":"Bakersfield",
    "sg:classifiers":[
        {
            "category":"Real Estate",
            "subcategory":"Real Estate Operator",
            "type":"Services"
        }
    ],
    "sg:phone":"+1 661 325 4942",
    "sg:postcode":"93309",
    "sg:province":"CA",
    "sg:tags":[
        "building",
        "apartment"
    ],
    "wof:name":"California Apartments",
    "wof:placetype":"venue"
},
  "geometry": {"coordinates":[-119.04965900000001,35.36722],"type":"Point"}
}