{
  "type": "Feature",
  "properties": {
    "iso:country":"US",
    "sg:address":"830 E Washington Blvd",
    "sg:city":"Los Angeles",
    "sg:classifiers":[
        {
            "category":"Restaurant",
            "type":"Food & Drink"
        }
    ],
    "sg:phone":"+1 213 747 3352",
    "sg:postcode":"90021",
    "sg:province":"CA",
    "wof:name":"Gayle's Famous Burgers",
    "wof:placetype":"venue"
},
  "geometry": {"coordinates":[-118.254997,34.026501],"type":"Point"}
}