{
  "type": "Feature",
  "properties": {
    "iso:country":"US",
    "sg:address":"41817 Driver Ln",
    "sg:city":"Temecula",
    "sg:classifiers":[
        {
            "category":"Wholesale",
            "subcategory":"Construction Materials",
            "type":"Manufacturing & Wholesale Goods"
        },
        {
            "category":"Home & Garden",
            "subcategory":"Building Materials",
            "type":"Retail Goods"
        }
    ],
    "sg:phone":"+1 951 693 2245",
    "sg:postcode":"92591",
    "sg:province":"CA",
    "sg:tags":[
        "windows-wholesale",
        "window",
        "manufacturer"
    ],
    "wof:name":"Mr Clean Window Solution",
    "wof:placetype":"venue"
},
  "geometry": {"coordinates":[-117.118759,33.511501],"type":"Point"}
}