{
  "type": "Feature",
  "properties": {
    "iso:country":"US",
    "sg:address":"6300 Irvine Blvd",
    "sg:city":"Irvine",
    "sg:classifiers":[
        {
            "category":"Cinema",
            "subcategory":"Movie Theater",
            "type":"Entertainment"
        }
    ],
    "sg:phone":"+1 949 559 1739",
    "sg:postcode":"92620",
    "sg:province":"CA",
    "sg:website":"www.redbox.com",
    "wof:name":"Redbox",
    "wof:placetype":"venue"
},
  "geometry": {"coordinates":[-117.73737,33.697812],"type":"Point"}
}