{
  "type": "Feature",
  "properties": {
    "iso:country":"US",
    "sg:address":"289 Vernon Way",
    "sg:city":"El Cajon",
    "sg:classifiers":[
        {
            "category":"Professional",
            "subcategory":"Accounting & Tax Preparation",
            "type":"Services"
        }
    ],
    "sg:phone":"+1 619 440 7559",
    "sg:postcode":"92020",
    "sg:province":"CA",
    "sg:tags":[
        "accountant"
    ],
    "wof:name":"Robert Bednar CPA",
    "wof:placetype":"venue"
},
  "geometry": {"coordinates":[-116.964374,32.81222],"type":"Point"}
}