{
  "type": "Feature",
  "properties": {
    "addr:full":"17514 Ventura Blvd Encino CA 91316",
    "addr:housenumber":"17514",
    "addr:postcode":"91316",
    "addr:street":"Ventura Blvd",
    "iso:country":"US",
    "sg:address":"17514 Ventura Blvd",
    "sg:city":"Encino",
    "sg:classifiers":[
        {
            "category":"Wholesale",
            "subcategory":"Machinery & Supplies",
            "type":"Manufacturing & Wholesale Goods"
        }
    ],
    "sg:phone":"+1 818 385 0454",
    "sg:postcode":"91316",
    "sg:province":"CA",
    "sg:tags":[
        "equipment",
        "laundry"
    ],
    "wof:name":"California Laundry Svc",
    "wof:placetype":"venue"
},
  "geometry": {"coordinates":[-118.51689,34.161901],"type":"Point"}
}