{
  "type": "Feature",
  "properties": {
    "addr:full":"8777 San Ysidro Ave Gilroy CA 95020",
    "addr:housenumber":"8777",
    "addr:postcode":"95020",
    "addr:street":"San Ysidro Ave",
    "iso:country":"US",
    "sg:address":"8777 San Ysidro Ave",
    "sg:city":"Gilroy",
    "sg:classifiers":[
        {
            "category":"Home & Garden",
            "subcategory":"Furniture",
            "type":"Retail Goods"
        }
    ],
    "sg:phone":"+1 408 846 5300",
    "sg:postcode":"95020",
    "sg:province":"CA",
    "sg:tags":[
        "mattress"
    ],
    "wof:name":"Macini's Sleepworld",
    "wof:placetype":"venue"
},
  "geometry": {"coordinates":[-121.567908,37.027995],"type":"Point"}
}