{
  "type": "Feature",
  "properties": {
    "iso:country":"US",
    "sg:address":"16400 Woodruff Ave",
    "sg:city":"Bellflower",
    "sg:classifiers":[
        {
            "category":"Education",
            "subcategory":"Preschool",
            "type":"Public Place"
        },
        {
            "category":"Education",
            "subcategory":"School",
            "type":"Public Place"
        }
    ],
    "sg:phone":"+1 562 867 8594",
    "sg:postcode":"90706",
    "sg:province":"CA",
    "sg:tags":[
        "high",
        "middle",
        "elementary"
    ],
    "sg:website":"www.southlandca.org",
    "wof:name":"Southland Christian Academy And Preschool",
    "wof:placetype":"venue"
},
  "geometry": {"coordinates":[-118.11730900000001,33.885765],"type":"Point"}
}