{
  "type": "Feature",
  "properties": {
    "addr:full":"265 E Stetson Ave Hemet CA 92543",
    "addr:housenumber":"265",
    "addr:postcode":"92543",
    "addr:street":"E Stetson Ave",
    "iso:country":"US",
    "sg:address":"265 E Stetson Ave",
    "sg:city":"Hemet",
    "sg:classifiers":[
        {
            "category":"Home & Garden",
            "subcategory":"Home Furnishings",
            "type":"Retail Goods"
        },
        {
            "category":"Home & Garden",
            "subcategory":"Carpets & Floor Coverings",
            "type":"Retail Goods"
        },
        {
            "category":"Wholesale",
            "subcategory":"Construction Materials",
            "type":"Manufacturing & Wholesale Goods"
        },
        {
            "category":"Wholesale",
            "subcategory":"Home Furnishings",
            "type":"Manufacturing & Wholesale Goods"
        }
    ],
    "sg:phone":"+1 951 765 0935",
    "sg:postcode":"92543",
    "sg:province":"CA",
    "sg:tags":[
        "set",
        "supply",
        "mattresses-wholesale",
        "bed",
        "mattress",
        "makers'",
        "bedroom",
        "manufacturer"
    ],
    "wof:name":"Rest Ez Mattress Co",
    "wof:placetype":"venue"
},
  "geometry": {"coordinates":[-116.96953999999999,33.729398],"type":"Point"}
}