{
  "type": "Feature",
  "properties": {
    "addr:full":"4225 Pepsi Pl Stockton CA 95215",
    "addr:housenumber":"4225",
    "addr:postcode":"95215",
    "addr:street":"Pepsi Pl",
    "iso:country":"US",
    "sg:address":"4225 Pepsi Pl",
    "sg:city":"Stockton",
    "sg:classifiers":[
        {
            "category":"Freight",
            "type":"Transportation"
        }
    ],
    "sg:phone":"+1 209 931 7200",
    "sg:postcode":"95215",
    "sg:province":"CA",
    "sg:tags":[
        "warehouse",
        "cold",
        "storage",
        "distribution"
    ],
    "wof:name":"Pepsico",
    "wof:placetype":"venue"
},
  "geometry": {"coordinates":[-121.24794,37.989186],"type":"Point"}
}