{
  "type": "Feature",
  "properties": {
    "iso:country":"US",
    "sg:address":"751 W Daily Dr",
    "sg:city":"Camarillo",
    "sg:classifiers":[
        {
            "category":"Restaurant",
            "type":"Food & Drink"
        }
    ],
    "sg:phone":"+1 805 482 6350",
    "sg:postcode":"93010",
    "sg:province":"CA",
    "sg:tags":[
        "shop",
        "coffee"
    ],
    "wof:name":"Starbucks",
    "wof:placetype":"venue"
},
  "geometry": {"coordinates":[-119.09187,34.221206],"type":"Point"}
}