{
  "type": "Feature",
  "properties": {
    "addr:full":"3300 Irvine Ave Ste 261 Newport Beach CA 92660",
    "addr:housenumber":"3300",
    "addr:postcode":"92660",
    "addr:street":"Irvine Ave Ste 261",
    "iso:country":"US",
    "sg:address":"3300 Irvine Ave Ste 261",
    "sg:city":"Newport Beach",
    "sg:classifiers":[
        {
            "category":"Professional",
            "subcategory":"Computer Services",
            "type":"Services"
        }
    ],
    "sg:phone":"+1 949 222 2287",
    "sg:postcode":"92660",
    "sg:province":"CA",
    "sg:tags":[
        "repair"
    ],
    "wof:name":"Network Dynamics Corporation",
    "wof:placetype":"venue"
},
  "geometry": {"coordinates":[-117.878998,33.659599],"type":"Point"}
}