{
  "type": "Feature",
  "properties": {
    "addr:full":"1716 N 11th Ave Hanford CA 93230",
    "addr:housenumber":"1716",
    "addr:postcode":"ca 93230",
    "addr:street":"N 11Th Ave",
    "iso:country":"US",
    "sg:address":"1716 N 11th Ave",
    "sg:city":"Hanford",
    "sg:classifiers":[
        {
            "category":"Personal",
            "subcategory":"Beauty Salon",
            "type":"Services"
        }
    ],
    "sg:phone":"+1 559 583 1333",
    "sg:postcode":"93230",
    "sg:province":"CA",
    "wof:name":"Shear Magic Inc",
    "wof:placetype":"venue"
},
  "geometry": {"coordinates":[-119.655243,36.343406],"type":"Point"}
}