{
  "type": "Feature",
  "properties": {
    "addr:full":"10512 Crawford Canyon Rd Santa Ana CA 92705",
    "addr:housenumber":"10512",
    "addr:postcode":"92705",
    "addr:street":"Crawford Canyon Rd",
    "iso:country":"US",
    "sg:address":"10512 Crawford Canyon Rd",
    "sg:city":"Santa Ana",
    "sg:classifiers":[
        {
            "category":"Education",
            "subcategory":"School",
            "type":"Public Place"
        }
    ],
    "sg:phone":"+1 714 532 8091",
    "sg:postcode":"92705",
    "sg:province":"CA",
    "sg:tags":[
        "high",
        "middle",
        "elementary"
    ],
    "wof:name":"Panorama Elementary School",
    "wof:placetype":"venue"
},
  "geometry": {"coordinates":[-117.792,33.7798],"type":"Point"}
}