{
  "type": "Feature",
  "properties": {
    "iso:country":"US",
    "sg:address":"1448 E 15th St",
    "sg:city":"Los Angeles",
    "sg:classifiers":[
        {
            "category":"Professional",
            "subcategory":"Employment Agencies",
            "type":"Services"
        }
    ],
    "sg:phone":"+1 213 487 1020",
    "sg:postcode":"90021",
    "sg:province":"CA",
    "sg:tags":[
        "opportunity"
    ],
    "wof:name":"Systematics EDP Agency",
    "wof:placetype":"venue"
},
  "geometry": {"coordinates":[-118.24661,34.026551],"type":"Point"}
}