{
  "type": "Feature",
  "properties": {
    "addr:full":"3626 11th Ave Los Angeles CA 90018",
    "addr:housenumber":"3626",
    "addr:postcode":"90018",
    "addr:street":"11Th Ave",
    "iso:country":"US",
    "sg:address":"3626 11th Ave",
    "sg:city":"Los Angeles",
    "sg:classifiers":[
        {
            "category":"Wholesale",
            "subcategory":"Groceries",
            "type":"Manufacturing & Wholesale Goods"
        }
    ],
    "sg:phone":"+1 323 731 8223",
    "sg:postcode":"90018",
    "sg:province":"CA",
    "sg:tags":[
        "grocer",
        "merchandise",
        "general"
    ],
    "sg:website":"www.uwgrocers.com",
    "wof:name":"Unified Western Grocers Inc",
    "wof:placetype":"venue"
},
  "geometry": {"coordinates":[-118.32946800000001,34.021947],"type":"Point"}
}