{
  "type": "Feature",
  "properties": {
    "iso:country":"US",
    "sg:address":"44 Montgomery St",
    "sg:city":"San Francisco",
    "sg:classifiers":[
        {
            "category":"Professional",
            "subcategory":"Management & Consulting",
            "type":"Services"
        }
    ],
    "sg:phone":"+1 415 986 4422",
    "sg:postcode":"94104",
    "sg:province":"CA",
    "sg:tags":[
        "print",
        "medium",
        "counselor",
        "relation",
        "public"
    ],
    "sg:website":"www.businesswire.com",
    "wof:name":"Business Wire",
    "wof:placetype":"venue"
},
  "geometry": {"coordinates":[-122.402095,37.78955],"type":"Point"}
}