{
  "type": "Feature",
  "properties": {
    "addr:full":"530 Shoreline Hwy Mill Valley CA 94941",
    "addr:housenumber":"530",
    "addr:postcode":"94941",
    "addr:street":"Shoreline Hwy",
    "iso:country":"US",
    "sg:address":"530 Shoreline Hwy",
    "sg:city":"Mill Valley",
    "sg:classifiers":[
        {
            "category":"Building & Trades",
            "subcategory":"Landscaping Services",
            "type":"Services"
        }
    ],
    "sg:phone":"+1 415 388 9017",
    "sg:postcode":"94941",
    "sg:province":"CA",
    "sg:tags":[
        "tree"
    ],
    "wof:name":"Shoreline Tree Svc",
    "wof:placetype":"venue"
},
  "geometry": {"coordinates":[-122.538253,37.88198],"type":"Point"}
}