{
  "type": "Feature",
  "properties": {
    "addr:full":"8430 On The Mall Buena Park CA 90620",
    "addr:postcode":"90620",
    "addr:street":"The Mall",
    "iso:country":"US",
    "sg:address":"8430 On The Mall",
    "sg:city":"Buena Park",
    "sg:classifiers":[
        {
            "category":"Sports & Exercise",
            "subcategory":"Gym",
            "type":"Entertainment"
        }
    ],
    "sg:phone":"+1 714 236 1800",
    "sg:postcode":"90620",
    "sg:province":"CA",
    "sg:website":"www.24hourfitness.com",
    "wof:name":"24 Hour Fitness",
    "wof:placetype":"venue"
},
  "geometry": {"coordinates":[-117.99057999999999,33.846193],"type":"Point"}
}