{
  "type": "Feature",
  "properties": {
    "addr:full":"2734 E Chapman Ave Orange CA 92869",
    "addr:housenumber":"2734",
    "addr:postcode":"92869",
    "addr:street":"E Chapman Ave",
    "iso:country":"US",
    "sg:address":"2734 E Chapman Ave",
    "sg:city":"Orange",
    "sg:classifiers":[
        {
            "category":"Retail",
            "subcategory":"Repair Shop",
            "type":"Services"
        }
    ],
    "sg:phone":"+1 714 997 4029",
    "sg:postcode":"92869",
    "sg:province":"CA",
    "sg:tags":[
        "jewelry"
    ],
    "wof:name":"Clock Master",
    "wof:placetype":"venue"
},
  "geometry": {"coordinates":[-117.82410299999999,33.787726],"type":"Point"}
}