{
  "type": "Feature",
  "properties": {
    "addr:full":"6420 Freeport Blvd Sacramento CA 95822",
    "addr:housenumber":"6420",
    "addr:postcode":"95822",
    "addr:street":"Freeport Blvd",
    "iso:country":"US",
    "sg:address":"6420 Freeport Blvd",
    "sg:city":"Sacramento",
    "sg:classifiers":[
        {
            "category":"Shopping",
            "subcategory":"Pets & Pet Supplies",
            "type":"Retail Goods"
        },
        {
            "category":"Retail",
            "subcategory":"Veterinary Services",
            "type":"Services"
        },
        {
            "category":"Retail",
            "subcategory":"Animal Services",
            "type":"Services"
        }
    ],
    "sg:phone":"+1 916 428 9202",
    "sg:postcode":"95822",
    "sg:province":"CA",
    "sg:tags":[
        "groomers",
        "emergency",
        "hospital",
        "specialty",
        "clinic",
        "veterinarian"
    ],
    "sg:website":"www.muellerpmc.com",
    "wof:name":"Mueller Pet Medical Center",
    "wof:placetype":"venue"
},
  "geometry": {"coordinates":[-121.502876,38.509663],"type":"Point"}
}