{
  "type": "Feature",
  "properties": {
    "addr:full":"714 Nash Ave Menlo Park CA 94025",
    "addr:housenumber":"714",
    "addr:postcode":"94025",
    "addr:street":"Nash Ave",
    "iso:country":"US",
    "sg:address":"714 Nash Ave",
    "sg:city":"Menlo Park",
    "sg:classifiers":[
        {
            "category":"Manufacturing",
            "subcategory":"Printing",
            "type":"Manufacturing & Wholesale Goods"
        }
    ],
    "sg:phone":"+1 650 328 4736",
    "sg:postcode":"94025",
    "sg:province":"CA",
    "sg:tags":[
        "bookbinder"
    ],
    "wof:name":"Syntagma Book Restoration",
    "wof:placetype":"venue"
},
  "geometry": {"coordinates":[-122.16448,37.459817],"type":"Point"}
}