{
  "type": "Feature",
  "properties": {
    "iso:country":"US",
    "sg:address":"41928 Tilton Dr",
    "sg:city":"Palmdale",
    "sg:classifiers":[
        {
            "category":"Autos & Motor Vehicles",
            "subcategory":"Motorcycle Sales",
            "type":"Retail Goods"
        }
    ],
    "sg:phone":"+1 661 943 0322",
    "sg:postcode":"93551",
    "sg:province":"CA",
    "sg:tags":[
        "scooter"
    ],
    "wof:name":"K L Racing",
    "wof:placetype":"venue"
},
  "geometry": {"coordinates":[-118.25770900000001,34.644861],"type":"Point"}
}