{
  "type": "Feature",
  "properties": {
    "iso:country":"US",
    "sg:address":"6657 El Colegio Rd Apt 2",
    "sg:city":"Goleta",
    "sg:classifiers":[
        {
            "category":"Real Estate",
            "subcategory":"Real Estate Services",
            "type":"Services"
        },
        {
            "category":"Real Estate",
            "subcategory":"Real Estate Operator",
            "type":"Services"
        }
    ],
    "sg:phone":"+1 805 968 3912",
    "sg:postcode":"93117",
    "sg:province":"CA",
    "sg:tags":[
        "apartment",
        "vacancy",
        "listing",
        "rental",
        "finder"
    ],
    "wof:name":"Westwinds Apartments",
    "wof:placetype":"venue"
},
  "geometry": {"coordinates":[-119.860741,34.417301],"type":"Point"}
}