{
  "type": "Feature",
  "properties": {
    "addr:full":"6825 Barcelona Way Riverside CA 92504",
    "addr:housenumber":"6825",
    "addr:postcode":"92504",
    "addr:street":"Barcelona Way",
    "iso:country":"US",
    "sg:address":"6825 Barcelona Way",
    "sg:city":"Riverside",
    "sg:classifiers":[
        {
            "category":"Home & Garden",
            "subcategory":"Household Appliances",
            "type":"Retail Goods"
        }
    ],
    "sg:phone":"+1 951 689 8575",
    "sg:postcode":"92504",
    "sg:province":"CA",
    "wof:name":"Leonard's Installation",
    "wof:placetype":"venue"
},
  "geometry": {"coordinates":[-117.414314,33.948371],"type":"Point"}
}