{
  "type": "Feature",
  "properties": {
    "addr:full":"1441 W Knox St Ste 400 Torrance CA 90501",
    "addr:housenumber":"1441",
    "addr:postcode":"90501",
    "addr:street":"W Knox St Ste 400",
    "iso:country":"US",
    "sg:address":"1441 W Knox St Ste 400",
    "sg:city":"Torrance",
    "sg:classifiers":[
        {
            "category":"Restaurant",
            "type":"Food & Drink"
        }
    ],
    "sg:phone":"+1 310 212 7808",
    "sg:postcode":"90501",
    "sg:province":"CA",
    "sg:tags":[
        "greek",
        "mediterranean"
    ],
    "wof:name":"BJ's Grill",
    "wof:placetype":"venue"
},
  "geometry": {"coordinates":[-118.300675,33.854204],"type":"Point"}
}