{
  "type": "Feature",
  "properties": {
    "addr:full":"308 San Miguel Ct Milpitas CA 95035",
    "addr:housenumber":"308",
    "addr:postcode":"95035",
    "addr:street":"San Miguel Ct",
    "iso:country":"US",
    "sg:address":"308 San Miguel Ct",
    "sg:city":"Milpitas",
    "sg:classifiers":[
        {
            "category":"Building & Trades",
            "subcategory":"Landscaping Services",
            "type":"Services"
        }
    ],
    "sg:phone":"+1 408 263 4162",
    "sg:postcode":"95035",
    "sg:province":"CA",
    "sg:tags":[
        "landscape",
        "contractor"
    ],
    "wof:name":"Lamas Gardening",
    "wof:placetype":"venue"
},
  "geometry": {"coordinates":[-121.91121,37.42451],"type":"Point"}
}