{
  "type": "Feature",
  "properties": {
    "addr:full":"5580 La Jolla Blvd. San Diego CA 92037",
    "addr:housenumber":"5580",
    "addr:postcode":"92037",
    "addr:street":"La Jolla Blvd.",
    "iso:country":"US",
    "sg:address":"5580 La Jolla Blvd.",
    "sg:city":"San Diego",
    "sg:classifiers":[
        {
            "category":"Autos & Motor Vehicles",
            "subcategory":"Automobile Sales",
            "type":"Retail Goods"
        }
    ],
    "sg:phone":"+1 619 228 3035",
    "sg:postcode":"92037",
    "sg:province":"CA",
    "sg:tags":[
        "limo"
    ],
    "sg:website":"www.mibtransportation.com",
    "wof:name":"San Diego Airport Limo",
    "wof:placetype":"venue"
},
  "geometry": {"coordinates":[-117.269447,32.81364],"type":"Point"}
}