{
  "type": "Feature",
  "properties": {
    "iso:country":"US",
    "sg:address":"11392 Ventura Blvd",
    "sg:city":"Studio City",
    "sg:classifiers":[
        {
            "category":"Shopping",
            "subcategory":"Pets & Pet Supplies",
            "type":"Retail Goods"
        }
    ],
    "sg:phone":"+1 818 762 0776",
    "sg:postcode":"91604",
    "sg:province":"CA",
    "sg:tags":[
        "groomers"
    ],
    "wof:name":"Splash Ur Doggy",
    "wof:placetype":"venue"
},
  "geometry": {"coordinates":[-118.378874,34.139899],"type":"Point"}
}