{
  "type": "Feature",
  "properties": {
    "iso:country":"US",
    "sg:address":"522 N Franklin St",
    "sg:city":"Fort Bragg",
    "sg:classifiers":[
        {
            "category":"Insurance",
            "subcategory":"Insurance Agent",
            "type":"Services"
        }
    ],
    "sg:phone":"+1 707 964 1271",
    "sg:postcode":"95437",
    "sg:province":"CA",
    "wof:name":"Northwest Insurance Inc",
    "wof:placetype":"venue"
},
  "geometry": {"coordinates":[-123.804452,39.447745],"type":"Point"}
}