{
  "type": "Feature",
  "properties": {
    "addr:full":"221 Market St Needles CA 92363",
    "addr:housenumber":"221",
    "addr:postcode":"92363",
    "addr:street":"Market St",
    "iso:country":"US",
    "sg:address":"221 Market St",
    "sg:city":"Needles",
    "sg:classifiers":[
        {
            "category":"Retail",
            "subcategory":"Laundry & Dry Cleaning",
            "type":"Services"
        }
    ],
    "sg:phone":"+1 760 326 2848",
    "sg:postcode":"92363",
    "sg:province":"CA",
    "sg:tags":[
        "cleaners",
        "upholstery"
    ],
    "wof:name":"Chavez Carpet Cleaning Svc",
    "wof:placetype":"venue"
},
  "geometry": {"coordinates":[-114.612146,34.847545],"type":"Point"}
}