{
  "type": "Feature",
  "properties": {
    "iso:country":"US",
    "sg:address":"2810 Rio Linda Blvd",
    "sg:city":"Sacramento",
    "sg:classifiers":[
        {
            "category":"Retail",
            "subcategory":"Auto Repair",
            "type":"Services"
        }
    ],
    "sg:phone":"+1 916 649 2245",
    "sg:postcode":"95815",
    "sg:province":"CA",
    "sg:tags":[
        "repairing",
        "automobile"
    ],
    "wof:name":"Pino's Automotive Repair",
    "wof:placetype":"venue"
},
  "geometry": {"coordinates":[-121.446083,38.619999],"type":"Point"}
}