{
  "type": "Feature",
  "properties": {
    "iso:country":"US",
    "sg:address":"3010 Lafayette Road",
    "sg:city":"Newport Beach",
    "sg:classifiers":[
        {
            "category":"Restaurant",
            "type":"Food & Drink"
        }
    ],
    "sg:phone":"+1 949 566 0060",
    "sg:postcode":"92663",
    "sg:province":"CA",
    "sg:website":"www.cannerynewport.com",
    "wof:name":"Cannery Seafood of the Pacific",
    "wof:placetype":"venue"
},
  "geometry": {"coordinates":[-117.927438,33.614747],"type":"Point"}
}