{
  "type": "Feature",
  "properties": {
    "addr:full":"259 Clara St San Francisco CA 94107",
    "addr:housenumber":"259",
    "addr:postcode":"94107",
    "addr:street":"Clara St",
    "iso:country":"US",
    "sg:address":"259 Clara St",
    "sg:city":"San Francisco",
    "sg:classifiers":[
        {
            "category":"Professional",
            "subcategory":"Art Services",
            "type":"Services"
        }
    ],
    "sg:phone":"+1 415 495 3556",
    "sg:postcode":"94107",
    "sg:province":"CA",
    "sg:tags":[
        "photographer"
    ],
    "wof:name":"Stephen Rahn Photography",
    "wof:placetype":"venue"
},
  "geometry": {"coordinates":[-122.40351,37.778687],"type":"Point"}
}