{
  "type": "Feature",
  "properties": {
    "addr:full":"1115 Stratford Ave Dixon CA 95620",
    "addr:housenumber":"1115",
    "addr:postcode":"95620",
    "addr:street":"Stratford Ave",
    "iso:country":"US",
    "sg:address":"1115 Stratford Ave",
    "sg:city":"Dixon",
    "sg:classifiers":[
        {
            "category":"Sports & Exercise",
            "subcategory":"Gym",
            "type":"Entertainment"
        }
    ],
    "sg:phone":"+1 707 693 9171",
    "sg:postcode":"95620",
    "sg:province":"CA",
    "sg:tags":[
        "club",
        "health",
        "studio",
        "gymnasium"
    ],
    "wof:name":"Dixon Fitness",
    "wof:placetype":"venue"
},
  "geometry": {"coordinates":[-121.837191,38.458139],"type":"Point"}
}