{
  "type": "Feature",
  "properties": {
    "iso:country":"US",
    "sg:address":"12109 Branford St",
    "sg:city":"Sun Valley",
    "sg:classifiers":[
        {
            "category":"Manufacturing",
            "subcategory":"Chemicals & Compounds",
            "type":"Manufacturing & Wholesale Goods"
        }
    ],
    "sg:phone":"+1 818 896 7418",
    "sg:postcode":"91352",
    "sg:province":"CA",
    "sg:tags":[
        "paint",
        "varnish",
        "allied",
        "product"
    ],
    "wof:name":"Quality Finishing Inc",
    "wof:placetype":"venue"
},
  "geometry": {"coordinates":[-118.399978,34.2511],"type":"Point"}
}