{
  "type": "Feature",
  "properties": {
    "iso:country":"US",
    "sg:address":"10951 San Pablo Ave",
    "sg:city":"El Cerrito",
    "sg:classifiers":[
        {
            "category":"Personal",
            "subcategory":"Massage",
            "type":"Services"
        },
        {
            "category":"Health Services",
            "subcategory":"Health Practitioner",
            "type":"Services"
        }
    ],
    "sg:phone":"+1 510 472 3027",
    "sg:postcode":"94530",
    "sg:province":"CA",
    "sg:tags":[
        "therapy",
        "physical"
    ],
    "sg:website":"www.cavancollins.com",
    "wof:name":"Foundation 1st Postural Bodywork & Massage",
    "wof:placetype":"venue"
},
  "geometry": {"coordinates":[-122.312518,37.916793],"type":"Point"}
}