{
  "type": "Feature",
  "properties": {
    "addr:full":"5179 Jones Ave Riverside CA 92505",
    "addr:housenumber":"5179",
    "addr:postcode":"92505",
    "addr:street":"Jones Ave",
    "iso:country":"US",
    "sg:address":"5179 Jones Ave",
    "sg:city":"Riverside",
    "sg:classifiers":[
        {
            "category":"Professional",
            "type":"Services"
        }
    ],
    "sg:phone":"+1 951 785 9304",
    "sg:postcode":"92505",
    "sg:province":"CA",
    "wof:name":"Gregory Boutique",
    "wof:placetype":"venue"
},
  "geometry": {"coordinates":[-117.479544,33.93083],"type":"Point"}
}