{
  "type": "Feature",
  "properties": {
    "addr:full":"7102 International Blvd Oakland CA 94621",
    "addr:housenumber":"7102",
    "addr:postcode":"94621",
    "addr:street":"International Blvd",
    "iso:country":"US",
    "sg:address":"7102 International Blvd",
    "sg:city":"Oakland",
    "sg:classifiers":[
        {
            "category":"Building & Trades",
            "subcategory":"Locksmith",
            "type":"Services"
        }
    ],
    "sg:phone":"+1 510 904 0511",
    "sg:postcode":"94621",
    "sg:province":"CA",
    "sg:tags":[
        "key"
    ],
    "wof:name":"24hrs Oakland Locksmith",
    "wof:placetype":"venue"
},
  "geometry": {"coordinates":[-122.188974,37.760126],"type":"Point"}
}