{
  "type": "Feature",
  "properties": {
    "addr:full":"1413 Crows Landing Rd Modesto CA 95351",
    "addr:housenumber":"1413",
    "addr:postcode":"ca 95351",
    "addr:street":"Crows Landing Rd",
    "iso:country":"US",
    "sg:address":"1413 Crows Landing Rd",
    "sg:city":"Modesto",
    "sg:classifiers":[
        {
            "category":"Shopping",
            "subcategory":"Clothing, Apparel, & Fashions",
            "type":"Retail Goods"
        }
    ],
    "sg:phone":"+1 209 527 4826",
    "sg:postcode":"95351",
    "sg:province":"CA",
    "sg:tags":[
        "western"
    ],
    "wof:name":"El Charro Western Wear",
    "wof:placetype":"venue"
},
  "geometry": {"coordinates":[-120.993683,37.609526],"type":"Point"}
}