{
  "type": "Feature",
  "properties": {
    "addr:full":"1562 Newport Blvd Costa Mesa CA 92627",
    "addr:housenumber":"1562",
    "addr:postcode":"92627",
    "addr:street":"Newport Blvd Costa",
    "iso:country":"US",
    "sg:address":"1562 Newport Blvd",
    "sg:city":"Costa Mesa",
    "sg:classifiers":[
        {
            "category":"Bars & Pubs",
            "type":"Food & Drink"
        },
        {
            "category":"Bars & Pubs",
            "subcategory":"Dive Bar",
            "type":"Food & Drink"
        }
    ],
    "sg:phone":"+1 949 548 6984",
    "sg:postcode":"92627",
    "sg:province":"CA",
    "sg:website":"eyecandybikinibar.com",
    "wof:name":"Eye Candy Bikini Bar",
    "wof:placetype":"venue"
},
  "geometry": {"coordinates":[-117.923164,33.631854],"type":"Point"}
}