{
  "type": "Feature",
  "properties": {
    "iso:country":"US",
    "sg:address":"2995 W Florida Ave",
    "sg:city":"Hemet",
    "sg:phone":"+1 951 658 4241",
    "sg:postcode":"92545",
    "sg:province":"CA",
    "wof:name":"Dream Tan",
    "wof:placetype":"venue"
},
  "geometry": {"coordinates":[-117.004643,33.747335],"type":"Point"}
}