{
  "type": "Feature",
  "properties": {
    "iso:country":"US",
    "sg:address":"24501 Marguerite Parkway",
    "sg:city":"Mission Viejo",
    "sg:classifiers":[
        {
            "category":"Banks & Credit Unions",
            "subcategory":"Bank",
            "type":"Services"
        }
    ],
    "sg:phone":"+1 949 855 9677",
    "sg:postcode":"92692",
    "sg:province":"CA",
    "sg:website":"www.statefarm.com",
    "wof:name":"Cohen Michael Insurance",
    "wof:placetype":"venue"
},
  "geometry": {"coordinates":[-117.655922,33.600501],"type":"Point"}
}