{
  "type": "Feature",
  "properties": {
    "iso:country":"US",
    "sg:address":"16441 Vanowen St",
    "sg:city":"Van Nuys",
    "sg:classifiers":[
        {
            "category":"Restaurant",
            "type":"Food & Drink"
        }
    ],
    "sg:phone":"+1 818 786 3621",
    "sg:postcode":"91406",
    "sg:province":"CA",
    "wof:name":"Costa Azul Restaurant",
    "wof:placetype":"venue"
},
  "geometry": {"coordinates":[-118.492036,34.193971],"type":"Point"}
}