{
  "type": "Feature",
  "properties": {
    "iso:country":"US",
    "sg:address":"4390 47th Ave",
    "sg:city":"Sacramento",
    "sg:classifiers":[
        {
            "category":"Restaurant",
            "type":"Food & Drink"
        }
    ],
    "sg:phone":"+1 916 422 7661",
    "sg:postcode":"95824",
    "sg:province":"CA",
    "sg:tags":[
        "american"
    ],
    "wof:name":"South Pointe Gardens",
    "wof:placetype":"venue"
},
  "geometry": {"coordinates":[-121.455354,38.51041],"type":"Point"}
}