{
  "type": "Feature",
  "properties": {
    "iso:country":"US",
    "sg:address":"18501 Collier Ave",
    "sg:city":"Lake Elsinore",
    "sg:classifiers":[
        {
            "category":"Building & Trades",
            "subcategory":"Construction",
            "type":"Services"
        }
    ],
    "sg:phone":"+1 951 471 0050",
    "sg:postcode":"92530",
    "sg:province":"CA",
    "sg:tags":[
        "pipe",
        "line",
        "contractor"
    ],
    "wof:name":"TCB Engineering",
    "wof:placetype":"venue"
},
  "geometry": {"coordinates":[-117.326426,33.678288],"type":"Point"}
}