{
  "type": "Feature",
  "properties": {
    "iso:country":"US",
    "sg:address":"7949 Woodley Ave",
    "sg:city":"Van Nuys",
    "sg:classifiers":[
        {
            "category":"Freight",
            "type":"Transportation"
        }
    ],
    "sg:phone":"+1 818 375 5054",
    "sg:postcode":"91406",
    "sg:province":"CA",
    "sg:tags":[
        "operator",
        "trucking"
    ],
    "wof:name":"Relocation Systems Inc",
    "wof:placetype":"venue"
},
  "geometry": {"coordinates":[-118.48375,34.215442],"type":"Point"}
}