{
  "type": "Feature",
  "properties": {
    "addr:full":"316 Clement Street San Francisco CA 94118",
    "addr:housenumber":"316",
    "addr:postcode":"94118",
    "addr:street":"Clement Street",
    "iso:country":"US",
    "sg:address":"316 Clement Street",
    "sg:city":"San Francisco",
    "sg:classifiers":[
        {
            "category":"Health Services",
            "subcategory":"Clinic",
            "type":"Services"
        }
    ],
    "sg:phone":"+1 415 750 0478",
    "sg:postcode":"94118",
    "sg:province":"CA",
    "sg:tags":[
        "counseling",
        "mental"
    ],
    "sg:website":"www.holosinstitute.net",
    "wof:name":"Holos Institute",
    "wof:placetype":"venue"
},
  "geometry": {"coordinates":[-122.462997,37.7831],"type":"Point"}
}