{
  "type": "Feature",
  "properties": {
    "iso:country":"US",
    "sg:address":"265 Dillon Ave",
    "sg:city":"Campbell",
    "sg:classifiers":[
        {
            "category":"Building & Trades",
            "subcategory":"Electrical",
            "type":"Services"
        }
    ],
    "sg:phone":"+1 408 866 7180",
    "sg:postcode":"95008",
    "sg:province":"CA",
    "sg:tags":[
        "electrician",
        "electric",
        "contractor"
    ],
    "sg:website":"www.southerelectric.com",
    "wof:name":"Souther Electric",
    "wof:placetype":"venue"
},
  "geometry": {"coordinates":[-121.943001,37.2841],"type":"Point"}
}