{
  "type": "Feature",
  "properties": {
    "iso:country":"US",
    "sg:address":"1333 N California Blvd",
    "sg:city":"Walnut Creek",
    "sg:classifiers":[
        {
            "category":"Real Estate",
            "subcategory":"Real Estate Agent",
            "type":"Services"
        }
    ],
    "sg:phone":"+1 925 946 2688",
    "sg:postcode":"94596",
    "sg:province":"CA",
    "wof:name":"California Property",
    "wof:placetype":"venue"
},
  "geometry": {"coordinates":[-122.063294,37.898921],"type":"Point"}
}