{
  "type": "Feature",
  "properties": {
    "iso:country":"US",
    "sg:address":"17442 Plz Sonada",
    "sg:city":"San Diego",
    "sg:classifiers":[
        {
            "category":"Wholesale",
            "subcategory":"Computers",
            "type":"Manufacturing & Wholesale Goods"
        }
    ],
    "sg:phone":"+1 858 485 0298",
    "sg:postcode":"92128",
    "sg:province":"CA",
    "sg:tags":[
        "programing",
        "custom"
    ],
    "wof:name":"Finesse Technology Corporation",
    "wof:placetype":"venue"
},
  "geometry": {"coordinates":[-117.058689,33.02872],"type":"Point"}
}