{
  "type": "Feature",
  "properties": {
    "addr:full":"1041 Yukonite Pl Oxnard CA 93030",
    "addr:housenumber":"1041",
    "addr:postcode":"93030",
    "addr:street":"Yukonite Pl",
    "iso:country":"US",
    "sg:address":"1041 Yukonite Pl",
    "sg:city":"Oxnard",
    "sg:classifiers":[
        {
            "category":"Professional",
            "type":"Services"
        }
    ],
    "sg:phone":"+1 805 988 1353",
    "sg:postcode":"93030",
    "sg:province":"CA",
    "wof:name":"Barron Santiago",
    "wof:placetype":"venue"
},
  "geometry": {"coordinates":[-119.203889,34.212829],"type":"Point"}
}