{
  "type": "Feature",
  "properties": {
    "addr:full":"1500 Park Ave Napa CA 94558",
    "addr:housenumber":"1500",
    "addr:postcode":"94558",
    "addr:street":"Park Ave",
    "iso:country":"US",
    "sg:address":"1500 Park Ave",
    "sg:city":"Napa",
    "sg:classifiers":[
        {
            "category":"Personal",
            "type":"Services"
        }
    ],
    "sg:phone":"+1 707 258 8334",
    "sg:postcode":"94558",
    "sg:province":"CA",
    "sg:tags":[
        "party",
        "planning",
        "event"
    ],
    "wof:name":"Magic Moments",
    "wof:placetype":"venue"
},
  "geometry": {"coordinates":[-122.30014799999999,38.312099],"type":"Point"}
}