{
  "type": "Feature",
  "properties": {
    "addr:full":"15695 Donner Pass Rd Truckee CA 96161",
    "addr:housenumber":"15695",
    "addr:postcode":"96161",
    "addr:street":"Donner Pass Rd",
    "iso:country":"US",
    "sg:address":"15695 Donner Pass Rd",
    "sg:city":"Truckee",
    "sg:classifiers":[
        {
            "category":"Professional",
            "subcategory":"Computer Services",
            "type":"Services"
        }
    ],
    "sg:phone":"+1 530 587 4312",
    "sg:postcode":"96161",
    "sg:province":"CA",
    "sg:tags":[
        "internet"
    ],
    "wof:name":"Exwire",
    "wof:placetype":"venue"
},
  "geometry": {"coordinates":[-120.291245,39.322959],"type":"Point"}
}