{
  "type": "Feature",
  "properties": {
    "addr:full":"101 Pacifica Irvine CA 92618",
    "addr:housenumber":"101",
    "addr:postcode":"92618",
    "addr:street":"Pacifica",
    "iso:country":"US",
    "sg:address":"101 Pacifica",
    "sg:city":"Irvine",
    "sg:classifiers":[
        {
            "category":"Real Estate",
            "subcategory":"Real Estate Agent",
            "type":"Services"
        }
    ],
    "sg:phone":"+1 949 453 8584",
    "sg:postcode":"92618",
    "sg:province":"CA",
    "sg:website":"www.credent.us",
    "wof:name":"Credent Real Estate",
    "wof:placetype":"venue"
},
  "geometry": {"coordinates":[-117.754402,33.659669],"type":"Point"}
}