{
  "type": "Feature",
  "properties": {
    "addr:full":"311 Bush St Salinas CA 93907",
    "addr:housenumber":"311",
    "addr:postcode":"93907",
    "addr:street":"Bush St",
    "iso:country":"US",
    "sg:address":"311 Bush St",
    "sg:city":"Salinas",
    "sg:classifiers":[
        {
            "category":"Wholesale",
            "subcategory":"Vending Machines",
            "type":"Manufacturing & Wholesale Goods"
        }
    ],
    "sg:phone":"+1 831 261 1066",
    "sg:postcode":"93907",
    "sg:province":"CA",
    "wof:name":"Kids World",
    "wof:placetype":"venue"
},
  "geometry": {"coordinates":[-121.659836,36.688891],"type":"Point"}
}