{
  "type": "Feature",
  "properties": {
    "addr:full":"1755 Broadway Oakland CA 94612",
    "addr:housenumber":"1755",
    "addr:postcode":"94612",
    "addr:street":"Broadway",
    "iso:country":"US",
    "sg:address":"1755 Broadway",
    "sg:city":"Oakland",
    "sg:classifiers":[
        {
            "category":"Health Services",
            "subcategory":"Clinic",
            "type":"Services"
        }
    ],
    "sg:phone":"+1 510 874 7850",
    "sg:postcode":"94612",
    "sg:province":"CA",
    "sg:tags":[
        "aids",
        "testing",
        "information"
    ],
    "sg:website":"www.calpep.org",
    "wof:name":"Cal Pep Day Treatment Ctr",
    "wof:placetype":"venue"
},
  "geometry": {"coordinates":[-122.269356,37.807521],"type":"Point"}
}