{
  "type": "Feature",
  "properties": {
    "addr:full":"4158 Ventura Canyon Ave Sherman Oaks CA 91423",
    "addr:housenumber":"4158",
    "addr:postcode":"91423",
    "addr:street":"Ventura Canyon Ave",
    "iso:country":"US",
    "sg:address":"4158 Ventura Canyon Ave",
    "sg:city":"Sherman Oaks",
    "sg:classifiers":[
        {
            "category":"Wholesale",
            "subcategory":"Plants",
            "type":"Manufacturing & Wholesale Goods"
        }
    ],
    "sg:phone":"+1 818 501 7848",
    "sg:postcode":"91423",
    "sg:province":"CA",
    "sg:tags":[
        "manufacture",
        "retail",
        "flower",
        "artificial"
    ],
    "wof:name":"Flowers That Last",
    "wof:placetype":"venue"
},
  "geometry": {"coordinates":[-118.429363,34.146777],"type":"Point"}
}