{
  "type": "Feature",
  "properties": {
    "addr:full":"11622 Markon Dr Garden Grove CA 92841",
    "addr:housenumber":"11622",
    "addr:postcode":"92841",
    "addr:street":"Markon Dr",
    "iso:country":"US",
    "sg:address":"11622 Markon Dr",
    "sg:city":"Garden Grove",
    "sg:classifiers":[
        {
            "category":"Shopping",
            "type":"Retail Goods"
        }
    ],
    "sg:phone":"+1 714 379 2111",
    "sg:postcode":"92841",
    "sg:province":"CA",
    "sg:tags":[
        "building",
        "product",
        "wood",
        "supply"
    ],
    "sg:website":"www.mouldingspecialist.com",
    "wof:name":"Moulding Specialist",
    "wof:placetype":"venue"
},
  "geometry": {"coordinates":[-118.00779,33.793886],"type":"Point"}
}