{
  "type": "Feature",
  "properties": {
    "addr:full":"23807 Aliso Creek Rd Ste 100 Laguna Niguel CA 92677",
    "addr:housenumber":"23807",
    "addr:postcode":"92677",
    "addr:street":"Aliso Creek Rd Ste 100",
    "iso:country":"US",
    "sg:address":"23807 Aliso Creek Rd Ste 100",
    "sg:city":"Laguna Niguel",
    "sg:classifiers":[
        {
            "category":"Travel",
            "subcategory":"Hotels & Motels",
            "type":"Entertainment"
        }
    ],
    "sg:phone":"+1 949 448 5150",
    "sg:postcode":"92677",
    "sg:province":"CA",
    "sg:website":"www.tradingplaces.com",
    "wof:name":"Trading Places International",
    "wof:placetype":"venue"
},
  "geometry": {"coordinates":[-117.724598,33.58996],"type":"Point"}
}