{
  "type": "Feature",
  "properties": {
    "iso:country":"US",
    "sg:address":"7805 Laguna Blvd",
    "sg:city":"Elk Grove",
    "sg:classifiers":[
        {
            "category":"Health Services",
            "subcategory":"Doctor",
            "type":"Services"
        }
    ],
    "sg:phone":"+1 916 691 5330",
    "sg:postcode":"95758",
    "sg:province":"CA",
    "sg:tags":[
        "dentist"
    ],
    "wof:name":"Profile Dental",
    "wof:placetype":"venue"
},
  "geometry": {"coordinates":[-121.406014,38.421838],"type":"Point"}
}