{
  "type": "Feature",
  "properties": {
    "iso:country":"US",
    "sg:address":"3868 Chicago Ave",
    "sg:city":"Riverside",
    "sg:classifiers":[
        {
            "category":"Professional",
            "subcategory":"Management & Consulting",
            "type":"Services"
        }
    ],
    "sg:phone":"+1 951 788 4210",
    "sg:postcode":"92507",
    "sg:province":"CA",
    "sg:tags":[
        "retail",
        "direct",
        "sales"
    ],
    "wof:name":"Crystal Agua",
    "wof:placetype":"venue"
},
  "geometry": {"coordinates":[-117.348423,33.972506],"type":"Point"}
}