{
  "type": "Feature",
  "properties": {
    "iso:country":"US",
    "sg:address":"544 Center Ave",
    "sg:city":"Martinez",
    "sg:classifiers":[
        {
            "category":"Shopping",
            "subcategory":"Shoes",
            "type":"Retail Goods"
        }
    ],
    "sg:phone":"+1 925 370 7123",
    "sg:postcode":"94553",
    "sg:province":"CA",
    "wof:name":"Payless Shoe Source",
    "wof:placetype":"venue"
},
  "geometry": {"coordinates":[-122.119165,37.993147],"type":"Point"}
}