{
  "type": "Feature",
  "properties": {
    "iso:country":"US",
    "sg:address":"2535 W 237th St",
    "sg:city":"Torrance",
    "sg:classifiers":[
        {
            "category":"Manufacturing",
            "subcategory":"Printing",
            "type":"Manufacturing & Wholesale Goods"
        }
    ],
    "sg:phone":"+1 310 626 8149",
    "sg:postcode":"90505",
    "sg:province":"CA",
    "wof:name":"Midnight Media",
    "wof:placetype":"venue"
},
  "geometry": {"coordinates":[-118.33117300000001,33.811301],"type":"Point"}
}