{
  "type": "Feature",
  "properties": {
    "addr:full":"10351 Crawford Canyon Rd Santa Ana CA 92705",
    "addr:housenumber":"10351",
    "addr:postcode":"92705",
    "addr:street":"Crawford Canyon Rd",
    "iso:country":"US",
    "sg:address":"10351 Crawford Canyon Rd",
    "sg:city":"Santa Ana",
    "sg:classifiers":[
        {
            "category":"Building & Trades",
            "subcategory":"Landscaping Services",
            "type":"Services"
        }
    ],
    "sg:phone":"+1 714 633 3200",
    "sg:postcode":"92705",
    "sg:province":"CA",
    "sg:tags":[
        "gardener"
    ],
    "wof:name":"Ochoa Joe Landscape Gardening",
    "wof:placetype":"venue"
},
  "geometry": {"coordinates":[-117.79499800000001,33.781601],"type":"Point"}
}