{
  "type": "Feature",
  "properties": {
    "iso:country":"US",
    "sg:address":"715 46th Ave",
    "sg:city":"Oakland",
    "sg:classifiers":[
        {
            "category":"Manufacturing",
            "subcategory":"Metals",
            "type":"Manufacturing & Wholesale Goods"
        }
    ],
    "sg:phone":"+1 510 261 7331",
    "sg:postcode":"94601",
    "sg:province":"CA",
    "sg:tags":[
        "galvanizing"
    ],
    "wof:name":"Pacific Galvanizing",
    "wof:placetype":"venue"
},
  "geometry": {"coordinates":[-122.216885,37.766833],"type":"Point"}
}