{
  "type": "Feature",
  "properties": {
    "iso:country":"US",
    "sg:address":"4169 Cushing Pkwy",
    "sg:city":"Fremont",
    "sg:classifiers":[
        {
            "category":"Restaurant",
            "type":"Food & Drink"
        }
    ],
    "sg:phone":"+1 510 651 6333",
    "sg:postcode":"94538",
    "sg:province":"CA",
    "sg:tags":[
        "mexican"
    ],
    "wof:name":"Santa Fe Mexican Grill",
    "wof:placetype":"venue"
},
  "geometry": {"coordinates":[-121.95034099999999,37.490404],"type":"Point"}
}