{
  "type": "Feature",
  "properties": {
    "iso:country":"US",
    "sg:address":"3923 W 6th Street Suite 301",
    "sg:city":"Los Angeles",
    "sg:classifiers":[
        {
            "category":"Real Estate",
            "subcategory":"Architect",
            "type":"Services"
        }
    ],
    "sg:phone":"+1 213 380 4478",
    "sg:postcode":"90020",
    "sg:province":"CA",
    "wof:name":"Construction Specifications Service",
    "wof:placetype":"venue"
},
  "geometry": {"coordinates":[-118.308421,34.06354],"type":"Point"}
}