{
  "type": "Feature",
  "properties": {
    "iso:country":"US",
    "sg:address":"313 Fairgrounds Dr",
    "sg:city":"Sacramento",
    "sg:classifiers":[
        {
            "category":"Shopping",
            "subcategory":"Computers & Home Electronics",
            "type":"Retail Goods"
        }
    ],
    "sg:phone":"+1 916 451 1855",
    "sg:postcode":"95817",
    "sg:province":"CA",
    "wof:name":"ABC Solutions",
    "wof:placetype":"venue"
},
  "geometry": {"coordinates":[-121.443946,38.547101],"type":"Point"}
}