{
  "type": "Feature",
  "properties": {
    "iso:country":"US",
    "sg:address":"1163 Cushman Ave",
    "sg:city":"San Diego",
    "sg:classifiers":[
        {
            "category":"Arts & Performance",
            "subcategory":"Arts Center",
            "type":"Entertainment"
        }
    ],
    "sg:phone":"+1 619 291 7666",
    "sg:postcode":"92110",
    "sg:province":"CA",
    "sg:tags":[
        "performing"
    ],
    "wof:name":"I Love To Dance & Travel On Location",
    "wof:placetype":"venue"
},
  "geometry": {"coordinates":[-117.19899700000001,32.7682],"type":"Point"}
}