{
  "type": "Feature",
  "properties": {
    "addr:full":"933 Manor Blvd San Leandro CA 94579",
    "addr:housenumber":"933",
    "addr:postcode":"94579",
    "addr:street":"Manor Blvd",
    "iso:country":"US",
    "sg:address":"933 Manor Blvd",
    "sg:city":"San Leandro",
    "sg:classifiers":[
        {
            "category":"Personal",
            "subcategory":"Barber",
            "type":"Services"
        }
    ],
    "sg:phone":"+1 510 357 5800",
    "sg:postcode":"94579",
    "sg:province":"CA",
    "wof:name":"George's Barber Shop",
    "wof:placetype":"venue"
},
  "geometry": {"coordinates":[-122.146828,37.691539],"type":"Point"}
}