{
  "type": "Feature",
  "properties": {
    "iso:country":"US",
    "sg:address":"10563 Chestnut Ave",
    "sg:city":"Stanton",
    "sg:classifiers":[
        {
            "category":"Retail",
            "subcategory":"Repair Shop",
            "type":"Services"
        }
    ],
    "sg:phone":"+1 714 527 1598",
    "sg:postcode":"90680",
    "sg:province":"CA",
    "sg:tags":[
        "welding"
    ],
    "wof:name":"Stanton Welding",
    "wof:placetype":"venue"
},
  "geometry": {"coordinates":[-117.992265,33.809505],"type":"Point"}
}