{
  "type": "Feature",
  "properties": {
    "addr:full":"215 S Carmalita St Hemet CA 92543",
    "addr:housenumber":"215",
    "addr:postcode":"92543",
    "addr:street":"S Carmalita St",
    "iso:country":"US",
    "sg:address":"215 S Carmalita St",
    "sg:city":"Hemet",
    "sg:classifiers":[
        {
            "category":"Real Estate",
            "subcategory":"Real Estate Agent",
            "type":"Services"
        }
    ],
    "sg:phone":"+1 951 658 8800",
    "sg:postcode":"92543",
    "sg:province":"CA",
    "wof:name":"John David Petty & Assoc Real",
    "wof:placetype":"venue"
},
  "geometry": {"coordinates":[-116.969534,33.744193],"type":"Point"}
}