{
  "type": "Feature",
  "properties": {
    "addr:full":"466 W Fallbrook Ave Fresno CA 93711",
    "addr:housenumber":"466",
    "addr:postcode":"93711",
    "addr:street":"W Fallbrook Ave",
    "iso:country":"US",
    "sg:address":"466 W Fallbrook Ave",
    "sg:city":"Fresno",
    "sg:classifiers":[
        {
            "category":"Insurance",
            "subcategory":"Insurance Agent",
            "type":"Services"
        }
    ],
    "sg:phone":"+1 559 448 8340",
    "sg:postcode":"93711",
    "sg:province":"CA",
    "wof:name":"Benefitmall",
    "wof:placetype":"venue"
},
  "geometry": {"coordinates":[-119.800623,36.849463],"type":"Point"}
}