{
  "type": "Feature",
  "properties": {
    "iso:country":"US",
    "sg:address":"2665 Clark Ave",
    "sg:city":"Norco",
    "sg:classifiers":[
        {
            "category":"Real Estate",
            "subcategory":"Real Estate Operator",
            "type":"Services"
        }
    ],
    "sg:phone":"+1 951 736 1665",
    "sg:postcode":"92860",
    "sg:province":"CA",
    "sg:tags":[
        "apartment"
    ],
    "wof:name":"Heritage Park Apartments",
    "wof:placetype":"venue"
},
  "geometry": {"coordinates":[-117.5608,33.920936],"type":"Point"}
}