{
  "type": "Feature",
  "properties": {
    "iso:country":"US",
    "sg:address":"1020 Ruff Dr",
    "sg:city":"San Jose",
    "sg:classifiers":[
        {
            "category":"Home & Garden",
            "subcategory":"Building Materials",
            "type":"Retail Goods"
        }
    ],
    "sg:phone":"+1 408 287 6091",
    "sg:postcode":"95110",
    "sg:province":"CA",
    "sg:tags":[
        "supply"
    ],
    "sg:website":"www.valleyconcrete.com",
    "wof:name":"Valley Concrete",
    "wof:placetype":"venue"
},
  "geometry": {"coordinates":[-121.912961,37.351881],"type":"Point"}
}