{
  "type": "Feature",
  "properties": {
    "addr:full":"5 White Oak Dr Lafayette CA 94549",
    "addr:housenumber":"5",
    "addr:postcode":"94549",
    "addr:street":"White Oak Dr",
    "iso:country":"US",
    "sg:address":"5 White Oak Dr",
    "sg:city":"Lafayette",
    "sg:classifiers":[
        {
            "category":"Autos & Motor Vehicles",
            "subcategory":"Auto Supplies",
            "type":"Retail Goods"
        }
    ],
    "sg:phone":"+1 925 283 8965",
    "sg:postcode":"94549",
    "sg:province":"CA",
    "sg:tags":[
        "automobile",
        "top",
        "upholstery",
        "covers",
        "seat"
    ],
    "wof:name":"King Kovers Upholstery, Inc",
    "wof:placetype":"venue"
},
  "geometry": {"coordinates":[-122.163985,37.889063],"type":"Point"}
}