{
  "type": "Feature",
  "properties": {
    "addr:full":"3980 Bandini Ave Riverside CA 92506",
    "addr:housenumber":"3980",
    "addr:postcode":"92506",
    "addr:street":"Bandini Ave",
    "iso:country":"US",
    "sg:address":"3980 Bandini Ave",
    "sg:city":"Riverside",
    "sg:classifiers":[
        {
            "category":"Manufacturing",
            "subcategory":"Metals",
            "type":"Manufacturing & Wholesale Goods"
        }
    ],
    "sg:phone":"+1 951 275 9922",
    "sg:postcode":"92506",
    "sg:province":"CA",
    "wof:name":"American Plating Service",
    "wof:placetype":"venue"
},
  "geometry": {"coordinates":[-117.39008200000001,33.966779],"type":"Point"}
}