{
  "type": "Feature",
  "properties": {
    "addr:full":"1632 Deer Run Santa Rosa CA 95405",
    "addr:housenumber":"1632",
    "addr:postcode":"95405",
    "addr:street":"Deer Run",
    "iso:country":"US",
    "sg:address":"1632 Deer Run",
    "sg:city":"Santa Rosa",
    "sg:classifiers":[
        {
            "category":"Real Estate",
            "subcategory":"Architect",
            "type":"Services"
        }
    ],
    "sg:phone":"+1 707 579 2170",
    "sg:postcode":"95405",
    "sg:province":"CA",
    "wof:name":"Robert G Zinkhan Architect Aia",
    "wof:placetype":"venue"
},
  "geometry": {"coordinates":[-122.681838,38.435626],"type":"Point"}
}