{
  "type": "Feature",
  "properties": {
    "iso:country":"US",
    "sg:address":"2021 Ygnacio Valley Rd",
    "sg:city":"Walnut Creek",
    "sg:classifiers":[
        {
            "category":"Health Services",
            "subcategory":"Dentist",
            "type":"Services"
        }
    ],
    "sg:phone":"+1 925 933 6092",
    "sg:postcode":"94598",
    "sg:province":"CA",
    "wof:name":"Tsaur Benjamin DDS",
    "wof:placetype":"venue"
},
  "geometry": {"coordinates":[-122.33892,37.920912],"type":"Point"}
}