{
  "type": "Feature",
  "properties": {
    "addr:full":"815 N Douty St Hanford CA 93230",
    "addr:housenumber":"815",
    "addr:postcode":"ca 93230",
    "addr:street":"N Douty St",
    "iso:country":"US",
    "sg:address":"815 N Douty St",
    "sg:city":"Hanford",
    "sg:classifiers":[
        {
            "category":"Health Services",
            "subcategory":"Clinic",
            "type":"Services"
        },
        {
            "category":"Community Center",
            "type":"Public Place"
        },
        {
            "category":"Health Services",
            "subcategory":"Hospital",
            "type":"Services"
        }
    ],
    "sg:phone":"+1 559 589 9801",
    "sg:postcode":"93230",
    "sg:province":"CA",
    "sg:tags":[
        "medical",
        "sleep",
        "treatment",
        "disorders-information"
    ],
    "wof:name":"Adventist Health Sleep Apnea Center",
    "wof:placetype":"venue"
},
  "geometry": {"coordinates":[-119.646019,36.333213],"type":"Point"}
}