{
  "type": "Feature",
  "properties": {
    "addr:full":"138 Lawson Rd Kensington CA 94707",
    "addr:housenumber":"138",
    "addr:postcode":"94707",
    "addr:street":"Lawson Rd",
    "iso:country":"US",
    "sg:address":"138 Lawson Rd",
    "sg:city":"Kensington",
    "sg:classifiers":[
        {
            "category":"Professional",
            "subcategory":"Detective & Security Services",
            "type":"Services"
        }
    ],
    "sg:phone":"+1 510 524 2606",
    "sg:postcode":"94707",
    "sg:province":"CA",
    "sg:tags":[
        "information",
        "bureau"
    ],
    "wof:name":"Anderson Tax Service",
    "wof:placetype":"venue"
},
  "geometry": {"coordinates":[-122.2808,37.916719],"type":"Point"}
}