{
  "type": "Feature",
  "properties": {
    "iso:country":"US",
    "sg:address":"82 South St",
    "sg:city":"Willits",
    "sg:classifiers":[
        {
            "category":"Health Services",
            "subcategory":"Doctor",
            "type":"Services"
        }
    ],
    "sg:phone":"+1 707 459 4500",
    "sg:postcode":"95490",
    "sg:province":"CA",
    "sg:tags":[
        "dentist"
    ],
    "wof:name":"Hans J Sawatzky DDS",
    "wof:placetype":"venue"
},
  "geometry": {"coordinates":[-123.351007,39.404198],"type":"Point"}
}