{
  "type": "Feature",
  "properties": {
    "addr:full":"661 el Cajon Blvd El Cajon CA 92020",
    "addr:housenumber":"661",
    "addr:postcode":"92020",
    "addr:street":"El Cajon Blvd",
    "iso:country":"US",
    "sg:address":"661 el Cajon Blvd",
    "sg:city":"El Cajon",
    "sg:classifiers":[
        {
            "category":"Wholesale",
            "subcategory":"Auto Parts",
            "type":"Manufacturing & Wholesale Goods"
        }
    ],
    "sg:phone":"+1 619 444 2175",
    "sg:postcode":"92020",
    "sg:province":"CA",
    "sg:tags":[
        "tire"
    ],
    "wof:name":"Al Archard Inc",
    "wof:placetype":"venue"
},
  "geometry": {"coordinates":[-116.973258,32.789221],"type":"Point"}
}