{
  "type": "Feature",
  "properties": {
    "iso:country":"US",
    "sg:address":"13694 Crape Myrtle Dr",
    "sg:city":"Moreno Valley",
    "sg:classifiers":[
        {
            "category":"Banks & Credit Unions",
            "subcategory":"Bank",
            "type":"Services"
        }
    ],
    "sg:phone":"+1 951 485 3173",
    "sg:postcode":"92553",
    "sg:province":"CA",
    "sg:tags":[
        "loan",
        "real estate"
    ],
    "wof:name":"Shorter Route Properties",
    "wof:placetype":"venue"
},
  "geometry": {"coordinates":[-117.22106,33.921697],"type":"Point"}
}