{
  "type": "Feature",
  "properties": {
    "addr:full":"4340 Genesee Ave San Diego CA 92117",
    "addr:housenumber":"4340",
    "addr:postcode":"92117",
    "addr:street":"Genesee Ave",
    "iso:country":"US",
    "sg:address":"4340 Genesee Ave",
    "sg:city":"San Diego",
    "sg:classifiers":[
        {
            "category":"Retail",
            "subcategory":"Laundry & Dry Cleaning",
            "type":"Services"
        }
    ],
    "sg:phone":"+1 858 278 4066",
    "sg:postcode":"92117",
    "sg:province":"CA",
    "sg:tags":[
        "cleaners"
    ],
    "wof:name":"Atlas Cleaners",
    "wof:placetype":"venue"
},
  "geometry": {"coordinates":[-117.183582,32.822272],"type":"Point"}
}