{
  "type": "Feature",
  "properties": {
    "addr:full":"758 Harbison Canyon Rd El Cajon CA 92019",
    "addr:housenumber":"758",
    "addr:postcode":"92019",
    "addr:street":"Harbison Canyon Rd",
    "iso:country":"US",
    "sg:address":"758 Harbison Canyon Rd",
    "sg:city":"El Cajon",
    "sg:classifiers":[
        {
            "category":"Building & Trades",
            "subcategory":"Landscaping Services",
            "type":"Services"
        }
    ],
    "sg:phone":"+1 619 659 5102",
    "sg:postcode":"92019",
    "sg:province":"CA",
    "sg:tags":[
        "designer",
        "landscape"
    ],
    "wof:name":"California Landscape Design",
    "wof:placetype":"venue"
},
  "geometry": {"coordinates":[-116.834005,32.816573],"type":"Point"}
}