{
  "type": "Feature",
  "properties": {
    "iso:country":"US",
    "sg:address":"20 Truman Street",
    "sg:city":"Irvine",
    "sg:classifiers":[
        {
            "category":"Professional",
            "subcategory":"Accounting & Tax Preparation",
            "type":"Services"
        }
    ],
    "sg:phone":"+1 949 551 9566",
    "sg:postcode":"92620",
    "sg:province":"CA",
    "sg:tags":[
        "accountant"
    ],
    "wof:name":"Winter Accountantcy",
    "wof:placetype":"venue"
},
  "geometry": {"coordinates":[-117.765914,33.710106],"type":"Point"}
}