{
  "type": "Feature",
  "properties": {
    "iso:country":"US",
    "sg:address":"6052 San Fernando Rd",
    "sg:city":"Glendale",
    "sg:classifiers":[
        {
            "category":"Professional",
            "subcategory":"Computer Services",
            "type":"Services"
        }
    ],
    "sg:phone":"+1 818 246 3494",
    "sg:postcode":"91202",
    "sg:province":"CA",
    "sg:tags":[
        "repair"
    ],
    "sg:website":"www.thecomputerfactory.com",
    "wof:name":"The Computer Factory",
    "wof:placetype":"venue"
},
  "geometry": {"coordinates":[-118.281413,34.160806],"type":"Point"}
}