{
  "type": "Feature",
  "properties": {
    "iso:country":"US",
    "sg:address":"2908 Main St",
    "sg:city":"Santa Monica",
    "sg:classifiers":[
        {
            "category":"Home & Garden",
            "subcategory":"Furniture",
            "type":"Retail Goods"
        }
    ],
    "sg:phone":"+1 310 664 0633",
    "sg:postcode":"90405",
    "sg:province":"CA",
    "wof:name":"2908",
    "wof:placetype":"venue"
},
  "geometry": {"coordinates":[-118.480846,33.999224],"type":"Point"}
}