{
  "type": "Feature",
  "properties": {
    "addr:full":"Westfield Century City 10250 Santa Monica Blvd Los Angeles CA 90067",
    "addr:postcode":"10250;90067",
    "addr:street":"Santa Monica Blvd",
    "iso:country":"US",
    "sg:address":"Westfield Century City 10250 Santa Monica Blvd",
    "sg:city":"Los Angeles",
    "sg:classifiers":[
        {
            "category":"Ice Cream",
            "type":"Food & Drink"
        }
    ],
    "sg:phone":"+1 310 553 8733",
    "sg:postcode":"90067",
    "sg:province":"CA",
    "sg:tags":[
        "frozen",
        "yogurt"
    ],
    "sg:website":"www.purenakedyogurt.com/",
    "wof:name":"Purenaked Yogurt",
    "wof:placetype":"venue"
},
  "geometry": {"coordinates":[-118.42082000000001,34.059463],"type":"Point"}
}