{
  "type": "Feature",
  "properties": {
    "addr:full":"23101 Lake Center Dr Ste 150 Lake Forest CA 92630",
    "addr:housenumber":"23101",
    "addr:postcode":"92630",
    "addr:street":"Lake Center Dr Ste 150",
    "iso:country":"US",
    "sg:address":"23101 Lake Center Dr Ste 150",
    "sg:city":"Lake Forest",
    "sg:classifiers":[
        {
            "category":"Banks & Credit Unions",
            "subcategory":"Financial Services",
            "type":"Services"
        }
    ],
    "sg:phone":"+1 949 540 0850",
    "sg:postcode":"92630",
    "sg:province":"CA",
    "sg:tags":[
        "broker",
        "mortgage"
    ],
    "wof:name":"Financial Center West",
    "wof:placetype":"venue"
},
  "geometry": {"coordinates":[-117.716932,33.627082],"type":"Point"}
}