{
  "type": "Feature",
  "properties": {
    "iso:country":"US",
    "sg:address":"826 Brookside Ave",
    "sg:city":"Redlands",
    "sg:classifiers":[
        {
            "category":"Real Estate",
            "subcategory":"Real Estate Agent",
            "type":"Services"
        }
    ],
    "sg:phone":"+1 909 792 3550",
    "sg:postcode":"92373",
    "sg:province":"CA",
    "wof:name":"Wallender Commercial Real",
    "wof:placetype":"venue"
},
  "geometry": {"coordinates":[-117.191991,34.05206],"type":"Point"}
}