{
  "type": "Feature",
  "properties": {
    "addr:full":"9580 Garden Grv Blvd Garden Grove CA 92844",
    "addr:housenumber":"9580",
    "addr:postcode":"92844",
    "addr:street":"Garden Grv Blvd",
    "iso:country":"US",
    "sg:address":"9580 Garden Grv Blvd",
    "sg:city":"Garden Grove",
    "sg:classifiers":[
        {
            "category":"Restaurant",
            "type":"Food & Drink"
        }
    ],
    "sg:phone":"+1 714 537 2007",
    "sg:postcode":"92844",
    "sg:province":"CA",
    "sg:tags":[
        "korean"
    ],
    "wof:name":"Kong Ji Ne 2",
    "wof:placetype":"venue"
},
  "geometry": {"coordinates":[-117.965192,33.77392],"type":"Point"}
}