{
  "type": "Feature",
  "properties": {
    "iso:country":"US",
    "sg:address":"2621 Raft Ln",
    "sg:city":"Oxnard",
    "sg:classifiers":[
        {
            "category":"Health Services",
            "subcategory":"Nursing And Care Facility",
            "type":"Services"
        }
    ],
    "sg:phone":"+1 805 815 4155",
    "sg:postcode":"93035",
    "sg:province":"CA",
    "sg:tags":[
        "skilled"
    ],
    "wof:name":"Serenity Elderly Care",
    "wof:placetype":"venue"
},
  "geometry": {"coordinates":[-119.205648,34.191557],"type":"Point"}
}