{
  "type": "Feature",
  "properties": {
    "addr:full":"1020 15th St Modesto CA 95354",
    "addr:housenumber":"1020",
    "addr:postcode":"ca 95354",
    "addr:street":"15Th St",
    "iso:country":"US",
    "sg:address":"1020 15th St",
    "sg:city":"Modesto",
    "sg:classifiers":[
        {
            "category":"Banks & Credit Unions",
            "subcategory":"Financial Services",
            "type":"Services"
        }
    ],
    "sg:phone":"+1 209 846 6400",
    "sg:postcode":"95354",
    "sg:province":"CA",
    "sg:tags":[
        "broker",
        "mortgage"
    ],
    "wof:name":"imortgage.com Inc",
    "wof:placetype":"venue"
},
  "geometry": {"coordinates":[-120.995632,37.644385],"type":"Point"}
}