{
  "type": "Feature",
  "properties": {
    "addr:full":"11924 W Washington Blvd Los Angeles CA 90034",
    "addr:housenumber":"11924",
    "addr:postcode":"90034",
    "addr:street":"W Washington Blvd",
    "iso:country":"US",
    "sg:address":"11924 W Washington Blvd",
    "sg:city":"Los Angeles",
    "sg:classifiers":[
        {
            "category":"Health Services",
            "subcategory":"Doctor",
            "type":"Services"
        },
        {
            "category":"Health Services",
            "subcategory":"Clinic",
            "type":"Services"
        },
        {
            "category":"Professional",
            "subcategory":"Management & Consulting",
            "type":"Services"
        }
    ],
    "sg:phone":"+1 310 781 0522",
    "sg:postcode":"90034",
    "sg:province":"CA",
    "sg:tags":[
        "counseling",
        "life",
        "coach",
        "mental"
    ],
    "sg:website":"www.drtaji.com",
    "wof:name":"Taji Huang PhD",
    "wof:placetype":"venue"
},
  "geometry": {"coordinates":[-118.42041,33.997777],"type":"Point"}
}