{
  "type": "Feature",
  "properties": {
    "iso:country":"US",
    "sg:address":"1024 E Pacific Coast Hwy",
    "sg:city":"Long Beach",
    "sg:classifiers":[
        {
            "category":"Health Services",
            "subcategory":"Doctor",
            "type":"Services"
        }
    ],
    "sg:phone":"+1 562 218 0131",
    "sg:postcode":"90806",
    "sg:province":"CA",
    "sg:tags":[
        "clinic"
    ],
    "wof:name":"Coast Medical Clinic",
    "wof:placetype":"venue"
},
  "geometry": {"coordinates":[-118.179196,33.78985],"type":"Point"}
}