{
  "type": "Feature",
  "properties": {
    "addr:full":"544 W 26th St Merced CA 95340",
    "addr:housenumber":"544",
    "addr:postcode":"95340",
    "addr:street":"W 26Th St",
    "iso:country":"US",
    "sg:address":"544 W 26th St",
    "sg:city":"Merced",
    "sg:classifiers":[
        {
            "category":"Health Services",
            "subcategory":"Doctor",
            "type":"Services"
        }
    ],
    "sg:phone":"+1 209 384 3223",
    "sg:postcode":"95340",
    "sg:province":"CA",
    "sg:tags":[
        "dentist"
    ],
    "wof:name":"Richard Rowan DDS",
    "wof:placetype":"venue"
},
  "geometry": {"coordinates":[-120.47915999999999,37.310643],"type":"Point"}
}