{
  "type": "Feature",
  "properties": {
    "addr:full":"8004 Folsom-Auburn Rd Folsom CA 95630",
    "addr:housenumber":"8004",
    "addr:postcode":"95630",
    "addr:street":"Folsom-Auburn Rd",
    "iso:country":"US",
    "sg:address":"8004 Folsom-Auburn Rd",
    "sg:city":"Folsom",
    "sg:classifiers":[
        {
            "category":"Personal",
            "subcategory":"Beauty Salon",
            "type":"Services"
        }
    ],
    "sg:phone":"+1 916 989 4229",
    "sg:postcode":"95630",
    "sg:province":"CA",
    "wof:name":"Dager Corp",
    "wof:placetype":"venue"
},
  "geometry": {"coordinates":[-121.174454,38.712212],"type":"Point"}
}