{
  "type": "Feature",
  "properties": {
    "addr:full":"13931 San Antonio Dr Norwalk CA 90650",
    "addr:housenumber":"13931",
    "addr:postcode":"90650",
    "addr:street":"San Antonio Dr",
    "iso:country":"US",
    "sg:address":"13931 San Antonio Dr",
    "sg:city":"Norwalk",
    "sg:classifiers":[
        {
            "category":"Home & Garden",
            "subcategory":"Carpets & Floor Coverings",
            "type":"Retail Goods"
        }
    ],
    "sg:phone":"+1 562 863 0457",
    "sg:postcode":"90650",
    "sg:province":"CA",
    "sg:tags":[
        "carpeting"
    ],
    "wof:name":"Paradise Carpet",
    "wof:placetype":"venue"
},
  "geometry": {"coordinates":[-118.08000199999999,33.9044],"type":"Point"}
}