{
  "type": "Feature",
  "properties": {
    "iso:country":"US",
    "sg:address":"5795 Dugan Ave",
    "sg:city":"La Mesa",
    "sg:classifiers":[
        {
            "category":"Banks & Credit Unions",
            "subcategory":"Financial Services",
            "type":"Services"
        }
    ],
    "sg:phone":"+1 619 463 9777",
    "sg:postcode":"91942",
    "sg:province":"CA",
    "sg:tags":[
        "trust",
        "management"
    ],
    "wof:name":"Brothers Family Trust",
    "wof:placetype":"venue"
},
  "geometry": {"coordinates":[-117.020268,32.782597],"type":"Point"}
}