{
  "type": "Feature",
  "properties": {
    "iso:country":"US",
    "sg:address":"11755 Slauson Ave",
    "sg:city":"Santa Fe Springs",
    "sg:classifiers":[
        {
            "category":"Professional",
            "subcategory":"Lawyer & Legal Services",
            "type":"Services"
        }
    ],
    "sg:phone":"+1 562 464 6934",
    "sg:postcode":"90670",
    "sg:province":"CA",
    "sg:tags":[
        "plan"
    ],
    "wof:name":"Felix & Felix Immigration Svc",
    "wof:placetype":"venue"
},
  "geometry": {"coordinates":[-118.060596,33.963757],"type":"Point"}
}