{
  "type": "Feature",
  "properties": {
    "addr:full":"286 Ashton Ave San Francisco CA 94112",
    "addr:housenumber":"286",
    "addr:postcode":"94112",
    "addr:street":"Ashton Ave",
    "iso:country":"US",
    "sg:address":"286 Ashton Ave",
    "sg:city":"San Francisco",
    "sg:classifiers":[
        {
            "category":"Organizations",
            "subcategory":"Religious Organization",
            "type":"Services"
        }
    ],
    "sg:phone":"+1 415 587 7066",
    "sg:postcode":"94112",
    "sg:province":"CA",
    "sg:tags":[
        "church"
    ],
    "wof:name":"St Emydius Church",
    "wof:placetype":"venue"
},
  "geometry": {"coordinates":[-122.462197,37.723175],"type":"Point"}
}