{
  "type": "Feature",
  "properties": {
    "addr:full":"2000 Giaramita St Richmond CA 94801",
    "addr:postcode":"94801",
    "addr:street":"St",
    "iso:country":"US",
    "sg:address":"2000 Giaramita St",
    "sg:city":"Richmond",
    "sg:classifiers":[
        {
            "category":"Education",
            "subcategory":"School",
            "type":"Public Place"
        }
    ],
    "sg:phone":"+1 510 237 0166",
    "sg:postcode":"94801",
    "sg:province":"CA",
    "wof:name":"Verde Elementary School",
    "wof:placetype":"venue"
},
  "geometry": {"coordinates":[-122.36324,37.960331],"type":"Point"}
}