{
  "type": "Feature",
  "properties": {
    "iso:country":"US",
    "sg:address":"15315 Magnolia Blvd",
    "sg:city":"Sherman Oaks",
    "sg:classifiers":[
        {
            "category":"Banks & Credit Unions",
            "subcategory":"Investment Brokerage",
            "type":"Services"
        }
    ],
    "sg:phone":"+1 818 788 4408",
    "sg:postcode":"91403",
    "sg:province":"CA",
    "sg:tags":[
        "funds",
        "mutual"
    ],
    "wof:name":"Edward Jones Co",
    "wof:placetype":"venue"
},
  "geometry": {"coordinates":[-118.469285,34.164845],"type":"Point"}
}