{
  "type": "Feature",
  "properties": {
    "iso:country":"US",
    "sg:address":"462 W Meda Ave",
    "sg:city":"Glendora",
    "sg:classifiers":[
        {
            "category":"Building & Trades",
            "subcategory":"Plumbing",
            "type":"Services"
        }
    ],
    "sg:phone":"+1 626 963 1043",
    "sg:postcode":"91741",
    "sg:province":"CA",
    "sg:tags":[
        "contractor"
    ],
    "wof:name":"J & P Mechanical",
    "wof:placetype":"venue"
},
  "geometry": {"coordinates":[-117.87127,34.138417],"type":"Point"}
}