{
  "type": "Feature",
  "properties": {
    "iso:country":"US",
    "sg:address":"7593 Broadway",
    "sg:city":"Lemon Grove",
    "sg:classifiers":[
        {
            "category":"Autos & Motor Vehicles",
            "subcategory":"Automobile Sales",
            "type":"Retail Goods"
        }
    ],
    "sg:phone":"+1 619 469 2696",
    "sg:postcode":"91945",
    "sg:province":"CA",
    "sg:tags":[
        "used"
    ],
    "wof:name":"San Diego Motors Inc",
    "wof:placetype":"venue"
},
  "geometry": {"coordinates":[-117.036202,32.742557],"type":"Point"}
}