{
  "type": "Feature",
  "properties": {
    "addr:full":"158 N Main St Lake Elsinore CA 92530",
    "addr:housenumber":"158",
    "addr:postcode":"92530",
    "addr:street":"N Main St",
    "iso:country":"US",
    "sg:address":"158 N Main St",
    "sg:city":"Lake Elsinore",
    "sg:classifiers":[
        {
            "category":"Professional",
            "subcategory":"Business Services",
            "type":"Services"
        }
    ],
    "sg:phone":"+1 951 471 8360",
    "sg:postcode":"92530",
    "sg:province":"CA",
    "sg:tags":[
        "liquidator"
    ],
    "wof:name":"TCN Liquidation Sales",
    "wof:placetype":"venue"
},
  "geometry": {"coordinates":[-117.32693999999999,33.669667],"type":"Point"}
}