{
  "type": "Feature",
  "properties": {
    "addr:full":"23010 8th St Newhall CA 91321",
    "addr:housenumber":"23010",
    "addr:postcode":"91321",
    "addr:street":"8Th St",
    "iso:country":"US",
    "sg:address":"23010 8th St",
    "sg:city":"Newhall",
    "sg:classifiers":[
        {
            "category":"Professional",
            "type":"Services"
        },
        {
            "category":"Arts & Performance",
            "subcategory":"Music",
            "type":"Entertainment"
        }
    ],
    "sg:phone":"+1 661 259 5755",
    "sg:postcode":"91321",
    "sg:province":"CA",
    "sg:tags":[
        "record",
        "producer",
        "label"
    ],
    "wof:name":"Jim Scott Production",
    "wof:placetype":"venue"
},
  "geometry": {"coordinates":[-118.532562,34.375298],"type":"Point"}
}