{
  "type": "Feature",
  "properties": {
    "addr:full":"1960 Morse Ave Sacramento CA 95825",
    "addr:housenumber":"1960",
    "addr:postcode":"95825",
    "addr:street":"Morse Ave",
    "iso:country":"US",
    "sg:address":"1960 Morse Ave",
    "sg:city":"Sacramento",
    "sg:classifiers":[
        {
            "category":"Real Estate",
            "subcategory":"Real Estate Operator",
            "type":"Services"
        }
    ],
    "sg:phone":"+1 916 978 0770",
    "sg:postcode":"95825",
    "sg:province":"CA",
    "sg:tags":[
        "apartment"
    ],
    "wof:name":"Morse Plaza Apartments",
    "wof:placetype":"venue"
},
  "geometry": {"coordinates":[-121.392127,38.60223],"type":"Point"}
}