{
  "type": "Feature",
  "properties": {
    "iso:country":"US",
    "sg:address":"14048 Sycamore Ave",
    "sg:city":"Poway",
    "sg:classifiers":[
        {
            "category":"Banks & Credit Unions",
            "subcategory":"Financial Services",
            "type":"Services"
        }
    ],
    "sg:phone":"+1 858 748 5076",
    "sg:postcode":"92064",
    "sg:province":"CA",
    "sg:tags":[
        "trust",
        "management"
    ],
    "wof:name":"Awbrey Family Trust",
    "wof:placetype":"venue"
},
  "geometry": {"coordinates":[-117.037639,32.968287],"type":"Point"}
}