{
  "type": "Feature",
  "properties": {
    "addr:full":"411 W 7th Street Los Angeles CA 90014",
    "addr:housenumber":"411",
    "addr:postcode":"90014",
    "addr:street":"W 7Th Street",
    "iso:country":"US",
    "sg:address":"411 W 7th Street",
    "sg:city":"Los Angeles",
    "sg:classifiers":[
        {
            "category":"Shopping",
            "subcategory":"Jewelry",
            "type":"Retail Goods"
        }
    ],
    "sg:phone":"+1 213 896 9250",
    "sg:postcode":"90014",
    "sg:province":"CA",
    "wof:name":"Sean's Jewerly",
    "wof:placetype":"venue"
},
  "geometry": {"coordinates":[-118.254673,34.045998],"type":"Point"}
}