{
  "type": "Feature",
  "properties": {
    "addr:full":"8088 Golden Ave Lemon Grove CA 91945",
    "addr:housenumber":"8088",
    "addr:postcode":"91945",
    "addr:street":"Golden Ave",
    "iso:country":"US",
    "sg:address":"8088 Golden Ave",
    "sg:city":"Lemon Grove",
    "sg:classifiers":[
        {
            "category":"Real Estate",
            "subcategory":"Real Estate Operator",
            "type":"Services"
        }
    ],
    "sg:phone":"+1 619 463 6059",
    "sg:postcode":"91945",
    "sg:province":"CA",
    "sg:tags":[
        "building",
        "apartment"
    ],
    "wof:name":"Golden Avenue Apartments",
    "wof:placetype":"venue"
},
  "geometry": {"coordinates":[-117.026067,32.742014],"type":"Point"}
}