{
  "type": "Feature",
  "properties": {
    "addr:full":"620 S Soto St Los Angeles CA 90023",
    "addr:housenumber":"620",
    "addr:postcode":"90023",
    "addr:street":"S Soto St",
    "iso:country":"US",
    "sg:address":"620 S Soto St",
    "sg:city":"Los Angeles",
    "sg:classifiers":[
        {
            "category":"Restaurant",
            "type":"Food & Drink"
        }
    ],
    "sg:phone":"+1 323 582 2611",
    "sg:postcode":"90023",
    "sg:province":"CA",
    "sg:tags":[
        "mexican"
    ],
    "wof:name":"El Jalisciense",
    "wof:placetype":"venue"
},
  "geometry": {"coordinates":[-118.21406,34.036914],"type":"Point"}
}