{
  "type": "Feature",
  "properties": {
    "addr:full":"4954 Huntington Dr S Los Angeles CA 90032",
    "addr:housenumber":"4954",
    "addr:postcode":"90032",
    "addr:street":"Huntington Dr S",
    "iso:country":"US",
    "sg:address":"4954 Huntington Dr S",
    "sg:city":"Los Angeles",
    "sg:classifiers":[
        {
            "category":"Shopping",
            "subcategory":"Shoes",
            "type":"Retail Goods"
        }
    ],
    "sg:phone":"+1 323 223 8300",
    "sg:postcode":"90032",
    "sg:province":"CA",
    "sg:tags":[
        "store"
    ],
    "sg:website":"www.shoepalace.com",
    "wof:name":"Shoe Palace",
    "wof:placetype":"venue"
},
  "geometry": {"coordinates":[-118.174809,34.08718],"type":"Point"}
}