{
  "type": "Feature",
  "properties": {
    "addr:full":"3119 Alta Arden Expy Sacramento CA 95825",
    "addr:housenumber":"3119",
    "addr:postcode":"95825",
    "addr:street":"Alta Arden Expy",
    "iso:country":"US",
    "sg:address":"3119 Alta Arden Expy",
    "sg:city":"Sacramento",
    "sg:classifiers":[
        {
            "category":"Place Of Worship",
            "subcategory":"Temple",
            "type":"Public Place"
        }
    ],
    "sg:phone":"+1 916 481 8781",
    "sg:postcode":"95825",
    "sg:province":"CA",
    "sg:tags":[
        "buddhist"
    ],
    "sg:website":"kimquang.org",
    "wof:name":"Kim Quang Temple",
    "wof:placetype":"venue"
},
  "geometry": {"coordinates":[-121.39153899999999,38.599791],"type":"Point"}
}