{
  "type": "Feature",
  "properties": {
    "addr:full":"6121 Shoup Ave Woodland Hills CA 91367",
    "addr:housenumber":"6121",
    "addr:postcode":"91367",
    "addr:street":"Shoup Ave",
    "iso:country":"US",
    "sg:address":"6121 Shoup Ave",
    "sg:city":"Woodland Hills",
    "sg:classifiers":[
        {
            "category":"Restaurant",
            "type":"Food & Drink"
        }
    ],
    "sg:phone":"+1 818 883 0000",
    "sg:postcode":"91367",
    "sg:province":"CA",
    "wof:name":"Eagle Bar & Grill",
    "wof:placetype":"venue"
},
  "geometry": {"coordinates":[-118.614688,34.182224],"type":"Point"}
}