{
  "type": "Feature",
  "properties": {
    "iso:country":"US",
    "sg:address":"1556 Meridian Ave",
    "sg:city":"San Jose",
    "sg:classifiers":[
        {
            "category":"Health Services",
            "subcategory":"Optometrist",
            "type":"Services"
        }
    ],
    "sg:phone":"+1 408 445 2020",
    "sg:postcode":"95125",
    "sg:province":"CA",
    "wof:name":"Murray Bradford OD",
    "wof:placetype":"venue"
},
  "geometry": {"coordinates":[-121.914001,37.296001],"type":"Point"}
}