{
  "type": "Feature",
  "properties": {
    "iso:country":"US",
    "sg:address":"777 Airport Blvd",
    "sg:city":"Burlingame",
    "sg:classifiers":[
        {
            "category":"Utilities",
            "type":"Services"
        },
        {
            "category":"Professional",
            "subcategory":"Computer Services",
            "type":"Services"
        }
    ],
    "sg:phone":"+1 650 579 5725",
    "sg:postcode":"94010",
    "sg:province":"CA",
    "sg:tags":[
        "isp",
        "provider",
        "internet"
    ],
    "wof:name":"Hotel Internet Services",
    "wof:placetype":"venue"
},
  "geometry": {"coordinates":[-122.34908299999999,37.589705],"type":"Point"}
}