{
  "type": "Feature",
  "properties": {
    "addr:full":"14901 Central Ave Chino CA 91710",
    "addr:housenumber":"14901",
    "addr:postcode":"91710",
    "addr:street":"Central Ave",
    "iso:country":"US",
    "sg:address":"14901 Central Ave",
    "sg:city":"Chino",
    "sg:classifiers":[
        {
            "category":"Health Services",
            "subcategory":"Clinic",
            "type":"Services"
        },
        {
            "category":"Health Services",
            "subcategory":"Hospital",
            "type":"Services"
        }
    ],
    "sg:phone":"+1 909 597 1821",
    "sg:postcode":"91710",
    "sg:province":"CA",
    "sg:tags":[
        "medical"
    ],
    "sg:website":"http://www.intermountaincamp.com",
    "wof:name":"California Institution for Men Hospital",
    "wof:placetype":"venue"
},
  "geometry": {"coordinates":[-117.68898,33.982769],"type":"Point"}
}