{
  "type": "Feature",
  "properties": {
    "addr:full":"104 E Ave G Lancaster CA 93535",
    "addr:housenumber":"104",
    "addr:postcode":"93535",
    "addr:street":"E Ave G",
    "iso:country":"US",
    "sg:address":"104 E Ave G",
    "sg:city":"Lancaster",
    "sg:classifiers":[
        {
            "category":"Shopping",
            "subcategory":"Musical Instruments",
            "type":"Retail Goods"
        }
    ],
    "sg:phone":"+1 661 948 3444",
    "sg:postcode":"93535",
    "sg:province":"CA",
    "sg:tags":[
        "music",
        "dealer"
    ],
    "wof:name":"Melody Music & Computer",
    "wof:placetype":"venue"
},
  "geometry": {"coordinates":[-118.12911200000001,34.733349],"type":"Point"}
}