{
  "type": "Feature",
  "properties": {
    "addr:full":"3819 W 6th St Los Angeles CA 90020",
    "addr:housenumber":"3819",
    "addr:postcode":"90020",
    "addr:street":"W 6Th St",
    "iso:country":"US",
    "sg:address":"3819 W 6th St",
    "sg:city":"Los Angeles",
    "sg:classifiers":[
        {
            "category":"Restaurant",
            "type":"Food & Drink"
        }
    ],
    "sg:phone":"+1 213 739 0321",
    "sg:postcode":"90020",
    "sg:province":"CA",
    "sg:tags":[
        "korean",
        "barbeque"
    ],
    "wof:name":"Byul Gobchang",
    "wof:placetype":"venue"
},
  "geometry": {"coordinates":[-118.305826,34.06354],"type":"Point"}
}