{
  "type": "Feature",
  "properties": {
    "iso:country":"US",
    "sg:address":"913 Sunset Dr",
    "sg:city":"Antioch",
    "sg:classifiers":[
        {
            "category":"Organizations",
            "subcategory":"Religious Organization",
            "type":"Services"
        }
    ],
    "sg:phone":"+1 925 522 2017",
    "sg:postcode":"94509",
    "sg:province":"CA",
    "sg:tags":[
        "church"
    ],
    "wof:name":"Grace Bible Fellowship",
    "wof:placetype":"venue"
},
  "geometry": {"coordinates":[-121.790603,37.997676],"type":"Point"}
}