{
  "type": "Feature",
  "properties": {
    "addr:full":"5050 el Molino Ln Sebastopol CA 95472",
    "addr:housenumber":"5050",
    "addr:postcode":"95472",
    "addr:street":"El Molino Ln",
    "iso:country":"US",
    "sg:address":"5050 el Molino Ln",
    "sg:city":"Sebastopol",
    "sg:classifiers":[
        {
            "category":"Farming",
            "subcategory":"Nursery",
            "type":"Manufacturing & Wholesale Goods"
        }
    ],
    "sg:phone":"+1 707 823 2605",
    "sg:postcode":"95472",
    "sg:province":"CA",
    "sg:tags":[
        "ornamental",
        "supply"
    ],
    "wof:name":"Shooting Star Propagation",
    "wof:placetype":"venue"
},
  "geometry": {"coordinates":[-122.902001,38.439859],"type":"Point"}
}