{
  "type": "Feature",
  "properties": {
    "iso:country":"US",
    "sg:address":"100 Lafayette Cir",
    "sg:city":"Lafayette",
    "sg:classifiers":[
        {
            "category":"Personal",
            "subcategory":"Beauty Salon",
            "type":"Services"
        }
    ],
    "sg:phone":"+1 925 283 0565",
    "sg:postcode":"94549",
    "sg:province":"CA",
    "wof:name":"Suite 102 Hair Design",
    "wof:placetype":"venue"
},
  "geometry": {"coordinates":[-122.122493,37.891274],"type":"Point"}
}