{
  "type": "Feature",
  "properties": {
    "iso:country":"US",
    "sg:address":"3247 S White Rd",
    "sg:city":"San Jose",
    "sg:classifiers":[
        {
            "category":"Food & Beverages",
            "subcategory":"Bakery",
            "type":"Retail Goods"
        }
    ],
    "sg:phone":"+1 408 239 0345",
    "sg:postcode":"95135",
    "sg:province":"CA",
    "sg:tags":[
        "sandwich"
    ],
    "sg:website":"www.togos.com",
    "wof:name":"Togo's",
    "wof:placetype":"venue"
},
  "geometry": {"coordinates":[-121.79291600000001,37.316068],"type":"Point"}
}