{
  "type": "Feature",
  "properties": {
    "iso:country":"US",
    "sg:address":"333 E Main St",
    "sg:city":"Alhambra",
    "sg:classifiers":[
        {
            "category":"Personal",
            "subcategory":"Beauty Salon",
            "type":"Services"
        }
    ],
    "sg:phone":"+1 626 570 1103",
    "sg:postcode":"91801",
    "sg:province":"CA",
    "wof:name":"PHD",
    "wof:placetype":"venue"
},
  "geometry": {"coordinates":[-118.122883,34.097081],"type":"Point"}
}