{
  "type": "Feature",
  "properties": {
    "iso:country":"US",
    "sg:address":"9535 Garden Grove Blvd",
    "sg:city":"Garden Grove",
    "sg:classifiers":[
        {
            "category":"Professional",
            "type":"Services"
        }
    ],
    "sg:phone":"+1 714 530 1460",
    "sg:postcode":"92844",
    "sg:province":"CA",
    "wof:name":"IL Young Corporation",
    "wof:placetype":"venue"
},
  "geometry": {"coordinates":[-117.965857,33.774051],"type":"Point"}
}