{
  "type": "Feature",
  "properties": {
    "addr:full":"8848 Painter Ave Ste C Whittier CA 90602",
    "addr:housenumber":"8848",
    "addr:postcode":"90602",
    "addr:street":"Painter Ave Ste C",
    "iso:country":"US",
    "sg:address":"8848 Painter Ave Ste C",
    "sg:city":"Whittier",
    "sg:classifiers":[
        {
            "category":"Autos & Motor Vehicles",
            "subcategory":"Motorcycle Sales",
            "type":"Retail Goods"
        }
    ],
    "sg:phone":"+1 562 907 3844",
    "sg:postcode":"90602",
    "sg:province":"CA",
    "sg:tags":[
        "scooters-parts",
        "supply"
    ],
    "wof:name":"Hyevon Speed Shop",
    "wof:placetype":"venue"
},
  "geometry": {"coordinates":[-118.03904300000001,33.957009],"type":"Point"}
}