{
  "type": "Feature",
  "properties": {
    "iso:country":"US",
    "sg:address":"22265 Parrotts Ferry Rd",
    "sg:city":"Sonora",
    "sg:classifiers":[
        {
            "category":"Manufacturing",
            "subcategory":"Food",
            "type":"Manufacturing & Wholesale Goods"
        }
    ],
    "sg:phone":"+1 209 532 3089",
    "sg:postcode":"95370",
    "sg:province":"CA",
    "sg:tags":[
        "brewer"
    ],
    "wof:name":"Old Stamp Mill Brewery",
    "wof:placetype":"venue"
},
  "geometry": {"coordinates":[-120.405326,38.02614],"type":"Point"}
}