{
  "type": "Feature",
  "properties": {
    "addr:full":"500 N Main St Sebastopol CA 95472",
    "addr:housenumber":"500",
    "addr:postcode":"95472",
    "addr:street":"N Main St",
    "iso:country":"US",
    "sg:address":"500 N Main St",
    "sg:city":"Sebastopol",
    "sg:classifiers":[
        {
            "category":"Organizations",
            "subcategory":"Religious Organization",
            "type":"Services"
        }
    ],
    "sg:phone":"+1 707 823 7971",
    "sg:postcode":"95472",
    "sg:province":"CA",
    "sg:tags":[
        "church"
    ],
    "wof:name":"Sebastopol United Methodist",
    "wof:placetype":"venue"
},
  "geometry": {"coordinates":[-122.826752,38.405954],"type":"Point"}
}