{
  "type": "Feature",
  "properties": {
    "addr:full":"1832 Marber Ave Long Beach CA 90815",
    "addr:housenumber":"1832",
    "addr:postcode":"90815",
    "addr:street":"Marber Ave",
    "iso:country":"US",
    "sg:address":"1832 Marber Ave",
    "sg:city":"Long Beach",
    "sg:classifiers":[
        {
            "category":"Professional",
            "subcategory":"Business Services",
            "type":"Services"
        }
    ],
    "sg:phone":"+1 562 431 5023",
    "sg:postcode":"90815",
    "sg:province":"CA",
    "sg:tags":[
        "drafting"
    ],
    "wof:name":"Thompson Design Build Assoc",
    "wof:placetype":"venue"
},
  "geometry": {"coordinates":[-118.12414099999999,33.791176],"type":"Point"}
}