{
  "type": "Feature",
  "properties": {
    "iso:country":"US",
    "sg:address":"51 Hitchcock Way",
    "sg:city":"Santa Barbara",
    "sg:classifiers":[
        {
            "category":"Health Services",
            "subcategory":"Doctor",
            "type":"Services"
        }
    ],
    "sg:phone":"+1 805 563 6133",
    "sg:postcode":"93105",
    "sg:province":"CA",
    "sg:tags":[
        "physician",
        "surgeon"
    ],
    "wof:name":"Prescription Pharmacy",
    "wof:placetype":"venue"
},
  "geometry": {"coordinates":[-119.74455,34.438869],"type":"Point"}
}