{
  "type": "Feature",
  "properties": {
    "addr:full":"1056 Ernst Way Concord CA 94518",
    "addr:housenumber":"1056",
    "addr:postcode":"94518",
    "addr:street":"Ernst Way",
    "iso:country":"US",
    "sg:address":"1056 Ernst Way",
    "sg:city":"Concord",
    "sg:classifiers":[
        {
            "category":"Building & Trades",
            "subcategory":"Cleaning & Sanitation",
            "type":"Services"
        }
    ],
    "sg:phone":"+1 925 459 8332",
    "sg:postcode":"94518",
    "sg:province":"CA",
    "sg:tags":[
        "maintenance"
    ],
    "wof:name":"Fernandez Son Maintenance Land",
    "wof:placetype":"venue"
},
  "geometry": {"coordinates":[-122.04412600000001,37.950013],"type":"Point"}
}