{
  "type": "Feature",
  "properties": {
    "addr:full":"5757 Lucas Valley Rd Nicasio CA 94946",
    "addr:housenumber":"5757",
    "addr:postcode":"94946",
    "addr:street":"Lucas Valley Rd",
    "iso:country":"US",
    "sg:address":"5757 Lucas Valley Rd",
    "sg:city":"Nicasio",
    "sg:classifiers":[
        {
            "category":"Building & Trades",
            "subcategory":"Landscaping Services",
            "type":"Services"
        }
    ],
    "sg:phone":"+1 415 662 2278",
    "sg:postcode":"94946",
    "sg:province":"CA",
    "sg:tags":[
        "lawn",
        "maintenance",
        "grounds"
    ],
    "wof:name":"Ron's Professional Tree Care",
    "wof:placetype":"venue"
},
  "geometry": {"coordinates":[-122.65723199999999,38.056354],"type":"Point"}
}