{
  "type": "Feature",
  "properties": {
    "addr:full":"198 N Arrowhead Ave San Bernardino CA 92408",
    "addr:housenumber":"198",
    "addr:postcode":"92408",
    "addr:street":"N Arrowhead Ave",
    "iso:country":"US",
    "sg:address":"198 N Arrowhead Ave",
    "sg:city":"San Bernardino",
    "sg:classifiers":[
        {
            "category":"Professional",
            "subcategory":"Lawyer & Legal Services",
            "type":"Services"
        }
    ],
    "sg:phone":"+1 909 888 8279",
    "sg:postcode":"92408",
    "sg:province":"CA",
    "sg:tags":[
        "attorney"
    ],
    "wof:name":"Mark L Gunn",
    "wof:placetype":"venue"
},
  "geometry": {"coordinates":[-117.289653,34.101939],"type":"Point"}
}