{
  "type": "Feature",
  "properties": {
    "iso:country":"US",
    "sg:address":"866 S Westmoreland Avenue # 101",
    "sg:city":"Los Angeles",
    "sg:classifiers":[
        {
            "category":"Health Services",
            "subcategory":"Doctor",
            "type":"Services"
        }
    ],
    "sg:phone":"+1 213 380 2266",
    "sg:postcode":"90005",
    "sg:province":"CA",
    "wof:name":"Sun J Shin MD",
    "wof:placetype":"venue"
},
  "geometry": {"coordinates":[-118.289096,34.056659],"type":"Point"}
}