{
  "type": "Feature",
  "properties": {
    "iso:country":"US",
    "sg:address":"530 Union Ave",
    "sg:city":"Fairfield",
    "sg:classifiers":[
        {
            "category":"Government",
            "subcategory":"Court House",
            "type":"Public Place"
        }
    ],
    "sg:phone":"+1 707 432 1896",
    "sg:postcode":"94533",
    "sg:province":"CA",
    "sg:tags":[
        "county"
    ],
    "wof:name":"Solano Superior Court Cmmssnrs",
    "wof:placetype":"venue"
},
  "geometry": {"coordinates":[-122.04044,38.247774],"type":"Point"}
}