{
  "type": "Feature",
  "properties": {
    "iso:country":"US",
    "sg:address":"22143 Dolores St",
    "sg:city":"Carson",
    "sg:classifiers":[
        {
            "category":"Professional",
            "type":"Services"
        }
    ],
    "sg:phone":"+1 310 513 0564",
    "sg:postcode":"90745",
    "sg:province":"CA",
    "wof:name":"A Better World Inc",
    "wof:placetype":"venue"
},
  "geometry": {"coordinates":[-118.272425,33.826045],"type":"Point"}
}