{
  "type": "Feature",
  "properties": {
    "addr:full":"2085 S Hobart Boulevard Los Angeles CA 90018",
    "addr:housenumber":"2085",
    "addr:postcode":"90018",
    "addr:street":"S Hobart Boulevard",
    "iso:country":"US",
    "sg:address":"2085 S Hobart Boulevard",
    "sg:city":"Los Angeles",
    "sg:classifiers":[
        {
            "category":"Social Services",
            "subcategory":"Child Care",
            "type":"Services"
        }
    ],
    "sg:phone":"+1 323 766 0722",
    "sg:postcode":"90018",
    "sg:province":"CA",
    "sg:tags":[
        "day"
    ],
    "wof:name":"Head Start At Christian Fellowship Church",
    "wof:placetype":"venue"
},
  "geometry": {"coordinates":[-118.307975,34.038069],"type":"Point"}
}