{
  "type": "Feature",
  "properties": {
    "iso:country":"US",
    "sg:address":"802 Prospect Blvd",
    "sg:city":"Pasadena",
    "sg:phone":"+1 626 792 9345",
    "sg:postcode":"91103",
    "sg:province":"CA",
    "sg:tags":[
        "equipment",
        "commercial"
    ],
    "wof:name":"Factory Signage & Graphics",
    "wof:placetype":"venue"
},
  "geometry": {"coordinates":[-118.16171900000001,34.157811],"type":"Point"}
}