{
  "type": "Feature",
  "properties": {
    "iso:country":"US",
    "sg:address":"5321 Grey Eagle Dr",
    "sg:city":"Anderson",
    "sg:classifiers":[
        {
            "category":"Professional",
            "subcategory":"Engineering",
            "type":"Services"
        }
    ],
    "sg:phone":"+1 530 365 8812",
    "sg:postcode":"96007",
    "sg:province":"CA",
    "sg:tags":[
        "engineer"
    ],
    "wof:name":"Mintz Engineering",
    "wof:placetype":"venue"
},
  "geometry": {"coordinates":[-122.244439,40.44216],"type":"Point"}
}