{
  "type": "Feature",
  "properties": {
    "iso:country":"US",
    "sg:address":"918 E Holt Ave",
    "sg:city":"Pomona",
    "sg:classifiers":[
        {
            "category":"Shopping",
            "subcategory":"Discount & Variety Stores",
            "type":"Retail Goods"
        }
    ],
    "sg:phone":"+1 909 622 7277",
    "sg:postcode":"91767",
    "sg:province":"CA",
    "sg:tags":[
        "merchandise",
        "general"
    ],
    "wof:name":"Perkins & Sons Sales & Svc",
    "wof:placetype":"venue"
},
  "geometry": {"coordinates":[-117.732087,34.062748],"type":"Point"}
}