{
  "type": "Feature",
  "properties": {
    "addr:full":"9230 Gold Coast Dr San Diego CA 92126",
    "addr:housenumber":"9230",
    "addr:postcode":"92126",
    "addr:street":"Gold Coast Dr",
    "iso:country":"US",
    "sg:address":"9230 Gold Coast Dr",
    "sg:city":"San Diego",
    "sg:classifiers":[
        {
            "category":"Education",
            "subcategory":"School",
            "type":"Public Place"
        }
    ],
    "sg:phone":"+1 858 578 1400",
    "sg:postcode":"92126",
    "sg:province":"CA",
    "sg:tags":[
        "high",
        "junior"
    ],
    "wof:name":"Wangenheim Junior High",
    "wof:placetype":"venue"
},
  "geometry": {"coordinates":[-117.12697199999999,32.905441],"type":"Point"}
}