{
  "type": "Feature",
  "properties": {
    "addr:full":"3321 N Hilliard St Fresno CA 93726",
    "addr:housenumber":"3321",
    "addr:postcode":"93726",
    "addr:street":"N Hilliard",
    "iso:country":"US",
    "sg:address":"3321 N Hilliard St",
    "sg:city":"Fresno",
    "sg:classifiers":[
        {
            "category":"Health Services",
            "subcategory":"Doctor",
            "type":"Services"
        }
    ],
    "sg:phone":"+1 559 227 3602",
    "sg:postcode":"93726",
    "sg:province":"CA",
    "sg:tags":[
        "dentist"
    ],
    "wof:name":"Steve J Lee DDS",
    "wof:placetype":"venue"
},
  "geometry": {"coordinates":[-119.76625799999999,36.779988],"type":"Point"}
}