{
  "type": "Feature",
  "properties": {
    "addr:full":"5405 Lindley Ave Tarzana CA 91356",
    "addr:housenumber":"5405",
    "addr:postcode":"91356",
    "addr:street":"Lindley Ave",
    "iso:country":"US",
    "sg:address":"5405 Lindley Ave",
    "sg:city":"Tarzana",
    "sg:classifiers":[
        {
            "category":"Real Estate",
            "subcategory":"Real Estate Operator",
            "type":"Services"
        }
    ],
    "sg:phone":"+1 818 996 7199",
    "sg:postcode":"91356",
    "sg:province":"CA",
    "sg:tags":[
        "apartment"
    ],
    "wof:name":"Lindley Manor Apartments",
    "wof:placetype":"venue"
},
  "geometry": {"coordinates":[-118.527345,34.167861],"type":"Point"}
}