{
  "type": "Feature",
  "properties": {
    "addr:full":"795 Tucker Rd Tehachapi CA 93561",
    "addr:housenumber":"795",
    "addr:postcode":"93561",
    "addr:street":"Tucker Rd",
    "iso:country":"US",
    "sg:address":"795 Tucker Rd",
    "sg:city":"Tehachapi",
    "sg:classifiers":[
        {
            "category":"Restaurant",
            "type":"Food & Drink"
        }
    ],
    "sg:phone":"+1 661 822 0948",
    "sg:postcode":"93561",
    "sg:province":"CA",
    "wof:name":"Mc Donald's",
    "wof:placetype":"venue"
},
  "geometry": {"coordinates":[-118.46785199999999,35.118068],"type":"Point"}
}