{
  "type": "Feature",
  "properties": {
    "iso:country":"US",
    "sg:address":"1172 Murphy Ave",
    "sg:city":"San Jose",
    "sg:classifiers":[
        {
            "category":"Banks & Credit Unions",
            "subcategory":"Financial Services",
            "type":"Services"
        }
    ],
    "sg:phone":"+1 408 573 7232",
    "sg:postcode":"95131",
    "sg:province":"CA",
    "sg:tags":[
        "broker",
        "mortgage"
    ],
    "wof:name":"Pacific Rim Financial & Investments Inc",
    "wof:placetype":"venue"
},
  "geometry": {"coordinates":[-121.893936,37.382601],"type":"Point"}
}