{
  "type": "Feature",
  "properties": {
    "iso:country":"US",
    "sg:address":"362 Reservation Rd",
    "sg:city":"Marina",
    "sg:classifiers":[
        {
            "category":"Autos & Motor Vehicles",
            "subcategory":"Automobile Sales",
            "type":"Retail Goods"
        }
    ],
    "sg:phone":"+1 831 384 6095",
    "sg:postcode":"93933",
    "sg:province":"CA",
    "sg:tags":[
        "dealers-used",
        "car",
        "used",
        "cars-wholesale",
        "new"
    ],
    "wof:name":"Cuquis Cars",
    "wof:placetype":"venue"
},
  "geometry": {"coordinates":[-121.788443,36.682309],"type":"Point"}
}