{
  "type": "Feature",
  "properties": {
    "iso:country":"US",
    "sg:address":"721 Francisco Blvd E",
    "sg:city":"San Rafael",
    "sg:classifiers":[
        {
            "category":"Wholesale",
            "subcategory":"Furniture",
            "type":"Manufacturing & Wholesale Goods"
        }
    ],
    "sg:phone":"+1 415 256 9616",
    "sg:postcode":"94901",
    "sg:province":"CA",
    "wof:name":"Brothers Furniture Warehouse",
    "wof:placetype":"venue"
},
  "geometry": {"coordinates":[-122.510593,37.963247],"type":"Point"}
}