{
  "type": "Feature",
  "properties": {
    "iso:country":"US",
    "sg:address":"100 World Way",
    "sg:city":"Los Angeles",
    "sg:classifiers":[
        {
            "category":"Restaurant",
            "type":"Food & Drink"
        }
    ],
    "sg:phone":"+1 310 216 0992",
    "sg:postcode":"90045",
    "sg:province":"CA",
    "wof:name":"Mac Donalds Termnal 1",
    "wof:placetype":"venue"
},
  "geometry": {"coordinates":[-118.406209,33.944711],"type":"Point"}
}