{
  "type": "Feature",
  "properties": {
    "iso:country":"US",
    "sg:address":"21801 Pittsford",
    "sg:city":"Lake Forest",
    "sg:classifiers":[
        {
            "category":"Education",
            "subcategory":"School",
            "type":"Public Place"
        }
    ],
    "sg:phone":"+1 949 830 9945",
    "sg:postcode":"92630",
    "sg:province":"CA",
    "sg:tags":[
        "high",
        "middle",
        "elementary"
    ],
    "wof:name":"Lake Forest Elementary School",
    "wof:placetype":"venue"
},
  "geometry": {"coordinates":[-117.670644,33.645522],"type":"Point"}
}