{
  "type": "Feature",
  "properties": {
    "iso:country":"US",
    "sg:address":"1466 Greenbriar Ave",
    "sg:city":"Corona",
    "sg:classifiers":[
        {
            "category":"Shopping",
            "subcategory":"Computers & Home Electronics",
            "type":"Retail Goods"
        }
    ],
    "sg:phone":"+1 951 340 2111",
    "sg:postcode":"92880",
    "sg:province":"CA",
    "sg:tags":[
        "software"
    ],
    "wof:name":"Simplex",
    "wof:placetype":"venue"
},
  "geometry": {"coordinates":[-117.585719,33.900683],"type":"Point"}
}