{
  "type": "Feature",
  "properties": {
    "addr:full":"1875 Pandora Dr San Jose CA 95124",
    "addr:housenumber":"1875",
    "addr:postcode":"95124",
    "addr:street":"Pandora Dr",
    "iso:country":"US",
    "sg:address":"1875 Pandora Dr",
    "sg:city":"San Jose",
    "sg:classifiers":[
        {
            "category":"Manufacturing",
            "subcategory":"Food",
            "type":"Manufacturing & Wholesale Goods"
        }
    ],
    "sg:phone":"+1 408 559 3255",
    "sg:postcode":"95124",
    "sg:province":"CA",
    "sg:tags":[
        "preparation",
        "mfg"
    ],
    "wof:name":"Denises Dry Rubs",
    "wof:placetype":"venue"
},
  "geometry": {"coordinates":[-121.922754,37.270448],"type":"Point"}
}