{
  "type": "Feature",
  "properties": {
    "iso:country":"US",
    "sg:address":"514 Ewing St",
    "sg:city":"Trinidad",
    "sg:classifiers":[
        {
            "category":"Manufacturing",
            "subcategory":"Printing",
            "type":"Manufacturing & Wholesale Goods"
        }
    ],
    "sg:phone":"+1 707 677 9010",
    "sg:postcode":"95570",
    "sg:province":"CA",
    "sg:tags":[
        "printer"
    ],
    "wof:name":"Linpress Printing Co",
    "wof:placetype":"venue"
},
  "geometry": {"coordinates":[-124.147488,41.059756],"type":"Point"}
}