{
  "type": "Feature",
  "properties": {
    "iso:country":"US",
    "sg:address":"9939 Norwalk Blvd",
    "sg:city":"Santa Fe Springs",
    "sg:classifiers":[
        {
            "category":"Freight",
            "type":"Transportation"
        }
    ],
    "sg:phone":"+1 562 906 6320",
    "sg:postcode":"90670",
    "sg:province":"CA",
    "sg:tags":[
        "operator",
        "local",
        "trucking"
    ],
    "wof:name":"Space Age Delivery",
    "wof:placetype":"venue"
},
  "geometry": {"coordinates":[-118.072671,33.947037],"type":"Point"}
}