{
  "type": "Feature",
  "properties": {
    "iso:country":"US",
    "sg:address":"7060 Miramar Rd",
    "sg:city":"San Diego",
    "sg:classifiers":[
        {
            "category":"Banks & Credit Unions",
            "subcategory":"Bank",
            "type":"Services"
        }
    ],
    "sg:phone":"+1 858 566 1777",
    "sg:postcode":"92121",
    "sg:province":"CA",
    "sg:tags":[
        "loan",
        "real estate"
    ],
    "wof:name":"Hobson Funding Inc",
    "wof:placetype":"venue"
},
  "geometry": {"coordinates":[-117.164549,32.878853],"type":"Point"}
}