{
  "type": "Feature",
  "properties": {
    "iso:country":"US",
    "sg:address":"7291 Martin Ln",
    "sg:city":"Ione",
    "sg:classifiers":[
        {
            "category":"Wholesale",
            "subcategory":"Durable Goods & Equipment",
            "type":"Manufacturing & Wholesale Goods"
        }
    ],
    "sg:phone":"+1 209 274 4890",
    "sg:postcode":"95640",
    "sg:province":"CA",
    "sg:tags":[
        "representative",
        "manufacturer"
    ],
    "wof:name":"J C Sales & Mfg Co",
    "wof:placetype":"venue"
},
  "geometry": {"coordinates":[-120.94502,38.309012],"type":"Point"}
}