{
  "type": "Feature",
  "properties": {
    "iso:country":"US",
    "sg:address":"2781 Lemon Grove Ave",
    "sg:city":"Lemon Grove",
    "sg:classifiers":[
        {
            "category":"Insurance",
            "subcategory":"Insurance Agent",
            "type":"Services"
        }
    ],
    "sg:phone":"+1 619 465 9100",
    "sg:postcode":"91945",
    "sg:province":"CA",
    "wof:name":"Horton Insurance",
    "wof:placetype":"venue"
},
  "geometry": {"coordinates":[-117.031575,32.735005],"type":"Point"}
}