{
  "type": "Feature",
  "properties": {
    "iso:country":"US",
    "sg:address":"777 Cypress Ave",
    "sg:city":"Redding",
    "sg:classifiers":[
        {
            "category":"Coffee & Tea",
            "type":"Food & Drink"
        },
        {
            "category":"Restaurant",
            "type":"Food & Drink"
        }
    ],
    "sg:phone":"+1 530 241 6490",
    "sg:postcode":"96001",
    "sg:province":"CA",
    "sg:tags":[
        "shop",
        "espresso"
    ],
    "wof:name":"City Java",
    "wof:placetype":"venue"
},
  "geometry": {"coordinates":[-122.380836,40.574479],"type":"Point"}
}