{
  "type": "Feature",
  "properties": {
    "iso:country":"US",
    "sg:address":"174 Lower Grass Valley Rd",
    "sg:city":"Nevada City",
    "sg:classifiers":[
        {
            "category":"Wholesale",
            "subcategory":"Machinery & Supplies",
            "type":"Manufacturing & Wholesale Goods"
        }
    ],
    "sg:phone":"+1 530 470 1990",
    "sg:postcode":"95959",
    "sg:province":"CA",
    "sg:tags":[
        "spraying",
        "equipment"
    ],
    "wof:name":"United States Legends",
    "wof:placetype":"venue"
},
  "geometry": {"coordinates":[-121.025767,39.248077],"type":"Point"}
}