{
  "type": "Feature",
  "properties": {
    "addr:full":"600 N Avalon Blvd Wilmington CA 90744",
    "addr:housenumber":"600",
    "addr:postcode":"90744",
    "addr:street":"N Avalon Blvd",
    "iso:country":"US",
    "sg:address":"600 N Avalon Blvd",
    "sg:city":"Wilmington",
    "sg:classifiers":[
        {
            "category":"Professional",
            "type":"Services"
        },
        {
            "category":"Shopping",
            "subcategory":"Bicycles & Sporting Goods",
            "type":"Retail Goods"
        }
    ],
    "sg:phone":"+1 310 518 2927",
    "sg:postcode":"90744",
    "sg:province":"CA",
    "sg:tags":[
        "equipment",
        "soccer",
        "supply"
    ],
    "wof:name":"Kismet Soccer Kings Inc",
    "wof:placetype":"venue"
},
  "geometry": {"coordinates":[-118.262317,33.778524],"type":"Point"}
}