{
  "type": "Feature",
  "properties": {
    "addr:full":"17627 Ventura Blvd Encino CA 91316",
    "addr:housenumber":"17627",
    "addr:postcode":"91316",
    "addr:street":"Ventura Blvd",
    "iso:country":"US",
    "sg:address":"17627 Ventura Blvd",
    "sg:city":"Encino",
    "sg:classifiers":[
        {
            "category":"Sports & Exercise",
            "subcategory":"Gym",
            "type":"Entertainment"
        }
    ],
    "sg:phone":"+1 818 986 7212",
    "sg:postcode":"91316",
    "sg:province":"CA",
    "sg:tags":[
        "club",
        "health",
        "studio",
        "gymnasium"
    ],
    "sg:website":"www.curvesinternational.com",
    "wof:name":"Curves For Women Sherman Oaks",
    "wof:placetype":"venue"
},
  "geometry": {"coordinates":[-118.518485,34.162479],"type":"Point"}
}