{
  "type": "Feature",
  "properties": {
    "addr:full":"4083 Emery St Emeryville CA 94608",
    "addr:housenumber":"4083",
    "addr:postcode":"94608",
    "addr:street":"Emery St",
    "iso:country":"US",
    "sg:address":"4083 Emery St",
    "sg:city":"Emeryville",
    "sg:classifiers":[
        {
            "category":"Professional",
            "type":"Services"
        }
    ],
    "sg:phone":"+1 510 653 8121",
    "sg:postcode":"94608",
    "sg:province":"CA",
    "sg:tags":[
        "clothing",
        "women's"
    ],
    "wof:name":"Karen Alexander Dresses",
    "wof:placetype":"venue"
},
  "geometry": {"coordinates":[-122.281998,37.831902],"type":"Point"}
}