{
  "type": "Feature",
  "properties": {
    "iso:country":"US",
    "sg:address":"771 Perkins Way",
    "sg:city":"Sacramento",
    "sg:classifiers":[
        {
            "category":"Building & Trades",
            "subcategory":"Construction",
            "type":"Services"
        }
    ],
    "sg:phone":"+1 916 443 0648",
    "sg:postcode":"95818",
    "sg:province":"CA",
    "sg:tags":[
        "concrete",
        "contractor"
    ],
    "wof:name":"Jay WEBB Construction",
    "wof:placetype":"venue"
},
  "geometry": {"coordinates":[-121.50739799999999,38.552439],"type":"Point"}
}