{
  "type": "Feature",
  "properties": {
    "addr:full":"2005 de la Cruz Blvd Santa Clara CA 95050",
    "addr:housenumber":"2005",
    "addr:postcode":"95050",
    "addr:street":"De La Cruz Blvd",
    "iso:country":"US",
    "sg:address":"2005 de la Cruz Blvd",
    "sg:city":"Santa Clara",
    "sg:classifiers":[
        {
            "category":"Manufacturing",
            "subcategory":"Electronics",
            "type":"Manufacturing & Wholesale Goods"
        }
    ],
    "sg:phone":"+1 408 748 9200",
    "sg:postcode":"95050",
    "sg:province":"CA",
    "sg:tags":[
        "equipment",
        "electronic",
        "supply"
    ],
    "wof:name":"Nanomotion Inc",
    "wof:placetype":"venue"
},
  "geometry": {"coordinates":[-121.941435,37.363382],"type":"Point"}
}