{
  "type": "Feature",
  "properties": {
    "addr:full":"6461 Roland St Buena Park CA 90621",
    "addr:housenumber":"6461",
    "addr:postcode":"90621",
    "addr:street":"Roland St",
    "iso:country":"US",
    "sg:address":"6461 Roland St",
    "sg:city":"Buena Park",
    "sg:classifiers":[
        {
            "category":"Wholesale",
            "subcategory":"Hardware",
            "type":"Manufacturing & Wholesale Goods"
        },
        {
            "category":"Manufacturing",
            "subcategory":"Retail Goods",
            "type":"Manufacturing & Wholesale Goods"
        }
    ],
    "sg:phone":"+1 714 522 2229",
    "sg:postcode":"90621",
    "sg:province":"CA",
    "sg:tags":[
        "box",
        "mail",
        "product",
        "mfg"
    ],
    "wof:name":"Ace Manufacturing",
    "wof:placetype":"venue"
},
  "geometry": {"coordinates":[-117.98308,33.86633],"type":"Point"}
}