{
  "type": "Feature",
  "properties": {
    "iso:country":"US",
    "sg:address":"501 Sequoia St",
    "sg:city":"Morro Bay",
    "sg:classifiers":[
        {
            "category":"Social Services",
            "subcategory":"Child Care",
            "type":"Services"
        }
    ],
    "sg:phone":"+1 805 772 2047",
    "sg:postcode":"93442",
    "sg:province":"CA",
    "wof:name":"Kids Club",
    "wof:placetype":"venue"
},
  "geometry": {"coordinates":[-120.858637,35.395953],"type":"Point"}
}