{
  "type": "Feature",
  "properties": {
    "addr:full":"1201 K St Sacramento CA 95814",
    "addr:housenumber":"1201",
    "addr:postcode":"95814",
    "addr:street":"K St",
    "iso:country":"US",
    "sg:address":"1201 K St",
    "sg:city":"Sacramento",
    "sg:classifiers":[
        {
            "category":"Professional",
            "subcategory":"Management & Consulting",
            "type":"Services"
        }
    ],
    "sg:phone":"+1 916 447 0448",
    "sg:postcode":"95814",
    "sg:province":"CA",
    "sg:tags":[
        "lobbyist"
    ],
    "wof:name":"Leesa Speer-Barish",
    "wof:placetype":"venue"
},
  "geometry": {"coordinates":[-121.48969099999999,38.578073],"type":"Point"}
}