{
  "type": "Feature",
  "properties": {
    "addr:full":"10125 Hole Ave Riverside CA 92503",
    "addr:housenumber":"10125",
    "addr:postcode":"92503",
    "addr:street":"Hole Ave",
    "iso:country":"US",
    "sg:address":"10125 Hole Ave",
    "sg:city":"Riverside",
    "sg:classifiers":[
        {
            "category":"Shopping",
            "subcategory":"Bicycles & Sporting Goods",
            "type":"Retail Goods"
        }
    ],
    "sg:phone":"+1 951 359 6629",
    "sg:postcode":"92503",
    "sg:province":"CA",
    "sg:tags":[
        "equipment",
        "skateboard"
    ],
    "wof:name":"C & C Worldwide",
    "wof:placetype":"venue"
},
  "geometry": {"coordinates":[-117.45936399999999,33.914507],"type":"Point"}
}