{
  "type": "Feature",
  "properties": {
    "addr:full":"336 Roberts Ln Bakersfield CA 93308",
    "addr:housenumber":"336",
    "addr:postcode":"93308",
    "addr:street":"Roberts Ln",
    "iso:country":"US",
    "sg:address":"336 Roberts Ln",
    "sg:city":"Bakersfield",
    "sg:classifiers":[
        {
            "category":"Real Estate",
            "subcategory":"Real Estate Operator",
            "type":"Services"
        }
    ],
    "sg:phone":"+1 661 399 9533",
    "sg:postcode":"93308",
    "sg:province":"CA",
    "sg:tags":[
        "apartment"
    ],
    "wof:name":"River Oaks Apartments",
    "wof:placetype":"venue"
},
  "geometry": {"coordinates":[-119.02789,35.408725],"type":"Point"}
}