{
  "type": "Feature",
  "properties": {
    "addr:full":"30082 Melinda Rd Rcho Sta Marg CA 92688",
    "addr:postcode":"30082;92688",
    "addr:street":"Melinda Rd;Sta Marg",
    "iso:country":"US",
    "sg:address":"30082 Melinda Rd",
    "sg:city":"Rcho Sta Marg",
    "sg:classifiers":[
        {
            "category":"Organizations",
            "subcategory":"Professional Association",
            "type":"Services"
        }
    ],
    "sg:phone":"+1 949 459 5379",
    "sg:postcode":"92688",
    "sg:province":"CA",
    "wof:name":"Altisima Park",
    "wof:placetype":"venue"
},
  "geometry": {"coordinates":[-117.61565400000001,33.664817],"type":"Point"}
}