{
  "type": "Feature",
  "properties": {
    "addr:full":"9064 Edinger Ave Fountain Valley CA 92708",
    "addr:housenumber":"9064",
    "addr:postcode":"92708",
    "addr:street":"Edinger Ave",
    "iso:country":"US",
    "sg:address":"9064 Edinger Ave",
    "sg:city":"Fountain Valley",
    "sg:classifiers":[
        {
            "category":"Retail",
            "subcategory":"Laundry & Dry Cleaning",
            "type":"Services"
        }
    ],
    "sg:phone":"+1 714 848 8611",
    "sg:postcode":"92708",
    "sg:province":"CA",
    "wof:name":"Edinger Cleaners",
    "wof:placetype":"venue"
},
  "geometry": {"coordinates":[-117.97199999999999,33.730202],"type":"Point"}
}