{
  "type": "Feature",
  "properties": {
    "iso:country":"US",
    "sg:address":"705 Lighthouse Ave",
    "sg:city":"Pacific Grove",
    "sg:classifiers":[
        {
            "category":"Professional",
            "subcategory":"Accounting & Tax Preparation",
            "type":"Services"
        }
    ],
    "sg:phone":"+1 831 372 8100",
    "sg:postcode":"93950",
    "sg:province":"CA",
    "sg:tags":[
        "bookkeeping",
        "general"
    ],
    "wof:name":"Monterey Bay Bookkeeping",
    "wof:placetype":"venue"
},
  "geometry": {"coordinates":[-121.92117500000001,36.622598],"type":"Point"}
}