{
  "type": "Feature",
  "properties": {
    "iso:country":"US",
    "sg:address":"800 S Harbor Blvd",
    "sg:city":"Anaheim",
    "sg:classifiers":[
        {
            "category":"Banks & Credit Unions",
            "subcategory":"Financial Services",
            "type":"Services"
        }
    ],
    "sg:phone":"+1 714 491 7400",
    "sg:postcode":"92805",
    "sg:province":"CA",
    "sg:tags":[
        "broker",
        "mortgage"
    ],
    "wof:name":"First Star Lending Inc",
    "wof:placetype":"venue"
},
  "geometry": {"coordinates":[-117.91651299999999,33.825473],"type":"Point"}
}