{
  "type": "Feature",
  "properties": {
    "addr:full":"320 N Washington St Lodi CA 95240",
    "addr:housenumber":"320",
    "addr:postcode":"95240",
    "addr:street":"N Washington St",
    "iso:country":"US",
    "sg:address":"320 N Washington St",
    "sg:city":"Lodi",
    "sg:classifiers":[
        {
            "category":"Organizations",
            "subcategory":"Community Association",
            "type":"Services"
        }
    ],
    "sg:phone":"+1 209 368 1420",
    "sg:postcode":"95240",
    "sg:province":"CA",
    "sg:tags":[
        "military"
    ],
    "wof:name":"American Legion",
    "wof:placetype":"venue"
},
  "geometry": {"coordinates":[-121.267601,38.13814],"type":"Point"}
}