{
  "type": "Feature",
  "properties": {
    "iso:country":"US",
    "sg:address":"675 W Oakland Ave",
    "sg:city":"Hemet",
    "sg:classifiers":[
        {
            "category":"Real Estate",
            "subcategory":"Real Estate Operator",
            "type":"Services"
        }
    ],
    "sg:phone":"+1 951 925 3418",
    "sg:postcode":"92543",
    "sg:province":"CA",
    "sg:tags":[
        "mobile",
        "home",
        "community"
    ],
    "wof:name":"Hemet Valley Mobile Estates",
    "wof:placetype":"venue"
},
  "geometry": {"coordinates":[-116.977936,33.754685],"type":"Point"}
}