{
  "type": "Feature",
  "properties": {
    "iso:country":"US",
    "sg:address":"2916 Willetts Way",
    "sg:city":"Ceres",
    "sg:classifiers":[
        {
            "category":"Building & Trades",
            "subcategory":"Cleaning & Sanitation",
            "type":"Services"
        }
    ],
    "sg:phone":"+1 209 538 2067",
    "sg:postcode":"95307",
    "sg:province":"CA",
    "sg:tags":[
        "janitor"
    ],
    "wof:name":"S M Cleaning Concept",
    "wof:placetype":"venue"
},
  "geometry": {"coordinates":[-120.965047,37.591055],"type":"Point"}
}