{
  "type": "Feature",
  "properties": {
    "addr:full":"5410 Wilshire Blvd Los Angeles CA 90036",
    "addr:housenumber":"5410",
    "addr:postcode":"90036",
    "addr:street":"Wilshire Blvd",
    "iso:country":"US",
    "sg:address":"5410 Wilshire Blvd",
    "sg:city":"Los Angeles",
    "sg:classifiers":[
        {
            "category":"Building & Trades",
            "subcategory":"Construction",
            "type":"Services"
        }
    ],
    "sg:phone":"+1 323 934 4414",
    "sg:postcode":"90036",
    "sg:province":"CA",
    "sg:tags":[
        "home",
        "builder"
    ],
    "wof:name":"Jennings Home & Commercial",
    "wof:placetype":"venue"
},
  "geometry": {"coordinates":[-118.346957,34.062153],"type":"Point"}
}