{
  "type": "Feature",
  "properties": {
    "addr:full":"7253 Lankershim Blvd North Hollywood CA 91605",
    "addr:housenumber":"7253",
    "addr:postcode":"91605",
    "addr:street":"Lankershim Blvd",
    "iso:country":"US",
    "sg:address":"7253 Lankershim Blvd",
    "sg:city":"North Hollywood",
    "sg:classifiers":[
        {
            "category":"Sports & Exercise",
            "subcategory":"Bicycle Rental",
            "type":"Entertainment"
        }
    ],
    "sg:phone":"+1 818 765 3131",
    "sg:postcode":"91605",
    "sg:province":"CA",
    "sg:tags":[
        "wear"
    ],
    "wof:name":"Allpro Sports",
    "wof:placetype":"venue"
},
  "geometry": {"coordinates":[-118.387935,34.202136],"type":"Point"}
}