{
  "type": "Feature",
  "properties": {
    "addr:full":"7235 Pacific Ave Pleasant Grove CA 95668",
    "addr:housenumber":"7235",
    "addr:postcode":"95668",
    "addr:street":"Pacific Ave",
    "iso:country":"US",
    "sg:address":"7235 Pacific Ave",
    "sg:city":"Pleasant Grove",
    "sg:classifiers":[
        {
            "category":"Freight",
            "type":"Transportation"
        }
    ],
    "sg:phone":"+1 916 655 3111",
    "sg:postcode":"95668",
    "sg:province":"CA",
    "sg:tags":[
        "grain",
        "elevator"
    ],
    "wof:name":"Busch Agricultural Resources",
    "wof:placetype":"venue"
},
  "geometry": {"coordinates":[-121.52540399999999,38.77055],"type":"Point"}
}