{
  "type": "Feature",
  "properties": {
    "addr:full":"8105 Edgewater Dr Oakland CA 94621",
    "addr:housenumber":"8105",
    "addr:postcode":"94621",
    "addr:street":"Edgewater Dr",
    "iso:country":"US",
    "sg:address":"8105 Edgewater Dr",
    "sg:city":"Oakland",
    "sg:classifiers":[
        {
            "category":"Insurance",
            "subcategory":"Insurance Agent",
            "type":"Services"
        },
        {
            "category":"Insurance",
            "subcategory":"Hazard Insurance",
            "type":"Services"
        },
        {
            "category":"Insurance",
            "subcategory":"Health Insurance",
            "type":"Services"
        }
    ],
    "sg:phone":"+1 510 562 7000",
    "sg:postcode":"94621",
    "sg:province":"CA",
    "sg:tags":[
        "employee",
        "auto",
        "benefit",
        "commercial",
        "business"
    ],
    "sg:website":"http://www.farmersagent.com/skim2",
    "wof:name":"Sukwon Kim Insurance Agency Farmers Insurance",
    "wof:placetype":"venue"
},
  "geometry": {"coordinates":[-122.201489,37.73984],"type":"Point"}
}