{
  "type": "Feature",
  "properties": {
    "addr:full":"40396 State Hwy 41 Oakhurst CA 93644",
    "addr:housenumber":"40396",
    "addr:postcode":"93644",
    "addr:street":"State Hwy 41",
    "iso:country":"US",
    "sg:address":"40396 State Hwy 41",
    "sg:city":"Oakhurst",
    "sg:classifiers":[
        {
            "category":"Professional",
            "subcategory":"Employment Agencies",
            "type":"Services"
        }
    ],
    "sg:phone":"+1 559 692 2302",
    "sg:postcode":"93644",
    "sg:province":"CA",
    "sg:tags":[
        "opportunity"
    ],
    "wof:name":"Execunet Technical Recruiters",
    "wof:placetype":"venue"
},
  "geometry": {"coordinates":[-119.647183,37.334278],"type":"Point"}
}