{
  "type": "Feature",
  "properties": {
    "iso:country":"US",
    "sg:address":"5245 Ave Encinas",
    "sg:city":"Carlsbad",
    "sg:classifiers":[
        {
            "category":"Retail",
            "subcategory":"Repair Shop",
            "type":"Services"
        }
    ],
    "sg:phone":"+1 760 431 9102",
    "sg:postcode":"92008",
    "sg:province":"CA",
    "sg:tags":[
        "plumbing",
        "con",
        "refrigeration",
        "heating",
        "air"
    ],
    "wof:name":"Ram Air Engineering Inc",
    "wof:placetype":"venue"
},
  "geometry": {"coordinates":[-117.330062,33.132742],"type":"Point"}
}