{
  "type": "Feature",
  "properties": {
    "iso:country":"US",
    "sg:address":"2005 W Raymer Ave",
    "sg:city":"Fullerton",
    "sg:classifiers":[
        {
            "category":"Manufacturing",
            "subcategory":"Tools & Machinery",
            "type":"Manufacturing & Wholesale Goods"
        }
    ],
    "sg:phone":"+1 714 680 4323",
    "sg:postcode":"92833",
    "sg:province":"CA",
    "sg:tags":[
        "industrial",
        "mfg"
    ],
    "wof:name":"Dinkos Machinery Co",
    "wof:placetype":"venue"
},
  "geometry": {"coordinates":[-117.964094,33.872114],"type":"Point"}
}