{
  "type": "Feature",
  "properties": {
    "addr:full":"1800 E Gage Ave Los Angeles CA 90001",
    "addr:housenumber":"1800",
    "addr:postcode":"90001",
    "addr:street":"E Gage Ave",
    "iso:country":"US",
    "sg:address":"1800 E Gage Ave",
    "sg:city":"Los Angeles",
    "sg:classifiers":[
        {
            "category":"Autos & Motor Vehicles",
            "subcategory":"Automobile Sales",
            "type":"Retail Goods"
        }
    ],
    "sg:phone":"+1 323 589 4760",
    "sg:postcode":"90001",
    "sg:province":"CA",
    "sg:tags":[
        "car",
        "dealer"
    ],
    "wof:name":"Almazan Enterprise",
    "wof:placetype":"venue"
},
  "geometry": {"coordinates":[-118.238961,33.982011],"type":"Point"}
}