{
  "type": "Feature",
  "properties": {
    "addr:full":"2992 Freeport Blvd Sacramento CA 95818",
    "addr:housenumber":"2992",
    "addr:postcode":"95818",
    "addr:street":"Freeport Blvd",
    "iso:country":"US",
    "sg:address":"2992 Freeport Blvd",
    "sg:city":"Sacramento",
    "sg:classifiers":[
        {
            "category":"Shopping",
            "subcategory":"Shoes",
            "type":"Retail Goods"
        }
    ],
    "sg:phone":"+1 916 442 2559",
    "sg:postcode":"95818",
    "sg:province":"CA",
    "sg:tags":[
        "store"
    ],
    "wof:name":"Shoe Daca",
    "wof:placetype":"venue"
},
  "geometry": {"coordinates":[-121.48885900000001,38.550739],"type":"Point"}
}