{
  "type": "Feature",
  "properties": {
    "addr:full":"11101 Freer St Temple City CA 91780",
    "addr:postcode":"11101;91780",
    "addr:street":"Freer St",
    "iso:country":"US",
    "sg:address":"11101 Freer St",
    "sg:city":"Temple City",
    "sg:classifiers":[
        {
            "category":"Professional",
            "subcategory":"Management & Consulting",
            "type":"Services"
        }
    ],
    "sg:phone":"+1 626 618 8818",
    "sg:postcode":"91780",
    "sg:province":"CA",
    "sg:tags":[
        "international",
        "business"
    ],
    "wof:name":"Baijia International Inc",
    "wof:placetype":"venue"
},
  "geometry": {"coordinates":[-118.026577,34.100707],"type":"Point"}
}