{
  "type": "Feature",
  "properties": {
    "iso:country":"US",
    "sg:address":"1111 Pine St",
    "sg:city":"Oakland",
    "sg:classifiers":[
        {
            "category":"Freight",
            "type":"Transportation"
        }
    ],
    "sg:phone":"+1 510 986 8792",
    "sg:postcode":"94607",
    "sg:province":"CA",
    "sg:tags":[
        "warehouse",
        "self",
        "storage"
    ],
    "wof:name":"Bayport Warehouse",
    "wof:placetype":"venue"
},
  "geometry": {"coordinates":[-122.300395,37.812485],"type":"Point"}
}