{
  "type": "Feature",
  "properties": {
    "addr:full":"3376 Butte House Rd Yuba City CA 95993",
    "addr:housenumber":"3376",
    "addr:postcode":"95993",
    "addr:street":"Butte House Rd",
    "iso:country":"US",
    "sg:address":"3376 Butte House Rd",
    "sg:city":"Yuba City",
    "sg:classifiers":[
        {
            "category":"Shopping",
            "subcategory":"Gifts & Souvenirs",
            "type":"Retail Goods"
        }
    ],
    "sg:phone":"+1 530 674 8733",
    "sg:postcode":"95993",
    "sg:province":"CA",
    "sg:tags":[
        "shop"
    ],
    "wof:name":"Barrow's Gift Shoppe",
    "wof:placetype":"venue"
},
  "geometry": {"coordinates":[-121.677392,39.157431],"type":"Point"}
}