{
  "type": "Feature",
  "properties": {
    "iso:country":"US",
    "sg:address":"6211 Country View Ln",
    "sg:city":"Riverside",
    "sg:classifiers":[
        {
            "category":"Professional",
            "subcategory":"Art Services",
            "type":"Services"
        }
    ],
    "sg:phone":"+1 951 274 0482",
    "sg:postcode":"92504",
    "sg:province":"CA",
    "sg:tags":[
        "consultant",
        "photographic"
    ],
    "wof:name":"Richmont Creations",
    "wof:placetype":"venue"
},
  "geometry": {"coordinates":[-117.42371,33.959545],"type":"Point"}
}