{
  "type": "Feature",
  "properties": {
    "iso:country":"US",
    "sg:address":"823 S Atlantic Blvd",
    "sg:city":"Monterey Park",
    "sg:classifiers":[
        {
            "category":"Health Services",
            "subcategory":"Doctor",
            "type":"Services"
        }
    ],
    "sg:phone":"+1 323 283 3662",
    "sg:postcode":"91754",
    "sg:province":"CA",
    "sg:tags":[
        "surgeon",
        "oral"
    ],
    "wof:name":"Sekiguchi Jill DDS",
    "wof:placetype":"venue"
},
  "geometry": {"coordinates":[-118.136002,34.053902],"type":"Point"}
}