{
  "type": "Feature",
  "properties": {
    "iso:country":"US",
    "sg:address":"410 E Dennett Ave",
    "sg:city":"Fresno",
    "sg:classifiers":[
        {
            "category":"Education",
            "subcategory":"School",
            "type":"Public Place"
        }
    ],
    "sg:phone":"+1 559 457 3150",
    "sg:postcode":"93728",
    "sg:province":"CA",
    "sg:tags":[
        "elementary"
    ],
    "sg:website":"http://www.fresno.k12.ca.us",
    "wof:name":"Muir Elementary School",
    "wof:placetype":"venue"
},
  "geometry": {"coordinates":[-119.806838,36.755791],"type":"Point"}
}