{
  "type": "Feature",
  "properties": {
    "iso:country":"US",
    "sg:address":"12061 Woodside Ave",
    "sg:city":"Lakeside",
    "sg:classifiers":[
        {
            "category":"Restaurant",
            "type":"Food & Drink"
        }
    ],
    "sg:menulink":"http://www.allmenus.com/ca/san-diego/198132-kfc---kentucky-fried-chicken/menu/",
    "sg:phone":"+1 619 561 8694",
    "sg:postcode":"92040",
    "sg:province":"CA",
    "sg:tags":[
        "american",
        "chicken"
    ],
    "wof:name":"KFC - Kentucky Fried Chicken",
    "wof:placetype":"venue"
},
  "geometry": {"coordinates":[-116.93212800000001,32.855602],"type":"Point"}
}