{
  "type": "Feature",
  "properties": {
    "iso:country":"US",
    "sg:address":"2990 Soquel Ave",
    "sg:city":"Santa Cruz",
    "sg:classifiers":[
        {
            "category":"Social Services",
            "subcategory":"Job Training",
            "type":"Services"
        }
    ],
    "sg:phone":"+1 831 479 0137",
    "sg:postcode":"95062",
    "sg:province":"CA",
    "sg:tags":[
        "rehabilitation"
    ],
    "wof:name":"South Pacific Rehabilitation",
    "wof:placetype":"venue"
},
  "geometry": {"coordinates":[-121.985232,36.98641],"type":"Point"}
}