{
  "type": "Feature",
  "properties": {
    "addr:full":"555 Rosewood Ave Camarillo CA 93010",
    "addr:housenumber":"555",
    "addr:postcode":"93010",
    "addr:street":"Rosewood Ave",
    "iso:country":"US",
    "sg:address":"555 Rosewood Ave",
    "sg:city":"Camarillo",
    "sg:classifiers":[
        {
            "category":"Real Estate",
            "subcategory":"Real Estate Operator",
            "type":"Services"
        }
    ],
    "sg:phone":"+1 805 322 7097",
    "sg:postcode":"93010",
    "sg:province":"CA",
    "sg:tags":[
        "apartment"
    ],
    "sg:website":"www.rosewood-apts.com/",
    "wof:name":"Rosewood Apartments",
    "wof:placetype":"venue"
},
  "geometry": {"coordinates":[-119.06217700000001,34.222215],"type":"Point"}
}