{
  "type": "Feature",
  "properties": {
    "addr:full":"1051 Lincoln Ave San Jose CA 95125",
    "addr:housenumber":"1051",
    "addr:postcode":"95125",
    "addr:street":"Lincoln Ave",
    "iso:country":"US",
    "sg:address":"1051 Lincoln Ave",
    "sg:city":"San Jose",
    "sg:classifiers":[
        {
            "category":"Personal",
            "type":"Services"
        },
        {
            "category":"Shopping",
            "subcategory":"Florist",
            "type":"Retail Goods"
        }
    ],
    "sg:phone":"+1 408 275 6900",
    "sg:postcode":"95125",
    "sg:province":"CA",
    "sg:tags":[
        "planning",
        "wedding"
    ],
    "sg:website":"www.midoriz.com",
    "wof:name":"Midoriz",
    "wof:placetype":"venue"
},
  "geometry": {"coordinates":[-121.90270599999999,37.310693],"type":"Point"}
}