{
  "type": "Feature",
  "properties": {
    "iso:country":"US",
    "sg:address":"P.O. Box 60253",
    "sg:city":"Palo Alto",
    "sg:classifiers":[
        {
            "category":"Professional",
            "subcategory":"Computer Services",
            "type":"Services"
        }
    ],
    "sg:postcode":"94306",
    "sg:province":"CA",
    "sg:website":"http://www.gabbly.com",
    "wof:name":"Gabbly",
    "wof:placetype":"venue"
},
  "geometry": {"coordinates":[-122.130765,37.415728],"type":"Point"}
}