{
  "type": "Feature",
  "properties": {
    "iso:country":"US",
    "sg:address":"8252 Santa Monica Blvd",
    "sg:city":"West Hollywood",
    "sg:classifiers":[
        {
            "category":"Restaurant",
            "type":"Food & Drink"
        }
    ],
    "sg:phone":"+1 323 656 1383",
    "sg:postcode":"90046",
    "sg:province":"CA",
    "sg:tags":[
        "eating"
    ],
    "wof:name":"Eat Well",
    "wof:placetype":"venue"
},
  "geometry": {"coordinates":[-118.368893,34.090705],"type":"Point"}
}