{
  "type": "Feature",
  "properties": {
    "iso:country":"US",
    "sg:address":"15695 Donner Pass Rd",
    "sg:city":"Truckee",
    "sg:classifiers":[
        {
            "category":"Professional",
            "subcategory":"Lawyer & Legal Services",
            "type":"Services"
        }
    ],
    "sg:phone":"+1 530 587 2333",
    "sg:postcode":"96161",
    "sg:province":"CA",
    "sg:tags":[
        "attorney"
    ],
    "wof:name":"A Aaffordable Legal Assistance",
    "wof:placetype":"venue"
},
  "geometry": {"coordinates":[-120.291245,39.322959],"type":"Point"}
}