{
  "type": "Feature",
  "properties": {
    "addr:full":"891 S Euclid St Anaheim CA 92802",
    "addr:housenumber":"891",
    "addr:postcode":"92802",
    "addr:street":"S Euclid St",
    "iso:country":"US",
    "sg:address":"891 S Euclid St",
    "sg:city":"Anaheim",
    "sg:classifiers":[
        {
            "category":"Insurance",
            "subcategory":"Insurance Agent",
            "type":"Services"
        }
    ],
    "sg:phone":"+1 714 776 1362",
    "sg:postcode":"92802",
    "sg:province":"CA",
    "wof:name":"Anguiano and Insurance Agency",
    "wof:placetype":"venue"
},
  "geometry": {"coordinates":[-117.941506,33.820807],"type":"Point"}
}