{
  "type": "Feature",
  "properties": {
    "addr:full":"15945 Ventura Blvd Encino CA 91436",
    "addr:housenumber":"15945",
    "addr:postcode":"91436",
    "addr:street":"Ventura Blvd",
    "iso:country":"US",
    "sg:address":"15945 Ventura Blvd",
    "sg:city":"Encino",
    "sg:classifiers":[
        {
            "category":"Shopping",
            "subcategory":"Department Store",
            "type":"Retail Goods"
        }
    ],
    "sg:phone":"+1 818 501 7135",
    "sg:postcode":"91436",
    "sg:province":"CA",
    "wof:name":"Marshalls",
    "wof:placetype":"venue"
},
  "geometry": {"coordinates":[-118.48061199999999,34.156011],"type":"Point"}
}