{
  "type": "Feature",
  "properties": {
    "addr:full":"26832 Cherry Hills Blvd Sun City CA 92586",
    "addr:housenumber":"26832",
    "addr:postcode":"92586",
    "addr:street":"Cherry Hills Blvd",
    "iso:country":"US",
    "sg:address":"26832 Cherry Hills Blvd",
    "sg:city":"Sun City",
    "sg:classifiers":[
        {
            "category":"Personal",
            "subcategory":"Tattoo Parlor",
            "type":"Services"
        }
    ],
    "sg:phone":"+1 951 672 3764",
    "sg:postcode":"92586",
    "sg:province":"CA",
    "wof:name":"Rauls Tattoos",
    "wof:placetype":"venue"
},
  "geometry": {"coordinates":[-117.189003,33.710899],"type":"Point"}
}