{
  "type": "Feature",
  "properties": {
    "addr:full":"2930 Hilltop Mall Rd Richmond CA 94806",
    "addr:housenumber":"2930",
    "addr:postcode":"94806",
    "addr:street":"Hilltop Mall Rd",
    "iso:country":"US",
    "sg:address":"2930 Hilltop Mall Rd",
    "sg:city":"Richmond",
    "sg:classifiers":[
        {
            "category":"Personal",
            "subcategory":"Beauty Salon",
            "type":"Services"
        }
    ],
    "sg:phone":"+1 510 222 8139",
    "sg:postcode":"94806",
    "sg:province":"CA",
    "sg:tags":[
        "manicuring"
    ],
    "wof:name":"Nail Express",
    "wof:placetype":"venue"
},
  "geometry": {"coordinates":[-122.33062200000001,37.978368],"type":"Point"}
}