{
  "type": "Feature",
  "properties": {
    "iso:country":"US",
    "sg:address":"820 Edgewood Ave",
    "sg:city":"Mill Valley",
    "sg:classifiers":[
        {
            "category":"Real Estate",
            "subcategory":"Developer",
            "type":"Services"
        }
    ],
    "sg:phone":"+1 415 381 6100",
    "sg:postcode":"94941",
    "sg:province":"CA",
    "sg:tags":[
        "development"
    ],
    "wof:name":"Werner & Associates RE Brkg",
    "wof:placetype":"venue"
},
  "geometry": {"coordinates":[-122.570652,37.907375],"type":"Point"}
}