{
  "type": "Feature",
  "properties": {
    "addr:full":"141 S Topanga Canyon Blvd Topanga CA 90290",
    "addr:housenumber":"141",
    "addr:postcode":"90290",
    "addr:street":"S Topanga Canyon Blvd",
    "iso:country":"US",
    "sg:address":"141 S Topanga Canyon Blvd",
    "sg:city":"Topanga",
    "sg:classifiers":[
        {
            "category":"Food & Beverages",
            "subcategory":"Groceries & Convenience Stores",
            "type":"Retail Goods"
        }
    ],
    "sg:phone":"+1 310 455 1250",
    "sg:postcode":"90290",
    "sg:province":"CA",
    "sg:tags":[
        "market"
    ],
    "wof:name":"Topanga Creek General Store",
    "wof:placetype":"venue"
},
  "geometry": {"coordinates":[-118.603996,34.089401],"type":"Point"}
}