{
  "type": "Feature",
  "properties": {
    "addr:full":"261 E Lake Ave Watsonville CA 95076",
    "addr:housenumber":"261",
    "addr:postcode":"95076",
    "addr:street":"E Lake Ave",
    "iso:country":"US",
    "sg:address":"261 E Lake Ave",
    "sg:city":"Watsonville",
    "sg:classifiers":[
        {
            "category":"Food & Beverages",
            "subcategory":"Groceries & Convenience Stores",
            "type":"Retail Goods"
        }
    ],
    "sg:phone":"+1 831 724 1223",
    "sg:postcode":"95076",
    "sg:province":"CA",
    "wof:name":"7-Eleven",
    "wof:placetype":"venue"
},
  "geometry": {"coordinates":[-121.75411800000001,36.914795],"type":"Point"}
}