{
  "type": "Feature",
  "properties": {
    "addr:full":"700 W Convention Way Anaheim CA 92802",
    "addr:housenumber":"700",
    "addr:postcode":"92802",
    "addr:street":"W Convention Way",
    "iso:country":"US",
    "sg:address":"700 W Convention Way",
    "sg:city":"Anaheim",
    "sg:classifiers":[
        {
            "category":"Restaurant",
            "type":"Food & Drink"
        }
    ],
    "sg:phone":"+1 714 703 3187",
    "sg:postcode":"92802",
    "sg:province":"CA",
    "sg:tags":[
        "steakhouse"
    ],
    "wof:name":"JW's Steakhouse",
    "wof:placetype":"venue"
},
  "geometry": {"coordinates":[-117.918969,33.798699],"type":"Point"}
}