{
  "type": "Feature",
  "properties": {
    "iso:country":"US",
    "sg:address":"500 Michael Dr",
    "sg:city":"Sonoma",
    "sg:classifiers":[
        {
            "category":"Travel",
            "subcategory":"Travel Agent",
            "type":"Entertainment"
        }
    ],
    "sg:phone":"+1 707 938 2100",
    "sg:postcode":"95476",
    "sg:province":"CA",
    "sg:tags":[
        "tours",
        "promoter"
    ],
    "wof:name":"Viviani Touring Co",
    "wof:placetype":"venue"
},
  "geometry": {"coordinates":[-122.465724,38.307238],"type":"Point"}
}