{
  "type": "Feature",
  "properties": {
    "iso:country":"US",
    "sg:address":"10050 Garvey Ave Ste 117",
    "sg:city":"El Monte",
    "sg:classifiers":[
        {
            "category":"Shopping",
            "subcategory":"Pharmacy",
            "type":"Retail Goods"
        }
    ],
    "sg:phone":"+1 626 448 9956",
    "sg:postcode":"91733",
    "sg:province":"CA",
    "sg:tags":[
        "drugstore"
    ],
    "wof:name":"Rosa 1 Pharmacy",
    "wof:placetype":"venue"
},
  "geometry": {"coordinates":[-118.045998,34.056099],"type":"Point"}
}