{
  "type": "Feature",
  "properties": {
    "addr:full":"20924 Mission Blvd Hayward CA 94541",
    "addr:housenumber":"20924",
    "addr:postcode":"94541",
    "addr:street":"Mission Blvd",
    "iso:country":"US",
    "sg:address":"20924 Mission Blvd",
    "sg:city":"Hayward",
    "sg:classifiers":[
        {
            "category":"Health Services",
            "subcategory":"Dentist",
            "type":"Services"
        }
    ],
    "sg:phone":"+1 510 317 0999",
    "sg:postcode":"94541",
    "sg:province":"CA",
    "sg:tags":[
        "clinic",
        "dental",
        "hygienist"
    ],
    "wof:name":"TN Dental",
    "wof:placetype":"venue"
},
  "geometry": {"coordinates":[-122.098417,37.683862],"type":"Point"}
}