{
  "type": "Feature",
  "properties": {
    "addr:full":"11161 Slater Ave Fountain Valley CA 92708",
    "addr:housenumber":"11161",
    "addr:postcode":"92708",
    "addr:street":"Slater Ave",
    "iso:country":"US",
    "sg:address":"11161 Slater Ave",
    "sg:city":"Fountain Valley",
    "sg:classifiers":[
        {
            "category":"Manufacturing",
            "subcategory":"Motor Vehicles & Parts",
            "type":"Manufacturing & Wholesale Goods"
        }
    ],
    "sg:phone":"+1 714 444 1700",
    "sg:postcode":"92708",
    "sg:province":"CA",
    "sg:tags":[
        "automotive",
        "prototype",
        "mfg"
    ],
    "sg:website":"www.metalcrafters.com",
    "wof:name":"Camera Ready Cars",
    "wof:placetype":"venue"
},
  "geometry": {"coordinates":[-117.933018,33.709232],"type":"Point"}
}