{
  "type": "Feature",
  "properties": {
    "iso:country":"US",
    "sg:address":"611 Veterans Blvd",
    "sg:city":"Redwood City",
    "sg:classifiers":[
        {
            "category":"Professional",
            "subcategory":"Advertising",
            "type":"Services"
        }
    ],
    "sg:phone":"+1 650 365 9619",
    "sg:postcode":"94063",
    "sg:province":"CA",
    "sg:tags":[
        "designer",
        "display",
        "producer"
    ],
    "wof:name":"Kaveh Design",
    "wof:placetype":"venue"
},
  "geometry": {"coordinates":[-122.231125,37.49187],"type":"Point"}
}