{
  "type": "Feature",
  "properties": {
    "iso:country":"US",
    "sg:address":"12701 de Foe Ave",
    "sg:city":"Sylmar",
    "sg:classifiers":[
        {
            "category":"Professional",
            "subcategory":"Accounting & Tax Preparation",
            "type":"Services"
        }
    ],
    "sg:phone":"+1 818 367 5410",
    "sg:postcode":"91342",
    "sg:province":"CA",
    "sg:tags":[
        "bookkeeping",
        "billing"
    ],
    "wof:name":"Jeanne Enterprises",
    "wof:placetype":"venue"
},
  "geometry": {"coordinates":[-118.44592299999999,34.300819],"type":"Point"}
}