{
  "type": "Feature",
  "properties": {
    "addr:full":"7949 Carlton Rd Sacramento CA 95826",
    "addr:housenumber":"7949",
    "addr:postcode":"95826",
    "addr:street":"Carlton Rd",
    "iso:country":"US",
    "sg:address":"7949 Carlton Rd",
    "sg:city":"Sacramento",
    "sg:classifiers":[
        {
            "category":"Organizations",
            "subcategory":"Religious Organization",
            "type":"Services"
        }
    ],
    "sg:phone":"+1 916 451 8078",
    "sg:postcode":"95826",
    "sg:province":"CA",
    "sg:tags":[
        "church"
    ],
    "wof:name":"Church Of God Of Prophecy",
    "wof:placetype":"venue"
},
  "geometry": {"coordinates":[-121.409285,38.53817],"type":"Point"}
}