{
  "type": "Feature",
  "properties": {
    "iso:country":"US",
    "sg:address":"11101 Beckford Ave",
    "sg:city":"Northridge",
    "sg:classifiers":[
        {
            "category":"Professional",
            "type":"Services"
        }
    ],
    "sg:phone":"+1 818 363 7416",
    "sg:postcode":"91326",
    "sg:province":"CA",
    "wof:name":"E Edit Inc",
    "wof:placetype":"venue"
},
  "geometry": {"coordinates":[-118.548705,34.272752],"type":"Point"}
}