{
  "type": "Feature",
  "properties": {
    "iso:country":"US",
    "sg:address":"348 E 18th St",
    "sg:city":"Costa Mesa",
    "sg:classifiers":[
        {
            "category":"Professional",
            "type":"Services"
        }
    ],
    "sg:phone":"+1 949 548 8556",
    "sg:postcode":"92627",
    "sg:province":"CA",
    "wof:name":"G Pike Robert",
    "wof:placetype":"venue"
},
  "geometry": {"coordinates":[-117.910676,33.634738],"type":"Point"}
}