{
  "type": "Feature",
  "properties": {
    "iso:country":"US",
    "sg:address":"3332 53rd St",
    "sg:city":"Sacramento",
    "sg:classifiers":[
        {
            "category":"Communications",
            "type":"Services"
        }
    ],
    "sg:phone":"+1 916 456 5607",
    "sg:postcode":"95820",
    "sg:province":"CA",
    "sg:tags":[
        "carrier",
        "radiotelephone",
        "communications-common"
    ],
    "wof:name":"Bernies Cb Shop",
    "wof:placetype":"venue"
},
  "geometry": {"coordinates":[-121.443962,38.544117],"type":"Point"}
}