{
  "type": "Feature",
  "properties": {
    "addr:full":"510 Steiner St, Suite 4 San Francisco CA 94117",
    "addr:housenumber":"510",
    "addr:postcode":"94117",
    "addr:street":"Steiner St Suite 4",
    "iso:country":"US",
    "sg:address":"510 Steiner St, Suite 4",
    "sg:city":"San Francisco",
    "sg:classifiers":[
        {
            "category":"Professional",
            "subcategory":"Lawyer & Legal Services",
            "type":"Services"
        }
    ],
    "sg:phone":"+1 415 509 8105",
    "sg:postcode":"94117",
    "sg:province":"CA",
    "sg:tags":[
        "litigation"
    ],
    "sg:website":"www.cantor-law.com",
    "wof:name":"Law Office of Andrew S. Cantor",
    "wof:placetype":"venue"
},
  "geometry": {"coordinates":[-122.432337,37.774013],"type":"Point"}
}