{
  "type": "Feature",
  "properties": {
    "iso:country":"US",
    "sg:address":"19732 Collyer Dr",
    "sg:city":"Redding",
    "sg:classifiers":[
        {
            "category":"Professional",
            "subcategory":"Business Services",
            "type":"Services"
        },
        {
            "category":"Retail",
            "subcategory":"Storage",
            "type":"Services"
        }
    ],
    "sg:phone":"+1 530 246 0566",
    "sg:postcode":"96003",
    "sg:province":"CA",
    "sg:tags":[
        "management",
        "records-storage",
        "automobile",
        "household",
        "recreational",
        "commercial",
        "campers-storage",
        "vehicle",
        "document",
        "self",
        "boat"
    ],
    "sg:website":"http://www.CandLsecurestorage.com",
    "wof:name":"C & L Secure Storage",
    "wof:placetype":"venue"
},
  "geometry": {"coordinates":[-122.31673600000001,40.622835],"type":"Point"}
}