{
  "type": "Feature",
  "properties": {
    "iso:country":"US",
    "sg:address":"3293 Crane Way",
    "sg:city":"Oakland",
    "sg:classifiers":[
        {
            "category":"Building & Trades",
            "subcategory":"Construction",
            "type":"Services"
        }
    ],
    "sg:phone":"+1 510 531 7144",
    "sg:postcode":"94602",
    "sg:province":"CA",
    "sg:tags":[
        "contractor"
    ],
    "wof:name":"Old World Builders",
    "wof:placetype":"venue"
},
  "geometry": {"coordinates":[-122.185761,37.808853],"type":"Point"}
}