{
  "type": "Feature",
  "properties": {
    "addr:full":"7707 W Sunset Blvd Los Angeles CA 90046",
    "addr:housenumber":"7707",
    "addr:postcode":"90046",
    "addr:street":"W Sunset Blvd",
    "iso:country":"US",
    "sg:address":"7707 W Sunset Blvd",
    "sg:city":"Los Angeles",
    "sg:classifiers":[
        {
            "category":"Real Estate",
            "subcategory":"Real Estate Agent",
            "type":"Services"
        }
    ],
    "sg:phone":"+1 323 876 4100",
    "sg:postcode":"90046",
    "sg:province":"CA",
    "wof:name":"Russ Vincent Realty Co",
    "wof:placetype":"venue"
},
  "geometry": {"coordinates":[-118.35806599999999,34.098133],"type":"Point"}
}