{
  "type": "Feature",
  "properties": {
    "iso:country":"US",
    "sg:address":"2070 E Washington Blvd",
    "sg:city":"Pasadena",
    "sg:classifiers":[
        {
            "category":"Professional",
            "subcategory":"Management & Consulting",
            "type":"Services"
        }
    ],
    "sg:phone":"+1 626 345 1351",
    "sg:postcode":"91104",
    "sg:province":"CA",
    "sg:tags":[
        "consultant",
        "construction"
    ],
    "wof:name":"United Fueling Systems",
    "wof:placetype":"venue"
},
  "geometry": {"coordinates":[-118.10584,34.16906],"type":"Point"}
}