{
  "type": "Feature",
  "properties": {
    "addr:full":"29300 Dry Creek Rd Galt CA 95632",
    "addr:housenumber":"29300",
    "addr:postcode":"95632",
    "addr:street":"Dry Creek Rd",
    "iso:country":"US",
    "sg:address":"29300 Dry Creek Rd",
    "sg:city":"Galt",
    "sg:classifiers":[
        {
            "category":"Farming",
            "subcategory":"Livestock Farm",
            "type":"Manufacturing & Wholesale Goods"
        }
    ],
    "sg:phone":"+1 209 369 3445",
    "sg:postcode":"95632",
    "sg:province":"CA",
    "sg:tags":[
        "breeder",
        "animal"
    ],
    "wof:name":"Twin Oaks Aussie",
    "wof:placetype":"venue"
},
  "geometry": {"coordinates":[-121.13543799999999,38.262251],"type":"Point"}
}