{
  "type": "Feature",
  "properties": {
    "addr:full":"5425 Wilson St Riverside CA 92509",
    "addr:housenumber":"5425",
    "addr:postcode":"92509",
    "addr:street":"Wilson St",
    "iso:country":"US",
    "sg:address":"5425 Wilson St",
    "sg:city":"Riverside",
    "sg:classifiers":[
        {
            "category":"Wholesale",
            "subcategory":"Groceries",
            "type":"Manufacturing & Wholesale Goods"
        }
    ],
    "sg:phone":"+1 951 682 8222",
    "sg:postcode":"92509",
    "sg:province":"CA",
    "sg:tags":[
        "food"
    ],
    "wof:name":"Inland Empire Foods Inc",
    "wof:placetype":"venue"
},
  "geometry": {"coordinates":[-117.385453,34.020918],"type":"Point"}
}