{
  "type": "Feature",
  "properties": {
    "iso:country":"US",
    "sg:address":"719 Niles St",
    "sg:city":"Bakersfield",
    "sg:classifiers":[
        {
            "category":"Insurance",
            "subcategory":"Insurance Agent",
            "type":"Services"
        }
    ],
    "sg:phone":"+1 661 327 3533",
    "sg:postcode":"93305",
    "sg:province":"CA",
    "wof:name":"Sceales & Assoc Insurance",
    "wof:placetype":"venue"
},
  "geometry": {"coordinates":[-118.98975900000001,35.381647],"type":"Point"}
}