{
  "type": "Feature",
  "properties": {
    "iso:country":"US",
    "sg:address":"2000 Van Ness Ave",
    "sg:city":"San Francisco",
    "sg:classifiers":[
        {
            "category":"Wholesale",
            "subcategory":"Machinery & Supplies",
            "type":"Manufacturing & Wholesale Goods"
        }
    ],
    "sg:phone":"+1 415 345 0007",
    "sg:postcode":"94109",
    "sg:province":"CA",
    "sg:tags":[
        "equipment",
        "motel",
        "hotel",
        "establishment"
    ],
    "wof:name":"Hotel Amenities Resource LLC",
    "wof:placetype":"venue"
},
  "geometry": {"coordinates":[-122.423227,37.794816],"type":"Point"}
}