{
  "type": "Feature",
  "properties": {
    "iso:country":"US",
    "sg:address":"204 Illinois St",
    "sg:city":"Travis Afb",
    "sg:classifiers":[
        {
            "category":"Shopping",
            "subcategory":"Discount & Variety Stores",
            "type":"Retail Goods"
        }
    ],
    "sg:phone":"+1 707 437 0214",
    "sg:postcode":"94535",
    "sg:province":"CA",
    "sg:tags":[
        "merchandise",
        "general"
    ],
    "wof:name":"M J Merchandisers",
    "wof:placetype":"venue"
},
  "geometry": {"coordinates":[-121.948784,38.276511],"type":"Point"}
}