{
  "type": "Feature",
  "properties": {
    "iso:country":"US",
    "sg:address":"344 Shire Oaks Ct",
    "sg:city":"Lafayette",
    "sg:classifiers":[
        {
            "category":"Utilities",
            "subcategory":"Fuel Oil & Lpg",
            "type":"Services"
        }
    ],
    "sg:phone":"+1 925 451 4748",
    "sg:postcode":"94549",
    "sg:province":"CA",
    "sg:tags":[
        "development",
        "exploration",
        "gas"
    ],
    "wof:name":"Faith Exploration",
    "wof:placetype":"venue"
},
  "geometry": {"coordinates":[-122.101669,37.856549],"type":"Point"}
}