{
  "type": "Feature",
  "properties": {
    "addr:full":"605 C St Ste 300 San Diego CA 92101",
    "addr:housenumber":"605",
    "addr:postcode":"92101",
    "addr:street":"C St Ste 300",
    "iso:country":"US",
    "sg:address":"605 C St Ste 300",
    "sg:city":"San Diego",
    "sg:classifiers":[
        {
            "category":"Professional",
            "subcategory":"Lawyer & Legal Services",
            "type":"Services"
        }
    ],
    "sg:phone":"+1 619 238 5252",
    "sg:postcode":"92101",
    "sg:province":"CA",
    "sg:website":"www.strong-law.com",
    "wof:name":"Strong Robert C Associates",
    "wof:placetype":"venue"
},
  "geometry": {"coordinates":[-117.15919100000001,32.716643],"type":"Point"}
}