{
  "type": "Feature",
  "properties": {
    "addr:full":"5125 Putah Creek Rd Winters CA 95694",
    "addr:housenumber":"5125",
    "addr:postcode":"95694",
    "addr:street":"Putah Creek Rd",
    "iso:country":"US",
    "sg:address":"5125 Putah Creek Rd",
    "sg:city":"Winters",
    "sg:classifiers":[
        {
            "category":"Farming",
            "subcategory":"Livestock Farm",
            "type":"Manufacturing & Wholesale Goods"
        }
    ],
    "sg:phone":"+1 530 795 5227",
    "sg:postcode":"95694",
    "sg:province":"CA",
    "sg:tags":[
        "ranch"
    ],
    "wof:name":"Burke Ranch",
    "wof:placetype":"venue"
},
  "geometry": {"coordinates":[-121.943318,38.529342],"type":"Point"}
}