{
  "type": "Feature",
  "properties": {
    "iso:country":"US",
    "sg:address":"1561 C St",
    "sg:city":"Brawley",
    "sg:classifiers":[
        {
            "category":"Building & Trades",
            "subcategory":"Construction",
            "type":"Services"
        }
    ],
    "sg:phone":"+1 760 344 6343",
    "sg:postcode":"92227",
    "sg:province":"CA",
    "sg:tags":[
        "welder"
    ],
    "wof:name":"Cummings J T Welding",
    "wof:placetype":"venue"
},
  "geometry": {"coordinates":[-115.51515999999999,32.98233],"type":"Point"}
}