{
  "type": "Feature",
  "properties": {
    "iso:country":"US",
    "sg:address":"711 Railroad Ave",
    "sg:city":"Pittsburg",
    "sg:classifiers":[
        {
            "category":"Home & Garden",
            "subcategory":"Furniture",
            "type":"Retail Goods"
        }
    ],
    "sg:phone":"+1 925 432 4757",
    "sg:postcode":"94565",
    "sg:province":"CA",
    "sg:website":"www.lanzafame.com",
    "wof:name":"Lanzafame Furniture Co",
    "wof:placetype":"venue"
},
  "geometry": {"coordinates":[-121.884382,38.029682],"type":"Point"}
}