{
  "type": "Feature",
  "properties": {
    "addr:full":"2812 Velarde Dr Thousand Oaks CA 91360",
    "addr:housenumber":"2812",
    "addr:postcode":"91360",
    "addr:street":"Velarde Dr",
    "iso:country":"US",
    "sg:address":"2812 Velarde Dr",
    "sg:city":"Thousand Oaks",
    "sg:classifiers":[
        {
            "category":"Real Estate",
            "subcategory":"Real Estate Agent",
            "type":"Services"
        }
    ],
    "sg:phone":"+1 805 241 5533",
    "sg:postcode":"91360",
    "sg:province":"CA",
    "sg:tags":[
        "inspection"
    ],
    "wof:name":"Pro-Home Inspections",
    "wof:placetype":"venue"
},
  "geometry": {"coordinates":[-118.898731,34.216997],"type":"Point"}
}