{
  "type": "Feature",
  "properties": {
    "addr:full":"2322 Senter Rd San Jose CA 95112",
    "addr:housenumber":"2322",
    "addr:postcode":"95112",
    "addr:street":"Senter Rd",
    "iso:country":"US",
    "sg:address":"2322 Senter Rd",
    "sg:city":"San Jose",
    "sg:classifiers":[
        {
            "category":"Personal",
            "subcategory":"Beauty Salon",
            "type":"Services"
        }
    ],
    "sg:phone":"+1 408 287 1058",
    "sg:postcode":"95112",
    "sg:province":"CA",
    "sg:tags":[
        "hair"
    ],
    "wof:name":"Teresa's Salon",
    "wof:placetype":"venue"
},
  "geometry": {"coordinates":[-121.84899900000001,37.3088],"type":"Point"}
}