{
  "type": "Feature",
  "properties": {
    "iso:country":"US",
    "sg:address":"6571 Imperial Ave",
    "sg:city":"San Diego",
    "sg:classifiers":[
        {
            "category":"Health Services",
            "subcategory":"Doctor",
            "type":"Services"
        }
    ],
    "sg:phone":"+1 619 262 0781",
    "sg:postcode":"92114",
    "sg:province":"CA",
    "sg:tags":[
        "dentist"
    ],
    "wof:name":"San Diego Trolley Dental Group",
    "wof:placetype":"venue"
},
  "geometry": {"coordinates":[-117.055908,32.710728],"type":"Point"}
}