{
  "type": "Feature",
  "properties": {
    "addr:full":"926 Stanford Ave Los Angeles CA 90021",
    "addr:housenumber":"926",
    "addr:postcode":"90021",
    "addr:street":"Stanford Ave",
    "iso:country":"US",
    "sg:address":"926 Stanford Ave",
    "sg:city":"Los Angeles",
    "sg:classifiers":[
        {
            "category":"Wholesale",
            "subcategory":"Motor Vehicles",
            "type":"Manufacturing & Wholesale Goods"
        }
    ],
    "sg:phone":"+1 213 489 1118",
    "sg:postcode":"90021",
    "sg:province":"CA",
    "wof:name":"Giumarra Trucking",
    "wof:placetype":"venue"
},
  "geometry": {"coordinates":[-118.248454,34.03404],"type":"Point"}
}