{
  "type": "Feature",
  "properties": {
    "iso:country":"US",
    "sg:address":"100 Citadel Dr",
    "sg:city":"Los Angeles",
    "sg:classifiers":[
        {
            "category":"Shopping",
            "type":"Retail Goods"
        }
    ],
    "sg:phone":"+1 323 887 9436",
    "sg:postcode":"90040",
    "sg:province":"CA",
    "sg:tags":[
        "factory",
        "outlet"
    ],
    "sg:website":"www.bassshoes.com",
    "wof:name":"Bass Apparel Factory Outlet",
    "wof:placetype":"venue"
},
  "geometry": {"coordinates":[-118.151225,34.005888],"type":"Point"}
}