{
  "type": "Feature",
  "properties": {
    "addr:full":"5952 Lankershim Blvd North Hollywood CA 91601",
    "addr:housenumber":"5952",
    "addr:postcode":"91601",
    "addr:street":"Lankershim Blvd",
    "iso:country":"US",
    "sg:address":"5952 Lankershim Blvd",
    "sg:city":"North Hollywood",
    "sg:classifiers":[
        {
            "category":"Restaurant",
            "type":"Food & Drink"
        }
    ],
    "sg:phone":"+1 818 508 8858",
    "sg:postcode":"91601",
    "sg:province":"CA",
    "sg:tags":[
        "chinese"
    ],
    "sg:website":"www.chinesedelight.net/index.htm",
    "wof:name":"Chinese Delight",
    "wof:placetype":"venue"
},
  "geometry": {"coordinates":[-118.383003,34.1791],"type":"Point"}
}