{
  "type": "Feature",
  "properties": {
    "addr:full":"3429 Pomona Blvd Ste N Pomona CA 91768",
    "addr:housenumber":"3429",
    "addr:postcode":"91768",
    "addr:street":"Pomona Blvd Ste N",
    "iso:country":"US",
    "sg:address":"3429 Pomona Blvd Ste N",
    "sg:city":"Pomona",
    "sg:classifiers":[
        {
            "category":"Manufacturing",
            "subcategory":"Glass & Minerals",
            "type":"Manufacturing & Wholesale Goods"
        },
        {
            "category":"Retail",
            "subcategory":"Auto Repair",
            "type":"Services"
        }
    ],
    "sg:phone":"+1 909 869 6377",
    "sg:postcode":"91768",
    "sg:province":"CA",
    "sg:tags":[
        "plate",
        "shape",
        "glass-wholesale",
        "window",
        "special",
        "circle",
        "windshield",
        "glass-auto",
        "manufacturer"
    ],
    "wof:name":"Cherry Glass",
    "wof:placetype":"venue"
},
  "geometry": {"coordinates":[-117.810384,34.047502],"type":"Point"}
}