{
  "type": "Feature",
  "properties": {
    "iso:country":"US",
    "sg:address":"4323 S Vermont Ave",
    "sg:city":"Los Angeles",
    "sg:classifiers":[
        {
            "category":"Cinema",
            "subcategory":"Movie Rental",
            "type":"Entertainment"
        }
    ],
    "sg:phone":"+1 323 238 0885",
    "sg:postcode":"90037",
    "sg:province":"CA",
    "sg:tags":[
        "leasing",
        "video",
        "disc",
        "tape"
    ],
    "wof:name":"Video Loco",
    "wof:placetype":"venue"
},
  "geometry": {"coordinates":[-118.291616,34.00501],"type":"Point"}
}