{
  "type": "Feature",
  "properties": {
    "iso:country":"US",
    "sg:address":"1010 Sundown Trl",
    "sg:city":"Santa Rosa",
    "sg:classifiers":[
        {
            "category":"Government",
            "subcategory":"Office",
            "type":"Public Place"
        }
    ],
    "sg:phone":"+1 707 573 1227",
    "sg:postcode":"95404",
    "sg:province":"CA",
    "sg:tags":[
        "educational",
        "program",
        "administrative"
    ],
    "wof:name":"Polestar Education Inc",
    "wof:placetype":"venue"
},
  "geometry": {"coordinates":[-122.71656299999999,38.506531],"type":"Point"}
}