{
  "type": "Feature",
  "properties": {
    "iso:country":"US",
    "sg:address":"6005 N Tamera Ave",
    "sg:city":"Fresno",
    "sg:classifiers":[
        {
            "category":"Social Services",
            "type":"Services"
        }
    ],
    "sg:phone":"+1 559 320 2100",
    "sg:postcode":"93711",
    "sg:province":"CA",
    "sg:tags":[
        "youth",
        "organization",
        "center"
    ],
    "wof:name":"Boy Scouts Of America",
    "wof:placetype":"venue"
},
  "geometry": {"coordinates":[-119.851783,36.824016],"type":"Point"}
}