{
  "type": "Feature",
  "properties": {
    "addr:full":"391 Leavenworth St San Francisco CA 94102",
    "addr:housenumber":"391",
    "addr:postcode":"94102",
    "addr:street":"Leavenworth St",
    "iso:country":"US",
    "sg:address":"391 Leavenworth St",
    "sg:city":"San Francisco",
    "sg:classifiers":[
        {
            "category":"Travel",
            "subcategory":"Hotels & Motels",
            "type":"Entertainment"
        }
    ],
    "sg:phone":"+1 415 885 0757",
    "sg:postcode":"94102",
    "sg:province":"CA",
    "sg:tags":[
        "operation"
    ],
    "wof:name":"Aarti Co Operative Hotel",
    "wof:placetype":"venue"
},
  "geometry": {"coordinates":[-122.41445,37.784306],"type":"Point"}
}