{
  "type": "Feature",
  "properties": {
    "iso:country":"US",
    "sg:address":"6060 Sunrise Vista Drive",
    "sg:city":"Citrus Heights",
    "sg:classifiers":[
        {
            "category":"Banks & Credit Unions",
            "subcategory":"Financial Services",
            "type":"Services"
        }
    ],
    "sg:phone":"+1 916 729 2000",
    "sg:postcode":"95610",
    "sg:province":"CA",
    "sg:tags":[
        "broker",
        "mortgage"
    ],
    "wof:name":"Sunrise Vista Mortgage",
    "wof:placetype":"venue"
},
  "geometry": {"coordinates":[-121.26448000000001,38.676091],"type":"Point"}
}