{
  "type": "Feature",
  "properties": {
    "addr:full":"1650 Lucerne Ave Dos Palos CA 93620",
    "addr:housenumber":"1650",
    "addr:postcode":"93620",
    "addr:street":"Lucerne Ave",
    "iso:country":"US",
    "sg:address":"1650 Lucerne Ave",
    "sg:city":"Dos Palos",
    "sg:classifiers":[
        {
            "category":"Organizations",
            "subcategory":"Religious Organization",
            "type":"Services"
        }
    ],
    "sg:phone":"+1 209 392 2724",
    "sg:postcode":"93620",
    "sg:province":"CA",
    "sg:tags":[
        "church"
    ],
    "wof:name":"Sacred Heart Catholic Church",
    "wof:placetype":"venue"
},
  "geometry": {"coordinates":[-120.625494,36.984206],"type":"Point"}
}