{
  "type": "Feature",
  "properties": {
    "addr:full":"10110 Alta Sierra Dr Grass Valley CA 95949",
    "addr:housenumber":"10110",
    "addr:postcode":"95949",
    "addr:street":"Alta Sierra Dr",
    "iso:country":"US",
    "sg:address":"10110 Alta Sierra Dr",
    "sg:city":"Grass Valley",
    "sg:classifiers":[
        {
            "category":"Health Services",
            "subcategory":"Chiropractor",
            "type":"Services"
        }
    ],
    "sg:phone":"+1 530 272 2612",
    "sg:postcode":"95949",
    "sg:province":"CA",
    "wof:name":"Alta Sierra Chiropractic Ofc",
    "wof:placetype":"venue"
},
  "geometry": {"coordinates":[-121.069335,39.141344],"type":"Point"}
}