{
  "type": "Feature",
  "properties": {
    "addr:full":"1510 W Branch St Arroyo Grande CA 93420",
    "addr:housenumber":"1510",
    "addr:postcode":"93420",
    "addr:street":"W Branch St",
    "iso:country":"US",
    "sg:address":"1510 W Branch St",
    "sg:city":"Arroyo Grande",
    "sg:classifiers":[
        {
            "category":"Health Services",
            "subcategory":"Health Practitioner",
            "type":"Services"
        }
    ],
    "sg:phone":"+1 805 489 7912",
    "sg:postcode":"93420",
    "sg:province":"CA",
    "sg:tags":[
        "therapist",
        "physical"
    ],
    "wof:name":"San Luis Sports Therapy",
    "wof:placetype":"venue"
},
  "geometry": {"coordinates":[-120.603604,35.129673],"type":"Point"}
}