{
  "type": "Feature",
  "properties": {
    "iso:country":"US",
    "sg:address":"15923 Bear Valley Rd",
    "sg:city":"Hesperia",
    "sg:classifiers":[
        {
            "category":"Insurance",
            "subcategory":"Insurance Agent",
            "type":"Services"
        },
        {
            "category":"Insurance",
            "subcategory":"Hazard Insurance",
            "type":"Services"
        },
        {
            "category":"Insurance",
            "subcategory":"Title Insurance",
            "type":"Services"
        },
        {
            "category":"Insurance",
            "subcategory":"Life Insurance",
            "type":"Services"
        }
    ],
    "sg:phone":"+1 760 948 1746",
    "sg:postcode":"92345",
    "sg:province":"CA",
    "sg:tags":[
        "business",
        "auto",
        "commercial",
        "homeowner",
        "motorcycle",
        "renter"
    ],
    "wof:name":"Allstate Insurance Company - Elizabeth Gonzalez",
    "wof:placetype":"venue"
},
  "geometry": {"coordinates":[-117.31628000000001,34.470685],"type":"Point"}
}