{
  "type": "Feature",
  "properties": {
    "iso:country":"US",
    "sg:address":"840 W 5th St",
    "sg:city":"Oxnard",
    "sg:classifiers":[
        {
            "category":"Real Estate",
            "subcategory":"Real Estate Operator",
            "type":"Services"
        }
    ],
    "sg:phone":"+1 805 483 7122",
    "sg:postcode":"93030",
    "sg:province":"CA",
    "sg:tags":[
        "apartment"
    ],
    "wof:name":"Casa Merced",
    "wof:placetype":"venue"
},
  "geometry": {"coordinates":[-119.18713,34.197659],"type":"Point"}
}