{
  "type": "Feature",
  "properties": {
    "iso:country":"US",
    "sg:address":"8723 Washington Blvd",
    "sg:city":"Culver City",
    "sg:classifiers":[
        {
            "category":"Professional",
            "subcategory":"Business Services",
            "type":"Services"
        }
    ],
    "sg:phone":"+1 310 558 0555",
    "sg:postcode":"90232",
    "sg:province":"CA",
    "sg:tags":[
        "recording",
        "studio"
    ],
    "sg:website":"www.mosesleroy.com",
    "wof:name":"Ultimatum Music",
    "wof:placetype":"venue"
},
  "geometry": {"coordinates":[-118.38533,34.028967],"type":"Point"}
}