{
  "type": "Feature",
  "properties": {
    "iso:country":"US",
    "sg:address":"839 Mitten Rd",
    "sg:city":"Burlingame",
    "sg:classifiers":[
        {
            "category":"Farming",
            "subcategory":"Nursery",
            "type":"Manufacturing & Wholesale Goods"
        }
    ],
    "sg:phone":"+1 650 697 7120",
    "sg:postcode":"94010",
    "sg:province":"CA",
    "sg:tags":[
        "greenhouse"
    ],
    "wof:name":"Tenex Greenhouse Ventures",
    "wof:placetype":"venue"
},
  "geometry": {"coordinates":[-122.37406,37.600896],"type":"Point"}
}