{
  "type": "Feature",
  "properties": {
    "iso:country":"US",
    "sg:address":"1550 Winchester Blvd",
    "sg:city":"Campbell",
    "sg:classifiers":[
        {
            "category":"Retail",
            "subcategory":"Repair Shop",
            "type":"Services"
        }
    ],
    "sg:phone":"+1 408 374 1490",
    "sg:postcode":"95008",
    "sg:province":"CA",
    "sg:tags":[
        "water",
        "heater"
    ],
    "wof:name":"Precision Plumbing",
    "wof:placetype":"venue"
},
  "geometry": {"coordinates":[-121.9498,37.29528],"type":"Point"}
}