{
  "type": "Feature",
  "properties": {
    "iso:country":"US",
    "sg:address":"6537 Telegraph Ave",
    "sg:city":"Oakland",
    "sg:classifiers":[
        {
            "category":"Shopping",
            "subcategory":"Books",
            "type":"Retail Goods"
        }
    ],
    "sg:phone":"+1 510 655 2405",
    "sg:postcode":"94609",
    "sg:province":"CA",
    "sg:tags":[
        "dealer"
    ],
    "wof:name":"Change Makers",
    "wof:placetype":"venue"
},
  "geometry": {"coordinates":[-122.260449,37.85168],"type":"Point"}
}