{
  "type": "Feature",
  "properties": {
    "iso:country":"US",
    "sg:address":"710 W Pedregosa St",
    "sg:city":"Santa Barbara",
    "sg:classifiers":[
        {
            "category":"Retail",
            "subcategory":"Laundry & Dry Cleaning",
            "type":"Services"
        }
    ],
    "sg:phone":"+1 805 967 3495",
    "sg:postcode":"93101",
    "sg:province":"CA",
    "sg:tags":[
        "cleaners",
        "rug",
        "carpet"
    ],
    "wof:name":"Carpet Master",
    "wof:placetype":"venue"
},
  "geometry": {"coordinates":[-119.72235999999999,34.421616],"type":"Point"}
}