{
  "type": "Feature",
  "properties": {
    "addr:full":"4190 County Rd E Orland CA 95963",
    "addr:housenumber":"4190",
    "addr:postcode":"95963",
    "addr:street":"County Rd E",
    "iso:country":"US",
    "sg:address":"4190 County Rd E",
    "sg:city":"Orland",
    "sg:classifiers":[
        {
            "category":"Building & Trades",
            "subcategory":"Equipment Rental",
            "type":"Services"
        }
    ],
    "sg:phone":"+1 530 865 8283",
    "sg:postcode":"95963",
    "sg:province":"CA",
    "sg:tags":[
        "yard",
        "leasing",
        "store"
    ],
    "wof:name":"Ramon Ramos Rentals",
    "wof:placetype":"venue"
},
  "geometry": {"coordinates":[-122.104327,39.723267],"type":"Point"}
}