{
  "type": "Feature",
  "properties": {
    "iso:country":"US",
    "sg:address":"704 Zephyr St",
    "sg:city":"Stockton",
    "sg:classifiers":[
        {
            "category":"Manufacturing",
            "subcategory":"Pet Food",
            "type":"Manufacturing & Wholesale Goods"
        }
    ],
    "sg:phone":"+1 209 982 5085",
    "sg:postcode":"95206",
    "sg:province":"CA",
    "sg:tags":[
        "feed"
    ],
    "wof:name":"Recycle To Conserve Inc",
    "wof:placetype":"venue"
},
  "geometry": {"coordinates":[-121.26130999999999,37.913664],"type":"Point"}
}