{
  "type": "Feature",
  "properties": {
    "iso:country":"US",
    "sg:address":"12122 Vanowen St",
    "sg:city":"North Hollywood",
    "sg:classifiers":[
        {
            "category":"Personal",
            "subcategory":"Shoe Repair & Shine",
            "type":"Services"
        }
    ],
    "sg:phone":"+1 818 982 1866",
    "sg:postcode":"91605",
    "sg:province":"CA",
    "sg:tags":[
        "repairing",
        "boot"
    ],
    "wof:name":"Fulton Shoe Repair",
    "wof:placetype":"venue"
},
  "geometry": {"coordinates":[-118.397003,34.194099],"type":"Point"}
}