{
  "type": "Feature",
  "properties": {
    "iso:country":"US",
    "sg:address":"350 2nd St",
    "sg:city":"Los Altos",
    "sg:classifiers":[
        {
            "category":"Health Services",
            "subcategory":"Health Practitioner",
            "type":"Services"
        }
    ],
    "sg:phone":"+1 650 941 9220",
    "sg:postcode":"94022",
    "sg:province":"CA",
    "sg:tags":[
        "psychotherapist"
    ],
    "wof:name":"Karla T Jurvetson",
    "wof:placetype":"venue"
},
  "geometry": {"coordinates":[-122.114796,37.375828],"type":"Point"}
}