{
  "type": "Feature",
  "properties": {
    "iso:country":"US",
    "sg:address":"2535 California St",
    "sg:city":"Mountain View",
    "sg:classifiers":[
        {
            "category":"Food & Beverages",
            "subcategory":"Groceries & Convenience Stores",
            "type":"Retail Goods"
        }
    ],
    "sg:phone":"+1 650 559 9585",
    "sg:postcode":"94040",
    "sg:province":"CA",
    "sg:tags":[
        "supermarket"
    ],
    "wof:name":"Albertsons 7121",
    "wof:placetype":"venue"
},
  "geometry": {"coordinates":[-122.10638400000001,37.403224],"type":"Point"}
}