{
  "type": "Feature",
  "properties": {
    "iso:country":"US",
    "sg:address":"731W N Market Blvd",
    "sg:city":"Sacramento",
    "sg:phone":"+1 916 929 4700",
    "sg:postcode":"95834",
    "sg:province":"CA",
    "wof:name":"MCM Enterprises",
    "wof:placetype":"venue"
},
  "geometry": {"coordinates":[-121.47942999999999,38.647296],"type":"Point"}
}