{
  "type": "Feature",
  "properties": {
    "addr:full":"3353 Bradshaw Rd Ste 215 Sacramento CA 95827",
    "addr:housenumber":"3353",
    "addr:postcode":"95827",
    "addr:street":"Bradshaw Rd Ste 215",
    "iso:country":"US",
    "sg:address":"3353 Bradshaw Rd Ste 215",
    "sg:city":"Sacramento",
    "sg:classifiers":[
        {
            "category":"Banks & Credit Unions",
            "subcategory":"Financial Services",
            "type":"Services"
        }
    ],
    "sg:phone":"+1 916 843 1290",
    "sg:postcode":"95827",
    "sg:province":"CA",
    "sg:tags":[
        "broker",
        "mortgage"
    ],
    "wof:name":"Greene Home Loans",
    "wof:placetype":"venue"
},
  "geometry": {"coordinates":[-121.335999,38.563702],"type":"Point"}
}