{
  "type": "Feature",
  "properties": {
    "addr:full":"439 S 7th St Modesto CA 95351",
    "addr:housenumber":"439",
    "addr:postcode":"ca 95351",
    "addr:street":"S 7Th St",
    "iso:country":"US",
    "sg:address":"439 S 7th St",
    "sg:city":"Modesto",
    "sg:classifiers":[
        {
            "category":"Food & Beverages",
            "subcategory":"Groceries & Convenience Stores",
            "type":"Retail Goods"
        }
    ],
    "sg:phone":"+1 209 544 1644",
    "sg:postcode":"95351",
    "sg:province":"CA",
    "sg:tags":[
        "grocer"
    ],
    "wof:name":"Lion's Market",
    "wof:placetype":"venue"
},
  "geometry": {"coordinates":[-120.99299600000001,37.6255],"type":"Point"}
}