{
  "type": "Feature",
  "properties": {
    "iso:country":"US",
    "sg:address":"10212 Stanford Ave",
    "sg:city":"Garden Grove",
    "sg:classifiers":[
        {
            "category":"Organizations",
            "subcategory":"Religious Organization",
            "type":"Services"
        }
    ],
    "sg:phone":"+1 714 638 1251",
    "sg:postcode":"92840",
    "sg:province":"CA",
    "wof:name":"Corporation of President of Th",
    "wof:placetype":"venue"
},
  "geometry": {"coordinates":[-117.95528299999999,33.777613],"type":"Point"}
}