{
  "type": "Feature",
  "properties": {
    "addr:full":"840 Sutro Ave Novato CA 94947",
    "addr:housenumber":"840",
    "addr:postcode":"94947",
    "addr:street":"Sutro Ave",
    "iso:country":"US",
    "sg:address":"840 Sutro Ave",
    "sg:city":"Novato",
    "sg:classifiers":[
        {
            "category":"Professional",
            "subcategory":"Detective & Security Services",
            "type":"Services"
        }
    ],
    "sg:phone":"+1 415 898 4555",
    "sg:postcode":"94947",
    "sg:province":"CA",
    "wof:name":"Smith & Wesson Security",
    "wof:placetype":"venue"
},
  "geometry": {"coordinates":[-122.610263,38.115428],"type":"Point"}
}