{
  "type": "Feature",
  "properties": {
    "addr:full":"1241 Cleveland Ave Santa Rosa CA 95401",
    "addr:housenumber":"1241",
    "addr:postcode":"95401",
    "addr:street":"Cleveland Ave",
    "iso:country":"US",
    "sg:address":"1241 Cleveland Ave",
    "sg:city":"Santa Rosa",
    "sg:classifiers":[
        {
            "category":"Professional",
            "subcategory":"Computer Services",
            "type":"Services"
        }
    ],
    "sg:phone":"+1 707 303 3200",
    "sg:postcode":"95401",
    "sg:province":"CA",
    "sg:tags":[
        "communications",
        "datum",
        "system"
    ],
    "wof:name":"Teltrex Net",
    "wof:placetype":"venue"
},
  "geometry": {"coordinates":[-122.726314,38.454019],"type":"Point"}
}