{
  "type": "Feature",
  "properties": {
    "iso:country":"US",
    "sg:address":"14087 Jean-O-Reno Rd",
    "sg:city":"Poway",
    "sg:classifiers":[
        {
            "category":"Professional",
            "type":"Services"
        }
    ],
    "sg:phone":"+1 858 486 1096",
    "sg:postcode":"92064",
    "sg:province":"CA",
    "wof:name":"Zaitz Inc",
    "wof:placetype":"venue"
},
  "geometry": {"coordinates":[-117.027867,32.957795],"type":"Point"}
}