{
  "type": "Feature",
  "properties": {
    "iso:country":"US",
    "sg:address":"685 N 13th Ave",
    "sg:city":"Upland",
    "sg:classifiers":[
        {
            "category":"Health Services",
            "subcategory":"Medical Lab",
            "type":"Services"
        }
    ],
    "sg:phone":"+1 909 920 6240",
    "sg:postcode":"91786",
    "sg:province":"CA",
    "sg:tags":[
        "test",
        "blood"
    ],
    "wof:name":"San Antonio Med Plz Laboratory",
    "wof:placetype":"venue"
},
  "geometry": {"coordinates":[-117.633498,34.100009],"type":"Point"}
}