{
  "type": "Feature",
  "properties": {
    "addr:full":"3852 Opal St Riverside CA 92509",
    "addr:housenumber":"3852",
    "addr:postcode":"92509",
    "addr:street":"Opal St",
    "iso:country":"US",
    "sg:address":"3852 Opal St",
    "sg:city":"Riverside",
    "sg:classifiers":[
        {
            "category":"Food & Beverages",
            "subcategory":"Bakery",
            "type":"Retail Goods"
        }
    ],
    "sg:phone":"+1 951 683 0137",
    "sg:postcode":"92509",
    "sg:province":"CA",
    "sg:tags":[
        "baker"
    ],
    "wof:name":"Ochoa's Mexican Bakery",
    "wof:placetype":"venue"
},
  "geometry": {"coordinates":[-117.42522099999999,34.004725],"type":"Point"}
}