{
  "type": "Feature",
  "properties": {
    "iso:country":"US",
    "sg:address":"26492 Towne Centre Dr",
    "sg:city":"Foothill Ranch",
    "sg:classifiers":[
        {
            "category":"Autos & Motor Vehicles",
            "subcategory":"Auto Supplies",
            "type":"Retail Goods"
        },
        {
            "category":"Retail",
            "subcategory":"Auto Repair",
            "type":"Services"
        }
    ],
    "sg:phone":"+1 949 587 0500",
    "sg:postcode":"92610",
    "sg:province":"CA",
    "sg:tags":[
        "oil",
        "change",
        "tire"
    ],
    "sg:website":"www.usaexpresstire.com",
    "wof:name":"USA Express Tire & Service",
    "wof:placetype":"venue"
},
  "geometry": {"coordinates":[-117.669803,33.681174],"type":"Point"}
}