{
  "type": "Feature",
  "properties": {
    "addr:full":"2059 Chardon Ln El Cajon CA 92019",
    "addr:housenumber":"2059",
    "addr:postcode":"92019",
    "addr:street":"Chardon Ln",
    "iso:country":"US",
    "sg:address":"2059 Chardon Ln",
    "sg:city":"El Cajon",
    "sg:classifiers":[
        {
            "category":"Wholesale",
            "subcategory":"Apparel",
            "type":"Manufacturing & Wholesale Goods"
        }
    ],
    "sg:phone":"+1 619 441 1873",
    "sg:postcode":"92019",
    "sg:province":"CA",
    "sg:tags":[
        "item",
        "child"
    ],
    "wof:name":"Double Blessings Inc",
    "wof:placetype":"venue"
},
  "geometry": {"coordinates":[-116.911778,32.765435],"type":"Point"}
}