{
  "type": "Feature",
  "properties": {
    "addr:full":"1319 98th Ave Oakland CA 94603",
    "addr:housenumber":"1319",
    "addr:postcode":"94603",
    "addr:street":"98Th Ave",
    "iso:country":"US",
    "sg:address":"1319 98th Ave",
    "sg:city":"Oakland",
    "sg:classifiers":[
        {
            "category":"Organizations",
            "subcategory":"Religious Organization",
            "type":"Services"
        }
    ],
    "sg:phone":"+1 510 553 1066",
    "sg:postcode":"94603",
    "sg:province":"CA",
    "wof:name":"St John's New Beginning Church",
    "wof:placetype":"venue"
},
  "geometry": {"coordinates":[-122.171997,37.743999],"type":"Point"}
}