{
  "type": "Feature",
  "properties": {
    "addr:full":"738 Oak St Colusa CA 95932",
    "addr:housenumber":"738",
    "addr:postcode":"95932",
    "addr:street":"Oak St",
    "iso:country":"US",
    "sg:address":"738 Oak St",
    "sg:city":"Colusa",
    "sg:classifiers":[
        {
            "category":"Professional",
            "subcategory":"Business Services",
            "type":"Services"
        }
    ],
    "sg:phone":"+1 530 520 1911",
    "sg:postcode":"95932",
    "sg:province":"CA",
    "sg:tags":[
        "notary",
        "public"
    ],
    "wof:name":"Barbara J Sachs",
    "wof:placetype":"venue"
},
  "geometry": {"coordinates":[-122.01192,39.213006],"type":"Point"}
}