{
  "type": "Feature",
  "properties": {
    "addr:full":"1911 Hartog Drive San Jose CA 95131",
    "addr:postcode":"1911;95131",
    "addr:street":"Hartog Drive",
    "iso:country":"US",
    "sg:address":"1911 Hartog Drive",
    "sg:city":"San Jose",
    "sg:classifiers":[
        {
            "category":"Wholesale",
            "subcategory":"Computers",
            "type":"Manufacturing & Wholesale Goods"
        }
    ],
    "sg:phone":"+1 408 453 1188",
    "sg:postcode":"95131",
    "sg:province":"CA",
    "sg:website":"www.astak.com",
    "wof:name":"Astak.",
    "wof:placetype":"venue"
},
  "geometry": {"coordinates":[-121.908681,37.382713],"type":"Point"}
}