{
  "type": "Feature",
  "properties": {
    "iso:country":"US",
    "sg:address":"3190 E Miraloma Ave",
    "sg:city":"Anaheim",
    "sg:classifiers":[
        {
            "category":"Manufacturing",
            "subcategory":"Electronics",
            "type":"Manufacturing & Wholesale Goods"
        }
    ],
    "sg:phone":"+1 714 238 7900",
    "sg:postcode":"92806",
    "sg:province":"CA",
    "sg:tags":[
        "recording",
        "audio",
        "video",
        "devices",
        "man"
    ],
    "wof:name":"T D K Electronics Corp",
    "wof:placetype":"venue"
},
  "geometry": {"coordinates":[-117.855203,33.859139],"type":"Point"}
}