{
  "type": "Feature",
  "properties": {
    "addr:full":"450 Peninsula Ave San Mateo CA 94401",
    "addr:housenumber":"450",
    "addr:postcode":"94401",
    "addr:street":"Peninsula Ave",
    "iso:country":"US",
    "sg:address":"450 Peninsula Ave",
    "sg:city":"San Mateo",
    "sg:classifiers":[
        {
            "category":"Social Services",
            "type":"Services"
        }
    ],
    "sg:phone":"+1 650 570 5441",
    "sg:postcode":"94401",
    "sg:province":"CA",
    "sg:tags":[
        "organization",
        "welfare"
    ],
    "wof:name":"Davis Memorial Foundation",
    "wof:placetype":"venue"
},
  "geometry": {"coordinates":[-122.333803,37.580918],"type":"Point"}
}