{
  "type": "Feature",
  "properties": {
    "addr:full":"1863 W San Carlos St San Jose CA 95128",
    "addr:housenumber":"1863",
    "addr:postcode":"95128",
    "addr:street":"W San Carlos St",
    "iso:country":"US",
    "sg:address":"1863 W San Carlos St",
    "sg:city":"San Jose",
    "sg:classifiers":[
        {
            "category":"Shopping",
            "subcategory":"Used Merchandise",
            "type":"Retail Goods"
        },
        {
            "category":"Shopping",
            "subcategory":"Gifts & Souvenirs",
            "type":"Retail Goods"
        }
    ],
    "sg:phone":"+1 408 292 2234",
    "sg:postcode":"95128",
    "sg:province":"CA",
    "sg:tags":[
        "collectible"
    ],
    "wof:name":"Evelyn's Antiques",
    "wof:placetype":"venue"
},
  "geometry": {"coordinates":[-121.927255,37.323485],"type":"Point"}
}