{
  "type": "Feature",
  "properties": {
    "iso:country":"US",
    "sg:address":"28751 Rancho California Rd",
    "sg:city":"Temecula",
    "sg:classifiers":[
        {
            "category":"Health Services",
            "subcategory":"Clinic",
            "type":"Services"
        }
    ],
    "sg:phone":"+1 951 699 3185",
    "sg:postcode":"92590",
    "sg:province":"CA",
    "wof:name":"QTC Medical Group",
    "wof:placetype":"venue"
},
  "geometry": {"coordinates":[-117.156809,33.498036],"type":"Point"}
}