{
  "type": "Feature",
  "properties": {
    "addr:full":"3356 Columbia St San Diego CA 92103",
    "addr:housenumber":"3356",
    "addr:postcode":"92103",
    "addr:street":"Columbia St",
    "iso:country":"US",
    "sg:address":"3356 Columbia St",
    "sg:city":"San Diego",
    "sg:classifiers":[
        {
            "category":"Professional",
            "type":"Services"
        }
    ],
    "sg:phone":"+1 619 298 1893",
    "sg:postcode":"92103",
    "sg:province":"CA",
    "wof:name":"Freeman Inc",
    "wof:placetype":"venue"
},
  "geometry": {"coordinates":[-117.175723,32.73809],"type":"Point"}
}