{
  "type": "Feature",
  "properties": {
    "iso:country":"US",
    "sg:address":"362 W 6th St",
    "sg:city":"San Bernardino",
    "sg:classifiers":[
        {
            "category":"Professional",
            "subcategory":"Lawyer & Legal Services",
            "type":"Services"
        }
    ],
    "sg:phone":"+1 909 889 2828",
    "sg:postcode":"92401",
    "sg:province":"CA",
    "sg:tags":[
        "attorney"
    ],
    "wof:name":"David A St Peter Law Offices",
    "wof:placetype":"venue"
},
  "geometry": {"coordinates":[-117.29187,34.110265],"type":"Point"}
}