{
  "type": "Feature",
  "properties": {
    "addr:full":"5367 E Whitmore Ave Hughson CA 95326",
    "addr:housenumber":"5367",
    "addr:postcode":"95326",
    "addr:street":"E Whitmore Ave",
    "iso:country":"US",
    "sg:address":"5367 E Whitmore Ave",
    "sg:city":"Hughson",
    "sg:classifiers":[
        {
            "category":"Farming",
            "subcategory":"Crops",
            "type":"Manufacturing & Wholesale Goods"
        }
    ],
    "sg:phone":"+1 209 883 2342",
    "sg:postcode":"95326",
    "sg:province":"CA",
    "sg:tags":[
        "grove",
        "nut",
        "tree"
    ],
    "wof:name":"Camagna RE Sons",
    "wof:placetype":"venue"
},
  "geometry": {"coordinates":[-120.888324,37.594845],"type":"Point"}
}