{
  "type": "Feature",
  "properties": {
    "iso:country":"US",
    "sg:address":"1398 Glenwood Ln",
    "sg:city":"Bishop",
    "sg:classifiers":[
        {
            "category":"Building & Trades",
            "subcategory":"Construction",
            "type":"Services"
        }
    ],
    "sg:phone":"+1 760 872 1787",
    "sg:postcode":"93514",
    "sg:province":"CA",
    "sg:tags":[
        "contractor"
    ],
    "wof:name":"Rock Drywall",
    "wof:placetype":"venue"
},
  "geometry": {"coordinates":[-118.418587,37.377241],"type":"Point"}
}