{
  "type": "Feature",
  "properties": {
    "iso:country":"US",
    "sg:address":"722 Broadway",
    "sg:city":"San Diego",
    "sg:classifiers":[
        {
            "category":"Professional",
            "type":"Services"
        }
    ],
    "sg:phone":"+1 619 234 3936",
    "sg:postcode":"92101",
    "sg:province":"CA",
    "sg:tags":[
        "establishment"
    ],
    "wof:name":"Opera House",
    "wof:placetype":"venue"
},
  "geometry": {"coordinates":[-117.157631,32.715788],"type":"Point"}
}