{
  "type": "Feature",
  "properties": {
    "iso:country":"US",
    "sg:address":"1224 10th Street",
    "sg:city":"Coronado",
    "sg:classifiers":[
        {
            "category":"Banks & Credit Unions",
            "subcategory":"Financial Services",
            "type":"Services"
        }
    ],
    "sg:phone":"+1 619 437 1828",
    "sg:postcode":"92118",
    "sg:province":"CA",
    "sg:tags":[
        "broker",
        "mortgage"
    ],
    "wof:name":"Sdr Finiancial-",
    "wof:placetype":"venue"
},
  "geometry": {"coordinates":[-117.178037,32.685111],"type":"Point"}
}