{
  "type": "Feature",
  "properties": {
    "addr:full":"4049 Marconi Ave Sacramento CA 95821",
    "addr:housenumber":"4049",
    "addr:postcode":"95821",
    "addr:street":"Marconi Ave",
    "iso:country":"US",
    "sg:address":"4049 Marconi Ave",
    "sg:city":"Sacramento",
    "sg:classifiers":[
        {
            "category":"Education",
            "subcategory":"School",
            "type":"Public Place"
        }
    ],
    "sg:phone":"+1 916 481 2593",
    "sg:postcode":"95821",
    "sg:province":"CA",
    "sg:tags":[
        "kindergarten",
        "religious",
        "preschool"
    ],
    "sg:website":"http://www.buildinguplives.com",
    "wof:name":"Town & Country Lutheran School",
    "wof:placetype":"venue"
},
  "geometry": {"coordinates":[-121.370003,38.617802],"type":"Point"}
}