{
  "type": "Feature",
  "properties": {
    "iso:country":"US",
    "sg:address":"1540 Blue Bird Canyon Dr",
    "sg:city":"Laguna Beach",
    "sg:classifiers":[
        {
            "category":"Wholesale",
            "subcategory":"Toys & Hobbies",
            "type":"Manufacturing & Wholesale Goods"
        }
    ],
    "sg:phone":"+1 949 497 8267",
    "sg:postcode":"92651",
    "sg:province":"CA",
    "sg:tags":[
        "wholesaler"
    ],
    "wof:name":"Old World Colors",
    "wof:placetype":"venue"
},
  "geometry": {"coordinates":[-117.763566,33.539233],"type":"Point"}
}