{
  "type": "Feature",
  "properties": {
    "iso:country":"US",
    "sg:address":"1800 Harrison St",
    "sg:city":"Oakland",
    "sg:classifiers":[
        {
            "category":"Autos & Motor Vehicles",
            "subcategory":"Automobile Sales",
            "type":"Retail Goods"
        },
        {
            "category":"Airline",
            "type":"Transportation"
        }
    ],
    "sg:phone":"+1 510 410 8080",
    "sg:postcode":"94612",
    "sg:province":"CA",
    "sg:tags":[
        "shuttle",
        "airport",
        "limo"
    ],
    "wof:name":"Airport Taxi & Limo Service",
    "wof:placetype":"venue"
},
  "geometry": {"coordinates":[-122.265214,37.805769],"type":"Point"}
}