{
  "type": "Feature",
  "properties": {
    "addr:full":"1845 N Case St Orange CA 92865",
    "addr:housenumber":"1845",
    "addr:postcode":"92865",
    "addr:street":"N Case St",
    "iso:country":"US",
    "sg:address":"1845 N Case St",
    "sg:city":"Orange",
    "sg:classifiers":[
        {
            "category":"Professional",
            "subcategory":"Research",
            "type":"Services"
        }
    ],
    "sg:phone":"+1 714 279 6777",
    "sg:postcode":"92865",
    "sg:province":"CA",
    "sg:tags":[
        "environmental",
        "ecological"
    ],
    "sg:website":"www.deltaaqs.com",
    "wof:name":"Delta Air Quality Svc",
    "wof:placetype":"venue"
},
  "geometry": {"coordinates":[-117.858724,33.817973],"type":"Point"}
}