{
  "type": "Feature",
  "properties": {
    "iso:country":"US",
    "sg:address":"1109 W 156th St",
    "sg:city":"Compton",
    "sg:classifiers":[
        {
            "category":"Building & Trades",
            "subcategory":"Electrical",
            "type":"Services"
        }
    ],
    "sg:phone":"+1 310 631 4743",
    "sg:postcode":"90220",
    "sg:province":"CA",
    "sg:tags":[
        "electrical",
        "contractor"
    ],
    "wof:name":"Driscoll Electric Inc",
    "wof:placetype":"venue"
},
  "geometry": {"coordinates":[-118.242569,33.891318],"type":"Point"}
}