{
  "type": "Feature",
  "properties": {
    "iso:country":"US",
    "sg:address":"45 Benedict Ct",
    "sg:city":"Alameda",
    "sg:classifiers":[
        {
            "category":"Banks & Credit Unions",
            "subcategory":"Investment Brokerage",
            "type":"Services"
        }
    ],
    "sg:phone":"+1 510 814 6175",
    "sg:postcode":"94502",
    "sg:province":"CA",
    "sg:tags":[
        "advisory"
    ],
    "wof:name":"Dianne Y Woon",
    "wof:placetype":"venue"
},
  "geometry": {"coordinates":[-122.25446599999999,37.736941],"type":"Point"}
}