{
  "type": "Feature",
  "properties": {
    "iso:country":"US",
    "sg:address":"395 Oyster Point Blvd",
    "sg:city":"S San Francisco",
    "sg:classifiers":[
        {
            "category":"Wholesale",
            "subcategory":"Durable Goods & Equipment",
            "type":"Manufacturing & Wholesale Goods"
        }
    ],
    "sg:phone":"+1 650 225 9999",
    "sg:postcode":"94080",
    "sg:province":"CA",
    "sg:tags":[
        "exporter"
    ],
    "wof:name":"Paxim",
    "wof:placetype":"venue"
},
  "geometry": {"coordinates":[-122.385648,37.662833],"type":"Point"}
}