{
  "type": "Feature",
  "properties": {
    "iso:country":"US",
    "sg:address":"2133 E 3rd Street",
    "sg:city":"Los Angeles",
    "sg:classifiers":[
        {
            "category":"Professional",
            "subcategory":"Lawyer & Legal Services",
            "type":"Services"
        }
    ],
    "sg:phone":"+1 323 269 3228",
    "sg:postcode":"90033",
    "sg:province":"CA",
    "sg:tags":[
        "notary"
    ],
    "wof:name":"Hernandez Julio Tax Preprtn",
    "wof:placetype":"venue"
},
  "geometry": {"coordinates":[-118.21373,34.04276],"type":"Point"}
}