{
  "type": "Feature",
  "properties": {
    "iso:country":"US",
    "sg:address":"20550 Corsair Blvd",
    "sg:city":"Hayward",
    "sg:classifiers":[
        {
            "category":"Manufacturing",
            "subcategory":"Rubber & Plastics",
            "type":"Manufacturing & Wholesale Goods"
        }
    ],
    "sg:phone":"+1 510 782 4322",
    "sg:postcode":"94545",
    "sg:province":"CA",
    "sg:tags":[
        "product",
        "metal",
        "can",
        "mfg"
    ],
    "wof:name":"Norton Containers/ Norpack",
    "wof:placetype":"venue"
},
  "geometry": {"coordinates":[-122.13002400000001,37.659271],"type":"Point"}
}