{
  "type": "Feature",
  "properties": {
    "iso:country":"US",
    "sg:address":"3901 Madison Ave",
    "sg:city":"North Highlands",
    "sg:classifiers":[
        {
            "category":"Food & Beverages",
            "subcategory":"Bakery",
            "type":"Retail Goods"
        }
    ],
    "sg:phone":"+1 916 332 2176",
    "sg:postcode":"95660",
    "sg:province":"CA",
    "sg:tags":[
        "doughnut"
    ],
    "wof:name":"Fancy Donuts & Bakery",
    "wof:placetype":"venue"
},
  "geometry": {"coordinates":[-121.37267199999999,38.661184],"type":"Point"}
}