{
  "type": "Feature",
  "properties": {
    "addr:full":"1724 Junction Ave Ste C San Jose CA 95112",
    "addr:housenumber":"1724",
    "addr:postcode":"95112",
    "addr:street":"Junction Ave Ste C",
    "iso:country":"US",
    "sg:address":"1724 Junction Ave Ste C",
    "sg:city":"San Jose",
    "sg:classifiers":[
        {
            "category":"Building & Trades",
            "subcategory":"Construction",
            "type":"Services"
        }
    ],
    "sg:phone":"+1 866 400 0777",
    "sg:postcode":"95112",
    "sg:province":"CA",
    "sg:tags":[
        "air",
        "heating",
        "conditioning/hvac"
    ],
    "sg:website":"www.comfort-airhvac.com",
    "wof:name":"Comfort-Air Hvac",
    "wof:placetype":"venue"
},
  "geometry": {"coordinates":[-121.905877,37.373777],"type":"Point"}
}