{
  "type": "Feature",
  "properties": {
    "iso:country":"US",
    "sg:address":"20700 Plummer St",
    "sg:city":"Chatsworth",
    "sg:classifiers":[
        {
            "category":"Wholesale",
            "subcategory":"Drugs",
            "type":"Manufacturing & Wholesale Goods"
        }
    ],
    "sg:phone":"+1 818 717 2252",
    "sg:postcode":"91311",
    "sg:province":"CA",
    "wof:name":"Cosmopros",
    "wof:placetype":"venue"
},
  "geometry": {"coordinates":[-118.585959,34.242723],"type":"Point"}
}