{
  "type": "Feature",
  "properties": {
    "iso:country":"US",
    "sg:address":"1979 Elden Dr",
    "sg:city":"San Jose",
    "sg:classifiers":[
        {
            "category":"Wholesale",
            "subcategory":"Non-durable Goods",
            "type":"Manufacturing & Wholesale Goods"
        }
    ],
    "sg:phone":"+1 408 559 9070",
    "sg:postcode":"95124",
    "sg:province":"CA",
    "wof:name":"Bridge Trading",
    "wof:placetype":"venue"
},
  "geometry": {"coordinates":[-121.93340000000001,37.275233],"type":"Point"}
}