{
  "type": "Feature",
  "properties": {
    "addr:full":"3023 Bunker Hill St San Diego CA 92109",
    "addr:housenumber":"3023",
    "addr:postcode":"92109",
    "addr:street":"Bunker Hill St",
    "iso:country":"US",
    "sg:address":"3023 Bunker Hill St",
    "sg:city":"San Diego",
    "sg:classifiers":[
        {
            "category":"Health Services",
            "subcategory":"Doctor",
            "type":"Services"
        }
    ],
    "sg:phone":"+1 619 275 4935",
    "sg:postcode":"92109",
    "sg:province":"CA",
    "sg:tags":[
        "physician",
        "surgeon"
    ],
    "wof:name":"Center For Cosmetic Surgery",
    "wof:placetype":"venue"
},
  "geometry": {"coordinates":[-117.214516,32.803627],"type":"Point"}
}