{
  "type": "Feature",
  "properties": {
    "addr:full":"768 Turnbull Canyon Rd City Of Industry CA 91745",
    "addr:housenumber":"768",
    "addr:postcode":"91745",
    "addr:street":"Turnbull Canyon Rd",
    "iso:country":"US",
    "sg:address":"768 Turnbull Canyon Rd",
    "sg:city":"City Of Industry",
    "sg:classifiers":[
        {
            "category":"Manufacturing",
            "subcategory":"Motor Vehicles & Parts",
            "type":"Manufacturing & Wholesale Goods"
        }
    ],
    "sg:phone":"+1 626 937 6988",
    "sg:postcode":"91745",
    "sg:province":"CA",
    "sg:tags":[
        "automobile",
        "supply"
    ],
    "sg:website":"www.pilotautomotive.com",
    "wof:name":"Wang's International Inc",
    "wof:placetype":"venue"
},
  "geometry": {"coordinates":[-117.972903,34.018881],"type":"Point"}
}