{
  "type": "Feature",
  "properties": {
    "iso:country":"US",
    "sg:address":"775 Clover Rd",
    "sg:city":"Tracy",
    "sg:classifiers":[
        {
            "category":"Restaurant",
            "type":"Food & Drink"
        }
    ],
    "sg:phone":"+1 209 832 9288",
    "sg:postcode":"95376",
    "sg:province":"CA",
    "wof:name":"Tracy Buffett",
    "wof:placetype":"venue"
},
  "geometry": {"coordinates":[-121.435432,37.761485],"type":"Point"}
}