{
  "type": "Feature",
  "properties": {
    "addr:full":"1300 Normandy Pl Santa Ana CA 92705",
    "addr:housenumber":"1300",
    "addr:postcode":"92705",
    "addr:street":"Normandy Pl",
    "iso:country":"US",
    "sg:address":"1300 Normandy Pl",
    "sg:city":"Santa Ana",
    "sg:classifiers":[
        {
            "category":"Professional",
            "subcategory":"Computer Services",
            "type":"Services"
        }
    ],
    "sg:phone":"+1 714 547 2024",
    "sg:postcode":"92705",
    "sg:province":"CA",
    "sg:tags":[
        "graphic"
    ],
    "wof:name":"Internet and Beyond Inc",
    "wof:placetype":"venue"
},
  "geometry": {"coordinates":[-117.85195400000001,33.735355],"type":"Point"}
}