{
  "type": "Feature",
  "properties": {
    "addr:full":"1104 Sunset Dr Healdsburg CA 95448",
    "addr:housenumber":"1104",
    "addr:postcode":"95448",
    "addr:street":"Sunset Dr",
    "iso:country":"US",
    "sg:address":"1104 Sunset Dr",
    "sg:city":"Healdsburg",
    "sg:classifiers":[
        {
            "category":"Professional",
            "subcategory":"Art Services",
            "type":"Services"
        }
    ],
    "sg:phone":"+1 707 433 4642",
    "sg:postcode":"95448",
    "sg:province":"CA",
    "sg:tags":[
        "graphic",
        "commercial",
        "designer",
        "artist"
    ],
    "wof:name":"Alligator Graphics",
    "wof:placetype":"venue"
},
  "geometry": {"coordinates":[-122.849861,38.620335],"type":"Point"}
}