{
  "type": "Feature",
  "properties": {
    "addr:full":"PO Box 60 Daly City CA 94016",
    "addr:housenumber":"po box 60",
    "addr:postcode":"94016",
    "iso:country":"US",
    "sg:address":"PO Box 60",
    "sg:city":"Daly City",
    "sg:classifiers":[
        {
            "category":"Professional",
            "type":"Services"
        }
    ],
    "sg:phone":"+1 415 493 8229",
    "sg:postcode":"94016",
    "sg:province":"CA",
    "sg:website":"www.ergobasics.com",
    "wof:name":"ErgoBasics",
    "wof:placetype":"venue"
},
  "geometry": {"coordinates":[-122.45,37.71],"type":"Point"}
}