{
  "type": "Feature",
  "properties": {
    "iso:country":"US",
    "sg:address":"7750 Bolsa Ave",
    "sg:city":"Midway City",
    "sg:classifiers":[
        {
            "category":"Real Estate",
            "subcategory":"Real Estate Agent",
            "type":"Services"
        }
    ],
    "sg:phone":"+1 714 890 1054",
    "sg:postcode":"92655",
    "sg:province":"CA",
    "wof:name":"Pacesetter Real Estate",
    "wof:placetype":"venue"
},
  "geometry": {"coordinates":[-117.99226899999999,33.744596],"type":"Point"}
}