{
  "type": "Feature",
  "properties": {
    "addr:full":"2003 Pasadena Ave Los Angeles CA 90031",
    "addr:housenumber":"2003",
    "addr:postcode":"90031",
    "addr:street":"Pasadena Ave",
    "iso:country":"US",
    "sg:address":"2003 Pasadena Ave",
    "sg:city":"Los Angeles",
    "sg:classifiers":[
        {
            "category":"Retail",
            "subcategory":"Auto Repair",
            "type":"Services"
        }
    ],
    "sg:phone":"+1 323 221 8043",
    "sg:postcode":"90031",
    "sg:province":"CA",
    "wof:name":"Broadway Radiator Shop",
    "wof:placetype":"venue"
},
  "geometry": {"coordinates":[-118.221001,34.074402],"type":"Point"}
}