{
  "type": "Feature",
  "properties": {
    "iso:country":"US",
    "sg:address":"12350 Mabury Rd",
    "sg:city":"San Jose",
    "sg:classifiers":[
        {
            "category":"Building & Trades",
            "subcategory":"Construction",
            "type":"Services"
        }
    ],
    "sg:phone":"+1 408 729 0429",
    "sg:postcode":"95133",
    "sg:province":"CA",
    "sg:tags":[
        "maker",
        "cabinet"
    ],
    "wof:name":"A 1 Custom Cabinet",
    "wof:placetype":"venue"
},
  "geometry": {"coordinates":[-121.866569,37.368606],"type":"Point"}
}