{
  "type": "Feature",
  "properties": {
    "addr:full":"29628 Squaw Valley Dr Sun City CA 92586",
    "addr:housenumber":"29628",
    "addr:postcode":"92586",
    "addr:street":"Squaw Valley Dr",
    "iso:country":"US",
    "sg:address":"29628 Squaw Valley Dr",
    "sg:city":"Sun City",
    "sg:classifiers":[
        {
            "category":"Building & Trades",
            "subcategory":"Construction",
            "type":"Services"
        }
    ],
    "sg:phone":"+1 951 672 2916",
    "sg:postcode":"92586",
    "sg:province":"CA",
    "sg:tags":[
        "general",
        "contractor"
    ],
    "wof:name":"Rick Jonsson Construction",
    "wof:placetype":"venue"
},
  "geometry": {"coordinates":[-117.204412,33.691592],"type":"Point"}
}