{
  "type": "Feature",
  "properties": {
    "iso:country":"US",
    "sg:address":"4522 Weedpatch Hwy",
    "sg:city":"Bakersfield",
    "sg:classifiers":[
        {
            "category":"Building & Trades",
            "subcategory":"Construction",
            "type":"Services"
        }
    ],
    "sg:phone":"+1 661 363 7129",
    "sg:postcode":"93307",
    "sg:province":"CA",
    "sg:tags":[
        "carpentry",
        "contractor"
    ],
    "wof:name":"Bailey & Robertson Co",
    "wof:placetype":"venue"
},
  "geometry": {"coordinates":[-118.91431,35.312508],"type":"Point"}
}