{
  "type": "Feature",
  "properties": {
    "iso:country":"US",
    "sg:address":"944 O St",
    "sg:city":"Firebaugh",
    "sg:classifiers":[
        {
            "category":"Health Services",
            "subcategory":"Doctor",
            "type":"Services"
        }
    ],
    "sg:phone":"+1 559 659 3011",
    "sg:postcode":"93622",
    "sg:province":"CA",
    "sg:tags":[
        "medicine",
        "physician",
        "practice",
        "surgeons",
        "family"
    ],
    "wof:name":"Firebaugh Family Health Center",
    "wof:placetype":"venue"
},
  "geometry": {"coordinates":[-120.45823799999999,36.860548],"type":"Point"}
}