{
  "type": "Feature",
  "properties": {
    "iso:country":"US",
    "sg:address":"737 David Rd",
    "sg:city":"Santa Maria",
    "sg:classifiers":[
        {
            "category":"Building & Trades",
            "subcategory":"Construction",
            "type":"Services"
        }
    ],
    "sg:phone":"+1 805 688 1020",
    "sg:postcode":"93455",
    "sg:province":"CA",
    "sg:tags":[
        "water",
        "restoration",
        "damage"
    ],
    "wof:name":"A-Ok Carpet & Upholstery Clng",
    "wof:placetype":"venue"
},
  "geometry": {"coordinates":[-120.426613,34.866554],"type":"Point"}
}