{
  "type": "Feature",
  "properties": {
    "iso:country":"US",
    "sg:address":"2264 Sierra Meadows Dr",
    "sg:city":"Rocklin",
    "sg:classifiers":[
        {
            "category":"Wholesale",
            "subcategory":"Hardware",
            "type":"Manufacturing & Wholesale Goods"
        }
    ],
    "sg:phone":"+1 916 624 8226",
    "sg:postcode":"95677",
    "sg:province":"CA",
    "sg:tags":[
        "air",
        "parts",
        "conditioning",
        "supply"
    ],
    "wof:name":"Atlas Sales Inc",
    "wof:placetype":"venue"
},
  "geometry": {"coordinates":[-121.222979,38.798798],"type":"Point"}
}