{
  "type": "Feature",
  "properties": {
    "iso:country":"US",
    "sg:address":"26861 Trabuco Rd",
    "sg:city":"Mission Viejo",
    "sg:classifiers":[
        {
            "category":"Building & Trades",
            "subcategory":"Construction",
            "type":"Services"
        }
    ],
    "sg:phone":"+1 949 586 3887",
    "sg:postcode":"92630",
    "sg:province":"CA",
    "sg:tags":[
        "contractor"
    ],
    "wof:name":"Viejo Roofing Co",
    "wof:placetype":"venue"
},
  "geometry": {"coordinates":[-117.657883,33.613433],"type":"Point"}
}