{
  "type": "Feature",
  "properties": {
    "iso:country":"US",
    "sg:address":"Kroeber Plaza Bancroft Way & College Ave",
    "sg:city":"Berkeley",
    "sg:classifiers":[
        {
            "category":"Wholesale",
            "subcategory":"Fruits & Vegetables",
            "type":"Manufacturing & Wholesale Goods"
        }
    ],
    "sg:postcode":"94720",
    "sg:province":"CA",
    "sg:tags":[
        "veggie"
    ],
    "wof:name":"The Local",
    "wof:placetype":"venue"
},
  "geometry": {"coordinates":[-122.254591,37.869296],"type":"Point"}
}