{
  "type": "Feature",
  "properties": {
    "iso:country":"US",
    "sg:address":"1421 Lirio Ave",
    "sg:city":"Ventura",
    "sg:classifiers":[
        {
            "category":"Professional",
            "subcategory":"Management & Consulting",
            "type":"Services"
        }
    ],
    "sg:phone":"+1 805 647 1817",
    "sg:postcode":"93004",
    "sg:province":"CA",
    "sg:tags":[
        "consultant",
        "construction"
    ],
    "wof:name":"Carr Clee Construction",
    "wof:placetype":"venue"
},
  "geometry": {"coordinates":[-119.14865,34.280299],"type":"Point"}
}