{
  "type": "Feature",
  "properties": {
    "addr:full":"3440 del Lago Blvd Escondido CA 92029",
    "addr:housenumber":"3440",
    "addr:postcode":"92029",
    "addr:street":"Del Lago Blvd",
    "iso:country":"US",
    "sg:address":"3440 del Lago Blvd",
    "sg:city":"Escondido",
    "sg:classifiers":[
        {
            "category":"Personal",
            "type":"Services"
        }
    ],
    "sg:phone":"+1 760 735 3271",
    "sg:postcode":"92029",
    "sg:province":"CA",
    "sg:tags":[
        "consultant",
        "wedding"
    ],
    "wof:name":"North County Wedding Planners",
    "wof:placetype":"venue"
},
  "geometry": {"coordinates":[-117.071089,33.070449],"type":"Point"}
}