{
  "type": "Feature",
  "properties": {
    "addr:full":"2463 N 10th Ave Hanford CA 93230",
    "addr:housenumber":"2463",
    "addr:postcode":"ca 93230",
    "addr:street":"N 10Th Ave",
    "iso:country":"US",
    "sg:address":"2463 N 10th Ave",
    "sg:city":"Hanford",
    "sg:classifiers":[
        {
            "category":"Restaurant",
            "type":"Food & Drink"
        }
    ],
    "sg:phone":"+1 559 584 8190",
    "sg:postcode":"93230",
    "sg:province":"CA",
    "wof:name":"Los Pericos De LA Frontera",
    "wof:placetype":"venue"
},
  "geometry": {"coordinates":[-119.637016,36.355888],"type":"Point"}
}