{
  "type": "Feature",
  "properties": {
    "addr:full":"987 S Mariposa Avenue Los Angeles CA 90006",
    "addr:housenumber":"987",
    "addr:postcode":"90006",
    "addr:street":"S Mariposa Avenue",
    "iso:country":"US",
    "sg:address":"987 S Mariposa Avenue",
    "sg:city":"Los Angeles",
    "sg:classifiers":[
        {
            "category":"Education",
            "subcategory":"Preschool",
            "type":"Public Place"
        },
        {
            "category":"Education",
            "subcategory":"School",
            "type":"Public Place"
        }
    ],
    "sg:phone":"+1 213 385 0241",
    "sg:postcode":"90006",
    "sg:province":"CA",
    "sg:tags":[
        "elementary"
    ],
    "sg:website":"www.lausd.net",
    "wof:name":"Los Angeles New Primary Center Number 5",
    "wof:placetype":"venue"
},
  "geometry": {"coordinates":[-118.298806,34.052645],"type":"Point"}
}