{
  "type": "Feature",
  "properties": {
    "iso:country":"US",
    "sg:address":"709 Sheraton Dr",
    "sg:city":"Sunnyvale",
    "sg:classifiers":[
        {
            "category":"Restaurant",
            "type":"Food & Drink"
        }
    ],
    "sg:phone":"+1 408 736 7098",
    "sg:postcode":"94087",
    "sg:province":"CA",
    "sg:tags":[
        "caterer"
    ],
    "wof:name":"Chef About Town",
    "wof:placetype":"venue"
},
  "geometry": {"coordinates":[-122.041957,37.357395],"type":"Point"}
}