{
  "type": "Feature",
  "properties": {
    "addr:full":"1299 Ocean Ave Santa Monica CA 90401",
    "addr:housenumber":"1299",
    "addr:postcode":"90401",
    "addr:street":"Ocean Ave",
    "iso:country":"US",
    "sg:address":"1299 Ocean Ave",
    "sg:city":"Santa Monica",
    "sg:classifiers":[
        {
            "category":"Communications",
            "subcategory":"Film & Video Production",
            "type":"Services"
        }
    ],
    "sg:phone":"+1 310 937 8181",
    "sg:postcode":"90401",
    "sg:province":"CA",
    "sg:tags":[
        "motion"
    ],
    "wof:name":"Coup Detete Inc",
    "wof:placetype":"venue"
},
  "geometry": {"coordinates":[-118.50117899999999,34.016782],"type":"Point"}
}