{
  "type": "Feature",
  "properties": {
    "iso:country":"US",
    "sg:address":"1585 W Holt Ave",
    "sg:city":"El Centro",
    "sg:classifiers":[
        {
            "category":"Retail",
            "subcategory":"Repair Shop",
            "type":"Services"
        }
    ],
    "sg:phone":"+1 760 353 8610",
    "sg:postcode":"92243",
    "sg:province":"CA",
    "sg:tags":[
        "appliance"
    ],
    "wof:name":"Carlos Monzon Handyman Work",
    "wof:placetype":"venue"
},
  "geometry": {"coordinates":[-115.573439,32.787926],"type":"Point"}
}