{
  "type": "Feature",
  "properties": {
    "iso:country":"US",
    "sg:address":"419 4th St",
    "sg:city":"Oakland",
    "sg:classifiers":[
        {
            "category":"Wholesale",
            "subcategory":"Groceries",
            "type":"Manufacturing & Wholesale Goods"
        }
    ],
    "sg:phone":"+1 510 893 2879",
    "sg:postcode":"94607",
    "sg:province":"CA",
    "sg:tags":[
        "general"
    ],
    "wof:name":"Sysco",
    "wof:placetype":"venue"
},
  "geometry": {"coordinates":[-122.275096,37.79716],"type":"Point"}
}