{
  "type": "Feature",
  "properties": {
    "addr:full":"2620 Mission St San Francisco CA 94110",
    "addr:housenumber":"2620",
    "addr:postcode":"94110",
    "addr:street":"Mission St",
    "iso:country":"US",
    "sg:address":"2620 Mission St",
    "sg:city":"San Francisco",
    "sg:classifiers":[
        {
            "category":"Shopping",
            "subcategory":"Clothing, Apparel, & Fashions",
            "type":"Retail Goods"
        }
    ],
    "sg:phone":"+1 415 648 0531",
    "sg:postcode":"94110",
    "sg:province":"CA",
    "sg:tags":[
        "furnishing"
    ],
    "wof:name":"S & N Fashions",
    "wof:placetype":"venue"
},
  "geometry": {"coordinates":[-122.418694,37.754158],"type":"Point"}
}