{
  "type": "Feature",
  "properties": {
    "iso:country":"US",
    "sg:address":"38970 Blacow Rd",
    "sg:city":"Fremont",
    "sg:classifiers":[
        {
            "category":"Professional",
            "type":"Services"
        },
        {
            "category":"Social Services",
            "type":"Services"
        }
    ],
    "sg:phone":"+1 510 794 8398",
    "sg:postcode":"94536",
    "sg:province":"CA",
    "sg:tags":[
        "counselor",
        "marriage",
        "family"
    ],
    "wof:name":"Altbaum Stephen Mft",
    "wof:placetype":"venue"
},
  "geometry": {"coordinates":[-122.000151,37.537359],"type":"Point"}
}