{
  "type": "Feature",
  "properties": {
    "addr:full":"37450 Middlebury St Palmdale CA 93550",
    "addr:postcode":"37450;ca 93550",
    "addr:street":"St",
    "iso:country":"US",
    "sg:address":"37450 Middlebury St",
    "sg:city":"Palmdale",
    "sg:classifiers":[
        {
            "category":"Shopping",
            "subcategory":"Clothing, Apparel, & Fashions",
            "type":"Retail Goods"
        }
    ],
    "sg:phone":"+1 661 947 4921",
    "sg:postcode":"93550",
    "sg:province":"CA",
    "wof:name":"A Pilots Life Active Wear",
    "wof:placetype":"venue"
},
  "geometry": {"coordinates":[-118.09870100000001,34.564251],"type":"Point"}
}