{
  "type": "Feature",
  "properties": {
    "addr:full":"8830 Siempre Viva Rd San Diego CA 92154",
    "addr:housenumber":"8830",
    "addr:postcode":"92154",
    "addr:street":"Siempre Viva Rd",
    "iso:country":"US",
    "sg:address":"8830 Siempre Viva Rd",
    "sg:city":"San Diego",
    "sg:classifiers":[
        {
            "category":"Freight",
            "type":"Transportation"
        }
    ],
    "sg:phone":"+1 619 671 0400",
    "sg:postcode":"92154",
    "sg:province":"CA",
    "sg:tags":[
        "not",
        "classified",
        "elsewhere"
    ],
    "wof:name":"Border Trade Services LLC",
    "wof:placetype":"venue"
},
  "geometry": {"coordinates":[-116.95001999999999,32.553214],"type":"Point"}
}