{
  "type": "Feature",
  "properties": {
    "iso:country":"US",
    "sg:address":"23325 Chase St",
    "sg:city":"West Hills",
    "sg:classifiers":[
        {
            "category":"Wholesale",
            "subcategory":"Sporting Goods",
            "type":"Manufacturing & Wholesale Goods"
        }
    ],
    "sg:phone":"+1 818 345 5900",
    "sg:postcode":"91304",
    "sg:province":"CA",
    "sg:tags":[
        "equipment",
        "pool",
        "swimming"
    ],
    "wof:name":"Water Hole",
    "wof:placetype":"venue"
},
  "geometry": {"coordinates":[-118.636413,34.222966],"type":"Point"}
}