{
  "type": "Feature",
  "properties": {
    "iso:country":"US",
    "sg:address":"1699 Van Ness Avenue",
    "sg:city":"San Francisco",
    "sg:classifiers":[
        {
            "category":"Real Estate",
            "subcategory":"Real Estate Agent",
            "type":"Services"
        }
    ],
    "sg:phone":"+1 415 229 1211",
    "sg:postcode":"94109",
    "sg:province":"CA",
    "sg:website":"www.sfproperties.com",
    "wof:name":"Malin Giddings",
    "wof:placetype":"venue"
},
  "geometry": {"coordinates":[-122.422997,37.7911],"type":"Point"}
}