{
  "type": "Feature",
  "properties": {
    "iso:country":"US",
    "sg:address":"113 W 2nd St",
    "sg:city":"Chico",
    "sg:classifiers":[
        {
            "category":"Shopping",
            "subcategory":"Party Supplies",
            "type":"Retail Goods"
        },
        {
            "category":"Shopping",
            "subcategory":"Gifts & Souvenirs",
            "type":"Retail Goods"
        }
    ],
    "sg:phone":"+1 530 345 3551",
    "sg:postcode":"95928",
    "sg:province":"CA",
    "sg:tags":[
        "shop",
        "wedding"
    ],
    "wof:name":"Zucchini & Vine",
    "wof:placetype":"venue"
},
  "geometry": {"coordinates":[-121.84047700000001,39.730264],"type":"Point"}
}