{
  "type": "Feature",
  "properties": {
    "iso:country":"US",
    "sg:address":"704 W Pacific Coast Hwy",
    "sg:city":"Wilmington",
    "sg:classifiers":[
        {
            "category":"Retail",
            "subcategory":"Auto Repair",
            "type":"Services"
        }
    ],
    "sg:phone":"+1 310 549 6464",
    "sg:postcode":"90744",
    "sg:province":"CA",
    "wof:name":"Ambassadors Business Systems",
    "wof:placetype":"venue"
},
  "geometry": {"coordinates":[-118.271004,33.790798],"type":"Point"}
}