{
  "type": "Feature",
  "properties": {
    "iso:country":"US",
    "sg:address":"2013 J St",
    "sg:city":"Sacramento",
    "sg:classifiers":[
        {
            "category":"Personal",
            "subcategory":"Nail Salon",
            "type":"Services"
        }
    ],
    "sg:phone":"+1 916 443 8634",
    "sg:postcode":"95814",
    "sg:province":"CA",
    "wof:name":"Midtown Nails",
    "wof:placetype":"venue"
},
  "geometry": {"coordinates":[-121.478996,38.576599],"type":"Point"}
}