{
  "type": "Feature",
  "properties": {
    "iso:country":"US",
    "sg:address":"12884 Bradley Ave",
    "sg:city":"Sylmar",
    "sg:classifiers":[
        {
            "category":"Wholesale",
            "subcategory":"Auto Parts",
            "type":"Manufacturing & Wholesale Goods"
        }
    ],
    "sg:phone":"+1 818 364 9751",
    "sg:postcode":"91342",
    "sg:province":"CA",
    "sg:tags":[
        "automobile"
    ],
    "wof:name":"Accurate Equipment",
    "wof:placetype":"venue"
},
  "geometry": {"coordinates":[-118.462196,34.307253],"type":"Point"}
}