{
  "type": "Feature",
  "properties": {
    "iso:country":"US",
    "sg:address":"4568 Missouri Flat Rd",
    "sg:city":"Placerville",
    "sg:classifiers":[
        {
            "category":"Recreation",
            "type":"Entertainment"
        }
    ],
    "sg:phone":"+1 530 622 2330",
    "sg:postcode":"95667",
    "sg:province":"CA",
    "sg:tags":[
        "martial",
        "arts",
        "instruction"
    ],
    "wof:name":"New Man's Karate",
    "wof:placetype":"venue"
},
  "geometry": {"coordinates":[-120.822993,38.69898],"type":"Point"}
}