{
  "type": "Feature",
  "properties": {
    "iso:country":"US",
    "sg:address":"5327 Foster Rd",
    "sg:city":"Paradise",
    "sg:classifiers":[
        {
            "category":"Building & Trades",
            "subcategory":"Construction",
            "type":"Services"
        }
    ],
    "sg:phone":"+1 530 877 5900",
    "sg:postcode":"95969",
    "sg:province":"CA",
    "sg:tags":[
        "sun",
        "solarium",
        "rooms"
    ],
    "wof:name":"Pacific Sunroom Co",
    "wof:placetype":"venue"
},
  "geometry": {"coordinates":[-121.628203,39.74002],"type":"Point"}
}