{
  "type": "Feature",
  "properties": {
    "iso:country":"US",
    "sg:address":"4501 S Alameda St",
    "sg:city":"Vernon",
    "sg:classifiers":[
        {
            "category":"Professional",
            "subcategory":"Art Services",
            "type":"Services"
        },
        {
            "category":"Professional",
            "subcategory":"Business Services",
            "type":"Services"
        }
    ],
    "sg:phone":"+1 323 846 8567",
    "sg:postcode":"90058",
    "sg:province":"CA",
    "sg:tags":[
        "development",
        "product",
        "graphic",
        "designers-industrial",
        "marketing",
        "commercial",
        "designer",
        "design"
    ],
    "wof:name":"D & Y Auto & Business Graphic Design",
    "wof:placetype":"venue"
},
  "geometry": {"coordinates":[-118.239098,34.002762],"type":"Point"}
}