{
  "type": "Feature",
  "properties": {
    "iso:country":"US",
    "sg:address":"1365 Crafton Ave",
    "sg:city":"Mentone",
    "sg:classifiers":[
        {
            "category":"Manufacturing",
            "subcategory":"Motor Vehicles & Parts",
            "type":"Manufacturing & Wholesale Goods"
        }
    ],
    "sg:phone":"+1 909 794 0141",
    "sg:postcode":"92359",
    "sg:province":"CA",
    "sg:tags":[
        "radiators-wholesale",
        "manufacturer"
    ],
    "wof:name":"Ace Radiator & Air Conditioning",
    "wof:placetype":"venue"
},
  "geometry": {"coordinates":[-117.121656,34.073325],"type":"Point"}
}