{
  "type": "Feature",
  "properties": {
    "iso:country":"US",
    "sg:address":"3507 Tully Rd",
    "sg:city":"Modesto",
    "sg:classifiers":[
        {
            "category":"Personal",
            "subcategory":"Beauty Salon",
            "type":"Services"
        }
    ],
    "sg:phone":"+1 209 525 8740",
    "sg:postcode":"95356",
    "sg:province":"CA",
    "sg:website":"www.skin-n-spa.com",
    "wof:name":"Valley Paramedical Skin Care",
    "wof:placetype":"venue"
},
  "geometry": {"coordinates":[-121.01259400000001,37.690858],"type":"Point"}
}