{
  "type": "Feature",
  "properties": {
    "iso:country":"US",
    "sg:address":"100 Nut Tree Pkwy",
    "sg:city":"Vacaville",
    "sg:classifiers":[
        {
            "category":"Fast Food",
            "type":"Food & Drink"
        },
        {
            "category":"Restaurant",
            "type":"Food & Drink"
        }
    ],
    "sg:phone":"+1 707 448 2715",
    "sg:postcode":"95687",
    "sg:province":"CA",
    "sg:tags":[
        "style",
        "family",
        "american",
        "take",
        "pasta",
        "italian"
    ],
    "sg:website":"http://www.olivegarden.com",
    "wof:name":"Olive Garden",
    "wof:placetype":"venue"
},
  "geometry": {"coordinates":[-121.956383,38.368374],"type":"Point"}
}