{
  "type": "Feature",
  "properties": {
    "iso:country":"US",
    "sg:address":"21845 Grand Terrace Rd",
    "sg:city":"Grand Terrace",
    "sg:classifiers":[
        {
            "category":"Real Estate",
            "subcategory":"Real Estate Operator",
            "type":"Services"
        }
    ],
    "sg:phone":"+1 909 514 0104",
    "sg:postcode":"92313",
    "sg:province":"CA",
    "sg:tags":[
        "mobile",
        "home",
        "community"
    ],
    "wof:name":"Grand Terrace Mobile Home Park",
    "wof:placetype":"venue"
},
  "geometry": {"coordinates":[-117.326773,34.037234],"type":"Point"}
}