{
  "type": "Feature",
  "properties": {
    "iso:country":"US",
    "sg:address":"3015 N Main St",
    "sg:city":"Santa Ana",
    "sg:classifiers":[
        {
            "category":"Personal",
            "subcategory":"Beauty Salon",
            "type":"Services"
        }
    ],
    "sg:phone":"+1 714 884 3771",
    "sg:postcode":"92705",
    "sg:province":"CA",
    "sg:tags":[
        "hair"
    ],
    "wof:name":"Instyle Beauty & Supply",
    "wof:placetype":"venue"
},
  "geometry": {"coordinates":[-117.867424,33.773038],"type":"Point"}
}