{
  "type": "Feature",
  "properties": {
    "addr:full":"20111 Stevens Creek Blvd Cupertino CA 95014",
    "addr:housenumber":"20111",
    "addr:postcode":"95014",
    "addr:street":"Stevens Creek Blvd",
    "iso:country":"US",
    "sg:address":"20111 Stevens Creek Blvd",
    "sg:city":"Cupertino",
    "sg:classifiers":[
        {
            "category":"Professional",
            "subcategory":"Computer Services",
            "type":"Services"
        }
    ],
    "sg:phone":"+1 408 253 3883",
    "sg:postcode":"95014",
    "sg:province":"CA",
    "sg:tags":[
        "consultant",
        "designer"
    ],
    "wof:name":"Lanwave Technology USA",
    "wof:placetype":"venue"
},
  "geometry": {"coordinates":[-122.023622,37.322927],"type":"Point"}
}