{
  "type": "Feature",
  "properties": {
    "addr:full":"110 W 7th St Hanford CA 93230",
    "addr:housenumber":"110",
    "addr:postcode":"ca 93230",
    "addr:street":"W 7Th St",
    "iso:country":"US",
    "sg:address":"110 W 7th St",
    "sg:city":"Hanford",
    "sg:classifiers":[
        {
            "category":"Personal",
            "subcategory":"Beauty Salon",
            "type":"Services"
        }
    ],
    "sg:phone":"+1 559 585 1300",
    "sg:postcode":"93230",
    "sg:province":"CA",
    "wof:name":"Jon Ver Salon",
    "wof:placetype":"venue"
},
  "geometry": {"coordinates":[-119.645833,36.326657],"type":"Point"}
}