{
  "type": "Feature",
  "properties": {
    "iso:country":"US",
    "sg:address":"1830 Loveridge Rd",
    "sg:city":"Pittsburg",
    "sg:classifiers":[
        {
            "category":"Home & Garden",
            "subcategory":"Building Materials",
            "type":"Retail Goods"
        },
        {
            "category":"Manufacturing",
            "subcategory":"Building Materials",
            "type":"Manufacturing & Wholesale Goods"
        },
        {
            "category":"Manufacturing",
            "subcategory":"Paper Products",
            "type":"Manufacturing & Wholesale Goods"
        }
    ],
    "sg:phone":"+1 925 432 3833",
    "sg:postcode":"94565",
    "sg:province":"CA",
    "sg:tags":[
        "window",
        "door",
        "screen",
        "molding"
    ],
    "sg:website":"http://www.rldoorco.com",
    "wof:name":"R & L Door Co.",
    "wof:placetype":"venue"
},
  "geometry": {"coordinates":[-121.86255199999999,38.013274],"type":"Point"}
}