{
  "type": "Feature",
  "properties": {
    "addr:full":"4283 N Wilson Way Stockton CA 95205",
    "addr:housenumber":"4283",
    "addr:postcode":"95205",
    "addr:street":"N Wilson Way",
    "iso:country":"US",
    "sg:address":"4283 N Wilson Way",
    "sg:city":"Stockton",
    "sg:classifiers":[
        {
            "category":"Retail",
            "subcategory":"Auto Repair",
            "type":"Services"
        }
    ],
    "sg:phone":"+1 209 946 0636",
    "sg:postcode":"95205",
    "sg:province":"CA",
    "sg:tags":[
        "repairing",
        "automobile"
    ],
    "wof:name":"Sharp Racing Enterprises",
    "wof:placetype":"venue"
},
  "geometry": {"coordinates":[-121.261498,37.998961],"type":"Point"}
}