{
  "type": "Feature",
  "properties": {
    "addr:full":"700 E Tulare Ave Shafter CA 93263",
    "addr:housenumber":"700",
    "addr:postcode":"93263",
    "addr:street":"E Tulare Ave",
    "iso:country":"US",
    "sg:address":"700 E Tulare Ave",
    "sg:city":"Shafter",
    "sg:classifiers":[
        {
            "category":"Recreation",
            "type":"Entertainment"
        }
    ],
    "sg:phone":"+1 661 746 3303",
    "sg:postcode":"93263",
    "sg:province":"CA",
    "sg:tags":[
        "center"
    ],
    "wof:name":"Shafter Recreation & Park Dist",
    "wof:placetype":"venue"
},
  "geometry": {"coordinates":[-119.26597599999999,35.507053],"type":"Point"}
}