{
  "type": "Feature",
  "properties": {
    "iso:country":"US",
    "sg:address":"600 W Evelyn Ave",
    "sg:city":"Mountain View",
    "sg:classifiers":[
        {
            "category":"Local Transit",
            "type":"Transportation"
        }
    ],
    "sg:postcode":"94041",
    "sg:province":"CA",
    "sg:tags":[
        "public"
    ],
    "sg:website":"www.caltrain.com",
    "wof:name":"Caltrain Station - Mountain View",
    "wof:placetype":"venue"
},
  "geometry": {"coordinates":[-122.07612,37.393868],"type":"Point"}
}