{
  "type": "Feature",
  "properties": {
    "addr:full":"17671 Irvine Blvd Ste 120 Tustin CA 92780",
    "addr:housenumber":"17671",
    "addr:postcode":"92780",
    "addr:street":"Irvine Blvd Ste 120",
    "iso:country":"US",
    "sg:address":"17671 Irvine Blvd Ste 120",
    "sg:city":"Tustin",
    "sg:classifiers":[
        {
            "category":"Professional",
            "subcategory":"Lawyer & Legal Services",
            "type":"Services"
        }
    ],
    "sg:phone":"+1 714 838 1099",
    "sg:postcode":"92780",
    "sg:province":"CA",
    "wof:name":"Dinnebier Richard A Atty",
    "wof:placetype":"venue"
},
  "geometry": {"coordinates":[-117.82399700000001,33.748402],"type":"Point"}
}