{
  "type": "Feature",
  "properties": {
    "iso:country":"US",
    "sg:address":"1207 Foothill Blvd",
    "sg:city":"La Verne",
    "sg:classifiers":[
        {
            "category":"Shopping",
            "subcategory":"Bicycles & Sporting Goods",
            "type":"Retail Goods"
        }
    ],
    "sg:phone":"+1 909 593 2755",
    "sg:postcode":"91750",
    "sg:province":"CA",
    "sg:tags":[
        "equipment",
        "skateboard"
    ],
    "wof:name":"Utility Board Shop",
    "wof:placetype":"venue"
},
  "geometry": {"coordinates":[-117.780603,34.118587],"type":"Point"}
}