{
  "type": "Feature",
  "properties": {
    "iso:country":"US",
    "sg:address":"1066 Eugenia Pl",
    "sg:city":"Carpinteria",
    "sg:classifiers":[
        {
            "category":"Health Services",
            "subcategory":"Dentist",
            "type":"Services"
        }
    ],
    "sg:phone":"+1 805 684 2171",
    "sg:postcode":"93013",
    "sg:province":"CA",
    "sg:website":"www.carpinteriasmiles.com/",
    "wof:name":"Sugiyama Janice M DDS Inc",
    "wof:placetype":"venue"
},
  "geometry": {"coordinates":[-119.516998,34.398602],"type":"Point"}
}