{
  "type": "Feature",
  "properties": {
    "iso:country":"US",
    "sg:address":"4694 Alvarado Canyon Rd",
    "sg:city":"San Diego",
    "sg:classifiers":[
        {
            "category":"Professional",
            "subcategory":"Business Services",
            "type":"Services"
        }
    ],
    "sg:phone":"+1 619 582 4881",
    "sg:postcode":"92120",
    "sg:province":"CA",
    "sg:tags":[
        "fund",
        "promotion",
        "raising"
    ],
    "wof:name":"D & S Promotional",
    "wof:placetype":"venue"
},
  "geometry": {"coordinates":[-117.097626,32.780093],"type":"Point"}
}