{
  "type": "Feature",
  "properties": {
    "iso:country":"US",
    "sg:address":"1601 N Mount Vernon Ave",
    "sg:city":"San Bernardino",
    "sg:classifiers":[
        {
            "category":"Wholesale",
            "subcategory":"Auto Parts",
            "type":"Manufacturing & Wholesale Goods"
        }
    ],
    "sg:phone":"+1 909 381 1580",
    "sg:postcode":"92411",
    "sg:province":"CA",
    "sg:tags":[
        "tire"
    ],
    "wof:name":"Los Aguayo Tire Shop",
    "wof:placetype":"venue"
},
  "geometry": {"coordinates":[-117.31383599999999,34.129758],"type":"Point"}
}