{
  "type": "Feature",
  "properties": {
    "addr:full":"6125 Watt Ave North Highlands CA 95660",
    "addr:housenumber":"6125",
    "addr:postcode":"95660",
    "addr:street":"Watt Ave",
    "iso:country":"US",
    "sg:address":"6125 Watt Ave",
    "sg:city":"North Highlands",
    "sg:classifiers":[
        {
            "category":"Organizations",
            "subcategory":"Religious Organization",
            "type":"Services"
        }
    ],
    "sg:phone":"+1 916 332 1711",
    "sg:postcode":"95660",
    "sg:province":"CA",
    "sg:tags":[
        "church"
    ],
    "wof:name":"First Baptist Church",
    "wof:placetype":"venue"
},
  "geometry": {"coordinates":[-121.38296699999999,38.676403],"type":"Point"}
}