{
  "type": "Feature",
  "properties": {
    "addr:full":"501 7th St San Jn Bautista CA 95045",
    "addr:housenumber":"501",
    "addr:postcode":"95045",
    "addr:street":"7Th St",
    "iso:country":"US",
    "sg:address":"501 7th St",
    "sg:city":"San Jn Bautista",
    "sg:classifiers":[
        {
            "category":"Freight",
            "type":"Transportation"
        }
    ],
    "sg:phone":"+1 831 623 2230",
    "sg:postcode":"95045",
    "sg:province":"CA",
    "sg:tags":[
        "trucking"
    ],
    "wof:name":"Holmes & Son's Trucking Inc",
    "wof:placetype":"venue"
},
  "geometry": {"coordinates":[-121.540757,36.842482],"type":"Point"}
}