{
  "type": "Feature",
  "properties": {
    "iso:country":"US",
    "sg:address":"108 Chalk Creek Ct",
    "sg:city":"Martinez",
    "sg:classifiers":[
        {
            "category":"Wholesale",
            "subcategory":"Auto Parts",
            "type":"Manufacturing & Wholesale Goods"
        }
    ],
    "sg:phone":"+1 925 930 7312",
    "sg:postcode":"94553",
    "sg:province":"CA",
    "wof:name":"Matco Tools",
    "wof:placetype":"venue"
},
  "geometry": {"coordinates":[-122.09605999999999,37.958427],"type":"Point"}
}