{
  "type": "Feature",
  "properties": {
    "addr:full":"22414 Saticoy St West Hills CA 91307",
    "addr:postcode":"22414;91307",
    "addr:street":"Saticoy St",
    "iso:country":"US",
    "sg:address":"22414 Saticoy St",
    "sg:city":"West Hills",
    "sg:classifiers":[
        {
            "category":"Social Services",
            "type":"Services"
        }
    ],
    "sg:phone":"+1 818 888 0039",
    "sg:postcode":"91307",
    "sg:province":"CA",
    "sg:tags":[
        "organization",
        "welfare"
    ],
    "wof:name":"Salvation Army",
    "wof:placetype":"venue"
},
  "geometry": {"coordinates":[-118.61879999999999,34.208183],"type":"Point"}
}