{
  "type": "Feature",
  "properties": {
    "iso:country":"US",
    "sg:address":"1375 S Eliseo Dr",
    "sg:city":"Greenbrae",
    "sg:classifiers":[
        {
            "category":"Health Services",
            "subcategory":"Doctor",
            "type":"Services"
        }
    ],
    "sg:phone":"+1 415 461 1032",
    "sg:postcode":"94904",
    "sg:province":"CA",
    "sg:tags":[
        "medical"
    ],
    "wof:name":"Robert Freinkel MD Inc",
    "wof:placetype":"venue"
},
  "geometry": {"coordinates":[-122.532415,37.943614],"type":"Point"}
}