{
  "type": "Feature",
  "properties": {
    "iso:country":"US",
    "sg:address":"11645 Sherman Way",
    "sg:city":"North Hollywood",
    "sg:classifiers":[
        {
            "category":"Wholesale",
            "subcategory":"Hardware",
            "type":"Manufacturing & Wholesale Goods"
        }
    ],
    "sg:phone":"+1 818 764 8973",
    "sg:postcode":"91605",
    "sg:province":"CA",
    "sg:tags":[
        "tool"
    ],
    "wof:name":"J M Tools",
    "wof:placetype":"venue"
},
  "geometry": {"coordinates":[-118.38627200000001,34.201272],"type":"Point"}
}