{
  "type": "Feature",
  "properties": {
    "addr:full":"3815 Floresta Way Los Angeles CA 90043",
    "addr:housenumber":"3815",
    "addr:postcode":"90043",
    "addr:street":"Floresta Way",
    "iso:country":"US",
    "sg:address":"3815 Floresta Way",
    "sg:city":"Los Angeles",
    "sg:classifiers":[
        {
            "category":"Professional",
            "subcategory":"Management & Consulting",
            "type":"Services"
        }
    ],
    "sg:phone":"+1 323 528 7647",
    "sg:postcode":"90043",
    "sg:province":"CA",
    "wof:name":"Blackwell-Byrant and Assoc",
    "wof:placetype":"venue"
},
  "geometry": {"coordinates":[-118.34032000000001,33.996978],"type":"Point"}
}