{
  "type": "Feature",
  "properties": {
    "addr:full":"2906 W Magnolia Blvd Burbank CA 91506",
    "addr:housenumber":"2906",
    "addr:postcode":"91506",
    "addr:street":"W Magnolia Blvd",
    "iso:country":"US",
    "sg:address":"2906 W Magnolia Blvd",
    "sg:city":"Burbank",
    "sg:classifiers":[
        {
            "category":"Professional",
            "subcategory":"Business Services",
            "type":"Services"
        }
    ],
    "sg:phone":"+1 626 304 2652",
    "sg:postcode":"91506",
    "sg:province":"CA",
    "sg:tags":[
        "messenger"
    ],
    "wof:name":"Now Messenger Svc",
    "wof:placetype":"venue"
},
  "geometry": {"coordinates":[-118.339797,34.170185],"type":"Point"}
}