{
  "type": "Feature",
  "properties": {
    "iso:country":"US",
    "sg:address":"6383 Las Positas Rd",
    "sg:city":"Livermore",
    "sg:classifiers":[
        {
            "category":"Manufacturing",
            "subcategory":"Furniture",
            "type":"Manufacturing & Wholesale Goods"
        }
    ],
    "sg:phone":"+1 925 447 9200",
    "sg:postcode":"94551",
    "sg:province":"CA",
    "sg:tags":[
        "bench"
    ],
    "sg:website":"www.johnsoncontrols.com",
    "wof:name":"Johnson Controls Inc",
    "wof:placetype":"venue"
},
  "geometry": {"coordinates":[-121.718591,37.703499],"type":"Point"}
}