{
  "type": "Feature",
  "properties": {
    "addr:full":"9515 Soquel Dr Aptos CA 95003",
    "addr:housenumber":"9515",
    "addr:postcode":"ca 95003",
    "addr:street":"Soquel Dr",
    "iso:country":"US",
    "sg:address":"9515 Soquel Dr",
    "sg:city":"Aptos",
    "sg:classifiers":[
        {
            "category":"Professional",
            "subcategory":"Accounting & Tax Preparation",
            "type":"Services"
        }
    ],
    "sg:phone":"+1 831 685 1401",
    "sg:postcode":"95003",
    "sg:province":"CA",
    "sg:tags":[
        "bookkeeping",
        "general"
    ],
    "wof:name":"Philip G Seydel CPA",
    "wof:placetype":"venue"
},
  "geometry": {"coordinates":[-121.88487000000001,36.975428],"type":"Point"}
}