{
  "type": "Feature",
  "properties": {
    "addr:full":"6232 Custer Ln Oroville CA 95966",
    "addr:housenumber":"6232",
    "addr:postcode":"95966",
    "addr:street":"Custer Ln",
    "iso:country":"US",
    "sg:address":"6232 Custer Ln",
    "sg:city":"Oroville",
    "sg:classifiers":[
        {
            "category":"Building & Trades",
            "subcategory":"Plumbing",
            "type":"Services"
        },
        {
            "category":"Building & Trades",
            "subcategory":"Cleaning & Sanitation",
            "type":"Services"
        }
    ],
    "sg:phone":"+1 530 533 4128",
    "sg:postcode":"95966",
    "sg:province":"CA",
    "sg:tags":[
        "cleaner",
        "plumber",
        "industrial",
        "repairer",
        "sewer",
        "contractors-commercial",
        "plumbing-drain"
    ],
    "wof:name":"Royal Flush Plumbing",
    "wof:placetype":"venue"
},
  "geometry": {"coordinates":[-121.553978,39.457956],"type":"Point"}
}