{
  "type": "Feature",
  "properties": {
    "addr:full":"3204 N Van Ness Blvd Fresno CA 93704",
    "addr:housenumber":"3204",
    "addr:postcode":"93704",
    "addr:street":"N Van Ness Blvd",
    "iso:country":"US",
    "sg:address":"3204 N Van Ness Blvd",
    "sg:city":"Fresno",
    "sg:classifiers":[
        {
            "category":"Building & Trades",
            "subcategory":"Construction",
            "type":"Services"
        }
    ],
    "sg:phone":"+1 559 224 8221",
    "sg:postcode":"93704",
    "sg:province":"CA",
    "sg:tags":[
        "pond",
        "supply"
    ],
    "wof:name":"Planet Earth Ponds",
    "wof:placetype":"venue"
},
  "geometry": {"coordinates":[-119.804033,36.780319],"type":"Point"}
}