{
  "type": "Feature",
  "properties": {
    "iso:country":"US",
    "sg:address":"1100 E 5th St",
    "sg:city":"Oxnard",
    "sg:classifiers":[
        {
            "category":"Wholesale",
            "subcategory":"Machinery & Supplies",
            "type":"Manufacturing & Wholesale Goods"
        }
    ],
    "sg:phone":"+1 805 486 1400",
    "sg:postcode":"93030",
    "sg:province":"CA",
    "sg:tags":[
        "equipment",
        "industrial"
    ],
    "wof:name":"Accu Air Gases & Equipment",
    "wof:placetype":"venue"
},
  "geometry": {"coordinates":[-119.159916,34.196937],"type":"Point"}
}