{
  "type": "Feature",
  "properties": {
    "iso:country":"US",
    "sg:address":"1214 252nd St",
    "sg:city":"Harbor City",
    "sg:classifiers":[
        {
            "category":"Personal",
            "subcategory":"Nail Salon",
            "type":"Services"
        }
    ],
    "sg:phone":"+1 310 257 0111",
    "sg:postcode":"90710",
    "sg:province":"CA",
    "wof:name":"Peter E Mathews Construction",
    "wof:placetype":"venue"
},
  "geometry": {"coordinates":[-118.297997,33.795799],"type":"Point"}
}