{
  "type": "Feature",
  "properties": {
    "addr:full":"16400 Prairie Avenue Lawndale CA 90260",
    "addr:housenumber":"16400",
    "addr:postcode":"ca 90260",
    "addr:street":"Prairie Avenue",
    "iso:country":"US",
    "sg:address":"16400 Prairie Avenue",
    "sg:city":"Lawndale",
    "sg:classifiers":[
        {
            "category":"Sports & Exercise",
            "subcategory":"Golf",
            "type":"Entertainment"
        }
    ],
    "sg:phone":"+1 310 217 9919",
    "sg:postcode":"90260",
    "sg:province":"CA",
    "wof:name":"Los Angeles County of",
    "wof:placetype":"venue"
},
  "geometry": {"coordinates":[-118.343818,33.881852],"type":"Point"}
}