{
  "type": "Feature",
  "properties": {
    "iso:country":"US",
    "sg:address":"14671 Tumble Weed Ln",
    "sg:city":"Watsonville",
    "sg:classifiers":[
        {
            "category":"Real Estate",
            "subcategory":"Architect",
            "type":"Services"
        }
    ],
    "sg:phone":"+1 831 761 3500",
    "sg:postcode":"95076",
    "sg:province":"CA",
    "sg:tags":[
        "building",
        "designer"
    ],
    "wof:name":"Shaffer & Fried Engineering",
    "wof:placetype":"venue"
},
  "geometry": {"coordinates":[-121.717537,36.831862],"type":"Point"}
}