{
  "type": "Feature",
  "properties": {
    "iso:country":"US",
    "sg:address":"10115 Donner Pass Rd",
    "sg:city":"Truckee",
    "sg:classifiers":[
        {
            "category":"Shopping",
            "type":"Retail Goods"
        }
    ],
    "sg:phone":"+1 530 587 5189",
    "sg:postcode":"96161",
    "sg:province":"CA",
    "sg:tags":[
        "art",
        "gallery",
        "dealer"
    ],
    "wof:name":"Artruckee",
    "wof:placetype":"venue"
},
  "geometry": {"coordinates":[-120.185367,39.327677],"type":"Point"}
}