{
  "type": "Feature",
  "properties": {
    "iso:country":"US",
    "sg:address":"2461 Park Avenue",
    "sg:city":"Tustin",
    "sg:classifiers":[
        {
            "category":"Food & Beverages",
            "subcategory":"Candy",
            "type":"Retail Goods"
        },
        {
            "category":"Food & Beverages",
            "subcategory":"Chocolate",
            "type":"Retail Goods"
        }
    ],
    "sg:phone":"+1 714 258 0026",
    "sg:postcode":"92782",
    "sg:province":"CA",
    "sg:tags":[
        "shop",
        "dessert",
        "chocolatiers"
    ],
    "sg:website":"rmcf.com/CA/Tustin50661",
    "wof:name":"Rocky Mountain Chocolate Factory",
    "wof:placetype":"venue"
},
  "geometry": {"coordinates":[-117.827421,33.698422],"type":"Point"}
}