{
  "type": "Feature",
  "properties": {
    "iso:country":"US",
    "sg:address":"16210 Monreal Rd",
    "sg:city":"Madera",
    "sg:classifiers":[
        {
            "category":"Building & Trades",
            "subcategory":"Construction",
            "type":"Services"
        }
    ],
    "sg:phone":"+1 559 474 9433",
    "sg:postcode":"93636",
    "sg:province":"CA",
    "sg:tags":[
        "contractor",
        "fence-sales"
    ],
    "wof:name":"Gerardo's Fence",
    "wof:placetype":"venue"
},
  "geometry": {"coordinates":[-119.886506,36.982837],"type":"Point"}
}