{
  "type": "Feature",
  "properties": {
    "iso:country":"US",
    "sg:address":"100 Buena Vista Ave",
    "sg:city":"Suisun City",
    "sg:classifiers":[
        {
            "category":"Arts & Performance",
            "subcategory":"Theater",
            "type":"Entertainment"
        }
    ],
    "sg:phone":"+1 707 425 0453",
    "sg:postcode":"94585",
    "sg:province":"CA",
    "sg:tags":[
        "talent",
        "agency",
        "casting"
    ],
    "wof:name":"Progeny MRTA",
    "wof:placetype":"venue"
},
  "geometry": {"coordinates":[-122.025823,38.249364],"type":"Point"}
}