{
  "type": "Feature",
  "properties": {
    "addr:full":"3642 N Freeway Blvd Sacramento CA 95833",
    "addr:housenumber":"3642",
    "addr:postcode":"95833",
    "addr:street":"N Freeway Blvd",
    "iso:country":"US",
    "sg:address":"3642 N Freeway Blvd",
    "sg:city":"Sacramento",
    "sg:classifiers":[
        {
            "category":"Shopping",
            "subcategory":"Clothing, Apparel, & Fashions",
            "type":"Retail Goods"
        }
    ],
    "sg:phone":"+1 916 285 7309",
    "sg:postcode":"95833",
    "sg:province":"CA",
    "sg:tags":[
        "children's",
        "men's",
        "clothing",
        "women's"
    ],
    "sg:website":"www.tillys.com",
    "wof:name":"Tilly's",
    "wof:placetype":"venue"
},
  "geometry": {"coordinates":[-121.49762699999999,38.639376],"type":"Point"}
}