{
  "type": "Feature",
  "properties": {
    "addr:full":"2181 Union St San Francisco CA 94123",
    "addr:housenumber":"2181",
    "addr:postcode":"94123",
    "addr:street":"Union St",
    "iso:country":"US",
    "sg:address":"2181 Union St",
    "sg:city":"San Francisco",
    "sg:classifiers":[
        {
            "category":"Shopping",
            "subcategory":"Jewelry",
            "type":"Retail Goods"
        }
    ],
    "sg:phone":"+1 415 346 7525",
    "sg:postcode":"94123",
    "sg:province":"CA",
    "sg:tags":[
        "jeweler"
    ],
    "wof:name":"Old & New Estates",
    "wof:placetype":"venue"
},
  "geometry": {"coordinates":[-122.43441799999999,37.797186],"type":"Point"}
}