{
  "type": "Feature",
  "properties": {
    "iso:country":"US",
    "sg:address":"1243 Alpine Rd",
    "sg:city":"Walnut Creek",
    "sg:classifiers":[
        {
            "category":"Professional",
            "subcategory":"Accounting & Tax Preparation",
            "type":"Services"
        }
    ],
    "sg:phone":"+1 925 937 2596",
    "sg:postcode":"94596",
    "sg:province":"CA",
    "sg:tags":[
        "accountant"
    ],
    "wof:name":"Jacqueline Hershey CPA",
    "wof:placetype":"venue"
},
  "geometry": {"coordinates":[-122.066763,37.896678],"type":"Point"}
}