{
  "type": "Feature",
  "properties": {
    "iso:country":"US",
    "sg:address":"6650 Flanders Dr",
    "sg:city":"San Diego",
    "sg:classifiers":[
        {
            "category":"Wholesale",
            "subcategory":"Medical Equipment & Supplies",
            "type":"Manufacturing & Wholesale Goods"
        }
    ],
    "sg:phone":"+1 858 578 6289",
    "sg:postcode":"92121",
    "sg:province":"CA",
    "sg:tags":[
        "instrument",
        "pneumatic"
    ],
    "wof:name":"TST",
    "wof:placetype":"venue"
},
  "geometry": {"coordinates":[-117.176917,32.904683],"type":"Point"}
}