{
  "type": "Feature",
  "properties": {
    "addr:full":"805 Oak Knoll Cir Pasadena CA 91106",
    "addr:housenumber":"805",
    "addr:postcode":"91106",
    "addr:street":"Oak Knoll Cir",
    "iso:country":"US",
    "sg:address":"805 Oak Knoll Cir",
    "sg:city":"Pasadena",
    "sg:classifiers":[
        {
            "category":"Professional",
            "type":"Services"
        }
    ],
    "sg:phone":"+1 626 792 9305",
    "sg:postcode":"91106",
    "sg:province":"CA",
    "wof:name":"Francesca De La Flor Anti",
    "wof:placetype":"venue"
},
  "geometry": {"coordinates":[-118.13356899999999,34.130022],"type":"Point"}
}