{
  "type": "Feature",
  "properties": {
    "iso:country":"US",
    "sg:address":"2101 W College Ave",
    "sg:city":"Santa Rosa",
    "sg:classifiers":[
        {
            "category":"Restaurant",
            "type":"Food & Drink"
        }
    ],
    "sg:menulink":"http://www.allmenus.com/ca/santa-rosa/77845-papa-murphys/menu/",
    "sg:phone":"+1 707 575 0444",
    "sg:postcode":"95401",
    "sg:province":"CA",
    "sg:tags":[
        "american",
        "pizza"
    ],
    "wof:name":"Papa Murphy's",
    "wof:placetype":"venue"
},
  "geometry": {"coordinates":[-122.752009,38.445572],"type":"Point"}
}