{
  "type": "Feature",
  "properties": {
    "addr:full":"160 S Old Springs Rd Anaheim CA 92808",
    "addr:housenumber":"160",
    "addr:postcode":"92808",
    "addr:street":"S Old Springs Rd",
    "iso:country":"US",
    "sg:address":"160 S Old Springs Rd",
    "sg:city":"Anaheim",
    "sg:classifiers":[
        {
            "category":"Professional",
            "subcategory":"Accounting & Tax Preparation",
            "type":"Services"
        }
    ],
    "sg:phone":"+1 714 637 4552",
    "sg:postcode":"92808",
    "sg:province":"CA",
    "sg:tags":[
        "accountant"
    ],
    "sg:website":"www.simonscorp.com",
    "wof:name":"Durst Engine H CPA",
    "wof:placetype":"venue"
},
  "geometry": {"coordinates":[-117.741511,33.864923],"type":"Point"}
}