{
  "type": "Feature",
  "properties": {
    "acgov:api":"0.0",
    "acgov:type":"Spec School",
    "addr:full":"500 Walnut Ave. Fremont CA",
    "wof:categories":[
        "education_and_religion:education=school"
    ],
    "wof:name":"California School for the Blind",
    "wof:placetype":"venue"
},
  "geometry": {"coordinates":[-121.96557444195116,37.56250733558952],"type":"Point"}
}