{
  "type": "Feature",
  "properties": {
    "addr:full":"147 Sacramento St Auburn CA 95603",
    "addr:housenumber":"147",
    "addr:postcode":"ca 95603",
    "addr:street":"Sacramento St",
    "iso:country":"US",
    "sg:address":"147 Sacramento St",
    "sg:city":"Auburn",
    "sg:classifiers":[
        {
            "category":"Shopping",
            "subcategory":"Hobbies, Toys, & Games",
            "type":"Retail Goods"
        },
        {
            "category":"Wholesale",
            "subcategory":"Jewelry",
            "type":"Manufacturing & Wholesale Goods"
        }
    ],
    "sg:phone":"+1 530 823 1020",
    "sg:postcode":"95603",
    "sg:province":"CA",
    "sg:tags":[
        "stone",
        "who",
        "beads"
    ],
    "sg:website":"www.gypsywindbeads.com",
    "wof:name":"Gypsy Wind Beads & Trims",
    "wof:placetype":"venue"
},
  "geometry": {"coordinates":[-121.078164,38.895663],"type":"Point"}
}