{
  "type": "Feature",
  "properties": {
    "iso:country":"US",
    "sg:address":"11125 Knott Ave",
    "sg:city":"Cypress",
    "sg:classifiers":[
        {
            "category":"Real Estate",
            "subcategory":"Real Estate Services",
            "type":"Services"
        }
    ],
    "sg:phone":"+1 714 893 1410",
    "sg:postcode":"90630",
    "sg:province":"CA",
    "sg:tags":[
        "management",
        "property"
    ],
    "wof:name":"Warland Investments Ltd",
    "wof:placetype":"venue"
},
  "geometry": {"coordinates":[-118.120502,33.799926],"type":"Point"}
}