{
  "type": "Feature",
  "properties": {
    "iso:country":"US",
    "sg:address":"5111 Santa Fe St",
    "sg:city":"San Diego",
    "sg:classifiers":[
        {
            "category":"Professional",
            "subcategory":"Business Services",
            "type":"Services"
        }
    ],
    "sg:phone":"+1 858 866 4478",
    "sg:postcode":"92109",
    "sg:province":"CA",
    "sg:tags":[
        "recording",
        "studio"
    ],
    "wof:name":"DLI Production",
    "wof:placetype":"venue"
},
  "geometry": {"coordinates":[-117.21863399999999,32.813477],"type":"Point"}
}