{
  "type": "Feature",
  "properties": {
    "iso:country":"US",
    "sg:address":"14429 Firmona Ave",
    "sg:city":"Lawndale",
    "sg:classifiers":[
        {
            "category":"Freight",
            "type":"Transportation"
        }
    ],
    "sg:phone":"+1 310 308 0542",
    "sg:postcode":"90260",
    "sg:province":"CA",
    "sg:tags":[
        "delivery"
    ],
    "wof:name":"Ground Rush Svc",
    "wof:placetype":"venue"
},
  "geometry": {"coordinates":[-118.357702,33.901266],"type":"Point"}
}