{
  "type": "Feature",
  "properties": {
    "addr:full":"15995 Tuscola Rd Apple Valley CA 92307",
    "addr:postcode":"15995;92307",
    "addr:street":"Tuscola Rd",
    "iso:country":"US",
    "sg:address":"15995 Tuscola Rd",
    "sg:city":"Apple Valley",
    "sg:classifiers":[
        {
            "category":"Health Services",
            "subcategory":"Doctor",
            "type":"Services"
        }
    ],
    "sg:phone":"+1 760 242 2620",
    "sg:postcode":"92307",
    "sg:province":"CA",
    "sg:tags":[
        "dentist"
    ],
    "wof:name":"Aspen Dental Group",
    "wof:placetype":"venue"
},
  "geometry": {"coordinates":[-117.269206,34.542677],"type":"Point"}
}