{
  "type": "Feature",
  "properties": {
    "addr:full":"3657 Stevens Creek Blvd Santa Clara CA 95051",
    "addr:housenumber":"3657",
    "addr:postcode":"95051",
    "addr:street":"Stevens Creek Blvd",
    "iso:country":"US",
    "sg:address":"3657 Stevens Creek Blvd",
    "sg:city":"Santa Clara",
    "sg:classifiers":[
        {
            "category":"Retail",
            "subcategory":"Auto Repair",
            "type":"Services"
        }
    ],
    "sg:phone":"+1 408 244 8666",
    "sg:postcode":"95051",
    "sg:province":"CA",
    "sg:tags":[
        "repairing",
        "automobile"
    ],
    "wof:name":"Precision Tune Auto Care",
    "wof:placetype":"venue"
},
  "geometry": {"coordinates":[-121.964989,37.323377],"type":"Point"}
}