{
  "type": "Feature",
  "properties": {
    "iso:country":"US",
    "sg:address":"1834 Mangrove Ave",
    "sg:city":"Chico",
    "sg:classifiers":[
        {
            "category":"Communications",
            "subcategory":"Film & Video Production",
            "type":"Services"
        }
    ],
    "sg:phone":"+1 530 893 0607",
    "sg:postcode":"95926",
    "sg:province":"CA",
    "sg:tags":[
        "taping"
    ],
    "wof:name":"Sun Ray Media",
    "wof:placetype":"venue"
},
  "geometry": {"coordinates":[-121.842775,39.748253],"type":"Point"}
}