{
  "type": "Feature",
  "properties": {
    "addr:full":"385 W Grant Line Rd Tracy CA 95376",
    "addr:housenumber":"385",
    "addr:postcode":"95376",
    "addr:street":"W Grant Line Rd",
    "iso:country":"US",
    "sg:address":"385 W Grant Line Rd",
    "sg:city":"Tracy",
    "sg:classifiers":[
        {
            "category":"Government",
            "subcategory":"Police Station",
            "type":"Public Place"
        }
    ],
    "sg:phone":"+1 209 835 8920",
    "sg:postcode":"95376",
    "sg:province":"CA",
    "sg:tags":[
        "state"
    ],
    "wof:name":"Highway Patrol",
    "wof:placetype":"venue"
},
  "geometry": {"coordinates":[-121.43114199999999,37.754316],"type":"Point"}
}