{
  "type": "Feature",
  "properties": {
    "addr:full":"242 Fawn Dr San Anselmo CA 94960",
    "addr:housenumber":"242",
    "addr:postcode":"94960",
    "addr:street":"Fawn Dr",
    "iso:country":"US",
    "sg:address":"242 Fawn Dr",
    "sg:city":"San Anselmo",
    "sg:classifiers":[
        {
            "category":"Professional",
            "type":"Services"
        }
    ],
    "sg:phone":"+1 415 721 5523",
    "sg:postcode":"94960",
    "sg:province":"CA",
    "sg:tags":[
        "establishment"
    ],
    "wof:name":"Haxton Place Assoc",
    "wof:placetype":"venue"
},
  "geometry": {"coordinates":[-122.571443,38.006093],"type":"Point"}
}