{
  "type": "Feature",
  "properties": {
    "addr:full":"2020 Gratton St Riverside CA 92504",
    "addr:housenumber":"2020",
    "addr:postcode":"92504",
    "addr:street":"Gratton St",
    "iso:country":"US",
    "sg:address":"2020 Gratton St",
    "sg:city":"Riverside",
    "sg:classifiers":[
        {
            "category":"Farming",
            "subcategory":"Orchard",
            "type":"Manufacturing & Wholesale Goods"
        }
    ],
    "sg:phone":"+1 951 689 6340",
    "sg:postcode":"92504",
    "sg:province":"CA",
    "sg:tags":[
        "citrus",
        "grove",
        "fruit"
    ],
    "wof:name":"William Kirby",
    "wof:placetype":"venue"
},
  "geometry": {"coordinates":[-117.40764,33.905579],"type":"Point"}
}