{
  "type": "Feature",
  "properties": {
    "addr:full":"21650 State Hwy 18 Apple Valley CA 92307",
    "addr:housenumber":"21650",
    "addr:postcode":"92307",
    "addr:street":"State Hwy 18",
    "iso:country":"US",
    "sg:address":"21650 State Hwy 18",
    "sg:city":"Apple Valley",
    "sg:classifiers":[
        {
            "category":"Retail",
            "subcategory":"Auto Rental",
            "type":"Services"
        }
    ],
    "sg:phone":"+1 760 961 2237",
    "sg:postcode":"92307",
    "sg:province":"CA",
    "sg:tags":[
        "renting",
        "truck",
        "leasing"
    ],
    "wof:name":"U-Haul Co",
    "wof:placetype":"venue"
},
  "geometry": {"coordinates":[-117.191565,34.50092],"type":"Point"}
}