{
  "type": "Feature",
  "properties": {
    "addr:full":"2323 de la Vina St Santa Barbara CA 93105",
    "addr:housenumber":"2323",
    "addr:postcode":"93105",
    "addr:street":"De La Vina St",
    "iso:country":"US",
    "sg:address":"2323 de la Vina St",
    "sg:city":"Santa Barbara",
    "sg:classifiers":[
        {
            "category":"Health Services",
            "subcategory":"Health Practitioner",
            "type":"Services"
        }
    ],
    "sg:phone":"+1 805 682 1866",
    "sg:postcode":"93105",
    "sg:province":"CA",
    "sg:tags":[
        "psychologist"
    ],
    "wof:name":"Gerald Schroeder PHD",
    "wof:placetype":"venue"
},
  "geometry": {"coordinates":[-119.72069999999999,34.431655],"type":"Point"}
}