{
  "type": "Feature",
  "properties": {
    "iso:country":"US",
    "sg:address":"5015 Lankershim Blvd",
    "sg:city":"North Hollywood",
    "sg:classifiers":[
        {
            "category":"Home & Garden",
            "subcategory":"Furniture",
            "type":"Retail Goods"
        }
    ],
    "sg:phone":"+1 818 509 2610",
    "sg:postcode":"91601",
    "sg:province":"CA",
    "sg:tags":[
        "store"
    ],
    "wof:name":"Simply Discount Furniture",
    "wof:placetype":"venue"
},
  "geometry": {"coordinates":[-118.373001,34.161598],"type":"Point"}
}