{
  "type": "Feature",
  "properties": {
    "iso:country":"US",
    "sg:address":"1022 E Alisal St",
    "sg:city":"Salinas",
    "sg:classifiers":[
        {
            "category":"Shopping",
            "subcategory":"Department Store",
            "type":"Retail Goods"
        }
    ],
    "sg:phone":"+1 831 754 2184",
    "sg:postcode":"93905",
    "sg:province":"CA",
    "wof:name":"Factory 2-U",
    "wof:placetype":"venue"
},
  "geometry": {"coordinates":[-121.625612,36.67267],"type":"Point"}
}