{
  "type": "Feature",
  "properties": {
    "iso:country":"US",
    "sg:address":"1537 N Neptune Ave",
    "sg:city":"Wilmington",
    "sg:classifiers":[
        {
            "category":"Organizations",
            "subcategory":"Religious Organization",
            "type":"Services"
        }
    ],
    "sg:phone":"+1 310 835 7870",
    "sg:postcode":"90744",
    "sg:province":"CA",
    "sg:tags":[
        "church"
    ],
    "wof:name":"St John's Episcopal Church",
    "wof:placetype":"venue"
},
  "geometry": {"coordinates":[-118.270051,33.794272],"type":"Point"}
}