{
  "type": "Feature",
  "properties": {
    "iso:country":"US",
    "sg:address":"2190 Crittenden Ln",
    "sg:city":"Mountain View",
    "sg:classifiers":[
        {
            "category":"Home & Garden",
            "subcategory":"Garden Supply",
            "type":"Retail Goods"
        }
    ],
    "sg:phone":"+1 650 968 6117",
    "sg:postcode":"94043",
    "sg:province":"CA",
    "sg:tags":[
        "nursery",
        "gardening"
    ],
    "wof:name":"A To Z Tree Nursery-Hydroseeding",
    "wof:placetype":"venue"
},
  "geometry": {"coordinates":[-122.077003,37.4249],"type":"Point"}
}