{
  "type": "Feature",
  "properties": {
    "iso:country":"US",
    "sg:address":"9769 W Pico Blvd",
    "sg:city":"Los Angeles",
    "sg:classifiers":[
        {
            "category":"Food & Beverages",
            "subcategory":"Groceries & Convenience Stores",
            "type":"Retail Goods"
        }
    ],
    "sg:phone":"+1 310 553 8181",
    "sg:postcode":"90035",
    "sg:province":"CA",
    "sg:website":"www.owensla.com",
    "wof:name":"Owen's Market by Mindy Weiss",
    "wof:placetype":"venue"
},
  "geometry": {"coordinates":[-118.401378,34.054241],"type":"Point"}
}