{
  "type": "Feature",
  "properties": {
    "addr:full":"4301 E Cesar E Chavez Ave Los Angeles CA 90022",
    "addr:housenumber":"4301",
    "addr:postcode":"90022",
    "addr:street":"E Cesar E Chavez Ave",
    "iso:country":"US",
    "sg:address":"4301 E Cesar E Chavez Ave",
    "sg:city":"Los Angeles",
    "sg:classifiers":[
        {
            "category":"Autos & Motor Vehicles",
            "subcategory":"Automobile Sales",
            "type":"Retail Goods"
        }
    ],
    "sg:phone":"+1 323 261 6448",
    "sg:postcode":"90022",
    "sg:province":"CA",
    "sg:tags":[
        "automotive"
    ],
    "sg:website":"www.autozone.com",
    "wof:name":"AutoZone",
    "wof:placetype":"venue"
},
  "geometry": {"coordinates":[-118.17358,34.040569],"type":"Point"}
}