{
  "type": "Feature",
  "properties": {
    "addr:full":"803 Vaca Valley Pkwy Vacaville CA 95688",
    "addr:housenumber":"803",
    "addr:postcode":"95688",
    "addr:street":"Vaca Valley Pkwy",
    "iso:country":"US",
    "sg:address":"803 Vaca Valley Pkwy",
    "sg:city":"Vacaville",
    "sg:classifiers":[
        {
            "category":"Home & Garden",
            "subcategory":"Building Materials",
            "type":"Retail Goods"
        }
    ],
    "sg:phone":"+1 707 454 0224",
    "sg:postcode":"95688",
    "sg:province":"CA",
    "sg:tags":[
        "windows"
    ],
    "wof:name":"ABC Window Contractors Inc",
    "wof:placetype":"venue"
},
  "geometry": {"coordinates":[-121.957649,38.395349],"type":"Point"}
}