{
  "type": "Feature",
  "properties": {
    "iso:country":"US",
    "sg:address":"18822 Brookhurst St",
    "sg:city":"Fountain Valley",
    "sg:classifiers":[
        {
            "category":"Shopping",
            "subcategory":"Pets & Pet Supplies",
            "type":"Retail Goods"
        }
    ],
    "sg:phone":"+1 714 964 3525",
    "sg:postcode":"92708",
    "sg:province":"CA",
    "sg:tags":[
        "store"
    ],
    "sg:website":"www.prehistoricpets.com",
    "wof:name":"Prehistoric Pets",
    "wof:placetype":"venue"
},
  "geometry": {"coordinates":[-117.95402199999999,33.690061],"type":"Point"}
}