{
  "type": "Feature",
  "properties": {
    "addr:full":"110 W Ocean Blvd Ste 537 Long Beach CA 90802",
    "addr:housenumber":"110",
    "addr:postcode":"90802",
    "addr:street":"W Ocean Blvd Ste 537",
    "iso:country":"US",
    "sg:address":"110 W Ocean Blvd Ste 537",
    "sg:city":"Long Beach",
    "sg:classifiers":[
        {
            "category":"Personal",
            "type":"Services"
        }
    ],
    "sg:phone":"+1 562 435 0065",
    "sg:postcode":"90802",
    "sg:province":"CA",
    "sg:tags":[
        "party",
        "planning",
        "event"
    ],
    "wof:name":"Bravo Productions",
    "wof:placetype":"venue"
},
  "geometry": {"coordinates":[-118.193001,33.766998],"type":"Point"}
}