{
  "type": "Feature",
  "properties": {
    "iso:country":"US",
    "sg:address":"186 E Cameron Pl",
    "sg:city":"Long Beach",
    "sg:classifiers":[
        {
            "category":"Real Estate",
            "subcategory":"Real Estate Services",
            "type":"Services"
        }
    ],
    "sg:phone":"+1 562 426 9604",
    "sg:postcode":"90807",
    "sg:province":"CA",
    "sg:tags":[
        "management",
        "property"
    ],
    "wof:name":"Shaver Investment Corp",
    "wof:placetype":"venue"
},
  "geometry": {"coordinates":[-118.19096,33.823052],"type":"Point"}
}