{
  "type": "Feature",
  "properties": {
    "iso:country":"US",
    "sg:address":"3325 Wilshire Blvd",
    "sg:city":"Los Angeles",
    "sg:classifiers":[
        {
            "category":"Professional",
            "subcategory":"Lawyer & Legal Services",
            "type":"Services"
        }
    ],
    "sg:phone":"+1 323 938 5248",
    "sg:postcode":"90010",
    "sg:province":"CA",
    "wof:name":"Bloom David B Atty",
    "wof:placetype":"venue"
},
  "geometry": {"coordinates":[-118.294998,34.061798],"type":"Point"}
}