{
  "type": "Feature",
  "properties": {
    "addr:full":"296 Oak Tree Dr Santa Rosa CA 95401",
    "addr:housenumber":"296",
    "addr:postcode":"95401",
    "addr:street":"Oak Tree Dr",
    "iso:country":"US",
    "sg:address":"296 Oak Tree Dr",
    "sg:city":"Santa Rosa",
    "sg:classifiers":[
        {
            "category":"Professional",
            "type":"Services"
        }
    ],
    "sg:phone":"+1 707 577 0307",
    "sg:postcode":"95401",
    "sg:province":"CA",
    "wof:name":"Hacienda De La Solana",
    "wof:placetype":"venue"
},
  "geometry": {"coordinates":[-122.801134,38.436609],"type":"Point"}
}