{
  "type": "Feature",
  "properties": {
    "addr:full":"1456 Peterson Ln Santa Rosa CA 95403",
    "addr:housenumber":"1456",
    "addr:postcode":"95403",
    "addr:street":"Peterson Ln",
    "iso:country":"US",
    "sg:address":"1456 Peterson Ln",
    "sg:city":"Santa Rosa",
    "sg:classifiers":[
        {
            "category":"Professional",
            "subcategory":"Business Services",
            "type":"Services"
        }
    ],
    "sg:phone":"+1 707 321 6681",
    "sg:postcode":"95403",
    "sg:province":"CA",
    "sg:tags":[
        "translator",
        "interpreter"
    ],
    "wof:name":"Spanish Services",
    "wof:placetype":"venue"
},
  "geometry": {"coordinates":[-122.764409,38.452206],"type":"Point"}
}