{
  "type": "Feature",
  "properties": {
    "addr:full":"842 S Sherbourne Dr Los Angeles CA 90035",
    "addr:housenumber":"842",
    "addr:postcode":"90035",
    "addr:street":"S Sherbourne Dr",
    "iso:country":"US",
    "sg:address":"842 S Sherbourne Dr",
    "sg:city":"Los Angeles",
    "sg:classifiers":[
        {
            "category":"Professional",
            "subcategory":"Business Services",
            "type":"Services"
        }
    ],
    "sg:phone":"+1 310 659 0678",
    "sg:postcode":"90035",
    "sg:province":"CA",
    "wof:name":"C J Holstrom Assoc",
    "wof:placetype":"venue"
},
  "geometry": {"coordinates":[-118.379212,34.061801],"type":"Point"}
}