{
  "type": "Feature",
  "properties": {
    "addr:full":"5412 San Pablo Ave Emeryville CA 94608",
    "addr:housenumber":"5412",
    "addr:postcode":"94608",
    "addr:street":"San Pablo Ave",
    "iso:country":"US",
    "sg:address":"5412 San Pablo Ave",
    "sg:city":"Emeryville",
    "sg:classifiers":[
        {
            "category":"Personal",
            "subcategory":"Barber",
            "type":"Services"
        }
    ],
    "sg:phone":"+1 510 969 5198",
    "sg:postcode":"94608",
    "sg:province":"CA",
    "wof:name":"Hair Mechanics The",
    "wof:placetype":"venue"
},
  "geometry": {"coordinates":[-122.281966,37.837774],"type":"Point"}
}