{
  "type": "Feature",
  "properties": {
    "addr:full":"12440 Cliff Ave Bakersfield CA 93306",
    "addr:housenumber":"12440",
    "addr:postcode":"93306",
    "addr:street":"Cliff Ave",
    "iso:country":"US",
    "sg:address":"12440 Cliff Ave",
    "sg:city":"Bakersfield",
    "sg:classifiers":[
        {
            "category":"Manufacturing",
            "subcategory":"Apparel",
            "type":"Manufacturing & Wholesale Goods"
        }
    ],
    "sg:phone":"+1 661 872 0028",
    "sg:postcode":"93306",
    "sg:province":"CA",
    "sg:tags":[
        "mfg"
    ],
    "wof:name":"Made In Character",
    "wof:placetype":"venue"
},
  "geometry": {"coordinates":[-118.863398,35.400023],"type":"Point"}
}