{
  "type": "Feature",
  "properties": {
    "addr:full":"148 S G St Arcata CA 95521",
    "addr:housenumber":"148",
    "addr:postcode":"95521",
    "addr:street":"S G St",
    "iso:country":"US",
    "sg:address":"148 S G St",
    "sg:city":"Arcata",
    "sg:classifiers":[
        {
            "category":"Professional",
            "type":"Services"
        }
    ],
    "sg:phone":"+1 707 822 9888",
    "sg:postcode":"95521",
    "sg:province":"CA",
    "sg:tags":[
        "equipment",
        "hydroponics",
        "supply"
    ],
    "wof:name":"Water Planet Garden Supply",
    "wof:placetype":"venue"
},
  "geometry": {"coordinates":[-124.08755600000001,40.863702],"type":"Point"}
}