{
  "type": "Feature",
  "properties": {
    "addr:full":"12055 Persimmon Ter Auburn CA 95603",
    "addr:housenumber":"12055",
    "addr:postcode":"ca 95603",
    "addr:street":"Persimmon Ter",
    "iso:country":"US",
    "sg:address":"12055 Persimmon Ter",
    "sg:city":"Auburn",
    "sg:classifiers":[
        {
            "category":"Health Services",
            "subcategory":"Chiropractor",
            "type":"Services"
        }
    ],
    "sg:phone":"+1 530 888 8771",
    "sg:postcode":"95603",
    "sg:province":"CA",
    "wof:name":"Health First Chiropractic",
    "wof:placetype":"venue"
},
  "geometry": {"coordinates":[-121.07646,38.910956],"type":"Point"}
}