{
  "type": "Feature",
  "properties": {
    "addr:full":"35442 Highway 41 Coarsegold CA 93614",
    "addr:housenumber":"35442",
    "addr:postcode":"93614",
    "addr:street":"Highway 41",
    "iso:country":"US",
    "sg:address":"35442 Highway 41",
    "sg:city":"Coarsegold",
    "sg:classifiers":[
        {
            "category":"Utilities",
            "subcategory":"Recycling",
            "type":"Services"
        }
    ],
    "sg:phone":"+1 559 683 7990",
    "sg:postcode":"93614",
    "sg:province":"CA",
    "wof:name":"Anderson Recycle Center",
    "wof:placetype":"venue"
},
  "geometry": {"coordinates":[-119.67171,37.270269],"type":"Point"}
}