{
  "type": "Feature",
  "properties": {
    "iso:country":"US",
    "sg:address":"26118 Research Pl",
    "sg:city":"Hayward",
    "sg:classifiers":[
        {
            "category":"Manufacturing",
            "subcategory":"Chemicals & Compounds",
            "type":"Manufacturing & Wholesale Goods"
        }
    ],
    "sg:phone":"+1 510 732 5551",
    "sg:postcode":"94545",
    "sg:province":"CA",
    "sg:tags":[
        "miller",
        "drug"
    ],
    "wof:name":"Questcor Pharmaceuticals Inc",
    "wof:placetype":"venue"
},
  "geometry": {"coordinates":[-122.12644400000001,37.625589],"type":"Point"}
}