{
  "type": "Feature",
  "properties": {
    "addr:full":"3828 W Carson St Ste 102 Torrance CA 90503",
    "addr:housenumber":"3828",
    "addr:postcode":"90503",
    "addr:street":"W Carson St Ste 102",
    "iso:country":"US",
    "sg:address":"3828 W Carson St Ste 102",
    "sg:city":"Torrance",
    "sg:classifiers":[
        {
            "category":"Professional",
            "subcategory":"Lawyer & Legal Services",
            "type":"Services"
        }
    ],
    "sg:phone":"+1 310 543 1240",
    "sg:postcode":"90503",
    "sg:province":"CA",
    "wof:name":"Guzman Denise M Attorney At Law",
    "wof:placetype":"venue"
},
  "geometry": {"coordinates":[-118.352997,33.831402],"type":"Point"}
}