{
  "type": "Feature",
  "properties": {
    "addr:full":"235 N 2nd St Campbell CA 95008",
    "addr:housenumber":"235",
    "addr:postcode":"95008",
    "addr:street":"N 2Nd St",
    "iso:country":"US",
    "sg:address":"235 N 2nd St",
    "sg:city":"Campbell",
    "sg:classifiers":[
        {
            "category":"Professional",
            "type":"Services"
        }
    ],
    "sg:phone":"+1 408 871 7885",
    "sg:postcode":"95008",
    "sg:province":"CA",
    "sg:tags":[
        "establishment"
    ],
    "wof:name":"Smith & Smith",
    "wof:placetype":"venue"
},
  "geometry": {"coordinates":[-121.946099,37.289715],"type":"Point"}
}