{
  "type": "Feature",
  "properties": {
    "iso:country":"US",
    "sg:address":"1029 K St",
    "sg:city":"Sacramento",
    "sg:classifiers":[
        {
            "category":"Professional",
            "subcategory":"Research",
            "type":"Services"
        }
    ],
    "sg:phone":"+1 916 446 4185",
    "sg:postcode":"95814",
    "sg:province":"CA",
    "wof:name":"Bipartisan Center For Research",
    "wof:placetype":"venue"
},
  "geometry": {"coordinates":[-121.492872,38.57902],"type":"Point"}
}