{
  "type": "Feature",
  "properties": {
    "addr:full":"252 N L St Dinuba CA 93618",
    "addr:housenumber":"252",
    "addr:postcode":"93618",
    "addr:street":"N L St",
    "iso:country":"US",
    "sg:address":"252 N L St",
    "sg:city":"Dinuba",
    "sg:classifiers":[
        {
            "category":"Retail",
            "subcategory":"Auto Repair",
            "type":"Services"
        }
    ],
    "sg:phone":"+1 559 591 4398",
    "sg:postcode":"93618",
    "sg:province":"CA",
    "sg:tags":[
        "repairing",
        "automobile"
    ],
    "wof:name":"Dinuba Auto Clinic",
    "wof:placetype":"venue"
},
  "geometry": {"coordinates":[-119.391836,36.542364],"type":"Point"}
}