{
  "type": "Feature",
  "properties": {
    "iso:country":"US",
    "sg:address":"1666 N St",
    "sg:city":"Merced",
    "sg:classifiers":[
        {
            "category":"Banks & Credit Unions",
            "subcategory":"Bank",
            "type":"Services"
        }
    ],
    "sg:phone":"+1 209 384 6880",
    "sg:postcode":"95340",
    "sg:province":"CA",
    "wof:name":"Westamerica Bank",
    "wof:placetype":"venue"
},
  "geometry": {"coordinates":[-120.486604,37.301825],"type":"Point"}
}