{
  "type": "Feature",
  "properties": {
    "iso:country":"US",
    "sg:address":"510 Myrtle Ave",
    "sg:city":"S San Francisco",
    "sg:classifiers":[
        {
            "category":"Shopping",
            "subcategory":"Stationery & Office Supplies",
            "type":"Retail Goods"
        }
    ],
    "sg:phone":"+1 650 873 8023",
    "sg:postcode":"94080",
    "sg:province":"CA",
    "sg:tags":[
        "equipment",
        "filing",
        "system"
    ],
    "sg:website":"www.scistorage.com",
    "wof:name":"Systems Concepts Inc",
    "wof:placetype":"venue"
},
  "geometry": {"coordinates":[-122.42056599999999,37.648019],"type":"Point"}
}