{
  "type": "Feature",
  "properties": {
    "iso:country":"US",
    "sg:address":"1015 Civic Center Dr West Ste 100",
    "sg:city":"Santa Ana",
    "sg:classifiers":[
        {
            "category":"Professional",
            "type":"Services"
        }
    ],
    "sg:phone":"+1 800 422 4540",
    "sg:postcode":"92703",
    "sg:province":"CA",
    "sg:website":"www.bailbondsorangecounty.net",
    "wof:name":"Orange County Bail Bonds",
    "wof:placetype":"venue"
},
  "geometry": {"coordinates":[-117.87867199999999,33.751544],"type":"Point"}
}