{
  "type": "Feature",
  "properties": {
    "iso:country":"US",
    "sg:address":"1631 Royal Ave",
    "sg:city":"Simi Valley",
    "sg:classifiers":[
        {
            "category":"Food & Beverages",
            "subcategory":"Groceries & Convenience Stores",
            "type":"Retail Goods"
        }
    ],
    "sg:phone":"+1 805 527 1905",
    "sg:postcode":"93065",
    "sg:province":"CA",
    "sg:tags":[
        "grocer"
    ],
    "wof:name":"El Mercadito",
    "wof:placetype":"venue"
},
  "geometry": {"coordinates":[-118.766352,34.264547],"type":"Point"}
}