{
  "type": "Feature",
  "properties": {
    "addr:full":"632 Switzer St San Diego CA 92101",
    "addr:housenumber":"632",
    "addr:postcode":"92101",
    "addr:street":"Switzer St",
    "iso:country":"US",
    "sg:address":"632 Switzer St",
    "sg:city":"San Diego",
    "sg:classifiers":[
        {
            "category":"Freight",
            "type":"Transportation"
        }
    ],
    "sg:phone":"+1 619 699 4898",
    "sg:postcode":"92101",
    "sg:province":"CA",
    "sg:tags":[
        "broker",
        "customs"
    ],
    "wof:name":"J & K Fresh San Diego",
    "wof:placetype":"venue"
},
  "geometry": {"coordinates":[-117.156001,32.700018],"type":"Point"}
}