{
  "type": "Feature",
  "properties": {
    "iso:country":"US",
    "sg:address":"21501 E Cliff Dr",
    "sg:city":"Santa Cruz",
    "sg:classifiers":[
        {
            "category":"Professional",
            "subcategory":"Computer Services",
            "type":"Services"
        }
    ],
    "sg:phone":"+1 831 316 0042",
    "sg:postcode":"95062",
    "sg:province":"CA",
    "sg:tags":[
        "repair"
    ],
    "wof:name":"Grey Wolf Computer",
    "wof:placetype":"venue"
},
  "geometry": {"coordinates":[-121.99006199999999,36.96326],"type":"Point"}
}