{
  "type": "Feature",
  "properties": {
    "iso:country":"US",
    "sg:address":"10126 Rosecrans Ave",
    "sg:city":"Bellflower",
    "sg:classifiers":[
        {
            "category":"Personal",
            "subcategory":"Beauty Salon",
            "type":"Services"
        }
    ],
    "sg:phone":"+1 562 461 1236",
    "sg:postcode":"90706",
    "sg:province":"CA",
    "sg:tags":[
        "nail",
        "manicuring"
    ],
    "wof:name":"Kim Nails & Spas",
    "wof:placetype":"venue"
},
  "geometry": {"coordinates":[-118.116997,33.901798],"type":"Point"}
}