{
  "type": "Feature",
  "properties": {
    "iso:country":"US",
    "sg:address":"19310 Superior St",
    "sg:city":"Northridge",
    "sg:classifiers":[
        {
            "category":"Professional",
            "subcategory":"Business Services",
            "type":"Services"
        }
    ],
    "sg:phone":"+1 818 349 9308",
    "sg:postcode":"91324",
    "sg:province":"CA",
    "sg:tags":[
        "interior",
        "consultant",
        "design",
        "decorator"
    ],
    "wof:name":"Tom Hamilton Interior Design",
    "wof:placetype":"venue"
},
  "geometry": {"coordinates":[-118.554247,34.246241],"type":"Point"}
}