{
  "type": "Feature",
  "properties": {
    "addr:full":"7750 Dagget St San Diego CA 92111",
    "addr:housenumber":"7750",
    "addr:postcode":"92111",
    "addr:street":"Dagget St",
    "iso:country":"US",
    "sg:address":"7750 Dagget St",
    "sg:city":"San Diego",
    "sg:classifiers":[
        {
            "category":"Education",
            "subcategory":"Music School",
            "type":"Public Place"
        },
        {
            "category":"Education",
            "subcategory":"Preschool",
            "type":"Public Place"
        },
        {
            "category":"Education",
            "subcategory":"School",
            "type":"Public Place"
        }
    ],
    "sg:phone":"+1 858 496 9212",
    "sg:postcode":"92111",
    "sg:province":"CA",
    "sg:tags":[
        "elementary",
        "instrument",
        "musical",
        "teacher"
    ],
    "wof:name":"United Education Center of San Diego",
    "wof:placetype":"venue"
},
  "geometry": {"coordinates":[-117.155998,32.823601],"type":"Point"}
}