{
  "type": "Feature",
  "properties": {
    "addr:full":"19279 Paradise Mountain Rd Valley Center CA 92082",
    "addr:housenumber":"19279",
    "addr:postcode":"92082",
    "addr:street":"Paradise Mountain Rd",
    "iso:country":"US",
    "sg:address":"19279 Paradise Mountain Rd",
    "sg:city":"Valley Center",
    "sg:classifiers":[
        {
            "category":"Recreation",
            "type":"Entertainment"
        }
    ],
    "sg:phone":"+1 760 631 1165",
    "sg:postcode":"92082",
    "sg:province":"CA",
    "sg:tags":[
        "stable"
    ],
    "wof:name":"Snow's Pony Rides",
    "wof:placetype":"venue"
},
  "geometry": {"coordinates":[-116.933582,33.203692],"type":"Point"}
}