{
  "type": "Feature",
  "properties": {
    "iso:country":"US",
    "sg:address":"20135 Leadwell St",
    "sg:city":"Winnetka",
    "sg:classifiers":[
        {
            "category":"Professional",
            "subcategory":"Computer Services",
            "type":"Services"
        }
    ],
    "sg:phone":"+1 818 882 5634",
    "sg:postcode":"91306",
    "sg:province":"CA",
    "wof:name":"Times A Wastin",
    "wof:placetype":"venue"
},
  "geometry": {"coordinates":[-118.570997,34.203494],"type":"Point"}
}