{
  "type": "Feature",
  "properties": {
    "addr:full":"5647 Glen Haven Ct San Jose CA 95129",
    "addr:housenumber":"5647",
    "addr:postcode":"95129",
    "addr:street":"Glen Haven Ct",
    "iso:country":"US",
    "sg:address":"5647 Glen Haven Ct",
    "sg:city":"San Jose",
    "sg:classifiers":[
        {
            "category":"Real Estate",
            "subcategory":"Real Estate Agent",
            "type":"Services"
        }
    ],
    "sg:phone":"+1 408 777 9800",
    "sg:postcode":"95129",
    "sg:province":"CA",
    "wof:name":"Esaving Home & Loan",
    "wof:placetype":"venue"
},
  "geometry": {"coordinates":[-122.001475,37.302077],"type":"Point"}
}