{
  "type": "Feature",
  "properties": {
    "iso:country":"US",
    "sg:address":"180 N Luring Dr",
    "sg:city":"Palm Springs",
    "sg:classifiers":[
        {
            "category":"Retail",
            "subcategory":"Auto Repair",
            "type":"Services"
        }
    ],
    "sg:phone":"+1 760 322 5573",
    "sg:postcode":"92262",
    "sg:province":"CA",
    "sg:tags":[
        "transmission"
    ],
    "sg:website":"www.natlsba.com",
    "wof:name":"National Small Business Cnsltg",
    "wof:placetype":"venue"
},
  "geometry": {"coordinates":[-116.52698599999999,33.824416],"type":"Point"}
}