{
  "type": "Feature",
  "properties": {
    "iso:country":"US",
    "sg:address":"1100 Space Park Dr",
    "sg:city":"Santa Clara",
    "sg:classifiers":[
        {
            "category":"Utilities",
            "subcategory":"Telephone",
            "type":"Services"
        }
    ],
    "sg:phone":"+1 408 727 2781",
    "sg:postcode":"95054",
    "sg:province":"CA",
    "sg:tags":[
        "telecommunication"
    ],
    "wof:name":"Tyco Telecommunications",
    "wof:placetype":"venue"
},
  "geometry": {"coordinates":[-121.956132,37.376175],"type":"Point"}
}