{
  "type": "Feature",
  "properties": {
    "addr:full":"24802 Rollingwood Rd Lake Forest CA 92630",
    "addr:housenumber":"24802",
    "addr:postcode":"92630",
    "addr:street":"Rollingwood Rd",
    "iso:country":"US",
    "sg:address":"24802 Rollingwood Rd",
    "sg:city":"Lake Forest",
    "sg:classifiers":[
        {
            "category":"Wholesale",
            "subcategory":"Stationery",
            "type":"Manufacturing & Wholesale Goods"
        }
    ],
    "sg:phone":"+1 949 380 7194",
    "sg:postcode":"92630",
    "sg:province":"CA",
    "sg:tags":[
        "business",
        "form"
    ],
    "wof:name":"Mv Whittaker Enterprises Inc",
    "wof:placetype":"venue"
},
  "geometry": {"coordinates":[-117.69825,33.63728],"type":"Point"}
}