{
  "type": "Feature",
  "properties": {
    "iso:country":"US",
    "sg:address":"334 Shaw Ave",
    "sg:city":"Clovis",
    "sg:classifiers":[
        {
            "category":"Health Services",
            "subcategory":"Doctor",
            "type":"Services"
        }
    ],
    "sg:phone":"+1 559 299 2168",
    "sg:postcode":"93612",
    "sg:province":"CA",
    "sg:tags":[
        "dentist"
    ],
    "wof:name":"Dennis E Quaglia Inc",
    "wof:placetype":"venue"
},
  "geometry": {"coordinates":[-119.70472700000001,36.808425],"type":"Point"}
}