{
  "type": "Feature",
  "properties": {
    "iso:country":"US",
    "sg:address":"11901 Arminta St",
    "sg:city":"North Hollywood",
    "sg:classifiers":[
        {
            "category":"Building & Trades",
            "subcategory":"Construction",
            "type":"Services"
        }
    ],
    "sg:phone":"+1 818 764 8428",
    "sg:postcode":"91605",
    "sg:province":"CA",
    "sg:tags":[
        "residential"
    ],
    "wof:name":"S/L Does It All",
    "wof:placetype":"venue"
},
  "geometry": {"coordinates":[-118.394334,34.213905],"type":"Point"}
}