{
  "type": "Feature",
  "properties": {
    "iso:country":"US",
    "sg:address":"2024 Firestone Blvd",
    "sg:city":"Los Angeles",
    "sg:classifiers":[
        {
            "category":"Retail",
            "subcategory":"Laundry & Dry Cleaning",
            "type":"Services"
        }
    ],
    "sg:phone":"+1 323 589 3984",
    "sg:postcode":"90001",
    "sg:province":"CA",
    "wof:name":"Firestone Laundry",
    "wof:placetype":"venue"
},
  "geometry": {"coordinates":[-118.235942,33.96007],"type":"Point"}
}