{
  "type": "Feature",
  "properties": {
    "addr:full":"499 N El Camino Real Encinitas CA 92024",
    "addr:housenumber":"499",
    "addr:postcode":"92024",
    "addr:street":"N El Camino Real",
    "iso:country":"US",
    "sg:address":"499 N El Camino Real",
    "sg:city":"Encinitas",
    "sg:classifiers":[
        {
            "category":"Health Services",
            "subcategory":"Doctor",
            "type":"Services"
        }
    ],
    "sg:phone":"+1 760 942 1311",
    "sg:postcode":"92024",
    "sg:province":"CA",
    "sg:tags":[
        "dermatologist"
    ],
    "wof:name":"Dermatologist Medical Group of North County Inc",
    "wof:placetype":"venue"
},
  "geometry": {"coordinates":[-117.26300000000001,33.058601],"type":"Point"}
}