{
  "type": "Feature",
  "properties": {
    "iso:country":"US",
    "sg:address":"443 E Alisal St",
    "sg:city":"Salinas",
    "sg:classifiers":[
        {
            "category":"Professional",
            "type":"Services"
        }
    ],
    "sg:phone":"+1 831 424 4982",
    "sg:postcode":"93905",
    "sg:province":"CA",
    "wof:name":"Mariachi & Folklorico Dan",
    "wof:placetype":"venue"
},
  "geometry": {"coordinates":[-121.638557,36.674103],"type":"Point"}
}