{
  "type": "Feature",
  "properties": {
    "iso:country":"US",
    "sg:address":"520 Grant Ave In the small chaple",
    "sg:city":"San Lorenzo",
    "sg:classifiers":[
        {
            "category":"Place Of Worship",
            "subcategory":"Church",
            "type":"Public Place"
        }
    ],
    "sg:phone":"+1 510 828 9084",
    "sg:postcode":"94580",
    "sg:province":"CA",
    "sg:website":"www.thelightofthespirit.org",
    "wof:name":"Resurrection Life Worship Center",
    "wof:placetype":"venue"
},
  "geometry": {"coordinates":[-122.12948299999999,37.682335],"type":"Point"}
}