{
  "type": "Feature",
  "properties": {
    "iso:country":"US",
    "sg:address":"1234 Studio Ln",
    "sg:city":"Oakland",
    "sg:classifiers":[
        {
            "category":"Arts & Performance",
            "subcategory":"Art Gallery",
            "type":"Entertainment"
        },
        {
            "category":"Communications",
            "subcategory":"Newspaper",
            "type":"Services"
        },
        {
            "category":"Professional",
            "subcategory":"Art Services",
            "type":"Services"
        }
    ],
    "sg:phone":"+1 206 851 8005",
    "sg:postcode":"94610",
    "sg:province":"CA",
    "sg:tags":[
        "print",
        "photographer",
        "medium"
    ],
    "wof:name":"Lauren Crew Photography",
    "wof:placetype":"venue"
},
  "geometry": {"coordinates":[-122.240515,37.823608],"type":"Point"}
}