{
  "type": "Feature",
  "properties": {
    "addr:full":"889 Howe Rd Martinez CA 94553",
    "addr:housenumber":"889",
    "addr:postcode":"94553",
    "addr:street":"Howe Rd",
    "iso:country":"US",
    "sg:address":"889 Howe Rd",
    "sg:city":"Martinez",
    "sg:classifiers":[
        {
            "category":"Retail",
            "subcategory":"Auto Repair",
            "type":"Services"
        }
    ],
    "sg:phone":"+1 925 370 6288",
    "sg:postcode":"94553",
    "sg:province":"CA",
    "sg:tags":[
        "road"
    ],
    "wof:name":"R & D Automotive",
    "wof:placetype":"venue"
},
  "geometry": {"coordinates":[-122.11090299999999,38.003555],"type":"Point"}
}