{
  "type": "Feature",
  "properties": {
    "addr:full":"3400 W Ball Rd Ste 102 Anaheim CA 92804",
    "addr:housenumber":"3400",
    "addr:postcode":"92804",
    "addr:street":"W Ball Rd Ste 102",
    "iso:country":"US",
    "sg:address":"3400 W Ball Rd Ste 102",
    "sg:city":"Anaheim",
    "sg:classifiers":[
        {
            "category":"Health Services",
            "subcategory":"Doctor",
            "type":"Services"
        }
    ],
    "sg:phone":"+1 714 816 0088",
    "sg:postcode":"92804",
    "sg:province":"CA",
    "wof:name":"Meris Maria C MD",
    "wof:placetype":"venue"
},
  "geometry": {"coordinates":[-118.008306,33.816843],"type":"Point"}
}