{
  "type": "Feature",
  "properties": {
    "addr:full":"1388 Searcy Dr San Jose CA 95118",
    "addr:housenumber":"1388",
    "addr:postcode":"95118",
    "addr:street":"Searcy Dr",
    "iso:country":"US",
    "sg:address":"1388 Searcy Dr",
    "sg:city":"San Jose",
    "sg:classifiers":[
        {
            "category":"Building & Trades",
            "subcategory":"Construction",
            "type":"Services"
        }
    ],
    "sg:phone":"+1 408 264 3710",
    "sg:postcode":"95118",
    "sg:province":"CA",
    "sg:tags":[
        "house"
    ],
    "wof:name":"Pinnicale Home Builders",
    "wof:placetype":"venue"
},
  "geometry": {"coordinates":[-121.88870300000001,37.26133],"type":"Point"}
}