{
  "type": "Feature",
  "properties": {
    "iso:country":"US",
    "sg:address":"601 W Shaw Ave",
    "sg:city":"Clovis",
    "sg:classifiers":[
        {
            "category":"Personal",
            "subcategory":"Beauty Salon",
            "type":"Services"
        }
    ],
    "sg:phone":"+1 559 298 4247",
    "sg:postcode":"93612",
    "sg:province":"CA",
    "wof:name":"Progressive Hair",
    "wof:placetype":"venue"
},
  "geometry": {"coordinates":[-119.72270899999999,36.808485],"type":"Point"}
}