{
  "type": "Feature",
  "properties": {
    "addr:full":"18991 Oriente Dr Yorba Linda CA 92886",
    "addr:housenumber":"18991",
    "addr:postcode":"92886",
    "addr:street":"Oriente Dr",
    "iso:country":"US",
    "sg:address":"18991 Oriente Dr",
    "sg:city":"Yorba Linda",
    "sg:classifiers":[
        {
            "category":"Building & Trades",
            "subcategory":"Construction",
            "type":"Services"
        }
    ],
    "sg:phone":"+1 714 779 2110",
    "sg:postcode":"92886",
    "sg:province":"CA",
    "sg:tags":[
        "concrete",
        "contractor"
    ],
    "wof:name":"Taylor Wm Construction",
    "wof:placetype":"venue"
},
  "geometry": {"coordinates":[-117.804213,33.894135],"type":"Point"}
}