{
  "type": "Feature",
  "properties": {
    "iso:country":"US",
    "sg:address":"122 E Tehachapi Blvd",
    "sg:city":"Tehachapi",
    "sg:classifiers":[
        {
            "category":"Insurance",
            "subcategory":"Insurance Agent",
            "type":"Services"
        }
    ],
    "sg:phone":"+1 619 523 1451",
    "sg:postcode":"93561",
    "sg:province":"CA",
    "sg:tags":[
        "adjuster"
    ],
    "wof:name":"Klure & Assoc",
    "wof:placetype":"venue"
},
  "geometry": {"coordinates":[-118.44723999999999,35.131977],"type":"Point"}
}