{
  "type": "Feature",
  "properties": {
    "iso:country":"US",
    "sg:address":"14547 Victory Blvd",
    "sg:city":"Van Nuys",
    "sg:classifiers":[
        {
            "category":"Health Services",
            "subcategory":"Chiropractor",
            "type":"Services"
        }
    ],
    "sg:phone":"+1 818 887 8854",
    "sg:postcode":"91411",
    "sg:province":"CA",
    "wof:name":"Akhavan Chiropractic Therapy",
    "wof:placetype":"venue"
},
  "geometry": {"coordinates":[-118.45005,34.186735],"type":"Point"}
}