{
  "type": "Feature",
  "properties": {
    "iso:country":"US",
    "sg:address":"18566 State Rte 108",
    "sg:city":"Jamestown",
    "sg:classifiers":[
        {
            "category":"Retail",
            "subcategory":"Repair Shop",
            "type":"Services"
        }
    ],
    "sg:phone":"+1 209 532 6638",
    "sg:postcode":"95327",
    "sg:province":"CA",
    "sg:tags":[
        "equipment",
        "gas"
    ],
    "wof:name":"Kamps Propane",
    "wof:placetype":"venue"
},
  "geometry": {"coordinates":[-120.411902,37.961673],"type":"Point"}
}