{
  "type": "Feature",
  "properties": {
    "iso:country":"US",
    "sg:address":"148 Griffin St",
    "sg:city":"Salinas",
    "sg:classifiers":[
        {
            "category":"Building & Trades",
            "subcategory":"Construction",
            "type":"Services"
        }
    ],
    "sg:phone":"+1 831 753 7761",
    "sg:postcode":"93901",
    "sg:province":"CA",
    "sg:tags":[
        "contractor"
    ],
    "wof:name":"Pro Custom Window Tinting",
    "wof:placetype":"venue"
},
  "geometry": {"coordinates":[-121.64293,36.676277],"type":"Point"}
}