{
  "type": "Feature",
  "properties": {
    "addr:full":"7300 Chevron Way Dixon CA 95620",
    "addr:housenumber":"7300",
    "addr:postcode":"95620",
    "addr:street":"Chevron Way",
    "iso:country":"US",
    "sg:address":"7300 Chevron Way",
    "sg:city":"Dixon",
    "sg:classifiers":[
        {
            "category":"Professional",
            "subcategory":"Research",
            "type":"Services"
        },
        {
            "category":"Utilities",
            "subcategory":"Refuse",
            "type":"Services"
        }
    ],
    "sg:phone":"+1 707 693 6000",
    "sg:postcode":"95620",
    "sg:province":"CA",
    "sg:tags":[
        "environmental",
        "ecological",
        "system"
    ],
    "wof:name":"Asbury Environmental Services",
    "wof:placetype":"venue"
},
  "geometry": {"coordinates":[-121.88996400000001,38.415977],"type":"Point"}
}