{
  "type": "Feature",
  "properties": {
    "iso:country":"US",
    "sg:address":"400 Ave Presidio",
    "sg:city":"San Clemente",
    "sg:classifiers":[
        {
            "category":"Real Estate",
            "subcategory":"Real Estate Agent",
            "type":"Services"
        }
    ],
    "sg:phone":"+1 949 492 4620",
    "sg:postcode":"92672",
    "sg:province":"CA",
    "wof:name":"William Jensen & Associates",
    "wof:placetype":"venue"
},
  "geometry": {"coordinates":[-117.60523999999999,33.432139],"type":"Point"}
}