{
  "type": "Feature",
  "properties": {
    "addr:full":"301 S St Andrews Pl Los Angeles CA 90020",
    "addr:housenumber":"301",
    "addr:postcode":"90020",
    "addr:street":"S St;Pl",
    "iso:country":"US",
    "sg:address":"301 S St Andrews Pl",
    "sg:city":"Los Angeles",
    "sg:classifiers":[
        {
            "category":"Utilities",
            "subcategory":"Telephone",
            "type":"Services"
        }
    ],
    "sg:phone":"+1 213 380 1117",
    "sg:postcode":"90020",
    "sg:province":"CA",
    "sg:tags":[
        "telecommunication"
    ],
    "wof:name":"Phone Expert",
    "wof:placetype":"venue"
},
  "geometry": {"coordinates":[-118.311593,34.067142],"type":"Point"}
}