{
  "type": "Feature",
  "properties": {
    "addr:full":"7901 Stoneridge Drive #555 Pleasanton CA 94588",
    "addr:housenumber":"7901",
    "addr:postcode":"94588",
    "addr:street":"Stoneridge Drive # 555",
    "iso:country":"US",
    "sg:address":"7901 Stoneridge Drive #555",
    "sg:city":"Pleasanton",
    "sg:classifiers":[
        {
            "category":"Professional",
            "subcategory":"Computer Services",
            "type":"Services"
        }
    ],
    "sg:phone":"+1 925 730 0073",
    "sg:postcode":"94588",
    "sg:province":"CA",
    "sg:tags":[
        "machine-learning",
        "evaluations",
        "search-engine",
        "work-at-home",
        "evaluation",
        "information-retrieval"
    ],
    "sg:website":"http://www.leapforceathome.com",
    "wof:name":"Leapforce",
    "wof:placetype":"venue"
},
  "geometry": {"coordinates":[-121.929892,37.688933],"type":"Point"}
}