{
  "type": "Feature",
  "properties": {
    "iso:country":"US",
    "sg:address":"15980 Bernardo Center Dr",
    "sg:city":"San Diego",
    "sg:classifiers":[
        {
            "category":"Wholesale",
            "subcategory":"Medical Equipment & Supplies",
            "type":"Manufacturing & Wholesale Goods"
        },
        {
            "category":"Manufacturing",
            "subcategory":"Tools & Machinery",
            "type":"Manufacturing & Wholesale Goods"
        }
    ],
    "sg:phone":"+1 858 487 8684",
    "sg:postcode":"92127",
    "sg:province":"CA",
    "sg:tags":[
        "physician",
        "surgeon",
        "ophthalmic"
    ],
    "sg:website":"www.americancontactlens.com",
    "wof:name":"American Contact Lens Inc",
    "wof:placetype":"venue"
},
  "geometry": {"coordinates":[-117.089753,33.006912],"type":"Point"}
}