{
  "type": "Feature",
  "properties": {
    "addr:full":"2751 Monument Blvd Concord CA 94520",
    "addr:housenumber":"2751",
    "addr:postcode":"94520",
    "addr:street":"Monument Blvd",
    "iso:country":"US",
    "sg:address":"2751 Monument Blvd",
    "sg:city":"Concord",
    "sg:classifiers":[
        {
            "category":"Freight",
            "type":"Transportation"
        }
    ],
    "sg:phone":"+1 925 686 6580",
    "sg:postcode":"94520",
    "sg:province":"CA",
    "sg:tags":[
        "operator",
        "local",
        "trucking"
    ],
    "wof:name":"T&M Trucking Co",
    "wof:placetype":"venue"
},
  "geometry": {"coordinates":[-122.031713,37.964083],"type":"Point"}
}