{
  "type": "Feature",
  "properties": {
    "iso:country":"US",
    "sg:address":"5334 Sterling Center Dr",
    "sg:city":"Westlake Village",
    "sg:classifiers":[
        {
            "category":"Manufacturing",
            "subcategory":"Printing",
            "type":"Manufacturing & Wholesale Goods"
        }
    ],
    "sg:phone":"+1 818 706 8330",
    "sg:postcode":"91361",
    "sg:province":"CA",
    "sg:tags":[
        "lithographic",
        "commercial"
    ],
    "wof:name":"T/O Printing",
    "wof:placetype":"venue"
},
  "geometry": {"coordinates":[-118.804005,34.14645],"type":"Point"}
}