{
  "type": "Feature",
  "properties": {
    "addr:full":"2029 Century Park E Suite 3400 Los Angeles CA 90067",
    "addr:housenumber":"2029",
    "addr:postcode":"90067",
    "addr:street":"Century Park E Suite 3400",
    "iso:country":"US",
    "sg:address":"2029 Century Park E Suite 3400",
    "sg:city":"Los Angeles",
    "sg:classifiers":[
        {
            "category":"Professional",
            "subcategory":"Lawyer & Legal Services",
            "type":"Services"
        }
    ],
    "sg:phone":"+1 310 552 3400",
    "sg:postcode":"90067",
    "sg:province":"CA",
    "wof:name":"Heuer John F",
    "wof:placetype":"venue"
},
  "geometry": {"coordinates":[-118.41292799999999,34.059473],"type":"Point"}
}