{
  "type": "Feature",
  "properties": {
    "addr:full":"2374 Montgomery St Oroville CA 95965",
    "addr:housenumber":"2374",
    "addr:postcode":"95965",
    "addr:street":"Montgomery St",
    "iso:country":"US",
    "sg:address":"2374 Montgomery St",
    "sg:city":"Oroville",
    "sg:classifiers":[
        {
            "category":"Recreation",
            "type":"Entertainment"
        }
    ],
    "sg:phone":"+1 530 533 9970",
    "sg:postcode":"95965",
    "sg:province":"CA",
    "sg:tags":[
        "hall",
        "auditorium"
    ],
    "wof:name":"Memorial Hall",
    "wof:placetype":"venue"
},
  "geometry": {"coordinates":[-121.55183100000001,39.515347],"type":"Point"}
}