{
  "type": "Feature",
  "properties": {
    "iso:country":"US",
    "sg:address":"1911 N River Rd",
    "sg:city":"Paso Robles",
    "sg:classifiers":[
        {
            "category":"Building & Trades",
            "subcategory":"Equipment Rental",
            "type":"Services"
        }
    ],
    "sg:phone":"+1 805 239 2007",
    "sg:postcode":"93446",
    "sg:province":"CA",
    "sg:tags":[
        "toilet"
    ],
    "wof:name":"American Sanitation",
    "wof:placetype":"venue"
},
  "geometry": {"coordinates":[-120.68207200000001,35.634256],"type":"Point"}
}