{
  "type": "Feature",
  "properties": {
    "iso:country":"US",
    "sg:address":"152 El Nido Ave",
    "sg:city":"Monrovia",
    "sg:classifiers":[
        {
            "category":"Building & Trades",
            "subcategory":"Plumbing",
            "type":"Services"
        }
    ],
    "sg:phone":"+1 909 623 0033",
    "sg:postcode":"91016",
    "sg:province":"CA",
    "wof:name":"USA Plumbing Service Inc",
    "wof:placetype":"venue"
},
  "geometry": {"coordinates":[-118.349722,34.152898],"type":"Point"}
}