{
  "type": "Feature",
  "properties": {
    "addr:full":"721 12th St Paso Robles CA 93446",
    "addr:housenumber":"721",
    "addr:postcode":"93446",
    "addr:street":"12Th St",
    "iso:country":"US",
    "sg:address":"721 12th St",
    "sg:city":"Paso Robles",
    "sg:classifiers":[
        {
            "category":"Shopping",
            "subcategory":"Books",
            "type":"Retail Goods"
        }
    ],
    "sg:phone":"+1 805 237 2464",
    "sg:postcode":"93446",
    "sg:province":"CA",
    "sg:tags":[
        "dealer"
    ],
    "wof:name":"Chelsea Bookshop & Cafe",
    "wof:placetype":"venue"
},
  "geometry": {"coordinates":[-120.68906800000001,35.626889],"type":"Point"}
}