{
  "type": "Feature",
  "properties": {
    "addr:full":"17800 Sierra Hwy Canyon Cntry CA 91351",
    "addr:housenumber":"17800",
    "addr:postcode":"91351",
    "addr:street":"Sierra Hwy Canyon Cntry",
    "iso:country":"US",
    "sg:address":"17800 Sierra Hwy",
    "sg:city":"Canyon Cntry",
    "sg:classifiers":[
        {
            "category":"Food & Beverages",
            "subcategory":"Liquor & Beverages",
            "type":"Retail Goods"
        }
    ],
    "sg:phone":"+1 661 298 0680",
    "sg:postcode":"91351",
    "sg:province":"CA",
    "sg:tags":[
        "beer",
        "spirit",
        "wine"
    ],
    "sg:website":"www.sierraliquor.com",
    "wof:name":"Sierra Liquor",
    "wof:placetype":"venue"
},
  "geometry": {"coordinates":[-118.447998,34.426102],"type":"Point"}
}