{
  "type": "Feature",
  "properties": {
    "addr:full":"1846 Placentia Ave Costa Mesa CA 92627",
    "addr:housenumber":"1846",
    "addr:postcode":"92627",
    "addr:street":"Placentia Ave",
    "iso:country":"US",
    "sg:address":"1846 Placentia Ave",
    "sg:city":"Costa Mesa",
    "sg:classifiers":[
        {
            "category":"Real Estate",
            "subcategory":"Real Estate Operator",
            "type":"Services"
        }
    ],
    "sg:phone":"+1 949 574 5060",
    "sg:postcode":"92627",
    "sg:province":"CA",
    "sg:tags":[
        "apartment"
    ],
    "wof:name":"Summer Palms",
    "wof:placetype":"venue"
},
  "geometry": {"coordinates":[-117.93188499999999,33.641714],"type":"Point"}
}