{
  "type": "Feature",
  "properties": {
    "iso:country":"US",
    "sg:address":"19725 Stevens Creek Blvd",
    "sg:city":"Cupertino",
    "sg:classifiers":[
        {
            "category":"Wholesale",
            "subcategory":"Electrical",
            "type":"Manufacturing & Wholesale Goods"
        }
    ],
    "sg:phone":"+1 408 252 9455",
    "sg:postcode":"95014",
    "sg:province":"CA",
    "sg:tags":[
        "alarm",
        "burglar",
        "system"
    ],
    "wof:name":"Alternative Alarm Systems",
    "wof:placetype":"venue"
},
  "geometry": {"coordinates":[-122.018526,37.322935],"type":"Point"}
}