{
  "type": "Feature",
  "properties": {
    "iso:country":"US",
    "sg:address":"635 Baker St",
    "sg:city":"Costa Mesa",
    "sg:classifiers":[
        {
            "category":"Shopping",
            "subcategory":"Gifts & Souvenirs",
            "type":"Retail Goods"
        }
    ],
    "sg:phone":"+1 714 241 1831",
    "sg:postcode":"92626",
    "sg:province":"CA",
    "wof:name":"Sky Blue Discounts",
    "wof:placetype":"venue"
},
  "geometry": {"coordinates":[-117.880803,33.680014],"type":"Point"}
}