{
  "type": "Feature",
  "properties": {
    "addr:full":"1204 Burlingame Avenue Burlingame CA 94010",
    "addr:housenumber":"1204",
    "addr:postcode":"94010",
    "addr:street":"Burlingame Avenue",
    "iso:country":"US",
    "sg:address":"1204 Burlingame Avenue",
    "sg:city":"Burlingame",
    "sg:classifiers":[
        {
            "category":"Professional",
            "subcategory":"Lawyer & Legal Services",
            "type":"Services"
        }
    ],
    "sg:phone":"+1 650 340 0215",
    "sg:postcode":"94010",
    "sg:province":"CA",
    "wof:name":"Pisano Robert Atty",
    "wof:placetype":"venue"
},
  "geometry": {"coordinates":[-122.346205,37.579208],"type":"Point"}
}