{
  "type": "Feature",
  "properties": {
    "addr:full":"2416 Broadway St Eureka CA 95501",
    "addr:housenumber":"2416",
    "addr:postcode":"95501",
    "addr:street":"Broadway St",
    "iso:country":"US",
    "sg:address":"2416 Broadway St",
    "sg:city":"Eureka",
    "sg:classifiers":[
        {
            "category":"Utilities",
            "subcategory":"Mobile Phone",
            "type":"Services"
        }
    ],
    "sg:phone":"+1 707 445 9665",
    "sg:postcode":"95501",
    "sg:province":"CA",
    "sg:tags":[
        "paging"
    ],
    "wof:name":"Power Page",
    "wof:placetype":"venue"
},
  "geometry": {"coordinates":[-124.182001,40.785332],"type":"Point"}
}