{
  "type": "Feature",
  "properties": {
    "iso:country":"US",
    "sg:address":"145 E L St",
    "sg:city":"Wilmington",
    "sg:classifiers":[
        {
            "category":"Restaurant",
            "type":"Food & Drink"
        }
    ],
    "sg:phone":"+1 310 830 6392",
    "sg:postcode":"90744",
    "sg:province":"CA",
    "sg:tags":[
        "chinese"
    ],
    "wof:name":"Louie's Chinese Restaurant",
    "wof:placetype":"venue"
},
  "geometry": {"coordinates":[-118.26300000000001,33.7868],"type":"Point"}
}