{
  "type": "Feature",
  "properties": {
    "iso:country":"US",
    "sg:address":"16737 Parkside Ave",
    "sg:city":"Cerritos",
    "sg:classifiers":[
        {
            "category":"Building & Trades",
            "subcategory":"Construction",
            "type":"Services"
        }
    ],
    "sg:phone":"+1 562 483 5244",
    "sg:postcode":"90703",
    "sg:province":"CA",
    "sg:tags":[
        "concrete",
        "cutting",
        "breaking",
        "sawing"
    ],
    "wof:name":"Mulder Concrete",
    "wof:placetype":"venue"
},
  "geometry": {"coordinates":[-118.07430600000001,33.8797],"type":"Point"}
}