{
  "type": "Feature",
  "properties": {
    "iso:country":"US",
    "sg:address":"1820 E Rosecrans Ave",
    "sg:city":"Compton",
    "sg:classifiers":[
        {
            "category":"Home & Garden",
            "subcategory":"Furniture",
            "type":"Retail Goods"
        }
    ],
    "sg:phone":"+1 310 537 3953",
    "sg:postcode":"90221",
    "sg:province":"CA",
    "sg:tags":[
        "mattress"
    ],
    "wof:name":"AC Mattress",
    "wof:placetype":"venue"
},
  "geometry": {"coordinates":[-118.20484399999999,33.903416],"type":"Point"}
}