{
  "type": "Feature",
  "properties": {
    "iso:country":"US",
    "sg:address":"20170 Sierra Soto Rd",
    "sg:city":"Murrieta",
    "sg:classifiers":[
        {
            "category":"Farming",
            "subcategory":"Vineyard",
            "type":"Manufacturing & Wholesale Goods"
        }
    ],
    "sg:phone":"+1 951 304 0205",
    "sg:postcode":"92562",
    "sg:province":"CA",
    "sg:tags":[
        "grape"
    ],
    "wof:name":"Plateau Vineyards",
    "wof:placetype":"venue"
},
  "geometry": {"coordinates":[-117.304777,33.531699],"type":"Point"}
}