{
  "type": "Feature",
  "properties": {
    "iso:country":"US",
    "sg:address":"1026 S Robertson Blvd",
    "sg:city":"Los Angeles",
    "sg:classifiers":[
        {
            "category":"Organizations",
            "subcategory":"Religious Organization",
            "type":"Services"
        }
    ],
    "sg:phone":"+1 310 659 1363",
    "sg:postcode":"90035",
    "sg:province":"CA",
    "sg:tags":[
        "church"
    ],
    "wof:name":"Torat Hayim",
    "wof:placetype":"venue"
},
  "geometry": {"coordinates":[-118.38358,34.057699],"type":"Point"}
}