{
  "type": "Feature",
  "properties": {
    "iso:country":"US",
    "sg:address":"1065 4th Ave",
    "sg:city":"San Diego",
    "sg:classifiers":[
        {
            "category":"Bars & Pubs",
            "type":"Food & Drink"
        },
        {
            "category":"Restaurant",
            "type":"Food & Drink"
        }
    ],
    "sg:phone":"+1 619 231 4447",
    "sg:postcode":"92101",
    "sg:province":"CA",
    "sg:tags":[
        "new",
        "american"
    ],
    "sg:website":"www.thelocalsandiego.com",
    "wof:name":"The Local",
    "wof:placetype":"venue"
},
  "geometry": {"coordinates":[-117.16100299999999,32.716599],"type":"Point"}
}