{
  "type": "Feature",
  "properties": {
    "iso:country":"US",
    "sg:address":"421 W Redlands Blvd",
    "sg:city":"Redlands",
    "sg:classifiers":[
        {
            "category":"Real Estate",
            "subcategory":"Real Estate Agent",
            "type":"Services"
        }
    ],
    "sg:phone":"+1 909 798 2273",
    "sg:postcode":"92373",
    "sg:province":"CA",
    "wof:name":"Duane De Wees Better Homes",
    "wof:placetype":"venue"
},
  "geometry": {"coordinates":[-117.195742,34.059573],"type":"Point"}
}