{
  "type": "Feature",
  "properties": {
    "addr:full":"2236 S Mountain Ave Ontario CA 91762",
    "addr:housenumber":"2236",
    "addr:postcode":"91762",
    "addr:street":"S Mountain Ave",
    "iso:country":"US",
    "sg:address":"2236 S Mountain Ave",
    "sg:city":"Ontario",
    "sg:classifiers":[
        {
            "category":"Restaurant",
            "type":"Food & Drink"
        }
    ],
    "sg:phone":"+1 909 986 2222",
    "sg:postcode":"91762",
    "sg:province":"CA",
    "sg:tags":[
        "pizza"
    ],
    "sg:website":"www.daliaspizza.com",
    "wof:name":"Dalia's Pizza Market",
    "wof:placetype":"venue"
},
  "geometry": {"coordinates":[-117.66972,34.03461],"type":"Point"}
}