{
  "type": "Feature",
  "properties": {
    "iso:country":"US",
    "sg:address":"13564 Imperial Hwy",
    "sg:city":"Santa Fe Springs",
    "sg:classifiers":[
        {
            "category":"Home & Garden",
            "subcategory":"Furniture",
            "type":"Retail Goods"
        }
    ],
    "sg:phone":"+1 562 229 9121",
    "sg:postcode":"90670",
    "sg:province":"CA",
    "sg:tags":[
        "store"
    ],
    "wof:name":"BIF USA INC",
    "wof:placetype":"venue"
},
  "geometry": {"coordinates":[-118.264227,33.916822],"type":"Point"}
}