{
  "type": "Feature",
  "properties": {
    "addr:full":"200 Hillmont Ave Ventura CA 93003",
    "addr:housenumber":"200",
    "addr:postcode":"93003",
    "addr:street":"Hillmont Ave",
    "iso:country":"US",
    "sg:address":"200 Hillmont Ave",
    "sg:city":"Ventura",
    "sg:classifiers":[
        {
            "category":"Health Services",
            "subcategory":"Doctor",
            "type":"Services"
        }
    ],
    "sg:phone":"+1 805 652 6000",
    "sg:postcode":"93003",
    "sg:province":"CA",
    "sg:tags":[
        "physician",
        "surgeon"
    ],
    "wof:name":"Ventura County Medical Ctr",
    "wof:placetype":"venue"
},
  "geometry": {"coordinates":[-119.254411,34.279794],"type":"Point"}
}