{
  "type": "Feature",
  "properties": {
    "addr:full":"2488 Townsgate Rd Westlake Village CA 91361",
    "addr:housenumber":"2488",
    "addr:postcode":"91361",
    "addr:street":"Townsgate Rd",
    "iso:country":"US",
    "sg:address":"2488 Townsgate Rd",
    "sg:city":"Westlake Village",
    "sg:classifiers":[
        {
            "category":"Real Estate",
            "subcategory":"Surveying",
            "type":"Services"
        }
    ],
    "sg:phone":"+1 805 497 0102",
    "sg:postcode":"91361",
    "sg:province":"CA",
    "sg:tags":[
        "surveyor"
    ],
    "sg:website":"www.peakinc.com",
    "wof:name":"Peak Surveys Inc",
    "wof:placetype":"venue"
},
  "geometry": {"coordinates":[-118.831495,34.159163],"type":"Point"}
}