{
  "type": "Feature",
  "properties": {
    "addr:full":"7418 N Blackstone Ave Fresno CA 93720",
    "addr:housenumber":"7418",
    "addr:postcode":"93720",
    "addr:street":"N Blackstone Ave",
    "iso:country":"US",
    "sg:address":"7418 N Blackstone Ave",
    "sg:city":"Fresno",
    "sg:classifiers":[
        {
            "category":"Shopping",
            "subcategory":"Clothing, Apparel, & Fashions",
            "type":"Retail Goods"
        }
    ],
    "sg:phone":"+1 559 440 1707",
    "sg:postcode":"93720",
    "sg:province":"CA",
    "wof:name":"Old Navy",
    "wof:placetype":"venue"
},
  "geometry": {"coordinates":[-119.790812,36.849191],"type":"Point"}
}