{
  "type": "Feature",
  "properties": {
    "addr:full":"1247 S Mission Rd Fallbrook CA 92028",
    "addr:housenumber":"1247",
    "addr:postcode":"92028",
    "addr:street":"S Mission Rd",
    "iso:country":"US",
    "sg:address":"1247 S Mission Rd",
    "sg:city":"Fallbrook",
    "sg:classifiers":[
        {
            "category":"Coffee & Tea",
            "type":"Food & Drink"
        }
    ],
    "sg:phone":"+1 760 731 1159",
    "sg:postcode":"92028",
    "sg:province":"CA",
    "wof:name":"Java Time",
    "wof:placetype":"venue"
},
  "geometry": {"coordinates":[-117.25099899999999,33.369701],"type":"Point"}
}