{
  "type": "Feature",
  "properties": {
    "iso:country":"US",
    "sg:address":"2 Belcourt Dr",
    "sg:city":"Newport Beach",
    "sg:classifiers":[
        {
            "category":"Professional",
            "type":"Services"
        }
    ],
    "sg:phone":"+1 949 760 6707",
    "sg:postcode":"92660",
    "sg:province":"CA",
    "wof:name":"Burlyn LLC",
    "wof:placetype":"venue"
},
  "geometry": {"coordinates":[-117.866488,33.629809],"type":"Point"}
}