{
  "type": "Feature",
  "properties": {
    "iso:country":"US",
    "sg:address":"34030 Ave J",
    "sg:city":"Yucaipa",
    "sg:classifiers":[
        {
            "category":"Organizations",
            "subcategory":"Religious Organization",
            "type":"Services"
        }
    ],
    "sg:phone":"+1 909 795 7830",
    "sg:postcode":"92399",
    "sg:province":"CA",
    "sg:tags":[
        "church"
    ],
    "wof:name":"Calimesa Community Church",
    "wof:placetype":"venue"
},
  "geometry": {"coordinates":[-117.061607,34.006676],"type":"Point"}
}