{
  "type": "Feature",
  "properties": {
    "addr:full":"34052 Doheny Park Rd Capistrano Beach CA 92624",
    "addr:postcode":"34052;92624",
    "addr:street":"Doheny Park Rd",
    "iso:country":"US",
    "sg:address":"34052 Doheny Park Rd",
    "sg:city":"Capistrano Beach",
    "sg:classifiers":[
        {
            "category":"Real Estate",
            "subcategory":"Real Estate Operator",
            "type":"Services"
        }
    ],
    "sg:phone":"+1 949 496 5522",
    "sg:postcode":"92624",
    "sg:province":"CA",
    "sg:tags":[
        "mobile",
        "home",
        "community"
    ],
    "wof:name":"Beachwood Park & Village Mbl",
    "wof:placetype":"venue"
},
  "geometry": {"coordinates":[-117.676439,33.467647],"type":"Point"}
}