{
  "type": "Feature",
  "properties": {
    "iso:country":"US",
    "sg:address":"14211 Euclid St Ste A",
    "sg:city":"Garden Grove",
    "sg:classifiers":[
        {
            "category":"Shopping",
            "subcategory":"Pharmacy",
            "type":"Retail Goods"
        }
    ],
    "sg:phone":"+1 714 530 3833",
    "sg:postcode":"92843",
    "sg:province":"CA",
    "sg:tags":[
        "drugstore"
    ],
    "wof:name":"Americare Plus Pharmacy Services Inc",
    "wof:placetype":"venue"
},
  "geometry": {"coordinates":[-117.93800400000001,33.7617],"type":"Point"}
}