{
  "type": "Feature",
  "properties": {
    "addr:full":"4350 Via Palma La Mesa CA 91941",
    "addr:housenumber":"4350",
    "addr:postcode":"91941",
    "addr:street":"Via Palma",
    "iso:country":"US",
    "sg:address":"4350 Via Palma",
    "sg:city":"La Mesa",
    "sg:classifiers":[
        {
            "category":"Professional",
            "type":"Services"
        }
    ],
    "sg:phone":"+1 619 463 0553",
    "sg:postcode":"91941",
    "sg:province":"CA",
    "sg:tags":[
        "establishment"
    ],
    "wof:name":"Transrate Logistics",
    "wof:placetype":"venue"
},
  "geometry": {"coordinates":[-116.953254,32.745958],"type":"Point"}
}