{
  "type": "Feature",
  "properties": {
    "iso:country":"US",
    "sg:address":"5724 W 3rd St",
    "sg:city":"Los Angeles",
    "sg:classifiers":[
        {
            "category":"Professional",
            "type":"Services"
        },
        {
            "category":"Building & Trades",
            "subcategory":"Construction",
            "type":"Services"
        }
    ],
    "sg:phone":"+1 323 525 1775",
    "sg:postcode":"90036",
    "sg:province":"CA",
    "sg:tags":[
        "contractor"
    ],
    "wof:name":"Mice Creative",
    "wof:placetype":"venue"
},
  "geometry": {"coordinates":[-118.344667,34.068816],"type":"Point"}
}