{
  "type": "Feature",
  "properties": {
    "iso:country":"US",
    "sg:address":"13040 Edgebrook Dr",
    "sg:city":"Corona",
    "sg:classifiers":[
        {
            "category":"Professional",
            "subcategory":"Art Services",
            "type":"Services"
        }
    ],
    "sg:phone":"+1 951 674 7844",
    "sg:postcode":"92883",
    "sg:province":"CA",
    "sg:tags":[
        "artist"
    ],
    "wof:name":"Webfoot Arts",
    "wof:placetype":"venue"
},
  "geometry": {"coordinates":[-117.432633,33.724441],"type":"Point"}
}