{
  "type": "Feature",
  "properties": {
    "iso:country":"US",
    "sg:address":"1515 Hilltop Dr",
    "sg:city":"Chula Vista",
    "sg:classifiers":[
        {
            "category":"Social Services",
            "type":"Services"
        }
    ],
    "sg:phone":"+1 619 498 0555",
    "sg:postcode":"91911",
    "sg:province":"CA",
    "sg:tags":[
        "shelter",
        "service/non-profit",
        "community",
        "homeless"
    ],
    "wof:name":"Casa Nuestra",
    "wof:placetype":"venue"
},
  "geometry": {"coordinates":[-117.05100299999999,32.599499],"type":"Point"}
}