{
  "type": "Feature",
  "properties": {
    "addr:full":"2223 4th St Eureka CA 95501",
    "addr:housenumber":"2223",
    "addr:postcode":"95501",
    "addr:street":"4Th St",
    "iso:country":"US",
    "sg:address":"2223 4th St",
    "sg:city":"Eureka",
    "sg:classifiers":[
        {
            "category":"Travel",
            "subcategory":"Hotels & Motels",
            "type":"Entertainment"
        }
    ],
    "sg:phone":"+1 707 442 3261",
    "sg:postcode":"95501",
    "sg:province":"CA",
    "wof:name":"Clarion Resort",
    "wof:placetype":"venue"
},
  "geometry": {"coordinates":[-124.148014,40.804746],"type":"Point"}
}