{
  "type": "Feature",
  "properties": {
    "iso:country":"US",
    "sg:address":"4743 Oliva Ave",
    "sg:city":"Lakewood",
    "sg:classifiers":[
        {
            "category":"Organizations",
            "subcategory":"Religious Organization",
            "type":"Services"
        }
    ],
    "sg:phone":"+1 562 420 1130",
    "sg:postcode":"90712",
    "sg:province":"CA",
    "sg:tags":[
        "church"
    ],
    "wof:name":"Kasaoka America Tenrikyo Flshp",
    "wof:placetype":"venue"
},
  "geometry": {"coordinates":[-118.14460099999999,33.844039],"type":"Point"}
}