{
  "type": "Feature",
  "properties": {
    "addr:full":"3620 Overland Ave Los Angeles CA 90034",
    "addr:housenumber":"3620",
    "addr:postcode":"90034",
    "addr:street":"Overland Ave",
    "iso:country":"US",
    "sg:address":"3620 Overland Ave",
    "sg:city":"Los Angeles",
    "sg:classifiers":[
        {
            "category":"Arts & Performance",
            "subcategory":"Arts Center",
            "type":"Entertainment"
        },
        {
            "category":"Education",
            "subcategory":"Special Training",
            "type":"Public Place"
        }
    ],
    "sg:phone":"+1 310 979 7625",
    "sg:postcode":"90034",
    "sg:province":"CA",
    "sg:tags":[
        "school",
        "performing",
        "specialty"
    ],
    "sg:website":"www.hollywoodrockacademy.com/",
    "wof:name":"Hollywood Rock Academy",
    "wof:placetype":"venue"
},
  "geometry": {"coordinates":[-118.409817,34.022934],"type":"Point"}
}