{
  "type": "Feature",
  "properties": {
    "addr:full":"4577 48th St San Diego CA 92115",
    "addr:housenumber":"4577",
    "addr:postcode":"92115",
    "addr:street":"48Th St",
    "iso:country":"US",
    "sg:address":"4577 48th St",
    "sg:city":"San Diego",
    "sg:classifiers":[
        {
            "category":"Real Estate",
            "subcategory":"Real Estate Agent",
            "type":"Services"
        }
    ],
    "sg:phone":"+1 619 733 4577",
    "sg:postcode":"92115",
    "sg:province":"CA",
    "wof:name":"Downtown Realty",
    "wof:placetype":"venue"
},
  "geometry": {"coordinates":[-117.090648,32.759862],"type":"Point"}
}