{
  "type": "Feature",
  "properties": {
    "iso:country":"US",
    "sg:address":"385 Homer Ave",
    "sg:city":"Palo Alto",
    "sg:classifiers":[
        {
            "category":"Utilities",
            "subcategory":"Mobile Phone",
            "type":"Services"
        }
    ],
    "sg:phone":"+1 650 321 4545",
    "sg:postcode":"94301",
    "sg:province":"CA",
    "sg:tags":[
        "telephone",
        "cellular"
    ],
    "wof:name":"Connective Capital",
    "wof:placetype":"venue"
},
  "geometry": {"coordinates":[-122.157707,37.443746],"type":"Point"}
}