{
  "type": "Feature",
  "properties": {
    "addr:full":"15883 Bernardo Center Dr San Diego CA 92128",
    "addr:housenumber":"15883",
    "addr:postcode":"92128",
    "addr:street":"Bernardo Center Dr",
    "iso:country":"US",
    "sg:address":"15883 Bernardo Center Dr",
    "sg:city":"San Diego",
    "sg:classifiers":[
        {
            "category":"Food & Beverages",
            "subcategory":"Groceries & Convenience Stores",
            "type":"Retail Goods"
        }
    ],
    "sg:phone":"+1 858 487 5396",
    "sg:postcode":"92128",
    "sg:province":"CA",
    "wof:name":"7-Eleven",
    "wof:placetype":"venue"
},
  "geometry": {"coordinates":[-117.09214900000001,33.005067],"type":"Point"}
}