{
  "type": "Feature",
  "properties": {
    "iso:country":"US",
    "sg:address":"8420 N Friant Rd",
    "sg:city":"Fresno",
    "sg:classifiers":[
        {
            "category":"Banks & Credit Unions",
            "subcategory":"Bank",
            "type":"Services"
        }
    ],
    "sg:phone":"+1 559 451 2260",
    "sg:postcode":"93720",
    "sg:province":"CA",
    "sg:website":"www.wellsfargo.com",
    "wof:name":"Wells Fargo Bank",
    "wof:placetype":"venue"
},
  "geometry": {"coordinates":[-119.785111,36.857537],"type":"Point"}
}