{
  "type": "Feature",
  "properties": {
    "addr:full":"4730 S Eastern Ave City Of Commerce CA 90040",
    "addr:housenumber":"4730",
    "addr:postcode":"90040",
    "addr:street":"S Eastern Ave",
    "iso:country":"US",
    "sg:address":"4730 S Eastern Ave",
    "sg:city":"City Of Commerce",
    "sg:classifiers":[
        {
            "category":"Health Services",
            "subcategory":"Health Practitioner",
            "type":"Services"
        }
    ],
    "sg:phone":"+1 323 887 2748",
    "sg:postcode":"90040",
    "sg:province":"CA",
    "sg:tags":[
        "therapist",
        "physical"
    ],
    "wof:name":"PTQD Inc",
    "wof:placetype":"venue"
},
  "geometry": {"coordinates":[-118.16125599999999,33.990722],"type":"Point"}
}