{
  "type": "Feature",
  "properties": {
    "addr:full":"1435 N Highland Avenue Los Angeles CA 90028",
    "addr:housenumber":"1435",
    "addr:postcode":"90028",
    "addr:street":"N Highland Avenue",
    "iso:country":"US",
    "sg:address":"1435 N Highland Avenue",
    "sg:city":"Los Angeles",
    "sg:classifiers":[
        {
            "category":"Restaurant",
            "type":"Food & Drink"
        }
    ],
    "sg:phone":"+1 323 467 9868",
    "sg:postcode":"90028",
    "sg:province":"CA",
    "wof:name":"Bangkok Gourmet",
    "wof:placetype":"venue"
},
  "geometry": {"coordinates":[-118.33878300000001,34.097233],"type":"Point"}
}