{
  "type": "Feature",
  "properties": {
    "addr:full":"1330 Lincoln Ave Calistoga CA 94515",
    "addr:housenumber":"1330",
    "addr:postcode":"94515",
    "addr:street":"Lincoln Ave",
    "iso:country":"US",
    "sg:address":"1330 Lincoln Ave",
    "sg:city":"Calistoga",
    "sg:classifiers":[
        {
            "category":"Shopping",
            "subcategory":"Books",
            "type":"Retail Goods"
        }
    ],
    "sg:phone":"+1 707 942 1616",
    "sg:postcode":"94515",
    "sg:province":"CA",
    "sg:tags":[
        "mags",
        "video",
        "books",
        "music"
    ],
    "wof:name":"Copperfield's Books & Music",
    "wof:placetype":"venue"
},
  "geometry": {"coordinates":[-122.579002,38.577599],"type":"Point"}
}