{
  "type": "Feature",
  "properties": {
    "iso:country":"US",
    "sg:address":"837 S Dora St",
    "sg:city":"Ukiah",
    "sg:classifiers":[
        {
            "category":"Health Services",
            "subcategory":"Health Practitioner",
            "type":"Services"
        }
    ],
    "sg:phone":"+1 707 463 1293",
    "sg:postcode":"95482",
    "sg:province":"CA",
    "sg:tags":[
        "psychologist"
    ],
    "wof:name":"Susan Vega",
    "wof:placetype":"venue"
},
  "geometry": {"coordinates":[-123.21032700000001,39.141206],"type":"Point"}
}