{
  "type": "Feature",
  "properties": {
    "addr:full":"702 N Thompson Ave Nipomo CA 93444",
    "addr:housenumber":"702",
    "addr:postcode":"93444",
    "addr:street":"N Thompson Ave",
    "iso:country":"US",
    "sg:address":"702 N Thompson Ave",
    "sg:city":"Nipomo",
    "sg:classifiers":[
        {
            "category":"Transit Center",
            "subcategory":"Freight",
            "type":"Transportation"
        },
        {
            "category":"Freight",
            "type":"Transportation"
        }
    ],
    "sg:phone":"+1 805 473 1237",
    "sg:postcode":"93444",
    "sg:province":"CA",
    "sg:tags":[
        "trucking-motor",
        "trucking"
    ],
    "wof:name":"Hale Enterprises",
    "wof:placetype":"venue"
},
  "geometry": {"coordinates":[-120.489756,35.055521],"type":"Point"}
}