{
  "type": "Feature",
  "properties": {
    "addr:full":"50 Douglas Dr Martinez CA 94553",
    "addr:housenumber":"50",
    "addr:postcode":"94553",
    "addr:street":"Douglas Dr",
    "iso:country":"US",
    "sg:address":"50 Douglas Dr",
    "sg:city":"Martinez",
    "sg:classifiers":[
        {
            "category":"Professional",
            "subcategory":"Lawyer & Legal Services",
            "type":"Services"
        }
    ],
    "sg:phone":"+1 925 957 7300",
    "sg:postcode":"94553",
    "sg:province":"CA",
    "wof:name":"Child Support Svcs",
    "wof:placetype":"venue"
},
  "geometry": {"coordinates":[-122.124258,37.993396],"type":"Point"}
}