{
  "type": "Feature",
  "properties": {
    "iso:country":"US",
    "sg:address":"11535 Martens River Cir",
    "sg:city":"Fountain Valley",
    "sg:classifiers":[
        {
            "category":"Manufacturing",
            "subcategory":"Printing",
            "type":"Manufacturing & Wholesale Goods"
        }
    ],
    "sg:phone":"+1 714 668 1000",
    "sg:postcode":"92708",
    "sg:province":"CA",
    "sg:tags":[
        "offset"
    ],
    "wof:name":"Printing Island Corporation",
    "wof:placetype":"venue"
},
  "geometry": {"coordinates":[-117.92632399999999,33.710342],"type":"Point"}
}