{
  "type": "Feature",
  "properties": {
    "iso:country":"US",
    "sg:address":"15462 Cabrito Rd",
    "sg:city":"Van Nuys",
    "sg:classifiers":[
        {
            "category":"Wholesale",
            "subcategory":"Electrical",
            "type":"Manufacturing & Wholesale Goods"
        }
    ],
    "sg:phone":"+1 818 787 8516",
    "sg:postcode":"91406",
    "sg:province":"CA",
    "sg:tags":[
        "recording",
        "studio"
    ],
    "wof:name":"Sound Image",
    "wof:placetype":"venue"
},
  "geometry": {"coordinates":[-118.471795,34.217114],"type":"Point"}
}