{
  "type": "Feature",
  "properties": {
    "addr:full":"4285 Pacheco Blvd Martinez CA 94553",
    "addr:housenumber":"4285",
    "addr:postcode":"94553",
    "addr:street":"Pacheco Blvd",
    "iso:country":"US",
    "sg:address":"4285 Pacheco Blvd",
    "sg:city":"Martinez",
    "sg:classifiers":[
        {
            "category":"Home & Garden",
            "subcategory":"Building Materials",
            "type":"Retail Goods"
        },
        {
            "category":"Building & Trades",
            "subcategory":"Construction",
            "type":"Services"
        },
        {
            "category":"Manufacturing",
            "subcategory":"Building Materials",
            "type":"Manufacturing & Wholesale Goods"
        }
    ],
    "sg:phone":"+1 925 370 7663",
    "sg:postcode":"94553",
    "sg:province":"CA",
    "sg:tags":[
        "roofing",
        "gutter",
        "supply",
        "contractor",
        "downspouts",
        "equipment",
        "industrial",
        "contractors-commercial"
    ],
    "sg:website":"http://www.steelroofs.net",
    "wof:name":"Western Sierra Roofing",
    "wof:placetype":"venue"
},
  "geometry": {"coordinates":[-122.09288599999999,38.007272],"type":"Point"}
}