{
  "type": "Feature",
  "properties": {
    "iso:country":"US",
    "sg:address":"5625 E Balch Ave",
    "sg:city":"Fresno",
    "sg:classifiers":[
        {
            "category":"Retail",
            "subcategory":"Repair Shop",
            "type":"Services"
        }
    ],
    "sg:phone":"+1 559 978 9727",
    "sg:postcode":"93727",
    "sg:province":"CA",
    "sg:tags":[
        "equipment",
        "printing"
    ],
    "wof:name":"Valley Printer Svc",
    "wof:placetype":"venue"
},
  "geometry": {"coordinates":[-119.697948,36.738534],"type":"Point"}
}