{
  "type": "Feature",
  "properties": {
    "iso:country":"US",
    "sg:address":"339 Maple St",
    "sg:city":"Salinas",
    "sg:classifiers":[
        {
            "category":"Building & Trades",
            "subcategory":"Cleaning & Sanitation",
            "type":"Services"
        }
    ],
    "sg:phone":"+1 831 422 2919",
    "sg:postcode":"93901",
    "sg:province":"CA",
    "sg:tags":[
        "house"
    ],
    "wof:name":"Merry Maids",
    "wof:placetype":"venue"
},
  "geometry": {"coordinates":[-121.646355,36.667193],"type":"Point"}
}