{
  "type": "Feature",
  "properties": {
    "iso:country":"US",
    "sg:address":"126 Confederation Way",
    "sg:city":"Irvine",
    "sg:classifiers":[
        {
            "category":"Utilities",
            "subcategory":"Telephone",
            "type":"Services"
        }
    ],
    "sg:phone":"+1 714 665 0000",
    "sg:postcode":"92602",
    "sg:province":"CA",
    "sg:tags":[
        "communications"
    ],
    "wof:name":"Sandmdesign",
    "wof:placetype":"venue"
},
  "geometry": {"coordinates":[-117.773753,33.733686],"type":"Point"}
}