{
  "type": "Feature",
  "properties": {
    "addr:full":"622 W Mariposa St Altadena CA 91001",
    "addr:housenumber":"622",
    "addr:postcode":"91001",
    "addr:street":"W Mariposa St",
    "iso:country":"US",
    "sg:address":"622 W Mariposa St",
    "sg:city":"Altadena",
    "sg:classifiers":[
        {
            "category":"Professional",
            "subcategory":"Management & Consulting",
            "type":"Services"
        }
    ],
    "sg:phone":"+1 626 794 4154",
    "sg:postcode":"91001",
    "sg:province":"CA",
    "sg:tags":[
        "retail",
        "direct",
        "sales"
    ],
    "wof:name":"Emmas Independent Avon",
    "wof:placetype":"venue"
},
  "geometry": {"coordinates":[-118.161035,34.196406],"type":"Point"}
}