{
  "type": "Feature",
  "properties": {
    "iso:country":"US",
    "sg:address":"1473 3rd St",
    "sg:city":"La Verne",
    "sg:classifiers":[
        {
            "category":"Banks & Credit Unions",
            "subcategory":"Financial Services",
            "type":"Services"
        }
    ],
    "sg:phone":"+1 909 596 9491",
    "sg:postcode":"91750",
    "sg:province":"CA",
    "sg:tags":[
        "trust",
        "investment",
        "real estate"
    ],
    "wof:name":"Rodarte Inc",
    "wof:placetype":"venue"
},
  "geometry": {"coordinates":[-117.781184,34.103466],"type":"Point"}
}