{
  "type": "Feature",
  "properties": {
    "iso:country":"US",
    "sg:address":"11511 Folsom Blvd",
    "sg:city":"Rancho Cordova",
    "sg:classifiers":[
        {
            "category":"Autos & Motor Vehicles",
            "subcategory":"Auto Supplies",
            "type":"Retail Goods"
        },
        {
            "category":"Wholesale",
            "subcategory":"Auto Parts",
            "type":"Manufacturing & Wholesale Goods"
        }
    ],
    "sg:phone":"+1 916 858 2000",
    "sg:postcode":"95742",
    "sg:province":"CA",
    "sg:tags":[
        "house",
        "mail",
        "automobile"
    ],
    "wof:name":"Central 4 Wheel Drive Inc",
    "wof:placetype":"venue"
},
  "geometry": {"coordinates":[-121.253043,38.61391],"type":"Point"}
}