{
  "type": "Feature",
  "properties": {
    "addr:full":"2760 Mariposa Ave Chico CA 95973",
    "addr:housenumber":"2760",
    "addr:postcode":"95973",
    "addr:street":"Mariposa Ave",
    "iso:country":"US",
    "sg:address":"2760 Mariposa Ave",
    "sg:city":"Chico",
    "sg:classifiers":[
        {
            "category":"Farming",
            "subcategory":"Nursery",
            "type":"Manufacturing & Wholesale Goods"
        }
    ],
    "sg:phone":"+1 530 345 9036",
    "sg:postcode":"95973",
    "sg:province":"CA",
    "sg:tags":[
        "field"
    ],
    "wof:name":"Box Brothers Nursery Inc",
    "wof:placetype":"venue"
},
  "geometry": {"coordinates":[-121.824698,39.769168],"type":"Point"}
}