{
  "type": "Feature",
  "properties": {
    "addr:full":"27212 Ave 96 Terra Bella CA 93270",
    "addr:housenumber":"27212;96",
    "addr:postcode":"93270",
    "addr:street":"Ave",
    "iso:country":"US",
    "sg:address":"27212 Ave 96",
    "sg:city":"Terra Bella",
    "sg:classifiers":[
        {
            "category":"Farming",
            "subcategory":"Orchard",
            "type":"Manufacturing & Wholesale Goods"
        }
    ],
    "sg:phone":"+1 559 535 4075",
    "sg:postcode":"93270",
    "sg:province":"CA",
    "sg:tags":[
        "citrus",
        "grove",
        "fruit"
    ],
    "wof:name":"Griswold Ranch",
    "wof:placetype":"venue"
},
  "geometry": {"coordinates":[-118.96441799999999,35.964225],"type":"Point"}
}