{
  "type": "Feature",
  "properties": {
    "addr:full":"4319 Railroad Ave Pleasanton CA 94566",
    "addr:housenumber":"4319",
    "addr:postcode":"94566",
    "addr:street":"Railroad Ave",
    "iso:country":"US",
    "sg:address":"4319 Railroad Ave",
    "sg:city":"Pleasanton",
    "sg:classifiers":[
        {
            "category":"Real Estate",
            "subcategory":"Real Estate Operator",
            "type":"Services"
        }
    ],
    "sg:phone":"+1 925 461 4820",
    "sg:postcode":"94566",
    "sg:province":"CA",
    "sg:tags":[
        "apartment"
    ],
    "wof:name":"Breilh Properties",
    "wof:placetype":"venue"
},
  "geometry": {"coordinates":[-121.87388900000001,37.661262],"type":"Point"}
}