{
  "type": "Feature",
  "properties": {
    "iso:country":"US",
    "sg:address":"504 N 3rd St",
    "sg:city":"King City",
    "sg:classifiers":[
        {
            "category":"Organizations",
            "subcategory":"Religious Organization",
            "type":"Services"
        }
    ],
    "sg:phone":"+1 831 385 3377",
    "sg:postcode":"93930",
    "sg:province":"CA",
    "sg:tags":[
        "church"
    ],
    "wof:name":"Catholic Church Of St John",
    "wof:placetype":"venue"
},
  "geometry": {"coordinates":[-121.130002,36.217453],"type":"Point"}
}