{
  "type": "Feature",
  "properties": {
    "addr:full":"1137 Broadway Ave Seaside CA 93955",
    "addr:housenumber":"1137",
    "addr:postcode":"93955",
    "addr:street":"Broadway Ave",
    "iso:country":"US",
    "sg:address":"1137 Broadway Ave",
    "sg:city":"Seaside",
    "sg:classifiers":[
        {
            "category":"Personal",
            "subcategory":"Beauty Salon",
            "type":"Services"
        }
    ],
    "sg:phone":"+1 831 392 1970",
    "sg:postcode":"93955",
    "sg:province":"CA",
    "wof:name":"Lafreida At Hair Cmp",
    "wof:placetype":"venue"
},
  "geometry": {"coordinates":[-121.841846,36.609105],"type":"Point"}
}