{
  "type": "Feature",
  "properties": {
    "addr:full":"1788 Palm Avenue San Diego CA 92154",
    "addr:housenumber":"1788",
    "addr:postcode":"92154",
    "addr:street":"Palm Avenue",
    "iso:country":"US",
    "sg:address":"1788 Palm Avenue",
    "sg:city":"San Diego",
    "sg:classifiers":[
        {
            "category":"Travel",
            "subcategory":"Hotels & Motels",
            "type":"Entertainment"
        }
    ],
    "sg:phone":"+1 619 575 4421",
    "sg:postcode":"92154",
    "sg:province":"CA",
    "wof:name":"Super 8 Motel",
    "wof:placetype":"venue"
},
  "geometry": {"coordinates":[-117.095203,32.583802],"type":"Point"}
}