{
  "type": "Feature",
  "properties": {
    "iso:country":"US",
    "sg:address":"2390 el Camino Real",
    "sg:city":"Palo Alto",
    "sg:classifiers":[
        {
            "category":"Banks & Credit Unions",
            "subcategory":"Bank",
            "type":"Services"
        }
    ],
    "sg:phone":"+1 650 494 3397",
    "sg:postcode":"94306",
    "sg:province":"CA",
    "sg:tags":[
        "loan"
    ],
    "sg:website":"www.baywide.com",
    "wof:name":"Baywide Funding Corp",
    "wof:placetype":"venue"
},
  "geometry": {"coordinates":[-122.146765,37.425418],"type":"Point"}
}