{
  "type": "Feature",
  "properties": {
    "addr:full":"5208 Melrose Ave Los Angeles CA 90038",
    "addr:housenumber":"5208",
    "addr:postcode":"90038",
    "addr:street":"Melrose Ave",
    "iso:country":"US",
    "sg:address":"5208 Melrose Ave",
    "sg:city":"Los Angeles",
    "sg:classifiers":[
        {
            "category":"Recreation",
            "type":"Entertainment"
        }
    ],
    "sg:phone":"+1 323 464 3911",
    "sg:postcode":"90038",
    "sg:province":"CA",
    "sg:tags":[
        "club",
        "membership"
    ],
    "wof:name":"Comedy First",
    "wof:placetype":"venue"
},
  "geometry": {"coordinates":[-118.31436600000001,34.083429],"type":"Point"}
}