{
  "type": "Feature",
  "properties": {
    "addr:full":"24326 Muirlands Boulevard Lake Forest CA 92630",
    "addr:housenumber":"24326",
    "addr:postcode":"92630",
    "addr:street":"Muirlands Boulevard",
    "iso:country":"US",
    "sg:address":"24326 Muirlands Boulevard",
    "sg:city":"Lake Forest",
    "sg:classifiers":[
        {
            "category":"Personal",
            "subcategory":"Nail Salon",
            "type":"Services"
        }
    ],
    "sg:phone":"+1 949 830 2968",
    "sg:postcode":"92630",
    "sg:province":"CA",
    "wof:name":"Star Line Nails",
    "wof:placetype":"venue"
},
  "geometry": {"coordinates":[-117.70470299999999,33.628345],"type":"Point"}
}