{
  "type": "Feature",
  "properties": {
    "addr:full":"12940 Victory Blvd North Hollywood CA 91606",
    "addr:housenumber":"12940",
    "addr:postcode":"91606",
    "addr:street":"Victory Blvd",
    "iso:country":"US",
    "sg:address":"12940 Victory Blvd",
    "sg:city":"North Hollywood",
    "sg:classifiers":[
        {
            "category":"Restaurant",
            "type":"Food & Drink"
        }
    ],
    "sg:phone":"+1 818 985 8014",
    "sg:postcode":"91606",
    "sg:province":"CA",
    "sg:tags":[
        "mexican"
    ],
    "wof:name":"Que Rico Tacos",
    "wof:placetype":"venue"
},
  "geometry": {"coordinates":[-118.41507,34.186684],"type":"Point"}
}