{
  "type": "Feature",
  "properties": {
    "iso:country":"US",
    "sg:address":"675 Clover Valley Rd",
    "sg:city":"Upper Lake",
    "sg:classifiers":[
        {
            "category":"Education",
            "subcategory":"School",
            "type":"Public Place"
        }
    ],
    "sg:phone":"+1 707 275 2338",
    "sg:postcode":"95485",
    "sg:province":"CA",
    "wof:name":"Upper Lake Union High School",
    "wof:placetype":"venue"
},
  "geometry": {"coordinates":[-122.90261099999999,39.164633],"type":"Point"}
}