{
  "type": "Feature",
  "properties": {
    "addr:full":"4249 Hardwood St Fremont CA 94538",
    "addr:housenumber":"4249",
    "addr:postcode":"94538",
    "addr:street":"Hardwood St",
    "iso:country":"US",
    "sg:address":"4249 Hardwood St",
    "sg:city":"Fremont",
    "sg:classifiers":[
        {
            "category":"Food & Beverages",
            "subcategory":"Groceries & Convenience Stores",
            "type":"Retail Goods"
        },
        {
            "category":"Shopping",
            "subcategory":"Gifts & Souvenirs",
            "type":"Retail Goods"
        }
    ],
    "sg:phone":"+1 510 651 1840",
    "sg:postcode":"94538",
    "sg:province":"CA",
    "sg:tags":[
        "grocer",
        "e"
    ],
    "wof:name":"My Sari-Sari Store Com",
    "wof:placetype":"venue"
},
  "geometry": {"coordinates":[-121.960747,37.516617],"type":"Point"}
}