{
  "type": "Feature",
  "properties": {
    "addr:full":"27412 Antonio Pkwy Ste R-6 Mission Viejo CA 92675",
    "addr:housenumber":"27412",
    "addr:postcode":"92675",
    "addr:street":"Antonio Pkwy Ste R-6",
    "iso:country":"US",
    "sg:address":"27412 Antonio Pkwy Ste R-6",
    "sg:city":"Mission Viejo",
    "sg:classifiers":[
        {
            "category":"Wholesale",
            "subcategory":"Home Furnishings",
            "type":"Manufacturing & Wholesale Goods"
        }
    ],
    "sg:phone":"+1 949 597 2008",
    "sg:postcode":"92675",
    "sg:province":"CA",
    "sg:tags":[
        "blind",
        "shade"
    ],
    "wof:name":"Homaira's Drapery & Design",
    "wof:placetype":"venue"
},
  "geometry": {"coordinates":[-117.627568,33.56466],"type":"Point"}
}