{
  "type": "Feature",
  "properties": {
    "iso:country":"US",
    "sg:address":"4283 Murietta Ave",
    "sg:city":"Sherman Oaks",
    "sg:classifiers":[
        {
            "category":"Professional",
            "type":"Services"
        }
    ],
    "sg:phone":"+1 818 817 9100",
    "sg:postcode":"91423",
    "sg:province":"CA",
    "sg:tags":[
        "establishment"
    ],
    "wof:name":"System Upgrade Inc",
    "wof:placetype":"venue"
},
  "geometry": {"coordinates":[-118.438445,34.146888],"type":"Point"}
}