{
  "type": "Feature",
  "properties": {
    "addr:full":"214 5th Ave City Of Industry CA 91746",
    "addr:housenumber":"214",
    "addr:postcode":"91746",
    "addr:street":"5Th Ave",
    "iso:country":"US",
    "sg:address":"214 5th Ave",
    "sg:city":"City Of Industry",
    "sg:classifiers":[
        {
            "category":"Manufacturing",
            "subcategory":"Tools & Machinery",
            "type":"Manufacturing & Wholesale Goods"
        }
    ],
    "sg:phone":"+1 626 934 9868",
    "sg:postcode":"91746",
    "sg:province":"CA",
    "sg:tags":[
        "computer"
    ],
    "sg:website":"www.eversun.com",
    "wof:name":"Eversun Technologies Inc",
    "wof:placetype":"venue"
},
  "geometry": {"coordinates":[-117.98374699999999,34.037679],"type":"Point"}
}