{
  "type": "Feature",
  "properties": {
    "addr:full":"710 1st St Benicia CA 94510",
    "addr:housenumber":"710",
    "addr:postcode":"94510",
    "addr:street":"1St St",
    "iso:country":"US",
    "sg:address":"710 1st St",
    "sg:city":"Benicia",
    "sg:classifiers":[
        {
            "category":"Cinema",
            "subcategory":"Movie Theater",
            "type":"Entertainment"
        }
    ],
    "sg:phone":"+1 707 747 6684",
    "sg:postcode":"94510",
    "sg:province":"CA",
    "sg:tags":[
        "motion",
        "picture",
        "except",
        "drive"
    ],
    "sg:website":"www.benicia2000.com",
    "wof:name":"Majestic Theatre",
    "wof:placetype":"venue"
},
  "geometry": {"coordinates":[-122.15853199999999,38.049842],"type":"Point"}
}