{
  "type": "Feature",
  "properties": {
    "addr:full":"43209 Osgood Rd Fremont CA 94539",
    "addr:housenumber":"43209",
    "addr:postcode":"94539",
    "addr:street":"Osgood Rd",
    "iso:country":"US",
    "sg:address":"43209 Osgood Rd",
    "sg:city":"Fremont",
    "sg:classifiers":[
        {
            "category":"Wholesale",
            "subcategory":"Non-durable Goods",
            "type":"Manufacturing & Wholesale Goods"
        }
    ],
    "sg:phone":"+1 510 656 3138",
    "sg:postcode":"94539",
    "sg:province":"CA",
    "sg:tags":[
        "tropical",
        "fish"
    ],
    "wof:name":"Golden Phoenix Fancy Goldfish",
    "wof:placetype":"venue"
},
  "geometry": {"coordinates":[-121.946437,37.519946],"type":"Point"}
}