{
  "type": "Feature",
  "properties": {
    "iso:country":"US",
    "sg:address":"1441 E Rowland Ave",
    "sg:city":"West Covina",
    "sg:classifiers":[
        {
            "category":"Real Estate",
            "subcategory":"Real Estate Agent",
            "type":"Services"
        }
    ],
    "sg:phone":"+1 626 966 8505",
    "sg:postcode":"91791",
    "sg:province":"CA",
    "sg:tags":[
        "investment"
    ],
    "wof:name":"Jnm Enterprises",
    "wof:placetype":"venue"
},
  "geometry": {"coordinates":[-117.913571,34.079176],"type":"Point"}
}