{
  "type": "Feature",
  "properties": {
    "addr:full":"1621 W 25th St San Pedro CA 90732",
    "addr:housenumber":"1621",
    "addr:postcode":"90732",
    "addr:street":"W 25Th St",
    "iso:country":"US",
    "sg:address":"1621 W 25th St",
    "sg:city":"San Pedro",
    "sg:classifiers":[
        {
            "category":"Building & Trades",
            "subcategory":"Construction",
            "type":"Services"
        }
    ],
    "sg:phone":"+1 310 515 1622",
    "sg:postcode":"90732",
    "sg:province":"CA",
    "sg:tags":[
        "carpenter"
    ],
    "wof:name":"Red's Construction",
    "wof:placetype":"venue"
},
  "geometry": {"coordinates":[-118.314441,33.723749],"type":"Point"}
}