{
  "type": "Feature",
  "properties": {
    "iso:country":"US",
    "sg:address":"2101 Ocean Park Blvd",
    "sg:city":"Santa Monica",
    "sg:classifiers":[
        {
            "category":"Education",
            "subcategory":"Library",
            "type":"Public Place"
        }
    ],
    "sg:phone":"+1 310 450 0443",
    "sg:postcode":"90405",
    "sg:province":"CA",
    "sg:tags":[
        "executive"
    ],
    "wof:name":"Fairview Branch Library",
    "wof:placetype":"venue"
},
  "geometry": {"coordinates":[-118.462752,34.014829],"type":"Point"}
}