{
  "type": "Feature",
  "properties": {
    "addr:full":"1347 Encinitas Blvd Encinitas CA 92024",
    "addr:housenumber":"1347",
    "addr:postcode":"92024",
    "addr:street":"Encinitas Blvd",
    "iso:country":"US",
    "sg:address":"1347 Encinitas Blvd",
    "sg:city":"Encinitas",
    "sg:classifiers":[
        {
            "category":"Shopping",
            "subcategory":"Shoes",
            "type":"Retail Goods"
        }
    ],
    "sg:phone":"+1 760 634 1600",
    "sg:postcode":"92024",
    "sg:province":"CA",
    "wof:name":"Foot Solutions",
    "wof:placetype":"venue"
},
  "geometry": {"coordinates":[-117.261349,33.045917],"type":"Point"}
}