{
  "type": "Feature",
  "properties": {
    "iso:country":"US",
    "sg:address":"1716 G St",
    "sg:city":"Rio Linda",
    "sg:classifiers":[
        {
            "category":"Travel",
            "subcategory":"Campground",
            "type":"Entertainment"
        }
    ],
    "sg:phone":"+1 916 991 5931",
    "sg:postcode":"95673",
    "sg:province":"CA",
    "sg:tags":[
        "camp"
    ],
    "wof:name":"Bob Olivers Baseball Academy",
    "wof:placetype":"venue"
},
  "geometry": {"coordinates":[-121.421974,38.679834],"type":"Point"}
}