{
  "type": "Feature",
  "properties": {
    "addr:full":"4 P St Bakersfield CA 93304",
    "addr:housenumber":"4 p",
    "addr:postcode":"93304",
    "addr:street":"St",
    "iso:country":"US",
    "sg:address":"4 P St",
    "sg:city":"Bakersfield",
    "sg:classifiers":[
        {
            "category":"Building & Trades",
            "subcategory":"Construction",
            "type":"Services"
        },
        {
            "category":"Manufacturing",
            "subcategory":"Building Materials",
            "type":"Manufacturing & Wholesale Goods"
        }
    ],
    "sg:phone":"+1 661 327 7663",
    "sg:postcode":"93304",
    "sg:province":"CA",
    "sg:tags":[
        "roofing",
        "industrial",
        "supply",
        "contractor",
        "equipment",
        "contractors-commercial"
    ],
    "sg:website":"http://www.bswroofing.com",
    "wof:name":"Bsw Roofing",
    "wof:placetype":"venue"
},
  "geometry": {"coordinates":[-119.011887,35.3539],"type":"Point"}
}