{
  "type": "Feature",
  "properties": {
    "addr:full":"1455 Ary Ln Dixon CA 95620",
    "addr:housenumber":"1455",
    "addr:postcode":"95620",
    "addr:street":"Ary Ln",
    "iso:country":"US",
    "sg:address":"1455 Ary Ln",
    "sg:city":"Dixon",
    "sg:classifiers":[
        {
            "category":"Restaurant",
            "type":"Food & Drink"
        }
    ],
    "sg:menulink":"http://www.allmenus.com/ca/dixon/74458-pizza-guys/menu/",
    "sg:phone":"+1 707 693 6666",
    "sg:postcode":"95620",
    "sg:province":"CA",
    "sg:tags":[
        "american",
        "pizza"
    ],
    "wof:name":"Pizza Guys",
    "wof:placetype":"venue"
},
  "geometry": {"coordinates":[-121.842455,38.456656],"type":"Point"}
}