{
  "type": "Feature",
  "properties": {
    "iso:country":"US",
    "sg:address":"6160 Egret Ct",
    "sg:city":"Benicia",
    "sg:classifiers":[
        {
            "category":"Manufacturing",
            "subcategory":"Tools & Machinery",
            "type":"Manufacturing & Wholesale Goods"
        }
    ],
    "sg:phone":"+1 707 747 9600",
    "sg:postcode":"94510",
    "sg:province":"CA",
    "sg:tags":[
        "ozone",
        "machine"
    ],
    "sg:website":"www.pacificozone.com",
    "wof:name":"Pacific Ozone Technology Inc",
    "wof:placetype":"venue"
},
  "geometry": {"coordinates":[-122.108318,38.084065],"type":"Point"}
}