{
  "type": "Feature",
  "properties": {
    "iso:country":"US",
    "sg:address":"7864 Pacific Coast Hwy",
    "sg:city":"Newport Beach",
    "sg:classifiers":[
        {
            "category":"Shopping",
            "subcategory":"Clothing, Apparel, & Fashions",
            "type":"Retail Goods"
        }
    ],
    "sg:phone":"+1 949 376 9119",
    "sg:postcode":"92660",
    "sg:province":"CA",
    "sg:tags":[
        "accessory",
        "clothing",
        "women's"
    ],
    "wof:name":"Ann Taylor Loft 1377",
    "wof:placetype":"venue"
},
  "geometry": {"coordinates":[-117.87948900000001,33.632027],"type":"Point"}
}