{
  "type": "Feature",
  "properties": {
    "addr:full":"5173 Waring Rd San Diego CA 92120",
    "addr:housenumber":"5173",
    "addr:postcode":"92120",
    "addr:street":"Waring Rd",
    "iso:country":"US",
    "sg:address":"5173 Waring Rd",
    "sg:city":"San Diego",
    "sg:classifiers":[
        {
            "category":"Travel",
            "subcategory":"Travel Agent",
            "type":"Entertainment"
        }
    ],
    "sg:phone":"+1 619 464 8808",
    "sg:postcode":"92120",
    "sg:province":"CA",
    "sg:tags":[
        "agency",
        "bureau"
    ],
    "wof:name":"Adventures In Travel",
    "wof:placetype":"venue"
},
  "geometry": {"coordinates":[-117.08193,32.791197],"type":"Point"}
}