{
  "type": "Feature",
  "properties": {
    "iso:country":"US",
    "sg:address":"589 Mendocino Ave",
    "sg:city":"Santa Rosa",
    "sg:classifiers":[
        {
            "category":"Personal",
            "subcategory":"Beauty Salon",
            "type":"Services"
        }
    ],
    "sg:phone":"+1 707 545 5527",
    "sg:postcode":"95401",
    "sg:province":"CA",
    "wof:name":"Julieta S Alma",
    "wof:placetype":"venue"
},
  "geometry": {"coordinates":[-122.716662,38.443969],"type":"Point"}
}