{
  "type": "Feature",
  "properties": {
    "iso:country":"US",
    "sg:address":"45 S Sanborn Rd",
    "sg:city":"Salinas",
    "sg:classifiers":[
        {
            "category":"Personal",
            "subcategory":"Beauty Salon",
            "type":"Services"
        }
    ],
    "sg:phone":"+1 831 757 7749",
    "sg:postcode":"93905",
    "sg:province":"CA",
    "wof:name":"Gabby Beauty Salon",
    "wof:placetype":"venue"
},
  "geometry": {"coordinates":[-121.627363,36.67275],"type":"Point"}
}