{
  "type": "Feature",
  "properties": {
    "addr:full":"2245 Gellert Blvd South San Francisco CA 94080",
    "addr:housenumber":"2245",
    "addr:postcode":"94080",
    "addr:street":"Gellert Blvd",
    "iso:country":"US",
    "sg:address":"2245 Gellert Blvd",
    "sg:city":"South San Francisco",
    "sg:classifiers":[
        {
            "category":"Home & Garden",
            "subcategory":"Hardware",
            "type":"Retail Goods"
        }
    ],
    "sg:phone":"+1 650 878 3322",
    "sg:postcode":"94080",
    "sg:province":"CA",
    "sg:tags":[
        "store"
    ],
    "sg:website":"osh.com",
    "wof:name":"Orchard Supply Hardware",
    "wof:placetype":"venue"
},
  "geometry": {"coordinates":[-122.453581,37.644519],"type":"Point"}
}