{
  "type": "Feature",
  "properties": {
    "iso:country":"US",
    "sg:address":"101 Olympic Blvd",
    "sg:city":"Los Angeles",
    "sg:classifiers":[
        {
            "category":"Building & Trades",
            "subcategory":"Cleaning & Sanitation",
            "type":"Services"
        }
    ],
    "sg:phone":"+1 310 770 9085",
    "sg:postcode":"90035",
    "sg:province":"CA",
    "sg:tags":[
        "carpet"
    ],
    "sg:website":"www.LACleaning.com",
    "wof:name":"LA Cleaning",
    "wof:placetype":"venue"
},
  "geometry": {"coordinates":[-118.25671,34.040421],"type":"Point"}
}