{
  "type": "Feature",
  "properties": {
    "addr:full":"23565 Avalon Blvd Carson CA 90745",
    "addr:housenumber":"23565",
    "addr:postcode":"90745",
    "addr:street":"Avalon Blvd",
    "iso:country":"US",
    "sg:address":"23565 Avalon Blvd",
    "sg:city":"Carson",
    "sg:classifiers":[
        {
            "category":"Restaurant",
            "type":"Food & Drink"
        }
    ],
    "sg:phone":"+1 310 549 1600",
    "sg:postcode":"90745",
    "sg:province":"CA",
    "sg:tags":[
        "pizza"
    ],
    "sg:website":"dominos.com",
    "wof:name":"Domino's Pizza",
    "wof:placetype":"venue"
},
  "geometry": {"coordinates":[-118.264,33.8116],"type":"Point"}
}