{
  "type": "Feature",
  "properties": {
    "addr:full":"7511 Jerez Ct Unit B Carlsbad CA 92009",
    "addr:housenumber":"7511",
    "addr:postcode":"92009",
    "addr:street":"Jerez Ct Unit B",
    "iso:country":"US",
    "sg:address":"7511 Jerez Ct Unit B",
    "sg:city":"Carlsbad",
    "sg:classifiers":[
        {
            "category":"Building & Trades",
            "subcategory":"Construction",
            "type":"Services"
        }
    ],
    "sg:phone":"+1 619 647 4629",
    "sg:postcode":"92009",
    "sg:province":"CA",
    "sg:tags":[
        "wallcoverings-installation",
        "wallpaper",
        "painting",
        "contractor"
    ],
    "wof:name":"K M G Painting",
    "wof:placetype":"venue"
},
  "geometry": {"coordinates":[-117.248126,33.088086],"type":"Point"}
}