{
  "type": "Feature",
  "properties": {
    "addr:full":"1990 Lombard St Ste 100 San Francisco CA 94123",
    "addr:housenumber":"1990",
    "addr:postcode":"94123",
    "addr:street":"Lombard St Ste 100",
    "iso:country":"US",
    "sg:address":"1990 Lombard St Ste 100",
    "sg:city":"San Francisco",
    "sg:classifiers":[
        {
            "category":"Health Services",
            "subcategory":"Health Practitioner",
            "type":"Services"
        }
    ],
    "sg:phone":"+1 415 686 9525",
    "sg:postcode":"94123",
    "sg:province":"CA",
    "sg:tags":[
        "acupuncture"
    ],
    "sg:website":"www.marinacupunctureworks.com",
    "wof:name":"Marin Acupuncture Works",
    "wof:placetype":"venue"
},
  "geometry": {"coordinates":[-122.434301,37.800373],"type":"Point"}
}