{
  "type": "Feature",
  "properties": {
    "addr:full":"13590 Aster Rd Victorville CA 92392",
    "addr:housenumber":"13590",
    "addr:postcode":"92392",
    "addr:street":"Aster Rd",
    "iso:country":"US",
    "sg:address":"13590 Aster Rd",
    "sg:city":"Victorville",
    "sg:classifiers":[
        {
            "category":"Professional",
            "subcategory":"Business Services",
            "type":"Services"
        }
    ],
    "sg:phone":"+1 760 245 0046",
    "sg:postcode":"92392",
    "sg:province":"CA",
    "sg:tags":[
        "paging",
        "answering"
    ],
    "wof:name":"Char Mar Answering",
    "wof:placetype":"venue"
},
  "geometry": {"coordinates":[-117.36582900000001,34.508745],"type":"Point"}
}