{
  "type": "Feature",
  "properties": {
    "addr:full":"5340 N 6th St Fresno CA 93710",
    "addr:housenumber":"5340",
    "addr:postcode":"93710",
    "addr:street":"N 6Th St",
    "iso:country":"US",
    "sg:address":"5340 N 6th St",
    "sg:city":"Fresno",
    "sg:classifiers":[
        {
            "category":"Real Estate",
            "subcategory":"Real Estate Operator",
            "type":"Services"
        }
    ],
    "sg:phone":"+1 559 226 4458",
    "sg:postcode":"93710",
    "sg:province":"CA",
    "sg:tags":[
        "apartment"
    ],
    "wof:name":"King's Court Apartments",
    "wof:placetype":"venue"
},
  "geometry": {"coordinates":[-119.762905,36.815136],"type":"Point"}
}