{
  "type": "Feature",
  "properties": {
    "iso:country":"US",
    "sg:address":"2132 Irving Street",
    "sg:city":"San Francisco",
    "sg:classifiers":[
        {
            "category":"Personal",
            "subcategory":"Massage",
            "type":"Services"
        }
    ],
    "sg:phone":"+1 415 661 4368",
    "sg:postcode":"94122",
    "sg:province":"CA",
    "wof:name":"Migun USA Sf Branch",
    "wof:placetype":"venue"
},
  "geometry": {"coordinates":[-122.481003,37.7635],"type":"Point"}
}