{
  "type": "Feature",
  "properties": {
    "addr:full":"15001 Vanowen St Van Nuys CA 91405",
    "addr:postcode":"15001;91405",
    "addr:street":"Vanowen St",
    "iso:country":"US",
    "sg:address":"15001 Vanowen St",
    "sg:city":"Van Nuys",
    "sg:classifiers":[
        {
            "category":"Professional",
            "type":"Services"
        }
    ],
    "sg:phone":"+1 818 787 5505",
    "sg:postcode":"91405",
    "sg:province":"CA",
    "sg:tags":[
        "establishment"
    ],
    "wof:name":"Thoughts & Things Etc",
    "wof:placetype":"venue"
},
  "geometry": {"coordinates":[-118.458907,34.193996],"type":"Point"}
}