{
  "type": "Feature",
  "properties": {
    "addr:full":"24305 Dana Dr Dana Point CA 92629",
    "addr:housenumber":"24305",
    "addr:postcode":"92629",
    "addr:street":"Dana Dr",
    "iso:country":"US",
    "sg:address":"24305 Dana Dr",
    "sg:city":"Dana Point",
    "sg:classifiers":[
        {
            "category":"Social Services",
            "subcategory":"Adult Care",
            "type":"Services"
        }
    ],
    "sg:phone":"+1 949 481 0838",
    "sg:postcode":"92629",
    "sg:province":"CA",
    "sg:tags":[
        "residential"
    ],
    "wof:name":"A R V Assisted Living Inc",
    "wof:placetype":"venue"
},
  "geometry": {"coordinates":[-117.70065700000001,33.458982],"type":"Point"}
}