{
  "type": "Feature",
  "properties": {
    "addr:full":"11282 Washington Boulevard Culver City CA 90232",
    "addr:housenumber":"11282",
    "addr:postcode":"90232",
    "addr:street":"Washington Boulevard",
    "iso:country":"US",
    "sg:address":"11282 Washington Boulevard",
    "sg:city":"Culver City",
    "sg:classifiers":[
        {
            "category":"Professional",
            "subcategory":"Accounting & Tax Preparation",
            "type":"Services"
        }
    ],
    "sg:phone":"+1 310 313 2700",
    "sg:postcode":"90232",
    "sg:province":"CA",
    "sg:tags":[
        "accountant"
    ],
    "wof:name":"Kothari Accountancy Corporation",
    "wof:placetype":"venue"
},
  "geometry": {"coordinates":[-118.414242,34.004206],"type":"Point"}
}