{
  "type": "Feature",
  "properties": {
    "iso:country":"US",
    "sg:address":"17633 Carpintero Ave",
    "sg:city":"Bellflower",
    "sg:classifiers":[
        {
            "category":"Building & Trades",
            "subcategory":"Construction",
            "type":"Services"
        }
    ],
    "sg:phone":"+1 562 925 6800",
    "sg:postcode":"90706",
    "sg:province":"CA",
    "sg:tags":[
        "contractor"
    ],
    "wof:name":"Mesa Verde Development Inc",
    "wof:placetype":"venue"
},
  "geometry": {"coordinates":[-118.114513,33.872557],"type":"Point"}
}