{
  "type": "Feature",
  "properties": {
    "addr:full":"916 Soquel Ave Ste E Santa Cruz CA 95062",
    "addr:housenumber":"916",
    "addr:postcode":"95062",
    "addr:street":"Soquel Ave Ste E",
    "iso:country":"US",
    "sg:address":"916 Soquel Ave Ste E",
    "sg:city":"Santa Cruz",
    "sg:classifiers":[
        {
            "category":"Retail",
            "subcategory":"Auto Repair",
            "type":"Services"
        },
        {
            "category":"Government",
            "subcategory":"Office",
            "type":"Public Place"
        }
    ],
    "sg:phone":"+1 831 458 1087",
    "sg:postcode":"95062",
    "sg:province":"CA",
    "sg:tags":[
        "smog",
        "check"
    ],
    "wof:name":"Fidelity Automotive",
    "wof:placetype":"venue"
},
  "geometry": {"coordinates":[-122.013406,36.977985],"type":"Point"}
}