{
  "type": "Feature",
  "properties": {
    "iso:country":"US",
    "sg:address":"352 S C St",
    "sg:city":"Madera",
    "sg:classifiers":[
        {
            "category":"Food & Beverages",
            "subcategory":"Bakery",
            "type":"Retail Goods"
        }
    ],
    "sg:phone":"+1 559 673 2849",
    "sg:postcode":"93638",
    "sg:province":"CA",
    "sg:tags":[
        "baker"
    ],
    "wof:name":"El Nopal Bakery",
    "wof:placetype":"venue"
},
  "geometry": {"coordinates":[-120.05462900000001,36.96067],"type":"Point"}
}