{
  "type": "Feature",
  "properties": {
    "addr:full":"959 E 4th St Ontario CA 91764",
    "addr:housenumber":"959",
    "addr:postcode":"91764",
    "addr:street":"E 4Th St",
    "iso:country":"US",
    "sg:address":"959 E 4th St",
    "sg:city":"Ontario",
    "sg:classifiers":[
        {
            "category":"Food & Beverages",
            "subcategory":"Groceries & Convenience Stores",
            "type":"Retail Goods"
        }
    ],
    "sg:phone":"+1 909 467 1996",
    "sg:postcode":"91764",
    "sg:province":"CA",
    "wof:name":"R Choice Market",
    "wof:placetype":"venue"
},
  "geometry": {"coordinates":[-117.63561300000001,34.078024],"type":"Point"}
}