{
  "type": "Feature",
  "properties": {
    "iso:country":"US",
    "sg:address":"532 N 2nd St",
    "sg:city":"El Cajon",
    "sg:classifiers":[
        {
            "category":"Personal",
            "subcategory":"Beauty Salon",
            "type":"Services"
        }
    ],
    "sg:phone":"+1 619 442 8343",
    "sg:postcode":"92021",
    "sg:province":"CA",
    "sg:tags":[
        "manicuring"
    ],
    "wof:name":"Number 1 Nails",
    "wof:placetype":"venue"
},
  "geometry": {"coordinates":[-116.93581399999999,32.801449],"type":"Point"}
}