{
  "type": "Feature",
  "properties": {
    "iso:country":"US",
    "sg:address":"205 Lemon Creek Dr",
    "sg:city":"Walnut",
    "sg:classifiers":[
        {
            "category":"Wholesale",
            "subcategory":"Machinery & Supplies",
            "type":"Manufacturing & Wholesale Goods"
        }
    ],
    "sg:phone":"+1 909 595 5122",
    "sg:postcode":"91789",
    "sg:province":"CA",
    "sg:tags":[
        "pump"
    ],
    "sg:website":"www.frederickpump.com",
    "wof:name":"Frederick Pump Co",
    "wof:placetype":"venue"
},
  "geometry": {"coordinates":[-117.862899,34.010414],"type":"Point"}
}