{
  "type": "Feature",
  "properties": {
    "iso:country":"US",
    "sg:address":"4811 Eureka Ave",
    "sg:city":"Yorba Linda",
    "sg:classifiers":[
        {
            "category":"Professional",
            "subcategory":"Management & Consulting",
            "type":"Services"
        }
    ],
    "sg:phone":"+1 714 572 3646",
    "sg:postcode":"92886",
    "sg:province":"CA",
    "sg:tags":[
        "consultant",
        "business"
    ],
    "wof:name":"AMS",
    "wof:placetype":"venue"
},
  "geometry": {"coordinates":[-117.820177,33.890108],"type":"Point"}
}