{
  "type": "Feature",
  "properties": {
    "addr:full":"180 Bliss Ave Pittsburg CA 94565",
    "addr:housenumber":"180",
    "addr:postcode":"94565",
    "addr:street":"Bliss Ave",
    "iso:country":"US",
    "sg:address":"180 Bliss Ave",
    "sg:city":"Pittsburg",
    "sg:classifiers":[
        {
            "category":"Wholesale",
            "subcategory":"Construction Materials",
            "type":"Manufacturing & Wholesale Goods"
        },
        {
            "category":"Home & Garden",
            "subcategory":"Building Materials",
            "type":"Retail Goods"
        },
        {
            "category":"Manufacturing",
            "subcategory":"Building Materials",
            "type":"Manufacturing & Wholesale Goods"
        }
    ],
    "sg:phone":"+1 925 439 6910",
    "sg:postcode":"94565",
    "sg:province":"CA",
    "sg:tags":[
        "bathroom",
        "supply",
        "top",
        "counter",
        "marble-cultured",
        "cabinet",
        "equipment",
        "fixtures",
        "accessory",
        "masonry"
    ],
    "sg:website":"http://www.themarbleshop.net",
    "wof:name":"The Marble Shop",
    "wof:placetype":"venue"
},
  "geometry": {"coordinates":[-121.884817,38.014442],"type":"Point"}
}