{
  "type": "Feature",
  "properties": {
    "addr:full":"1013 San Bernardino Ave Pomona CA 91767",
    "addr:housenumber":"1013",
    "addr:postcode":"91767",
    "addr:street":"San Bernardino Ave",
    "iso:country":"US",
    "sg:address":"1013 San Bernardino Ave",
    "sg:city":"Pomona",
    "sg:classifiers":[
        {
            "category":"Organizations",
            "subcategory":"Religious Organization",
            "type":"Services"
        }
    ],
    "sg:phone":"+1 909 629 0711",
    "sg:postcode":"91767",
    "sg:province":"CA",
    "sg:tags":[
        "church"
    ],
    "wof:name":"Holy Missionary Baptist Church",
    "wof:placetype":"venue"
},
  "geometry": {"coordinates":[-117.729175,34.075929],"type":"Point"}
}