{
  "type": "Feature",
  "properties": {
    "addr:full":"7040 Katella Ave Stanton CA 90680",
    "addr:housenumber":"7040",
    "addr:postcode":"ca 90680",
    "addr:street":"Katella Ave",
    "iso:country":"US",
    "sg:address":"7040 Katella Ave",
    "sg:city":"Stanton",
    "sg:classifiers":[
        {
            "category":"Personal",
            "subcategory":"Barber",
            "type":"Services"
        }
    ],
    "sg:phone":"+1 714 892 9190",
    "sg:postcode":"90680",
    "sg:province":"CA",
    "wof:name":"Garden Park Barber Shop",
    "wof:placetype":"venue"
},
  "geometry": {"coordinates":[-118.010002,33.8027],"type":"Point"}
}