{
  "type": "Feature",
  "properties": {
    "addr:full":"2445 Cabrillo Ave Santa Clara CA 95051",
    "addr:housenumber":"2445",
    "addr:postcode":"95051",
    "addr:street":"Cabrillo Ave",
    "iso:country":"US",
    "sg:address":"2445 Cabrillo Ave",
    "sg:city":"Santa Clara",
    "sg:classifiers":[
        {
            "category":"Organizations",
            "subcategory":"Religious Organization",
            "type":"Services"
        }
    ],
    "sg:phone":"+1 408 248 1770",
    "sg:postcode":"95051",
    "sg:province":"CA",
    "sg:tags":[
        "church"
    ],
    "sg:website":"www.scnazarene.org",
    "wof:name":"Santa Clara First Chr-Nazarene",
    "wof:placetype":"venue"
},
  "geometry": {"coordinates":[-121.97031699999999,37.359187],"type":"Point"}
}