{
  "type": "Feature",
  "properties": {
    "iso:country":"US",
    "sg:address":"2025 Mountain View Rd",
    "sg:city":"South El Monte",
    "sg:classifiers":[
        {
            "category":"Wholesale",
            "subcategory":"Durable Goods & Equipment",
            "type":"Manufacturing & Wholesale Goods"
        }
    ],
    "sg:phone":"+1 626 401 0232",
    "sg:postcode":"91733",
    "sg:province":"CA",
    "sg:tags":[
        "importer"
    ],
    "wof:name":"East West United Group Inc",
    "wof:placetype":"venue"
},
  "geometry": {"coordinates":[-118.035567,34.051252],"type":"Point"}
}