{
  "type": "Feature",
  "properties": {
    "iso:country":"US",
    "sg:address":"982 Las Pavadas Ave",
    "sg:city":"San Rafael",
    "sg:classifiers":[
        {
            "category":"Real Estate",
            "subcategory":"Real Estate Agent",
            "type":"Services"
        }
    ],
    "sg:phone":"+1 415 479 7339",
    "sg:postcode":"94903",
    "sg:province":"CA",
    "sg:tags":[
        "inspection"
    ],
    "wof:name":"Bay Area Property Inspection",
    "wof:placetype":"venue"
},
  "geometry": {"coordinates":[-122.55583799999999,38.011469],"type":"Point"}
}