{
  "type": "Feature",
  "properties": {
    "addr:full":"715 Spring St San Jose CA 95110",
    "addr:housenumber":"715",
    "addr:postcode":"95110",
    "addr:street":"Spring St",
    "iso:country":"US",
    "sg:address":"715 Spring St",
    "sg:city":"San Jose",
    "sg:classifiers":[
        {
            "category":"Recreation",
            "type":"Entertainment"
        }
    ],
    "sg:phone":"+1 408 298 7657",
    "sg:postcode":"95110",
    "sg:province":"CA",
    "sg:tags":[
        "center"
    ],
    "wof:name":"Friends Of Guadalupe River",
    "wof:placetype":"venue"
},
  "geometry": {"coordinates":[-121.909295,37.344681],"type":"Point"}
}