{
  "type": "Feature",
  "properties": {
    "addr:full":"7305 Greenback Ln Citrus Heights CA 95621",
    "addr:housenumber":"7305",
    "addr:postcode":"95621",
    "addr:street":"Greenback Ln",
    "iso:country":"US",
    "sg:address":"7305 Greenback Ln",
    "sg:city":"Citrus Heights",
    "sg:classifiers":[
        {
            "category":"Shopping",
            "subcategory":"Used Merchandise",
            "type":"Retail Goods"
        }
    ],
    "sg:phone":"+1 916 729 8474",
    "sg:postcode":"95621",
    "sg:province":"CA",
    "sg:tags":[
        "vintage",
        "consignment"
    ],
    "wof:name":"Eco Thrift",
    "wof:placetype":"venue"
},
  "geometry": {"coordinates":[-121.294327,38.678436],"type":"Point"}
}