{
  "type": "Feature",
  "properties": {
    "addr:full":"12368 Valley Blvd El Monte CA 91732",
    "addr:housenumber":"12368",
    "addr:postcode":"91732",
    "addr:street":"Valley Blvd",
    "iso:country":"US",
    "sg:address":"12368 Valley Blvd",
    "sg:city":"El Monte",
    "sg:classifiers":[
        {
            "category":"Wholesale",
            "subcategory":"Durable Goods & Equipment",
            "type":"Manufacturing & Wholesale Goods"
        }
    ],
    "sg:phone":"+1 626 350 0589",
    "sg:postcode":"91732",
    "sg:province":"CA",
    "sg:tags":[
        "importer"
    ],
    "wof:name":"Panatoz Inc",
    "wof:placetype":"venue"
},
  "geometry": {"coordinates":[-118.012816,34.059491],"type":"Point"}
}