{
  "type": "Feature",
  "properties": {
    "addr:full":"20974 Currier Rd Walnut CA 91789",
    "addr:postcode":"20974;91789",
    "addr:street":"Currier Rd",
    "iso:country":"US",
    "sg:address":"20974 Currier Rd",
    "sg:city":"Walnut",
    "sg:classifiers":[
        {
            "category":"Building & Trades",
            "subcategory":"Construction",
            "type":"Services"
        }
    ],
    "sg:phone":"+1 626 913 0045",
    "sg:postcode":"91789",
    "sg:province":"CA",
    "sg:tags":[
        "roofing",
        "contractor"
    ],
    "wof:name":"Giant Roofing Co",
    "wof:placetype":"venue"
},
  "geometry": {"coordinates":[-117.849248,34.008197],"type":"Point"}
}