{
  "type": "Feature",
  "properties": {
    "addr:full":"5151 Pistachio Ln Placerville CA 95667",
    "addr:housenumber":"5151",
    "addr:postcode":"95667",
    "addr:street":"Pistachio Ln",
    "iso:country":"US",
    "sg:address":"5151 Pistachio Ln",
    "sg:city":"Placerville",
    "sg:classifiers":[
        {
            "category":"Food & Beverages",
            "subcategory":"Specialty",
            "type":"Retail Goods"
        }
    ],
    "sg:phone":"+1 530 626 5024",
    "sg:postcode":"95667",
    "sg:province":"CA",
    "sg:tags":[
        "nuts-edible"
    ],
    "wof:name":"William Rush",
    "wof:placetype":"venue"
},
  "geometry": {"coordinates":[-120.705699,38.638046],"type":"Point"}
}