{
  "type": "Feature",
  "properties": {
    "iso:country":"US",
    "sg:address":"4230 Balboa Ave",
    "sg:city":"San Diego",
    "sg:classifiers":[
        {
            "category":"Shopping",
            "type":"Retail Goods"
        }
    ],
    "sg:phone":"+1 858 483 3100",
    "sg:postcode":"92117",
    "sg:province":"CA",
    "sg:tags":[
        "equipment",
        "pool",
        "swimming"
    ],
    "wof:name":"Discount Pool Supply",
    "wof:placetype":"venue"
},
  "geometry": {"coordinates":[-117.200451,32.811806],"type":"Point"}
}