{
  "type": "Feature",
  "properties": {
    "iso:country":"US",
    "sg:address":"801 Opal Ave",
    "sg:city":"Mentone",
    "sg:classifiers":[
        {
            "category":"Manufacturing",
            "subcategory":"Furniture",
            "type":"Manufacturing & Wholesale Goods"
        }
    ],
    "sg:phone":"+1 909 794 7661",
    "sg:postcode":"92359",
    "sg:province":"CA",
    "sg:website":"www.klaussner.com",
    "wof:name":"Klaussner Furniture-California",
    "wof:placetype":"venue"
},
  "geometry": {"coordinates":[-117.134556,34.066391],"type":"Point"}
}