{
  "type": "Feature",
  "properties": {
    "addr:full":"22371 Banducci Rd Tehachapi CA 93561",
    "addr:postcode":"22371;93561",
    "addr:street":"Banducci Rd",
    "iso:country":"US",
    "sg:address":"22371 Banducci Rd",
    "sg:city":"Tehachapi",
    "sg:classifiers":[
        {
            "category":"Real Estate",
            "subcategory":"Real Estate Agent",
            "type":"Services"
        }
    ],
    "sg:phone":"+1 661 822 0165",
    "sg:postcode":"93561",
    "sg:province":"CA",
    "wof:name":"Apple Tree Realty",
    "wof:placetype":"venue"
},
  "geometry": {"coordinates":[-118.535235,35.102164],"type":"Point"}
}