{
  "type": "Feature",
  "properties": {
    "addr:full":"2901 S Sepulveda Blvd Los Angeles CA 90064",
    "addr:housenumber":"2901",
    "addr:postcode":"90064",
    "addr:street":"S Sepulveda Blvd",
    "iso:country":"US",
    "sg:address":"2901 S Sepulveda Blvd",
    "sg:city":"Los Angeles",
    "sg:classifiers":[
        {
            "category":"Real Estate",
            "subcategory":"Real Estate Operator",
            "type":"Services"
        }
    ],
    "sg:phone":"+1 310 479 2120",
    "sg:postcode":"90064",
    "sg:province":"CA",
    "sg:tags":[
        "apartment"
    ],
    "sg:website":"www.westwoodvillaapts.com",
    "wof:name":"Westwood Villa",
    "wof:placetype":"venue"
},
  "geometry": {"coordinates":[-118.43014599999999,34.028834],"type":"Point"}
}