{
  "type": "Feature",
  "properties": {
    "addr:full":"13143 Rosecrans Ave Santa Fe Springs CA 90670",
    "addr:housenumber":"13143",
    "addr:postcode":"90670",
    "addr:street":"Rosecrans Ave",
    "iso:country":"US",
    "sg:address":"13143 Rosecrans Ave",
    "sg:city":"Santa Fe Springs",
    "sg:classifiers":[
        {
            "category":"Wholesale",
            "subcategory":"Auto Parts",
            "type":"Manufacturing & Wholesale Goods"
        }
    ],
    "sg:phone":"+1 562 921 9788",
    "sg:postcode":"90670",
    "sg:province":"CA",
    "sg:tags":[
        "trailer"
    ],
    "wof:name":"Miller Bilt",
    "wof:placetype":"venue"
},
  "geometry": {"coordinates":[-118.05030499999999,33.90241],"type":"Point"}
}