{
  "type": "Feature",
  "properties": {
    "iso:country":"US",
    "sg:address":"580 Irwin St",
    "sg:city":"San Rafael",
    "sg:classifiers":[
        {
            "category":"Building & Trades",
            "subcategory":"Construction",
            "type":"Services"
        }
    ],
    "sg:phone":"+1 415 457 1190",
    "sg:postcode":"94901",
    "sg:province":"CA",
    "sg:tags":[
        "maker",
        "cabinet"
    ],
    "wof:name":"William Eichenberger Woodwork",
    "wof:placetype":"venue"
},
  "geometry": {"coordinates":[-122.522102,37.964559],"type":"Point"}
}