{
  "type": "Feature",
  "properties": {
    "addr:full":"9627 Las Tunas Dr Temple City CA 91780",
    "addr:housenumber":"9627",
    "addr:postcode":"91780",
    "addr:street":"Las Tunas Dr",
    "iso:country":"US",
    "sg:address":"9627 Las Tunas Dr",
    "sg:city":"Temple City",
    "sg:classifiers":[
        {
            "category":"Health Services",
            "subcategory":"Health Practitioner",
            "type":"Services"
        }
    ],
    "sg:phone":"+1 626 292 1793",
    "sg:postcode":"91780",
    "sg:province":"CA",
    "sg:tags":[
        "therapist",
        "therapy",
        "physical"
    ],
    "wof:name":"Turning Point Physical Therapy Inc",
    "wof:placetype":"venue"
},
  "geometry": {"coordinates":[-118.05999799999999,34.106899],"type":"Point"}
}