{
  "type": "Feature",
  "properties": {
    "addr:full":"10631 Western Ave Downey CA 90241",
    "addr:housenumber":"10631",
    "addr:postcode":"90241",
    "addr:street":"Western Ave",
    "iso:country":"US",
    "sg:address":"10631 Western Ave",
    "sg:city":"Downey",
    "sg:classifiers":[
        {
            "category":"Wholesale",
            "subcategory":"Auto Parts",
            "type":"Manufacturing & Wholesale Goods"
        }
    ],
    "sg:phone":"+1 213 312 9836",
    "sg:postcode":"90241",
    "sg:province":"CA",
    "sg:tags":[
        "tire"
    ],
    "wof:name":"Eagle Industrial Tire Company",
    "wof:placetype":"venue"
},
  "geometry": {"coordinates":[-118.132182,33.946648],"type":"Point"}
}