{
  "type": "Feature",
  "properties": {
    "iso:country":"US",
    "sg:address":"4295 University Ave",
    "sg:city":"San Diego",
    "sg:classifiers":[
        {
            "category":"Home & Garden",
            "subcategory":"Furniture",
            "type":"Retail Goods"
        }
    ],
    "sg:phone":"+1 619 281 9988",
    "sg:postcode":"92105",
    "sg:province":"CA",
    "sg:tags":[
        "store"
    ],
    "wof:name":"Payless Furniture Source",
    "wof:placetype":"venue"
},
  "geometry": {"coordinates":[-117.101997,32.749699],"type":"Point"}
}