{
  "type": "Feature",
  "properties": {
    "addr:full":"The District at Tustin Legacy 2459 Park Ave Tustin CA 92782",
    "addr:housenumber":"2459",
    "addr:postcode":"92782",
    "addr:street":"Park Ave",
    "iso:country":"US",
    "sg:address":"The District at Tustin Legacy 2459 Park Ave",
    "sg:city":"Tustin",
    "sg:classifiers":[
        {
            "category":"Ice Cream",
            "type":"Food & Drink"
        }
    ],
    "sg:phone":"+1 714 258 0808",
    "sg:postcode":"92782",
    "sg:province":"CA",
    "sg:tags":[
        "frozen",
        "yogurt"
    ],
    "sg:website":"www.benjerry.com",
    "wof:name":"Ben & Jerry's",
    "wof:placetype":"venue"
},
  "geometry": {"coordinates":[-117.827586,33.698442],"type":"Point"}
}