{
  "type": "Feature",
  "properties": {
    "iso:country":"US",
    "sg:address":"2860 Graceland Way",
    "sg:city":"Glendale",
    "sg:classifiers":[
        {
            "category":"Manufacturing",
            "subcategory":"Printing",
            "type":"Manufacturing & Wholesale Goods"
        }
    ],
    "sg:phone":"+1 818 504 4888",
    "sg:postcode":"91206",
    "sg:province":"CA",
    "sg:tags":[
        "broker"
    ],
    "wof:name":"L A Publishing",
    "wof:placetype":"venue"
},
  "geometry": {"coordinates":[-118.208483,34.168554],"type":"Point"}
}