{
  "type": "Feature",
  "properties": {
    "addr:full":"350 Victory Ave South San Francisco CA 94080",
    "addr:housenumber":"350",
    "addr:postcode":"94080",
    "addr:street":"Victory Ave",
    "iso:country":"US",
    "sg:address":"350 Victory Ave",
    "sg:city":"South San Francisco",
    "sg:classifiers":[
        {
            "category":"Manufacturing",
            "subcategory":"Printing",
            "type":"Manufacturing & Wholesale Goods"
        }
    ],
    "sg:phone":"+1 650 583 1958",
    "sg:postcode":"94080",
    "sg:province":"CA",
    "sg:tags":[
        "commercial",
        "lithographic"
    ],
    "wof:name":"Westrade Printing",
    "wof:placetype":"venue"
},
  "geometry": {"coordinates":[-122.414008,37.647099],"type":"Point"}
}