{
  "type": "Feature",
  "properties": {
    "addr:full":"2305 Fruitvale Ave Bakersfield CA 93308",
    "addr:housenumber":"2305",
    "addr:postcode":"93308",
    "addr:street":"Fruitvale Ave",
    "iso:country":"US",
    "sg:address":"2305 Fruitvale Ave",
    "sg:city":"Bakersfield",
    "sg:classifiers":[
        {
            "category":"Wholesale",
            "subcategory":"Machinery & Supplies",
            "type":"Manufacturing & Wholesale Goods"
        }
    ],
    "sg:phone":"+1 661 322 6894",
    "sg:postcode":"93308",
    "sg:province":"CA",
    "sg:tags":[
        "valve"
    ],
    "wof:name":"Quality Service",
    "wof:placetype":"venue"
},
  "geometry": {"coordinates":[-119.074258,35.383272],"type":"Point"}
}