{
  "type": "Feature",
  "properties": {
    "addr:full":"955 43rd Ave Sacramento CA 95831",
    "addr:housenumber":"955",
    "addr:postcode":"95831",
    "addr:street":"43Rd Ave",
    "iso:country":"US",
    "sg:address":"955 43rd Ave",
    "sg:city":"Sacramento",
    "sg:classifiers":[
        {
            "category":"Real Estate",
            "subcategory":"Real Estate Operator",
            "type":"Services"
        }
    ],
    "sg:phone":"+1 916 392 2950",
    "sg:postcode":"95831",
    "sg:province":"CA",
    "sg:tags":[
        "apartment"
    ],
    "wof:name":"Wedgewood Commons Apt",
    "wof:placetype":"venue"
},
  "geometry": {"coordinates":[-121.525002,38.5158],"type":"Point"}
}