{
  "type": "Feature",
  "properties": {
    "iso:country":"US",
    "sg:address":"4732 Commons Way",
    "sg:city":"Calabasas",
    "sg:classifiers":[
        {
            "category":"Personal",
            "subcategory":"Nail Salon",
            "type":"Services"
        }
    ],
    "sg:phone":"+1 818 222 7811",
    "sg:postcode":"91302",
    "sg:province":"CA",
    "wof:name":"Nails by Taylor",
    "wof:placetype":"venue"
},
  "geometry": {"coordinates":[-118.644997,34.154598],"type":"Point"}
}