{
  "type": "Feature",
  "properties": {
    "iso:country":"US",
    "sg:address":"500 E Esplanade Dr",
    "sg:city":"Oxnard",
    "sg:classifiers":[
        {
            "category":"Social Services",
            "subcategory":"Adult Care",
            "type":"Services"
        }
    ],
    "sg:phone":"+1 805 485 3884",
    "sg:postcode":"93036",
    "sg:province":"CA",
    "sg:tags":[
        "foster"
    ],
    "wof:name":"Koinonia Foster Homes",
    "wof:placetype":"venue"
},
  "geometry": {"coordinates":[-119.171211,34.229069],"type":"Point"}
}