{
  "type": "Feature",
  "properties": {
    "addr:full":"605 Main St Martinez CA 94553",
    "addr:housenumber":"605",
    "addr:postcode":"94553",
    "addr:street":"Main St",
    "iso:country":"US",
    "sg:address":"605 Main St",
    "sg:city":"Martinez",
    "sg:classifiers":[
        {
            "category":"Shopping",
            "subcategory":"Used Merchandise",
            "type":"Retail Goods"
        }
    ],
    "sg:phone":"+1 925 229 2775",
    "sg:postcode":"94553",
    "sg:province":"CA",
    "sg:tags":[
        "antique"
    ],
    "wof:name":"Crane's Antiques",
    "wof:placetype":"venue"
},
  "geometry": {"coordinates":[-122.137548,38.016838],"type":"Point"}
}