{
  "type": "Feature",
  "properties": {
    "iso:country":"US",
    "sg:address":"4460 Redwood Hwy",
    "sg:city":"San Rafael",
    "sg:classifiers":[
        {
            "category":"Professional",
            "subcategory":"Detective & Security Services",
            "type":"Services"
        }
    ],
    "sg:phone":"+1 415 336 5601",
    "sg:postcode":"94903",
    "sg:province":"CA",
    "sg:tags":[
        "guard",
        "patrol"
    ],
    "wof:name":"J T Executive Protection",
    "wof:placetype":"venue"
},
  "geometry": {"coordinates":[-122.539627,38.01821],"type":"Point"}
}