{
  "type": "Feature",
  "properties": {
    "iso:country":"US",
    "sg:address":"201 Fern St",
    "sg:city":"Santa Cruz",
    "sg:classifiers":[
        {
            "category":"Manufacturing",
            "subcategory":"Metals",
            "type":"Manufacturing & Wholesale Goods"
        }
    ],
    "sg:phone":"+1 831 423 3188",
    "sg:postcode":"95060",
    "sg:province":"CA",
    "sg:tags":[
        "ornamental",
        "work"
    ],
    "sg:website":"www.eachasemetalsmithing.com",
    "wof:name":"Chase Metalsmithing",
    "wof:placetype":"venue"
},
  "geometry": {"coordinates":[-122.032309,36.9858],"type":"Point"}
}