{
  "type": "Feature",
  "properties": {
    "iso:country":"US",
    "sg:address":"5835 Hollister Ave",
    "sg:city":"Goleta",
    "sg:classifiers":[
        {
            "category":"Shopping",
            "subcategory":"Computers & Home Electronics",
            "type":"Retail Goods"
        }
    ],
    "sg:phone":"+1 805 563 9972",
    "sg:postcode":"93117",
    "sg:province":"CA",
    "sg:tags":[
        "software"
    ],
    "wof:name":"Sanity Software",
    "wof:placetype":"venue"
},
  "geometry": {"coordinates":[-119.827109,34.435738],"type":"Point"}
}