{
  "type": "Feature",
  "properties": {
    "iso:country":"US",
    "sg:address":"4965 Cass St",
    "sg:city":"San Diego",
    "sg:classifiers":[
        {
            "category":"Sports & Exercise",
            "subcategory":"Gym",
            "type":"Entertainment"
        }
    ],
    "sg:phone":"+1 858 270 3356",
    "sg:postcode":"92109",
    "sg:province":"CA",
    "sg:tags":[
        "club",
        "health",
        "studio",
        "gymnasium"
    ],
    "wof:name":"Cass Gym",
    "wof:placetype":"venue"
},
  "geometry": {"coordinates":[-117.254256,32.805521],"type":"Point"}
}