{
  "type": "Feature",
  "properties": {
    "iso:country":"US",
    "sg:address":"188 N Rosemead Blvd",
    "sg:city":"Pasadena",
    "sg:classifiers":[
        {
            "category":"Building & Trades",
            "subcategory":"Construction",
            "type":"Services"
        }
    ],
    "sg:phone":"+1 626 358 3145",
    "sg:postcode":"91107",
    "sg:province":"CA",
    "sg:tags":[
        "contractor"
    ],
    "sg:website":"www.changemycabinets.com/",
    "wof:name":"Kitchen Cabinets More and Inc",
    "wof:placetype":"venue"
},
  "geometry": {"coordinates":[-118.07308999999999,34.149656],"type":"Point"}
}