{
  "type": "Feature",
  "properties": {
    "iso:country":"US",
    "sg:address":"12618 W Washington Blvd.",
    "sg:city":"Culver City",
    "sg:classifiers":[
        {
            "category":"Restaurant",
            "type":"Food & Drink"
        }
    ],
    "sg:phone":"+1 310 572 4625",
    "sg:postcode":"90232",
    "sg:province":"CA",
    "sg:tags":[
        "mexican"
    ],
    "wof:name":"Lulu's Fountain Juice Bar",
    "wof:placetype":"venue"
},
  "geometry": {"coordinates":[-118.358976,34.039778],"type":"Point"}
}