{
  "type": "Feature",
  "properties": {
    "iso:country":"US",
    "sg:address":"2290 Ringwood Ave",
    "sg:city":"San Jose",
    "sg:classifiers":[
        {
            "category":"Manufacturing",
            "subcategory":"Metals",
            "type":"Manufacturing & Wholesale Goods"
        }
    ],
    "sg:phone":"+1 408 954 8405",
    "sg:postcode":"95131",
    "sg:province":"CA",
    "sg:tags":[
        "plating",
        "nickel",
        "gold"
    ],
    "wof:name":"PSI",
    "wof:placetype":"venue"
},
  "geometry": {"coordinates":[-121.895742,37.403632],"type":"Point"}
}