{
  "type": "Feature",
  "properties": {
    "iso:country":"US",
    "sg:address":"6505 E Serrano Ave Ste D",
    "sg:city":"Anaheim",
    "sg:classifiers":[
        {
            "category":"Building & Trades",
            "subcategory":"Construction",
            "type":"Services"
        }
    ],
    "sg:phone":"+1 714 921 8033",
    "sg:postcode":"92807",
    "sg:province":"CA",
    "sg:tags":[
        "contractor"
    ],
    "wof:name":"B M W Builders And Contractors",
    "wof:placetype":"venue"
},
  "geometry": {"coordinates":[-117.76055700000001,33.831106],"type":"Point"}
}