{
  "type": "Feature",
  "properties": {
    "addr:full":"4004 3rd St San Francisco CA 94123",
    "addr:housenumber":"4004",
    "addr:postcode":"94123",
    "addr:street":"3Rd St",
    "iso:country":"US",
    "sg:address":"4004 3rd St",
    "sg:city":"San Francisco",
    "sg:classifiers":[
        {
            "category":"Bars & Pubs",
            "type":"Food & Drink"
        },
        {
            "category":"Restaurant",
            "type":"Food & Drink"
        }
    ],
    "sg:phone":"+1 415 282 4003",
    "sg:postcode":"94123",
    "sg:province":"CA",
    "sg:tags":[
        "barbeque"
    ],
    "wof:name":"Sam Jordan's Bar",
    "wof:placetype":"venue"
},
  "geometry": {"coordinates":[-122.388868,37.741058],"type":"Point"}
}