{
  "type": "Feature",
  "properties": {
    "iso:country":"US",
    "sg:address":"610 W Main St",
    "sg:city":"Visalia",
    "sg:classifiers":[
        {
            "category":"Real Estate",
            "subcategory":"Real Estate Services",
            "type":"Services"
        },
        {
            "category":"Real Estate",
            "subcategory":"Real Estate Agent",
            "type":"Services"
        }
    ],
    "sg:phone":"+1 559 627 4008",
    "sg:postcode":"93291",
    "sg:province":"CA",
    "sg:tags":[
        "buyer",
        "broker"
    ],
    "wof:name":"Ray Mannon Coldwell",
    "wof:placetype":"venue"
},
  "geometry": {"coordinates":[-119.297836,36.330156],"type":"Point"}
}