{
  "type": "Feature",
  "properties": {
    "addr:full":"1175 Darlene Dr Santa Cruz CA 95062",
    "addr:housenumber":"1175",
    "addr:postcode":"95062",
    "addr:street":"Darlene Dr",
    "iso:country":"US",
    "sg:address":"1175 Darlene Dr",
    "sg:city":"Santa Cruz",
    "sg:classifiers":[
        {
            "category":"Wholesale",
            "subcategory":"Auto Parts",
            "type":"Manufacturing & Wholesale Goods"
        }
    ],
    "sg:phone":"+1 831 479 7450",
    "sg:postcode":"95062",
    "sg:province":"CA",
    "sg:tags":[
        "oil"
    ],
    "wof:name":"R & J Losee Enterprises",
    "wof:placetype":"venue"
},
  "geometry": {"coordinates":[-121.97792800000001,36.968832],"type":"Point"}
}