{
  "type": "Feature",
  "properties": {
    "addr:full":"1875 Glenrose Ave Sacramento CA 95815",
    "addr:housenumber":"1875",
    "addr:postcode":"95815",
    "addr:street":"Glenrose Ave",
    "iso:country":"US",
    "sg:address":"1875 Glenrose Ave",
    "sg:city":"Sacramento",
    "sg:classifiers":[
        {
            "category":"Shopping",
            "subcategory":"Clothing, Apparel, & Fashions",
            "type":"Retail Goods"
        }
    ],
    "sg:phone":"+1 916 564 7512",
    "sg:postcode":"95815",
    "sg:province":"CA",
    "sg:tags":[
        "family"
    ],
    "wof:name":"Monni Apparel Ltd",
    "wof:placetype":"venue"
},
  "geometry": {"coordinates":[-121.424547,38.614784],"type":"Point"}
}