{
  "type": "Feature",
  "properties": {
    "iso:country":"US",
    "sg:address":"9425 Valley Blvd",
    "sg:city":"Rosemead",
    "sg:classifiers":[
        {
            "category":"Restaurant",
            "type":"Food & Drink"
        }
    ],
    "sg:phone":"+1 626 350 8992",
    "sg:postcode":"91770",
    "sg:province":"CA",
    "sg:tags":[
        "mexican"
    ],
    "wof:name":"Hilario's Mexican Restaurant",
    "wof:placetype":"venue"
},
  "geometry": {"coordinates":[-118.06367299999999,34.081152],"type":"Point"}
}