{
  "type": "Feature",
  "properties": {
    "addr:full":"31141 State Rte 20 Fort Bragg CA 95437",
    "addr:housenumber":"31141",
    "addr:postcode":"95437",
    "addr:street":"State Rte 20",
    "iso:country":"US",
    "sg:address":"31141 State Rte 20",
    "sg:city":"Fort Bragg",
    "sg:classifiers":[
        {
            "category":"Home & Garden",
            "subcategory":"Building Materials",
            "type":"Retail Goods"
        }
    ],
    "sg:phone":"+1 707 964 1234",
    "sg:postcode":"95437",
    "sg:province":"CA",
    "sg:tags":[
        "glass",
        "window",
        "plate"
    ],
    "wof:name":"Windshields For Less",
    "wof:placetype":"venue"
},
  "geometry": {"coordinates":[-123.775475,39.415395],"type":"Point"}
}