{
  "type": "Feature",
  "properties": {
    "addr:full":"1765 S Broadway Santa Maria CA 93454",
    "addr:housenumber":"1765",
    "addr:postcode":"93454",
    "addr:street":"S Broadway",
    "iso:country":"US",
    "sg:address":"1765 S Broadway",
    "sg:city":"Santa Maria",
    "sg:classifiers":[
        {
            "category":"Shopping",
            "subcategory":"Crafts & Fabrics",
            "type":"Retail Goods"
        }
    ],
    "sg:phone":"+1 805 925 1888",
    "sg:postcode":"93454",
    "sg:province":"CA",
    "sg:tags":[
        "material",
        "quilting",
        "supply"
    ],
    "wof:name":"Sophie Ann's Quilts",
    "wof:placetype":"venue"
},
  "geometry": {"coordinates":[-120.43619,34.928438],"type":"Point"}
}