{
  "type": "Feature",
  "properties": {
    "addr:full":"13960 Seal Beach Blvd Seal Beach CA 90740",
    "addr:housenumber":"13960",
    "addr:postcode":"90740",
    "addr:street":"Seal Beach Blvd",
    "iso:country":"US",
    "sg:address":"13960 Seal Beach Blvd",
    "sg:city":"Seal Beach",
    "sg:classifiers":[
        {
            "category":"Building & Trades",
            "subcategory":"Construction",
            "type":"Services"
        }
    ],
    "sg:phone":"+1 562 493 2512",
    "sg:postcode":"90740",
    "sg:province":"CA",
    "sg:tags":[
        "general",
        "commercial",
        "contractor"
    ],
    "wof:name":"Pulsar Development Inc",
    "wof:placetype":"venue"
},
  "geometry": {"coordinates":[-118.07746299999999,33.761869],"type":"Point"}
}