{
  "type": "Feature",
  "properties": {
    "iso:country":"US",
    "sg:address":"30075 Ahern Ave",
    "sg:city":"Union City",
    "sg:classifiers":[
        {
            "category":"Professional",
            "type":"Services"
        }
    ],
    "sg:phone":"+1 510 324 3968",
    "sg:postcode":"94587",
    "sg:province":"CA",
    "wof:name":"P C Ic Inc",
    "wof:placetype":"venue"
},
  "geometry": {"coordinates":[-122.076619,37.607846],"type":"Point"}
}