{
  "type": "Feature",
  "properties": {
    "addr:full":"2576 Scott Blvd Santa Clara CA 95050",
    "addr:housenumber":"2576",
    "addr:postcode":"95050",
    "addr:street":"Scott Blvd",
    "iso:country":"US",
    "sg:address":"2576 Scott Blvd",
    "sg:city":"Santa Clara",
    "sg:classifiers":[
        {
            "category":"Retail",
            "subcategory":"Storage",
            "type":"Services"
        }
    ],
    "sg:phone":"+1 408 855 8544",
    "sg:postcode":"95050",
    "sg:province":"CA",
    "sg:tags":[
        "self"
    ],
    "sg:website":"www.extraspace.com",
    "wof:name":"Extra Space Storage",
    "wof:placetype":"venue"
},
  "geometry": {"coordinates":[-121.95954500000001,37.36779],"type":"Point"}
}