{
  "type": "Feature",
  "properties": {
    "addr:full":"5667 Gibraltar Dr Pleasanton CA 94588",
    "addr:housenumber":"5667",
    "addr:postcode":"94588",
    "addr:street":"Gibraltar Dr",
    "iso:country":"US",
    "sg:address":"5667 Gibraltar Dr",
    "sg:city":"Pleasanton",
    "sg:classifiers":[
        {
            "category":"Utilities",
            "subcategory":"Telephone",
            "type":"Services"
        }
    ],
    "sg:phone":"+1 925 924 8000",
    "sg:postcode":"94588",
    "sg:province":"CA",
    "sg:tags":[
        "communications"
    ],
    "wof:name":"Divine Managed Services",
    "wof:placetype":"venue"
},
  "geometry": {"coordinates":[-121.891769,37.687838],"type":"Point"}
}