{
  "type": "Feature",
  "properties": {
    "iso:country":"US",
    "sg:address":"555 12th St Ste 1250",
    "sg:city":"Oakland",
    "sg:classifiers":[
        {
            "category":"Banks & Credit Unions",
            "subcategory":"Investment Brokerage",
            "type":"Services"
        },
        {
            "category":"Banks & Credit Unions",
            "subcategory":"Financial Services",
            "type":"Services"
        }
    ],
    "sg:phone":"+1 510 587 0950",
    "sg:postcode":"94607",
    "sg:province":"CA",
    "sg:tags":[
        "investing",
        "advisory",
        "planning",
        "retirement",
        "planner"
    ],
    "sg:website":"www.entrustcalifornia.com/oakland/",
    "wof:name":"Entrust Administration Inc",
    "wof:placetype":"venue"
},
  "geometry": {"coordinates":[-122.27532100000001,37.803935],"type":"Point"}
}