{
  "type": "Feature",
  "properties": {
    "addr:full":"2801 Summit St Oakland CA 94609",
    "addr:housenumber":"2801",
    "addr:postcode":"94609",
    "addr:street":"Summit St",
    "iso:country":"US",
    "sg:address":"2801 Summit St",
    "sg:city":"Oakland",
    "sg:classifiers":[
        {
            "category":"Real Estate",
            "subcategory":"Real Estate Operator",
            "type":"Services"
        }
    ],
    "sg:phone":"+1 510 452 2471",
    "sg:postcode":"94609",
    "sg:province":"CA",
    "sg:tags":[
        "apartment"
    ],
    "wof:name":"Summit Crest Apartments",
    "wof:placetype":"venue"
},
  "geometry": {"coordinates":[-122.264999,37.816399],"type":"Point"}
}