{
  "type": "Feature",
  "properties": {
    "addr:full":"1841 Rubenstein Dr Cardiff By The Sea CA 92007",
    "addr:housenumber":"1841",
    "addr:postcode":"92007",
    "addr:street":"Rubenstein Dr",
    "iso:country":"US",
    "sg:address":"1841 Rubenstein Dr",
    "sg:city":"Cardiff By The Sea",
    "sg:classifiers":[
        {
            "category":"Wholesale",
            "subcategory":"Apparel",
            "type":"Manufacturing & Wholesale Goods"
        }
    ],
    "sg:phone":"+1 760 944 0542",
    "sg:postcode":"92007",
    "sg:province":"CA",
    "sg:tags":[
        "clothing"
    ],
    "wof:name":"Frangipani",
    "wof:placetype":"venue"
},
  "geometry": {"coordinates":[-117.283496,33.027256],"type":"Point"}
}