{
  "type": "Feature",
  "properties": {
    "addr:full":"1575 Pioneer Way El Cajon CA 92020",
    "addr:housenumber":"1575",
    "addr:postcode":"92020",
    "addr:street":"Pioneer Way",
    "iso:country":"US",
    "sg:address":"1575 Pioneer Way",
    "sg:city":"El Cajon",
    "sg:classifiers":[
        {
            "category":"Autos & Motor Vehicles",
            "subcategory":"Auto Supplies",
            "type":"Retail Goods"
        }
    ],
    "sg:phone":"+1 619 588 0349",
    "sg:postcode":"92020",
    "sg:province":"CA",
    "sg:tags":[
        "equipment",
        "racing",
        "car",
        "automobile"
    ],
    "wof:name":"Norm Francis Street Rods",
    "wof:placetype":"venue"
},
  "geometry": {"coordinates":[-116.96767800000001,32.813199],"type":"Point"}
}