{
  "type": "Feature",
  "properties": {
    "iso:country":"US",
    "sg:address":"1322 Ross St",
    "sg:city":"Petaluma",
    "sg:classifiers":[
        {
            "category":"Home & Garden",
            "subcategory":"Building Materials",
            "type":"Retail Goods"
        }
    ],
    "sg:phone":"+1 707 778 3880",
    "sg:postcode":"94954",
    "sg:province":"CA",
    "sg:tags":[
        "glass",
        "leaded"
    ],
    "wof:name":"Glass Pedal",
    "wof:placetype":"venue"
},
  "geometry": {"coordinates":[-122.66403699999999,38.268853],"type":"Point"}
}