{
  "type": "Feature",
  "properties": {
    "addr:full":"110 Buck Cir Folsom CA 95630",
    "addr:housenumber":"110",
    "addr:postcode":"95630",
    "addr:street":"Buck Cir",
    "iso:country":"US",
    "sg:address":"110 Buck Cir",
    "sg:city":"Folsom",
    "sg:classifiers":[
        {
            "category":"Restaurant",
            "type":"Food & Drink"
        }
    ],
    "sg:phone":"+1 916 989 3880",
    "sg:postcode":"95630",
    "sg:province":"CA",
    "sg:tags":[
        "school",
        "eating"
    ],
    "wof:name":"Sacramento Grt Wl Chns Schl",
    "wof:placetype":"venue"
},
  "geometry": {"coordinates":[-121.191722,38.686899],"type":"Point"}
}