{
  "type": "Feature",
  "properties": {
    "addr:full":"3823 International Blvd Oakland CA 94601",
    "addr:housenumber":"3823",
    "addr:postcode":"94601",
    "addr:street":"International Blvd",
    "iso:country":"US",
    "sg:address":"3823 International Blvd",
    "sg:city":"Oakland",
    "sg:classifiers":[
        {
            "category":"Personal",
            "subcategory":"Beauty Salon",
            "type":"Services"
        }
    ],
    "sg:phone":"+1 510 534 5594",
    "sg:postcode":"94601",
    "sg:province":"CA",
    "sg:tags":[
        "manicuring"
    ],
    "wof:name":"International Cathy Nails",
    "wof:placetype":"venue"
},
  "geometry": {"coordinates":[-122.21919699999999,37.774389],"type":"Point"}
}