{
  "type": "Feature",
  "properties": {
    "iso:country":"US",
    "sg:address":"555 W Arrow Hwy",
    "sg:city":"Claremont",
    "sg:classifiers":[
        {
            "category":"Professional",
            "subcategory":"Engineering",
            "type":"Services"
        },
        {
            "category":"Utilities",
            "subcategory":"Fuel Oil & Lpg",
            "type":"Services"
        }
    ],
    "sg:phone":"+1 909 447 3600",
    "sg:postcode":"91711",
    "sg:province":"CA",
    "sg:tags":[
        "consultant",
        "petroleum",
        "engineer"
    ],
    "wof:name":"Tp Usa",
    "wof:placetype":"venue"
},
  "geometry": {"coordinates":[-117.722612,34.090481],"type":"Point"}
}