{
  "type": "Feature",
  "properties": {
    "iso:country":"US",
    "sg:address":"2033 Taraval St.",
    "sg:city":"San Francisco",
    "sg:classifiers":[
        {
            "category":"Personal",
            "subcategory":"Beauty Salon",
            "type":"Services"
        }
    ],
    "sg:phone":"+1 415 664 6336",
    "sg:postcode":"94116",
    "sg:province":"CA",
    "sg:tags":[
        "hair"
    ],
    "wof:name":"Taraval Hair Design",
    "wof:placetype":"venue"
},
  "geometry": {"coordinates":[-122.488141,37.742255],"type":"Point"}
}