{
  "type": "Feature",
  "properties": {
    "addr:full":"13615 Bear Valley Rd Victorville CA 92392",
    "addr:housenumber":"13615",
    "addr:postcode":"92392",
    "addr:street":"Bear Valley Rd",
    "iso:country":"US",
    "sg:address":"13615 Bear Valley Rd",
    "sg:city":"Victorville",
    "sg:classifiers":[
        {
            "category":"Social Services",
            "subcategory":"Child Care",
            "type":"Services"
        },
        {
            "category":"Education",
            "subcategory":"Preschool",
            "type":"Public Place"
        }
    ],
    "sg:phone":"+1 760 949 8539",
    "sg:postcode":"92392",
    "sg:province":"CA",
    "sg:tags":[
        "kindergarten",
        "nursery",
        "day"
    ],
    "sg:website":"http://www.kindercare.com/our-centers/center-details/301854/?cid=YP_KC301854",
    "wof:name":"KinderCare of Victorville",
    "wof:placetype":"venue"
},
  "geometry": {"coordinates":[-117.366927,34.47038],"type":"Point"}
}