{
  "type": "Feature",
  "properties": {
    "iso:country":"US",
    "sg:address":"673 2nd Ave",
    "sg:city":"San Bruno",
    "sg:classifiers":[
        {
            "category":"Wholesale",
            "subcategory":"Home Furnishings",
            "type":"Manufacturing & Wholesale Goods"
        }
    ],
    "sg:phone":"+1 650 589 0943",
    "sg:postcode":"94066",
    "sg:province":"CA",
    "sg:tags":[
        "curtain",
        "drapery"
    ],
    "wof:name":"Tamara's Draperies",
    "wof:placetype":"venue"
},
  "geometry": {"coordinates":[-122.40872,37.627065],"type":"Point"}
}