{
  "type": "Feature",
  "properties": {
    "iso:country":"US",
    "sg:address":"26400 Gading Rd",
    "sg:city":"Hayward",
    "sg:classifiers":[
        {
            "category":"Education",
            "subcategory":"School",
            "type":"Public Place"
        }
    ],
    "sg:phone":"+1 510 785 1313",
    "sg:postcode":"94544",
    "sg:province":"CA",
    "sg:tags":[
        "high",
        "middle",
        "elementary"
    ],
    "wof:name":"Bayside Seventh-Day Adventist Christian School",
    "wof:placetype":"venue"
},
  "geometry": {"coordinates":[-122.081001,37.641998],"type":"Point"}
}