{
  "type": "Feature",
  "properties": {
    "addr:full":"1061 Deltaview Ln Pittsburg CA 94565",
    "addr:housenumber":"1061",
    "addr:postcode":"94565",
    "addr:street":"Deltaview Ln",
    "iso:country":"US",
    "sg:address":"1061 Deltaview Ln",
    "sg:city":"Pittsburg",
    "sg:classifiers":[
        {
            "category":"Wholesale",
            "subcategory":"Durable Goods & Equipment",
            "type":"Manufacturing & Wholesale Goods"
        }
    ],
    "sg:phone":"+1 925 250 6867",
    "sg:postcode":"94565",
    "sg:province":"CA",
    "wof:name":"Pol",
    "wof:placetype":"venue"
},
  "geometry": {"coordinates":[-121.954824,38.027682],"type":"Point"}
}