{
  "type": "Feature",
  "properties": {
    "addr:full":"25475 Clough Rd Escalon CA 95320",
    "addr:housenumber":"25475",
    "addr:postcode":"95320",
    "addr:street":"Clough Rd",
    "iso:country":"US",
    "sg:address":"25475 Clough Rd",
    "sg:city":"Escalon",
    "sg:classifiers":[
        {
            "category":"Wholesale",
            "subcategory":"Machinery & Supplies",
            "type":"Manufacturing & Wholesale Goods"
        }
    ],
    "sg:phone":"+1 209 838 6080",
    "sg:postcode":"95320",
    "sg:province":"CA",
    "sg:tags":[
        "equipment",
        "dairy"
    ],
    "wof:name":"San Joaquin Dairy Svc",
    "wof:placetype":"venue"
},
  "geometry": {"coordinates":[-120.99626000000001,37.780318],"type":"Point"}
}