{
  "type": "Feature",
  "properties": {
    "iso:country":"US",
    "sg:address":"1391 Woodland Ave",
    "sg:city":"Menlo Park",
    "sg:classifiers":[
        {
            "category":"Building & Trades",
            "subcategory":"Landscaping Services",
            "type":"Services"
        }
    ],
    "sg:phone":"+1 650 853 0443",
    "sg:postcode":"94025",
    "sg:province":"CA",
    "wof:name":"Creekside Landscaping Inc",
    "wof:placetype":"venue"
},
  "geometry": {"coordinates":[-122.146326,37.457406],"type":"Point"}
}