{
  "type": "Feature",
  "properties": {
    "iso:country":"US",
    "sg:address":"4311 San Pablo Cir",
    "sg:city":"Yorba Linda",
    "sg:classifiers":[
        {
            "category":"Shopping",
            "subcategory":"Bicycles & Sporting Goods",
            "type":"Retail Goods"
        }
    ],
    "sg:phone":"+1 714 996 7678",
    "sg:postcode":"92886",
    "sg:province":"CA",
    "wof:name":"Ergonomic Resources",
    "wof:placetype":"venue"
},
  "geometry": {"coordinates":[-117.823345,33.898592],"type":"Point"}
}