{
  "type": "Feature",
  "properties": {
    "addr:full":"21550 Oxnard St Fl 3 Woodland Hills CA 91367",
    "addr:housenumber":"21550;3",
    "addr:postcode":"91367",
    "addr:street":"Oxnard St",
    "iso:country":"US",
    "sg:address":"21550 Oxnard St Fl 3",
    "sg:city":"Woodland Hills",
    "sg:classifiers":[
        {
            "category":"Professional",
            "subcategory":"Lawyer & Legal Services",
            "type":"Services"
        }
    ],
    "sg:phone":"+1 818 340 4479",
    "sg:postcode":"91367",
    "sg:province":"CA",
    "wof:name":"Sirkin and Sirkin",
    "wof:placetype":"venue"
},
  "geometry": {"coordinates":[-118.59982599999999,34.178906],"type":"Point"}
}