{
  "type": "Feature",
  "properties": {
    "addr:full":"430 Main St Placerville CA 95667",
    "addr:housenumber":"430",
    "addr:postcode":"95667",
    "addr:street":"Main St",
    "iso:country":"US",
    "sg:address":"430 Main St",
    "sg:city":"Placerville",
    "sg:classifiers":[
        {
            "category":"Shopping",
            "subcategory":"Used Merchandise",
            "type":"Retail Goods"
        }
    ],
    "sg:phone":"+1 530 642 2800",
    "sg:postcode":"95667",
    "sg:province":"CA",
    "wof:name":"Annies Antiques",
    "wof:placetype":"venue"
},
  "geometry": {"coordinates":[-120.800337,38.729294],"type":"Point"}
}