{
  "type": "Feature",
  "properties": {
    "iso:country":"US",
    "sg:address":"2208 Kendree St",
    "sg:city":"Antioch",
    "sg:classifiers":[
        {
            "category":"Organizations",
            "subcategory":"Religious Organization",
            "type":"Services"
        }
    ],
    "sg:phone":"+1 925 757 1837",
    "sg:postcode":"94509",
    "sg:province":"CA",
    "sg:tags":[
        "church"
    ],
    "wof:name":"First Assembly Of God",
    "wof:placetype":"venue"
},
  "geometry": {"coordinates":[-121.847152,38.004615],"type":"Point"}
}