{
  "type": "Feature",
  "properties": {
    "addr:full":"17309 Pioneer Blvd Artesia CA 90701",
    "addr:housenumber":"17309",
    "addr:postcode":"90701",
    "addr:street":"Pioneer Blvd",
    "iso:country":"US",
    "sg:address":"17309 Pioneer Blvd",
    "sg:city":"Artesia",
    "sg:classifiers":[
        {
            "category":"Shopping",
            "type":"Retail Goods"
        }
    ],
    "sg:phone":"+1 562 246 1688",
    "sg:postcode":"90701",
    "sg:province":"CA",
    "sg:tags":[
        "telephone",
        "cellular"
    ],
    "wof:name":"G P Commnications",
    "wof:placetype":"venue"
},
  "geometry": {"coordinates":[-118.08237,33.874222],"type":"Point"}
}