{
  "type": "Feature",
  "properties": {
    "iso:country":"US",
    "sg:address":"2808 Lafayette Rd",
    "sg:city":"Newport Beach",
    "sg:classifiers":[
        {
            "category":"Real Estate",
            "subcategory":"Real Estate Agent",
            "type":"Services"
        }
    ],
    "sg:phone":"+1 949 723 0050",
    "sg:postcode":"92663",
    "sg:province":"CA",
    "sg:tags":[
        "consultant",
        "commercial"
    ],
    "wof:name":"Elden",
    "wof:placetype":"venue"
},
  "geometry": {"coordinates":[-117.927997,33.613557],"type":"Point"}
}