{
  "type": "Feature",
  "properties": {
    "iso:country":"US",
    "sg:address":"6 Casa Grande Dr",
    "sg:city":"Red Bluff",
    "sg:classifiers":[
        {
            "category":"Manufacturing",
            "subcategory":"Toys & Sporting Goods",
            "type":"Manufacturing & Wholesale Goods"
        }
    ],
    "sg:phone":"+1 530 527 4936",
    "sg:postcode":"96080",
    "sg:province":"CA",
    "sg:tags":[
        "product",
        "wood",
        "mfg"
    ],
    "wof:name":"Barbs Business",
    "wof:placetype":"venue"
},
  "geometry": {"coordinates":[-122.21062499999999,40.203417],"type":"Point"}
}