{
  "type": "Feature",
  "properties": {
    "iso:country":"US",
    "sg:address":"2207 Pacific Coast Hwy",
    "sg:city":"Lomita",
    "sg:classifiers":[
        {
            "category":"Health Services",
            "subcategory":"Dentist",
            "type":"Services"
        }
    ],
    "sg:phone":"+1 310 534 2633",
    "sg:postcode":"90717",
    "sg:province":"CA",
    "wof:name":"Pch Dental",
    "wof:placetype":"venue"
},
  "geometry": {"coordinates":[-118.32,33.789398],"type":"Point"}
}