{
  "type": "Feature",
  "properties": {
    "addr:full":"151 Seadrift Rd Stinson Beach CA 94970",
    "addr:housenumber":"151",
    "addr:postcode":"94970",
    "addr:street":"Seadrift Rd",
    "iso:country":"US",
    "sg:address":"151 Seadrift Rd",
    "sg:city":"Stinson Beach",
    "sg:classifiers":[
        {
            "category":"Professional",
            "subcategory":"Lawyer & Legal Services",
            "type":"Services"
        }
    ],
    "sg:phone":"+1 415 868 2251",
    "sg:postcode":"94970",
    "sg:province":"CA",
    "sg:tags":[
        "attorney"
    ],
    "wof:name":"Waldman & Yolles",
    "wof:placetype":"venue"
},
  "geometry": {"coordinates":[-122.667976,37.907181],"type":"Point"}
}