{
  "type": "Feature",
  "properties": {
    "addr:full":"Crocker Galleria 50 Post St San Francisco CA 94104",
    "addr:housenumber":"50",
    "addr:postcode":"94104",
    "addr:street":"Galleria;Post St",
    "iso:country":"US",
    "sg:address":"Crocker Galleria 50 Post St",
    "sg:city":"San Francisco",
    "sg:classifiers":[
        {
            "category":"Food & Beverages",
            "subcategory":"Candy",
            "type":"Retail Goods"
        }
    ],
    "sg:phone":"+1 415 398 4847",
    "sg:postcode":"94104",
    "sg:province":"CA",
    "sg:tags":[
        "store"
    ],
    "wof:name":"Naturally Edible",
    "wof:placetype":"venue"
},
  "geometry": {"coordinates":[-122.40285,37.789023],"type":"Point"}
}