{
  "type": "Feature",
  "properties": {
    "addr:full":"610 Newport Center Dr Newport Beach CA 92660",
    "addr:housenumber":"610",
    "addr:postcode":"92660",
    "addr:street":"Newport Center Dr",
    "iso:country":"US",
    "sg:address":"610 Newport Center Dr",
    "sg:city":"Newport Beach",
    "sg:classifiers":[
        {
            "category":"Professional",
            "subcategory":"Lawyer & Legal Services",
            "type":"Services"
        }
    ],
    "sg:phone":"+1 949 640 5700",
    "sg:postcode":"92660",
    "sg:province":"CA",
    "sg:tags":[
        "attorney"
    ],
    "wof:name":"Holly Akhlaghi Law Offices",
    "wof:placetype":"venue"
},
  "geometry": {"coordinates":[-117.873126,33.61841],"type":"Point"}
}