{
  "type": "Feature",
  "properties": {
    "addr:full":"115 Torrance Blvd Redondo Beach CA 90277",
    "addr:housenumber":"115",
    "addr:postcode":"90277",
    "addr:street":"Torrance Blvd",
    "iso:country":"US",
    "sg:address":"115 Torrance Blvd",
    "sg:city":"Redondo Beach",
    "sg:classifiers":[
        {
            "category":"Real Estate",
            "subcategory":"Real Estate Agent",
            "type":"Services"
        }
    ],
    "sg:phone":"+1 310 798 9154",
    "sg:postcode":"90277",
    "sg:province":"CA",
    "sg:tags":[
        "management"
    ],
    "wof:name":"Jamison Management Co",
    "wof:placetype":"venue"
},
  "geometry": {"coordinates":[-118.38749799999999,33.838307],"type":"Point"}
}