{
  "type": "Feature",
  "properties": {
    "addr:full":"21301 Ventura Blvd Woodland Hills CA 91364",
    "addr:housenumber":"21301",
    "addr:postcode":"91364",
    "addr:street":"Ventura Blvd",
    "iso:country":"US",
    "sg:address":"21301 Ventura Blvd",
    "sg:city":"Woodland Hills",
    "sg:classifiers":[
        {
            "category":"Retail",
            "subcategory":"Auto Repair",
            "type":"Services"
        }
    ],
    "sg:phone":"+1 818 703 8580",
    "sg:postcode":"91364",
    "sg:province":"CA",
    "sg:tags":[
        "body",
        "shop"
    ],
    "sg:website":"www.holmesbodyshop.com",
    "wof:name":"Holmes Body Shop",
    "wof:placetype":"venue"
},
  "geometry": {"coordinates":[-118.596001,34.1675],"type":"Point"}
}