{
  "type": "Feature",
  "properties": {
    "iso:country":"US",
    "sg:address":"370 E Rowland St",
    "sg:city":"Covina",
    "sg:classifiers":[
        {
            "category":"Real Estate",
            "subcategory":"Real Estate Agent",
            "type":"Services"
        }
    ],
    "sg:phone":"+1 626 332 2978",
    "sg:postcode":"91723",
    "sg:province":"CA",
    "wof:name":"Mc Intyre Builders Inc",
    "wof:placetype":"venue"
},
  "geometry": {"coordinates":[-117.883789,34.079026],"type":"Point"}
}