{
  "type": "Feature",
  "properties": {
    "addr:full":"370 E Rowland St Covina CA 91723",
    "addr:housenumber":"370",
    "addr:postcode":"91723",
    "addr:street":"E Rowland St",
    "iso:country":"US",
    "sg:address":"370 E Rowland St",
    "sg:city":"Covina",
    "sg:classifiers":[
        {
            "category":"Real Estate",
            "subcategory":"Real Estate Agent",
            "type":"Services"
        }
    ],
    "sg:phone":"+1 626 332 2978",
    "sg:postcode":"91723",
    "sg:province":"CA",
    "wof:name":"Mc Intyre Builders Inc",
    "wof:placetype":"venue"
},
  "geometry": {"coordinates":[-117.88378899999999,34.079026],"type":"Point"}
}