{
  "type": "Feature",
  "properties": {
    "addr:full":"310 W el Norte Pkwy Escondido CA 92026",
    "addr:housenumber":"310",
    "addr:postcode":"92026",
    "addr:street":"W El Norte Pkwy",
    "iso:country":"US",
    "sg:address":"310 W el Norte Pkwy",
    "sg:city":"Escondido",
    "sg:classifiers":[
        {
            "category":"Restaurant",
            "type":"Food & Drink"
        }
    ],
    "sg:phone":"+1 760 740 0737",
    "sg:postcode":"92026",
    "sg:province":"CA",
    "sg:tags":[
        "parlor",
        "ice",
        "cream"
    ],
    "sg:website":"www.dairyqueen.com",
    "wof:name":"Dairy Queen",
    "wof:placetype":"venue"
},
  "geometry": {"coordinates":[-117.094358,33.140588],"type":"Point"}
}