{
  "type": "Feature",
  "properties": {
    "addr:full":"32103 Spring Hill Ct Coarsegold CA 93614",
    "addr:housenumber":"32103",
    "addr:postcode":"93614",
    "addr:street":"Spring Hill Ct",
    "iso:country":"US",
    "sg:address":"32103 Spring Hill Ct",
    "sg:city":"Coarsegold",
    "sg:classifiers":[
        {
            "category":"Manufacturing",
            "subcategory":"Retail Goods",
            "type":"Manufacturing & Wholesale Goods"
        }
    ],
    "sg:phone":"+1 559 658 5413",
    "sg:postcode":"93614",
    "sg:province":"CA",
    "sg:tags":[
        "manufacturer"
    ],
    "wof:name":"Yosemite Teddy Bear Factory",
    "wof:placetype":"venue"
},
  "geometry": {"coordinates":[-119.73424799999999,37.214388],"type":"Point"}
}