{
  "type": "Feature",
  "properties": {
    "iso:country":"US",
    "sg:address":"536 Whiting St",
    "sg:city":"Grass Valley",
    "sg:classifiers":[
        {
            "category":"Arts & Performance",
            "subcategory":"Theater",
            "type":"Entertainment"
        }
    ],
    "sg:phone":"+1 530 274 2418",
    "sg:postcode":"95945",
    "sg:province":"CA",
    "sg:tags":[
        "live",
        "music"
    ],
    "sg:website":"www.mywayproductions.com",
    "wof:name":"My Way Productions",
    "wof:placetype":"venue"
},
  "geometry": {"coordinates":[-121.066169,39.208655],"type":"Point"}
}