{
  "type": "Feature",
  "properties": {
    "iso:country":"US",
    "sg:address":"305 N Willowbrook Ave",
    "sg:city":"Compton",
    "sg:classifiers":[
        {
            "category":"Transit Center",
            "subcategory":"Passenger",
            "type":"Transportation"
        },
        {
            "category":"Bus Station",
            "type":"Transportation"
        },
        {
            "category":"Local Transit",
            "type":"Transportation"
        }
    ],
    "sg:phone":"+1 310 632 5310",
    "sg:postcode":"90220",
    "sg:province":"CA",
    "sg:tags":[
        "line",
        "agency",
        "ticket",
        "public"
    ],
    "sg:website":"http://www.greyhound.com",
    "wof:name":"Greyhound Bus Lines",
    "wof:placetype":"venue"
},
  "geometry": {"coordinates":[-118.22448900000001,33.897572],"type":"Point"}
}