{
  "type": "Feature",
  "properties": {
    "addr:full":"11851 Auburn Ave Yucaipa CA 92399",
    "addr:housenumber":"11851",
    "addr:postcode":"92399",
    "addr:street":"Auburn Ave",
    "iso:country":"US",
    "sg:address":"11851 Auburn Ave",
    "sg:city":"Yucaipa",
    "sg:classifiers":[
        {
            "category":"Government",
            "subcategory":"Office",
            "type":"Public Place"
        }
    ],
    "sg:phone":"+1 909 797 8109",
    "sg:postcode":"92399",
    "sg:province":"CA",
    "sg:tags":[
        "stenographers-public"
    ],
    "wof:name":"Vicki's Medical Transcription",
    "wof:placetype":"venue"
},
  "geometry": {"coordinates":[-117.033126,34.039052],"type":"Point"}
}