{
  "type": "Feature",
  "properties": {
    "addr:full":"10919 Goss St Sun Valley CA 91352",
    "addr:housenumber":"10919",
    "addr:postcode":"91352",
    "addr:street":"Goss St",
    "iso:country":"US",
    "sg:address":"10919 Goss St",
    "sg:city":"Sun Valley",
    "sg:classifiers":[
        {
            "category":"Social Services",
            "subcategory":"Adult Care",
            "type":"Services"
        }
    ],
    "sg:phone":"+1 818 504 2645",
    "sg:postcode":"91352",
    "sg:province":"CA",
    "sg:tags":[
        "home",
        "residential"
    ],
    "wof:name":"Anne's Home",
    "wof:placetype":"venue"
},
  "geometry": {"coordinates":[-118.369097,34.229757],"type":"Point"}
}