{
  "type": "Feature",
  "properties": {
    "addr:full":"4695 MacArthur Ct Ste 1000 Newport Beach CA 92660",
    "addr:housenumber":"4695",
    "addr:postcode":"92660",
    "addr:street":"Macarthur Ct Ste 1000",
    "iso:country":"US",
    "sg:address":"4695 MacArthur Ct Ste 1000",
    "sg:city":"Newport Beach",
    "sg:classifiers":[
        {
            "category":"Banks & Credit Unions",
            "subcategory":"Financial Services",
            "type":"Services"
        }
    ],
    "sg:phone":"+1 949 660 1717",
    "sg:postcode":"92660",
    "sg:province":"CA",
    "sg:tags":[
        "advising"
    ],
    "wof:name":"Mass Mutual",
    "wof:placetype":"venue"
},
  "geometry": {"coordinates":[-117.862551,33.669801],"type":"Point"}
}