{
  "type": "Feature",
  "properties": {
    "iso:country":"US",
    "sg:address":"17100 Ventura Blvd",
    "sg:city":"Encino",
    "sg:classifiers":[
        {
            "category":"Real Estate",
            "subcategory":"Real Estate Agent",
            "type":"Services"
        }
    ],
    "sg:phone":"+1 818 990 1335",
    "sg:postcode":"91316",
    "sg:province":"CA",
    "sg:tags":[
        "consultant"
    ],
    "wof:name":"Marv Fagenson Investments",
    "wof:placetype":"venue"
},
  "geometry": {"coordinates":[-118.50850699999999,34.160672],"type":"Point"}
}