{
  "type": "Feature",
  "properties": {
    "addr:full":"412 34th Ave Santa Cruz CA 95062",
    "addr:housenumber":"412",
    "addr:postcode":"95062",
    "addr:street":"34Th Ave",
    "iso:country":"US",
    "sg:address":"412 34th Ave",
    "sg:city":"Santa Cruz",
    "sg:classifiers":[
        {
            "category":"Building & Trades",
            "subcategory":"Construction",
            "type":"Services"
        }
    ],
    "sg:phone":"+1 831 479 1050",
    "sg:postcode":"95062",
    "sg:province":"CA",
    "sg:tags":[
        "foundation",
        "drilling"
    ],
    "wof:name":"Dollar Drilling & Construction",
    "wof:placetype":"venue"
},
  "geometry": {"coordinates":[-121.971206,36.960729],"type":"Point"}
}