{
  "type": "Feature",
  "properties": {
    "addr:full":"717 Brockton St El Cajon CA 92020",
    "addr:housenumber":"717",
    "addr:postcode":"92020",
    "addr:street":"Brockton St",
    "iso:country":"US",
    "sg:address":"717 Brockton St",
    "sg:city":"El Cajon",
    "sg:classifiers":[
        {
            "category":"Banks & Credit Unions",
            "subcategory":"Financial Services",
            "type":"Services"
        }
    ],
    "sg:phone":"+1 619 713 2013",
    "sg:postcode":"92020",
    "sg:province":"CA",
    "sg:tags":[
        "broker",
        "mortgage"
    ],
    "wof:name":"Providence Mortgage Planners",
    "wof:placetype":"venue"
},
  "geometry": {"coordinates":[-116.99545999999999,32.804031],"type":"Point"}
}