{
  "type": "Feature",
  "properties": {
    "addr:full":"1725 Novato Blvd Novato CA 94947",
    "addr:housenumber":"1725",
    "addr:postcode":"94947",
    "addr:street":"Novato Blvd",
    "iso:country":"US",
    "sg:address":"1725 Novato Blvd",
    "sg:city":"Novato",
    "sg:classifiers":[
        {
            "category":"Building & Trades",
            "subcategory":"Construction",
            "type":"Services"
        }
    ],
    "sg:phone":"+1 415 892 7799",
    "sg:postcode":"94947",
    "sg:province":"CA",
    "sg:tags":[
        "painter"
    ],
    "wof:name":"Biazar Enterprises",
    "wof:placetype":"venue"
},
  "geometry": {"coordinates":[-122.582425,38.107663],"type":"Point"}
}