{
  "type": "Feature",
  "properties": {
    "iso:country":"US",
    "sg:address":"200 Whitney Pl",
    "sg:city":"Fremont",
    "sg:classifiers":[
        {
            "category":"Education",
            "subcategory":"Vocational School",
            "type":"Public Place"
        }
    ],
    "sg:phone":"+1 510 490 6900",
    "sg:postcode":"94539",
    "sg:province":"CA",
    "sg:website":"www.sequoiainstitute.com",
    "wof:name":"Wyo Tech",
    "wof:placetype":"venue"
},
  "geometry": {"coordinates":[-121.919731,37.469615],"type":"Point"}
}