{
  "type": "Feature",
  "properties": {
    "iso:country":"US",
    "sg:address":"Balboa Park 2001 Pan American Plz",
    "sg:city":"San Diego",
    "sg:classifiers":[
        {
            "category":"Museum",
            "type":"Entertainment"
        }
    ],
    "sg:phone":"+1 619 234 8291",
    "sg:postcode":"92101",
    "sg:province":"CA",
    "sg:website":"www.sandiegoairandspace.org/",
    "wof:name":"San Diego Air & Space Museum",
    "wof:placetype":"venue"
},
  "geometry": {"coordinates":[-117.154752,32.725798],"type":"Point"}
}