{
  "type": "Feature",
  "properties": {
    "addr:full":"68366 Perez Rd Cathedral City CA 92234",
    "addr:housenumber":"68366",
    "addr:postcode":"92234",
    "addr:street":"Perez Rd",
    "iso:country":"US",
    "sg:address":"68366 Perez Rd",
    "sg:city":"Cathedral City",
    "sg:classifiers":[
        {
            "category":"Cinema",
            "subcategory":"Movie Rental",
            "type":"Entertainment"
        }
    ],
    "sg:phone":"+1 760 321 1033",
    "sg:postcode":"92234",
    "sg:province":"CA",
    "sg:tags":[
        "video",
        "game",
        "disc",
        "leasing",
        "tape"
    ],
    "wof:name":"Perez Image Video",
    "wof:placetype":"venue"
},
  "geometry": {"coordinates":[-116.469228,33.785035],"type":"Point"}
}