{
  "type": "Feature",
  "properties": {
    "iso:country":"US",
    "sg:address":"21853 Hidden Acres Rd",
    "sg:city":"Redding",
    "sg:classifiers":[
        {
            "category":"Home & Garden",
            "subcategory":"Garden Supply",
            "type":"Retail Goods"
        }
    ],
    "sg:phone":"+1 530 549 5723",
    "sg:postcode":"96003",
    "sg:province":"CA",
    "sg:tags":[
        "fountain",
        "display"
    ],
    "wof:name":"Just Ponden",
    "wof:placetype":"venue"
},
  "geometry": {"coordinates":[-122.24788700000001,40.629376],"type":"Point"}
}