{
  "type": "Feature",
  "properties": {
    "addr:full":"2731 Nugget Ave Lake Isabella CA 93240",
    "addr:housenumber":"2731",
    "addr:postcode":"93240",
    "addr:street":"Nugget Ave",
    "iso:country":"US",
    "sg:address":"2731 Nugget Ave",
    "sg:city":"Lake Isabella",
    "sg:classifiers":[
        {
            "category":"Health Services",
            "subcategory":"Doctor",
            "type":"Services"
        }
    ],
    "sg:phone":"+1 760 379 3412",
    "sg:postcode":"93240",
    "sg:province":"CA",
    "sg:tags":[
        "clinic"
    ],
    "wof:name":"College Health Clinic",
    "wof:placetype":"venue"
},
  "geometry": {"coordinates":[-118.473669,35.626661],"type":"Point"}
}