{
  "type": "Feature",
  "properties": {
    "addr:full":"29395 Agoura Rd Agoura Hills CA 91301",
    "addr:housenumber":"29395",
    "addr:postcode":"91301",
    "addr:street":"Agoura Rd",
    "iso:country":"US",
    "sg:address":"29395 Agoura Rd",
    "sg:city":"Agoura Hills",
    "sg:classifiers":[
        {
            "category":"Wholesale",
            "subcategory":"Medical Equipment & Supplies",
            "type":"Manufacturing & Wholesale Goods"
        }
    ],
    "sg:phone":"+1 818 991 4001",
    "sg:postcode":"91301",
    "sg:province":"CA",
    "sg:tags":[
        "physician",
        "surgeon"
    ],
    "wof:name":"In Care DME",
    "wof:placetype":"venue"
},
  "geometry": {"coordinates":[-118.771503,34.145235],"type":"Point"}
}