{
  "type": "Feature",
  "properties": {
    "iso:country":"US",
    "sg:address":"9730 Reseda Blvd",
    "sg:city":"Northridge",
    "sg:classifiers":[
        {
            "category":"Real Estate",
            "subcategory":"Real Estate Operator",
            "type":"Services"
        }
    ],
    "sg:phone":"+1 818 998 3977",
    "sg:postcode":"91324",
    "sg:province":"CA",
    "sg:tags":[
        "apartment"
    ],
    "wof:name":"Windscape Apartments",
    "wof:placetype":"venue"
},
  "geometry": {"coordinates":[-118.53609,34.246379],"type":"Point"}
}