{
  "type": "Feature",
  "properties": {
    "iso:country":"US",
    "sg:address":"4126 S Demaree St",
    "sg:city":"Visalia",
    "sg:classifiers":[
        {
            "category":"Health Services",
            "subcategory":"Chiropractor",
            "type":"Services"
        }
    ],
    "sg:phone":"+1 559 733 7711",
    "sg:postcode":"93277",
    "sg:province":"CA",
    "sg:tags":[
        "chiropractic"
    ],
    "wof:name":"Spineworks Chiropractic Center",
    "wof:placetype":"venue"
},
  "geometry": {"coordinates":[-119.331444,36.29337],"type":"Point"}
}