{
  "type": "Feature",
  "properties": {
    "addr:full":"11174 Atlantic Ave Lynwood CA 90262",
    "addr:housenumber":"11174",
    "addr:postcode":"90262",
    "addr:street":"Atlantic Ave",
    "iso:country":"US",
    "sg:address":"11174 Atlantic Ave",
    "sg:city":"Lynwood",
    "sg:classifiers":[
        {
            "category":"Home & Garden",
            "subcategory":"Furniture",
            "type":"Retail Goods"
        }
    ],
    "sg:phone":"+1 310 639 4378",
    "sg:postcode":"90262",
    "sg:province":"CA",
    "wof:name":"J & S Furniture",
    "wof:placetype":"venue"
},
  "geometry": {"coordinates":[-118.185035,33.927142],"type":"Point"}
}