{
  "type": "Feature",
  "properties": {
    "iso:country":"US",
    "sg:address":"303 W Washington Ave",
    "sg:city":"Sunnyvale",
    "sg:classifiers":[
        {
            "category":"Personal",
            "subcategory":"Beauty Salon",
            "type":"Services"
        }
    ],
    "sg:phone":"+1 408 245 6772",
    "sg:postcode":"94086",
    "sg:province":"CA",
    "sg:tags":[
        "manicuring"
    ],
    "wof:name":"Shiny Nails",
    "wof:placetype":"venue"
},
  "geometry": {"coordinates":[-122.032363,37.37646],"type":"Point"}
}