{
  "type": "Feature",
  "properties": {
    "addr:full":"400 W Florence Ave Inglewood CA 90301",
    "addr:housenumber":"400",
    "addr:postcode":"90301",
    "addr:street":"W Florence Ave",
    "iso:country":"US",
    "sg:address":"400 W Florence Ave",
    "sg:city":"Inglewood",
    "sg:classifiers":[
        {
            "category":"Organizations",
            "subcategory":"Religious Organization",
            "type":"Services"
        }
    ],
    "sg:phone":"+1 310 342 3700",
    "sg:postcode":"90301",
    "sg:province":"CA",
    "sg:tags":[
        "church"
    ],
    "wof:name":"Grace Place",
    "wof:placetype":"venue"
},
  "geometry": {"coordinates":[-118.363963,33.965783],"type":"Point"}
}