{
  "type": "Feature",
  "properties": {
    "addr:full":"2288 Firestone Boulevard Los Angeles CA 90002",
    "addr:housenumber":"2288",
    "addr:postcode":"90002",
    "addr:street":"Firestone Boulevard",
    "iso:country":"US",
    "sg:address":"2288 Firestone Boulevard",
    "sg:city":"Los Angeles",
    "sg:classifiers":[
        {
            "category":"Professional",
            "subcategory":"Computer Services",
            "type":"Services"
        }
    ],
    "sg:phone":"+1 323 587 1723",
    "sg:postcode":"90002",
    "sg:province":"CA",
    "sg:tags":[
        "repair"
    ],
    "wof:name":"Elektra Tv & Computer Service",
    "wof:placetype":"venue"
},
  "geometry": {"coordinates":[-118.230931,33.95756],"type":"Point"}
}