{
  "type": "Feature",
  "properties": {
    "addr:full":"870 Market St Ste 547 San Francisco CA 94102",
    "addr:housenumber":"870",
    "addr:postcode":"94102",
    "addr:street":"Market St Ste 547",
    "iso:country":"US",
    "sg:address":"870 Market St Ste 547",
    "sg:city":"San Francisco",
    "sg:classifiers":[
        {
            "category":"Professional",
            "subcategory":"Accounting & Tax Preparation",
            "type":"Services"
        }
    ],
    "sg:phone":"+1 415 834 0829",
    "sg:postcode":"94102",
    "sg:province":"CA",
    "sg:tags":[
        "accountant"
    ],
    "sg:website":"www.pereztaxassociates.com",
    "wof:name":"Perez Tax Associates",
    "wof:placetype":"venue"
},
  "geometry": {"coordinates":[-122.40742299999999,37.785111],"type":"Point"}
}