{
  "type": "Feature",
  "properties": {
    "iso:country":"US",
    "sg:address":"12103 Lakeland Rd",
    "sg:city":"Santa Fe Springs",
    "sg:classifiers":[
        {
            "category":"Autos & Motor Vehicles",
            "subcategory":"Auto Supplies",
            "type":"Retail Goods"
        }
    ],
    "sg:phone":"+1 562 946 8813",
    "sg:postcode":"90670",
    "sg:province":"CA",
    "sg:tags":[
        "equipment",
        "air",
        "conditioning",
        "automobile"
    ],
    "wof:name":"Aapak Of California",
    "wof:placetype":"venue"
},
  "geometry": {"coordinates":[-118.074429,33.931778],"type":"Point"}
}