{
  "type": "Feature",
  "properties": {
    "addr:full":"730 Meridian St Duarte CA 91010",
    "addr:housenumber":"730",
    "addr:postcode":"91010",
    "addr:street":"Meridian St",
    "iso:country":"US",
    "sg:address":"730 Meridian St",
    "sg:city":"Duarte",
    "sg:classifiers":[
        {
            "category":"Building & Trades",
            "subcategory":"Construction",
            "type":"Services"
        }
    ],
    "sg:phone":"+1 626 357 3372",
    "sg:postcode":"91010",
    "sg:province":"CA",
    "sg:tags":[
        "contractor"
    ],
    "wof:name":"Tri Em Construction",
    "wof:placetype":"venue"
},
  "geometry": {"coordinates":[-117.98942099999999,34.121745],"type":"Point"}
}