{
  "type": "Feature",
  "properties": {
    "iso:country":"US",
    "sg:address":"20271 SW Birch St",
    "sg:city":"Newport Beach",
    "sg:classifiers":[
        {
            "category":"Professional",
            "subcategory":"Computer Services",
            "type":"Services"
        }
    ],
    "sg:phone":"+1 949 752 6364",
    "sg:postcode":"92660",
    "sg:province":"CA",
    "sg:tags":[
        "home",
        "consulting",
        "page",
        "dev",
        "internet"
    ],
    "wof:name":"Kettley Productions",
    "wof:placetype":"venue"
},
  "geometry": {"coordinates":[-117.878265,33.656514],"type":"Point"}
}