{
  "type": "Feature",
  "properties": {
    "addr:full":"11377 Markon Dr Garden Grove CA 92841",
    "addr:postcode":"11377;92841",
    "addr:street":"Markon Dr",
    "iso:country":"US",
    "sg:address":"11377 Markon Dr",
    "sg:city":"Garden Grove",
    "sg:classifiers":[
        {
            "category":"Wholesale",
            "subcategory":"Chemicals & Plastics",
            "type":"Manufacturing & Wholesale Goods"
        }
    ],
    "sg:phone":"+1 714 891 1795",
    "sg:postcode":"92841",
    "sg:province":"CA",
    "sg:tags":[
        "product",
        "polyurethane"
    ],
    "sg:website":"www.elascourethane.com",
    "wof:name":"Elasco Inc",
    "wof:placetype":"venue"
},
  "geometry": {"coordinates":[-118.008178,33.796095],"type":"Point"}
}