{
  "type": "Feature",
  "properties": {
    "addr:full":"8800 Foothill Blvd Sunland CA 91040",
    "addr:housenumber":"8800",
    "addr:postcode":"91040",
    "addr:street":"Foothill Blvd",
    "iso:country":"US",
    "sg:address":"8800 Foothill Blvd",
    "sg:city":"Sunland",
    "sg:classifiers":[
        {
            "category":"Shopping",
            "subcategory":"Used Merchandise",
            "type":"Retail Goods"
        }
    ],
    "sg:phone":"+1 818 951 7150",
    "sg:postcode":"91040",
    "sg:province":"CA",
    "sg:tags":[
        "shop",
        "thrift"
    ],
    "wof:name":"Sun Thrift Store",
    "wof:placetype":"venue"
},
  "geometry": {"coordinates":[-118.324175,34.260419],"type":"Point"}
}