{
  "type": "Feature",
  "properties": {
    "iso:country":"US",
    "sg:address":"16900 Lakewood Blvd",
    "sg:city":"Bellflower",
    "sg:classifiers":[
        {
            "category":"Professional",
            "subcategory":"Computer Services",
            "type":"Services"
        }
    ],
    "sg:phone":"+1 562 866 8849",
    "sg:postcode":"90706",
    "sg:province":"CA",
    "sg:tags":[
        "repair"
    ],
    "wof:name":"Computer Network Zone",
    "wof:placetype":"venue"
},
  "geometry": {"coordinates":[-118.142364,33.8811],"type":"Point"}
}