{
  "type": "Feature",
  "properties": {
    "iso:country":"US",
    "sg:address":"8588 Thys Ct",
    "sg:city":"Sacramento",
    "sg:classifiers":[
        {
            "category":"Wholesale",
            "subcategory":"Scrap",
            "type":"Manufacturing & Wholesale Goods"
        }
    ],
    "sg:phone":"+1 916 388 2093",
    "sg:postcode":"95828",
    "sg:province":"CA",
    "sg:tags":[
        "recycling",
        "center"
    ],
    "wof:name":"Tri C Tire Recycling",
    "wof:placetype":"venue"
},
  "geometry": {"coordinates":[-121.38941699999999,38.518718],"type":"Point"}
}