{
  "type": "Feature",
  "properties": {
    "iso:country":"US",
    "sg:address":"68555 Ramon Rd",
    "sg:city":"Cathedral City",
    "sg:classifiers":[
        {
            "category":"Education",
            "subcategory":"Vocational School",
            "type":"Public Place"
        }
    ],
    "sg:phone":"+1 760 202 3307",
    "sg:postcode":"92234",
    "sg:province":"CA",
    "wof:name":"International Casino Academy",
    "wof:placetype":"venue"
},
  "geometry": {"coordinates":[-116.465208,33.815951],"type":"Point"}
}