{
  "type": "Feature",
  "properties": {
    "addr:full":"7210 Yosemite Park Way Yosemite Natl Pk CA 95389",
    "addr:housenumber":"7210",
    "addr:postcode":"95389",
    "addr:street":"Yosemite Park Way Yosemite Natl",
    "iso:country":"US",
    "sg:address":"7210 Yosemite Park Way",
    "sg:city":"Yosemite Natl Pk",
    "sg:classifiers":[
        {
            "category":"Travel",
            "subcategory":"Hotels & Motels",
            "type":"Entertainment"
        }
    ],
    "sg:phone":"+1 209 375 1414",
    "sg:postcode":"95389",
    "sg:province":"CA",
    "sg:tags":[
        "breakfast",
        "accommodation",
        "bed"
    ],
    "wof:name":"Yosemite Falls B & B",
    "wof:placetype":"venue"
},
  "geometry": {"coordinates":[-119.719376,37.649644],"type":"Point"}
}