{
  "type": "Feature",
  "properties": {
    "addr:full":"10080 International Rd Los Angeles CA 90045",
    "addr:housenumber":"10080",
    "addr:postcode":"90045",
    "addr:street":"International Rd",
    "iso:country":"US",
    "sg:address":"10080 International Rd",
    "sg:city":"Los Angeles",
    "sg:classifiers":[
        {
            "category":"Airline",
            "type":"Transportation"
        }
    ],
    "sg:phone":"+1 310 338 0965",
    "sg:postcode":"90045",
    "sg:province":"CA",
    "sg:tags":[
        "cargo",
        "air"
    ],
    "wof:name":"Kitty Hawk Cargo",
    "wof:placetype":"venue"
},
  "geometry": {"coordinates":[-118.381495,33.94554],"type":"Point"}
}