{
  "type": "Feature",
  "properties": {
    "addr:full":"8600 W Harding Rd Turlock CA 95380",
    "addr:housenumber":"8600",
    "addr:postcode":"95380",
    "addr:street":"W Harding Rd",
    "iso:country":"US",
    "sg:address":"8600 W Harding Rd",
    "sg:city":"Turlock",
    "sg:classifiers":[
        {
            "category":"Building & Trades",
            "subcategory":"Electrical",
            "type":"Services"
        }
    ],
    "sg:phone":"+1 209 664 1980",
    "sg:postcode":"95380",
    "sg:province":"CA",
    "sg:tags":[
        "electric",
        "contractor"
    ],
    "wof:name":"Advanced Electrical Technolgy",
    "wof:placetype":"venue"
},
  "geometry": {"coordinates":[-120.94483,37.46358],"type":"Point"}
}