{
  "type": "Feature",
  "properties": {
    "iso:country":"US",
    "sg:address":"320 N Broadway",
    "sg:city":"Escondido",
    "sg:classifiers":[
        {
            "category":"Wholesale",
            "subcategory":"Furniture",
            "type":"Manufacturing & Wholesale Goods"
        }
    ],
    "sg:phone":"+1 858 729 0622",
    "sg:postcode":"92025",
    "sg:province":"CA",
    "wof:name":"Aja Design Ctr",
    "wof:placetype":"venue"
},
  "geometry": {"coordinates":[-117.083068,33.125203],"type":"Point"}
}