{
  "type": "Feature",
  "properties": {
    "iso:country":"US",
    "sg:address":"601 S Raymond Ave",
    "sg:city":"Fullerton",
    "sg:classifiers":[
        {
            "category":"Bars & Pubs",
            "type":"Food & Drink"
        }
    ],
    "sg:phone":"+1 714 871 7390",
    "sg:postcode":"92831",
    "sg:province":"CA",
    "sg:tags":[
        "lounge",
        "cocktail"
    ],
    "wof:name":"Bananas Bar & Grill",
    "wof:placetype":"venue"
},
  "geometry": {"coordinates":[-117.906891,33.865021],"type":"Point"}
}