{
  "type": "Feature",
  "properties": {
    "addr:full":"1649 Elzworth St Bakersfield CA 93312",
    "addr:housenumber":"1649",
    "addr:postcode":"93312",
    "addr:street":"Elzworth St",
    "iso:country":"US",
    "sg:address":"1649 Elzworth St",
    "sg:city":"Bakersfield",
    "sg:classifiers":[
        {
            "category":"Shopping",
            "subcategory":"Hobbies, Toys, & Games",
            "type":"Retail Goods"
        }
    ],
    "sg:phone":"+1 661 587 9633",
    "sg:postcode":"93312",
    "sg:province":"CA",
    "sg:tags":[
        "supply"
    ],
    "wof:name":"Decision Games",
    "wof:placetype":"venue"
},
  "geometry": {"coordinates":[-119.105592,35.373027],"type":"Point"}
}