{
  "type": "Feature",
  "properties": {
    "addr:full":"511 Ohlone Trl Watsonville CA 95066",
    "addr:housenumber":"511",
    "addr:postcode":"95066",
    "addr:street":"Ohlone Trl",
    "iso:country":"US",
    "sg:address":"511 Ohlone Trl",
    "sg:city":"Watsonville",
    "sg:classifiers":[
        {
            "category":"Wholesale",
            "subcategory":"Auto Parts",
            "type":"Manufacturing & Wholesale Goods"
        }
    ],
    "sg:phone":"+1 831 728 2032",
    "sg:postcode":"95066",
    "sg:province":"CA",
    "sg:tags":[
        "automobile"
    ],
    "wof:name":"G & G Used Auto Parts",
    "wof:placetype":"venue"
},
  "geometry": {"coordinates":[-122.03212000000001,37.090112],"type":"Point"}
}