{
  "type": "Feature",
  "properties": {
    "addr:full":"3825 Birch St Newport Beach CA 92660",
    "addr:housenumber":"3825",
    "addr:postcode":"92660",
    "addr:street":"Birch St",
    "iso:country":"US",
    "sg:address":"3825 Birch St",
    "sg:city":"Newport Beach",
    "sg:classifiers":[
        {
            "category":"Retail",
            "subcategory":"Repair Shop",
            "type":"Services"
        }
    ],
    "sg:phone":"+1 949 673 1453",
    "sg:postcode":"92660",
    "sg:province":"CA",
    "sg:tags":[
        "bathtub",
        "sink",
        "refinishing"
    ],
    "sg:website":"www.calbath.com",
    "wof:name":"California Bath Restoration",
    "wof:placetype":"venue"
},
  "geometry": {"coordinates":[-117.868371,33.666231],"type":"Point"}
}