{
  "type": "Feature",
  "properties": {
    "iso:country":"US",
    "sg:address":"7101 E Slauson Ave",
    "sg:city":"Los Angeles",
    "sg:classifiers":[
        {
            "category":"Restaurant",
            "type":"Food & Drink"
        }
    ],
    "sg:phone":"+1 323 721 6100",
    "sg:postcode":"90040",
    "sg:province":"CA",
    "sg:website":"www.jfc.com",
    "wof:name":"JFC International",
    "wof:placetype":"venue"
},
  "geometry": {"coordinates":[-118.136084,33.981421],"type":"Point"}
}