{
  "type": "Feature",
  "properties": {
    "addr:full":"3649 10th St Riverside CA 92501",
    "addr:housenumber":"3649",
    "addr:postcode":"92501",
    "addr:street":"10Th St",
    "iso:country":"US",
    "sg:address":"3649 10th St",
    "sg:city":"Riverside",
    "sg:classifiers":[
        {
            "category":"Restaurant",
            "type":"Food & Drink"
        }
    ],
    "sg:phone":"+1 951 328 0866",
    "sg:postcode":"92501",
    "sg:province":"CA",
    "sg:tags":[
        "shop",
        "coffee"
    ],
    "wof:name":"Coffee Court",
    "wof:placetype":"venue"
},
  "geometry": {"coordinates":[-117.37522,33.979798],"type":"Point"}
}