{
  "type": "Feature",
  "properties": {
    "iso:country":"US",
    "sg:address":"625 E Carter St",
    "sg:city":"Rialto",
    "sg:classifiers":[
        {
            "category":"Building & Trades",
            "subcategory":"Plumbing",
            "type":"Services"
        }
    ],
    "sg:phone":"+1 909 875 1861",
    "sg:postcode":"92376",
    "sg:province":"CA",
    "sg:tags":[
        "conditioning",
        "air",
        "system",
        "contractor"
    ],
    "wof:name":"A & V Svc Air Cond & Heating",
    "wof:placetype":"venue"
},
  "geometry": {"coordinates":[-117.35969900000001,34.090774],"type":"Point"}
}