{
  "type": "Feature",
  "properties": {
    "addr:full":"1101 W Turner Rd Lodi CA 95242",
    "addr:housenumber":"1101",
    "addr:postcode":"95242",
    "addr:street":"W Turner Rd",
    "iso:country":"US",
    "sg:address":"1101 W Turner Rd",
    "sg:city":"Lodi",
    "sg:classifiers":[
        {
            "category":"Recreation",
            "type":"Entertainment"
        }
    ],
    "sg:phone":"+1 209 368 5624",
    "sg:postcode":"95242",
    "sg:province":"CA",
    "sg:tags":[
        "parks"
    ],
    "wof:name":"Lodi Lake",
    "wof:placetype":"venue"
},
  "geometry": {"coordinates":[-121.322266,38.145672],"type":"Point"}
}