{
  "type": "Feature",
  "properties": {
    "iso:country":"US",
    "sg:address":"4612 Auburn Blvd",
    "sg:city":"Sacramento",
    "sg:classifiers":[
        {
            "category":"Wholesale",
            "subcategory":"Painting Supplies",
            "type":"Manufacturing & Wholesale Goods"
        }
    ],
    "sg:phone":"+1 916 482 7100",
    "sg:postcode":"95841",
    "sg:province":"CA",
    "sg:tags":[
        "equipment",
        "painter"
    ],
    "wof:name":"Asv",
    "wof:placetype":"venue"
},
  "geometry": {"coordinates":[-121.35489099999999,38.653116],"type":"Point"}
}