{
  "type": "Feature",
  "properties": {
    "iso:country":"US",
    "sg:address":"6319 de Soto Ave",
    "sg:city":"Woodland Hills",
    "sg:classifiers":[
        {
            "category":"Travel",
            "subcategory":"Travel Agent",
            "type":"Entertainment"
        }
    ],
    "sg:phone":"+1 818 888 3808",
    "sg:postcode":"91303",
    "sg:province":"CA",
    "sg:tags":[
        "agency"
    ],
    "wof:name":"World Travel Management",
    "wof:placetype":"venue"
},
  "geometry": {"coordinates":[-118.588525,34.188036],"type":"Point"}
}