{
  "type": "Feature",
  "properties": {
    "addr:full":"720 W 27th Street Los Angeles CA 90007",
    "addr:housenumber":"720",
    "addr:postcode":"90007",
    "addr:street":"W 27Th Street",
    "iso:country":"US",
    "sg:address":"720 W 27th Street",
    "sg:city":"Los Angeles",
    "sg:classifiers":[
        {
            "category":"Real Estate",
            "subcategory":"Real Estate Operator",
            "type":"Services"
        }
    ],
    "sg:phone":"+1 213 747 5200",
    "sg:postcode":"90007",
    "sg:province":"CA",
    "sg:tags":[
        "apartment"
    ],
    "wof:name":"Mardi Gras Apartments",
    "wof:placetype":"venue"
},
  "geometry": {"coordinates":[-118.27925399999999,34.02822],"type":"Point"}
}