{
  "type": "Feature",
  "properties": {
    "iso:country":"US",
    "sg:address":"4600 Georgian Ave",
    "sg:city":"Sacramento",
    "sg:classifiers":[
        {
            "category":"Building & Trades",
            "subcategory":"Construction",
            "type":"Services"
        }
    ],
    "sg:phone":"+1 916 947 0224",
    "sg:postcode":"95821",
    "sg:province":"CA",
    "sg:tags":[
        "handyman"
    ],
    "wof:name":"P T Construction",
    "wof:placetype":"venue"
},
  "geometry": {"coordinates":[-121.356975,38.631288],"type":"Point"}
}