{
  "type": "Feature",
  "properties": {
    "addr:full":"6670 Miramar Rd San Diego CA 92121",
    "addr:housenumber":"6670",
    "addr:postcode":"92121",
    "addr:street":"Miramar Rd",
    "iso:country":"US",
    "sg:address":"6670 Miramar Rd",
    "sg:city":"San Diego",
    "sg:classifiers":[
        {
            "category":"Retail",
            "subcategory":"Auto Repair",
            "type":"Services"
        }
    ],
    "sg:phone":"+1 858 535 1919",
    "sg:postcode":"92121",
    "sg:province":"CA",
    "sg:tags":[
        "automobile",
        "smog"
    ],
    "wof:name":"Lo Sieu Smog Test Only Ctr",
    "wof:placetype":"venue"
},
  "geometry": {"coordinates":[-117.170852,32.877759],"type":"Point"}
}