{
  "type": "Feature",
  "properties": {
    "iso:country":"US",
    "sg:address":"6700 8th St",
    "sg:city":"Rio Linda",
    "sg:classifiers":[
        {
            "category":"Organizations",
            "subcategory":"Community Association",
            "type":"Services"
        }
    ],
    "sg:phone":"+1 916 991 9921",
    "sg:postcode":"95673",
    "sg:province":"CA",
    "sg:tags":[
        "military"
    ],
    "wof:name":"American Legion",
    "wof:placetype":"venue"
},
  "geometry": {"coordinates":[-121.44762,38.691075],"type":"Point"}
}