{
  "type": "Feature",
  "properties": {
    "addr:full":"2606 Bravado Dr Rancho Cordova CA 95670",
    "addr:housenumber":"2606",
    "addr:postcode":"95670",
    "addr:street":"Bravado Dr",
    "iso:country":"US",
    "sg:address":"2606 Bravado Dr",
    "sg:city":"Rancho Cordova",
    "sg:classifiers":[
        {
            "category":"Professional",
            "subcategory":"Accounting & Tax Preparation",
            "type":"Services"
        }
    ],
    "sg:phone":"+1 916 947 0906",
    "sg:postcode":"95670",
    "sg:province":"CA",
    "sg:tags":[
        "accountant"
    ],
    "wof:name":"Accounting Consulting Tax Svc",
    "wof:placetype":"venue"
},
  "geometry": {"coordinates":[-121.31788299999999,38.584955],"type":"Point"}
}