{
  "type": "Feature",
  "properties": {
    "addr:full":"634 Lucille Cir Moorpark CA 93021",
    "addr:housenumber":"634",
    "addr:postcode":"ca 93021",
    "addr:street":"Lucille Cir",
    "iso:country":"US",
    "sg:address":"634 Lucille Cir",
    "sg:city":"Moorpark",
    "sg:classifiers":[
        {
            "category":"Building & Trades",
            "subcategory":"Plumbing",
            "type":"Services"
        }
    ],
    "sg:phone":"+1 805 529 7622",
    "sg:postcode":"93021",
    "sg:province":"CA",
    "sg:tags":[
        "contractor"
    ],
    "wof:name":"Richco Plumbing",
    "wof:placetype":"venue"
},
  "geometry": {"coordinates":[-118.87150800000001,34.286517],"type":"Point"}
}