{
  "type": "Feature",
  "properties": {
    "addr:full":"1200 Wilshire Boulevard Los Angeles CA 90017",
    "addr:housenumber":"1200",
    "addr:postcode":"90017",
    "addr:street":"Wilshire Boulevard",
    "iso:country":"US",
    "sg:address":"1200 Wilshire Boulevard",
    "sg:city":"Los Angeles",
    "sg:classifiers":[
        {
            "category":"Banks & Credit Unions",
            "subcategory":"Investment Brokerage",
            "type":"Services"
        }
    ],
    "sg:phone":"+1 213 482 3061",
    "sg:postcode":"90017",
    "sg:province":"CA",
    "sg:tags":[
        "investing"
    ],
    "wof:name":"American Ready Cash",
    "wof:placetype":"venue"
},
  "geometry": {"coordinates":[-118.26486199999999,34.052963],"type":"Point"}
}