{
  "type": "Feature",
  "properties": {
    "iso:country":"US",
    "sg:address":"1200 Wilshire Boulevard",
    "sg:city":"Los Angeles",
    "sg:classifiers":[
        {
            "category":"Banks & Credit Unions",
            "subcategory":"Investment Brokerage",
            "type":"Services"
        }
    ],
    "sg:phone":"+1 213 482 3061",
    "sg:postcode":"90017",
    "sg:province":"CA",
    "sg:tags":[
        "investing"
    ],
    "wof:name":"American Ready Cash",
    "wof:placetype":"venue"
},
  "geometry": {"coordinates":[-118.264862,34.052963],"type":"Point"}
}