{
  "type": "Feature",
  "properties": {
    "iso:country":"US",
    "sg:address":"1222 1st Ave",
    "sg:city":"San Diego",
    "sg:classifiers":[
        {
            "category":"Government",
            "subcategory":"Fire Station",
            "type":"Public Place"
        }
    ],
    "sg:phone":"+1 619 236 6815",
    "sg:postcode":"92101",
    "sg:province":"CA",
    "sg:tags":[
        "protection"
    ],
    "wof:name":"Fire Dept- Station 1",
    "wof:placetype":"venue"
},
  "geometry": {"coordinates":[-117.163921,32.718592],"type":"Point"}
}