{
  "type": "Feature",
  "properties": {
    "iso:country":"US",
    "sg:address":"709 E Adele St",
    "sg:city":"Anaheim",
    "sg:classifiers":[
        {
            "category":"Wholesale",
            "subcategory":"Auto Parts",
            "type":"Manufacturing & Wholesale Goods"
        }
    ],
    "sg:phone":"+1 714 758 8500",
    "sg:postcode":"92805",
    "sg:province":"CA",
    "sg:tags":[
        "automobile",
        "wrecking"
    ],
    "wof:name":"AASCO",
    "wof:placetype":"venue"
},
  "geometry": {"coordinates":[-117.908125,33.840424],"type":"Point"}
}