{
  "type": "Feature",
  "properties": {
    "addr:full":"4501 Ashe Rd Bakersfield CA 93313",
    "addr:housenumber":"4501",
    "addr:postcode":"93313",
    "addr:street":"Ashe Rd",
    "iso:country":"US",
    "sg:address":"4501 Ashe Rd",
    "sg:city":"Bakersfield",
    "sg:classifiers":[
        {
            "category":"Wholesale",
            "subcategory":"Machinery & Supplies",
            "type":"Manufacturing & Wholesale Goods"
        }
    ],
    "sg:phone":"+1 661 827 0130",
    "sg:postcode":"93313",
    "sg:province":"CA",
    "sg:tags":[
        "equipment",
        "irrigation",
        "system"
    ],
    "wof:name":"Ewing Irrigation Golf & Ind",
    "wof:placetype":"venue"
},
  "geometry": {"coordinates":[-119.074512,35.315064],"type":"Point"}
}