{
  "type": "Feature",
  "properties": {
    "iso:country":"US",
    "sg:address":"3177 17th Street",
    "sg:city":"San Francisco",
    "sg:classifiers":[
        {
            "category":"Organizations",
            "subcategory":"Non-profit Organization",
            "type":"Services"
        }
    ],
    "sg:phone":"+1 415 522 1550",
    "sg:postcode":"94110",
    "sg:province":"CA",
    "sg:tags":[
        "service/non-profit",
        "community"
    ],
    "sg:website":"www.7tepees.org",
    "wof:name":"7 Tepees Youth Program",
    "wof:placetype":"venue"
},
  "geometry": {"coordinates":[-122.416926,37.763505],"type":"Point"}
}