{
  "type": "Feature",
  "properties": {
    "addr:full":"2123 W 8th Street Los Angeles CA 90057",
    "addr:housenumber":"2123",
    "addr:postcode":"90057",
    "addr:street":"W 8Th Street",
    "iso:country":"US",
    "sg:address":"2123 W 8th Street",
    "sg:city":"Los Angeles",
    "sg:classifiers":[
        {
            "category":"Personal",
            "type":"Services"
        }
    ],
    "sg:phone":"+1 213 383 7316",
    "sg:postcode":"90057",
    "sg:province":"CA",
    "sg:tags":[
        "mover"
    ],
    "wof:name":"Transportes San Jose",
    "wof:placetype":"venue"
},
  "geometry": {"coordinates":[-118.278445,34.055022],"type":"Point"}
}