{
  "type": "Feature",
  "properties": {
    "iso:country":"US",
    "sg:address":"1148 S Bristol St",
    "sg:city":"Santa Ana",
    "sg:classifiers":[
        {
            "category":"Ice Cream",
            "type":"Food & Drink"
        }
    ],
    "sg:phone":"+1 714 540 0313",
    "sg:postcode":"92704",
    "sg:province":"CA",
    "sg:tags":[
        "frozen",
        "yogurt"
    ],
    "wof:name":"Carnation Ice Cream Land",
    "wof:placetype":"venue"
},
  "geometry": {"coordinates":[-117.885002,33.7328],"type":"Point"}
}