{
  "type": "Feature",
  "properties": {
    "addr:full":"8903 Laurel Canyon Blvd Sun Valley CA 91352",
    "addr:housenumber":"8903",
    "addr:postcode":"91352",
    "addr:street":"Laurel Canyon Blvd",
    "iso:country":"US",
    "sg:address":"8903 Laurel Canyon Blvd",
    "sg:city":"Sun Valley",
    "sg:classifiers":[
        {
            "category":"Food & Beverages",
            "subcategory":"Meat & Fish",
            "type":"Retail Goods"
        }
    ],
    "sg:phone":"+1 818 768 6787",
    "sg:postcode":"91352",
    "sg:province":"CA",
    "wof:name":"Carniceria Serrano",
    "wof:placetype":"venue"
},
  "geometry": {"coordinates":[-118.4028,34.230946],"type":"Point"}
}