{
  "type": "Feature",
  "properties": {
    "addr:full":"4931 Pacheco Blvd Martinez CA 94553",
    "addr:housenumber":"4931",
    "addr:postcode":"94553",
    "addr:street":"Pacheco Blvd",
    "iso:country":"US",
    "sg:address":"4931 Pacheco Blvd",
    "sg:city":"Martinez",
    "sg:classifiers":[
        {
            "category":"Building & Trades",
            "subcategory":"Construction",
            "type":"Services"
        }
    ],
    "sg:phone":"+1 925 313 9075",
    "sg:postcode":"94553",
    "sg:province":"CA",
    "sg:tags":[
        "excavating",
        "contractor"
    ],
    "wof:name":"Phil's Backhoe Svc",
    "wof:placetype":"venue"
},
  "geometry": {"coordinates":[-122.07713,37.997372],"type":"Point"}
}