{
  "type": "Feature",
  "properties": {
    "addr:full":"204 E Main St Ripon CA 95366",
    "addr:housenumber":"204",
    "addr:postcode":"ca 95366",
    "addr:street":"E Main St",
    "iso:country":"US",
    "sg:address":"204 E Main St",
    "sg:city":"Ripon",
    "sg:classifiers":[
        {
            "category":"Personal",
            "subcategory":"Beauty Salon",
            "type":"Services"
        }
    ],
    "sg:phone":"+1 209 599 2511",
    "sg:postcode":"95366",
    "sg:province":"CA",
    "wof:name":"Barbouri",
    "wof:placetype":"venue"
},
  "geometry": {"coordinates":[-121.12211499999999,37.738957],"type":"Point"}
}