{
  "type": "Feature",
  "properties": {
    "addr:full":"800 S Alta St Gonzales CA 93926",
    "addr:housenumber":"800",
    "addr:postcode":"93926",
    "addr:street":"S Alta St",
    "iso:country":"US",
    "sg:address":"800 S Alta St",
    "sg:city":"Gonzales",
    "sg:classifiers":[
        {
            "category":"Farming",
            "subcategory":"Vineyard",
            "type":"Manufacturing & Wholesale Goods"
        }
    ],
    "sg:phone":"+1 831 675 4000",
    "sg:postcode":"93926",
    "sg:province":"CA",
    "wof:name":"Monterey Vineyard",
    "wof:placetype":"venue"
},
  "geometry": {"coordinates":[-121.436859,36.499647],"type":"Point"}
}