{
  "type": "Feature",
  "properties": {
    "addr:full":"1226 Anacapa St Santa Barbara CA 93101",
    "addr:housenumber":"1226",
    "addr:postcode":"93101",
    "addr:street":"Anacapa St",
    "iso:country":"US",
    "sg:address":"1226 Anacapa St",
    "sg:city":"Santa Barbara",
    "sg:classifiers":[
        {
            "category":"Government",
            "subcategory":"Office",
            "type":"Public Place"
        }
    ],
    "sg:phone":"+1 805 568 2040",
    "sg:postcode":"93101",
    "sg:province":"CA",
    "wof:name":"Santa Barbara Energy Div",
    "wof:placetype":"venue"
},
  "geometry": {"coordinates":[-119.704258,34.42517],"type":"Point"}
}