{
  "type": "Feature",
  "properties": {
    "addr:full":"2150 E 19th St Oakland CA 94606",
    "addr:housenumber":"2150",
    "addr:postcode":"94606",
    "addr:street":"E 19Th St",
    "iso:country":"US",
    "sg:address":"2150 E 19th St",
    "sg:city":"Oakland",
    "sg:classifiers":[
        {
            "category":"Building & Trades",
            "subcategory":"Construction",
            "type":"Services"
        }
    ],
    "sg:phone":"+1 415 572 3932",
    "sg:postcode":"94606",
    "sg:province":"CA",
    "sg:tags":[
        "industrial",
        "contractors-commercial",
        "contractor"
    ],
    "wof:name":"Yursta Construction",
    "wof:placetype":"venue"
},
  "geometry": {"coordinates":[-122.23523,37.788207],"type":"Point"}
}