{
  "type": "Feature",
  "properties": {
    "addr:full":"5329 Broadway Oakland CA 94618",
    "addr:housenumber":"5329",
    "addr:postcode":"94618",
    "addr:street":"Broadway",
    "iso:country":"US",
    "sg:address":"5329 Broadway",
    "sg:city":"Oakland",
    "sg:classifiers":[
        {
            "category":"Professional",
            "subcategory":"Computer Services",
            "type":"Services"
        }
    ],
    "sg:phone":"+1 415 254 6501",
    "sg:postcode":"94618",
    "sg:province":"CA",
    "sg:tags":[
        "wine",
        "food",
        "wine-guide",
        "wine-pairing",
        "cooking",
        "iphone"
    ],
    "sg:website":"http://pairitapp.com",
    "wof:name":"Pair It!",
    "wof:placetype":"venue"
},
  "geometry": {"coordinates":[-122.249684,37.838987],"type":"Point"}
}