{
  "type": "Feature",
  "properties": {
    "iso:country":"US",
    "sg:address":"4213 Barrymore Dr",
    "sg:city":"San Jose",
    "sg:classifiers":[
        {
            "category":"Personal",
            "subcategory":"Tattoo Parlor",
            "type":"Services"
        }
    ],
    "sg:phone":"+1 408 247 4878",
    "sg:postcode":"95117",
    "sg:province":"CA",
    "sg:website":"www.gurutattoo.net",
    "wof:name":"Guru Tattoo",
    "wof:placetype":"venue"
},
  "geometry": {"coordinates":[-121.978692,37.30348],"type":"Point"}
}