{
  "type": "Feature",
  "properties": {
    "addr:full":"1450 Fallsview Pl Escondido CA 92027",
    "addr:housenumber":"1450",
    "addr:postcode":"92027",
    "addr:street":"Fallsview Pl",
    "iso:country":"US",
    "sg:address":"1450 Fallsview Pl",
    "sg:city":"Escondido",
    "sg:classifiers":[
        {
            "category":"Building & Trades",
            "subcategory":"Plumbing",
            "type":"Services"
        }
    ],
    "sg:phone":"+1 619 851 7144",
    "sg:postcode":"92027",
    "sg:province":"CA",
    "sg:tags":[
        "conditioning",
        "air",
        "system",
        "contractor"
    ],
    "wof:name":"Barbin Heating & Air Condition",
    "wof:placetype":"venue"
},
  "geometry": {"coordinates":[-117.07592699999999,33.150414],"type":"Point"}
}