{
  "type": "Feature",
  "properties": {
    "addr:full":"1620 School St Moraga CA 94556",
    "addr:housenumber":"1620",
    "addr:postcode":"94556",
    "addr:street":"School St",
    "iso:country":"US",
    "sg:address":"1620 School St",
    "sg:city":"Moraga",
    "sg:classifiers":[
        {
            "category":"Professional",
            "subcategory":"Management & Consulting",
            "type":"Services"
        }
    ],
    "sg:phone":"+1 925 376 9497",
    "sg:postcode":"94556",
    "sg:province":"CA",
    "sg:tags":[
        "consultant",
        "lighting"
    ],
    "sg:website":"www.ejc.com",
    "wof:name":"Edward J Cansino & Assoc",
    "wof:placetype":"venue"
},
  "geometry": {"coordinates":[-122.132373,37.833429],"type":"Point"}
}