{
  "type": "Feature",
  "properties": {
    "iso:country":"US",
    "sg:address":"1563 State Hwy 99",
    "sg:city":"Gridley",
    "sg:classifiers":[
        {
            "category":"Home & Garden",
            "subcategory":"Building Materials",
            "type":"Retail Goods"
        }
    ],
    "sg:phone":"+1 530 846 4375",
    "sg:postcode":"95948",
    "sg:province":"CA",
    "sg:tags":[
        "glass",
        "leaded"
    ],
    "wof:name":"Stained Glass Junction",
    "wof:placetype":"venue"
},
  "geometry": {"coordinates":[-121.687968,39.362213],"type":"Point"}
}