{
  "type": "Feature",
  "properties": {
    "addr:full":"5463 Century Park Way San Jose CA 95111",
    "addr:housenumber":"5463",
    "addr:postcode":"95111",
    "addr:street":"Century Park Way",
    "iso:country":"US",
    "sg:address":"5463 Century Park Way",
    "sg:city":"San Jose",
    "sg:classifiers":[
        {
            "category":"Organizations",
            "subcategory":"Professional Association",
            "type":"Services"
        }
    ],
    "sg:phone":"+1 408 281 9098",
    "sg:postcode":"95111",
    "sg:province":"CA",
    "wof:name":"Campbell Highland Games Assn",
    "wof:placetype":"venue"
},
  "geometry": {"coordinates":[-121.79593,37.258522],"type":"Point"}
}