{
  "type": "Feature",
  "properties": {
    "addr:full":"307 E Banyan St Ontario CA 91761",
    "addr:housenumber":"307",
    "addr:postcode":"91761",
    "addr:street":"E Banyan St",
    "iso:country":"US",
    "sg:address":"307 E Banyan St",
    "sg:city":"Ontario",
    "sg:classifiers":[
        {
            "category":"Food & Beverages",
            "subcategory":"Specialty",
            "type":"Retail Goods"
        }
    ],
    "sg:phone":"+1 909 988 5274",
    "sg:postcode":"91761",
    "sg:province":"CA",
    "wof:name":"Max Nutrition & Weight Loss",
    "wof:placetype":"venue"
},
  "geometry": {"coordinates":[-117.646869,34.028153],"type":"Point"}
}