{
  "type": "Feature",
  "properties": {
    "addr:full":"585 Mowry Ave Fremont CA 94536",
    "addr:housenumber":"585",
    "addr:postcode":"94536",
    "addr:street":"Mowry Ave",
    "iso:country":"US",
    "sg:address":"585 Mowry Ave",
    "sg:city":"Fremont",
    "sg:classifiers":[
        {
            "category":"Bars & Pubs",
            "type":"Food & Drink"
        },
        {
            "category":"Shopping",
            "subcategory":"Party Supplies",
            "type":"Retail Goods"
        },
        {
            "category":"Sports & Exercise",
            "subcategory":"Bowling",
            "type":"Entertainment"
        }
    ],
    "sg:phone":"+1 510 794 7777",
    "sg:postcode":"94536",
    "sg:province":"CA",
    "sg:tags":[
        "children's",
        "planning"
    ],
    "sg:website":"http://www.amf.com",
    "wof:name":"AMF Mowry Lanes",
    "wof:placetype":"venue"
},
  "geometry": {"coordinates":[-121.97309,37.567442],"type":"Point"}
}