{
  "type": "Feature",
  "properties": {
    "addr:full":"24325 Cimarron Ct Laguna Niguel CA 92677",
    "addr:housenumber":"24325",
    "addr:postcode":"92677",
    "addr:street":"Cimarron Ct",
    "iso:country":"US",
    "sg:address":"24325 Cimarron Ct",
    "sg:city":"Laguna Niguel",
    "sg:classifiers":[
        {
            "category":"Wholesale",
            "subcategory":"Stationery",
            "type":"Manufacturing & Wholesale Goods"
        }
    ],
    "sg:phone":"+1 949 362 6110",
    "sg:postcode":"92677",
    "sg:province":"CA",
    "sg:tags":[
        "school",
        "supply"
    ],
    "wof:name":"It's About Time",
    "wof:placetype":"venue"
},
  "geometry": {"coordinates":[-117.70456299999999,33.551277],"type":"Point"}
}