{
  "type": "Feature",
  "properties": {
    "addr:full":"9370 Telegraph Rd Downey CA 90240",
    "addr:housenumber":"9370",
    "addr:postcode":"90240",
    "addr:street":"Telegraph Rd",
    "iso:country":"US",
    "sg:address":"9370 Telegraph Rd",
    "sg:city":"Downey",
    "sg:classifiers":[
        {
            "category":"Bars & Pubs",
            "subcategory":"Sports Bar",
            "type":"Food & Drink"
        }
    ],
    "sg:phone":"+1 562 862 5802",
    "sg:postcode":"90240",
    "sg:province":"CA",
    "wof:name":"Las Chabelitas Sports Bar",
    "wof:placetype":"venue"
},
  "geometry": {"coordinates":[-118.102711,33.955885],"type":"Point"}
}