{
  "type": "Feature",
  "properties": {
    "iso:country":"US",
    "sg:address":"13262 Bradley Ave",
    "sg:city":"Sylmar",
    "sg:classifiers":[
        {
            "category":"Organizations",
            "subcategory":"Religious Organization",
            "type":"Services"
        }
    ],
    "sg:phone":"+1 818 367 2670",
    "sg:postcode":"91342",
    "sg:province":"CA",
    "sg:tags":[
        "church"
    ],
    "wof:name":"Jehovah's Witnesses",
    "wof:placetype":"venue"
},
  "geometry": {"coordinates":[-118.469004,34.312567],"type":"Point"}
}