{
  "type": "Feature",
  "properties": {
    "iso:country":"US",
    "sg:address":"5805 Teresa St",
    "sg:city":"Atascadero",
    "sg:classifiers":[
        {
            "category":"Professional",
            "subcategory":"Detective & Security Services",
            "type":"Services"
        }
    ],
    "sg:phone":"+1 805 466 1993",
    "sg:postcode":"93422",
    "sg:province":"CA",
    "sg:tags":[
        "information",
        "bureau"
    ],
    "wof:name":"C Chubb",
    "wof:placetype":"venue"
},
  "geometry": {"coordinates":[-120.66730699999999,35.504725],"type":"Point"}
}