{
  "type": "Feature",
  "properties": {
    "iso:country":"US",
    "sg:address":"656 S Oakland Ave",
    "sg:city":"Pasadena",
    "sg:classifiers":[
        {
            "category":"Wholesale",
            "subcategory":"Electrical",
            "type":"Manufacturing & Wholesale Goods"
        }
    ],
    "sg:phone":"+1 626 818 1850",
    "sg:postcode":"91106",
    "sg:province":"CA",
    "sg:tags":[
        "equipment",
        "electric",
        "supply"
    ],
    "wof:name":"Elektra & Assoc",
    "wof:placetype":"venue"
},
  "geometry": {"coordinates":[-118.139578,34.135271],"type":"Point"}
}