{
  "type": "Feature",
  "properties": {
    "iso:country":"US",
    "sg:address":"2015 W Redondo Beach Blvd",
    "sg:city":"Gardena",
    "sg:classifiers":[
        {
            "category":"Building & Trades",
            "subcategory":"Construction",
            "type":"Services"
        }
    ],
    "sg:phone":"+1 310 409 2678",
    "sg:postcode":"90249",
    "sg:province":"CA",
    "sg:tags":[
        "contractor"
    ],
    "wof:name":"Gardena Garage Door Opener Repair",
    "wof:placetype":"venue"
},
  "geometry": {"coordinates":[-118.313984,33.887464],"type":"Point"}
}