{
  "type": "Feature",
  "properties": {
    "iso:country":"US",
    "sg:address":"794 McAllister St",
    "sg:city":"San Francisco",
    "sg:classifiers":[
        {
            "category":"Organizations",
            "subcategory":"Community Association",
            "type":"Services"
        }
    ],
    "sg:phone":"+1 415 922 1850",
    "sg:postcode":"94102",
    "sg:province":"CA",
    "sg:tags":[
        "support",
        "business"
    ],
    "wof:name":"First Dynsty Records",
    "wof:placetype":"venue"
},
  "geometry": {"coordinates":[-122.423875,37.779741],"type":"Point"}
}