{
  "type": "Feature",
  "properties": {
    "addr:full":"3401 Watkins Dr Riverside CA 92507",
    "addr:housenumber":"3401",
    "addr:postcode":"92507",
    "addr:street":"Watkins Dr",
    "iso:country":"US",
    "sg:address":"3401 Watkins Dr",
    "sg:city":"Riverside",
    "sg:classifiers":[
        {
            "category":"Education",
            "subcategory":"Library",
            "type":"Public Place"
        }
    ],
    "sg:phone":"+1 951 787 3221",
    "sg:postcode":"92507",
    "sg:province":"CA",
    "wof:name":"Ucr Rivera Library",
    "wof:placetype":"venue"
},
  "geometry": {"coordinates":[-117.323587,33.981002],"type":"Point"}
}