{
  "type": "Feature",
  "properties": {
    "addr:full":"11910 Crystal Wells Rd Nevada City CA 95959",
    "addr:housenumber":"11910",
    "addr:postcode":"95959",
    "addr:street":"Crystal Wells Rd",
    "iso:country":"US",
    "sg:address":"11910 Crystal Wells Rd",
    "sg:city":"Nevada City",
    "sg:classifiers":[
        {
            "category":"Travel",
            "subcategory":"Travel Agent",
            "type":"Entertainment"
        }
    ],
    "sg:phone":"+1 530 265 5823",
    "sg:postcode":"95959",
    "sg:province":"CA",
    "sg:tags":[
        "agency"
    ],
    "wof:name":"Travel By Mindy",
    "wof:placetype":"venue"
},
  "geometry": {"coordinates":[-120.95695499999999,39.257482],"type":"Point"}
}