{
  "type": "Feature",
  "properties": {
    "addr:full":"1904 Biglow Dr Antioch CA 94509",
    "addr:housenumber":"1904",
    "addr:postcode":"ca 94509",
    "addr:street":"Biglow Dr",
    "iso:country":"US",
    "sg:address":"1904 Biglow Dr",
    "sg:city":"Antioch",
    "sg:classifiers":[
        {
            "category":"Real Estate",
            "subcategory":"Real Estate Agent",
            "type":"Services"
        }
    ],
    "sg:phone":"+1 925 757 0420",
    "sg:postcode":"94509",
    "sg:province":"CA",
    "wof:name":"Real Estate Connection The",
    "wof:placetype":"venue"
},
  "geometry": {"coordinates":[-121.793971,38.000784],"type":"Point"}
}