{
  "type": "Feature",
  "properties": {
    "addr:full":"850 Cirby Way Roseville CA 95661",
    "addr:housenumber":"850",
    "addr:postcode":"95661",
    "addr:street":"Cirby Way",
    "iso:country":"US",
    "sg:address":"850 Cirby Way",
    "sg:city":"Roseville",
    "sg:classifiers":[
        {
            "category":"Place Of Worship",
            "subcategory":"Church",
            "type":"Public Place"
        },
        {
            "category":"Place Of Worship",
            "type":"Public Place"
        },
        {
            "category":"Organizations",
            "subcategory":"Religious Organization",
            "type":"Services"
        }
    ],
    "sg:phone":"+1 916 787 5260",
    "sg:postcode":"95661",
    "sg:province":"CA",
    "sg:tags":[
        "god",
        "god-independent",
        "churches-assemblies",
        "denomination",
        "churches-interdenominational",
        "churches-various"
    ],
    "sg:website":"http://www.lightofthegospel.org",
    "wof:name":"Light Of The Gospel Missionary",
    "wof:placetype":"venue"
},
  "geometry": {"coordinates":[-121.282471,38.72945],"type":"Point"}
}