{
  "type": "Feature",
  "properties": {
    "addr:full":"4729 San Juan Ave Fair Oaks CA 95628",
    "addr:housenumber":"4729",
    "addr:postcode":"95628",
    "addr:street":"San Juan Ave",
    "iso:country":"US",
    "sg:address":"4729 San Juan Ave",
    "sg:city":"Fair Oaks",
    "sg:classifiers":[
        {
            "category":"Bars & Pubs",
            "type":"Food & Drink"
        }
    ],
    "sg:phone":"+1 916 966 1953",
    "sg:postcode":"95628",
    "sg:province":"CA",
    "sg:website":"www.timeouttavern.net",
    "wof:name":"Time Out Tavern",
    "wof:placetype":"venue"
},
  "geometry": {"coordinates":[-121.29209899999999,38.6493],"type":"Point"}
}