{
  "type": "Feature",
  "properties": {
    "iso:country":"US",
    "sg:address":"1710 Miramonte Ave",
    "sg:city":"Mountain View",
    "sg:classifiers":[
        {
            "category":"Social Services",
            "subcategory":"Child Care",
            "type":"Services"
        }
    ],
    "sg:phone":"+1 650 938 1323",
    "sg:postcode":"94040",
    "sg:province":"CA",
    "wof:name":"Wedgewood Preschool",
    "wof:placetype":"venue"
},
  "geometry": {"coordinates":[-122.087104,37.371388],"type":"Point"}
}