{
  "type": "Feature",
  "properties": {
    "addr:full":"18241 Slover Ave Bloomington CA 92316",
    "addr:housenumber":"18241",
    "addr:postcode":"92316",
    "addr:street":"Slover Ave",
    "iso:country":"US",
    "sg:address":"18241 Slover Ave",
    "sg:city":"Bloomington",
    "sg:classifiers":[
        {
            "category":"Building & Trades",
            "subcategory":"Construction",
            "type":"Services"
        }
    ],
    "sg:phone":"+1 909 421 2218",
    "sg:postcode":"92316",
    "sg:province":"CA",
    "sg:tags":[
        "concrete",
        "contractor"
    ],
    "wof:name":"Santana Concrete",
    "wof:placetype":"venue"
},
  "geometry": {"coordinates":[-117.40783,34.063072],"type":"Point"}
}