{
  "type": "Feature",
  "properties": {
    "iso:country":"US",
    "sg:address":"2519 Coffee Rd",
    "sg:city":"Modesto",
    "sg:classifiers":[
        {
            "category":"Coffee & Tea",
            "type":"Food & Drink"
        }
    ],
    "sg:menulink":"http://www.allmenus.com/ca/modesto/109643-starbucks-coffee/menu/",
    "sg:phone":"+1 209 578 0231",
    "sg:postcode":"95355",
    "sg:province":"CA",
    "sg:tags":[
        "american"
    ],
    "wof:name":"Starbucks Coffee",
    "wof:placetype":"venue"
},
  "geometry": {"coordinates":[-120.97627900000001,37.677689],"type":"Point"}
}