{
  "type": "Feature",
  "properties": {
    "addr:full":"1212 N Broadway Santa Ana CA 92701",
    "addr:housenumber":"1212",
    "addr:postcode":"92701",
    "addr:street":"N Broadway",
    "iso:country":"US",
    "sg:address":"1212 N Broadway",
    "sg:city":"Santa Ana",
    "sg:classifiers":[
        {
            "category":"Health Services",
            "subcategory":"Clinic",
            "type":"Services"
        }
    ],
    "sg:phone":"+1 714 972 2610",
    "sg:postcode":"92701",
    "sg:province":"CA",
    "sg:website":"www.oc-moms.org",
    "wof:name":"MOMS Resource Ctr",
    "wof:placetype":"venue"
},
  "geometry": {"coordinates":[-117.86977400000001,33.7552],"type":"Point"}
}