{
  "type": "Feature",
  "properties": {
    "iso:country":"US",
    "sg:address":"20700 Ventura Blvd., #100",
    "sg:city":"Los Angeles",
    "sg:classifiers":[
        {
            "category":"Health Services",
            "subcategory":"Clinic",
            "type":"Services"
        },
        {
            "category":"Education",
            "subcategory":"Dance Studio",
            "type":"Public Place"
        }
    ],
    "sg:phone":"+1 818 716 7677",
    "sg:postcode":"91364",
    "sg:province":"CA",
    "sg:tags":[
        "medical"
    ],
    "sg:website":"www.dancefitnesswithrhonda.com",
    "wof:name":"Jazzercise",
    "wof:placetype":"venue"
},
  "geometry": {"coordinates":[-118.58398,34.166656],"type":"Point"}
}