{
  "type": "Feature",
  "properties": {
    "iso:country":"US",
    "sg:address":"11241 Valley Spring Ln",
    "sg:city":"North Hollywood",
    "sg:classifiers":[
        {
            "category":"Professional",
            "type":"Services"
        }
    ],
    "sg:phone":"+1 818 487 8544",
    "sg:postcode":"91602",
    "sg:province":"CA",
    "wof:name":"Cheryl C Quinto",
    "wof:placetype":"venue"
},
  "geometry": {"coordinates":[-118.37640399999999,34.147258],"type":"Point"}
}