{
  "type": "Feature",
  "properties": {
    "addr:full":"3076 Union Ave. San Jose CA 95124",
    "addr:housenumber":"3076",
    "addr:postcode":"95124",
    "addr:street":"Union Ave.",
    "iso:country":"US",
    "sg:address":"3076 Union Ave.",
    "sg:city":"San Jose",
    "sg:classifiers":[
        {
            "category":"Health Services",
            "subcategory":"Clinic",
            "type":"Services"
        },
        {
            "category":"Personal",
            "subcategory":"Beauty Salon",
            "type":"Services"
        }
    ],
    "sg:phone":"+1 408 469 5633",
    "sg:postcode":"95124",
    "sg:province":"CA",
    "sg:tags":[
        "spa",
        "medical"
    ],
    "wof:name":"Daniel Moskowitz",
    "wof:placetype":"venue"
},
  "geometry": {"coordinates":[-121.931106,37.266625],"type":"Point"}
}