{
  "type": "Feature",
  "properties": {
    "iso:country":"US",
    "sg:address":"1324 S La Brea Ave",
    "sg:city":"Los Angeles",
    "sg:classifiers":[
        {
            "category":"Retail",
            "subcategory":"Auto Repair",
            "type":"Services"
        }
    ],
    "sg:phone":"+1 323 938 7977",
    "sg:postcode":"90019",
    "sg:province":"CA",
    "sg:tags":[
        "body",
        "shop"
    ],
    "wof:name":"Citizen Collision",
    "wof:placetype":"venue"
},
  "geometry": {"coordinates":[-118.344002,34.049702],"type":"Point"}
}