{
  "type": "Feature",
  "properties": {
    "addr:full":"40277 Big Bear Blvd Big Bear Lake CA 92315",
    "addr:housenumber":"40277",
    "addr:postcode":"92315",
    "addr:street":"Big Bear Blvd",
    "iso:country":"US",
    "sg:address":"40277 Big Bear Blvd",
    "sg:city":"Big Bear Lake",
    "sg:classifiers":[
        {
            "category":"Building & Trades",
            "subcategory":"Construction",
            "type":"Services"
        }
    ],
    "sg:phone":"+1 909 866 0675",
    "sg:postcode":"92315",
    "sg:province":"CA",
    "sg:tags":[
        "contractor"
    ],
    "wof:name":"Heritage Construction Svc",
    "wof:placetype":"venue"
},
  "geometry": {"coordinates":[-116.9233,34.238676],"type":"Point"}
}