{
  "type": "Feature",
  "properties": {
    "addr:full":"1820 Empire Industrial Ct Santa Rosa CA 95403",
    "addr:housenumber":"1820",
    "addr:postcode":"95403",
    "addr:street":"Empire Industrial Ct",
    "iso:country":"US",
    "sg:address":"1820 Empire Industrial Ct",
    "sg:city":"Santa Rosa",
    "sg:classifiers":[
        {
            "category":"Wholesale",
            "subcategory":"Office Equipment",
            "type":"Manufacturing & Wholesale Goods"
        }
    ],
    "sg:phone":"+1 707 528 7878",
    "sg:postcode":"95403",
    "sg:province":"CA",
    "sg:tags":[
        "credit",
        "system",
        "card"
    ],
    "wof:name":"North Bay Merchant Svc",
    "wof:placetype":"venue"
},
  "geometry": {"coordinates":[-122.747833,38.469714],"type":"Point"}
}