{
  "type": "Feature",
  "properties": {
    "iso:country":"US",
    "sg:address":"5545 Ardilla Rd",
    "sg:city":"Atascadero",
    "sg:classifiers":[
        {
            "category":"Organizations",
            "subcategory":"Religious Organization",
            "type":"Services"
        }
    ],
    "sg:phone":"+1 805 466 2626",
    "sg:postcode":"93422",
    "sg:province":"CA",
    "sg:tags":[
        "church"
    ],
    "sg:website":"www.atascaderofirst.com",
    "wof:name":"First Assembly Of God",
    "wof:placetype":"venue"
},
  "geometry": {"coordinates":[-120.676316,35.48984],"type":"Point"}
}