{
  "type": "Feature",
  "properties": {
    "addr:full":"4189 Rolando Blvd San Diego CA 92115",
    "addr:housenumber":"4189",
    "addr:postcode":"92115",
    "addr:street":"Rolando Blvd",
    "iso:country":"US",
    "sg:address":"4189 Rolando Blvd",
    "sg:city":"San Diego",
    "sg:classifiers":[
        {
            "category":"Retail",
            "subcategory":"Auto Repair",
            "type":"Services"
        }
    ],
    "sg:phone":"+1 619 287 8556",
    "sg:postcode":"92115",
    "sg:province":"CA",
    "sg:tags":[
        "repairing",
        "automobile"
    ],
    "wof:name":"Charles Auto Repair",
    "wof:placetype":"venue"
},
  "geometry": {"coordinates":[-117.058262,32.754025],"type":"Point"}
}