{
  "type": "Feature",
  "properties": {
    "addr:full":"4221 Wilshire Blvd Los Angeles CA 90010",
    "addr:housenumber":"4221",
    "addr:postcode":"90010",
    "addr:street":"Wilshire Blvd",
    "iso:country":"US",
    "sg:address":"4221 Wilshire Blvd",
    "sg:city":"Los Angeles",
    "sg:classifiers":[
        {
            "category":"Real Estate",
            "subcategory":"Real Estate Agent",
            "type":"Services"
        }
    ],
    "sg:phone":"+1 323 937 7800",
    "sg:postcode":"90010",
    "sg:province":"CA",
    "wof:name":"Citizens Realty Inc",
    "wof:placetype":"venue"
},
  "geometry": {"coordinates":[-118.31965,34.061813],"type":"Point"}
}