{
  "type": "Feature",
  "properties": {
    "addr:full":"15126 Paramount Blvd Paramount CA 90723",
    "addr:housenumber":"15126",
    "addr:postcode":"90723",
    "addr:street":"Paramount Blvd",
    "iso:country":"US",
    "sg:address":"15126 Paramount Blvd",
    "sg:city":"Paramount",
    "sg:classifiers":[
        {
            "category":"Shopping",
            "subcategory":"Mobile Phones",
            "type":"Retail Goods"
        }
    ],
    "sg:phone":"+1 562 630 2100",
    "sg:postcode":"90723",
    "sg:province":"CA",
    "wof:name":"Axscell",
    "wof:placetype":"venue"
},
  "geometry": {"coordinates":[-118.159864,33.89598],"type":"Point"}
}