{
  "type": "Feature",
  "properties": {
    "iso:country":"US",
    "sg:address":"7777 Alvarado Rd",
    "sg:city":"La Mesa",
    "sg:classifiers":[
        {
            "category":"Banks & Credit Unions",
            "subcategory":"Financial Services",
            "type":"Services"
        }
    ],
    "sg:phone":"+1 619 520 9138",
    "sg:postcode":"91942",
    "sg:province":"CA",
    "sg:tags":[
        "broker",
        "mortgage"
    ],
    "sg:website":"imortgage.com/",
    "wof:name":"Imortgage",
    "wof:placetype":"venue"
},
  "geometry": {"coordinates":[-117.031814,32.771774],"type":"Point"}
}