{
  "type": "Feature",
  "properties": {
    "iso:country":"US",
    "sg:address":"538 Abrego St",
    "sg:city":"Monterey",
    "sg:classifiers":[
        {
            "category":"Professional",
            "subcategory":"Business Services",
            "type":"Services"
        }
    ],
    "sg:phone":"+1 831 647 9777",
    "sg:postcode":"93940",
    "sg:province":"CA",
    "sg:tags":[
        "information",
        "referral"
    ],
    "wof:name":"Targus Info",
    "wof:placetype":"venue"
},
  "geometry": {"coordinates":[-121.89237300000001,36.596659],"type":"Point"}
}