{
  "type": "Feature",
  "properties": {
    "iso:country":"US",
    "sg:address":"292 Alamo Dr",
    "sg:city":"Vacaville",
    "sg:classifiers":[
        {
            "category":"Health Services",
            "subcategory":"Health Practitioner",
            "type":"Services"
        }
    ],
    "sg:phone":"+1 707 446 8001",
    "sg:postcode":"95688",
    "sg:province":"CA",
    "sg:tags":[
        "psychologist"
    ],
    "wof:name":"John E Leonard PHD",
    "wof:placetype":"venue"
},
  "geometry": {"coordinates":[-122.009808,38.355193],"type":"Point"}
}