{
  "type": "Feature",
  "properties": {
    "iso:country":"US",
    "sg:address":"10668 Summer Breeze Dr",
    "sg:city":"Moreno Valley",
    "sg:classifiers":[
        {
            "category":"Building & Trades",
            "subcategory":"Landscaping Services",
            "type":"Services"
        }
    ],
    "sg:phone":"+1 951 247 7905",
    "sg:postcode":"92557",
    "sg:province":"CA",
    "wof:name":"Jz Landscaping",
    "wof:placetype":"venue"
},
  "geometry": {"coordinates":[-117.229939,33.96587],"type":"Point"}
}