{
  "type": "Feature",
  "properties": {
    "addr:full":"812 W Laurel Ave Lompoc CA 93436",
    "addr:housenumber":"812",
    "addr:postcode":"93436",
    "addr:street":"W Laurel Ave",
    "iso:country":"US",
    "sg:address":"812 W Laurel Ave",
    "sg:city":"Lompoc",
    "sg:classifiers":[
        {
            "category":"Real Estate",
            "subcategory":"Real Estate Operator",
            "type":"Services"
        }
    ],
    "sg:phone":"+1 805 736 3350",
    "sg:postcode":"93436",
    "sg:province":"CA",
    "sg:tags":[
        "apartment"
    ],
    "wof:name":"Bay Laurel Apartments",
    "wof:placetype":"venue"
},
  "geometry": {"coordinates":[-120.467046,34.643821],"type":"Point"}
}