{
  "type": "Feature",
  "properties": {
    "iso:country":"US",
    "sg:address":"2107 W Florida Ave",
    "sg:city":"Hemet",
    "sg:classifiers":[
        {
            "category":"Real Estate",
            "subcategory":"Real Estate Agent",
            "type":"Services"
        }
    ],
    "sg:phone":"+1 951 766 0039",
    "sg:postcode":"92545",
    "sg:province":"CA",
    "wof:name":"Valley Wide Realty",
    "wof:placetype":"venue"
},
  "geometry": {"coordinates":[-116.993503,33.747366],"type":"Point"}
}