{
  "type": "Feature",
  "properties": {
    "iso:country":"US",
    "sg:address":"2356 Alum Rock Ave",
    "sg:city":"San Jose",
    "sg:classifiers":[
        {
            "category":"Professional",
            "subcategory":"Lawyer & Legal Services",
            "type":"Services"
        }
    ],
    "sg:phone":"+1 408 929 3635",
    "sg:postcode":"95116",
    "sg:province":"CA",
    "sg:tags":[
        "attorney"
    ],
    "wof:name":"Vu Long Law Office",
    "wof:placetype":"venue"
},
  "geometry": {"coordinates":[-121.842426,37.358932],"type":"Point"}
}