{
  "type": "Feature",
  "properties": {
    "addr:full":"4910 Birch Street Newport Beach CA 92660",
    "addr:housenumber":"4910",
    "addr:postcode":"92660",
    "addr:street":"Birch Street",
    "iso:country":"US",
    "sg:address":"4910 Birch Street",
    "sg:city":"Newport Beach",
    "sg:classifiers":[
        {
            "category":"Banks & Credit Unions",
            "subcategory":"Investment Brokerage",
            "type":"Services"
        }
    ],
    "sg:phone":"+1 949 752 1400",
    "sg:postcode":"92660",
    "sg:province":"CA",
    "sg:tags":[
        "investing"
    ],
    "wof:name":"Monex Deposit Company",
    "wof:placetype":"venue"
},
  "geometry": {"coordinates":[-117.860608,33.667433],"type":"Point"}
}