{
  "type": "Feature",
  "properties": {
    "iso:country":"US",
    "sg:address":"463 S Patrick Rd",
    "sg:city":"Stockton",
    "sg:phone":"+1 209 944 9944",
    "sg:postcode":"95215",
    "sg:province":"CA",
    "sg:tags":[
        "farm",
        "corn"
    ],
    "wof:name":"Julio Escobedo",
    "wof:placetype":"venue"
},
  "geometry": {"coordinates":[-121.17111,37.962241],"type":"Point"}
}