{
  "type": "Feature",
  "properties": {
    "iso:country":"US",
    "sg:address":"10162 Live Oak Ave",
    "sg:city":"Fontana",
    "sg:classifiers":[
        {
            "category":"Autos & Motor Vehicles",
            "subcategory":"Automobile Sales",
            "type":"Retail Goods"
        }
    ],
    "sg:phone":"+1 951 232 7272",
    "sg:postcode":"92335",
    "sg:province":"CA",
    "sg:tags":[
        "car",
        "dealer"
    ],
    "wof:name":"Pacific Enterprise",
    "wof:placetype":"venue"
},
  "geometry": {"coordinates":[-117.480038,34.068323],"type":"Point"}
}