{
  "type": "Feature",
  "properties": {
    "addr:full":"2211 Corinth Ave Ste 307 Los Angeles CA 90064",
    "addr:housenumber":"2211",
    "addr:postcode":"90064",
    "addr:street":"Corinth Ave Ste 307",
    "iso:country":"US",
    "sg:address":"2211 Corinth Ave Ste 307",
    "sg:city":"Los Angeles",
    "sg:classifiers":[
        {
            "category":"Health Services",
            "subcategory":"Health Practitioner",
            "type":"Services"
        },
        {
            "category":"Health Services",
            "subcategory":"Chiropractor",
            "type":"Services"
        }
    ],
    "sg:phone":"+1 310 312 4888",
    "sg:postcode":"90064",
    "sg:province":"CA",
    "sg:tags":[
        "nutritionist"
    ],
    "wof:name":"Creative Nutrition",
    "wof:placetype":"venue"
},
  "geometry": {"coordinates":[-118.442003,34.036887],"type":"Point"}
}