{
  "type": "Feature",
  "properties": {
    "addr:full":"23545 Old 44 Dr Millville CA 96062",
    "addr:housenumber":"23545",
    "addr:postcode":"96062",
    "addr:street":"Old 44 Dr",
    "iso:country":"US",
    "sg:address":"23545 Old 44 Dr",
    "sg:city":"Millville",
    "sg:classifiers":[
        {
            "category":"Farming",
            "subcategory":"Livestock Farm",
            "type":"Manufacturing & Wholesale Goods"
        }
    ],
    "sg:phone":"+1 530 547 5184",
    "sg:postcode":"96062",
    "sg:province":"CA",
    "sg:tags":[
        "emu"
    ],
    "wof:name":"Emu America Extraordinaire",
    "wof:placetype":"venue"
},
  "geometry": {"coordinates":[-122.19036199999999,40.562713],"type":"Point"}
}