{
  "type": "Feature",
  "properties": {
    "addr:full":"105 Tamarack Dr Hillsborough CA 94010",
    "addr:housenumber":"105",
    "addr:postcode":"94010",
    "addr:street":"Tamarack Dr",
    "iso:country":"US",
    "sg:address":"105 Tamarack Dr",
    "sg:city":"Hillsborough",
    "sg:classifiers":[
        {
            "category":"Banks & Credit Unions",
            "subcategory":"Investment Brokerage",
            "type":"Services"
        }
    ],
    "sg:phone":"+1 650 558 1962",
    "sg:postcode":"94010",
    "sg:province":"CA",
    "sg:tags":[
        "advisory"
    ],
    "wof:name":"Cozad Investments Lp",
    "wof:placetype":"venue"
},
  "geometry": {"coordinates":[-122.35914699999999,37.565],"type":"Point"}
}