{
  "type": "Feature",
  "properties": {
    "iso:country":"US",
    "sg:address":"4354 Clear Valley Dr",
    "sg:city":"Encino",
    "sg:classifiers":[
        {
            "category":"Professional",
            "subcategory":"Business Services",
            "type":"Services"
        }
    ],
    "sg:phone":"+1 818 990 3247",
    "sg:postcode":"91436",
    "sg:province":"CA",
    "sg:tags":[
        "interior",
        "consultant",
        "design",
        "decorator"
    ],
    "wof:name":"Richard Savage & Assoc Inc",
    "wof:placetype":"venue"
},
  "geometry": {"coordinates":[-118.48586899999999,34.150694],"type":"Point"}
}