{
  "type": "Feature",
  "properties": {
    "iso:country":"US",
    "sg:address":"5995 Pacific Mesa Ct",
    "sg:city":"San Diego",
    "sg:classifiers":[
        {
            "category":"Travel",
            "subcategory":"Hotels & Motels",
            "type":"Entertainment"
        }
    ],
    "sg:phone":"+1 858 552 9100",
    "sg:postcode":"92121",
    "sg:province":"CA",
    "sg:tags":[
        "operation"
    ],
    "wof:name":"Residence Inn By Marriott",
    "wof:placetype":"venue"
},
  "geometry": {"coordinates":[-117.191096,32.902166],"type":"Point"}
}