{
  "type": "Feature",
  "properties": {
    "addr:full":"1460 E Holt Ave Pomona CA 91767",
    "addr:housenumber":"1460",
    "addr:postcode":"91767",
    "addr:street":"E Holt Ave",
    "iso:country":"US",
    "sg:address":"1460 E Holt Ave",
    "sg:city":"Pomona",
    "sg:classifiers":[
        {
            "category":"Education",
            "subcategory":"Special Training",
            "type":"Public Place"
        }
    ],
    "sg:phone":"+1 909 623 8816",
    "sg:postcode":"91767",
    "sg:province":"CA",
    "sg:tags":[
        "educational"
    ],
    "wof:name":"Pomona Valley Education Fndtn",
    "wof:placetype":"venue"
},
  "geometry": {"coordinates":[-117.721386,34.063012],"type":"Point"}
}