{
  "type": "Feature",
  "properties": {
    "iso:country":"US",
    "sg:address":"4330 District Blvd",
    "sg:city":"Vernon",
    "sg:classifiers":[
        {
            "category":"Manufacturing",
            "subcategory":"Soap",
            "type":"Manufacturing & Wholesale Goods"
        }
    ],
    "sg:phone":"+1 323 585 8706",
    "sg:postcode":"90058",
    "sg:province":"CA",
    "sg:tags":[
        "housewares-wholesale",
        "manufacturer"
    ],
    "wof:name":"Classic Slipcovers Inc.",
    "wof:placetype":"venue"
},
  "geometry": {"coordinates":[-118.201075,34.000048],"type":"Point"}
}