{
  "type": "Feature",
  "properties": {
    "iso:country":"US",
    "sg:address":"4300 Waterloo Rd",
    "sg:city":"Stockton",
    "sg:classifiers":[
        {
            "category":"Restaurant",
            "type":"Food & Drink"
        }
    ],
    "sg:phone":"+1 209 931 5611",
    "sg:postcode":"95215",
    "sg:province":"CA",
    "wof:name":"Perko's Cafe",
    "wof:placetype":"venue"
},
  "geometry": {"coordinates":[-121.24557299999999,37.987326],"type":"Point"}
}