{
  "type": "Feature",
  "properties": {
    "addr:full":"11217 BARNWALL ST NORWALK CA 90650",
    "addr:housenumber":"11217",
    "addr:postcode":"90650",
    "addr:street":"Barnwall St",
    "iso:country":"US",
    "sg:address":"11217 BARNWALL ST",
    "sg:city":"NORWALK",
    "sg:classifiers":[
        {
            "category":"Real Estate",
            "subcategory":"Real Estate Operator",
            "type":"Services"
        }
    ],
    "sg:phone":"+1 866 310 7829",
    "sg:postcode":"90650",
    "sg:province":"CA",
    "sg:tags":[
        "apartment"
    ],
    "sg:website":"http://www.VillaDelSol-Apts.com",
    "wof:name":"Villa Del Sol",
    "wof:placetype":"venue"
},
  "geometry": {"coordinates":[-118.095027,33.89119],"type":"Point"}
}