{
  "type": "Feature",
  "properties": {
    "addr:full":"13377 Mountain Spring Rd Nevada City CA 95959",
    "addr:housenumber":"13377",
    "addr:postcode":"95959",
    "addr:street":"Mountain Spring Rd",
    "iso:country":"US",
    "sg:address":"13377 Mountain Spring Rd",
    "sg:city":"Nevada City",
    "sg:classifiers":[
        {
            "category":"Home & Garden",
            "subcategory":"Garden Supply",
            "type":"Retail Goods"
        }
    ],
    "sg:phone":"+1 530 559 1475",
    "sg:postcode":"95959",
    "sg:province":"CA",
    "sg:tags":[
        "fertilizer"
    ],
    "wof:name":"Green Arrow Organics",
    "wof:placetype":"venue"
},
  "geometry": {"coordinates":[-120.980994,39.338377],"type":"Point"}
}