{
  "type": "Feature",
  "properties": {
    "addr:full":"3884 1/2 Caminito Aguilar San Diego CA 92111",
    "addr:housenumber":"3884 1 / 2",
    "addr:postcode":"92111",
    "addr:street":"Caminito Aguilar",
    "iso:country":"US",
    "sg:address":"3884 1/2 Caminito Aguilar",
    "sg:city":"San Diego",
    "sg:classifiers":[
        {
            "category":"Real Estate",
            "subcategory":"Real Estate Operator",
            "type":"Services"
        }
    ],
    "sg:phone":"+1 858 278 5200",
    "sg:postcode":"92111",
    "sg:province":"CA",
    "sg:tags":[
        "apartment"
    ],
    "wof:name":"The Stratton Apartments",
    "wof:placetype":"venue"
},
  "geometry": {"coordinates":[-117.176755,32.817107],"type":"Point"}
}