{
  "type": "Feature",
  "properties": {
    "iso:country":"US",
    "sg:address":"1459 E Thousand Oaks Blvd",
    "sg:city":"Thousand Oaks",
    "sg:classifiers":[
        {
            "category":"Shopping",
            "subcategory":"Used Merchandise",
            "type":"Retail Goods"
        }
    ],
    "sg:phone":"+1 805 371 5333",
    "sg:postcode":"91362",
    "sg:province":"CA",
    "sg:tags":[
        "shop",
        "thrift"
    ],
    "wof:name":"Rose Buds",
    "wof:placetype":"venue"
},
  "geometry": {"coordinates":[-118.851347,34.177857],"type":"Point"}
}