{
  "type": "Feature",
  "properties": {
    "addr:full":"1235 N Harbor Blvd Ste 265 Fullerton CA 92832",
    "addr:housenumber":"1235",
    "addr:postcode":"92832",
    "addr:street":"N Harbor Blvd Ste 265",
    "iso:country":"US",
    "sg:address":"1235 N Harbor Blvd Ste 265",
    "sg:city":"Fullerton",
    "sg:classifiers":[
        {
            "category":"Banks & Credit Unions",
            "subcategory":"Bank",
            "type":"Services"
        }
    ],
    "sg:phone":"+1 714 556 2996",
    "sg:postcode":"92832",
    "sg:province":"CA",
    "wof:name":"State Farm Insurance",
    "wof:placetype":"venue"
},
  "geometry": {"coordinates":[-117.925003,33.882401],"type":"Point"}
}