{
  "type": "Feature",
  "properties": {
    "iso:country":"US",
    "sg:address":"14668 7th St",
    "sg:city":"Victorville",
    "sg:classifiers":[
        {
            "category":"Shopping",
            "subcategory":"Jewelry",
            "type":"Retail Goods"
        }
    ],
    "sg:phone":"+1 760 243 6929",
    "sg:postcode":"92395",
    "sg:province":"CA",
    "sg:tags":[
        "jeweler"
    ],
    "wof:name":"Caleb Jewelry",
    "wof:placetype":"venue"
},
  "geometry": {"coordinates":[-117.315246,34.514446],"type":"Point"}
}