{
  "type": "Feature",
  "properties": {
    "addr:full":"3683 E Colorado Blvd Pasadena CA 91107",
    "addr:housenumber":"3683",
    "addr:postcode":"91107",
    "addr:street":"E Colorado Blvd",
    "iso:country":"US",
    "sg:address":"3683 E Colorado Blvd",
    "sg:city":"Pasadena",
    "sg:classifiers":[
        {
            "category":"Shopping",
            "subcategory":"Computers & Home Electronics",
            "type":"Retail Goods"
        }
    ],
    "sg:phone":"+1 626 792 4145",
    "sg:postcode":"91107",
    "sg:province":"CA",
    "wof:name":"Electro Tec Services",
    "wof:placetype":"venue"
},
  "geometry": {"coordinates":[-118.07399700000001,34.1464],"type":"Point"}
}