{
  "type": "Feature",
  "properties": {
    "iso:country":"US",
    "sg:address":"PO Box 381071",
    "sg:city":"Los Angeles",
    "sg:classifiers":[
        {
            "category":"Retail",
            "subcategory":"Auto Repair",
            "type":"Services"
        }
    ],
    "sg:phone":"+1 323 466 3004",
    "sg:postcode":"90038",
    "sg:province":"CA",
    "wof:name":"Hollywood Transmissions",
    "wof:placetype":"venue"
},
  "geometry": {"coordinates":[-118.323997,34.089802],"type":"Point"}
}