{
  "type": "Feature",
  "properties": {
    "addr:full":"3925 Rosemead Blvd Rosemead CA 91770",
    "addr:housenumber":"3925",
    "addr:postcode":"91770",
    "addr:street":"Rosemead Blvd",
    "iso:country":"US",
    "sg:address":"3925 Rosemead Blvd",
    "sg:city":"Rosemead",
    "sg:classifiers":[
        {
            "category":"Insurance",
            "subcategory":"Insurance Agent",
            "type":"Services"
        },
        {
            "category":"Insurance",
            "subcategory":"Hazard Insurance",
            "type":"Services"
        },
        {
            "category":"Insurance",
            "subcategory":"Title Insurance",
            "type":"Services"
        },
        {
            "category":"Insurance",
            "subcategory":"Life Insurance",
            "type":"Services"
        }
    ],
    "sg:phone":"+1 626 571 8834",
    "sg:postcode":"91770",
    "sg:province":"CA",
    "sg:tags":[
        "business",
        "auto",
        "commercial",
        "homeowner",
        "motorcycle",
        "renter"
    ],
    "wof:name":"Allstate Insurance Company - Steve Wong",
    "wof:placetype":"venue"
},
  "geometry": {"coordinates":[-118.07322499999999,34.079391],"type":"Point"}
}