{
  "type": "Feature",
  "properties": {
    "iso:country":"US",
    "sg:address":"2288 Westwood Blvd Ste 100",
    "sg:city":"Los Angeles",
    "sg:classifiers":[
        {
            "category":"Health Services",
            "subcategory":"Doctor",
            "type":"Services"
        }
    ],
    "sg:phone":"+1 310 475 5377",
    "sg:postcode":"90064",
    "sg:province":"CA",
    "sg:tags":[
        "podiatrist"
    ],
    "wof:name":"Chun Carolyn DPM",
    "wof:placetype":"venue"
},
  "geometry": {"coordinates":[-118.43,34.0425],"type":"Point"}
}