{
  "type": "Feature",
  "properties": {
    "iso:country":"US",
    "sg:address":"405 W College Ave",
    "sg:city":"Santa Rosa",
    "sg:classifiers":[
        {
            "category":"Wholesale",
            "subcategory":"Office Equipment",
            "type":"Manufacturing & Wholesale Goods"
        }
    ],
    "sg:phone":"+1 707 584 4777",
    "sg:postcode":"95401",
    "sg:province":"CA",
    "sg:tags":[
        "machine",
        "duplicating",
        "copying"
    ],
    "wof:name":"Lainer Worldwide Inc",
    "wof:placetype":"venue"
},
  "geometry": {"coordinates":[-122.73147400000001,38.445843],"type":"Point"}
}