{
  "type": "Feature",
  "properties": {
    "addr:full":"2072 Lynwood Ter San Jose CA 95128",
    "addr:housenumber":"2072",
    "addr:postcode":"95128",
    "addr:street":"Lynwood Ter",
    "iso:country":"US",
    "sg:address":"2072 Lynwood Ter",
    "sg:city":"San Jose",
    "sg:classifiers":[
        {
            "category":"Building & Trades",
            "subcategory":"Plumbing",
            "type":"Services"
        }
    ],
    "sg:phone":"+1 408 249 0190",
    "sg:postcode":"95128",
    "sg:province":"CA",
    "sg:tags":[
        "air",
        "heating",
        "conditioning",
        "contractor"
    ],
    "wof:name":"Bayless Heating & AC",
    "wof:placetype":"venue"
},
  "geometry": {"coordinates":[-121.936515,37.332447],"type":"Point"}
}