{
  "type": "Feature",
  "properties": {
    "iso:country":"US",
    "sg:address":"433 E Foothill Blvd",
    "sg:city":"Pomona",
    "sg:classifiers":[
        {
            "category":"Travel",
            "subcategory":"Hotels & Motels",
            "type":"Entertainment"
        }
    ],
    "sg:phone":"+1 909 624 2896",
    "sg:postcode":"91767",
    "sg:province":"CA",
    "wof:name":"Stardust Motel",
    "wof:placetype":"venue"
},
  "geometry": {"coordinates":[-117.74164,34.10724],"type":"Point"}
}