{
  "type": "Feature",
  "properties": {
    "iso:country":"US",
    "sg:address":"801 Woodside Rd",
    "sg:city":"Redwood City",
    "sg:classifiers":[
        {
            "category":"Manufacturing",
            "subcategory":"Printing",
            "type":"Manufacturing & Wholesale Goods"
        }
    ],
    "sg:phone":"+1 650 365 4982",
    "sg:postcode":"94061",
    "sg:province":"CA",
    "sg:tags":[
        "commercial",
        "lithographic"
    ],
    "wof:name":"A M Printing & Graphics",
    "wof:placetype":"venue"
},
  "geometry": {"coordinates":[-122.224124,37.466666],"type":"Point"}
}