{
  "type": "Feature",
  "properties": {
    "addr:full":"2412 Stefanie Dr Rocklin CA 95765",
    "addr:housenumber":"2412",
    "addr:postcode":"95765",
    "addr:street":"Stefanie Dr",
    "iso:country":"US",
    "sg:address":"2412 Stefanie Dr",
    "sg:city":"Rocklin",
    "sg:classifiers":[
        {
            "category":"Local Transit",
            "type":"Transportation"
        }
    ],
    "sg:phone":"+1 916 435 3644",
    "sg:postcode":"95765",
    "sg:province":"CA",
    "sg:tags":[
        "passenger"
    ],
    "wof:name":"Coast Limousine & Car Service",
    "wof:placetype":"venue"
},
  "geometry": {"coordinates":[-121.264938,38.82265],"type":"Point"}
}