{
  "type": "Feature",
  "properties": {
    "iso:country":"US",
    "sg:address":"1911 19th St",
    "sg:city":"Santa Monica",
    "sg:classifiers":[
        {
            "category":"Communications",
            "subcategory":"Radio Station",
            "type":"Services"
        }
    ],
    "sg:phone":"+1 310 450 0889",
    "sg:postcode":"90404",
    "sg:province":"CA",
    "sg:tags":[
        "broadcast"
    ],
    "wof:name":"Lifeline Brdcstg Foundation",
    "wof:placetype":"venue"
},
  "geometry": {"coordinates":[-118.471902,34.020288],"type":"Point"}
}