{
  "type": "Feature",
  "properties": {
    "addr:full":"3149 California St. San Francisco CA 94115",
    "addr:housenumber":"3149",
    "addr:postcode":"94115",
    "addr:street":"California St.",
    "iso:country":"US",
    "sg:address":"3149 California St.",
    "sg:city":"San Francisco",
    "sg:classifiers":[
        {
            "category":"Education",
            "subcategory":"Special Training",
            "type":"Public Place"
        }
    ],
    "sg:phone":"+1 415 448 7452",
    "sg:postcode":"94115",
    "sg:province":"CA",
    "sg:tags":[
        "tutoring"
    ],
    "sg:website":"www.msrtutors.com",
    "wof:name":"Ms. R Tutors",
    "wof:placetype":"venue"
},
  "geometry": {"coordinates":[-122.445993,37.787022],"type":"Point"}
}