{
  "type": "Feature",
  "properties": {
    "addr:full":"5252 Topeka Dr Tarzana CA 91356",
    "addr:housenumber":"5252",
    "addr:postcode":"91356",
    "addr:street":"Topeka Dr",
    "iso:country":"US",
    "sg:address":"5252 Topeka Dr",
    "sg:city":"Tarzana",
    "sg:classifiers":[
        {
            "category":"Real Estate",
            "subcategory":"Real Estate Operator",
            "type":"Services"
        }
    ],
    "sg:phone":"+1 818 609 7856",
    "sg:postcode":"91356",
    "sg:province":"CA",
    "sg:tags":[
        "property",
        "lessor"
    ],
    "wof:name":"Genibel",
    "wof:placetype":"venue"
},
  "geometry": {"coordinates":[-118.546498,34.167632],"type":"Point"}
}