{
  "type": "Feature",
  "properties": {
    "iso:country":"US",
    "sg:address":"1171 E Alosta Ave",
    "sg:city":"Azusa",
    "sg:classifiers":[
        {
            "category":"Recreation",
            "type":"Entertainment"
        }
    ],
    "sg:phone":"+1 626 335 0216",
    "sg:postcode":"91702",
    "sg:province":"CA",
    "sg:tags":[
        "martial",
        "arts",
        "instruction"
    ],
    "wof:name":"Red Dragon Karate",
    "wof:placetype":"venue"
},
  "geometry": {"coordinates":[-117.882534,34.128582],"type":"Point"}
}