{
  "type": "Feature",
  "properties": {
    "iso:country":"US",
    "sg:address":"554 E Alisal St",
    "sg:city":"Salinas",
    "sg:classifiers":[
        {
            "category":"Manufacturing",
            "subcategory":"Printing",
            "type":"Manufacturing & Wholesale Goods"
        }
    ],
    "sg:phone":"+1 831 757 3636",
    "sg:postcode":"93905",
    "sg:province":"CA",
    "sg:tags":[
        "commercial"
    ],
    "sg:website":"www.rapidprintingcenter.com",
    "wof:name":"Rapid Printing Ctr",
    "wof:placetype":"venue"
},
  "geometry": {"coordinates":[-121.635713,36.673684],"type":"Point"}
}