{
  "type": "Feature",
  "properties": {
    "iso:country":"US",
    "sg:address":"15816 Arminta St",
    "sg:city":"Van Nuys",
    "sg:classifiers":[
        {
            "category":"Building & Trades",
            "subcategory":"Construction",
            "type":"Services"
        }
    ],
    "sg:phone":"+1 818 781 6220",
    "sg:postcode":"91406",
    "sg:province":"CA",
    "sg:tags":[
        "contractor"
    ],
    "wof:name":"Restore-It",
    "wof:placetype":"venue"
},
  "geometry": {"coordinates":[-118.477827,34.213811],"type":"Point"}
}