{
  "type": "Feature",
  "properties": {
    "addr:full":"1835 Noriega St San Francisco CA 94122",
    "addr:housenumber":"1835",
    "addr:postcode":"94122",
    "addr:street":"Noriega St",
    "iso:country":"US",
    "sg:address":"1835 Noriega St",
    "sg:city":"San Francisco",
    "sg:classifiers":[
        {
            "category":"Banks & Credit Unions",
            "subcategory":"Investment Brokerage",
            "type":"Services"
        }
    ],
    "sg:phone":"+1 415 753 2122",
    "sg:postcode":"94122",
    "sg:province":"CA",
    "sg:tags":[
        "retirement",
        "planning"
    ],
    "wof:name":"Premier Retirement Planning",
    "wof:placetype":"venue"
},
  "geometry": {"coordinates":[-122.48367500000001,37.753851],"type":"Point"}
}