{
  "type": "Feature",
  "properties": {
    "addr:full":"212 G St Eureka CA 95501",
    "addr:housenumber":"212",
    "addr:postcode":"95501",
    "addr:street":"G St",
    "iso:country":"US",
    "sg:address":"212 G St",
    "sg:city":"Eureka",
    "sg:classifiers":[
        {
            "category":"Social Services",
            "type":"Services"
        }
    ],
    "sg:phone":"+1 707 442 5239",
    "sg:postcode":"95501",
    "sg:province":"CA",
    "sg:tags":[
        "organization",
        "welfare"
    ],
    "wof:name":"Community Resource Ctr",
    "wof:placetype":"venue"
},
  "geometry": {"coordinates":[-124.16552799999999,40.804431],"type":"Point"}
}