{
  "type": "Feature",
  "properties": {
    "addr:full":"22361 Antonio Pkwy Rcho Sta Marg CA 92688",
    "addr:housenumber":"22361",
    "addr:postcode":"92688",
    "addr:street":"Antonio Pkwy;Sta Marg",
    "iso:country":"US",
    "sg:address":"22361 Antonio Pkwy",
    "sg:city":"Rcho Sta Marg",
    "sg:classifiers":[
        {
            "category":"Health Services",
            "subcategory":"Chiropractor",
            "type":"Services"
        }
    ],
    "sg:phone":"+1 949 459 8127",
    "sg:postcode":"92688",
    "sg:province":"CA",
    "wof:name":"Advanced Care Chiropractic",
    "wof:placetype":"venue"
},
  "geometry": {"coordinates":[-117.59273,33.633546],"type":"Point"}
}