{
  "type": "Feature",
  "properties": {
    "addr:full":"27240 Turnberry Ln Valencia CA 91355",
    "addr:postcode":"27240;91355",
    "addr:street":"Turnberry Ln",
    "iso:country":"US",
    "sg:address":"27240 Turnberry Ln",
    "sg:city":"Valencia",
    "sg:classifiers":[
        {
            "category":"Health Services",
            "subcategory":"Nursing And Care Facility",
            "type":"Services"
        }
    ],
    "sg:phone":"+1 661 362 0744",
    "sg:postcode":"91355",
    "sg:province":"CA",
    "sg:tags":[
        "home",
        "retirement",
        "community"
    ],
    "wof:name":"Retiring America",
    "wof:placetype":"venue"
},
  "geometry": {"coordinates":[-118.577048,34.421055],"type":"Point"}
}