{
  "type": "Feature",
  "properties": {
    "addr:full":"41655 Regan Way Murrieta CA 92562",
    "addr:postcode":"41655;92562",
    "addr:street":"Regan Way",
    "iso:country":"US",
    "sg:address":"41655 Regan Way",
    "sg:city":"Murrieta",
    "sg:classifiers":[
        {
            "category":"Building & Trades",
            "subcategory":"Construction",
            "type":"Services"
        }
    ],
    "sg:phone":"+1 951 696 4394",
    "sg:postcode":"92562",
    "sg:province":"CA",
    "sg:tags":[
        "general",
        "contractor"
    ],
    "wof:name":"Diligent Contractors",
    "wof:placetype":"venue"
},
  "geometry": {"coordinates":[-117.176473,33.526119],"type":"Point"}
}