{
  "type": "Feature",
  "properties": {
    "addr:full":"9935 Horn Rd Sacramento CA 95827",
    "addr:housenumber":"9935",
    "addr:postcode":"95827",
    "addr:street":"Horn Rd",
    "iso:country":"US",
    "sg:address":"9935 Horn Rd",
    "sg:city":"Sacramento",
    "sg:classifiers":[
        {
            "category":"Wholesale",
            "subcategory":"Construction Materials",
            "type":"Manufacturing & Wholesale Goods"
        },
        {
            "category":"Building & Trades",
            "subcategory":"Construction",
            "type":"Services"
        }
    ],
    "sg:phone":"+1 916 369 1882",
    "sg:postcode":"95827",
    "sg:province":"CA",
    "sg:tags":[
        "granite",
        "contractor"
    ],
    "wof:name":"A Perfect Edge",
    "wof:placetype":"venue"
},
  "geometry": {"coordinates":[-121.324721,38.576189],"type":"Point"}
}