{
  "type": "Feature",
  "properties": {
    "addr:full":"2360 Stockton Blvd Sacramento CA 95817",
    "addr:housenumber":"2360",
    "addr:postcode":"95817",
    "addr:street":"Stockton Blvd",
    "iso:country":"US",
    "sg:address":"2360 Stockton Blvd",
    "sg:city":"Sacramento",
    "sg:classifiers":[
        {
            "category":"Health Services",
            "subcategory":"Dentist",
            "type":"Services"
        }
    ],
    "sg:phone":"+1 916 453 5405",
    "sg:postcode":"95817",
    "sg:province":"CA",
    "wof:name":"Knowles John C Dds Msd",
    "wof:placetype":"venue"
},
  "geometry": {"coordinates":[-121.45711799999999,38.553754],"type":"Point"}
}