{
  "type": "Feature",
  "properties": {
    "iso:country":"US",
    "sg:address":"1588 W Base Line St",
    "sg:city":"San Bernardino",
    "sg:classifiers":[
        {
            "category":"Wholesale",
            "subcategory":"Machinery & Supplies",
            "type":"Manufacturing & Wholesale Goods"
        }
    ],
    "sg:phone":"+1 909 884 7270",
    "sg:postcode":"92411",
    "sg:province":"CA",
    "sg:tags":[
        "salon",
        "beauty"
    ],
    "wof:name":"Hair Town Beauty Supply",
    "wof:placetype":"venue"
},
  "geometry": {"coordinates":[-117.32185800000001,34.121427],"type":"Point"}
}