{
  "type": "Feature",
  "properties": {
    "addr:full":"747 Rimgrove Dr La Puente CA 91744",
    "addr:housenumber":"747",
    "addr:postcode":"91744",
    "addr:street":"Rimgrove Dr",
    "iso:country":"US",
    "sg:address":"747 Rimgrove Dr",
    "sg:city":"La Puente",
    "sg:classifiers":[
        {
            "category":"Recreation",
            "type":"Entertainment"
        }
    ],
    "sg:phone":"+1 626 961 6393",
    "sg:postcode":"91744",
    "sg:province":"CA",
    "sg:tags":[
        "parks"
    ],
    "wof:name":"Parks & Recreation Dept",
    "wof:placetype":"venue"
},
  "geometry": {"coordinates":[-117.919816,34.030332],"type":"Point"}
}