{
  "type": "Feature",
  "properties": {
    "addr:full":"166 N Sunrise Way Palm Springs CA 92262",
    "addr:housenumber":"166",
    "addr:postcode":"92262",
    "addr:street":"N Sunrise Way",
    "iso:country":"US",
    "sg:address":"166 N Sunrise Way",
    "sg:city":"Palm Springs",
    "sg:classifiers":[
        {
            "category":"Autos & Motor Vehicles",
            "subcategory":"Fuel & Gas Station",
            "type":"Retail Goods"
        }
    ],
    "sg:phone":"+1 760 323 3212",
    "sg:postcode":"92262",
    "sg:province":"CA",
    "sg:tags":[
        "oil"
    ],
    "wof:name":"Palm Springs Oil Company",
    "wof:placetype":"venue"
},
  "geometry": {"coordinates":[-116.52800000000001,33.824001],"type":"Point"}
}