{
  "type": "Feature",
  "properties": {
    "addr:full":"5000 Redwood Rd Hughson CA 95326",
    "addr:housenumber":"5000",
    "addr:postcode":"95326",
    "addr:street":"Redwood Rd",
    "iso:country":"US",
    "sg:address":"5000 Redwood Rd",
    "sg:city":"Hughson",
    "sg:classifiers":[
        {
            "category":"Farming",
            "subcategory":"Crops",
            "type":"Manufacturing & Wholesale Goods"
        }
    ],
    "sg:phone":"+1 209 883 0591",
    "sg:postcode":"95326",
    "sg:province":"CA",
    "sg:tags":[
        "grove",
        "nut",
        "tree"
    ],
    "wof:name":"Turner Farms",
    "wof:placetype":"venue"
},
  "geometry": {"coordinates":[-120.89266000000001,37.572925],"type":"Point"}
}