{
  "type": "Feature",
  "properties": {
    "addr:full":"337 N Avalon Blvd Wilmington CA 90744",
    "addr:housenumber":"337",
    "addr:postcode":"90744",
    "addr:street":"N Avalon Blvd",
    "iso:country":"US",
    "sg:address":"337 N Avalon Blvd",
    "sg:city":"Wilmington",
    "sg:classifiers":[
        {
            "category":"Wholesale",
            "subcategory":"Machinery & Supplies",
            "type":"Manufacturing & Wholesale Goods"
        }
    ],
    "sg:phone":"+1 310 518 5021",
    "sg:postcode":"90744",
    "sg:province":"CA",
    "sg:tags":[
        "machine",
        "shop"
    ],
    "wof:name":"E & V Auto Parts",
    "wof:placetype":"venue"
},
  "geometry": {"coordinates":[-118.262016,33.773636],"type":"Point"}
}