{
  "type": "Feature",
  "properties": {
    "iso:country":"US",
    "sg:address":"112 B Stockton Ave",
    "sg:city":"Capitola",
    "sg:classifiers":[
        {
            "category":"Personal",
            "subcategory":"Psychics & Astrologers",
            "type":"Services"
        }
    ],
    "sg:phone":"+1 831 435 8459",
    "sg:postcode":"95010",
    "sg:province":"CA",
    "sg:website":"www.yourpsychicsolution.info",
    "wof:name":"Psychic Solutions",
    "wof:placetype":"venue"
},
  "geometry": {"coordinates":[-121.952338,36.972859],"type":"Point"}
}