{
  "type": "Feature",
  "properties": {
    "iso:country":"US",
    "sg:address":"139 Ave Mateo",
    "sg:city":"San Clemente",
    "sg:classifiers":[
        {
            "category":"Building & Trades",
            "subcategory":"Construction",
            "type":"Services"
        }
    ],
    "sg:phone":"+1 949 361 4811",
    "sg:postcode":"92672",
    "sg:province":"CA",
    "sg:tags":[
        "house"
    ],
    "wof:name":"G&M Handyman Services",
    "wof:placetype":"venue"
},
  "geometry": {"coordinates":[-117.611089,33.425136],"type":"Point"}
}