{
  "type": "Feature",
  "properties": {
    "addr:full":"73402 Varner Rd Thousand Palms CA 92276",
    "addr:postcode":"73402;92276",
    "addr:street":"Varner Rd",
    "iso:country":"US",
    "sg:address":"73402 Varner Rd",
    "sg:city":"Thousand Palms",
    "sg:classifiers":[
        {
            "category":"Freight",
            "type":"Transportation"
        }
    ],
    "sg:phone":"+1 760 343 1550",
    "sg:postcode":"92276",
    "sg:province":"CA",
    "sg:tags":[
        "commercial",
        "storage"
    ],
    "wof:name":"Monterey Palms Self Storage",
    "wof:placetype":"venue"
},
  "geometry": {"coordinates":[-116.38276,33.803084],"type":"Point"}
}