{
  "type": "Feature",
  "properties": {
    "addr:full":"1320 Apple Ave Ste 102 Hayward CA 94541",
    "addr:housenumber":"1320",
    "addr:postcode":"94541",
    "addr:street":"Apple Ave Ste 102",
    "iso:country":"US",
    "sg:address":"1320 Apple Ave Ste 102",
    "sg:city":"Hayward",
    "sg:classifiers":[
        {
            "category":"Health Services",
            "subcategory":"Doctor",
            "type":"Services"
        }
    ],
    "sg:phone":"+1 510 886 8854",
    "sg:postcode":"94541",
    "sg:province":"CA",
    "wof:name":"Rajaram Kasturi MD Faap",
    "wof:placetype":"venue"
},
  "geometry": {"coordinates":[-122.093002,37.684502],"type":"Point"}
}