{
  "type": "Feature",
  "properties": {
    "iso:country":"US",
    "sg:address":"1441 W Central Park Ave N",
    "sg:city":"Anaheim",
    "sg:classifiers":[
        {
            "category":"Food & Beverages",
            "subcategory":"Candy",
            "type":"Retail Goods"
        }
    ],
    "sg:phone":"+1 714 999 5967",
    "sg:postcode":"92802",
    "sg:province":"CA",
    "sg:tags":[
        "store"
    ],
    "wof:name":"Caracol Toys",
    "wof:placetype":"venue"
},
  "geometry": {"coordinates":[-117.931527,33.827347],"type":"Point"}
}