{
  "type": "Feature",
  "properties": {
    "iso:country":"US",
    "sg:address":"2575 5th Ave",
    "sg:city":"Oroville",
    "sg:classifiers":[
        {
            "category":"Manufacturing",
            "subcategory":"Tools & Machinery",
            "type":"Manufacturing & Wholesale Goods"
        }
    ],
    "sg:phone":"+1 530 533 2261",
    "sg:postcode":"95965",
    "sg:province":"CA",
    "sg:tags":[
        "machine",
        "shop"
    ],
    "wof:name":"Wright Precision",
    "wof:placetype":"venue"
},
  "geometry": {"coordinates":[-121.565465,39.497114],"type":"Point"}
}