{
  "type": "Feature",
  "properties": {
    "iso:country":"US",
    "sg:address":"2483 N Marks Ave",
    "sg:city":"Fresno",
    "sg:classifiers":[
        {
            "category":"Home & Garden",
            "subcategory":"Building Materials",
            "type":"Retail Goods"
        },
        {
            "category":"Retail",
            "subcategory":"Repair Shop",
            "type":"Services"
        }
    ],
    "sg:phone":"+1 559 275 8505",
    "sg:postcode":"93722",
    "sg:province":"CA",
    "sg:tags":[
        "plate",
        "window",
        "glass",
        "flat",
        "mfg"
    ],
    "wof:name":"Dan's Glass & Screen",
    "wof:placetype":"venue"
},
  "geometry": {"coordinates":[-119.844418,36.774068],"type":"Point"}
}