{
  "type": "Feature",
  "properties": {
    "iso:country":"US",
    "sg:address":"927 F St",
    "sg:city":"Fresno",
    "sg:classifiers":[
        {
            "category":"Restaurant",
            "type":"Food & Drink"
        }
    ],
    "sg:phone":"+1 559 233 8024",
    "sg:postcode":"93706",
    "sg:province":"CA",
    "sg:tags":[
        "eating"
    ],
    "wof:name":"Paris Cafe",
    "wof:placetype":"venue"
},
  "geometry": {"coordinates":[-119.794698,36.730151],"type":"Point"}
}