{
  "type": "Feature",
  "properties": {
    "iso:country":"US",
    "sg:address":"7567 Victoria Ave",
    "sg:city":"Highland",
    "sg:classifiers":[
        {
            "category":"Food & Beverages",
            "subcategory":"Liquor & Beverages",
            "type":"Retail Goods"
        }
    ],
    "sg:phone":"+1 909 864 5010",
    "sg:postcode":"92346",
    "sg:province":"CA",
    "sg:tags":[
        "store"
    ],
    "wof:name":"Highland Liquor",
    "wof:placetype":"venue"
},
  "geometry": {"coordinates":[-117.22618900000001,34.116335],"type":"Point"}
}