{
  "type": "Feature",
  "properties": {
    "addr:full":"23211 Erwin St Woodland Hills CA 91367",
    "addr:housenumber":"23211",
    "addr:postcode":"91367",
    "addr:street":"Erwin St",
    "iso:country":"US",
    "sg:address":"23211 Erwin St",
    "sg:city":"Woodland Hills",
    "sg:classifiers":[
        {
            "category":"Retail",
            "subcategory":"Portrait Studio",
            "type":"Services"
        }
    ],
    "sg:phone":"+1 818 591 2880",
    "sg:postcode":"91367",
    "sg:province":"CA",
    "sg:tags":[
        "photographer"
    ],
    "sg:website":"www.springphotography.com",
    "wof:name":"Spring Photography",
    "wof:placetype":"venue"
},
  "geometry": {"coordinates":[-118.63266299999999,34.182863],"type":"Point"}
}