{
  "type": "Feature",
  "properties": {
    "iso:country":"US",
    "sg:address":"35327 Glenwall St",
    "sg:city":"Santa Clarita",
    "sg:classifiers":[
        {
            "category":"Manufacturing",
            "subcategory":"Printing",
            "type":"Manufacturing & Wholesale Goods"
        }
    ],
    "sg:phone":"+1 661 269 0884",
    "sg:postcode":"91390",
    "sg:province":"CA",
    "sg:tags":[
        "newspaper"
    ],
    "wof:name":"Country Journal-Agua Dulce-Act",
    "wof:placetype":"venue"
},
  "geometry": {"coordinates":[-118.254586,34.519542],"type":"Point"}
}