{
  "type": "Feature",
  "properties": {
    "addr:full":"910 J Street San Diego CA 92101",
    "addr:housenumber":"910",
    "addr:postcode":"92101",
    "addr:street":"J Street",
    "iso:country":"US",
    "sg:address":"910 J Street",
    "sg:city":"San Diego",
    "sg:classifiers":[
        {
            "category":"Restaurant",
            "type":"Food & Drink"
        }
    ],
    "sg:phone":"+1 619 232 4782",
    "sg:postcode":"92101",
    "sg:province":"CA",
    "wof:name":"Quiznos Sub",
    "wof:placetype":"venue"
},
  "geometry": {"coordinates":[-117.15646700000001,32.709389],"type":"Point"}
}