{
  "type": "Feature",
  "properties": {
    "addr:full":"115 1st Ave Daly City CA 94014",
    "addr:housenumber":"115",
    "addr:postcode":"94014",
    "addr:street":"1St Ave",
    "iso:country":"US",
    "sg:address":"115 1st Ave",
    "sg:city":"Daly City",
    "sg:classifiers":[
        {
            "category":"Education",
            "subcategory":"School",
            "type":"Public Place"
        }
    ],
    "sg:phone":"+1 650 992 2685",
    "sg:postcode":"94014",
    "sg:province":"CA",
    "sg:website":"www.juhsd.k12.ca.us",
    "wof:name":"Thornton High School",
    "wof:placetype":"venue"
},
  "geometry": {"coordinates":[-122.464162,37.690013],"type":"Point"}
}