{
  "type": "Feature",
  "properties": {
    "addr:full":"1550 S Anaheim Blvd Anaheim CA 92805",
    "addr:housenumber":"1550",
    "addr:postcode":"92805",
    "addr:street":"S Anaheim Blvd",
    "iso:country":"US",
    "sg:address":"1550 S Anaheim Blvd",
    "sg:city":"Anaheim",
    "sg:classifiers":[
        {
            "category":"Shopping",
            "type":"Retail Goods"
        }
    ],
    "sg:phone":"+1 714 635 1401",
    "sg:postcode":"92805",
    "sg:province":"CA",
    "sg:tags":[
        "limb",
        "artificial"
    ],
    "wof:name":"AM-Pro Prosthetics",
    "wof:placetype":"venue"
},
  "geometry": {"coordinates":[-117.905901,33.809886],"type":"Point"}
}