{
  "type": "Feature",
  "properties": {
    "addr:full":"604 N Flores St West Hollywood CA 90048",
    "addr:housenumber":"604",
    "addr:postcode":"90048",
    "addr:street":"N Flores St",
    "iso:country":"US",
    "sg:address":"604 N Flores St",
    "sg:city":"West Hollywood",
    "sg:classifiers":[
        {
            "category":"Home & Garden",
            "subcategory":"Building Materials",
            "type":"Retail Goods"
        }
    ],
    "sg:phone":"+1 323 658 7815",
    "sg:postcode":"90048",
    "sg:province":"CA",
    "sg:tags":[
        "equipment",
        "fixture",
        "lighting"
    ],
    "wof:name":"A-Best Appliance Services",
    "wof:placetype":"venue"
},
  "geometry": {"coordinates":[-118.37094999999999,34.082317],"type":"Point"}
}