{
  "type": "Feature",
  "properties": {
    "addr:full":"919 8th St San Fernando CA 91340",
    "addr:housenumber":"919",
    "addr:postcode":"91340",
    "addr:street":"8Th St",
    "iso:country":"US",
    "sg:address":"919 8th St",
    "sg:city":"San Fernando",
    "sg:classifiers":[
        {
            "category":"Education",
            "subcategory":"School",
            "type":"Public Place"
        }
    ],
    "sg:phone":"+1 818 837 4420",
    "sg:postcode":"91340",
    "sg:province":"CA",
    "sg:website":"www.aboutccms.org",
    "wof:name":"Community Charter Middle Schl",
    "wof:placetype":"venue"
},
  "geometry": {"coordinates":[-118.423064,34.295487],"type":"Point"}
}