{
  "type": "Feature",
  "properties": {
    "addr:full":"445 S Cedar Ave Fresno CA 93702",
    "addr:housenumber":"445",
    "addr:postcode":"93702",
    "addr:street":"S Cedar Ave",
    "iso:country":"US",
    "sg:address":"445 S Cedar Ave",
    "sg:city":"Fresno",
    "sg:classifiers":[
        {
            "category":"Health Services",
            "subcategory":"Doctor",
            "type":"Services"
        }
    ],
    "sg:phone":"+1 559 459 5700",
    "sg:postcode":"93702",
    "sg:province":"CA",
    "sg:tags":[
        "physician",
        "family",
        "practice",
        "surgeons",
        "medicine",
        "surgeon"
    ],
    "wof:name":"Tevendale Robert MD",
    "wof:placetype":"venue"
},
  "geometry": {"coordinates":[-119.754385,36.738931],"type":"Point"}
}