{
  "type": "Feature",
  "properties": {
    "iso:country":"US",
    "sg:address":"847 W 15th St",
    "sg:city":"Long Beach",
    "sg:classifiers":[
        {
            "category":"Wholesale",
            "subcategory":"Metals & Minerals",
            "type":"Manufacturing & Wholesale Goods"
        }
    ],
    "sg:phone":"+1 562 491 0308",
    "sg:postcode":"90813",
    "sg:province":"CA",
    "sg:tags":[
        "center"
    ],
    "wof:name":"Overseas Precision Casting",
    "wof:placetype":"venue"
},
  "geometry": {"coordinates":[-118.201823,33.785921],"type":"Point"}
}