{
  "type": "Feature",
  "properties": {
    "addr:full":"2215 Sonoma Blvd Vallejo CA 94590",
    "addr:housenumber":"2215",
    "addr:postcode":"94590",
    "addr:street":"Sonoma Blvd",
    "iso:country":"US",
    "sg:address":"2215 Sonoma Blvd",
    "sg:city":"Vallejo",
    "sg:classifiers":[
        {
            "category":"Shopping",
            "subcategory":"Computers & Home Electronics",
            "type":"Retail Goods"
        }
    ],
    "sg:phone":"+1 707 647 2039",
    "sg:postcode":"94590",
    "sg:province":"CA",
    "sg:tags":[
        "software"
    ],
    "wof:name":"Excel Magnetic Intl Trading",
    "wof:placetype":"venue"
},
  "geometry": {"coordinates":[-122.25490000000001,38.10639],"type":"Point"}
}