{
  "type": "Feature",
  "properties": {
    "addr:full":"26 Salvatore Dr Novato CA 94949",
    "addr:housenumber":"26",
    "addr:postcode":"94949",
    "addr:street":"Salvatore Dr",
    "iso:country":"US",
    "sg:address":"26 Salvatore Dr",
    "sg:city":"Novato",
    "sg:classifiers":[
        {
            "category":"Professional",
            "subcategory":"Art Services",
            "type":"Services"
        }
    ],
    "sg:phone":"+1 415 382 8206",
    "sg:postcode":"94949",
    "sg:province":"CA",
    "sg:tags":[
        "graphic",
        "designer"
    ],
    "wof:name":"Ranch 7",
    "wof:placetype":"venue"
},
  "geometry": {"coordinates":[-122.541183,38.067114],"type":"Point"}
}