{
  "type": "Feature",
  "properties": {
    "iso:country":"US",
    "sg:address":"8358 Sunset Blvd.",
    "sg:city":"West Hollywood",
    "sg:classifiers":[
        {
            "category":"Professional",
            "type":"Services"
        },
        {
            "category":"Personal",
            "subcategory":"Beauty Salon",
            "type":"Services"
        }
    ],
    "sg:phone":"+1 619 876 8676",
    "sg:postcode":"90069",
    "sg:province":"CA",
    "sg:tags":[
        "spa"
    ],
    "sg:website":"www.sherribelanger.com",
    "wof:name":"Sherri Does Hot Hair",
    "wof:placetype":"venue"
},
  "geometry": {"coordinates":[-118.372284,34.09538],"type":"Point"}
}