{
  "type": "Feature",
  "properties": {
    "addr:full":"3598 Gravenstein Hwy S Sebastopol CA 95472",
    "addr:housenumber":"3598",
    "addr:postcode":"95472",
    "addr:street":"Gravenstein Hwy S",
    "iso:country":"US",
    "sg:address":"3598 Gravenstein Hwy S",
    "sg:city":"Sebastopol",
    "sg:classifiers":[
        {
            "category":"Education",
            "subcategory":"Special Training",
            "type":"Public Place"
        }
    ],
    "sg:phone":"+1 707 829 5668",
    "sg:postcode":"95472",
    "sg:province":"CA",
    "sg:tags":[
        "instruction",
        "music"
    ],
    "wof:name":"Great Burro Studios",
    "wof:placetype":"venue"
},
  "geometry": {"coordinates":[-122.781952,38.366146],"type":"Point"}
}