{
  "type": "Feature",
  "properties": {
    "addr:full":"2400 N Main St Walnut Creek CA 94596",
    "addr:housenumber":"2400",
    "addr:postcode":"94596",
    "addr:street":"N Main St",
    "iso:country":"US",
    "sg:address":"2400 N Main St",
    "sg:city":"Walnut Creek",
    "sg:classifiers":[
        {
            "category":"Restaurant",
            "type":"Food & Drink"
        }
    ],
    "sg:menulink":"http://www.allmenus.com/ca/central-contra-costa/214266-taco-bell/menu/",
    "sg:phone":"+1 925 932 9321",
    "sg:postcode":"94596",
    "sg:province":"CA",
    "sg:tags":[
        "mexican"
    ],
    "wof:name":"Taco Bell",
    "wof:placetype":"venue"
},
  "geometry": {"coordinates":[-122.06509,37.913248],"type":"Point"}
}