{
  "type": "Feature",
  "properties": {
    "addr:full":"1268 Bridgeport Rd Corona CA 92882",
    "addr:housenumber":"1268",
    "addr:postcode":"92882",
    "addr:street":"Bridgeport Rd",
    "iso:country":"US",
    "sg:address":"1268 Bridgeport Rd",
    "sg:city":"Corona",
    "sg:classifiers":[
        {
            "category":"Manufacturing",
            "subcategory":"Motor Vehicles & Parts",
            "type":"Manufacturing & Wholesale Goods"
        }
    ],
    "sg:phone":"+1 951 270 0531",
    "sg:postcode":"92882",
    "sg:province":"CA",
    "sg:tags":[
        "body",
        "mfg"
    ],
    "wof:name":"Bregan Custom Creations",
    "wof:placetype":"venue"
},
  "geometry": {"coordinates":[-117.58782100000001,33.853043],"type":"Point"}
}