{
  "type": "Feature",
  "properties": {
    "addr:full":"1717 Glendale Boulevard Los Angeles CA 90026",
    "addr:housenumber":"1717",
    "addr:postcode":"90026",
    "addr:street":"Glendale Boulevard",
    "iso:country":"US",
    "sg:address":"1717 Glendale Boulevard",
    "sg:city":"Los Angeles",
    "sg:classifiers":[
        {
            "category":"Personal",
            "type":"Services"
        }
    ],
    "sg:phone":"+1 323 660 4600",
    "sg:postcode":"90026",
    "sg:province":"CA",
    "sg:tags":[
        "mover"
    ],
    "wof:name":"Thriftee Storage",
    "wof:placetype":"venue"
},
  "geometry": {"coordinates":[-118.26007799999999,34.086034],"type":"Point"}
}