{
  "type": "Feature",
  "properties": {
    "addr:full":"199 Brannan St San Francisco CA 94107",
    "addr:housenumber":"199",
    "addr:postcode":"94107",
    "addr:street":"Brannan St",
    "iso:country":"US",
    "sg:address":"199 Brannan St",
    "sg:city":"San Francisco",
    "sg:classifiers":[
        {
            "category":"Shopping",
            "subcategory":"Pets & Pet Supplies",
            "type":"Retail Goods"
        }
    ],
    "sg:phone":"+1 415 882 7297",
    "sg:postcode":"94107",
    "sg:province":"CA",
    "sg:tags":[
        "store",
        "groomers"
    ],
    "sg:website":"www.pawtrero.com",
    "wof:name":"Pawtrero Hill Bathhouse & Feed Co.",
    "wof:placetype":"venue"
},
  "geometry": {"coordinates":[-122.389814,37.783608],"type":"Point"}
}