{
  "type": "Feature",
  "properties": {
    "addr:full":"46670 Mohave Dr Fremont CA 94539",
    "addr:postcode":"46670;94539",
    "addr:street":"Mohave Dr",
    "iso:country":"US",
    "sg:address":"46670 Mohave Dr",
    "sg:city":"Fremont",
    "sg:classifiers":[
        {
            "category":"Retail",
            "subcategory":"Laundry & Dry Cleaning",
            "type":"Services"
        }
    ],
    "sg:phone":"+1 510 651 7694",
    "sg:postcode":"94539",
    "sg:province":"CA",
    "wof:name":"Stars Cleaners",
    "wof:placetype":"venue"
},
  "geometry": {"coordinates":[-121.92800099999999,37.492901],"type":"Point"}
}