{
  "type": "Feature",
  "properties": {
    "addr:full":"389 W River Dr Brawley CA 92227",
    "addr:housenumber":"389",
    "addr:postcode":"92227",
    "addr:street":"W River Dr",
    "iso:country":"US",
    "sg:address":"389 W River Dr",
    "sg:city":"Brawley",
    "sg:phone":"+1 760 344 5444",
    "sg:postcode":"92227",
    "sg:province":"CA",
    "sg:tags":[
        "farm",
        "field",
        "crop"
    ],
    "wof:name":"K Hoskins",
    "wof:placetype":"venue"
},
  "geometry": {"coordinates":[-115.54775100000001,32.986587],"type":"Point"}
}