{
  "type": "Feature",
  "properties": {
    "addr:full":"3809 Ming Ave Bakersfield CA 93309",
    "addr:housenumber":"3809",
    "addr:postcode":"93309",
    "addr:street":"Ming Ave",
    "iso:country":"US",
    "sg:address":"3809 Ming Ave",
    "sg:city":"Bakersfield",
    "sg:classifiers":[
        {
            "category":"Bars & Pubs",
            "type":"Food & Drink"
        }
    ],
    "sg:phone":"+1 661 836 3960",
    "sg:postcode":"93309",
    "sg:province":"CA",
    "wof:name":"Cheers",
    "wof:placetype":"venue"
},
  "geometry": {"coordinates":[-119.044955,35.339442],"type":"Point"}
}