{
  "type": "Feature",
  "properties": {
    "addr:full":"729 Heinz Ave Ste 2 Berkeley CA 94710",
    "addr:housenumber":"729",
    "addr:postcode":"94710",
    "addr:street":"Heinz Ave Ste 2",
    "iso:country":"US",
    "sg:address":"729 Heinz Ave Ste 2",
    "sg:city":"Berkeley",
    "sg:classifiers":[
        {
            "category":"Real Estate",
            "subcategory":"Architect",
            "type":"Services"
        }
    ],
    "sg:phone":"+1 510 848 0895",
    "sg:postcode":"94710",
    "sg:province":"CA",
    "wof:name":"Goring Straja Architects",
    "wof:placetype":"venue"
},
  "geometry": {"coordinates":[-122.294262,37.853139],"type":"Point"}
}