{
  "type": "Feature",
  "properties": {
    "addr:full":"3100 26th St San Francisco CA 94110",
    "addr:housenumber":"3100",
    "addr:postcode":"94110",
    "addr:street":"26Th St",
    "iso:country":"US",
    "sg:address":"3100 26th St",
    "sg:city":"San Francisco",
    "sg:classifiers":[
        {
            "category":"Park",
            "type":"Public Place"
        }
    ],
    "sg:postcode":"94110",
    "sg:province":"CA",
    "wof:name":"Garfield Square & Athletic Field",
    "wof:placetype":"venue"
},
  "geometry": {"coordinates":[-122.411736,37.749454],"type":"Point"}
}