{
  "type": "Feature",
  "properties": {
    "iso:country":"US",
    "sg:address":"1093 S Main St",
    "sg:city":"Salinas",
    "sg:classifiers":[
        {
            "category":"Home & Garden",
            "subcategory":"Home Furnishings",
            "type":"Retail Goods"
        }
    ],
    "sg:phone":"+1 831 424 4270",
    "sg:postcode":"93901",
    "sg:province":"CA",
    "sg:tags":[
        "cutlery"
    ],
    "wof:name":"Cutco Cutlery",
    "wof:placetype":"venue"
},
  "geometry": {"coordinates":[-121.65853,36.660344],"type":"Point"}
}