{
  "type": "Feature",
  "properties": {
    "iso:country":"US",
    "sg:address":"12164 Middlebrook Sq",
    "sg:city":"San Diego",
    "sg:classifiers":[
        {
            "category":"Manufacturing",
            "subcategory":"Metals",
            "type":"Manufacturing & Wholesale Goods"
        }
    ],
    "sg:phone":"+1 858 675 0073",
    "sg:postcode":"92128",
    "sg:province":"CA",
    "sg:tags":[
        "metalwork",
        "sheet",
        "mfg"
    ],
    "wof:name":"Credo Sheet Metal",
    "wof:placetype":"venue"
},
  "geometry": {"coordinates":[-117.06997,32.979389],"type":"Point"}
}