{
  "type": "Feature",
  "properties": {
    "addr:full":"17861 Sierra Hwy Canyon Country CA 91351",
    "addr:housenumber":"17861",
    "addr:postcode":"91351",
    "addr:street":"Sierra Hwy",
    "iso:country":"US",
    "sg:address":"17861 Sierra Hwy",
    "sg:city":"Canyon Country",
    "sg:classifiers":[
        {
            "category":"Retail",
            "subcategory":"Auto Rental",
            "type":"Services"
        }
    ],
    "sg:phone":"+1 661 250 9131",
    "sg:postcode":"91351",
    "sg:province":"CA",
    "sg:tags":[
        "renting",
        "automobile"
    ],
    "wof:name":"Always Auto Rental & Sales",
    "wof:placetype":"venue"
},
  "geometry": {"coordinates":[-118.44704299999999,34.427012],"type":"Point"}
}