{
  "type": "Feature",
  "properties": {
    "addr:full":"8868 Clairemont Mesa Blvd San Diego CA 92117",
    "addr:housenumber":"8868",
    "addr:postcode":"92117",
    "addr:street":"Clairemont Mesa Blvd",
    "iso:country":"US",
    "sg:address":"8868 Clairemont Mesa Blvd",
    "sg:city":"San Diego",
    "sg:classifiers":[
        {
            "category":"Wholesale",
            "subcategory":"Electrical",
            "type":"Manufacturing & Wholesale Goods"
        }
    ],
    "sg:phone":"+1 858 751 5900",
    "sg:postcode":"92117",
    "sg:province":"CA",
    "sg:tags":[
        "control",
        "security",
        "system"
    ],
    "wof:name":"Alarm King",
    "wof:placetype":"venue"
},
  "geometry": {"coordinates":[-117.136825,32.831472],"type":"Point"}
}