{
  "type": "Feature",
  "properties": {
    "addr:full":"7617 W Sunset Blvd Los Angeles CA 90046",
    "addr:housenumber":"7617",
    "addr:postcode":"90046",
    "addr:street":"W Sunset Blvd",
    "iso:country":"US",
    "sg:address":"7617 W Sunset Blvd",
    "sg:city":"Los Angeles",
    "sg:classifiers":[
        {
            "category":"Restaurant",
            "type":"Food & Drink"
        }
    ],
    "sg:phone":"+1 323 876 2799",
    "sg:postcode":"90046",
    "sg:province":"CA",
    "sg:tags":[
        "indian"
    ],
    "wof:name":"Curry Palace Indian Restaurant",
    "wof:placetype":"venue"
},
  "geometry": {"coordinates":[-118.356003,34.0979],"type":"Point"}
}