{
  "type": "Feature",
  "properties": {
    "iso:country":"US",
    "sg:address":"266 S Harvard Boulevard",
    "sg:city":"Los Angeles",
    "sg:classifiers":[
        {
            "category":"Social Services",
            "subcategory":"Child Care",
            "type":"Services"
        }
    ],
    "sg:phone":"+1 213 385 0066",
    "sg:postcode":"90004",
    "sg:province":"CA",
    "sg:tags":[
        "day"
    ],
    "wof:name":"Skinpia",
    "wof:placetype":"venue"
},
  "geometry": {"coordinates":[-118.304101,34.069596],"type":"Point"}
}