{
  "type": "Feature",
  "properties": {
    "iso:country":"US",
    "sg:address":"2829 Childress Dr",
    "sg:city":"Anderson",
    "sg:classifiers":[
        {
            "category":"Building & Trades",
            "subcategory":"Landscaping Services",
            "type":"Services"
        }
    ],
    "sg:phone":"+1 530 224 3300",
    "sg:postcode":"96007",
    "sg:province":"CA",
    "sg:tags":[
        "tree"
    ],
    "sg:website":"www.covantaenergy.com",
    "wof:name":"Pacific Wood Fuel",
    "wof:placetype":"venue"
},
  "geometry": {"coordinates":[-122.28956700000001,40.454607],"type":"Point"}
}