{
  "type": "Feature",
  "properties": {
    "addr:full":"13652 Rose Ave Livingston CA 95334",
    "addr:housenumber":"13652",
    "addr:postcode":"95334",
    "addr:street":"Rose Ave",
    "iso:country":"US",
    "sg:address":"13652 Rose Ave",
    "sg:city":"Livingston",
    "sg:classifiers":[
        {
            "category":"Farming",
            "subcategory":"Dairy Farm",
            "type":"Manufacturing & Wholesale Goods"
        }
    ],
    "sg:phone":"+1 209 394 3504",
    "sg:postcode":"95334",
    "sg:province":"CA",
    "wof:name":"Lourenco Dairy",
    "wof:placetype":"venue"
},
  "geometry": {"coordinates":[-120.737229,37.324159],"type":"Point"}
}