{
  "type": "Feature",
  "properties": {
    "iso:country":"US",
    "sg:address":"1797 W Hacienda Ave",
    "sg:city":"Campbell",
    "sg:classifiers":[
        {
            "category":"Government",
            "subcategory":"Court House",
            "type":"Public Place"
        }
    ],
    "sg:phone":"+1 408 866 8911",
    "sg:postcode":"95008",
    "sg:province":"CA",
    "sg:tags":[
        "legal"
    ],
    "wof:name":"Daniel C Weinblatt",
    "wof:placetype":"venue"
},
  "geometry": {"coordinates":[-121.98140100000001,37.268119],"type":"Point"}
}