{
  "type": "Feature",
  "properties": {
    "addr:full":"4450 Enterprise St Fremont CA 94538",
    "addr:housenumber":"4450",
    "addr:postcode":"94538",
    "addr:street":"Enterprise St",
    "iso:country":"US",
    "sg:address":"4450 Enterprise St",
    "sg:city":"Fremont",
    "sg:classifiers":[
        {
            "category":"Building & Trades",
            "subcategory":"Plumbing",
            "type":"Services"
        }
    ],
    "sg:phone":"+1 510 445 0700",
    "sg:postcode":"94538",
    "sg:province":"CA",
    "sg:tags":[
        "conditioning",
        "air",
        "system",
        "contractor"
    ],
    "sg:website":"www.budgetwaterheater.com",
    "wof:name":"Thermoscape",
    "wof:placetype":"venue"
},
  "geometry": {"coordinates":[-121.95968999999999,37.503148],"type":"Point"}
}