{
  "type": "Feature",
  "properties": {
    "iso:country":"US",
    "sg:address":"285 California St",
    "sg:city":"Woodland",
    "sg:classifiers":[
        {
            "category":"Home & Garden",
            "subcategory":"Furniture",
            "type":"Retail Goods"
        }
    ],
    "sg:phone":"+1 530 666 3395",
    "sg:postcode":"95695",
    "sg:province":"CA",
    "sg:website":"www.mcmahansfurniture.com",
    "wof:name":"Mc Mahan's Furniture & Appls",
    "wof:placetype":"venue"
},
  "geometry": {"coordinates":[-121.78851899999999,38.679183],"type":"Point"}
}