{
  "type": "Feature",
  "properties": {
    "iso:country":"US",
    "sg:address":"8400 State Street",
    "sg:city":"South Gate",
    "sg:classifiers":[
        {
            "category":"Health Services",
            "subcategory":"Dentist",
            "type":"Services"
        }
    ],
    "sg:phone":"+1 323 567 1485",
    "sg:postcode":"90280",
    "sg:province":"CA",
    "wof:name":"Rodriguez Cristina DDS",
    "wof:placetype":"venue"
},
  "geometry": {"coordinates":[-118.21154,33.960294],"type":"Point"}
}