{
  "type": "Feature",
  "properties": {
    "addr:full":"889 Cape Diamond Dr San Jose CA 95133",
    "addr:housenumber":"889",
    "addr:postcode":"95133",
    "addr:street":"Cape Diamond Dr",
    "iso:country":"US",
    "sg:address":"889 Cape Diamond Dr",
    "sg:city":"San Jose",
    "sg:classifiers":[
        {
            "category":"Professional",
            "subcategory":"Management & Consulting",
            "type":"Services"
        }
    ],
    "sg:phone":"+1 408 363 4790",
    "sg:postcode":"95133",
    "sg:province":"CA",
    "sg:tags":[
        "marketing",
        "consultant"
    ],
    "wof:name":"Smart Solution",
    "wof:placetype":"venue"
},
  "geometry": {"coordinates":[-121.867932,37.371492],"type":"Point"}
}