{
  "type": "Feature",
  "properties": {
    "iso:country":"US",
    "sg:address":"3540 Nantucket Dr",
    "sg:city":"Fairfield",
    "sg:classifiers":[
        {
            "category":"Arts & Performance",
            "subcategory":"Theater",
            "type":"Entertainment"
        }
    ],
    "sg:phone":"+1 707 429 3551",
    "sg:postcode":"94534",
    "sg:province":"CA",
    "sg:tags":[
        "opera",
        "company"
    ],
    "sg:website":"www.northbayopera.org",
    "wof:name":"North Bay Opera",
    "wof:placetype":"venue"
},
  "geometry": {"coordinates":[-122.079617,38.264002],"type":"Point"}
}