{
  "type": "Feature",
  "properties": {
    "iso:country":"US",
    "sg:address":"2535 W 237th St",
    "sg:city":"Torrance",
    "sg:classifiers":[
        {
            "category":"Shopping",
            "subcategory":"Clothing, Apparel, & Fashions",
            "type":"Retail Goods"
        },
        {
            "category":"Wholesale",
            "subcategory":"Fruits & Vegetables",
            "type":"Manufacturing & Wholesale Goods"
        }
    ],
    "sg:phone":"+1 310 257 8636",
    "sg:postcode":"90505",
    "sg:province":"CA",
    "sg:tags":[
        "women's",
        "clothing",
        "veggie",
        "accessory"
    ],
    "wof:name":"All New Fashions Inc",
    "wof:placetype":"venue"
},
  "geometry": {"coordinates":[-118.330401,33.811011],"type":"Point"}
}