{
  "type": "Feature",
  "properties": {
    "addr:full":"900 E Washington Blvd Crescent City CA 95531",
    "addr:housenumber":"900",
    "addr:postcode":"95531",
    "addr:street":"E Washington Blvd Crescent",
    "iso:country":"US",
    "sg:address":"900 E Washington Blvd",
    "sg:city":"Crescent City",
    "sg:classifiers":[
        {
            "category":"Shopping",
            "subcategory":"Department Store",
            "type":"Retail Goods"
        }
    ],
    "sg:phone":"+1 707 464 1198",
    "sg:postcode":"95531",
    "sg:province":"CA",
    "sg:tags":[
        "discount"
    ],
    "sg:website":"www.walmart.com",
    "wof:name":"Wal-Mart",
    "wof:placetype":"venue"
},
  "geometry": {"coordinates":[-124.19565900000001,41.772767],"type":"Point"}
}