{
  "type": "Feature",
  "properties": {
    "iso:country":"US",
    "sg:address":"1111 Rancho Conejo Blvd",
    "sg:city":"Newbury Park",
    "sg:classifiers":[
        {
            "category":"Recreation",
            "type":"Entertainment"
        }
    ],
    "sg:phone":"+1 805 499 9033",
    "sg:postcode":"91320",
    "sg:province":"CA",
    "sg:tags":[
        "martial",
        "arts",
        "instruction"
    ],
    "wof:name":"Warrior Quest Society-Ninjutsu",
    "wof:placetype":"venue"
},
  "geometry": {"coordinates":[-118.92327,34.192157],"type":"Point"}
}