{
  "type": "Feature",
  "properties": {
    "addr:full":"114 Winfield St San Francisco CA 94110",
    "addr:housenumber":"114",
    "addr:postcode":"94110",
    "addr:street":"Winfield St",
    "iso:country":"US",
    "sg:address":"114 Winfield St",
    "sg:city":"San Francisco",
    "sg:classifiers":[
        {
            "category":"Professional",
            "type":"Services"
        }
    ],
    "sg:phone":"+1 415 268 4322",
    "sg:postcode":"94110",
    "sg:province":"CA",
    "wof:name":"Rustic Tooling",
    "wof:placetype":"venue"
},
  "geometry": {"coordinates":[-122.418828,37.74229],"type":"Point"}
}