{
  "type": "Feature",
  "properties": {
    "addr:full":"5646 Schaefer Ave Chino CA 91710",
    "addr:housenumber":"5646",
    "addr:postcode":"91710",
    "addr:street":"Schaefer Ave",
    "iso:country":"US",
    "sg:address":"5646 Schaefer Ave",
    "sg:city":"Chino",
    "sg:classifiers":[
        {
            "category":"Wholesale",
            "subcategory":"Stationery",
            "type":"Manufacturing & Wholesale Goods"
        }
    ],
    "sg:phone":"+1 909 464 2648",
    "sg:postcode":"91710",
    "sg:province":"CA",
    "sg:tags":[
        "product",
        "paper"
    ],
    "sg:website":"www.basspaper.com",
    "wof:name":"Bass Paper Co",
    "wof:placetype":"venue"
},
  "geometry": {"coordinates":[-117.683273,34.00466],"type":"Point"}
}