{
  "type": "Feature",
  "properties": {
    "iso:country":"US",
    "sg:address":"8027 West Ln",
    "sg:city":"Stockton",
    "sg:classifiers":[
        {
            "category":"Shopping",
            "subcategory":"Used Merchandise",
            "type":"Retail Goods"
        }
    ],
    "sg:phone":"+1 209 474 8530",
    "sg:postcode":"95210",
    "sg:province":"CA",
    "sg:tags":[
        "shop",
        "thrift"
    ],
    "wof:name":"Big Valley Thrift",
    "wof:placetype":"venue"
},
  "geometry": {"coordinates":[-121.294984,38.021369],"type":"Point"}
}