{
  "type": "Feature",
  "properties": {
    "addr:full":"108 Arlington Ave Kensington CA 94707",
    "addr:housenumber":"108",
    "addr:postcode":"94707",
    "addr:street":"Arlington Ave",
    "iso:country":"US",
    "sg:address":"108 Arlington Ave",
    "sg:city":"Kensington",
    "sg:classifiers":[
        {
            "category":"Building & Trades",
            "subcategory":"Construction",
            "type":"Services"
        }
    ],
    "sg:phone":"+1 510 524 0301",
    "sg:postcode":"94707",
    "sg:province":"CA",
    "sg:tags":[
        "painter"
    ],
    "wof:name":"Bridge Painting",
    "wof:placetype":"venue"
},
  "geometry": {"coordinates":[-122.280709,37.90997],"type":"Point"}
}