{
  "type": "Feature",
  "properties": {
    "iso:country":"US",
    "sg:address":"1410 Wible Rd",
    "sg:city":"Bakersfield",
    "sg:classifiers":[
        {
            "category":"Food & Beverages",
            "subcategory":"Groceries & Convenience Stores",
            "type":"Retail Goods"
        }
    ],
    "sg:phone":"+1 661 832 4111",
    "sg:postcode":"93304",
    "sg:province":"CA",
    "sg:tags":[
        "grocer"
    ],
    "wof:name":"A 1 Indian Grocery",
    "wof:placetype":"venue"
},
  "geometry": {"coordinates":[-119.038882,35.340632],"type":"Point"}
}