{
  "type": "Feature",
  "properties": {
    "addr:full":"8895 Towne Centre Dr Ste 105 San Diego CA 92122",
    "addr:housenumber":"8895",
    "addr:postcode":"92122",
    "addr:street":"Towne Centre Dr Ste 105",
    "iso:country":"US",
    "sg:address":"8895 Towne Centre Dr Ste 105",
    "sg:city":"San Diego",
    "sg:classifiers":[
        {
            "category":"Freight",
            "type":"Transportation"
        }
    ],
    "sg:phone":"+1 858 546 1700",
    "sg:postcode":"92122",
    "sg:province":"CA",
    "sg:tags":[
        "shipping"
    ],
    "sg:website":"www.postalannex.com",
    "wof:name":"PostalAnnex+",
    "wof:placetype":"venue"
},
  "geometry": {"coordinates":[-117.206203,32.867403],"type":"Point"}
}