{
  "type": "Feature",
  "properties": {
    "addr:full":"5 Skyline Blvd Oroville CA 95966",
    "addr:housenumber":"5",
    "addr:postcode":"95966",
    "addr:street":"Skyline Blvd",
    "iso:country":"US",
    "sg:address":"5 Skyline Blvd",
    "sg:city":"Oroville",
    "sg:classifiers":[
        {
            "category":"Real Estate",
            "subcategory":"Real Estate Agent",
            "type":"Services"
        }
    ],
    "sg:phone":"+1 530 589 1800",
    "sg:postcode":"95966",
    "sg:province":"CA",
    "wof:name":"Mc Canless Counseling",
    "wof:placetype":"venue"
},
  "geometry": {"coordinates":[-121.48894199999999,39.510031],"type":"Point"}
}