{
  "type": "Feature",
  "properties": {
    "iso:country":"US",
    "sg:address":"113 6th St",
    "sg:city":"Seal Beach",
    "sg:classifiers":[
        {
            "category":"Banks & Credit Unions",
            "subcategory":"Bank",
            "type":"Services"
        }
    ],
    "sg:phone":"+1 562 594 6463",
    "sg:postcode":"90740",
    "sg:province":"CA",
    "sg:tags":[
        "loan"
    ],
    "wof:name":"Appraisal Loan Svc",
    "wof:placetype":"venue"
},
  "geometry": {"coordinates":[-118.108457,33.741422],"type":"Point"}
}