{
  "type": "Feature",
  "properties": {
    "iso:country":"US",
    "sg:address":"2007 Larkspur Landing Cir",
    "sg:city":"Larkspur",
    "sg:classifiers":[
        {
            "category":"Insurance",
            "subcategory":"Hazard Insurance",
            "type":"Services"
        },
        {
            "category":"Travel",
            "subcategory":"Travel Agent",
            "type":"Entertainment"
        }
    ],
    "sg:phone":"+1 415 925 1200",
    "sg:postcode":"94939",
    "sg:province":"CA",
    "sg:tags":[
        "agency"
    ],
    "wof:name":"Aaa Insurance Svc",
    "wof:placetype":"venue"
},
  "geometry": {"coordinates":[-122.50887299999999,37.948234],"type":"Point"}
}