{
  "type": "Feature",
  "properties": {
    "addr:full":"7440 District Blvd Bakersfield CA 93313",
    "addr:postcode":"7440;93313",
    "addr:street":"District Blvd",
    "iso:country":"US",
    "sg:address":"7440 District Blvd",
    "sg:city":"Bakersfield",
    "sg:classifiers":[
        {
            "category":"Home & Garden",
            "subcategory":"Furniture",
            "type":"Retail Goods"
        }
    ],
    "sg:phone":"+1 661 834 1414",
    "sg:postcode":"93313",
    "sg:province":"CA",
    "sg:tags":[
        "cabinet"
    ],
    "wof:name":"Andy's Cabinets & Granite",
    "wof:placetype":"venue"
},
  "geometry": {"coordinates":[-119.08205599999999,35.313137],"type":"Point"}
}