{
  "type": "Feature",
  "properties": {
    "iso:country":"US",
    "sg:address":"3725 N Fruit Ave",
    "sg:city":"Fresno",
    "sg:classifiers":[
        {
            "category":"Real Estate",
            "subcategory":"Real Estate Agent",
            "type":"Services"
        }
    ],
    "sg:phone":"+1 559 304 8827",
    "sg:postcode":"93705",
    "sg:province":"CA",
    "wof:name":"Affordable Real Estate",
    "wof:placetype":"venue"
},
  "geometry": {"coordinates":[-119.817587,36.786546],"type":"Point"}
}