{
  "type": "Feature",
  "properties": {
    "addr:full":"200 N. San Mateo Drive San Mateo CA 94401",
    "addr:housenumber":"200",
    "addr:postcode":"94401",
    "addr:street":"N. San Mateo Drive",
    "iso:country":"US",
    "sg:address":"200 N. San Mateo Drive",
    "sg:city":"San Mateo",
    "sg:classifiers":[
        {
            "category":"Personal",
            "subcategory":"Massage",
            "type":"Services"
        }
    ],
    "sg:phone":"+1 650 307 3251",
    "sg:postcode":"94401",
    "sg:province":"CA",
    "wof:name":"Alanna Rose Foster CMT",
    "wof:placetype":"venue"
},
  "geometry": {"coordinates":[-122.32963700000001,37.569919],"type":"Point"}
}