{
  "type": "Feature",
  "properties": {
    "addr:full":"3185 Bell Rd Auburn CA 95603",
    "addr:housenumber":"3185",
    "addr:postcode":"ca 95603",
    "addr:street":"Bell Rd",
    "iso:country":"US",
    "sg:address":"3185 Bell Rd",
    "sg:city":"Auburn",
    "sg:classifiers":[
        {
            "category":"Real Estate",
            "subcategory":"Real Estate Operator",
            "type":"Services"
        },
        {
            "category":"Recreation",
            "type":"Entertainment"
        }
    ],
    "sg:phone":"+1 530 885 3974",
    "sg:postcode":"95603",
    "sg:province":"CA",
    "sg:tags":[
        "hall",
        "auditorium"
    ],
    "wof:name":"Mount Vernon Grange Hall",
    "wof:placetype":"venue"
},
  "geometry": {"coordinates":[-121.10567899999999,38.941859],"type":"Point"}
}