{
  "type": "Feature",
  "properties": {
    "addr:full":"24921 Largo Dr Laguna Hills CA 92653",
    "addr:housenumber":"24921",
    "addr:postcode":"92653",
    "addr:street":"Largo Dr",
    "iso:country":"US",
    "sg:address":"24921 Largo Dr",
    "sg:city":"Laguna Hills",
    "sg:classifiers":[
        {
            "category":"Professional",
            "subcategory":"Business Services",
            "type":"Services"
        }
    ],
    "sg:phone":"+1 949 887 0516",
    "sg:postcode":"92653",
    "sg:province":"CA",
    "wof:name":"Prodocs",
    "wof:placetype":"venue"
},
  "geometry": {"coordinates":[-117.69305900000001,33.592072],"type":"Point"}
}