{
  "type": "Feature",
  "properties": {
    "iso:country":"US",
    "sg:address":"4926 W Turner Rd",
    "sg:city":"Lodi",
    "sg:classifiers":[
        {
            "category":"Food & Beverages",
            "subcategory":"Farmers Market",
            "type":"Retail Goods"
        }
    ],
    "sg:phone":"+1 209 333 3711",
    "sg:postcode":"95242",
    "sg:province":"CA",
    "sg:tags":[
        "vegetable",
        "fruit",
        "shipper",
        "grower"
    ],
    "wof:name":"A F Mills Vineyards",
    "wof:placetype":"venue"
},
  "geometry": {"coordinates":[-121.37616199999999,38.145822],"type":"Point"}
}