{
  "type": "Feature",
  "properties": {
    "addr:full":"119 Franklin St Redwood City CA 94063",
    "addr:housenumber":"119",
    "addr:postcode":"94063",
    "addr:street":"Franklin St",
    "iso:country":"US",
    "sg:address":"119 Franklin St",
    "sg:city":"Redwood City",
    "sg:classifiers":[
        {
            "category":"Professional",
            "type":"Services"
        }
    ],
    "sg:phone":"+1 650 361 8283",
    "sg:postcode":"94063",
    "sg:province":"CA",
    "wof:name":"Guadalupe Ruiz",
    "wof:placetype":"venue"
},
  "geometry": {"coordinates":[-122.22825,37.482493],"type":"Point"}
}