{
  "type": "Feature",
  "properties": {
    "addr:full":"1070 Commerce St San Marcos CA 92078",
    "addr:housenumber":"1070",
    "addr:postcode":"92078",
    "addr:street":"Commerce St",
    "iso:country":"US",
    "sg:address":"1070 Commerce St",
    "sg:city":"San Marcos",
    "sg:classifiers":[
        {
            "category":"Building & Trades",
            "subcategory":"Electrical",
            "type":"Services"
        }
    ],
    "sg:phone":"+1 760 744 6880",
    "sg:postcode":"92078",
    "sg:province":"CA",
    "sg:tags":[
        "electric",
        "contractor"
    ],
    "wof:name":"Robeck Electrical Maintenance",
    "wof:placetype":"venue"
},
  "geometry": {"coordinates":[-117.18715899999999,33.137667],"type":"Point"}
}