{
  "type": "Feature",
  "properties": {
    "iso:country":"US",
    "sg:address":"327 Stedman Pl",
    "sg:city":"Monrovia",
    "sg:classifiers":[
        {
            "category":"Communications",
            "subcategory":"Film & Video Production",
            "type":"Services"
        }
    ],
    "sg:phone":"+1 818 845 0605",
    "sg:postcode":"91016",
    "sg:province":"CA",
    "sg:tags":[
        "services-commercial"
    ],
    "wof:name":"Moving Images",
    "wof:placetype":"venue"
},
  "geometry": {"coordinates":[-118.002257,34.157861],"type":"Point"}
}