{
  "type": "Feature",
  "properties": {
    "addr:full":"42320 Baracoa Dr Bermuda Dunes CA 92203",
    "addr:postcode":"42320;92203",
    "addr:street":"Baracoa Dr",
    "iso:country":"US",
    "sg:address":"42320 Baracoa Dr",
    "sg:city":"Bermuda Dunes",
    "sg:classifiers":[
        {
            "category":"Professional",
            "subcategory":"Business Services",
            "type":"Services"
        }
    ],
    "sg:phone":"+1 760 485 6563",
    "sg:postcode":"92203",
    "sg:province":"CA",
    "sg:tags":[
        "broker"
    ],
    "wof:name":"Prudential Business Sales",
    "wof:placetype":"venue"
},
  "geometry": {"coordinates":[-116.28553700000001,33.741346],"type":"Point"}
}