{
  "type": "Feature",
  "properties": {
    "iso:country":"US",
    "sg:address":"3650 W Martin Luther King Jr Blvd",
    "sg:city":"Los Angeles",
    "sg:classifiers":[
        {
            "category":"Shopping",
            "subcategory":"Gifts & Souvenirs",
            "type":"Retail Goods"
        }
    ],
    "sg:phone":"+1 323 293 8253",
    "sg:postcode":"90008",
    "sg:province":"CA",
    "wof:name":"Gift 4 Less",
    "wof:placetype":"venue"
},
  "geometry": {"coordinates":[-118.336728,34.011425],"type":"Point"}
}