{
  "type": "Feature",
  "properties": {
    "addr:full":"220 E Compton Blvd Compton CA 90220",
    "addr:housenumber":"220",
    "addr:postcode":"90220",
    "addr:street":"E Compton Blvd",
    "iso:country":"US",
    "sg:address":"220 E Compton Blvd",
    "sg:city":"Compton",
    "sg:classifiers":[
        {
            "category":"Shopping",
            "subcategory":"Pharmacy",
            "type":"Retail Goods"
        }
    ],
    "sg:phone":"+1 310 604 1747",
    "sg:postcode":"90220",
    "sg:province":"CA",
    "sg:tags":[
        "drugstore"
    ],
    "sg:website":"www.cvs.com",
    "wof:name":"CVS Pharmacy",
    "wof:placetype":"venue"
},
  "geometry": {"coordinates":[-118.221586,33.895488],"type":"Point"}
}