{
  "type": "Feature",
  "properties": {
    "iso:country":"US",
    "sg:address":"2074 National Ave",
    "sg:city":"Hayward",
    "sg:classifiers":[
        {
            "category":"Retail",
            "subcategory":"Auto Rental",
            "type":"Services"
        }
    ],
    "sg:phone":"+1 800 884 5089",
    "sg:postcode":"94545",
    "sg:province":"CA",
    "sg:tags":[
        "renting",
        "leasing",
        "trailer"
    ],
    "wof:name":"Carrier Transicold of Northern California",
    "wof:placetype":"venue"
},
  "geometry": {"coordinates":[-122.128564,37.648889],"type":"Point"}
}