{
  "type": "Feature",
  "properties": {
    "iso:country":"US",
    "sg:address":"449 23rd St",
    "sg:city":"Oakland",
    "sg:classifiers":[
        {
            "category":"Retail",
            "subcategory":"Auto Repair",
            "type":"Services"
        }
    ],
    "sg:phone":"+1 510 444 4269",
    "sg:postcode":"94612",
    "sg:province":"CA",
    "sg:tags":[
        "repairing",
        "automobile"
    ],
    "wof:name":"On Track Bmw",
    "wof:placetype":"venue"
},
  "geometry": {"coordinates":[-122.266386,37.81216],"type":"Point"}
}