{
  "type": "Feature",
  "properties": {
    "addr:full":"1530 Whipple Rd Union City CA 94587",
    "addr:housenumber":"1530",
    "addr:postcode":"94587",
    "addr:street":"Whipple Rd",
    "iso:country":"US",
    "sg:address":"1530 Whipple Rd",
    "sg:city":"Union City",
    "sg:classifiers":[
        {
            "category":"Freight",
            "type":"Transportation"
        }
    ],
    "sg:phone":"+1 510 780 9309",
    "sg:postcode":"94587",
    "sg:province":"CA",
    "sg:tags":[
        "mover"
    ],
    "sg:website":"www.moveusa.net",
    "wof:name":"Move USA",
    "wof:placetype":"venue"
},
  "geometry": {"coordinates":[-122.044793,37.605892],"type":"Point"}
}