{
  "type": "Feature",
  "properties": {
    "iso:country":"US",
    "sg:address":"452 N Los Robles Ave",
    "sg:city":"Pasadena",
    "sg:classifiers":[
        {
            "category":"Shopping",
            "subcategory":"Pharmacy",
            "type":"Retail Goods"
        }
    ],
    "sg:phone":"+1 626 449 1471",
    "sg:postcode":"91101",
    "sg:province":"CA",
    "wof:name":"Family Pharmacy",
    "wof:placetype":"venue"
},
  "geometry": {"coordinates":[-118.14147199999999,34.152373],"type":"Point"}
}