{
  "type": "Feature",
  "properties": {
    "addr:full":"2491 Carmichael Dr Chico CA 95928",
    "addr:housenumber":"2491",
    "addr:postcode":"95928",
    "addr:street":"Carmichael Dr",
    "iso:country":"US",
    "sg:address":"2491 Carmichael Dr",
    "sg:city":"Chico",
    "sg:classifiers":[
        {
            "category":"Social Services",
            "subcategory":"Adult Care",
            "type":"Services"
        }
    ],
    "sg:phone":"+1 530 898 6716",
    "sg:postcode":"95928",
    "sg:province":"CA",
    "sg:tags":[
        "organization",
        "senior",
        "citizen"
    ],
    "wof:name":"Health Insurance Counseling",
    "wof:placetype":"venue"
},
  "geometry": {"coordinates":[-121.80524,39.715016],"type":"Point"}
}