{
  "type": "Feature",
  "properties": {
    "addr:full":"555 Fremont St Colusa CA 95932",
    "addr:housenumber":"555",
    "addr:postcode":"95932",
    "addr:street":"Fremont St",
    "iso:country":"US",
    "sg:address":"555 Fremont St",
    "sg:city":"Colusa",
    "sg:classifiers":[
        {
            "category":"Social Services",
            "type":"Services"
        }
    ],
    "sg:phone":"+1 530 458 8817",
    "sg:postcode":"95932",
    "sg:province":"CA",
    "sg:tags":[
        "pregnancy",
        "counseling",
        "information"
    ],
    "wof:name":"Perinatal Care Program",
    "wof:placetype":"venue"
},
  "geometry": {"coordinates":[-122.011202,39.207836],"type":"Point"}
}