{
  "type": "Feature",
  "properties": {
    "iso:country":"US",
    "sg:address":"2003 Mentone Blvd",
    "sg:city":"Mentone",
    "sg:classifiers":[
        {
            "category":"Building & Trades",
            "subcategory":"Equipment Rental",
            "type":"Services"
        }
    ],
    "sg:phone":"+1 909 794 1465",
    "sg:postcode":"92359",
    "sg:province":"CA",
    "sg:tags":[
        "yard"
    ],
    "wof:name":"Mentone Rentals",
    "wof:placetype":"venue"
},
  "geometry": {"coordinates":[-117.121712,34.069941],"type":"Point"}
}