{
  "type": "Feature",
  "properties": {
    "iso:country":"US",
    "sg:address":"2661 Gravenstein Hwy S",
    "sg:city":"Sebastopol",
    "sg:classifiers":[
        {
            "category":"Manufacturing",
            "subcategory":"Apparel",
            "type":"Manufacturing & Wholesale Goods"
        }
    ],
    "sg:phone":"+1 707 823 2033",
    "sg:postcode":"95472",
    "sg:province":"CA",
    "sg:tags":[
        "hat"
    ],
    "wof:name":"Pan Tropics",
    "wof:placetype":"venue"
},
  "geometry": {"coordinates":[-122.791466,38.374534],"type":"Point"}
}