{
  "type": "Feature",
  "properties": {
    "addr:full":"512 Fremont St Monterey CA 93940",
    "addr:housenumber":"512",
    "addr:postcode":"93940",
    "addr:street":"Fremont St",
    "iso:country":"US",
    "sg:address":"512 Fremont St",
    "sg:city":"Monterey",
    "sg:classifiers":[
        {
            "category":"Wholesale",
            "subcategory":"Electrical",
            "type":"Manufacturing & Wholesale Goods"
        }
    ],
    "sg:phone":"+1 831 643 2337",
    "sg:postcode":"93940",
    "sg:province":"CA",
    "sg:tags":[
        "radio"
    ],
    "wof:name":"Cal Com Paging Svc",
    "wof:placetype":"venue"
},
  "geometry": {"coordinates":[-121.89015000000001,36.595068],"type":"Point"}
}