{
  "type": "Feature",
  "properties": {
    "iso:country":"US",
    "sg:address":"1736 Westwood Blvd",
    "sg:city":"Los Angeles",
    "sg:classifiers":[
        {
            "category":"Professional",
            "type":"Services"
        }
    ],
    "sg:phone":"+1 310 441 5556",
    "sg:postcode":"90024",
    "sg:province":"CA",
    "wof:name":"Juliet Rohde-Brown",
    "wof:placetype":"venue"
},
  "geometry": {"coordinates":[-118.437484,34.050623],"type":"Point"}
}