{
  "type": "Feature",
  "properties": {
    "iso:country":"US",
    "sg:address":"2001 Drake Dr",
    "sg:city":"Oakland",
    "sg:classifiers":[
        {
            "category":"Manufacturing",
            "subcategory":"Paper Products",
            "type":"Manufacturing & Wholesale Goods"
        }
    ],
    "sg:phone":"+1 510 339 6767",
    "sg:postcode":"94611",
    "sg:province":"CA",
    "sg:tags":[
        "products-wholesale",
        "manufacturer"
    ],
    "wof:name":"Budowski",
    "wof:placetype":"venue"
},
  "geometry": {"coordinates":[-122.20491,37.828442],"type":"Point"}
}