{
  "type": "Feature",
  "properties": {
    "iso:country":"US",
    "sg:address":"140 W Valley Blvd",
    "sg:city":"San Gabriel",
    "sg:classifiers":[
        {
            "category":"Shopping",
            "subcategory":"Clothing, Apparel, & Fashions",
            "type":"Retail Goods"
        }
    ],
    "sg:phone":"+1 626 280 4866",
    "sg:postcode":"91776",
    "sg:province":"CA",
    "sg:tags":[
        "clothing",
        "women's"
    ],
    "wof:name":"House of Italy",
    "wof:placetype":"venue"
},
  "geometry": {"coordinates":[-118.099998,34.0797],"type":"Point"}
}