{
  "type": "Feature",
  "properties": {
    "addr:full":"5110 Hillsdale Cir El Dorado Hills CA 95762",
    "addr:housenumber":"5110",
    "addr:postcode":"95762",
    "addr:street":"Hillsdale Cir",
    "iso:country":"US",
    "sg:address":"5110 Hillsdale Cir",
    "sg:city":"El Dorado Hills",
    "sg:classifiers":[
        {
            "category":"Freight",
            "type":"Transportation"
        }
    ],
    "sg:phone":"+1 916 939 9999",
    "sg:postcode":"95762",
    "sg:province":"CA",
    "sg:tags":[
        "commercial",
        "storage"
    ],
    "wof:name":"El Dorado Self Storage",
    "wof:placetype":"venue"
},
  "geometry": {"coordinates":[-121.058683,38.620732],"type":"Point"}
}