{
  "type": "Feature",
  "properties": {
    "addr:full":"3690 S El Camino Real San Mateo CA 94403",
    "addr:housenumber":"3690",
    "addr:postcode":"94403",
    "addr:street":"S El Camino Real",
    "iso:country":"US",
    "sg:address":"3690 S El Camino Real",
    "sg:city":"San Mateo",
    "sg:classifiers":[
        {
            "category":"Shopping",
            "subcategory":"Shoes",
            "type":"Retail Goods"
        }
    ],
    "sg:phone":"+1 650 341 8398",
    "sg:postcode":"94403",
    "sg:province":"CA",
    "sg:tags":[
        "store"
    ],
    "wof:name":"Payless Shoe Source",
    "wof:placetype":"venue"
},
  "geometry": {"coordinates":[-122.29503800000001,37.534572],"type":"Point"}
}