{
  "type": "Feature",
  "properties": {
    "addr:full":"54 Sand St Laguna Niguel CA 92677",
    "addr:housenumber":"54",
    "addr:postcode":"92677",
    "addr:street":"Sand St",
    "iso:country":"US",
    "sg:address":"54 Sand St",
    "sg:city":"Laguna Niguel",
    "sg:classifiers":[
        {
            "category":"Building & Trades",
            "subcategory":"Construction",
            "type":"Services"
        }
    ],
    "sg:phone":"+1 949 786 0976",
    "sg:postcode":"92677",
    "sg:province":"CA",
    "sg:tags":[
        "pipe",
        "line",
        "contractor"
    ],
    "wof:name":"Robert J Grodach",
    "wof:placetype":"venue"
},
  "geometry": {"coordinates":[-117.68633,33.517631],"type":"Point"}
}