{
  "type": "Feature",
  "properties": {
    "iso:country":"US",
    "sg:address":"42103 50th St W",
    "sg:city":"Lancaster",
    "sg:classifiers":[
        {
            "category":"Professional",
            "subcategory":"Business Services",
            "type":"Services"
        },
        {
            "category":"Government",
            "subcategory":"Post Office",
            "type":"Public Place"
        }
    ],
    "sg:phone":"+1 800 275 8777",
    "sg:postcode":"93536",
    "sg:province":"CA",
    "sg:tags":[
        "mail",
        "shipping"
    ],
    "sg:website":"http://www.usps.com",
    "wof:name":"USPS - United States Post Office - Quartz Hill",
    "wof:placetype":"venue"
},
  "geometry": {"coordinates":[-118.218462,34.647452],"type":"Point"}
}