{
  "type": "Feature",
  "properties": {
    "addr:full":"210 E Katella Ave Orange CA 92867",
    "addr:housenumber":"210",
    "addr:postcode":"92867",
    "addr:street":"E Katella Ave",
    "iso:country":"US",
    "sg:address":"210 E Katella Ave",
    "sg:city":"Orange",
    "sg:classifiers":[
        {
            "category":"Food & Beverages",
            "subcategory":"Specialty",
            "type":"Retail Goods"
        }
    ],
    "sg:phone":"+1 714 535 1606",
    "sg:postcode":"92867",
    "sg:province":"CA",
    "sg:tags":[
        "water",
        "bulk",
        "company"
    ],
    "wof:name":"Cantarito El Aqua Pura",
    "wof:placetype":"venue"
},
  "geometry": {"coordinates":[-117.849879,33.809033],"type":"Point"}
}