{
  "type": "Feature",
  "properties": {
    "addr:full":"218 Broadway Ave Millbrae CA 94030",
    "addr:housenumber":"218",
    "addr:postcode":"94030",
    "addr:street":"Broadway Ave",
    "iso:country":"US",
    "sg:address":"218 Broadway Ave",
    "sg:city":"Millbrae",
    "sg:classifiers":[
        {
            "category":"Personal",
            "subcategory":"Beauty Salon",
            "type":"Services"
        },
        {
            "category":"Personal",
            "subcategory":"Hair Removal",
            "type":"Services"
        },
        {
            "category":"Personal",
            "subcategory":"Skin Care",
            "type":"Services"
        }
    ],
    "sg:phone":"+1 650 692 9997",
    "sg:postcode":"94030",
    "sg:province":"CA",
    "sg:tags":[
        "makeup",
        "artist"
    ],
    "sg:website":"www.happybeautycenter.com",
    "wof:name":"Happy Beauty Center - POLA Cosmetics",
    "wof:placetype":"venue"
},
  "geometry": {"coordinates":[-122.39068,37.600337],"type":"Point"}
}