{
  "type": "Feature",
  "properties": {
    "addr:full":"13230 Saticoy St North Hollywood CA 91605",
    "addr:housenumber":"13230",
    "addr:postcode":"91605",
    "addr:street":"Saticoy St",
    "iso:country":"US",
    "sg:address":"13230 Saticoy St",
    "sg:city":"North Hollywood",
    "sg:classifiers":[
        {
            "category":"Manufacturing",
            "subcategory":"Glass & Minerals",
            "type":"Manufacturing & Wholesale Goods"
        }
    ],
    "sg:phone":"+1 818 982 3600",
    "sg:postcode":"91605",
    "sg:province":"CA",
    "sg:tags":[
        "fabricator",
        "fiber"
    ],
    "sg:website":"www.armorcastprod.com",
    "wof:name":"Armorcast Products Co",
    "wof:placetype":"venue"
},
  "geometry": {"coordinates":[-118.423546,34.20842],"type":"Point"}
}