{
  "type": "Feature",
  "properties": {
    "addr:full":"1942 Center Rd Novato CA 94947",
    "addr:housenumber":"1942",
    "addr:postcode":"94947",
    "addr:street":"Center Rd",
    "iso:country":"US",
    "sg:address":"1942 Center Rd",
    "sg:city":"Novato",
    "sg:classifiers":[
        {
            "category":"Health Services",
            "subcategory":"Nursing And Care Facility",
            "type":"Services"
        }
    ],
    "sg:phone":"+1 415 897 0250",
    "sg:postcode":"94947",
    "sg:province":"CA",
    "sg:tags":[
        "home",
        "convalescent"
    ],
    "wof:name":"St James Residence",
    "wof:placetype":"venue"
},
  "geometry": {"coordinates":[-122.589467,38.106764],"type":"Point"}
}