{
  "type": "Feature",
  "properties": {
    "addr:full":"1330 W 12th Street Los Angeles CA 90015",
    "addr:housenumber":"1330",
    "addr:postcode":"90015",
    "addr:street":"W 12Th Street",
    "iso:country":"US",
    "sg:address":"1330 W 12th Street",
    "sg:city":"Los Angeles",
    "sg:classifiers":[
        {
            "category":"Building & Trades",
            "subcategory":"Construction",
            "type":"Services"
        }
    ],
    "sg:phone":"+1 213 745 8433",
    "sg:postcode":"90015",
    "sg:province":"CA",
    "sg:tags":[
        "interior",
        "design"
    ],
    "wof:name":"Inex Design Studio",
    "wof:placetype":"venue"
},
  "geometry": {"coordinates":[-118.27283799999999,34.04489],"type":"Point"}
}