{
  "type": "Feature",
  "properties": {
    "iso:country":"US",
    "sg:address":"41-995 Boardwalk Suite K",
    "sg:city":"Palm Desert",
    "sg:classifiers":[
        {
            "category":"Professional",
            "subcategory":"Research",
            "type":"Services"
        }
    ],
    "sg:postcode":"92211",
    "sg:province":"CA",
    "sg:tags":[
        "cleantech",
        "electricity",
        "power",
        "power-generation",
        "fuel-cell",
        "combined-heat-and-power",
        "chp",
        "micro-chp",
        "self-generated-power",
        "hydrogen",
        "directed-biogas",
        "sgip",
        "alternative-energy",
        "renewable-energy"
    ],
    "sg:website":"http://www.clearedgepower.com",
    "wof:name":"ClearEdge Power",
    "wof:placetype":"venue"
},
  "geometry": {"coordinates":[-116.35494199999999,33.746277],"type":"Point"}
}