{
  "type": "Feature",
  "properties": {
    "iso:country":"US",
    "sg:address":"1333 Gough Street",
    "sg:city":"San Francisco",
    "sg:classifiers":[
        {
            "category":"Autos & Motor Vehicles",
            "subcategory":"Automobile Sales",
            "type":"Retail Goods"
        }
    ],
    "sg:phone":"+1 415 928 1115",
    "sg:postcode":"94109",
    "sg:province":"CA",
    "sg:tags":[
        "limo"
    ],
    "wof:name":"T & Y Pacific Limousine Service",
    "wof:placetype":"venue"
},
  "geometry": {"coordinates":[-122.424846,37.785957],"type":"Point"}
}