{
  "type": "Feature",
  "properties": {
    "iso:country":"US",
    "sg:address":"6 Burlington Cir",
    "sg:city":"Salinas",
    "sg:classifiers":[
        {
            "category":"Freight",
            "type":"Transportation"
        }
    ],
    "sg:phone":"+1 831 444 6299",
    "sg:postcode":"93906",
    "sg:province":"CA",
    "sg:tags":[
        "mover"
    ],
    "wof:name":"Moore's Executive Moving Svc",
    "wof:placetype":"venue"
},
  "geometry": {"coordinates":[-121.61839,36.706694],"type":"Point"}
}