{
  "type": "Feature",
  "properties": {
    "iso:country":"US",
    "sg:address":"2929 Theresa Dr",
    "sg:city":"Newbury Park",
    "sg:classifiers":[
        {
            "category":"Shopping",
            "subcategory":"Thrift Store",
            "type":"Retail Goods"
        }
    ],
    "sg:phone":"+1 805 498 7886",
    "sg:postcode":"91320",
    "sg:province":"CA",
    "wof:name":"Merry Hall Tree Thrift Shop",
    "wof:placetype":"venue"
},
  "geometry": {"coordinates":[-118.939003,34.178799],"type":"Point"}
}