{
  "type": "Feature",
  "properties": {
    "addr:full":"15061 Springdale St Ste 102 Huntington Beach CA 92649",
    "addr:housenumber":"15061",
    "addr:postcode":"92649",
    "addr:street":"Springdale St Ste 102",
    "iso:country":"US",
    "sg:address":"15061 Springdale St Ste 102",
    "sg:city":"Huntington Beach",
    "sg:classifiers":[
        {
            "category":"Wholesale",
            "subcategory":"Computers",
            "type":"Manufacturing & Wholesale Goods"
        },
        {
            "category":"Shopping",
            "subcategory":"Music",
            "type":"Retail Goods"
        },
        {
            "category":"Professional",
            "subcategory":"Computer Services",
            "type":"Services"
        }
    ],
    "sg:phone":"+1 714 891 4205",
    "sg:postcode":"92649",
    "sg:province":"CA",
    "sg:tags":[
        "repair",
        "dvd's"
    ],
    "wof:name":"Lms North America",
    "wof:placetype":"venue"
},
  "geometry": {"coordinates":[-118.02488200000001,33.743803],"type":"Point"}
}