{
  "type": "Feature",
  "properties": {
    "iso:country":"US",
    "sg:address":"3430 Robin Ln",
    "sg:city":"Cameron Park",
    "sg:classifiers":[
        {
            "category":"Personal",
            "type":"Services"
        }
    ],
    "sg:phone":"+1 530 676 5984",
    "sg:postcode":"95682",
    "sg:province":"CA",
    "sg:tags":[
        "therapist",
        "massage"
    ],
    "wof:name":"Lisa Harris",
    "wof:placetype":"venue"
},
  "geometry": {"coordinates":[-120.966083,38.655516],"type":"Point"}
}