{
  "type": "Feature",
  "properties": {
    "iso:country":"US",
    "sg:address":"3144 W Adams St",
    "sg:city":"Santa Ana",
    "sg:classifiers":[
        {
            "category":"Manufacturing",
            "subcategory":"Food",
            "type":"Manufacturing & Wholesale Goods"
        }
    ],
    "sg:phone":"+1 714 540 3535",
    "sg:postcode":"92704",
    "sg:province":"CA",
    "sg:tags":[
        "frozen",
        "bakery",
        "product",
        "mfg"
    ],
    "wof:name":"Bonerts Inc",
    "wof:placetype":"venue"
},
  "geometry": {"coordinates":[-117.912171,33.711125],"type":"Point"}
}