{
  "type": "Feature",
  "properties": {
    "addr:full":"411 W 7th St Los Angeles CA 90014",
    "addr:housenumber":"411",
    "addr:postcode":"90014",
    "addr:street":"W 7Th St",
    "iso:country":"US",
    "sg:address":"411 W 7th St",
    "sg:city":"Los Angeles",
    "sg:classifiers":[
        {
            "category":"Professional",
            "subcategory":"Management & Consulting",
            "type":"Services"
        }
    ],
    "sg:phone":"+1 213 624 2202",
    "sg:postcode":"90014",
    "sg:province":"CA",
    "sg:tags":[
        "break",
        "coffee",
        "supply"
    ],
    "wof:name":"Cafe Argentina",
    "wof:placetype":"venue"
},
  "geometry": {"coordinates":[-118.25473700000001,34.046156],"type":"Point"}
}