{
  "type": "Feature",
  "properties": {
    "addr:full":"3609 C Midway Dr San Diego CA 92110",
    "addr:housenumber":"3609 c",
    "addr:postcode":"92110",
    "addr:street":"Midway Dr",
    "iso:country":"US",
    "sg:address":"3609 C Midway Dr",
    "sg:city":"San Diego",
    "sg:classifiers":[
        {
            "category":"Shopping",
            "subcategory":"Thrift Store",
            "type":"Retail Goods"
        }
    ],
    "sg:phone":"+1 619 224 4336",
    "sg:postcode":"92110",
    "sg:province":"CA",
    "sg:website":"cancer.org/discovery",
    "wof:name":"American Cancer Society Discovery Shop",
    "wof:placetype":"venue"
},
  "geometry": {"coordinates":[-117.215852,32.752011],"type":"Point"}
}