{
  "type": "Feature",
  "properties": {
    "iso:country":"US",
    "sg:address":"1850 Hacienda Dr Ste 15",
    "sg:city":"Vista",
    "sg:classifiers":[
        {
            "category":"Health Services",
            "subcategory":"Health Practitioner",
            "type":"Services"
        }
    ],
    "sg:phone":"+1 760 806 0064",
    "sg:postcode":"92081",
    "sg:province":"CA",
    "sg:tags":[
        "acupuncture"
    ],
    "wof:name":"A CHEN'S ACUPUNCTURE & HERBS",
    "wof:placetype":"venue"
},
  "geometry": {"coordinates":[-117.28061,33.186652],"type":"Point"}
}