{
  "type": "Feature",
  "properties": {
    "iso:country":"US",
    "sg:address":"415 E 19th St Apt 5",
    "sg:city":"Oakland",
    "sg:classifiers":[
        {
            "category":"Shopping",
            "subcategory":"Music",
            "type":"Retail Goods"
        }
    ],
    "sg:phone":"+1 831 331 0930",
    "sg:postcode":"94606",
    "sg:province":"CA",
    "sg:tags":[
        "store"
    ],
    "wof:name":"Bersa Discos",
    "wof:placetype":"venue"
},
  "geometry": {"coordinates":[-122.249534,37.799367],"type":"Point"}
}