{
  "type": "Feature",
  "properties": {
    "iso:country":"US",
    "sg:address":"3871 20th St",
    "sg:city":"San Francisco",
    "sg:classifiers":[
        {
            "category":"Building & Trades",
            "subcategory":"Landscaping Services",
            "type":"Services"
        }
    ],
    "sg:phone":"+1 415 505 7900",
    "sg:postcode":"94114",
    "sg:province":"CA",
    "sg:tags":[
        "landscape"
    ],
    "sg:website":"www.avantgardener.org",
    "wof:name":"The Avant Gardener",
    "wof:placetype":"venue"
},
  "geometry": {"coordinates":[-122.42730400000001,37.75789],"type":"Point"}
}