{
  "type": "Feature",
  "properties": {
    "iso:country":"US",
    "sg:address":"6938 Almaden Expy",
    "sg:city":"San Jose",
    "sg:classifiers":[
        {
            "category":"Food & Beverages",
            "subcategory":"Groceries & Convenience Stores",
            "type":"Retail Goods"
        }
    ],
    "sg:phone":"+1 408 997 2202",
    "sg:postcode":"95120",
    "sg:province":"CA",
    "wof:name":"PW Super",
    "wof:placetype":"venue"
},
  "geometry": {"coordinates":[-121.87117600000001,37.231603],"type":"Point"}
}