{
  "type": "Feature",
  "properties": {
    "iso:country":"US",
    "sg:address":"24711 Redlands Blvd",
    "sg:city":"Loma Linda",
    "sg:classifiers":[
        {
            "category":"Manufacturing",
            "subcategory":"Signs",
            "type":"Manufacturing & Wholesale Goods"
        }
    ],
    "sg:phone":"+1 909 799 7000",
    "sg:postcode":"92354",
    "sg:province":"CA",
    "sg:tags":[
        "specialty",
        "mfg"
    ],
    "wof:name":"Xgraphix",
    "wof:placetype":"venue"
},
  "geometry": {"coordinates":[-117.261207,34.063065],"type":"Point"}
}