{
  "type": "Feature",
  "properties": {
    "iso:country":"US",
    "sg:address":"13423 S Budlong Ave",
    "sg:city":"Gardena",
    "sg:classifiers":[
        {
            "category":"Wholesale",
            "subcategory":"Scrap",
            "type":"Manufacturing & Wholesale Goods"
        }
    ],
    "sg:phone":"+1 310 768 1730",
    "sg:postcode":"90247",
    "sg:province":"CA",
    "sg:tags":[
        "recycling",
        "center"
    ],
    "wof:name":"American Pad Ex",
    "wof:placetype":"venue"
},
  "geometry": {"coordinates":[-118.29644,33.909449],"type":"Point"}
}