{
  "type": "Feature",
  "properties": {
    "iso:country":"US",
    "sg:address":"2080 Llano Rd",
    "sg:city":"Santa Rosa",
    "sg:classifiers":[
        {
            "category":"Autos & Motor Vehicles",
            "subcategory":"Recreational Vehicle Sales",
            "type":"Retail Goods"
        },
        {
            "category":"Wholesale",
            "subcategory":"Auto Parts",
            "type":"Manufacturing & Wholesale Goods"
        }
    ],
    "sg:phone":"+1 707 571 1878",
    "sg:postcode":"95407",
    "sg:province":"CA",
    "sg:tags":[
        "equipment",
        "truck"
    ],
    "wof:name":"Ultimate Bed Linings",
    "wof:placetype":"venue"
},
  "geometry": {"coordinates":[-122.788468,38.401934],"type":"Point"}
}