{
  "type": "Feature",
  "properties": {
    "addr:full":"1875 S Grant St San Mateo CA 94402",
    "addr:housenumber":"1875",
    "addr:postcode":"94402",
    "addr:street":"S Grant St",
    "iso:country":"US",
    "sg:address":"1875 S Grant St",
    "sg:city":"San Mateo",
    "sg:classifiers":[
        {
            "category":"Professional",
            "subcategory":"Research",
            "type":"Services"
        }
    ],
    "sg:phone":"+1 650 286 4000",
    "sg:postcode":"94402",
    "sg:province":"CA",
    "sg:tags":[
        "biotechnology",
        "product"
    ],
    "sg:website":"www.bioform.com",
    "wof:name":"Bioform",
    "wof:placetype":"venue"
},
  "geometry": {"coordinates":[-122.302091,37.554463],"type":"Point"}
}