{
  "type": "Feature",
  "properties": {
    "iso:country":"US",
    "sg:address":"3100 Telegraph Ave",
    "sg:city":"Oakland",
    "sg:classifiers":[
        {
            "category":"Health Services",
            "subcategory":"Doctor",
            "type":"Services"
        }
    ],
    "sg:phone":"+1 510 893 6060",
    "sg:postcode":"94609",
    "sg:province":"CA",
    "wof:name":"Calma Jacques MD Internal Medicine",
    "wof:placetype":"venue"
},
  "geometry": {"coordinates":[-122.266998,37.82],"type":"Point"}
}