{
  "type": "Feature",
  "properties": {
    "addr:full":"645 W Olive Ave Merced CA 95348",
    "addr:housenumber":"645",
    "addr:postcode":"95348",
    "addr:street":"W Olive Ave",
    "iso:country":"US",
    "sg:address":"645 W Olive Ave",
    "sg:city":"Merced",
    "sg:classifiers":[
        {
            "category":"Organizations",
            "subcategory":"Non-profit Organization",
            "type":"Services"
        }
    ],
    "sg:phone":"+1 209 383 4700",
    "sg:postcode":"95348",
    "sg:province":"CA",
    "sg:tags":[
        "alternative",
        "abortion"
    ],
    "wof:name":"Alpha Pregnancy Health Ctr",
    "wof:placetype":"venue"
},
  "geometry": {"coordinates":[-120.480463,37.319344],"type":"Point"}
}