{
  "type": "Feature",
  "properties": {
    "iso:country":"US",
    "sg:address":"6713 Ave 424",
    "sg:city":"Dinuba",
    "sg:classifiers":[
        {
            "category":"Personal",
            "subcategory":"Beauty Salon",
            "type":"Services"
        }
    ],
    "sg:phone":"+1 559 591 4500",
    "sg:postcode":"93618",
    "sg:province":"CA",
    "wof:name":"Martie's Hair Styles",
    "wof:placetype":"venue"
},
  "geometry": {"coordinates":[-119.424117,36.560618],"type":"Point"}
}