{
  "type": "Feature",
  "properties": {
    "addr:full":"408 Union Ave #C Fairfield CA 94533",
    "addr:housenumber":"408",
    "addr:postcode":"94533",
    "addr:street":"Union Ave # C",
    "iso:country":"US",
    "sg:address":"408 Union Ave #C",
    "sg:city":"Fairfield",
    "sg:classifiers":[
        {
            "category":"Autos & Motor Vehicles",
            "subcategory":"Auto Supplies",
            "type":"Retail Goods"
        },
        {
            "category":"Retail",
            "subcategory":"Auto Repair",
            "type":"Services"
        }
    ],
    "sg:phone":"+1 707 428 3707",
    "sg:postcode":"94533",
    "sg:province":"CA",
    "sg:tags":[
        "exhaust",
        "absorber",
        "clutch",
        "shock",
        "system",
        "strut",
        "brake",
        "muffler",
        "hitch",
        "trailer"
    ],
    "wof:name":"Muffler Store II",
    "wof:placetype":"venue"
},
  "geometry": {"coordinates":[-122.04055700000001,38.245973],"type":"Point"}
}