{
  "type": "Feature",
  "properties": {
    "addr:full":"221 Ridge Rd Pismo Beach CA 93449",
    "addr:housenumber":"221",
    "addr:postcode":"93449",
    "addr:street":"Ridge Rd",
    "iso:country":"US",
    "sg:address":"221 Ridge Rd",
    "sg:city":"Pismo Beach",
    "sg:classifiers":[
        {
            "category":"Professional",
            "subcategory":"Engineering",
            "type":"Services"
        }
    ],
    "sg:phone":"+1 805 474 4764",
    "sg:postcode":"93449",
    "sg:province":"CA",
    "wof:name":"Adair Engineering Inc",
    "wof:placetype":"venue"
},
  "geometry": {"coordinates":[-120.61425800000001,35.137108],"type":"Point"}
}