{
  "type": "Feature",
  "properties": {
    "addr:full":"7634 Pearblossom Hwy Littlerock CA 93543",
    "addr:housenumber":"7634",
    "addr:postcode":"93543",
    "addr:street":"Pearblossom Hwy",
    "iso:country":"US",
    "sg:address":"7634 Pearblossom Hwy",
    "sg:city":"Littlerock",
    "sg:classifiers":[
        {
            "category":"Autos & Motor Vehicles",
            "subcategory":"Auto Supplies",
            "type":"Retail Goods"
        }
    ],
    "sg:phone":"+1 661 944 0492",
    "sg:postcode":"93543",
    "sg:province":"CA",
    "sg:tags":[
        "tire"
    ],
    "wof:name":"Central Tire",
    "wof:placetype":"venue"
},
  "geometry": {"coordinates":[-117.99496499999999,34.521046],"type":"Point"}
}