{
  "type": "Feature",
  "properties": {
    "iso:country":"US",
    "sg:address":"5660 Freeport Blvd",
    "sg:city":"Sacramento",
    "sg:classifiers":[
        {
            "category":"Recreation",
            "type":"Entertainment"
        }
    ],
    "sg:phone":"+1 916 395 7827",
    "sg:postcode":"95822",
    "sg:province":"CA",
    "sg:tags":[
        "entertainers-family",
        "business"
    ],
    "wof:name":"Mgm Entertainment Incorporated",
    "wof:placetype":"venue"
},
  "geometry": {"coordinates":[-121.497726,38.52343],"type":"Point"}
}