{
  "type": "Feature",
  "properties": {
    "addr:full":"3412 E Miner Ave Stockton CA 95205",
    "addr:housenumber":"3412",
    "addr:postcode":"95205",
    "addr:street":"E Miner Ave",
    "iso:country":"US",
    "sg:address":"3412 E Miner Ave",
    "sg:city":"Stockton",
    "sg:classifiers":[
        {
            "category":"Wholesale",
            "subcategory":"Machinery & Supplies",
            "type":"Manufacturing & Wholesale Goods"
        }
    ],
    "sg:phone":"+1 209 462 1495",
    "sg:postcode":"95205",
    "sg:province":"CA",
    "sg:tags":[
        "dyer",
        "cleaners",
        "equipment"
    ],
    "sg:website":"www.frimair.com",
    "wof:name":"Frimair USA West Inc",
    "wof:placetype":"venue"
},
  "geometry": {"coordinates":[-121.246061,37.96508],"type":"Point"}
}