{
  "type": "Feature",
  "properties": {
    "addr:full":"425 Market Street Suite 2210 San Francisco CA 94105",
    "addr:housenumber":"425",
    "addr:postcode":"94105",
    "addr:street":"Market Street Suite 2210",
    "iso:country":"US",
    "sg:address":"425 Market Street Suite 2210",
    "sg:city":"San Francisco",
    "sg:classifiers":[
        {
            "category":"Professional",
            "subcategory":"Computer Services",
            "type":"Services"
        }
    ],
    "sg:phone":"+1 877 826 6427",
    "sg:postcode":"94105",
    "sg:province":"CA",
    "sg:tags":[
        "remote-support",
        "remote-control",
        "remote-access",
        "helpdesk",
        "remote-desktop-control",
        "service-desk"
    ],
    "sg:website":"http://www.bomgar.com/",
    "wof:name":"Bomgar",
    "wof:placetype":"venue"
},
  "geometry": {"coordinates":[-122.39887299999999,37.791095],"type":"Point"}
}