{
  "type": "Feature",
  "properties": {
    "addr:full":"30 Melsenna Ct Danville CA 94506",
    "addr:housenumber":"30",
    "addr:postcode":"94506",
    "addr:street":"Melsenna Ct",
    "iso:country":"US",
    "sg:address":"30 Melsenna Ct",
    "sg:city":"Danville",
    "sg:classifiers":[
        {
            "category":"Wholesale",
            "subcategory":"Electrical",
            "type":"Manufacturing & Wholesale Goods"
        },
        {
            "category":"Shopping",
            "subcategory":"Computers & Home Electronics",
            "type":"Retail Goods"
        }
    ],
    "sg:phone":"+1 925 766 4343",
    "sg:postcode":"94506",
    "sg:province":"CA",
    "sg:tags":[
        "equipment",
        "consumer",
        "electric",
        "supply"
    ],
    "wof:name":"Hidden Hills Electronics",
    "wof:placetype":"venue"
},
  "geometry": {"coordinates":[-121.902282,37.79366],"type":"Point"}
}