{
  "type": "Feature",
  "properties": {
    "addr:full":"3031 Tisch Way Ste 1, Plaza S San Jose CA 95128",
    "addr:postcode":"3031;95128",
    "addr:street":"Tisch Way Ste 1 Plaza S",
    "iso:country":"US",
    "sg:address":"3031 Tisch Way Ste 1, Plaza S",
    "sg:city":"San Jose",
    "sg:classifiers":[
        {
            "category":"Personal",
            "subcategory":"Massage",
            "type":"Services"
        },
        {
            "category":"Education",
            "subcategory":"Special Training",
            "type":"Public Place"
        }
    ],
    "sg:phone":"+1 408 423 8004",
    "sg:postcode":"95128",
    "sg:province":"CA",
    "sg:tags":[
        "school",
        "specialty",
        "adult"
    ],
    "sg:website":"www.nhi.edu",
    "wof:name":"National Holistic Institute",
    "wof:placetype":"venue"
},
  "geometry": {"coordinates":[-121.94852400000001,37.317181],"type":"Point"}
}