{
  "type": "Feature",
  "properties": {
    "addr:full":"1725 W Florida Ave Hemet CA 92545",
    "addr:housenumber":"1725",
    "addr:postcode":"92545",
    "addr:street":"W Florida Ave",
    "iso:country":"US",
    "sg:address":"1725 W Florida Ave",
    "sg:city":"Hemet",
    "sg:classifiers":[
        {
            "category":"Shopping",
            "subcategory":"Bicycles & Sporting Goods",
            "type":"Retail Goods"
        }
    ],
    "sg:phone":"+1 951 658 2676",
    "sg:postcode":"92545",
    "sg:province":"CA",
    "wof:name":"Bicycle Service Center",
    "wof:placetype":"venue"
},
  "geometry": {"coordinates":[-116.989302,33.747384],"type":"Point"}
}