{
  "type": "Feature",
  "properties": {
    "iso:country":"US",
    "sg:address":"6693 Greenback Ln",
    "sg:city":"Citrus Heights",
    "sg:classifiers":[
        {
            "category":"Professional",
            "subcategory":"Printing & Photocopies",
            "type":"Services"
        }
    ],
    "sg:phone":"+1 916 725 7661",
    "sg:postcode":"95621",
    "sg:province":"CA",
    "wof:name":"Gilliam & Associates Printing Services",
    "wof:placetype":"venue"
},
  "geometry": {"coordinates":[-121.308723,38.678399],"type":"Point"}
}