{
  "type": "Feature",
  "properties": {
    "iso:country":"US",
    "sg:address":"800 W. El Camino Real Suite 180",
    "sg:city":"Mountain View",
    "sg:classifiers":[
        {
            "category":"Professional",
            "subcategory":"Computer Services",
            "type":"Services"
        }
    ],
    "sg:postcode":"94040",
    "sg:province":"CA",
    "sg:tags":[
        "ajax",
        "javascript",
        "forums",
        "australia"
    ],
    "sg:website":"http://www.tangler.com",
    "wof:name":"Tangler",
    "wof:placetype":"venue"
},
  "geometry": {"coordinates":[-122.082551,37.385036],"type":"Point"}
}