{
  "type": "Feature",
  "properties": {
    "addr:full":"13475 Danielson St # 220 Poway CA 92064",
    "addr:housenumber":"13475",
    "addr:postcode":"ca 92064",
    "addr:street":"Danielson St # 220",
    "iso:country":"US",
    "sg:address":"13475 Danielson St # 220",
    "sg:city":"Poway",
    "sg:classifiers":[
        {
            "category":"Professional",
            "subcategory":"Computer Services",
            "type":"Services"
        }
    ],
    "sg:phone":"+1 858 427 4554",
    "sg:postcode":"92064",
    "sg:province":"CA",
    "sg:tags":[
        "publisher",
        "developer",
        "software"
    ],
    "sg:website":"http://www.ccsincus.com",
    "wof:name":"California Creative Solutions, Inc",
    "wof:placetype":"venue"
},
  "geometry": {"coordinates":[-117.037885,32.939868],"type":"Point"}
}