{
  "type": "Feature",
  "properties": {
    "addr:full":"417 Main St Ste 101 Huntington Beach CA 92648",
    "addr:housenumber":"417",
    "addr:postcode":"92648",
    "addr:street":"Main St Ste 101",
    "iso:country":"US",
    "sg:address":"417 Main St Ste 101",
    "sg:city":"Huntington Beach",
    "sg:classifiers":[
        {
            "category":"Wholesale",
            "subcategory":"Computers",
            "type":"Manufacturing & Wholesale Goods"
        },
        {
            "category":"Professional",
            "subcategory":"Computer Services",
            "type":"Services"
        }
    ],
    "sg:phone":"+1 714 969 3001",
    "sg:postcode":"92648",
    "sg:province":"CA",
    "sg:tags":[
        "repair"
    ],
    "sg:website":"www.hbtechusa.com",
    "wof:name":"H B Tech Corp",
    "wof:placetype":"venue"
},
  "geometry": {"coordinates":[-117.99903399999999,33.660561],"type":"Point"}
}