{
  "type": "Feature",
  "properties": {
    "iso:country":"US",
    "sg:address":"15900 S Broadway",
    "sg:city":"Blythe",
    "sg:classifiers":[
        {
            "category":"Wholesale",
            "subcategory":"Farm Supplies",
            "type":"Manufacturing & Wholesale Goods"
        }
    ],
    "sg:phone":"+1 760 922 2276",
    "sg:postcode":"92225",
    "sg:province":"CA",
    "sg:tags":[
        "feed"
    ],
    "wof:name":"Leonard's Broadway Gardens",
    "wof:placetype":"venue"
},
  "geometry": {"coordinates":[-114.59626400000001,33.588334],"type":"Point"}
}