{
  "type": "Feature",
  "properties": {
    "iso:country":"US",
    "sg:address":"328 N Maple Dr",
    "sg:city":"Beverly Hills",
    "sg:classifiers":[
        {
            "category":"Manufacturing",
            "subcategory":"Printing",
            "type":"Manufacturing & Wholesale Goods"
        }
    ],
    "sg:phone":"+1 310 271 9839",
    "sg:postcode":"90210",
    "sg:province":"CA",
    "sg:tags":[
        "miscellaneous",
        "publishing"
    ],
    "wof:name":"Tobias Associates Inc",
    "wof:placetype":"venue"
},
  "geometry": {"coordinates":[-118.393429,34.072645],"type":"Point"}
}