{
  "type": "Feature",
  "properties": {
    "addr:full":"366 Fisher St Los Angeles CA 90042",
    "addr:housenumber":"366",
    "addr:postcode":"90042",
    "addr:street":"Fisher St",
    "iso:country":"US",
    "sg:address":"366 Fisher St",
    "sg:city":"Los Angeles",
    "sg:classifiers":[
        {
            "category":"Health Services",
            "subcategory":"Clinic",
            "type":"Services"
        }
    ],
    "sg:phone":"+1 323 550 1650",
    "sg:postcode":"90042",
    "sg:province":"CA",
    "wof:name":"Goodlife Health & Nutrition",
    "wof:placetype":"venue"
},
  "geometry": {"coordinates":[-118.18187399999999,34.120754],"type":"Point"}
}