{
  "type": "Feature",
  "properties": {
    "addr:full":"1550 State Hwy 46 Paso Robles CA 93446",
    "addr:housenumber":"1550",
    "addr:postcode":"93446",
    "addr:street":"State Hwy 46",
    "iso:country":"US",
    "sg:address":"1550 State Hwy 46",
    "sg:city":"Paso Robles",
    "sg:phone":"+1 805 238 3482",
    "sg:postcode":"93446",
    "sg:province":"CA",
    "sg:tags":[
        "farm",
        "field",
        "crop"
    ],
    "wof:name":"Anderson John",
    "wof:placetype":"venue"
},
  "geometry": {"coordinates":[-120.720882,35.579472],"type":"Point"}
}