{
  "type": "Feature",
  "properties": {
    "addr:full":"11234 Anderson St Loma Linda CA 92354",
    "addr:housenumber":"11234",
    "addr:postcode":"92354",
    "addr:street":"Anderson St",
    "iso:country":"US",
    "sg:address":"11234 Anderson St",
    "sg:city":"Loma Linda",
    "sg:classifiers":[
        {
            "category":"Health Services",
            "subcategory":"Doctor",
            "type":"Services"
        }
    ],
    "sg:phone":"+1 909 796 7311",
    "sg:postcode":"92354",
    "sg:province":"CA",
    "sg:tags":[
        "physician",
        "surgeon"
    ],
    "wof:name":"Maureen H Bull MD",
    "wof:placetype":"venue"
},
  "geometry": {"coordinates":[-117.26120299999999,34.049464],"type":"Point"}
}