{
  "type": "Feature",
  "properties": {
    "iso:country":"US",
    "sg:address":"900 Main St",
    "sg:city":"Janesville",
    "sg:classifiers":[
        {
            "category":"Freight",
            "type":"Transportation"
        }
    ],
    "sg:phone":"+1 530 253 2233",
    "sg:postcode":"96114",
    "sg:province":"CA",
    "sg:tags":[
        "commercial",
        "storage"
    ],
    "wof:name":"Janesville Self Storage",
    "wof:placetype":"venue"
},
  "geometry": {"coordinates":[-120.525398,40.297073],"type":"Point"}
}