{
  "type": "Feature",
  "properties": {
    "addr:full":"540 Warner Ave Los Angeles CA 90024",
    "addr:housenumber":"540",
    "addr:postcode":"90024",
    "addr:street":"Warner Ave",
    "iso:country":"US",
    "sg:address":"540 Warner Ave",
    "sg:city":"Los Angeles",
    "sg:classifiers":[
        {
            "category":"Professional",
            "subcategory":"Accounting & Tax Preparation",
            "type":"Services"
        }
    ],
    "sg:phone":"+1 310 475 1813",
    "sg:postcode":"90024",
    "sg:province":"CA",
    "sg:tags":[
        "accountant"
    ],
    "wof:name":"Golman Leroy H",
    "wof:placetype":"venue"
},
  "geometry": {"coordinates":[-118.435997,34.0709],"type":"Point"}
}