{
  "type": "Feature",
  "properties": {
    "addr:full":"823 Arguello St Redwood City CA 94063",
    "addr:housenumber":"823",
    "addr:postcode":"94063",
    "addr:street":"Arguello St",
    "iso:country":"US",
    "sg:address":"823 Arguello St",
    "sg:city":"Redwood City",
    "sg:classifiers":[
        {
            "category":"Building & Trades",
            "subcategory":"Construction",
            "type":"Services"
        }
    ],
    "sg:phone":"+1 650 366 8803",
    "sg:postcode":"94063",
    "sg:province":"CA",
    "sg:tags":[
        "contractor"
    ],
    "wof:name":"Butterfield Construction",
    "wof:placetype":"venue"
},
  "geometry": {"coordinates":[-122.234849,37.488258],"type":"Point"}
}