{
  "type": "Feature",
  "properties": {
    "iso:country":"US",
    "sg:address":"309 Roundtree Ct",
    "sg:city":"Brea",
    "sg:classifiers":[
        {
            "category":"Building & Trades",
            "subcategory":"Construction",
            "type":"Services"
        }
    ],
    "sg:phone":"+1 714 990 9151",
    "sg:postcode":"92821",
    "sg:province":"CA",
    "sg:tags":[
        "house"
    ],
    "wof:name":"Johnsons Home Builders",
    "wof:placetype":"venue"
},
  "geometry": {"coordinates":[-117.868928,33.922218],"type":"Point"}
}