{
  "type": "Feature",
  "properties": {
    "iso:country":"US",
    "sg:address":"1634 Pacific Coast Hwy",
    "sg:city":"Harbor City",
    "sg:classifiers":[
        {
            "category":"Travel",
            "subcategory":"Hotels & Motels",
            "type":"Entertainment"
        }
    ],
    "sg:phone":"+1 310 325 0066",
    "sg:postcode":"90710",
    "sg:province":"CA",
    "wof:name":"Guest House Inn",
    "wof:placetype":"venue"
},
  "geometry": {"coordinates":[-118.306,33.7896],"type":"Point"}
}