{
  "type": "Feature",
  "properties": {
    "iso:country":"US",
    "sg:address":"216 Broad St",
    "sg:city":"Nevada City",
    "sg:classifiers":[
        {
            "category":"Restaurant",
            "type":"Food & Drink"
        }
    ],
    "sg:phone":"+1 530 265 9440",
    "sg:postcode":"95959",
    "sg:province":"CA",
    "wof:name":"Downtown Georges",
    "wof:placetype":"venue"
},
  "geometry": {"coordinates":[-121.017456,39.262391],"type":"Point"}
}