{
  "type": "Feature",
  "properties": {
    "addr:full":"18811 Huntington Street Huntington Beach CA 92648",
    "addr:housenumber":"18811",
    "addr:postcode":"92648",
    "addr:street":"Huntington Street",
    "iso:country":"US",
    "sg:address":"18811 Huntington Street",
    "sg:city":"Huntington Beach",
    "sg:classifiers":[
        {
            "category":"Health Services",
            "subcategory":"Doctor",
            "type":"Services"
        },
        {
            "category":"Health Services",
            "subcategory":"Health Practitioner",
            "type":"Services"
        }
    ],
    "sg:phone":"+1 714 596 1105",
    "sg:postcode":"92648",
    "sg:province":"CA",
    "sg:tags":[
        "therapy",
        "physical"
    ],
    "sg:website":"www.californiacoastmedical.com",
    "wof:name":"Kockinis Thomas MD",
    "wof:placetype":"venue"
},
  "geometry": {"coordinates":[-117.995378,33.689415],"type":"Point"}
}