{
  "type": "Feature",
  "properties": {
    "iso:country":"US",
    "sg:address":"2145 Court St",
    "sg:city":"Redding",
    "sg:classifiers":[
        {
            "category":"Health Services",
            "subcategory":"Medical Lab",
            "type":"Services"
        }
    ],
    "sg:phone":"+1 530 243 7030",
    "sg:postcode":"96001",
    "sg:province":"CA",
    "sg:tags":[
        "laboratory"
    ],
    "wof:name":"Northern Diagnostic Pathology",
    "wof:placetype":"venue"
},
  "geometry": {"coordinates":[-122.39349300000001,40.578417],"type":"Point"}
}