{
  "type": "Feature",
  "properties": {
    "addr:full":"23900 Constantine Dr Murrieta CA 92562",
    "addr:postcode":"23900;92562",
    "addr:street":"Constantine Dr",
    "iso:country":"US",
    "sg:address":"23900 Constantine Dr",
    "sg:city":"Murrieta",
    "sg:classifiers":[
        {
            "category":"Autos & Motor Vehicles",
            "subcategory":"Automobile Sales",
            "type":"Retail Goods"
        }
    ],
    "sg:phone":"+1 951 698 6144",
    "sg:postcode":"92562",
    "sg:province":"CA",
    "sg:tags":[
        "car",
        "used"
    ],
    "wof:name":"3 Cs Fine Sauces",
    "wof:placetype":"venue"
},
  "geometry": {"coordinates":[-117.222138,33.574579],"type":"Point"}
}