{
  "type": "Feature",
  "properties": {
    "addr:full":"12120 Tech Center Dr Poway CA 92064",
    "addr:housenumber":"12120",
    "addr:postcode":"ca 92064",
    "addr:street":"Tech Center Dr",
    "iso:country":"US",
    "sg:address":"12120 Tech Center Dr",
    "sg:city":"Poway",
    "sg:classifiers":[
        {
            "category":"Building & Trades",
            "subcategory":"Plumbing",
            "type":"Services"
        }
    ],
    "sg:phone":"+1 858 486 5111",
    "sg:postcode":"92064",
    "sg:province":"CA",
    "sg:tags":[
        "plumber",
        "industrial",
        "sewer",
        "cleaning",
        "plumbing-drain",
        "contractors-commercial"
    ],
    "sg:website":"http://www.dependableplumbingco.com",
    "wof:name":"Dependable Plumbing",
    "wof:placetype":"venue"
},
  "geometry": {"coordinates":[-117.036592,32.936794],"type":"Point"}
}