{
  "type": "Feature",
  "properties": {
    "iso:country":"US",
    "sg:address":"10112 Indiana Ave",
    "sg:city":"Riverside",
    "sg:classifiers":[
        {
            "category":"Personal",
            "subcategory":"Nail Salon",
            "type":"Services"
        }
    ],
    "sg:phone":"+1 951 785 0144",
    "sg:postcode":"92503",
    "sg:province":"CA",
    "wof:name":"Nails N Beyond",
    "wof:placetype":"venue"
},
  "geometry": {"coordinates":[-117.452792,33.907629],"type":"Point"}
}