{
  "type": "Feature",
  "properties": {
    "addr:full":"4505 44th St Sacramento CA 95820",
    "addr:housenumber":"4505",
    "addr:postcode":"95820",
    "addr:street":"44Th St",
    "iso:country":"US",
    "sg:address":"4505 44th St",
    "sg:city":"Sacramento",
    "sg:classifiers":[
        {
            "category":"Social Services",
            "subcategory":"Child Care",
            "type":"Services"
        }
    ],
    "sg:phone":"+1 916 457 1229",
    "sg:postcode":"95820",
    "sg:province":"CA",
    "wof:name":"Open Arms Ministry",
    "wof:placetype":"venue"
},
  "geometry": {"coordinates":[-121.45537899999999,38.533722],"type":"Point"}
}