{
  "type": "Feature",
  "properties": {
    "addr:full":"330 S Magnolia Ave El Cajon CA 92020",
    "addr:housenumber":"330",
    "addr:postcode":"92020",
    "addr:street":"S Magnolia Ave",
    "iso:country":"US",
    "sg:address":"330 S Magnolia Ave",
    "sg:city":"El Cajon",
    "sg:classifiers":[
        {
            "category":"Building & Trades",
            "subcategory":"Construction",
            "type":"Services"
        }
    ],
    "sg:phone":"+1 619 593 3527",
    "sg:postcode":"92020",
    "sg:province":"CA",
    "sg:tags":[
        "contractor"
    ],
    "wof:name":"Halbert Construction",
    "wof:placetype":"venue"
},
  "geometry": {"coordinates":[-116.962399,32.79194],"type":"Point"}
}