{
  "type": "Feature",
  "properties": {
    "iso:country":"US",
    "sg:address":"1777 Yosemite Ave",
    "sg:city":"San Francisco",
    "sg:classifiers":[
        {
            "category":"Building & Trades",
            "subcategory":"Landscaping Services",
            "type":"Services"
        }
    ],
    "sg:phone":"+1 415 671 2190",
    "sg:postcode":"94124",
    "sg:province":"CA",
    "sg:tags":[
        "designer",
        "landscape"
    ],
    "wof:name":"Jenn Carroll Wilson Landscape",
    "wof:placetype":"venue"
},
  "geometry": {"coordinates":[-122.394311,37.728095],"type":"Point"}
}