{
  "type": "Feature",
  "properties": {
    "iso:country":"US",
    "sg:address":"976 Embarcadero del Mar",
    "sg:city":"Goleta",
    "sg:classifiers":[
        {
            "category":"Place Of Worship",
            "subcategory":"Church",
            "type":"Public Place"
        },
        {
            "category":"Place Of Worship",
            "type":"Public Place"
        }
    ],
    "sg:phone":"+1 805 968 8028",
    "sg:postcode":"93117",
    "sg:province":"CA",
    "sg:tags":[
        "churches-interdenominational",
        "churches-various",
        "denomination"
    ],
    "wof:name":"Saint Brigid Fellowship",
    "wof:placetype":"venue"
},
  "geometry": {"coordinates":[-119.857017,34.411412],"type":"Point"}
}