{
  "type": "Feature",
  "properties": {
    "addr:full":"2200 County Center Dr Santa Rosa CA 95403",
    "addr:housenumber":"2200",
    "addr:postcode":"95403",
    "addr:street":"County Center Dr",
    "iso:country":"US",
    "sg:address":"2200 County Center Dr",
    "sg:city":"Santa Rosa",
    "sg:classifiers":[
        {
            "category":"Professional",
            "type":"Services"
        }
    ],
    "sg:phone":"+1 707 570 1780",
    "sg:postcode":"95403",
    "sg:province":"CA",
    "wof:name":"Redwood LLC",
    "wof:placetype":"venue"
},
  "geometry": {"coordinates":[-122.726101,38.463102],"type":"Point"}
}