{
  "type": "Feature",
  "properties": {
    "iso:country":"US",
    "sg:address":"3855 E La Palma Ste 115",
    "sg:city":"Anaheim",
    "sg:classifiers":[
        {
            "category":"Health Services",
            "subcategory":"Clinic",
            "type":"Services"
        }
    ],
    "sg:phone":"+1 714 747 6959",
    "sg:postcode":"92807",
    "sg:province":"CA",
    "sg:tags":[
        "counseling",
        "mental"
    ],
    "sg:website":"www.SandyMWolf.com",
    "wof:name":"Sandra M. Wolf, MFT",
    "wof:placetype":"venue"
},
  "geometry": {"coordinates":[-117.834585,33.856003],"type":"Point"}
}