{
  "type": "Feature",
  "properties": {
    "iso:country":"US",
    "sg:address":"850 Harbor Blvd",
    "sg:city":"Ventura",
    "sg:classifiers":[
        {
            "category":"Recreation",
            "type":"Entertainment"
        }
    ],
    "sg:phone":"+1 805 650 7770",
    "sg:postcode":"93001",
    "sg:province":"CA",
    "sg:tags":[
        "bicycle"
    ],
    "wof:name":"Wheel Fun Rentals",
    "wof:placetype":"venue"
},
  "geometry": {"coordinates":[-119.284783,34.273143],"type":"Point"}
}