{
  "type": "Feature",
  "properties": {
    "iso:country":"US",
    "sg:address":"Brookhurst & Yorktow",
    "sg:city":"Huntington Beach",
    "sg:classifiers":[
        {
            "category":"Restaurant",
            "type":"Food & Drink"
        }
    ],
    "sg:phone":"+1 714 964 4477",
    "sg:postcode":"92646",
    "sg:province":"CA",
    "sg:tags":[
        "pizza"
    ],
    "wof:name":"Little Caesar's Pizza",
    "wof:placetype":"venue"
},
  "geometry": {"coordinates":[-117.969689,33.667481],"type":"Point"}
}