{
  "type": "Feature",
  "properties": {
    "iso:country":"US",
    "sg:address":"7793 Wren Ave",
    "sg:city":"Gilroy",
    "sg:classifiers":[
        {
            "category":"Health Services",
            "subcategory":"Doctor",
            "type":"Services"
        }
    ],
    "sg:phone":"+1 408 848 0444",
    "sg:postcode":"95020",
    "sg:province":"CA",
    "sg:tags":[
        "physician",
        "family",
        "practice",
        "surgeons",
        "medicine",
        "surgeon"
    ],
    "wof:name":"Soderberg, Beck B, Md - Pinnacle Healthcare",
    "wof:placetype":"venue"
},
  "geometry": {"coordinates":[-121.587051,37.010404],"type":"Point"}
}