{
  "type": "Feature",
  "properties": {
    "iso:country":"US",
    "sg:address":"9005 Elk Grove Blvd",
    "sg:city":"Elk Grove",
    "sg:classifiers":[
        {
            "category":"Shopping",
            "type":"Retail Goods"
        }
    ],
    "sg:phone":"+1 916 714 4515",
    "sg:postcode":"95624",
    "sg:province":"CA",
    "sg:tags":[
        "cards",
        "sport",
        "baseball",
        "memorabilia"
    ],
    "wof:name":"Sports Card Mania Of Elk Grove",
    "wof:placetype":"venue"
},
  "geometry": {"coordinates":[-121.366338,38.40908],"type":"Point"}
}