{
  "type": "Feature",
  "properties": {
    "addr:full":"629 Lynwood St Thousand Oaks CA 91360",
    "addr:housenumber":"629",
    "addr:postcode":"91360",
    "addr:street":"Lynwood St",
    "iso:country":"US",
    "sg:address":"629 Lynwood St",
    "sg:city":"Thousand Oaks",
    "sg:classifiers":[
        {
            "category":"Manufacturing",
            "subcategory":"Electronics",
            "type":"Manufacturing & Wholesale Goods"
        }
    ],
    "sg:phone":"+1 805 241 9530",
    "sg:postcode":"91360",
    "sg:province":"CA",
    "sg:tags":[
        "devices",
        "mfg"
    ],
    "wof:name":"Asce Power Inc",
    "wof:placetype":"venue"
},
  "geometry": {"coordinates":[-118.89543500000001,34.201346],"type":"Point"}
}