{
  "type": "Feature",
  "properties": {
    "addr:full":"3217 1/2 W Beverly Blvd Montebello CA 90640",
    "addr:housenumber":"3217 1 / 2",
    "addr:postcode":"90640",
    "addr:street":"W Beverly Blvd",
    "iso:country":"US",
    "sg:address":"3217 1/2 W Beverly Blvd",
    "sg:city":"Montebello",
    "sg:phone":"+1 323 723 7435",
    "sg:postcode":"90640",
    "sg:province":"CA",
    "wof:name":"Don's Body Shop",
    "wof:placetype":"venue"
},
  "geometry": {"coordinates":[-118.138334,34.023883],"type":"Point"}
}