{
  "type": "Feature",
  "properties": {
    "addr:full":"1680 Civic Center Dr Santa Clara CA 95050",
    "addr:housenumber":"1680",
    "addr:postcode":"95050",
    "addr:street":"Civic Center Dr",
    "iso:country":"US",
    "sg:address":"1680 Civic Center Dr",
    "sg:city":"Santa Clara",
    "sg:classifiers":[
        {
            "category":"Building & Trades",
            "subcategory":"Construction",
            "type":"Services"
        }
    ],
    "sg:phone":"+1 408 249 1820",
    "sg:postcode":"95050",
    "sg:province":"CA",
    "sg:tags":[
        "contractor"
    ],
    "wof:name":"Construction Contractor Club Inc",
    "wof:placetype":"venue"
},
  "geometry": {"coordinates":[-121.957384,37.353727],"type":"Point"}
}