{
  "type": "Feature",
  "properties": {
    "addr:full":"1611 Lyon St San Francisco CA 94115",
    "addr:housenumber":"1611",
    "addr:postcode":"94115",
    "addr:street":"Lyon St",
    "iso:country":"US",
    "sg:address":"1611 Lyon St",
    "sg:city":"San Francisco",
    "sg:classifiers":[
        {
            "category":"Travel",
            "subcategory":"Travel Agent",
            "type":"Entertainment"
        }
    ],
    "sg:phone":"+1 415 931 1591",
    "sg:postcode":"94115",
    "sg:province":"CA",
    "sg:tags":[
        "agency"
    ],
    "wof:name":"Wellington World Travel",
    "wof:placetype":"venue"
},
  "geometry": {"coordinates":[-122.445267,37.786373],"type":"Point"}
}