{
  "type": "Feature",
  "properties": {
    "iso:country":"US",
    "sg:address":"1510 W 228th St",
    "sg:city":"Torrance",
    "sg:classifiers":[
        {
            "category":"Freight",
            "type":"Transportation"
        }
    ],
    "sg:phone":"+1 310 891 2377",
    "sg:postcode":"90501",
    "sg:province":"CA",
    "sg:tags":[
        "operator",
        "trucking"
    ],
    "wof:name":"Tonka Moving Company",
    "wof:placetype":"venue"
},
  "geometry": {"coordinates":[-118.30608,33.818948],"type":"Point"}
}