{
  "type": "Feature",
  "properties": {
    "addr:full":"7000 Maze Blvd Modesto CA 95358",
    "addr:postcode":"7000;ca 95358",
    "addr:street":"Maze Blvd",
    "iso:country":"US",
    "sg:address":"7000 Maze Blvd",
    "sg:city":"Modesto",
    "sg:classifiers":[
        {
            "category":"Bars & Pubs",
            "type":"Food & Drink"
        }
    ],
    "sg:phone":"+1 209 529 7007",
    "sg:postcode":"95358",
    "sg:province":"CA",
    "sg:tags":[
        "drinking"
    ],
    "wof:name":"Mint Club",
    "wof:placetype":"venue"
},
  "geometry": {"coordinates":[-121.135852,37.637826],"type":"Point"}
}