{
  "type": "Feature",
  "properties": {
    "addr:full":"14160 Hesperia Rd Victorville CA 92395",
    "addr:housenumber":"14160",
    "addr:postcode":"92395",
    "addr:street":"Hesperia Rd",
    "iso:country":"US",
    "sg:address":"14160 Hesperia Rd",
    "sg:city":"Victorville",
    "sg:classifiers":[
        {
            "category":"Building & Trades",
            "subcategory":"Plumbing",
            "type":"Services"
        },
        {
            "category":"Building & Trades",
            "subcategory":"Construction",
            "type":"Services"
        }
    ],
    "sg:phone":"+1 760 245 5557",
    "sg:postcode":"92395",
    "sg:province":"CA",
    "sg:tags":[
        "plumber",
        "system",
        "specialty",
        "heating",
        "contractor",
        "plumbing-drain",
        "air conditioning",
        "sewer",
        "cleaning"
    ],
    "sg:website":"http://www.beamanbrosplumbing.com",
    "wof:name":"Beaman Brothers - Plumbing - Heating Air Conditioning",
    "wof:placetype":"venue"
},
  "geometry": {"coordinates":[-117.296936,34.508134],"type":"Point"}
}