{
  "type": "Feature",
  "properties": {
    "addr:full":"325 E Bidwell St Folsom CA 95630",
    "addr:housenumber":"325",
    "addr:postcode":"95630",
    "addr:street":"E Bidwell St",
    "iso:country":"US",
    "sg:address":"325 E Bidwell St",
    "sg:city":"Folsom",
    "sg:classifiers":[
        {
            "category":"Shopping",
            "subcategory":"Clothing, Apparel, & Fashions",
            "type":"Retail Goods"
        }
    ],
    "sg:phone":"+1 916 984 9543",
    "sg:postcode":"95630",
    "sg:province":"CA",
    "sg:tags":[
        "infant",
        "wear"
    ],
    "wof:name":"Gymboree",
    "wof:placetype":"venue"
},
  "geometry": {"coordinates":[-121.168285,38.674179],"type":"Point"}
}