{
  "type": "Feature",
  "properties": {
    "addr:full":"3757 Santa Rosalia Dr Los Angeles CA 90008",
    "addr:housenumber":"3757",
    "addr:postcode":"90008",
    "addr:street":"Santa Rosalia Dr",
    "iso:country":"US",
    "sg:address":"3757 Santa Rosalia Dr",
    "sg:city":"Los Angeles",
    "sg:classifiers":[
        {
            "category":"Health Services",
            "subcategory":"Doctor",
            "type":"Services"
        }
    ],
    "sg:phone":"+1 323 564 4331",
    "sg:postcode":"90008",
    "sg:province":"CA",
    "sg:tags":[
        "physician",
        "surgeon"
    ],
    "wof:name":"RCA Medical Group",
    "wof:placetype":"venue"
},
  "geometry": {"coordinates":[-118.338617,34.008397],"type":"Point"}
}