{
  "type": "Feature",
  "properties": {
    "iso:country":"US",
    "sg:address":"4056 Easy St",
    "sg:city":"El Monte",
    "sg:classifiers":[
        {
            "category":"Manufacturing",
            "subcategory":"Rubber & Plastics",
            "type":"Manufacturing & Wholesale Goods"
        }
    ],
    "sg:phone":"+1 626 443 6094",
    "sg:postcode":"91731",
    "sg:province":"CA",
    "sg:tags":[
        "laminate",
        "sheet",
        "mfg"
    ],
    "sg:website":"www.mcgillcorp.com",
    "wof:name":"M C Gill Corp",
    "wof:placetype":"venue"
},
  "geometry": {"coordinates":[-118.060629,34.082422],"type":"Point"}
}