{
  "type": "Feature",
  "properties": {
    "iso:country":"US",
    "sg:address":"8118 Sikes Rd",
    "sg:city":"Dixon",
    "sg:classifiers":[
        {
            "category":"Farming",
            "subcategory":"Dairy Farm",
            "type":"Manufacturing & Wholesale Goods"
        }
    ],
    "sg:phone":"+1 707 678 5704",
    "sg:postcode":"95620",
    "sg:province":"CA",
    "wof:name":"B & G Dixon Dairy",
    "wof:placetype":"venue"
},
  "geometry": {"coordinates":[-121.748976,38.464993],"type":"Point"}
}