{
  "type": "Feature",
  "properties": {
    "iso:country":"US",
    "sg:address":"695 Atherton Pl",
    "sg:city":"Hayward",
    "sg:classifiers":[
        {
            "category":"Professional",
            "type":"Services"
        }
    ],
    "sg:phone":"+1 510 889 8332",
    "sg:postcode":"94541",
    "sg:province":"CA",
    "wof:name":"Dotdiva Designs",
    "wof:placetype":"venue"
},
  "geometry": {"coordinates":[-122.084768,37.669313],"type":"Point"}
}