{
  "type": "Feature",
  "properties": {
    "iso:country":"US",
    "sg:address":"3221 Hollis St",
    "sg:city":"Emeryville",
    "sg:classifiers":[
        {
            "category":"Professional",
            "type":"Services"
        }
    ],
    "sg:phone":"+1 510 985 1022",
    "sg:postcode":"94608",
    "sg:province":"CA",
    "wof:name":"Polywog",
    "wof:placetype":"venue"
},
  "geometry": {"coordinates":[-122.284178,37.825723],"type":"Point"}
}