{
  "type": "Feature",
  "properties": {
    "addr:full":"660 Main St Red Bluff CA 96080",
    "addr:housenumber":"660",
    "addr:postcode":"96080",
    "addr:street":"Main St",
    "iso:country":"US",
    "sg:address":"660 Main St",
    "sg:city":"Red Bluff",
    "sg:classifiers":[
        {
            "category":"Real Estate",
            "subcategory":"Real Estate Agent",
            "type":"Services"
        }
    ],
    "sg:phone":"+1 530 529 2300",
    "sg:postcode":"96080",
    "sg:province":"CA",
    "wof:name":"Gipson Realty",
    "wof:placetype":"venue"
},
  "geometry": {"coordinates":[-122.234506,40.176995],"type":"Point"}
}