{
  "type": "Feature",
  "properties": {
    "iso:country":"US",
    "sg:address":"82524 Miles Ave",
    "sg:city":"Indio",
    "sg:classifiers":[
        {
            "category":"Recreation",
            "type":"Entertainment"
        }
    ],
    "sg:phone":"+1 760 342 2346",
    "sg:postcode":"92201",
    "sg:province":"CA",
    "sg:tags":[
        "club",
        "membership"
    ],
    "wof:name":"Boy Scouts Of America",
    "wof:placetype":"venue"
},
  "geometry": {"coordinates":[-116.22426,33.721272],"type":"Point"}
}