{
  "type": "Feature",
  "properties": {
    "addr:full":"99 Pullman Way San Jose CA 95111",
    "addr:housenumber":"99",
    "addr:postcode":"95111",
    "addr:street":"Pullman Way",
    "iso:country":"US",
    "sg:address":"99 Pullman Way",
    "sg:city":"San Jose",
    "sg:classifiers":[
        {
            "category":"Building & Trades",
            "subcategory":"Construction",
            "type":"Services"
        }
    ],
    "sg:phone":"+1 408 300 5605",
    "sg:postcode":"95111",
    "sg:province":"CA",
    "sg:tags":[
        "contractor"
    ],
    "sg:website":"www.appianengineering.com",
    "wof:name":"Appian Engineering",
    "wof:placetype":"venue"
},
  "geometry": {"coordinates":[-121.849738,37.29022],"type":"Point"}
}