{
  "type": "Feature",
  "properties": {
    "addr:full":"2642 Water Tree Way Sacramento CA 95826",
    "addr:housenumber":"2642",
    "addr:postcode":"95826",
    "addr:street":"Water Tree Way",
    "iso:country":"US",
    "sg:address":"2642 Water Tree Way",
    "sg:city":"Sacramento",
    "sg:classifiers":[
        {
            "category":"Professional",
            "subcategory":"Computer Services",
            "type":"Services"
        }
    ],
    "sg:phone":"+1 916 368 7333",
    "sg:postcode":"95826",
    "sg:province":"CA",
    "sg:tags":[
        "website",
        "design"
    ],
    "wof:name":"Independent Development",
    "wof:placetype":"venue"
},
  "geometry": {"coordinates":[-121.371516,38.561501],"type":"Point"}
}