{
  "type": "Feature",
  "properties": {
    "iso:country":"US",
    "sg:address":"3200 Rio Lindo Ave",
    "sg:city":"Healdsburg",
    "sg:classifiers":[
        {
            "category":"Education",
            "subcategory":"Special Training",
            "type":"Public Place"
        }
    ],
    "sg:phone":"+1 707 431 5153",
    "sg:postcode":"95448",
    "sg:province":"CA",
    "sg:tags":[
        "instruction",
        "driving"
    ],
    "wof:name":"Bright Horizon School-Driving",
    "wof:placetype":"venue"
},
  "geometry": {"coordinates":[-122.829536,38.615105],"type":"Point"}
}