{
  "type": "Feature",
  "properties": {
    "iso:country":"US",
    "sg:address":"112 S La Brea Ave",
    "sg:city":"Los Angeles",
    "sg:classifiers":[
        {
            "category":"Shopping",
            "subcategory":"Clothing, Apparel, & Fashions",
            "type":"Retail Goods"
        }
    ],
    "sg:phone":"+1 323 933 2251",
    "sg:postcode":"90036",
    "sg:province":"CA",
    "sg:tags":[
        "men's",
        "clothing",
        "women's"
    ],
    "wof:name":"Stussy",
    "wof:placetype":"venue"
},
  "geometry": {"coordinates":[-118.344002,34.073101],"type":"Point"}
}