{
  "type": "Feature",
  "properties": {
    "iso:country":"US",
    "sg:address":"1114 S Truro Ave",
    "sg:city":"Inglewood",
    "sg:classifiers":[
        {
            "category":"Building & Trades",
            "subcategory":"Landscaping Services",
            "type":"Services"
        }
    ],
    "sg:phone":"+1 310 677 9652",
    "sg:postcode":"90301",
    "sg:province":"CA",
    "wof:name":"Rudys Landscaping Service",
    "wof:placetype":"venue"
},
  "geometry": {"coordinates":[-118.35794,33.947533],"type":"Point"}
}