{
  "type": "Feature",
  "properties": {
    "addr:full":"9287 S Ravine Ln Fair Oaks CA 95628",
    "addr:housenumber":"9287",
    "addr:postcode":"95628",
    "addr:street":"S Ravine Ln",
    "iso:country":"US",
    "sg:address":"9287 S Ravine Ln",
    "sg:city":"Fair Oaks",
    "sg:classifiers":[
        {
            "category":"Professional",
            "subcategory":"Management & Consulting",
            "type":"Services"
        }
    ],
    "sg:phone":"+1 916 765 1122",
    "sg:postcode":"95628",
    "sg:province":"CA",
    "sg:tags":[
        "fuel"
    ],
    "wof:name":"Osterlund Project Mgmt",
    "wof:placetype":"venue"
},
  "geometry": {"coordinates":[-121.20761,38.658532],"type":"Point"}
}