{
  "type": "Feature",
  "properties": {
    "addr:full":"1460 N Lake Ave Pasadena CA 91104",
    "addr:housenumber":"1460",
    "addr:postcode":"91104",
    "addr:street":"N Lake Ave",
    "iso:country":"US",
    "sg:address":"1460 N Lake Ave",
    "sg:city":"Pasadena",
    "sg:classifiers":[
        {
            "category":"Manufacturing",
            "subcategory":"Chemicals & Compounds",
            "type":"Manufacturing & Wholesale Goods"
        },
        {
            "category":"Animal Shelter",
            "type":"Public Place"
        },
        {
            "category":"Building & Trades",
            "subcategory":"Pest Control",
            "type":"Services"
        }
    ],
    "sg:phone":"+1 866 574 1660",
    "sg:postcode":"91104",
    "sg:province":"CA",
    "sg:tags":[
        "industrial",
        "supply",
        "services-commercial",
        "termite",
        "bee",
        "equipment",
        "mothproofing",
        "removal"
    ],
    "sg:website":"http://orkin.com",
    "wof:name":"Orkin Pest & Termite Control",
    "wof:placetype":"venue"
},
  "geometry": {"coordinates":[-118.13215,34.17123],"type":"Point"}
}