{
  "type": "Feature",
  "properties": {
    "iso:country":"US",
    "sg:address":"950 W D St",
    "sg:city":"Ontario",
    "sg:classifiers":[
        {
            "category":"Education",
            "subcategory":"School",
            "type":"Public Place"
        }
    ],
    "sg:phone":"+1 909 459 2500",
    "sg:postcode":"91762",
    "sg:province":"CA",
    "sg:tags":[
        "district"
    ],
    "sg:website":"www.omsd.k12.ca.us",
    "wof:name":"Ontario-Montclair School Dist",
    "wof:placetype":"venue"
},
  "geometry": {"coordinates":[-117.667636,34.067044],"type":"Point"}
}