{
  "type": "Feature",
  "properties": {
    "iso:country":"US",
    "sg:address":"1882 Winterwood Ct",
    "sg:city":"Redding",
    "sg:classifiers":[
        {
            "category":"Professional",
            "subcategory":"Business Services",
            "type":"Services"
        }
    ],
    "sg:phone":"+1 530 221 7063",
    "sg:postcode":"96002",
    "sg:province":"CA",
    "sg:tags":[
        "appraiser"
    ],
    "wof:name":"W Coast Appraisals",
    "wof:placetype":"venue"
},
  "geometry": {"coordinates":[-122.335831,40.557926],"type":"Point"}
}