{
  "type": "Feature",
  "properties": {
    "addr:full":"26285 Windsor Dr Loma Linda CA 92354",
    "addr:housenumber":"26285",
    "addr:postcode":"92354",
    "addr:street":"Windsor Dr",
    "iso:country":"US",
    "sg:address":"26285 Windsor Dr",
    "sg:city":"Loma Linda",
    "sg:classifiers":[
        {
            "category":"Health Services",
            "subcategory":"Hospital",
            "type":"Services"
        }
    ],
    "sg:phone":"+1 323 260 4145",
    "sg:postcode":"92354",
    "sg:province":"CA",
    "sg:tags":[
        "general"
    ],
    "wof:name":"East Los Angels Hospital",
    "wof:placetype":"venue"
},
  "geometry": {"coordinates":[-117.231939,34.042465],"type":"Point"}
}