{
  "type": "Feature",
  "properties": {
    "iso:country":"US",
    "sg:address":"2265 Westwood Blvd",
    "sg:city":"Los Angeles",
    "sg:classifiers":[
        {
            "category":"Banks & Credit Unions",
            "subcategory":"Investment Brokerage",
            "type":"Services"
        }
    ],
    "sg:phone":"+1 310 281 6164",
    "sg:postcode":"90064",
    "sg:province":"CA",
    "sg:tags":[
        "management",
        "asset"
    ],
    "wof:name":"Asset Investigations",
    "wof:placetype":"venue"
},
  "geometry": {"coordinates":[-118.431208,34.043322],"type":"Point"}
}