{
  "type": "Feature",
  "properties": {
    "addr:full":"1935 Alpine Blvd Alpine CA 91901",
    "addr:housenumber":"1935",
    "addr:postcode":"91901",
    "addr:street":"Alpine Blvd",
    "iso:country":"US",
    "sg:address":"1935 Alpine Blvd",
    "sg:city":"Alpine",
    "sg:classifiers":[
        {
            "category":"Shopping",
            "type":"Retail Goods"
        }
    ],
    "sg:phone":"+1 619 659 8459",
    "sg:postcode":"91901",
    "sg:province":"CA",
    "sg:tags":[
        "merchandise"
    ],
    "wof:name":"Finders Keepers Shoppe",
    "wof:placetype":"venue"
},
  "geometry": {"coordinates":[-116.77247300000001,32.837055],"type":"Point"}
}