{
  "type": "Feature",
  "properties": {
    "iso:country":"US",
    "sg:address":"206 E Marlette St",
    "sg:city":"Ione",
    "sg:classifiers":[
        {
            "category":"Wholesale",
            "subcategory":"Vending Machines",
            "type":"Manufacturing & Wholesale Goods"
        }
    ],
    "sg:phone":"+1 209 274 2882",
    "sg:postcode":"95640",
    "sg:province":"CA",
    "wof:name":"Johnson's Vending",
    "wof:placetype":"venue"
},
  "geometry": {"coordinates":[-120.930061,38.351118],"type":"Point"}
}