{
  "type": "Feature",
  "properties": {
    "addr:full":"3240 Scott St San Francisco CA 94123",
    "addr:housenumber":"3240",
    "addr:postcode":"94123",
    "addr:street":"Scott St",
    "iso:country":"US",
    "sg:address":"3240 Scott St",
    "sg:city":"San Francisco",
    "sg:classifiers":[
        {
            "category":"Real Estate",
            "subcategory":"Architect",
            "type":"Services"
        }
    ],
    "sg:phone":"+1 415 563 0608",
    "sg:postcode":"94123",
    "sg:province":"CA",
    "sg:tags":[
        "designer",
        "architectural"
    ],
    "wof:name":"Mc Carville Design",
    "wof:placetype":"venue"
},
  "geometry": {"coordinates":[-122.441039,37.799803],"type":"Point"}
}