{
  "type": "Feature",
  "properties": {
    "iso:country":"US",
    "sg:address":"1533 Via Leon",
    "sg:city":"Palos Verdes Peninsula",
    "sg:classifiers":[
        {
            "category":"Professional",
            "type":"Services"
        }
    ],
    "sg:phone":"+1 310 544 9684",
    "sg:postcode":"90274",
    "sg:province":"CA",
    "wof:name":"Maximum Life Foundation",
    "wof:placetype":"venue"
},
  "geometry": {"coordinates":[-118.405337,33.778943],"type":"Point"}
}