{
  "type": "Feature",
  "properties": {
    "iso:country":"US",
    "sg:address":"321 W 135th St",
    "sg:city":"Los Angeles",
    "sg:classifiers":[
        {
            "category":"Retail",
            "subcategory":"Auto Repair",
            "type":"Services"
        }
    ],
    "sg:phone":"+1 310 324 2181",
    "sg:postcode":"90061",
    "sg:province":"CA",
    "sg:tags":[
        "spring"
    ],
    "wof:name":"American Spring",
    "wof:placetype":"venue"
},
  "geometry": {"coordinates":[-118.280491,33.909244],"type":"Point"}
}