{
  "type": "Feature",
  "properties": {
    "addr:full":"1970 Chestnut Street Berkeley CA 94702",
    "addr:housenumber":"1970",
    "addr:postcode":"94702",
    "addr:street":"Chestnut Street",
    "iso:country":"US",
    "sg:address":"1970 Chestnut Street",
    "sg:city":"Berkeley",
    "sg:classifiers":[
        {
            "category":"Education",
            "subcategory":"Preschool",
            "type":"Public Place"
        }
    ],
    "sg:postcode":"94702",
    "sg:province":"CA",
    "sg:website":"www.girotondoschool.org",
    "wof:name":"Girotondo Italian Preschool",
    "wof:placetype":"venue"
},
  "geometry": {"coordinates":[-122.288387,37.870188],"type":"Point"}
}