{
  "type": "Feature",
  "properties": {
    "addr:full":"1162 Josselyn Canyon Rd Monterey CA 93940",
    "addr:housenumber":"1162",
    "addr:postcode":"93940",
    "addr:street":"Josselyn Canyon Rd",
    "iso:country":"US",
    "sg:address":"1162 Josselyn Canyon Rd",
    "sg:city":"Monterey",
    "sg:classifiers":[
        {
            "category":"Manufacturing",
            "subcategory":"Toys & Sporting Goods",
            "type":"Manufacturing & Wholesale Goods"
        }
    ],
    "sg:phone":"+1 831 373 4297",
    "sg:postcode":"93940",
    "sg:province":"CA",
    "sg:tags":[
        "mfg"
    ],
    "wof:name":"Ohana Distributing",
    "wof:placetype":"venue"
},
  "geometry": {"coordinates":[-121.87041000000001,36.592772],"type":"Point"}
}