{
  "type": "Feature",
  "properties": {
    "iso:country":"US",
    "sg:address":"3001 N Sepulveda Blvd",
    "sg:city":"Manhattan Beach",
    "sg:classifiers":[
        {
            "category":"Personal",
            "subcategory":"Shoe Repair & Shine",
            "type":"Services"
        }
    ],
    "sg:phone":"+1 310 546 7977",
    "sg:postcode":"90266",
    "sg:province":"CA",
    "sg:tags":[
        "repairing",
        "boot"
    ],
    "wof:name":"Village Shoe Repair",
    "wof:placetype":"venue"
},
  "geometry": {"coordinates":[-118.396004,33.897301],"type":"Point"}
}