{
  "type": "Feature",
  "properties": {
    "addr:full":"115 W Linden Ct Burbank CA 91502",
    "addr:housenumber":"115",
    "addr:postcode":"91502",
    "addr:street":"W Linden Ct",
    "iso:country":"US",
    "sg:address":"115 W Linden Ct",
    "sg:city":"Burbank",
    "sg:classifiers":[
        {
            "category":"Building & Trades",
            "subcategory":"Construction",
            "type":"Services"
        }
    ],
    "sg:phone":"+1 818 846 0695",
    "sg:postcode":"91502",
    "sg:province":"CA",
    "sg:tags":[
        "contractor"
    ],
    "wof:name":"Sierra Pacific General Contrs",
    "wof:placetype":"venue"
},
  "geometry": {"coordinates":[-118.30077,34.168474],"type":"Point"}
}