{
  "type": "Feature",
  "properties": {
    "iso:country":"US",
    "sg:address":"931 California Ave",
    "sg:city":"Bakersfield",
    "sg:classifiers":[
        {
            "category":"Retail",
            "subcategory":"Repair Shop",
            "type":"Services"
        }
    ],
    "sg:phone":"+1 661 322 2044",
    "sg:postcode":"93304",
    "sg:province":"CA",
    "sg:tags":[
        "jewelry"
    ],
    "wof:name":"Craig's Custom Jewelry",
    "wof:placetype":"venue"
},
  "geometry": {"coordinates":[-119.012681,35.368389],"type":"Point"}
}