{
  "type": "Feature",
  "properties": {
    "addr:full":"1617 Westcliff Drive Suite 109 Newport Beach CA 92660",
    "addr:housenumber":"1617",
    "addr:postcode":"92660",
    "addr:street":"Westcliff Drive Suite 109",
    "iso:country":"US",
    "sg:address":"1617 Westcliff Drive Suite 109",
    "sg:city":"Newport Beach",
    "sg:classifiers":[
        {
            "category":"Sports & Exercise",
            "subcategory":"Gym",
            "type":"Entertainment"
        }
    ],
    "sg:phone":"+1 949 642 5866",
    "sg:postcode":"92660",
    "sg:province":"CA",
    "sg:tags":[
        "trainer"
    ],
    "wof:name":"No Xcuz Fitness",
    "wof:placetype":"venue"
},
  "geometry": {"coordinates":[-117.905181,33.625895],"type":"Point"}
}