{
  "type": "Feature",
  "properties": {
    "iso:country":"US",
    "sg:address":"367 Burns Dr",
    "sg:city":"Yuba City",
    "sg:classifiers":[
        {
            "category":"Real Estate",
            "subcategory":"Real Estate Operator",
            "type":"Services"
        }
    ],
    "sg:phone":"+1 530 674 7565",
    "sg:postcode":"95991",
    "sg:province":"CA",
    "sg:tags":[
        "apartment"
    ],
    "wof:name":"Carb Shop",
    "wof:placetype":"venue"
},
  "geometry": {"coordinates":[-121.609172,39.10948],"type":"Point"}
}