{
  "type": "Feature",
  "properties": {
    "iso:country":"US",
    "sg:address":"5716 Main St",
    "sg:city":"Kelseyville",
    "sg:classifiers":[
        {
            "category":"Real Estate",
            "subcategory":"Real Estate Agent",
            "type":"Services"
        }
    ],
    "sg:phone":"+1 707 279 2790",
    "sg:postcode":"95451",
    "sg:province":"CA",
    "sg:website":"www.bigvalleyproperties.com",
    "wof:name":"Big Valley Properties",
    "wof:placetype":"venue"
},
  "geometry": {"coordinates":[-122.829981,38.972123],"type":"Point"}
}