{
  "type": "Feature",
  "properties": {
    "iso:country":"US",
    "sg:address":"6445 Cottle Rd",
    "sg:city":"San Jose",
    "sg:classifiers":[
        {
            "category":"Farming",
            "subcategory":"Farm",
            "type":"Manufacturing & Wholesale Goods"
        }
    ],
    "sg:phone":"+1 408 629 1216",
    "sg:postcode":"95123",
    "sg:province":"CA",
    "sg:tags":[
        "crop",
        "general"
    ],
    "wof:name":"Randy Goettsch",
    "wof:placetype":"venue"
},
  "geometry": {"coordinates":[-121.807649,37.22589],"type":"Point"}
}