{
  "type": "Feature",
  "properties": {
    "iso:country":"US",
    "sg:address":"2516 Heide Ct",
    "sg:city":"El Sobrante",
    "sg:classifiers":[
        {
            "category":"Professional",
            "type":"Services"
        }
    ],
    "sg:phone":"+1 510 222 4236",
    "sg:postcode":"94803",
    "sg:province":"CA",
    "wof:name":"Sterrett Family Ltd Partnr",
    "wof:placetype":"venue"
},
  "geometry": {"coordinates":[-122.265798,37.95195],"type":"Point"}
}