{
  "type": "Feature",
  "properties": {
    "addr:full":"1600 Oak St South Pasadena CA 91030",
    "addr:housenumber":"1600",
    "addr:postcode":"91030",
    "addr:street":"Oak St",
    "iso:country":"US",
    "sg:address":"1600 Oak St",
    "sg:city":"South Pasadena",
    "sg:classifiers":[
        {
            "category":"Education",
            "subcategory":"School",
            "type":"Public Place"
        }
    ],
    "sg:phone":"+1 626 441 5830",
    "sg:postcode":"91030",
    "sg:province":"CA",
    "sg:tags":[
        "high",
        "middle",
        "elementary"
    ],
    "wof:name":"South Pasadena Unified School District",
    "wof:placetype":"venue"
},
  "geometry": {"coordinates":[-118.15031999999999,34.107897],"type":"Point"}
}