{
  "type": "Feature",
  "properties": {
    "iso:country":"US",
    "sg:address":"220 Five Cities Dr",
    "sg:city":"Pismo Beach",
    "sg:classifiers":[
        {
            "category":"Restaurant",
            "type":"Food & Drink"
        }
    ],
    "sg:phone":"+1 805 773 2772",
    "sg:postcode":"93449",
    "sg:province":"CA",
    "wof:name":"Vallarta Mexican Restaurant",
    "wof:placetype":"venue"
},
  "geometry": {"coordinates":[-120.630353,35.137589],"type":"Point"}
}