{
  "type": "Feature",
  "properties": {
    "iso:country":"US",
    "sg:address":"40690 California Oaks Rd",
    "sg:city":"Murrieta",
    "sg:classifiers":[
        {
            "category":"Health Services",
            "subcategory":"Doctor",
            "type":"Services"
        }
    ],
    "sg:phone":"+1 951 698 5765",
    "sg:postcode":"92562",
    "sg:province":"CA",
    "sg:tags":[
        "physician",
        "surgeon"
    ],
    "wof:name":"Pervaiz Channah & Assoc",
    "wof:placetype":"venue"
},
  "geometry": {"coordinates":[-117.203473,33.572353],"type":"Point"}
}