{
  "type": "Feature",
  "properties": {
    "addr:full":"11289 Baseline Rd Rancho Cucamonga CA 91730",
    "addr:housenumber":"11289",
    "addr:postcode":"91730",
    "addr:street":"Baseline Rd",
    "iso:country":"US",
    "sg:address":"11289 Baseline Rd",
    "sg:city":"Rancho Cucamonga",
    "sg:classifiers":[
        {
            "category":"Professional",
            "subcategory":"Management & Consulting",
            "type":"Services"
        }
    ],
    "sg:phone":"+1 909 476 6930",
    "sg:postcode":"91730",
    "sg:province":"CA",
    "sg:tags":[
        "consultant",
        "business"
    ],
    "wof:name":"CAR Enterprises Inc",
    "wof:placetype":"venue"
},
  "geometry": {"coordinates":[-117.55964400000001,34.121407],"type":"Point"}
}