{
  "type": "Feature",
  "properties": {
    "addr:full":"90 Glenn Way San Carlos CA 94070",
    "addr:housenumber":"90",
    "addr:postcode":"94070",
    "addr:street":"Glenn Way",
    "iso:country":"US",
    "sg:address":"90 Glenn Way",
    "sg:city":"San Carlos",
    "sg:classifiers":[
        {
            "category":"Building & Trades",
            "subcategory":"Cleaning & Sanitation",
            "type":"Services"
        }
    ],
    "sg:phone":"+1 707 453 1375",
    "sg:postcode":"94070",
    "sg:province":"CA",
    "sg:tags":[
        "janitor"
    ],
    "wof:name":"Qwest Commercial Svc",
    "wof:placetype":"venue"
},
  "geometry": {"coordinates":[-122.264788,37.514615],"type":"Point"}
}