{
  "type": "Feature",
  "properties": {
    "addr:full":"5485 Club Dr San Jose CA 95127",
    "addr:housenumber":"5485",
    "addr:postcode":"95127",
    "addr:street":"Club Dr",
    "iso:country":"US",
    "sg:address":"5485 Club Dr",
    "sg:city":"San Jose",
    "sg:classifiers":[
        {
            "category":"Shopping",
            "subcategory":"Computers & Home Electronics",
            "type":"Retail Goods"
        }
    ],
    "sg:phone":"+1 408 729 7445",
    "sg:postcode":"95127",
    "sg:province":"CA",
    "wof:name":"Packards California",
    "wof:placetype":"venue"
},
  "geometry": {"coordinates":[-121.821268,37.384637],"type":"Point"}
}