{
  "type": "Feature",
  "properties": {
    "iso:country":"US",
    "sg:address":"708 State St",
    "sg:city":"Santa Barbara",
    "sg:classifiers":[
        {
            "category":"Professional",
            "subcategory":"Business Services",
            "type":"Services"
        }
    ],
    "sg:phone":"+1 805 892 5561",
    "sg:postcode":"93101",
    "sg:province":"CA",
    "sg:tags":[
        "interior",
        "consultant",
        "design",
        "decorator"
    ],
    "wof:name":"Nest",
    "wof:placetype":"venue"
},
  "geometry": {"coordinates":[-119.699021,34.419456],"type":"Point"}
}