{
  "type": "Feature",
  "properties": {
    "iso:country":"US",
    "sg:address":"7814 Ivanhoe Ave",
    "sg:city":"La Jolla",
    "sg:classifiers":[
        {
            "category":"Professional",
            "subcategory":"Accounting & Tax Preparation",
            "type":"Services"
        }
    ],
    "sg:phone":"+1 858 454 8433",
    "sg:postcode":"92037",
    "sg:province":"CA",
    "sg:tags":[
        "accountant"
    ],
    "wof:name":"Massey Ward & Company CPA",
    "wof:placetype":"venue"
},
  "geometry": {"coordinates":[-117.272003,32.8461],"type":"Point"}
}