{
  "type": "Feature",
  "properties": {
    "iso:country":"US",
    "sg:address":"20432 Silverado Ave",
    "sg:city":"Cupertino",
    "sg:classifiers":[
        {
            "category":"Health Services",
            "subcategory":"Health Practitioner",
            "type":"Services"
        }
    ],
    "sg:phone":"+1 408 257 0317",
    "sg:postcode":"95014",
    "sg:province":"CA",
    "sg:tags":[
        "hypnotist"
    ],
    "wof:name":"Quality Of Life Hypnosis",
    "wof:placetype":"venue"
},
  "geometry": {"coordinates":[-122.029188,37.315148],"type":"Point"}
}