{
  "type": "Feature",
  "properties": {
    "iso:country":"US",
    "sg:address":"2151 Michelson Dr Ste 100",
    "sg:city":"Irvine",
    "sg:classifiers":[
        {
            "category":"Shopping",
            "subcategory":"Music",
            "type":"Retail Goods"
        }
    ],
    "sg:phone":"+1 949 788 1470",
    "sg:postcode":"92612",
    "sg:province":"CA",
    "sg:tags":[
        "dvd's"
    ],
    "sg:website":"www.uniloc.com",
    "wof:name":"Uniloc",
    "wof:placetype":"venue"
},
  "geometry": {"coordinates":[-117.856949,33.677599],"type":"Point"}
}