{
  "type": "Feature",
  "properties": {
    "addr:full":"1083 Newpark Mall Newark CA 94560",
    "addr:housenumber":"1083",
    "addr:postcode":"94560",
    "addr:street":"Newpark Mall",
    "iso:country":"US",
    "sg:address":"1083 Newpark Mall",
    "sg:city":"Newark",
    "sg:classifiers":[
        {
            "category":"Shopping",
            "subcategory":"Clothing, Apparel, & Fashions",
            "type":"Retail Goods"
        }
    ],
    "sg:phone":"+1 510 494 9403",
    "sg:postcode":"94560",
    "sg:province":"CA",
    "wof:name":"Demo",
    "wof:placetype":"venue"
},
  "geometry": {"coordinates":[-122.00515,37.526154],"type":"Point"}
}