{
  "type": "Feature",
  "properties": {
    "iso:country":"US",
    "sg:address":"29435 Edgewood Rd",
    "sg:city":"San Juan Capistrano",
    "sg:classifiers":[
        {
            "category":"Manufacturing",
            "subcategory":"Jewelry",
            "type":"Manufacturing & Wholesale Goods"
        }
    ],
    "sg:phone":"+1 949 388 8149",
    "sg:postcode":"92675",
    "sg:province":"CA",
    "sg:tags":[
        "precious",
        "metal",
        "mfg"
    ],
    "wof:name":"K LI",
    "wof:placetype":"venue"
},
  "geometry": {"coordinates":[-117.669916,33.535541],"type":"Point"}
}