{
  "type": "Feature",
  "properties": {
    "iso:country":"US",
    "sg:address":"555 The Shops at Mission Viejo Level 1",
    "sg:city":"Mission Viejo",
    "sg:classifiers":[
        {
            "category":"Personal",
            "subcategory":"Hair Removal",
            "type":"Services"
        }
    ],
    "sg:phone":"+1 815 931 4317",
    "sg:postcode":"92691",
    "sg:province":"CA",
    "wof:name":"Klassic Brow",
    "wof:placetype":"venue"
},
  "geometry": {"coordinates":[-117.66923,33.561406],"type":"Point"}
}