{
  "type": "Feature",
  "properties": {
    "iso:country":"US",
    "sg:address":"2727 E Vista Way",
    "sg:city":"Vista",
    "sg:classifiers":[
        {
            "category":"Home & Garden",
            "subcategory":"Garden Supply",
            "type":"Retail Goods"
        }
    ],
    "sg:phone":"+1 760 732 0767",
    "sg:postcode":"92084",
    "sg:province":"CA",
    "sg:tags":[
        "nurseryman"
    ],
    "wof:name":"Butterlfly Nurseries Inc",
    "wof:placetype":"venue"
},
  "geometry": {"coordinates":[-117.226349,33.243199],"type":"Point"}
}