{
  "type": "Feature",
  "properties": {
    "iso:country":"US",
    "sg:address":"130 E Hanford Armona Rd",
    "sg:city":"Lemoore",
    "sg:classifiers":[
        {
            "category":"Professional",
            "type":"Services"
        }
    ],
    "sg:phone":"+1 559 924 0109",
    "sg:postcode":"93245",
    "sg:province":"CA",
    "wof:name":"Botanica La Caridad",
    "wof:placetype":"venue"
},
  "geometry": {"coordinates":[-119.78004,36.313487],"type":"Point"}
}