{
  "type": "Feature",
  "properties": {
    "addr:full":"11231 Otsego St Ofc North Hollywood CA 91601",
    "addr:postcode":"11231;91601",
    "addr:street":"Otsego St",
    "iso:country":"US",
    "sg:address":"11231 Otsego St Ofc",
    "sg:city":"North Hollywood",
    "sg:classifiers":[
        {
            "category":"Real Estate",
            "subcategory":"Real Estate Operator",
            "type":"Services"
        }
    ],
    "sg:phone":"+1 818 762 6274",
    "sg:postcode":"91601",
    "sg:province":"CA",
    "sg:tags":[
        "apartment"
    ],
    "wof:name":"Las Casitas Apartments",
    "wof:placetype":"venue"
},
  "geometry": {"coordinates":[-118.37599899999999,34.162998],"type":"Point"}
}