{
  "type": "Feature",
  "properties": {
    "addr:full":"1447 6th St Santa Monica CA 90401",
    "addr:housenumber":"1447",
    "addr:postcode":"90401",
    "addr:street":"6Th St",
    "iso:country":"US",
    "sg:address":"1447 6th St",
    "sg:city":"Santa Monica",
    "sg:classifiers":[
        {
            "category":"Building & Trades",
            "subcategory":"Construction",
            "type":"Services"
        }
    ],
    "sg:phone":"+1 310 458 4025",
    "sg:postcode":"90401",
    "sg:province":"CA",
    "sg:tags":[
        "contractor"
    ],
    "wof:name":"Welsh Dragon Construction",
    "wof:placetype":"venue"
},
  "geometry": {"coordinates":[-118.492245,34.017293],"type":"Point"}
}