{
  "type": "Feature",
  "properties": {
    "iso:country":"US",
    "sg:address":"14241 Pacific Ave",
    "sg:city":"Westminster",
    "sg:classifiers":[
        {
            "category":"Professional",
            "type":"Services"
        }
    ],
    "sg:phone":"+1 714 890 0290",
    "sg:postcode":"92683",
    "sg:province":"CA",
    "wof:name":"HI Fidelity Quartet",
    "wof:placetype":"venue"
},
  "geometry": {"coordinates":[-117.991955,33.75507],"type":"Point"}
}