{
  "type": "Feature",
  "properties": {
    "iso:country":"US",
    "sg:address":"18310 Ricardo Ave",
    "sg:city":"Hayward",
    "sg:classifiers":[
        {
            "category":"Restaurant",
            "type":"Food & Drink"
        }
    ],
    "sg:phone":"+1 510 271 6753",
    "sg:postcode":"94541",
    "sg:province":"CA",
    "sg:tags":[
        "caterer"
    ],
    "wof:name":"Santa Fe Special Events",
    "wof:placetype":"venue"
},
  "geometry": {"coordinates":[-122.115784,37.674549],"type":"Point"}
}