{
  "type": "Feature",
  "properties": {
    "addr:full":"2116 Main St Julian CA 92036",
    "addr:housenumber":"2116",
    "addr:postcode":"92036",
    "addr:street":"Main St",
    "iso:country":"US",
    "sg:address":"2116 Main St",
    "sg:city":"Julian",
    "sg:classifiers":[
        {
            "category":"Shopping",
            "subcategory":"Hobbies, Toys, & Games",
            "type":"Retail Goods"
        }
    ],
    "sg:phone":"+1 760 765 2262",
    "sg:postcode":"92036",
    "sg:province":"CA",
    "wof:name":"Julian's Toy Chest",
    "wof:placetype":"venue"
},
  "geometry": {"coordinates":[-116.601573,33.078084],"type":"Point"}
}