{
  "type": "Feature",
  "properties": {
    "iso:country":"US",
    "sg:address":"10666 Riverside Dr",
    "sg:city":"North Hollywood",
    "sg:classifiers":[
        {
            "category":"Sports & Exercise",
            "subcategory":"Gym",
            "type":"Entertainment"
        }
    ],
    "sg:phone":"+1 818 763 1726",
    "sg:postcode":"91602",
    "sg:province":"CA",
    "wof:name":"Push Private Fitness",
    "wof:placetype":"venue"
},
  "geometry": {"coordinates":[-118.364998,34.152401],"type":"Point"}
}