{
  "type": "Feature",
  "properties": {
    "addr:full":"41078 Big Bear Blvd Big Bear Lake CA 92315",
    "addr:housenumber":"41078",
    "addr:postcode":"92315",
    "addr:street":"Big Bear Blvd",
    "iso:country":"US",
    "sg:address":"41078 Big Bear Blvd",
    "sg:city":"Big Bear Lake",
    "sg:classifiers":[
        {
            "category":"Food & Beverages",
            "subcategory":"Groceries & Convenience Stores",
            "type":"Retail Goods"
        }
    ],
    "sg:phone":"+1 909 866 9492",
    "sg:postcode":"92315",
    "sg:province":"CA",
    "sg:tags":[
        "market"
    ],
    "wof:name":"Forest Farms Farmers Market",
    "wof:placetype":"venue"
},
  "geometry": {"coordinates":[-116.90606,34.243693],"type":"Point"}
}