{
  "type": "Feature",
  "properties": {
    "iso:country":"US",
    "sg:address":"5490 Wisteria Dr",
    "sg:city":"Pollock Pines",
    "sg:classifiers":[
        {
            "category":"Professional",
            "subcategory":"Business Services",
            "type":"Services"
        }
    ],
    "sg:phone":"+1 530 644 3295",
    "sg:postcode":"95726",
    "sg:province":"CA",
    "sg:tags":[
        "drafting"
    ],
    "wof:name":"Discovery Detailing",
    "wof:placetype":"venue"
},
  "geometry": {"coordinates":[-120.614521,38.705784],"type":"Point"}
}