{
  "type": "Feature",
  "properties": {
    "addr:full":"360 Langton St San Francisco CA 94103",
    "addr:housenumber":"360",
    "addr:postcode":"94103",
    "addr:street":"Langton St",
    "iso:country":"US",
    "sg:address":"360 Langton St",
    "sg:city":"San Francisco",
    "sg:classifiers":[
        {
            "category":"Retail",
            "subcategory":"Laundry & Dry Cleaning",
            "type":"Services"
        }
    ],
    "sg:phone":"+1 415 861 8003",
    "sg:postcode":"94103",
    "sg:province":"CA",
    "sg:tags":[
        "cleaners",
        "rug",
        "carpet"
    ],
    "wof:name":"Dry Fast Superior Carpet",
    "wof:placetype":"venue"
},
  "geometry": {"coordinates":[-122.404961,37.773574],"type":"Point"}
}