{
  "type": "Feature",
  "properties": {
    "addr:full":"8 Palm Avenue Apt 2 San Francisco CA 94118",
    "addr:housenumber":"8;2",
    "addr:postcode":"94118",
    "addr:street":"Palm Avenue Apt",
    "iso:country":"US",
    "sg:address":"8 Palm Avenue Apt 2",
    "sg:city":"San Francisco",
    "sg:classifiers":[
        {
            "category":"Building & Trades",
            "subcategory":"Construction",
            "type":"Services"
        }
    ],
    "sg:phone":"+1 415 752 4687",
    "sg:postcode":"94118",
    "sg:province":"CA",
    "sg:tags":[
        "painter"
    ],
    "wof:name":"Mvp Painting",
    "wof:placetype":"venue"
},
  "geometry": {"coordinates":[-122.458,37.785702],"type":"Point"}
}