{
  "type": "Feature",
  "properties": {
    "iso:country":"US",
    "sg:address":"1079 S Green Valley Rd",
    "sg:city":"Watsonville",
    "sg:classifiers":[
        {
            "category":"Shopping",
            "subcategory":"Used Merchandise",
            "type":"Retail Goods"
        }
    ],
    "sg:phone":"+1 831 724 1692",
    "sg:postcode":"95076",
    "sg:province":"CA",
    "sg:tags":[
        "shop",
        "thrift"
    ],
    "wof:name":"Salvation Army Thrift Store",
    "wof:placetype":"venue"
},
  "geometry": {"coordinates":[-121.784424,36.917194],"type":"Point"}
}