{
  "type": "Feature",
  "properties": {
    "addr:full":"525 W Grand Ave Escondido CA 92025",
    "addr:housenumber":"525",
    "addr:postcode":"92025",
    "addr:street":"W Grand Ave",
    "iso:country":"US",
    "sg:address":"525 W Grand Ave",
    "sg:city":"Escondido",
    "sg:classifiers":[
        {
            "category":"Food & Beverages",
            "subcategory":"Groceries & Convenience Stores",
            "type":"Retail Goods"
        }
    ],
    "sg:phone":"+1 760 746 3693",
    "sg:postcode":"92025",
    "sg:province":"CA",
    "sg:tags":[
        "grocer"
    ],
    "wof:name":"Latino Meat Market",
    "wof:placetype":"venue"
},
  "geometry": {"coordinates":[-117.087915,33.118352],"type":"Point"}
}