{
  "type": "Feature",
  "properties": {
    "iso:country":"US",
    "sg:address":"1951 S Vermont Avenue",
    "sg:city":"Los Angeles",
    "sg:classifiers":[
        {
            "category":"Retail",
            "subcategory":"Event Space",
            "type":"Services"
        },
        {
            "category":"Bars & Pubs",
            "subcategory":"Nightclub",
            "type":"Food & Drink"
        }
    ],
    "sg:phone":"+1 323 734 0674",
    "sg:postcode":"90007",
    "sg:province":"CA",
    "sg:tags":[
        "venue",
        "nightlife"
    ],
    "wof:name":"Lazaro's Ballroom & Cocktail Lounge",
    "wof:placetype":"venue"
},
  "geometry": {"coordinates":[-118.291432,34.038754],"type":"Point"}
}