{
  "type": "Feature",
  "properties": {
    "addr:full":"1190 Via Verde San Dimas CA 91773",
    "addr:housenumber":"1190",
    "addr:postcode":"91773",
    "addr:street":"Via Verde",
    "iso:country":"US",
    "sg:address":"1190 Via Verde",
    "sg:city":"San Dimas",
    "sg:classifiers":[
        {
            "category":"Social Services",
            "subcategory":"Child Care",
            "type":"Services"
        }
    ],
    "sg:phone":"+1 909 599 2224",
    "sg:postcode":"91773",
    "sg:province":"CA",
    "wof:name":"Children's Montessori Ctr",
    "wof:placetype":"venue"
},
  "geometry": {"coordinates":[-117.829408,34.073505],"type":"Point"}
}