{
  "type": "Feature",
  "properties": {
    "iso:country":"US",
    "sg:address":"7341 Excalibur Cir",
    "sg:city":"Stockton",
    "sg:classifiers":[
        {
            "category":"Home & Garden",
            "subcategory":"Building Materials",
            "type":"Retail Goods"
        },
        {
            "category":"Professional",
            "subcategory":"Printing & Photocopies",
            "type":"Services"
        }
    ],
    "sg:phone":"+1 209 373 3013",
    "sg:postcode":"95210",
    "sg:province":"CA",
    "sg:tags":[
        "garage",
        "opener",
        "door",
        "door-overhead",
        "type"
    ],
    "wof:name":"Infiniti Garage Doors Inc",
    "wof:placetype":"venue"
},
  "geometry": {"coordinates":[-121.285005,38.018661],"type":"Point"}
}