{
  "type": "Feature",
  "properties": {
    "iso:country":"US",
    "sg:address":"19343 Statton Acres Rd",
    "sg:city":"Lakehead",
    "sg:classifiers":[
        {
            "category":"Building & Trades",
            "subcategory":"Construction",
            "type":"Services"
        }
    ],
    "sg:phone":"+1 530 238 2611",
    "sg:postcode":"96051",
    "sg:province":"CA",
    "sg:tags":[
        "resurfacing",
        "laying",
        "refinishing",
        "floor"
    ],
    "wof:name":"Dwinell Flooring",
    "wof:placetype":"venue"
},
  "geometry": {"coordinates":[-122.33325600000001,40.816405],"type":"Point"}
}