{
  "type": "Feature",
  "properties": {
    "addr:full":"600 E Green St Pasadena CA 91101",
    "addr:housenumber":"600",
    "addr:postcode":"91101",
    "addr:street":"E Green St",
    "iso:country":"US",
    "sg:address":"600 E Green St",
    "sg:city":"Pasadena",
    "sg:classifiers":[
        {
            "category":"Professional",
            "subcategory":"Lawyer & Legal Services",
            "type":"Services"
        }
    ],
    "sg:phone":"+1 626 793 3863",
    "sg:postcode":"91101",
    "sg:province":"CA",
    "wof:name":"Harker Robert O Atty",
    "wof:placetype":"venue"
},
  "geometry": {"coordinates":[-118.138367,34.144569],"type":"Point"}
}