{
  "type": "Feature",
  "properties": {
    "iso:country":"US",
    "sg:address":"1201 Grass Valley Hwy",
    "sg:city":"Auburn",
    "sg:classifiers":[
        {
            "category":"Banks & Credit Unions",
            "subcategory":"Bank",
            "type":"Services"
        }
    ],
    "sg:phone":"+1 530 887 5050",
    "sg:postcode":"95603",
    "sg:province":"CA",
    "sg:tags":[
        "loan",
        "real estate"
    ],
    "wof:name":"Mortgage Co Of America",
    "wof:placetype":"venue"
},
  "geometry": {"coordinates":[-121.08356999999999,38.923432],"type":"Point"}
}