{
  "type": "Feature",
  "properties": {
    "iso:country":"US",
    "sg:address":"212 Fountain Ave",
    "sg:city":"Pacific Grove",
    "sg:classifiers":[
        {
            "category":"Building & Trades",
            "subcategory":"Electrical",
            "type":"Services"
        }
    ],
    "sg:phone":"+1 831 373 3348",
    "sg:postcode":"93950",
    "sg:province":"CA",
    "sg:tags":[
        "electrical",
        "contractor"
    ],
    "wof:name":"Pacific Electric",
    "wof:placetype":"venue"
},
  "geometry": {"coordinates":[-121.917147,36.61962],"type":"Point"}
}