{
  "type": "Feature",
  "properties": {
    "addr:full":"3551 Truxel Rd Sacramento CA 95834",
    "addr:housenumber":"3551",
    "addr:postcode":"95834",
    "addr:street":"Truxel Rd",
    "iso:country":"US",
    "sg:address":"3551 Truxel Rd",
    "sg:city":"Sacramento",
    "sg:classifiers":[
        {
            "category":"Restaurant",
            "type":"Food & Drink"
        }
    ],
    "sg:phone":"+1 916 419 8318",
    "sg:postcode":"95834",
    "sg:province":"CA",
    "sg:tags":[
        "mongolian",
        "chinese"
    ],
    "wof:name":"Sizzling Fresh Mongolian BBQ",
    "wof:placetype":"venue"
},
  "geometry": {"coordinates":[-121.50299800000001,38.636501],"type":"Point"}
}