{
  "type": "Feature",
  "properties": {
    "addr:full":"4275 N University Pkwy San Bernardino CA 92407",
    "addr:housenumber":"4275",
    "addr:postcode":"92407",
    "addr:street":"N University Pkwy",
    "iso:country":"US",
    "sg:address":"4275 N University Pkwy",
    "sg:city":"San Bernardino",
    "sg:classifiers":[
        {
            "category":"Coffee & Tea",
            "type":"Food & Drink"
        }
    ],
    "sg:phone":"+1 909 887 2256",
    "sg:postcode":"92407",
    "sg:province":"CA",
    "sg:website":"www.starbucks.com",
    "wof:name":"Starbucks",
    "wof:placetype":"venue"
},
  "geometry": {"coordinates":[-117.33150500000001,34.16713],"type":"Point"}
}