{
  "type": "Feature",
  "properties": {
    "iso:country":"US",
    "sg:address":"4200 Latham St",
    "sg:city":"Riverside",
    "sg:classifiers":[
        {
            "category":"Government",
            "subcategory":"Court House",
            "type":"Public Place"
        }
    ],
    "sg:phone":"+1 951 782 4313",
    "sg:postcode":"92501",
    "sg:province":"CA",
    "sg:tags":[
        "enforcement",
        "narcotic"
    ],
    "wof:name":"Bureau Narcotics Enforcement",
    "wof:placetype":"venue"
},
  "geometry": {"coordinates":[-117.372218,34.00156],"type":"Point"}
}