{
  "type": "Feature",
  "properties": {
    "iso:country":"US",
    "sg:address":"26 Executive Park",
    "sg:city":"Irvine",
    "sg:classifiers":[
        {
            "category":"Building & Trades",
            "subcategory":"Construction",
            "type":"Services"
        }
    ],
    "sg:phone":"+1 949 852 9411",
    "sg:postcode":"92614",
    "sg:province":"CA",
    "sg:tags":[
        "house",
        "builder",
        "home"
    ],
    "wof:name":"Greystone Homes Inc",
    "wof:placetype":"venue"
},
  "geometry": {"coordinates":[-117.858121,33.683976],"type":"Point"}
}