{
  "type": "Feature",
  "properties": {
    "addr:full":"21524 Ventura Blvd Woodland Hills CA 91364",
    "addr:housenumber":"21524",
    "addr:postcode":"91364",
    "addr:street":"Ventura Blvd",
    "iso:country":"US",
    "sg:address":"21524 Ventura Blvd",
    "sg:city":"Woodland Hills",
    "sg:classifiers":[
        {
            "category":"Personal",
            "subcategory":"Massage",
            "type":"Services"
        },
        {
            "category":"Personal",
            "subcategory":"Beauty Salon",
            "type":"Services"
        },
        {
            "category":"Personal",
            "subcategory":"Skin Care",
            "type":"Services"
        }
    ],
    "sg:phone":"+1 818 887 3627",
    "sg:postcode":"91364",
    "sg:province":"CA",
    "sg:tags":[
        "hair"
    ],
    "sg:website":"www.bigoudi-intl.com",
    "wof:name":"Bigoudi International Salon",
    "wof:placetype":"venue"
},
  "geometry": {"coordinates":[-118.599287,34.168182],"type":"Point"}
}