{
  "type": "Feature",
  "properties": {
    "addr:full":"15868 Monterey St Morgan Hill CA 95037",
    "addr:housenumber":"15868",
    "addr:postcode":"95037",
    "addr:street":"Monterey St",
    "iso:country":"US",
    "sg:address":"15868 Monterey St",
    "sg:city":"Morgan Hill",
    "sg:classifiers":[
        {
            "category":"Professional",
            "subcategory":"Accounting & Tax Preparation",
            "type":"Services"
        }
    ],
    "sg:phone":"+1 408 779 4513",
    "sg:postcode":"95037",
    "sg:province":"CA",
    "sg:tags":[
        "return"
    ],
    "wof:name":"H & R Block",
    "wof:placetype":"venue"
},
  "geometry": {"coordinates":[-121.641046,37.111284],"type":"Point"}
}