{
  "type": "Feature",
  "properties": {
    "iso:country":"US",
    "sg:address":"525 E Cotati Ave",
    "sg:city":"Cotati",
    "sg:classifiers":[
        {
            "category":"Health Services",
            "subcategory":"Health Practitioner",
            "type":"Services"
        }
    ],
    "sg:phone":"+1 707 795 6338",
    "sg:postcode":"94931",
    "sg:province":"CA",
    "sg:tags":[
        "acupuncture"
    ],
    "wof:name":"Healing Lotus Yoga & Wellness",
    "wof:placetype":"venue"
},
  "geometry": {"coordinates":[-122.698495,38.329079],"type":"Point"}
}