{
  "type": "Feature",
  "properties": {
    "addr:full":"586 N 1st St San Jose CA 95112",
    "addr:housenumber":"586",
    "addr:postcode":"95112",
    "addr:street":"N 1St St",
    "iso:country":"US",
    "sg:address":"586 N 1st St",
    "sg:city":"San Jose",
    "sg:classifiers":[
        {
            "category":"Professional",
            "subcategory":"Accounting & Tax Preparation",
            "type":"Services"
        }
    ],
    "sg:phone":"+1 408 279 5843",
    "sg:postcode":"95112",
    "sg:province":"CA",
    "sg:tags":[
        "return",
        "filing"
    ],
    "wof:name":"Champion Tax & Accounting Svc",
    "wof:placetype":"venue"
},
  "geometry": {"coordinates":[-121.898427,37.346827],"type":"Point"}
}