{
  "type": "Feature",
  "properties": {
    "iso:country":"US",
    "sg:address":"76 Belvedere St",
    "sg:city":"San Rafael",
    "sg:classifiers":[
        {
            "category":"Food & Beverages",
            "subcategory":"Specialty",
            "type":"Retail Goods"
        }
    ],
    "sg:phone":"+1 415 482 6007",
    "sg:postcode":"94901",
    "sg:province":"CA",
    "sg:tags":[
        "health",
        "diet"
    ],
    "wof:name":"Productos De Control De Peso",
    "wof:placetype":"venue"
},
  "geometry": {"coordinates":[-122.504956,37.963006],"type":"Point"}
}