{
  "type": "Feature",
  "properties": {
    "addr:full":"5435 Driftwood St Oxnard CA 93035",
    "addr:housenumber":"5435",
    "addr:postcode":"93035",
    "addr:street":"Driftwood St",
    "iso:country":"US",
    "sg:address":"5435 Driftwood St",
    "sg:city":"Oxnard",
    "sg:classifiers":[
        {
            "category":"Professional",
            "subcategory":"Management & Consulting",
            "type":"Services"
        }
    ],
    "sg:phone":"+1 805 985 0857",
    "sg:postcode":"93035",
    "sg:province":"CA",
    "sg:tags":[
        "consultant",
        "business"
    ],
    "wof:name":"Joyce Jones & Assoc",
    "wof:placetype":"venue"
},
  "geometry": {"coordinates":[-119.243781,34.195628],"type":"Point"}
}