{
  "type": "Feature",
  "properties": {
    "addr:full":"1775 Broadway Suite 8 San Francisco CA 94109",
    "addr:housenumber":"1775",
    "addr:postcode":"94109",
    "addr:street":"Broadway Suite 8",
    "iso:country":"US",
    "sg:address":"1775 Broadway Suite 8",
    "sg:city":"San Francisco",
    "sg:classifiers":[
        {
            "category":"Building & Trades",
            "subcategory":"Construction",
            "type":"Services"
        },
        {
            "category":"Real Estate",
            "subcategory":"Architect",
            "type":"Services"
        }
    ],
    "sg:phone":"+1 415 265 2201",
    "sg:postcode":"94109",
    "sg:province":"CA",
    "sg:tags":[
        "contractor"
    ],
    "sg:website":"www.evergreencali.com",
    "wof:name":"Evergreen Construction & Consulting, Inc.",
    "wof:placetype":"venue"
},
  "geometry": {"coordinates":[-122.41409899999999,37.796925],"type":"Point"}
}