{
  "type": "Feature",
  "properties": {
    "iso:country":"US",
    "sg:address":"664 Alameda St",
    "sg:city":"Altadena",
    "sg:classifiers":[
        {
            "category":"Personal",
            "subcategory":"Beauty Salon",
            "type":"Services"
        }
    ],
    "sg:phone":"+1 626 398 7000",
    "sg:postcode":"91001",
    "sg:province":"CA",
    "wof:name":"James Stephen Salon",
    "wof:placetype":"venue"
},
  "geometry": {"coordinates":[-118.136706,34.183181],"type":"Point"}
}