{
  "type": "Feature",
  "properties": {
    "iso:country":"US",
    "sg:address":"5625 State Farm Dr",
    "sg:city":"Rohnert Park",
    "sg:classifiers":[
        {
            "category":"Retail",
            "subcategory":"Repair Shop",
            "type":"Services"
        }
    ],
    "sg:phone":"+1 707 584 3899",
    "sg:postcode":"94928",
    "sg:province":"CA",
    "sg:tags":[
        "refinishing",
        "furniture"
    ],
    "wof:name":"Final Touch Finishing",
    "wof:placetype":"venue"
},
  "geometry": {"coordinates":[-122.70896999999999,38.356099],"type":"Point"}
}