{
  "type": "Feature",
  "properties": {
    "addr:full":"451 W Lambert Rd Ste 208 Brea CA 92821",
    "addr:housenumber":"451",
    "addr:postcode":"92821",
    "addr:street":"W Lambert Rd Ste 208",
    "iso:country":"US",
    "sg:address":"451 W Lambert Rd Ste 208",
    "sg:city":"Brea",
    "sg:classifiers":[
        {
            "category":"Wholesale",
            "subcategory":"Construction Materials",
            "type":"Manufacturing & Wholesale Goods"
        },
        {
            "category":"Home & Garden",
            "subcategory":"Building Materials",
            "type":"Retail Goods"
        }
    ],
    "sg:phone":"+1 714 990 9988",
    "sg:postcode":"92821",
    "sg:province":"CA",
    "sg:tags":[
        "windows-wholesale",
        "window",
        "manufacturer"
    ],
    "sg:website":"http://www.preferredwindow.com",
    "wof:name":"Intelligent Marketing Group",
    "wof:placetype":"venue"
},
  "geometry": {"coordinates":[-117.901386,33.92476],"type":"Point"}
}