{
  "type": "Feature",
  "properties": {
    "addr:full":"1307 Travis Blvd Fairfield CA 94533",
    "addr:housenumber":"1307",
    "addr:postcode":"94533",
    "addr:street":"Travis Blvd",
    "iso:country":"US",
    "sg:address":"1307 Travis Blvd",
    "sg:city":"Fairfield",
    "sg:classifiers":[
        {
            "category":"Banks & Credit Unions",
            "subcategory":"Bank",
            "type":"Services"
        }
    ],
    "sg:phone":"+1 707 422 7283",
    "sg:postcode":"94533",
    "sg:province":"CA",
    "wof:name":"US Bank",
    "wof:placetype":"venue"
},
  "geometry": {"coordinates":[-122.04937,38.257985],"type":"Point"}
}