{
  "type": "Feature",
  "properties": {
    "addr:full":"23935 Ventura Blvd Calabasas CA 91302",
    "addr:housenumber":"23935",
    "addr:postcode":"91302",
    "addr:street":"Ventura Blvd",
    "iso:country":"US",
    "sg:address":"23935 Ventura Blvd",
    "sg:city":"Calabasas",
    "sg:classifiers":[
        {
            "category":"Professional",
            "subcategory":"Advertising",
            "type":"Services"
        }
    ],
    "sg:phone":"+1 818 591 9010",
    "sg:postcode":"91302",
    "sg:province":"CA",
    "sg:tags":[
        "advertising-promotional",
        "product"
    ],
    "wof:name":"Direct Promotions",
    "wof:placetype":"venue"
},
  "geometry": {"coordinates":[-118.648982,34.155012],"type":"Point"}
}