{
  "type": "Feature",
  "properties": {
    "iso:country":"US",
    "sg:address":"1260 Lake Blvd",
    "sg:city":"Davis",
    "sg:classifiers":[
        {
            "category":"Personal",
            "subcategory":"Beauty Salon",
            "type":"Services"
        }
    ],
    "sg:phone":"+1 530 757 7308",
    "sg:postcode":"95616",
    "sg:province":"CA",
    "sg:tags":[
        "manicuring"
    ],
    "wof:name":"Modern Nails",
    "wof:placetype":"venue"
},
  "geometry": {"coordinates":[-121.78721,38.551193],"type":"Point"}
}