{
  "type": "Feature",
  "properties": {
    "addr:full":"10995 Gold Center Drive Rancho Cordova CA 95670",
    "addr:housenumber":"10995",
    "addr:postcode":"95670",
    "addr:street":"Gold Center Drive",
    "iso:country":"US",
    "sg:address":"10995 Gold Center Drive",
    "sg:city":"Rancho Cordova",
    "sg:classifiers":[
        {
            "category":"Banks & Credit Unions",
            "subcategory":"Bank",
            "type":"Services"
        }
    ],
    "sg:phone":"+1 916 852 1668",
    "sg:postcode":"95670",
    "sg:province":"CA",
    "wof:name":"Credit Union Direct Lending Corporation",
    "wof:placetype":"venue"
},
  "geometry": {"coordinates":[-121.282252,38.591134],"type":"Point"}
}