{
  "type": "Feature",
  "properties": {
    "addr:full":"45901 Sandia Creek Dr Temecula CA 92590",
    "addr:housenumber":"45901",
    "addr:postcode":"92590",
    "addr:street":"Sandia Creek Dr",
    "iso:country":"US",
    "sg:address":"45901 Sandia Creek Dr",
    "sg:city":"Temecula",
    "sg:classifiers":[
        {
            "category":"Professional",
            "subcategory":"Engineering",
            "type":"Services"
        }
    ],
    "sg:phone":"+1 951 699 2666",
    "sg:postcode":"92590",
    "sg:province":"CA",
    "sg:tags":[
        "engineer"
    ],
    "wof:name":"Structural Engineering",
    "wof:placetype":"venue"
},
  "geometry": {"coordinates":[-117.224582,33.477396],"type":"Point"}
}