{
  "type": "Feature",
  "properties": {
    "iso:country":"US",
    "sg:address":"683 West Maude Avenue",
    "sg:city":"Sunnyvale",
    "sg:classifiers":[
        {
            "category":"Manufacturing",
            "subcategory":"Electronics",
            "type":"Manufacturing & Wholesale Goods"
        }
    ],
    "sg:phone":"+1 408 530 2500",
    "sg:postcode":"94085",
    "sg:province":"CA",
    "sg:website":"http://www.aquestsystems.com/",
    "wof:name":"Aquest Systems",
    "wof:placetype":"venue"
},
  "geometry": {"coordinates":[-122.03491,37.391169],"type":"Point"}
}