{
  "type": "Feature",
  "properties": {
    "iso:country":"US",
    "sg:address":"740 Pendegast Cir",
    "sg:city":"Woodland",
    "sg:classifiers":[
        {
            "category":"Building & Trades",
            "subcategory":"Construction",
            "type":"Services"
        }
    ],
    "sg:phone":"+1 530 666 3275",
    "sg:postcode":"95695",
    "sg:province":"CA",
    "sg:tags":[
        "house",
        "architectural"
    ],
    "wof:name":"Starwood Construction",
    "wof:placetype":"venue"
},
  "geometry": {"coordinates":[-121.778347,38.67052],"type":"Point"}
}