{
  "type": "Feature",
  "properties": {
    "iso:country":"US",
    "sg:address":"841 San Bruno Ave W Ste 10",
    "sg:city":"San Bruno",
    "sg:classifiers":[
        {
            "category":"Health Services",
            "subcategory":"Health Practitioner",
            "type":"Services"
        }
    ],
    "sg:phone":"+1 650 588 0888",
    "sg:postcode":"94066",
    "sg:province":"CA",
    "sg:tags":[
        "acupuncture"
    ],
    "sg:website":"www.acuspawellness.com",
    "wof:name":"AcuSpa",
    "wof:placetype":"venue"
},
  "geometry": {"coordinates":[-122.418035,37.628204],"type":"Point"}
}