{
  "type": "Feature",
  "properties": {
    "iso:country":"US",
    "sg:address":"5353 Claremont Ave Ste 2B",
    "sg:city":"Oakland",
    "sg:classifiers":[
        {
            "category":"Banks & Credit Unions",
            "subcategory":"Financial Services",
            "type":"Services"
        }
    ],
    "sg:phone":"+1 510 450 9930",
    "sg:postcode":"94618",
    "sg:province":"CA",
    "sg:website":"www.fiducial.com",
    "wof:name":"FIducial Business Centers, Inc.",
    "wof:placetype":"venue"
},
  "geometry": {"coordinates":[-122.259877,37.840003],"type":"Point"}
}