{
  "type": "Feature",
  "properties": {
    "addr:full":"322 Princeton Ave Half Moon Bay CA 94019",
    "addr:housenumber":"322",
    "addr:postcode":"94019",
    "addr:street":"Princeton Ave",
    "iso:country":"US",
    "sg:address":"322 Princeton Ave",
    "sg:city":"Half Moon Bay",
    "sg:classifiers":[
        {
            "category":"Building & Trades",
            "subcategory":"Electrical",
            "type":"Services"
        }
    ],
    "sg:phone":"+1 650 728 2262",
    "sg:postcode":"94019",
    "sg:province":"CA",
    "sg:tags":[
        "electrical",
        "contractor"
    ],
    "wof:name":"Ingraham Electric",
    "wof:placetype":"venue"
},
  "geometry": {"coordinates":[-122.48784499999999,37.503983],"type":"Point"}
}