{
  "type": "Feature",
  "properties": {
    "addr:full":"14153 Garvey Ave Baldwin Park CA 91706",
    "addr:housenumber":"14153",
    "addr:postcode":"91706",
    "addr:street":"Garvey Ave",
    "iso:country":"US",
    "sg:address":"14153 Garvey Ave",
    "sg:city":"Baldwin Park",
    "sg:classifiers":[
        {
            "category":"Wholesale",
            "subcategory":"Durable Goods & Equipment",
            "type":"Manufacturing & Wholesale Goods"
        }
    ],
    "sg:phone":"+1 626 444 1867",
    "sg:postcode":"91706",
    "sg:province":"CA",
    "sg:tags":[
        "exporter"
    ],
    "sg:website":"www.americancampersandtrailers.com",
    "wof:name":"American Sales",
    "wof:placetype":"venue"
},
  "geometry": {"coordinates":[-117.967607,34.069729],"type":"Point"}
}