{
  "type": "Feature",
  "properties": {
    "addr:full":"5221 Hazelbrook Avenue Lakewood CA 90712",
    "addr:postcode":"5221;90712",
    "addr:street":"Hazelbrook Avenue",
    "iso:country":"US",
    "sg:address":"5221 Hazelbrook Avenue",
    "sg:city":"Lakewood",
    "sg:classifiers":[
        {
            "category":"Shopping",
            "subcategory":"Books",
            "type":"Retail Goods"
        }
    ],
    "sg:phone":"+1 562 531 9181",
    "sg:postcode":"90712",
    "sg:province":"CA",
    "sg:tags":[
        "bookstore"
    ],
    "sg:website":"www.borders.com",
    "wof:name":"Borders Express",
    "wof:placetype":"venue"
},
  "geometry": {"coordinates":[-118.139814,33.851588],"type":"Point"}
}