{
  "type": "Feature",
  "properties": {
    "iso:country":"US",
    "sg:address":"1101 Irving St",
    "sg:city":"San Francisco",
    "sg:classifiers":[
        {
            "category":"Retail",
            "subcategory":"Laundry & Dry Cleaning",
            "type":"Services"
        }
    ],
    "sg:postcode":"94122",
    "sg:province":"CA",
    "wof:name":"Coiniop Washidry",
    "wof:placetype":"venue"
},
  "geometry": {"coordinates":[-122.469672,37.76394],"type":"Point"}
}