{
  "type": "Feature",
  "properties": {
    "addr:full":"1615 Sweetwater Rd National City CA 91950",
    "addr:housenumber":"1615",
    "addr:postcode":"91950",
    "addr:street":"Sweetwater Rd",
    "iso:country":"US",
    "sg:address":"1615 Sweetwater Rd",
    "sg:city":"National City",
    "sg:classifiers":[
        {
            "category":"Restaurant",
            "type":"Food & Drink"
        }
    ],
    "sg:postcode":"91950",
    "sg:province":"CA",
    "sg:tags":[
        "filipino"
    ],
    "wof:name":"Ben's 1615",
    "wof:placetype":"venue"
},
  "geometry": {"coordinates":[-117.08311999999999,32.661695],"type":"Point"}
}