{
  "type": "Feature",
  "properties": {
    "iso:country":"US",
    "sg:address":"2420 Covelite Way",
    "sg:city":"Antioch",
    "sg:classifiers":[
        {
            "category":"Shopping",
            "subcategory":"Computers & Home Electronics",
            "type":"Retail Goods"
        }
    ],
    "sg:phone":"+1 925 777 9331",
    "sg:postcode":"94531",
    "sg:province":"CA",
    "sg:tags":[
        "equipment",
        "dealer"
    ],
    "wof:name":"B & G Enterprises",
    "wof:placetype":"venue"
},
  "geometry": {"coordinates":[-121.780863,37.978508],"type":"Point"}
}