{
  "type": "Feature",
  "properties": {
    "iso:country":"US",
    "sg:address":"713 W Duarte Rd Ste B",
    "sg:city":"Arcadia",
    "sg:classifiers":[
        {
            "category":"Personal",
            "subcategory":"Beauty Salon",
            "type":"Services"
        }
    ],
    "sg:phone":"+1 626 446 6882",
    "sg:postcode":"91007",
    "sg:province":"CA",
    "sg:tags":[
        "hair"
    ],
    "wof:name":"D Two Hair Salon",
    "wof:placetype":"venue"
},
  "geometry": {"coordinates":[-118.055669,34.125958],"type":"Point"}
}