{
  "type": "Feature",
  "properties": {
    "iso:country":"US",
    "sg:address":"1442 E Lincoln Ave",
    "sg:city":"Orange",
    "sg:classifiers":[
        {
            "category":"Communications",
            "subcategory":"Film & Video Production",
            "type":"Services"
        }
    ],
    "sg:phone":"+1 714 685 9600",
    "sg:postcode":"92865",
    "sg:province":"CA",
    "sg:tags":[
        "tv",
        "radio",
        "services-commercial",
        "companies-film"
    ],
    "sg:website":"http://www.impvideo.com",
    "wof:name":"Innovative Media Productions",
    "wof:placetype":"venue"
},
  "geometry": {"coordinates":[-117.83902999999999,33.835017],"type":"Point"}
}