{
  "type": "Feature",
  "properties": {
    "iso:country":"US",
    "sg:address":"1435 Koll Cir",
    "sg:city":"San Jose",
    "sg:classifiers":[
        {
            "category":"Utilities",
            "subcategory":"Telephone",
            "type":"Services"
        }
    ],
    "sg:phone":"+1 408 453 4064",
    "sg:postcode":"95112",
    "sg:province":"CA",
    "sg:tags":[
        "telecommunication"
    ],
    "wof:name":"Netdirect Communications Inc",
    "wof:placetype":"venue"
},
  "geometry": {"coordinates":[-121.906514,37.365914],"type":"Point"}
}