{
  "type": "Feature",
  "properties": {
    "addr:full":"3303 Dewey Ct Stockton CA 95212",
    "addr:housenumber":"3303",
    "addr:postcode":"95212",
    "addr:street":"Dewey Ct",
    "iso:country":"US",
    "sg:address":"3303 Dewey Ct",
    "sg:city":"Stockton",
    "sg:classifiers":[
        {
            "category":"Shopping",
            "subcategory":"Clothing, Apparel, & Fashions",
            "type":"Retail Goods"
        }
    ],
    "sg:phone":"+1 209 955 1870",
    "sg:postcode":"95212",
    "sg:province":"CA",
    "sg:tags":[
        "baby",
        "accessory"
    ],
    "wof:name":"Parrilla Etc",
    "wof:placetype":"venue"
},
  "geometry": {"coordinates":[-121.27152599999999,38.032697],"type":"Point"}
}