{
  "type": "Feature",
  "properties": {
    "addr:full":"1782 Church St San Francisco CA 94131",
    "addr:housenumber":"1782",
    "addr:postcode":"94131",
    "addr:street":"Church St",
    "iso:country":"US",
    "sg:address":"1782 Church St",
    "sg:city":"San Francisco",
    "sg:classifiers":[
        {
            "category":"Health Services",
            "subcategory":"Clinic",
            "type":"Services"
        }
    ],
    "sg:phone":"+1 415 648 2644",
    "sg:postcode":"94131",
    "sg:province":"CA",
    "sg:tags":[
        "counseling",
        "mental"
    ],
    "sg:website":"www.integralcounselingcenter.org",
    "wof:name":"Integral Counseling Center",
    "wof:placetype":"venue"
},
  "geometry": {"coordinates":[-122.42659399999999,37.742408],"type":"Point"}
}