{
  "type": "Feature",
  "properties": {
    "iso:country":"US",
    "sg:address":"515 L St",
    "sg:city":"Sacramento",
    "sg:classifiers":[
        {
            "category":"Shopping",
            "subcategory":"Hobbies, Toys, & Games",
            "type":"Retail Goods"
        }
    ],
    "sg:phone":"+1 916 441 3272",
    "sg:postcode":"95814",
    "sg:province":"CA",
    "sg:tags":[
        "supply"
    ],
    "wof:name":"Puzzled",
    "wof:placetype":"venue"
},
  "geometry": {"coordinates":[-121.49983400000001,38.579638],"type":"Point"}
}