{
  "type": "Feature",
  "properties": {
    "addr:full":"365 Plz Central Los Altos CA 94022",
    "addr:housenumber":"365",
    "addr:postcode":"94022",
    "addr:street":"Plz",
    "iso:country":"US",
    "sg:address":"365 Plz Central",
    "sg:city":"Los Altos",
    "sg:classifiers":[
        {
            "category":"Personal",
            "subcategory":"Barber",
            "type":"Services"
        }
    ],
    "sg:phone":"+1 650 947 4944",
    "sg:postcode":"94022",
    "sg:province":"CA",
    "wof:name":"Al's Barber Shop",
    "wof:placetype":"venue"
},
  "geometry": {"coordinates":[-122.117499,37.378281],"type":"Point"}
}