{
  "type": "Feature",
  "properties": {
    "iso:country":"US",
    "sg:address":"1350 E Slauson Ave",
    "sg:city":"Los Angeles",
    "sg:classifiers":[
        {
            "category":"Home & Garden",
            "subcategory":"Furniture",
            "type":"Retail Goods"
        }
    ],
    "sg:phone":"+1 323 588 0311",
    "sg:postcode":"90011",
    "sg:province":"CA",
    "sg:tags":[
        "mattress"
    ],
    "wof:name":"L A Furniture & Mattress",
    "wof:placetype":"venue"
},
  "geometry": {"coordinates":[-118.248658,33.98925],"type":"Point"}
}