{
  "type": "Feature",
  "properties": {
    "iso:country":"US",
    "sg:address":"2288 E Main St",
    "sg:city":"Quincy",
    "sg:classifiers":[
        {
            "category":"Personal",
            "type":"Services"
        }
    ],
    "sg:phone":"+1 530 283 9801",
    "sg:postcode":"95971",
    "sg:province":"CA",
    "sg:tags":[
        "therapist",
        "massage"
    ],
    "wof:name":"Native Touch Massage & Body",
    "wof:placetype":"venue"
},
  "geometry": {"coordinates":[-120.895477,39.933741],"type":"Point"}
}