{
  "type": "Feature",
  "properties": {
    "addr:full":"400 Citadel Dr Los Angeles CA 90040",
    "addr:housenumber":"400",
    "addr:postcode":"90040",
    "addr:street":"Citadel Dr",
    "iso:country":"US",
    "sg:address":"400 Citadel Dr",
    "sg:city":"Los Angeles",
    "sg:classifiers":[
        {
            "category":"Real Estate",
            "subcategory":"Real Estate Agent",
            "type":"Services"
        }
    ],
    "sg:phone":"+1 323 201 3600",
    "sg:postcode":"90040",
    "sg:province":"CA",
    "wof:name":"NAI Capital Commercial",
    "wof:placetype":"venue"
},
  "geometry": {"coordinates":[-118.151849,34.005222],"type":"Point"}
}