{
  "type": "Feature",
  "properties": {
    "iso:country":"US",
    "sg:address":"168 N Brent St",
    "sg:city":"Ventura",
    "sg:classifiers":[
        {
            "category":"Health Services",
            "subcategory":"Doctor",
            "type":"Services"
        }
    ],
    "sg:phone":"+1 805 653 0101",
    "sg:postcode":"93003",
    "sg:province":"CA",
    "sg:tags":[
        "physician",
        "surgeon",
        "surgeons",
        "cardiology"
    ],
    "sg:website":"http://www.cardiacadvantage.com",
    "wof:name":"Lee Andrew C MD",
    "wof:placetype":"venue"
},
  "geometry": {"coordinates":[-119.25721,34.274212],"type":"Point"}
}