{
  "type": "Feature",
  "properties": {
    "addr:full":"1920 W Princeton Ave Visalia CA 93277",
    "addr:housenumber":"1920",
    "addr:postcode":"93277",
    "addr:street":"W Princeton Ave",
    "iso:country":"US",
    "sg:address":"1920 W Princeton Ave",
    "sg:city":"Visalia",
    "sg:classifiers":[
        {
            "category":"Real Estate",
            "subcategory":"Real Estate Services",
            "type":"Services"
        },
        {
            "category":"Professional",
            "subcategory":"Business Services",
            "type":"Services"
        },
        {
            "category":"Real Estate",
            "subcategory":"Surveying",
            "type":"Services"
        }
    ],
    "sg:phone":"+1 559 636 0797",
    "sg:postcode":"93277",
    "sg:province":"CA",
    "sg:tags":[
        "commercial",
        "appraisers-business",
        "industrial",
        "appraisers-commercial",
        "appraiser"
    ],
    "wof:name":"Quality Appraisal Service",
    "wof:placetype":"venue"
},
  "geometry": {"coordinates":[-119.312423,36.315609],"type":"Point"}
}