{
  "type": "Feature",
  "properties": {
    "iso:country":"US",
    "sg:address":"16167 E Eight Mile Rd",
    "sg:city":"Linden",
    "sg:classifiers":[
        {
            "category":"Wholesale",
            "subcategory":"Fruits & Vegetables",
            "type":"Manufacturing & Wholesale Goods"
        }
    ],
    "sg:phone":"+1 209 931 3799",
    "sg:postcode":"95236",
    "sg:province":"CA",
    "wof:name":"Solari Ranch",
    "wof:placetype":"venue"
},
  "geometry": {"coordinates":[-121.10615300000001,38.059742],"type":"Point"}
}