{
  "type": "Feature",
  "properties": {
    "addr:full":"3125 E 15th St Oakland CA 94601",
    "addr:housenumber":"3125",
    "addr:postcode":"94601",
    "addr:street":"E 15Th St",
    "iso:country":"US",
    "sg:address":"3125 E 15th St",
    "sg:city":"Oakland",
    "sg:classifiers":[
        {
            "category":"Social Services",
            "type":"Services"
        }
    ],
    "sg:phone":"+1 510 533 0115",
    "sg:postcode":"94601",
    "sg:province":"CA",
    "sg:tags":[
        "center",
        "convalescent",
        "home",
        "care",
        "day",
        "nursing"
    ],
    "sg:website":"www.over21inc.org",
    "wof:name":"Over 21 Adult Day Program",
    "wof:placetype":"venue"
},
  "geometry": {"coordinates":[-122.225914,37.778942],"type":"Point"}
}