{
  "type": "Feature",
  "properties": {
    "addr:full":"8113 Solis Rancho Gilroy CA 95020",
    "addr:housenumber":"8113",
    "addr:postcode":"95020",
    "addr:street":"Solis Rancho Gilroy",
    "iso:country":"US",
    "sg:address":"8113 Solis Rancho",
    "sg:city":"Gilroy",
    "sg:classifiers":[
        {
            "category":"Building & Trades",
            "subcategory":"Construction",
            "type":"Services"
        }
    ],
    "sg:phone":"+1 408 847 1618",
    "sg:postcode":"95020",
    "sg:province":"CA",
    "sg:tags":[
        "contractor"
    ],
    "wof:name":"Circle S Construction Co",
    "wof:placetype":"venue"
},
  "geometry": {"coordinates":[-121.65978,37.014869],"type":"Point"}
}