{
  "type": "Feature",
  "properties": {
    "iso:country":"US",
    "sg:address":"3516 Sacramento St",
    "sg:city":"San Francisco",
    "sg:classifiers":[
        {
            "category":"Building & Trades",
            "subcategory":"Construction",
            "type":"Services"
        }
    ],
    "sg:phone":"+1 415 771 2244",
    "sg:postcode":"94118",
    "sg:province":"CA",
    "sg:tags":[
        "tinning"
    ],
    "wof:name":"Coco Boutique",
    "wof:placetype":"venue"
},
  "geometry": {"coordinates":[-122.451745,37.787661],"type":"Point"}
}