{
  "type": "Feature",
  "properties": {
    "addr:full":"12000 Berryessa Rd San Jose CA 95133",
    "addr:housenumber":"12000",
    "addr:postcode":"95133",
    "addr:street":"Berryessa Rd",
    "iso:country":"US",
    "sg:address":"12000 Berryessa Rd",
    "sg:city":"San Jose",
    "sg:classifiers":[
        {
            "category":"Wholesale",
            "subcategory":"Fruits & Vegetables",
            "type":"Manufacturing & Wholesale Goods"
        }
    ],
    "sg:phone":"+1 408 452 5768",
    "sg:postcode":"95133",
    "sg:province":"CA",
    "sg:tags":[
        "veggie"
    ],
    "wof:name":"El Greco Produce",
    "wof:placetype":"venue"
},
  "geometry": {"coordinates":[-121.879997,37.3685],"type":"Point"}
}