{
  "type": "Feature",
  "properties": {
    "iso:country":"US",
    "sg:address":"101 W Foothill Blvd",
    "sg:city":"Rialto",
    "sg:classifiers":[
        {
            "category":"Retail",
            "subcategory":"Auto Repair",
            "type":"Services"
        }
    ],
    "sg:phone":"+1 909 877 5446",
    "sg:postcode":"92376",
    "sg:province":"CA",
    "sg:tags":[
        "repairing",
        "automobile"
    ],
    "wof:name":"Rialto Unocal 76",
    "wof:placetype":"venue"
},
  "geometry": {"coordinates":[-117.37057299999999,34.106766],"type":"Point"}
}