{
  "type": "Feature",
  "properties": {
    "iso:country":"US",
    "sg:address":"14543 Burbank Blvd",
    "sg:city":"Sherman Oaks",
    "sg:classifiers":[
        {
            "category":"Professional",
            "subcategory":"Employment Agencies",
            "type":"Services"
        }
    ],
    "sg:phone":"+1 818 901 8887",
    "sg:postcode":"91411",
    "sg:province":"CA",
    "wof:name":"Cocktail Connection",
    "wof:placetype":"venue"
},
  "geometry": {"coordinates":[-118.450113,34.17219],"type":"Point"}
}