{
  "type": "Feature",
  "properties": {
    "addr:full":"9855 Arata Ln Windsor CA 95492",
    "addr:housenumber":"9855",
    "addr:postcode":"95492",
    "addr:street":"Arata Ln",
    "iso:country":"US",
    "sg:address":"9855 Arata Ln",
    "sg:city":"Windsor",
    "sg:classifiers":[
        {
            "category":"Building & Trades",
            "subcategory":"Construction",
            "type":"Services"
        }
    ],
    "sg:phone":"+1 707 838 7653",
    "sg:postcode":"95492",
    "sg:province":"CA",
    "sg:tags":[
        "excavating",
        "contractor"
    ],
    "wof:name":"Bottasso Backhoe Svc",
    "wof:placetype":"venue"
},
  "geometry": {"coordinates":[-122.804374,38.562154],"type":"Point"}
}