{
  "type": "Feature",
  "properties": {
    "iso:country":"US",
    "sg:address":"1269 N 10th Ave",
    "sg:city":"Hanford",
    "sg:classifiers":[
        {
            "category":"Shopping",
            "subcategory":"Jewelry",
            "type":"Retail Goods"
        }
    ],
    "sg:phone":"+1 559 589 0565",
    "sg:postcode":"93230",
    "sg:province":"CA",
    "sg:tags":[
        "jeweler"
    ],
    "wof:name":"Leo's Party Supply & Jewelry",
    "wof:placetype":"venue"
},
  "geometry": {"coordinates":[-119.636948,36.338115],"type":"Point"}
}