{
  "type": "Feature",
  "properties": {
    "iso:country":"US",
    "sg:address":"1500 21st St",
    "sg:city":"Sacramento",
    "sg:classifiers":[
        {
            "category":"Health Services",
            "subcategory":"Clinic",
            "type":"Services"
        },
        {
            "category":"Health Services",
            "subcategory":"Nursing And Care Facility",
            "type":"Services"
        },
        {
            "category":"Health Services",
            "subcategory":"Health Practitioner",
            "type":"Services"
        }
    ],
    "sg:phone":"+1 916 443 3299",
    "sg:postcode":"95811",
    "sg:province":"CA",
    "sg:tags":[
        "home",
        "medical",
        "eldercare-home"
    ],
    "sg:website":"http://www.caresclinic.org",
    "wof:name":"Center for Aids Research Education & Services",
    "wof:placetype":"venue"
},
  "geometry": {"coordinates":[-121.480988,38.570801],"type":"Point"}
}