{
  "type": "Feature",
  "properties": {
    "addr:full":"310 Broadway Millbrae CA 94030",
    "addr:housenumber":"310",
    "addr:postcode":"94030",
    "addr:street":"Broadway",
    "iso:country":"US",
    "sg:address":"310 Broadway",
    "sg:city":"Millbrae",
    "sg:classifiers":[
        {
            "category":"Restaurant",
            "type":"Food & Drink"
        }
    ],
    "sg:postcode":"94030",
    "sg:province":"CA",
    "sg:tags":[
        "traditional",
        "american",
        "diner"
    ],
    "wof:name":"Peter's Cafe",
    "wof:placetype":"venue"
},
  "geometry": {"coordinates":[-122.391747,37.601153],"type":"Point"}
}