{
  "type": "Feature",
  "properties": {
    "iso:country":"US",
    "sg:address":"18442 Macnab Cypress Rd",
    "sg:city":"Nevada City",
    "sg:classifiers":[
        {
            "category":"Wholesale",
            "subcategory":"Hardware",
            "type":"Manufacturing & Wholesale Goods"
        }
    ],
    "sg:phone":"+1 530 292 1001",
    "sg:postcode":"95959",
    "sg:province":"CA",
    "sg:tags":[
        "equipment",
        "energy",
        "solar"
    ],
    "wof:name":"Black Oak Electric",
    "wof:placetype":"venue"
},
  "geometry": {"coordinates":[-121.011677,39.344453],"type":"Point"}
}