{
  "type": "Feature",
  "properties": {
    "addr:full":"558 3rd St W Sonoma CA 95476",
    "addr:housenumber":"558",
    "addr:postcode":"95476",
    "addr:street":"3Rd St W",
    "iso:country":"US",
    "sg:address":"558 3rd St W",
    "sg:city":"Sonoma",
    "sg:classifiers":[
        {
            "category":"Health Services",
            "subcategory":"Doctor",
            "type":"Services"
        }
    ],
    "sg:phone":"+1 707 935 1470",
    "sg:postcode":"95476",
    "sg:province":"CA",
    "sg:tags":[
        "physician",
        "surgeon"
    ],
    "wof:name":"Sonoma Cardiology",
    "wof:placetype":"venue"
},
  "geometry": {"coordinates":[-122.463526,38.291492],"type":"Point"}
}