{
  "type": "Feature",
  "properties": {
    "addr:full":"625 W 1st St San Pedro CA 90731",
    "addr:housenumber":"625",
    "addr:postcode":"90731",
    "addr:street":"W 1St St",
    "iso:country":"US",
    "sg:address":"625 W 1st St",
    "sg:city":"San Pedro",
    "sg:classifiers":[
        {
            "category":"Building & Trades",
            "subcategory":"Landscaping Services",
            "type":"Services"
        }
    ],
    "sg:phone":"+1 310 560 6410",
    "sg:postcode":"90731",
    "sg:province":"CA",
    "sg:tags":[
        "landscape"
    ],
    "wof:name":"Sandoval Landscape",
    "wof:placetype":"venue"
},
  "geometry": {"coordinates":[-118.291854,33.743227],"type":"Point"}
}