{
  "type": "Feature",
  "properties": {
    "addr:full":"12974 Carmel Creek Rd San Diego CA 92130",
    "addr:housenumber":"12974",
    "addr:postcode":"92130",
    "addr:street":"Carmel Creek Rd",
    "iso:country":"US",
    "sg:address":"12974 Carmel Creek Rd",
    "sg:city":"San Diego",
    "sg:classifiers":[
        {
            "category":"Shopping",
            "subcategory":"Clothing, Apparel, & Fashions",
            "type":"Retail Goods"
        }
    ],
    "sg:phone":"+1 858 259 6762",
    "sg:postcode":"92130",
    "sg:province":"CA",
    "wof:name":"S&H Distributors",
    "wof:placetype":"venue"
},
  "geometry": {"coordinates":[-117.226839,32.951826],"type":"Point"}
}