{
  "type": "Feature",
  "properties": {
    "addr:full":"915 Sunbonnet Loop San Jose CA 95125",
    "addr:housenumber":"915",
    "addr:postcode":"95125",
    "addr:street":"Sunbonnet Loop",
    "iso:country":"US",
    "sg:address":"915 Sunbonnet Loop",
    "sg:city":"San Jose",
    "sg:classifiers":[
        {
            "category":"Manufacturing",
            "subcategory":"Electronics",
            "type":"Manufacturing & Wholesale Goods"
        }
    ],
    "sg:phone":"+1 408 267 3909",
    "sg:postcode":"95125",
    "sg:province":"CA",
    "sg:tags":[
        "devices",
        "mfg"
    ],
    "wof:name":"First Wang",
    "wof:placetype":"venue"
},
  "geometry": {"coordinates":[-121.877323,37.282354],"type":"Point"}
}