{
  "type": "Feature",
  "properties": {
    "iso:country":"US",
    "sg:address":"4550 E Olympic Boulevard",
    "sg:city":"Los Angeles",
    "sg:classifiers":[
        {
            "category":"Personal",
            "type":"Services"
        }
    ],
    "sg:phone":"+1 323 268 6063",
    "sg:postcode":"90022",
    "sg:province":"CA",
    "sg:tags":[
        "mover"
    ],
    "wof:name":"Expert Movers",
    "wof:placetype":"venue"
},
  "geometry": {"coordinates":[-118.171924,34.01881],"type":"Point"}
}