{
  "type": "Feature",
  "properties": {
    "addr:full":"8202 Sorensen Ave Santa Fe Springs CA 90670",
    "addr:housenumber":"8202",
    "addr:postcode":"90670",
    "addr:street":"Sorensen Ave",
    "iso:country":"US",
    "sg:address":"8202 Sorensen Ave",
    "sg:city":"Santa Fe Springs",
    "sg:classifiers":[
        {
            "category":"Shopping",
            "type":"Retail Goods"
        },
        {
            "category":"Manufacturing",
            "subcategory":"Wood Products",
            "type":"Manufacturing & Wholesale Goods"
        }
    ],
    "sg:phone":"+1 562 698 8508",
    "sg:postcode":"90670",
    "sg:province":"CA",
    "sg:tags":[
        "mfg",
        "carving"
    ],
    "wof:name":"Contreras Carvings",
    "wof:placetype":"venue"
},
  "geometry": {"coordinates":[-118.060029,33.968424],"type":"Point"}
}