{
  "type": "Feature",
  "properties": {
    "addr:full":"1129 Lauriston Dr San Diego CA 92154",
    "addr:housenumber":"1129",
    "addr:postcode":"92154",
    "addr:street":"Lauriston Dr",
    "iso:country":"US",
    "sg:address":"1129 Lauriston Dr",
    "sg:city":"San Diego",
    "sg:classifiers":[
        {
            "category":"Banks & Credit Unions",
            "subcategory":"Financial Services",
            "type":"Services"
        }
    ],
    "sg:phone":"+1 619 429 1643",
    "sg:postcode":"92154",
    "sg:province":"CA",
    "sg:tags":[
        "trust",
        "management"
    ],
    "wof:name":"Feeser Survivors Trust 09",
    "wof:placetype":"venue"
},
  "geometry": {"coordinates":[-117.071479,32.574428],"type":"Point"}
}