{
  "type": "Feature",
  "properties": {
    "addr:full":"617 Stanford Avenue Los Angeles CA 90021",
    "addr:housenumber":"617",
    "addr:postcode":"90021",
    "addr:street":"Stanford Avenue",
    "iso:country":"US",
    "sg:address":"617 Stanford Avenue",
    "sg:city":"Los Angeles",
    "sg:classifiers":[
        {
            "category":"Food & Beverages",
            "subcategory":"Meat & Fish",
            "type":"Retail Goods"
        }
    ],
    "sg:phone":"+1 213 688 8836",
    "sg:postcode":"90021",
    "sg:province":"CA",
    "sg:tags":[
        "seafood",
        "market"
    ],
    "wof:name":"Pescaderia Tampico",
    "wof:placetype":"venue"
},
  "geometry": {"coordinates":[-118.243354,34.039999],"type":"Point"}
}