{
  "type": "Feature",
  "properties": {
    "addr:full":"429 Littlefield Ave S San Francisco CA 94080",
    "addr:housenumber":"429",
    "addr:postcode":"94080",
    "addr:street":"Littlefield Ave S",
    "iso:country":"US",
    "sg:address":"429 Littlefield Ave",
    "sg:city":"S San Francisco",
    "sg:classifiers":[
        {
            "category":"Wholesale",
            "subcategory":"Office Equipment",
            "type":"Manufacturing & Wholesale Goods"
        }
    ],
    "sg:phone":"+1 415 626 2202",
    "sg:postcode":"94080",
    "sg:province":"CA",
    "sg:tags":[
        "chalkboard"
    ],
    "wof:name":"Fred Turner Co",
    "wof:placetype":"venue"
},
  "geometry": {"coordinates":[-122.39451800000001,37.650702],"type":"Point"}
}