{
  "type": "Feature",
  "properties": {
    "iso:country":"US",
    "sg:address":"7433 Florence Ave",
    "sg:city":"Downey",
    "sg:classifiers":[
        {
            "category":"Professional",
            "subcategory":"Management & Consulting",
            "type":"Services"
        }
    ],
    "sg:phone":"+1 562 964 8467",
    "sg:postcode":"90240",
    "sg:province":"CA",
    "sg:tags":[
        "environmental",
        "ecological",
        "consultant"
    ],
    "wof:name":"Entrix",
    "wof:placetype":"venue"
},
  "geometry": {"coordinates":[-118.13947,33.95831],"type":"Point"}
}