{
  "type": "Feature",
  "properties": {
    "iso:country":"US",
    "sg:address":"2700 Las Positas Rd",
    "sg:city":"Livermore",
    "sg:classifiers":[
        {
            "category":"Shopping",
            "type":"Retail Goods"
        }
    ],
    "sg:phone":"+1 925 371 1300",
    "sg:postcode":"94550",
    "sg:province":"CA",
    "sg:tags":[
        "telephone",
        "cellular"
    ],
    "wof:name":"Cellular Warehouse",
    "wof:placetype":"venue"
},
  "geometry": {"coordinates":[-121.765553,37.698879],"type":"Point"}
}