{
  "type": "Feature",
  "properties": {
    "addr:full":"51 Havelock St San Francisco CA 94112",
    "addr:housenumber":"51",
    "addr:postcode":"94112",
    "addr:street":"Havelock St",
    "iso:country":"US",
    "sg:address":"51 Havelock St",
    "sg:city":"San Francisco",
    "sg:classifiers":[
        {
            "category":"Recreation",
            "type":"Entertainment"
        }
    ],
    "sg:phone":"+1 415 337 4701",
    "sg:postcode":"94112",
    "sg:province":"CA",
    "sg:tags":[
        "pool",
        "swimming"
    ],
    "wof:name":"Balboa Park Swimming Pool",
    "wof:placetype":"venue"
},
  "geometry": {"coordinates":[-122.442356,37.726681],"type":"Point"}
}