{
  "type": "Feature",
  "properties": {
    "addr:full":"15221 Winton Way San Jose CA 95124",
    "addr:housenumber":"15221",
    "addr:postcode":"95124",
    "addr:street":"Winton Way",
    "iso:country":"US",
    "sg:address":"15221 Winton Way",
    "sg:city":"San Jose",
    "sg:classifiers":[
        {
            "category":"Banks & Credit Unions",
            "subcategory":"Investment Brokerage",
            "type":"Services"
        }
    ],
    "sg:phone":"+1 408 358 8537",
    "sg:postcode":"95124",
    "sg:province":"CA",
    "sg:tags":[
        "stock",
        "bond"
    ],
    "wof:name":"Linsco Private Ledger Fncl Svc",
    "wof:placetype":"venue"
},
  "geometry": {"coordinates":[-121.941671,37.247451],"type":"Point"}
}