{
  "type": "Feature",
  "properties": {
    "addr:full":"1181-83 UNIVERSITY AVE Berkeley CA 94702",
    "addr:housenumber":"1181-83",
    "addr:postcode":"94702",
    "addr:street":"University Ave",
    "iso:country":"US",
    "sg:address":"1181-83 UNIVERSITY AVE",
    "sg:city":"Berkeley",
    "sg:classifiers":[
        {
            "category":"Fast Food",
            "type":"Food & Drink"
        },
        {
            "category":"Restaurant",
            "type":"Food & Drink"
        }
    ],
    "sg:phone":"+1 510 548 3278",
    "sg:postcode":"94702",
    "sg:province":"CA",
    "sg:tags":[
        "thai",
        "asian",
        "pan",
        "take"
    ],
    "sg:website":"http://www.atSiamCuisine.com",
    "wof:name":"at Siam Cuisine",
    "wof:placetype":"venue"
},
  "geometry": {"coordinates":[-122.28373000000001,37.85437],"type":"Point"}
}