{
  "type": "Feature",
  "properties": {
    "addr:full":"239 N Robertson Blvd Beverly Hills CA 90211",
    "addr:housenumber":"239",
    "addr:postcode":"90211",
    "addr:street":"N Robertson Blvd",
    "iso:country":"US",
    "sg:address":"239 N Robertson Blvd",
    "sg:city":"Beverly Hills",
    "sg:classifiers":[
        {
            "category":"Personal",
            "subcategory":"Nail Salon",
            "type":"Services"
        }
    ],
    "sg:phone":"+1 310 550 5822",
    "sg:postcode":"90211",
    "sg:province":"CA",
    "sg:website":"www.bellacures.com",
    "wof:name":"Bellacures",
    "wof:placetype":"venue"
},
  "geometry": {"coordinates":[-118.384005,34.069827],"type":"Point"}
}