{
  "type": "Feature",
  "properties": {
    "iso:country":"US",
    "sg:address":"1905 Preston Ave",
    "sg:city":"Los Angeles",
    "sg:classifiers":[
        {
            "category":"Building & Trades",
            "subcategory":"Construction",
            "type":"Services"
        }
    ],
    "sg:phone":"+1 213 280 6419",
    "sg:postcode":"90026",
    "sg:province":"CA",
    "sg:tags":[
        "contractor"
    ],
    "wof:name":"Porcelain Coat",
    "wof:placetype":"venue"
},
  "geometry": {"coordinates":[-118.251366,34.088077],"type":"Point"}
}