{
  "type": "Feature",
  "properties": {
    "iso:country":"US",
    "sg:address":"1550 Canyon Rd",
    "sg:city":"Moraga",
    "sg:classifiers":[
        {
            "category":"Farming",
            "subcategory":"Nursery",
            "type":"Manufacturing & Wholesale Goods"
        },
        {
            "category":"Home & Garden",
            "subcategory":"Hardware",
            "type":"Retail Goods"
        },
        {
            "category":"Home & Garden",
            "subcategory":"Building Materials",
            "type":"Retail Goods"
        },
        {
            "category":"Home & Garden",
            "subcategory":"Garden Supply",
            "type":"Retail Goods"
        }
    ],
    "sg:phone":"+1 925 377 0994",
    "sg:postcode":"94556",
    "sg:province":"CA",
    "sg:tags":[
        "improvement",
        "tree",
        "store",
        "nurseries-plants"
    ],
    "sg:website":"http://www.osh.com/?utm_source=yp&utm_medium=tl&utm_campaign=store421",
    "wof:name":"Orchard Supply Hardware",
    "wof:placetype":"venue"
},
  "geometry": {"coordinates":[-122.12821099999999,37.833322],"type":"Point"}
}