{
  "type": "Feature",
  "properties": {
    "addr:full":"40366 State Hwy 41 Oakhurst CA 93644",
    "addr:housenumber":"40366",
    "addr:postcode":"93644",
    "addr:street":"State Hwy 41",
    "iso:country":"US",
    "sg:address":"40366 State Hwy 41",
    "sg:city":"Oakhurst",
    "sg:classifiers":[
        {
            "category":"Real Estate",
            "subcategory":"Real Estate Agent",
            "type":"Services"
        }
    ],
    "sg:phone":"+1 559 683 7477",
    "sg:postcode":"93644",
    "sg:province":"CA",
    "wof:name":"Pine Tree Realty",
    "wof:placetype":"venue"
},
  "geometry": {"coordinates":[-119.646671,37.334498],"type":"Point"}
}