{
  "type": "Feature",
  "properties": {
    "iso:country":"US",
    "sg:address":"15466 Los Gatos Blvd",
    "sg:city":"Los Gatos",
    "sg:classifiers":[
        {
            "category":"Manufacturing",
            "subcategory":"Printing",
            "type":"Manufacturing & Wholesale Goods"
        }
    ],
    "sg:phone":"+1 408 358 2427",
    "sg:postcode":"95032",
    "sg:province":"CA",
    "sg:tags":[
        "book"
    ],
    "wof:name":"Woodshed Productions",
    "wof:placetype":"venue"
},
  "geometry": {"coordinates":[-121.959299,37.243507],"type":"Point"}
}