{
  "type": "Feature",
  "properties": {
    "iso:country":"US",
    "sg:address":"536 Brinkerhoff Ave",
    "sg:city":"Santa Barbara",
    "sg:classifiers":[
        {
            "category":"Social Services",
            "subcategory":"Child Care",
            "type":"Services"
        }
    ],
    "sg:phone":"+1 805 962 4433",
    "sg:postcode":"93101",
    "sg:province":"CA",
    "sg:website":"www.childtimenanny.com",
    "wof:name":"Childtime Professional Nanny",
    "wof:placetype":"venue"
},
  "geometry": {"coordinates":[-119.69766199999999,34.415296],"type":"Point"}
}