{
  "type": "Feature",
  "properties": {
    "addr:full":"2 Corporate Plaza Dr Newport Beach CA 92660",
    "addr:housenumber":"2",
    "addr:postcode":"92660",
    "addr:street":"Corporate Plaza Dr",
    "iso:country":"US",
    "sg:address":"2 Corporate Plaza Dr",
    "sg:city":"Newport Beach",
    "sg:classifiers":[
        {
            "category":"Professional",
            "type":"Services"
        }
    ],
    "sg:phone":"+1 949 706 6737",
    "sg:postcode":"92660",
    "sg:province":"CA",
    "wof:name":"Newport Dental Spa",
    "wof:placetype":"venue"
},
  "geometry": {"coordinates":[-117.876835,33.607183],"type":"Point"}
}