{
  "type": "Feature",
  "properties": {
    "iso:country":"US",
    "sg:address":"4150 W Riverside Dr Ste A",
    "sg:city":"Burbank",
    "sg:classifiers":[
        {
            "category":"Coffee & Tea",
            "type":"Food & Drink"
        }
    ],
    "sg:phone":"+1 818 843 5707",
    "sg:postcode":"91505",
    "sg:province":"CA",
    "sg:website":"www.priscillascoffee.com/",
    "wof:name":"Priscilla's Gourmet Coffee Tea & Gifts",
    "wof:placetype":"venue"
},
  "geometry": {"coordinates":[-118.345001,34.152199],"type":"Point"}
}