{
  "type": "Feature",
  "properties": {
    "iso:country":"US",
    "sg:address":"3221 Adams Ave",
    "sg:city":"San Diego",
    "sg:classifiers":[
        {
            "category":"Bars & Pubs",
            "subcategory":"Sports Bar",
            "type":"Food & Drink"
        },
        {
            "category":"Bars & Pubs",
            "subcategory":"Dive Bar",
            "type":"Food & Drink"
        }
    ],
    "sg:phone":"+1 619 281 0263",
    "sg:postcode":"92116",
    "sg:province":"CA",
    "wof:name":"Triple Crown Pub",
    "wof:placetype":"venue"
},
  "geometry": {"coordinates":[-117.125,32.7635],"type":"Point"}
}