{
  "type": "Feature",
  "properties": {
    "iso:country":"US",
    "sg:address":"2930 Bristol St Ste A111",
    "sg:city":"Costa Mesa",
    "sg:classifiers":[
        {
            "category":"Shopping",
            "subcategory":"Department Store",
            "type":"Retail Goods"
        }
    ],
    "sg:phone":"+1 714 966 1666",
    "sg:postcode":"92626",
    "sg:province":"CA",
    "sg:website":"www.urbanoutfitters.com",
    "wof:name":"Urban Outfitters",
    "wof:placetype":"venue"
},
  "geometry": {"coordinates":[-117.886955,33.677197],"type":"Point"}
}