{
  "type": "Feature",
  "properties": {
    "addr:full":"800 S Figueroa St Los Angeles CA 90017",
    "addr:housenumber":"800",
    "addr:postcode":"90017",
    "addr:street":"S Figueroa St",
    "iso:country":"US",
    "sg:address":"800 S Figueroa St",
    "sg:city":"Los Angeles",
    "sg:classifiers":[
        {
            "category":"Shopping",
            "subcategory":"Clothing, Apparel, & Fashions",
            "type":"Retail Goods"
        }
    ],
    "sg:phone":"+1 323 856 0024",
    "sg:postcode":"90017",
    "sg:province":"CA",
    "sg:tags":[
        "infant",
        "wear"
    ],
    "wof:name":"Fifi Et Fafa Inc",
    "wof:placetype":"venue"
},
  "geometry": {"coordinates":[-118.26223,34.046825],"type":"Point"}
}