{
  "type": "Feature",
  "properties": {
    "addr:full":"1311 Chica Way Sacramento CA 95864",
    "addr:housenumber":"1311",
    "addr:postcode":"95864",
    "addr:street":"Chica Way",
    "iso:country":"US",
    "sg:address":"1311 Chica Way",
    "sg:city":"Sacramento",
    "sg:classifiers":[
        {
            "category":"Building & Trades",
            "subcategory":"Electrical",
            "type":"Services"
        }
    ],
    "sg:phone":"+1 916 487 4345",
    "sg:postcode":"95864",
    "sg:province":"CA",
    "sg:tags":[
        "booth",
        "equipment",
        "telephone",
        "pay"
    ],
    "wof:name":"Samuel A Pyle Pay Phones",
    "wof:placetype":"venue"
},
  "geometry": {"coordinates":[-121.369367,38.590807],"type":"Point"}
}