{
  "type": "Feature",
  "properties": {
    "iso:country":"US",
    "sg:address":"12622 Long Beach Blvd",
    "sg:city":"Lynwood",
    "sg:classifiers":[
        {
            "category":"Farming",
            "subcategory":"Nursery",
            "type":"Manufacturing & Wholesale Goods"
        }
    ],
    "sg:phone":"+1 310 603 0461",
    "sg:postcode":"90262",
    "sg:province":"CA",
    "sg:tags":[
        "ornamental"
    ],
    "wof:name":"Areli Flowers",
    "wof:placetype":"venue"
},
  "geometry": {"coordinates":[-118.208849,33.911858],"type":"Point"}
}