{
  "type": "Feature",
  "properties": {
    "addr:full":"19655 Ventura Blvd Tarzana CA 91356",
    "addr:housenumber":"19655",
    "addr:postcode":"91356",
    "addr:street":"Ventura Blvd",
    "iso:country":"US",
    "sg:address":"19655 Ventura Blvd",
    "sg:city":"Tarzana",
    "sg:classifiers":[
        {
            "category":"Professional",
            "subcategory":"Computer Services",
            "type":"Services"
        }
    ],
    "sg:phone":"+1 818 774 9503",
    "sg:postcode":"91356",
    "sg:province":"CA",
    "sg:tags":[
        "repair"
    ],
    "wof:name":"L A Electric Service",
    "wof:placetype":"venue"
},
  "geometry": {"coordinates":[-118.560997,34.1726],"type":"Point"}
}