{
  "type": "Feature",
  "properties": {
    "addr:full":"1805 S Chester Ave Bakersfield CA 93304",
    "addr:housenumber":"1805",
    "addr:postcode":"93304",
    "addr:street":"S Chester Ave",
    "iso:country":"US",
    "sg:address":"1805 S Chester Ave",
    "sg:city":"Bakersfield",
    "sg:classifiers":[
        {
            "category":"Retail",
            "subcategory":"Auto Repair",
            "type":"Services"
        }
    ],
    "sg:phone":"+1 661 397 0421",
    "sg:postcode":"93304",
    "sg:province":"CA",
    "sg:tags":[
        "transmission"
    ],
    "wof:name":"Quality Transmission & Clutch",
    "wof:placetype":"venue"
},
  "geometry": {"coordinates":[-119.017616,35.33746],"type":"Point"}
}