{
  "type": "Feature",
  "properties": {
    "addr:full":"18126 Parthenia St Northridge CA 91325",
    "addr:housenumber":"18126",
    "addr:postcode":"91325",
    "addr:street":"Parthenia St",
    "iso:country":"US",
    "sg:address":"18126 Parthenia St",
    "sg:city":"Northridge",
    "sg:classifiers":[
        {
            "category":"Utilities",
            "subcategory":"Cable",
            "type":"Services"
        }
    ],
    "sg:phone":"+1 818 727 7777",
    "sg:postcode":"91325",
    "sg:province":"CA",
    "sg:tags":[
        "television"
    ],
    "wof:name":"Dish Network",
    "wof:placetype":"venue"
},
  "geometry": {"coordinates":[-118.531795,34.228606],"type":"Point"}
}