{
  "type": "Feature",
  "properties": {
    "addr:full":"9929 Hibert St San Diego CA 92131",
    "addr:housenumber":"9929",
    "addr:postcode":"92131",
    "addr:street":"Hibert St",
    "iso:country":"US",
    "sg:address":"9929 Hibert St",
    "sg:city":"San Diego",
    "sg:classifiers":[
        {
            "category":"Building & Trades",
            "subcategory":"Plumbing",
            "type":"Services"
        }
    ],
    "sg:phone":"+1 619 280 6552",
    "sg:postcode":"92131",
    "sg:province":"CA",
    "sg:tags":[
        "plumbing",
        "contractor"
    ],
    "sg:website":"www.yoursubcontractors.com",
    "wof:name":"Black Mountain Plumping",
    "wof:placetype":"venue"
},
  "geometry": {"coordinates":[-117.11212999999999,32.913759],"type":"Point"}
}