{
  "type": "Feature",
  "properties": {
    "addr:full":"455 S Sierra Way San Bernardino CA 92408",
    "addr:housenumber":"455",
    "addr:postcode":"92408",
    "addr:street":"S Sierra Way",
    "iso:country":"US",
    "sg:address":"455 S Sierra Way",
    "sg:city":"San Bernardino",
    "sg:classifiers":[
        {
            "category":"Manufacturing",
            "subcategory":"Tools & Machinery",
            "type":"Manufacturing & Wholesale Goods"
        }
    ],
    "sg:phone":"+1 909 885 4210",
    "sg:postcode":"92408",
    "sg:province":"CA",
    "sg:tags":[
        "machine",
        "shop"
    ],
    "wof:name":"Ross Machine & Mfg",
    "wof:placetype":"venue"
},
  "geometry": {"coordinates":[-117.285079,34.095589],"type":"Point"}
}