{
  "type": "Feature",
  "properties": {
    "iso:country":"US",
    "sg:address":"455 S Sierra Way",
    "sg:city":"San Bernardino",
    "sg:classifiers":[
        {
            "category":"Manufacturing",
            "subcategory":"Tools & Machinery",
            "type":"Manufacturing & Wholesale Goods"
        }
    ],
    "sg:phone":"+1 909 885 4210",
    "sg:postcode":"92408",
    "sg:province":"CA",
    "sg:tags":[
        "machine",
        "shop"
    ],
    "wof:name":"Ross Machine & Mfg",
    "wof:placetype":"venue"
},
  "geometry": {"coordinates":[-117.285079,34.095589],"type":"Point"}
}