{
  "type": "Feature",
  "properties": {
    "iso:country":"US",
    "sg:address":"11051 Via el Mercado",
    "sg:city":"Los Alamitos",
    "sg:classifiers":[
        {
            "category":"Professional",
            "subcategory":"Management & Consulting",
            "type":"Services"
        }
    ],
    "sg:phone":"+1 562 598 6616",
    "sg:postcode":"90720",
    "sg:province":"CA",
    "sg:tags":[
        "coffee",
        "brewing",
        "devices"
    ],
    "wof:name":"Cleland Sales Co",
    "wof:placetype":"venue"
},
  "geometry": {"coordinates":[-118.03881699999999,33.801991],"type":"Point"}
}