{
  "type": "Feature",
  "properties": {
    "addr:full":"32930 Lakeview Ter Lake Elsinore CA 92530",
    "addr:housenumber":"32930",
    "addr:postcode":"92530",
    "addr:street":"Lakeview Ter",
    "iso:country":"US",
    "sg:address":"32930 Lakeview Ter",
    "sg:city":"Lake Elsinore",
    "sg:classifiers":[
        {
            "category":"Building & Trades",
            "subcategory":"Construction",
            "type":"Services"
        }
    ],
    "sg:phone":"+1 951 674 5903",
    "sg:postcode":"92530",
    "sg:province":"CA",
    "sg:tags":[
        "house"
    ],
    "wof:name":"Ssk Enterprises",
    "wof:placetype":"venue"
},
  "geometry": {"coordinates":[-117.287024,33.642657],"type":"Point"}
}