{
  "type": "Feature",
  "properties": {
    "iso:country":"US",
    "sg:address":"30116 Lexington Dr",
    "sg:city":"Castaic",
    "sg:classifiers":[
        {
            "category":"Professional",
            "type":"Services"
        }
    ],
    "sg:phone":"+1 661 702 9307",
    "sg:postcode":"91384",
    "sg:province":"CA",
    "wof:name":"Jeff Engels",
    "wof:placetype":"venue"
},
  "geometry": {"coordinates":[-118.660391,34.448412],"type":"Point"}
}