{
  "type": "Feature",
  "properties": {
    "iso:country":"US",
    "sg:address":"220 Shoreview Ave",
    "sg:city":"Pacifica",
    "sg:classifiers":[
        {
            "category":"Organizations",
            "subcategory":"Religious Organization",
            "type":"Services"
        }
    ],
    "sg:phone":"+1 650 738 5980",
    "sg:postcode":"94044",
    "sg:province":"CA",
    "sg:tags":[
        "church"
    ],
    "wof:name":"Baha'i Faith",
    "wof:placetype":"venue"
},
  "geometry": {"coordinates":[-122.492739,37.637421],"type":"Point"}
}