{
  "type": "Feature",
  "properties": {
    "iso:country":"US",
    "sg:address":"1915 N Tipton St",
    "sg:city":"Visalia",
    "sg:classifiers":[
        {
            "category":"Home & Garden",
            "subcategory":"Building Materials",
            "type":"Retail Goods"
        },
        {
            "category":"Building & Trades",
            "subcategory":"Construction",
            "type":"Services"
        }
    ],
    "sg:phone":"+1 559 740 0925",
    "sg:postcode":"93292",
    "sg:province":"CA",
    "sg:tags":[
        "concrete",
        "staining",
        "contractor"
    ],
    "wof:name":"M & C Concrete Construction",
    "wof:placetype":"venue"
},
  "geometry": {"coordinates":[-119.287111,36.346262],"type":"Point"}
}