{
  "type": "Feature",
  "properties": {
    "iso:country":"US",
    "sg:address":"1250 Bella Oaks Ln",
    "sg:city":"Rutherford",
    "sg:classifiers":[
        {
            "category":"Manufacturing",
            "subcategory":"Food",
            "type":"Manufacturing & Wholesale Goods"
        }
    ],
    "sg:phone":"+1 707 963 1192",
    "sg:postcode":"94558",
    "sg:province":"CA",
    "sg:tags":[
        "winery"
    ],
    "wof:name":"Pine Ridge Winery",
    "wof:placetype":"venue"
},
  "geometry": {"coordinates":[-122.421675,38.444629],"type":"Point"}
}