{
  "type": "Feature",
  "properties": {
    "addr:full":"4089 Oceanside Blvd Ste D Oceanside CA 92056",
    "addr:housenumber":"4089",
    "addr:postcode":"92056",
    "addr:street":"Oceanside Blvd Ste D",
    "iso:country":"US",
    "sg:address":"4089 Oceanside Blvd Ste D",
    "sg:city":"Oceanside",
    "sg:classifiers":[
        {
            "category":"Shopping",
            "subcategory":"Beauty & Cosmetics",
            "type":"Retail Goods"
        }
    ],
    "sg:phone":"+1 760 724 9434",
    "sg:postcode":"92056",
    "sg:province":"CA",
    "sg:tags":[
        "supply"
    ],
    "wof:name":"Odyssey Salon Services",
    "wof:placetype":"venue"
},
  "geometry": {"coordinates":[-117.28972899999999,33.205687],"type":"Point"}
}