{
  "type": "Feature",
  "properties": {
    "iso:country":"US",
    "sg:address":"1033 5th St",
    "sg:city":"Clovis",
    "sg:classifiers":[
        {
            "category":"Government",
            "subcategory":"Office",
            "type":"Public Place"
        }
    ],
    "sg:phone":"+1 559 324 2101",
    "sg:postcode":"93612",
    "sg:province":"CA",
    "sg:tags":[
        "city",
        "taxation"
    ],
    "sg:website":"www.ci.clovis.ca.us",
    "wof:name":"Clovis Finance Dept",
    "wof:placetype":"venue"
},
  "geometry": {"coordinates":[-119.694556,36.824022],"type":"Point"}
}