{
  "type": "Feature",
  "properties": {
    "iso:country":"US",
    "sg:address":"7702 Adwen St",
    "sg:city":"Downey",
    "sg:classifiers":[
        {
            "category":"Organizations",
            "subcategory":"Non-profit Organization",
            "type":"Services"
        }
    ],
    "sg:phone":"+1 562 862 8844",
    "sg:postcode":"90241",
    "sg:province":"CA",
    "sg:tags":[
        "charity",
        "foundations-educational",
        "philanthropic",
        "research"
    ],
    "wof:name":"Rabbit Rescue Inc",
    "wof:placetype":"venue"
},
  "geometry": {"coordinates":[-118.146854,33.941684],"type":"Point"}
}