{
  "type": "Feature",
  "properties": {
    "addr:full":"107 S Andreasen Dr Escondido CA 92029",
    "addr:housenumber":"107",
    "addr:postcode":"92029",
    "addr:street":"S Andreasen Dr",
    "iso:country":"US",
    "sg:address":"107 S Andreasen Dr",
    "sg:city":"Escondido",
    "sg:classifiers":[
        {
            "category":"Manufacturing",
            "subcategory":"Printing",
            "type":"Manufacturing & Wholesale Goods"
        }
    ],
    "sg:phone":"+1 760 747 7468",
    "sg:postcode":"92029",
    "sg:province":"CA",
    "sg:tags":[
        "commercial"
    ],
    "sg:website":"www.goprintworld.com",
    "wof:name":"Print World",
    "wof:placetype":"venue"
},
  "geometry": {"coordinates":[-117.110803,33.117145],"type":"Point"}
}