{
  "type": "Feature",
  "properties": {
    "iso:country":"US",
    "sg:address":"1942 University Ave",
    "sg:city":"Berkeley",
    "sg:classifiers":[
        {
            "category":"Professional",
            "subcategory":"Computer Services",
            "type":"Services"
        }
    ],
    "sg:phone":"+1 510 649 0600",
    "sg:postcode":"94704",
    "sg:province":"CA",
    "sg:tags":[
        "software"
    ],
    "wof:name":"Sure Analytics",
    "wof:placetype":"venue"
},
  "geometry": {"coordinates":[-122.272002,37.871698],"type":"Point"}
}