{
  "type": "Feature",
  "properties": {
    "addr:full":"5915 Kenneth Ave Apt 50 Carmichael CA 95608",
    "addr:housenumber":"5915;50",
    "addr:postcode":"95608",
    "addr:street":"Kenneth Ave Apt",
    "iso:country":"US",
    "sg:address":"5915 Kenneth Ave Apt 50",
    "sg:city":"Carmichael",
    "sg:classifiers":[
        {
            "category":"Retail",
            "subcategory":"Auto Rental",
            "type":"Services"
        }
    ],
    "sg:phone":"+1 916 488 8288",
    "sg:postcode":"95608",
    "sg:province":"CA",
    "sg:tags":[
        "car"
    ],
    "wof:name":"Mobileobdtech Inc",
    "wof:placetype":"venue"
},
  "geometry": {"coordinates":[-121.32778999999999,38.613497],"type":"Point"}
}