{
  "type": "Feature",
  "properties": {
    "addr:full":"3426 Whittier Blvd Los Angeles CA 90023",
    "addr:housenumber":"3426",
    "addr:postcode":"90023",
    "addr:street":"Whittier Blvd",
    "iso:country":"US",
    "sg:address":"3426 Whittier Blvd",
    "sg:city":"Los Angeles",
    "sg:classifiers":[
        {
            "category":"Food & Beverages",
            "subcategory":"Groceries & Convenience Stores",
            "type":"Retail Goods"
        }
    ],
    "sg:phone":"+1 323 263 8617",
    "sg:postcode":"90023",
    "sg:province":"CA",
    "wof:name":"Penny Discount",
    "wof:placetype":"venue"
},
  "geometry": {"coordinates":[-118.199997,34.0271],"type":"Point"}
}