{
  "type": "Feature",
  "properties": {
    "addr:full":"7929 Sitio Peral Carlsbad CA 92009",
    "addr:housenumber":"7929",
    "addr:postcode":"92009",
    "addr:street":"Sitio Peral",
    "iso:country":"US",
    "sg:address":"7929 Sitio Peral",
    "sg:city":"Carlsbad",
    "sg:classifiers":[
        {
            "category":"Home & Garden",
            "subcategory":"Home Furnishings",
            "type":"Retail Goods"
        }
    ],
    "sg:phone":"+1 760 633 1385",
    "sg:postcode":"92009",
    "sg:province":"CA",
    "wof:name":"Corian Creations",
    "wof:placetype":"venue"
},
  "geometry": {"coordinates":[-117.24955799999999,33.076696],"type":"Point"}
}