{
  "type": "Feature",
  "properties": {
    "addr:full":"31 Park Ave Monterey CA 93940",
    "addr:housenumber":"31",
    "addr:postcode":"93940",
    "addr:street":"Park Ave",
    "iso:country":"US",
    "sg:address":"31 Park Ave",
    "sg:city":"Monterey",
    "sg:classifiers":[
        {
            "category":"Retail",
            "subcategory":"Animal Services",
            "type":"Services"
        }
    ],
    "sg:phone":"+1 831 375 3646",
    "sg:postcode":"93940",
    "sg:province":"CA",
    "sg:tags":[
        "pet",
        "grooming",
        "washing"
    ],
    "wof:name":"Alta Vista Pet Salon",
    "wof:placetype":"venue"
},
  "geometry": {"coordinates":[-121.88218500000001,36.599783],"type":"Point"}
}