{
  "type": "Feature",
  "properties": {
    "addr:full":"1022 G St Reedley CA 93654",
    "addr:housenumber":"1022",
    "addr:postcode":"93654",
    "addr:street":"G St",
    "iso:country":"US",
    "sg:address":"1022 G St",
    "sg:city":"Reedley",
    "sg:classifiers":[
        {
            "category":"Shopping",
            "subcategory":"Used Merchandise",
            "type":"Retail Goods"
        }
    ],
    "sg:phone":"+1 559 638 7697",
    "sg:postcode":"93654",
    "sg:province":"CA",
    "sg:tags":[
        "shop",
        "thrift"
    ],
    "wof:name":"Nearly New Shop",
    "wof:placetype":"venue"
},
  "geometry": {"coordinates":[-119.451035,36.59666],"type":"Point"}
}