{
  "type": "Feature",
  "properties": {
    "iso:country":"US",
    "sg:address":"3035 Prospect Park Dr",
    "sg:city":"Rancho Cordova",
    "sg:classifiers":[
        {
            "category":"Professional",
            "type":"Services"
        }
    ],
    "sg:phone":"+1 916 861 0882",
    "sg:postcode":"95670",
    "sg:province":"CA",
    "wof:name":"Austel Inc",
    "wof:placetype":"venue"
},
  "geometry": {"coordinates":[-121.276293,38.591809],"type":"Point"}
}