{
  "type": "Feature",
  "properties": {
    "addr:full":"2125 E Cardella St Firebaugh CA 93622",
    "addr:housenumber":"2125",
    "addr:postcode":"93622",
    "addr:street":"E Cardella St",
    "iso:country":"US",
    "sg:address":"2125 E Cardella St",
    "sg:city":"Firebaugh",
    "sg:phone":"+1 559 659 2877",
    "sg:postcode":"93622",
    "sg:province":"CA",
    "sg:tags":[
        "farm"
    ],
    "wof:name":"Gilbert Coelho",
    "wof:placetype":"venue"
},
  "geometry": {"coordinates":[-120.443855,36.849671],"type":"Point"}
}