{
  "type": "Feature",
  "properties": {
    "iso:country":"US",
    "sg:address":"500 S Demaree St",
    "sg:city":"Visalia",
    "sg:classifiers":[
        {
            "category":"Restaurant",
            "type":"Food & Drink"
        }
    ],
    "sg:menulink":"http://www.allmenus.com/ca/visalia/171798-burger-king/menu/",
    "sg:phone":"+1 559 739 1084",
    "sg:postcode":"93277",
    "sg:province":"CA",
    "sg:tags":[
        "burger",
        "american"
    ],
    "wof:name":"Burger King",
    "wof:placetype":"venue"
},
  "geometry": {"coordinates":[-119.331701,36.326564],"type":"Point"}
}