{
  "type": "Feature",
  "properties": {
    "iso:country":"US",
    "sg:address":"1310 Griffith St",
    "sg:city":"San Francisco",
    "sg:classifiers":[
        {
            "category":"Building & Trades",
            "subcategory":"Construction",
            "type":"Services"
        }
    ],
    "sg:postcode":"94124",
    "sg:province":"CA",
    "sg:tags":[
        "painter"
    ],
    "sg:website":"sfbaypainting.com",
    "wof:name":"Clisham Painting",
    "wof:placetype":"venue"
},
  "geometry": {"coordinates":[-122.380596,37.726706],"type":"Point"}
}