{
  "type": "Feature",
  "properties": {
    "addr:full":"2260 S State St Ukiah CA 95482",
    "addr:housenumber":"2260",
    "addr:postcode":"ca 95482",
    "addr:street":"S State St",
    "iso:country":"US",
    "sg:address":"2260 S State St",
    "sg:city":"Ukiah",
    "sg:classifiers":[
        {
            "category":"Real Estate",
            "subcategory":"Real Estate Operator",
            "type":"Services"
        }
    ],
    "sg:phone":"+1 707 462 2027",
    "sg:postcode":"95482",
    "sg:province":"CA",
    "sg:tags":[
        "building",
        "apartment"
    ],
    "wof:name":"Rose Apartments",
    "wof:placetype":"venue"
},
  "geometry": {"coordinates":[-123.20226599999999,39.119774],"type":"Point"}
}