{
  "type": "Feature",
  "properties": {
    "iso:country":"US",
    "sg:address":"2260 S State St",
    "sg:city":"Ukiah",
    "sg:classifiers":[
        {
            "category":"Real Estate",
            "subcategory":"Real Estate Operator",
            "type":"Services"
        }
    ],
    "sg:phone":"+1 707 462 2027",
    "sg:postcode":"95482",
    "sg:province":"CA",
    "sg:tags":[
        "building",
        "apartment"
    ],
    "wof:name":"Rose Apartments",
    "wof:placetype":"venue"
},
  "geometry": {"coordinates":[-123.202266,39.119774],"type":"Point"}
}