{
  "type": "Feature",
  "properties": {
    "iso:country":"US",
    "sg:address":"9910 Magnolia Ave",
    "sg:city":"Riverside",
    "sg:classifiers":[
        {
            "category":"Restaurant",
            "type":"Food & Drink"
        }
    ],
    "sg:phone":"+1 951 688 2471",
    "sg:postcode":"92503",
    "sg:province":"CA",
    "wof:name":"George's Drive-In",
    "wof:placetype":"venue"
},
  "geometry": {"coordinates":[-117.454581,33.915756],"type":"Point"}
}