{
  "type": "Feature",
  "properties": {
    "addr:full":"416 W 4th St Santa Ana CA 92701",
    "addr:housenumber":"416",
    "addr:postcode":"92701",
    "addr:street":"W 4Th St",
    "iso:country":"US",
    "sg:address":"416 W 4th St",
    "sg:city":"Santa Ana",
    "sg:classifiers":[
        {
            "category":"Recreation",
            "subcategory":"Dance Hall",
            "type":"Entertainment"
        }
    ],
    "sg:postcode":"92701",
    "sg:province":"CA",
    "sg:tags":[
        "club"
    ],
    "sg:website":"www.VelvetOC.com",
    "wof:name":"Velvet Lounge",
    "wof:placetype":"venue"
},
  "geometry": {"coordinates":[-117.87158700000001,33.747973],"type":"Point"}
}