{
  "type": "Feature",
  "properties": {
    "iso:country":"US",
    "sg:address":"105 Alpine Ter",
    "sg:city":"San Francisco",
    "sg:classifiers":[
        {
            "category":"Professional",
            "type":"Services"
        }
    ],
    "sg:phone":"+1 415 701 9023",
    "sg:postcode":"94117",
    "sg:province":"CA",
    "sg:tags":[
        "establishment"
    ],
    "wof:name":"Nordan Inc",
    "wof:placetype":"venue"
},
  "geometry": {"coordinates":[-122.43723,37.767302],"type":"Point"}
}