{
  "type": "Feature",
  "properties": {
    "addr:full":"1120 W 135th St Gardena CA 90247",
    "addr:housenumber":"1120",
    "addr:postcode":"90247",
    "addr:street":"W 135Th St",
    "iso:country":"US",
    "sg:address":"1120 W 135th St",
    "sg:city":"Gardena",
    "sg:classifiers":[
        {
            "category":"Professional",
            "subcategory":"Business Services",
            "type":"Services"
        }
    ],
    "sg:phone":"+1 310 324 4404",
    "sg:postcode":"90247",
    "sg:province":"CA",
    "sg:tags":[
        "convention",
        "meeting",
        "facility"
    ],
    "wof:name":"Soest & Assoc",
    "wof:placetype":"venue"
},
  "geometry": {"coordinates":[-118.294524,33.909179],"type":"Point"}
}