{
  "type": "Feature",
  "properties": {
    "iso:country":"US",
    "sg:address":"1509 W 125th St",
    "sg:city":"Los Angeles",
    "sg:classifiers":[
        {
            "category":"Building & Trades",
            "subcategory":"Construction",
            "type":"Services"
        }
    ],
    "sg:phone":"+1 323 731 1783",
    "sg:postcode":"90047",
    "sg:province":"CA",
    "sg:tags":[
        "coping",
        "plastering",
        "tiling",
        "pool",
        "swimming"
    ],
    "wof:name":"ABC Pool",
    "wof:placetype":"venue"
},
  "geometry": {"coordinates":[-118.304378,33.919331],"type":"Point"}
}