{
  "type": "Feature",
  "properties": {
    "iso:country":"US",
    "sg:address":"10111 Old Placerville Rd",
    "sg:city":"Sacramento",
    "sg:classifiers":[
        {
            "category":"Professional",
            "subcategory":"Management & Consulting",
            "type":"Services"
        }
    ],
    "sg:phone":"+1 916 362 0372",
    "sg:postcode":"95827",
    "sg:province":"CA",
    "sg:tags":[
        "consultant",
        "construction"
    ],
    "wof:name":"Fite Development",
    "wof:placetype":"venue"
},
  "geometry": {"coordinates":[-121.316992,38.561317],"type":"Point"}
}