{
  "type": "Feature",
  "properties": {
    "iso:country":"US",
    "sg:address":"8520 National Blvd Suite 110",
    "sg:city":"Culver City",
    "sg:classifiers":[
        {
            "category":"Banks & Credit Unions",
            "subcategory":"Financial Services",
            "type":"Services"
        },
        {
            "category":"Utilities",
            "type":"Services"
        }
    ],
    "sg:phone":"+1 310 202 1392",
    "sg:postcode":"90232",
    "sg:province":"CA",
    "sg:tags":[
        "provider",
        "broker",
        "mortgage",
        "internet"
    ],
    "wof:name":"Media Temple",
    "wof:placetype":"venue"
},
  "geometry": {"coordinates":[-118.379577,34.026456],"type":"Point"}
}