{
  "type": "Feature",
  "properties": {
    "addr:full":"6669 Clark Rd Paradise CA 95969",
    "addr:housenumber":"6669",
    "addr:postcode":"95969",
    "addr:street":"Clark Rd",
    "iso:country":"US",
    "sg:address":"6669 Clark Rd",
    "sg:city":"Paradise",
    "sg:classifiers":[
        {
            "category":"Banks & Credit Unions",
            "subcategory":"Investment Brokerage",
            "type":"Services"
        }
    ],
    "sg:phone":"+1 530 877 5183",
    "sg:postcode":"95969",
    "sg:province":"CA",
    "sg:tags":[
        "security"
    ],
    "wof:name":"Wm Financial Inc",
    "wof:placetype":"venue"
},
  "geometry": {"coordinates":[-121.589364,39.780119],"type":"Point"}
}