{
  "type": "Feature",
  "properties": {
    "iso:country":"US",
    "sg:address":"2438 Peck Rd",
    "sg:city":"Whittier",
    "sg:classifiers":[
        {
            "category":"Manufacturing",
            "subcategory":"Rubber & Plastics",
            "type":"Manufacturing & Wholesale Goods"
        }
    ],
    "sg:phone":"+1 562 695 5686",
    "sg:postcode":"90601",
    "sg:province":"CA",
    "sg:tags":[
        "tires-wholesale",
        "manufacturer"
    ],
    "wof:name":"Trelleborg Wheel System",
    "wof:placetype":"venue"
},
  "geometry": {"coordinates":[-118.03718000000001,34.030319],"type":"Point"}
}