{
  "type": "Feature",
  "properties": {
    "addr:full":"300 Santa Rosa Ave Santa Rosa CA 95404",
    "addr:housenumber":"300",
    "addr:postcode":"95404",
    "addr:street":"Santa Rosa Ave",
    "iso:country":"US",
    "sg:address":"300 Santa Rosa Ave",
    "sg:city":"Santa Rosa",
    "sg:classifiers":[
        {
            "category":"Government",
            "subcategory":"Office",
            "type":"Public Place"
        }
    ],
    "sg:phone":"+1 707 543 3223",
    "sg:postcode":"95404",
    "sg:province":"CA",
    "sg:tags":[
        "city",
        "planning",
        "dev"
    ],
    "wof:name":"Zoning & Land Use",
    "wof:placetype":"venue"
},
  "geometry": {"coordinates":[-122.71198099999999,38.434934],"type":"Point"}
}