{
  "type": "Feature",
  "properties": {
    "iso:country":"US",
    "sg:address":"2609 G St",
    "sg:city":"Bakersfield",
    "sg:classifiers":[
        {
            "category":"Health Services",
            "subcategory":"Medical Lab",
            "type":"Services"
        }
    ],
    "sg:phone":"+1 661 323 1404",
    "sg:postcode":"93301",
    "sg:province":"CA",
    "sg:tags":[
        "laboratory"
    ],
    "wof:name":"Aztec Dental Laboratory",
    "wof:placetype":"venue"
},
  "geometry": {"coordinates":[-119.02238800000001,35.383793],"type":"Point"}
}