{
  "type": "Feature",
  "properties": {
    "addr:full":"6030 Morella Ave North Hollywood CA 91606",
    "addr:housenumber":"6030",
    "addr:postcode":"91606",
    "addr:street":"Morella Ave",
    "iso:country":"US",
    "sg:address":"6030 Morella Ave",
    "sg:city":"North Hollywood",
    "sg:classifiers":[
        {
            "category":"Professional",
            "subcategory":"Art Services",
            "type":"Services"
        }
    ],
    "sg:phone":"+1 818 761 0080",
    "sg:postcode":"91606",
    "sg:province":"CA",
    "sg:tags":[
        "graphic",
        "designer"
    ],
    "wof:name":"JCM Graphics LLC",
    "wof:placetype":"venue"
},
  "geometry": {"coordinates":[-118.389883,34.180671],"type":"Point"}
}