{
  "type": "Feature",
  "properties": {
    "addr:full":"21476 Silvertree Ln Trabuco Canyon CA 92679",
    "addr:housenumber":"21476",
    "addr:postcode":"92679",
    "addr:street":"Silvertree Ln",
    "iso:country":"US",
    "sg:address":"21476 Silvertree Ln",
    "sg:city":"Trabuco Canyon",
    "sg:classifiers":[
        {
            "category":"Manufacturing",
            "subcategory":"Chemicals & Compounds",
            "type":"Manufacturing & Wholesale Goods"
        }
    ],
    "sg:phone":"+1 949 589 1104",
    "sg:postcode":"92679",
    "sg:province":"CA",
    "sg:tags":[
        "preparation",
        "pharmaceutical",
        "mfg"
    ],
    "wof:name":"Colgate-Palmolive",
    "wof:placetype":"venue"
},
  "geometry": {"coordinates":[-117.564661,33.651094],"type":"Point"}
}