{
  "type": "Feature",
  "properties": {
    "addr:full":"3721 Fruitvale Ave Oakland CA 94602",
    "addr:housenumber":"3721",
    "addr:postcode":"94602",
    "addr:street":"Fruitvale Ave",
    "iso:country":"US",
    "sg:address":"3721 Fruitvale Ave",
    "sg:city":"Oakland",
    "sg:classifiers":[
        {
            "category":"Retail",
            "subcategory":"Repair Shop",
            "type":"Services"
        }
    ],
    "sg:phone":"+1 510 530 0808",
    "sg:postcode":"94602",
    "sg:province":"CA",
    "sg:tags":[
        "cleaner",
        "drain",
        "repairer",
        "sewer",
        "cleaning",
        "plumbing"
    ],
    "wof:name":"Piedmont Rooter Plumbing & Heating",
    "wof:placetype":"venue"
},
  "geometry": {"coordinates":[-122.214996,37.8032],"type":"Point"}
}