{
  "type": "Feature",
  "properties": {
    "iso:country":"US",
    "sg:address":"3860 Morrow Ln",
    "sg:city":"Chico",
    "sg:classifiers":[
        {
            "category":"Wholesale",
            "subcategory":"Machinery & Supplies",
            "type":"Manufacturing & Wholesale Goods"
        }
    ],
    "sg:phone":"+1 530 891 1602",
    "sg:postcode":"95928",
    "sg:province":"CA",
    "sg:tags":[
        "equipment",
        "layer",
        "establishment",
        "carpet"
    ],
    "wof:name":"Bruns Flooring Supply",
    "wof:placetype":"venue"
},
  "geometry": {"coordinates":[-121.786984,39.712652],"type":"Point"}
}