{
  "type": "Feature",
  "properties": {
    "iso:country":"US",
    "sg:address":"8626 Commerce Ave",
    "sg:city":"San Diego",
    "sg:classifiers":[
        {
            "category":"Manufacturing",
            "subcategory":"Textiles",
            "type":"Manufacturing & Wholesale Goods"
        }
    ],
    "sg:phone":"+1 858 549 3989",
    "sg:postcode":"92121",
    "sg:province":"CA",
    "sg:tags":[
        "curtain"
    ],
    "wof:name":"Draperies By Picazo Inc",
    "wof:placetype":"venue"
},
  "geometry": {"coordinates":[-117.167734,32.881166],"type":"Point"}
}