{
  "type": "Feature",
  "properties": {
    "iso:country":"US",
    "sg:address":"159 N Lester Dr",
    "sg:city":"Orange",
    "sg:classifiers":[
        {
            "category":"Wholesale",
            "subcategory":"Home Furnishings",
            "type":"Manufacturing & Wholesale Goods"
        }
    ],
    "sg:phone":"+1 714 997 5234",
    "sg:postcode":"92868",
    "sg:province":"CA",
    "wof:name":"California Great White Towels",
    "wof:placetype":"venue"
},
  "geometry": {"coordinates":[-117.864618,33.788619],"type":"Point"}
}