{
  "type": "Feature",
  "properties": {
    "iso:country":"US",
    "sg:address":"29588 Mission Blvd",
    "sg:city":"Hayward",
    "sg:classifiers":[
        {
            "category":"Autos & Motor Vehicles",
            "subcategory":"Auto Supplies",
            "type":"Retail Goods"
        }
    ],
    "sg:phone":"+1 510 887 2378",
    "sg:postcode":"94544",
    "sg:province":"CA",
    "sg:tags":[
        "battery",
        "batteries-storage"
    ],
    "wof:name":"America's Best Battery Co.",
    "wof:placetype":"venue"
},
  "geometry": {"coordinates":[-122.04761999999999,37.630369],"type":"Point"}
}