{
  "type": "Feature",
  "properties": {
    "addr:full":"5306 S Normandie Ave Los Angeles CA 90037",
    "addr:housenumber":"5306",
    "addr:postcode":"90037",
    "addr:street":"S Normandie Ave",
    "iso:country":"US",
    "sg:address":"5306 S Normandie Ave",
    "sg:city":"Los Angeles",
    "sg:classifiers":[
        {
            "category":"Organizations",
            "subcategory":"Religious Organization",
            "type":"Services"
        }
    ],
    "sg:phone":"+1 323 758 5384",
    "sg:postcode":"90037",
    "sg:province":"CA",
    "sg:tags":[
        "church"
    ],
    "wof:name":"Church Of God Santa Sion",
    "wof:placetype":"venue"
},
  "geometry": {"coordinates":[-118.300111,33.993282],"type":"Point"}
}