{
  "type": "Feature",
  "properties": {
    "addr:full":"4801 Wilshire Blvd Los Angeles CA 90010",
    "addr:housenumber":"4801",
    "addr:postcode":"90010",
    "addr:street":"Wilshire Blvd",
    "iso:country":"US",
    "sg:address":"4801 Wilshire Blvd",
    "sg:city":"Los Angeles",
    "sg:classifiers":[
        {
            "category":"Professional",
            "type":"Services"
        }
    ],
    "sg:phone":"+1 323 525 1009",
    "sg:postcode":"90010",
    "sg:province":"CA",
    "sg:tags":[
        "establishment"
    ],
    "wof:name":"VXO Partners LLC",
    "wof:placetype":"venue"
},
  "geometry": {"coordinates":[-118.334805,34.062042],"type":"Point"}
}