{
  "type": "Feature",
  "properties": {
    "iso:country":"US",
    "sg:address":"1 Post Street Suite 400",
    "sg:city":"San Francisco",
    "sg:classifiers":[
        {
            "category":"Banks & Credit Unions",
            "subcategory":"Financial Services",
            "type":"Services"
        }
    ],
    "sg:phone":"+1 415 397 2200",
    "sg:postcode":"94104",
    "sg:province":"CA",
    "sg:tags":[
        "broker",
        "mortgage"
    ],
    "wof:name":"Cohen Financial",
    "wof:placetype":"venue"
},
  "geometry": {"coordinates":[-122.402,37.791599],"type":"Point"}
}