{
  "type": "Feature",
  "properties": {
    "iso:country":"US",
    "sg:address":"138 E Pomegranate Ave",
    "sg:city":"Rialto",
    "sg:classifiers":[
        {
            "category":"Professional",
            "type":"Services"
        }
    ],
    "sg:phone":"+1 909 875 2462",
    "sg:postcode":"92377",
    "sg:province":"CA",
    "wof:name":"Onesimo Corral",
    "wof:placetype":"venue"
},
  "geometry": {"coordinates":[-117.371836,34.140396],"type":"Point"}
}