{
  "type": "Feature",
  "properties": {
    "iso:country":"US",
    "sg:address":"74900 Hwy 111",
    "sg:city":"Indian Wells",
    "sg:classifiers":[
        {
            "category":"Wholesale",
            "subcategory":"Office Equipment",
            "type":"Manufacturing & Wholesale Goods"
        }
    ],
    "sg:phone":"+1 760 776 5954",
    "sg:postcode":"92210",
    "sg:province":"CA",
    "sg:tags":[
        "credit",
        "system",
        "card"
    ],
    "sg:website":"www.transpayprocessing.com",
    "wof:name":"Transpay Inc",
    "wof:placetype":"venue"
},
  "geometry": {"coordinates":[-116.35632,33.721402],"type":"Point"}
}