{
  "type": "Feature",
  "properties": {
    "addr:full":"6633 Foothill Blvd Oakland CA 94605",
    "addr:housenumber":"6633",
    "addr:postcode":"94605",
    "addr:street":"Foothill Blvd",
    "iso:country":"US",
    "sg:address":"6633 Foothill Blvd",
    "sg:city":"Oakland",
    "sg:classifiers":[
        {
            "category":"Professional",
            "type":"Services"
        }
    ],
    "sg:phone":"+1 510 261 6684",
    "sg:postcode":"94605",
    "sg:province":"CA",
    "sg:tags":[
        "establishment"
    ],
    "wof:name":"Lane Mac Arthur",
    "wof:placetype":"venue"
},
  "geometry": {"coordinates":[-122.180261,37.770191],"type":"Point"}
}