{
  "type": "Feature",
  "properties": {
    "iso:country":"US",
    "sg:address":"2831 G St",
    "sg:city":"Sacramento",
    "sg:classifiers":[
        {
            "category":"Professional",
            "subcategory":"Accounting & Tax Preparation",
            "type":"Services"
        }
    ],
    "sg:phone":"+1 916 447 0197",
    "sg:postcode":"95816",
    "sg:province":"CA",
    "sg:tags":[
        "accountant"
    ],
    "wof:name":"Jay Brockman CPA",
    "wof:placetype":"venue"
},
  "geometry": {"coordinates":[-121.466742,38.576944],"type":"Point"}
}