{
  "type": "Feature",
  "properties": {
    "iso:country":"US",
    "sg:address":"8290 Belvedere Ave",
    "sg:city":"Sacramento",
    "sg:classifiers":[
        {
            "category":"Building & Trades",
            "subcategory":"Construction",
            "type":"Services"
        }
    ],
    "sg:phone":"+1 916 456 3007",
    "sg:postcode":"95826",
    "sg:province":"CA",
    "sg:tags":[
        "general",
        "contractor"
    ],
    "wof:name":"Nu Construction",
    "wof:placetype":"venue"
},
  "geometry": {"coordinates":[-121.403093,38.53787],"type":"Point"}
}