{
  "type": "Feature",
  "properties": {
    "addr:full":"2441 N 10th Ave Hanford CA 93230",
    "addr:housenumber":"2441",
    "addr:postcode":"ca 93230",
    "addr:street":"N 10Th Ave",
    "iso:country":"US",
    "sg:address":"2441 N 10th Ave",
    "sg:city":"Hanford",
    "sg:classifiers":[
        {
            "category":"Education",
            "subcategory":"Special Training",
            "type":"Public Place"
        }
    ],
    "sg:phone":"+1 559 585 8885",
    "sg:postcode":"93230",
    "sg:province":"CA",
    "sg:tags":[
        "center"
    ],
    "wof:name":"Sunshine Friend Learning Ctr",
    "wof:placetype":"venue"
},
  "geometry": {"coordinates":[-119.63701399999999,36.356111],"type":"Point"}
}