{
  "type": "Feature",
  "properties": {
    "iso:country":"US",
    "sg:address":"450 N Abby St",
    "sg:city":"Fresno",
    "sg:classifiers":[
        {
            "category":"Autos & Motor Vehicles",
            "subcategory":"Automobile Sales",
            "type":"Retail Goods"
        }
    ],
    "sg:phone":"+1 559 412 8374",
    "sg:postcode":"93701",
    "sg:province":"CA",
    "sg:tags":[
        "new",
        "used",
        "car"
    ],
    "wof:name":"Kms Cars",
    "wof:placetype":"venue"
},
  "geometry": {"coordinates":[-119.789394,36.749481],"type":"Point"}
}