{
  "type": "Feature",
  "properties": {
    "iso:country":"US",
    "sg:address":"1951 Chailly Dr",
    "sg:city":"Chula Vista",
    "sg:classifiers":[
        {
            "category":"Professional",
            "type":"Services"
        }
    ],
    "sg:phone":"+1 619 656 8188",
    "sg:postcode":"91913",
    "sg:province":"CA",
    "wof:name":"Cristina Campbell Di",
    "wof:placetype":"venue"
},
  "geometry": {"coordinates":[-116.972099,32.625794],"type":"Point"}
}