{
  "type": "Feature",
  "properties": {
    "addr:full":"2689 Marsh Dr San Ramon CA 94583",
    "addr:housenumber":"2689",
    "addr:postcode":"94583",
    "addr:street":"Marsh Dr",
    "iso:country":"US",
    "sg:address":"2689 Marsh Dr",
    "sg:city":"San Ramon",
    "sg:classifiers":[
        {
            "category":"Retail",
            "subcategory":"Animal Services",
            "type":"Services"
        }
    ],
    "sg:phone":"+1 925 324 5759",
    "sg:postcode":"94583",
    "sg:province":"CA",
    "sg:tags":[
        "training",
        "dog"
    ],
    "wof:name":"California Canine Academy",
    "wof:placetype":"venue"
},
  "geometry": {"coordinates":[-121.979105,37.766984],"type":"Point"}
}