{
  "type": "Feature",
  "properties": {
    "addr:full":"120 Briggs Ranch Dr Folsom CA 95630",
    "addr:housenumber":"120",
    "addr:postcode":"95630",
    "addr:street":"Briggs Ranch Dr",
    "iso:country":"US",
    "sg:address":"120 Briggs Ranch Dr",
    "sg:city":"Folsom",
    "sg:classifiers":[
        {
            "category":"Home & Garden",
            "subcategory":"Home Furnishings",
            "type":"Retail Goods"
        }
    ],
    "sg:phone":"+1 916 985 3444",
    "sg:postcode":"95630",
    "sg:province":"CA",
    "sg:tags":[
        "curtain",
        "made",
        "drapery"
    ],
    "wof:name":"Window Fashions By Larry",
    "wof:placetype":"venue"
},
  "geometry": {"coordinates":[-121.140269,38.690501],"type":"Point"}
}