{
  "type": "Feature",
  "properties": {
    "iso:country":"US",
    "sg:address":"395 2nd St",
    "sg:city":"Laguna Beach",
    "sg:classifiers":[
        {
            "category":"Professional",
            "subcategory":"Advertising",
            "type":"Services"
        }
    ],
    "sg:phone":"+1 949 376 5101",
    "sg:postcode":"92651",
    "sg:province":"CA",
    "wof:name":"OCHOUSERENTALS.COM",
    "wof:placetype":"venue"
},
  "geometry": {"coordinates":[-117.78202400000001,33.543943],"type":"Point"}
}