{
  "type": "Feature",
  "properties": {
    "addr:full":"1416 N Brand Blvd Glendale CA 91202",
    "addr:housenumber":"1416",
    "addr:postcode":"91202",
    "addr:street":"N Brand Blvd",
    "iso:country":"US",
    "sg:address":"1416 N Brand Blvd",
    "sg:city":"Glendale",
    "sg:classifiers":[
        {
            "category":"Manufacturing",
            "subcategory":"Textiles",
            "type":"Manufacturing & Wholesale Goods"
        }
    ],
    "sg:phone":"+1 818 247 0506",
    "sg:postcode":"91202",
    "sg:province":"CA",
    "sg:tags":[
        "mill",
        "thread"
    ],
    "wof:name":"Devoiddesigns",
    "wof:placetype":"venue"
},
  "geometry": {"coordinates":[-118.255088,34.167871],"type":"Point"}
}