{
  "type": "Feature",
  "properties": {
    "addr:full":"275 San Clemente St Ventura CA 93001",
    "addr:housenumber":"275",
    "addr:postcode":"93001",
    "addr:street":"San Clemente St",
    "iso:country":"US",
    "sg:address":"275 San Clemente St",
    "sg:city":"Ventura",
    "sg:classifiers":[
        {
            "category":"Real Estate",
            "subcategory":"Architect",
            "type":"Services"
        }
    ],
    "sg:phone":"+1 805 653 5088",
    "sg:postcode":"93001",
    "sg:province":"CA",
    "wof:name":"Arketype Inc Architects",
    "wof:placetype":"venue"
},
  "geometry": {"coordinates":[-119.26931,34.273948],"type":"Point"}
}