{
  "type": "Feature",
  "properties": {
    "addr:full":"1330 10th Street Arcata CA 95521",
    "addr:housenumber":"1330",
    "addr:postcode":"95521",
    "addr:street":"10Th Street",
    "iso:country":"US",
    "sg:address":"1330 10th Street",
    "sg:city":"Arcata",
    "sg:classifiers":[
        {
            "category":"Shopping",
            "subcategory":"Antiques",
            "type":"Retail Goods"
        },
        {
            "category":"Professional",
            "subcategory":"Art Services",
            "type":"Services"
        },
        {
            "category":"Manufacturing",
            "subcategory":"Furniture",
            "type":"Manufacturing & Wholesale Goods"
        },
        {
            "category":"Manufacturing",
            "subcategory":"Glass & Minerals",
            "type":"Manufacturing & Wholesale Goods"
        },
        {
            "category":"Building & Trades",
            "subcategory":"Construction",
            "type":"Services"
        }
    ],
    "sg:phone":"+1 707 825 9663",
    "sg:postcode":"95521",
    "sg:province":"CA",
    "sg:tags":[
        "repair",
        "designer",
        "leaded-commercial",
        "builder",
        "stained",
        "carpenter",
        "custom",
        "restoration",
        "reproduction"
    ],
    "sg:website":"http://www.dkcustomdesign.com",
    "wof:name":"Kelley David Woodworking",
    "wof:placetype":"venue"
},
  "geometry": {"coordinates":[-124.091866,40.871036],"type":"Point"}
}