{
  "type": "Feature",
  "properties": {
    "iso:country":"US",
    "sg:address":"1053 Eastridge Dr",
    "sg:city":"Napa",
    "sg:classifiers":[
        {
            "category":"Retail",
            "subcategory":"Repair Shop",
            "type":"Services"
        }
    ],
    "sg:phone":"+1 707 257 7200",
    "sg:postcode":"94558",
    "sg:province":"CA",
    "sg:tags":[
        "cleaners",
        "parts",
        "vacuum"
    ],
    "wof:name":"Rainbow Clean-Air",
    "wof:placetype":"venue"
},
  "geometry": {"coordinates":[-122.182326,38.515135],"type":"Point"}
}