{
  "type": "Feature",
  "properties": {
    "addr:full":"7476 3rd Ave Hesperia CA 92345",
    "addr:housenumber":"7476",
    "addr:postcode":"92345",
    "addr:street":"3Rd Ave",
    "iso:country":"US",
    "sg:address":"7476 3rd Ave",
    "sg:city":"Hesperia",
    "sg:classifiers":[
        {
            "category":"Freight",
            "type":"Transportation"
        }
    ],
    "sg:phone":"+1 760 244 4780",
    "sg:postcode":"92345",
    "sg:province":"CA",
    "sg:tags":[
        "operator",
        "local",
        "trucking"
    ],
    "wof:name":"RE Jansen Trucking Inc",
    "wof:placetype":"venue"
},
  "geometry": {"coordinates":[-117.314322,34.386505],"type":"Point"}
}