{
  "type": "Feature",
  "properties": {
    "iso:country":"US",
    "sg:address":"5442 Thornburn St",
    "sg:city":"Los Angeles",
    "sg:classifiers":[
        {
            "category":"Real Estate",
            "subcategory":"Real Estate Operator",
            "type":"Services"
        }
    ],
    "sg:phone":"+1 310 641 4999",
    "sg:postcode":"90045",
    "sg:province":"CA",
    "sg:tags":[
        "apartment"
    ],
    "wof:name":"Thornburn Apartments",
    "wof:placetype":"venue"
},
  "geometry": {"coordinates":[-118.37548,33.971868],"type":"Point"}
}