{
  "type": "Feature",
  "properties": {
    "addr:full":"370 Airpark Rd Atwater CA 95301",
    "addr:housenumber":"370",
    "addr:postcode":"95301",
    "addr:street":"Airpark Rd",
    "iso:country":"US",
    "sg:address":"370 Airpark Rd",
    "sg:city":"Atwater",
    "sg:classifiers":[
        {
            "category":"Home & Garden",
            "subcategory":"Furniture",
            "type":"Retail Goods"
        }
    ],
    "sg:phone":"+1 209 358 6286",
    "sg:postcode":"95301",
    "sg:province":"CA",
    "sg:tags":[
        "top",
        "counter"
    ],
    "wof:name":"Ira Howe Ceramic Tile",
    "wof:placetype":"venue"
},
  "geometry": {"coordinates":[-120.603515,37.336965],"type":"Point"}
}