{
  "type": "Feature",
  "properties": {
    "addr:full":"110 E 15th Street Los Angeles CA 90015",
    "addr:housenumber":"110",
    "addr:postcode":"90015",
    "addr:street":"E 15Th Street",
    "iso:country":"US",
    "sg:address":"110 E 15th Street",
    "sg:city":"Los Angeles",
    "sg:classifiers":[
        {
            "category":"Shopping",
            "subcategory":"Clothing, Apparel, & Fashions",
            "type":"Retail Goods"
        }
    ],
    "sg:phone":"+1 213 748 9460",
    "sg:postcode":"90015",
    "sg:province":"CA",
    "sg:tags":[
        "clothing",
        "women's"
    ],
    "wof:name":"Real Outlet",
    "wof:placetype":"venue"
},
  "geometry": {"coordinates":[-118.26154200000001,34.033879],"type":"Point"}
}