{
  "type": "Feature",
  "properties": {
    "addr:full":"6405 Shattuck Ave Oakland CA 94609",
    "addr:housenumber":"6405",
    "addr:postcode":"94609",
    "addr:street":"Shattuck Ave",
    "iso:country":"US",
    "sg:address":"6405 Shattuck Ave",
    "sg:city":"Oakland",
    "sg:classifiers":[
        {
            "category":"Home & Garden",
            "subcategory":"Building Materials",
            "type":"Retail Goods"
        }
    ],
    "sg:phone":"+1 510 601 8100",
    "sg:postcode":"94609",
    "sg:province":"CA",
    "sg:tags":[
        "repair",
        "plate",
        "auto",
        "glass",
        "window",
        "mirror"
    ],
    "wof:name":"Cal Glass",
    "wof:placetype":"venue"
},
  "geometry": {"coordinates":[-122.26599899999999,37.8498],"type":"Point"}
}