{
  "type": "Feature",
  "properties": {
    "addr:full":"1050 OAKVILLE CROSS Yountville CA 94599",
    "addr:housenumber":"1050",
    "addr:postcode":"ca 94599",
    "addr:street":"Oakville Cross",
    "iso:country":"US",
    "sg:address":"1050 OAKVILLE CROSS",
    "sg:city":"Yountville",
    "sg:classifiers":[
        {
            "category":"Personal",
            "subcategory":"Beauty Salon",
            "type":"Services"
        },
        {
            "category":"Food & Beverages",
            "subcategory":"Liquor & Beverages",
            "type":"Retail Goods"
        },
        {
            "category":"Wholesale",
            "subcategory":"Wine & Distilled Alcoholic Beverages",
            "type":"Manufacturing & Wholesale Goods"
        }
    ],
    "sg:phone":"+1 707 967 3500",
    "sg:postcode":"94599",
    "sg:province":"CA",
    "sg:tags":[
        "broker"
    ],
    "wof:name":"Swanson Vineyards",
    "wof:placetype":"venue"
},
  "geometry": {"coordinates":[-122.360489,38.399052],"type":"Point"}
}