{
  "type": "Feature",
  "properties": {
    "addr:full":"5119 Canterbury Dr San Diego CA 92116",
    "addr:housenumber":"5119",
    "addr:postcode":"92116",
    "addr:street":"Canterbury Dr",
    "iso:country":"US",
    "sg:address":"5119 Canterbury Dr",
    "sg:city":"San Diego",
    "sg:classifiers":[
        {
            "category":"Real Estate",
            "subcategory":"Real Estate Operator",
            "type":"Services"
        }
    ],
    "sg:phone":"+1 619 284 7752",
    "sg:postcode":"92116",
    "sg:province":"CA",
    "sg:tags":[
        "property",
        "lessor"
    ],
    "wof:name":"Kobusch Property Management",
    "wof:placetype":"venue"
},
  "geometry": {"coordinates":[-117.10894,32.7706],"type":"Point"}
}