{
  "type": "Feature",
  "properties": {
    "addr:full":"560 Pacific Ave San Francisco CA 94133",
    "addr:housenumber":"560",
    "addr:postcode":"94133",
    "addr:street":"Pacific Ave",
    "iso:country":"US",
    "sg:address":"560 Pacific Ave",
    "sg:city":"San Francisco",
    "sg:classifiers":[
        {
            "category":"Professional",
            "subcategory":"Computer Services",
            "type":"Services"
        }
    ],
    "sg:phone":"+1 415 318 4395",
    "sg:postcode":"94133",
    "sg:province":"CA",
    "sg:website":"www.treeaxis.com",
    "wof:name":"Tree-Axis",
    "wof:placetype":"venue"
},
  "geometry": {"coordinates":[-122.404606,37.797262],"type":"Point"}
}