{
  "type": "Feature",
  "properties": {
    "iso:country":"US",
    "sg:address":"6749 Stanley Ave",
    "sg:city":"Carmichael",
    "sg:phone":"+1 916 944 0653",
    "sg:postcode":"95608",
    "sg:province":"CA",
    "sg:tags":[
        "farm",
        "wheat"
    ],
    "wof:name":"Wellman Family Farm",
    "wof:placetype":"venue"
},
  "geometry": {"coordinates":[-121.30991299999999,38.622039],"type":"Point"}
}