{
  "type": "Feature",
  "properties": {
    "addr:full":"519 W Chapman Ave Anaheim CA 92802",
    "addr:housenumber":"519",
    "addr:postcode":"92802",
    "addr:street":"W Chapman Ave",
    "iso:country":"US",
    "sg:address":"519 W Chapman Ave",
    "sg:city":"Anaheim",
    "sg:classifiers":[
        {
            "category":"Retail",
            "subcategory":"Photofinishing",
            "type":"Services"
        }
    ],
    "sg:phone":"+1 714 971 1071",
    "sg:postcode":"92802",
    "sg:province":"CA",
    "sg:tags":[
        "photo",
        "finishing"
    ],
    "wof:name":"Anaheim Photo Lab & Studio",
    "wof:placetype":"venue"
},
  "geometry": {"coordinates":[-118.032779,33.788453],"type":"Point"}
}