{
  "type": "Feature",
  "properties": {
    "iso:country":"US",
    "sg:address":"4703 York Blvd",
    "sg:city":"Los Angeles",
    "sg:classifiers":[
        {
            "category":"Wholesale",
            "subcategory":"Auto Parts",
            "type":"Manufacturing & Wholesale Goods"
        }
    ],
    "sg:phone":"+1 323 255 5053",
    "sg:postcode":"90042",
    "sg:province":"CA",
    "wof:name":"Mixteca",
    "wof:placetype":"venue"
},
  "geometry": {"coordinates":[-118.212086,34.122551],"type":"Point"}
}