{
  "type": "Feature",
  "properties": {
    "iso:country":"US",
    "sg:address":"4513 Cornfield Way",
    "sg:city":"Elk Grove",
    "sg:classifiers":[
        {
            "category":"Professional",
            "subcategory":"Management & Consulting",
            "type":"Services"
        }
    ],
    "sg:phone":"+1 916 393 1603",
    "sg:postcode":"95758",
    "sg:province":"CA",
    "sg:tags":[
        "consultant",
        "business"
    ],
    "wof:name":"Debra J Crumpton & Assoc Inc",
    "wof:placetype":"venue"
},
  "geometry": {"coordinates":[-121.45310000000001,38.432332],"type":"Point"}
}