{
  "type": "Feature",
  "properties": {
    "iso:country":"US",
    "sg:address":"12351 Marshall Ave",
    "sg:city":"Chino",
    "sg:classifiers":[
        {
            "category":"Retail",
            "subcategory":"Animal Services",
            "type":"Services"
        }
    ],
    "sg:phone":"+1 909 627 0140",
    "sg:postcode":"91710",
    "sg:province":"CA",
    "sg:tags":[
        "pet"
    ],
    "wof:name":"Pet King Enterprises",
    "wof:placetype":"venue"
},
  "geometry": {"coordinates":[-117.691516,34.028723],"type":"Point"}
}