{
  "type": "Feature",
  "properties": {
    "addr:full":"541 Cowper St Palo Alto CA 94301",
    "addr:housenumber":"541",
    "addr:postcode":"94301",
    "addr:street":"Cowper St",
    "iso:country":"US",
    "sg:address":"541 Cowper St",
    "sg:city":"Palo Alto",
    "sg:classifiers":[
        {
            "category":"Social Services",
            "subcategory":"Job Training",
            "type":"Services"
        }
    ],
    "sg:phone":"+1 650 322 2882",
    "sg:postcode":"94301",
    "sg:province":"CA",
    "sg:tags":[
        "rehabilitation"
    ],
    "wof:name":"Tyler Wilson Certified Hand",
    "wof:placetype":"venue"
},
  "geometry": {"coordinates":[-122.158625,37.448043],"type":"Point"}
}