{
  "type": "Feature",
  "properties": {
    "addr:full":"909 Hyde Street Ofc San Francisco CA 94109",
    "addr:housenumber":"909",
    "addr:postcode":"94109",
    "addr:street":"Hyde Street",
    "iso:country":"US",
    "sg:address":"909 Hyde Street Ofc",
    "sg:city":"San Francisco",
    "sg:classifiers":[
        {
            "category":"Health Services",
            "subcategory":"Doctor",
            "type":"Services"
        }
    ],
    "sg:phone":"+1 415 474 3668",
    "sg:postcode":"94109",
    "sg:province":"CA",
    "sg:tags":[
        "podiatrist"
    ],
    "wof:name":"Wolff Lesley J DPM",
    "wof:placetype":"venue"
},
  "geometry": {"coordinates":[-122.417,37.7892],"type":"Point"}
}