{
  "type": "Feature",
  "properties": {
    "addr:full":"9070 Artesia Blvd Bellflower CA 90706",
    "addr:housenumber":"9070",
    "addr:postcode":"90706",
    "addr:street":"Artesia Blvd",
    "iso:country":"US",
    "sg:address":"9070 Artesia Blvd",
    "sg:city":"Bellflower",
    "sg:classifiers":[
        {
            "category":"Manufacturing",
            "subcategory":"Printing",
            "type":"Manufacturing & Wholesale Goods"
        }
    ],
    "sg:phone":"+1 562 804 6202",
    "sg:postcode":"90706",
    "sg:province":"CA",
    "sg:tags":[
        "lithographic",
        "commercial"
    ],
    "wof:name":"A&G Printing",
    "wof:placetype":"venue"
},
  "geometry": {"coordinates":[-118.141684,33.874672],"type":"Point"}
}