{
  "type": "Feature",
  "properties": {
    "addr:full":"23456 Hawthorne Blvd Ste 130 Torrance CA 90505",
    "addr:housenumber":"23456",
    "addr:postcode":"90505",
    "addr:street":"Hawthorne Blvd Ste 130",
    "iso:country":"US",
    "sg:address":"23456 Hawthorne Blvd Ste 130",
    "sg:city":"Torrance",
    "sg:classifiers":[
        {
            "category":"Professional",
            "subcategory":"Lawyer & Legal Services",
            "type":"Services"
        }
    ],
    "sg:phone":"+1 310 378 6360",
    "sg:postcode":"90505",
    "sg:province":"CA",
    "wof:name":"Bistline & Cohoon",
    "wof:placetype":"venue"
},
  "geometry": {"coordinates":[-118.350998,33.812901],"type":"Point"}
}