{
  "type": "Feature",
  "properties": {
    "addr:full":"355 E Empire St San Jose CA 95112",
    "addr:housenumber":"355",
    "addr:postcode":"95112",
    "addr:street":"E Empire St",
    "iso:country":"US",
    "sg:address":"355 E Empire St",
    "sg:city":"San Jose",
    "sg:classifiers":[
        {
            "category":"Home & Garden",
            "subcategory":"Household Appliances",
            "type":"Retail Goods"
        }
    ],
    "sg:phone":"+1 408 295 7626",
    "sg:postcode":"95112",
    "sg:province":"CA",
    "sg:tags":[
        "repair"
    ],
    "wof:name":"Minh Hoa Appliances",
    "wof:placetype":"venue"
},
  "geometry": {"coordinates":[-121.889,37.348499],"type":"Point"}
}