{
  "type": "Feature",
  "properties": {
    "addr:full":"13230 Evening Creek Dr San Diego CA 92128",
    "addr:housenumber":"13230",
    "addr:postcode":"92128",
    "addr:street":"Evening Creek Dr",
    "iso:country":"US",
    "sg:address":"13230 Evening Creek Dr",
    "sg:city":"San Diego",
    "sg:classifiers":[
        {
            "category":"Real Estate",
            "subcategory":"Real Estate Agent",
            "type":"Services"
        }
    ],
    "sg:phone":"+1 858 485 5100",
    "sg:postcode":"92128",
    "sg:province":"CA",
    "wof:name":"Shea Realty",
    "wof:placetype":"venue"
},
  "geometry": {"coordinates":[-117.094814,32.96061],"type":"Point"}
}