{
  "type": "Feature",
  "properties": {
    "iso:country":"US",
    "sg:address":"343 Coral Cir",
    "sg:city":"El Segundo",
    "sg:classifiers":[
        {
            "category":"Manufacturing",
            "subcategory":"Signs",
            "type":"Manufacturing & Wholesale Goods"
        }
    ],
    "sg:phone":"+1 310 726 2150",
    "sg:postcode":"90245",
    "sg:province":"CA",
    "sg:tags":[
        "merchandising",
        "store",
        "display"
    ],
    "wof:name":"White Plus Image Design",
    "wof:placetype":"venue"
},
  "geometry": {"coordinates":[-118.384712,33.913071],"type":"Point"}
}