{
  "type": "Feature",
  "properties": {
    "iso:country":"US",
    "sg:address":"2544 Elden Ave",
    "sg:city":"Costa Mesa",
    "sg:classifiers":[
        {
            "category":"Professional",
            "subcategory":"Management & Consulting",
            "type":"Services"
        }
    ],
    "sg:phone":"+1 949 515 0200",
    "sg:postcode":"92627",
    "sg:province":"CA",
    "sg:tags":[
        "consultant",
        "safety"
    ],
    "wof:name":"Dynamic Safety Inc",
    "wof:placetype":"venue"
},
  "geometry": {"coordinates":[-117.89721,33.65987],"type":"Point"}
}