{
  "type": "Feature",
  "properties": {
    "addr:full":"1635 Elks Club Dr South Lake Tahoe CA 96150",
    "addr:housenumber":"1635",
    "addr:postcode":"96150",
    "addr:street":"Elks Club Dr",
    "iso:country":"US",
    "sg:address":"1635 Elks Club Dr",
    "sg:city":"South Lake Tahoe",
    "sg:classifiers":[
        {
            "category":"Organizations",
            "subcategory":"Community Association",
            "type":"Services"
        }
    ],
    "sg:phone":"+1 530 577 2094",
    "sg:postcode":"96150",
    "sg:province":"CA",
    "sg:tags":[
        "fraternal"
    ],
    "wof:name":"Elks Lodge",
    "wof:placetype":"venue"
},
  "geometry": {"coordinates":[-120.005582,38.87432],"type":"Point"}
}