{
  "type": "Feature",
  "properties": {
    "addr:full":"1871 Merced Ave South El Monte CA 91733",
    "addr:housenumber":"1871",
    "addr:postcode":"91733",
    "addr:street":"Merced Ave",
    "iso:country":"US",
    "sg:address":"1871 Merced Ave",
    "sg:city":"South El Monte",
    "sg:classifiers":[
        {
            "category":"Manufacturing",
            "subcategory":"Metals",
            "type":"Manufacturing & Wholesale Goods"
        }
    ],
    "sg:phone":"+1 626 579 2595",
    "sg:postcode":"91733",
    "sg:province":"CA",
    "sg:tags":[
        "polishing"
    ],
    "wof:name":"J & J Metal Finishing",
    "wof:placetype":"venue"
},
  "geometry": {"coordinates":[-118.05136,34.051522],"type":"Point"}
}