{
  "type": "Feature",
  "properties": {
    "iso:country":"US",
    "sg:address":"73941 Hwy 111",
    "sg:city":"Palm Desert",
    "sg:classifiers":[
        {
            "category":"Shopping",
            "subcategory":"Hobbies, Toys, & Games",
            "type":"Retail Goods"
        },
        {
            "category":"Recreation",
            "type":"Entertainment"
        }
    ],
    "sg:phone":"+1 760 346 4472",
    "sg:postcode":"92260",
    "sg:province":"CA",
    "sg:tags":[
        "merchandise",
        "doll"
    ],
    "wof:name":"Bizzy Handz",
    "wof:placetype":"venue"
},
  "geometry": {"coordinates":[-116.375784,33.72123],"type":"Point"}
}