{
  "type": "Feature",
  "properties": {
    "addr:full":"521 Brown St Healdsburg CA 95448",
    "addr:housenumber":"521",
    "addr:postcode":"95448",
    "addr:street":"Brown St",
    "iso:country":"US",
    "sg:address":"521 Brown St",
    "sg:city":"Healdsburg",
    "sg:classifiers":[
        {
            "category":"Autos & Motor Vehicles",
            "subcategory":"Boat Sales",
            "type":"Retail Goods"
        }
    ],
    "sg:phone":"+1 707 473 9283",
    "sg:postcode":"95448",
    "sg:province":"CA",
    "sg:tags":[
        "canoe"
    ],
    "wof:name":"A Standing Wave Kayaking",
    "wof:placetype":"venue"
},
  "geometry": {"coordinates":[-122.864631,38.615495],"type":"Point"}
}