{
  "type": "Feature",
  "properties": {
    "iso:country":"US",
    "sg:address":"385 S Vine St",
    "sg:city":"Anaheim",
    "sg:classifiers":[
        {
            "category":"Real Estate",
            "subcategory":"Real Estate Operator",
            "type":"Services"
        }
    ],
    "sg:phone":"+1 714 817 1902",
    "sg:postcode":"92805",
    "sg:province":"CA",
    "sg:tags":[
        "apartment"
    ],
    "wof:name":"The Vineyard Town Homes",
    "wof:placetype":"venue"
},
  "geometry": {"coordinates":[-117.904951,33.834208],"type":"Point"}
}