{
  "type": "Feature",
  "properties": {
    "iso:country":"US",
    "sg:address":"250 Bridge St",
    "sg:city":"Yuba City",
    "sg:classifiers":[
        {
            "category":"Autos & Motor Vehicles",
            "subcategory":"Automobile Sales",
            "type":"Retail Goods"
        }
    ],
    "sg:phone":"+1 530 671 4050",
    "sg:postcode":"95991",
    "sg:province":"CA",
    "sg:tags":[
        "car",
        "dealer"
    ],
    "wof:name":"Top Notch Auto Sales",
    "wof:placetype":"venue"
},
  "geometry": {"coordinates":[-121.60954099999999,39.137377],"type":"Point"}
}