{
  "type": "Feature",
  "properties": {
    "iso:country":"US",
    "sg:address":"3091 Alhambra Dr",
    "sg:city":"Cameron Park",
    "sg:classifiers":[
        {
            "category":"Health Services",
            "subcategory":"Chiropractor",
            "type":"Services"
        }
    ],
    "sg:phone":"+1 530 677 4468",
    "sg:postcode":"95682",
    "sg:province":"CA",
    "wof:name":"Cameron Park Chiropractic",
    "wof:placetype":"venue"
},
  "geometry": {"coordinates":[-120.989116,38.686501],"type":"Point"}
}