{
  "type": "Feature",
  "properties": {
    "addr:full":"125 N Jackson Avenue Suite 104 San Jose CA 95116",
    "addr:housenumber":"125",
    "addr:postcode":"95116",
    "addr:street":"N Jackson Avenue Suite 104",
    "iso:country":"US",
    "sg:address":"125 N Jackson Avenue Suite 104",
    "sg:city":"San Jose",
    "sg:classifiers":[
        {
            "category":"Health Services",
            "subcategory":"Dentist",
            "type":"Services"
        }
    ],
    "sg:phone":"+1 408 923 8272",
    "sg:postcode":"95116",
    "sg:province":"CA",
    "wof:name":"To Hue DDS",
    "wof:placetype":"venue"
},
  "geometry": {"coordinates":[-121.84653400000001,37.361537],"type":"Point"}
}