{
  "type": "Feature",
  "properties": {
    "addr:full":"447 Great Mall Dr Milpitas CA 95035",
    "addr:housenumber":"447",
    "addr:postcode":"95035",
    "addr:street":"Great Mall Dr",
    "iso:country":"US",
    "sg:address":"447 Great Mall Dr",
    "sg:city":"Milpitas",
    "sg:classifiers":[
        {
            "category":"Shopping",
            "subcategory":"Optical Goods",
            "type":"Retail Goods"
        }
    ],
    "sg:phone":"+1 408 719 9886",
    "sg:postcode":"95035",
    "sg:province":"CA",
    "sg:tags":[
        "sun",
        "goggles",
        "sunglasses"
    ],
    "wof:name":"New York Shade",
    "wof:placetype":"venue"
},
  "geometry": {"coordinates":[-121.895914,37.415197],"type":"Point"}
}