{
  "type": "Feature",
  "properties": {
    "addr:full":"2562 N Fordham Ave Fresno CA 93727",
    "addr:housenumber":"2562",
    "addr:postcode":"93727",
    "addr:street":"N Fordham Ave",
    "iso:country":"US",
    "sg:address":"2562 N Fordham Ave",
    "sg:city":"Fresno",
    "sg:classifiers":[
        {
            "category":"Wholesale",
            "subcategory":"Machinery & Supplies",
            "type":"Manufacturing & Wholesale Goods"
        }
    ],
    "sg:phone":"+1 559 348 1776",
    "sg:postcode":"93727",
    "sg:province":"CA",
    "sg:tags":[
        "dry wall",
        "contractor"
    ],
    "wof:name":"Tube Shop Inc",
    "wof:placetype":"venue"
},
  "geometry": {"coordinates":[-119.687459,36.773621],"type":"Point"}
}