{
  "type": "Feature",
  "properties": {
    "iso:country":"US",
    "sg:address":"624 S Grand Ave",
    "sg:city":"Los Angeles",
    "sg:classifiers":[
        {
            "category":"Utilities",
            "subcategory":"Telephone",
            "type":"Services"
        }
    ],
    "sg:phone":"+1 213 627 8889",
    "sg:postcode":"90017",
    "sg:province":"CA",
    "sg:tags":[
        "communications"
    ],
    "wof:name":"China Telecom",
    "wof:placetype":"venue"
},
  "geometry": {"coordinates":[-118.255476,34.048504],"type":"Point"}
}