{
  "type": "Feature",
  "properties": {
    "addr:full":"31194 Gold Run Rd Gold Run CA 95717",
    "addr:housenumber":"31194",
    "addr:postcode":"95717",
    "addr:street":"Gold Run Rd",
    "iso:country":"US",
    "sg:address":"31194 Gold Run Rd",
    "sg:city":"Gold Run",
    "sg:classifiers":[
        {
            "category":"Government",
            "subcategory":"Post Office",
            "type":"Public Place"
        }
    ],
    "sg:phone":"+1 530 389 2686",
    "sg:postcode":"95717",
    "sg:province":"CA",
    "wof:name":"US Post Office",
    "wof:placetype":"venue"
},
  "geometry": {"coordinates":[-120.85905200000001,39.175883],"type":"Point"}
}