{
  "type": "Feature",
  "properties": {
    "addr:full":"1772 N Milpitas Blvd Fl 2 Milpitas CA 95035",
    "addr:housenumber":"1772;2",
    "addr:postcode":"95035",
    "addr:street":"N Milpitas Blvd Fl",
    "iso:country":"US",
    "sg:address":"1772 N Milpitas Blvd Fl 2",
    "sg:city":"Milpitas",
    "sg:classifiers":[
        {
            "category":"Health Services",
            "subcategory":"Clinic",
            "type":"Services"
        },
        {
            "category":"Community Center",
            "type":"Public Place"
        }
    ],
    "sg:phone":"+1 408 262 9992",
    "sg:postcode":"95035",
    "sg:province":"CA",
    "sg:tags":[
        "medical"
    ],
    "wof:name":"Pacific Medical Center",
    "wof:placetype":"venue"
},
  "geometry": {"coordinates":[-121.910991,37.455202],"type":"Point"}
}