{
  "type": "Feature",
  "properties": {
    "iso:country":"US",
    "sg:address":"8552 Gibson Ranch Rd",
    "sg:city":"Elverta",
    "sg:classifiers":[
        {
            "category":"Government",
            "subcategory":"Office",
            "type":"Public Place"
        }
    ],
    "sg:phone":"+1 916 991 0225",
    "sg:postcode":"95626",
    "sg:province":"CA",
    "sg:tags":[
        "executive"
    ],
    "wof:name":"Gibson Ranch Regional Park",
    "wof:placetype":"venue"
},
  "geometry": {"coordinates":[-121.39923,38.728213],"type":"Point"}
}