{
  "type": "Feature",
  "properties": {
    "iso:country":"US",
    "sg:address":"216 E 7th St",
    "sg:city":"Hanford",
    "sg:classifiers":[
        {
            "category":"Autos & Motor Vehicles",
            "subcategory":"Auto Supplies",
            "type":"Retail Goods"
        }
    ],
    "sg:phone":"+1 559 583 7325",
    "sg:postcode":"93230",
    "sg:province":"CA",
    "sg:tags":[
        "automobile",
        "stereo",
        "radio"
    ],
    "wof:name":"American Audio",
    "wof:placetype":"venue"
},
  "geometry": {"coordinates":[-119.642712,36.327142],"type":"Point"}
}