{
  "type": "Feature",
  "properties": {
    "addr:full":"2576 Hartnell Ave Redding CA 96002",
    "addr:housenumber":"2576",
    "addr:postcode":"96002",
    "addr:street":"Hartnell Ave",
    "iso:country":"US",
    "sg:address":"2576 Hartnell Ave",
    "sg:city":"Redding",
    "sg:classifiers":[
        {
            "category":"Home & Garden",
            "subcategory":"Home Furnishings",
            "type":"Retail Goods"
        }
    ],
    "sg:phone":"+1 530 223 4410",
    "sg:postcode":"96002",
    "sg:province":"CA",
    "sg:tags":[
        "stove",
        "wood",
        "burning"
    ],
    "wof:name":"Cozy Stove & Spa Co",
    "wof:placetype":"venue"
},
  "geometry": {"coordinates":[-122.325076,40.563828],"type":"Point"}
}