{
  "type": "Feature",
  "properties": {
    "addr:full":"9405 Main St Lamont CA 93241",
    "addr:housenumber":"9405",
    "addr:postcode":"93241",
    "addr:street":"Main St",
    "iso:country":"US",
    "sg:address":"9405 Main St",
    "sg:city":"Lamont",
    "sg:classifiers":[
        {
            "category":"Autos & Motor Vehicles",
            "subcategory":"Automobile Sales",
            "type":"Retail Goods"
        }
    ],
    "sg:phone":"+1 661 845 1900",
    "sg:postcode":"93241",
    "sg:province":"CA",
    "sg:tags":[
        "car",
        "dealer"
    ],
    "wof:name":"Ray & Lupe's Auto Sales",
    "wof:placetype":"venue"
},
  "geometry": {"coordinates":[-118.914387,35.2688],"type":"Point"}
}