{
  "type": "Feature",
  "properties": {
    "addr:full":"44911 Golf Center Pkwy Indio CA 92201",
    "addr:housenumber":"44911",
    "addr:postcode":"92201",
    "addr:street":"Golf Center Pkwy",
    "iso:country":"US",
    "sg:address":"44911 Golf Center Pkwy",
    "sg:city":"Indio",
    "sg:classifiers":[
        {
            "category":"Manufacturing",
            "subcategory":"Food",
            "type":"Manufacturing & Wholesale Goods"
        }
    ],
    "sg:phone":"+1 760 347 7770",
    "sg:postcode":"92201",
    "sg:province":"CA",
    "sg:tags":[
        "product",
        "manufacturer"
    ],
    "wof:name":"Kids Business Inc",
    "wof:placetype":"venue"
},
  "geometry": {"coordinates":[-116.20430500000001,33.724096],"type":"Point"}
}