{
  "type": "Feature",
  "properties": {
    "addr:full":"1334 Dayton St Salinas CA 93901",
    "addr:housenumber":"1334",
    "addr:postcode":"93901",
    "addr:street":"Dayton St",
    "iso:country":"US",
    "sg:address":"1334 Dayton St",
    "sg:city":"Salinas",
    "sg:classifiers":[
        {
            "category":"Wholesale",
            "subcategory":"Machinery & Supplies",
            "type":"Manufacturing & Wholesale Goods"
        }
    ],
    "sg:phone":"+1 831 757 0991",
    "sg:postcode":"93901",
    "sg:province":"CA",
    "sg:tags":[
        "equipment",
        "industrial"
    ],
    "sg:website":"www.grainger.com",
    "wof:name":"Grainger Inc",
    "wof:placetype":"venue"
},
  "geometry": {"coordinates":[-121.62869999999999,36.647737],"type":"Point"}
}