{
  "type": "Feature",
  "properties": {
    "addr:full":"1060 Auto Center Ct Ste G Carlsbad CA 92008",
    "addr:housenumber":"1060",
    "addr:postcode":"92008",
    "addr:street":"Auto Center Ct Ste G",
    "iso:country":"US",
    "sg:address":"1060 Auto Center Ct Ste G",
    "sg:city":"Carlsbad",
    "sg:classifiers":[
        {
            "category":"Autos & Motor Vehicles",
            "subcategory":"Automobile Sales",
            "type":"Retail Goods"
        },
        {
            "category":"Retail",
            "subcategory":"Auto Rental",
            "type":"Services"
        }
    ],
    "sg:phone":"+1 760 931 1111",
    "sg:postcode":"92008",
    "sg:province":"CA",
    "sg:tags":[
        "car",
        "leasing",
        "truck"
    ],
    "sg:website":"http://www.enterprise.com/car_rental/deeplinkmap.do?gpbr=3246&bid=004&cnty=US&arc=YPTRL01&cm_mmc=Yellowpages.com-_-IYP-_-Tradelisting-_-branch",
    "wof:name":"Enterprise Rent-A-Car",
    "wof:placetype":"venue"
},
  "geometry": {"coordinates":[-117.324139,33.134185],"type":"Point"}
}