{
  "type": "Feature",
  "properties": {
    "addr:full":"17265 Letteau Ave Delhi CA 95315",
    "addr:postcode":"17265;95315",
    "addr:street":"Letteau Ave",
    "iso:country":"US",
    "sg:address":"17265 Letteau Ave",
    "sg:city":"Delhi",
    "sg:classifiers":[
        {
            "category":"Organizations",
            "subcategory":"Community Association",
            "type":"Services"
        }
    ],
    "sg:phone":"+1 209 667 7446",
    "sg:postcode":"95315",
    "sg:province":"CA",
    "wof:name":"Grange Patrons of Husbandry",
    "wof:placetype":"venue"
},
  "geometry": {"coordinates":[-120.79894400000001,37.433778],"type":"Point"}
}