{
  "type": "Feature",
  "properties": {
    "addr:full":"21351 Pacific Coast Hwy Huntington Beach CA 92648",
    "addr:housenumber":"21351",
    "addr:postcode":"92648",
    "addr:street":"Pacific Coast Hwy",
    "iso:country":"US",
    "sg:address":"21351 Pacific Coast Hwy",
    "sg:city":"Huntington Beach",
    "sg:classifiers":[
        {
            "category":"Restaurant",
            "type":"Food & Drink"
        }
    ],
    "sg:phone":"+1 714 969 3043",
    "sg:postcode":"92648",
    "sg:province":"CA",
    "sg:tags":[
        "mexican"
    ],
    "sg:website":"www.wahoos.com",
    "wof:name":"Wahoo's Fish Taco",
    "wof:placetype":"venue"
},
  "geometry": {"coordinates":[-117.99236000000001,33.651087],"type":"Point"}
}