{
  "type": "Feature",
  "properties": {
    "addr:full":"1117 Tanglewood Way San Mateo CA 94403",
    "addr:housenumber":"1117",
    "addr:postcode":"94403",
    "addr:street":"Tanglewood Way",
    "iso:country":"US",
    "sg:address":"1117 Tanglewood Way",
    "sg:city":"San Mateo",
    "sg:classifiers":[
        {
            "category":"Health Services",
            "subcategory":"Nursing And Care Facility",
            "type":"Services"
        }
    ],
    "sg:phone":"+1 650 345 7111",
    "sg:postcode":"94403",
    "sg:province":"CA",
    "sg:tags":[
        "home",
        "intermediate"
    ],
    "wof:name":"Stilt Court Regency Care Home",
    "wof:placetype":"venue"
},
  "geometry": {"coordinates":[-122.278887,37.529411],"type":"Point"}
}