{
  "type": "Feature",
  "properties": {
    "addr:full":"360 W Portal Ave San Francisco CA 94127",
    "addr:housenumber":"360",
    "addr:postcode":"94127",
    "addr:street":"W Portal Ave",
    "iso:country":"US",
    "sg:address":"360 W Portal Ave",
    "sg:city":"San Francisco",
    "sg:classifiers":[
        {
            "category":"Restaurant",
            "type":"Food & Drink"
        }
    ],
    "sg:menulink":"http://www.allmenus.com/ca/san-francisco/62152-sushi-suki/menu/",
    "sg:phone":"+1 415 242 5667",
    "sg:postcode":"94127",
    "sg:province":"CA",
    "sg:tags":[
        "japanese",
        "asian"
    ],
    "wof:name":"Sushi Suki",
    "wof:placetype":"venue"
},
  "geometry": {"coordinates":[-122.47011000000001,37.73724],"type":"Point"}
}