{
  "type": "Feature",
  "properties": {
    "addr:full":"5911 E Spring St Long Beach CA 90808",
    "addr:housenumber":"5911",
    "addr:postcode":"90808",
    "addr:street":"E Spring St",
    "iso:country":"US",
    "sg:address":"5911 E Spring St",
    "sg:city":"Long Beach",
    "sg:classifiers":[
        {
            "category":"Health Services",
            "subcategory":"Medical Lab",
            "type":"Services"
        }
    ],
    "sg:phone":"+1 562 234 0053",
    "sg:postcode":"90808",
    "sg:province":"CA",
    "sg:tags":[
        "laboratory"
    ],
    "sg:website":"www.jonesbiomed.cjb.net",
    "wof:name":"Jones Biomedicals & Lab",
    "wof:placetype":"venue"
},
  "geometry": {"coordinates":[-118.115352,33.810577],"type":"Point"}
}