{
  "type": "Feature",
  "properties": {
    "addr:full":"6420 Wagon Loop Placerville CA 95667",
    "addr:housenumber":"6420",
    "addr:postcode":"95667",
    "addr:street":"Wagon Loop",
    "iso:country":"US",
    "sg:address":"6420 Wagon Loop",
    "sg:city":"Placerville",
    "sg:classifiers":[
        {
            "category":"Food & Beverages",
            "subcategory":"Bakery",
            "type":"Retail Goods"
        },
        {
            "category":"Wholesale",
            "subcategory":"Groceries",
            "type":"Manufacturing & Wholesale Goods"
        }
    ],
    "sg:phone":"+1 530 621 2017",
    "sg:postcode":"95667",
    "sg:province":"CA",
    "sg:tags":[
        "cooky",
        "crackers-wholesale",
        "bakers-wholesale",
        "manufacturer"
    ],
    "wof:name":"Mommys Cookies",
    "wof:placetype":"venue"
},
  "geometry": {"coordinates":[-120.883374,38.721182],"type":"Point"}
}