{
  "type": "Feature",
  "properties": {
    "iso:country":"US",
    "sg:address":"251 N 2nd Ave",
    "sg:city":"Upland",
    "sg:classifiers":[
        {
            "category":"Shopping",
            "subcategory":"Used Merchandise",
            "type":"Retail Goods"
        }
    ],
    "sg:phone":"+1 909 982 2543",
    "sg:postcode":"91786",
    "sg:province":"CA",
    "wof:name":"Carriage House Antiques",
    "wof:placetype":"venue"
},
  "geometry": {"coordinates":[-117.64850800000001,34.096693],"type":"Point"}
}