{
  "type": "Feature",
  "properties": {
    "iso:country":"US",
    "sg:address":"11 S San Joaquin St",
    "sg:city":"Stockton",
    "sg:classifiers":[
        {
            "category":"Health Services",
            "subcategory":"Medical Lab",
            "type":"Services"
        },
        {
            "category":"Professional",
            "subcategory":"Lawyer & Legal Services",
            "type":"Services"
        }
    ],
    "sg:phone":"+1 209 460 1820",
    "sg:postcode":"95202",
    "sg:province":"CA",
    "sg:tags":[
        "litigation",
        "attorney",
        "injury",
        "personal",
        "civil",
        "practice",
        "trial",
        "malpractice",
        "harassment",
        "law",
        "sexual"
    ],
    "wof:name":"Nolan, Joseph W",
    "wof:placetype":"venue"
},
  "geometry": {"coordinates":[-121.287183,37.953031],"type":"Point"}
}