{
  "type": "Feature",
  "properties": {
    "iso:country":"US",
    "sg:address":"2518 W Beverly Blvd",
    "sg:city":"Montebello",
    "sg:classifiers":[
        {
            "category":"Health Services",
            "subcategory":"Clinic",
            "type":"Services"
        }
    ],
    "sg:phone":"+1 323 887 8720",
    "sg:postcode":"90640",
    "sg:province":"CA",
    "wof:name":"Alcoholics Anonyms Los Amigos",
    "wof:placetype":"venue"
},
  "geometry": {"coordinates":[-118.13009599999999,34.020898],"type":"Point"}
}