{
  "type": "Feature",
  "properties": {
    "iso:country":"US",
    "sg:address":"13921 Sycamore Way",
    "sg:city":"Chino",
    "sg:classifiers":[
        {
            "category":"Home & Garden",
            "subcategory":"Furniture",
            "type":"Retail Goods"
        }
    ],
    "sg:phone":"+1 909 902 5023",
    "sg:postcode":"91710",
    "sg:province":"CA",
    "wof:name":"Furniture Masters",
    "wof:placetype":"venue"
},
  "geometry": {"coordinates":[-117.67437,34.000709],"type":"Point"}
}