{
  "type": "Feature",
  "properties": {
    "iso:country":"US",
    "sg:address":"3039 W Ave J",
    "sg:city":"Lancaster",
    "sg:classifiers":[
        {
            "category":"Building & Trades",
            "subcategory":"Plumbing",
            "type":"Services"
        }
    ],
    "sg:phone":"+1 661 917 5312",
    "sg:postcode":"93536",
    "sg:province":"CA",
    "sg:tags":[
        "plumbing",
        "contractor"
    ],
    "wof:name":"Patriot Plumbing",
    "wof:placetype":"venue"
},
  "geometry": {"coordinates":[-118.18418800000001,34.689394],"type":"Point"}
}