{
  "type": "Feature",
  "properties": {
    "iso:country":"US",
    "sg:address":"21007 Victor St",
    "sg:city":"Torrance",
    "sg:classifiers":[
        {
            "category":"Wholesale",
            "subcategory":"Electrical",
            "type":"Manufacturing & Wholesale Goods"
        }
    ],
    "sg:phone":"+1 310 938 9214",
    "sg:postcode":"90503",
    "sg:province":"CA",
    "sg:tags":[
        "electronic",
        "merchandise"
    ],
    "wof:name":"Jda Enterprise",
    "wof:placetype":"venue"
},
  "geometry": {"coordinates":[-118.36677,33.839248],"type":"Point"}
}