{
  "type": "Feature",
  "properties": {
    "addr:full":"1465 Glendale Blvd Los Angeles CA 90026",
    "addr:housenumber":"1465",
    "addr:postcode":"90026",
    "addr:street":"Glendale Blvd",
    "iso:country":"US",
    "sg:address":"1465 Glendale Blvd",
    "sg:city":"Los Angeles",
    "sg:classifiers":[
        {
            "category":"Autos & Motor Vehicles",
            "subcategory":"Fuel & Gas Station",
            "type":"Retail Goods"
        }
    ],
    "sg:phone":"+1 213 484 0148",
    "sg:postcode":"90026",
    "sg:province":"CA",
    "sg:website":"www.chevron.com",
    "wof:name":"Chevron Echo Park",
    "wof:placetype":"venue"
},
  "geometry": {"coordinates":[-118.26055100000001,34.08195],"type":"Point"}
}