{
  "type": "Feature",
  "properties": {
    "iso:country":"US",
    "sg:address":"2222 Watt Ave",
    "sg:city":"Sacramento",
    "sg:classifiers":[
        {
            "category":"Health Services",
            "subcategory":"Podiatrist",
            "type":"Services"
        }
    ],
    "sg:phone":"+1 916 483 1493",
    "sg:postcode":"95825",
    "sg:province":"CA",
    "wof:name":"Jody B Laurence DPM",
    "wof:placetype":"venue"
},
  "geometry": {"coordinates":[-121.383118,38.606037],"type":"Point"}
}