{
  "type": "Feature",
  "properties": {
    "addr:full":"6610 Hembree Ln Windsor CA 95492",
    "addr:housenumber":"6610",
    "addr:postcode":"95492",
    "addr:street":"Hembree Ln",
    "iso:country":"US",
    "sg:address":"6610 Hembree Ln",
    "sg:city":"Windsor",
    "sg:classifiers":[
        {
            "category":"Restaurant",
            "type":"Food & Drink"
        }
    ],
    "sg:menulink":"http://www.allmenus.com/ca/healdsburg/197885-kfc---kentucky-fried-chicken/menu/",
    "sg:phone":"+1 707 837 8885",
    "sg:postcode":"95492",
    "sg:province":"CA",
    "sg:tags":[
        "american",
        "chicken"
    ],
    "wof:name":"KFC - Kentucky Fried Chicken",
    "wof:placetype":"venue"
},
  "geometry": {"coordinates":[-122.789787,38.526548],"type":"Point"}
}