{
  "type": "Feature",
  "properties": {
    "iso:country":"US",
    "sg:address":"3007 Bunsen Ave",
    "sg:city":"Ventura",
    "sg:classifiers":[
        {
            "category":"Manufacturing",
            "subcategory":"Tools & Machinery",
            "type":"Manufacturing & Wholesale Goods"
        }
    ],
    "sg:phone":"+1 805 658 2984",
    "sg:postcode":"93003",
    "sg:province":"CA",
    "sg:tags":[
        "physician",
        "surgeon"
    ],
    "wof:name":"Ventrex Inc",
    "wof:placetype":"venue"
},
  "geometry": {"coordinates":[-119.209567,34.245387],"type":"Point"}
}