{
  "type": "Feature",
  "properties": {
    "iso:country":"US",
    "sg:address":"2576 Clairemont Dr",
    "sg:city":"San Diego",
    "sg:classifiers":[
        {
            "category":"Autos & Motor Vehicles",
            "subcategory":"Fuel & Gas Station",
            "type":"Retail Goods"
        }
    ],
    "sg:phone":"+1 619 276 7676",
    "sg:postcode":"92117",
    "sg:province":"CA",
    "sg:tags":[
        "oil"
    ],
    "wof:name":"Bay Park 76",
    "wof:placetype":"venue"
},
  "geometry": {"coordinates":[-117.205405,32.790761],"type":"Point"}
}