{
  "type": "Feature",
  "properties": {
    "iso:country":"US",
    "sg:address":"235 Montgomery St",
    "sg:city":"San Francisco",
    "sg:classifiers":[
        {
            "category":"Banks & Credit Unions",
            "subcategory":"Investment Brokerage",
            "type":"Services"
        }
    ],
    "sg:phone":"+1 415 273 7931",
    "sg:postcode":"94104",
    "sg:province":"CA",
    "sg:tags":[
        "management"
    ],
    "wof:name":"Jackson Capital LLC",
    "wof:placetype":"venue"
},
  "geometry": {"coordinates":[-122.402593,37.791564],"type":"Point"}
}