{
  "type": "Feature",
  "properties": {
    "addr:full":"1025 Drever St West Sacramento CA 95691",
    "addr:housenumber":"1025",
    "addr:postcode":"95691",
    "addr:street":"Drever St",
    "iso:country":"US",
    "sg:address":"1025 Drever St",
    "sg:city":"West Sacramento",
    "sg:classifiers":[
        {
            "category":"Home & Garden",
            "subcategory":"Garden Supply",
            "type":"Retail Goods"
        },
        {
            "category":"Building & Trades",
            "subcategory":"Landscaping Services",
            "type":"Services"
        }
    ],
    "sg:phone":"+1 916 320 6481",
    "sg:postcode":"95691",
    "sg:province":"CA",
    "sg:tags":[
        "lawn"
    ],
    "wof:name":"Knot Hole Creations",
    "wof:placetype":"venue"
},
  "geometry": {"coordinates":[-121.52338399999999,38.572913],"type":"Point"}
}