{
  "type": "Feature",
  "properties": {
    "iso:country":"US",
    "sg:address":"25 N 14th St Ste 125 Suite 150",
    "sg:city":"San Jose",
    "sg:classifiers":[
        {
            "category":"Personal",
            "subcategory":"Nail Salon",
            "type":"Services"
        }
    ],
    "sg:phone":"+1 408 293 1120",
    "sg:postcode":"95112",
    "sg:province":"CA",
    "wof:name":"K L Hair & Nails",
    "wof:placetype":"venue"
},
  "geometry": {"coordinates":[-121.877864,37.342898],"type":"Point"}
}