{
  "type": "Feature",
  "properties": {
    "iso:country":"US",
    "sg:address":"2435 Venice Dr E",
    "sg:city":"South Lake Tahoe",
    "sg:classifiers":[
        {
            "category":"Professional",
            "type":"Services"
        }
    ],
    "sg:phone":"+1 530 541 7673",
    "sg:postcode":"96150",
    "sg:province":"CA",
    "wof:name":"Rose Safari",
    "wof:placetype":"venue"
},
  "geometry": {"coordinates":[-120.003792,38.930222],"type":"Point"}
}