{
  "type": "Feature",
  "properties": {
    "iso:country":"US",
    "sg:address":"87 Scripps Dr Ste 112",
    "sg:city":"Sacramento",
    "sg:classifiers":[
        {
            "category":"Health Services",
            "subcategory":"Doctor",
            "type":"Services"
        },
        {
            "category":"Health Services",
            "subcategory":"Clinic",
            "type":"Services"
        }
    ],
    "sg:phone":"+1 916 570 3088",
    "sg:postcode":"95825",
    "sg:province":"CA",
    "sg:tags":[
        "physician",
        "medical",
        "surgeons",
        "cosmetic",
        "plastic",
        "surgery",
        "reconstructive"
    ],
    "wof:name":"Gallia Lou MD FACS A Medical Corporation",
    "wof:placetype":"venue"
},
  "geometry": {"coordinates":[-121.41149299999999,38.572382],"type":"Point"}
}