{
  "type": "Feature",
  "properties": {
    "addr:full":"333 Sunrise Ave Roseville CA 95661",
    "addr:housenumber":"333",
    "addr:postcode":"95661",
    "addr:street":"Sunrise Ave",
    "iso:country":"US",
    "sg:address":"333 Sunrise Ave",
    "sg:city":"Roseville",
    "sg:classifiers":[
        {
            "category":"Professional",
            "subcategory":"Computer Services",
            "type":"Services"
        }
    ],
    "sg:phone":"+1 916 789 2574",
    "sg:postcode":"95661",
    "sg:province":"CA",
    "sg:tags":[
        "consultant",
        "designer"
    ],
    "wof:name":"Trivad",
    "wof:placetype":"venue"
},
  "geometry": {"coordinates":[-121.271934,38.741027],"type":"Point"}
}