{
  "type": "Feature",
  "properties": {
    "iso:country":"US",
    "sg:address":"393 E Walnut St",
    "sg:city":"Pasadena",
    "sg:classifiers":[
        {
            "category":"Education",
            "subcategory":"Library",
            "type":"Public Place"
        }
    ],
    "sg:phone":"+1 626 405 3089",
    "sg:postcode":"91101",
    "sg:province":"CA",
    "sg:tags":[
        "special",
        "interest"
    ],
    "wof:name":"Management Effectiveness Libr",
    "wof:placetype":"venue"
},
  "geometry": {"coordinates":[-118.14192300000001,34.149601],"type":"Point"}
}