{
  "type": "Feature",
  "properties": {
    "iso:country":"US",
    "sg:address":"25527 Flanders Dr",
    "sg:city":"Carmel",
    "sg:classifiers":[
        {
            "category":"Social Services",
            "subcategory":"Adult Care",
            "type":"Services"
        }
    ],
    "sg:phone":"+1 831 625 2194",
    "sg:postcode":"93923",
    "sg:province":"CA",
    "sg:tags":[
        "home",
        "residential"
    ],
    "wof:name":"Agape Of Carmel",
    "wof:placetype":"venue"
},
  "geometry": {"coordinates":[-121.908669,36.556523],"type":"Point"}
}