{
  "type": "Feature",
  "properties": {
    "iso:country":"US",
    "sg:address":"6328 Fairmount Ave Ste 220",
    "sg:city":"El Cerrito",
    "sg:classifiers":[
        {
            "category":"Health Services",
            "subcategory":"Health Practitioner",
            "type":"Services"
        }
    ],
    "sg:phone":"+1 510 525 2700",
    "sg:postcode":"94530",
    "sg:province":"CA",
    "sg:tags":[
        "acupuncture",
        "therapy",
        "physical"
    ],
    "sg:website":"handtherapyandacupuncture.com",
    "wof:name":"El Cerrito & Oakland Hand Therapy and Acupuncture",
    "wof:placetype":"venue"
},
  "geometry": {"coordinates":[-122.301321,37.90063],"type":"Point"}
}