{
  "type": "Feature",
  "properties": {
    "iso:country":"US",
    "sg:address":"606 S Hill St",
    "sg:city":"Los Angeles",
    "sg:classifiers":[
        {
            "category":"Shopping",
            "subcategory":"Jewelry",
            "type":"Retail Goods"
        }
    ],
    "sg:phone":"+1 213 689 9155",
    "sg:postcode":"90014",
    "sg:province":"CA",
    "wof:name":"Elias Fine Jewelry",
    "wof:placetype":"venue"
},
  "geometry": {"coordinates":[-118.252954,34.047001],"type":"Point"}
}