{
  "type": "Feature",
  "properties": {
    "iso:country":"US",
    "sg:address":"77 Fair Dr",
    "sg:city":"Costa Mesa",
    "sg:classifiers":[
        {
            "category":"Government",
            "subcategory":"Office",
            "type":"Public Place"
        }
    ],
    "sg:phone":"+1 714 754 4891",
    "sg:postcode":"92626",
    "sg:province":"CA",
    "sg:tags":[
        "village"
    ],
    "sg:website":"www.ci.costa-mesa.ca.us",
    "wof:name":"Costa Mesa Management Info Svc",
    "wof:placetype":"venue"
},
  "geometry": {"coordinates":[-117.899376,33.663826],"type":"Point"}
}