{
  "type": "Feature",
  "properties": {
    "addr:full":"1320 Pacific Ave Santa Cruz CA 95060",
    "addr:housenumber":"1320",
    "addr:postcode":"95060",
    "addr:street":"Pacific Ave",
    "iso:country":"US",
    "sg:address":"1320 Pacific Ave",
    "sg:city":"Santa Cruz",
    "sg:classifiers":[
        {
            "category":"Shopping",
            "subcategory":"Jewelry",
            "type":"Retail Goods"
        }
    ],
    "sg:phone":"+1 831 423 4100",
    "sg:postcode":"95060",
    "sg:province":"CA",
    "sg:tags":[
        "watch"
    ],
    "sg:website":"www.dellwilliams.com",
    "wof:name":"Dell Williams Jewelers",
    "wof:placetype":"venue"
},
  "geometry": {"coordinates":[-122.02600099999999,36.974201],"type":"Point"}
}