{
  "type": "Feature",
  "properties": {
    "addr:full":"3136 E Tulare Ave Fresno CA 93702",
    "addr:housenumber":"3136",
    "addr:postcode":"93702",
    "addr:street":"E Tulare Ave",
    "iso:country":"US",
    "sg:address":"3136 E Tulare Ave",
    "sg:city":"Fresno",
    "sg:classifiers":[
        {
            "category":"Retail",
            "subcategory":"Laundry & Dry Cleaning",
            "type":"Services"
        }
    ],
    "sg:phone":"+1 559 497 5339",
    "sg:postcode":"93702",
    "sg:province":"CA",
    "wof:name":"Bethel Laundry",
    "wof:placetype":"venue"
},
  "geometry": {"coordinates":[-119.77142000000001,36.743086],"type":"Point"}
}