{
  "type": "Feature",
  "properties": {
    "iso:country":"US",
    "sg:address":"1038 E 52nd St",
    "sg:city":"Los Angeles",
    "sg:classifiers":[
        {
            "category":"Cinema",
            "subcategory":"Movie Rental",
            "type":"Entertainment"
        }
    ],
    "sg:phone":"+1 323 233 3632",
    "sg:postcode":"90011",
    "sg:province":"CA",
    "sg:tags":[
        "leasing",
        "video",
        "disc",
        "tape"
    ],
    "wof:name":"Go Fabulous Inc Video & Prdctn",
    "wof:placetype":"venue"
},
  "geometry": {"coordinates":[-118.257413,33.995752],"type":"Point"}
}