{
  "type": "Feature",
  "properties": {
    "addr:full":"30 Main St Woodland CA 95695",
    "addr:housenumber":"30",
    "addr:postcode":"95695",
    "addr:street":"Main St",
    "iso:country":"US",
    "sg:address":"30 Main St",
    "sg:city":"Woodland",
    "sg:classifiers":[
        {
            "category":"Personal",
            "type":"Services"
        }
    ],
    "sg:phone":"+1 530 219 3571",
    "sg:postcode":"95695",
    "sg:province":"CA",
    "sg:tags":[
        "therapist",
        "massage"
    ],
    "wof:name":"Life's Treasure Massage",
    "wof:placetype":"venue"
},
  "geometry": {"coordinates":[-121.782875,38.677469],"type":"Point"}
}