{
  "type": "Feature",
  "properties": {
    "addr:full":"4902 Morningstar Dr Sacramento CA 95824",
    "addr:housenumber":"4902",
    "addr:postcode":"95824",
    "addr:street":"Morningstar Dr",
    "iso:country":"US",
    "sg:address":"4902 Morningstar Dr",
    "sg:city":"Sacramento",
    "sg:classifiers":[
        {
            "category":"Building & Trades",
            "subcategory":"Construction",
            "type":"Services"
        }
    ],
    "sg:phone":"+1 916 212 2063",
    "sg:postcode":"95824",
    "sg:province":"CA",
    "sg:tags":[
        "carpenter"
    ],
    "wof:name":"Fernandez",
    "wof:placetype":"venue"
},
  "geometry": {"coordinates":[-121.44684100000001,38.512333],"type":"Point"}
}