{
  "type": "Feature",
  "properties": {
    "iso:country":"US",
    "sg:address":"1421 N Harbor Blvd",
    "sg:city":"Santa Ana",
    "sg:classifiers":[
        {
            "category":"Wholesale",
            "subcategory":"Non-durable Goods",
            "type":"Manufacturing & Wholesale Goods"
        }
    ],
    "sg:phone":"+1 714 554 4871",
    "sg:postcode":"92703",
    "sg:province":"CA",
    "wof:name":"Makoto Co",
    "wof:placetype":"venue"
},
  "geometry": {"coordinates":[-117.92024600000001,33.758145],"type":"Point"}
}