{
  "type": "Feature",
  "properties": {
    "addr:full":"651 Portal St Cotati CA 94931",
    "addr:housenumber":"651",
    "addr:postcode":"94931",
    "addr:street":"Portal St",
    "iso:country":"US",
    "sg:address":"651 Portal St",
    "sg:city":"Cotati",
    "sg:classifiers":[
        {
            "category":"Building & Trades",
            "subcategory":"Construction",
            "type":"Services"
        }
    ],
    "sg:phone":"+1 707 665 9490",
    "sg:postcode":"94931",
    "sg:province":"CA",
    "sg:tags":[
        "general",
        "contractor"
    ],
    "wof:name":"Bedell General Contractors",
    "wof:placetype":"venue"
},
  "geometry": {"coordinates":[-122.71718799999999,38.342305],"type":"Point"}
}