{
  "type": "Feature",
  "properties": {
    "iso:country":"US",
    "sg:address":"426 Vernon St",
    "sg:city":"Roseville",
    "sg:classifiers":[
        {
            "category":"Education",
            "subcategory":"School",
            "type":"Public Place"
        }
    ],
    "sg:phone":"+1 916 773 9188",
    "sg:postcode":"95678",
    "sg:province":"CA",
    "wof:name":"Home School Services",
    "wof:placetype":"venue"
},
  "geometry": {"coordinates":[-121.286148,38.747446],"type":"Point"}
}