{
  "type": "Feature",
  "properties": {
    "addr:full":"2200 University Ave Palo Alto CA 94303",
    "addr:housenumber":"2200",
    "addr:postcode":"94303",
    "addr:street":"University Ave",
    "iso:country":"US",
    "sg:address":"2200 University Ave",
    "sg:city":"Palo Alto",
    "sg:classifiers":[
        {
            "category":"Government",
            "subcategory":"Office",
            "type":"Public Place"
        }
    ],
    "sg:phone":"+1 650 853 3189",
    "sg:postcode":"94303",
    "sg:province":"CA",
    "sg:tags":[
        "development",
        "works",
        "community"
    ],
    "wof:name":"Community Dev & Pub Works",
    "wof:placetype":"venue"
},
  "geometry": {"coordinates":[-122.14144,37.46854],"type":"Point"}
}