{
  "type": "Feature",
  "properties": {
    "iso:country":"US",
    "sg:address":"2204 Tulare Ave",
    "sg:city":"Burbank",
    "sg:classifiers":[
        {
            "category":"Home & Garden",
            "subcategory":"Building Materials",
            "type":"Retail Goods"
        }
    ],
    "sg:phone":"+1 818 841 2335",
    "sg:postcode":"91504",
    "sg:province":"CA",
    "sg:tags":[
        "glass",
        "window",
        "plate"
    ],
    "wof:name":"Burbank Glass & Mirror",
    "wof:placetype":"venue"
},
  "geometry": {"coordinates":[-118.334295,34.202835],"type":"Point"}
}