{
  "type": "Feature",
  "properties": {
    "iso:country":"US",
    "sg:address":"1407 J St",
    "sg:city":"Sacramento",
    "sg:classifiers":[
        {
            "category":"Real Estate",
            "subcategory":"Real Estate Agent",
            "type":"Services"
        }
    ],
    "sg:phone":"+1 916 966 6905",
    "sg:postcode":"95814",
    "sg:province":"CA",
    "wof:name":"Realty World",
    "wof:placetype":"venue"
},
  "geometry": {"coordinates":[-121.487781,38.578828],"type":"Point"}
}