{
  "type": "Feature",
  "properties": {
    "addr:full":"619 S Roselawn Ave Turlock CA 95380",
    "addr:housenumber":"619",
    "addr:postcode":"95380",
    "addr:street":"S Roselawn Ave",
    "iso:country":"US",
    "sg:address":"619 S Roselawn Ave",
    "sg:city":"Turlock",
    "sg:classifiers":[
        {
            "category":"Freight",
            "type":"Transportation"
        }
    ],
    "sg:phone":"+1 209 632 4602",
    "sg:postcode":"95380",
    "sg:province":"CA",
    "sg:tags":[
        "tank",
        "trucking",
        "raw",
        "truck",
        "intrastate",
        "milk"
    ],
    "wof:name":"Serpa's Milk Transport",
    "wof:placetype":"venue"
},
  "geometry": {"coordinates":[-120.798829,37.4876],"type":"Point"}
}