{
  "type": "Feature",
  "properties": {
    "addr:full":"5885 E Bonnyview Rd Redding CA 96001",
    "addr:housenumber":"5885",
    "addr:postcode":"96001",
    "addr:street":"E Bonnyview Rd",
    "iso:country":"US",
    "sg:address":"5885 E Bonnyview Rd",
    "sg:city":"Redding",
    "sg:classifiers":[
        {
            "category":"Education",
            "subcategory":"School",
            "type":"Public Place"
        }
    ],
    "sg:phone":"+1 530 225 0011",
    "sg:postcode":"96001",
    "sg:province":"CA",
    "sg:tags":[
        "elementary"
    ],
    "wof:name":"Redding Elementary School District",
    "wof:placetype":"venue"
},
  "geometry": {"coordinates":[-122.37397900000001,40.52974],"type":"Point"}
}