{
  "type": "Feature",
  "properties": {
    "iso:country":"US",
    "sg:address":"3701 S Harbor",
    "sg:city":"Santa Ana",
    "sg:classifiers":[
        {
            "category":"Restaurant",
            "type":"Food & Drink"
        }
    ],
    "sg:phone":"+1 714 432 7602",
    "sg:postcode":"92704",
    "sg:province":"CA",
    "sg:tags":[
        "japanese"
    ],
    "wof:name":"Miyako",
    "wof:placetype":"venue"
},
  "geometry": {"coordinates":[-117.919421,33.697705],"type":"Point"}
}