{
  "type": "Feature",
  "properties": {
    "addr:full":"7077 Redwood Blvd Novato CA 94945",
    "addr:housenumber":"7077",
    "addr:postcode":"94945",
    "addr:street":"Redwood Blvd",
    "iso:country":"US",
    "sg:address":"7077 Redwood Blvd",
    "sg:city":"Novato",
    "sg:classifiers":[
        {
            "category":"Autos & Motor Vehicles",
            "subcategory":"Motorcycle Sales",
            "type":"Retail Goods"
        }
    ],
    "sg:phone":"+1 415 878 4988",
    "sg:postcode":"94945",
    "sg:province":"CA",
    "sg:tags":[
        "scooter"
    ],
    "wof:name":"Golden Gate Harley-Davidson",
    "wof:placetype":"venue"
},
  "geometry": {"coordinates":[-122.565881,38.098165],"type":"Point"}
}