{
  "type": "Feature",
  "properties": {
    "addr:full":"1175 N Tracy Blvd Tracy CA 95376",
    "addr:housenumber":"1175",
    "addr:postcode":"95376",
    "addr:street":"N Tracy Blvd",
    "iso:country":"US",
    "sg:address":"1175 N Tracy Blvd",
    "sg:city":"Tracy",
    "sg:classifiers":[
        {
            "category":"Banks & Credit Unions",
            "subcategory":"Bank",
            "type":"Services"
        }
    ],
    "sg:phone":"+1 209 820 2000",
    "sg:postcode":"95376",
    "sg:province":"CA",
    "sg:tags":[
        "saving",
        "commercial"
    ],
    "sg:website":"http://www.bankofstockton.com",
    "wof:name":"Bank of Stockton",
    "wof:placetype":"venue"
},
  "geometry": {"coordinates":[-121.436286,37.74062],"type":"Point"}
}