{
  "type": "Feature",
  "properties": {
    "iso:country":"US",
    "sg:address":"1601 W Collins Ave",
    "sg:city":"Orange",
    "sg:classifiers":[
        {
            "category":"Shopping",
            "subcategory":"Used Merchandise",
            "type":"Retail Goods"
        }
    ],
    "sg:phone":"+1 714 532 5294",
    "sg:postcode":"92867",
    "sg:province":"CA",
    "sg:tags":[
        "antique",
        "durable"
    ],
    "wof:name":"Antique Trade Center",
    "wof:placetype":"venue"
},
  "geometry": {"coordinates":[-117.869526,33.802492],"type":"Point"}
}