{
  "type": "Feature",
  "properties": {
    "iso:country":"US",
    "sg:address":"510 Winston Ct",
    "sg:city":"Tracy",
    "sg:classifiers":[
        {
            "category":"Professional",
            "type":"Services"
        }
    ],
    "sg:phone":"+1 209 832 7948",
    "sg:postcode":"95376",
    "sg:province":"CA",
    "wof:name":"A Home For Hopeful Acts",
    "wof:placetype":"venue"
},
  "geometry": {"coordinates":[-121.417343,37.754644],"type":"Point"}
}