{
  "type": "Feature",
  "properties": {
    "iso:country":"US",
    "sg:address":"26 Tennessee St",
    "sg:city":"Vallejo",
    "sg:classifiers":[
        {
            "category":"Restaurant",
            "type":"Food & Drink"
        }
    ],
    "sg:phone":"+1 707 644 0950",
    "sg:postcode":"94590",
    "sg:province":"CA",
    "wof:name":"King Alberts BBQ",
    "wof:placetype":"venue"
},
  "geometry": {"coordinates":[-122.26175499999999,38.110186],"type":"Point"}
}