{
  "type": "Feature",
  "properties": {
    "addr:full":"21243 S Avalon Blvd Carson CA 90745",
    "addr:housenumber":"21243",
    "addr:postcode":"90745",
    "addr:street":"S Avalon Blvd",
    "iso:country":"US",
    "sg:address":"21243 S Avalon Blvd",
    "sg:city":"Carson",
    "sg:classifiers":[
        {
            "category":"Autos & Motor Vehicles",
            "subcategory":"Automobile Sales",
            "type":"Retail Goods"
        },
        {
            "category":"Retail",
            "subcategory":"Auto Repair",
            "type":"Services"
        }
    ],
    "sg:phone":"+1 310 816 9800",
    "sg:postcode":"90745",
    "sg:province":"CA",
    "sg:tags":[
        "car"
    ],
    "sg:website":"www.carproskiacarson.com",
    "wof:name":"Car Pros Kia of Carson",
    "wof:placetype":"venue"
},
  "geometry": {"coordinates":[-118.263628,33.837332],"type":"Point"}
}