{
  "type": "Feature",
  "properties": {
    "addr:full":"5900 Sepulveda Blvd Van Nuys CA 91411",
    "addr:housenumber":"5900",
    "addr:postcode":"91411",
    "addr:street":"Sepulveda Blvd",
    "iso:country":"US",
    "sg:address":"5900 Sepulveda Blvd",
    "sg:city":"Van Nuys",
    "sg:classifiers":[
        {
            "category":"Government",
            "subcategory":"Office",
            "type":"Public Place"
        }
    ],
    "sg:phone":"+1 818 901 5024",
    "sg:postcode":"91411",
    "sg:province":"CA",
    "sg:tags":[
        "state",
        "program",
        "rehabilitation"
    ],
    "sg:website":"www.dor.ca.gov.com",
    "wof:name":"Rehabilitation California Dept",
    "wof:placetype":"venue"
},
  "geometry": {"coordinates":[-118.466097,34.177538],"type":"Point"}
}