{
  "type": "Feature",
  "properties": {
    "addr:full":"13012 Pomerado Rd Poway CA 92064",
    "addr:housenumber":"13012",
    "addr:postcode":"ca 92064",
    "addr:street":"Pomerado Rd",
    "iso:country":"US",
    "sg:address":"13012 Pomerado Rd",
    "sg:city":"Poway",
    "sg:classifiers":[
        {
            "category":"Autos & Motor Vehicles",
            "subcategory":"Fuel & Gas Station",
            "type":"Retail Goods"
        }
    ],
    "sg:phone":"+1 858 748 7603",
    "sg:postcode":"92064",
    "sg:province":"CA",
    "sg:tags":[
        "oil"
    ],
    "wof:name":"California Finest Oil",
    "wof:placetype":"venue"
},
  "geometry": {"coordinates":[-117.062551,32.954787],"type":"Point"}
}