{
  "type": "Feature",
  "properties": {
    "addr:full":"525 University Ave Palo Alto CA 94301",
    "addr:housenumber":"525",
    "addr:postcode":"94301",
    "addr:street":"University Ave",
    "iso:country":"US",
    "sg:address":"525 University Ave",
    "sg:city":"Palo Alto",
    "sg:classifiers":[
        {
            "category":"Real Estate",
            "subcategory":"Real Estate Agent",
            "type":"Services"
        }
    ],
    "sg:phone":"+1 650 326 6480",
    "sg:postcode":"94301",
    "sg:province":"CA",
    "wof:name":"C M Golden Gate Inc",
    "wof:placetype":"venue"
},
  "geometry": {"coordinates":[-122.15894,37.448623],"type":"Point"}
}