{
  "type": "Feature",
  "properties": {
    "addr:full":"4057 W Shaw Ave Fresno CA 93722",
    "addr:housenumber":"4057",
    "addr:postcode":"93722",
    "addr:street":"W Shaw Ave",
    "iso:country":"US",
    "sg:address":"4057 W Shaw Ave",
    "sg:city":"Fresno",
    "sg:classifiers":[
        {
            "category":"Wholesale",
            "subcategory":"Furniture",
            "type":"Manufacturing & Wholesale Goods"
        }
    ],
    "sg:phone":"+1 559 275 4111",
    "sg:postcode":"93722",
    "sg:province":"CA",
    "wof:name":"Peninsula Business Interiors",
    "wof:placetype":"venue"
},
  "geometry": {"coordinates":[-119.86537199999999,36.808169],"type":"Point"}
}