{
  "type": "Feature",
  "properties": {
    "addr:full":"1731 N Texas St Ste C Fairfield CA 94533",
    "addr:housenumber":"1731",
    "addr:postcode":"94533",
    "addr:street":"N Texas St Ste C",
    "iso:country":"US",
    "sg:address":"1731 N Texas St Ste C",
    "sg:city":"Fairfield",
    "sg:classifiers":[
        {
            "category":"Professional",
            "type":"Services"
        },
        {
            "category":"Personal",
            "type":"Services"
        },
        {
            "category":"Restaurant",
            "type":"Food & Drink"
        },
        {
            "category":"Retail",
            "subcategory":"Event Space",
            "type":"Services"
        }
    ],
    "sg:phone":"+1 707 422 2108",
    "sg:postcode":"94533",
    "sg:province":"CA",
    "sg:tags":[
        "mexican",
        "facility",
        "hall",
        "planning",
        "reception",
        "caterer",
        "party",
        "meeting",
        "banquet"
    ],
    "sg:website":"http://www.aztecamex.com",
    "wof:name":"El Azteca Mexican Food",
    "wof:placetype":"venue"
},
  "geometry": {"coordinates":[-122.034246,38.260732],"type":"Point"}
}