{
  "type": "Feature",
  "properties": {
    "addr:full":"7083 Hollywood Boulevard Suite 602 Los Angeles CA 90028",
    "addr:housenumber":"7083",
    "addr:postcode":"90028",
    "addr:street":"Hollywood Boulevard Suite 602",
    "iso:country":"US",
    "sg:address":"7083 Hollywood Boulevard Suite 602",
    "sg:city":"Los Angeles",
    "sg:classifiers":[
        {
            "category":"Professional",
            "subcategory":"Lawyer & Legal Services",
            "type":"Services"
        }
    ],
    "sg:phone":"+1 323 468 0330",
    "sg:postcode":"90028",
    "sg:province":"CA",
    "wof:name":"Pennington Gregg",
    "wof:placetype":"venue"
},
  "geometry": {"coordinates":[-118.344661,34.101572],"type":"Point"}
}