{
  "type": "Feature",
  "properties": {
    "iso:country":"US",
    "sg:address":"5080 Shoreham Place",
    "sg:city":"San Diego",
    "sg:classifiers":[
        {
            "category":"Professional",
            "subcategory":"Accounting & Tax Preparation",
            "type":"Services"
        }
    ],
    "sg:phone":"+1 858 646 0681",
    "sg:postcode":"92122",
    "sg:province":"CA",
    "sg:tags":[
        "accountant"
    ],
    "wof:name":"Zweig Gary M An Accountancy Corporation",
    "wof:placetype":"venue"
},
  "geometry": {"coordinates":[-117.185481,32.852651],"type":"Point"}
}