{
  "type": "Feature",
  "properties": {
    "addr:full":"7356 Center Ave Huntington Beach CA 92647",
    "addr:housenumber":"7356",
    "addr:postcode":"92647",
    "addr:street":"Center Ave",
    "iso:country":"US",
    "sg:address":"7356 Center Ave",
    "sg:city":"Huntington Beach",
    "sg:classifiers":[
        {
            "category":"Personal",
            "subcategory":"Beauty Salon",
            "type":"Services"
        },
        {
            "category":"Personal",
            "subcategory":"Hair Removal",
            "type":"Services"
        }
    ],
    "sg:phone":"+1 714 894 9668",
    "sg:postcode":"92647",
    "sg:province":"CA",
    "sg:website":"www.HairDoandThreading.com",
    "wof:name":"Hair-Do & Threading Salon",
    "wof:placetype":"venue"
},
  "geometry": {"coordinates":[-117.99959200000001,33.733751],"type":"Point"}
}