{
  "type": "Feature",
  "properties": {
    "iso:country":"US",
    "sg:address":"4776 Mount Royal Ave",
    "sg:city":"San Diego",
    "sg:classifiers":[
        {
            "category":"Professional",
            "type":"Services"
        }
    ],
    "sg:phone":"+1 858 541 1828",
    "sg:postcode":"92117",
    "sg:province":"CA",
    "wof:name":"Suspicious International Co",
    "wof:placetype":"venue"
},
  "geometry": {"coordinates":[-117.187551,32.833598],"type":"Point"}
}