{
  "type": "Feature",
  "properties": {
    "addr:full":"2040 Union St San Francisco CA 94123",
    "addr:housenumber":"2040",
    "addr:postcode":"94123",
    "addr:street":"Union St",
    "iso:country":"US",
    "sg:address":"2040 Union St",
    "sg:city":"San Francisco",
    "sg:classifiers":[
        {
            "category":"Personal",
            "subcategory":"Beauty Salon",
            "type":"Services"
        },
        {
            "category":"Shopping",
            "subcategory":"Beauty & Cosmetics",
            "type":"Retail Goods"
        }
    ],
    "sg:phone":"+1 415 409 1500",
    "sg:postcode":"94123",
    "sg:province":"CA",
    "sg:tags":[
        "hair",
        "supply"
    ],
    "sg:website":"www.milvali.com",
    "wof:name":"Milvali Salon and Cosmetics",
    "wof:placetype":"venue"
},
  "geometry": {"coordinates":[-122.432956,37.797573],"type":"Point"}
}