{
  "type": "Feature",
  "properties": {
    "addr:full":"255 E 40th St San Bernardino CA 92404",
    "addr:housenumber":"255",
    "addr:postcode":"92404",
    "addr:street":"E 40Th St",
    "iso:country":"US",
    "sg:address":"255 E 40th St",
    "sg:city":"San Bernardino",
    "sg:classifiers":[
        {
            "category":"Restaurant",
            "type":"Food & Drink"
        }
    ],
    "sg:phone":"+1 909 886 4490",
    "sg:postcode":"92404",
    "sg:province":"CA",
    "wof:name":"Ye Old Lamplighter",
    "wof:placetype":"venue"
},
  "geometry": {"coordinates":[-117.279999,34.1651],"type":"Point"}
}