{
  "type": "Feature",
  "properties": {
    "iso:country":"US",
    "sg:address":"8461 Martinique Way",
    "sg:city":"Cypress",
    "sg:classifiers":[
        {
            "category":"Retail",
            "subcategory":"Repair Shop",
            "type":"Services"
        }
    ],
    "sg:phone":"+1 714 220 0444",
    "sg:postcode":"90630",
    "sg:province":"CA",
    "sg:tags":[
        "facsimile"
    ],
    "wof:name":"Fix N Fax",
    "wof:placetype":"venue"
},
  "geometry": {"coordinates":[-118.05240499999999,33.839057],"type":"Point"}
}