{
  "type": "Feature",
  "properties": {
    "addr:full":"3890 Main St Kelseyville CA 95451",
    "addr:housenumber":"3890",
    "addr:postcode":"95451",
    "addr:street":"Main St",
    "iso:country":"US",
    "sg:address":"3890 Main St",
    "sg:city":"Kelseyville",
    "sg:classifiers":[
        {
            "category":"Autos & Motor Vehicles",
            "subcategory":"Automobile Sales",
            "type":"Retail Goods"
        }
    ],
    "sg:phone":"+1 707 279 8108",
    "sg:postcode":"95451",
    "sg:province":"CA",
    "sg:tags":[
        "car",
        "dealer"
    ],
    "wof:name":"Buckmaster Repair & Sales",
    "wof:placetype":"venue"
},
  "geometry": {"coordinates":[-122.83905900000001,38.978067],"type":"Point"}
}