{
  "type": "Feature",
  "properties": {
    "iso:country":"US",
    "sg:address":"2990 San Pablo Ave",
    "sg:city":"Berkeley",
    "sg:classifiers":[
        {
            "category":"Arts & Performance",
            "subcategory":"Art Gallery",
            "type":"Entertainment"
        },
        {
            "category":"Shopping",
            "subcategory":"Crafts & Fabrics",
            "type":"Retail Goods"
        }
    ],
    "sg:phone":"+1 510 841 7000",
    "sg:postcode":"94702",
    "sg:province":"CA",
    "sg:tags":[
        "consultant",
        "galleries",
        "instruction"
    ],
    "wof:name":"Kala Art Gallery",
    "wof:placetype":"venue"
},
  "geometry": {"coordinates":[-122.286946,37.852283],"type":"Point"}
}