{
  "type": "Feature",
  "properties": {
    "addr:full":"2993 Cheyenne Rd Riverside CA 92506",
    "addr:housenumber":"2993",
    "addr:postcode":"92506",
    "addr:street":"Cheyenne Rd",
    "iso:country":"US",
    "sg:address":"2993 Cheyenne Rd",
    "sg:city":"Riverside",
    "sg:classifiers":[
        {
            "category":"Retail",
            "subcategory":"Repair Shop",
            "type":"Services"
        }
    ],
    "sg:phone":"+1 951 788 3034",
    "sg:postcode":"92506",
    "sg:province":"CA",
    "sg:tags":[
        "small",
        "major",
        "appliance",
        "refinishing"
    ],
    "wof:name":"Apple Appliance Service",
    "wof:placetype":"venue"
},
  "geometry": {"coordinates":[-117.377557,33.948071],"type":"Point"}
}