{
  "type": "Feature",
  "properties": {
    "iso:country":"US",
    "sg:address":"5816 Temple City Blvd",
    "sg:city":"Temple City",
    "sg:classifiers":[
        {
            "category":"Professional",
            "subcategory":"Lawyer & Legal Services",
            "type":"Services"
        }
    ],
    "sg:phone":"+1 626 286 3710",
    "sg:postcode":"91780",
    "sg:province":"CA",
    "sg:tags":[
        "attorney"
    ],
    "wof:name":"John L Shaw",
    "wof:placetype":"venue"
},
  "geometry": {"coordinates":[-118.060778,34.106405],"type":"Point"}
}