{
  "type": "Feature",
  "properties": {
    "iso:country":"US",
    "sg:address":"2211 Lombard St",
    "sg:city":"San Francisco",
    "sg:classifiers":[
        {
            "category":"Personal",
            "type":"Services"
        }
    ],
    "sg:phone":"+1 415 929 8255",
    "sg:postcode":"94123",
    "sg:province":"CA",
    "sg:tags":[
        "program",
        "physical",
        "exercise",
        "fitness"
    ],
    "wof:name":"Giddy",
    "wof:placetype":"venue"
},
  "geometry": {"coordinates":[-122.43917,37.799308],"type":"Point"}
}