{
  "type": "Feature",
  "properties": {
    "iso:country":"US",
    "sg:address":"323 Geary Street Suite 513",
    "sg:city":"San Francisco",
    "sg:classifiers":[
        {
            "category":"Real Estate",
            "subcategory":"Real Estate Services",
            "type":"Services"
        }
    ],
    "sg:phone":"+1 415 788 1076",
    "sg:postcode":"94102",
    "sg:province":"CA",
    "wof:name":"Newman Walter S Coml Rl Est",
    "wof:placetype":"venue"
},
  "geometry": {"coordinates":[-122.408997,37.7873],"type":"Point"}
}