{
  "type": "Feature",
  "properties": {
    "addr:full":"44 Vista Del Mar Orinda CA 94563",
    "addr:housenumber":"44",
    "addr:postcode":"94563",
    "addr:street":"Vista Del Mar",
    "iso:country":"US",
    "sg:address":"44 Vista Del Mar",
    "sg:city":"Orinda",
    "sg:classifiers":[
        {
            "category":"Shopping",
            "subcategory":"Stationery & Office Supplies",
            "type":"Retail Goods"
        },
        {
            "category":"Manufacturing",
            "subcategory":"Paper Products",
            "type":"Manufacturing & Wholesale Goods"
        }
    ],
    "sg:phone":"+1 925 254 5006",
    "sg:postcode":"94563",
    "sg:province":"CA",
    "sg:tags":[
        "equipment",
        "stationery-wholesale",
        "manufacturer"
    ],
    "wof:name":"B & B Sales",
    "wof:placetype":"venue"
},
  "geometry": {"coordinates":[-122.200996,37.895699],"type":"Point"}
}