{
  "type": "Feature",
  "properties": {
    "addr:full":"1100 Glendon Ave Los Angeles CA 90024",
    "addr:housenumber":"1100",
    "addr:postcode":"90024",
    "addr:street":"Glendon Ave",
    "iso:country":"US",
    "sg:address":"1100 Glendon Ave",
    "sg:city":"Los Angeles",
    "sg:classifiers":[
        {
            "category":"Health Services",
            "subcategory":"Doctor",
            "type":"Services"
        }
    ],
    "sg:phone":"+1 310 824 1990",
    "sg:postcode":"90024",
    "sg:province":"CA",
    "sg:tags":[
        "physician",
        "surgeon"
    ],
    "wof:name":"Bradley Warren Inc",
    "wof:placetype":"venue"
},
  "geometry": {"coordinates":[-118.443737,34.060296],"type":"Point"}
}