{
  "type": "Feature",
  "properties": {
    "iso:country":"US",
    "sg:address":"1065 Los Carneros Ave",
    "sg:city":"Napa",
    "sg:classifiers":[
        {
            "category":"Manufacturing",
            "subcategory":"Glass & Minerals",
            "type":"Manufacturing & Wholesale Goods"
        }
    ],
    "sg:phone":"+1 707 226 3100",
    "sg:postcode":"94559",
    "sg:province":"CA",
    "sg:tags":[
        "tile"
    ],
    "sg:website":"www.pecktile.com",
    "wof:name":"Peck Tile Pottery & Sculpture",
    "wof:placetype":"venue"
},
  "geometry": {"coordinates":[-122.32925,38.2517],"type":"Point"}
}