{
  "type": "Feature",
  "properties": {
    "addr:full":"5855 Mission Gorge Rd San Diego CA 92120",
    "addr:housenumber":"5855",
    "addr:postcode":"92120",
    "addr:street":"Mission Gorge Rd",
    "iso:country":"US",
    "sg:address":"5855 Mission Gorge Rd",
    "sg:city":"San Diego",
    "sg:classifiers":[
        {
            "category":"Restaurant",
            "type":"Food & Drink"
        }
    ],
    "sg:menulink":"http://www.allmenus.com/ca/san-diego/31183-szechuan-mandarin/menu/",
    "sg:phone":"+1 619 280 4600",
    "sg:postcode":"92120",
    "sg:province":"CA",
    "sg:tags":[
        "asian",
        "chinese"
    ],
    "wof:name":"Szechuan Mandarin",
    "wof:placetype":"venue"
},
  "geometry": {"coordinates":[-117.10065400000001,32.78187],"type":"Point"}
}