{
  "type": "Feature",
  "properties": {
    "addr:full":"3500 Ocean View Blvd Glendale CA 91020",
    "addr:housenumber":"3500",
    "addr:postcode":"91020",
    "addr:street":"Ocean View Blvd",
    "iso:country":"US",
    "sg:address":"3500 Ocean View Blvd",
    "sg:city":"Glendale",
    "sg:classifiers":[
        {
            "category":"Building & Trades",
            "subcategory":"Construction",
            "type":"Services"
        }
    ],
    "sg:phone":"+1 818 249 8397",
    "sg:postcode":"91020",
    "sg:province":"CA",
    "sg:tags":[
        "contracting",
        "restoration",
        "insurance",
        "gen"
    ],
    "sg:website":"www.rossmoyneinc.com",
    "wof:name":"Rossmoyne Inc",
    "wof:placetype":"venue"
},
  "geometry": {"coordinates":[-118.22807899999999,34.204398],"type":"Point"}
}