{
  "type": "Feature",
  "properties": {
    "iso:country":"US",
    "sg:address":"6300 E Manning Ave",
    "sg:city":"Fowler",
    "sg:classifiers":[
        {
            "category":"Farming",
            "subcategory":"Vineyard",
            "type":"Manufacturing & Wholesale Goods"
        }
    ],
    "sg:phone":"+1 559 834 3577",
    "sg:postcode":"93625",
    "sg:province":"CA",
    "sg:tags":[
        "grape"
    ],
    "wof:name":"Joan Markarian",
    "wof:placetype":"venue"
},
  "geometry": {"coordinates":[-119.666321,36.605449],"type":"Point"}
}