{
  "type": "Feature",
  "properties": {
    "addr:full":"459 E. Orange Grove Blvd #105 Pasadena CA 91101",
    "addr:housenumber":"459",
    "addr:postcode":"91101",
    "addr:street":"E. Orange Grove Blvd # 105",
    "iso:country":"US",
    "sg:address":"459 E. Orange Grove Blvd #105",
    "sg:city":"Pasadena",
    "sg:classifiers":[
        {
            "category":"Restaurant",
            "type":"Food & Drink"
        }
    ],
    "sg:phone":"+1 626 440 8886",
    "sg:postcode":"91101",
    "sg:province":"CA",
    "sg:tags":[
        "chinese"
    ],
    "wof:name":"Panda Bowl",
    "wof:placetype":"venue"
},
  "geometry": {"coordinates":[-118.14066699999999,34.157776],"type":"Point"}
}