{
  "type": "Feature",
  "properties": {
    "addr:full":"238 Todd Rd Santa Rosa CA 95407",
    "addr:housenumber":"238",
    "addr:postcode":"95407",
    "addr:street":"Todd Rd",
    "iso:country":"US",
    "sg:address":"238 Todd Rd",
    "sg:city":"Santa Rosa",
    "sg:classifiers":[
        {
            "category":"Wholesale",
            "subcategory":"Machinery & Supplies",
            "type":"Manufacturing & Wholesale Goods"
        }
    ],
    "sg:phone":"+1 707 584 7272",
    "sg:postcode":"95407",
    "sg:province":"CA",
    "sg:tags":[
        "irrigation",
        "sprinkler",
        "system"
    ],
    "wof:name":"Horizon",
    "wof:placetype":"venue"
},
  "geometry": {"coordinates":[-122.72294100000001,38.387133],"type":"Point"}
}