{
  "type": "Feature",
  "properties": {
    "iso:country":"US",
    "sg:address":"5301 W Adams Blvd",
    "sg:city":"Los Angeles",
    "sg:classifiers":[
        {
            "category":"Organizations",
            "subcategory":"Religious Organization",
            "type":"Services"
        }
    ],
    "sg:phone":"+1 909 931 1477",
    "sg:postcode":"90016",
    "sg:province":"CA",
    "sg:tags":[
        "church"
    ],
    "wof:name":"Zoe Church",
    "wof:placetype":"venue"
},
  "geometry": {"coordinates":[-118.36253000000001,34.032549],"type":"Point"}
}