{
  "type": "Feature",
  "properties": {
    "iso:country":"US",
    "sg:address":"133 E Victoria St",
    "sg:city":"Carson",
    "sg:classifiers":[
        {
            "category":"Building & Trades",
            "subcategory":"Construction",
            "type":"Services"
        }
    ],
    "sg:phone":"+1 310 769 5530",
    "sg:postcode":"90746",
    "sg:province":"CA",
    "sg:tags":[
        "contractor"
    ],
    "wof:name":"Dorman Dale L Inc",
    "wof:placetype":"venue"
},
  "geometry": {"coordinates":[-118.275002,33.8657],"type":"Point"}
}