{
  "type": "Feature",
  "properties": {
    "iso:country":"US",
    "sg:address":"205 Ocean Ave",
    "sg:city":"San Francisco",
    "sg:classifiers":[
        {
            "category":"Personal",
            "subcategory":"Beauty Salon",
            "type":"Services"
        }
    ],
    "sg:phone":"+1 415 587 6575",
    "sg:postcode":"94112",
    "sg:province":"CA",
    "sg:tags":[
        "hair"
    ],
    "wof:name":"Classy Creations",
    "wof:placetype":"venue"
},
  "geometry": {"coordinates":[-122.441181,37.723359],"type":"Point"}
}