{
  "type": "Feature",
  "properties": {
    "iso:country":"US",
    "sg:address":"1540 S Page Ct",
    "sg:city":"Anaheim",
    "sg:classifiers":[
        {
            "category":"Manufacturing",
            "subcategory":"Furniture",
            "type":"Manufacturing & Wholesale Goods"
        }
    ],
    "sg:phone":"+1 714 937 1514",
    "sg:postcode":"92806",
    "sg:province":"CA",
    "sg:tags":[
        "drapery",
        "mfg"
    ],
    "wof:name":"Window Accessories Unlimited",
    "wof:placetype":"venue"
},
  "geometry": {"coordinates":[-117.886939,33.807339],"type":"Point"}
}