{
  "type": "Feature",
  "properties": {
    "iso:country":"US",
    "sg:address":"16065 Mateo St",
    "sg:city":"San Leandro",
    "sg:classifiers":[
        {
            "category":"Personal",
            "type":"Services"
        },
        {
            "category":"Retail",
            "subcategory":"Auto Repair",
            "type":"Services"
        }
    ],
    "sg:phone":"+1 510 357 3880",
    "sg:postcode":"94578",
    "sg:province":"CA",
    "sg:tags":[
        "towing"
    ],
    "wof:name":"Hank's Automotive Service Inc",
    "wof:placetype":"venue"
},
  "geometry": {"coordinates":[-122.116997,37.700001],"type":"Point"}
}