{
  "type": "Feature",
  "properties": {
    "addr:full":"742 Market St Ste 3 San Diego CA 92101",
    "addr:housenumber":"742",
    "addr:postcode":"92101",
    "addr:street":"Market St Ste 3",
    "iso:country":"US",
    "sg:address":"742 Market St Ste 3",
    "sg:city":"San Diego",
    "sg:classifiers":[
        {
            "category":"Real Estate",
            "subcategory":"Real Estate Services",
            "type":"Services"
        }
    ],
    "sg:phone":"+1 619 544 1798",
    "sg:postcode":"92101",
    "sg:province":"CA",
    "sg:tags":[
        "management",
        "property"
    ],
    "wof:name":"Concord Management",
    "wof:placetype":"venue"
},
  "geometry": {"coordinates":[-117.157605,32.711782],"type":"Point"}
}