{
  "type": "Feature",
  "properties": {
    "iso:country":"US",
    "sg:address":"130 N Naomi St",
    "sg:city":"Burbank",
    "sg:classifiers":[
        {
            "category":"Restaurant",
            "type":"Food & Drink"
        }
    ],
    "sg:phone":"+1 818 219 1199",
    "sg:postcode":"91505",
    "sg:province":"CA",
    "sg:tags":[
        "personal",
        "eating"
    ],
    "wof:name":"A Sophisticated Palate",
    "wof:placetype":"venue"
},
  "geometry": {"coordinates":[-118.331149,34.159642],"type":"Point"}
}