{
  "type": "Feature",
  "properties": {
    "addr:full":"1451 W Artesia Blvd Gardena CA 90248",
    "addr:housenumber":"1451",
    "addr:postcode":"90248",
    "addr:street":"W Artesia Blvd",
    "iso:country":"US",
    "sg:address":"1451 W Artesia Blvd",
    "sg:city":"Gardena",
    "sg:classifiers":[
        {
            "category":"Insurance",
            "subcategory":"Insurance Agent",
            "type":"Services"
        }
    ],
    "sg:phone":"+1 310 512 6456",
    "sg:postcode":"90248",
    "sg:province":"CA",
    "wof:name":"Randy R Matsumoto Insurance",
    "wof:placetype":"venue"
},
  "geometry": {"coordinates":[-118.302105,33.872907],"type":"Point"}
}