{
  "type": "Feature",
  "properties": {
    "iso:country":"US",
    "sg:address":"5220 Rbert J Mathews Parkway",
    "sg:city":"El Dorado Hills",
    "sg:classifiers":[
        {
            "category":"Professional",
            "subcategory":"Computer Services",
            "type":"Services"
        }
    ],
    "sg:phone":"+1 916 939 6040",
    "sg:postcode":"95762-5705",
    "sg:province":"CA",
    "wof:name":"CableData",
    "wof:placetype":"venue"
},
  "geometry": {"coordinates":[-121.05577,38.614969],"type":"Point"}
}