{
  "type": "Feature",
  "properties": {
    "iso:country":"US",
    "sg:address":"4176 Redwood Hwy",
    "sg:city":"San Rafael",
    "sg:classifiers":[
        {
            "category":"Personal",
            "subcategory":"Beauty Salon",
            "type":"Services"
        }
    ],
    "sg:phone":"+1 415 492 1000",
    "sg:postcode":"94903",
    "sg:province":"CA",
    "wof:name":"Children's Hair Club",
    "wof:placetype":"venue"
},
  "geometry": {"coordinates":[-122.541529,38.009707],"type":"Point"}
}