{
  "type": "Feature",
  "properties": {
    "iso:country":"US",
    "sg:address":"20472 Crescent Bay Dr",
    "sg:city":"Lake Forest",
    "sg:classifiers":[
        {
            "category":"Wholesale",
            "subcategory":"Non-durable Goods",
            "type":"Manufacturing & Wholesale Goods"
        }
    ],
    "sg:phone":"+1 949 206 8547",
    "sg:postcode":"92630",
    "sg:province":"CA",
    "sg:tags":[
        "pet",
        "supply"
    ],
    "sg:website":"www.grandmalucys.com",
    "wof:name":"Grandma Lucys",
    "wof:placetype":"venue"
},
  "geometry": {"coordinates":[-117.689862,33.665445],"type":"Point"}
}