{
  "type": "Feature",
  "properties": {
    "iso:country":"US",
    "sg:address":"15 Crow Canyon Ct",
    "sg:city":"Chico",
    "sg:classifiers":[
        {
            "category":"Food & Beverages",
            "subcategory":"Candy",
            "type":"Retail Goods"
        }
    ],
    "sg:phone":"+1 530 893 8611",
    "sg:postcode":"95928",
    "sg:province":"CA",
    "sg:tags":[
        "nut"
    ],
    "wof:name":"G S Sales",
    "wof:placetype":"venue"
},
  "geometry": {"coordinates":[-121.789866,39.760985],"type":"Point"}
}