{
  "type": "Feature",
  "properties": {
    "iso:country":"US",
    "sg:address":"2150 Main St",
    "sg:city":"Red Bluff",
    "sg:classifiers":[
        {
            "category":"Banks & Credit Unions",
            "subcategory":"Investment Brokerage",
            "type":"Services"
        }
    ],
    "sg:phone":"+1 530 529 0760",
    "sg:postcode":"96080",
    "sg:province":"CA",
    "sg:tags":[
        "security"
    ],
    "wof:name":"First Wall Street",
    "wof:placetype":"venue"
},
  "geometry": {"coordinates":[-122.241228,40.19564],"type":"Point"}
}