{
  "type": "Feature",
  "properties": {
    "addr:full":"555 E Hardy St Inglewood CA 90301",
    "addr:housenumber":"555",
    "addr:postcode":"90301",
    "addr:street":"E Hardy St",
    "iso:country":"US",
    "sg:address":"555 E Hardy St",
    "sg:city":"Inglewood",
    "sg:classifiers":[
        {
            "category":"Sports & Exercise",
            "subcategory":"Gym",
            "type":"Entertainment"
        }
    ],
    "sg:phone":"+1 310 649 6700",
    "sg:postcode":"90301",
    "sg:province":"CA",
    "sg:tags":[
        "trainer"
    ],
    "wof:name":"Centinela Hospital Fitness Institute",
    "wof:placetype":"venue"
},
  "geometry": {"coordinates":[-118.348,33.9492],"type":"Point"}
}