{
  "type": "Feature",
  "properties": {
    "iso:country":"US",
    "sg:address":"6782 Stanton Ave Ste F",
    "sg:city":"Buena Park",
    "sg:classifiers":[
        {
            "category":"Place Of Worship",
            "subcategory":"Church",
            "type":"Public Place"
        }
    ],
    "sg:phone":"+1 714 994 3200",
    "sg:postcode":"90621",
    "sg:province":"CA",
    "sg:website":"www.stepoffministry.com",
    "wof:name":"Step Off Ministry",
    "wof:placetype":"venue"
},
  "geometry": {"coordinates":[-117.993757,33.861793],"type":"Point"}
}