{
  "type": "Feature",
  "properties": {
    "addr:full":"1401 S 6th Ave Arcadia CA 91006",
    "addr:housenumber":"1401",
    "addr:postcode":"91006",
    "addr:street":"S 6Th Ave",
    "iso:country":"US",
    "sg:address":"1401 S 6th Ave",
    "sg:city":"Arcadia",
    "sg:classifiers":[
        {
            "category":"Manufacturing",
            "subcategory":"Retail Goods",
            "type":"Manufacturing & Wholesale Goods"
        }
    ],
    "sg:phone":"+1 626 447 1866",
    "sg:postcode":"91006",
    "sg:province":"CA",
    "sg:tags":[
        "product",
        "mfg"
    ],
    "wof:name":"Josh Ochs",
    "wof:placetype":"venue"
},
  "geometry": {"coordinates":[-118.018761,34.12464],"type":"Point"}
}