{
  "type": "Feature",
  "properties": {
    "addr:full":"400 W 157th St Gardena CA 90248",
    "addr:housenumber":"400",
    "addr:postcode":"90248",
    "addr:street":"W 157Th St",
    "iso:country":"US",
    "sg:address":"400 W 157th St",
    "sg:city":"Gardena",
    "sg:classifiers":[
        {
            "category":"Freight",
            "type":"Transportation"
        }
    ],
    "sg:phone":"+1 310 515 5355",
    "sg:postcode":"90248",
    "sg:province":"CA",
    "sg:tags":[
        "arrangement"
    ],
    "wof:name":"Freight Enterprises",
    "wof:placetype":"venue"
},
  "geometry": {"coordinates":[-118.280344,33.889088],"type":"Point"}
}