{
  "type": "Feature",
  "properties": {
    "addr:full":"5105 Venice Blvd Los Angeles CA 90019",
    "addr:housenumber":"5105",
    "addr:postcode":"90019",
    "addr:street":"Venice Blvd",
    "iso:country":"US",
    "sg:address":"5105 Venice Blvd",
    "sg:city":"Los Angeles",
    "sg:classifiers":[
        {
            "category":"Restaurant",
            "type":"Food & Drink"
        }
    ],
    "sg:phone":"+1 323 936 0231",
    "sg:postcode":"90019",
    "sg:province":"CA",
    "sg:tags":[
        "american",
        "latin"
    ],
    "sg:website":"www.esconsabor.com",
    "wof:name":"Con Sabor Restaurant",
    "wof:placetype":"venue"
},
  "geometry": {"coordinates":[-118.350998,34.045101],"type":"Point"}
}