{
  "type": "Feature",
  "properties": {
    "addr:full":"1150 E Almond Ave Madera CA 93637",
    "addr:housenumber":"1150",
    "addr:postcode":"93637",
    "addr:street":"E Almond Ave",
    "iso:country":"US",
    "sg:address":"1150 E Almond Ave",
    "sg:city":"Madera",
    "sg:classifiers":[
        {
            "category":"Health Services",
            "subcategory":"Doctor",
            "type":"Services"
        },
        {
            "category":"Health Services",
            "subcategory":"Dentist",
            "type":"Services"
        }
    ],
    "sg:phone":"+1 559 674 9122",
    "sg:postcode":"93637",
    "sg:province":"CA",
    "sg:tags":[
        "dentists-oral",
        "physician",
        "maxillofacial",
        "surgeons",
        "surgery",
        "oral"
    ],
    "wof:name":"Bryan John DMD",
    "wof:placetype":"venue"
},
  "geometry": {"coordinates":[-120.04577399999999,36.945436],"type":"Point"}
}