{
  "type": "Feature",
  "properties": {
    "iso:country":"US",
    "sg:address":"1303 W 135th St",
    "sg:city":"Gardena",
    "sg:classifiers":[
        {
            "category":"Building & Trades",
            "subcategory":"Construction",
            "type":"Services"
        }
    ],
    "sg:phone":"+1 800 439 9722",
    "sg:postcode":"90247",
    "sg:province":"CA",
    "sg:tags":[
        "maker",
        "cabinet"
    ],
    "wof:name":"Premiere Cabinets",
    "wof:placetype":"venue"
},
  "geometry": {"coordinates":[-118.298935,33.909181],"type":"Point"}
}