{
  "type": "Feature",
  "properties": {
    "addr:full":"101 Main St Huntington Beach CA 92648",
    "addr:housenumber":"101",
    "addr:postcode":"92648",
    "addr:street":"Main St",
    "iso:country":"US",
    "sg:address":"101 Main St",
    "sg:city":"Huntington Beach",
    "sg:classifiers":[
        {
            "category":"Wholesale",
            "subcategory":"Non-durable Goods",
            "type":"Manufacturing & Wholesale Goods"
        }
    ],
    "sg:phone":"+1 714 536 9238",
    "sg:postcode":"92648",
    "sg:province":"CA",
    "wof:name":"Freightsaver Com",
    "wof:placetype":"venue"
},
  "geometry": {"coordinates":[-118.00109,33.658069],"type":"Point"}
}