{
  "type": "Feature",
  "properties": {
    "addr:full":"1028 N Lake Ave Pasadena CA 91104",
    "addr:housenumber":"1028",
    "addr:postcode":"91104",
    "addr:street":"N Lake Ave",
    "iso:country":"US",
    "sg:address":"1028 N Lake Ave",
    "sg:city":"Pasadena",
    "sg:classifiers":[
        {
            "category":"Professional",
            "subcategory":"Computer Services",
            "type":"Services"
        }
    ],
    "sg:phone":"+1 213 630 5550",
    "sg:postcode":"91104",
    "sg:province":"CA",
    "sg:tags":[
        "consultant",
        "designer"
    ],
    "sg:website":"www.anei.net",
    "wof:name":"Advanced Network Engineering",
    "wof:placetype":"venue"
},
  "geometry": {"coordinates":[-118.13237700000001,34.16411],"type":"Point"}
}