{
  "type": "Feature",
  "properties": {
    "iso:country":"US",
    "sg:address":"5631 Palmer Way Ste C",
    "sg:city":"Carlsbad",
    "sg:classifiers":[
        {
            "category":"Building & Trades",
            "subcategory":"Construction",
            "type":"Services"
        }
    ],
    "sg:phone":"+1 760 304 3100",
    "sg:postcode":"92010",
    "sg:province":"CA",
    "sg:tags":[
        "handyman"
    ],
    "sg:website":"www.hometodos.com",
    "wof:name":"Home To-Do's",
    "wof:placetype":"venue"
},
  "geometry": {"coordinates":[-117.274863,33.141567],"type":"Point"}
}