{
  "type": "Feature",
  "properties": {
    "iso:country":"US",
    "sg:address":"1579 Morena Blvd",
    "sg:city":"San Diego",
    "sg:classifiers":[
        {
            "category":"Home & Garden",
            "subcategory":"Building Materials",
            "type":"Retail Goods"
        }
    ],
    "sg:phone":"+1 619 275 2683",
    "sg:postcode":"92110",
    "sg:province":"CA",
    "sg:tags":[
        "door"
    ],
    "wof:name":"J D Garage Door Installers",
    "wof:placetype":"venue"
},
  "geometry": {"coordinates":[-117.206506,32.774995],"type":"Point"}
}