{
  "type": "Feature",
  "properties": {
    "addr:full":"4036 Capstan Pl Byron CA 94505",
    "addr:housenumber":"4036",
    "addr:postcode":"94505",
    "addr:street":"Capstan Pl",
    "iso:country":"US",
    "sg:address":"4036 Capstan Pl",
    "sg:city":"Byron",
    "sg:classifiers":[
        {
            "category":"Real Estate",
            "subcategory":"Real Estate Agent",
            "type":"Services"
        }
    ],
    "sg:phone":"+1 925 634 7540",
    "sg:postcode":"94505",
    "sg:province":"CA",
    "wof:name":"Wk Associates",
    "wof:placetype":"venue"
},
  "geometry": {"coordinates":[-118.05601799999999,35.215513],"type":"Point"}
}