{
  "type": "Feature",
  "properties": {
    "iso:country":"US",
    "sg:address":"2785 Highway 46",
    "sg:city":"Wasco",
    "sg:classifiers":[
        {
            "category":"Professional",
            "type":"Services"
        },
        {
            "category":"Restaurant",
            "type":"Food & Drink"
        },
        {
            "category":"Fast Food",
            "type":"Food & Drink"
        }
    ],
    "sg:phone":"+1 661 758 3583",
    "sg:postcode":"93280",
    "sg:province":"CA",
    "sg:tags":[
        "delivery",
        "take",
        "pizza"
    ],
    "sg:website":"http://www.littlecaesars.com",
    "wof:name":"Little Caesars Pizza",
    "wof:placetype":"venue"
},
  "geometry": {"coordinates":[-119.354112,35.601494],"type":"Point"}
}