{
  "type": "Feature",
  "properties": {
    "addr:full":"4965 Valley View Ave Yorba Linda CA 92886",
    "addr:housenumber":"4965",
    "addr:postcode":"92886",
    "addr:street":"Valley View Ave",
    "iso:country":"US",
    "sg:address":"4965 Valley View Ave",
    "sg:city":"Yorba Linda",
    "sg:classifiers":[
        {
            "category":"Retail",
            "subcategory":"Animal Services",
            "type":"Services"
        }
    ],
    "sg:phone":"+1 714 577 8987",
    "sg:postcode":"92886",
    "sg:province":"CA",
    "wof:name":"Dawgs House of Grooming",
    "wof:placetype":"venue"
},
  "geometry": {"coordinates":[-117.82874,33.889218],"type":"Point"}
}