{
  "type": "Feature",
  "properties": {
    "addr:full":"888 Embarcadero del Mar Goleta CA 93117",
    "addr:housenumber":"888",
    "addr:postcode":"93117",
    "addr:street":"Embarcadero Del Mar",
    "iso:country":"US",
    "sg:address":"888 Embarcadero del Mar",
    "sg:city":"Goleta",
    "sg:classifiers":[
        {
            "category":"Restaurant",
            "type":"Food & Drink"
        }
    ],
    "sg:phone":"+1 805 685 1888",
    "sg:postcode":"93117",
    "sg:province":"CA",
    "wof:name":"Caliroll Express",
    "wof:placetype":"venue"
},
  "geometry": {"coordinates":[-119.85697500000001,34.413524],"type":"Point"}
}