{
  "type": "Feature",
  "properties": {
    "iso:country":"US",
    "sg:address":"4501 Orcutt Rd",
    "sg:city":"San Luis Obispo",
    "sg:classifiers":[
        {
            "category":"Health Services",
            "subcategory":"Doctor",
            "type":"Services"
        }
    ],
    "sg:phone":"+1 805 784 9322",
    "sg:postcode":"93401",
    "sg:province":"CA",
    "sg:tags":[
        "physician",
        "surgeon"
    ],
    "wof:name":"Robert C Palmer MD",
    "wof:placetype":"venue"
},
  "geometry": {"coordinates":[-120.60385599999999,35.238865],"type":"Point"}
}