{
  "type": "Feature",
  "properties": {
    "addr:full":"27124 Meines St Highland CA 92346",
    "addr:postcode":"27124;92346",
    "addr:street":"Meines St",
    "iso:country":"US",
    "sg:address":"27124 Meines St",
    "sg:city":"Highland",
    "sg:classifiers":[
        {
            "category":"Organizations",
            "subcategory":"Professional Association",
            "type":"Services"
        }
    ],
    "sg:phone":"+1 909 862 6810",
    "sg:postcode":"92346",
    "sg:province":"CA",
    "wof:name":"Filipino Association",
    "wof:placetype":"venue"
},
  "geometry": {"coordinates":[-117.212368,34.108814],"type":"Point"}
}