{
  "type": "Feature",
  "properties": {
    "iso:country":"US",
    "sg:address":"35056 County Line Rd",
    "sg:city":"Yucaipa",
    "sg:classifiers":[
        {
            "category":"Retail",
            "subcategory":"Storage",
            "type":"Services"
        }
    ],
    "sg:phone":"+1 909 446 0610",
    "sg:postcode":"92399",
    "sg:province":"CA",
    "sg:tags":[
        "self"
    ],
    "wof:name":"County Line Self Storage",
    "wof:placetype":"venue"
},
  "geometry": {"coordinates":[-117.05100299999999,34.004002],"type":"Point"}
}