{
  "type": "Feature",
  "properties": {
    "iso:country":"US",
    "sg:address":"7057 Lanewood Ave",
    "sg:city":"Los Angeles",
    "sg:classifiers":[
        {
            "category":"Communications",
            "subcategory":"Film & Video Production",
            "type":"Services"
        }
    ],
    "sg:phone":"+1 323 463 6832",
    "sg:postcode":"90028",
    "sg:province":"CA",
    "sg:tags":[
        "taping"
    ],
    "wof:name":"Streetvision Productions",
    "wof:placetype":"venue"
},
  "geometry": {"coordinates":[-118.343017,34.099282],"type":"Point"}
}