{
  "type": "Feature",
  "properties": {
    "addr:full":"253 Post St San Francisco CA 94108",
    "addr:housenumber":"253",
    "addr:postcode":"94108",
    "addr:street":"Post St",
    "iso:country":"US",
    "sg:address":"253 Post St",
    "sg:city":"San Francisco",
    "sg:classifiers":[
        {
            "category":"Shopping",
            "subcategory":"Discount & Variety Stores",
            "type":"Retail Goods"
        }
    ],
    "sg:phone":"+1 415 986 1244",
    "sg:postcode":"94108",
    "sg:province":"CA",
    "sg:tags":[
        "merchandise",
        "general"
    ],
    "wof:name":"Sharper Image",
    "wof:placetype":"venue"
},
  "geometry": {"coordinates":[-122.406109,37.788528],"type":"Point"}
}