{
  "type": "Feature",
  "properties": {
    "iso:country":"US",
    "sg:address":"1200 Ledell Dr",
    "sg:city":"Redding",
    "sg:classifiers":[
        {
            "category":"Health Services",
            "subcategory":"Medical Lab",
            "type":"Services"
        }
    ],
    "sg:phone":"+1 530 221 9391",
    "sg:postcode":"96002",
    "sg:province":"CA",
    "sg:tags":[
        "laboratory"
    ],
    "wof:name":"Excalibur Dental Laboratory",
    "wof:placetype":"venue"
},
  "geometry": {"coordinates":[-122.350706,40.547903],"type":"Point"}
}