{
  "type": "Feature",
  "properties": {
    "iso:country":"US",
    "sg:address":"4520 E Washington Blvd",
    "sg:city":"Commerce",
    "sg:classifiers":[
        {
            "category":"Manufacturing",
            "subcategory":"Textiles",
            "type":"Manufacturing & Wholesale Goods"
        }
    ],
    "sg:phone":"+1 800 576 6942",
    "sg:postcode":"90040",
    "sg:province":"CA",
    "sg:tags":[
        "brakes-lining-wholesale",
        "manufacturer"
    ],
    "wof:name":"Hicks Enterprises",
    "wof:placetype":"venue"
},
  "geometry": {"coordinates":[-118.176547,34.00599],"type":"Point"}
}