{
  "type": "Feature",
  "properties": {
    "addr:full":"1244 S Bascom Avenue San Jose CA 95128",
    "addr:housenumber":"1244",
    "addr:postcode":"95128",
    "addr:street":"S Bascom Avenue",
    "iso:country":"US",
    "sg:address":"1244 S Bascom Avenue",
    "sg:city":"San Jose",
    "sg:classifiers":[
        {
            "category":"Sports & Exercise",
            "subcategory":"Gym",
            "type":"Entertainment"
        }
    ],
    "sg:phone":"+1 408 286 8663",
    "sg:postcode":"95128",
    "sg:province":"CA",
    "wof:name":"Curves For Women",
    "wof:placetype":"venue"
},
  "geometry": {"coordinates":[-121.93176800000001,37.303127],"type":"Point"}
}