{
  "type": "Feature",
  "properties": {
    "addr:full":"5644 N Blackstone Ave Fresno CA 93710",
    "addr:housenumber":"5644",
    "addr:postcode":"93710",
    "addr:street":"N Blackstone Ave",
    "iso:country":"US",
    "sg:address":"5644 N Blackstone Ave",
    "sg:city":"Fresno",
    "sg:classifiers":[
        {
            "category":"Wholesale",
            "subcategory":"Plants",
            "type":"Manufacturing & Wholesale Goods"
        }
    ],
    "sg:phone":"+1 559 439 2981",
    "sg:postcode":"93710",
    "sg:province":"CA",
    "sg:tags":[
        "florist"
    ],
    "wof:name":"Aurora's Flowers Wholesale",
    "wof:placetype":"venue"
},
  "geometry": {"coordinates":[-119.79028,36.822071],"type":"Point"}
}