{
  "type": "Feature",
  "properties": {
    "addr:full":"702 E Heil Ave El Centro CA 92243",
    "addr:housenumber":"702",
    "addr:postcode":"92243",
    "addr:street":"E Heil Ave",
    "iso:country":"US",
    "sg:address":"702 E Heil Ave",
    "sg:city":"El Centro",
    "sg:classifiers":[
        {
            "category":"Utilities",
            "subcategory":"Refuse",
            "type":"Services"
        },
        {
            "category":"Wholesale",
            "subcategory":"Scrap",
            "type":"Manufacturing & Wholesale Goods"
        }
    ],
    "sg:phone":"+1 760 336 0044",
    "sg:postcode":"92243",
    "sg:province":"CA",
    "sg:tags":[
        "recycling",
        "center",
        "system"
    ],
    "wof:name":"Valley Environmental Services",
    "wof:placetype":"venue"
},
  "geometry": {"coordinates":[-115.528584,32.787027],"type":"Point"}
}