{
  "type": "Feature",
  "properties": {
    "addr:full":"4630 Natomas Blvd Ste 100 Sacramento CA 95835",
    "addr:housenumber":"4630",
    "addr:postcode":"95835",
    "addr:street":"Natomas Blvd Ste 100",
    "iso:country":"US",
    "sg:address":"4630 Natomas Blvd Ste 100",
    "sg:city":"Sacramento",
    "sg:classifiers":[
        {
            "category":"Fast Food",
            "type":"Food & Drink"
        }
    ],
    "sg:phone":"+1 916 419 4109",
    "sg:postcode":"95835",
    "sg:province":"CA",
    "sg:tags":[
        "burger"
    ],
    "sg:website":"www.fiveguys.com",
    "wof:name":"Five Guys Burgers and Fries",
    "wof:placetype":"venue"
},
  "geometry": {"coordinates":[-121.51184499999999,38.656804],"type":"Point"}
}