{
  "type": "Feature",
  "properties": {
    "iso:country":"US",
    "sg:address":"1321 8th St Ste 2",
    "sg:city":"Berkeley",
    "sg:classifiers":[
        {
            "category":"Real Estate",
            "subcategory":"Architect",
            "type":"Services"
        }
    ],
    "sg:phone":"+1 510 528 5477",
    "sg:postcode":"94710",
    "sg:province":"CA",
    "sg:website":"www.toddjerseyarchitecture.com",
    "wof:name":"Todd Jersey Architecture",
    "wof:placetype":"venue"
},
  "geometry": {"coordinates":[-122.29889799999999,37.879485],"type":"Point"}
}