{
  "type": "Feature",
  "properties": {
    "addr:full":"424 Corte Mismo Bakersfield CA 93314",
    "addr:housenumber":"424",
    "addr:postcode":"93314",
    "addr:street":"Corte Mismo",
    "iso:country":"US",
    "sg:address":"424 Corte Mismo",
    "sg:city":"Bakersfield",
    "sg:classifiers":[
        {
            "category":"Manufacturing",
            "subcategory":"Signs",
            "type":"Manufacturing & Wholesale Goods"
        }
    ],
    "sg:phone":"+1 661 588 4405",
    "sg:postcode":"93314",
    "sg:province":"CA",
    "sg:tags":[
        "specialty",
        "mfg"
    ],
    "wof:name":"Southwest Signs",
    "wof:placetype":"venue"
},
  "geometry": {"coordinates":[-119.158339,35.358647],"type":"Point"}
}