{
  "type": "Feature",
  "properties": {
    "iso:country":"US",
    "sg:address":"1541 E Brundage Ln",
    "sg:city":"Bakersfield",
    "sg:classifiers":[
        {
            "category":"Wholesale",
            "subcategory":"Construction Materials",
            "type":"Manufacturing & Wholesale Goods"
        }
    ],
    "sg:phone":"+1 661 324 5799",
    "sg:postcode":"93307",
    "sg:province":"CA",
    "sg:tags":[
        "sand",
        "gravel"
    ],
    "wof:name":"Mid-Cal Materials Inc",
    "wof:placetype":"venue"
},
  "geometry": {"coordinates":[-118.978127,35.353935],"type":"Point"}
}