{
  "type": "Feature",
  "properties": {
    "iso:country":"US",
    "sg:address":"Suite 100 11149 Brockway Road",
    "sg:city":"Truckee",
    "sg:classifiers":[
        {
            "category":"Professional",
            "subcategory":"Lawyer & Legal Services",
            "type":"Services"
        }
    ],
    "sg:phone":"+1 215 979 1000",
    "sg:postcode":"96161-2213",
    "sg:province":"CA",
    "sg:website":"http://www.duanemorris.com",
    "wof:name":"Duane Morris LLP",
    "wof:placetype":"venue"
},
  "geometry": {"coordinates":[-120.182776,39.326119],"type":"Point"}
}