{
  "type": "Feature",
  "properties": {
    "iso:country":"US",
    "sg:address":"4850 Freedom Blvd",
    "sg:city":"Aptos",
    "sg:classifiers":[
        {
            "category":"Personal",
            "type":"Services"
        }
    ],
    "sg:phone":"+1 831 768 0212",
    "sg:postcode":"95003",
    "sg:province":"CA",
    "sg:tags":[
        "genealogist"
    ],
    "wof:name":"Karen L Robert",
    "wof:placetype":"venue"
},
  "geometry": {"coordinates":[-121.83363,36.986289],"type":"Point"}
}