{
  "type": "Feature",
  "properties": {
    "addr:full":"231 Nord Ave Chico CA 95926",
    "addr:housenumber":"231",
    "addr:postcode":"95926",
    "addr:street":"Nord Ave",
    "iso:country":"US",
    "sg:address":"231 Nord Ave",
    "sg:city":"Chico",
    "sg:classifiers":[
        {
            "category":"Autos & Motor Vehicles",
            "subcategory":"Motorcycle Sales",
            "type":"Retail Goods"
        }
    ],
    "sg:phone":"+1 530 342 4216",
    "sg:postcode":"95926",
    "sg:province":"CA",
    "sg:tags":[
        "scooter"
    ],
    "wof:name":"Chico Honda Motorcycles",
    "wof:placetype":"venue"
},
  "geometry": {"coordinates":[-121.850702,39.725091],"type":"Point"}
}