{
  "type": "Feature",
  "properties": {
    "iso:country":"US",
    "sg:address":"7261 Pritchard Rd",
    "sg:city":"Sacramento",
    "sg:classifiers":[
        {
            "category":"Organizations",
            "subcategory":"Religious Organization",
            "type":"Services"
        }
    ],
    "sg:phone":"+1 916 383 5781",
    "sg:postcode":"95828",
    "sg:province":"CA",
    "sg:tags":[
        "church"
    ],
    "wof:name":"Florin Baptist Church",
    "wof:placetype":"venue"
},
  "geometry": {"coordinates":[-121.399607,38.493998],"type":"Point"}
}