{
  "type": "Feature",
  "properties": {
    "addr:full":"1770 1st Ave Walnut Creek CA 94597",
    "addr:housenumber":"1770",
    "addr:postcode":"94597",
    "addr:street":"1St Ave",
    "iso:country":"US",
    "sg:address":"1770 1st Ave",
    "sg:city":"Walnut Creek",
    "sg:classifiers":[
        {
            "category":"Professional",
            "subcategory":"Accounting & Tax Preparation",
            "type":"Services"
        }
    ],
    "sg:phone":"+1 925 210 0950",
    "sg:postcode":"94597",
    "sg:province":"CA",
    "sg:tags":[
        "accountant"
    ],
    "wof:name":"Steven J Wiesenthal & Assoc",
    "wof:placetype":"venue"
},
  "geometry": {"coordinates":[-122.072761,37.924132],"type":"Point"}
}