{
  "type": "Feature",
  "properties": {
    "addr:full":"249 S Diamond Bar Blvd Diamond Bar CA 91765",
    "addr:housenumber":"249",
    "addr:postcode":"91765",
    "addr:street":"S;Blvd",
    "iso:country":"US",
    "sg:address":"249 S Diamond Bar Blvd",
    "sg:city":"Diamond Bar",
    "sg:classifiers":[
        {
            "category":"Shopping",
            "subcategory":"Department Store",
            "type":"Retail Goods"
        }
    ],
    "sg:phone":"+1 909 861 7741",
    "sg:postcode":"91765",
    "sg:province":"CA",
    "wof:name":"Kmart",
    "wof:placetype":"venue"
},
  "geometry": {"coordinates":[-117.810142,34.021181],"type":"Point"}
}