{
  "type": "Feature",
  "properties": {
    "iso:country":"US",
    "sg:address":"1232 15th St",
    "sg:city":"Santa Monica",
    "sg:classifiers":[
        {
            "category":"Health Services",
            "subcategory":"Health Practitioner",
            "type":"Services"
        }
    ],
    "sg:phone":"+1 310 395 5377",
    "sg:postcode":"90404",
    "sg:province":"CA",
    "sg:tags":[
        "psychologist"
    ],
    "wof:name":"Arla S Wallace PHD",
    "wof:placetype":"venue"
},
  "geometry": {"coordinates":[-118.486874,34.02656],"type":"Point"}
}