{
  "type": "Feature",
  "properties": {
    "addr:full":"2099 E Tahquitz Canyon Way Palm Springs CA 92262",
    "addr:housenumber":"2099",
    "addr:postcode":"92262",
    "addr:street":"E Tahquitz Canyon Way",
    "iso:country":"US",
    "sg:address":"2099 E Tahquitz Canyon Way",
    "sg:city":"Palm Springs",
    "sg:classifiers":[
        {
            "category":"Insurance",
            "subcategory":"Insurance Agent",
            "type":"Services"
        }
    ],
    "sg:phone":"+1 760 320 1111",
    "sg:postcode":"92262",
    "sg:province":"CA",
    "wof:name":"Garcia Insurance Inc",
    "wof:placetype":"venue"
},
  "geometry": {"coordinates":[-116.52475,33.823161],"type":"Point"}
}