{
  "type": "Feature",
  "properties": {
    "addr:full":"7039 Greenleaf Ave Whittier CA 90602",
    "addr:housenumber":"7039",
    "addr:postcode":"90602",
    "addr:street":"Greenleaf Ave",
    "iso:country":"US",
    "sg:address":"7039 Greenleaf Ave",
    "sg:city":"Whittier",
    "sg:classifiers":[
        {
            "category":"Restaurant",
            "type":"Food & Drink"
        }
    ],
    "sg:phone":"+1 562 698 4144",
    "sg:postcode":"90602",
    "sg:province":"CA",
    "sg:tags":[
        "mexican"
    ],
    "sg:website":"www.lapescadora.com",
    "wof:name":"La Pescadora",
    "wof:placetype":"venue"
},
  "geometry": {"coordinates":[-118.03772600000001,33.977945],"type":"Point"}
}