{
  "type": "Feature",
  "properties": {
    "addr:full":"7812 Gerber Rd Sacramento CA 95828",
    "addr:housenumber":"7812",
    "addr:postcode":"95828",
    "addr:street":"Gerber Rd",
    "iso:country":"US",
    "sg:address":"7812 Gerber Rd",
    "sg:city":"Sacramento",
    "sg:classifiers":[
        {
            "category":"Food & Beverages",
            "subcategory":"Liquor & Beverages",
            "type":"Retail Goods"
        }
    ],
    "sg:phone":"+1 916 689 2050",
    "sg:postcode":"95828",
    "sg:province":"CA",
    "sg:tags":[
        "alcoholic"
    ],
    "wof:name":"Pal's Wines & Liquor",
    "wof:placetype":"venue"
},
  "geometry": {"coordinates":[-121.41218000000001,38.481601],"type":"Point"}
}