{
  "type": "Feature",
  "properties": {
    "iso:country":"US",
    "sg:address":"1000 4th St",
    "sg:city":"San Rafael",
    "sg:classifiers":[
        {
            "category":"Real Estate",
            "subcategory":"Real Estate Agent",
            "type":"Services"
        }
    ],
    "sg:phone":"+1 415 453 8339",
    "sg:postcode":"94901",
    "sg:province":"CA",
    "wof:name":"K & C Investments",
    "wof:placetype":"venue"
},
  "geometry": {"coordinates":[-122.528205,37.973145],"type":"Point"}
}