{
  "type": "Feature",
  "properties": {
    "addr:full":"940 Ave 64 Pasadena CA 91105",
    "addr:housenumber":"940;64",
    "addr:postcode":"91105",
    "addr:street":"Ave",
    "iso:country":"US",
    "sg:address":"940 Ave 64",
    "sg:city":"Pasadena",
    "sg:classifiers":[
        {
            "category":"Social Services",
            "type":"Services"
        }
    ],
    "sg:phone":"+1 323 254 2274",
    "sg:postcode":"91105",
    "sg:province":"CA",
    "sg:tags":[
        "organization",
        "welfare"
    ],
    "sg:website":"www.hillsides.org",
    "wof:name":"Hillsides Residential",
    "wof:placetype":"venue"
},
  "geometry": {"coordinates":[-118.176451,34.126751],"type":"Point"}
}