{
  "type": "Feature",
  "properties": {
    "addr:full":"616 J Street San Diego CA 92101",
    "addr:housenumber":"616",
    "addr:postcode":"92101",
    "addr:street":"J Street",
    "iso:country":"US",
    "sg:address":"616 J Street",
    "sg:city":"San Diego",
    "sg:classifiers":[
        {
            "category":"Bars & Pubs",
            "type":"Food & Drink"
        },
        {
            "category":"Restaurant",
            "type":"Food & Drink"
        }
    ],
    "sg:phone":"+1 619 531 8744",
    "sg:postcode":"92101",
    "sg:province":"CA",
    "sg:website":"www.jsixsandiego.com/jsixjbar/in...",
    "wof:name":"LOUNGEsix",
    "wof:placetype":"venue"
},
  "geometry": {"coordinates":[-117.158997,32.709499],"type":"Point"}
}