{
  "type": "Feature",
  "properties": {
    "iso:country":"US",
    "sg:address":"42442 10th St W",
    "sg:city":"Lancaster",
    "sg:classifiers":[
        {
            "category":"Health Services",
            "subcategory":"Doctor",
            "type":"Services"
        }
    ],
    "sg:phone":"+1 661 729 3910",
    "sg:postcode":"93534",
    "sg:province":"CA",
    "sg:tags":[
        "clinic"
    ],
    "wof:name":"Palmdale Lancaster Surgery Ctr",
    "wof:placetype":"venue"
},
  "geometry": {"coordinates":[-118.14758399999999,34.652055],"type":"Point"}
}