{
  "type": "Feature",
  "properties": {
    "addr:full":"10080 Missile Way Mather CA 95655",
    "addr:postcode":"10080;95655",
    "addr:street":"Missile Way",
    "iso:country":"US",
    "sg:address":"10080 Missile Way",
    "sg:city":"Mather",
    "sg:classifiers":[
        {
            "category":"Professional",
            "subcategory":"Lawyer & Legal Services",
            "type":"Services"
        }
    ],
    "sg:phone":"+1 916 364 4440",
    "sg:postcode":"95655",
    "sg:province":"CA",
    "sg:tags":[
        "attorney",
        "law",
        "administrative",
        "governmental"
    ],
    "sg:website":"http://www.doj.state.wi.us",
    "wof:name":"California Department Of Justice",
    "wof:placetype":"venue"
},
  "geometry": {"coordinates":[-121.315702,38.557398],"type":"Point"}
}