{
  "type": "Feature",
  "properties": {
    "addr:full":"900 Post Rd Oakdale CA 95361",
    "addr:housenumber":"900",
    "addr:postcode":"95361",
    "addr:street":"Post Rd",
    "iso:country":"US",
    "sg:address":"900 Post Rd",
    "sg:city":"Oakdale",
    "sg:classifiers":[
        {
            "category":"Retail",
            "subcategory":"Veterinary Services",
            "type":"Services"
        }
    ],
    "sg:phone":"+1 209 848 1531",
    "sg:postcode":"95361",
    "sg:province":"CA",
    "sg:tags":[
        "veterinarian"
    ],
    "wof:name":"Creative Genetics",
    "wof:placetype":"venue"
},
  "geometry": {"coordinates":[-120.832639,37.760942],"type":"Point"}
}