{
  "type": "Feature",
  "properties": {
    "iso:country":"US",
    "sg:address":"42374 Radio Ln",
    "sg:city":"Auberry",
    "sg:classifiers":[
        {
            "category":"Wholesale",
            "subcategory":"Electrical",
            "type":"Manufacturing & Wholesale Goods"
        }
    ],
    "sg:phone":"+1 559 855 8390",
    "sg:postcode":"93602",
    "sg:province":"CA",
    "sg:tags":[
        "systems-wholesale",
        "communication",
        "manufacturer",
        "radio",
        "equipment"
    ],
    "wof:name":"Hk Mfg",
    "wof:placetype":"venue"
},
  "geometry": {"coordinates":[-119.43207,37.07444],"type":"Point"}
}