{
  "type": "Feature",
  "properties": {
    "iso:country":"US",
    "sg:address":"1320 S Los Angeles St",
    "sg:city":"Los Angeles",
    "sg:classifiers":[
        {
            "category":"Shopping",
            "subcategory":"Clothing, Apparel, & Fashions",
            "type":"Retail Goods"
        }
    ],
    "sg:phone":"+1 213 749 7560",
    "sg:postcode":"90015",
    "sg:province":"CA",
    "sg:tags":[
        "accessory",
        "clothing",
        "women's"
    ],
    "wof:name":"Star Boutique",
    "wof:placetype":"venue"
},
  "geometry": {"coordinates":[-118.259479,34.035006],"type":"Point"}
}