{
  "type": "Feature",
  "properties": {
    "addr:full":"1776 Botelho Dr Walnut Creek CA 94596",
    "addr:housenumber":"1776",
    "addr:postcode":"94596",
    "addr:street":"Botelho Dr",
    "iso:country":"US",
    "sg:address":"1776 Botelho Dr",
    "sg:city":"Walnut Creek",
    "sg:classifiers":[
        {
            "category":"Real Estate",
            "subcategory":"Real Estate Operator",
            "type":"Services"
        }
    ],
    "sg:phone":"+1 925 939 1900",
    "sg:postcode":"94596",
    "sg:province":"CA",
    "sg:tags":[
        "apartment"
    ],
    "wof:name":"Alpine Park Apartments",
    "wof:placetype":"venue"
},
  "geometry": {"coordinates":[-122.063652,37.893651],"type":"Point"}
}