{
  "type": "Feature",
  "properties": {
    "iso:country":"US",
    "sg:address":"4903 Torrance Blvd",
    "sg:city":"Torrance",
    "sg:classifiers":[
        {
            "category":"Restaurant",
            "type":"Food & Drink"
        }
    ],
    "sg:phone":"+1 310 542 1578",
    "sg:postcode":"90503",
    "sg:province":"CA",
    "wof:name":"Chicken Factory & More",
    "wof:placetype":"venue"
},
  "geometry": {"coordinates":[-118.36607600000001,33.837672],"type":"Point"}
}