{
  "type": "Feature",
  "properties": {
    "iso:country":"US",
    "sg:address":"809 Academy Dr",
    "sg:city":"Solana Beach",
    "sg:classifiers":[
        {
            "category":"Building & Trades",
            "subcategory":"Construction",
            "type":"Services"
        }
    ],
    "sg:phone":"+1 858 792 0861",
    "sg:postcode":"92075",
    "sg:province":"CA",
    "sg:tags":[
        "designer",
        "dealer",
        "pool",
        "swimming"
    ],
    "wof:name":"Leathem & Co",
    "wof:placetype":"venue"
},
  "geometry": {"coordinates":[-117.26017299999999,32.991108],"type":"Point"}
}