{
  "type": "Feature",
  "properties": {
    "iso:country":"US",
    "sg:address":"200 Pine Street",
    "sg:city":"San Francisco",
    "sg:classifiers":[
        {
            "category":"Fast Food",
            "type":"Food & Drink"
        },
        {
            "category":"Bakery",
            "type":"Food & Drink"
        }
    ],
    "sg:postcode":"94104",
    "sg:province":"CA",
    "sg:website":"www.thecravery.com",
    "wof:name":"The Carvery",
    "wof:placetype":"venue"
},
  "geometry": {"coordinates":[-122.399778,37.792275],"type":"Point"}
}