{
  "type": "Feature",
  "properties": {
    "addr:full":"2601 W Florence Ave Los Angeles CA 90043",
    "addr:housenumber":"2601",
    "addr:postcode":"90043",
    "addr:street":"W Florence Ave",
    "iso:country":"US",
    "sg:address":"2601 W Florence Ave",
    "sg:city":"Los Angeles",
    "sg:classifiers":[
        {
            "category":"Retail",
            "subcategory":"Auto Repair",
            "type":"Services"
        }
    ],
    "sg:phone":"+1 323 971 3560",
    "sg:postcode":"90043",
    "sg:province":"CA",
    "sg:tags":[
        "repairing",
        "automobile"
    ],
    "wof:name":"Chong's Auto Repair",
    "wof:placetype":"venue"
},
  "geometry": {"coordinates":[-118.32209400000001,33.974568],"type":"Point"}
}