{
  "type": "Feature",
  "properties": {
    "iso:country":"US",
    "sg:address":"10968 Garvey Ave",
    "sg:city":"El Monte",
    "sg:classifiers":[
        {
            "category":"Autos & Motor Vehicles",
            "subcategory":"Fuel & Gas Station",
            "type":"Retail Goods"
        }
    ],
    "sg:phone":"+1 626 443 1316",
    "sg:postcode":"91733",
    "sg:province":"CA",
    "sg:tags":[
        "oil"
    ],
    "wof:name":"Price's Auto Inspection",
    "wof:placetype":"venue"
},
  "geometry": {"coordinates":[-118.03766400000001,34.062751],"type":"Point"}
}