{
  "type": "Feature",
  "properties": {
    "addr:full":"5230 Huntington Ave Richmond CA 94804",
    "addr:housenumber":"5230",
    "addr:postcode":"94804",
    "addr:street":"Huntington Ave",
    "iso:country":"US",
    "sg:address":"5230 Huntington Ave",
    "sg:city":"Richmond",
    "sg:classifiers":[
        {
            "category":"Shopping",
            "subcategory":"Gifts & Souvenirs",
            "type":"Retail Goods"
        }
    ],
    "sg:phone":"+1 510 601 8066",
    "sg:postcode":"94804",
    "sg:province":"CA",
    "wof:name":"Lady Beau",
    "wof:placetype":"venue"
},
  "geometry": {"coordinates":[-122.314228,37.905294],"type":"Point"}
}