{
  "type": "Feature",
  "properties": {
    "iso:country":"US",
    "sg:address":"1301 17th St",
    "sg:city":"San Francisco",
    "sg:classifiers":[
        {
            "category":"Home & Garden",
            "subcategory":"Furniture",
            "type":"Retail Goods"
        }
    ],
    "sg:phone":"+1 415 553 7774",
    "sg:postcode":"94107",
    "sg:province":"CA",
    "wof:name":"Far Company",
    "wof:placetype":"venue"
},
  "geometry": {"coordinates":[-122.39773700000001,37.765072],"type":"Point"}
}