{
  "type": "Feature",
  "properties": {
    "addr:full":"9262 Magnolia Ave Riverside CA 92503",
    "addr:housenumber":"9262",
    "addr:postcode":"92503",
    "addr:street":"Magnolia Ave",
    "iso:country":"US",
    "sg:address":"9262 Magnolia Ave",
    "sg:city":"Riverside",
    "sg:classifiers":[
        {
            "category":"Building & Trades",
            "subcategory":"Cleaning & Sanitation",
            "type":"Services"
        }
    ],
    "sg:phone":"+1 951 637 3868",
    "sg:postcode":"92503",
    "sg:province":"CA",
    "sg:tags":[
        "janitor"
    ],
    "wof:name":"Unlimited Services",
    "wof:placetype":"venue"
},
  "geometry": {"coordinates":[-117.442477,33.922609],"type":"Point"}
}