{
  "type": "Feature",
  "properties": {
    "iso:country":"US",
    "sg:address":"1529 S Garey Ave",
    "sg:city":"Pomona",
    "sg:classifiers":[
        {
            "category":"Retail",
            "subcategory":"Laundry & Dry Cleaning",
            "type":"Services"
        }
    ],
    "sg:phone":"+1 909 620 1991",
    "sg:postcode":"91766",
    "sg:province":"CA",
    "wof:name":"Launderland Coin-Op Laundry",
    "wof:placetype":"venue"
},
  "geometry": {"coordinates":[-117.749666,34.042756],"type":"Point"}
}