{
  "type": "Feature",
  "properties": {
    "addr:full":"1206 3rd St San Rafael CA 94901",
    "addr:housenumber":"1206",
    "addr:postcode":"94901",
    "addr:street":"3Rd St",
    "iso:country":"US",
    "sg:address":"1206 3rd St",
    "sg:city":"San Rafael",
    "sg:classifiers":[
        {
            "category":"Professional",
            "subcategory":"Employment Agencies",
            "type":"Services"
        }
    ],
    "sg:phone":"+1 415 383 9446",
    "sg:postcode":"94901",
    "sg:province":"CA",
    "sg:tags":[
        "opportunity"
    ],
    "sg:website":"www.whimagency.com",
    "wof:name":"Whim Agency",
    "wof:placetype":"venue"
},
  "geometry": {"coordinates":[-122.53081299999999,37.972479],"type":"Point"}
}