{
  "type": "Feature",
  "properties": {
    "addr:full":"2717 W Olive Ave Burbank CA 91505",
    "addr:housenumber":"2717",
    "addr:postcode":"91505",
    "addr:street":"W Olive Ave",
    "iso:country":"US",
    "sg:address":"2717 W Olive Ave",
    "sg:city":"Burbank",
    "sg:classifiers":[
        {
            "category":"Communications",
            "subcategory":"Film & Video Production",
            "type":"Services"
        }
    ],
    "sg:phone":"+1 818 729 0800",
    "sg:postcode":"91505",
    "sg:province":"CA",
    "sg:tags":[
        "motion",
        "picture",
        "studio",
        "producer"
    ],
    "sg:website":"www.cmpla.com",
    "wof:name":"Craig Murray Productions",
    "wof:placetype":"venue"
},
  "geometry": {"coordinates":[-118.33193799999999,34.158972],"type":"Point"}
}