{
  "type": "Feature",
  "properties": {
    "addr:full":"415 Railroad Ave Danville CA 94526",
    "addr:housenumber":"415",
    "addr:postcode":"94526",
    "addr:street":"Railroad Ave",
    "iso:country":"US",
    "sg:address":"415 Railroad Ave",
    "sg:city":"Danville",
    "sg:classifiers":[
        {
            "category":"Wholesale",
            "subcategory":"Machinery & Supplies",
            "type":"Manufacturing & Wholesale Goods"
        }
    ],
    "sg:phone":"+1 925 837 7226",
    "sg:postcode":"94526",
    "sg:province":"CA",
    "sg:tags":[
        "salon",
        "beauty"
    ],
    "wof:name":"Beauty Source",
    "wof:placetype":"venue"
},
  "geometry": {"coordinates":[-121.996681,37.818971],"type":"Point"}
}