{
  "type": "Feature",
  "properties": {
    "addr:full":"4765 W Jennifer Ave Fresno CA 93722",
    "addr:housenumber":"4765",
    "addr:postcode":"93722",
    "addr:street":"W Jennifer Ave",
    "iso:country":"US",
    "sg:address":"4765 W Jennifer Ave",
    "sg:city":"Fresno",
    "sg:classifiers":[
        {
            "category":"Retail",
            "subcategory":"Repair Shop",
            "type":"Services"
        }
    ],
    "sg:phone":"+1 559 277 9780",
    "sg:postcode":"93722",
    "sg:province":"CA",
    "sg:tags":[
        "upholsterer"
    ],
    "wof:name":"Just Furniture Upholstery",
    "wof:placetype":"venue"
},
  "geometry": {"coordinates":[-119.88025,36.812542],"type":"Point"}
}