{
  "type": "Feature",
  "properties": {
    "addr:full":"160 Bonview St San Francisco CA 94110",
    "addr:housenumber":"160",
    "addr:postcode":"94110",
    "addr:street":"Bonview St",
    "iso:country":"US",
    "sg:address":"160 Bonview St",
    "sg:city":"San Francisco",
    "sg:classifiers":[
        {
            "category":"Building & Trades",
            "subcategory":"Electrical",
            "type":"Services"
        }
    ],
    "sg:phone":"+1 415 602 5862",
    "sg:postcode":"94110",
    "sg:province":"CA",
    "sg:tags":[
        "electrician",
        "electric",
        "contractor"
    ],
    "wof:name":"Mission Creek Electric",
    "wof:placetype":"venue"
},
  "geometry": {"coordinates":[-122.417894,37.741745],"type":"Point"}
}