{
  "type": "Feature",
  "properties": {
    "addr:full":"2811 Aborn Rd San Jose CA 95135",
    "addr:housenumber":"2811",
    "addr:postcode":"95135",
    "addr:street":"Aborn Rd",
    "iso:country":"US",
    "sg:address":"2811 Aborn Rd",
    "sg:city":"San Jose",
    "sg:classifiers":[
        {
            "category":"Restaurant",
            "type":"Food & Drink"
        }
    ],
    "sg:phone":"+1 408 238 8687",
    "sg:postcode":"95135",
    "sg:province":"CA",
    "wof:name":"KFC",
    "wof:placetype":"venue"
},
  "geometry": {"coordinates":[-121.79012400000001,37.31424],"type":"Point"}
}