{
  "type": "Feature",
  "properties": {
    "iso:country":"US",
    "sg:address":"11019 Jacinto Way",
    "sg:city":"Ventura",
    "sg:classifiers":[
        {
            "category":"Manufacturing",
            "subcategory":"Tools & Machinery",
            "type":"Manufacturing & Wholesale Goods"
        }
    ],
    "sg:phone":"+1 805 647 8101",
    "sg:postcode":"93004",
    "sg:province":"CA",
    "sg:tags":[
        "die",
        "maker",
        "mfg"
    ],
    "wof:name":"Pac Die",
    "wof:placetype":"venue"
},
  "geometry": {"coordinates":[-119.14581800000001,34.278533],"type":"Point"}
}