{
  "type": "Feature",
  "properties": {
    "addr:full":"25 Embarcadero Cv Oakland CA 94606",
    "addr:housenumber":"25",
    "addr:postcode":"94606",
    "addr:street":"Embarcadero Cv",
    "iso:country":"US",
    "sg:address":"25 Embarcadero Cv",
    "sg:city":"Oakland",
    "sg:classifiers":[
        {
            "category":"Retail",
            "subcategory":"Auto Rental",
            "type":"Services"
        }
    ],
    "sg:phone":"+1 510 532 0444",
    "sg:postcode":"94606",
    "sg:province":"CA",
    "sg:tags":[
        "car"
    ],
    "wof:name":"Enterprise Rent-A-Car",
    "wof:placetype":"venue"
},
  "geometry": {"coordinates":[-122.24299600000001,37.780602],"type":"Point"}
}