{
  "type": "Feature",
  "properties": {
    "iso:country":"US",
    "sg:address":"1819 W Ave H",
    "sg:city":"Lancaster",
    "sg:classifiers":[
        {
            "category":"Professional",
            "subcategory":"Employment Agencies",
            "type":"Services"
        }
    ],
    "sg:phone":"+1 661 942 8165",
    "sg:postcode":"93536",
    "sg:province":"CA",
    "sg:tags":[
        "opportunity"
    ],
    "wof:name":"Power Nanny Agency",
    "wof:placetype":"venue"
},
  "geometry": {"coordinates":[-118.167239,34.718855],"type":"Point"}
}