{
  "type": "Feature",
  "properties": {
    "addr:full":"16324 Merrill Ave Fontana CA 92335",
    "addr:housenumber":"16324",
    "addr:postcode":"92335",
    "addr:street":"Merrill Ave",
    "iso:country":"US",
    "sg:address":"16324 Merrill Ave",
    "sg:city":"Fontana",
    "sg:classifiers":[
        {
            "category":"Personal",
            "type":"Services"
        }
    ],
    "sg:phone":"+1 909 429 1259",
    "sg:postcode":"92335",
    "sg:province":"CA",
    "sg:tags":[
        "credit",
        "debt",
        "counseling"
    ],
    "wof:name":"Hump Phrey Credit Repair",
    "wof:placetype":"venue"
},
  "geometry": {"coordinates":[-117.447157,34.092171],"type":"Point"}
}