{
  "type": "Feature",
  "properties": {
    "addr:full":"7 Holland Drive Irvine CA 926077",
    "addr:housenumber":"7",
    "addr:postcode":"926077",
    "addr:street":"Holland Drive",
    "iso:country":"US",
    "sg:address":"7 Holland Drive",
    "sg:city":"Irvine",
    "sg:classifiers":[
        {
            "category":"Professional",
            "subcategory":"Computer Services",
            "type":"Services"
        }
    ],
    "sg:postcode":"926077",
    "sg:province":"CA",
    "sg:website":"http://www.designbyhumans.com/",
    "wof:name":"Design by Humans",
    "wof:placetype":"venue"
},
  "geometry": {"coordinates":[-86.18124,42.768888],"type":"Point"}
}