{
  "type": "Feature",
  "properties": {
    "iso:country":"US",
    "sg:address":"15227 Mesa Estates Ct",
    "sg:city":"Ramona",
    "sg:classifiers":[
        {
            "category":"Professional",
            "subcategory":"Advertising",
            "type":"Services"
        }
    ],
    "sg:phone":"+1 760 788 7375",
    "sg:postcode":"92065",
    "sg:province":"CA",
    "sg:tags":[
        "print"
    ],
    "sg:website":"http://www.wakeworld.com",
    "wof:name":"Ewake",
    "wof:placetype":"venue"
},
  "geometry": {"coordinates":[-116.784762,32.987722],"type":"Point"}
}