{
  "type": "Feature",
  "properties": {
    "addr:full":"8601 Bellanca Ave Los Angeles CA 90045",
    "addr:housenumber":"8601",
    "addr:postcode":"90045",
    "addr:street":"Bellanca Ave",
    "iso:country":"US",
    "sg:address":"8601 Bellanca Ave",
    "sg:city":"Los Angeles",
    "sg:classifiers":[
        {
            "category":"Restaurant",
            "type":"Food & Drink"
        }
    ],
    "sg:phone":"+1 310 410 1222",
    "sg:postcode":"90045",
    "sg:province":"CA",
    "sg:tags":[
        "breakfast",
        "brunch",
        "diner"
    ],
    "sg:website":"www.dennys.com",
    "wof:name":"Denny's",
    "wof:placetype":"venue"
},
  "geometry": {"coordinates":[-118.380735,33.959674],"type":"Point"}
}