{
  "type": "Feature",
  "properties": {
    "iso:country":"US",
    "sg:address":"2400 E Katella Ave",
    "sg:city":"Anaheim",
    "sg:classifiers":[
        {
            "category":"Wholesale",
            "subcategory":"Jewelry",
            "type":"Manufacturing & Wholesale Goods"
        }
    ],
    "sg:phone":"+1 949 370 3601",
    "sg:postcode":"92805",
    "sg:province":"CA",
    "sg:tags":[
        "buyer",
        "diamond"
    ],
    "wof:name":"Arth Brothers",
    "wof:placetype":"venue"
},
  "geometry": {"coordinates":[-117.883043,33.805817],"type":"Point"}
}