{
  "type": "Feature",
  "properties": {
    "addr:full":"9076 Campina Dr La Mesa CA 91942",
    "addr:housenumber":"9076",
    "addr:postcode":"91942",
    "addr:street":"Campina Dr",
    "iso:country":"US",
    "sg:address":"9076 Campina Dr",
    "sg:city":"La Mesa",
    "sg:classifiers":[
        {
            "category":"Real Estate",
            "subcategory":"Real Estate Operator",
            "type":"Services"
        }
    ],
    "sg:phone":"+1 619 465 3444",
    "sg:postcode":"91942",
    "sg:province":"CA",
    "sg:tags":[
        "apartment"
    ],
    "wof:name":"Park Grossmont Apartments",
    "wof:placetype":"venue"
},
  "geometry": {"coordinates":[-117.001999,32.7845],"type":"Point"}
}