{
  "type": "Feature",
  "properties": {
    "iso:country":"US",
    "sg:address":"2999 College Ave",
    "sg:city":"Berkeley",
    "sg:classifiers":[
        {
            "category":"Arts & Performance",
            "subcategory":"Art Gallery",
            "type":"Entertainment"
        },
        {
            "category":"Farming",
            "subcategory":"Fish & Marine Products",
            "type":"Manufacturing & Wholesale Goods"
        },
        {
            "category":"Professional",
            "subcategory":"Art Services",
            "type":"Services"
        }
    ],
    "sg:phone":"+1 510 644 2356",
    "sg:postcode":"94705",
    "sg:province":"CA",
    "sg:tags":[
        "picture",
        "frame",
        "framing"
    ],
    "sg:website":"www.frame-o-rama.com",
    "wof:name":"Frame-O-Rama",
    "wof:placetype":"venue"
},
  "geometry": {"coordinates":[-122.252937,37.855922],"type":"Point"}
}