{
  "type": "Feature",
  "properties": {
    "iso:country":"US",
    "sg:address":"523 Encinitas Blvd",
    "sg:city":"Encinitas",
    "sg:classifiers":[
        {
            "category":"Banks & Credit Unions",
            "subcategory":"Bank",
            "type":"Services"
        }
    ],
    "sg:phone":"+1 760 634 6536",
    "sg:postcode":"92024",
    "sg:province":"CA",
    "sg:tags":[
        "escrow"
    ],
    "wof:name":"Pickford Realty Escrow Div",
    "wof:placetype":"venue"
},
  "geometry": {"coordinates":[-117.280422,33.04682],"type":"Point"}
}