{
  "type": "Feature",
  "properties": {
    "addr:full":"583 E Dinuba Ave Reedley CA 93654",
    "addr:housenumber":"583",
    "addr:postcode":"93654",
    "addr:street":"E Dinuba Ave",
    "iso:country":"US",
    "sg:address":"583 E Dinuba Ave",
    "sg:city":"Reedley",
    "sg:classifiers":[
        {
            "category":"Wholesale",
            "subcategory":"Electrical",
            "type":"Manufacturing & Wholesale Goods"
        }
    ],
    "sg:phone":"+1 559 638 5115",
    "sg:postcode":"93654",
    "sg:province":"CA",
    "sg:tags":[
        "control"
    ],
    "wof:name":"Valley Controls",
    "wof:placetype":"venue"
},
  "geometry": {"coordinates":[-119.444992,36.589623],"type":"Point"}
}