{
  "type": "Feature",
  "properties": {
    "iso:country":"US",
    "sg:address":"2636 Leonis Blvd",
    "sg:city":"Los Angeles",
    "sg:classifiers":[
        {
            "category":"Banks & Credit Unions",
            "subcategory":"Bank",
            "type":"Services"
        }
    ],
    "sg:phone":"+1 323 581 0008",
    "sg:postcode":"90058",
    "sg:province":"CA",
    "wof:name":"Angelus Can Employees Fcu",
    "wof:placetype":"venue"
},
  "geometry": {"coordinates":[-118.22322800000001,33.999955],"type":"Point"}
}