{
  "type": "Feature",
  "properties": {
    "addr:full":"320 Santa Fe Dr Ste Ll4 Encinitas CA 92024",
    "addr:housenumber":"320",
    "addr:postcode":"92024",
    "addr:street":"Santa Fe Dr Ste Ll4",
    "iso:country":"US",
    "sg:address":"320 Santa Fe Dr Ste Ll4",
    "sg:city":"Encinitas",
    "sg:classifiers":[
        {
            "category":"Health Services",
            "subcategory":"Doctor",
            "type":"Services"
        }
    ],
    "sg:phone":"+1 760 944 4407",
    "sg:postcode":"92024",
    "sg:province":"CA",
    "wof:name":"Margot J Aiken, MD",
    "wof:placetype":"venue"
},
  "geometry": {"coordinates":[-117.28562599999999,33.038824],"type":"Point"}
}