{
  "type": "Feature",
  "properties": {
    "iso:country":"US",
    "sg:address":"965 Balboa Ave",
    "sg:city":"Coronado",
    "sg:classifiers":[
        {
            "category":"Organizations",
            "subcategory":"Non-profit Organization",
            "type":"Services"
        }
    ],
    "sg:phone":"+1 858 616 5818",
    "sg:postcode":"92118",
    "sg:province":"CA",
    "sg:tags":[
        "health",
        "welfare"
    ],
    "wof:name":"Health & Human Services",
    "wof:placetype":"venue"
},
  "geometry": {"coordinates":[-117.189941,32.693117],"type":"Point"}
}