{
  "type": "Feature",
  "properties": {
    "addr:full":"430 Cornish Ct Oakley CA 94561",
    "addr:housenumber":"430",
    "addr:postcode":"94561",
    "addr:street":"Cornish Ct",
    "iso:country":"US",
    "sg:address":"430 Cornish Ct",
    "sg:city":"Oakley",
    "sg:classifiers":[
        {
            "category":"Shopping",
            "type":"Retail Goods"
        }
    ],
    "sg:phone":"+1 925 625 8082",
    "sg:postcode":"94561",
    "sg:province":"CA",
    "sg:tags":[
        "trophy",
        "medal",
        "award"
    ],
    "wof:name":"Star Awards",
    "wof:placetype":"venue"
},
  "geometry": {"coordinates":[-121.72202799999999,37.991783],"type":"Point"}
}