{
  "type": "Feature",
  "properties": {
    "addr:full":"1472 B St Livingston CA 95334",
    "addr:housenumber":"1472",
    "addr:postcode":"95334",
    "addr:street":"B St",
    "iso:country":"US",
    "sg:address":"1472 B St",
    "sg:city":"Livingston",
    "sg:classifiers":[
        {
            "category":"Banks & Credit Unions",
            "subcategory":"Investment Brokerage",
            "type":"Services"
        }
    ],
    "sg:phone":"+1 209 394 8162",
    "sg:postcode":"95334",
    "sg:province":"CA",
    "sg:tags":[
        "advisory",
        "financial"
    ],
    "wof:name":"Patterson Financial",
    "wof:placetype":"venue"
},
  "geometry": {"coordinates":[-120.722585,37.385878],"type":"Point"}
}