{
  "type": "Feature",
  "properties": {
    "iso:country":"US",
    "sg:address":"1490 S Vineyard Ave",
    "sg:city":"Ontario",
    "sg:classifiers":[
        {
            "category":"Wholesale",
            "subcategory":"Groceries",
            "type":"Manufacturing & Wholesale Goods"
        }
    ],
    "sg:phone":"+1 909 947 9848",
    "sg:postcode":"91761",
    "sg:province":"CA",
    "sg:tags":[
        "grocer"
    ],
    "wof:name":"Universal Wholesale Inc",
    "wof:placetype":"venue"
},
  "geometry": {"coordinates":[-117.61099,34.048396],"type":"Point"}
}