{
  "type": "Feature",
  "properties": {
    "iso:country":"US",
    "sg:address":"4165 Commercial Dr",
    "sg:city":"Tracy",
    "sg:classifiers":[
        {
            "category":"Wholesale",
            "subcategory":"Machinery & Supplies",
            "type":"Manufacturing & Wholesale Goods"
        }
    ],
    "sg:phone":"+1 209 836 3780",
    "sg:postcode":"95304",
    "sg:province":"CA",
    "sg:tags":[
        "industrial"
    ],
    "wof:name":"CA",
    "wof:placetype":"venue"
},
  "geometry": {"coordinates":[-121.429163,37.766623],"type":"Point"}
}