{
  "type": "Feature",
  "properties": {
    "addr:full":"2219 Cowlin Avenue Los Angeles CA 90040",
    "addr:housenumber":"2219",
    "addr:postcode":"90040",
    "addr:street":"Cowlin Avenue",
    "iso:country":"US",
    "sg:address":"2219 Cowlin Avenue",
    "sg:city":"Los Angeles",
    "sg:classifiers":[
        {
            "category":"Building & Trades",
            "subcategory":"Plumbing",
            "type":"Services"
        }
    ],
    "sg:phone":"+1 323 262 5193",
    "sg:postcode":"90040",
    "sg:province":"CA",
    "wof:name":"A B C Plumbing & Heating Company",
    "wof:placetype":"venue"
},
  "geometry": {"coordinates":[-118.16402100000001,34.006556],"type":"Point"}
}