{
  "type": "Feature",
  "properties": {
    "iso:country":"US",
    "sg:address":"640 N 9th St",
    "sg:city":"San Jose",
    "sg:classifiers":[
        {
            "category":"Restaurant",
            "type":"Food & Drink"
        }
    ],
    "sg:phone":"+1 408 298 6389",
    "sg:postcode":"95112",
    "sg:province":"CA",
    "sg:tags":[
        "vietnamese"
    ],
    "wof:name":"Lee's Sandwiches",
    "wof:placetype":"venue"
},
  "geometry": {"coordinates":[-121.89099899999999,37.351799],"type":"Point"}
}