{
  "type": "Feature",
  "properties": {
    "addr:full":"1888 Century Park E Suite 1550 Los Angeles CA 90067",
    "addr:housenumber":"1888",
    "addr:postcode":"90067",
    "addr:street":"Century Park E Suite 1550",
    "iso:country":"US",
    "sg:address":"1888 Century Park E Suite 1550",
    "sg:city":"Los Angeles",
    "sg:classifiers":[
        {
            "category":"Professional",
            "subcategory":"Lawyer & Legal Services",
            "type":"Services"
        }
    ],
    "sg:phone":"+1 310 277 7747",
    "sg:postcode":"90067",
    "sg:province":"CA",
    "wof:name":"Williamson Richard E --Atty--",
    "wof:placetype":"venue"
},
  "geometry": {"coordinates":[-118.41447700000001,34.061301],"type":"Point"}
}