{
  "type": "Feature",
  "properties": {
    "addr:full":"8001 Canoga Ave Canoga Park CA 91304",
    "addr:housenumber":"8001",
    "addr:postcode":"91304",
    "addr:street":"Canoga Ave",
    "iso:country":"US",
    "sg:address":"8001 Canoga Ave",
    "sg:city":"Canoga Park",
    "sg:classifiers":[
        {
            "category":"Education",
            "subcategory":"Vocational School",
            "type":"Public Place"
        }
    ],
    "sg:phone":"+1 818 888 6267",
    "sg:postcode":"91304",
    "sg:province":"CA",
    "wof:name":"Contractors State License Schl",
    "wof:placetype":"venue"
},
  "geometry": {"coordinates":[-118.59753499999999,34.219789],"type":"Point"}
}