{
  "type": "Feature",
  "properties": {
    "addr:full":"1991 Village Park Way Encinitas CA 92024",
    "addr:housenumber":"1991",
    "addr:postcode":"92024",
    "addr:street":"Village Park Way",
    "iso:country":"US",
    "sg:address":"1991 Village Park Way",
    "sg:city":"Encinitas",
    "sg:classifiers":[
        {
            "category":"Personal",
            "subcategory":"Massage",
            "type":"Services"
        }
    ],
    "sg:phone":"+1 760 415 8620",
    "sg:postcode":"92024",
    "sg:province":"CA",
    "sg:website":"www.bodytherapyarts.com",
    "wof:name":"Tripp Valerie",
    "wof:placetype":"venue"
},
  "geometry": {"coordinates":[-117.245284,33.053138],"type":"Point"}
}