{
  "type": "Feature",
  "properties": {
    "addr:full":"1366 Heritage Ct Escondido CA 92027",
    "addr:housenumber":"1366",
    "addr:postcode":"92027",
    "addr:street":"Heritage Ct",
    "iso:country":"US",
    "sg:address":"1366 Heritage Ct",
    "sg:city":"Escondido",
    "sg:classifiers":[
        {
            "category":"Wholesale",
            "subcategory":"Durable Goods & Equipment",
            "type":"Manufacturing & Wholesale Goods"
        }
    ],
    "sg:phone":"+1 760 480 0473",
    "sg:postcode":"92027",
    "sg:province":"CA",
    "sg:tags":[
        "representative",
        "manufacturer"
    ],
    "sg:website":"www.sccontrols.com",
    "wof:name":"S C Controls",
    "wof:placetype":"venue"
},
  "geometry": {"coordinates":[-117.05828099999999,33.123126],"type":"Point"}
}