{
  "type": "Feature",
  "properties": {
    "addr:full":"1073 Westward Way Sacramento CA 95833",
    "addr:housenumber":"1073",
    "addr:postcode":"95833",
    "addr:street":"Westward Way",
    "iso:country":"US",
    "sg:address":"1073 Westward Way",
    "sg:city":"Sacramento",
    "sg:classifiers":[
        {
            "category":"Restaurant",
            "type":"Food & Drink"
        }
    ],
    "sg:phone":"+1 916 565 1196",
    "sg:postcode":"95833",
    "sg:province":"CA",
    "sg:tags":[
        "parlor",
        "ice",
        "cream"
    ],
    "wof:name":"N A Ice Cream",
    "wof:placetype":"venue"
},
  "geometry": {"coordinates":[-121.484999,38.624687],"type":"Point"}
}