{
  "type": "Feature",
  "properties": {
    "iso:country":"US",
    "sg:address":"4900 Madison Ave",
    "sg:city":"Sacramento",
    "sg:classifiers":[
        {
            "category":"Shopping",
            "subcategory":"Florist",
            "type":"Retail Goods"
        }
    ],
    "sg:phone":"+1 916 348 0777",
    "sg:postcode":"95841",
    "sg:province":"CA",
    "wof:name":"Madison Avenue Florist",
    "wof:placetype":"venue"
},
  "geometry": {"coordinates":[-121.350511,38.660712],"type":"Point"}
}