{
  "type": "Feature",
  "properties": {
    "addr:full":"13331 Beach Blvd Westminster CA 92683",
    "addr:housenumber":"13331",
    "addr:postcode":"92683",
    "addr:street":"Beach Blvd",
    "iso:country":"US",
    "sg:address":"13331 Beach Blvd",
    "sg:city":"Westminster",
    "sg:classifiers":[
        {
            "category":"Retail",
            "subcategory":"Portrait Studio",
            "type":"Services"
        }
    ],
    "sg:phone":"+1 714 799 3944",
    "sg:postcode":"92683",
    "sg:province":"CA",
    "sg:tags":[
        "photo"
    ],
    "wof:name":"P C A Intl Studio 2495",
    "wof:placetype":"venue"
},
  "geometry": {"coordinates":[-117.990645,33.767746],"type":"Point"}
}