{
  "type": "Feature",
  "properties": {
    "addr:full":"117 Capistrano Ct Bakersfield CA 93314",
    "addr:housenumber":"117",
    "addr:postcode":"93314",
    "addr:street":"Capistrano Ct",
    "iso:country":"US",
    "sg:address":"117 Capistrano Ct",
    "sg:city":"Bakersfield",
    "sg:classifiers":[
        {
            "category":"Mining & Drilling",
            "type":"Manufacturing & Wholesale Goods"
        }
    ],
    "sg:phone":"+1 661 589 8272",
    "sg:postcode":"93314",
    "sg:province":"CA",
    "sg:tags":[
        "oil",
        "well",
        "casing"
    ],
    "wof:name":"Wiggins Oil Tool Co Inc",
    "wof:placetype":"venue"
},
  "geometry": {"coordinates":[-119.14783300000001,35.355771],"type":"Point"}
}