{
  "type": "Feature",
  "properties": {
    "iso:country":"US",
    "sg:address":"2200 N Chester Ave",
    "sg:city":"Bakersfield",
    "sg:classifiers":[
        {
            "category":"Autos & Motor Vehicles",
            "subcategory":"Auto Supplies",
            "type":"Retail Goods"
        }
    ],
    "sg:phone":"+1 661 393 3116",
    "sg:postcode":"93308",
    "sg:province":"CA",
    "sg:tags":[
        "automobile",
        "parts"
    ],
    "wof:name":"Carquest Of Oildole",
    "wof:placetype":"venue"
},
  "geometry": {"coordinates":[-119.021239,35.426733],"type":"Point"}
}