{
  "type": "Feature",
  "properties": {
    "addr:full":"1957 W Redondo Beach Blvd Gardena CA 90247",
    "addr:housenumber":"1957",
    "addr:postcode":"90247",
    "addr:street":"W Redondo Beach Blvd",
    "iso:country":"US",
    "sg:address":"1957 W Redondo Beach Blvd",
    "sg:city":"Gardena",
    "sg:classifiers":[
        {
            "category":"Social Services",
            "subcategory":"Child Care",
            "type":"Services"
        }
    ],
    "sg:phone":"+1 310 329 4030",
    "sg:postcode":"90247",
    "sg:province":"CA",
    "sg:tags":[
        "elementary",
        "kindergarten",
        "school",
        "academic"
    ],
    "wof:name":"Presbyterian Pre-School",
    "wof:placetype":"venue"
},
  "geometry": {"coordinates":[-118.31300400000001,33.887199],"type":"Point"}
}