{
  "type": "Feature",
  "properties": {
    "addr:full":"8593 Aero Dr San Diego CA 92123",
    "addr:housenumber":"8593",
    "addr:postcode":"92123",
    "addr:street":"Aero Dr",
    "iso:country":"US",
    "sg:address":"8593 Aero Dr",
    "sg:city":"San Diego",
    "sg:classifiers":[
        {
            "category":"Professional",
            "subcategory":"Research",
            "type":"Services"
        }
    ],
    "sg:phone":"+1 619 299 5883",
    "sg:postcode":"92123",
    "sg:province":"CA",
    "sg:tags":[
        "marketing",
        "market",
        "analysis"
    ],
    "sg:website":"www.diresearch.com",
    "wof:name":"Directions In Research Inc",
    "wof:placetype":"venue"
},
  "geometry": {"coordinates":[-117.141738,32.809605],"type":"Point"}
}