{
  "type": "Feature",
  "properties": {
    "iso:country":"US",
    "sg:address":"41619 Margarita Rd",
    "sg:city":"Temecula",
    "sg:classifiers":[
        {
            "category":"Building & Trades",
            "subcategory":"Construction",
            "type":"Services"
        }
    ],
    "sg:phone":"+1 951 308 6000",
    "sg:postcode":"92591",
    "sg:province":"CA",
    "sg:tags":[
        "contractor"
    ],
    "wof:name":"Schafer Construction Group Inc",
    "wof:placetype":"venue"
},
  "geometry": {"coordinates":[-117.14994799999999,33.516312],"type":"Point"}
}