{
  "type": "Feature",
  "properties": {
    "addr:full":"1940 Oceanside Blvd Oceanside CA 92054",
    "addr:housenumber":"1940",
    "addr:postcode":"92054",
    "addr:street":"Oceanside Blvd",
    "iso:country":"US",
    "sg:address":"1940 Oceanside Blvd",
    "sg:city":"Oceanside",
    "sg:classifiers":[
        {
            "category":"Restaurant",
            "type":"Food & Drink"
        }
    ],
    "sg:phone":"+1 760 722 0925",
    "sg:postcode":"92054",
    "sg:province":"CA",
    "wof:name":"Taco Bell",
    "wof:placetype":"venue"
},
  "geometry": {"coordinates":[-117.355003,33.193901],"type":"Point"}
}