{
  "type": "Feature",
  "properties": {
    "iso:country":"US",
    "sg:address":"1576 Vervais Ave",
    "sg:city":"Vallejo",
    "sg:classifiers":[
        {
            "category":"Real Estate",
            "subcategory":"Real Estate Operator",
            "type":"Services"
        }
    ],
    "sg:phone":"+1 707 644 0131",
    "sg:postcode":"94591",
    "sg:province":"CA",
    "sg:tags":[
        "building",
        "nonresidential"
    ],
    "wof:name":"Michael J Coakley",
    "wof:placetype":"venue"
},
  "geometry": {"coordinates":[-122.224162,38.113698],"type":"Point"}
}