{
  "type": "Feature",
  "properties": {
    "addr:full":"516 Shasta Blvd Grenada CA 96038",
    "addr:housenumber":"516",
    "addr:postcode":"96038",
    "addr:street":"Shasta Blvd",
    "iso:country":"US",
    "sg:address":"516 Shasta Blvd",
    "sg:city":"Grenada",
    "sg:classifiers":[
        {
            "category":"Education",
            "subcategory":"School",
            "type":"Public Place"
        }
    ],
    "sg:phone":"+1 530 436 2233",
    "sg:postcode":"96038",
    "sg:province":"CA",
    "wof:name":"Grenada Elementary School",
    "wof:placetype":"venue"
},
  "geometry": {"coordinates":[-122.524855,41.645528],"type":"Point"}
}