{
  "type": "Feature",
  "properties": {
    "iso:country":"US",
    "sg:address":"12165 Kiowa Rd",
    "sg:city":"Apple Valley",
    "sg:classifiers":[
        {
            "category":"Home & Garden",
            "subcategory":"Household Appliances",
            "type":"Retail Goods"
        }
    ],
    "sg:phone":"+1 760 240 3756",
    "sg:postcode":"92308",
    "sg:province":"CA",
    "wof:name":"Jim's Appliance Svc",
    "wof:placetype":"venue"
},
  "geometry": {"coordinates":[-117.20767,34.473566],"type":"Point"}
}