{
  "type": "Feature",
  "properties": {
    "addr:full":"3936 Bardaquera Pl Bonita CA 91902",
    "addr:housenumber":"3936",
    "addr:postcode":"91902",
    "addr:street":"Bardaquera Pl",
    "iso:country":"US",
    "sg:address":"3936 Bardaquera Pl",
    "sg:city":"Bonita",
    "sg:classifiers":[
        {
            "category":"Place Of Worship",
            "subcategory":"Church",
            "type":"Public Place"
        },
        {
            "category":"Place Of Worship",
            "type":"Public Place"
        }
    ],
    "sg:phone":"+1 619 267 0080",
    "sg:postcode":"91902",
    "sg:province":"CA",
    "sg:tags":[
        "churches-salvation",
        "army"
    ],
    "wof:name":"Bentley Priory",
    "wof:placetype":"venue"
},
  "geometry": {"coordinates":[-117.045242,32.666409],"type":"Point"}
}