{
  "type": "Feature",
  "properties": {
    "addr:full":"9925 Main St Monte Rio CA 95462",
    "addr:housenumber":"9925",
    "addr:postcode":"95462",
    "addr:street":"Main St",
    "iso:country":"US",
    "sg:address":"9925 Main St",
    "sg:city":"Monte Rio",
    "sg:classifiers":[
        {
            "category":"Sports & Exercise",
            "subcategory":"Gym",
            "type":"Entertainment"
        }
    ],
    "sg:phone":"+1 707 865 9230",
    "sg:postcode":"95462",
    "sg:province":"CA",
    "sg:tags":[
        "pilate"
    ],
    "sg:website":"www.russianriverpilates.com",
    "wof:name":"Russian River Pilates",
    "wof:placetype":"venue"
},
  "geometry": {"coordinates":[-123.009215,38.463772],"type":"Point"}
}