{
  "type": "Feature",
  "properties": {
    "iso:country":"US",
    "sg:address":"3000 Dutton Ave",
    "sg:city":"Santa Rosa",
    "sg:classifiers":[
        {
            "category":"Freight",
            "type":"Transportation"
        }
    ],
    "sg:phone":"+1 707 547 0840",
    "sg:postcode":"95407",
    "sg:province":"CA",
    "sg:tags":[
        "commercial",
        "storage"
    ],
    "wof:name":"Global Portable Buildings",
    "wof:placetype":"venue"
},
  "geometry": {"coordinates":[-122.723512,38.40381],"type":"Point"}
}