{
  "type": "Feature",
  "properties": {
    "iso:country":"US",
    "sg:address":"8474 Old Redwood Hwy",
    "sg:city":"Windsor",
    "sg:classifiers":[
        {
            "category":"Home & Garden",
            "subcategory":"Building Materials",
            "type":"Retail Goods"
        }
    ],
    "sg:phone":"+1 707 838 4359",
    "sg:postcode":"95492",
    "sg:province":"CA",
    "sg:tags":[
        "shower",
        "door",
        "enclosure"
    ],
    "wof:name":"Sequoia Glass",
    "wof:placetype":"venue"
},
  "geometry": {"coordinates":[-122.80129100000001,38.54391],"type":"Point"}
}