{
  "type": "Feature",
  "properties": {
    "addr:full":"1900 E Wooley Rd Oxnard CA 93030",
    "addr:housenumber":"1900",
    "addr:postcode":"93030",
    "addr:street":"E Wooley Rd",
    "iso:country":"US",
    "sg:address":"1900 E Wooley Rd",
    "sg:city":"Oxnard",
    "sg:classifiers":[
        {
            "category":"Farming",
            "subcategory":"Berry Farm",
            "type":"Manufacturing & Wholesale Goods"
        }
    ],
    "sg:phone":"+1 805 483 3678",
    "sg:postcode":"93030",
    "sg:province":"CA",
    "sg:tags":[
        "strawberry",
        "raspberry",
        "grower"
    ],
    "wof:name":"Donlon Ranch",
    "wof:placetype":"venue"
},
  "geometry": {"coordinates":[-119.144429,34.189659],"type":"Point"}
}