{
  "type": "Feature",
  "properties": {
    "addr:full":"2621 Bayview Dr Alameda CA 94501",
    "addr:housenumber":"2621",
    "addr:postcode":"94501",
    "addr:street":"Bayview Dr",
    "iso:country":"US",
    "sg:address":"2621 Bayview Dr",
    "sg:city":"Alameda",
    "sg:classifiers":[
        {
            "category":"Home & Garden",
            "subcategory":"Garden Supply",
            "type":"Retail Goods"
        }
    ],
    "sg:phone":"+1 510 523 8125",
    "sg:postcode":"94501",
    "sg:province":"CA",
    "sg:tags":[
        "sprinkler"
    ],
    "wof:name":"Diablo Lawn Sprinkler Co",
    "wof:placetype":"venue"
},
  "geometry": {"coordinates":[-122.245248,37.753024],"type":"Point"}
}