{
  "type": "Feature",
  "properties": {
    "addr:full":"4519 Admiralty Way Ste 202 Marina Del Rey CA 90292",
    "addr:housenumber":"4519",
    "addr:postcode":"90292",
    "addr:street":"Admiralty Way Ste 202",
    "iso:country":"US",
    "sg:address":"4519 Admiralty Way Ste 202",
    "sg:city":"Marina Del Rey",
    "sg:classifiers":[
        {
            "category":"Professional",
            "subcategory":"Lawyer & Legal Services",
            "type":"Services"
        }
    ],
    "sg:phone":"+1 310 306 3349",
    "sg:postcode":"90292",
    "sg:province":"CA",
    "wof:name":"Levin Michael A Atty",
    "wof:placetype":"venue"
},
  "geometry": {"coordinates":[-118.444,33.983398],"type":"Point"}
}