{
  "type": "Feature",
  "properties": {
    "iso:country":"US",
    "sg:address":"607 4th St",
    "sg:city":"San Fernando",
    "sg:classifiers":[
        {
            "category":"Organizations",
            "subcategory":"Religious Organization",
            "type":"Services"
        }
    ],
    "sg:phone":"+1 818 361 4979",
    "sg:postcode":"91340",
    "sg:province":"CA",
    "sg:tags":[
        "church"
    ],
    "wof:name":"Jehovah's Witnesses",
    "wof:placetype":"venue"
},
  "geometry": {"coordinates":[-118.433052,34.282973],"type":"Point"}
}