{
  "type": "Feature",
  "properties": {
    "iso:country":"US",
    "sg:address":"26 E Gutierrez St",
    "sg:city":"Santa Barbara",
    "sg:classifiers":[
        {
            "category":"Shopping",
            "subcategory":"Bicycles & Sporting Goods",
            "type":"Retail Goods"
        }
    ],
    "sg:phone":"+1 805 899 1586",
    "sg:postcode":"93101",
    "sg:province":"CA",
    "sg:tags":[
        "equipment",
        "skateboard"
    ],
    "wof:name":"Church Of Skatan",
    "wof:placetype":"venue"
},
  "geometry": {"coordinates":[-119.69323199999999,34.416604],"type":"Point"}
}