{
  "type": "Feature",
  "properties": {
    "iso:country":"US",
    "sg:address":"25574 Rye Canyon Rd",
    "sg:city":"Valencia",
    "sg:classifiers":[
        {
            "category":"Shopping",
            "subcategory":"Catalog Store",
            "type":"Retail Goods"
        }
    ],
    "sg:phone":"+1 661 257 3949",
    "sg:postcode":"91355",
    "sg:province":"CA",
    "sg:tags":[
        "house",
        "mail"
    ],
    "wof:name":"Sey Co Fine Food Inc",
    "wof:placetype":"venue"
},
  "geometry": {"coordinates":[-118.58414999999999,34.434432],"type":"Point"}
}