{
  "type": "Feature",
  "properties": {
    "iso:country":"US",
    "sg:address":"359 W Olive Ave",
    "sg:city":"Turlock",
    "sg:classifiers":[
        {
            "category":"Building & Trades",
            "subcategory":"Construction",
            "type":"Services"
        }
    ],
    "sg:phone":"+1 209 634 3079",
    "sg:postcode":"95380",
    "sg:province":"CA",
    "sg:tags":[
        "painter"
    ],
    "wof:name":"Mercado Painting",
    "wof:placetype":"venue"
},
  "geometry": {"coordinates":[-120.851951,37.493803],"type":"Point"}
}