{
  "type": "Feature",
  "properties": {
    "addr:full":"2351 W Whittier Blvd Montebello CA 90640",
    "addr:housenumber":"2351",
    "addr:postcode":"90640",
    "addr:street":"W Whittier Blvd",
    "iso:country":"US",
    "sg:address":"2351 W Whittier Blvd",
    "sg:city":"Montebello",
    "sg:classifiers":[
        {
            "category":"Food & Beverages",
            "subcategory":"Groceries & Convenience Stores",
            "type":"Retail Goods"
        }
    ],
    "sg:phone":"+1 323 724 2044",
    "sg:postcode":"90640",
    "sg:province":"CA",
    "wof:name":"Shirak Grocery & Deli",
    "wof:placetype":"venue"
},
  "geometry": {"coordinates":[-118.126999,34.013802],"type":"Point"}
}