{
  "type": "Feature",
  "properties": {
    "iso:country":"US",
    "sg:address":"2436 N Euclid Ave",
    "sg:city":"Upland",
    "sg:classifiers":[
        {
            "category":"Wholesale",
            "subcategory":"Machinery & Supplies",
            "type":"Manufacturing & Wholesale Goods"
        }
    ],
    "sg:phone":"+1 909 920 1977",
    "sg:postcode":"91784",
    "sg:province":"CA",
    "sg:tags":[
        "rubber",
        "product"
    ],
    "wof:name":"Dichtomatik North America",
    "wof:placetype":"venue"
},
  "geometry": {"coordinates":[-117.651582,34.151438],"type":"Point"}
}