{
  "type": "Feature",
  "properties": {
    "iso:country":"US",
    "sg:address":"1535 Olympic Blvd",
    "sg:city":"Walnut Creek",
    "sg:classifiers":[
        {
            "category":"Restaurant",
            "type":"Food & Drink"
        }
    ],
    "sg:phone":"+1 925 932 9202",
    "sg:postcode":"94595",
    "sg:province":"CA",
    "wof:name":"Tiki Tom's",
    "wof:placetype":"venue"
},
  "geometry": {"coordinates":[-122.060947,37.896128],"type":"Point"}
}