{
  "type": "Feature",
  "properties": {
    "iso:country":"US",
    "sg:address":"5264 Diamond Heights Blvd",
    "sg:city":"San Francisco",
    "sg:classifiers":[
        {
            "category":"Retail",
            "subcategory":"Veterinary Services",
            "type":"Services"
        }
    ],
    "sg:phone":"+1 415 920 6980",
    "sg:postcode":"94131",
    "sg:province":"CA",
    "sg:tags":[
        "veterinarian"
    ],
    "wof:name":"Animal Health Network Inc",
    "wof:placetype":"venue"
},
  "geometry": {"coordinates":[-122.439438,37.744517],"type":"Point"}
}