{
  "type": "Feature",
  "properties": {
    "iso:country":"US",
    "sg:address":"7720 Lorraine Ave",
    "sg:city":"Stockton",
    "sg:classifiers":[
        {
            "category":"Home & Garden",
            "subcategory":"Building Materials",
            "type":"Retail Goods"
        }
    ],
    "sg:phone":"+1 209 951 2829",
    "sg:postcode":"95210",
    "sg:province":"CA",
    "sg:tags":[
        "glass",
        "window",
        "plate"
    ],
    "wof:name":"Auto Boat Commercial Window",
    "wof:placetype":"venue"
},
  "geometry": {"coordinates":[-121.283292,38.019612],"type":"Point"}
}