{
  "type": "Feature",
  "properties": {
    "addr:full":"4698 San Fernando Rd Glendale CA 91204",
    "addr:housenumber":"4698",
    "addr:postcode":"91204",
    "addr:street":"San Fernando Rd",
    "iso:country":"US",
    "sg:address":"4698 San Fernando Rd",
    "sg:city":"Glendale",
    "sg:classifiers":[
        {
            "category":"Retail",
            "subcategory":"Auto Repair",
            "type":"Services"
        }
    ],
    "sg:phone":"+1 818 246 1200",
    "sg:postcode":"91204",
    "sg:province":"CA",
    "wof:name":"Jesus Auto Shop",
    "wof:placetype":"venue"
},
  "geometry": {"coordinates":[-118.266998,34.137299],"type":"Point"}
}