{
  "type": "Feature",
  "properties": {
    "iso:country":"US",
    "sg:address":"9320 Mira Mesa Blvd",
    "sg:city":"San Diego",
    "sg:classifiers":[
        {
            "category":"Autos & Motor Vehicles",
            "subcategory":"Fuel & Gas Station",
            "type":"Retail Goods"
        }
    ],
    "sg:phone":"+1 858 566 1944",
    "sg:postcode":"92126",
    "sg:province":"CA",
    "sg:tags":[
        "oil"
    ],
    "wof:name":"Mira Mesa Black Mountain",
    "wof:placetype":"venue"
},
  "geometry": {"coordinates":[-117.120798,32.917282],"type":"Point"}
}