{
  "type": "Feature",
  "properties": {
    "iso:country":"US",
    "sg:address":"4121 Redwood Ave",
    "sg:city":"Los Angeles",
    "sg:classifiers":[
        {
            "category":"Communications",
            "subcategory":"Film & Video Production",
            "type":"Services"
        }
    ],
    "sg:phone":"+1 310 577 3737",
    "sg:postcode":"90066",
    "sg:province":"CA",
    "sg:tags":[
        "audio"
    ],
    "wof:name":"Red Productions",
    "wof:placetype":"venue"
},
  "geometry": {"coordinates":[-118.439232,33.989823],"type":"Point"}
}