{
  "type": "Feature",
  "properties": {
    "addr:full":"6023 Bristol Pkwy Culver City CA 90230",
    "addr:housenumber":"6023",
    "addr:postcode":"90230",
    "addr:street":"Bristol Pkwy",
    "iso:country":"US",
    "sg:address":"6023 Bristol Pkwy",
    "sg:city":"Culver City",
    "sg:classifiers":[
        {
            "category":"Professional",
            "subcategory":"Accounting & Tax Preparation",
            "type":"Services"
        }
    ],
    "sg:phone":"+1 310 568 9595",
    "sg:postcode":"90230",
    "sg:province":"CA",
    "sg:tags":[
        "billing"
    ],
    "sg:website":"www.sienahealthcare.com",
    "wof:name":"Siena Health Care Solutions",
    "wof:placetype":"venue"
},
  "geometry": {"coordinates":[-118.387456,33.985608],"type":"Point"}
}