{
  "type": "Feature",
  "properties": {
    "addr:full":"374 Merchant St Vacaville CA 95688",
    "addr:housenumber":"374",
    "addr:postcode":"95688",
    "addr:street":"Merchant St",
    "iso:country":"US",
    "sg:address":"374 Merchant St",
    "sg:city":"Vacaville",
    "sg:classifiers":[
        {
            "category":"Restaurant",
            "type":"Food & Drink"
        }
    ],
    "sg:phone":"+1 707 448 0490",
    "sg:postcode":"95688",
    "sg:province":"CA",
    "wof:name":"Downtown Cafe",
    "wof:placetype":"venue"
},
  "geometry": {"coordinates":[-121.989189,38.355859],"type":"Point"}
}