{
  "type": "Feature",
  "properties": {
    "addr:full":"2211 Encinitas Blvd Encinitas CA 92024",
    "addr:housenumber":"2211",
    "addr:postcode":"92024",
    "addr:street":"Encinitas Blvd",
    "iso:country":"US",
    "sg:address":"2211 Encinitas Blvd",
    "sg:city":"Encinitas",
    "sg:classifiers":[
        {
            "category":"Professional",
            "subcategory":"Management & Consulting",
            "type":"Services"
        }
    ],
    "sg:phone":"+1 760 634 2131",
    "sg:postcode":"92024",
    "sg:province":"CA",
    "sg:tags":[
        "consultant"
    ],
    "wof:name":"Latimer Consulting",
    "wof:placetype":"venue"
},
  "geometry": {"coordinates":[-117.23904899999999,33.03733],"type":"Point"}
}