{
  "type": "Feature",
  "properties": {
    "addr:full":"2880 Zanker Rd San Jose CA 95134",
    "addr:housenumber":"2880",
    "addr:postcode":"95134",
    "addr:street":"Zanker Rd",
    "iso:country":"US",
    "sg:address":"2880 Zanker Rd",
    "sg:city":"San Jose",
    "sg:classifiers":[
        {
            "category":"Education",
            "subcategory":"Vocational School",
            "type":"Public Place"
        }
    ],
    "sg:phone":"+1 408 433 0990",
    "sg:postcode":"95134",
    "sg:province":"CA",
    "sg:tags":[
        "training",
        "computer"
    ],
    "wof:name":"Mentor Training",
    "wof:placetype":"venue"
},
  "geometry": {"coordinates":[-121.928414,37.394005],"type":"Point"}
}