{
  "type": "Feature",
  "properties": {
    "addr:full":"5050 el Cajon Blvd San Diego CA 92115",
    "addr:housenumber":"5050",
    "addr:postcode":"92115",
    "addr:street":"El Cajon Blvd",
    "iso:country":"US",
    "sg:address":"5050 el Cajon Blvd",
    "sg:city":"San Diego",
    "sg:classifiers":[
        {
            "category":"Food & Beverages",
            "subcategory":"Groceries & Convenience Stores",
            "type":"Retail Goods"
        }
    ],
    "sg:phone":"+1 619 583 8512",
    "sg:postcode":"92115",
    "sg:province":"CA",
    "sg:tags":[
        "grocer"
    ],
    "wof:name":"Four Seasons Market",
    "wof:placetype":"venue"
},
  "geometry": {"coordinates":[-117.08523099999999,32.757],"type":"Point"}
}