{
  "type": "Feature",
  "properties": {
    "addr:full":"16190 Mulholland Dr Los Angeles CA 90049",
    "addr:housenumber":"16190",
    "addr:postcode":"90049",
    "addr:street":"Mulholland Dr",
    "iso:country":"US",
    "sg:address":"16190 Mulholland Dr",
    "sg:city":"Los Angeles",
    "sg:classifiers":[
        {
            "category":"Education",
            "subcategory":"School",
            "type":"Public Place"
        }
    ],
    "sg:phone":"+1 818 788 4778",
    "sg:postcode":"90049",
    "sg:province":"CA",
    "wof:name":"Stephen Wise Middle High Sch",
    "wof:placetype":"venue"
},
  "geometry": {"coordinates":[-118.48725899999999,34.129958],"type":"Point"}
}