{
  "type": "Feature",
  "properties": {
    "addr:full":"4401 Blanc Ct Oakley CA 94561",
    "addr:housenumber":"4401",
    "addr:postcode":"94561",
    "addr:street":"Blanc Ct",
    "iso:country":"US",
    "sg:address":"4401 Blanc Ct",
    "sg:city":"Oakley",
    "sg:classifiers":[
        {
            "category":"Social Services",
            "subcategory":"Child Care",
            "type":"Services"
        }
    ],
    "sg:phone":"+1 925 679 9832",
    "sg:postcode":"94561",
    "sg:province":"CA",
    "wof:name":"Linda's Little Lambs Childcare",
    "wof:placetype":"venue"
},
  "geometry": {"coordinates":[-121.718977,37.989682],"type":"Point"}
}