{
  "type": "Feature",
  "properties": {
    "iso:country":"US",
    "sg:address":"3547 State Highway 128",
    "sg:city":"Calistoga",
    "sg:classifiers":[
        {
            "category":"Retail",
            "subcategory":"Animal Services",
            "type":"Services"
        }
    ],
    "sg:phone":"+1 707 942 1081",
    "sg:postcode":"94515",
    "sg:province":"CA",
    "sg:tags":[
        "pet"
    ],
    "wof:name":"Blossom Creek Farm",
    "wof:placetype":"venue"
},
  "geometry": {"coordinates":[-122.614732,38.594433],"type":"Point"}
}