{
  "type": "Feature",
  "properties": {
    "iso:country":"US",
    "sg:address":"3265 Mission St",
    "sg:city":"San Francisco",
    "sg:classifiers":[
        {
            "category":"Personal",
            "subcategory":"Beauty Salon",
            "type":"Services"
        }
    ],
    "sg:phone":"+1 415 647 1489",
    "sg:postcode":"94110",
    "sg:province":"CA",
    "wof:name":"City Hair Cuts",
    "wof:placetype":"venue"
},
  "geometry": {"coordinates":[-122.420445,37.744749],"type":"Point"}
}