{
  "type": "Feature",
  "properties": {
    "addr:full":"1915 San Pablo Avenue, Oakland, CA, USA",
    "addr:housenumber":"1915",
    "addr:postcode":"94612",
    "addr:street":"San Pablo Avenue",
    "addr:website":"http://www.hopscotchoakland.com/",
    "wof:name":"Hopscotch",
    "wof:placetype":"venue"
},
  "geometry": {"coordinates":[-122.273094,37.80927],"type":"Point"}
}