{
  "type": "Feature",
  "properties": {
    "addr:full":"5049 Jacobs Ct Agoura Hills CA 91377",
    "addr:housenumber":"5049",
    "addr:postcode":"91377",
    "addr:street":"Jacobs Ct",
    "iso:country":"US",
    "sg:address":"5049 Jacobs Ct",
    "sg:city":"Agoura Hills",
    "sg:classifiers":[
        {
            "category":"Professional",
            "type":"Services"
        }
    ],
    "sg:phone":"+1 818 991 7658",
    "sg:postcode":"91377",
    "sg:province":"CA",
    "wof:name":"Steven Primack",
    "wof:placetype":"venue"
},
  "geometry": {"coordinates":[-118.781707,34.196289],"type":"Point"}
}