{
  "type": "Feature",
  "properties": {
    "iso:country":"US",
    "sg:address":"758 E Bullard Ave",
    "sg:city":"Fresno",
    "sg:phone":"+1 559 436 4782",
    "sg:postcode":"93710",
    "sg:province":"CA",
    "sg:website":"http://www.auspicehomecare.com",
    "wof:name":"Auspice Home Care Solutions",
    "wof:placetype":"venue"
},
  "geometry": {"coordinates":[-119.773532,36.823109],"type":"Point"}
}