{
  "type": "Feature",
  "properties": {
    "iso:country":"US",
    "sg:address":"925 W Hedding St",
    "sg:city":"San Jose",
    "sg:classifiers":[
        {
            "category":"Health Services",
            "subcategory":"Health Practitioner",
            "type":"Services"
        }
    ],
    "sg:phone":"+1 408 246 4422",
    "sg:postcode":"95126",
    "sg:province":"CA",
    "sg:tags":[
        "psychotherapist"
    ],
    "wof:name":"Maria Flaherty",
    "wof:placetype":"venue"
},
  "geometry": {"coordinates":[-121.920925,37.342364],"type":"Point"}
}