{
  "type": "Feature",
  "properties": {
    "addr:full":"8824 S Gate Ave South Gate CA 90280",
    "addr:housenumber":"8824",
    "addr:postcode":"90280",
    "addr:street":"S Gate Ave;Gate",
    "iso:country":"US",
    "sg:address":"8824 S Gate Ave",
    "sg:city":"South Gate",
    "sg:classifiers":[
        {
            "category":"Organizations",
            "subcategory":"Religious Organization",
            "type":"Services"
        }
    ],
    "sg:phone":"+1 323 563 6377",
    "sg:postcode":"90280",
    "sg:province":"CA",
    "sg:tags":[
        "church"
    ],
    "wof:name":"Iglesia Calvario",
    "wof:placetype":"venue"
},
  "geometry": {"coordinates":[-118.214114,33.957376],"type":"Point"}
}