{
  "type": "Feature",
  "properties": {
    "iso:country":"US",
    "sg:address":"1202 E Walnut St",
    "sg:city":"Santa Ana",
    "sg:classifiers":[
        {
            "category":"Professional",
            "type":"Services"
        }
    ],
    "sg:phone":"+1 949 279 7953",
    "sg:postcode":"92701",
    "sg:province":"CA",
    "wof:name":"Rockshows Com",
    "wof:placetype":"venue"
},
  "geometry": {"coordinates":[-117.852763,33.744356],"type":"Point"}
}