{
  "type": "Feature",
  "properties": {
    "addr:full":"6200 Van Nuys Blvd Van Nuys CA 91401",
    "addr:housenumber":"6200",
    "addr:postcode":"91401",
    "addr:street":"Van Nuys Blvd",
    "iso:country":"US",
    "sg:address":"6200 Van Nuys Blvd",
    "sg:city":"Van Nuys",
    "sg:classifiers":[
        {
            "category":"Government",
            "subcategory":"Post Office",
            "type":"Public Place"
        }
    ],
    "sg:phone":"+1 818 785 1198",
    "sg:postcode":"91401",
    "sg:province":"CA",
    "wof:name":"US Post Office",
    "wof:placetype":"venue"
},
  "geometry": {"coordinates":[-118.448713,34.183637],"type":"Point"}
}