{
  "type": "Feature",
  "properties": {
    "addr:full":"211 E Ave F Lancaster CA 93535",
    "addr:housenumber":"211",
    "addr:postcode":"93535",
    "addr:street":"E Ave F",
    "iso:country":"US",
    "sg:address":"211 E Ave F",
    "sg:city":"Lancaster",
    "sg:classifiers":[
        {
            "category":"Professional",
            "subcategory":"Computer Services",
            "type":"Services"
        }
    ],
    "sg:phone":"+1 661 940 7070",
    "sg:postcode":"93535",
    "sg:province":"CA",
    "sg:website":"www.2geeksinabox.com",
    "wof:name":"2 Geeksina Box Inc",
    "wof:placetype":"venue"
},
  "geometry": {"coordinates":[-118.125675,34.74817],"type":"Point"}
}