{
  "type": "Feature",
  "properties": {
    "iso:country":"US",
    "sg:address":"1111 Broadway",
    "sg:city":"Oakland",
    "sg:classifiers":[
        {
            "category":"Professional",
            "subcategory":"Accounting & Tax Preparation",
            "type":"Services"
        }
    ],
    "sg:phone":"+1 510 250 1000",
    "sg:postcode":"94607",
    "sg:province":"CA",
    "sg:tags":[
        "accountant"
    ],
    "sg:website":"www.mdcllp.com",
    "wof:name":"Morris Davis & Chan",
    "wof:placetype":"venue"
},
  "geometry": {"coordinates":[-122.272211,37.802929],"type":"Point"}
}