{
  "type": "Feature",
  "properties": {
    "iso:country":"US",
    "sg:address":"2311 Palmetto Ave",
    "sg:city":"Pacifica",
    "sg:classifiers":[
        {
            "category":"Travel",
            "subcategory":"Travel Agent",
            "type":"Entertainment"
        }
    ],
    "sg:phone":"+1 650 355 5110",
    "sg:postcode":"94044",
    "sg:province":"CA",
    "sg:tags":[
        "ticket",
        "agency",
        "airline"
    ],
    "sg:website":"www.hendersontravel.net",
    "wof:name":"Henderson Travel",
    "wof:placetype":"venue"
},
  "geometry": {"coordinates":[-122.49256099999999,37.631963],"type":"Point"}
}