{
  "type": "Feature",
  "properties": {
    "addr:full":"885 Oak Grove Ave Menlo Park CA 94025",
    "addr:housenumber":"885",
    "addr:postcode":"94025",
    "addr:street":"Oak Grove Ave",
    "iso:country":"US",
    "sg:address":"885 Oak Grove Ave",
    "sg:city":"Menlo Park",
    "sg:classifiers":[
        {
            "category":"Social Services",
            "type":"Services"
        }
    ],
    "sg:phone":"+1 650 329 9813",
    "sg:postcode":"94025",
    "sg:province":"CA",
    "sg:tags":[
        "counselor",
        "marriage",
        "family"
    ],
    "wof:name":"Ruth Anne Woodruff",
    "wof:placetype":"venue"
},
  "geometry": {"coordinates":[-122.186538,37.451597],"type":"Point"}
}