{
  "type": "Feature",
  "properties": {
    "iso:country":"US",
    "sg:address":"5780 E La Palma Ave",
    "sg:city":"Anaheim",
    "sg:classifiers":[
        {
            "category":"Home & Garden",
            "subcategory":"Garden Supply",
            "type":"Retail Goods"
        }
    ],
    "sg:phone":"+1 714 779 2091",
    "sg:postcode":"92807",
    "sg:province":"CA",
    "sg:tags":[
        "nursery",
        "gardening"
    ],
    "wof:name":"Armstrong Garden Centers Inc",
    "wof:placetype":"venue"
},
  "geometry": {"coordinates":[-117.78800200000001,33.8591],"type":"Point"}
}