{
  "type": "Feature",
  "properties": {
    "addr:full":"11561 Crane St Castroville CA 95012",
    "addr:housenumber":"11561",
    "addr:postcode":"95012",
    "addr:street":"Crane St",
    "iso:country":"US",
    "sg:address":"11561 Crane St",
    "sg:city":"Castroville",
    "sg:classifiers":[
        {
            "category":"Building & Trades",
            "subcategory":"Construction",
            "type":"Services"
        }
    ],
    "sg:phone":"+1 831 633 0532",
    "sg:postcode":"95012",
    "sg:province":"CA",
    "sg:tags":[
        "excavation",
        "contractor"
    ],
    "wof:name":"RC Backhoe Service",
    "wof:placetype":"venue"
},
  "geometry": {"coordinates":[-121.75303599999999,36.769095],"type":"Point"}
}