{
  "type": "Feature",
  "properties": {
    "addr:full":"720 N Virgil Ave #4, Los Angeles, CA, USA",
    "addr:housenumber":720,
    "addr:phone":"323-284-8147",
    "addr:postcode":"90029",
    "addr:street":"N Virgil Ave",
    "addr:website":"http://sqirlla.com/",
    "name:eng_x_preferred":[
        "Sqirl"
    ],
    "wof:name":"Sqirl",
    "wof:placetype":"venue"
},
  "geometry": {"coordinates":[-118.286688,34.084295],"type":"Point"}
}