{
  "type": "Feature",
  "properties": {
    "iso:country":"US",
    "sg:address":"8322 Compton Avenue",
    "sg:city":"Los Angeles",
    "sg:classifiers":[
        {
            "category":"Food & Beverages",
            "subcategory":"Groceries & Convenience Stores",
            "type":"Retail Goods"
        }
    ],
    "sg:phone":"+1 323 589 0495",
    "sg:postcode":"90001",
    "sg:province":"CA",
    "wof:name":"Samaritana Mini Market",
    "wof:placetype":"venue"
},
  "geometry": {"coordinates":[-118.247795,33.962734],"type":"Point"}
}