{
  "type": "Feature",
  "properties": {
    "addr:full":"41 Osgood Pl San Francisco CA 94133",
    "addr:housenumber":"41",
    "addr:postcode":"94133",
    "addr:street":"Osgood Pl",
    "iso:country":"US",
    "sg:address":"41 Osgood Pl",
    "sg:city":"San Francisco",
    "sg:classifiers":[
        {
            "category":"Professional",
            "subcategory":"Management & Consulting",
            "type":"Services"
        }
    ],
    "sg:phone":"+1 415 434 2629",
    "sg:postcode":"94133",
    "sg:province":"CA",
    "sg:tags":[
        "marketing",
        "consultant"
    ],
    "wof:name":"Bob Young Marketing",
    "wof:placetype":"venue"
},
  "geometry": {"coordinates":[-122.402991,37.797445],"type":"Point"}
}