{
  "type": "Feature",
  "properties": {
    "addr:full":"5000 Parkway Calabasas Calabasas CA 91302",
    "addr:housenumber":"5000",
    "addr:postcode":"91302",
    "addr:street":"Parkway",
    "iso:country":"US",
    "sg:address":"5000 Parkway Calabasas",
    "sg:city":"Calabasas",
    "sg:classifiers":[
        {
            "category":"Professional",
            "subcategory":"Lawyer & Legal Services",
            "type":"Services"
        }
    ],
    "sg:phone":"+1 818 223 8321",
    "sg:postcode":"91302",
    "sg:province":"CA",
    "wof:name":"Hynick George R Atty",
    "wof:placetype":"venue"
},
  "geometry": {"coordinates":[-118.65300000000001,34.154099],"type":"Point"}
}