{
  "type": "Feature",
  "properties": {
    "iso:country":"US",
    "sg:address":"1962 Chardonnay Dr",
    "sg:city":"Oakley",
    "sg:classifiers":[
        {
            "category":"Retail",
            "subcategory":"Laundry & Dry Cleaning",
            "type":"Services"
        }
    ],
    "sg:phone":"+1 925 679 0677",
    "sg:postcode":"94561",
    "sg:province":"CA",
    "sg:tags":[
        "cleaners",
        "rug",
        "carpet"
    ],
    "wof:name":"Beary Clean Svc",
    "wof:placetype":"venue"
},
  "geometry": {"coordinates":[-121.728109,37.994538],"type":"Point"}
}