{
  "type": "Feature",
  "properties": {
    "addr:full":"4304 Narragansett Ave San Diego CA 92107",
    "addr:housenumber":"4304",
    "addr:postcode":"92107",
    "addr:street":"Narragansett Ave",
    "iso:country":"US",
    "sg:address":"4304 Narragansett Ave",
    "sg:city":"San Diego",
    "sg:classifiers":[
        {
            "category":"Building & Trades",
            "subcategory":"Construction",
            "type":"Services"
        }
    ],
    "sg:phone":"+1 619 226 1671",
    "sg:postcode":"92107",
    "sg:province":"CA",
    "sg:tags":[
        "contractor"
    ],
    "wof:name":"Bob English Construction",
    "wof:placetype":"venue"
},
  "geometry": {"coordinates":[-117.242001,32.738799],"type":"Point"}
}