{
  "type": "Feature",
  "properties": {
    "addr:full":"370 Industrial Rd San Carlos CA 94070",
    "addr:housenumber":"370",
    "addr:postcode":"94070",
    "addr:street":"Industrial Rd",
    "iso:country":"US",
    "sg:address":"370 Industrial Rd",
    "sg:city":"San Carlos",
    "sg:classifiers":[
        {
            "category":"Manufacturing",
            "subcategory":"Tools & Machinery",
            "type":"Manufacturing & Wholesale Goods"
        }
    ],
    "sg:phone":"+1 650 593 1064",
    "sg:postcode":"94070",
    "sg:province":"CA",
    "sg:tags":[
        "furnace"
    ],
    "wof:name":"Camco",
    "wof:placetype":"venue"
},
  "geometry": {"coordinates":[-122.25930099999999,37.512971],"type":"Point"}
}