{
  "type": "Feature",
  "properties": {
    "iso:country":"US",
    "sg:address":"5218 War Wagon Dr",
    "sg:city":"San Jose",
    "sg:classifiers":[
        {
            "category":"Professional",
            "subcategory":"Art Services",
            "type":"Services"
        }
    ],
    "sg:phone":"+1 408 972 0699",
    "sg:postcode":"95136",
    "sg:province":"CA",
    "sg:tags":[
        "graphic",
        "designer"
    ],
    "wof:name":"Macro Graphics Multimedia",
    "wof:placetype":"venue"
},
  "geometry": {"coordinates":[-121.82112499999999,37.26042],"type":"Point"}
}