{
  "type": "Feature",
  "properties": {
    "addr:full":"20067 Stanton Hill Ct Castro Valley CA 94546",
    "addr:housenumber":"20067",
    "addr:postcode":"94546",
    "addr:street":"Stanton Hill Ct",
    "iso:country":"US",
    "sg:address":"20067 Stanton Hill Ct",
    "sg:city":"Castro Valley",
    "sg:classifiers":[
        {
            "category":"Wholesale",
            "subcategory":"Vending Machines",
            "type":"Manufacturing & Wholesale Goods"
        }
    ],
    "sg:phone":"+1 510 537 6177",
    "sg:postcode":"94546",
    "sg:province":"CA",
    "wof:name":"Innovating Vending",
    "wof:placetype":"venue"
},
  "geometry": {"coordinates":[-122.091719,37.697155],"type":"Point"}
}