{
  "type": "Feature",
  "properties": {
    "addr:full":"1580 Valencia St Ste 804 San Francisco CA 94110",
    "addr:housenumber":"1580",
    "addr:postcode":"94110",
    "addr:street":"Valencia St Ste 804",
    "iso:country":"US",
    "sg:address":"1580 Valencia St Ste 804",
    "sg:city":"San Francisco",
    "sg:classifiers":[
        {
            "category":"Health Services",
            "subcategory":"Doctor",
            "type":"Services"
        }
    ],
    "sg:phone":"+1 415 392 5626",
    "sg:postcode":"94110",
    "sg:province":"CA",
    "sg:tags":[
        "podiatrist"
    ],
    "wof:name":"Jay K Benard, DPM",
    "wof:placetype":"venue"
},
  "geometry": {"coordinates":[-122.420332,37.746859],"type":"Point"}
}