{
  "type": "Feature",
  "properties": {
    "addr:full":"55 Francisco Street Suite 450 San Francisco CA 94133",
    "addr:housenumber":"55",
    "addr:postcode":"94133",
    "addr:street":"Francisco Street Suite 450",
    "iso:country":"US",
    "sg:address":"55 Francisco Street Suite 450",
    "sg:city":"San Francisco",
    "sg:classifiers":[
        {
            "category":"Arts & Performance",
            "subcategory":"Art Gallery",
            "type":"Entertainment"
        }
    ],
    "sg:phone":"+1 415 772 9000",
    "sg:postcode":"94133",
    "sg:province":"CA",
    "wof:name":"Courtney Davis",
    "wof:placetype":"venue"
},
  "geometry": {"coordinates":[-122.405998,37.805599],"type":"Point"}
}