{
  "type": "Feature",
  "properties": {
    "addr:full":"1320 E San Fernando St San Jose CA 95116",
    "addr:housenumber":"1320",
    "addr:postcode":"95116",
    "addr:street":"E San Fernando St",
    "iso:country":"US",
    "sg:address":"1320 E San Fernando St",
    "sg:city":"San Jose",
    "sg:classifiers":[
        {
            "category":"Government",
            "subcategory":"Office",
            "type":"Public Place"
        }
    ],
    "sg:phone":"+1 408 920 6698",
    "sg:postcode":"95116",
    "sg:province":"CA",
    "sg:tags":[
        "smog",
        "check"
    ],
    "wof:name":"Tony Smog Test Only",
    "wof:placetype":"venue"
},
  "geometry": {"coordinates":[-121.863502,37.346642],"type":"Point"}
}