{
  "type": "Feature",
  "properties": {
    "addr:full":"540 Porter Way Placentia CA 92870",
    "addr:housenumber":"540",
    "addr:postcode":"ca 92870",
    "addr:street":"Porter Way",
    "iso:country":"US",
    "sg:address":"540 Porter Way",
    "sg:city":"Placentia",
    "sg:classifiers":[
        {
            "category":"Manufacturing",
            "subcategory":"Metals",
            "type":"Manufacturing & Wholesale Goods"
        }
    ],
    "sg:phone":"+1 714 961 1015",
    "sg:postcode":"92870",
    "sg:province":"CA",
    "sg:tags":[
        "extruded",
        "product",
        "aluminum",
        "mfg"
    ],
    "wof:name":"Novator Corporation",
    "wof:placetype":"venue"
},
  "geometry": {"coordinates":[-117.867971,33.867151],"type":"Point"}
}