{
  "type": "Feature",
  "properties": {
    "addr:full":"7430 Redwood Blvd Novato CA 94945",
    "addr:housenumber":"7430",
    "addr:postcode":"94945",
    "addr:street":"Redwood Blvd",
    "iso:country":"US",
    "sg:address":"7430 Redwood Blvd",
    "sg:city":"Novato",
    "sg:classifiers":[
        {
            "category":"Building & Trades",
            "subcategory":"Construction",
            "type":"Services"
        }
    ],
    "sg:phone":"+1 415 897 2253",
    "sg:postcode":"94945",
    "sg:province":"CA",
    "sg:tags":[
        "designer",
        "dealer",
        "pool",
        "swimming"
    ],
    "sg:website":"www.poolscene.com",
    "wof:name":"POOL Scene Inc",
    "wof:placetype":"venue"
},
  "geometry": {"coordinates":[-122.569238,38.1099],"type":"Point"}
}