{
  "type": "Feature",
  "properties": {
    "addr:full":"2880 Gateway Oaks Dr Sacramento CA 95833",
    "addr:housenumber":"2880",
    "addr:postcode":"95833",
    "addr:street":"Gateway Oaks Dr",
    "iso:country":"US",
    "sg:address":"2880 Gateway Oaks Dr",
    "sg:city":"Sacramento",
    "sg:classifiers":[
        {
            "category":"Professional",
            "type":"Services"
        }
    ],
    "sg:phone":"+1 916 286 8800",
    "sg:postcode":"95833",
    "sg:province":"CA",
    "sg:tags":[
        "establishment"
    ],
    "sg:website":"www.air.org",
    "wof:name":"American Institutes-Research",
    "wof:placetype":"venue"
},
  "geometry": {"coordinates":[-121.519115,38.620265],"type":"Point"}
}