{
  "type": "Feature",
  "properties": {
    "iso:country":"US",
    "sg:address":"13335 Oxnard St",
    "sg:city":"Van Nuys",
    "sg:classifiers":[
        {
            "category":"Building & Trades",
            "subcategory":"Construction",
            "type":"Services"
        }
    ],
    "sg:phone":"+1 818 997 7766",
    "sg:postcode":"91401",
    "sg:province":"CA",
    "sg:tags":[
        "layer",
        "carpet"
    ],
    "wof:name":"Moshe's Carpet Cleaning",
    "wof:placetype":"venue"
},
  "geometry": {"coordinates":[-118.424797,34.179401],"type":"Point"}
}