{
  "type": "Feature",
  "properties": {
    "iso:country":"US",
    "sg:address":"28 2nd Street 3rd Floor",
    "sg:city":"San Francisco",
    "sg:classifiers":[
        {
            "category":"Professional",
            "subcategory":"Computer Services",
            "type":"Services"
        }
    ],
    "sg:phone":"+1 415 398 2644",
    "sg:postcode":"94105",
    "sg:province":"CA",
    "sg:website":"http://www.marketcetera.com",
    "wof:name":"Marketcetera",
    "wof:placetype":"venue"
},
  "geometry": {"coordinates":[-122.40118699999999,37.789086],"type":"Point"}
}