{
  "type": "Feature",
  "properties": {
    "addr:full":"9825 Long Beach Blvd South Gate CA 90280",
    "addr:housenumber":"9825",
    "addr:postcode":"90280",
    "addr:street":"Long Beach Blvd;Gate",
    "iso:country":"US",
    "sg:address":"9825 Long Beach Blvd",
    "sg:city":"South Gate",
    "sg:classifiers":[
        {
            "category":"Shopping",
            "subcategory":"Mobile Phones",
            "type":"Retail Goods"
        }
    ],
    "sg:phone":"+1 323 566 9666",
    "sg:postcode":"90280",
    "sg:province":"CA",
    "wof:name":"Metro PCS Authorized Dealer Metro Zone Communications",
    "wof:placetype":"venue"
},
  "geometry": {"coordinates":[-118.216536,33.946019],"type":"Point"}
}