{
  "type": "Feature",
  "properties": {
    "iso:country":"US",
    "sg:address":"375 Gellert Blvd",
    "sg:city":"Daly City",
    "sg:classifiers":[
        {
            "category":"Home & Garden",
            "subcategory":"Carpets & Floor Coverings",
            "type":"Retail Goods"
        }
    ],
    "sg:phone":"+1 650 994 4000",
    "sg:postcode":"94015",
    "sg:province":"CA",
    "sg:tags":[
        "linoleum"
    ],
    "wof:name":"MMM Carpets Unlimited",
    "wof:placetype":"venue"
},
  "geometry": {"coordinates":[-122.4691,37.66426],"type":"Point"}
}