{
  "type": "Feature",
  "properties": {
    "iso:country":"US",
    "sg:address":"2425 National City Blvd",
    "sg:city":"National City",
    "sg:classifiers":[
        {
            "category":"Home & Garden",
            "subcategory":"Building Materials",
            "type":"Retail Goods"
        }
    ],
    "sg:phone":"+1 619 474 5299",
    "sg:postcode":"91950",
    "sg:province":"CA",
    "sg:tags":[
        "glass",
        "window",
        "plate"
    ],
    "wof:name":"Poor Man's Auto Glass",
    "wof:placetype":"venue"
},
  "geometry": {"coordinates":[-117.101214,32.661396],"type":"Point"}
}