{
  "type": "Feature",
  "properties": {
    "addr:full":"535 N La Cienega Boulevard West Hollywood CA 90048",
    "addr:housenumber":"535",
    "addr:postcode":"90048",
    "addr:street":"N La Cienega Boulevard",
    "iso:country":"US",
    "sg:address":"535 N La Cienega Boulevard",
    "sg:city":"West Hollywood",
    "sg:classifiers":[
        {
            "category":"Shopping",
            "subcategory":"Clothing, Apparel, & Fashions",
            "type":"Retail Goods"
        }
    ],
    "sg:phone":"+1 310 855 1272",
    "sg:postcode":"90048",
    "sg:province":"CA",
    "sg:tags":[
        "accessory",
        "clothing",
        "women's"
    ],
    "wof:name":"Nino Boutique",
    "wof:placetype":"venue"
},
  "geometry": {"coordinates":[-118.37666900000001,34.081251],"type":"Point"}
}