{
  "type": "Feature",
  "properties": {
    "addr:full":"1378 Sutter Street San Francisco CA 94109",
    "addr:housenumber":"1378",
    "addr:postcode":"94109",
    "addr:street":"Sutter Street",
    "iso:country":"US",
    "sg:address":"1378 Sutter Street",
    "sg:city":"San Francisco",
    "sg:classifiers":[
        {
            "category":"Home & Garden",
            "subcategory":"Carpets & Floor Coverings",
            "type":"Retail Goods"
        }
    ],
    "sg:phone":"+1 415 346 8333",
    "sg:postcode":"94109",
    "sg:province":"CA",
    "sg:tags":[
        "carpeting"
    ],
    "wof:name":"David Morris",
    "wof:placetype":"venue"
},
  "geometry": {"coordinates":[-122.422997,37.787498],"type":"Point"}
}