{
  "type": "Feature",
  "properties": {
    "addr:full":"622 W Duarte Rd Arcadia CA 91007",
    "addr:housenumber":"622",
    "addr:postcode":"91007",
    "addr:street":"W Duarte Rd",
    "iso:country":"US",
    "sg:address":"622 W Duarte Rd",
    "sg:city":"Arcadia",
    "sg:classifiers":[
        {
            "category":"Health Services",
            "subcategory":"Doctor",
            "type":"Services"
        }
    ],
    "sg:phone":"+1 626 821 9808",
    "sg:postcode":"91007",
    "sg:province":"CA",
    "sg:tags":[
        "physician",
        "surgeon"
    ],
    "wof:name":"John J Tzeng MD",
    "wof:placetype":"venue"
},
  "geometry": {"coordinates":[-118.05418,34.126122],"type":"Point"}
}