{
  "type": "Feature",
  "properties": {
    "iso:country":"US",
    "sg:address":"7800 Orange St",
    "sg:city":"Highland",
    "sg:classifiers":[
        {
            "category":"Education",
            "subcategory":"School",
            "type":"Public Place"
        }
    ],
    "sg:phone":"+1 909 307 2400",
    "sg:postcode":"92346",
    "sg:province":"CA",
    "sg:website":"http://www.redlandsusd.net",
    "wof:name":"Beattie Middle School",
    "wof:placetype":"venue"
},
  "geometry": {"coordinates":[-117.21313499999999,34.129396],"type":"Point"}
}