{
  "type": "Feature",
  "properties": {
    "addr:full":"5880 District Blvd Bakersfield CA 93313",
    "addr:postcode":"5880;93313",
    "addr:street":"District Blvd",
    "iso:country":"US",
    "sg:address":"5880 District Blvd",
    "sg:city":"Bakersfield",
    "sg:classifiers":[
        {
            "category":"Professional",
            "subcategory":"Testing Lab",
            "type":"Services"
        }
    ],
    "sg:phone":"+1 661 397 5995",
    "sg:postcode":"93313",
    "sg:province":"CA",
    "sg:tags":[
        "electrical",
        "system",
        "power"
    ],
    "wof:name":"Delta Testing Svc Inc",
    "wof:placetype":"venue"
},
  "geometry": {"coordinates":[-119.063215,35.313118],"type":"Point"}
}