{
  "type": "Feature",
  "properties": {
    "addr:full":"2600 E Ponderosa Dr Camarillo CA 93010",
    "addr:housenumber":"2600",
    "addr:postcode":"93010",
    "addr:street":"E Ponderosa Dr",
    "iso:country":"US",
    "sg:address":"2600 E Ponderosa Dr",
    "sg:city":"Camarillo",
    "sg:classifiers":[
        {
            "category":"Real Estate",
            "subcategory":"Real Estate Operator",
            "type":"Services"
        }
    ],
    "sg:phone":"+1 805 482 1682",
    "sg:postcode":"93010",
    "sg:province":"CA",
    "sg:tags":[
        "apartment"
    ],
    "wof:name":"Villa Caprice",
    "wof:placetype":"venue"
},
  "geometry": {"coordinates":[-119.027,34.2323],"type":"Point"}
}