{
  "type": "Feature",
  "properties": {
    "addr:full":"5665 E Westover Ave Fresno CA 93727",
    "addr:housenumber":"5665",
    "addr:postcode":"93727",
    "addr:street":"E Westover Ave",
    "iso:country":"US",
    "sg:address":"5665 E Westover Ave",
    "sg:city":"Fresno",
    "sg:classifiers":[
        {
            "category":"Retail",
            "subcategory":"Portrait Studio",
            "type":"Services"
        }
    ],
    "sg:phone":"+1 559 292 8161",
    "sg:postcode":"93727",
    "sg:province":"CA",
    "sg:tags":[
        "photographer"
    ],
    "wof:name":"Larson Brothers Photography",
    "wof:placetype":"venue"
},
  "geometry": {"coordinates":[-119.699264,36.775803],"type":"Point"}
}