{
  "type": "Feature",
  "properties": {
    "addr:full":"2962 Blanding Ct Hayward CA 94541",
    "addr:housenumber":"2962",
    "addr:postcode":"94541",
    "addr:street":"Blanding Ct",
    "iso:country":"US",
    "sg:address":"2962 Blanding Ct",
    "sg:city":"Hayward",
    "sg:classifiers":[
        {
            "category":"Manufacturing",
            "subcategory":"Signs",
            "type":"Manufacturing & Wholesale Goods"
        }
    ],
    "sg:phone":"+1 510 537 1498",
    "sg:postcode":"94541",
    "sg:province":"CA",
    "wof:name":"Moon Signs & Design",
    "wof:placetype":"venue"
},
  "geometry": {"coordinates":[-122.053803,37.687717],"type":"Point"}
}