{
  "type": "Feature",
  "properties": {
    "addr:full":"20536 Carrey Rd Walnut CA 91789",
    "addr:postcode":"20536;91789",
    "addr:street":"Carrey Rd",
    "iso:country":"US",
    "sg:address":"20536 Carrey Rd",
    "sg:city":"Walnut",
    "sg:classifiers":[
        {
            "category":"Wholesale",
            "subcategory":"Chemicals & Plastics",
            "type":"Manufacturing & Wholesale Goods"
        }
    ],
    "sg:phone":"+1 909 869 6016",
    "sg:postcode":"91789",
    "sg:province":"CA",
    "wof:name":"Hangzhou Sanhe USA Inc",
    "wof:placetype":"venue"
},
  "geometry": {"coordinates":[-117.856399,34.01605],"type":"Point"}
}