{
  "type": "Feature",
  "properties": {
    "addr:full":"35 Seneca Ave. San Francisco CA 94112",
    "addr:housenumber":"35",
    "addr:postcode":"94112",
    "addr:street":"Seneca Ave.",
    "iso:country":"US",
    "sg:address":"35 Seneca Ave.",
    "sg:city":"San Francisco",
    "sg:classifiers":[
        {
            "category":"Personal",
            "type":"Services"
        }
    ],
    "sg:phone":"+1 415 584 5538",
    "sg:postcode":"94112",
    "sg:province":"CA",
    "sg:tags":[
        "mover"
    ],
    "wof:name":"JC Moving Services",
    "wof:placetype":"venue"
},
  "geometry": {"coordinates":[-122.441002,37.717899],"type":"Point"}
}