{
  "type": "Feature",
  "properties": {
    "iso:country":"US",
    "sg:address":"12420 Ventura Blvd",
    "sg:city":"Studio City",
    "sg:classifiers":[
        {
            "category":"Real Estate",
            "subcategory":"Real Estate Services",
            "type":"Services"
        }
    ],
    "sg:phone":"+1 818 766 4866",
    "sg:postcode":"91604",
    "sg:province":"CA",
    "sg:tags":[
        "home",
        "inspector"
    ],
    "sg:website":"www.safer-baby.com",
    "wof:name":"Safer-Baby",
    "wof:placetype":"venue"
},
  "geometry": {"coordinates":[-118.40381499999999,34.142531],"type":"Point"}
}