{
  "type": "Feature",
  "properties": {
    "addr:full":"3873 San Pablo Dam Rd El Sobrante CA 94803",
    "addr:housenumber":"3873",
    "addr:postcode":"94803",
    "addr:street":"San Pablo Dam Rd",
    "iso:country":"US",
    "sg:address":"3873 San Pablo Dam Rd",
    "sg:city":"El Sobrante",
    "sg:classifiers":[
        {
            "category":"Restaurant",
            "type":"Food & Drink"
        }
    ],
    "sg:phone":"+1 510 222 6960",
    "sg:postcode":"94803",
    "sg:province":"CA",
    "wof:name":"Tina's Creekside Cafe",
    "wof:placetype":"venue"
},
  "geometry": {"coordinates":[-122.314213,37.964998],"type":"Point"}
}