{
  "type": "Feature",
  "properties": {
    "addr:full":"2985 Coronado Avenue San Diego CA 92154",
    "addr:housenumber":"2985",
    "addr:postcode":"92154",
    "addr:street":"Coronado Avenue",
    "iso:country":"US",
    "sg:address":"2985 Coronado Avenue",
    "sg:city":"San Diego",
    "sg:classifiers":[
        {
            "category":"Shopping",
            "subcategory":"Florist",
            "type":"Retail Goods"
        }
    ],
    "sg:phone":"+1 619 429 3627",
    "sg:postcode":"92154",
    "sg:province":"CA",
    "wof:name":"Nieblas Flower's",
    "wof:placetype":"venue"
},
  "geometry": {"coordinates":[-117.06934200000001,32.576595],"type":"Point"}
}