{
  "type": "Feature",
  "properties": {
    "addr:full":"5700 Gravenstein Highway North Forestville CA 95463",
    "addr:housenumber":"5700",
    "addr:postcode":"95463",
    "addr:street":"Gravenstein Highway",
    "iso:country":"US",
    "sg:address":"5700 Gravenstein Highway North",
    "sg:city":"Forestville",
    "sg:classifiers":[
        {
            "category":"Winery",
            "type":"Food & Drink"
        }
    ],
    "sg:phone":"+1 707 887 3344",
    "sg:postcode":"95463",
    "sg:province":"CA",
    "sg:website":"www.russianrivervineyards.com/",
    "wof:name":"Russian River Vineyards",
    "wof:placetype":"venue"
},
  "geometry": {"coordinates":[-122.879301,38.463466],"type":"Point"}
}