{
  "type": "Feature",
  "properties": {
    "addr:full":"1501 W 9th St Upland CA 91786",
    "addr:housenumber":"1501",
    "addr:postcode":"91786",
    "addr:street":"W 9Th St",
    "iso:country":"US",
    "sg:address":"1501 W 9th St",
    "sg:city":"Upland",
    "sg:classifiers":[
        {
            "category":"Social Services",
            "type":"Services"
        }
    ],
    "sg:phone":"+1 909 920 5568",
    "sg:postcode":"91786",
    "sg:province":"CA",
    "sg:tags":[
        "organization",
        "welfare"
    ],
    "wof:name":"Foothill Family Shelter Inc",
    "wof:placetype":"venue"
},
  "geometry": {"coordinates":[-117.67103899999999,34.096101],"type":"Point"}
}