{
  "type": "Feature",
  "properties": {
    "iso:country":"US",
    "sg:address":"434 Redcliff Dr",
    "sg:city":"Redding",
    "sg:classifiers":[
        {
            "category":"Professional",
            "subcategory":"Engineering",
            "type":"Services"
        },
        {
            "category":"Real Estate",
            "subcategory":"Surveying",
            "type":"Services"
        }
    ],
    "sg:phone":"+1 530 222 5194",
    "sg:postcode":"96002",
    "sg:province":"CA",
    "sg:tags":[
        "civil",
        "surveyor",
        "land",
        "engineer"
    ],
    "wof:name":"Robertson and Dominick",
    "wof:placetype":"venue"
},
  "geometry": {"coordinates":[-122.36331199999999,40.574957],"type":"Point"}
}