{
  "type": "Feature",
  "properties": {
    "addr:full":"4811 Parker Ave Mcclellan CA 95652",
    "addr:housenumber":"4811",
    "addr:postcode":"95652",
    "addr:street":"Parker Ave",
    "iso:country":"US",
    "sg:address":"4811 Parker Ave",
    "sg:city":"Mcclellan",
    "sg:classifiers":[
        {
            "category":"Transit Center",
            "subcategory":"Freight",
            "type":"Transportation"
        },
        {
            "category":"Freight",
            "type":"Transportation"
        }
    ],
    "sg:phone":"+1 916 640 0640",
    "sg:postcode":"95652",
    "sg:province":"CA",
    "sg:tags":[
        "trucking-motor",
        "trucking"
    ],
    "wof:name":"Budway Enterprises, Inc.",
    "wof:placetype":"venue"
},
  "geometry": {"coordinates":[-121.417671,38.659889],"type":"Point"}
}