{
  "type": "Feature",
  "properties": {
    "addr:full":"3985 Harney St San Diego CA 92110",
    "addr:housenumber":"3985",
    "addr:postcode":"92110",
    "addr:street":"Harney St",
    "iso:country":"US",
    "sg:address":"3985 Harney St",
    "sg:city":"San Diego",
    "sg:classifiers":[
        {
            "category":"Shopping",
            "subcategory":"Gifts & Souvenirs",
            "type":"Retail Goods"
        }
    ],
    "sg:phone":"+1 619 692 3511",
    "sg:postcode":"92110",
    "sg:province":"CA",
    "sg:tags":[
        "basket",
        "parcel"
    ],
    "wof:name":"Jin-Cal Intl",
    "wof:placetype":"venue"
},
  "geometry": {"coordinates":[-117.195279,32.752161],"type":"Point"}
}