{
  "type": "Feature",
  "properties": {
    "addr:full":"4590 Riverside Dr Chino CA 91710",
    "addr:housenumber":"4590",
    "addr:postcode":"91710",
    "addr:street":"Riverside Dr",
    "iso:country":"US",
    "sg:address":"4590 Riverside Dr",
    "sg:city":"Chino",
    "sg:classifiers":[
        {
            "category":"Health Services",
            "subcategory":"Doctor",
            "type":"Services"
        }
    ],
    "sg:phone":"+1 909 902 9934",
    "sg:postcode":"91710",
    "sg:province":"CA",
    "sg:tags":[
        "physician",
        "surgeon"
    ],
    "wof:name":"Harpreet Kujar Inc",
    "wof:placetype":"venue"
},
  "geometry": {"coordinates":[-117.706504,34.01904],"type":"Point"}
}