{
  "type": "Feature",
  "properties": {
    "iso:country":"US",
    "sg:address":"2611 Lemon Grove Ave",
    "sg:city":"Lemon Grove",
    "sg:classifiers":[
        {
            "category":"Shopping",
            "subcategory":"Beauty & Cosmetics",
            "type":"Retail Goods"
        }
    ],
    "sg:phone":"+1 619 461 3120",
    "sg:postcode":"91945",
    "sg:province":"CA",
    "sg:tags":[
        "supply"
    ],
    "wof:name":"PURE IMAGE HAIR DESIGN",
    "wof:placetype":"venue"
},
  "geometry": {"coordinates":[-117.225236,32.733657],"type":"Point"}
}