{
  "type": "Feature",
  "properties": {
    "iso:country":"US",
    "sg:address":"14569 Meadow Dr",
    "sg:city":"Grass Valley",
    "sg:classifiers":[
        {
            "category":"Shopping",
            "subcategory":"Clothing, Apparel, & Fashions",
            "type":"Retail Goods"
        }
    ],
    "sg:phone":"+1 530 272 5176",
    "sg:postcode":"95945",
    "sg:province":"CA",
    "sg:tags":[
        "dressmaker"
    ],
    "wof:name":"J D Originals",
    "wof:placetype":"venue"
},
  "geometry": {"coordinates":[-120.994591,39.179071],"type":"Point"}
}