{
  "type": "Feature",
  "properties": {
    "addr:full":"3751 E Calwa Ave Fresno CA 93725",
    "addr:housenumber":"3751",
    "addr:postcode":"93725",
    "addr:street":"E Calwa Ave",
    "iso:country":"US",
    "sg:address":"3751 E Calwa Ave",
    "sg:city":"Fresno",
    "sg:classifiers":[
        {
            "category":"Wholesale",
            "subcategory":"Machinery & Supplies",
            "type":"Manufacturing & Wholesale Goods"
        }
    ],
    "sg:phone":"+1 559 233 0187",
    "sg:postcode":"93725",
    "sg:province":"CA",
    "sg:tags":[
        "farm",
        "equipment"
    ],
    "sg:website":"www.jmequipment.com",
    "wof:name":"J M Equipment Co Inc",
    "wof:placetype":"venue"
},
  "geometry": {"coordinates":[-119.760509,36.704963],"type":"Point"}
}