{
  "type": "Feature",
  "properties": {
    "iso:country":"US",
    "sg:address":"46750 Mountain Cove Dr",
    "sg:city":"Indian Wells",
    "sg:classifiers":[
        {
            "category":"Wholesale",
            "subcategory":"Groceries",
            "type":"Manufacturing & Wholesale Goods"
        }
    ],
    "sg:phone":"+1 760 360 1406",
    "sg:postcode":"92210",
    "sg:province":"CA",
    "sg:tags":[
        "baker"
    ],
    "wof:name":"PSI Love You Products Co",
    "wof:placetype":"venue"
},
  "geometry": {"coordinates":[-116.303065,33.708047],"type":"Point"}
}