{
  "type": "Feature",
  "properties": {
    "iso:country":"US",
    "sg:address":"26741 Portola Pkwy Ste 1E-718",
    "sg:city":"El Toro",
    "sg:classifiers":[
        {
            "category":"Building & Trades",
            "subcategory":"Construction",
            "type":"Services"
        },
        {
            "category":"Home & Garden",
            "subcategory":"Carpets & Floor Coverings",
            "type":"Retail Goods"
        }
    ],
    "sg:phone":"+1 877 373 6110",
    "sg:postcode":"92610",
    "sg:province":"CA",
    "sg:tags":[
        "flooring",
        "contractor"
    ],
    "wof:name":"Eden Flooring and Construction",
    "wof:placetype":"venue"
},
  "geometry": {"coordinates":[-117.663495,33.680693],"type":"Point"}
}