{
  "type": "Feature",
  "properties": {
    "addr:full":"2575 N Lincoln St Burbank CA 91504",
    "addr:housenumber":"2575",
    "addr:postcode":"91504",
    "addr:street":"N Lincoln St",
    "iso:country":"US",
    "sg:address":"2575 N Lincoln St",
    "sg:city":"Burbank",
    "sg:classifiers":[
        {
            "category":"Wholesale",
            "subcategory":"Durable Goods & Equipment",
            "type":"Manufacturing & Wholesale Goods"
        }
    ],
    "sg:phone":"+1 818 843 3855",
    "sg:postcode":"91504",
    "sg:province":"CA",
    "wof:name":"Region",
    "wof:placetype":"venue"
},
  "geometry": {"coordinates":[-118.335717,34.199587],"type":"Point"}
}