{
  "type": "Feature",
  "properties": {
    "addr:full":"26524 Ruether Ave #410 Santa Clarita CA 91351",
    "addr:postcode":"26524;91351",
    "addr:street":"Ruether Ave # 410",
    "iso:country":"US",
    "sg:address":"26524 Ruether Ave #410",
    "sg:city":"Santa Clarita",
    "sg:classifiers":[
        {
            "category":"Autos & Motor Vehicles",
            "subcategory":"Automobile Sales",
            "type":"Retail Goods"
        }
    ],
    "sg:phone":"+1 661 251 6737",
    "sg:postcode":"91351",
    "sg:province":"CA",
    "sg:tags":[
        "automotive"
    ],
    "sg:website":"www.allautocare.us",
    "wof:name":"All Auto Care",
    "wof:placetype":"venue"
},
  "geometry": {"coordinates":[-118.499559,34.416449],"type":"Point"}
}