{
  "type": "Feature",
  "properties": {
    "addr:full":"7818 Florence Avenue Downey CA 90240",
    "addr:housenumber":"7818",
    "addr:postcode":"90240",
    "addr:street":"Florence Avenue",
    "iso:country":"US",
    "sg:address":"7818 Florence Avenue",
    "sg:city":"Downey",
    "sg:classifiers":[
        {
            "category":"Home & Garden",
            "subcategory":"Furniture",
            "type":"Retail Goods"
        }
    ],
    "sg:phone":"+1 562 287 2822",
    "sg:postcode":"90240",
    "sg:province":"CA",
    "sg:tags":[
        "store"
    ],
    "wof:name":"La Paloma Furniture",
    "wof:placetype":"venue"
},
  "geometry": {"coordinates":[-118.135183,33.957238],"type":"Point"}
}