{
  "type": "Feature",
  "properties": {
    "iso:country":"US",
    "sg:address":"115 Florence St",
    "sg:city":"Turlock",
    "sg:classifiers":[
        {
            "category":"Retail",
            "subcategory":"Auto Repair",
            "type":"Services"
        }
    ],
    "sg:phone":"+1 209 634 3031",
    "sg:postcode":"95380",
    "sg:province":"CA",
    "sg:tags":[
        "body",
        "automobile",
        "painting"
    ],
    "wof:name":"Smith Chevrolet Bodyshop",
    "wof:placetype":"venue"
},
  "geometry": {"coordinates":[-120.849132,37.495864],"type":"Point"}
}