{
  "type": "Feature",
  "properties": {
    "addr:full":"161 Mitchell Blvd San Rafael CA 94903",
    "addr:housenumber":"161",
    "addr:postcode":"94903",
    "addr:street":"Mitchell Blvd",
    "iso:country":"US",
    "sg:address":"161 Mitchell Blvd",
    "sg:city":"San Rafael",
    "sg:classifiers":[
        {
            "category":"Government",
            "subcategory":"Office",
            "type":"Public Place"
        }
    ],
    "sg:phone":"+1 415 499 6871",
    "sg:postcode":"94903",
    "sg:province":"CA",
    "wof:name":"Marin County Emergency Med Svc",
    "wof:placetype":"venue"
},
  "geometry": {"coordinates":[-122.534763,38.015742],"type":"Point"}
}