{
  "type": "Feature",
  "properties": {
    "iso:country":"US",
    "sg:address":"20190 Redwood Dr",
    "sg:city":"Foresthill",
    "sg:classifiers":[
        {
            "category":"Building & Trades",
            "subcategory":"Construction",
            "type":"Services"
        }
    ],
    "sg:phone":"+1 530 367 3656",
    "sg:postcode":"95631",
    "sg:province":"CA",
    "sg:tags":[
        "maker",
        "cabinet"
    ],
    "wof:name":"Trout Creek Original Woodcarv",
    "wof:placetype":"venue"
},
  "geometry": {"coordinates":[-120.89953,38.985467],"type":"Point"}
}