{
  "type": "Feature",
  "properties": {
    "addr:full":"701 S Parker St Orange CA 92868",
    "addr:housenumber":"701",
    "addr:postcode":"92868",
    "addr:street":"S Parker St",
    "iso:country":"US",
    "sg:address":"701 S Parker St",
    "sg:city":"Orange",
    "sg:classifiers":[
        {
            "category":"Banks & Credit Unions",
            "subcategory":"Bank",
            "type":"Services"
        }
    ],
    "sg:phone":"+1 714 978 7770",
    "sg:postcode":"92868",
    "sg:province":"CA",
    "sg:tags":[
        "company",
        "mortgage"
    ],
    "wof:name":"First United Home Loans",
    "wof:placetype":"venue"
},
  "geometry": {"coordinates":[-117.859589,33.776621],"type":"Point"}
}