{
  "type": "Feature",
  "properties": {
    "addr:full":"500 6th Street Ofc Broderick CA 95605",
    "addr:housenumber":"500",
    "addr:postcode":"95605",
    "addr:street":"6Th Street",
    "iso:country":"US",
    "sg:address":"500 6th Street Ofc",
    "sg:city":"Broderick",
    "sg:classifiers":[
        {
            "category":"Real Estate",
            "subcategory":"Real Estate Operator",
            "type":"Services"
        }
    ],
    "sg:phone":"+1 916 371 1008",
    "sg:postcode":"95605",
    "sg:province":"CA",
    "sg:tags":[
        "apartment"
    ],
    "wof:name":"East Yolo Manor Apartments",
    "wof:placetype":"venue"
},
  "geometry": {"coordinates":[-121.51470399999999,38.586369],"type":"Point"}
}