{
  "type": "Feature",
  "properties": {
    "addr:full":"975 Broadway Chula Vista CA 91911",
    "addr:housenumber":"975",
    "addr:postcode":"91911",
    "addr:street":"Broadway",
    "iso:country":"US",
    "sg:address":"975 Broadway",
    "sg:city":"Chula Vista",
    "sg:classifiers":[
        {
            "category":"Restaurant",
            "type":"Food & Drink"
        }
    ],
    "sg:phone":"+1 619 420 1625",
    "sg:postcode":"91911",
    "sg:province":"CA",
    "wof:name":"LA Nena Mexican Food",
    "wof:placetype":"venue"
},
  "geometry": {"coordinates":[-117.08296,32.614605],"type":"Point"}
}