{
  "type": "Feature",
  "properties": {
    "iso:country":"US",
    "sg:address":"650 W Duarte Rd",
    "sg:city":"Arcadia",
    "sg:classifiers":[
        {
            "category":"Health Services",
            "subcategory":"Doctor",
            "type":"Services"
        }
    ],
    "sg:phone":"+1 626 446 8699",
    "sg:postcode":"91007",
    "sg:province":"CA",
    "sg:tags":[
        "physician",
        "surgeon"
    ],
    "wof:name":"Tseng's Medical Center Inc",
    "wof:placetype":"venue"
},
  "geometry": {"coordinates":[-118.05300099999999,34.126301],"type":"Point"}
}