{
  "type": "Feature",
  "properties": {
    "addr:full":"20543 Saticoy St Winnetka CA 91306",
    "addr:postcode":"20543;91306",
    "addr:street":"Saticoy St",
    "iso:country":"US",
    "sg:address":"20543 Saticoy St",
    "sg:city":"Winnetka",
    "sg:classifiers":[
        {
            "category":"Education",
            "subcategory":"Preschool",
            "type":"Public Place"
        },
        {
            "category":"Education",
            "subcategory":"School",
            "type":"Public Place"
        }
    ],
    "sg:phone":"+1 818 347 5805",
    "sg:postcode":"91306",
    "sg:province":"CA",
    "sg:tags":[
        "elementary"
    ],
    "wof:name":"Wishing Well Academic Pre School",
    "wof:placetype":"venue"
},
  "geometry": {"coordinates":[-118.581001,34.208199],"type":"Point"}
}