{
  "type": "Feature",
  "properties": {
    "iso:country":"US",
    "sg:address":"540 N N St",
    "sg:city":"Oxnard",
    "sg:classifiers":[
        {
            "category":"Professional",
            "subcategory":"Business Services",
            "type":"Services"
        }
    ],
    "sg:phone":"+1 805 487 0373",
    "sg:postcode":"93030",
    "sg:province":"CA",
    "sg:tags":[
        "consultant",
        "coach"
    ],
    "wof:name":"Huff Consulting",
    "wof:placetype":"venue"
},
  "geometry": {"coordinates":[-119.193539,34.207583],"type":"Point"}
}