{
  "type": "Feature",
  "properties": {
    "addr:full":"3616 47th St San Diego CA 92105",
    "addr:housenumber":"3616",
    "addr:postcode":"92105",
    "addr:street":"47Th St",
    "iso:country":"US",
    "sg:address":"3616 47th St",
    "sg:city":"San Diego",
    "sg:classifiers":[
        {
            "category":"Organizations",
            "subcategory":"Religious Organization",
            "type":"Services"
        }
    ],
    "sg:phone":"+1 619 282 0613",
    "sg:postcode":"92105",
    "sg:province":"CA",
    "sg:tags":[
        "church"
    ],
    "wof:name":"Cambodian Buddhist Society",
    "wof:placetype":"venue"
},
  "geometry": {"coordinates":[-117.094205,32.745559],"type":"Point"}
}