{
  "type": "Feature",
  "properties": {
    "iso:country":"US",
    "sg:address":"120 Horton Plz",
    "sg:city":"San Diego",
    "sg:classifiers":[
        {
            "category":"Shopping",
            "subcategory":"Clothing, Apparel, & Fashions",
            "type":"Retail Goods"
        },
        {
            "category":"Shopping Center",
            "type":"Public Place"
        }
    ],
    "sg:phone":"+1 619 233 0705",
    "sg:postcode":"92101",
    "sg:province":"CA",
    "sg:tags":[
        "accessory",
        "clothing",
        "women's"
    ],
    "sg:website":"www.anntaylor.com",
    "wof:name":"Ann Taylor",
    "wof:placetype":"venue"
},
  "geometry": {"coordinates":[-117.162423,32.713668],"type":"Point"}
}