{
  "type": "Feature",
  "properties": {
    "iso:country":"US",
    "sg:address":"3504 University Ave",
    "sg:city":"San Diego",
    "sg:classifiers":[
        {
            "category":"Food Court",
            "type":"Food & Drink"
        }
    ],
    "sg:postcode":"92104",
    "sg:province":"CA",
    "sg:tags":[
        "stand"
    ],
    "wof:name":"Marisco's German Taco Truck 3",
    "wof:placetype":"venue"
},
  "geometry": {"coordinates":[-117.117677,32.749801],"type":"Point"}
}