{
  "type": "Feature",
  "properties": {
    "addr:full":"9800 Lantz Dr Morgan Hill CA 95037",
    "addr:postcode":"9800;95037",
    "addr:street":"Lantz Dr",
    "iso:country":"US",
    "sg:address":"9800 Lantz Dr",
    "sg:city":"Morgan Hill",
    "sg:classifiers":[
        {
            "category":"Park",
            "type":"Public Place"
        },
        {
            "category":"Sports & Exercise",
            "subcategory":"Sports Center",
            "type":"Entertainment"
        }
    ],
    "sg:phone":"+1 408 776 0101",
    "sg:postcode":"95037",
    "sg:province":"CA",
    "sg:tags":[
        "amateur",
        "team"
    ],
    "wof:name":"Santa Clra Cnty Mdl Arcrft Skyprk Avp Dstrct X Amt",
    "wof:placetype":"venue"
},
  "geometry": {"coordinates":[-121.71700300000001,37.1824],"type":"Point"}
}