{
  "type": "Feature",
  "properties": {
    "addr:full":"2 Embarcadero Center San Francisco CA 94111",
    "addr:housenumber":"2",
    "addr:postcode":"94111",
    "addr:street":"Embarcadero Center",
    "iso:country":"US",
    "sg:address":"2 Embarcadero Center",
    "sg:city":"San Francisco",
    "sg:classifiers":[
        {
            "category":"Wholesale",
            "subcategory":"Stationery",
            "type":"Manufacturing & Wholesale Goods"
        }
    ],
    "sg:phone":"+1 415 781 8777",
    "sg:postcode":"94111",
    "sg:province":"CA",
    "sg:tags":[
        "card"
    ],
    "sg:website":"www.papyrusonline.com",
    "wof:name":"Papyrus",
    "wof:placetype":"venue"
},
  "geometry": {"coordinates":[-122.398003,37.7948],"type":"Point"}
}