{
  "type": "Feature",
  "properties": {
    "addr:full":"1180 S Beverly Drive Los Angeles CA 90035",
    "addr:housenumber":"1180",
    "addr:postcode":"90035",
    "addr:street":"S Beverly Drive",
    "iso:country":"US",
    "sg:address":"1180 S Beverly Drive",
    "sg:city":"Los Angeles",
    "sg:classifiers":[
        {
            "category":"Professional",
            "subcategory":"Accounting & Tax Preparation",
            "type":"Services"
        }
    ],
    "sg:phone":"+1 310 553 0052",
    "sg:postcode":"90035",
    "sg:province":"CA",
    "sg:tags":[
        "accountant"
    ],
    "wof:name":"Ackerman Irving CPA",
    "wof:placetype":"venue"
},
  "geometry": {"coordinates":[-118.395549,34.055509],"type":"Point"}
}