{
  "type": "Feature",
  "properties": {
    "addr:full":"13037 Telfair Ave Sylmar CA 91342",
    "addr:housenumber":"13037",
    "addr:postcode":"91342",
    "addr:street":"Telfair Ave",
    "iso:country":"US",
    "sg:address":"13037 Telfair Ave",
    "sg:city":"Sylmar",
    "sg:classifiers":[
        {
            "category":"Building & Trades",
            "subcategory":"Landscaping Services",
            "type":"Services"
        }
    ],
    "sg:phone":"+1 818 768 1825",
    "sg:postcode":"91342",
    "sg:province":"CA",
    "sg:tags":[
        "landscape",
        "contractor"
    ],
    "wof:name":"Tokiwa Landscape",
    "wof:placetype":"venue"
},
  "geometry": {"coordinates":[-118.47575000000001,34.306426],"type":"Point"}
}