{
  "type": "Feature",
  "properties": {
    "addr:full":"34012 Webfoot Loop Fremont CA 94555",
    "addr:postcode":"34012;94555",
    "addr:street":"Webfoot Loop",
    "iso:country":"US",
    "sg:address":"34012 Webfoot Loop",
    "sg:city":"Fremont",
    "sg:classifiers":[
        {
            "category":"Wholesale",
            "subcategory":"Computers",
            "type":"Manufacturing & Wholesale Goods"
        }
    ],
    "sg:phone":"+1 510 790 6291",
    "sg:postcode":"94555",
    "sg:province":"CA",
    "wof:name":"Sapphire Information Systems",
    "wof:placetype":"venue"
},
  "geometry": {"coordinates":[-122.057672,37.566814],"type":"Point"}
}