{
  "type": "Feature",
  "properties": {
    "addr:full":"450 Washington Blvd Marina Del Rey CA 90292",
    "addr:housenumber":"450",
    "addr:postcode":"90292",
    "addr:street":"Washington Blvd",
    "iso:country":"US",
    "sg:address":"450 Washington Blvd",
    "sg:city":"Marina Del Rey",
    "sg:classifiers":[
        {
            "category":"Real Estate",
            "subcategory":"Real Estate Agent",
            "type":"Services"
        }
    ],
    "sg:phone":"+1 310 821 8822",
    "sg:postcode":"90292",
    "sg:province":"CA",
    "sg:website":"www.bergmanrealestate.com",
    "wof:name":"Bergman Estates",
    "wof:placetype":"venue"
},
  "geometry": {"coordinates":[-118.462262,33.981679],"type":"Point"}
}