{
  "type": "Feature",
  "properties": {
    "iso:country":"US",
    "sg:address":"388 2nd St",
    "sg:city":"Los Altos",
    "sg:classifiers":[
        {
            "category":"Wholesale",
            "subcategory":"Durable Goods & Equipment",
            "type":"Manufacturing & Wholesale Goods"
        }
    ],
    "sg:phone":"+1 650 948 7374",
    "sg:postcode":"94022",
    "sg:province":"CA",
    "sg:tags":[
        "importer"
    ],
    "wof:name":"Francisco Diamond Import",
    "wof:placetype":"venue"
},
  "geometry": {"coordinates":[-122.115372,37.37655],"type":"Point"}
}