{
  "type": "Feature",
  "properties": {
    "iso:country":"US",
    "sg:address":"10934 Ironwood Rd",
    "sg:city":"San Diego",
    "sg:classifiers":[
        {
            "category":"Insurance",
            "subcategory":"Insurance Agent",
            "type":"Services"
        }
    ],
    "sg:phone":"+1 858 566 0278",
    "sg:postcode":"92131",
    "sg:province":"CA",
    "wof:name":"Cres Insurance",
    "wof:placetype":"venue"
},
  "geometry": {"coordinates":[-117.097134,32.902906],"type":"Point"}
}