{
  "type": "Feature",
  "properties": {
    "addr:full":"13002 Philadelphia St Whittier CA 90601",
    "addr:housenumber":"13002",
    "addr:postcode":"90601",
    "addr:street":"Philadelphia St",
    "iso:country":"US",
    "sg:address":"13002 Philadelphia St",
    "sg:city":"Whittier",
    "sg:classifiers":[
        {
            "category":"Bars & Pubs",
            "type":"Food & Drink"
        }
    ],
    "sg:phone":"+1 562 693 7998",
    "sg:postcode":"90601",
    "sg:province":"CA",
    "sg:tags":[
        "club",
        "night"
    ],
    "wof:name":"Ibiza Restaurant & Bar",
    "wof:placetype":"venue"
},
  "geometry": {"coordinates":[-118.03674100000001,33.97903],"type":"Point"}
}