{
  "type": "Feature",
  "properties": {
    "addr:full":"7415 Woodley Ave Van Nuys CA 91406",
    "addr:housenumber":"7415",
    "addr:postcode":"91406",
    "addr:street":"Woodley Ave",
    "iso:country":"US",
    "sg:address":"7415 Woodley Ave",
    "sg:city":"Van Nuys",
    "sg:classifiers":[
        {
            "category":"Professional",
            "type":"Services"
        }
    ],
    "sg:phone":"+1 818 785 2560",
    "sg:postcode":"91406",
    "sg:province":"CA",
    "sg:tags":[
        "establishment"
    ],
    "wof:name":"Nemesis Inc Com",
    "wof:placetype":"venue"
},
  "geometry": {"coordinates":[-118.48374,34.205259],"type":"Point"}
}