{
  "type": "Feature",
  "properties": {
    "addr:full":"2724 San Juan Ln Costa Mesa CA 92626",
    "addr:housenumber":"2724",
    "addr:postcode":"92626",
    "addr:street":"San Juan Ln",
    "iso:country":"US",
    "sg:address":"2724 San Juan Ln",
    "sg:city":"Costa Mesa",
    "sg:classifiers":[
        {
            "category":"Travel",
            "subcategory":"Travel Agent",
            "type":"Entertainment"
        }
    ],
    "sg:phone":"+1 714 979 6276",
    "sg:postcode":"92626",
    "sg:province":"CA",
    "sg:tags":[
        "operator",
        "tour"
    ],
    "wof:name":"Bennet Travel & Tours",
    "wof:placetype":"venue"
},
  "geometry": {"coordinates":[-117.89962,33.67467],"type":"Point"}
}