{
  "type": "Feature",
  "properties": {
    "addr:full":"1200 Burlingame Ave Burlingame CA 94010",
    "addr:housenumber":"1200",
    "addr:postcode":"94010",
    "addr:street":"Burlingame Ave",
    "iso:country":"US",
    "sg:address":"1200 Burlingame Ave",
    "sg:city":"Burlingame",
    "sg:classifiers":[
        {
            "category":"Shopping",
            "subcategory":"Luggage & Leather Goods",
            "type":"Retail Goods"
        }
    ],
    "sg:phone":"+1 415 543 3771",
    "sg:postcode":"94010",
    "sg:province":"CA",
    "wof:name":"The Luggage Center",
    "wof:placetype":"venue"
},
  "geometry": {"coordinates":[-122.346001,37.579201],"type":"Point"}
}