{
  "type": "Feature",
  "properties": {
    "addr:full":"1127 N Avalon Blvd Wilmington CA 90744",
    "addr:housenumber":"1127",
    "addr:postcode":"90744",
    "addr:street":"N Avalon Blvd",
    "iso:country":"US",
    "sg:address":"1127 N Avalon Blvd",
    "sg:city":"Wilmington",
    "sg:classifiers":[
        {
            "category":"Health Services",
            "subcategory":"Doctor",
            "type":"Services"
        }
    ],
    "sg:phone":"+1 310 830 3130",
    "sg:postcode":"90744",
    "sg:province":"CA",
    "sg:tags":[
        "clinic"
    ],
    "wof:name":"Seaview Community Clinic",
    "wof:placetype":"venue"
},
  "geometry": {"coordinates":[-118.262998,33.786177],"type":"Point"}
}