{
  "type": "Feature",
  "properties": {
    "iso:country":"US",
    "sg:address":"231 Via Olivera",
    "sg:city":"Camarillo",
    "sg:classifiers":[
        {
            "category":"Professional",
            "type":"Services"
        }
    ],
    "sg:phone":"+1 805 987 2610",
    "sg:postcode":"93012",
    "sg:province":"CA",
    "wof:name":"Joe Martinez",
    "wof:placetype":"venue"
},
  "geometry": {"coordinates":[-119.01340500000001,34.219012],"type":"Point"}
}