{
  "type": "Feature",
  "properties": {
    "iso:country":"US",
    "sg:address":"190 N Plaza St",
    "sg:city":"Brawley",
    "sg:classifiers":[
        {
            "category":"Personal",
            "subcategory":"Beauty Salon",
            "type":"Services"
        }
    ],
    "sg:phone":"+1 760 344 1243",
    "sg:postcode":"92227",
    "sg:province":"CA",
    "wof:name":"Michele's Salon",
    "wof:placetype":"venue"
},
  "geometry": {"coordinates":[-115.534882,32.979623],"type":"Point"}
}