{
  "type": "Feature",
  "properties": {
    "iso:country":"US",
    "sg:address":"6021 Hollywood Blvd",
    "sg:city":"Los Angeles",
    "sg:classifiers":[
        {
            "category":"Recreation",
            "subcategory":"Dance Hall",
            "type":"Entertainment"
        }
    ],
    "sg:phone":"+1 323 463 3331",
    "sg:postcode":"90028",
    "sg:province":"CA",
    "sg:tags":[
        "club"
    ],
    "sg:website":"www.vanguardla.com",
    "wof:name":"Vanguard",
    "wof:placetype":"venue"
},
  "geometry": {"coordinates":[-118.320633,34.101666],"type":"Point"}
}