{
  "type": "Feature",
  "properties": {
    "addr:full":"19682 Beach Blvd Huntington Beach CA 92648",
    "addr:housenumber":"19682",
    "addr:postcode":"92648",
    "addr:street":"Beach Blvd",
    "iso:country":"US",
    "sg:address":"19682 Beach Blvd",
    "sg:city":"Huntington Beach",
    "sg:classifiers":[
        {
            "category":"Personal",
            "subcategory":"Tanning Parlor",
            "type":"Services"
        }
    ],
    "sg:phone":"+1 714 962 6013",
    "sg:postcode":"92648",
    "sg:province":"CA",
    "sg:website":"www.solsticetanningco.com",
    "wof:name":"Solstice Tanning Co",
    "wof:placetype":"venue"
},
  "geometry": {"coordinates":[-117.988998,33.677299],"type":"Point"}
}