{
  "type": "Feature",
  "properties": {
    "addr:full":"737 Arnold Dr Martinez CA 94553",
    "addr:housenumber":"737",
    "addr:postcode":"94553",
    "addr:street":"Arnold Dr",
    "iso:country":"US",
    "sg:address":"737 Arnold Dr",
    "sg:city":"Martinez",
    "sg:classifiers":[
        {
            "category":"Real Estate",
            "subcategory":"Real Estate Services",
            "type":"Services"
        }
    ],
    "sg:phone":"+1 925 688 3342",
    "sg:postcode":"94553",
    "sg:province":"CA",
    "sg:tags":[
        "company",
        "title"
    ],
    "wof:name":"First American Title Co",
    "wof:placetype":"venue"
},
  "geometry": {"coordinates":[-122.111818,37.996655],"type":"Point"}
}