{
  "type": "Feature",
  "properties": {
    "addr:full":"2900 N Rodeo Gulch Rd Soquel CA 95073",
    "addr:housenumber":"2900",
    "addr:postcode":"95073",
    "addr:street":"N Rodeo Gulch Rd",
    "iso:country":"US",
    "sg:address":"2900 N Rodeo Gulch Rd",
    "sg:city":"Soquel",
    "sg:classifiers":[
        {
            "category":"Sports & Exercise",
            "subcategory":"Gym",
            "type":"Entertainment"
        }
    ],
    "sg:phone":"+1 831 462 4712",
    "sg:postcode":"95073",
    "sg:province":"CA",
    "sg:tags":[
        "yoga"
    ],
    "wof:name":"Sri Chaitanya Saraswat Seva Ashram",
    "wof:placetype":"venue"
},
  "geometry": {"coordinates":[-121.96199799999999,37.0214],"type":"Point"}
}