{
  "type": "Feature",
  "properties": {
    "iso:country":"US",
    "sg:address":"1497 S San Jacinto Ave",
    "sg:city":"San Jacinto",
    "sg:classifiers":[
        {
            "category":"Banks & Credit Unions",
            "subcategory":"Bank",
            "type":"Services"
        }
    ],
    "sg:phone":"+1 951 654 2605",
    "sg:postcode":"92583",
    "sg:province":"CA",
    "sg:tags":[
        "state",
        "commercial"
    ],
    "wof:name":"Bank Of Hemet",
    "wof:placetype":"venue"
},
  "geometry": {"coordinates":[-116.958688,33.770194],"type":"Point"}
}