{
  "type": "Feature",
  "properties": {
    "addr:full":"45250 Club Dr Indian Wells CA 92210",
    "addr:housenumber":"45250",
    "addr:postcode":"92210",
    "addr:street":"Club Dr",
    "iso:country":"US",
    "sg:address":"45250 Club Dr",
    "sg:city":"Indian Wells",
    "sg:classifiers":[
        {
            "category":"Mining & Drilling",
            "type":"Manufacturing & Wholesale Goods"
        }
    ],
    "sg:phone":"+1 760 772 0250",
    "sg:postcode":"92210",
    "sg:province":"CA",
    "sg:tags":[
        "exploration"
    ],
    "wof:name":"Martin I Smith Inc",
    "wof:placetype":"venue"
},
  "geometry": {"coordinates":[-116.326707,33.720636],"type":"Point"}
}