{
  "type": "Feature",
  "properties": {
    "iso:country":"US",
    "sg:address":"710 N Heliotrope Dr",
    "sg:city":"Los Angeles",
    "sg:classifiers":[
        {
            "category":"Coffee & Tea",
            "type":"Food & Drink"
        }
    ],
    "sg:phone":"+1 213 305 4484",
    "sg:postcode":"90029",
    "sg:province":"CA",
    "wof:name":"Cafecito Organico",
    "wof:placetype":"venue"
},
  "geometry": {"coordinates":[-118.29483399999999,34.084013],"type":"Point"}
}