{
  "type": "Feature",
  "properties": {
    "addr:full":"938 Windham St Santa Cruz CA 95062",
    "addr:housenumber":"938",
    "addr:postcode":"95062",
    "addr:street":"Windham St",
    "iso:country":"US",
    "sg:address":"938 Windham St",
    "sg:city":"Santa Cruz",
    "sg:classifiers":[
        {
            "category":"Building & Trades",
            "subcategory":"Construction",
            "type":"Services"
        }
    ],
    "sg:phone":"+1 831 425 7636",
    "sg:postcode":"95062",
    "sg:province":"CA",
    "sg:tags":[
        "equipment",
        "computer",
        "rooms"
    ],
    "wof:name":"Nite & Day Power Technologies",
    "wof:placetype":"venue"
},
  "geometry": {"coordinates":[-122.003075,36.973486],"type":"Point"}
}