{
  "type": "Feature",
  "properties": {
    "iso:country":"US",
    "sg:address":"3450 W 6th St Ste 109B",
    "sg:city":"Los Angeles",
    "sg:classifiers":[
        {
            "category":"Professional",
            "type":"Services"
        },
        {
            "category":"Restaurant",
            "type":"Food & Drink"
        }
    ],
    "sg:phone":"+1 213 388 5507",
    "sg:postcode":"90020",
    "sg:province":"CA",
    "sg:tags":[
        "korean",
        "caterer"
    ],
    "wof:name":"Rin Picnic",
    "wof:placetype":"venue"
},
  "geometry": {"coordinates":[-118.29694000000001,34.063343],"type":"Point"}
}