{
  "type": "Feature",
  "properties": {
    "iso:country":"US",
    "sg:address":"4790 Manzanita Avenue",
    "sg:city":"Carmichael",
    "sg:classifiers":[
        {
            "category":"Personal",
            "subcategory":"Beauty Salon",
            "type":"Services"
        }
    ],
    "sg:phone":"+1 916 486 1503",
    "sg:postcode":"95608",
    "sg:province":"CA",
    "sg:tags":[
        "hair"
    ],
    "wof:name":"Gibson Paul D Hairstlst",
    "wof:placetype":"venue"
},
  "geometry": {"coordinates":[-121.32753200000001,38.650849],"type":"Point"}
}