{
  "type": "Feature",
  "properties": {
    "addr:full":"815 5th St Jackson CA 95648",
    "addr:housenumber":"815",
    "addr:postcode":"95648",
    "addr:street":"5Th St",
    "iso:country":"US",
    "sg:address":"815 5th St",
    "sg:city":"Jackson",
    "sg:classifiers":[
        {
            "category":"Health Services",
            "subcategory":"Doctor",
            "type":"Services"
        }
    ],
    "sg:phone":"+1 209 223 5445",
    "sg:postcode":"95648",
    "sg:province":"CA",
    "sg:tags":[
        "physician",
        "surgeon"
    ],
    "wof:name":"Northern California Cardiology",
    "wof:placetype":"venue"
},
  "geometry": {"coordinates":[-121.294219,38.891792],"type":"Point"}
}