{
  "type": "Feature",
  "properties": {
    "addr:full":"242 W Portal Ave San Francisco CA 94127",
    "addr:housenumber":"242",
    "addr:postcode":"94127",
    "addr:street":"W Portal Ave",
    "iso:country":"US",
    "sg:address":"242 W Portal Ave",
    "sg:city":"San Francisco",
    "sg:classifiers":[
        {
            "category":"Shopping",
            "subcategory":"Clothing, Apparel, & Fashions",
            "type":"Retail Goods"
        }
    ],
    "sg:phone":"+1 415 681 5411",
    "sg:postcode":"94127",
    "sg:province":"CA",
    "wof:name":"White Rose Boutique",
    "wof:placetype":"venue"
},
  "geometry": {"coordinates":[-122.467958,37.739305],"type":"Point"}
}