{
  "type": "Feature",
  "properties": {
    "iso:country":"US",
    "sg:address":"2635 Lavery Ct",
    "sg:city":"Newbury Park",
    "sg:classifiers":[
        {
            "category":"Building & Trades",
            "subcategory":"Electrical",
            "type":"Services"
        }
    ],
    "sg:phone":"+1 818 991 8858",
    "sg:postcode":"91320",
    "sg:province":"CA",
    "sg:tags":[
        "electrical",
        "electric",
        "contractor"
    ],
    "wof:name":"Security Electric & Lighting",
    "wof:placetype":"venue"
},
  "geometry": {"coordinates":[-118.92748,34.194141],"type":"Point"}
}