{
  "type": "Feature",
  "properties": {
    "iso:country":"US",
    "sg:address":"3711 Saviers Rd",
    "sg:city":"Oxnard",
    "sg:classifiers":[
        {
            "category":"Health Services",
            "subcategory":"Chiropractor",
            "type":"Services"
        }
    ],
    "sg:phone":"+1 805 486 9689",
    "sg:postcode":"93033",
    "sg:province":"CA",
    "wof:name":"Marvin Wergeland Chiropractic",
    "wof:placetype":"venue"
},
  "geometry": {"coordinates":[-119.177724,34.165188],"type":"Point"}
}