{
  "type": "Feature",
  "properties": {
    "addr:full":"112 Clearbrook Ln Costa Mesa CA 92626",
    "addr:housenumber":"112",
    "addr:postcode":"92626",
    "addr:street":"Clearbrook Ln",
    "iso:country":"US",
    "sg:address":"112 Clearbrook Ln",
    "sg:city":"Costa Mesa",
    "sg:classifiers":[
        {
            "category":"Professional",
            "type":"Services"
        }
    ],
    "sg:phone":"+1 714 436 0667",
    "sg:postcode":"92626",
    "sg:province":"CA",
    "wof:name":"Rob Edman",
    "wof:placetype":"venue"
},
  "geometry": {"coordinates":[-117.905756,33.662838],"type":"Point"}
}