{
  "type": "Feature",
  "properties": {
    "addr:full":"6331 Orange St Los Angeles CA 90048",
    "addr:housenumber":"6331",
    "addr:postcode":"90048",
    "addr:street":"Orange St",
    "iso:country":"US",
    "sg:address":"6331 Orange St",
    "sg:city":"Los Angeles",
    "sg:classifiers":[
        {
            "category":"Real Estate",
            "subcategory":"Real Estate Operator",
            "type":"Services"
        }
    ],
    "sg:phone":"+1 323 933 1580",
    "sg:postcode":"90048",
    "sg:province":"CA",
    "sg:tags":[
        "apartment"
    ],
    "wof:name":"Wilshire Regency",
    "wof:placetype":"venue"
},
  "geometry": {"coordinates":[-118.36599699999999,34.064602],"type":"Point"}
}