{
  "type": "Feature",
  "properties": {
    "addr:full":"BART/Muni Embarcadero Station 298 Market Street San Francisco CA 94111",
    "addr:housenumber":"298",
    "addr:postcode":"94111",
    "addr:street":"Embarcadero;Market Street",
    "iso:country":"US",
    "sg:address":"BART/Muni Embarcadero Station 298 Market Street",
    "sg:city":"San Francisco",
    "sg:classifiers":[
        {
            "category":"Coffee & Tea",
            "type":"Food & Drink"
        }
    ],
    "sg:phone":"+1 415 970 6608",
    "sg:postcode":"94111",
    "sg:province":"CA",
    "sg:website":"www.peets.com",
    "wof:name":"Peet's Coffee & Tea",
    "wof:placetype":"venue"
},
  "geometry": {"coordinates":[-122.39738800000001,37.792433],"type":"Point"}
}