{
  "type": "Feature",
  "properties": {
    "addr:full":"14927 Magnolia Blvd Sherman Oaks CA 91403",
    "addr:housenumber":"14927",
    "addr:postcode":"91403",
    "addr:street":"Magnolia Blvd",
    "iso:country":"US",
    "sg:address":"14927 Magnolia Blvd",
    "sg:city":"Sherman Oaks",
    "sg:classifiers":[
        {
            "category":"Restaurant",
            "type":"Food & Drink"
        }
    ],
    "sg:phone":"+1 818 779 1088",
    "sg:postcode":"91403",
    "sg:province":"CA",
    "wof:name":"Pizza Man He Delivers",
    "wof:placetype":"venue"
},
  "geometry": {"coordinates":[-118.459588,34.164925],"type":"Point"}
}