{
  "type": "Feature",
  "properties": {
    "addr:full":"5960 Florence Ave Bell Gardens CA 90201",
    "addr:housenumber":"5960",
    "addr:postcode":"90201",
    "addr:street":"Florence Ave",
    "iso:country":"US",
    "sg:address":"5960 Florence Ave",
    "sg:city":"Bell Gardens",
    "sg:classifiers":[
        {
            "category":"Professional",
            "subcategory":"Accounting & Tax Preparation",
            "type":"Services"
        }
    ],
    "sg:phone":"+1 323 562 1717",
    "sg:postcode":"90201",
    "sg:province":"CA",
    "sg:tags":[
        "return",
        "filing"
    ],
    "wof:name":"Jackson Hewitt Tax Svc",
    "wof:placetype":"venue"
},
  "geometry": {"coordinates":[-118.158221,33.96715],"type":"Point"}
}