{
  "type": "Feature",
  "properties": {
    "iso:country":"US",
    "sg:address":"203 Mann Dr",
    "sg:city":"Big Bear City",
    "sg:classifiers":[
        {
            "category":"Building & Trades",
            "subcategory":"Construction",
            "type":"Services"
        }
    ],
    "sg:phone":"+1 909 584 9700",
    "sg:postcode":"92314",
    "sg:province":"CA",
    "sg:tags":[
        "fire",
        "restoration",
        "damage"
    ],
    "wof:name":"AAA Mountainview Restoration",
    "wof:placetype":"venue"
},
  "geometry": {"coordinates":[-116.821382,34.260408],"type":"Point"}
}