{
  "type": "Feature",
  "properties": {
    "addr:full":"1010 Clement Street San Francisco CA 94118",
    "addr:housenumber":"1010",
    "addr:postcode":"94118",
    "addr:street":"Clement Street",
    "iso:country":"US",
    "sg:address":"1010 Clement Street",
    "sg:city":"San Francisco",
    "sg:classifiers":[
        {
            "category":"Retail",
            "subcategory":"Laundry & Dry Cleaning",
            "type":"Services"
        }
    ],
    "sg:phone":"+1 415 752 1008",
    "sg:postcode":"94118",
    "sg:province":"CA",
    "wof:name":"Ten Ten Full Service Dry Cleaner",
    "wof:placetype":"venue"
},
  "geometry": {"coordinates":[-122.470001,37.782799],"type":"Point"}
}