{
  "type": "Feature",
  "properties": {
    "addr:full":"1788 S Victoria Ave Ventura CA 93003",
    "addr:housenumber":"1788",
    "addr:postcode":"93003",
    "addr:street":"S Victoria Ave",
    "iso:country":"US",
    "sg:address":"1788 S Victoria Ave",
    "sg:city":"Ventura",
    "sg:classifiers":[
        {
            "category":"Cinema",
            "subcategory":"Movie Rental",
            "type":"Entertainment"
        }
    ],
    "sg:phone":"+1 805 639 3216",
    "sg:postcode":"93003",
    "sg:province":"CA",
    "sg:tags":[
        "leasing",
        "video",
        "disc",
        "tape"
    ],
    "wof:name":"Hollywood Video",
    "wof:placetype":"venue"
},
  "geometry": {"coordinates":[-119.21065,34.257306],"type":"Point"}
}