{
  "type": "Feature",
  "properties": {
    "addr:full":"425 E Alvarado St Ste C Fallbrook CA 92028",
    "addr:housenumber":"425",
    "addr:postcode":"92028",
    "addr:street":"E Alvarado St Ste C",
    "iso:country":"US",
    "sg:address":"425 E Alvarado St Ste C",
    "sg:city":"Fallbrook",
    "sg:classifiers":[
        {
            "category":"Health Services",
            "subcategory":"Doctor",
            "type":"Services"
        },
        {
            "category":"Health Services",
            "subcategory":"Dentist",
            "type":"Services"
        }
    ],
    "sg:phone":"+1 760 728 5575",
    "sg:postcode":"92028",
    "sg:province":"CA",
    "sg:tags":[
        "surgeon",
        "oral",
        "orthodontist"
    ],
    "wof:name":"Mohr Robert P DDS",
    "wof:placetype":"venue"
},
  "geometry": {"coordinates":[-117.248001,33.382],"type":"Point"}
}