{
  "type": "Feature",
  "properties": {
    "addr:full":"3780 Kilroy Airport Way #880 Long Beach CA 90806",
    "addr:housenumber":"3780;880",
    "addr:postcode":"90806",
    "addr:street":"Kilroy Airport Way #",
    "iso:country":"US",
    "sg:address":"3780 Kilroy Airport Way #880",
    "sg:city":"Long Beach",
    "sg:classifiers":[
        {
            "category":"Real Estate",
            "subcategory":"Real Estate Services",
            "type":"Services"
        }
    ],
    "sg:phone":"+1 562 795 6900",
    "sg:postcode":"90806",
    "sg:province":"CA",
    "sg:website":"www.charlesdunn.com",
    "wof:name":"Charles Dunn Company",
    "wof:placetype":"venue"
},
  "geometry": {"coordinates":[-118.146348,33.80679],"type":"Point"}
}