{
  "type": "Feature",
  "properties": {
    "iso:country":"US",
    "sg:address":"19634 Ventura Blvd",
    "sg:city":"Tarzana",
    "sg:classifiers":[
        {
            "category":"Health Services",
            "subcategory":"Health Practitioner",
            "type":"Services"
        }
    ],
    "sg:phone":"+1 818 996 3142",
    "sg:postcode":"91356",
    "sg:province":"CA",
    "sg:tags":[
        "psychologist",
        "doctor"
    ],
    "wof:name":"Ackerman Andrea PHD",
    "wof:placetype":"venue"
},
  "geometry": {"coordinates":[-118.560997,34.172699],"type":"Point"}
}