{
  "type": "Feature",
  "properties": {
    "addr:full":"10261 Trask Ave Garden Grove CA 92843",
    "addr:postcode":"10261;92843",
    "addr:street":"Trask Ave",
    "iso:country":"US",
    "sg:address":"10261 Trask Ave",
    "sg:city":"Garden Grove",
    "sg:classifiers":[
        {
            "category":"Shopping",
            "subcategory":"Hobbies, Toys, & Games",
            "type":"Retail Goods"
        }
    ],
    "sg:phone":"+1 714 638 5505",
    "sg:postcode":"92843",
    "sg:province":"CA",
    "wof:name":"EZ Crafts",
    "wof:placetype":"venue"
},
  "geometry": {"coordinates":[-117.949913,33.766893],"type":"Point"}
}