{
  "type": "Feature",
  "properties": {
    "iso:country":"US",
    "sg:address":"12882 Falcon Point Pl",
    "sg:city":"Truckee",
    "sg:classifiers":[
        {
            "category":"Wholesale",
            "subcategory":"Groceries",
            "type":"Manufacturing & Wholesale Goods"
        }
    ],
    "sg:phone":"+1 530 587 0272",
    "sg:postcode":"96161",
    "sg:province":"CA",
    "sg:tags":[
        "food",
        "product"
    ],
    "wof:name":"Facciola Food Svc",
    "wof:placetype":"venue"
},
  "geometry": {"coordinates":[-120.228807,39.352445],"type":"Point"}
}