{
  "type": "Feature",
  "properties": {
    "iso:country":"US",
    "sg:address":"1205 Coast Village Rd",
    "sg:city":"Montecito",
    "sg:classifiers":[
        {
            "category":"Personal",
            "subcategory":"Beauty Salon",
            "type":"Services"
        }
    ],
    "sg:phone":"+1 805 969 4506",
    "sg:postcode":"93108",
    "sg:province":"CA",
    "wof:name":"Nona & Co",
    "wof:placetype":"venue"
},
  "geometry": {"coordinates":[-119.641695,34.421329],"type":"Point"}
}