{
  "type": "Feature",
  "properties": {
    "addr:full":"11952 Challenger Ct Moorpark CA 93021",
    "addr:housenumber":"11952",
    "addr:postcode":"ca 93021",
    "addr:street":"Challenger Ct",
    "iso:country":"US",
    "sg:address":"11952 Challenger Ct",
    "sg:city":"Moorpark",
    "sg:classifiers":[
        {
            "category":"Manufacturing",
            "subcategory":"Electronics",
            "type":"Manufacturing & Wholesale Goods"
        }
    ],
    "sg:phone":"+1 805 529 3788",
    "sg:postcode":"93021",
    "sg:province":"CA",
    "sg:tags":[
        "equipment",
        "electronic",
        "supply"
    ],
    "sg:website":"www.sliprings.com",
    "wof:name":"Danmar Industries Inc",
    "wof:placetype":"venue"
},
  "geometry": {"coordinates":[-118.895482,34.280872],"type":"Point"}
}