{
  "type": "Feature",
  "properties": {
    "addr:full":"2480 Merrychase Dr Cameron Park CA 95682",
    "addr:postcode":"2480;95682",
    "addr:street":"Merrychase Dr",
    "iso:country":"US",
    "sg:address":"2480 Merrychase Dr",
    "sg:city":"Cameron Park",
    "sg:classifiers":[
        {
            "category":"Education",
            "subcategory":"School",
            "type":"Public Place"
        }
    ],
    "sg:phone":"+1 916 933 0584",
    "sg:postcode":"95682",
    "sg:province":"CA",
    "wof:name":"Camerado Springs Middle School",
    "wof:placetype":"venue"
},
  "geometry": {"coordinates":[-121.00265899999999,38.657101],"type":"Point"}
}