{
  "type": "Feature",
  "properties": {
    "iso:country":"US",
    "sg:address":"1405 S El Camino Real",
    "sg:city":"Oceanside",
    "sg:classifiers":[
        {
            "category":"Restaurant",
            "type":"Food & Drink"
        }
    ],
    "sg:phone":"+1 760 967 6024",
    "sg:postcode":"92054",
    "sg:province":"CA",
    "sg:tags":[
        "seafood",
        "mexican"
    ],
    "wof:name":"Mariscos La Ensenada",
    "wof:placetype":"venue"
},
  "geometry": {"coordinates":[-117.331001,33.199501],"type":"Point"}
}