{
  "type": "Feature",
  "properties": {
    "iso:country":"US",
    "sg:address":"655 2nd St",
    "sg:city":"Encinitas",
    "sg:classifiers":[
        {
            "category":"Professional",
            "type":"Services"
        }
    ],
    "sg:phone":"+1 760 632 7112",
    "sg:postcode":"92024",
    "sg:province":"CA",
    "wof:name":"Artha Zahniser Inc",
    "wof:placetype":"venue"
},
  "geometry": {"coordinates":[-117.294443,33.044002],"type":"Point"}
}