{
  "type": "Feature",
  "properties": {
    "iso:country":"US",
    "sg:address":"2428 Pamela Ln",
    "sg:city":"Modesto",
    "sg:classifiers":[
        {
            "category":"Manufacturing",
            "subcategory":"Tools & Machinery",
            "type":"Manufacturing & Wholesale Goods"
        }
    ],
    "sg:phone":"+1 209 550 0999",
    "sg:postcode":"95350",
    "sg:province":"CA",
    "sg:tags":[
        "mfg",
        "ophthalmic"
    ],
    "wof:name":"James P Eichberger Optician",
    "wof:placetype":"venue"
},
  "geometry": {"coordinates":[-121.039005,37.676332],"type":"Point"}
}