{
  "type": "Feature",
  "properties": {
    "iso:country":"US",
    "sg:address":"7464 Bulkley Rd",
    "sg:city":"Dixon",
    "sg:classifiers":[
        {
            "category":"Building & Trades",
            "subcategory":"Construction",
            "type":"Services"
        }
    ],
    "sg:phone":"+1 707 678 3279",
    "sg:postcode":"95620",
    "sg:province":"CA",
    "sg:tags":[
        "excavation",
        "contractor"
    ],
    "wof:name":"Atkinson Land Leveling",
    "wof:placetype":"venue"
},
  "geometry": {"coordinates":[-121.721373,38.429826],"type":"Point"}
}