{
  "type": "Feature",
  "properties": {
    "addr:full":"22285 Erwin St Woodland Hills CA 91367",
    "addr:housenumber":"22285",
    "addr:postcode":"91367",
    "addr:street":"Erwin St",
    "iso:country":"US",
    "sg:address":"22285 Erwin St",
    "sg:city":"Woodland Hills",
    "sg:classifiers":[
        {
            "category":"Professional",
            "subcategory":"Art Services",
            "type":"Services"
        }
    ],
    "sg:phone":"+1 818 227 5644",
    "sg:postcode":"91367",
    "sg:province":"CA",
    "sg:tags":[
        "photographer"
    ],
    "wof:name":"Lester Photography",
    "wof:placetype":"venue"
},
  "geometry": {"coordinates":[-118.61451099999999,34.1829],"type":"Point"}
}