{
  "type": "Feature",
  "properties": {
    "addr:full":"606 Clement St San Francisco CA 94118",
    "addr:housenumber":"606",
    "addr:postcode":"94118",
    "addr:street":"Clement St",
    "iso:country":"US",
    "sg:address":"606 Clement St",
    "sg:city":"San Francisco",
    "sg:classifiers":[
        {
            "category":"Wholesale",
            "subcategory":"Non-durable Goods",
            "type":"Manufacturing & Wholesale Goods"
        }
    ],
    "sg:phone":"+1 415 752 7092",
    "sg:postcode":"94118",
    "sg:province":"CA",
    "wof:name":"99 Cent Depot",
    "wof:placetype":"venue"
},
  "geometry": {"coordinates":[-122.466515,37.782926],"type":"Point"}
}