{
  "type": "Feature",
  "properties": {
    "iso:country":"US",
    "sg:address":"2434 Vineyard Ave",
    "sg:city":"Escondido",
    "sg:classifiers":[
        {
            "category":"Personal",
            "subcategory":"Shoe Repair & Shine",
            "type":"Services"
        }
    ],
    "sg:phone":"+1 760 233 1307",
    "sg:postcode":"92029",
    "sg:province":"CA",
    "sg:tags":[
        "repairing",
        "boot"
    ],
    "wof:name":"Code Cobblers Inc",
    "wof:placetype":"venue"
},
  "geometry": {"coordinates":[-117.118681,33.124331],"type":"Point"}
}