{
  "type": "Feature",
  "properties": {
    "iso:country":"US",
    "sg:address":"2007 Preisker Ln",
    "sg:city":"Santa Maria",
    "sg:classifiers":[
        {
            "category":"Building & Trades",
            "subcategory":"Construction",
            "type":"Services"
        }
    ],
    "sg:phone":"+1 805 928 8948",
    "sg:postcode":"93454",
    "sg:province":"CA",
    "sg:tags":[
        "contractor"
    ],
    "wof:name":"Halsell Builders",
    "wof:placetype":"venue"
},
  "geometry": {"coordinates":[-120.431618,34.978997],"type":"Point"}
}