{
  "type": "Feature",
  "properties": {
    "iso:country":"US",
    "sg:address":"5433 Laurel Canyon Blvd",
    "sg:city":"Valley Village",
    "sg:classifiers":[
        {
            "category":"Communications",
            "subcategory":"Film & Video Production",
            "type":"Services"
        }
    ],
    "sg:phone":"+1 323 851 2333",
    "sg:postcode":"91607",
    "sg:province":"CA",
    "sg:tags":[
        "motion"
    ],
    "wof:name":"Pie Town Productions Inc",
    "wof:placetype":"venue"
},
  "geometry": {"coordinates":[-118.396576,34.16978],"type":"Point"}
}