{
  "type": "Feature",
  "properties": {
    "addr:full":"12071 Seal Beach Blvd Seal Beach CA 90740",
    "addr:housenumber":"12071",
    "addr:postcode":"90740",
    "addr:street":"Seal Beach Blvd",
    "iso:country":"US",
    "sg:address":"12071 Seal Beach Blvd",
    "sg:city":"Seal Beach",
    "sg:classifiers":[
        {
            "category":"Autos & Motor Vehicles",
            "subcategory":"Fuel & Gas Station",
            "type":"Retail Goods"
        },
        {
            "category":"Retail",
            "subcategory":"Auto Repair",
            "type":"Services"
        }
    ],
    "sg:phone":"+1 562 493 4581",
    "sg:postcode":"90740",
    "sg:province":"CA",
    "wof:name":"Conkle Union 76",
    "wof:placetype":"venue"
},
  "geometry": {"coordinates":[-118.07199900000001,33.7868],"type":"Point"}
}