{
  "type": "Feature",
  "properties": {
    "addr:full":"300 1st St Woodland CA 95695",
    "addr:housenumber":"300",
    "addr:postcode":"95695",
    "addr:street":"1St St",
    "iso:country":"US",
    "sg:address":"300 1st St",
    "sg:city":"Woodland",
    "sg:classifiers":[
        {
            "category":"Government",
            "subcategory":"Office",
            "type":"Public Place"
        }
    ],
    "sg:phone":"+1 530 661 5816",
    "sg:postcode":"95695",
    "sg:province":"CA",
    "sg:tags":[
        "village"
    ],
    "sg:website":"www.cityofwoodland.org",
    "wof:name":"Building Inspection & Permits",
    "wof:placetype":"venue"
},
  "geometry": {"coordinates":[-121.77314800000001,38.678117],"type":"Point"}
}