{
  "type": "Feature",
  "properties": {
    "addr:full":"1277 Kern St Taft CA 93268",
    "addr:housenumber":"1277",
    "addr:postcode":"93268",
    "addr:street":"Kern St",
    "iso:country":"US",
    "sg:address":"1277 Kern St",
    "sg:city":"Taft",
    "sg:classifiers":[
        {
            "category":"Wholesale",
            "subcategory":"Scrap",
            "type":"Manufacturing & Wholesale Goods"
        }
    ],
    "sg:phone":"+1 661 765 6752",
    "sg:postcode":"93268",
    "sg:province":"CA",
    "sg:tags":[
        "recycling",
        "center"
    ],
    "wof:name":"J & D Recycling",
    "wof:placetype":"venue"
},
  "geometry": {"coordinates":[-119.470164,35.146455],"type":"Point"}
}