{
  "type": "Feature",
  "properties": {
    "iso:country":"US",
    "sg:address":"430 N Euclid St",
    "sg:city":"Anaheim",
    "sg:classifiers":[
        {
            "category":"Shopping",
            "subcategory":"Pets & Pet Supplies",
            "type":"Retail Goods"
        }
    ],
    "sg:phone":"+1 714 635 1417",
    "sg:postcode":"92801",
    "sg:province":"CA",
    "sg:tags":[
        "store"
    ],
    "wof:name":"Petco",
    "wof:placetype":"venue"
},
  "geometry": {"coordinates":[-117.941002,33.837399],"type":"Point"}
}