{
  "type": "Feature",
  "properties": {
    "addr:full":"710 Camino Del Mar Stratford Inn Del Mar CA 92014",
    "addr:housenumber":"710",
    "addr:postcode":"92014",
    "addr:street":"Camino Del Mar",
    "iso:country":"US",
    "sg:address":"710 Camino Del Mar Stratford Inn",
    "sg:city":"Del Mar",
    "sg:classifiers":[
        {
            "category":"Personal",
            "subcategory":"Beauty Salon",
            "type":"Services"
        }
    ],
    "sg:phone":"+1 858 356 0307",
    "sg:postcode":"92014",
    "sg:province":"CA",
    "sg:tags":[
        "spa"
    ],
    "sg:website":"www.spanamara.com",
    "wof:name":"SPA Namara",
    "wof:placetype":"venue"
},
  "geometry": {"coordinates":[-117.262451,32.950034],"type":"Point"}
}