{
  "type": "Feature",
  "properties": {
    "addr:full":"33087 Rd 228 North Fork CA 93643",
    "addr:postcode":"33087;93643",
    "addr:street":"Rd 228",
    "iso:country":"US",
    "sg:address":"33087 Rd 228",
    "sg:city":"North Fork",
    "sg:classifiers":[
        {
            "category":"Education",
            "subcategory":"School",
            "type":"Public Place"
        }
    ],
    "sg:phone":"+1 559 877 2215",
    "sg:postcode":"93643",
    "sg:province":"CA",
    "wof:name":"North Fork Elementary School",
    "wof:placetype":"venue"
},
  "geometry": {"coordinates":[-119.503325,37.223454],"type":"Point"}
}