{
  "type": "Feature",
  "properties": {
    "iso:country":"US",
    "sg:address":"370 W 6th St",
    "sg:city":"San Bernardino",
    "sg:classifiers":[
        {
            "category":"Banks & Credit Unions",
            "subcategory":"Investment Brokerage",
            "type":"Services"
        }
    ],
    "sg:phone":"+1 909 383 8621",
    "sg:postcode":"92401",
    "sg:province":"CA",
    "sg:tags":[
        "advisory"
    ],
    "wof:name":"Freedom Equity Group & Allfund",
    "wof:placetype":"venue"
},
  "geometry": {"coordinates":[-117.291652,34.110267],"type":"Point"}
}