{
  "type": "Feature",
  "properties": {
    "iso:country":"US",
    "sg:address":"286 S Washington St",
    "sg:city":"Sonora",
    "sg:classifiers":[
        {
            "category":"Travel",
            "subcategory":"Hotels & Motels",
            "type":"Entertainment"
        }
    ],
    "sg:phone":"+1 209 532 3421",
    "sg:postcode":"95370",
    "sg:province":"CA",
    "wof:name":"Gunn House Motor Hotel",
    "wof:placetype":"venue"
},
  "geometry": {"coordinates":[-120.382167,37.981785],"type":"Point"}
}