{
  "type": "Feature",
  "properties": {
    "iso:country":"US",
    "sg:address":"900 E Port Hueneme Rd",
    "sg:city":"Port Hueneme",
    "sg:classifiers":[
        {
            "category":"Freight",
            "type":"Transportation"
        }
    ],
    "sg:phone":"+1 805 488 3886",
    "sg:postcode":"93041",
    "sg:province":"CA",
    "sg:tags":[
        "general"
    ],
    "wof:name":"Channel Islands Self Storage",
    "wof:placetype":"venue"
},
  "geometry": {"coordinates":[-119.186588,34.147425],"type":"Point"}
}