{
  "type": "Feature",
  "properties": {
    "addr:full":"1141 S Crescent Heights Blvd Los Angeles CA 90035",
    "addr:housenumber":"1141",
    "addr:postcode":"90035",
    "addr:street":"S Crescent Heights Blvd",
    "iso:country":"US",
    "sg:address":"1141 S Crescent Heights Blvd",
    "sg:city":"Los Angeles",
    "sg:classifiers":[
        {
            "category":"Professional",
            "type":"Services"
        },
        {
            "category":"Professional",
            "subcategory":"Business Services",
            "type":"Services"
        }
    ],
    "sg:phone":"+1 323 965 8858",
    "sg:postcode":"90035",
    "sg:province":"CA",
    "sg:tags":[
        "lecture",
        "bureau",
        "seminar"
    ],
    "wof:name":"Tillman Acting Seminars",
    "wof:placetype":"venue"
},
  "geometry": {"coordinates":[-118.370988,34.055219],"type":"Point"}
}