{
  "type": "Feature",
  "properties": {
    "addr:full":"1861 Lomita Blvd Ste F Lomita CA 90717",
    "addr:housenumber":"1861",
    "addr:postcode":"90717",
    "addr:street":"Lomita Blvd Ste F",
    "iso:country":"US",
    "sg:address":"1861 Lomita Blvd Ste F",
    "sg:city":"Lomita",
    "sg:classifiers":[
        {
            "category":"Building & Trades",
            "subcategory":"Landscaping Services",
            "type":"Services"
        }
    ],
    "sg:phone":"+1 310 326 2679",
    "sg:postcode":"90717",
    "sg:province":"CA",
    "sg:tags":[
        "lawn",
        "designer",
        "consultant",
        "contractor",
        "maintenance",
        "landscape"
    ],
    "wof:name":"Green Scene Landscapes",
    "wof:placetype":"venue"
},
  "geometry": {"coordinates":[-118.310997,33.7985],"type":"Point"}
}