{
  "type": "Feature",
  "properties": {
    "addr:full":"16940 Krameria Ave Riverside CA 92504",
    "addr:housenumber":"16940",
    "addr:postcode":"92504",
    "addr:street":"Krameria Ave",
    "iso:country":"US",
    "sg:address":"16940 Krameria Ave",
    "sg:city":"Riverside",
    "sg:classifiers":[
        {
            "category":"Education",
            "subcategory":"School",
            "type":"Public Place"
        }
    ],
    "sg:phone":"+1 951 788 7117",
    "sg:postcode":"92504",
    "sg:province":"CA",
    "wof:name":"Woodcrest Elementary School",
    "wof:placetype":"venue"
},
  "geometry": {"coordinates":[-117.36944800000001,33.879955],"type":"Point"}
}