{
  "type": "Feature",
  "properties": {
    "addr:full":"3049 Laurashawn Ln Escondido CA 92026",
    "addr:housenumber":"3049",
    "addr:postcode":"92026",
    "addr:street":"Laurashawn Ln",
    "iso:country":"US",
    "sg:address":"3049 Laurashawn Ln",
    "sg:city":"Escondido",
    "sg:classifiers":[
        {
            "category":"Retail",
            "subcategory":"Auto Repair",
            "type":"Services"
        }
    ],
    "sg:phone":"+1 760 741 3651",
    "sg:postcode":"92026",
    "sg:province":"CA",
    "sg:tags":[
        "repairing",
        "automobile"
    ],
    "wof:name":"Motors Unlimited",
    "wof:placetype":"venue"
},
  "geometry": {"coordinates":[-117.08616600000001,33.179434],"type":"Point"}
}