{
  "type": "Feature",
  "properties": {
    "addr:full":"3211 Holiday Ct San Diego CA 92121",
    "addr:housenumber":"3211",
    "addr:postcode":"92121",
    "addr:street":"Holiday Ct",
    "iso:country":"US",
    "sg:address":"3211 Holiday Ct",
    "sg:city":"San Diego",
    "sg:classifiers":[
        {
            "category":"Real Estate",
            "subcategory":"Real Estate Services",
            "type":"Services"
        }
    ],
    "sg:phone":"+1 858 587 4812",
    "sg:postcode":"92121",
    "sg:province":"CA",
    "wof:name":"I National Closing & Escrow",
    "wof:placetype":"venue"
},
  "geometry": {"coordinates":[-117.233116,32.870288],"type":"Point"}
}