{
  "type": "Feature",
  "properties": {
    "iso:country":"US",
    "sg:address":"217 Ohio St",
    "sg:city":"Vallejo",
    "sg:classifiers":[
        {
            "category":"Professional",
            "subcategory":"Advertising",
            "type":"Services"
        }
    ],
    "sg:phone":"+1 707 644 4218",
    "sg:postcode":"94590",
    "sg:province":"CA",
    "sg:tags":[
        "counselor"
    ],
    "wof:name":"By Design Multimedia",
    "wof:placetype":"venue"
},
  "geometry": {"coordinates":[-122.26170999999999,38.107072],"type":"Point"}
}