{
  "type": "Feature",
  "properties": {
    "iso:country":"US",
    "sg:address":"1896 Curtner Ave",
    "sg:city":"San Jose",
    "sg:classifiers":[
        {
            "category":"Restaurant",
            "type":"Food & Drink"
        }
    ],
    "sg:phone":"+1 408 369 9905",
    "sg:postcode":"95124",
    "sg:province":"CA",
    "sg:tags":[
        "mexican"
    ],
    "sg:website":"www.adelitastaqueria.com",
    "wof:name":"Adelita's Taqueria",
    "wof:placetype":"venue"
},
  "geometry": {"coordinates":[-121.923784,37.27548],"type":"Point"}
}