{
  "type": "Feature",
  "properties": {
    "iso:country":"US",
    "sg:address":"201 N E St",
    "sg:city":"San Bernardino",
    "sg:classifiers":[
        {
            "category":"Building & Trades",
            "subcategory":"Landscaping Services",
            "type":"Services"
        }
    ],
    "sg:phone":"+1 909 383 5228",
    "sg:postcode":"92401",
    "sg:province":"CA",
    "sg:tags":[
        "landscape",
        "contractor"
    ],
    "sg:website":"www.iccals.com",
    "wof:name":"I C Cals",
    "wof:placetype":"venue"
},
  "geometry": {"coordinates":[-117.294074,34.104114],"type":"Point"}
}