{
  "type": "Feature",
  "properties": {
    "addr:full":"1503 South 56th St El Cerrito CA 94530",
    "addr:housenumber":"1503",
    "addr:postcode":"94530",
    "addr:street":"South 56Th St",
    "iso:country":"US",
    "sg:address":"1503 South 56th St",
    "sg:city":"El Cerrito",
    "sg:classifiers":[
        {
            "category":"Building & Trades",
            "subcategory":"Plumbing",
            "type":"Services"
        },
        {
            "category":"Building & Trades",
            "subcategory":"Construction",
            "type":"Services"
        },
        {
            "category":"Building & Trades",
            "subcategory":"Electrical",
            "type":"Services"
        }
    ],
    "sg:phone":"+1 510 367 6112",
    "sg:postcode":"94530",
    "sg:province":"CA",
    "sg:tags":[
        "electrician",
        "contractor"
    ],
    "sg:website":"www.keenebuilders.com",
    "wof:name":"Keene Builders, Plumbers and Consultants",
    "wof:placetype":"venue"
},
  "geometry": {"coordinates":[-122.316884,37.919758],"type":"Point"}
}