{
  "type": "Feature",
  "properties": {
    "iso:country":"US",
    "sg:address":"1261 Goodrich Ave",
    "sg:city":"Wilmington",
    "sg:classifiers":[
        {
            "category":"Freight",
            "type":"Transportation"
        }
    ],
    "sg:phone":"+1 310 835 4504",
    "sg:postcode":"90744",
    "sg:province":"CA",
    "sg:tags":[
        "trucking"
    ],
    "wof:name":"F X Express",
    "wof:placetype":"venue"
},
  "geometry": {"coordinates":[-118.238947,33.790141],"type":"Point"}
}