{
  "type": "Feature",
  "properties": {
    "iso:country":"US",
    "sg:address":"501B S Center St",
    "sg:city":"Turlock",
    "sg:classifiers":[
        {
            "category":"Health Services",
            "subcategory":"Dentist",
            "type":"Services"
        }
    ],
    "sg:phone":"+1 800 350 6293",
    "sg:postcode":"95380",
    "sg:province":"CA",
    "sg:tags":[
        "equipment",
        "dental",
        "supply"
    ],
    "wof:name":"Maxdent Dental Supply Co.",
    "wof:placetype":"venue"
},
  "geometry": {"coordinates":[-120.841103,37.491718],"type":"Point"}
}