{
  "type": "Feature",
  "properties": {
    "addr:full":"17737 Gale Ave City Of Industry CA 91748",
    "addr:housenumber":"17737",
    "addr:postcode":"91748",
    "addr:street":"Gale Ave",
    "iso:country":"US",
    "sg:address":"17737 Gale Ave",
    "sg:city":"City Of Industry",
    "sg:classifiers":[
        {
            "category":"Home & Garden",
            "subcategory":"Furniture",
            "type":"Retail Goods"
        }
    ],
    "sg:phone":"+1 626 581 1975",
    "sg:postcode":"91748",
    "sg:province":"CA",
    "wof:name":"Century Home Furnishings",
    "wof:placetype":"venue"
},
  "geometry": {"coordinates":[-117.9165,33.995515],"type":"Point"}
}