{
  "type": "Feature",
  "properties": {
    "addr:full":"4224 Balboa Ave San Diego CA 92117",
    "addr:housenumber":"4224",
    "addr:postcode":"92117",
    "addr:street":"Balboa Ave",
    "iso:country":"US",
    "sg:address":"4224 Balboa Ave",
    "sg:city":"San Diego",
    "sg:classifiers":[
        {
            "category":"Shopping",
            "subcategory":"Books",
            "type":"Retail Goods"
        }
    ],
    "sg:phone":"+1 858 483 4853",
    "sg:postcode":"92117",
    "sg:province":"CA",
    "sg:tags":[
        "comic"
    ],
    "sg:website":"www.comicgalleryonline.com",
    "wof:name":"Comic Gallery",
    "wof:placetype":"venue"
},
  "geometry": {"coordinates":[-117.200256,32.811807],"type":"Point"}
}