{
  "type": "Feature",
  "properties": {
    "addr:full":"2086 Newpark Mall Newark CA 94560",
    "addr:housenumber":"2086",
    "addr:postcode":"94560",
    "addr:street":"Newpark Mall",
    "iso:country":"US",
    "sg:address":"2086 Newpark Mall",
    "sg:city":"Newark",
    "sg:classifiers":[
        {
            "category":"Coffee & Tea",
            "type":"Food & Drink"
        }
    ],
    "sg:menulink":"http://www.allmenus.com/ca/fremont/118689-starbucks-coffee/menu/",
    "sg:phone":"+1 510 794 0975",
    "sg:postcode":"94560",
    "sg:province":"CA",
    "sg:tags":[
        "american"
    ],
    "wof:name":"Starbucks Coffee",
    "wof:placetype":"venue"
},
  "geometry": {"coordinates":[-122.001385,37.528308],"type":"Point"}
}