{
  "type": "Feature",
  "properties": {
    "iso:country":"US",
    "sg:address":"12030 Donner Pass Rd",
    "sg:city":"Truckee",
    "sg:classifiers":[
        {
            "category":"Shopping",
            "subcategory":"Used Merchandise",
            "type":"Retail Goods"
        }
    ],
    "sg:phone":"+1 530 587 4123",
    "sg:postcode":"96161",
    "sg:province":"CA",
    "sg:tags":[
        "shop",
        "thrift"
    ],
    "wof:name":"Thrill Of The Find Thrift",
    "wof:placetype":"venue"
},
  "geometry": {"coordinates":[-120.22221399999999,39.325585],"type":"Point"}
}