{
  "type": "Feature",
  "properties": {
    "addr:full":"13888 Ransom Rd Moorpark CA 93021",
    "addr:housenumber":"13888",
    "addr:postcode":"ca 93021",
    "addr:street":"Ransom Rd",
    "iso:country":"US",
    "sg:address":"13888 Ransom Rd",
    "sg:city":"Moorpark",
    "sg:classifiers":[
        {
            "category":"Retail",
            "subcategory":"Portrait Studio",
            "type":"Services"
        }
    ],
    "sg:phone":"+1 805 529 1240",
    "sg:postcode":"93021",
    "sg:province":"CA",
    "sg:tags":[
        "photographer"
    ],
    "sg:website":"www.bennettphotography.com",
    "wof:name":"Bennett Photography",
    "wof:placetype":"venue"
},
  "geometry": {"coordinates":[-118.868308,34.262084],"type":"Point"}
}