{
  "type": "Feature",
  "properties": {
    "addr:full":"45 E Huntington Dr 45B Arcadia CA 91006",
    "addr:housenumber":"45;45b",
    "addr:postcode":"91006",
    "addr:street":"E Huntington Dr",
    "iso:country":"US",
    "sg:address":"45 E Huntington Dr 45B",
    "sg:city":"Arcadia",
    "sg:classifiers":[
        {
            "category":"Professional",
            "subcategory":"Lawyer & Legal Services",
            "type":"Services"
        }
    ],
    "sg:phone":"+1 626 254 0758",
    "sg:postcode":"91006",
    "sg:province":"CA",
    "sg:tags":[
        "attorney",
        "practice",
        "plan"
    ],
    "wof:name":"Law Office Of Thomas Prince",
    "wof:placetype":"venue"
},
  "geometry": {"coordinates":[-118.029347,34.140068],"type":"Point"}
}