{
  "type": "Feature",
  "properties": {
    "iso:country":"US",
    "sg:address":"3006 Enrique",
    "sg:city":"San Clemente",
    "sg:classifiers":[
        {
            "category":"Professional",
            "subcategory":"Accounting & Tax Preparation",
            "type":"Services"
        }
    ],
    "sg:phone":"+1 949 498 9681",
    "sg:postcode":"92673",
    "sg:province":"CA",
    "sg:tags":[
        "return",
        "filing"
    ],
    "wof:name":"Yengo's Accounting",
    "wof:placetype":"venue"
},
  "geometry": {"coordinates":[-117.634772,33.473377],"type":"Point"}
}