{
  "type": "Feature",
  "properties": {
    "iso:country":"US",
    "sg:address":"7 Hangar Way",
    "sg:city":"Watsonville",
    "sg:classifiers":[
        {
            "category":"Wholesale",
            "subcategory":"Durable Goods & Equipment",
            "type":"Manufacturing & Wholesale Goods"
        }
    ],
    "sg:phone":"+1 831 724 5738",
    "sg:postcode":"95076",
    "sg:province":"CA",
    "sg:tags":[
        "environmental",
        "product"
    ],
    "sg:website":"www.vena.com",
    "wof:name":"Vena Engineering Corp",
    "wof:placetype":"venue"
},
  "geometry": {"coordinates":[-121.790897,36.928716],"type":"Point"}
}