{
  "type": "Feature",
  "properties": {
    "iso:country":"US",
    "sg:address":"1909 Terrace Dr",
    "sg:city":"Antioch",
    "sg:classifiers":[
        {
            "category":"Shopping",
            "subcategory":"Hobbies, Toys, & Games",
            "type":"Retail Goods"
        }
    ],
    "sg:phone":"+1 925 754 5927",
    "sg:postcode":"94509",
    "sg:province":"CA",
    "sg:tags":[
        "craft"
    ],
    "wof:name":"Four Season's Country Crafts",
    "wof:placetype":"venue"
},
  "geometry": {"coordinates":[-121.791736,38.003102],"type":"Point"}
}