{
  "type": "Feature",
  "properties": {
    "addr:full":"339 Fontaine Dr Danville CA 94506",
    "addr:housenumber":"339",
    "addr:postcode":"94506",
    "addr:street":"Fontaine Dr",
    "iso:country":"US",
    "sg:address":"339 Fontaine Dr",
    "sg:city":"Danville",
    "sg:classifiers":[
        {
            "category":"Professional",
            "type":"Services"
        }
    ],
    "sg:phone":"+1 925 736 2900",
    "sg:postcode":"94506",
    "sg:province":"CA",
    "sg:website":"www.integra-sales.com",
    "wof:name":"Byedesign Solutions",
    "wof:placetype":"venue"
},
  "geometry": {"coordinates":[-121.930609,37.801139],"type":"Point"}
}