{
  "type": "Feature",
  "properties": {
    "addr:full":"1193 Carolyn Dr Santa Clara CA 95050",
    "addr:housenumber":"1193",
    "addr:postcode":"95050",
    "addr:street":"Carolyn Dr",
    "iso:country":"US",
    "sg:address":"1193 Carolyn Dr",
    "sg:city":"Santa Clara",
    "sg:classifiers":[
        {
            "category":"Arts & Performance",
            "subcategory":"Theater",
            "type":"Entertainment"
        }
    ],
    "sg:phone":"+1 408 246 5744",
    "sg:postcode":"95050",
    "sg:province":"CA",
    "sg:tags":[
        "live",
        "music"
    ],
    "wof:name":"Good Time Mobile Music",
    "wof:placetype":"venue"
},
  "geometry": {"coordinates":[-121.96674,37.347781],"type":"Point"}
}