{
  "type": "Feature",
  "properties": {
    "iso:country":"US",
    "sg:address":"16923 N Friant Rd",
    "sg:city":"Friant",
    "sg:classifiers":[
        {
            "category":"Shopping",
            "type":"Retail Goods"
        }
    ],
    "sg:phone":"+1 559 822 2315",
    "sg:postcode":"93626",
    "sg:province":"CA",
    "sg:tags":[
        "wedding",
        "supply"
    ],
    "wof:name":"Cliff Finch's Topiary Zoo",
    "wof:placetype":"venue"
},
  "geometry": {"coordinates":[-119.71786400000001,36.981031],"type":"Point"}
}