{
  "type": "Feature",
  "properties": {
    "addr:full":"857 Cleveland Street Los Angeles CA 90012",
    "addr:housenumber":"857",
    "addr:postcode":"90012",
    "addr:street":"Cleveland Street",
    "iso:country":"US",
    "sg:address":"857 Cleveland Street",
    "sg:city":"Los Angeles",
    "sg:classifiers":[
        {
            "category":"Health Services",
            "subcategory":"Doctor",
            "type":"Services"
        }
    ],
    "sg:phone":"+1 213 620 1781",
    "sg:postcode":"90012",
    "sg:province":"CA",
    "wof:name":"Ng Chung W MD",
    "wof:placetype":"venue"
},
  "geometry": {"coordinates":[-118.240983,34.064646],"type":"Point"}
}