{
  "type": "Feature",
  "properties": {
    "addr:full":"2240 S Elm Ave Fresno CA 93706",
    "addr:housenumber":"2240",
    "addr:postcode":"93706",
    "addr:street":"S Elm Ave",
    "iso:country":"US",
    "sg:address":"2240 S Elm Ave",
    "sg:city":"Fresno",
    "sg:classifiers":[
        {
            "category":"Food & Beverages",
            "subcategory":"Candy",
            "type":"Retail Goods"
        }
    ],
    "sg:phone":"+1 559 264 2399",
    "sg:postcode":"93706",
    "sg:province":"CA",
    "sg:tags":[
        "confectionery"
    ],
    "wof:name":"Sweet Candy Delights",
    "wof:placetype":"venue"
},
  "geometry": {"coordinates":[-119.790789,36.718549],"type":"Point"}
}