{
  "type": "Feature",
  "properties": {
    "addr:full":"200 Tucker Rd Watsonville CA 95076",
    "addr:housenumber":"200",
    "addr:postcode":"95076",
    "addr:street":"Tucker Rd",
    "iso:country":"US",
    "sg:address":"200 Tucker Rd",
    "sg:city":"Watsonville",
    "sg:classifiers":[
        {
            "category":"Building & Trades",
            "subcategory":"Construction",
            "type":"Services"
        }
    ],
    "sg:phone":"+1 831 722 3433",
    "sg:postcode":"95076",
    "sg:province":"CA",
    "sg:tags":[
        "excavation",
        "paving",
        "contractor"
    ],
    "wof:name":"Larry Clark's Paving & Grading",
    "wof:placetype":"venue"
},
  "geometry": {"coordinates":[-121.70168700000001,36.825281],"type":"Point"}
}