{
  "type": "Feature",
  "properties": {
    "addr:full":"289 S Robertson Blvd Beverly Hills CA 90211",
    "addr:housenumber":"289",
    "addr:postcode":"90211",
    "addr:street":"S Robertson Blvd",
    "iso:country":"US",
    "sg:address":"289 S Robertson Blvd",
    "sg:city":"Beverly Hills",
    "sg:classifiers":[
        {
            "category":"Professional",
            "subcategory":"Lawyer & Legal Services",
            "type":"Services"
        }
    ],
    "sg:phone":"+1 310 358 0906",
    "sg:postcode":"90211",
    "sg:province":"CA",
    "sg:tags":[
        "attorney"
    ],
    "wof:name":"Marilyn Mora Law Office",
    "wof:placetype":"venue"
},
  "geometry": {"coordinates":[-118.38365,34.064775],"type":"Point"}
}