{
  "type": "Feature",
  "properties": {
    "iso:country":"US",
    "sg:address":"917 Manhattan Beach Blvd",
    "sg:city":"Manhattan Beach",
    "sg:classifiers":[
        {
            "category":"Professional",
            "type":"Services"
        }
    ],
    "sg:phone":"+1 310 545 9778",
    "sg:postcode":"90266",
    "sg:province":"CA",
    "wof:name":"Marilee Dolan",
    "wof:placetype":"venue"
},
  "geometry": {"coordinates":[-118.399943,33.887456],"type":"Point"}
}