{
  "type": "Feature",
  "properties": {
    "iso:country":"US",
    "sg:address":"220 N Lake Ave",
    "sg:city":"Pasadena",
    "sg:classifiers":[
        {
            "category":"Restaurant",
            "type":"Food & Drink"
        }
    ],
    "sg:phone":"+1 626 795 6816",
    "sg:postcode":"91101",
    "sg:province":"CA",
    "sg:tags":[
        "pizza"
    ],
    "wof:name":"Bono Corso's Italian Rstrnt",
    "wof:placetype":"venue"
},
  "geometry": {"coordinates":[-118.132324,34.150205],"type":"Point"}
}