{
  "type": "Feature",
  "properties": {
    "addr:full":"5634 Lightle Ln Montague CA 96094",
    "addr:housenumber":"5634",
    "addr:postcode":"96094",
    "addr:street":"Lightle Ln",
    "iso:country":"US",
    "sg:address":"5634 Lightle Ln",
    "sg:city":"Montague",
    "sg:classifiers":[
        {
            "category":"Farming",
            "subcategory":"Livestock Farm",
            "type":"Manufacturing & Wholesale Goods"
        }
    ],
    "sg:phone":"+1 530 459 1024",
    "sg:postcode":"96094",
    "sg:province":"CA",
    "sg:tags":[
        "animal",
        "general"
    ],
    "wof:name":"J C Lightle Ranches",
    "wof:placetype":"venue"
},
  "geometry": {"coordinates":[-122.531125,41.753022],"type":"Point"}
}