{
  "type": "Feature",
  "properties": {
    "iso:country":"US",
    "sg:address":"1845 W Gage Ave",
    "sg:city":"Los Angeles",
    "sg:classifiers":[
        {
            "category":"Autos & Motor Vehicles",
            "subcategory":"Automobile Sales",
            "type":"Retail Goods"
        }
    ],
    "sg:phone":"+1 323 752 3946",
    "sg:postcode":"90047",
    "sg:province":"CA",
    "sg:tags":[
        "automotive"
    ],
    "wof:name":"M & R Auto Body Collition",
    "wof:placetype":"venue"
},
  "geometry": {"coordinates":[-118.310372,33.981886],"type":"Point"}
}