{
  "type": "Feature",
  "properties": {
    "iso:country":"US",
    "sg:address":"105 Ascot Dr",
    "sg:city":"Roseville",
    "sg:classifiers":[
        {
            "category":"Personal",
            "subcategory":"Beauty Salon",
            "type":"Services"
        }
    ],
    "sg:phone":"+1 916 782 7991",
    "sg:postcode":"95661",
    "sg:province":"CA",
    "sg:tags":[
        "treatment",
        "skin"
    ],
    "wof:name":"Ellen Bennett Esthetics",
    "wof:placetype":"venue"
},
  "geometry": {"coordinates":[-121.268491,38.743572],"type":"Point"}
}