{
  "type": "Feature",
  "properties": {
    "iso:country":"US",
    "sg:address":"2806 Aurora Ave",
    "sg:city":"Sacramento",
    "sg:classifiers":[
        {
            "category":"Education",
            "subcategory":"Music School",
            "type":"Public Place"
        },
        {
            "category":"Arts & Performance",
            "subcategory":"Music",
            "type":"Entertainment"
        }
    ],
    "sg:phone":"+1 916 929 8810",
    "sg:postcode":"95821",
    "sg:province":"CA",
    "sg:tags":[
        "musician",
        "instruction-instrumental"
    ],
    "wof:name":"Mike Rogers Presents",
    "wof:placetype":"venue"
},
  "geometry": {"coordinates":[-121.418656,38.615582],"type":"Point"}
}