{
  "type": "Feature",
  "properties": {
    "addr:full":"3436 Dimond Ave Oakland CA 94602",
    "addr:housenumber":"3436",
    "addr:postcode":"94602",
    "addr:street":"Dimond Ave",
    "iso:country":"US",
    "sg:address":"3436 Dimond Ave",
    "sg:city":"Oakland",
    "sg:classifiers":[
        {
            "category":"Manufacturing",
            "subcategory":"Glass & Minerals",
            "type":"Manufacturing & Wholesale Goods"
        }
    ],
    "sg:phone":"+1 800 701 8122",
    "sg:postcode":"94602",
    "sg:province":"CA",
    "sg:tags":[
        "plate",
        "window",
        "glass-auto"
    ],
    "wof:name":"C T Glass On Wheels",
    "wof:placetype":"venue"
},
  "geometry": {"coordinates":[-122.217569,37.79984],"type":"Point"}
}