{
  "type": "Feature",
  "properties": {
    "addr:full":"264 N Palm Ave Fresno CA 93701",
    "addr:housenumber":"264",
    "addr:postcode":"93701",
    "addr:street":"N Palm Ave",
    "iso:country":"US",
    "sg:address":"264 N Palm Ave",
    "sg:city":"Fresno",
    "sg:classifiers":[
        {
            "category":"Restaurant",
            "type":"Food & Drink"
        },
        {
            "category":"Ice Cream",
            "type":"Food & Drink"
        }
    ],
    "sg:phone":"+1 559 499 6300",
    "sg:postcode":"93701",
    "sg:province":"CA",
    "sg:tags":[
        "frozen",
        "dessert"
    ],
    "sg:website":"http://www.haagendazs.com",
    "wof:name":"Haagen-Dazs",
    "wof:placetype":"venue"
},
  "geometry": {"coordinates":[-119.80825299999999,36.747332],"type":"Point"}
}