{
  "type": "Feature",
  "properties": {
    "addr:full":"1441 W Pacific Coast Hwy Long Beach CA 90810",
    "addr:housenumber":"1441",
    "addr:postcode":"90810",
    "addr:street":"W Pacific Coast Hwy",
    "iso:country":"US",
    "sg:address":"1441 W Pacific Coast Hwy",
    "sg:city":"Long Beach",
    "sg:classifiers":[
        {
            "category":"Travel",
            "subcategory":"Hotels & Motels",
            "type":"Entertainment"
        }
    ],
    "sg:phone":"+1 562 436 6669",
    "sg:postcode":"90810",
    "sg:province":"CA",
    "wof:name":"Highland Motel",
    "wof:placetype":"venue"
},
  "geometry": {"coordinates":[-118.210999,33.789799],"type":"Point"}
}