{
  "type": "Feature",
  "properties": {
    "addr:full":"59 Fortune Dr Irvine CA 92618",
    "addr:housenumber":"59",
    "addr:postcode":"92618",
    "addr:street":"Fortune Dr",
    "iso:country":"US",
    "sg:address":"59 Fortune Dr",
    "sg:city":"Irvine",
    "sg:classifiers":[
        {
            "category":"Restaurant",
            "type":"Food & Drink"
        }
    ],
    "sg:phone":"+1 949 453 9500",
    "sg:postcode":"92618",
    "sg:province":"CA",
    "sg:tags":[
        "japanese"
    ],
    "wof:name":"Izakaya Wasa",
    "wof:placetype":"venue"
},
  "geometry": {"coordinates":[-117.746934,33.651746],"type":"Point"}
}