{
  "type": "Feature",
  "properties": {
    "addr:full":"1401 Burlingame Ave Burlingame CA 94010",
    "addr:housenumber":"1401",
    "addr:postcode":"94010",
    "addr:street":"Burlingame Ave",
    "iso:country":"US",
    "sg:address":"1401 Burlingame Ave",
    "sg:city":"Burlingame",
    "sg:classifiers":[
        {
            "category":"Restaurant",
            "type":"Food & Drink"
        }
    ],
    "sg:phone":"+1 650 344 1462",
    "sg:postcode":"94010",
    "sg:province":"CA",
    "wof:name":"Towle's Cafe",
    "wof:placetype":"venue"
},
  "geometry": {"coordinates":[-122.35005700000001,37.576397],"type":"Point"}
}