{
  "type": "Feature",
  "properties": {
    "addr:full":"1840 Winona Blvd Los Angeles CA 90027",
    "addr:housenumber":"1840",
    "addr:postcode":"90027",
    "addr:street":"Winona Blvd",
    "iso:country":"US",
    "sg:address":"1840 Winona Blvd",
    "sg:city":"Los Angeles",
    "sg:classifiers":[
        {
            "category":"Arts & Performance",
            "subcategory":"Theater",
            "type":"Entertainment"
        }
    ],
    "sg:phone":"+1 323 644 2635",
    "sg:postcode":"90027",
    "sg:province":"CA",
    "sg:tags":[
        "bureau"
    ],
    "wof:name":"Joe Bananas",
    "wof:placetype":"venue"
},
  "geometry": {"coordinates":[-118.301939,34.102822],"type":"Point"}
}