{
  "type": "Feature",
  "properties": {
    "addr:full":"840 Hinckley Rd Ste 220 Burlingame CA 94010",
    "addr:housenumber":"840",
    "addr:postcode":"94010",
    "addr:street":"Hinckley Rd Ste 220",
    "iso:country":"US",
    "sg:address":"840 Hinckley Rd Ste 220",
    "sg:city":"Burlingame",
    "sg:classifiers":[
        {
            "category":"Professional",
            "subcategory":"Lawyer & Legal Services",
            "type":"Services"
        }
    ],
    "sg:phone":"+1 650 692 4800",
    "sg:postcode":"94010",
    "sg:province":"CA",
    "wof:name":"Brose Law Offices",
    "wof:placetype":"venue"
},
  "geometry": {"coordinates":[-122.368711,37.598256],"type":"Point"}
}