{
  "type": "Feature",
  "properties": {
    "addr:full":"23818 Crown Hill Ln Escondido CA 92027",
    "addr:housenumber":"23818",
    "addr:postcode":"92027",
    "addr:street":"Crown Hill Ln",
    "iso:country":"US",
    "sg:address":"23818 Crown Hill Ln",
    "sg:city":"Escondido",
    "sg:classifiers":[
        {
            "category":"Retail",
            "subcategory":"Repair Shop",
            "type":"Services"
        }
    ],
    "sg:phone":"+1 760 751 1840",
    "sg:postcode":"92027",
    "sg:province":"CA",
    "sg:tags":[
        "equipment",
        "electronic",
        "supply"
    ],
    "wof:name":"Ebersole Electronics",
    "wof:placetype":"venue"
},
  "geometry": {"coordinates":[-116.956137,33.154737],"type":"Point"}
}