{
  "type": "Feature",
  "properties": {
    "iso:country":"US",
    "sg:address":"428 C St",
    "sg:city":"Eureka",
    "sg:classifiers":[
        {
            "category":"Social Services",
            "type":"Services"
        }
    ],
    "sg:phone":"+1 707 445 4871",
    "sg:postcode":"95501",
    "sg:province":"CA",
    "sg:tags":[
        "organization",
        "welfare"
    ],
    "wof:name":"Big Brothers & Big Sisters",
    "wof:placetype":"venue"
},
  "geometry": {"coordinates":[-124.169373,40.802062],"type":"Point"}
}