{
  "type": "Feature",
  "properties": {
    "addr:full":"125 Grobric Ct Fairfield CA 94534",
    "addr:housenumber":"125",
    "addr:postcode":"94534",
    "addr:street":"Grobric Ct",
    "iso:country":"US",
    "sg:address":"125 Grobric Ct",
    "sg:city":"Fairfield",
    "sg:classifiers":[
        {
            "category":"Building & Trades",
            "subcategory":"Electrical",
            "type":"Services"
        }
    ],
    "sg:phone":"+1 707 864 3652",
    "sg:postcode":"94534",
    "sg:province":"CA",
    "sg:tags":[
        "electrical",
        "electric",
        "contractor"
    ],
    "wof:name":"Western Electric",
    "wof:placetype":"venue"
},
  "geometry": {"coordinates":[-122.134737,38.21636],"type":"Point"}
}