{
  "type": "Feature",
  "properties": {
    "iso:country":"US",
    "sg:address":"14894 Rockridge Ln",
    "sg:city":"Fontana",
    "sg:classifiers":[
        {
            "category":"Shopping",
            "type":"Retail Goods"
        }
    ],
    "sg:phone":"+1 909 822 1283",
    "sg:postcode":"92337",
    "sg:province":"CA",
    "sg:tags":[
        "cosmetic",
        "perfume"
    ],
    "wof:name":"Jafra Cosmetics-Janiece",
    "wof:placetype":"venue"
},
  "geometry": {"coordinates":[-117.480357,34.036851],"type":"Point"}
}