{
  "type": "Feature",
  "properties": {
    "iso:country":"US",
    "sg:address":"2210 Sunset Blvd",
    "sg:city":"Rocklin",
    "sg:classifiers":[
        {
            "category":"Restaurant",
            "type":"Food & Drink"
        }
    ],
    "sg:menulink":"http://www.allmenus.com/ca/loomis-basin-folsom-lake/239996-panda-express/menu/",
    "sg:phone":"+1 916 789 2268",
    "sg:postcode":"95765",
    "sg:province":"CA",
    "sg:tags":[
        "asian",
        "chinese"
    ],
    "wof:name":"Panda Express",
    "wof:placetype":"venue"
},
  "geometry": {"coordinates":[-121.27203,38.80362],"type":"Point"}
}