{
  "type": "Feature",
  "properties": {
    "addr:full":"9663 Santa Monica Blvd Ste 494 Beverly Hills CA 90210",
    "addr:housenumber":"9663",
    "addr:postcode":"90210",
    "addr:street":"Santa Monica Blvd Ste 494;Hills Ca",
    "iso:country":"US",
    "sg:address":"9663 Santa Monica Blvd Ste 494",
    "sg:city":"Beverly Hills",
    "sg:classifiers":[
        {
            "category":"Personal",
            "type":"Services"
        }
    ],
    "sg:phone":"+1 310 713 6704",
    "sg:postcode":"90210",
    "sg:province":"CA",
    "sg:tags":[
        "home"
    ],
    "sg:website":"www.purveyorsoftime.com",
    "wof:name":"Purveyors of Time",
    "wof:placetype":"venue"
},
  "geometry": {"coordinates":[-118.406999,34.069429],"type":"Point"}
}