{
  "type": "Feature",
  "properties": {
    "iso:country":"US",
    "sg:address":"1347 Loma St",
    "sg:city":"Long Beach",
    "sg:classifiers":[
        {
            "category":"Sports & Exercise",
            "subcategory":"Gym",
            "type":"Entertainment"
        }
    ],
    "sg:phone":"+1 562 688 1716",
    "sg:postcode":"90804",
    "sg:province":"CA",
    "sg:website":"www.powerhousefit.com/",
    "wof:name":"Powerhouse Fitness",
    "wof:placetype":"venue"
},
  "geometry": {"coordinates":[-118.150249,33.783651],"type":"Point"}
}