{
  "type": "Feature",
  "properties": {
    "iso:country":"US",
    "sg:address":"838 Pacific Ave",
    "sg:city":"San Francisco",
    "sg:classifiers":[
        {
            "category":"Real Estate",
            "subcategory":"Real Estate Agent",
            "type":"Services"
        }
    ],
    "sg:phone":"+1 415 362 2065",
    "sg:postcode":"94133",
    "sg:province":"CA",
    "sg:tags":[
        "authorities",
        "housing"
    ],
    "wof:name":"S F Housing Authority Site Ofc",
    "wof:placetype":"venue"
},
  "geometry": {"coordinates":[-122.409088,37.796701],"type":"Point"}
}