{
  "type": "Feature",
  "properties": {
    "iso:country":"US",
    "sg:address":"6252 Alamo Ave",
    "sg:city":"Bell",
    "sg:classifiers":[
        {
            "category":"Freight",
            "type":"Transportation"
        }
    ],
    "sg:phone":"+1 323 560 2865",
    "sg:postcode":"90201",
    "sg:province":"CA",
    "sg:tags":[
        "operator",
        "local",
        "trucking"
    ],
    "wof:name":"Rogelios Trucking",
    "wof:placetype":"venue"
},
  "geometry": {"coordinates":[-118.175087,33.979953],"type":"Point"}
}