{
  "type": "Feature",
  "properties": {
    "iso:country":"US",
    "sg:address":"6111 County Oak Rd",
    "sg:city":"Woodland Hills",
    "sg:classifiers":[
        {
            "category":"Professional",
            "type":"Services"
        }
    ],
    "sg:phone":"+1 818 884 8326",
    "sg:postcode":"91367",
    "sg:province":"CA",
    "wof:name":"Advanced Info Systems LLC",
    "wof:placetype":"venue"
},
  "geometry": {"coordinates":[-118.666112,34.182615],"type":"Point"}
}