{
  "type": "Feature",
  "properties": {
    "addr:full":"1055 Reno Ave Modesto CA 95351",
    "addr:housenumber":"1055",
    "addr:postcode":"ca 95351",
    "addr:street":"Reno Ave",
    "iso:country":"US",
    "sg:address":"1055 Reno Ave",
    "sg:city":"Modesto",
    "sg:classifiers":[
        {
            "category":"Building & Trades",
            "subcategory":"Construction",
            "type":"Services"
        }
    ],
    "sg:phone":"+1 209 524 2739",
    "sg:postcode":"95351",
    "sg:province":"CA",
    "sg:tags":[
        "painter"
    ],
    "sg:website":"www.apexpainting.com",
    "wof:name":"Apex Painting Inc",
    "wof:placetype":"venue"
},
  "geometry": {"coordinates":[-121.02932199999999,37.649423],"type":"Point"}
}