{
  "type": "Feature",
  "properties": {
    "iso:country":"US",
    "sg:address":"6101 Hillegass Ave",
    "sg:city":"Oakland",
    "sg:classifiers":[
        {
            "category":"Education",
            "subcategory":"School",
            "type":"Public Place"
        }
    ],
    "sg:phone":"+1 510 601 9243",
    "sg:postcode":"94618",
    "sg:province":"CA",
    "wof:name":"School Crossings",
    "wof:placetype":"venue"
},
  "geometry": {"coordinates":[-122.254474,37.849099],"type":"Point"}
}