{
  "type": "Feature",
  "properties": {
    "iso:country":"US",
    "sg:address":"530 Pollasky Ave",
    "sg:city":"Clovis",
    "sg:classifiers":[
        {
            "category":"Restaurant",
            "type":"Food & Drink"
        }
    ],
    "sg:phone":"+1 559 298 7139",
    "sg:postcode":"93612",
    "sg:province":"CA",
    "sg:tags":[
        "italian"
    ],
    "sg:website":"http://www.giovanniscaffe.com",
    "wof:name":"Giovannis Caffe",
    "wof:placetype":"venue"
},
  "geometry": {"coordinates":[-119.70200800000001,36.823667],"type":"Point"}
}