{
  "type": "Feature",
  "properties": {
    "addr:full":"18745 State St Corona CA 92881",
    "addr:housenumber":"18745",
    "addr:postcode":"92881",
    "addr:street":"State St",
    "iso:country":"US",
    "sg:address":"18745 State St",
    "sg:city":"Corona",
    "sg:classifiers":[
        {
            "category":"Real Estate",
            "subcategory":"Real Estate Agent",
            "type":"Services"
        }
    ],
    "sg:phone":"+1 951 272 9323",
    "sg:postcode":"92881",
    "sg:province":"CA",
    "wof:name":"Bruce Mattis",
    "wof:placetype":"venue"
},
  "geometry": {"coordinates":[-117.53192799999999,33.849304],"type":"Point"}
}