{
  "type": "Feature",
  "properties": {
    "iso:country":"US",
    "sg:address":"44530 San Pablo Ave",
    "sg:city":"Palm Desert",
    "sg:classifiers":[
        {
            "category":"Health Services",
            "subcategory":"Chiropractor",
            "type":"Services"
        }
    ],
    "sg:phone":"+1 760 340 1264",
    "sg:postcode":"92260",
    "sg:province":"CA",
    "wof:name":"Hathaway William DC",
    "wof:placetype":"venue"
},
  "geometry": {"coordinates":[-116.382171,33.725016],"type":"Point"}
}