{
  "type": "Feature",
  "properties": {
    "addr:full":"1860 Mowry Ave Fremont CA 94538",
    "addr:housenumber":"1860",
    "addr:postcode":"94538",
    "addr:street":"Mowry Ave",
    "iso:country":"US",
    "sg:address":"1860 Mowry Ave",
    "sg:city":"Fremont",
    "sg:classifiers":[
        {
            "category":"Health Services",
            "subcategory":"Medical Lab",
            "type":"Services"
        }
    ],
    "sg:phone":"+1 510 742 9101",
    "sg:postcode":"94538",
    "sg:province":"CA",
    "sg:tags":[
        "laboratory"
    ],
    "wof:name":"Unilab Corp",
    "wof:placetype":"venue"
},
  "geometry": {"coordinates":[-121.980029,37.558856],"type":"Point"}
}