{
  "type": "Feature",
  "properties": {
    "iso:country":"US",
    "sg:address":"790 Beaumont Ave",
    "sg:city":"Beaumont",
    "sg:classifiers":[
        {
            "category":"Cinema",
            "subcategory":"Movie Rental",
            "type":"Entertainment"
        }
    ],
    "sg:phone":"+1 951 845 8777",
    "sg:postcode":"92223",
    "sg:province":"CA",
    "sg:tags":[
        "leasing",
        "video",
        "disc",
        "tape"
    ],
    "wof:name":"Good Hart's",
    "wof:placetype":"venue"
},
  "geometry": {"coordinates":[-116.977091,33.931059],"type":"Point"}
}