{
  "type": "Feature",
  "properties": {
    "addr:full":"4657 Cll Mar de Armonia San Diego CA 92130",
    "addr:housenumber":"4657",
    "addr:postcode":"92130",
    "addr:street":"Cll Mar De Armonia",
    "iso:country":"US",
    "sg:address":"4657 Cll Mar de Armonia",
    "sg:city":"San Diego",
    "sg:classifiers":[
        {
            "category":"Professional",
            "subcategory":"Computer Services",
            "type":"Services"
        }
    ],
    "sg:phone":"+1 858 523 0829",
    "sg:postcode":"92130",
    "sg:province":"CA",
    "sg:tags":[
        "website",
        "design"
    ],
    "wof:name":"Amberdot LLC",
    "wof:placetype":"venue"
},
  "geometry": {"coordinates":[-117.214405,32.923275],"type":"Point"}
}