{
  "type": "Feature",
  "properties": {
    "addr:full":"705 Lincoln Ave Napa CA 94558",
    "addr:housenumber":"705",
    "addr:postcode":"94558",
    "addr:street":"Lincoln Ave",
    "iso:country":"US",
    "sg:address":"705 Lincoln Ave",
    "sg:city":"Napa",
    "sg:classifiers":[
        {
            "category":"Cinema",
            "subcategory":"Movie Rental",
            "type":"Entertainment"
        }
    ],
    "sg:phone":"+1 707 258 2850",
    "sg:postcode":"94558",
    "sg:province":"CA",
    "sg:tags":[
        "leasing",
        "video",
        "disc",
        "tape"
    ],
    "sg:website":"www.hollywoodvideo.com",
    "wof:name":"Hollywood Video",
    "wof:placetype":"venue"
},
  "geometry": {"coordinates":[-122.28597499999999,38.31006],"type":"Point"}
}