{
  "type": "Feature",
  "properties": {
    "iso:country":"US",
    "sg:address":"1039 N Highland Ave",
    "sg:city":"Los Angeles",
    "sg:classifiers":[
        {
            "category":"Professional",
            "type":"Services"
        }
    ],
    "sg:phone":"+1 323 467 0768",
    "sg:postcode":"90038",
    "sg:province":"CA",
    "sg:tags":[
        "editorial"
    ],
    "sg:website":"www.tapeeffects.com",
    "wof:name":"Tape Effects Inc",
    "wof:placetype":"venue"
},
  "geometry": {"coordinates":[-118.33867,34.09001],"type":"Point"}
}