{
  "type": "Feature",
  "properties": {
    "addr:full":"27 Trumbull Ct Novato CA 94947",
    "addr:housenumber":"27",
    "addr:postcode":"94947",
    "addr:street":"Trumbull Ct",
    "iso:country":"US",
    "sg:address":"27 Trumbull Ct",
    "sg:city":"Novato",
    "sg:classifiers":[
        {
            "category":"Professional",
            "subcategory":"Management & Consulting",
            "type":"Services"
        }
    ],
    "sg:phone":"+1 415 898 8796",
    "sg:postcode":"94947",
    "sg:province":"CA",
    "sg:tags":[
        "conference",
        "consultant",
        "meeting"
    ],
    "wof:name":"Marin Planning Co",
    "wof:placetype":"venue"
},
  "geometry": {"coordinates":[-122.60229099999999,38.104771],"type":"Point"}
}