{
  "type": "Feature",
  "properties": {
    "addr:full":"735 Kearney St El Cerrito CA 94530",
    "addr:housenumber":"735",
    "addr:postcode":"94530",
    "addr:street":"Kearney St",
    "iso:country":"US",
    "sg:address":"735 Kearney St",
    "sg:city":"El Cerrito",
    "sg:classifiers":[
        {
            "category":"Restaurant",
            "type":"Food & Drink"
        }
    ],
    "sg:postcode":"94530",
    "sg:province":"CA",
    "sg:tags":[
        "flavor",
        "local"
    ],
    "wof:name":"My House",
    "wof:placetype":"venue"
},
  "geometry": {"coordinates":[-122.30453799999999,37.907004],"type":"Point"}
}