{
  "type": "Feature",
  "properties": {
    "iso:country":"US",
    "sg:address":"3941 J St Ste 460",
    "sg:city":"Sacramento",
    "sg:classifiers":[
        {
            "category":"Health Services",
            "subcategory":"Clinic",
            "type":"Services"
        }
    ],
    "sg:phone":"+1 916 733 6940",
    "sg:postcode":"95819",
    "sg:province":"CA",
    "sg:tags":[
        "outpatient"
    ],
    "wof:name":"Sacramento Midtown Endoscopy Center",
    "wof:placetype":"venue"
},
  "geometry": {"coordinates":[-121.453853,38.569745],"type":"Point"}
}