{
  "type": "Feature",
  "properties": {
    "addr:full":"1405 Maple Ave Santa Rosa CA 95404",
    "addr:housenumber":"1405",
    "addr:postcode":"95404",
    "addr:street":"Maple Ave",
    "iso:country":"US",
    "sg:address":"1405 Maple Ave",
    "sg:city":"Santa Rosa",
    "sg:classifiers":[
        {
            "category":"Banks & Credit Unions",
            "subcategory":"Bank",
            "type":"Services"
        }
    ],
    "sg:phone":"+1 707 527 5950",
    "sg:postcode":"95404",
    "sg:province":"CA",
    "sg:tags":[
        "money",
        "order"
    ],
    "wof:name":"LA Joyita",
    "wof:placetype":"venue"
},
  "geometry": {"coordinates":[-122.696652,38.434458],"type":"Point"}
}