{
  "type": "Feature",
  "properties": {
    "iso:country":"US",
    "sg:address":"33 S Palm St",
    "sg:city":"Ventura",
    "sg:classifiers":[
        {
            "category":"Home & Garden",
            "subcategory":"Furniture",
            "type":"Retail Goods"
        }
    ],
    "sg:phone":"+1 805 641 9909",
    "sg:postcode":"93001",
    "sg:province":"CA",
    "wof:name":"Oasis Garden & Patio",
    "wof:placetype":"venue"
},
  "geometry": {"coordinates":[-119.296256,34.279937],"type":"Point"}
}