{
  "type": "Feature",
  "properties": {
    "iso:country":"US",
    "sg:address":"17450 Main St",
    "sg:city":"Hesperia",
    "sg:classifiers":[
        {
            "category":"Health Services",
            "subcategory":"Clinic",
            "type":"Services"
        }
    ],
    "sg:phone":"+1 760 244 1737",
    "sg:postcode":"92345",
    "sg:province":"CA",
    "sg:tags":[
        "medical",
        "group"
    ],
    "wof:name":"Desert Valley Medical Group",
    "wof:placetype":"venue"
},
  "geometry": {"coordinates":[-117.282124,34.418751],"type":"Point"}
}