{
  "type": "Feature",
  "properties": {
    "iso:country":"US",
    "sg:address":"1545 River Park Dr Ste 375",
    "sg:city":"Sacramento",
    "sg:classifiers":[
        {
            "category":"Professional",
            "subcategory":"Accounting & Tax Preparation",
            "type":"Services"
        }
    ],
    "sg:phone":"+1 916 929 1006",
    "sg:postcode":"95815",
    "sg:province":"CA",
    "sg:tags":[
        "accountant"
    ],
    "wof:name":"Caniglia Mry Tte Prpp Bggs & Sgmto An Accntncy Crp",
    "wof:placetype":"venue"
},
  "geometry": {"coordinates":[-121.43800400000001,38.599098],"type":"Point"}
}