{
  "type": "Feature",
  "properties": {
    "addr:full":"4226 Indian Peak Rd Mariposa CA 95338",
    "addr:housenumber":"4226",
    "addr:postcode":"95338",
    "addr:street":"Indian Peak Rd",
    "iso:country":"US",
    "sg:address":"4226 Indian Peak Rd",
    "sg:city":"Mariposa",
    "sg:classifiers":[
        {
            "category":"Building & Trades",
            "subcategory":"Landscaping Services",
            "type":"Services"
        }
    ],
    "sg:phone":"+1 209 966 7340",
    "sg:postcode":"95338",
    "sg:province":"CA",
    "sg:tags":[
        "sod",
        "sodding"
    ],
    "wof:name":"Christie Brothers Enterprises",
    "wof:placetype":"venue"
},
  "geometry": {"coordinates":[-119.865577,37.41632],"type":"Point"}
}