{
  "type": "Feature",
  "properties": {
    "iso:country":"US",
    "sg:address":"3411 E 12th St",
    "sg:city":"Oakland",
    "sg:classifiers":[
        {
            "category":"Shopping",
            "subcategory":"Florist",
            "type":"Retail Goods"
        }
    ],
    "sg:phone":"+1 510 533 3344",
    "sg:postcode":"94601",
    "sg:province":"CA",
    "wof:name":"Soap Garden",
    "wof:placetype":"venue"
},
  "geometry": {"coordinates":[-122.223257,37.775595],"type":"Point"}
}