{
  "type": "Feature",
  "properties": {
    "iso:country":"US",
    "sg:address":"909 N Main St",
    "sg:city":"Santa Ana",
    "sg:classifiers":[
        {
            "category":"Social Services",
            "type":"Services"
        }
    ],
    "sg:phone":"+1 714 569 2000",
    "sg:postcode":"92701",
    "sg:province":"CA",
    "sg:tags":[
        "probation"
    ],
    "wof:name":"County Probation",
    "wof:placetype":"venue"
},
  "geometry": {"coordinates":[-117.867536,33.753329],"type":"Point"}
}