{
  "type": "Feature",
  "properties": {
    "iso:country":"US",
    "sg:address":"2533 W McKinley Ave",
    "sg:city":"Fresno",
    "sg:classifiers":[
        {
            "category":"Real Estate",
            "subcategory":"Real Estate Operator",
            "type":"Services"
        }
    ],
    "sg:phone":"+1 559 264 9112",
    "sg:postcode":"93728",
    "sg:province":"CA",
    "sg:tags":[
        "mobile",
        "home",
        "community"
    ],
    "wof:name":"Villa Fresno",
    "wof:placetype":"venue"
},
  "geometry": {"coordinates":[-119.841843,36.764601],"type":"Point"}
}