{
  "type": "Feature",
  "properties": {
    "iso:country":"US",
    "sg:address":"9701 Owensmouth Ave",
    "sg:city":"Chatsworth",
    "sg:classifiers":[
        {
            "category":"Manufacturing",
            "subcategory":"Tools & Machinery",
            "type":"Manufacturing & Wholesale Goods"
        }
    ],
    "sg:phone":"+1 818 700 0309",
    "sg:postcode":"91311",
    "sg:province":"CA",
    "sg:tags":[
        "machine",
        "shop"
    ],
    "wof:name":"Clark Tool & Die Co",
    "wof:placetype":"venue"
},
  "geometry": {"coordinates":[-118.60249,34.243646],"type":"Point"}
}