{
  "type": "Feature",
  "properties": {
    "iso:country":"US",
    "sg:address":"11299 San Pablo Avenue",
    "sg:city":"El Cerrito",
    "sg:classifiers":[
        {
            "category":"Health Services",
            "subcategory":"Dentist",
            "type":"Services"
        }
    ],
    "sg:phone":"+1 510 231 0147",
    "sg:postcode":"94530",
    "sg:province":"CA",
    "wof:name":"Western Dental",
    "wof:placetype":"venue"
},
  "geometry": {"coordinates":[-122.31557599999999,37.919986],"type":"Point"}
}