{
  "type": "Feature",
  "properties": {
    "addr:full":"1472 Fresno St Fresno CA 93706",
    "addr:housenumber":"1472",
    "addr:postcode":"93706",
    "addr:street":"Fresno St",
    "iso:country":"US",
    "sg:address":"1472 Fresno St",
    "sg:city":"Fresno",
    "sg:classifiers":[
        {
            "category":"Shopping",
            "type":"Retail Goods"
        }
    ],
    "sg:phone":"+1 559 498 0401",
    "sg:postcode":"93706",
    "sg:province":"CA",
    "sg:tags":[
        "perfume"
    ],
    "wof:name":"East West Fragrance",
    "wof:placetype":"venue"
},
  "geometry": {"coordinates":[-119.797118,36.732465],"type":"Point"}
}