{
  "type": "Feature",
  "properties": {
    "iso:country":"US",
    "sg:address":"11812 Hawthorne Blvd",
    "sg:city":"Hawthorne",
    "sg:classifiers":[
        {
            "category":"Wholesale",
            "subcategory":"Machinery & Supplies",
            "type":"Manufacturing & Wholesale Goods"
        }
    ],
    "sg:phone":"+1 310 675 8825",
    "sg:postcode":"90250",
    "sg:province":"CA",
    "sg:tags":[
        "equipment",
        "cosmetic",
        "beauty"
    ],
    "wof:name":"Beauty Supply & Salon",
    "wof:placetype":"venue"
},
  "geometry": {"coordinates":[-118.352997,33.9268],"type":"Point"}
}