{
  "type": "Feature",
  "properties": {
    "addr:full":"7636 Burnet Ave Van Nuys CA 91405",
    "addr:housenumber":"7636",
    "addr:postcode":"91405",
    "addr:street":"Burnet Ave",
    "iso:country":"US",
    "sg:address":"7636 Burnet Ave",
    "sg:city":"Van Nuys",
    "sg:classifiers":[
        {
            "category":"Health Services",
            "subcategory":"Medical Lab",
            "type":"Services"
        }
    ],
    "sg:phone":"+1 818 908 3600",
    "sg:postcode":"91405",
    "sg:province":"CA",
    "sg:tags":[
        "laboratory"
    ],
    "wof:name":"West Coast Clinical Labs",
    "wof:placetype":"venue"
},
  "geometry": {"coordinates":[-118.46285,34.209596],"type":"Point"}
}