{
  "type": "Feature",
  "properties": {
    "iso:country":"US",
    "sg:address":"250 Sutter St",
    "sg:city":"San Francisco",
    "sg:classifiers":[
        {
            "category":"Real Estate",
            "subcategory":"Architect",
            "type":"Services"
        }
    ],
    "sg:phone":"+1 415 291 8680",
    "sg:postcode":"94108",
    "sg:province":"CA",
    "sg:website":"www.cdrobinson.com",
    "wof:name":"C David Robinson Architects",
    "wof:placetype":"venue"
},
  "geometry": {"coordinates":[-122.404345,37.78985],"type":"Point"}
}