{
  "type": "Feature",
  "properties": {
    "addr:full":"250 Sutter St San Francisco CA 94108",
    "addr:housenumber":"250",
    "addr:postcode":"94108",
    "addr:street":"Sutter St",
    "iso:country":"US",
    "sg:address":"250 Sutter St",
    "sg:city":"San Francisco",
    "sg:classifiers":[
        {
            "category":"Real Estate",
            "subcategory":"Architect",
            "type":"Services"
        }
    ],
    "sg:phone":"+1 415 291 8680",
    "sg:postcode":"94108",
    "sg:province":"CA",
    "sg:website":"www.cdrobinson.com",
    "wof:name":"C David Robinson Architects",
    "wof:placetype":"venue"
},
  "geometry": {"coordinates":[-122.40434500000001,37.78985],"type":"Point"}
}