{
  "type": "Feature",
  "properties": {
    "iso:country":"US",
    "sg:address":"1141 N Capitol Ave",
    "sg:city":"San Jose",
    "sg:classifiers":[
        {
            "category":"Autos & Motor Vehicles",
            "subcategory":"Fuel & Gas Station",
            "type":"Retail Goods"
        }
    ],
    "sg:phone":"+1 408 926 3436",
    "sg:postcode":"95132",
    "sg:province":"CA",
    "sg:tags":[
        "oil"
    ],
    "wof:name":"Prestige Stations",
    "wof:placetype":"venue"
},
  "geometry": {"coordinates":[-121.862319,37.388304],"type":"Point"}
}