{
  "type": "Feature",
  "properties": {
    "addr:full":"1007 Via Pintada Riverside CA 92507",
    "addr:housenumber":"1007",
    "addr:postcode":"92507",
    "addr:street":"Via Pintada",
    "iso:country":"US",
    "sg:address":"1007 Via Pintada",
    "sg:city":"Riverside",
    "sg:classifiers":[
        {
            "category":"Building & Trades",
            "subcategory":"Construction",
            "type":"Services"
        }
    ],
    "sg:phone":"+1 951 683 1473",
    "sg:postcode":"92507",
    "sg:province":"CA",
    "sg:tags":[
        "general",
        "contractor"
    ],
    "wof:name":"Nicolaisen & Sons Constr Inc",
    "wof:placetype":"venue"
},
  "geometry": {"coordinates":[-117.33187599999999,33.953172],"type":"Point"}
}