{
  "type": "Feature",
  "properties": {
    "addr:full":"527 San Mateo Rd Half Moon Bay CA 94019",
    "addr:housenumber":"527",
    "addr:postcode":"94019",
    "addr:street":"San Mateo Rd",
    "iso:country":"US",
    "sg:address":"527 San Mateo Rd",
    "sg:city":"Half Moon Bay",
    "sg:classifiers":[
        {
            "category":"Retail",
            "subcategory":"Auto Repair",
            "type":"Services"
        }
    ],
    "sg:phone":"+1 650 726 6121",
    "sg:postcode":"94019",
    "sg:province":"CA",
    "sg:tags":[
        "repairing",
        "automobile"
    ],
    "wof:name":"Heinz Auto Svc",
    "wof:placetype":"venue"
},
  "geometry": {"coordinates":[-122.410839,37.478951],"type":"Point"}
}