{
  "type": "Feature",
  "properties": {
    "addr:full":"233 Prospect Pl Coronado CA 92118",
    "addr:housenumber":"233",
    "addr:postcode":"92118",
    "addr:street":"Prospect Pl",
    "iso:country":"US",
    "sg:address":"233 Prospect Pl",
    "sg:city":"Coronado",
    "sg:classifiers":[
        {
            "category":"Building & Trades",
            "subcategory":"Electrical",
            "type":"Services"
        }
    ],
    "sg:phone":"+1 619 437 1847",
    "sg:postcode":"92118",
    "sg:province":"CA",
    "sg:tags":[
        "electric",
        "contractor"
    ],
    "wof:name":"General Electric Health Care",
    "wof:placetype":"venue"
},
  "geometry": {"coordinates":[-117.168077,32.693966],"type":"Point"}
}