{
  "type": "Feature",
  "properties": {
    "addr:full":"15123 W Sunset Blvd Pacific Plsds CA 90272",
    "addr:housenumber":"15123",
    "addr:postcode":"90272",
    "addr:street":"W Sunset Blvd",
    "iso:country":"US",
    "sg:address":"15123 W Sunset Blvd",
    "sg:city":"Pacific Plsds",
    "sg:classifiers":[
        {
            "category":"Personal",
            "subcategory":"Shoe Repair & Shine",
            "type":"Services"
        }
    ],
    "sg:phone":"+1 310 454 4583",
    "sg:postcode":"90272",
    "sg:province":"CA",
    "sg:tags":[
        "repairing",
        "boot"
    ],
    "wof:name":"Shoe Fits Shoes Boot Luggage",
    "wof:placetype":"venue"
},
  "geometry": {"coordinates":[-118.523522,34.045527],"type":"Point"}
}