{
  "type": "Feature",
  "properties": {
    "iso:country":"US",
    "sg:address":"6500 Flotilla St",
    "sg:city":"Los Angeles",
    "sg:classifiers":[
        {
            "category":"Wholesale",
            "subcategory":"Machinery & Supplies",
            "type":"Manufacturing & Wholesale Goods"
        }
    ],
    "sg:phone":"+1 818 374 4949",
    "sg:postcode":"90040",
    "sg:province":"CA",
    "sg:tags":[
        "equipment",
        "establishment"
    ],
    "wof:name":"Value Laundry Equipment",
    "wof:placetype":"venue"
},
  "geometry": {"coordinates":[-118.131421,34.005745],"type":"Point"}
}