{
  "type": "Feature",
  "properties": {
    "addr:full":"5908 San Pablo Ave Emeryville CA 94608",
    "addr:housenumber":"5908",
    "addr:postcode":"94608",
    "addr:street":"San Pablo Ave",
    "iso:country":"US",
    "sg:address":"5908 San Pablo Ave",
    "sg:city":"Emeryville",
    "sg:classifiers":[
        {
            "category":"Food & Beverages",
            "subcategory":"Groceries & Convenience Stores",
            "type":"Retail Goods"
        }
    ],
    "sg:phone":"+1 510 655 4622",
    "sg:postcode":"94608",
    "sg:province":"CA",
    "sg:tags":[
        "grocer",
        "super",
        "supermarket"
    ],
    "wof:name":"Gateway Supermarket Inc",
    "wof:placetype":"venue"
},
  "geometry": {"coordinates":[-122.283997,37.842602],"type":"Point"}
}