{
  "type": "Feature",
  "properties": {
    "iso:country":"US",
    "sg:address":"5670 el Camino Real",
    "sg:city":"Carlsbad",
    "sg:classifiers":[
        {
            "category":"Shopping",
            "subcategory":"Computers & Home Electronics",
            "type":"Retail Goods"
        }
    ],
    "sg:phone":"+1 760 476 1401",
    "sg:postcode":"92008",
    "sg:province":"CA",
    "sg:tags":[
        "software"
    ],
    "wof:name":"Method 1",
    "wof:placetype":"venue"
},
  "geometry": {"coordinates":[-117.274716,33.13879],"type":"Point"}
}