{
  "type": "Feature",
  "properties": {
    "addr:full":"1305 S Meyler St San Pedro CA 90731",
    "addr:housenumber":"1305",
    "addr:postcode":"90731",
    "addr:street":"S Meyler St",
    "iso:country":"US",
    "sg:address":"1305 S Meyler St",
    "sg:city":"San Pedro",
    "sg:classifiers":[
        {
            "category":"Building & Trades",
            "subcategory":"Construction",
            "type":"Services"
        }
    ],
    "sg:phone":"+1 310 548 1563",
    "sg:postcode":"90731",
    "sg:province":"CA",
    "sg:tags":[
        "contractor"
    ],
    "wof:name":"A Plus Pools",
    "wof:placetype":"venue"
},
  "geometry": {"coordinates":[-118.296845,33.731568],"type":"Point"}
}