{
  "type": "Feature",
  "properties": {
    "iso:country":"US",
    "sg:address":"300 Bayswater Ave",
    "sg:city":"Burlingame",
    "sg:classifiers":[
        {
            "category":"Building & Trades",
            "subcategory":"Construction",
            "type":"Services"
        }
    ],
    "sg:phone":"+1 650 347 5051",
    "sg:postcode":"94010",
    "sg:province":"CA",
    "sg:tags":[
        "concrete",
        "pumping",
        "contractor"
    ],
    "wof:name":"K & L Concrete Pumping",
    "wof:placetype":"venue"
},
  "geometry": {"coordinates":[-122.334534,37.582741],"type":"Point"}
}