{
  "type": "Feature",
  "properties": {
    "iso:country":"US",
    "sg:address":"2357 Mountain View Ct",
    "sg:city":"Fairfield",
    "sg:classifiers":[
        {
            "category":"Shopping",
            "subcategory":"Hobbies, Toys, & Games",
            "type":"Retail Goods"
        }
    ],
    "sg:phone":"+1 707 435 1999",
    "sg:postcode":"94534",
    "sg:province":"CA",
    "wof:name":"West Coast Hobbies",
    "wof:placetype":"venue"
},
  "geometry": {"coordinates":[-122.050701,38.283259],"type":"Point"}
}