{
  "type": "Feature",
  "properties": {
    "iso:country":"US",
    "sg:address":"22320 Redwood Rd",
    "sg:city":"Castro Valley",
    "sg:classifiers":[
        {
            "category":"Retail",
            "subcategory":"Auto Repair",
            "type":"Services"
        }
    ],
    "sg:phone":"+1 510 538 1648",
    "sg:postcode":"94546",
    "sg:province":"CA",
    "wof:name":"Kling Neal Muffler Service",
    "wof:placetype":"venue"
},
  "geometry": {"coordinates":[-122.07399700000001,37.683601],"type":"Point"}
}