{
  "type": "Feature",
  "properties": {
    "addr:full":"724 Berry Ave Los Altos CA 94024",
    "addr:housenumber":"724",
    "addr:postcode":"94024",
    "addr:street":"Berry Ave",
    "iso:country":"US",
    "sg:address":"724 Berry Ave",
    "sg:city":"Los Altos",
    "sg:classifiers":[
        {
            "category":"Real Estate",
            "subcategory":"Architect",
            "type":"Services"
        }
    ],
    "sg:phone":"+1 650 969 2555",
    "sg:postcode":"94024",
    "sg:province":"CA",
    "wof:name":"Remodeling Project Inc",
    "wof:placetype":"venue"
},
  "geometry": {"coordinates":[-122.09571200000001,37.361375],"type":"Point"}
}