{
  "type": "Feature",
  "properties": {
    "addr:full":"18816 Devon Ave Saratoga CA 95070",
    "addr:housenumber":"18816",
    "addr:postcode":"95070",
    "addr:street":"Devon Ave",
    "iso:country":"US",
    "sg:address":"18816 Devon Ave",
    "sg:city":"Saratoga",
    "sg:classifiers":[
        {
            "category":"Professional",
            "type":"Services"
        }
    ],
    "sg:phone":"+1 408 866 0458",
    "sg:postcode":"95070",
    "sg:province":"CA",
    "wof:name":"A Lorincz",
    "wof:placetype":"venue"
},
  "geometry": {"coordinates":[-122.001029,37.278614],"type":"Point"}
}