{
  "type": "Feature",
  "properties": {
    "addr:full":"7329 Quimby St Paramount CA 90723",
    "addr:housenumber":"7329",
    "addr:postcode":"90723",
    "addr:street":"Quimby St",
    "iso:country":"US",
    "sg:address":"7329 Quimby St",
    "sg:city":"Paramount",
    "sg:classifiers":[
        {
            "category":"Autos & Motor Vehicles",
            "subcategory":"Auto Supplies",
            "type":"Retail Goods"
        }
    ],
    "sg:phone":"+1 562 634 0466",
    "sg:postcode":"90723",
    "sg:province":"CA",
    "sg:tags":[
        "automobile",
        "sunroof"
    ],
    "sg:website":"www.americansunroof.com",
    "wof:name":"American Sunroof",
    "wof:placetype":"venue"
},
  "geometry": {"coordinates":[-118.169335,33.905988],"type":"Point"}
}