{
  "type": "Feature",
  "properties": {
    "addr:full":"4766 Park Granada Calabasas CA 91302",
    "addr:housenumber":"4766",
    "addr:postcode":"91302",
    "addr:street":"Park Granada",
    "iso:country":"US",
    "sg:address":"4766 Park Granada",
    "sg:city":"Calabasas",
    "sg:classifiers":[
        {
            "category":"Professional",
            "subcategory":"Lawyer & Legal Services",
            "type":"Services"
        }
    ],
    "sg:phone":"+1 818 224 5683",
    "sg:postcode":"91302",
    "sg:province":"CA",
    "wof:name":"Love Stephen Attorney At Law",
    "wof:placetype":"venue"
},
  "geometry": {"coordinates":[-118.64299800000001,34.155499],"type":"Point"}
}