{
  "type": "Feature",
  "properties": {
    "iso:country":"US",
    "sg:address":"3811 Lakeside Dr",
    "sg:city":"San Pablo",
    "sg:classifiers":[
        {
            "category":"Real Estate",
            "subcategory":"Real Estate Operator",
            "type":"Services"
        }
    ],
    "sg:phone":"+1 510 262 9482",
    "sg:postcode":"94806",
    "sg:province":"CA",
    "sg:tags":[
        "apartment"
    ],
    "wof:name":"Heritage Park At Hilltop",
    "wof:placetype":"venue"
},
  "geometry": {"coordinates":[-122.331272,37.983391],"type":"Point"}
}