{
  "type": "Feature",
  "properties": {
    "addr:full":"340 Market St Colusa CA 95932",
    "addr:housenumber":"340",
    "addr:postcode":"95932",
    "addr:street":"Market St",
    "iso:country":"US",
    "sg:address":"340 Market St",
    "sg:city":"Colusa",
    "sg:classifiers":[
        {
            "category":"Professional",
            "subcategory":"Business Services",
            "type":"Services"
        }
    ],
    "sg:phone":"+1 530 458 3723",
    "sg:postcode":"95932",
    "sg:province":"CA",
    "wof:name":"Multi1 Services",
    "wof:placetype":"venue"
},
  "geometry": {"coordinates":[-122.00619500000001,39.213693],"type":"Point"}
}