{
  "type": "Feature",
  "properties": {
    "addr:full":"2119 E 7th St Long Beach CA 90804",
    "addr:housenumber":"2119",
    "addr:postcode":"90804",
    "addr:street":"E 7Th St",
    "iso:country":"US",
    "sg:address":"2119 E 7th St",
    "sg:city":"Long Beach",
    "sg:classifiers":[
        {
            "category":"Home & Garden",
            "subcategory":"Hardware",
            "type":"Retail Goods"
        }
    ],
    "sg:phone":"+1 562 439 4826",
    "sg:postcode":"90804",
    "sg:province":"CA",
    "sg:tags":[
        "store"
    ],
    "wof:name":"67th Hardware",
    "wof:placetype":"venue"
},
  "geometry": {"coordinates":[-118.166363,33.775477],"type":"Point"}
}