{
  "type": "Feature",
  "properties": {
    "iso:country":"US",
    "sg:address":"9495 S Santa Monica Blvd",
    "sg:city":"Beverly Hills",
    "sg:classifiers":[
        {
            "category":"Shopping",
            "subcategory":"Clothing, Apparel, & Fashions",
            "type":"Retail Goods"
        }
    ],
    "sg:phone":"+1 310 248 4830",
    "sg:postcode":"90210",
    "sg:province":"CA",
    "sg:tags":[
        "clothing",
        "women's"
    ],
    "sg:website":"www.shopenvie.com",
    "wof:name":"Envie",
    "wof:placetype":"venue"
},
  "geometry": {"coordinates":[-118.404305,34.070651],"type":"Point"}
}