{
  "type": "Feature",
  "properties": {
    "iso:country":"US",
    "sg:address":"2534 W Main St",
    "sg:city":"Visalia",
    "sg:classifiers":[
        {
            "category":"Professional",
            "subcategory":"Lawyer & Legal Services",
            "type":"Services"
        }
    ],
    "sg:phone":"+1 559 635 1234",
    "sg:postcode":"93291",
    "sg:province":"CA",
    "sg:tags":[
        "attorney"
    ],
    "wof:name":"Ninnis & Cribbs",
    "wof:placetype":"venue"
},
  "geometry": {"coordinates":[-119.319841,36.32955],"type":"Point"}
}