{
  "type": "Feature",
  "properties": {
    "iso:country":"US",
    "sg:address":"261 Beach Rd",
    "sg:city":"Marina",
    "sg:classifiers":[
        {
            "category":"Education",
            "subcategory":"School",
            "type":"Public Place"
        }
    ],
    "sg:phone":"+1 831 384 7952",
    "sg:postcode":"93933",
    "sg:province":"CA",
    "wof:name":"Monterey Peninsula Unified School District",
    "wof:placetype":"venue"
},
  "geometry": {"coordinates":[-121.79221699999999,36.691885],"type":"Point"}
}