{
  "type": "Feature",
  "properties": {
    "iso:country":"US",
    "sg:address":"3880 W Rosecrans Ave",
    "sg:city":"Hawthorne",
    "sg:classifiers":[
        {
            "category":"Shopping",
            "subcategory":"Pharmacy",
            "type":"Retail Goods"
        }
    ],
    "sg:phone":"+1 310 675 4221",
    "sg:postcode":"90250",
    "sg:province":"CA",
    "sg:tags":[
        "drug",
        "store"
    ],
    "wof:name":"Sav-On 9405",
    "wof:placetype":"venue"
},
  "geometry": {"coordinates":[-118.340193,33.901847],"type":"Point"}
}