{
  "type": "Feature",
  "properties": {
    "iso:country":"US",
    "sg:address":"1615 Stanford St",
    "sg:city":"Santa Monica",
    "sg:classifiers":[
        {
            "category":"Building & Trades",
            "subcategory":"Construction",
            "type":"Services"
        }
    ],
    "sg:phone":"+1 310 315 9220",
    "sg:postcode":"90404",
    "sg:province":"CA",
    "sg:tags":[
        "interior",
        "design"
    ],
    "wof:name":"Errico Thompson",
    "wof:placetype":"venue"
},
  "geometry": {"coordinates":[-118.466579,34.372219],"type":"Point"}
}