{
  "type": "Feature",
  "properties": {
    "addr:full":"1859 E Dakota Ave Fresno CA 93726",
    "addr:housenumber":"1859",
    "addr:postcode":"93726",
    "addr:street":"E Dakota Ave",
    "iso:country":"US",
    "sg:address":"1859 E Dakota Ave",
    "sg:city":"Fresno",
    "sg:classifiers":[
        {
            "category":"Shopping",
            "subcategory":"Tobacco",
            "type":"Retail Goods"
        }
    ],
    "sg:phone":"+1 559 225 2011",
    "sg:postcode":"93726",
    "sg:province":"CA",
    "sg:tags":[
        "cigarette",
        "cigar",
        "dealer"
    ],
    "wof:name":"Fresno Cigarette & Cigars",
    "wof:placetype":"venue"
},
  "geometry": {"coordinates":[-119.788893,36.786841],"type":"Point"}
}