{
  "type": "Feature",
  "properties": {
    "addr:full":"4540 Tobias Ave Sherman Oaks CA 91403",
    "addr:housenumber":"4540",
    "addr:postcode":"91403",
    "addr:street":"Tobias Ave",
    "iso:country":"US",
    "sg:address":"4540 Tobias Ave",
    "sg:city":"Sherman Oaks",
    "sg:classifiers":[
        {
            "category":"Health Services",
            "subcategory":"Doctor",
            "type":"Services"
        }
    ],
    "sg:phone":"+1 818 788 3958",
    "sg:postcode":"91403",
    "sg:province":"CA",
    "sg:tags":[
        "dentist"
    ],
    "wof:name":"Digital Dentist",
    "wof:placetype":"venue"
},
  "geometry": {"coordinates":[-118.451908,34.153132],"type":"Point"}
}