{
  "type": "Feature",
  "properties": {
    "iso:country":"US",
    "sg:address":"17301 Sunburst St",
    "sg:city":"Northridge",
    "sg:classifiers":[
        {
            "category":"Wholesale",
            "subcategory":"Meat",
            "type":"Manufacturing & Wholesale Goods"
        }
    ],
    "sg:phone":"+1 818 341 9164",
    "sg:postcode":"91325",
    "sg:province":"CA",
    "wof:name":"Toledo Meats Inc",
    "wof:placetype":"venue"
},
  "geometry": {"coordinates":[-118.51564999999999,34.234546],"type":"Point"}
}