{
  "type": "Feature",
  "properties": {
    "iso:country":"US",
    "sg:address":"1122 Wall St Ste H",
    "sg:city":"Los Angeles",
    "sg:classifiers":[
        {
            "category":"Shopping",
            "subcategory":"Clothing, Apparel, & Fashions",
            "type":"Retail Goods"
        }
    ],
    "sg:phone":"+1 213 748 0210",
    "sg:postcode":"90015",
    "sg:province":"CA",
    "sg:tags":[
        "accessory",
        "clothing",
        "women's"
    ],
    "sg:website":"www.fannyfashion.com",
    "wof:name":"Fanny Fashion",
    "wof:placetype":"venue"
},
  "geometry": {"coordinates":[-118.254411,34.035634],"type":"Point"}
}