{
  "type": "Feature",
  "properties": {
    "iso:country":"US",
    "sg:address":"321 Potrero",
    "sg:city":"San Francisco",
    "sg:classifiers":[
        {
            "category":"Professional",
            "subcategory":"Computer Services",
            "type":"Services"
        }
    ],
    "sg:postcode":"94103",
    "sg:province":"CA",
    "sg:website":"http://www.snappytv.com",
    "wof:name":"SnappyTV",
    "wof:placetype":"venue"
},
  "geometry": {"coordinates":[-122.407364,37.764757],"type":"Point"}
}