{
  "type": "Feature",
  "properties": {
    "addr:full":"2115 W Washington St Stockton CA 95203",
    "addr:housenumber":"2115",
    "addr:postcode":"95203",
    "addr:street":"W Washington St",
    "iso:country":"US",
    "sg:address":"2115 W Washington St",
    "sg:city":"Stockton",
    "sg:classifiers":[
        {
            "category":"Wholesale",
            "subcategory":"Farm Supplies",
            "type":"Manufacturing & Wholesale Goods"
        }
    ],
    "sg:phone":"+1 209 466 4391",
    "sg:postcode":"95203",
    "sg:province":"CA",
    "sg:tags":[
        "feed",
        "concentrate",
        "supplement"
    ],
    "wof:name":"PMAG Products Inc",
    "wof:placetype":"venue"
},
  "geometry": {"coordinates":[-121.321214,37.94537],"type":"Point"}
}