{
  "type": "Feature",
  "properties": {
    "addr:full":"803 E Palmdale Blvd Palmdale CA 93550",
    "addr:housenumber":"803",
    "addr:postcode":"ca 93550",
    "addr:street":"E Palmdale Blvd",
    "iso:country":"US",
    "sg:address":"803 E Palmdale Blvd",
    "sg:city":"Palmdale",
    "sg:classifiers":[
        {
            "category":"Banks & Credit Unions",
            "subcategory":"Bank",
            "type":"Services"
        }
    ],
    "sg:phone":"+1 661 947 5511",
    "sg:postcode":"93550",
    "sg:province":"CA",
    "sg:tags":[
        "cashing",
        "check"
    ],
    "wof:name":"Checknet USA",
    "wof:placetype":"venue"
},
  "geometry": {"coordinates":[-118.115814,34.579596],"type":"Point"}
}