{
  "type": "Feature",
  "properties": {
    "addr:full":"35 W Victoria St Santa Barbara CA 93101",
    "addr:housenumber":"35",
    "addr:postcode":"93101",
    "addr:street":"W Victoria St",
    "iso:country":"US",
    "sg:address":"35 W Victoria St",
    "sg:city":"Santa Barbara",
    "sg:classifiers":[
        {
            "category":"Social Services",
            "subcategory":"Adult Care",
            "type":"Services"
        }
    ],
    "sg:phone":"+1 805 963 0474",
    "sg:postcode":"93101",
    "sg:province":"CA",
    "sg:tags":[
        "organization",
        "senior",
        "citizen"
    ],
    "wof:name":"RSVP-Retired Senior Program",
    "wof:placetype":"venue"
},
  "geometry": {"coordinates":[-119.706436,34.423541],"type":"Point"}
}