{
  "type": "Feature",
  "properties": {
    "addr:full":"1751 N D St San Bernardino CA 92405",
    "addr:housenumber":"1751",
    "addr:postcode":"92405",
    "addr:street":"N D St",
    "iso:country":"US",
    "sg:address":"1751 N D St",
    "sg:city":"San Bernardino",
    "sg:classifiers":[
        {
            "category":"Wholesale",
            "subcategory":"Medical Equipment & Supplies",
            "type":"Manufacturing & Wholesale Goods"
        }
    ],
    "sg:phone":"+1 909 881 6013",
    "sg:postcode":"92405",
    "sg:province":"CA",
    "sg:tags":[
        "physician",
        "surgeon"
    ],
    "wof:name":"ABA Medical Supply",
    "wof:placetype":"venue"
},
  "geometry": {"coordinates":[-117.291848,34.130743],"type":"Point"}
}