{
  "type": "Feature",
  "properties": {
    "addr:full":"1009 S Coast Hwy Laguna Beach CA 92651",
    "addr:housenumber":"1009",
    "addr:postcode":"92651",
    "addr:street":"S Coast Hwy",
    "iso:country":"US",
    "sg:address":"1009 S Coast Hwy",
    "sg:city":"Laguna Beach",
    "sg:classifiers":[
        {
            "category":"Retail",
            "subcategory":"Car Wash",
            "type":"Services"
        }
    ],
    "sg:phone":"+1 949 494 9611",
    "sg:postcode":"92651",
    "sg:province":"CA",
    "sg:tags":[
        "automobile",
        "detail",
        "clean"
    ],
    "wof:name":"Sweetwater Mid Town",
    "wof:placetype":"venue"
},
  "geometry": {"coordinates":[-117.77712200000001,33.534184],"type":"Point"}
}