{
  "type": "Feature",
  "properties": {
    "iso:country":"US",
    "sg:address":"12624 Poway Rd",
    "sg:city":"Poway",
    "sg:classifiers":[
        {
            "category":"Professional",
            "type":"Services"
        }
    ],
    "sg:phone":"+1 858 748 8072",
    "sg:postcode":"92064",
    "sg:province":"CA",
    "sg:tags":[
        "establishment"
    ],
    "wof:name":"Groovy Gear",
    "wof:placetype":"venue"
},
  "geometry": {"coordinates":[-117.05670000000001,32.954523],"type":"Point"}
}