{
  "type": "Feature",
  "properties": {
    "iso:country":"US",
    "sg:address":"863 E Stanley Blvd",
    "sg:city":"Livermore",
    "sg:classifiers":[
        {
            "category":"Shopping",
            "subcategory":"Tobacco",
            "type":"Retail Goods"
        }
    ],
    "sg:phone":"+1 925 454 1690",
    "sg:postcode":"94550",
    "sg:province":"CA",
    "sg:tags":[
        "cigarette",
        "cigar",
        "dealer"
    ],
    "wof:name":"Livermore Smoke Shop",
    "wof:placetype":"venue"
},
  "geometry": {"coordinates":[-121.785107,37.678349],"type":"Point"}
}