{
  "type": "Feature",
  "properties": {
    "addr:full":"2353 McBryde Ave Richmond CA 94804",
    "addr:housenumber":"2353",
    "addr:postcode":"94804",
    "addr:street":"Mcbryde Ave",
    "iso:country":"US",
    "sg:address":"2353 McBryde Ave",
    "sg:city":"Richmond",
    "sg:classifiers":[
        {
            "category":"Retail",
            "subcategory":"Laundry & Dry Cleaning",
            "type":"Services"
        }
    ],
    "sg:phone":"+1 510 412 0974",
    "sg:postcode":"94804",
    "sg:province":"CA",
    "sg:tags":[
        "cleaner",
        "rug",
        "carpet"
    ],
    "wof:name":"Variety Maintenance",
    "wof:placetype":"venue"
},
  "geometry": {"coordinates":[-122.34699999999999,37.947201],"type":"Point"}
}