{
  "type": "Feature",
  "properties": {
    "addr:full":"1027 Broadway El Cajon CA 92021",
    "addr:housenumber":"1027",
    "addr:postcode":"92021",
    "addr:street":"Broadway",
    "iso:country":"US",
    "sg:address":"1027 Broadway",
    "sg:city":"El Cajon",
    "sg:classifiers":[
        {
            "category":"Wholesale",
            "subcategory":"Machinery & Supplies",
            "type":"Manufacturing & Wholesale Goods"
        }
    ],
    "sg:phone":"+1 619 442 8669",
    "sg:postcode":"92021",
    "sg:province":"CA",
    "sg:tags":[
        "equipment",
        "establishment"
    ],
    "wof:name":"West Coast Casket Supply",
    "wof:placetype":"venue"
},
  "geometry": {"coordinates":[-116.94548399999999,32.807631],"type":"Point"}
}