{
  "type": "Feature",
  "properties": {
    "addr:full":"2605 Jacaranda Ave Carlsbad CA 92009",
    "addr:housenumber":"2605",
    "addr:postcode":"92009",
    "addr:street":"Jacaranda Ave",
    "iso:country":"US",
    "sg:address":"2605 Jacaranda Ave",
    "sg:city":"Carlsbad",
    "sg:classifiers":[
        {
            "category":"Building & Trades",
            "subcategory":"Cleaning & Sanitation",
            "type":"Services"
        }
    ],
    "sg:phone":"+1 760 420 2075",
    "sg:postcode":"92009",
    "sg:province":"CA",
    "sg:tags":[
        "carpet"
    ],
    "wof:name":"Cleaning Company The",
    "wof:placetype":"venue"
},
  "geometry": {"coordinates":[-117.253848,33.755275],"type":"Point"}
}