{
  "type": "Feature",
  "properties": {
    "iso:country":"US",
    "sg:address":"6380 Florence Ave",
    "sg:city":"Bell Gardens",
    "sg:classifiers":[
        {
            "category":"Professional",
            "subcategory":"Computer Services",
            "type":"Services"
        }
    ],
    "sg:phone":"+1 323 205 2281",
    "sg:postcode":"90201",
    "sg:province":"CA",
    "sg:tags":[
        "repair"
    ],
    "sg:website":"www.geeksquadcomputerhelp.com/",
    "wof:name":"Geeks Quad Computer",
    "wof:placetype":"venue"
},
  "geometry": {"coordinates":[-118.15084899999999,33.964284],"type":"Point"}
}