{
  "type": "Feature",
  "properties": {
    "addr:full":"311 Pollasky Ave Clovis CA 93612",
    "addr:housenumber":"311",
    "addr:postcode":"93612",
    "addr:street":"Pollasky Ave",
    "iso:country":"US",
    "sg:address":"311 Pollasky Ave",
    "sg:city":"Clovis",
    "sg:classifiers":[
        {
            "category":"Restaurant",
            "type":"Food & Drink"
        }
    ],
    "sg:phone":"+1 559 298 2211",
    "sg:postcode":"93612",
    "sg:province":"CA",
    "wof:name":"LA Posada Restaurant",
    "wof:placetype":"venue"
},
  "geometry": {"coordinates":[-119.701916,36.825388],"type":"Point"}
}