{
  "type": "Feature",
  "properties": {
    "addr:full":"120 E 4th St Cloverdale CA 95425",
    "addr:housenumber":"120",
    "addr:postcode":"95425",
    "addr:street":"E 4Th St",
    "iso:country":"US",
    "sg:address":"120 E 4th St",
    "sg:city":"Cloverdale",
    "sg:classifiers":[
        {
            "category":"Banks & Credit Unions",
            "subcategory":"Bank",
            "type":"Services"
        }
    ],
    "sg:phone":"+1 707 894 0703",
    "sg:postcode":"95425",
    "sg:province":"CA",
    "sg:tags":[
        "loan",
        "real estate"
    ],
    "wof:name":"Rainbow Mortgage & Investment",
    "wof:placetype":"venue"
},
  "geometry": {"coordinates":[-123.019141,38.808932],"type":"Point"}
}