{
  "type": "Feature",
  "properties": {
    "iso:country":"US",
    "sg:address":"1420 W Valley Blvd",
    "sg:city":"Alhambra",
    "sg:classifiers":[
        {
            "category":"Autos & Motor Vehicles",
            "subcategory":"Auto Supplies",
            "type":"Retail Goods"
        }
    ],
    "sg:phone":"+1 626 458 0865",
    "sg:postcode":"91803",
    "sg:province":"CA",
    "sg:tags":[
        "automobile",
        "stereo",
        "installation",
        "alarm"
    ],
    "wof:name":"Viceli's Car Alarm & Stereo",
    "wof:placetype":"venue"
},
  "geometry": {"coordinates":[-118.138695,34.077478],"type":"Point"}
}