{
  "type": "Feature",
  "properties": {
    "addr:full":"1276 S Main St Salinas CA 93901",
    "addr:housenumber":"1276",
    "addr:postcode":"93901",
    "addr:street":"S Main St",
    "iso:country":"US",
    "sg:address":"1276 S Main St",
    "sg:city":"Salinas",
    "sg:classifiers":[
        {
            "category":"Shopping",
            "subcategory":"Gifts & Souvenirs",
            "type":"Retail Goods"
        }
    ],
    "sg:phone":"+1 831 755 7718",
    "sg:postcode":"93901",
    "sg:province":"CA",
    "wof:name":"Game Crazy",
    "wof:placetype":"venue"
},
  "geometry": {"coordinates":[-121.660162,36.656179],"type":"Point"}
}