{
  "type": "Feature",
  "properties": {
    "addr:full":"3728 Cesar Chavez San Francisco CA 94110",
    "addr:housenumber":"3728",
    "addr:postcode":"94110",
    "addr:street":"Cesar Chavez",
    "iso:country":"US",
    "sg:address":"3728 Cesar Chavez",
    "sg:city":"San Francisco",
    "sg:classifiers":[
        {
            "category":"Organizations",
            "subcategory":"Religious Organization",
            "type":"Services"
        }
    ],
    "sg:phone":"+1 415 647 1330",
    "sg:postcode":"94110",
    "sg:province":"CA",
    "sg:tags":[
        "church"
    ],
    "sg:website":"www.sfmissionsoutpost.org",
    "wof:name":"First Church Of God-Anderson",
    "wof:placetype":"venue"
},
  "geometry": {"coordinates":[-122.42421899999999,37.74795],"type":"Point"}
}