{
  "type": "Feature",
  "properties": {
    "addr:full":"1275 W 29th Street Los Angeles CA 90007",
    "addr:housenumber":"1275",
    "addr:postcode":"90007",
    "addr:street":"W 29Th Street",
    "iso:country":"US",
    "sg:address":"1275 W 29th Street",
    "sg:city":"Los Angeles",
    "sg:classifiers":[
        {
            "category":"Education",
            "subcategory":"University",
            "type":"Public Place"
        }
    ],
    "sg:phone":"+1 213 743 2256",
    "sg:postcode":"90007",
    "sg:province":"CA",
    "sg:tags":[
        "college"
    ],
    "wof:name":"University of Southern California University Park",
    "wof:placetype":"venue"
},
  "geometry": {"coordinates":[-118.28835599999999,34.028405],"type":"Point"}
}