{
  "type": "Feature",
  "properties": {
    "addr:full":"1802 Webster St Alameda CA 94501",
    "addr:housenumber":"1802",
    "addr:postcode":"94501",
    "addr:street":"Webster St",
    "iso:country":"US",
    "sg:address":"1802 Webster St",
    "sg:city":"Alameda",
    "sg:classifiers":[
        {
            "category":"Autos & Motor Vehicles",
            "subcategory":"Fuel & Gas Station",
            "type":"Retail Goods"
        },
        {
            "category":"Retail",
            "subcategory":"Auto Repair",
            "type":"Services"
        }
    ],
    "sg:phone":"+1 510 522 8459",
    "sg:postcode":"94501",
    "sg:province":"CA",
    "wof:name":"Chevron Service-Cliff Maderia",
    "wof:placetype":"venue"
},
  "geometry": {"coordinates":[-122.27600099999999,37.777699],"type":"Point"}
}