{
  "type": "Feature",
  "properties": {
    "addr:full":"1405 E Olive Ave Fresno CA 93728",
    "addr:housenumber":"1405",
    "addr:postcode":"93728",
    "addr:street":"E Olive Ave",
    "iso:country":"US",
    "sg:address":"1405 E Olive Ave",
    "sg:city":"Fresno",
    "sg:classifiers":[
        {
            "category":"Professional",
            "subcategory":"Credit Reporting & Collection",
            "type":"Services"
        }
    ],
    "sg:phone":"+1 559 441 4100",
    "sg:postcode":"93728",
    "sg:province":"CA",
    "sg:tags":[
        "agency"
    ],
    "wof:name":"J M Hollister Inc",
    "wof:placetype":"venue"
},
  "geometry": {"coordinates":[-119.793989,36.757762],"type":"Point"}
}