{
  "type": "Feature",
  "properties": {
    "iso:country":"US",
    "sg:address":"9042 Garfield Ave",
    "sg:city":"Huntington Beach",
    "sg:classifiers":[
        {
            "category":"Professional",
            "type":"Services"
        }
    ],
    "sg:phone":"+1 714 594 0775",
    "sg:postcode":"92646",
    "sg:province":"CA",
    "sg:website":"www.myphonecompany.com",
    "wof:name":"1-Plus Services Inc",
    "wof:placetype":"venue"
},
  "geometry": {"coordinates":[-117.96943899999999,33.686768],"type":"Point"}
}