{
  "type": "Feature",
  "properties": {
    "addr:full":"8472 Copper Dr Redding CA 96001",
    "addr:housenumber":"8472",
    "addr:postcode":"96001",
    "addr:street":"Copper Dr",
    "iso:country":"US",
    "sg:address":"8472 Copper Dr",
    "sg:city":"Redding",
    "sg:classifiers":[
        {
            "category":"Building & Trades",
            "subcategory":"Construction",
            "type":"Services"
        }
    ],
    "sg:phone":"+1 530 244 9708",
    "sg:postcode":"96001",
    "sg:province":"CA",
    "sg:tags":[
        "contractor"
    ],
    "wof:name":"Window Crafts By Jack Witt",
    "wof:placetype":"venue"
},
  "geometry": {"coordinates":[-122.38545999999999,40.502088],"type":"Point"}
}