{
  "type": "Feature",
  "properties": {
    "addr:full":"3718 Kenora Dr Spring Valley CA 91977",
    "addr:housenumber":"3718",
    "addr:postcode":"91977",
    "addr:street":"Kenora Dr",
    "iso:country":"US",
    "sg:address":"3718 Kenora Dr",
    "sg:city":"Spring Valley",
    "sg:classifiers":[
        {
            "category":"Retail",
            "subcategory":"Car Wash",
            "type":"Services"
        }
    ],
    "sg:phone":"+1 619 462 4101",
    "sg:postcode":"91977",
    "sg:province":"CA",
    "sg:tags":[
        "polishing",
        "washing"
    ],
    "wof:name":"Casa De Oro Car Wash",
    "wof:placetype":"venue"
},
  "geometry": {"coordinates":[-116.988508,32.746937],"type":"Point"}
}