{
  "type": "Feature",
  "properties": {
    "addr:full":"2609 W Wyoming Ave Burbank CA 91505",
    "addr:housenumber":"2609",
    "addr:postcode":"91505",
    "addr:street":"W Wyoming Ave",
    "iso:country":"US",
    "sg:address":"2609 W Wyoming Ave",
    "sg:city":"Burbank",
    "sg:classifiers":[
        {
            "category":"Social Services",
            "type":"Services"
        }
    ],
    "sg:phone":"+1 818 845 2669",
    "sg:postcode":"91505",
    "sg:province":"CA",
    "sg:tags":[
        "counselor",
        "marriage",
        "family"
    ],
    "wof:name":"Personal Growth & Family",
    "wof:placetype":"venue"
},
  "geometry": {"coordinates":[-118.34015599999999,34.178576],"type":"Point"}
}