{
  "type": "Feature",
  "properties": {
    "iso:country":"US",
    "sg:address":"1510 E Olive Ave",
    "sg:city":"Fresno",
    "sg:classifiers":[
        {
            "category":"Health Services",
            "subcategory":"Doctor",
            "type":"Services"
        }
    ],
    "sg:phone":"+1 559 266 1508",
    "sg:postcode":"93728",
    "sg:province":"CA",
    "sg:tags":[
        "clinic"
    ],
    "wof:name":"Fresno Madera Conditional",
    "wof:placetype":"venue"
},
  "geometry": {"coordinates":[-119.792511,36.757622],"type":"Point"}
}