{
  "type": "Feature",
  "properties": {
    "addr:full":"1510 E Olive Ave Fresno CA 93728",
    "addr:housenumber":"1510",
    "addr:postcode":"93728",
    "addr:street":"E Olive Ave",
    "iso:country":"US",
    "sg:address":"1510 E Olive Ave",
    "sg:city":"Fresno",
    "sg:classifiers":[
        {
            "category":"Health Services",
            "subcategory":"Doctor",
            "type":"Services"
        }
    ],
    "sg:phone":"+1 559 266 1508",
    "sg:postcode":"93728",
    "sg:province":"CA",
    "sg:tags":[
        "clinic"
    ],
    "wof:name":"Fresno Madera Conditional",
    "wof:placetype":"venue"
},
  "geometry": {"coordinates":[-119.792511,36.757622],"type":"Point"}
}