{
  "type": "Feature",
  "properties": {
    "iso:country":"US",
    "sg:address":"688 Sierra Point Rd",
    "sg:city":"Brisbane",
    "sg:classifiers":[
        {
            "category":"Home & Garden",
            "subcategory":"Hardware",
            "type":"Retail Goods"
        }
    ],
    "sg:phone":"+1 415 468 3891",
    "sg:postcode":"94005",
    "sg:province":"CA",
    "sg:tags":[
        "measuring",
        "device"
    ],
    "wof:name":"Compass Wind",
    "wof:placetype":"venue"
},
  "geometry": {"coordinates":[-122.399905,37.679015],"type":"Point"}
}