{
  "type": "Feature",
  "properties": {
    "iso:country":"US",
    "sg:address":"2745 Spring St",
    "sg:city":"Redwood City",
    "sg:classifiers":[
        {
            "category":"Home & Garden",
            "subcategory":"Building Materials",
            "type":"Retail Goods"
        }
    ],
    "sg:phone":"+1 650 366 2243",
    "sg:postcode":"94063",
    "sg:province":"CA",
    "sg:tags":[
        "shutter"
    ],
    "wof:name":"Spraymate",
    "wof:placetype":"venue"
},
  "geometry": {"coordinates":[-122.206639,37.482121],"type":"Point"}
}