{
  "type": "Feature",
  "properties": {
    "iso:country":"US",
    "sg:address":"3763 Arlington Ave",
    "sg:city":"Riverside",
    "sg:classifiers":[
        {
            "category":"Banks & Credit Unions",
            "subcategory":"Bank",
            "type":"Services"
        }
    ],
    "sg:phone":"+1 951 328 9959",
    "sg:postcode":"92506",
    "sg:province":"CA",
    "sg:tags":[
        "financing"
    ],
    "wof:name":"Inland Empire Funding",
    "wof:placetype":"venue"
},
  "geometry": {"coordinates":[-117.396888,33.946336],"type":"Point"}
}