{
  "type": "Feature",
  "properties": {
    "addr:full":"2575 Fortune Way Vista CA 92081",
    "addr:housenumber":"2575",
    "addr:postcode":"92081",
    "addr:street":"Fortune Way",
    "iso:country":"US",
    "sg:address":"2575 Fortune Way",
    "sg:city":"Vista",
    "sg:classifiers":[
        {
            "category":"Wholesale",
            "subcategory":"Durable Goods & Equipment",
            "type":"Manufacturing & Wholesale Goods"
        }
    ],
    "sg:phone":"+1 760 599 0071",
    "sg:postcode":"92081",
    "sg:province":"CA",
    "sg:tags":[
        "importer"
    ],
    "sg:website":"www.tlcproducts.com",
    "wof:name":"American Legacy Products Inc",
    "wof:placetype":"venue"
},
  "geometry": {"coordinates":[-117.223804,33.150906],"type":"Point"}
}