{
  "type": "Feature",
  "properties": {
    "iso:country":"US",
    "sg:address":"6221 Enterprise Dr",
    "sg:city":"Diamond Springs",
    "sg:classifiers":[
        {
            "category":"Retail",
            "subcategory":"Auto Repair",
            "type":"Services"
        }
    ],
    "sg:phone":"+1 530 295 3727",
    "sg:postcode":"95619",
    "sg:province":"CA",
    "sg:tags":[
        "automobile",
        "top",
        "upholstery"
    ],
    "sg:website":"www.santanainteriors.com",
    "wof:name":"Santana Interior Design",
    "wof:placetype":"venue"
},
  "geometry": {"coordinates":[-120.82477299999999,38.69637],"type":"Point"}
}