{
  "type": "Feature",
  "properties": {
    "addr:full":"417 S Broadway Santa Ana CA 92701",
    "addr:housenumber":"417",
    "addr:postcode":"92701",
    "addr:street":"S Broadway",
    "iso:country":"US",
    "sg:address":"417 S Broadway",
    "sg:city":"Santa Ana",
    "sg:classifiers":[
        {
            "category":"Building & Trades",
            "subcategory":"Cleaning & Sanitation",
            "type":"Services"
        }
    ],
    "sg:phone":"+1 714 547 6239",
    "sg:postcode":"92701",
    "sg:province":"CA",
    "sg:tags":[
        "janitor"
    ],
    "wof:name":"Hernando Tineo Janitorial Svc",
    "wof:placetype":"venue"
},
  "geometry": {"coordinates":[-117.869685,33.741028],"type":"Point"}
}