{
  "type": "Feature",
  "properties": {
    "iso:country":"US",
    "sg:address":"407 Clement St",
    "sg:city":"San Francisco",
    "sg:classifiers":[
        {
            "category":"Cafe",
            "type":"Food & Drink"
        }
    ],
    "sg:menulink":"http://www.allmenus.com/ca/san-francisco/52209-d--a-cafe/menu/",
    "sg:phone":"+1 415 668 7883",
    "sg:postcode":"94118",
    "sg:province":"CA",
    "sg:tags":[
        "asian",
        "chinese"
    ],
    "wof:name":"D & A Cafe",
    "wof:placetype":"venue"
},
  "geometry": {"coordinates":[-122.463542,37.783035],"type":"Point"}
}