{
  "type": "Feature",
  "properties": {
    "addr:full":"2241 S Park Ave Pomona CA 91766",
    "addr:housenumber":"2241",
    "addr:postcode":"91766",
    "addr:street":"S Park Ave",
    "iso:country":"US",
    "sg:address":"2241 S Park Ave",
    "sg:city":"Pomona",
    "sg:classifiers":[
        {
            "category":"Freight",
            "type":"Transportation"
        }
    ],
    "sg:phone":"+1 909 628 7894",
    "sg:postcode":"91766",
    "sg:province":"CA",
    "sg:tags":[
        "trucking"
    ],
    "wof:name":"C & C Trucking",
    "wof:placetype":"venue"
},
  "geometry": {"coordinates":[-117.75348700000001,34.029564],"type":"Point"}
}