{
  "type": "Feature",
  "properties": {
    "iso:country":"US",
    "sg:address":"1490 Tehama Ave",
    "sg:city":"Oroville",
    "sg:classifiers":[
        {
            "category":"Manufacturing",
            "subcategory":"Electronics",
            "type":"Manufacturing & Wholesale Goods"
        }
    ],
    "sg:phone":"+1 530 534 0971",
    "sg:postcode":"95965",
    "sg:province":"CA",
    "sg:tags":[
        "device",
        "communication",
        "mfg"
    ],
    "wof:name":"Line Master Industries",
    "wof:placetype":"venue"
},
  "geometry": {"coordinates":[-121.59504,39.515478],"type":"Point"}
}