{
  "type": "Feature",
  "properties": {
    "addr:full":"6035 University Ave San Diego CA 92115",
    "addr:housenumber":"6035",
    "addr:postcode":"92115",
    "addr:street":"University Ave",
    "iso:country":"US",
    "sg:address":"6035 University Ave",
    "sg:city":"San Diego",
    "sg:classifiers":[
        {
            "category":"Organizations",
            "subcategory":"Religious Organization",
            "type":"Services"
        }
    ],
    "sg:phone":"+1 619 858 1860",
    "sg:postcode":"92115",
    "sg:province":"CA",
    "wof:name":"South Sudan Christian Group",
    "wof:placetype":"venue"
},
  "geometry": {"coordinates":[-117.066002,32.7523],"type":"Point"}
}