{
  "type": "Feature",
  "properties": {
    "addr:full":"6168 Shadow Ln Citrus Heights CA 95621",
    "addr:housenumber":"6168",
    "addr:postcode":"95621",
    "addr:street":"Shadow Ln",
    "iso:country":"US",
    "sg:address":"6168 Shadow Ln",
    "sg:city":"Citrus Heights",
    "sg:classifiers":[
        {
            "category":"Restaurant",
            "type":"Food & Drink"
        }
    ],
    "sg:phone":"+1 916 725 6009",
    "sg:postcode":"95621",
    "sg:province":"CA",
    "wof:name":"Kifune Restaurant",
    "wof:placetype":"venue"
},
  "geometry": {"coordinates":[-121.322862,38.675879],"type":"Point"}
}