{
  "type": "Feature",
  "properties": {
    "iso:country":"US",
    "sg:address":"3830 5th Ave",
    "sg:city":"San Diego",
    "sg:classifiers":[
        {
            "category":"Shopping",
            "subcategory":"Gifts & Souvenirs",
            "type":"Retail Goods"
        }
    ],
    "sg:phone":"+1 619 296 3234",
    "sg:postcode":"92103",
    "sg:province":"CA",
    "sg:tags":[
        "shop"
    ],
    "wof:name":"Fifth Avenue Card Co",
    "wof:placetype":"venue"
},
  "geometry": {"coordinates":[-117.160506,32.747867],"type":"Point"}
}