{
  "type": "Feature",
  "properties": {
    "iso:country":"US",
    "sg:address":"5151 F St",
    "sg:city":"Chino",
    "sg:classifiers":[
        {
            "category":"Organizations",
            "subcategory":"Non-profit Organization",
            "type":"Services"
        }
    ],
    "sg:phone":"+1 909 613 1495",
    "sg:postcode":"91710",
    "sg:province":"CA",
    "sg:tags":[
        "info",
        "addiction",
        "abuse",
        "treatment",
        "drug"
    ],
    "wof:name":"Jericho Mens Home",
    "wof:placetype":"venue"
},
  "geometry": {"coordinates":[-117.692308,34.010909],"type":"Point"}
}