{
  "type": "Feature",
  "properties": {
    "addr:full":"786 N Garey Ave Pomona CA 91767",
    "addr:housenumber":"786",
    "addr:postcode":"91767",
    "addr:street":"N Garey Ave",
    "iso:country":"US",
    "sg:address":"786 N Garey Ave",
    "sg:city":"Pomona",
    "sg:classifiers":[
        {
            "category":"Shopping",
            "subcategory":"Florist",
            "type":"Retail Goods"
        }
    ],
    "sg:phone":"+1 909 622 9840",
    "sg:postcode":"91767",
    "sg:province":"CA",
    "sg:website":"www.ftd.com",
    "wof:name":"Alan's Flowers",
    "wof:placetype":"venue"
},
  "geometry": {"coordinates":[-117.751008,34.065763],"type":"Point"}
}