{
  "type": "Feature",
  "properties": {
    "iso:country":"US",
    "sg:address":"1190 E Santa Clara St",
    "sg:city":"San Jose",
    "sg:classifiers":[
        {
            "category":"Professional",
            "subcategory":"Accounting & Tax Preparation",
            "type":"Services"
        }
    ],
    "sg:phone":"+1 408 995 6677",
    "sg:postcode":"95116",
    "sg:province":"CA",
    "sg:tags":[
        "return",
        "filing"
    ],
    "wof:name":"Santa Clara Income Tax",
    "wof:placetype":"venue"
},
  "geometry": {"coordinates":[-121.867542,37.347011],"type":"Point"}
}