{
  "type": "Feature",
  "properties": {
    "iso:country":"US",
    "sg:address":"2508 Barstow Ave",
    "sg:city":"Clovis",
    "sg:classifiers":[
        {
            "category":"Health Services",
            "subcategory":"Doctor",
            "type":"Services"
        }
    ],
    "sg:phone":"+1 559 298 0403",
    "sg:postcode":"93611",
    "sg:province":"CA",
    "sg:tags":[
        "physician",
        "surgeon"
    ],
    "wof:name":"Anjaleoni Enterprises Inc",
    "wof:placetype":"venue"
},
  "geometry": {"coordinates":[-119.667829,36.815617],"type":"Point"}
}