{
  "type": "Feature",
  "properties": {
    "addr:full":"1310 N Sweetzer Ave Los Angeles CA 90069",
    "addr:housenumber":"1310",
    "addr:postcode":"90069",
    "addr:street":"N Sweetzer Ave",
    "iso:country":"US",
    "sg:address":"1310 N Sweetzer Ave",
    "sg:city":"Los Angeles",
    "sg:classifiers":[
        {
            "category":"Building & Trades",
            "subcategory":"Construction",
            "type":"Services"
        }
    ],
    "sg:phone":"+1 323 654 9135",
    "sg:postcode":"90069",
    "sg:province":"CA",
    "sg:tags":[
        "interior",
        "designer"
    ],
    "wof:name":"Roxane Berger Designs",
    "wof:placetype":"venue"
},
  "geometry": {"coordinates":[-118.370216,34.095301],"type":"Point"}
}