{
  "type": "Feature",
  "properties": {
    "addr:full":"231 Pso Bernal Moraga CA 94556",
    "addr:housenumber":"231",
    "addr:postcode":"94556",
    "addr:street":"Pso Bernal",
    "iso:country":"US",
    "sg:address":"231 Pso Bernal",
    "sg:city":"Moraga",
    "sg:classifiers":[
        {
            "category":"Professional",
            "subcategory":"Management & Consulting",
            "type":"Services"
        }
    ],
    "sg:phone":"+1 925 376 4904",
    "sg:postcode":"94556",
    "sg:province":"CA",
    "sg:tags":[
        "consultant",
        "business"
    ],
    "wof:name":"Terra Management Corp Inc",
    "wof:placetype":"venue"
},
  "geometry": {"coordinates":[-122.122601,37.837851],"type":"Point"}
}