{
  "type": "Feature",
  "properties": {
    "addr:full":"16228 Estella Ave Cerritos CA 90703",
    "addr:postcode":"16228;ca 90703",
    "addr:street":"Estella Ave",
    "iso:country":"US",
    "sg:address":"16228 Estella Ave",
    "sg:city":"Cerritos",
    "sg:classifiers":[
        {
            "category":"Manufacturing",
            "subcategory":"Printing",
            "type":"Manufacturing & Wholesale Goods"
        }
    ],
    "sg:phone":"+1 562 865 2888",
    "sg:postcode":"90703",
    "sg:province":"CA",
    "sg:tags":[
        "marketing",
        "book",
        "publishing"
    ],
    "wof:name":"Wine Treasures",
    "wof:placetype":"venue"
},
  "geometry": {"coordinates":[-118.102215,33.883327],"type":"Point"}
}