{
  "type": "Feature",
  "properties": {
    "iso:country":"US",
    "sg:address":"925 Adams St",
    "sg:city":"Albany",
    "sg:classifiers":[
        {
            "category":"Building & Trades",
            "subcategory":"Landscaping Services",
            "type":"Services"
        }
    ],
    "sg:phone":"+1 510 524 4063",
    "sg:postcode":"94706",
    "sg:province":"CA",
    "sg:tags":[
        "tree"
    ],
    "wof:name":"Otterstad's Brush Clearing Svc",
    "wof:placetype":"venue"
},
  "geometry": {"coordinates":[-122.299272,37.888328],"type":"Point"}
}