{
  "type": "Feature",
  "properties": {
    "addr:full":"1615 Monrovia Ave Costa Mesa CA 92627",
    "addr:postcode":"1615;92627",
    "addr:street":"Monrovia Ave",
    "iso:country":"US",
    "sg:address":"1615 Monrovia Ave",
    "sg:city":"Costa Mesa",
    "sg:classifiers":[
        {
            "category":"Shopping",
            "subcategory":"Computers & Home Electronics",
            "type":"Retail Goods"
        }
    ],
    "sg:phone":"+1 949 515 9496",
    "sg:postcode":"92627",
    "sg:province":"CA",
    "sg:tags":[
        "audio"
    ],
    "wof:name":"Fusion Audio Inc",
    "wof:placetype":"venue"
},
  "geometry": {"coordinates":[-117.936268,33.633226],"type":"Point"}
}