{
  "type": "Feature",
  "properties": {
    "addr:full":"1720 Oregon St Berkeley CA 94703",
    "addr:housenumber":"1720",
    "addr:postcode":"94703",
    "addr:street":"Oregon St",
    "iso:country":"US",
    "sg:address":"1720 Oregon St",
    "sg:city":"Berkeley",
    "sg:classifiers":[
        {
            "category":"Professional",
            "subcategory":"Management & Consulting",
            "type":"Services"
        }
    ],
    "sg:phone":"+1 510 845 3495",
    "sg:postcode":"94703",
    "sg:province":"CA",
    "sg:tags":[
        "construction"
    ],
    "wof:name":"Vanir Construction Mgmt Inc",
    "wof:placetype":"venue"
},
  "geometry": {"coordinates":[-122.27345,37.85674],"type":"Point"}
}