{
  "type": "Feature",
  "properties": {
    "addr:full":"602 Yosemite Ave Manteca CA 95336",
    "addr:housenumber":"602",
    "addr:postcode":"95336",
    "addr:street":"Yosemite Ave",
    "iso:country":"US",
    "sg:address":"602 Yosemite Ave",
    "sg:city":"Manteca",
    "sg:classifiers":[
        {
            "category":"Manufacturing",
            "subcategory":"Printing",
            "type":"Manufacturing & Wholesale Goods"
        }
    ],
    "sg:phone":"+1 209 577 1380",
    "sg:postcode":"95336",
    "sg:province":"CA",
    "sg:tags":[
        "newspaper"
    ],
    "wof:name":"Manteca News",
    "wof:placetype":"venue"
},
  "geometry": {"coordinates":[-121.207916,37.797361],"type":"Point"}
}