{
  "type": "Feature",
  "properties": {
    "addr:full":"1601 N Sepulveda Blvd Manhattan Beach CA 90266",
    "addr:housenumber":"1601",
    "addr:postcode":"90266",
    "addr:street":"N Sepulveda Blvd",
    "iso:country":"US",
    "sg:address":"1601 N Sepulveda Blvd",
    "sg:city":"Manhattan Beach",
    "sg:classifiers":[
        {
            "category":"Banks & Credit Unions",
            "subcategory":"Financial Services",
            "type":"Services"
        }
    ],
    "sg:phone":"+1 310 371 6364",
    "sg:postcode":"90266",
    "sg:province":"CA",
    "sg:tags":[
        "trust",
        "investment",
        "real estate"
    ],
    "wof:name":"Flamingo West",
    "wof:placetype":"venue"
},
  "geometry": {"coordinates":[-118.39604,33.890086],"type":"Point"}
}