{
  "type": "Feature",
  "properties": {
    "addr:full":"5510 Monterey Rd. San Jose CA 95013",
    "addr:housenumber":"5510",
    "addr:postcode":"95013",
    "addr:street":"Monterey Rd.",
    "iso:country":"US",
    "sg:address":"5510 Monterey Rd.",
    "sg:city":"San Jose",
    "sg:classifiers":[
        {
            "category":"Food & Beverages",
            "subcategory":"Groceries & Convenience Stores",
            "type":"Retail Goods"
        }
    ],
    "sg:phone":"+1 408 972 0681",
    "sg:postcode":"95013",
    "sg:province":"CA",
    "sg:website":"www.luckysupermarkets.com",
    "wof:name":"Lucky Supermarket",
    "wof:placetype":"venue"
},
  "geometry": {"coordinates":[-121.738944,37.216149],"type":"Point"}
}