{
  "type": "Feature",
  "properties": {
    "iso:country":"US",
    "sg:address":"207 Dunecrest Ave",
    "sg:city":"Monterey",
    "sg:classifiers":[
        {
            "category":"Health Services",
            "subcategory":"Clinic",
            "type":"Services"
        }
    ],
    "sg:phone":"+1 831 655 9544",
    "sg:postcode":"93940",
    "sg:province":"CA",
    "sg:tags":[
        "welfare"
    ],
    "wof:name":"Dunecrest Associates",
    "wof:placetype":"venue"
},
  "geometry": {"coordinates":[-121.86647000000001,36.603356],"type":"Point"}
}