{
  "type": "Feature",
  "properties": {
    "addr:full":"130 Dore St San Francisco CA 94103",
    "addr:housenumber":"130",
    "addr:postcode":"94103",
    "addr:street":"Dore St",
    "iso:country":"US",
    "sg:address":"130 Dore St",
    "sg:city":"San Francisco",
    "sg:classifiers":[
        {
            "category":"Building & Trades",
            "subcategory":"Construction",
            "type":"Services"
        }
    ],
    "sg:phone":"+1 415 550 6691",
    "sg:postcode":"94103",
    "sg:province":"CA",
    "sg:tags":[
        "contractor"
    ],
    "wof:name":"TCB Builders",
    "wof:placetype":"venue"
},
  "geometry": {"coordinates":[-122.411996,37.77285],"type":"Point"}
}