{
  "type": "Feature",
  "properties": {
    "addr:full":"12000 Firestone Blvd Norwalk CA 90650",
    "addr:housenumber":"12000",
    "addr:postcode":"90650",
    "addr:street":"Firestone Blvd",
    "iso:country":"US",
    "sg:address":"12000 Firestone Blvd",
    "sg:city":"Norwalk",
    "sg:classifiers":[
        {
            "category":"Autos & Motor Vehicles",
            "subcategory":"Automobile Sales",
            "type":"Retail Goods"
        },
        {
            "category":"Retail",
            "subcategory":"Auto Repair",
            "type":"Services"
        }
    ],
    "sg:phone":"+1 562 372 5111",
    "sg:postcode":"90650",
    "sg:province":"CA",
    "sg:tags":[
        "car"
    ],
    "wof:name":"Keystone Ford Inc",
    "wof:placetype":"venue"
},
  "geometry": {"coordinates":[-118.077003,33.909801],"type":"Point"}
}