{
  "type": "Feature",
  "properties": {
    "iso:country":"US",
    "sg:address":"8347 Tamarind Ave",
    "sg:city":"Fontana",
    "sg:classifiers":[
        {
            "category":"Organizations",
            "subcategory":"Community Association",
            "type":"Services"
        }
    ],
    "sg:phone":"+1 909 997 5724",
    "sg:postcode":"92335",
    "sg:province":"CA",
    "sg:tags":[
        "club"
    ],
    "wof:name":"Fontana Boxing Club",
    "wof:placetype":"venue"
},
  "geometry": {"coordinates":[-117.422736,34.101106],"type":"Point"}
}