{
  "type": "Feature",
  "properties": {
    "iso:country":"US",
    "sg:address":"7200 Greenleaf Ave",
    "sg:city":"Whittier",
    "sg:classifiers":[
        {
            "category":"Social Services",
            "type":"Services"
        }
    ],
    "sg:phone":"+1 562 693 8826",
    "sg:postcode":"90602",
    "sg:province":"CA",
    "sg:tags":[
        "organization",
        "welfare"
    ],
    "sg:website":"www.capcinc.org",
    "wof:name":"CAPC Adult Svc",
    "wof:placetype":"venue"
},
  "geometry": {"coordinates":[-118.03733800000001,33.97546],"type":"Point"}
}