{
  "type": "Feature",
  "properties": {
    "addr:full":"15777 del Obisbo Rd Fontana CA 92337",
    "addr:housenumber":"15777",
    "addr:postcode":"92337",
    "addr:street":"Del Obisbo Rd",
    "iso:country":"US",
    "sg:address":"15777 del Obisbo Rd",
    "sg:city":"Fontana",
    "sg:classifiers":[
        {
            "category":"Shopping",
            "subcategory":"Gifts & Souvenirs",
            "type":"Retail Goods"
        }
    ],
    "sg:phone":"+1 909 574 8746",
    "sg:postcode":"92337",
    "sg:province":"CA",
    "sg:tags":[
        "party",
        "supply"
    ],
    "wof:name":"B & J Jumpers",
    "wof:placetype":"venue"
},
  "geometry": {"coordinates":[-117.46069199999999,34.047544],"type":"Point"}
}