{
  "type": "Feature",
  "properties": {
    "addr:full":"1791 Southgate St Hayward CA 94545",
    "addr:housenumber":"1791",
    "addr:postcode":"94545",
    "addr:street":"Southgate St",
    "iso:country":"US",
    "sg:address":"1791 Southgate St",
    "sg:city":"Hayward",
    "sg:classifiers":[
        {
            "category":"Airline",
            "type":"Transportation"
        }
    ],
    "sg:phone":"+1 510 783 0136",
    "sg:postcode":"94545",
    "sg:province":"CA",
    "sg:tags":[
        "shuttle",
        "airport"
    ],
    "wof:name":"Amei Airport Service",
    "wof:placetype":"venue"
},
  "geometry": {"coordinates":[-122.093002,37.636398],"type":"Point"}
}