{
  "type": "Feature",
  "properties": {
    "iso:country":"US",
    "sg:address":"967 Beach Crest Ct",
    "sg:city":"Carlsbad",
    "sg:classifiers":[
        {
            "category":"Professional",
            "subcategory":"Advertising",
            "type":"Services"
        }
    ],
    "sg:phone":"+1 760 431 0895",
    "sg:postcode":"92011",
    "sg:province":"CA",
    "wof:name":"Alpha Promotions",
    "wof:placetype":"venue"
},
  "geometry": {"coordinates":[-117.312382,33.11814],"type":"Point"}
}