{
  "type": "Feature",
  "properties": {
    "addr:full":"2007 W 78th St Los Angeles CA 90047",
    "addr:housenumber":"2007",
    "addr:postcode":"90047",
    "addr:street":"W 78Th St",
    "iso:country":"US",
    "sg:address":"2007 W 78th St",
    "sg:city":"Los Angeles",
    "sg:classifiers":[
        {
            "category":"Manufacturing",
            "subcategory":"Tools & Machinery",
            "type":"Manufacturing & Wholesale Goods"
        }
    ],
    "sg:phone":"+1 323 971 6541",
    "sg:postcode":"90047",
    "sg:province":"CA",
    "sg:tags":[
        "industry",
        "mfg"
    ],
    "wof:name":"Mida Business Concepts",
    "wof:placetype":"venue"
},
  "geometry": {"coordinates":[-118.315445,33.969157],"type":"Point"}
}