{
  "type": "Feature",
  "properties": {
    "iso:country":"US",
    "sg:address":"1206 Main St",
    "sg:city":"Fortuna",
    "sg:classifiers":[
        {
            "category":"Restaurant",
            "type":"Food & Drink"
        }
    ],
    "sg:phone":"+1 707 725 3998",
    "sg:postcode":"95540",
    "sg:province":"CA",
    "wof:name":"Redwood Cafe",
    "wof:placetype":"venue"
},
  "geometry": {"coordinates":[-124.15440099999999,40.59806],"type":"Point"}
}