{
  "type": "Feature",
  "properties": {
    "addr:full":"970 Chorro St San Luis Obispo CA 93401",
    "addr:housenumber":"970",
    "addr:postcode":"93401",
    "addr:street":"Chorro St",
    "iso:country":"US",
    "sg:address":"970 Chorro St",
    "sg:city":"San Luis Obispo",
    "sg:classifiers":[
        {
            "category":"Personal",
            "subcategory":"Massage",
            "type":"Services"
        }
    ],
    "sg:phone":"+1 805 787 0970",
    "sg:postcode":"93401",
    "sg:province":"CA",
    "sg:website":"www.ifoundbliss.com",
    "wof:name":"Bliss Body Spa",
    "wof:placetype":"venue"
},
  "geometry": {"coordinates":[-120.663445,35.280638],"type":"Point"}
}