{
  "type": "Feature",
  "properties": {
    "addr:full":"24309 San Fernando Rd Santa Clarita CA 91321",
    "addr:housenumber":"24309",
    "addr:postcode":"91321",
    "addr:street":"San Fernando Rd",
    "iso:country":"US",
    "sg:address":"24309 San Fernando Rd",
    "sg:city":"Santa Clarita",
    "sg:classifiers":[
        {
            "category":"Retail",
            "subcategory":"Self-service Laundry",
            "type":"Services"
        }
    ],
    "sg:phone":"+1 661 253 2773",
    "sg:postcode":"91321",
    "sg:province":"CA",
    "wof:name":"Newhall Coin Laundry",
    "wof:placetype":"venue"
},
  "geometry": {"coordinates":[-118.528003,34.378799],"type":"Point"}
}