{
  "type": "Feature",
  "properties": {
    "addr:full":"1618 Union Street San Francisco CA 94123",
    "addr:housenumber":"1618",
    "addr:postcode":"94123",
    "addr:street":"Union Street",
    "iso:country":"US",
    "sg:address":"1618 Union Street",
    "sg:city":"San Francisco",
    "sg:classifiers":[
        {
            "category":"Personal",
            "subcategory":"Hair Removal",
            "type":"Services"
        }
    ],
    "sg:phone":"+1 415 516 3018",
    "sg:postcode":"94123",
    "sg:province":"CA",
    "wof:name":"Carrie Jossel Waxing @ Union Retreat",
    "wof:placetype":"venue"
},
  "geometry": {"coordinates":[-122.42600899999999,37.798391],"type":"Point"}
}