{
  "type": "Feature",
  "properties": {
    "addr:full":"410 S Melrose Dr Ste 101 Vista CA 92081",
    "addr:housenumber":"410",
    "addr:postcode":"92081",
    "addr:street":"S Melrose Dr Ste 101",
    "iso:country":"US",
    "sg:address":"410 S Melrose Dr Ste 101",
    "sg:city":"Vista",
    "sg:classifiers":[
        {
            "category":"Health Services",
            "subcategory":"Health Practitioner",
            "type":"Services"
        }
    ],
    "sg:phone":"+1 760 690 1147",
    "sg:postcode":"92081",
    "sg:province":"CA",
    "sg:tags":[
        "home",
        "care"
    ],
    "wof:name":"Right at Home",
    "wof:placetype":"venue"
},
  "geometry": {"coordinates":[-117.25371,33.190427],"type":"Point"}
}