{
  "type": "Feature",
  "properties": {
    "iso:country":"US",
    "sg:address":"2850 Artesia Blvd",
    "sg:city":"Redondo Beach",
    "sg:classifiers":[
        {
            "category":"Personal",
            "type":"Services"
        }
    ],
    "sg:phone":"+1 310 921 3585",
    "sg:postcode":"90278",
    "sg:province":"CA",
    "sg:tags":[
        "therapist",
        "massage"
    ],
    "wof:name":"Radiant Massage Therapy",
    "wof:placetype":"venue"
},
  "geometry": {"coordinates":[-118.358828,33.872856],"type":"Point"}
}