{
  "type": "Feature",
  "properties": {
    "iso:country":"US",
    "sg:address":"1042 Florin Rd",
    "sg:city":"Sacramento",
    "sg:classifiers":[
        {
            "category":"Coffee & Tea",
            "type":"Food & Drink"
        }
    ],
    "sg:menulink":"http://www.allmenus.com/ca/sacramento/108839-starbucks-coffee/menu/",
    "sg:phone":"+1 916 427 9312",
    "sg:postcode":"95831",
    "sg:province":"CA",
    "sg:tags":[
        "american"
    ],
    "wof:name":"Starbucks Coffee",
    "wof:placetype":"venue"
},
  "geometry": {"coordinates":[-121.52087899999999,38.495176],"type":"Point"}
}