{
  "type": "Feature",
  "properties": {
    "iso:country":"US",
    "sg:address":"3920 Coronado St",
    "sg:city":"Anaheim",
    "sg:classifiers":[
        {
            "category":"Professional",
            "subcategory":"Advertising",
            "type":"Services"
        }
    ],
    "sg:phone":"+1 714 632 8425",
    "sg:postcode":"92807",
    "sg:province":"CA",
    "wof:name":"Impressions",
    "wof:placetype":"venue"
},
  "geometry": {"coordinates":[-117.832875,33.859145],"type":"Point"}
}