{
  "type": "Feature",
  "properties": {
    "iso:country":"US",
    "sg:address":"320 9th St",
    "sg:city":"Modesto",
    "sg:classifiers":[
        {
            "category":"Real Estate",
            "subcategory":"Real Estate Services",
            "type":"Services"
        },
        {
            "category":"Animal Shelter",
            "type":"Public Place"
        }
    ],
    "sg:phone":"+1 209 529 7507",
    "sg:postcode":"95351",
    "sg:province":"CA",
    "sg:tags":[
        "consultant",
        "housing",
        "referral"
    ],
    "wof:name":"Transitional Housing",
    "wof:placetype":"venue"
},
  "geometry": {"coordinates":[-120.99345099999999,37.633264],"type":"Point"}
}