{
  "type": "Feature",
  "properties": {
    "addr:full":"3208 Danville Blvd Alamo CA 94507",
    "addr:housenumber":"3208",
    "addr:postcode":"94507",
    "addr:street":"Danville Blvd",
    "iso:country":"US",
    "sg:address":"3208 Danville Blvd",
    "sg:city":"Alamo",
    "sg:classifiers":[
        {
            "category":"Personal",
            "subcategory":"Nail Salon",
            "type":"Services"
        }
    ],
    "sg:phone":"+1 925 820 3189",
    "sg:postcode":"94507",
    "sg:province":"CA",
    "wof:name":"New York Nails",
    "wof:placetype":"venue"
},
  "geometry": {"coordinates":[-122.195572,37.849621],"type":"Point"}
}