{
  "type": "Feature",
  "properties": {
    "iso:country":"US",
    "sg:address":"1253 Urania Ave",
    "sg:city":"Encinitas",
    "sg:classifiers":[
        {
            "category":"Home & Garden",
            "subcategory":"Garden Supply",
            "type":"Retail Goods"
        }
    ],
    "sg:phone":"+1 760 436 0194",
    "sg:postcode":"92024",
    "sg:province":"CA",
    "sg:tags":[
        "nursery",
        "gardening"
    ],
    "wof:name":"Chino Greenhouses Inc",
    "wof:placetype":"venue"
},
  "geometry": {"coordinates":[-117.290001,33.071201],"type":"Point"}
}