{
  "type": "Feature",
  "properties": {
    "iso:country":"US",
    "sg:address":"1777 W Arrow Rte",
    "sg:city":"Upland",
    "sg:classifiers":[
        {
            "category":"Building & Trades",
            "subcategory":"Construction",
            "type":"Services"
        }
    ],
    "sg:phone":"+1 909 946 1272",
    "sg:postcode":"91786",
    "sg:province":"CA",
    "sg:tags":[
        "resurfacing",
        "laying",
        "refinishing",
        "floor"
    ],
    "wof:name":"Trend West Flooring",
    "wof:placetype":"venue"
},
  "geometry": {"coordinates":[-117.68492000000001,34.099683],"type":"Point"}
}