{
  "type": "Feature",
  "properties": {
    "addr:full":"14748 Bethany St San Leandro CA 94579",
    "addr:housenumber":"14748",
    "addr:postcode":"94579",
    "addr:street":"Bethany St",
    "iso:country":"US",
    "sg:address":"14748 Bethany St",
    "sg:city":"San Leandro",
    "sg:classifiers":[
        {
            "category":"Building & Trades",
            "subcategory":"Plumbing",
            "type":"Services"
        }
    ],
    "sg:phone":"+1 510 346 8828",
    "sg:postcode":"94579",
    "sg:province":"CA",
    "wof:name":"Clausen-Patten",
    "wof:placetype":"venue"
},
  "geometry": {"coordinates":[-122.154982,37.697742],"type":"Point"}
}