{
  "type": "Feature",
  "properties": {
    "iso:country":"US",
    "sg:address":"1363 Hermes Ave",
    "sg:city":"Encinitas",
    "sg:classifiers":[
        {
            "category":"Shopping",
            "subcategory":"Clothing, Apparel, & Fashions",
            "type":"Retail Goods"
        }
    ],
    "sg:phone":"+1 760 753 7883",
    "sg:postcode":"92024",
    "sg:province":"CA",
    "wof:name":"S B Clothing",
    "wof:placetype":"venue"
},
  "geometry": {"coordinates":[-117.302544,33.072321],"type":"Point"}
}