{
  "type": "Feature",
  "properties": {
    "addr:full":"3637 Church St Occidental CA 95465",
    "addr:housenumber":"3637",
    "addr:postcode":"95465",
    "addr:street":"Church St",
    "iso:country":"US",
    "sg:address":"3637 Church St",
    "sg:city":"Occidental",
    "sg:classifiers":[
        {
            "category":"Organizations",
            "subcategory":"Religious Organization",
            "type":"Services"
        }
    ],
    "sg:phone":"+1 707 874 3501",
    "sg:postcode":"95465",
    "sg:province":"CA",
    "sg:tags":[
        "church"
    ],
    "wof:name":"Occidental Community Church",
    "wof:placetype":"venue"
},
  "geometry": {"coordinates":[-122.946736,38.407303],"type":"Point"}
}