{
  "type": "Feature",
  "properties": {
    "addr:full":"1439 Foxworthy Ave San Jose CA 95118",
    "addr:housenumber":"1439",
    "addr:postcode":"95118",
    "addr:street":"Foxworthy Ave",
    "iso:country":"US",
    "sg:address":"1439 Foxworthy Ave",
    "sg:city":"San Jose",
    "sg:classifiers":[
        {
            "category":"Shopping",
            "type":"Retail Goods"
        }
    ],
    "sg:phone":"+1 408 269 3888",
    "sg:postcode":"95118",
    "sg:province":"CA",
    "sg:tags":[
        "pet",
        "food",
        "supply"
    ],
    "wof:name":"Noah's Ark",
    "wof:placetype":"venue"
},
  "geometry": {"coordinates":[-121.891696,37.275074],"type":"Point"}
}