{
  "type": "Feature",
  "properties": {
    "addr:full":"2600 N Figueroa Street Los Angeles CA 90065",
    "addr:housenumber":"2600",
    "addr:postcode":"90065",
    "addr:street":"N Figueroa Street",
    "iso:country":"US",
    "sg:address":"2600 N Figueroa Street",
    "sg:city":"Los Angeles",
    "sg:classifiers":[
        {
            "category":"Autos & Motor Vehicles",
            "subcategory":"Fuel & Gas Station",
            "type":"Retail Goods"
        }
    ],
    "sg:phone":"+1 323 222 4595",
    "sg:postcode":"90065",
    "sg:province":"CA",
    "wof:name":"Andy's Gas and Foodmart",
    "wof:placetype":"venue"
},
  "geometry": {"coordinates":[-118.222149,34.083933],"type":"Point"}
}