{
  "type": "Feature",
  "properties": {
    "iso:country":"US",
    "sg:address":"27555 Ynez Rd",
    "sg:city":"Temecula",
    "sg:classifiers":[
        {
            "category":"Real Estate",
            "subcategory":"Real Estate Operator",
            "type":"Services"
        }
    ],
    "sg:phone":"+1 951 694 3500",
    "sg:postcode":"92591",
    "sg:province":"CA",
    "sg:tags":[
        "building",
        "parks"
    ],
    "wof:name":"Tower Office Plaza",
    "wof:placetype":"venue"
},
  "geometry": {"coordinates":[-117.15006,33.506348],"type":"Point"}
}