{
  "type": "Feature",
  "properties": {
    "addr:full":"220 E 5th St Long Beach CA 90802",
    "addr:housenumber":"220",
    "addr:postcode":"90802",
    "addr:street":"E 5Th St",
    "iso:country":"US",
    "sg:address":"220 E 5th St",
    "sg:city":"Long Beach",
    "sg:classifiers":[
        {
            "category":"Shopping",
            "subcategory":"Jewelry",
            "type":"Retail Goods"
        }
    ],
    "sg:phone":"+1 562 495 3300",
    "sg:postcode":"90802",
    "sg:province":"CA",
    "sg:tags":[
        "jeweler"
    ],
    "wof:name":"Crescent Jewelers",
    "wof:placetype":"venue"
},
  "geometry": {"coordinates":[-118.191093,33.772864],"type":"Point"}
}