{
  "type": "Feature",
  "properties": {
    "iso:country":"US",
    "sg:address":"1914 S Pacific Coast Hwy",
    "sg:city":"Redondo Beach",
    "sg:classifiers":[
        {
            "category":"Travel",
            "subcategory":"Travel Agent",
            "type":"Entertainment"
        }
    ],
    "sg:phone":"+1 310 540 7767",
    "sg:postcode":"90277",
    "sg:province":"CA",
    "sg:tags":[
        "agency",
        "bureau"
    ],
    "sg:website":"www.findacruisedeal.com",
    "wof:name":"FINDACRUISEDEAL.COM",
    "wof:placetype":"venue"
},
  "geometry": {"coordinates":[-118.376865,33.815889],"type":"Point"}
}