{
  "type": "Feature",
  "properties": {
    "addr:full":"2401 West Beverly Blvd Montebello CA 90640",
    "addr:housenumber":"2401",
    "addr:postcode":"90640",
    "addr:street":"West Beverly Blvd",
    "iso:country":"US",
    "sg:address":"2401 West Beverly Blvd",
    "sg:city":"Montebello",
    "sg:classifiers":[
        {
            "category":"Bakery",
            "type":"Food & Drink"
        }
    ],
    "sg:phone":"+1 323 722 8706",
    "sg:postcode":"90640",
    "sg:province":"CA",
    "wof:name":"Hye Bakery",
    "wof:placetype":"venue"
},
  "geometry": {"coordinates":[-118.126029,34.021123],"type":"Point"}
}