{
  "type": "Feature",
  "properties": {
    "iso:country":"US",
    "sg:address":"34249 Fremont Blvd",
    "sg:city":"Fremont",
    "sg:classifiers":[
        {
            "category":"Professional",
            "type":"Services"
        }
    ],
    "sg:phone":"+1 510 505 0638",
    "sg:postcode":"94555",
    "sg:province":"CA",
    "wof:name":"Louisa Kim",
    "wof:placetype":"venue"
},
  "geometry": {"coordinates":[-122.04348,37.576142],"type":"Point"}
}