{
  "type": "Feature",
  "properties": {
    "iso:country":"US",
    "sg:address":"9501 Lokern Rd",
    "sg:city":"Mc Kittrick",
    "sg:classifiers":[
        {
            "category":"Farming",
            "subcategory":"Livestock Farm",
            "type":"Manufacturing & Wholesale Goods"
        }
    ],
    "sg:phone":"+1 661 762 7528",
    "sg:postcode":"93251",
    "sg:province":"CA",
    "sg:tags":[
        "feedlot",
        "cattle",
        "animal",
        "beef",
        "general"
    ],
    "wof:name":"Tembler Ranch",
    "wof:placetype":"venue"
},
  "geometry": {"coordinates":[-119.731503,35.397475],"type":"Point"}
}