{
  "type": "Feature",
  "properties": {
    "addr:full":"473 King St Redwood City CA 94062",
    "addr:housenumber":"473",
    "addr:postcode":"94062",
    "addr:street":"King St",
    "iso:country":"US",
    "sg:address":"473 King St",
    "sg:city":"Redwood City",
    "sg:classifiers":[
        {
            "category":"Building & Trades",
            "subcategory":"Construction",
            "type":"Services"
        }
    ],
    "sg:phone":"+1 650 299 9114",
    "sg:postcode":"94062",
    "sg:province":"CA",
    "sg:tags":[
        "contractor"
    ],
    "wof:name":"Bay Counties Roofing",
    "wof:placetype":"venue"
},
  "geometry": {"coordinates":[-122.240848,37.477546],"type":"Point"}
}