{
  "type": "Feature",
  "properties": {
    "addr:full":"943 Vernon Way El Cajon CA 92020",
    "addr:housenumber":"943",
    "addr:postcode":"92020",
    "addr:street":"Vernon Way",
    "iso:country":"US",
    "sg:address":"943 Vernon Way",
    "sg:city":"El Cajon",
    "sg:classifiers":[
        {
            "category":"Autos & Motor Vehicles",
            "subcategory":"Automobile Sales",
            "type":"Retail Goods"
        }
    ],
    "sg:phone":"+1 619 449 7100",
    "sg:postcode":"92020",
    "sg:province":"CA",
    "sg:tags":[
        "buggy",
        "dune"
    ],
    "sg:website":"www.chenowth.com",
    "wof:name":"Chenowth Racing Products",
    "wof:placetype":"venue"
},
  "geometry": {"coordinates":[-116.97124599999999,32.812331],"type":"Point"}
}