{
  "type": "Feature",
  "properties": {
    "iso:country":"US",
    "sg:address":"3127 Saviers Rd",
    "sg:city":"Oxnard",
    "sg:classifiers":[
        {
            "category":"Food & Beverages",
            "subcategory":"Fruits & Vegetables",
            "type":"Retail Goods"
        }
    ],
    "sg:phone":"+1 805 486 5454",
    "sg:postcode":"93033",
    "sg:province":"CA",
    "sg:tags":[
        "produce"
    ],
    "wof:name":"Cervantes Produce",
    "wof:placetype":"venue"
},
  "geometry": {"coordinates":[-119.177651,34.17233],"type":"Point"}
}