{
  "type": "Feature",
  "properties": {
    "addr:full":"2801 W Valley Blvd Alhambra CA 91803",
    "addr:housenumber":"2801",
    "addr:postcode":"91803",
    "addr:street":"W Valley Blvd",
    "iso:country":"US",
    "sg:address":"2801 W Valley Blvd",
    "sg:city":"Alhambra",
    "sg:classifiers":[
        {
            "category":"Shopping",
            "subcategory":"Thrift Store",
            "type":"Retail Goods"
        }
    ],
    "sg:phone":"+1 626 289 6440",
    "sg:postcode":"91803",
    "sg:province":"CA",
    "wof:name":"Victory Outreach Second Time Around Thrift Store",
    "wof:placetype":"venue"
},
  "geometry": {"coordinates":[-118.154104,34.076998],"type":"Point"}
}