{
  "type": "Feature",
  "properties": {
    "iso:country":"US",
    "sg:address":"16091 Kamana Rd",
    "sg:city":"Apple Valley",
    "sg:classifiers":[
        {
            "category":"Autos & Motor Vehicles",
            "subcategory":"Motorcycle Sales",
            "type":"Retail Goods"
        }
    ],
    "sg:phone":"+1 760 242 9111",
    "sg:postcode":"92307",
    "sg:province":"CA",
    "sg:tags":[
        "scooter"
    ],
    "wof:name":"Atlas Precision Pro Magnum",
    "wof:placetype":"venue"
},
  "geometry": {"coordinates":[-117.270701,34.543229],"type":"Point"}
}