{
  "type": "Feature",
  "properties": {
    "addr:full":"2602 Laird St Santa Ana CA 92706",
    "addr:housenumber":"2602",
    "addr:postcode":"92706",
    "addr:street":"Laird St",
    "iso:country":"US",
    "sg:address":"2602 Laird St",
    "sg:city":"Santa Ana",
    "sg:classifiers":[
        {
            "category":"Manufacturing",
            "subcategory":"Metals",
            "type":"Manufacturing & Wholesale Goods"
        }
    ],
    "sg:phone":"+1 714 971 9771",
    "sg:postcode":"92706",
    "sg:province":"CA",
    "sg:tags":[
        "mfg",
        "contractor",
        "architectural",
        "metalwork",
        "trade"
    ],
    "wof:name":"Lennys Portable Welding Svc",
    "wof:placetype":"venue"
},
  "geometry": {"coordinates":[-117.899412,33.771815],"type":"Point"}
}