{
  "type": "Feature",
  "properties": {
    "iso:country":"US",
    "sg:address":"304 W Bunny Ave",
    "sg:city":"Santa Maria",
    "sg:classifiers":[
        {
            "category":"Building & Trades",
            "subcategory":"Landscaping Services",
            "type":"Services"
        }
    ],
    "sg:phone":"+1 805 928 6435",
    "sg:postcode":"93458",
    "sg:province":"CA",
    "sg:tags":[
        "landscape",
        "contractor"
    ],
    "wof:name":"Natures Way Landscaping",
    "wof:placetype":"venue"
},
  "geometry": {"coordinates":[-120.438832,34.963559],"type":"Point"}
}