{
  "type": "Feature",
  "properties": {
    "iso:country":"US",
    "sg:address":"3714 Mission Blvd",
    "sg:city":"San Diego",
    "sg:classifiers":[
        {
            "category":"Restaurant",
            "type":"Food & Drink"
        }
    ],
    "sg:phone":"+1 858 488 6688",
    "sg:postcode":"92109",
    "sg:province":"CA",
    "sg:tags":[
        "new",
        "american"
    ],
    "sg:website":"www.guava-beach.com",
    "wof:name":"Guava Beach Bar & Grill",
    "wof:placetype":"venue"
},
  "geometry": {"coordinates":[-117.251999,32.782902],"type":"Point"}
}