{
  "type": "Feature",
  "properties": {
    "iso:country":"US",
    "sg:address":"801 I St",
    "sg:city":"Sacramento",
    "sg:classifiers":[
        {
            "category":"Government",
            "subcategory":"Office",
            "type":"Public Place"
        }
    ],
    "sg:phone":"+1 916 498 6654",
    "sg:postcode":"95814",
    "sg:province":"CA",
    "sg:tags":[
        "federal",
        "program",
        "social",
        "human",
        "manpower"
    ],
    "wof:name":"Railroad Retirement Board US",
    "wof:placetype":"venue"
},
  "geometry": {"coordinates":[-121.49434,38.581759],"type":"Point"}
}