{
  "type": "Feature",
  "properties": {
    "addr:full":"25151 Granville St Moreno Valley CA 92551",
    "addr:housenumber":"25151",
    "addr:postcode":"92551",
    "addr:street":"Granville St",
    "iso:country":"US",
    "sg:address":"25151 Granville St",
    "sg:city":"Moreno Valley",
    "sg:classifiers":[
        {
            "category":"Freight",
            "type":"Transportation"
        }
    ],
    "sg:phone":"+1 951 601 1433",
    "sg:postcode":"92551",
    "sg:province":"CA",
    "sg:tags":[
        "operator",
        "local",
        "trucking"
    ],
    "wof:name":"Today Delivery",
    "wof:placetype":"venue"
},
  "geometry": {"coordinates":[-117.223624,33.880432],"type":"Point"}
}