{
  "type": "Feature",
  "properties": {
    "iso:country":"US",
    "sg:address":"2140 Walnut Ct",
    "sg:city":"Rescue",
    "sg:classifiers":[
        {
            "category":"Building & Trades",
            "subcategory":"Construction",
            "type":"Services"
        }
    ],
    "sg:phone":"+1 530 677 3924",
    "sg:postcode":"95672",
    "sg:province":"CA",
    "sg:tags":[
        "general"
    ],
    "wof:name":"R T English Construction Co",
    "wof:placetype":"venue"
},
  "geometry": {"coordinates":[-120.96983,38.694138],"type":"Point"}
}