{
  "type": "Feature",
  "properties": {
    "iso:country":"US",
    "sg:address":"1109 Via Verde",
    "sg:city":"San Dimas",
    "sg:classifiers":[
        {
            "category":"Professional",
            "subcategory":"Accounting & Tax Preparation",
            "type":"Services"
        }
    ],
    "sg:phone":"+1 909 599 1412",
    "sg:postcode":"91773",
    "sg:province":"CA",
    "sg:tags":[
        "bookkeeping",
        "general"
    ],
    "wof:name":"Automated Financial Svc",
    "wof:placetype":"venue"
},
  "geometry": {"coordinates":[-117.828642,34.074315],"type":"Point"}
}