{
  "type": "Feature",
  "properties": {
    "iso:country":"US",
    "sg:address":"1205 Lamberton Cir",
    "sg:city":"Sacramento",
    "sg:classifiers":[
        {
            "category":"Wholesale",
            "subcategory":"Computers",
            "type":"Manufacturing & Wholesale Goods"
        }
    ],
    "sg:phone":"+1 916 568 9776",
    "sg:postcode":"95838",
    "sg:province":"CA",
    "sg:tags":[
        "equipment"
    ],
    "wof:name":"Blue Tech Inc",
    "wof:placetype":"venue"
},
  "geometry": {"coordinates":[-121.43721499999999,38.646673],"type":"Point"}
}