{
  "type": "Feature",
  "properties": {
    "iso:country":"US",
    "sg:address":"668 Brenda Lee Dr",
    "sg:city":"San Jose",
    "sg:classifiers":[
        {
            "category":"Travel",
            "subcategory":"Hotels & Motels",
            "type":"Entertainment"
        }
    ],
    "sg:phone":"+1 408 970 6110",
    "sg:postcode":"95123",
    "sg:province":"CA",
    "wof:name":"Marriott",
    "wof:placetype":"venue"
},
  "geometry": {"coordinates":[-121.833909,37.229149],"type":"Point"}
}