{
  "type": "Feature",
  "properties": {
    "iso:country":"US",
    "sg:address":"72820 Ramon Rd",
    "sg:city":"Thousand Palms",
    "sg:classifiers":[
        {
            "category":"Autos & Motor Vehicles",
            "subcategory":"Automobile Sales",
            "type":"Retail Goods"
        }
    ],
    "sg:phone":"+1 760 343 0544",
    "sg:postcode":"92276",
    "sg:province":"CA",
    "sg:tags":[
        "car",
        "dealer"
    ],
    "wof:name":"Cars 4 Less",
    "wof:placetype":"venue"
},
  "geometry": {"coordinates":[-116.391187,33.816486],"type":"Point"}
}