{
  "type": "Feature",
  "properties": {
    "iso:country":"US",
    "sg:address":"321 Georgetown Ave",
    "sg:city":"San Mateo",
    "sg:classifiers":[
        {
            "category":"Real Estate",
            "subcategory":"Real Estate Agent",
            "type":"Services"
        }
    ],
    "sg:phone":"+1 650 343 1643",
    "sg:postcode":"94402",
    "sg:province":"CA",
    "wof:name":"Tennant-Mac Donald Co",
    "wof:placetype":"venue"
},
  "geometry": {"coordinates":[-122.32782,37.55518],"type":"Point"}
}