{
  "type": "Feature",
  "properties": {
    "iso:country":"US",
    "sg:address":"22647 Ventura Blvd",
    "sg:city":"Woodland Hills",
    "sg:classifiers":[
        {
            "category":"Professional",
            "subcategory":"Management & Consulting",
            "type":"Services"
        }
    ],
    "sg:phone":"+1 818 883 5300",
    "sg:postcode":"91364",
    "sg:province":"CA",
    "sg:tags":[
        "consultant",
        "specification"
    ],
    "wof:name":"Jerome Orland",
    "wof:placetype":"venue"
},
  "geometry": {"coordinates":[-118.620042,34.167184],"type":"Point"}
}