{
  "type": "Feature",
  "properties": {
    "addr:full":"255 W Court St Ste B Woodland CA 95695",
    "addr:housenumber":"255",
    "addr:postcode":"95695",
    "addr:street":"W Court St Ste B",
    "iso:country":"US",
    "sg:address":"255 W Court St Ste B",
    "sg:city":"Woodland",
    "sg:classifiers":[
        {
            "category":"Structure",
            "subcategory":"Office Building",
            "type":"Public Place"
        }
    ],
    "sg:phone":"+1 530 661 1811",
    "sg:postcode":"95695",
    "sg:province":"CA",
    "sg:tags":[
        "park"
    ],
    "wof:name":"Executive Park Professionals",
    "wof:placetype":"venue"
},
  "geometry": {"coordinates":[-121.79509,38.67894],"type":"Point"}
}