{
  "type": "Feature",
  "properties": {
    "addr:full":"1058 Lake Blvd Redding CA 96003",
    "addr:housenumber":"1058",
    "addr:postcode":"96003",
    "addr:street":"Lake Blvd",
    "iso:country":"US",
    "sg:address":"1058 Lake Blvd",
    "sg:city":"Redding",
    "sg:classifiers":[
        {
            "category":"Retail",
            "subcategory":"Repair Shop",
            "type":"Services"
        }
    ],
    "sg:phone":"+1 530 243 7118",
    "sg:postcode":"96003",
    "sg:province":"CA",
    "sg:tags":[
        "related"
    ],
    "wof:name":"Shasta County Customs",
    "wof:placetype":"venue"
},
  "geometry": {"coordinates":[-122.404205,40.623218],"type":"Point"}
}