{
  "type": "Feature",
  "properties": {
    "addr:full":"515 Embarcadero W Oakland CA 94607",
    "addr:housenumber":"515",
    "addr:postcode":"94607",
    "addr:street":"Embarcadero W",
    "iso:country":"US",
    "sg:address":"515 Embarcadero W",
    "sg:city":"Oakland",
    "sg:classifiers":[
        {
            "category":"Restaurant",
            "type":"Food & Drink"
        }
    ],
    "sg:menulink":"http://www.allmenus.com/ca/oakland/60053-subway/menu/",
    "sg:phone":"+1 510 663 3030",
    "sg:postcode":"94607",
    "sg:province":"CA",
    "sg:tags":[
        "american",
        "sandwich"
    ],
    "wof:name":"Subway",
    "wof:placetype":"venue"
},
  "geometry": {"coordinates":[-122.278488,37.795994],"type":"Point"}
}