{
  "type": "Feature",
  "properties": {
    "iso:country":"US",
    "sg:address":"258 Vernon St",
    "sg:city":"San Francisco",
    "sg:classifiers":[
        {
            "category":"Freight",
            "type":"Transportation"
        }
    ],
    "sg:phone":"+1 415 452 8196",
    "sg:postcode":"94132",
    "sg:province":"CA",
    "sg:tags":[
        "operator",
        "trucking"
    ],
    "wof:name":"New Home Moving Co",
    "wof:placetype":"venue"
},
  "geometry": {"coordinates":[-122.467952,37.716837],"type":"Point"}
}