{
  "type": "Feature",
  "properties": {
    "addr:full":"1666 N Main St Santa Ana CA 92701",
    "addr:housenumber":"1666",
    "addr:postcode":"92701",
    "addr:street":"N Main St",
    "iso:country":"US",
    "sg:address":"1666 N Main St",
    "sg:city":"Santa Ana",
    "sg:classifiers":[
        {
            "category":"Banks & Credit Unions",
            "subcategory":"Bank",
            "type":"Services"
        }
    ],
    "sg:phone":"+1 714 648 0865",
    "sg:postcode":"92701",
    "sg:province":"CA",
    "wof:name":"Grandpoint Bank And Trust",
    "wof:placetype":"venue"
},
  "geometry": {"coordinates":[-117.867734,33.759616],"type":"Point"}
}