{
  "type": "Feature",
  "properties": {
    "addr:full":"7700 Woodman Ave Van Nuys CA 91402",
    "addr:housenumber":"7700",
    "addr:postcode":"91402",
    "addr:street":"Woodman Ave",
    "iso:country":"US",
    "sg:address":"7700 Woodman Ave",
    "sg:city":"Van Nuys",
    "sg:classifiers":[
        {
            "category":"Home & Garden",
            "subcategory":"Furniture",
            "type":"Retail Goods"
        }
    ],
    "sg:phone":"+1 818 904 9414",
    "sg:postcode":"91402",
    "sg:province":"CA",
    "sg:tags":[
        "store"
    ],
    "sg:website":"www.michaelsfurniture.net",
    "wof:name":"Michael's Furniture",
    "wof:placetype":"venue"
},
  "geometry": {"coordinates":[-118.42976899999999,34.210203],"type":"Point"}
}