{
  "type": "Feature",
  "properties": {
    "addr:full":"5019 Queen Victoria Rd Woodland Hills CA 91364",
    "addr:housenumber":"5019",
    "addr:postcode":"91364",
    "addr:street":"Queen Victoria Rd",
    "iso:country":"US",
    "sg:address":"5019 Queen Victoria Rd",
    "sg:city":"Woodland Hills",
    "sg:classifiers":[
        {
            "category":"Building & Trades",
            "subcategory":"Construction",
            "type":"Services"
        }
    ],
    "sg:phone":"+1 818 999 5628",
    "sg:postcode":"91364",
    "sg:province":"CA",
    "sg:tags":[
        "interior",
        "design"
    ],
    "wof:name":"Wristy Business",
    "wof:placetype":"venue"
},
  "geometry": {"coordinates":[-118.565285,34.161622],"type":"Point"}
}