{
  "type": "Feature",
  "properties": {
    "iso:country":"US",
    "sg:address":"10010 Mesa Rim Rd",
    "sg:city":"San Diego",
    "sg:classifiers":[
        {
            "category":"Manufacturing",
            "subcategory":"Tools & Machinery",
            "type":"Manufacturing & Wholesale Goods"
        }
    ],
    "sg:phone":"+1 858 450 9811",
    "sg:postcode":"92121",
    "sg:province":"CA",
    "sg:tags":[
        "devices"
    ],
    "sg:website":"www.thermo.com",
    "wof:name":"Thermo Electron Corp",
    "wof:placetype":"venue"
},
  "geometry": {"coordinates":[-117.1784,32.899371],"type":"Point"}
}