{
  "type": "Feature",
  "properties": {
    "addr:full":"18848 Brookhurst St Fountain Valley CA 92708",
    "addr:housenumber":"18848",
    "addr:postcode":"92708",
    "addr:street":"Brookhurst St",
    "iso:country":"US",
    "sg:address":"18848 Brookhurst St",
    "sg:city":"Fountain Valley",
    "sg:classifiers":[
        {
            "category":"Retail",
            "subcategory":"Animal Services",
            "type":"Services"
        }
    ],
    "sg:phone":"+1 714 962 1005",
    "sg:postcode":"92708",
    "sg:province":"CA",
    "sg:tags":[
        "pet"
    ],
    "sg:website":"www.clawsnpawsdayspa.com",
    "wof:name":"Claws N Paws Day Spa",
    "wof:placetype":"venue"
},
  "geometry": {"coordinates":[-117.954002,33.688599],"type":"Point"}
}