{
  "type": "Feature",
  "properties": {
    "iso:country":"US",
    "sg:address":"32 Acorn",
    "sg:city":"Irvine",
    "sg:phone":"+1 949 857 6394",
    "sg:postcode":"92604",
    "sg:province":"CA",
    "sg:tags":[
        "equipment",
        "commercial"
    ],
    "wof:name":"Cornucopia Vending & Cof Svcs",
    "wof:placetype":"venue"
},
  "geometry": {"coordinates":[-117.78838500000001,33.684223],"type":"Point"}
}