{
  "type": "Feature",
  "properties": {
    "iso:country":"US",
    "sg:address":"21216 Pacific Coast Hwy",
    "sg:city":"Malibu",
    "sg:classifiers":[
        {
            "category":"Autos & Motor Vehicles",
            "subcategory":"Fuel & Gas Station",
            "type":"Retail Goods"
        }
    ],
    "sg:phone":"+1 310 456 6684",
    "sg:postcode":"90265",
    "sg:province":"CA",
    "sg:tags":[
        "oil"
    ],
    "wof:name":"Malibu Union Unocal 76",
    "wof:placetype":"venue"
},
  "geometry": {"coordinates":[-118.638011,34.037084],"type":"Point"}
}