{
  "type": "Feature",
  "properties": {
    "iso:country":"US",
    "sg:address":"10 Westcliff Ct",
    "sg:city":"Pacifica",
    "sg:classifiers":[
        {
            "category":"Building & Trades",
            "subcategory":"Electrical",
            "type":"Services"
        }
    ],
    "sg:phone":"+1 650 872 2848",
    "sg:postcode":"94044",
    "sg:province":"CA",
    "sg:tags":[
        "electrician"
    ],
    "wof:name":"Healy Electric",
    "wof:placetype":"venue"
},
  "geometry": {"coordinates":[-122.48371299999999,37.664602],"type":"Point"}
}