{
  "type": "Feature",
  "properties": {
    "addr:full":"1905 Concourse Dr San Jose CA 95131",
    "addr:housenumber":"1905",
    "addr:postcode":"95131",
    "addr:street":"Concourse Dr",
    "iso:country":"US",
    "sg:address":"1905 Concourse Dr",
    "sg:city":"San Jose",
    "sg:classifiers":[
        {
            "category":"Insurance",
            "subcategory":"Insurance Agent",
            "type":"Services"
        }
    ],
    "sg:phone":"+1 408 526 1800",
    "sg:postcode":"95131",
    "sg:province":"CA",
    "wof:name":"Farmer Insurance Nga Truong",
    "wof:placetype":"venue"
},
  "geometry": {"coordinates":[-121.89107,37.397124],"type":"Point"}
}