{
  "type": "Feature",
  "properties": {
    "iso:country":"US",
    "sg:address":"453 Los Cerritos Mall",
    "sg:city":"Cerritos",
    "sg:classifiers":[
        {
            "category":"Shopping",
            "subcategory":"Shoes",
            "type":"Retail Goods"
        }
    ],
    "sg:phone":"+1 562 860 4119",
    "sg:postcode":"90703",
    "sg:province":"CA",
    "sg:tags":[
        "store"
    ],
    "wof:name":"Shoe Box",
    "wof:placetype":"venue"
},
  "geometry": {"coordinates":[-118.094002,33.8643],"type":"Point"}
}