{
  "type": "Feature",
  "properties": {
    "addr:full":"11280 National Blvd Los Angeles CA 90064",
    "addr:housenumber":"11280",
    "addr:postcode":"90064",
    "addr:street":"National Blvd",
    "iso:country":"US",
    "sg:address":"11280 National Blvd",
    "sg:city":"Los Angeles",
    "sg:classifiers":[
        {
            "category":"Autos & Motor Vehicles",
            "subcategory":"Fuel & Gas Station",
            "type":"Retail Goods"
        },
        {
            "category":"Retail",
            "subcategory":"Car Wash",
            "type":"Services"
        }
    ],
    "sg:phone":"+1 310 478 5783",
    "sg:postcode":"90064",
    "sg:province":"CA",
    "wof:name":"Sinaco Oil Company",
    "wof:placetype":"venue"
},
  "geometry": {"coordinates":[-118.431,34.026501],"type":"Point"}
}