{
  "type": "Feature",
  "properties": {
    "addr:full":"6295 Co Rd 25 Orland CA 95963",
    "addr:housenumber":"6295;25",
    "addr:postcode":"95963",
    "addr:street":"Co Rd",
    "iso:country":"US",
    "sg:address":"6295 Co Rd 25",
    "sg:city":"Orland",
    "sg:classifiers":[
        {
            "category":"Building & Trades",
            "subcategory":"Construction",
            "type":"Services"
        }
    ],
    "sg:phone":"+1 530 865 3216",
    "sg:postcode":"95963",
    "sg:province":"CA",
    "sg:tags":[
        "steel",
        "erection",
        "structural"
    ],
    "wof:name":"Myers Welding",
    "wof:placetype":"venue"
},
  "geometry": {"coordinates":[-122.222982,39.697081],"type":"Point"}
}