{
  "type": "Feature",
  "properties": {
    "addr:full":"8253 N College Ave Fresno CA 93711",
    "addr:housenumber":"8253",
    "addr:postcode":"93711",
    "addr:street":"N College Ave",
    "iso:country":"US",
    "sg:address":"8253 N College Ave",
    "sg:city":"Fresno",
    "sg:classifiers":[
        {
            "category":"Home & Garden",
            "subcategory":"Home Furnishings",
            "type":"Retail Goods"
        }
    ],
    "sg:phone":"+1 559 431 8855",
    "sg:postcode":"93711",
    "sg:province":"CA",
    "sg:tags":[
        "window",
        "covering"
    ],
    "wof:name":"Premier Window Coverings",
    "wof:placetype":"venue"
},
  "geometry": {"coordinates":[-119.79664,36.855896],"type":"Point"}
}