{
  "type": "Feature",
  "properties": {
    "iso:country":"US",
    "sg:address":"681 Edna Way",
    "sg:city":"San Mateo",
    "sg:classifiers":[
        {
            "category":"Manufacturing",
            "subcategory":"Tools & Machinery",
            "type":"Manufacturing & Wholesale Goods"
        }
    ],
    "sg:phone":"+1 650 573 8232",
    "sg:postcode":"94402",
    "sg:province":"CA",
    "sg:tags":[
        "industry",
        "mfg"
    ],
    "wof:name":"Cleaning Machine",
    "wof:placetype":"venue"
},
  "geometry": {"coordinates":[-122.304793,37.555558],"type":"Point"}
}