{
  "type": "Feature",
  "properties": {
    "addr:full":"4171 Oceanside Blvd Oceanside CA 92056",
    "addr:housenumber":"4171",
    "addr:postcode":"92056",
    "addr:street":"Oceanside Blvd",
    "iso:country":"US",
    "sg:address":"4171 Oceanside Blvd",
    "sg:city":"Oceanside",
    "sg:classifiers":[
        {
            "category":"Retail",
            "subcategory":"Laundry & Dry Cleaning",
            "type":"Services"
        }
    ],
    "sg:phone":"+1 760 940 8776",
    "sg:postcode":"92056",
    "sg:province":"CA",
    "wof:name":"College Cleaners",
    "wof:placetype":"venue"
},
  "geometry": {"coordinates":[-117.286292,33.206654],"type":"Point"}
}