{
  "type": "Feature",
  "properties": {
    "addr:full":"33041 Auberry Rd Auberry CA 93602",
    "addr:postcode":"33041;93602",
    "addr:street":"Auberry Rd",
    "iso:country":"US",
    "sg:address":"33041 Auberry Rd",
    "sg:city":"Auberry",
    "sg:classifiers":[
        {
            "category":"Real Estate",
            "subcategory":"Surveying",
            "type":"Services"
        }
    ],
    "sg:phone":"+1 559 855 3112",
    "sg:postcode":"93602",
    "sg:province":"CA",
    "sg:tags":[
        "surveyor"
    ],
    "wof:name":"Lyle Brewer Civil Engineering",
    "wof:placetype":"venue"
},
  "geometry": {"coordinates":[-119.48533,37.07531],"type":"Point"}
}