{
  "type": "Feature",
  "properties": {
    "addr:full":"5616 Corporate Ave Cypress CA 90630",
    "addr:housenumber":"5616",
    "addr:postcode":"90630",
    "addr:street":"Corporate Ave",
    "iso:country":"US",
    "sg:address":"5616 Corporate Ave",
    "sg:city":"Cypress",
    "sg:classifiers":[
        {
            "category":"Shopping",
            "subcategory":"Computers & Home Electronics",
            "type":"Retail Goods"
        }
    ],
    "sg:phone":"+1 714 821 9990",
    "sg:postcode":"90630",
    "sg:province":"CA",
    "sg:tags":[
        "equipment",
        "electronic",
        "supply"
    ],
    "wof:name":"Automation Controls Group Inc",
    "wof:placetype":"venue"
},
  "geometry": {"coordinates":[-118.031492,33.807912],"type":"Point"}
}