{
  "type": "Feature",
  "properties": {
    "addr:full":"8605 Santa Monica Blvd West Hollywood CA 90069",
    "addr:housenumber":"8605",
    "addr:postcode":"90069",
    "addr:street":"Santa Monica Blvd",
    "iso:country":"US",
    "sg:address":"8605 Santa Monica Blvd",
    "sg:city":"West Hollywood",
    "sg:classifiers":[
        {
            "category":"Professional",
            "subcategory":"Management & Consulting",
            "type":"Services"
        }
    ],
    "sg:phone":"+1 310 751 0656",
    "sg:postcode":"90069",
    "sg:province":"CA",
    "sg:tags":[
        "life",
        "coach"
    ],
    "sg:website":"www.PebbleStorm.com",
    "wof:name":"PebbleStorm",
    "wof:placetype":"venue"
},
  "geometry": {"coordinates":[-118.37911699999999,34.088048],"type":"Point"}
}