{
  "type": "Feature",
  "properties": {
    "addr:full":"168 Park Dartmouth Pl San Jose CA 95136",
    "addr:housenumber":"168",
    "addr:postcode":"95136",
    "addr:street":"Park Dartmouth Pl",
    "iso:country":"US",
    "sg:address":"168 Park Dartmouth Pl",
    "sg:city":"San Jose",
    "sg:phone":"+1 408 629 9407",
    "sg:postcode":"95136",
    "sg:province":"CA",
    "sg:tags":[
        "oil"
    ],
    "wof:name":"Amsoil Synthetic Lubricants",
    "wof:placetype":"venue"
},
  "geometry": {"coordinates":[-121.830581,37.268578],"type":"Point"}
}