{
  "type": "Feature",
  "properties": {
    "iso:country":"US",
    "sg:address":"512 Silver Leaf Ct",
    "sg:city":"Nipomo",
    "sg:classifiers":[
        {
            "category":"Building & Trades",
            "subcategory":"Construction",
            "type":"Services"
        }
    ],
    "sg:phone":"+1 805 931 0957",
    "sg:postcode":"93444",
    "sg:province":"CA",
    "sg:tags":[
        "steam",
        "cleaning"
    ],
    "wof:name":"Quality Mobile Wash",
    "wof:placetype":"venue"
},
  "geometry": {"coordinates":[-120.489115,35.019241],"type":"Point"}
}