{
  "type": "Feature",
  "properties": {
    "addr:full":"1216 N Tustin St Orange CA 92867",
    "addr:housenumber":"1216",
    "addr:postcode":"92867",
    "addr:street":"N Tustin St",
    "iso:country":"US",
    "sg:address":"1216 N Tustin St",
    "sg:city":"Orange",
    "sg:classifiers":[
        {
            "category":"Shopping",
            "subcategory":"Gifts & Souvenirs",
            "type":"Retail Goods"
        }
    ],
    "sg:phone":"+1 714 453 0235",
    "sg:postcode":"92867",
    "sg:province":"CA",
    "sg:tags":[
        "party",
        "supply"
    ],
    "wof:name":"Republican Party Of Oc",
    "wof:placetype":"venue"
},
  "geometry": {"coordinates":[-117.83577099999999,33.806898],"type":"Point"}
}