{
  "type": "Feature",
  "properties": {
    "iso:country":"US",
    "sg:address":"2407 Troy Ave",
    "sg:city":"South El Monte",
    "sg:classifiers":[
        {
            "category":"Retail",
            "subcategory":"Repair Shop",
            "type":"Services"
        }
    ],
    "sg:phone":"+1 626 443 8380",
    "sg:postcode":"91733",
    "sg:province":"CA",
    "sg:tags":[
        "welding"
    ],
    "wof:name":"Zamora's Welding",
    "wof:placetype":"venue"
},
  "geometry": {"coordinates":[-118.065922,34.058944],"type":"Point"}
}