{
  "type": "Feature",
  "properties": {
    "addr:full":"295 West St Santa Maria CA 93458",
    "addr:housenumber":"295",
    "addr:postcode":"93458",
    "addr:street":"West St",
    "iso:country":"US",
    "sg:address":"295 West St",
    "sg:city":"Santa Maria",
    "sg:classifiers":[
        {
            "category":"Manufacturing",
            "subcategory":"Metals",
            "type":"Manufacturing & Wholesale Goods"
        }
    ],
    "sg:phone":"+1 805 922 2752",
    "sg:postcode":"93458",
    "sg:province":"CA",
    "sg:tags":[
        "fabrication",
        "structural"
    ],
    "wof:name":"Custom Iron Works",
    "wof:placetype":"venue"
},
  "geometry": {"coordinates":[-120.439831,34.923582],"type":"Point"}
}