{
  "type": "Feature",
  "properties": {
    "iso:country":"US",
    "sg:address":"37020 State Rte 299 E",
    "sg:city":"Burney",
    "sg:classifiers":[
        {
            "category":"Shopping",
            "subcategory":"Used Merchandise",
            "type":"Retail Goods"
        },
        {
            "category":"Professional",
            "type":"Services"
        }
    ],
    "sg:phone":"+1 530 335 4690",
    "sg:postcode":"96013",
    "sg:province":"CA",
    "sg:tags":[
        "shop",
        "thrift"
    ],
    "wof:name":"What's It Worth",
    "wof:placetype":"venue"
},
  "geometry": {"coordinates":[-121.67095,40.881861],"type":"Point"}
}