{
  "type": "Feature",
  "properties": {
    "iso:country":"US",
    "sg:address":"30019 Hawthorne Blvd",
    "sg:city":"Rancho Pls Vrds",
    "sg:classifiers":[
        {
            "category":"Food & Beverages",
            "subcategory":"Groceries & Convenience Stores",
            "type":"Retail Goods"
        }
    ],
    "sg:phone":"+1 310 377 6829",
    "sg:postcode":"90275",
    "sg:province":"CA",
    "sg:tags":[
        "grocer"
    ],
    "wof:name":"Ralph's Pharmacy",
    "wof:placetype":"venue"
},
  "geometry": {"coordinates":[-118.395085,33.758081],"type":"Point"}
}