{
  "type": "Feature",
  "properties": {
    "iso:country":"US",
    "sg:address":"306 W 3rd St",
    "sg:city":"Santa Ana",
    "sg:classifiers":[
        {
            "category":"Shopping",
            "subcategory":"Clothing, Apparel, & Fashions",
            "type":"Retail Goods"
        },
        {
            "category":"Shopping",
            "subcategory":"Hobbies, Toys, & Games",
            "type":"Retail Goods"
        },
        {
            "category":"Shopping",
            "subcategory":"Shoes",
            "type":"Retail Goods"
        }
    ],
    "sg:phone":"+1 714 543 5500",
    "sg:postcode":"92701",
    "sg:province":"CA",
    "sg:tags":[
        "shop",
        "hobby",
        "men's",
        "clothing",
        "store"
    ],
    "sg:website":"avntgrde.com",
    "wof:name":"AVNT/GRDE",
    "wof:placetype":"venue"
},
  "geometry": {"coordinates":[-117.86998199999999,33.747118],"type":"Point"}
}