{
  "type": "Feature",
  "properties": {
    "addr:full":"28623 S Western Ave Rancho Palos Verdes CA 90275",
    "addr:housenumber":"28623",
    "addr:postcode":"90275",
    "addr:street":"S Western Ave",
    "iso:country":"US",
    "sg:address":"28623 S Western Ave",
    "sg:city":"Rancho Palos Verdes",
    "sg:classifiers":[
        {
            "category":"Education",
            "subcategory":"School",
            "type":"Public Place"
        }
    ],
    "sg:phone":"+1 310 294 1200",
    "sg:postcode":"90275",
    "sg:province":"CA",
    "wof:name":"The Tutor Center",
    "wof:placetype":"venue"
},
  "geometry": {"coordinates":[-118.31254800000001,33.758496],"type":"Point"}
}