{
  "type": "Feature",
  "properties": {
    "addr:full":"2725 Jefferson St Ste 5 Carlsbad CA 92008",
    "addr:housenumber":"2725",
    "addr:postcode":"92008",
    "addr:street":"Jefferson St Ste 5",
    "iso:country":"US",
    "sg:address":"2725 Jefferson St Ste 5",
    "sg:city":"Carlsbad",
    "sg:classifiers":[
        {
            "category":"Real Estate",
            "subcategory":"Real Estate Services",
            "type":"Services"
        }
    ],
    "sg:phone":"+1 760 585 2355",
    "sg:postcode":"92008",
    "sg:province":"CA",
    "sg:tags":[
        "home",
        "inspector"
    ],
    "wof:name":"AMERISPEC INSPECTION SERVICE",
    "wof:placetype":"venue"
},
  "geometry": {"coordinates":[-117.34842500000001,33.164556],"type":"Point"}
}