{
  "type": "Feature",
  "properties": {
    "iso:country":"US",
    "sg:address":"2915 Telegraph Avenue Suite 200",
    "sg:city":"Berkeley",
    "sg:classifiers":[
        {
            "category":"Health Services",
            "subcategory":"Doctor",
            "type":"Services"
        }
    ],
    "sg:phone":"+1 510 204 8190",
    "sg:postcode":"94705",
    "sg:province":"CA",
    "sg:tags":[
        "obstetrician",
        "gynecologist"
    ],
    "sg:website":"www.sebmf.org",
    "wof:name":"Katarina Lanner-Cusin, MD",
    "wof:placetype":"venue"
},
  "geometry": {"coordinates":[-122.259399,37.857124],"type":"Point"}
}