{
  "type": "Feature",
  "properties": {
    "iso:country":"US",
    "sg:address":"101 Coombs St",
    "sg:city":"Napa",
    "sg:classifiers":[
        {
            "category":"Professional",
            "subcategory":"Research",
            "type":"Services"
        }
    ],
    "sg:phone":"+1 707 252 4620",
    "sg:postcode":"94559",
    "sg:province":"CA",
    "sg:tags":[
        "development",
        "laboratory"
    ],
    "wof:name":"Sonoma Research Co",
    "wof:placetype":"venue"
},
  "geometry": {"coordinates":[-122.286492,38.289004],"type":"Point"}
}