{
  "type": "Feature",
  "properties": {
    "addr:full":"30019 Marvin Ave Castaic CA 91384",
    "addr:housenumber":"30019",
    "addr:postcode":"91384",
    "addr:street":"Marvin Ave",
    "iso:country":"US",
    "sg:address":"30019 Marvin Ave",
    "sg:city":"Castaic",
    "sg:classifiers":[
        {
            "category":"Organizations",
            "subcategory":"Religious Organization",
            "type":"Services"
        }
    ],
    "sg:phone":"+1 661 257 4110",
    "sg:postcode":"91384",
    "sg:province":"CA",
    "wof:name":"Macedonia Church of God In Christ",
    "wof:placetype":"venue"
},
  "geometry": {"coordinates":[-118.65799699999999,34.445599],"type":"Point"}
}