{
  "type": "Feature",
  "properties": {
    "iso:country":"US",
    "sg:address":"22310 Graystone Ct",
    "sg:city":"Palo Cedro",
    "sg:classifiers":[
        {
            "category":"Professional",
            "type":"Services"
        }
    ],
    "sg:phone":"+1 530 549 3669",
    "sg:postcode":"96073",
    "sg:province":"CA",
    "wof:name":"Tig Tech",
    "wof:placetype":"venue"
},
  "geometry": {"coordinates":[-122.232238,40.607643],"type":"Point"}
}