{
  "type": "Feature",
  "properties": {
    "addr:full":"2690 el Portal Dr San Pablo CA 94806",
    "addr:housenumber":"2690",
    "addr:postcode":"94806",
    "addr:street":"El Portal Dr",
    "iso:country":"US",
    "sg:address":"2690 el Portal Dr",
    "sg:city":"San Pablo",
    "sg:classifiers":[
        {
            "category":"Freight",
            "type":"Transportation"
        }
    ],
    "sg:phone":"+1 510 222 6471",
    "sg:postcode":"94806",
    "sg:province":"CA",
    "sg:tags":[
        "arrangement"
    ],
    "wof:name":"Atlas Shippers International",
    "wof:placetype":"venue"
},
  "geometry": {"coordinates":[-122.33714999999999,37.963117],"type":"Point"}
}