{
  "type": "Feature",
  "properties": {
    "iso:country":"US",
    "sg:address":"4911 Paoli Loop Rd",
    "sg:city":"American Canyon",
    "sg:classifiers":[
        {
            "category":"Manufacturing",
            "subcategory":"Tools & Machinery",
            "type":"Manufacturing & Wholesale Goods"
        }
    ],
    "sg:phone":"+1 707 647 0513",
    "sg:postcode":"94503",
    "sg:province":"CA",
    "sg:tags":[
        "machine",
        "shop"
    ],
    "wof:name":"Bob Weir Machinery",
    "wof:placetype":"venue"
},
  "geometry": {"coordinates":[-122.25654,38.19383],"type":"Point"}
}