{
  "type": "Feature",
  "properties": {
    "addr:full":"2056 Pacific Ave Long Beach CA 90806",
    "addr:housenumber":"2056",
    "addr:postcode":"90806",
    "addr:street":"Pacific Ave",
    "iso:country":"US",
    "sg:address":"2056 Pacific Ave",
    "sg:city":"Long Beach",
    "sg:classifiers":[
        {
            "category":"Retail",
            "subcategory":"Self-service Laundry",
            "type":"Services"
        }
    ],
    "sg:phone":"+1 562 591 5580",
    "sg:postcode":"90806",
    "sg:province":"CA",
    "wof:name":"Launderland",
    "wof:placetype":"venue"
},
  "geometry": {"coordinates":[-118.193714,33.795303],"type":"Point"}
}