{
  "type": "Feature",
  "properties": {
    "addr:full":"5666 Mission Street San Francisco CA 94112",
    "addr:housenumber":"5666",
    "addr:postcode":"94112",
    "addr:street":"Mission Street",
    "iso:country":"US",
    "sg:address":"5666 Mission Street",
    "sg:city":"San Francisco",
    "sg:classifiers":[
        {
            "category":"Retail",
            "subcategory":"Auto Repair",
            "type":"Services"
        }
    ],
    "sg:phone":"+1 415 334 4484",
    "sg:postcode":"94112",
    "sg:province":"CA",
    "sg:tags":[
        "body",
        "shop"
    ],
    "wof:name":"Mission Auto Body",
    "wof:placetype":"venue"
},
  "geometry": {"coordinates":[-122.44846699999999,37.710587],"type":"Point"}
}