{
  "type": "Feature",
  "properties": {
    "addr:full":"7757 Mission Gorge Rd Santee CA 92071",
    "addr:housenumber":"7757",
    "addr:postcode":"92071",
    "addr:street":"Mission Gorge Rd",
    "iso:country":"US",
    "sg:address":"7757 Mission Gorge Rd",
    "sg:city":"Santee",
    "sg:classifiers":[
        {
            "category":"Food & Beverages",
            "subcategory":"Groceries & Convenience Stores",
            "type":"Retail Goods"
        }
    ],
    "sg:phone":"+1 619 258 7100",
    "sg:postcode":"92071",
    "sg:province":"CA",
    "sg:tags":[
        "grocer"
    ],
    "wof:name":"Mission Gorge Market & Deli",
    "wof:placetype":"venue"
},
  "geometry": {"coordinates":[-117.02934500000001,32.837398],"type":"Point"}
}