{
  "type": "Feature",
  "properties": {
    "addr:full":"133 W el Camino Real Mountain View CA 94040",
    "addr:housenumber":"133",
    "addr:postcode":"94040",
    "addr:street":"W El Camino Real",
    "iso:country":"US",
    "sg:address":"133 W el Camino Real",
    "sg:city":"Mountain View",
    "sg:classifiers":[
        {
            "category":"Shopping",
            "subcategory":"Bicycles & Sporting Goods",
            "type":"Retail Goods"
        }
    ],
    "sg:phone":"+1 650 988 6800",
    "sg:postcode":"94040",
    "sg:province":"CA",
    "wof:name":"Play It Again Sports",
    "wof:placetype":"venue"
},
  "geometry": {"coordinates":[-122.076251,37.381783],"type":"Point"}
}