{
  "type": "Feature",
  "properties": {
    "addr:full":"3435 Wilshire Blvd Ste 3060 Los Angeles CA 90010",
    "addr:housenumber":"3435",
    "addr:postcode":"3060;90010",
    "addr:street":"Wilshire Blvd Ste",
    "iso:country":"US",
    "sg:address":"3435 Wilshire Blvd Ste 3060",
    "sg:city":"Los Angeles",
    "sg:classifiers":[
        {
            "category":"Banks & Credit Unions",
            "subcategory":"Financial Services",
            "type":"Services"
        }
    ],
    "sg:phone":"+1 949 257 7060",
    "sg:postcode":"90010",
    "sg:province":"CA",
    "sg:tags":[
        "broker",
        "mortgage"
    ],
    "wof:name":"Plus Mortgage Group",
    "wof:placetype":"venue"
},
  "geometry": {"coordinates":[-118.2987,34.06185],"type":"Point"}
}