{
  "type": "Feature",
  "properties": {
    "addr:full":"1248 Palmetto St. Los Angeles CA 90013",
    "addr:housenumber":"1248",
    "addr:postcode":"90013",
    "addr:street":"Palmetto St.",
    "iso:country":"US",
    "sg:address":"1248 Palmetto St.",
    "sg:city":"Los Angeles",
    "sg:classifiers":[
        {
            "category":"Personal",
            "type":"Services"
        }
    ],
    "sg:postcode":"90013",
    "sg:province":"CA",
    "sg:tags":[
        "mover"
    ],
    "sg:website":"www.moveeast.com",
    "wof:name":"California NY Express",
    "wof:placetype":"venue"
},
  "geometry": {"coordinates":[-118.23361800000001,34.039725],"type":"Point"}
}