{
  "type": "Feature",
  "properties": {
    "addr:full":"142 Norwich Rd Alameda CA 94502",
    "addr:housenumber":"142",
    "addr:postcode":"94502",
    "addr:street":"Norwich Rd",
    "iso:country":"US",
    "sg:address":"142 Norwich Rd",
    "sg:city":"Alameda",
    "sg:classifiers":[
        {
            "category":"Shopping",
            "subcategory":"Bicycles & Sporting Goods",
            "type":"Retail Goods"
        }
    ],
    "sg:phone":"+1 510 749 9149",
    "sg:postcode":"94502",
    "sg:province":"CA",
    "sg:tags":[
        "equipment",
        "golf",
        "supply"
    ],
    "sg:website":"www.clubdoctor.com",
    "wof:name":"Alameda Golf Shop",
    "wof:placetype":"venue"
},
  "geometry": {"coordinates":[-122.243154,37.746342],"type":"Point"}
}