{
  "type": "Feature",
  "properties": {
    "addr:full":"4840 Old Redwood Hwy Santa Rosa CA 95403",
    "addr:housenumber":"4840",
    "addr:postcode":"95403",
    "addr:street":"Old Redwood Hwy",
    "iso:country":"US",
    "sg:address":"4840 Old Redwood Hwy",
    "sg:city":"Santa Rosa",
    "sg:classifiers":[
        {
            "category":"Autos & Motor Vehicles",
            "subcategory":"Fuel & Gas Station",
            "type":"Retail Goods"
        }
    ],
    "sg:phone":"+1 707 542 7101",
    "sg:postcode":"95403",
    "sg:province":"CA",
    "sg:tags":[
        "oil"
    ],
    "wof:name":"Larkfield Chevron",
    "wof:placetype":"venue"
},
  "geometry": {"coordinates":[-122.75232,38.501442],"type":"Point"}
}