{
  "type": "Feature",
  "properties": {
    "addr:full":"546 S Pacific St San Marcos CA 92078",
    "addr:housenumber":"546",
    "addr:postcode":"92078",
    "addr:street":"S Pacific St",
    "iso:country":"US",
    "sg:address":"546 S Pacific St",
    "sg:city":"San Marcos",
    "sg:classifiers":[
        {
            "category":"Manufacturing",
            "subcategory":"Tools & Machinery",
            "type":"Manufacturing & Wholesale Goods"
        }
    ],
    "sg:phone":"+1 760 744 6115",
    "sg:postcode":"92078",
    "sg:province":"CA",
    "sg:tags":[
        "machine",
        "shop"
    ],
    "wof:name":"Ly's Precision Machining",
    "wof:placetype":"venue"
},
  "geometry": {"coordinates":[-117.197444,33.133633],"type":"Point"}
}