{
  "type": "Feature",
  "properties": {
    "iso:country":"US",
    "sg:address":"12121 Wilshire Blvd",
    "sg:city":"Los Angeles",
    "sg:classifiers":[
        {
            "category":"Real Estate",
            "subcategory":"Real Estate Agent",
            "type":"Services"
        }
    ],
    "sg:phone":"+1 310 207 5996",
    "sg:postcode":"90025",
    "sg:province":"CA",
    "wof:name":"Amherst Real Estate Capital",
    "wof:placetype":"venue"
},
  "geometry": {"coordinates":[-118.468221,34.043614],"type":"Point"}
}