{
  "type": "Feature",
  "properties": {
    "iso:country":"US",
    "sg:address":"9623 Downey Ave",
    "sg:city":"Downey",
    "sg:classifiers":[
        {
            "category":"Professional",
            "type":"Services"
        }
    ],
    "sg:phone":"+1 562 869 6042",
    "sg:postcode":"90240",
    "sg:province":"CA",
    "wof:name":"Davis Housing Inc",
    "wof:placetype":"venue"
},
  "geometry": {"coordinates":[-118.121672,33.956824],"type":"Point"}
}