{
  "type": "Feature",
  "properties": {
    "addr:full":"2012 W Whittier Blvd Montebello CA 90640",
    "addr:housenumber":"2012",
    "addr:postcode":"90640",
    "addr:street":"W Whittier Blvd",
    "iso:country":"US",
    "sg:address":"2012 W Whittier Blvd",
    "sg:city":"Montebello",
    "sg:classifiers":[
        {
            "category":"Restaurant",
            "type":"Food & Drink"
        }
    ],
    "sg:phone":"+1 323 721 0637",
    "sg:postcode":"90640",
    "sg:province":"CA",
    "sg:tags":[
        "pizza"
    ],
    "wof:name":"Tony's Italian Delicatessen",
    "wof:placetype":"venue"
},
  "geometry": {"coordinates":[-118.123001,34.013401],"type":"Point"}
}