{
  "type": "Feature",
  "properties": {
    "addr:full":"2940 Del Loma Dr Campbell CA 95008",
    "addr:housenumber":"2940",
    "addr:postcode":"95008",
    "addr:street":"Del Loma Dr",
    "iso:country":"US",
    "sg:address":"2940 Del Loma Dr",
    "sg:city":"Campbell",
    "sg:classifiers":[
        {
            "category":"Personal",
            "type":"Services"
        }
    ],
    "sg:phone":"+1 408 813 0923",
    "sg:postcode":"95008",
    "sg:province":"CA",
    "sg:tags":[
        "home"
    ],
    "wof:name":"Julian Ramos Pool Service",
    "wof:placetype":"venue"
},
  "geometry": {"coordinates":[-121.98248100000001,37.267117],"type":"Point"}
}