{
  "type": "Feature",
  "properties": {
    "addr:full":"2460 San Vicente Rd Ramona CA 92065",
    "addr:housenumber":"2460",
    "addr:postcode":"92065",
    "addr:street":"San Vicente Rd",
    "iso:country":"US",
    "sg:address":"2460 San Vicente Rd",
    "sg:city":"Ramona",
    "sg:classifiers":[
        {
            "category":"Home & Garden",
            "subcategory":"Furniture",
            "type":"Retail Goods"
        }
    ],
    "sg:phone":"+1 760 789 6260",
    "sg:postcode":"92065",
    "sg:province":"CA",
    "sg:tags":[
        "store"
    ],
    "wof:name":"Lisa Gouse",
    "wof:placetype":"venue"
},
  "geometry": {"coordinates":[-116.865588,33.007588],"type":"Point"}
}