{
  "type": "Feature",
  "properties": {
    "iso:country":"US",
    "sg:address":"11725 Bennetta Ln",
    "sg:city":"Gilroy",
    "sg:classifiers":[
        {
            "category":"Real Estate",
            "subcategory":"Real Estate Agent",
            "type":"Services"
        }
    ],
    "sg:phone":"+1 408 683 2662",
    "sg:postcode":"95020",
    "sg:province":"CA",
    "wof:name":"Memorial Property Management",
    "wof:placetype":"venue"
},
  "geometry": {"coordinates":[-121.577352,37.073141],"type":"Point"}
}