{
  "type": "Feature",
  "properties": {
    "addr:full":"7009 Bianca Ave Van Nuys CA 91406",
    "addr:housenumber":"7009",
    "addr:postcode":"91406",
    "addr:street":"Bianca Ave",
    "iso:country":"US",
    "sg:address":"7009 Bianca Ave",
    "sg:city":"Van Nuys",
    "sg:classifiers":[
        {
            "category":"Building & Trades",
            "subcategory":"Landscaping Services",
            "type":"Services"
        }
    ],
    "sg:phone":"+1 818 705 0598",
    "sg:postcode":"91406",
    "sg:province":"CA",
    "sg:tags":[
        "landscape",
        "contractor"
    ],
    "wof:name":"Roman's Landscaping",
    "wof:placetype":"venue"
},
  "geometry": {"coordinates":[-118.51320200000001,34.199957],"type":"Point"}
}