{
  "type": "Feature",
  "properties": {
    "iso:country":"US",
    "sg:address":"4450 Capitola Road",
    "sg:city":"Capitola",
    "sg:classifiers":[
        {
            "category":"Professional",
            "subcategory":"Lawyer & Legal Services",
            "type":"Services"
        }
    ],
    "sg:phone":"+1 831 462 3220",
    "sg:postcode":"95010",
    "sg:province":"CA",
    "wof:name":"Bodmer Kathleen Lawler Attorney At Law PC",
    "wof:placetype":"venue"
},
  "geometry": {"coordinates":[-121.96044000000001,36.97372],"type":"Point"}
}