{
  "type": "Feature",
  "properties": {
    "addr:full":"7000 Franklin Blvd # 1100 Sacramento CA 95823",
    "addr:housenumber":"7000",
    "addr:postcode":"95823",
    "addr:street":"Franklin Blvd # 1100",
    "iso:country":"US",
    "sg:address":"7000 Franklin Blvd # 1100",
    "sg:city":"Sacramento",
    "sg:classifiers":[
        {
            "category":"Government",
            "subcategory":"Office",
            "type":"Public Place"
        }
    ],
    "sg:phone":"+1 916 262 2160",
    "sg:postcode":"95823",
    "sg:province":"CA",
    "sg:tags":[
        "government-united",
        "state"
    ],
    "sg:website":"http://www.scworksource.com",
    "wof:name":"Labor Market Information Div",
    "wof:placetype":"venue"
},
  "geometry": {"coordinates":[-121.461456,38.500038],"type":"Point"}
}