{
  "type": "Feature",
  "properties": {
    "addr:full":"1750 W Ave N Palmdale CA 93551",
    "addr:housenumber":"1750",
    "addr:postcode":"ca 93551",
    "addr:street":"W Ave N",
    "iso:country":"US",
    "sg:address":"1750 W Ave N",
    "sg:city":"Palmdale",
    "sg:classifiers":[
        {
            "category":"Organizations",
            "subcategory":"Religious Organization",
            "type":"Services"
        }
    ],
    "sg:phone":"+1 661 224 1605",
    "sg:postcode":"93551",
    "sg:province":"CA",
    "sg:tags":[
        "church"
    ],
    "wof:name":"Archangel Rafael St Mina",
    "wof:placetype":"venue"
},
  "geometry": {"coordinates":[-118.16174700000001,34.631061],"type":"Point"}
}