{
  "type": "Feature",
  "properties": {
    "addr:full":"8301 White Oak Ave Northridge CA 91325",
    "addr:housenumber":"8301",
    "addr:postcode":"91325",
    "addr:street":"White Oak Ave",
    "iso:country":"US",
    "sg:address":"8301 White Oak Ave",
    "sg:city":"Northridge",
    "sg:classifiers":[
        {
            "category":"Manufacturing",
            "subcategory":"Building Materials",
            "type":"Manufacturing & Wholesale Goods"
        }
    ],
    "sg:phone":"+1 818 757 0751",
    "sg:postcode":"91325",
    "sg:province":"CA",
    "sg:tags":[
        "mfg",
        "wood",
        "kitchen",
        "cabinet"
    ],
    "wof:name":"Tobias Horler Kitchen Cabinets",
    "wof:placetype":"venue"
},
  "geometry": {"coordinates":[-118.519042,34.222781],"type":"Point"}
}