{
  "type": "Feature",
  "properties": {
    "addr:full":"21540 Prairie St Chatsworth CA 91311",
    "addr:housenumber":"21540",
    "addr:postcode":"91311",
    "addr:street":"Prairie St",
    "iso:country":"US",
    "sg:address":"21540 Prairie St",
    "sg:city":"Chatsworth",
    "sg:classifiers":[
        {
            "category":"Shopping",
            "subcategory":"Computers & Home Electronics",
            "type":"Retail Goods"
        }
    ],
    "sg:phone":"+1 818 407 1555",
    "sg:postcode":"91311",
    "sg:province":"CA",
    "sg:tags":[
        "parts",
        "supply"
    ],
    "wof:name":"Computer Supply",
    "wof:placetype":"venue"
},
  "geometry": {"coordinates":[-118.598473,34.239005],"type":"Point"}
}