{
  "type": "Feature",
  "properties": {
    "iso:country":"US",
    "sg:address":"301 W Huntington Dr Ste 408",
    "sg:city":"Arcadia",
    "sg:classifiers":[
        {
            "category":"Health Services",
            "subcategory":"Doctor",
            "type":"Services"
        }
    ],
    "sg:phone":"+1 626 821 0707",
    "sg:postcode":"91007",
    "sg:province":"CA",
    "sg:tags":[
        "orthopedist"
    ],
    "wof:name":"West Coast Orthopaedic Medical Group",
    "wof:placetype":"venue"
},
  "geometry": {"coordinates":[-118.039001,34.1385],"type":"Point"}
}