{
  "type": "Feature",
  "properties": {
    "iso:country":"US",
    "sg:address":"2018 2nd St",
    "sg:city":"Selma",
    "sg:classifiers":[
        {
            "category":"Banks & Credit Unions",
            "subcategory":"Bank",
            "type":"Services"
        }
    ],
    "sg:phone":"+1 559 896 0248",
    "sg:postcode":"93662",
    "sg:province":"CA",
    "sg:tags":[
        "loan",
        "real estate"
    ],
    "wof:name":"Wausau Mortgage",
    "wof:placetype":"venue"
},
  "geometry": {"coordinates":[-119.611171,36.567022],"type":"Point"}
}