{
  "type": "Feature",
  "properties": {
    "iso:country":"US",
    "sg:address":"9920 Freeman Ave",
    "sg:city":"Santa Fe Springs",
    "sg:classifiers":[
        {
            "category":"Wholesale",
            "subcategory":"Machinery & Supplies",
            "type":"Manufacturing & Wholesale Goods"
        }
    ],
    "sg:phone":"+1 562 944 4441",
    "sg:postcode":"90670",
    "sg:province":"CA",
    "sg:tags":[
        "rebuilding",
        "aircraft"
    ],
    "sg:website":"www.goodrich.com",
    "wof:name":"Goodrich Aircraft Wheel",
    "wof:placetype":"venue"
},
  "geometry": {"coordinates":[-118.057569,33.947585],"type":"Point"}
}