{
  "type": "Feature",
  "properties": {
    "iso:country":"US",
    "sg:address":"12300 De Sanka Avenue",
    "sg:city":"Saratoga",
    "sg:classifiers":[
        {
            "category":"Social Services",
            "subcategory":"Child Care",
            "type":"Services"
        }
    ],
    "sg:phone":"+1 408 725 0505",
    "sg:postcode":"95070",
    "sg:province":"CA",
    "sg:tags":[
        "day"
    ],
    "wof:name":"YMCA of Santa Clara Valley",
    "wof:placetype":"venue"
},
  "geometry": {"coordinates":[-122.02607399999999,37.289853],"type":"Point"}
}