{
  "type": "Feature",
  "properties": {
    "addr:full":"1115 Van Ness Ave Torrance CA 90501",
    "addr:housenumber":"1115",
    "addr:postcode":"90501",
    "addr:street":"Van Ness Ave",
    "iso:country":"US",
    "sg:address":"1115 Van Ness Ave",
    "sg:city":"Torrance",
    "sg:classifiers":[
        {
            "category":"Retail",
            "subcategory":"Auto Repair",
            "type":"Services"
        }
    ],
    "sg:phone":"+1 310 320 1052",
    "sg:postcode":"90501",
    "sg:province":"CA",
    "sg:tags":[
        "repairing",
        "automobile"
    ],
    "wof:name":"Tips Cadillac",
    "wof:placetype":"venue"
},
  "geometry": {"coordinates":[-118.316002,33.8372],"type":"Point"}
}