{
  "type": "Feature",
  "properties": {
    "iso:country":"US",
    "sg:address":"1714 1st Ave",
    "sg:city":"Walnut Creek",
    "sg:classifiers":[
        {
            "category":"Professional",
            "subcategory":"Management & Consulting",
            "type":"Services"
        }
    ],
    "sg:phone":"+1 925 256 7636",
    "sg:postcode":"94597",
    "sg:province":"CA",
    "sg:tags":[
        "consultant",
        "training"
    ],
    "wof:name":"Art Of Living",
    "wof:placetype":"venue"
},
  "geometry": {"coordinates":[-122.069719,37.924162],"type":"Point"}
}