{
  "type": "Feature",
  "properties": {
    "addr:full":"6298 Mount Pinos Ct Rancho Cucamonga CA 91737",
    "addr:housenumber":"6298",
    "addr:postcode":"91737",
    "addr:street":"Mount Pinos Ct",
    "iso:country":"US",
    "sg:address":"6298 Mount Pinos Ct",
    "sg:city":"Rancho Cucamonga",
    "sg:classifiers":[
        {
            "category":"Wholesale",
            "subcategory":"Hardware",
            "type":"Manufacturing & Wholesale Goods"
        }
    ],
    "sg:phone":"+1 909 980 2044",
    "sg:postcode":"91737",
    "sg:province":"CA",
    "wof:name":"Soft Jamb Company",
    "wof:placetype":"venue"
},
  "geometry": {"coordinates":[-117.549847,34.140553],"type":"Point"}
}