{
  "type": "Feature",
  "properties": {
    "iso:country":"US",
    "sg:address":"3231 Bus Park Dr",
    "sg:city":"Vista",
    "sg:classifiers":[
        {
            "category":"Professional",
            "subcategory":"Computer Services",
            "type":"Services"
        }
    ],
    "sg:phone":"+1 760 597 1589",
    "sg:postcode":"92081",
    "sg:province":"CA",
    "wof:name":"Innoverus",
    "wof:placetype":"venue"
},
  "geometry": {"coordinates":[-117.22918,33.13431],"type":"Point"}
}