{
  "type": "Feature",
  "properties": {
    "iso:country":"US",
    "sg:address":"21826 Ventura Blvd",
    "sg:city":"Woodland Hills",
    "sg:classifiers":[
        {
            "category":"Restaurant",
            "type":"Food & Drink"
        }
    ],
    "sg:phone":"+1 818 887 6353",
    "sg:postcode":"91364",
    "sg:province":"CA",
    "sg:tags":[
        "middle",
        "eastern"
    ],
    "sg:website":"shirinrestaurantinc.com/",
    "wof:name":"Shirin Restaurant",
    "wof:placetype":"venue"
},
  "geometry": {"coordinates":[-118.602997,34.168499],"type":"Point"}
}