{
  "type": "Feature",
  "properties": {
    "iso:country":"US",
    "sg:address":"2742 W Orangethorpe Ave Ste L",
    "sg:city":"Fullerton",
    "sg:classifiers":[
        {
            "category":"Building & Trades",
            "subcategory":"Construction",
            "type":"Services"
        }
    ],
    "sg:phone":"+1 714 738 5050",
    "sg:postcode":"92833",
    "sg:province":"CA",
    "sg:tags":[
        "painter"
    ],
    "wof:name":"Professional's Maintenance",
    "wof:placetype":"venue"
},
  "geometry": {"coordinates":[-117.97620000000001,33.859102],"type":"Point"}
}