{
  "type": "Feature",
  "properties": {
    "iso:country":"US",
    "sg:address":"441 S California Ave",
    "sg:city":"Palo Alto",
    "sg:classifiers":[
        {
            "category":"Organizations",
            "subcategory":"Non-profit Organization",
            "type":"Services"
        }
    ],
    "sg:phone":"+1 650 325 6666",
    "sg:postcode":"94306",
    "sg:province":"CA",
    "wof:name":"California Youth Symphony Assn",
    "wof:placetype":"venue"
},
  "geometry": {"coordinates":[-122.145399,37.425597],"type":"Point"}
}