{
  "type": "Feature",
  "properties": {
    "iso:country":"US",
    "sg:address":"2175 Acoma St",
    "sg:city":"Sacramento",
    "sg:classifiers":[
        {
            "category":"Freight",
            "type":"Transportation"
        },
        {
            "category":"Utilities",
            "subcategory":"Refuse",
            "type":"Services"
        }
    ],
    "sg:phone":"+1 916 924 3231",
    "sg:postcode":"95815",
    "sg:province":"CA",
    "sg:tags":[
        "operator",
        "local",
        "garbage",
        "collection",
        "trucking"
    ],
    "wof:name":"D & D Disposal",
    "wof:placetype":"venue"
},
  "geometry": {"coordinates":[-121.466622,38.603948],"type":"Point"}
}