{
  "type": "Feature",
  "properties": {
    "addr:full":"2790 S King Rd San Jose CA 95122",
    "addr:housenumber":"2790",
    "addr:postcode":"95122",
    "addr:street":"S King Rd",
    "iso:country":"US",
    "sg:address":"2790 S King Rd",
    "sg:city":"San Jose",
    "sg:classifiers":[
        {
            "category":"Organizations",
            "subcategory":"Religious Organization",
            "type":"Services"
        }
    ],
    "sg:phone":"+1 408 274 5611",
    "sg:postcode":"95122",
    "sg:province":"CA",
    "sg:tags":[
        "church"
    ],
    "sg:website":"www.libertybaptist.org",
    "wof:name":"Liberty Baptist Church",
    "wof:placetype":"venue"
},
  "geometry": {"coordinates":[-121.818004,37.314219],"type":"Point"}
}