{
  "type": "Feature",
  "properties": {
    "addr:full":"1632 19th St Santa Monica CA 90404",
    "addr:housenumber":"1632",
    "addr:postcode":"90404",
    "addr:street":"19Th St",
    "iso:country":"US",
    "sg:address":"1632 19th St",
    "sg:city":"Santa Monica",
    "sg:classifiers":[
        {
            "category":"Banks & Credit Unions",
            "subcategory":"Financial Services",
            "type":"Services"
        }
    ],
    "sg:phone":"+1 310 453 6911",
    "sg:postcode":"90404",
    "sg:province":"CA",
    "sg:tags":[
        "company",
        "holding"
    ],
    "wof:name":"Cal First Holdings Inc",
    "wof:placetype":"venue"
},
  "geometry": {"coordinates":[-118.475883,34.02359],"type":"Point"}
}