{
  "type": "Feature",
  "properties": {
    "addr:full":"4903 Eagle Rock Boulevard Los Angeles CA 90041",
    "addr:housenumber":"4903",
    "addr:postcode":"90041",
    "addr:street":"Eagle Rock Boulevard",
    "iso:country":"US",
    "sg:address":"4903 Eagle Rock Boulevard",
    "sg:city":"Los Angeles",
    "sg:classifiers":[
        {
            "category":"Restaurant",
            "type":"Food & Drink"
        }
    ],
    "sg:phone":"+1 323 254 2272",
    "sg:postcode":"90041",
    "sg:province":"CA",
    "sg:website":"www.kazifoodsinc.com",
    "wof:name":"Kazi Foods",
    "wof:placetype":"venue"
},
  "geometry": {"coordinates":[-118.215462,34.135159],"type":"Point"}
}