{
  "type": "Feature",
  "properties": {
    "iso:country":"US",
    "sg:address":"8930 Morro Rd",
    "sg:city":"Atascadero",
    "sg:classifiers":[
        {
            "category":"Professional",
            "subcategory":"Lawyer & Legal Services",
            "type":"Services"
        }
    ],
    "sg:phone":"+1 805 466 4711",
    "sg:postcode":"93422",
    "sg:province":"CA",
    "sg:tags":[
        "attorney"
    ],
    "wof:name":"David Fleishman",
    "wof:placetype":"venue"
},
  "geometry": {"coordinates":[-120.669725,35.469254],"type":"Point"}
}