{
  "type": "Feature",
  "properties": {
    "addr:full":"25381 Alicia Pkwy Ste M Laguna Hills CA 92653",
    "addr:housenumber":"25381",
    "addr:postcode":"92653",
    "addr:street":"Alicia Pkwy Ste M",
    "iso:country":"US",
    "sg:address":"25381 Alicia Pkwy Ste M",
    "sg:city":"Laguna Hills",
    "sg:classifiers":[
        {
            "category":"Restaurant",
            "type":"Food & Drink"
        }
    ],
    "sg:phone":"+1 949 830 5051",
    "sg:postcode":"92653",
    "sg:province":"CA",
    "sg:tags":[
        "sushi",
        "bar"
    ],
    "wof:name":"You & I Sushi",
    "wof:placetype":"venue"
},
  "geometry": {"coordinates":[-117.698246,33.593247],"type":"Point"}
}