{
  "type": "Feature",
  "properties": {
    "iso:country":"US",
    "sg:address":"1568 E Brockton Ave",
    "sg:city":"Redlands",
    "sg:classifiers":[
        {
            "category":"Home & Garden",
            "subcategory":"Home Furnishings",
            "type":"Retail Goods"
        }
    ],
    "sg:phone":"+1 951 453 1280",
    "sg:postcode":"92374",
    "sg:province":"CA",
    "sg:tags":[
        "venetian",
        "blind"
    ],
    "wof:name":"L & L Blinds & Shutters",
    "wof:placetype":"venue"
},
  "geometry": {"coordinates":[-117.150378,34.066351],"type":"Point"}
}