{
  "type": "Feature",
  "properties": {
    "addr:full":"500 W Bonita Ave San Dimas CA 91773",
    "addr:housenumber":"500",
    "addr:postcode":"91773",
    "addr:street":"W Bonita Ave",
    "iso:country":"US",
    "sg:address":"500 W Bonita Ave",
    "sg:city":"San Dimas",
    "sg:classifiers":[
        {
            "category":"Insurance",
            "subcategory":"Insurance Agent",
            "type":"Services"
        }
    ],
    "sg:phone":"+1 909 599 9616",
    "sg:postcode":"91773",
    "sg:province":"CA",
    "wof:name":"State Farm Insurance",
    "wof:placetype":"venue"
},
  "geometry": {"coordinates":[-117.818198,34.106676],"type":"Point"}
}