{
  "type": "Feature",
  "properties": {
    "addr:full":"5955 E Spring St Long Beach CA 90808",
    "addr:housenumber":"5955",
    "addr:postcode":"90808",
    "addr:street":"E Spring St",
    "iso:country":"US",
    "sg:address":"5955 E Spring St",
    "sg:city":"Long Beach",
    "sg:classifiers":[
        {
            "category":"Banks & Credit Unions",
            "subcategory":"Financial Services",
            "type":"Services"
        }
    ],
    "sg:phone":"+1 562 427 0955",
    "sg:postcode":"90808",
    "sg:province":"CA",
    "sg:tags":[
        "broker",
        "mortgage"
    ],
    "wof:name":"Beneficial California Inc",
    "wof:placetype":"venue"
},
  "geometry": {"coordinates":[-118.115528,33.810595],"type":"Point"}
}