{
  "type": "Feature",
  "properties": {
    "iso:country":"US",
    "sg:address":"14715 Rinaldi St",
    "sg:city":"San Fernando",
    "sg:classifiers":[
        {
            "category":"Shopping",
            "subcategory":"Jewelry",
            "type":"Retail Goods"
        }
    ],
    "sg:phone":"+1 818 838 9299",
    "sg:postcode":"91345",
    "sg:province":"CA",
    "sg:tags":[
        "jeweler"
    ],
    "wof:name":"Don Roberto Jewelers",
    "wof:placetype":"venue"
},
  "geometry": {"coordinates":[-118.454266,34.280196],"type":"Point"}
}