{
  "type": "Feature",
  "properties": {
    "addr:full":"2470 Estand Way Pleasant Hill CA 94523",
    "addr:housenumber":"2470",
    "addr:postcode":"94523",
    "addr:street":"Estand Way",
    "iso:country":"US",
    "sg:address":"2470 Estand Way",
    "sg:city":"Pleasant Hill",
    "sg:classifiers":[
        {
            "category":"Home & Garden",
            "subcategory":"Furniture",
            "type":"Retail Goods"
        }
    ],
    "sg:phone":"+1 925 686 6355",
    "sg:postcode":"94523",
    "sg:province":"CA",
    "sg:tags":[
        "equipment",
        "consulting"
    ],
    "wof:name":"Creative Office Systems Inc",
    "wof:placetype":"venue"
},
  "geometry": {"coordinates":[-122.05353700000001,37.940982],"type":"Point"}
}