{
  "type": "Feature",
  "properties": {
    "addr:full":"5842 Kingsley Cir Oakland CA 94605",
    "addr:housenumber":"5842",
    "addr:postcode":"94605",
    "addr:street":"Kingsley Cir",
    "iso:country":"US",
    "sg:address":"5842 Kingsley Cir",
    "sg:city":"Oakland",
    "sg:classifiers":[
        {
            "category":"Building & Trades",
            "subcategory":"Construction",
            "type":"Services"
        }
    ],
    "sg:phone":"+1 510 827 8356",
    "sg:postcode":"94605",
    "sg:province":"CA",
    "sg:tags":[
        "handyman"
    ],
    "wof:name":"Trinity Auto Repair",
    "wof:placetype":"venue"
},
  "geometry": {"coordinates":[-122.19090799999999,37.772943],"type":"Point"}
}