{
  "type": "Feature",
  "properties": {
    "iso:country":"US",
    "sg:address":"1688 N Beale Rd",
    "sg:city":"Marysville",
    "sg:classifiers":[
        {
            "category":"Shopping",
            "subcategory":"Discount & Variety Stores",
            "type":"Retail Goods"
        }
    ],
    "sg:phone":"+1 530 742 7971",
    "sg:postcode":"95901",
    "sg:province":"CA",
    "wof:name":"Dollar Giant",
    "wof:placetype":"venue"
},
  "geometry": {"coordinates":[-121.55481,39.127698],"type":"Point"}
}