{
  "type": "Feature",
  "properties": {
    "addr:full":"1777 Vine St Los Angeles CA 90028",
    "addr:housenumber":"1777",
    "addr:postcode":"90028",
    "addr:street":"Vine St",
    "iso:country":"US",
    "sg:address":"1777 Vine St",
    "sg:city":"Los Angeles",
    "sg:classifiers":[
        {
            "category":"Professional",
            "subcategory":"Lawyer & Legal Services",
            "type":"Services"
        }
    ],
    "sg:phone":"+1 323 464 6184",
    "sg:postcode":"90028",
    "sg:province":"CA",
    "sg:tags":[
        "attorney"
    ],
    "wof:name":"Thomas Hunter Russell Law Ofcs",
    "wof:placetype":"venue"
},
  "geometry": {"coordinates":[-118.326761,34.102099],"type":"Point"}
}