{
  "type": "Feature",
  "properties": {
    "iso:country":"US",
    "sg:address":"11791 S Clovis Ave",
    "sg:city":"Selma",
    "sg:classifiers":[
        {
            "category":"Farming",
            "subcategory":"Orchard",
            "type":"Manufacturing & Wholesale Goods"
        }
    ],
    "sg:phone":"+1 559 834 1328",
    "sg:postcode":"93662",
    "sg:province":"CA",
    "sg:tags":[
        "fruit",
        "tree"
    ],
    "wof:name":"Jcapple",
    "wof:placetype":"venue"
},
  "geometry": {"coordinates":[-119.70060100000001,36.566736],"type":"Point"}
}