{
  "type": "Feature",
  "properties": {
    "addr:full":"4629 Cass St San Diego CA 92109",
    "addr:housenumber":"4629",
    "addr:postcode":"92109",
    "addr:street":"Cass St",
    "iso:country":"US",
    "sg:address":"4629 Cass St",
    "sg:city":"San Diego",
    "sg:classifiers":[
        {
            "category":"Real Estate",
            "subcategory":"Real Estate Agent",
            "type":"Services"
        }
    ],
    "sg:phone":"+1 858 514 8334",
    "sg:postcode":"92109",
    "sg:province":"CA",
    "sg:tags":[
        "appraiser"
    ],
    "wof:name":"Chandos Pacific Certified",
    "wof:placetype":"venue"
},
  "geometry": {"coordinates":[-117.25231599999999,32.79918],"type":"Point"}
}