{
  "type": "Feature",
  "properties": {
    "iso:country":"US",
    "sg:address":"5245 W Centinela Avenue",
    "sg:city":"Los Angeles",
    "sg:classifiers":[
        {
            "category":"Banks & Credit Unions",
            "subcategory":"Bank",
            "type":"Services"
        }
    ],
    "sg:phone":"+1 310 338 8321",
    "sg:postcode":"90045",
    "sg:province":"CA",
    "sg:website":"www.downeysavings.com",
    "wof:name":"Downey Savings & Loan Assn",
    "wof:placetype":"venue"
},
  "geometry": {"coordinates":[-118.37213800000001,33.97722],"type":"Point"}
}