{
  "type": "Feature",
  "properties": {
    "iso:country":"US",
    "sg:address":"2335 Tulip Ct",
    "sg:city":"Mckinleyville",
    "sg:classifiers":[
        {
            "category":"Restaurant",
            "type":"Food & Drink"
        }
    ],
    "sg:phone":"+1 707 839 1730",
    "sg:postcode":"95519",
    "sg:province":"CA",
    "sg:tags":[
        "caterer"
    ],
    "wof:name":"Classic Catering",
    "wof:placetype":"venue"
},
  "geometry": {"coordinates":[-124.11368299999999,40.947919],"type":"Point"}
}