{
  "type": "Feature",
  "properties": {
    "addr:full":"819 S Alvarado Street Los Angeles CA 90057",
    "addr:housenumber":"819",
    "addr:postcode":"90057",
    "addr:street":"S Alvarado Street",
    "iso:country":"US",
    "sg:address":"819 S Alvarado Street",
    "sg:city":"Los Angeles",
    "sg:classifiers":[
        {
            "category":"Health Services",
            "subcategory":"Chiropractor",
            "type":"Services"
        }
    ],
    "sg:phone":"+1 213 365 0444",
    "sg:postcode":"90057",
    "sg:province":"CA",
    "wof:name":"Binafard Bob DC",
    "wof:placetype":"venue"
},
  "geometry": {"coordinates":[-118.278018,34.05461],"type":"Point"}
}