{
  "type": "Feature",
  "properties": {
    "iso:country":"US",
    "sg:address":"13373 Road 29",
    "sg:city":"Madera",
    "sg:classifiers":[
        {
            "category":"Place Of Worship",
            "subcategory":"Church",
            "type":"Public Place"
        },
        {
            "category":"Place Of Worship",
            "type":"Public Place"
        }
    ],
    "sg:phone":"+1 559 673 3810",
    "sg:postcode":"93638",
    "sg:province":"CA",
    "sg:tags":[
        "churches-apostolic",
        "churches-pentecostal-apostolic"
    ],
    "wof:name":"Iglesia Unida Apostolica",
    "wof:placetype":"venue"
},
  "geometry": {"coordinates":[-120.019407,36.943075],"type":"Point"}
}