{
  "type": "Feature",
  "properties": {
    "addr:full":"12841 Hawthorne Blvd Hawthorne CA 90250",
    "addr:housenumber":"12841",
    "addr:postcode":"90250",
    "addr:street":"Hawthorne Blvd",
    "iso:country":"US",
    "sg:address":"12841 Hawthorne Blvd",
    "sg:city":"Hawthorne",
    "sg:classifiers":[
        {
            "category":"Personal",
            "type":"Services"
        }
    ],
    "sg:phone":"+1 310 280 9921",
    "sg:postcode":"90250",
    "sg:province":"CA",
    "sg:tags":[
        "mail",
        "receiving"
    ],
    "wof:name":"Pony Express Depot",
    "wof:placetype":"venue"
},
  "geometry": {"coordinates":[-118.352469,33.915895],"type":"Point"}
}