{
  "type": "Feature",
  "properties": {
    "iso:country":"US",
    "sg:address":"6353 N Blackstone Ave",
    "sg:city":"Fresno",
    "sg:classifiers":[
        {
            "category":"Autos & Motor Vehicles",
            "subcategory":"Automobile Sales",
            "type":"Retail Goods"
        }
    ],
    "sg:phone":"+1 559 447 9500",
    "sg:postcode":"93710",
    "sg:province":"CA",
    "sg:tags":[
        "car",
        "dealer"
    ],
    "wof:name":"European Auto Imports",
    "wof:placetype":"venue"
},
  "geometry": {"coordinates":[-119.790361,36.829032],"type":"Point"}
}