{
  "type": "Feature",
  "properties": {
    "addr:full":"5916 Via Casitas Carmichael CA 95608",
    "addr:housenumber":"5916",
    "addr:postcode":"95608",
    "addr:street":"Via Casitas",
    "iso:country":"US",
    "sg:address":"5916 Via Casitas",
    "sg:city":"Carmichael",
    "sg:classifiers":[
        {
            "category":"Professional",
            "subcategory":"Computer Services",
            "type":"Services"
        },
        {
            "category":"Internet Cafe",
            "subcategory":"None",
            "type":"Food & Drink"
        }
    ],
    "sg:phone":"+1 916 331 2778",
    "sg:postcode":"95608",
    "sg:province":"CA",
    "sg:tags":[
        "product",
        "software"
    ],
    "wof:name":"Trans Digital Corp",
    "wof:placetype":"venue"
},
  "geometry": {"coordinates":[-121.32638900000001,38.670219],"type":"Point"}
}