{
  "type": "Feature",
  "properties": {
    "iso:country":"US",
    "sg:address":"1275 S Winchester Blvd",
    "sg:city":"San Jose",
    "sg:classifiers":[
        {
            "category":"Organizations",
            "subcategory":"Professional Association",
            "type":"Services"
        }
    ],
    "sg:phone":"+1 408 260 6741",
    "sg:postcode":"95128",
    "sg:province":"CA",
    "sg:tags":[
        "education",
        "health"
    ],
    "wof:name":"Community Wellness",
    "wof:placetype":"venue"
},
  "geometry": {"coordinates":[-121.949996,37.298538],"type":"Point"}
}