{
  "type": "Feature",
  "properties": {
    "addr:full":"1421 N Alston Ave Colton CA 92324",
    "addr:housenumber":"1421",
    "addr:postcode":"92324",
    "addr:street":"N Alston Ave",
    "iso:country":"US",
    "sg:address":"1421 N Alston Ave",
    "sg:city":"Colton",
    "sg:classifiers":[
        {
            "category":"Home & Garden",
            "subcategory":"Building Materials",
            "type":"Retail Goods"
        }
    ],
    "sg:phone":"+1 909 953 4166",
    "sg:postcode":"92324",
    "sg:province":"CA",
    "sg:tags":[
        "mixed",
        "concrete"
    ],
    "wof:name":"Olivar Ready Mix",
    "wof:placetype":"venue"
},
  "geometry": {"coordinates":[-117.335235,34.083168],"type":"Point"}
}