{
  "type": "Feature",
  "properties": {
    "iso:country":"US",
    "sg:address":"116 Washington Ave",
    "sg:city":"Richmond",
    "sg:classifiers":[
        {
            "category":"Food & Beverages",
            "subcategory":"Specialty",
            "type":"Retail Goods"
        },
        {
            "category":"Wholesale",
            "subcategory":"Groceries",
            "type":"Manufacturing & Wholesale Goods"
        }
    ],
    "sg:phone":"+1 510 412 0900",
    "sg:postcode":"94801",
    "sg:province":"CA",
    "sg:tags":[
        "gourmet",
        "shop",
        "organic",
        "certified"
    ],
    "wof:name":"Multiple Organics Inc",
    "wof:placetype":"venue"
},
  "geometry": {"coordinates":[-122.385796,37.926459],"type":"Point"}
}