{
  "type": "Feature",
  "properties": {
    "addr:full":"10951 Cherry Ave Los Alamitos CA 90720",
    "addr:housenumber":"10951",
    "addr:postcode":"90720",
    "addr:street":"Cherry Ave",
    "iso:country":"US",
    "sg:address":"10951 Cherry Ave",
    "sg:city":"Los Alamitos",
    "sg:classifiers":[
        {
            "category":"Health Services",
            "subcategory":"Optometrist",
            "type":"Services"
        }
    ],
    "sg:phone":"+1 562 430 6161",
    "sg:postcode":"90720",
    "sg:province":"CA",
    "sg:website":"alamitoseyecare.com/",
    "wof:name":"Avani Patel OD",
    "wof:placetype":"venue"
},
  "geometry": {"coordinates":[-118.06833,33.803507],"type":"Point"}
}