{
  "type": "Feature",
  "properties": {
    "addr:full":"139 E Hermosa St Lindsay CA 93247",
    "addr:housenumber":"139",
    "addr:postcode":"93247",
    "addr:street":"E Hermosa St",
    "iso:country":"US",
    "sg:address":"139 E Hermosa St",
    "sg:city":"Lindsay",
    "sg:classifiers":[
        {
            "category":"Retail",
            "subcategory":"Veterinary Services",
            "type":"Services"
        }
    ],
    "sg:phone":"+1 559 562 6018",
    "sg:postcode":"93247",
    "sg:province":"CA",
    "sg:tags":[
        "veterinarian"
    ],
    "wof:name":"Lindsay-Westwood Veterinary",
    "wof:placetype":"venue"
},
  "geometry": {"coordinates":[-119.09122600000001,36.205104],"type":"Point"}
}