{
  "type": "Feature",
  "properties": {
    "addr:full":"25500 Rancho Niguel Rd. #210 Laguna Niguel CA 92677",
    "addr:housenumber":"25500",
    "addr:postcode":"92677",
    "addr:street":"Rancho Niguel Rd. # 210",
    "iso:country":"US",
    "sg:address":"25500 Rancho Niguel Rd. #210",
    "sg:city":"Laguna Niguel",
    "sg:classifiers":[
        {
            "category":"Health Services",
            "subcategory":"Dentist",
            "type":"Services"
        }
    ],
    "sg:phone":"+1 949 215 0112",
    "sg:postcode":"92677",
    "sg:province":"CA",
    "wof:name":"Damian L Newhart DDS",
    "wof:placetype":"venue"
},
  "geometry": {"coordinates":[-117.684485,33.555442],"type":"Point"}
}