{
  "type": "Feature",
  "properties": {
    "addr:full":"15333 Culver Dr Ste 500 Irvine CA 92604",
    "addr:housenumber":"15333",
    "addr:postcode":"92604",
    "addr:street":"Culver Dr Ste 500",
    "iso:country":"US",
    "sg:address":"15333 Culver Dr Ste 500",
    "sg:city":"Irvine",
    "sg:classifiers":[
        {
            "category":"Shopping",
            "subcategory":"Pets & Pet Supplies",
            "type":"Retail Goods"
        }
    ],
    "sg:phone":"+1 949 262 1400",
    "sg:postcode":"92604",
    "sg:province":"CA",
    "sg:tags":[
        "store"
    ],
    "wof:name":"Petco",
    "wof:placetype":"venue"
},
  "geometry": {"coordinates":[-117.796997,33.695801],"type":"Point"}
}