{
  "type": "Feature",
  "properties": {
    "addr:full":"8001 Laurel Canyon Blvd North Hollywood CA 91605",
    "addr:housenumber":"8001",
    "addr:postcode":"91605",
    "addr:street":"Laurel Canyon Blvd",
    "iso:country":"US",
    "sg:address":"8001 Laurel Canyon Blvd",
    "sg:city":"North Hollywood",
    "sg:classifiers":[
        {
            "category":"Health Services",
            "subcategory":"Doctor",
            "type":"Services"
        }
    ],
    "sg:phone":"+1 818 767 1973",
    "sg:postcode":"91605",
    "sg:province":"CA",
    "wof:name":"Jim-Sher Medical Group",
    "wof:placetype":"venue"
},
  "geometry": {"coordinates":[-118.397003,34.215698],"type":"Point"}
}