{
  "type": "Feature",
  "properties": {
    "iso:country":"US",
    "sg:address":"7484 Mitchell Dr",
    "sg:city":"Rohnert Park",
    "sg:classifiers":[
        {
            "category":"Professional",
            "subcategory":"Engineering",
            "type":"Services"
        }
    ],
    "sg:phone":"+1 707 763 2862",
    "sg:postcode":"94928",
    "sg:province":"CA",
    "sg:tags":[
        "engineer"
    ],
    "wof:name":"Hartman Civil Engineering Inc",
    "wof:placetype":"venue"
},
  "geometry": {"coordinates":[-122.68156,38.333827],"type":"Point"}
}