{
  "type": "Feature",
  "properties": {
    "addr:full":"5002 B Telegraph Ave Oakland CA 94609",
    "addr:housenumber":"5002 b",
    "addr:postcode":"94609",
    "addr:street":"Telegraph Ave",
    "iso:country":"US",
    "sg:address":"5002 B Telegraph Ave",
    "sg:city":"Oakland",
    "sg:classifiers":[
        {
            "category":"Food & Beverages",
            "subcategory":"Chocolate",
            "type":"Retail Goods"
        }
    ],
    "sg:phone":"+1 877 612 2639",
    "sg:postcode":"94609",
    "sg:province":"CA",
    "sg:tags":[
        "shop",
        "chocolatiers"
    ],
    "sg:website":"www.cosmicchocolate.com",
    "wof:name":"Cosmic Chocolate",
    "wof:placetype":"venue"
},
  "geometry": {"coordinates":[-122.26238600000001,37.836585],"type":"Point"}
}