{
  "type": "Feature",
  "properties": {
    "addr:full":"449 N Santa Cruz Ave Los Gatos CA 95030",
    "addr:housenumber":"449",
    "addr:postcode":"95030",
    "addr:street":"N Santa Cruz Ave",
    "iso:country":"US",
    "sg:address":"449 N Santa Cruz Ave",
    "sg:city":"Los Gatos",
    "sg:classifiers":[
        {
            "category":"Real Estate",
            "subcategory":"Real Estate Services",
            "type":"Services"
        }
    ],
    "sg:phone":"+1 408 489 0793",
    "sg:postcode":"95030",
    "sg:province":"CA",
    "sg:website":"www.MarinaZierk.com",
    "wof:name":"Marina Zierk Residential Real Estate",
    "wof:placetype":"venue"
},
  "geometry": {"coordinates":[-121.980457,37.23079],"type":"Point"}
}