{
  "type": "Feature",
  "properties": {
    "addr:full":"1055 W 21st St San Bernardino CA 92405",
    "addr:housenumber":"1055",
    "addr:postcode":"92405",
    "addr:street":"W 21St St",
    "iso:country":"US",
    "sg:address":"1055 W 21st St",
    "sg:city":"San Bernardino",
    "sg:classifiers":[
        {
            "category":"Home & Garden",
            "subcategory":"Building Materials",
            "type":"Retail Goods"
        }
    ],
    "sg:phone":"+1 909 881 1851",
    "sg:postcode":"92405",
    "sg:province":"CA",
    "sg:tags":[
        "supply"
    ],
    "sg:website":"www.homedepot.com",
    "wof:name":"Home Depot",
    "wof:placetype":"venue"
},
  "geometry": {"coordinates":[-117.306635,34.135031],"type":"Point"}
}