{
  "type": "Feature",
  "properties": {
    "addr:full":"441 Marsh St San Luis Obispo CA 93401",
    "addr:housenumber":"441",
    "addr:postcode":"93401",
    "addr:street":"Marsh St",
    "iso:country":"US",
    "sg:address":"441 Marsh St",
    "sg:city":"San Luis Obispo",
    "sg:classifiers":[
        {
            "category":"Sports & Exercise",
            "subcategory":"Gym",
            "type":"Entertainment"
        }
    ],
    "sg:phone":"+1 805 543 4563",
    "sg:postcode":"93401",
    "sg:province":"CA",
    "sg:tags":[
        "club",
        "health",
        "studio",
        "gymnasium"
    ],
    "wof:name":"Curves For Women",
    "wof:placetype":"venue"
},
  "geometry": {"coordinates":[-120.666774,35.276155],"type":"Point"}
}