{
  "type": "Feature",
  "properties": {
    "addr:full":"1311 Merced St Richmond CA 94804",
    "addr:housenumber":"1311",
    "addr:postcode":"94804",
    "addr:street":"Merced St",
    "iso:country":"US",
    "sg:address":"1311 Merced St",
    "sg:city":"Richmond",
    "sg:classifiers":[
        {
            "category":"Professional",
            "type":"Services"
        }
    ],
    "sg:phone":"+1 510 237 4990",
    "sg:postcode":"94804",
    "sg:province":"CA",
    "wof:name":"Ancient Free & Accepted M",
    "wof:placetype":"venue"
},
  "geometry": {"coordinates":[-122.319427,37.913765],"type":"Point"}
}