{
  "type": "Feature",
  "properties": {
    "iso:country":"US",
    "sg:address":"1311 Merced St",
    "sg:city":"Richmond",
    "sg:classifiers":[
        {
            "category":"Professional",
            "type":"Services"
        }
    ],
    "sg:phone":"+1 510 237 4990",
    "sg:postcode":"94804",
    "sg:province":"CA",
    "wof:name":"Ancient Free & Accepted M",
    "wof:placetype":"venue"
},
  "geometry": {"coordinates":[-122.319427,37.913765],"type":"Point"}
}