{
  "type": "Feature",
  "properties": {
    "addr:full":"4442 Piedmont Ave Oakland CA 94611",
    "addr:housenumber":"4442",
    "addr:postcode":"94611",
    "addr:street":"Piedmont Ave",
    "iso:country":"US",
    "sg:address":"4442 Piedmont Ave",
    "sg:city":"Oakland",
    "sg:classifiers":[
        {
            "category":"Real Estate",
            "subcategory":"Real Estate Agent",
            "type":"Services"
        }
    ],
    "sg:phone":"+1 510 652 1480",
    "sg:postcode":"94611",
    "sg:province":"CA",
    "wof:name":"Help U Sell",
    "wof:placetype":"venue"
},
  "geometry": {"coordinates":[-122.245998,37.831199],"type":"Point"}
}