{
  "type": "Feature",
  "properties": {
    "iso:country":"US",
    "sg:address":"78 Normandy Ln",
    "sg:city":"Atherton",
    "sg:classifiers":[
        {
            "category":"Building & Trades",
            "subcategory":"Electrical",
            "type":"Services"
        }
    ],
    "sg:phone":"+1 650 462 1999",
    "sg:postcode":"94027",
    "sg:province":"CA",
    "sg:tags":[
        "lighting",
        "landscape"
    ],
    "wof:name":"Outdoor Lighting Perspectives",
    "wof:placetype":"venue"
},
  "geometry": {"coordinates":[-122.20159700000001,37.463633],"type":"Point"}
}