{
  "type": "Feature",
  "properties": {
    "iso:country":"US",
    "sg:address":"8141 Firestone Blvd",
    "sg:city":"Downey",
    "sg:classifiers":[
        {
            "category":"Utilities",
            "subcategory":"Cable",
            "type":"Services"
        }
    ],
    "sg:phone":"+1 562 862 2222",
    "sg:postcode":"90241",
    "sg:province":"CA",
    "sg:tags":[
        "television"
    ],
    "wof:name":"Douglas A Maniaci",
    "wof:placetype":"venue"
},
  "geometry": {"coordinates":[-118.135385,33.941543],"type":"Point"}
}