{
  "type": "Feature",
  "properties": {
    "addr:full":"5060 S Montclair Plaza Ln Montclair CA 91763",
    "addr:housenumber":"5060",
    "addr:postcode":"91763",
    "addr:street":"S Montclair Plaza Ln",
    "iso:country":"US",
    "sg:address":"5060 S Montclair Plaza Ln",
    "sg:city":"Montclair",
    "sg:classifiers":[
        {
            "category":"Shopping",
            "type":"Retail Goods"
        }
    ],
    "sg:phone":"+1 909 447 4618",
    "sg:postcode":"91763",
    "sg:province":"CA",
    "sg:tags":[
        "material",
        "artist",
        "supply"
    ],
    "wof:name":"Magic Colors",
    "wof:placetype":"venue"
},
  "geometry": {"coordinates":[-117.691638,34.085254],"type":"Point"}
}