{
  "type": "Feature",
  "properties": {
    "addr:full":"16000 Ventura Blvd Encino CA 91436",
    "addr:housenumber":"16000",
    "addr:postcode":"91436",
    "addr:street":"Ventura Blvd",
    "iso:country":"US",
    "sg:address":"16000 Ventura Blvd",
    "sg:city":"Encino",
    "sg:classifiers":[
        {
            "category":"Manufacturing",
            "subcategory":"Petroleum Products",
            "type":"Manufacturing & Wholesale Goods"
        }
    ],
    "sg:phone":"+1 818 728 8700",
    "sg:postcode":"91436",
    "sg:province":"CA",
    "sg:tags":[
        "contract"
    ],
    "wof:name":"Neongrid",
    "wof:placetype":"venue"
},
  "geometry": {"coordinates":[-118.48146800000001,34.156052],"type":"Point"}
}