{
  "type": "Feature",
  "properties": {
    "iso:country":"US",
    "sg:address":"1951 E Valley Pkwy",
    "sg:city":"Escondido",
    "sg:classifiers":[
        {
            "category":"Education",
            "subcategory":"College",
            "type":"Public Place"
        }
    ],
    "sg:phone":"+1 760 432 0624",
    "sg:postcode":"92027",
    "sg:province":"CA",
    "sg:tags":[
        "academic",
        "school"
    ],
    "sg:website":"www.palomar.edu",
    "wof:name":"Escondido Education Ctr",
    "wof:placetype":"venue"
},
  "geometry": {"coordinates":[-117.053465,33.136558],"type":"Point"}
}