{
  "type": "Feature",
  "properties": {
    "iso:country":"US",
    "sg:address":"1132 S Marengo Ave",
    "sg:city":"Pasadena",
    "sg:classifiers":[
        {
            "category":"Recreation",
            "type":"Entertainment"
        }
    ],
    "sg:phone":"+1 626 799 6745",
    "sg:postcode":"91106",
    "sg:province":"CA",
    "sg:tags":[
        "club",
        "membership",
        "baseball"
    ],
    "wof:name":"Pasadena Southwest Little Leag",
    "wof:placetype":"venue"
},
  "geometry": {"coordinates":[-118.145686,34.125937],"type":"Point"}
}