{
  "type": "Feature",
  "properties": {
    "iso:country":"US",
    "sg:address":"50 Sand Creek Rd",
    "sg:city":"Brentwood",
    "sg:classifiers":[
        {
            "category":"Professional",
            "subcategory":"Management & Consulting",
            "type":"Services"
        }
    ],
    "sg:phone":"+1 925 947 4858",
    "sg:postcode":"94513",
    "sg:province":"CA",
    "sg:tags":[
        "construction"
    ],
    "wof:name":"GBM",
    "wof:placetype":"venue"
},
  "geometry": {"coordinates":[-121.697956,37.94664],"type":"Point"}
}