{
  "type": "Feature",
  "properties": {
    "iso:country":"US",
    "sg:address":"175 S Anza St",
    "sg:city":"El Cajon",
    "sg:classifiers":[
        {
            "category":"Social Services",
            "subcategory":"Adult Care",
            "type":"Services"
        }
    ],
    "sg:phone":"+1 619 593 1077",
    "sg:postcode":"92020",
    "sg:province":"CA",
    "sg:tags":[
        "organization",
        "senior",
        "citizen"
    ],
    "wof:name":"Salvation Army",
    "wof:placetype":"venue"
},
  "geometry": {"coordinates":[-116.948127,32.793961],"type":"Point"}
}