{
  "type": "Feature",
  "properties": {
    "iso:country":"US",
    "sg:address":"14814 Hawthorne Blvd",
    "sg:city":"Lawndale",
    "sg:classifiers":[
        {
            "category":"Travel",
            "subcategory":"Hotels & Motels",
            "type":"Entertainment"
        }
    ],
    "sg:phone":"+1 310 676 1111",
    "sg:postcode":"90260",
    "sg:province":"CA",
    "sg:website":"www.baymontinns.com/Baymont/cont...",
    "wof:name":"Baymont Inn & Suites",
    "wof:placetype":"venue"
},
  "geometry": {"coordinates":[-118.351665,33.896805],"type":"Point"}
}