{
  "type": "Feature",
  "properties": {
    "addr:full":"628 Thompson Ave Glendale CA 91201",
    "addr:housenumber":"628",
    "addr:postcode":"91201",
    "addr:street":"Thompson Ave",
    "iso:country":"US",
    "sg:address":"628 Thompson Ave",
    "sg:city":"Glendale",
    "sg:classifiers":[
        {
            "category":"Building & Trades",
            "subcategory":"Electrical",
            "type":"Services"
        }
    ],
    "sg:phone":"+1 818 240 4060",
    "sg:postcode":"91201",
    "sg:province":"CA",
    "sg:tags":[
        "industrial",
        "electrician",
        "contractors-commercial",
        "electric"
    ],
    "wof:name":"Reyes Electrical Contractors",
    "wof:placetype":"venue"
},
  "geometry": {"coordinates":[-118.297873,34.166615],"type":"Point"}
}