{
  "type": "Feature",
  "properties": {
    "addr:full":"1660 8th St Los Osos CA 93402",
    "addr:housenumber":"1660",
    "addr:postcode":"93402",
    "addr:street":"8Th St",
    "iso:country":"US",
    "sg:address":"1660 8th St",
    "sg:city":"Los Osos",
    "sg:classifiers":[
        {
            "category":"Shopping",
            "subcategory":"Clothing, Apparel, & Fashions",
            "type":"Retail Goods"
        }
    ],
    "sg:phone":"+1 805 528 3463",
    "sg:postcode":"93402",
    "sg:province":"CA",
    "sg:tags":[
        "infant",
        "wear"
    ],
    "wof:name":"Naturally Jennifer",
    "wof:placetype":"venue"
},
  "geometry": {"coordinates":[-120.83428600000001,35.321338],"type":"Point"}
}