{
  "type": "Feature",
  "properties": {
    "addr:full":"11664 National Blvd #404 Los Angeles CA 90064",
    "addr:housenumber":"11664",
    "addr:postcode":"90064",
    "addr:street":"National Blvd # 404",
    "iso:country":"US",
    "sg:address":"11664 National Blvd #404",
    "sg:city":"Los Angeles",
    "sg:classifiers":[
        {
            "category":"Building & Trades",
            "subcategory":"Plumbing",
            "type":"Services"
        }
    ],
    "sg:phone":"+1 310 410 2900",
    "sg:postcode":"90064",
    "sg:province":"CA",
    "sg:website":"www.michaelmeyerplumbing.blogspo...",
    "wof:name":"Michael Meyer Plumbing",
    "wof:placetype":"venue"
},
  "geometry": {"coordinates":[-118.43813299999999,34.022949],"type":"Point"}
}