{
  "type": "Feature",
  "properties": {
    "iso:country":"US",
    "sg:address":"737 Fairview Dr",
    "sg:city":"Woodland",
    "sg:classifiers":[
        {
            "category":"Professional",
            "subcategory":"Business Services",
            "type":"Services"
        }
    ],
    "sg:phone":"+1 530 662 4132",
    "sg:postcode":"95695",
    "sg:province":"CA",
    "wof:name":"Creations By Marilyn",
    "wof:placetype":"venue"
},
  "geometry": {"coordinates":[-121.798951,38.671079],"type":"Point"}
}