{
  "type": "Feature",
  "properties": {
    "addr:full":"3010 Canyon Vista Dr Colton CA 92324",
    "addr:housenumber":"3010",
    "addr:postcode":"92324",
    "addr:street":"Canyon Vista Dr",
    "iso:country":"US",
    "sg:address":"3010 Canyon Vista Dr",
    "sg:city":"Colton",
    "sg:classifiers":[
        {
            "category":"Health Services",
            "subcategory":"Medical Lab",
            "type":"Services"
        }
    ],
    "sg:phone":"+1 909 370 4784",
    "sg:postcode":"92324",
    "sg:province":"CA",
    "sg:tags":[
        "laboratory",
        "dental"
    ],
    "wof:name":"Select Dental Lab",
    "wof:placetype":"venue"
},
  "geometry": {"coordinates":[-117.277079,34.040527],"type":"Point"}
}