{
  "type": "Feature",
  "properties": {
    "addr:full":"3623 Planz Rd Bakersfield CA 93309",
    "addr:housenumber":"3623",
    "addr:postcode":"93309",
    "addr:street":"Planz Rd",
    "iso:country":"US",
    "sg:address":"3623 Planz Rd",
    "sg:city":"Bakersfield",
    "sg:classifiers":[
        {
            "category":"Home & Garden",
            "subcategory":"Home Furnishings",
            "type":"Retail Goods"
        }
    ],
    "sg:phone":"+1 661 831 0742",
    "sg:postcode":"93309",
    "sg:province":"CA",
    "sg:tags":[
        "beveled",
        "glass",
        "ornamental"
    ],
    "wof:name":"RDS Imports & Exclusive Gift",
    "wof:placetype":"venue"
},
  "geometry": {"coordinates":[-119.04403499999999,35.32491],"type":"Point"}
}