{
  "type": "Feature",
  "properties": {
    "iso:country":"US",
    "sg:address":"27468 Ynez Rd",
    "sg:city":"Temecula",
    "sg:classifiers":[
        {
            "category":"Shopping",
            "subcategory":"Stationery & Office Supplies",
            "type":"Retail Goods"
        }
    ],
    "sg:phone":"+1 951 506 5276",
    "sg:postcode":"92591",
    "sg:province":"CA",
    "sg:tags":[
        "album",
        "scrapbook"
    ],
    "wof:name":"Mad Scrapper",
    "wof:placetype":"venue"
},
  "geometry": {"coordinates":[-117.150165,33.506889],"type":"Point"}
}