{
  "type": "Feature",
  "properties": {
    "iso:country":"US",
    "sg:address":"1065 E Bradley Ave",
    "sg:city":"El Cajon",
    "sg:classifiers":[
        {
            "category":"Manufacturing",
            "subcategory":"Signs",
            "type":"Manufacturing & Wholesale Goods"
        }
    ],
    "sg:phone":"+1 619 596 9989",
    "sg:postcode":"92021",
    "sg:province":"CA",
    "wof:name":"Signagraphics",
    "wof:placetype":"venue"
},
  "geometry": {"coordinates":[-116.94664400000001,32.819029],"type":"Point"}
}