{
  "type": "Feature",
  "properties": {
    "iso:country":"US",
    "sg:address":"27736 Industrial Blvd",
    "sg:city":"Hayward",
    "sg:classifiers":[
        {
            "category":"Autos & Motor Vehicles",
            "subcategory":"Auto Supplies",
            "type":"Retail Goods"
        }
    ],
    "sg:phone":"+1 510 784 2549",
    "sg:postcode":"94545",
    "sg:province":"CA",
    "sg:tags":[
        "equipment",
        "racing",
        "car",
        "automobile"
    ],
    "wof:name":"Teizin Trading Co",
    "wof:placetype":"venue"
},
  "geometry": {"coordinates":[-122.105546,37.626458],"type":"Point"}
}