{
  "type": "Feature",
  "properties": {
    "addr:full":"2 Vashell Way Orinda CA 94563",
    "addr:housenumber":"2",
    "addr:postcode":"94563",
    "addr:street":"Vashell Way",
    "iso:country":"US",
    "sg:address":"2 Vashell Way",
    "sg:city":"Orinda",
    "sg:classifiers":[
        {
            "category":"Retail",
            "subcategory":"Veterinary Services",
            "type":"Services"
        }
    ],
    "sg:phone":"+1 925 254 0491",
    "sg:postcode":"94563",
    "sg:province":"CA",
    "wof:name":"Crossroads Veterinary",
    "wof:placetype":"venue"
},
  "geometry": {"coordinates":[-122.182152,37.879027],"type":"Point"}
}