{
  "type": "Feature",
  "properties": {
    "iso:country":"US",
    "sg:address":"730 Euclid Ave",
    "sg:city":"San Francisco",
    "sg:classifiers":[
        {
            "category":"Arts & Performance",
            "subcategory":"Arts Center",
            "type":"Entertainment"
        }
    ],
    "sg:phone":"+1 415 387 6833",
    "sg:postcode":"94118",
    "sg:province":"CA",
    "sg:tags":[
        "performing"
    ],
    "wof:name":"Belly Dancing by Baptiste",
    "wof:placetype":"venue"
},
  "geometry": {"coordinates":[-122.457387,37.784153],"type":"Point"}
}