{
  "type": "Feature",
  "properties": {
    "addr:full":"221 S Beverly Dr Beverly Hills CA 90212",
    "addr:housenumber":"221",
    "addr:postcode":"90212",
    "addr:street":"S Beverly Dr",
    "iso:country":"US",
    "sg:address":"221 S Beverly Dr",
    "sg:city":"Beverly Hills",
    "sg:classifiers":[
        {
            "category":"Retail",
            "subcategory":"Storage",
            "type":"Services"
        }
    ],
    "sg:phone":"+1 310 271 3800",
    "sg:postcode":"90212",
    "sg:province":"CA",
    "sg:tags":[
        "self"
    ],
    "sg:website":"sites.google.com/site/beverlyhil...",
    "wof:name":"Beverly Hills Storage",
    "wof:placetype":"venue"
},
  "geometry": {"coordinates":[-118.399089,34.064141],"type":"Point"}
}