{
  "type": "Feature",
  "properties": {
    "addr:full":"1272 Yosemite Ave Manteca CA 95336",
    "addr:housenumber":"1272",
    "addr:postcode":"95336",
    "addr:street":"Yosemite Ave",
    "iso:country":"US",
    "sg:address":"1272 Yosemite Ave",
    "sg:city":"Manteca",
    "sg:classifiers":[
        {
            "category":"Restaurant",
            "type":"Food & Drink"
        }
    ],
    "sg:phone":"+1 209 824 4499",
    "sg:postcode":"95336",
    "sg:province":"CA",
    "wof:name":"Applebee's Neighborhood Grill",
    "wof:placetype":"venue"
},
  "geometry": {"coordinates":[-121.201634,37.797444],"type":"Point"}
}