{
  "type": "Feature",
  "properties": {
    "addr:full":"5575 Fircrest Dr Yorba Linda CA 92886",
    "addr:housenumber":"5575",
    "addr:postcode":"92886",
    "addr:street":"Fircrest Dr",
    "iso:country":"US",
    "sg:address":"5575 Fircrest Dr",
    "sg:city":"Yorba Linda",
    "sg:classifiers":[
        {
            "category":"Banks & Credit Unions",
            "subcategory":"Financial Services",
            "type":"Services"
        }
    ],
    "sg:phone":"+1 714 777 6663",
    "sg:postcode":"92886",
    "sg:province":"CA",
    "sg:tags":[
        "broker",
        "mortgage"
    ],
    "wof:name":"Olympic Financial Services",
    "wof:placetype":"venue"
},
  "geometry": {"coordinates":[-117.805725,33.881032],"type":"Point"}
}