{
  "type": "Feature",
  "properties": {
    "addr:full":"University of Southern California 3502 Watt Way Los Angeles CA 90089",
    "addr:housenumber":"3502",
    "addr:postcode":"90089",
    "addr:street":"Watt Way",
    "iso:country":"US",
    "sg:address":"University of Southern California 3502 Watt Way",
    "sg:city":"Los Angeles",
    "sg:classifiers":[
        {
            "category":"Education",
            "subcategory":"University",
            "type":"Public Place"
        }
    ],
    "sg:phone":"+1 213 740 5297",
    "sg:postcode":"90089",
    "sg:province":"CA",
    "sg:tags":[
        "college"
    ],
    "sg:website":"annenberg.usc.edu/",
    "wof:name":"Annenberg School for Communication & Journalism",
    "wof:placetype":"venue"
},
  "geometry": {"coordinates":[-118.285858,34.023357],"type":"Point"}
}