{
  "type": "Feature",
  "properties": {
    "addr:full":"4029 N Marks Ave Fresno CA 93722",
    "addr:housenumber":"4029",
    "addr:postcode":"93722",
    "addr:street":"N Marks Ave",
    "iso:country":"US",
    "sg:address":"4029 N Marks Ave",
    "sg:city":"Fresno",
    "sg:classifiers":[
        {
            "category":"Restaurant",
            "type":"Food & Drink"
        }
    ],
    "sg:phone":"+1 559 224 1800",
    "sg:postcode":"93722",
    "sg:province":"CA",
    "wof:name":"Pizza Land Inc",
    "wof:placetype":"venue"
},
  "geometry": {"coordinates":[-119.844352,36.794148],"type":"Point"}
}