{
  "type": "Feature",
  "properties": {
    "iso:country":"US",
    "sg:address":"1325 Shenandoah Rd",
    "sg:city":"San Marino",
    "sg:classifiers":[
        {
            "category":"Professional",
            "type":"Services"
        }
    ],
    "sg:phone":"+1 626 795 9186",
    "sg:postcode":"91108",
    "sg:province":"CA",
    "wof:name":"Dcng LLC",
    "wof:placetype":"venue"
},
  "geometry": {"coordinates":[-118.122087,34.121775],"type":"Point"}
}