{
  "type": "Feature",
  "properties": {
    "iso:country":"US",
    "sg:address":"1012 N Santa Anita Ave",
    "sg:city":"Arcadia",
    "sg:classifiers":[
        {
            "category":"Manufacturing",
            "subcategory":"Printing",
            "type":"Manufacturing & Wholesale Goods"
        }
    ],
    "sg:phone":"+1 626 445 2268",
    "sg:postcode":"91006",
    "sg:province":"CA",
    "sg:tags":[
        "commercial"
    ],
    "wof:name":"Point",
    "wof:placetype":"venue"
},
  "geometry": {"coordinates":[-118.03156,34.150868],"type":"Point"}
}