{
  "type": "Feature",
  "properties": {
    "iso:country":"US",
    "sg:address":"4001 Mount Blackburn Ave",
    "sg:city":"San Diego",
    "sg:classifiers":[
        {
            "category":"Shopping",
            "type":"Retail Goods"
        }
    ],
    "sg:phone":"+1 858 277 3800",
    "sg:postcode":"92111",
    "sg:province":"CA",
    "sg:tags":[
        "mural"
    ],
    "wof:name":"Mural Magic",
    "wof:placetype":"venue"
},
  "geometry": {"coordinates":[-117.185975,32.814546],"type":"Point"}
}