{
  "type": "Feature",
  "properties": {
    "iso:country":"US",
    "sg:address":"435 N Bedford Dr",
    "sg:city":"Beverly Hills",
    "sg:classifiers":[
        {
            "category":"Health Services",
            "subcategory":"Doctor",
            "type":"Services"
        }
    ],
    "sg:phone":"+1 310 276 2009",
    "sg:postcode":"90210",
    "sg:province":"CA",
    "sg:tags":[
        "dentist"
    ],
    "wof:name":"Janet Refoa DDS",
    "wof:placetype":"venue"
},
  "geometry": {"coordinates":[-118.405789,34.068491],"type":"Point"}
}