{
  "type": "Feature",
  "properties": {
    "addr:full":"2021 N Gateway Blvd Fresno CA 93727",
    "addr:housenumber":"2021",
    "addr:postcode":"93727",
    "addr:street":"N Gateway Blvd",
    "iso:country":"US",
    "sg:address":"2021 N Gateway Blvd",
    "sg:city":"Fresno",
    "sg:classifiers":[
        {
            "category":"Professional",
            "subcategory":"Engineering",
            "type":"Services"
        }
    ],
    "sg:phone":"+1 559 252 7223",
    "sg:postcode":"93727",
    "sg:province":"CA",
    "sg:tags":[
        "engineer"
    ],
    "sg:website":"www.rabeengineering.com",
    "wof:name":"Rabe Engineering Inc",
    "wof:placetype":"venue"
},
  "geometry": {"coordinates":[-119.726832,36.767328],"type":"Point"}
}