{
  "type": "Feature",
  "properties": {
    "iso:country":"US",
    "sg:address":"1128 Jacklin Road, #A",
    "sg:city":"Milpitas",
    "sg:classifiers":[
        {
            "category":"Insurance",
            "subcategory":"Hazard Insurance",
            "type":"Services"
        }
    ],
    "sg:phone":"+1 408 966 0318",
    "sg:postcode":"95035",
    "sg:province":"CA",
    "sg:website":"www.frankfanginsurance.com",
    "wof:name":"Frank Fang Insurance Service - Farmers",
    "wof:placetype":"venue"
},
  "geometry": {"coordinates":[-121.889759,37.446882],"type":"Point"}
}