{
  "type": "Feature",
  "properties": {
    "iso:country":"US",
    "sg:address":"13421 Highland Valley Rd",
    "sg:city":"Escondido",
    "sg:classifiers":[
        {
            "category":"Real Estate",
            "subcategory":"Real Estate Agent",
            "type":"Services"
        }
    ],
    "sg:phone":"+1 858 566 7466",
    "sg:postcode":"92128",
    "sg:province":"CA",
    "sg:website":"www.pinerychristmastrees.com",
    "wof:name":"Pinery Christmas Trees Co",
    "wof:placetype":"venue"
},
  "geometry": {"coordinates":[-117.059293,33.053582],"type":"Point"}
}