{
  "type": "Feature",
  "properties": {
    "iso:country":"US",
    "sg:address":"950 E Katella Ave STE 6",
    "sg:city":"Orange",
    "sg:classifiers":[
        {
            "category":"Professional",
            "type":"Services"
        },
        {
            "category":"Banks & Credit Unions",
            "subcategory":"Financial Services",
            "type":"Services"
        }
    ],
    "sg:phone":"+1 714 769 3410",
    "sg:postcode":"92867",
    "sg:province":"CA",
    "sg:website":"www.bigfishpayroll.com",
    "wof:name":"Big Fish Payroll Services",
    "wof:placetype":"venue"
},
  "geometry": {"coordinates":[-117.843953,33.808262],"type":"Point"}
}