{
  "type": "Feature",
  "properties": {
    "iso:country":"US",
    "sg:address":"605 Valley View Dr",
    "sg:city":"Redlands",
    "sg:classifiers":[
        {
            "category":"Building & Trades",
            "subcategory":"Electrical",
            "type":"Services"
        }
    ],
    "sg:phone":"+1 909 307 1256",
    "sg:postcode":"92373",
    "sg:province":"CA",
    "sg:tags":[
        "industrial",
        "electrician",
        "contractors-commercial",
        "electric"
    ],
    "wof:name":"Redlands Electric Inc",
    "wof:placetype":"venue"
},
  "geometry": {"coordinates":[-117.14539000000001,34.028704],"type":"Point"}
}