{
  "type": "Feature",
  "properties": {
    "iso:country":"US",
    "sg:address":"18000 Studebaker Rd",
    "sg:city":"Cerritos",
    "sg:classifiers":[
        {
            "category":"Real Estate",
            "subcategory":"Real Estate Agent",
            "type":"Services"
        }
    ],
    "sg:phone":"+1 562 468 4680",
    "sg:postcode":"90703",
    "sg:province":"CA",
    "sg:tags":[
        "broker",
        "mortgage"
    ],
    "sg:website":"www.allcaliforniabrokerage.com",
    "wof:name":"ALL California Brokerage Inc",
    "wof:placetype":"venue"
},
  "geometry": {"coordinates":[-118.09929,33.867597],"type":"Point"}
}