{
  "type": "Feature",
  "properties": {
    "addr:full":"7630 el Camino Real Atascadero CA 93422",
    "addr:housenumber":"7630",
    "addr:postcode":"93422",
    "addr:street":"El Camino Real",
    "iso:country":"US",
    "sg:address":"7630 el Camino Real",
    "sg:city":"Atascadero",
    "sg:classifiers":[
        {
            "category":"Personal",
            "subcategory":"Beauty Salon",
            "type":"Services"
        }
    ],
    "sg:phone":"+1 805 461 3555",
    "sg:postcode":"93422",
    "sg:province":"CA",
    "wof:name":"Art Of Nails",
    "wof:placetype":"venue"
},
  "geometry": {"coordinates":[-120.658171,35.480232],"type":"Point"}
}