{
  "type": "Feature",
  "properties": {
    "iso:country":"US",
    "sg:address":"2540 N Fitzsimmons Ave",
    "sg:city":"Rialto",
    "sg:classifiers":[
        {
            "category":"Professional",
            "subcategory":"Business Services",
            "type":"Services"
        }
    ],
    "sg:phone":"+1 909 456 6292",
    "sg:postcode":"92377",
    "sg:province":"CA",
    "wof:name":"Network Business Svc",
    "wof:placetype":"venue"
},
  "geometry": {"coordinates":[-117.407058,34.146003],"type":"Point"}
}