{
  "type": "Feature",
  "properties": {
    "addr:full":"23251 Peralta Dr Laguna Hills CA 92653",
    "addr:housenumber":"23251",
    "addr:postcode":"92653",
    "addr:street":"Peralta Dr",
    "iso:country":"US",
    "sg:address":"23251 Peralta Dr",
    "sg:city":"Laguna Hills",
    "sg:classifiers":[
        {
            "category":"Wholesale",
            "subcategory":"Sporting Goods",
            "type":"Manufacturing & Wholesale Goods"
        }
    ],
    "sg:phone":"+1 949 588 1228",
    "sg:postcode":"92653",
    "sg:province":"CA",
    "sg:tags":[
        "pool",
        "swimming"
    ],
    "wof:name":"Life Saver Pool Products",
    "wof:placetype":"venue"
},
  "geometry": {"coordinates":[-117.725025,33.625015],"type":"Point"}
}