{
  "type": "Feature",
  "properties": {
    "addr:full":"16890 Church St Morgan Hill CA 95037",
    "addr:housenumber":"16890",
    "addr:postcode":"95037",
    "addr:street":"Church St",
    "iso:country":"US",
    "sg:address":"16890 Church St",
    "sg:city":"Morgan Hill",
    "sg:classifiers":[
        {
            "category":"Manufacturing",
            "subcategory":"Furniture",
            "type":"Manufacturing & Wholesale Goods"
        },
        {
            "category":"Home & Garden",
            "subcategory":"Furniture",
            "type":"Retail Goods"
        }
    ],
    "sg:phone":"+1 408 782 1313",
    "sg:postcode":"95037",
    "sg:province":"CA",
    "sg:tags":[
        "household",
        "wood",
        "cabinet",
        "mfg"
    ],
    "wof:name":"California Drawers",
    "wof:placetype":"venue"
},
  "geometry": {"coordinates":[-121.646857,37.123262],"type":"Point"}
}