{
  "type": "Feature",
  "properties": {
    "iso:country":"US",
    "sg:address":"15117 Ventura Blvd",
    "sg:city":"Sherman Oaks",
    "sg:classifiers":[
        {
            "category":"Insurance",
            "subcategory":"Insurance Agent",
            "type":"Services"
        }
    ],
    "sg:phone":"+1 818 380 0087",
    "sg:postcode":"91403",
    "sg:province":"CA",
    "wof:name":"Zip Insurance Svc",
    "wof:placetype":"venue"
},
  "geometry": {"coordinates":[-118.463753,34.153478],"type":"Point"}
}