{
  "type": "Feature",
  "properties": {
    "addr:full":"28490 Yucca Trl Escondido CA 92026",
    "addr:housenumber":"28490",
    "addr:postcode":"92026",
    "addr:street":"Yucca Trl",
    "iso:country":"US",
    "sg:address":"28490 Yucca Trl",
    "sg:city":"Escondido",
    "sg:classifiers":[
        {
            "category":"Building & Trades",
            "subcategory":"Equipment Rental",
            "type":"Services"
        }
    ],
    "sg:phone":"+1 760 749 7477",
    "sg:postcode":"92026",
    "sg:province":"CA",
    "sg:tags":[
        "crane"
    ],
    "wof:name":"B & C Crane Svc",
    "wof:placetype":"venue"
},
  "geometry": {"coordinates":[-117.105701,33.226125],"type":"Point"}
}