{
  "type": "Feature",
  "properties": {
    "iso:country":"US",
    "sg:address":"2 Palo Alto Sq",
    "sg:city":"Palo Alto",
    "sg:classifiers":[
        {
            "category":"Professional",
            "subcategory":"Lawyer & Legal Services",
            "type":"Services"
        }
    ],
    "sg:phone":"+1 650 325 4517",
    "sg:postcode":"94306",
    "sg:province":"CA",
    "sg:tags":[
        "attorney"
    ],
    "wof:name":"William R Dawson",
    "wof:placetype":"venue"
},
  "geometry": {"coordinates":[-122.142521,37.423731],"type":"Point"}
}