{
  "type": "Feature",
  "properties": {
    "iso:country":"US",
    "sg:address":"238 S Arden Blvd",
    "sg:city":"Los Angeles",
    "sg:classifiers":[
        {
            "category":"Wholesale",
            "subcategory":"Apparel",
            "type":"Manufacturing & Wholesale Goods"
        }
    ],
    "sg:phone":"+1 323 935 3760",
    "sg:postcode":"90004",
    "sg:province":"CA",
    "sg:tags":[
        "clothing"
    ],
    "wof:name":"Vogue Fashion Inc",
    "wof:placetype":"venue"
},
  "geometry": {"coordinates":[-118.325886,34.069787],"type":"Point"}
}