{
  "type": "Feature",
  "properties": {
    "addr:full":"23 Sepulveda Rancho Santa Margarita CA 92688",
    "addr:housenumber":"23",
    "addr:postcode":"92688",
    "addr:street":"Sepulveda",
    "iso:country":"US",
    "sg:address":"23 Sepulveda",
    "sg:city":"Rancho Santa Margarita",
    "sg:classifiers":[
        {
            "category":"Professional",
            "subcategory":"Management & Consulting",
            "type":"Services"
        }
    ],
    "sg:phone":"+1 949 713 5871",
    "sg:postcode":"92688",
    "sg:province":"CA",
    "wof:name":"Parsons Marketing",
    "wof:placetype":"venue"
},
  "geometry": {"coordinates":[-117.616883,33.623287],"type":"Point"}
}