{
  "type": "Feature",
  "properties": {
    "addr:full":"11373 Trade Center Dr Rancho Cordova CA 95742",
    "addr:housenumber":"11373",
    "addr:postcode":"95742",
    "addr:street":"Trade Center Dr",
    "iso:country":"US",
    "sg:address":"11373 Trade Center Dr",
    "sg:city":"Rancho Cordova",
    "sg:classifiers":[
        {
            "category":"Building & Trades",
            "subcategory":"Construction",
            "type":"Services"
        }
    ],
    "sg:phone":"+1 916 972 7607",
    "sg:postcode":"95742",
    "sg:province":"CA",
    "sg:tags":[
        "contractor"
    ],
    "wof:name":"Sierra Sun Screens",
    "wof:placetype":"venue"
},
  "geometry": {"coordinates":[-121.26097900000001,38.60773],"type":"Point"}
}