{
  "type": "Feature",
  "properties": {
    "iso:country":"US",
    "sg:address":"202 W Walnut Ave",
    "sg:city":"Rialto",
    "sg:classifiers":[
        {
            "category":"Building & Trades",
            "subcategory":"Construction",
            "type":"Services"
        }
    ],
    "sg:phone":"+1 909 357 3031",
    "sg:postcode":"92376",
    "sg:province":"CA",
    "sg:tags":[
        "contractor"
    ],
    "wof:name":"C D & G Inc",
    "wof:placetype":"venue"
},
  "geometry": {"coordinates":[-117.374816,34.128735],"type":"Point"}
}