{
  "type": "Feature",
  "properties": {
    "iso:country":"US",
    "sg:address":"81500 Ave 52",
    "sg:city":"Indio",
    "sg:classifiers":[
        {
            "category":"Retail",
            "subcategory":"Veterinary Services",
            "type":"Services"
        }
    ],
    "sg:phone":"+1 760 342 8261",
    "sg:postcode":"92201",
    "sg:province":"CA",
    "sg:tags":[
        "veterinarian"
    ],
    "wof:name":"Farm Vet",
    "wof:placetype":"venue"
},
  "geometry": {"coordinates":[-116.24112599999999,33.671107],"type":"Point"}
}