{
  "type": "Feature",
  "properties": {
    "addr:full":"2832 N Bellflower Blvd Long Beach CA 90899",
    "addr:housenumber":"2832",
    "addr:postcode":"90899",
    "addr:street":"N Bellflower Blvd",
    "iso:country":"US",
    "sg:address":"2832 N Bellflower Blvd",
    "sg:city":"Long Beach",
    "sg:classifiers":[
        {
            "category":"Health Services",
            "subcategory":"Health Practitioner",
            "type":"Services"
        }
    ],
    "sg:postcode":"90899",
    "sg:province":"CA",
    "sg:tags":[
        "nutritionist"
    ],
    "sg:website":"www.weightwatchers.com",
    "wof:name":"Weight Watchers",
    "wof:placetype":"venue"
},
  "geometry": {"coordinates":[-118.125173,33.807365],"type":"Point"}
}