{
  "type": "Feature",
  "properties": {
    "iso:country":"US",
    "sg:address":"161 Cll del Oaks",
    "sg:city":"Monterey",
    "sg:classifiers":[
        {
            "category":"Utilities",
            "subcategory":"Telephone",
            "type":"Services"
        }
    ],
    "sg:phone":"+1 831 394 2690",
    "sg:postcode":"93940",
    "sg:province":"CA",
    "sg:tags":[
        "communications"
    ],
    "wof:name":"SBC",
    "wof:placetype":"venue"
},
  "geometry": {"coordinates":[-121.830504,36.584587],"type":"Point"}
}