{
  "type": "Feature",
  "properties": {
    "addr:full":"2167 White Dr Durham CA 95938",
    "addr:housenumber":"2167",
    "addr:postcode":"95938",
    "addr:street":"White Dr",
    "iso:country":"US",
    "sg:address":"2167 White Dr",
    "sg:city":"Durham",
    "sg:classifiers":[
        {
            "category":"Farming",
            "subcategory":"Crops",
            "type":"Manufacturing & Wholesale Goods"
        }
    ],
    "sg:phone":"+1 530 893 2030",
    "sg:postcode":"95938",
    "sg:province":"CA",
    "sg:tags":[
        "grove",
        "nut",
        "tree"
    ],
    "wof:name":"Nathan Horn",
    "wof:placetype":"venue"
},
  "geometry": {"coordinates":[-121.79042699999999,39.612768],"type":"Point"}
}