{
  "type": "Feature",
  "properties": {
    "addr:full":"3634 Elizabeth St Riverside CA 92506",
    "addr:housenumber":"3634",
    "addr:postcode":"92506",
    "addr:street":"Elizabeth St",
    "iso:country":"US",
    "sg:address":"3634 Elizabeth St",
    "sg:city":"Riverside",
    "sg:classifiers":[
        {
            "category":"Health Services",
            "subcategory":"Doctor",
            "type":"Services"
        }
    ],
    "sg:phone":"+1 951 341 8930",
    "sg:postcode":"92506",
    "sg:province":"CA",
    "sg:tags":[
        "physician",
        "surgeon"
    ],
    "sg:website":"www.dogonmentalhealth.com",
    "wof:name":"Dogon Psychiatric Medical Grp",
    "wof:placetype":"venue"
},
  "geometry": {"coordinates":[-117.392642,33.959388],"type":"Point"}
}