{
  "type": "Feature",
  "properties": {
    "iso:country":"US",
    "sg:address":"5540 Loganberry Ln",
    "sg:city":"Yorba Linda",
    "sg:classifiers":[
        {
            "category":"Shopping",
            "subcategory":"Gifts & Souvenirs",
            "type":"Retail Goods"
        }
    ],
    "sg:phone":"+1 714 692 2006",
    "sg:postcode":"92887",
    "sg:province":"CA",
    "wof:name":"Afis Gifts",
    "wof:placetype":"venue"
},
  "geometry": {"coordinates":[-117.706851,33.877933],"type":"Point"}
}