{
  "type": "Feature",
  "properties": {
    "addr:full":"7494 Santa Monica Blvd Ste 302 West Hollywood CA 90046",
    "addr:housenumber":"7494",
    "addr:postcode":"90046",
    "addr:street":"Santa Monica Blvd Ste 302",
    "iso:country":"US",
    "sg:address":"7494 Santa Monica Blvd Ste 302",
    "sg:city":"West Hollywood",
    "sg:classifiers":[
        {
            "category":"Professional",
            "type":"Services"
        },
        {
            "category":"Education",
            "subcategory":"Vocational School",
            "type":"Public Place"
        }
    ],
    "sg:phone":"+1 323 512 5544",
    "sg:postcode":"90046",
    "sg:province":"CA",
    "sg:tags":[
        "cooking",
        "caterer"
    ],
    "sg:website":"www.sporkfoods.com",
    "wof:name":"Spork Foods",
    "wof:placetype":"venue"
},
  "geometry": {"coordinates":[-118.352919,34.090683],"type":"Point"}
}