{
  "type": "Feature",
  "properties": {
    "iso:country":"US",
    "sg:address":"318 5th St",
    "sg:city":"Eureka",
    "sg:classifiers":[
        {
            "category":"Banks & Credit Unions",
            "subcategory":"Investment Brokerage",
            "type":"Services"
        }
    ],
    "sg:phone":"+1 707 442 2422",
    "sg:postcode":"95501",
    "sg:province":"CA",
    "sg:tags":[
        "security"
    ],
    "wof:name":"A G Edwards & Sons Inc",
    "wof:placetype":"venue"
},
  "geometry": {"coordinates":[-124.167143,40.801651],"type":"Point"}
}