{
  "type": "Feature",
  "properties": {
    "iso:country":"US",
    "sg:address":"4854 S Bradley Rd",
    "sg:city":"Santa Maria",
    "sg:classifiers":[
        {
            "category":"Retail",
            "subcategory":"Laundry & Dry Cleaning",
            "type":"Services"
        }
    ],
    "sg:phone":"+1 805 937 5097",
    "sg:postcode":"93455",
    "sg:province":"CA",
    "sg:tags":[
        "cleaners"
    ],
    "wof:name":"Paramount Cleaners & Laundry",
    "wof:placetype":"venue"
},
  "geometry": {"coordinates":[-120.418664,34.866857],"type":"Point"}
}