{
  "type": "Feature",
  "properties": {
    "addr:full":"31244 Palos Verdes Dr W Rancho Pls Vrds CA 90275",
    "addr:housenumber":"31244",
    "addr:postcode":"90275",
    "addr:street":"Palos Verdes Dr W",
    "iso:country":"US",
    "sg:address":"31244 Palos Verdes Dr W",
    "sg:city":"Rancho Pls Vrds",
    "sg:classifiers":[
        {
            "category":"Wholesale",
            "subcategory":"Machinery & Supplies",
            "type":"Manufacturing & Wholesale Goods"
        }
    ],
    "sg:phone":"+1 310 541 6888",
    "sg:postcode":"90275",
    "sg:province":"CA",
    "sg:tags":[
        "industrial",
        "miscellaneous"
    ],
    "wof:name":"C & I Equipment Sales Inc",
    "wof:placetype":"venue"
},
  "geometry": {"coordinates":[-118.407633,33.749161],"type":"Point"}
}