{
  "type": "Feature",
  "properties": {
    "iso:country":"US",
    "sg:address":"1881 Sutter St",
    "sg:city":"San Francisco",
    "sg:classifiers":[
        {
            "category":"Communications",
            "type":"Services"
        },
        {
            "category":"Professional",
            "subcategory":"Computer Services",
            "type":"Services"
        }
    ],
    "sg:phone":"+1 415 294 1463",
    "sg:postcode":"94115",
    "sg:province":"CA",
    "sg:tags":[
        "repair",
        "design",
        "web"
    ],
    "wof:name":"Hondo Software",
    "wof:placetype":"venue"
},
  "geometry": {"coordinates":[-122.431023,37.786146],"type":"Point"}
}