{
  "type": "Feature",
  "properties": {
    "addr:full":"4961 Mission St San Francisco CA 94112",
    "addr:housenumber":"4961",
    "addr:postcode":"94112",
    "addr:street":"Mission St",
    "iso:country":"US",
    "sg:address":"4961 Mission St",
    "sg:city":"San Francisco",
    "sg:classifiers":[
        {
            "category":"Real Estate",
            "subcategory":"Real Estate Agent",
            "type":"Services"
        }
    ],
    "sg:phone":"+1 415 452 2607",
    "sg:postcode":"94112",
    "sg:province":"CA",
    "wof:name":"California Realty & Investment",
    "wof:placetype":"venue"
},
  "geometry": {"coordinates":[-122.43916299999999,37.718812],"type":"Point"}
}