{
  "type": "Feature",
  "properties": {
    "iso:country":"US",
    "sg:address":"1926 E 51st St",
    "sg:city":"Vernon",
    "sg:classifiers":[
        {
            "category":"Manufacturing",
            "subcategory":"Textiles",
            "type":"Manufacturing & Wholesale Goods"
        }
    ],
    "sg:phone":"+1 323 584 5123",
    "sg:postcode":"90058",
    "sg:province":"CA",
    "sg:tags":[
        "goods-wholesale",
        "knit",
        "manufacturer"
    ],
    "wof:name":"Milan Knitting Mill Inc.",
    "wof:placetype":"venue"
},
  "geometry": {"coordinates":[-118.237927,33.996684],"type":"Point"}
}