{
  "type": "Feature",
  "properties": {
    "addr:full":"2344 Curlew St San Diego CA 92101",
    "addr:housenumber":"2344",
    "addr:postcode":"92101",
    "addr:street":"Curlew St",
    "iso:country":"US",
    "sg:address":"2344 Curlew St",
    "sg:city":"San Diego",
    "sg:classifiers":[
        {
            "category":"Arts & Performance",
            "subcategory":"Arts Center",
            "type":"Entertainment"
        }
    ],
    "sg:phone":"+1 619 230 1117",
    "sg:postcode":"92101",
    "sg:province":"CA",
    "sg:website":"www.tostadosisters.com/",
    "wof:name":"Tostado Sisters Unforgettable Entertainment",
    "wof:placetype":"venue"
},
  "geometry": {"coordinates":[-117.16787100000001,32.729912],"type":"Point"}
}