{
  "type": "Feature",
  "properties": {
    "addr:full":"4963 Alto St Eureka CA 95503",
    "addr:housenumber":"4963",
    "addr:postcode":"95503",
    "addr:street":"Alto St",
    "iso:country":"US",
    "sg:address":"4963 Alto St",
    "sg:city":"Eureka",
    "sg:classifiers":[
        {
            "category":"Building & Trades",
            "subcategory":"Cleaning & Sanitation",
            "type":"Services"
        }
    ],
    "sg:phone":"+1 707 443 5906",
    "sg:postcode":"95503",
    "sg:province":"CA",
    "sg:tags":[
        "fireplace",
        "chimney"
    ],
    "wof:name":"Chamberlain Chimney Sweep",
    "wof:placetype":"venue"
},
  "geometry": {"coordinates":[-124.17370699999999,40.761544],"type":"Point"}
}