{
  "type": "Feature",
  "properties": {
    "iso:country":"US",
    "sg:address":"1011 College Ave",
    "sg:city":"Santa Rosa",
    "sg:classifiers":[
        {
            "category":"Organizations",
            "subcategory":"Community Association",
            "type":"Services"
        }
    ],
    "sg:phone":"+1 707 542 0908",
    "sg:postcode":"95404",
    "sg:province":"CA",
    "sg:tags":[
        "fraternal"
    ],
    "wof:name":"Druids",
    "wof:placetype":"venue"
},
  "geometry": {"coordinates":[-122.708297,38.445466],"type":"Point"}
}