{
  "type": "Feature",
  "properties": {
    "addr:full":"5332 College Ave Oakland CA 94618",
    "addr:housenumber":"5332",
    "addr:postcode":"94618",
    "addr:street":"College Ave",
    "iso:country":"US",
    "sg:address":"5332 College Ave",
    "sg:city":"Oakland",
    "sg:classifiers":[
        {
            "category":"Shopping",
            "subcategory":"Clothing, Apparel, & Fashions",
            "type":"Retail Goods"
        }
    ],
    "sg:phone":"+1 510 428 2208",
    "sg:postcode":"94618",
    "sg:province":"CA",
    "sg:tags":[
        "clothing",
        "women's"
    ],
    "sg:website":"www.dress-sf.com",
    "wof:name":"Dress: Luxury Attire on Loan",
    "wof:placetype":"venue"
},
  "geometry": {"coordinates":[-122.250986,37.83891],"type":"Point"}
}