{
  "type": "Feature",
  "properties": {
    "addr:full":"9424 Sage Creek Ct Elk Grove CA 95624",
    "addr:housenumber":"9424",
    "addr:postcode":"95624",
    "addr:street":"Sage Creek Ct",
    "iso:country":"US",
    "sg:address":"9424 Sage Creek Ct",
    "sg:city":"Elk Grove",
    "sg:classifiers":[
        {
            "category":"Professional",
            "type":"Services"
        }
    ],
    "sg:phone":"+1 916 714 1515",
    "sg:postcode":"95624",
    "sg:province":"CA",
    "sg:tags":[
        "establishment"
    ],
    "wof:name":"John Daniel Corp",
    "wof:placetype":"venue"
},
  "geometry": {"coordinates":[-121.33543400000001,38.414916],"type":"Point"}
}