{
  "type": "Feature",
  "properties": {
    "iso:country":"US",
    "sg:address":"16437 Ventura Blvd",
    "sg:city":"Encino",
    "sg:classifiers":[
        {
            "category":"Banks & Credit Unions",
            "subcategory":"Bank",
            "type":"Services"
        }
    ],
    "sg:phone":"+1 818 788 0837",
    "sg:postcode":"91436",
    "sg:province":"CA",
    "sg:website":"www.wamu.com",
    "wof:name":"Washington Mutual",
    "wof:placetype":"venue"
},
  "geometry": {"coordinates":[-118.491667,34.157528],"type":"Point"}
}