{
  "type": "Feature",
  "properties": {
    "addr:full":"7530 Jerez Ct Unit 14 Carlsbad CA 92009",
    "addr:housenumber":"14",
    "addr:postcode":"7530;92009",
    "addr:street":"Jerez Ct Unit",
    "iso:country":"US",
    "sg:address":"7530 Jerez Ct Unit 14",
    "sg:city":"Carlsbad",
    "sg:classifiers":[
        {
            "category":"Retail",
            "subcategory":"Pet Boarding",
            "type":"Services"
        }
    ],
    "sg:phone":"+1 760 635 3978",
    "sg:postcode":"92009",
    "sg:province":"CA",
    "sg:tags":[
        "boarding/pet",
        "sitting"
    ],
    "wof:name":"Animal House Temporary Services",
    "wof:placetype":"venue"
},
  "geometry": {"coordinates":[-117.24805600000001,33.087505],"type":"Point"}
}