{
  "type": "Feature",
  "properties": {
    "iso:country":"US",
    "sg:address":"433 E El Camino Real",
    "sg:city":"Sunnyvale",
    "sg:classifiers":[
        {
            "category":"Education",
            "subcategory":"Special Training",
            "type":"Public Place"
        }
    ],
    "sg:phone":"+1 408 245 3200",
    "sg:postcode":"94087",
    "sg:province":"CA",
    "sg:tags":[
        "tutoring"
    ],
    "sg:website":"www.kumonsunnyvale.com/",
    "wof:name":"Kumon Sunnyvale Central",
    "wof:placetype":"venue"
},
  "geometry": {"coordinates":[-122.028064,37.364474],"type":"Point"}
}