{
  "type": "Feature",
  "properties": {
    "addr:full":"620 C St San Diego CA 92101",
    "addr:housenumber":"620",
    "addr:postcode":"92101",
    "addr:street":"C St",
    "iso:country":"US",
    "sg:address":"620 C St",
    "sg:city":"San Diego",
    "sg:classifiers":[
        {
            "category":"Professional",
            "subcategory":"Management & Consulting",
            "type":"Services"
        }
    ],
    "sg:phone":"+1 619 233 4287",
    "sg:postcode":"92101",
    "sg:province":"CA",
    "sg:tags":[
        "consultant",
        "hygiene",
        "industrial"
    ],
    "wof:name":"Dan Napier & Assoc",
    "wof:placetype":"venue"
},
  "geometry": {"coordinates":[-117.158536,32.716838],"type":"Point"}
}