{
  "type": "Feature",
  "properties": {
    "iso:country":"US",
    "sg:address":"907 Alegre Pl",
    "sg:city":"Los Angeles",
    "sg:classifiers":[
        {
            "category":"Communications",
            "subcategory":"Film & Video Production",
            "type":"Services"
        }
    ],
    "sg:phone":"+1 323 258 7666",
    "sg:postcode":"90065",
    "sg:province":"CA",
    "sg:tags":[
        "audio"
    ],
    "wof:name":"Bob Hata Audio Mastering",
    "wof:placetype":"venue"
},
  "geometry": {"coordinates":[-118.22135,34.114619],"type":"Point"}
}