{
  "type": "Feature",
  "properties": {
    "iso:country":"US",
    "sg:address":"7134 GARDEN GROVE BLVD.",
    "sg:city":"Westminster",
    "sg:classifiers":[
        {
            "category":"Personal",
            "subcategory":"Tattoo Parlor",
            "type":"Services"
        }
    ],
    "sg:phone":"+1 714 899 1144",
    "sg:postcode":"92683",
    "sg:province":"CA",
    "sg:website":"WWW.OCTATTOO.COM",
    "wof:name":"OC TATTOO INC",
    "wof:placetype":"venue"
},
  "geometry": {"coordinates":[-118.008561,33.773282],"type":"Point"}
}