{
  "type": "Feature",
  "properties": {
    "iso:country":"US",
    "sg:address":"2169 Wright Ave",
    "sg:city":"La Verne",
    "sg:classifiers":[
        {
            "category":"Freight",
            "type":"Transportation"
        }
    ],
    "sg:phone":"+1 909 450 0941",
    "sg:postcode":"91750",
    "sg:province":"CA",
    "sg:tags":[
        "delivery"
    ],
    "sg:website":"www.jetdelivery.com",
    "wof:name":"Jet Delivery",
    "wof:placetype":"venue"
},
  "geometry": {"coordinates":[-117.772075,34.094909],"type":"Point"}
}