{
  "type": "Feature",
  "properties": {
    "addr:full":"1117 W San Jose Ave Fresno CA 93711",
    "addr:housenumber":"1117",
    "addr:postcode":"93711",
    "addr:street":"W San Jose Ave",
    "iso:country":"US",
    "sg:address":"1117 W San Jose Ave",
    "sg:city":"Fresno",
    "sg:classifiers":[
        {
            "category":"Professional",
            "type":"Services"
        }
    ],
    "sg:phone":"+1 559 222 7411",
    "sg:postcode":"93711",
    "sg:province":"CA",
    "wof:name":"Adat Shalom of Fresno",
    "wof:placetype":"venue"
},
  "geometry": {"coordinates":[-119.812231,36.811896],"type":"Point"}
}