{
  "type": "Feature",
  "properties": {
    "iso:country":"US",
    "sg:address":"14365 Foothill Blvd",
    "sg:city":"Sylmar",
    "sg:classifiers":[
        {
            "category":"Health Services",
            "subcategory":"Nursing And Care Facility",
            "type":"Services"
        }
    ],
    "sg:phone":"+1 818 362 6777",
    "sg:postcode":"91342",
    "sg:province":"CA",
    "sg:tags":[
        "home",
        "convalescent"
    ],
    "wof:name":"New Image Foundations",
    "wof:placetype":"venue"
},
  "geometry": {"coordinates":[-118.44763,34.320939],"type":"Point"}
}