{
  "type": "Feature",
  "properties": {
    "iso:country":"US",
    "sg:address":"15206 Elm Park Ct",
    "sg:city":"Los Gatos",
    "sg:classifiers":[
        {
            "category":"Wholesale",
            "subcategory":"Beer",
            "type":"Manufacturing & Wholesale Goods"
        }
    ],
    "sg:phone":"+1 408 259 0430",
    "sg:postcode":"95030",
    "sg:province":"CA",
    "sg:tags":[
        "drink",
        "soft"
    ],
    "wof:name":"Coors",
    "wof:placetype":"venue"
},
  "geometry": {"coordinates":[-121.98591399999999,37.247675],"type":"Point"}
}