{
  "type": "Feature",
  "properties": {
    "addr:full":"1674 Story Road San Jose CA 95122",
    "addr:housenumber":"1674",
    "addr:postcode":"95122",
    "addr:street":"Story Road",
    "iso:country":"US",
    "sg:address":"1674 Story Road",
    "sg:city":"San Jose",
    "sg:classifiers":[
        {
            "category":"Personal",
            "subcategory":"Day Spa",
            "type":"Services"
        }
    ],
    "sg:phone":"+1 408 251 6000",
    "sg:postcode":"95122",
    "sg:province":"CA",
    "wof:name":"Studio 28 Spa",
    "wof:placetype":"venue"
},
  "geometry": {"coordinates":[-121.843519,37.339403],"type":"Point"}
}