{
  "type": "Feature",
  "properties": {
    "iso:country":"US",
    "sg:address":"2940 E la Cresta Ave",
    "sg:city":"Anaheim",
    "sg:classifiers":[
        {
            "category":"Professional",
            "subcategory":"Engineering",
            "type":"Services"
        }
    ],
    "sg:phone":"+1 714 333 9020",
    "sg:postcode":"92806",
    "sg:province":"CA",
    "sg:tags":[
        "system",
        "cad"
    ],
    "sg:website":"http://www.cad-cam.com",
    "wof:name":"Cad-Cam Consulting Services Inc",
    "wof:placetype":"venue"
},
  "geometry": {"coordinates":[-117.86795600000001,33.854118],"type":"Point"}
}