{
  "type": "Feature",
  "properties": {
    "addr:full":"23734 Arlington Ave Torrance CA 90501",
    "addr:housenumber":"23734",
    "addr:postcode":"90501",
    "addr:street":"Arlington Ave",
    "iso:country":"US",
    "sg:address":"23734 Arlington Ave",
    "sg:city":"Torrance",
    "sg:classifiers":[
        {
            "category":"Social Services",
            "subcategory":"Adult Care",
            "type":"Services"
        }
    ],
    "sg:phone":"+1 310 891 2369",
    "sg:postcode":"90501",
    "sg:province":"CA",
    "sg:tags":[
        "home",
        "residential"
    ],
    "wof:name":"Breakthrough Services Inc",
    "wof:placetype":"venue"
},
  "geometry": {"coordinates":[-118.31983,33.809115],"type":"Point"}
}