{
  "type": "Feature",
  "properties": {
    "iso:country":"US",
    "sg:address":"116 Grand Ave",
    "sg:city":"South San Francisco",
    "sg:classifiers":[
        {
            "category":"Restaurant",
            "type":"Food & Drink"
        }
    ],
    "sg:menulink":"http://www.allmenus.com/ca/south-san-francisco/55989-los-compadres-taqueria/menu/",
    "sg:phone":"+1 650 583 5772",
    "sg:postcode":"94080",
    "sg:province":"CA",
    "sg:tags":[
        "mexican"
    ],
    "wof:name":"Los Compadres Taqueria",
    "wof:placetype":"venue"
},
  "geometry": {"coordinates":[-122.408058,37.654696],"type":"Point"}
}