{
  "type": "Feature",
  "properties": {
    "iso:country":"US",
    "sg:address":"829 7th St",
    "sg:city":"Wasco",
    "sg:classifiers":[
        {
            "category":"Shopping",
            "subcategory":"Clothing, Apparel, & Fashions",
            "type":"Retail Goods"
        }
    ],
    "sg:phone":"+1 661 758 0590",
    "sg:postcode":"93280",
    "sg:province":"CA",
    "sg:tags":[
        "infant",
        "wear"
    ],
    "wof:name":"Gonzalez Kids Clothes",
    "wof:placetype":"venue"
},
  "geometry": {"coordinates":[-119.334778,35.594153],"type":"Point"}
}