{
  "type": "Feature",
  "properties": {
    "iso:country":"US",
    "sg:address":"4027 Slauson Ave",
    "sg:city":"Maywood",
    "sg:classifiers":[
        {
            "category":"Food & Beverages",
            "subcategory":"Groceries & Convenience Stores",
            "type":"Retail Goods"
        }
    ],
    "sg:phone":"+1 323 582 8462",
    "sg:postcode":"90270",
    "sg:province":"CA",
    "wof:name":"Maywood Market",
    "wof:placetype":"venue"
},
  "geometry": {"coordinates":[-118.193793,33.988141],"type":"Point"}
}