{
  "type": "Feature",
  "properties": {
    "addr:full":"3707 Madison Ave North Highlands CA 95660",
    "addr:housenumber":"3707",
    "addr:postcode":"95660",
    "addr:street":"Madison Ave",
    "iso:country":"US",
    "sg:address":"3707 Madison Ave",
    "sg:city":"North Highlands",
    "sg:classifiers":[
        {
            "category":"Home & Garden",
            "subcategory":"Building Materials",
            "type":"Retail Goods"
        }
    ],
    "sg:phone":"+1 916 332 0195",
    "sg:postcode":"95660",
    "sg:province":"CA",
    "sg:tags":[
        "glass",
        "window",
        "plate"
    ],
    "wof:name":"Star Lite Glass",
    "wof:placetype":"venue"
},
  "geometry": {"coordinates":[-121.376295,38.661289],"type":"Point"}
}