{
  "type": "Feature",
  "properties": {
    "iso:country":"US",
    "sg:address":"2033 Gateway Pl",
    "sg:city":"San Jose",
    "sg:classifiers":[
        {
            "category":"Utilities",
            "subcategory":"Telephone",
            "type":"Services"
        }
    ],
    "sg:phone":"+1 408 453 9896",
    "sg:postcode":"95110",
    "sg:province":"CA",
    "sg:tags":[
        "company"
    ],
    "wof:name":"Concert Management Svc Inc",
    "wof:placetype":"venue"
},
  "geometry": {"coordinates":[-121.922728,37.370632],"type":"Point"}
}