{
  "type": "Feature",
  "properties": {
    "addr:full":"788 Arlington St Cambria CA 93428",
    "addr:housenumber":"788",
    "addr:postcode":"93428",
    "addr:street":"Arlington St",
    "iso:country":"US",
    "sg:address":"788 Arlington St",
    "sg:city":"Cambria",
    "sg:classifiers":[
        {
            "category":"Real Estate",
            "subcategory":"Architect",
            "type":"Services"
        }
    ],
    "sg:phone":"+1 805 927 8118",
    "sg:postcode":"93428",
    "sg:province":"CA",
    "wof:name":"Richard Low Assoc Inc",
    "wof:placetype":"venue"
},
  "geometry": {"coordinates":[-121.09992800000001,35.567631],"type":"Point"}
}