{
  "type": "Feature",
  "properties": {
    "addr:full":"390 Jackson St Quincy CA 95971",
    "addr:housenumber":"390",
    "addr:postcode":"95971",
    "addr:street":"Jackson St",
    "iso:country":"US",
    "sg:address":"390 Jackson St",
    "sg:city":"Quincy",
    "sg:classifiers":[
        {
            "category":"Shopping",
            "subcategory":"Crafts & Fabrics",
            "type":"Retail Goods"
        }
    ],
    "sg:phone":"+1 530 283 0648",
    "sg:postcode":"95971",
    "sg:province":"CA",
    "sg:tags":[
        "shop",
        "instruction",
        "knit",
        "yarn"
    ],
    "wof:name":"The Woolroom",
    "wof:placetype":"venue"
},
  "geometry": {"coordinates":[-120.946512,39.935799],"type":"Point"}
}