{
  "type": "Feature",
  "properties": {
    "addr:full":"5420 Geary Blvd San Francisco CA 94121",
    "addr:housenumber":"5420",
    "addr:postcode":"94121",
    "addr:street":"Geary Blvd",
    "iso:country":"US",
    "sg:address":"5420 Geary Blvd",
    "sg:city":"San Francisco",
    "sg:classifiers":[
        {
            "category":"Bagels",
            "subcategory":"None",
            "type":"Food & Drink"
        }
    ],
    "sg:postcode":"94121",
    "sg:province":"CA",
    "wof:name":"The Posh Bagel",
    "wof:placetype":"venue"
},
  "geometry": {"coordinates":[-122.477808,37.780787],"type":"Point"}
}