{
  "type": "Feature",
  "properties": {
    "addr:full":"50 Castilian Dr Goleta CA 93117",
    "addr:housenumber":"50",
    "addr:postcode":"93117",
    "addr:street":"Castilian Dr",
    "iso:country":"US",
    "sg:address":"50 Castilian Dr",
    "sg:city":"Goleta",
    "sg:classifiers":[
        {
            "category":"Health Services",
            "subcategory":"Hospital",
            "type":"Services"
        }
    ],
    "sg:phone":"+1 805 569 7570",
    "sg:postcode":"93117",
    "sg:province":"CA",
    "wof:name":"Santa Barbara Cottage Hospital",
    "wof:placetype":"venue"
},
  "geometry": {"coordinates":[-119.86378999999999,34.433919],"type":"Point"}
}