{
  "type": "Feature",
  "properties": {
    "addr:full":"8135 W Manchester Ave Playa Del Rey CA 90293",
    "addr:housenumber":"8135",
    "addr:postcode":"90293",
    "addr:street":"W Manchester Ave",
    "iso:country":"US",
    "sg:address":"8135 W Manchester Ave",
    "sg:city":"Playa Del Rey",
    "sg:classifiers":[
        {
            "category":"Personal",
            "subcategory":"Nail Salon",
            "type":"Services"
        }
    ],
    "sg:phone":"+1 310 821 9056",
    "sg:postcode":"90293",
    "sg:province":"CA",
    "wof:name":"Diane's Nail & Spa",
    "wof:placetype":"venue"
},
  "geometry": {"coordinates":[-118.439003,33.958099],"type":"Point"}
}