{
  "type": "Feature",
  "properties": {
    "iso:country":"US",
    "sg:address":"9520 Soquel Dr",
    "sg:city":"Aptos",
    "sg:classifiers":[
        {
            "category":"Personal",
            "subcategory":"Beauty Salon",
            "type":"Services"
        }
    ],
    "sg:phone":"+1 831 688 0122",
    "sg:postcode":"95003",
    "sg:province":"CA",
    "wof:name":"Master Hairdressers",
    "wof:placetype":"venue"
},
  "geometry": {"coordinates":[-121.884846,36.975338],"type":"Point"}
}