{
  "type": "Feature",
  "properties": {
    "iso:country":"US",
    "sg:address":"4240 Mesa Ct",
    "sg:city":"Rocklin",
    "sg:classifiers":[
        {
            "category":"Professional",
            "subcategory":"Advertising",
            "type":"Services"
        }
    ],
    "sg:phone":"+1 916 630 0869",
    "sg:postcode":"95677",
    "sg:province":"CA",
    "sg:tags":[
        "distribution"
    ],
    "wof:name":"First Distributors Inc",
    "wof:placetype":"venue"
},
  "geometry": {"coordinates":[-121.236436,38.801353],"type":"Point"}
}