{
  "type": "Feature",
  "properties": {
    "iso:country":"US",
    "sg:address":"1330 Lincoln Ave",
    "sg:city":"San Rafael",
    "sg:classifiers":[
        {
            "category":"Professional",
            "subcategory":"Lawyer & Legal Services",
            "type":"Services"
        }
    ],
    "sg:phone":"+1 415 485 1330",
    "sg:postcode":"94901",
    "sg:province":"CA",
    "sg:tags":[
        "attorney"
    ],
    "wof:name":"Drexler & Leach",
    "wof:placetype":"venue"
},
  "geometry": {"coordinates":[-122.522254,37.977317],"type":"Point"}
}