{
  "type": "Feature",
  "properties": {
    "iso:country":"US",
    "sg:address":"1192 E Colorado Blvd",
    "sg:city":"Pasadena",
    "sg:classifiers":[
        {
            "category":"Manufacturing",
            "subcategory":"Apparel",
            "type":"Manufacturing & Wholesale Goods"
        }
    ],
    "sg:phone":"+1 626 564 2702",
    "sg:postcode":"91106",
    "sg:province":"CA",
    "sg:tags":[
        "screen",
        "printing",
        "embroidery"
    ],
    "wof:name":"Pasadena Embroidery",
    "wof:placetype":"venue"
},
  "geometry": {"coordinates":[-118.12646599999999,34.146022],"type":"Point"}
}