{
  "type": "Feature",
  "properties": {
    "addr:full":"10940 Wilshire Blvd Los Angeles CA 90024",
    "addr:housenumber":"10940",
    "addr:postcode":"90024",
    "addr:street":"Wilshire Blvd",
    "iso:country":"US",
    "sg:address":"10940 Wilshire Blvd",
    "sg:city":"Los Angeles",
    "sg:classifiers":[
        {
            "category":"Professional",
            "subcategory":"Lawyer & Legal Services",
            "type":"Services"
        }
    ],
    "sg:phone":"+1 310 943 2339",
    "sg:postcode":"90024",
    "sg:province":"CA",
    "sg:tags":[
        "attorney"
    ],
    "wof:name":"Ebbi Izadian Law Office",
    "wof:placetype":"venue"
},
  "geometry": {"coordinates":[-118.44441399999999,34.058615],"type":"Point"}
}