{
  "type": "Feature",
  "properties": {
    "iso:country":"US",
    "sg:address":"3509 N 1st St",
    "sg:city":"Fresno",
    "sg:classifiers":[
        {
            "category":"Organizations",
            "subcategory":"Community Association",
            "type":"Services"
        }
    ],
    "sg:phone":"+1 559 224 0522",
    "sg:postcode":"93726",
    "sg:province":"CA",
    "sg:tags":[
        "military"
    ],
    "wof:name":"American Legion",
    "wof:placetype":"venue"
},
  "geometry": {"coordinates":[-119.772577,36.78238],"type":"Point"}
}