{
  "type": "Feature",
  "properties": {
    "iso:country":"US",
    "sg:address":"2392 Woodhill Dr",
    "sg:city":"Pittsburg",
    "sg:classifiers":[
        {
            "category":"Building & Trades",
            "subcategory":"Construction",
            "type":"Services"
        }
    ],
    "sg:phone":"+1 925 261 9747",
    "sg:postcode":"94565",
    "sg:province":"CA",
    "sg:tags":[
        "general",
        "contractor"
    ],
    "wof:name":"M & F General Contractors",
    "wof:placetype":"venue"
},
  "geometry": {"coordinates":[-121.952157,38.007903],"type":"Point"}
}