{
  "type": "Feature",
  "properties": {
    "addr:full":"21034 Golden Springs Dr Walnut CA 91789",
    "addr:housenumber":"21034",
    "addr:postcode":"91789",
    "addr:street":"Golden Springs Dr",
    "iso:country":"US",
    "sg:address":"21034 Golden Springs Dr",
    "sg:city":"Walnut",
    "sg:classifiers":[
        {
            "category":"Retail",
            "subcategory":"Laundry & Dry Cleaning",
            "type":"Services"
        }
    ],
    "sg:phone":"+1 909 595 4505",
    "sg:postcode":"91789",
    "sg:province":"CA",
    "sg:tags":[
        "cleaners"
    ],
    "wof:name":"Diamond Creek Cleaners",
    "wof:placetype":"venue"
},
  "geometry": {"coordinates":[-117.846954,33.999223],"type":"Point"}
}