{
  "type": "Feature",
  "properties": {
    "addr:full":"16672 Beach Boulevard Huntington Beach CA 92647",
    "addr:housenumber":"16672",
    "addr:postcode":"92647",
    "addr:street":"Beach Boulevard",
    "iso:country":"US",
    "sg:address":"16672 Beach Boulevard",
    "sg:city":"Huntington Beach",
    "sg:classifiers":[
        {
            "category":"Shopping",
            "subcategory":"Optician",
            "type":"Retail Goods"
        }
    ],
    "sg:phone":"+1 714 842 7022",
    "sg:postcode":"92647",
    "sg:province":"CA",
    "sg:tags":[
        "eyewear"
    ],
    "wof:name":"For Eyes Optical Company",
    "wof:placetype":"venue"
},
  "geometry": {"coordinates":[-117.98903900000001,33.72005],"type":"Point"}
}