{
  "type": "Feature",
  "properties": {
    "addr:full":"4444 E 26th St Los Angeles CA 90023",
    "addr:housenumber":"4444",
    "addr:postcode":"90023",
    "addr:street":"E 26Th St",
    "iso:country":"US",
    "sg:address":"4444 E 26th St",
    "sg:city":"Los Angeles",
    "sg:classifiers":[
        {
            "category":"Freight",
            "type":"Transportation"
        }
    ],
    "sg:phone":"+1 323 269 0525",
    "sg:postcode":"90023",
    "sg:province":"CA",
    "sg:tags":[
        "general"
    ],
    "wof:name":"F & S Distributing Co Inc",
    "wof:placetype":"venue"
},
  "geometry": {"coordinates":[-118.18267899999999,34.003808],"type":"Point"}
}