{
  "type": "Feature",
  "properties": {
    "iso:country":"US",
    "sg:address":"35863 Fairview Rd",
    "sg:city":"Hinkley",
    "sg:classifiers":[
        {
            "category":"Utilities",
            "subcategory":"Natural Gas",
            "type":"Services"
        }
    ],
    "sg:phone":"+1 760 253 2925",
    "sg:postcode":"92347",
    "sg:province":"CA",
    "sg:tags":[
        "company"
    ],
    "sg:website":"www.pge.com",
    "wof:name":"Pacific Gas & Electric Co",
    "wof:placetype":"venue"
},
  "geometry": {"coordinates":[-117.162526,34.902988],"type":"Point"}
}