{
  "type": "Feature",
  "properties": {
    "iso:country":"US",
    "sg:address":"33265 Yucaipa Blvd",
    "sg:city":"Yucaipa",
    "sg:classifiers":[
        {
            "category":"Fast Food",
            "type":"Food & Drink"
        },
        {
            "category":"Restaurant",
            "type":"Food & Drink"
        }
    ],
    "sg:phone":"+1 909 797 6018",
    "sg:postcode":"92399",
    "sg:province":"CA",
    "sg:tags":[
        "shop",
        "hamburger",
        "dog",
        "hot",
        "fountain",
        "soda",
        "american"
    ],
    "sg:website":"http://www.awrestaurants.com",
    "wof:name":"A & W Restaurants",
    "wof:placetype":"venue"
},
  "geometry": {"coordinates":[-117.078667,34.03384],"type":"Point"}
}