{
  "type": "Feature",
  "properties": {
    "addr:full":"1617 S Pacific Coast Hwy Redondo Beach CA 90277",
    "addr:housenumber":"1617",
    "addr:postcode":"90277",
    "addr:street":"S Pacific Coast Hwy",
    "iso:country":"US",
    "sg:address":"1617 S Pacific Coast Hwy",
    "sg:city":"Redondo Beach",
    "sg:classifiers":[
        {
            "category":"Real Estate",
            "subcategory":"Real Estate Agent",
            "type":"Services"
        }
    ],
    "sg:phone":"+1 310 792 4330",
    "sg:postcode":"90277",
    "sg:province":"CA",
    "sg:website":"www.aaainvestments.com",
    "wof:name":"Robbie Mills Real Estate",
    "wof:placetype":"venue"
},
  "geometry": {"coordinates":[-118.38515700000001,33.820086],"type":"Point"}
}