{
  "type": "Feature",
  "properties": {
    "iso:country":"US",
    "sg:address":"486 W Burnett St",
    "sg:city":"Long Beach",
    "sg:classifiers":[
        {
            "category":"Freight",
            "type":"Transportation"
        }
    ],
    "sg:phone":"+1 562 427 9360",
    "sg:postcode":"90806",
    "sg:province":"CA",
    "wof:name":"International Transportation",
    "wof:placetype":"venue"
},
  "geometry": {"coordinates":[-118.19737600000001,33.800679],"type":"Point"}
}