{
  "type": "Feature",
  "properties": {
    "addr:full":"1508 Walnut St. Suite D Berkeley CA 94709",
    "addr:housenumber":"1508",
    "addr:postcode":"94709",
    "addr:street":"Walnut St. Suite D",
    "iso:country":"US",
    "sg:address":"1508 Walnut St. Suite D",
    "sg:city":"Berkeley",
    "sg:classifiers":[
        {
            "category":"Health Services",
            "subcategory":"Optometrist",
            "type":"Services"
        },
        {
            "category":"Shopping",
            "subcategory":"Optician",
            "type":"Retail Goods"
        }
    ],
    "sg:phone":"+1 510 540 5555",
    "sg:postcode":"94709",
    "sg:province":"CA",
    "sg:tags":[
        "eyewear"
    ],
    "sg:website":"eyeseeyou.net",
    "wof:name":"Dr. Lesli Handmacher, OD",
    "wof:placetype":"venue"
},
  "geometry": {"coordinates":[-122.268185,37.88],"type":"Point"}
}