{
  "type": "Feature",
  "properties": {
    "addr:full":"2855 Ray Lawyer Dr Placerville CA 95667",
    "addr:housenumber":"2855",
    "addr:postcode":"95667",
    "addr:street":"Ray Lawyer Dr",
    "iso:country":"US",
    "sg:address":"2855 Ray Lawyer Dr",
    "sg:city":"Placerville",
    "sg:classifiers":[
        {
            "category":"Professional",
            "type":"Services"
        }
    ],
    "sg:phone":"+1 530 344 0549",
    "sg:postcode":"95667",
    "sg:province":"CA",
    "wof:name":"Washoe Tribe of Nevada and Cal",
    "wof:placetype":"venue"
},
  "geometry": {"coordinates":[-120.835915,38.72828],"type":"Point"}
}