{
  "type": "Feature",
  "properties": {
    "iso:country":"US",
    "sg:address":"329 Ingalls St",
    "sg:city":"Santa Cruz",
    "sg:classifiers":[
        {
            "category":"Professional",
            "type":"Services"
        }
    ],
    "sg:phone":"+1 831 426 4283",
    "sg:postcode":"95060",
    "sg:province":"CA",
    "sg:tags":[
        "establishment"
    ],
    "wof:name":"Walls Harrison & Assoc",
    "wof:placetype":"venue"
},
  "geometry": {"coordinates":[-122.048602,36.9584],"type":"Point"}
}