{
  "type": "Feature",
  "properties": {
    "iso:country":"US",
    "sg:address":"612 Hampton Dr",
    "sg:city":"Venice",
    "sg:classifiers":[
        {
            "category":"Communications",
            "subcategory":"Film & Video Production",
            "type":"Services"
        }
    ],
    "sg:phone":"+1 310 392 8771",
    "sg:postcode":"90291",
    "sg:province":"CA",
    "sg:tags":[
        "television",
        "producer"
    ],
    "sg:website":"www.cmifilms.com",
    "wof:name":"Celestial Mechanix Inc",
    "wof:placetype":"venue"
},
  "geometry": {"coordinates":[-118.474783,33.994412],"type":"Point"}
}