{
  "type": "Feature",
  "properties": {
    "iso:country":"US",
    "sg:address":"4544 el Cerrito Dr",
    "sg:city":"San Diego",
    "sg:classifiers":[
        {
            "category":"Organizations",
            "subcategory":"Religious Organization",
            "type":"Services"
        }
    ],
    "sg:phone":"+1 619 582 4633",
    "sg:postcode":"92115",
    "sg:province":"CA",
    "sg:tags":[
        "church"
    ],
    "wof:name":"Blessed Sacrament Religious Ed",
    "wof:placetype":"venue"
},
  "geometry": {"coordinates":[-117.073756,32.759845],"type":"Point"}
}