{
  "type": "Feature",
  "properties": {
    "addr:full":"5116 E 12th St Oakland CA 94601",
    "addr:housenumber":"5116",
    "addr:postcode":"94601",
    "addr:street":"E 12Th St",
    "iso:country":"US",
    "sg:address":"5116 E 12th St",
    "sg:city":"Oakland",
    "sg:classifiers":[
        {
            "category":"Retail",
            "subcategory":"Auto Repair",
            "type":"Services"
        }
    ],
    "sg:phone":"+1 510 532 2537",
    "sg:postcode":"94601",
    "sg:province":"CA",
    "sg:tags":[
        "body",
        "automobile",
        "painting"
    ],
    "wof:name":"El Flaco Auto Body & Repair",
    "wof:placetype":"venue"
},
  "geometry": {"coordinates":[-122.20925200000001,37.766753],"type":"Point"}
}