{
  "type": "Feature",
  "properties": {
    "addr:full":"29019 S Western Ave Rancho Pls Vrds CA 90275",
    "addr:housenumber":"29019",
    "addr:postcode":"90275",
    "addr:street":"S Western Ave",
    "iso:country":"US",
    "sg:address":"29019 S Western Ave",
    "sg:city":"Rancho Pls Vrds",
    "sg:classifiers":[
        {
            "category":"Wholesale",
            "subcategory":"Apparel",
            "type":"Manufacturing & Wholesale Goods"
        },
        {
            "category":"Shopping",
            "subcategory":"Clothing, Apparel, & Fashions",
            "type":"Retail Goods"
        }
    ],
    "sg:phone":"+1 310 832 7519",
    "sg:postcode":"90275",
    "sg:province":"CA",
    "sg:tags":[
        "furnishing"
    ],
    "wof:name":"Planet Kids",
    "wof:placetype":"venue"
},
  "geometry": {"coordinates":[-118.309083,33.754012],"type":"Point"}
}