{
  "type": "Feature",
  "properties": {
    "addr:full":"3959 Laurel Canyon Blvd Arw A Studio City CA 91604",
    "addr:housenumber":"3959",
    "addr:postcode":"91604",
    "addr:street":"Laurel Canyon Blvd",
    "iso:country":"US",
    "sg:address":"3959 Laurel Canyon Blvd Arw A",
    "sg:city":"Studio City",
    "sg:classifiers":[
        {
            "category":"Personal",
            "subcategory":"Adult",
            "type":"Services"
        }
    ],
    "sg:phone":"+1 818 760 6541",
    "sg:postcode":"91604",
    "sg:province":"CA",
    "sg:tags":[
        "midwife"
    ],
    "sg:website":"www.homebirthservice.com",
    "wof:name":"Home Birth Service of Los Angeles",
    "wof:placetype":"venue"
},
  "geometry": {"coordinates":[-118.395184,34.142451],"type":"Point"}
}