{
  "type": "Feature",
  "properties": {
    "addr:full":"12280 Stonemill Dr Poway CA 92064",
    "addr:housenumber":"12280",
    "addr:postcode":"ca 92064",
    "addr:street":"Stonemill Dr",
    "iso:country":"US",
    "sg:address":"12280 Stonemill Dr",
    "sg:city":"Poway",
    "sg:classifiers":[
        {
            "category":"Manufacturing",
            "subcategory":"Printing",
            "type":"Manufacturing & Wholesale Goods"
        }
    ],
    "sg:phone":"+1 858 271 8456",
    "sg:postcode":"92064",
    "sg:province":"CA",
    "sg:tags":[
        "commercial"
    ],
    "wof:name":"Danielle Spartz",
    "wof:placetype":"venue"
},
  "geometry": {"coordinates":[-117.05867600000001,32.930516],"type":"Point"}
}