{
  "type": "Feature",
  "properties": {
    "addr:full":"1190 N Forbes St Lakeport CA 95453",
    "addr:housenumber":"1190",
    "addr:postcode":"95453",
    "addr:street":"N Forbes St",
    "iso:country":"US",
    "sg:address":"1190 N Forbes St",
    "sg:city":"Lakeport",
    "sg:classifiers":[
        {
            "category":"Organizations",
            "subcategory":"Religious Organization",
            "type":"Services"
        }
    ],
    "sg:phone":"+1 707 263 4785",
    "sg:postcode":"95453",
    "sg:province":"CA",
    "sg:tags":[
        "church"
    ],
    "wof:name":"St John's Episcopal Church",
    "wof:placetype":"venue"
},
  "geometry": {"coordinates":[-122.91600800000001,39.049049],"type":"Point"}
}