{
  "type": "Feature",
  "properties": {
    "addr:full":"8141 E Kaiser Blvd Anaheim CA 92808",
    "addr:housenumber":"8141",
    "addr:postcode":"92808",
    "addr:street":"E Kaiser Blvd",
    "iso:country":"US",
    "sg:address":"8141 E Kaiser Blvd",
    "sg:city":"Anaheim",
    "sg:classifiers":[
        {
            "category":"Professional",
            "subcategory":"Lawyer & Legal Services",
            "type":"Services"
        }
    ],
    "sg:phone":"+1 714 283 0140",
    "sg:postcode":"92808",
    "sg:province":"CA",
    "wof:name":"Fields C Kerry Attorney At Law",
    "wof:placetype":"venue"
},
  "geometry": {"coordinates":[-117.74400300000001,33.865898],"type":"Point"}
}