{
  "type": "Feature",
  "properties": {
    "iso:country":"US",
    "sg:address":"4300 Ming Ave",
    "sg:city":"Bakersfield",
    "sg:classifiers":[
        {
            "category":"Utilities",
            "subcategory":"Mobile Phone",
            "type":"Services"
        }
    ],
    "sg:phone":"+1 661 398 2000",
    "sg:postcode":"93309",
    "sg:province":"CA",
    "sg:tags":[
        "telephone",
        "cellular"
    ],
    "wof:name":"Cingular Wireless",
    "wof:placetype":"venue"
},
  "geometry": {"coordinates":[-119.05071599999999,35.339569],"type":"Point"}
}