{
  "type": "Feature",
  "properties": {
    "addr:full":"6601 Lakeview Dr Huntington Beach CA 92648",
    "addr:housenumber":"6601",
    "addr:postcode":"92648",
    "addr:street":"Lakeview Dr",
    "iso:country":"US",
    "sg:address":"6601 Lakeview Dr",
    "sg:city":"Huntington Beach",
    "sg:classifiers":[
        {
            "category":"Professional",
            "type":"Services"
        }
    ],
    "sg:phone":"+1 714 847 7037",
    "sg:postcode":"92648",
    "sg:province":"CA",
    "wof:name":"Eugene Long Lappl",
    "wof:placetype":"venue"
},
  "geometry": {"coordinates":[-118.010969,33.700218],"type":"Point"}
}