{
  "type": "Feature",
  "properties": {
    "addr:full":"126 E Haley St Santa Barbara CA 93101",
    "addr:housenumber":"126",
    "addr:postcode":"93101",
    "addr:street":"E Haley St",
    "iso:country":"US",
    "sg:address":"126 E Haley St",
    "sg:city":"Santa Barbara",
    "sg:classifiers":[
        {
            "category":"Shopping",
            "subcategory":"Stationery & Office Supplies",
            "type":"Retail Goods"
        }
    ],
    "sg:phone":"+1 805 965 0475",
    "sg:postcode":"93101",
    "sg:province":"CA",
    "sg:tags":[
        "educational",
        "material"
    ],
    "sg:website":"www.dollardiva.com",
    "wof:name":"Independent Means Inc",
    "wof:placetype":"venue"
},
  "geometry": {"coordinates":[-119.693639,34.418385],"type":"Point"}
}