{
  "type": "Feature",
  "properties": {
    "iso:country":"US",
    "sg:address":"1136 Loma Ave",
    "sg:city":"Coronado",
    "sg:classifiers":[
        {
            "category":"Personal",
            "subcategory":"Beauty Salon",
            "type":"Services"
        }
    ],
    "sg:phone":"+1 619 886 3658",
    "sg:postcode":"92118",
    "sg:province":"CA",
    "wof:name":"Wax Pot",
    "wof:placetype":"venue"
},
  "geometry": {"coordinates":[-117.179439,32.683682],"type":"Point"}
}