{
  "type": "Feature",
  "properties": {
    "iso:country":"US",
    "sg:address":"7700 College Town Dr # 101",
    "sg:city":"Sacramento",
    "sg:classifiers":[
        {
            "category":"Banks & Credit Unions",
            "subcategory":"Investment Brokerage",
            "type":"Services"
        },
        {
            "category":"Real Estate",
            "subcategory":"Developer",
            "type":"Services"
        }
    ],
    "sg:phone":"+1 916 383 2500",
    "sg:postcode":"95826",
    "sg:province":"CA",
    "sg:tags":[
        "investing"
    ],
    "wof:name":"North Natomas 575 Investors",
    "wof:placetype":"venue"
},
  "geometry": {"coordinates":[-121.414124,38.554173],"type":"Point"}
}