{
  "type": "Feature",
  "properties": {
    "iso:country":"US",
    "sg:address":"1440 Spring St",
    "sg:city":"St Helena",
    "sg:classifiers":[
        {
            "category":"Social Services",
            "subcategory":"Child Care",
            "type":"Services"
        }
    ],
    "sg:phone":"+1 707 967 8143",
    "sg:postcode":"94574",
    "sg:province":"CA",
    "sg:tags":[
        "kindergarten",
        "academic",
        "school"
    ],
    "wof:name":"TLC Preschool",
    "wof:placetype":"venue"
},
  "geometry": {"coordinates":[-122.470981,38.500804],"type":"Point"}
}