{
  "type": "Feature",
  "properties": {
    "iso:country":"US",
    "sg:address":"2663 Cordova Lane",
    "sg:city":"Rancho Cordova",
    "sg:classifiers":[
        {
            "category":"Shopping",
            "subcategory":"Pets & Pet Supplies",
            "type":"Retail Goods"
        }
    ],
    "sg:phone":"+1 916 635 1397",
    "sg:postcode":"95670",
    "sg:province":"CA",
    "sg:tags":[
        "store"
    ],
    "wof:name":"White Lion Pet Grooming",
    "wof:placetype":"venue"
},
  "geometry": {"coordinates":[-121.282955,38.600732],"type":"Point"}
}