{
  "type": "Feature",
  "properties": {
    "iso:country":"US",
    "sg:address":"12642 Casa Vista Rd",
    "sg:city":"Lakeside",
    "sg:classifiers":[
        {
            "category":"Building & Trades",
            "subcategory":"Construction",
            "type":"Services"
        }
    ],
    "sg:phone":"+1 619 334 7313",
    "sg:postcode":"92040",
    "sg:province":"CA",
    "sg:tags":[
        "painter"
    ],
    "wof:name":"Wright Painting Co",
    "wof:placetype":"venue"
},
  "geometry": {"coordinates":[-116.917428,32.852405],"type":"Point"}
}