{
  "type": "Feature",
  "properties": {
    "addr:full":"6260 Belleau Wood Ln Sacramento CA 95822",
    "addr:housenumber":"6260",
    "addr:postcode":"95822",
    "addr:street":"Belleau Wood Ln",
    "iso:country":"US",
    "sg:address":"6260 Belleau Wood Ln",
    "sg:city":"Sacramento",
    "sg:classifiers":[
        {
            "category":"Wholesale",
            "subcategory":"Non-durable Goods",
            "type":"Manufacturing & Wholesale Goods"
        },
        {
            "category":"Shopping",
            "subcategory":"Department Store",
            "type":"Retail Goods"
        },
        {
            "category":"Building & Trades",
            "subcategory":"Cleaning & Sanitation",
            "type":"Services"
        },
        {
            "category":"Home & Garden",
            "subcategory":"Hardware",
            "type":"Retail Goods"
        },
        {
            "category":"Autos & Motor Vehicles",
            "subcategory":"Auto Supplies",
            "type":"Retail Goods"
        }
    ],
    "sg:phone":"+1 916 421 9112",
    "sg:postcode":"95822",
    "sg:province":"CA",
    "sg:tags":[
        "cleaner",
        "house",
        "rug",
        "equipment",
        "manufacturer",
        "janitor",
        "supplies-wholesale",
        "carpet"
    ],
    "wof:name":"Merit Janitorial Supply",
    "wof:placetype":"venue"
},
  "geometry": {"coordinates":[-121.504456,38.512524],"type":"Point"}
}