{
  "type": "Feature",
  "properties": {
    "addr:full":"742 Park Way South San Francisco CA 94080",
    "addr:housenumber":"742",
    "addr:postcode":"94080",
    "addr:street":"Park Way",
    "iso:country":"US",
    "sg:address":"742 Park Way",
    "sg:city":"South San Francisco",
    "sg:classifiers":[
        {
            "category":"Organizations",
            "subcategory":"Religious Organization",
            "type":"Services"
        }
    ],
    "sg:phone":"+1 650 273 1497",
    "sg:postcode":"94080",
    "sg:province":"CA",
    "wof:name":"Bay Church",
    "wof:placetype":"venue"
},
  "geometry": {"coordinates":[-122.422408,37.662162],"type":"Point"}
}