{
  "type": "Feature",
  "properties": {
    "addr:full":"2373 E Muscat Ave Fresno CA 93725",
    "addr:housenumber":"2373",
    "addr:postcode":"93725",
    "addr:street":"E Muscat Ave",
    "iso:country":"US",
    "sg:address":"2373 E Muscat Ave",
    "sg:city":"Fresno",
    "sg:classifiers":[
        {
            "category":"Wholesale",
            "subcategory":"Machinery & Supplies",
            "type":"Manufacturing & Wholesale Goods"
        }
    ],
    "sg:phone":"+1 559 486 6821",
    "sg:postcode":"93725",
    "sg:province":"CA",
    "sg:tags":[
        "equipment"
    ],
    "wof:name":"Multi-Ag Systems",
    "wof:placetype":"venue"
},
  "geometry": {"coordinates":[-119.748244,36.685085],"type":"Point"}
}