{
  "type": "Feature",
  "properties": {
    "addr:full":"4501 Y Ste Ste 1008 Sacramento CA 95814",
    "addr:housenumber":"4501",
    "addr:postcode":"95814",
    "addr:street":"Y Ste Ste 1008",
    "iso:country":"US",
    "sg:address":"4501 Y Ste Ste 1008",
    "sg:city":"Sacramento",
    "sg:classifiers":[
        {
            "category":"Community Center",
            "type":"Public Place"
        }
    ],
    "sg:phone":"+1 916 734 5865",
    "sg:postcode":"95814",
    "sg:province":"CA",
    "sg:tags":[
        "medical"
    ],
    "wof:name":"UC Davis Health System",
    "wof:placetype":"venue"
},
  "geometry": {"coordinates":[-121.526978,38.589548],"type":"Point"}
}