{
  "type": "Feature",
  "properties": {
    "iso:country":"US",
    "sg:address":"234 Main St",
    "sg:city":"Pleasanton",
    "sg:classifiers":[
        {
            "category":"Travel",
            "subcategory":"Travel Agent",
            "type":"Entertainment"
        }
    ],
    "sg:phone":"+1 925 462 8484",
    "sg:postcode":"94566",
    "sg:province":"CA",
    "sg:tags":[
        "agency",
        "bureau"
    ],
    "wof:name":"Pleasanton Travel",
    "wof:placetype":"venue"
},
  "geometry": {"coordinates":[-121.876784,37.658698],"type":"Point"}
}