{
  "type": "Feature",
  "properties": {
    "addr:full":"5237 W Troy Fresno CA 93722",
    "addr:housenumber":"5237",
    "addr:postcode":"93722",
    "addr:street":"W",
    "iso:country":"US",
    "sg:address":"5237 W Troy",
    "sg:city":"Fresno",
    "sg:classifiers":[
        {
            "category":"Wholesale",
            "subcategory":"Vending Machines",
            "type":"Manufacturing & Wholesale Goods"
        }
    ],
    "sg:phone":"+1 559 271 7521",
    "sg:postcode":"93722",
    "sg:province":"CA",
    "sg:tags":[
        "operator"
    ],
    "wof:name":"Garrard Vending",
    "wof:placetype":"venue"
},
  "geometry": {"coordinates":[-119.88494799999999,36.847439],"type":"Point"}
}