{
  "type": "Feature",
  "properties": {
    "iso:country":"US",
    "sg:address":"978 Garnet Ave",
    "sg:city":"San Diego",
    "sg:classifiers":[
        {
            "category":"Restaurant",
            "type":"Food & Drink"
        }
    ],
    "sg:menulink":"http://www.allmenus.com/ca/san-diego/26870-limonz/menu/",
    "sg:phone":"+1 858 605 0093",
    "sg:postcode":"92109",
    "sg:province":"CA",
    "sg:tags":[
        "mexican"
    ],
    "wof:name":"Limonz",
    "wof:placetype":"venue"
},
  "geometry": {"coordinates":[-117.252217,32.797288],"type":"Point"}
}