{
  "type": "Feature",
  "properties": {
    "iso:country":"US",
    "sg:address":"5438 Holt Blvd",
    "sg:city":"Montclair",
    "sg:classifiers":[
        {
            "category":"Retail",
            "subcategory":"Auto Repair",
            "type":"Services"
        }
    ],
    "sg:phone":"+1 909 625 3939",
    "sg:postcode":"91763",
    "sg:province":"CA",
    "sg:tags":[
        "glass",
        "coating",
        "tinting"
    ],
    "sg:website":"www.acutint.com",
    "wof:name":"ACUTINT.COM",
    "wof:placetype":"venue"
},
  "geometry": {"coordinates":[-117.686095,34.063335],"type":"Point"}
}