{
  "type": "Feature",
  "properties": {
    "addr:full":"640 S Hayden Dr Escondido CA 92027",
    "addr:housenumber":"640",
    "addr:postcode":"92027",
    "addr:street":"S Hayden Dr",
    "iso:country":"US",
    "sg:address":"640 S Hayden Dr",
    "sg:city":"Escondido",
    "sg:classifiers":[
        {
            "category":"Shopping",
            "subcategory":"Florist",
            "type":"Retail Goods"
        }
    ],
    "sg:phone":"+1 760 745 3086",
    "sg:postcode":"92027",
    "sg:province":"CA",
    "wof:name":"Epis By Vogt",
    "wof:placetype":"venue"
},
  "geometry": {"coordinates":[-117.03456799999999,33.136067],"type":"Point"}
}