{
  "type": "Feature",
  "properties": {
    "iso:country":"US",
    "sg:address":"3500 Panama Ln",
    "sg:city":"Bakersfield",
    "sg:classifiers":[
        {
            "category":"Food & Beverages",
            "subcategory":"Groceries & Convenience Stores",
            "type":"Retail Goods"
        }
    ],
    "sg:phone":"+1 661 827 0394",
    "sg:postcode":"93313",
    "sg:province":"CA",
    "sg:tags":[
        "grocer"
    ],
    "sg:website":"http://www.albertsons.com/",
    "wof:name":"Albertson's",
    "wof:placetype":"venue"
},
  "geometry": {"coordinates":[-119.040547,35.295979],"type":"Point"}
}