{
  "type": "Feature",
  "properties": {
    "addr:full":"127 Heritage Village Way Campbell CA 95008",
    "addr:housenumber":"127",
    "addr:postcode":"95008",
    "addr:street":"Heritage Village Way",
    "iso:country":"US",
    "sg:address":"127 Heritage Village Way",
    "sg:city":"Campbell",
    "sg:classifiers":[
        {
            "category":"Retail",
            "subcategory":"Auto Repair",
            "type":"Services"
        }
    ],
    "sg:phone":"+1 408 374 6408",
    "sg:postcode":"95008",
    "sg:province":"CA",
    "sg:tags":[
        "automotive",
        "good",
        "mfg"
    ],
    "wof:name":"Mr Tint & Polish",
    "wof:placetype":"venue"
},
  "geometry": {"coordinates":[-121.94951399999999,37.289265],"type":"Point"}
}