{
  "type": "Feature",
  "properties": {
    "addr:full":"3468 Ave 408 Kingsburg CA 93631",
    "addr:housenumber":"3468",
    "addr:postcode":"93631",
    "addr:street":"Ave 408",
    "iso:country":"US",
    "sg:address":"3468 Ave 408",
    "sg:city":"Kingsburg",
    "sg:classifiers":[
        {
            "category":"Farming",
            "subcategory":"Farm",
            "type":"Manufacturing & Wholesale Goods"
        }
    ],
    "sg:phone":"+1 559 897 2057",
    "sg:postcode":"93631",
    "sg:province":"CA",
    "sg:tags":[
        "crop",
        "general"
    ],
    "wof:name":"RAD Farms",
    "wof:placetype":"venue"
},
  "geometry": {"coordinates":[-119.497952,36.532302],"type":"Point"}
}