{
  "type": "Feature",
  "properties": {
    "iso:country":"US",
    "sg:address":"127 N Campus Ave",
    "sg:city":"Upland",
    "sg:classifiers":[
        {
            "category":"Building & Trades",
            "subcategory":"Pest Control",
            "type":"Services"
        }
    ],
    "sg:phone":"+1 909 984 8262",
    "sg:postcode":"91786",
    "sg:province":"CA",
    "wof:name":"New Century Pest Control",
    "wof:placetype":"venue"
},
  "geometry": {"coordinates":[-117.641563,34.095778],"type":"Point"}
}