{
  "type": "Feature",
  "properties": {
    "addr:full":"1601 McDonald Way Bakersfield CA 93309",
    "addr:housenumber":"1601",
    "addr:postcode":"93309",
    "addr:street":"Mcdonald Way",
    "iso:country":"US",
    "sg:address":"1601 McDonald Way",
    "sg:city":"Bakersfield",
    "sg:classifiers":[
        {
            "category":"Retail",
            "subcategory":"Laundry & Dry Cleaning",
            "type":"Services"
        }
    ],
    "sg:phone":"+1 661 834 4953",
    "sg:postcode":"93309",
    "sg:province":"CA",
    "sg:tags":[
        "cleaners"
    ],
    "wof:name":"One Hour Martinizing",
    "wof:placetype":"venue"
},
  "geometry": {"coordinates":[-119.05305,35.339679],"type":"Point"}
}