{
  "type": "Feature",
  "properties": {
    "addr:full":"1310 Bay Rd East Palo Alto CA 94303",
    "addr:housenumber":"1310",
    "addr:postcode":"94303",
    "addr:street":"Bay Rd",
    "iso:country":"US",
    "sg:address":"1310 Bay Rd",
    "sg:city":"East Palo Alto",
    "sg:classifiers":[
        {
            "category":"Organizations",
            "subcategory":"Community Association",
            "type":"Services"
        }
    ],
    "sg:phone":"+1 650 853 9893",
    "sg:postcode":"94303",
    "sg:province":"CA",
    "sg:tags":[
        "club"
    ],
    "wof:name":"Tulip L Jones Clubhouse Inc",
    "wof:placetype":"venue"
},
  "geometry": {"coordinates":[-122.146091,37.470779],"type":"Point"}
}