{
  "type": "Feature",
  "properties": {
    "iso:country":"US",
    "sg:address":"1215 el Carmel Pl",
    "sg:city":"San Diego",
    "sg:classifiers":[
        {
            "category":"Organizations",
            "subcategory":"Community Association",
            "type":"Services"
        }
    ],
    "sg:phone":"+1 858 488 0501",
    "sg:postcode":"92109",
    "sg:province":"CA",
    "sg:tags":[
        "club"
    ],
    "sg:website":"www.mbyc.org",
    "wof:name":"Mission Bay Yacht Club",
    "wof:placetype":"venue"
},
  "geometry": {"coordinates":[-117.25078999999999,32.778321],"type":"Point"}
}