{
  "type": "Feature",
  "properties": {
    "addr:full":"107 Bridge St Arroyo Grande CA 93420",
    "addr:housenumber":"107",
    "addr:postcode":"93420",
    "addr:street":"Bridge St",
    "iso:country":"US",
    "sg:address":"107 Bridge St",
    "sg:city":"Arroyo Grande",
    "sg:classifiers":[
        {
            "category":"Wholesale",
            "subcategory":"Sporting Goods",
            "type":"Manufacturing & Wholesale Goods"
        }
    ],
    "sg:phone":"+1 805 489 5074",
    "sg:postcode":"93420",
    "sg:province":"CA",
    "wof:name":"Coast Cycling Specialties",
    "wof:placetype":"venue"
},
  "geometry": {"coordinates":[-120.578959,35.123105],"type":"Point"}
}