{
  "type": "Feature",
  "properties": {
    "addr:full":"500 N Central Ave. Suite 760 Glendale CA 91203",
    "addr:housenumber":"500",
    "addr:postcode":"91203",
    "addr:street":"N Central Ave. Suite 760",
    "iso:country":"US",
    "sg:address":"500 N Central Ave. Suite 760",
    "sg:city":"Glendale",
    "sg:classifiers":[
        {
            "category":"Health Services",
            "subcategory":"Dentist",
            "type":"Services"
        }
    ],
    "sg:phone":"+1 818 242 5400",
    "sg:postcode":"91203",
    "sg:province":"CA",
    "wof:name":"Dr. Michael O Downs DDS",
    "wof:placetype":"venue"
},
  "geometry": {"coordinates":[-118.257198,34.153226],"type":"Point"}
}