{
  "type": "Feature",
  "properties": {
    "iso:country":"US",
    "sg:address":"5800 Knoxville Rd",
    "sg:city":"Napa",
    "sg:classifiers":[
        {
            "category":"Recreation",
            "type":"Entertainment"
        }
    ],
    "sg:phone":"+1 707 966 2827",
    "sg:postcode":"94558",
    "sg:province":"CA",
    "sg:tags":[
        "charter",
        "boat"
    ],
    "wof:name":"Berryessa House Boat Rental",
    "wof:placetype":"venue"
},
  "geometry": {"coordinates":[-122.25479,38.585465],"type":"Point"}
}