{
  "type": "Feature",
  "properties": {
    "iso:country":"US",
    "sg:address":"6219 Van Nuys Blvd",
    "sg:city":"Van Nuys",
    "sg:classifiers":[
        {
            "category":"Restaurant",
            "type":"Food & Drink"
        }
    ],
    "sg:phone":"+1 818 901 9009",
    "sg:postcode":"91411",
    "sg:province":"CA",
    "sg:tags":[
        "traditional",
        "american"
    ],
    "wof:name":"Al's Chicken",
    "wof:placetype":"venue"
},
  "geometry": {"coordinates":[-118.44873699999999,34.183258],"type":"Point"}
}