{
  "type": "Feature",
  "properties": {
    "addr:full":"224 Meyers St Chico CA 95928",
    "addr:housenumber":"224",
    "addr:postcode":"95928",
    "addr:street":"Meyers St",
    "iso:country":"US",
    "sg:address":"224 Meyers St",
    "sg:city":"Chico",
    "sg:classifiers":[
        {
            "category":"Wholesale",
            "subcategory":"Hardware",
            "type":"Manufacturing & Wholesale Goods"
        }
    ],
    "sg:phone":"+1 530 894 1325",
    "sg:postcode":"95928",
    "sg:province":"CA",
    "sg:tags":[
        "plumbing"
    ],
    "wof:name":"J W Wood Co Inc",
    "wof:placetype":"venue"
},
  "geometry": {"coordinates":[-121.81867,39.713291],"type":"Point"}
}