{
  "type": "Feature",
  "properties": {
    "addr:full":"1201 Howard Avenue Burlingame CA 94010",
    "addr:housenumber":"1201",
    "addr:postcode":"94010",
    "addr:street":"Howard Avenue",
    "iso:country":"US",
    "sg:address":"1201 Howard Avenue",
    "sg:city":"Burlingame",
    "sg:classifiers":[
        {
            "category":"Professional",
            "subcategory":"Lawyer & Legal Services",
            "type":"Services"
        },
        {
            "category":"Building & Trades",
            "subcategory":"Construction",
            "type":"Services"
        }
    ],
    "sg:phone":"+1 650 579 7900",
    "sg:postcode":"94010",
    "sg:province":"CA",
    "sg:tags":[
        "contractor"
    ],
    "wof:name":"Stevens Nicholas A Company",
    "wof:placetype":"venue"
},
  "geometry": {"coordinates":[-122.34470399999999,37.577898],"type":"Point"}
}