{
  "type": "Feature",
  "properties": {
    "addr:full":"632 23rd St Richmond CA 94804",
    "addr:housenumber":"632",
    "addr:postcode":"94804",
    "addr:street":"23Rd St",
    "iso:country":"US",
    "sg:address":"632 23rd St",
    "sg:city":"Richmond",
    "sg:classifiers":[
        {
            "category":"Shopping",
            "subcategory":"Used Merchandise",
            "type":"Retail Goods"
        }
    ],
    "sg:phone":"+1 510 232 5253",
    "sg:postcode":"94804",
    "sg:province":"CA",
    "wof:name":"El Baratillo",
    "wof:placetype":"venue"
},
  "geometry": {"coordinates":[-122.347398,37.941044],"type":"Point"}
}