{
  "type": "Feature",
  "properties": {
    "iso:country":"US",
    "sg:address":"137 W Walnut Ave",
    "sg:city":"Monrovia",
    "sg:classifiers":[
        {
            "category":"Wholesale",
            "subcategory":"Durable Goods & Equipment",
            "type":"Manufacturing & Wholesale Goods"
        }
    ],
    "sg:phone":"+1 626 445 3370",
    "sg:postcode":"91016",
    "sg:province":"CA",
    "sg:tags":[
        "representative",
        "manufacturer"
    ],
    "wof:name":"SMA Marketing",
    "wof:placetype":"venue"
},
  "geometry": {"coordinates":[-118.00241800000001,34.143774],"type":"Point"}
}