{
  "type": "Feature",
  "properties": {
    "addr:full":"1608 W Campbell Ave Ste 313 Campbell CA 95008",
    "addr:housenumber":"1608",
    "addr:postcode":"95008",
    "addr:street":"W Campbell Ave Ste 313",
    "iso:country":"US",
    "sg:address":"1608 W Campbell Ave Ste 313",
    "sg:city":"Campbell",
    "sg:classifiers":[
        {
            "category":"Health Services",
            "subcategory":"Clinic",
            "type":"Services"
        }
    ],
    "sg:phone":"+1 530 873 4543",
    "sg:postcode":"95008",
    "sg:province":"CA",
    "sg:tags":[
        "counseling",
        "mental"
    ],
    "sg:website":"www.drmadelinedaniels.com/",
    "wof:name":"Dr. Madeline Daniels",
    "wof:placetype":"venue"
},
  "geometry": {"coordinates":[-121.979291,37.285321],"type":"Point"}
}