{
  "type": "Feature",
  "properties": {
    "iso:country":"US",
    "sg:address":"11655 Washington Blvd",
    "sg:city":"Whittier",
    "sg:classifiers":[
        {
            "category":"Manufacturing",
            "subcategory":"Motor Vehicles & Parts",
            "type":"Manufacturing & Wholesale Goods"
        }
    ],
    "sg:phone":"+1 562 464 9674",
    "sg:postcode":"90606",
    "sg:province":"CA",
    "sg:tags":[
        "body",
        "truck",
        "mfg"
    ],
    "wof:name":"Pacific Truck Equipment Inc",
    "wof:placetype":"venue"
},
  "geometry": {"coordinates":[-118.063896,33.97031],"type":"Point"}
}