{
  "type": "Feature",
  "properties": {
    "iso:country":"US",
    "sg:address":"757 E Arrow Hwy",
    "sg:city":"Glendora",
    "sg:classifiers":[
        {
            "category":"Recreation",
            "type":"Entertainment"
        }
    ],
    "sg:phone":"+1 626 857 9472",
    "sg:postcode":"91740",
    "sg:province":"CA",
    "sg:tags":[
        "martial",
        "arts",
        "instruction"
    ],
    "wof:name":"Academy Of Young Master",
    "wof:placetype":"venue"
},
  "geometry": {"coordinates":[-117.872013,34.106288],"type":"Point"}
}