{
  "type": "Feature",
  "properties": {
    "iso:country":"US",
    "sg:address":"8885 Rio San Diego Dr",
    "sg:city":"San Diego",
    "sg:classifiers":[
        {
            "category":"Banks & Credit Unions",
            "subcategory":"Investment Brokerage",
            "type":"Services"
        }
    ],
    "sg:phone":"+1 619 574 2550",
    "sg:postcode":"92108",
    "sg:province":"CA",
    "sg:tags":[
        "advisory",
        "financial"
    ],
    "sg:website":"www.mycountywide.com",
    "wof:name":"County Wide Financial",
    "wof:placetype":"venue"
},
  "geometry": {"coordinates":[-117.139879,32.775828],"type":"Point"}
}