{
  "type": "Feature",
  "properties": {
    "iso:country":"US",
    "sg:address":"654 Oakland Avenue",
    "sg:city":"Oakland",
    "sg:classifiers":[
        {
            "category":"Health Services",
            "subcategory":"Clinic",
            "type":"Services"
        }
    ],
    "sg:phone":"+1 510 229 4555",
    "sg:postcode":"94611",
    "sg:province":"CA",
    "sg:tags":[
        "counseling",
        "mental"
    ],
    "sg:website":"www.toilynnwyle.com/Andreatherap...",
    "wof:name":"The Healing Road",
    "wof:placetype":"venue"
},
  "geometry": {"coordinates":[-122.250237,37.820708],"type":"Point"}
}