{
  "type": "Feature",
  "properties": {
    "iso:country":"US",
    "sg:address":"3075 Citrus Cir",
    "sg:city":"Walnut Creek",
    "sg:classifiers":[
        {
            "category":"Professional",
            "subcategory":"Management & Consulting",
            "type":"Services"
        }
    ],
    "sg:phone":"+1 925 934 4393",
    "sg:postcode":"94598",
    "sg:province":"CA",
    "sg:tags":[
        "marketing",
        "consultant"
    ],
    "wof:name":"PDP Co",
    "wof:placetype":"venue"
},
  "geometry": {"coordinates":[-122.01478,37.92871],"type":"Point"}
}