{
  "type": "Feature",
  "properties": {
    "addr:full":"450 Charcot Ave San Jose CA 95131",
    "addr:housenumber":"450",
    "addr:postcode":"95131",
    "addr:street":"Charcot Ave",
    "iso:country":"US",
    "sg:address":"450 Charcot Ave",
    "sg:city":"San Jose",
    "sg:classifiers":[
        {
            "category":"Personal",
            "type":"Services"
        }
    ],
    "sg:phone":"+1 408 678 9900",
    "sg:postcode":"95131",
    "sg:province":"CA",
    "sg:tags":[
        "mover"
    ],
    "wof:name":"Corovan",
    "wof:placetype":"venue"
},
  "geometry": {"coordinates":[-121.91394200000001,37.383055],"type":"Point"}
}