{
  "type": "Feature",
  "properties": {
    "iso:country":"US",
    "sg:address":"4330 Clayton Rd",
    "sg:city":"Concord",
    "sg:classifiers":[
        {
            "category":"Personal",
            "subcategory":"Beauty Salon",
            "type":"Services"
        }
    ],
    "sg:phone":"+1 925 827 1618",
    "sg:postcode":"94521",
    "sg:province":"CA",
    "wof:name":"All Perfect Nails",
    "wof:placetype":"venue"
},
  "geometry": {"coordinates":[-121.991219,37.964208],"type":"Point"}
}