{
  "type": "Feature",
  "properties": {
    "addr:full":"2811 Castro Valley Blvd Castro Valley CA 94546",
    "addr:housenumber":"2811",
    "addr:postcode":"94546",
    "addr:street":"Castro Valley Blvd",
    "iso:country":"US",
    "sg:address":"2811 Castro Valley Blvd",
    "sg:city":"Castro Valley",
    "sg:classifiers":[
        {
            "category":"Insurance",
            "subcategory":"Insurance Agent",
            "type":"Services"
        }
    ],
    "sg:phone":"+1 510 537 6420",
    "sg:postcode":"94546",
    "sg:province":"CA",
    "wof:name":"State Farm Insurance",
    "wof:placetype":"venue"
},
  "geometry": {"coordinates":[-122.083063,37.695263],"type":"Point"}
}