{
  "type": "Feature",
  "properties": {
    "addr:full":"2660 Castro Valley Blvd Castro Valley CA 94546",
    "addr:housenumber":"2660",
    "addr:postcode":"94546",
    "addr:street":"Castro Valley Blvd",
    "iso:country":"US",
    "sg:address":"2660 Castro Valley Blvd",
    "sg:city":"Castro Valley",
    "sg:classifiers":[
        {
            "category":"Bars & Pubs",
            "subcategory":"Sports Bar",
            "type":"Food & Drink"
        }
    ],
    "sg:phone":"+1 510 581 4820",
    "sg:postcode":"94546",
    "sg:province":"CA",
    "wof:name":"Valley Inn",
    "wof:placetype":"venue"
},
  "geometry": {"coordinates":[-122.087604,37.694172],"type":"Point"}
}