{
  "type": "Feature",
  "properties": {
    "addr:full":"5050 Salida Blvd Salida CA 95368",
    "addr:housenumber":"5050",
    "addr:postcode":"95368",
    "addr:street":"Salida Blvd",
    "iso:country":"US",
    "sg:address":"5050 Salida Blvd",
    "sg:city":"Salida",
    "sg:classifiers":[
        {
            "category":"Professional",
            "subcategory":"Research",
            "type":"Services"
        }
    ],
    "sg:phone":"+1 209 545 1011",
    "sg:postcode":"95368",
    "sg:province":"CA",
    "sg:tags":[
        "environmental",
        "ecological"
    ],
    "sg:website":"www.safety-kleen.com",
    "wof:name":"Safety-Kleen Corp",
    "wof:placetype":"venue"
},
  "geometry": {"coordinates":[-121.086957,37.711306],"type":"Point"}
}