{
  "type": "Feature",
  "properties": {
    "iso:country":"US",
    "sg:address":"29 Montrose Ave",
    "sg:city":"Daly City",
    "sg:classifiers":[
        {
            "category":"Professional",
            "subcategory":"Management & Consulting",
            "type":"Services"
        }
    ],
    "sg:phone":"+1 650 991 6947",
    "sg:postcode":"94015",
    "sg:province":"CA",
    "sg:tags":[
        "marketing",
        "consultant"
    ],
    "wof:name":"Freds Garage",
    "wof:placetype":"venue"
},
  "geometry": {"coordinates":[-122.488494,37.689151],"type":"Point"}
}