{
  "type": "Feature",
  "properties": {
    "iso:country":"US",
    "sg:address":"119 W 223rd St",
    "sg:city":"Carson",
    "sg:classifiers":[
        {
            "category":"Travel",
            "subcategory":"Travel Agent",
            "type":"Entertainment"
        }
    ],
    "sg:phone":"+1 310 835 8533",
    "sg:postcode":"90745",
    "sg:province":"CA",
    "sg:tags":[
        "agency",
        "bureau"
    ],
    "wof:name":"R C Travel & Tours",
    "wof:placetype":"venue"
},
  "geometry": {"coordinates":[-118.277098,33.824444],"type":"Point"}
}