{
  "type": "Feature",
  "properties": {
    "addr:full":"10790 Wilshire Blvd Los Angeles CA 90024",
    "addr:housenumber":"10790",
    "addr:postcode":"90024",
    "addr:street":"Wilshire Blvd",
    "iso:country":"US",
    "sg:address":"10790 Wilshire Blvd",
    "sg:city":"Los Angeles",
    "sg:classifiers":[
        {
            "category":"Professional",
            "type":"Services"
        }
    ],
    "sg:phone":"+1 310 474 7914",
    "sg:postcode":"90024",
    "sg:province":"CA",
    "sg:tags":[
        "establishment"
    ],
    "wof:name":"Hamka Corp",
    "wof:placetype":"venue"
},
  "geometry": {"coordinates":[-118.43848699999999,34.060199],"type":"Point"}
}