{
  "type": "Feature",
  "properties": {
    "addr:full":"29524 Union City Blvd Union City CA 94587",
    "addr:housenumber":"29524",
    "addr:postcode":"94587",
    "addr:street":"Union City Blvd",
    "iso:country":"US",
    "sg:address":"29524 Union City Blvd",
    "sg:city":"Union City",
    "sg:classifiers":[
        {
            "category":"Professional",
            "type":"Services"
        }
    ],
    "sg:phone":"+1 510 476 0950",
    "sg:postcode":"94587",
    "sg:province":"CA",
    "sg:tags":[
        "establishment"
    ],
    "sg:website":"www.kumetrix.com",
    "wof:name":"Kumetrix Inc",
    "wof:placetype":"venue"
},
  "geometry": {"coordinates":[-122.082599,37.606918],"type":"Point"}
}