{
  "type": "Feature",
  "properties": {
    "addr:full":"605 Middlefield Rd Redwood City CA 94063",
    "addr:housenumber":"605",
    "addr:postcode":"94063",
    "addr:street":"Middlefield Rd",
    "iso:country":"US",
    "sg:address":"605 Middlefield Rd",
    "sg:city":"Redwood City",
    "sg:classifiers":[
        {
            "category":"Professional",
            "subcategory":"Lawyer & Legal Services",
            "type":"Services"
        }
    ],
    "sg:phone":"+1 650 365 7850",
    "sg:postcode":"94063",
    "sg:province":"CA",
    "sg:tags":[
        "attorney"
    ],
    "wof:name":"Pomeroy & Inama",
    "wof:placetype":"venue"
},
  "geometry": {"coordinates":[-122.229136,37.487574],"type":"Point"}
}