{
  "type": "Feature",
  "properties": {
    "addr:full":"5400 Cherry Ave Long Beach CA 90805",
    "addr:housenumber":"5400",
    "addr:postcode":"90805",
    "addr:street":"Cherry Ave",
    "iso:country":"US",
    "sg:address":"5400 Cherry Ave",
    "sg:city":"Long Beach",
    "sg:classifiers":[
        {
            "category":"Restaurant",
            "type":"Food & Drink"
        }
    ],
    "sg:phone":"+1 562 422 8395",
    "sg:postcode":"90805",
    "sg:province":"CA",
    "wof:name":"M & M Soul Food",
    "wof:placetype":"venue"
},
  "geometry": {"coordinates":[-118.16812299999999,33.855247],"type":"Point"}
}