{
  "type": "Feature",
  "properties": {
    "addr:full":"803 Coffee Rd Modesto CA 95355",
    "addr:housenumber":"803",
    "addr:postcode":"ca 95355",
    "addr:street":"Coffee Rd",
    "iso:country":"US",
    "sg:address":"803 Coffee Rd",
    "sg:city":"Modesto",
    "sg:classifiers":[
        {
            "category":"Health Services",
            "subcategory":"Doctor",
            "type":"Services"
        }
    ],
    "sg:phone":"+1 209 569 0776",
    "sg:postcode":"95355",
    "sg:province":"CA",
    "sg:tags":[
        "physician",
        "surgeon"
    ],
    "wof:name":"Frank Fine MD",
    "wof:placetype":"venue"
},
  "geometry": {"coordinates":[-120.97566999999999,37.657178],"type":"Point"}
}