{
  "type": "Feature",
  "properties": {
    "addr:full":"870 S Western Ave Los Angeles CA 90005",
    "addr:housenumber":"870",
    "addr:postcode":"90005",
    "addr:street":"S Western Ave",
    "iso:country":"US",
    "sg:address":"870 S Western Ave",
    "sg:city":"Los Angeles",
    "sg:classifiers":[
        {
            "category":"Shopping",
            "subcategory":"Clothing, Apparel, & Fashions",
            "type":"Retail Goods"
        }
    ],
    "sg:phone":"+1 213 383 9161",
    "sg:postcode":"90005",
    "sg:province":"CA",
    "sg:tags":[
        "accessory",
        "clothing",
        "women's"
    ],
    "wof:name":"Coco Fashion",
    "wof:placetype":"venue"
},
  "geometry": {"coordinates":[-118.308998,34.056499],"type":"Point"}
}