{
  "type": "Feature",
  "properties": {
    "addr:full":"23082 Terra Dr Laguna Hills CA 92653",
    "addr:housenumber":"23082",
    "addr:postcode":"92653",
    "addr:street":"Terra Dr",
    "iso:country":"US",
    "sg:address":"23082 Terra Dr",
    "sg:city":"Laguna Hills",
    "sg:classifiers":[
        {
            "category":"Food & Beverages",
            "subcategory":"Specialty",
            "type":"Retail Goods"
        }
    ],
    "sg:phone":"+1 949 855 1640",
    "sg:postcode":"92653",
    "sg:province":"CA",
    "sg:tags":[
        "water",
        "bulk",
        "company"
    ],
    "wof:name":"ITM Realty Inc",
    "wof:placetype":"venue"
},
  "geometry": {"coordinates":[-117.727987,33.626766],"type":"Point"}
}