{
  "type": "Feature",
  "properties": {
    "addr:full":"35 W Huntington Dr Arcadia CA 91006",
    "addr:housenumber":"35",
    "addr:postcode":"91006",
    "addr:street":"W Huntington Dr",
    "iso:country":"US",
    "sg:address":"35 W Huntington Dr",
    "sg:city":"Arcadia",
    "sg:classifiers":[
        {
            "category":"Retail",
            "subcategory":"Auto Rental",
            "type":"Services"
        }
    ],
    "sg:phone":"+1 626 574 0316",
    "sg:postcode":"91006",
    "sg:province":"CA",
    "sg:tags":[
        "renting",
        "truck",
        "leasing"
    ],
    "wof:name":"U-Haul Co",
    "wof:placetype":"venue"
},
  "geometry": {"coordinates":[-118.032274,34.140121],"type":"Point"}
}