{
  "type": "Feature",
  "properties": {
    "iso:country":"US",
    "sg:address":"1100 64th Ave",
    "sg:city":"Oakland",
    "sg:classifiers":[
        {
            "category":"Community Center",
            "subcategory":"Senior",
            "type":"Public Place"
        },
        {
            "category":"Social Services",
            "subcategory":"Adult Care",
            "type":"Services"
        },
        {
            "category":"Community Center",
            "type":"Public Place"
        }
    ],
    "sg:phone":"+1 510 562 7538",
    "sg:postcode":"94621",
    "sg:province":"CA",
    "sg:tags":[
        "counseling",
        "recreation",
        "citizen"
    ],
    "wof:name":"Palo Vista Senior Center",
    "wof:placetype":"venue"
},
  "geometry": {"coordinates":[-122.19921100000001,37.761139],"type":"Point"}
}