{
  "type": "Feature",
  "properties": {
    "addr:full":"1818 W Beverly Blvd Ste 103 Montebello CA 90640",
    "addr:housenumber":"1818",
    "addr:postcode":"90640",
    "addr:street":"W Beverly Blvd Ste 103",
    "iso:country":"US",
    "sg:address":"1818 W Beverly Blvd Ste 103",
    "sg:city":"Montebello",
    "sg:classifiers":[
        {
            "category":"Banks & Credit Unions",
            "subcategory":"Financial Services",
            "type":"Services"
        }
    ],
    "sg:phone":"+1 323 722 4411",
    "sg:postcode":"90640",
    "sg:province":"CA",
    "sg:tags":[
        "broker",
        "mortgage"
    ],
    "wof:name":"Executive Mortgage Group",
    "wof:placetype":"venue"
},
  "geometry": {"coordinates":[-118.11799600000001,34.019901],"type":"Point"}
}