{
  "type": "Feature",
  "properties": {
    "iso:country":"US",
    "sg:address":"2202 E Rosecrans Avenue",
    "sg:city":"Compton",
    "sg:classifiers":[
        {
            "category":"Building & Trades",
            "subcategory":"Locksmith",
            "type":"Services"
        }
    ],
    "sg:phone":"+1 310 637 7941",
    "sg:postcode":"90221",
    "sg:province":"CA",
    "sg:tags":[
        "key"
    ],
    "wof:name":"Mr G Locks & Key Service",
    "wof:placetype":"venue"
},
  "geometry": {"coordinates":[-118.199939,33.903382],"type":"Point"}
}