{
  "type": "Feature",
  "properties": {
    "addr:full":"3645 San Gabriel River Pkwy Pico Rivera CA 90660",
    "addr:housenumber":"3645",
    "addr:postcode":"90660",
    "addr:street":"San Gabriel River Pkwy",
    "iso:country":"US",
    "sg:address":"3645 San Gabriel River Pkwy",
    "sg:city":"Pico Rivera",
    "sg:classifiers":[
        {
            "category":"Manufacturing",
            "subcategory":"Tools & Machinery",
            "type":"Manufacturing & Wholesale Goods"
        }
    ],
    "sg:phone":"+1 562 463 7200",
    "sg:postcode":"90660",
    "sg:province":"CA",
    "sg:tags":[
        "equipment",
        "janitor",
        "supply"
    ],
    "wof:name":"Southcoast Sanitary Supply",
    "wof:placetype":"venue"
},
  "geometry": {"coordinates":[-118.058633,34.013686],"type":"Point"}
}