{
  "type": "Feature",
  "properties": {
    "addr:full":"2900 N Brea Blvd Fullerton CA 92835",
    "addr:housenumber":"2900",
    "addr:postcode":"92835",
    "addr:street":"N Brea Blvd",
    "iso:country":"US",
    "sg:address":"2900 N Brea Blvd",
    "sg:city":"Fullerton",
    "sg:classifiers":[
        {
            "category":"Retail",
            "subcategory":"Laundry & Dry Cleaning",
            "type":"Services"
        }
    ],
    "sg:phone":"+1 714 255 1153",
    "sg:postcode":"92835",
    "sg:province":"CA",
    "sg:tags":[
        "cleaners"
    ],
    "wof:name":"Regal Cleaners",
    "wof:placetype":"venue"
},
  "geometry": {"coordinates":[-117.90684,33.90443],"type":"Point"}
}