{
  "type": "Feature",
  "properties": {
    "iso:country":"US",
    "sg:address":"1970 E Grand Ave",
    "sg:city":"El Segundo",
    "sg:classifiers":[
        {
            "category":"Utilities",
            "subcategory":"Telephone",
            "type":"Services"
        }
    ],
    "sg:phone":"+1 310 426 9644",
    "sg:postcode":"90245",
    "sg:province":"CA",
    "sg:tags":[
        "communications"
    ],
    "wof:name":"Global Crossing USA Inc",
    "wof:placetype":"venue"
},
  "geometry": {"coordinates":[-118.392366,33.91938],"type":"Point"}
}