{
  "type": "Feature",
  "properties": {
    "iso:country":"US",
    "sg:address":"29229 Canwood St",
    "sg:city":"Agoura Hills",
    "sg:classifiers":[
        {
            "category":"Banks & Credit Unions",
            "subcategory":"Bank",
            "type":"Services"
        }
    ],
    "sg:phone":"+1 818 991 4600",
    "sg:postcode":"91301",
    "sg:province":"CA",
    "sg:tags":[
        "assistance",
        "foreclosure"
    ],
    "wof:name":"SBS Trust Deed Network",
    "wof:placetype":"venue"
},
  "geometry": {"coordinates":[-118.76137,34.1471],"type":"Point"}
}