{
  "type": "Feature",
  "properties": {
    "iso:country":"US",
    "sg:address":"204 S Ave 20",
    "sg:city":"Los Angeles",
    "sg:classifiers":[
        {
            "category":"Retail",
            "subcategory":"Laundry & Dry Cleaning",
            "type":"Services"
        }
    ],
    "sg:phone":"+1 323 221 0499",
    "sg:postcode":"90031",
    "sg:province":"CA",
    "sg:tags":[
        "cleaners",
        "rug",
        "carpet"
    ],
    "wof:name":"Paradise Carpet",
    "wof:placetype":"venue"
},
  "geometry": {"coordinates":[-118.218885,34.070803],"type":"Point"}
}