{
  "type": "Feature",
  "properties": {
    "iso:country":"US",
    "sg:address":"614 S Cleveland St",
    "sg:city":"Oceanside",
    "sg:classifiers":[
        {
            "category":"Building & Trades",
            "subcategory":"Construction",
            "type":"Services"
        }
    ],
    "sg:phone":"+1 760 943 1412",
    "sg:postcode":"92054",
    "sg:province":"CA",
    "sg:tags":[
        "contractor"
    ],
    "wof:name":"Choice General Construction",
    "wof:placetype":"venue"
},
  "geometry": {"coordinates":[-117.374881,33.187735],"type":"Point"}
}