{
  "type": "Feature",
  "properties": {
    "iso:country":"US",
    "sg:address":"3503 Lowell St",
    "sg:city":"San Diego",
    "sg:classifiers":[
        {
            "category":"Recreation",
            "type":"Entertainment"
        }
    ],
    "sg:phone":"+1 619 523 1913",
    "sg:postcode":"92106",
    "sg:province":"CA",
    "sg:tags":[
        "aquarium"
    ],
    "wof:name":"California Aquatics",
    "wof:placetype":"venue"
},
  "geometry": {"coordinates":[-117.231126,32.732051],"type":"Point"}
}