{
  "type": "Feature",
  "properties": {
    "addr:full":"864 Laurel St San Carlos CA 94070",
    "addr:housenumber":"864",
    "addr:postcode":"94070",
    "addr:street":"Laurel St",
    "iso:country":"US",
    "sg:address":"864 Laurel St",
    "sg:city":"San Carlos",
    "sg:classifiers":[
        {
            "category":"Health Services",
            "subcategory":"Health Practitioner",
            "type":"Services"
        }
    ],
    "sg:phone":"+1 650 508 0595",
    "sg:postcode":"94070",
    "sg:province":"CA",
    "sg:tags":[
        "therapist",
        "physical"
    ],
    "wof:name":"Studio Physical Therapy",
    "wof:placetype":"venue"
},
  "geometry": {"coordinates":[-122.25733200000001,37.503295],"type":"Point"}
}