{
  "type": "Feature",
  "properties": {
    "addr:full":"5050 Palo Verde St Montclair CA 91763",
    "addr:housenumber":"5050",
    "addr:postcode":"91763",
    "addr:street":"Palo Verde St",
    "iso:country":"US",
    "sg:address":"5050 Palo Verde St",
    "sg:city":"Montclair",
    "sg:classifiers":[
        {
            "category":"Banks & Credit Unions",
            "subcategory":"Investment Brokerage",
            "type":"Services"
        }
    ],
    "sg:phone":"+1 909 621 4703",
    "sg:postcode":"91763",
    "sg:province":"CA",
    "sg:tags":[
        "advisory",
        "financial"
    ],
    "wof:name":"Fac",
    "wof:placetype":"venue"
},
  "geometry": {"coordinates":[-117.695639,34.08148],"type":"Point"}
}