{
  "type": "Feature",
  "properties": {
    "addr:full":"8908 Madison Ave Fair Oaks CA 95628",
    "addr:housenumber":"8908",
    "addr:postcode":"95628",
    "addr:street":"Madison Ave",
    "iso:country":"US",
    "sg:address":"8908 Madison Ave",
    "sg:city":"Fair Oaks",
    "sg:classifiers":[
        {
            "category":"Health Services",
            "subcategory":"Doctor",
            "type":"Services"
        }
    ],
    "sg:phone":"+1 916 635 5509",
    "sg:postcode":"95628",
    "sg:province":"CA",
    "sg:tags":[
        "dentist"
    ],
    "wof:name":"Tim Landis DDS",
    "wof:placetype":"venue"
},
  "geometry": {"coordinates":[-121.223167,38.663856],"type":"Point"}
}