{
  "type": "Feature",
  "properties": {
    "addr:full":"670 N Archibald Ave Ontario CA 91764",
    "addr:housenumber":"670",
    "addr:postcode":"91764",
    "addr:street":"N Archibald Ave",
    "iso:country":"US",
    "sg:address":"670 N Archibald Ave",
    "sg:city":"Ontario",
    "sg:classifiers":[
        {
            "category":"Autos & Motor Vehicles",
            "subcategory":"Fuel & Gas Station",
            "type":"Retail Goods"
        }
    ],
    "sg:phone":"+1 909 941 0922",
    "sg:postcode":"91764",
    "sg:province":"CA",
    "sg:tags":[
        "oil"
    ],
    "wof:name":"Archibald Car Wash",
    "wof:placetype":"venue"
},
  "geometry": {"coordinates":[-117.59329,34.070157],"type":"Point"}
}