{
  "type": "Feature",
  "properties": {
    "addr:full":"5767 Rose Brook Dr Riverbank CA 95367",
    "addr:housenumber":"5767",
    "addr:postcode":"95367",
    "addr:street":"Rose Brook Dr",
    "iso:country":"US",
    "sg:address":"5767 Rose Brook Dr",
    "sg:city":"Riverbank",
    "sg:classifiers":[
        {
            "category":"Professional",
            "subcategory":"Computer Services",
            "type":"Services"
        }
    ],
    "sg:phone":"+1 209 869 4416",
    "sg:postcode":"95367",
    "sg:province":"CA",
    "sg:tags":[
        "repair"
    ],
    "wof:name":"Custom PC Of Central Valley",
    "wof:placetype":"venue"
},
  "geometry": {"coordinates":[-120.942117,37.722952],"type":"Point"}
}