{
  "type": "Feature",
  "properties": {
    "addr:full":"335 Bright St San Francisco CA 94132",
    "addr:housenumber":"335",
    "addr:postcode":"94132",
    "addr:street":"Bright St",
    "iso:country":"US",
    "sg:address":"335 Bright St",
    "sg:city":"San Francisco",
    "sg:classifiers":[
        {
            "category":"Professional",
            "type":"Services"
        }
    ],
    "sg:phone":"+1 415 771 1875",
    "sg:postcode":"94132",
    "sg:province":"CA",
    "wof:name":"United Fysts Operation",
    "wof:placetype":"venue"
},
  "geometry": {"coordinates":[-122.463611,37.717306],"type":"Point"}
}