{
  "type": "Feature",
  "properties": {
    "iso:country":"US",
    "sg:address":"15185 Mountain Lily Rd",
    "sg:city":"Sonora",
    "sg:classifiers":[
        {
            "category":"Building & Trades",
            "subcategory":"Plumbing",
            "type":"Services"
        }
    ],
    "sg:phone":"+1 209 532 0136",
    "sg:postcode":"95370",
    "sg:province":"CA",
    "sg:tags":[
        "plumbing",
        "contractor"
    ],
    "wof:name":"A-Able Plumbing",
    "wof:placetype":"venue"
},
  "geometry": {"coordinates":[-120.311076,37.949147],"type":"Point"}
}