{
  "type": "Feature",
  "properties": {
    "iso:country":"US",
    "sg:address":"668 E Redlands Blvd",
    "sg:city":"Redlands",
    "sg:classifiers":[
        {
            "category":"Insurance",
            "subcategory":"Hazard Insurance",
            "type":"Services"
        },
        {
            "category":"Insurance",
            "subcategory":"Insurance Agent",
            "type":"Services"
        },
        {
            "category":"Insurance",
            "subcategory":"Life Insurance",
            "type":"Services"
        },
        {
            "category":"Insurance",
            "subcategory":"Title Insurance",
            "type":"Services"
        }
    ],
    "sg:phone":"+1 909 793 3284",
    "sg:postcode":"92373",
    "sg:province":"CA",
    "sg:tags":[
        "auto",
        "commercial",
        "business",
        "homeowner"
    ],
    "sg:website":"http://www.farmersagent.com/bbeyerle/",
    "wof:name":"Elward Beyerle - Farmers Insurance",
    "wof:placetype":"venue"
},
  "geometry": {"coordinates":[-117.174215,34.053671],"type":"Point"}
}