{
  "type": "Feature",
  "properties": {
    "iso:country":"US",
    "sg:address":"461 E Johnston Ave",
    "sg:city":"Hemet",
    "sg:classifiers":[
        {
            "category":"Health Services",
            "subcategory":"Nursing And Care Facility",
            "type":"Services"
        }
    ],
    "sg:phone":"+1 951 658 2293",
    "sg:postcode":"92543",
    "sg:province":"CA",
    "sg:tags":[
        "home",
        "convalescent"
    ],
    "wof:name":"Meadowbrook Convalescent Hosp",
    "wof:placetype":"venue"
},
  "geometry": {"coordinates":[-116.96822,33.732968],"type":"Point"}
}