{
  "type": "Feature",
  "properties": {
    "addr:full":"415 Northgate Ct Tracy CA 95376",
    "addr:housenumber":"415",
    "addr:postcode":"95376",
    "addr:street":"Northgate Ct",
    "iso:country":"US",
    "sg:address":"415 Northgate Ct",
    "sg:city":"Tracy",
    "sg:classifiers":[
        {
            "category":"Professional",
            "type":"Services"
        }
    ],
    "sg:phone":"+1 209 832 0824",
    "sg:postcode":"95376",
    "sg:province":"CA",
    "wof:name":"Dianes Personal Creations",
    "wof:placetype":"venue"
},
  "geometry": {"coordinates":[-121.431928,37.760046],"type":"Point"}
}