{
  "type": "Feature",
  "properties": {
    "addr:full":"1327 S 46th St Richmond CA 94804",
    "addr:housenumber":"1327",
    "addr:postcode":"94804",
    "addr:street":"S 46Th St",
    "iso:country":"US",
    "sg:address":"1327 S 46th St",
    "sg:city":"Richmond",
    "sg:classifiers":[
        {
            "category":"Organizations",
            "subcategory":"Non-profit Organization",
            "type":"Services"
        }
    ],
    "sg:phone":"+1 510 231 5655",
    "sg:postcode":"94804",
    "sg:province":"CA",
    "sg:website":"www.aoinstitute.org",
    "wof:name":"Aquatic Outreach Institute",
    "wof:placetype":"venue"
},
  "geometry": {"coordinates":[-122.331632,37.915507],"type":"Point"}
}