{
  "type": "Feature",
  "properties": {
    "iso:country":"US",
    "sg:address":"530 MAIN ST.",
    "sg:city":"Weaverville",
    "sg:classifiers":[
        {
            "category":"Banks & Credit Unions",
            "subcategory":"Bank",
            "type":"Services"
        },
        {
            "category":"Banks & Credit Unions",
            "subcategory":"Financial Services",
            "type":"Services"
        }
    ],
    "sg:phone":"+1 530 623 2732",
    "sg:postcode":"96093",
    "sg:province":"CA",
    "sg:tags":[
        "saving",
        "loan",
        "commercial"
    ],
    "sg:website":"http://www.scottvalleybank.com",
    "wof:name":"Scott Valley Bank",
    "wof:placetype":"venue"
},
  "geometry": {"coordinates":[-122.938316,40.739819],"type":"Point"}
}