{
  "type": "Feature",
  "properties": {
    "iso:country":"US",
    "sg:address":"3219 Montrose Ave",
    "sg:city":"Glendale",
    "sg:classifiers":[
        {
            "category":"Building & Trades",
            "subcategory":"Construction",
            "type":"Services"
        }
    ],
    "sg:phone":"+1 818 248 3939",
    "sg:postcode":"91214",
    "sg:province":"CA",
    "sg:tags":[
        "interior",
        "design"
    ],
    "wof:name":"Studio Exodus Inc",
    "wof:placetype":"venue"
},
  "geometry": {"coordinates":[-118.249353,34.22229],"type":"Point"}
}