{
  "type": "Feature",
  "properties": {
    "addr:full":"177 Valencia St San Francisco CA 94102",
    "addr:housenumber":"177",
    "addr:postcode":"94102",
    "addr:street":"Valencia St",
    "iso:country":"US",
    "sg:address":"177 Valencia St",
    "sg:city":"San Francisco",
    "sg:classifiers":[
        {
            "category":"Personal",
            "subcategory":"Tattoo Parlor",
            "type":"Services"
        }
    ],
    "sg:phone":"+1 415 431 2100",
    "sg:postcode":"94102",
    "sg:province":"CA",
    "sg:tags":[
        "tattooing"
    ],
    "sg:website":"blackhearttattoosf.com",
    "wof:name":"Black Heart Tattoo",
    "wof:placetype":"venue"
},
  "geometry": {"coordinates":[-122.42241799999999,37.770369],"type":"Point"}
}