{
  "type": "Feature",
  "properties": {
    "iso:country":"US",
    "sg:address":"3031 W March Ln",
    "sg:city":"Stockton",
    "sg:classifiers":[
        {
            "category":"Health Services",
            "subcategory":"Doctor",
            "type":"Services"
        }
    ],
    "sg:phone":"+1 209 951 0673",
    "sg:postcode":"95219",
    "sg:province":"CA",
    "sg:tags":[
        "dentist"
    ],
    "wof:name":"Gary Sakai DDS",
    "wof:placetype":"venue"
},
  "geometry": {"coordinates":[-121.348743,37.984336],"type":"Point"}
}