{
  "type": "Feature",
  "properties": {
    "iso:country":"US",
    "sg:address":"101 Roblar Dr",
    "sg:city":"Novato",
    "sg:classifiers":[
        {
            "category":"Shopping",
            "type":"Retail Goods"
        }
    ],
    "sg:phone":"+1 415 499 1313",
    "sg:postcode":"94949",
    "sg:province":"CA",
    "sg:tags":[
        "repair",
        "hot",
        "tub",
        "spa"
    ],
    "wof:name":"Spa Warrior",
    "wof:placetype":"venue"
},
  "geometry": {"coordinates":[-122.534444,38.065837],"type":"Point"}
}