{
  "type": "Feature",
  "properties": {
    "iso:country":"US",
    "sg:address":"85 Saratoga Ave",
    "sg:city":"Santa Clara",
    "sg:classifiers":[
        {
            "category":"Real Estate",
            "subcategory":"Real Estate Agent",
            "type":"Services"
        }
    ],
    "sg:phone":"+1 408 615 6911",
    "sg:postcode":"95051",
    "sg:province":"CA",
    "wof:name":"Awbrey Development Inc",
    "wof:placetype":"venue"
},
  "geometry": {"coordinates":[-121.969853,37.323395],"type":"Point"}
}