{
  "type": "Feature",
  "properties": {
    "addr:full":"22708 Broadway St Columbia CA 95310",
    "addr:housenumber":"22708",
    "addr:postcode":"95310",
    "addr:street":"Broadway St",
    "iso:country":"US",
    "sg:address":"22708 Broadway St",
    "sg:city":"Columbia",
    "sg:classifiers":[
        {
            "category":"Government",
            "subcategory":"Office",
            "type":"Public Place"
        }
    ],
    "sg:phone":"+1 209 532 0150",
    "sg:postcode":"95310",
    "sg:province":"CA",
    "sg:tags":[
        "state",
        "park"
    ],
    "wof:name":"Calaveras District Office",
    "wof:placetype":"venue"
},
  "geometry": {"coordinates":[-120.401796,38.035508],"type":"Point"}
}