{
  "type": "Feature",
  "properties": {
    "iso:country":"US",
    "sg:address":"12565 S Manthey Rd",
    "sg:city":"Lathrop",
    "sg:classifiers":[
        {
            "category":"Freight",
            "type":"Transportation"
        }
    ],
    "sg:phone":"+1 209 234 8888",
    "sg:postcode":"95330",
    "sg:province":"CA",
    "sg:tags":[
        "special",
        "general"
    ],
    "wof:name":"Silver Chase Self Storage",
    "wof:placetype":"venue"
},
  "geometry": {"coordinates":[-121.285831,37.842504],"type":"Point"}
}