{
  "type": "Feature",
  "properties": {
    "addr:full":"2655 E Colorado Blvd Pasadena CA 91107",
    "addr:housenumber":"2655",
    "addr:postcode":"91107",
    "addr:street":"E Colorado Blvd",
    "iso:country":"US",
    "sg:address":"2655 E Colorado Blvd",
    "sg:city":"Pasadena",
    "sg:classifiers":[
        {
            "category":"Autos & Motor Vehicles",
            "subcategory":"Automobile Sales",
            "type":"Retail Goods"
        },
        {
            "category":"Autos & Motor Vehicles",
            "subcategory":"Auto Supplies",
            "type":"Retail Goods"
        }
    ],
    "sg:phone":"+1 626 564 0953",
    "sg:postcode":"91107",
    "sg:province":"CA",
    "sg:tags":[
        "used",
        "car",
        "accessory",
        "dealers-used",
        "part",
        "new",
        "cars-wholesale"
    ],
    "sg:website":"www.pasadenacarsales.com",
    "wof:name":"Pasadena Car Sales",
    "wof:placetype":"venue"
},
  "geometry": {"coordinates":[-118.09552600000001,34.146432],"type":"Point"}
}