{
  "type": "Feature",
  "properties": {
    "addr:full":"3929 W Olympic Blvd Los Angeles CA 90019",
    "addr:housenumber":"3929",
    "addr:postcode":"90019",
    "addr:street":"W Olympic Blvd",
    "iso:country":"US",
    "sg:address":"3929 W Olympic Blvd",
    "sg:city":"Los Angeles",
    "sg:classifiers":[
        {
            "category":"Restaurant",
            "type":"Food & Drink"
        }
    ],
    "sg:phone":"+1 323 935 5554",
    "sg:postcode":"90019",
    "sg:province":"CA",
    "sg:tags":[
        "korean"
    ],
    "wof:name":"Baek Ha Chong",
    "wof:placetype":"venue"
},
  "geometry": {"coordinates":[-118.320308,34.053671],"type":"Point"}
}