{
  "type": "Feature",
  "properties": {
    "iso:country":"US",
    "sg:address":"5855 E Naples Plz",
    "sg:city":"Long Beach",
    "sg:classifiers":[
        {
            "category":"Insurance",
            "subcategory":"Insurance Agent",
            "type":"Services"
        }
    ],
    "sg:phone":"+1 562 439 8004",
    "sg:postcode":"90803",
    "sg:province":"CA",
    "wof:name":"Robert Hickey Insurance",
    "wof:placetype":"venue"
},
  "geometry": {"coordinates":[-118.119691,33.755972],"type":"Point"}
}