{
  "type": "Feature",
  "properties": {
    "iso:country":"US",
    "sg:address":"1210 Vera Ave",
    "sg:city":"Ripon",
    "sg:classifiers":[
        {
            "category":"Government",
            "subcategory":"Office",
            "type":"Public Place"
        }
    ],
    "sg:phone":"+1 209 599 2151",
    "sg:postcode":"95366",
    "sg:province":"CA",
    "sg:tags":[
        "housing",
        "program"
    ],
    "wof:name":"Department Bldg & Pub Works",
    "wof:placetype":"venue"
},
  "geometry": {"coordinates":[-121.132909,37.730754],"type":"Point"}
}