{
  "type": "Feature",
  "properties": {
    "addr:full":"230 S Irwindale Ave Azusa CA 91702",
    "addr:housenumber":"230",
    "addr:postcode":"91702",
    "addr:street":"S Irwindale Ave",
    "iso:country":"US",
    "sg:address":"230 S Irwindale Ave",
    "sg:city":"Azusa",
    "sg:classifiers":[
        {
            "category":"Wholesale",
            "subcategory":"Machinery & Supplies",
            "type":"Manufacturing & Wholesale Goods"
        }
    ],
    "sg:phone":"+1 626 969 7044",
    "sg:postcode":"91702",
    "sg:province":"CA",
    "sg:tags":[
        "heavy",
        "equipment",
        "construction"
    ],
    "wof:name":"Co Op Backhoe Service",
    "wof:placetype":"venue"
},
  "geometry": {"coordinates":[-117.933871,34.119001],"type":"Point"}
}