{
  "type": "Feature",
  "properties": {
    "iso:country":"US",
    "sg:address":"2102 Business Center Dr 115M",
    "sg:city":"Irvine",
    "sg:classifiers":[
        {
            "category":"Professional",
            "subcategory":"Engineering",
            "type":"Services"
        }
    ],
    "sg:phone":"+1 949 651 1164",
    "sg:postcode":"92612",
    "sg:province":"CA",
    "sg:tags":[
        "industrial",
        "engineer"
    ],
    "wof:name":"Vertech Industrial Systems",
    "wof:placetype":"venue"
},
  "geometry": {"coordinates":[-117.857263,33.678244],"type":"Point"}
}