{
  "type": "Feature",
  "properties": {
    "iso:country":"US",
    "sg:address":"123 W Honolulu St",
    "sg:city":"Lindsay",
    "sg:classifiers":[
        {
            "category":"Restaurant",
            "type":"Food & Drink"
        }
    ],
    "sg:phone":"+1 559 562 2330",
    "sg:postcode":"93247",
    "sg:province":"CA",
    "sg:tags":[
        "mexican"
    ],
    "wof:name":"El Patio Restaurant",
    "wof:placetype":"venue"
},
  "geometry": {"coordinates":[-119.090328,36.202509],"type":"Point"}
}