{
  "type": "Feature",
  "properties": {
    "addr:full":"1851 Montebello Town Center Montebello CA 90640",
    "addr:housenumber":"1851",
    "addr:postcode":"90640",
    "addr:street":"Montebello Town",
    "iso:country":"US",
    "sg:address":"1851 Montebello Town Center",
    "sg:city":"Montebello",
    "sg:classifiers":[
        {
            "category":"Shopping",
            "subcategory":"Gifts & Souvenirs",
            "type":"Retail Goods"
        }
    ],
    "sg:phone":"+1 323 889 1930",
    "sg:postcode":"90640",
    "sg:province":"CA",
    "wof:name":"Ruggles",
    "wof:placetype":"venue"
},
  "geometry": {"coordinates":[-118.087334,34.035407],"type":"Point"}
}