{
  "type": "Feature",
  "properties": {
    "addr:full":"14956 Delano St Van Nuys CA 91411",
    "addr:housenumber":"14956",
    "addr:postcode":"91411",
    "addr:street":"Delano St",
    "iso:country":"US",
    "sg:address":"14956 Delano St",
    "sg:city":"Van Nuys",
    "sg:classifiers":[
        {
            "category":"Communications",
            "subcategory":"Film & Video Production",
            "type":"Services"
        }
    ],
    "sg:phone":"+1 818 908 1087",
    "sg:postcode":"91411",
    "sg:province":"CA",
    "sg:tags":[
        "motion",
        "picture",
        "studio",
        "producer"
    ],
    "wof:name":"G M Foam",
    "wof:placetype":"venue"
},
  "geometry": {"coordinates":[-118.458596,34.182498],"type":"Point"}
}