{
  "type": "Feature",
  "properties": {
    "addr:full":"345 Spear Street San Francisco CA 94105",
    "addr:housenumber":"345",
    "addr:postcode":"94105",
    "addr:street":"Spear Street",
    "iso:country":"US",
    "sg:address":"345 Spear Street",
    "sg:city":"San Francisco",
    "sg:classifiers":[
        {
            "category":"Communications",
            "subcategory":"Newspaper",
            "type":"Services"
        },
        {
            "category":"Professional",
            "subcategory":"Business Services",
            "type":"Services"
        }
    ],
    "sg:phone":"+1 415 882 9494",
    "sg:postcode":"94105",
    "sg:province":"CA",
    "sg:tags":[
        "relation",
        "public",
        "advertising"
    ],
    "wof:name":"Loomis Group",
    "wof:placetype":"venue"
},
  "geometry": {"coordinates":[-122.389999,37.789501],"type":"Point"}
}