{
  "type": "Feature",
  "properties": {
    "iso:country":"US",
    "sg:address":"1525 Olympic Blvd",
    "sg:city":"Walnut Creek",
    "sg:classifiers":[
        {
            "category":"Personal",
            "subcategory":"Beauty Salon",
            "type":"Services"
        }
    ],
    "sg:phone":"+1 925 930 7878",
    "sg:postcode":"94595",
    "sg:province":"CA",
    "sg:tags":[
        "manicuring"
    ],
    "wof:name":"Olympic Nail Care",
    "wof:placetype":"venue"
},
  "geometry": {"coordinates":[-122.06106699999999,37.896112],"type":"Point"}
}