{
  "type": "Feature",
  "properties": {
    "iso:country":"US",
    "sg:address":"2605 E Foothill Blvd",
    "sg:city":"Glendora",
    "sg:classifiers":[
        {
            "category":"Manufacturing",
            "subcategory":"Printing",
            "type":"Manufacturing & Wholesale Goods"
        }
    ],
    "sg:phone":"+1 626 852 9904",
    "sg:postcode":"91740",
    "sg:province":"CA",
    "sg:tags":[
        "printer"
    ],
    "wof:name":"Direct Print & Promotion",
    "wof:placetype":"venue"
},
  "geometry": {"coordinates":[-117.812966,34.125794],"type":"Point"}
}