{
  "type": "Feature",
  "properties": {
    "addr:full":"2112 W Whittier Blvd Montebello CA 90640",
    "addr:housenumber":"2112",
    "addr:postcode":"90640",
    "addr:street":"W Whittier Blvd",
    "iso:country":"US",
    "sg:address":"2112 W Whittier Blvd",
    "sg:city":"Montebello",
    "sg:classifiers":[
        {
            "category":"Professional",
            "subcategory":"Accounting & Tax Preparation",
            "type":"Services"
        }
    ],
    "sg:phone":"+1 323 728 6551",
    "sg:postcode":"90640",
    "sg:province":"CA",
    "sg:tags":[
        "accountant"
    ],
    "wof:name":"Accounting & Tax Services Russell Palfreyman",
    "wof:placetype":"venue"
},
  "geometry": {"coordinates":[-118.12400100000001,34.013401],"type":"Point"}
}