{
  "type": "Feature",
  "properties": {
    "iso:country":"US",
    "sg:address":"755 N Kilkea Drive",
    "sg:city":"Los Angeles",
    "sg:classifiers":[
        {
            "category":"Building & Trades",
            "subcategory":"Construction",
            "type":"Services"
        }
    ],
    "sg:phone":"+1 323 782 4949",
    "sg:postcode":"90046",
    "sg:province":"CA",
    "sg:tags":[
        "interior",
        "design"
    ],
    "wof:name":"Hutt Antonia & Associates",
    "wof:placetype":"venue"
},
  "geometry": {"coordinates":[-118.367082,34.085291],"type":"Point"}
}