{
  "type": "Feature",
  "properties": {
    "addr:full":"3501 Fruitvale Ave Bakersfield CA 93308",
    "addr:housenumber":"3501",
    "addr:postcode":"93308",
    "addr:street":"Fruitvale Ave",
    "iso:country":"US",
    "sg:address":"3501 Fruitvale Ave",
    "sg:city":"Bakersfield",
    "sg:classifiers":[
        {
            "category":"Building & Trades",
            "subcategory":"Equipment Rental",
            "type":"Services"
        }
    ],
    "sg:phone":"+1 661 588 8770",
    "sg:postcode":"93308",
    "sg:province":"CA",
    "sg:tags":[
        "yard"
    ],
    "sg:website":"www.qrs-cat.com",
    "wof:name":"Quinn Rental Svc",
    "wof:placetype":"venue"
},
  "geometry": {"coordinates":[-119.07441900000001,35.393816],"type":"Point"}
}