{
  "type": "Feature",
  "properties": {
    "addr:full":"104 7th St San Francisco CA 94103",
    "addr:housenumber":"104",
    "addr:postcode":"94103",
    "addr:street":"7Th St",
    "iso:country":"US",
    "sg:address":"104 7th St",
    "sg:city":"San Francisco",
    "sg:classifiers":[
        {
            "category":"Restaurant",
            "type":"Food & Drink"
        }
    ],
    "sg:phone":"+1 415 626 8381",
    "sg:postcode":"94103",
    "sg:province":"CA",
    "wof:name":"Soma Pizza",
    "wof:placetype":"venue"
},
  "geometry": {"coordinates":[-122.410515,37.778793],"type":"Point"}
}