{
  "type": "Feature",
  "properties": {
    "addr:full":"2160 Bacon St San Diego CA 92107",
    "addr:housenumber":"2160",
    "addr:postcode":"92107",
    "addr:street":"Bacon St",
    "iso:country":"US",
    "sg:address":"2160 Bacon St",
    "sg:city":"San Diego",
    "sg:classifiers":[
        {
            "category":"Organizations",
            "subcategory":"Religious Organization",
            "type":"Services"
        }
    ],
    "sg:phone":"+1 619 222 1224",
    "sg:postcode":"92107",
    "sg:province":"CA",
    "wof:name":"New Life Christian Chapel",
    "wof:placetype":"venue"
},
  "geometry": {"coordinates":[-117.24700199999999,32.751202],"type":"Point"}
}