{
  "type": "Feature",
  "properties": {
    "iso:country":"US",
    "sg:address":"19315 Saticoy St",
    "sg:city":"Reseda",
    "sg:classifiers":[
        {
            "category":"Wholesale",
            "subcategory":"Toys & Hobbies",
            "type":"Manufacturing & Wholesale Goods"
        }
    ],
    "sg:phone":"+1 818 885 0202",
    "sg:postcode":"91335",
    "sg:province":"CA",
    "sg:tags":[
        "tape",
        "video",
        "rental"
    ],
    "wof:name":"20/20 Video Inc",
    "wof:placetype":"venue"
},
  "geometry": {"coordinates":[-118.555437,34.208288],"type":"Point"}
}