{
  "type": "Feature",
  "properties": {
    "addr:full":"12334 Kenny Dr Granada Hills CA 91344",
    "addr:housenumber":"12334",
    "addr:postcode":"91344",
    "addr:street":"Kenny Dr",
    "iso:country":"US",
    "sg:address":"12334 Kenny Dr",
    "sg:city":"Granada Hills",
    "sg:classifiers":[
        {
            "category":"Insurance",
            "subcategory":"Insurance Agent",
            "type":"Services"
        }
    ],
    "sg:phone":"+1 818 368 1232",
    "sg:postcode":"91344",
    "sg:province":"CA",
    "wof:name":"Bryant Insurance Services",
    "wof:placetype":"venue"
},
  "geometry": {"coordinates":[-118.498454,34.294379],"type":"Point"}
}