{
  "type": "Feature",
  "properties": {
    "addr:full":"728 Via Otono San Clemente CA 92672",
    "addr:housenumber":"728",
    "addr:postcode":"92672",
    "addr:street":"Via Otono",
    "iso:country":"US",
    "sg:address":"728 Via Otono",
    "sg:city":"San Clemente",
    "sg:classifiers":[
        {
            "category":"Professional",
            "type":"Services"
        }
    ],
    "sg:phone":"+1 949 498 2715",
    "sg:postcode":"92672",
    "sg:province":"CA",
    "wof:name":"Compass Organization",
    "wof:placetype":"venue"
},
  "geometry": {"coordinates":[-117.60014,33.446759],"type":"Point"}
}