{
  "type": "Feature",
  "properties": {
    "addr:full":"10010 Magnolia Ave Riverside CA 92503",
    "addr:housenumber":"10010",
    "addr:postcode":"92503",
    "addr:street":"Magnolia Ave",
    "iso:country":"US",
    "sg:address":"10010 Magnolia Ave",
    "sg:city":"Riverside",
    "sg:classifiers":[
        {
            "category":"Restaurant",
            "type":"Food & Drink"
        }
    ],
    "sg:menulink":"http://www.allmenus.com/ca/riverside/170856-carls-jr/menu/",
    "sg:phone":"+1 951 351 0818",
    "sg:postcode":"92503",
    "sg:province":"CA",
    "sg:tags":[
        "burger",
        "american"
    ],
    "wof:name":"Carl's Jr.",
    "wof:placetype":"venue"
},
  "geometry": {"coordinates":[-117.45608,33.914405],"type":"Point"}
}