{
  "type": "Feature",
  "properties": {
    "addr:full":"32451 Golden Lantern Laguna Niguel CA 92677",
    "addr:housenumber":"32451",
    "addr:postcode":"92677",
    "addr:street":"Golden Lantern",
    "iso:country":"US",
    "sg:address":"32451 Golden Lantern",
    "sg:city":"Laguna Niguel",
    "sg:classifiers":[
        {
            "category":"Sports & Exercise",
            "subcategory":"Gym",
            "type":"Entertainment"
        }
    ],
    "sg:phone":"+1 949 443 2440",
    "sg:postcode":"92677",
    "sg:province":"CA",
    "sg:tags":[
        "club",
        "health",
        "studio",
        "gymnasium"
    ],
    "wof:name":"24 Hour Fitness",
    "wof:placetype":"venue"
},
  "geometry": {"coordinates":[-117.69673899999999,33.492327],"type":"Point"}
}