{
  "type": "Feature",
  "properties": {
    "iso:country":"US",
    "sg:address":"3706 Merrimac Ave",
    "sg:city":"San Diego",
    "sg:classifiers":[
        {
            "category":"Building & Trades",
            "subcategory":"Construction",
            "type":"Services"
        }
    ],
    "sg:phone":"+1 858 272 6023",
    "sg:postcode":"92117",
    "sg:province":"CA",
    "sg:tags":[
        "concrete",
        "contractor"
    ],
    "wof:name":"Richwood Floors",
    "wof:placetype":"venue"
},
  "geometry": {"coordinates":[-117.206228,32.83617],"type":"Point"}
}