{
  "type": "Feature",
  "properties": {
    "iso:country":"US",
    "sg:address":"636 Mindy Way",
    "sg:city":"San Jose",
    "sg:classifiers":[
        {
            "category":"Recreation",
            "type":"Entertainment"
        }
    ],
    "sg:phone":"+1 408 225 1929",
    "sg:postcode":"95123",
    "sg:province":"CA",
    "sg:tags":[
        "ticket"
    ],
    "wof:name":"Johns Giants",
    "wof:placetype":"venue"
},
  "geometry": {"coordinates":[-121.829116,37.228526],"type":"Point"}
}