{
  "type": "Feature",
  "properties": {
    "addr:full":"5750 Woodman Ave Van Nuys CA 91401",
    "addr:housenumber":"5750",
    "addr:postcode":"91401",
    "addr:street":"Woodman Ave",
    "iso:country":"US",
    "sg:address":"5750 Woodman Ave",
    "sg:city":"Van Nuys",
    "sg:classifiers":[
        {
            "category":"Wholesale",
            "subcategory":"Machinery & Supplies",
            "type":"Manufacturing & Wholesale Goods"
        }
    ],
    "sg:phone":"+1 818 780 8421",
    "sg:postcode":"91401",
    "sg:province":"CA",
    "sg:tags":[
        "chemical",
        "preparation",
        "industrial",
        "mfg"
    ],
    "wof:name":"Fujita Richard & Assoc",
    "wof:placetype":"venue"
},
  "geometry": {"coordinates":[-118.431168,34.174828],"type":"Point"}
}