{
  "type": "Feature",
  "properties": {
    "iso:country":"US",
    "sg:address":"720 A St",
    "sg:city":"Hayward",
    "sg:classifiers":[
        {
            "category":"Shopping",
            "subcategory":"Beauty & Cosmetics",
            "type":"Retail Goods"
        }
    ],
    "sg:phone":"+1 510 727 9181",
    "sg:postcode":"94541",
    "sg:province":"CA",
    "sg:tags":[
        "supply"
    ],
    "wof:name":"Hollywood Hair",
    "wof:placetype":"venue"
},
  "geometry": {"coordinates":[-122.08699799999999,37.671902],"type":"Point"}
}