{
  "type": "Feature",
  "properties": {
    "addr:full":"3282 N Sepulveda Blvd Manhattan Beach CA 90266",
    "addr:housenumber":"3282",
    "addr:postcode":"90266",
    "addr:street":"N Sepulveda Blvd",
    "iso:country":"US",
    "sg:address":"3282 N Sepulveda Blvd",
    "sg:city":"Manhattan Beach",
    "sg:classifiers":[
        {
            "category":"Restaurant",
            "type":"Food & Drink"
        }
    ],
    "sg:phone":"+1 310 546 7284",
    "sg:postcode":"90266",
    "sg:province":"CA",
    "sg:tags":[
        "fusion",
        "asian",
        "chinese"
    ],
    "sg:website":"www.chinagrillbistro.com",
    "wof:name":"China Grill",
    "wof:placetype":"venue"
},
  "geometry": {"coordinates":[-118.396004,33.898701],"type":"Point"}
}