{
  "type": "Feature",
  "properties": {
    "iso:country":"US",
    "sg:address":"1920 Main St",
    "sg:city":"Irvine",
    "sg:classifiers":[
        {
            "category":"Professional",
            "subcategory":"Lawyer & Legal Services",
            "type":"Services"
        }
    ],
    "sg:phone":"+1 949 851 9090",
    "sg:postcode":"92614",
    "sg:province":"CA",
    "sg:tags":[
        "attorney"
    ],
    "wof:name":"James M Trush Law Office",
    "wof:placetype":"venue"
},
  "geometry": {"coordinates":[-117.85715,33.685933],"type":"Point"}
}