{
  "type": "Feature",
  "properties": {
    "addr:full":"95 Linden St Oakland CA 94607",
    "addr:housenumber":"95",
    "addr:postcode":"94607",
    "addr:street":"Linden St",
    "iso:country":"US",
    "sg:address":"95 Linden St",
    "sg:city":"Oakland",
    "sg:classifiers":[
        {
            "category":"Professional",
            "type":"Services"
        }
    ],
    "sg:phone":"+1 510 496 6008",
    "sg:postcode":"94607",
    "sg:province":"CA",
    "sg:website":"www.sunsfreesolar.com",
    "wof:name":"Sun's Free Solar",
    "wof:placetype":"venue"
},
  "geometry": {"coordinates":[-122.28748,37.799431],"type":"Point"}
}