{
  "type": "Feature",
  "properties": {
    "iso:country":"US",
    "sg:address":"204 W 4th St",
    "sg:city":"Alturas",
    "sg:classifiers":[
        {
            "category":"Local Transit",
            "type":"Transportation"
        }
    ],
    "sg:phone":"+1 530 233 3883",
    "sg:postcode":"96101",
    "sg:province":"CA",
    "wof:name":"Sage Stage Bus",
    "wof:placetype":"venue"
},
  "geometry": {"coordinates":[-120.543539,41.487417],"type":"Point"}
}