{
  "type": "Feature",
  "properties": {
    "addr:full":"10 Ross Aly San Francisco CA 94108",
    "addr:housenumber":"10",
    "addr:postcode":"94108",
    "addr:street":"Ross Aly",
    "iso:country":"US",
    "sg:address":"10 Ross Aly",
    "sg:city":"San Francisco",
    "sg:classifiers":[
        {
            "category":"Organizations",
            "subcategory":"Religious Organization",
            "type":"Services"
        }
    ],
    "sg:phone":"+1 415 981 5135",
    "sg:postcode":"94108",
    "sg:province":"CA",
    "wof:name":"Chinese Christian Mission INC",
    "wof:placetype":"venue"
},
  "geometry": {"coordinates":[-122.407236,37.795262],"type":"Point"}
}