{
  "type": "Feature",
  "properties": {
    "iso:country":"US",
    "sg:address":"1223 Wall Street",
    "sg:city":"Los Angeles",
    "sg:classifiers":[
        {
            "category":"Shopping",
            "subcategory":"Clothing, Apparel, & Fashions",
            "type":"Retail Goods"
        }
    ],
    "sg:phone":"+1 213 749 7311",
    "sg:postcode":"90015",
    "sg:province":"CA",
    "sg:tags":[
        "children's",
        "clothing"
    ],
    "wof:name":"Toby Kids",
    "wof:placetype":"venue"
},
  "geometry": {"coordinates":[-118.255691,34.03436],"type":"Point"}
}