{
  "type": "Feature",
  "properties": {
    "iso:country":"US",
    "sg:address":"2411 Old Crow Canyon Rd",
    "sg:city":"San Ramon",
    "sg:classifiers":[
        {
            "category":"Real Estate",
            "subcategory":"Real Estate Agent",
            "type":"Services"
        }
    ],
    "sg:phone":"+1 925 820 6629",
    "sg:postcode":"94583",
    "sg:province":"CA",
    "sg:website":"www.hgenebrown.com",
    "wof:name":"Realty World Diablo Homes",
    "wof:placetype":"venue"
},
  "geometry": {"coordinates":[-121.979589,37.779215],"type":"Point"}
}