{
  "type": "Feature",
  "properties": {
    "addr:full":"303 Market St Ste 525 San Diego CA 92101",
    "addr:housenumber":"303",
    "addr:postcode":"92101",
    "addr:street":"Market St Ste 525",
    "iso:country":"US",
    "sg:address":"303 Market St Ste 525",
    "sg:city":"San Diego",
    "sg:classifiers":[
        {
            "category":"Real Estate",
            "subcategory":"Real Estate Services",
            "type":"Services"
        },
        {
            "category":"Professional",
            "type":"Services"
        }
    ],
    "sg:phone":"+1 619 546 6165",
    "sg:postcode":"92101",
    "sg:province":"CA",
    "sg:website":"www.sterling-sd.com",
    "wof:name":"Sterling Land Surveying Inc",
    "wof:placetype":"venue"
},
  "geometry": {"coordinates":[-117.16165100000001,32.711199],"type":"Point"}
}