{
  "type": "Feature",
  "properties": {
    "addr:full":"11175 183rd St Cerritos CA 90703",
    "addr:housenumber":"11175",
    "addr:postcode":"ca 90703",
    "addr:street":"183Rd St",
    "iso:country":"US",
    "sg:address":"11175 183rd St",
    "sg:city":"Cerritos",
    "sg:classifiers":[
        {
            "category":"Home & Garden",
            "subcategory":"Furniture",
            "type":"Retail Goods"
        }
    ],
    "sg:phone":"+1 562 860 7744",
    "sg:postcode":"90703",
    "sg:province":"CA",
    "sg:tags":[
        "store"
    ],
    "sg:website":"www.la-z-boy.com/",
    "wof:name":"La-Z-Boy Furniture Galleries",
    "wof:placetype":"venue"
},
  "geometry": {"coordinates":[-118.095297,33.865728],"type":"Point"}
}