{
  "type": "Feature",
  "properties": {
    "iso:country":"US",
    "sg:address":"155 Balboa St",
    "sg:city":"San Marcos",
    "sg:classifiers":[
        {
            "category":"Professional",
            "type":"Services"
        }
    ],
    "sg:phone":"+1 760 752 9393",
    "sg:postcode":"92069",
    "sg:province":"CA",
    "sg:tags":[
        "establishment"
    ],
    "wof:name":"Masters Mechiancal Inc",
    "wof:placetype":"venue"
},
  "geometry": {"coordinates":[-117.192219,33.148828],"type":"Point"}
}