{
  "type": "Feature",
  "properties": {
    "addr:full":"8704 N Bank Dr Ventura CA 93004",
    "addr:housenumber":"8704",
    "addr:postcode":"93004",
    "addr:street":"N Bank Dr",
    "iso:country":"US",
    "sg:address":"8704 N Bank Dr",
    "sg:city":"Ventura",
    "sg:classifiers":[
        {
            "category":"Personal",
            "type":"Services"
        }
    ],
    "sg:phone":"+1 805 647 6808",
    "sg:postcode":"93004",
    "sg:province":"CA",
    "sg:tags":[
        "wedding",
        "chapel"
    ],
    "wof:name":"A Day To Remember Weddings",
    "wof:placetype":"venue"
},
  "geometry": {"coordinates":[-119.172691,34.264522],"type":"Point"}
}