{
  "type": "Feature",
  "properties": {
    "iso:country":"US",
    "sg:address":"8703 La Tijera Blvd Ste 202",
    "sg:city":"Los Angeles",
    "sg:classifiers":[
        {
            "category":"Professional",
            "subcategory":"Lawyer & Legal Services",
            "type":"Services"
        }
    ],
    "sg:phone":"+1 310 670 6071",
    "sg:postcode":"90045",
    "sg:province":"CA",
    "wof:name":"Law Offices of Kathleen L Jernigan",
    "wof:placetype":"venue"
},
  "geometry": {"coordinates":[-118.39331,33.958197],"type":"Point"}
}