{
  "type": "Feature",
  "properties": {
    "addr:full":"6135 Pedernal Ave Goleta CA 93117",
    "addr:postcode":"6135;93117",
    "addr:street":"Pedernal Ave",
    "iso:country":"US",
    "sg:address":"6135 Pedernal Ave",
    "sg:city":"Goleta",
    "sg:classifiers":[
        {
            "category":"Utilities",
            "type":"Services"
        }
    ],
    "sg:phone":"+1 805 683 0993",
    "sg:postcode":"93117",
    "sg:province":"CA",
    "sg:tags":[
        "sweeping"
    ],
    "wof:name":"A-1 Commercial Sweeping",
    "wof:placetype":"venue"
},
  "geometry": {"coordinates":[-119.83644,34.443118],"type":"Point"}
}