{
  "type": "Feature",
  "properties": {
    "addr:full":"308 Harbor Dr Sausalito CA 94965",
    "addr:housenumber":"308",
    "addr:postcode":"94965",
    "addr:street":"Harbor Dr",
    "iso:country":"US",
    "sg:address":"308 Harbor Dr",
    "sg:city":"Sausalito",
    "sg:classifiers":[
        {
            "category":"Autos & Motor Vehicles",
            "subcategory":"Boat Sales",
            "type":"Retail Goods"
        }
    ],
    "sg:phone":"+1 415 331 0533",
    "sg:postcode":"94965",
    "sg:province":"CA",
    "sg:tags":[
        "dealer",
        "sales"
    ],
    "wof:name":"Oceanic Yacht Sales Inc",
    "wof:placetype":"venue"
},
  "geometry": {"coordinates":[-122.50000300000001,37.867403],"type":"Point"}
}