{
  "type": "Feature",
  "properties": {
    "addr:full":"1324 W Rosecrans Ave Gardena CA 90247",
    "addr:housenumber":"1324",
    "addr:postcode":"90247",
    "addr:street":"W Rosecrans Ave",
    "iso:country":"US",
    "sg:address":"1324 W Rosecrans Ave",
    "sg:city":"Gardena",
    "sg:classifiers":[
        {
            "category":"Professional",
            "subcategory":"Computer Services",
            "type":"Services"
        }
    ],
    "sg:phone":"+1 310 527 5522",
    "sg:postcode":"90247",
    "sg:province":"CA",
    "sg:tags":[
        "stereo",
        "installation"
    ],
    "sg:website":"www.alphacarstereoalarm.com",
    "wof:name":"Alpha Electronics",
    "wof:placetype":"venue"
},
  "geometry": {"coordinates":[-118.299863,33.901889],"type":"Point"}
}