{
  "type": "Feature",
  "properties": {
    "addr:full":"1 Post St San Francisco CA 94104",
    "addr:housenumber":"1",
    "addr:postcode":"94104",
    "addr:street":"Post St",
    "iso:country":"US",
    "sg:address":"1 Post St",
    "sg:city":"San Francisco",
    "sg:classifiers":[
        {
            "category":"Professional",
            "subcategory":"Research",
            "type":"Services"
        }
    ],
    "sg:phone":"+1 415 362 7500",
    "sg:postcode":"94104",
    "sg:province":"CA",
    "sg:tags":[
        "market",
        "analysis"
    ],
    "wof:name":"Mediadev Corp",
    "wof:placetype":"venue"
},
  "geometry": {"coordinates":[-122.402632,37.789023],"type":"Point"}
}