{
  "type": "Feature",
  "properties": {
    "addr:full":"4233 W Sierra Madre Ave Fresno CA 93722",
    "addr:housenumber":"4233",
    "addr:postcode":"93722",
    "addr:street":"W Sierra Madre Ave",
    "iso:country":"US",
    "sg:address":"4233 W Sierra Madre Ave",
    "sg:city":"Fresno",
    "sg:classifiers":[
        {
            "category":"Food & Beverages",
            "subcategory":"Specialty",
            "type":"Retail Goods"
        }
    ],
    "sg:phone":"+1 559 277 9644",
    "sg:postcode":"93722",
    "sg:province":"CA",
    "sg:tags":[
        "water",
        "bulk",
        "company"
    ],
    "wof:name":"Monterey Water Co",
    "wof:placetype":"venue"
},
  "geometry": {"coordinates":[-119.867028,36.806707],"type":"Point"}
}