{
  "type": "Feature",
  "properties": {
    "iso:country":"US",
    "sg:address":"1324 Court St",
    "sg:city":"Redding",
    "sg:classifiers":[
        {
            "category":"Sports & Exercise",
            "subcategory":"Gym",
            "type":"Entertainment"
        }
    ],
    "sg:phone":"+1 530 246 7181",
    "sg:postcode":"96001",
    "sg:province":"CA",
    "sg:tags":[
        "personal",
        "trainer"
    ],
    "wof:name":"Pilates Training",
    "wof:placetype":"venue"
},
  "geometry": {"coordinates":[-122.396315,40.584359],"type":"Point"}
}