{
  "type": "Feature",
  "properties": {
    "iso:country":"US",
    "sg:address":"52 Alvarado Rd",
    "sg:city":"Berkeley",
    "sg:classifiers":[
        {
            "category":"Professional",
            "subcategory":"Business Services",
            "type":"Services"
        }
    ],
    "sg:phone":"+1 510 486 1957",
    "sg:postcode":"94705",
    "sg:province":"CA",
    "sg:tags":[
        "interior",
        "consultant",
        "design",
        "decorator"
    ],
    "wof:name":"Aging Gracefully",
    "wof:placetype":"venue"
},
  "geometry": {"coordinates":[-122.240816,37.85789],"type":"Point"}
}