{
  "type": "Feature",
  "properties": {
    "addr:full":"359 Park Marina Cir Redding CA 96001",
    "addr:housenumber":"359",
    "addr:postcode":"96001",
    "addr:street":"Park Marina Cir",
    "iso:country":"US",
    "sg:address":"359 Park Marina Cir",
    "sg:city":"Redding",
    "sg:classifiers":[
        {
            "category":"Cinema",
            "subcategory":"Movie Theater",
            "type":"Entertainment"
        }
    ],
    "sg:phone":"+1 530 243 7202",
    "sg:postcode":"96001",
    "sg:province":"CA",
    "wof:name":"Movies 8",
    "wof:placetype":"venue"
},
  "geometry": {"coordinates":[-122.372446,40.576332],"type":"Point"}
}