{
  "type": "Feature",
  "properties": {
    "addr:full":"2355 India St San Diego CA 92101",
    "addr:housenumber":"2355",
    "addr:postcode":"92101",
    "addr:street":"India St",
    "iso:country":"US",
    "sg:address":"2355 India St",
    "sg:city":"San Diego",
    "sg:classifiers":[
        {
            "category":"Retail",
            "subcategory":"Auto Repair",
            "type":"Services"
        }
    ],
    "sg:phone":"+1 619 238 1161",
    "sg:postcode":"92101",
    "sg:province":"CA",
    "sg:tags":[
        "repairing",
        "automobile"
    ],
    "wof:name":"Centre City Automotive",
    "wof:placetype":"venue"
},
  "geometry": {"coordinates":[-117.170433,32.728805],"type":"Point"}
}