{
  "type": "Feature",
  "properties": {
    "addr:full":"330 N el Cerrito Dr Brawley CA 92227",
    "addr:housenumber":"330",
    "addr:postcode":"92227",
    "addr:street":"N El Cerrito Dr",
    "iso:country":"US",
    "sg:address":"330 N el Cerrito Dr",
    "sg:city":"Brawley",
    "sg:classifiers":[
        {
            "category":"Freight",
            "type":"Transportation"
        }
    ],
    "sg:phone":"+1 760 351 1427",
    "sg:postcode":"92227",
    "sg:province":"CA",
    "sg:tags":[
        "operator",
        "local",
        "trucking"
    ],
    "wof:name":"Ayala Trucking",
    "wof:placetype":"venue"
},
  "geometry": {"coordinates":[-115.545806,32.983212],"type":"Point"}
}