{
  "type": "Feature",
  "properties": {
    "addr:full":"740 M St Rio Linda CA 95673",
    "addr:housenumber":"740",
    "addr:postcode":"95673",
    "addr:street":"M St",
    "iso:country":"US",
    "sg:address":"740 M St",
    "sg:city":"Rio Linda",
    "sg:classifiers":[
        {
            "category":"Banks & Credit Unions",
            "subcategory":"Bank",
            "type":"Services"
        }
    ],
    "sg:phone":"+1 916 991 8121",
    "sg:postcode":"95673",
    "sg:province":"CA",
    "sg:tags":[
        "loan"
    ],
    "wof:name":"California Loan Ctr",
    "wof:placetype":"venue"
},
  "geometry": {"coordinates":[-121.447799,38.691003],"type":"Point"}
}