{
  "type": "Feature",
  "properties": {
    "iso:country":"US",
    "sg:address":"11049 Vernon Ave",
    "sg:city":"Ontario",
    "sg:classifiers":[
        {
            "category":"Building & Trades",
            "subcategory":"Pest Control",
            "type":"Services"
        }
    ],
    "sg:phone":"+1 909 628 4172",
    "sg:postcode":"91762",
    "sg:province":"CA",
    "wof:name":"J T Devries Pest Control",
    "wof:placetype":"venue"
},
  "geometry": {"coordinates":[-117.68499300000001,34.052556],"type":"Point"}
}