{
  "type": "Feature",
  "properties": {
    "addr:full":"4050 Phelan Rd Phelan CA 92371",
    "addr:housenumber":"4050",
    "addr:postcode":"92371",
    "addr:street":"Phelan Rd",
    "iso:country":"US",
    "sg:address":"4050 Phelan Rd",
    "sg:city":"Phelan",
    "sg:classifiers":[
        {
            "category":"Shopping",
            "subcategory":"Discount & Variety Stores",
            "type":"Retail Goods"
        }
    ],
    "sg:phone":"+1 760 868 6191",
    "sg:postcode":"92371",
    "sg:province":"CA",
    "sg:tags":[
        "merchandise",
        "general"
    ],
    "wof:name":"98 Cent Store",
    "wof:placetype":"venue"
},
  "geometry": {"coordinates":[-117.573725,34.426403],"type":"Point"}
}