{
  "type": "Feature",
  "properties": {
    "addr:full":"838 Alejandro Way Arroyo Grande CA 93420",
    "addr:housenumber":"838",
    "addr:postcode":"93420",
    "addr:street":"Alejandro Way",
    "iso:country":"US",
    "sg:address":"838 Alejandro Way",
    "sg:city":"Arroyo Grande",
    "sg:classifiers":[
        {
            "category":"Home & Garden",
            "subcategory":"Household Appliances",
            "type":"Retail Goods"
        }
    ],
    "sg:phone":"+1 805 925 2143",
    "sg:postcode":"93420",
    "sg:province":"CA",
    "wof:name":"MRH Appliance Repair",
    "wof:placetype":"venue"
},
  "geometry": {"coordinates":[-120.57481199999999,35.042459],"type":"Point"}
}