{
  "type": "Feature",
  "properties": {
    "addr:full":"2801 Pullman St Santa Ana CA 92705",
    "addr:housenumber":"2801",
    "addr:postcode":"92705",
    "addr:street":"Pullman St",
    "iso:country":"US",
    "sg:address":"2801 Pullman St",
    "sg:city":"Santa Ana",
    "sg:classifiers":[
        {
            "category":"Manufacturing",
            "subcategory":"Textiles",
            "type":"Manufacturing & Wholesale Goods"
        }
    ],
    "sg:phone":"+1 949 261 7181",
    "sg:postcode":"92705",
    "sg:province":"CA",
    "sg:tags":[
        "rug",
        "carpet"
    ],
    "sg:website":"www.fabrica.com",
    "wof:name":"Fabrica International",
    "wof:placetype":"venue"
},
  "geometry": {"coordinates":[-117.8484,33.708429],"type":"Point"}
}