{
  "type": "Feature",
  "properties": {
    "addr:full":"3415 S Sepulveda Blvd Los Angeles CA 90034",
    "addr:housenumber":"3415",
    "addr:postcode":"90034",
    "addr:street":"S Sepulveda Blvd",
    "iso:country":"US",
    "sg:address":"3415 S Sepulveda Blvd",
    "sg:city":"Los Angeles",
    "sg:classifiers":[
        {
            "category":"Professional",
            "subcategory":"Management & Consulting",
            "type":"Services"
        }
    ],
    "sg:phone":"+1 310 390 4099",
    "sg:postcode":"90034",
    "sg:province":"CA",
    "sg:tags":[
        "technology",
        "system",
        "business"
    ],
    "wof:name":"Medaphis",
    "wof:placetype":"venue"
},
  "geometry": {"coordinates":[-118.42247399999999,34.0195],"type":"Point"}
}