{
  "type": "Feature",
  "properties": {
    "iso:country":"US",
    "sg:address":"544 Bryant St",
    "sg:city":"San Francisco",
    "sg:classifiers":[
        {
            "category":"Manufacturing",
            "subcategory":"Printing",
            "type":"Manufacturing & Wholesale Goods"
        }
    ],
    "sg:phone":"+1 415 896 2026",
    "sg:postcode":"94107",
    "sg:province":"CA",
    "sg:tags":[
        "printer"
    ],
    "wof:name":"Adprint",
    "wof:placetype":"venue"
},
  "geometry": {"coordinates":[-122.39774199999999,37.779991],"type":"Point"}
}