{
  "type": "Feature",
  "properties": {
    "iso:country":"US",
    "sg:address":"1214 W 254th St",
    "sg:city":"Harbor City",
    "sg:classifiers":[
        {
            "category":"Wholesale",
            "subcategory":"Auto Parts",
            "type":"Manufacturing & Wholesale Goods"
        }
    ],
    "sg:phone":"+1 310 257 1723",
    "sg:postcode":"90710",
    "sg:province":"CA",
    "sg:tags":[
        "used"
    ],
    "wof:name":"A P B & Associates",
    "wof:placetype":"venue"
},
  "geometry": {"coordinates":[-118.298728,33.793692],"type":"Point"}
}