{
  "type": "Feature",
  "properties": {
    "addr:full":"2700 Monterey Hwy San Jose CA 95111",
    "addr:housenumber":"2700",
    "addr:postcode":"95111",
    "addr:street":"Monterey Hwy",
    "iso:country":"US",
    "sg:address":"2700 Monterey Hwy",
    "sg:city":"San Jose",
    "sg:classifiers":[
        {
            "category":"Professional",
            "type":"Services"
        }
    ],
    "sg:phone":"+1 408 972 8291",
    "sg:postcode":"95111",
    "sg:province":"CA",
    "wof:name":"Juan Quintero",
    "wof:placetype":"venue"
},
  "geometry": {"coordinates":[-121.851833,37.294056],"type":"Point"}
}