{
  "type": "Feature",
  "properties": {
    "addr:full":"753 Folger Ave Berkeley CA 94710",
    "addr:housenumber":"753",
    "addr:postcode":"94710",
    "addr:street":"Folger Ave",
    "iso:country":"US",
    "sg:address":"753 Folger Ave",
    "sg:city":"Berkeley",
    "sg:classifiers":[
        {
            "category":"Retail",
            "subcategory":"Auto Repair",
            "type":"Services"
        }
    ],
    "sg:phone":"+1 510 843 9118",
    "sg:postcode":"94710",
    "sg:province":"CA",
    "sg:tags":[
        "automobile",
        "electric"
    ],
    "sg:website":"www.unitechsubaru.com",
    "wof:name":"Unitech",
    "wof:placetype":"venue"
},
  "geometry": {"coordinates":[-122.292726,37.849979],"type":"Point"}
}