{
  "type": "Feature",
  "properties": {
    "addr:full":"90 New Montgomery St San Francisco CA 94105",
    "addr:housenumber":"90",
    "addr:postcode":"94105",
    "addr:street":"New Montgomery St",
    "iso:country":"US",
    "sg:address":"90 New Montgomery St",
    "sg:city":"San Francisco",
    "sg:classifiers":[
        {
            "category":"Shopping",
            "subcategory":"Computers & Home Electronics",
            "type":"Retail Goods"
        }
    ],
    "sg:phone":"+1 415 543 1515",
    "sg:postcode":"94105",
    "sg:province":"CA",
    "sg:tags":[
        "software"
    ],
    "sg:website":"www.forecross.com",
    "wof:name":"Forecross Corp",
    "wof:placetype":"venue"
},
  "geometry": {"coordinates":[-122.400637,37.787481],"type":"Point"}
}