{
  "type": "Feature",
  "properties": {
    "addr:full":"San Jose Ave & Ocean Ave San Francisco CA 94112",
    "addr:postcode":"94112",
    "addr:street":"San Jose Ave & Ocean Ave",
    "iso:country":"US",
    "sg:address":"San Jose Ave & Ocean Ave",
    "sg:city":"San Francisco",
    "sg:classifiers":[
        {
            "category":"Park",
            "type":"Public Place"
        },
        {
            "category":"Recreation",
            "subcategory":"Playground",
            "type":"Entertainment"
        }
    ],
    "sg:postcode":"94112",
    "sg:province":"CA",
    "wof:name":"Balboa Park",
    "wof:placetype":"venue"
},
  "geometry": {"coordinates":[-122.444795,37.722901],"type":"Point"}
}