{
  "type": "Feature",
  "properties": {
    "addr:full":"3095 King Edward Rd West Sacramento CA 95691",
    "addr:housenumber":"3095",
    "addr:postcode":"95691",
    "addr:street":"King Edward Rd",
    "iso:country":"US",
    "sg:address":"3095 King Edward Rd",
    "sg:city":"West Sacramento",
    "sg:classifiers":[
        {
            "category":"Building & Trades",
            "subcategory":"Electrical",
            "type":"Services"
        }
    ],
    "sg:phone":"+1 916 371 8570",
    "sg:postcode":"95691",
    "sg:province":"CA",
    "sg:tags":[
        "electrician"
    ],
    "sg:website":"www.johnparkselectric.com",
    "wof:name":"Parks Electric",
    "wof:placetype":"venue"
},
  "geometry": {"coordinates":[-121.56121899999999,38.538417],"type":"Point"}
}