{
  "type": "Feature",
  "properties": {
    "iso:country":"US",
    "sg:address":"3400 Torrance Blvd",
    "sg:city":"Torrance",
    "sg:classifiers":[
        {
            "category":"Professional",
            "subcategory":"Advertising",
            "type":"Services"
        }
    ],
    "sg:phone":"+1 310 793 5100",
    "sg:postcode":"90503",
    "sg:province":"CA",
    "sg:website":"www.pennysaverusa.com",
    "wof:name":"Pennysaver",
    "wof:placetype":"venue"
},
  "geometry": {"coordinates":[-118.344965,33.837525],"type":"Point"}
}