{
  "type": "Feature",
  "properties": {
    "iso:country":"US",
    "sg:address":"838 Grant Ave",
    "sg:city":"San Francisco",
    "sg:classifiers":[
        {
            "category":"Shopping",
            "type":"Retail Goods"
        }
    ],
    "sg:phone":"+1 415 837 1509",
    "sg:postcode":"94108",
    "sg:province":"CA",
    "sg:tags":[
        "art",
        "gallery",
        "dealer"
    ],
    "wof:name":"China Trade Ctr Art Gallery",
    "wof:placetype":"venue"
},
  "geometry": {"coordinates":[-122.406349,37.794814],"type":"Point"}
}