{
  "type": "Feature",
  "properties": {
    "addr:full":"1552 E Ocean Blvd Newport Beach CA 92661",
    "addr:housenumber":"1552",
    "addr:postcode":"92661",
    "addr:street":"E Ocean Blvd",
    "iso:country":"US",
    "sg:address":"1552 E Ocean Blvd",
    "sg:city":"Newport Beach",
    "sg:classifiers":[
        {
            "category":"Manufacturing",
            "subcategory":"Electronics",
            "type":"Manufacturing & Wholesale Goods"
        }
    ],
    "sg:phone":"+1 949 922 7865",
    "sg:postcode":"92661",
    "sg:province":"CA",
    "sg:tags":[
        "prerecorded",
        "mfg"
    ],
    "wof:name":"Prime Directive Productions",
    "wof:placetype":"venue"
},
  "geometry": {"coordinates":[-117.889895,33.597979],"type":"Point"}
}