{
  "type": "Feature",
  "properties": {
    "iso:country":"US",
    "sg:address":"160 Evan Ct",
    "sg:city":"Freedom",
    "sg:classifiers":[
        {
            "category":"Building & Trades",
            "subcategory":"Construction",
            "type":"Services"
        }
    ],
    "sg:phone":"+1 831 840 2538",
    "sg:postcode":"95019",
    "sg:province":"CA",
    "sg:tags":[
        "woodworker"
    ],
    "wof:name":"Stoll Development",
    "wof:placetype":"venue"
},
  "geometry": {"coordinates":[-121.78273799999999,36.932486],"type":"Point"}
}