{
  "type": "Feature",
  "properties": {
    "iso:country":"US",
    "sg:address":"2249 W Rosecrans Ave",
    "sg:city":"Gardena",
    "sg:classifiers":[
        {
            "category":"Banks & Credit Unions",
            "subcategory":"Bank",
            "type":"Services"
        }
    ],
    "sg:phone":"+1 310 532 3800",
    "sg:postcode":"90249",
    "sg:province":"CA",
    "sg:tags":[
        "loan"
    ],
    "wof:name":"Cash America",
    "wof:placetype":"venue"
},
  "geometry": {"coordinates":[-118.320077,33.902008],"type":"Point"}
}