{
  "type": "Feature",
  "properties": {
    "addr:full":"1429 E Albion Ln Orange CA 92866",
    "addr:housenumber":"1429",
    "addr:postcode":"92866",
    "addr:street":"E Albion Ln",
    "iso:country":"US",
    "sg:address":"1429 E Albion Ln",
    "sg:city":"Orange",
    "sg:classifiers":[
        {
            "category":"Professional",
            "subcategory":"Business Services",
            "type":"Services"
        }
    ],
    "sg:phone":"+1 714 997 5630",
    "sg:postcode":"92866",
    "sg:province":"CA",
    "sg:tags":[
        "appraiser"
    ],
    "wof:name":"Appraisals By Carson",
    "wof:placetype":"venue"
},
  "geometry": {"coordinates":[-117.83761800000001,33.774808],"type":"Point"}
}