{
  "type": "Feature",
  "properties": {
    "iso:country":"US",
    "sg:address":"7711 Laguna Blvd",
    "sg:city":"Elk Grove",
    "sg:classifiers":[
        {
            "category":"Retail",
            "subcategory":"Laundry & Dry Cleaning",
            "type":"Services"
        }
    ],
    "sg:phone":"+1 916 684 9617",
    "sg:postcode":"95758",
    "sg:province":"CA",
    "sg:tags":[
        "cleaners"
    ],
    "wof:name":"Paul's Cleaners",
    "wof:placetype":"venue"
},
  "geometry": {"coordinates":[-121.403803,38.422058],"type":"Point"}
}