{
  "type": "Feature",
  "properties": {
    "addr:full":"1234 Fortna Ave Woodland CA 95776",
    "addr:housenumber":"1234",
    "addr:postcode":"95776",
    "addr:street":"Fortna Ave",
    "iso:country":"US",
    "sg:address":"1234 Fortna Ave",
    "sg:city":"Woodland",
    "sg:classifiers":[
        {
            "category":"Building & Trades",
            "subcategory":"Pest Control",
            "type":"Services"
        }
    ],
    "sg:phone":"+1 530 668 3400",
    "sg:postcode":"95776",
    "sg:province":"CA",
    "wof:name":"Sacramento Yolo Mosquito",
    "wof:placetype":"venue"
},
  "geometry": {"coordinates":[-121.76215999999999,38.689942],"type":"Point"}
}