{
  "type": "Feature",
  "properties": {
    "iso:country":"US",
    "sg:address":"7610 Hanford Ave",
    "sg:city":"Yucca Valley",
    "sg:classifiers":[
        {
            "category":"Building & Trades",
            "subcategory":"Construction",
            "type":"Services"
        }
    ],
    "sg:phone":"+1 760 365 6339",
    "sg:postcode":"92284",
    "sg:province":"CA",
    "sg:tags":[
        "contractor"
    ],
    "sg:website":"www.sunbelt-construction.com",
    "wof:name":"Sunbelt Construction",
    "wof:placetype":"venue"
},
  "geometry": {"coordinates":[-116.39308,34.114176],"type":"Point"}
}