{
  "type": "Feature",
  "properties": {
    "addr:full":"506 Red Hill Ave San Anselmo CA 94960",
    "addr:housenumber":"506",
    "addr:postcode":"94960",
    "addr:street":"Red Hill Ave",
    "iso:country":"US",
    "sg:address":"506 Red Hill Ave",
    "sg:city":"San Anselmo",
    "sg:classifiers":[
        {
            "category":"Shopping",
            "subcategory":"Computers & Home Electronics",
            "type":"Retail Goods"
        }
    ],
    "sg:phone":"+1 415 485 0630",
    "sg:postcode":"94960",
    "sg:province":"CA",
    "sg:tags":[
        "audio"
    ],
    "sg:website":"www.museumtools.com",
    "wof:name":"Museum Tools",
    "wof:placetype":"venue"
},
  "geometry": {"coordinates":[-122.559651,37.976654],"type":"Point"}
}