{
  "type": "Feature",
  "properties": {
    "iso:country":"US",
    "sg:address":"222 Willow St",
    "sg:city":"San Jose",
    "sg:classifiers":[
        {
            "category":"Insurance",
            "subcategory":"Insurance Agent",
            "type":"Services"
        }
    ],
    "sg:phone":"+1 408 993 1055",
    "sg:postcode":"95110",
    "sg:province":"CA",
    "wof:name":"Ruben Reyna Insurance Services",
    "wof:placetype":"venue"
},
  "geometry": {"coordinates":[-121.882758,37.318553],"type":"Point"}
}