{
  "type": "Feature",
  "properties": {
    "addr:full":"1667 Royal Ave Simi Valley CA 93065",
    "addr:housenumber":"1667",
    "addr:postcode":"93065",
    "addr:street":"Royal Ave",
    "iso:country":"US",
    "sg:address":"1667 Royal Ave",
    "sg:city":"Simi Valley",
    "sg:classifiers":[
        {
            "category":"Wholesale",
            "subcategory":"Computers",
            "type":"Manufacturing & Wholesale Goods"
        }
    ],
    "sg:phone":"+1 805 527 7362",
    "sg:postcode":"93065",
    "sg:province":"CA",
    "sg:tags":[
        "software"
    ],
    "sg:website":"www.dataconn.com",
    "wof:name":"Data Connections",
    "wof:placetype":"venue"
},
  "geometry": {"coordinates":[-118.76660699999999,34.264546],"type":"Point"}
}