{
  "type": "Feature",
  "properties": {
    "addr:full":"11435 Simmerhorn Rd Galt CA 95632",
    "addr:housenumber":"11435",
    "addr:postcode":"95632",
    "addr:street":"Simmerhorn Rd",
    "iso:country":"US",
    "sg:address":"11435 Simmerhorn Rd",
    "sg:city":"Galt",
    "sg:classifiers":[
        {
            "category":"Retail",
            "subcategory":"Animal Services",
            "type":"Services"
        }
    ],
    "sg:phone":"+1 209 745 7297",
    "sg:postcode":"95632",
    "sg:province":"CA",
    "sg:tags":[
        "shelter"
    ],
    "sg:website":"www.pawsweb.org",
    "wof:name":"Paws",
    "wof:placetype":"venue"
},
  "geometry": {"coordinates":[-121.25957699999999,38.262641],"type":"Point"}
}