{
  "type": "Feature",
  "properties": {
    "iso:country":"US",
    "sg:address":"1540 Commerce St",
    "sg:city":"Corona",
    "sg:classifiers":[
        {
            "category":"Manufacturing",
            "subcategory":"Motor Vehicles & Parts",
            "type":"Manufacturing & Wholesale Goods"
        }
    ],
    "sg:phone":"+1 951 279 8026",
    "sg:postcode":"92880",
    "sg:province":"CA",
    "sg:tags":[
        "equipment",
        "repair",
        "truck",
        "automotive",
        "mfg"
    ],
    "wof:name":"Inland Empire Drive Line Svc",
    "wof:placetype":"venue"
},
  "geometry": {"coordinates":[-117.595716,33.885389],"type":"Point"}
}