{
  "type": "Feature",
  "properties": {
    "addr:full":"26500 Agoura Rd Ste 109 Calabasas CA 91302",
    "addr:housenumber":"26500",
    "addr:postcode":"91302",
    "addr:street":"Agoura Rd Ste 109",
    "iso:country":"US",
    "sg:address":"26500 Agoura Rd Ste 109",
    "sg:city":"Calabasas",
    "sg:classifiers":[
        {
            "category":"Professional",
            "subcategory":"Lawyer & Legal Services",
            "type":"Services"
        }
    ],
    "sg:phone":"+1 818 880 8990",
    "sg:postcode":"91302",
    "sg:province":"CA",
    "sg:tags":[
        "divorce",
        "law",
        "family"
    ],
    "wof:name":"Conviser Donald F Law Offices",
    "wof:placetype":"venue"
},
  "geometry": {"coordinates":[-118.697998,34.143799],"type":"Point"}
}