{
  "type": "Feature",
  "properties": {
    "addr:full":"Tanforan Shopping Center 1150 El Camino Real San Bruno CA 94066",
    "addr:housenumber":"1150",
    "addr:postcode":"94066",
    "addr:street":"El Camino Real",
    "iso:country":"US",
    "sg:address":"Tanforan Shopping Center 1150 El Camino Real",
    "sg:city":"San Bruno",
    "sg:classifiers":[
        {
            "category":"Brewery",
            "type":"Food & Drink"
        }
    ],
    "sg:phone":"+1 650 243 4530",
    "sg:postcode":"94066",
    "sg:province":"CA",
    "sg:website":"www.bjsrestaurants.com",
    "wof:name":"BJ's Restaurant & Brewhouse",
    "wof:placetype":"venue"
},
  "geometry": {"coordinates":[-122.418335,37.63631],"type":"Point"}
}