{
  "type": "Feature",
  "properties": {
    "addr:full":"719 N Fairfax Ave Los Angeles CA 90046",
    "addr:housenumber":"719",
    "addr:postcode":"90046",
    "addr:street":"N Fairfax Ave",
    "iso:country":"US",
    "sg:address":"719 N Fairfax Ave",
    "sg:city":"Los Angeles",
    "sg:classifiers":[
        {
            "category":"Real Estate",
            "subcategory":"Architect",
            "type":"Services"
        }
    ],
    "sg:phone":"+1 323 651 3316",
    "sg:postcode":"90046",
    "sg:province":"CA",
    "sg:website":"www.gantman.com",
    "wof:name":"Martin Gantman Studio",
    "wof:placetype":"venue"
},
  "geometry": {"coordinates":[-118.361403,34.085112],"type":"Point"}
}