{
  "type": "Feature",
  "properties": {
    "addr:full":"3069 Wiljan Ct Santa Rosa CA 95407",
    "addr:housenumber":"3069",
    "addr:postcode":"95407",
    "addr:street":"Wiljan Ct",
    "iso:country":"US",
    "sg:address":"3069 Wiljan Ct",
    "sg:city":"Santa Rosa",
    "sg:classifiers":[
        {
            "category":"Wholesale",
            "subcategory":"Machinery & Supplies",
            "type":"Manufacturing & Wholesale Goods"
        }
    ],
    "sg:phone":"+1 707 527 6096",
    "sg:postcode":"95407",
    "sg:province":"CA",
    "sg:tags":[
        "machine",
        "shop"
    ],
    "wof:name":"North Bay Cutting Tools",
    "wof:placetype":"venue"
},
  "geometry": {"coordinates":[-122.71986099999999,38.403125],"type":"Point"}
}