{
  "type": "Feature",
  "properties": {
    "iso:country":"US",
    "sg:address":"946 Notre Dame Ave",
    "sg:city":"Concord",
    "sg:classifiers":[
        {
            "category":"Building & Trades",
            "subcategory":"Construction",
            "type":"Services"
        }
    ],
    "sg:phone":"+1 925 680 7558",
    "sg:postcode":"94518",
    "sg:province":"CA",
    "sg:tags":[
        "general",
        "contractor"
    ],
    "wof:name":"J W Construction Inc",
    "wof:placetype":"venue"
},
  "geometry": {"coordinates":[-122.029859,37.949054],"type":"Point"}
}