{
  "type": "Feature",
  "properties": {
    "addr:full":"13640 Foothill Blvd Sylmar CA 91342",
    "addr:housenumber":"13640",
    "addr:postcode":"91342",
    "addr:street":"Foothill Blvd",
    "iso:country":"US",
    "sg:address":"13640 Foothill Blvd",
    "sg:city":"Sylmar",
    "sg:classifiers":[
        {
            "category":"Health Services",
            "subcategory":"Doctor",
            "type":"Services"
        }
    ],
    "sg:phone":"+1 818 364 6768",
    "sg:postcode":"91342",
    "sg:province":"CA",
    "sg:tags":[
        "dentist"
    ],
    "wof:name":"Family Dental Connection",
    "wof:placetype":"venue"
},
  "geometry": {"coordinates":[-118.43365300000001,34.309919],"type":"Point"}
}