{
  "type": "Feature",
  "properties": {
    "addr:full":"17841 Beach Boulevard Huntington Beach CA 92647",
    "addr:housenumber":"17841",
    "addr:postcode":"92647",
    "addr:street":"Beach Boulevard",
    "iso:country":"US",
    "sg:address":"17841 Beach Boulevard",
    "sg:city":"Huntington Beach",
    "sg:classifiers":[
        {
            "category":"Shopping",
            "subcategory":"Tobacco",
            "type":"Retail Goods"
        }
    ],
    "sg:phone":"+1 714 848 7179",
    "sg:postcode":"92647",
    "sg:province":"CA",
    "sg:tags":[
        "shop"
    ],
    "wof:name":"The Glass Garden",
    "wof:placetype":"venue"
},
  "geometry": {"coordinates":[-117.98915,33.703489],"type":"Point"}
}