{
  "type": "Feature",
  "properties": {
    "iso:country":"US",
    "sg:address":"2398 E Brandon Ln",
    "sg:city":"Fresno",
    "sg:classifiers":[
        {
            "category":"Shopping",
            "subcategory":"Discount & Variety Stores",
            "type":"Retail Goods"
        }
    ],
    "sg:phone":"+1 559 433 8872",
    "sg:postcode":"93720",
    "sg:province":"CA",
    "sg:tags":[
        "merchandise",
        "general"
    ],
    "wof:name":"Amandas Bow Shoppe",
    "wof:placetype":"venue"
},
  "geometry": {"coordinates":[-119.741429,36.872607],"type":"Point"}
}