{
  "type": "Feature",
  "properties": {
    "addr:full":"5720 Stoneridge Mall Rd Ste 270 Pleasanton CA 94588",
    "addr:housenumber":"5720",
    "addr:postcode":"94588",
    "addr:street":"Stoneridge Mall Rd Ste 270",
    "iso:country":"US",
    "sg:address":"5720 Stoneridge Mall Rd Ste 270",
    "sg:city":"Pleasanton",
    "sg:classifiers":[
        {
            "category":"Health Services",
            "subcategory":"Doctor",
            "type":"Services"
        }
    ],
    "sg:phone":"+1 925 737 0307",
    "sg:postcode":"94588",
    "sg:province":"CA",
    "sg:tags":[
        "medicine",
        "physician",
        "surgeon",
        "internal",
        "surgeons"
    ],
    "wof:name":"Fernandina Fay Lo Md",
    "wof:placetype":"venue"
},
  "geometry": {"coordinates":[-121.929626,37.692293],"type":"Point"}
}