{
  "type": "Feature",
  "properties": {
    "addr:full":"40205 10th St W Palmdale CA 93551",
    "addr:housenumber":"40205",
    "addr:postcode":"ca 93551",
    "addr:street":"10Th St W",
    "iso:country":"US",
    "sg:address":"40205 10th St W",
    "sg:city":"Palmdale",
    "sg:classifiers":[
        {
            "category":"Restaurant",
            "type":"Food & Drink"
        }
    ],
    "sg:phone":"+1 661 266 9625",
    "sg:postcode":"93551",
    "sg:province":"CA",
    "sg:tags":[
        "style",
        "family"
    ],
    "wof:name":"Speedy Joe's",
    "wof:placetype":"venue"
},
  "geometry": {"coordinates":[-118.147744,34.61305],"type":"Point"}
}