{
  "type": "Feature",
  "properties": {
    "iso:country":"US",
    "sg:address":"1301 Shoreway Rd Suite 425",
    "sg:city":"Belmont",
    "sg:classifiers":[
        {
            "category":"Professional",
            "subcategory":"Research",
            "type":"Services"
        }
    ],
    "sg:phone":"+1 650 632 4199",
    "sg:postcode":"94002 ",
    "sg:province":"CA",
    "sg:website":"http://www.ventusmedical.com/",
    "wof:name":"Ventus Medical",
    "wof:placetype":"venue"
},
  "geometry": {"coordinates":[-122.267577,37.527682],"type":"Point"}
}