{
  "type": "Feature",
  "properties": {
    "addr:full":"9039 E. Adams Ave. Huntington Beach CA 92646",
    "addr:housenumber":"9039",
    "addr:postcode":"92646",
    "addr:street":"E. Adams Ave.",
    "iso:country":"US",
    "sg:address":"9039 E. Adams Ave.",
    "sg:city":"Huntington Beach",
    "sg:classifiers":[
        {
            "category":"Personal",
            "type":"Services"
        }
    ],
    "sg:phone":"+1 951 741 4410",
    "sg:postcode":"92646",
    "sg:province":"CA",
    "sg:tags":[
        "planning",
        "wedding"
    ],
    "wof:name":"events by SAVVY",
    "wof:placetype":"venue"
},
  "geometry": {"coordinates":[-117.97020500000001,33.672343],"type":"Point"}
}