{
  "type": "Feature",
  "properties": {
    "iso:country":"US",
    "sg:address":"2855 Telegraph Ave Ste 400",
    "sg:city":"Berkeley",
    "sg:classifiers":[
        {
            "category":"Health Services",
            "subcategory":"Doctor",
            "type":"Services"
        }
    ],
    "sg:phone":"+1 510 841 9056",
    "sg:postcode":"94705",
    "sg:province":"CA",
    "wof:name":"Wright Institute",
    "wof:placetype":"venue"
},
  "geometry": {"coordinates":[-122.25881,37.858189],"type":"Point"}
}