{
  "type": "Feature",
  "properties": {
    "iso:country":"US",
    "sg:address":"6260 W Sunset Boulevard",
    "sg:city":"Los Angeles",
    "sg:classifiers":[
        {
            "category":"Shopping",
            "subcategory":"Florist",
            "type":"Retail Goods"
        }
    ],
    "sg:phone":"+1 323 466 4060",
    "sg:postcode":"90028",
    "sg:province":"CA",
    "wof:name":"Pete's Flowers",
    "wof:placetype":"venue"
},
  "geometry": {"coordinates":[-118.325646,34.098113],"type":"Point"}
}