{
  "type": "Feature",
  "properties": {
    "iso:country":"US",
    "sg:address":"225 Post St",
    "sg:city":"San Francisco",
    "sg:classifiers":[
        {
            "category":"Shopping",
            "subcategory":"Clothing, Apparel, & Fashions",
            "type":"Retail Goods"
        }
    ],
    "sg:phone":"+1 415 392 2200",
    "sg:postcode":"94108",
    "sg:province":"CA",
    "sg:tags":[
        "furnishing"
    ],
    "wof:name":"Burberry",
    "wof:placetype":"venue"
},
  "geometry": {"coordinates":[-122.406458,37.788473],"type":"Point"}
}