{
  "type": "Feature",
  "properties": {
    "iso:country":"US",
    "sg:address":"1107 Yerba Buena Rd",
    "sg:city":"San Jose",
    "sg:classifiers":[
        {
            "category":"Manufacturing",
            "subcategory":"Tools & Machinery",
            "type":"Manufacturing & Wholesale Goods"
        }
    ],
    "sg:phone":"+1 408 225 2836",
    "sg:postcode":"95121",
    "sg:province":"CA",
    "sg:tags":[
        "engineering"
    ],
    "wof:name":"Primrose Technology",
    "wof:placetype":"venue"
},
  "geometry": {"coordinates":[-121.814903,37.291538],"type":"Point"}
}