{
  "type": "Feature",
  "properties": {
    "addr:full":"1365 N Willow Ave Clovis CA 93619",
    "addr:housenumber":"1365",
    "addr:postcode":"93619",
    "addr:street":"N Willow Ave",
    "iso:country":"US",
    "sg:address":"1365 N Willow Ave",
    "sg:city":"Clovis",
    "sg:phone":"+1 559 299 2504",
    "sg:postcode":"93619",
    "sg:province":"CA",
    "wof:name":"Guadalajara Restaurant Inc",
    "wof:placetype":"venue"
},
  "geometry": {"coordinates":[-119.72970599999999,36.857311],"type":"Point"}
}