{
  "type": "Feature",
  "properties": {
    "addr:full":"1402 W 6th St Los Angeles CA 90017",
    "addr:housenumber":"1402",
    "addr:postcode":"90017",
    "addr:street":"W 6Th St",
    "iso:country":"US",
    "sg:address":"1402 W 6th St",
    "sg:city":"Los Angeles",
    "sg:classifiers":[
        {
            "category":"Donuts",
            "subcategory":"None",
            "type":"Food & Drink"
        }
    ],
    "sg:phone":"+1 213 483 2712",
    "sg:postcode":"90017",
    "sg:province":"CA",
    "wof:name":"Magee's Donuts",
    "wof:placetype":"venue"
},
  "geometry": {"coordinates":[-118.266998,34.0564],"type":"Point"}
}