{
  "type": "Feature",
  "properties": {
    "iso:country":"US",
    "sg:address":"31702 Hayman St",
    "sg:city":"Hayward",
    "sg:classifiers":[
        {
            "category":"Wholesale",
            "subcategory":"Chemicals & Plastics",
            "type":"Manufacturing & Wholesale Goods"
        }
    ],
    "sg:phone":"+1 510 471 5421",
    "sg:postcode":"94544",
    "sg:province":"CA",
    "sg:tags":[
        "paint",
        "material"
    ],
    "sg:website":"www.chemcentral.com",
    "wof:name":"Chemcentral-San Francisco",
    "wof:placetype":"venue"
},
  "geometry": {"coordinates":[-122.044876,37.611545],"type":"Point"}
}