{
  "type": "Feature",
  "properties": {
    "addr:full":"1850 Irving St San Francisco CA 94122",
    "addr:housenumber":"1850",
    "addr:postcode":"94122",
    "addr:street":"Irving St",
    "iso:country":"US",
    "sg:address":"1850 Irving St",
    "sg:city":"San Francisco",
    "sg:classifiers":[
        {
            "category":"Banks & Credit Unions",
            "subcategory":"Financial Services",
            "type":"Services"
        }
    ],
    "sg:phone":"+1 415 661 5353",
    "sg:postcode":"94122",
    "sg:province":"CA",
    "sg:website":"www.usbank.com",
    "wof:name":"U.S. Bank",
    "wof:placetype":"venue"
},
  "geometry": {"coordinates":[-122.477992,37.763532],"type":"Point"}
}