{
  "type": "Feature",
  "properties": {
    "iso:country":"US",
    "sg:address":"3939 San Pablo Dam Rd",
    "sg:city":"El Sobrante",
    "sg:classifiers":[
        {
            "category":"Banks & Credit Unions",
            "subcategory":"Bank",
            "type":"Services"
        }
    ],
    "sg:phone":"+1 510 649 6600",
    "sg:postcode":"94803",
    "sg:province":"CA",
    "wof:name":"Bank Of America",
    "wof:placetype":"venue"
},
  "geometry": {"coordinates":[-122.310036,37.966164],"type":"Point"}
}