{
  "type": "Feature",
  "properties": {
    "addr:full":"104 N Raymond Ave Ste A-2 Fullerton CA 92831",
    "addr:housenumber":"104",
    "addr:postcode":"92831",
    "addr:street":"N Raymond Ave Ste A-2",
    "iso:country":"US",
    "sg:address":"104 N Raymond Ave Ste A-2",
    "sg:city":"Fullerton",
    "sg:classifiers":[
        {
            "category":"Health Services",
            "subcategory":"Clinic",
            "type":"Services"
        }
    ],
    "sg:phone":"+1 714 992 1677",
    "sg:postcode":"92831",
    "sg:province":"CA",
    "sg:tags":[
        "counseling",
        "mental"
    ],
    "wof:name":"Addiction Treatment Center",
    "wof:placetype":"venue"
},
  "geometry": {"coordinates":[-117.905857,33.871204],"type":"Point"}
}