{
  "type": "Feature",
  "properties": {
    "iso:country":"US",
    "sg:address":"4236 el Cajon Blvd",
    "sg:city":"San Diego",
    "sg:classifiers":[
        {
            "category":"Health Services",
            "subcategory":"Doctor",
            "type":"Services"
        }
    ],
    "sg:phone":"+1 619 584 4015",
    "sg:postcode":"92105",
    "sg:province":"CA",
    "sg:tags":[
        "dentist"
    ],
    "wof:name":"Bao Loc DDS",
    "wof:placetype":"venue"
},
  "geometry": {"coordinates":[-117.104415,32.755216],"type":"Point"}
}