{
  "type": "Feature",
  "properties": {
    "addr:full":"611 E Cerritos Ave Anaheim CA 92805",
    "addr:housenumber":"611",
    "addr:postcode":"92805",
    "addr:street":"E Cerritos Ave",
    "iso:country":"US",
    "sg:address":"611 E Cerritos Ave",
    "sg:city":"Anaheim",
    "sg:classifiers":[
        {
            "category":"Home & Garden",
            "subcategory":"Building Materials",
            "type":"Retail Goods"
        },
        {
            "category":"Professional",
            "subcategory":"Business Services",
            "type":"Services"
        }
    ],
    "sg:phone":"+1 714 520 4100",
    "sg:postcode":"92805",
    "sg:province":"CA",
    "sg:tags":[
        "marble-natural-wholesale",
        "marble-natural",
        "manufacturer"
    ],
    "wof:name":"Import Stone",
    "wof:placetype":"venue"
},
  "geometry": {"coordinates":[-117.901111,33.810602],"type":"Point"}
}