{
  "type": "Feature",
  "properties": {
    "iso:country":"US",
    "sg:address":"701 del Norte Blvd",
    "sg:city":"Oxnard",
    "sg:classifiers":[
        {
            "category":"Wholesale",
            "subcategory":"Toys & Hobbies",
            "type":"Manufacturing & Wholesale Goods"
        }
    ],
    "sg:phone":"+1 805 983 1314",
    "sg:postcode":"93030",
    "sg:province":"CA",
    "sg:tags":[
        "wholesaler"
    ],
    "wof:name":"Prosource Wholesale Floor",
    "wof:placetype":"venue"
},
  "geometry": {"coordinates":[-119.12711899999999,34.206635],"type":"Point"}
}