{
  "type": "Feature",
  "properties": {
    "iso:country":"US",
    "sg:address":"5509 Peppertree Ln",
    "sg:city":"Bakersfield",
    "sg:classifiers":[
        {
            "category":"Professional",
            "type":"Services"
        }
    ],
    "sg:phone":"+1 661 832 8442",
    "sg:postcode":"93309",
    "sg:province":"CA",
    "sg:tags":[
        "establishment"
    ],
    "wof:name":"ABS",
    "wof:placetype":"venue"
},
  "geometry": {"coordinates":[-119.063479,35.325973],"type":"Point"}
}