{
  "type": "Feature",
  "properties": {
    "addr:full":"4765 E Bryson St Anaheim CA 92807",
    "addr:housenumber":"4765",
    "addr:postcode":"92807",
    "addr:street":"E Bryson St",
    "iso:country":"US",
    "sg:address":"4765 E Bryson St",
    "sg:city":"Anaheim",
    "sg:classifiers":[
        {
            "category":"Shopping",
            "subcategory":"Department Store",
            "type":"Retail Goods"
        }
    ],
    "sg:phone":"+1 714 779 0990",
    "sg:postcode":"92807",
    "sg:province":"CA",
    "sg:tags":[
        "product",
        "plastics-foam"
    ],
    "wof:name":"Foam Plastics & Rubber Products, Corp.",
    "wof:placetype":"venue"
},
  "geometry": {"coordinates":[-117.814888,33.862549],"type":"Point"}
}