{
  "type": "Feature",
  "properties": {
    "iso:country":"US",
    "sg:address":"1155 Palm Ave",
    "sg:city":"Imperial Beach",
    "sg:classifiers":[
        {
            "category":"Personal",
            "subcategory":"Tattoo Parlor",
            "type":"Services"
        }
    ],
    "sg:phone":"+1 619 424 8983",
    "sg:postcode":"91932",
    "sg:province":"CA",
    "wof:name":"F S G Ink Tattoo Parlor",
    "wof:placetype":"venue"
},
  "geometry": {"coordinates":[-117.10900100000001,32.5839],"type":"Point"}
}