{
  "type": "Feature",
  "properties": {
    "addr:full":"276 Mitchell Lake Ln Copperopolis CA 95228",
    "addr:housenumber":"276",
    "addr:postcode":"95228",
    "addr:street":"Mitchell Lake Ln",
    "iso:country":"US",
    "sg:address":"276 Mitchell Lake Ln",
    "sg:city":"Copperopolis",
    "sg:classifiers":[
        {
            "category":"Manufacturing",
            "subcategory":"Buildings",
            "type":"Manufacturing & Wholesale Goods"
        },
        {
            "category":"Building & Trades",
            "subcategory":"Construction",
            "type":"Services"
        }
    ],
    "sg:phone":"+1 209 785 6564",
    "sg:postcode":"95228",
    "sg:province":"CA",
    "sg:tags":[
        "industrial",
        "system",
        "specialty",
        "builder",
        "heating",
        "contractor",
        "contractors-commercial",
        "home",
        "air conditioning"
    ],
    "wof:name":"Mid Matthews Construction",
    "wof:placetype":"venue"
},
  "geometry": {"coordinates":[-120.636118,37.91304],"type":"Point"}
}