{
  "type": "Feature",
  "properties": {
    "addr:full":"44 Montgomery St, Ste 4210 San Francisco CA 94104",
    "addr:housenumber":"44",
    "addr:postcode":"94104",
    "addr:street":"Montgomery St Ste 4210",
    "iso:country":"US",
    "sg:address":"44 Montgomery St, Ste 4210",
    "sg:city":"San Francisco",
    "sg:classifiers":[
        {
            "category":"Banks & Credit Unions",
            "subcategory":"Investment Brokerage",
            "type":"Services"
        },
        {
            "category":"Banks & Credit Unions",
            "subcategory":"Financial Services",
            "type":"Services"
        }
    ],
    "sg:phone":"+1 415 623 2452",
    "sg:postcode":"94104",
    "sg:province":"CA",
    "sg:tags":[
        "investing",
        "advising"
    ],
    "sg:website":"www.ameripriseadvisors.com/joann...",
    "wof:name":"Joanne Jordan - Ameriprise Financial Advisor",
    "wof:placetype":"venue"
},
  "geometry": {"coordinates":[-122.401736,37.789775],"type":"Point"}
}