{
  "type": "Feature",
  "properties": {
    "addr:full":"5127 Richmond Dr Pico Rivera CA 90660",
    "addr:housenumber":"5127",
    "addr:postcode":"90660",
    "addr:street":"Richmond Dr",
    "iso:country":"US",
    "sg:address":"5127 Richmond Dr",
    "sg:city":"Pico Rivera",
    "sg:classifiers":[
        {
            "category":"Professional",
            "type":"Services"
        }
    ],
    "sg:phone":"+1 562 949 5495",
    "sg:postcode":"90660",
    "sg:province":"CA",
    "wof:name":"Veronica Products",
    "wof:placetype":"venue"
},
  "geometry": {"coordinates":[-118.084813,33.999175],"type":"Point"}
}