{
  "type": "Feature",
  "properties": {
    "iso:country":"US",
    "sg:address":"3402 S Patton Ave",
    "sg:city":"San Pedro",
    "sg:classifiers":[
        {
            "category":"Real Estate",
            "subcategory":"Real Estate Agent",
            "type":"Services"
        }
    ],
    "sg:phone":"+1 310 833 1998",
    "sg:postcode":"90731",
    "sg:province":"CA",
    "wof:name":"Group Mark",
    "wof:placetype":"venue"
},
  "geometry": {"coordinates":[-118.30542699999999,33.716949],"type":"Point"}
}