{
  "type": "Feature",
  "properties": {
    "addr:full":"1084 Laurie Ave San Jose CA 95125",
    "addr:housenumber":"1084",
    "addr:postcode":"95125",
    "addr:street":"Laurie Ave",
    "iso:country":"US",
    "sg:address":"1084 Laurie Ave",
    "sg:city":"San Jose",
    "sg:classifiers":[
        {
            "category":"Building & Trades",
            "subcategory":"Landscaping Services",
            "type":"Services"
        }
    ],
    "sg:phone":"+1 408 298 1550",
    "sg:postcode":"95125",
    "sg:province":"CA",
    "sg:tags":[
        "designer",
        "landscape"
    ],
    "wof:name":"Urban Garden Design",
    "wof:placetype":"venue"
},
  "geometry": {"coordinates":[-121.889633,37.29765],"type":"Point"}
}