{
  "type": "Feature",
  "properties": {
    "iso:country":"US",
    "sg:address":"150 Shoreline Hwy",
    "sg:city":"Mill Valley",
    "sg:classifiers":[
        {
            "category":"Health Services",
            "subcategory":"Health Practitioner",
            "type":"Services"
        }
    ],
    "sg:phone":"+1 415 332 3352",
    "sg:postcode":"94965",
    "sg:province":"CA",
    "sg:tags":[
        "psychologist"
    ],
    "wof:name":"Behavior Therapy Institute",
    "wof:placetype":"venue"
},
  "geometry": {"coordinates":[-122.522606,37.879536],"type":"Point"}
}