{
  "type": "Feature",
  "properties": {
    "addr:full":"14050 Doolittle Dr San Leandro CA 94577",
    "addr:housenumber":"14050",
    "addr:postcode":"94577",
    "addr:street":"Doolittle Dr",
    "iso:country":"US",
    "sg:address":"14050 Doolittle Dr",
    "sg:city":"San Leandro",
    "sg:classifiers":[
        {
            "category":"Mining & Drilling",
            "type":"Manufacturing & Wholesale Goods"
        }
    ],
    "sg:phone":"+1 510 618 1333",
    "sg:postcode":"94577",
    "sg:province":"CA",
    "sg:tags":[
        "stone"
    ],
    "wof:name":"Golden Stone Granite Marble",
    "wof:placetype":"venue"
},
  "geometry": {"coordinates":[-122.17597000000001,37.698732],"type":"Point"}
}