{
  "type": "Feature",
  "properties": {
    "addr:full":"1035 N Armando St Anaheim CA 92806",
    "addr:housenumber":"1035",
    "addr:postcode":"92806",
    "addr:street":"N Armando St",
    "iso:country":"US",
    "sg:address":"1035 N Armando St",
    "sg:city":"Anaheim",
    "sg:classifiers":[
        {
            "category":"Wholesale",
            "subcategory":"Construction Materials",
            "type":"Manufacturing & Wholesale Goods"
        }
    ],
    "sg:phone":"+1 714 630 6042",
    "sg:postcode":"92806",
    "sg:province":"CA",
    "sg:tags":[
        "tile"
    ],
    "wof:name":"American Bullnose Corp",
    "wof:placetype":"venue"
},
  "geometry": {"coordinates":[-117.860029,33.848935],"type":"Point"}
}