{
  "type": "Feature",
  "properties": {
    "iso:country":"US",
    "sg:address":"28999 Rancho California Rd",
    "sg:city":"Temecula",
    "sg:classifiers":[
        {
            "category":"Restaurant",
            "type":"Food & Drink"
        }
    ],
    "sg:menulink":"http://www.allmenus.com/ca/murrieta/5796-pat--oscars-restaurants/menu/",
    "sg:phone":"+1 951 695 2422",
    "sg:postcode":"92590",
    "sg:province":"CA",
    "sg:tags":[
        "american"
    ],
    "wof:name":"Pat & Oscar's Restaurants",
    "wof:placetype":"venue"
},
  "geometry": {"coordinates":[-117.15218299999999,33.500095],"type":"Point"}
}