{
  "type": "Feature",
  "properties": {
    "iso:country":"US",
    "sg:address":"818 Park Row",
    "sg:city":"Salinas",
    "sg:classifiers":[
        {
            "category":"Food & Beverages",
            "subcategory":"Bakery",
            "type":"Retail Goods"
        }
    ],
    "sg:phone":"+1 831 771 8670",
    "sg:postcode":"93901",
    "sg:province":"CA",
    "sg:tags":[
        "bagel"
    ],
    "wof:name":"Bagel Corner",
    "wof:placetype":"venue"
},
  "geometry": {"coordinates":[-121.659063,36.66485],"type":"Point"}
}