{
  "type": "Feature",
  "properties": {
    "addr:full":"1631 N 1st St San Jose CA 95112",
    "addr:housenumber":"1631",
    "addr:postcode":"95112",
    "addr:street":"N 1St St",
    "iso:country":"US",
    "sg:address":"1631 N 1st St",
    "sg:city":"San Jose",
    "sg:classifiers":[
        {
            "category":"Wholesale",
            "subcategory":"Electrical",
            "type":"Manufacturing & Wholesale Goods"
        }
    ],
    "sg:phone":"+1 408 452 8906",
    "sg:postcode":"95112",
    "sg:province":"CA",
    "sg:tags":[
        "semiconductor"
    ],
    "wof:name":"Scientific Measurement Systems",
    "wof:placetype":"venue"
},
  "geometry": {"coordinates":[-121.913245,37.366436],"type":"Point"}
}