{
  "type": "Feature",
  "properties": {
    "iso:country":"US",
    "sg:address":"255 Crestlake Dr",
    "sg:city":"San Francisco",
    "sg:phone":"+1 415 519 8351",
    "sg:postcode":"94132",
    "sg:province":"CA",
    "wof:name":"Ideal Carpentry",
    "wof:placetype":"venue"
},
  "geometry": {"coordinates":[-122.48525100000001,37.734882],"type":"Point"}
}