{
  "type": "Feature",
  "properties": {
    "iso:country":"US",
    "sg:address":"31417 Park Ave",
    "sg:city":"Nuevo",
    "sg:classifiers":[
        {
            "category":"Building & Trades",
            "subcategory":"Landscaping Services",
            "type":"Services"
        }
    ],
    "sg:phone":"+1 951 928 3537",
    "sg:postcode":"92567",
    "sg:province":"CA",
    "sg:tags":[
        "lawn",
        "maintenance",
        "grounds"
    ],
    "wof:name":"Clean Up Patrol",
    "wof:placetype":"venue"
},
  "geometry": {"coordinates":[-117.11336,33.807892],"type":"Point"}
}