{
  "type": "Feature",
  "properties": {
    "iso:country":"US",
    "sg:address":"3114 Pacific Coast Hwy",
    "sg:city":"Torrance",
    "sg:classifiers":[
        {
            "category":"Food & Beverages",
            "subcategory":"Liquor & Beverages",
            "type":"Retail Goods"
        }
    ],
    "sg:phone":"+1 310 534 0060",
    "sg:postcode":"90505",
    "sg:province":"CA",
    "sg:tags":[
        "beer",
        "spirit",
        "wine"
    ],
    "wof:name":"Royal Liquor",
    "wof:placetype":"venue"
},
  "geometry": {"coordinates":[-118.339996,33.797798],"type":"Point"}
}