{
  "type": "Feature",
  "properties": {
    "addr:full":"145 Linden Ave Long Beach CA 90802",
    "addr:housenumber":"145",
    "addr:postcode":"90802",
    "addr:street":"Linden Ave",
    "iso:country":"US",
    "sg:address":"145 Linden Ave",
    "sg:city":"Long Beach",
    "sg:classifiers":[
        {
            "category":"Shopping",
            "subcategory":"Clothing, Apparel, & Fashions",
            "type":"Retail Goods"
        }
    ],
    "sg:phone":"+1 562 436 9869",
    "sg:postcode":"90802",
    "sg:province":"CA",
    "sg:tags":[
        "accessory",
        "clothing",
        "women's"
    ],
    "wof:name":"See Jane...",
    "wof:placetype":"venue"
},
  "geometry": {"coordinates":[-118.186373,33.769031],"type":"Point"}
}