{
  "type": "Feature",
  "properties": {
    "iso:country":"US",
    "sg:address":"1999 W Holt Ave",
    "sg:city":"Pomona",
    "sg:classifiers":[
        {
            "category":"Home & Garden",
            "subcategory":"Building Materials",
            "type":"Retail Goods"
        }
    ],
    "sg:phone":"+1 909 469 1288",
    "sg:postcode":"91768",
    "sg:province":"CA",
    "sg:tags":[
        "glass",
        "leaded"
    ],
    "sg:website":"www.adgu.com",
    "wof:name":"Door & Glass Unique",
    "wof:placetype":"venue"
},
  "geometry": {"coordinates":[-117.78627,34.061481],"type":"Point"}
}