{
  "type": "Feature",
  "properties": {
    "addr:full":"1200 N State St Los Angeles CA 90033",
    "addr:housenumber":"1200",
    "addr:postcode":"90033",
    "addr:street":"N State St",
    "iso:country":"US",
    "sg:address":"1200 N State St",
    "sg:city":"Los Angeles",
    "sg:classifiers":[
        {
            "category":"Building & Trades",
            "subcategory":"Electrical",
            "type":"Services"
        }
    ],
    "sg:phone":"+1 323 227 6089",
    "sg:postcode":"90033",
    "sg:province":"CA",
    "sg:tags":[
        "electrical",
        "contractor"
    ],
    "wof:name":"Northstar Fire Protection",
    "wof:placetype":"venue"
},
  "geometry": {"coordinates":[-118.209368,34.060412],"type":"Point"}
}