{
  "type": "Feature",
  "properties": {
    "iso:country":"US",
    "sg:address":"2358 1/2 S Robertson Blvd",
    "sg:city":"Los Angeles",
    "sg:classifiers":[
        {
            "category":"Building & Trades",
            "subcategory":"Construction",
            "type":"Services"
        }
    ],
    "sg:phone":"+1 310 839 3994",
    "sg:postcode":"90034",
    "sg:province":"CA",
    "sg:tags":[
        "contractor"
    ],
    "wof:name":"Sztain-Chulak Construction",
    "wof:placetype":"venue"
},
  "geometry": {"coordinates":[-118.387651,34.039979],"type":"Point"}
}