{
  "type": "Feature",
  "properties": {
    "iso:country":"US",
    "sg:address":"835 Terry Francois St",
    "sg:city":"San Francisco",
    "sg:classifiers":[
        {
            "category":"Recreation",
            "subcategory":"Marina",
            "type":"Entertainment"
        }
    ],
    "sg:phone":"+1 415 626 9172",
    "sg:postcode":"94158",
    "sg:province":"CA",
    "sg:tags":[
        "repairing",
        "boat"
    ],
    "wof:name":"SFBW",
    "wof:placetype":"venue"
},
  "geometry": {"coordinates":[-122.387041,37.765201],"type":"Point"}
}