{
  "type": "Feature",
  "properties": {
    "addr:full":"200 E Highway 12 Valley Springs CA 95252",
    "addr:housenumber":"200",
    "addr:postcode":"95252",
    "addr:street":"E Highway 12",
    "iso:country":"US",
    "sg:address":"200 E Highway 12",
    "sg:city":"Valley Springs",
    "sg:classifiers":[
        {
            "category":"Restaurant",
            "type":"Food & Drink"
        }
    ],
    "sg:menulink":"http://www.allmenus.com/ca/san-andreas/150576-subway/menu/",
    "sg:phone":"+1 209 772 3500",
    "sg:postcode":"95252",
    "sg:province":"CA",
    "sg:tags":[
        "american",
        "sandwich"
    ],
    "wof:name":"Subway",
    "wof:placetype":"venue"
},
  "geometry": {"coordinates":[-120.82575199999999,38.192451],"type":"Point"}
}