{
  "type": "Feature",
  "properties": {
    "iso:country":"US",
    "sg:address":"1735 Enterprise Dr",
    "sg:city":"Fairfield",
    "sg:classifiers":[
        {
            "category":"Wholesale",
            "subcategory":"Office Equipment",
            "type":"Manufacturing & Wholesale Goods"
        }
    ],
    "sg:phone":"+1 707 421 2679",
    "sg:postcode":"94533",
    "sg:province":"CA",
    "sg:tags":[
        "machine",
        "duplicating",
        "copying"
    ],
    "wof:name":"Wolco Business Systems",
    "wof:placetype":"venue"
},
  "geometry": {"coordinates":[-122.06159700000001,38.242955],"type":"Point"}
}