{
  "type": "Feature",
  "properties": {
    "iso:country":"US",
    "sg:address":"311 Boyd Street",
    "sg:city":"Los Angeles",
    "sg:classifiers":[
        {
            "category":"Food & Beverages",
            "subcategory":"Groceries & Convenience Stores",
            "type":"Retail Goods"
        }
    ],
    "sg:phone":"+1 213 620 0129",
    "sg:postcode":"90013",
    "sg:province":"CA",
    "wof:name":"Hpk",
    "wof:placetype":"venue"
},
  "geometry": {"coordinates":[-118.243501,34.047063],"type":"Point"}
}