{
  "type": "Feature",
  "properties": {
    "iso:country":"US",
    "sg:address":"160 E Freedom Ave",
    "sg:city":"Anaheim",
    "sg:classifiers":[
        {
            "category":"Manufacturing",
            "subcategory":"Retail Goods",
            "type":"Manufacturing & Wholesale Goods"
        }
    ],
    "sg:phone":"+1 714 879 5970",
    "sg:postcode":"92801",
    "sg:province":"CA",
    "sg:tags":[
        "manufacturer"
    ],
    "wof:name":"Crow Enterprises Inc",
    "wof:placetype":"venue"
},
  "geometry": {"coordinates":[-117.91971599999999,33.862456],"type":"Point"}
}