{
  "type": "Feature",
  "properties": {
    "addr:full":"100 S Sunrise Way Palm Springs CA 92262",
    "addr:housenumber":"100",
    "addr:postcode":"92262",
    "addr:street":"S Sunrise Way",
    "iso:country":"US",
    "sg:address":"100 S Sunrise Way",
    "sg:city":"Palm Springs",
    "sg:classifiers":[
        {
            "category":"Building & Trades",
            "subcategory":"Plumbing",
            "type":"Services"
        }
    ],
    "sg:phone":"+1 951 924 7611",
    "sg:postcode":"92262",
    "sg:province":"CA",
    "sg:tags":[
        "contractor"
    ],
    "wof:name":"Agape Heating & Cooling",
    "wof:placetype":"venue"
},
  "geometry": {"coordinates":[-116.52821400000001,33.821309],"type":"Point"}
}