{
  "type": "Feature",
  "properties": {
    "addr:full":"22130 Clarendon St Woodland Hills CA 91367",
    "addr:housenumber":"22130",
    "addr:postcode":"91367",
    "addr:street":"Clarendon St",
    "iso:country":"US",
    "sg:address":"22130 Clarendon St",
    "sg:city":"Woodland Hills",
    "sg:classifiers":[
        {
            "category":"Professional",
            "subcategory":"Lawyer & Legal Services",
            "type":"Services"
        }
    ],
    "sg:phone":"+1 818 884 8075",
    "sg:postcode":"91367",
    "sg:province":"CA",
    "wof:name":"B & D Global Properties",
    "wof:placetype":"venue"
},
  "geometry": {"coordinates":[-118.608689,34.169512],"type":"Point"}
}