{
  "type": "Feature",
  "properties": {
    "iso:country":"US",
    "sg:address":"398 Alvarado St",
    "sg:city":"Monterey",
    "sg:classifiers":[
        {
            "category":"Restaurant",
            "type":"Food & Drink"
        }
    ],
    "sg:menulink":"http://www.allmenus.com/ca/seaside-monterey/135561-jamba-juice/menu/",
    "sg:phone":"+1 831 655 9696",
    "sg:postcode":"93940",
    "sg:province":"CA",
    "sg:tags":[
        "smoothy",
        "juice",
        "american"
    ],
    "wof:name":"Jamba Juice",
    "wof:placetype":"venue"
},
  "geometry": {"coordinates":[-121.894604,36.600166],"type":"Point"}
}