{
  "type": "Feature",
  "properties": {
    "iso:country":"US",
    "sg:address":"3605 Long Beach Blvd Ste 210",
    "sg:city":"Long Beach",
    "sg:classifiers":[
        {
            "category":"Professional",
            "subcategory":"Lawyer & Legal Services",
            "type":"Services"
        }
    ],
    "sg:phone":"+1 562 988 8086",
    "sg:postcode":"90807",
    "sg:province":"CA",
    "sg:website":"www.attorneyaid.com",
    "wof:name":"Attorney Solutions",
    "wof:placetype":"venue"
},
  "geometry": {"coordinates":[-118.189003,33.8223],"type":"Point"}
}