{
  "type": "Feature",
  "properties": {
    "addr:full":"1200 W Main St Alhambra CA 91801",
    "addr:housenumber":"1200",
    "addr:postcode":"91801",
    "addr:street":"W Main St",
    "iso:country":"US",
    "sg:address":"1200 W Main St",
    "sg:city":"Alhambra",
    "sg:classifiers":[
        {
            "category":"Autos & Motor Vehicles",
            "subcategory":"Automobile Sales",
            "type":"Retail Goods"
        }
    ],
    "sg:phone":"+1 626 576 2800",
    "sg:postcode":"91801",
    "sg:province":"CA",
    "sg:tags":[
        "car"
    ],
    "sg:website":"www.alhambramazda.com/",
    "wof:name":"Mazda of Alhambra",
    "wof:placetype":"venue"
},
  "geometry": {"coordinates":[-118.136002,34.091599],"type":"Point"}
}