{
  "type": "Feature",
  "properties": {
    "addr:full":"318 Rose Ave Danville CA 94526",
    "addr:housenumber":"318",
    "addr:postcode":"94526",
    "addr:street":"Rose Ave",
    "iso:country":"US",
    "sg:address":"318 Rose Ave",
    "sg:city":"Danville",
    "sg:classifiers":[
        {
            "category":"Personal",
            "subcategory":"Beauty Salon",
            "type":"Services"
        }
    ],
    "sg:phone":"+1 925 820 4846",
    "sg:postcode":"94526",
    "sg:province":"CA",
    "wof:name":"Hair Avenue",
    "wof:placetype":"venue"
},
  "geometry": {"coordinates":[-122.00118999999999,37.82412],"type":"Point"}
}