{
  "type": "Feature",
  "properties": {
    "iso:country":"US",
    "sg:address":"172 W Highland Ave",
    "sg:city":"San Bernardino",
    "sg:classifiers":[
        {
            "category":"Recreation",
            "type":"Entertainment"
        }
    ],
    "sg:phone":"+1 909 882 1106",
    "sg:postcode":"92405",
    "sg:province":"CA",
    "sg:tags":[
        "amusement"
    ],
    "wof:name":"Unique Motorsports",
    "wof:placetype":"venue"
},
  "geometry": {"coordinates":[-117.286563,34.136025],"type":"Point"}
}