{
  "type": "Feature",
  "properties": {
    "iso:country":"US",
    "sg:address":"10690 San Pablo Ave",
    "sg:city":"El Cerrito",
    "sg:classifiers":[
        {
            "category":"Health Services",
            "subcategory":"Doctor",
            "type":"Services"
        }
    ],
    "sg:phone":"+1 510 528 9590",
    "sg:postcode":"94530",
    "sg:province":"CA",
    "sg:tags":[
        "clinic"
    ],
    "wof:name":"Gambro Healthcare",
    "wof:placetype":"venue"
},
  "geometry": {"coordinates":[-122.30929999999999,37.912472],"type":"Point"}
}