{
  "type": "Feature",
  "properties": {
    "iso:country":"US",
    "sg:address":"5141 Moorpark Ave",
    "sg:city":"San Jose",
    "sg:classifiers":[
        {
            "category":"Health Services",
            "subcategory":"Medical Lab",
            "type":"Services"
        }
    ],
    "sg:phone":"+1 408 257 4323",
    "sg:postcode":"95129",
    "sg:province":"CA",
    "sg:tags":[
        "laboratory"
    ],
    "wof:name":"ABC Dental Lab",
    "wof:placetype":"venue"
},
  "geometry": {"coordinates":[-121.99245999999999,37.309729],"type":"Point"}
}