{
  "type": "Feature",
  "properties": {
    "addr:full":"11042 Atlantic Avenue Lynwood CA 90262",
    "addr:housenumber":"11042",
    "addr:postcode":"90262",
    "addr:street":"Atlantic Avenue",
    "iso:country":"US",
    "sg:address":"11042 Atlantic Avenue",
    "sg:city":"Lynwood",
    "sg:classifiers":[
        {
            "category":"Autos & Motor Vehicles",
            "subcategory":"Motorcycle Sales",
            "type":"Retail Goods"
        }
    ],
    "sg:phone":"+1 310 537 7480",
    "sg:postcode":"90262",
    "sg:province":"CA",
    "wof:name":"Cycle Works",
    "wof:placetype":"venue"
},
  "geometry": {"coordinates":[-118.184363,33.928974],"type":"Point"}
}