{
  "type": "Feature",
  "properties": {
    "addr:full":"3093 Citrus Cir Walnut Creek CA 94598",
    "addr:housenumber":"3093",
    "addr:postcode":"94598",
    "addr:street":"Citrus Cir",
    "iso:country":"US",
    "sg:address":"3093 Citrus Cir",
    "sg:city":"Walnut Creek",
    "sg:classifiers":[
        {
            "category":"Professional",
            "subcategory":"Employment Agencies",
            "type":"Services"
        }
    ],
    "sg:phone":"+1 925 937 4874",
    "sg:postcode":"94598",
    "sg:province":"CA",
    "sg:tags":[
        "opportunity"
    ],
    "sg:website":"www.harvtech.com",
    "wof:name":"Harvest Technical Svc",
    "wof:placetype":"venue"
},
  "geometry": {"coordinates":[-122.015238,37.92925],"type":"Point"}
}