{
  "type": "Feature",
  "properties": {
    "addr:full":"1144 S Robertson Blvd Los Angeles CA 90035",
    "addr:housenumber":"1144",
    "addr:postcode":"90035",
    "addr:street":"S Robertson Blvd",
    "iso:country":"US",
    "sg:address":"1144 S Robertson Blvd",
    "sg:city":"Los Angeles",
    "sg:classifiers":[
        {
            "category":"Professional",
            "type":"Services"
        }
    ],
    "sg:phone":"+1 310 273 3330",
    "sg:postcode":"90035",
    "sg:province":"CA",
    "wof:name":"Typesetting, Ink",
    "wof:placetype":"venue"
},
  "geometry": {"coordinates":[-118.38400300000001,34.056499],"type":"Point"}
}