{
  "type": "Feature",
  "properties": {
    "iso:country":"US",
    "sg:address":"1144 S Robertson Blvd",
    "sg:city":"Los Angeles",
    "sg:classifiers":[
        {
            "category":"Professional",
            "type":"Services"
        }
    ],
    "sg:phone":"+1 310 273 3330",
    "sg:postcode":"90035",
    "sg:province":"CA",
    "wof:name":"Typesetting, Ink",
    "wof:placetype":"venue"
},
  "geometry": {"coordinates":[-118.384003,34.056499],"type":"Point"}
}