{
  "type": "Feature",
  "properties": {
    "addr:full":"3100 Stine Rd Bakersfield CA 93309",
    "addr:housenumber":"3100",
    "addr:postcode":"93309",
    "addr:street":"Stine Rd",
    "iso:country":"US",
    "sg:address":"3100 Stine Rd",
    "sg:city":"Bakersfield",
    "sg:classifiers":[
        {
            "category":"Wholesale",
            "subcategory":"Electrical",
            "type":"Manufacturing & Wholesale Goods"
        }
    ],
    "sg:phone":"+1 661 397 3052",
    "sg:postcode":"93309",
    "sg:province":"CA",
    "sg:tags":[
        "control",
        "security",
        "system"
    ],
    "wof:name":"Mr Built-In's",
    "wof:placetype":"venue"
},
  "geometry": {"coordinates":[-119.05667099999999,35.325058],"type":"Point"}
}