{
  "type": "Feature",
  "properties": {
    "iso:country":"US",
    "sg:address":"42600 Cook St",
    "sg:city":"Palm Desert",
    "sg:classifiers":[
        {
            "category":"Social Services",
            "type":"Services"
        }
    ],
    "sg:phone":"+1 760 568 3977",
    "sg:postcode":"92211",
    "sg:province":"CA",
    "sg:tags":[
        "organization",
        "welfare"
    ],
    "wof:name":"Big Brothers & Big Sisters",
    "wof:placetype":"venue"
},
  "geometry": {"coordinates":[-116.35624199999999,33.739034],"type":"Point"}
}