{
  "type": "Feature",
  "properties": {
    "addr:full":"2454 Telegraph Ave Berkeley CA 94704",
    "addr:housenumber":"2454",
    "addr:postcode":"94704",
    "addr:street":"Telegraph Ave",
    "iso:country":"US",
    "sg:address":"2454 Telegraph Ave",
    "sg:city":"Berkeley",
    "sg:classifiers":[
        {
            "category":"Shopping",
            "subcategory":"Florist",
            "type":"Retail Goods"
        }
    ],
    "sg:phone":"+1 510 548 2765",
    "sg:postcode":"94704",
    "sg:province":"CA",
    "sg:website":"www.telegraphflower.com",
    "wof:name":"Telegraph Flowers",
    "wof:placetype":"venue"
},
  "geometry": {"coordinates":[-122.258635,37.865966],"type":"Point"}
}