{
  "type": "Feature",
  "properties": {
    "iso:country":"US",
    "sg:address":"3105 Easy Ave",
    "sg:city":"Long Beach",
    "sg:classifiers":[
        {
            "category":"Education",
            "subcategory":"School",
            "type":"Public Place"
        }
    ],
    "sg:phone":"+1 562 427 5515",
    "sg:postcode":"90810",
    "sg:province":"CA",
    "sg:tags":[
        "high",
        "middle",
        "elementary"
    ],
    "wof:name":"John Muir Elementary School",
    "wof:placetype":"venue"
},
  "geometry": {"coordinates":[-118.210165,33.813534],"type":"Point"}
}