{
  "type": "Feature",
  "properties": {
    "iso:country":"US",
    "sg:address":"105 W Walnut St",
    "sg:city":"Lodi",
    "sg:classifiers":[
        {
            "category":"Personal",
            "subcategory":"Beauty Salon",
            "type":"Services"
        }
    ],
    "sg:phone":"+1 209 368 9861",
    "sg:postcode":"95240",
    "sg:province":"CA",
    "wof:name":"Jill Perry Dermatherapy",
    "wof:placetype":"venue"
},
  "geometry": {"coordinates":[-121.275119,38.13192],"type":"Point"}
}