{
  "type": "Feature",
  "properties": {
    "addr:full":"751 Sutter St Yuba City CA 95991",
    "addr:housenumber":"751",
    "addr:postcode":"95991",
    "addr:street":"Sutter St",
    "iso:country":"US",
    "sg:address":"751 Sutter St",
    "sg:city":"Yuba City",
    "sg:classifiers":[
        {
            "category":"Wholesale",
            "subcategory":"Toys & Hobbies",
            "type":"Manufacturing & Wholesale Goods"
        },
        {
            "category":"Shopping",
            "subcategory":"Hobbies, Toys, & Games",
            "type":"Retail Goods"
        }
    ],
    "sg:phone":"+1 530 751 3004",
    "sg:postcode":"95991",
    "sg:province":"CA",
    "sg:tags":[
        "supply"
    ],
    "wof:name":"Hero's Hideout",
    "wof:placetype":"venue"
},
  "geometry": {"coordinates":[-121.61061100000001,39.141276],"type":"Point"}
}