{
  "type": "Feature",
  "properties": {
    "addr:full":"6852 Jonathan Ave Cypress CA 90630",
    "addr:housenumber":"6852",
    "addr:postcode":"90630",
    "addr:street":"Jonathan Ave",
    "iso:country":"US",
    "sg:address":"6852 Jonathan Ave",
    "sg:city":"Cypress",
    "sg:classifiers":[
        {
            "category":"Building & Trades",
            "subcategory":"Construction",
            "type":"Services"
        }
    ],
    "sg:phone":"+1 714 396 6201",
    "sg:postcode":"90630",
    "sg:province":"CA",
    "sg:tags":[
        "general",
        "contractor"
    ],
    "wof:name":"Ameripol",
    "wof:placetype":"venue"
},
  "geometry": {"coordinates":[-118.01258799999999,33.806694],"type":"Point"}
}