{
  "type": "Feature",
  "properties": {
    "iso:country":"US",
    "sg:address":"2128 Hillhurst Ave",
    "sg:city":"Los Angeles",
    "sg:classifiers":[
        {
            "category":"Restaurant",
            "type":"Food & Drink"
        }
    ],
    "sg:phone":"+1 323 669 7640",
    "sg:postcode":"90027",
    "sg:province":"CA",
    "wof:name":"LA Belle Epoque",
    "wof:placetype":"venue"
},
  "geometry": {"coordinates":[-118.28743299999999,34.111888],"type":"Point"}
}