{
  "type": "Feature",
  "properties": {
    "addr:full":"1182 Chestnut St Menlo Park CA 94025",
    "addr:housenumber":"1182",
    "addr:postcode":"94025",
    "addr:street":"Chestnut St",
    "iso:country":"US",
    "sg:address":"1182 Chestnut St",
    "sg:city":"Menlo Park",
    "sg:classifiers":[
        {
            "category":"Insurance",
            "subcategory":"Insurance Agent",
            "type":"Services"
        }
    ],
    "sg:phone":"+1 650 322 3499",
    "sg:postcode":"94025",
    "sg:province":"CA",
    "wof:name":"Steve Fiorentino Insurance Inc",
    "wof:placetype":"venue"
},
  "geometry": {"coordinates":[-122.185757,37.452431],"type":"Point"}
}