{
  "type": "Feature",
  "properties": {
    "iso:country":"US",
    "sg:address":"16055 Ventura Blvd",
    "sg:city":"Encino",
    "sg:classifiers":[
        {
            "category":"Professional",
            "subcategory":"Accounting & Tax Preparation",
            "type":"Services"
        }
    ],
    "sg:phone":"+1 323 872 2034",
    "sg:postcode":"91436",
    "sg:province":"CA",
    "sg:tags":[
        "accountant"
    ],
    "wof:name":"Paul Golub CPA",
    "wof:placetype":"venue"
},
  "geometry": {"coordinates":[-118.482609,34.156279],"type":"Point"}
}