{
  "type": "Feature",
  "properties": {
    "addr:full":"1240 W 20th St San Pedro CA 90731",
    "addr:housenumber":"1240",
    "addr:postcode":"90731",
    "addr:street":"W 20Th St",
    "iso:country":"US",
    "sg:address":"1240 W 20th St",
    "sg:city":"San Pedro",
    "sg:classifiers":[
        {
            "category":"Shopping",
            "subcategory":"Catalog Store",
            "type":"Retail Goods"
        }
    ],
    "sg:phone":"+1 310 548 8522",
    "sg:postcode":"90731",
    "sg:province":"CA",
    "sg:tags":[
        "mail",
        "house"
    ],
    "wof:name":"Applied Mktg Solutions LLC",
    "wof:placetype":"venue"
},
  "geometry": {"coordinates":[-118.304103,33.726187],"type":"Point"}
}