{
  "type": "Feature",
  "properties": {
    "addr:full":"941 Ontario St Escondido CA 92025",
    "addr:housenumber":"941",
    "addr:postcode":"92025",
    "addr:street":"Ontario St",
    "iso:country":"US",
    "sg:address":"941 Ontario St",
    "sg:city":"Escondido",
    "sg:classifiers":[
        {
            "category":"Place Of Worship",
            "type":"Public Place"
        }
    ],
    "sg:phone":"+1 760 432 8495",
    "sg:postcode":"92025",
    "sg:province":"CA",
    "sg:tags":[
        "church"
    ],
    "wof:name":"New Church Day",
    "wof:placetype":"venue"
},
  "geometry": {"coordinates":[-117.08907499999999,33.107152],"type":"Point"}
}