{
  "type": "Feature",
  "properties": {
    "addr:full":"4266 Elton St Baldwin Park CA 91706",
    "addr:housenumber":"4266",
    "addr:postcode":"91706",
    "addr:street":"Elton St",
    "iso:country":"US",
    "sg:address":"4266 Elton St",
    "sg:city":"Baldwin Park",
    "sg:classifiers":[
        {
            "category":"Building & Trades",
            "subcategory":"Construction",
            "type":"Services"
        }
    ],
    "sg:phone":"+1 626 960 4143",
    "sg:postcode":"91706",
    "sg:province":"CA",
    "sg:tags":[
        "sewer",
        "contractor"
    ],
    "wof:name":"Larry Penunuri",
    "wof:placetype":"venue"
},
  "geometry": {"coordinates":[-117.950778,34.089678],"type":"Point"}
}