{
  "type": "Feature",
  "properties": {
    "iso:country":"US",
    "sg:address":"915 Capitol Mall",
    "sg:city":"Sacramento",
    "sg:classifiers":[
        {
            "category":"Government",
            "subcategory":"Office",
            "type":"Public Place"
        }
    ],
    "sg:phone":"+1 916 653 3255",
    "sg:postcode":"95814",
    "sg:province":"CA",
    "wof:name":"Debt Limit",
    "wof:placetype":"venue"
},
  "geometry": {"coordinates":[-121.49603500000001,38.57738],"type":"Point"}
}