{
  "type": "Feature",
  "properties": {
    "addr:full":"493 W Orange Show Rd San Bernardino CA 92408",
    "addr:housenumber":"493",
    "addr:postcode":"92408",
    "addr:street":"W Orange Show Rd",
    "iso:country":"US",
    "sg:address":"493 W Orange Show Rd",
    "sg:city":"San Bernardino",
    "sg:classifiers":[
        {
            "category":"Shopping",
            "subcategory":"Computers & Home Electronics",
            "type":"Retail Goods"
        }
    ],
    "sg:phone":"+1 909 888 8884",
    "sg:postcode":"92408",
    "sg:province":"CA",
    "sg:tags":[
        "equipment",
        "electronic",
        "supply"
    ],
    "wof:name":"Radio Shack",
    "wof:placetype":"venue"
},
  "geometry": {"coordinates":[-117.291622,34.079547],"type":"Point"}
}