{
  "type": "Feature",
  "properties": {
    "addr:full":"8232 Christian Ave Dos Palos CA 93620",
    "addr:housenumber":"8232",
    "addr:postcode":"93620",
    "addr:street":"Christian Ave",
    "iso:country":"US",
    "sg:address":"8232 Christian Ave",
    "sg:city":"Dos Palos",
    "sg:classifiers":[
        {
            "category":"Freight",
            "type":"Transportation"
        }
    ],
    "sg:phone":"+1 209 392 0130",
    "sg:postcode":"93620",
    "sg:province":"CA",
    "sg:tags":[
        "operator",
        "local",
        "trucking"
    ],
    "wof:name":"Gonzalez Trucking",
    "wof:placetype":"venue"
},
  "geometry": {"coordinates":[-120.641336,36.97469],"type":"Point"}
}