{
  "type": "Feature",
  "properties": {
    "iso:country":"US",
    "sg:address":"1666 Garnet Ave",
    "sg:city":"San Diego",
    "sg:classifiers":[
        {
            "category":"Shopping",
            "subcategory":"Clothing, Apparel, & Fashions",
            "type":"Retail Goods"
        }
    ],
    "sg:phone":"+1 858 688 5052",
    "sg:postcode":"92109",
    "sg:province":"CA",
    "sg:tags":[
        "family"
    ],
    "wof:name":"Dopamine Clothing",
    "wof:placetype":"venue"
},
  "geometry": {"coordinates":[-117.240124,32.799997],"type":"Point"}
}