{
  "type": "Feature",
  "properties": {
    "addr:full":"440 E 58th St Los Angeles CA 90011",
    "addr:housenumber":"440",
    "addr:postcode":"90011",
    "addr:street":"E 58Th St",
    "iso:country":"US",
    "sg:address":"440 E 58th St",
    "sg:city":"Los Angeles",
    "sg:classifiers":[
        {
            "category":"Wholesale",
            "subcategory":"Apparel",
            "type":"Manufacturing & Wholesale Goods"
        }
    ],
    "sg:phone":"+1 323 233 3000",
    "sg:postcode":"90011",
    "sg:province":"CA",
    "wof:name":"Kooh's Jean Inc",
    "wof:placetype":"venue"
},
  "geometry": {"coordinates":[-118.265552,33.989758],"type":"Point"}
}