{
  "type": "Feature",
  "properties": {
    "iso:country":"US",
    "sg:address":"523 Octavia St",
    "sg:city":"San Francisco",
    "sg:classifiers":[
        {
            "category":"Professional",
            "type":"Services"
        }
    ],
    "sg:phone":"+1 415 285 1282",
    "sg:postcode":"94102",
    "sg:province":"CA",
    "wof:name":"Plea For Peace Foundation",
    "wof:placetype":"venue"
},
  "geometry": {"coordinates":[-122.424733,37.776762],"type":"Point"}
}