{
  "type": "Feature",
  "properties": {
    "addr:full":"25485 Iverson Rd Gonzales CA 93926",
    "addr:housenumber":"25485",
    "addr:postcode":"93926",
    "addr:street":"Iverson Rd",
    "iso:country":"US",
    "sg:address":"25485 Iverson Rd",
    "sg:city":"Gonzales",
    "sg:classifiers":[
        {
            "category":"Farming",
            "subcategory":"Livestock Farm",
            "type":"Manufacturing & Wholesale Goods"
        }
    ],
    "sg:phone":"+1 831 675 2593",
    "sg:postcode":"93926",
    "sg:province":"CA",
    "sg:tags":[
        "animal",
        "general"
    ],
    "wof:name":"Handley Family Ranch LLC",
    "wof:placetype":"venue"
},
  "geometry": {"coordinates":[-121.442982,36.553289],"type":"Point"}
}