{
  "type": "Feature",
  "properties": {
    "iso:country":"US",
    "sg:address":"935 Moraga Rd",
    "sg:city":"Lafayette",
    "sg:classifiers":[
        {
            "category":"Health Services",
            "subcategory":"Health Practitioner",
            "type":"Services"
        }
    ],
    "sg:phone":"+1 925 284 3916",
    "sg:postcode":"94549",
    "sg:province":"CA",
    "sg:tags":[
        "psychologist"
    ],
    "wof:name":"Pamela Rudd PHD",
    "wof:placetype":"venue"
},
  "geometry": {"coordinates":[-122.118458,37.889672],"type":"Point"}
}