{
  "type": "Feature",
  "properties": {
    "addr:full":"1114 State St Santa Barbara CA 93101",
    "addr:housenumber":"1114",
    "addr:postcode":"93101",
    "addr:street":"State St",
    "iso:country":"US",
    "sg:address":"1114 State St",
    "sg:city":"Santa Barbara",
    "sg:classifiers":[
        {
            "category":"Professional",
            "subcategory":"Accounting & Tax Preparation",
            "type":"Services"
        }
    ],
    "sg:phone":"+1 805 965 2022",
    "sg:postcode":"93101",
    "sg:province":"CA",
    "sg:tags":[
        "accountant"
    ],
    "wof:name":"Frank E Mc Ginity CPA",
    "wof:placetype":"venue"
},
  "geometry": {"coordinates":[-119.704244,34.423284],"type":"Point"}
}