{
  "type": "Feature",
  "properties": {
    "iso:country":"US",
    "sg:address":"143 N Harvard Ave",
    "sg:city":"Claremont",
    "sg:classifiers":[
        {
            "category":"Shopping",
            "subcategory":"Books",
            "type":"Retail Goods"
        }
    ],
    "sg:phone":"+1 909 626 8283",
    "sg:postcode":"91711",
    "sg:province":"CA",
    "wof:name":"Iris Wild Bookstore",
    "wof:placetype":"venue"
},
  "geometry": {"coordinates":[-117.716478,34.095235],"type":"Point"}
}