{
  "type": "Feature",
  "properties": {
    "addr:full":"425 California St Ste 900 San Francisco CA 94104",
    "addr:housenumber":"425",
    "addr:postcode":"94104",
    "addr:street":"California St Ste 900",
    "iso:country":"US",
    "sg:address":"425 California St Ste 900",
    "sg:city":"San Francisco",
    "sg:classifiers":[
        {
            "category":"Professional",
            "subcategory":"Lawyer & Legal Services",
            "type":"Services"
        }
    ],
    "sg:phone":"+1 415 296 0800",
    "sg:postcode":"94104",
    "sg:province":"CA",
    "sg:tags":[
        "divorce",
        "law",
        "family"
    ],
    "sg:website":"www.bryanhinshaw.com",
    "wof:name":"BRYAN-HINSHAW",
    "wof:placetype":"venue"
},
  "geometry": {"coordinates":[-122.40163,37.79287],"type":"Point"}
}