{
  "type": "Feature",
  "properties": {
    "addr:full":"1825 N Edgemont St Los Angeles CA 90027",
    "addr:housenumber":"1825",
    "addr:postcode":"90027",
    "addr:street":"N Edgemont St",
    "iso:country":"US",
    "sg:address":"1825 N Edgemont St",
    "sg:city":"Los Angeles",
    "sg:classifiers":[
        {
            "category":"Wholesale",
            "subcategory":"Motor Vehicles",
            "type":"Manufacturing & Wholesale Goods"
        }
    ],
    "sg:phone":"+1 323 660 4177",
    "sg:postcode":"90027",
    "sg:province":"CA",
    "wof:name":"Terraplane Motor Co",
    "wof:placetype":"venue"
},
  "geometry": {"coordinates":[-118.296235,34.103124],"type":"Point"}
}