{
  "type": "Feature",
  "properties": {
    "iso:country":"US",
    "sg:address":"850 S Alta Vista Ave",
    "sg:city":"Monrovia",
    "sg:classifiers":[
        {
            "category":"Shopping",
            "subcategory":"Catalog Store",
            "type":"Retail Goods"
        }
    ],
    "sg:phone":"+1 626 256 6522",
    "sg:postcode":"91016",
    "sg:province":"CA",
    "sg:tags":[
        "mail",
        "house"
    ],
    "wof:name":"Dramatic Ware",
    "wof:placetype":"venue"
},
  "geometry": {"coordinates":[-118.007442,34.14253],"type":"Point"}
}