{
  "type": "Feature",
  "properties": {
    "iso:country":"US",
    "sg:address":"8166 W 3rd St",
    "sg:city":"Los Angeles",
    "sg:classifiers":[
        {
            "category":"Retail",
            "subcategory":"Laundry & Dry Cleaning",
            "type":"Services"
        }
    ],
    "sg:phone":"+1 323 653 6637",
    "sg:postcode":"90048",
    "sg:province":"CA",
    "wof:name":"Sloan's Dry Cleaners",
    "wof:placetype":"venue"
},
  "geometry": {"coordinates":[-118.36769,34.072109],"type":"Point"}
}