{
  "type": "Feature",
  "properties": {
    "addr:full":"8166 W 3rd St Los Angeles CA 90048",
    "addr:housenumber":"8166",
    "addr:postcode":"90048",
    "addr:street":"W 3Rd St",
    "iso:country":"US",
    "sg:address":"8166 W 3rd St",
    "sg:city":"Los Angeles",
    "sg:classifiers":[
        {
            "category":"Retail",
            "subcategory":"Laundry & Dry Cleaning",
            "type":"Services"
        }
    ],
    "sg:phone":"+1 323 653 6637",
    "sg:postcode":"90048",
    "sg:province":"CA",
    "wof:name":"Sloan's Dry Cleaners",
    "wof:placetype":"venue"
},
  "geometry": {"coordinates":[-118.36769,34.072109],"type":"Point"}
}