{
  "type": "Feature",
  "properties": {
    "addr:full":"1285 Poplar Dr Oakley CA 94561",
    "addr:housenumber":"1285",
    "addr:postcode":"94561",
    "addr:street":"Poplar Dr",
    "iso:country":"US",
    "sg:address":"1285 Poplar Dr",
    "sg:city":"Oakley",
    "sg:classifiers":[
        {
            "category":"Cinema",
            "subcategory":"Movie Rental",
            "type":"Entertainment"
        }
    ],
    "sg:phone":"+1 925 420 5829",
    "sg:postcode":"94561",
    "sg:province":"CA",
    "sg:tags":[
        "motion",
        "picture",
        "distributor",
        "film",
        "exchange"
    ],
    "wof:name":"Fantabulous Productions",
    "wof:placetype":"venue"
},
  "geometry": {"coordinates":[-121.638834,37.987978],"type":"Point"}
}