{
  "type": "Feature",
  "properties": {
    "iso:country":"US",
    "sg:address":"505 S Main St Ste 275",
    "sg:city":"Orange",
    "sg:classifiers":[
        {
            "category":"Health Services",
            "subcategory":"Doctor",
            "type":"Services"
        }
    ],
    "sg:phone":"+1 714 836 6607",
    "sg:postcode":"92868",
    "sg:province":"CA",
    "wof:name":"Camilon Felizardo S Jr MDfAAP",
    "wof:placetype":"venue"
},
  "geometry": {"coordinates":[-117.867105,33.780237],"type":"Point"}
}