{
  "type": "Feature",
  "properties": {
    "addr:full":"541 Hayes St San Francisco CA 94102",
    "addr:housenumber":"541",
    "addr:postcode":"94102",
    "addr:street":"Hayes St",
    "iso:country":"US",
    "sg:address":"541 Hayes St",
    "sg:city":"San Francisco",
    "sg:classifiers":[
        {
            "category":"Shopping",
            "subcategory":"Clothing, Apparel, & Fashions",
            "type":"Retail Goods"
        }
    ],
    "sg:phone":"+1 415 252 5997",
    "sg:postcode":"94102",
    "sg:province":"CA",
    "wof:name":"Dish Clothing",
    "wof:placetype":"venue"
},
  "geometry": {"coordinates":[-122.42572199999999,37.776476],"type":"Point"}
}