{
  "type": "Feature",
  "properties": {
    "addr:full":"2479 E Bayshore Rd Palo Alto CA 94303",
    "addr:housenumber":"2479",
    "addr:postcode":"94303",
    "addr:street":"E Bayshore Rd",
    "iso:country":"US",
    "sg:address":"2479 E Bayshore Rd",
    "sg:city":"Palo Alto",
    "sg:classifiers":[
        {
            "category":"Professional",
            "subcategory":"Lawyer & Legal Services",
            "type":"Services"
        }
    ],
    "sg:phone":"+1 650 328 3200",
    "sg:postcode":"94303",
    "sg:province":"CA",
    "sg:tags":[
        "attorney"
    ],
    "sg:website":"www.jkrueger.com",
    "wof:name":"Jane L Krueger",
    "wof:placetype":"venue"
},
  "geometry": {"coordinates":[-122.1183,37.446267],"type":"Point"}
}