{
  "type": "Feature",
  "properties": {
    "iso:country":"US",
    "sg:address":"43923 Sierra Hwy",
    "sg:city":"Lancaster",
    "sg:classifiers":[
        {
            "category":"Autos & Motor Vehicles",
            "subcategory":"Auto Supplies",
            "type":"Retail Goods"
        }
    ],
    "sg:phone":"+1 661 945 1833",
    "sg:postcode":"93534",
    "sg:province":"CA",
    "sg:tags":[
        "tire"
    ],
    "sg:website":"http://www.tirestoreAV.com/",
    "wof:name":"The Tire Store",
    "wof:placetype":"venue"
},
  "geometry": {"coordinates":[-118.133822,34.680975],"type":"Point"}
}