{
  "type": "Feature",
  "properties": {
    "iso:country":"US",
    "sg:address":"7279 N Rosemead Blvd",
    "sg:city":"Arcadia",
    "sg:classifiers":[
        {
            "category":"Shopping",
            "subcategory":"Department Store",
            "type":"Retail Goods"
        }
    ],
    "sg:phone":"+1 626 451 5818",
    "sg:postcode":"91775",
    "sg:province":"CA",
    "sg:website":"www.kohls.com",
    "wof:name":"Kohl's",
    "wof:placetype":"venue"
},
  "geometry": {"coordinates":[-118.073244,34.13048],"type":"Point"}
}