{
  "type": "Feature",
  "properties": {
    "iso:country":"US",
    "sg:address":"20260 Quail Hollow Rd",
    "sg:city":"Apple Valley",
    "sg:classifiers":[
        {
            "category":"Real Estate",
            "subcategory":"Real Estate Agent",
            "type":"Services"
        }
    ],
    "sg:phone":"+1 760 961 1666",
    "sg:postcode":"92308",
    "sg:province":"CA",
    "sg:tags":[
        "house",
        "construct"
    ],
    "wof:name":"Shear Realty",
    "wof:placetype":"venue"
},
  "geometry": {"coordinates":[-117.221987,34.484825],"type":"Point"}
}