{
  "type": "Feature",
  "properties": {
    "iso:country":"US",
    "sg:address":"2100 Arden Way",
    "sg:city":"Sacramento",
    "sg:classifiers":[
        {
            "category":"Shopping",
            "subcategory":"Gifts & Souvenirs",
            "type":"Retail Goods"
        }
    ],
    "sg:phone":"+1 916 564 4256",
    "sg:postcode":"95825",
    "sg:province":"CA",
    "sg:tags":[
        "shop"
    ],
    "wof:name":"Angels & Treasures",
    "wof:placetype":"venue"
},
  "geometry": {"coordinates":[-121.417138,38.596058],"type":"Point"}
}