{
  "type": "Feature",
  "properties": {
    "iso:country":"US",
    "sg:address":"1450 Grant Ave",
    "sg:city":"Novato",
    "sg:classifiers":[
        {
            "category":"Professional",
            "subcategory":"Accounting & Tax Preparation",
            "type":"Services"
        }
    ],
    "sg:phone":"+1 415 898 0600",
    "sg:postcode":"94945",
    "sg:province":"CA",
    "sg:tags":[
        "accountant"
    ],
    "sg:website":"www.morrecpa.com",
    "wof:name":"Morre & Co",
    "wof:placetype":"venue"
},
  "geometry": {"coordinates":[-122.57539,38.108637],"type":"Point"}
}