{
  "type": "Feature",
  "properties": {
    "addr:full":"5919 3rd St San Francisco CA 94124",
    "addr:housenumber":"5919",
    "addr:postcode":"94124",
    "addr:street":"3Rd St",
    "iso:country":"US",
    "sg:address":"5919 3rd St",
    "sg:city":"San Francisco",
    "sg:classifiers":[
        {
            "category":"Professional",
            "type":"Services"
        }
    ],
    "sg:phone":"+1 415 822 4024",
    "sg:postcode":"94124",
    "sg:province":"CA",
    "sg:tags":[
        "caterer"
    ],
    "sg:website":"www.ichisushi.com",
    "wof:name":"ICHI Catering",
    "wof:placetype":"venue"
},
  "geometry": {"coordinates":[-122.394582,37.724584],"type":"Point"}
}