{
  "type": "Feature",
  "properties": {
    "iso:country":"US",
    "sg:address":"5601 Hillsdale Blvd",
    "sg:city":"Sacramento",
    "sg:classifiers":[
        {
            "category":"Personal",
            "subcategory":"Beauty Salon",
            "type":"Services"
        }
    ],
    "sg:phone":"+1 916 334 6160",
    "sg:postcode":"95842",
    "sg:province":"CA",
    "wof:name":"J's Beauty",
    "wof:placetype":"venue"
},
  "geometry": {"coordinates":[-121.36207899999999,38.668587],"type":"Point"}
}