{
  "type": "Feature",
  "properties": {
    "iso:country":"US",
    "sg:address":"818 Carmel Ave",
    "sg:city":"Pacific Grove",
    "sg:classifiers":[
        {
            "category":"Wholesale",
            "subcategory":"Stationery",
            "type":"Manufacturing & Wholesale Goods"
        }
    ],
    "sg:phone":"+1 831 375 9985",
    "sg:postcode":"93950",
    "sg:province":"CA",
    "sg:tags":[
        "supply"
    ],
    "wof:name":"Mack Products",
    "wof:placetype":"venue"
},
  "geometry": {"coordinates":[-121.915808,36.612535],"type":"Point"}
}