{
  "type": "Feature",
  "properties": {
    "addr:full":"2642 Crenshaw Blvd Los Angeles CA 90016",
    "addr:housenumber":"2642",
    "addr:postcode":"90016",
    "addr:street":"Crenshaw Blvd",
    "iso:country":"US",
    "sg:address":"2642 Crenshaw Blvd",
    "sg:city":"Los Angeles",
    "sg:classifiers":[
        {
            "category":"Food & Beverages",
            "subcategory":"Liquor & Beverages",
            "type":"Retail Goods"
        }
    ],
    "sg:phone":"+1 323 735 0283",
    "sg:postcode":"90016",
    "sg:province":"CA",
    "sg:tags":[
        "beer",
        "spirit",
        "wine"
    ],
    "wof:name":"Bottle Bar Liquor Store",
    "wof:placetype":"venue"
},
  "geometry": {"coordinates":[-118.334999,34.031399],"type":"Point"}
}