{
  "type": "Feature",
  "properties": {
    "iso:country":"US",
    "sg:address":"670 W 17th St Ste G8",
    "sg:city":"Costa Mesa",
    "sg:classifiers":[
        {
            "category":"Restaurant",
            "type":"Food & Drink"
        }
    ],
    "sg:phone":"+1 949 645 8873",
    "sg:postcode":"92627",
    "sg:province":"CA",
    "sg:tags":[
        "seafood"
    ],
    "sg:website":"www.Catalinafishkitchen.com",
    "wof:name":"Catalina Fish Kitchen",
    "wof:placetype":"venue"
},
  "geometry": {"coordinates":[-117.926941,33.636438],"type":"Point"}
}