{
  "type": "Feature",
  "properties": {
    "iso:country":"US",
    "sg:address":"16542 Ventura Blvd",
    "sg:city":"Encino",
    "sg:classifiers":[
        {
            "category":"Retail",
            "subcategory":"Veterinary Services",
            "type":"Services"
        }
    ],
    "sg:phone":"+1 818 990 9381",
    "sg:postcode":"91436",
    "sg:province":"CA",
    "sg:tags":[
        "pet",
        "health",
        "plan",
        "for"
    ],
    "wof:name":"Petsaver Health Plan America",
    "wof:placetype":"venue"
},
  "geometry": {"coordinates":[-118.493514,34.157627],"type":"Point"}
}