{
  "type": "Feature",
  "properties": {
    "addr:full":"32285 Mission Trl Lake Elsinore CA 92530",
    "addr:housenumber":"32285",
    "addr:postcode":"92530",
    "addr:street":"Mission Trl",
    "iso:country":"US",
    "sg:address":"32285 Mission Trl",
    "sg:city":"Lake Elsinore",
    "sg:classifiers":[
        {
            "category":"Shopping",
            "subcategory":"Clothing, Apparel, & Fashions",
            "type":"Retail Goods"
        }
    ],
    "sg:phone":"+1 951 674 0737",
    "sg:postcode":"92530",
    "sg:province":"CA",
    "sg:tags":[
        "accessory",
        "clothing",
        "women's"
    ],
    "wof:name":"Fashion Art",
    "wof:placetype":"venue"
},
  "geometry": {"coordinates":[-117.296997,33.653599],"type":"Point"}
}