{
  "type": "Feature",
  "properties": {
    "addr:full":"660 W Wilson St Costa Mesa CA 92627",
    "addr:housenumber":"660",
    "addr:postcode":"92627",
    "addr:street":"W Wilson St",
    "iso:country":"US",
    "sg:address":"660 W Wilson St",
    "sg:city":"Costa Mesa",
    "sg:classifiers":[
        {
            "category":"Shopping",
            "subcategory":"Gifts & Souvenirs",
            "type":"Retail Goods"
        }
    ],
    "sg:phone":"+1 949 631 2638",
    "sg:postcode":"92627",
    "sg:province":"CA",
    "wof:name":"P R V Variety Enterprises",
    "wof:placetype":"venue"
},
  "geometry": {"coordinates":[-117.927126,33.656195],"type":"Point"}
}