{
  "type": "Feature",
  "properties": {
    "addr:full":"8408 Rochester Ave Rancho Cucamonga CA 91730",
    "addr:housenumber":"8408",
    "addr:postcode":"91730",
    "addr:street":"Rochester Ave",
    "iso:country":"US",
    "sg:address":"8408 Rochester Ave",
    "sg:city":"Rancho Cucamonga",
    "sg:classifiers":[
        {
            "category":"Recreation",
            "type":"Entertainment"
        }
    ],
    "sg:phone":"+1 909 481 5000",
    "sg:postcode":"91730",
    "sg:province":"CA",
    "sg:tags":[
        "club",
        "baseball"
    ],
    "sg:website":"www.rcquakes.com",
    "wof:name":"Rancho Cucamonga Quakes",
    "wof:placetype":"venue"
},
  "geometry": {"coordinates":[-117.545822,34.100194],"type":"Point"}
}