{
  "type": "Feature",
  "properties": {
    "addr:full":"180 Oak Dr Oak View CA 93022",
    "addr:housenumber":"180",
    "addr:postcode":"93022",
    "addr:street":"Oak Dr",
    "iso:country":"US",
    "sg:address":"180 Oak Dr",
    "sg:city":"Oak View",
    "sg:classifiers":[
        {
            "category":"Retail",
            "subcategory":"Repair Shop",
            "type":"Services"
        }
    ],
    "sg:phone":"+1 805 649 3898",
    "sg:postcode":"93022",
    "sg:province":"CA",
    "sg:tags":[
        "instrument",
        "musical"
    ],
    "wof:name":"Ojai Guitar Co",
    "wof:placetype":"venue"
},
  "geometry": {"coordinates":[-119.297156,34.402599],"type":"Point"}
}