{
  "type": "Feature",
  "properties": {
    "addr:full":"119 Garden Dr Bakersfield CA 93307",
    "addr:housenumber":"119",
    "addr:postcode":"93307",
    "addr:street":"Garden Dr",
    "iso:country":"US",
    "sg:address":"119 Garden Dr",
    "sg:city":"Bakersfield",
    "sg:classifiers":[
        {
            "category":"Building & Trades",
            "subcategory":"Construction",
            "type":"Services"
        }
    ],
    "sg:phone":"+1 661 397 9689",
    "sg:postcode":"93307",
    "sg:province":"CA",
    "sg:tags":[
        "designer",
        "dealer",
        "pool",
        "swimming"
    ],
    "wof:name":"Aloha Pools",
    "wof:placetype":"venue"
},
  "geometry": {"coordinates":[-118.994354,35.305811],"type":"Point"}
}