{
  "type": "Feature",
  "properties": {
    "addr:full":"10841 Modoc St Rancho Cucamonga CA 91701",
    "addr:housenumber":"10841",
    "addr:postcode":"91701",
    "addr:street":"Modoc St",
    "iso:country":"US",
    "sg:address":"10841 Modoc St",
    "sg:city":"Rancho Cucamonga",
    "sg:classifiers":[
        {
            "category":"Manufacturing",
            "subcategory":"Signs",
            "type":"Manufacturing & Wholesale Goods"
        }
    ],
    "sg:phone":"+1 909 989 2445",
    "sg:postcode":"91701",
    "sg:province":"CA",
    "sg:tags":[
        "specialty",
        "mfg"
    ],
    "wof:name":"Rocket Signs",
    "wof:placetype":"venue"
},
  "geometry": {"coordinates":[-117.569142,34.131939],"type":"Point"}
}