{
  "type": "Feature",
  "properties": {
    "addr:full":"13180 Casa Linda Ln Apt 14 Garden Grove CA 92844",
    "addr:housenumber":"13180;14",
    "addr:postcode":"92844",
    "addr:street":"Casa Linda Ln Apt",
    "iso:country":"US",
    "sg:address":"13180 Casa Linda Ln Apt 14",
    "sg:city":"Garden Grove",
    "sg:classifiers":[
        {
            "category":"Real Estate",
            "subcategory":"Real Estate Operator",
            "type":"Services"
        }
    ],
    "sg:phone":"+1 714 638 0360",
    "sg:postcode":"92844",
    "sg:province":"CA",
    "sg:tags":[
        "apartment"
    ],
    "wof:name":"Versailles Apartments",
    "wof:placetype":"venue"
},
  "geometry": {"coordinates":[-117.969002,33.771999],"type":"Point"}
}