{
  "type": "Feature",
  "properties": {
    "addr:full":"787 S Blossom Rd Waterford CA 95386",
    "addr:housenumber":"787",
    "addr:postcode":"95386",
    "addr:street":"S Blossom Rd",
    "iso:country":"US",
    "sg:address":"787 S Blossom Rd",
    "sg:city":"Waterford",
    "sg:classifiers":[
        {
            "category":"Building & Trades",
            "subcategory":"Construction",
            "type":"Services"
        }
    ],
    "sg:phone":"+1 209 523 0293",
    "sg:postcode":"95386",
    "sg:province":"CA",
    "sg:tags":[
        "maker",
        "cabinet"
    ],
    "wof:name":"Cowan Cabinet Co LLC",
    "wof:placetype":"venue"
},
  "geometry": {"coordinates":[-120.796724,37.633123],"type":"Point"}
}