{
  "type": "Feature",
  "properties": {
    "iso:country":"US",
    "sg:address":"1620 W El Camino Ave Ste 147",
    "sg:city":"Sacramento",
    "sg:classifiers":[
        {
            "category":"Restaurant",
            "type":"Food & Drink"
        }
    ],
    "sg:phone":"+1 916 922 7410",
    "sg:postcode":"95833",
    "sg:province":"CA",
    "sg:tags":[
        "thai",
        "asian",
        "pan"
    ],
    "wof:name":"Bangkok City Thai Cuisine",
    "wof:placetype":"venue"
},
  "geometry": {"coordinates":[-121.49819100000001,38.612689],"type":"Point"}
}