{
  "type": "Feature",
  "properties": {
    "iso:country":"US",
    "sg:address":"12770 High Bluff Drive",
    "sg:city":"San Diego",
    "sg:classifiers":[
        {
            "category":"Real Estate",
            "subcategory":"Real Estate Services",
            "type":"Services"
        }
    ],
    "sg:phone":"+1 858 350 1140",
    "sg:postcode":"92130",
    "sg:province":"CA",
    "sg:tags":[
        "management",
        "property"
    ],
    "wof:name":"Carramerica Realty",
    "wof:placetype":"venue"
},
  "geometry": {"coordinates":[-117.23924,32.950375],"type":"Point"}
}