{
  "type": "Feature",
  "properties": {
    "addr:full":"2703 Whitson St Selma CA 93662",
    "addr:housenumber":"2703",
    "addr:postcode":"93662",
    "addr:street":"Whitson St",
    "iso:country":"US",
    "sg:address":"2703 Whitson St",
    "sg:city":"Selma",
    "sg:classifiers":[
        {
            "category":"Personal",
            "type":"Services"
        }
    ],
    "sg:phone":"+1 559 898 0858",
    "sg:postcode":"93662",
    "sg:province":"CA",
    "sg:tags":[
        "control",
        "weight"
    ],
    "wof:name":"Slender Lady Of Selma",
    "wof:placetype":"venue"
},
  "geometry": {"coordinates":[-119.621759,36.573438],"type":"Point"}
}