{
  "type": "Feature",
  "properties": {
    "iso:country":"US",
    "sg:address":"2115 Beverly Blvd",
    "sg:city":"Los Angeles",
    "sg:classifiers":[
        {
            "category":"Organizations",
            "subcategory":"Non-profit Organization",
            "type":"Services"
        }
    ],
    "sg:phone":"+1 213 484 0868",
    "sg:postcode":"90057",
    "sg:province":"CA",
    "sg:tags":[
        "social"
    ],
    "wof:name":"Sendigan Adult Day Health Care",
    "wof:placetype":"venue"
},
  "geometry": {"coordinates":[-118.271171,34.067125],"type":"Point"}
}