{
  "type": "Feature",
  "properties": {
    "addr:full":"316 E Tulare Ave Tulare CA 93274",
    "addr:housenumber":"316",
    "addr:postcode":"93274",
    "addr:street":"E Tulare Ave",
    "iso:country":"US",
    "sg:address":"316 E Tulare Ave",
    "sg:city":"Tulare",
    "sg:classifiers":[
        {
            "category":"Banks & Credit Unions",
            "subcategory":"Bank",
            "type":"Services"
        }
    ],
    "sg:phone":"+1 559 687 1690",
    "sg:postcode":"93274",
    "sg:province":"CA",
    "sg:tags":[
        "loan",
        "real estate"
    ],
    "wof:name":"American Capital Mortgage",
    "wof:placetype":"venue"
},
  "geometry": {"coordinates":[-119.34425899999999,36.208436],"type":"Point"}
}