{
  "type": "Feature",
  "properties": {
    "addr:full":"5619 Hollywood Blvd Los Angeles CA 90028",
    "addr:housenumber":"5619",
    "addr:postcode":"90028",
    "addr:street":"Hollywood Blvd",
    "iso:country":"US",
    "sg:address":"5619 Hollywood Blvd",
    "sg:city":"Los Angeles",
    "sg:classifiers":[
        {
            "category":"Retail",
            "subcategory":"Auto Rental",
            "type":"Services"
        }
    ],
    "sg:phone":"+1 888 323 0303",
    "sg:postcode":"90028",
    "sg:province":"CA",
    "sg:tags":[
        "car"
    ],
    "sg:website":"hollywoodrac.com/",
    "wof:name":"Hollywood Rent A Car",
    "wof:placetype":"venue"
},
  "geometry": {"coordinates":[-118.312138,34.101742],"type":"Point"}
}