{
  "type": "Feature",
  "properties": {
    "iso:country":"US",
    "sg:address":"2349 Gambier Dr",
    "sg:city":"Pomona",
    "sg:classifiers":[
        {
            "category":"Wholesale",
            "subcategory":"Furniture",
            "type":"Manufacturing & Wholesale Goods"
        }
    ],
    "sg:phone":"+1 909 627 8785",
    "sg:postcode":"91766",
    "sg:province":"CA",
    "wof:name":"Laura Vela",
    "wof:placetype":"venue"
},
  "geometry": {"coordinates":[-117.752264,34.027844],"type":"Point"}
}