{
  "type": "Feature",
  "properties": {
    "addr:full":"4171 Lafayette Pl Culver City CA 90232",
    "addr:housenumber":"4171",
    "addr:postcode":"90232",
    "addr:street":"Lafayette Pl",
    "iso:country":"US",
    "sg:address":"4171 Lafayette Pl",
    "sg:city":"Culver City",
    "sg:classifiers":[
        {
            "category":"Real Estate",
            "subcategory":"Real Estate Agent",
            "type":"Services"
        }
    ],
    "sg:phone":"+1 310 837 9995",
    "sg:postcode":"90232",
    "sg:province":"CA",
    "wof:name":"Dreamfields",
    "wof:placetype":"venue"
},
  "geometry": {"coordinates":[-118.392493,34.020324],"type":"Point"}
}