{
  "type": "Feature",
  "properties": {
    "addr:full":"9669 Aero Dr San Diego CA 92123",
    "addr:housenumber":"9669",
    "addr:postcode":"92123",
    "addr:street":"Aero Dr",
    "iso:country":"US",
    "sg:address":"9669 Aero Dr",
    "sg:city":"San Diego",
    "sg:classifiers":[
        {
            "category":"Wholesale",
            "subcategory":"Apparel",
            "type":"Manufacturing & Wholesale Goods"
        }
    ],
    "sg:phone":"+1 858 277 7770",
    "sg:postcode":"92123",
    "sg:province":"CA",
    "sg:tags":[
        "upholstery",
        "fabric"
    ],
    "wof:name":"Keyston Brothers",
    "wof:placetype":"venue"
},
  "geometry": {"coordinates":[-117.12080400000001,32.808247],"type":"Point"}
}