{
  "type": "Feature",
  "properties": {
    "iso:country":"US",
    "sg:address":"9750 Airport Blvd",
    "sg:city":"Los Angeles",
    "sg:classifiers":[
        {
            "category":"Restaurant",
            "type":"Food & Drink"
        }
    ],
    "sg:phone":"+1 310 645 4600",
    "sg:postcode":"90045",
    "sg:province":"CA",
    "sg:tags":[
        "traditional",
        "american"
    ],
    "sg:website":"www.fourpointslax.com",
    "wof:name":"T.H. Brewsters in the Four Points Sheraton LAX",
    "wof:placetype":"venue"
},
  "geometry": {"coordinates":[-118.385989,33.947745],"type":"Point"}
}