{
  "type": "Feature",
  "properties": {
    "addr:full":"222 N 2nd St Porterville CA 93257",
    "addr:housenumber":"222",
    "addr:postcode":"93257",
    "addr:street":"N 2Nd St",
    "iso:country":"US",
    "sg:address":"222 N 2nd St",
    "sg:city":"Porterville",
    "sg:classifiers":[
        {
            "category":"Organizations",
            "subcategory":"Religious Organization",
            "type":"Services"
        }
    ],
    "sg:phone":"+1 559 782 0531",
    "sg:postcode":"93257",
    "sg:province":"CA",
    "sg:tags":[
        "church"
    ],
    "wof:name":"Porterville Believers Church",
    "wof:placetype":"venue"
},
  "geometry": {"coordinates":[-119.01512,36.070532],"type":"Point"}
}