{
  "type": "Feature",
  "properties": {
    "addr:full":"7454 Girard Ave La Jolla CA 92037",
    "addr:housenumber":"7454",
    "addr:postcode":"92037",
    "addr:street":"Girard Ave",
    "iso:country":"US",
    "sg:address":"7454 Girard Ave",
    "sg:city":"La Jolla",
    "sg:classifiers":[
        {
            "category":"Personal",
            "subcategory":"Nail Salon",
            "type":"Services"
        }
    ],
    "sg:phone":"+1 858 459 4740",
    "sg:postcode":"92037",
    "sg:province":"CA",
    "wof:name":"Girard Nail & Skin Care",
    "wof:placetype":"venue"
},
  "geometry": {"coordinates":[-117.272003,32.840199],"type":"Point"}
}