{
  "type": "Feature",
  "properties": {
    "addr:full":"5461 Ligurian Dr San Jose CA 95138",
    "addr:housenumber":"5461",
    "addr:postcode":"95138",
    "addr:street":"Ligurian Dr",
    "iso:country":"US",
    "sg:address":"5461 Ligurian Dr",
    "sg:city":"San Jose",
    "sg:classifiers":[
        {
            "category":"Professional",
            "type":"Services"
        }
    ],
    "sg:phone":"+1 408 238 0242",
    "sg:postcode":"95138",
    "sg:province":"CA",
    "wof:name":"Andreas O Goedde",
    "wof:placetype":"venue"
},
  "geometry": {"coordinates":[-121.765466,37.282667],"type":"Point"}
}