{
  "type": "Feature",
  "properties": {
    "iso:country":"US",
    "sg:address":"2105 S Juniper St",
    "sg:city":"Escondido",
    "sg:classifiers":[
        {
            "category":"Real Estate",
            "subcategory":"Real Estate Services",
            "type":"Services"
        },
        {
            "category":"Building & Trades",
            "subcategory":"Cleaning & Sanitation",
            "type":"Services"
        }
    ],
    "sg:phone":"+1 760 746 5587",
    "sg:postcode":"92025",
    "sg:province":"CA",
    "sg:tags":[
        "maintenance",
        "cleaners-interior"
    ],
    "wof:name":"Lm Commercial Cleaning Service",
    "wof:placetype":"venue"
},
  "geometry": {"coordinates":[-117.065245,33.099756],"type":"Point"}
}