{
  "type": "Feature",
  "properties": {
    "addr:full":"5008 Telegraph Ave Oakland CA 94609",
    "addr:housenumber":"5008",
    "addr:postcode":"94609",
    "addr:street":"Telegraph Ave",
    "iso:country":"US",
    "sg:address":"5008 Telegraph Ave",
    "sg:city":"Oakland",
    "sg:classifiers":[
        {
            "category":"Restaurant",
            "type":"Food & Drink"
        }
    ],
    "sg:phone":"+1 510 652 4888",
    "sg:postcode":"94609",
    "sg:province":"CA",
    "sg:tags":[
        "style",
        "italian",
        "family",
        "pizza"
    ],
    "sg:website":"www.pizzaiolooakland.com",
    "wof:name":"Pizzaiolo",
    "wof:placetype":"venue"
},
  "geometry": {"coordinates":[-122.262376,37.836622],"type":"Point"}
}