{
  "type": "Feature",
  "properties": {
    "addr:full":"3601 W Pico Blvd Los Angeles CA 90019",
    "addr:housenumber":"3601",
    "addr:postcode":"90019",
    "addr:street":"W Pico Blvd",
    "iso:country":"US",
    "sg:address":"3601 W Pico Blvd",
    "sg:city":"Los Angeles",
    "sg:classifiers":[
        {
            "category":"Restaurant",
            "type":"Food & Drink"
        },
        {
            "category":"Food & Beverages",
            "subcategory":"Meat & Fish",
            "type":"Retail Goods"
        }
    ],
    "sg:phone":"+1 323 730 1188",
    "sg:postcode":"90019",
    "sg:province":"CA",
    "sg:tags":[
        "seafood",
        "market"
    ],
    "wof:name":"Louisiana Pico Seafood",
    "wof:placetype":"venue"
},
  "geometry": {"coordinates":[-118.320086,34.047222],"type":"Point"}
}