{
  "type": "Feature",
  "properties": {
    "iso:country":"US",
    "sg:address":"3070 W Lincoln Ave Ste G",
    "sg:city":"Anaheim",
    "sg:classifiers":[
        {
            "category":"Arts & Performance",
            "subcategory":"Arts Center",
            "type":"Entertainment"
        }
    ],
    "sg:phone":"+1 714 527 7003",
    "sg:postcode":"92801",
    "sg:province":"CA",
    "sg:tags":[
        "performing"
    ],
    "wof:name":"Nonosina Polynesian Dance Studio",
    "wof:placetype":"venue"
},
  "geometry": {"coordinates":[-117.99700199999999,33.831902],"type":"Point"}
}