{
  "type": "Feature",
  "properties": {
    "addr:full":"4035 California Ave Norco CA 92860",
    "addr:housenumber":"4035",
    "addr:postcode":"92860",
    "addr:street":"California Ave",
    "iso:country":"US",
    "sg:address":"4035 California Ave",
    "sg:city":"Norco",
    "sg:classifiers":[
        {
            "category":"Building & Trades",
            "subcategory":"Plumbing",
            "type":"Services"
        }
    ],
    "sg:phone":"+1 951 371 0660",
    "sg:postcode":"92860",
    "sg:province":"CA",
    "sg:tags":[
        "contractor"
    ],
    "wof:name":"Arroyo Air Comfort",
    "wof:placetype":"venue"
},
  "geometry": {"coordinates":[-117.528105,33.941677],"type":"Point"}
}