{
  "type": "Feature",
  "properties": {
    "addr:full":"2600 Standiford Ave Apt B101 Modesto CA 95350",
    "addr:housenumber":"2600",
    "addr:postcode":"ca 95350",
    "addr:street":"Standiford Ave Apt B101",
    "iso:country":"US",
    "sg:address":"2600 Standiford Ave Apt B101",
    "sg:city":"Modesto",
    "sg:classifiers":[
        {
            "category":"Real Estate",
            "subcategory":"Real Estate Services",
            "type":"Services"
        },
        {
            "category":"Real Estate",
            "subcategory":"Real Estate Operator",
            "type":"Services"
        }
    ],
    "sg:phone":"+1 209 523 4152",
    "sg:postcode":"95350",
    "sg:province":"CA",
    "sg:tags":[
        "vacancy",
        "apartment",
        "rental",
        "listing"
    ],
    "wof:name":"Vinewood Apts. Senior Citizens",
    "wof:placetype":"venue"
},
  "geometry": {"coordinates":[-121.042939,37.685734],"type":"Point"}
}