{
  "type": "Feature",
  "properties": {
    "iso:country":"US",
    "sg:address":"7075 Mission Gorge Road",
    "sg:city":"San Diego",
    "sg:classifiers":[
        {
            "category":"Retail",
            "subcategory":"Repair Shop",
            "type":"Services"
        }
    ],
    "sg:phone":"+1 619 229 8540",
    "sg:postcode":"92120",
    "sg:province":"CA",
    "sg:tags":[
        "reupholstery",
        "furniture"
    ],
    "sg:website":"www.signstop.com",
    "wof:name":"Sign Stop",
    "wof:placetype":"venue"
},
  "geometry": {"coordinates":[-117.090656,32.800894],"type":"Point"}
}