{
  "type": "Feature",
  "properties": {
    "iso:country":"US",
    "sg:address":"123 W Plz",
    "sg:city":"Solana Beach",
    "sg:classifiers":[
        {
            "category":"Bars & Pubs",
            "type":"Food & Drink"
        }
    ],
    "sg:phone":"+1 858 755 5007",
    "sg:postcode":"92075",
    "sg:province":"CA",
    "wof:name":"McCaffrey's Pub",
    "wof:placetype":"venue"
},
  "geometry": {"coordinates":[-117.273279,32.991761],"type":"Point"}
}