{
  "type": "Feature",
  "properties": {
    "addr:full":"1330 Lander Ave Turlock CA 95380",
    "addr:housenumber":"1330",
    "addr:postcode":"95380",
    "addr:street":"Lander Ave",
    "iso:country":"US",
    "sg:address":"1330 Lander Ave",
    "sg:city":"Turlock",
    "sg:classifiers":[
        {
            "category":"Wholesale",
            "subcategory":"Motor Vehicles",
            "type":"Manufacturing & Wholesale Goods"
        }
    ],
    "sg:phone":"+1 209 667 0114",
    "sg:postcode":"95380",
    "sg:province":"CA",
    "sg:tags":[
        "automobile",
        "truck",
        "broker"
    ],
    "wof:name":"Automobile Brokers-Ca",
    "wof:placetype":"venue"
},
  "geometry": {"coordinates":[-120.848885,37.480554],"type":"Point"}
}