{
  "type": "Feature",
  "properties": {
    "iso:country":"US",
    "sg:address":"1431 Ocean Ave",
    "sg:city":"Santa Monica",
    "sg:classifiers":[
        {
            "category":"Insurance",
            "subcategory":"Insurance Agent",
            "type":"Services"
        }
    ],
    "sg:phone":"+1 310 395 5333",
    "sg:postcode":"90401",
    "sg:province":"CA",
    "wof:name":"Guarantee Life Co",
    "wof:placetype":"venue"
},
  "geometry": {"coordinates":[-118.496827,34.013203],"type":"Point"}
}