{
  "type": "Feature",
  "properties": {
    "iso:country":"US",
    "sg:address":"425 Elder Ave",
    "sg:city":"Seaside",
    "sg:classifiers":[
        {
            "category":"Professional",
            "type":"Services"
        }
    ],
    "sg:phone":"+1 831 583 0800",
    "sg:postcode":"93955",
    "sg:province":"CA",
    "sg:tags":[
        "arts",
        "artist"
    ],
    "wof:name":"P K Fine Artifacts",
    "wof:placetype":"venue"
},
  "geometry": {"coordinates":[-121.85232600000001,36.611807],"type":"Point"}
}