{
  "type": "Feature",
  "properties": {
    "iso:country":"US",
    "sg:address":"17032 Ave 296",
    "sg:city":"Farmersville",
    "sg:classifiers":[
        {
            "category":"Farming",
            "subcategory":"Livestock Farm",
            "type":"Manufacturing & Wholesale Goods"
        }
    ],
    "sg:phone":"+1 559 592 0114",
    "sg:postcode":"93292",
    "sg:province":"CA",
    "sg:tags":[
        "ranch"
    ],
    "wof:name":"Double R Ranch",
    "wof:placetype":"venue"
},
  "geometry": {"coordinates":[-119.19183,36.326806],"type":"Point"}
}