{
  "type": "Feature",
  "properties": {
    "iso:country":"US",
    "sg:address":"1116 E 1st St",
    "sg:city":"Stockton",
    "sg:classifiers":[
        {
            "category":"Government",
            "subcategory":"Fire Station",
            "type":"Public Place"
        }
    ],
    "sg:phone":"+1 209 462 1386",
    "sg:postcode":"95206",
    "sg:province":"CA",
    "sg:tags":[
        "consultant",
        "protection"
    ],
    "wof:name":"Fire Dept",
    "wof:placetype":"venue"
},
  "geometry": {"coordinates":[-121.272175,37.940128],"type":"Point"}
}