{
  "type": "Feature",
  "properties": {
    "iso:country":"US",
    "sg:address":"222 W Eulalia St Ste 300",
    "sg:city":"Glendale",
    "sg:classifiers":[
        {
            "category":"Health Services",
            "subcategory":"Doctor",
            "type":"Services"
        }
    ],
    "sg:phone":"+1 818 547 0608",
    "sg:postcode":"91204",
    "sg:province":"CA",
    "sg:tags":[
        "orthopedist"
    ],
    "sg:website":"www.glendaleorthopaedics.com",
    "wof:name":"Vahan Cepkinian, MD",
    "wof:placetype":"venue"
},
  "geometry": {"coordinates":[-118.256891,34.126559],"type":"Point"}
}