{
  "type": "Feature",
  "properties": {
    "addr:full":"290 E Compton Blvd Compton CA 90220",
    "addr:housenumber":"290",
    "addr:postcode":"90220",
    "addr:street":"E Compton Blvd",
    "iso:country":"US",
    "sg:address":"290 E Compton Blvd",
    "sg:city":"Compton",
    "sg:classifiers":[
        {
            "category":"Restaurant",
            "type":"Food & Drink"
        }
    ],
    "sg:phone":"+1 310 635 6345",
    "sg:postcode":"90220",
    "sg:province":"CA",
    "wof:name":"Burger King",
    "wof:placetype":"venue"
},
  "geometry": {"coordinates":[-118.27383399999999,33.89488],"type":"Point"}
}