{
  "type": "Feature",
  "properties": {
    "addr:full":"29628 Anthony Rd Valley Center CA 92082",
    "addr:housenumber":"29628",
    "addr:postcode":"92082",
    "addr:street":"Anthony Rd",
    "iso:country":"US",
    "sg:address":"29628 Anthony Rd",
    "sg:city":"Valley Center",
    "sg:classifiers":[
        {
            "category":"Recreation",
            "type":"Entertainment"
        }
    ],
    "sg:phone":"+1 760 751 3493",
    "sg:postcode":"92082",
    "sg:province":"CA",
    "sg:tags":[
        "stable"
    ],
    "wof:name":"Hidden Valley Horse Care",
    "wof:placetype":"venue"
},
  "geometry": {"coordinates":[-117.050848,33.247177],"type":"Point"}
}