{
  "type": "Feature",
  "properties": {
    "addr:full":"36318 Tunbridge Dr Newark CA 94560",
    "addr:postcode":"36318;94560",
    "addr:street":"Tunbridge Dr",
    "iso:country":"US",
    "sg:address":"36318 Tunbridge Dr",
    "sg:city":"Newark",
    "sg:classifiers":[
        {
            "category":"Wholesale",
            "subcategory":"Groceries",
            "type":"Manufacturing & Wholesale Goods"
        }
    ],
    "sg:phone":"+1 510 742 8908",
    "sg:postcode":"94560",
    "sg:province":"CA",
    "sg:tags":[
        "general"
    ],
    "wof:name":"Cbk USA",
    "wof:placetype":"venue"
},
  "geometry": {"coordinates":[-122.02810700000001,37.551517],"type":"Point"}
}