{
  "type": "Feature",
  "properties": {
    "iso:country":"US",
    "sg:address":"12892 Bubbling Well Rd",
    "sg:city":"Santa Ana",
    "sg:classifiers":[
        {
            "category":"Home & Garden",
            "subcategory":"Furniture",
            "type":"Retail Goods"
        }
    ],
    "sg:phone":"+1 714 665 3383",
    "sg:postcode":"92705",
    "sg:province":"CA",
    "sg:tags":[
        "store"
    ],
    "sg:website":"www.spacebetween.com",
    "wof:name":"Space Between the",
    "wof:placetype":"venue"
},
  "geometry": {"coordinates":[-117.797997,33.741402],"type":"Point"}
}