{
  "type": "Feature",
  "properties": {
    "iso:country":"US",
    "sg:address":"724 E Carson St",
    "sg:city":"Carson",
    "sg:classifiers":[
        {
            "category":"Insurance",
            "subcategory":"Hazard Insurance",
            "type":"Services"
        }
    ],
    "sg:phone":"+1 310 549 0033",
    "sg:postcode":"90745",
    "sg:province":"CA",
    "sg:tags":[
        "bond"
    ],
    "wof:name":"Carson Bail Bonds",
    "wof:placetype":"venue"
},
  "geometry": {"coordinates":[-118.262513,33.831535],"type":"Point"}
}