{
  "type": "Feature",
  "properties": {
    "iso:country":"US",
    "sg:address":"440 Canyon Dr",
    "sg:city":"Oceanside",
    "sg:classifiers":[
        {
            "category":"Wholesale",
            "subcategory":"Sporting Goods",
            "type":"Manufacturing & Wholesale Goods"
        }
    ],
    "sg:phone":"+1 760 415 0678",
    "sg:postcode":"92054",
    "sg:province":"CA",
    "wof:name":"Cor",
    "wof:placetype":"venue"
},
  "geometry": {"coordinates":[-117.35390599999999,33.197306],"type":"Point"}
}