{
  "type": "Feature",
  "properties": {
    "addr:full":"8732 Imperial Hwy Downey CA 90242",
    "addr:housenumber":"8732",
    "addr:postcode":"90242",
    "addr:street":"Imperial Hwy",
    "iso:country":"US",
    "sg:address":"8732 Imperial Hwy",
    "sg:city":"Downey",
    "sg:classifiers":[
        {
            "category":"Personal",
            "subcategory":"Beauty Salon",
            "type":"Services"
        }
    ],
    "sg:phone":"+1 562 869 4760",
    "sg:postcode":"90242",
    "sg:province":"CA",
    "wof:name":"Sunny Beauty Salon",
    "wof:placetype":"venue"
},
  "geometry": {"coordinates":[-118.139989,33.91768],"type":"Point"}
}