{
  "type": "Feature",
  "properties": {
    "iso:country":"US",
    "sg:address":"405 Sherman Ave",
    "sg:city":"Palo Alto",
    "sg:classifiers":[
        {
            "category":"Professional",
            "subcategory":"Lawyer & Legal Services",
            "type":"Services"
        }
    ],
    "sg:phone":"+1 650 326 8322",
    "sg:postcode":"94306",
    "sg:province":"CA",
    "wof:name":"Palo Alto Area Bar Assn",
    "wof:placetype":"venue"
},
  "geometry": {"coordinates":[-122.144699,37.424605],"type":"Point"}
}