{
  "type": "Feature",
  "properties": {
    "addr:full":"2967 Michelson Drive, Unit G301 Irvine CA 92612",
    "addr:postcode":"2967;92612",
    "addr:street":"Michelson Drive Unit G301",
    "iso:country":"US",
    "sg:address":"2967 Michelson Drive, Unit G301",
    "sg:city":"Irvine",
    "sg:classifiers":[
        {
            "category":"Shopping",
            "subcategory":"Used Merchandise",
            "type":"Retail Goods"
        }
    ],
    "sg:phone":"+1 949 500 8343",
    "sg:postcode":"92612",
    "sg:province":"CA",
    "sg:tags":[
        "computer"
    ],
    "sg:website":"http://www.gogreenewaste.com",
    "wof:name":"GO GREEN EWASTE RECYCLERS",
    "wof:placetype":"venue"
},
  "geometry": {"coordinates":[-117.845564,33.671297],"type":"Point"}
}