{
  "type": "Feature",
  "properties": {
    "iso:country":"US",
    "sg:address":"1600 W Slauson Ave",
    "sg:city":"Los Angeles",
    "sg:classifiers":[
        {
            "category":"Professional",
            "type":"Services"
        }
    ],
    "sg:phone":"+1 323 565 3436",
    "sg:postcode":"90047",
    "sg:province":"CA",
    "wof:name":"Kim Ki Sup",
    "wof:placetype":"venue"
},
  "geometry": {"coordinates":[-118.306311,33.989122],"type":"Point"}
}