{
  "type": "Feature",
  "properties": {
    "addr:full":"3225 Zinfandel Dr Ste 2 Rancho Cordova CA 95670",
    "addr:housenumber":"3225",
    "addr:postcode":"95670",
    "addr:street":"Zinfandel Dr Ste 2",
    "iso:country":"US",
    "sg:address":"3225 Zinfandel Dr Ste 2",
    "sg:city":"Rancho Cordova",
    "sg:classifiers":[
        {
            "category":"Personal",
            "type":"Services"
        }
    ],
    "sg:phone":"+1 916 858 2323",
    "sg:postcode":"95670",
    "sg:province":"CA",
    "sg:tags":[
        "mover"
    ],
    "sg:website":"subway.com",
    "wof:name":"Subway",
    "wof:placetype":"venue"
},
  "geometry": {"coordinates":[-121.285372,38.583706],"type":"Point"}
}