{
  "type": "Feature",
  "properties": {
    "addr:full":"250 E Gish Rd San Jose CA 95112",
    "addr:housenumber":"250",
    "addr:postcode":"95112",
    "addr:street":"E Gish Rd",
    "iso:country":"US",
    "sg:address":"250 E Gish Rd",
    "sg:city":"San Jose",
    "sg:classifiers":[
        {
            "category":"Manufacturing",
            "subcategory":"Electronics",
            "type":"Manufacturing & Wholesale Goods"
        }
    ],
    "sg:phone":"+1 408 487 1700",
    "sg:postcode":"95112",
    "sg:province":"CA",
    "sg:tags":[
        "semiconductor",
        "related",
        "devices"
    ],
    "wof:name":"Us Export Authority Inc",
    "wof:placetype":"venue"
},
  "geometry": {"coordinates":[-121.90516599999999,37.364067],"type":"Point"}
}