{
  "type": "Feature",
  "properties": {
    "addr:full":"2735 Marconi Ave Sacramento CA 95821",
    "addr:housenumber":"2735",
    "addr:postcode":"95821",
    "addr:street":"Marconi Ave",
    "iso:country":"US",
    "sg:address":"2735 Marconi Ave",
    "sg:city":"Sacramento",
    "sg:classifiers":[
        {
            "category":"Bakery",
            "type":"Food & Drink"
        }
    ],
    "sg:phone":"+1 916 487 4049",
    "sg:postcode":"95821",
    "sg:province":"CA",
    "wof:name":"Juan Tamayo",
    "wof:placetype":"venue"
},
  "geometry": {"coordinates":[-121.39833900000001,38.617985],"type":"Point"}
}