{
  "type": "Feature",
  "properties": {
    "iso:country":"US",
    "sg:address":"10 N Almaden Ave",
    "sg:city":"San Jose",
    "sg:classifiers":[
        {
            "category":"Parking",
            "type":"Transportation"
        }
    ],
    "sg:phone":"+1 408 298 5367",
    "sg:postcode":"95110",
    "sg:province":"CA",
    "sg:website":"www.abm.com",
    "wof:name":"Ampco System Parking",
    "wof:placetype":"venue"
},
  "geometry": {"coordinates":[-121.896692,37.335487],"type":"Point"}
}