{
  "type": "Feature",
  "properties": {
    "addr:full":"733 W Harvard Blvd Santa Paula CA 93060",
    "addr:housenumber":"733",
    "addr:postcode":"93060",
    "addr:street":"W Harvard Blvd",
    "iso:country":"US",
    "sg:address":"733 W Harvard Blvd",
    "sg:city":"Santa Paula",
    "sg:classifiers":[
        {
            "category":"Banks & Credit Unions",
            "subcategory":"Bank",
            "type":"Services"
        }
    ],
    "sg:phone":"+1 805 933 4050",
    "sg:postcode":"93060",
    "sg:province":"CA",
    "sg:tags":[
        "loan",
        "real estate"
    ],
    "wof:name":"Tafoya Realty",
    "wof:placetype":"venue"
},
  "geometry": {"coordinates":[-119.083754,34.341043],"type":"Point"}
}