{
  "type": "Feature",
  "properties": {
    "addr:full":"14656 Road 192 Porterville CA 93257",
    "addr:housenumber":"14656",
    "addr:postcode":"93257",
    "addr:street":"Road 192",
    "iso:country":"US",
    "sg:address":"14656 Road 192",
    "sg:city":"Porterville",
    "sg:classifiers":[
        {
            "category":"Social Services",
            "type":"Services"
        }
    ],
    "sg:phone":"+1 559 784 7009",
    "sg:postcode":"93257",
    "sg:province":"CA",
    "wof:name":"Poplar Community Service District",
    "wof:placetype":"venue"
},
  "geometry": {"coordinates":[-119.143117,36.056001],"type":"Point"}
}