{
  "type": "Feature",
  "properties": {
    "addr:full":"9878 Hibert St San Diego CA 92131",
    "addr:housenumber":"9878",
    "addr:postcode":"92131",
    "addr:street":"Hibert St",
    "iso:country":"US",
    "sg:address":"9878 Hibert St",
    "sg:city":"San Diego",
    "sg:classifiers":[
        {
            "category":"Real Estate",
            "subcategory":"Real Estate Agent",
            "type":"Services"
        }
    ],
    "sg:phone":"+1 858 547 6026",
    "sg:postcode":"92131",
    "sg:province":"CA",
    "wof:name":"Prudential California Real Est",
    "wof:placetype":"venue"
},
  "geometry": {"coordinates":[-117.11122899999999,32.913908],"type":"Point"}
}