{
  "type": "Feature",
  "properties": {
    "iso:country":"US",
    "sg:address":"13052 Ave 440",
    "sg:city":"Orosi",
    "sg:classifiers":[
        {
            "category":"Farming",
            "subcategory":"Orchard",
            "type":"Manufacturing & Wholesale Goods"
        }
    ],
    "sg:phone":"+1 559 528 3969",
    "sg:postcode":"93647",
    "sg:province":"CA",
    "sg:tags":[
        "citrus",
        "grove",
        "fruit"
    ],
    "wof:name":"Dennis Howard",
    "wof:placetype":"venue"
},
  "geometry": {"coordinates":[-119.279499,36.587924],"type":"Point"}
}