{
  "type": "Feature",
  "properties": {
    "addr:full":"25125 Santa Clara St Hayward CA 94544",
    "addr:postcode":"25125;94544",
    "addr:street":"Santa Clara St",
    "iso:country":"US",
    "sg:address":"25125 Santa Clara St",
    "sg:city":"Hayward",
    "sg:classifiers":[
        {
            "category":"Manufacturing",
            "subcategory":"Textiles",
            "type":"Manufacturing & Wholesale Goods"
        }
    ],
    "sg:phone":"+1 925 277 7780",
    "sg:postcode":"94544",
    "sg:province":"CA",
    "sg:tags":[
        "mfg"
    ],
    "wof:name":"Analytical Component Serv",
    "wof:placetype":"venue"
},
  "geometry": {"coordinates":[-122.090059,37.648834],"type":"Point"}
}