{
  "type": "Feature",
  "properties": {
    "addr:full":"106 Airport Blvd Freedom CA 95019",
    "addr:housenumber":"106",
    "addr:postcode":"95019",
    "addr:street":"Airport Blvd",
    "iso:country":"US",
    "sg:address":"106 Airport Blvd",
    "sg:city":"Freedom",
    "sg:classifiers":[
        {
            "category":"Manufacturing",
            "subcategory":"Apparel",
            "type":"Manufacturing & Wholesale Goods"
        }
    ],
    "sg:phone":"+1 831 761 0549",
    "sg:postcode":"95019",
    "sg:province":"CA",
    "wof:name":"Stitch N Press",
    "wof:placetype":"venue"
},
  "geometry": {"coordinates":[-121.777912,36.938344],"type":"Point"}
}