{
  "type": "Feature",
  "properties": {
    "addr:full":"28900 Bay Ave Moreno Valley CA 92555",
    "addr:housenumber":"28900",
    "addr:postcode":"92555",
    "addr:street":"Bay Ave",
    "iso:country":"US",
    "sg:address":"28900 Bay Ave",
    "sg:city":"Moreno Valley",
    "sg:classifiers":[
        {
            "category":"Manufacturing",
            "subcategory":"Tools & Machinery",
            "type":"Manufacturing & Wholesale Goods"
        }
    ],
    "sg:phone":"+1 951 485 6960",
    "sg:postcode":"92555",
    "sg:province":"CA",
    "sg:tags":[
        "product",
        "mfg",
        "plastic"
    ],
    "wof:name":"G E T Precision Molds",
    "wof:placetype":"venue"
},
  "geometry": {"coordinates":[-117.156677,33.921012],"type":"Point"}
}