{
  "type": "Feature",
  "properties": {
    "iso:country":"US",
    "sg:address":"2124 Taraval St",
    "sg:city":"San Francisco",
    "sg:classifiers":[
        {
            "category":"Real Estate",
            "subcategory":"Real Estate Agent",
            "type":"Services"
        }
    ],
    "sg:phone":"+1 415 682 2888",
    "sg:postcode":"94116",
    "sg:province":"CA",
    "sg:website":"www.evergreen-re.com",
    "wof:name":"Evergreen Realty Inc",
    "wof:placetype":"venue"
},
  "geometry": {"coordinates":[-122.489416,37.742523],"type":"Point"}
}