{
  "type": "Feature",
  "properties": {
    "iso:country":"US",
    "sg:address":"3288 Firtree Way",
    "sg:city":"Paso Robles",
    "sg:classifiers":[
        {
            "category":"Retail",
            "subcategory":"Auto Repair",
            "type":"Services"
        }
    ],
    "sg:phone":"+1 805 434 2456",
    "sg:postcode":"93446",
    "sg:province":"CA",
    "sg:tags":[
        "machine",
        "automobile",
        "shop"
    ],
    "wof:name":"Alternative Performance",
    "wof:placetype":"venue"
},
  "geometry": {"coordinates":[-120.70442,35.573771],"type":"Point"}
}