{
  "type": "Feature",
  "properties": {
    "iso:country":"US",
    "sg:address":"2350 Mission College Blvd Ste 800",
    "sg:city":"Santa Clara",
    "sg:classifiers":[
        {
            "category":"Professional",
            "subcategory":"Employment Agencies",
            "type":"Services"
        }
    ],
    "sg:phone":"+1 408 844 9101",
    "sg:postcode":"95054",
    "sg:province":"CA",
    "sg:website":"www.accountemps.com",
    "wof:name":"Accountemps",
    "wof:placetype":"venue"
},
  "geometry": {"coordinates":[-121.966003,37.388802],"type":"Point"}
}