{
  "type": "Feature",
  "properties": {
    "addr:full":"2842 Sherwin Ave Ventura CA 93003",
    "addr:housenumber":"2842",
    "addr:postcode":"93003",
    "addr:street":"Sherwin Ave",
    "iso:country":"US",
    "sg:address":"2842 Sherwin Ave",
    "sg:city":"Ventura",
    "sg:classifiers":[
        {
            "category":"Manufacturing",
            "subcategory":"Tools & Machinery",
            "type":"Manufacturing & Wholesale Goods"
        }
    ],
    "sg:phone":"+1 805 642 3281",
    "sg:postcode":"93003",
    "sg:province":"CA",
    "sg:tags":[
        "machine",
        "shop",
        "industrial",
        "mfg"
    ],
    "wof:name":"Double H Precision Machining",
    "wof:placetype":"venue"
},
  "geometry": {"coordinates":[-119.198745,34.250147],"type":"Point"}
}