{
  "type": "Feature",
  "properties": {
    "addr:full":"780 San Ramon Valley Blvd Danville CA 94583",
    "addr:housenumber":"780",
    "addr:postcode":"94583",
    "addr:street":"San Ramon Valley Blvd",
    "iso:country":"US",
    "sg:address":"780 San Ramon Valley Blvd",
    "sg:city":"Danville",
    "sg:classifiers":[
        {
            "category":"Manufacturing",
            "subcategory":"Jewelry",
            "type":"Manufacturing & Wholesale Goods"
        },
        {
            "category":"Wholesale",
            "subcategory":"Jewelry",
            "type":"Manufacturing & Wholesale Goods"
        }
    ],
    "sg:phone":"+1 925 855 0448",
    "sg:postcode":"94583",
    "sg:province":"CA",
    "sg:tags":[
        "stone",
        "diamond",
        "mfg",
        "metal",
        "buyer",
        "precious"
    ],
    "wof:name":"Sam Bloch Jewelers",
    "wof:placetype":"venue"
},
  "geometry": {"coordinates":[-121.99508299999999,37.811022],"type":"Point"}
}