{
  "type": "Feature",
  "properties": {
    "iso:country":"US",
    "sg:address":"140 Calistoga Rd",
    "sg:city":"Santa Rosa",
    "sg:classifiers":[
        {
            "category":"Restaurant",
            "type":"Food & Drink"
        }
    ],
    "sg:menulink":"http://www.allmenus.com/ca/santa-rosa/77846-papa-murphys/menu/",
    "sg:phone":"+1 707 538 8880",
    "sg:postcode":"95409",
    "sg:province":"CA",
    "sg:tags":[
        "american",
        "pizza"
    ],
    "wof:name":"Papa Murphy's",
    "wof:placetype":"venue"
},
  "geometry": {"coordinates":[-122.653407,38.465309],"type":"Point"}
}