{
  "type": "Feature",
  "properties": {
    "iso:country":"US",
    "sg:address":"25710 Taylor Rd",
    "sg:city":"Perris",
    "sg:classifiers":[
        {
            "category":"Home & Garden",
            "subcategory":"Home Furnishings",
            "type":"Retail Goods"
        }
    ],
    "sg:phone":"+1 951 657 4793",
    "sg:postcode":"92570",
    "sg:province":"CA",
    "wof:name":"L J R Stove Works",
    "wof:placetype":"venue"
},
  "geometry": {"coordinates":[-117.275292,33.747474],"type":"Point"}
}