{
  "type": "Feature",
  "properties": {
    "addr:full":"24 Menker St Watsonville CA 95076",
    "addr:housenumber":"24",
    "addr:postcode":"95076",
    "addr:street":"Menker St",
    "iso:country":"US",
    "sg:address":"24 Menker St",
    "sg:city":"Watsonville",
    "sg:classifiers":[
        {
            "category":"Building & Trades",
            "subcategory":"Construction",
            "type":"Services"
        }
    ],
    "sg:phone":"+1 831 722 2220",
    "sg:postcode":"95076",
    "sg:province":"CA",
    "sg:tags":[
        "carpentry",
        "contractor"
    ],
    "wof:name":"Bfd Inc",
    "wof:placetype":"venue"
},
  "geometry": {"coordinates":[-121.75672299999999,36.905761],"type":"Point"}
}