{
  "type": "Feature",
  "properties": {
    "addr:full":"1044 Walnutwood Ct Los Banos CA 93635",
    "addr:housenumber":"1044",
    "addr:postcode":"93635",
    "addr:street":"Walnutwood Ct",
    "iso:country":"US",
    "sg:address":"1044 Walnutwood Ct",
    "sg:city":"Los Banos",
    "sg:classifiers":[
        {
            "category":"Professional",
            "subcategory":"Accounting & Tax Preparation",
            "type":"Services"
        }
    ],
    "sg:phone":"+1 209 826 9273",
    "sg:postcode":"93635",
    "sg:province":"CA",
    "sg:tags":[
        "bookkeeping",
        "general"
    ],
    "wof:name":"Virginia Tax Preperation",
    "wof:placetype":"venue"
},
  "geometry": {"coordinates":[-120.841078,37.079121],"type":"Point"}
}