{
  "type": "Feature",
  "properties": {
    "iso:country":"US",
    "sg:address":"3616 Gage Ave",
    "sg:city":"Bell",
    "sg:classifiers":[
        {
            "category":"Personal",
            "subcategory":"Barber",
            "type":"Services"
        }
    ],
    "sg:phone":"+1 323 588 2923",
    "sg:postcode":"90201",
    "sg:province":"CA",
    "wof:name":"Aly's Hairstyle",
    "wof:placetype":"venue"
},
  "geometry": {"coordinates":[-118.200495,33.97939],"type":"Point"}
}