{
  "type": "Feature",
  "properties": {
    "iso:country":"US",
    "sg:address":"934 Venice Blvd",
    "sg:city":"Los Angeles",
    "sg:classifiers":[
        {
            "category":"Professional",
            "subcategory":"Printing & Photocopies",
            "type":"Services"
        }
    ],
    "sg:phone":"+1 213 745 3145",
    "sg:postcode":"90015",
    "sg:province":"CA",
    "sg:tags":[
        "photocopying",
        "design",
        "commercial"
    ],
    "sg:website":"www.fordgraphics.com",
    "wof:name":"Ford Graphics",
    "wof:placetype":"venue"
},
  "geometry": {"coordinates":[-118.277,34.0406],"type":"Point"}
}