{
  "type": "Feature",
  "properties": {
    "addr:full":"66 Antelope St Woodland CA 95695",
    "addr:housenumber":"66",
    "addr:postcode":"95695",
    "addr:street":"Antelope St",
    "iso:country":"US",
    "sg:address":"66 Antelope St",
    "sg:city":"Woodland",
    "sg:classifiers":[
        {
            "category":"Retail",
            "subcategory":"Repair Shop",
            "type":"Services"
        }
    ],
    "sg:phone":"+1 530 662 6392",
    "sg:postcode":"95695",
    "sg:province":"CA",
    "wof:name":"Cesareos Gunsmith & Sale",
    "wof:placetype":"venue"
},
  "geometry": {"coordinates":[-121.785782,38.684116],"type":"Point"}
}