{
  "type": "Feature",
  "properties": {
    "addr:full":"9850 Lewis Ave Fountain Valley CA 92708",
    "addr:housenumber":"9850",
    "addr:postcode":"92708",
    "addr:street":"Lewis Ave",
    "iso:country":"US",
    "sg:address":"9850 Lewis Ave",
    "sg:city":"Fountain Valley",
    "sg:classifiers":[
        {
            "category":"Manufacturing",
            "subcategory":"Printing",
            "type":"Manufacturing & Wholesale Goods"
        }
    ],
    "sg:phone":"+1 714 965 4570",
    "sg:postcode":"92708",
    "sg:province":"CA",
    "sg:tags":[
        "publishing"
    ],
    "wof:name":"Pocket Reference Journals Inc",
    "wof:placetype":"venue"
},
  "geometry": {"coordinates":[-117.957469,33.699016],"type":"Point"}
}