{
  "type": "Feature",
  "properties": {
    "iso:country":"US",
    "sg:address":"7525 Fairmount Ave",
    "sg:city":"El Cerrito",
    "sg:classifiers":[
        {
            "category":"Restaurant",
            "type":"Food & Drink"
        }
    ],
    "sg:phone":"+1 510 528 3433",
    "sg:postcode":"94530",
    "sg:province":"CA",
    "sg:tags":[
        "traditional",
        "american"
    ],
    "wof:name":"Fat Apple's Restaurant & Bakery",
    "wof:placetype":"venue"
},
  "geometry": {"coordinates":[-122.291488,37.904321],"type":"Point"}
}