{
  "type": "Feature",
  "properties": {
    "addr:full":"23720 Arlington Ave Torrance CA 90501",
    "addr:housenumber":"23720",
    "addr:postcode":"90501",
    "addr:street":"Arlington Ave",
    "iso:country":"US",
    "sg:address":"23720 Arlington Ave",
    "sg:city":"Torrance",
    "sg:classifiers":[
        {
            "category":"Professional",
            "subcategory":"Management & Consulting",
            "type":"Services"
        }
    ],
    "sg:phone":"+1 951 681 3327",
    "sg:postcode":"90501",
    "sg:province":"CA",
    "sg:tags":[
        "consultant",
        "business"
    ],
    "wof:name":"TLM Consulting",
    "wof:placetype":"venue"
},
  "geometry": {"coordinates":[-118.31983200000001,33.808904],"type":"Point"}
}