{
  "type": "Feature",
  "properties": {
    "addr:full":"491 Hardy Street Oakland CA 94618",
    "addr:housenumber":"491",
    "addr:postcode":"94618",
    "addr:street":"Hardy Street",
    "iso:country":"US",
    "sg:address":"491 Hardy Street",
    "sg:city":"Oakland",
    "sg:classifiers":[
        {
            "category":"Park",
            "type":"Public Place"
        }
    ],
    "sg:postcode":"94618",
    "sg:province":"CA",
    "sg:website":"www.oaklandnet.com/parks/facilit...",
    "wof:name":"Hardy Dog Park",
    "wof:placetype":"venue"
},
  "geometry": {"coordinates":[-122.25700399999999,37.8419],"type":"Point"}
}