{
  "type": "Feature",
  "properties": {
    "iso:country":"US",
    "sg:address":"660 Hawkcrest Cir",
    "sg:city":"Sacramento",
    "sg:classifiers":[
        {
            "category":"Education",
            "subcategory":"Preschool",
            "type":"Public Place"
        }
    ],
    "sg:phone":"+1 916 949 9989",
    "sg:postcode":"95835",
    "sg:province":"CA",
    "sg:tags":[
        "kindergarten"
    ],
    "wof:name":"Kool Kids Preschool",
    "wof:placetype":"venue"
},
  "geometry": {"coordinates":[-121.547141,38.663379],"type":"Point"}
}