{
  "type": "Feature",
  "properties": {
    "iso:country":"US",
    "sg:address":"5772 E Jurupa St",
    "sg:city":"Ontario",
    "sg:classifiers":[
        {
            "category":"Wholesale",
            "subcategory":"Groceries",
            "type":"Manufacturing & Wholesale Goods"
        }
    ],
    "sg:phone":"+1 909 974 0700",
    "sg:postcode":"91761",
    "sg:province":"CA",
    "wof:name":"Arrowhead Spring Water",
    "wof:placetype":"venue"
},
  "geometry": {"coordinates":[-117.525986,34.046904],"type":"Point"}
}