{
  "type": "Feature",
  "properties": {
    "addr:full":"12814 Maxella Ave Los Angeles CA 90066",
    "addr:housenumber":"12814",
    "addr:postcode":"90066",
    "addr:street":"Maxella Ave",
    "iso:country":"US",
    "sg:address":"12814 Maxella Ave",
    "sg:city":"Los Angeles",
    "sg:classifiers":[
        {
            "category":"Education",
            "subcategory":"School",
            "type":"Public Place"
        }
    ],
    "sg:phone":"+1 310 397 4234",
    "sg:postcode":"90066",
    "sg:province":"CA",
    "sg:website":"www.lausd.k12.ca.us",
    "wof:name":"Short Avenue Elementary School",
    "wof:placetype":"venue"
},
  "geometry": {"coordinates":[-118.43294899999999,33.990832],"type":"Point"}
}