{
  "type": "Feature",
  "properties": {
    "addr:full":"1190 Russell Way Hayward CA 94541",
    "addr:housenumber":"1190",
    "addr:postcode":"94541",
    "addr:street":"Russell Way",
    "iso:country":"US",
    "sg:address":"1190 Russell Way",
    "sg:city":"Hayward",
    "sg:classifiers":[
        {
            "category":"Sports & Exercise",
            "subcategory":"Gym",
            "type":"Entertainment"
        }
    ],
    "sg:phone":"+1 510 728 8043",
    "sg:postcode":"94541",
    "sg:province":"CA",
    "sg:tags":[
        "fitness",
        "program",
        "physical"
    ],
    "wof:name":"Brick Oasis",
    "wof:placetype":"venue"
},
  "geometry": {"coordinates":[-122.08107800000001,37.67704],"type":"Point"}
}