{
  "type": "Feature",
  "properties": {
    "iso:country":"US",
    "sg:address":"101 Main St",
    "sg:city":"Huntington Beach",
    "sg:classifiers":[
        {
            "category":"Professional",
            "subcategory":"Business Services",
            "type":"Services"
        }
    ],
    "sg:phone":"+1 714 374 7123",
    "sg:postcode":"92648",
    "sg:province":"CA",
    "sg:tags":[
        "auctioneer"
    ],
    "sg:website":"www.dovebid.com",
    "wof:name":"Dovebid",
    "wof:placetype":"venue"
},
  "geometry": {"coordinates":[-118.00109,33.658069],"type":"Point"}
}