{
  "type": "Feature",
  "properties": {
    "iso:country":"US",
    "sg:address":"6661 Darby Ave",
    "sg:city":"Reseda",
    "sg:classifiers":[
        {
            "category":"Building & Trades",
            "subcategory":"Landscaping Services",
            "type":"Services"
        }
    ],
    "sg:phone":"+1 818 996 1227",
    "sg:postcode":"91335",
    "sg:province":"CA",
    "wof:name":"Rodriguez Landscape Maintenanc",
    "wof:placetype":"venue"
},
  "geometry": {"coordinates":[-118.53356,34.191907],"type":"Point"}
}