{
  "type": "Feature",
  "properties": {
    "addr:full":"4537 Valmonte Dr Sacramento CA 95864",
    "addr:housenumber":"4537",
    "addr:postcode":"95864",
    "addr:street":"Valmonte Dr",
    "iso:country":"US",
    "sg:address":"4537 Valmonte Dr",
    "sg:city":"Sacramento",
    "sg:classifiers":[
        {
            "category":"Health Services",
            "subcategory":"Doctor",
            "type":"Services"
        }
    ],
    "sg:phone":"+1 916 973 5175",
    "sg:postcode":"95864",
    "sg:province":"CA",
    "sg:tags":[
        "physician",
        "surgeon"
    ],
    "wof:name":"Kaiser Permanente",
    "wof:placetype":"venue"
},
  "geometry": {"coordinates":[-121.35531400000001,38.594206],"type":"Point"}
}