{
  "type": "Feature",
  "properties": {
    "addr:full":"3249 Terminal Dr Santa Maria CA 93455",
    "addr:housenumber":"3249",
    "addr:postcode":"93455",
    "addr:street":"Terminal Dr",
    "iso:country":"US",
    "sg:address":"3249 Terminal Dr",
    "sg:city":"Santa Maria",
    "sg:classifiers":[
        {
            "category":"Professional",
            "type":"Services"
        }
    ],
    "sg:phone":"+1 805 925 0909",
    "sg:postcode":"93455",
    "sg:province":"CA",
    "sg:tags":[
        "weather"
    ],
    "wof:name":"National Weather Service",
    "wof:placetype":"venue"
},
  "geometry": {"coordinates":[-120.446782,34.898723],"type":"Point"}
}