{
  "type": "Feature",
  "properties": {
    "addr:full":"13800 Skyline Blvd Redwood City CA 94062",
    "addr:housenumber":"13800",
    "addr:postcode":"94062",
    "addr:street":"Skyline Blvd",
    "iso:country":"US",
    "sg:address":"13800 Skyline Blvd",
    "sg:city":"Redwood City",
    "sg:classifiers":[
        {
            "category":"Building & Trades",
            "subcategory":"Plumbing",
            "type":"Services"
        }
    ],
    "sg:phone":"+1 650 851 8103",
    "sg:postcode":"94062",
    "sg:province":"CA",
    "sg:tags":[
        "contractor"
    ],
    "wof:name":"Soult Plumbing",
    "wof:placetype":"venue"
},
  "geometry": {"coordinates":[-122.31876699999999,37.434807],"type":"Point"}
}