{
  "type": "Feature",
  "properties": {
    "addr:full":"609 Sweetwater Rd Spring Valley CA 91977",
    "addr:housenumber":"609",
    "addr:postcode":"91977",
    "addr:street":"Sweetwater Rd",
    "iso:country":"US",
    "sg:address":"609 Sweetwater Rd",
    "sg:city":"Spring Valley",
    "sg:classifiers":[
        {
            "category":"Personal",
            "subcategory":"Beauty Salon",
            "type":"Services"
        }
    ],
    "sg:phone":"+1 619 462 9218",
    "sg:postcode":"91977",
    "sg:province":"CA",
    "wof:name":"New Image Hair & Nail Studio",
    "wof:placetype":"venue"
},
  "geometry": {"coordinates":[-117.01096200000001,32.707262],"type":"Point"}
}