{
  "type": "Feature",
  "properties": {
    "addr:full":"1700 N 1st St San Jose CA 95112",
    "addr:housenumber":"1700",
    "addr:postcode":"95112",
    "addr:street":"N 1St St",
    "iso:country":"US",
    "sg:address":"1700 N 1st St",
    "sg:city":"San Jose",
    "sg:classifiers":[
        {
            "category":"Building & Trades",
            "subcategory":"Construction",
            "type":"Services"
        }
    ],
    "sg:phone":"+1 408 898 7298",
    "sg:postcode":"95112",
    "sg:province":"CA",
    "sg:tags":[
        "roofing"
    ],
    "sg:website":"www.principleroofing.com",
    "wof:name":"Principle Roofing",
    "wof:placetype":"venue"
},
  "geometry": {"coordinates":[-121.91352000000001,37.367158],"type":"Point"}
}