{
  "type": "Feature",
  "properties": {
    "addr:full":"386 Geary St San Francisco CA 94102",
    "addr:housenumber":"386",
    "addr:postcode":"94102",
    "addr:street":"Geary St",
    "iso:country":"US",
    "sg:address":"386 Geary St",
    "sg:city":"San Francisco",
    "sg:classifiers":[
        {
            "category":"Travel",
            "subcategory":"Hotels & Motels",
            "type":"Entertainment"
        }
    ],
    "sg:phone":"+1 415 986 2000",
    "sg:postcode":"94102",
    "sg:province":"CA",
    "sg:website":"www.maxwellhotel.com",
    "wof:name":"Maxwell Hotel",
    "wof:placetype":"venue"
},
  "geometry": {"coordinates":[-122.408744,37.787406],"type":"Point"}
}