{
  "type": "Feature",
  "properties": {
    "addr:full":"9151 Chesapeake Dr San Diego CA 92123",
    "addr:housenumber":"9151",
    "addr:postcode":"92123",
    "addr:street":"Chesapeake Dr",
    "iso:country":"US",
    "sg:address":"9151 Chesapeake Dr",
    "sg:city":"San Diego",
    "sg:classifiers":[
        {
            "category":"Home & Garden",
            "subcategory":"Household Appliances",
            "type":"Retail Goods"
        }
    ],
    "sg:phone":"+1 858 505 0800",
    "sg:postcode":"92123",
    "sg:province":"CA",
    "sg:tags":[
        "repair"
    ],
    "wof:name":"A-Aall Services",
    "wof:placetype":"venue"
},
  "geometry": {"coordinates":[-117.13099699999999,32.838501],"type":"Point"}
}