{
  "type": "Feature",
  "properties": {
    "addr:full":"10 Mountain Laurel Trabuco Canyon CA 92679",
    "addr:housenumber":"10",
    "addr:postcode":"92679",
    "addr:street":"Mountain Laurel",
    "iso:country":"US",
    "sg:address":"10 Mountain Laurel",
    "sg:city":"Trabuco Canyon",
    "sg:classifiers":[
        {
            "category":"Building & Trades",
            "subcategory":"Construction",
            "type":"Services"
        }
    ],
    "sg:phone":"+1 949 244 9748",
    "sg:postcode":"92679",
    "sg:province":"CA",
    "sg:tags":[
        "nonresidential"
    ],
    "wof:name":"Davlor Company",
    "wof:placetype":"venue"
},
  "geometry": {"coordinates":[-117.56943200000001,33.620169],"type":"Point"}
}