{
  "type": "Feature",
  "properties": {
    "iso:country":"US",
    "sg:address":"80 Bolivar Dr",
    "sg:city":"Berkeley",
    "sg:classifiers":[
        {
            "category":"Recreation",
            "subcategory":"Boat Charter",
            "type":"Entertainment"
        },
        {
            "category":"Park",
            "type":"Public Place"
        }
    ],
    "sg:phone":"+1 510 981 6700",
    "sg:postcode":"94701",
    "sg:province":"CA",
    "sg:tags":[
        "boating"
    ],
    "sg:website":"www.ci.berkeley.ca.us/ContentDis...",
    "wof:name":"Berkeley Aquatic Park",
    "wof:placetype":"venue"
},
  "geometry": {"coordinates":[-122.29808800000001,37.85673],"type":"Point"}
}