{
  "type": "Feature",
  "properties": {
    "iso:country":"US",
    "sg:address":"601 Van Ness Avenue Suite 2002",
    "sg:city":"San Francisco",
    "sg:classifiers":[
        {
            "category":"Community Center",
            "type":"Public Place"
        }
    ],
    "sg:phone":"+1 415 674 7000",
    "sg:postcode":"94102",
    "sg:province":"CA",
    "sg:tags":[
        "medical"
    ],
    "wof:name":"Kaiser Permanente Medical Center San Francisco",
    "wof:placetype":"venue"
},
  "geometry": {"coordinates":[-122.420998,37.781101],"type":"Point"}
}