{
  "type": "Feature",
  "properties": {
    "iso:country":"US",
    "sg:address":"2491 Grand Teton Ave",
    "sg:city":"Hemet",
    "sg:classifiers":[
        {
            "category":"Shopping",
            "type":"Retail Goods"
        }
    ],
    "sg:phone":"+1 951 925 9007",
    "sg:postcode":"92544",
    "sg:province":"CA",
    "sg:tags":[
        "equipment",
        "telephone",
        "supply"
    ],
    "wof:name":"Pju Telecomm",
    "wof:placetype":"venue"
},
  "geometry": {"coordinates":[-116.94721199999999,33.752657],"type":"Point"}
}