{
  "type": "Feature",
  "properties": {
    "iso:country":"US",
    "sg:address":"81691 US Hwy 111",
    "sg:city":"Indio",
    "sg:classifiers":[
        {
            "category":"Retail",
            "subcategory":"Portrait Studio",
            "type":"Services"
        }
    ],
    "sg:phone":"+1 760 775 6811",
    "sg:postcode":"92201",
    "sg:province":"CA",
    "sg:tags":[
        "photo"
    ],
    "wof:name":"P C A LLC",
    "wof:placetype":"venue"
},
  "geometry": {"coordinates":[-116.241589,33.707906],"type":"Point"}
}