{
  "type": "Feature",
  "properties": {
    "iso:country":"US",
    "sg:address":"14 Willow St",
    "sg:city":"San Rafael",
    "sg:classifiers":[
        {
            "category":"Building & Trades",
            "subcategory":"Landscaping Services",
            "type":"Services"
        }
    ],
    "sg:phone":"+1 415 459 4083",
    "sg:postcode":"94901",
    "sg:province":"CA",
    "wof:name":"Pedros Tree Service",
    "wof:placetype":"venue"
},
  "geometry": {"coordinates":[-122.531017,37.968784],"type":"Point"}
}