{
  "type": "Feature",
  "properties": {
    "addr:full":"14 Willow St San Rafael CA 94901",
    "addr:housenumber":"14",
    "addr:postcode":"94901",
    "addr:street":"Willow St",
    "iso:country":"US",
    "sg:address":"14 Willow St",
    "sg:city":"San Rafael",
    "sg:classifiers":[
        {
            "category":"Building & Trades",
            "subcategory":"Landscaping Services",
            "type":"Services"
        }
    ],
    "sg:phone":"+1 415 459 4083",
    "sg:postcode":"94901",
    "sg:province":"CA",
    "wof:name":"Pedros Tree Service",
    "wof:placetype":"venue"
},
  "geometry": {"coordinates":[-122.53101700000001,37.968784],"type":"Point"}
}