{
  "type": "Feature",
  "properties": {
    "addr:full":"351 Rendova Rd Marina CA 93933",
    "addr:housenumber":"351",
    "addr:postcode":"93933",
    "addr:street":"Rendova Rd",
    "iso:country":"US",
    "sg:address":"351 Rendova Rd",
    "sg:city":"Marina",
    "sg:classifiers":[
        {
            "category":"Social Services",
            "subcategory":"Child Care",
            "type":"Services"
        }
    ],
    "sg:phone":"+1 831 384 8771",
    "sg:postcode":"93933",
    "sg:province":"CA",
    "sg:tags":[
        "kindergarten",
        "academic",
        "school"
    ],
    "wof:name":"Head Start Ctr-Monterey County",
    "wof:placetype":"venue"
},
  "geometry": {"coordinates":[-121.80173499999999,36.673779],"type":"Point"}
}