{
  "type": "Feature",
  "properties": {
    "addr:full":"2401 Manning St Sacramento CA 95815",
    "addr:housenumber":"2401",
    "addr:postcode":"95815",
    "addr:street":"Manning St",
    "iso:country":"US",
    "sg:address":"2401 Manning St",
    "sg:city":"Sacramento",
    "sg:classifiers":[
        {
            "category":"Retail",
            "subcategory":"Auto Repair",
            "type":"Services"
        }
    ],
    "sg:phone":"+1 916 649 0222",
    "sg:postcode":"95815",
    "sg:province":"CA",
    "sg:tags":[
        "repairing",
        "automobile"
    ],
    "wof:name":"Corfee Car Care",
    "wof:placetype":"venue"
},
  "geometry": {"coordinates":[-121.433998,38.6101],"type":"Point"}
}