{
  "type": "Feature",
  "properties": {
    "iso:country":"US",
    "sg:address":"12954 Bess Ave",
    "sg:city":"Baldwin Park",
    "sg:classifiers":[
        {
            "category":"Food & Beverages",
            "subcategory":"Groceries & Convenience Stores",
            "type":"Retail Goods"
        }
    ],
    "sg:phone":"+1 626 337 8833",
    "sg:postcode":"91706",
    "sg:province":"CA",
    "wof:name":"7-Eleven",
    "wof:placetype":"venue"
},
  "geometry": {"coordinates":[-117.991395,34.06679],"type":"Point"}
}