{
  "type": "Feature",
  "properties": {
    "iso:country":"US",
    "sg:address":"3359 Putting Green Ct",
    "sg:city":"Oceanside",
    "sg:classifiers":[
        {
            "category":"Wholesale",
            "subcategory":"Construction Materials",
            "type":"Manufacturing & Wholesale Goods"
        },
        {
            "category":"Home & Garden",
            "subcategory":"Building Materials",
            "type":"Retail Goods"
        }
    ],
    "sg:phone":"+1 760 721 6020",
    "sg:postcode":"92056",
    "sg:province":"CA",
    "sg:tags":[
        "windows-wholesale",
        "window",
        "manufacturer"
    ],
    "wof:name":"Abc Discount Window Care",
    "wof:placetype":"venue"
},
  "geometry": {"coordinates":[-117.31124800000001,33.185868],"type":"Point"}
}