{
  "type": "Feature",
  "properties": {
    "iso:country":"US",
    "sg:address":"2716 W Pico Boulevard",
    "sg:city":"Los Angeles",
    "sg:classifiers":[
        {
            "category":"Bakery",
            "type":"Food & Drink"
        }
    ],
    "sg:phone":"+1 323 734 1535",
    "sg:postcode":"90006",
    "sg:province":"CA",
    "wof:name":"Panaderia Sabor Latino",
    "wof:placetype":"venue"
},
  "geometry": {"coordinates":[-118.298096,34.047343],"type":"Point"}
}