{
  "type": "Feature",
  "properties": {
    "iso:country":"US",
    "sg:address":"317 W Acacia Ave",
    "sg:city":"Glendale",
    "sg:classifiers":[
        {
            "category":"Professional",
            "type":"Services"
        }
    ],
    "sg:phone":"+1 818 240 4209",
    "sg:postcode":"91204",
    "sg:province":"CA",
    "wof:name":"ARA Bagdasaryan",
    "wof:placetype":"venue"
},
  "geometry": {"coordinates":[-118.25827700000001,34.134931],"type":"Point"}
}