{
  "type": "Feature",
  "properties": {
    "iso:country":"US",
    "sg:address":"2900 Bristol St Ste J103",
    "sg:city":"Costa Mesa",
    "sg:classifiers":[
        {
            "category":"Health Services",
            "subcategory":"Clinic",
            "type":"Services"
        },
        {
            "category":"Personal",
            "subcategory":"Day Spa",
            "type":"Services"
        }
    ],
    "sg:phone":"+1 714 668 9660",
    "sg:postcode":"92626",
    "sg:province":"CA",
    "sg:tags":[
        "loss",
        "weight"
    ],
    "sg:website":"chocolatedayspa.com/",
    "wof:name":"The Chocolate Day Spa",
    "wof:placetype":"venue"
},
  "geometry": {"coordinates":[-117.88693499999999,33.676135],"type":"Point"}
}