{
  "type": "Feature",
  "properties": {
    "iso:country":"US",
    "sg:address":"15110 Rosecrans Ave",
    "sg:city":"La Mirada",
    "sg:classifiers":[
        {
            "category":"Restaurant",
            "type":"Food & Drink"
        }
    ],
    "sg:phone":"+1 714 523 9156",
    "sg:postcode":"90638",
    "sg:province":"CA",
    "sg:tags":[
        "parlor",
        "ice",
        "cream"
    ],
    "wof:name":"TCBY",
    "wof:placetype":"venue"
},
  "geometry": {"coordinates":[-118.009186,33.898424],"type":"Point"}
}