{
  "type": "Feature",
  "properties": {
    "addr:full":"2428 Armstrong St Livermore CA 94551",
    "addr:housenumber":"2428",
    "addr:postcode":"94551",
    "addr:street":"Armstrong St",
    "iso:country":"US",
    "sg:address":"2428 Armstrong St",
    "sg:city":"Livermore",
    "sg:classifiers":[
        {
            "category":"Professional",
            "subcategory":"Computer Services",
            "type":"Services"
        }
    ],
    "sg:phone":"+1 925 449 2029",
    "sg:postcode":"94551",
    "sg:province":"CA",
    "sg:tags":[
        "consultant",
        "designer"
    ],
    "wof:name":"New Frontiers Software",
    "wof:placetype":"venue"
},
  "geometry": {"coordinates":[-121.812111,37.697667],"type":"Point"}
}