{
  "type": "Feature",
  "properties": {
    "iso:country":"US",
    "sg:address":"540 S Indian Canyon Dr",
    "sg:city":"Palm Springs",
    "sg:classifiers":[
        {
            "category":"Professional",
            "type":"Services"
        }
    ],
    "sg:phone":"+1 760 323 4577",
    "sg:postcode":"92264",
    "sg:province":"CA",
    "sg:tags":[
        "establishment"
    ],
    "wof:name":"Nino Fontana's Italian Groc",
    "wof:placetype":"venue"
},
  "geometry": {"coordinates":[-116.54551499999999,33.814815],"type":"Point"}
}