{
  "type": "Feature",
  "properties": {
    "addr:full":"375 Woodworth Ave Clovis CA 93612",
    "addr:housenumber":"375",
    "addr:postcode":"93612",
    "addr:street":"Woodworth Ave",
    "iso:country":"US",
    "sg:address":"375 Woodworth Ave",
    "sg:city":"Clovis",
    "sg:classifiers":[
        {
            "category":"Building & Trades",
            "subcategory":"Construction",
            "type":"Services"
        }
    ],
    "sg:phone":"+1 559 322 1388",
    "sg:postcode":"93612",
    "sg:province":"CA",
    "sg:tags":[
        "contractor"
    ],
    "wof:name":"Tyler Building",
    "wof:placetype":"venue"
},
  "geometry": {"coordinates":[-119.703287,36.826231],"type":"Point"}
}