{
  "type": "Feature",
  "properties": {
    "iso:country":"US",
    "sg:address":"1746 N Hudson Ave",
    "sg:city":"Los Angeles",
    "sg:classifiers":[
        {
            "category":"Arts & Performance",
            "subcategory":"Theater",
            "type":"Entertainment"
        }
    ],
    "sg:phone":"+1 323 461 1047",
    "sg:postcode":"90028",
    "sg:province":"CA",
    "sg:tags":[
        "magician"
    ],
    "wof:name":"Fairy Tale Productions",
    "wof:placetype":"venue"
},
  "geometry": {"coordinates":[-118.332127,34.102525],"type":"Point"}
}