{
  "type": "Feature",
  "properties": {
    "addr:full":"5001 Willows Rd Alpine CA 91901",
    "addr:housenumber":"5001",
    "addr:postcode":"91901",
    "addr:street":"Willows Rd",
    "iso:country":"US",
    "sg:address":"5001 Willows Rd",
    "sg:city":"Alpine",
    "sg:classifiers":[
        {
            "category":"Shopping",
            "subcategory":"Clothing, Apparel, & Fashions",
            "type":"Retail Goods"
        }
    ],
    "sg:phone":"+1 619 659 1655",
    "sg:postcode":"91901",
    "sg:province":"CA",
    "sg:tags":[
        "sportswear"
    ],
    "wof:name":"Big Dog Sportswear",
    "wof:placetype":"venue"
},
  "geometry": {"coordinates":[-116.701638,32.842249],"type":"Point"}
}