{
  "type": "Feature",
  "properties": {
    "addr:full":"1334 S Lorena St Los Angeles CA 90023",
    "addr:housenumber":"1334",
    "addr:postcode":"90023",
    "addr:street":"S Lorena St",
    "iso:country":"US",
    "sg:address":"1334 S Lorena St",
    "sg:city":"Los Angeles",
    "sg:classifiers":[
        {
            "category":"Social Services",
            "type":"Services"
        }
    ],
    "sg:phone":"+1 323 221 7737",
    "sg:postcode":"90023",
    "sg:province":"CA",
    "sg:tags":[
        "organization",
        "welfare"
    ],
    "sg:website":"www.maof.org",
    "wof:name":"MAOF Handyman Program",
    "wof:placetype":"venue"
},
  "geometry": {"coordinates":[-118.20587500000001,34.019889],"type":"Point"}
}