{
  "type": "Feature",
  "properties": {
    "iso:country":"US",
    "sg:address":"317 W Main St",
    "sg:city":"Alhambra",
    "sg:classifiers":[
        {
            "category":"Manufacturing",
            "subcategory":"Paper Products",
            "type":"Manufacturing & Wholesale Goods"
        }
    ],
    "sg:phone":"+1 626 457 8528",
    "sg:postcode":"91801",
    "sg:province":"CA",
    "wof:name":"Liko Enterprises",
    "wof:placetype":"venue"
},
  "geometry": {"coordinates":[-118.131032,34.093295],"type":"Point"}
}