{
  "type": "Feature",
  "properties": {
    "addr:full":"311 S Mount Vernon Ave San Bernardino CA 92410",
    "addr:housenumber":"311",
    "addr:postcode":"92410",
    "addr:street":"S Mount Vernon Ave",
    "iso:country":"US",
    "sg:address":"311 S Mount Vernon Ave",
    "sg:city":"San Bernardino",
    "sg:classifiers":[
        {
            "category":"Personal",
            "subcategory":"Beauty Salon",
            "type":"Services"
        }
    ],
    "sg:phone":"+1 909 384 1090",
    "sg:postcode":"92410",
    "sg:province":"CA",
    "wof:name":"Cindy's Beauty Salon",
    "wof:placetype":"venue"
},
  "geometry": {"coordinates":[-117.313789,34.095858],"type":"Point"}
}