{
  "type": "Feature",
  "properties": {
    "addr:full":"11413 South St Cerritos CA 90703",
    "addr:housenumber":"11413",
    "addr:postcode":"ca 90703",
    "addr:street":"South St",
    "iso:country":"US",
    "sg:address":"11413 South St",
    "sg:city":"Cerritos",
    "sg:classifiers":[
        {
            "category":"Restaurant",
            "type":"Food & Drink"
        }
    ],
    "sg:phone":"+1 562 809 9292",
    "sg:postcode":"90703",
    "sg:province":"CA",
    "sg:tags":[
        "hawaiian"
    ],
    "sg:website":"www.hawaiianbarbecue.com/",
    "wof:name":"L & L Hawaiian Barbeque",
    "wof:placetype":"venue"
},
  "geometry": {"coordinates":[-118.09054999999999,33.858491],"type":"Point"}
}