{
  "type": "Feature",
  "properties": {
    "iso:country":"US",
    "sg:address":"2601 Airport Dr",
    "sg:city":"Torrance",
    "sg:classifiers":[
        {
            "category":"Professional",
            "subcategory":"Lawyer & Legal Services",
            "type":"Services"
        }
    ],
    "sg:phone":"+1 310 257 9363",
    "sg:postcode":"90505",
    "sg:province":"CA",
    "wof:name":"Albert & Will Attorneys At Law",
    "wof:placetype":"venue"
},
  "geometry": {"coordinates":[-118.329002,33.791901],"type":"Point"}
}