{
  "type": "Feature",
  "properties": {
    "iso:country":"US",
    "sg:address":"S Santa Cruz Ave",
    "sg:city":"Los Gatos",
    "sg:classifiers":[
        {
            "category":"Professional",
            "subcategory":"Art Services",
            "type":"Services"
        }
    ],
    "sg:phone":"+1 408 354 8750",
    "sg:postcode":"95030",
    "sg:province":"CA",
    "sg:tags":[
        "photographer"
    ],
    "sg:website":"www.bugsandbutterfliesphotograph...",
    "wof:name":"Bugs and Butterflies Photography",
    "wof:placetype":"venue"
},
  "geometry": {"coordinates":[-121.984993,37.220847],"type":"Point"}
}