{
  "type": "Feature",
  "properties": {
    "iso:country":"US",
    "sg:address":"110 Tiburon Blvd",
    "sg:city":"Mill Valley",
    "sg:classifiers":[
        {
            "category":"Banks & Credit Unions",
            "subcategory":"Investment Brokerage",
            "type":"Services"
        }
    ],
    "sg:phone":"+1 415 383 1464",
    "sg:postcode":"94920",
    "sg:province":"CA",
    "sg:tags":[
        "consultant",
        "planning",
        "financial"
    ],
    "wof:name":"Gerken Capital Assoc",
    "wof:placetype":"venue"
},
  "geometry": {"coordinates":[-122.510223,37.901736],"type":"Point"}
}