{
  "type": "Feature",
  "properties": {
    "iso:country":"US",
    "sg:address":"18977 Covina St",
    "sg:city":"Hesperia",
    "sg:classifiers":[
        {
            "category":"Building & Trades",
            "subcategory":"Construction",
            "type":"Services"
        }
    ],
    "sg:phone":"+1 760 244 3952",
    "sg:postcode":"92345",
    "sg:province":"CA",
    "sg:tags":[
        "contractor"
    ],
    "wof:name":"Jed Construction",
    "wof:placetype":"venue"
},
  "geometry": {"coordinates":[-117.24979500000001,34.44633],"type":"Point"}
}