{
  "type": "Feature",
  "properties": {
    "iso:country":"US",
    "sg:address":"5125 Caterpillar Rd",
    "sg:city":"Redding",
    "sg:classifiers":[
        {
            "category":"Manufacturing",
            "subcategory":"Tools & Machinery",
            "type":"Manufacturing & Wholesale Goods"
        }
    ],
    "sg:phone":"+1 530 224 4070",
    "sg:postcode":"96003",
    "sg:province":"CA",
    "sg:tags":[
        "engine",
        "diesel",
        "mfg"
    ],
    "wof:name":"Shanney Head Equipment",
    "wof:placetype":"venue"
},
  "geometry": {"coordinates":[-122.368988,40.625394],"type":"Point"}
}