{
  "type": "Feature",
  "properties": {
    "iso:country":"US",
    "sg:address":"1108 Tamalpais Ave",
    "sg:city":"San Rafael",
    "sg:classifiers":[
        {
            "category":"Professional",
            "subcategory":"Lawyer & Legal Services",
            "type":"Services"
        }
    ],
    "sg:phone":"+1 415 454 1490",
    "sg:postcode":"94901",
    "sg:province":"CA",
    "sg:tags":[
        "attorney"
    ],
    "wof:name":"Weintraub Genshlea & Sproul",
    "wof:placetype":"venue"
},
  "geometry": {"coordinates":[-122.522156,37.974026],"type":"Point"}
}