{
  "type": "Feature",
  "properties": {
    "iso:country":"US",
    "sg:address":"16745 Saticoy St",
    "sg:city":"Van Nuys",
    "sg:classifiers":[
        {
            "category":"Shopping",
            "type":"Retail Goods"
        }
    ],
    "sg:phone":"+1 818 780 3223",
    "sg:postcode":"91406",
    "sg:province":"CA",
    "sg:tags":[
        "mgr",
        "prosthetics",
        "merchandise"
    ],
    "wof:name":"Massey Prosthetic Arts",
    "wof:placetype":"venue"
},
  "geometry": {"coordinates":[-118.498801,34.208348],"type":"Point"}
}