{
  "type": "Feature",
  "properties": {
    "iso:country":"US",
    "sg:address":"899 Laguna Dr #D",
    "sg:city":"Carlsbad",
    "sg:classifiers":[
        {
            "category":"Shopping",
            "subcategory":"Party Supplies",
            "type":"Retail Goods"
        }
    ],
    "sg:phone":"+1 858 829 9382",
    "sg:postcode":"92008",
    "sg:province":"CA",
    "sg:tags":[
        "wedding"
    ],
    "sg:website":"http://www.amorimagery.com",
    "wof:name":"Amor Imagery Wedding Photography",
    "wof:placetype":"venue"
},
  "geometry": {"coordinates":[-117.348373,33.16523],"type":"Point"}
}