{
  "type": "Feature",
  "properties": {
    "iso:country":"US",
    "sg:address":"12801 Excelsior Dr",
    "sg:city":"Santa Fe Springs",
    "sg:classifiers":[
        {
            "category":"Banks & Credit Unions",
            "subcategory":"Bank",
            "type":"Services"
        }
    ],
    "sg:phone":"+1 562 921 4446",
    "sg:postcode":"90670",
    "sg:province":"CA",
    "sg:website":"shop.safeway.com",
    "wof:name":"Vons Employee Federal Credit Union",
    "wof:placetype":"venue"
},
  "geometry": {"coordinates":[-118.059998,33.895199],"type":"Point"}
}