{
  "type": "Feature",
  "properties": {
    "addr:full":"623 Plaza Ave Sacramento CA 95815",
    "addr:housenumber":"623",
    "addr:postcode":"95815",
    "addr:street":"Plaza Ave",
    "iso:country":"US",
    "sg:address":"623 Plaza Ave",
    "sg:city":"Sacramento",
    "sg:classifiers":[
        {
            "category":"Building & Trades",
            "subcategory":"Construction",
            "type":"Services"
        }
    ],
    "sg:phone":"+1 916 920 4711",
    "sg:postcode":"95815",
    "sg:province":"CA",
    "sg:tags":[
        "painter"
    ],
    "wof:name":"Chavarria Painting Svc",
    "wof:placetype":"venue"
},
  "geometry": {"coordinates":[-121.45135999999999,38.613011],"type":"Point"}
}