{
  "type": "Feature",
  "properties": {
    "addr:full":"24500 Cll el Rosario Salinas CA 93908",
    "addr:postcode":"24500;93908",
    "addr:street":"Cll;Rosario",
    "iso:country":"US",
    "sg:address":"24500 Cll el Rosario",
    "sg:city":"Salinas",
    "sg:classifiers":[
        {
            "category":"Food & Beverages",
            "subcategory":"Groceries & Convenience Stores",
            "type":"Retail Goods"
        }
    ],
    "sg:phone":"+1 831 757 1971",
    "sg:postcode":"93908",
    "sg:province":"CA",
    "sg:tags":[
        "grocer"
    ],
    "wof:name":"Prende O Se Seca",
    "wof:placetype":"venue"
},
  "geometry": {"coordinates":[-121.537983,36.642501],"type":"Point"}
}