{
  "type": "Feature",
  "properties": {
    "addr:full":"5841 S Maple Ave Fresno CA 93725",
    "addr:housenumber":"5841",
    "addr:postcode":"93725",
    "addr:street":"S Maple Ave",
    "iso:country":"US",
    "sg:address":"5841 S Maple Ave",
    "sg:city":"Fresno",
    "sg:classifiers":[
        {
            "category":"Farming",
            "subcategory":"Crops",
            "type":"Manufacturing & Wholesale Goods"
        }
    ],
    "sg:phone":"+1 559 834 5063",
    "sg:postcode":"93725",
    "sg:province":"CA",
    "sg:tags":[
        "grove",
        "nut",
        "tree"
    ],
    "wof:name":"Lazarus Farms",
    "wof:placetype":"venue"
},
  "geometry": {"coordinates":[-119.745842,36.653741],"type":"Point"}
}