{
  "type": "Feature",
  "properties": {
    "iso:country":"US",
    "sg:address":"810 E Main St",
    "sg:city":"Ontario",
    "sg:classifiers":[
        {
            "category":"Wholesale",
            "subcategory":"Machinery & Supplies",
            "type":"Manufacturing & Wholesale Goods"
        }
    ],
    "sg:phone":"+1 909 988 4450",
    "sg:postcode":"91761",
    "sg:province":"CA",
    "sg:tags":[
        "equipment",
        "industrial"
    ],
    "wof:name":"M & M Machinery Sales",
    "wof:placetype":"venue"
},
  "geometry": {"coordinates":[-117.63461100000001,34.061102],"type":"Point"}
}