{
  "type": "Feature",
  "properties": {
    "addr:full":"7207 Murray Dr Stockton CA 95210",
    "addr:housenumber":"7207",
    "addr:postcode":"95210",
    "addr:street":"Murray Dr",
    "iso:country":"US",
    "sg:address":"7207 Murray Dr",
    "sg:city":"Stockton",
    "sg:classifiers":[
        {
            "category":"Building & Trades",
            "subcategory":"Construction",
            "type":"Services"
        }
    ],
    "sg:phone":"+1 209 474 6301",
    "sg:postcode":"95210",
    "sg:province":"CA",
    "sg:tags":[
        "excavating",
        "contractor"
    ],
    "wof:name":"K M Jackson Engineering Inc",
    "wof:placetype":"venue"
},
  "geometry": {"coordinates":[-121.303094,38.019483],"type":"Point"}
}