{
  "type": "Feature",
  "properties": {
    "addr:full":"2135 Pacific Ave Long Beach CA 90806",
    "addr:housenumber":"2135",
    "addr:postcode":"90806",
    "addr:street":"Pacific Ave",
    "iso:country":"US",
    "sg:address":"2135 Pacific Ave",
    "sg:city":"Long Beach",
    "sg:classifiers":[
        {
            "category":"Retail",
            "subcategory":"Repair Shop",
            "type":"Services"
        }
    ],
    "sg:phone":"+1 562 599 5480",
    "sg:postcode":"90806",
    "sg:province":"CA",
    "sg:tags":[
        "jewelry"
    ],
    "wof:name":"Leo's Jewelry Repair",
    "wof:placetype":"venue"
},
  "geometry": {"coordinates":[-118.193781,33.796488],"type":"Point"}
}