{
  "type": "Feature",
  "properties": {
    "iso:country":"US",
    "sg:address":"11319 Lakeland Rd",
    "sg:city":"Norwalk",
    "sg:classifiers":[
        {
            "category":"Building & Trades",
            "subcategory":"Construction",
            "type":"Services"
        }
    ],
    "sg:phone":"+1 626 934 1112",
    "sg:postcode":"90650",
    "sg:province":"CA",
    "sg:tags":[
        "contractor"
    ],
    "wof:name":"Mtm Construction",
    "wof:placetype":"venue"
},
  "geometry": {"coordinates":[-118.245949,33.931325],"type":"Point"}
}