{
  "type": "Feature",
  "properties": {
    "iso:country":"US",
    "sg:address":"1170 Harding St",
    "sg:city":"Escondido",
    "sg:classifiers":[
        {
            "category":"Building & Trades",
            "subcategory":"Landscaping Services",
            "type":"Services"
        }
    ],
    "sg:phone":"+1 760 480 4664",
    "sg:postcode":"92027",
    "sg:province":"CA",
    "wof:name":"Mr Zs Landscape Services",
    "wof:placetype":"venue"
},
  "geometry": {"coordinates":[-117.070504,33.141485],"type":"Point"}
}