{
  "type": "Feature",
  "properties": {
    "addr:full":"720 Capitola Avenue Capitola CA 95010",
    "addr:housenumber":"720",
    "addr:postcode":"95010",
    "addr:street":"Capitola Avenue",
    "iso:country":"US",
    "sg:address":"720 Capitola Avenue",
    "sg:city":"Capitola",
    "sg:classifiers":[
        {
            "category":"Professional",
            "subcategory":"Accounting & Tax Preparation",
            "type":"Services"
        }
    ],
    "sg:phone":"+1 831 476 7079",
    "sg:postcode":"95010",
    "sg:province":"CA",
    "sg:tags":[
        "accountant"
    ],
    "wof:name":"Gusarson Donald D CPA An Accountancy Corporation",
    "wof:placetype":"venue"
},
  "geometry": {"coordinates":[-121.95286900000001,36.979785],"type":"Point"}
}