{
  "type": "Feature",
  "properties": {
    "iso:country":"US",
    "sg:address":"1802 Floral Ave",
    "sg:city":"Selma",
    "sg:classifiers":[
        {
            "category":"Social Services",
            "subcategory":"Child Care",
            "type":"Services"
        }
    ],
    "sg:phone":"+1 559 896 5881",
    "sg:postcode":"93662",
    "sg:province":"CA",
    "wof:name":"YMCA Child Care",
    "wof:placetype":"venue"
},
  "geometry": {"coordinates":[-119.609033,36.576273],"type":"Point"}
}