{
  "type": "Feature",
  "properties": {
    "addr:full":"14831 Turner Rd Victorville CA 92394",
    "addr:housenumber":"14831",
    "addr:postcode":"92394",
    "addr:street":"Turner Rd",
    "iso:country":"US",
    "sg:address":"14831 Turner Rd",
    "sg:city":"Victorville",
    "sg:classifiers":[
        {
            "category":"Organizations",
            "subcategory":"Non-profit Organization",
            "type":"Services"
        }
    ],
    "sg:phone":"+1 760 246 8579",
    "sg:postcode":"92394",
    "sg:province":"CA",
    "wof:name":"Freedom Animal Rescue Ranch",
    "wof:placetype":"venue"
},
  "geometry": {"coordinates":[-117.336558,34.572611],"type":"Point"}
}