{
  "type": "Feature",
  "properties": {
    "iso:country":"US",
    "sg:address":"119 Gilbert Ave",
    "sg:city":"Santa Clara",
    "sg:classifiers":[
        {
            "category":"Professional",
            "subcategory":"Engineering",
            "type":"Services"
        }
    ],
    "sg:phone":"+1 408 985 2205",
    "sg:postcode":"95051",
    "sg:province":"CA",
    "sg:tags":[
        "lighting",
        "engineer"
    ],
    "wof:name":"Stage & Sell",
    "wof:placetype":"venue"
},
  "geometry": {"coordinates":[-121.984751,37.326813],"type":"Point"}
}