{
  "type": "Feature",
  "properties": {
    "addr:full":"7047 James Ln Atwater CA 95301",
    "addr:housenumber":"7047",
    "addr:postcode":"95301",
    "addr:street":"James Ln",
    "iso:country":"US",
    "sg:address":"7047 James Ln",
    "sg:city":"Atwater",
    "sg:classifiers":[
        {
            "category":"Building & Trades",
            "subcategory":"Construction",
            "type":"Services"
        }
    ],
    "sg:phone":"+1 209 358 1031",
    "sg:postcode":"95301",
    "sg:province":"CA",
    "sg:tags":[
        "roofing",
        "industrial",
        "contractors-commercial",
        "contractor"
    ],
    "wof:name":"Aqua-Therm Roofing Services",
    "wof:placetype":"venue"
},
  "geometry": {"coordinates":[-120.615854,37.33976],"type":"Point"}
}