{
  "type": "Feature",
  "properties": {
    "iso:country":"US",
    "sg:address":"898 S Harbor Blvd",
    "sg:city":"Anaheim",
    "sg:classifiers":[
        {
            "category":"Health Services",
            "subcategory":"Doctor",
            "type":"Services"
        },
        {
            "category":"Health Services",
            "subcategory":"Clinic",
            "type":"Services"
        }
    ],
    "sg:phone":"+1 714 491 1026",
    "sg:postcode":"92805",
    "sg:province":"CA",
    "sg:tags":[
        "physician",
        "family",
        "medical",
        "practice",
        "surgeons",
        "medicine"
    ],
    "wof:name":"Clinica Medica Central",
    "wof:placetype":"venue"
},
  "geometry": {"coordinates":[-117.91548899999999,33.821838],"type":"Point"}
}