{
  "type": "Feature",
  "properties": {
    "iso:country":"US",
    "sg:address":"12508 Wicks St",
    "sg:city":"Sun Valley",
    "sg:classifiers":[
        {
            "category":"Education",
            "subcategory":"School",
            "type":"Public Place"
        }
    ],
    "sg:phone":"+1 818 767 3759",
    "sg:postcode":"91352",
    "sg:province":"CA",
    "wof:name":"Robert H Lewis High School",
    "wof:placetype":"venue"
},
  "geometry": {"coordinates":[-118.406864,34.224358],"type":"Point"}
}