{
  "type": "Feature",
  "properties": {
    "iso:country":"US",
    "sg:address":"3645 10th Ave",
    "sg:city":"Los Angeles",
    "sg:classifiers":[
        {
            "category":"Wholesale",
            "subcategory":"Home Furnishings",
            "type":"Manufacturing & Wholesale Goods"
        }
    ],
    "sg:phone":"+1 323 731 6660",
    "sg:postcode":"90018",
    "sg:province":"CA",
    "sg:tags":[
        "lamp"
    ],
    "wof:name":"Revival Lightwork",
    "wof:placetype":"venue"
},
  "geometry": {"coordinates":[-118.32841000000001,34.022057],"type":"Point"}
}