{
  "type": "Feature",
  "properties": {
    "addr:full":"100 N Lake Ave Ste 201 Pasadena CA 91101",
    "addr:housenumber":"100",
    "addr:postcode":"91101",
    "addr:street":"N Lake Ave Ste 201",
    "iso:country":"US",
    "sg:address":"100 N Lake Ave Ste 201",
    "sg:city":"Pasadena",
    "sg:classifiers":[
        {
            "category":"Banks & Credit Unions",
            "subcategory":"Financial Services",
            "type":"Services"
        }
    ],
    "sg:phone":"+1 626 792 8207",
    "sg:postcode":"91101",
    "sg:province":"CA",
    "sg:tags":[
        "broker",
        "mortgage"
    ],
    "wof:name":"VFS Mortgage Company",
    "wof:placetype":"venue"
},
  "geometry": {"coordinates":[-118.13217400000001,34.147232],"type":"Point"}
}