{
  "type": "Feature",
  "properties": {
    "addr:full":"2910 S Cherry Ave Fresno CA 93706",
    "addr:housenumber":"2910",
    "addr:postcode":"93706",
    "addr:street":"S Cherry Ave",
    "iso:country":"US",
    "sg:address":"2910 S Cherry Ave",
    "sg:city":"Fresno",
    "sg:classifiers":[
        {
            "category":"Wholesale",
            "subcategory":"Scrap",
            "type":"Manufacturing & Wholesale Goods"
        }
    ],
    "sg:phone":"+1 559 264 6246",
    "sg:postcode":"93706",
    "sg:province":"CA",
    "sg:tags":[
        "recycling",
        "center"
    ],
    "wof:name":"Western Metal Co",
    "wof:placetype":"venue"
},
  "geometry": {"coordinates":[-119.781803,36.697131],"type":"Point"}
}