{
  "type": "Feature",
  "properties": {
    "iso:country":"US",
    "sg:address":"27485 Pso Lindero",
    "sg:city":"San Juan Capistrano",
    "sg:classifiers":[
        {
            "category":"Professional",
            "type":"Services"
        }
    ],
    "sg:phone":"+1 949 240 2145",
    "sg:postcode":"92675",
    "sg:province":"CA",
    "wof:name":"Bevill Prorperties",
    "wof:placetype":"venue"
},
  "geometry": {"coordinates":[-117.65009000000001,33.491234],"type":"Point"}
}