{
  "type": "Feature",
  "properties": {
    "addr:full":"2401 Pomona Rd Corona CA 92880",
    "addr:housenumber":"2401",
    "addr:postcode":"92880",
    "addr:street":"Pomona Rd",
    "iso:country":"US",
    "sg:address":"2401 Pomona Rd",
    "sg:city":"Corona",
    "sg:classifiers":[
        {
            "category":"Manufacturing",
            "subcategory":"Metals",
            "type":"Manufacturing & Wholesale Goods"
        }
    ],
    "sg:phone":"+1 951 520 1157",
    "sg:postcode":"92880",
    "sg:province":"CA",
    "sg:tags":[
        "precision",
        "grinding"
    ],
    "wof:name":"Sheldon Precision Grinding",
    "wof:placetype":"venue"
},
  "geometry": {"coordinates":[-117.610207,33.884121],"type":"Point"}
}