{
  "type": "Feature",
  "properties": {
    "iso:country":"US",
    "sg:address":"130 Doolittle Dr",
    "sg:city":"San Leandro",
    "sg:classifiers":[
        {
            "category":"Professional",
            "subcategory":"Printing & Photocopies",
            "type":"Services"
        }
    ],
    "sg:phone":"+1 510 553 0940",
    "sg:postcode":"94577",
    "sg:province":"CA",
    "wof:name":"Duplicating Center",
    "wof:placetype":"venue"
},
  "geometry": {"coordinates":[-122.19499999999999,37.723202],"type":"Point"}
}