{
  "type": "Feature",
  "properties": {
    "addr:full":"5205 Kearny Villa Way San Diego CA 92123",
    "addr:housenumber":"5205",
    "addr:postcode":"92123",
    "addr:street":"Kearny Villa Way",
    "iso:country":"US",
    "sg:address":"5205 Kearny Villa Way",
    "sg:city":"San Diego",
    "sg:classifiers":[
        {
            "category":"Communications",
            "subcategory":"Radio Station",
            "type":"Services"
        }
    ],
    "sg:phone":"+1 858 573 2376",
    "sg:postcode":"92123",
    "sg:province":"CA",
    "sg:tags":[
        "broadcast"
    ],
    "wof:name":"Armed Forces Radio Network",
    "wof:placetype":"venue"
},
  "geometry": {"coordinates":[-117.14012099999999,32.830085],"type":"Point"}
}