{
  "type": "Feature",
  "properties": {
    "addr:full":"2230 Mayfaire Dr Turlock CA 95380",
    "addr:housenumber":"2230",
    "addr:postcode":"95380",
    "addr:street":"Mayfaire Dr",
    "iso:country":"US",
    "sg:address":"2230 Mayfaire Dr",
    "sg:city":"Turlock",
    "sg:classifiers":[
        {
            "category":"Autos & Motor Vehicles",
            "subcategory":"Automobile Sales",
            "type":"Retail Goods"
        }
    ],
    "sg:phone":"+1 209 667 7109",
    "sg:postcode":"95380",
    "sg:province":"CA",
    "sg:tags":[
        "performance",
        "race",
        "dealer"
    ],
    "wof:name":"AMP Racing",
    "wof:placetype":"venue"
},
  "geometry": {"coordinates":[-120.872563,37.503609],"type":"Point"}
}