{
  "type": "Feature",
  "properties": {
    "addr:full":"10743 Edison Ct Rancho Cucamonga CA 91730",
    "addr:housenumber":"10743",
    "addr:postcode":"91730",
    "addr:street":"Edison Ct",
    "iso:country":"US",
    "sg:address":"10743 Edison Ct",
    "sg:city":"Rancho Cucamonga",
    "sg:classifiers":[
        {
            "category":"Manufacturing",
            "subcategory":"Motor Vehicles & Parts",
            "type":"Manufacturing & Wholesale Goods"
        }
    ],
    "sg:phone":"+1 909 481 0600",
    "sg:postcode":"91730",
    "sg:province":"CA",
    "sg:tags":[
        "scooter",
        "motorcycle"
    ],
    "wof:name":"Horsepower & Chrome",
    "wof:placetype":"venue"
},
  "geometry": {"coordinates":[-117.569569,34.097769],"type":"Point"}
}