{
  "type": "Feature",
  "properties": {
    "addr:full":"1021 Kirkwood Ave Pasadena CA 91103",
    "addr:housenumber":"1021",
    "addr:postcode":"91103",
    "addr:street":"Kirkwood Ave",
    "iso:country":"US",
    "sg:address":"1021 Kirkwood Ave",
    "sg:city":"Pasadena",
    "sg:classifiers":[
        {
            "category":"Banks & Credit Unions",
            "subcategory":"Investment Brokerage",
            "type":"Services"
        }
    ],
    "sg:phone":"+1 626 798 7849",
    "sg:postcode":"91103",
    "sg:province":"CA",
    "sg:tags":[
        "advisory",
        "financial"
    ],
    "wof:name":"Money Masters",
    "wof:placetype":"venue"
},
  "geometry": {"coordinates":[-118.153693,34.163373],"type":"Point"}
}