{
  "type": "Feature",
  "properties": {
    "addr:full":"4700 Cll Alto Camarillo CA 93012",
    "addr:postcode":"4700;93012",
    "addr:street":"Cll Alto",
    "iso:country":"US",
    "sg:address":"4700 Cll Alto",
    "sg:city":"Camarillo",
    "sg:classifiers":[
        {
            "category":"Manufacturing",
            "subcategory":"Glass & Minerals",
            "type":"Manufacturing & Wholesale Goods"
        },
        {
            "category":"Manufacturing",
            "subcategory":"Rubber & Plastics",
            "type":"Manufacturing & Wholesale Goods"
        }
    ],
    "sg:phone":"+1 805 484 2774",
    "sg:postcode":"93012",
    "sg:province":"CA",
    "sg:tags":[
        "b",
        "mfg",
        "fiberglass",
        "material",
        "acoustical",
        "insulation",
        "turbine"
    ],
    "sg:website":"www.hitemp-ca.com",
    "wof:name":"HI Temp Insulation Inc",
    "wof:placetype":"venue"
},
  "geometry": {"coordinates":[-119.00644200000001,34.203441],"type":"Point"}
}