{
  "type": "Feature",
  "properties": {
    "addr:full":"4545 Moran Rd Avery CA 95224",
    "addr:housenumber":"4545",
    "addr:postcode":"95224",
    "addr:street":"Moran Rd",
    "iso:country":"US",
    "sg:address":"4545 Moran Rd",
    "sg:city":"Avery",
    "sg:classifiers":[
        {
            "category":"Education",
            "subcategory":"School",
            "type":"Public Place"
        }
    ],
    "sg:phone":"+1 209 795 8045",
    "sg:postcode":"95224",
    "sg:province":"CA",
    "wof:name":"Avery Middle School",
    "wof:placetype":"venue"
},
  "geometry": {"coordinates":[-120.3665,38.206862],"type":"Point"}
}