{
  "type": "Feature",
  "properties": {
    "iso:country":"US",
    "sg:address":"313 S Borchard Dr",
    "sg:city":"Ventura",
    "sg:classifiers":[
        {
            "category":"Personal",
            "subcategory":"Beauty Salon",
            "type":"Services"
        }
    ],
    "sg:phone":"+1 805 641 0631",
    "sg:postcode":"93003",
    "sg:province":"CA",
    "wof:name":"New Birds Hair Salon",
    "wof:placetype":"venue"
},
  "geometry": {"coordinates":[-119.26194700000001,34.269935],"type":"Point"}
}