{
  "type": "Feature",
  "properties": {
    "iso:country":"US",
    "sg:address":"162 Baxter St",
    "sg:city":"Vallejo",
    "sg:classifiers":[
        {
            "category":"Manufacturing",
            "subcategory":"Printing",
            "type":"Manufacturing & Wholesale Goods"
        }
    ],
    "sg:phone":"+1 707 644 6186",
    "sg:postcode":"94590",
    "sg:province":"CA",
    "sg:tags":[
        "printer"
    ],
    "wof:name":"Iconixdotbiz",
    "wof:placetype":"venue"
},
  "geometry": {"coordinates":[-122.266199,38.116492],"type":"Point"}
}