{
  "type": "Feature",
  "properties": {
    "addr:full":"2960 Wilshire Blvd Los Angeles CA 90010",
    "addr:housenumber":"2960",
    "addr:postcode":"90010",
    "addr:street":"Wilshire Blvd",
    "iso:country":"US",
    "sg:address":"2960 Wilshire Blvd",
    "sg:city":"Los Angeles",
    "sg:classifiers":[
        {
            "category":"Real Estate",
            "subcategory":"Real Estate Services",
            "type":"Services"
        }
    ],
    "sg:phone":"+1 213 380 4989",
    "sg:postcode":"90010",
    "sg:province":"CA",
    "sg:tags":[
        "management",
        "property"
    ],
    "wof:name":"Modern Investment & Realty Co",
    "wof:placetype":"venue"
},
  "geometry": {"coordinates":[-118.285945,34.061686],"type":"Point"}
}