{
  "type": "Feature",
  "properties": {
    "addr:full":"888 Valencia St San Francisco CA 94110",
    "addr:housenumber":"888",
    "addr:postcode":"94110",
    "addr:street":"Valencia St",
    "iso:country":"US",
    "sg:address":"888 Valencia St",
    "sg:city":"San Francisco",
    "sg:classifiers":[
        {
            "category":"Shopping",
            "subcategory":"Books",
            "type":"Retail Goods"
        }
    ],
    "sg:phone":"+1 415 282 9246",
    "sg:postcode":"94110",
    "sg:province":"CA",
    "sg:tags":[
        "dealer"
    ],
    "sg:website":"www.moderntimesbookstore.com",
    "wof:name":"Modern Times Bookstore",
    "wof:placetype":"venue"
},
  "geometry": {"coordinates":[-122.42139899999999,37.759192],"type":"Point"}
}