{
  "type": "Feature",
  "properties": {
    "iso:country":"US",
    "sg:address":"815 S Ardmore Ave",
    "sg:city":"Los Angeles",
    "sg:classifiers":[
        {
            "category":"Health Services",
            "subcategory":"Doctor",
            "type":"Services"
        }
    ],
    "sg:phone":"+1 213 387 6548",
    "sg:postcode":"90005",
    "sg:province":"CA",
    "wof:name":"Ham Chan H MD",
    "wof:placetype":"venue"
},
  "geometry": {"coordinates":[-118.302002,34.0569],"type":"Point"}
}