{
  "type": "Feature",
  "properties": {
    "addr:full":"3011 Beech St San Diego CA 92102",
    "addr:housenumber":"3011",
    "addr:postcode":"92102",
    "addr:street":"Beech St",
    "iso:country":"US",
    "sg:address":"3011 Beech St",
    "sg:city":"San Diego",
    "sg:classifiers":[
        {
            "category":"Real Estate",
            "subcategory":"Real Estate Services",
            "type":"Services"
        }
    ],
    "sg:phone":"+1 619 234 9553",
    "sg:postcode":"92102",
    "sg:province":"CA",
    "sg:tags":[
        "management",
        "property"
    ],
    "wof:name":"Vintage Realty",
    "wof:placetype":"venue"
},
  "geometry": {"coordinates":[-117.129997,32.721401],"type":"Point"}
}