{
  "type": "Feature",
  "properties": {
    "iso:country":"US",
    "sg:address":"3437 Myrtle Avenue Suite 335",
    "sg:city":"North Highlands",
    "sg:classifiers":[
        {
            "category":"Professional",
            "subcategory":"Computer Services",
            "type":"Services"
        }
    ],
    "sg:phone":"+1 916 349 0545",
    "sg:postcode":"95660",
    "sg:province":"CA",
    "sg:tags":[
        "repair"
    ],
    "sg:website":"www.laserage.biz",
    "wof:name":"Laser Age",
    "wof:placetype":"venue"
},
  "geometry": {"coordinates":[-121.384501,38.654176],"type":"Point"}
}