{
  "type": "Feature",
  "properties": {
    "addr:full":"16147 Crooked Creek Ct Chino Hills CA 91709",
    "addr:housenumber":"16147",
    "addr:postcode":"91709",
    "addr:street":"Crooked Creek Ct",
    "iso:country":"US",
    "sg:address":"16147 Crooked Creek Ct",
    "sg:city":"Chino Hills",
    "sg:classifiers":[
        {
            "category":"Professional",
            "subcategory":"Engineering",
            "type":"Services"
        }
    ],
    "sg:phone":"+1 909 518 5268",
    "sg:postcode":"91709",
    "sg:province":"CA",
    "sg:tags":[
        "engineer"
    ],
    "wof:name":"Eagle Mold Engineering",
    "wof:placetype":"venue"
},
  "geometry": {"coordinates":[-117.706022,33.960221],"type":"Point"}
}