{
  "type": "Feature",
  "properties": {
    "addr:full":"591 E Elder St Fallbrook CA 92028",
    "addr:housenumber":"591",
    "addr:postcode":"92028",
    "addr:street":"E Elder St",
    "iso:country":"US",
    "sg:address":"591 E Elder St",
    "sg:city":"Fallbrook",
    "sg:classifiers":[
        {
            "category":"Health Services",
            "subcategory":"Doctor",
            "type":"Services"
        }
    ],
    "sg:phone":"+1 760 723 6501",
    "sg:postcode":"92028",
    "sg:province":"CA",
    "sg:tags":[
        "physician",
        "surgeon"
    ],
    "wof:name":"Fallbrook Medical Assoc",
    "wof:placetype":"venue"
},
  "geometry": {"coordinates":[-117.246537,33.380103],"type":"Point"}
}