{
  "type": "Feature",
  "properties": {
    "addr:full":"44 Peppertree Ln Watsonville CA 95076",
    "addr:housenumber":"44",
    "addr:postcode":"95076",
    "addr:street":"Peppertree Ln",
    "iso:country":"US",
    "sg:address":"44 Peppertree Ln",
    "sg:city":"Watsonville",
    "sg:classifiers":[
        {
            "category":"Professional",
            "type":"Services"
        }
    ],
    "sg:phone":"+1 831 724 2145",
    "sg:postcode":"95076",
    "sg:province":"CA",
    "wof:name":"Daniel Robins",
    "wof:placetype":"venue"
},
  "geometry": {"coordinates":[-121.77808,36.926573],"type":"Point"}
}