{
  "type": "Feature",
  "properties": {
    "iso:country":"US",
    "sg:address":"5905 Corporate Ave",
    "sg:city":"Cypress",
    "sg:classifiers":[
        {
            "category":"Travel",
            "subcategory":"Hotels & Motels",
            "type":"Entertainment"
        }
    ],
    "sg:phone":"+1 714 828 4000",
    "sg:postcode":"90630",
    "sg:province":"CA",
    "wof:name":"Woodfin Suites Hotel Cypress",
    "wof:placetype":"venue"
},
  "geometry": {"coordinates":[-118.029999,33.807999],"type":"Point"}
}