{
  "type": "Feature",
  "properties": {
    "iso:country":"US",
    "sg:address":"1345 Park St",
    "sg:city":"Paso Robles",
    "sg:classifiers":[
        {
            "category":"Health Services",
            "subcategory":"Health Practitioner",
            "type":"Services"
        }
    ],
    "sg:phone":"+1 805 226 0975",
    "sg:postcode":"93446",
    "sg:province":"CA",
    "sg:tags":[
        "therapist",
        "physical"
    ],
    "wof:name":"San Luis Sports Therapy",
    "wof:placetype":"venue"
},
  "geometry": {"coordinates":[-120.690333,35.628399],"type":"Point"}
}