{
  "type": "Feature",
  "properties": {
    "iso:country":"US",
    "sg:address":"3445 S Main St",
    "sg:city":"Los Angeles",
    "sg:classifiers":[
        {
            "category":"Shopping",
            "subcategory":"Clothing, Apparel, & Fashions",
            "type":"Retail Goods"
        }
    ],
    "sg:phone":"+1 323 232 0567",
    "sg:postcode":"90007",
    "sg:province":"CA",
    "wof:name":"Y K Fashion",
    "wof:placetype":"venue"
},
  "geometry": {"coordinates":[-118.273076,34.018124],"type":"Point"}
}