{
  "type": "Feature",
  "properties": {
    "addr:full":"3048 Faith Home Rd Ceres CA 95307",
    "addr:housenumber":"3048",
    "addr:postcode":"95307",
    "addr:street":"Faith Home Rd",
    "iso:country":"US",
    "sg:address":"3048 Faith Home Rd",
    "sg:city":"Ceres",
    "sg:classifiers":[
        {
            "category":"Farming",
            "subcategory":"Crops",
            "type":"Manufacturing & Wholesale Goods"
        }
    ],
    "sg:phone":"+1 209 538 8410",
    "sg:postcode":"95307",
    "sg:province":"CA",
    "sg:tags":[
        "grove",
        "nut",
        "tree"
    ],
    "wof:name":"Frank Gomes",
    "wof:placetype":"venue"
},
  "geometry": {"coordinates":[-120.920378,37.592528],"type":"Point"}
}