{
  "type": "Feature",
  "properties": {
    "iso:country":"US",
    "sg:address":"1269 Fremont Blvd",
    "sg:city":"Seaside",
    "sg:classifiers":[
        {
            "category":"Shopping",
            "subcategory":"Used Merchandise",
            "type":"Retail Goods"
        }
    ],
    "sg:phone":"+1 831 899 2211",
    "sg:postcode":"93955",
    "sg:province":"CA",
    "sg:tags":[
        "shop",
        "thrift"
    ],
    "wof:name":"St Vincent De Paul Society Ctr",
    "wof:placetype":"venue"
},
  "geometry": {"coordinates":[-121.847912,36.604409],"type":"Point"}
}