{
  "type": "Feature",
  "properties": {
    "addr:full":"1162 Samoa Blvd Arcata CA 95521",
    "addr:housenumber":"1162",
    "addr:postcode":"95521",
    "addr:street":"Samoa Blvd",
    "iso:country":"US",
    "sg:address":"1162 Samoa Blvd",
    "sg:city":"Arcata",
    "sg:classifiers":[
        {
            "category":"Wholesale",
            "subcategory":"Sporting Goods",
            "type":"Manufacturing & Wholesale Goods"
        }
    ],
    "sg:phone":"+1 707 826 2887",
    "sg:postcode":"95521",
    "sg:province":"CA",
    "sg:tags":[
        "distributor",
        "boat"
    ],
    "sg:website":"www.wing.com",
    "wof:name":"Wing Inflatables",
    "wof:placetype":"venue"
},
  "geometry": {"coordinates":[-124.091922,40.865983],"type":"Point"}
}