{
  "type": "Feature",
  "properties": {
    "addr:full":"14141 Pso Verde Tustin CA 92780",
    "addr:housenumber":"14141",
    "addr:postcode":"92780",
    "addr:street":"Pso Verde",
    "iso:country":"US",
    "sg:address":"14141 Pso Verde",
    "sg:city":"Tustin",
    "sg:classifiers":[
        {
            "category":"Professional",
            "type":"Services"
        }
    ],
    "sg:phone":"+1 714 731 1294",
    "sg:postcode":"92780",
    "sg:province":"CA",
    "wof:name":"E Janedoe Co",
    "wof:placetype":"venue"
},
  "geometry": {"coordinates":[-117.828275,33.757637],"type":"Point"}
}