{
  "type": "Feature",
  "properties": {
    "iso:country":"US",
    "sg:address":"2724 Garnet Ave",
    "sg:city":"San Diego",
    "sg:classifiers":[
        {
            "category":"Retail",
            "subcategory":"Auto Repair",
            "type":"Services"
        }
    ],
    "sg:phone":"+1 858 581 9000",
    "sg:postcode":"92109",
    "sg:province":"CA",
    "sg:tags":[
        "repairing",
        "tire"
    ],
    "sg:website":"www.discounttire.com",
    "wof:name":"Discount Tire Co",
    "wof:placetype":"venue"
},
  "geometry": {"coordinates":[-117.221062,32.805639],"type":"Point"}
}