{
  "type": "Feature",
  "properties": {
    "addr:full":"212 N Yale Ave Claremont CA 91711",
    "addr:housenumber":"212",
    "addr:postcode":"91711",
    "addr:street":"N Yale Ave",
    "iso:country":"US",
    "sg:address":"212 N Yale Ave",
    "sg:city":"Claremont",
    "sg:classifiers":[
        {
            "category":"Banks & Credit Unions",
            "subcategory":"Investment Brokerage",
            "type":"Services"
        }
    ],
    "sg:phone":"+1 909 625 5751",
    "sg:postcode":"91711",
    "sg:province":"CA",
    "sg:tags":[
        "consultant",
        "planning",
        "financial"
    ],
    "wof:name":"Carlos A Bolanos & Assoc",
    "wof:placetype":"venue"
},
  "geometry": {"coordinates":[-117.71781,34.096487],"type":"Point"}
}