{
  "type": "Feature",
  "properties": {
    "addr:full":"10101 Yucca Rd Adelanto CA 92301",
    "addr:housenumber":"10101",
    "addr:postcode":"92301",
    "addr:street":"Yucca Rd",
    "iso:country":"US",
    "sg:address":"10101 Yucca Rd",
    "sg:city":"Adelanto",
    "sg:classifiers":[
        {
            "category":"Manufacturing",
            "subcategory":"Toys & Sporting Goods",
            "type":"Manufacturing & Wholesale Goods"
        }
    ],
    "sg:phone":"+1 760 246 6462",
    "sg:postcode":"92301",
    "sg:province":"CA",
    "sg:tags":[
        "hobby",
        "model",
        "supply"
    ],
    "sg:website":"www.houseofbalsa.com",
    "wof:name":"House Of Balsa Inc",
    "wof:placetype":"venue"
},
  "geometry": {"coordinates":[-117.444228,34.564845],"type":"Point"}
}