{
  "type": "Feature",
  "properties": {
    "iso:country":"US",
    "sg:address":"3340 Revere Ave",
    "sg:city":"Oakland",
    "sg:classifiers":[
        {
            "category":"Wholesale",
            "subcategory":"Electrical",
            "type":"Manufacturing & Wholesale Goods"
        }
    ],
    "sg:phone":"+1 510 562 3102",
    "sg:postcode":"94605",
    "sg:province":"CA",
    "sg:tags":[
        "alarm",
        "burglar",
        "system"
    ],
    "wof:name":"MIGA Security Burglar Alarm",
    "wof:placetype":"venue"
},
  "geometry": {"coordinates":[-122.132217,37.734697],"type":"Point"}
}