{
  "type": "Feature",
  "properties": {
    "iso:country":"US",
    "sg:address":"17410 Ave 352",
    "sg:city":"Visalia",
    "sg:classifiers":[
        {
            "category":"Wholesale",
            "subcategory":"Groceries",
            "type":"Manufacturing & Wholesale Goods"
        }
    ],
    "sg:phone":"+1 559 798 0283",
    "sg:postcode":"93292",
    "sg:province":"CA",
    "sg:tags":[
        "grocer"
    ],
    "wof:name":"Lo Bue Farms Inc",
    "wof:placetype":"venue"
},
  "geometry": {"coordinates":[-119.187774,36.428398],"type":"Point"}
}