{
  "type": "Feature",
  "properties": {
    "addr:full":"12341 Harbor Blvd Garden Grove CA 92840",
    "addr:housenumber":"12341",
    "addr:postcode":"92840",
    "addr:street":"Harbor Blvd",
    "iso:country":"US",
    "sg:address":"12341 Harbor Blvd",
    "sg:city":"Garden Grove",
    "sg:classifiers":[
        {
            "category":"Donuts",
            "subcategory":"None",
            "type":"Food & Drink"
        }
    ],
    "sg:phone":"+1 714 534 4251",
    "sg:postcode":"92840",
    "sg:province":"CA",
    "wof:name":"Donuts & Pastries",
    "wof:placetype":"venue"
},
  "geometry": {"coordinates":[-117.915001,33.783901],"type":"Point"}
}