{
  "type": "Feature",
  "properties": {
    "iso:country":"US",
    "sg:address":"2170 Academy Ave",
    "sg:city":"Sanger",
    "sg:classifiers":[
        {
            "category":"Manufacturing",
            "subcategory":"Tools & Machinery",
            "type":"Manufacturing & Wholesale Goods"
        }
    ],
    "sg:phone":"+1 559 875 5563",
    "sg:postcode":"93657",
    "sg:province":"CA",
    "sg:tags":[
        "paper",
        "industrial",
        "mfg"
    ],
    "wof:name":"Adco Manufacturing",
    "wof:placetype":"venue"
},
  "geometry": {"coordinates":[-119.55439,36.691092],"type":"Point"}
}