{
  "type": "Feature",
  "properties": {
    "iso:country":"US",
    "sg:address":"401 Santa Fe Ave",
    "sg:city":"Richmond",
    "sg:classifiers":[
        {
            "category":"Wholesale",
            "subcategory":"Office Equipment",
            "type":"Manufacturing & Wholesale Goods"
        },
        {
            "category":"Shopping",
            "subcategory":"Stationery & Office Supplies",
            "type":"Retail Goods"
        }
    ],
    "sg:phone":"+1 510 232 8887",
    "sg:postcode":"94801",
    "sg:province":"CA",
    "sg:tags":[
        "register",
        "autographic"
    ],
    "wof:name":"Jackforms",
    "wof:placetype":"venue"
},
  "geometry": {"coordinates":[-122.388059,37.925526],"type":"Point"}
}