{
  "type": "Feature",
  "properties": {
    "addr:full":"1121 15th Street Sacramento CA 95814",
    "addr:housenumber":"1121",
    "addr:postcode":"95814",
    "addr:street":"15Th Street",
    "iso:country":"US",
    "sg:address":"1121 15th Street",
    "sg:city":"Sacramento",
    "sg:classifiers":[
        {
            "category":"Travel",
            "subcategory":"Hotels & Motels",
            "type":"Entertainment"
        }
    ],
    "sg:phone":"+1 916 443 0500",
    "sg:postcode":"95814",
    "sg:province":"CA",
    "sg:website":"www.marriott.com/hotels/travel/s...",
    "wof:name":"Residence Inn",
    "wof:placetype":"venue"
},
  "geometry": {"coordinates":[-121.487134,38.577132],"type":"Point"}
}