{
  "type": "Feature",
  "properties": {
    "iso:country":"US",
    "sg:address":"525 South Dr",
    "sg:city":"Mountain View",
    "sg:classifiers":[
        {
            "category":"Health Services",
            "subcategory":"Doctor",
            "type":"Services"
        }
    ],
    "sg:phone":"+1 650 988 7945",
    "sg:postcode":"94040",
    "sg:province":"CA",
    "wof:name":"Thomas Lei MD",
    "wof:placetype":"venue"
},
  "geometry": {"coordinates":[-122.084868,37.367092],"type":"Point"}
}