{
  "type": "Feature",
  "properties": {
    "iso:country":"US",
    "sg:address":"513 30th St Suite 100",
    "sg:city":"Newport Beach",
    "sg:classifiers":[
        {
            "category":"Banks & Credit Unions",
            "subcategory":"Investment Brokerage",
            "type":"Services"
        }
    ],
    "sg:phone":"+1 949 720 3800",
    "sg:postcode":"92663",
    "sg:province":"CA",
    "sg:tags":[
        "investing"
    ],
    "wof:name":"Belcourt Investments",
    "wof:placetype":"venue"
},
  "geometry": {"coordinates":[-117.927938,33.614846],"type":"Point"}
}