{
  "type": "Feature",
  "properties": {
    "addr:full":"370 - 43rd St Oakland CA 94609",
    "addr:housenumber":"370",
    "addr:postcode":"94609",
    "addr:street":"43Rd St",
    "iso:country":"US",
    "sg:address":"370 - 43rd St",
    "sg:city":"Oakland",
    "sg:classifiers":[
        {
            "category":"Recreation",
            "type":"Entertainment"
        }
    ],
    "sg:phone":"+1 510 719 8652",
    "sg:postcode":"94609",
    "sg:province":"CA",
    "sg:tags":[
        "summer",
        "camp"
    ],
    "sg:website":"parkdaysummerartscamp.com",
    "wof:name":"Park Day Summer Arts Camp",
    "wof:placetype":"venue"
},
  "geometry": {"coordinates":[-122.25753400000001,37.832245],"type":"Point"}
}