{
  "type": "Feature",
  "properties": {
    "addr:full":"25 Van Ness Ave San Francisco CA 94102",
    "addr:housenumber":"25",
    "addr:postcode":"94102",
    "addr:street":"Van Ness Ave",
    "iso:country":"US",
    "sg:address":"25 Van Ness Ave",
    "sg:city":"San Francisco",
    "sg:classifiers":[
        {
            "category":"Government",
            "subcategory":"Office",
            "type":"Public Place"
        }
    ],
    "sg:phone":"+1 415 554 9800",
    "sg:postcode":"94102",
    "sg:province":"CA",
    "sg:tags":[
        "village"
    ],
    "wof:name":"S F Parking & Traffic Comm",
    "wof:placetype":"venue"
},
  "geometry": {"coordinates":[-122.419606,37.776327],"type":"Point"}
}