{
  "type": "Feature",
  "properties": {
    "iso:country":"US",
    "sg:address":"16161 Ventura Blvd. Suite C840",
    "sg:city":"Encino",
    "sg:classifiers":[
        {
            "category":"Professional",
            "subcategory":"Computer Services",
            "type":"Services"
        }
    ],
    "sg:phone":"+1 310 954 1994",
    "sg:postcode":"91436",
    "sg:province":"CA",
    "sg:tags":[
        "pop-culture",
        "news-wire",
        "content"
    ],
    "sg:website":"http://www.popnewswire.tv/",
    "wof:name":"PopNews Wire",
    "wof:placetype":"venue"
},
  "geometry": {"coordinates":[-118.486876,34.15686],"type":"Point"}
}