{
  "type": "Feature",
  "properties": {
    "addr:full":"5450 Fulton Rd Santa Rosa CA 95403",
    "addr:housenumber":"5450",
    "addr:postcode":"95403",
    "addr:street":"Fulton Rd",
    "iso:country":"US",
    "sg:address":"5450 Fulton Rd",
    "sg:city":"Santa Rosa",
    "sg:classifiers":[
        {
            "category":"Retail",
            "subcategory":"Repair Shop",
            "type":"Services"
        }
    ],
    "sg:phone":"+1 707 523 1330",
    "sg:postcode":"95403",
    "sg:province":"CA",
    "sg:tags":[
        "upholsterer"
    ],
    "wof:name":"LJM Mobile Upholstery",
    "wof:placetype":"venue"
},
  "geometry": {"coordinates":[-122.76978800000001,38.513801],"type":"Point"}
}