{
  "type": "Feature",
  "properties": {
    "addr:full":"2420 Palm Ave San Diego CA 92154",
    "addr:housenumber":"2420",
    "addr:postcode":"92154",
    "addr:street":"Palm Ave",
    "iso:country":"US",
    "sg:address":"2420 Palm Ave",
    "sg:city":"San Diego",
    "sg:classifiers":[
        {
            "category":"Real Estate",
            "subcategory":"Real Estate Operator",
            "type":"Services"
        }
    ],
    "sg:phone":"+1 619 423 6330",
    "sg:postcode":"92154",
    "sg:province":"CA",
    "sg:tags":[
        "mobile",
        "home",
        "community"
    ],
    "wof:name":"LA Palma Mobile Estates",
    "wof:placetype":"venue"
},
  "geometry": {"coordinates":[-117.081734,32.583969],"type":"Point"}
}