{
  "type": "Feature",
  "properties": {
    "iso:country":"US",
    "sg:address":"160 Ware Rd",
    "sg:city":"Redwood City",
    "sg:classifiers":[
        {
            "category":"Professional",
            "type":"Services"
        }
    ],
    "sg:phone":"+1 650 851 4653",
    "sg:postcode":"94062",
    "sg:province":"CA",
    "wof:name":"Andrew Porter",
    "wof:placetype":"venue"
},
  "geometry": {"coordinates":[-122.328582,37.443265],"type":"Point"}
}