{
  "type": "Feature",
  "properties": {
    "iso:country":"US",
    "sg:address":"15642 Sand Canyon Ave",
    "sg:city":"Irvine",
    "sg:classifiers":[
        {
            "category":"Government",
            "subcategory":"Post Office",
            "type":"Public Place"
        }
    ],
    "sg:phone":"+1 949 453 4948",
    "sg:postcode":"92618",
    "sg:province":"CA",
    "sg:tags":[
        "postal",
        "us"
    ],
    "wof:name":"US Post Office",
    "wof:placetype":"venue"
},
  "geometry": {"coordinates":[-117.765705,33.669886],"type":"Point"}
}