{
  "type": "Feature",
  "properties": {
    "addr:full":"3973 Schaefer Ave Chino CA 91710",
    "addr:housenumber":"3973",
    "addr:postcode":"91710",
    "addr:street":"Schaefer Ave",
    "iso:country":"US",
    "sg:address":"3973 Schaefer Ave",
    "sg:city":"Chino",
    "sg:classifiers":[
        {
            "category":"Health Services",
            "subcategory":"Podiatrist",
            "type":"Services"
        }
    ],
    "sg:phone":"+1 909 591 7888",
    "sg:postcode":"91710",
    "sg:province":"CA",
    "sg:tags":[
        "equipment",
        "supply"
    ],
    "wof:name":"Gloveco, Inc",
    "wof:placetype":"venue"
},
  "geometry": {"coordinates":[-117.718058,34.00436],"type":"Point"}
}