{
  "type": "Feature",
  "properties": {
    "addr:full":"13781 Ave 328 Visalia CA 93292",
    "addr:housenumber":"13781",
    "addr:postcode":"93292",
    "addr:street":"Ave 328",
    "iso:country":"US",
    "sg:address":"13781 Ave 328",
    "sg:city":"Visalia",
    "sg:classifiers":[
        {
            "category":"Organizations",
            "subcategory":"Professional Association",
            "type":"Services"
        }
    ],
    "sg:phone":"+1 559 732 3257",
    "sg:postcode":"93292",
    "sg:province":"CA",
    "wof:name":"Elbow Creek Grange Hall",
    "wof:placetype":"venue"
},
  "geometry": {"coordinates":[-119.265872,36.385426],"type":"Point"}
}