{
  "type": "Feature",
  "properties": {
    "addr:full":"12250 Craig Ave Red Bluff CA 96080",
    "addr:housenumber":"12250",
    "addr:postcode":"96080",
    "addr:street":"Craig Ave",
    "iso:country":"US",
    "sg:address":"12250 Craig Ave",
    "sg:city":"Red Bluff",
    "sg:classifiers":[
        {
            "category":"Building & Trades",
            "subcategory":"Construction",
            "type":"Services"
        }
    ],
    "sg:phone":"+1 530 527 9370",
    "sg:postcode":"96080",
    "sg:province":"CA",
    "sg:tags":[
        "designer",
        "dealer",
        "pool",
        "swimming"
    ],
    "wof:name":"Blue Haven Pools",
    "wof:placetype":"venue"
},
  "geometry": {"coordinates":[-122.135299,40.151393],"type":"Point"}
}