{
  "type": "Feature",
  "properties": {
    "iso:country":"US",
    "sg:address":"2559 El Camino Real",
    "sg:city":"Carlsbad",
    "sg:classifiers":[
        {
            "category":"Restaurant",
            "type":"Food & Drink"
        }
    ],
    "sg:phone":"+1 760 729 2400",
    "sg:postcode":"92008",
    "sg:province":"CA",
    "wof:name":"Einstein Noah Restaurant Group, Inc.",
    "wof:placetype":"venue"
},
  "geometry": {"coordinates":[-117.326767,33.178379],"type":"Point"}
}