{
  "type": "Feature",
  "properties": {
    "iso:country":"US",
    "sg:address":"2302 Bessie Ave",
    "sg:city":"Tracy",
    "sg:classifiers":[
        {
            "category":"Government",
            "subcategory":"Office",
            "type":"Public Place"
        }
    ],
    "sg:phone":"+1 209 832 7881",
    "sg:postcode":"95376",
    "sg:province":"CA",
    "sg:tags":[
        "village"
    ],
    "wof:name":"Tracy Teen Ctr",
    "wof:placetype":"venue"
},
  "geometry": {"coordinates":[-121.43302300000001,37.754102],"type":"Point"}
}