{
  "type": "Feature",
  "properties": {
    "addr:full":"711 Eddy St San Francisco CA 94109",
    "addr:housenumber":"711",
    "addr:postcode":"94109",
    "addr:street":"Eddy St",
    "iso:country":"US",
    "sg:address":"711 Eddy St",
    "sg:city":"San Francisco",
    "sg:classifiers":[
        {
            "category":"Social Services",
            "type":"Services"
        }
    ],
    "sg:phone":"+1 415 776 0114",
    "sg:postcode":"94109",
    "sg:province":"CA",
    "sg:tags":[
        "housing",
        "assistance"
    ],
    "sg:website":"www.ncphs.org",
    "wof:name":"Eastern Park Apartments",
    "wof:placetype":"venue"
},
  "geometry": {"coordinates":[-122.42067299999999,37.782841],"type":"Point"}
}