{
  "type": "Feature",
  "properties": {
    "addr:full":"3244 E Thousand Oaks Blvd Thousand Oaks CA 91362",
    "addr:housenumber":"3244",
    "addr:postcode":"91362",
    "addr:street":"E Thousand Oaks Blvd",
    "iso:country":"US",
    "sg:address":"3244 E Thousand Oaks Blvd",
    "sg:city":"Thousand Oaks",
    "sg:classifiers":[
        {
            "category":"Autos & Motor Vehicles",
            "subcategory":"Automobile Sales",
            "type":"Retail Goods"
        }
    ],
    "sg:phone":"+1 805 496 8095",
    "sg:postcode":"91362",
    "sg:province":"CA",
    "sg:tags":[
        "used"
    ],
    "wof:name":"Resale Motors Of Thousand Oaks",
    "wof:placetype":"venue"
},
  "geometry": {"coordinates":[-118.835426,34.168531],"type":"Point"}
}