{
  "type": "Feature",
  "properties": {
    "addr:full":"1307 N H St Ste C Lompoc CA 93436",
    "addr:housenumber":"1307",
    "addr:postcode":"93436",
    "addr:street":"N H St Ste C",
    "iso:country":"US",
    "sg:address":"1307 N H St Ste C",
    "sg:city":"Lompoc",
    "sg:classifiers":[
        {
            "category":"Banks & Credit Unions",
            "subcategory":"Bank",
            "type":"Services"
        }
    ],
    "sg:phone":"+1 805 735 8882",
    "sg:postcode":"93436",
    "sg:province":"CA",
    "sg:tags":[
        "saving",
        "commercial"
    ],
    "sg:website":"http://www.pacificcapitalbank.com",
    "wof:name":"Pacific Capital Bankcorp",
    "wof:placetype":"venue"
},
  "geometry": {"coordinates":[-120.45764,34.659068],"type":"Point"}
}