{
  "type": "Feature",
  "properties": {
    "addr:full":"7406 State St Huntington Park CA 90255",
    "addr:housenumber":"7406",
    "addr:postcode":"90255",
    "addr:street":"State St;Park",
    "iso:country":"US",
    "sg:address":"7406 State St",
    "sg:city":"Huntington Park",
    "sg:classifiers":[
        {
            "category":"Personal",
            "subcategory":"Beauty Salon",
            "type":"Services"
        }
    ],
    "sg:phone":"+1 323 587 3088",
    "sg:postcode":"90255",
    "sg:province":"CA",
    "sg:tags":[
        "nail",
        "manicuring"
    ],
    "wof:name":"Nail Club",
    "wof:placetype":"venue"
},
  "geometry": {"coordinates":[-118.209999,33.9706],"type":"Point"}
}