{
  "type": "Feature",
  "properties": {
    "addr:full":"716 S Corrida Dr Covina CA 91724",
    "addr:housenumber":"716",
    "addr:postcode":"91724",
    "addr:street":"S Corrida Dr",
    "iso:country":"US",
    "sg:address":"716 S Corrida Dr",
    "sg:city":"Covina",
    "sg:classifiers":[
        {
            "category":"Professional",
            "type":"Services"
        }
    ],
    "sg:phone":"+1 626 332 0482",
    "sg:postcode":"91724",
    "sg:province":"CA",
    "wof:name":"Sam Melendres",
    "wof:placetype":"venue"
},
  "geometry": {"coordinates":[-117.86259200000001,34.075828],"type":"Point"}
}