{
  "type": "Feature",
  "properties": {
    "addr:full":"407 S Anaheim Blvd Anaheim CA 92805",
    "addr:housenumber":"407",
    "addr:postcode":"92805",
    "addr:street":"S Anaheim Blvd",
    "iso:country":"US",
    "sg:address":"407 S Anaheim Blvd",
    "sg:city":"Anaheim",
    "sg:classifiers":[
        {
            "category":"Autos & Motor Vehicles",
            "subcategory":"Automobile Sales",
            "type":"Retail Goods"
        }
    ],
    "sg:phone":"+1 714 776 7230",
    "sg:postcode":"92805",
    "sg:province":"CA",
    "sg:tags":[
        "car",
        "dealer"
    ],
    "wof:name":"Acapulco Auto Sales",
    "wof:placetype":"venue"
},
  "geometry": {"coordinates":[-117.912623,33.83165],"type":"Point"}
}