{
  "type": "Feature",
  "properties": {
    "addr:full":"20054 Northcliff Dr Santa Clarita CA 91351",
    "addr:postcode":"20054;91351",
    "addr:street":"Northcliff Dr",
    "iso:country":"US",
    "sg:address":"20054 Northcliff Dr",
    "sg:city":"Santa Clarita",
    "sg:classifiers":[
        {
            "category":"Professional",
            "type":"Services"
        }
    ],
    "sg:phone":"+1 818 326 6942",
    "sg:postcode":"91351",
    "sg:province":"CA",
    "wof:name":"Meghan Aileen Photography",
    "wof:placetype":"venue"
},
  "geometry": {"coordinates":[-118.484235,34.429585],"type":"Point"}
}