{
  "type": "Feature",
  "properties": {
    "iso:country":"US",
    "sg:address":"111 E Lime Ave",
    "sg:city":"Monrovia",
    "sg:classifiers":[
        {
            "category":"Personal",
            "subcategory":"Beauty Salon",
            "type":"Services"
        }
    ],
    "sg:phone":"+1 626 303 4247",
    "sg:postcode":"91016",
    "sg:province":"CA",
    "wof:name":"Verita",
    "wof:placetype":"venue"
},
  "geometry": {"coordinates":[-118.00074600000001,34.148074],"type":"Point"}
}