{
  "type": "Feature",
  "properties": {
    "iso:country":"US",
    "sg:address":"728 Cornish Dr",
    "sg:city":"Encinitas",
    "sg:classifiers":[
        {
            "category":"Communications",
            "subcategory":"Radio Station",
            "type":"Services"
        }
    ],
    "sg:phone":"+1 760 944 8999",
    "sg:postcode":"92024",
    "sg:province":"CA",
    "sg:tags":[
        "broadcast"
    ],
    "wof:name":"Digital Broadcasting Services",
    "wof:placetype":"venue"
},
  "geometry": {"coordinates":[-117.290355,33.042713],"type":"Point"}
}