{
  "type": "Feature",
  "properties": {
    "addr:full":"780 E Gilbert St San Bernardino CA 92404",
    "addr:housenumber":"780",
    "addr:postcode":"92404",
    "addr:street":"E Gilbert St",
    "iso:country":"US",
    "sg:address":"780 E Gilbert St",
    "sg:city":"San Bernardino",
    "sg:classifiers":[
        {
            "category":"Education",
            "subcategory":"Library",
            "type":"Public Place"
        }
    ],
    "sg:phone":"+1 909 387 7996",
    "sg:postcode":"92404",
    "sg:province":"CA",
    "sg:tags":[
        "special",
        "interest"
    ],
    "wof:name":"Medical Center Library",
    "wof:placetype":"venue"
},
  "geometry": {"coordinates":[-117.269876,34.126886],"type":"Point"}
}