{
  "type": "Feature",
  "properties": {
    "iso:country":"US",
    "sg:address":"1601 W Imperial Hwy",
    "sg:city":"La Habra",
    "sg:classifiers":[
        {
            "category":"Shopping",
            "subcategory":"Clothing, Apparel, & Fashions",
            "type":"Retail Goods"
        },
        {
            "category":"Shopping",
            "subcategory":"Party Supplies",
            "type":"Retail Goods"
        }
    ],
    "sg:phone":"+1 562 697 0086",
    "sg:postcode":"90631",
    "sg:province":"CA",
    "sg:tags":[
        "costume"
    ],
    "wof:name":"Party City of La Habra",
    "wof:placetype":"venue"
},
  "geometry": {"coordinates":[-117.963997,33.917198],"type":"Point"}
}