{
  "type": "Feature",
  "properties": {
    "addr:full":"117 W 9th St Los Angeles CA 90015",
    "addr:housenumber":"117",
    "addr:postcode":"90015",
    "addr:street":"W 9Th St",
    "iso:country":"US",
    "sg:address":"117 W 9th St",
    "sg:city":"Los Angeles",
    "sg:classifiers":[
        {
            "category":"Manufacturing",
            "subcategory":"Jewelry",
            "type":"Manufacturing & Wholesale Goods"
        },
        {
            "category":"Shopping",
            "subcategory":"Jewelry",
            "type":"Retail Goods"
        }
    ],
    "sg:phone":"+1 213 622 2868",
    "sg:postcode":"90015",
    "sg:province":"CA",
    "sg:tags":[
        "precious",
        "designer",
        "metal",
        "mfg"
    ],
    "wof:name":"Yeung Designs",
    "wof:placetype":"venue"
},
  "geometry": {"coordinates":[-118.255214,34.041843],"type":"Point"}
}