{
  "type": "Feature",
  "properties": {
    "iso:country":"US",
    "sg:address":"1040 N Grove St",
    "sg:city":"Anaheim",
    "sg:classifiers":[
        {
            "category":"Autos & Motor Vehicles",
            "subcategory":"Automobile Sales",
            "type":"Retail Goods"
        }
    ],
    "sg:phone":"+1 714 630 4687",
    "sg:postcode":"92806",
    "sg:province":"CA",
    "sg:tags":[
        "trailer",
        "transport"
    ],
    "wof:name":"Apex Custom and Trailers",
    "wof:placetype":"venue"
},
  "geometry": {"coordinates":[-117.842231,33.85174],"type":"Point"}
}