{
  "type": "Feature",
  "properties": {
    "iso:country":"US",
    "sg:address":"96 N 3rd Street",
    "sg:city":"San Jose",
    "sg:classifiers":[
        {
            "category":"Professional",
            "subcategory":"Lawyer & Legal Services",
            "type":"Services"
        }
    ],
    "sg:phone":"+1 408 999 5678",
    "sg:postcode":"95112",
    "sg:province":"CA",
    "wof:name":"Taaffe Christopher E Atty",
    "wof:placetype":"venue"
},
  "geometry": {"coordinates":[-121.889438,37.33858],"type":"Point"}
}