{
  "type": "Feature",
  "properties": {
    "iso:country":"US",
    "sg:address":"2109 Shattuck Avenue Apt 206",
    "sg:city":"Berkeley",
    "sg:classifiers":[
        {
            "category":"Education",
            "subcategory":"Music School",
            "type":"Public Place"
        }
    ],
    "sg:phone":"+1 510 548 5146",
    "sg:postcode":"94704",
    "sg:province":"CA",
    "sg:tags":[
        "instrument",
        "teacher",
        "musical"
    ],
    "wof:name":"John Peters Piano Service",
    "wof:placetype":"venue"
},
  "geometry": {"coordinates":[-122.26799800000001,37.8703],"type":"Point"}
}