{
  "type": "Feature",
  "properties": {
    "iso:country":"US",
    "sg:address":"141 Sand Creek Rd",
    "sg:city":"Brentwood",
    "sg:classifiers":[
        {
            "category":"Health Services",
            "subcategory":"Dentist",
            "type":"Services"
        }
    ],
    "sg:phone":"+1 925 240 8843",
    "sg:postcode":"94513",
    "sg:province":"CA",
    "wof:name":"CASTRO MIGUEL A DDS",
    "wof:placetype":"venue"
},
  "geometry": {"coordinates":[-121.698823,37.946857],"type":"Point"}
}