{
  "type": "Feature",
  "properties": {
    "iso:country":"US",
    "sg:address":"311 N Robertson Blvd Ste 705",
    "sg:city":"Beverly Hills",
    "sg:classifiers":[
        {
            "category":"Personal",
            "type":"Services"
        }
    ],
    "sg:phone":"+1 310 657 7364",
    "sg:postcode":"90211",
    "sg:province":"CA",
    "sg:tags":[
        "shopping"
    ],
    "sg:website":"www.remiofbh.com",
    "wof:name":"REMI Beverly Hills",
    "wof:placetype":"venue"
},
  "geometry": {"coordinates":[-118.383741,34.077481],"type":"Point"}
}