{
  "type": "Feature",
  "properties": {
    "addr:full":"4921 Cedar Ave El Monte CA 91732",
    "addr:housenumber":"4921",
    "addr:postcode":"91732",
    "addr:street":"Cedar Ave",
    "iso:country":"US",
    "sg:address":"4921 Cedar Ave",
    "sg:city":"El Monte",
    "sg:classifiers":[
        {
            "category":"Education",
            "subcategory":"School",
            "type":"Public Place"
        }
    ],
    "sg:phone":"+1 626 444 9201",
    "sg:postcode":"91732",
    "sg:province":"CA",
    "wof:name":"Arroyo High School",
    "wof:placetype":"venue"
},
  "geometry": {"coordinates":[-118.020403,34.094178],"type":"Point"}
}