{
  "type": "Feature",
  "properties": {
    "addr:full":"90 S Spruce Ave S San Francisco CA 94080",
    "addr:housenumber":"90",
    "addr:postcode":"94080",
    "addr:street":"S Spruce Ave S",
    "iso:country":"US",
    "sg:address":"90 S Spruce Ave",
    "sg:city":"S San Francisco",
    "sg:classifiers":[
        {
            "category":"Professional",
            "subcategory":"Accounting & Tax Preparation",
            "type":"Services"
        }
    ],
    "sg:phone":"+1 650 872 3862",
    "sg:postcode":"94080",
    "sg:province":"CA",
    "sg:tags":[
        "return",
        "filing"
    ],
    "wof:name":"System Designers' Group",
    "wof:placetype":"venue"
},
  "geometry": {"coordinates":[-122.41704799999999,37.653549],"type":"Point"}
}