{
  "type": "Feature",
  "properties": {
    "iso:country":"US",
    "sg:address":"381 Sandburg Dr",
    "sg:city":"Sacramento",
    "sg:classifiers":[
        {
            "category":"Manufacturing",
            "subcategory":"Printing",
            "type":"Manufacturing & Wholesale Goods"
        }
    ],
    "sg:phone":"+1 916 455 5890",
    "sg:postcode":"95819",
    "sg:province":"CA",
    "sg:tags":[
        "broker"
    ],
    "wof:name":"Sfl Graphics & Printing Svc",
    "wof:placetype":"venue"
},
  "geometry": {"coordinates":[-121.427988,38.569873],"type":"Point"}
}