{
  "type": "Feature",
  "properties": {
    "addr:full":"4921 Birch St Ste 100 Newport Beach CA 92660",
    "addr:housenumber":"4921",
    "addr:postcode":"92660",
    "addr:street":"Birch St Ste 100",
    "iso:country":"US",
    "sg:address":"4921 Birch St Ste 100",
    "sg:city":"Newport Beach",
    "sg:classifiers":[
        {
            "category":"Real Estate",
            "subcategory":"Architect",
            "type":"Services"
        }
    ],
    "sg:phone":"+1 949 261 1800",
    "sg:postcode":"92660",
    "sg:province":"CA",
    "wof:name":"Adapt Architecture Inc.",
    "wof:placetype":"venue"
},
  "geometry": {"coordinates":[-117.86017699999999,33.667348],"type":"Point"}
}