{
  "type": "Feature",
  "properties": {
    "iso:country":"US",
    "sg:address":"14484 Lost Hills Rd",
    "sg:city":"Lost Hills",
    "sg:classifiers":[
        {
            "category":"Mining & Drilling",
            "type":"Manufacturing & Wholesale Goods"
        }
    ],
    "sg:phone":"+1 661 797 2811",
    "sg:postcode":"93249",
    "sg:province":"CA",
    "sg:tags":[
        "mud",
        "oil",
        "well",
        "additive"
    ],
    "wof:name":"California Drilling Fluids",
    "wof:placetype":"venue"
},
  "geometry": {"coordinates":[-119.689695,35.619888],"type":"Point"}
}