{
  "type": "Feature",
  "properties": {
    "addr:full":"13901 Hawthorne Boulevard Hawthorne CA 90250",
    "addr:housenumber":"13901",
    "addr:postcode":"90250",
    "addr:street":"Hawthorne Boulevard",
    "iso:country":"US",
    "sg:address":"13901 Hawthorne Boulevard",
    "sg:city":"Hawthorne",
    "sg:classifiers":[
        {
            "category":"Retail",
            "subcategory":"Auto Rental",
            "type":"Services"
        }
    ],
    "sg:phone":"+1 310 679 7368",
    "sg:postcode":"90250",
    "sg:province":"CA",
    "sg:tags":[
        "car"
    ],
    "wof:name":"Enterprise Rent-A-Car",
    "wof:placetype":"venue"
},
  "geometry": {"coordinates":[-118.352823,33.90524],"type":"Point"}
}