{
  "type": "Feature",
  "properties": {
    "addr:full":"6421 Hedding St Los Angeles CA 90045",
    "addr:postcode":"6421;90045",
    "addr:street":"Hedding St",
    "iso:country":"US",
    "sg:address":"6421 Hedding St",
    "sg:city":"Los Angeles",
    "sg:classifiers":[
        {
            "category":"Museum",
            "type":"Entertainment"
        }
    ],
    "sg:phone":"+1 310 215 0215",
    "sg:postcode":"90045",
    "sg:province":"CA",
    "wof:name":"Art Mural",
    "wof:placetype":"venue"
},
  "geometry": {"coordinates":[-118.403009,33.975861],"type":"Point"}
}