{
  "type": "Feature",
  "properties": {
    "iso:country":"US",
    "sg:address":"3089 Balmoral Dr",
    "sg:city":"San Jose",
    "sg:classifiers":[
        {
            "category":"Utilities",
            "subcategory":"Telephone",
            "type":"Services"
        }
    ],
    "sg:phone":"+1 408 481 3368",
    "sg:postcode":"95132",
    "sg:province":"CA",
    "sg:tags":[
        "communications"
    ],
    "wof:name":"Hart of Gold",
    "wof:placetype":"venue"
},
  "geometry": {"coordinates":[-121.865042,37.406454],"type":"Point"}
}