{
  "type": "Feature",
  "properties": {
    "iso:country":"US",
    "sg:address":"15047 Goldenwest Street",
    "sg:city":"Huntington Beach",
    "sg:classifiers":[
        {
            "category":"Health Services",
            "subcategory":"Dentist",
            "type":"Services"
        }
    ],
    "sg:phone":"+1 714 898 4425",
    "sg:postcode":"92647",
    "sg:province":"CA",
    "sg:tags":[
        "orthodontist"
    ],
    "sg:website":"www.johncolemandds.com",
    "wof:name":"Coleman John M",
    "wof:placetype":"venue"
},
  "geometry": {"coordinates":[-118.006844,33.743817],"type":"Point"}
}