{
  "type": "Feature",
  "properties": {
    "addr:full":"2390 el Camino Real Palo Alto CA 94306",
    "addr:housenumber":"2390",
    "addr:postcode":"94306",
    "addr:street":"El Camino Real",
    "iso:country":"US",
    "sg:address":"2390 el Camino Real",
    "sg:city":"Palo Alto",
    "sg:classifiers":[
        {
            "category":"Banks & Credit Unions",
            "subcategory":"Bank",
            "type":"Services"
        }
    ],
    "sg:phone":"+1 650 858 1400",
    "sg:postcode":"94306",
    "sg:province":"CA",
    "wof:name":"America California Bank",
    "wof:placetype":"venue"
},
  "geometry": {"coordinates":[-122.146765,37.425418],"type":"Point"}
}