{
  "type": "Feature",
  "properties": {
    "iso:country":"US",
    "sg:address":"40755 Winding Way",
    "sg:city":"Oakhurst",
    "sg:classifiers":[
        {
            "category":"Local Transit",
            "type":"Transportation"
        }
    ],
    "sg:phone":"+1 559 642 0650",
    "sg:postcode":"93644",
    "sg:province":"CA",
    "sg:tags":[
        "ambulance"
    ],
    "sg:website":"www.sierraambulance.org",
    "wof:name":"Sierra Ambulance Svc Inc",
    "wof:placetype":"venue"
},
  "geometry": {"coordinates":[-119.643101,37.3408],"type":"Point"}
}