{
  "type": "Feature",
  "properties": {
    "iso:country":"US",
    "sg:address":"2031 Whitman Ave",
    "sg:city":"Chico",
    "sg:classifiers":[
        {
            "category":"Cinema",
            "subcategory":"Movie Rental",
            "type":"Entertainment"
        }
    ],
    "sg:phone":"+1 530 895 8838",
    "sg:postcode":"95928",
    "sg:province":"CA",
    "sg:tags":[
        "leasing",
        "video",
        "disc",
        "tape"
    ],
    "wof:name":"Blockbuster Video",
    "wof:placetype":"venue"
},
  "geometry": {"coordinates":[-121.80834299999999,39.721386],"type":"Point"}
}