{
  "type": "Feature",
  "properties": {
    "addr:full":"998 S Coast Hwy Laguna Beach CA 92651",
    "addr:housenumber":"998",
    "addr:postcode":"92651",
    "addr:street":"S Coast Hwy",
    "iso:country":"US",
    "sg:address":"998 S Coast Hwy",
    "sg:city":"Laguna Beach",
    "sg:classifiers":[
        {
            "category":"Shopping",
            "subcategory":"Florist",
            "type":"Retail Goods"
        }
    ],
    "sg:phone":"+1 949 497 9775",
    "sg:postcode":"92651",
    "sg:province":"CA",
    "wof:name":"Stems Fabulous Flowers",
    "wof:placetype":"venue"
},
  "geometry": {"coordinates":[-117.77814499999999,33.535672],"type":"Point"}
}