{
  "type": "Feature",
  "properties": {
    "iso:country":"US",
    "sg:address":"2417 Mariner Sq Lp",
    "sg:city":"Alameda",
    "sg:classifiers":[
        {
            "category":"Professional",
            "type":"Services"
        }
    ],
    "sg:phone":"+1 510 522 5016",
    "sg:postcode":"94501",
    "sg:province":"CA",
    "sg:tags":[
        "arranger",
        "music",
        "composer"
    ],
    "wof:name":"Urban Life Distribution",
    "wof:placetype":"venue"
},
  "geometry": {"coordinates":[-122.278602,37.786431],"type":"Point"}
}