{
  "type": "Feature",
  "properties": {
    "iso:country":"US",
    "sg:address":"5236 Colodny Dr",
    "sg:city":"Agoura Hills",
    "sg:classifiers":[
        {
            "category":"Professional",
            "type":"Services"
        }
    ],
    "sg:phone":"+1 818 889 9151",
    "sg:postcode":"91301",
    "sg:province":"CA",
    "wof:name":"My Home Concepts",
    "wof:placetype":"venue"
},
  "geometry": {"coordinates":[-118.74247200000001,34.144106],"type":"Point"}
}