{
  "type": "Feature",
  "properties": {
    "iso:country":"US",
    "sg:address":"2000 University Ave Au Coquelet Cafe",
    "sg:city":"Berkeley",
    "sg:classifiers":[
        {
            "category":"Education",
            "subcategory":"Special Training",
            "type":"Public Place"
        }
    ],
    "sg:phone":"+1 510 596 4607",
    "sg:postcode":"94704",
    "sg:province":"CA",
    "sg:tags":[
        "adult"
    ],
    "sg:website":"berkcom.freetoasthost.us/page2.html",
    "wof:name":"The Berkeley Communicators - Toastmasters International Club",
    "wof:placetype":"venue"
},
  "geometry": {"coordinates":[-122.270742,37.871799],"type":"Point"}
}