{
  "type": "Feature",
  "properties": {
    "iso:country":"US",
    "sg:address":"107 N Joy St",
    "sg:city":"Corona",
    "sg:classifiers":[
        {
            "category":"Building & Trades",
            "subcategory":"Construction",
            "type":"Services"
        }
    ],
    "sg:phone":"+1 951 371 9581",
    "sg:postcode":"92879",
    "sg:province":"CA",
    "sg:tags":[
        "plastering",
        "contractor"
    ],
    "wof:name":"Pro Line Plastering",
    "wof:placetype":"venue"
},
  "geometry": {"coordinates":[-117.560371,33.881282],"type":"Point"}
}