{
  "type": "Feature",
  "properties": {
    "iso:country":"US",
    "sg:address":"32490 Avalon Ln",
    "sg:city":"Menifee",
    "sg:classifiers":[
        {
            "category":"Home & Garden",
            "subcategory":"Garden Supply",
            "type":"Retail Goods"
        }
    ],
    "sg:phone":"+1 951 301 8735",
    "sg:postcode":"92584",
    "sg:province":"CA",
    "sg:tags":[
        "nurseryman"
    ],
    "wof:name":"Asian Fruits & Trees Nursery",
    "wof:placetype":"venue"
},
  "geometry": {"coordinates":[-117.147461,33.650571],"type":"Point"}
}