{
  "type": "Feature",
  "properties": {
    "addr:full":"24260 Valencia Blvd Valencia CA 91355",
    "addr:housenumber":"24260",
    "addr:postcode":"91355",
    "addr:street":"Valencia Blvd",
    "iso:country":"US",
    "sg:address":"24260 Valencia Blvd",
    "sg:city":"Valencia",
    "sg:classifiers":[
        {
            "category":"Shopping",
            "subcategory":"Jewelry",
            "type":"Retail Goods"
        }
    ],
    "sg:phone":"+1 661 254 4155",
    "sg:postcode":"91355",
    "sg:province":"CA",
    "sg:tags":[
        "jeweler"
    ],
    "sg:website":"www.classicdesignsjewelry.com",
    "wof:name":"Classic Designs Jewelry",
    "wof:placetype":"venue"
},
  "geometry": {"coordinates":[-118.558396,34.413006],"type":"Point"}
}