{
  "type": "Feature",
  "properties": {
    "iso:country":"US",
    "sg:address":"7149 Mission Gorge Rd",
    "sg:city":"San Diego",
    "sg:classifiers":[
        {
            "category":"Retail",
            "subcategory":"Auto Repair",
            "type":"Services"
        }
    ],
    "sg:phone":"+1 619 229 7765",
    "sg:postcode":"92120",
    "sg:province":"CA",
    "sg:tags":[
        "machine",
        "automobile",
        "shop"
    ],
    "wof:name":"Esi Engine System Inc",
    "wof:placetype":"venue"
},
  "geometry": {"coordinates":[-117.090926,32.800691],"type":"Point"}
}