{
  "type": "Feature",
  "properties": {
    "addr:full":"517 Union Pl Brea CA 92821",
    "addr:housenumber":"517",
    "addr:postcode":"92821",
    "addr:street":"Union Pl",
    "iso:country":"US",
    "sg:address":"517 Union Pl",
    "sg:city":"Brea",
    "sg:classifiers":[
        {
            "category":"Building & Trades",
            "subcategory":"Landscaping Services",
            "type":"Services"
        }
    ],
    "sg:phone":"+1 714 671 1246",
    "sg:postcode":"92821",
    "sg:province":"CA",
    "wof:name":"Scots Lawn & Garden",
    "wof:placetype":"venue"
},
  "geometry": {"coordinates":[-117.89557000000001,33.913783],"type":"Point"}
}