{
  "type": "Feature",
  "properties": {
    "addr:full":"730 San Bruno Ct Concord CA 94518",
    "addr:housenumber":"730",
    "addr:postcode":"94518",
    "addr:street":"San Bruno Ct",
    "iso:country":"US",
    "sg:address":"730 San Bruno Ct",
    "sg:city":"Concord",
    "sg:classifiers":[
        {
            "category":"Professional",
            "subcategory":"Detective & Security Services",
            "type":"Services"
        },
        {
            "category":"Professional",
            "subcategory":"Computer Services",
            "type":"Services"
        },
        {
            "category":"Shopping",
            "subcategory":"Computers & Home Electronics",
            "type":"Retail Goods"
        },
        {
            "category":"Home & Garden",
            "subcategory":"Carpets & Floor Coverings",
            "type":"Retail Goods"
        }
    ],
    "sg:phone":"+1 925 818 8638",
    "sg:postcode":"94518",
    "sg:province":"CA",
    "sg:tags":[
        "control",
        "stereo",
        "theater",
        "network",
        "monitoring",
        "system",
        "automation",
        "design",
        "equipment-dealers",
        "video",
        "audio"
    ],
    "sg:website":"http://www.creationnetworks.net",
    "wof:name":"Creation Networks",
    "wof:placetype":"venue"
},
  "geometry": {"coordinates":[-122.012356,37.939999],"type":"Point"}
}