{
  "type": "Feature",
  "properties": {
    "addr:full":"21015 Mendenhall Ct Topanga CA 90290",
    "addr:housenumber":"21015",
    "addr:postcode":"90290",
    "addr:street":"Mendenhall Ct",
    "iso:country":"US",
    "sg:address":"21015 Mendenhall Ct",
    "sg:city":"Topanga",
    "sg:classifiers":[
        {
            "category":"Professional",
            "type":"Services"
        }
    ],
    "sg:phone":"+1 818 704 5212",
    "sg:postcode":"90290",
    "sg:province":"CA",
    "wof:name":"Lewis Landau",
    "wof:placetype":"venue"
},
  "geometry": {"coordinates":[-118.588138,34.133912],"type":"Point"}
}