{
  "type": "Feature",
  "properties": {
    "addr:full":"500 E California Ave Bakersfield CA 93307",
    "addr:housenumber":"500",
    "addr:postcode":"93307",
    "addr:street":"E California Ave",
    "iso:country":"US",
    "sg:address":"500 E California Ave",
    "sg:city":"Bakersfield",
    "sg:classifiers":[
        {
            "category":"Social Services",
            "type":"Services"
        }
    ],
    "sg:phone":"+1 661 327 3074",
    "sg:postcode":"93307",
    "sg:province":"CA",
    "sg:tags":[
        "organization",
        "welfare"
    ],
    "wof:name":"Programs Wic",
    "wof:placetype":"venue"
},
  "geometry": {"coordinates":[-118.998232,35.368441],"type":"Point"}
}