{
  "type": "Feature",
  "properties": {
    "iso:country":"US",
    "sg:address":"3660 Wilshire Blvd Ste 1020",
    "sg:city":"Los Angeles",
    "sg:classifiers":[
        {
            "category":"Professional",
            "subcategory":"Lawyer & Legal Services",
            "type":"Services"
        }
    ],
    "sg:phone":"+1 213 383 4421",
    "sg:postcode":"90010",
    "sg:province":"CA",
    "wof:name":"Thomas Christopher Dexter",
    "wof:placetype":"venue"
},
  "geometry": {"coordinates":[-118.30526999999999,34.158286],"type":"Point"}
}