{
  "type": "Feature",
  "properties": {
    "iso:country":"US",
    "sg:address":"10799 Merritt St",
    "sg:city":"Castroville",
    "sg:classifiers":[
        {
            "category":"Government",
            "subcategory":"Post Office",
            "type":"Public Place"
        }
    ],
    "sg:phone":"+1 831 633 2636",
    "sg:postcode":"95012",
    "sg:province":"CA",
    "wof:name":"Castroville Post Office",
    "wof:placetype":"venue"
},
  "geometry": {"coordinates":[-121.757423,36.765277],"type":"Point"}
}