{
  "type": "Feature",
  "properties": {
    "addr:full":"2929 Newport Blvd Newport Beach CA 92663",
    "addr:housenumber":"2929",
    "addr:postcode":"92663",
    "addr:street":"Newport Blvd",
    "iso:country":"US",
    "sg:address":"2929 Newport Blvd",
    "sg:city":"Newport Beach",
    "sg:classifiers":[
        {
            "category":"Banks & Credit Unions",
            "subcategory":"Bank",
            "type":"Services"
        }
    ],
    "sg:phone":"+1 949 723 7733",
    "sg:postcode":"92663",
    "sg:province":"CA",
    "sg:tags":[
        "loan",
        "real estate"
    ],
    "wof:name":"Allstate Funding",
    "wof:placetype":"venue"
},
  "geometry": {"coordinates":[-117.92987100000001,33.61415],"type":"Point"}
}