{
  "type": "Feature",
  "properties": {
    "iso:country":"US",
    "sg:address":"6191 Santa Teresa Blvd",
    "sg:city":"San Jose",
    "sg:classifiers":[
        {
            "category":"Restaurant",
            "type":"Food & Drink"
        }
    ],
    "sg:menulink":"http://www.allmenus.com/ca/san-jose/69311-mountain-mikes-pizza/menu/",
    "sg:phone":"+1 408 226 5885",
    "sg:postcode":"95123",
    "sg:province":"CA",
    "sg:tags":[
        "american",
        "pizza"
    ],
    "wof:name":"Mountain Mike's Pizza",
    "wof:placetype":"venue"
},
  "geometry": {"coordinates":[-121.804986,37.236828],"type":"Point"}
}