{
  "type": "Feature",
  "properties": {
    "iso:country":"US",
    "sg:address":"1763 Palm Ave",
    "sg:city":"San Diego",
    "sg:classifiers":[
        {
            "category":"Personal",
            "subcategory":"Beauty Salon",
            "type":"Services"
        }
    ],
    "sg:phone":"+1 619 575 2624",
    "sg:postcode":"92154",
    "sg:province":"CA",
    "wof:name":"Emiko Hair Styles",
    "wof:placetype":"venue"
},
  "geometry": {"coordinates":[-117.096062,32.583768],"type":"Point"}
}