{
  "type": "Feature",
  "properties": {
    "iso:country":"US",
    "sg:address":"2006 W Belmont Ave",
    "sg:city":"Fresno",
    "sg:classifiers":[
        {
            "category":"Autos & Motor Vehicles",
            "subcategory":"Boat Sales",
            "type":"Retail Goods"
        }
    ],
    "sg:phone":"+1 559 237 2597",
    "sg:postcode":"93728",
    "sg:province":"CA",
    "sg:tags":[
        "dealer",
        "sales"
    ],
    "wof:name":"Belmont Marine",
    "wof:placetype":"venue"
},
  "geometry": {"coordinates":[-119.82906199999999,36.750306],"type":"Point"}
}