{
  "type": "Feature",
  "properties": {
    "addr:full":"10790 Civic Center Dr Rancho Cucamonga CA 91730",
    "addr:housenumber":"10790",
    "addr:postcode":"91730",
    "addr:street":"Civic Center Dr",
    "iso:country":"US",
    "sg:address":"10790 Civic Center Dr",
    "sg:city":"Rancho Cucamonga",
    "sg:classifiers":[
        {
            "category":"Professional",
            "subcategory":"Detective & Security Services",
            "type":"Services"
        }
    ],
    "sg:phone":"+1 909 944 9302",
    "sg:postcode":"91730",
    "sg:province":"CA",
    "sg:tags":[
        "investigator"
    ],
    "wof:name":"Arrowhead Investigations",
    "wof:placetype":"venue"
},
  "geometry": {"coordinates":[-117.571083,34.101073],"type":"Point"}
}