{
  "type": "Feature",
  "properties": {
    "addr:full":"73350 el Paseo Palm Desert CA 92260",
    "addr:housenumber":"73350",
    "addr:postcode":"ca 92260",
    "addr:street":"El Paseo",
    "iso:country":"US",
    "sg:address":"73350 el Paseo",
    "sg:city":"Palm Desert",
    "sg:classifiers":[
        {
            "category":"Insurance",
            "subcategory":"Insurance Agent",
            "type":"Services"
        }
    ],
    "sg:phone":"+1 760 773 5671",
    "sg:postcode":"92260",
    "sg:province":"CA",
    "wof:name":"Boelzner & Assoc Insurance",
    "wof:placetype":"venue"
},
  "geometry": {"coordinates":[-116.386127,33.719847],"type":"Point"}
}