{
  "type": "Feature",
  "properties": {
    "iso:country":"US",
    "sg:address":"2307 Pacific Ave",
    "sg:city":"Alameda",
    "sg:classifiers":[
        {
            "category":"Autos & Motor Vehicles",
            "subcategory":"Fuel & Gas Station",
            "type":"Retail Goods"
        }
    ],
    "sg:phone":"+1 510 865 9503",
    "sg:postcode":"94501",
    "sg:province":"CA",
    "sg:tags":[
        "oil"
    ],
    "wof:name":"Xtra Oil Co",
    "wof:placetype":"venue"
},
  "geometry": {"coordinates":[-122.240754,37.767607],"type":"Point"}
}