{
  "type": "Feature",
  "properties": {
    "addr:full":"2255 S Garey Ave Pomona CA 91766",
    "addr:housenumber":"2255",
    "addr:postcode":"91766",
    "addr:street":"S Garey Ave",
    "iso:country":"US",
    "sg:address":"2255 S Garey Ave",
    "sg:city":"Pomona",
    "sg:classifiers":[
        {
            "category":"Education",
            "subcategory":"Dance Studio",
            "type":"Public Place"
        },
        {
            "category":"Personal",
            "subcategory":"Beauty Salon",
            "type":"Services"
        }
    ],
    "sg:phone":"+1 909 591 0096",
    "sg:postcode":"91766",
    "sg:province":"CA",
    "wof:name":"Altaira Hair Salon",
    "wof:placetype":"venue"
},
  "geometry": {"coordinates":[-117.74927599999999,34.032496],"type":"Point"}
}