{
  "type": "Feature",
  "properties": {
    "iso:country":"US",
    "sg:address":"505 S Pastoria Ave Ste 22",
    "sg:city":"Sunnyvale",
    "sg:classifiers":[
        {
            "category":"Retail",
            "subcategory":"Laundry & Dry Cleaning",
            "type":"Services"
        }
    ],
    "sg:phone":"+1 408 749 8448",
    "sg:postcode":"94086",
    "sg:province":"CA",
    "wof:name":"Q Cleaners",
    "wof:placetype":"venue"
},
  "geometry": {"coordinates":[-122.04055,37.371107],"type":"Point"}
}