{
  "type": "Feature",
  "properties": {
    "iso:country":"US",
    "sg:address":"7653 Telegraph Rd",
    "sg:city":"Montebello",
    "sg:classifiers":[
        {
            "category":"Restaurant",
            "type":"Food & Drink"
        },
        {
            "category":"Bakery",
            "type":"Food & Drink"
        }
    ],
    "sg:phone":"+1 323 346 0730",
    "sg:postcode":"90640",
    "sg:province":"CA",
    "wof:name":"Bakery Depot Inc",
    "wof:placetype":"venue"
},
  "geometry": {"coordinates":[-118.12535099999999,33.976711],"type":"Point"}
}