{
  "type": "Feature",
  "properties": {
    "addr:full":"42072 Big Bear Blvd Big Bear Lake CA 92314",
    "addr:housenumber":"42072",
    "addr:postcode":"92314",
    "addr:street":"Big Bear Blvd",
    "iso:country":"US",
    "sg:address":"42072 Big Bear Blvd",
    "sg:city":"Big Bear Lake",
    "sg:classifiers":[
        {
            "category":"Home & Garden",
            "subcategory":"Furniture",
            "type":"Retail Goods"
        }
    ],
    "sg:phone":"+1 909 878 2204",
    "sg:postcode":"92314",
    "sg:province":"CA",
    "wof:name":"Unreal Furnishing",
    "wof:placetype":"venue"
},
  "geometry": {"coordinates":[-116.885007,34.243961],"type":"Point"}
}