{
  "type": "Feature",
  "properties": {
    "iso:country":"US",
    "sg:address":"10934 Portal Dr",
    "sg:city":"Los Alamitos",
    "sg:classifiers":[
        {
            "category":"Retail",
            "subcategory":"Auto Repair",
            "type":"Services"
        }
    ],
    "sg:phone":"+1 562 596 1827",
    "sg:postcode":"90720",
    "sg:province":"CA",
    "sg:tags":[
        "repairing",
        "automobile"
    ],
    "wof:name":"Alamitos Enterprises",
    "wof:placetype":"venue"
},
  "geometry": {"coordinates":[-118.06009,33.804914],"type":"Point"}
}