{
  "type": "Feature",
  "properties": {
    "iso:country":"US",
    "sg:address":"895 Napa Ave Ste A3",
    "sg:city":"Morro Bay",
    "sg:classifiers":[
        {
            "category":"Professional",
            "subcategory":"Accounting & Tax Preparation",
            "type":"Services"
        }
    ],
    "sg:phone":"+1 805 772 5800",
    "sg:postcode":"93442",
    "sg:province":"CA",
    "sg:tags":[
        "accountant"
    ],
    "wof:name":"O'grady Patrick CPA",
    "wof:placetype":"venue"
},
  "geometry": {"coordinates":[-120.848,35.366798],"type":"Point"}
}