{
  "type": "Feature",
  "properties": {
    "iso:country":"US",
    "sg:address":"1700 Mchenry Ave",
    "sg:city":"Modesto",
    "sg:classifiers":[
        {
            "category":"Shopping",
            "subcategory":"Department Store",
            "type":"Retail Goods"
        }
    ],
    "sg:phone":"+1 209 527 5543",
    "sg:postcode":"95350",
    "sg:province":"CA",
    "wof:name":"Santaplus",
    "wof:placetype":"venue"
},
  "geometry": {"coordinates":[-120.993988,37.668869],"type":"Point"}
}