{
  "type": "Feature",
  "properties": {
    "addr:full":"3400 Fulton Ave Sacramento CA 95821",
    "addr:housenumber":"3400",
    "addr:postcode":"95821",
    "addr:street":"Fulton Ave",
    "iso:country":"US",
    "sg:address":"3400 Fulton Ave",
    "sg:city":"Sacramento",
    "sg:classifiers":[
        {
            "category":"Retail",
            "subcategory":"Auto Repair",
            "type":"Services"
        }
    ],
    "sg:phone":"+1 916 484 9900",
    "sg:postcode":"95821",
    "sg:province":"CA",
    "sg:tags":[
        "muffler",
        "exhaust",
        "system"
    ],
    "wof:name":"A-1 Express Muffler",
    "wof:placetype":"venue"
},
  "geometry": {"coordinates":[-121.40138399999999,38.628343],"type":"Point"}
}