{
  "type": "Feature",
  "properties": {
    "iso:country":"US",
    "sg:address":"3315 E Miraloma Ave Ste 113",
    "sg:city":"Anaheim",
    "sg:classifiers":[
        {
            "category":"Banks & Credit Unions",
            "subcategory":"Bank",
            "type":"Services"
        }
    ],
    "sg:phone":"+1 714 528 7283",
    "sg:postcode":"92806",
    "sg:province":"CA",
    "wof:name":"Savings In OC",
    "wof:placetype":"venue"
},
  "geometry": {"coordinates":[-117.851232,33.860378],"type":"Point"}
}