{
  "type": "Feature",
  "properties": {
    "iso:country":"US",
    "sg:address":"15230 Polk Dr",
    "sg:city":"Clearlake",
    "sg:classifiers":[
        {
            "category":"Building & Trades",
            "subcategory":"Construction",
            "type":"Services"
        }
    ],
    "sg:phone":"+1 707 994 1056",
    "sg:postcode":"95422",
    "sg:province":"CA",
    "sg:tags":[
        "house"
    ],
    "wof:name":"Reiter Built Construction",
    "wof:placetype":"venue"
},
  "geometry": {"coordinates":[-122.62716,38.960123],"type":"Point"}
}