{
  "type": "Feature",
  "properties": {
    "iso:country":"US",
    "sg:address":"618 Lakeside Dr",
    "sg:city":"Fullerton",
    "sg:classifiers":[
        {
            "category":"Manufacturing",
            "subcategory":"Apparel",
            "type":"Manufacturing & Wholesale Goods"
        }
    ],
    "sg:phone":"+1 714 746 1330",
    "sg:postcode":"92835",
    "sg:province":"CA",
    "sg:tags":[
        "uniform"
    ],
    "wof:name":"Gma Uniforms Inc",
    "wof:placetype":"venue"
},
  "geometry": {"coordinates":[-117.93596700000001,33.906895],"type":"Point"}
}