{
  "type": "Feature",
  "properties": {
    "iso:country":"US",
    "sg:address":"3301 Jewett Ave",
    "sg:city":"Bakersfield",
    "sg:classifiers":[
        {
            "category":"Wholesale",
            "subcategory":"Scrap",
            "type":"Manufacturing & Wholesale Goods"
        }
    ],
    "sg:phone":"+1 661 325 3508",
    "sg:postcode":"93301",
    "sg:province":"CA",
    "sg:tags":[
        "recycling",
        "center"
    ],
    "wof:name":"New World Recycling Ctr",
    "wof:placetype":"venue"
},
  "geometry": {"coordinates":[-119.01430999999999,35.390501],"type":"Point"}
}