{
  "type": "Feature",
  "properties": {
    "addr:full":"2290 Ringwood Avenue San Jose CA 95131",
    "addr:housenumber":"2290",
    "addr:postcode":"95131",
    "addr:street":"Ringwood Avenue",
    "iso:country":"US",
    "sg:address":"2290 Ringwood Avenue",
    "sg:city":"San Jose",
    "sg:classifiers":[
        {
            "category":"Shopping",
            "subcategory":"Bicycles & Sporting Goods",
            "type":"Retail Goods"
        }
    ],
    "sg:phone":"+1 408 432 8228",
    "sg:postcode":"95131",
    "sg:province":"CA",
    "wof:name":"Accusplit",
    "wof:placetype":"venue"
},
  "geometry": {"coordinates":[-121.89816,37.401003],"type":"Point"}
}