{
  "type": "Feature",
  "properties": {
    "iso:country":"US",
    "sg:address":"5683 Cochran St",
    "sg:city":"Simi Valley",
    "sg:classifiers":[
        {
            "category":"Education",
            "subcategory":"Special Training",
            "type":"Public Place"
        }
    ],
    "sg:phone":"+1 805 584 6793",
    "sg:postcode":"93063",
    "sg:province":"CA",
    "sg:tags":[
        "instruction",
        "music"
    ],
    "wof:name":"David Schuman Piano Lessons",
    "wof:placetype":"venue"
},
  "geometry": {"coordinates":[-118.681771,34.279072],"type":"Point"}
}