{
  "type": "Feature",
  "properties": {
    "iso:country":"US",
    "sg:address":"29057 Stevens Ave",
    "sg:city":"Moreno Valley",
    "sg:classifiers":[
        {
            "category":"Building & Trades",
            "subcategory":"Construction",
            "type":"Services"
        }
    ],
    "sg:phone":"+1 951 924 1621",
    "sg:postcode":"92555",
    "sg:province":"CA",
    "sg:tags":[
        "roofing",
        "contractor"
    ],
    "wof:name":"J M Hayes Roofing",
    "wof:placetype":"venue"
},
  "geometry": {"coordinates":[-117.154248,33.92003],"type":"Point"}
}