{
  "type": "Feature",
  "properties": {
    "addr:full":"1217 26th St Sacramento CA 95816",
    "addr:housenumber":"1217",
    "addr:postcode":"95816",
    "addr:street":"26Th St",
    "iso:country":"US",
    "sg:address":"1217 26th St",
    "sg:city":"Sacramento",
    "sg:phone":"+1 916 441 2366",
    "sg:postcode":"95816",
    "sg:province":"CA",
    "wof:name":"Solano, Fernando H, Dds - Samuel M Goby Inc",
    "wof:placetype":"venue"
},
  "geometry": {"coordinates":[-121.472956,38.572178],"type":"Point"}
}