{
  "type": "Feature",
  "properties": {
    "iso:country":"US",
    "sg:address":"19301 Parthenia St",
    "sg:city":"Northridge",
    "sg:classifiers":[
        {
            "category":"Autos & Motor Vehicles",
            "subcategory":"Fuel & Gas Station",
            "type":"Retail Goods"
        }
    ],
    "sg:phone":"+1 818 701 7534",
    "sg:postcode":"91324",
    "sg:province":"CA",
    "sg:tags":[
        "oil"
    ],
    "wof:name":"USA Petroleum Corp",
    "wof:placetype":"venue"
},
  "geometry": {"coordinates":[-118.55793199999999,34.228224],"type":"Point"}
}