{
  "type": "Feature",
  "properties": {
    "addr:full":"1615 Bonanza St Walnut Creek CA 94596",
    "addr:housenumber":"1615",
    "addr:postcode":"94596",
    "addr:street":"Bonanza St",
    "iso:country":"US",
    "sg:address":"1615 Bonanza St",
    "sg:city":"Walnut Creek",
    "sg:classifiers":[
        {
            "category":"Professional",
            "subcategory":"Lawyer & Legal Services",
            "type":"Services"
        }
    ],
    "sg:phone":"+1 925 256 7402",
    "sg:postcode":"94596",
    "sg:province":"CA",
    "wof:name":"Bouey & Black LLP",
    "wof:placetype":"venue"
},
  "geometry": {"coordinates":[-122.24130599999999,37.899463],"type":"Point"}
}