{
  "type": "Feature",
  "properties": {
    "addr:full":"1020 Del Paso Rd Ste 200 Sacramento CA 95834",
    "addr:housenumber":"1020",
    "addr:postcode":"95834",
    "addr:street":"Del Paso Rd Ste 200",
    "iso:country":"US",
    "sg:address":"1020 Del Paso Rd Ste 200",
    "sg:city":"Sacramento",
    "sg:classifiers":[
        {
            "category":"Autos & Motor Vehicles",
            "subcategory":"Auto Supplies",
            "type":"Retail Goods"
        },
        {
            "category":"Retail",
            "subcategory":"Auto Repair",
            "type":"Services"
        }
    ],
    "sg:phone":"+1 916 419 6366",
    "sg:postcode":"95834",
    "sg:province":"CA",
    "sg:tags":[
        "tire"
    ],
    "wof:name":"Midas Auto Service Experts - Natomas",
    "wof:placetype":"venue"
},
  "geometry": {"coordinates":[-121.48818900000001,38.656235],"type":"Point"}
}