{
  "type": "Feature",
  "properties": {
    "addr:full":"1725 4th Ave Chula Vista CA 91911",
    "addr:housenumber":"1725",
    "addr:postcode":"91911",
    "addr:street":"4Th Ave",
    "iso:country":"US",
    "sg:address":"1725 4th Ave",
    "sg:city":"Chula Vista",
    "sg:classifiers":[
        {
            "category":"Retail",
            "subcategory":"Laundry & Dry Cleaning",
            "type":"Services"
        }
    ],
    "sg:phone":"+1 619 422 2273",
    "sg:postcode":"91911",
    "sg:province":"CA",
    "sg:tags":[
        "cleaners",
        "rug",
        "carpet"
    ],
    "wof:name":"Bonita Carpet Care",
    "wof:placetype":"venue"
},
  "geometry": {"coordinates":[-117.06876200000001,32.594334],"type":"Point"}
}