{
  "type": "Feature",
  "properties": {
    "addr:full":"11947 Florence Ave Santa Fe Springs CA 90670",
    "addr:housenumber":"11947",
    "addr:postcode":"90670",
    "addr:street":"Florence Ave",
    "iso:country":"US",
    "sg:address":"11947 Florence Ave",
    "sg:city":"Santa Fe Springs",
    "sg:classifiers":[
        {
            "category":"Shopping",
            "subcategory":"Musical Instruments",
            "type":"Retail Goods"
        }
    ],
    "sg:phone":"+1 562 944 2442",
    "sg:postcode":"90670",
    "sg:province":"CA",
    "sg:tags":[
        "music",
        "dealer"
    ],
    "sg:website":"www.jwpepper.com",
    "wof:name":"J W Pepper",
    "wof:placetype":"venue"
},
  "geometry": {"coordinates":[-118.079489,33.935336],"type":"Point"}
}