{
  "type": "Feature",
  "properties": {
    "addr:full":"79580 Port Royal Ave Indio CA 92203",
    "addr:housenumber":"79580",
    "addr:postcode":"92203",
    "addr:street":"Port Royal Ave",
    "iso:country":"US",
    "sg:address":"79580 Port Royal Ave",
    "sg:city":"Indio",
    "sg:classifiers":[
        {
            "category":"Manufacturing",
            "subcategory":"Toys & Sporting Goods",
            "type":"Manufacturing & Wholesale Goods"
        }
    ],
    "sg:phone":"+1 760 345 5881",
    "sg:postcode":"92203",
    "sg:province":"CA",
    "sg:tags":[
        "mfg"
    ],
    "wof:name":"Porcelain Dolls By Lorraine",
    "wof:placetype":"venue"
},
  "geometry": {"coordinates":[-116.276464,33.745002],"type":"Point"}
}