{
  "type": "Feature",
  "properties": {
    "addr:full":"3945 Mitchell Ave Selma CA 93662",
    "addr:housenumber":"3945",
    "addr:postcode":"93662",
    "addr:street":"Mitchell Ave",
    "iso:country":"US",
    "sg:address":"3945 Mitchell Ave",
    "sg:city":"Selma",
    "sg:classifiers":[
        {
            "category":"Building & Trades",
            "subcategory":"Plumbing",
            "type":"Services"
        }
    ],
    "sg:phone":"+1 559 898 0764",
    "sg:postcode":"93662",
    "sg:province":"CA",
    "sg:tags":[
        "contractor"
    ],
    "wof:name":"Sal S Heating Cooling",
    "wof:placetype":"venue"
},
  "geometry": {"coordinates":[-119.623717,36.590859],"type":"Point"}
}