{
  "type": "Feature",
  "properties": {
    "addr:full":"1700 Iowa Ave Riverside CA 92507",
    "addr:housenumber":"1700",
    "addr:postcode":"92507",
    "addr:street":"Iowa Ave",
    "iso:country":"US",
    "sg:address":"1700 Iowa Ave",
    "sg:city":"Riverside",
    "sg:classifiers":[
        {
            "category":"Professional",
            "subcategory":"Employment Agencies",
            "type":"Services"
        }
    ],
    "sg:phone":"+1 951 341 0101",
    "sg:postcode":"92507",
    "sg:province":"CA",
    "sg:tags":[
        "opportunity"
    ],
    "wof:name":"Adecco",
    "wof:placetype":"venue"
},
  "geometry": {"coordinates":[-117.33974000000001,33.995052],"type":"Point"}
}