{
  "type": "Feature",
  "properties": {
    "iso:country":"US",
    "sg:address":"3841 Otto Dr",
    "sg:city":"Stockton",
    "sg:classifiers":[
        {
            "category":"Health Services",
            "subcategory":"Nursing And Care Facility",
            "type":"Services"
        }
    ],
    "sg:phone":"+1 209 477 3810",
    "sg:postcode":"95209",
    "sg:province":"CA",
    "sg:tags":[
        "intermediate"
    ],
    "wof:name":"Rubel Care Home",
    "wof:placetype":"venue"
},
  "geometry": {"coordinates":[-121.364221,38.03763],"type":"Point"}
}