{
  "type": "Feature",
  "properties": {
    "iso:country":"US",
    "sg:address":"3905 Club Rancho Blvd",
    "sg:city":"Palmdale",
    "sg:classifiers":[
        {
            "category":"Restaurant",
            "type":"Food & Drink"
        }
    ],
    "sg:phone":"+1 661 272 9082",
    "sg:postcode":"93551",
    "sg:province":"CA",
    "sg:tags":[
        "personal",
        "eating"
    ],
    "wof:name":"Cascades",
    "wof:placetype":"venue"
},
  "geometry": {"coordinates":[-118.197747,34.619008],"type":"Point"}
}