{
  "type": "Feature",
  "properties": {
    "iso:country":"US",
    "sg:address":"7949 Silverton Ave",
    "sg:city":"San Diego",
    "sg:classifiers":[
        {
            "category":"Building & Trades",
            "subcategory":"Construction",
            "type":"Services"
        }
    ],
    "sg:phone":"+1 858 689 8190",
    "sg:postcode":"92126",
    "sg:province":"CA",
    "sg:tags":[
        "industrial"
    ],
    "wof:name":"Guy Of Diego",
    "wof:placetype":"venue"
},
  "geometry": {"coordinates":[-117.14842,32.89054],"type":"Point"}
}