{
  "type": "Feature",
  "properties": {
    "addr:full":"2219 Morello Ave Pleasant Hill CA 94523",
    "addr:housenumber":"2219",
    "addr:postcode":"94523",
    "addr:street":"Morello Ave",
    "iso:country":"US",
    "sg:address":"2219 Morello Ave",
    "sg:city":"Pleasant Hill",
    "sg:classifiers":[
        {
            "category":"Recreation",
            "type":"Entertainment"
        }
    ],
    "sg:phone":"+1 925 676 4414",
    "sg:postcode":"94523",
    "sg:province":"CA",
    "sg:tags":[
        "bridge",
        "instruction"
    ],
    "wof:name":"Bridge Center",
    "wof:placetype":"venue"
},
  "geometry": {"coordinates":[-122.07893799999999,37.961077],"type":"Point"}
}