{
  "type": "Feature",
  "properties": {
    "iso:country":"US",
    "sg:address":"8118 Loren Lane",
    "sg:city":"Rosemead",
    "sg:classifiers":[
        {
            "category":"Personal",
            "subcategory":"Beauty Salon",
            "type":"Services"
        }
    ],
    "sg:phone":"+1 626 497 9499",
    "sg:postcode":"91770",
    "sg:province":"CA",
    "sg:tags":[
        "spa"
    ],
    "sg:website":"www.infinity888.myarbonne.com",
    "wof:name":"Arbonne International Independant Consultant #10630267",
    "wof:placetype":"venue"
},
  "geometry": {"coordinates":[-118.09200300000001,34.051498],"type":"Point"}
}