{
  "type": "Feature",
  "properties": {
    "addr:full":"334 Main St Los Altos CA 94022",
    "addr:housenumber":"334",
    "addr:postcode":"94022",
    "addr:street":"Main St",
    "iso:country":"US",
    "sg:address":"334 Main St",
    "sg:city":"Los Altos",
    "sg:classifiers":[
        {
            "category":"Manufacturing",
            "subcategory":"Apparel",
            "type":"Manufacturing & Wholesale Goods"
        }
    ],
    "sg:phone":"+1 650 559 0781",
    "sg:postcode":"94022",
    "sg:province":"CA",
    "sg:tags":[
        "manufacturer"
    ],
    "sg:website":"www.victoriabracha.com",
    "wof:name":"Bracha LLC",
    "wof:placetype":"venue"
},
  "geometry": {"coordinates":[-122.11742099999999,37.378057],"type":"Point"}
}