{
  "type": "Feature",
  "properties": {
    "iso:country":"US",
    "sg:address":"705 Bordeaux Dr",
    "sg:city":"Petaluma",
    "sg:classifiers":[
        {
            "category":"Food & Beverages",
            "subcategory":"Dairy",
            "type":"Retail Goods"
        }
    ],
    "sg:phone":"+1 707 778 0876",
    "sg:postcode":"94954",
    "sg:province":"CA",
    "sg:tags":[
        "product"
    ],
    "wof:name":"Wild Oak Dairy",
    "wof:placetype":"venue"
},
  "geometry": {"coordinates":[-122.60901800000001,38.252067],"type":"Point"}
}