{
  "type": "Feature",
  "properties": {
    "iso:country":"US",
    "sg:address":"7401 Morton Ave",
    "sg:city":"Newark",
    "sg:classifiers":[
        {
            "category":"Wholesale",
            "subcategory":"Groceries",
            "type":"Manufacturing & Wholesale Goods"
        }
    ],
    "sg:phone":"+1 510 797 7249",
    "sg:postcode":"94560",
    "sg:province":"CA",
    "sg:tags":[
        "food",
        "products-wholesale"
    ],
    "wof:name":"Alidoro Gourment Int",
    "wof:placetype":"venue"
},
  "geometry": {"coordinates":[-122.032387,37.520567],"type":"Point"}
}