{
  "type": "Feature",
  "properties": {
    "iso:country":"US",
    "sg:address":"72880 Hwy 111",
    "sg:city":"Palm Desert",
    "sg:classifiers":[
        {
            "category":"Shopping",
            "subcategory":"Department Store",
            "type":"Retail Goods"
        },
        {
            "category":"Shopping",
            "subcategory":"Computers & Home Electronics",
            "type":"Retail Goods"
        }
    ],
    "sg:phone":"+1 760 837 4000",
    "sg:postcode":"92260",
    "sg:province":"CA",
    "sg:website":"www.sears.com",
    "wof:name":"Sears",
    "wof:placetype":"venue"
},
  "geometry": {"coordinates":[-116.393664,33.722886],"type":"Point"}
}