{
  "type": "Feature",
  "properties": {
    "iso:country":"US",
    "sg:address":"11768 Atwood Rd",
    "sg:city":"Auburn",
    "sg:classifiers":[
        {
            "category":"Communications",
            "type":"Services"
        }
    ],
    "sg:phone":"+1 530 889 2241",
    "sg:postcode":"95603",
    "sg:province":"CA",
    "sg:tags":[
        "consultant",
        "telecommunication"
    ],
    "wof:name":"Citizen Potawatomi",
    "wof:placetype":"venue"
},
  "geometry": {"coordinates":[-121.096991,38.93489],"type":"Point"}
}