{
  "type": "Feature",
  "properties": {
    "iso:country":"US",
    "sg:address":"2121 Canada Blvd",
    "sg:city":"Glendale",
    "sg:classifiers":[
        {
            "category":"Wholesale",
            "subcategory":"Apparel",
            "type":"Manufacturing & Wholesale Goods"
        }
    ],
    "sg:phone":"+1 818 240 7225",
    "sg:postcode":"91208",
    "sg:province":"CA",
    "sg:tags":[
        "clothing"
    ],
    "wof:name":"First Comes Love",
    "wof:placetype":"venue"
},
  "geometry": {"coordinates":[-118.229072,34.179311],"type":"Point"}
}