{
  "type": "Feature",
  "properties": {
    "addr:full":"514 Lee Pl Placentia CA 92870",
    "addr:housenumber":"514",
    "addr:postcode":"ca 92870",
    "addr:street":"Lee Pl",
    "iso:country":"US",
    "sg:address":"514 Lee Pl",
    "sg:city":"Placentia",
    "sg:classifiers":[
        {
            "category":"Professional",
            "subcategory":"Computer Services",
            "type":"Services"
        }
    ],
    "sg:phone":"+1 866 417 7244",
    "sg:postcode":"92870",
    "sg:province":"CA",
    "sg:tags":[
        "isp",
        "provider",
        "internet"
    ],
    "wof:name":"Integrity Network Services, Inc.",
    "wof:placetype":"venue"
},
  "geometry": {"coordinates":[-117.873171,33.894162],"type":"Point"}
}