{
  "type": "Feature",
  "properties": {
    "addr:full":"6724 Alameda St Huntington Park CA 90255",
    "addr:housenumber":"6724",
    "addr:postcode":"90255",
    "addr:street":"Alameda St;Park",
    "iso:country":"US",
    "sg:address":"6724 Alameda St",
    "sg:city":"Huntington Park",
    "sg:classifiers":[
        {
            "category":"Education",
            "subcategory":"School",
            "type":"Public Place"
        }
    ],
    "sg:phone":"+1 323 583 5421",
    "sg:postcode":"90255",
    "sg:province":"CA",
    "wof:name":"Aspire Public Schools",
    "wof:placetype":"venue"
},
  "geometry": {"coordinates":[-118.234858,33.977907],"type":"Point"}
}