{
  "type": "Feature",
  "properties": {
    "addr:full":"1420 Burlingame Ave Burlingame CA 94010",
    "addr:housenumber":"1420",
    "addr:postcode":"94010",
    "addr:street":"Burlingame Ave",
    "iso:country":"US",
    "sg:address":"1420 Burlingame Ave",
    "sg:city":"Burlingame",
    "sg:classifiers":[
        {
            "category":"Shopping",
            "subcategory":"Clothing, Apparel, & Fashions",
            "type":"Retail Goods"
        }
    ],
    "sg:phone":"+1 650 347 7130",
    "sg:postcode":"94010",
    "sg:province":"CA",
    "sg:tags":[
        "clothing",
        "women's"
    ],
    "sg:website":"www.anntaylorloft.com",
    "wof:name":"Ann Taylor Loft",
    "wof:placetype":"venue"
},
  "geometry": {"coordinates":[-122.34858699999999,37.577503],"type":"Point"}
}