{
  "type": "Feature",
  "properties": {
    "iso:country":"US",
    "sg:address":"24009 Ventura Blvd",
    "sg:city":"Calabasas",
    "sg:classifiers":[
        {
            "category":"Insurance",
            "subcategory":"Insurance Agent",
            "type":"Services"
        }
    ],
    "sg:phone":"+1 818 225 1912",
    "sg:postcode":"91302",
    "sg:province":"CA",
    "wof:name":"Hostetter Financial Group",
    "wof:placetype":"venue"
},
  "geometry": {"coordinates":[-118.650177,34.154886],"type":"Point"}
}