{
  "type": "Feature",
  "properties": {
    "addr:full":"21 Palos Irvine CA 92612",
    "addr:housenumber":"21",
    "addr:postcode":"92612",
    "addr:street":"Palos",
    "iso:country":"US",
    "sg:address":"21 Palos",
    "sg:city":"Irvine",
    "sg:classifiers":[
        {
            "category":"Wholesale",
            "subcategory":"Construction Materials",
            "type":"Manufacturing & Wholesale Goods"
        }
    ],
    "sg:phone":"+1 949 854 3720",
    "sg:postcode":"92612",
    "sg:province":"CA",
    "wof:name":"Oxygen Technology Company Inc",
    "wof:placetype":"venue"
},
  "geometry": {"coordinates":[-117.834633,33.659488],"type":"Point"}
}