{
  "type": "Feature",
  "properties": {
    "iso:country":"US",
    "sg:address":"3960 N Fruit Ave",
    "sg:city":"Fresno",
    "sg:classifiers":[
        {
            "category":"Education",
            "subcategory":"Special Training",
            "type":"Public Place"
        }
    ],
    "sg:phone":"+1 559 273 2942",
    "sg:postcode":"93705",
    "sg:province":"CA",
    "sg:tags":[
        "program"
    ],
    "wof:name":"Assessment Training & Research",
    "wof:placetype":"venue"
},
  "geometry": {"coordinates":[-119.81744,36.788627],"type":"Point"}
}