{
  "type": "Feature",
  "properties": {
    "iso:country":"US",
    "sg:address":"5000 California Ave",
    "sg:city":"Bakersfield",
    "sg:classifiers":[
        {
            "category":"Wholesale",
            "subcategory":"Durable Goods & Equipment",
            "type":"Manufacturing & Wholesale Goods"
        }
    ],
    "sg:phone":"+1 661 635 2030",
    "sg:postcode":"93309",
    "sg:province":"CA",
    "sg:tags":[
        "exporter"
    ],
    "wof:name":"ACX Trading",
    "wof:placetype":"venue"
},
  "geometry": {"coordinates":[-119.058741,35.362657],"type":"Point"}
}