{
  "type": "Feature",
  "properties": {
    "iso:country":"US",
    "sg:address":"560 Pirinen Ln",
    "sg:city":"Modesto",
    "sg:classifiers":[
        {
            "category":"Farming",
            "subcategory":"Dairy Farm",
            "type":"Manufacturing & Wholesale Goods"
        }
    ],
    "sg:phone":"+1 209 523 1636",
    "sg:postcode":"95354",
    "sg:province":"CA",
    "wof:name":"C & C Dairy",
    "wof:placetype":"venue"
},
  "geometry": {"coordinates":[-120.940271,37.646943],"type":"Point"}
}