{
  "type": "Feature",
  "properties": {
    "addr:full":"240 S Broadway Los Angeles CA 90012",
    "addr:housenumber":"240",
    "addr:postcode":"90012",
    "addr:street":"S Broadway",
    "iso:country":"US",
    "sg:address":"240 S Broadway",
    "sg:city":"Los Angeles",
    "sg:classifiers":[
        {
            "category":"Manufacturing",
            "subcategory":"Signs",
            "type":"Manufacturing & Wholesale Goods"
        }
    ],
    "sg:phone":"+1 213 620 5758",
    "sg:postcode":"90012",
    "sg:province":"CA",
    "sg:tags":[
        "specialty",
        "mfg"
    ],
    "wof:name":"Victor Van Genderen",
    "wof:placetype":"venue"
},
  "geometry": {"coordinates":[-118.247505,34.051501],"type":"Point"}
}