{
  "type": "Feature",
  "properties": {
    "addr:full":"610 N Glenoaks Blvd # 103 Burbank CA 91502",
    "addr:housenumber":"610",
    "addr:postcode":"91502",
    "addr:street":"N Glenoaks Blvd # 103",
    "iso:country":"US",
    "sg:address":"610 N Glenoaks Blvd # 103",
    "sg:city":"Burbank",
    "sg:classifiers":[
        {
            "category":"Food & Beverages",
            "subcategory":"Groceries & Convenience Stores",
            "type":"Retail Goods"
        }
    ],
    "sg:phone":"+1 818 239 1383",
    "sg:postcode":"91502",
    "sg:province":"CA",
    "wof:name":"A & K Trading Inc",
    "wof:placetype":"venue"
},
  "geometry": {"coordinates":[-118.310997,34.186901],"type":"Point"}
}