{
  "type": "Feature",
  "properties": {
    "addr:full":"16950 Gramercy Pl Spc 82A Gardena CA 90247",
    "addr:housenumber":"16950;82a",
    "addr:postcode":"90247",
    "addr:street":"Gramercy Pl Spc",
    "iso:country":"US",
    "sg:address":"16950 Gramercy Pl Spc 82A",
    "sg:city":"Gardena",
    "sg:classifiers":[
        {
            "category":"Social Services",
            "type":"Services"
        },
        {
            "category":"Professional",
            "subcategory":"Employment Agencies",
            "type":"Services"
        }
    ],
    "sg:phone":"+1 310 920 9470",
    "sg:postcode":"90247",
    "sg:province":"CA",
    "sg:tags":[
        "workers'",
        "placement",
        "volunteer"
    ],
    "wof:name":"The Adolfo Science Education Foundation",
    "wof:placetype":"venue"
},
  "geometry": {"coordinates":[-118.313523,33.877301],"type":"Point"}
}