{
  "type": "Feature",
  "properties": {
    "addr:full":"13926 San Antonio Dr Norwalk CA 90650",
    "addr:housenumber":"13926",
    "addr:postcode":"90650",
    "addr:street":"San Antonio Dr",
    "iso:country":"US",
    "sg:address":"13926 San Antonio Dr",
    "sg:city":"Norwalk",
    "sg:classifiers":[
        {
            "category":"Health Services",
            "subcategory":"Dentist",
            "type":"Services"
        }
    ],
    "sg:phone":"+1 562 863 4110",
    "sg:postcode":"90650",
    "sg:province":"CA",
    "sg:tags":[
        "dentists-oral",
        "dentists-cosmetic",
        "maxillofacial",
        "dentists-pediatric",
        "dentists-orthodontists",
        "dentistry",
        "implant",
        "surgery",
        "dentists-implantology"
    ],
    "sg:website":"www.drbarme.com",
    "wof:name":"Barme Michael DDS Inc",
    "wof:placetype":"venue"
},
  "geometry": {"coordinates":[-118.08000199999999,33.904701],"type":"Point"}
}