{
  "type": "Feature",
  "properties": {
    "addr:full":"675 Campbell Technology Parkway Suite 250 Campbell CA 95008",
    "addr:housenumber":"675",
    "addr:postcode":"95008",
    "addr:street":"Campbell Technology Parkway Suite 250",
    "iso:country":"US",
    "sg:address":"675 Campbell Technology Parkway Suite 250",
    "sg:city":"Campbell",
    "sg:classifiers":[
        {
            "category":"Professional",
            "subcategory":"Computer Services",
            "type":"Services"
        }
    ],
    "sg:postcode":"95008",
    "sg:province":"CA",
    "sg:tags":[
        "virtual-event",
        "virtual-tradeshow",
        "virtual-job-fair",
        "virtual-recruiting",
        "virtual-conference",
        "virtual-software",
        "virtual-business-solution",
        "virtual-solution"
    ],
    "wof:name":"6connex",
    "wof:placetype":"venue"
},
  "geometry": {"coordinates":[-121.941283,37.279296],"type":"Point"}
}