{
  "type": "Feature",
  "properties": {
    "addr:full":"2616 Greenfield Way Carmichael CA 95608",
    "addr:housenumber":"2616",
    "addr:postcode":"95608",
    "addr:street":"Greenfield Way",
    "iso:country":"US",
    "sg:address":"2616 Greenfield Way",
    "sg:city":"Carmichael",
    "sg:classifiers":[
        {
            "category":"Home & Garden",
            "subcategory":"Furniture",
            "type":"Retail Goods"
        }
    ],
    "sg:phone":"+1 916 481 2963",
    "sg:postcode":"95608",
    "sg:province":"CA",
    "sg:tags":[
        "builder",
        "custom"
    ],
    "wof:name":"Jrm Stands",
    "wof:placetype":"venue"
},
  "geometry": {"coordinates":[-121.354142,38.611307],"type":"Point"}
}