{
  "type": "Feature",
  "properties": {
    "iso:country":"US",
    "sg:address":"3443 Cahuenga Blvd W",
    "sg:city":"Los Angeles",
    "sg:classifiers":[
        {
            "category":"Building & Trades",
            "subcategory":"Construction",
            "type":"Services"
        }
    ],
    "sg:phone":"+1 323 850 6726",
    "sg:postcode":"90068",
    "sg:province":"CA",
    "sg:tags":[
        "contractor"
    ],
    "wof:name":"D R Remodeling Svc",
    "wof:placetype":"venue"
},
  "geometry": {"coordinates":[-118.353294,34.132186],"type":"Point"}
}