{
  "type": "Feature",
  "properties": {
    "addr:full":"1454 Whitecliff Way Walnut Creek CA 94596",
    "addr:housenumber":"1454",
    "addr:postcode":"94596",
    "addr:street":"Whitecliff Way",
    "iso:country":"US",
    "sg:address":"1454 Whitecliff Way",
    "sg:city":"Walnut Creek",
    "sg:classifiers":[
        {
            "category":"Building & Trades",
            "subcategory":"Landscaping Services",
            "type":"Services"
        }
    ],
    "sg:phone":"+1 925 938 1777",
    "sg:postcode":"94596",
    "sg:province":"CA",
    "sg:tags":[
        "landscape",
        "contractor"
    ],
    "wof:name":"Pacific Landscaping",
    "wof:placetype":"venue"
},
  "geometry": {"coordinates":[-122.02531999999999,37.880946],"type":"Point"}
}