{
  "type": "Feature",
  "properties": {
    "addr:full":"7712 Fair Oaks Blvd Carmichael CA 95608",
    "addr:housenumber":"7712",
    "addr:postcode":"95608",
    "addr:street":"Fair Oaks Blvd",
    "iso:country":"US",
    "sg:address":"7712 Fair Oaks Blvd",
    "sg:city":"Carmichael",
    "sg:classifiers":[
        {
            "category":"Professional",
            "subcategory":"Engineering",
            "type":"Services"
        }
    ],
    "sg:phone":"+1 916 944 7685",
    "sg:postcode":"95608",
    "sg:province":"CA",
    "sg:tags":[
        "engineer"
    ],
    "wof:name":"John D Russ",
    "wof:placetype":"venue"
},
  "geometry": {"coordinates":[-121.32126599999999,38.636699],"type":"Point"}
}