{
  "type": "Feature",
  "properties": {
    "iso:country":"US",
    "sg:address":"1321 Waller St",
    "sg:city":"San Francisco",
    "sg:classifiers":[
        {
            "category":"Professional",
            "type":"Services"
        }
    ],
    "sg:phone":"+1 415 863 8910",
    "sg:postcode":"94117",
    "sg:province":"CA",
    "wof:name":"I Science Corp",
    "wof:placetype":"venue"
},
  "geometry": {"coordinates":[-122.44564099999999,37.769149],"type":"Point"}
}