{
  "type": "Feature",
  "properties": {
    "iso:country":"US",
    "sg:address":"4572 W Telephone Rd",
    "sg:city":"Ventura",
    "sg:classifiers":[
        {
            "category":"Freight",
            "type":"Transportation"
        }
    ],
    "sg:phone":"+1 805 658 1872",
    "sg:postcode":"93003",
    "sg:province":"CA",
    "sg:tags":[
        "arrangement"
    ],
    "wof:name":"Packaging Store",
    "wof:placetype":"venue"
},
  "geometry": {"coordinates":[-119.225849,34.263331],"type":"Point"}
}