{
  "type": "Feature",
  "properties": {
    "iso:country":"US",
    "sg:address":"901 W Esplanade Ave",
    "sg:city":"San Jacinto",
    "sg:classifiers":[
        {
            "category":"Organizations",
            "subcategory":"Non-profit Organization",
            "type":"Services"
        }
    ],
    "sg:phone":"+1 951 487 2380",
    "sg:postcode":"92582",
    "sg:province":"CA",
    "sg:tags":[
        "info",
        "addiction",
        "abuse",
        "treatment",
        "drug"
    ],
    "wof:name":"Valley-Wide Outreach Svc",
    "wof:placetype":"venue"
},
  "geometry": {"coordinates":[-116.975821,33.773003],"type":"Point"}
}