{
  "type": "Feature",
  "properties": {
    "addr:full":"3628 Rio Loma Way Sacramento CA 95834",
    "addr:housenumber":"3628",
    "addr:postcode":"95834",
    "addr:street":"Rio Loma Way",
    "iso:country":"US",
    "sg:address":"3628 Rio Loma Way",
    "sg:city":"Sacramento",
    "sg:classifiers":[
        {
            "category":"Building & Trades",
            "subcategory":"Construction",
            "type":"Services"
        }
    ],
    "sg:phone":"+1 916 343 9638",
    "sg:postcode":"95834",
    "sg:province":"CA",
    "sg:tags":[
        "sealcoating",
        "paving",
        "asphalt",
        "contractor"
    ],
    "wof:name":"A&B Paving Stone",
    "wof:placetype":"venue"
},
  "geometry": {"coordinates":[-121.48519400000001,38.632719],"type":"Point"}
}