{
  "type": "Feature",
  "properties": {
    "addr:full":"5701 Eugenia Ct Orangevale CA 95662",
    "addr:housenumber":"5701",
    "addr:postcode":"95662",
    "addr:street":"Eugenia Ct",
    "iso:country":"US",
    "sg:address":"5701 Eugenia Ct",
    "sg:city":"Orangevale",
    "sg:classifiers":[
        {
            "category":"Home & Garden",
            "subcategory":"Building Materials",
            "type":"Retail Goods"
        }
    ],
    "sg:phone":"+1 916 987 1104",
    "sg:postcode":"95662",
    "sg:province":"CA",
    "sg:tags":[
        "glass",
        "leaded"
    ],
    "wof:name":"Classical Glass By JR",
    "wof:placetype":"venue"
},
  "geometry": {"coordinates":[-121.20382499999999,38.669149],"type":"Point"}
}