{
  "type": "Feature",
  "properties": {
    "addr:full":"3479 Orange Grove Ave North Highlands CA 95660",
    "addr:housenumber":"3479",
    "addr:postcode":"95660",
    "addr:street":"Orange Grove Ave",
    "iso:country":"US",
    "sg:address":"3479 Orange Grove Ave",
    "sg:city":"North Highlands",
    "sg:classifiers":[
        {
            "category":"Professional",
            "subcategory":"Printing & Photocopies",
            "type":"Services"
        }
    ],
    "sg:phone":"+1 916 972 0606",
    "sg:postcode":"95660",
    "sg:province":"CA",
    "sg:tags":[
        "blueprinting"
    ],
    "sg:website":"www.century1.com",
    "wof:name":"Century Graphics",
    "wof:placetype":"venue"
},
  "geometry": {"coordinates":[-121.386866,38.646628],"type":"Point"}
}