{
  "type": "Feature",
  "properties": {
    "addr:full":"924 S Figueroa St Santa Ana CA 92704",
    "addr:housenumber":"924",
    "addr:postcode":"92704",
    "addr:street":"S Figueroa St",
    "iso:country":"US",
    "sg:address":"924 S Figueroa St",
    "sg:city":"Santa Ana",
    "sg:classifiers":[
        {
            "category":"Building & Trades",
            "subcategory":"Landscaping Services",
            "type":"Services"
        }
    ],
    "sg:phone":"+1 714 775 6529",
    "sg:postcode":"92704",
    "sg:province":"CA",
    "wof:name":"Professional Gardening Service",
    "wof:placetype":"venue"
},
  "geometry": {"coordinates":[-117.91851800000001,33.735578],"type":"Point"}
}