{
  "type": "Feature",
  "properties": {
    "iso:country":"US",
    "sg:address":"601 E Lake Ave",
    "sg:city":"Watsonville",
    "sg:classifiers":[
        {
            "category":"Manufacturing",
            "subcategory":"Printing",
            "type":"Manufacturing & Wholesale Goods"
        }
    ],
    "sg:phone":"+1 831 724 3034",
    "sg:postcode":"95076",
    "sg:province":"CA",
    "sg:tags":[
        "printer"
    ],
    "wof:name":"Offset Printing Diseno",
    "wof:placetype":"venue"
},
  "geometry": {"coordinates":[-121.747703,36.91998],"type":"Point"}
}