{
  "type": "Feature",
  "properties": {
    "addr:full":"2409 N Fresno St Fresno CA 93703",
    "addr:housenumber":"2409",
    "addr:postcode":"93703",
    "addr:street":"N Fresno",
    "iso:country":"US",
    "sg:address":"2409 N Fresno St",
    "sg:city":"Fresno",
    "sg:classifiers":[
        {
            "category":"Retail",
            "subcategory":"Auto Repair",
            "type":"Services"
        }
    ],
    "sg:phone":"+1 559 227 5290",
    "sg:postcode":"93703",
    "sg:province":"CA",
    "sg:tags":[
        "automobile",
        "smog"
    ],
    "wof:name":"C & E Auto Repair & Smog Check",
    "wof:placetype":"venue"
},
  "geometry": {"coordinates":[-119.781617,36.773105],"type":"Point"}
}