{
  "type": "Feature",
  "properties": {
    "iso:country":"US",
    "sg:address":"325 N Downs St",
    "sg:city":"Ridgecrest",
    "sg:classifiers":[
        {
            "category":"Organizations",
            "subcategory":"Non-profit Organization",
            "type":"Services"
        }
    ],
    "sg:phone":"+1 760 371 9120",
    "sg:postcode":"93555",
    "sg:province":"CA",
    "sg:tags":[
        "information",
        "alcoholism",
        "treatment"
    ],
    "wof:name":"Alano High Desert Club",
    "wof:placetype":"venue"
},
  "geometry": {"coordinates":[-117.687771,35.626646],"type":"Point"}
}