{
  "type": "Feature",
  "properties": {
    "addr:full":"4590 E Grant Ave Fresno CA 93702",
    "addr:housenumber":"4590",
    "addr:postcode":"93702",
    "addr:street":"E Grant Ave",
    "iso:country":"US",
    "sg:address":"4590 E Grant Ave",
    "sg:city":"Fresno",
    "sg:classifiers":[
        {
            "category":"Arts & Performance",
            "subcategory":"Theater",
            "type":"Entertainment"
        }
    ],
    "sg:phone":"+1 559 905 7566",
    "sg:postcode":"93702",
    "sg:province":"CA",
    "sg:tags":[
        "bureau"
    ],
    "wof:name":"Centuria Records",
    "wof:placetype":"venue"
},
  "geometry": {"coordinates":[-119.74726,36.748561],"type":"Point"}
}