{
  "type": "Feature",
  "properties": {
    "addr:full":"8416 Secura Way Santa Fe Springs CA 90670",
    "addr:housenumber":"8416",
    "addr:postcode":"90670",
    "addr:street":"Secura Way",
    "iso:country":"US",
    "sg:address":"8416 Secura Way",
    "sg:city":"Santa Fe Springs",
    "sg:classifiers":[
        {
            "category":"Wholesale",
            "subcategory":"Auto Parts",
            "type":"Manufacturing & Wholesale Goods"
        }
    ],
    "sg:phone":"+1 562 698 2726",
    "sg:postcode":"90670",
    "sg:province":"CA",
    "sg:tags":[
        "automobile",
        "supply"
    ],
    "wof:name":"Worldwide Inc",
    "wof:placetype":"venue"
},
  "geometry": {"coordinates":[-118.056591,33.964345],"type":"Point"}
}