{
  "type": "Feature",
  "properties": {
    "addr:full":"949 N Enterprise St Orange CA 92867",
    "addr:housenumber":"949",
    "addr:postcode":"92867",
    "addr:street":"N Enterprise St",
    "iso:country":"US",
    "sg:address":"949 N Enterprise St",
    "sg:city":"Orange",
    "sg:classifiers":[
        {
            "category":"Professional",
            "subcategory":"Management & Consulting",
            "type":"Services"
        }
    ],
    "sg:phone":"+1 714 639 1578",
    "sg:postcode":"92867",
    "sg:province":"CA",
    "sg:tags":[
        "consultant",
        "construction"
    ],
    "wof:name":"Lazzari Tile & Stone Constr",
    "wof:placetype":"venue"
},
  "geometry": {"coordinates":[-117.86492,33.803257],"type":"Point"}
}