{
  "type": "Feature",
  "properties": {
    "iso:country":"US",
    "sg:address":"3221 Stevens Creek Blvd",
    "sg:city":"San Jose",
    "sg:classifiers":[
        {
            "category":"Insurance",
            "subcategory":"Insurance Agent",
            "type":"Services"
        }
    ],
    "sg:phone":"+1 408 243 8645",
    "sg:postcode":"95014",
    "sg:province":"CA",
    "sg:website":"www.walliserins.com",
    "wof:name":"Walliser Associates Insurance",
    "wof:placetype":"venue"
},
  "geometry": {"coordinates":[-121.954031,37.323274],"type":"Point"}
}