{
  "type": "Feature",
  "properties": {
    "addr:full":"126 Post St Ste 616 San Francisco CA 94108",
    "addr:housenumber":"126",
    "addr:postcode":"94108",
    "addr:street":"Post St Ste 616",
    "iso:country":"US",
    "sg:address":"126 Post St Ste 616",
    "sg:city":"San Francisco",
    "sg:classifiers":[
        {
            "category":"Health Services",
            "subcategory":"Clinic",
            "type":"Services"
        },
        {
            "category":"Health Services",
            "subcategory":"Health Practitioner",
            "type":"Services"
        }
    ],
    "sg:phone":"+1 415 438 4999",
    "sg:postcode":"94108",
    "sg:province":"CA",
    "sg:tags":[
        "nutritionist",
        "loss",
        "weight"
    ],
    "sg:website":"www.jumpstartmedicine.com",
    "wof:name":"Jumpstart Medicine",
    "wof:placetype":"venue"
},
  "geometry": {"coordinates":[-122.404292,37.789102],"type":"Point"}
}