{
  "type": "Feature",
  "properties": {
    "addr:full":"649 Laurel St San Carlos CA 94070",
    "addr:housenumber":"649",
    "addr:postcode":"94070",
    "addr:street":"Laurel St",
    "iso:country":"US",
    "sg:address":"649 Laurel St",
    "sg:city":"San Carlos",
    "sg:classifiers":[
        {
            "category":"Wholesale",
            "subcategory":"Jewelry",
            "type":"Manufacturing & Wholesale Goods"
        }
    ],
    "sg:phone":"+1 650 595 2223",
    "sg:postcode":"94070",
    "sg:province":"CA",
    "sg:tags":[
        "stone",
        "diamond",
        "importer",
        "colored"
    ],
    "wof:name":"Emkay Diamonds and Gems",
    "wof:placetype":"venue"
},
  "geometry": {"coordinates":[-122.26027999999999,37.505925],"type":"Point"}
}