{
  "type": "Feature",
  "properties": {
    "iso:country":"US",
    "sg:address":"1061 N Emerald Ave",
    "sg:city":"Modesto",
    "sg:classifiers":[
        {
            "category":"Building & Trades",
            "subcategory":"Construction",
            "type":"Services"
        }
    ],
    "sg:phone":"+1 209 529 1470",
    "sg:postcode":"95351",
    "sg:province":"CA",
    "sg:tags":[
        "industrial",
        "painting",
        "contractors-commercial",
        "contractor"
    ],
    "sg:website":"http://www.donldavis.com",
    "wof:name":"Don L Davis Inc",
    "wof:placetype":"venue"
},
  "geometry": {"coordinates":[-121.021089,37.649518],"type":"Point"}
}