{
  "type": "Feature",
  "properties": {
    "addr:full":"7427 Crenshaw Blvd Los Angeles CA 90043",
    "addr:housenumber":"7427",
    "addr:postcode":"90043",
    "addr:street":"Crenshaw Blvd",
    "iso:country":"US",
    "sg:address":"7427 Crenshaw Blvd",
    "sg:city":"Los Angeles",
    "sg:classifiers":[
        {
            "category":"Personal",
            "subcategory":"Beauty Salon",
            "type":"Services"
        }
    ],
    "sg:phone":"+1 323 751 3345",
    "sg:postcode":"90043",
    "sg:province":"CA",
    "wof:name":"L A Difference Hair Design",
    "wof:placetype":"venue"
},
  "geometry": {"coordinates":[-118.330915,33.97204],"type":"Point"}
}