{
  "type": "Feature",
  "properties": {
    "addr:full":"2200 Oak St Bakersfield CA 93301",
    "addr:housenumber":"2200",
    "addr:postcode":"93301",
    "addr:street":"Oak St",
    "iso:country":"US",
    "sg:address":"2200 Oak St",
    "sg:city":"Bakersfield",
    "sg:classifiers":[
        {
            "category":"Social Services",
            "type":"Services"
        }
    ],
    "sg:phone":"+1 661 325 2188",
    "sg:postcode":"93301",
    "sg:province":"CA",
    "sg:tags":[
        "counselor",
        "marriage",
        "family"
    ],
    "wof:name":"Oak Park Counseling Ctr",
    "wof:placetype":"venue"
},
  "geometry": {"coordinates":[-119.038618,35.381114],"type":"Point"}
}