{
  "type": "Feature",
  "properties": {
    "addr:full":"1000 S Fremont Ave Alhambra CA 91803",
    "addr:housenumber":"1000",
    "addr:postcode":"91803",
    "addr:street":"S Fremont Ave",
    "iso:country":"US",
    "sg:address":"1000 S Fremont Ave",
    "sg:city":"Alhambra",
    "sg:classifiers":[
        {
            "category":"Education",
            "subcategory":"Special Training",
            "type":"Public Place"
        },
        {
            "category":"Education",
            "subcategory":"Vocational School",
            "type":"Public Place"
        },
        {
            "category":"Education",
            "subcategory":"School",
            "type":"Public Place"
        },
        {
            "category":"Education",
            "subcategory":"University",
            "type":"Public Place"
        }
    ],
    "sg:phone":"+1 877 268 3879",
    "sg:postcode":"91803",
    "sg:province":"CA",
    "sg:tags":[
        "college",
        "adult",
        "business"
    ],
    "sg:website":"http://www.kelleradvantage.com/landing36/index.html?vc=167328",
    "wof:name":"Keller Graduate School of Management",
    "wof:placetype":"venue"
},
  "geometry": {"coordinates":[-118.151901,34.080471],"type":"Point"}
}