{
  "type": "Feature",
  "properties": {
    "iso:country":"US",
    "sg:address":"1520 State St",
    "sg:city":"Santa Barbara",
    "sg:classifiers":[
        {
            "category":"Professional",
            "subcategory":"Business Services",
            "type":"Services"
        }
    ],
    "sg:phone":"+1 805 962 4462",
    "sg:postcode":"93101",
    "sg:province":"CA",
    "sg:tags":[
        "interior",
        "consultant",
        "design",
        "decorator"
    ],
    "wof:name":"Marsha Byers Interior Design",
    "wof:placetype":"venue"
},
  "geometry": {"coordinates":[-119.7093,34.426956],"type":"Point"}
}