{
  "type": "Feature",
  "properties": {
    "iso:country":"US",
    "sg:address":"927 S Azusa Ave",
    "sg:city":"City Of Industry",
    "sg:classifiers":[
        {
            "category":"Professional",
            "type":"Services"
        }
    ],
    "sg:phone":"+1 626 964 6060",
    "sg:postcode":"91745",
    "sg:province":"CA",
    "sg:tags":[
        "establishment"
    ],
    "wof:name":"Pacific Hong Intl Corp",
    "wof:placetype":"venue"
},
  "geometry": {"coordinates":[-117.930488,34.002385],"type":"Point"}
}