{
  "type": "Feature",
  "properties": {
    "addr:full":"4331 Mission Blvd Montclair CA 91763",
    "addr:housenumber":"4331",
    "addr:postcode":"91763",
    "addr:street":"Mission Blvd",
    "iso:country":"US",
    "sg:address":"4331 Mission Blvd",
    "sg:city":"Montclair",
    "sg:classifiers":[
        {
            "category":"Shopping",
            "type":"Retail Goods"
        }
    ],
    "sg:phone":"+1 909 627 1459",
    "sg:postcode":"91763",
    "sg:province":"CA",
    "sg:tags":[
        "equipment",
        "pool",
        "swimming"
    ],
    "wof:name":"Secard Pools Inc",
    "wof:placetype":"venue"
},
  "geometry": {"coordinates":[-117.707407,34.055873],"type":"Point"}
}