{
  "type": "Feature",
  "properties": {
    "addr:full":"1826 S Coast Hwy Oceanside CA 92054",
    "addr:housenumber":"1826",
    "addr:postcode":"92054",
    "addr:street":"S Coast Hwy",
    "iso:country":"US",
    "sg:address":"1826 S Coast Hwy",
    "sg:city":"Oceanside",
    "sg:classifiers":[
        {
            "category":"Shopping",
            "type":"Retail Goods"
        }
    ],
    "sg:phone":"+1 760 433 5055",
    "sg:postcode":"92054",
    "sg:province":"CA",
    "sg:tags":[
        "picture",
        "frame"
    ],
    "wof:name":"Frame House",
    "wof:placetype":"venue"
},
  "geometry": {"coordinates":[-117.361186,33.174169],"type":"Point"}
}