{
  "type": "Feature",
  "properties": {
    "addr:full":"5527 N Biola Ave Fresno CA 93723",
    "addr:housenumber":"5527",
    "addr:postcode":"93723",
    "addr:street":"N Biola Ave",
    "iso:country":"US",
    "sg:address":"5527 N Biola Ave",
    "sg:city":"Fresno",
    "sg:classifiers":[
        {
            "category":"Manufacturing",
            "subcategory":"Buildings",
            "type":"Manufacturing & Wholesale Goods"
        },
        {
            "category":"Building & Trades",
            "subcategory":"Construction",
            "type":"Services"
        }
    ],
    "sg:phone":"+1 559 351 0120",
    "sg:postcode":"93723",
    "sg:province":"CA",
    "sg:tags":[
        "home",
        "builder",
        "contractor"
    ],
    "wof:name":"Parker Custom Builders",
    "wof:placetype":"venue"
},
  "geometry": {"coordinates":[-120.01558199999999,36.815318],"type":"Point"}
}