{
  "type": "Feature",
  "properties": {
    "iso:country":"US",
    "sg:address":"2457 Lyndale Ave",
    "sg:city":"Pomona",
    "sg:classifiers":[
        {
            "category":"Freight",
            "type":"Transportation"
        }
    ],
    "sg:phone":"+1 714 594 2316",
    "sg:postcode":"91768",
    "sg:province":"CA",
    "sg:tags":[
        "operator",
        "local",
        "trucking"
    ],
    "wof:name":"Milicich Trucking Service",
    "wof:placetype":"venue"
},
  "geometry": {"coordinates":[-117.79730600000001,34.061713],"type":"Point"}
}