{
  "type": "Feature",
  "properties": {
    "iso:country":"US",
    "sg:address":"20740 Martha St",
    "sg:city":"San Fernando Valley",
    "sg:classifiers":[
        {
            "category":"Health Services",
            "subcategory":"Clinic",
            "type":"Services"
        }
    ],
    "sg:phone":"+1 818 884 8557",
    "sg:postcode":"91367",
    "sg:province":"CA",
    "sg:tags":[
        "counseling",
        "mental"
    ],
    "wof:name":"Richard Golden",
    "wof:placetype":"venue"
},
  "geometry": {"coordinates":[-118.58517999999999,34.172479],"type":"Point"}
}