{
  "type": "Feature",
  "properties": {
    "iso:country":"US",
    "sg:address":"1585 W Tedmar Ave",
    "sg:city":"Anaheim",
    "sg:classifiers":[
        {
            "category":"Professional",
            "subcategory":"Computer Services",
            "type":"Services"
        }
    ],
    "sg:phone":"+1 714 956 5405",
    "sg:postcode":"92802",
    "sg:province":"CA",
    "sg:tags":[
        "repair"
    ],
    "wof:name":"A Plus Computer Medic",
    "wof:placetype":"venue"
},
  "geometry": {"coordinates":[-117.935655,33.82688],"type":"Point"}
}