{
  "type": "Feature",
  "properties": {
    "iso:country":"US",
    "sg:address":"2617 Pacific Coast Highway",
    "sg:city":"Torrance",
    "sg:classifiers":[
        {
            "category":"Personal",
            "subcategory":"Beauty Salon",
            "type":"Services"
        }
    ],
    "sg:phone":"+1 310 630 7756",
    "sg:postcode":"90505",
    "sg:province":"CA",
    "sg:tags":[
        "hair"
    ],
    "sg:website":"www.racheledavis.com/",
    "wof:name":"Hair By Rachele",
    "wof:placetype":"venue"
},
  "geometry": {"coordinates":[-118.331216,33.790651],"type":"Point"}
}