{
  "type": "Feature",
  "properties": {
    "addr:full":"6829 Walthall Way Paramount CA 90723",
    "addr:housenumber":"6829",
    "addr:postcode":"90723",
    "addr:street":"Walthall Way",
    "iso:country":"US",
    "sg:address":"6829 Walthall Way",
    "sg:city":"Paramount",
    "sg:classifiers":[
        {
            "category":"Manufacturing",
            "subcategory":"Metals",
            "type":"Manufacturing & Wholesale Goods"
        }
    ],
    "sg:phone":"+1 562 531 9970",
    "sg:postcode":"90723",
    "sg:province":"CA",
    "sg:tags":[
        "production",
        "grinding"
    ],
    "sg:website":"www.wegrind.com",
    "wof:name":"Commercial Grinding Co",
    "wof:placetype":"venue"
},
  "geometry": {"coordinates":[-118.178747,33.905714],"type":"Point"}
}