{
  "type": "Feature",
  "properties": {
    "addr:full":"6600 W Manchester Avenue Los Angeles CA 90045",
    "addr:housenumber":"6600",
    "addr:postcode":"90045",
    "addr:street":"W Manchester Avenue",
    "iso:country":"US",
    "sg:address":"6600 W Manchester Avenue",
    "sg:city":"Los Angeles",
    "sg:classifiers":[
        {
            "category":"Autos & Motor Vehicles",
            "subcategory":"Fuel & Gas Station",
            "type":"Retail Goods"
        }
    ],
    "sg:phone":"+1 310 645 1666",
    "sg:postcode":"90045",
    "sg:province":"CA",
    "wof:name":"Westchester Mobil",
    "wof:placetype":"venue"
},
  "geometry": {"coordinates":[-118.40595999999999,33.959872],"type":"Point"}
}