{
  "type": "Feature",
  "properties": {
    "addr:full":"490 N Craig Ave Pasadena CA 91107",
    "addr:housenumber":"490",
    "addr:postcode":"91107",
    "addr:street":"N Craig Ave",
    "iso:country":"US",
    "sg:address":"490 N Craig Ave",
    "sg:city":"Pasadena",
    "sg:classifiers":[
        {
            "category":"Communications",
            "type":"Services"
        }
    ],
    "sg:phone":"+1 626 795 8355",
    "sg:postcode":"91107",
    "sg:province":"CA",
    "sg:tags":[
        "pathologist",
        "speech-language"
    ],
    "wof:name":"Villa Esperanza Speech Ctr",
    "wof:placetype":"venue"
},
  "geometry": {"coordinates":[-118.10626499999999,34.154555],"type":"Point"}
}