{
  "type": "Feature",
  "properties": {
    "addr:full":"6551 Warner Ave Huntington Beach CA 92647",
    "addr:housenumber":"6551",
    "addr:postcode":"92647",
    "addr:street":"Warner Ave",
    "iso:country":"US",
    "sg:address":"6551 Warner Ave",
    "sg:city":"Huntington Beach",
    "sg:classifiers":[
        {
            "category":"Wholesale",
            "subcategory":"Office Equipment",
            "type":"Manufacturing & Wholesale Goods"
        }
    ],
    "sg:phone":"+1 714 997 4043",
    "sg:postcode":"92647",
    "sg:province":"CA",
    "wof:name":"Orange Coast Copiers",
    "wof:placetype":"venue"
},
  "geometry": {"coordinates":[-118.01411,33.715502],"type":"Point"}
}