{
  "type": "Feature",
  "properties": {
    "iso:country":"US",
    "sg:address":"5517 Cleon Ave",
    "sg:city":"North Hollywood",
    "sg:classifiers":[
        {
            "category":"Food & Beverages",
            "subcategory":"Groceries & Convenience Stores",
            "type":"Retail Goods"
        }
    ],
    "sg:phone":"+1 818 508 3060",
    "sg:postcode":"91601",
    "sg:province":"CA",
    "wof:name":"Larry Marciano",
    "wof:placetype":"venue"
},
  "geometry": {"coordinates":[-118.368781,34.170728],"type":"Point"}
}