{
  "type": "Feature",
  "properties": {
    "addr:full":"4801 Laurel Canyon Blvd Valley Village CA 91607",
    "addr:housenumber":"4801",
    "addr:postcode":"91607",
    "addr:street":"Laurel Canyon Blvd",
    "iso:country":"US",
    "sg:address":"4801 Laurel Canyon Blvd",
    "sg:city":"Valley Village",
    "sg:classifiers":[
        {
            "category":"Autos & Motor Vehicles",
            "subcategory":"Fuel & Gas Station",
            "type":"Retail Goods"
        }
    ],
    "sg:phone":"+1 818 980 1366",
    "sg:postcode":"91607",
    "sg:province":"CA",
    "wof:name":"Sam Dugum Mobil",
    "wof:placetype":"venue"
},
  "geometry": {"coordinates":[-118.397003,34.157902],"type":"Point"}
}