{
  "type": "Feature",
  "properties": {
    "iso:country":"US",
    "sg:address":"565 Higuera St",
    "sg:city":"San Luis Obispo",
    "sg:classifiers":[
        {
            "category":"Retail",
            "subcategory":"Auto Repair",
            "type":"Services"
        }
    ],
    "sg:phone":"+1 805 544 1813",
    "sg:postcode":"93401",
    "sg:province":"CA",
    "sg:tags":[
        "muffler",
        "exhaust",
        "system"
    ],
    "wof:name":"Super Muffler & Brakes",
    "wof:placetype":"venue"
},
  "geometry": {"coordinates":[-120.667245,35.27692],"type":"Point"}
}