{
  "type": "Feature",
  "properties": {
    "addr:full":"14041 Lambert Rd Whittier CA 90605",
    "addr:housenumber":"14041",
    "addr:postcode":"90605",
    "addr:street":"Lambert Rd",
    "iso:country":"US",
    "sg:address":"14041 Lambert Rd",
    "sg:city":"Whittier",
    "sg:classifiers":[
        {
            "category":"Shopping",
            "subcategory":"Clothing, Apparel, & Fashions",
            "type":"Retail Goods"
        }
    ],
    "sg:phone":"+1 562 693 9894",
    "sg:postcode":"90605",
    "sg:province":"CA",
    "sg:tags":[
        "apparel",
        "men's",
        "clothing",
        "sportswear",
        "women's"
    ],
    "sg:website":"http://www.sportsjacketsunlimited.com",
    "wof:name":"Sport Jackets Unlimited",
    "wof:placetype":"venue"
},
  "geometry": {"coordinates":[-118.028121,33.951365],"type":"Point"}
}