{
  "type": "Feature",
  "properties": {
    "addr:full":"22730 Victory Blvd Woodland Hills CA 91367",
    "addr:housenumber":"22730",
    "addr:postcode":"91367",
    "addr:street":"Victory Blvd",
    "iso:country":"US",
    "sg:address":"22730 Victory Blvd",
    "sg:city":"Woodland Hills",
    "sg:classifiers":[
        {
            "category":"Restaurant",
            "type":"Food & Drink"
        }
    ],
    "sg:phone":"+1 818 715 0550",
    "sg:postcode":"91367",
    "sg:province":"CA",
    "wof:name":"Jack-In-the-Box Family Restaurants",
    "wof:placetype":"venue"
},
  "geometry": {"coordinates":[-118.62200199999999,34.1866],"type":"Point"}
}