{
  "type": "Feature",
  "properties": {
    "addr:full":"21159 Calistoga St Middletown CA 95461",
    "addr:housenumber":"21159",
    "addr:postcode":"95461",
    "addr:street":"Calistoga St",
    "iso:country":"US",
    "sg:address":"21159 Calistoga St",
    "sg:city":"Middletown",
    "sg:classifiers":[
        {
            "category":"Real Estate",
            "subcategory":"Architect",
            "type":"Services"
        }
    ],
    "sg:phone":"+1 707 987 9720",
    "sg:postcode":"95461",
    "sg:province":"CA",
    "sg:tags":[
        "estimate",
        "construction"
    ],
    "wof:name":"Calistoga Laundromat",
    "wof:placetype":"venue"
},
  "geometry": {"coordinates":[-122.615118,38.752733],"type":"Point"}
}