{
  "type": "Feature",
  "properties": {
    "addr:full":"302 Santo Tomas St Costa Mesa CA 92627",
    "addr:housenumber":"302",
    "addr:postcode":"92627",
    "addr:street":"Santo Tomas St",
    "iso:country":"US",
    "sg:address":"302 Santo Tomas St",
    "sg:city":"Costa Mesa",
    "sg:classifiers":[
        {
            "category":"Manufacturing",
            "subcategory":"Motor Vehicles & Parts",
            "type":"Manufacturing & Wholesale Goods"
        }
    ],
    "sg:phone":"+1 949 515 9479",
    "sg:postcode":"92627",
    "sg:province":"CA",
    "sg:tags":[
        "body",
        "car",
        "mfg"
    ],
    "wof:name":"RPM Motorsports",
    "wof:placetype":"venue"
},
  "geometry": {"coordinates":[-117.88783599999999,33.659895],"type":"Point"}
}