{
  "type": "Feature",
  "properties": {
    "addr:full":"651 Harding St San Fernando CA 91340",
    "addr:housenumber":"651",
    "addr:postcode":"91340",
    "addr:street":"Harding St",
    "iso:country":"US",
    "sg:address":"651 Harding St",
    "sg:city":"San Fernando",
    "sg:classifiers":[
        {
            "category":"Building & Trades",
            "subcategory":"Landscaping Services",
            "type":"Services"
        }
    ],
    "sg:phone":"+1 818 365 5039",
    "sg:postcode":"91340",
    "sg:province":"CA",
    "wof:name":"J P Gonzalez Gardening",
    "wof:placetype":"venue"
},
  "geometry": {"coordinates":[-118.435782,34.292214],"type":"Point"}
}