{
  "type": "Feature",
  "properties": {
    "addr:full":"28 W Cabrillo Blvd Santa Barbara CA 93101",
    "addr:housenumber":"28",
    "addr:postcode":"93101",
    "addr:street":"W Cabrillo Blvd",
    "iso:country":"US",
    "sg:address":"28 W Cabrillo Blvd",
    "sg:city":"Santa Barbara",
    "sg:classifiers":[
        {
            "category":"Travel",
            "subcategory":"Hotels & Motels",
            "type":"Entertainment"
        }
    ],
    "sg:phone":"+1 805 963 0780",
    "sg:postcode":"93101",
    "sg:province":"CA",
    "wof:name":"Harbor View Inn",
    "wof:placetype":"venue"
},
  "geometry": {"coordinates":[-119.690147,34.411474],"type":"Point"}
}