{
  "type": "Feature",
  "properties": {
    "addr:full":"246 Golf Club Rd Pleasant Hill CA 94523",
    "addr:housenumber":"246",
    "addr:postcode":"94523",
    "addr:street":"Golf Club Rd",
    "iso:country":"US",
    "sg:address":"246 Golf Club Rd",
    "sg:city":"Pleasant Hill",
    "sg:classifiers":[
        {
            "category":"Education",
            "subcategory":"Special Training",
            "type":"Public Place"
        }
    ],
    "sg:phone":"+1 925 676 4600",
    "sg:postcode":"94523",
    "sg:province":"CA",
    "sg:tags":[
        "school",
        "language"
    ],
    "wof:name":"International Education Ctr",
    "wof:placetype":"venue"
},
  "geometry": {"coordinates":[-122.069104,37.971457],"type":"Point"}
}