{
  "type": "Feature",
  "properties": {
    "iso:country":"US",
    "sg:address":"53 Fern Ave",
    "sg:city":"Mill Valley",
    "sg:classifiers":[
        {
            "category":"Building & Trades",
            "subcategory":"Construction",
            "type":"Services"
        }
    ],
    "sg:phone":"+1 415 381 8688",
    "sg:postcode":"94941",
    "sg:province":"CA",
    "sg:tags":[
        "house"
    ],
    "wof:name":"Anawalt Custom Builders",
    "wof:placetype":"venue"
},
  "geometry": {"coordinates":[-122.536548,37.901598],"type":"Point"}
}