{
  "type": "Feature",
  "properties": {
    "addr:full":"7280 Kensington Ct Highland CA 92346",
    "addr:housenumber":"7280",
    "addr:postcode":"92346",
    "addr:street":"Kensington Ct",
    "iso:country":"US",
    "sg:address":"7280 Kensington Ct",
    "sg:city":"Highland",
    "sg:classifiers":[
        {
            "category":"Retail",
            "subcategory":"Laundry & Dry Cleaning",
            "type":"Services"
        }
    ],
    "sg:phone":"+1 909 864 3598",
    "sg:postcode":"92346",
    "sg:province":"CA",
    "sg:tags":[
        "cleaners",
        "rug",
        "carpet"
    ],
    "wof:name":"M & M Carpet Cleaning",
    "wof:placetype":"venue"
},
  "geometry": {"coordinates":[-117.220613,34.122593],"type":"Point"}
}