{
  "type": "Feature",
  "properties": {
    "addr:full":"437 US Hwy 101 Crescent City CA 95531",
    "addr:housenumber":"437",
    "addr:postcode":"95531",
    "addr:street":"Us Hwy 101 Crescent",
    "iso:country":"US",
    "sg:address":"437 US Hwy 101",
    "sg:city":"Crescent City",
    "sg:classifiers":[
        {
            "category":"Food & Beverages",
            "subcategory":"Specialty",
            "type":"Retail Goods"
        }
    ],
    "sg:phone":"+1 707 465 4439",
    "sg:postcode":"95531",
    "sg:province":"CA",
    "sg:tags":[
        "bars",
        "espresso"
    ],
    "wof:name":"Java Hut",
    "wof:placetype":"venue"
},
  "geometry": {"coordinates":[-124.19768999999999,41.759866],"type":"Point"}
}