{
  "type": "Feature",
  "properties": {
    "addr:full":"6801 E Washington Blvd Los Angeles CA 90040",
    "addr:housenumber":"6801",
    "addr:postcode":"90040",
    "addr:street":"E Washington Blvd",
    "iso:country":"US",
    "sg:address":"6801 E Washington Blvd",
    "sg:city":"Los Angeles",
    "sg:classifiers":[
        {
            "category":"Organizations",
            "subcategory":"Labor Organization",
            "type":"Services"
        }
    ],
    "sg:phone":"+1 323 722 3790",
    "sg:postcode":"90040",
    "sg:province":"CA",
    "wof:name":"Baker's",
    "wof:placetype":"venue"
},
  "geometry": {"coordinates":[-118.128816,33.999019],"type":"Point"}
}