{
  "type": "Feature",
  "properties": {
    "iso:country":"US",
    "sg:address":"2671 Fresno Street",
    "sg:city":"Santa Cruz",
    "sg:classifiers":[
        {
            "category":"Building & Trades",
            "subcategory":"Construction",
            "type":"Services"
        }
    ],
    "sg:phone":"+1 831 476 2045",
    "sg:postcode":"95062",
    "sg:province":"CA",
    "sg:tags":[
        "contractor"
    ],
    "wof:name":"Carr Construction",
    "wof:placetype":"venue"
},
  "geometry": {"coordinates":[-121.977895,36.95988],"type":"Point"}
}