{
  "type": "Feature",
  "properties": {
    "iso:country":"US",
    "sg:address":"2001 Mount Vernon Ave",
    "sg:city":"Pomona",
    "sg:classifiers":[
        {
            "category":"Building & Trades",
            "subcategory":"Construction",
            "type":"Services"
        }
    ],
    "sg:phone":"+1 909 868 1991",
    "sg:postcode":"91768",
    "sg:province":"CA",
    "sg:tags":[
        "excavating",
        "contractor"
    ],
    "sg:website":"www.rjjconstruction.com",
    "wof:name":"R J & J Construction Inc",
    "wof:placetype":"venue"
},
  "geometry": {"coordinates":[-117.785141,34.05835],"type":"Point"}
}