{
  "type": "Feature",
  "properties": {
    "addr:full":"5600 Harold Way Los Angeles CA 90028",
    "addr:housenumber":"5600",
    "addr:postcode":"90028",
    "addr:street":"Harold Way",
    "iso:country":"US",
    "sg:address":"5600 Harold Way",
    "sg:city":"Los Angeles",
    "sg:classifiers":[
        {
            "category":"Retail",
            "subcategory":"Animal Services",
            "type":"Services"
        }
    ],
    "sg:phone":"+1 323 462 5964",
    "sg:postcode":"90028",
    "sg:province":"CA",
    "wof:name":"Canine Shine",
    "wof:placetype":"venue"
},
  "geometry": {"coordinates":[-118.313619,34.099328],"type":"Point"}
}