{
  "type": "Feature",
  "properties": {
    "addr:full":"1212 N Bellflower Blvd Long Beach CA 90815",
    "addr:housenumber":"1212",
    "addr:postcode":"90815",
    "addr:street":"N Bellflower Blvd",
    "iso:country":"US",
    "sg:address":"1212 N Bellflower Blvd",
    "sg:city":"Long Beach",
    "sg:classifiers":[
        {
            "category":"Restaurant",
            "type":"Food & Drink"
        }
    ],
    "sg:phone":"+1 562 498 6696",
    "sg:postcode":"90815",
    "sg:province":"CA",
    "wof:name":"Carl's Jr Restaurant",
    "wof:placetype":"venue"
},
  "geometry": {"coordinates":[-118.12200199999999,33.7822],"type":"Point"}
}