{
  "type": "Feature",
  "properties": {
    "iso:country":"US",
    "sg:address":"3050 W Shaw Ave Ste 108",
    "sg:city":"Fresno",
    "sg:classifiers":[
        {
            "category":"Restaurant",
            "type":"Food & Drink"
        }
    ],
    "sg:phone":"+1 559 275 1100",
    "sg:postcode":"93711",
    "sg:province":"CA",
    "sg:tags":[
        "indian"
    ],
    "wof:name":"Brahma",
    "wof:placetype":"venue"
},
  "geometry": {"coordinates":[-119.845732,36.808406],"type":"Point"}
}