{
  "type": "Feature",
  "properties": {
    "addr:full":"3663 Petersen Rd Stockton CA 95215",
    "addr:housenumber":"3663",
    "addr:postcode":"95215",
    "addr:street":"Petersen Rd",
    "iso:country":"US",
    "sg:address":"3663 Petersen Rd",
    "sg:city":"Stockton",
    "sg:classifiers":[
        {
            "category":"Retail",
            "subcategory":"Auto Rental",
            "type":"Services"
        }
    ],
    "sg:phone":"+1 209 948 1500",
    "sg:postcode":"95215",
    "sg:province":"CA",
    "sg:tags":[
        "renting",
        "truck",
        "leasing"
    ],
    "sg:website":"www.penske.com",
    "wof:name":"Penske Truck Leasing",
    "wof:placetype":"venue"
},
  "geometry": {"coordinates":[-121.230333,37.936918],"type":"Point"}
}