{
  "type": "Feature",
  "properties": {
    "addr:full":"1824 Heller Ln Redding CA 96001",
    "addr:housenumber":"1824",
    "addr:postcode":"96001",
    "addr:street":"Heller Ln",
    "iso:country":"US",
    "sg:address":"1824 Heller Ln",
    "sg:city":"Redding",
    "sg:classifiers":[
        {
            "category":"Manufacturing",
            "subcategory":"Lumber",
            "type":"Manufacturing & Wholesale Goods"
        }
    ],
    "sg:phone":"+1 530 243 9010",
    "sg:postcode":"96001",
    "sg:province":"CA",
    "sg:tags":[
        "tree",
        "sale",
        "collection",
        "to",
        "cone",
        "flo",
        "pine",
        "limb"
    ],
    "wof:name":"Natures Bounty",
    "wof:placetype":"venue"
},
  "geometry": {"coordinates":[-122.392066,40.534711],"type":"Point"}
}