{
  "type": "Feature",
  "properties": {
    "iso:country":"US",
    "sg:address":"26811 Seco Canyon Rd",
    "sg:city":"Saugus",
    "sg:classifiers":[
        {
            "category":"Building & Trades",
            "subcategory":"Construction",
            "type":"Services"
        }
    ],
    "sg:phone":"+1 661 296 5489",
    "sg:postcode":"91350",
    "sg:province":"CA",
    "sg:tags":[
        "builder",
        "patio",
        "deck"
    ],
    "wof:name":"Custom Design Patio Covers",
    "wof:placetype":"venue"
},
  "geometry": {"coordinates":[-118.531961,34.434998],"type":"Point"}
}