{
  "type": "Feature",
  "properties": {
    "addr:full":"2948 Sybil Way Carmichael CA 95608",
    "addr:housenumber":"2948",
    "addr:postcode":"95608",
    "addr:street":"Sybil Way",
    "iso:country":"US",
    "sg:address":"2948 Sybil Way",
    "sg:city":"Carmichael",
    "sg:classifiers":[
        {
            "category":"Shopping",
            "subcategory":"Discount & Variety Stores",
            "type":"Retail Goods"
        }
    ],
    "sg:phone":"+1 916 481 6511",
    "sg:postcode":"95608",
    "sg:province":"CA",
    "sg:tags":[
        "merchandise",
        "general"
    ],
    "sg:website":"www.renegaderelicart.com",
    "wof:name":"Renegade Relic Art",
    "wof:placetype":"venue"
},
  "geometry": {"coordinates":[-121.33800599999999,38.619217],"type":"Point"}
}