{
  "type": "Feature",
  "properties": {
    "iso:country":"US",
    "sg:address":"1807 Academy Ave",
    "sg:city":"Sanger",
    "sg:classifiers":[
        {
            "category":"Shopping",
            "subcategory":"Jewelry",
            "type":"Retail Goods"
        }
    ],
    "sg:phone":"+1 559 875 5633",
    "sg:postcode":"93657",
    "sg:province":"CA",
    "sg:tags":[
        "repair",
        "clocks",
        "watch",
        "jeweler"
    ],
    "wof:name":"Stancraft Designer Jewelry",
    "wof:placetype":"venue"
},
  "geometry": {"coordinates":[-119.554205,36.692278],"type":"Point"}
}