{
  "type": "Feature",
  "properties": {
    "addr:full":"Fullerton Promenade 215 N Harbor Blvd Fullerton CA 92832",
    "addr:housenumber":"215",
    "addr:postcode":"92832",
    "addr:street":"Fullerton Promenade;N Harbor Blvd",
    "iso:country":"US",
    "sg:address":"Fullerton Promenade 215 N Harbor Blvd",
    "sg:city":"Fullerton",
    "sg:classifiers":[
        {
            "category":"Shopping",
            "subcategory":"Used Merchandise",
            "type":"Retail Goods"
        }
    ],
    "sg:phone":"+1 714 870 6855",
    "sg:postcode":"92832",
    "sg:province":"CA",
    "sg:tags":[
        "vintage",
        "consignment"
    ],
    "sg:website":"www.buffaloexchange.com/",
    "wof:name":"Buffalo Exchange",
    "wof:placetype":"venue"
},
  "geometry": {"coordinates":[-117.92468100000001,33.871899],"type":"Point"}
}