{
  "type": "Feature",
  "properties": {
    "addr:full":"16199 Eucalyptus St Hesperia CA 92345",
    "addr:housenumber":"16199",
    "addr:postcode":"92345",
    "addr:street":"Eucalyptus St",
    "iso:country":"US",
    "sg:address":"16199 Eucalyptus St",
    "sg:city":"Hesperia",
    "sg:classifiers":[
        {
            "category":"Professional",
            "subcategory":"Credit Reporting & Collection",
            "type":"Services"
        }
    ],
    "sg:phone":"+1 760 949 0944",
    "sg:postcode":"92345",
    "sg:province":"CA",
    "sg:tags":[
        "agency"
    ],
    "wof:name":"Empire Legal Judgement Rcvry",
    "wof:placetype":"venue"
},
  "geometry": {"coordinates":[-117.311126,34.456097],"type":"Point"}
}