{
  "type": "Feature",
  "properties": {
    "addr:full":"16225 Wells Fargo Ave Palmdale CA 93591",
    "addr:housenumber":"16225",
    "addr:postcode":"ca 93591",
    "addr:street":"Wells Fargo Ave",
    "iso:country":"US",
    "sg:address":"16225 Wells Fargo Ave",
    "sg:city":"Palmdale",
    "sg:classifiers":[
        {
            "category":"Organizations",
            "subcategory":"Community Association",
            "type":"Services"
        }
    ],
    "sg:phone":"+1 661 727 9122",
    "sg:postcode":"93591",
    "sg:province":"CA",
    "wof:name":"Lodge 2467 - Lake Los Angeles",
    "wof:placetype":"venue"
},
  "geometry": {"coordinates":[-117.839562,34.59683],"type":"Point"}
}