{
  "type": "Feature",
  "properties": {
    "iso:country":"US",
    "sg:address":"1291 Hays St",
    "sg:city":"San Leandro",
    "sg:classifiers":[
        {
            "category":"Real Estate",
            "subcategory":"Real Estate Agent",
            "type":"Services"
        }
    ],
    "sg:phone":"+1 510 552 2651",
    "sg:postcode":"94577",
    "sg:province":"CA",
    "wof:name":"United Investments Enterprise",
    "wof:placetype":"venue"
},
  "geometry": {"coordinates":[-122.15799199999999,37.725165],"type":"Point"}
}