{
  "type": "Feature",
  "properties": {
    "iso:country":"US",
    "sg:address":"2097 N Towne Ave",
    "sg:city":"Pomona",
    "sg:classifiers":[
        {
            "category":"Food & Beverages",
            "subcategory":"Bakery",
            "type":"Retail Goods"
        }
    ],
    "sg:phone":"+1 909 620 9592",
    "sg:postcode":"91767",
    "sg:province":"CA",
    "sg:tags":[
        "doughnut"
    ],
    "wof:name":"Jelly Donut",
    "wof:placetype":"venue"
},
  "geometry": {"coordinates":[-117.74104,34.079363],"type":"Point"}
}