{
  "type": "Feature",
  "properties": {
    "addr:full":"6454 Pony Express Trl #33-233 Pollock Pines CA 95726",
    "addr:housenumber":"6454",
    "addr:postcode":"95726",
    "addr:street":"Pony Express Trl # 33-233",
    "iso:country":"US",
    "sg:address":"6454 Pony Express Trl #33-233",
    "sg:city":"Pollock Pines",
    "sg:classifiers":[
        {
            "category":"Retail",
            "subcategory":"Animal Services",
            "type":"Services"
        }
    ],
    "sg:phone":"+1 877 475 2275",
    "sg:postcode":"95726",
    "sg:province":"CA",
    "sg:tags":[
        "pet"
    ],
    "sg:website":"DogFriendly.com",
    "wof:name":"DogFriendly.com, Inc.",
    "wof:placetype":"venue"
},
  "geometry": {"coordinates":[-120.579314,38.762933],"type":"Point"}
}