{
  "type": "Feature",
  "properties": {
    "iso:country":"US",
    "sg:address":"17330 Muskrat Ave",
    "sg:city":"Adelanto",
    "sg:classifiers":[
        {
            "category":"Building & Trades",
            "subcategory":"Plumbing",
            "type":"Services"
        }
    ],
    "sg:phone":"+1 760 246 0480",
    "sg:postcode":"92301",
    "sg:province":"CA",
    "sg:tags":[
        "plumbing",
        "contractor"
    ],
    "wof:name":"RCR Co",
    "wof:placetype":"venue"
},
  "geometry": {"coordinates":[-117.44945,34.56813],"type":"Point"}
}