{
  "type": "Feature",
  "properties": {
    "iso:country":"US",
    "sg:address":"721 E Foothill Blvd",
    "sg:city":"Baldwin Park",
    "sg:classifiers":[
        {
            "category":"Manufacturing",
            "subcategory":"Tools & Machinery",
            "type":"Manufacturing & Wholesale Goods"
        }
    ],
    "sg:phone":"+1 626 962 1222",
    "sg:postcode":"91711",
    "sg:province":"CA",
    "sg:tags":[
        "devices",
        "mfg"
    ],
    "wof:name":"Cpat Distribution Inc",
    "wof:placetype":"venue"
},
  "geometry": {"coordinates":[-117.70120300000001,34.106878],"type":"Point"}
}