{
  "type": "Feature",
  "properties": {
    "iso:country":"US",
    "sg:address":"909 10th St",
    "sg:city":"Firebaugh",
    "sg:classifiers":[
        {
            "category":"Home & Garden",
            "subcategory":"Garden Supply",
            "type":"Retail Goods"
        },
        {
            "category":"Building & Trades",
            "subcategory":"Cleaning & Sanitation",
            "type":"Services"
        },
        {
            "category":"Farming",
            "subcategory":"Nursery",
            "type":"Manufacturing & Wholesale Goods"
        }
    ],
    "sg:phone":"+1 559 659 2198",
    "sg:postcode":"93622",
    "sg:province":"CA",
    "sg:tags":[
        "equipment",
        "seed",
        "growers'",
        "bulb"
    ],
    "wof:name":"Shamrock Seed Company",
    "wof:placetype":"venue"
},
  "geometry": {"coordinates":[-120.46465600000001,36.855433],"type":"Point"}
}