{
  "type": "Feature",
  "properties": {
    "addr:full":"269 22nd St Costa Mesa CA 92627",
    "addr:housenumber":"269",
    "addr:postcode":"92627",
    "addr:street":"22Nd St",
    "iso:country":"US",
    "sg:address":"269 22nd St",
    "sg:city":"Costa Mesa",
    "sg:classifiers":[
        {
            "category":"Shopping",
            "subcategory":"Clothing, Apparel, & Fashions",
            "type":"Retail Goods"
        }
    ],
    "sg:phone":"+1 949 722 9769",
    "sg:postcode":"92627",
    "sg:province":"CA",
    "sg:tags":[
        "sportswear"
    ],
    "wof:name":"O C Ski",
    "wof:placetype":"venue"
},
  "geometry": {"coordinates":[-117.903683,33.648601],"type":"Point"}
}