{
  "type": "Feature",
  "properties": {
    "iso:country":"US",
    "sg:address":"880 N State St",
    "sg:city":"Hemet",
    "sg:classifiers":[
        {
            "category":"Health Services",
            "subcategory":"Clinic",
            "type":"Services"
        }
    ],
    "sg:phone":"+1 951 766 2450",
    "sg:postcode":"92543",
    "sg:province":"CA",
    "sg:tags":[
        "welfare"
    ],
    "wof:name":"Hamet Health Center",
    "wof:placetype":"venue"
},
  "geometry": {"coordinates":[-116.971811,33.761335],"type":"Point"}
}