{
  "type": "Feature",
  "properties": {
    "iso:country":"US",
    "sg:address":"2605 N Pacific Ave",
    "sg:city":"Stockton",
    "sg:classifiers":[
        {
            "category":"Banks & Credit Unions",
            "subcategory":"Bank",
            "type":"Services"
        }
    ],
    "sg:phone":"+1 209 944 5651",
    "sg:postcode":"95204",
    "sg:province":"CA",
    "sg:tags":[
        "financing"
    ],
    "wof:name":"Beneficial California Inc",
    "wof:placetype":"venue"
},
  "geometry": {"coordinates":[-121.30297899999999,37.97496],"type":"Point"}
}