{
  "type": "Feature",
  "properties": {
    "addr:full":"1220 Marsh St San Luis Obispo CA 93401",
    "addr:housenumber":"1220",
    "addr:postcode":"93401",
    "addr:street":"Marsh St",
    "iso:country":"US",
    "sg:address":"1220 Marsh St",
    "sg:city":"San Luis Obispo",
    "sg:classifiers":[
        {
            "category":"Professional",
            "subcategory":"Employment Agencies",
            "type":"Services"
        }
    ],
    "sg:phone":"+1 805 489 1225",
    "sg:postcode":"93401",
    "sg:province":"CA",
    "sg:tags":[
        "opportunity"
    ],
    "wof:name":"LA Petit Nanny Agency",
    "wof:placetype":"venue"
},
  "geometry": {"coordinates":[-120.65615099999999,35.282854],"type":"Point"}
}