{
  "type": "Feature",
  "properties": {
    "addr:full":"7662 Melrose Ave Los Angeles CA 90046",
    "addr:housenumber":"7662",
    "addr:postcode":"90046",
    "addr:street":"Melrose Ave",
    "iso:country":"US",
    "sg:address":"7662 Melrose Ave",
    "sg:city":"Los Angeles",
    "sg:classifiers":[
        {
            "category":"Shopping",
            "subcategory":"Clothing, Apparel, & Fashions",
            "type":"Retail Goods"
        }
    ],
    "sg:phone":"+1 323 655 0770",
    "sg:postcode":"90046",
    "sg:province":"CA",
    "sg:tags":[
        "men's",
        "clothing",
        "women's"
    ],
    "sg:website":"www.suru-la.com",
    "wof:name":"SURU",
    "wof:placetype":"venue"
},
  "geometry": {"coordinates":[-118.356951,34.083493],"type":"Point"}
}