{
  "type": "Feature",
  "properties": {
    "iso:country":"US",
    "sg:address":"12328 Los Osos Valley Rd",
    "sg:city":"San Luis Obispo",
    "sg:classifiers":[
        {
            "category":"Health Services",
            "subcategory":"Clinic",
            "type":"Services"
        }
    ],
    "sg:phone":"+1 805 594 1332",
    "sg:postcode":"93405",
    "sg:province":"CA",
    "sg:tags":[
        "equipment",
        "therapy",
        "oxygen"
    ],
    "wof:name":"Pacific Pulmonary Svc",
    "wof:placetype":"venue"
},
  "geometry": {"coordinates":[-120.683652,35.247917],"type":"Point"}
}