{
  "type": "Feature",
  "properties": {
    "addr:full":"108 S Sunnyvale Ave Sunnyvale CA 94086",
    "addr:housenumber":"108",
    "addr:postcode":"94086",
    "addr:street":"S Sunnyvale Ave",
    "iso:country":"US",
    "sg:address":"108 S Sunnyvale Ave",
    "sg:city":"Sunnyvale",
    "sg:classifiers":[
        {
            "category":"Shopping",
            "type":"Retail Goods"
        }
    ],
    "sg:phone":"+1 408 616 7777",
    "sg:postcode":"94086",
    "sg:province":"CA",
    "sg:tags":[
        "merchandise"
    ],
    "wof:name":"Rluv of Candles & Art",
    "wof:placetype":"venue"
},
  "geometry": {"coordinates":[-122.029285,37.375882],"type":"Point"}
}