{
  "type": "Feature",
  "properties": {
    "addr:full":"4213 Terrace St Oakland CA 94611",
    "addr:housenumber":"4213",
    "addr:postcode":"94611",
    "addr:street":"Terrace St",
    "iso:country":"US",
    "sg:address":"4213 Terrace St",
    "sg:city":"Oakland",
    "sg:classifiers":[
        {
            "category":"Building & Trades",
            "subcategory":"Construction",
            "type":"Services"
        }
    ],
    "sg:phone":"+1 510 652 9426",
    "sg:postcode":"94611",
    "sg:province":"CA",
    "sg:tags":[
        "contractor"
    ],
    "wof:name":"Bay Area Contractor Referral",
    "wof:placetype":"venue"
},
  "geometry": {"coordinates":[-122.254229,37.829953],"type":"Point"}
}