{
  "type": "Feature",
  "properties": {
    "addr:full":"19023 Pine Canyon Rd Lake Hughes CA 93532",
    "addr:housenumber":"19023",
    "addr:postcode":"93532",
    "addr:street":"Pine Canyon Rd",
    "iso:country":"US",
    "sg:address":"19023 Pine Canyon Rd",
    "sg:city":"Lake Hughes",
    "sg:classifiers":[
        {
            "category":"Local Transit",
            "type":"Transportation"
        }
    ],
    "sg:phone":"+1 661 724 1285",
    "sg:postcode":"93532",
    "sg:province":"CA",
    "sg:tags":[
        "bus",
        "line"
    ],
    "wof:name":"Santa Barbara Transportation",
    "wof:placetype":"venue"
},
  "geometry": {"coordinates":[-118.469685,34.686225],"type":"Point"}
}