{
  "type": "Feature",
  "properties": {
    "addr:full":"1700 Alum Rock Avenue San Jose CA 95116",
    "addr:housenumber":"1700",
    "addr:postcode":"95116",
    "addr:street":"Alum Rock Avenue",
    "iso:country":"US",
    "sg:address":"1700 Alum Rock Avenue",
    "sg:city":"San Jose",
    "sg:classifiers":[
        {
            "category":"Museum",
            "type":"Entertainment"
        }
    ],
    "sg:phone":"+1 408 928 5500",
    "sg:postcode":"95116",
    "sg:province":"CA",
    "wof:name":"Mexican Heritage Corporation of San Jose",
    "wof:placetype":"venue"
},
  "geometry": {"coordinates":[-121.854913,37.35292],"type":"Point"}
}