{
  "type": "Feature",
  "properties": {
    "iso:country":"US",
    "sg:address":"487 Magnolia Ave",
    "sg:city":"Corona",
    "sg:classifiers":[
        {
            "category":"Shopping",
            "subcategory":"Gifts & Souvenirs",
            "type":"Retail Goods"
        }
    ],
    "sg:phone":"+1 951 272 4040",
    "sg:postcode":"92879",
    "sg:province":"CA",
    "sg:tags":[
        "shop"
    ],
    "wof:name":"Mary Conklin Collectibles",
    "wof:placetype":"venue"
},
  "geometry": {"coordinates":[-117.561227,33.855151],"type":"Point"}
}