{
  "type": "Feature",
  "properties": {
    "addr:full":"330 Cordova St Pasadena CA 91101",
    "addr:housenumber":"330",
    "addr:postcode":"91101",
    "addr:street":"Cordova St",
    "iso:country":"US",
    "sg:address":"330 Cordova St",
    "sg:city":"Pasadena",
    "sg:classifiers":[
        {
            "category":"Real Estate",
            "subcategory":"Real Estate Services",
            "type":"Services"
        },
        {
            "category":"Real Estate",
            "subcategory":"Real Estate Agent",
            "type":"Services"
        }
    ],
    "sg:phone":"+1 626 577 4630",
    "sg:postcode":"91101",
    "sg:province":"CA",
    "sg:tags":[
        "buyer",
        "broker"
    ],
    "wof:name":"Potter, Malcolm",
    "wof:placetype":"venue"
},
  "geometry": {"coordinates":[-118.14314400000001,34.142138],"type":"Point"}
}