{
  "type": "Feature",
  "properties": {
    "addr:full":"4755 Holt Blvd Montclair CA 91763",
    "addr:housenumber":"4755",
    "addr:postcode":"91763",
    "addr:street":"Holt Blvd",
    "iso:country":"US",
    "sg:address":"4755 Holt Blvd",
    "sg:city":"Montclair",
    "sg:classifiers":[
        {
            "category":"Utilities",
            "subcategory":"Mobile Phone",
            "type":"Services"
        }
    ],
    "sg:phone":"+1 909 621 6706",
    "sg:postcode":"91763",
    "sg:province":"CA",
    "sg:tags":[
        "telephone",
        "cellular"
    ],
    "wof:name":"Nextel Communications Inc",
    "wof:placetype":"venue"
},
  "geometry": {"coordinates":[-117.705502,34.063101],"type":"Point"}
}