{
  "type": "Feature",
  "properties": {
    "addr:full":"3135 16th Street San Francisco CA 94103",
    "addr:housenumber":"3135",
    "addr:postcode":"94103",
    "addr:street":"16Th Street",
    "iso:country":"US",
    "sg:address":"3135 16th Street",
    "sg:city":"San Francisco",
    "sg:classifiers":[
        {
            "category":"Personal",
            "subcategory":"Shoe Repair & Shine",
            "type":"Services"
        }
    ],
    "sg:phone":"+1 415 861 1851",
    "sg:postcode":"94103",
    "sg:province":"CA",
    "wof:name":"Sam's Shoe Service",
    "wof:placetype":"venue"
},
  "geometry": {"coordinates":[-122.422997,37.764801],"type":"Point"}
}