{
  "type": "Feature",
  "properties": {
    "addr:full":"937 Paradise Blvd Hayward CA 94541",
    "addr:housenumber":"937",
    "addr:postcode":"94541",
    "addr:street":"Paradise Blvd",
    "iso:country":"US",
    "sg:address":"937 Paradise Blvd",
    "sg:city":"Hayward",
    "sg:classifiers":[
        {
            "category":"Banks & Credit Unions",
            "subcategory":"Investment Brokerage",
            "type":"Services"
        }
    ],
    "sg:phone":"+1 510 276 0918",
    "sg:postcode":"94541",
    "sg:province":"CA",
    "sg:tags":[
        "consultant",
        "planning",
        "financial"
    ],
    "wof:name":"Redwood Financial Analysis",
    "wof:placetype":"venue"
},
  "geometry": {"coordinates":[-122.105442,37.686323],"type":"Point"}
}