{
  "type": "Feature",
  "properties": {
    "addr:full":"1090 La Playa Dr Hayward CA 94545",
    "addr:housenumber":"1090",
    "addr:postcode":"94545",
    "addr:street":"La Playa Dr",
    "iso:country":"US",
    "sg:address":"1090 La Playa Dr",
    "sg:city":"Hayward",
    "sg:classifiers":[
        {
            "category":"Health Services",
            "subcategory":"Doctor",
            "type":"Services"
        }
    ],
    "sg:phone":"+1 510 785 5555",
    "sg:postcode":"94545",
    "sg:province":"CA",
    "sg:tags":[
        "medicine",
        "internal"
    ],
    "wof:name":"Kannan Nirmala MD",
    "wof:placetype":"venue"
},
  "geometry": {"coordinates":[-122.105397,37.647434],"type":"Point"}
}