{
  "type": "Feature",
  "properties": {
    "addr:full":"429 N 3rd Street San Jose CA 95112",
    "addr:housenumber":"429",
    "addr:postcode":"95112",
    "addr:street":"N 3Rd Street",
    "iso:country":"US",
    "sg:address":"429 N 3rd Street",
    "sg:city":"San Jose",
    "sg:classifiers":[
        {
            "category":"Health Services",
            "subcategory":"Optometrist",
            "type":"Services"
        }
    ],
    "sg:phone":"+1 408 295 3098",
    "sg:postcode":"95112",
    "sg:province":"CA",
    "sg:website":"www.preferredvisiongroup.com",
    "wof:name":"Preferred Vision Group",
    "wof:placetype":"venue"
},
  "geometry": {"coordinates":[-121.89390899999999,37.34429],"type":"Point"}
}