{
  "type": "Feature",
  "properties": {
    "addr:full":"333 S Gilbert St Hemet CA 92543",
    "addr:housenumber":"333",
    "addr:postcode":"92543",
    "addr:street":"S Gilbert St",
    "iso:country":"US",
    "sg:address":"333 S Gilbert St",
    "sg:city":"Hemet",
    "sg:classifiers":[
        {
            "category":"Utilities",
            "subcategory":"Telephone",
            "type":"Services"
        }
    ],
    "sg:phone":"+1 951 766 6525",
    "sg:postcode":"92543",
    "sg:province":"CA",
    "sg:tags":[
        "internet"
    ],
    "wof:name":"Affiliatemall2000com",
    "wof:placetype":"venue"
},
  "geometry": {"coordinates":[-116.97604,33.742679],"type":"Point"}
}