{
  "type": "Feature",
  "properties": {
    "iso:country":"US",
    "sg:address":"806 W 131st St",
    "sg:city":"Gardena",
    "sg:classifiers":[
        {
            "category":"Wholesale",
            "subcategory":"Durable Goods & Equipment",
            "type":"Manufacturing & Wholesale Goods"
        }
    ],
    "sg:phone":"+1 310 251 3954",
    "sg:postcode":"90247",
    "sg:province":"CA",
    "wof:name":"Rauls Butcher Supplies",
    "wof:placetype":"venue"
},
  "geometry": {"coordinates":[-118.291517,33.913257],"type":"Point"}
}