{
  "type": "Feature",
  "properties": {
    "addr:full":"30100 Mission Blvd Hayward CA 94544",
    "addr:housenumber":"30100",
    "addr:postcode":"94544",
    "addr:street":"Mission Blvd",
    "iso:country":"US",
    "sg:address":"30100 Mission Blvd",
    "sg:city":"Hayward",
    "sg:classifiers":[
        {
            "category":"Professional",
            "subcategory":"Accounting & Tax Preparation",
            "type":"Services"
        }
    ],
    "sg:phone":"+1 510 487 1691",
    "sg:postcode":"94544",
    "sg:province":"CA",
    "sg:tags":[
        "return",
        "filing"
    ],
    "wof:name":"Adtech Tax & Payroll",
    "wof:placetype":"venue"
},
  "geometry": {"coordinates":[-122.043091,37.626661],"type":"Point"}
}