{
  "type": "Feature",
  "properties": {
    "iso:country":"US",
    "sg:address":"1111 S Arroyo Pkwy, Suite 220",
    "sg:city":"Pasadena",
    "sg:classifiers":[
        {
            "category":"Professional",
            "type":"Services"
        }
    ],
    "sg:phone":"+1 626 799 7955",
    "sg:postcode":"91105",
    "sg:province":"CA",
    "sg:website":"www.expressiveconnections.org",
    "wof:name":"Expressive Connections",
    "wof:placetype":"venue"
},
  "geometry": {"coordinates":[-118.16342400000001,34.126892],"type":"Point"}
}