{
  "type": "Feature",
  "properties": {
    "iso:country":"US",
    "sg:address":"2570 Napa Nook Rd",
    "sg:city":"Yountville",
    "sg:classifiers":[
        {
            "category":"Manufacturing",
            "subcategory":"Food",
            "type":"Manufacturing & Wholesale Goods"
        }
    ],
    "sg:phone":"+1 707 944 8954",
    "sg:postcode":"94599",
    "sg:province":"CA",
    "sg:tags":[
        "winery"
    ],
    "sg:website":"www.dominusestate.com",
    "wof:name":"Dominus Estate",
    "wof:placetype":"venue"
},
  "geometry": {"coordinates":[-122.369115,38.405792],"type":"Point"}
}