{
  "type": "Feature",
  "properties": {
    "iso:country":"US",
    "sg:address":"2835 Darwin St",
    "sg:city":"Hayward",
    "sg:classifiers":[
        {
            "category":"Freight",
            "type":"Transportation"
        }
    ],
    "sg:phone":"+1 510 782 5148",
    "sg:postcode":"94545",
    "sg:province":"CA",
    "sg:tags":[
        "courier"
    ],
    "wof:name":"Singhs Courier Service",
    "wof:placetype":"venue"
},
  "geometry": {"coordinates":[-122.107698,37.629263],"type":"Point"}
}