{
  "type": "Feature",
  "properties": {
    "addr:full":"67890 E Palm Canyon Dr Cathedral City CA 92234",
    "addr:housenumber":"67890",
    "addr:postcode":"92234",
    "addr:street":"E Palm Canyon Dr",
    "iso:country":"US",
    "sg:address":"67890 E Palm Canyon Dr",
    "sg:city":"Cathedral City",
    "sg:classifiers":[
        {
            "category":"Autos & Motor Vehicles",
            "subcategory":"Fuel & Gas Station",
            "type":"Retail Goods"
        },
        {
            "category":"Food & Beverages",
            "subcategory":"Groceries & Convenience Stores",
            "type":"Retail Goods"
        }
    ],
    "sg:phone":"+1 760 324 0188",
    "sg:postcode":"92234",
    "sg:province":"CA",
    "wof:name":"Valero",
    "wof:placetype":"venue"
},
  "geometry": {"coordinates":[-116.477227,33.785629],"type":"Point"}
}