{
  "type": "Feature",
  "properties": {
    "addr:full":"700 Illinois St Unit 110 San Francisco CA 94107",
    "addr:housenumber":"700;110",
    "addr:postcode":"94107",
    "addr:street":"Illinois St Unit",
    "iso:country":"US",
    "sg:address":"700 Illinois St Unit 110",
    "sg:city":"San Francisco",
    "sg:classifiers":[
        {
            "category":"Professional",
            "subcategory":"Art Services",
            "type":"Services"
        },
        {
            "category":"Communications",
            "type":"Services"
        }
    ],
    "sg:phone":"+1 415 436 9902",
    "sg:postcode":"94107",
    "sg:province":"CA",
    "sg:tags":[
        "web",
        "graphic",
        "design"
    ],
    "sg:website":"www.ordinarykids.com",
    "wof:name":"Ordinarykids",
    "wof:placetype":"venue"
},
  "geometry": {"coordinates":[-122.388255,37.762341],"type":"Point"}
}