{
  "type": "Feature",
  "properties": {
    "iso:country":"US",
    "sg:address":"1143 Westminster Ave",
    "sg:city":"Alhambra",
    "sg:classifiers":[
        {
            "category":"Professional",
            "subcategory":"Management & Consulting",
            "type":"Services"
        }
    ],
    "sg:phone":"+1 626 281 9979",
    "sg:postcode":"91803",
    "sg:province":"CA",
    "sg:tags":[
        "consultant",
        "educational"
    ],
    "wof:name":"BELI-Behavior Education",
    "wof:placetype":"venue"
},
  "geometry": {"coordinates":[-118.156145,34.084141],"type":"Point"}
}