{
  "type": "Feature",
  "properties": {
    "iso:country":"US",
    "sg:address":"127 N Reino Rd",
    "sg:city":"Newbury Park",
    "sg:classifiers":[
        {
            "category":"Retail",
            "subcategory":"Laundry & Dry Cleaning",
            "type":"Services"
        }
    ],
    "sg:phone":"+1 805 498 1800",
    "sg:postcode":"91320",
    "sg:province":"CA",
    "wof:name":"Majesty Cleaners",
    "wof:placetype":"venue"
},
  "geometry": {"coordinates":[-118.953003,34.182098],"type":"Point"}
}