{
  "type": "Feature",
  "properties": {
    "addr:full":"16386 Keyes Rd Snelling CA 95369",
    "addr:housenumber":"16386",
    "addr:postcode":"95369",
    "addr:street":"Keyes Rd",
    "iso:country":"US",
    "sg:address":"16386 Keyes Rd",
    "sg:city":"Snelling",
    "sg:classifiers":[
        {
            "category":"Professional",
            "type":"Services"
        }
    ],
    "sg:phone":"+1 209 563 0057",
    "sg:postcode":"95369",
    "sg:province":"CA",
    "sg:tags":[
        "establishment"
    ],
    "wof:name":"Can American Fresh Berries",
    "wof:placetype":"venue"
},
  "geometry": {"coordinates":[-120.447855,37.530776],"type":"Point"}
}