{
  "type": "Feature",
  "properties": {
    "addr:full":"2727 Thomas Rd Hollister CA 95023",
    "addr:housenumber":"2727",
    "addr:postcode":"hollister ca 95023",
    "addr:street":"Thomas Rd",
    "iso:country":"US",
    "sg:address":"2727 Thomas Rd",
    "sg:city":"Hollister",
    "sg:classifiers":[
        {
            "category":"Retail",
            "subcategory":"Animal Services",
            "type":"Services"
        }
    ],
    "sg:phone":"+1 831 637 2235",
    "sg:postcode":"95023",
    "sg:province":"CA",
    "sg:tags":[
        "breeder",
        "horse"
    ],
    "wof:name":"D'Arcangel Ranch",
    "wof:placetype":"venue"
},
  "geometry": {"coordinates":[-121.32083299999999,36.744598],"type":"Point"}
}