{
  "type": "Feature",
  "properties": {
    "addr:full":"417 River Meadows Dr Woodbridge CA 95258",
    "addr:housenumber":"417",
    "addr:postcode":"95258",
    "addr:street":"River Meadows Dr",
    "iso:country":"US",
    "sg:address":"417 River Meadows Dr",
    "sg:city":"Woodbridge",
    "sg:classifiers":[
        {
            "category":"Building & Trades",
            "subcategory":"Construction",
            "type":"Services"
        }
    ],
    "sg:phone":"+1 209 368 1222",
    "sg:postcode":"95258",
    "sg:province":"CA",
    "sg:tags":[
        "house",
        "nonresidential"
    ],
    "wof:name":"Matthew L Mc Carty Cnstr",
    "wof:placetype":"venue"
},
  "geometry": {"coordinates":[-121.310726,38.159379],"type":"Point"}
}