{
  "type": "Feature",
  "properties": {
    "addr:full":"120 Majorca Pl Placentia CA 92870",
    "addr:housenumber":"120",
    "addr:postcode":"ca 92870",
    "addr:street":"Majorca Pl",
    "iso:country":"US",
    "sg:address":"120 Majorca Pl",
    "sg:city":"Placentia",
    "sg:classifiers":[
        {
            "category":"Real Estate",
            "subcategory":"Real Estate Services",
            "type":"Services"
        },
        {
            "category":"Real Estate",
            "subcategory":"Real Estate Agent",
            "type":"Services"
        }
    ],
    "sg:phone":"+1 714 524 2444",
    "sg:postcode":"92870",
    "sg:province":"CA",
    "sg:tags":[
        "management"
    ],
    "wof:name":"Vistara Homes",
    "wof:placetype":"venue"
},
  "geometry": {"coordinates":[-117.84987599999999,33.86879],"type":"Point"}
}