{
  "type": "Feature",
  "properties": {
    "iso:country":"US",
    "sg:address":"2960 Dolores Way",
    "sg:city":"Burlingame",
    "sg:classifiers":[
        {
            "category":"Professional",
            "subcategory":"Art Services",
            "type":"Services"
        }
    ],
    "sg:phone":"+1 650 692 1839",
    "sg:postcode":"94010",
    "sg:province":"CA",
    "sg:tags":[
        "artist"
    ],
    "wof:name":"Peter Siu",
    "wof:placetype":"venue"
},
  "geometry": {"coordinates":[-122.399913,37.583109],"type":"Point"}
}