{
  "type": "Feature",
  "properties": {
    "iso:country":"US",
    "sg:address":"1442 Walnut St",
    "sg:city":"Berkeley",
    "sg:classifiers":[
        {
            "category":"Professional",
            "subcategory":"Secretarial Services",
            "type":"Services"
        }
    ],
    "sg:phone":"+1 510 525 1578",
    "sg:postcode":"94709",
    "sg:province":"CA",
    "sg:tags":[
        "convention",
        "court",
        "reporter"
    ],
    "wof:name":"World Record Reporters",
    "wof:placetype":"venue"
},
  "geometry": {"coordinates":[-122.26846500000001,37.881832],"type":"Point"}
}