{
  "type": "Feature",
  "properties": {
    "iso:country":"US",
    "sg:address":"1117 G St",
    "sg:city":"Sacramento",
    "sg:classifiers":[
        {
            "category":"Organizations",
            "subcategory":"Non-profit Organization",
            "type":"Services"
        }
    ],
    "sg:phone":"+1 916 442 2582",
    "sg:postcode":"95814",
    "sg:province":"CA",
    "sg:tags":[
        "service/non-profit",
        "community"
    ],
    "sg:website":"www.bgcsac.org",
    "wof:name":"Boys & Girls Clubs of Greater Sacramento",
    "wof:placetype":"venue"
},
  "geometry": {"coordinates":[-121.49048500000001,38.583195],"type":"Point"}
}