{
  "type": "Feature",
  "properties": {
    "iso:country":"US",
    "sg:address":"761 Rodmartin Ct",
    "sg:city":"Folsom",
    "sg:classifiers":[
        {
            "category":"Professional",
            "type":"Services"
        },
        {
            "category":"Professional",
            "subcategory":"Advertising",
            "type":"Services"
        }
    ],
    "sg:phone":"+1 916 983 5505",
    "sg:postcode":"95630",
    "sg:province":"CA",
    "sg:tags":[
        "sample",
        "product",
        "service-circular",
        "fair",
        "agency",
        "specialty",
        "trade",
        "distributing",
        "exposition",
        "advertising-promotional",
        "shows"
    ],
    "wof:name":"Rm Specialty Advertising & Gift",
    "wof:placetype":"venue"
},
  "geometry": {"coordinates":[-121.13891700000001,38.664184],"type":"Point"}
}