{
  "type": "Feature",
  "properties": {
    "iso:country":"US",
    "sg:address":"2 la Porte St",
    "sg:city":"Arcadia",
    "sg:classifiers":[
        {
            "category":"Building & Trades",
            "subcategory":"Construction",
            "type":"Services"
        }
    ],
    "sg:phone":"+1 626 821 4665",
    "sg:postcode":"91006",
    "sg:province":"CA",
    "sg:tags":[
        "roofing",
        "contractor",
        "industrial",
        "contractors-commercial",
        "consultant"
    ],
    "wof:name":"J N Davis Roofing",
    "wof:placetype":"venue"
},
  "geometry": {"coordinates":[-118.031464,34.144451],"type":"Point"}
}