{
  "type": "Feature",
  "properties": {
    "addr:full":"5700 Whitsett Ave Valley Village CA 91607",
    "addr:housenumber":"5700",
    "addr:postcode":"91607",
    "addr:street":"Whitsett Ave",
    "iso:country":"US",
    "sg:address":"5700 Whitsett Ave",
    "sg:city":"Valley Village",
    "sg:classifiers":[
        {
            "category":"Manufacturing",
            "subcategory":"Apparel",
            "type":"Manufacturing & Wholesale Goods"
        }
    ],
    "sg:phone":"+1 818 762 2917",
    "sg:postcode":"91607",
    "sg:province":"CA",
    "sg:tags":[
        "curvaceous",
        "lingerie",
        "for",
        "woman"
    ],
    "wof:name":"Stephannas Curves",
    "wof:placetype":"venue"
},
  "geometry": {"coordinates":[-118.40524600000001,34.174855],"type":"Point"}
}