{
  "type": "Feature",
  "properties": {
    "addr:full":"90 Spruce Ave S San Francisco CA 94080",
    "addr:housenumber":"90",
    "addr:postcode":"94080",
    "addr:street":"Spruce Ave S",
    "iso:country":"US",
    "sg:address":"90 Spruce Ave",
    "sg:city":"S San Francisco",
    "sg:classifiers":[
        {
            "category":"Travel",
            "subcategory":"Travel Agent",
            "type":"Entertainment"
        }
    ],
    "sg:phone":"+1 650 553 9500",
    "sg:postcode":"94080",
    "sg:province":"CA",
    "sg:tags":[
        "agency",
        "bureau"
    ],
    "wof:name":"Ole Travel",
    "wof:placetype":"venue"
},
  "geometry": {"coordinates":[-122.41676699999999,37.654123],"type":"Point"}
}