{
  "type": "Feature",
  "properties": {
    "iso:country":"US",
    "sg:address":"1507 Grant St",
    "sg:city":"Calistoga",
    "sg:classifiers":[
        {
            "category":"Education",
            "subcategory":"School",
            "type":"Public Place"
        }
    ],
    "sg:phone":"+1 707 942 5255",
    "sg:postcode":"94515",
    "sg:province":"CA",
    "sg:tags":[
        "high",
        "middle",
        "elementary"
    ],
    "wof:name":"Calistoga Joint Unified School District",
    "wof:placetype":"venue"
},
  "geometry": {"coordinates":[-122.57801000000001,38.583086],"type":"Point"}
}