{
  "type": "Feature",
  "properties": {
    "iso:country":"US",
    "sg:address":"3350 Wilshire Blvd",
    "sg:city":"Los Angeles",
    "sg:classifiers":[
        {
            "category":"Professional",
            "subcategory":"Accounting & Tax Preparation",
            "type":"Services"
        }
    ],
    "sg:phone":"+1 213 384 2149",
    "sg:postcode":"90010",
    "sg:province":"CA",
    "sg:tags":[
        "accountant"
    ],
    "wof:name":"Peter Yoon & Co",
    "wof:placetype":"venue"
},
  "geometry": {"coordinates":[-118.29624,34.061693],"type":"Point"}
}