{
  "type": "Feature",
  "properties": {
    "addr:full":"1830 W Romneya Dr Anaheim CA 92801",
    "addr:housenumber":"1830",
    "addr:postcode":"92801",
    "addr:street":"W Romneya Dr",
    "iso:country":"US",
    "sg:address":"1830 W Romneya Dr",
    "sg:city":"Anaheim",
    "sg:classifiers":[
        {
            "category":"Professional",
            "type":"Services"
        }
    ],
    "sg:phone":"+1 714 808 4608",
    "sg:postcode":"92801",
    "sg:province":"CA",
    "wof:name":"Rebrac",
    "wof:placetype":"venue"
},
  "geometry": {"coordinates":[-117.944091,33.850639],"type":"Point"}
}