{
  "type": "Feature",
  "properties": {
    "iso:country":"US",
    "sg:address":"233 Santa Monica Blvd",
    "sg:city":"Santa Monica",
    "sg:classifiers":[
        {
            "category":"Health Services",
            "subcategory":"Optometrist",
            "type":"Services"
        }
    ],
    "sg:phone":"+1 310 394 7775",
    "sg:postcode":"90401",
    "sg:province":"CA",
    "wof:name":"Optometric Options",
    "wof:placetype":"venue"
},
  "geometry": {"coordinates":[-118.496414,34.015473],"type":"Point"}
}