{
  "type": "Feature",
  "properties": {
    "iso:country":"US",
    "sg:address":"1036 N Marcin St",
    "sg:city":"Visalia",
    "sg:classifiers":[
        {
            "category":"Autos & Motor Vehicles",
            "subcategory":"Motorcycle Sales",
            "type":"Retail Goods"
        }
    ],
    "sg:phone":"+1 559 622 0939",
    "sg:postcode":"93291",
    "sg:province":"CA",
    "sg:tags":[
        "scooter"
    ],
    "wof:name":"Cyclecraft Engineering",
    "wof:placetype":"venue"
},
  "geometry": {"coordinates":[-119.36399400000001,36.339351],"type":"Point"}
}