{
  "type": "Feature",
  "properties": {
    "iso:country":"US",
    "sg:address":"1111 N Bristol St Ste K",
    "sg:city":"Santa Ana",
    "sg:classifiers":[
        {
            "category":"Health Services",
            "subcategory":"Doctor",
            "type":"Services"
        }
    ],
    "sg:phone":"+1 714 542 2133",
    "sg:postcode":"92703",
    "sg:province":"CA",
    "sg:tags":[
        "surgeon",
        "oral"
    ],
    "wof:name":"Manchandia C R DDS",
    "wof:placetype":"venue"
},
  "geometry": {"coordinates":[-117.885002,33.754299],"type":"Point"}
}