{
  "type": "Feature",
  "properties": {
    "addr:full":"6741 Dakota Ave Alta Loma CA 91701",
    "addr:housenumber":"6741",
    "addr:postcode":"91701",
    "addr:street":"Dakota Ave",
    "iso:country":"US",
    "sg:address":"6741 Dakota Ave",
    "sg:city":"Alta Loma",
    "sg:classifiers":[
        {
            "category":"Building & Trades",
            "subcategory":"Construction",
            "type":"Services"
        }
    ],
    "sg:phone":"+1 909 987 5325",
    "sg:postcode":"91701",
    "sg:province":"CA",
    "sg:tags":[
        "contractor"
    ],
    "wof:name":"R G Collins General Contr",
    "wof:placetype":"venue"
},
  "geometry": {"coordinates":[-117.575086,34.130922],"type":"Point"}
}