{
  "type": "Feature",
  "properties": {
    "addr:full":"1850 Douglas Blvd Roseville CA 95678",
    "addr:housenumber":"1850",
    "addr:postcode":"95678",
    "addr:street":"Douglas Blvd",
    "iso:country":"US",
    "sg:address":"1850 Douglas Blvd",
    "sg:city":"Roseville",
    "sg:classifiers":[
        {
            "category":"Shopping",
            "subcategory":"Computers & Home Electronics",
            "type":"Retail Goods"
        }
    ],
    "sg:phone":"+1 916 781 2577",
    "sg:postcode":"95678",
    "sg:province":"CA",
    "sg:tags":[
        "equipment",
        "dealer"
    ],
    "wof:name":"Ambassador Computers",
    "wof:placetype":"venue"
},
  "geometry": {"coordinates":[-121.257806,38.74414],"type":"Point"}
}