{
  "type": "Feature",
  "properties": {
    "addr:full":"8811 Garvey Ave Rosemead CA 91770",
    "addr:housenumber":"8811",
    "addr:postcode":"91770",
    "addr:street":"Garvey Ave",
    "iso:country":"US",
    "sg:address":"8811 Garvey Ave",
    "sg:city":"Rosemead",
    "sg:classifiers":[
        {
            "category":"Professional",
            "subcategory":"Printing & Photocopies",
            "type":"Services"
        }
    ],
    "sg:phone":"+1 626 571 4544",
    "sg:postcode":"91770",
    "sg:province":"CA",
    "sg:tags":[
        "duplicating",
        "copying"
    ],
    "wof:name":"Westside Copymaster",
    "wof:placetype":"venue"
},
  "geometry": {"coordinates":[-118.07596100000001,34.062751],"type":"Point"}
}