{
  "type": "Feature",
  "properties": {
    "iso:country":"US",
    "sg:address":"900 Golden Gate Terrace, Suite E",
    "sg:city":"Grass Valley",
    "sg:classifiers":[
        {
            "category":"Professional",
            "subcategory":"Research",
            "type":"Services"
        }
    ],
    "sg:phone":"+1 530 273 3096",
    "sg:postcode":"95945",
    "sg:province":"CA",
    "sg:tags":[
        "solar-power-harvesting",
        "photovoltaic",
        "power-optimizer",
        "solar-inverter",
        "pv-inverter",
        "pv-monitoring",
        "solar-monitoring-software",
        "pv-safety",
        "pv-systems",
        "microinverters"
    ],
    "sg:website":"http://www.solaredge.com/",
    "wof:name":"SolarEdge",
    "wof:placetype":"venue"
},
  "geometry": {"coordinates":[-121.09832900000001,39.211123],"type":"Point"}
}