{
  "type": "Feature",
  "properties": {
    "addr:full":"2306 Central Ave Alameda CA 94501",
    "addr:housenumber":"2306",
    "addr:postcode":"94501",
    "addr:street":"Central Ave",
    "iso:country":"US",
    "sg:address":"2306 Central Ave",
    "sg:city":"Alameda",
    "sg:classifiers":[
        {
            "category":"Travel",
            "subcategory":"Travel Agent",
            "type":"Entertainment"
        }
    ],
    "sg:phone":"+1 510 521 8511",
    "sg:postcode":"94501",
    "sg:province":"CA",
    "sg:tags":[
        "agency",
        "bureau"
    ],
    "wof:name":"Alameda Cruise & Tour Center",
    "wof:placetype":"venue"
},
  "geometry": {"coordinates":[-122.243022,37.764147],"type":"Point"}
}