{
  "type": "Feature",
  "properties": {
    "addr:full":"627 W 232nd St Carson CA 90745",
    "addr:housenumber":"627",
    "addr:postcode":"90745",
    "addr:street":"W 232Nd St",
    "iso:country":"US",
    "sg:address":"627 W 232nd St",
    "sg:city":"Carson",
    "sg:classifiers":[
        {
            "category":"Health Services",
            "subcategory":"Clinic",
            "type":"Services"
        }
    ],
    "sg:phone":"+1 310 835 8432",
    "sg:postcode":"90745",
    "sg:province":"CA",
    "sg:tags":[
        "home",
        "care"
    ],
    "wof:name":"Medings Homecare",
    "wof:placetype":"venue"
},
  "geometry": {"coordinates":[-118.286613,33.815559],"type":"Point"}
}