{
  "type": "Feature",
  "properties": {
    "addr:full":"702 S San Joaquin St Stockton CA 95203",
    "addr:housenumber":"702",
    "addr:postcode":"95203",
    "addr:street":"S San Joaquin St",
    "iso:country":"US",
    "sg:address":"702 S San Joaquin St",
    "sg:city":"Stockton",
    "sg:classifiers":[
        {
            "category":"Home & Garden",
            "subcategory":"Building Materials",
            "type":"Retail Goods"
        }
    ],
    "sg:phone":"+1 209 466 4761",
    "sg:postcode":"95203",
    "sg:province":"CA",
    "sg:tags":[
        "glass",
        "window",
        "plate"
    ],
    "sg:website":"www.valleyglasscompany.com",
    "wof:name":"Valley Glass Co",
    "wof:placetype":"venue"
},
  "geometry": {"coordinates":[-121.285079,37.94582],"type":"Point"}
}