{
  "type": "Feature",
  "properties": {
    "addr:full":"351 E Hedding St San Jose CA 95112",
    "addr:housenumber":"351",
    "addr:postcode":"95112",
    "addr:street":"E Hedding St",
    "iso:country":"US",
    "sg:address":"351 E Hedding St",
    "sg:city":"San Jose",
    "sg:classifiers":[
        {
            "category":"Restaurant",
            "type":"Food & Drink"
        }
    ],
    "sg:phone":"+1 408 298 2824",
    "sg:postcode":"95112",
    "sg:province":"CA",
    "sg:tags":[
        "caterer"
    ],
    "wof:name":"Ice Cream Catering By Uncle",
    "wof:placetype":"venue"
},
  "geometry": {"coordinates":[-121.89595199999999,37.35691],"type":"Point"}
}