{
  "type": "Feature",
  "properties": {
    "iso:country":"US",
    "sg:address":"446 S Marengo Ave",
    "sg:city":"Pasadena",
    "sg:classifiers":[
        {
            "category":"Health Services",
            "subcategory":"Health Practitioner",
            "type":"Services"
        }
    ],
    "sg:phone":"+1 626 792 9082",
    "sg:postcode":"91101",
    "sg:province":"CA",
    "sg:tags":[
        "psychotherapist"
    ],
    "wof:name":"Cherylynne Berger",
    "wof:placetype":"venue"
},
  "geometry": {"coordinates":[-118.145798,34.138038],"type":"Point"}
}