{
  "type": "Feature",
  "properties": {
    "iso:country":"US",
    "sg:address":"661 S Rancho Santa Fe Rd",
    "sg:city":"San Marcos",
    "sg:classifiers":[
        {
            "category":"Personal",
            "subcategory":"Beauty Salon",
            "type":"Services"
        }
    ],
    "sg:phone":"+1 760 744 4560",
    "sg:postcode":"92078",
    "sg:province":"CA",
    "wof:name":"Impressions Hair Styling",
    "wof:placetype":"venue"
},
  "geometry": {"coordinates":[-117.208045,33.131566],"type":"Point"}
}