{
  "type": "Feature",
  "properties": {
    "addr:full":"744 Market St San Diego CA 92101",
    "addr:housenumber":"744",
    "addr:postcode":"92101",
    "addr:street":"Market St",
    "iso:country":"US",
    "sg:address":"744 Market St",
    "sg:city":"San Diego",
    "sg:classifiers":[
        {
            "category":"Restaurant",
            "type":"Food & Drink"
        }
    ],
    "sg:phone":"+1 619 531 1199",
    "sg:postcode":"92101",
    "sg:province":"CA",
    "sg:tags":[
        "pizza"
    ],
    "wof:name":"Padre's Ballpark Pizzaria",
    "wof:placetype":"venue"
},
  "geometry": {"coordinates":[-117.157905,32.711514],"type":"Point"}
}