{
  "type": "Feature",
  "properties": {
    "iso:country":"US",
    "sg:address":"6517 Commerce Way",
    "sg:city":"Diamond Springs",
    "sg:classifiers":[
        {
            "category":"Building & Trades",
            "subcategory":"Construction",
            "type":"Services"
        }
    ],
    "sg:phone":"+1 530 626 7068",
    "sg:postcode":"95619",
    "sg:province":"CA",
    "sg:tags":[
        "maker",
        "cabinet"
    ],
    "wof:name":"Rich's & Mike's Cabinets",
    "wof:placetype":"venue"
},
  "geometry": {"coordinates":[-120.830039,38.693907],"type":"Point"}
}