{
  "type": "Feature",
  "properties": {
    "addr:full":"1128 Cypress St Santa Maria CA 93458",
    "addr:housenumber":"1128",
    "addr:postcode":"93458",
    "addr:street":"Cypress St",
    "iso:country":"US",
    "sg:address":"1128 Cypress St",
    "sg:city":"Santa Maria",
    "sg:classifiers":[
        {
            "category":"Organizations",
            "subcategory":"Religious Organization",
            "type":"Services"
        }
    ],
    "sg:phone":"+1 805 922 1590",
    "sg:postcode":"93458",
    "sg:province":"CA",
    "sg:tags":[
        "church"
    ],
    "wof:name":"St Paul Baptist Church",
    "wof:placetype":"venue"
},
  "geometry": {"coordinates":[-120.45205799999999,34.950749],"type":"Point"}
}