{
  "type": "Feature",
  "properties": {
    "iso:country":"US",
    "sg:address":"127 8th Ave",
    "sg:city":"La Puente",
    "sg:classifiers":[
        {
            "category":"Manufacturing",
            "subcategory":"Printing",
            "type":"Manufacturing & Wholesale Goods"
        }
    ],
    "sg:phone":"+1 626 961 6986",
    "sg:postcode":"91746",
    "sg:province":"CA",
    "sg:tags":[
        "printer"
    ],
    "wof:name":"J K Printing Co",
    "wof:placetype":"venue"
},
  "geometry": {"coordinates":[-117.974047,34.029777],"type":"Point"}
}