{
  "type": "Feature",
  "properties": {
    "iso:country":"US",
    "sg:address":"118 Natoma St",
    "sg:city":"Folsom",
    "sg:classifiers":[
        {
            "category":"Health Services",
            "subcategory":"Doctor",
            "type":"Services"
        }
    ],
    "sg:phone":"+1 916 985 3571",
    "sg:postcode":"95630",
    "sg:province":"CA",
    "sg:tags":[
        "dentist"
    ],
    "wof:name":"John B Croft Inc",
    "wof:placetype":"venue"
},
  "geometry": {"coordinates":[-121.167502,38.679266],"type":"Point"}
}