{
  "type": "Feature",
  "properties": {
    "addr:full":"10064 Mesa Ridge Ct San Diego CA 92121",
    "addr:housenumber":"10064",
    "addr:postcode":"92121",
    "addr:street":"Mesa Ridge Ct",
    "iso:country":"US",
    "sg:address":"10064 Mesa Ridge Ct",
    "sg:city":"San Diego",
    "sg:classifiers":[
        {
            "category":"Manufacturing",
            "subcategory":"Tools & Machinery",
            "type":"Manufacturing & Wholesale Goods"
        }
    ],
    "sg:phone":"+1 858 535 0012",
    "sg:postcode":"92121",
    "sg:province":"CA",
    "sg:tags":[
        "physician",
        "surgeon"
    ],
    "sg:website":"www.apexmedtech.com",
    "wof:name":"Apex Medical Technologies Inc",
    "wof:placetype":"venue"
},
  "geometry": {"coordinates":[-117.175307,32.901479],"type":"Point"}
}