{
  "type": "Feature",
  "properties": {
    "addr:full":"5312 Whittier Blvd Los Angeles CA 90022",
    "addr:housenumber":"5312",
    "addr:postcode":"90022",
    "addr:street":"Whittier Blvd",
    "iso:country":"US",
    "sg:address":"5312 Whittier Blvd",
    "sg:city":"Los Angeles",
    "sg:classifiers":[
        {
            "category":"Shopping",
            "subcategory":"Clothing, Apparel, & Fashions",
            "type":"Retail Goods"
        }
    ],
    "sg:phone":"+1 323 261 0771",
    "sg:postcode":"90022",
    "sg:province":"CA",
    "sg:tags":[
        "shop",
        "bridal"
    ],
    "wof:name":"Susy's Bridal",
    "wof:placetype":"venue"
},
  "geometry": {"coordinates":[-118.155716,34.020002],"type":"Point"}
}