{
  "type": "Feature",
  "properties": {
    "iso:country":"US",
    "sg:address":"250 Napoleon St",
    "sg:city":"San Francisco",
    "sg:classifiers":[
        {
            "category":"Wholesale",
            "subcategory":"Seafood",
            "type":"Manufacturing & Wholesale Goods"
        }
    ],
    "sg:phone":"+1 415 821 4701",
    "sg:postcode":"94124",
    "sg:province":"CA",
    "wof:name":"Scandinavian Smokehouse",
    "wof:placetype":"venue"
},
  "geometry": {"coordinates":[-122.397802,37.747188],"type":"Point"}
}