{
  "type": "Feature",
  "properties": {
    "iso:country":"US",
    "sg:address":"3901 Pacific Coast Hwy",
    "sg:city":"Torrance",
    "sg:classifiers":[
        {
            "category":"Building & Trades",
            "subcategory":"Locksmith",
            "type":"Services"
        }
    ],
    "sg:phone":"+1 424 201 0018",
    "sg:postcode":"90505",
    "sg:province":"CA",
    "sg:tags":[
        "key"
    ],
    "wof:name":"Always Affective Available Emergency",
    "wof:placetype":"venue"
},
  "geometry": {"coordinates":[-118.35437899999999,33.806527],"type":"Point"}
}