{
  "type": "Feature",
  "properties": {
    "iso:country":"US",
    "sg:address":"1331 N Pennsylvania Ave",
    "sg:city":"Colton",
    "sg:classifiers":[
        {
            "category":"Professional",
            "type":"Services"
        }
    ],
    "sg:phone":"+1 909 824 6618",
    "sg:postcode":"92324",
    "sg:province":"CA",
    "wof:name":"Mex-Xi-An International",
    "wof:placetype":"venue"
},
  "geometry": {"coordinates":[-117.327197,34.082896],"type":"Point"}
}