{
  "type": "Feature",
  "properties": {
    "addr:full":"5455 E Home Ave Fresno CA 93727",
    "addr:housenumber":"5455",
    "addr:postcode":"93727",
    "addr:street":"E Home Ave",
    "iso:country":"US",
    "sg:address":"5455 E Home Ave",
    "sg:city":"Fresno",
    "sg:classifiers":[
        {
            "category":"Wholesale",
            "subcategory":"Metals & Minerals",
            "type":"Manufacturing & Wholesale Goods"
        }
    ],
    "sg:phone":"+1 800 337 3766",
    "sg:postcode":"93727",
    "sg:province":"CA",
    "sg:tags":[
        "center"
    ],
    "wof:name":"Aerodyne",
    "wof:placetype":"venue"
},
  "geometry": {"coordinates":[-119.706452,36.763196],"type":"Point"}
}