{
  "type": "Feature",
  "properties": {
    "iso:country":"US",
    "sg:address":"6040 Magnolia Ave",
    "sg:city":"Riverside",
    "sg:classifiers":[
        {
            "category":"Retail",
            "subcategory":"Portrait Studio",
            "type":"Services"
        }
    ],
    "sg:phone":"+1 951 787 6228",
    "sg:postcode":"92506",
    "sg:province":"CA",
    "sg:tags":[
        "photographer"
    ],
    "wof:name":"Foto Y Video Rivas",
    "wof:placetype":"venue"
},
  "geometry": {"coordinates":[-117.392566,33.95959],"type":"Point"}
}