{
  "type": "Feature",
  "properties": {
    "iso:country":"US",
    "sg:address":"110 E Montecito St",
    "sg:city":"Santa Barbara",
    "sg:classifiers":[
        {
            "category":"Building & Trades",
            "subcategory":"Construction",
            "type":"Services"
        }
    ],
    "sg:phone":"+1 805 882 2256",
    "sg:postcode":"93101",
    "sg:province":"CA",
    "sg:tags":[
        "heavy",
        "merchandise"
    ],
    "wof:name":"Santa Barbara Koi",
    "wof:placetype":"venue"
},
  "geometry": {"coordinates":[-119.691379,34.416152],"type":"Point"}
}