{
  "type": "Feature",
  "properties": {
    "iso:country":"US",
    "sg:address":"2148 W Pomona Blvd",
    "sg:city":"Pomona",
    "sg:classifiers":[
        {
            "category":"Manufacturing",
            "subcategory":"Food",
            "type":"Manufacturing & Wholesale Goods"
        }
    ],
    "sg:phone":"+1 909 629 6565",
    "sg:postcode":"91768",
    "sg:province":"CA",
    "sg:tags":[
        "product",
        "manufacturer"
    ],
    "wof:name":"American Color Research Ctr",
    "wof:placetype":"venue"
},
  "geometry": {"coordinates":[-117.78627299999999,34.057875],"type":"Point"}
}