{
  "type": "Feature",
  "properties": {
    "addr:full":"5356 Jillson St City Of Commerce CA 90040",
    "addr:housenumber":"5356",
    "addr:postcode":"90040",
    "addr:street":"Jillson St",
    "iso:country":"US",
    "sg:address":"5356 Jillson St",
    "sg:city":"City Of Commerce",
    "sg:classifiers":[
        {
            "category":"Wholesale",
            "subcategory":"Stationery",
            "type":"Manufacturing & Wholesale Goods"
        }
    ],
    "sg:phone":"+1 323 780 5900",
    "sg:postcode":"90040",
    "sg:province":"CA",
    "sg:tags":[
        "business",
        "form",
        "system"
    ],
    "wof:name":"Autographic Business Forms",
    "wof:placetype":"venue"
},
  "geometry": {"coordinates":[-118.163667,34.002576],"type":"Point"}
}