{
  "type": "Feature",
  "properties": {
    "iso:country":"US",
    "sg:address":"6365 Freeport Blvd",
    "sg:city":"Sacramento",
    "sg:classifiers":[
        {
            "category":"Wholesale",
            "subcategory":"Machinery & Supplies",
            "type":"Manufacturing & Wholesale Goods"
        }
    ],
    "sg:phone":"+1 916 428 3392",
    "sg:postcode":"95822",
    "sg:province":"CA",
    "sg:tags":[
        "aircraft",
        "avionics"
    ],
    "wof:name":"Airborne Electronics",
    "wof:placetype":"venue"
},
  "geometry": {"coordinates":[-121.502298,38.510715],"type":"Point"}
}