{
  "type": "Feature",
  "properties": {
    "iso:country":"US",
    "sg:address":"30800 Palo Alto Dr",
    "sg:city":"Redlands",
    "sg:classifiers":[
        {
            "category":"Education",
            "subcategory":"School",
            "type":"Public Place"
        }
    ],
    "sg:phone":"+1 909 794 5560",
    "sg:postcode":"92373",
    "sg:province":"CA",
    "wof:name":"Redlands Unified School District",
    "wof:placetype":"venue"
},
  "geometry": {"coordinates":[-117.132385,34.022145],"type":"Point"}
}