{
  "type": "Feature",
  "properties": {
    "addr:full":"6247 Solomon Ct San Jose CA 95123",
    "addr:housenumber":"6247",
    "addr:postcode":"95123",
    "addr:street":"Solomon Ct",
    "iso:country":"US",
    "sg:address":"6247 Solomon Ct",
    "sg:city":"San Jose",
    "sg:classifiers":[
        {
            "category":"Banks & Credit Unions",
            "subcategory":"Investment Brokerage",
            "type":"Services"
        }
    ],
    "sg:phone":"+1 408 978 1000",
    "sg:postcode":"95123",
    "sg:province":"CA",
    "sg:tags":[
        "consultant",
        "planning",
        "financial"
    ],
    "wof:name":"IRA Ctr",
    "wof:placetype":"venue"
},
  "geometry": {"coordinates":[-121.806837,37.232414],"type":"Point"}
}