{
  "type": "Feature",
  "properties": {
    "addr:full":"4740 E Kings Canyon Rd Fresno CA 93702",
    "addr:housenumber":"4740",
    "addr:postcode":"93702",
    "addr:street":"E Kings Canyon Rd",
    "iso:country":"US",
    "sg:address":"4740 E Kings Canyon Rd",
    "sg:city":"Fresno",
    "sg:classifiers":[
        {
            "category":"Autos & Motor Vehicles",
            "subcategory":"Auto Supplies",
            "type":"Retail Goods"
        }
    ],
    "sg:phone":"+1 559 255 0800",
    "sg:postcode":"93702",
    "sg:province":"CA",
    "sg:tags":[
        "battery",
        "batteries-storage"
    ],
    "wof:name":"Jorgensen's Batteries Inc.",
    "wof:placetype":"venue"
},
  "geometry": {"coordinates":[-119.73914499999999,36.735857],"type":"Point"}
}