{
  "type": "Feature",
  "properties": {
    "addr:full":"1655 9th St Santa Monica CA 90404",
    "addr:housenumber":"1655",
    "addr:postcode":"90404",
    "addr:street":"9Th St",
    "iso:country":"US",
    "sg:address":"1655 9th St",
    "sg:city":"Santa Monica",
    "sg:classifiers":[
        {
            "category":"Professional",
            "subcategory":"Business Services",
            "type":"Services"
        }
    ],
    "sg:phone":"+1 310 581 3400",
    "sg:postcode":"90404",
    "sg:province":"CA",
    "sg:tags":[
        "recording",
        "studio"
    ],
    "wof:name":"Klown Records",
    "wof:placetype":"venue"
},
  "geometry": {"coordinates":[-118.48584099999999,34.016439],"type":"Point"}
}