{
  "type": "Feature",
  "properties": {
    "iso:country":"US",
    "sg:address":"570 Lighthouse Ave",
    "sg:city":"Monterey",
    "sg:classifiers":[
        {
            "category":"Restaurant",
            "type":"Food & Drink"
        }
    ],
    "sg:phone":"+1 831 656 0672",
    "sg:postcode":"93940",
    "sg:province":"CA",
    "wof:name":"Won Ju Korean Restaurant",
    "wof:placetype":"venue"
},
  "geometry": {"coordinates":[-121.90114199999999,36.612871],"type":"Point"}
}