{
  "type": "Feature",
  "properties": {
    "addr:full":"71 S Shepherd St Sonora CA 95370",
    "addr:housenumber":"71",
    "addr:postcode":"95370",
    "addr:street":"S Shepherd St",
    "iso:country":"US",
    "sg:address":"71 S Shepherd St",
    "sg:city":"Sonora",
    "sg:classifiers":[
        {
            "category":"Professional",
            "subcategory":"Business Services",
            "type":"Services"
        }
    ],
    "sg:phone":"+1 209 532 3183",
    "sg:postcode":"95370",
    "sg:province":"CA",
    "sg:tags":[
        "paging",
        "answering"
    ],
    "sg:website":"www.motherlodeansweringservice.com",
    "wof:name":"Mother Lode Answering Svc",
    "wof:placetype":"venue"
},
  "geometry": {"coordinates":[-120.381598,37.985111],"type":"Point"}
}