{
  "type": "Feature",
  "properties": {
    "iso:country":"US",
    "sg:address":"1301 S 46th St",
    "sg:city":"Richmond",
    "sg:classifiers":[
        {
            "category":"Government",
            "subcategory":"Police Station",
            "type":"Public Place"
        }
    ],
    "sg:phone":"+1 510 231 9441",
    "sg:postcode":"94804",
    "sg:province":"CA",
    "sg:tags":[
        "protection"
    ],
    "wof:name":"U C Police",
    "wof:placetype":"venue"
},
  "geometry": {"coordinates":[-122.331833,37.915364],"type":"Point"}
}