{
  "type": "Feature",
  "properties": {
    "iso:country":"US",
    "sg:address":"548 Diamond Pl",
    "sg:city":"Walnut",
    "sg:classifiers":[
        {
            "category":"Wholesale",
            "subcategory":"Home Furnishings",
            "type":"Manufacturing & Wholesale Goods"
        }
    ],
    "sg:phone":"+1 626 964 1702",
    "sg:postcode":"91789",
    "sg:province":"CA",
    "wof:name":"Srithai Corporation",
    "wof:placetype":"venue"
},
  "geometry": {"coordinates":[-117.884733,34.020405],"type":"Point"}
}