{
  "type": "Feature",
  "properties": {
    "addr:full":"2351 Stanley Ave Signal Hill CA 90755",
    "addr:housenumber":"2351",
    "addr:postcode":"90755",
    "addr:street":"Stanley Ave",
    "iso:country":"US",
    "sg:address":"2351 Stanley Ave",
    "sg:city":"Signal Hill",
    "sg:classifiers":[
        {
            "category":"Professional",
            "subcategory":"Computer Services",
            "type":"Services"
        }
    ],
    "sg:phone":"+1 562 276 3375",
    "sg:postcode":"90755",
    "sg:province":"CA",
    "sg:tags":[
        "repair"
    ],
    "sg:website":"www.chandlercom.com",
    "wof:name":"Chandler Communications",
    "wof:placetype":"venue"
},
  "geometry": {"coordinates":[-118.16258000000001,33.799957],"type":"Point"}
}