{
  "type": "Feature",
  "properties": {
    "addr:full":"14018 Carmenita Rd Santa Fe Springs CA 90670",
    "addr:housenumber":"14018",
    "addr:postcode":"90670",
    "addr:street":"Carmenita Rd",
    "iso:country":"US",
    "sg:address":"14018 Carmenita Rd",
    "sg:city":"Santa Fe Springs",
    "sg:classifiers":[
        {
            "category":"Freight",
            "type":"Transportation"
        },
        {
            "category":"Building & Trades",
            "subcategory":"Construction",
            "type":"Services"
        }
    ],
    "sg:phone":"+1 562 864 2953",
    "sg:postcode":"90670",
    "sg:province":"CA",
    "sg:tags":[
        "pumping",
        "contractor"
    ],
    "wof:name":"Robert's Liquid Disposal",
    "wof:placetype":"venue"
},
  "geometry": {"coordinates":[-118.04662999999999,33.903025],"type":"Point"}
}