{
  "type": "Feature",
  "properties": {
    "addr:full":"675 Tampico Walnut Creek CA 94598",
    "addr:housenumber":"675",
    "addr:postcode":"94598",
    "addr:street":"Tampico",
    "iso:country":"US",
    "sg:address":"675 Tampico",
    "sg:city":"Walnut Creek",
    "sg:classifiers":[
        {
            "category":"Professional",
            "subcategory":"Accounting & Tax Preparation",
            "type":"Services"
        }
    ],
    "sg:phone":"+1 925 944 1992",
    "sg:postcode":"94598",
    "sg:province":"CA",
    "sg:tags":[
        "return",
        "filing"
    ],
    "wof:name":"Pak Financial Management",
    "wof:placetype":"venue"
},
  "geometry": {"coordinates":[-122.043385,37.910062],"type":"Point"}
}