{
  "type": "Feature",
  "properties": {
    "iso:country":"US",
    "sg:address":"2707 del Paso Blvd",
    "sg:city":"Sacramento",
    "sg:classifiers":[
        {
            "category":"Building & Trades",
            "subcategory":"Construction",
            "type":"Services"
        }
    ],
    "sg:phone":"+1 916 925 8559",
    "sg:postcode":"95815",
    "sg:province":"CA",
    "sg:tags":[
        "house"
    ],
    "wof:name":"Famous Builders Inc",
    "wof:placetype":"venue"
},
  "geometry": {"coordinates":[-121.44056,38.617398],"type":"Point"}
}