{
  "type": "Feature",
  "properties": {
    "addr:full":"609 Theresa Dr S San Francisco CA 94080",
    "addr:housenumber":"609",
    "addr:postcode":"94080",
    "addr:street":"Theresa Dr S",
    "iso:country":"US",
    "sg:address":"609 Theresa Dr",
    "sg:city":"S San Francisco",
    "sg:classifiers":[
        {
            "category":"Shopping",
            "subcategory":"Bicycles & Sporting Goods",
            "type":"Retail Goods"
        }
    ],
    "sg:phone":"+1 650 588 0245",
    "sg:postcode":"94080",
    "sg:province":"CA",
    "wof:name":"Armanino Gun Shop",
    "wof:placetype":"venue"
},
  "geometry": {"coordinates":[-122.450582,37.658536],"type":"Point"}
}