{
  "type": "Feature",
  "properties": {
    "addr:full":"1323 E 4th St Ontario CA 91764",
    "addr:housenumber":"1323",
    "addr:postcode":"91764",
    "addr:street":"E 4Th St",
    "iso:country":"US",
    "sg:address":"1323 E 4th St",
    "sg:city":"Ontario",
    "sg:classifiers":[
        {
            "category":"Building & Trades",
            "subcategory":"Equipment Rental",
            "type":"Services"
        }
    ],
    "sg:phone":"+1 909 983 4770",
    "sg:postcode":"91764",
    "sg:province":"CA",
    "sg:tags":[
        "yard"
    ],
    "wof:name":"Rent-A-Center",
    "wof:placetype":"venue"
},
  "geometry": {"coordinates":[-117.627994,34.077743],"type":"Point"}
}