{
  "type": "Feature",
  "properties": {
    "iso:country":"US",
    "sg:address":"2713 W Lincoln Ave",
    "sg:city":"Anaheim",
    "sg:classifiers":[
        {
            "category":"Insurance",
            "subcategory":"Health Insurance",
            "type":"Services"
        }
    ],
    "sg:phone":"+1 714 821 6811",
    "sg:postcode":"92801",
    "sg:province":"CA",
    "sg:tags":[
        "market"
    ],
    "wof:name":"All Nature's Own Nutrition",
    "wof:placetype":"venue"
},
  "geometry": {"coordinates":[-117.980003,33.8321],"type":"Point"}
}