{
  "type": "Feature",
  "properties": {
    "addr:full":"17532 Metzler Lane Huntington Beach CA 92647",
    "addr:postcode":"17532;92647",
    "addr:street":"Metzler Lane",
    "iso:country":"US",
    "sg:address":"17532 Metzler Lane",
    "sg:city":"Huntington Beach",
    "sg:classifiers":[
        {
            "category":"Retail",
            "subcategory":"Auto Repair",
            "type":"Services"
        }
    ],
    "sg:phone":"+1 714 842 5574",
    "sg:postcode":"92647",
    "sg:province":"CA",
    "wof:name":"Midway Auto Service",
    "wof:placetype":"venue"
},
  "geometry": {"coordinates":[-117.998529,33.707957],"type":"Point"}
}