{
  "type": "Feature",
  "properties": {
    "addr:full":"756 Trestle Glen Rd Oakland CA 94610",
    "addr:housenumber":"756",
    "addr:postcode":"94610",
    "addr:street":"Trestle Glen Rd",
    "iso:country":"US",
    "sg:address":"756 Trestle Glen Rd",
    "sg:city":"Oakland",
    "sg:classifiers":[
        {
            "category":"Insurance",
            "subcategory":"Insurance Agent",
            "type":"Services"
        }
    ],
    "sg:phone":"+1 510 451 0912",
    "sg:postcode":"94610",
    "sg:province":"CA",
    "wof:name":"Leonie Calvert Insurance Svc",
    "wof:placetype":"venue"
},
  "geometry": {"coordinates":[-122.237205,37.80717],"type":"Point"}
}