{
  "type": "Feature",
  "properties": {
    "iso:country":"US",
    "sg:address":"45 San Clemente Dr",
    "sg:city":"Corte Madera",
    "sg:classifiers":[
        {
            "category":"Health Services",
            "subcategory":"Health Practitioner",
            "type":"Services"
        }
    ],
    "sg:phone":"+1 415 847 9990",
    "sg:postcode":"94925",
    "sg:province":"CA",
    "sg:tags":[
        "acupuncture"
    ],
    "wof:name":"Kathleen Cutter Hiatt LAC",
    "wof:placetype":"venue"
},
  "geometry": {"coordinates":[-122.510968,37.924464],"type":"Point"}
}