{
  "type": "Feature",
  "properties": {
    "iso:country":"US",
    "sg:address":"757 W Garvey Ave",
    "sg:city":"Monterey Park",
    "sg:classifiers":[
        {
            "category":"Banks & Credit Unions",
            "subcategory":"Bank",
            "type":"Services"
        }
    ],
    "sg:phone":"+1 626 293 8500",
    "sg:postcode":"91754",
    "sg:province":"CA",
    "wof:name":"Universal Bank",
    "wof:placetype":"venue"
},
  "geometry": {"coordinates":[-118.13400300000001,34.062401],"type":"Point"}
}