{
  "type": "Feature",
  "properties": {
    "addr:full":"1550 Flower St Glendale CA 91201",
    "addr:housenumber":"1550",
    "addr:postcode":"91201",
    "addr:street":"Flower St",
    "iso:country":"US",
    "sg:address":"1550 Flower St",
    "sg:city":"Glendale",
    "sg:classifiers":[
        {
            "category":"Organizations",
            "subcategory":"Religious Organization",
            "type":"Services"
        }
    ],
    "sg:phone":"+1 818 291 9349",
    "sg:postcode":"91201",
    "sg:province":"CA",
    "wof:name":"Universal Church The",
    "wof:placetype":"venue"
},
  "geometry": {"coordinates":[-118.293154,34.164022],"type":"Point"}
}