{
  "type": "Feature",
  "properties": {
    "addr:full":"211 W Whittier Blvd Montebello CA 90640",
    "addr:housenumber":"211",
    "addr:postcode":"90640",
    "addr:street":"W Whittier Blvd",
    "iso:country":"US",
    "sg:address":"211 W Whittier Blvd",
    "sg:city":"Montebello",
    "sg:classifiers":[
        {
            "category":"Travel",
            "subcategory":"Hotels & Motels",
            "type":"Entertainment"
        }
    ],
    "sg:phone":"+1 323 721 5518",
    "sg:postcode":"90640",
    "sg:province":"CA",
    "wof:name":"Californian Motel the",
    "wof:placetype":"venue"
},
  "geometry": {"coordinates":[-118.101997,34.008701],"type":"Point"}
}