{
  "type": "Feature",
  "properties": {
    "iso:country":"US",
    "sg:address":"140 S 14th St",
    "sg:city":"San Jose",
    "sg:classifiers":[
        {
            "category":"Professional",
            "subcategory":"Business Services",
            "type":"Services"
        }
    ],
    "sg:phone":"+1 408 885 0556",
    "sg:postcode":"95112",
    "sg:province":"CA",
    "sg:tags":[
        "interior",
        "consultant",
        "design",
        "decorator"
    ],
    "wof:name":"Jeck Interiors",
    "wof:placetype":"venue"
},
  "geometry": {"coordinates":[-121.875051,37.339903],"type":"Point"}
}