{
  "type": "Feature",
  "properties": {
    "addr:full":"2800 Jefferson St Napa CA 94558",
    "addr:housenumber":"2800",
    "addr:postcode":"94558",
    "addr:street":"Jefferson St",
    "iso:country":"US",
    "sg:address":"2800 Jefferson St",
    "sg:city":"Napa",
    "sg:classifiers":[
        {
            "category":"Utilities",
            "type":"Services"
        }
    ],
    "sg:phone":"+1 707 255 1769",
    "sg:postcode":"94558",
    "sg:province":"CA",
    "sg:tags":[
        "sweeping"
    ],
    "sg:website":"www.commercialpowersweep.net",
    "wof:name":"Commercial Power Sweep",
    "wof:placetype":"venue"
},
  "geometry": {"coordinates":[-122.297809,38.315636],"type":"Point"}
}