{
  "type": "Feature",
  "properties": {
    "addr:full":"7601 Telegraph Road Montebello CA 90640",
    "addr:housenumber":"7601",
    "addr:postcode":"90640",
    "addr:street":"Telegraph Road",
    "iso:country":"US",
    "sg:address":"7601 Telegraph Road",
    "sg:city":"Montebello",
    "sg:classifiers":[
        {
            "category":"Home & Garden",
            "subcategory":"Building Materials",
            "type":"Retail Goods"
        }
    ],
    "sg:phone":"+1 323 727 2731",
    "sg:postcode":"90640",
    "sg:province":"CA",
    "sg:tags":[
        "supply"
    ],
    "sg:website":"www.hdsupplyrepairandremodel.com",
    "wof:name":"HD Supply Repair & Remodel",
    "wof:placetype":"venue"
},
  "geometry": {"coordinates":[-118.125934,33.978391],"type":"Point"}
}