{
  "type": "Feature",
  "properties": {
    "iso:country":"US",
    "sg:address":"1115 Lake St",
    "sg:city":"Venice",
    "sg:classifiers":[
        {
            "category":"Shopping",
            "subcategory":"Clothing, Apparel, & Fashions",
            "type":"Retail Goods"
        }
    ],
    "sg:phone":"+1 310 399 6551",
    "sg:postcode":"90291",
    "sg:province":"CA",
    "sg:tags":[
        "garment"
    ],
    "wof:name":"Break Up Line",
    "wof:placetype":"venue"
},
  "geometry": {"coordinates":[-118.458917,34.004423],"type":"Point"}
}