{
  "type": "Feature",
  "properties": {
    "addr:full":"23084 Broadmoor Ct Auburn CA 95602",
    "addr:housenumber":"23084",
    "addr:postcode":"ca 95602",
    "addr:street":"Broadmoor Ct",
    "iso:country":"US",
    "sg:address":"23084 Broadmoor Ct",
    "sg:city":"Auburn",
    "sg:classifiers":[
        {
            "category":"Utilities",
            "subcategory":"Recycling",
            "type":"Services"
        }
    ],
    "sg:phone":"+1 530 268 9104",
    "sg:postcode":"95602",
    "sg:province":"CA",
    "sg:tags":[
        "disposal",
        "waste",
        "equipment"
    ],
    "wof:name":"Alley Kat Hauling",
    "wof:placetype":"venue"
},
  "geometry": {"coordinates":[-121.06013400000001,39.046117],"type":"Point"}
}