{
  "type": "Feature",
  "properties": {
    "addr:full":"Long Beach Convention Center Long Beach CA 90899",
    "addr:postcode":"90899",
    "iso:country":"US",
    "sg:address":"Long Beach Convention Center",
    "sg:city":"Long Beach",
    "sg:classifiers":[
        {
            "category":"Personal",
            "subcategory":"Beauty Salon",
            "type":"Services"
        }
    ],
    "sg:postcode":"90899",
    "sg:province":"CA",
    "sg:tags":[
        "spa"
    ],
    "sg:website":"www.probeauty.org/isse",
    "wof:name":"International Salon & Spa Expo",
    "wof:placetype":"venue"
},
  "geometry": {"coordinates":[-118.190465,33.76465],"type":"Point"}
}