{
  "type": "Feature",
  "properties": {
    "addr:full":"1733 Crestmont Dr Bakersfield CA 93306",
    "addr:housenumber":"1733",
    "addr:postcode":"93306",
    "addr:street":"Crestmont Dr",
    "iso:country":"US",
    "sg:address":"1733 Crestmont Dr",
    "sg:city":"Bakersfield",
    "sg:classifiers":[
        {
            "category":"Building & Trades",
            "subcategory":"Construction",
            "type":"Services"
        }
    ],
    "sg:phone":"+1 661 331 6854",
    "sg:postcode":"93306",
    "sg:province":"CA",
    "sg:tags":[
        "handyman"
    ],
    "wof:name":"Simpson Handyman Svc",
    "wof:placetype":"venue"
},
  "geometry": {"coordinates":[-118.95264299999999,35.381129],"type":"Point"}
}