{
  "type": "Feature",
  "properties": {
    "iso:country":"US",
    "sg:address":"123 S Pastoria Ave",
    "sg:city":"Sunnyvale",
    "sg:classifiers":[
        {
            "category":"Personal",
            "type":"Services"
        }
    ],
    "sg:phone":"+1 650 814 2889",
    "sg:postcode":"94086",
    "sg:province":"CA",
    "sg:tags":[
        "local"
    ],
    "wof:name":"Goin' Green",
    "wof:placetype":"venue"
},
  "geometry": {"coordinates":[-122.037798,37.379903],"type":"Point"}
}