{
  "type": "Feature",
  "properties": {
    "iso:country":"US",
    "sg:address":"457 Cinderella Ln",
    "sg:city":"Santa Barbara",
    "sg:classifiers":[
        {
            "category":"Professional",
            "subcategory":"Management & Consulting",
            "type":"Services"
        }
    ],
    "sg:phone":"+1 805 964 4007",
    "sg:postcode":"93111",
    "sg:province":"CA",
    "sg:tags":[
        "consultant",
        "business"
    ],
    "wof:name":"United Communication Co",
    "wof:placetype":"venue"
},
  "geometry": {"coordinates":[-119.803768,34.43191],"type":"Point"}
}