{
  "type": "Feature",
  "properties": {
    "iso:country":"US",
    "sg:address":"234 Euclid Ave",
    "sg:city":"San Bruno",
    "sg:phone":"+1 650 583 9521",
    "sg:postcode":"94066",
    "sg:province":"CA",
    "sg:tags":[
        "equipment",
        "commercial"
    ],
    "wof:name":"Kurt W Bullard & Associates",
    "wof:placetype":"venue"
},
  "geometry": {"coordinates":[-122.41445400000001,37.632012],"type":"Point"}
}