{
  "type": "Feature",
  "properties": {
    "addr:full":"1960 5th Ave San Rafael CA 94901",
    "addr:housenumber":"1960",
    "addr:postcode":"94901",
    "addr:street":"5Th Ave",
    "iso:country":"US",
    "sg:address":"1960 5th Ave",
    "sg:city":"San Rafael",
    "sg:classifiers":[
        {
            "category":"Education",
            "subcategory":"Special Training",
            "type":"Public Place"
        }
    ],
    "sg:phone":"+1 415 454 9072",
    "sg:postcode":"94901",
    "sg:province":"CA",
    "sg:tags":[
        "school",
        "language"
    ],
    "wof:name":"Language Study Abroad",
    "wof:placetype":"venue"
},
  "geometry": {"coordinates":[-122.54196399999999,37.978476],"type":"Point"}
}