{
  "type": "Feature",
  "properties": {
    "addr:full":"13 Spinnaker Irvine CA 92614",
    "addr:housenumber":"13",
    "addr:postcode":"92614",
    "addr:street":"Spinnaker",
    "iso:country":"US",
    "sg:address":"13 Spinnaker",
    "sg:city":"Irvine",
    "sg:classifiers":[
        {
            "category":"Professional",
            "type":"Services"
        }
    ],
    "sg:phone":"+1 949 552 4527",
    "sg:postcode":"92614",
    "sg:province":"CA",
    "wof:name":"Ama Services",
    "wof:placetype":"venue"
},
  "geometry": {"coordinates":[-117.80652600000001,33.672031],"type":"Point"}
}