{
  "type": "Feature",
  "properties": {
    "iso:country":"US",
    "sg:address":"119 S Main St",
    "sg:city":"Alturas",
    "sg:classifiers":[
        {
            "category":"Shopping",
            "subcategory":"Hobbies, Toys, & Games",
            "type":"Retail Goods"
        }
    ],
    "sg:phone":"+1 530 233 2845",
    "sg:postcode":"96101",
    "sg:province":"CA",
    "sg:tags":[
        "craft",
        "supply"
    ],
    "wof:name":"Old Tyme Treasures & What Not",
    "wof:placetype":"venue"
},
  "geometry": {"coordinates":[-120.542513,41.483957],"type":"Point"}
}