{
  "type": "Feature",
  "properties": {
    "addr:full":"17071 Ventura Blvd # 211 Encino CA 91316",
    "addr:housenumber":"17071",
    "addr:postcode":"91316",
    "addr:street":"Ventura Blvd # 211",
    "iso:country":"US",
    "sg:address":"17071 Ventura Blvd # 211",
    "sg:city":"Encino",
    "sg:classifiers":[
        {
            "category":"Professional",
            "subcategory":"Employment Agencies",
            "type":"Services"
        }
    ],
    "sg:phone":"+1 818 788 1307",
    "sg:postcode":"91316",
    "sg:province":"CA",
    "sg:tags":[
        "opportunity"
    ],
    "wof:name":"Domestic Alliance Agency",
    "wof:placetype":"venue"
},
  "geometry": {"coordinates":[-118.504864,34.160098],"type":"Point"}
}