{
  "type": "Feature",
  "properties": {
    "iso:country":"US",
    "sg:address":"20222 Orchid St",
    "sg:city":"Newport Beach",
    "sg:classifiers":[
        {
            "category":"Home & Garden",
            "subcategory":"Garden Supply",
            "type":"Retail Goods"
        }
    ],
    "sg:phone":"+1 949 757 0298",
    "sg:postcode":"92660",
    "sg:province":"CA",
    "sg:tags":[
        "center"
    ],
    "wof:name":"Streamgardens",
    "wof:placetype":"venue"
},
  "geometry": {"coordinates":[-117.871634,33.657837],"type":"Point"}
}