{
  "type": "Feature",
  "properties": {
    "iso:country":"US",
    "sg:address":"42605 Rd 72",
    "sg:city":"Dinuba",
    "sg:classifiers":[
        {
            "category":"Utilities",
            "subcategory":"Refuse",
            "type":"Services"
        }
    ],
    "sg:phone":"+1 559 595 1313",
    "sg:postcode":"93618",
    "sg:province":"CA",
    "sg:tags":[
        "garbage",
        "collection"
    ],
    "wof:name":"Miramonte Sanitation Svc",
    "wof:placetype":"venue"
},
  "geometry": {"coordinates":[-119.412983,36.565484],"type":"Point"}
}