{
  "type": "Feature",
  "properties": {
    "iso:country":"US",
    "sg:address":"21 Cll Ameno",
    "sg:city":"San Clemente",
    "sg:classifiers":[
        {
            "category":"Professional",
            "subcategory":"Business Services",
            "type":"Services"
        }
    ],
    "sg:phone":"+1 760 753 2819",
    "sg:postcode":"92672",
    "sg:province":"CA",
    "wof:name":"Allstar Pool & Spa Service",
    "wof:placetype":"venue"
},
  "geometry": {"coordinates":[-117.595607,33.426402],"type":"Point"}
}