{
  "type": "Feature",
  "properties": {
    "iso:country":"US",
    "sg:address":"415 Aldo Ave",
    "sg:city":"Santa Clara",
    "sg:classifiers":[
        {
            "category":"Freight",
            "type":"Transportation"
        }
    ],
    "sg:phone":"+1 408 988 9223",
    "sg:postcode":"95054",
    "sg:province":"CA",
    "sg:tags":[
        "trucking"
    ],
    "wof:name":"Gagliasso Chas F Trucking Inc",
    "wof:placetype":"venue"
},
  "geometry": {"coordinates":[-121.94015,37.387448],"type":"Point"}
}