{
  "type": "Feature",
  "properties": {
    "iso:country":"US",
    "sg:address":"27525 Puerta Real",
    "sg:city":"Mission Viejo",
    "sg:classifiers":[
        {
            "category":"Manufacturing",
            "subcategory":"Printing",
            "type":"Manufacturing & Wholesale Goods"
        }
    ],
    "sg:phone":"+1 949 271 5343",
    "sg:postcode":"92691",
    "sg:province":"CA",
    "sg:tags":[
        "lithographic",
        "commercial"
    ],
    "wof:name":"Creative Printing",
    "wof:placetype":"venue"
},
  "geometry": {"coordinates":[-117.671539,33.564419],"type":"Point"}
}