{
  "type": "Feature",
  "properties": {
    "addr:full":"1904 Franklin St Oakland CA 94612",
    "addr:housenumber":"1904",
    "addr:postcode":"94612",
    "addr:street":"Franklin St",
    "iso:country":"US",
    "sg:address":"1904 Franklin St",
    "sg:city":"Oakland",
    "sg:classifiers":[
        {
            "category":"Utilities",
            "subcategory":"Refuse",
            "type":"Services"
        }
    ],
    "sg:phone":"+1 510 272 0862",
    "sg:postcode":"94612",
    "sg:province":"CA",
    "sg:tags":[
        "equipment",
        "recycling",
        "system"
    ],
    "wof:name":"Multi Material Management",
    "wof:placetype":"venue"
},
  "geometry": {"coordinates":[-122.26743999999999,37.807786],"type":"Point"}
}