{
  "type": "Feature",
  "properties": {
    "iso:country":"US",
    "sg:address":"7590 N Glenoaks Blvd Ste 103",
    "sg:city":"Burbank",
    "sg:classifiers":[
        {
            "category":"Professional",
            "type":"Services"
        }
    ],
    "sg:phone":"+1 818 768 7068",
    "sg:postcode":"91504",
    "sg:province":"CA",
    "sg:website":"www.affinitylit.com",
    "wof:name":"Affinity Court Reporters",
    "wof:placetype":"venue"
},
  "geometry": {"coordinates":[-118.34300399999999,34.208988],"type":"Point"}
}