{
  "type": "Feature",
  "properties": {
    "addr:full":"180 Newport Center Dr Ste 240 Newport Beach CA 92660",
    "addr:housenumber":"180",
    "addr:postcode":"92660",
    "addr:street":"Newport Center Dr Ste 240",
    "iso:country":"US",
    "sg:address":"180 Newport Center Dr Ste 240",
    "sg:city":"Newport Beach",
    "sg:classifiers":[
        {
            "category":"Health Services",
            "subcategory":"Dentist",
            "type":"Services"
        }
    ],
    "sg:phone":"+1 949 729 2200",
    "sg:postcode":"92660",
    "sg:province":"CA",
    "wof:name":"Richard C Wittenauer DDS",
    "wof:placetype":"venue"
},
  "geometry": {"coordinates":[-117.875434,33.612404],"type":"Point"}
}