{
  "type": "Feature",
  "properties": {
    "addr:full":"25072 Via Portola Laguna Niguel CA 92677",
    "addr:housenumber":"25072",
    "addr:postcode":"92677",
    "addr:street":"Via Portola",
    "iso:country":"US",
    "sg:address":"25072 Via Portola",
    "sg:city":"Laguna Niguel",
    "sg:classifiers":[
        {
            "category":"Building & Trades",
            "subcategory":"Landscaping Services",
            "type":"Services"
        }
    ],
    "sg:phone":"+1 949 495 3087",
    "sg:postcode":"92677",
    "sg:province":"CA",
    "wof:name":"Rainer W Metz",
    "wof:placetype":"venue"
},
  "geometry": {"coordinates":[-117.691653,33.531417],"type":"Point"}
}