{
  "type": "Feature",
  "properties": {
    "addr:full":"1510 S Central Ave Ste 500 Glendale CA 91204",
    "addr:housenumber":"1510",
    "addr:postcode":"91204",
    "addr:street":"S Central Ave Ste 500",
    "iso:country":"US",
    "sg:address":"1510 S Central Ave Ste 500",
    "sg:city":"Glendale",
    "sg:classifiers":[
        {
            "category":"Health Services",
            "subcategory":"Doctor",
            "type":"Services"
        }
    ],
    "sg:phone":"+1 818 507 0686",
    "sg:postcode":"91204",
    "sg:province":"CA",
    "wof:name":"Karayan Sooren MD Inc",
    "wof:placetype":"venue"
},
  "geometry": {"coordinates":[-118.2573,34.127083],"type":"Point"}
}