{
  "type": "Feature",
  "properties": {
    "addr:full":"15105 Washington Ave San Leandro CA 94579",
    "addr:housenumber":"15105",
    "addr:postcode":"94579",
    "addr:street":"Washington Ave",
    "iso:country":"US",
    "sg:address":"15105 Washington Ave",
    "sg:city":"San Leandro",
    "sg:classifiers":[
        {
            "category":"Bars & Pubs",
            "type":"Food & Drink"
        }
    ],
    "sg:phone":"+1 510 352 4660",
    "sg:postcode":"94579",
    "sg:province":"CA",
    "sg:tags":[
        "lounge"
    ],
    "wof:name":"Jokers",
    "wof:placetype":"venue"
},
  "geometry": {"coordinates":[-122.139154,37.68811],"type":"Point"}
}