{
  "type": "Feature",
  "properties": {
    "iso:country":"US",
    "sg:address":"22141 Ventura Blvd",
    "sg:city":"Woodland Hills",
    "sg:classifiers":[
        {
            "category":"Retail",
            "subcategory":"Portrait Studio",
            "type":"Services"
        }
    ],
    "sg:phone":"+1 818 713 0223",
    "sg:postcode":"91364",
    "sg:province":"CA",
    "sg:tags":[
        "photography"
    ],
    "wof:name":"Paul Lester Photography",
    "wof:placetype":"venue"
},
  "geometry": {"coordinates":[-118.60936700000001,34.16869],"type":"Point"}
}