{
  "type": "Feature",
  "properties": {
    "iso:country":"US",
    "sg:address":"1484 N Fancher Ave",
    "sg:city":"Fresno",
    "sg:classifiers":[
        {
            "category":"Professional",
            "subcategory":"Management & Consulting",
            "type":"Services"
        }
    ],
    "sg:phone":"+1 559 251 6360",
    "sg:postcode":"93727",
    "sg:province":"CA",
    "sg:tags":[
        "consultant"
    ],
    "wof:name":"Doug Harrison Prof Svcs",
    "wof:placetype":"venue"
},
  "geometry": {"coordinates":[-119.632453,36.757274],"type":"Point"}
}