{
  "type": "Feature",
  "properties": {
    "addr:full":"3896 Stevens Creek Blvd San Jose CA 95128",
    "addr:housenumber":"3896",
    "addr:postcode":"95128",
    "addr:street":"Stevens Creek Blvd",
    "iso:country":"US",
    "sg:address":"3896 Stevens Creek Blvd",
    "sg:city":"San Jose",
    "sg:classifiers":[
        {
            "category":"Manufacturing",
            "subcategory":"Tools & Machinery",
            "type":"Manufacturing & Wholesale Goods"
        }
    ],
    "sg:phone":"+1 408 554 6666",
    "sg:postcode":"95128",
    "sg:province":"CA",
    "sg:tags":[
        "navigation",
        "system"
    ],
    "wof:name":"AMS Car Stereo Inc",
    "wof:placetype":"venue"
},
  "geometry": {"coordinates":[-121.96971499999999,37.323037],"type":"Point"}
}