{
  "type": "Feature",
  "properties": {
    "iso:country":"US",
    "sg:address":"3896 Stevens Creek Blvd",
    "sg:city":"San Jose",
    "sg:classifiers":[
        {
            "category":"Manufacturing",
            "subcategory":"Tools & Machinery",
            "type":"Manufacturing & Wholesale Goods"
        }
    ],
    "sg:phone":"+1 408 554 6666",
    "sg:postcode":"95128",
    "sg:province":"CA",
    "sg:tags":[
        "navigation",
        "system"
    ],
    "wof:name":"AMS Car Stereo Inc",
    "wof:placetype":"venue"
},
  "geometry": {"coordinates":[-121.969715,37.323037],"type":"Point"}
}