{
  "type": "Feature",
  "properties": {
    "iso:country":"US",
    "sg:address":"6423 Yucca St",
    "sg:city":"Los Angeles",
    "sg:classifiers":[
        {
            "category":"Bars & Pubs",
            "subcategory":"Nightclub",
            "type":"Food & Drink"
        }
    ],
    "sg:phone":"+1 323 962 2913",
    "sg:postcode":"90028",
    "sg:province":"CA",
    "sg:tags":[
        "nightlife"
    ],
    "wof:name":"Goldfinger's Bar & Nightclub",
    "wof:placetype":"venue"
},
  "geometry": {"coordinates":[-118.330002,34.103802],"type":"Point"}
}