{
  "type": "Feature",
  "properties": {
    "addr:full":"6423 Yucca St Los Angeles CA 90028",
    "addr:housenumber":"6423",
    "addr:postcode":"90028",
    "addr:street":"Yucca St",
    "iso:country":"US",
    "sg:address":"6423 Yucca St",
    "sg:city":"Los Angeles",
    "sg:classifiers":[
        {
            "category":"Bars & Pubs",
            "subcategory":"Nightclub",
            "type":"Food & Drink"
        }
    ],
    "sg:phone":"+1 323 962 2913",
    "sg:postcode":"90028",
    "sg:province":"CA",
    "sg:tags":[
        "nightlife"
    ],
    "wof:name":"Goldfinger's Bar & Nightclub",
    "wof:placetype":"venue"
},
  "geometry": {"coordinates":[-118.33000199999999,34.103802],"type":"Point"}
}