{
  "type": "Feature",
  "properties": {
    "iso:country":"US",
    "sg:address":"1499 Oliver Rd",
    "sg:city":"Fairfield",
    "sg:classifiers":[
        {
            "category":"Real Estate",
            "subcategory":"Real Estate Services",
            "type":"Services"
        }
    ],
    "sg:phone":"+1 707 427 5400",
    "sg:postcode":"94534",
    "sg:province":"CA",
    "sg:tags":[
        "company",
        "title"
    ],
    "sg:website":"www.frontiertitleco.com",
    "wof:name":"Frontier Title Co",
    "wof:placetype":"venue"
},
  "geometry": {"coordinates":[-122.07125600000001,38.26155],"type":"Point"}
}