{
  "type": "Feature",
  "properties": {
    "iso:country":"US",
    "sg:address":"7417 Quill Dr",
    "sg:city":"Downey",
    "sg:classifiers":[
        {
            "category":"Building & Trades",
            "subcategory":"Construction",
            "type":"Services"
        }
    ],
    "sg:phone":"+1 562 862 9531",
    "sg:postcode":"90242",
    "sg:province":"CA",
    "sg:tags":[
        "contractor"
    ],
    "wof:name":"Robert Warren Roofing",
    "wof:placetype":"venue"
},
  "geometry": {"coordinates":[-118.15605,33.930106],"type":"Point"}
}