{
  "type": "Feature",
  "properties": {
    "iso:country":"US",
    "sg:address":"371 W el Camino Ave",
    "sg:city":"Sacramento",
    "sg:classifiers":[
        {
            "category":"Building & Trades",
            "subcategory":"Construction",
            "type":"Services"
        }
    ],
    "sg:phone":"+1 916 920 4357",
    "sg:postcode":"95833",
    "sg:province":"CA",
    "sg:tags":[
        "residential",
        "contractor"
    ],
    "sg:website":"www.buildingvalue.com",
    "wof:name":"New Haven Homes",
    "wof:placetype":"venue"
},
  "geometry": {"coordinates":[-121.469195,38.611264],"type":"Point"}
}