{
  "type": "Feature",
  "properties": {
    "addr:full":"1201 el Camino Ave Sacramento CA 95815",
    "addr:housenumber":"1201",
    "addr:postcode":"95815",
    "addr:street":"El Camino Ave",
    "iso:country":"US",
    "sg:address":"1201 el Camino Ave",
    "sg:city":"Sacramento",
    "sg:classifiers":[
        {
            "category":"Wholesale",
            "subcategory":"Groceries",
            "type":"Manufacturing & Wholesale Goods"
        }
    ],
    "sg:phone":"+1 916 922 1635",
    "sg:postcode":"95815",
    "sg:province":"CA",
    "sg:tags":[
        "baker"
    ],
    "wof:name":"Orowheat",
    "wof:placetype":"venue"
},
  "geometry": {"coordinates":[-121.438118,38.611064],"type":"Point"}
}