{
  "type": "Feature",
  "properties": {
    "addr:full":"2209 N Hathaway St Santa Ana CA 92705",
    "addr:housenumber":"2209",
    "addr:postcode":"92705",
    "addr:street":"N Hathaway St",
    "iso:country":"US",
    "sg:address":"2209 N Hathaway St",
    "sg:city":"Santa Ana",
    "sg:classifiers":[
        {
            "category":"Professional",
            "type":"Services"
        }
    ],
    "sg:phone":"+1 714 973 1679",
    "sg:postcode":"92705",
    "sg:province":"CA",
    "wof:name":"David R Santana",
    "wof:placetype":"venue"
},
  "geometry": {"coordinates":[-117.85372,33.766575],"type":"Point"}
}