{
  "type": "Feature",
  "properties": {
    "iso:country":"US",
    "sg:address":"2905 Santa Monica Blvd",
    "sg:city":"Santa Monica",
    "sg:classifiers":[
        {
            "category":"Shopping",
            "subcategory":"Clothing, Apparel, & Fashions",
            "type":"Retail Goods"
        }
    ],
    "sg:phone":"+1 310 453 3083",
    "sg:postcode":"90404",
    "sg:province":"CA",
    "sg:tags":[
        "shop",
        "bridal"
    ],
    "wof:name":"Dina's Bridal Shop",
    "wof:placetype":"venue"
},
  "geometry": {"coordinates":[-118.470608,34.036373],"type":"Point"}
}