{
  "type": "Feature",
  "properties": {
    "iso:country":"US",
    "sg:address":"1282 Ray Ct",
    "sg:city":"Turlock",
    "sg:classifiers":[
        {
            "category":"Building & Trades",
            "subcategory":"Landscaping Services",
            "type":"Services"
        }
    ],
    "sg:phone":"+1 209 632 6548",
    "sg:postcode":"95380",
    "sg:province":"CA",
    "sg:tags":[
        "landscape"
    ],
    "wof:name":"Silvas Landscaping",
    "wof:placetype":"venue"
},
  "geometry": {"coordinates":[-120.835748,37.479682],"type":"Point"}
}