{
  "type": "Feature",
  "properties": {
    "addr:full":"1662 Zenos Rd Holtville CA 92250",
    "addr:housenumber":"1662",
    "addr:postcode":"92250",
    "addr:street":"Zenos Rd",
    "iso:country":"US",
    "sg:address":"1662 Zenos Rd",
    "sg:city":"Holtville",
    "sg:classifiers":[
        {
            "category":"Farming",
            "subcategory":"Farm",
            "type":"Manufacturing & Wholesale Goods"
        }
    ],
    "sg:phone":"+1 760 356 2870",
    "sg:postcode":"92250",
    "sg:province":"CA",
    "wof:name":"Baja Farms",
    "wof:placetype":"venue"
},
  "geometry": {"coordinates":[-115.391763,32.812855],"type":"Point"}
}