{
  "type": "Feature",
  "properties": {
    "iso:country":"US",
    "sg:address":"13366 Grass Valley Avenue Unit H",
    "sg:city":"Grass Valley",
    "sg:classifiers":[
        {
            "category":"Manufacturing",
            "subcategory":"Electronics",
            "type":"Manufacturing & Wholesale Goods"
        }
    ],
    "sg:phone":"+1 415 230 0612",
    "sg:postcode":"95945",
    "sg:province":"CA",
    "sg:website":"http://www.cinegest.com",
    "wof:name":"Cinegest, Inc.",
    "wof:placetype":"venue"
},
  "geometry": {"coordinates":[-121.012545,39.218265],"type":"Point"}
}