{
  "type": "Feature",
  "properties": {
    "addr:full":"2505 S H St Bakersfield CA 93304",
    "addr:housenumber":"2505",
    "addr:postcode":"93304",
    "addr:street":"S H St",
    "iso:country":"US",
    "sg:address":"2505 S H St",
    "sg:city":"Bakersfield",
    "sg:classifiers":[
        {
            "category":"Shopping",
            "subcategory":"Department Store",
            "type":"Retail Goods"
        }
    ],
    "sg:phone":"+1 661 837 9898",
    "sg:postcode":"93304",
    "sg:province":"CA",
    "sg:tags":[
        "shop"
    ],
    "sg:website":"www.dollartree.com",
    "wof:name":"Dollar Tree",
    "wof:placetype":"venue"
},
  "geometry": {"coordinates":[-119.02127900000001,35.328827],"type":"Point"}
}