{
  "type": "Feature",
  "properties": {
    "iso:country":"US",
    "sg:address":"23011 Alcalde Dr",
    "sg:city":"Laguna Hills",
    "sg:classifiers":[
        {
            "category":"Shopping",
            "type":"Retail Goods"
        }
    ],
    "sg:phone":"+1 949 380 7707",
    "sg:postcode":"92653",
    "sg:province":"CA",
    "sg:tags":[
        "trophy",
        "medal",
        "award"
    ],
    "sg:website":"www.usa-trophy.com",
    "wof:name":"USA Trophy",
    "wof:placetype":"venue"
},
  "geometry": {"coordinates":[-117.72685199999999,33.624003],"type":"Point"}
}