{
  "type": "Feature",
  "properties": {
    "iso:country":"US",
    "sg:address":"416 E School Ave",
    "sg:city":"Visalia",
    "sg:classifiers":[
        {
            "category":"Manufacturing",
            "subcategory":"Glass & Minerals",
            "type":"Manufacturing & Wholesale Goods"
        }
    ],
    "sg:phone":"+1 559 732 6854",
    "sg:postcode":"93291",
    "sg:province":"CA",
    "sg:tags":[
        "ready",
        "concrete",
        "mfg"
    ],
    "wof:name":"Viking Ready Mix Co Inc",
    "wof:placetype":"venue"
},
  "geometry": {"coordinates":[-119.288089,36.332963],"type":"Point"}
}