{
  "type": "Feature",
  "properties": {
    "addr:full":"1718 Hicks St Oceanside CA 92054",
    "addr:housenumber":"1718",
    "addr:postcode":"92054",
    "addr:street":"Hicks St",
    "iso:country":"US",
    "sg:address":"1718 Hicks St",
    "sg:city":"Oceanside",
    "sg:classifiers":[
        {
            "category":"Banks & Credit Unions",
            "subcategory":"Investment Brokerage",
            "type":"Services"
        }
    ],
    "sg:phone":"+1 760 757 0290",
    "sg:postcode":"92054",
    "sg:province":"CA",
    "sg:tags":[
        "trust"
    ],
    "wof:name":"Pepper Family Trust 02 07",
    "wof:placetype":"venue"
},
  "geometry": {"coordinates":[-117.35328800000001,33.182149],"type":"Point"}
}