{
  "type": "Feature",
  "properties": {
    "addr:full":"675 Hartz Ave Danville CA 94526",
    "addr:housenumber":"675",
    "addr:postcode":"94526",
    "addr:street":"Hartz Ave",
    "iso:country":"US",
    "sg:address":"675 Hartz Ave",
    "sg:city":"Danville",
    "sg:classifiers":[
        {
            "category":"Professional",
            "subcategory":"Advertising",
            "type":"Services"
        }
    ],
    "sg:phone":"+1 925 831 1175",
    "sg:postcode":"94526",
    "sg:province":"CA",
    "sg:tags":[
        "counselor"
    ],
    "wof:name":"Action Yellow Pages",
    "wof:placetype":"venue"
},
  "geometry": {"coordinates":[-121.996987,37.819761],"type":"Point"}
}