{
  "type": "Feature",
  "properties": {
    "addr:full":"1512 Queens Ave Modesto CA 95355",
    "addr:housenumber":"1512",
    "addr:postcode":"ca 95355",
    "addr:street":"Queens Ave",
    "iso:country":"US",
    "sg:address":"1512 Queens Ave",
    "sg:city":"Modesto",
    "sg:classifiers":[
        {
            "category":"Shopping",
            "type":"Retail Goods"
        }
    ],
    "sg:phone":"+1 209 527 1354",
    "sg:postcode":"95355",
    "sg:province":"CA",
    "sg:tags":[
        "merchandise"
    ],
    "wof:name":"The Little Shop On The Web",
    "wof:placetype":"venue"
},
  "geometry": {"coordinates":[-120.967686,37.66544],"type":"Point"}
}