{
  "type": "Feature",
  "properties": {
    "iso:country":"US",
    "sg:address":"22069 Van Buren St",
    "sg:city":"Grand Terrace",
    "sg:classifiers":[
        {
            "category":"Freight",
            "type":"Transportation"
        }
    ],
    "sg:phone":"+1 909 512 1276",
    "sg:postcode":"92313",
    "sg:province":"CA",
    "sg:tags":[
        "arrangement"
    ],
    "wof:name":"Lightning Logistics",
    "wof:placetype":"venue"
},
  "geometry": {"coordinates":[-117.330281,34.026608],"type":"Point"}
}