{
  "type": "Feature",
  "properties": {
    "iso:country":"US",
    "sg:address":"73 Mountain View Ave",
    "sg:city":"San Anselmo",
    "sg:classifiers":[
        {
            "category":"Building & Trades",
            "subcategory":"Landscaping Services",
            "type":"Services"
        }
    ],
    "sg:phone":"+1 415 451 4850",
    "sg:postcode":"94960",
    "sg:province":"CA",
    "sg:tags":[
        "tree"
    ],
    "wof:name":"Shade Tree Inc",
    "wof:placetype":"venue"
},
  "geometry": {"coordinates":[-122.57137299999999,37.986543],"type":"Point"}
}