{
  "type": "Feature",
  "properties": {
    "addr:full":"22075 Lone Tree Rd Escalon CA 95320",
    "addr:housenumber":"22075",
    "addr:postcode":"95320",
    "addr:street":"Lone Tree Rd",
    "iso:country":"US",
    "sg:address":"22075 Lone Tree Rd",
    "sg:city":"Escalon",
    "sg:classifiers":[
        {
            "category":"Farming",
            "subcategory":"Dairy Farm",
            "type":"Manufacturing & Wholesale Goods"
        }
    ],
    "sg:phone":"+1 209 838 7462",
    "sg:postcode":"95320",
    "sg:province":"CA",
    "wof:name":"John M Vierira Dairy Farm",
    "wof:placetype":"venue"
},
  "geometry": {"coordinates":[-121.035471,37.827772],"type":"Point"}
}