{
  "type": "Feature",
  "properties": {
    "addr:full":"8801 Central Ave Montclair CA 91763",
    "addr:housenumber":"8801",
    "addr:postcode":"91763",
    "addr:street":"Central Ave",
    "iso:country":"US",
    "sg:address":"8801 Central Ave",
    "sg:city":"Montclair",
    "sg:classifiers":[
        {
            "category":"Restaurant",
            "type":"Food & Drink"
        }
    ],
    "sg:menulink":"http://www.allmenus.com/ca/ontario/123929-quiznos-sub/menu/",
    "sg:phone":"+1 909 482 1800",
    "sg:postcode":"91763",
    "sg:province":"CA",
    "sg:tags":[
        "wrap",
        "american",
        "sandwich"
    ],
    "wof:name":"Quiznos Sub",
    "wof:placetype":"venue"
},
  "geometry": {"coordinates":[-117.688748,34.093101],"type":"Point"}
}