{
  "type": "Feature",
  "properties": {
    "addr:full":"2010 Ocean Avenue San Francisco CA 94127",
    "addr:housenumber":"2010",
    "addr:postcode":"94127",
    "addr:street":"Ocean Avenue",
    "iso:country":"US",
    "sg:address":"2010 Ocean Avenue",
    "sg:city":"San Francisco",
    "sg:classifiers":[
        {
            "category":"Banks & Credit Unions",
            "subcategory":"Financial Services",
            "type":"Services"
        }
    ],
    "sg:phone":"+1 415 333 3979",
    "sg:postcode":"94127",
    "sg:province":"CA",
    "sg:tags":[
        "broker",
        "mortgage"
    ],
    "wof:name":"Veracity Mortgage",
    "wof:placetype":"venue"
},
  "geometry": {"coordinates":[-122.464743,37.726272],"type":"Point"}
}