{
  "type": "Feature",
  "properties": {
    "iso:country":"US",
    "sg:address":"2424 Tapo St",
    "sg:city":"Simi Valley",
    "sg:classifiers":[
        {
            "category":"Retail",
            "subcategory":"Auto Repair",
            "type":"Services"
        }
    ],
    "sg:phone":"+1 805 581 1141",
    "sg:postcode":"93063",
    "sg:province":"CA",
    "sg:tags":[
        "body",
        "automobile",
        "top",
        "upholstery",
        "go"
    ],
    "wof:name":"Unida Custom Auto Upholstery",
    "wof:placetype":"venue"
},
  "geometry": {"coordinates":[-118.708865,34.280279],"type":"Point"}
}