{
  "type": "Feature",
  "properties": {
    "iso:country":"US",
    "sg:address":"5705 Evening Way",
    "sg:city":"Santa Rosa",
    "sg:classifiers":[
        {
            "category":"Insurance",
            "subcategory":"Insurance Agent",
            "type":"Services"
        }
    ],
    "sg:phone":"+1 707 545 3086",
    "sg:postcode":"95409",
    "sg:province":"CA",
    "wof:name":"Redwood Premier Insurance Svc",
    "wof:placetype":"venue"
},
  "geometry": {"coordinates":[-122.646493,38.464407],"type":"Point"}
}