{
  "type": "Feature",
  "properties": {
    "addr:full":"16828 S. Broadway Gardena CA 90248",
    "addr:housenumber":"16828",
    "addr:postcode":"90248",
    "addr:street":"S. Broadway",
    "iso:country":"US",
    "sg:address":"16828 S. Broadway",
    "sg:city":"Gardena",
    "sg:classifiers":[
        {
            "category":"Building & Trades",
            "subcategory":"Construction",
            "type":"Services"
        }
    ],
    "sg:phone":"+1 310 515 9423",
    "sg:postcode":"90248",
    "sg:province":"CA",
    "sg:tags":[
        "contractor"
    ],
    "sg:website":"avalonroofing.com",
    "wof:name":"Avalon Roofing INC",
    "wof:placetype":"venue"
},
  "geometry": {"coordinates":[-118.27720100000001,33.878646],"type":"Point"}
}