{
  "type": "Feature",
  "properties": {
    "addr:full":"5814 Holmby Ct Cypress CA 90630",
    "addr:housenumber":"5814",
    "addr:postcode":"90630",
    "addr:street":"Holmby Ct",
    "iso:country":"US",
    "sg:address":"5814 Holmby Ct",
    "sg:city":"Cypress",
    "sg:classifiers":[
        {
            "category":"Professional",
            "subcategory":"Management & Consulting",
            "type":"Services"
        }
    ],
    "sg:phone":"+1 714 816 1111",
    "sg:postcode":"90630",
    "sg:province":"CA",
    "sg:tags":[
        "consultant"
    ],
    "wof:name":"Warcass Enterprises",
    "wof:placetype":"venue"
},
  "geometry": {"coordinates":[-118.031435,33.814299],"type":"Point"}
}