{
  "type": "Feature",
  "properties": {
    "addr:full":"1250 Broadway Ave Seaside CA 93955",
    "addr:housenumber":"1250",
    "addr:postcode":"93955",
    "addr:street":"Broadway Ave",
    "iso:country":"US",
    "sg:address":"1250 Broadway Ave",
    "sg:city":"Seaside",
    "sg:classifiers":[
        {
            "category":"Banks & Credit Unions",
            "subcategory":"Bank",
            "type":"Services"
        }
    ],
    "sg:phone":"+1 831 394 2362",
    "sg:postcode":"93955",
    "sg:province":"CA",
    "sg:tags":[
        "financing"
    ],
    "wof:name":"Mortgage Center Of America",
    "wof:placetype":"venue"
},
  "geometry": {"coordinates":[-121.838758,36.608976],"type":"Point"}
}