{
  "type": "Feature",
  "properties": {
    "iso:country":"US",
    "sg:address":"21098 Bake Pkwy Ste 112",
    "sg:city":"Lake Forest",
    "sg:classifiers":[
        {
            "category":"Shopping",
            "subcategory":"Bicycles & Sporting Goods",
            "type":"Retail Goods"
        },
        {
            "category":"Sports & Exercise",
            "subcategory":"Bicycle Rental",
            "type":"Entertainment"
        }
    ],
    "sg:phone":"+1 949 470 1099",
    "sg:postcode":"92630",
    "sg:province":"CA",
    "sg:tags":[
        "bike"
    ],
    "wof:name":"The Bike Company",
    "wof:placetype":"venue"
},
  "geometry": {"coordinates":[-117.700253,33.656557],"type":"Point"}
}