{
  "type": "Feature",
  "properties": {
    "addr:full":"1 Silver Maple Ct Napa CA 94558",
    "addr:housenumber":"1",
    "addr:postcode":"94558",
    "addr:street":"Silver Maple Ct",
    "iso:country":"US",
    "sg:address":"1 Silver Maple Ct",
    "sg:city":"Napa",
    "sg:classifiers":[
        {
            "category":"Utilities",
            "subcategory":"Telephone",
            "type":"Services"
        }
    ],
    "sg:phone":"+1 707 226 7251",
    "sg:postcode":"94558",
    "sg:province":"CA",
    "sg:tags":[
        "telecommunication"
    ],
    "wof:name":"William Hand",
    "wof:placetype":"venue"
},
  "geometry": {"coordinates":[-122.321555,38.327693],"type":"Point"}
}