{
  "type": "Feature",
  "properties": {
    "iso:country":"US",
    "sg:address":"1040 E Ave J",
    "sg:city":"Lancaster",
    "sg:classifiers":[
        {
            "category":"Government",
            "subcategory":"Court House",
            "type":"Public Place"
        }
    ],
    "sg:phone":"+1 661 945 6355",
    "sg:postcode":"93535",
    "sg:province":"CA",
    "wof:name":"Lancaster Court Criminal",
    "wof:placetype":"venue"
},
  "geometry": {"coordinates":[-118.11156,34.689339],"type":"Point"}
}