{
  "type": "Feature",
  "properties": {
    "iso:country":"US",
    "sg:address":"3307 Sweet Dr",
    "sg:city":"Lafayette",
    "sg:classifiers":[
        {
            "category":"Communications",
            "subcategory":"Film & Video Production",
            "type":"Services"
        }
    ],
    "sg:phone":"+1 925 284 4264",
    "sg:postcode":"94549",
    "sg:province":"CA",
    "sg:tags":[
        "taping"
    ],
    "wof:name":"S T Video Productions",
    "wof:placetype":"venue"
},
  "geometry": {"coordinates":[-122.101947,37.875208],"type":"Point"}
}