{
  "type": "Feature",
  "properties": {
    "iso:country":"US",
    "sg:address":"6300 E Keyes Rd",
    "sg:city":"Turlock",
    "sg:classifiers":[
        {
            "category":"Farming",
            "subcategory":"Crops",
            "type":"Manufacturing & Wholesale Goods"
        }
    ],
    "sg:phone":"+1 209 667 8843",
    "sg:postcode":"95382",
    "sg:province":"CA",
    "sg:tags":[
        "grove",
        "nut",
        "tree"
    ],
    "wof:name":"Wetherbee Farms",
    "wof:placetype":"venue"
},
  "geometry": {"coordinates":[-120.872381,37.55112],"type":"Point"}
}