{
  "type": "Feature",
  "properties": {
    "iso:country":"US",
    "sg:address":"2511 Pacific Coast Hwy",
    "sg:city":"Torrance",
    "sg:classifiers":[
        {
            "category":"Shopping",
            "subcategory":"Computers & Home Electronics",
            "type":"Retail Goods"
        }
    ],
    "sg:phone":"+1 310 784 0880",
    "sg:postcode":"90505",
    "sg:province":"CA",
    "sg:tags":[
        "television",
        "radio"
    ],
    "wof:name":"Electronic Repair Ctr",
    "wof:placetype":"venue"
},
  "geometry": {"coordinates":[-118.328575,33.789635],"type":"Point"}
}