{
  "type": "Feature",
  "properties": {
    "iso:country":"US",
    "sg:address":"1250 Harter Ave",
    "sg:city":"Woodland",
    "sg:classifiers":[
        {
            "category":"Recreation",
            "type":"Entertainment"
        }
    ],
    "sg:phone":"+1 530 666 5414",
    "sg:postcode":"95776",
    "sg:province":"CA",
    "sg:tags":[
        "instruction",
        "gymnastic"
    ],
    "sg:website":"www.woodlandgymnastics.com",
    "wof:name":"Woodland Gymnastics",
    "wof:placetype":"venue"
},
  "geometry": {"coordinates":[-121.764734,38.693371],"type":"Point"}
}