{
  "type": "Feature",
  "properties": {
    "iso:country":"US",
    "sg:address":"3407 E Lochleven Ln",
    "sg:city":"Orange",
    "sg:classifiers":[
        {
            "category":"Professional",
            "type":"Services"
        }
    ],
    "sg:phone":"+1 714 633 8331",
    "sg:postcode":"92869",
    "sg:province":"CA",
    "wof:name":"Richard A Jones",
    "wof:placetype":"venue"
},
  "geometry": {"coordinates":[-117.816928,33.791871],"type":"Point"}
}