{
  "type": "Feature",
  "properties": {
    "iso:country":"US",
    "sg:address":"1870 Via Primero",
    "sg:city":"Oceanside",
    "sg:classifiers":[
        {
            "category":"Banks & Credit Unions",
            "subcategory":"Financial Services",
            "type":"Services"
        }
    ],
    "sg:phone":"+1 760 806 1178",
    "sg:postcode":"92056",
    "sg:province":"CA",
    "sg:tags":[
        "debt",
        "adjuster"
    ],
    "wof:name":"Jerry M Walsh Jr",
    "wof:placetype":"venue"
},
  "geometry": {"coordinates":[-117.285107,33.21259],"type":"Point"}
}