{
  "type": "Feature",
  "properties": {
    "addr:full":"4317 Casanna Way Apt 1603 Oceanside CA 92057",
    "addr:housenumber":"4317",
    "addr:postcode":"92057",
    "addr:street":"Casanna Way Apt 1603",
    "iso:country":"US",
    "sg:address":"4317 Casanna Way Apt 1603",
    "sg:city":"Oceanside",
    "sg:classifiers":[
        {
            "category":"Personal",
            "subcategory":"Beauty Salon",
            "type":"Services"
        }
    ],
    "sg:phone":"+1 760 805 8001",
    "sg:postcode":"92057",
    "sg:province":"CA",
    "wof:name":"Serenity Day Spa",
    "wof:placetype":"venue"
},
  "geometry": {"coordinates":[-117.301666,33.221572],"type":"Point"}
}