{
  "type": "Feature",
  "properties": {
    "addr:full":"904 Scott St San Diego CA 92106",
    "addr:housenumber":"904",
    "addr:postcode":"92106",
    "addr:street":"Scott St",
    "iso:country":"US",
    "sg:address":"904 Scott St",
    "sg:city":"San Diego",
    "sg:classifiers":[
        {
            "category":"Real Estate",
            "subcategory":"Real Estate Agent",
            "type":"Services"
        }
    ],
    "sg:phone":"+1 619 222 9309",
    "sg:postcode":"92106",
    "sg:province":"CA",
    "wof:name":"Baker Daniel Investment RE",
    "wof:placetype":"venue"
},
  "geometry": {"coordinates":[-117.231939,32.719641],"type":"Point"}
}