{
  "type": "Feature",
  "properties": {
    "iso:country":"US",
    "sg:address":"Brock Real Estate - Silverlake 2235 Hyperion Ave",
    "sg:city":"Los Angeles",
    "sg:classifiers":[
        {
            "category":"Real Estate",
            "subcategory":"Real Estate Services",
            "type":"Services"
        },
        {
            "category":"Real Estate",
            "subcategory":"Real Estate Agent",
            "type":"Services"
        }
    ],
    "sg:phone":"+1 323 919 0375",
    "sg:postcode":"90027",
    "sg:province":"CA",
    "sg:website":"www.greenlivinganddesign.com/",
    "wof:name":"Courtney Poulos - Realtor, NAR Green, EcoBroker Certified",
    "wof:placetype":"venue"
},
  "geometry": {"coordinates":[-118.273511,34.100976],"type":"Point"}
}