{
  "type": "Feature",
  "properties": {
    "iso:country":"US",
    "sg:address":"23720 el Toro Rd",
    "sg:city":"Lake Forest",
    "sg:classifiers":[
        {
            "category":"Professional",
            "subcategory":"Accounting & Tax Preparation",
            "type":"Services"
        }
    ],
    "sg:phone":"+1 949 215 5008",
    "sg:postcode":"92630",
    "sg:province":"CA",
    "sg:tags":[
        "billing"
    ],
    "wof:name":"Creative Billing Svc",
    "wof:placetype":"venue"
},
  "geometry": {"coordinates":[-117.702888,33.618543],"type":"Point"}
}