{
  "type": "Feature",
  "properties": {
    "iso:country":"US",
    "sg:address":"4932 Casa Loma Ave",
    "sg:city":"Yorba Linda",
    "sg:classifiers":[
        {
            "category":"Building & Trades",
            "subcategory":"Landscaping Services",
            "type":"Services"
        }
    ],
    "sg:phone":"+1 714 996 8040",
    "sg:postcode":"92886",
    "sg:province":"CA",
    "sg:tags":[
        "landscape"
    ],
    "wof:name":"Dreamscapes",
    "wof:placetype":"venue"
},
  "geometry": {"coordinates":[-117.824235,33.889189],"type":"Point"}
}