{
  "type": "Feature",
  "properties": {
    "addr:full":"804 Sutter St San Francisco CA 94109",
    "addr:housenumber":"804",
    "addr:postcode":"94109",
    "addr:street":"Sutter St",
    "iso:country":"US",
    "sg:address":"804 Sutter St",
    "sg:city":"San Francisco",
    "sg:classifiers":[
        {
            "category":"Arts & Performance",
            "subcategory":"Art Gallery",
            "type":"Entertainment"
        }
    ],
    "sg:phone":"+1 415 255 9508",
    "sg:postcode":"94109",
    "sg:province":"CA",
    "sg:website":"www.silverman-gallery.com",
    "wof:name":"SIlverman Gallery",
    "wof:placetype":"venue"
},
  "geometry": {"coordinates":[-122.413647,37.788639],"type":"Point"}
}