{
  "type": "Feature",
  "properties": {
    "iso:country":"US",
    "sg:address":"6203 W 87th St",
    "sg:city":"Los Angeles",
    "sg:classifiers":[
        {
            "category":"Professional",
            "subcategory":"Business Services",
            "type":"Services"
        }
    ],
    "sg:phone":"+1 310 670 6050",
    "sg:postcode":"90045",
    "sg:province":"CA",
    "sg:tags":[
        "fund",
        "promotion",
        "raising"
    ],
    "wof:name":"Christians Promotional Gvwys",
    "wof:placetype":"venue"
},
  "geometry": {"coordinates":[-118.394713,33.958635],"type":"Point"}
}