{
  "type": "Feature",
  "properties": {
    "addr:full":"4835 Colt St Ventura CA 93003",
    "addr:housenumber":"4835",
    "addr:postcode":"93003",
    "addr:street":"Colt St",
    "iso:country":"US",
    "sg:address":"4835 Colt St",
    "sg:city":"Ventura",
    "sg:classifiers":[
        {
            "category":"Professional",
            "subcategory":"Business Services",
            "type":"Services"
        }
    ],
    "sg:phone":"+1 805 658 0600",
    "sg:postcode":"93003",
    "sg:province":"CA",
    "sg:tags":[
        "water",
        "treatment"
    ],
    "sg:website":"www.remco.com",
    "wof:name":"Remco Engineering",
    "wof:placetype":"venue"
},
  "geometry": {"coordinates":[-119.22636799999999,34.250294],"type":"Point"}
}