{
  "type": "Feature",
  "properties": {
    "iso:country":"US",
    "sg:address":"9836 Foothill Blvd",
    "sg:city":"Rancho Cucamonga",
    "sg:classifiers":[
        {
            "category":"Professional",
            "subcategory":"Lawyer & Legal Services",
            "type":"Services"
        }
    ],
    "sg:phone":"+1 909 466 0215",
    "sg:postcode":"91730",
    "sg:province":"CA",
    "sg:tags":[
        "attorney"
    ],
    "wof:name":"Mike Pendleton",
    "wof:placetype":"venue"
},
  "geometry": {"coordinates":[-117.591751,34.106698],"type":"Point"}
}