{
  "type": "Feature",
  "properties": {
    "iso:country":"US",
    "sg:address":"11704 Wilshire Blvd",
    "sg:city":"Los Angeles",
    "sg:classifiers":[
        {
            "category":"Health Services",
            "subcategory":"Doctor",
            "type":"Services"
        }
    ],
    "sg:phone":"+1 310 477 2236",
    "sg:postcode":"90025",
    "sg:province":"CA",
    "sg:tags":[
        "physician",
        "surgeon"
    ],
    "wof:name":"Abdollah Gilani MD",
    "wof:placetype":"venue"
},
  "geometry": {"coordinates":[-118.46177,34.048721],"type":"Point"}
}