{
  "type": "Feature",
  "properties": {
    "addr:full":"660 Newport Center Dr Newport Beach CA 92660",
    "addr:housenumber":"660",
    "addr:postcode":"92660",
    "addr:street":"Newport Center Dr",
    "iso:country":"US",
    "sg:address":"660 Newport Center Dr",
    "sg:city":"Newport Beach",
    "sg:classifiers":[
        {
            "category":"Professional",
            "subcategory":"Management & Consulting",
            "type":"Services"
        }
    ],
    "sg:phone":"+1 949 720 8365",
    "sg:postcode":"92660",
    "sg:province":"CA",
    "sg:tags":[
        "consultant",
        "business"
    ],
    "wof:name":"Mooers Strategy Group",
    "wof:placetype":"venue"
},
  "geometry": {"coordinates":[-117.87533500000001,33.619305],"type":"Point"}
}