{
  "type": "Feature",
  "properties": {
    "addr:full":"741 Spruce St Berkeley CA 94707",
    "addr:housenumber":"741",
    "addr:postcode":"94707",
    "addr:street":"Spruce St",
    "iso:country":"US",
    "sg:address":"741 Spruce St",
    "sg:city":"Berkeley",
    "sg:classifiers":[
        {
            "category":"Professional",
            "type":"Services"
        }
    ],
    "sg:phone":"+1 510 528 3203",
    "sg:postcode":"94707",
    "sg:province":"CA",
    "wof:name":"Jewel Baker Educatn Foundation",
    "wof:placetype":"venue"
},
  "geometry": {"coordinates":[-122.26951200000001,37.897142],"type":"Point"}
}