{
  "type": "Feature",
  "properties": {
    "addr:full":"7501 S Western Ave Los Angeles CA 90047",
    "addr:housenumber":"7501",
    "addr:postcode":"90047",
    "addr:street":"S Western Ave",
    "iso:country":"US",
    "sg:address":"7501 S Western Ave",
    "sg:city":"Los Angeles",
    "sg:classifiers":[
        {
            "category":"Retail",
            "subcategory":"Auto Repair",
            "type":"Services"
        }
    ],
    "sg:phone":"+1 323 750 5952",
    "sg:postcode":"90047",
    "sg:province":"CA",
    "sg:tags":[
        "body",
        "automobile",
        "painting"
    ],
    "wof:name":"Mecanica Aguilar",
    "wof:placetype":"venue"
},
  "geometry": {"coordinates":[-118.308984,33.97091],"type":"Point"}
}