{
  "type": "Feature",
  "properties": {
    "addr:full":"250 W Jackson St Hayward CA 94544",
    "addr:housenumber":"250",
    "addr:postcode":"94544",
    "addr:street":"W Jackson St",
    "iso:country":"US",
    "sg:address":"250 W Jackson St",
    "sg:city":"Hayward",
    "sg:classifiers":[
        {
            "category":"Real Estate",
            "subcategory":"Real Estate Operator",
            "type":"Services"
        }
    ],
    "sg:phone":"+1 510 782 6640",
    "sg:postcode":"94544",
    "sg:province":"CA",
    "sg:tags":[
        "apartment"
    ],
    "sg:website":"www.tikialoha.com",
    "wof:name":"Aloha Apartments",
    "wof:placetype":"venue"
},
  "geometry": {"coordinates":[-122.089996,37.6521],"type":"Point"}
}