{
  "type": "Feature",
  "properties": {
    "iso:country":"US",
    "sg:address":"25530 N Ave Stanford",
    "sg:city":"Valencia",
    "sg:classifiers":[
        {
            "category":"Professional",
            "subcategory":"Business Services",
            "type":"Services"
        }
    ],
    "sg:phone":"+1 661 284 6944",
    "sg:postcode":"91355",
    "sg:province":"CA",
    "wof:name":"Aastra Business Equipment",
    "wof:placetype":"venue"
},
  "geometry": {"coordinates":[-118.587211,34.432594],"type":"Point"}
}