{
  "type": "Feature",
  "properties": {
    "addr:full":"103 Mar Vista Dr Aptos CA 95003",
    "addr:housenumber":"103",
    "addr:postcode":"ca 95003",
    "addr:street":"Mar Vista Dr",
    "iso:country":"US",
    "sg:address":"103 Mar Vista Dr",
    "sg:city":"Aptos",
    "sg:classifiers":[
        {
            "category":"Professional",
            "subcategory":"Art Services",
            "type":"Services"
        }
    ],
    "sg:phone":"+1 831 687 0239",
    "sg:postcode":"95003",
    "sg:province":"CA",
    "sg:tags":[
        "graphic",
        "designer"
    ],
    "wof:name":"Aurelio Henderson Design Assoc",
    "wof:placetype":"venue"
},
  "geometry": {"coordinates":[-121.917158,36.975037],"type":"Point"}
}