{
  "type": "Feature",
  "properties": {
    "addr:full":"750 Beyer Way San Diego CA 92154",
    "addr:housenumber":"750",
    "addr:postcode":"92154",
    "addr:street":"Beyer Way",
    "iso:country":"US",
    "sg:address":"750 Beyer Way",
    "sg:city":"San Diego",
    "sg:classifiers":[
        {
            "category":"Education",
            "subcategory":"Vocational School",
            "type":"Public Place"
        }
    ],
    "sg:phone":"+1 619 575 1511",
    "sg:postcode":"92154",
    "sg:province":"CA",
    "sg:tags":[
        "cosmetology"
    ],
    "wof:name":"Avance' Beauty College",
    "wof:placetype":"venue"
},
  "geometry": {"coordinates":[-117.061983,32.581592],"type":"Point"}
}