{
  "type": "Feature",
  "properties": {
    "addr:full":"8 Whatney Suite 125 Irvine CA 92618",
    "addr:housenumber":"8;suite 125",
    "addr:postcode":"92618",
    "addr:street":"Whatney",
    "iso:country":"US",
    "sg:address":"8 Whatney Suite 125",
    "sg:city":"Irvine",
    "sg:classifiers":[
        {
            "category":"Professional",
            "subcategory":"Lawyer & Legal Services",
            "type":"Services"
        }
    ],
    "sg:phone":"+1 877 947 7497",
    "sg:postcode":"92618",
    "sg:province":"CA",
    "sg:tags":[
        "litigation"
    ],
    "wof:name":"The Convenant Law Center",
    "wof:placetype":"venue"
},
  "geometry": {"coordinates":[-117.721683,33.637589],"type":"Point"}
}