{
  "type": "Feature",
  "properties": {
    "iso:country":"US",
    "sg:address":"8277 Elder Creek Rd",
    "sg:city":"Sacramento",
    "sg:classifiers":[
        {
            "category":"Military Area",
            "type":"Public Place"
        }
    ],
    "sg:phone":"+1 916 387 7100",
    "sg:postcode":"95828",
    "sg:province":"CA",
    "sg:tags":[
        "force",
        "armed",
        "recruiting"
    ],
    "sg:website":"http://www.navy.com",
    "wof:name":"Us Naval Rsrve/N Mcrc Scrmento",
    "wof:placetype":"venue"
},
  "geometry": {"coordinates":[-121.40279200000001,38.510577],"type":"Point"}
}