{
  "type": "Feature",
  "properties": {
    "iso:country":"US",
    "sg:address":"373 Montana Ave",
    "sg:city":"Turlock",
    "sg:classifiers":[
        {
            "category":"Building & Trades",
            "subcategory":"Construction",
            "type":"Services"
        }
    ],
    "sg:phone":"+1 209 634 5302",
    "sg:postcode":"95380",
    "sg:province":"CA",
    "sg:tags":[
        "contractor"
    ],
    "wof:name":"Bullock Construction",
    "wof:placetype":"venue"
},
  "geometry": {"coordinates":[-120.852444,37.480091],"type":"Point"}
}