{
  "type": "Feature",
  "properties": {
    "iso:country":"US",
    "sg:address":"500 Spruce St Rm 203",
    "sg:city":"San Francisco",
    "sg:classifiers":[
        {
            "category":"Health Services",
            "subcategory":"Doctor",
            "type":"Services"
        },
        {
            "category":"Health Services",
            "subcategory":"Dentist",
            "type":"Services"
        }
    ],
    "sg:phone":"+1 415 752 5244",
    "sg:postcode":"94118",
    "sg:province":"CA",
    "wof:name":"Tran Hao C DMD",
    "wof:placetype":"venue"
},
  "geometry": {"coordinates":[-122.45338700000001,37.786416],"type":"Point"}
}