{
  "type": "Feature",
  "properties": {
    "addr:full":"4130 N Viking Way Long Beach CA 90808",
    "addr:housenumber":"4130",
    "addr:postcode":"90808",
    "addr:street":"N Viking Way",
    "iso:country":"US",
    "sg:address":"4130 N Viking Way",
    "sg:city":"Long Beach",
    "sg:classifiers":[
        {
            "category":"Health Services",
            "subcategory":"Optometrist",
            "type":"Services"
        }
    ],
    "sg:phone":"+1 562 982 1596",
    "sg:postcode":"90808",
    "sg:province":"CA",
    "wof:name":"Kara M Takeda OD",
    "wof:placetype":"venue"
},
  "geometry": {"coordinates":[-118.126266,33.832832],"type":"Point"}
}