{
  "type": "Feature",
  "properties": {
    "iso:country":"US",
    "sg:address":"1832 Saviers Rd",
    "sg:city":"Oxnard",
    "sg:classifiers":[
        {
            "category":"Shopping",
            "type":"Retail Goods"
        }
    ],
    "sg:phone":"+1 805 487 2717",
    "sg:postcode":"93033",
    "sg:province":"CA",
    "sg:tags":[
        "repair",
        "calculator",
        "rent",
        "typewriter"
    ],
    "wof:name":"Eds Typewritter Service",
    "wof:placetype":"venue"
},
  "geometry": {"coordinates":[-119.177415,34.180754],"type":"Point"}
}