{
  "type": "Feature",
  "properties": {
    "addr:full":"431 Georgia St Vallejo CA 94590",
    "addr:housenumber":"431",
    "addr:postcode":"94590",
    "addr:street":"Georgia St",
    "iso:country":"US",
    "sg:address":"431 Georgia St",
    "sg:city":"Vallejo",
    "sg:classifiers":[
        {
            "category":"Organizations",
            "subcategory":"Professional Association",
            "type":"Services"
        }
    ],
    "sg:phone":"+1 707 648 9336",
    "sg:postcode":"94590",
    "sg:province":"CA",
    "wof:name":"Redmen Building",
    "wof:placetype":"venue"
},
  "geometry": {"coordinates":[-122.255353,38.101028],"type":"Point"}
}