{
  "type": "Feature",
  "properties": {
    "addr:full":"448 S Hill St Ste 1304 Los Angeles CA 90013",
    "addr:housenumber":"448",
    "addr:postcode":"90013",
    "addr:street":"S Hill St Ste 1304",
    "iso:country":"US",
    "sg:address":"448 S Hill St Ste 1304",
    "sg:city":"Los Angeles",
    "sg:classifiers":[
        {
            "category":"Shopping",
            "subcategory":"Jewelry",
            "type":"Retail Goods"
        }
    ],
    "sg:phone":"+1 213 892 0888",
    "sg:postcode":"90013",
    "sg:province":"CA",
    "wof:name":"Rafi's Jewelry Mfg Inc",
    "wof:placetype":"venue"
},
  "geometry": {"coordinates":[-118.25099899999999,34.0495],"type":"Point"}
}