{
  "type": "Feature",
  "properties": {
    "addr:full":"5775 Lemon Hill Ave Sacramento CA 95824",
    "addr:housenumber":"5775",
    "addr:postcode":"95824",
    "addr:street":"Lemon Hill Ave",
    "iso:country":"US",
    "sg:address":"5775 Lemon Hill Ave",
    "sg:city":"Sacramento",
    "sg:classifiers":[
        {
            "category":"Shopping",
            "subcategory":"Beauty & Cosmetics",
            "type":"Retail Goods"
        }
    ],
    "sg:phone":"+1 916 421 6075",
    "sg:postcode":"95824",
    "sg:province":"CA",
    "sg:tags":[
        "supply"
    ],
    "wof:name":"Millennium Beauty Supply",
    "wof:placetype":"venue"
},
  "geometry": {"coordinates":[-121.439003,38.5159],"type":"Point"}
}