{
  "type": "Feature",
  "properties": {
    "iso:country":"US",
    "sg:address":"387 Hillcrest Ave",
    "sg:city":"Marina",
    "sg:classifiers":[
        {
            "category":"Building & Trades",
            "subcategory":"Landscaping Services",
            "type":"Services"
        }
    ],
    "sg:phone":"+1 831 384 1873",
    "sg:postcode":"93933",
    "sg:province":"CA",
    "sg:tags":[
        "lawn",
        "maintenance",
        "grounds"
    ],
    "wof:name":"Te Oriental Garden Services",
    "wof:placetype":"venue"
},
  "geometry": {"coordinates":[-121.79088900000001,36.676488],"type":"Point"}
}