{
  "type": "Feature",
  "properties": {
    "iso:country":"US",
    "sg:address":"3825 Rosin Court",
    "sg:city":"Sacramento",
    "sg:classifiers":[
        {
            "category":"Travel",
            "subcategory":"Hotels & Motels",
            "type":"Entertainment"
        }
    ],
    "sg:phone":"+1 916 920 8199",
    "sg:postcode":"95834",
    "sg:province":"CA",
    "wof:name":"Extended Stayamerica",
    "wof:placetype":"venue"
},
  "geometry": {"coordinates":[-121.475673,38.637436],"type":"Point"}
}