{
  "type": "Feature",
  "properties": {
    "addr:full":"39211 Chalfont Ln Palmdale CA 93551",
    "addr:postcode":"39211;ca 93551",
    "addr:street":"Chalfont Ln",
    "iso:country":"US",
    "sg:address":"39211 Chalfont Ln",
    "sg:city":"Palmdale",
    "sg:classifiers":[
        {
            "category":"Education",
            "subcategory":"Special Training",
            "type":"Public Place"
        }
    ],
    "sg:phone":"+1 661 645 0283",
    "sg:postcode":"93551",
    "sg:province":"CA",
    "sg:tags":[
        "instruction",
        "music"
    ],
    "wof:name":"KERI Purpura's Music Studio",
    "wof:placetype":"venue"
},
  "geometry": {"coordinates":[-118.186843,34.595638],"type":"Point"}
}