{
  "type": "Feature",
  "properties": {
    "iso:country":"US",
    "sg:address":"1844 Timber Trl",
    "sg:city":"Vista",
    "sg:classifiers":[
        {
            "category":"Professional",
            "subcategory":"Business Services",
            "type":"Services"
        }
    ],
    "sg:phone":"+1 760 598 8394",
    "sg:postcode":"92081",
    "sg:province":"CA",
    "wof:name":"Pharmacy Business Svc",
    "wof:placetype":"venue"
},
  "geometry": {"coordinates":[-117.256353,33.160342],"type":"Point"}
}