{
  "type": "Feature",
  "properties": {
    "addr:full":"8530 Torbett Way Riverside CA 92504",
    "addr:postcode":"8530;92504",
    "addr:street":"Torbett Way",
    "iso:country":"US",
    "sg:address":"8530 Torbett Way",
    "sg:city":"Riverside",
    "sg:classifiers":[
        {
            "category":"Local Transit",
            "type":"Transportation"
        }
    ],
    "sg:phone":"+1 951 359 7322",
    "sg:postcode":"92504",
    "sg:province":"CA",
    "sg:tags":[
        "limousine"
    ],
    "wof:name":"Exclusively Yours Limousine",
    "wof:placetype":"venue"
},
  "geometry": {"coordinates":[-117.433545,33.935882],"type":"Point"}
}