{
  "type": "Feature",
  "properties": {
    "addr:full":"1099 Bedford Dr Camarillo CA 93010",
    "addr:housenumber":"1099",
    "addr:postcode":"93010",
    "addr:street":"Bedford Dr",
    "iso:country":"US",
    "sg:address":"1099 Bedford Dr",
    "sg:city":"Camarillo",
    "sg:classifiers":[
        {
            "category":"Education",
            "subcategory":"School",
            "type":"Public Place"
        }
    ],
    "sg:phone":"+1 805 482 1954",
    "sg:postcode":"93010",
    "sg:province":"CA",
    "sg:tags":[
        "high",
        "middle",
        "elementary"
    ],
    "wof:name":"El Descanso Elementary School",
    "wof:placetype":"venue"
},
  "geometry": {"coordinates":[-119.046997,34.228001],"type":"Point"}
}