{
  "type": "Feature",
  "properties": {
    "iso:country":"US",
    "sg:address":"13819 Slover Ave",
    "sg:city":"Fontana",
    "sg:classifiers":[
        {
            "category":"Freight",
            "type":"Transportation"
        }
    ],
    "sg:phone":"+1 909 574 0122",
    "sg:postcode":"92337",
    "sg:province":"CA",
    "sg:tags":[
        "trucking"
    ],
    "wof:name":"So Cal Transport",
    "wof:placetype":"venue"
},
  "geometry": {"coordinates":[-117.504428,34.062741],"type":"Point"}
}