{
  "type": "Feature",
  "properties": {
    "iso:country":"US",
    "sg:address":"199 Potrero Ave",
    "sg:city":"San Francisco",
    "sg:classifiers":[
        {
            "category":"Personal",
            "type":"Services"
        },
        {
            "category":"Home & Garden",
            "subcategory":"Building Materials",
            "type":"Retail Goods"
        }
    ],
    "sg:phone":"+1 415 431 6727",
    "sg:postcode":"94103",
    "sg:province":"CA",
    "sg:tags":[
        "equipment",
        "lighting",
        "fixture"
    ],
    "sg:website":"dogfork.com",
    "wof:name":"Dogfork Lamp Arts",
    "wof:placetype":"venue"
},
  "geometry": {"coordinates":[-122.407679,37.767107],"type":"Point"}
}