{
  "type": "Feature",
  "properties": {
    "addr:full":"1390 Ryan Ridge Rd El Cajon CA 92021",
    "addr:housenumber":"1390",
    "addr:postcode":"92021",
    "addr:street":"Ryan Ridge Rd",
    "iso:country":"US",
    "sg:address":"1390 Ryan Ridge Rd",
    "sg:city":"El Cajon",
    "sg:classifiers":[
        {
            "category":"Real Estate",
            "subcategory":"Real Estate Operator",
            "type":"Services"
        }
    ],
    "sg:phone":"+1 619 441 9322",
    "sg:postcode":"92021",
    "sg:province":"CA",
    "sg:tags":[
        "building",
        "nonresidential"
    ],
    "wof:name":"Boxer Enterprises Inc",
    "wof:placetype":"venue"
},
  "geometry": {"coordinates":[-116.847264,32.828611],"type":"Point"}
}