{
  "type": "Feature",
  "properties": {
    "addr:full":"15475 Hampton Ct Fontana CA 92337",
    "addr:housenumber":"15475",
    "addr:postcode":"92337",
    "addr:street":"Hampton Ct",
    "iso:country":"US",
    "sg:address":"15475 Hampton Ct",
    "sg:city":"Fontana",
    "sg:classifiers":[
        {
            "category":"Banks & Credit Unions",
            "subcategory":"Bank",
            "type":"Services"
        }
    ],
    "sg:phone":"+1 909 429 4419",
    "sg:postcode":"92337",
    "sg:province":"CA",
    "sg:tags":[
        "loan",
        "real estate"
    ],
    "wof:name":"R & B Home Loans Inc",
    "wof:placetype":"venue"
},
  "geometry": {"coordinates":[-117.467741,34.044746],"type":"Point"}
}