{
  "type": "Feature",
  "properties": {
    "iso:country":"US",
    "sg:address":"1160 Erickson Rd",
    "sg:city":"Concord",
    "sg:classifiers":[
        {
            "category":"Retail",
            "subcategory":"Auto Repair",
            "type":"Services"
        }
    ],
    "sg:phone":"+1 925 827 4848",
    "sg:postcode":"94520",
    "sg:province":"CA",
    "sg:tags":[
        "body",
        "automobile",
        "painting"
    ],
    "wof:name":"Professional Automotive Entrps",
    "wof:placetype":"venue"
},
  "geometry": {"coordinates":[-122.037727,37.958447],"type":"Point"}
}