{
  "type": "Feature",
  "properties": {
    "addr:full":"808 W Commonwealth Ave Fullerton CA 92832",
    "addr:housenumber":"808",
    "addr:postcode":"92832",
    "addr:street":"W Commonwealth Ave",
    "iso:country":"US",
    "sg:address":"808 W Commonwealth Ave",
    "sg:city":"Fullerton",
    "sg:classifiers":[
        {
            "category":"Sports & Exercise",
            "subcategory":"Gym",
            "type":"Entertainment"
        }
    ],
    "sg:phone":"+1 714 870 9800",
    "sg:postcode":"92832",
    "sg:province":"CA",
    "wof:name":"SOCO Sports Club",
    "wof:placetype":"venue"
},
  "geometry": {"coordinates":[-117.93966899999999,33.870202],"type":"Point"}
}