{
  "type": "Feature",
  "properties": {
    "iso:country":"US",
    "sg:address":"22097 Bonness Rd",
    "sg:city":"Sonoma",
    "sg:classifiers":[
        {
            "category":"Farming",
            "subcategory":"Vineyard",
            "type":"Manufacturing & Wholesale Goods"
        }
    ],
    "sg:phone":"+1 707 996 6245",
    "sg:postcode":"95476",
    "sg:province":"CA",
    "sg:tags":[
        "grape"
    ],
    "wof:name":"Bryton Vineyards",
    "wof:placetype":"venue"
},
  "geometry": {"coordinates":[-122.480586,38.245158],"type":"Point"}
}