{
  "type": "Feature",
  "properties": {
    "iso:country":"US",
    "sg:address":"411 S 3rd Ave",
    "sg:city":"Arcadia",
    "sg:classifiers":[
        {
            "category":"Travel",
            "subcategory":"Travel Agent",
            "type":"Entertainment"
        }
    ],
    "sg:phone":"+1 626 446 9368",
    "sg:postcode":"91006",
    "sg:province":"CA",
    "sg:tags":[
        "operator",
        "tour"
    ],
    "wof:name":"Wonder Tours USA",
    "wof:placetype":"venue"
},
  "geometry": {"coordinates":[-118.02360899999999,34.134762],"type":"Point"}
}