{
  "type": "Feature",
  "properties": {
    "iso:country":"US",
    "sg:address":"2978 Diamond St",
    "sg:city":"Rosamond",
    "sg:classifiers":[
        {
            "category":"Real Estate",
            "subcategory":"Real Estate Agent",
            "type":"Services"
        }
    ],
    "sg:phone":"+1 661 256 2200",
    "sg:postcode":"93560",
    "sg:province":"CA",
    "wof:name":"A V Land",
    "wof:placetype":"venue"
},
  "geometry": {"coordinates":[-118.16454299999999,34.864112],"type":"Point"}
}