{
  "type": "Feature",
  "properties": {
    "iso:country":"US",
    "sg:address":"28831 Shady Pl",
    "sg:city":"Laguna Beach",
    "sg:classifiers":[
        {
            "category":"Parking",
            "type":"Transportation"
        }
    ],
    "sg:phone":"+1 949 497 3301",
    "sg:postcode":"92651",
    "sg:province":"CA",
    "sg:tags":[
        "attendant"
    ],
    "wof:name":"Class Act Valet",
    "wof:placetype":"venue"
},
  "geometry": {"coordinates":[-117.752889,33.54418],"type":"Point"}
}