{
  "type": "Feature",
  "properties": {
    "iso:country":"US",
    "sg:address":"1545 S Garey Ave",
    "sg:city":"Pomona",
    "sg:classifiers":[
        {
            "category":"Food & Beverages",
            "subcategory":"Bakery",
            "type":"Retail Goods"
        }
    ],
    "sg:phone":"+1 909 623 8329",
    "sg:postcode":"91766",
    "sg:province":"CA",
    "sg:tags":[
        "doughnut"
    ],
    "wof:name":"Sunshine Donut",
    "wof:placetype":"venue"
},
  "geometry": {"coordinates":[-117.749672,34.042952],"type":"Point"}
}