{
  "type": "Feature",
  "properties": {
    "iso:country":"US",
    "sg:address":"1214 N Parker St",
    "sg:city":"Orange",
    "sg:classifiers":[
        {
            "category":"Food & Beverages",
            "subcategory":"Groceries & Convenience Stores",
            "type":"Retail Goods"
        }
    ],
    "sg:phone":"+1 714 315 6448",
    "sg:postcode":"92867",
    "sg:province":"CA",
    "wof:name":"Moms Specialty Food",
    "wof:placetype":"venue"
},
  "geometry": {"coordinates":[-117.859832,33.808797],"type":"Point"}
}