{
  "type": "Feature",
  "properties": {
    "iso:country":"US",
    "sg:address":"2359 Harrison St",
    "sg:city":"Oakland",
    "sg:classifiers":[
        {
            "category":"Autos & Motor Vehicles",
            "subcategory":"Auto Supplies",
            "type":"Retail Goods"
        }
    ],
    "sg:phone":"+1 510 451 6600",
    "sg:postcode":"94612",
    "sg:province":"CA",
    "sg:tags":[
        "tire"
    ],
    "wof:name":"Wheel Works",
    "wof:placetype":"venue"
},
  "geometry": {"coordinates":[-122.262011,37.812542],"type":"Point"}
}