{
  "type": "Feature",
  "properties": {
    "iso:country":"US",
    "sg:address":"7358 Riverton Ave",
    "sg:city":"Sun Valley",
    "sg:classifiers":[
        {
            "category":"Building & Trades",
            "subcategory":"Construction",
            "type":"Services"
        }
    ],
    "sg:phone":"+1 818 255 3787",
    "sg:postcode":"91352",
    "sg:province":"CA",
    "sg:tags":[
        "coping",
        "plastering",
        "tiling",
        "pool",
        "swimming"
    ],
    "wof:name":"Zenner Pools",
    "wof:placetype":"venue"
},
  "geometry": {"coordinates":[-118.365741,34.202895],"type":"Point"}
}