{
  "type": "Feature",
  "properties": {
    "addr:full":"616 Park Ln Madera CA 93637",
    "addr:housenumber":"616",
    "addr:postcode":"93637",
    "addr:street":"Park Ln",
    "iso:country":"US",
    "sg:address":"616 Park Ln",
    "sg:city":"Madera",
    "sg:classifiers":[
        {
            "category":"Farming",
            "subcategory":"Farm",
            "type":"Manufacturing & Wholesale Goods"
        }
    ],
    "sg:phone":"+1 559 673 0437",
    "sg:postcode":"93637",
    "sg:province":"CA",
    "wof:name":"Ww Pitman Farms Llp",
    "wof:placetype":"venue"
},
  "geometry": {"coordinates":[-120.07064099999999,36.960785],"type":"Point"}
}