{
  "type": "Feature",
  "properties": {
    "addr:full":"3150 Hilltop Mall Rd Richmond CA 94806",
    "addr:housenumber":"3150",
    "addr:postcode":"94806",
    "addr:street":"Hilltop Mall Rd",
    "iso:country":"US",
    "sg:address":"3150 Hilltop Mall Rd",
    "sg:city":"Richmond",
    "sg:classifiers":[
        {
            "category":"Professional",
            "subcategory":"Lawyer & Legal Services",
            "type":"Services"
        }
    ],
    "sg:phone":"+1 510 262 9343",
    "sg:postcode":"94806",
    "sg:province":"CA",
    "sg:tags":[
        "attorney"
    ],
    "wof:name":"Charles V Stebley",
    "wof:placetype":"venue"
},
  "geometry": {"coordinates":[-122.32430100000001,37.980861],"type":"Point"}
}