{
  "type": "Feature",
  "properties": {
    "iso:country":"US",
    "sg:address":"1770 Kofford Rd",
    "sg:city":"Gridley",
    "sg:classifiers":[
        {
            "category":"Building & Trades",
            "subcategory":"Construction",
            "type":"Services"
        }
    ],
    "sg:phone":"+1 530 846 3981",
    "sg:postcode":"95948",
    "sg:province":"CA",
    "sg:tags":[
        "roofing",
        "industrial",
        "contractors-commercial",
        "contractor"
    ],
    "wof:name":"Bill's Roofing",
    "wof:placetype":"venue"
},
  "geometry": {"coordinates":[-121.718433,39.368528],"type":"Point"}
}