{
  "type": "Feature",
  "properties": {
    "addr:full":"7255 Alvarado Rd La Mesa CA 91941",
    "addr:housenumber":"7255",
    "addr:postcode":"91941",
    "addr:street":"Alvarado Rd",
    "iso:country":"US",
    "sg:address":"7255 Alvarado Rd",
    "sg:city":"La Mesa",
    "sg:classifiers":[
        {
            "category":"Local Transit",
            "type":"Transportation"
        }
    ],
    "sg:phone":"+1 619 233 3004",
    "sg:postcode":"91941",
    "sg:province":"CA",
    "sg:tags":[
        "public"
    ],
    "sg:website":"www.sdcommute.com",
    "wof:name":"70th Street Green Line Station",
    "wof:placetype":"venue"
},
  "geometry": {"coordinates":[-117.041218,32.77224],"type":"Point"}
}