{
  "type": "Feature",
  "properties": {
    "addr:full":"5535 Balboa Blvd Encino CA 91316",
    "addr:housenumber":"5535",
    "addr:postcode":"91316",
    "addr:street":"Balboa Blvd",
    "iso:country":"US",
    "sg:address":"5535 Balboa Blvd",
    "sg:city":"Encino",
    "sg:classifiers":[
        {
            "category":"Professional",
            "subcategory":"Accounting & Tax Preparation",
            "type":"Services"
        }
    ],
    "sg:phone":"+1 818 981 4773",
    "sg:postcode":"91316",
    "sg:province":"CA",
    "sg:tags":[
        "return",
        "preparation-business"
    ],
    "wof:name":"Steven Alper Sj Alper Tax & Bookinping",
    "wof:placetype":"venue"
},
  "geometry": {"coordinates":[-118.501167,34.171322],"type":"Point"}
}