{
  "type": "Feature",
  "properties": {
    "addr:full":"1681 Lewis Ln Tulare CA 93274",
    "addr:housenumber":"1681",
    "addr:postcode":"93274",
    "addr:street":"Lewis Ln",
    "iso:country":"US",
    "sg:address":"1681 Lewis Ln",
    "sg:city":"Tulare",
    "sg:classifiers":[
        {
            "category":"Manufacturing",
            "subcategory":"Electronics",
            "type":"Manufacturing & Wholesale Goods"
        }
    ],
    "sg:phone":"+1 559 688 5303",
    "sg:postcode":"93274",
    "sg:province":"CA",
    "sg:tags":[
        "equipment",
        "mfg",
        "home"
    ],
    "wof:name":"Holy Grail Audio",
    "wof:placetype":"venue"
},
  "geometry": {"coordinates":[-119.298374,36.229795],"type":"Point"}
}