{
  "type": "Feature",
  "properties": {
    "addr:full":"2432 Mckinley Ave Berkeley CA 94703",
    "addr:housenumber":"2432",
    "addr:postcode":"94703",
    "addr:street":"Mckinley Ave",
    "iso:country":"US",
    "sg:address":"2432 Mckinley Ave",
    "sg:city":"Berkeley",
    "sg:classifiers":[
        {
            "category":"Recreation",
            "type":"Entertainment"
        }
    ],
    "sg:phone":"+1 510 843 6157",
    "sg:postcode":"94703",
    "sg:province":"CA",
    "sg:tags":[
        "camps-recreational"
    ],
    "sg:website":"http://www.campchrysalis.com",
    "wof:name":"Camp Chrysalis",
    "wof:placetype":"venue"
},
  "geometry": {"coordinates":[-122.27340100000001,37.864429],"type":"Point"}
}