{
  "type": "Feature",
  "properties": {
    "iso:country":"US",
    "sg:address":"2591 61st Ave",
    "sg:city":"Oakland",
    "sg:classifiers":[
        {
            "category":"Transit Center",
            "subcategory":"Freight",
            "type":"Transportation"
        },
        {
            "category":"Freight",
            "type":"Transportation"
        }
    ],
    "sg:phone":"+1 510 638 7768",
    "sg:postcode":"94605",
    "sg:province":"CA",
    "sg:tags":[
        "local",
        "trucking-motor",
        "trucking"
    ],
    "wof:name":"Doc Transportation",
    "wof:placetype":"venue"
},
  "geometry": {"coordinates":[-122.18876,37.770616],"type":"Point"}
}