{
  "type": "Feature",
  "properties": {
    "iso:country":"US",
    "sg:address":"610 W Tefft St",
    "sg:city":"Nipomo",
    "sg:classifiers":[
        {
            "category":"Shopping",
            "subcategory":"Pharmacy",
            "type":"Retail Goods"
        }
    ],
    "sg:phone":"+1 805 929 2740",
    "sg:postcode":"93444",
    "sg:province":"CA",
    "wof:name":"Sav-On Drugs",
    "wof:placetype":"venue"
},
  "geometry": {"coordinates":[-120.485461,35.036379],"type":"Point"}
}