{
  "type": "Feature",
  "properties": {
    "addr:full":"131 S Central Ave Los Angeles CA 90012",
    "addr:housenumber":"131",
    "addr:postcode":"90012",
    "addr:street":"S Central Ave",
    "iso:country":"US",
    "sg:address":"131 S Central Ave",
    "sg:city":"Los Angeles",
    "sg:classifiers":[
        {
            "category":"Juice Bar",
            "subcategory":"None",
            "type":"Food & Drink"
        }
    ],
    "sg:phone":"+1 213 626 2848",
    "sg:postcode":"90012",
    "sg:province":"CA",
    "sg:tags":[
        "smoothy"
    ],
    "sg:website":"www.robeks.com",
    "wof:name":"Robeks Juice",
    "wof:placetype":"venue"
},
  "geometry": {"coordinates":[-118.23917299999999,34.04873],"type":"Point"}
}