{
  "type": "Feature",
  "properties": {
    "addr:full":"14581 Golders Green Ln Westminster CA 92683",
    "addr:housenumber":"14581",
    "addr:postcode":"92683",
    "addr:street":"Golders Green Ln",
    "iso:country":"US",
    "sg:address":"14581 Golders Green Ln",
    "sg:city":"Westminster",
    "sg:classifiers":[
        {
            "category":"Shopping",
            "subcategory":"Florist",
            "type":"Retail Goods"
        }
    ],
    "sg:phone":"+1 714 531 5600",
    "sg:postcode":"92683",
    "sg:province":"CA",
    "wof:name":"Paradise Delight Florist",
    "wof:placetype":"venue"
},
  "geometry": {"coordinates":[-117.95246400000001,33.751031],"type":"Point"}
}