{
  "type": "Feature",
  "properties": {
    "addr:full":"706 Oak St San Francisco CA 94117",
    "addr:housenumber":"706",
    "addr:postcode":"94117",
    "addr:street":"Oak St",
    "iso:country":"US",
    "sg:address":"706 Oak St",
    "sg:city":"San Francisco",
    "sg:classifiers":[
        {
            "category":"Building & Trades",
            "subcategory":"Equipment Rental",
            "type":"Services"
        }
    ],
    "sg:phone":"+1 415 621 2616",
    "sg:postcode":"94117",
    "sg:province":"CA",
    "sg:tags":[
        "yard"
    ],
    "wof:name":"Mortimer Brothers",
    "wof:placetype":"venue"
},
  "geometry": {"coordinates":[-122.432407,37.773848],"type":"Point"}
}