{
  "type": "Feature",
  "properties": {
    "addr:full":"1080 F St Arcata CA 95521",
    "addr:housenumber":"1080",
    "addr:postcode":"95521",
    "addr:street":"F St",
    "iso:country":"US",
    "sg:address":"1080 F St",
    "sg:city":"Arcata",
    "sg:classifiers":[
        {
            "category":"Retail",
            "subcategory":"Self-service Laundry",
            "type":"Services"
        }
    ],
    "sg:phone":"+1 707 822 1317",
    "sg:postcode":"95521",
    "sg:province":"CA",
    "wof:name":"Arcata Speed Wash",
    "wof:placetype":"venue"
},
  "geometry": {"coordinates":[-124.08422899999999,40.869498],"type":"Point"}
}