{
  "type": "Feature",
  "properties": {
    "iso:country":"US",
    "sg:address":"6218 Griffith Ave",
    "sg:city":"Marysville",
    "sg:phone":"+1 530 743 2354",
    "sg:postcode":"95901",
    "sg:province":"CA",
    "sg:tags":[
        "farm",
        "grain",
        "cash",
        "equine"
    ],
    "wof:name":"Roy Staas",
    "wof:placetype":"venue"
},
  "geometry": {"coordinates":[-121.52377799999999,39.134666],"type":"Point"}
}