{
  "type": "Feature",
  "properties": {
    "addr:full":"999 W Cutting Blvd Ste 15 Richmond CA 94804",
    "addr:housenumber":"999;15",
    "addr:postcode":"94804",
    "addr:street":"W Cutting Blvd Ste",
    "iso:country":"US",
    "sg:address":"999 W Cutting Blvd Ste 15",
    "sg:city":"Richmond",
    "sg:phone":"+1 510 237 1132",
    "sg:postcode":"94804",
    "sg:province":"CA",
    "wof:name":"Litton Cycles",
    "wof:placetype":"venue"
},
  "geometry": {"coordinates":[-122.380306,37.925289],"type":"Point"}
}