{
  "type": "Feature",
  "properties": {
    "addr:full":"724 H St Petaluma CA 94952",
    "addr:housenumber":"724",
    "addr:postcode":"94952",
    "addr:street":"H St",
    "iso:country":"US",
    "sg:address":"724 H St",
    "sg:city":"Petaluma",
    "sg:classifiers":[
        {
            "category":"Building & Trades",
            "subcategory":"Construction",
            "type":"Services"
        }
    ],
    "sg:phone":"+1 707 782 1044",
    "sg:postcode":"94952",
    "sg:province":"CA",
    "sg:tags":[
        "instrument",
        "contractor",
        "musical",
        "mfg"
    ],
    "wof:name":"String Bass",
    "wof:placetype":"venue"
},
  "geometry": {"coordinates":[-122.634574,38.226368],"type":"Point"}
}