{
  "type": "Feature",
  "properties": {
    "addr:full":"1818 Palo Verde Ave Long Beach CA 90815",
    "addr:housenumber":"1818",
    "addr:postcode":"90815",
    "addr:street":"Palo Verde Ave",
    "iso:country":"US",
    "sg:address":"1818 Palo Verde Ave",
    "sg:city":"Long Beach",
    "sg:classifiers":[
        {
            "category":"Personal",
            "subcategory":"Beauty Salon",
            "type":"Services"
        }
    ],
    "sg:phone":"+1 562 594 4247",
    "sg:postcode":"90815",
    "sg:province":"CA",
    "wof:name":"Gary Mc Henry Salon",
    "wof:placetype":"venue"
},
  "geometry": {"coordinates":[-118.10787500000001,33.79042],"type":"Point"}
}