{
  "type": "Feature",
  "properties": {
    "iso:country":"US",
    "sg:address":"3264 Cahuenga Blvd W",
    "sg:city":"Los Angeles",
    "sg:classifiers":[
        {
            "category":"Real Estate",
            "subcategory":"Real Estate Agent",
            "type":"Services"
        }
    ],
    "sg:phone":"+1 323 851 7172",
    "sg:postcode":"90068",
    "sg:province":"CA",
    "wof:name":"Moizel Investments",
    "wof:placetype":"venue"
},
  "geometry": {"coordinates":[-118.349518,34.130098],"type":"Point"}
}