{
  "type": "Feature",
  "properties": {
    "addr:full":"5627 E Beverly Blvd Los Angeles CA 90022",
    "addr:housenumber":"5627",
    "addr:postcode":"90022",
    "addr:street":"E Beverly Blvd",
    "iso:country":"US",
    "sg:address":"5627 E Beverly Blvd",
    "sg:city":"Los Angeles",
    "sg:classifiers":[
        {
            "category":"Organizations",
            "subcategory":"Community Association",
            "type":"Services"
        }
    ],
    "sg:phone":"+1 323 728 7651",
    "sg:postcode":"90022",
    "sg:province":"CA",
    "sg:tags":[
        "military"
    ],
    "wof:name":"Veterans Of Foreign Wars 2317",
    "wof:placetype":"venue"
},
  "geometry": {"coordinates":[-118.14446599999999,34.026708],"type":"Point"}
}