{
  "type": "Feature",
  "properties": {
    "addr:full":"10551 Bloomfield St Los Alamitos CA 90720",
    "addr:housenumber":"10551",
    "addr:postcode":"90720",
    "addr:street":"Bloomfield St",
    "iso:country":"US",
    "sg:address":"10551 Bloomfield St",
    "sg:city":"Los Alamitos",
    "sg:classifiers":[
        {
            "category":"Communications",
            "type":"Services"
        }
    ],
    "sg:phone":"+1 714 722 0243",
    "sg:postcode":"90720",
    "sg:province":"CA",
    "sg:tags":[
        "recording",
        "rehearsal",
        "studio"
    ],
    "sg:website":"myspace.com/selahrecording",
    "wof:name":"Selah Recording",
    "wof:placetype":"venue"
},
  "geometry": {"coordinates":[-118.06300400000001,33.809601],"type":"Point"}
}