{
  "type": "Feature",
  "properties": {
    "addr:full":"3005 Ramona Rd Atascadero CA 93422",
    "addr:housenumber":"3005",
    "addr:postcode":"93422",
    "addr:street":"Ramona Rd",
    "iso:country":"US",
    "sg:address":"3005 Ramona Rd",
    "sg:city":"Atascadero",
    "sg:classifiers":[
        {
            "category":"Building & Trades",
            "subcategory":"Construction",
            "type":"Services"
        }
    ],
    "sg:phone":"+1 805 464 1012",
    "sg:postcode":"93422",
    "sg:province":"CA",
    "sg:tags":[
        "wallcoverings-installation",
        "wallpaper",
        "painting",
        "contractor"
    ],
    "wof:name":"D H R Painting",
    "wof:placetype":"venue"
},
  "geometry": {"coordinates":[-120.693764,35.503576],"type":"Point"}
}