{
  "type": "Feature",
  "properties": {
    "addr:full":"3036 Clarence Ct Chico CA 95973",
    "addr:housenumber":"3036",
    "addr:postcode":"95973",
    "addr:street":"Clarence Ct",
    "iso:country":"US",
    "sg:address":"3036 Clarence Ct",
    "sg:city":"Chico",
    "sg:classifiers":[
        {
            "category":"Wholesale",
            "subcategory":"Auto Parts",
            "type":"Manufacturing & Wholesale Goods"
        }
    ],
    "sg:phone":"+1 530 345 9219",
    "sg:postcode":"95973",
    "sg:province":"CA",
    "sg:tags":[
        "automotive",
        "equipment"
    ],
    "wof:name":"C & D Enterprises",
    "wof:placetype":"venue"
},
  "geometry": {"coordinates":[-121.873499,39.761988],"type":"Point"}
}