{
  "type": "Feature",
  "properties": {
    "addr:full":"1615 Innes Ave San Francisco CA 94124",
    "addr:housenumber":"1615",
    "addr:postcode":"94124",
    "addr:street":"Innes Ave",
    "iso:country":"US",
    "sg:address":"1615 Innes Ave",
    "sg:city":"San Francisco",
    "sg:classifiers":[
        {
            "category":"Wholesale",
            "subcategory":"Electrical",
            "type":"Manufacturing & Wholesale Goods"
        }
    ],
    "sg:phone":"+1 415 282 1118",
    "sg:postcode":"94124",
    "sg:province":"CA",
    "sg:tags":[
        "lighting",
        "fixture"
    ],
    "wof:name":"L & B Light Box LLC",
    "wof:placetype":"venue"
},
  "geometry": {"coordinates":[-122.390687,37.740378],"type":"Point"}
}