{
  "type": "Feature",
  "properties": {
    "addr:full":"1670 Connecticut Dr Redwood City CA 94061",
    "addr:housenumber":"1670",
    "addr:postcode":"94061",
    "addr:street":"Connecticut Dr",
    "iso:country":"US",
    "sg:address":"1670 Connecticut Dr",
    "sg:city":"Redwood City",
    "sg:classifiers":[
        {
            "category":"Building & Trades",
            "subcategory":"Cleaning & Sanitation",
            "type":"Services"
        }
    ],
    "sg:phone":"+1 650 366 4734",
    "sg:postcode":"94061",
    "sg:province":"CA",
    "sg:tags":[
        "house"
    ],
    "wof:name":"V & G House Cleaning",
    "wof:placetype":"venue"
},
  "geometry": {"coordinates":[-122.232682,37.457918],"type":"Point"}
}