{
  "type": "Feature",
  "properties": {
    "iso:country":"US",
    "sg:address":"93 Jefferson St",
    "sg:city":"San Francisco",
    "sg:classifiers":[
        {
            "category":"Manufacturing",
            "subcategory":"Leather Goods",
            "type":"Manufacturing & Wholesale Goods"
        }
    ],
    "sg:phone":"+1 415 433 9320",
    "sg:postcode":"94133",
    "sg:province":"CA",
    "wof:name":"D & K Leathers",
    "wof:placetype":"venue"
},
  "geometry": {"coordinates":[-122.412935,37.808538],"type":"Point"}
}