{
  "type": "Feature",
  "properties": {
    "iso:country":"US",
    "sg:address":"513 W 1st St",
    "sg:city":"Rialto",
    "sg:classifiers":[
        {
            "category":"Retail",
            "subcategory":"Repair Shop",
            "type":"Services"
        }
    ],
    "sg:phone":"+1 909 875 6911",
    "sg:postcode":"92376",
    "sg:province":"CA",
    "sg:tags":[
        "equipment"
    ],
    "wof:name":"Classic Mechanical",
    "wof:placetype":"venue"
},
  "geometry": {"coordinates":[-117.383253,34.100484],"type":"Point"}
}