{
  "type": "Feature",
  "properties": {
    "addr:full":"1110 E Market St Salinas CA 93905",
    "addr:housenumber":"1110",
    "addr:postcode":"93905",
    "addr:street":"E Market St",
    "iso:country":"US",
    "sg:address":"1110 E Market St",
    "sg:city":"Salinas",
    "sg:classifiers":[
        {
            "category":"Personal",
            "subcategory":"Beauty Salon",
            "type":"Services"
        }
    ],
    "sg:phone":"+1 831 422 5659",
    "sg:postcode":"93905",
    "sg:province":"CA",
    "wof:name":"Sosi's Hair Salon",
    "wof:placetype":"venue"
},
  "geometry": {"coordinates":[-121.621771,36.676842],"type":"Point"}
}