{
  "type": "Feature",
  "properties": {
    "iso:country":"US",
    "sg:address":"950 Tower Ln",
    "sg:city":"Foster City",
    "sg:classifiers":[
        {
            "category":"Real Estate",
            "subcategory":"Real Estate Services",
            "type":"Services"
        }
    ],
    "sg:phone":"+1 650 357 1792",
    "sg:postcode":"94404",
    "sg:province":"CA",
    "sg:tags":[
        "management",
        "property"
    ],
    "wof:name":"Equity Office",
    "wof:placetype":"venue"
},
  "geometry": {"coordinates":[-122.277,37.558498],"type":"Point"}
}