{
  "type": "Feature",
  "properties": {
    "iso:country":"US",
    "sg:address":"1080 Emeline Ave",
    "sg:city":"Santa Cruz",
    "sg:classifiers":[
        {
            "category":"Government",
            "subcategory":"Office",
            "type":"Public Place"
        }
    ],
    "sg:phone":"+1 831 454 4100",
    "sg:postcode":"95060",
    "sg:province":"CA",
    "sg:tags":[
        "county",
        "program",
        "health"
    ],
    "wof:name":"Santa Cruz Health Ctr",
    "wof:placetype":"venue"
},
  "geometry": {"coordinates":[-122.017633,36.992346],"type":"Point"}
}