{
  "type": "Feature",
  "properties": {
    "iso:country":"US",
    "sg:address":"4949 Calle De Escuela",
    "sg:city":"Santa Clara",
    "sg:classifiers":[
        {
            "category":"Education",
            "subcategory":"School",
            "type":"Public Place"
        }
    ],
    "sg:phone":"+1 408 988 2390",
    "sg:postcode":"95054",
    "sg:province":"CA",
    "sg:tags":[
        "high",
        "middle",
        "elementary"
    ],
    "wof:name":"Santa Clara Unified School District",
    "wof:placetype":"venue"
},
  "geometry": {"coordinates":[-121.96375399999999,37.406303],"type":"Point"}
}