{
  "type": "Feature",
  "properties": {
    "addr:full":"38300 30th St E Palmdale CA 93550",
    "addr:housenumber":"38300",
    "addr:postcode":"ca 93550",
    "addr:street":"30Th St E",
    "iso:country":"US",
    "sg:address":"38300 30th St E",
    "sg:city":"Palmdale",
    "sg:classifiers":[
        {
            "category":"Real Estate",
            "subcategory":"Real Estate Operator",
            "type":"Services"
        }
    ],
    "sg:phone":"+1 661 273 4757",
    "sg:postcode":"93550",
    "sg:province":"CA",
    "sg:tags":[
        "apartment"
    ],
    "wof:name":"Fountains",
    "wof:placetype":"venue"
},
  "geometry": {"coordinates":[-118.076196,34.577259],"type":"Point"}
}