{
  "type": "Feature",
  "properties": {
    "iso:country":"US",
    "sg:address":"504 6th St",
    "sg:city":"Manhattan Beach",
    "sg:classifiers":[
        {
            "category":"Building & Trades",
            "subcategory":"Construction",
            "type":"Services"
        }
    ],
    "sg:phone":"+1 310 379 6700",
    "sg:postcode":"90266",
    "sg:province":"CA",
    "sg:tags":[
        "designer",
        "dealer",
        "pool",
        "swimming"
    ],
    "wof:name":"David Tisherman Visuals Inc",
    "wof:placetype":"venue"
},
  "geometry": {"coordinates":[-118.404567,33.882305],"type":"Point"}
}