{
  "type": "Feature",
  "properties": {
    "iso:country":"US",
    "sg:address":"21481 8th St E",
    "sg:city":"Sonoma",
    "sg:classifiers":[
        {
            "category":"Professional",
            "type":"Services"
        },
        {
            "category":"Professional",
            "subcategory":"Business Services",
            "type":"Services"
        },
        {
            "category":"Manufacturing",
            "subcategory":"Paper Products",
            "type":"Manufacturing & Wholesale Goods"
        }
    ],
    "sg:phone":"+1 707 933 9063",
    "sg:postcode":"95476",
    "sg:province":"CA",
    "sg:tags":[
        "fiber",
        "materials-wholesale",
        "labeling",
        "packaging",
        "boxes-corrugated",
        "manufacturer"
    ],
    "wof:name":"Wineshipping Com",
    "wof:placetype":"venue"
},
  "geometry": {"coordinates":[-122.439899,38.263543],"type":"Point"}
}