{
  "type": "Feature",
  "properties": {
    "addr:full":"6832 Ave 280 Visalia CA 93277",
    "addr:housenumber":"280",
    "addr:postcode":"93277",
    "addr:street":"6832 Ave",
    "iso:country":"US",
    "sg:address":"6832 Ave 280",
    "sg:city":"Visalia",
    "sg:classifiers":[
        {
            "category":"Education",
            "subcategory":"School",
            "type":"Public Place"
        }
    ],
    "sg:phone":"+1 559 730 7491",
    "sg:postcode":"93277",
    "sg:province":"CA",
    "wof:name":"Charter Alternetives Acc",
    "wof:placetype":"venue"
},
  "geometry": {"coordinates":[-119.42036899999999,36.29798],"type":"Point"}
}