{
  "type": "Feature",
  "properties": {
    "iso:country":"US",
    "sg:address":"907 S Hill St",
    "sg:city":"Los Angeles",
    "sg:classifiers":[
        {
            "category":"Recreation",
            "type":"Entertainment"
        }
    ],
    "sg:phone":"+1 213 489 7620",
    "sg:postcode":"90015",
    "sg:province":"CA",
    "sg:tags":[
        "space",
        "venue",
        "event",
        "hall",
        "auditorium"
    ],
    "wof:name":"Nine Zero Seven Club",
    "wof:placetype":"venue"
},
  "geometry": {"coordinates":[-118.258003,34.041901],"type":"Point"}
}