{
  "type": "Feature",
  "properties": {
    "addr:full":"144 Hartnell Pl Sacramento CA 95825",
    "addr:housenumber":"144",
    "addr:postcode":"95825",
    "addr:street":"Hartnell Pl",
    "iso:country":"US",
    "sg:address":"144 Hartnell Pl",
    "sg:city":"Sacramento",
    "sg:classifiers":[
        {
            "category":"Professional",
            "type":"Services"
        }
    ],
    "sg:phone":"+1 916 922 9463",
    "sg:postcode":"95825",
    "sg:province":"CA",
    "wof:name":"Antoine P Song",
    "wof:placetype":"venue"
},
  "geometry": {"coordinates":[-121.41428500000001,38.566356],"type":"Point"}
}