{
  "type": "Feature",
  "properties": {
    "addr:full":"21610 Valley Blvd Walnut CA 91789",
    "addr:housenumber":"21610",
    "addr:postcode":"91789",
    "addr:street":"Valley Blvd",
    "iso:country":"US",
    "sg:address":"21610 Valley Blvd",
    "sg:city":"Walnut",
    "sg:classifiers":[
        {
            "category":"Fast Food",
            "type":"Food & Drink"
        },
        {
            "category":"Restaurant",
            "type":"Food & Drink"
        }
    ],
    "sg:phone":"+1 909 594 8656",
    "sg:postcode":"91789",
    "sg:province":"CA",
    "sg:tags":[
        "chicken",
        "mexican",
        "take"
    ],
    "sg:website":"http://www.elpolloloco.com",
    "wof:name":"El Pollo Loco",
    "wof:placetype":"venue"
},
  "geometry": {"coordinates":[-117.835454,34.027354],"type":"Point"}
}