{
  "type": "Feature",
  "properties": {
    "addr:full":"178 N Main St Porterville CA 93257",
    "addr:housenumber":"178",
    "addr:postcode":"93257",
    "addr:street":"N Main St",
    "iso:country":"US",
    "sg:address":"178 N Main St",
    "sg:city":"Porterville",
    "sg:classifiers":[
        {
            "category":"Food & Beverages",
            "subcategory":"Bakery",
            "type":"Retail Goods"
        }
    ],
    "sg:phone":"+1 559 783 2686",
    "sg:postcode":"93257",
    "sg:province":"CA",
    "sg:tags":[
        "baker"
    ],
    "wof:name":"Cookie Cottage",
    "wof:placetype":"venue"
},
  "geometry": {"coordinates":[-119.01619100000001,36.068112],"type":"Point"}
}