{
  "type": "Feature",
  "properties": {
    "iso:country":"US",
    "sg:address":"325 E Arrow Hwy",
    "sg:city":"San Dimas",
    "sg:classifiers":[
        {
            "category":"Building & Trades",
            "subcategory":"Construction",
            "type":"Services"
        }
    ],
    "sg:phone":"+1 909 592 3981",
    "sg:postcode":"91773",
    "sg:province":"CA",
    "sg:tags":[
        "detector",
        "gas"
    ],
    "wof:name":"Thermo Gas Tech Field Svc Ctr",
    "wof:placetype":"venue"
},
  "geometry": {"coordinates":[-117.80036800000001,34.103027],"type":"Point"}
}