{
  "type": "Feature",
  "properties": {
    "addr:full":"20900 Stevens Creek Blvd. Cupertino CA 95014",
    "addr:housenumber":"20900",
    "addr:postcode":"95014",
    "addr:street":"Stevens Creek Blvd.",
    "iso:country":"US",
    "sg:address":"20900 Stevens Creek Blvd.",
    "sg:city":"Cupertino",
    "sg:classifiers":[
        {
            "category":"Place Of Worship",
            "subcategory":"Church",
            "type":"Public Place"
        }
    ],
    "sg:phone":"+1 408 252 4478",
    "sg:postcode":"95014",
    "sg:province":"CA",
    "sg:website":"www.unionchurch.org",
    "wof:name":"Union Church of Cupertino",
    "wof:placetype":"venue"
},
  "geometry": {"coordinates":[-122.0395,37.321931],"type":"Point"}
}