{
  "type": "Feature",
  "properties": {
    "addr:full":"2744 E. Chapman Ave Orange CA 92869",
    "addr:housenumber":"2744",
    "addr:postcode":"92869",
    "addr:street":"E. Chapman Ave",
    "iso:country":"US",
    "sg:address":"2744 E. Chapman Ave",
    "sg:city":"Orange",
    "sg:classifiers":[
        {
            "category":"Shopping",
            "subcategory":"Hobbies, Toys, & Games",
            "type":"Retail Goods"
        }
    ],
    "sg:phone":"+1 714 538 7191",
    "sg:postcode":"92869",
    "sg:province":"CA",
    "sg:tags":[
        "shop",
        "hobby"
    ],
    "sg:website":"www.steelhawkairsoft.com",
    "wof:name":"Steelhawk Airsoft",
    "wof:placetype":"venue"
},
  "geometry": {"coordinates":[-117.82347799999999,33.787735],"type":"Point"}
}