{
  "type": "Feature",
  "properties": {
    "iso:country":"US",
    "sg:address":"University Student Union 1212 Bellflower Blvd Bldg 243",
    "sg:city":"Long Beach",
    "sg:classifiers":[
        {
            "category":"Ice Cream",
            "type":"Food & Drink"
        }
    ],
    "sg:phone":"+1 562 986 4802",
    "sg:postcode":"90815",
    "sg:province":"CA",
    "sg:tags":[
        "frozen",
        "yogurt"
    ],
    "sg:website":"www.facebook.com/#!/pages/Long-B...",
    "wof:name":"YoGo! Creations",
    "wof:placetype":"venue"
},
  "geometry": {"coordinates":[-118.122375,33.782496],"type":"Point"}
}