{
  "type": "Feature",
  "properties": {
    "iso:country":"US",
    "sg:address":"1147 Broadway St",
    "sg:city":"Fairfield",
    "sg:classifiers":[
        {
            "category":"Organizations",
            "subcategory":"Religious Organization",
            "type":"Services"
        }
    ],
    "sg:phone":"+1 707 428 4620",
    "sg:postcode":"94533",
    "sg:province":"CA",
    "sg:tags":[
        "church"
    ],
    "wof:name":"Berean Baptist Church",
    "wof:placetype":"venue"
},
  "geometry": {"coordinates":[-122.048081,38.245829],"type":"Point"}
}