{
  "type": "Feature",
  "properties": {
    "addr:full":"22256 Summit Hill Dr Lake Forest CA 92630",
    "addr:housenumber":"22256",
    "addr:postcode":"92630",
    "addr:street":"Summit Hill Dr",
    "iso:country":"US",
    "sg:address":"22256 Summit Hill Dr",
    "sg:city":"Lake Forest",
    "sg:classifiers":[
        {
            "category":"Manufacturing",
            "subcategory":"Jewelry",
            "type":"Manufacturing & Wholesale Goods"
        }
    ],
    "sg:phone":"+1 949 458 2563",
    "sg:postcode":"92630",
    "sg:province":"CA",
    "sg:tags":[
        "precious",
        "metal",
        "mfg"
    ],
    "wof:name":"Designs By Mona",
    "wof:placetype":"venue"
},
  "geometry": {"coordinates":[-117.671564,33.640607],"type":"Point"}
}