{
  "type": "Feature",
  "properties": {
    "iso:country":"US",
    "sg:address":"4236 Roseville Rd",
    "sg:city":"North Highlands",
    "sg:classifiers":[
        {
            "category":"Retail",
            "subcategory":"Auto Repair",
            "type":"Services"
        }
    ],
    "sg:phone":"+1 916 481 5943",
    "sg:postcode":"95660",
    "sg:province":"CA",
    "sg:tags":[
        "body",
        "automobile",
        "painting"
    ],
    "wof:name":"Carrera Custom",
    "wof:placetype":"venue"
},
  "geometry": {"coordinates":[-121.398226,38.644423],"type":"Point"}
}