{
  "type": "Feature",
  "properties": {
    "addr:full":"10788 Civic Center Dr Rancho Cucamonga CA 91730",
    "addr:housenumber":"10788",
    "addr:postcode":"91730",
    "addr:street":"Civic Center Dr",
    "iso:country":"US",
    "sg:address":"10788 Civic Center Dr",
    "sg:city":"Rancho Cucamonga",
    "sg:classifiers":[
        {
            "category":"Professional",
            "subcategory":"Lawyer & Legal Services",
            "type":"Services"
        }
    ],
    "sg:phone":"+1 909 989 1777",
    "sg:postcode":"91730",
    "sg:province":"CA",
    "sg:tags":[
        "attorney"
    ],
    "wof:name":"Terrence F Riley Law Offices",
    "wof:placetype":"venue"
},
  "geometry": {"coordinates":[-117.57111399999999,34.101073],"type":"Point"}
}