{
  "type": "Feature",
  "properties": {
    "addr:full":"11359 Deerfield Dr Truckee CA 96161",
    "addr:housenumber":"11359",
    "addr:postcode":"96161",
    "addr:street":"Deerfield Dr",
    "iso:country":"US",
    "sg:address":"11359 Deerfield Dr",
    "sg:city":"Truckee",
    "sg:classifiers":[
        {
            "category":"Shopping",
            "subcategory":"Music",
            "type":"Retail Goods"
        }
    ],
    "sg:phone":"+1 530 582 4015",
    "sg:postcode":"96161",
    "sg:province":"CA",
    "sg:tags":[
        "compact",
        "record",
        "disc",
        "tape"
    ],
    "wof:name":"Joby's Music",
    "wof:placetype":"venue"
},
  "geometry": {"coordinates":[-120.20972399999999,39.320744],"type":"Point"}
}