{
  "type": "Feature",
  "properties": {
    "iso:country":"US",
    "sg:address":"14149 Twin Peaks Rd Ste 10",
    "sg:city":"Poway",
    "sg:classifiers":[
        {
            "category":"Restaurant",
            "type":"Food & Drink"
        }
    ],
    "sg:phone":"+1 858 679 1154",
    "sg:postcode":"92064",
    "sg:province":"CA",
    "sg:tags":[
        "mexican"
    ],
    "wof:name":"El Ranchito Taco Shop",
    "wof:placetype":"venue"
},
  "geometry": {"coordinates":[-117.024384,32.978123],"type":"Point"}
}