{
  "type": "Feature",
  "properties": {
    "iso:country":"US",
    "sg:address":"8536 Elder Creek Rd",
    "sg:city":"Sacramento",
    "sg:classifiers":[
        {
            "category":"Manufacturing",
            "subcategory":"Signs",
            "type":"Manufacturing & Wholesale Goods"
        }
    ],
    "sg:phone":"+1 916 388 9300",
    "sg:postcode":"95828",
    "sg:province":"CA",
    "sg:tags":[
        "truss",
        "construction-wholesale",
        "manufacturer"
    ],
    "wof:name":"General Truss Co Inc",
    "wof:placetype":"venue"
},
  "geometry": {"coordinates":[-121.389229,38.510623],"type":"Point"}
}