{
  "type": "Feature",
  "properties": {
    "addr:full":"11937 Woodside Ave Lakeside CA 92040",
    "addr:housenumber":"11937",
    "addr:postcode":"92040",
    "addr:street":"Woodside Ave",
    "iso:country":"US",
    "sg:address":"11937 Woodside Ave",
    "sg:city":"Lakeside",
    "sg:classifiers":[
        {
            "category":"Manufacturing",
            "subcategory":"Furniture",
            "type":"Manufacturing & Wholesale Goods"
        }
    ],
    "sg:phone":"+1 619 561 9242",
    "sg:postcode":"92040",
    "sg:province":"CA",
    "sg:tags":[
        "bar",
        "fixture"
    ],
    "wof:name":"SDS Bar & Restaurant",
    "wof:placetype":"venue"
},
  "geometry": {"coordinates":[-116.936226,32.85527],"type":"Point"}
}