{
  "type": "Feature",
  "properties": {
    "iso:country":"US",
    "sg:address":"3201 Santa Fe Way Fl 1",
    "sg:city":"Rocklin",
    "sg:classifiers":[
        {
            "category":"Social Services",
            "subcategory":"Job Training",
            "type":"Services"
        },
        {
            "category":"Health Services",
            "subcategory":"Nursing And Care Facility",
            "type":"Services"
        },
        {
            "category":"Social Services",
            "subcategory":"Adult Care",
            "type":"Services"
        },
        {
            "category":"Social Services",
            "subcategory":"Retirement Home",
            "type":"Services"
        }
    ],
    "sg:phone":"+1 916 435 8800",
    "sg:postcode":"95765",
    "sg:province":"CA",
    "sg:tags":[
        "living",
        "homes-skilled",
        "nurses-home",
        "personal",
        "assisted",
        "community",
        "alzheimer's",
        "convalescent"
    ],
    "sg:website":"http://www.mbkseniorliving.com",
    "wof:name":"Casa De Santa Fe",
    "wof:placetype":"venue"
},
  "geometry": {"coordinates":[-121.257683,38.811581],"type":"Point"}
}