{
  "type": "Feature",
  "properties": {
    "iso:country":"US",
    "sg:address":"2061 Cox Rd",
    "sg:city":"Aptos",
    "sg:classifiers":[
        {
            "category":"Real Estate",
            "subcategory":"Real Estate Services",
            "type":"Services"
        },
        {
            "category":"Real Estate",
            "subcategory":"Real Estate Agent",
            "type":"Services"
        }
    ],
    "sg:phone":"+1 831 684 1149",
    "sg:postcode":"95003",
    "sg:province":"CA",
    "sg:tags":[
        "management"
    ],
    "wof:name":"Curtis Robert Appraisal Servic",
    "wof:placetype":"venue"
},
  "geometry": {"coordinates":[-121.85704,36.997509],"type":"Point"}
}