{
  "type": "Feature",
  "properties": {
    "iso:country":"US",
    "sg:address":"866 Mackilhaffy Dr",
    "sg:city":"Patterson",
    "sg:classifiers":[
        {
            "category":"Food & Beverages",
            "subcategory":"Specialty",
            "type":"Retail Goods"
        }
    ],
    "sg:phone":"+1 209 602 1619",
    "sg:postcode":"95363",
    "sg:province":"CA",
    "sg:tags":[
        "water",
        "bulk",
        "company"
    ],
    "wof:name":"Aqua-Tech",
    "wof:placetype":"venue"
},
  "geometry": {"coordinates":[-121.139773,37.460984],"type":"Point"}
}