{
  "type": "Feature",
  "properties": {
    "iso:country":"US",
    "sg:address":"13007 La Porta Pt.",
    "sg:city":"San Diego",
    "sg:classifiers":[
        {
            "category":"Sports & Exercise",
            "subcategory":"Gym",
            "type":"Entertainment"
        }
    ],
    "sg:phone":"+1 858 722 9070",
    "sg:postcode":"92130",
    "sg:province":"CA",
    "sg:tags":[
        "trainer"
    ],
    "sg:website":"www.mobilemusclesd.com",
    "wof:name":"Mobile Muscle",
    "wof:placetype":"venue"
},
  "geometry": {"coordinates":[-117.18530699999999,32.961402],"type":"Point"}
}