{
  "type": "Feature",
  "properties": {
    "iso:country":"US",
    "sg:address":"2142 Valentine St",
    "sg:city":"Los Angeles",
    "sg:classifiers":[
        {
            "category":"Shopping",
            "subcategory":"Florist",
            "type":"Retail Goods"
        }
    ],
    "sg:phone":"+1 323 663 1991",
    "sg:postcode":"90026",
    "sg:province":"CA",
    "wof:name":"Sheilas Flower Garden",
    "wof:placetype":"venue"
},
  "geometry": {"coordinates":[-118.247606,34.089736],"type":"Point"}
}