{
  "type": "Feature",
  "properties": {
    "addr:full":"2506 Galisteo St Corona CA 92882",
    "addr:housenumber":"2506",
    "addr:postcode":"92882",
    "addr:street":"Galisteo St",
    "iso:country":"US",
    "sg:address":"2506 Galisteo St",
    "sg:city":"Corona",
    "sg:classifiers":[
        {
            "category":"Professional",
            "type":"Services"
        }
    ],
    "sg:phone":"+1 951 277 4635",
    "sg:postcode":"92882",
    "sg:province":"CA",
    "wof:name":"Lhunt Studio",
    "wof:placetype":"venue"
},
  "geometry": {"coordinates":[-117.582911,33.854012],"type":"Point"}
}