{
  "type": "Feature",
  "properties": {
    "addr:full":"5907 Bufkin Dr San Jose CA 95123",
    "addr:housenumber":"5907",
    "addr:postcode":"95123",
    "addr:street":"Bufkin Dr",
    "iso:country":"US",
    "sg:address":"5907 Bufkin Dr",
    "sg:city":"San Jose",
    "sg:classifiers":[
        {
            "category":"Wholesale",
            "subcategory":"Hardware",
            "type":"Manufacturing & Wholesale Goods"
        }
    ],
    "sg:phone":"+1 408 229 2170",
    "sg:postcode":"95123",
    "sg:province":"CA",
    "sg:tags":[
        "tool"
    ],
    "wof:name":"Woodwright Tools Inc",
    "wof:placetype":"venue"
},
  "geometry": {"coordinates":[-121.82127800000001,37.239788],"type":"Point"}
}