{
  "type": "Feature",
  "properties": {
    "addr:full":"4045 N Fresno St Fresno CA 93726",
    "addr:housenumber":"4045",
    "addr:postcode":"93726",
    "addr:street":"N Fresno",
    "iso:country":"US",
    "sg:address":"4045 N Fresno St",
    "sg:city":"Fresno",
    "sg:classifiers":[
        {
            "category":"Professional",
            "subcategory":"Engineering",
            "type":"Services"
        }
    ],
    "sg:phone":"+1 559 226 4848",
    "sg:postcode":"93726",
    "sg:province":"CA",
    "sg:tags":[
        "engineer"
    ],
    "wof:name":"Mark T Chin Engineering",
    "wof:placetype":"venue"
},
  "geometry": {"coordinates":[-119.781487,36.792071],"type":"Point"}
}