{
  "type": "Feature",
  "properties": {
    "iso:country":"US",
    "sg:address":"95 W Grant St",
    "sg:city":"Healdsburg",
    "sg:classifiers":[
        {
            "category":"Farming",
            "subcategory":"Farm & Veterinary Services",
            "type":"Manufacturing & Wholesale Goods"
        }
    ],
    "sg:phone":"+1 707 433 4383",
    "sg:postcode":"95448",
    "sg:province":"CA",
    "sg:tags":[
        "vineyard"
    ],
    "wof:name":"Sinclair Ranch",
    "wof:placetype":"venue"
},
  "geometry": {"coordinates":[-122.875678,38.615832],"type":"Point"}
}