{
  "type": "Feature",
  "properties": {
    "addr:full":"1148 W 210th St Torrance CA 90502",
    "addr:housenumber":"1148",
    "addr:postcode":"90502",
    "addr:street":"W 210Th St",
    "iso:country":"US",
    "sg:address":"1148 W 210th St",
    "sg:city":"Torrance",
    "sg:classifiers":[
        {
            "category":"Building & Trades",
            "subcategory":"Plumbing",
            "type":"Services"
        }
    ],
    "sg:phone":"+1 310 320 0829",
    "sg:postcode":"90502",
    "sg:province":"CA",
    "sg:tags":[
        "contractor"
    ],
    "wof:name":"Armed Plumbing Constructi",
    "wof:placetype":"venue"
},
  "geometry": {"coordinates":[-118.296437,33.83914],"type":"Point"}
}