{
  "type": "Feature",
  "properties": {
    "iso:country":"US",
    "sg:address":"1313 Celeste Dr",
    "sg:city":"Modesto",
    "sg:classifiers":[
        {
            "category":"Real Estate",
            "subcategory":"Real Estate Operator",
            "type":"Services"
        }
    ],
    "sg:phone":"+1 209 526 2747",
    "sg:postcode":"95355",
    "sg:province":"CA",
    "sg:tags":[
        "apartment"
    ],
    "sg:website":"www.chardonnayridge.com",
    "wof:name":"Chardonnay Ridge",
    "wof:placetype":"venue"
},
  "geometry": {"coordinates":[-120.973945,37.671984],"type":"Point"}
}