{
  "type": "Feature",
  "properties": {
    "acgov:api":"0.0",
    "acgov:type":"6  to 12",
    "addr:full":"1231 Solano Avenue Albany CA",
    "wof:categories":[
        "education_and_religion:education=school"
    ],
    "wof:name":"Tilden Preparatory School",
    "wof:placetype":"venue"
},
  "geometry": {"coordinates":[-122.29479825043734,37.89064296442016],"type":"Point"}
}