{
  "type": "Feature",
  "properties": {
    "addr:full":"5431 W 98th St Los Angeles CA 90045",
    "addr:housenumber":"5431",
    "addr:postcode":"90045",
    "addr:street":"W 98Th St",
    "iso:country":"US",
    "sg:address":"5431 W 98th St",
    "sg:city":"Los Angeles",
    "sg:classifiers":[
        {
            "category":"Education",
            "subcategory":"School",
            "type":"Public Place"
        }
    ],
    "sg:phone":"+1 310 649 5580",
    "sg:postcode":"90045",
    "sg:province":"CA",
    "wof:name":"Bright Star Secondary Charter",
    "wof:placetype":"venue"
},
  "geometry": {"coordinates":[-118.375713,33.947849],"type":"Point"}
}