{
  "type": "Feature",
  "properties": {
    "iso:country":"US",
    "sg:address":"3911 Broadway Pl",
    "sg:city":"Los Angeles",
    "sg:classifiers":[
        {
            "category":"Manufacturing",
            "subcategory":"Signs",
            "type":"Manufacturing & Wholesale Goods"
        }
    ],
    "sg:phone":"+1 323 234 2100",
    "sg:postcode":"90037",
    "sg:province":"CA",
    "wof:name":"Pacific Sign Co",
    "wof:placetype":"venue"
},
  "geometry": {"coordinates":[-118.277425,34.01124],"type":"Point"}
}