{
  "type": "Feature",
  "properties": {
    "addr:full":"16870 W Hobsonway Blythe CA 92225",
    "addr:housenumber":"16870",
    "addr:postcode":"92225",
    "addr:street":"W Hobsonway",
    "iso:country":"US",
    "sg:address":"16870 W Hobsonway",
    "sg:city":"Blythe",
    "sg:classifiers":[
        {
            "category":"Government",
            "subcategory":"Office",
            "type":"Public Place"
        }
    ],
    "sg:phone":"+1 760 922 6715",
    "sg:postcode":"92225",
    "sg:province":"CA",
    "sg:tags":[
        "naturalization",
        "immigration"
    ],
    "wof:name":"Blythe Border Patrol",
    "wof:placetype":"venue"
},
  "geometry": {"coordinates":[-114.706149,33.609749],"type":"Point"}
}