{
  "type": "Feature",
  "properties": {
    "iso:country":"US",
    "sg:address":"1752 S Berendo St",
    "sg:city":"Los Angeles",
    "sg:classifiers":[
        {
            "category":"Professional",
            "type":"Services"
        }
    ],
    "sg:phone":"+1 323 373 1210",
    "sg:postcode":"90006",
    "sg:province":"CA",
    "wof:name":"Hazels General Merchandise",
    "wof:placetype":"venue"
},
  "geometry": {"coordinates":[-118.29331999999999,34.042155],"type":"Point"}
}