{
  "type": "Feature",
  "properties": {
    "iso:country":"US",
    "sg:address":"13125 Lakeland Rd",
    "sg:city":"Santa Fe Springs",
    "sg:classifiers":[
        {
            "category":"Building & Trades",
            "subcategory":"Pest Control",
            "type":"Services"
        }
    ],
    "sg:phone":"+1 562 946 9200",
    "sg:postcode":"90670",
    "sg:province":"CA",
    "wof:name":"Jade Termite & Pest Control",
    "wof:placetype":"venue"
},
  "geometry": {"coordinates":[-118.278432,33.931855],"type":"Point"}
}