{
  "type": "Feature",
  "properties": {
    "addr:full":"1254 E Florence Avenue Los Angeles CA 90001",
    "addr:housenumber":"1254",
    "addr:postcode":"90001",
    "addr:street":"E Florence Avenue",
    "iso:country":"US",
    "sg:address":"1254 E Florence Avenue",
    "sg:city":"Los Angeles",
    "sg:classifiers":[
        {
            "category":"Education",
            "subcategory":"Vocational School",
            "type":"Public Place"
        }
    ],
    "sg:phone":"+1 323 589 7472",
    "sg:postcode":"90001",
    "sg:province":"CA",
    "sg:tags":[
        "cooking"
    ],
    "wof:name":"Create A Cake",
    "wof:placetype":"venue"
},
  "geometry": {"coordinates":[-118.252652,33.974655],"type":"Point"}
}