{
  "type": "Feature",
  "properties": {
    "addr:full":"4820 San Fernando Rd Glendale CA 91204",
    "addr:housenumber":"4820",
    "addr:postcode":"91204",
    "addr:street":"San Fernando Rd",
    "iso:country":"US",
    "sg:address":"4820 San Fernando Rd",
    "sg:city":"Glendale",
    "sg:classifiers":[
        {
            "category":"Retail",
            "subcategory":"Storage",
            "type":"Services"
        }
    ],
    "sg:phone":"+1 818 507 1981",
    "sg:postcode":"91204",
    "sg:province":"CA",
    "sg:tags":[
        "self"
    ],
    "wof:name":"Public Storage",
    "wof:placetype":"venue"
},
  "geometry": {"coordinates":[-118.26799800000001,34.139198],"type":"Point"}
}