{
  "type": "Feature",
  "properties": {
    "addr:full":"4181 State St Santa Barbara CA 93110",
    "addr:housenumber":"4181",
    "addr:postcode":"93110",
    "addr:street":"State St",
    "iso:country":"US",
    "sg:address":"4181 State St",
    "sg:city":"Santa Barbara",
    "sg:classifiers":[
        {
            "category":"Professional",
            "subcategory":"Computer Services",
            "type":"Services"
        }
    ],
    "sg:phone":"+1 805 692 6220",
    "sg:postcode":"93110",
    "sg:province":"CA",
    "sg:website":"www.occamnetworks.com",
    "wof:name":"Occam Networks Inc",
    "wof:placetype":"venue"
},
  "geometry": {"coordinates":[-119.76361900000001,34.440526],"type":"Point"}
}