{
  "type": "Feature",
  "properties": {
    "addr:full":"1450 N Tustin Ave Ste 223 Santa Ana CA 92705",
    "addr:housenumber":"1450",
    "addr:postcode":"92705",
    "addr:street":"N Tustin Ave Ste 223",
    "iso:country":"US",
    "sg:address":"1450 N Tustin Ave Ste 223",
    "sg:city":"Santa Ana",
    "sg:classifiers":[
        {
            "category":"Professional",
            "subcategory":"Accounting & Tax Preparation",
            "type":"Services"
        }
    ],
    "sg:phone":"+1 714 834 0454",
    "sg:postcode":"92705",
    "sg:province":"CA",
    "sg:tags":[
        "accountant"
    ],
    "wof:name":"Starr & Walters Certified Public Accountants",
    "wof:placetype":"venue"
},
  "geometry": {"coordinates":[-117.817001,33.759998],"type":"Point"}
}