{
  "type": "Feature",
  "properties": {
    "addr:full":"10528 Cypress Ave Riverside CA 92505",
    "addr:housenumber":"10528",
    "addr:postcode":"92505",
    "addr:street":"Cypress Ave",
    "iso:country":"US",
    "sg:address":"10528 Cypress Ave",
    "sg:city":"Riverside",
    "sg:classifiers":[
        {
            "category":"Travel",
            "subcategory":"Travel Agent",
            "type":"Entertainment"
        }
    ],
    "sg:phone":"+1 951 689 8954",
    "sg:postcode":"92505",
    "sg:province":"CA",
    "sg:tags":[
        "agency"
    ],
    "wof:name":"A Cruise & Travel Agency",
    "wof:placetype":"venue"
},
  "geometry": {"coordinates":[-117.48495699999999,33.940811],"type":"Point"}
}