{
  "type": "Feature",
  "properties": {
    "addr:full":"3489 16th St San Francisco CA 94114",
    "addr:housenumber":"3489",
    "addr:postcode":"94114",
    "addr:street":"16Th St",
    "iso:country":"US",
    "sg:address":"3489 16th St",
    "sg:city":"San Francisco",
    "sg:classifiers":[
        {
            "category":"Food & Beverages",
            "subcategory":"Chocolate",
            "type":"Retail Goods"
        }
    ],
    "sg:phone":"+1 415 861 8682",
    "sg:postcode":"94114",
    "sg:province":"CA",
    "sg:tags":[
        "shop",
        "chocolatiers"
    ],
    "sg:website":"www.saratogachocolates.com",
    "wof:name":"Saratoga Chocolates",
    "wof:placetype":"venue"
},
  "geometry": {"coordinates":[-122.43057,37.764158],"type":"Point"}
}