{
  "type": "Feature",
  "properties": {
    "addr:full":"382 N Allen Ave Pasadena CA 91106",
    "addr:housenumber":"382",
    "addr:postcode":"91106",
    "addr:street":"N Allen Ave",
    "iso:country":"US",
    "sg:address":"382 N Allen Ave",
    "sg:city":"Pasadena",
    "sg:classifiers":[
        {
            "category":"Personal",
            "subcategory":"Massage",
            "type":"Services"
        }
    ],
    "sg:phone":"+1 626 396 9989",
    "sg:postcode":"91106",
    "sg:province":"CA",
    "wof:name":"Oriental Massage",
    "wof:placetype":"venue"
},
  "geometry": {"coordinates":[-118.112904,34.151844],"type":"Point"}
}