{
  "type": "Feature",
  "properties": {
    "addr:full":"1327 Preston Way Venice CA 90291",
    "addr:housenumber":"1327",
    "addr:postcode":"90291",
    "addr:street":"Preston Way",
    "iso:country":"US",
    "sg:address":"1327 Preston Way",
    "sg:city":"Venice",
    "sg:classifiers":[
        {
            "category":"Professional",
            "type":"Services"
        }
    ],
    "sg:phone":"+1 310 392 4126",
    "sg:postcode":"90291",
    "sg:province":"CA",
    "wof:name":"Edwin L Rosengrant",
    "wof:placetype":"venue"
},
  "geometry": {"coordinates":[-118.452438,34.004013],"type":"Point"}
}