{
  "type": "Feature",
  "properties": {
    "addr:full":"1016 Morse Ave Sunnyvale CA 94086",
    "addr:housenumber":"1016",
    "addr:postcode":"94086",
    "addr:street":"Morse Ave",
    "iso:country":"US",
    "sg:address":"1016 Morse Ave",
    "sg:city":"Sunnyvale",
    "sg:classifiers":[
        {
            "category":"Professional",
            "subcategory":"Research",
            "type":"Services"
        },
        {
            "category":"Wholesale",
            "subcategory":"Electrical",
            "type":"Manufacturing & Wholesale Goods"
        }
    ],
    "sg:phone":"+1 408 745 6561",
    "sg:postcode":"94086",
    "sg:province":"CA",
    "sg:tags":[
        "design",
        "engineering",
        "video",
        "equipment"
    ],
    "sg:website":"www.appliedmicrovideo.com",
    "wof:name":"Applied Microvideo Inc",
    "wof:placetype":"venue"
},
  "geometry": {"coordinates":[-122.01752,37.39698],"type":"Point"}
}