{
  "type": "Feature",
  "properties": {
    "addr:full":"1017 Frances Dr Chico CA 95973",
    "addr:housenumber":"1017",
    "addr:postcode":"95973",
    "addr:street":"Frances Dr",
    "iso:country":"US",
    "sg:address":"1017 Frances Dr",
    "sg:city":"Chico",
    "sg:classifiers":[
        {
            "category":"Manufacturing",
            "subcategory":"Retail Goods",
            "type":"Manufacturing & Wholesale Goods"
        }
    ],
    "sg:phone":"+1 530 893 0830",
    "sg:postcode":"95973",
    "sg:province":"CA",
    "sg:tags":[
        "manufacturer"
    ],
    "wof:name":"Tommy's Industries Inc",
    "wof:placetype":"venue"
},
  "geometry": {"coordinates":[-121.880286,39.74611],"type":"Point"}
}