{
  "type": "Feature",
  "properties": {
    "addr:full":"13159 Apple Rd Wilton CA 95693",
    "addr:housenumber":"13159",
    "addr:postcode":"95693",
    "addr:street":"Apple Rd",
    "iso:country":"US",
    "sg:address":"13159 Apple Rd",
    "sg:city":"Wilton",
    "sg:classifiers":[
        {
            "category":"Freight",
            "type":"Transportation"
        }
    ],
    "sg:phone":"+1 916 425 5012",
    "sg:postcode":"95693",
    "sg:province":"CA",
    "sg:tags":[
        "operator",
        "local",
        "trucking"
    ],
    "wof:name":"JD Kenney Trucking",
    "wof:placetype":"venue"
},
  "geometry": {"coordinates":[-121.178104,38.455782],"type":"Point"}
}