{
  "type": "Feature",
  "properties": {
    "addr:full":"5825 Kanan Rd Agoura Hills CA 91301",
    "addr:housenumber":"5825",
    "addr:postcode":"91301",
    "addr:street":"Kanan Rd",
    "iso:country":"US",
    "sg:address":"5825 Kanan Rd",
    "sg:city":"Agoura Hills",
    "sg:classifiers":[
        {
            "category":"Cinema",
            "subcategory":"Movie Rental",
            "type":"Entertainment"
        }
    ],
    "sg:phone":"+1 818 991 3584",
    "sg:postcode":"91301",
    "sg:province":"CA",
    "sg:tags":[
        "game",
        "video"
    ],
    "wof:name":"Blockbuster Video",
    "wof:placetype":"venue"
},
  "geometry": {"coordinates":[-118.75700399999999,34.1605],"type":"Point"}
}