{
  "type": "Feature",
  "properties": {
    "addr:full":"6036 N 1st St Fresno CA 93710",
    "addr:housenumber":"6036",
    "addr:postcode":"93710",
    "addr:street":"N 1St St",
    "iso:country":"US",
    "sg:address":"6036 N 1st St",
    "sg:city":"Fresno",
    "sg:classifiers":[
        {
            "category":"Shopping",
            "subcategory":"Department Store",
            "type":"Retail Goods"
        }
    ],
    "sg:phone":"+1 559 438 8599",
    "sg:postcode":"93710",
    "sg:province":"CA",
    "sg:tags":[
        "shop"
    ],
    "wof:name":"99 Cents Only",
    "wof:placetype":"venue"
},
  "geometry": {"coordinates":[-119.772167,36.82513],"type":"Point"}
}