{
  "type": "Feature",
  "properties": {
    "iso:country":"US",
    "sg:address":"20 Oceano Ave",
    "sg:city":"Santa Barbara",
    "sg:classifiers":[
        {
            "category":"Professional",
            "subcategory":"Management & Consulting",
            "type":"Services"
        }
    ],
    "sg:phone":"+1 805 448 1329",
    "sg:postcode":"93109",
    "sg:province":"CA",
    "sg:tags":[
        "consultant",
        "business"
    ],
    "wof:name":"Alternative Board",
    "wof:placetype":"venue"
},
  "geometry": {"coordinates":[-119.702895,34.402656],"type":"Point"}
}