{
  "type": "Feature",
  "properties": {
    "addr:full":"671 S Cooley Dr W Colton CA 92324",
    "addr:housenumber":"671",
    "addr:postcode":"92324",
    "addr:street":"S Cooley Dr W",
    "iso:country":"US",
    "sg:address":"671 S Cooley Dr W",
    "sg:city":"Colton",
    "sg:classifiers":[
        {
            "category":"Shopping",
            "subcategory":"Discount & Variety Stores",
            "type":"Retail Goods"
        }
    ],
    "sg:phone":"+1 909 824 9195",
    "sg:postcode":"92324",
    "sg:province":"CA",
    "wof:name":"Maben Vending",
    "wof:placetype":"venue"
},
  "geometry": {"coordinates":[-117.304219,34.059936],"type":"Point"}
}