{
  "type": "Feature",
  "properties": {
    "addr:full":"3996 N Sierra Way San Bernardino CA 92405",
    "addr:housenumber":"3996",
    "addr:postcode":"92405",
    "addr:street":"N Sierra Way",
    "iso:country":"US",
    "sg:address":"3996 N Sierra Way",
    "sg:city":"San Bernardino",
    "sg:classifiers":[
        {
            "category":"Personal",
            "subcategory":"Barber",
            "type":"Services"
        }
    ],
    "sg:phone":"+1 909 883 2006",
    "sg:postcode":"92405",
    "sg:province":"CA",
    "wof:name":"Dorina's Barber Shop",
    "wof:placetype":"venue"
},
  "geometry": {"coordinates":[-117.285175,34.164854],"type":"Point"}
}