{
  "type": "Feature",
  "properties": {
    "iso:country":"US",
    "sg:address":"369 S Glassell St",
    "sg:city":"Orange",
    "sg:classifiers":[
        {
            "category":"Banks & Credit Unions",
            "subcategory":"Investment Brokerage",
            "type":"Services"
        }
    ],
    "sg:phone":"+1 714 771 6000",
    "sg:postcode":"92866",
    "sg:province":"CA",
    "sg:tags":[
        "advice",
        "financial"
    ],
    "wof:name":"Ulivi Wealth Management",
    "wof:placetype":"venue"
},
  "geometry": {"coordinates":[-117.853025,33.783677],"type":"Point"}
}