{
  "type": "Feature",
  "properties": {
    "addr:full":"130 Travalini Ct El Sobrante CA 94803",
    "addr:housenumber":"130",
    "addr:postcode":"94803",
    "addr:street":"Travalini Ct",
    "iso:country":"US",
    "sg:address":"130 Travalini Ct",
    "sg:city":"El Sobrante",
    "sg:classifiers":[
        {
            "category":"Manufacturing",
            "subcategory":"Chemicals & Compounds",
            "type":"Manufacturing & Wholesale Goods"
        }
    ],
    "sg:phone":"+1 510 758 1388",
    "sg:postcode":"94803",
    "sg:province":"CA",
    "sg:tags":[
        "supply"
    ],
    "wof:name":"Promy Chemical LLC",
    "wof:placetype":"venue"
},
  "geometry": {"coordinates":[-122.274334,37.965742],"type":"Point"}
}