{
  "type": "Feature",
  "properties": {
    "iso:country":"US",
    "sg:address":"822 Hartz Way",
    "sg:city":"Danville",
    "sg:classifiers":[
        {
            "category":"Travel",
            "subcategory":"Travel Agent",
            "type":"Entertainment"
        }
    ],
    "sg:phone":"+1 925 820 6924",
    "sg:postcode":"94526",
    "sg:province":"CA",
    "sg:tags":[
        "agency",
        "bureau"
    ],
    "sg:website":"www.travelconcepts1.com",
    "wof:name":"Travel Concepts",
    "wof:placetype":"venue"
},
  "geometry": {"coordinates":[-121.995037,37.81941],"type":"Point"}
}