{
  "type": "Feature",
  "properties": {
    "addr:full":"12206 Cantura St Studio City CA 91604",
    "addr:housenumber":"12206",
    "addr:postcode":"91604",
    "addr:street":"Cantura St",
    "iso:country":"US",
    "sg:address":"12206 Cantura St",
    "sg:city":"Studio City",
    "sg:classifiers":[
        {
            "category":"Arts & Performance",
            "subcategory":"Theater",
            "type":"Entertainment"
        }
    ],
    "sg:phone":"+1 818 760 1763",
    "sg:postcode":"91604",
    "sg:province":"CA",
    "sg:tags":[
        "bureau"
    ],
    "wof:name":"Journey Entertainment Inc",
    "wof:placetype":"venue"
},
  "geometry": {"coordinates":[-118.399156,34.142261],"type":"Point"}
}