{
  "type": "Feature",
  "properties": {
    "addr:full":"1357 Kansas St San Francisco CA 94107",
    "addr:housenumber":"1357",
    "addr:postcode":"94107",
    "addr:street":"Kansas St",
    "iso:country":"US",
    "sg:address":"1357 Kansas St",
    "sg:city":"San Francisco",
    "sg:classifiers":[
        {
            "category":"Professional",
            "subcategory":"Lawyer & Legal Services",
            "type":"Services"
        }
    ],
    "sg:phone":"+1 415 241 0444",
    "sg:postcode":"94107",
    "sg:province":"CA",
    "sg:tags":[
        "attorney"
    ],
    "wof:name":"Linda Votaw Law Offices",
    "wof:placetype":"venue"
},
  "geometry": {"coordinates":[-122.402295,37.752695],"type":"Point"}
}