{
  "type": "Feature",
  "properties": {
    "addr:full":"742 Tudor Cir Thousand Oaks CA 91360",
    "addr:housenumber":"742",
    "addr:postcode":"91360",
    "addr:street":"Tudor Cir",
    "iso:country":"US",
    "sg:address":"742 Tudor Cir",
    "sg:city":"Thousand Oaks",
    "sg:classifiers":[
        {
            "category":"Wholesale",
            "subcategory":"Electrical",
            "type":"Manufacturing & Wholesale Goods"
        }
    ],
    "sg:phone":"+1 805 371 4332",
    "sg:postcode":"91360",
    "sg:province":"CA",
    "sg:tags":[
        "equipment",
        "electronic",
        "supply"
    ],
    "wof:name":"Partners Sourcing",
    "wof:placetype":"venue"
},
  "geometry": {"coordinates":[-118.86494399999999,34.190901],"type":"Point"}
}