{
  "type": "Feature",
  "properties": {
    "iso:country":"US",
    "sg:address":"403 S Imperial Ave",
    "sg:city":"Calexico",
    "sg:classifiers":[
        {
            "category":"Banks & Credit Unions",
            "subcategory":"Bank",
            "type":"Services"
        }
    ],
    "sg:phone":"+1 760 357 5080",
    "sg:postcode":"92231",
    "sg:province":"CA",
    "sg:tags":[
        "money",
        "broker"
    ],
    "wof:name":"Rene's Casa De Cambio",
    "wof:placetype":"venue"
},
  "geometry": {"coordinates":[-115.498746,32.669822],"type":"Point"}
}