{
  "type": "Feature",
  "properties": {
    "addr:full":"509 S Cedros Ave Solana Beach CA 92075",
    "addr:housenumber":"509",
    "addr:postcode":"92075",
    "addr:street":"S Cedros Ave",
    "iso:country":"US",
    "sg:address":"509 S Cedros Ave",
    "sg:city":"Solana Beach",
    "sg:classifiers":[
        {
            "category":"Health Services",
            "subcategory":"Doctor",
            "type":"Services"
        }
    ],
    "sg:phone":"+1 858 350 4414",
    "sg:postcode":"92075",
    "sg:province":"CA",
    "sg:tags":[
        "physician",
        "surgeon"
    ],
    "wof:name":"Masilungan Benjo MD",
    "wof:placetype":"venue"
},
  "geometry": {"coordinates":[-117.269237,32.986252],"type":"Point"}
}