{
  "type": "Feature",
  "properties": {
    "addr:full":"2444 Fender Ave Fullerton CA 92831",
    "addr:housenumber":"2444",
    "addr:postcode":"92831",
    "addr:street":"Fender Ave",
    "iso:country":"US",
    "sg:address":"2444 Fender Ave",
    "sg:city":"Fullerton",
    "sg:classifiers":[
        {
            "category":"Wholesale",
            "subcategory":"Petroleum",
            "type":"Manufacturing & Wholesale Goods"
        }
    ],
    "sg:phone":"+1 714 526 5511",
    "sg:postcode":"92831",
    "sg:province":"CA",
    "sg:tags":[
        "bulk",
        "station"
    ],
    "wof:name":"Keesee Supply Co",
    "wof:placetype":"venue"
},
  "geometry": {"coordinates":[-117.88484200000001,33.868059],"type":"Point"}
}