{
  "type": "Feature",
  "properties": {
    "iso:country":"US",
    "sg:address":"321 E Heil Ave",
    "sg:city":"El Centro",
    "sg:classifiers":[
        {
            "category":"Insurance",
            "subcategory":"Hazard Insurance",
            "type":"Services"
        }
    ],
    "sg:phone":"+1 760 337 8038",
    "sg:postcode":"92243",
    "sg:province":"CA",
    "sg:tags":[
        "bond"
    ],
    "wof:name":"Romo Rolando Bail Bonds",
    "wof:placetype":"venue"
},
  "geometry": {"coordinates":[-115.53591299999999,32.786726],"type":"Point"}
}