{
  "type": "Feature",
  "properties": {
    "iso:country":"US",
    "sg:address":"13721 Park Palisade Dr",
    "sg:city":"Bakersfield",
    "sg:classifiers":[
        {
            "category":"Real Estate",
            "subcategory":"Real Estate Services",
            "type":"Services"
        },
        {
            "category":"Real Estate",
            "subcategory":"Real Estate Agent",
            "type":"Services"
        }
    ],
    "sg:phone":"+1 661 871 1864",
    "sg:postcode":"93306",
    "sg:province":"CA",
    "sg:tags":[
        "buyer",
        "broker"
    ],
    "wof:name":"Savic Real Estate",
    "wof:placetype":"venue"
},
  "geometry": {"coordinates":[-118.85217400000001,35.408306],"type":"Point"}
}