{
  "type": "Feature",
  "properties": {
    "addr:full":"2170 White Ln Bakersfield CA 93304",
    "addr:housenumber":"2170",
    "addr:postcode":"93304",
    "addr:street":"White Ln",
    "iso:country":"US",
    "sg:address":"2170 White Ln",
    "sg:city":"Bakersfield",
    "sg:classifiers":[
        {
            "category":"Building & Trades",
            "subcategory":"Electrical",
            "type":"Services"
        },
        {
            "category":"Building & Trades",
            "subcategory":"Construction",
            "type":"Services"
        }
    ],
    "sg:phone":"+1 661 831 0201",
    "sg:postcode":"93304",
    "sg:province":"CA",
    "sg:tags":[
        "cabling",
        "wiring",
        "electrical",
        "telecommunication",
        "contractor"
    ],
    "wof:name":"Cellular Satellite 2000 Commu",
    "wof:placetype":"venue"
},
  "geometry": {"coordinates":[-119.028796,35.317745],"type":"Point"}
}