{
  "type": "Feature",
  "properties": {
    "addr:full":"3329 Division St Los Angeles CA 90065",
    "addr:housenumber":"3329",
    "addr:postcode":"90065",
    "addr:street":"Division St",
    "iso:country":"US",
    "sg:address":"3329 Division St",
    "sg:city":"Los Angeles",
    "sg:classifiers":[
        {
            "category":"Food & Beverages",
            "subcategory":"Bakery",
            "type":"Retail Goods"
        }
    ],
    "sg:phone":"+1 323 221 1060",
    "sg:postcode":"90065",
    "sg:province":"CA",
    "sg:tags":[
        "sandwich"
    ],
    "sg:website":"www.labento.com",
    "wof:name":"L.A. Bento",
    "wof:placetype":"venue"
},
  "geometry": {"coordinates":[-118.229974,34.105075],"type":"Point"}
}