{
  "type": "Feature",
  "properties": {
    "iso:country":"US",
    "sg:address":"5300 White Oak Ave",
    "sg:city":"Encino",
    "sg:classifiers":[
        {
            "category":"Professional",
            "subcategory":"Management & Consulting",
            "type":"Services"
        }
    ],
    "sg:phone":"+1 818 501 1065",
    "sg:postcode":"91316",
    "sg:province":"CA",
    "sg:tags":[
        "retail",
        "direct",
        "sales"
    ],
    "wof:name":"Vicko Food Services",
    "wof:placetype":"venue"
},
  "geometry": {"coordinates":[-118.518547,34.168605],"type":"Point"}
}