{
  "type": "Feature",
  "properties": {
    "addr:full":"461 E Main St Ventura CA 93001",
    "addr:housenumber":"461",
    "addr:postcode":"93001",
    "addr:street":"E Main St",
    "iso:country":"US",
    "sg:address":"461 E Main St",
    "sg:city":"Ventura",
    "sg:classifiers":[
        {
            "category":"Professional",
            "subcategory":"Business Services",
            "type":"Services"
        }
    ],
    "sg:phone":"+1 805 643 9910",
    "sg:postcode":"93001",
    "sg:province":"CA",
    "sg:tags":[
        "interior",
        "consultant",
        "design",
        "decorator"
    ],
    "wof:name":"Annette Duston Interiors",
    "wof:placetype":"venue"
},
  "geometry": {"coordinates":[-119.293891,34.28089],"type":"Point"}
}