{
  "type": "Feature",
  "properties": {
    "iso:country":"US",
    "sg:address":"2081 Harbison Dr",
    "sg:city":"Vacaville",
    "sg:classifiers":[
        {
            "category":"Restaurant",
            "type":"Food & Drink"
        }
    ],
    "sg:menulink":"http://www.allmenus.com/ca/vacaville/197914-kfc---kentucky-fried-chicken/menu/",
    "sg:phone":"+1 707 446 1843",
    "sg:postcode":"95687",
    "sg:province":"CA",
    "sg:tags":[
        "american",
        "chicken"
    ],
    "wof:name":"KFC - Kentucky Fried Chicken",
    "wof:placetype":"venue"
},
  "geometry": {"coordinates":[-121.965266,38.361372],"type":"Point"}
}