{
  "type": "Feature",
  "properties": {
    "iso:country":"US",
    "sg:address":"14419 Cerritos Ave",
    "sg:city":"Bellflower",
    "sg:classifiers":[
        {
            "category":"Professional",
            "subcategory":"Advertising",
            "type":"Services"
        }
    ],
    "sg:phone":"+1 562 630 6280",
    "sg:postcode":"90706",
    "sg:province":"CA",
    "sg:tags":[
        "counselor"
    ],
    "wof:name":"Recreation Media Advertising",
    "wof:placetype":"venue"
},
  "geometry": {"coordinates":[-118.137075,33.90208],"type":"Point"}
}