{
  "type": "Feature",
  "properties": {
    "addr:full":"2077 Mountain Blvd Oakland CA 94611",
    "addr:housenumber":"2077",
    "addr:postcode":"94611",
    "addr:street":"Mountain Blvd",
    "iso:country":"US",
    "sg:address":"2077 Mountain Blvd",
    "sg:city":"Oakland",
    "sg:classifiers":[
        {
            "category":"Real Estate",
            "subcategory":"Real Estate Services",
            "type":"Services"
        },
        {
            "category":"Real Estate",
            "subcategory":"Real Estate Agent",
            "type":"Services"
        }
    ],
    "sg:phone":"+1 510 517 6280",
    "sg:postcode":"94611",
    "sg:province":"CA",
    "sg:website":"www.BruceWagg.com",
    "wof:name":"Bruce Wagg - Prudential California Realty",
    "wof:placetype":"venue"
},
  "geometry": {"coordinates":[-122.209462,37.825955],"type":"Point"}
}