{
  "type": "Feature",
  "properties": {
    "iso:country":"US",
    "sg:address":"1115 Stratford Ave",
    "sg:city":"Dixon",
    "sg:classifiers":[
        {
            "category":"Banks & Credit Unions",
            "subcategory":"Bank",
            "type":"Services"
        }
    ],
    "sg:phone":"+1 707 678 3021",
    "sg:postcode":"95620",
    "sg:province":"CA",
    "sg:tags":[
        "loan"
    ],
    "sg:website":"www.centstatemtg.com",
    "wof:name":"Central State Mortgage Corp",
    "wof:placetype":"venue"
},
  "geometry": {"coordinates":[-121.837191,38.458139],"type":"Point"}
}