{
  "type": "Feature",
  "properties": {
    "addr:full":"725 E Gutierrez St Santa Barbara CA 93103",
    "addr:housenumber":"725",
    "addr:postcode":"93103",
    "addr:street":"E Gutierrez St",
    "iso:country":"US",
    "sg:address":"725 E Gutierrez St",
    "sg:city":"Santa Barbara",
    "sg:classifiers":[
        {
            "category":"Retail",
            "subcategory":"Auto Repair",
            "type":"Services"
        }
    ],
    "sg:phone":"+1 805 962 1152",
    "sg:postcode":"93103",
    "sg:province":"CA",
    "sg:tags":[
        "repairing",
        "automobile"
    ],
    "wof:name":"Quality Automotive Repair",
    "wof:placetype":"venue"
},
  "geometry": {"coordinates":[-119.68526199999999,34.424327],"type":"Point"}
}