{
  "type": "Feature",
  "properties": {
    "addr:full":"946 Miramar Dr Vista CA 92081",
    "addr:housenumber":"946",
    "addr:postcode":"92081",
    "addr:street":"Miramar Dr",
    "iso:country":"US",
    "sg:address":"946 Miramar Dr",
    "sg:city":"Vista",
    "sg:classifiers":[
        {
            "category":"Insurance",
            "subcategory":"Insurance Agent",
            "type":"Services"
        }
    ],
    "sg:phone":"+1 760 945 2310",
    "sg:postcode":"92081",
    "sg:province":"CA",
    "wof:name":"Shupack Jay Company",
    "wof:placetype":"venue"
},
  "geometry": {"coordinates":[-117.23972000000001,33.179949],"type":"Point"}
}