{
  "type": "Feature",
  "properties": {
    "addr:full":"101 W 2nd Ave Escondido CA 92025",
    "addr:housenumber":"101",
    "addr:postcode":"92025",
    "addr:street":"W 2Nd Ave",
    "iso:country":"US",
    "sg:address":"101 W 2nd Ave",
    "sg:city":"Escondido",
    "sg:classifiers":[
        {
            "category":"Shopping",
            "subcategory":"Florist",
            "type":"Retail Goods"
        }
    ],
    "sg:phone":"+1 760 745 1191",
    "sg:postcode":"92025",
    "sg:province":"CA",
    "wof:name":"Rosemary-Duff Florist",
    "wof:placetype":"venue"
},
  "geometry": {"coordinates":[-117.08219099999999,33.120056],"type":"Point"}
}