{
  "type": "Feature",
  "properties": {
    "iso:country":"US",
    "sg:address":"109 S Main St",
    "sg:city":"Lake Elsinore",
    "sg:classifiers":[
        {
            "category":"Organizations",
            "subcategory":"Professional Association",
            "type":"Services"
        }
    ],
    "sg:phone":"+1 951 674 2577",
    "sg:postcode":"92530",
    "sg:province":"CA",
    "sg:tags":[
        "chambers",
        "commerce"
    ],
    "wof:name":"Tri-Valley Info Ctr",
    "wof:placetype":"venue"
},
  "geometry": {"coordinates":[-117.327772,33.667962],"type":"Point"}
}