{
  "type": "Feature",
  "properties": {
    "iso:country":"US",
    "sg:address":"10301 Magnolia Ave",
    "sg:city":"Riverside",
    "sg:classifiers":[
        {
            "category":"Restaurant",
            "type":"Food & Drink"
        }
    ],
    "sg:menulink":"http://www.allmenus.com/ca/riverside/97081-ihop/menu/",
    "sg:phone":"+1 951 688 9806",
    "sg:postcode":"92505",
    "sg:province":"CA",
    "sg:tags":[
        "sandwich",
        "salad",
        "burger",
        "soup",
        "american",
        "steakhouse",
        "wrap"
    ],
    "wof:name":"IHOP",
    "wof:placetype":"venue"
},
  "geometry": {"coordinates":[-117.462034,33.912125],"type":"Point"}
}