{
  "type": "Feature",
  "properties": {
    "addr:full":"115 N Hollywood Way Burbank CA 91505",
    "addr:housenumber":"115",
    "addr:postcode":"91505",
    "addr:street":"N Hollywood Way",
    "iso:country":"US",
    "sg:address":"115 N Hollywood Way",
    "sg:city":"Burbank",
    "sg:classifiers":[
        {
            "category":"Professional",
            "type":"Services"
        }
    ],
    "sg:phone":"+1 818 526 0580",
    "sg:postcode":"91505",
    "sg:province":"CA",
    "sg:tags":[
        "elementary",
        "school"
    ],
    "wof:name":"Children First",
    "wof:placetype":"venue"
},
  "geometry": {"coordinates":[-118.339996,34.152401],"type":"Point"}
}