{
  "type": "Feature",
  "properties": {
    "iso:country":"US",
    "sg:address":"950 Oakdale Rd Ste J",
    "sg:city":"Modesto",
    "sg:classifiers":[
        {
            "category":"Personal",
            "subcategory":"Tanning Parlor",
            "type":"Services"
        },
        {
            "category":"Shopping",
            "subcategory":"Shoes",
            "type":"Retail Goods"
        },
        {
            "category":"Personal",
            "subcategory":"Nail Salon",
            "type":"Services"
        }
    ],
    "sg:phone":"+1 209 579 2222",
    "sg:postcode":"95355",
    "sg:province":"CA",
    "sg:tags":[
        "store"
    ],
    "wof:name":"BODY & SOL",
    "wof:placetype":"venue"
},
  "geometry": {"coordinates":[-120.957241,37.655953],"type":"Point"}
}