{
  "type": "Feature",
  "properties": {
    "addr:full":"515 Kelly St Half Moon Bay CA 94019",
    "addr:housenumber":"515",
    "addr:postcode":"94019",
    "addr:street":"Kelly St",
    "iso:country":"US",
    "sg:address":"515 Kelly St",
    "sg:city":"Half Moon Bay",
    "sg:classifiers":[
        {
            "category":"Shopping",
            "subcategory":"Used Merchandise",
            "type":"Retail Goods"
        }
    ],
    "sg:phone":"+1 650 726 6543",
    "sg:postcode":"94019",
    "sg:province":"CA",
    "sg:tags":[
        "shop",
        "thrift"
    ],
    "wof:name":"Next To New Thrift Shop Inc",
    "wof:placetype":"venue"
},
  "geometry": {"coordinates":[-122.43144599999999,37.463927],"type":"Point"}
}