{
  "type": "Feature",
  "properties": {
    "iso:country":"US",
    "sg:address":"4231 Park Blvd",
    "sg:city":"Oakland",
    "sg:classifiers":[
        {
            "category":"Shopping",
            "subcategory":"Musical Instruments",
            "type":"Retail Goods"
        }
    ],
    "sg:phone":"+1 510 482 3900",
    "sg:postcode":"94602",
    "sg:province":"CA",
    "sg:tags":[
        "piano",
        "organ"
    ],
    "sg:website":"http://www.jnelson.com",
    "wof:name":"J Nelson & Co",
    "wof:placetype":"venue"
},
  "geometry": {"coordinates":[-122.222301,37.807423],"type":"Point"}
}