{
  "type": "Feature",
  "properties": {
    "addr:full":"4450 State Rd Bakersfield CA 93308",
    "addr:housenumber":"4450",
    "addr:postcode":"93308",
    "addr:street":"State Rd",
    "iso:country":"US",
    "sg:address":"4450 State Rd",
    "sg:city":"Bakersfield",
    "sg:classifiers":[
        {
            "category":"Farming",
            "subcategory":"Farm & Veterinary Services",
            "type":"Manufacturing & Wholesale Goods"
        }
    ],
    "sg:phone":"+1 661 391 9081",
    "sg:postcode":"93308",
    "sg:province":"CA",
    "sg:tags":[
        "aerial",
        "applicator"
    ],
    "wof:name":"Schaben Industries",
    "wof:placetype":"venue"
},
  "geometry": {"coordinates":[-119.05274900000001,35.411501],"type":"Point"}
}