{
  "type": "Feature",
  "properties": {
    "addr:full":"20558 Stevens Creek Blvd Cupertino CA 95014",
    "addr:housenumber":"20558",
    "addr:postcode":"95014",
    "addr:street":"Stevens Creek Blvd",
    "iso:country":"US",
    "sg:address":"20558 Stevens Creek Blvd",
    "sg:city":"Cupertino",
    "sg:classifiers":[
        {
            "category":"Shopping",
            "subcategory":"Pets & Pet Supplies",
            "type":"Retail Goods"
        }
    ],
    "sg:phone":"+1 408 725 9530",
    "sg:postcode":"95014",
    "sg:province":"CA",
    "sg:tags":[
        "training",
        "store"
    ],
    "sg:website":"www.petsmart.com/",
    "wof:name":"PetSmart",
    "wof:placetype":"venue"
},
  "geometry": {"coordinates":[-122.03241300000001,37.322809],"type":"Point"}
}