{
  "type": "Feature",
  "properties": {
    "iso:country":"US",
    "sg:address":"515 S 10th St",
    "sg:city":"San Jose",
    "sg:classifiers":[
        {
            "category":"Restaurant",
            "type":"Food & Drink"
        },
        {
            "category":"Shopping",
            "type":"Retail Goods"
        }
    ],
    "sg:phone":"+1 408 947 7710",
    "sg:postcode":"95112",
    "sg:province":"CA",
    "sg:tags":[
        "american",
        "latin",
        "mexican"
    ],
    "sg:website":"www.chalateco.com",
    "wof:name":"Chalateco",
    "wof:placetype":"venue"
},
  "geometry": {"coordinates":[-121.875,37.332699],"type":"Point"}
}