{
  "type": "Feature",
  "properties": {
    "iso:country":"US",
    "sg:address":"7122 Beverly Blvd",
    "sg:city":"Los Angeles",
    "sg:classifiers":[
        {
            "category":"Professional",
            "subcategory":"Management & Consulting",
            "type":"Services"
        }
    ],
    "sg:phone":"+1 323 954 7628",
    "sg:postcode":"90036",
    "sg:province":"CA",
    "sg:tags":[
        "marketing",
        "consultant"
    ],
    "sg:website":"www.addmarketing.com",
    "wof:name":"ADD Marketing",
    "wof:placetype":"venue"
},
  "geometry": {"coordinates":[-118.344717,34.076086],"type":"Point"}
}