{
  "type": "Feature",
  "properties": {
    "iso:country":"US",
    "sg:address":"21 Metro Dr",
    "sg:city":"San Jose",
    "sg:classifiers":[
        {
            "category":"Coffee & Tea",
            "type":"Food & Drink"
        },
        {
            "category":"Food & Beverages",
            "subcategory":"Bakery",
            "type":"Retail Goods"
        },
        {
            "category":"Bakery",
            "type":"Food & Drink"
        }
    ],
    "sg:phone":"+1 408 573 7770",
    "sg:postcode":"95110",
    "sg:province":"CA",
    "sg:tags":[
        "sandwich"
    ],
    "wof:name":"Le Boulanger",
    "wof:placetype":"venue"
},
  "geometry": {"coordinates":[-121.915949,37.36935],"type":"Point"}
}