{
  "type": "Feature",
  "properties": {
    "addr:full":"914 S Gerhart Ave Los Angeles CA 90022",
    "addr:housenumber":"914",
    "addr:postcode":"90022",
    "addr:street":"S Gerhart Ave",
    "iso:country":"US",
    "sg:address":"914 S Gerhart Ave",
    "sg:city":"Los Angeles",
    "sg:classifiers":[
        {
            "category":"Retail",
            "subcategory":"Auto Repair",
            "type":"Services"
        }
    ],
    "sg:phone":"+1 323 724 0187",
    "sg:postcode":"90022",
    "sg:province":"CA",
    "sg:tags":[
        "repairing",
        "automobile"
    ],
    "wof:name":"Dave's Auto Repair",
    "wof:placetype":"venue"
},
  "geometry": {"coordinates":[-118.14693200000001,34.01802],"type":"Point"}
}