{
  "type": "Feature",
  "properties": {
    "addr:full":"19 N 5th St Redlands CA 92373",
    "addr:housenumber":"19",
    "addr:postcode":"92373",
    "addr:street":"N 5Th St",
    "iso:country":"US",
    "sg:address":"19 N 5th St",
    "sg:city":"Redlands",
    "sg:classifiers":[
        {
            "category":"Restaurant",
            "type":"Food & Drink"
        }
    ],
    "sg:phone":"+1 909 792 8211",
    "sg:postcode":"92373",
    "sg:province":"CA",
    "sg:website":"http://www.oscarsmexicanrestaurant.com",
    "wof:name":"Oscars Mexican Restaurant",
    "wof:placetype":"venue"
},
  "geometry": {"coordinates":[-117.18145,34.055708],"type":"Point"}
}