{
  "type": "Feature",
  "properties": {
    "addr:full":"16161 Ventura Blvd Encino CA 91436",
    "addr:housenumber":"16161",
    "addr:postcode":"91436",
    "addr:street":"Ventura Blvd",
    "iso:country":"US",
    "sg:address":"16161 Ventura Blvd",
    "sg:city":"Encino",
    "sg:classifiers":[
        {
            "category":"Restaurant",
            "type":"Food & Drink"
        }
    ],
    "sg:phone":"+1 818 906 8913",
    "sg:postcode":"91436",
    "sg:province":"CA",
    "wof:name":"Mika Sushi",
    "wof:placetype":"venue"
},
  "geometry": {"coordinates":[-118.486876,34.15686],"type":"Point"}
}