{
  "type": "Feature",
  "properties": {
    "iso:country":"US",
    "sg:address":"4001 J St",
    "sg:city":"Sacramento",
    "sg:classifiers":[
        {
            "category":"Health Services",
            "subcategory":"Doctor",
            "type":"Services"
        }
    ],
    "sg:phone":"+1 916 453 4528",
    "sg:postcode":"95819",
    "sg:province":"CA",
    "wof:name":"Russell Anthony H MD",
    "wof:placetype":"venue"
},
  "geometry": {"coordinates":[-121.452003,38.5695],"type":"Point"}
}