{
  "type": "Feature",
  "properties": {
    "addr:full":"13321 Brookhurst St Garden Grove CA 92843",
    "addr:housenumber":"13321",
    "addr:postcode":"92843",
    "addr:street":"Brookhurst St",
    "iso:country":"US",
    "sg:address":"13321 Brookhurst St",
    "sg:city":"Garden Grove",
    "sg:classifiers":[
        {
            "category":"Restaurant",
            "type":"Food & Drink"
        }
    ],
    "sg:phone":"+1 714 539 8989",
    "sg:postcode":"92843",
    "sg:province":"CA",
    "sg:tags":[
        "korean"
    ],
    "wof:name":"Ku Wol San",
    "wof:placetype":"venue"
},
  "geometry": {"coordinates":[-117.955129,33.769108],"type":"Point"}
}