{
  "type": "Feature",
  "properties": {
    "iso:country":"US",
    "sg:address":"1626 W 107th St",
    "sg:city":"Los Angeles",
    "sg:classifiers":[
        {
            "category":"Organizations",
            "subcategory":"Non-profit Organization",
            "type":"Services"
        }
    ],
    "sg:phone":"+1 323 756 0261",
    "sg:postcode":"90047",
    "sg:province":"CA",
    "sg:tags":[
        "social"
    ],
    "wof:name":"Curtis Jenkins",
    "wof:placetype":"venue"
},
  "geometry": {"coordinates":[-118.308547,33.939031],"type":"Point"}
}