{
  "type": "Feature",
  "properties": {
    "addr:full":"111 S College Ave Claremont CA 91711",
    "addr:housenumber":"111",
    "addr:postcode":"91711",
    "addr:street":"S College Ave",
    "iso:country":"US",
    "sg:address":"111 S College Ave",
    "sg:city":"Claremont",
    "sg:classifiers":[
        {
            "category":"Manufacturing",
            "subcategory":"Printing",
            "type":"Manufacturing & Wholesale Goods"
        }
    ],
    "sg:phone":"+1 909 621 4761",
    "sg:postcode":"91711",
    "sg:province":"CA",
    "sg:tags":[
        "newspaper"
    ],
    "wof:name":"Claremont Courier",
    "wof:placetype":"venue"
},
  "geometry": {"coordinates":[-117.714986,34.09345],"type":"Point"}
}