{
  "type": "Feature",
  "properties": {
    "addr:full":"629 Plum St Novato CA 94945",
    "addr:housenumber":"629",
    "addr:postcode":"94945",
    "addr:street":"Plum St",
    "iso:country":"US",
    "sg:address":"629 Plum St",
    "sg:city":"Novato",
    "sg:classifiers":[
        {
            "category":"Social Services",
            "subcategory":"Child Care",
            "type":"Services"
        }
    ],
    "sg:phone":"+1 415 892 4111",
    "sg:postcode":"94945",
    "sg:province":"CA",
    "wof:name":"Quality Care For Kids",
    "wof:placetype":"venue"
},
  "geometry": {"coordinates":[-122.560892,38.111617],"type":"Point"}
}