{
  "type": "Feature",
  "properties": {
    "addr:full":"903 S Main St Bishop CA 93514",
    "addr:housenumber":"903",
    "addr:postcode":"93514",
    "addr:street":"S Main St",
    "iso:country":"US",
    "sg:address":"903 S Main St",
    "sg:city":"Bishop",
    "sg:classifiers":[
        {
            "category":"Farming",
            "subcategory":"Livestock Farm",
            "type":"Manufacturing & Wholesale Goods"
        }
    ],
    "sg:phone":"+1 760 873 7398",
    "sg:postcode":"93514",
    "sg:province":"CA",
    "sg:tags":[
        "beef",
        "feedlot",
        "cattle"
    ],
    "wof:name":"Gary Rossi Ranch",
    "wof:placetype":"venue"
},
  "geometry": {"coordinates":[-118.395269,37.349207],"type":"Point"}
}