{
  "type": "Feature",
  "properties": {
    "iso:country":"US",
    "sg:address":"2281 E Carson St",
    "sg:city":"Long Beach",
    "sg:classifiers":[
        {
            "category":"Retail",
            "subcategory":"Veterinary Services",
            "type":"Services"
        }
    ],
    "sg:phone":"+1 562 426 2327",
    "sg:postcode":"90807",
    "sg:province":"CA",
    "sg:tags":[
        "veterinarian"
    ],
    "wof:name":"Shenoda Sam DVM",
    "wof:placetype":"venue"
},
  "geometry": {"coordinates":[-118.229118,33.832028],"type":"Point"}
}