{
  "type": "Feature",
  "properties": {
    "addr:full":"7452 Lankershim Blvd North Hollywood CA 91605",
    "addr:housenumber":"7452",
    "addr:postcode":"91605",
    "addr:street":"Lankershim Blvd",
    "iso:country":"US",
    "sg:address":"7452 Lankershim Blvd",
    "sg:city":"North Hollywood",
    "sg:classifiers":[
        {
            "category":"Retail",
            "subcategory":"Auto Repair",
            "type":"Services"
        }
    ],
    "sg:phone":"+1 818 765 3731",
    "sg:postcode":"91605",
    "sg:province":"CA",
    "sg:tags":[
        "wheel",
        "axle",
        "alignment"
    ],
    "wof:name":"Andy's In & Out Alignment",
    "wof:placetype":"venue"
},
  "geometry": {"coordinates":[-118.387704,34.206606],"type":"Point"}
}