{
  "type": "Feature",
  "properties": {
    "addr:full":"4305 Torrance Blvd Ste 100 Torrance CA 90503",
    "addr:housenumber":"4305",
    "addr:postcode":"90503",
    "addr:street":"Torrance Blvd Ste 100",
    "iso:country":"US",
    "sg:address":"4305 Torrance Blvd Ste 100",
    "sg:city":"Torrance",
    "sg:classifiers":[
        {
            "category":"Health Services",
            "subcategory":"Doctor",
            "type":"Services"
        }
    ],
    "sg:phone":"+1 310 214 0000",
    "sg:postcode":"90503",
    "sg:province":"CA",
    "wof:name":"Brown Thomas R MD",
    "wof:placetype":"venue"
},
  "geometry": {"coordinates":[-118.35933,33.837717],"type":"Point"}
}