{
  "type": "Feature",
  "properties": {
    "addr:full":"8881 Pipestone Way San Diego CA 92129",
    "addr:housenumber":"8881",
    "addr:postcode":"92129",
    "addr:street":"Pipestone Way",
    "iso:country":"US",
    "sg:address":"8881 Pipestone Way",
    "sg:city":"San Diego",
    "sg:classifiers":[
        {
            "category":"Wholesale",
            "subcategory":"Electrical",
            "type":"Manufacturing & Wholesale Goods"
        }
    ],
    "sg:phone":"+1 858 484 8199",
    "sg:postcode":"92129",
    "sg:province":"CA",
    "wof:name":"Dodson Audio Inc",
    "wof:placetype":"venue"
},
  "geometry": {"coordinates":[-117.135807,32.970148],"type":"Point"}
}