{
  "type": "Feature",
  "properties": {
    "addr:full":"5925 Estrella Ave Los Angeles CA 90044",
    "addr:housenumber":"5925",
    "addr:postcode":"90044",
    "addr:street":"Estrella Ave",
    "iso:country":"US",
    "sg:address":"5925 Estrella Ave",
    "sg:city":"Los Angeles",
    "sg:classifiers":[
        {
            "category":"Shopping",
            "subcategory":"Party Supplies",
            "type":"Retail Goods"
        }
    ],
    "sg:phone":"+1 323 752 5781",
    "sg:postcode":"90044",
    "sg:province":"CA",
    "wof:name":"Party Supply Godoy Gifts & Rental",
    "wof:placetype":"venue"
},
  "geometry": {"coordinates":[-118.284886,33.986587],"type":"Point"}
}