{
  "type": "Feature",
  "properties": {
    "addr:full":"81557 Doctor Carreon Blvd Indio CA 92201",
    "addr:housenumber":"81557",
    "addr:postcode":"92201",
    "addr:street":"Doctor Carreon Blvd",
    "iso:country":"US",
    "sg:address":"81557 Doctor Carreon Blvd",
    "sg:city":"Indio",
    "sg:classifiers":[
        {
            "category":"Insurance",
            "subcategory":"Insurance Agent",
            "type":"Services"
        }
    ],
    "sg:phone":"+1 760 347 5552",
    "sg:postcode":"92201",
    "sg:province":"CA",
    "wof:name":"Coachella Valley Insurance",
    "wof:placetype":"venue"
},
  "geometry": {"coordinates":[-116.23987700000001,33.707318],"type":"Point"}
}