{
  "type": "Feature",
  "properties": {
    "iso:country":"US",
    "sg:address":"3094 Lake Dr Apt A1",
    "sg:city":"Marina",
    "sg:classifiers":[
        {
            "category":"Real Estate",
            "subcategory":"Real Estate Operator",
            "type":"Services"
        }
    ],
    "sg:phone":"+1 831 384 3443",
    "sg:postcode":"93933",
    "sg:province":"CA",
    "sg:tags":[
        "apartment"
    ],
    "wof:name":"Seabreeze Apartments",
    "wof:placetype":"venue"
},
  "geometry": {"coordinates":[-121.806,36.685398],"type":"Point"}
}