{
  "type": "Feature",
  "properties": {
    "addr:full":"24799 Joe Mary St Hayward CA 94541",
    "addr:housenumber":"24799",
    "addr:postcode":"94541",
    "addr:street":"Joe Mary St",
    "iso:country":"US",
    "sg:address":"24799 Joe Mary St",
    "sg:city":"Hayward",
    "sg:classifiers":[
        {
            "category":"Wholesale",
            "subcategory":"Machinery & Supplies",
            "type":"Manufacturing & Wholesale Goods"
        }
    ],
    "sg:phone":"+1 510 537 9988",
    "sg:postcode":"94541",
    "sg:province":"CA",
    "sg:tags":[
        "equipment",
        "safety",
        "clothing"
    ],
    "wof:name":"Distress Signals",
    "wof:placetype":"venue"
},
  "geometry": {"coordinates":[-122.061886,37.669198],"type":"Point"}
}