{
  "type": "Feature",
  "properties": {
    "iso:country":"US",
    "sg:address":"2558 Cottage Way",
    "sg:city":"Sacramento",
    "sg:classifiers":[
        {
            "category":"Restaurant",
            "type":"Food & Drink"
        }
    ],
    "sg:phone":"+1 916 483 3730",
    "sg:postcode":"95825",
    "sg:province":"CA",
    "sg:tags":[
        "fish",
        "chip"
    ],
    "wof:name":"Ocean Fish & Chips",
    "wof:placetype":"venue"
},
  "geometry": {"coordinates":[-121.401905,38.603426],"type":"Point"}
}