{
  "type": "Feature",
  "properties": {
    "addr:full":"4266 Nottingham Dr Danville CA 94506",
    "addr:housenumber":"4266",
    "addr:postcode":"94506",
    "addr:street":"Nottingham Dr",
    "iso:country":"US",
    "sg:address":"4266 Nottingham Dr",
    "sg:city":"Danville",
    "sg:classifiers":[
        {
            "category":"Professional",
            "type":"Services"
        }
    ],
    "sg:phone":"+1 925 736 1835",
    "sg:postcode":"94506",
    "sg:province":"CA",
    "wof:name":"M Akhavan",
    "wof:placetype":"venue"
},
  "geometry": {"coordinates":[-121.910658,37.804322],"type":"Point"}
}