{
  "type": "Feature",
  "properties": {
    "iso:country":"US",
    "sg:address":"4460 Brooks St",
    "sg:city":"Montclair",
    "sg:classifiers":[
        {
            "category":"Real Estate",
            "subcategory":"Real Estate Agent",
            "type":"Services"
        }
    ],
    "sg:phone":"+1 909 635 1130",
    "sg:postcode":"91763",
    "sg:province":"CA",
    "wof:name":"Real Estate Solutions",
    "wof:placetype":"venue"
},
  "geometry": {"coordinates":[-117.709624,34.061732],"type":"Point"}
}