{
  "type": "Feature",
  "properties": {
    "iso:country":"US",
    "sg:address":"6025 Loynes Dr",
    "sg:city":"Long Beach",
    "sg:classifiers":[
        {
            "category":"Wholesale",
            "subcategory":"Machinery & Supplies",
            "type":"Manufacturing & Wholesale Goods"
        }
    ],
    "sg:phone":"+1 562 498 3573",
    "sg:postcode":"90803",
    "sg:province":"CA",
    "sg:tags":[
        "equipment",
        "plastic"
    ],
    "wof:name":"A C Plastics Machinery",
    "wof:placetype":"venue"
},
  "geometry": {"coordinates":[-118.114403,33.768025],"type":"Point"}
}