{
  "type": "Feature",
  "properties": {
    "addr:full":"3174 W Lincoln Ave Ste 100 Anaheim CA 92801",
    "addr:housenumber":"3174",
    "addr:postcode":"92801",
    "addr:street":"W Lincoln Ave Ste 100",
    "iso:country":"US",
    "sg:address":"3174 W Lincoln Ave Ste 100",
    "sg:city":"Anaheim",
    "sg:classifiers":[
        {
            "category":"Fast Food",
            "type":"Food & Drink"
        },
        {
            "category":"Food & Beverages",
            "subcategory":"Bakery",
            "type":"Retail Goods"
        }
    ],
    "sg:phone":"+1 714 527 0262",
    "sg:postcode":"92801",
    "sg:province":"CA",
    "sg:tags":[
        "sandwich"
    ],
    "sg:website":"www.subway.com",
    "wof:name":"Subway",
    "wof:placetype":"venue"
},
  "geometry": {"coordinates":[-117.919845,33.850839],"type":"Point"}
}