{
  "type": "Feature",
  "properties": {
    "addr:full":"860 Corn Camp Rd Buttonwillow CA 93206",
    "addr:housenumber":"860",
    "addr:postcode":"93206",
    "addr:street":"Corn Camp Rd",
    "iso:country":"US",
    "sg:address":"860 Corn Camp Rd",
    "sg:city":"Buttonwillow",
    "sg:classifiers":[
        {
            "category":"Manufacturing",
            "subcategory":"Textiles",
            "type":"Manufacturing & Wholesale Goods"
        }
    ],
    "sg:phone":"+1 661 764 5903",
    "sg:postcode":"93206",
    "sg:province":"CA",
    "sg:tags":[
        "processing",
        "cotton"
    ],
    "wof:name":"Burnt School Gin",
    "wof:placetype":"venue"
},
  "geometry": {"coordinates":[-119.51836,35.428552],"type":"Point"}
}