{
  "type": "Feature",
  "properties": {
    "addr:full":"37107 State Rte 299 E Burney CA 96013",
    "addr:housenumber":"37107",
    "addr:postcode":"96013",
    "addr:street":"State Rte 299 E",
    "iso:country":"US",
    "sg:address":"37107 State Rte 299 E",
    "sg:city":"Burney",
    "sg:classifiers":[
        {
            "category":"Real Estate",
            "subcategory":"Real Estate Agent",
            "type":"Services"
        }
    ],
    "sg:phone":"+1 530 335 4549",
    "sg:postcode":"96013",
    "sg:province":"CA",
    "wof:name":"Century 21",
    "wof:placetype":"venue"
},
  "geometry": {"coordinates":[-121.664312,40.882097],"type":"Point"}
}