{
  "type": "Feature",
  "properties": {
    "iso:country":"US",
    "sg:address":"918 N Morgan St",
    "sg:city":"Orange",
    "sg:classifiers":[
        {
            "category":"Professional",
            "subcategory":"Secretarial Services",
            "type":"Services"
        }
    ],
    "sg:phone":"+1 714 997 2516",
    "sg:postcode":"92867",
    "sg:province":"CA",
    "sg:tags":[
        "reporting",
        "court"
    ],
    "wof:name":"Helen Brown Secretarial-Orange",
    "wof:placetype":"venue"
},
  "geometry": {"coordinates":[-117.81989400000001,33.802471],"type":"Point"}
}