{
  "type": "Feature",
  "properties": {
    "iso:country":"US",
    "sg:address":"15150 Genova Ct",
    "sg:city":"Chino Hills",
    "sg:classifiers":[
        {
            "category":"Building & Trades",
            "subcategory":"Plumbing",
            "type":"Services"
        }
    ],
    "sg:phone":"+1 909 597 9190",
    "sg:postcode":"91709",
    "sg:province":"CA",
    "sg:tags":[
        "contractor"
    ],
    "wof:name":"Accelerated Air Conditioning",
    "wof:placetype":"venue"
},
  "geometry": {"coordinates":[-117.727019,33.979886],"type":"Point"}
}