{
  "type": "Feature",
  "properties": {
    "iso:country":"US",
    "sg:address":"4263 Overland Ave",
    "sg:city":"Culver City",
    "sg:classifiers":[
        {
            "category":"Restaurant",
            "type":"Food & Drink"
        }
    ],
    "sg:phone":"+1 310 559 8827",
    "sg:postcode":"90230",
    "sg:province":"CA",
    "sg:tags":[
        "traditional",
        "american"
    ],
    "sg:website":"tubschili.com/",
    "wof:name":"Tubs Fine Chili",
    "wof:placetype":"venue"
},
  "geometry": {"coordinates":[-118.400538,34.011763],"type":"Point"}
}