{
  "type": "Feature",
  "properties": {
    "iso:country":"US",
    "sg:address":"688 Broadway",
    "sg:city":"Sonoma",
    "sg:classifiers":[
        {
            "category":"Personal",
            "subcategory":"Massage",
            "type":"Services"
        }
    ],
    "sg:phone":"+1 707 939 3551",
    "sg:postcode":"95476",
    "sg:province":"CA",
    "sg:tags":[
        "salon",
        "beauty"
    ],
    "sg:website":"http://www.pierrettesofsonoma.com",
    "wof:name":"Pierrette's Of Sonoma",
    "wof:placetype":"venue"
},
  "geometry": {"coordinates":[-122.45835599999999,38.288497],"type":"Point"}
}