{
  "type": "Feature",
  "properties": {
    "iso:country":"US",
    "sg:address":"31080 Union City Blvd",
    "sg:city":"Union City",
    "sg:classifiers":[
        {
            "category":"Personal",
            "subcategory":"Beauty Salon",
            "type":"Services"
        }
    ],
    "sg:phone":"+1 510 441 1807",
    "sg:postcode":"94587",
    "sg:province":"CA",
    "wof:name":"From Hair To Eternity",
    "wof:placetype":"venue"
},
  "geometry": {"coordinates":[-122.080914,37.595586],"type":"Point"}
}