{
  "type": "Feature",
  "properties": {
    "addr:full":"72 S Main St Templeton CA 93465",
    "addr:housenumber":"72",
    "addr:postcode":"93465",
    "addr:street":"S Main St",
    "iso:country":"US",
    "sg:address":"72 S Main St",
    "sg:city":"Templeton",
    "sg:classifiers":[
        {
            "category":"Personal",
            "subcategory":"Beauty Salon",
            "type":"Services"
        }
    ],
    "sg:phone":"+1 805 434 5250",
    "sg:postcode":"93465",
    "sg:province":"CA",
    "sg:tags":[
        "spa",
        "day"
    ],
    "wof:name":"Cobalt Blue Dayspa",
    "wof:placetype":"venue"
},
  "geometry": {"coordinates":[-120.70232799999999,35.552793],"type":"Point"}
}