{
  "type": "Feature",
  "properties": {
    "addr:full":"3768 Harrison St Apt 204 Oakland CA 94611",
    "addr:housenumber":"3768;204",
    "addr:postcode":"94611",
    "addr:street":"Harrison St Apt",
    "iso:country":"US",
    "sg:address":"3768 Harrison St Apt 204",
    "sg:city":"Oakland",
    "sg:classifiers":[
        {
            "category":"Health Services",
            "subcategory":"Clinic",
            "type":"Services"
        }
    ],
    "sg:phone":"+1 510 655 1949",
    "sg:postcode":"94611",
    "sg:province":"CA",
    "sg:tags":[
        "welfare"
    ],
    "wof:name":"Beacon For Health",
    "wof:placetype":"venue"
},
  "geometry": {"coordinates":[-122.25239999999999,37.821006],"type":"Point"}
}