{
  "type": "Feature",
  "properties": {
    "addr:full":"3292 Sierra Rd San Jose CA 95132",
    "addr:housenumber":"3292",
    "addr:postcode":"95132",
    "addr:street":"Sierra Rd",
    "iso:country":"US",
    "sg:address":"3292 Sierra Rd",
    "sg:city":"San Jose",
    "sg:classifiers":[
        {
            "category":"Building & Trades",
            "subcategory":"Construction",
            "type":"Services"
        }
    ],
    "sg:phone":"+1 408 254 2559",
    "sg:postcode":"95132",
    "sg:province":"CA",
    "sg:tags":[
        "contractor"
    ],
    "wof:name":"C T Electric",
    "wof:placetype":"venue"
},
  "geometry": {"coordinates":[-121.847568,37.399312],"type":"Point"}
}