{
  "type": "Feature",
  "properties": {
    "addr:full":"505 E Romie Ln Salinas CA 93901",
    "addr:housenumber":"505",
    "addr:postcode":"93901",
    "addr:street":"E Romie Ln",
    "iso:country":"US",
    "sg:address":"505 E Romie Ln",
    "sg:city":"Salinas",
    "sg:classifiers":[
        {
            "category":"Health Services",
            "subcategory":"Doctor",
            "type":"Services"
        }
    ],
    "sg:phone":"+1 831 755 1701",
    "sg:postcode":"93901",
    "sg:province":"CA",
    "sg:tags":[
        "physician",
        "surgeon"
    ],
    "wof:name":"Los Palos Medical Assoc Inc",
    "wof:placetype":"venue"
},
  "geometry": {"coordinates":[-121.644751,36.659708],"type":"Point"}
}