{
  "type": "Feature",
  "properties": {
    "addr:full":"106 S Juniper St Escondido CA 92025",
    "addr:housenumber":"106",
    "addr:postcode":"92025",
    "addr:street":"S Juniper St",
    "iso:country":"US",
    "sg:address":"106 S Juniper St",
    "sg:city":"Escondido",
    "sg:classifiers":[
        {
            "category":"Personal",
            "subcategory":"Beauty Salon",
            "type":"Services"
        }
    ],
    "sg:phone":"+1 760 839 6906",
    "sg:postcode":"92025",
    "sg:province":"CA",
    "wof:name":"Caballero International",
    "wof:placetype":"venue"
},
  "geometry": {"coordinates":[-117.07838599999999,33.12265],"type":"Point"}
}