{
  "type": "Feature",
  "properties": {
    "iso:country":"US",
    "sg:address":"20 Bay Dr",
    "sg:city":"Bay Point",
    "sg:classifiers":[
        {
            "category":"Building & Trades",
            "subcategory":"Construction",
            "type":"Services"
        }
    ],
    "sg:phone":"+1 925 261 1591",
    "sg:postcode":"94565",
    "sg:province":"CA",
    "sg:tags":[
        "home",
        "improvement"
    ],
    "wof:name":"Rodriguez Complete Home Repair",
    "wof:placetype":"venue"
},
  "geometry": {"coordinates":[-121.963718,38.037241],"type":"Point"}
}