{
  "type": "Feature",
  "properties": {
    "addr:full":"2272 Trade Zone Blvd San Jose CA 95131",
    "addr:housenumber":"2272",
    "addr:postcode":"95131",
    "addr:street":"Trade Zone Blvd",
    "iso:country":"US",
    "sg:address":"2272 Trade Zone Blvd",
    "sg:city":"San Jose",
    "sg:classifiers":[
        {
            "category":"Wholesale",
            "subcategory":"Machinery & Supplies",
            "type":"Manufacturing & Wholesale Goods"
        }
    ],
    "sg:phone":"+1 408 934 0838",
    "sg:postcode":"95131",
    "sg:province":"CA",
    "wof:name":"K & K Machinery Inc",
    "wof:placetype":"venue"
},
  "geometry": {"coordinates":[-121.88788099999999,37.403174],"type":"Point"}
}