{
  "type": "Feature",
  "properties": {
    "addr:full":"34527 Heathrow Ter Fremont CA 94555",
    "addr:postcode":"34527;94555",
    "addr:street":"Ter",
    "iso:country":"US",
    "sg:address":"34527 Heathrow Ter",
    "sg:city":"Fremont",
    "sg:classifiers":[
        {
            "category":"Real Estate",
            "subcategory":"Real Estate Agent",
            "type":"Services"
        }
    ],
    "sg:phone":"+1 510 794 5701",
    "sg:postcode":"94555",
    "sg:province":"CA",
    "wof:name":"High Tech Appraisers",
    "wof:placetype":"venue"
},
  "geometry": {"coordinates":[-122.05777500000001,37.555125],"type":"Point"}
}