{
  "type": "Feature",
  "properties": {
    "iso:country":"US",
    "sg:address":"427 Main St",
    "sg:city":"Ferndale",
    "sg:classifiers":[
        {
            "category":"Education",
            "subcategory":"Junior College",
            "type":"Public Place"
        }
    ],
    "sg:phone":"+1 707 786 9006",
    "sg:postcode":"95536",
    "sg:province":"CA",
    "sg:tags":[
        "doll"
    ],
    "wof:name":"Annalisa's Doll House",
    "wof:placetype":"venue"
},
  "geometry": {"coordinates":[-124.26363499999999,40.576678],"type":"Point"}
}