{
  "type": "Feature",
  "properties": {
    "addr:full":"3580 Mt Acadia Blvd San Diego CA 92111",
    "addr:housenumber":"3580",
    "addr:postcode":"92111",
    "addr:street":"Mt Acadia Blvd",
    "iso:country":"US",
    "sg:address":"3580 Mt Acadia Blvd",
    "sg:city":"San Diego",
    "sg:classifiers":[
        {
            "category":"Social Services",
            "subcategory":"Child Care",
            "type":"Services"
        },
        {
            "category":"Education",
            "subcategory":"Preschool",
            "type":"Public Place"
        },
        {
            "category":"Education",
            "subcategory":"School",
            "type":"Public Place"
        }
    ],
    "sg:phone":"+1 858 560 0985",
    "sg:postcode":"92111",
    "sg:province":"CA",
    "sg:tags":[
        "elementary",
        "day"
    ],
    "wof:name":"Wee Care Preschool",
    "wof:placetype":"venue"
},
  "geometry": {"coordinates":[-117.18279099999999,32.806717],"type":"Point"}
}