{
  "type": "Feature",
  "properties": {
    "iso:country":"US",
    "sg:address":"955 Calimesa Blvd",
    "sg:city":"Calimesa",
    "sg:classifiers":[
        {
            "category":"Wholesale",
            "subcategory":"Toys & Hobbies",
            "type":"Manufacturing & Wholesale Goods"
        }
    ],
    "sg:phone":"+1 909 795 5640",
    "sg:postcode":"92320",
    "sg:province":"CA",
    "sg:tags":[
        "porcelain",
        "supply",
        "doll",
        "mfg"
    ],
    "wof:name":"Ceramics Things",
    "wof:placetype":"venue"
},
  "geometry": {"coordinates":[-117.061176,34.00175],"type":"Point"}
}