{
  "type": "Feature",
  "properties": {
    "addr:full":"663 W Clifton Ave Redlands CA 92373",
    "addr:housenumber":"663",
    "addr:postcode":"92373",
    "addr:street":"W Clifton Ave",
    "iso:country":"US",
    "sg:address":"663 W Clifton Ave",
    "sg:city":"Redlands",
    "sg:classifiers":[
        {
            "category":"Professional",
            "subcategory":"Business Services",
            "type":"Services"
        }
    ],
    "sg:phone":"+1 909 335 9151",
    "sg:postcode":"92373",
    "sg:province":"CA",
    "sg:tags":[
        "paralegal"
    ],
    "wof:name":"H & H Concepts",
    "wof:placetype":"venue"
},
  "geometry": {"coordinates":[-117.182118,34.041865],"type":"Point"}
}