{
  "type": "Feature",
  "properties": {
    "iso:country":"US",
    "sg:address":"5631 Lone Tree Way",
    "sg:city":"Brentwood",
    "sg:classifiers":[
        {
            "category":"Manufacturing",
            "subcategory":"Tools & Machinery",
            "type":"Manufacturing & Wholesale Goods"
        },
        {
            "category":"Retail",
            "subcategory":"Repair Shop",
            "type":"Services"
        },
        {
            "category":"Home & Garden",
            "subcategory":"Hardware",
            "type":"Retail Goods"
        },
        {
            "category":"Home & Garden",
            "subcategory":"Building Materials",
            "type":"Retail Goods"
        },
        {
            "category":"Wholesale",
            "subcategory":"Painting Supplies",
            "type":"Manufacturing & Wholesale Goods"
        },
        {
            "category":"Retail",
            "subcategory":"Auto Rental",
            "type":"Services"
        },
        {
            "category":"Building & Trades",
            "subcategory":"Equipment Rental",
            "type":"Services"
        }
    ],
    "sg:phone":"+1 925 513 6060",
    "sg:postcode":"94513",
    "sg:province":"CA",
    "sg:tags":[
        "yard",
        "rug",
        "improvement",
        "paint",
        "truck",
        "cleaning",
        "tools-renting",
        "contractors'",
        "store",
        "carpet"
    ],
    "sg:website":"http://clk.atdmt.com/IWC/go/266744407/direct/01/",
    "wof:name":"The Home Depot Tool Rental",
    "wof:placetype":"venue"
},
  "geometry": {"coordinates":[-121.746227,37.961568],"type":"Point"}
}