{
  "type": "Feature",
  "properties": {
    "addr:full":"16671 Malcolm Ln Yorba Linda CA 92886",
    "addr:housenumber":"16671",
    "addr:postcode":"92886",
    "addr:street":"Malcolm Ln",
    "iso:country":"US",
    "sg:address":"16671 Malcolm Ln",
    "sg:city":"Yorba Linda",
    "sg:classifiers":[
        {
            "category":"Manufacturing",
            "subcategory":"Signs",
            "type":"Manufacturing & Wholesale Goods"
        }
    ],
    "sg:phone":"+1 714 528 1460",
    "sg:postcode":"92886",
    "sg:province":"CA",
    "sg:tags":[
        "specialty",
        "mfg"
    ],
    "wof:name":"West Coast Signs Inc",
    "wof:placetype":"venue"
},
  "geometry": {"coordinates":[-117.842152,33.890817],"type":"Point"}
}