{
  "type": "Feature",
  "properties": {
    "iso:country":"US",
    "sg:address":"400 S el Camino Real",
    "sg:city":"San Mateo",
    "sg:classifiers":[
        {
            "category":"Social Services",
            "type":"Services"
        }
    ],
    "sg:phone":"+1 650 347 6415",
    "sg:postcode":"94402",
    "sg:province":"CA",
    "sg:tags":[
        "youth",
        "organization",
        "center"
    ],
    "sg:website":"www.jsa.org",
    "wof:name":"Junior Statesmen Foundation",
    "wof:placetype":"venue"
},
  "geometry": {"coordinates":[-122.324479,37.561645],"type":"Point"}
}