{
  "type": "Feature",
  "properties": {
    "iso:country":"US",
    "sg:address":"25 Skygate",
    "sg:city":"Aliso Viejo",
    "sg:classifiers":[
        {
            "category":"Professional",
            "type":"Services"
        }
    ],
    "sg:phone":"+1 949 448 0187",
    "sg:postcode":"92656",
    "sg:province":"CA",
    "wof:name":"Shirley A O Connor",
    "wof:placetype":"venue"
},
  "geometry": {"coordinates":[-117.740644,33.59383],"type":"Point"}
}