{
  "type": "Feature",
  "properties": {
    "iso:country":"US",
    "sg:address":"600 E Todd Rd",
    "sg:city":"Santa Rosa",
    "sg:classifiers":[
        {
            "category":"Wholesale",
            "subcategory":"Machinery & Supplies",
            "type":"Manufacturing & Wholesale Goods"
        }
    ],
    "sg:phone":"+1 707 588 1444",
    "sg:postcode":"95407",
    "sg:province":"CA",
    "sg:tags":[
        "equipment",
        "irrigation",
        "system"
    ],
    "sg:website":"www.driwater.com",
    "wof:name":"Driwater Inc",
    "wof:placetype":"venue"
},
  "geometry": {"coordinates":[-122.709008,38.387111],"type":"Point"}
}