{
  "type": "Feature",
  "properties": {
    "addr:full":"4435 S Santa Fe Ave Los Angeles CA 90058",
    "addr:housenumber":"4435",
    "addr:postcode":"90058",
    "addr:street":"S Santa Fe Ave",
    "iso:country":"US",
    "sg:address":"4435 S Santa Fe Ave",
    "sg:city":"Los Angeles",
    "sg:classifiers":[
        {
            "category":"Wholesale",
            "subcategory":"Machinery & Supplies",
            "type":"Manufacturing & Wholesale Goods"
        }
    ],
    "sg:phone":"+1 323 582 8321",
    "sg:postcode":"90058",
    "sg:province":"CA",
    "sg:tags":[
        "bushing"
    ],
    "wof:name":"Monarch Bearing Co",
    "wof:placetype":"venue"
},
  "geometry": {"coordinates":[-118.230209,34.000527],"type":"Point"}
}