{
  "type": "Feature",
  "properties": {
    "iso:country":"US",
    "sg:address":"7560 Woodman Pl",
    "sg:city":"Van Nuys",
    "sg:classifiers":[
        {
            "category":"Travel",
            "subcategory":"Campground",
            "type":"Entertainment"
        }
    ],
    "sg:phone":"+1 818 785 6266",
    "sg:postcode":"91405",
    "sg:province":"CA",
    "wof:name":"Sierra Springs Village",
    "wof:placetype":"venue"
},
  "geometry": {"coordinates":[-118.43003899999999,34.20705],"type":"Point"}
}