{
  "type": "Feature",
  "properties": {
    "iso:country":"US",
    "sg:address":"38855 Barrington St",
    "sg:city":"Palmdale",
    "sg:classifiers":[
        {
            "category":"Wholesale",
            "subcategory":"Durable Goods & Equipment",
            "type":"Manufacturing & Wholesale Goods"
        }
    ],
    "sg:phone":"+1 661 538 1289",
    "sg:postcode":"93551",
    "sg:province":"CA",
    "sg:tags":[
        "importer"
    ],
    "wof:name":"Bestway Autosports",
    "wof:placetype":"venue"
},
  "geometry": {"coordinates":[-118.17676400000001,34.588359],"type":"Point"}
}