{
  "type": "Feature",
  "properties": {
    "addr:full":"500 Potrero Grande Dr Monterey Park CA 91755",
    "addr:housenumber":"500",
    "addr:postcode":"91755",
    "addr:street":"Potrero Grande Dr",
    "iso:country":"US",
    "sg:address":"500 Potrero Grande Dr",
    "sg:city":"Monterey Park",
    "sg:classifiers":[
        {
            "category":"Home & Garden",
            "subcategory":"Garden Supply",
            "type":"Retail Goods"
        }
    ],
    "sg:phone":"+1 323 728 4044",
    "sg:postcode":"91755",
    "sg:province":"CA",
    "sg:tags":[
        "nursery",
        "gardening"
    ],
    "wof:name":"Landscape Growers Nursery",
    "wof:placetype":"venue"
},
  "geometry": {"coordinates":[-118.120003,34.033901],"type":"Point"}
}