{
  "type": "Feature",
  "properties": {
    "addr:full":"9235 Research Dr Irvine CA 92618",
    "addr:housenumber":"9235",
    "addr:postcode":"92618",
    "addr:street":"Research Dr",
    "iso:country":"US",
    "sg:address":"9235 Research Dr",
    "sg:city":"Irvine",
    "sg:classifiers":[
        {
            "category":"Health Services",
            "subcategory":"Optometrist",
            "type":"Services"
        }
    ],
    "sg:phone":"+1 949 379 3970",
    "sg:postcode":"92618",
    "sg:province":"CA",
    "wof:name":"Usa Vision System",
    "wof:placetype":"venue"
},
  "geometry": {"coordinates":[-117.736017,33.638592],"type":"Point"}
}