{
  "type": "Feature",
  "properties": {
    "addr:full":"302 Virginia Ave Modesto CA 95354",
    "addr:housenumber":"302",
    "addr:postcode":"ca 95354",
    "addr:street":"Virginia Ave",
    "iso:country":"US",
    "sg:address":"302 Virginia Ave",
    "sg:city":"Modesto",
    "sg:classifiers":[
        {
            "category":"Manufacturing",
            "subcategory":"Buildings",
            "type":"Manufacturing & Wholesale Goods"
        },
        {
            "category":"Building & Trades",
            "subcategory":"Construction",
            "type":"Services"
        }
    ],
    "sg:phone":"+1 209 526 2283",
    "sg:postcode":"95354",
    "sg:province":"CA",
    "sg:tags":[
        "home",
        "builder",
        "contractor"
    ],
    "wof:name":"Cabrick Construction Inc",
    "wof:placetype":"venue"
},
  "geometry": {"coordinates":[-121.00282300000001,37.648516],"type":"Point"}
}