{
  "type": "Feature",
  "properties": {
    "iso:country":"US",
    "sg:address":"22809 Tamarack Ln",
    "sg:city":"Santa Clarita",
    "sg:classifiers":[
        {
            "category":"Building & Trades",
            "subcategory":"Construction",
            "type":"Services"
        }
    ],
    "sg:phone":"+1 661 296 5527",
    "sg:postcode":"91390",
    "sg:province":"CA",
    "sg:tags":[
        "house"
    ],
    "wof:name":"M Storvis Const",
    "wof:placetype":"venue"
},
  "geometry": {"coordinates":[-118.535475,34.471887],"type":"Point"}
}