{
  "type": "Feature",
  "properties": {
    "addr:full":"2727 N 11th Ave Hanford CA 93230",
    "addr:housenumber":"2727",
    "addr:postcode":"ca 93230",
    "addr:street":"N 11Th Ave",
    "iso:country":"US",
    "sg:address":"2727 N 11th Ave",
    "sg:city":"Hanford",
    "sg:classifiers":[
        {
            "category":"Real Estate",
            "subcategory":"Real Estate Operator",
            "type":"Services"
        }
    ],
    "sg:phone":"+1 559 587 9999",
    "sg:postcode":"93230",
    "sg:province":"CA",
    "sg:tags":[
        "building",
        "apartment"
    ],
    "wof:name":"Wilshire Retirement Residence",
    "wof:placetype":"venue"
},
  "geometry": {"coordinates":[-119.65511100000001,36.36003],"type":"Point"}
}