{
  "type": "Feature",
  "properties": {
    "addr:full":"1585 Heartwood Dr Mckinleyville CA 95519",
    "addr:housenumber":"1585",
    "addr:postcode":"95519",
    "addr:street":"Heartwood Dr",
    "iso:country":"US",
    "sg:address":"1585 Heartwood Dr",
    "sg:city":"Mckinleyville",
    "sg:classifiers":[
        {
            "category":"Professional",
            "subcategory":"Engineering",
            "type":"Services"
        }
    ],
    "sg:phone":"+1 707 839 4336",
    "sg:postcode":"95519",
    "sg:province":"CA",
    "sg:tags":[
        "engineer"
    ],
    "wof:name":"Spencer Engineering",
    "wof:placetype":"venue"
},
  "geometry": {"coordinates":[-124.09974699999999,40.939573],"type":"Point"}
}