{
  "type": "Feature",
  "properties": {
    "addr:full":"4444 W Riverside Dr Burbank CA 91505",
    "addr:housenumber":"4444",
    "addr:postcode":"91505",
    "addr:street":"W Riverside Dr",
    "iso:country":"US",
    "sg:address":"4444 W Riverside Dr",
    "sg:city":"Burbank",
    "sg:classifiers":[
        {
            "category":"Health Services",
            "subcategory":"Health Practitioner",
            "type":"Services"
        }
    ],
    "sg:phone":"+1 818 848 2305",
    "sg:postcode":"91505",
    "sg:province":"CA",
    "sg:tags":[
        "psychologist"
    ],
    "wof:name":"Ann Bassett",
    "wof:placetype":"venue"
},
  "geometry": {"coordinates":[-118.34863,34.152134],"type":"Point"}
}