{
  "type": "Feature",
  "properties": {
    "addr:full":"5636 York Blvd Los Angeles CA 90042",
    "addr:housenumber":"5636",
    "addr:postcode":"90042",
    "addr:street":"York Blvd",
    "iso:country":"US",
    "sg:address":"5636 York Blvd",
    "sg:city":"Los Angeles",
    "sg:classifiers":[
        {
            "category":"Food & Beverages",
            "subcategory":"Groceries & Convenience Stores",
            "type":"Retail Goods"
        }
    ],
    "sg:phone":"+1 323 259 0280",
    "sg:postcode":"90042",
    "sg:province":"CA",
    "sg:tags":[
        "grocer"
    ],
    "wof:name":"El Latino Market",
    "wof:placetype":"venue"
},
  "geometry": {"coordinates":[-118.19614799999999,34.119261],"type":"Point"}
}