{
  "type": "Feature",
  "properties": {
    "addr:full":"18353 Vanowen St Reseda CA 91335",
    "addr:postcode":"18353;91335",
    "addr:street":"Vanowen St",
    "iso:country":"US",
    "sg:address":"18353 Vanowen St",
    "sg:city":"Reseda",
    "sg:classifiers":[
        {
            "category":"Home & Garden",
            "subcategory":"Furniture",
            "type":"Retail Goods"
        }
    ],
    "sg:phone":"+1 818 881 2605",
    "sg:postcode":"91335",
    "sg:province":"CA",
    "wof:name":"Bargain City",
    "wof:placetype":"venue"
},
  "geometry": {"coordinates":[-118.53446099999999,34.19393],"type":"Point"}
}