{
  "type": "Feature",
  "properties": {
    "addr:full":"700 Airport Blvd Burlingame CA 94010",
    "addr:housenumber":"700",
    "addr:postcode":"94010",
    "addr:street":"Airport Blvd",
    "iso:country":"US",
    "sg:address":"700 Airport Blvd",
    "sg:city":"Burlingame",
    "sg:classifiers":[
        {
            "category":"Food & Beverages",
            "subcategory":"Specialty",
            "type":"Retail Goods"
        }
    ],
    "sg:phone":"+1 650 344 4001",
    "sg:postcode":"94010",
    "sg:province":"CA",
    "sg:tags":[
        "tea",
        "coffee"
    ],
    "wof:name":"Daily Perk Espresso Co",
    "wof:placetype":"venue"
},
  "geometry": {"coordinates":[-122.344015,37.589469],"type":"Point"}
}