{
  "type": "Feature",
  "properties": {
    "iso:country":"US",
    "sg:address":"460 North St",
    "sg:city":"Montague",
    "sg:classifiers":[
        {
            "category":"Building & Trades",
            "subcategory":"Cleaning & Sanitation",
            "type":"Services"
        }
    ],
    "sg:phone":"+1 530 459 5131",
    "sg:postcode":"96064",
    "sg:province":"CA",
    "sg:tags":[
        "janitor"
    ],
    "wof:name":"E Z Carpet Cleaning & Jntrl",
    "wof:placetype":"venue"
},
  "geometry": {"coordinates":[-122.51689399999999,41.732938],"type":"Point"}
}