{
  "type": "Feature",
  "properties": {
    "addr:full":"222 Barber Ln Milpitas CA 95035",
    "addr:housenumber":"222",
    "addr:postcode":"95035",
    "addr:street":"Barber Ln",
    "iso:country":"US",
    "sg:address":"222 Barber Ln",
    "sg:city":"Milpitas",
    "sg:classifiers":[
        {
            "category":"Restaurant",
            "type":"Food & Drink"
        }
    ],
    "sg:postcode":"95035",
    "sg:province":"CA",
    "sg:tags":[
        "korean"
    ],
    "wof:name":"In Chon Tofu",
    "wof:placetype":"venue"
},
  "geometry": {"coordinates":[-121.918823,37.423202],"type":"Point"}
}