{
  "type": "Feature",
  "properties": {
    "iso:country":"US",
    "sg:address":"5001 Birch St",
    "sg:city":"Newport Beach",
    "sg:classifiers":[
        {
            "category":"Banks & Credit Unions",
            "subcategory":"Bank",
            "type":"Services"
        }
    ],
    "sg:phone":"+1 949 553 1888",
    "sg:postcode":"92660",
    "sg:province":"CA",
    "sg:tags":[
        "loan",
        "real estate"
    ],
    "wof:name":"Reliance Financial Corp",
    "wof:placetype":"venue"
},
  "geometry": {"coordinates":[-117.86047000000001,33.667458],"type":"Point"}
}