{
  "type": "Feature",
  "properties": {
    "addr:full":"3111 Shattuck Ave Berkeley CA 94705",
    "addr:housenumber":"3111",
    "addr:postcode":"94705",
    "addr:street":"Shattuck Ave",
    "iso:country":"US",
    "sg:address":"3111 Shattuck Ave",
    "sg:city":"Berkeley",
    "sg:classifiers":[
        {
            "category":"Health Services",
            "subcategory":"Health Practitioner",
            "type":"Services"
        }
    ],
    "sg:phone":"+1 510 227 4028",
    "sg:postcode":"94705",
    "sg:province":"CA",
    "sg:tags":[
        "acupuncture"
    ],
    "sg:website":"the-yellow-emperor.com/",
    "wof:name":"The Yellow Emperor Community Acupuncture Clinic",
    "wof:placetype":"venue"
},
  "geometry": {"coordinates":[-122.265829,37.852649],"type":"Point"}
}