{
  "type": "Feature",
  "properties": {
    "addr:full":"6002 Klump Ave North Hollywood CA 91606",
    "addr:housenumber":"6002",
    "addr:postcode":"91606",
    "addr:street":"Klump Ave",
    "iso:country":"US",
    "sg:address":"6002 Klump Ave",
    "sg:city":"North Hollywood",
    "sg:classifiers":[
        {
            "category":"Manufacturing",
            "subcategory":"Printing",
            "type":"Manufacturing & Wholesale Goods"
        }
    ],
    "sg:phone":"+1 818 760 3158",
    "sg:postcode":"91606",
    "sg:province":"CA",
    "sg:tags":[
        "newspaper",
        "advertising"
    ],
    "wof:name":"El Columbiano Newspaper",
    "wof:placetype":"venue"
},
  "geometry": {"coordinates":[-118.37568899999999,34.181198],"type":"Point"}
}