{
  "type": "Feature",
  "properties": {
    "iso:country":"US",
    "sg:address":"15260 Fairgrove Ave",
    "sg:city":"La Puente",
    "sg:classifiers":[
        {
            "category":"Health Services",
            "subcategory":"Doctor",
            "type":"Services"
        }
    ],
    "sg:phone":"+1 626 968 4733",
    "sg:postcode":"91744",
    "sg:province":"CA",
    "sg:tags":[
        "dentist"
    ],
    "wof:name":"Fairgrove Dental Ctr",
    "wof:placetype":"venue"
},
  "geometry": {"coordinates":[-117.949899,34.042331],"type":"Point"}
}