{
  "type": "Feature",
  "properties": {
    "addr:full":"6801 Sikorsky St San Diego CA 92154",
    "addr:housenumber":"6801",
    "addr:postcode":"92154",
    "addr:street":"Sikorsky St",
    "iso:country":"US",
    "sg:address":"6801 Sikorsky St",
    "sg:city":"San Diego",
    "sg:classifiers":[
        {
            "category":"Retail",
            "subcategory":"Auto Repair",
            "type":"Services"
        }
    ],
    "sg:phone":"+1 619 661 7114",
    "sg:postcode":"92154",
    "sg:province":"CA",
    "sg:tags":[
        "automobile",
        "installation",
        "glass"
    ],
    "wof:name":"Dave's Auto Glass",
    "wof:placetype":"venue"
},
  "geometry": {"coordinates":[-116.993483,32.569797],"type":"Point"}
}