{
  "type": "Feature",
  "properties": {
    "addr:full":"4564 Garfield St La Mesa CA 91941",
    "addr:housenumber":"4564",
    "addr:postcode":"91941",
    "addr:street":"Garfield St",
    "iso:country":"US",
    "sg:address":"4564 Garfield St",
    "sg:city":"La Mesa",
    "sg:classifiers":[
        {
            "category":"Building & Trades",
            "subcategory":"Plumbing",
            "type":"Services"
        }
    ],
    "sg:phone":"+1 619 667 0390",
    "sg:postcode":"91941",
    "sg:province":"CA",
    "sg:tags":[
        "plumbing",
        "contractor"
    ],
    "wof:name":"Streamline Plumbing",
    "wof:placetype":"venue"
},
  "geometry": {"coordinates":[-117.00417400000001,32.760762],"type":"Point"}
}