{
  "type": "Feature",
  "properties": {
    "iso:country":"US",
    "sg:address":"14043 Parthenia St",
    "sg:city":"Panorama City",
    "sg:classifiers":[
        {
            "category":"Professional",
            "type":"Services"
        }
    ],
    "sg:phone":"+1 818 895 7568",
    "sg:postcode":"91402",
    "sg:province":"CA",
    "wof:name":"Raul Espinoza",
    "wof:placetype":"venue"
},
  "geometry": {"coordinates":[-118.439228,34.229726],"type":"Point"}
}