{
  "type": "Feature",
  "properties": {
    "addr:full":"40044 Hwy 49 Oakhurst CA 93644",
    "addr:housenumber":"40044",
    "addr:postcode":"93644",
    "addr:street":"Hwy 49",
    "iso:country":"US",
    "sg:address":"40044 Hwy 49",
    "sg:city":"Oakhurst",
    "sg:classifiers":[
        {
            "category":"Shopping",
            "subcategory":"Pharmacy",
            "type":"Retail Goods"
        }
    ],
    "sg:phone":"+1 559 642 4222",
    "sg:postcode":"93644",
    "sg:province":"CA",
    "wof:name":"Longs Drug",
    "wof:placetype":"venue"
},
  "geometry": {"coordinates":[-119.65580199999999,37.331107],"type":"Point"}
}