{
  "type": "Feature",
  "properties": {
    "addr:full":"13470 Lincoln Way Auburn CA 95603",
    "addr:housenumber":"13470",
    "addr:postcode":"ca 95603",
    "addr:street":"Lincoln Way",
    "iso:country":"US",
    "sg:address":"13470 Lincoln Way",
    "sg:city":"Auburn",
    "sg:classifiers":[
        {
            "category":"Restaurant",
            "type":"Food & Drink"
        }
    ],
    "sg:phone":"+1 530 823 1772",
    "sg:postcode":"95603",
    "sg:province":"CA",
    "sg:tags":[
        "shop",
        "coffee"
    ],
    "wof:name":"Coffee Classic",
    "wof:placetype":"venue"
},
  "geometry": {"coordinates":[-121.056055,38.926652],"type":"Point"}
}