{
  "type": "Feature",
  "properties": {
    "addr:full":"144 Matheson St Healdsburg CA 95448",
    "addr:housenumber":"144",
    "addr:postcode":"95448",
    "addr:street":"Matheson St",
    "iso:country":"US",
    "sg:address":"144 Matheson St",
    "sg:city":"Healdsburg",
    "sg:classifiers":[
        {
            "category":"Banks & Credit Unions",
            "subcategory":"Investment Brokerage",
            "type":"Services"
        }
    ],
    "sg:phone":"+1 707 433 7827",
    "sg:postcode":"95448",
    "sg:province":"CA",
    "sg:tags":[
        "stock",
        "bond"
    ],
    "wof:name":"Edward Jones Co",
    "wof:placetype":"venue"
},
  "geometry": {"coordinates":[-122.86855300000001,38.610609],"type":"Point"}
}