{
  "type": "Feature",
  "properties": {
    "iso:country":"US",
    "sg:address":"1104 Pheasant Ct",
    "sg:city":"San Marcos",
    "sg:classifiers":[
        {
            "category":"Professional",
            "subcategory":"Management & Consulting",
            "type":"Services"
        }
    ],
    "sg:phone":"+1 760 752 9311",
    "sg:postcode":"92078",
    "sg:province":"CA",
    "sg:tags":[
        "retail",
        "direct",
        "sales"
    ],
    "wof:name":"Birthangelcompany",
    "wof:placetype":"venue"
},
  "geometry": {"coordinates":[-117.193434,33.124799],"type":"Point"}
}