{
  "type": "Feature",
  "properties": {
    "addr:full":"1214 E Madison Ave Santa Ana CA 92707",
    "addr:housenumber":"1214",
    "addr:postcode":"92707",
    "addr:street":"E Madison Ave",
    "iso:country":"US",
    "sg:address":"1214 E Madison Ave",
    "sg:city":"Santa Ana",
    "sg:classifiers":[
        {
            "category":"Manufacturing",
            "subcategory":"Printing",
            "type":"Manufacturing & Wholesale Goods"
        }
    ],
    "sg:phone":"+1 714 401 5391",
    "sg:postcode":"92707",
    "sg:province":"CA",
    "sg:tags":[
        "lithographic",
        "commercial"
    ],
    "wof:name":"Master Screen Printing",
    "wof:placetype":"venue"
},
  "geometry": {"coordinates":[-117.85497599999999,33.727313],"type":"Point"}
}