{
  "type": "Feature",
  "properties": {
    "addr:full":"1091 Pinehurst Ln Palm Desert CA 92260",
    "addr:housenumber":"1091",
    "addr:postcode":"ca 92260",
    "addr:street":"Pinehurst Ln",
    "iso:country":"US",
    "sg:address":"1091 Pinehurst Ln",
    "sg:city":"Palm Desert",
    "sg:classifiers":[
        {
            "category":"Professional",
            "subcategory":"Lawyer & Legal Services",
            "type":"Services"
        }
    ],
    "sg:phone":"+1 760 837 3833",
    "sg:postcode":"92260",
    "sg:province":"CA",
    "sg:tags":[
        "attorney"
    ],
    "wof:name":"King & Ferlauto",
    "wof:placetype":"venue"
},
  "geometry": {"coordinates":[-116.358732,33.751941],"type":"Point"}
}