{
  "type": "Feature",
  "properties": {
    "iso:country":"US",
    "sg:address":"15315 S Figueroa Street",
    "sg:city":"Gardena",
    "sg:classifiers":[
        {
            "category":"Restaurant",
            "type":"Food & Drink"
        }
    ],
    "sg:phone":"+1 310 516 0047",
    "sg:postcode":"90248",
    "sg:province":"CA",
    "wof:name":"Kunchorn Thai Food",
    "wof:placetype":"venue"
},
  "geometry": {"coordinates":[-118.296387,33.870528],"type":"Point"}
}