{
  "type": "Feature",
  "properties": {
    "addr:full":"8211 Medill Ave El Cajon CA 92021",
    "addr:housenumber":"8211",
    "addr:postcode":"92021",
    "addr:street":"Medill Ave",
    "iso:country":"US",
    "sg:address":"8211 Medill Ave",
    "sg:city":"El Cajon",
    "sg:classifiers":[
        {
            "category":"Building & Trades",
            "subcategory":"Construction",
            "type":"Services"
        }
    ],
    "sg:phone":"+1 619 443 1979",
    "sg:postcode":"92021",
    "sg:province":"CA",
    "sg:tags":[
        "contractor"
    ],
    "wof:name":"Konrad S Leak & Assoc",
    "wof:placetype":"venue"
},
  "geometry": {"coordinates":[-116.908226,32.827905],"type":"Point"}
}