{
  "type": "Feature",
  "properties": {
    "addr:full":"15400 Civic Dr Victorville CA 92392",
    "addr:housenumber":"15400",
    "addr:postcode":"92392",
    "addr:street":"Civic Dr",
    "iso:country":"US",
    "sg:address":"15400 Civic Dr",
    "sg:city":"Victorville",
    "sg:classifiers":[
        {
            "category":"Government",
            "subcategory":"Office",
            "type":"Public Place"
        }
    ],
    "sg:phone":"+1 760 243 5227",
    "sg:postcode":"92392",
    "sg:province":"CA",
    "sg:tags":[
        "county",
        "resource"
    ],
    "wof:name":"San Bernardino Child Support",
    "wof:placetype":"venue"
},
  "geometry": {"coordinates":[-117.328605,34.50993],"type":"Point"}
}