{
  "type": "Feature",
  "properties": {
    "addr:full":"1100 Howe Ave Sacramento CA 95825",
    "addr:housenumber":"1100",
    "addr:postcode":"95825",
    "addr:street":"Howe Ave",
    "iso:country":"US",
    "sg:address":"1100 Howe Ave",
    "sg:city":"Sacramento",
    "sg:classifiers":[
        {
            "category":"Real Estate",
            "subcategory":"Real Estate Services",
            "type":"Services"
        },
        {
            "category":"Real Estate",
            "subcategory":"Real Estate Operator",
            "type":"Services"
        }
    ],
    "sg:phone":"+1 916 927 0571",
    "sg:postcode":"95825",
    "sg:province":"CA",
    "sg:tags":[
        "apartment",
        "rental",
        "finder"
    ],
    "wof:name":"Fair Lake Apartments",
    "wof:placetype":"venue"
},
  "geometry": {"coordinates":[-121.41541700000001,38.585622],"type":"Point"}
}