{
  "type": "Feature",
  "properties": {
    "iso:country":"US",
    "sg:address":"11355 Santa Monica Blvd",
    "sg:city":"Los Angeles",
    "sg:classifiers":[
        {
            "category":"Food & Beverages",
            "subcategory":"Specialty",
            "type":"Retail Goods"
        }
    ],
    "sg:phone":"+1 310 477 2663",
    "sg:postcode":"90025",
    "sg:province":"CA",
    "sg:tags":[
        "oriental"
    ],
    "wof:name":"Kabuki Gifts & Imports",
    "wof:placetype":"venue"
},
  "geometry": {"coordinates":[-118.45045399999999,34.046012],"type":"Point"}
}