{
  "type": "Feature",
  "properties": {
    "addr:full":"5124 Churchward St San Diego CA 92114",
    "addr:housenumber":"5124",
    "addr:postcode":"92114",
    "addr:street":"Churchward St",
    "iso:country":"US",
    "sg:address":"5124 Churchward St",
    "sg:city":"San Diego",
    "sg:classifiers":[
        {
            "category":"Organizations",
            "subcategory":"Religious Organization",
            "type":"Services"
        }
    ],
    "sg:phone":"+1 619 264 3165",
    "sg:postcode":"92114",
    "sg:province":"CA",
    "sg:tags":[
        "school"
    ],
    "wof:name":"Saint Ritas Church",
    "wof:placetype":"venue"
},
  "geometry": {"coordinates":[-117.083512,32.704161],"type":"Point"}
}