{
  "type": "Feature",
  "properties": {
    "iso:country":"US",
    "sg:address":"585 W Sierra Ave",
    "sg:city":"Fresno",
    "sg:classifiers":[
        {
            "category":"Professional",
            "type":"Services"
        }
    ],
    "sg:phone":"+1 559 431 5511",
    "sg:postcode":"93704",
    "sg:province":"CA",
    "wof:name":"Digital Editing",
    "wof:placetype":"venue"
},
  "geometry": {"coordinates":[-119.803353,36.830007],"type":"Point"}
}