{
  "type": "Feature",
  "properties": {
    "iso:country":"US",
    "sg:address":"9825 Carroll Centre Rd",
    "sg:city":"San Diego",
    "sg:classifiers":[
        {
            "category":"Shopping",
            "type":"Retail Goods"
        }
    ],
    "sg:phone":"+1 858 689 1121",
    "sg:postcode":"92126",
    "sg:province":"CA",
    "sg:tags":[
        "aquarium"
    ],
    "wof:name":"Aqua C",
    "wof:placetype":"venue"
},
  "geometry": {"coordinates":[-117.12179,32.899065],"type":"Point"}
}