{
  "type": "Feature",
  "properties": {
    "addr:full":"19382 Lemon Hill Dr Santa Ana CA 92705",
    "addr:housenumber":"19382",
    "addr:postcode":"92705",
    "addr:street":"Lemon Hill Dr",
    "iso:country":"US",
    "sg:address":"19382 Lemon Hill Dr",
    "sg:city":"Santa Ana",
    "sg:classifiers":[
        {
            "category":"Wholesale",
            "subcategory":"Apparel",
            "type":"Manufacturing & Wholesale Goods"
        }
    ],
    "sg:phone":"+1 714 505 5855",
    "sg:postcode":"92705",
    "sg:province":"CA",
    "sg:tags":[
        "handbag"
    ],
    "wof:name":"Grapevine Merchandising",
    "wof:placetype":"venue"
},
  "geometry": {"coordinates":[-117.794543,33.770279],"type":"Point"}
}