{
  "type": "Feature",
  "properties": {
    "addr:full":"2525 Whitaker Bluff Rd Tomales CA 94952",
    "addr:housenumber":"2525",
    "addr:postcode":"94952",
    "addr:street":"Whitaker Bluff Rd",
    "iso:country":"US",
    "sg:address":"2525 Whitaker Bluff Rd",
    "sg:city":"Tomales",
    "sg:classifiers":[
        {
            "category":"Education",
            "subcategory":"Special Training",
            "type":"Public Place"
        }
    ],
    "sg:phone":"+1 707 878 2456",
    "sg:postcode":"94952",
    "sg:province":"CA",
    "sg:tags":[
        "aid",
        "instruction",
        "first"
    ],
    "wof:name":"Be Ready-U Lrn Cpr & First Aid",
    "wof:placetype":"venue"
},
  "geometry": {"coordinates":[-122.900335,38.27641],"type":"Point"}
}