{
  "type": "Feature",
  "properties": {
    "addr:full":"3900 Sandra Dr Bakersfield CA 93304",
    "addr:housenumber":"3900",
    "addr:postcode":"93304",
    "addr:street":"Sandra Dr",
    "iso:country":"US",
    "sg:address":"3900 Sandra Dr",
    "sg:city":"Bakersfield",
    "sg:classifiers":[
        {
            "category":"Building & Trades",
            "subcategory":"Equipment Rental",
            "type":"Services"
        }
    ],
    "sg:phone":"+1 661 831 4177",
    "sg:postcode":"93304",
    "sg:province":"CA",
    "sg:tags":[
        "crane"
    ],
    "wof:name":"Oilfield Crane Svc",
    "wof:placetype":"venue"
},
  "geometry": {"coordinates":[-119.01631399999999,35.319292],"type":"Point"}
}