{
  "type": "Feature",
  "properties": {
    "addr:full":"5236 Geer Rd Hughson CA 95326",
    "addr:housenumber":"5236",
    "addr:postcode":"95326",
    "addr:street":"Geer Rd",
    "iso:country":"US",
    "sg:address":"5236 Geer Rd",
    "sg:city":"Hughson",
    "sg:classifiers":[
        {
            "category":"Manufacturing",
            "subcategory":"Food",
            "type":"Manufacturing & Wholesale Goods"
        }
    ],
    "sg:phone":"+1 209 669 6323",
    "sg:postcode":"95326",
    "sg:province":"CA",
    "sg:tags":[
        "winery"
    ],
    "wof:name":"Beekman & Beekman",
    "wof:placetype":"venue"
},
  "geometry": {"coordinates":[-120.846929,37.559093],"type":"Point"}
}