{
  "type": "Feature",
  "properties": {
    "addr:full":"1818 Harmon St Berkeley CA 94703",
    "addr:housenumber":"1818",
    "addr:postcode":"94703",
    "addr:street":"Harmon St",
    "iso:country":"US",
    "sg:address":"1818 Harmon St",
    "sg:city":"Berkeley",
    "sg:classifiers":[
        {
            "category":"Building & Trades",
            "subcategory":"Construction",
            "type":"Services"
        }
    ],
    "sg:phone":"+1 510 841 5533",
    "sg:postcode":"94703",
    "sg:province":"CA",
    "sg:tags":[
        "abatement",
        "lead",
        "removal"
    ],
    "wof:name":"Marfield Co Inc",
    "wof:placetype":"venue"
},
  "geometry": {"coordinates":[-122.271677,37.849554],"type":"Point"}
}