{
  "type": "Feature",
  "properties": {
    "iso:country":"US",
    "sg:address":"10285 Central Ave",
    "sg:city":"Montclair",
    "sg:classifiers":[
        {
            "category":"Professional",
            "subcategory":"Employment Agencies",
            "type":"Services"
        }
    ],
    "sg:phone":"+1 909 399 9009",
    "sg:postcode":"91763",
    "sg:province":"CA",
    "sg:tags":[
        "help",
        "contractor"
    ],
    "wof:name":"Express Personnel Svc",
    "wof:placetype":"venue"
},
  "geometry": {"coordinates":[-117.689469,34.070159],"type":"Point"}
}