{
  "type": "Feature",
  "properties": {
    "iso:country":"US",
    "sg:address":"3336 W Rosecrans Ave",
    "sg:city":"Hawthorne",
    "sg:classifiers":[
        {
            "category":"Home & Garden",
            "subcategory":"Home Furnishings",
            "type":"Retail Goods"
        }
    ],
    "sg:phone":"+1 310 675 3212",
    "sg:postcode":"90250",
    "sg:province":"CA",
    "sg:tags":[
        "bath",
        "kitchen"
    ],
    "sg:website":"www.faucetsgaloretileandstone.com",
    "wof:name":"Faucets Galore",
    "wof:placetype":"venue"
},
  "geometry": {"coordinates":[-118.331594,33.901925],"type":"Point"}
}