{
  "type": "Feature",
  "properties": {
    "addr:full":"16252 Swartz Canyon Rd Ramona CA 92065",
    "addr:housenumber":"16252",
    "addr:postcode":"92065",
    "addr:street":"Swartz Canyon Rd",
    "iso:country":"US",
    "sg:address":"16252 Swartz Canyon Rd",
    "sg:city":"Ramona",
    "sg:classifiers":[
        {
            "category":"Building & Trades",
            "subcategory":"Construction",
            "type":"Services"
        }
    ],
    "sg:phone":"+1 619 992 6117",
    "sg:postcode":"92065",
    "sg:province":"CA",
    "sg:tags":[
        "house"
    ],
    "wof:name":"D R Schafer Construction",
    "wof:placetype":"venue"
},
  "geometry": {"coordinates":[-116.804789,33.014447],"type":"Point"}
}