{
  "type": "Feature",
  "properties": {
    "iso:country":"US",
    "sg:address":"1590 Indiana St",
    "sg:city":"San Francisco",
    "sg:classifiers":[
        {
            "category":"Taxi",
            "type":"Transportation"
        }
    ],
    "sg:phone":"+1 415 781 1138",
    "sg:postcode":"94107",
    "sg:province":"CA",
    "sg:tags":[
        "taxicab"
    ],
    "wof:name":"Diamond Cab Co",
    "wof:placetype":"venue"
},
  "geometry": {"coordinates":[-122.390603,37.75128],"type":"Point"}
}