{
  "type": "Feature",
  "properties": {
    "addr:full":"5305 White Oak Ave Encino CA 91316",
    "addr:housenumber":"5305",
    "addr:postcode":"91316",
    "addr:street":"White Oak Ave",
    "iso:country":"US",
    "sg:address":"5305 White Oak Ave",
    "sg:city":"Encino",
    "sg:classifiers":[
        {
            "category":"Real Estate",
            "subcategory":"Real Estate Agent",
            "type":"Services"
        }
    ],
    "sg:phone":"+1 818 344 9008",
    "sg:postcode":"91316",
    "sg:province":"CA",
    "sg:tags":[
        "management"
    ],
    "wof:name":"Key Management",
    "wof:placetype":"venue"
},
  "geometry": {"coordinates":[-118.51862199999999,34.16853],"type":"Point"}
}