{
  "type": "Feature",
  "properties": {
    "addr:full":"4999 Appian Way El Sobrante CA 94803",
    "addr:housenumber":"4999",
    "addr:postcode":"94803",
    "addr:street":"Appian Way",
    "iso:country":"US",
    "sg:address":"4999 Appian Way",
    "sg:city":"El Sobrante",
    "sg:classifiers":[
        {
            "category":"Professional",
            "subcategory":"Accounting & Tax Preparation",
            "type":"Services"
        }
    ],
    "sg:phone":"+1 510 758 6800",
    "sg:postcode":"94803",
    "sg:province":"CA",
    "sg:tags":[
        "accountant"
    ],
    "wof:name":"Lynden & Co",
    "wof:placetype":"venue"
},
  "geometry": {"coordinates":[-122.297406,37.976227],"type":"Point"}
}