{
  "type": "Feature",
  "properties": {
    "addr:full":"2206 S Figueroa Street Los Angeles CA 90007",
    "addr:housenumber":"2206",
    "addr:postcode":"90007",
    "addr:street":"S Figueroa Street",
    "iso:country":"US",
    "sg:address":"2206 S Figueroa Street",
    "sg:city":"Los Angeles",
    "sg:classifiers":[
        {
            "category":"Health Services",
            "subcategory":"Dentist",
            "type":"Services"
        }
    ],
    "sg:phone":"+1 213 748 8448",
    "sg:postcode":"90007",
    "sg:province":"CA",
    "wof:name":"Crystal Dental",
    "wof:placetype":"venue"
},
  "geometry": {"coordinates":[-118.274034,34.031485],"type":"Point"}
}