{
  "type": "Feature",
  "properties": {
    "addr:full":"2645 Pittsburg Antioch Hwy Antioch CA 94509",
    "addr:housenumber":"2645",
    "addr:postcode":"ca 94509",
    "addr:street":"Antioch Hwy",
    "iso:country":"US",
    "sg:address":"2645 Pittsburg Antioch Hwy",
    "sg:city":"Antioch",
    "sg:classifiers":[
        {
            "category":"Home & Garden",
            "subcategory":"Building Materials",
            "type":"Retail Goods"
        },
        {
            "category":"Building & Trades",
            "subcategory":"Construction",
            "type":"Services"
        }
    ],
    "sg:phone":"+1 925 755 4940",
    "sg:postcode":"94509",
    "sg:province":"CA",
    "sg:tags":[
        "industrial",
        "contractor",
        "concrete",
        "contractors-commercial",
        "staining",
        "masonry",
        "mason"
    ],
    "sg:website":"http://www.paradigmconcrete.com",
    "wof:name":"Paradigm Concrete & Constr Inc",
    "wof:placetype":"venue"
},
  "geometry": {"coordinates":[-121.851636,38.01249],"type":"Point"}
}