{
  "type": "Feature",
  "properties": {
    "iso:country":"US",
    "sg:address":"Folsom and 21st St",
    "sg:city":"San Francisco",
    "sg:classifiers":[
        {
            "category":"Sports & Exercise",
            "subcategory":"Gym",
            "type":"Entertainment"
        },
        {
            "category":"Sports & Exercise",
            "subcategory":"Tennis Court",
            "type":"Entertainment"
        }
    ],
    "sg:phone":"+1 347 267 5912",
    "sg:postcode":"94110",
    "sg:province":"CA",
    "sg:tags":[
        "trainer"
    ],
    "wof:name":"Tennis USA",
    "wof:placetype":"venue"
},
  "geometry": {"coordinates":[-122.414541,37.757298],"type":"Point"}
}