{
  "type": "Feature",
  "properties": {
    "iso:country":"US",
    "sg:address":"1927 11th St",
    "sg:city":"Santa Monica",
    "sg:classifiers":[
        {
            "category":"Professional",
            "type":"Services"
        }
    ],
    "sg:phone":"+1 310 452 3673",
    "sg:postcode":"90404",
    "sg:province":"CA",
    "wof:name":"Paul Ford Co",
    "wof:placetype":"venue"
},
  "geometry": {"coordinates":[-118.480962,34.015496],"type":"Point"}
}