{
  "type": "Feature",
  "properties": {
    "addr:full":"13907 Horsetrail Ln Victorville CA 92394",
    "addr:housenumber":"13907",
    "addr:postcode":"92394",
    "addr:street":"Horsetrail Ln",
    "iso:country":"US",
    "sg:address":"13907 Horsetrail Ln",
    "sg:city":"Victorville",
    "sg:classifiers":[
        {
            "category":"Professional",
            "type":"Services"
        }
    ],
    "sg:phone":"+1 760 245 9280",
    "sg:postcode":"92394",
    "sg:province":"CA",
    "wof:name":"Your Family My Family Our Fami",
    "wof:placetype":"venue"
},
  "geometry": {"coordinates":[-117.35961500000001,34.518523],"type":"Point"}
}