{
  "type": "Feature",
  "properties": {
    "iso:country":"US",
    "sg:address":"488 E 17th St",
    "sg:city":"Costa Mesa",
    "sg:classifiers":[
        {
            "category":"Personal",
            "subcategory":"Beauty Salon",
            "type":"Services"
        }
    ],
    "sg:phone":"+1 949 631 6890",
    "sg:postcode":"92627",
    "sg:province":"CA",
    "wof:name":"Marsyls Salon",
    "wof:placetype":"venue"
},
  "geometry": {"coordinates":[-117.91158299999999,33.630574],"type":"Point"}
}