{
  "type": "Feature",
  "properties": {
    "iso:country":"US",
    "sg:address":"11527 Lower Azusa Rd",
    "sg:city":"El Monte",
    "sg:classifiers":[
        {
            "category":"Manufacturing",
            "subcategory":"Printing",
            "type":"Manufacturing & Wholesale Goods"
        }
    ],
    "sg:phone":"+1 626 448 3124",
    "sg:postcode":"91732",
    "sg:province":"CA",
    "sg:tags":[
        "periodical"
    ],
    "wof:name":"Cycle Edge Magazine",
    "wof:placetype":"venue"
},
  "geometry": {"coordinates":[-118.017104,34.091284],"type":"Point"}
}