{
  "type": "Feature",
  "properties": {
    "iso:country":"US",
    "sg:address":"806 Collins Ave",
    "sg:city":"Fresno",
    "sg:classifiers":[
        {
            "category":"Organizations",
            "subcategory":"Religious Organization",
            "type":"Services"
        }
    ],
    "sg:phone":"+1 559 297 6336",
    "sg:postcode":"93706",
    "sg:province":"CA",
    "sg:tags":[
        "church"
    ],
    "wof:name":"Mt Carmel Missionary Baptist",
    "wof:placetype":"venue"
},
  "geometry": {"coordinates":[-119.80089099999999,36.724366],"type":"Point"}
}