{
  "type": "Feature",
  "properties": {
    "iso:country":"US",
    "sg:address":"4166 N Norse Way",
    "sg:city":"Long Beach",
    "sg:classifiers":[
        {
            "category":"Personal",
            "subcategory":"Beauty Salon",
            "type":"Services"
        }
    ],
    "sg:phone":"+1 562 377 0656",
    "sg:postcode":"90808",
    "sg:province":"CA",
    "wof:name":"Darnita's Beauty Box",
    "wof:placetype":"venue"
},
  "geometry": {"coordinates":[-118.142201,33.833811],"type":"Point"}
}