{
  "type": "Feature",
  "properties": {
    "addr:full":"515 Broadway Santa Cruz CA 95060",
    "addr:housenumber":"515",
    "addr:postcode":"95060",
    "addr:street":"Broadway",
    "iso:country":"US",
    "sg:address":"515 Broadway",
    "sg:city":"Santa Cruz",
    "sg:classifiers":[
        {
            "category":"Organizations",
            "subcategory":"Community Association",
            "type":"Services"
        }
    ],
    "sg:phone":"+1 831 423 1626",
    "sg:postcode":"95060",
    "sg:province":"CA",
    "sg:tags":[
        "peace"
    ],
    "sg:website":"www.rcnv.org",
    "wof:name":"Resource Center-Non Violence",
    "wof:placetype":"venue"
},
  "geometry": {"coordinates":[-122.01732,36.973861],"type":"Point"}
}