{
  "type": "Feature",
  "properties": {
    "iso:country":"US",
    "sg:address":"1155 W Brooks St",
    "sg:city":"Ontario",
    "sg:classifiers":[
        {
            "category":"Arts & Performance",
            "subcategory":"Theater",
            "type":"Entertainment"
        }
    ],
    "sg:phone":"+1 909 986 2363",
    "sg:postcode":"91762",
    "sg:province":"CA",
    "sg:tags":[
        "scenery",
        "studio"
    ],
    "wof:name":"WJS Studios",
    "wof:placetype":"venue"
},
  "geometry": {"coordinates":[-117.676014,34.061828],"type":"Point"}
}