{
  "type": "Feature",
  "properties": {
    "addr:full":"730 Bryant St San Francisco CA 94107",
    "addr:housenumber":"730",
    "addr:postcode":"94107",
    "addr:street":"Bryant St",
    "iso:country":"US",
    "sg:address":"730 Bryant St",
    "sg:city":"San Francisco",
    "sg:classifiers":[
        {
            "category":"Manufacturing",
            "subcategory":"Rubber & Plastics",
            "type":"Manufacturing & Wholesale Goods"
        }
    ],
    "sg:phone":"+1 415 896 6283",
    "sg:postcode":"94107",
    "sg:province":"CA",
    "wof:name":"Douglas & Sturgess",
    "wof:placetype":"venue"
},
  "geometry": {"coordinates":[-122.40138,37.777055],"type":"Point"}
}