{
  "type": "Feature",
  "properties": {
    "addr:full":"1605 West Olympic Blvd Los Angeles CA 90015",
    "addr:housenumber":"1605",
    "addr:postcode":"90015",
    "addr:street":"West Olympic Blvd",
    "iso:country":"US",
    "sg:address":"1605 West Olympic Blvd",
    "sg:city":"Los Angeles",
    "sg:classifiers":[
        {
            "category":"Fast Food",
            "type":"Food & Drink"
        },
        {
            "category":"Restaurant",
            "type":"Food & Drink"
        }
    ],
    "sg:phone":"+1 213 251 8594",
    "sg:postcode":"90015",
    "sg:province":"CA",
    "sg:tags":[
        "american",
        "latin"
    ],
    "sg:website":"www.campero.com",
    "wof:name":"Pollo Campero",
    "wof:placetype":"venue"
},
  "geometry": {"coordinates":[-118.274002,34.0494],"type":"Point"}
}