{
  "type": "Feature",
  "properties": {
    "iso:country":"US",
    "sg:address":"9630 Oso Ave",
    "sg:city":"Chatsworth",
    "sg:classifiers":[
        {
            "category":"Building & Trades",
            "subcategory":"Landscaping Services",
            "type":"Services"
        }
    ],
    "sg:phone":"+1 818 709 6128",
    "sg:postcode":"91311",
    "sg:province":"CA",
    "wof:name":"C K Gardening Service",
    "wof:placetype":"venue"
},
  "geometry": {"coordinates":[-118.575314,34.246016],"type":"Point"}
}