{
  "type": "Feature",
  "properties": {
    "iso:country":"US",
    "sg:address":"1644 17th St",
    "sg:city":"Santa Monica",
    "sg:classifiers":[
        {
            "category":"Local Transit",
            "type":"Transportation"
        }
    ],
    "sg:phone":"+1 310 452 9738",
    "sg:postcode":"90404",
    "sg:province":"CA",
    "sg:tags":[
        "passenger"
    ],
    "wof:name":"American Medical Response Inc",
    "wof:placetype":"venue"
},
  "geometry": {"coordinates":[-118.47830999999999,34.022439],"type":"Point"}
}