{
  "type": "Feature",
  "properties": {
    "iso:country":"US",
    "sg:address":"302 Tejon Pl",
    "sg:city":"Palos Vrds Ests",
    "sg:classifiers":[
        {
            "category":"Personal",
            "subcategory":"Beauty Salon",
            "type":"Services"
        }
    ],
    "sg:phone":"+1 310 373 1558",
    "sg:postcode":"90274",
    "sg:province":"CA",
    "sg:tags":[
        "manicuring"
    ],
    "wof:name":"Anny Nail Salon",
    "wof:placetype":"venue"
},
  "geometry": {"coordinates":[-118.391626,33.799479],"type":"Point"}
}