{
  "type": "Feature",
  "properties": {
    "iso:country":"US",
    "sg:address":"12200 Santa Fe Avenue",
    "sg:city":"Lynwood",
    "sg:classifiers":[
        {
            "category":"Real Estate",
            "subcategory":"Real Estate Operator",
            "type":"Services"
        }
    ],
    "sg:phone":"+1 310 635 5771",
    "sg:postcode":"90262",
    "sg:province":"CA",
    "sg:tags":[
        "apartment"
    ],
    "wof:name":"Holmberg John",
    "wof:placetype":"venue"
},
  "geometry": {"coordinates":[-118.197328,33.923948],"type":"Point"}
}