{
  "type": "Feature",
  "properties": {
    "iso:country":"US",
    "sg:address":"California St at S Mary Ave",
    "sg:city":"Sunnyvale",
    "sg:classifiers":[
        {
            "category":"Shopping",
            "subcategory":"Beauty & Cosmetics",
            "type":"Retail Goods"
        }
    ],
    "sg:phone":"+1 408 329 8745",
    "sg:postcode":"94086",
    "sg:province":"CA",
    "sg:tags":[
        "supply"
    ],
    "sg:website":"www.youravon.com/astallings",
    "wof:name":"Avon Independent Sales Representative - Alissa S.",
    "wof:placetype":"venue"
},
  "geometry": {"coordinates":[-122.04388899999999,37.385193],"type":"Point"}
}