{
  "type": "Feature",
  "properties": {
    "iso:country":"US",
    "sg:address":"13530 Sherman Way",
    "sg:city":"Van Nuys",
    "sg:classifiers":[
        {
            "category":"Social Services",
            "subcategory":"Adult Care",
            "type":"Services"
        }
    ],
    "sg:phone":"+1 818 786 1425",
    "sg:postcode":"91405",
    "sg:province":"CA",
    "sg:tags":[
        "residential"
    ],
    "wof:name":"Country Villa Woodman Assisted",
    "wof:placetype":"venue"
},
  "geometry": {"coordinates":[-118.42684800000001,34.201191],"type":"Point"}
}