{
  "type": "Feature",
  "properties": {
    "iso:country":"US",
    "sg:address":"969 Stone Canyon Rd",
    "sg:city":"Los Angeles",
    "sg:classifiers":[
        {
            "category":"Manufacturing",
            "subcategory":"Printing",
            "type":"Manufacturing & Wholesale Goods"
        }
    ],
    "sg:phone":"+1 310 440 9134",
    "sg:postcode":"90077",
    "sg:province":"CA",
    "sg:tags":[
        "publishing"
    ],
    "wof:name":"Greybull Press",
    "wof:placetype":"venue"
},
  "geometry": {"coordinates":[-118.446832,34.090567],"type":"Point"}
}