{
  "type": "Feature",
  "properties": {
    "iso:country":"US",
    "sg:address":"10481 Fire Mountain View Ln",
    "sg:city":"Palo Cedro",
    "sg:classifiers":[
        {
            "category":"Building & Trades",
            "subcategory":"Construction",
            "type":"Services"
        }
    ],
    "sg:phone":"+1 530 549 4555",
    "sg:postcode":"96073",
    "sg:province":"CA",
    "sg:tags":[
        "contractor"
    ],
    "wof:name":"Tom Shaw Construction",
    "wof:placetype":"venue"
},
  "geometry": {"coordinates":[-122.24941,40.591675],"type":"Point"}
}