{
  "type": "Feature",
  "properties": {
    "addr:full":"1331 Turquoise Ave Mentone CA 92359",
    "addr:housenumber":"1331",
    "addr:postcode":"92359",
    "addr:street":"Turquoise Ave",
    "iso:country":"US",
    "sg:address":"1331 Turquoise Ave",
    "sg:city":"Mentone",
    "sg:classifiers":[
        {
            "category":"Organizations",
            "subcategory":"Religious Organization",
            "type":"Services"
        }
    ],
    "sg:phone":"+1 909 794 6768",
    "sg:postcode":"92359",
    "sg:province":"CA",
    "sg:tags":[
        "church"
    ],
    "wof:name":"Calvary Community Chapel",
    "wof:placetype":"venue"
},
  "geometry": {"coordinates":[-117.132385,34.074923],"type":"Point"}
}