{
  "type": "Feature",
  "properties": {
    "iso:country":"US",
    "sg:address":"65 Cahill St",
    "sg:city":"San Jose",
    "sg:classifiers":[
        {
            "category":"Transit Center",
            "subcategory":"Passenger",
            "type":"Transportation"
        }
    ],
    "sg:phone":"+1 408 287 7462",
    "sg:postcode":"95110",
    "sg:province":"CA",
    "wof:name":"Amtrak",
    "wof:placetype":"venue"
},
  "geometry": {"coordinates":[-121.902405,37.329931],"type":"Point"}
}