{
  "type": "Feature",
  "properties": {
    "addr:full":"Albany Estate Sales 567 San Pablo Ave Albany CA 94706",
    "addr:housenumber":"567",
    "addr:postcode":"94706",
    "addr:street":"San Pablo Ave",
    "iso:country":"US",
    "sg:address":"Albany Estate Sales 567 San Pablo Ave",
    "sg:city":"Albany",
    "sg:classifiers":[
        {
            "category":"Shopping",
            "subcategory":"Antiques",
            "type":"Retail Goods"
        },
        {
            "category":"Home & Garden",
            "subcategory":"Furniture",
            "type":"Retail Goods"
        }
    ],
    "sg:phone":"+1 510 528 8850",
    "sg:postcode":"94706",
    "sg:province":"CA",
    "sg:tags":[
        "store"
    ],
    "sg:website":"lux-perpetua.com/",
    "wof:name":"Lux Perpetua Lighting",
    "wof:placetype":"venue"
},
  "geometry": {"coordinates":[-122.300303,37.895626],"type":"Point"}
}