{
  "type": "Feature",
  "properties": {
    "iso:country":"US",
    "sg:address":"6733 el Rodeo Rd",
    "sg:city":"Rancho Pls Vrds",
    "sg:classifiers":[
        {
            "category":"Professional",
            "subcategory":"Management & Consulting",
            "type":"Services"
        }
    ],
    "sg:phone":"+1 310 507 2800",
    "sg:postcode":"90275",
    "sg:province":"CA",
    "sg:tags":[
        "marketing",
        "consultant"
    ],
    "wof:name":"Rolling Hills Assoc Inc",
    "wof:placetype":"venue"
},
  "geometry": {"coordinates":[-118.396467,33.769612],"type":"Point"}
}