{
  "type": "Feature",
  "properties": {
    "iso:country":"US",
    "sg:address":"1167 Foothill Blvd",
    "sg:city":"La Verne",
    "sg:classifiers":[
        {
            "category":"Retail",
            "subcategory":"Laundry & Dry Cleaning",
            "type":"Services"
        }
    ],
    "sg:phone":"+1 909 392 5730",
    "sg:postcode":"91750",
    "sg:province":"CA",
    "sg:tags":[
        "cleaners"
    ],
    "wof:name":"Green Clean",
    "wof:placetype":"venue"
},
  "geometry": {"coordinates":[-117.78224899999999,34.119141],"type":"Point"}
}