{
  "type": "Feature",
  "properties": {
    "iso:country":"US",
    "sg:address":"8635 Florence Avenue Suite 105",
    "sg:city":"Downey",
    "sg:classifiers":[
        {
            "category":"Banks & Credit Unions",
            "subcategory":"Financial Services",
            "type":"Services"
        }
    ],
    "sg:phone":"+1 562 231 1999",
    "sg:postcode":"90240",
    "sg:province":"CA",
    "sg:tags":[
        "broker",
        "mortgage"
    ],
    "wof:name":"America's Lending Group",
    "wof:placetype":"venue"
},
  "geometry": {"coordinates":[-118.118516,33.948201],"type":"Point"}
}