{
  "type": "Feature",
  "properties": {
    "addr:full":"18995 Ave 40 Earlimart CA 93219",
    "addr:housenumber":"18995;40",
    "addr:postcode":"93219",
    "addr:street":"Ave",
    "iso:country":"US",
    "sg:address":"18995 Ave 40",
    "sg:city":"Earlimart",
    "sg:classifiers":[
        {
            "category":"Retail",
            "subcategory":"Repair Shop",
            "type":"Services"
        }
    ],
    "sg:phone":"+1 661 849 2877",
    "sg:postcode":"93219",
    "sg:province":"CA",
    "sg:tags":[
        "welding"
    ],
    "wof:name":"M & P",
    "wof:placetype":"venue"
},
  "geometry": {"coordinates":[-119.151946,35.863123],"type":"Point"}
}