{
  "type": "Feature",
  "properties": {
    "iso:country":"US",
    "sg:address":"4347 Lakeville Hwy",
    "sg:city":"Petaluma",
    "sg:classifiers":[
        {
            "category":"Professional",
            "subcategory":"Engineering",
            "type":"Services"
        }
    ],
    "sg:phone":"+1 707 763 9203",
    "sg:postcode":"94954",
    "sg:province":"CA",
    "sg:tags":[
        "engineer"
    ],
    "wof:name":"Redwood AG Management",
    "wof:placetype":"venue"
},
  "geometry": {"coordinates":[-122.570419,38.2235],"type":"Point"}
}