{
  "type": "Feature",
  "properties": {
    "iso:country":"US",
    "sg:address":"3007 Washington Blvd",
    "sg:city":"Marina Del Rey",
    "sg:classifiers":[
        {
            "category":"Professional",
            "subcategory":"Business Services",
            "type":"Services"
        }
    ],
    "sg:phone":"+1 310 822 8814",
    "sg:postcode":"90292",
    "sg:province":"CA",
    "wof:name":"Fernandez & Assoc",
    "wof:placetype":"venue"
},
  "geometry": {"coordinates":[-118.449901,33.989477],"type":"Point"}
}