{
  "type": "Feature",
  "properties": {
    "iso:country":"US",
    "sg:address":"1317 Carrie Lee Way",
    "sg:city":"San Jose",
    "sg:classifiers":[
        {
            "category":"Shopping",
            "subcategory":"Musical Instruments",
            "type":"Retail Goods"
        }
    ],
    "sg:phone":"+1 408 504 9270",
    "sg:postcode":"95118",
    "sg:province":"CA",
    "sg:tags":[
        "piano"
    ],
    "wof:name":"Music Bus",
    "wof:placetype":"venue"
},
  "geometry": {"coordinates":[-121.886179,37.268379],"type":"Point"}
}