{
  "type": "Feature",
  "properties": {
    "addr:full":"10960 Lyra Ct San Diego CA 92126",
    "addr:housenumber":"10960",
    "addr:postcode":"92126",
    "addr:street":"Lyra Ct",
    "iso:country":"US",
    "sg:address":"10960 Lyra Ct",
    "sg:city":"San Diego",
    "sg:classifiers":[
        {
            "category":"Shopping",
            "subcategory":"Computers & Home Electronics",
            "type":"Retail Goods"
        }
    ],
    "sg:phone":"+1 858 566 0301",
    "sg:postcode":"92126",
    "sg:province":"CA",
    "sg:tags":[
        "software"
    ],
    "wof:name":"Marcoux Computer Svc",
    "wof:placetype":"venue"
},
  "geometry": {"coordinates":[-117.128539,32.919412],"type":"Point"}
}