{
  "type": "Feature",
  "properties": {
    "addr:full":"1782 Neptune Dr San Leandro CA 94577",
    "addr:housenumber":"1782",
    "addr:postcode":"94577",
    "addr:street":"Neptune Dr",
    "iso:country":"US",
    "sg:address":"1782 Neptune Dr",
    "sg:city":"San Leandro",
    "sg:classifiers":[
        {
            "category":"Building & Trades",
            "subcategory":"Construction",
            "type":"Services"
        }
    ],
    "sg:phone":"+1 510 357 7525",
    "sg:postcode":"94577",
    "sg:province":"CA",
    "sg:tags":[
        "maker",
        "cabinet"
    ],
    "sg:website":"www.shivny.com",
    "wof:name":"Shivny European Style Cabinets",
    "wof:placetype":"venue"
},
  "geometry": {"coordinates":[-122.19002500000001,37.704975],"type":"Point"}
}