{
  "type": "Feature",
  "properties": {
    "iso:country":"US",
    "sg:address":"1001 San Julian St",
    "sg:city":"Los Angeles",
    "sg:classifiers":[
        {
            "category":"Manufacturing",
            "subcategory":"Apparel",
            "type":"Manufacturing & Wholesale Goods"
        }
    ],
    "sg:phone":"+1 213 749 9923",
    "sg:postcode":"90015",
    "sg:province":"CA",
    "wof:name":"Tamore",
    "wof:placetype":"venue"
},
  "geometry": {"coordinates":[-118.253142,34.035858],"type":"Point"}
}