{
  "type": "Feature",
  "properties": {
    "addr:full":"19405 Foresthill Rd Foresthill CA 95631",
    "addr:postcode":"19405;95631",
    "addr:street":"Foresthill Rd",
    "iso:country":"US",
    "sg:address":"19405 Foresthill Rd",
    "sg:city":"Foresthill",
    "sg:classifiers":[
        {
            "category":"Freight",
            "type":"Transportation"
        }
    ],
    "sg:phone":"+1 530 367 3792",
    "sg:postcode":"95631",
    "sg:province":"CA",
    "sg:tags":[
        "trucking"
    ],
    "wof:name":"Bm&M & H Trucking",
    "wof:placetype":"venue"
},
  "geometry": {"coordinates":[-120.92483,38.991777],"type":"Point"}
}