{
  "type": "Feature",
  "properties": {
    "addr:full":"509 Palo Verde St Holtville CA 92250",
    "addr:housenumber":"509",
    "addr:postcode":"92250",
    "addr:street":"Palo Verde St",
    "iso:country":"US",
    "sg:address":"509 Palo Verde St",
    "sg:city":"Holtville",
    "sg:classifiers":[
        {
            "category":"Shopping",
            "subcategory":"Gifts & Souvenirs",
            "type":"Retail Goods"
        }
    ],
    "sg:phone":"+1 760 356 1495",
    "sg:postcode":"92250",
    "sg:province":"CA",
    "wof:name":"Andres Gift Shop",
    "wof:placetype":"venue"
},
  "geometry": {"coordinates":[-115.392528,32.811608],"type":"Point"}
}