{
  "type": "Feature",
  "properties": {
    "iso:country":"US",
    "sg:address":"1 Sansome Street Fl 35",
    "sg:city":"San Francisco",
    "sg:classifiers":[
        {
            "category":"Professional",
            "subcategory":"Lawyer & Legal Services",
            "type":"Services"
        }
    ],
    "sg:phone":"+1 415 956 5544",
    "sg:postcode":"94104",
    "sg:province":"CA",
    "sg:tags":[
        "personal",
        "injury"
    ],
    "wof:name":"Baum David B",
    "wof:placetype":"venue"
},
  "geometry": {"coordinates":[-122.400564,37.790302],"type":"Point"}
}