{
  "type": "Feature",
  "properties": {
    "addr:full":"3833 Foothill Blvd La Crescenta CA 91214",
    "addr:housenumber":"3833",
    "addr:postcode":"91214",
    "addr:street":"Foothill Blvd",
    "iso:country":"US",
    "sg:address":"3833 Foothill Blvd",
    "sg:city":"La Crescenta",
    "sg:classifiers":[
        {
            "category":"Retail",
            "subcategory":"Auto Repair",
            "type":"Services"
        }
    ],
    "sg:phone":"+1 818 248 6221",
    "sg:postcode":"91214",
    "sg:province":"CA",
    "sg:tags":[
        "repairing",
        "automobile"
    ],
    "wof:name":"C V Tire",
    "wof:placetype":"venue"
},
  "geometry": {"coordinates":[-118.263319,34.238706],"type":"Point"}
}