{
  "type": "Feature",
  "properties": {
    "addr:full":"6419 Montana Ct. San Jose CA 95120",
    "addr:housenumber":"6419",
    "addr:postcode":"95120",
    "addr:street":"Montana Ct.",
    "iso:country":"US",
    "sg:address":"6419 Montana Ct.",
    "sg:city":"San Jose",
    "sg:classifiers":[
        {
            "category":"Professional",
            "type":"Services"
        }
    ],
    "sg:phone":"+1 408 323 2500",
    "sg:postcode":"95120",
    "sg:province":"CA",
    "wof:name":"Surefire Security Solutions",
    "wof:placetype":"venue"
},
  "geometry": {"coordinates":[-121.86258599999999,37.223193],"type":"Point"}
}