{
  "type": "Feature",
  "properties": {
    "addr:full":"1600 Geary Blvd San Francisco CA 94115",
    "addr:housenumber":"1600",
    "addr:postcode":"94115",
    "addr:street":"Geary Blvd",
    "iso:country":"US",
    "sg:address":"1600 Geary Blvd",
    "sg:city":"San Francisco",
    "sg:classifiers":[
        {
            "category":"Retail",
            "subcategory":"Car Wash",
            "type":"Services"
        }
    ],
    "sg:phone":"+1 415 921 9274",
    "sg:postcode":"94115",
    "sg:province":"CA",
    "sg:tags":[
        "polishing",
        "washing"
    ],
    "wof:name":"Magic Kar Wash",
    "wof:placetype":"venue"
},
  "geometry": {"coordinates":[-122.43120500000001,37.784568],"type":"Point"}
}