{
  "type": "Feature",
  "properties": {
    "addr:full":"92 Windsor River Rd Windsor CA 95492",
    "addr:housenumber":"92",
    "addr:postcode":"95492",
    "addr:street":"Windsor River Rd",
    "iso:country":"US",
    "sg:address":"92 Windsor River Rd",
    "sg:city":"Windsor",
    "sg:classifiers":[
        {
            "category":"Professional",
            "subcategory":"Lawyer & Legal Services",
            "type":"Services"
        }
    ],
    "sg:phone":"+1 707 837 1959",
    "sg:postcode":"95492",
    "sg:province":"CA",
    "sg:tags":[
        "attorney"
    ],
    "wof:name":"Parks Joseph A Law Offices Of",
    "wof:placetype":"venue"
},
  "geometry": {"coordinates":[-122.81192900000001,38.547323],"type":"Point"}
}