{
  "type": "Feature",
  "properties": {
    "iso:country":"US",
    "sg:address":"11700 Victory Blvd",
    "sg:city":"North Hollywood",
    "sg:classifiers":[
        {
            "category":"Recreation",
            "subcategory":"Dance Hall",
            "type":"Entertainment"
        }
    ],
    "sg:phone":"+1 818 506 8664",
    "sg:postcode":"91606",
    "sg:province":"CA",
    "sg:tags":[
        "club"
    ],
    "wof:name":"Hacienda Corona",
    "wof:placetype":"venue"
},
  "geometry": {"coordinates":[-118.387001,34.186798],"type":"Point"}
}