{
  "type": "Feature",
  "properties": {
    "addr:full":"6131 Goshen St Simi Valley CA 93063",
    "addr:housenumber":"6131",
    "addr:postcode":"93063",
    "addr:street":"Goshen St",
    "iso:country":"US",
    "sg:address":"6131 Goshen St",
    "sg:city":"Simi Valley",
    "sg:classifiers":[
        {
            "category":"Building & Trades",
            "subcategory":"Construction",
            "type":"Services"
        }
    ],
    "sg:phone":"+1 805 582 2623",
    "sg:postcode":"93063",
    "sg:province":"CA",
    "sg:tags":[
        "hanging",
        "contractor"
    ],
    "wof:name":"Don Hubbs Painting",
    "wof:placetype":"venue"
},
  "geometry": {"coordinates":[-118.667782,34.276174],"type":"Point"}
}