{
  "type": "Feature",
  "properties": {
    "iso:country":"US",
    "sg:address":"370 E. Glenarm St",
    "sg:city":"Pasadena",
    "sg:classifiers":[
        {
            "category":"Professional",
            "subcategory":"Lawyer & Legal Services",
            "type":"Services"
        }
    ],
    "sg:phone":"+1 626 799 3999",
    "sg:postcode":"91106",
    "sg:province":"CA",
    "sg:website":"www.fan-law.com",
    "wof:name":"Fan and Fitzpatrick P A Immigration Law",
    "wof:placetype":"venue"
},
  "geometry": {"coordinates":[-118.14251400000001,34.127294],"type":"Point"}
}