{
  "type": "Feature",
  "properties": {
    "iso:country":"US",
    "sg:address":"4653 Sonoma Hwy",
    "sg:city":"Santa Rosa",
    "sg:classifiers":[
        {
            "category":"Retail",
            "subcategory":"Repair Shop",
            "type":"Services"
        }
    ],
    "sg:phone":"+1 707 584 3402",
    "sg:postcode":"95409",
    "sg:province":"CA",
    "sg:tags":[
        "equipment"
    ],
    "wof:name":"Nagler Safe Co",
    "wof:placetype":"venue"
},
  "geometry": {"coordinates":[-122.669082,38.462254],"type":"Point"}
}