{
  "type": "Feature",
  "properties": {
    "addr:full":"123 E Carmel St San Marcos CA 92078",
    "addr:housenumber":"123",
    "addr:postcode":"92078",
    "addr:street":"E Carmel St",
    "iso:country":"US",
    "sg:address":"123 E Carmel St",
    "sg:city":"San Marcos",
    "sg:classifiers":[
        {
            "category":"Travel",
            "subcategory":"Hotels & Motels",
            "type":"Entertainment"
        }
    ],
    "sg:phone":"+1 760 736 9249",
    "sg:postcode":"92078",
    "sg:province":"CA",
    "wof:name":"Hampton Inn",
    "wof:placetype":"venue"
},
  "geometry": {"coordinates":[-117.158519,33.137456],"type":"Point"}
}