{
  "type": "Feature",
  "properties": {
    "addr:full":"17361 17th St Tustin CA 92780",
    "addr:housenumber":"17361",
    "addr:postcode":"92780",
    "addr:street":"17Th St",
    "iso:country":"US",
    "sg:address":"17361 17th St",
    "sg:city":"Tustin",
    "sg:classifiers":[
        {
            "category":"Sports & Exercise",
            "subcategory":"Gym",
            "type":"Entertainment"
        }
    ],
    "sg:phone":"+1 714 665 0260",
    "sg:postcode":"92780",
    "sg:province":"CA",
    "sg:tags":[
        "club",
        "health",
        "studio",
        "gymnasium"
    ],
    "wof:name":"All About You Health & Fitness",
    "wof:placetype":"venue"
},
  "geometry": {"coordinates":[-117.827219,33.759904],"type":"Point"}
}