{
  "type": "Feature",
  "properties": {
    "addr:full":"7986 California Ave Fair Oaks CA 95628",
    "addr:housenumber":"7986",
    "addr:postcode":"95628",
    "addr:street":"California Ave",
    "iso:country":"US",
    "sg:address":"7986 California Ave",
    "sg:city":"Fair Oaks",
    "sg:classifiers":[
        {
            "category":"Personal",
            "subcategory":"Beauty Salon",
            "type":"Services"
        }
    ],
    "sg:phone":"+1 916 962 3534",
    "sg:postcode":"95628",
    "sg:province":"CA",
    "wof:name":"Heidi C Konkel",
    "wof:placetype":"venue"
},
  "geometry": {"coordinates":[-121.26787,38.64205],"type":"Point"}
}