{
  "type": "Feature",
  "properties": {
    "iso:country":"US",
    "sg:address":"24820 Orchard Village Rd Ste B",
    "sg:city":"Valencia",
    "sg:classifiers":[
        {
            "category":"Retail",
            "subcategory":"Laundry & Dry Cleaning",
            "type":"Services"
        }
    ],
    "sg:phone":"+1 661 291 1244",
    "sg:postcode":"91355",
    "sg:province":"CA",
    "wof:name":"Apex Cleaners",
    "wof:placetype":"venue"
},
  "geometry": {"coordinates":[-118.541,34.3801],"type":"Point"}
}