{
  "type": "Feature",
  "properties": {
    "addr:full":"San Francisco International Airport Intl Terminal, Pre-Security Behind Checkin Counter 1 San Francisco CA 94128",
    "addr:housenumber":"1",
    "addr:postcode":"94128",
    "addr:street":"Behind Checkin Counter",
    "iso:country":"US",
    "sg:address":"San Francisco International Airport Intl Terminal, Pre-Security Behind Checkin Counter 1",
    "sg:city":"San Francisco",
    "sg:classifiers":[
        {
            "category":"Restaurant",
            "type":"Food & Drink"
        }
    ],
    "sg:phone":"+1 650 821 8282",
    "sg:postcode":"94128",
    "sg:province":"CA",
    "sg:tags":[
        "chinese"
    ],
    "wof:name":"Fung Lum",
    "wof:placetype":"venue"
},
  "geometry": {"coordinates":[-122.381592,37.623908],"type":"Point"}
}