{
  "type": "Feature",
  "properties": {
    "addr:full":"519 Mission Ave Oceanside CA 92054",
    "addr:housenumber":"519",
    "addr:postcode":"92054",
    "addr:street":"Mission Ave",
    "iso:country":"US",
    "sg:address":"519 Mission Ave",
    "sg:city":"Oceanside",
    "sg:classifiers":[
        {
            "category":"Shopping",
            "subcategory":"Beauty & Cosmetics",
            "type":"Retail Goods"
        }
    ],
    "sg:phone":"+1 760 722 5588",
    "sg:postcode":"92054",
    "sg:province":"CA",
    "sg:tags":[
        "supply"
    ],
    "wof:name":"Oriental Wigs and Gifts",
    "wof:placetype":"venue"
},
  "geometry": {"coordinates":[-117.379997,33.195999],"type":"Point"}
}