{
  "type": "Feature",
  "properties": {
    "addr:full":"405 N Vineyard Ave Ontario CA 91764",
    "addr:housenumber":"405",
    "addr:postcode":"91764",
    "addr:street":"N Vineyard Ave",
    "iso:country":"US",
    "sg:address":"405 N Vineyard Ave",
    "sg:city":"Ontario",
    "sg:classifiers":[
        {
            "category":"Restaurant",
            "type":"Food & Drink"
        }
    ],
    "sg:menulink":"http://www.allmenus.com/ca/ontario/238816-yoshinoya/menu/",
    "sg:phone":"+1 909 937 6832",
    "sg:postcode":"91764",
    "sg:province":"CA",
    "sg:tags":[
        "korean",
        "noodle",
        "bar",
        "japanese",
        "asian"
    ],
    "wof:name":"Yoshinoya",
    "wof:placetype":"venue"
},
  "geometry": {"coordinates":[-117.611639,34.067491],"type":"Point"}
}