{
  "type": "Feature",
  "properties": {
    "iso:country":"US",
    "sg:address":"23830 Fairfield Pl",
    "sg:city":"Carmel",
    "sg:classifiers":[
        {
            "category":"Professional",
            "subcategory":"Business Services",
            "type":"Services"
        }
    ],
    "sg:phone":"+1 831 649 3830",
    "sg:postcode":"93923",
    "sg:province":"CA",
    "sg:tags":[
        "recording",
        "studio"
    ],
    "wof:name":"Forty Karat Productions",
    "wof:placetype":"venue"
},
  "geometry": {"coordinates":[-121.888345,36.576239],"type":"Point"}
}