{
  "type": "Feature",
  "properties": {
    "addr:full":"14658 Central Ave Chino CA 91710",
    "addr:postcode":"14658;91710",
    "addr:street":"Central Ave",
    "iso:country":"US",
    "sg:address":"14658 Central Ave",
    "sg:city":"Chino",
    "sg:classifiers":[
        {
            "category":"Restaurant",
            "type":"Food & Drink"
        }
    ],
    "sg:phone":"+1 909 393 0996",
    "sg:postcode":"91710",
    "sg:province":"CA",
    "sg:tags":[
        "sandwich"
    ],
    "wof:name":"Central Park Deli",
    "wof:placetype":"venue"
},
  "geometry": {"coordinates":[-117.68898299999999,33.985694],"type":"Point"}
}