{
  "type": "Feature",
  "properties": {
    "iso:country":"US",
    "sg:address":"14658 Central Ave",
    "sg:city":"Chino",
    "sg:classifiers":[
        {
            "category":"Restaurant",
            "type":"Food & Drink"
        }
    ],
    "sg:phone":"+1 909 393 0996",
    "sg:postcode":"91710",
    "sg:province":"CA",
    "sg:tags":[
        "sandwich"
    ],
    "wof:name":"Central Park Deli",
    "wof:placetype":"venue"
},
  "geometry": {"coordinates":[-117.688983,33.985694],"type":"Point"}
}