{
  "type": "Feature",
  "properties": {
    "addr:full":"1757 Mesa Verde Ave Ventura CA 93003",
    "addr:housenumber":"1757",
    "addr:postcode":"93003",
    "addr:street":"Mesa Verde Ave",
    "iso:country":"US",
    "sg:address":"1757 Mesa Verde Ave",
    "sg:city":"Ventura",
    "sg:classifiers":[
        {
            "category":"Social Services",
            "subcategory":"Job Training",
            "type":"Services"
        }
    ],
    "sg:phone":"+1 805 658 6733",
    "sg:postcode":"93003",
    "sg:province":"CA",
    "sg:tags":[
        "rehabilitation"
    ],
    "wof:name":"Bridges Vocational Svc",
    "wof:placetype":"venue"
},
  "geometry": {"coordinates":[-119.216921,34.258453],"type":"Point"}
}