{
  "type": "Feature",
  "properties": {
    "iso:country":"US",
    "sg:address":"17631 17th St",
    "sg:city":"Tustin",
    "sg:classifiers":[
        {
            "category":"Restaurant",
            "type":"Food & Drink"
        }
    ],
    "sg:phone":"+1 714 832 3338",
    "sg:postcode":"92780",
    "sg:province":"CA",
    "sg:tags":[
        "chinese",
        "buffet"
    ],
    "wof:name":"Cafe China",
    "wof:placetype":"venue"
},
  "geometry": {"coordinates":[-117.82368200000001,33.759856],"type":"Point"}
}