{
  "type": "Feature",
  "properties": {
    "addr:full":"805 Lindley Ave Nevada City CA 95959",
    "addr:housenumber":"805",
    "addr:postcode":"95959",
    "addr:street":"Lindley Ave",
    "iso:country":"US",
    "sg:address":"805 Lindley Ave",
    "sg:city":"Nevada City",
    "sg:classifiers":[
        {
            "category":"Education",
            "subcategory":"School",
            "type":"Public Place"
        }
    ],
    "sg:phone":"+1 530 265 1870",
    "sg:postcode":"95959",
    "sg:province":"CA",
    "wof:name":"Deer Creek School",
    "wof:placetype":"venue"
},
  "geometry": {"coordinates":[-121.028068,39.251427],"type":"Point"}
}