{
  "type": "Feature",
  "properties": {
    "iso:country":"US",
    "sg:address":"2579 Atwater Blvd",
    "sg:city":"Atwater",
    "sg:classifiers":[
        {
            "category":"Home & Garden",
            "subcategory":"Household Appliances",
            "type":"Retail Goods"
        },
        {
            "category":"Building & Trades",
            "subcategory":"Construction",
            "type":"Services"
        },
        {
            "category":"Professional",
            "subcategory":"Engineering",
            "type":"Services"
        }
    ],
    "sg:phone":"+1 209 358 1456",
    "sg:postcode":"95301",
    "sg:province":"CA",
    "sg:tags":[
        "purifying",
        "system",
        "specialty",
        "equipment",
        "heating",
        "cleaning",
        "contractor",
        "air conditioning"
    ],
    "sg:website":"http://find.americanstandardair.com/customer-care-dealer-412465?utm_source=YP&utm_medium=banner&utm_campaign=TL",
    "wof:name":"KYHN'S AC & HEATING",
    "wof:placetype":"venue"
},
  "geometry": {"coordinates":[-120.624422,37.351341],"type":"Point"}
}