{
  "type": "Feature",
  "properties": {
    "iso:country":"US",
    "sg:address":"2010 Mary St",
    "sg:city":"Sanger",
    "sg:classifiers":[
        {
            "category":"Home & Garden",
            "subcategory":"Home Furnishings",
            "type":"Retail Goods"
        },
        {
            "category":"Manufacturing",
            "subcategory":"Glass & Minerals",
            "type":"Manufacturing & Wholesale Goods"
        },
        {
            "category":"Retail",
            "subcategory":"Auto Repair",
            "type":"Services"
        }
    ],
    "sg:phone":"+1 559 875 5579",
    "sg:postcode":"93657",
    "sg:province":"CA",
    "sg:tags":[
        "plate",
        "window",
        "windshield",
        "glass-auto",
        "mirror"
    ],
    "wof:name":"Academy Discount Auto Glass",
    "wof:placetype":"venue"
},
  "geometry": {"coordinates":[-119.565517,36.704059],"type":"Point"}
}