{
  "type": "Feature",
  "properties": {
    "addr:full":"1023 Meridian Avenue San Jose CA 95125",
    "addr:housenumber":"1023",
    "addr:postcode":"95125",
    "addr:street":"Meridian Avenue",
    "iso:country":"US",
    "sg:address":"1023 Meridian Avenue",
    "sg:city":"San Jose",
    "sg:classifiers":[
        {
            "category":"Professional",
            "subcategory":"Accounting & Tax Preparation",
            "type":"Services"
        }
    ],
    "sg:phone":"+1 408 265 5660",
    "sg:postcode":"95125",
    "sg:province":"CA",
    "sg:tags":[
        "accountant"
    ],
    "wof:name":"Rosbrugh Accountancy Corporation.",
    "wof:placetype":"venue"
},
  "geometry": {"coordinates":[-121.913479,37.305867],"type":"Point"}
}