{
  "type": "Feature",
  "properties": {
    "iso:country":"US",
    "sg:address":"4101 Goodwin Ave",
    "sg:city":"Los Angeles",
    "sg:classifiers":[
        {
            "category":"Building & Trades",
            "subcategory":"Cleaning & Sanitation",
            "type":"Services"
        }
    ],
    "sg:phone":"+1 800 675 7768",
    "sg:postcode":"90039",
    "sg:province":"CA",
    "sg:tags":[
        "carpet"
    ],
    "sg:website":"www.qualitycarpetcleaning.com",
    "wof:name":"Quality Carpet Cleaning",
    "wof:placetype":"venue"
},
  "geometry": {"coordinates":[-118.269037,34.137106],"type":"Point"}
}