{
  "type": "Feature",
  "properties": {
    "iso:country":"US",
    "sg:address":"1925 W Capitol Ave",
    "sg:city":"West Sacramento",
    "sg:classifiers":[
        {
            "category":"Retail",
            "subcategory":"Auto Rental",
            "type":"Services"
        }
    ],
    "sg:phone":"+1 916 372 9988",
    "sg:postcode":"95691",
    "sg:province":"CA",
    "sg:tags":[
        "renting",
        "automobile"
    ],
    "wof:name":"Speedy's Car Rental",
    "wof:placetype":"venue"
},
  "geometry": {"coordinates":[-121.536765,38.579863],"type":"Point"}
}