{
  "type": "Feature",
  "properties": {
    "addr:full":"12835 Sussex Cir Garden Grove CA 92840",
    "addr:housenumber":"12835",
    "addr:postcode":"92840",
    "addr:street":"Sussex Cir",
    "iso:country":"US",
    "sg:address":"12835 Sussex Cir",
    "sg:city":"Garden Grove",
    "sg:classifiers":[
        {
            "category":"Building & Trades",
            "subcategory":"Construction",
            "type":"Services"
        }
    ],
    "sg:phone":"+1 714 971 8080",
    "sg:postcode":"92840",
    "sg:province":"CA",
    "sg:tags":[
        "painter"
    ],
    "wof:name":"All Star Painting",
    "wof:placetype":"venue"
},
  "geometry": {"coordinates":[-117.908749,33.790048],"type":"Point"}
}