{
  "type": "Feature",
  "properties": {
    "iso:country":"US",
    "sg:address":"3465 S El Pomar Rd",
    "sg:city":"Templeton",
    "sg:classifiers":[
        {
            "category":"Building & Trades",
            "subcategory":"Landscaping Services",
            "type":"Services"
        }
    ],
    "sg:phone":"+1 805 434 5618",
    "sg:postcode":"93465",
    "sg:province":"CA",
    "sg:tags":[
        "tree"
    ],
    "wof:name":"Twin Pines Tree Farm",
    "wof:placetype":"venue"
},
  "geometry": {"coordinates":[-120.642263,35.524731],"type":"Point"}
}