{
  "type": "Feature",
  "properties": {
    "addr:full":"938 Menlo Ave Los Angeles CA 90006",
    "addr:housenumber":"938",
    "addr:postcode":"90006",
    "addr:street":"Menlo Ave",
    "iso:country":"US",
    "sg:address":"938 Menlo Ave",
    "sg:city":"Los Angeles",
    "sg:classifiers":[
        {
            "category":"Social Services",
            "subcategory":"Child Care",
            "type":"Services"
        }
    ],
    "sg:phone":"+1 213 389 1155",
    "sg:postcode":"90006",
    "sg:province":"CA",
    "sg:tags":[
        "kindergarten",
        "academic",
        "school"
    ],
    "wof:name":"Rainbow Child Development Ctr",
    "wof:placetype":"venue"
},
  "geometry": {"coordinates":[-118.29028,34.053404],"type":"Point"}
}