{
  "type": "Feature",
  "properties": {
    "iso:country":"US",
    "sg:address":"1117 Soquel Ave",
    "sg:city":"Santa Cruz",
    "sg:classifiers":[
        {
            "category":"Wholesale",
            "subcategory":"Hardware",
            "type":"Manufacturing & Wholesale Goods"
        }
    ],
    "sg:phone":"+1 831 423 3008",
    "sg:postcode":"95062",
    "sg:province":"CA",
    "sg:tags":[
        "plumbing"
    ],
    "wof:name":"Pacific Alternative Energy",
    "wof:placetype":"venue"
},
  "geometry": {"coordinates":[-122.012209,36.979022],"type":"Point"}
}