{
  "type": "Feature",
  "properties": {
    "iso:country":"US",
    "sg:address":"53 10th St",
    "sg:city":"Tracy",
    "sg:classifiers":[
        {
            "category":"Shopping",
            "subcategory":"Musical Instruments",
            "type":"Retail Goods"
        }
    ],
    "sg:phone":"+1 209 835 1125",
    "sg:postcode":"95376",
    "sg:province":"CA",
    "wof:name":"Main Street Music",
    "wof:placetype":"venue"
},
  "geometry": {"coordinates":[-121.424631,37.738602],"type":"Point"}
}