{
  "type": "Feature",
  "properties": {
    "iso:country":"US",
    "sg:address":"1736 Fitzgerald Avenue",
    "sg:city":"San Francisco",
    "sg:classifiers":[
        {
            "category":"Restaurant",
            "type":"Food & Drink"
        }
    ],
    "sg:phone":"+1 415 468 7000",
    "sg:postcode":"94124",
    "sg:province":"CA",
    "sg:website":"www.vcfoods.com",
    "wof:name":"V & C Foods",
    "wof:placetype":"venue"
},
  "geometry": {"coordinates":[-122.40113100000001,37.726873],"type":"Point"}
}