{
  "type": "Feature",
  "properties": {
    "addr:full":"2441 E Coast Hwy Corona Del Mar CA 92625",
    "addr:housenumber":"2441",
    "addr:postcode":"92625",
    "addr:street":"E Coast Hwy",
    "iso:country":"US",
    "sg:address":"2441 E Coast Hwy",
    "sg:city":"Corona Del Mar",
    "sg:classifiers":[
        {
            "category":"Restaurant",
            "type":"Food & Drink"
        }
    ],
    "sg:phone":"+1 949 673 6585",
    "sg:postcode":"92625",
    "sg:province":"CA",
    "sg:tags":[
        "new",
        "american"
    ],
    "sg:website":"thebungalowrestaurant.com",
    "wof:name":"The Bungalow Restaurant",
    "wof:placetype":"venue"
},
  "geometry": {"coordinates":[-117.87480100000001,33.604797],"type":"Point"}
}