{
  "type": "Feature",
  "properties": {
    "addr:full":"13682 Newport Ave Tustin CA 92780",
    "addr:housenumber":"13682",
    "addr:postcode":"92780",
    "addr:street":"Newport Ave",
    "iso:country":"US",
    "sg:address":"13682 Newport Ave",
    "sg:city":"Tustin",
    "sg:classifiers":[
        {
            "category":"Bagels",
            "subcategory":"None",
            "type":"Food & Drink"
        },
        {
            "category":"Ice Cream",
            "type":"Food & Drink"
        }
    ],
    "sg:phone":"+1 714 731 1035",
    "sg:postcode":"92780",
    "sg:province":"CA",
    "sg:tags":[
        "frozen",
        "yogurt"
    ],
    "sg:website":"www.bagelme.com",
    "wof:name":"Bagel Me",
    "wof:placetype":"venue"
},
  "geometry": {"coordinates":[-117.818488,33.741288],"type":"Point"}
}