{
  "type": "Feature",
  "properties": {
    "iso:country":"US",
    "sg:address":"8852 W Avenue D12",
    "sg:city":"Lancaster",
    "sg:classifiers":[
        {
            "category":"Home & Garden",
            "subcategory":"Building Materials",
            "type":"Retail Goods"
        },
        {
            "category":"Building & Trades",
            "subcategory":"Construction",
            "type":"Services"
        }
    ],
    "sg:phone":"+1 661 816 1639",
    "sg:postcode":"93536",
    "sg:province":"CA",
    "sg:tags":[
        "concrete",
        "staining",
        "contractor"
    ],
    "wof:name":"Concrete Impressions",
    "wof:placetype":"venue"
},
  "geometry": {"coordinates":[-118.28974700000001,34.765536],"type":"Point"}
}