{
  "type": "Feature",
  "properties": {
    "iso:country":"US",
    "sg:address":"432 W Shaw Ave",
    "sg:city":"Clovis",
    "sg:classifiers":[
        {
            "category":"Shopping",
            "subcategory":"Department Store",
            "type":"Retail Goods"
        }
    ],
    "sg:phone":"+1 559 324 9256",
    "sg:postcode":"93612",
    "sg:province":"CA",
    "wof:name":"Factory 2-U",
    "wof:placetype":"venue"
},
  "geometry": {"coordinates":[-119.720924,36.8084],"type":"Point"}
}