{
  "type": "Feature",
  "properties": {
    "iso:country":"US",
    "sg:address":"1273 E Valley Blvd",
    "sg:city":"Alhambra",
    "sg:classifiers":[
        {
            "category":"Bakery",
            "type":"Food & Drink"
        }
    ],
    "sg:phone":"+1 626 308 3277",
    "sg:postcode":"91801",
    "sg:province":"CA",
    "wof:name":"Taipan Bakery",
    "wof:placetype":"venue"
},
  "geometry": {"coordinates":[-118.110406,34.079244],"type":"Point"}
}