{
  "type": "Feature",
  "properties": {
    "iso:country":"US",
    "sg:address":"23211 Huber Ave",
    "sg:city":"Torrance",
    "sg:classifiers":[
        {
            "category":"Freight",
            "type":"Transportation"
        },
        {
            "category":"Building & Trades",
            "subcategory":"Construction",
            "type":"Services"
        }
    ],
    "sg:phone":"+1 310 326 6351",
    "sg:postcode":"90501",
    "sg:province":"CA",
    "sg:tags":[
        "heavy",
        "equipment",
        "erectors",
        "transporting",
        "local",
        "machinery"
    ],
    "wof:name":"Nichols Machinery Movers Inc",
    "wof:placetype":"venue"
},
  "geometry": {"coordinates":[-118.310008,33.814553],"type":"Point"}
}