{
  "type": "Feature",
  "properties": {
    "iso:country":"US",
    "sg:address":"7528 Camp Far West Rd",
    "sg:city":"Wheatland",
    "sg:classifiers":[
        {
            "category":"Farming",
            "subcategory":"Livestock Farm",
            "type":"Manufacturing & Wholesale Goods"
        }
    ],
    "sg:phone":"+1 530 633 0388",
    "sg:postcode":"95692",
    "sg:province":"CA",
    "sg:tags":[
        "animal",
        "general"
    ],
    "wof:name":"El Shaddai Family Ranch",
    "wof:placetype":"venue"
},
  "geometry": {"coordinates":[-121.34425299999999,39.04921],"type":"Point"}
}