{
  "type": "Feature",
  "properties": {
    "addr:full":"2712 W Shaw Ave Fresno CA 93711",
    "addr:housenumber":"2712",
    "addr:postcode":"93711",
    "addr:street":"W Shaw Ave",
    "iso:country":"US",
    "sg:address":"2712 W Shaw Ave",
    "sg:city":"Fresno",
    "sg:classifiers":[
        {
            "category":"Banks & Credit Unions",
            "subcategory":"Bank",
            "type":"Services"
        }
    ],
    "sg:phone":"+1 559 275 5600",
    "sg:postcode":"93711",
    "sg:province":"CA",
    "sg:tags":[
        "loan"
    ],
    "wof:name":"Check 'n Go",
    "wof:placetype":"venue"
},
  "geometry": {"coordinates":[-119.842195,36.808326],"type":"Point"}
}