{
  "type": "Feature",
  "properties": {
    "addr:full":"272 Montego Key Novato CA 94949",
    "addr:housenumber":"272",
    "addr:postcode":"94949",
    "addr:street":"Montego Key",
    "iso:country":"US",
    "sg:address":"272 Montego Key",
    "sg:city":"Novato",
    "sg:classifiers":[
        {
            "category":"Freight",
            "type":"Transportation"
        }
    ],
    "sg:phone":"+1 415 883 1648",
    "sg:postcode":"94949",
    "sg:province":"CA",
    "sg:tags":[
        "heavy",
        "equipment",
        "trucking"
    ],
    "wof:name":"Mauch Trucking Inc",
    "wof:placetype":"venue"
},
  "geometry": {"coordinates":[-122.524944,38.083761],"type":"Point"}
}