{
  "type": "Feature",
  "properties": {
    "iso:country":"US",
    "sg:address":"400 Marsh Hawk Dr",
    "sg:city":"Folsom",
    "sg:classifiers":[
        {
            "category":"Shopping",
            "type":"Retail Goods"
        }
    ],
    "sg:phone":"+1 916 397 8424",
    "sg:postcode":"95630",
    "sg:province":"CA",
    "sg:tags":[
        "miscellaneous",
        "store"
    ],
    "wof:name":"Specialty Metal Sales",
    "wof:placetype":"venue"
},
  "geometry": {"coordinates":[-121.143122,38.652719],"type":"Point"}
}