{
  "type": "Feature",
  "properties": {
    "addr:full":"5417 La Jolla Blvd La Jolla CA 92037",
    "addr:housenumber":"5417",
    "addr:postcode":"92037",
    "addr:street":"La Jolla Blvd",
    "iso:country":"US",
    "sg:address":"5417 La Jolla Blvd",
    "sg:city":"La Jolla",
    "sg:classifiers":[
        {
            "category":"Travel",
            "subcategory":"Hotels & Motels",
            "type":"Entertainment"
        }
    ],
    "sg:phone":"+1 858 459 3336",
    "sg:postcode":"92037",
    "sg:province":"CA",
    "sg:website":"www.sandsoflajolla.com",
    "wof:name":"Sands of La Jolla Motel",
    "wof:placetype":"venue"
},
  "geometry": {"coordinates":[-117.266998,32.811298],"type":"Point"}
}