{
  "type": "Feature",
  "properties": {
    "addr:full":"945 Hornblend St Ste F San Diego CA 92109",
    "addr:housenumber":"945",
    "addr:postcode":"92109",
    "addr:street":"Hornblend St Ste F",
    "iso:country":"US",
    "sg:address":"945 Hornblend St Ste F",
    "sg:city":"San Diego",
    "sg:classifiers":[
        {
            "category":"Real Estate",
            "subcategory":"Real Estate Services",
            "type":"Services"
        }
    ],
    "sg:phone":"+1 858 456 5111",
    "sg:postcode":"92109",
    "sg:province":"CA",
    "sg:website":"www.mhrvadvisors.com",
    "wof:name":"MHRV Advisors",
    "wof:placetype":"venue"
},
  "geometry": {"coordinates":[-117.25256,32.796223],"type":"Point"}
}