{
  "type": "Feature",
  "properties": {
    "iso:country":"US",
    "sg:address":"3718 Muscatel Ave",
    "sg:city":"Rosemead",
    "sg:classifiers":[
        {
            "category":"Freight",
            "type":"Transportation"
        }
    ],
    "sg:phone":"+1 310 628 9140",
    "sg:postcode":"91770",
    "sg:province":"CA",
    "wof:name":"2000 Express",
    "wof:placetype":"venue"
},
  "geometry": {"coordinates":[-118.077386,34.076042],"type":"Point"}
}