{
  "type": "Feature",
  "properties": {
    "iso:country":"US",
    "sg:address":"229 Brannan St",
    "sg:city":"San Francisco",
    "sg:classifiers":[
        {
            "category":"Manufacturing",
            "subcategory":"Food",
            "type":"Manufacturing & Wholesale Goods"
        }
    ],
    "sg:phone":"+1 415 865 6110",
    "sg:postcode":"94107",
    "sg:province":"CA",
    "sg:tags":[
        "wine"
    ],
    "wof:name":"Surh-Luchtel Cellars Inc",
    "wof:placetype":"venue"
},
  "geometry": {"coordinates":[-122.38984600000001,37.783609],"type":"Point"}
}