{
  "type": "Feature",
  "properties": {
    "iso:country":"US",
    "sg:address":"2620 Barrington Ct",
    "sg:city":"Hayward",
    "sg:classifiers":[
        {
            "category":"Wholesale",
            "subcategory":"Home Furnishings",
            "type":"Manufacturing & Wholesale Goods"
        }
    ],
    "sg:phone":"+1 510 635 8616",
    "sg:postcode":"94545",
    "sg:province":"CA",
    "sg:tags":[
        "table",
        "cloth"
    ],
    "wof:name":"Henan Artex American Corp",
    "wof:placetype":"venue"
},
  "geometry": {"coordinates":[-122.140801,37.655404],"type":"Point"}
}