{
  "type": "Feature",
  "properties": {
    "addr:full":"203 S 8th St Santa Paula CA 93060",
    "addr:housenumber":"203",
    "addr:postcode":"93060",
    "addr:street":"S 8Th St",
    "iso:country":"US",
    "sg:address":"203 S 8th St",
    "sg:city":"Santa Paula",
    "sg:classifiers":[
        {
            "category":"Organizations",
            "subcategory":"Religious Organization",
            "type":"Services"
        }
    ],
    "sg:phone":"+1 805 525 2910",
    "sg:postcode":"93060",
    "sg:province":"CA",
    "sg:tags":[
        "church"
    ],
    "wof:name":"Citrus Valley Christian Ctr",
    "wof:placetype":"venue"
},
  "geometry": {"coordinates":[-119.063238,34.35096],"type":"Point"}
}