{
  "type": "Feature",
  "properties": {
    "addr:full":"120 Cll Amistad San Clemente CA 92673",
    "addr:housenumber":"120",
    "addr:postcode":"92673",
    "addr:street":"Cll Amistad",
    "iso:country":"US",
    "sg:address":"120 Cll Amistad",
    "sg:city":"San Clemente",
    "sg:classifiers":[
        {
            "category":"Travel",
            "subcategory":"Hotels & Motels",
            "type":"Entertainment"
        }
    ],
    "sg:phone":"+1 949 498 8433",
    "sg:postcode":"92673",
    "sg:province":"CA",
    "wof:name":"Corporate Suites",
    "wof:placetype":"venue"
},
  "geometry": {"coordinates":[-117.574215,33.46091],"type":"Point"}
}