{
  "type": "Feature",
  "properties": {
    "iso:country":"US",
    "sg:address":"2626 S Malt Ave",
    "sg:city":"Los Angeles",
    "sg:classifiers":[
        {
            "category":"Shopping",
            "subcategory":"Clothing, Apparel, & Fashions",
            "type":"Retail Goods"
        }
    ],
    "sg:phone":"+1 323 728 5012",
    "sg:postcode":"90040",
    "sg:province":"CA",
    "sg:tags":[
        "designer"
    ],
    "wof:name":"4what It's Worth Inc",
    "wof:placetype":"venue"
},
  "geometry": {"coordinates":[-118.135999,33.995325],"type":"Point"}
}