{
  "type": "Feature",
  "properties": {
    "iso:country":"US",
    "sg:address":"4778 Whittier Blvd",
    "sg:city":"Los Angeles",
    "sg:classifiers":[
        {
            "category":"Shopping",
            "subcategory":"Gifts & Souvenirs",
            "type":"Retail Goods"
        }
    ],
    "sg:phone":"+1 323 780 9717",
    "sg:postcode":"90022",
    "sg:province":"CA",
    "sg:tags":[
        "party",
        "supply"
    ],
    "wof:name":"Jaris Party Supply",
    "wof:placetype":"venue"
},
  "geometry": {"coordinates":[-118.165238,34.021998],"type":"Point"}
}