{
  "type": "Feature",
  "properties": {
    "iso:country":"US",
    "sg:address":"429 Leslie St",
    "sg:city":"Los Alamos",
    "sg:classifiers":[
        {
            "category":"Recreation",
            "type":"Entertainment"
        }
    ],
    "sg:phone":"+1 805 344 3500",
    "sg:postcode":"93440",
    "sg:province":"CA",
    "sg:tags":[
        "hall",
        "auditorium"
    ],
    "wof:name":"Los Alamos Valley Men's Club",
    "wof:placetype":"venue"
},
  "geometry": {"coordinates":[-120.27858500000001,34.744847],"type":"Point"}
}