{
  "type": "Feature",
  "properties": {
    "iso:country":"US",
    "sg:address":"1081 Post Street",
    "sg:city":"San Francisco",
    "sg:classifiers":[
        {
            "category":"Bars & Pubs",
            "subcategory":"Gay Bar",
            "type":"Food & Drink"
        }
    ],
    "sg:phone":"+1 415 928 6006",
    "sg:postcode":"94109",
    "sg:province":"CA",
    "wof:name":"The Motherlode",
    "wof:placetype":"venue"
},
  "geometry": {"coordinates":[-122.41999800000001,37.7868],"type":"Point"}
}