{
  "type": "Feature",
  "properties": {
    "addr:full":"4425 N Pershing Ave Stockton CA 95207",
    "addr:housenumber":"4425",
    "addr:postcode":"95207",
    "addr:street":"N Pershing Ave",
    "iso:country":"US",
    "sg:address":"4425 N Pershing Ave",
    "sg:city":"Stockton",
    "sg:classifiers":[
        {
            "category":"Retail",
            "subcategory":"Self-service Laundry",
            "type":"Services"
        }
    ],
    "sg:phone":"+1 209 474 5878",
    "sg:postcode":"95207",
    "sg:province":"CA",
    "wof:name":"Wash Depot",
    "wof:placetype":"venue"
},
  "geometry": {"coordinates":[-121.320215,37.984588],"type":"Point"}
}