{
  "type": "Feature",
  "properties": {
    "iso:country":"US",
    "sg:address":"99 Racquet Club Dr",
    "sg:city":"San Rafael",
    "sg:classifiers":[
        {
            "category":"Restaurant",
            "type":"Food & Drink"
        }
    ],
    "sg:menulink":"http://www.allmenus.com/ca/ross-valley/22302-seafood-peddler/menu/",
    "sg:phone":"+1 415 460 6669",
    "sg:postcode":"94901",
    "sg:province":"CA",
    "sg:tags":[
        "seafood",
        "american"
    ],
    "wof:name":"Seafood Peddler",
    "wof:placetype":"venue"
},
  "geometry": {"coordinates":[-122.55180799999999,37.981579],"type":"Point"}
}