{
  "type": "Feature",
  "properties": {
    "addr:full":"420 E 3rd St Los Angeles CA 90013",
    "addr:housenumber":"420",
    "addr:postcode":"90013",
    "addr:street":"E 3Rd St",
    "iso:country":"US",
    "sg:address":"420 E 3rd St",
    "sg:city":"Los Angeles",
    "sg:classifiers":[
        {
            "category":"Farming",
            "subcategory":"Crops",
            "type":"Manufacturing & Wholesale Goods"
        }
    ],
    "sg:phone":"+1 213 628 6294",
    "sg:postcode":"90013",
    "sg:province":"CA",
    "sg:tags":[
        "beef",
        "grove",
        "nut",
        "tree",
        "cattle",
        "feedlot"
    ],
    "wof:name":"Kings River Ranch Inc",
    "wof:placetype":"venue"
},
  "geometry": {"coordinates":[-118.241553,34.046862],"type":"Point"}
}