{
  "type": "Feature",
  "properties": {
    "addr:full":"1000 Grant Ave San Francisco CA 94133",
    "addr:housenumber":"1000",
    "addr:postcode":"94133",
    "addr:street":"Grant Ave",
    "iso:country":"US",
    "sg:address":"1000 Grant Ave",
    "sg:city":"San Francisco",
    "sg:classifiers":[
        {
            "category":"Banks & Credit Unions",
            "subcategory":"Bank",
            "type":"Services"
        }
    ],
    "sg:phone":"+1 800 627 3999",
    "sg:postcode":"94133",
    "sg:province":"CA",
    "sg:website":"www.citibank.com",
    "wof:name":"Citibank",
    "wof:placetype":"venue"
},
  "geometry": {"coordinates":[-122.406515,37.796206],"type":"Point"}
}