{
  "type": "Feature",
  "properties": {
    "iso:country":"US",
    "sg:address":"15405 S San Pedro St",
    "sg:city":"Gardena",
    "sg:classifiers":[
        {
            "category":"Wholesale",
            "subcategory":"Machinery & Supplies",
            "type":"Manufacturing & Wholesale Goods"
        }
    ],
    "sg:phone":"+1 310 327 4920",
    "sg:postcode":"90248",
    "sg:province":"CA",
    "sg:tags":[
        "abrasive"
    ],
    "sg:website":"www.abesco.com",
    "wof:name":"Abesco Inc",
    "wof:placetype":"venue"
},
  "geometry": {"coordinates":[-118.266268,33.889744],"type":"Point"}
}