{
  "type": "Feature",
  "properties": {
    "iso:country":"US",
    "sg:address":"2904 N Blackstone Ave",
    "sg:city":"Fresno",
    "sg:classifiers":[
        {
            "category":"Farming",
            "subcategory":"Farm",
            "type":"Manufacturing & Wholesale Goods"
        }
    ],
    "sg:phone":"+1 559 224 2417",
    "sg:postcode":"93704",
    "sg:province":"CA",
    "wof:name":"Small Farms Resource & Trnng",
    "wof:placetype":"venue"
},
  "geometry": {"coordinates":[-119.790464,36.777662],"type":"Point"}
}