{
  "type": "Feature",
  "properties": {
    "addr:full":"40 W Shaw Ave Clovis CA 93612",
    "addr:housenumber":"40",
    "addr:postcode":"93612",
    "addr:street":"W Shaw Ave",
    "iso:country":"US",
    "sg:address":"40 W Shaw Ave",
    "sg:city":"Clovis",
    "sg:classifiers":[
        {
            "category":"Shopping",
            "subcategory":"Tobacco",
            "type":"Retail Goods"
        }
    ],
    "sg:phone":"+1 559 322 0400",
    "sg:postcode":"93612",
    "sg:province":"CA",
    "sg:tags":[
        "cigarette",
        "product",
        "cigar",
        "dealer"
    ],
    "wof:name":"Clovis Discount Cigarette Inc",
    "wof:placetype":"venue"
},
  "geometry": {"coordinates":[-119.70966300000001,36.808408],"type":"Point"}
}