{
  "type": "Feature",
  "properties": {
    "iso:country":"US",
    "sg:address":"3021 State St",
    "sg:city":"Carlsbad",
    "sg:classifiers":[
        {
            "category":"Manufacturing",
            "subcategory":"Printing",
            "type":"Manufacturing & Wholesale Goods"
        }
    ],
    "sg:phone":"+1 760 434 6955",
    "sg:postcode":"92008",
    "sg:province":"CA",
    "sg:tags":[
        "lithographic",
        "commercial"
    ],
    "wof:name":"Pacific Coast Printing",
    "wof:placetype":"venue"
},
  "geometry": {"coordinates":[-117.348584,33.159325],"type":"Point"}
}