{
  "type": "Feature",
  "properties": {
    "iso:country":"US",
    "sg:address":"2842 Rutgers Pl",
    "sg:city":"Oceanside",
    "sg:classifiers":[
        {
            "category":"Building & Trades",
            "subcategory":"Landscaping Services",
            "type":"Services"
        }
    ],
    "sg:phone":"+1 760 754 3978",
    "sg:postcode":"92056",
    "sg:province":"CA",
    "wof:name":"Michael A Sterkin",
    "wof:placetype":"venue"
},
  "geometry": {"coordinates":[-117.304816,33.196847],"type":"Point"}
}