{
  "type": "Feature",
  "properties": {
    "addr:full":"2040 Broad St San Luis Obispo CA 93401",
    "addr:housenumber":"2040",
    "addr:postcode":"93401",
    "addr:street":"Broad St",
    "iso:country":"US",
    "sg:address":"2040 Broad St",
    "sg:city":"San Luis Obispo",
    "sg:classifiers":[
        {
            "category":"Health Services",
            "subcategory":"Doctor",
            "type":"Services"
        }
    ],
    "sg:phone":"+1 805 541 2452",
    "sg:postcode":"93401",
    "sg:province":"CA",
    "sg:tags":[
        "physician",
        "surgeon"
    ],
    "wof:name":"Nir Y Lorant MD",
    "wof:placetype":"venue"
},
  "geometry": {"coordinates":[-120.65810500000001,35.27182],"type":"Point"}
}