{
  "type": "Feature",
  "properties": {
    "iso:country":"US",
    "sg:address":"2230 Foothill Blvd",
    "sg:city":"La Canada Flintridge",
    "sg:classifiers":[
        {
            "category":"Restaurant",
            "type":"Food & Drink"
        }
    ],
    "sg:menulink":"http://www.allmenus.com/ca/pasadena/168972-el-pollo-loco/menu/",
    "sg:phone":"+1 818 249 3538",
    "sg:postcode":"91011",
    "sg:province":"CA",
    "sg:tags":[
        "american",
        "mexican",
        "tex-mex"
    ],
    "wof:name":"El Pollo Loco",
    "wof:placetype":"venue"
},
  "geometry": {"coordinates":[-118.22610899999999,34.216143],"type":"Point"}
}