{
  "type": "Feature",
  "properties": {
    "addr:full":"383 W Badillo St Covina CA 91723",
    "addr:housenumber":"383",
    "addr:postcode":"91723",
    "addr:street":"W Badillo St",
    "iso:country":"US",
    "sg:address":"383 W Badillo St",
    "sg:city":"Covina",
    "sg:classifiers":[
        {
            "category":"Communications",
            "type":"Services"
        }
    ],
    "sg:phone":"+1 626 858 0032",
    "sg:postcode":"91723",
    "sg:province":"CA",
    "sg:tags":[
        "marketing"
    ],
    "wof:name":"Patchworks",
    "wof:placetype":"venue"
},
  "geometry": {"coordinates":[-117.89470300000001,34.086371],"type":"Point"}
}