{
  "type": "Feature",
  "properties": {
    "iso:country":"US",
    "sg:address":"7061 N San Pablo Ave",
    "sg:city":"Pinedale",
    "sg:classifiers":[
        {
            "category":"Organizations",
            "subcategory":"Religious Organization",
            "type":"Services"
        }
    ],
    "sg:phone":"+1 559 439 0711",
    "sg:postcode":"93650",
    "sg:province":"CA",
    "sg:tags":[
        "church"
    ],
    "wof:name":"Assembly Of God Tabernacle",
    "wof:placetype":"venue"
},
  "geometry": {"coordinates":[-119.794592,36.839016],"type":"Point"}
}