{
  "type": "Feature",
  "properties": {
    "addr:full":"39935 Vista Del Sol Rancho Mirage CA 92270",
    "addr:housenumber":"39935",
    "addr:postcode":"92270",
    "addr:street":"Vista Del Sol",
    "iso:country":"US",
    "sg:address":"39935 Vista Del Sol",
    "sg:city":"Rancho Mirage",
    "sg:classifiers":[
        {
            "category":"Health Services",
            "subcategory":"Doctor",
            "type":"Services"
        },
        {
            "category":"Health Services",
            "subcategory":"Hospital",
            "type":"Services"
        }
    ],
    "sg:phone":"+1 760 837 9944",
    "sg:postcode":"92270",
    "sg:province":"CA",
    "sg:tags":[
        "surgeon",
        "oral"
    ],
    "wof:name":"Scheer Peter Ms DDS",
    "wof:placetype":"venue"
},
  "geometry": {"coordinates":[-116.398003,33.762402],"type":"Point"}
}