{
  "type": "Feature",
  "properties": {
    "addr:full":"Campbell Pruneyard Campbell CA 95008",
    "addr:postcode":"95008",
    "addr:street":"Campbell",
    "iso:country":"US",
    "sg:address":"Campbell Pruneyard",
    "sg:city":"Campbell",
    "sg:classifiers":[
        {
            "category":"Restaurant",
            "type":"Food & Drink"
        }
    ],
    "sg:phone":"+1 408 866 7744",
    "sg:postcode":"95008",
    "sg:province":"CA",
    "sg:tags":[
        "pizza"
    ],
    "wof:name":"Pizza My Heart",
    "wof:placetype":"venue"
},
  "geometry": {"coordinates":[-121.95331299999999,37.278956],"type":"Point"}
}