{
  "type": "Feature",
  "properties": {
    "iso:country":"US",
    "sg:address":"1100 Roseville Pkwy Apt 923",
    "sg:city":"Roseville",
    "sg:classifiers":[
        {
            "category":"Shopping",
            "subcategory":"Pets & Pet Supplies",
            "type":"Retail Goods"
        }
    ],
    "sg:phone":"+1 916 532 7199",
    "sg:postcode":"95678",
    "sg:province":"CA",
    "sg:tags":[
        "furnishing",
        "dog",
        "store",
        "cat"
    ],
    "wof:name":"Peace Of Mind Pet Sitting",
    "wof:placetype":"venue"
},
  "geometry": {"coordinates":[-121.264259,38.767979],"type":"Point"}
}