{
  "type": "Feature",
  "properties": {
    "addr:full":"67 W Palm Dr Arcadia CA 91007",
    "addr:housenumber":"67",
    "addr:postcode":"91007",
    "addr:street":"W Palm Dr",
    "iso:country":"US",
    "sg:address":"67 W Palm Dr",
    "sg:city":"Arcadia",
    "sg:classifiers":[
        {
            "category":"Health Services",
            "subcategory":"Hospital",
            "type":"Services"
        }
    ],
    "sg:phone":"+1 626 202 7322",
    "sg:postcode":"91007",
    "sg:province":"CA",
    "sg:tags":[
        "mental"
    ],
    "wof:name":"Subi Pediatric Therapy",
    "wof:placetype":"venue"
},
  "geometry": {"coordinates":[-118.033652,34.111874],"type":"Point"}
}