{
  "type": "Feature",
  "properties": {
    "addr:full":"10824 Tabor St Los Angeles CA 90034",
    "addr:housenumber":"10824",
    "addr:postcode":"90034",
    "addr:street":"Tabor St",
    "iso:country":"US",
    "sg:address":"10824 Tabor St",
    "sg:city":"Los Angeles",
    "sg:classifiers":[
        {
            "category":"Wholesale",
            "subcategory":"Stationery",
            "type":"Manufacturing & Wholesale Goods"
        }
    ],
    "sg:phone":"+1 310 838 8080",
    "sg:postcode":"90034",
    "sg:province":"CA",
    "sg:tags":[
        "supply"
    ],
    "wof:name":"Goodman & Associates",
    "wof:placetype":"venue"
},
  "geometry": {"coordinates":[-118.413599,34.02148],"type":"Point"}
}