{
  "type": "Feature",
  "properties": {
    "addr:full":"2520 Continental Ave El Monte CA 91733",
    "addr:housenumber":"2520",
    "addr:postcode":"91733",
    "addr:street":"Continental Ave",
    "iso:country":"US",
    "sg:address":"2520 Continental Ave",
    "sg:city":"El Monte",
    "sg:classifiers":[
        {
            "category":"Wholesale",
            "subcategory":"Medical Equipment & Supplies",
            "type":"Manufacturing & Wholesale Goods"
        }
    ],
    "sg:phone":"+1 626 454 5188",
    "sg:postcode":"91733",
    "sg:province":"CA",
    "sg:tags":[
        "sun",
        "goggles",
        "sunglasses"
    ],
    "wof:name":"Frontier Fashion Inc",
    "wof:placetype":"venue"
},
  "geometry": {"coordinates":[-118.038071,34.058011],"type":"Point"}
}