{
  "type": "Feature",
  "properties": {
    "iso:country":"US",
    "sg:address":"73730 Highway 111 Ste 7",
    "sg:city":"Palm Desert",
    "sg:classifiers":[
        {
            "category":"Personal",
            "subcategory":"Skin Care",
            "type":"Services"
        }
    ],
    "sg:phone":"+1 760 779 5533",
    "sg:postcode":"92260",
    "sg:province":"CA",
    "wof:name":"Touched By An Angel",
    "wof:placetype":"venue"
},
  "geometry": {"coordinates":[-116.37843100000001,33.72152],"type":"Point"}
}