{
  "type": "Feature",
  "properties": {
    "addr:full":"19 Redwood Ave Redwood City CA 94061",
    "addr:housenumber":"19",
    "addr:postcode":"94061",
    "addr:street":"Redwood Ave",
    "iso:country":"US",
    "sg:address":"19 Redwood Ave",
    "sg:city":"Redwood City",
    "sg:classifiers":[
        {
            "category":"Professional",
            "type":"Services"
        }
    ],
    "sg:phone":"+1 650 839 0233",
    "sg:postcode":"94061",
    "sg:province":"CA",
    "wof:name":"Antonio Castillo",
    "wof:placetype":"venue"
},
  "geometry": {"coordinates":[-122.222756,37.475343],"type":"Point"}
}