{
  "type": "Feature",
  "properties": {
    "addr:full":"207 Skyline Boulevard San Francisco CA 94132",
    "addr:housenumber":"207",
    "addr:postcode":"94132",
    "addr:street":"Skyline Boulevard",
    "iso:country":"US",
    "sg:address":"207 Skyline Boulevard",
    "sg:city":"San Francisco",
    "sg:classifiers":[
        {
            "category":"Sports & Exercise",
            "subcategory":"Sports Center",
            "type":"Entertainment"
        },
        {
            "category":"Retail",
            "subcategory":"Event Space",
            "type":"Services"
        }
    ],
    "sg:phone":"+1 415 665 4100",
    "sg:postcode":"94132",
    "sg:province":"CA",
    "sg:tags":[
        "venue",
        "amateur",
        "team"
    ],
    "wof:name":"Recreation Center For the Handicapped-Rch",
    "wof:placetype":"venue"
},
  "geometry": {"coordinates":[-122.50099899999999,37.728901],"type":"Point"}
}