{
  "type": "Feature",
  "properties": {
    "addr:full":"4221 N Freeway Blvd Sacramento CA 95834",
    "addr:housenumber":"4221",
    "addr:postcode":"95834",
    "addr:street":"N Freeway Blvd",
    "iso:country":"US",
    "sg:address":"4221 N Freeway Blvd",
    "sg:city":"Sacramento",
    "sg:classifiers":[
        {
            "category":"Government",
            "subcategory":"Jail",
            "type":"Public Place"
        }
    ],
    "sg:phone":"+1 916 874 5181",
    "sg:postcode":"95834",
    "sg:province":"CA",
    "sg:tags":[
        "correctional",
        "institution"
    ],
    "wof:name":"Sacramnto Cnty Shrff Dept Jail",
    "wof:placetype":"venue"
},
  "geometry": {"coordinates":[-121.47961599999999,38.641051],"type":"Point"}
}