{
  "type": "Feature",
  "properties": {
    "addr:full":"10845 Queensland St Los Angeles CA 90034",
    "addr:housenumber":"10845",
    "addr:postcode":"90034",
    "addr:street":"Queensland St",
    "iso:country":"US",
    "sg:address":"10845 Queensland St",
    "sg:city":"Los Angeles",
    "sg:classifiers":[
        {
            "category":"Shopping",
            "type":"Retail Goods"
        }
    ],
    "sg:phone":"+1 310 765 4081",
    "sg:postcode":"90034",
    "sg:province":"CA",
    "sg:tags":[
        "medical",
        "video",
        "supply"
    ],
    "wof:name":"Jerabek & Company Inc",
    "wof:placetype":"venue"
},
  "geometry": {"coordinates":[-118.419436,34.027998],"type":"Point"}
}