{
  "type": "Feature",
  "properties": {
    "iso:country":"US",
    "sg:address":"609 Jefferson St",
    "sg:city":"Fairfield",
    "sg:classifiers":[
        {
            "category":"Health Services",
            "subcategory":"Hospital",
            "type":"Services"
        }
    ],
    "sg:phone":"+1 707 434 0962",
    "sg:postcode":"94533",
    "sg:province":"CA",
    "sg:tags":[
        "mental"
    ],
    "wof:name":"Sharon Bender",
    "wof:placetype":"venue"
},
  "geometry": {"coordinates":[-122.041992,38.248589],"type":"Point"}
}