{
  "type": "Feature",
  "properties": {
    "iso:country":"US",
    "sg:address":"239 Valparaiso Ave",
    "sg:city":"Cotati",
    "sg:classifiers":[
        {
            "category":"Building & Trades",
            "subcategory":"Construction",
            "type":"Services"
        }
    ],
    "sg:phone":"+1 707 664 0439",
    "sg:postcode":"94931",
    "sg:province":"CA",
    "sg:tags":[
        "house",
        "con"
    ],
    "wof:name":"Vargas Construction",
    "wof:placetype":"venue"
},
  "geometry": {"coordinates":[-122.70653799999999,38.322362],"type":"Point"}
}