{
  "type": "Feature",
  "properties": {
    "addr:full":"700 Cannery Row Monterey CA 93940",
    "addr:housenumber":"700",
    "addr:postcode":"93940",
    "addr:street":"Cannery Row",
    "iso:country":"US",
    "sg:address":"700 Cannery Row",
    "sg:city":"Monterey",
    "sg:classifiers":[
        {
            "category":"Restaurant",
            "type":"Food & Drink"
        }
    ],
    "sg:phone":"+1 831 649 8050",
    "sg:postcode":"93940",
    "sg:province":"CA",
    "wof:name":"Sly Mc Fly's Lunch & Dinner",
    "wof:placetype":"venue"
},
  "geometry": {"coordinates":[-121.90123199999999,36.617079],"type":"Point"}
}