{
  "type": "Feature",
  "properties": {
    "addr:full":"2150 Monterey Hwy San Jose CA 95112",
    "addr:housenumber":"2150",
    "addr:postcode":"95112",
    "addr:street":"Monterey Hwy",
    "iso:country":"US",
    "sg:address":"2150 Monterey Hwy",
    "sg:city":"San Jose",
    "sg:classifiers":[
        {
            "category":"Banks & Credit Unions",
            "subcategory":"Investment Brokerage",
            "type":"Services"
        }
    ],
    "sg:phone":"+1 408 292 0791",
    "sg:postcode":"95112",
    "sg:province":"CA",
    "wof:name":"Jpp Investments",
    "wof:placetype":"venue"
},
  "geometry": {"coordinates":[-121.86058199999999,37.302994],"type":"Point"}
}