{
  "type": "Feature",
  "properties": {
    "addr:full":"2202 Main St Santa Monica CA 90405",
    "addr:housenumber":"2202",
    "addr:postcode":"90405",
    "addr:street":"Main St",
    "iso:country":"US",
    "sg:address":"2202 Main St",
    "sg:city":"Santa Monica",
    "sg:classifiers":[
        {
            "category":"Communications",
            "subcategory":"Film & Video Production",
            "type":"Services"
        }
    ],
    "sg:phone":"+1 310 450 1942",
    "sg:postcode":"90405",
    "sg:province":"CA",
    "sg:tags":[
        "motion",
        "picture",
        "studio",
        "producer"
    ],
    "wof:name":"Plum Productions",
    "wof:placetype":"venue"
},
  "geometry": {"coordinates":[-118.486654,34.004841],"type":"Point"}
}