{
  "type": "Feature",
  "properties": {
    "addr:full":"626 Lincoln St Santa Clara CA 95050",
    "addr:housenumber":"626",
    "addr:postcode":"95050",
    "addr:street":"Lincoln St",
    "iso:country":"US",
    "sg:address":"626 Lincoln St",
    "sg:city":"Santa Clara",
    "sg:classifiers":[
        {
            "category":"Local Transit",
            "type":"Transportation"
        }
    ],
    "sg:phone":"+1 408 554 9465",
    "sg:postcode":"95050",
    "sg:province":"CA",
    "sg:tags":[
        "passenger",
        "limo"
    ],
    "wof:name":"Image 2000 Limousine",
    "wof:placetype":"venue"
},
  "geometry": {"coordinates":[-121.949997,37.344002],"type":"Point"}
}