{
  "type": "Feature",
  "properties": {
    "addr:full":"1536 N Western Ave Los Angeles CA 90027",
    "addr:housenumber":"1536",
    "addr:postcode":"90027",
    "addr:street":"N Western Ave",
    "iso:country":"US",
    "sg:address":"1536 N Western Ave",
    "sg:city":"Los Angeles",
    "sg:classifiers":[
        {
            "category":"Travel",
            "subcategory":"Hotels & Motels",
            "type":"Entertainment"
        }
    ],
    "sg:phone":"+1 323 467 3131",
    "sg:postcode":"90027",
    "sg:province":"CA",
    "sg:website":"www.super8.com",
    "wof:name":"Legacy Hotel",
    "wof:placetype":"venue"
},
  "geometry": {"coordinates":[-118.308998,34.098801],"type":"Point"}
}