{
  "type": "Feature",
  "properties": {
    "addr:full":"61612 Sagebrush Rd North Palm Spgs CA 92258",
    "addr:housenumber":"61612",
    "addr:postcode":"92258",
    "addr:street":"Sagebrush Rd",
    "iso:country":"US",
    "sg:address":"61612 Sagebrush Rd",
    "sg:city":"North Palm Spgs",
    "sg:classifiers":[
        {
            "category":"Building & Trades",
            "subcategory":"Construction",
            "type":"Services"
        }
    ],
    "sg:phone":"+1 760 251 6898",
    "sg:postcode":"92258",
    "sg:province":"CA",
    "sg:tags":[
        "contractor"
    ],
    "wof:name":"Enbody Construction",
    "wof:placetype":"venue"
},
  "geometry": {"coordinates":[-116.580611,33.928403],"type":"Point"}
}