{
  "type": "Feature",
  "properties": {
    "addr:full":"2828 35th Ave San Francisco CA 94116",
    "addr:housenumber":"2828",
    "addr:postcode":"94116",
    "addr:street":"35Th Ave",
    "iso:country":"US",
    "sg:address":"2828 35th Ave",
    "sg:city":"San Francisco",
    "sg:classifiers":[
        {
            "category":"Professional",
            "subcategory":"Art Services",
            "type":"Services"
        }
    ],
    "sg:phone":"+1 415 948 1489",
    "sg:postcode":"94116",
    "sg:province":"CA",
    "sg:tags":[
        "photographer"
    ],
    "wof:name":"L 2 Photography",
    "wof:placetype":"venue"
},
  "geometry": {"coordinates":[-122.492231,37.734763],"type":"Point"}
}