{
  "type": "Feature",
  "properties": {
    "addr:full":"Corner of Juniper and Sagewood Streets San Leandro CA 94579",
    "addr:housenumber":"and",
    "addr:postcode":"94579",
    "addr:street":"Corner Of;Sagewood Streets",
    "iso:country":"US",
    "sg:address":"Corner of Juniper and Sagewood Streets",
    "sg:city":"San Leandro",
    "sg:classifiers":[
        {
            "category":"Park",
            "type":"Public Place"
        }
    ],
    "sg:phone":"+1 510 577 3462",
    "sg:postcode":"94579",
    "sg:province":"CA",
    "sg:website":"www.ci.san-leandro.ca.us/slparks...",
    "wof:name":"Bonaire Park",
    "wof:placetype":"venue"
},
  "geometry": {"coordinates":[-122.16013100000001,37.693796],"type":"Point"}
}