{
  "type": "Feature",
  "properties": {
    "iso:country":"US",
    "sg:address":"550 Pacific Avenue",
    "sg:city":"San Francisco",
    "sg:classifiers":[
        {
            "category":"Building & Trades",
            "subcategory":"Construction",
            "type":"Services"
        }
    ],
    "sg:phone":"+1 415 772 5550",
    "sg:postcode":"94133",
    "sg:province":"CA",
    "sg:tags":[
        "interior",
        "design"
    ],
    "wof:name":"Volpe Steven Design",
    "wof:placetype":"venue"
},
  "geometry": {"coordinates":[-122.40441,37.797363],"type":"Point"}
}