{
  "type": "Feature",
  "properties": {
    "addr:full":"6424 San Fernando Rd Glendale CA 91201",
    "addr:housenumber":"6424",
    "addr:postcode":"91201",
    "addr:street":"San Fernando Rd",
    "iso:country":"US",
    "sg:address":"6424 San Fernando Rd",
    "sg:city":"Glendale",
    "sg:classifiers":[
        {
            "category":"Restaurant",
            "type":"Food & Drink"
        }
    ],
    "sg:phone":"+1 818 241 1648",
    "sg:postcode":"91201",
    "sg:province":"CA",
    "wof:name":"Yo Yo",
    "wof:placetype":"venue"
},
  "geometry": {"coordinates":[-118.28829,34.165963],"type":"Point"}
}