{
  "type": "Feature",
  "properties": {
    "addr:full":"12491 Loma Rica Dr Grass Valley CA 95945",
    "addr:housenumber":"12491",
    "addr:postcode":"95945",
    "addr:street":"Loma Rica Dr",
    "iso:country":"US",
    "sg:address":"12491 Loma Rica Dr",
    "sg:city":"Grass Valley",
    "sg:classifiers":[
        {
            "category":"Utilities",
            "subcategory":"Telephone",
            "type":"Services"
        }
    ],
    "sg:phone":"+1 530 272 3600",
    "sg:postcode":"95945",
    "sg:province":"CA",
    "sg:tags":[
        "communications"
    ],
    "wof:name":"Kls Technologies LLC",
    "wof:placetype":"venue"
},
  "geometry": {"coordinates":[-121.01423,39.22108],"type":"Point"}
}