{
  "type": "Feature",
  "properties": {
    "iso:country":"US",
    "sg:address":"23361 El Toro Rd Ste 220",
    "sg:city":"Lake Forest",
    "sg:classifiers":[
        {
            "category":"Health Services",
            "subcategory":"Doctor",
            "type":"Services"
        }
    ],
    "sg:phone":"+1 949 770 3145",
    "sg:postcode":"92630",
    "sg:province":"CA",
    "sg:tags":[
        "psychiatrist"
    ],
    "wof:name":"Kuechler James MD",
    "wof:placetype":"venue"
},
  "geometry": {"coordinates":[-117.697028,33.623583],"type":"Point"}
}