{
  "type": "Feature",
  "properties": {
    "addr:full":"641 N Main St Corona CA 92880",
    "addr:housenumber":"641",
    "addr:postcode":"92880",
    "addr:street":"N Main St",
    "iso:country":"US",
    "sg:address":"641 N Main St",
    "sg:city":"Corona",
    "sg:classifiers":[
        {
            "category":"Manufacturing",
            "subcategory":"Signs",
            "type":"Manufacturing & Wholesale Goods"
        }
    ],
    "sg:phone":"+1 951 735 3362",
    "sg:postcode":"92880",
    "sg:province":"CA",
    "sg:tags":[
        "specialty",
        "mfg"
    ],
    "wof:name":"Empire Sign Solutions",
    "wof:placetype":"venue"
},
  "geometry": {"coordinates":[-117.56372500000001,33.892113],"type":"Point"}
}