{
  "type": "Feature",
  "properties": {
    "iso:country":"US",
    "sg:address":"27192 Sun City Blvd",
    "sg:city":"Sun City",
    "sg:classifiers":[
        {
            "category":"Professional",
            "subcategory":"Computer Services",
            "type":"Services"
        }
    ],
    "sg:phone":"+1 951 679 2327",
    "sg:postcode":"92586",
    "sg:province":"CA",
    "sg:tags":[
        "internet"
    ],
    "sg:website":"www.media.com",
    "wof:name":"MEDIA.COM",
    "wof:placetype":"venue"
},
  "geometry": {"coordinates":[-117.193815,33.712915],"type":"Point"}
}