{
  "type": "Feature",
  "properties": {
    "addr:full":"11580 Mirror Lake Ct Grass Valley CA 95945",
    "addr:housenumber":"11580",
    "addr:postcode":"95945",
    "addr:street":"Mirror Lake Ct",
    "iso:country":"US",
    "sg:address":"11580 Mirror Lake Ct",
    "sg:city":"Grass Valley",
    "sg:classifiers":[
        {
            "category":"Insurance",
            "subcategory":"Insurance Agent",
            "type":"Services"
        }
    ],
    "sg:phone":"+1 530 274 7188",
    "sg:postcode":"95945",
    "sg:province":"CA",
    "wof:name":"Horace Mann Insurance Co",
    "wof:placetype":"venue"
},
  "geometry": {"coordinates":[-121.03291299999999,39.15251],"type":"Point"}
}