{
  "type": "Feature",
  "properties": {
    "iso:country":"US",
    "sg:address":"72929 Sonora Dr",
    "sg:city":"Palm Desert",
    "sg:classifiers":[
        {
            "category":"Restaurant",
            "type":"Food & Drink"
        }
    ],
    "sg:phone":"+1 760 341 4091",
    "sg:postcode":"92260",
    "sg:province":"CA",
    "sg:tags":[
        "caterer"
    ],
    "wof:name":"Akamoos Island Sushi",
    "wof:placetype":"venue"
},
  "geometry": {"coordinates":[-116.39272699999999,33.727232],"type":"Point"}
}