{
  "type": "Feature",
  "properties": {
    "iso:country":"US",
    "sg:address":"9283 Karerllyn Dr",
    "sg:city":"Santee",
    "sg:classifiers":[
        {
            "category":"Freight",
            "type":"Transportation"
        }
    ],
    "sg:phone":"+1 619 596 2888",
    "sg:postcode":"92071",
    "sg:province":"CA",
    "sg:tags":[
        "operator",
        "trucking"
    ],
    "wof:name":"Western Trucking LLC",
    "wof:placetype":"venue"
},
  "geometry": {"coordinates":[-116.948183,32.848869],"type":"Point"}
}