{
  "type": "Feature",
  "properties": {
    "iso:country":"US",
    "sg:address":"2523 W Temple St",
    "sg:city":"Los Angeles",
    "sg:classifiers":[
        {
            "category":"Restaurant",
            "type":"Food & Drink"
        }
    ],
    "sg:phone":"+1 213 386 7411",
    "sg:postcode":"90026",
    "sg:province":"CA",
    "wof:name":"Doris Bakery",
    "wof:placetype":"venue"
},
  "geometry": {"coordinates":[-118.274745,34.072558],"type":"Point"}
}