{
  "type": "Feature",
  "properties": {
    "addr:full":"609 E Balboa Boulevard Newport Beach CA 92661",
    "addr:housenumber":"609",
    "addr:postcode":"92661",
    "addr:street":"E Balboa Boulevard",
    "iso:country":"US",
    "sg:address":"609 E Balboa Boulevard",
    "sg:city":"Newport Beach",
    "sg:classifiers":[
        {
            "category":"Personal",
            "subcategory":"Tattoo Parlor",
            "type":"Services"
        }
    ],
    "sg:phone":"+1 949 675 1412",
    "sg:postcode":"92661",
    "sg:province":"CA",
    "sg:website":"www.electrictattooingoc.com",
    "wof:name":"Electric Tattooing",
    "wof:placetype":"venue"
},
  "geometry": {"coordinates":[-117.900977,33.602525],"type":"Point"}
}