{
  "type": "Feature",
  "properties": {
    "addr:full":"750 Design Ct Ste 106 Chula Vista CA 91911",
    "addr:housenumber":"750",
    "addr:postcode":"91911",
    "addr:street":"Design Ct Ste 106",
    "iso:country":"US",
    "sg:address":"750 Design Ct Ste 106",
    "sg:city":"Chula Vista",
    "sg:classifiers":[
        {
            "category":"Shopping",
            "subcategory":"Bicycles & Sporting Goods",
            "type":"Retail Goods"
        }
    ],
    "sg:phone":"+1 619 482 8833",
    "sg:postcode":"91911",
    "sg:province":"CA",
    "wof:name":"Fleet Food Service Equipment",
    "wof:placetype":"venue"
},
  "geometry": {"coordinates":[-117.056,32.608101],"type":"Point"}
}