{
  "type": "Feature",
  "properties": {
    "iso:country":"US",
    "sg:address":"1617 Tyler St",
    "sg:city":"Berkeley",
    "sg:classifiers":[
        {
            "category":"Professional",
            "subcategory":"Advertising",
            "type":"Services"
        }
    ],
    "sg:phone":"+1 510 859 4236",
    "sg:postcode":"94703",
    "sg:province":"CA",
    "sg:tags":[
        "marketing"
    ],
    "sg:website":"www.upayaservices.com",
    "wof:name":"Upaya Services",
    "wof:placetype":"venue"
},
  "geometry": {"coordinates":[-122.27575299999999,37.853056],"type":"Point"}
}