{
  "type": "Feature",
  "properties": {
    "addr:full":"695 Bridgeway Sausalito CA 94965",
    "addr:housenumber":"695",
    "addr:postcode":"94965",
    "addr:street":"Bridgeway",
    "iso:country":"US",
    "sg:address":"695 Bridgeway",
    "sg:city":"Sausalito",
    "sg:classifiers":[
        {
            "category":"Shopping",
            "subcategory":"Hobbies, Toys, & Games",
            "type":"Retail Goods"
        }
    ],
    "sg:phone":"+1 415 332 4151",
    "sg:postcode":"94965",
    "sg:province":"CA",
    "wof:name":"Games People Play Inc",
    "wof:placetype":"venue"
},
  "geometry": {"coordinates":[-122.47917,37.85512],"type":"Point"}
}