{
  "type": "Feature",
  "properties": {
    "addr:full":"12720 Norwalk Blvd Norwalk CA 90650",
    "addr:housenumber":"12720",
    "addr:postcode":"90650",
    "addr:street":"Norwalk Blvd",
    "iso:country":"US",
    "sg:address":"12720 Norwalk Blvd",
    "sg:city":"Norwalk",
    "sg:classifiers":[
        {
            "category":"Restaurant",
            "type":"Food & Drink"
        }
    ],
    "sg:phone":"+1 562 868 2026",
    "sg:postcode":"90650",
    "sg:province":"CA",
    "sg:tags":[
        "shop",
        "tea",
        "coffee"
    ],
    "wof:name":"Balani's Snacks & Food Service",
    "wof:placetype":"venue"
},
  "geometry": {"coordinates":[-118.072998,33.915401],"type":"Point"}
}