{
  "type": "Feature",
  "properties": {
    "addr:full":"29343 Merced Ave Shafter CA 93263",
    "addr:housenumber":"29343",
    "addr:postcode":"93263",
    "addr:street":"Merced Ave",
    "iso:country":"US",
    "sg:address":"29343 Merced Ave",
    "sg:city":"Shafter",
    "sg:classifiers":[
        {
            "category":"Building & Trades",
            "subcategory":"Landscaping Services",
            "type":"Services"
        }
    ],
    "sg:phone":"+1 661 746 9999",
    "sg:postcode":"93263",
    "sg:province":"CA",
    "sg:tags":[
        "landscape",
        "supply"
    ],
    "wof:name":"Nickel Palm Nursery",
    "wof:placetype":"venue"
},
  "geometry": {"coordinates":[-119.33041900000001,35.528923],"type":"Point"}
}