{
  "type": "Feature",
  "properties": {
    "addr:full":"1925 Jerrold Ave San Francisco CA 94124",
    "addr:housenumber":"1925",
    "addr:postcode":"94124",
    "addr:street":"Jerrold Ave",
    "iso:country":"US",
    "sg:address":"1925 Jerrold Ave",
    "sg:city":"San Francisco",
    "sg:classifiers":[
        {
            "category":"Wholesale",
            "subcategory":"Furniture",
            "type":"Manufacturing & Wholesale Goods"
        }
    ],
    "sg:phone":"+1 650 878 8513",
    "sg:postcode":"94124",
    "sg:province":"CA",
    "sg:tags":[
        "household",
        "product"
    ],
    "wof:name":"Golden 8 Trading",
    "wof:placetype":"venue"
},
  "geometry": {"coordinates":[-122.396631,37.742573],"type":"Point"}
}