{
  "type": "Feature",
  "properties": {
    "iso:country":"US",
    "sg:address":"1620 N Vista Ave",
    "sg:city":"Rialto",
    "sg:classifiers":[
        {
            "category":"Restaurant",
            "type":"Food & Drink"
        }
    ],
    "sg:phone":"+1 909 873 1688",
    "sg:postcode":"92376",
    "sg:province":"CA",
    "sg:tags":[
        "catering"
    ],
    "wof:name":"At Your Service Catering",
    "wof:placetype":"venue"
},
  "geometry": {"coordinates":[-117.377568,34.129887],"type":"Point"}
}