{
  "type": "Feature",
  "properties": {
    "iso:country":"US",
    "sg:address":"28310 Roadside Dr",
    "sg:city":"Agoura Hills",
    "sg:classifiers":[
        {
            "category":"Wholesale",
            "subcategory":"Computers",
            "type":"Manufacturing & Wholesale Goods"
        }
    ],
    "sg:phone":"+1 818 597 1002",
    "sg:postcode":"91301",
    "sg:province":"CA",
    "wof:name":"Ctxpert",
    "wof:placetype":"venue"
},
  "geometry": {"coordinates":[-118.743421,34.142646],"type":"Point"}
}