{
  "type": "Feature",
  "properties": {
    "iso:country":"US",
    "sg:address":"749 N Plano St",
    "sg:city":"Porterville",
    "sg:classifiers":[
        {
            "category":"Manufacturing",
            "subcategory":"Food",
            "type":"Manufacturing & Wholesale Goods"
        }
    ],
    "sg:phone":"+1 559 784 3468",
    "sg:postcode":"93257",
    "sg:province":"CA",
    "sg:tags":[
        "olive",
        "oil"
    ],
    "wof:name":"Golden Eagle Olive Products",
    "wof:placetype":"venue"
},
  "geometry": {"coordinates":[-119.00862100000001,36.077499],"type":"Point"}
}