{
  "type": "Feature",
  "properties": {
    "iso:country":"US",
    "sg:address":"1444 N Poinsettia Pl",
    "sg:city":"Los Angeles",
    "sg:classifiers":[
        {
            "category":"Real Estate",
            "subcategory":"Real Estate Operator",
            "type":"Services"
        }
    ],
    "sg:phone":"+1 323 874 4662",
    "sg:postcode":"90046",
    "sg:province":"CA",
    "sg:tags":[
        "apartment"
    ],
    "wof:name":"Poinsettia Club Apartments",
    "wof:placetype":"venue"
},
  "geometry": {"coordinates":[-118.34825600000001,34.09545],"type":"Point"}
}