{
  "type": "Feature",
  "properties": {
    "iso:country":"US",
    "sg:address":"7826 Norwalk Blvd",
    "sg:city":"Whittier",
    "sg:classifiers":[
        {
            "category":"Professional",
            "subcategory":"Accounting & Tax Preparation",
            "type":"Services"
        }
    ],
    "sg:phone":"+1 562 908 2001",
    "sg:postcode":"90606",
    "sg:province":"CA",
    "sg:tags":[
        "return",
        "filing"
    ],
    "wof:name":"Jackson Hewitt Tax Svc",
    "wof:placetype":"venue"
},
  "geometry": {"coordinates":[-118.074634,33.974273],"type":"Point"}
}