{
  "type": "Feature",
  "properties": {
    "addr:full":"20936 Gresham St Canoga Park CA 91304",
    "addr:housenumber":"20936",
    "addr:postcode":"91304",
    "addr:street":"Gresham St",
    "iso:country":"US",
    "sg:address":"20936 Gresham St",
    "sg:city":"Canoga Park",
    "sg:classifiers":[
        {
            "category":"Shopping",
            "subcategory":"Catalog Store",
            "type":"Retail Goods"
        }
    ],
    "sg:phone":"+1 818 718 2884",
    "sg:postcode":"91304",
    "sg:province":"CA",
    "sg:tags":[
        "mail",
        "house"
    ],
    "wof:name":"SC Merchandise",
    "wof:placetype":"venue"
},
  "geometry": {"coordinates":[-118.590046,34.230545],"type":"Point"}
}