{
  "type": "Feature",
  "properties": {
    "addr:full":"1700 E Bullard Ave Fresno CA 93710",
    "addr:housenumber":"1700",
    "addr:postcode":"93710",
    "addr:street":"E Bullard Ave",
    "iso:country":"US",
    "sg:address":"1700 E Bullard Ave",
    "sg:city":"Fresno",
    "sg:classifiers":[
        {
            "category":"Health Services",
            "subcategory":"Health Practitioner",
            "type":"Services"
        }
    ],
    "sg:phone":"+1 559 438 8531",
    "sg:postcode":"93710",
    "sg:province":"CA",
    "sg:tags":[
        "therapist",
        "physical"
    ],
    "wof:name":"Mc Guire Physical Therapy Inc",
    "wof:placetype":"venue"
},
  "geometry": {"coordinates":[-119.75488900000001,36.823195],"type":"Point"}
}