{
  "type": "Feature",
  "properties": {
    "addr:full":"1001 Roseglen Way Corona CA 92882",
    "addr:housenumber":"1001",
    "addr:postcode":"92882",
    "addr:street":"Roseglen Way",
    "iso:country":"US",
    "sg:address":"1001 Roseglen Way",
    "sg:city":"Corona",
    "sg:classifiers":[
        {
            "category":"Real Estate",
            "subcategory":"Real Estate Operator",
            "type":"Services"
        }
    ],
    "sg:phone":"+1 951 734 7421",
    "sg:postcode":"92882",
    "sg:province":"CA",
    "sg:tags":[
        "mobile",
        "home",
        "community"
    ],
    "wof:name":"Village Grove Mobile Home",
    "wof:placetype":"venue"
},
  "geometry": {"coordinates":[-117.593486,33.873539],"type":"Point"}
}