{
  "type": "Feature",
  "properties": {
    "addr:full":"11967 Pinnacle Pl Beverly Hills CA 90210",
    "addr:housenumber":"11967",
    "addr:postcode":"90210",
    "addr:street":"Pinnacle Pl",
    "iso:country":"US",
    "sg:address":"11967 Pinnacle Pl",
    "sg:city":"Beverly Hills",
    "sg:classifiers":[
        {
            "category":"Professional",
            "subcategory":"Lawyer & Legal Services",
            "type":"Services"
        }
    ],
    "sg:phone":"+1 310 859 0060",
    "sg:postcode":"90210",
    "sg:province":"CA",
    "sg:tags":[
        "attorney"
    ],
    "wof:name":"Professional Design Co-Op",
    "wof:placetype":"venue"
},
  "geometry": {"coordinates":[-118.397964,34.125897],"type":"Point"}
}