{
  "type": "Feature",
  "properties": {
    "addr:full":"110 W Barstow Ave Fresno CA 93704",
    "addr:housenumber":"110",
    "addr:postcode":"93704",
    "addr:street":"W Barstow Ave",
    "iso:country":"US",
    "sg:address":"110 W Barstow Ave",
    "sg:city":"Fresno",
    "sg:classifiers":[
        {
            "category":"Freight",
            "type":"Transportation"
        }
    ],
    "sg:phone":"+1 559 436 4879",
    "sg:postcode":"93704",
    "sg:province":"CA",
    "sg:tags":[
        "operator",
        "local",
        "trucking"
    ],
    "wof:name":"Mythos",
    "wof:placetype":"venue"
},
  "geometry": {"coordinates":[-119.79192399999999,36.815773],"type":"Point"}
}