{
  "type": "Feature",
  "properties": {
    "addr:full":"5449 Cherry Ave Long Beach CA 90805",
    "addr:housenumber":"5449",
    "addr:postcode":"90805",
    "addr:street":"Cherry Ave",
    "iso:country":"US",
    "sg:address":"5449 Cherry Ave",
    "sg:city":"Long Beach",
    "sg:classifiers":[
        {
            "category":"Restaurant",
            "type":"Food & Drink"
        }
    ],
    "sg:phone":"+1 562 428 0337",
    "sg:postcode":"90805",
    "sg:province":"CA",
    "wof:name":"Kim Sun Kitchen",
    "wof:placetype":"venue"
},
  "geometry": {"coordinates":[-118.168601,33.856489],"type":"Point"}
}