{
  "type": "Feature",
  "properties": {
    "addr:full":"20041 Bollinger Rd Cupertino CA 95014",
    "addr:housenumber":"20041",
    "addr:postcode":"95014",
    "addr:street":"Bollinger Rd",
    "iso:country":"US",
    "sg:address":"20041 Bollinger Rd",
    "sg:city":"Cupertino",
    "sg:classifiers":[
        {
            "category":"Freight",
            "type":"Transportation"
        }
    ],
    "sg:phone":"+1 408 255 6557",
    "sg:postcode":"95014",
    "sg:province":"CA",
    "sg:tags":[
        "delivery"
    ],
    "wof:name":"Ho Ho Restaurant Delivery",
    "wof:placetype":"venue"
},
  "geometry": {"coordinates":[-122.023438,37.310008],"type":"Point"}
}