{
  "type": "Feature",
  "properties": {
    "addr:full":"934 N Perris St San Bernardino CA 92411",
    "addr:housenumber":"934",
    "addr:postcode":"92411",
    "addr:street":"N Perris St",
    "iso:country":"US",
    "sg:address":"934 N Perris St",
    "sg:city":"San Bernardino",
    "sg:classifiers":[
        {
            "category":"Banks & Credit Unions",
            "subcategory":"Investment Brokerage",
            "type":"Services"
        }
    ],
    "sg:phone":"+1 909 885 9775",
    "sg:postcode":"92411",
    "sg:province":"CA",
    "wof:name":"J & L Investing",
    "wof:placetype":"venue"
},
  "geometry": {"coordinates":[-117.30687,34.116162],"type":"Point"}
}