{
  "type": "Feature",
  "properties": {
    "addr:full":"31 N 2nd St Ste 270 San Jose CA 95113",
    "addr:housenumber":"31",
    "addr:postcode":"95113",
    "addr:street":"N 2Nd St Ste 270",
    "iso:country":"US",
    "sg:address":"31 N 2nd St Ste 270",
    "sg:city":"San Jose",
    "sg:classifiers":[
        {
            "category":"Insurance",
            "subcategory":"Hazard Insurance",
            "type":"Services"
        }
    ],
    "sg:phone":"+1 408 297 0591",
    "sg:postcode":"95113",
    "sg:province":"CA",
    "wof:name":"Nicholson John Brokers",
    "wof:placetype":"venue"
},
  "geometry": {"coordinates":[-121.890247,37.33707],"type":"Point"}
}