{
  "type": "Feature",
  "properties": {
    "addr:full":"25411 Cabot Rd Laguna Hills CA 92653",
    "addr:housenumber":"25411",
    "addr:postcode":"92653",
    "addr:street":"Cabot Rd",
    "iso:country":"US",
    "sg:address":"25411 Cabot Rd",
    "sg:city":"Laguna Hills",
    "sg:classifiers":[
        {
            "category":"Real Estate",
            "subcategory":"Real Estate Agent",
            "type":"Services"
        }
    ],
    "sg:phone":"+1 949 855 3224",
    "sg:postcode":"92653",
    "sg:province":"CA",
    "wof:name":"Elite Real Estate Brokers",
    "wof:placetype":"venue"
},
  "geometry": {"coordinates":[-117.674672,33.592394],"type":"Point"}
}