{
  "type": "Feature",
  "properties": {
    "addr:full":"13785 Ramona Ave Chino CA 91710",
    "addr:housenumber":"13785",
    "addr:postcode":"91710",
    "addr:street":"Ramona Ave",
    "iso:country":"US",
    "sg:address":"13785 Ramona Ave",
    "sg:city":"Chino",
    "sg:classifiers":[
        {
            "category":"Wholesale",
            "subcategory":"Electrical",
            "type":"Manufacturing & Wholesale Goods"
        }
    ],
    "sg:phone":"+1 909 628 1511",
    "sg:postcode":"91710",
    "sg:province":"CA",
    "sg:tags":[
        "equipment"
    ],
    "wof:name":"Direct Lighting",
    "wof:placetype":"venue"
},
  "geometry": {"coordinates":[-117.70635799999999,33.997624],"type":"Point"}
}