{
  "type": "Feature",
  "properties": {
    "addr:full":"163 Plaza Dr Vallejo CA 94591",
    "addr:housenumber":"163",
    "addr:postcode":"94591",
    "addr:street":"Plaza Dr",
    "iso:country":"US",
    "sg:address":"163 Plaza Dr",
    "sg:city":"Vallejo",
    "sg:classifiers":[
        {
            "category":"Restaurant",
            "type":"Food & Drink"
        }
    ],
    "sg:phone":"+1 707 557 6100",
    "sg:postcode":"94591",
    "sg:province":"CA",
    "sg:tags":[
        "italian"
    ],
    "wof:name":"Pasta Pomodoro",
    "wof:placetype":"venue"
},
  "geometry": {"coordinates":[-122.21676100000001,38.132901],"type":"Point"}
}