{
  "type": "Feature",
  "properties": {
    "iso:country":"US",
    "sg:address":"2204 E Foothill Blvd",
    "sg:city":"Pasadena",
    "sg:classifiers":[
        {
            "category":"Retail",
            "subcategory":"Veterinary Services",
            "type":"Services"
        },
        {
            "category":"Retail",
            "subcategory":"Pet Boarding",
            "type":"Services"
        }
    ],
    "sg:phone":"+1 626 792 1187",
    "sg:postcode":"91107",
    "sg:province":"CA",
    "sg:tags":[
        "veterinarian",
        "boarding/pet",
        "sitting"
    ],
    "wof:name":"Bell Robert E DVM",
    "wof:placetype":"venue"
},
  "geometry": {"coordinates":[-118.105003,34.149502],"type":"Point"}
}