{
  "type": "Feature",
  "properties": {
    "addr:full":"26490 Jefferson Ave Murrieta CA 92562",
    "addr:housenumber":"26490",
    "addr:postcode":"92562",
    "addr:street":"Jefferson Ave",
    "iso:country":"US",
    "sg:address":"26490 Jefferson Ave",
    "sg:city":"Murrieta",
    "sg:classifiers":[
        {
            "category":"Education",
            "subcategory":"Dance Studio",
            "type":"Public Place"
        }
    ],
    "sg:phone":"+1 951 304 1015",
    "sg:postcode":"92562",
    "sg:province":"CA",
    "sg:tags":[
        "instruction",
        "dancing"
    ],
    "wof:name":"Claddagh Dance Co",
    "wof:placetype":"venue"
},
  "geometry": {"coordinates":[-117.17816000000001,33.533288],"type":"Point"}
}