{
  "type": "Feature",
  "properties": {
    "addr:full":"5155 W Rosecrans Ave Hawthorne CA 90250",
    "addr:housenumber":"5155",
    "addr:postcode":"90250",
    "addr:street":"W Rosecrans Ave",
    "iso:country":"US",
    "sg:address":"5155 W Rosecrans Ave",
    "sg:city":"Hawthorne",
    "sg:classifiers":[
        {
            "category":"Professional",
            "type":"Services"
        }
    ],
    "sg:phone":"+1 310 978 4924",
    "sg:postcode":"90250",
    "sg:province":"CA",
    "sg:tags":[
        "establishment"
    ],
    "wof:name":"Synapse Inc",
    "wof:placetype":"venue"
},
  "geometry": {"coordinates":[-118.370227,33.901829],"type":"Point"}
}