{
  "type": "Feature",
  "properties": {
    "addr:full":"47673 Butterfly Ln Squaw Valley CA 93675",
    "addr:postcode":"47673;93675",
    "addr:street":"Butterfly Ln",
    "iso:country":"US",
    "sg:address":"47673 Butterfly Ln",
    "sg:city":"Squaw Valley",
    "sg:classifiers":[
        {
            "category":"Retail",
            "subcategory":"Laundry & Dry Cleaning",
            "type":"Services"
        }
    ],
    "sg:phone":"+1 559 338 2675",
    "sg:postcode":"93675",
    "sg:province":"CA",
    "sg:tags":[
        "cleaners",
        "rug",
        "carpet"
    ],
    "sg:website":"www.spaceagespotter.com",
    "wof:name":"LWS Svc",
    "wof:placetype":"venue"
},
  "geometry": {"coordinates":[-119.142966,36.690021],"type":"Point"}
}