{
  "type": "Feature",
  "properties": {
    "addr:full":"3564 Enterprise Dr Anaheim CA 92807",
    "addr:housenumber":"3564",
    "addr:postcode":"92807",
    "addr:street":"Enterprise Dr",
    "iso:country":"US",
    "sg:address":"3564 Enterprise Dr",
    "sg:city":"Anaheim",
    "sg:classifiers":[
        {
            "category":"Manufacturing",
            "subcategory":"Tools & Machinery",
            "type":"Manufacturing & Wholesale Goods"
        }
    ],
    "sg:phone":"+1 714 764 0060",
    "sg:postcode":"92807",
    "sg:province":"CA",
    "sg:tags":[
        "machine",
        "copying",
        "supply"
    ],
    "sg:website":"www.ecopyamerica.com",
    "wof:name":"Copy America",
    "wof:placetype":"venue"
},
  "geometry": {"coordinates":[-117.840639,33.860124],"type":"Point"}
}