{
  "type": "Feature",
  "properties": {
    "iso:country":"US",
    "sg:address":"2500 W. Lincoln Dr. #1",
    "sg:city":"Anaheim",
    "sg:classifiers":[
        {
            "category":"Donuts",
            "subcategory":"None",
            "type":"Food & Drink"
        }
    ],
    "sg:postcode":"92801",
    "sg:province":"CA",
    "wof:name":"LUV'IN \u00a0Donuts",
    "wof:placetype":"venue"
},
  "geometry": {"coordinates":[-117.972979,33.832182],"type":"Point"}
}