{
  "type": "Feature",
  "properties": {
    "iso:country":"US",
    "sg:address":"1125 Colusa Ave",
    "sg:city":"Yuba City",
    "sg:classifiers":[
        {
            "category":"Shopping",
            "subcategory":"Clothing, Apparel, & Fashions",
            "type":"Retail Goods"
        }
    ],
    "sg:phone":"+1 530 755 2161",
    "sg:postcode":"95991",
    "sg:province":"CA",
    "wof:name":"Rave",
    "wof:placetype":"venue"
},
  "geometry": {"coordinates":[-121.633488,39.141832],"type":"Point"}
}