{
  "type": "Feature",
  "properties": {
    "iso:country":"US",
    "sg:address":"9531 Milliken Ave",
    "sg:city":"Rancho Cucamonga",
    "sg:classifiers":[
        {
            "category":"Insurance",
            "subcategory":"Insurance Agent",
            "type":"Services"
        }
    ],
    "sg:phone":"+1 909 481 3600",
    "sg:postcode":"91730",
    "sg:province":"CA",
    "sg:tags":[
        "claim"
    ],
    "wof:name":"State Farm Insurance",
    "wof:placetype":"venue"
},
  "geometry": {"coordinates":[-117.558212,34.078297],"type":"Point"}
}