{
  "type": "Feature",
  "properties": {
    "addr:full":"162 N 2nd Ave Oakdale CA 95361",
    "addr:housenumber":"162",
    "addr:postcode":"95361",
    "addr:street":"N 2Nd Ave",
    "iso:country":"US",
    "sg:address":"162 N 2nd Ave",
    "sg:city":"Oakdale",
    "sg:classifiers":[
        {
            "category":"Organizations",
            "subcategory":"Religious Organization",
            "type":"Services"
        }
    ],
    "sg:phone":"+1 209 847 2363",
    "sg:postcode":"95361",
    "sg:province":"CA",
    "sg:tags":[
        "church"
    ],
    "wof:name":"First Baptist Church",
    "wof:placetype":"venue"
},
  "geometry": {"coordinates":[-120.849183,37.766322],"type":"Point"}
}