{
  "type": "Feature",
  "properties": {
    "iso:country":"US",
    "sg:address":"9777 Wilshire Blvd",
    "sg:city":"Beverly Hills",
    "sg:classifiers":[
        {
            "category":"Professional",
            "subcategory":"Business Services",
            "type":"Services"
        }
    ],
    "sg:phone":"+1 310 276 1405",
    "sg:postcode":"90212",
    "sg:province":"CA",
    "wof:name":"Cohen-Roth Elana",
    "wof:placetype":"venue"
},
  "geometry": {"coordinates":[-118.409389,34.067154],"type":"Point"}
}