{
  "type": "Feature",
  "properties": {
    "iso:country":"US",
    "sg:address":"1900 W Lambert Rd",
    "sg:city":"La Habra",
    "sg:classifiers":[
        {
            "category":"Real Estate",
            "subcategory":"Real Estate Agent",
            "type":"Services"
        }
    ],
    "sg:phone":"+1 562 266 3105",
    "sg:postcode":"90631",
    "sg:province":"CA",
    "wof:name":"New Town Realtor",
    "wof:placetype":"venue"
},
  "geometry": {"coordinates":[-117.967802,33.92453],"type":"Point"}
}