{
  "type": "Feature",
  "properties": {
    "addr:full":"2220 Fern St San Diego CA 92104",
    "addr:housenumber":"2220",
    "addr:postcode":"92104",
    "addr:street":"Fern St",
    "iso:country":"US",
    "sg:address":"2220 Fern St",
    "sg:city":"San Diego",
    "sg:classifiers":[
        {
            "category":"Shopping",
            "subcategory":"Bicycles & Sporting Goods",
            "type":"Retail Goods"
        }
    ],
    "sg:phone":"+1 619 819 8569",
    "sg:postcode":"92104",
    "sg:province":"CA",
    "sg:tags":[
        "bike"
    ],
    "sg:website":"www.velocult.com",
    "wof:name":"Velo Cult",
    "wof:placetype":"venue"
},
  "geometry": {"coordinates":[-117.129589,32.72914],"type":"Point"}
}