{
  "type": "Feature",
  "properties": {
    "iso:country":"US",
    "sg:address":"6351 Owensmouth Ave Ste 104",
    "sg:city":"Woodland Hills",
    "sg:classifiers":[
        {
            "category":"Professional",
            "subcategory":"Accounting & Tax Preparation",
            "type":"Services"
        }
    ],
    "sg:phone":"+1 818 887 1040",
    "sg:postcode":"91367",
    "sg:province":"CA",
    "sg:tags":[
        "accountant"
    ],
    "wof:name":"Minovitz Marc A CPA",
    "wof:placetype":"venue"
},
  "geometry": {"coordinates":[-118.601997,34.185799],"type":"Point"}
}