{
  "type": "Feature",
  "properties": {
    "addr:full":"434 S Grand Avenue Los Angeles CA 90071",
    "addr:housenumber":"434",
    "addr:postcode":"90071",
    "addr:street":"S Grand Avenue",
    "iso:country":"US",
    "sg:address":"434 S Grand Avenue",
    "sg:city":"Los Angeles",
    "sg:classifiers":[
        {
            "category":"Landmark",
            "subcategory":"Tourist Information",
            "type":"Public Place"
        }
    ],
    "sg:phone":"+1 323 766 0500",
    "sg:postcode":"90071",
    "sg:province":"CA",
    "sg:tags":[
        "tour"
    ],
    "wof:name":"Dong Sin Tour",
    "wof:placetype":"venue"
},
  "geometry": {"coordinates":[-118.253203,34.051146],"type":"Point"}
}