{
  "type": "Feature",
  "properties": {
    "iso:country":"US",
    "sg:address":"323 E Matilija St",
    "sg:city":"Ojai",
    "sg:classifiers":[
        {
            "category":"Shopping",
            "subcategory":"Clothing, Apparel, & Fashions",
            "type":"Retail Goods"
        }
    ],
    "sg:phone":"+1 805 646 0457",
    "sg:postcode":"93023",
    "sg:province":"CA",
    "wof:name":"Bird In Paradise",
    "wof:placetype":"venue"
},
  "geometry": {"coordinates":[-119.245128,34.448737],"type":"Point"}
}