{
  "type": "Feature",
  "properties": {
    "addr:full":"5121 Stockdale Hwy Bakersfield CA 93309",
    "addr:housenumber":"5121",
    "addr:postcode":"93309",
    "addr:street":"Stockdale Hwy",
    "iso:country":"US",
    "sg:address":"5121 Stockdale Hwy",
    "sg:city":"Bakersfield",
    "sg:classifiers":[
        {
            "category":"Government",
            "subcategory":"Office",
            "type":"Public Place"
        }
    ],
    "sg:phone":"+1 661 325 4473",
    "sg:postcode":"93309",
    "sg:province":"CA",
    "sg:tags":[
        "program",
        "administrative"
    ],
    "wof:name":"Career Services Center",
    "wof:placetype":"venue"
},
  "geometry": {"coordinates":[-119.060405,35.35416],"type":"Point"}
}