{
  "type": "Feature",
  "properties": {
    "iso:country":"US",
    "sg:address":"45974 National Trails Hwy",
    "sg:city":"Newberry Springs",
    "sg:classifiers":[
        {
            "category":"Organizations",
            "subcategory":"Professional Association",
            "type":"Services"
        }
    ],
    "sg:phone":"+1 760 257 1072",
    "sg:postcode":"92365",
    "sg:province":"CA",
    "sg:tags":[
        "chambers",
        "commerce"
    ],
    "wof:name":"Newberry Springs Chamber",
    "wof:placetype":"venue"
},
  "geometry": {"coordinates":[-116.655145,34.821596],"type":"Point"}
}