{
  "type": "Feature",
  "properties": {
    "addr:full":"101 Central Ave Vallejo CA 94590",
    "addr:housenumber":"101",
    "addr:postcode":"94590",
    "addr:street":"Central Ave",
    "iso:country":"US",
    "sg:address":"101 Central Ave",
    "sg:city":"Vallejo",
    "sg:classifiers":[
        {
            "category":"Building & Trades",
            "subcategory":"Construction",
            "type":"Services"
        }
    ],
    "sg:phone":"+1 707 864 2803",
    "sg:postcode":"94590",
    "sg:province":"CA",
    "sg:tags":[
        "contractor",
        "laying",
        "floor",
        "covering"
    ],
    "wof:name":"G Baca Flooring",
    "wof:placetype":"venue"
},
  "geometry": {"coordinates":[-122.23970799999999,38.099989],"type":"Point"}
}