{
  "type": "Feature",
  "properties": {
    "iso:country":"US",
    "sg:address":"16008 Gale Ave",
    "sg:city":"Hacienda Heights",
    "sg:classifiers":[
        {
            "category":"Personal",
            "subcategory":"Beauty Salon",
            "type":"Services"
        }
    ],
    "sg:phone":"+1 626 330 5364",
    "sg:postcode":"91745",
    "sg:province":"CA",
    "wof:name":"Carmen's Hair & Skin Care",
    "wof:placetype":"venue"
},
  "geometry": {"coordinates":[-117.957105,34.008951],"type":"Point"}
}