{
  "type": "Feature",
  "properties": {
    "iso:country":"US",
    "sg:address":"5610 Elvas Ave",
    "sg:city":"Sacramento",
    "sg:classifiers":[
        {
            "category":"Real Estate",
            "subcategory":"Real Estate Agent",
            "type":"Services"
        }
    ],
    "sg:phone":"+1 916 456 1235",
    "sg:postcode":"95819",
    "sg:province":"CA",
    "wof:name":"Witt's Remodeling Building",
    "wof:placetype":"venue"
},
  "geometry": {"coordinates":[-121.43331999999999,38.570413],"type":"Point"}
}