{
  "type": "Feature",
  "properties": {
    "addr:full":"150 N Robertson Blvd Ste 200 Beverly Hills CA 90211",
    "addr:housenumber":"150",
    "addr:postcode":"90211",
    "addr:street":"N Robertson Blvd Ste 200;Hills Ca",
    "iso:country":"US",
    "sg:address":"150 N Robertson Blvd Ste 200",
    "sg:city":"Beverly Hills",
    "sg:classifiers":[
        {
            "category":"Health Services",
            "subcategory":"Doctor",
            "type":"Services"
        }
    ],
    "sg:phone":"+1 310 652 9347",
    "sg:postcode":"90211",
    "sg:province":"CA",
    "sg:tags":[
        "obstetrician",
        "gynecologist"
    ],
    "sg:website":"www.drbanooni.yourmd.com",
    "wof:name":"Peyman Banooni, MD",
    "wof:placetype":"venue"
},
  "geometry": {"coordinates":[-118.383695,34.068216],"type":"Point"}
}