{
  "type": "Feature",
  "properties": {
    "addr:full":"1525 Lyle Ln Paso Robles CA 93446",
    "addr:housenumber":"1525",
    "addr:postcode":"93446",
    "addr:street":"Lyle Ln",
    "iso:country":"US",
    "sg:address":"1525 Lyle Ln",
    "sg:city":"Paso Robles",
    "sg:classifiers":[
        {
            "category":"Personal",
            "subcategory":"Beauty Salon",
            "type":"Services"
        }
    ],
    "sg:phone":"+1 805 712 5288",
    "sg:postcode":"93446",
    "sg:province":"CA",
    "wof:name":"Lauri M O'Neill",
    "wof:placetype":"venue"
},
  "geometry": {"coordinates":[-120.667945,35.636642],"type":"Point"}
}