{
  "type": "Feature",
  "properties": {
    "addr:full":"425 N Kaweah Ave Exeter CA 93221",
    "addr:housenumber":"425",
    "addr:postcode":"93221",
    "addr:street":"N Kaweah Ave",
    "iso:country":"US",
    "sg:address":"425 N Kaweah Ave",
    "sg:city":"Exeter",
    "sg:classifiers":[
        {
            "category":"Retail",
            "subcategory":"Funeral Services",
            "type":"Services"
        }
    ],
    "sg:phone":"+1 559 592 5161",
    "sg:postcode":"93221",
    "sg:province":"CA",
    "sg:tags":[
        "director"
    ],
    "wof:name":"Evans Miller Exeter Funeral",
    "wof:placetype":"venue"
},
  "geometry": {"coordinates":[-119.13561300000001,36.303996],"type":"Point"}
}