{
  "type": "Feature",
  "properties": {
    "addr:full":"1876 Country Club Blvd Stockton CA 95204",
    "addr:housenumber":"1876",
    "addr:postcode":"95204",
    "addr:street":"Country Club Blvd",
    "iso:country":"US",
    "sg:address":"1876 Country Club Blvd",
    "sg:city":"Stockton",
    "sg:classifiers":[
        {
            "category":"Building & Trades",
            "subcategory":"Landscaping Services",
            "type":"Services"
        }
    ],
    "sg:phone":"+1 209 942 0373",
    "sg:postcode":"95204",
    "sg:province":"CA",
    "sg:tags":[
        "landscape",
        "contractor"
    ],
    "wof:name":"Avant Garden",
    "wof:placetype":"venue"
},
  "geometry": {"coordinates":[-121.32213400000001,37.967678],"type":"Point"}
}