{
  "type": "Feature",
  "properties": {
    "addr:full":"16817 Hobart Blvd Gardena CA 90247",
    "addr:housenumber":"16817",
    "addr:postcode":"90247",
    "addr:street":"Hobart Blvd",
    "iso:country":"US",
    "sg:address":"16817 Hobart Blvd",
    "sg:city":"Gardena",
    "sg:classifiers":[
        {
            "category":"Building & Trades",
            "subcategory":"Construction",
            "type":"Services"
        }
    ],
    "sg:phone":"+1 310 527 2080",
    "sg:postcode":"90247",
    "sg:province":"CA",
    "sg:tags":[
        "nonresidential"
    ],
    "wof:name":"T & P Construction Inc",
    "wof:placetype":"venue"
},
  "geometry": {"coordinates":[-118.30801099999999,33.877545],"type":"Point"}
}