{
  "type": "Feature",
  "properties": {
    "addr:full":"500 Maitland Dr Alameda CA 94502",
    "addr:housenumber":"500",
    "addr:postcode":"94502",
    "addr:street":"Maitland Dr",
    "iso:country":"US",
    "sg:address":"500 Maitland Dr",
    "sg:city":"Alameda",
    "sg:classifiers":[
        {
            "category":"Retail",
            "subcategory":"Storage",
            "type":"Services"
        }
    ],
    "sg:phone":"+1 510 769 5222",
    "sg:postcode":"94502",
    "sg:province":"CA",
    "sg:tags":[
        "self"
    ],
    "wof:name":"Harbor Bay Rv & Self Storage",
    "wof:placetype":"venue"
},
  "geometry": {"coordinates":[-122.230003,37.728199],"type":"Point"}
}