{
  "type": "Feature",
  "properties": {
    "addr:full":"5375 Avenida Encinas Ste C Carlsbad CA 92008",
    "addr:housenumber":"5375",
    "addr:postcode":"92008",
    "addr:street":"Avenida Encinas Ste C",
    "iso:country":"US",
    "sg:address":"5375 Avenida Encinas Ste C",
    "sg:city":"Carlsbad",
    "sg:classifiers":[
        {
            "category":"Wholesale",
            "subcategory":"Medical Equipment & Supplies",
            "type":"Manufacturing & Wholesale Goods"
        },
        {
            "category":"Health Services",
            "subcategory":"Dentist",
            "type":"Services"
        }
    ],
    "sg:phone":"+1 760 602 0521",
    "sg:postcode":"92008",
    "sg:province":"CA",
    "sg:tags":[
        "dental",
        "refinishing",
        "equipment-repairing"
    ],
    "sg:website":"http://www.hayeshandpiece.com",
    "wof:name":"Hayes Handpiece Franchises Inc",
    "wof:placetype":"venue"
},
  "geometry": {"coordinates":[-117.32583099999999,33.127527],"type":"Point"}
}