{
  "type": "Feature",
  "properties": {
    "iso:country":"US",
    "sg:address":"6015 Park Dr",
    "sg:city":"Wrightwood",
    "sg:classifiers":[
        {
            "category":"Shopping",
            "subcategory":"Gifts & Souvenirs",
            "type":"Retail Goods"
        }
    ],
    "sg:phone":"+1 760 249 5444",
    "sg:postcode":"92397",
    "sg:province":"CA",
    "sg:tags":[
        "shop"
    ],
    "wof:name":"Silk Penguin",
    "wof:placetype":"venue"
},
  "geometry": {"coordinates":[-117.633755,34.359833],"type":"Point"}
}