{
  "type": "Feature",
  "properties": {
    "iso:country":"US",
    "sg:address":"2900 Standiford Ave",
    "sg:city":"Modesto",
    "sg:classifiers":[
        {
            "category":"Ice Cream",
            "type":"Food & Drink"
        }
    ],
    "sg:menulink":"http://www.allmenus.com/ca/modesto/242449-baskin-robbins/menu/",
    "sg:phone":"+1 209 544 8686",
    "sg:postcode":"95350",
    "sg:province":"CA",
    "sg:tags":[
        "american"
    ],
    "wof:name":"Baskin-Robbins",
    "wof:placetype":"venue"
},
  "geometry": {"coordinates":[-121.04996,37.684449],"type":"Point"}
}