{
  "type": "Feature",
  "properties": {
    "iso:country":"US",
    "sg:address":"17229 Newhope St",
    "sg:city":"Fountain Valley",
    "sg:classifiers":[
        {
            "category":"Building & Trades",
            "subcategory":"Construction",
            "type":"Services"
        }
    ],
    "sg:phone":"+1 714 557 0542",
    "sg:postcode":"92708",
    "sg:province":"CA",
    "sg:tags":[
        "contractor"
    ],
    "wof:name":"J & A Glass",
    "wof:placetype":"venue"
},
  "geometry": {"coordinates":[-117.92846,33.712516],"type":"Point"}
}