{
  "type": "Feature",
  "properties": {
    "iso:country":"US",
    "sg:address":"243 Vernon St",
    "sg:city":"San Francisco",
    "sg:classifiers":[
        {
            "category":"Wholesale",
            "subcategory":"Office Equipment",
            "type":"Manufacturing & Wholesale Goods"
        }
    ],
    "sg:phone":"+1 415 587 9301",
    "sg:postcode":"94132",
    "sg:province":"CA",
    "sg:tags":[
        "credit",
        "system",
        "card"
    ],
    "wof:name":"First Bank Card Merchant Svc",
    "wof:placetype":"venue"
},
  "geometry": {"coordinates":[-122.46810499999999,37.717129],"type":"Point"}
}