{
  "type": "Feature",
  "properties": {
    "iso:country":"US",
    "sg:address":"800 Charcot Ave",
    "sg:city":"San Jose",
    "sg:classifiers":[
        {
            "category":"Professional",
            "type":"Services"
        },
        {
            "category":"Shopping",
            "subcategory":"Computers & Home Electronics",
            "type":"Retail Goods"
        }
    ],
    "sg:phone":"+1 408 433 9383",
    "sg:postcode":"95131",
    "sg:province":"CA",
    "sg:tags":[
        "software"
    ],
    "wof:name":"Csoft Corp",
    "wof:placetype":"venue"
},
  "geometry": {"coordinates":[-121.905883,37.386966],"type":"Point"}
}