{
  "type": "Feature",
  "properties": {
    "addr:full":"4250 Atlantic Ave Long Beach CA 90807",
    "addr:housenumber":"4250",
    "addr:postcode":"90807",
    "addr:street":"Atlantic Ave",
    "iso:country":"US",
    "sg:address":"4250 Atlantic Ave",
    "sg:city":"Long Beach",
    "sg:classifiers":[
        {
            "category":"Shopping",
            "subcategory":"Hobbies, Toys, & Games",
            "type":"Retail Goods"
        }
    ],
    "sg:phone":"+1 562 426 1949",
    "sg:postcode":"90807",
    "sg:province":"CA",
    "sg:tags":[
        "craft",
        "supply"
    ],
    "wof:name":"Betty Bear Crafts & Scrapbook",
    "wof:placetype":"venue"
},
  "geometry": {"coordinates":[-118.184923,33.833504],"type":"Point"}
}