{
  "type": "Feature",
  "properties": {
    "addr:full":"3957 Pierce St Riverside CA 92505",
    "addr:housenumber":"3957",
    "addr:postcode":"92505",
    "addr:street":"Pierce St",
    "iso:country":"US",
    "sg:address":"3957 Pierce St",
    "sg:city":"Riverside",
    "sg:classifiers":[
        {
            "category":"Real Estate",
            "subcategory":"Real Estate Operator",
            "type":"Services"
        }
    ],
    "sg:phone":"+1 951 354 2558",
    "sg:postcode":"92505",
    "sg:province":"CA",
    "sg:tags":[
        "building",
        "apartment"
    ],
    "wof:name":"American Express",
    "wof:placetype":"venue"
},
  "geometry": {"coordinates":[-117.49345099999999,33.898098],"type":"Point"}
}