{
  "type": "Feature",
  "properties": {
    "iso:country":"US",
    "sg:address":"170 2nd St",
    "sg:city":"Watsonville",
    "sg:classifiers":[
        {
            "category":"Building & Trades",
            "subcategory":"Construction",
            "type":"Services"
        }
    ],
    "sg:phone":"+1 831 688 6835",
    "sg:postcode":"95076",
    "sg:province":"CA",
    "sg:tags":[
        "roofing",
        "contractor"
    ],
    "wof:name":"Central Roofing Co",
    "wof:placetype":"venue"
},
  "geometry": {"coordinates":[-121.759306,36.906704],"type":"Point"}
}