{
  "type": "Feature",
  "properties": {
    "addr:full":"72534 Edgehill Dr Palm Desert CA 92260",
    "addr:postcode":"72534;ca 92260",
    "addr:street":"Edgehill Dr",
    "iso:country":"US",
    "sg:address":"72534 Edgehill Dr",
    "sg:city":"Palm Desert",
    "sg:classifiers":[
        {
            "category":"Professional",
            "subcategory":"Art Services",
            "type":"Services"
        }
    ],
    "sg:phone":"+1 760 424 6974",
    "sg:postcode":"92260",
    "sg:province":"CA",
    "sg:tags":[
        "graphic",
        "designer"
    ],
    "wof:name":"Miranda Design & Marketing",
    "wof:placetype":"venue"
},
  "geometry": {"coordinates":[-116.397717,33.706921],"type":"Point"}
}