{
  "type": "Feature",
  "properties": {
    "iso:country":"US",
    "sg:address":"3840 Valley Centre Dr",
    "sg:city":"San Diego",
    "sg:classifiers":[
        {
            "category":"Shopping",
            "subcategory":"Shoes",
            "type":"Retail Goods"
        }
    ],
    "sg:phone":"+1 858 259 2570",
    "sg:postcode":"92130",
    "sg:province":"CA",
    "sg:tags":[
        "store"
    ],
    "wof:name":"Shoe Line",
    "wof:placetype":"venue"
},
  "geometry": {"coordinates":[-117.231551,32.939558],"type":"Point"}
}