{
  "type": "Feature",
  "properties": {
    "addr:full":"3427 Railroad Ave Ste 10 Ceres CA 95307",
    "addr:housenumber":"3427",
    "addr:postcode":"95307",
    "addr:street":"Railroad Ave Ste 10",
    "iso:country":"US",
    "sg:address":"3427 Railroad Ave Ste 10",
    "sg:city":"Ceres",
    "sg:classifiers":[
        {
            "category":"Autos & Motor Vehicles",
            "subcategory":"Automobile Sales",
            "type":"Retail Goods"
        }
    ],
    "sg:phone":"+1 209 537 6021",
    "sg:postcode":"95307",
    "sg:province":"CA",
    "sg:tags":[
        "limo"
    ],
    "sg:website":"www.hobolimousine.com",
    "wof:name":"Hobo Limousine Service",
    "wof:placetype":"venue"
},
  "geometry": {"coordinates":[-120.95293100000001,37.587032],"type":"Point"}
}