{
  "type": "Feature",
  "properties": {
    "addr:full":"1702 Meridian Ave San Jose CA 95125",
    "addr:housenumber":"1702",
    "addr:postcode":"95125",
    "addr:street":"Meridian Ave",
    "iso:country":"US",
    "sg:address":"1702 Meridian Ave",
    "sg:city":"San Jose",
    "sg:classifiers":[
        {
            "category":"Professional",
            "subcategory":"Advertising",
            "type":"Services"
        }
    ],
    "sg:phone":"+1 408 265 5005",
    "sg:postcode":"95125",
    "sg:province":"CA",
    "sg:tags":[
        "mailing",
        "shipping"
    ],
    "wof:name":"UPS Store",
    "wof:placetype":"venue"
},
  "geometry": {"coordinates":[-121.91351299999999,37.291622],"type":"Point"}
}