{
  "type": "Feature",
  "properties": {
    "iso:country":"US",
    "sg:address":"505 W Olive Ave",
    "sg:city":"Sunnyvale",
    "sg:classifiers":[
        {
            "category":"Government",
            "subcategory":"Office",
            "type":"Public Place"
        }
    ],
    "sg:phone":"+1 408 730 7232",
    "sg:postcode":"94086",
    "sg:province":"CA",
    "sg:tags":[
        "employment",
        "village"
    ],
    "wof:name":"Employment Development CA Dept",
    "wof:placetype":"venue"
},
  "geometry": {"coordinates":[-122.039311,37.371292],"type":"Point"}
}