{
  "type": "Feature",
  "properties": {
    "addr:full":"18873 Whitney Pl Rowland Heights CA 91748",
    "addr:housenumber":"18873",
    "addr:postcode":"91748",
    "addr:street":"Whitney Pl",
    "iso:country":"US",
    "sg:address":"18873 Whitney Pl",
    "sg:city":"Rowland Heights",
    "sg:classifiers":[
        {
            "category":"Wholesale",
            "subcategory":"Non-durable Goods",
            "type":"Manufacturing & Wholesale Goods"
        }
    ],
    "sg:phone":"+1 626 964 3608",
    "sg:postcode":"91748",
    "sg:province":"CA",
    "wof:name":"Xin Wang America Trading Inc",
    "wof:placetype":"venue"
},
  "geometry": {"coordinates":[-117.889987,33.97186],"type":"Point"}
}