{
  "type": "Feature",
  "properties": {
    "iso:country":"US",
    "sg:address":"4442 Lakewood Blvd",
    "sg:city":"Long Beach",
    "sg:classifiers":[
        {
            "category":"Freight",
            "type":"Transportation"
        }
    ],
    "sg:phone":"+1 562 377 5521",
    "sg:postcode":"90808",
    "sg:province":"CA",
    "sg:tags":[
        "operator",
        "local",
        "trucking"
    ],
    "wof:name":"Whirlwind Delivery Service",
    "wof:placetype":"venue"
},
  "geometry": {"coordinates":[-118.142438,33.839544],"type":"Point"}
}