{
  "type": "Feature",
  "properties": {
    "addr:full":"6101 Quail Valley Ct Riverside CA 92507",
    "addr:housenumber":"6101",
    "addr:postcode":"92507",
    "addr:street":"Quail Valley Ct",
    "iso:country":"US",
    "sg:address":"6101 Quail Valley Ct",
    "sg:city":"Riverside",
    "sg:classifiers":[
        {
            "category":"Building & Trades",
            "subcategory":"Construction",
            "type":"Services"
        }
    ],
    "sg:phone":"+1 951 543 8901",
    "sg:postcode":"92507",
    "sg:province":"CA",
    "sg:tags":[
        "contractor"
    ],
    "wof:name":"Aquatic Dimensions",
    "wof:placetype":"venue"
},
  "geometry": {"coordinates":[-117.295311,33.939492],"type":"Point"}
}