{
  "type": "Feature",
  "properties": {
    "addr:full":"8221 Econ Ct Fair Oaks CA 95628",
    "addr:housenumber":"8221",
    "addr:postcode":"95628",
    "addr:street":"Econ Ct",
    "iso:country":"US",
    "sg:address":"8221 Econ Ct",
    "sg:city":"Fair Oaks",
    "sg:classifiers":[
        {
            "category":"Professional",
            "subcategory":"Management & Consulting",
            "type":"Services"
        }
    ],
    "sg:phone":"+1 916 966 8834",
    "sg:postcode":"95628",
    "sg:province":"CA",
    "sg:tags":[
        "consultant",
        "construction"
    ],
    "wof:name":"Facilities Design & Constr Svc",
    "wof:placetype":"venue"
},
  "geometry": {"coordinates":[-121.256843,38.671824],"type":"Point"}
}