{
  "type": "Feature",
  "properties": {
    "iso:country":"US",
    "sg:address":"79395 US Hwy 111",
    "sg:city":"La Quinta",
    "sg:classifiers":[
        {
            "category":"Shopping",
            "subcategory":"Department Store",
            "type":"Retail Goods"
        }
    ],
    "sg:phone":"+1 760 777 4684",
    "sg:postcode":"92253",
    "sg:province":"CA",
    "wof:name":"Marshalls",
    "wof:placetype":"venue"
},
  "geometry": {"coordinates":[-116.277859,33.707296],"type":"Point"}
}