{
  "type": "Feature",
  "properties": {
    "addr:full":"6990 Watt Avenue North Highlands CA 95660",
    "addr:housenumber":"6990",
    "addr:postcode":"95660",
    "addr:street":"Watt Avenue",
    "iso:country":"US",
    "sg:address":"6990 Watt Avenue",
    "sg:city":"North Highlands",
    "sg:classifiers":[
        {
            "category":"Retail",
            "subcategory":"Auto Repair",
            "type":"Services"
        }
    ],
    "sg:phone":"+1 916 332 1681",
    "sg:postcode":"95660",
    "sg:province":"CA",
    "wof:name":"Econo Lube & Tune & Brakes No 59",
    "wof:placetype":"venue"
},
  "geometry": {"coordinates":[-121.382617,38.69294],"type":"Point"}
}