{
  "type": "Feature",
  "properties": {
    "iso:country":"US",
    "sg:address":"3604 4th Avenue Ste 2",
    "sg:city":"San Diego",
    "sg:classifiers":[
        {
            "category":"Professional",
            "subcategory":"Accounting & Tax Preparation",
            "type":"Services"
        },
        {
            "category":"Banks & Credit Unions",
            "subcategory":"Financial Services",
            "type":"Services"
        }
    ],
    "sg:phone":"+1 619 291 0426",
    "sg:postcode":"92103",
    "sg:province":"CA",
    "sg:tags":[
        "accountant",
        "advising"
    ],
    "sg:website":"www.independentbookkeepingservic...",
    "wof:name":"Independent Bookkeeping Service",
    "wof:placetype":"venue"
},
  "geometry": {"coordinates":[-117.161823,32.743505],"type":"Point"}
}