{
  "type": "Feature",
  "properties": {
    "addr:full":"466 E Montecito Ave Sierra Madre CA 91024",
    "addr:housenumber":"466",
    "addr:postcode":"91024",
    "addr:street":"E Montecito Ave",
    "iso:country":"US",
    "sg:address":"466 E Montecito Ave",
    "sg:city":"Sierra Madre",
    "sg:classifiers":[
        {
            "category":"Building & Trades",
            "subcategory":"Electrical",
            "type":"Services"
        }
    ],
    "sg:phone":"+1 626 355 3131",
    "sg:postcode":"91024",
    "sg:province":"CA",
    "sg:tags":[
        "electrical",
        "contractor"
    ],
    "wof:name":"Eds Electric",
    "wof:placetype":"venue"
},
  "geometry": {"coordinates":[-118.04307300000001,34.162689],"type":"Point"}
}