{
  "type": "Feature",
  "properties": {
    "iso:country":"US",
    "sg:address":"466 E Montecito Ave",
    "sg:city":"Sierra Madre",
    "sg:classifiers":[
        {
            "category":"Building & Trades",
            "subcategory":"Electrical",
            "type":"Services"
        }
    ],
    "sg:phone":"+1 626 355 3131",
    "sg:postcode":"91024",
    "sg:province":"CA",
    "sg:tags":[
        "electrical",
        "contractor"
    ],
    "wof:name":"Eds Electric",
    "wof:placetype":"venue"
},
  "geometry": {"coordinates":[-118.043073,34.162689],"type":"Point"}
}