{
  "type": "Feature",
  "properties": {
    "addr:full":"198 W Main St El Cajon CA 92020",
    "addr:housenumber":"198",
    "addr:postcode":"92020",
    "addr:street":"W Main St",
    "iso:country":"US",
    "sg:address":"198 W Main St",
    "sg:city":"El Cajon",
    "sg:classifiers":[
        {
            "category":"Shopping",
            "subcategory":"Pharmacy",
            "type":"Retail Goods"
        }
    ],
    "sg:phone":"+1 619 590 0353",
    "sg:postcode":"92020",
    "sg:province":"CA",
    "sg:tags":[
        "drugstore"
    ],
    "wof:name":"Albertson's Food & Drug",
    "wof:placetype":"venue"
},
  "geometry": {"coordinates":[-116.962997,32.795101],"type":"Point"}
}