{
  "type": "Feature",
  "properties": {
    "iso:country":"US",
    "sg:address":"2364 Geary Blvd",
    "sg:city":"San Francisco",
    "sg:classifiers":[
        {
            "category":"Health Services",
            "subcategory":"Dentist",
            "type":"Services"
        }
    ],
    "sg:phone":"+1 415 921 6722",
    "sg:postcode":"94115",
    "sg:province":"CA",
    "wof:name":"Kelso James",
    "wof:placetype":"venue"
},
  "geometry": {"coordinates":[-122.442218,37.783172],"type":"Point"}
}