{
  "type": "Feature",
  "properties": {
    "addr:full":"3705 Coon Hollow Rd Placerville CA 95667",
    "addr:housenumber":"3705",
    "addr:postcode":"95667",
    "addr:street":"Coon Hollow Rd",
    "iso:country":"US",
    "sg:address":"3705 Coon Hollow Rd",
    "sg:city":"Placerville",
    "sg:classifiers":[
        {
            "category":"Building & Trades",
            "subcategory":"Construction",
            "type":"Services"
        }
    ],
    "sg:phone":"+1 530 295 0231",
    "sg:postcode":"95667",
    "sg:province":"CA",
    "sg:tags":[
        "contractor"
    ],
    "wof:name":"Bath Technology",
    "wof:placetype":"venue"
},
  "geometry": {"coordinates":[-120.80556199999999,38.713281],"type":"Point"}
}