{
  "type": "Feature",
  "properties": {
    "addr:full":"6985 San Luis Ave Atascadero CA 93422",
    "addr:housenumber":"6985",
    "addr:postcode":"93422",
    "addr:street":"San Luis Ave",
    "iso:country":"US",
    "sg:address":"6985 San Luis Ave",
    "sg:city":"Atascadero",
    "sg:classifiers":[
        {
            "category":"Food & Beverages",
            "subcategory":"Specialty",
            "type":"Retail Goods"
        }
    ],
    "sg:phone":"+1 805 466 3202",
    "sg:postcode":"93422",
    "sg:province":"CA",
    "sg:tags":[
        "health",
        "diet"
    ],
    "wof:name":"Harvest Health Foods",
    "wof:placetype":"venue"
},
  "geometry": {"coordinates":[-120.659322,35.479562],"type":"Point"}
}