{
  "type": "Feature",
  "properties": {
    "iso:country":"US",
    "sg:address":"332 Vernon Ave",
    "sg:city":"Venice",
    "sg:classifiers":[
        {
            "category":"Manufacturing",
            "subcategory":"Retail Goods",
            "type":"Manufacturing & Wholesale Goods"
        }
    ],
    "sg:phone":"+1 310 450 4581",
    "sg:postcode":"90291",
    "sg:province":"CA",
    "sg:tags":[
        "product",
        "mfg"
    ],
    "wof:name":"Welmark Industries",
    "wof:placetype":"venue"
},
  "geometry": {"coordinates":[-118.473394,33.994878],"type":"Point"}
}