{
  "type": "Feature",
  "properties": {
    "iso:country":"US",
    "sg:address":"4675 MacArthur Ct Ste 550",
    "sg:city":"Newport Beach",
    "sg:classifiers":[
        {
            "category":"Professional",
            "subcategory":"Lawyer & Legal Services",
            "type":"Services"
        }
    ],
    "sg:phone":"+1 949 852 0710",
    "sg:postcode":"92660",
    "sg:province":"CA",
    "wof:name":"Law Offices of Madison Spach",
    "wof:placetype":"venue"
},
  "geometry": {"coordinates":[-117.862999,33.671001],"type":"Point"}
}