{
  "type": "Feature",
  "properties": {
    "addr:full":"1080 S De Anza Blvd San Jose CA 95129",
    "addr:housenumber":"1080",
    "addr:postcode":"95129",
    "addr:street":"S De Anza Blvd",
    "iso:country":"US",
    "sg:address":"1080 S De Anza Blvd",
    "sg:city":"San Jose",
    "sg:classifiers":[
        {
            "category":"Banks & Credit Unions",
            "subcategory":"Financial Services",
            "type":"Services"
        }
    ],
    "sg:phone":"+1 408 252 1783",
    "sg:postcode":"95129",
    "sg:province":"CA",
    "sg:website":"www.hrblock.com/",
    "wof:name":"H & R Block",
    "wof:placetype":"venue"
},
  "geometry": {"coordinates":[-122.031882,37.306842],"type":"Point"}
}