{
  "type": "Feature",
  "properties": {
    "iso:country":"US",
    "sg:address":"848 Stewart Drive",
    "sg:city":"Sunnyvale",
    "sg:classifiers":[
        {
            "category":"Organizations",
            "subcategory":"Religious Organization",
            "type":"Services"
        }
    ],
    "sg:phone":"+1 408 773 8891",
    "sg:postcode":"94085",
    "sg:province":"CA",
    "wof:name":"Sacred Logos Resource Center-Sagos",
    "wof:placetype":"venue"
},
  "geometry": {"coordinates":[-122.011047,37.383865],"type":"Point"}
}