{
  "type": "Feature",
  "properties": {
    "iso:country":"US",
    "sg:address":"31 Mariposa Ln",
    "sg:city":"Orinda",
    "sg:classifiers":[
        {
            "category":"Building & Trades",
            "subcategory":"Construction",
            "type":"Services"
        }
    ],
    "sg:phone":"+1 925 254 3530",
    "sg:postcode":"94563",
    "sg:province":"CA",
    "sg:tags":[
        "house",
        "residential"
    ],
    "wof:name":"Dietkus Construction Co",
    "wof:placetype":"venue"
},
  "geometry": {"coordinates":[-122.197205,37.883549],"type":"Point"}
}