{
  "type": "Feature",
  "properties": {
    "addr:full":"1901 Olympic Blvd Walnut Creek CA 94595",
    "addr:housenumber":"1901",
    "addr:postcode":"94595",
    "addr:street":"Olympic Blvd",
    "iso:country":"US",
    "sg:address":"1901 Olympic Blvd",
    "sg:city":"Walnut Creek",
    "sg:classifiers":[
        {
            "category":"Professional",
            "subcategory":"Lawyer & Legal Services",
            "type":"Services"
        }
    ],
    "sg:phone":"+1 925 944 5000",
    "sg:postcode":"94595",
    "sg:province":"CA",
    "sg:tags":[
        "attorney"
    ],
    "wof:name":"Little & Saputo",
    "wof:placetype":"venue"
},
  "geometry": {"coordinates":[-122.062819,37.895979],"type":"Point"}
}