{
  "type": "Feature",
  "properties": {
    "addr:full":"4309 N Babigian Ave Fresno CA 93722",
    "addr:housenumber":"4309",
    "addr:postcode":"93722",
    "addr:street":"N Babigian Ave",
    "iso:country":"US",
    "sg:address":"4309 N Babigian Ave",
    "sg:city":"Fresno",
    "sg:classifiers":[
        {
            "category":"Building & Trades",
            "subcategory":"Construction",
            "type":"Services"
        }
    ],
    "sg:phone":"+1 559 275 2405",
    "sg:postcode":"93722",
    "sg:province":"CA",
    "sg:tags":[
        "house"
    ],
    "wof:name":"Task Cnstr & Property MGT",
    "wof:placetype":"venue"
},
  "geometry": {"coordinates":[-119.87556499999999,36.798291],"type":"Point"}
}