{
  "type": "Feature",
  "properties": {
    "addr:full":"2919 Linden St Emeryville CA 94608",
    "addr:housenumber":"2919",
    "addr:postcode":"94608",
    "addr:street":"Linden St",
    "iso:country":"US",
    "sg:address":"2919 Linden St",
    "sg:city":"Emeryville",
    "sg:classifiers":[
        {
            "category":"Bars & Pubs",
            "type":"Food & Drink"
        },
        {
            "category":"Bars & Pubs",
            "subcategory":"Lounge",
            "type":"Food & Drink"
        }
    ],
    "sg:phone":"+1 510 834 4308",
    "sg:postcode":"94608",
    "sg:province":"CA",
    "sg:tags":[
        "cocktail"
    ],
    "wof:name":"Lions Den Entertainment",
    "wof:placetype":"venue"
},
  "geometry": {"coordinates":[-122.27972200000001,37.820838],"type":"Point"}
}