{
  "type": "Feature",
  "properties": {
    "iso:country":"US",
    "sg:address":"903 de la Vina St",
    "sg:city":"Santa Barbara",
    "sg:classifiers":[
        {
            "category":"Personal",
            "subcategory":"Beauty Salon",
            "type":"Services"
        }
    ],
    "sg:phone":"+1 805 966 3443",
    "sg:postcode":"93101",
    "sg:province":"CA",
    "wof:name":"Cut Me Some Slack",
    "wof:placetype":"venue"
},
  "geometry": {"coordinates":[-119.704168,34.419267],"type":"Point"}
}