{
  "type": "Feature",
  "properties": {
    "iso:country":"US",
    "sg:address":"872 N Ventura Rd",
    "sg:city":"Port Hueneme",
    "sg:classifiers":[
        {
            "category":"Food & Beverages",
            "subcategory":"Groceries & Convenience Stores",
            "type":"Retail Goods"
        }
    ],
    "sg:phone":"+1 805 483 5506",
    "sg:postcode":"93041",
    "sg:province":"CA",
    "sg:tags":[
        "market"
    ],
    "wof:name":"Tradewinds Market",
    "wof:placetype":"venue"
},
  "geometry": {"coordinates":[-119.195104,34.155333],"type":"Point"}
}