{
  "type": "Feature",
  "properties": {
    "iso:country":"US",
    "sg:address":"7505 N Ashley Ln",
    "sg:city":"Stockton",
    "sg:classifiers":[
        {
            "category":"Farming",
            "subcategory":"Orchard",
            "type":"Manufacturing & Wholesale Goods"
        }
    ],
    "sg:phone":"+1 209 931 0196",
    "sg:postcode":"95212",
    "sg:province":"CA",
    "sg:tags":[
        "fruit",
        "tree"
    ],
    "wof:name":"L Perirano",
    "wof:placetype":"venue"
},
  "geometry": {"coordinates":[-121.224355,38.026446],"type":"Point"}
}