{
  "type": "Feature",
  "properties": {
    "iso:country":"US",
    "sg:address":"2975 N Farmersville Blvd",
    "sg:city":"Farmersville",
    "sg:classifiers":[
        {
            "category":"Utilities",
            "subcategory":"Electric",
            "type":"Services"
        },
        {
            "category":"Utilities",
            "type":"Services"
        }
    ],
    "sg:phone":"+1 559 747 5604",
    "sg:postcode":"93223",
    "sg:province":"CA",
    "sg:website":"http://www.kdwcd.com",
    "wof:name":"Kaweah River Power Authority",
    "wof:placetype":"venue"
},
  "geometry": {"coordinates":[-119.20714,36.324639],"type":"Point"}
}