{
  "type": "Feature",
  "properties": {
    "iso:country":"US",
    "sg:address":"1333 E Foothill Blvd",
    "sg:city":"Upland",
    "sg:classifiers":[
        {
            "category":"Cinema",
            "subcategory":"Movie Rental",
            "type":"Entertainment"
        }
    ],
    "sg:phone":"+1 909 931 4040",
    "sg:postcode":"91786",
    "sg:province":"CA",
    "sg:tags":[
        "video",
        "disc",
        "leasing",
        "tape"
    ],
    "sg:website":"http://www.hollywoodvideo.com",
    "wof:name":"Hollywood Video",
    "wof:placetype":"venue"
},
  "geometry": {"coordinates":[-117.633185,34.10725],"type":"Point"}
}