{
  "type": "Feature",
  "properties": {
    "addr:full":"7495 Donohue Dr Dublin CA 94568",
    "addr:housenumber":"7495",
    "addr:postcode":"94568",
    "addr:street":"Donohue Dr",
    "iso:country":"US",
    "sg:address":"7495 Donohue Dr",
    "sg:city":"Dublin",
    "sg:classifiers":[
        {
            "category":"Real Estate",
            "subcategory":"Real Estate Operator",
            "type":"Services"
        }
    ],
    "sg:phone":"+1 925 803 1813",
    "sg:postcode":"94568",
    "sg:province":"CA",
    "sg:tags":[
        "apartment"
    ],
    "wof:name":"Evan Alan Apartments",
    "wof:placetype":"venue"
},
  "geometry": {"coordinates":[-121.93308,37.709284],"type":"Point"}
}