{
  "type": "Feature",
  "properties": {
    "iso:country":"US",
    "sg:address":"21250 Hawthorne Blvd",
    "sg:city":"Torrance",
    "sg:classifiers":[
        {
            "category":"Real Estate",
            "subcategory":"Real Estate Agent",
            "type":"Services"
        }
    ],
    "sg:phone":"+1 310 792 7488",
    "sg:postcode":"90503",
    "sg:province":"CA",
    "wof:name":"Preferred Real Estate",
    "wof:placetype":"venue"
},
  "geometry": {"coordinates":[-118.35332,33.836367],"type":"Point"}
}