{
  "type": "Feature",
  "properties": {
    "iso:country":"US",
    "sg:address":"13453 Debby St",
    "sg:city":"Van Nuys",
    "sg:classifiers":[
        {
            "category":"Professional",
            "type":"Services"
        }
    ],
    "sg:phone":"+1 818 785 2787",
    "sg:postcode":"91401",
    "sg:province":"CA",
    "sg:tags":[
        "establishment"
    ],
    "wof:name":"Runken G",
    "wof:placetype":"venue"
},
  "geometry": {"coordinates":[-118.424419,34.184054],"type":"Point"}
}