{
  "type": "Feature",
  "properties": {
    "addr:full":"13031 Thoroughbred St Bakersfield CA 93313",
    "addr:housenumber":"13031",
    "addr:postcode":"93313",
    "addr:street":"Thoroughbred St",
    "iso:country":"US",
    "sg:address":"13031 Thoroughbred St",
    "sg:city":"Bakersfield",
    "sg:classifiers":[
        {
            "category":"Building & Trades",
            "subcategory":"Construction",
            "type":"Services"
        }
    ],
    "sg:phone":"+1 661 397 6630",
    "sg:postcode":"93313",
    "sg:province":"CA",
    "sg:tags":[
        "pipe",
        "line",
        "contractor"
    ],
    "wof:name":"Mayberry's Pipeline Constr",
    "wof:placetype":"venue"
},
  "geometry": {"coordinates":[-119.018688,35.234305],"type":"Point"}
}