{
  "type": "Feature",
  "properties": {
    "iso:country":"US",
    "sg:address":"2373 2nd St",
    "sg:city":"La Verne",
    "sg:classifiers":[
        {
            "category":"Building & Trades",
            "subcategory":"Plumbing",
            "type":"Services"
        }
    ],
    "sg:phone":"+1 909 593 0855",
    "sg:postcode":"91750",
    "sg:province":"CA",
    "sg:tags":[
        "plumbing",
        "contractor"
    ],
    "wof:name":"A-1 Quality Plumbing",
    "wof:placetype":"venue"
},
  "geometry": {"coordinates":[-117.766158,34.098507],"type":"Point"}
}