{
  "type": "Feature",
  "properties": {
    "addr:full":"27574 Sierra Hwy Canyon Country CA 91351",
    "addr:housenumber":"27574",
    "addr:postcode":"91351",
    "addr:street":"Sierra Hwy",
    "iso:country":"US",
    "sg:address":"27574 Sierra Hwy",
    "sg:city":"Canyon Country",
    "sg:classifiers":[
        {
            "category":"Sports & Exercise",
            "subcategory":"Gym",
            "type":"Entertainment"
        }
    ],
    "sg:phone":"+1 661 250 8842",
    "sg:postcode":"91351",
    "sg:province":"CA",
    "sg:tags":[
        "club",
        "health",
        "studio",
        "gymnasium"
    ],
    "wof:name":"Curves For Women",
    "wof:placetype":"venue"
},
  "geometry": {"coordinates":[-118.462535,34.407111],"type":"Point"}
}