{
  "type": "Feature",
  "properties": {
    "addr:full":"520 Galvez St Stanford CA 94305",
    "addr:housenumber":"520",
    "addr:postcode":"94305",
    "addr:street":"Galvez St",
    "iso:country":"US",
    "sg:address":"520 Galvez St",
    "sg:city":"Stanford",
    "sg:classifiers":[
        {
            "category":"Education",
            "subcategory":"College",
            "type":"Public Place"
        }
    ],
    "sg:phone":"+1 650 723 4891",
    "sg:postcode":"94305",
    "sg:province":"CA",
    "wof:name":"Standard Teacher Education",
    "wof:placetype":"venue"
},
  "geometry": {"coordinates":[-122.16613,37.42534],"type":"Point"}
}