{
  "type": "Feature",
  "properties": {
    "iso:country":"US",
    "sg:address":"8025 Greenback Ln",
    "sg:city":"Citrus Heights",
    "sg:classifiers":[
        {
            "category":"Shopping",
            "subcategory":"Music",
            "type":"Retail Goods"
        }
    ],
    "sg:phone":"+1 916 728 6004",
    "sg:postcode":"95610",
    "sg:province":"CA",
    "sg:tags":[
        "game",
        "disc",
        "tape",
        "video",
        "rental",
        "cassette"
    ],
    "wof:name":"Video Clearance Center",
    "wof:placetype":"venue"
},
  "geometry": {"coordinates":[-121.26599899999999,38.6786],"type":"Point"}
}