{
  "type": "Feature",
  "properties": {
    "addr:full":"1400 Cleveland Ave National City CA 91950",
    "addr:housenumber":"1400",
    "addr:postcode":"91950",
    "addr:street":"Cleveland Ave",
    "iso:country":"US",
    "sg:address":"1400 Cleveland Ave",
    "sg:city":"National City",
    "sg:classifiers":[
        {
            "category":"Manufacturing",
            "subcategory":"Metals",
            "type":"Manufacturing & Wholesale Goods"
        }
    ],
    "sg:phone":"+1 619 474 4424",
    "sg:postcode":"91950",
    "sg:province":"CA",
    "sg:tags":[
        "plating"
    ],
    "wof:name":"Lemon Grove Plating",
    "wof:placetype":"venue"
},
  "geometry": {"coordinates":[-117.113113,32.668362],"type":"Point"}
}