{
  "type": "Feature",
  "properties": {
    "addr:full":"7701 Canoga Ave Canoga Park CA 91304",
    "addr:housenumber":"7701",
    "addr:postcode":"91304",
    "addr:street":"Canoga Ave",
    "iso:country":"US",
    "sg:address":"7701 Canoga Ave",
    "sg:city":"Canoga Park",
    "sg:classifiers":[
        {
            "category":"Wholesale",
            "subcategory":"Machinery & Supplies",
            "type":"Manufacturing & Wholesale Goods"
        }
    ],
    "sg:phone":"+1 818 704 4888",
    "sg:postcode":"91304",
    "sg:province":"CA",
    "sg:tags":[
        "contractor"
    ],
    "wof:name":"Discount Contractor Supply",
    "wof:placetype":"venue"
},
  "geometry": {"coordinates":[-118.59752400000001,34.211922],"type":"Point"}
}