{
  "type": "Feature",
  "properties": {
    "iso:country":"US",
    "sg:address":"3049 Clearview Dr",
    "sg:city":"Yuba City",
    "sg:classifiers":[
        {
            "category":"Real Estate",
            "subcategory":"Real Estate Agent",
            "type":"Services"
        }
    ],
    "sg:phone":"+1 530 671 3787",
    "sg:postcode":"95993",
    "sg:province":"CA",
    "wof:name":"Capitol Data Link",
    "wof:placetype":"venue"
},
  "geometry": {"coordinates":[-121.673528,39.160392],"type":"Point"}
}