{
  "type": "Feature",
  "properties": {
    "addr:full":"21515 S Western Ave Torrance CA 90501",
    "addr:housenumber":"21515",
    "addr:postcode":"90501",
    "addr:street":"S Western Ave",
    "iso:country":"US",
    "sg:address":"21515 S Western Ave",
    "sg:city":"Torrance",
    "sg:classifiers":[
        {
            "category":"Sports & Exercise",
            "subcategory":"Bowling",
            "type":"Entertainment"
        }
    ],
    "sg:phone":"+1 310 782 6800",
    "sg:postcode":"90501",
    "sg:province":"CA",
    "sg:tags":[
        "center"
    ],
    "sg:website":"www.mitsuwa.com",
    "wof:name":"Mitsuwa Corp",
    "wof:placetype":"venue"
},
  "geometry": {"coordinates":[-118.309112,33.832643],"type":"Point"}
}