{
  "type": "Feature",
  "properties": {
    "addr:full":"1251 Sussex Ct Gustine CA 95322",
    "addr:housenumber":"1251",
    "addr:postcode":"95322",
    "addr:street":"Sussex Ct",
    "iso:country":"US",
    "sg:address":"1251 Sussex Ct",
    "sg:city":"Gustine",
    "sg:classifiers":[
        {
            "category":"Building & Trades",
            "subcategory":"Construction",
            "type":"Services"
        },
        {
            "category":"Military Area",
            "subcategory":"Armory",
            "type":"Public Place"
        }
    ],
    "sg:phone":"+1 209 854 6950",
    "sg:postcode":"95322",
    "sg:province":"CA",
    "sg:tags":[
        "repair",
        "fence-sales",
        "fence",
        "contractor"
    ],
    "wof:name":"Union Fence",
    "wof:placetype":"venue"
},
  "geometry": {"coordinates":[-121.010712,37.246489],"type":"Point"}
}