{
  "type": "Feature",
  "properties": {
    "addr:full":"4594 30th St San Diego CA 92116",
    "addr:housenumber":"4594",
    "addr:postcode":"92116",
    "addr:street":"30Th St",
    "iso:country":"US",
    "sg:address":"4594 30th St",
    "sg:city":"San Diego",
    "sg:classifiers":[
        {
            "category":"Personal",
            "subcategory":"Nail Salon",
            "type":"Services"
        }
    ],
    "sg:phone":"+1 619 281 2608",
    "sg:postcode":"92116",
    "sg:province":"CA",
    "wof:name":"Spectrum Nails",
    "wof:placetype":"venue"
},
  "geometry": {"coordinates":[-117.129997,32.7607],"type":"Point"}
}