{
  "type": "Feature",
  "properties": {
    "addr:full":"3340 E 12th St # 200 Oakland CA 94601",
    "addr:housenumber":"3340",
    "addr:postcode":"94601",
    "addr:street":"E 12Th St # 200",
    "iso:country":"US",
    "sg:address":"3340 E 12th St # 200",
    "sg:city":"Oakland",
    "sg:classifiers":[
        {
            "category":"Shopping",
            "subcategory":"Hobbies, Toys, & Games",
            "type":"Retail Goods"
        },
        {
            "category":"Shopping",
            "subcategory":"Jewelry",
            "type":"Retail Goods"
        }
    ],
    "sg:phone":"+1 510 385 0628",
    "sg:postcode":"94601",
    "sg:province":"CA",
    "sg:tags":[
        "shop",
        "hobby"
    ],
    "wof:name":"Ceras Y Pulseras Parafina",
    "wof:placetype":"venue"
},
  "geometry": {"coordinates":[-122.224616,37.776337],"type":"Point"}
}