{
  "type": "Feature",
  "properties": {
    "addr:full":"27031 Vista Ter Lake Forest CA 92630",
    "addr:housenumber":"27031",
    "addr:postcode":"92630",
    "addr:street":"Vista Ter",
    "iso:country":"US",
    "sg:address":"27031 Vista Ter",
    "sg:city":"Lake Forest",
    "sg:classifiers":[
        {
            "category":"Sports & Exercise",
            "subcategory":"Bicycle Rental",
            "type":"Entertainment"
        }
    ],
    "sg:phone":"+1 949 581 3319",
    "sg:postcode":"92630",
    "sg:province":"CA",
    "sg:tags":[
        "wear"
    ],
    "wof:name":"Primesource Sports",
    "wof:placetype":"venue"
},
  "geometry": {"coordinates":[-117.65905100000001,33.665368],"type":"Point"}
}