{
  "type": "Feature",
  "properties": {
    "iso:country":"US",
    "sg:address":"1200 S Brookhurst St",
    "sg:city":"Anaheim",
    "sg:classifiers":[
        {
            "category":"Home & Garden",
            "subcategory":"Home Furnishings",
            "type":"Retail Goods"
        }
    ],
    "sg:phone":"+1 714 491 0031",
    "sg:postcode":"92804",
    "sg:province":"CA",
    "sg:tags":[
        "linen"
    ],
    "wof:name":"Alkam Home Fashions",
    "wof:placetype":"venue"
},
  "geometry": {"coordinates":[-117.95891399999999,33.814687],"type":"Point"}
}