{
  "type": "Feature",
  "properties": {
    "addr:full":"4405 Redwood Rd Napa CA 94558",
    "addr:housenumber":"4405",
    "addr:postcode":"94558",
    "addr:street":"Redwood Rd",
    "iso:country":"US",
    "sg:address":"4405 Redwood Rd",
    "sg:city":"Napa",
    "sg:classifiers":[
        {
            "category":"Professional",
            "type":"Services"
        }
    ],
    "sg:phone":"+1 707 252 3821",
    "sg:postcode":"94558",
    "sg:province":"CA",
    "sg:tags":[
        "establishment"
    ],
    "wof:name":"Novitiate Community",
    "wof:placetype":"venue"
},
  "geometry": {"coordinates":[-122.385492,38.338097],"type":"Point"}
}