{
  "type": "Feature",
  "properties": {
    "addr:full":"1412 N Hundley St Anaheim CA 92806",
    "addr:housenumber":"1412",
    "addr:postcode":"92806",
    "addr:street":"N Hundley St",
    "iso:country":"US",
    "sg:address":"1412 N Hundley St",
    "sg:city":"Anaheim",
    "sg:classifiers":[
        {
            "category":"Building & Trades",
            "subcategory":"Construction",
            "type":"Services"
        }
    ],
    "sg:phone":"+1 714 632 1516",
    "sg:postcode":"92806",
    "sg:province":"CA",
    "sg:tags":[
        "contractor"
    ],
    "wof:name":"Bear State Development",
    "wof:placetype":"venue"
},
  "geometry": {"coordinates":[-117.864679,33.861064],"type":"Point"}
}