{
  "type": "Feature",
  "properties": {
    "iso:country":"US",
    "sg:address":"1291 Maple Ct Apt A",
    "sg:city":"Novato",
    "sg:classifiers":[
        {
            "category":"Personal",
            "type":"Services"
        },
        {
            "category":"Professional",
            "subcategory":"Art Services",
            "type":"Services"
        }
    ],
    "sg:phone":"+1 415 892 2310",
    "sg:postcode":"94947",
    "sg:province":"CA",
    "sg:tags":[
        "photography",
        "videography",
        "wedding"
    ],
    "wof:name":"Photo As Art",
    "wof:placetype":"venue"
},
  "geometry": {"coordinates":[-122.55486500000001,38.087509],"type":"Point"}
}