{
  "type": "Feature",
  "properties": {
    "addr:full":"128 E Donovan Rd Santa Maria CA 93454",
    "addr:housenumber":"128",
    "addr:postcode":"93454",
    "addr:street":"E Donovan Rd",
    "iso:country":"US",
    "sg:address":"128 E Donovan Rd",
    "sg:city":"Santa Maria",
    "sg:classifiers":[
        {
            "category":"Sports & Exercise",
            "subcategory":"Bowling",
            "type":"Entertainment"
        },
        {
            "category":"Shopping",
            "subcategory":"Bicycles & Sporting Goods",
            "type":"Retail Goods"
        }
    ],
    "sg:phone":"+1 805 925 9930",
    "sg:postcode":"93454",
    "sg:province":"CA",
    "sg:tags":[
        "apparel",
        "center",
        "accessory"
    ],
    "wof:name":"Strike Zone",
    "wof:placetype":"venue"
},
  "geometry": {"coordinates":[-120.43471099999999,34.967603],"type":"Point"}
}