{
  "type": "Feature",
  "properties": {
    "addr:full":"7705 Eastdumfries Ln Bakersfield CA 93309",
    "addr:housenumber":"7705",
    "addr:postcode":"93309",
    "addr:street":"Eastdumfries Ln",
    "iso:country":"US",
    "sg:address":"7705 Eastdumfries Ln",
    "sg:city":"Bakersfield",
    "sg:classifiers":[
        {
            "category":"Mining & Drilling",
            "type":"Manufacturing & Wholesale Goods"
        }
    ],
    "sg:phone":"+1 661 325 2893",
    "sg:postcode":"93309",
    "sg:province":"CA",
    "sg:tags":[
        "field",
        "oil"
    ],
    "wof:name":"Enhanced Petroleum Tech Inc",
    "wof:placetype":"venue"
},
  "geometry": {"coordinates":[-119.087232,35.336143],"type":"Point"}
}