{
  "type": "Feature",
  "properties": {
    "addr:full":"3042 W Pico Blvd Los Angeles CA 90006",
    "addr:housenumber":"3042",
    "addr:postcode":"90006",
    "addr:street":"W Pico Blvd",
    "iso:country":"US",
    "sg:address":"3042 W Pico Blvd",
    "sg:city":"Los Angeles",
    "sg:classifiers":[
        {
            "category":"Wholesale",
            "subcategory":"Durable Goods & Equipment",
            "type":"Manufacturing & Wholesale Goods"
        }
    ],
    "sg:phone":"+1 323 732 6949",
    "sg:postcode":"90006",
    "sg:province":"CA",
    "sg:tags":[
        "exporter"
    ],
    "wof:name":"Transportes Escuintla",
    "wof:placetype":"venue"
},
  "geometry": {"coordinates":[-118.308725,34.047118],"type":"Point"}
}