{
  "type": "Feature",
  "properties": {
    "addr:full":"1137 S Golden Gate Ave Stockton CA 95205",
    "addr:housenumber":"1137",
    "addr:postcode":"95205",
    "addr:street":"S Golden Gate Ave",
    "iso:country":"US",
    "sg:address":"1137 S Golden Gate Ave",
    "sg:city":"Stockton",
    "sg:classifiers":[
        {
            "category":"Recreation",
            "subcategory":"Marina",
            "type":"Entertainment"
        }
    ],
    "sg:phone":"+1 209 464 2628",
    "sg:postcode":"95205",
    "sg:province":"CA",
    "sg:tags":[
        "repairing",
        "boat"
    ],
    "wof:name":"Aqua Tech",
    "wof:placetype":"venue"
},
  "geometry": {"coordinates":[-121.24269099999999,37.950123],"type":"Point"}
}