{
  "type": "Feature",
  "properties": {
    "addr:full":"333 W Main St Ripon CA 95366",
    "addr:housenumber":"333",
    "addr:postcode":"ca 95366",
    "addr:street":"W Main St",
    "iso:country":"US",
    "sg:address":"333 W Main St",
    "sg:city":"Ripon",
    "sg:classifiers":[
        {
            "category":"Home & Garden",
            "subcategory":"Hardware",
            "type":"Retail Goods"
        }
    ],
    "sg:phone":"+1 209 599 2142",
    "sg:postcode":"95366",
    "sg:province":"CA",
    "wof:name":"Hardware Schemper's",
    "wof:placetype":"venue"
},
  "geometry": {"coordinates":[-121.126938,37.739445],"type":"Point"}
}