{
  "type": "Feature",
  "properties": {
    "addr:full":"3044 Industry St Oceanside CA 92054",
    "addr:housenumber":"3044",
    "addr:postcode":"92054",
    "addr:street":"Industry St",
    "iso:country":"US",
    "sg:address":"3044 Industry St",
    "sg:city":"Oceanside",
    "sg:classifiers":[
        {
            "category":"Home & Garden",
            "subcategory":"Building Materials",
            "type":"Retail Goods"
        }
    ],
    "sg:phone":"+1 760 967 7197",
    "sg:postcode":"92054",
    "sg:province":"CA",
    "sg:tags":[
        "paint"
    ],
    "wof:name":"Pacific Shores Paint & Designs",
    "wof:placetype":"venue"
},
  "geometry": {"coordinates":[-117.333381,33.200711],"type":"Point"}
}