{
  "type": "Feature",
  "properties": {
    "addr:full":"6 Wisteria Ct Novato CA 94945",
    "addr:housenumber":"6",
    "addr:postcode":"94945",
    "addr:street":"Wisteria Ct",
    "iso:country":"US",
    "sg:address":"6 Wisteria Ct",
    "sg:city":"Novato",
    "sg:classifiers":[
        {
            "category":"Organizations",
            "subcategory":"Religious Organization",
            "type":"Services"
        }
    ],
    "sg:phone":"+1 415 878 2003",
    "sg:postcode":"94945",
    "sg:province":"CA",
    "sg:tags":[
        "church"
    ],
    "wof:name":"Church Development Systems",
    "wof:placetype":"venue"
},
  "geometry": {"coordinates":[-122.570689,38.116192],"type":"Point"}
}