{
  "type": "Feature",
  "properties": {
    "addr:full":"9650 Miramar Rd San Diego CA 92126",
    "addr:housenumber":"9650",
    "addr:postcode":"92126",
    "addr:street":"Miramar Rd",
    "iso:country":"US",
    "sg:address":"9650 Miramar Rd",
    "sg:city":"San Diego",
    "sg:classifiers":[
        {
            "category":"Retail",
            "subcategory":"Car Wash",
            "type":"Services"
        }
    ],
    "sg:phone":"+1 858 695 0307",
    "sg:postcode":"92126",
    "sg:province":"CA",
    "sg:tags":[
        "polishing",
        "washing"
    ],
    "wof:name":"Scripps Miramar Car Wash",
    "wof:placetype":"venue"
},
  "geometry": {"coordinates":[-117.119557,32.893895],"type":"Point"}
}