{
  "type": "Feature",
  "properties": {
    "addr:full":"2411 Old Crow Canyon Rd San Ramon CA 94583",
    "addr:housenumber":"2411",
    "addr:postcode":"ca 94583",
    "addr:street":"Old Crow Canyon Rd",
    "iso:country":"US",
    "sg:address":"2411 Old Crow Canyon Rd",
    "sg:city":"San Ramon",
    "sg:classifiers":[
        {
            "category":"Manufacturing",
            "subcategory":"Printing",
            "type":"Manufacturing & Wholesale Goods"
        }
    ],
    "sg:phone":"+1 925 743 4055",
    "sg:postcode":"94583",
    "sg:province":"CA",
    "sg:tags":[
        "publisher",
        "software"
    ],
    "wof:name":"Faronics Technologies USA",
    "wof:placetype":"venue"
},
  "geometry": {"coordinates":[-121.979589,37.779215],"type":"Point"}
}