{
  "type": "Feature",
  "properties": {
    "addr:full":"1407 N Batavia St Orange CA 92867",
    "addr:housenumber":"1407",
    "addr:postcode":"92867",
    "addr:street":"N Batavia St",
    "iso:country":"US",
    "sg:address":"1407 N Batavia St",
    "sg:city":"Orange",
    "sg:classifiers":[
        {
            "category":"Retail",
            "subcategory":"Repair Shop",
            "type":"Services"
        }
    ],
    "sg:phone":"+1 714 633 7233",
    "sg:postcode":"92867",
    "sg:province":"CA",
    "sg:tags":[
        "equipment",
        "conditioning",
        "air"
    ],
    "wof:name":"Ron's Heating & Air Cond",
    "wof:placetype":"venue"
},
  "geometry": {"coordinates":[-117.862354,33.811169],"type":"Point"}
}