{
  "type": "Feature",
  "properties": {
    "iso:country":"US",
    "sg:address":"222 Dakota Dr",
    "sg:city":"Ventura",
    "sg:classifiers":[
        {
            "category":"Building & Trades",
            "subcategory":"Plumbing",
            "type":"Services"
        }
    ],
    "sg:phone":"+1 805 648 4552",
    "sg:postcode":"93001",
    "sg:province":"CA",
    "sg:tags":[
        "contractor"
    ],
    "wof:name":"BT Plumbing & Heating",
    "wof:placetype":"venue"
},
  "geometry": {"coordinates":[-119.28865399999999,34.309344],"type":"Point"}
}