{
  "type": "Feature",
  "properties": {
    "addr:full":"3835 Cross Creek Rd Suite 9B Malibu CA 90265",
    "addr:housenumber":"3835;9b",
    "addr:postcode":"90265",
    "addr:street":"Cross Creek Rd Suite",
    "iso:country":"US",
    "sg:address":"3835 Cross Creek Rd Suite 9B",
    "sg:city":"Malibu",
    "sg:classifiers":[
        {
            "category":"Shopping",
            "subcategory":"Clothing, Apparel, & Fashions",
            "type":"Retail Goods"
        }
    ],
    "sg:phone":"+1 310 456 1203",
    "sg:postcode":"90265",
    "sg:province":"CA",
    "sg:tags":[
        "apparel",
        "jean",
        "clothing",
        "store",
        "women's"
    ],
    "wof:name":"7 For All Mankind",
    "wof:placetype":"venue"
},
  "geometry": {"coordinates":[-118.68552099999999,34.036592],"type":"Point"}
}