{
  "type": "Feature",
  "properties": {
    "addr:full":"3804 Grim Ave San Diego CA 92104",
    "addr:housenumber":"3804",
    "addr:postcode":"92104",
    "addr:street":"Grim Ave",
    "iso:country":"US",
    "sg:address":"3804 Grim Ave",
    "sg:city":"San Diego",
    "sg:classifiers":[
        {
            "category":"Restaurant",
            "type":"Food & Drink"
        }
    ],
    "sg:phone":"+1 619 297 2760",
    "sg:postcode":"92104",
    "sg:province":"CA",
    "sg:tags":[
        "breakfast",
        "brunch"
    ],
    "wof:name":"Lucky's Breakfast",
    "wof:placetype":"venue"
},
  "geometry": {"coordinates":[-117.12854,32.747578],"type":"Point"}
}