{
  "type": "Feature",
  "properties": {
    "addr:full":"133 Starlite St S San Francisco CA 94080",
    "addr:housenumber":"133",
    "addr:postcode":"94080",
    "addr:street":"Starlite St S",
    "iso:country":"US",
    "sg:address":"133 Starlite St",
    "sg:city":"S San Francisco",
    "sg:classifiers":[
        {
            "category":"Manufacturing",
            "subcategory":"Furniture",
            "type":"Manufacturing & Wholesale Goods"
        }
    ],
    "sg:phone":"+1 650 873 4585",
    "sg:postcode":"94080",
    "sg:province":"CA",
    "sg:tags":[
        "equipment",
        "supply"
    ],
    "sg:website":"www.broadwaysheetmetal.com",
    "wof:name":"Broadway Sheet Metal & Mfg",
    "wof:placetype":"venue"
},
  "geometry": {"coordinates":[-122.417351,37.649061],"type":"Point"}
}