{
  "type": "Feature",
  "properties": {
    "addr:full":"2601 W Orangethorpe Ave Fullerton CA 92833",
    "addr:housenumber":"2601",
    "addr:postcode":"92833",
    "addr:street":"W Orangethorpe Ave",
    "iso:country":"US",
    "sg:address":"2601 W Orangethorpe Ave",
    "sg:city":"Fullerton",
    "sg:classifiers":[
        {
            "category":"Travel",
            "subcategory":"Hotels & Motels",
            "type":"Entertainment"
        },
        {
            "category":"Travel",
            "subcategory":"Bed & Breakfast",
            "type":"Entertainment"
        }
    ],
    "sg:phone":"+1 714 773 4900",
    "sg:postcode":"92833",
    "sg:province":"CA",
    "wof:name":"Fullerton Inn",
    "wof:placetype":"venue"
},
  "geometry": {"coordinates":[-117.973,33.859001],"type":"Point"}
}