{
  "type": "Feature",
  "properties": {
    "addr:full":"1963 Carlson Blvd Richmond CA 94804",
    "addr:housenumber":"1963",
    "addr:postcode":"94804",
    "addr:street":"Carlson Blvd",
    "iso:country":"US",
    "sg:address":"1963 Carlson Blvd",
    "sg:city":"Richmond",
    "sg:classifiers":[
        {
            "category":"Place Of Worship",
            "subcategory":"Church",
            "type":"Public Place"
        },
        {
            "category":"Place Of Worship",
            "type":"Public Place"
        }
    ],
    "sg:phone":"+1 510 526 5304",
    "sg:postcode":"94804",
    "sg:province":"CA",
    "sg:tags":[
        "lutheran",
        "america",
        "churches-lutheran",
        "churches-lutheran-evangelical"
    ],
    "wof:name":"Life Lutheran Church",
    "wof:placetype":"venue"
},
  "geometry": {"coordinates":[-122.310757,37.909365],"type":"Point"}
}