{
  "type": "Feature",
  "properties": {
    "addr:full":"235 Montgomery St San Francisco CA 94104",
    "addr:housenumber":"235",
    "addr:postcode":"94104",
    "addr:street":"Montgomery St",
    "iso:country":"US",
    "sg:address":"235 Montgomery St",
    "sg:city":"San Francisco",
    "sg:classifiers":[
        {
            "category":"Banks & Credit Unions",
            "subcategory":"Investment Brokerage",
            "type":"Services"
        }
    ],
    "sg:phone":"+1 415 391 6943",
    "sg:postcode":"94104",
    "sg:province":"CA",
    "wof:name":"CBC Investments",
    "wof:placetype":"venue"
},
  "geometry": {"coordinates":[-122.402593,37.791564],"type":"Point"}
}