{
  "type": "Feature",
  "properties": {
    "iso:country":"US",
    "sg:address":"2801 McHenry Ave",
    "sg:city":"Modesto",
    "sg:classifiers":[
        {
            "category":"Personal",
            "subcategory":"Tanning Parlor",
            "type":"Services"
        }
    ],
    "sg:phone":"+1 209 544 0186",
    "sg:postcode":"95350",
    "sg:province":"CA",
    "sg:tags":[
        "salon"
    ],
    "wof:name":"Fantasy Nails & Tanning",
    "wof:placetype":"venue"
},
  "geometry": {"coordinates":[-120.994182,37.681765],"type":"Point"}
}