{
  "type": "Feature",
  "properties": {
    "addr:full":"10680 Broadway Rd Moorpark CA 93021",
    "addr:housenumber":"10680",
    "addr:postcode":"ca 93021",
    "addr:street":"Broadway Rd",
    "iso:country":"US",
    "sg:address":"10680 Broadway Rd",
    "sg:city":"Moorpark",
    "sg:classifiers":[
        {
            "category":"Farming",
            "subcategory":"Farm",
            "type":"Manufacturing & Wholesale Goods"
        }
    ],
    "sg:phone":"+1 805 531 5482",
    "sg:postcode":"93021",
    "sg:province":"CA",
    "sg:tags":[
        "crop",
        "general"
    ],
    "wof:name":"White Birch Farm",
    "wof:placetype":"venue"
},
  "geometry": {"coordinates":[-118.91896300000001,34.315123],"type":"Point"}
}