{
  "type": "Feature",
  "properties": {
    "iso:country":"US",
    "sg:address":"2430 Las Plumas Ave",
    "sg:city":"Oroville",
    "sg:classifiers":[
        {
            "category":"Personal",
            "type":"Services"
        }
    ],
    "sg:phone":"+1 530 533 1725",
    "sg:postcode":"95966",
    "sg:province":"CA",
    "sg:tags":[
        "control",
        "weight"
    ],
    "wof:name":"Lifetime Nutrition",
    "wof:placetype":"venue"
},
  "geometry": {"coordinates":[-121.534744,39.48039],"type":"Point"}
}