{
  "type": "Feature",
  "properties": {
    "iso:country":"US",
    "sg:address":"4036 Cedarhurst Dr Apt 108",
    "sg:city":"Santa Maria",
    "sg:classifiers":[
        {
            "category":"Real Estate",
            "subcategory":"Real Estate Services",
            "type":"Services"
        },
        {
            "category":"Real Estate",
            "subcategory":"Real Estate Operator",
            "type":"Services"
        }
    ],
    "sg:phone":"+1 805 937 0281",
    "sg:postcode":"93455",
    "sg:province":"CA",
    "sg:tags":[
        "apartment",
        "property",
        "management"
    ],
    "wof:name":"Knollwood Meadows",
    "wof:placetype":"venue"
},
  "geometry": {"coordinates":[-120.429001,34.888699],"type":"Point"}
}