{
  "type": "Feature",
  "properties": {
    "iso:country":"US",
    "sg:address":"14420 Civic Dr Ste 9",
    "sg:city":"Victorville",
    "sg:classifiers":[
        {
            "category":"Insurance",
            "subcategory":"Hazard Insurance",
            "type":"Services"
        }
    ],
    "sg:phone":"+1 760 243 2495",
    "sg:postcode":"92392",
    "sg:province":"CA",
    "sg:tags":[
        "commercial",
        "business"
    ],
    "sg:website":"http://www.principal.com",
    "wof:name":"The Principal Financial Group",
    "wof:placetype":"venue"
},
  "geometry": {"coordinates":[-117.32365299999999,34.512712],"type":"Point"}
}