{
  "type": "Feature",
  "properties": {
    "addr:full":"421 Main St Half Moon Bay CA 94019",
    "addr:housenumber":"421",
    "addr:postcode":"94019",
    "addr:street":"Main St",
    "iso:country":"US",
    "sg:address":"421 Main St",
    "sg:city":"Half Moon Bay",
    "sg:classifiers":[
        {
            "category":"Shopping",
            "type":"Retail Goods"
        }
    ],
    "sg:phone":"+1 650 712 9135",
    "sg:postcode":"94019",
    "sg:province":"CA",
    "sg:tags":[
        "art",
        "gallery",
        "dealer"
    ],
    "sg:website":"www.nutierra.com",
    "wof:name":"Nuestra Tierra Inc",
    "wof:placetype":"venue"
},
  "geometry": {"coordinates":[-122.429078,37.464645],"type":"Point"}
}