{
  "type": "Feature",
  "properties": {
    "iso:country":"US",
    "sg:address":"4949 W Slauson Ave",
    "sg:city":"Los Angeles",
    "sg:classifiers":[
        {
            "category":"Donuts",
            "subcategory":"None",
            "type":"Food & Drink"
        }
    ],
    "sg:phone":"+1 323 292 8770",
    "sg:postcode":"90056",
    "sg:province":"CA",
    "wof:name":"Spudnuts Donuts",
    "wof:placetype":"venue"
},
  "geometry": {"coordinates":[-118.364193,33.987593],"type":"Point"}
}