{
  "type": "Feature",
  "properties": {
    "addr:full":"1100 Crows Landing Rd Modesto CA 95351",
    "addr:housenumber":"1100",
    "addr:postcode":"ca 95351",
    "addr:street":"Crows Landing Rd",
    "iso:country":"US",
    "sg:address":"1100 Crows Landing Rd",
    "sg:city":"Modesto",
    "sg:classifiers":[
        {
            "category":"Personal",
            "subcategory":"Barber",
            "type":"Services"
        }
    ],
    "sg:phone":"+1 209 496 2035",
    "sg:postcode":"95351",
    "sg:province":"CA",
    "wof:name":"Platinum Cuts",
    "wof:placetype":"venue"
},
  "geometry": {"coordinates":[-120.99363200000001,37.612563],"type":"Point"}
}