{
  "type": "Feature",
  "properties": {
    "iso:country":"US",
    "sg:address":"3730 Turri Rd",
    "sg:city":"San Luis Obispo",
    "sg:classifiers":[
        {
            "category":"Farming",
            "subcategory":"Livestock Farm",
            "type":"Manufacturing & Wholesale Goods"
        }
    ],
    "sg:phone":"+1 805 543 7066",
    "sg:postcode":"93405",
    "sg:province":"CA",
    "sg:tags":[
        "crop",
        "cattle"
    ],
    "wof:name":"Turri Ranch & Cattle Co",
    "wof:placetype":"venue"
},
  "geometry": {"coordinates":[-120.775268,35.306937],"type":"Point"}
}