{
  "type": "Feature",
  "properties": {
    "addr:full":"8200 Slauson Ave Pico Rivera CA 90660",
    "addr:postcode":"8200;90660",
    "addr:street":"Slauson Ave",
    "iso:country":"US",
    "sg:address":"8200 Slauson Ave",
    "sg:city":"Pico Rivera",
    "sg:classifiers":[
        {
            "category":"Professional",
            "subcategory":"Employment Agencies",
            "type":"Services"
        }
    ],
    "sg:phone":"+1 562 942 8775",
    "sg:postcode":"90660",
    "sg:province":"CA",
    "sg:tags":[
        "opportunity"
    ],
    "wof:name":"Staffmark",
    "wof:placetype":"venue"
},
  "geometry": {"coordinates":[-118.118571,33.975088],"type":"Point"}
}