{
  "type": "Feature",
  "properties": {
    "addr:full":"1081 Cam del Rio S San Diego CA 92108",
    "addr:housenumber":"1081",
    "addr:postcode":"92108",
    "addr:street":"Cam Del Rio S",
    "iso:country":"US",
    "sg:address":"1081 Cam del Rio S",
    "sg:city":"San Diego",
    "sg:classifiers":[
        {
            "category":"Professional",
            "subcategory":"Management & Consulting",
            "type":"Services"
        }
    ],
    "sg:phone":"+1 858 453 9390",
    "sg:postcode":"92108",
    "sg:province":"CA",
    "sg:tags":[
        "consultant",
        "business"
    ],
    "sg:website":"www.ksa.com",
    "wof:name":"KSA",
    "wof:placetype":"venue"
},
  "geometry": {"coordinates":[-117.153926,32.764295],"type":"Point"}
}