{
  "type": "Feature",
  "properties": {
    "iso:country":"US",
    "sg:address":"1070 Lincoln Ave",
    "sg:city":"San Jose",
    "sg:classifiers":[
        {
            "category":"Sports & Exercise",
            "subcategory":"Gym",
            "type":"Entertainment"
        }
    ],
    "sg:phone":"+1 408 294 9656",
    "sg:postcode":"95125",
    "sg:province":"CA",
    "sg:tags":[
        "trainer",
        "pilate"
    ],
    "sg:website":"www.tru-balance.com",
    "wof:name":"Tru-Balance Pilates Fitness Studio",
    "wof:placetype":"venue"
},
  "geometry": {"coordinates":[-121.90218900000001,37.31003],"type":"Point"}
}