{
  "type": "Feature",
  "properties": {
    "addr:full":"2121 Tustin Ave Costa Mesa CA 92627",
    "addr:housenumber":"2121",
    "addr:postcode":"92627",
    "addr:street":"Tustin Ave",
    "iso:country":"US",
    "sg:address":"2121 Tustin Ave",
    "sg:city":"Costa Mesa",
    "sg:classifiers":[
        {
            "category":"Manufacturing",
            "subcategory":"Retail Goods",
            "type":"Manufacturing & Wholesale Goods"
        }
    ],
    "sg:phone":"+1 949 645 8975",
    "sg:postcode":"92627",
    "sg:province":"CA",
    "sg:tags":[
        "product",
        "mfg"
    ],
    "wof:name":"Immigrant Industries",
    "wof:placetype":"venue"
},
  "geometry": {"coordinates":[-117.900655,33.642263],"type":"Point"}
}