{
  "type": "Feature",
  "properties": {
    "iso:country":"US",
    "sg:address":"555 Capitol Mall",
    "sg:city":"Sacramento",
    "sg:classifiers":[
        {
            "category":"Wholesale",
            "subcategory":"Office Equipment",
            "type":"Manufacturing & Wholesale Goods"
        }
    ],
    "sg:phone":"+1 916 646 4285",
    "sg:postcode":"95814",
    "sg:province":"CA",
    "wof:name":"E C R M E",
    "wof:placetype":"venue"
},
  "geometry": {"coordinates":[-121.500748,38.57866],"type":"Point"}
}