{
  "type": "Feature",
  "properties": {
    "iso:country":"US",
    "sg:address":"1442 Irvine Blvd",
    "sg:city":"Tustin",
    "sg:classifiers":[
        {
            "category":"Professional",
            "subcategory":"Accounting & Tax Preparation",
            "type":"Services"
        }
    ],
    "sg:phone":"+1 714 730 9814",
    "sg:postcode":"92780",
    "sg:province":"CA",
    "sg:tags":[
        "accountant"
    ],
    "wof:name":"Jaubert Junius L CPA",
    "wof:placetype":"venue"
},
  "geometry": {"coordinates":[-117.80500000000001,33.745098],"type":"Point"}
}