{
  "type": "Feature",
  "properties": {
    "addr:full":"1674 Pleasant Valley Rd Aptos CA 95003",
    "addr:housenumber":"1674",
    "addr:postcode":"ca 95003",
    "addr:street":"Pleasant Valley Rd",
    "iso:country":"US",
    "sg:address":"1674 Pleasant Valley Rd",
    "sg:city":"Aptos",
    "sg:classifiers":[
        {
            "category":"Building & Trades",
            "subcategory":"Construction",
            "type":"Services"
        }
    ],
    "sg:phone":"+1 831 761 2170",
    "sg:postcode":"95003",
    "sg:province":"CA",
    "sg:tags":[
        "contractor"
    ],
    "wof:name":"Byers Construction",
    "wof:placetype":"venue"
},
  "geometry": {"coordinates":[-121.83099199999999,36.996591],"type":"Point"}
}