{
  "type": "Feature",
  "properties": {
    "iso:country":"US",
    "sg:address":"535 E Bonnie View Dr",
    "sg:city":"Rialto",
    "sg:classifiers":[
        {
            "category":"Retail",
            "subcategory":"Car Wash",
            "type":"Services"
        }
    ],
    "sg:phone":"+1 909 874 9048",
    "sg:postcode":"92376",
    "sg:province":"CA",
    "sg:tags":[
        "carwash",
        "repair",
        "trade",
        "contractor"
    ],
    "wof:name":"Rick Meisenbacher Enterprises",
    "wof:placetype":"venue"
},
  "geometry": {"coordinates":[-117.357972,34.096428],"type":"Point"}
}