{
  "type": "Feature",
  "properties": {
    "addr:full":"1840 S 7th St San Jose CA 95112",
    "addr:housenumber":"1840",
    "addr:postcode":"95112",
    "addr:street":"S 7Th St",
    "iso:country":"US",
    "sg:address":"1840 S 7th St",
    "sg:city":"San Jose",
    "sg:classifiers":[
        {
            "category":"Retail",
            "subcategory":"Repair Shop",
            "type":"Services"
        }
    ],
    "sg:phone":"+1 408 293 9500",
    "sg:postcode":"95112",
    "sg:province":"CA",
    "sg:tags":[
        "plumbing",
        "drain",
        "cleaning",
        "sewer"
    ],
    "wof:name":"Reliable Rooter",
    "wof:placetype":"venue"
},
  "geometry": {"coordinates":[-121.865246,37.313757],"type":"Point"}
}