{
  "type": "Feature",
  "properties": {
    "iso:country":"US",
    "sg:address":"765 The City Dr S",
    "sg:city":"Orange",
    "sg:classifiers":[
        {
            "category":"Shopping",
            "subcategory":"Computers & Home Electronics",
            "type":"Retail Goods"
        }
    ],
    "sg:phone":"+1 714 740 2004",
    "sg:postcode":"92868",
    "sg:province":"CA",
    "sg:tags":[
        "equipment",
        "dealer"
    ],
    "wof:name":"Bluevar",
    "wof:placetype":"venue"
},
  "geometry": {"coordinates":[-117.888864,33.778842],"type":"Point"}
}