{
  "type": "Feature",
  "properties": {
    "iso:country":"US",
    "sg:address":"1620 Colorado Boulevard",
    "sg:city":"Los Angeles",
    "sg:classifiers":[
        {
            "category":"Building & Trades",
            "subcategory":"Cleaning & Sanitation",
            "type":"Services"
        },
        {
            "category":"Home & Garden",
            "subcategory":"Hardware",
            "type":"Retail Goods"
        }
    ],
    "sg:phone":"+1 323 255 8222",
    "sg:postcode":"90041",
    "sg:province":"CA",
    "sg:tags":[
        "store",
        "carpet"
    ],
    "wof:name":"The Rug Doctor",
    "wof:placetype":"venue"
},
  "geometry": {"coordinates":[-118.201763,34.139511],"type":"Point"}
}