{
  "type": "Feature",
  "properties": {
    "addr:full":"8976 Laurel Canyon Blvd Sun Valley CA 91352",
    "addr:housenumber":"8976",
    "addr:postcode":"91352",
    "addr:street":"Laurel Canyon Blvd",
    "iso:country":"US",
    "sg:address":"8976 Laurel Canyon Blvd",
    "sg:city":"Sun Valley",
    "sg:classifiers":[
        {
            "category":"Retail",
            "subcategory":"Auto Repair",
            "type":"Services"
        }
    ],
    "sg:phone":"+1 818 504 2522",
    "sg:postcode":"91352",
    "sg:province":"CA",
    "sg:tags":[
        "truck"
    ],
    "wof:name":"American Fleet Svc",
    "wof:placetype":"venue"
},
  "geometry": {"coordinates":[-118.40526800000001,34.233295],"type":"Point"}
}