{
  "type": "Feature",
  "properties": {
    "iso:country":"US",
    "sg:address":"346 Rheem Blvd",
    "sg:city":"Moraga",
    "sg:classifiers":[
        {
            "category":"Retail",
            "subcategory":"Repair Shop",
            "type":"Services"
        }
    ],
    "sg:phone":"+1 925 933 1245",
    "sg:postcode":"94556",
    "sg:province":"CA",
    "sg:tags":[
        "water",
        "heater"
    ],
    "wof:name":"Link's Plumbing",
    "wof:placetype":"venue"
},
  "geometry": {"coordinates":[-122.12508200000001,37.860265],"type":"Point"}
}