{
  "type": "Feature",
  "properties": {
    "iso:country":"US",
    "sg:address":"4141 Pestana Pl",
    "sg:city":"Fremont",
    "sg:classifiers":[
        {
            "category":"Professional",
            "type":"Services"
        },
        {
            "category":"Retail",
            "subcategory":"Auto Rental",
            "type":"Services"
        },
        {
            "category":"Travel",
            "subcategory":"Travel Agent",
            "type":"Entertainment"
        },
        {
            "category":"Airport",
            "type":"Transportation"
        },
        {
            "category":"Local Transit",
            "type":"Transportation"
        }
    ],
    "sg:phone":"+1 510 413 7061",
    "sg:postcode":"94538",
    "sg:province":"CA",
    "sg:tags":[
        "shuttle",
        "consultant",
        "limousine"
    ],
    "sg:website":"http://www.yext.com/p/superpages/san-francisco-bay-area-limousine-fremont-california.html",
    "wof:name":"San Francisco Bay Area Limousine",
    "wof:placetype":"venue"
},
  "geometry": {"coordinates":[-121.950019,37.504118],"type":"Point"}
}