{
  "type": "Feature",
  "properties": {
    "addr:full":"219 Canterbury Dr Vallejo CA 94591",
    "addr:housenumber":"219",
    "addr:postcode":"94591",
    "addr:street":"Canterbury Dr",
    "iso:country":"US",
    "sg:address":"219 Canterbury Dr",
    "sg:city":"Vallejo",
    "sg:classifiers":[
        {
            "category":"Social Services",
            "subcategory":"Adult Care",
            "type":"Services"
        }
    ],
    "sg:phone":"+1 707 643 0349",
    "sg:postcode":"94591",
    "sg:province":"CA",
    "sg:tags":[
        "home",
        "residential"
    ],
    "wof:name":"Twin Residential Care Home",
    "wof:placetype":"venue"
},
  "geometry": {"coordinates":[-122.194346,38.106864],"type":"Point"}
}