{
  "type": "Feature",
  "properties": {
    "iso:country":"US",
    "sg:address":"39026 Palm Tree Way",
    "sg:city":"Palmdale",
    "sg:classifiers":[
        {
            "category":"Professional",
            "type":"Services"
        }
    ],
    "sg:phone":"+1 323 755 8628",
    "sg:postcode":"93551",
    "sg:province":"CA",
    "wof:name":"Blessing Untold Dayc",
    "wof:placetype":"venue"
},
  "geometry": {"coordinates":[-118.152953,34.59179],"type":"Point"}
}