{
  "type": "Feature",
  "properties": {
    "iso:country":"US",
    "sg:address":"930 45th Ave",
    "sg:city":"Oakland",
    "sg:classifiers":[
        {
            "category":"Building & Trades",
            "subcategory":"Construction",
            "type":"Services"
        }
    ],
    "sg:phone":"+1 510 532 5931",
    "sg:postcode":"94601",
    "sg:province":"CA",
    "sg:tags":[
        "supply",
        "maker",
        "cabinet"
    ],
    "sg:website":"www.parkmeadproducts.com",
    "wof:name":"Parkmead Products",
    "wof:placetype":"venue"
},
  "geometry": {"coordinates":[-122.216003,37.7691],"type":"Point"}
}