{
  "type": "Feature",
  "properties": {
    "iso:country":"US",
    "sg:address":"16336 Whittier Blvd",
    "sg:city":"Whittier",
    "sg:classifiers":[
        {
            "category":"Health Services",
            "subcategory":"Dentist",
            "type":"Services"
        }
    ],
    "sg:phone":"+1 562 943 2585",
    "sg:postcode":"90603",
    "sg:province":"CA",
    "wof:name":"ELMI PAULA G DMD",
    "wof:placetype":"venue"
},
  "geometry": {"coordinates":[-117.98185700000001,33.939874],"type":"Point"}
}