{
  "type": "Feature",
  "properties": {
    "addr:full":"611 K Street, Suite B San Diego CA 92037",
    "addr:housenumber":"611",
    "addr:postcode":"92037",
    "addr:street":"K Street Suite B",
    "iso:country":"US",
    "sg:address":"611 K Street, Suite B",
    "sg:city":"San Diego",
    "sg:classifiers":[
        {
            "category":"Shopping",
            "subcategory":"Jewelry",
            "type":"Retail Goods"
        }
    ],
    "sg:phone":"+1 877 443 3823",
    "sg:postcode":"92037",
    "sg:province":"CA",
    "sg:tags":[
        "watch"
    ],
    "sg:website":"www.deucebrand.com/Default.aspx",
    "wof:name":"Deuce Brand",
    "wof:placetype":"venue"
},
  "geometry": {"coordinates":[-117.159111,32.708337],"type":"Point"}
}