{
  "type": "Feature",
  "properties": {
    "addr:full":"945 Fourth Ave San Diego CA 92101",
    "addr:housenumber":"945",
    "addr:postcode":"92101",
    "addr:street":"Fourth Ave",
    "iso:country":"US",
    "sg:address":"945 Fourth Ave",
    "sg:city":"San Diego",
    "sg:classifiers":[
        {
            "category":"Professional",
            "subcategory":"Lawyer & Legal Services",
            "type":"Services"
        }
    ],
    "sg:phone":"+1 619 233 1888",
    "sg:postcode":"92101",
    "sg:province":"CA",
    "sg:website":"www.wertzmcdade.com",
    "wof:name":"Wertz McDade Wallace Moot & Brower",
    "wof:placetype":"venue"
},
  "geometry": {"coordinates":[-117.16107599999999,32.715295],"type":"Point"}
}