{
  "type": "Feature",
  "properties": {
    "addr:full":"1139 Yulupa Ave Santa Rosa CA 95405",
    "addr:housenumber":"1139",
    "addr:postcode":"95405",
    "addr:street":"Yulupa Ave",
    "iso:country":"US",
    "sg:address":"1139 Yulupa Ave",
    "sg:city":"Santa Rosa",
    "sg:classifiers":[
        {
            "category":"Retail",
            "subcategory":"Self-service Laundry",
            "type":"Services"
        }
    ],
    "sg:phone":"+1 707 527 5822",
    "sg:postcode":"95405",
    "sg:province":"CA",
    "wof:name":"Wash Board Laundromat",
    "wof:placetype":"venue"
},
  "geometry": {"coordinates":[-122.67391600000001,38.442457],"type":"Point"}
}