{
  "type": "Feature",
  "properties": {
    "addr:full":"1039 Columbus Dr Santa Maria CA 93454",
    "addr:housenumber":"1039",
    "addr:postcode":"93454",
    "addr:street":"Columbus Dr",
    "iso:country":"US",
    "sg:address":"1039 Columbus Dr",
    "sg:city":"Santa Maria",
    "sg:classifiers":[
        {
            "category":"Building & Trades",
            "subcategory":"Construction",
            "type":"Services"
        }
    ],
    "sg:phone":"+1 805 349 8377",
    "sg:postcode":"93454",
    "sg:province":"CA",
    "sg:tags":[
        "concrete",
        "resurfacing"
    ],
    "wof:name":"Custom Concrete Resurfacing",
    "wof:placetype":"venue"
},
  "geometry": {"coordinates":[-120.418434,34.96887],"type":"Point"}
}