{
  "type": "Feature",
  "properties": {
    "addr:full":"3365 India St San Diego CA 92103",
    "addr:housenumber":"3365",
    "addr:postcode":"92103",
    "addr:street":"India St",
    "iso:country":"US",
    "sg:address":"3365 India St",
    "sg:city":"San Diego",
    "sg:classifiers":[
        {
            "category":"Bars & Pubs",
            "subcategory":"Lounge",
            "type":"Food & Drink"
        },
        {
            "category":"Bars & Pubs",
            "subcategory":"Dive Bar",
            "type":"Food & Drink"
        }
    ],
    "sg:phone":"+1 619 297 7211",
    "sg:postcode":"92103",
    "sg:province":"CA",
    "sg:website":"www.aeroclubbar.com",
    "wof:name":"The Aero Club Bar",
    "wof:placetype":"venue"
},
  "geometry": {"coordinates":[-117.177002,32.7379],"type":"Point"}
}