{
  "type": "Feature",
  "properties": {
    "iso:country":"US",
    "sg:address":"560 W Milling St",
    "sg:city":"Lancaster",
    "sg:classifiers":[
        {
            "category":"Personal",
            "subcategory":"Beauty Salon",
            "type":"Services"
        }
    ],
    "sg:phone":"+1 661 948 7447",
    "sg:postcode":"93534",
    "sg:province":"CA",
    "sg:tags":[
        "therapist",
        "massage"
    ],
    "wof:name":"Bella West Salon & Spa",
    "wof:placetype":"venue"
},
  "geometry": {"coordinates":[-118.138238,34.69637],"type":"Point"}
}