{
  "type": "Feature",
  "properties": {
    "addr:full":"2675 Avenue 352 Kingsburg CA 93631",
    "addr:housenumber":"2675",
    "addr:postcode":"93631",
    "addr:street":"Avenue 352",
    "iso:country":"US",
    "sg:address":"2675 Avenue 352",
    "sg:city":"Kingsburg",
    "sg:classifiers":[
        {
            "category":"Farming",
            "subcategory":"Fish & Marine Products",
            "type":"Manufacturing & Wholesale Goods"
        }
    ],
    "sg:phone":"+1 559 897 3262",
    "sg:postcode":"93631",
    "sg:province":"CA",
    "sg:website":"http://www.talktalk.net",
    "wof:name":"Danny Jones",
    "wof:placetype":"venue"
},
  "geometry": {"coordinates":[-119.52381,36.430614],"type":"Point"}
}