{
  "type": "Feature",
  "properties": {
    "iso:country":"US",
    "sg:address":"1755 W Glenoaks Blvd Unit F",
    "sg:city":"Glendale",
    "sg:classifiers":[
        {
            "category":"Shopping",
            "subcategory":"Pharmacy",
            "type":"Retail Goods"
        }
    ],
    "sg:phone":"+1 818 549 0008",
    "sg:postcode":"91201",
    "sg:province":"CA",
    "sg:tags":[
        "drugstore"
    ],
    "wof:name":"Remedy Drugs",
    "wof:placetype":"venue"
},
  "geometry": {"coordinates":[-118.295998,34.178001],"type":"Point"}
}