{
  "type": "Feature",
  "properties": {
    "addr:full":"10730 Foothill Blvd Rancho Cucamonga CA 91730",
    "addr:housenumber":"10730",
    "addr:postcode":"91730",
    "addr:street":"Foothill Blvd",
    "iso:country":"US",
    "sg:address":"10730 Foothill Blvd",
    "sg:city":"Rancho Cucamonga",
    "sg:classifiers":[
        {
            "category":"Shopping",
            "subcategory":"Florist",
            "type":"Retail Goods"
        }
    ],
    "sg:phone":"+1 909 948 9098",
    "sg:postcode":"91730",
    "sg:province":"CA",
    "wof:name":"Tommy Austin's Florist",
    "wof:placetype":"venue"
},
  "geometry": {"coordinates":[-117.56756,34.106573],"type":"Point"}
}