{
  "type": "Feature",
  "properties": {
    "addr:full":"1471 N Beale Rd Marysville CA 95901",
    "addr:housenumber":"1471",
    "addr:postcode":"95901",
    "addr:street":"N Beale Rd",
    "iso:country":"US",
    "sg:address":"1471 N Beale Rd",
    "sg:city":"Marysville",
    "sg:classifiers":[
        {
            "category":"Home & Garden",
            "subcategory":"Household Appliances",
            "type":"Retail Goods"
        }
    ],
    "sg:phone":"+1 530 749 1003",
    "sg:postcode":"95901",
    "sg:province":"CA",
    "wof:name":"S K Appliance Repair & Service",
    "wof:placetype":"venue"
},
  "geometry": {"coordinates":[-121.564947,39.126959],"type":"Point"}
}