{
  "type": "Feature",
  "properties": {
    "addr:full":"2221 Morse Avenue Sacramento CA 95825",
    "addr:housenumber":"2221",
    "addr:postcode":"95825",
    "addr:street":"Morse Avenue",
    "iso:country":"US",
    "sg:address":"2221 Morse Avenue",
    "sg:city":"Sacramento",
    "sg:classifiers":[
        {
            "category":"Education",
            "subcategory":"School",
            "type":"Public Place"
        }
    ],
    "sg:phone":"+1 916 575 2306",
    "sg:postcode":"95825",
    "sg:province":"CA",
    "sg:tags":[
        "high",
        "middle",
        "elementary"
    ],
    "wof:name":"Cottage Elementary School",
    "wof:placetype":"venue"
},
  "geometry": {"coordinates":[-121.392037,38.60568],"type":"Point"}
}