{
  "type": "Feature",
  "properties": {
    "addr:full":"13318 Talc St Lathrop CA 95330",
    "addr:housenumber":"13318",
    "addr:postcode":"95330",
    "addr:street":"Talc St",
    "iso:country":"US",
    "sg:address":"13318 Talc St",
    "sg:city":"Lathrop",
    "sg:classifiers":[
        {
            "category":"Banks & Credit Unions",
            "subcategory":"Investment Brokerage",
            "type":"Services"
        }
    ],
    "sg:phone":"+1 209 451 4950",
    "sg:postcode":"95330",
    "sg:province":"CA",
    "sg:tags":[
        "advisory"
    ],
    "wof:name":"Kimbro Business & Investment Group",
    "wof:placetype":"venue"
},
  "geometry": {"coordinates":[-121.281277,37.839727],"type":"Point"}
}