{
  "type": "Feature",
  "properties": {
    "addr:full":"544 Cleveland Ave. Albany CA 94710",
    "addr:housenumber":"544",
    "addr:postcode":"94710",
    "addr:street":"Cleveland Ave.",
    "iso:country":"US",
    "sg:address":"544 Cleveland Ave.",
    "sg:city":"Albany",
    "sg:classifiers":[
        {
            "category":"Retail",
            "subcategory":"Auto Repair",
            "type":"Services"
        }
    ],
    "sg:phone":"+1 415 771 8460",
    "sg:postcode":"94710",
    "sg:province":"CA",
    "sg:website":"www.englisheuropean.com",
    "wof:name":"English & European Car Service",
    "wof:placetype":"venue"
},
  "geometry": {"coordinates":[-122.308736,37.895519],"type":"Point"}
}