{
  "type": "Feature",
  "properties": {
    "addr:full":"19310 Sonoma Hwy Sonoma CA 95476",
    "addr:housenumber":"19310",
    "addr:postcode":"95476",
    "addr:street":"Sonoma Hwy",
    "iso:country":"US",
    "sg:address":"19310 Sonoma Hwy",
    "sg:city":"Sonoma",
    "sg:classifiers":[
        {
            "category":"Banks & Credit Unions",
            "subcategory":"Investment Brokerage",
            "type":"Services"
        }
    ],
    "sg:phone":"+1 707 939 6961",
    "sg:postcode":"95476",
    "sg:province":"CA",
    "sg:tags":[
        "security"
    ],
    "wof:name":"Edward Jones Co",
    "wof:placetype":"venue"
},
  "geometry": {"coordinates":[-122.47516299999999,38.298373],"type":"Point"}
}