{
  "type": "Feature",
  "properties": {
    "iso:country":"US",
    "sg:address":"6184 Atlantic Ave",
    "sg:city":"Long Beach",
    "sg:classifiers":[
        {
            "category":"Food & Beverages",
            "subcategory":"Specialty",
            "type":"Retail Goods"
        }
    ],
    "sg:phone":"+1 562 422 4847",
    "sg:postcode":"90805",
    "sg:province":"CA",
    "sg:tags":[
        "vitamin"
    ],
    "wof:name":"Ronaldo Ramos",
    "wof:placetype":"venue"
},
  "geometry": {"coordinates":[-118.185004,33.865772],"type":"Point"}
}