{
  "type": "Feature",
  "properties": {
    "addr:full":"840 S 47th St San Diego CA 92113",
    "addr:housenumber":"840",
    "addr:postcode":"92113",
    "addr:street":"S 47Th St",
    "iso:country":"US",
    "sg:address":"840 S 47th St",
    "sg:city":"San Diego",
    "sg:classifiers":[
        {
            "category":"Restaurant",
            "type":"Food & Drink"
        }
    ],
    "sg:phone":"+1 619 262 5128",
    "sg:postcode":"92113",
    "sg:province":"CA",
    "sg:tags":[
        "mexican"
    ],
    "wof:name":"Tacos El Paisa",
    "wof:placetype":"venue"
},
  "geometry": {"coordinates":[-117.094039,32.697047],"type":"Point"}
}