{
  "type": "Feature",
  "properties": {
    "addr:full":"2940 E Thousand Oaks Blvd Thousand Oaks CA 91362",
    "addr:housenumber":"2940",
    "addr:postcode":"91362",
    "addr:street":"E Thousand Oaks Blvd",
    "iso:country":"US",
    "sg:address":"2940 E Thousand Oaks Blvd",
    "sg:city":"Thousand Oaks",
    "sg:classifiers":[
        {
            "category":"Shopping",
            "subcategory":"Books",
            "type":"Retail Goods"
        }
    ],
    "sg:phone":"+1 805 374 0084",
    "sg:postcode":"91362",
    "sg:province":"CA",
    "sg:tags":[
        "dealer"
    ],
    "sg:website":"www.mysteriestodiefor.com",
    "wof:name":"Mysteries To Die For",
    "wof:placetype":"venue"
},
  "geometry": {"coordinates":[-118.837979,34.170531],"type":"Point"}
}