{
  "type": "Feature",
  "properties": {
    "addr:full":"2360 McKee Rd San Jose CA 95116",
    "addr:housenumber":"2360",
    "addr:postcode":"95116",
    "addr:street":"Mckee Rd",
    "iso:country":"US",
    "sg:address":"2360 McKee Rd",
    "sg:city":"San Jose",
    "sg:classifiers":[
        {
            "category":"Health Services",
            "subcategory":"Doctor",
            "type":"Services"
        }
    ],
    "sg:phone":"+1 408 923 8138",
    "sg:postcode":"95116",
    "sg:province":"CA",
    "sg:tags":[
        "physician",
        "surgeon"
    ],
    "wof:name":"San Jose Eye Health",
    "wof:placetype":"venue"
},
  "geometry": {"coordinates":[-121.84726000000001,37.367059],"type":"Point"}
}