{
  "type": "Feature",
  "properties": {
    "iso:country":"US",
    "sg:address":"1457 18th St",
    "sg:city":"San Francisco",
    "sg:classifiers":[
        {
            "category":"Restaurant",
            "type":"Food & Drink"
        }
    ],
    "sg:menulink":"http://www.allmenus.com/ca/san-francisco/61817-elizas/menu/",
    "sg:phone":"+1 415 648 9999",
    "sg:postcode":"94107",
    "sg:province":"CA",
    "sg:tags":[
        "asian",
        "chinese"
    ],
    "wof:name":"Eliza's",
    "wof:placetype":"venue"
},
  "geometry": {"coordinates":[-122.397068,37.762596],"type":"Point"}
}