{
  "type": "Feature",
  "properties": {
    "addr:full":"4945 E Lane Ave Fresno CA 93727",
    "addr:housenumber":"4945",
    "addr:postcode":"93727",
    "addr:street":"E Lane Ave",
    "iso:country":"US",
    "sg:address":"4945 E Lane Ave",
    "sg:city":"Fresno",
    "sg:classifiers":[
        {
            "category":"Recreation",
            "type":"Entertainment"
        }
    ],
    "sg:phone":"+1 559 621 6600",
    "sg:postcode":"93727",
    "sg:province":"CA",
    "sg:tags":[
        "parks"
    ],
    "wof:name":"Pilibos Soccer Park",
    "wof:placetype":"venue"
},
  "geometry": {"coordinates":[-119.72903700000001,36.732351],"type":"Point"}
}