{
  "type": "Feature",
  "properties": {
    "addr:full":"2852 Colorado Ave Santa Monica CA 90404",
    "addr:housenumber":"2852",
    "addr:postcode":"90404",
    "addr:street":"Colorado Ave",
    "iso:country":"US",
    "sg:address":"2852 Colorado Ave",
    "sg:city":"Santa Monica",
    "sg:classifiers":[
        {
            "category":"Building & Trades",
            "subcategory":"Construction",
            "type":"Services"
        }
    ],
    "sg:phone":"+1 310 453 0204",
    "sg:postcode":"90404",
    "sg:province":"CA",
    "sg:tags":[
        "general",
        "contractor"
    ],
    "wof:name":"Balcorp Construction",
    "wof:placetype":"venue"
},
  "geometry": {"coordinates":[-118.468379,34.032695],"type":"Point"}
}