{
  "type": "Feature",
  "properties": {
    "addr:full":"4545 Mission Blvd Montclair CA 91763",
    "addr:housenumber":"4545",
    "addr:postcode":"91763",
    "addr:street":"Mission Blvd",
    "iso:country":"US",
    "sg:address":"4545 Mission Blvd",
    "sg:city":"Montclair",
    "sg:classifiers":[
        {
            "category":"Restaurant",
            "type":"Food & Drink"
        }
    ],
    "sg:menulink":"http://www.allmenus.com/ca/ontario/150315-subway/menu/",
    "sg:phone":"+1 909 627 2711",
    "sg:postcode":"91763",
    "sg:province":"CA",
    "sg:tags":[
        "american",
        "sandwich"
    ],
    "wof:name":"Subway",
    "wof:placetype":"venue"
},
  "geometry": {"coordinates":[-117.70599199999999,34.055459],"type":"Point"}
}