{
  "type": "Feature",
  "properties": {
    "iso:country":"US",
    "sg:address":"61 W Main St",
    "sg:city":"Merced",
    "sg:classifiers":[
        {
            "category":"Restaurant",
            "type":"Food & Drink"
        }
    ],
    "sg:phone":"+1 209 723 1515",
    "sg:postcode":"95340",
    "sg:province":"CA",
    "wof:name":"Cotija Taco Shop",
    "wof:placetype":"venue"
},
  "geometry": {"coordinates":[-120.476571,37.298949],"type":"Point"}
}