{
  "type": "Feature",
  "properties": {
    "iso:country":"US",
    "sg:address":"22959 Sierra Hwy",
    "sg:city":"Newhall",
    "sg:classifiers":[
        {
            "category":"Building & Trades",
            "subcategory":"Construction",
            "type":"Services"
        }
    ],
    "sg:phone":"+1 661 753 9224",
    "sg:postcode":"91321",
    "sg:province":"CA",
    "sg:tags":[
        "concrete",
        "contractor"
    ],
    "wof:name":"First American Gunite",
    "wof:placetype":"venue"
},
  "geometry": {"coordinates":[-118.507054,34.359568],"type":"Point"}
}