{
  "type": "Feature",
  "properties": {
    "addr:full":"5675 Telegraph Rd City Of Commerce CA 90040",
    "addr:housenumber":"5675",
    "addr:postcode":"90040",
    "addr:street":"Telegraph Rd",
    "iso:country":"US",
    "sg:address":"5675 Telegraph Rd",
    "sg:city":"City Of Commerce",
    "sg:classifiers":[
        {
            "category":"Professional",
            "subcategory":"Business Services",
            "type":"Services"
        }
    ],
    "sg:phone":"+1 323 887 9627",
    "sg:postcode":"90040",
    "sg:province":"CA",
    "sg:tags":[
        "development"
    ],
    "wof:name":"Commerce Small Business Devlpt",
    "wof:placetype":"venue"
},
  "geometry": {"coordinates":[-118.15422599999999,34.00607],"type":"Point"}
}