{
  "type": "Feature",
  "properties": {
    "iso:country":"US",
    "sg:address":"1018 E Colorado St",
    "sg:city":"Glendale",
    "sg:classifiers":[
        {
            "category":"Restaurant",
            "type":"Food & Drink"
        }
    ],
    "sg:phone":"+1 818 240 8717",
    "sg:postcode":"91205",
    "sg:province":"CA",
    "wof:name":"Leonardo's Restaurant & Nite Club",
    "wof:placetype":"venue"
},
  "geometry": {"coordinates":[-118.241997,34.142502],"type":"Point"}
}