{
  "type": "Feature",
  "properties": {
    "iso:country":"US",
    "sg:address":"5432 W 104th St",
    "sg:city":"Los Angeles",
    "sg:classifiers":[
        {
            "category":"Travel",
            "subcategory":"Travel Agent",
            "type":"Entertainment"
        }
    ],
    "sg:phone":"+1 310 649 0064",
    "sg:postcode":"90045",
    "sg:province":"CA",
    "sg:tags":[
        "agency"
    ],
    "sg:website":"www.air-apparent.com",
    "wof:name":"Air Apparent Inc",
    "wof:placetype":"venue"
},
  "geometry": {"coordinates":[-118.373952,33.941893],"type":"Point"}
}