{
  "type": "Feature",
  "properties": {
    "iso:country":"US",
    "sg:address":"630 Bercut Dr",
    "sg:city":"Sacramento",
    "sg:classifiers":[
        {
            "category":"Building & Trades",
            "subcategory":"Electrical",
            "type":"Services"
        }
    ],
    "sg:phone":"+1 916 448 0194",
    "sg:postcode":"95811",
    "sg:province":"CA",
    "sg:tags":[
        "installation"
    ],
    "wof:name":"Verizon PBX Instltn & Mntnc",
    "wof:placetype":"venue"
},
  "geometry": {"coordinates":[-121.502276,38.598368],"type":"Point"}
}