{
  "type": "Feature",
  "properties": {
    "iso:country":"US",
    "sg:address":"315 W Milgeo Ave",
    "sg:city":"Ripon",
    "sg:classifiers":[
        {
            "category":"Wholesale",
            "subcategory":"Groceries",
            "type":"Manufacturing & Wholesale Goods"
        }
    ],
    "sg:phone":"+1 209 599 5355",
    "sg:postcode":"95366",
    "sg:province":"CA",
    "wof:name":"Nadines Naturals",
    "wof:placetype":"venue"
},
  "geometry": {"coordinates":[-121.12585900000001,37.746724],"type":"Point"}
}