{
  "type": "Feature",
  "properties": {
    "iso:country":"US",
    "sg:address":"6083 Maxwell Dr",
    "sg:city":"Paradise",
    "sg:classifiers":[
        {
            "category":"Professional",
            "subcategory":"Engineering",
            "type":"Services"
        }
    ],
    "sg:phone":"+1 530 877 4080",
    "sg:postcode":"95969",
    "sg:province":"CA",
    "sg:tags":[
        "general",
        "contractor"
    ],
    "wof:name":"David C Schott Construction",
    "wof:placetype":"venue"
},
  "geometry": {"coordinates":[-121.612479,39.766259],"type":"Point"}
}