{
  "type": "Feature",
  "properties": {
    "addr:full":"4337 Songbird Way Redding CA 96001",
    "addr:housenumber":"4337",
    "addr:postcode":"96001",
    "addr:street":"Songbird Way",
    "iso:country":"US",
    "sg:address":"4337 Songbird Way",
    "sg:city":"Redding",
    "sg:classifiers":[
        {
            "category":"Building & Trades",
            "subcategory":"Electrical",
            "type":"Services"
        },
        {
            "category":"Manufacturing",
            "subcategory":"Signs",
            "type":"Manufacturing & Wholesale Goods"
        }
    ],
    "sg:phone":"+1 530 244 3202",
    "sg:postcode":"96001",
    "sg:province":"CA",
    "sg:tags":[
        "electrical",
        "contractor"
    ],
    "wof:name":"Larry's Lighting & Electrical",
    "wof:placetype":"venue"
},
  "geometry": {"coordinates":[-122.41132500000001,40.552338],"type":"Point"}
}