{
  "type": "Feature",
  "properties": {
    "iso:country":"US",
    "sg:address":"25000 Glen Ivy Rd",
    "sg:city":"Corona",
    "sg:classifiers":[
        {
            "category":"Health Services",
            "subcategory":"Doctor",
            "type":"Services"
        },
        {
            "category":"Personal",
            "subcategory":"Beauty Salon",
            "type":"Services"
        },
        {
            "category":"Personal",
            "subcategory":"Barber",
            "type":"Services"
        },
        {
            "category":"Personal",
            "subcategory":"Hair Removal",
            "type":"Services"
        },
        {
            "category":"Personal",
            "subcategory":"Day Spa",
            "type":"Services"
        }
    ],
    "sg:phone":"+1 951 277 3529",
    "sg:postcode":"92883",
    "sg:province":"CA",
    "sg:tags":[
        "weaving",
        "replacement"
    ],
    "sg:website":"http://www.glenivy.com",
    "wof:name":"Glen Ivy Hot Springs",
    "wof:placetype":"venue"
},
  "geometry": {"coordinates":[-117.494034,33.759935],"type":"Point"}
}