{
  "type": "Feature",
  "properties": {
    "iso:country":"US",
    "sg:address":"2303 Mesa Vista Ct",
    "sg:city":"Paso Robles",
    "sg:classifiers":[
        {
            "category":"Social Services",
            "subcategory":"Adult Care",
            "type":"Services"
        }
    ],
    "sg:phone":"+1 805 238 6515",
    "sg:postcode":"93446",
    "sg:province":"CA",
    "sg:tags":[
        "home",
        "residential"
    ],
    "wof:name":"K C's Helping Hands Home Care",
    "wof:placetype":"venue"
},
  "geometry": {"coordinates":[-120.664484,35.642998],"type":"Point"}
}