{
  "type": "Feature",
  "properties": {
    "iso:country":"US",
    "sg:address":"7430 Corbin Ave Unit 19",
    "sg:city":"Reseda",
    "sg:classifiers":[
        {
            "category":"Shopping",
            "subcategory":"Florist",
            "type":"Retail Goods"
        }
    ],
    "sg:phone":"+1 818 885 0600",
    "sg:postcode":"91335",
    "sg:province":"CA",
    "sg:website":"www.floraldesignsbymichael.com",
    "wof:name":"FLORAL DESIGNS BY MICHAEL",
    "wof:placetype":"venue"
},
  "geometry": {"coordinates":[-118.56209,34.205479],"type":"Point"}
}