{
  "type": "Feature",
  "properties": {
    "iso:country":"US",
    "sg:address":"230 Helicopter Cir",
    "sg:city":"Corona",
    "sg:classifiers":[
        {
            "category":"Building & Trades",
            "subcategory":"Construction",
            "type":"Services"
        }
    ],
    "sg:phone":"+1 951 735 8100",
    "sg:postcode":"92880",
    "sg:province":"CA",
    "sg:tags":[
        "product",
        "asphalt"
    ],
    "sg:website":"www.reganpaving.com",
    "wof:name":"Charles C Regan Paving Inc",
    "wof:placetype":"venue"
},
  "geometry": {"coordinates":[-117.603493,33.888923],"type":"Point"}
}