{
  "type": "Feature",
  "properties": {
    "iso:country":"US",
    "sg:address":"6937 Federal Blvd",
    "sg:city":"Lemon Grove",
    "sg:classifiers":[
        {
            "category":"Wholesale",
            "subcategory":"Plants",
            "type":"Manufacturing & Wholesale Goods"
        }
    ],
    "sg:phone":"+1 619 464 2575",
    "sg:postcode":"91945",
    "sg:province":"CA",
    "sg:tags":[
        "supply"
    ],
    "wof:name":"Rich & Bennys",
    "wof:placetype":"venue"
},
  "geometry": {"coordinates":[-117.046891,32.742272],"type":"Point"}
}