{
  "type": "Feature",
  "properties": {
    "iso:country":"US",
    "sg:address":"22 N Union St",
    "sg:city":"Stockton",
    "sg:classifiers":[
        {
            "category":"Organizations",
            "subcategory":"Labor Organization",
            "type":"Services"
        }
    ],
    "sg:phone":"+1 209 464 1827",
    "sg:postcode":"95205",
    "sg:province":"CA",
    "wof:name":"ILWU Local",
    "wof:placetype":"venue"
},
  "geometry": {"coordinates":[-121.276915,37.955744],"type":"Point"}
}