{
  "type": "Feature",
  "properties": {
    "iso:country":"US",
    "sg:address":"5800 Carter Ave",
    "sg:city":"Bakersfield",
    "sg:classifiers":[
        {
            "category":"Real Estate",
            "subcategory":"Real Estate Agent",
            "type":"Services"
        }
    ],
    "sg:phone":"+1 661 399 2838",
    "sg:postcode":"93308",
    "sg:province":"CA",
    "wof:name":"Associated Reality",
    "wof:placetype":"venue"
},
  "geometry": {"coordinates":[-119.070067,35.415417],"type":"Point"}
}