{
  "type": "Feature",
  "properties": {
    "iso:country":"US",
    "sg:address":"233 California Dr",
    "sg:city":"Burlingame",
    "sg:classifiers":[
        {
            "category":"Home & Garden",
            "subcategory":"Furniture",
            "type":"Retail Goods"
        }
    ],
    "sg:phone":"+1 650 642 1500",
    "sg:postcode":"94010",
    "sg:province":"CA",
    "sg:tags":[
        "store"
    ],
    "wof:name":"Fine Consign Quality Furniture",
    "wof:placetype":"venue"
},
  "geometry": {"coordinates":[-122.344002,37.5788],"type":"Point"}
}