{
  "type": "Feature",
  "properties": {
    "iso:country":"US",
    "sg:address":"39519 10th St W",
    "sg:city":"Palmdale",
    "sg:classifiers":[
        {
            "category":"Restaurant",
            "type":"Food & Drink"
        }
    ],
    "sg:menulink":"http://www.allmenus.com/ca/south-antelope-valley/121696-fazolis/menu/",
    "sg:phone":"+1 661 273 1444",
    "sg:postcode":"93551",
    "sg:province":"CA",
    "sg:tags":[
        "italian"
    ],
    "wof:name":"Fazoli's",
    "wof:placetype":"venue"
},
  "geometry": {"coordinates":[-118.147813,34.600824],"type":"Point"}
}