{
  "type": "Feature",
  "properties": {
    "addr:full":"61 Laurel Ln El Sobrante CA 94803",
    "addr:housenumber":"61",
    "addr:postcode":"94803",
    "addr:street":"Laurel Ln",
    "iso:country":"US",
    "sg:address":"61 Laurel Ln",
    "sg:city":"El Sobrante",
    "sg:classifiers":[
        {
            "category":"Shopping",
            "subcategory":"Clothing, Apparel, & Fashions",
            "type":"Retail Goods"
        }
    ],
    "sg:phone":"+1 510 223 7255",
    "sg:postcode":"94803",
    "sg:province":"CA",
    "wof:name":"Solis Inc",
    "wof:placetype":"venue"
},
  "geometry": {"coordinates":[-122.298929,37.967492],"type":"Point"}
}