{
  "type": "Feature",
  "properties": {
    "iso:country":"US",
    "sg:address":"2028 Quail St",
    "sg:city":"Newport Beach",
    "sg:classifiers":[
        {
            "category":"Sports & Exercise",
            "subcategory":"Gym",
            "type":"Entertainment"
        }
    ],
    "sg:phone":"+1 949 475 5555",
    "sg:postcode":"92660",
    "sg:province":"CA",
    "sg:tags":[
        "trainer"
    ],
    "sg:website":"www.yourbestselffitness.com",
    "wof:name":"Your Best Self Fitness",
    "wof:placetype":"venue"
},
  "geometry": {"coordinates":[-117.871461,33.664448],"type":"Point"}
}