{
  "type": "Feature",
  "properties": {
    "addr:full":"15791 Rockfield Boulevard Suite L Irvine CA 92618",
    "addr:housenumber":"15791",
    "addr:postcode":"92618",
    "addr:street":"Rockfield Boulevard Suite L",
    "iso:country":"US",
    "sg:address":"15791 Rockfield Boulevard Suite L",
    "sg:city":"Irvine",
    "sg:classifiers":[
        {
            "category":"Retail",
            "subcategory":"Auto Repair",
            "type":"Services"
        }
    ],
    "sg:phone":"+1 949 768 3777",
    "sg:postcode":"92618",
    "sg:province":"CA",
    "wof:name":"Land Rover Unlimited",
    "wof:placetype":"venue"
},
  "geometry": {"coordinates":[-117.72033500000001,33.633446],"type":"Point"}
}