{
  "type": "Feature",
  "properties": {
    "addr:full":"952 Kate Linde Cir Stockton CA 95206",
    "addr:housenumber":"952",
    "addr:postcode":"95206",
    "addr:street":"Kate Linde Cir",
    "iso:country":"US",
    "sg:address":"952 Kate Linde Cir",
    "sg:city":"Stockton",
    "sg:classifiers":[
        {
            "category":"Professional",
            "subcategory":"Engineering",
            "type":"Services"
        },
        {
            "category":"Home & Garden",
            "subcategory":"Building Materials",
            "type":"Retail Goods"
        },
        {
            "category":"Building & Trades",
            "subcategory":"Construction",
            "type":"Services"
        }
    ],
    "sg:phone":"+1 209 982 1050",
    "sg:postcode":"95206",
    "sg:province":"CA",
    "sg:tags":[
        "repair",
        "system",
        "specialty",
        "heating",
        "equipment",
        "contractor",
        "air conditioning"
    ],
    "sg:website":"http://centralvalley.aireserv.com",
    "wof:name":"Aire Serv Of Central Valley",
    "wof:placetype":"venue"
},
  "geometry": {"coordinates":[-121.297754,37.908932],"type":"Point"}
}