{
  "type": "Feature",
  "properties": {
    "acgov:api":"0.0",
    "acgov:type":"Small Schools",
    "addr:full":"7850 Earhart Road Oakland CA",
    "wof:categories":[
        "education_and_religion:education=school"
    ],
    "wof:name":"Oakland Aviation High",
    "wof:placetype":"venue"
},
  "geometry": {"coordinates":[-122.214003159325,37.73322563641151],"type":"Point"}
}