{
  "type": "Feature",
  "properties": {
    "addr:full":"400 W Compton Blvd Gardena CA 90248",
    "addr:housenumber":"400",
    "addr:postcode":"90248",
    "addr:street":"W Compton Blvd",
    "iso:country":"US",
    "sg:address":"400 W Compton Blvd",
    "sg:city":"Gardena",
    "sg:classifiers":[
        {
            "category":"Retail",
            "subcategory":"Auto Rental",
            "type":"Services"
        }
    ],
    "sg:phone":"+1 310 767 5988",
    "sg:postcode":"90248",
    "sg:province":"CA",
    "sg:tags":[
        "home",
        "leasing",
        "motor"
    ],
    "sg:website":"www.moturis.com",
    "wof:name":"Moturis Rv Rentals",
    "wof:placetype":"venue"
},
  "geometry": {"coordinates":[-118.280334,33.894708],"type":"Point"}
}