{
  "type": "Feature",
  "properties": {
    "addr:full":"325 W Cerritos Ave Glendale CA 91204",
    "addr:housenumber":"325",
    "addr:postcode":"91204",
    "addr:street":"W Cerritos Ave",
    "iso:country":"US",
    "sg:address":"325 W Cerritos Ave",
    "sg:city":"Glendale",
    "sg:classifiers":[
        {
            "category":"Shopping",
            "subcategory":"Clothing, Apparel, & Fashions",
            "type":"Retail Goods"
        }
    ],
    "sg:phone":"+1 818 508 9195",
    "sg:postcode":"91204",
    "sg:province":"CA",
    "sg:tags":[
        "men's",
        "clothing",
        "lingerie"
    ],
    "sg:website":"www.andrewchristian.com",
    "wof:name":"Andrew Christian",
    "wof:placetype":"venue"
},
  "geometry": {"coordinates":[-118.25758,34.124784],"type":"Point"}
}