{
  "type": "Feature",
  "properties": {
    "addr:full":"13375 Wheeler Ave Sylmar CA 91342",
    "addr:housenumber":"13375",
    "addr:postcode":"91342",
    "addr:street":"Wheeler Ave",
    "iso:country":"US",
    "sg:address":"13375 Wheeler Ave",
    "sg:city":"Sylmar",
    "sg:classifiers":[
        {
            "category":"Building & Trades",
            "subcategory":"Plumbing",
            "type":"Services"
        }
    ],
    "sg:phone":"+1 818 837 3888",
    "sg:postcode":"91342",
    "sg:province":"CA",
    "sg:tags":[
        "conditioning"
    ],
    "wof:name":"JP Air Conditioning Inc",
    "wof:placetype":"venue"
},
  "geometry": {"coordinates":[-118.43288,34.316152],"type":"Point"}
}