{
  "type": "Feature",
  "properties": {
    "iso:country":"US",
    "sg:address":"790 E Willow St Ste 100",
    "sg:city":"Long Beach",
    "sg:classifiers":[
        {
            "category":"Health Services",
            "subcategory":"Doctor",
            "type":"Services"
        }
    ],
    "sg:phone":"+1 562 595 4014",
    "sg:postcode":"90806",
    "sg:province":"CA",
    "sg:tags":[
        "obstetrician",
        "gynecologist"
    ],
    "wof:name":"Kogan Seth A MD",
    "wof:placetype":"venue"
},
  "geometry": {"coordinates":[-118.182999,33.804199],"type":"Point"}
}