{
  "type": "Feature",
  "properties": {
    "addr:full":"4676 Adolfo Rd Camarillo CA 93012",
    "addr:housenumber":"4676",
    "addr:postcode":"93012",
    "addr:street":"Adolfo Rd",
    "iso:country":"US",
    "sg:address":"4676 Adolfo Rd",
    "sg:city":"Camarillo",
    "sg:classifiers":[
        {
            "category":"Retail",
            "subcategory":"Auto Repair",
            "type":"Services"
        }
    ],
    "sg:phone":"+1 805 383 0088",
    "sg:postcode":"93012",
    "sg:province":"CA",
    "sg:tags":[
        "repairing",
        "automobile"
    ],
    "wof:name":"Hi Tech Auto Care",
    "wof:placetype":"venue"
},
  "geometry": {"coordinates":[-119.002566,34.216939],"type":"Point"}
}