{
  "type": "Feature",
  "properties": {
    "addr:full":"424 W Colorado St Glendale CA 91204",
    "addr:housenumber":"424",
    "addr:postcode":"91204",
    "addr:street":"W Colorado St",
    "iso:country":"US",
    "sg:address":"424 W Colorado St",
    "sg:city":"Glendale",
    "sg:classifiers":[
        {
            "category":"Professional",
            "subcategory":"Accounting & Tax Preparation",
            "type":"Services"
        }
    ],
    "sg:phone":"+1 818 553 3745",
    "sg:postcode":"91204",
    "sg:province":"CA",
    "sg:tags":[
        "bookkeeping",
        "general"
    ],
    "wof:name":"Accuracy",
    "wof:placetype":"venue"
},
  "geometry": {"coordinates":[-118.263621,34.142438],"type":"Point"}
}