{
  "type": "Feature",
  "properties": {
    "iso:country":"US",
    "sg:address":"9632 Emerald Oak Dr",
    "sg:city":"Elk Grove",
    "sg:classifiers":[
        {
            "category":"Food & Beverages",
            "subcategory":"Liquor & Beverages",
            "type":"Retail Goods"
        }
    ],
    "sg:phone":"+1 916 686 7858",
    "sg:postcode":"95624",
    "sg:province":"CA",
    "wof:name":"Discount Food & Liquor",
    "wof:placetype":"venue"
},
  "geometry": {"coordinates":[-121.378934,38.408702],"type":"Point"}
}