{
  "type": "Feature",
  "properties": {
    "addr:full":"740 Ventura Blvd Ste 506 Camarillo CA 93010",
    "addr:housenumber":"740",
    "addr:postcode":"93010",
    "addr:street":"Ventura Blvd Ste 506",
    "iso:country":"US",
    "sg:address":"740 Ventura Blvd Ste 506",
    "sg:city":"Camarillo",
    "sg:classifiers":[
        {
            "category":"Food & Beverages",
            "subcategory":"Candy",
            "type":"Retail Goods"
        }
    ],
    "sg:phone":"+1 805 445 1150",
    "sg:postcode":"93010",
    "sg:province":"CA",
    "sg:tags":[
        "store"
    ],
    "wof:name":"Rocky Mountain Chocolate Factory",
    "wof:placetype":"venue"
},
  "geometry": {"coordinates":[-119.060997,34.217999],"type":"Point"}
}