{
  "type": "Feature",
  "properties": {
    "addr:full":"629 2nd St Orland CA 95963",
    "addr:housenumber":"629",
    "addr:postcode":"95963",
    "addr:street":"2Nd St",
    "iso:country":"US",
    "sg:address":"629 2nd St",
    "sg:city":"Orland",
    "sg:classifiers":[
        {
            "category":"Professional",
            "subcategory":"Lawyer & Legal Services",
            "type":"Services"
        }
    ],
    "sg:phone":"+1 530 865 2960",
    "sg:postcode":"95963",
    "sg:province":"CA",
    "sg:tags":[
        "attorney"
    ],
    "wof:name":"Robert L Benson Law Office",
    "wof:placetype":"venue"
},
  "geometry": {"coordinates":[-122.191356,39.748166],"type":"Point"}
}