{
  "type": "Feature",
  "properties": {
    "iso:country":"US",
    "sg:address":"20646 State Hwy 18",
    "sg:city":"Apple Valley",
    "sg:classifiers":[
        {
            "category":"Organizations",
            "subcategory":"Religious Organization",
            "type":"Services"
        }
    ],
    "sg:phone":"+1 760 961 1006",
    "sg:postcode":"92307",
    "sg:province":"CA",
    "sg:tags":[
        "church"
    ],
    "wof:name":"Apple Valley Seventh Day Advnt",
    "wof:placetype":"venue"
},
  "geometry": {"coordinates":[-117.21051900000001,34.517981],"type":"Point"}
}