{
  "type": "Feature",
  "properties": {
    "addr:full":"641 Broadway St King City CA 93930",
    "addr:housenumber":"641",
    "addr:postcode":"93930",
    "addr:street":"Broadway St",
    "iso:country":"US",
    "sg:address":"641 Broadway St",
    "sg:city":"King City",
    "sg:classifiers":[
        {
            "category":"Real Estate",
            "subcategory":"Real Estate Agent",
            "type":"Services"
        }
    ],
    "sg:phone":"+1 831 385 4084",
    "sg:postcode":"93930",
    "sg:province":"CA",
    "sg:tags":[
        "appraiser"
    ],
    "wof:name":"Bray Enterprises",
    "wof:placetype":"venue"
},
  "geometry": {"coordinates":[-121.13087,36.210243],"type":"Point"}
}