{
  "type": "Feature",
  "properties": {
    "addr:full":"954 Q St Sacramento CA 95811",
    "addr:housenumber":"954",
    "addr:postcode":"95811",
    "addr:street":"Q St",
    "iso:country":"US",
    "sg:address":"954 Q St",
    "sg:city":"Sacramento",
    "sg:classifiers":[
        {
            "category":"Health Services",
            "subcategory":"Doctor",
            "type":"Services"
        }
    ],
    "sg:phone":"+1 916 929 7627",
    "sg:postcode":"95811",
    "sg:province":"CA",
    "sg:tags":[
        "physician",
        "surgeon"
    ],
    "wof:name":"Thomas A Daniel Psychiatry",
    "wof:placetype":"venue"
},
  "geometry": {"coordinates":[-121.497417,38.572695],"type":"Point"}
}