{
  "type": "Feature",
  "properties": {
    "iso:country":"US",
    "sg:address":"1000 Bristol St",
    "sg:city":"Costa Mesa",
    "sg:classifiers":[
        {
            "category":"Shopping",
            "subcategory":"Mobile Phones",
            "type":"Retail Goods"
        }
    ],
    "sg:phone":"+1 949 833 2901",
    "sg:postcode":"92626",
    "sg:province":"CA",
    "sg:website":"www.bellsouth.com",
    "wof:name":"AT&T",
    "wof:placetype":"venue"
},
  "geometry": {"coordinates":[-117.887241,33.671535],"type":"Point"}
}