{
  "type": "Feature",
  "properties": {
    "addr:full":"9701 W Pico Blvd Los Angeles CA 90035",
    "addr:housenumber":"9701",
    "addr:postcode":"90035",
    "addr:street":"W Pico Blvd",
    "iso:country":"US",
    "sg:address":"9701 W Pico Blvd",
    "sg:city":"Los Angeles",
    "sg:classifiers":[
        {
            "category":"Professional",
            "subcategory":"Research",
            "type":"Services"
        }
    ],
    "sg:phone":"+1 310 552 3200",
    "sg:postcode":"90035",
    "sg:province":"CA",
    "sg:tags":[
        "ergonomics"
    ],
    "wof:name":"Humanspace Ergonomics",
    "wof:placetype":"venue"
},
  "geometry": {"coordinates":[-118.39798500000001,34.05515],"type":"Point"}
}