{
  "type": "Feature",
  "properties": {
    "addr:full":"55 Almaden Blvd 7th Floor San Jose CA 95113",
    "addr:housenumber":"55",
    "addr:postcode":"95113",
    "addr:street":"Almaden Blvd 7Th Floor",
    "iso:country":"US",
    "sg:address":"55 Almaden Blvd 7th Floor",
    "sg:city":"San Jose",
    "sg:classifiers":[
        {
            "category":"Professional",
            "type":"Services"
        }
    ],
    "sg:phone":"+1 866 500 9696",
    "sg:postcode":"95113",
    "sg:province":"CA",
    "sg:website":"concentric.com",
    "wof:name":"Concentric Hosting",
    "wof:placetype":"venue"
},
  "geometry": {"coordinates":[-121.894649,37.332918],"type":"Point"}
}