{
  "type": "Feature",
  "properties": {
    "addr:full":"2963 Fulton Ave Sacramento CA 95821",
    "addr:housenumber":"2963",
    "addr:postcode":"95821",
    "addr:street":"Fulton Ave",
    "iso:country":"US",
    "sg:address":"2963 Fulton Ave",
    "sg:city":"Sacramento",
    "sg:classifiers":[
        {
            "category":"Government",
            "subcategory":"Office",
            "type":"Public Place"
        }
    ],
    "sg:phone":"+1 916 979 2075",
    "sg:postcode":"95821",
    "sg:province":"CA",
    "sg:tags":[
        "federal",
        "program"
    ],
    "wof:name":"US Agricultural Marketing Svc",
    "wof:placetype":"venue"
},
  "geometry": {"coordinates":[-121.40148600000001,38.618321],"type":"Point"}
}