{
  "type": "Feature",
  "properties": {
    "addr:full":"20423 Sherman Way Canoga Park CA 91306",
    "addr:housenumber":"20423",
    "addr:postcode":"91306",
    "addr:street":"Sherman Way",
    "iso:country":"US",
    "sg:address":"20423 Sherman Way",
    "sg:city":"Canoga Park",
    "sg:classifiers":[
        {
            "category":"Restaurant",
            "type":"Food & Drink"
        }
    ],
    "sg:phone":"+1 818 347 3211",
    "sg:postcode":"91306",
    "sg:province":"CA",
    "wof:name":"Popeyes Chicken & Biscuits",
    "wof:placetype":"venue"
},
  "geometry": {"coordinates":[-118.57932099999999,34.201013],"type":"Point"}
}