{
  "type": "Feature",
  "properties": {
    "iso:country":"US",
    "sg:address":"20423 Sherman Way",
    "sg:city":"Canoga Park",
    "sg:classifiers":[
        {
            "category":"Restaurant",
            "type":"Food & Drink"
        }
    ],
    "sg:phone":"+1 818 347 3211",
    "sg:postcode":"91306",
    "sg:province":"CA",
    "wof:name":"Popeyes Chicken & Biscuits",
    "wof:placetype":"venue"
},
  "geometry": {"coordinates":[-118.579321,34.201013],"type":"Point"}
}