{
  "type": "Feature",
  "properties": {
    "iso:country":"US",
    "sg:address":"16315 Main St",
    "sg:city":"Guerneville",
    "sg:classifiers":[
        {
            "category":"Real Estate",
            "subcategory":"Real Estate Agent",
            "type":"Services"
        }
    ],
    "sg:phone":"+1 707 217 1786",
    "sg:postcode":"95446",
    "sg:province":"CA",
    "sg:website":"www.davidrmillar.com",
    "wof:name":"David R Millar",
    "wof:placetype":"venue"
},
  "geometry": {"coordinates":[-122.99896699999999,38.501807],"type":"Point"}
}