{
  "type": "Feature",
  "properties": {
    "addr:full":"12041 Sabre Springs Pkwy San Diego CA 92128",
    "addr:housenumber":"12041",
    "addr:postcode":"92128",
    "addr:street":"Sabre Springs Pkwy",
    "iso:country":"US",
    "sg:address":"12041 Sabre Springs Pkwy",
    "sg:city":"San Diego",
    "sg:classifiers":[
        {
            "category":"Professional",
            "subcategory":"Engineering",
            "type":"Services"
        }
    ],
    "sg:phone":"+1 858 748 1080",
    "sg:postcode":"92128",
    "sg:province":"CA",
    "sg:tags":[
        "engineer"
    ],
    "wof:name":"Polytechnica",
    "wof:placetype":"venue"
},
  "geometry": {"coordinates":[-117.08518100000001,32.943636],"type":"Point"}
}