{
  "type": "Feature",
  "properties": {
    "iso:country":"US",
    "sg:address":"712 Main St",
    "sg:city":"Cambria",
    "sg:classifiers":[
        {
            "category":"Shopping",
            "subcategory":"Used Merchandise",
            "type":"Retail Goods"
        }
    ],
    "sg:phone":"+1 805 927 8126",
    "sg:postcode":"93428",
    "sg:province":"CA",
    "sg:tags":[
        "book",
        "rare",
        "dealer"
    ],
    "wof:name":"Jane Coats Books",
    "wof:placetype":"venue"
},
  "geometry": {"coordinates":[-121.099188,35.566577],"type":"Point"}
}