{
  "type": "Feature",
  "properties": {
    "iso:country":"US",
    "sg:address":"41050 Rolling Hills Dr",
    "sg:city":"Aguanga",
    "sg:classifiers":[
        {
            "category":"Professional",
            "subcategory":"Art Services",
            "type":"Services"
        }
    ],
    "sg:phone":"+1 951 763 1500",
    "sg:postcode":"92536",
    "sg:province":"CA",
    "sg:tags":[
        "photographer"
    ],
    "wof:name":"Ace Aerial Photography",
    "wof:placetype":"venue"
},
  "geometry": {"coordinates":[-116.804608,33.517084],"type":"Point"}
}