{
  "type": "Feature",
  "properties": {
    "addr:full":"628 Lynwood St Thousand Oaks CA 91360",
    "addr:housenumber":"628",
    "addr:postcode":"91360",
    "addr:street":"Lynwood St",
    "iso:country":"US",
    "sg:address":"628 Lynwood St",
    "sg:city":"Thousand Oaks",
    "sg:classifiers":[
        {
            "category":"Professional",
            "subcategory":"Art Services",
            "type":"Services"
        }
    ],
    "sg:phone":"+1 805 407 1418",
    "sg:postcode":"91360",
    "sg:province":"CA",
    "sg:tags":[
        "photographer"
    ],
    "wof:name":"Matthew Lenehan Photography",
    "wof:placetype":"venue"
},
  "geometry": {"coordinates":[-118.895392,34.201202],"type":"Point"}
}