{
  "type": "Feature",
  "properties": {
    "iso:country":"US",
    "sg:address":"16 W Mission St",
    "sg:city":"Santa Barbara",
    "sg:classifiers":[
        {
            "category":"Utilities",
            "subcategory":"Telephone",
            "type":"Services"
        }
    ],
    "sg:phone":"+1 805 568 3711",
    "sg:postcode":"93101",
    "sg:province":"CA",
    "sg:tags":[
        "company"
    ],
    "sg:website":"www.earthtel.com",
    "wof:name":"Earth Tel",
    "wof:placetype":"venue"
},
  "geometry": {"coordinates":[-119.71574,34.429963],"type":"Point"}
}