{
  "type": "Feature",
  "properties": {
    "iso:country":"US",
    "sg:address":"400 E 2nd St",
    "sg:city":"Los Angeles",
    "sg:classifiers":[
        {
            "category":"Insurance",
            "subcategory":"Insurance Agent",
            "type":"Services"
        }
    ],
    "sg:phone":"+1 213 626 1547",
    "sg:postcode":"90012",
    "sg:province":"CA",
    "wof:name":"Buna Insurance",
    "wof:placetype":"venue"
},
  "geometry": {"coordinates":[-118.238151,34.047162],"type":"Point"}
}