{
  "type": "Feature",
  "properties": {
    "iso:country":"US",
    "sg:address":"1001 E Florence Ave",
    "sg:city":"Fresno",
    "sg:classifiers":[
        {
            "category":"Education",
            "subcategory":"School",
            "type":"Public Place"
        }
    ],
    "sg:phone":"+1 559 457 2970",
    "sg:postcode":"93706",
    "sg:province":"CA",
    "wof:name":"King Engineering Ctr",
    "wof:placetype":"venue"
},
  "geometry": {"coordinates":[-119.797579,36.717746],"type":"Point"}
}