{
  "type": "Feature",
  "properties": {
    "addr:full":"621 Montara Rd Barstow CA 92311",
    "addr:housenumber":"621",
    "addr:postcode":"92311",
    "addr:street":"Montara Rd",
    "iso:country":"US",
    "sg:address":"621 Montara Rd",
    "sg:city":"Barstow",
    "sg:classifiers":[
        {
            "category":"Retail",
            "subcategory":"Photofinishing",
            "type":"Services"
        }
    ],
    "sg:phone":"+1 760 252 7615",
    "sg:postcode":"92311",
    "sg:province":"CA",
    "sg:tags":[
        "photo",
        "finishing"
    ],
    "wof:name":"One Hour Photo",
    "wof:placetype":"venue"
},
  "geometry": {"coordinates":[-116.9937,34.88164],"type":"Point"}
}