{
  "type": "Feature",
  "properties": {
    "addr:full":"18115 Pitache St Hesperia CA 92345",
    "addr:housenumber":"18115",
    "addr:postcode":"92345",
    "addr:street":"Pitache St",
    "iso:country":"US",
    "sg:address":"18115 Pitache St",
    "sg:city":"Hesperia",
    "sg:classifiers":[
        {
            "category":"Building & Trades",
            "subcategory":"Construction",
            "type":"Services"
        }
    ],
    "sg:phone":"+1 760 947 3700",
    "sg:postcode":"92345",
    "sg:province":"CA",
    "sg:tags":[
        "fire",
        "restoration",
        "damage"
    ],
    "wof:name":"Hamilton Tomes Builder",
    "wof:placetype":"venue"
},
  "geometry": {"coordinates":[-117.267959,34.467111],"type":"Point"}
}