{
  "type": "Feature",
  "properties": {
    "iso:country":"US",
    "sg:address":"107 Arbona Cir N",
    "sg:city":"Sonora",
    "sg:classifiers":[
        {
            "category":"Professional",
            "type":"Services"
        }
    ],
    "sg:phone":"+1 209 533 2037",
    "sg:postcode":"95370",
    "sg:province":"CA",
    "sg:tags":[
        "arts",
        "artist"
    ],
    "wof:name":"Palemone Arts",
    "wof:placetype":"venue"
},
  "geometry": {"coordinates":[-120.395335,37.989272],"type":"Point"}
}