{
  "type": "Feature",
  "properties": {
    "iso:country":"US",
    "sg:address":"3425 Cabrillo Blvd",
    "sg:city":"Los Angeles",
    "sg:classifiers":[
        {
            "category":"Professional",
            "type":"Services"
        }
    ],
    "sg:phone":"+1 310 915 5225",
    "sg:postcode":"90066",
    "sg:province":"CA",
    "wof:name":"Jack Bitton & Asssociates",
    "wof:placetype":"venue"
},
  "geometry": {"coordinates":[-118.44574,34.010443],"type":"Point"}
}