{
  "type": "Feature",
  "properties": {
    "addr:full":"452 N Campus Ave Upland CA 91786",
    "addr:housenumber":"452",
    "addr:postcode":"91786",
    "addr:street":"N Campus Ave",
    "iso:country":"US",
    "sg:address":"452 N Campus Ave",
    "sg:city":"Upland",
    "sg:classifiers":[
        {
            "category":"Communications",
            "subcategory":"Film & Video Production",
            "type":"Services"
        }
    ],
    "sg:phone":"+1 909 949 9939",
    "sg:postcode":"91786",
    "sg:province":"CA",
    "sg:tags":[
        "recording",
        "service-sound"
    ],
    "wof:name":"Joel Paat",
    "wof:placetype":"venue"
},
  "geometry": {"coordinates":[-117.64147699999999,34.099238],"type":"Point"}
}