{
  "type": "Feature",
  "properties": {
    "addr:full":"35813 Carter St Yucaipa CA 92399",
    "addr:housenumber":"35813",
    "addr:postcode":"92399",
    "addr:street":"Carter St",
    "iso:country":"US",
    "sg:address":"35813 Carter St",
    "sg:city":"Yucaipa",
    "sg:classifiers":[
        {
            "category":"Professional",
            "subcategory":"Research",
            "type":"Services"
        }
    ],
    "sg:phone":"+1 909 797 5740",
    "sg:postcode":"92399",
    "sg:province":"CA",
    "sg:tags":[
        "environmental",
        "ecological"
    ],
    "wof:name":"Biological Resource Specialist",
    "wof:placetype":"venue"
},
  "geometry": {"coordinates":[-117.019426,34.062833],"type":"Point"}
}