{
  "type": "Feature",
  "properties": {
    "addr:full":"151 S Doheny Dr Beverly Hills CA 90209",
    "addr:housenumber":"151",
    "addr:postcode":"90209",
    "addr:street":"S Doheny Dr",
    "iso:country":"US",
    "sg:address":"151 S Doheny Dr",
    "sg:city":"Beverly Hills",
    "sg:classifiers":[
        {
            "category":"Restaurant",
            "type":"Food & Drink"
        }
    ],
    "sg:phone":"+1 310 786 7858",
    "sg:postcode":"90209",
    "sg:province":"CA",
    "sg:tags":[
        "pakistani",
        "indian"
    ],
    "wof:name":"Maurya Indian Cuisine",
    "wof:placetype":"venue"
},
  "geometry": {"coordinates":[-118.389999,34.066002],"type":"Point"}
}