{
  "type": "Feature",
  "properties": {
    "addr:full":"2303 Trower Ave Napa CA 94558",
    "addr:housenumber":"2303",
    "addr:postcode":"94558",
    "addr:street":"Trower Ave",
    "iso:country":"US",
    "sg:address":"2303 Trower Ave",
    "sg:city":"Napa",
    "sg:classifiers":[
        {
            "category":"Organizations",
            "subcategory":"Religious Organization",
            "type":"Services"
        }
    ],
    "sg:phone":"+1 707 252 2100",
    "sg:postcode":"94558",
    "sg:province":"CA",
    "sg:tags":[
        "church"
    ],
    "sg:website":"www.napavalleybaptist.org",
    "wof:name":"Napa Valley Baptist Church",
    "wof:placetype":"venue"
},
  "geometry": {"coordinates":[-122.322951,38.327547],"type":"Point"}
}