{
  "type": "Feature",
  "properties": {
    "addr:full":"6049 E 7th St Long Beach CA 90804",
    "addr:housenumber":"6049",
    "addr:postcode":"90804",
    "addr:street":"E 7Th St",
    "iso:country":"US",
    "sg:address":"6049 E 7th St",
    "sg:city":"Long Beach",
    "sg:classifiers":[
        {
            "category":"Organizations",
            "subcategory":"Non-profit Organization",
            "type":"Services"
        }
    ],
    "sg:phone":"+1 562 985 4138",
    "sg:postcode":"90804",
    "sg:province":"CA",
    "sg:website":"www.shopthebeach.com",
    "wof:name":"Forty-Niner Shops Inc",
    "wof:placetype":"venue"
},
  "geometry": {"coordinates":[-118.117715,33.775243],"type":"Point"}
}