{
  "type": "Feature",
  "properties": {
    "iso:country":"US",
    "sg:address":"14641 Pavo Ct",
    "sg:city":"Victorville",
    "sg:classifiers":[
        {
            "category":"Building & Trades",
            "subcategory":"Plumbing",
            "type":"Services"
        }
    ],
    "sg:phone":"+1 760 955 1904",
    "sg:postcode":"92394",
    "sg:province":"CA",
    "sg:tags":[
        "contractor"
    ],
    "wof:name":"Mike Shine Plumbing",
    "wof:placetype":"venue"
},
  "geometry": {"coordinates":[-117.345244,34.548972],"type":"Point"}
}