{
  "type": "Feature",
  "properties": {
    "iso:country":"US",
    "sg:address":"275 Walnut Ave",
    "sg:city":"Holtville",
    "sg:classifiers":[
        {
            "category":"Wholesale",
            "subcategory":"Fruits & Vegetables",
            "type":"Manufacturing & Wholesale Goods"
        }
    ],
    "sg:phone":"+1 760 356 4567",
    "sg:postcode":"92250",
    "sg:province":"CA",
    "sg:tags":[
        "shipper"
    ],
    "wof:name":"William Bolthouse Farms Inc",
    "wof:placetype":"venue"
},
  "geometry": {"coordinates":[-115.376503,32.80662],"type":"Point"}
}