{
  "type": "Feature",
  "properties": {
    "addr:full":"113 W Las Tunas Dr Ste 203 San Gabriel CA 91775",
    "addr:housenumber":"113",
    "addr:postcode":"91775",
    "addr:street":"W Las Tunas Dr Ste 203",
    "iso:country":"US",
    "sg:address":"113 W Las Tunas Dr Ste 203",
    "sg:city":"San Gabriel",
    "sg:classifiers":[
        {
            "category":"Professional",
            "type":"Services"
        },
        {
            "category":"Banks & Credit Unions",
            "subcategory":"Financial Services",
            "type":"Services"
        }
    ],
    "sg:phone":"+1 626 287 1188",
    "sg:postcode":"91775",
    "sg:province":"CA",
    "sg:tags":[
        "advising"
    ],
    "sg:website":"www.solidrockdebt.com",
    "wof:name":"Solid Rock Debt Services Center, LLC",
    "wof:placetype":"venue"
},
  "geometry": {"coordinates":[-118.100505,34.103091],"type":"Point"}
}