{
  "type": "Feature",
  "properties": {
    "addr:full":"19732 Colima Rd Rowland Heights CA 91748",
    "addr:housenumber":"19732",
    "addr:postcode":"91748",
    "addr:street":"Colima Rd",
    "iso:country":"US",
    "sg:address":"19732 Colima Rd",
    "sg:city":"Rowland Heights",
    "sg:classifiers":[
        {
            "category":"Real Estate",
            "subcategory":"Real Estate Agent",
            "type":"Services"
        }
    ],
    "sg:phone":"+1 909 598 0660",
    "sg:postcode":"91748",
    "sg:province":"CA",
    "sg:website":"www.presidentialinc.com",
    "wof:name":"Presidential Real Estate",
    "wof:placetype":"venue"
},
  "geometry": {"coordinates":[-117.870671,33.986325],"type":"Point"}
}