{
  "type": "Feature",
  "properties": {
    "iso:country":"US",
    "sg:address":"3725 Sundale Rd",
    "sg:city":"Lafayette",
    "sg:classifiers":[
        {
            "category":"Manufacturing",
            "subcategory":"Buildings",
            "type":"Manufacturing & Wholesale Goods"
        },
        {
            "category":"Building & Trades",
            "subcategory":"Construction",
            "type":"Services"
        }
    ],
    "sg:phone":"+1 925 299 2938",
    "sg:postcode":"94549",
    "sg:province":"CA",
    "sg:tags":[
        "home",
        "builder",
        "industrial",
        "contractors-commercial",
        "contractor"
    ],
    "wof:name":"Build Tech Construction Co.",
    "wof:placetype":"venue"
},
  "geometry": {"coordinates":[-122.131145,37.88715],"type":"Point"}
}