{
  "type": "Feature",
  "properties": {
    "iso:country":"US",
    "sg:address":"25301 Cabot Rd",
    "sg:city":"Laguna Hills",
    "sg:classifiers":[
        {
            "category":"Professional",
            "subcategory":"Employment Agencies",
            "type":"Services"
        }
    ],
    "sg:phone":"+1 949 586 2342",
    "sg:postcode":"92653",
    "sg:province":"CA",
    "sg:tags":[
        "opportunity"
    ],
    "wof:name":"Adecco",
    "wof:placetype":"venue"
},
  "geometry": {"coordinates":[-117.67460699999999,33.591833],"type":"Point"}
}