{
  "type": "Feature",
  "properties": {
    "iso:country":"US",
    "sg:address":"244 Hillsdale Ave",
    "sg:city":"San Jose",
    "sg:classifiers":[
        {
            "category":"Manufacturing",
            "subcategory":"Tools & Machinery",
            "type":"Manufacturing & Wholesale Goods"
        }
    ],
    "sg:phone":"+1 408 264 2045",
    "sg:postcode":"95136",
    "sg:province":"CA",
    "sg:tags":[
        "machine",
        "shop"
    ],
    "wof:name":"G W Precision",
    "wof:placetype":"venue"
},
  "geometry": {"coordinates":[-121.84918999999999,37.280481],"type":"Point"}
}