{
  "type": "Feature",
  "properties": {
    "addr:full":"1923 Micheltorena St Los Angeles CA 90039",
    "addr:housenumber":"1923",
    "addr:postcode":"90039",
    "addr:street":"Micheltorena St",
    "iso:country":"US",
    "sg:address":"1923 Micheltorena St",
    "sg:city":"Los Angeles",
    "sg:classifiers":[
        {
            "category":"Home & Garden",
            "subcategory":"Home Furnishings",
            "type":"Retail Goods"
        }
    ],
    "sg:phone":"+1 323 933 9100",
    "sg:postcode":"90039",
    "sg:province":"CA",
    "sg:tags":[
        "pillow"
    ],
    "wof:name":"Odalisque",
    "wof:placetype":"venue"
},
  "geometry": {"coordinates":[-118.271038,34.095632],"type":"Point"}
}