{
  "type": "Feature",
  "properties": {
    "iso:country":"US",
    "sg:address":"676 Vermont St",
    "sg:city":"Gridley",
    "sg:classifiers":[
        {
            "category":"Building & Trades",
            "subcategory":"Construction",
            "type":"Services"
        }
    ],
    "sg:phone":"+1 530 846 0602",
    "sg:postcode":"95948",
    "sg:province":"CA",
    "sg:tags":[
        "insulation",
        "heat",
        "contractor"
    ],
    "wof:name":"Residential Wall Insulation",
    "wof:placetype":"venue"
},
  "geometry": {"coordinates":[-121.69907000000001,39.364405],"type":"Point"}
}