{
  "type": "Feature",
  "properties": {
    "iso:country":"US",
    "sg:address":"8705 Truxton Ave",
    "sg:city":"Los Angeles",
    "sg:classifiers":[
        {
            "category":"Wholesale",
            "subcategory":"Durable Goods & Equipment",
            "type":"Manufacturing & Wholesale Goods"
        }
    ],
    "sg:phone":"+1 310 337 1283",
    "sg:postcode":"90045",
    "sg:province":"CA",
    "wof:name":"Global Industrial Supply",
    "wof:placetype":"venue"
},
  "geometry": {"coordinates":[-118.393227,33.958256],"type":"Point"}
}