{
  "type": "Feature",
  "properties": {
    "addr:full":"10741 Sherman Way Sun Valley CA 91352",
    "addr:housenumber":"10741",
    "addr:postcode":"91352",
    "addr:street":"Sherman Way",
    "iso:country":"US",
    "sg:address":"10741 Sherman Way",
    "sg:city":"Sun Valley",
    "sg:classifiers":[
        {
            "category":"Shopping",
            "subcategory":"Shoes",
            "type":"Retail Goods"
        }
    ],
    "sg:phone":"+1 818 764 6778",
    "sg:postcode":"91352",
    "sg:province":"CA",
    "sg:tags":[
        "store"
    ],
    "wof:name":"Red Kiss Footwear",
    "wof:placetype":"venue"
},
  "geometry": {"coordinates":[-118.364271,34.201347],"type":"Point"}
}