{
  "type": "Feature",
  "properties": {
    "addr:full":"2121 41st Avenue, Suite 202 Capitola CA 95010",
    "addr:housenumber":"2121",
    "addr:postcode":"95010",
    "addr:street":"41St Avenue Suite 202",
    "iso:country":"US",
    "sg:address":"2121 41st Avenue, Suite 202",
    "sg:city":"Capitola",
    "sg:classifiers":[
        {
            "category":"Professional",
            "subcategory":"Management & Consulting",
            "type":"Services"
        },
        {
            "category":"Personal",
            "type":"Services"
        },
        {
            "category":"Education",
            "subcategory":"School",
            "type":"Public Place"
        }
    ],
    "sg:phone":"+1 831 464 2378",
    "sg:postcode":"95010",
    "sg:province":"CA",
    "sg:tags":[
        "consultant",
        "educational",
        "local"
    ],
    "sg:website":"www.simplyyourbest.com",
    "wof:name":"Simply Your Best",
    "wof:placetype":"venue"
},
  "geometry": {"coordinates":[-121.965003,36.97963],"type":"Point"}
}