{
  "type": "Feature",
  "properties": {
    "iso:country":"US",
    "sg:address":"896 E Foster Rd",
    "sg:city":"Santa Maria",
    "sg:classifiers":[
        {
            "category":"Professional",
            "subcategory":"Detective & Security Services",
            "type":"Services"
        }
    ],
    "sg:phone":"+1 805 934 5911",
    "sg:postcode":"93455",
    "sg:province":"CA",
    "sg:tags":[
        "guard",
        "patrol"
    ],
    "wof:name":"Venco Security Patrol",
    "wof:placetype":"venue"
},
  "geometry": {"coordinates":[-120.423163,34.883023],"type":"Point"}
}