{
  "type": "Feature",
  "properties": {
    "addr:full":"900 Veterans Blvd Redwood City CA 94063",
    "addr:housenumber":"900",
    "addr:postcode":"94063",
    "addr:street":"Veterans Blvd",
    "iso:country":"US",
    "sg:address":"900 Veterans Blvd",
    "sg:city":"Redwood City",
    "sg:classifiers":[
        {
            "category":"Professional",
            "subcategory":"Lawyer & Legal Services",
            "type":"Services"
        }
    ],
    "sg:phone":"+1 650 368 4662",
    "sg:postcode":"94063",
    "sg:province":"CA",
    "sg:tags":[
        "attorney"
    ],
    "wof:name":"Aaron Riechert Carpol & Riffle",
    "wof:placetype":"venue"
},
  "geometry": {"coordinates":[-122.22735,37.490131],"type":"Point"}
}