{
  "type": "Feature",
  "properties": {
    "iso:country":"US",
    "sg:address":"516 Saint Vincent Ln",
    "sg:city":"San Mateo",
    "sg:classifiers":[
        {
            "category":"Government",
            "subcategory":"Office",
            "type":"Public Place"
        }
    ],
    "sg:phone":"+1 650 570 2292",
    "sg:postcode":"94404",
    "sg:province":"CA",
    "sg:tags":[
        "national",
        "security"
    ],
    "wof:name":"Airforce Reserves",
    "wof:placetype":"venue"
},
  "geometry": {"coordinates":[-122.264481,37.536752],"type":"Point"}
}