{
  "type": "Feature",
  "properties": {
    "iso:country":"US",
    "sg:address":"205 E Hill Dr",
    "sg:city":"San Bernardino",
    "sg:classifiers":[
        {
            "category":"Freight",
            "type":"Transportation"
        }
    ],
    "sg:phone":"+1 909 882 0151",
    "sg:postcode":"92404",
    "sg:province":"CA",
    "sg:tags":[
        "operator",
        "local",
        "trucking"
    ],
    "wof:name":"Thompson Transportation Svc",
    "wof:placetype":"venue"
},
  "geometry": {"coordinates":[-117.281712,34.177016],"type":"Point"}
}