{
  "type": "Feature",
  "properties": {
    "addr:full":"586 N. 1st St. #215 San Jose CA 95112",
    "addr:housenumber":"586",
    "addr:postcode":"95112",
    "addr:street":"N. 1St St. # 215",
    "iso:country":"US",
    "sg:address":"586 N. 1st St. #215",
    "sg:city":"San Jose",
    "sg:classifiers":[
        {
            "category":"Professional",
            "subcategory":"Computer Services",
            "type":"Services"
        }
    ],
    "sg:phone":"+1 408 728 8141",
    "sg:postcode":"95112",
    "sg:province":"CA",
    "sg:tags":[
        "repair"
    ],
    "sg:website":"www.elysiumsolutions.com",
    "wof:name":"Elysium Solutions LLC",
    "wof:placetype":"venue"
},
  "geometry": {"coordinates":[-121.89796,37.346729],"type":"Point"}
}