{
  "type": "Feature",
  "properties": {
    "addr:full":"944 Market St San Francisco CA 94102",
    "addr:housenumber":"944",
    "addr:postcode":"94102",
    "addr:street":"Market St",
    "iso:country":"US",
    "sg:address":"944 Market St",
    "sg:city":"San Francisco",
    "sg:classifiers":[
        {
            "category":"Professional",
            "subcategory":"Lawyer & Legal Services",
            "type":"Services"
        }
    ],
    "sg:phone":"+1 415 362 4344",
    "sg:postcode":"94102",
    "sg:province":"CA",
    "sg:tags":[
        "attorney"
    ],
    "wof:name":"Elisabeth Wolter Law Ofc",
    "wof:placetype":"venue"
},
  "geometry": {"coordinates":[-122.408164,37.784048],"type":"Point"}
}