{
  "type": "Feature",
  "properties": {
    "addr:full":"136 S Main St Bishop CA 93514",
    "addr:housenumber":"136",
    "addr:postcode":"93514",
    "addr:street":"S Main St",
    "iso:country":"US",
    "sg:address":"136 S Main St",
    "sg:city":"Bishop",
    "sg:classifiers":[
        {
            "category":"Professional",
            "subcategory":"Accounting & Tax Preparation",
            "type":"Services"
        }
    ],
    "sg:phone":"+1 760 872 1090",
    "sg:postcode":"93514",
    "sg:province":"CA",
    "sg:tags":[
        "bookkeeping",
        "general"
    ],
    "wof:name":"Joann Stotlz Tax & Business",
    "wof:placetype":"venue"
},
  "geometry": {"coordinates":[-118.395205,37.361081],"type":"Point"}
}