{
  "type": "Feature",
  "properties": {
    "iso:country":"US",
    "sg:address":"789 23rd St",
    "sg:city":"Richmond",
    "sg:classifiers":[
        {
            "category":"Shopping",
            "subcategory":"Jewelry",
            "type":"Retail Goods"
        }
    ],
    "sg:phone":"+1 510 234 5880",
    "sg:postcode":"94804",
    "sg:province":"CA",
    "sg:tags":[
        "jeweler"
    ],
    "wof:name":"Bravo's Joyeria",
    "wof:placetype":"venue"
},
  "geometry": {"coordinates":[-122.34754599999999,37.943742],"type":"Point"}
}