{
  "type": "Feature",
  "properties": {
    "addr:full":"13210 S Normandie Ave Gardena CA 90249",
    "addr:housenumber":"13210",
    "addr:postcode":"90249",
    "addr:street":"S Normandie Ave",
    "iso:country":"US",
    "sg:address":"13210 S Normandie Ave",
    "sg:city":"Gardena",
    "sg:classifiers":[
        {
            "category":"Retail",
            "subcategory":"Auto Repair",
            "type":"Services"
        }
    ],
    "sg:phone":"+1 310 327 1340",
    "sg:postcode":"90249",
    "sg:province":"CA",
    "wof:name":"Prime Automotive Group",
    "wof:placetype":"venue"
},
  "geometry": {"coordinates":[-118.300234,33.912547],"type":"Point"}
}