{
  "type": "Feature",
  "properties": {
    "addr:full":"7363 Atoll Ave North Hollywood CA 91605",
    "addr:housenumber":"7363",
    "addr:postcode":"91605",
    "addr:street":"Atoll Ave",
    "iso:country":"US",
    "sg:address":"7363 Atoll Ave",
    "sg:city":"North Hollywood",
    "sg:classifiers":[
        {
            "category":"Manufacturing",
            "subcategory":"Building Materials",
            "type":"Manufacturing & Wholesale Goods"
        },
        {
            "category":"Building & Trades",
            "subcategory":"Construction",
            "type":"Services"
        }
    ],
    "sg:phone":"+1 818 765 0708",
    "sg:postcode":"91605",
    "sg:province":"CA",
    "sg:tags":[
        "mfg",
        "contractor",
        "wood",
        "carpentry",
        "cabinet",
        "maker",
        "kitchen"
    ],
    "wof:name":"Elegant Design Woodwork",
    "wof:placetype":"venue"
},
  "geometry": {"coordinates":[-118.421125,34.20445],"type":"Point"}
}