{
  "type": "Feature",
  "properties": {
    "addr:full":"305 N 2nd Ave Upland CA 91786",
    "addr:housenumber":"305",
    "addr:postcode":"91786",
    "addr:street":"N 2Nd Ave",
    "iso:country":"US",
    "sg:address":"305 N 2nd Ave",
    "sg:city":"Upland",
    "sg:classifiers":[
        {
            "category":"Building & Trades",
            "subcategory":"Landscaping Services",
            "type":"Services"
        }
    ],
    "sg:phone":"+1 909 982 0782",
    "sg:postcode":"91786",
    "sg:province":"CA",
    "sg:tags":[
        "landscape",
        "contractor"
    ],
    "wof:name":"Groundskeeper",
    "wof:placetype":"venue"
},
  "geometry": {"coordinates":[-117.648504,34.097875],"type":"Point"}
}