{
  "type": "Feature",
  "properties": {
    "addr:full":"12669 Auberry Rd Clovis CA 93619",
    "addr:housenumber":"12669",
    "addr:postcode":"93619",
    "addr:street":"Auberry Rd",
    "iso:country":"US",
    "sg:address":"12669 Auberry Rd",
    "sg:city":"Clovis",
    "sg:classifiers":[
        {
            "category":"Banks & Credit Unions",
            "subcategory":"Investment Brokerage",
            "type":"Services"
        }
    ],
    "sg:phone":"+1 559 298 4999",
    "sg:postcode":"93619",
    "sg:province":"CA",
    "sg:tags":[
        "trust"
    ],
    "wof:name":"Cj Bennett Family Trust Of 198",
    "wof:placetype":"venue"
},
  "geometry": {"coordinates":[-119.713087,36.919415],"type":"Point"}
}