{
  "type": "Feature",
  "properties": {
    "addr:full":"1926 S Pacific Coast Hwy Suite 112 Redondo Beach CA 90277",
    "addr:housenumber":"1926",
    "addr:postcode":"90277",
    "addr:street":"S Pacific Coast Hwy Suite 112",
    "iso:country":"US",
    "sg:address":"1926 S Pacific Coast Hwy Suite 112",
    "sg:city":"Redondo Beach",
    "sg:classifiers":[
        {
            "category":"Insurance",
            "subcategory":"Health Insurance",
            "type":"Services"
        }
    ],
    "sg:phone":"+1 310 944 3200",
    "sg:postcode":"90277",
    "sg:province":"CA",
    "sg:tags":[
        "market"
    ],
    "wof:name":"Sea Breeze Medical Supply",
    "wof:placetype":"venue"
},
  "geometry": {"coordinates":[-118.37918999999999,33.816191],"type":"Point"}
}