{
  "type": "Feature",
  "properties": {
    "addr:full":"21850 Oxnard Street Lobby of Marriott Warner Center Woodland Hills CA 91367",
    "addr:housenumber":"21850",
    "addr:postcode":"91367",
    "addr:street":"Oxnard Street",
    "iso:country":"US",
    "sg:address":"21850 Oxnard Street Lobby of Marriott Warner Center",
    "sg:city":"Woodland Hills",
    "sg:classifiers":[
        {
            "category":"Coffee & Tea",
            "type":"Food & Drink"
        }
    ],
    "sg:postcode":"91367",
    "sg:province":"CA",
    "sg:website":"www.starbucks.com",
    "wof:name":"Starbucks",
    "wof:placetype":"venue"
},
  "geometry": {"coordinates":[-118.603601,34.178496],"type":"Point"}
}