{
  "type": "Feature",
  "properties": {
    "addr:full":"1480 Foothill Blvd La Verne CA 91750",
    "addr:housenumber":"1480",
    "addr:postcode":"91750",
    "addr:street":"Foothill Blvd",
    "iso:country":"US",
    "sg:address":"1480 Foothill Blvd",
    "sg:city":"La Verne",
    "sg:classifiers":[
        {
            "category":"Shopping",
            "subcategory":"Pharmacy",
            "type":"Retail Goods"
        }
    ],
    "sg:phone":"+1 909 593 2619",
    "sg:postcode":"91750",
    "sg:province":"CA",
    "wof:name":"Rite Aid Pharmacy",
    "wof:placetype":"venue"
},
  "geometry": {"coordinates":[-117.77527600000001,34.116607],"type":"Point"}
}