{
  "type": "Feature",
  "properties": {
    "addr:full":"1140 Pitt School Rd Dixon CA 95620",
    "addr:housenumber":"1140",
    "addr:postcode":"95620",
    "addr:street":"Pitt School Rd",
    "iso:country":"US",
    "sg:address":"1140 Pitt School Rd",
    "sg:city":"Dixon",
    "sg:classifiers":[
        {
            "category":"Retail",
            "subcategory":"Laundry & Dry Cleaning",
            "type":"Services"
        }
    ],
    "sg:phone":"+1 707 678 5334",
    "sg:postcode":"95620",
    "sg:province":"CA",
    "sg:tags":[
        "cleaners",
        "rug",
        "carpet"
    ],
    "wof:name":"Heaven's Best Carpet Cleaning",
    "wof:placetype":"venue"
},
  "geometry": {"coordinates":[-121.84085399999999,38.456485],"type":"Point"}
}