{
  "type": "Feature",
  "properties": {
    "iso:country":"US",
    "sg:address":"16147 Pebble Beach Ln",
    "sg:city":"Chino Hills",
    "sg:classifiers":[
        {
            "category":"Sports & Exercise",
            "subcategory":"Gym",
            "type":"Entertainment"
        }
    ],
    "sg:phone":"+1 909 393 0404",
    "sg:postcode":"91709",
    "sg:province":"CA",
    "sg:tags":[
        "spa",
        "health"
    ],
    "wof:name":"Magic Fingers",
    "wof:placetype":"venue"
},
  "geometry": {"coordinates":[-117.715918,33.959331],"type":"Point"}
}