{
  "type": "Feature",
  "properties": {
    "iso:country":"US",
    "sg:address":"981 E Quincy Ave",
    "sg:city":"Fresno",
    "sg:classifiers":[
        {
            "category":"Building & Trades",
            "subcategory":"Construction",
            "type":"Services"
        }
    ],
    "sg:phone":"+1 559 440 9915",
    "sg:postcode":"93720",
    "sg:province":"CA",
    "sg:tags":[
        "fence",
        "contractor"
    ],
    "wof:name":"Yard Dogs",
    "wof:placetype":"venue"
},
  "geometry": {"coordinates":[-119.766685,36.856717],"type":"Point"}
}