{
  "type": "Feature",
  "properties": {
    "iso:country":"US",
    "sg:address":"11812 La Costa Ct",
    "sg:city":"Yucaipa",
    "sg:classifiers":[
        {
            "category":"Building & Trades",
            "subcategory":"Cleaning & Sanitation",
            "type":"Services"
        },
        {
            "category":"Building & Trades",
            "subcategory":"Construction",
            "type":"Services"
        }
    ],
    "sg:phone":"+1 909 790 2045",
    "sg:postcode":"92399",
    "sg:province":"CA",
    "sg:tags":[
        "cleaner",
        "pool",
        "contractor"
    ],
    "wof:name":"Rhodes Custom Pools",
    "wof:placetype":"venue"
},
  "geometry": {"coordinates":[-117.079668,34.039212],"type":"Point"}
}