{
  "type": "Feature",
  "properties": {
    "iso:country":"US",
    "sg:address":"7506 Whisperwillow Dr",
    "sg:city":"Sacramento",
    "sg:classifiers":[
        {
            "category":"Building & Trades",
            "subcategory":"Construction",
            "type":"Services"
        }
    ],
    "sg:phone":"+1 916 803 0500",
    "sg:postcode":"95828",
    "sg:province":"CA",
    "sg:tags":[
        "general",
        "contractor"
    ],
    "wof:name":"Platinum Home Inspection",
    "wof:placetype":"venue"
},
  "geometry": {"coordinates":[-121.419845,38.482037],"type":"Point"}
}