{
  "type": "Feature",
  "properties": {
    "iso:country":"US",
    "sg:address":"19181 McCarthy Ln",
    "sg:city":"Yorba Linda",
    "sg:classifiers":[
        {
            "category":"Professional",
            "subcategory":"Business Services",
            "type":"Services"
        }
    ],
    "sg:phone":"+1 714 779 7877",
    "sg:postcode":"92886",
    "sg:province":"CA",
    "wof:name":"Casco Communications Inc",
    "wof:placetype":"venue"
},
  "geometry": {"coordinates":[-117.799597,33.881375],"type":"Point"}
}