{
  "type": "Feature",
  "properties": {
    "addr:full":"19181 McCarthy Ln Yorba Linda CA 92886",
    "addr:housenumber":"19181",
    "addr:postcode":"92886",
    "addr:street":"Mccarthy Ln",
    "iso:country":"US",
    "sg:address":"19181 McCarthy Ln",
    "sg:city":"Yorba Linda",
    "sg:classifiers":[
        {
            "category":"Professional",
            "subcategory":"Business Services",
            "type":"Services"
        }
    ],
    "sg:phone":"+1 714 779 7877",
    "sg:postcode":"92886",
    "sg:province":"CA",
    "wof:name":"Casco Communications Inc",
    "wof:placetype":"venue"
},
  "geometry": {"coordinates":[-117.79959700000001,33.881375],"type":"Point"}
}