{
  "type": "Feature",
  "properties": {
    "addr:full":"2475 N Garey Ave Pomona CA 91767",
    "addr:housenumber":"2475",
    "addr:postcode":"91767",
    "addr:street":"N Garey Ave",
    "iso:country":"US",
    "sg:address":"2475 N Garey Ave",
    "sg:city":"Pomona",
    "sg:classifiers":[
        {
            "category":"Health Services",
            "subcategory":"Doctor",
            "type":"Services"
        }
    ],
    "sg:phone":"+1 909 596 9997",
    "sg:postcode":"91767",
    "sg:province":"CA",
    "sg:tags":[
        "physician",
        "surgeon"
    ],
    "sg:website":"www.gambrohealthcare.com",
    "wof:name":"Gambro Healthcare",
    "wof:placetype":"venue"
},
  "geometry": {"coordinates":[-117.748885,34.09107],"type":"Point"}
}