{
  "type": "Feature",
  "properties": {
    "iso:country":"US",
    "sg:address":"2560 Young Ave",
    "sg:city":"Thousand Oaks",
    "sg:classifiers":[
        {
            "category":"Wholesale",
            "subcategory":"Computers",
            "type":"Manufacturing & Wholesale Goods"
        }
    ],
    "sg:phone":"+1 805 492 5045",
    "sg:postcode":"91360",
    "sg:province":"CA",
    "sg:tags":[
        "peripheral",
        "retail",
        "ergonomic"
    ],
    "wof:name":"Dmb Ergonomics",
    "wof:placetype":"venue"
},
  "geometry": {"coordinates":[-118.877522,34.214048],"type":"Point"}
}