{
  "type": "Feature",
  "properties": {
    "iso:country":"US",
    "sg:address":"202 Newport Center Dr",
    "sg:city":"Newport Beach",
    "sg:classifiers":[
        {
            "category":"Restaurant",
            "type":"Food & Drink"
        }
    ],
    "sg:phone":"+1 949 640 4110",
    "sg:postcode":"92660",
    "sg:province":"CA",
    "sg:tags":[
        "bar"
    ],
    "wof:name":"Muldoons A Dublin Pub",
    "wof:placetype":"venue"
},
  "geometry": {"coordinates":[-117.87515500000001,33.612549],"type":"Point"}
}