{
  "type": "Feature",
  "properties": {
    "addr:full":"9838 Lincoln Village Dr # 83 Sacramento CA 95827",
    "addr:housenumber":"9838",
    "addr:postcode":"95827",
    "addr:street":"Lincoln Village Dr # 83",
    "iso:country":"US",
    "sg:address":"9838 Lincoln Village Dr # 83",
    "sg:city":"Sacramento",
    "sg:classifiers":[
        {
            "category":"Shopping",
            "type":"Retail Goods"
        }
    ],
    "sg:phone":"+1 916 541 6069",
    "sg:postcode":"95827",
    "sg:province":"CA",
    "sg:tags":[
        "merchandising"
    ],
    "wof:name":"Specialty Rmfcted Grn Car",
    "wof:placetype":"venue"
},
  "geometry": {"coordinates":[-121.330685,38.561769],"type":"Point"}
}