{
  "type": "Feature",
  "properties": {
    "iso:country":"US",
    "sg:address":"67625 Ovante Rd",
    "sg:city":"Cathedral City",
    "sg:classifiers":[
        {
            "category":"Building & Trades",
            "subcategory":"Cleaning & Sanitation",
            "type":"Services"
        }
    ],
    "sg:phone":"+1 760 327 9396",
    "sg:postcode":"92234",
    "sg:province":"CA",
    "sg:tags":[
        "janitor"
    ],
    "wof:name":"Experts Cleaning Svc",
    "wof:placetype":"venue"
},
  "geometry": {"coordinates":[-116.478858,33.847399],"type":"Point"}
}