{
  "type": "Feature",
  "properties": {
    "addr:full":"442 Main St Placerville CA 95667",
    "addr:housenumber":"442",
    "addr:postcode":"95667",
    "addr:street":"Main St",
    "iso:country":"US",
    "sg:address":"442 Main St",
    "sg:city":"Placerville",
    "sg:classifiers":[
        {
            "category":"Shopping",
            "subcategory":"Used Merchandise",
            "type":"Retail Goods"
        }
    ],
    "sg:phone":"+1 530 622 7901",
    "sg:postcode":"95667",
    "sg:province":"CA",
    "wof:name":"Consign-It of Placerville",
    "wof:placetype":"venue"
},
  "geometry": {"coordinates":[-120.800483,38.729211],"type":"Point"}
}