{
  "type": "Feature",
  "properties": {
    "iso:country":"US",
    "sg:address":"638 Camino De Los Mares",
    "sg:city":"San Clemente",
    "sg:classifiers":[
        {
            "category":"Restaurant",
            "type":"Food & Drink"
        }
    ],
    "sg:menulink":"http://www.allmenus.com/ca/south-coast/149804-subway/menu/",
    "sg:phone":"+1 949 488 3090",
    "sg:postcode":"92673",
    "sg:province":"CA",
    "sg:tags":[
        "american",
        "sandwich"
    ],
    "wof:name":"Subway",
    "wof:placetype":"venue"
},
  "geometry": {"coordinates":[-117.651365,33.459056],"type":"Point"}
}