{
  "type": "Feature",
  "properties": {
    "addr:full":"333 S Farrell Dr Palm Springs CA 92262",
    "addr:housenumber":"333",
    "addr:postcode":"92262",
    "addr:street":"S Farrell Dr",
    "iso:country":"US",
    "sg:address":"333 S Farrell Dr",
    "sg:city":"Palm Springs",
    "sg:classifiers":[
        {
            "category":"Education",
            "subcategory":"School",
            "type":"Public Place"
        },
        {
            "category":"Education",
            "subcategory":"University",
            "type":"Public Place"
        }
    ],
    "sg:phone":"+1 760 416 8450",
    "sg:postcode":"92262",
    "sg:province":"CA",
    "sg:tags":[
        "high",
        "middle",
        "college",
        "elementary"
    ],
    "wof:name":"Palm Springs Unified School District",
    "wof:placetype":"venue"
},
  "geometry": {"coordinates":[-116.518165,33.818958],"type":"Point"}
}