{
  "type": "Feature",
  "properties": {
    "addr:full":"10341 Parkview Ave Westminster CA 92683",
    "addr:housenumber":"10341",
    "addr:postcode":"92683",
    "addr:street":"Parkview Ave",
    "iso:country":"US",
    "sg:address":"10341 Parkview Ave",
    "sg:city":"Westminster",
    "sg:classifiers":[
        {
            "category":"Wholesale",
            "subcategory":"Wine & Distilled Alcoholic Beverages",
            "type":"Manufacturing & Wholesale Goods"
        }
    ],
    "sg:phone":"+1 714 839 3648",
    "sg:postcode":"92683",
    "sg:province":"CA",
    "sg:tags":[
        "liquors-wholesale"
    ],
    "wof:name":"B And B Liquors",
    "wof:placetype":"venue"
},
  "geometry": {"coordinates":[-117.951072,33.750385],"type":"Point"}
}