{
  "type": "Feature",
  "properties": {
    "addr:full":"5545 Merchant Cir Placerville CA 95667",
    "addr:housenumber":"5545",
    "addr:postcode":"95667",
    "addr:street":"Merchant Cir",
    "iso:country":"US",
    "sg:address":"5545 Merchant Cir",
    "sg:city":"Placerville",
    "sg:classifiers":[
        {
            "category":"Freight",
            "type":"Transportation"
        }
    ],
    "sg:phone":"+1 530 626 0240",
    "sg:postcode":"95667",
    "sg:province":"CA",
    "sg:tags":[
        "operator",
        "local",
        "trucking"
    ],
    "wof:name":"Larry Jenkins Trucking Inc",
    "wof:placetype":"venue"
},
  "geometry": {"coordinates":[-120.88004100000001,38.676159],"type":"Point"}
}