{
  "type": "Feature",
  "properties": {
    "iso:country":"US",
    "sg:address":"984 N Main St",
    "sg:city":"Orange",
    "sg:classifiers":[
        {
            "category":"Food & Beverages",
            "subcategory":"Bakery",
            "type":"Retail Goods"
        }
    ],
    "sg:phone":"+1 714 771 2114",
    "sg:postcode":"92867",
    "sg:province":"CA",
    "wof:name":"Nikos Greek Specialty Pdts",
    "wof:placetype":"venue"
},
  "geometry": {"coordinates":[-117.866903,33.804537],"type":"Point"}
}