{
  "type": "Feature",
  "properties": {
    "iso:country":"US",
    "sg:address":"7730 Morro Rd",
    "sg:city":"Atascadero",
    "sg:classifiers":[
        {
            "category":"Insurance",
            "subcategory":"Insurance Agent",
            "type":"Services"
        },
        {
            "category":"Insurance",
            "subcategory":"Hazard Insurance",
            "type":"Services"
        }
    ],
    "sg:phone":"+1 805 466 7333",
    "sg:postcode":"93422",
    "sg:province":"CA",
    "sg:tags":[
        "fidelity",
        "surety",
        "bond"
    ],
    "wof:name":"Farmers Insurance Group",
    "wof:placetype":"venue"
},
  "geometry": {"coordinates":[-120.66848299999999,35.473753],"type":"Point"}
}