{
  "type": "Feature",
  "properties": {
    "addr:full":"45015 Via Vaquero Temecula CA 92590",
    "addr:housenumber":"45015",
    "addr:postcode":"92590",
    "addr:street":"Via Vaquero",
    "iso:country":"US",
    "sg:address":"45015 Via Vaquero",
    "sg:city":"Temecula",
    "sg:classifiers":[
        {
            "category":"Building & Trades",
            "subcategory":"Construction",
            "type":"Services"
        },
        {
            "category":"Utilities",
            "type":"Services"
        }
    ],
    "sg:phone":"+1 951 506 1518",
    "sg:postcode":"92590",
    "sg:province":"CA",
    "sg:tags":[
        "industrial",
        "contractors-commercial",
        "contractor"
    ],
    "wof:name":"Whitehead Construction",
    "wof:placetype":"venue"
},
  "geometry": {"coordinates":[-117.21656,33.475829],"type":"Point"}
}