{
  "type": "Feature",
  "properties": {
    "addr:full":"718 S Broadway Los Angeles CA 90014",
    "addr:housenumber":"718",
    "addr:postcode":"90014",
    "addr:street":"S Broadway",
    "iso:country":"US",
    "sg:address":"718 S Broadway",
    "sg:city":"Los Angeles",
    "sg:classifiers":[
        {
            "category":"Manufacturing",
            "subcategory":"Signs",
            "type":"Manufacturing & Wholesale Goods"
        }
    ],
    "sg:phone":"+1 213 623 8636",
    "sg:postcode":"90014",
    "sg:province":"CA",
    "sg:tags":[
        "specialty",
        "mfg"
    ],
    "wof:name":"Lighthouse Design",
    "wof:placetype":"venue"
},
  "geometry": {"coordinates":[-118.25444299999999,34.043993],"type":"Point"}
}