{
  "type": "Feature",
  "properties": {
    "addr:full":"689 Abbey Ct Benicia CA 94510",
    "addr:housenumber":"689",
    "addr:postcode":"94510",
    "addr:street":"Abbey Ct",
    "iso:country":"US",
    "sg:address":"689 Abbey Ct",
    "sg:city":"Benicia",
    "sg:classifiers":[
        {
            "category":"Wholesale",
            "subcategory":"Medical Equipment & Supplies",
            "type":"Manufacturing & Wholesale Goods"
        }
    ],
    "sg:phone":"+1 707 746 1781",
    "sg:postcode":"94510",
    "sg:province":"CA",
    "sg:tags":[
        "physician",
        "surgeon"
    ],
    "sg:website":"www.ahelpnhand.com",
    "wof:name":"A Helping Hand",
    "wof:placetype":"venue"
},
  "geometry": {"coordinates":[-122.174601,38.087686],"type":"Point"}
}