{
  "type": "Feature",
  "properties": {
    "addr:full":"2001 Virginia Rd Hughson CA 95326",
    "addr:housenumber":"2001",
    "addr:postcode":"95326",
    "addr:street":"Virginia Rd",
    "iso:country":"US",
    "sg:address":"2001 Virginia Rd",
    "sg:city":"Hughson",
    "sg:classifiers":[
        {
            "category":"Farming",
            "subcategory":"Farm",
            "type":"Manufacturing & Wholesale Goods"
        }
    ],
    "sg:phone":"+1 209 883 4330",
    "sg:postcode":"95326",
    "sg:province":"CA",
    "sg:tags":[
        "crop",
        "general"
    ],
    "wof:name":"Dbk Orchard",
    "wof:placetype":"venue"
},
  "geometry": {"coordinates":[-120.776202,37.600162],"type":"Point"}
}