{
  "type": "Feature",
  "properties": {
    "addr:full":"3647 Shasta St Chino CA 91710",
    "addr:housenumber":"3647",
    "addr:postcode":"91710",
    "addr:street":"Shasta St",
    "iso:country":"US",
    "sg:address":"3647 Shasta St",
    "sg:city":"Chino",
    "sg:classifiers":[
        {
            "category":"Manufacturing",
            "subcategory":"Paper Products",
            "type":"Manufacturing & Wholesale Goods"
        }
    ],
    "sg:phone":"+1 909 591 8768",
    "sg:postcode":"91710",
    "sg:province":"CA",
    "sg:tags":[
        "bag",
        "coated",
        "plastic"
    ],
    "wof:name":"Shannon Packaging",
    "wof:placetype":"venue"
},
  "geometry": {"coordinates":[-117.725436,34.028832],"type":"Point"}
}