{
  "type": "Feature",
  "properties": {
    "addr:full":"6745 20th Street Rio Linda CA 95673",
    "addr:housenumber":"6745",
    "addr:postcode":"95673",
    "addr:street":"20Th Street",
    "iso:country":"US",
    "sg:address":"6745 20th Street",
    "sg:city":"Rio Linda",
    "sg:classifiers":[
        {
            "category":"Shopping",
            "subcategory":"Bicycles & Sporting Goods",
            "type":"Retail Goods"
        },
        {
            "category":"Shopping",
            "subcategory":"Shoes",
            "type":"Retail Goods"
        }
    ],
    "sg:phone":"+1 916 991 5298",
    "sg:postcode":"95673",
    "sg:province":"CA",
    "sg:tags":[
        "store"
    ],
    "wof:name":"Elkhorn Bait & Tackle",
    "wof:placetype":"venue"
},
  "geometry": {"coordinates":[-121.42,38.689443],"type":"Point"}
}