{
  "type": "Feature",
  "properties": {
    "addr:full":"1275 California Dr Burlingame CA 94010",
    "addr:housenumber":"1275",
    "addr:postcode":"94010",
    "addr:street":"California Dr",
    "iso:country":"US",
    "sg:address":"1275 California Dr",
    "sg:city":"Burlingame",
    "sg:classifiers":[
        {
            "category":"Health Services",
            "subcategory":"Chiropractor",
            "type":"Services"
        }
    ],
    "sg:phone":"+1 650 347 2225",
    "sg:postcode":"94010",
    "sg:province":"CA",
    "sg:tags":[
        "chiropractic"
    ],
    "wof:name":"Kavvadias Platon DC",
    "wof:placetype":"venue"
},
  "geometry": {"coordinates":[-122.365341,37.58832],"type":"Point"}
}