{
  "type": "Feature",
  "properties": {
    "addr:full":"9348 Jamacha Blvd Spring Valley CA 91977",
    "addr:housenumber":"9348",
    "addr:postcode":"91977",
    "addr:street":"Jamacha Blvd",
    "iso:country":"US",
    "sg:address":"9348 Jamacha Blvd",
    "sg:city":"Spring Valley",
    "sg:classifiers":[
        {
            "category":"Professional",
            "subcategory":"Accounting & Tax Preparation",
            "type":"Services"
        }
    ],
    "sg:phone":"+1 619 460 8297",
    "sg:postcode":"91977",
    "sg:province":"CA",
    "sg:tags":[
        "return",
        "filing"
    ],
    "wof:name":"Jackson Hewitt Tax Svc",
    "wof:placetype":"venue"
},
  "geometry": {"coordinates":[-116.999391,32.707937],"type":"Point"}
}