{
  "type": "Feature",
  "properties": {
    "iso:country":"US",
    "sg:address":"2025 Bella Vista Dr",
    "sg:city":"Adelanto",
    "sg:classifiers":[
        {
            "category":"Farming",
            "subcategory":"Poultry Farm",
            "type":"Manufacturing & Wholesale Goods"
        }
    ],
    "sg:phone":"+1 760 388 4229",
    "sg:postcode":"92301",
    "sg:province":"CA",
    "sg:tags":[
        "egg"
    ],
    "wof:name":"El Mirage Pig Paradise",
    "wof:placetype":"venue"
},
  "geometry": {"coordinates":[-117.623307,34.624205],"type":"Point"}
}