{
  "type": "Feature",
  "properties": {
    "addr:full":"6106 Fair Ave North Hollywood CA 91606",
    "addr:housenumber":"6106",
    "addr:postcode":"91606",
    "addr:street":"Fair Ave",
    "iso:country":"US",
    "sg:address":"6106 Fair Ave",
    "sg:city":"North Hollywood",
    "sg:classifiers":[
        {
            "category":"Manufacturing",
            "subcategory":"Printing",
            "type":"Manufacturing & Wholesale Goods"
        }
    ],
    "sg:phone":"+1 818 389 5394",
    "sg:postcode":"91606",
    "sg:province":"CA",
    "sg:tags":[
        "commercial"
    ],
    "wof:name":"Biz Map Guides",
    "wof:placetype":"venue"
},
  "geometry": {"coordinates":[-118.3746,34.182941],"type":"Point"}
}