{
  "type": "Feature",
  "properties": {
    "iso:country":"US",
    "sg:address":"1077 E Shaw Ave",
    "sg:city":"Fresno",
    "sg:classifiers":[
        {
            "category":"Social Services",
            "type":"Services"
        }
    ],
    "sg:phone":"+1 559 224 0162",
    "sg:postcode":"93710",
    "sg:province":"CA",
    "sg:tags":[
        "organization",
        "welfare"
    ],
    "wof:name":"Goodwill Industries",
    "wof:placetype":"venue"
},
  "geometry": {"coordinates":[-119.77189799999999,36.808481],"type":"Point"}
}