{
  "type": "Feature",
  "properties": {
    "iso:country":"US",
    "sg:address":"1144 N 1st St",
    "sg:city":"Fresno",
    "sg:classifiers":[
        {
            "category":"Travel",
            "subcategory":"Travel Agent",
            "type":"Entertainment"
        }
    ],
    "sg:phone":"+1 559 233 4779",
    "sg:postcode":"93702",
    "sg:province":"CA",
    "sg:tags":[
        "agency",
        "business"
    ],
    "wof:name":"Pure & Fresh Drinking Water",
    "wof:placetype":"venue"
},
  "geometry": {"coordinates":[-119.772411,36.757444],"type":"Point"}
}