{
  "type": "Feature",
  "properties": {
    "iso:country":"US",
    "sg:address":"1115 Uintah St",
    "sg:city":"La Canada Flintridge",
    "sg:classifiers":[
        {
            "category":"Building & Trades",
            "subcategory":"Electrical",
            "type":"Services"
        }
    ],
    "sg:phone":"+1 818 957 6269",
    "sg:postcode":"91011",
    "sg:province":"CA",
    "sg:tags":[
        "electrical",
        "contractor"
    ],
    "wof:name":"Anthony Newcombe Electric",
    "wof:placetype":"venue"
},
  "geometry": {"coordinates":[-118.20281199999999,34.211416],"type":"Point"}
}