{
  "type": "Feature",
  "properties": {
    "iso:country":"US",
    "sg:address":"2448 Sacramento St",
    "sg:city":"Berkeley",
    "sg:classifiers":[
        {
            "category":"Restaurant",
            "type":"Food & Drink"
        }
    ],
    "sg:phone":"+1 510 848 7684",
    "sg:postcode":"94702",
    "sg:province":"CA",
    "sg:tags":[
        "indian"
    ],
    "sg:website":"www.breadsofindia.com/menu.shtml",
    "wof:name":"Breads of India & Gourmet Curries",
    "wof:placetype":"venue"
},
  "geometry": {"coordinates":[-122.281344,37.863102],"type":"Point"}
}