{
  "type": "Feature",
  "properties": {
    "addr:full":"4130 Redwood Rd Oakland CA 94619",
    "addr:housenumber":"4130",
    "addr:postcode":"94619",
    "addr:street":"Redwood Rd",
    "iso:country":"US",
    "sg:address":"4130 Redwood Rd",
    "sg:city":"Oakland",
    "sg:classifiers":[
        {
            "category":"Shopping",
            "subcategory":"Music",
            "type":"Retail Goods"
        }
    ],
    "sg:phone":"+1 510 530 1717",
    "sg:postcode":"94619",
    "sg:province":"CA",
    "sg:tags":[
        "video",
        "disc",
        "tape",
        "cassette"
    ],
    "wof:name":"Home Box Video",
    "wof:placetype":"venue"
},
  "geometry": {"coordinates":[-122.18252200000001,37.796612],"type":"Point"}
}