{
  "type": "Feature",
  "properties": {
    "iso:country":"US",
    "sg:address":"833 F Street",
    "sg:city":"Sacramento",
    "sg:classifiers":[
        {
            "category":"Professional",
            "subcategory":"Lawyer & Legal Services",
            "type":"Services"
        }
    ],
    "sg:phone":"+1 916 446 6457",
    "sg:postcode":"95814",
    "sg:province":"CA",
    "wof:name":"Farina Joseph Law Offices of",
    "wof:placetype":"venue"
},
  "geometry": {"coordinates":[-121.49312399999999,38.585286],"type":"Point"}
}