{
  "type": "Feature",
  "properties": {
    "iso:country":"US",
    "sg:address":"1101 Stroud Ave",
    "sg:city":"Kingsburg",
    "sg:classifiers":[
        {
            "category":"Health Services",
            "subcategory":"Nursing And Care Facility",
            "type":"Services"
        }
    ],
    "sg:phone":"+1 559 897 5881",
    "sg:postcode":"93631",
    "sg:province":"CA",
    "wof:name":"Sunbrdge Care Ctr For Kngsburg",
    "wof:placetype":"venue"
},
  "geometry": {"coordinates":[-119.555677,36.525237],"type":"Point"}
}