{
  "type": "Feature",
  "properties": {
    "addr:full":"14469 Rattlesnake Rd Grass Valley CA 95945",
    "addr:postcode":"14469;95945",
    "addr:street":"Rattlesnake Rd",
    "iso:country":"US",
    "sg:address":"14469 Rattlesnake Rd",
    "sg:city":"Grass Valley",
    "sg:classifiers":[
        {
            "category":"Building & Trades",
            "subcategory":"Landscaping Services",
            "type":"Services"
        }
    ],
    "sg:phone":"+1 530 477 6826",
    "sg:postcode":"95945",
    "sg:province":"CA",
    "sg:tags":[
        "lawn",
        "maintenance",
        "grounds"
    ],
    "wof:name":"Bmi Svc",
    "wof:placetype":"venue"
},
  "geometry": {"coordinates":[-121.03121,39.173813],"type":"Point"}
}