{
  "type": "Feature",
  "properties": {
    "addr:full":"139 W 1st St Chico CA 95928",
    "addr:housenumber":"139",
    "addr:postcode":"95928",
    "addr:street":"W 1St St",
    "iso:country":"US",
    "sg:address":"139 W 1st St",
    "sg:city":"Chico",
    "sg:classifiers":[
        {
            "category":"Arts & Performance",
            "subcategory":"Theater",
            "type":"Entertainment"
        }
    ],
    "sg:phone":"+1 530 895 3749",
    "sg:postcode":"95928",
    "sg:province":"CA",
    "wof:name":"Blue Room Theater",
    "wof:placetype":"venue"
},
  "geometry": {"coordinates":[-121.841452,39.730868],"type":"Point"}
}