{
  "type": "Feature",
  "properties": {
    "iso:country":"US",
    "sg:address":"2136 N Dinuba Blvd",
    "sg:city":"Visalia",
    "sg:classifiers":[
        {
            "category":"Food & Beverages",
            "subcategory":"Fruits & Vegetables",
            "type":"Retail Goods"
        }
    ],
    "sg:phone":"+1 559 732 5020",
    "sg:postcode":"93291",
    "sg:province":"CA",
    "sg:tags":[
        "produce"
    ],
    "wof:name":"Valley San Joaquin Produce",
    "wof:placetype":"venue"
},
  "geometry": {"coordinates":[-119.296843,36.348869],"type":"Point"}
}