{
  "type": "Feature",
  "properties": {
    "iso:country":"US",
    "sg:address":"3643 Bradshaw Rd Ste J",
    "sg:city":"Sacramento",
    "sg:classifiers":[
        {
            "category":"Restaurant",
            "type":"Food & Drink"
        }
    ],
    "sg:phone":"+1 916 368 6688",
    "sg:postcode":"95827",
    "sg:province":"CA",
    "sg:tags":[
        "chinese"
    ],
    "wof:name":"Happy Palace",
    "wof:placetype":"venue"
},
  "geometry": {"coordinates":[-121.33502,38.5551],"type":"Point"}
}