{
  "type": "Feature",
  "properties": {
    "addr:full":"6400 Parsons Way Bakersfield CA 93307",
    "addr:housenumber":"6400",
    "addr:postcode":"93307",
    "addr:street":"Parsons Way",
    "iso:country":"US",
    "sg:address":"6400 Parsons Way",
    "sg:city":"Bakersfield",
    "sg:classifiers":[
        {
            "category":"Building & Trades",
            "subcategory":"Equipment Rental",
            "type":"Services"
        }
    ],
    "sg:phone":"+1 661 836 1343",
    "sg:postcode":"93307",
    "sg:province":"CA",
    "sg:tags":[
        "yard",
        "leasing",
        "store"
    ],
    "wof:name":"Cockerels Housing & Rentals",
    "wof:placetype":"venue"
},
  "geometry": {"coordinates":[-119.019897,35.29674],"type":"Point"}
}