{
  "type": "Feature",
  "properties": {
    "iso:country":"US",
    "sg:address":"1225 W 17th St",
    "sg:city":"Santa Ana",
    "sg:classifiers":[
        {
            "category":"Professional",
            "subcategory":"Business Services",
            "type":"Services"
        }
    ],
    "sg:phone":"+1 714 210 4750",
    "sg:postcode":"92706",
    "sg:province":"CA",
    "sg:tags":[
        "telemarketing"
    ],
    "wof:name":"Att-USA Wireless",
    "wof:placetype":"venue"
},
  "geometry": {"coordinates":[-117.88329899999999,33.76012],"type":"Point"}
}