{
  "type": "Feature",
  "properties": {
    "iso:country":"US",
    "sg:address":"10875 State Rte 49",
    "sg:city":"Sonora",
    "sg:classifiers":[
        {
            "category":"Autos & Motor Vehicles",
            "subcategory":"Automobile Sales",
            "type":"Retail Goods"
        }
    ],
    "sg:phone":"+1 209 223 9333",
    "sg:postcode":"95370",
    "sg:province":"CA",
    "sg:tags":[
        "car",
        "dealer"
    ],
    "wof:name":"Mountain Auto",
    "wof:placetype":"venue"
},
  "geometry": {"coordinates":[-120.405091,38.01115],"type":"Point"}
}