{
  "type": "Feature",
  "properties": {
    "iso:country":"US",
    "sg:address":"44870 Osgood Rd",
    "sg:city":"Fremont",
    "sg:classifiers":[
        {
            "category":"Shopping",
            "subcategory":"Computers & Home Electronics",
            "type":"Retail Goods"
        }
    ],
    "sg:phone":"+1 510 490 8133",
    "sg:postcode":"94539",
    "sg:province":"CA",
    "sg:tags":[
        "equipment",
        "dealer"
    ],
    "wof:name":"Atech Digilog Inc",
    "wof:placetype":"venue"
},
  "geometry": {"coordinates":[-121.93805,37.506035],"type":"Point"}
}