{
  "type": "Feature",
  "properties": {
    "addr:full":"435 Shoreline Village Dr Long Beach CA 90802",
    "addr:housenumber":"435",
    "addr:postcode":"90802",
    "addr:street":"Shoreline Village Dr",
    "iso:country":"US",
    "sg:address":"435 Shoreline Village Dr",
    "sg:city":"Long Beach",
    "sg:classifiers":[
        {
            "category":"Restaurant",
            "type":"Food & Drink"
        }
    ],
    "sg:phone":"+1 562 432 6500",
    "sg:postcode":"90802",
    "sg:province":"CA",
    "sg:tags":[
        "bar",
        "nightlife",
        "banquet",
        "room"
    ],
    "sg:website":"www.parkerslighthouse.com",
    "wof:name":"Parkers' Lighthouse",
    "wof:placetype":"venue"
},
  "geometry": {"coordinates":[-118.189526,33.76014],"type":"Point"}
}