{
  "type": "Feature",
  "properties": {
    "iso:country":"US",
    "sg:address":"1595 Grand Ave",
    "sg:city":"San Marcos",
    "sg:classifiers":[
        {
            "category":"Health Services",
            "subcategory":"Health Practitioner",
            "type":"Services"
        }
    ],
    "sg:phone":"+1 760 471 1196",
    "sg:postcode":"92069",
    "sg:province":"CA",
    "sg:tags":[
        "audiologists"
    ],
    "wof:name":"Hearing Health Care",
    "wof:placetype":"venue"
},
  "geometry": {"coordinates":[-117.19741500000001,33.145013],"type":"Point"}
}