{
  "type": "Feature",
  "properties": {
    "iso:country":"US",
    "sg:address":"7219 Lynch Rd",
    "sg:city":"Sebastopol",
    "sg:classifiers":[
        {
            "category":"Building & Trades",
            "subcategory":"Landscaping Services",
            "type":"Services"
        }
    ],
    "sg:phone":"+1 707 824 8343",
    "sg:postcode":"95472",
    "sg:province":"CA",
    "sg:tags":[
        "lawn",
        "maintenance",
        "grounds"
    ],
    "wof:name":"Arborists That Climb",
    "wof:placetype":"venue"
},
  "geometry": {"coordinates":[-122.821399,38.38797],"type":"Point"}
}