{
  "type": "Feature",
  "properties": {
    "addr:full":"5543 Morning Canyon Way Rancho Cucamonga CA 91737",
    "addr:housenumber":"5543",
    "addr:postcode":"91737",
    "addr:street":"Morning Canyon Way",
    "iso:country":"US",
    "sg:address":"5543 Morning Canyon Way",
    "sg:city":"Rancho Cucamonga",
    "sg:classifiers":[
        {
            "category":"Manufacturing",
            "subcategory":"Furniture",
            "type":"Manufacturing & Wholesale Goods"
        }
    ],
    "sg:phone":"+1 909 987 0309",
    "sg:postcode":"91737",
    "sg:province":"CA",
    "sg:tags":[
        "household",
        "metal",
        "mfg"
    ],
    "wof:name":"Lows Custom Stainless",
    "wof:placetype":"venue"
},
  "geometry": {"coordinates":[-117.588128,34.153062],"type":"Point"}
}