{
  "type": "Feature",
  "properties": {
    "addr:full":"13684 Comuna Dr Poway CA 92064",
    "addr:housenumber":"13684",
    "addr:postcode":"ca 92064",
    "addr:street":"Comuna Dr",
    "iso:country":"US",
    "sg:address":"13684 Comuna Dr",
    "sg:city":"Poway",
    "sg:classifiers":[
        {
            "category":"Building & Trades",
            "subcategory":"Landscaping Services",
            "type":"Services"
        }
    ],
    "sg:phone":"+1 858 679 8832",
    "sg:postcode":"92064",
    "sg:province":"CA",
    "sg:tags":[
        "landscape"
    ],
    "wof:name":"Westrack Landscaping",
    "wof:placetype":"venue"
},
  "geometry": {"coordinates":[-117.043997,32.961738],"type":"Point"}
}