{
  "type": "Feature",
  "properties": {
    "addr:full":"16 Red Maple Pl Danville CA 94506",
    "addr:housenumber":"16",
    "addr:postcode":"94506",
    "addr:street":"Red Maple Pl",
    "iso:country":"US",
    "sg:address":"16 Red Maple Pl",
    "sg:city":"Danville",
    "sg:classifiers":[
        {
            "category":"Home & Garden",
            "subcategory":"Kitchen Supply",
            "type":"Retail Goods"
        }
    ],
    "sg:phone":"+1 925 736 2784",
    "sg:postcode":"94506",
    "sg:province":"CA",
    "sg:tags":[
        "food",
        "equipment",
        "processing"
    ],
    "wof:name":"California Food Technology",
    "wof:placetype":"venue"
},
  "geometry": {"coordinates":[-121.921589,37.804762],"type":"Point"}
}