{
  "type": "Feature",
  "properties": {
    "addr:full":"2020 Rosemead Blvd South El Monte CA 91733",
    "addr:housenumber":"2020",
    "addr:postcode":"91733",
    "addr:street":"Rosemead Blvd",
    "iso:country":"US",
    "sg:address":"2020 Rosemead Blvd",
    "sg:city":"South El Monte",
    "sg:classifiers":[
        {
            "category":"Retail",
            "subcategory":"Auto Repair",
            "type":"Services"
        }
    ],
    "sg:phone":"+1 626 582 1648",
    "sg:postcode":"91733",
    "sg:province":"CA",
    "wof:name":"Phil's Certified Auto Center",
    "wof:placetype":"venue"
},
  "geometry": {"coordinates":[-118.064003,34.051998],"type":"Point"}
}