{
  "type": "Feature",
  "properties": {
    "addr:full":"824 Spence St Los Angeles CA 90023",
    "addr:housenumber":"824",
    "addr:postcode":"90023",
    "addr:street":"Spence St",
    "iso:country":"US",
    "sg:address":"824 Spence St",
    "sg:city":"Los Angeles",
    "sg:classifiers":[
        {
            "category":"Wholesale",
            "subcategory":"Apparel",
            "type":"Manufacturing & Wholesale Goods"
        }
    ],
    "sg:phone":"+1 323 264 9564",
    "sg:postcode":"90023",
    "sg:province":"CA",
    "sg:tags":[
        "footwear"
    ],
    "wof:name":"American Shoe & Apparrel",
    "wof:placetype":"venue"
},
  "geometry": {"coordinates":[-118.198306,34.026916],"type":"Point"}
}