{
  "type": "Feature",
  "properties": {
    "addr:full":"13820 Foothill Blvd Sylmar CA 91342",
    "addr:housenumber":"13820",
    "addr:postcode":"91342",
    "addr:street":"Foothill Blvd",
    "iso:country":"US",
    "sg:address":"13820 Foothill Blvd",
    "sg:city":"Sylmar",
    "sg:classifiers":[
        {
            "category":"Food & Beverages",
            "subcategory":"Groceries & Convenience Stores",
            "type":"Retail Goods"
        }
    ],
    "sg:phone":"+1 818 362 7577",
    "sg:postcode":"91342",
    "sg:province":"CA",
    "sg:tags":[
        "market"
    ],
    "wof:name":"Super Mercaso Vallarta",
    "wof:placetype":"venue"
},
  "geometry": {"coordinates":[-118.43728,34.312847],"type":"Point"}
}