{
  "type": "Feature",
  "properties": {
    "addr:full":"1121 Artesia Boulevard Manhattan Beach CA 90266",
    "addr:housenumber":"1121",
    "addr:postcode":"90266",
    "addr:street":"Artesia Boulevard",
    "iso:country":"US",
    "sg:address":"1121 Artesia Boulevard",
    "sg:city":"Manhattan Beach",
    "sg:classifiers":[
        {
            "category":"Health Services",
            "subcategory":"Health Practitioner",
            "type":"Services"
        },
        {
            "category":"Insurance",
            "subcategory":"Health Insurance",
            "type":"Services"
        }
    ],
    "sg:phone":"+1 310 372 1028",
    "sg:postcode":"90266",
    "sg:province":"CA",
    "sg:tags":[
        "nutritionist",
        "market"
    ],
    "sg:website":"www.lindbergnutrition.com/",
    "wof:name":"Lindberg Nutrition Store",
    "wof:placetype":"venue"
},
  "geometry": {"coordinates":[-118.399047,33.888945],"type":"Point"}
}