{
  "type": "Feature",
  "properties": {
    "addr:full":"7687 N San Fernando Rd Burbank CA 91505",
    "addr:housenumber":"7687",
    "addr:postcode":"91505",
    "addr:street":"N San Fernando Rd",
    "iso:country":"US",
    "sg:address":"7687 N San Fernando Rd",
    "sg:city":"Burbank",
    "sg:classifiers":[
        {
            "category":"Airline",
            "type":"Transportation"
        }
    ],
    "sg:phone":"+1 818 768 3171",
    "sg:postcode":"91505",
    "sg:province":"CA",
    "sg:tags":[
        "airport"
    ],
    "wof:name":"Burbank Airport Commerce Center",
    "wof:placetype":"venue"
},
  "geometry": {"coordinates":[-118.35602299999999,34.210066],"type":"Point"}
}