{
  "type": "Feature",
  "properties": {
    "iso:country":"US",
    "sg:address":"5411 Ave Encinas",
    "sg:city":"Carlsbad",
    "sg:classifiers":[
        {
            "category":"Banks & Credit Unions",
            "subcategory":"Bank",
            "type":"Services"
        }
    ],
    "sg:phone":"+1 760 431 8510",
    "sg:postcode":"92008",
    "sg:province":"CA",
    "sg:tags":[
        "mortgage"
    ],
    "wof:name":"Gibraltar Capital",
    "wof:placetype":"venue"
},
  "geometry": {"coordinates":[-117.327287,33.129988],"type":"Point"}
}