{
  "type": "Feature",
  "properties": {
    "iso:country":"US",
    "sg:address":"8600 W Pico Blvd",
    "sg:city":"Los Angeles",
    "sg:classifiers":[
        {
            "category":"Home & Garden",
            "subcategory":"Furniture",
            "type":"Retail Goods"
        }
    ],
    "sg:phone":"+1 310 652 7400",
    "sg:postcode":"90035",
    "sg:province":"CA",
    "sg:tags":[
        "builder",
        "custom"
    ],
    "sg:website":"www.horizonfurniture.com",
    "wof:name":"Wall Systems",
    "wof:placetype":"venue"
},
  "geometry": {"coordinates":[-118.379537,34.053971],"type":"Point"}
}