{
  "type": "Feature",
  "properties": {
    "iso:country":"US",
    "sg:address":"5905 Lincoln Ave",
    "sg:city":"Rocklin",
    "sg:classifiers":[
        {
            "category":"Freight",
            "type":"Transportation"
        }
    ],
    "sg:phone":"+1 916 925 7264",
    "sg:postcode":"95677",
    "sg:province":"CA",
    "sg:tags":[
        "arrangement"
    ],
    "wof:name":"Airland Express Inc",
    "wof:placetype":"venue"
},
  "geometry": {"coordinates":[-121.262522,38.782136],"type":"Point"}
}