{
  "type": "Feature",
  "properties": {
    "addr:full":"3333 W Pacific Ave Burbank CA 91505",
    "addr:housenumber":"3333",
    "addr:postcode":"91505",
    "addr:street":"W Pacific Ave",
    "iso:country":"US",
    "sg:address":"3333 W Pacific Ave",
    "sg:city":"Burbank",
    "sg:classifiers":[
        {
            "category":"Banks & Credit Unions",
            "subcategory":"Financial Services",
            "type":"Services"
        }
    ],
    "sg:phone":"+1 818 846 3327",
    "sg:postcode":"91505",
    "sg:province":"CA",
    "sg:tags":[
        "company",
        "holding"
    ],
    "wof:name":"Talsha LLC",
    "wof:placetype":"venue"
},
  "geometry": {"coordinates":[-118.34649899999999,34.18843],"type":"Point"}
}