{
  "type": "Feature",
  "properties": {
    "iso:country":"US",
    "sg:address":"2422 W Summerset Dr",
    "sg:city":"Rialto",
    "sg:classifiers":[
        {
            "category":"Professional",
            "subcategory":"Business Services",
            "type":"Services"
        }
    ],
    "sg:phone":"+1 909 562 4145",
    "sg:postcode":"92377",
    "sg:province":"CA",
    "sg:tags":[
        "management"
    ],
    "wof:name":"Ck Unlimited",
    "wof:placetype":"venue"
},
  "geometry": {"coordinates":[-117.421252,34.167725],"type":"Point"}
}