{
  "type": "Feature",
  "properties": {
    "iso:country":"US",
    "sg:address":"3711 Saviers Rd",
    "sg:city":"Oxnard",
    "sg:classifiers":[
        {
            "category":"Professional",
            "subcategory":"Business Services",
            "type":"Services"
        }
    ],
    "sg:phone":"+1 805 486 4247",
    "sg:postcode":"93033",
    "sg:province":"CA",
    "sg:tags":[
        "embroidery"
    ],
    "wof:name":"A C M Intl",
    "wof:placetype":"venue"
},
  "geometry": {"coordinates":[-119.177724,34.165188],"type":"Point"}
}