{
  "type": "Feature",
  "properties": {
    "addr:full":"5461 Starkes Grade Rd Pollock Pines CA 95726",
    "addr:housenumber":"5461",
    "addr:postcode":"95726",
    "addr:street":"Starkes Grade Rd",
    "iso:country":"US",
    "sg:address":"5461 Starkes Grade Rd",
    "sg:city":"Pollock Pines",
    "sg:classifiers":[
        {
            "category":"Real Estate",
            "subcategory":"Developer",
            "type":"Services"
        }
    ],
    "sg:phone":"+1 530 644 6861",
    "sg:postcode":"95726",
    "sg:province":"CA",
    "wof:name":"Designtech",
    "wof:placetype":"venue"
},
  "geometry": {"coordinates":[-120.620102,38.723067],"type":"Point"}
}