{
  "type": "Feature",
  "properties": {
    "iso:country":"US",
    "sg:address":"4802 W 111th Pl",
    "sg:city":"Inglewood",
    "sg:classifiers":[
        {
            "category":"Shopping",
            "subcategory":"Gifts & Souvenirs",
            "type":"Retail Goods"
        }
    ],
    "sg:phone":"+1 310 677 0362",
    "sg:postcode":"90304",
    "sg:province":"CA",
    "wof:name":"Arzals Party Rentals",
    "wof:placetype":"venue"
},
  "geometry": {"coordinates":[-118.36190999999999,33.933598],"type":"Point"}
}