{
  "type": "Feature",
  "properties": {
    "addr:full":"2204 Nola Dr San Jose CA 95125",
    "addr:housenumber":"2204",
    "addr:postcode":"95125",
    "addr:street":"Nola Dr",
    "iso:country":"US",
    "sg:address":"2204 Nola Dr",
    "sg:city":"San Jose",
    "sg:classifiers":[
        {
            "category":"Manufacturing",
            "subcategory":"Metals",
            "type":"Manufacturing & Wholesale Goods"
        }
    ],
    "sg:phone":"+1 408 265 0936",
    "sg:postcode":"95125",
    "sg:province":"CA",
    "sg:tags":[
        "plumbing",
        "decorative",
        "distribute"
    ],
    "wof:name":"Pure Life Products LLC",
    "wof:placetype":"venue"
},
  "geometry": {"coordinates":[-121.89932399999999,37.286865],"type":"Point"}
}