{
  "type": "Feature",
  "properties": {
    "addr:full":"5300 W Century Blvd Los Angeles CA 90009",
    "addr:housenumber":"5300",
    "addr:postcode":"90009",
    "addr:street":"W Century Blvd",
    "iso:country":"US",
    "sg:address":"5300 W Century Blvd",
    "sg:city":"Los Angeles",
    "sg:classifiers":[
        {
            "category":"Personal",
            "type":"Services"
        }
    ],
    "sg:phone":"+1 888 310 1570",
    "sg:postcode":"90009",
    "sg:province":"CA",
    "sg:tags":[
        "local"
    ],
    "sg:website":"www.voicetelmedia.com",
    "wof:name":"Voicetel Media",
    "wof:placetype":"venue"
},
  "geometry": {"coordinates":[-118.372709,33.94531],"type":"Point"}
}