{
  "type": "Feature",
  "properties": {
    "iso:country":"US",
    "sg:address":"1829 Camphor Way",
    "sg:city":"Lodi",
    "sg:classifiers":[
        {
            "category":"Manufacturing",
            "subcategory":"Metals",
            "type":"Manufacturing & Wholesale Goods"
        }
    ],
    "sg:phone":"+1 209 369 6833",
    "sg:postcode":"95242",
    "sg:province":"CA",
    "sg:tags":[
        "engraver"
    ],
    "wof:name":"Custom Trophies & Awards",
    "wof:placetype":"venue"
},
  "geometry": {"coordinates":[-121.295079,38.110491],"type":"Point"}
}