{
  "type": "Feature",
  "properties": {
    "iso:country":"US",
    "sg:address":"2808 S Halcyon Rd",
    "sg:city":"Arroyo Grande",
    "sg:classifiers":[
        {
            "category":"Restaurant",
            "type":"Food & Drink"
        }
    ],
    "sg:phone":"+1 805 481 1179",
    "sg:postcode":"93420",
    "sg:province":"CA",
    "wof:name":"Planet Java",
    "wof:placetype":"venue"
},
  "geometry": {"coordinates":[-120.587516,35.081568],"type":"Point"}
}