{
  "type": "Feature",
  "properties": {
    "addr:full":"14507 Sylvan St Van Nuys CA 91411",
    "addr:housenumber":"14507",
    "addr:postcode":"91411",
    "addr:street":"Sylvan St",
    "iso:country":"US",
    "sg:address":"14507 Sylvan St",
    "sg:city":"Van Nuys",
    "sg:classifiers":[
        {
            "category":"Travel",
            "subcategory":"Travel Agent",
            "type":"Entertainment"
        }
    ],
    "sg:phone":"+1 818 901 1583",
    "sg:postcode":"91411",
    "sg:province":"CA",
    "sg:tags":[
        "agency",
        "bureau"
    ],
    "wof:name":"Priority Travel",
    "wof:placetype":"venue"
},
  "geometry": {"coordinates":[-118.450785,34.184728],"type":"Point"}
}