{
  "type": "Feature",
  "properties": {
    "iso:country":"US",
    "sg:address":"5846 W Manchester Avenue",
    "sg:city":"Los Angeles",
    "sg:classifiers":[
        {
            "category":"Personal",
            "subcategory":"Barber",
            "type":"Services"
        }
    ],
    "sg:phone":"+1 310 642 6736",
    "sg:postcode":"90045",
    "sg:province":"CA",
    "wof:name":"Sport Cuts",
    "wof:placetype":"venue"
},
  "geometry": {"coordinates":[-118.384515,33.959932],"type":"Point"}
}