{
  "type": "Feature",
  "properties": {
    "iso:country":"US",
    "sg:address":"1330 S Broadway",
    "sg:city":"Santa Ana",
    "sg:classifiers":[
        {
            "category":"Professional",
            "subcategory":"Management & Consulting",
            "type":"Services"
        }
    ],
    "sg:phone":"+1 714 543 5951",
    "sg:postcode":"92707",
    "sg:province":"CA",
    "sg:tags":[
        "marketing",
        "program"
    ],
    "wof:name":"Bradford & Ivy Marketing",
    "wof:placetype":"venue"
},
  "geometry": {"coordinates":[-117.869926,33.729522],"type":"Point"}
}