{
  "type": "Feature",
  "properties": {
    "iso:country":"US",
    "sg:address":"724 Aldo Ave",
    "sg:city":"Santa Clara",
    "sg:classifiers":[
        {
            "category":"Building & Trades",
            "subcategory":"Electrical",
            "type":"Services"
        }
    ],
    "sg:phone":"+1 408 727 1545",
    "sg:postcode":"95054",
    "sg:province":"CA",
    "sg:tags":[
        "electrician"
    ],
    "wof:name":"Stuart & Sons Electric Contractors.",
    "wof:placetype":"venue"
},
  "geometry": {"coordinates":[-121.947304,37.383846],"type":"Point"}
}