{
  "type": "Feature",
  "properties": {
    "addr:full":"1814 Franklin St Ste 325 Oakland CA 94612",
    "addr:housenumber":"1814",
    "addr:postcode":"94612",
    "addr:street":"Franklin St Ste 325",
    "iso:country":"US",
    "sg:address":"1814 Franklin St Ste 325",
    "sg:city":"Oakland",
    "sg:classifiers":[
        {
            "category":"Personal",
            "type":"Services"
        }
    ],
    "sg:phone":"+1 510 893 7106",
    "sg:postcode":"94612",
    "sg:province":"CA",
    "sg:tags":[
        "local"
    ],
    "sg:website":"www.workingeastbay.org",
    "wof:name":"East Bay Alliance For Sustainable Economy",
    "wof:placetype":"venue"
},
  "geometry": {"coordinates":[-122.267608,37.806971],"type":"Point"}
}