{
  "type": "Feature",
  "properties": {
    "iso:country":"US",
    "sg:address":"57626 29 Palms Hwy",
    "sg:city":"Yucca Valley",
    "sg:classifiers":[
        {
            "category":"Restaurant",
            "type":"Food & Drink"
        }
    ],
    "sg:menulink":"http://www.allmenus.com/ca/twentynine-palms-morongo-valley/216558-mcdonalds/menu/",
    "sg:postcode":"92284",
    "sg:province":"CA",
    "sg:tags":[
        "burger",
        "american"
    ],
    "wof:name":"McDonald's",
    "wof:placetype":"venue"
},
  "geometry": {"coordinates":[-116.405855,34.126504],"type":"Point"}
}