{
  "type": "Feature",
  "properties": {
    "addr:full":"2116 Coronet Blvd Belmont CA 94002",
    "addr:housenumber":"2116",
    "addr:postcode":"94002",
    "addr:street":"Coronet Blvd",
    "iso:country":"US",
    "sg:address":"2116 Coronet Blvd",
    "sg:city":"Belmont",
    "sg:classifiers":[
        {
            "category":"Shopping",
            "subcategory":"Computers & Home Electronics",
            "type":"Retail Goods"
        }
    ],
    "sg:phone":"+1 650 593 3532",
    "sg:postcode":"94002",
    "sg:province":"CA",
    "sg:tags":[
        "software"
    ],
    "sg:website":"www.caddow.com",
    "wof:name":"Clearly Business Inc",
    "wof:placetype":"venue"
},
  "geometry": {"coordinates":[-122.29885400000001,37.519463],"type":"Point"}
}