{
  "type": "Feature",
  "properties": {
    "addr:full":"3015 Cornwall Dr Glendale CA 91206",
    "addr:housenumber":"3015",
    "addr:postcode":"91206",
    "addr:street":"Cornwall Dr",
    "iso:country":"US",
    "sg:address":"3015 Cornwall Dr",
    "sg:city":"Glendale",
    "sg:classifiers":[
        {
            "category":"Shopping",
            "subcategory":"Gifts & Souvenirs",
            "type":"Retail Goods"
        }
    ],
    "sg:phone":"+1 818 956 6095",
    "sg:postcode":"91206",
    "sg:province":"CA",
    "wof:name":"Hairy Potter The",
    "wof:placetype":"venue"
},
  "geometry": {"coordinates":[-118.20107400000001,34.169959],"type":"Point"}
}