{
  "type": "Feature",
  "properties": {
    "iso:country":"US",
    "sg:address":"1504 Canyon Del Rey Blvd",
    "sg:city":"Seaside",
    "sg:classifiers":[
        {
            "category":"Coffee & Tea",
            "type":"Food & Drink"
        }
    ],
    "sg:menulink":"http://www.allmenus.com/ca/seaside-monterey/116554-starbucks-coffee/menu/",
    "sg:phone":"+1 831 393 1835",
    "sg:postcode":"93955",
    "sg:province":"CA",
    "sg:tags":[
        "american"
    ],
    "wof:name":"Starbucks Coffee",
    "wof:placetype":"venue"
},
  "geometry": {"coordinates":[-121.855795,36.607756],"type":"Point"}
}