{
  "type": "Feature",
  "properties": {
    "iso:country":"US",
    "sg:address":"3908 Greenwood Ave",
    "sg:city":"Oakland",
    "sg:classifiers":[
        {
            "category":"Communications",
            "subcategory":"Film & Video Production",
            "type":"Services"
        }
    ],
    "sg:phone":"+1 510 482 6341",
    "sg:postcode":"94602",
    "sg:province":"CA",
    "sg:tags":[
        "motion",
        "picture",
        "distributor",
        "audio",
        "exchange"
    ],
    "wof:name":"Prometheus Productions",
    "wof:placetype":"venue"
},
  "geometry": {"coordinates":[-122.228667,37.805512],"type":"Point"}
}