{
  "type": "Feature",
  "properties": {
    "iso:country":"US",
    "sg:address":"7705 Garvey Ave",
    "sg:city":"Rosemead",
    "sg:classifiers":[
        {
            "category":"Professional",
            "subcategory":"Accounting & Tax Preparation",
            "type":"Services"
        }
    ],
    "sg:phone":"+1 626 573 9831",
    "sg:postcode":"91770",
    "sg:province":"CA",
    "sg:tags":[
        "return",
        "filing"
    ],
    "wof:name":"N & M Professional Svc",
    "wof:placetype":"venue"
},
  "geometry": {"coordinates":[-118.102908,34.062687],"type":"Point"}
}