{
  "type": "Feature",
  "properties": {
    "iso:country":"US",
    "sg:address":"539 E Miner Ave",
    "sg:city":"Stockton",
    "sg:classifiers":[
        {
            "category":"Wholesale",
            "subcategory":"Toys & Hobbies",
            "type":"Manufacturing & Wholesale Goods"
        }
    ],
    "sg:phone":"+1 209 473 7362",
    "sg:postcode":"95202",
    "sg:province":"CA",
    "sg:tags":[
        "distributor",
        "game",
        "video"
    ],
    "wof:name":"Fun Place Amusement",
    "wof:placetype":"venue"
},
  "geometry": {"coordinates":[-121.28669,37.956357],"type":"Point"}
}