{
  "type": "Feature",
  "properties": {
    "iso:country":"US",
    "sg:address":"23928 Lyons Ave Ste 201",
    "sg:city":"Newhall",
    "sg:classifiers":[
        {
            "category":"Health Services",
            "subcategory":"Doctor",
            "type":"Services"
        }
    ],
    "sg:phone":"+1 661 254 1663",
    "sg:postcode":"91321",
    "sg:province":"CA",
    "wof:name":"Mysko David E MD",
    "wof:placetype":"venue"
},
  "geometry": {"coordinates":[-118.519997,34.383598],"type":"Point"}
}