{
  "type": "Feature",
  "properties": {
    "iso:country":"US",
    "sg:address":"1401 Los Gamos Dr",
    "sg:city":"San Rafael",
    "sg:classifiers":[
        {
            "category":"Banks & Credit Unions",
            "subcategory":"Bank",
            "type":"Services"
        }
    ],
    "sg:phone":"+1 415 479 9700",
    "sg:postcode":"94903",
    "sg:province":"CA",
    "sg:tags":[
        "banker",
        "mortgage"
    ],
    "wof:name":"Paul Financial LLC",
    "wof:placetype":"venue"
},
  "geometry": {"coordinates":[-122.542433,38.019109],"type":"Point"}
}