{
  "type": "Feature",
  "properties": {
    "iso:country":"US",
    "sg:address":"3914 International Blvd",
    "sg:city":"Oakland",
    "sg:classifiers":[
        {
            "category":"Food & Beverages",
            "subcategory":"Specialty",
            "type":"Retail Goods"
        }
    ],
    "sg:phone":"+1 510 261 0791",
    "sg:postcode":"94601",
    "sg:province":"CA",
    "sg:tags":[
        "herb",
        "spice"
    ],
    "wof:name":"La Fuente De La Salud",
    "wof:placetype":"venue"
},
  "geometry": {"coordinates":[-122.21872399999999,37.774216],"type":"Point"}
}