{
  "type": "Feature",
  "properties": {
    "iso:country":"US",
    "sg:address":"5497 North Main Street",
    "sg:city":"Irvine",
    "sg:classifiers":[
        {
            "category":"Health Services",
            "subcategory":"Dentist",
            "type":"Services"
        }
    ],
    "sg:phone":"+1 949 734 4228",
    "sg:postcode":"92614",
    "sg:province":"CA",
    "sg:tags":[
        "cosmetic"
    ],
    "wof:name":"Best-Cosmetic-Dentist.org",
    "wof:placetype":"venue"
},
  "geometry": {"coordinates":[-117.828603,33.6771],"type":"Point"}
}