{
  "type": "Feature",
  "properties": {
    "addr:full":"1430 Fountain St Alameda CA 94501",
    "addr:housenumber":"1430",
    "addr:postcode":"94501",
    "addr:street":"Fountain St",
    "iso:country":"US",
    "sg:address":"1430 Fountain St",
    "sg:city":"Alameda",
    "sg:classifiers":[
        {
            "category":"Health Services",
            "subcategory":"Medical Lab",
            "type":"Services"
        }
    ],
    "sg:phone":"+1 510 522 3861",
    "sg:postcode":"94501",
    "sg:province":"CA",
    "sg:tags":[
        "laboratory"
    ],
    "wof:name":"Geneva Dental Studio",
    "wof:placetype":"venue"
},
  "geometry": {"coordinates":[-122.23199700000001,37.759288],"type":"Point"}
}