{
  "type": "Feature",
  "properties": {
    "iso:country":"US",
    "sg:address":"3809 Plaza Dr",
    "sg:city":"Oceanside",
    "sg:classifiers":[
        {
            "category":"Restaurant",
            "type":"Food & Drink"
        }
    ],
    "sg:phone":"+1 760 630 8889",
    "sg:postcode":"92056",
    "sg:province":"CA",
    "sg:tags":[
        "vietnamese"
    ],
    "sg:website":"www.ilovepho.net/",
    "wof:name":"I Love Pho",
    "wof:placetype":"venue"
},
  "geometry": {"coordinates":[-117.29304999999999,33.181533],"type":"Point"}
}