{
  "type": "Feature",
  "properties": {
    "addr:full":"4412 Macarthur Blvd Oakland CA 94619",
    "addr:housenumber":"4412",
    "addr:postcode":"94619",
    "addr:street":"Macarthur Blvd",
    "iso:country":"US",
    "sg:address":"4412 Macarthur Blvd",
    "sg:city":"Oakland",
    "sg:classifiers":[
        {
            "category":"Autos & Motor Vehicles",
            "subcategory":"Automobile Sales",
            "type":"Retail Goods"
        }
    ],
    "sg:phone":"+1 510 530 1800",
    "sg:postcode":"94619",
    "sg:province":"CA",
    "sg:tags":[
        "car",
        "used",
        "cars-wholesale",
        "dealers-used"
    ],
    "wof:name":"Scheberies Inc",
    "wof:placetype":"venue"
},
  "geometry": {"coordinates":[-122.193574,37.786204],"type":"Point"}
}