{
  "type": "Feature",
  "properties": {
    "iso:country":"US",
    "sg:address":"235 Palm Ave",
    "sg:city":"Santa Barbara",
    "sg:classifiers":[
        {
            "category":"Building & Trades",
            "subcategory":"Landscaping Services",
            "type":"Services"
        }
    ],
    "sg:phone":"+1 805 730 7444",
    "sg:postcode":"93101",
    "sg:province":"CA",
    "sg:tags":[
        "designer",
        "landscape"
    ],
    "wof:name":"Van Atta Associates",
    "wof:placetype":"venue"
},
  "geometry": {"coordinates":[-119.69083999999999,34.418283],"type":"Point"}
}