{
  "type": "Feature",
  "properties": {
    "iso:country":"US",
    "sg:address":"9335 Reseda Blvd",
    "sg:city":"Northridge",
    "sg:classifiers":[
        {
            "category":"Social Services",
            "type":"Services"
        }
    ],
    "sg:phone":"+1 818 701 0107",
    "sg:postcode":"91324",
    "sg:province":"CA",
    "sg:tags":[
        "counselor",
        "marriage",
        "family"
    ],
    "wof:name":"Living Springs Psychthrptc Svc",
    "wof:placetype":"venue"
},
  "geometry": {"coordinates":[-118.536163,34.240306],"type":"Point"}
}