{
  "type": "Feature",
  "properties": {
    "addr:full":"555 S Sunrise Way Palm Springs CA 92264",
    "addr:housenumber":"555",
    "addr:postcode":"92264",
    "addr:street":"S Sunrise Way",
    "iso:country":"US",
    "sg:address":"555 S Sunrise Way",
    "sg:city":"Palm Springs",
    "sg:classifiers":[
        {
            "category":"Restaurant",
            "type":"Food & Drink"
        }
    ],
    "sg:phone":"+1 760 323 8552",
    "sg:postcode":"92264",
    "sg:province":"CA",
    "sg:tags":[
        "pizza"
    ],
    "wof:name":"Cissy's Pizza",
    "wof:placetype":"venue"
},
  "geometry": {"coordinates":[-116.52825,33.8137],"type":"Point"}
}