{
  "type": "Feature",
  "properties": {
    "iso:country":"US",
    "sg:address":"14849 Vanowen St",
    "sg:city":"Van Nuys",
    "sg:classifiers":[
        {
            "category":"Retail",
            "subcategory":"Laundry & Dry Cleaning",
            "type":"Services"
        }
    ],
    "sg:phone":"+1 818 997 6823",
    "sg:postcode":"91405",
    "sg:province":"CA",
    "sg:tags":[
        "cleaners",
        "rug",
        "carpet"
    ],
    "wof:name":"A G Carpet Care",
    "wof:placetype":"venue"
},
  "geometry": {"coordinates":[-118.454753,34.193998],"type":"Point"}
}