{
  "type": "Feature",
  "properties": {
    "addr:full":"64 Sunnybrae Center Arcata CA 95521",
    "addr:housenumber":"64",
    "addr:postcode":"95521",
    "addr:street":"Sunnybrae Center",
    "iso:country":"US",
    "sg:address":"64 Sunnybrae Center",
    "sg:city":"Arcata",
    "sg:classifiers":[
        {
            "category":"Shopping",
            "subcategory":"Music",
            "type":"Retail Goods"
        }
    ],
    "sg:phone":"+1 707 825 1012",
    "sg:postcode":"95521",
    "sg:province":"CA",
    "sg:tags":[
        "compact",
        "record",
        "disc",
        "tape"
    ],
    "wof:name":"Hip Stop Record Shop",
    "wof:placetype":"venue"
},
  "geometry": {"coordinates":[-124.071961,40.857453],"type":"Point"}
}