{
  "type": "Feature",
  "properties": {
    "iso:country":"US",
    "sg:address":"5211 E Washington Blvd Suite 158",
    "sg:city":"Commerce",
    "sg:classifiers":[
        {
            "category":"Professional",
            "subcategory":"Employment Agencies",
            "type":"Services"
        }
    ],
    "sg:phone":"+1 323 838 1020",
    "sg:postcode":"90040",
    "sg:province":"CA",
    "sg:tags":[
        "opportunity",
        "temporary",
        "contractor"
    ],
    "sg:website":"www.remedystaff.com",
    "wof:name":"Remedy Intelligent Staffing",
    "wof:placetype":"venue"
},
  "geometry": {"coordinates":[-118.166763,34.003189],"type":"Point"}
}