{
  "type": "Feature",
  "properties": {
    "iso:country":"US",
    "sg:address":"1734 65th Ave",
    "sg:city":"Oakland",
    "sg:classifiers":[
        {
            "category":"Professional",
            "type":"Services"
        }
    ],
    "sg:phone":"+1 510 978 1443",
    "sg:postcode":"94620",
    "sg:province":"CA",
    "wof:name":"Absolute Best Drain Cleaning & Plumbing",
    "wof:placetype":"venue"
},
  "geometry": {"coordinates":[-122.19158400000001,37.764382],"type":"Point"}
}