{
  "type": "Feature",
  "properties": {
    "addr:full":"4 The Embarcadero San Francisco CA 94102",
    "addr:housenumber":"4",
    "addr:postcode":"94102",
    "addr:street":"The Embarcadero",
    "iso:country":"US",
    "sg:address":"4 The Embarcadero",
    "sg:city":"San Francisco",
    "sg:classifiers":[
        {
            "category":"Professional",
            "subcategory":"Lawyer & Legal Services",
            "type":"Services"
        }
    ],
    "sg:phone":"+1 415 981 1400",
    "sg:postcode":"94102",
    "sg:province":"CA",
    "sg:website":"www.greeneradovsky.com",
    "wof:name":"Knox Fumi Atty",
    "wof:placetype":"venue"
},
  "geometry": {"coordinates":[-122.390989,37.792603],"type":"Point"}
}