{
  "type": "Feature",
  "properties": {
    "addr:full":"1174 Airport Rd Monterey CA 93940",
    "addr:housenumber":"1174",
    "addr:postcode":"93940",
    "addr:street":"Airport Rd",
    "iso:country":"US",
    "sg:address":"1174 Airport Rd",
    "sg:city":"Monterey",
    "sg:classifiers":[
        {
            "category":"Local Transit",
            "type":"Transportation"
        }
    ],
    "sg:phone":"+1 831 643 2800",
    "sg:postcode":"93940",
    "sg:province":"CA",
    "sg:tags":[
        "limousine"
    ],
    "wof:name":"Your Maitre D",
    "wof:placetype":"venue"
},
  "geometry": {"coordinates":[-121.849129,36.592346],"type":"Point"}
}