{
  "type": "Feature",
  "properties": {
    "iso:country":"US",
    "sg:address":"814 27th St Frnt",
    "sg:city":"Oakland",
    "sg:classifiers":[
        {
            "category":"Personal",
            "subcategory":"Beauty Salon",
            "type":"Services"
        }
    ],
    "sg:phone":"+1 510 622 8171",
    "sg:postcode":"94607",
    "sg:province":"CA",
    "wof:name":"Klips Beauty Studio",
    "wof:placetype":"venue"
},
  "geometry": {"coordinates":[-122.274584,37.817509],"type":"Point"}
}