{
  "type": "Feature",
  "properties": {
    "iso:country":"US",
    "sg:address":"26811 Aliso Creek Rd",
    "sg:city":"Aliso Viejo",
    "sg:classifiers":[
        {
            "category":"Building & Trades",
            "subcategory":"Construction",
            "type":"Services"
        }
    ],
    "sg:phone":"+1 949 360 7916",
    "sg:postcode":"92656",
    "sg:province":"CA",
    "sg:tags":[
        "contractor"
    ],
    "wof:name":"Seaport Construction",
    "wof:placetype":"venue"
},
  "geometry": {"coordinates":[-117.723479,33.57141],"type":"Point"}
}