{
  "type": "Feature",
  "properties": {
    "addr:full":"78692 US Hwy 111 La Quinta CA 92253",
    "addr:housenumber":"78692",
    "addr:postcode":"92253",
    "addr:street":"Us Hwy 111",
    "iso:country":"US",
    "sg:address":"78692 US Hwy 111",
    "sg:city":"La Quinta",
    "sg:classifiers":[
        {
            "category":"Cinema",
            "subcategory":"Movie Rental",
            "type":"Entertainment"
        }
    ],
    "sg:phone":"+1 760 771 3331",
    "sg:postcode":"92253",
    "sg:province":"CA",
    "sg:tags":[
        "leasing",
        "video",
        "disc",
        "tape"
    ],
    "wof:name":"Blockbuster Video",
    "wof:placetype":"venue"
},
  "geometry": {"coordinates":[-116.293019,33.713881],"type":"Point"}
}