{
  "type": "Feature",
  "properties": {
    "iso:country":"US",
    "sg:address":"5220 Melrose Ave",
    "sg:city":"Los Angeles",
    "sg:classifiers":[
        {
            "category":"Home & Garden",
            "subcategory":"Furniture",
            "type":"Retail Goods"
        }
    ],
    "sg:phone":"+1 323 466 3705",
    "sg:postcode":"90038",
    "sg:province":"CA",
    "sg:tags":[
        "builder",
        "custom"
    ],
    "sg:website":"www.herculesfurniture.com",
    "wof:name":"Hercules Custom Furniture",
    "wof:placetype":"venue"
},
  "geometry": {"coordinates":[-118.31397800000001,34.083429],"type":"Point"}
}