{
  "type": "Feature",
  "properties": {
    "iso:country":"US",
    "sg:address":"1415 Garden Hwy",
    "sg:city":"Yuba City",
    "sg:classifiers":[
        {
            "category":"Retail",
            "subcategory":"Laundry & Dry Cleaning",
            "type":"Services"
        }
    ],
    "sg:phone":"+1 530 673 3441",
    "sg:postcode":"95991",
    "sg:province":"CA",
    "sg:tags":[
        "cleaners"
    ],
    "wof:name":"Zelie's Cleaners Alterations",
    "wof:placetype":"venue"
},
  "geometry": {"coordinates":[-121.61645900000001,39.10552],"type":"Point"}
}