{
  "type": "Feature",
  "properties": {
    "addr:full":"1000 Aurora St Stockton CA 95206",
    "addr:housenumber":"1000",
    "addr:postcode":"95206",
    "addr:street":"Aurora St",
    "iso:country":"US",
    "sg:address":"1000 Aurora St",
    "sg:city":"Stockton",
    "sg:classifiers":[
        {
            "category":"Wholesale",
            "subcategory":"Scrap",
            "type":"Manufacturing & Wholesale Goods"
        }
    ],
    "sg:phone":"+1 209 948 4000",
    "sg:postcode":"95206",
    "sg:province":"CA",
    "sg:tags":[
        "recycling",
        "center"
    ],
    "sg:website":"www.simsmetal.com",
    "wof:name":"Sims Metal",
    "wof:placetype":"venue"
},
  "geometry": {"coordinates":[-121.276403,37.943582],"type":"Point"}
}