{
  "type": "Feature",
  "properties": {
    "addr:full":"1412 14th St Los Osos CA 93402",
    "addr:housenumber":"1412",
    "addr:postcode":"93402",
    "addr:street":"14Th St",
    "iso:country":"US",
    "sg:address":"1412 14th St",
    "sg:city":"Los Osos",
    "sg:classifiers":[
        {
            "category":"Wholesale",
            "subcategory":"Durable Goods & Equipment",
            "type":"Manufacturing & Wholesale Goods"
        }
    ],
    "sg:phone":"+1 805 528 7763",
    "sg:postcode":"93402",
    "sg:province":"CA",
    "wof:name":"S & L Safety Products",
    "wof:placetype":"venue"
},
  "geometry": {"coordinates":[-120.82761499999999,35.325952],"type":"Point"}
}