{
  "type": "Feature",
  "properties": {
    "addr:full":"4777 E McKinley Ave Fresno CA 93703",
    "addr:housenumber":"4777",
    "addr:postcode":"93703",
    "addr:street":"E Mckinley Ave",
    "iso:country":"US",
    "sg:address":"4777 E McKinley Ave",
    "sg:city":"Fresno",
    "sg:classifiers":[
        {
            "category":"Restaurant",
            "type":"Food & Drink"
        }
    ],
    "sg:phone":"+1 559 252 4161",
    "sg:postcode":"93703",
    "sg:province":"CA",
    "sg:tags":[
        "delicatessen"
    ],
    "wof:name":"Airport Liquor",
    "wof:placetype":"venue"
},
  "geometry": {"coordinates":[-119.73690000000001,36.76524],"type":"Point"}
}