{
  "type": "Feature",
  "properties": {
    "addr:full":"565 Westlake St Frnt Encinitas CA 92024",
    "addr:housenumber":"565",
    "addr:postcode":"92024",
    "addr:street":"Westlake St",
    "iso:country":"US",
    "sg:address":"565 Westlake St Frnt",
    "sg:city":"Encinitas",
    "sg:classifiers":[
        {
            "category":"Shopping",
            "subcategory":"Hobbies, Toys, & Games",
            "type":"Retail Goods"
        }
    ],
    "sg:phone":"+1 760 634 5910",
    "sg:postcode":"92024",
    "sg:province":"CA",
    "sg:tags":[
        "toy",
        "store"
    ],
    "wof:name":"U S A Opoly Inc",
    "wof:placetype":"venue"
},
  "geometry": {"coordinates":[-117.278999,33.0462],"type":"Point"}
}