{
  "type": "Feature",
  "properties": {
    "addr:full":"2030 Burkett Rd South El Monte CA 91733",
    "addr:housenumber":"2030",
    "addr:postcode":"91733",
    "addr:street":"Burkett Rd",
    "iso:country":"US",
    "sg:address":"2030 Burkett Rd",
    "sg:city":"South El Monte",
    "sg:classifiers":[
        {
            "category":"Wholesale",
            "subcategory":"Home Furnishings",
            "type":"Manufacturing & Wholesale Goods"
        }
    ],
    "sg:phone":"+1 626 575 1504",
    "sg:postcode":"91733",
    "sg:province":"CA",
    "sg:tags":[
        "closet",
        "accessory"
    ],
    "wof:name":"Universal Closets",
    "wof:placetype":"venue"
},
  "geometry": {"coordinates":[-118.024675,34.04389],"type":"Point"}
}