{
  "type": "Feature",
  "properties": {
    "iso:country":"US",
    "sg:address":"17818 Regentview Ave",
    "sg:city":"Bellflower",
    "sg:classifiers":[
        {
            "category":"Building & Trades",
            "subcategory":"Plumbing",
            "type":"Services"
        }
    ],
    "sg:phone":"+1 562 925 9643",
    "sg:postcode":"90706",
    "sg:province":"CA",
    "wof:name":"Salie's Plumbing",
    "wof:placetype":"venue"
},
  "geometry": {"coordinates":[-118.112999,33.8699],"type":"Point"}
}