{
  "type": "Feature",
  "properties": {
    "addr:full":"1168 W San Madele Ave Fresno CA 93711",
    "addr:housenumber":"1168",
    "addr:postcode":"93711",
    "addr:street":"W San Madele Ave",
    "iso:country":"US",
    "sg:address":"1168 W San Madele Ave",
    "sg:city":"Fresno",
    "sg:classifiers":[
        {
            "category":"Professional",
            "type":"Services"
        }
    ],
    "sg:phone":"+1 559 435 3751",
    "sg:postcode":"93711",
    "sg:province":"CA",
    "sg:tags":[
        "establishment"
    ],
    "wof:name":"Outdoor Co",
    "wof:placetype":"venue"
},
  "geometry": {"coordinates":[-119.81058,36.814772],"type":"Point"}
}