{
  "type": "Feature",
  "properties": {
    "iso:country":"US",
    "sg:address":"4907 Shafter Ave",
    "sg:city":"Oakland",
    "sg:classifiers":[
        {
            "category":"Professional",
            "type":"Services"
        }
    ],
    "sg:phone":"+1 510 653 4576",
    "sg:postcode":"94609",
    "sg:province":"CA",
    "sg:tags":[
        "writer"
    ],
    "wof:name":"Temescal Writers",
    "wof:placetype":"venue"
},
  "geometry": {"coordinates":[-122.258621,37.835944],"type":"Point"}
}