{
  "type": "Feature",
  "properties": {
    "iso:country":"US",
    "sg:address":"232 Shoreline Hwy",
    "sg:city":"Mill Valley",
    "sg:classifiers":[
        {
            "category":"Manufacturing",
            "subcategory":"Metals",
            "type":"Manufacturing & Wholesale Goods"
        },
        {
            "category":"Retail",
            "subcategory":"Repair Shop",
            "type":"Services"
        }
    ],
    "sg:phone":"+1 415 388 9777",
    "sg:postcode":"94941",
    "sg:province":"CA",
    "sg:tags":[
        "machine",
        "re",
        "welding",
        "fabricated",
        "structural"
    ],
    "wof:name":"Bay Metalfab",
    "wof:placetype":"venue"
},
  "geometry": {"coordinates":[-122.524166,37.880752],"type":"Point"}
}