{
  "type": "Feature",
  "properties": {
    "iso:country":"US",
    "sg:address":"1800 S Main St",
    "sg:city":"Lakeport",
    "sg:classifiers":[
        {
            "category":"Real Estate",
            "subcategory":"Real Estate Operator",
            "type":"Services"
        }
    ],
    "sg:phone":"+1 707 263 4113",
    "sg:postcode":"95453",
    "sg:province":"CA",
    "sg:tags":[
        "mobile",
        "home",
        "community"
    ],
    "wof:name":"Lakeport Lagoons",
    "wof:placetype":"venue"
},
  "geometry": {"coordinates":[-122.915949,39.032374],"type":"Point"}
}