{
  "type": "Feature",
  "properties": {
    "addr:full":"627 Irving St San Francisco CA 94122",
    "addr:housenumber":"627",
    "addr:postcode":"94122",
    "addr:street":"Irving St",
    "iso:country":"US",
    "sg:address":"627 Irving St",
    "sg:city":"San Francisco",
    "sg:classifiers":[
        {
            "category":"Professional",
            "type":"Services"
        },
        {
            "category":"Food & Beverages",
            "subcategory":"Bakery",
            "type":"Retail Goods"
        }
    ],
    "sg:phone":"+1 415 753 8867",
    "sg:postcode":"94122",
    "sg:province":"CA",
    "sg:tags":[
        "sandwich",
        "caterer"
    ],
    "sg:website":"www.plutosfreshfood.com",
    "wof:name":"Pluto's",
    "wof:placetype":"venue"
},
  "geometry": {"coordinates":[-122.46471,37.763828],"type":"Point"}
}