{
  "type": "Feature",
  "properties": {
    "iso:country":"US",
    "sg:address":"5737 Adobe Rd",
    "sg:city":"Twentynine Palms",
    "sg:classifiers":[
        {
            "category":"Personal",
            "subcategory":"Beauty Salon",
            "type":"Services"
        }
    ],
    "sg:phone":"+1 760 361 3999",
    "sg:postcode":"92277",
    "sg:province":"CA",
    "sg:tags":[
        "manicuring"
    ],
    "wof:name":"29 Palms Spa & Nails",
    "wof:placetype":"venue"
},
  "geometry": {"coordinates":[-116.054101,34.148898],"type":"Point"}
}