{
  "type": "Feature",
  "properties": {
    "addr:full":"2606 Maple Ave Manhattan Beach CA 90266",
    "addr:housenumber":"2606",
    "addr:postcode":"90266",
    "addr:street":"Maple Ave",
    "iso:country":"US",
    "sg:address":"2606 Maple Ave",
    "sg:city":"Manhattan Beach",
    "sg:classifiers":[
        {
            "category":"Professional",
            "subcategory":"Advertising",
            "type":"Services"
        }
    ],
    "sg:phone":"+1 310 545 0414",
    "sg:postcode":"90266",
    "sg:province":"CA",
    "sg:tags":[
        "counselor"
    ],
    "wof:name":"Just Ellie Art Direction",
    "wof:placetype":"venue"
},
  "geometry": {"coordinates":[-118.402477,33.896084],"type":"Point"}
}