{
  "type": "Feature",
  "properties": {
    "addr:full":"11090 Rosemary Dr Auburn CA 95603",
    "addr:housenumber":"11090",
    "addr:postcode":"ca 95603",
    "addr:street":"Rosemary Dr",
    "iso:country":"US",
    "sg:address":"11090 Rosemary Dr",
    "sg:city":"Auburn",
    "sg:classifiers":[
        {
            "category":"Shopping",
            "subcategory":"Gifts & Souvenirs",
            "type":"Retail Goods"
        }
    ],
    "sg:phone":"+1 530 305 9066",
    "sg:postcode":"95603",
    "sg:province":"CA",
    "wof:name":"Brighter Side",
    "wof:placetype":"venue"
},
  "geometry": {"coordinates":[-121.078203,38.871939],"type":"Point"}
}