{
  "type": "Feature",
  "properties": {
    "iso:country":"US",
    "sg:address":"1070 N Ventura Ave",
    "sg:city":"Ventura",
    "sg:classifiers":[
        {
            "category":"Building & Trades",
            "subcategory":"Construction",
            "type":"Services"
        }
    ],
    "sg:phone":"+1 805 641 3656",
    "sg:postcode":"93001",
    "sg:province":"CA",
    "sg:tags":[
        "fence",
        "contractor"
    ],
    "wof:name":"Magnum Fence & Security",
    "wof:placetype":"venue"
},
  "geometry": {"coordinates":[-119.297233,34.29278],"type":"Point"}
}