{
  "type": "Feature",
  "properties": {
    "iso:country":"US",
    "sg:address":"77670 Springfield Ln",
    "sg:city":"Palm Desert",
    "sg:classifiers":[
        {
            "category":"Building & Trades",
            "subcategory":"Electrical",
            "type":"Services"
        }
    ],
    "sg:phone":"+1 760 200 5220",
    "sg:postcode":"92211",
    "sg:province":"CA",
    "sg:tags":[
        "electric",
        "contractor"
    ],
    "wof:name":"Rangel Electric",
    "wof:placetype":"venue"
},
  "geometry": {"coordinates":[-116.30896199999999,33.759442],"type":"Point"}
}