{
  "type": "Feature",
  "properties": {
    "iso:country":"US",
    "sg:address":"846 Carley Rd",
    "sg:city":"Santa Rosa",
    "sg:classifiers":[
        {
            "category":"Insurance",
            "subcategory":"Insurance Agent",
            "type":"Services"
        }
    ],
    "sg:phone":"+1 707 570 1938",
    "sg:postcode":"95405",
    "sg:province":"CA",
    "wof:name":"Amg Insurance Svc Inc",
    "wof:placetype":"venue"
},
  "geometry": {"coordinates":[-122.668959,38.446692],"type":"Point"}
}