{
  "type": "Feature",
  "properties": {
    "iso:country":"US",
    "sg:address":"2330 Santa Fe Ave",
    "sg:city":"Long Beach",
    "sg:classifiers":[
        {
            "category":"Banks & Credit Unions",
            "subcategory":"Financial Services",
            "type":"Services"
        }
    ],
    "sg:phone":"+1 562 424 8131",
    "sg:postcode":"90810",
    "sg:province":"CA",
    "sg:tags":[
        "broker",
        "mortgage"
    ],
    "wof:name":"Crown Equities",
    "wof:placetype":"venue"
},
  "geometry": {"coordinates":[-118.214996,33.7995],"type":"Point"}
}