{
  "type": "Feature",
  "properties": {
    "addr:full":"333 S Hope St Los Angeles CA 90071",
    "addr:housenumber":"333",
    "addr:postcode":"90071",
    "addr:street":"S Hope St",
    "iso:country":"US",
    "sg:address":"333 S Hope St",
    "sg:city":"Los Angeles",
    "sg:classifiers":[
        {
            "category":"Banks & Credit Unions",
            "subcategory":"Bank",
            "type":"Services"
        }
    ],
    "sg:phone":"+1 213 437 9300",
    "sg:postcode":"90071",
    "sg:province":"CA",
    "sg:tags":[
        "state",
        "commercial"
    ],
    "wof:name":"Jpmorgan Chase Bank Nat Assn",
    "wof:placetype":"venue"
},
  "geometry": {"coordinates":[-118.252275,34.053711],"type":"Point"}
}