{
  "type": "Feature",
  "properties": {
    "addr:full":"936 Yosemite St Stockton CA 95203",
    "addr:housenumber":"936",
    "addr:postcode":"95203",
    "addr:street":"Yosemite St",
    "iso:country":"US",
    "sg:address":"936 Yosemite St",
    "sg:city":"Stockton",
    "sg:classifiers":[
        {
            "category":"Personal",
            "subcategory":"Beauty Salon",
            "type":"Services"
        }
    ],
    "sg:phone":"+1 209 465 0324",
    "sg:postcode":"95203",
    "sg:province":"CA",
    "wof:name":"Miracle's Beauty Ctr",
    "wof:placetype":"venue"
},
  "geometry": {"coordinates":[-121.306652,37.959827],"type":"Point"}
}