{
  "type": "Feature",
  "properties": {
    "iso:country":"US",
    "sg:address":"2904 Rowena Ave",
    "sg:city":"Los Angeles",
    "sg:classifiers":[
        {
            "category":"Health Services",
            "subcategory":"Health Practitioner",
            "type":"Services"
        }
    ],
    "sg:phone":"+1 323 663 2998",
    "sg:postcode":"90039",
    "sg:province":"CA",
    "sg:tags":[
        "psychotherapist"
    ],
    "wof:name":"Silverlake Psychotherapy Assoc",
    "wof:placetype":"venue"
},
  "geometry": {"coordinates":[-118.26708,34.108027],"type":"Point"}
}