{
  "type": "Feature",
  "properties": {
    "iso:country":"US",
    "sg:address":"18600 Parthenia St",
    "sg:city":"Northridge",
    "sg:classifiers":[
        {
            "category":"Shopping",
            "type":"Retail Goods"
        }
    ],
    "sg:phone":"+1 818 349 0052",
    "sg:postcode":"91324",
    "sg:province":"CA",
    "sg:tags":[
        "candle"
    ],
    "wof:name":"Botanica LA Merced",
    "wof:placetype":"venue"
},
  "geometry": {"coordinates":[-118.540456,34.228234],"type":"Point"}
}