{
  "type": "Feature",
  "properties": {
    "iso:country":"US",
    "sg:address":"1875 21st Ave",
    "sg:city":"San Francisco",
    "sg:classifiers":[
        {
            "category":"Professional",
            "subcategory":"Computer Services",
            "type":"Services"
        }
    ],
    "sg:phone":"+1 415 753 0503",
    "sg:postcode":"94122",
    "sg:province":"CA",
    "sg:tags":[
        "internet"
    ],
    "wof:name":"Joy Time Gifts",
    "wof:placetype":"venue"
},
  "geometry": {"coordinates":[-122.478638,37.753685],"type":"Point"}
}