{
  "type": "Feature",
  "properties": {
    "iso:country":"US",
    "sg:address":"461 7th St W",
    "sg:city":"Sonoma",
    "sg:classifiers":[
        {
            "category":"Health Services",
            "subcategory":"Doctor",
            "type":"Services"
        }
    ],
    "sg:phone":"+1 707 938 1423",
    "sg:postcode":"95476",
    "sg:province":"CA",
    "sg:tags":[
        "physician",
        "surgeon"
    ],
    "wof:name":"L R Dondero MD",
    "wof:placetype":"venue"
},
  "geometry": {"coordinates":[-122.47163,38.29388],"type":"Point"}
}