{
  "type": "Feature",
  "properties": {
    "iso:country":"US",
    "sg:address":"1695 Alum Rock Avenue Suite 3",
    "sg:city":"San Jose",
    "sg:classifiers":[
        {
            "category":"Health Services",
            "subcategory":"Doctor",
            "type":"Services"
        }
    ],
    "sg:phone":"+1 408 923 9283",
    "sg:postcode":"95116",
    "sg:province":"CA",
    "wof:name":"South Bay Imaging Center",
    "wof:placetype":"venue"
},
  "geometry": {"coordinates":[-121.855934,37.35274],"type":"Point"}
}