{
  "type": "Feature",
  "properties": {
    "addr:full":"5180 Tapo Canyon Rd Simi Valley CA 93063",
    "addr:housenumber":"5180",
    "addr:postcode":"93063",
    "addr:street":"Tapo Canyon Rd",
    "iso:country":"US",
    "sg:address":"5180 Tapo Canyon Rd",
    "sg:city":"Simi Valley",
    "sg:classifiers":[
        {
            "category":"Farming",
            "subcategory":"Livestock Farm",
            "type":"Manufacturing & Wholesale Goods"
        }
    ],
    "sg:phone":"+1 805 526 0321",
    "sg:postcode":"93063",
    "sg:province":"CA",
    "sg:tags":[
        "equine"
    ],
    "wof:name":"Mike Boyle Ranches",
    "wof:placetype":"venue"
},
  "geometry": {"coordinates":[-118.71955,34.30703],"type":"Point"}
}