{
  "type": "Feature",
  "properties": {
    "iso:country":"US",
    "sg:address":"1000 E Washington Blvd",
    "sg:city":"Los Angeles",
    "sg:classifiers":[
        {
            "category":"Organizations",
            "subcategory":"Religious Organization",
            "type":"Services"
        }
    ],
    "sg:phone":"+1 213 749 1054",
    "sg:postcode":"90021",
    "sg:province":"CA",
    "wof:name":"Tabernaculo Biblico Bautista",
    "wof:placetype":"venue"
},
  "geometry": {"coordinates":[-118.253539,34.025938],"type":"Point"}
}