{
  "type": "Feature",
  "properties": {
    "addr:full":"10565 Arno Rd Galt CA 95632",
    "addr:housenumber":"10565",
    "addr:postcode":"95632",
    "addr:street":"Arno Rd",
    "iso:country":"US",
    "sg:address":"10565 Arno Rd",
    "sg:city":"Galt",
    "sg:classifiers":[
        {
            "category":"Professional",
            "type":"Services"
        }
    ],
    "sg:phone":"+1 209 745 6062",
    "sg:postcode":"95632",
    "sg:province":"CA",
    "wof:name":"Richard A Bjelland",
    "wof:placetype":"venue"
},
  "geometry": {"coordinates":[-121.29762599999999,38.333183],"type":"Point"}
}