{
  "type": "Feature",
  "properties": {
    "addr:full":"3330 Vincent Rd Pleasant Hill CA 94523",
    "addr:housenumber":"3330",
    "addr:postcode":"94523",
    "addr:street":"Vincent Rd",
    "iso:country":"US",
    "sg:address":"3330 Vincent Rd",
    "sg:city":"Pleasant Hill",
    "sg:classifiers":[
        {
            "category":"Retail",
            "subcategory":"Laundry & Dry Cleaning",
            "type":"Services"
        }
    ],
    "sg:phone":"+1 925 254 2866",
    "sg:postcode":"94523",
    "sg:province":"CA",
    "sg:tags":[
        "cleaners",
        "rug",
        "carpet"
    ],
    "wof:name":"Kirby Carpet Cleaning",
    "wof:placetype":"venue"
},
  "geometry": {"coordinates":[-122.05401999999999,37.94048],"type":"Point"}
}