{
  "type": "Feature",
  "properties": {
    "iso:country":"US",
    "sg:address":"361 Hospital Road",
    "sg:city":"Newport Beach",
    "sg:classifiers":[
        {
            "category":"Health Services",
            "subcategory":"Doctor",
            "type":"Services"
        }
    ],
    "sg:phone":"+1 949 574 0777",
    "sg:postcode":"92663",
    "sg:province":"CA",
    "wof:name":"Yu Michael MD",
    "wof:placetype":"venue"
},
  "geometry": {"coordinates":[-117.930525,33.625762],"type":"Point"}
}