{
  "type": "Feature",
  "properties": {
    "addr:full":"620 S Grand Ave Santa Ana CA 92705",
    "addr:housenumber":"620",
    "addr:postcode":"92705",
    "addr:street":"S Grand Ave",
    "iso:country":"US",
    "sg:address":"620 S Grand Ave",
    "sg:city":"Santa Ana",
    "sg:classifiers":[
        {
            "category":"Manufacturing",
            "subcategory":"Furniture",
            "type":"Manufacturing & Wholesale Goods"
        }
    ],
    "sg:phone":"+1 714 547 1446",
    "sg:postcode":"92705",
    "sg:province":"CA",
    "sg:tags":[
        "mfg"
    ],
    "wof:name":"C&G Furniture",
    "wof:placetype":"venue"
},
  "geometry": {"coordinates":[-117.850308,33.740382],"type":"Point"}
}