{
  "type": "Feature",
  "properties": {
    "iso:country":"US",
    "sg:address":"21880 N Petaluma Ave",
    "sg:city":"Fort Bragg",
    "sg:classifiers":[
        {
            "category":"Freight",
            "type":"Transportation"
        }
    ],
    "sg:phone":"+1 707 964 8252",
    "sg:postcode":"95437",
    "sg:province":"CA",
    "wof:name":"Rex Smith Trucking",
    "wof:placetype":"venue"
},
  "geometry": {"coordinates":[-123.790524,39.454387],"type":"Point"}
}