{
  "type": "Feature",
  "properties": {
    "addr:full":"1633 Marina Ct San Mateo CA 94403",
    "addr:housenumber":"1633",
    "addr:postcode":"94403",
    "addr:street":"Marina Ct",
    "iso:country":"US",
    "sg:address":"1633 Marina Ct",
    "sg:city":"San Mateo",
    "sg:classifiers":[
        {
            "category":"Real Estate",
            "subcategory":"Real Estate Operator",
            "type":"Services"
        }
    ],
    "sg:phone":"+1 866 571 7179",
    "sg:postcode":"94403",
    "sg:province":"CA",
    "sg:tags":[
        "apartment"
    ],
    "sg:website":"www.chesapeakepoint.com/",
    "wof:name":"Chesapeake Point Apartments",
    "wof:placetype":"venue"
},
  "geometry": {"coordinates":[-122.285455,37.551647],"type":"Point"}
}