{
  "type": "Feature",
  "properties": {
    "addr:full":"38103 Cll Quedo Murrieta CA 92563",
    "addr:postcode":"38103;92563",
    "addr:street":"Cll Quedo",
    "iso:country":"US",
    "sg:address":"38103 Cll Quedo",
    "sg:city":"Murrieta",
    "sg:classifiers":[
        {
            "category":"Wholesale",
            "subcategory":"Apparel",
            "type":"Manufacturing & Wholesale Goods"
        }
    ],
    "sg:phone":"+1 951 600 2880",
    "sg:postcode":"92563",
    "sg:province":"CA",
    "sg:tags":[
        "piece"
    ],
    "wof:name":"Prescription Packaging Product",
    "wof:placetype":"venue"
},
  "geometry": {"coordinates":[-117.159302,33.567462],"type":"Point"}
}