{
  "type": "Feature",
  "properties": {
    "iso:country":"US",
    "sg:address":"2605 Carlsbad Blvd",
    "sg:city":"Carlsbad",
    "sg:classifiers":[
        {
            "category":"Education",
            "subcategory":"School",
            "type":"Public Place"
        }
    ],
    "sg:phone":"+1 760 729 2385",
    "sg:postcode":"92008",
    "sg:province":"CA",
    "sg:tags":[
        "high",
        "middle",
        "elementary"
    ],
    "sg:website":"www.armyandnavyacademy.org/defau...",
    "wof:name":"Army and Navy Academy",
    "wof:placetype":"venue"
},
  "geometry": {"coordinates":[-117.353996,33.161701],"type":"Point"}
}