{
  "type": "Feature",
  "properties": {
    "iso:country":"US",
    "sg:address":"1817 N Symphony St",
    "sg:city":"Anaheim",
    "sg:classifiers":[
        {
            "category":"Professional",
            "subcategory":"Computer Services",
            "type":"Services"
        }
    ],
    "sg:phone":"+1 714 970 7259",
    "sg:postcode":"92807",
    "sg:province":"CA",
    "sg:tags":[
        "repair"
    ],
    "sg:website":"www.jckcomputing.com",
    "wof:name":"JCK Computing",
    "wof:placetype":"venue"
},
  "geometry": {"coordinates":[-117.8095,33.868899],"type":"Point"}
}