{
  "type": "Feature",
  "properties": {
    "addr:full":"8525 Madison Ave Fair Oaks CA 95628",
    "addr:housenumber":"8525",
    "addr:postcode":"95628",
    "addr:street":"Madison Ave",
    "iso:country":"US",
    "sg:address":"8525 Madison Ave",
    "sg:city":"Fair Oaks",
    "sg:classifiers":[
        {
            "category":"Real Estate",
            "subcategory":"Real Estate Services",
            "type":"Services"
        }
    ],
    "sg:phone":"+1 916 537 2600",
    "sg:postcode":"95628",
    "sg:province":"CA",
    "sg:tags":[
        "company",
        "title"
    ],
    "wof:name":"Financial Title Co",
    "wof:placetype":"venue"
},
  "geometry": {"coordinates":[-121.240073,38.664313],"type":"Point"}
}