{
  "type": "Feature",
  "properties": {
    "iso:country":"US",
    "sg:address":"14520 Whittram Ave",
    "sg:city":"Fontana",
    "sg:classifiers":[
        {
            "category":"Wholesale",
            "subcategory":"Machinery & Supplies",
            "type":"Manufacturing & Wholesale Goods"
        }
    ],
    "sg:phone":"+1 909 829 9230",
    "sg:postcode":"92335",
    "sg:province":"CA",
    "sg:tags":[
        "heavy",
        "equipment"
    ],
    "sg:website":"www.terryequipment.com",
    "wof:name":"Terry Equipment Inc",
    "wof:placetype":"venue"
},
  "geometry": {"coordinates":[-117.48482,34.095809],"type":"Point"}
}