{
  "type": "Feature",
  "properties": {
    "addr:full":"2501 Tipperay Ave South San Francisco CA 94080",
    "addr:housenumber":"2501",
    "addr:postcode":"94080",
    "addr:street":"Tipperay Ave",
    "iso:country":"US",
    "sg:address":"2501 Tipperay Ave",
    "sg:city":"South San Francisco",
    "sg:classifiers":[
        {
            "category":"Social Services",
            "subcategory":"Child Care",
            "type":"Services"
        }
    ],
    "sg:phone":"+1 650 583 4099",
    "sg:postcode":"94080",
    "sg:province":"CA",
    "sg:tags":[
        "day"
    ],
    "wof:name":"Angelitos Family Day Care",
    "wof:placetype":"venue"
},
  "geometry": {"coordinates":[-122.451787,37.638624],"type":"Point"}
}