{
  "type": "Feature",
  "properties": {
    "iso:country":"US",
    "sg:address":"3515 Hill Crest Dr",
    "sg:city":"Westwood",
    "sg:classifiers":[
        {
            "category":"Building & Trades",
            "subcategory":"Construction",
            "type":"Services"
        }
    ],
    "sg:phone":"+1 530 596 3514",
    "sg:postcode":"96137",
    "sg:province":"CA",
    "sg:tags":[
        "painter"
    ],
    "wof:name":"Frederick A Lepage Painting",
    "wof:placetype":"venue"
},
  "geometry": {"coordinates":[-121.096976,40.276739],"type":"Point"}
}