{
  "type": "Feature",
  "properties": {
    "addr:full":"28382 Tricia Pl Escondido CA 92026",
    "addr:housenumber":"28382",
    "addr:postcode":"92026",
    "addr:street":"Tricia Pl",
    "iso:country":"US",
    "sg:address":"28382 Tricia Pl",
    "sg:city":"Escondido",
    "sg:classifiers":[
        {
            "category":"Professional",
            "subcategory":"Business Services",
            "type":"Services"
        }
    ],
    "sg:phone":"+1 760 749 4222",
    "sg:postcode":"92026",
    "sg:province":"CA",
    "wof:name":"Quelque Chose Ltd",
    "wof:placetype":"venue"
},
  "geometry": {"coordinates":[-117.112482,33.221934],"type":"Point"}
}