{
  "type": "Feature",
  "properties": {
    "iso:country":"US",
    "sg:address":"1675 California St",
    "sg:city":"San Francisco",
    "sg:classifiers":[
        {
            "category":"Government",
            "subcategory":"City Hall",
            "type":"Public Place"
        }
    ],
    "sg:phone":"+1 415 982 8999",
    "sg:postcode":"94109",
    "sg:province":"CA",
    "sg:website":"www.volunteercentersbayarea.org/...",
    "wof:name":"The Volunteer Center",
    "wof:placetype":"venue"
},
  "geometry": {"coordinates":[-122.42191099999999,37.790389],"type":"Point"}
}