{
  "type": "Feature",
  "properties": {
    "addr:full":"9500 Jeronimo Rd Irvine CA 92618",
    "addr:housenumber":"9500",
    "addr:postcode":"92618",
    "addr:street":"Jeronimo Rd",
    "iso:country":"US",
    "sg:address":"9500 Jeronimo Rd",
    "sg:city":"Irvine",
    "sg:classifiers":[
        {
            "category":"Manufacturing",
            "subcategory":"Chemicals & Compounds",
            "type":"Manufacturing & Wholesale Goods"
        }
    ],
    "sg:phone":"+1 949 598 1200",
    "sg:postcode":"92618",
    "sg:province":"CA",
    "sg:tags":[
        "product",
        "mfg",
        "diagnostic"
    ],
    "wof:name":"Bio-RAD E C S",
    "wof:placetype":"venue"
},
  "geometry": {"coordinates":[-117.719504,33.650862],"type":"Point"}
}