{
  "type": "Feature",
  "properties": {
    "addr:full":"1344 N McCadden Pl Los Angeles CA 90028",
    "addr:housenumber":"1344",
    "addr:postcode":"90028",
    "addr:street":"N Mccadden Pl",
    "iso:country":"US",
    "sg:address":"1344 N McCadden Pl",
    "sg:city":"Los Angeles",
    "sg:classifiers":[
        {
            "category":"Professional",
            "subcategory":"Business Services",
            "type":"Services"
        }
    ],
    "sg:phone":"+1 323 469 3202",
    "sg:postcode":"90028",
    "sg:province":"CA",
    "sg:tags":[
        "consultant",
        "production",
        "music"
    ],
    "wof:name":"John Vitale",
    "wof:placetype":"venue"
},
  "geometry": {"coordinates":[-118.337399,34.095363],"type":"Point"}
}