{
  "type": "Feature",
  "properties": {
    "iso:country":"US",
    "sg:address":"6600 Dumbarton Cir",
    "sg:city":"Fremont",
    "sg:classifiers":[
        {
            "category":"Education",
            "subcategory":"Special Training",
            "type":"Public Place"
        },
        {
            "category":"Education",
            "subcategory":"Vocational School",
            "type":"Public Place"
        },
        {
            "category":"Education",
            "subcategory":"School",
            "type":"Public Place"
        },
        {
            "category":"Education",
            "subcategory":"University",
            "type":"Public Place"
        }
    ],
    "sg:phone":"+1 877 268 3879",
    "sg:postcode":"94555",
    "sg:province":"CA",
    "sg:tags":[
        "college",
        "adult",
        "business"
    ],
    "sg:website":"http://www.kelleradvantage.com/landing36/index.html?vc=167328",
    "wof:name":"Keller Graduate School of Management",
    "wof:placetype":"venue"
},
  "geometry": {"coordinates":[-122.05919799999999,37.55001],"type":"Point"}
}