{
  "type": "Feature",
  "properties": {
    "addr:full":"8275 Happy Camp Rd Moorpark CA 93021",
    "addr:housenumber":"8275",
    "addr:postcode":"ca 93021",
    "addr:street":"Happy Camp Rd",
    "iso:country":"US",
    "sg:address":"8275 Happy Camp Rd",
    "sg:city":"Moorpark",
    "sg:classifiers":[
        {
            "category":"Recreation",
            "type":"Entertainment"
        }
    ],
    "sg:phone":"+1 805 532 1231",
    "sg:postcode":"93021",
    "sg:province":"CA",
    "sg:tags":[
        "stable"
    ],
    "wof:name":"Steve Cross Stables",
    "wof:placetype":"venue"
},
  "geometry": {"coordinates":[-118.88026000000001,34.318976],"type":"Point"}
}