{
  "type": "Feature",
  "properties": {
    "addr:full":"1434 6th St Santa Monica CA 90401",
    "addr:housenumber":"1434",
    "addr:postcode":"90401",
    "addr:street":"6Th St",
    "iso:country":"US",
    "sg:address":"1434 6th St",
    "sg:city":"Santa Monica",
    "sg:classifiers":[
        {
            "category":"Travel",
            "subcategory":"Travel Agent",
            "type":"Entertainment"
        }
    ],
    "sg:phone":"+1 310 458 1707",
    "sg:postcode":"90401",
    "sg:province":"CA",
    "sg:tags":[
        "agency"
    ],
    "wof:name":"S A T A",
    "wof:placetype":"venue"
},
  "geometry": {"coordinates":[-118.492199,34.017023],"type":"Point"}
}