{
  "type": "Feature",
  "properties": {
    "iso:country":"US",
    "sg:address":"21514 Norwalk Blvd",
    "sg:city":"Hawaiian Gardens",
    "sg:classifiers":[
        {
            "category":"Retail",
            "subcategory":"Repair Shop",
            "type":"Services"
        }
    ],
    "sg:phone":"+1 562 402 9695",
    "sg:postcode":"90716",
    "sg:province":"CA",
    "sg:tags":[
        "reupholstery",
        "furniture"
    ],
    "wof:name":"Jaime's Upholstery",
    "wof:placetype":"venue"
},
  "geometry": {"coordinates":[-118.071999,33.833599],"type":"Point"}
}