{
  "type": "Feature",
  "properties": {
    "addr:full":"41986 Fremont Blvd Fremont CA 94538",
    "addr:housenumber":"41986",
    "addr:postcode":"94538",
    "addr:street":"Fremont Blvd",
    "iso:country":"US",
    "sg:address":"41986 Fremont Blvd",
    "sg:city":"Fremont",
    "sg:classifiers":[
        {
            "category":"Professional",
            "type":"Services"
        }
    ],
    "sg:phone":"+1 510 797 7444",
    "sg:postcode":"94538",
    "sg:province":"CA",
    "sg:tags":[
        "establishment"
    ],
    "wof:name":"AAA Above Kings",
    "wof:placetype":"venue"
},
  "geometry": {"coordinates":[-121.957515,37.523949],"type":"Point"}
}