{
  "type": "Feature",
  "properties": {
    "iso:country":"US",
    "sg:address":"10001 Venice Boulevard",
    "sg:city":"Los Angeles",
    "sg:classifiers":[
        {
            "category":"Real Estate",
            "subcategory":"Real Estate Operator",
            "type":"Services"
        }
    ],
    "sg:phone":"+1 310 815 1355",
    "sg:postcode":"90034",
    "sg:province":"CA",
    "sg:tags":[
        "apartment"
    ],
    "sg:website":"www.equityapartments.com/Los-Ang...",
    "wof:name":"Victor On Venice",
    "wof:placetype":"venue"
},
  "geometry": {"coordinates":[-118.400144,34.022976],"type":"Point"}
}