{
  "type": "Feature",
  "properties": {
    "iso:country":"US",
    "sg:address":"3400 Pegasus Dr",
    "sg:city":"Bakersfield",
    "sg:classifiers":[
        {
            "category":"Government",
            "subcategory":"Post Office",
            "type":"Public Place"
        }
    ],
    "sg:phone":"+1 661 392 6178",
    "sg:postcode":"93308",
    "sg:province":"CA",
    "sg:tags":[
        "postal",
        "us"
    ],
    "wof:name":"Bakersfield Post Office",
    "wof:placetype":"venue"
},
  "geometry": {"coordinates":[-119.06822,35.436268],"type":"Point"}
}