{
  "type": "Feature",
  "properties": {
    "iso:country":"US",
    "sg:address":"732 N Avalon Blvd",
    "sg:city":"Wilmington",
    "sg:classifiers":[
        {
            "category":"Shopping",
            "subcategory":"Clothing, Apparel, & Fashions",
            "type":"Retail Goods"
        }
    ],
    "sg:phone":"+1 310 834 4360",
    "sg:postcode":"90744",
    "sg:province":"CA",
    "sg:tags":[
        "designer"
    ],
    "wof:name":"Ceres Discount Outlet",
    "wof:placetype":"venue"
},
  "geometry": {"coordinates":[-118.26236900000001,33.779016],"type":"Point"}
}