{
  "type": "Feature",
  "properties": {
    "iso:country":"US",
    "sg:address":"1590 W San Marcos Blvd",
    "sg:city":"San Marcos",
    "sg:classifiers":[
        {
            "category":"Health Services",
            "subcategory":"Nursing And Care Facility",
            "type":"Services"
        }
    ],
    "sg:phone":"+1 760 471 9904",
    "sg:postcode":"92078",
    "sg:province":"CA",
    "sg:tags":[
        "home",
        "retirement",
        "community"
    ],
    "wof:name":"Brookdale Place Of San Marcos",
    "wof:placetype":"venue"
},
  "geometry": {"coordinates":[-117.208234,33.131413],"type":"Point"}
}