{
  "type": "Feature",
  "properties": {
    "addr:full":"9892 Broadway Live Oak CA 95953",
    "addr:housenumber":"9892",
    "addr:postcode":"95953",
    "addr:street":"Broadway",
    "iso:country":"US",
    "sg:address":"9892 Broadway",
    "sg:city":"Live Oak",
    "sg:classifiers":[
        {
            "category":"Personal",
            "subcategory":"Beauty Salon",
            "type":"Services"
        }
    ],
    "sg:phone":"+1 530 695 2267",
    "sg:postcode":"95953",
    "sg:province":"CA",
    "wof:name":"Judy's Hair & Beauty Salon",
    "wof:placetype":"venue"
},
  "geometry": {"coordinates":[-121.662114,39.274779],"type":"Point"}
}