{
  "type": "Feature",
  "properties": {
    "addr:full":"565 E Lindo Ave Chico CA 95926",
    "addr:housenumber":"565",
    "addr:postcode":"95926",
    "addr:street":"E Lindo Ave",
    "iso:country":"US",
    "sg:address":"565 E Lindo Ave",
    "sg:city":"Chico",
    "sg:classifiers":[
        {
            "category":"Professional",
            "subcategory":"Accounting & Tax Preparation",
            "type":"Services"
        }
    ],
    "sg:phone":"+1 530 899 1370",
    "sg:postcode":"95926",
    "sg:province":"CA",
    "sg:tags":[
        "accountant"
    ],
    "wof:name":"Teri V Montz CPA",
    "wof:placetype":"venue"
},
  "geometry": {"coordinates":[-121.8455,39.750874],"type":"Point"}
}