{
  "type": "Feature",
  "properties": {
    "iso:country":"US",
    "sg:address":"600 N 13th Ave",
    "sg:city":"Upland",
    "sg:classifiers":[
        {
            "category":"Health Services",
            "subcategory":"Doctor",
            "type":"Services"
        }
    ],
    "sg:phone":"+1 866 571 6766",
    "sg:postcode":"91786",
    "sg:province":"CA",
    "sg:tags":[
        "physician",
        "surgeon",
        "kidneys",
        "surgeons",
        "nephrology"
    ],
    "sg:website":"http://www.davita.com/tools/find-a-center/display_map.cfm?recordID=3903&dav=1",
    "wof:name":"DaVita Upland",
    "wof:placetype":"venue"
},
  "geometry": {"coordinates":[-117.63352399999999,34.10045],"type":"Point"}
}