{
  "type": "Feature",
  "properties": {
    "addr:full":"2330 E 119th Street Los Angeles CA 90059",
    "addr:housenumber":"2330",
    "addr:postcode":"90059",
    "addr:street":"E 119Th Street",
    "iso:country":"US",
    "sg:address":"2330 E 119th Street",
    "sg:city":"Los Angeles",
    "sg:classifiers":[
        {
            "category":"Autos & Motor Vehicles",
            "subcategory":"Automobile Sales",
            "type":"Retail Goods"
        }
    ],
    "sg:phone":"+1 323 249 9675",
    "sg:postcode":"90059",
    "sg:province":"CA",
    "sg:tags":[
        "limo"
    ],
    "wof:name":"Johnson's Limousine Service",
    "wof:placetype":"venue"
},
  "geometry": {"coordinates":[-118.230749,33.92454],"type":"Point"}
}