{
  "type": "Feature",
  "properties": {
    "addr:full":"210 N 4th St Ste 150 San Jose CA 95112",
    "addr:housenumber":"210",
    "addr:postcode":"95112",
    "addr:street":"N 4Th St Ste 150",
    "iso:country":"US",
    "sg:address":"210 N 4th St Ste 150",
    "sg:city":"San Jose",
    "sg:classifiers":[
        {
            "category":"Professional",
            "subcategory":"Lawyer & Legal Services",
            "type":"Services"
        }
    ],
    "sg:phone":"+1 408 536 0500",
    "sg:postcode":"95112",
    "sg:province":"CA",
    "wof:name":"Berger & Hopkins",
    "wof:placetype":"venue"
},
  "geometry": {"coordinates":[-121.889999,37.340801],"type":"Point"}
}