{
  "type": "Feature",
  "properties": {
    "addr:full":"7095 Cerritos Ave Stanton CA 90680",
    "addr:housenumber":"7095",
    "addr:postcode":"ca 90680",
    "addr:street":"Cerritos Ave",
    "iso:country":"US",
    "sg:address":"7095 Cerritos Ave",
    "sg:city":"Stanton",
    "sg:classifiers":[
        {
            "category":"Wholesale",
            "subcategory":"Vending Machines",
            "type":"Manufacturing & Wholesale Goods"
        }
    ],
    "sg:phone":"+1 310 779 9302",
    "sg:postcode":"90680",
    "sg:province":"CA",
    "wof:name":"S & J Vending",
    "wof:placetype":"venue"
},
  "geometry": {"coordinates":[-118.009086,33.810082],"type":"Point"}
}