{
  "type": "Feature",
  "properties": {
    "addr:full":"7708 Industry Ave Pico Rivera CA 90660",
    "addr:housenumber":"7708",
    "addr:postcode":"90660",
    "addr:street":"Industry Ave",
    "iso:country":"US",
    "sg:address":"7708 Industry Ave",
    "sg:city":"Pico Rivera",
    "sg:classifiers":[
        {
            "category":"Local Transit",
            "type":"Transportation"
        }
    ],
    "sg:phone":"+1 562 801 1941",
    "sg:postcode":"90660",
    "sg:province":"CA",
    "wof:name":"Frank N Me Inc",
    "wof:placetype":"venue"
},
  "geometry": {"coordinates":[-118.112323,33.979411],"type":"Point"}
}