{
  "type": "Feature",
  "properties": {
    "addr:full":"1142 Orange Ave Coronado CA 92118",
    "addr:housenumber":"1142",
    "addr:postcode":"92118",
    "addr:street":"Orange Ave",
    "iso:country":"US",
    "sg:address":"1142 Orange Ave",
    "sg:city":"Coronado",
    "sg:classifiers":[
        {
            "category":"Arts & Performance",
            "subcategory":"Theater",
            "type":"Entertainment"
        }
    ],
    "sg:phone":"+1 619 437 0600",
    "sg:postcode":"92118",
    "sg:province":"CA",
    "sg:tags":[
        "performing"
    ],
    "sg:website":"www.lambsplayers.org",
    "wof:name":"Lamb's Players Theatre",
    "wof:placetype":"venue"
},
  "geometry": {"coordinates":[-117.179033,32.683991],"type":"Point"}
}