{
  "type": "Feature",
  "properties": {
    "addr:full":"2835 Camino Del Rio South Suite 220 San Diego CA 92108",
    "addr:housenumber":"2835",
    "addr:postcode":"92108",
    "addr:street":"Camino Del Rio South Suite 220",
    "iso:country":"US",
    "sg:address":"2835 Camino Del Rio South Suite 220",
    "sg:city":"San Diego",
    "sg:classifiers":[
        {
            "category":"Professional",
            "subcategory":"Employment Agencies",
            "type":"Services"
        }
    ],
    "sg:phone":"+1 619 574 7600",
    "sg:postcode":"92108",
    "sg:province":"CA",
    "sg:website":"www.astarstaffing.com",
    "wof:name":"A-Star Staffing",
    "wof:placetype":"venue"
},
  "geometry": {"coordinates":[-117.132868,32.769797],"type":"Point"}
}