{
  "type": "Feature",
  "properties": {
    "iso:country":"US",
    "sg:address":"1 Ferry Building",
    "sg:city":"San Francisco",
    "sg:classifiers":[
        {
            "category":"Restaurant",
            "type":"Food & Drink"
        }
    ],
    "sg:menulink":"http://www.allmenus.com/ca/san-francisco/61824-delica-rf-1/menu/",
    "sg:phone":"+1 415 834 0344",
    "sg:postcode":"94111",
    "sg:province":"CA",
    "sg:tags":[
        "japanese",
        "asian"
    ],
    "wof:name":"Delica rf-1",
    "wof:placetype":"venue"
},
  "geometry": {"coordinates":[-122.39318799999999,37.794653],"type":"Point"}
}