{
  "type": "Feature",
  "properties": {
    "addr:full":"49030 Seminole Dr Cabazon CA 92230",
    "addr:housenumber":"49030",
    "addr:postcode":"92230",
    "addr:street":"Seminole Dr",
    "iso:country":"US",
    "sg:address":"49030 Seminole Dr",
    "sg:city":"Cabazon",
    "sg:classifiers":[
        {
            "category":"Restaurant",
            "type":"Food & Drink"
        }
    ],
    "sg:phone":"+1 951 849 3301",
    "sg:postcode":"92230",
    "sg:province":"CA",
    "wof:name":"A & W Family Restaurant",
    "wof:placetype":"venue"
},
  "geometry": {"coordinates":[-116.812707,33.925893],"type":"Point"}
}