{
  "type": "Feature",
  "properties": {
    "addr:full":"3500 Carson Road #D2 Camino CA 95709",
    "addr:housenumber":"3500",
    "addr:postcode":"95709",
    "addr:street":"Carson Road # D2 Camino",
    "iso:country":"US",
    "sg:address":"3500 Carson Road #D2",
    "sg:city":"Camino",
    "sg:classifiers":[
        {
            "category":"Winery",
            "type":"Food & Drink"
        }
    ],
    "sg:phone":"+1 530 647 8078",
    "sg:postcode":"95709",
    "sg:province":"CA",
    "sg:website":"www.aurigawines.com",
    "wof:name":"Auriga Wine Cellars",
    "wof:placetype":"venue"
},
  "geometry": {"coordinates":[-120.70065,38.73949],"type":"Point"}
}