{
  "type": "Feature",
  "properties": {
    "iso:country":"US",
    "sg:address":"541 S Maclay St",
    "sg:city":"San Fernando",
    "sg:classifiers":[
        {
            "category":"Real Estate",
            "subcategory":"Real Estate Agent",
            "type":"Services"
        }
    ],
    "sg:phone":"+1 818 838 4975",
    "sg:postcode":"91340",
    "sg:province":"CA",
    "wof:name":"Oak Central Realty & Mortgage",
    "wof:placetype":"venue"
},
  "geometry": {"coordinates":[-118.445519,34.280315],"type":"Point"}
}