{
  "type": "Feature",
  "properties": {
    "addr:full":"555 Naples St Ofc Chula Vista CA 91911",
    "addr:housenumber":"555",
    "addr:postcode":"91911",
    "addr:street":"Naples St",
    "iso:country":"US",
    "sg:address":"555 Naples St Ofc",
    "sg:city":"Chula Vista",
    "sg:classifiers":[
        {
            "category":"Real Estate",
            "subcategory":"Real Estate Operator",
            "type":"Services"
        }
    ],
    "sg:phone":"+1 619 427 7373",
    "sg:postcode":"91911",
    "sg:province":"CA",
    "sg:tags":[
        "apartment"
    ],
    "wof:name":"Villa Seville Apartments",
    "wof:placetype":"venue"
},
  "geometry": {"coordinates":[-117.079002,32.610802],"type":"Point"}
}