{
  "type": "Feature",
  "properties": {
    "addr:full":"1427 E 6th St Los Angeles CA 90021",
    "addr:housenumber":"1427",
    "addr:postcode":"90021",
    "addr:street":"E 6Th St",
    "iso:country":"US",
    "sg:address":"1427 E 6th St",
    "sg:city":"Los Angeles",
    "sg:classifiers":[
        {
            "category":"Home & Garden",
            "subcategory":"Furniture",
            "type":"Retail Goods"
        }
    ],
    "sg:phone":"+1 213 995 0697",
    "sg:postcode":"90021",
    "sg:province":"CA",
    "sg:tags":[
        "builder",
        "custom"
    ],
    "wof:name":"Peter Alexander Furniture",
    "wof:placetype":"venue"
},
  "geometry": {"coordinates":[-118.23196900000001,34.038385],"type":"Point"}
}