{
  "type": "Feature",
  "properties": {
    "addr:full":"101 Daggett Dr San Jose CA 95134",
    "addr:housenumber":"101",
    "addr:postcode":"95134",
    "addr:street":"Daggett Dr",
    "iso:country":"US",
    "sg:address":"101 Daggett Dr",
    "sg:city":"San Jose",
    "sg:classifiers":[
        {
            "category":"Real Estate",
            "subcategory":"Real Estate Agent",
            "type":"Services"
        }
    ],
    "sg:phone":"+1 408 428 0648",
    "sg:postcode":"95134",
    "sg:province":"CA",
    "wof:name":"Silicon Valley Properties",
    "wof:placetype":"venue"
},
  "geometry": {"coordinates":[-121.931003,37.395493],"type":"Point"}
}