{
  "type": "Feature",
  "properties": {
    "iso:country":"US",
    "sg:address":"2724 School St",
    "sg:city":"Oakland",
    "sg:classifiers":[
        {
            "category":"Building & Trades",
            "subcategory":"Locksmith",
            "type":"Services"
        }
    ],
    "sg:phone":"+1 510 228 4884",
    "sg:postcode":"94602",
    "sg:province":"CA",
    "sg:tags":[
        "key"
    ],
    "wof:name":"Always Affective Available Emergency",
    "wof:placetype":"venue"
},
  "geometry": {"coordinates":[-122.217544,37.795905],"type":"Point"}
}