{
  "type": "Feature",
  "properties": {
    "iso:country":"US",
    "sg:address":"120 S Spalding Drive Suite 300",
    "sg:city":"Beverly Hills",
    "sg:classifiers":[
        {
            "category":"Health Services",
            "subcategory":"Doctor",
            "type":"Services"
        },
        {
            "category":"Health Services",
            "subcategory":"Health Practitioner",
            "type":"Services"
        }
    ],
    "sg:phone":"+1 310 657 7600",
    "sg:postcode":"90212",
    "sg:province":"CA",
    "sg:tags":[
        "acupuncture"
    ],
    "wof:name":"Marshak Harry MD",
    "wof:placetype":"venue"
},
  "geometry": {"coordinates":[-118.400189,34.06227],"type":"Point"}
}