{
  "type": "Feature",
  "properties": {
    "addr:full":"7611 Beach Blvd Buena Park CA 90620",
    "addr:housenumber":"7611",
    "addr:postcode":"90620",
    "addr:street":"Beach Blvd",
    "iso:country":"US",
    "sg:address":"7611 Beach Blvd",
    "sg:city":"Buena Park",
    "sg:classifiers":[
        {
            "category":"Restaurant",
            "type":"Food & Drink"
        }
    ],
    "sg:menulink":"http://www.allmenus.com/ca/anaheim-santa-ana-garden-grove/172109-burger-king/menu/",
    "sg:phone":"+1 714 523 2324",
    "sg:postcode":"90620",
    "sg:province":"CA",
    "sg:tags":[
        "burger",
        "american"
    ],
    "wof:name":"Burger King",
    "wof:placetype":"venue"
},
  "geometry": {"coordinates":[-117.99848299999999,33.853222],"type":"Point"}
}