{
  "type": "Feature",
  "properties": {
    "iso:country":"US",
    "sg:address":"308 Mchenry Rd",
    "sg:city":"Glendale",
    "sg:classifiers":[
        {
            "category":"Building & Trades",
            "subcategory":"Landscaping Services",
            "type":"Services"
        }
    ],
    "sg:phone":"+1 818 507 7454",
    "sg:postcode":"91206",
    "sg:province":"CA",
    "sg:tags":[
        "landscape",
        "contractor"
    ],
    "wof:name":"Bedrose M Derbedrosian",
    "wof:placetype":"venue"
},
  "geometry": {"coordinates":[-118.23922,34.149987],"type":"Point"}
}