{
  "type": "Feature",
  "properties": {
    "addr:full":"4131 Manzanita Irvine CA 92604",
    "addr:housenumber":"4131",
    "addr:postcode":"92604",
    "addr:street":"Manzanita",
    "iso:country":"US",
    "sg:address":"4131 Manzanita",
    "sg:city":"Irvine",
    "sg:classifiers":[
        {
            "category":"Real Estate",
            "subcategory":"Real Estate Agent",
            "type":"Services"
        }
    ],
    "sg:phone":"+1 949 559 6211",
    "sg:postcode":"92604",
    "sg:province":"CA",
    "wof:name":"Barot Real Estate",
    "wof:placetype":"venue"
},
  "geometry": {"coordinates":[-117.78946000000001,33.699965],"type":"Point"}
}