{
  "type": "Feature",
  "properties": {
    "addr:full":"15011 Highland Valley Rd Escondido CA 92025",
    "addr:housenumber":"15011",
    "addr:postcode":"92025",
    "addr:street":"Highland Valley Rd",
    "iso:country":"US",
    "sg:address":"15011 Highland Valley Rd",
    "sg:city":"Escondido",
    "sg:classifiers":[
        {
            "category":"Professional",
            "subcategory":"Computer Services",
            "type":"Services"
        }
    ],
    "sg:phone":"+1 760 740 1787",
    "sg:postcode":"92025",
    "sg:province":"CA",
    "sg:tags":[
        "scanning"
    ],
    "sg:website":"www.dwmi.com",
    "wof:name":"Digital West Media Inc",
    "wof:placetype":"venue"
},
  "geometry": {"coordinates":[-117.011613,33.066257],"type":"Point"}
}