{
  "type": "Feature",
  "properties": {
    "addr:full":"1650 Park St Alameda CA 94501",
    "addr:housenumber":"1650",
    "addr:postcode":"94501",
    "addr:street":"Park St",
    "iso:country":"US",
    "sg:address":"1650 Park St",
    "sg:city":"Alameda",
    "sg:classifiers":[
        {
            "category":"Wholesale",
            "subcategory":"Poultry",
            "type":"Manufacturing & Wholesale Goods"
        },
        {
            "category":"Food & Beverages",
            "subcategory":"Meat & Fish",
            "type":"Retail Goods"
        }
    ],
    "sg:phone":"+1 510 864 1915",
    "sg:postcode":"94501",
    "sg:province":"CA",
    "sg:tags":[
        "seafood",
        "market"
    ],
    "sg:website":"www.baronsmeats.com",
    "wof:name":"Baron's Meat & Poultry",
    "wof:placetype":"venue"
},
  "geometry": {"coordinates":[-122.239408,37.767776],"type":"Point"}
}