{
  "type": "Feature",
  "properties": {
    "addr:full":"616 Grant Ave San Francisco CA 94108",
    "addr:housenumber":"616",
    "addr:postcode":"94108",
    "addr:street":"Grant Ave",
    "iso:country":"US",
    "sg:address":"616 Grant Ave",
    "sg:city":"San Francisco",
    "sg:classifiers":[
        {
            "category":"Shopping",
            "subcategory":"Jewelry",
            "type":"Retail Goods"
        }
    ],
    "sg:phone":"+1 415 362 5750",
    "sg:postcode":"94108",
    "sg:province":"CA",
    "sg:tags":[
        "jeweler"
    ],
    "wof:name":"Canton Bazaar",
    "wof:placetype":"venue"
},
  "geometry": {"coordinates":[-122.40603,37.79324],"type":"Point"}
}