{
  "type": "Feature",
  "properties": {
    "iso:country":"US",
    "sg:address":"101 S Shafter Ave",
    "sg:city":"Shafter",
    "sg:classifiers":[
        {
            "category":"Restaurant",
            "type":"Food & Drink"
        }
    ],
    "sg:phone":"+1 661 746 3079",
    "sg:postcode":"93263",
    "sg:province":"CA",
    "wof:name":"El Taco Loco",
    "wof:placetype":"venue"
},
  "geometry": {"coordinates":[-119.278311,35.499839],"type":"Point"}
}