{
  "type": "Feature",
  "properties": {
    "addr:full":"969 Buckaroo Ln Bonita CA 91902",
    "addr:housenumber":"969",
    "addr:postcode":"91902",
    "addr:street":"Buckaroo Ln",
    "iso:country":"US",
    "sg:address":"969 Buckaroo Ln",
    "sg:city":"Bonita",
    "sg:classifiers":[
        {
            "category":"Professional",
            "subcategory":"Business Services",
            "type":"Services"
        }
    ],
    "sg:phone":"+1 619 479 5447",
    "sg:postcode":"91902",
    "sg:province":"CA",
    "sg:tags":[
        "auctioneer"
    ],
    "wof:name":"Brandywine Auction Co",
    "wof:placetype":"venue"
},
  "geometry": {"coordinates":[-117.030021,32.656459],"type":"Point"}
}