{
  "type": "Feature",
  "properties": {
    "iso:country":"US",
    "sg:address":"203 E St",
    "sg:city":"Fresno",
    "sg:classifiers":[
        {
            "category":"Shopping",
            "type":"Retail Goods"
        }
    ],
    "sg:phone":"+1 559 283 8973",
    "sg:postcode":"93706",
    "sg:province":"CA",
    "sg:tags":[
        "merchandise"
    ],
    "wof:name":"World Products",
    "wof:placetype":"venue"
},
  "geometry": {"coordinates":[-119.78729300000001,36.721822],"type":"Point"}
}