{
  "type": "Feature",
  "properties": {
    "addr:full":"3711 S Port Dr Sacramento CA 95826",
    "addr:housenumber":"3711",
    "addr:postcode":"95826",
    "addr:street":"S Port Dr",
    "iso:country":"US",
    "sg:address":"3711 S Port Dr",
    "sg:city":"Sacramento",
    "sg:classifiers":[
        {
            "category":"Freight",
            "type":"Transportation"
        }
    ],
    "sg:phone":"+1 916 362 5037",
    "sg:postcode":"95826",
    "sg:province":"CA",
    "sg:tags":[
        "operator",
        "local",
        "trucking"
    ],
    "wof:name":"Hundal Trucking",
    "wof:placetype":"venue"
},
  "geometry": {"coordinates":[-121.362253,38.546185],"type":"Point"}
}