{
  "type": "Feature",
  "properties": {
    "iso:country":"US",
    "sg:address":"7100 Fruitridge Rd",
    "sg:city":"Sacramento",
    "sg:classifiers":[
        {
            "category":"Utilities",
            "subcategory":"Mobile Phone",
            "type":"Services"
        }
    ],
    "sg:phone":"+1 916 387 8799",
    "sg:postcode":"95820",
    "sg:province":"CA",
    "sg:tags":[
        "telephone",
        "cellular"
    ],
    "sg:website":"www.facebook.com/home.php?ref=ho...",
    "wof:name":"Cellular Express",
    "wof:placetype":"venue"
},
  "geometry": {"coordinates":[-121.420998,38.525002],"type":"Point"}
}