{
  "type": "Feature",
  "properties": {
    "iso:country":"US",
    "sg:address":"1255 Kern St",
    "sg:city":"Fresno",
    "sg:classifiers":[
        {
            "category":"Shopping",
            "subcategory":"Computers & Home Electronics",
            "type":"Retail Goods"
        }
    ],
    "sg:phone":"+1 559 266 3632",
    "sg:postcode":"93706",
    "sg:province":"CA",
    "sg:tags":[
        "television",
        "radio"
    ],
    "wof:name":"Ancel's Color TV",
    "wof:placetype":"venue"
},
  "geometry": {"coordinates":[-119.79646099999999,36.727658],"type":"Point"}
}