{
  "type": "Feature",
  "properties": {
    "addr:full":"303 Potrero St #45-101 Santa Cruz CA 95060",
    "addr:housenumber":"303",
    "addr:postcode":"95060",
    "addr:street":"Potrero St # 45-101",
    "iso:country":"US",
    "sg:address":"303 Potrero St #45-101",
    "sg:city":"Santa Cruz",
    "sg:classifiers":[
        {
            "category":"Shopping",
            "subcategory":"Clothing, Apparel, & Fashions",
            "type":"Retail Goods"
        },
        {
            "category":"Shopping",
            "subcategory":"Bridal",
            "type":"Retail Goods"
        }
    ],
    "sg:postcode":"95060",
    "sg:province":"CA",
    "sg:tags":[
        "lingerie",
        "clothing",
        "women's"
    ],
    "sg:website":"www.henryandjune.com",
    "wof:name":"Henry And June",
    "wof:placetype":"venue"
},
  "geometry": {"coordinates":[-122.031648,36.980784],"type":"Point"}
}