{
  "type": "Feature",
  "properties": {
    "iso:country":"US",
    "sg:address":"2520 50th Ave",
    "sg:city":"Sacramento",
    "sg:classifiers":[
        {
            "category":"Health Services",
            "subcategory":"Doctor",
            "type":"Services"
        }
    ],
    "sg:phone":"+1 916 703 0300",
    "sg:postcode":"95822",
    "sg:province":"CA",
    "sg:tags":[
        "practice",
        "family"
    ],
    "wof:name":"Uc Davis Medical Group",
    "wof:placetype":"venue"
},
  "geometry": {"coordinates":[-121.479794,38.506543],"type":"Point"}
}