{
  "type": "Feature",
  "properties": {
    "addr:full":"534 Valley Blvd, #1 San Gabriel CA 91776",
    "addr:housenumber":"534",
    "addr:postcode":"91776",
    "addr:street":"Valley Blvd # 1",
    "iso:country":"US",
    "sg:address":"534 Valley Blvd, #1",
    "sg:city":"San Gabriel",
    "sg:classifiers":[
        {
            "category":"Restaurant",
            "type":"Food & Drink"
        }
    ],
    "sg:phone":"+1 626 659 9777",
    "sg:postcode":"91776",
    "sg:province":"CA",
    "wof:name":"B.J. Tofu",
    "wof:placetype":"venue"
},
  "geometry": {"coordinates":[-118.108024,34.079355],"type":"Point"}
}