{
  "type": "Feature",
  "properties": {
    "addr:full":"1297 W El Camino Real Sunnyvale CA 94087",
    "addr:housenumber":"1297",
    "addr:postcode":"94087",
    "addr:street":"W El Camino Real",
    "iso:country":"US",
    "sg:address":"1297 W El Camino Real",
    "sg:city":"Sunnyvale",
    "sg:classifiers":[
        {
            "category":"Retail",
            "subcategory":"Auto Repair",
            "type":"Services"
        }
    ],
    "sg:phone":"+1 650 967 4030",
    "sg:postcode":"94087",
    "sg:province":"CA",
    "wof:name":"Bmb Motors",
    "wof:placetype":"venue"
},
  "geometry": {"coordinates":[-122.058998,37.375],"type":"Point"}
}