{
  "type": "Feature",
  "properties": {
    "addr:full":"1627 Lafayette St Santa Clara CA 95050",
    "addr:housenumber":"1627",
    "addr:postcode":"95050",
    "addr:street":"Lafayette St",
    "iso:country":"US",
    "sg:address":"1627 Lafayette St",
    "sg:city":"Santa Clara",
    "sg:classifiers":[
        {
            "category":"Manufacturing",
            "subcategory":"Tools & Machinery",
            "type":"Manufacturing & Wholesale Goods"
        }
    ],
    "sg:phone":"+1 408 727 0101",
    "sg:postcode":"95050",
    "sg:province":"CA",
    "sg:tags":[
        "equipment",
        "system",
        "automation"
    ],
    "wof:name":"Celmacs SMT",
    "wof:placetype":"venue"
},
  "geometry": {"coordinates":[-121.94663799999999,37.356498],"type":"Point"}
}