{
  "type": "Feature",
  "properties": {
    "iso:country":"US",
    "sg:address":"1627 Lafayette St",
    "sg:city":"Santa Clara",
    "sg:classifiers":[
        {
            "category":"Manufacturing",
            "subcategory":"Tools & Machinery",
            "type":"Manufacturing & Wholesale Goods"
        }
    ],
    "sg:phone":"+1 408 727 0101",
    "sg:postcode":"95050",
    "sg:province":"CA",
    "sg:tags":[
        "equipment",
        "system",
        "automation"
    ],
    "wof:name":"Celmacs SMT",
    "wof:placetype":"venue"
},
  "geometry": {"coordinates":[-121.946638,37.356498],"type":"Point"}
}