{
  "type": "Feature",
  "properties": {
    "iso:country":"US",
    "sg:address":"6690 Mission Gorge Rd Ste J",
    "sg:city":"San Diego",
    "sg:classifiers":[
        {
            "category":"Personal",
            "subcategory":"Massage",
            "type":"Services"
        },
        {
            "category":"Health Services",
            "subcategory":"Health Practitioner",
            "type":"Services"
        }
    ],
    "sg:phone":"+1 619 764 7117",
    "sg:postcode":"92120",
    "sg:province":"CA",
    "sg:tags":[
        "therapy",
        "physical"
    ],
    "sg:website":"www.serenityzonesd.com",
    "wof:name":"Serenity Zone",
    "wof:placetype":"venue"
},
  "geometry": {"coordinates":[-117.098688,32.793682],"type":"Point"}
}