{
  "type": "Feature",
  "properties": {
    "iso:country":"US",
    "sg:address":"604 S Beach Blvd",
    "sg:city":"Anaheim",
    "sg:classifiers":[
        {
            "category":"Shopping",
            "subcategory":"Catalog Store",
            "type":"Retail Goods"
        }
    ],
    "sg:phone":"+1 714 484 6778",
    "sg:postcode":"92804",
    "sg:province":"CA",
    "sg:tags":[
        "mail",
        "house"
    ],
    "wof:name":"Aoyagi Makiko",
    "wof:placetype":"venue"
},
  "geometry": {"coordinates":[-117.99332099999999,33.822911],"type":"Point"}
}