{
  "type": "Feature",
  "properties": {
    "addr:full":"4557 Mills Cir Ontario CA 91764",
    "addr:housenumber":"4557",
    "addr:postcode":"91764",
    "addr:street":"Mills Cir",
    "iso:country":"US",
    "sg:address":"4557 Mills Cir",
    "sg:city":"Ontario",
    "sg:classifiers":[
        {
            "category":"Manufacturing",
            "subcategory":"Retail Goods",
            "type":"Manufacturing & Wholesale Goods"
        }
    ],
    "sg:phone":"+1 909 980 2448",
    "sg:postcode":"91764",
    "sg:province":"CA",
    "sg:tags":[
        "manufacturer"
    ],
    "wof:name":"Nike Factory Store",
    "wof:placetype":"venue"
},
  "geometry": {"coordinates":[-117.55456599999999,34.070795],"type":"Point"}
}