{
  "type": "Feature",
  "properties": {
    "addr:full":"Arden Fair Mall Sacramento CA 95814",
    "addr:postcode":"95814",
    "iso:country":"US",
    "sg:address":"Arden Fair Mall",
    "sg:city":"Sacramento",
    "sg:classifiers":[
        {
            "category":"Health Services",
            "subcategory":"Optometrist",
            "type":"Services"
        },
        {
            "category":"Shopping",
            "subcategory":"Optician",
            "type":"Retail Goods"
        }
    ],
    "sg:phone":"+1 916 648 0209",
    "sg:postcode":"95814",
    "sg:province":"CA",
    "sg:tags":[
        "eyewear"
    ],
    "wof:name":"Pearle Vision",
    "wof:placetype":"venue"
},
  "geometry": {"coordinates":[-121.492394,38.57756],"type":"Point"}
}