{
  "type": "Feature",
  "properties": {
    "iso:country":"US",
    "sg:address":"1144 E Champlain Dr",
    "sg:city":"Fresno",
    "sg:classifiers":[
        {
            "category":"Restaurant",
            "type":"Food & Drink"
        },
        {
            "category":"Food & Beverages",
            "subcategory":"Ethnic Foods",
            "type":"Retail Goods"
        }
    ],
    "sg:phone":"+1 559 433 9200",
    "sg:postcode":"93720",
    "sg:province":"CA",
    "sg:tags":[
        "asian",
        "pan",
        "vietnamese"
    ],
    "wof:name":"Aqua Shi Asian Fusion Grill",
    "wof:placetype":"venue"
},
  "geometry": {"coordinates":[-119.764618,36.872299],"type":"Point"}
}