{
  "type": "Feature",
  "properties": {
    "iso:country":"US",
    "sg:address":"5405 Wilshire Blvd",
    "sg:city":"Los Angeles",
    "sg:classifiers":[
        {
            "category":"Education",
            "subcategory":"Special Training",
            "type":"Public Place"
        }
    ],
    "sg:phone":"+1 310 467 7687",
    "sg:postcode":"90036",
    "sg:province":"CA",
    "sg:tags":[
        "school",
        "language"
    ],
    "sg:website":"lahungarianteacher.com",
    "wof:name":"The Los Angeles Hungarian Teacher",
    "wof:placetype":"venue"
},
  "geometry": {"coordinates":[-118.346637,34.062343],"type":"Point"}
}