{
  "type": "Feature",
  "properties": {
    "addr:full":"2908 N Kenwood Ave San Bernardino CA 92404",
    "addr:housenumber":"2908",
    "addr:postcode":"92404",
    "addr:street":"N Kenwood Ave",
    "iso:country":"US",
    "sg:address":"2908 N Kenwood Ave",
    "sg:city":"San Bernardino",
    "sg:classifiers":[
        {
            "category":"Professional",
            "type":"Services"
        }
    ],
    "sg:phone":"+1 909 886 6623",
    "sg:postcode":"92404",
    "sg:province":"CA",
    "wof:name":"Chuck E Freshwater",
    "wof:placetype":"venue"
},
  "geometry": {"coordinates":[-117.276017,34.144417],"type":"Point"}
}