{
  "type": "Feature",
  "properties": {
    "iso:country":"US",
    "sg:address":"1031 E Latham Ave Ste 1",
    "sg:city":"Hemet",
    "sg:classifiers":[
        {
            "category":"Health Services",
            "subcategory":"Clinic",
            "type":"Services"
        }
    ],
    "sg:phone":"+1 951 306 9888",
    "sg:postcode":"92543",
    "sg:province":"CA",
    "sg:tags":[
        "welfare"
    ],
    "wof:name":"Salud Optima Medical Clin",
    "wof:placetype":"venue"
},
  "geometry": {"coordinates":[-116.961567,33.749397],"type":"Point"}
}