{
  "type": "Feature",
  "properties": {
    "addr:full":"13749 Riverside Dr Ste 201 Sherman Oaks CA 91423",
    "addr:housenumber":"13749",
    "addr:postcode":"91423",
    "addr:street":"Riverside Dr Ste 201",
    "iso:country":"US",
    "sg:address":"13749 Riverside Dr Ste 201",
    "sg:city":"Sherman Oaks",
    "sg:classifiers":[
        {
            "category":"Health Services",
            "subcategory":"Clinic",
            "type":"Services"
        }
    ],
    "sg:phone":"+1 818 209 7292",
    "sg:postcode":"91423",
    "sg:province":"CA",
    "sg:tags":[
        "counseling",
        "mental"
    ],
    "sg:website":"parentalkline.com",
    "wof:name":"Robert Schneider, LMFT",
    "wof:placetype":"venue"
},
  "geometry": {"coordinates":[-118.432822,34.157629],"type":"Point"}
}