{
  "type": "Feature",
  "properties": {
    "addr:full":"8230 Beverly Blvd Los Angeles CA 90048",
    "addr:housenumber":"8230",
    "addr:postcode":"90048",
    "addr:street":"Beverly Blvd",
    "iso:country":"US",
    "sg:address":"8230 Beverly Blvd",
    "sg:city":"Los Angeles",
    "sg:classifiers":[
        {
            "category":"Professional",
            "type":"Services"
        },
        {
            "category":"Manufacturing",
            "subcategory":"Printing",
            "type":"Manufacturing & Wholesale Goods"
        }
    ],
    "sg:phone":"+1 323 655 9001",
    "sg:postcode":"90048",
    "sg:province":"CA",
    "sg:tags":[
        "editorial",
        "periodical"
    ],
    "wof:name":"Weston Production",
    "wof:placetype":"venue"
},
  "geometry": {"coordinates":[-118.36995899999999,34.075992],"type":"Point"}
}