{
  "type": "Feature",
  "properties": {
    "iso:country":"US",
    "sg:address":"584 W Van Koevering St",
    "sg:city":"Rialto",
    "sg:classifiers":[
        {
            "category":"Social Services",
            "subcategory":"Adult Care",
            "type":"Services"
        }
    ],
    "sg:phone":"+1 909 874 1814",
    "sg:postcode":"92376",
    "sg:province":"CA",
    "sg:tags":[
        "home",
        "residential"
    ],
    "wof:name":"Tamarind Home",
    "wof:placetype":"venue"
},
  "geometry": {"coordinates":[-117.381472,34.112686],"type":"Point"}
}