{
  "type": "Feature",
  "properties": {
    "addr:full":"1100 Hensley St Richmond CA 94801",
    "addr:housenumber":"1100",
    "addr:postcode":"94801",
    "addr:street":"Hensley St",
    "iso:country":"US",
    "sg:address":"1100 Hensley St",
    "sg:city":"Richmond",
    "sg:classifiers":[
        {
            "category":"Manufacturing",
            "subcategory":"Chemicals & Compounds",
            "type":"Manufacturing & Wholesale Goods"
        }
    ],
    "sg:phone":"+1 510 234 8062",
    "sg:postcode":"94801",
    "sg:province":"CA",
    "sg:tags":[
        "bulk",
        "plant",
        "production",
        "gas"
    ],
    "wof:name":"Air Liquide America Corp",
    "wof:placetype":"venue"
},
  "geometry": {"coordinates":[-122.36303599999999,37.94942],"type":"Point"}
}