{
  "type": "Feature",
  "properties": {
    "addr:full":"403 49th St Oakland CA 94609",
    "addr:housenumber":"403",
    "addr:postcode":"94609",
    "addr:street":"49Th St",
    "iso:country":"US",
    "sg:address":"403 49th St",
    "sg:city":"Oakland",
    "sg:classifiers":[
        {
            "category":"Professional",
            "subcategory":"Computer Services",
            "type":"Services"
        }
    ],
    "sg:phone":"+1 510 530 8312",
    "sg:postcode":"94609",
    "sg:province":"CA",
    "sg:tags":[
        "consultant",
        "designer"
    ],
    "wof:name":"Donald J Hess & Assoc",
    "wof:placetype":"venue"
},
  "geometry": {"coordinates":[-122.25979599999999,37.835415],"type":"Point"}
}