{
  "type": "Feature",
  "properties": {
    "iso:country":"US",
    "sg:address":"4342 Moorpark Ave",
    "sg:city":"San Jose",
    "sg:classifiers":[
        {
            "category":"Food & Beverages",
            "subcategory":"Liquor & Beverages",
            "type":"Retail Goods"
        }
    ],
    "sg:phone":"+1 408 257 3200",
    "sg:postcode":"95129",
    "sg:province":"CA",
    "sg:tags":[
        "beer",
        "spirit",
        "wine"
    ],
    "wof:name":"Strawberry Park Liquors",
    "wof:placetype":"venue"
},
  "geometry": {"coordinates":[-121.978996,37.316002],"type":"Point"}
}