{
  "type": "Feature",
  "properties": {
    "iso:country":"US",
    "sg:address":"15732 Los Gatos Blvd",
    "sg:city":"Los Gatos",
    "sg:classifiers":[
        {
            "category":"Manufacturing",
            "subcategory":"Electronics",
            "type":"Manufacturing & Wholesale Goods"
        }
    ],
    "sg:phone":"+1 408 378 6540",
    "sg:postcode":"95032",
    "sg:province":"CA",
    "sg:tags":[
        "equipment",
        "electronic",
        "supply"
    ],
    "sg:website":"www.soundtechnology.com",
    "wof:name":"Sound Technology",
    "wof:placetype":"venue"
},
  "geometry": {"coordinates":[-121.961105,37.23978],"type":"Point"}
}