{
  "type": "Feature",
  "properties": {
    "addr:full":"140 E Santa Clara St Arcadia CA 91006",
    "addr:housenumber":"140",
    "addr:postcode":"91006",
    "addr:street":"E Santa Clara St",
    "iso:country":"US",
    "sg:address":"140 E Santa Clara St",
    "sg:city":"Arcadia",
    "sg:classifiers":[
        {
            "category":"Shopping",
            "subcategory":"Optician",
            "type":"Retail Goods"
        }
    ],
    "sg:phone":"+1 626 462 9834",
    "sg:postcode":"91006",
    "sg:province":"CA",
    "sg:tags":[
        "eyewear"
    ],
    "wof:name":"Ion Optical",
    "wof:placetype":"venue"
},
  "geometry": {"coordinates":[-118.68994499999999,34.142163],"type":"Point"}
}