{
  "type": "Feature",
  "properties": {
    "iso:country":"US",
    "sg:address":"54 N Oakland Ave",
    "sg:city":"Pasadena",
    "sg:classifiers":[
        {
            "category":"Organizations",
            "subcategory":"Non-profit Organization",
            "type":"Services"
        }
    ],
    "sg:phone":"+1 626 577 6987",
    "sg:postcode":"91101",
    "sg:province":"CA",
    "sg:tags":[
        "social"
    ],
    "wof:name":"Habbam",
    "wof:placetype":"venue"
},
  "geometry": {"coordinates":[-118.139867,34.14781],"type":"Point"}
}