{
  "type": "Feature",
  "properties": {
    "addr:full":"3300 Bridle Path Ln Modesto CA 95356",
    "addr:housenumber":"3300",
    "addr:postcode":"ca 95356",
    "addr:street":"Bridle Path Ln",
    "iso:country":"US",
    "sg:address":"3300 Bridle Path Ln",
    "sg:city":"Modesto",
    "sg:classifiers":[
        {
            "category":"Retail",
            "subcategory":"Repair Shop",
            "type":"Services"
        }
    ],
    "sg:phone":"+1 209 524 6110",
    "sg:postcode":"95356",
    "sg:province":"CA",
    "sg:tags":[
        "taxidermist"
    ],
    "wof:name":"Robert Brunetti Fish Artistry",
    "wof:placetype":"venue"
},
  "geometry": {"coordinates":[-121.03768599999999,37.688811],"type":"Point"}
}