{
  "type": "Feature",
  "properties": {
    "addr:full":"2211 San Elijo Ave Cardiff CA 92007",
    "addr:housenumber":"2211",
    "addr:postcode":"92007",
    "addr:street":"San Elijo Ave",
    "iso:country":"US",
    "sg:address":"2211 San Elijo Ave",
    "sg:city":"Cardiff",
    "sg:classifiers":[
        {
            "category":"Food & Beverages",
            "subcategory":"Groceries & Convenience Stores",
            "type":"Retail Goods"
        }
    ],
    "sg:phone":"+1 760 436 0895",
    "sg:postcode":"92007",
    "sg:province":"CA",
    "sg:website":"www.7-eleven.com",
    "wof:name":"7-Eleven",
    "wof:placetype":"venue"
},
  "geometry": {"coordinates":[-117.280998,33.019402],"type":"Point"}
}