{
  "type": "Feature",
  "properties": {
    "addr:full":"1912 Poli St Ventura CA 93001",
    "addr:housenumber":"1912",
    "addr:postcode":"93001",
    "addr:street":"Poli St",
    "iso:country":"US",
    "sg:address":"1912 Poli St",
    "sg:city":"Ventura",
    "sg:classifiers":[
        {
            "category":"Professional",
            "type":"Services"
        }
    ],
    "sg:phone":"+1 805 643 7153",
    "sg:postcode":"93001",
    "sg:province":"CA",
    "wof:name":"Mission First Aid & Safet",
    "wof:placetype":"venue"
},
  "geometry": {"coordinates":[-119.27090099999999,34.279864],"type":"Point"}
}