{
  "type": "Feature",
  "properties": {
    "iso:country":"US",
    "sg:address":"23023 Hilse Ln",
    "sg:city":"Newhall",
    "sg:classifiers":[
        {
            "category":"Organizations",
            "subcategory":"Religious Organization",
            "type":"Services"
        }
    ],
    "sg:phone":"+1 661 255 6410",
    "sg:postcode":"91321",
    "sg:province":"CA",
    "sg:tags":[
        "synagogue"
    ],
    "sg:website":"www.templebethami.org",
    "wof:name":"Temple Beth Ami A Reform Synagogue",
    "wof:placetype":"venue"
},
  "geometry": {"coordinates":[-118.540001,34.392101],"type":"Point"}
}