{
  "type": "Feature",
  "properties": {
    "addr:full":"616 W Hammer Ln Stockton CA 95210",
    "addr:housenumber":"616",
    "addr:postcode":"95210",
    "addr:street":"W Hammer Ln",
    "iso:country":"US",
    "sg:address":"616 W Hammer Ln",
    "sg:city":"Stockton",
    "sg:classifiers":[
        {
            "category":"Restaurant",
            "type":"Food & Drink"
        }
    ],
    "sg:menulink":"http://www.allmenus.com/ca/stockton/240066-panda-express/menu/",
    "sg:phone":"+1 209 475 0138",
    "sg:postcode":"95210",
    "sg:province":"CA",
    "sg:tags":[
        "asian",
        "chinese"
    ],
    "wof:name":"Panda Express",
    "wof:placetype":"venue"
},
  "geometry": {"coordinates":[-121.32002199999999,38.020952],"type":"Point"}
}