{
  "type": "Feature",
  "properties": {
    "iso:country":"US",
    "sg:address":"2603 W Pomona Blvd",
    "sg:city":"Pomona",
    "sg:classifiers":[
        {
            "category":"Wholesale",
            "subcategory":"Non-durable Goods",
            "type":"Manufacturing & Wholesale Goods"
        }
    ],
    "sg:phone":"+1 909 869 7789",
    "sg:postcode":"91768",
    "sg:province":"CA",
    "wof:name":"Acehigh Tech Corp",
    "wof:placetype":"venue"
},
  "geometry": {"coordinates":[-117.799094,34.055233],"type":"Point"}
}