{
  "type": "Feature",
  "properties": {
    "addr:full":"12338 Ventura Blvd Studio City CA 91604",
    "addr:housenumber":"12338",
    "addr:postcode":"91604",
    "addr:street":"Ventura Blvd",
    "iso:country":"US",
    "sg:address":"12338 Ventura Blvd",
    "sg:city":"Studio City",
    "sg:classifiers":[
        {
            "category":"Shopping",
            "subcategory":"Stationery & Office Supplies",
            "type":"Retail Goods"
        }
    ],
    "sg:phone":"+1 818 760 0244",
    "sg:postcode":"91604",
    "sg:province":"CA",
    "sg:tags":[
        "equipment"
    ],
    "sg:website":"www.anbstationery.com",
    "wof:name":"A N B Stationery Inc",
    "wof:placetype":"venue"
},
  "geometry": {"coordinates":[-118.40165,34.142863],"type":"Point"}
}