{
  "type": "Feature",
  "properties": {
    "addr:full":"7180 View Point Dr Aptos CA 95003",
    "addr:housenumber":"7180",
    "addr:postcode":"ca 95003",
    "addr:street":"View Point Dr",
    "iso:country":"US",
    "sg:address":"7180 View Point Dr",
    "sg:city":"Aptos",
    "sg:classifiers":[
        {
            "category":"Professional",
            "subcategory":"Management & Consulting",
            "type":"Services"
        }
    ],
    "sg:phone":"+1 831 661 0881",
    "sg:postcode":"95003",
    "sg:province":"CA",
    "sg:tags":[
        "marketing",
        "consultant"
    ],
    "wof:name":"GIG Productions",
    "wof:placetype":"venue"
},
  "geometry": {"coordinates":[-121.914692,36.989724],"type":"Point"}
}