{
  "type": "Feature",
  "properties": {
    "addr:full":"702 W Colton Ave Redlands CA 92374",
    "addr:housenumber":"702",
    "addr:postcode":"92374",
    "addr:street":"W Colton Ave",
    "iso:country":"US",
    "sg:address":"702 W Colton Ave",
    "sg:city":"Redlands",
    "sg:classifiers":[
        {
            "category":"Shopping",
            "type":"Retail Goods"
        }
    ],
    "sg:phone":"+1 909 307 3707",
    "sg:postcode":"92374",
    "sg:province":"CA",
    "sg:tags":[
        "wedding",
        "supply"
    ],
    "wof:name":"Wedding & Baby Shower",
    "wof:placetype":"venue"
},
  "geometry": {"coordinates":[-117.191383,34.062933],"type":"Point"}
}