{
  "type": "Feature",
  "properties": {
    "addr:full":"8747 S Main St San Joaquin CA 93660",
    "addr:housenumber":"8747",
    "addr:postcode":"93660",
    "addr:street":"S Main St",
    "iso:country":"US",
    "sg:address":"8747 S Main St",
    "sg:city":"San Joaquin",
    "sg:classifiers":[
        {
            "category":"Personal",
            "subcategory":"Beauty Salon",
            "type":"Services"
        }
    ],
    "sg:phone":"+1 559 693 4657",
    "sg:postcode":"93660",
    "sg:province":"CA",
    "wof:name":"Alicia's Beauty Palace",
    "wof:placetype":"venue"
},
  "geometry": {"coordinates":[-120.186626,36.607418],"type":"Point"}
}