{
  "type": "Feature",
  "properties": {
    "iso:country":"US",
    "sg:address":"3223 Centre Lake Dr",
    "sg:city":"Ontario",
    "sg:classifiers":[
        {
            "category":"Restaurant",
            "type":"Food & Drink"
        }
    ],
    "sg:menulink":"http://www.allmenus.com/ca/san-bernardino/236003-panda-inn/menu/",
    "sg:phone":"+1 909 390 2888",
    "sg:postcode":"91761",
    "sg:province":"CA",
    "sg:tags":[
        "asian",
        "chinese"
    ],
    "wof:name":"Panda Inn",
    "wof:placetype":"venue"
},
  "geometry": {"coordinates":[-117.58190399999999,34.066905],"type":"Point"}
}