{
  "type": "Feature",
  "properties": {
    "addr:full":"1959 Cheremoya Avenue Los Angeles CA 90068",
    "addr:housenumber":"1959",
    "addr:postcode":"90068",
    "addr:street":"Cheremoya Avenue",
    "iso:country":"US",
    "sg:address":"1959 Cheremoya Avenue",
    "sg:city":"Los Angeles",
    "sg:classifiers":[
        {
            "category":"Real Estate",
            "subcategory":"Real Estate Operator",
            "type":"Services"
        }
    ],
    "sg:phone":"+1 323 465 4655",
    "sg:postcode":"90068",
    "sg:province":"CA",
    "sg:tags":[
        "apartment"
    ],
    "wof:name":"Cheremoya Apartments",
    "wof:placetype":"venue"
},
  "geometry": {"coordinates":[-118.320453,34.106872],"type":"Point"}
}