{
  "type": "Feature",
  "properties": {
    "addr:full":"2620 Saturn Ave Huntington Park CA 90255",
    "addr:housenumber":"2620",
    "addr:postcode":"90255",
    "addr:street":"Saturn Ave;Park",
    "iso:country":"US",
    "sg:address":"2620 Saturn Ave",
    "sg:city":"Huntington Park",
    "sg:classifiers":[
        {
            "category":"Shopping",
            "subcategory":"Gifts & Souvenirs",
            "type":"Retail Goods"
        }
    ],
    "sg:phone":"+1 323 582 3103",
    "sg:postcode":"90255",
    "sg:province":"CA",
    "sg:tags":[
        "party",
        "supply"
    ],
    "wof:name":"Koko's Party Supplies",
    "wof:placetype":"venue"
},
  "geometry": {"coordinates":[-118.224998,33.976799],"type":"Point"}
}