{
  "type": "Feature",
  "properties": {
    "iso:country":"US",
    "sg:address":"3003 N Blackstone Ave",
    "sg:city":"Fresno",
    "sg:classifiers":[
        {
            "category":"Manufacturing",
            "subcategory":"Jewelry",
            "type":"Manufacturing & Wholesale Goods"
        }
    ],
    "sg:phone":"+1 559 226 0639",
    "sg:postcode":"93704",
    "sg:province":"CA",
    "sg:tags":[
        "mfg"
    ],
    "wof:name":"Glm Designs",
    "wof:placetype":"venue"
},
  "geometry": {"coordinates":[-119.79061400000001,36.778603],"type":"Point"}
}