{
  "type": "Feature",
  "properties": {
    "iso:country":"US",
    "sg:address":"100 Crest Dr",
    "sg:city":"Pismo Beach",
    "sg:classifiers":[
        {
            "category":"Government",
            "subcategory":"Post Office",
            "type":"Public Place"
        }
    ],
    "sg:phone":"+1 805 481 5971",
    "sg:postcode":"93449",
    "sg:province":"CA",
    "wof:name":"Pismo Beach Main Office",
    "wof:placetype":"venue"
},
  "geometry": {"coordinates":[-120.607974,35.13463],"type":"Point"}
}