{
  "type": "Feature",
  "properties": {
    "iso:country":"US",
    "sg:address":"20055 Lake Chabot Rd",
    "sg:city":"Castro Valley",
    "sg:classifiers":[
        {
            "category":"Health Services",
            "subcategory":"Doctor",
            "type":"Services"
        }
    ],
    "sg:phone":"+1 510 886 3138",
    "sg:postcode":"94546",
    "sg:province":"CA",
    "sg:tags":[
        "physician",
        "surgeon"
    ],
    "wof:name":"Pacific Brain & Spine Med Grp",
    "wof:placetype":"venue"
},
  "geometry": {"coordinates":[-122.08708799999999,37.697284],"type":"Point"}
}