{
  "type": "Feature",
  "properties": {
    "addr:full":"310 Townsend St San Francisco CA 94107",
    "addr:housenumber":"310",
    "addr:postcode":"94107",
    "addr:street":"Townsend St",
    "iso:country":"US",
    "sg:address":"310 Townsend St",
    "sg:city":"San Francisco",
    "sg:classifiers":[
        {
            "category":"Wholesale",
            "subcategory":"Seafood",
            "type":"Manufacturing & Wholesale Goods"
        }
    ],
    "sg:phone":"+1 415 401 0073",
    "sg:postcode":"94107",
    "sg:province":"CA",
    "wof:name":"Paramount Ocean Products Inc",
    "wof:placetype":"venue"
},
  "geometry": {"coordinates":[-122.397206,37.775332],"type":"Point"}
}