{
  "type": "Feature",
  "properties": {
    "addr:full":"2456 3rd St Livermore CA 94550",
    "addr:housenumber":"2456",
    "addr:postcode":"94550",
    "addr:street":"3Rd St",
    "iso:country":"US",
    "sg:address":"2456 3rd St",
    "sg:city":"Livermore",
    "sg:classifiers":[
        {
            "category":"Shopping",
            "subcategory":"Books",
            "type":"Retail Goods"
        }
    ],
    "sg:phone":"+1 925 373 7390",
    "sg:postcode":"94550",
    "sg:province":"CA",
    "sg:tags":[
        "dealer"
    ],
    "wof:name":"Pocket Book",
    "wof:placetype":"venue"
},
  "geometry": {"coordinates":[-121.765413,37.68197],"type":"Point"}
}