{
  "type": "Feature",
  "properties": {
    "iso:country":"US",
    "sg:address":"311 E Hillcrest Blvd",
    "sg:city":"Monrovia",
    "sg:classifiers":[
        {
            "category":"Place Of Worship",
            "type":"Public Place"
        }
    ],
    "sg:phone":"+1 626 815 8679",
    "sg:postcode":"91016",
    "sg:province":"CA",
    "sg:tags":[
        "church"
    ],
    "wof:name":"Alfatiha Center Inc",
    "wof:placetype":"venue"
},
  "geometry": {"coordinates":[-117.996369,34.160098],"type":"Point"}
}