{
  "type": "Feature",
  "properties": {
    "addr:full":"5397 Kingsley St Montclair CA 91763",
    "addr:housenumber":"5397",
    "addr:postcode":"91763",
    "addr:street":"Kingsley St",
    "iso:country":"US",
    "sg:address":"5397 Kingsley St",
    "sg:city":"Montclair",
    "sg:classifiers":[
        {
            "category":"Recreation",
            "type":"Entertainment"
        }
    ],
    "sg:phone":"+1 909 625 1164",
    "sg:postcode":"91763",
    "sg:province":"CA",
    "sg:tags":[
        "club",
        "baseball"
    ],
    "wof:name":"Montclair Little League",
    "wof:placetype":"venue"
},
  "geometry": {"coordinates":[-117.688044,34.066697],"type":"Point"}
}