{
  "type": "Feature",
  "properties": {
    "iso:country":"US",
    "sg:address":"17821 17th St",
    "sg:city":"Tustin",
    "sg:classifiers":[
        {
            "category":"Education",
            "subcategory":"Vocational School",
            "type":"Public Place"
        }
    ],
    "sg:phone":"+1 714 730 7080",
    "sg:postcode":"92780",
    "sg:province":"CA",
    "wof:name":"Adcon Technical Institutions",
    "wof:placetype":"venue"
},
  "geometry": {"coordinates":[-117.820984,33.75991],"type":"Point"}
}