{
  "type": "Feature",
  "properties": {
    "addr:full":"6929 E Nebraska Ave Selma CA 93662",
    "addr:housenumber":"6929",
    "addr:postcode":"93662",
    "addr:street":"E Nebraska Ave",
    "iso:country":"US",
    "sg:address":"6929 E Nebraska Ave",
    "sg:city":"Selma",
    "sg:classifiers":[
        {
            "category":"Freight",
            "type":"Transportation"
        }
    ],
    "sg:phone":"+1 559 896 3470",
    "sg:postcode":"93662",
    "sg:province":"CA",
    "sg:tags":[
        "trucking"
    ],
    "wof:name":"Boyajian Trucking",
    "wof:placetype":"venue"
},
  "geometry": {"coordinates":[-119.665932,36.561544],"type":"Point"}
}