{
  "type": "Feature",
  "properties": {
    "iso:country":"US",
    "sg:address":"7225 Owensmouth Ave",
    "sg:city":"Canoga Park",
    "sg:classifiers":[
        {
            "category":"Professional",
            "subcategory":"Accounting & Tax Preparation",
            "type":"Services"
        }
    ],
    "sg:phone":"+1 818 992 4692",
    "sg:postcode":"91303",
    "sg:province":"CA",
    "sg:tags":[
        "return",
        "filing"
    ],
    "wof:name":"OLA",
    "wof:placetype":"venue"
},
  "geometry": {"coordinates":[-118.601645,34.202397],"type":"Point"}
}