{
  "type": "Feature",
  "properties": {
    "iso:country":"US",
    "sg:address":"1809 Picasso Ave",
    "sg:city":"Davis",
    "sg:classifiers":[
        {
            "category":"Sports & Exercise",
            "subcategory":"Sports Center",
            "type":"Entertainment"
        },
        {
            "category":"Community Center",
            "type":"Public Place"
        },
        {
            "category":"Arena",
            "subcategory":"Sports Club",
            "type":"Entertainment"
        }
    ],
    "sg:phone":"+1 530 756 3200",
    "sg:postcode":"95618",
    "sg:province":"CA",
    "sg:tags":[
        "recreation",
        "soccer",
        "manager",
        "promoter"
    ],
    "wof:name":"Goalgetters Indoor Soccer",
    "wof:placetype":"venue"
},
  "geometry": {"coordinates":[-121.728979,38.564173],"type":"Point"}
}