{
  "type": "Feature",
  "properties": {
    "iso:country":"US",
    "sg:address":"745 S. Marengo Avenue",
    "sg:city":"Pasadena",
    "sg:classifiers":[
        {
            "category":"Health Services",
            "subcategory":"Clinic",
            "type":"Services"
        }
    ],
    "sg:phone":"+1 626 298 1047",
    "sg:postcode":"91106",
    "sg:province":"CA",
    "sg:tags":[
        "counseling",
        "mental"
    ],
    "sg:website":"www.DrFallynn.com",
    "wof:name":"Fallynn C. Cox, Psy.D.",
    "wof:placetype":"venue"
},
  "geometry": {"coordinates":[-118.146255,34.132651],"type":"Point"}
}