{
  "type": "Feature",
  "properties": {
    "iso:country":"US",
    "sg:address":"1123 Grand Ave",
    "sg:city":"Grover Beach",
    "sg:classifiers":[
        {
            "category":"Wholesale",
            "subcategory":"Electrical",
            "type":"Manufacturing & Wholesale Goods"
        }
    ],
    "sg:phone":"+1 805 474 8743",
    "sg:postcode":"93433",
    "sg:province":"CA",
    "sg:tags":[
        "sound",
        "equipment",
        "system"
    ],
    "wof:name":"Audio Habitat",
    "wof:placetype":"venue"
},
  "geometry": {"coordinates":[-120.617543,35.121464],"type":"Point"}
}