{
  "type": "Feature",
  "properties": {
    "addr:full":"2756 E Bidwell St Ste 300 Folsom CA 95630",
    "addr:housenumber":"2756",
    "addr:postcode":"95630",
    "addr:street":"E Bidwell St Ste 300",
    "iso:country":"US",
    "sg:address":"2756 E Bidwell St Ste 300",
    "sg:city":"Folsom",
    "sg:classifiers":[
        {
            "category":"Shopping",
            "subcategory":"Stationery & Office Supplies",
            "type":"Retail Goods"
        },
        {
            "category":"Professional",
            "type":"Services"
        },
        {
            "category":"Professional",
            "subcategory":"Business Services",
            "type":"Services"
        },
        {
            "category":"Government",
            "subcategory":"Post Office",
            "type":"Public Place"
        }
    ],
    "sg:phone":"+1 916 983 1610",
    "sg:postcode":"95630",
    "sg:province":"CA",
    "sg:tags":[
        "mailbox-rental",
        "shipping",
        "materials-shipping",
        "packaging",
        "packing",
        "notary",
        "mail",
        "receiving"
    ],
    "sg:website":"http://www.ampostal.com",
    "wof:name":"United States Postal Service",
    "wof:placetype":"venue"
},
  "geometry": {"coordinates":[-121.12387200000001,38.655191],"type":"Point"}
}