{
  "type": "Feature",
  "properties": {
    "addr:full":"1100 E Rosecrans Ave E Rancho Dmngz CA 90221",
    "addr:housenumber":"1100",
    "addr:postcode":"90221",
    "addr:street":"E Rosecrans Ave E",
    "iso:country":"US",
    "sg:address":"1100 E Rosecrans Ave",
    "sg:city":"E Rancho Dmngz",
    "sg:classifiers":[
        {
            "category":"Professional",
            "subcategory":"Accounting & Tax Preparation",
            "type":"Services"
        }
    ],
    "sg:phone":"+1 310 537 2512",
    "sg:postcode":"90221",
    "sg:province":"CA",
    "sg:tags":[
        "return",
        "filing"
    ],
    "wof:name":"Jasper Tax & Business Svc",
    "wof:placetype":"venue"
},
  "geometry": {"coordinates":[-118.21091699999999,33.903441],"type":"Point"}
}