{
  "type": "Feature",
  "properties": {
    "addr:full":"221 W Los Angeles Ave Moorpark CA 93021",
    "addr:housenumber":"221",
    "addr:postcode":"ca 93021",
    "addr:street":"W Los Angeles Ave",
    "iso:country":"US",
    "sg:address":"221 W Los Angeles Ave",
    "sg:city":"Moorpark",
    "sg:classifiers":[
        {
            "category":"Personal",
            "subcategory":"Beauty Salon",
            "type":"Services"
        }
    ],
    "sg:phone":"+1 805 529 8475",
    "sg:postcode":"93021",
    "sg:province":"CA",
    "wof:name":"Hair Concepts",
    "wof:placetype":"venue"
},
  "geometry": {"coordinates":[-118.80694099999999,34.28572],"type":"Point"}
}