{
  "type": "Feature",
  "properties": {
    "addr:full":"3015 Durahart St Riverside CA 92507",
    "addr:housenumber":"3015",
    "addr:postcode":"92507",
    "addr:street":"Durahart St",
    "iso:country":"US",
    "sg:address":"3015 Durahart St",
    "sg:city":"Riverside",
    "sg:classifiers":[
        {
            "category":"Building & Trades",
            "subcategory":"Plumbing",
            "type":"Services"
        }
    ],
    "sg:phone":"+1 951 682 3336",
    "sg:postcode":"92507",
    "sg:province":"CA",
    "sg:tags":[
        "conditioning",
        "air",
        "system",
        "contractor"
    ],
    "wof:name":"Hasco Heating Air",
    "wof:placetype":"venue"
},
  "geometry": {"coordinates":[-117.349942,33.984068],"type":"Point"}
}