{
  "type": "Feature",
  "properties": {
    "addr:full":"9816 Bus Park Dr Sacramento CA 95827",
    "addr:housenumber":"9816",
    "addr:postcode":"95827",
    "addr:street":"Bus Park Dr",
    "iso:country":"US",
    "sg:address":"9816 Bus Park Dr",
    "sg:city":"Sacramento",
    "sg:classifiers":[
        {
            "category":"Shopping",
            "type":"Retail Goods"
        }
    ],
    "sg:phone":"+1 916 364 7777",
    "sg:postcode":"95827",
    "sg:province":"CA",
    "sg:tags":[
        "spa",
        "hot",
        "tub"
    ],
    "wof:name":"Spa & Pool World",
    "wof:placetype":"venue"
},
  "geometry": {"coordinates":[-121.330451,38.57007],"type":"Point"}
}