{
  "type": "Feature",
  "properties": {
    "iso:country":"US",
    "sg:address":"5753 11th Ave",
    "sg:city":"Los Angeles",
    "sg:classifiers":[
        {
            "category":"Manufacturing",
            "subcategory":"Apparel",
            "type":"Manufacturing & Wholesale Goods"
        }
    ],
    "sg:phone":"+1 323 292 1145",
    "sg:postcode":"90043",
    "sg:province":"CA",
    "sg:tags":[
        "textile",
        "product",
        "fabricated",
        "mfg"
    ],
    "wof:name":"Crafts By Earma",
    "wof:placetype":"venue"
},
  "geometry": {"coordinates":[-118.329477,33.990005],"type":"Point"}
}