{
  "type": "Feature",
  "properties": {
    "iso:country":"US",
    "sg:address":"100 World Way",
    "sg:city":"Los Angeles",
    "sg:classifiers":[
        {
            "category":"Airline",
            "type":"Transportation"
        }
    ],
    "sg:phone":"+1 310 348 7974",
    "sg:postcode":"90045",
    "sg:province":"CA",
    "sg:tags":[
        "company"
    ],
    "wof:name":"America West Airlines Inc",
    "wof:placetype":"venue"
},
  "geometry": {"coordinates":[-118.406209,33.944711],"type":"Point"}
}