{
  "type": "Feature",
  "properties": {
    "addr:full":"506 N Diamond Bar Blvd Diamond Bar CA 91765",
    "addr:housenumber":"506",
    "addr:postcode":"91765",
    "addr:street":"N Diamond Bar Blvd",
    "iso:country":"US",
    "sg:address":"506 N Diamond Bar Blvd",
    "sg:city":"Diamond Bar",
    "sg:classifiers":[
        {
            "category":"Insurance",
            "subcategory":"Insurance Agent",
            "type":"Services"
        }
    ],
    "sg:phone":"+1 909 860 0959",
    "sg:postcode":"91765",
    "sg:province":"CA",
    "wof:name":"State Farm Insurance",
    "wof:placetype":"venue"
},
  "geometry": {"coordinates":[-117.81035300000001,34.029116],"type":"Point"}
}