{
  "type": "Feature",
  "properties": {
    "iso:country":"US",
    "sg:address":"10426 San Vincente Blvd",
    "sg:city":"Spring Valley",
    "sg:classifiers":[
        {
            "category":"Building & Trades",
            "subcategory":"Construction",
            "type":"Services"
        }
    ],
    "sg:phone":"+1 619 660 0761",
    "sg:postcode":"91977",
    "sg:province":"CA",
    "sg:tags":[
        "contractor"
    ],
    "wof:name":"Calavo Builders",
    "wof:placetype":"venue"
},
  "geometry": {"coordinates":[-116.96678799999999,32.747261],"type":"Point"}
}