{
  "type": "Feature",
  "properties": {
    "iso:country":"US",
    "sg:address":"1258 Pacific Ave",
    "sg:city":"San Francisco",
    "sg:classifiers":[
        {
            "category":"Home & Garden",
            "subcategory":"Building Materials",
            "type":"Retail Goods"
        }
    ],
    "sg:phone":"+1 415 447 8311",
    "sg:postcode":"94109",
    "sg:province":"CA",
    "wof:name":"Steven F Stevens",
    "wof:placetype":"venue"
},
  "geometry": {"coordinates":[-122.41589399999999,37.795867],"type":"Point"}
}