{
  "type": "Feature",
  "properties": {
    "iso:country":"US",
    "sg:address":"7534 Auburn Blvd",
    "sg:city":"Citrus Heights",
    "sg:classifiers":[
        {
            "category":"Manufacturing",
            "subcategory":"Leather Goods",
            "type":"Manufacturing & Wholesale Goods"
        }
    ],
    "sg:phone":"+1 916 726 4413",
    "sg:postcode":"95610",
    "sg:province":"CA",
    "sg:tags":[
        "shoes"
    ],
    "sg:website":"www.attixshoes.com",
    "wof:name":"Romeo & Juliet Inc",
    "wof:placetype":"venue"
},
  "geometry": {"coordinates":[-121.29031500000001,38.703324],"type":"Point"}
}