{
  "type": "Feature",
  "properties": {
    "iso:country":"US",
    "sg:address":"72373 Country Club Dr",
    "sg:city":"Rancho Mirage",
    "sg:classifiers":[
        {
            "category":"Professional",
            "type":"Services"
        }
    ],
    "sg:phone":"+1 760 340 2751",
    "sg:postcode":"92270",
    "sg:province":"CA",
    "sg:tags":[
        "establishment"
    ],
    "wof:name":"Wilshire Palms",
    "wof:placetype":"venue"
},
  "geometry": {"coordinates":[-116.399978,33.757813],"type":"Point"}
}