{
  "type": "Feature",
  "properties": {
    "iso:country":"US",
    "sg:address":"725 Sheridan Rd",
    "sg:city":"Arroyo Grande",
    "sg:classifiers":[
        {
            "category":"Freight",
            "type":"Transportation"
        }
    ],
    "sg:phone":"+1 805 343 0114",
    "sg:postcode":"93420",
    "sg:province":"CA",
    "sg:tags":[
        "recreational",
        "vehicle"
    ],
    "wof:name":"Pace Self Storage",
    "wof:placetype":"venue"
},
  "geometry": {"coordinates":[-120.57684399999999,35.046446],"type":"Point"}
}