{
  "type": "Feature",
  "properties": {
    "iso:country":"US",
    "sg:address":"3636 Encinal Ave",
    "sg:city":"La Crescenta",
    "sg:classifiers":[
        {
            "category":"Wholesale",
            "subcategory":"Machinery & Supplies",
            "type":"Manufacturing & Wholesale Goods"
        }
    ],
    "sg:phone":"+1 818 248 9441",
    "sg:postcode":"91214",
    "sg:province":"CA",
    "sg:tags":[
        "equipment",
        "establishment"
    ],
    "wof:name":"HCP Enterprises",
    "wof:placetype":"venue"
},
  "geometry": {"coordinates":[-118.257972,34.229756],"type":"Point"}
}