{
  "type": "Feature",
  "properties": {
    "iso:country":"US",
    "sg:address":"10582 Laurelwood Dr",
    "sg:city":"Truckee",
    "sg:classifiers":[
        {
            "category":"Professional",
            "subcategory":"Management & Consulting",
            "type":"Services"
        }
    ],
    "sg:phone":"+1 530 582 4878",
    "sg:postcode":"96161",
    "sg:province":"CA",
    "sg:tags":[
        "facility"
    ],
    "wof:name":"Space Design & Planning",
    "wof:placetype":"venue"
},
  "geometry": {"coordinates":[-120.170693,39.365631],"type":"Point"}
}