{
  "type": "Feature",
  "properties": {
    "iso:country":"US",
    "sg:address":"6116 W Pico Blvd",
    "sg:city":"Los Angeles",
    "sg:classifiers":[
        {
            "category":"Autos & Motor Vehicles",
            "subcategory":"Auto Supplies",
            "type":"Retail Goods"
        }
    ],
    "sg:phone":"+1 323 852 1010",
    "sg:postcode":"90035",
    "sg:province":"CA",
    "sg:tags":[
        "battery"
    ],
    "wof:name":"Cellular Outlet",
    "wof:placetype":"venue"
},
  "geometry": {"coordinates":[-118.375108,34.053046],"type":"Point"}
}