{
  "type": "Feature",
  "properties": {
    "iso:country":"US",
    "sg:address":"13551 Rangoon St",
    "sg:city":"Pacoima",
    "sg:classifiers":[
        {
            "category":"Wholesale",
            "subcategory":"Groceries",
            "type":"Manufacturing & Wholesale Goods"
        }
    ],
    "sg:phone":"+1 818 785 0793",
    "sg:postcode":"91331",
    "sg:province":"CA",
    "sg:tags":[
        "general"
    ],
    "wof:name":"Gst Intrnational Import/Export",
    "wof:placetype":"venue"
},
  "geometry": {"coordinates":[-118.42934200000001,34.225814],"type":"Point"}
}