{
  "type": "Feature",
  "properties": {
    "iso:country":"US",
    "sg:address":"40087 Mission Blvd Ste 236",
    "sg:city":"Fremont",
    "sg:classifiers":[
        {
            "category":"Communications",
            "subcategory":"Film & Video Production",
            "type":"Services"
        }
    ],
    "sg:phone":"+1 925 286 0177",
    "sg:postcode":"94539",
    "sg:province":"CA",
    "sg:tags":[
        "tv",
        "radio",
        "services-commercial",
        "companies-film"
    ],
    "wof:name":"Gradmemory",
    "wof:placetype":"venue"
},
  "geometry": {"coordinates":[-121.95115800000001,37.556946],"type":"Point"}
}