{
  "type": "Feature",
  "properties": {
    "iso:country":"US",
    "sg:address":"221 N Figueroa St",
    "sg:city":"Los Angeles",
    "sg:classifiers":[
        {
            "category":"Government",
            "subcategory":"Office",
            "type":"Public Place"
        }
    ],
    "sg:phone":"+1 213 482 6787",
    "sg:postcode":"90012",
    "sg:province":"CA",
    "sg:tags":[
        "development"
    ],
    "wof:name":"Building & Safety Dept",
    "wof:placetype":"venue"
},
  "geometry": {"coordinates":[-118.248996,34.059709],"type":"Point"}
}