{
  "type": "Feature",
  "properties": {
    "addr:full":"9841 Airport Blvd Ste 700 Los Angeles CA 90045",
    "addr:housenumber":"9841",
    "addr:postcode":"90045",
    "addr:street":"Airport Blvd Ste 700",
    "iso:country":"US",
    "sg:address":"9841 Airport Blvd Ste 700",
    "sg:city":"Los Angeles",
    "sg:classifiers":[
        {
            "category":"Real Estate",
            "subcategory":"Real Estate Services",
            "type":"Services"
        }
    ],
    "sg:phone":"+1 310 337 2955",
    "sg:postcode":"90045",
    "sg:province":"CA",
    "sg:tags":[
        "management",
        "property"
    ],
    "wof:name":"Festival Companies the",
    "wof:placetype":"venue"
},
  "geometry": {"coordinates":[-118.386002,33.946201],"type":"Point"}
}