{
  "type": "Feature",
  "properties": {
    "addr:full":"1634 Henderson Ln Paradise CA 95969",
    "addr:housenumber":"1634",
    "addr:postcode":"95969",
    "addr:street":"Henderson Ln",
    "iso:country":"US",
    "sg:address":"1634 Henderson Ln",
    "sg:city":"Paradise",
    "sg:classifiers":[
        {
            "category":"Professional",
            "type":"Services"
        }
    ],
    "sg:phone":"+1 530 877 5270",
    "sg:postcode":"95969",
    "sg:province":"CA",
    "sg:tags":[
        "establishment"
    ],
    "wof:name":"Osland & Osland",
    "wof:placetype":"venue"
},
  "geometry": {"coordinates":[-121.58297899999999,39.740249],"type":"Point"}
}