{
  "type": "Feature",
  "properties": {
    "addr:full":"606 2nd St Corning CA 96021",
    "addr:housenumber":"606",
    "addr:postcode":"96021",
    "addr:street":"2Nd St",
    "iso:country":"US",
    "sg:address":"606 2nd St",
    "sg:city":"Corning",
    "sg:classifiers":[
        {
            "category":"Freight",
            "type":"Transportation"
        }
    ],
    "sg:phone":"+1 530 824 5588",
    "sg:postcode":"96021",
    "sg:province":"CA",
    "sg:tags":[
        "commercial",
        "storage"
    ],
    "wof:name":"Corning Mini-Storage",
    "wof:placetype":"venue"
},
  "geometry": {"coordinates":[-122.178124,39.929828],"type":"Point"}
}