{
  "type": "Feature",
  "properties": {
    "iso:country":"US",
    "sg:address":"405 Primrose Rd Ste 212",
    "sg:city":"Burlingame",
    "sg:classifiers":[
        {
            "category":"Health Services",
            "subcategory":"Clinic",
            "type":"Services"
        }
    ],
    "sg:phone":"+1 650 375 1442",
    "sg:postcode":"94010",
    "sg:province":"CA",
    "sg:tags":[
        "counseling",
        "mental"
    ],
    "wof:name":"Cronin Pamela A Mft",
    "wof:placetype":"venue"
},
  "geometry": {"coordinates":[-122.34899900000001,37.5788],"type":"Point"}
}