{
  "type": "Feature",
  "properties": {
    "iso:country":"US",
    "sg:address":"18 Alder Cir",
    "sg:city":"Salinas",
    "sg:classifiers":[
        {
            "category":"Shopping",
            "subcategory":"Gifts & Souvenirs",
            "type":"Retail Goods"
        }
    ],
    "sg:phone":"+1 831 422 5099",
    "sg:postcode":"93905",
    "sg:province":"CA",
    "wof:name":"Monterey Gift Co",
    "wof:placetype":"venue"
},
  "geometry": {"coordinates":[-121.60372099999999,36.697871],"type":"Point"}
}