{
  "type": "Feature",
  "properties": {
    "addr:full":"620 Americana Way Glendale CA 91204",
    "addr:housenumber":"620",
    "addr:postcode":"91204",
    "addr:street":"Americana Way",
    "iso:country":"US",
    "sg:address":"620 Americana Way",
    "sg:city":"Glendale",
    "sg:classifiers":[
        {
            "category":"Bakery",
            "type":"Food & Drink"
        }
    ],
    "sg:phone":"+1 818 241 0465",
    "sg:postcode":"91204",
    "sg:province":"CA",
    "sg:website":"www.wetzels.com",
    "wof:name":"Wetzel's Pretzels",
    "wof:placetype":"venue"
},
  "geometry": {"coordinates":[-118.257536,34.144383],"type":"Point"}
}