{
  "type": "Feature",
  "properties": {
    "iso:country":"US",
    "sg:address":"14914 Olympic Dr",
    "sg:city":"Clearlake",
    "sg:classifiers":[
        {
            "category":"Fast Food",
            "type":"Food & Drink"
        },
        {
            "category":"Restaurant",
            "type":"Food & Drink"
        }
    ],
    "sg:phone":"+1 707 994 6777",
    "sg:postcode":"95422",
    "sg:province":"CA",
    "sg:tags":[
        "take",
        "pizza"
    ],
    "wof:name":"Papas Pizza N More",
    "wof:placetype":"venue"
},
  "geometry": {"coordinates":[-122.633765,38.96182],"type":"Point"}
}