{
  "type": "Feature",
  "properties": {
    "iso:country":"US",
    "sg:address":"10940 Wilshire Blvd Ste 2100",
    "sg:city":"Los Angeles",
    "sg:classifiers":[
        {
            "category":"Professional",
            "subcategory":"Lawyer & Legal Services",
            "type":"Services"
        }
    ],
    "sg:phone":"+1 310 209 8800",
    "sg:postcode":"90024",
    "sg:province":"CA",
    "wof:name":"Armbruster and Assoc",
    "wof:placetype":"venue"
},
  "geometry": {"coordinates":[-118.445,34.058399],"type":"Point"}
}