{
  "type": "Feature",
  "properties": {
    "iso:country":"US",
    "sg:address":"4539 W 159th St",
    "sg:city":"Lawndale",
    "sg:classifiers":[
        {
            "category":"Building & Trades",
            "subcategory":"Construction",
            "type":"Services"
        }
    ],
    "sg:phone":"+1 310 371 5000",
    "sg:postcode":"90260",
    "sg:province":"CA",
    "sg:tags":[
        "concrete",
        "contractor"
    ],
    "wof:name":"Ingram's Concrete Works",
    "wof:placetype":"venue"
},
  "geometry": {"coordinates":[-118.35700799999999,33.886512],"type":"Point"}
}