{
  "type": "Feature",
  "properties": {
    "iso:country":"US",
    "sg:address":"1928 W Holt Ave",
    "sg:city":"Pomona",
    "sg:classifiers":[
        {
            "category":"Wholesale",
            "subcategory":"Home Furnishings",
            "type":"Manufacturing & Wholesale Goods"
        }
    ],
    "sg:phone":"+1 909 469 5769",
    "sg:postcode":"91768",
    "sg:province":"CA",
    "sg:tags":[
        "glassware"
    ],
    "wof:name":"Perfect Design",
    "wof:placetype":"venue"
},
  "geometry": {"coordinates":[-117.78523800000001,34.061434],"type":"Point"}
}