{
  "type": "Feature",
  "properties": {
    "addr:full":"945 E Pacific Coast Hwy Long Beach CA 90806",
    "addr:housenumber":"945",
    "addr:postcode":"90806",
    "addr:street":"E Pacific Coast Hwy",
    "iso:country":"US",
    "sg:address":"945 E Pacific Coast Hwy",
    "sg:city":"Long Beach",
    "sg:classifiers":[
        {
            "category":"Food & Beverages",
            "subcategory":"Liquor & Beverages",
            "type":"Retail Goods"
        }
    ],
    "sg:phone":"+1 562 599 6656",
    "sg:postcode":"90806",
    "sg:province":"CA",
    "sg:tags":[
        "beer",
        "spirit",
        "wine"
    ],
    "wof:name":"Whistler Liquor",
    "wof:placetype":"venue"
},
  "geometry": {"coordinates":[-118.181,33.790001],"type":"Point"}
}