{
  "type": "Feature",
  "properties": {
    "iso:country":"US",
    "sg:address":"796 Munras Ave",
    "sg:city":"Monterey",
    "sg:classifiers":[
        {
            "category":"Professional",
            "subcategory":"Art Services",
            "type":"Services"
        }
    ],
    "sg:phone":"+1 831 375 1237",
    "sg:postcode":"93940",
    "sg:province":"CA",
    "sg:tags":[
        "graphic",
        "designer"
    ],
    "wof:name":"Melissa Thoeny Designs",
    "wof:placetype":"venue"
},
  "geometry": {"coordinates":[-121.893486,36.593801],"type":"Point"}
}