{
  "type": "Feature",
  "properties": {
    "iso:country":"US",
    "sg:address":"2713 New York Dr",
    "sg:city":"Pasadena",
    "sg:classifiers":[
        {
            "category":"Sports & Exercise",
            "subcategory":"Sports Center",
            "type":"Entertainment"
        },
        {
            "category":"Arena",
            "subcategory":"Sports Club",
            "type":"Entertainment"
        }
    ],
    "sg:phone":"+1 626 798 9909",
    "sg:postcode":"91107",
    "sg:province":"CA",
    "sg:tags":[
        "professional",
        "amateur",
        "team"
    ],
    "wof:name":"Gerrish Swim & Tennis Club",
    "wof:placetype":"venue"
},
  "geometry": {"coordinates":[-118.095001,34.174198],"type":"Point"}
}