{
  "type": "Feature",
  "properties": {
    "addr:full":"2601 S H St Bakersfield CA 93304",
    "addr:housenumber":"2601",
    "addr:postcode":"93304",
    "addr:street":"S H St",
    "iso:country":"US",
    "sg:address":"2601 S H St",
    "sg:city":"Bakersfield",
    "sg:classifiers":[
        {
            "category":"Shopping",
            "subcategory":"Crafts & Fabrics",
            "type":"Retail Goods"
        }
    ],
    "sg:phone":"+1 661 833 6875",
    "sg:postcode":"93304",
    "sg:province":"CA",
    "sg:tags":[
        "shop"
    ],
    "wof:name":"Hancock Fabrics",
    "wof:placetype":"venue"
},
  "geometry": {"coordinates":[-119.021278,35.329645],"type":"Point"}
}