{
  "type": "Feature",
  "properties": {
    "iso:country":"US",
    "sg:address":"1627 Fawley Ln",
    "sg:city":"Vista",
    "sg:classifiers":[
        {
            "category":"Freight",
            "type":"Transportation"
        }
    ],
    "sg:phone":"+1 760 724 3812",
    "sg:postcode":"92083",
    "sg:province":"CA",
    "sg:tags":[
        "operator",
        "local",
        "trucking"
    ],
    "wof:name":"Discount Tractor Company",
    "wof:placetype":"venue"
},
  "geometry": {"coordinates":[-117.224504,33.17922],"type":"Point"}
}