{
  "type": "Feature",
  "properties": {
    "iso:country":"US",
    "sg:address":"5046 Commercial Cir",
    "sg:city":"Concord",
    "sg:classifiers":[
        {
            "category":"Shopping",
            "subcategory":"Gifts & Souvenirs",
            "type":"Retail Goods"
        }
    ],
    "sg:phone":"+1 925 687 1590",
    "sg:postcode":"94520",
    "sg:province":"CA",
    "wof:name":"Collectibles & Engraving",
    "wof:placetype":"venue"
},
  "geometry": {"coordinates":[-122.030407,38.019847],"type":"Point"}
}