{
  "type": "Feature",
  "properties": {
    "iso:country":"US",
    "sg:address":"549 E Market St",
    "sg:city":"Salinas",
    "sg:classifiers":[
        {
            "category":"Food & Beverages",
            "subcategory":"Groceries & Convenience Stores",
            "type":"Retail Goods"
        }
    ],
    "sg:phone":"+1 831 758 2166",
    "sg:postcode":"93905",
    "sg:province":"CA",
    "sg:tags":[
        "grocer"
    ],
    "wof:name":"Maritez Market",
    "wof:placetype":"venue"
},
  "geometry": {"coordinates":[-121.637697,36.67724],"type":"Point"}
}