{
  "type": "Feature",
  "properties": {
    "addr:full":"2300 W Magnolia Blvd Burbank CA 91506",
    "addr:housenumber":"2300",
    "addr:postcode":"91506",
    "addr:street":"W Magnolia Blvd",
    "iso:country":"US",
    "sg:address":"2300 W Magnolia Blvd",
    "sg:city":"Burbank",
    "sg:classifiers":[
        {
            "category":"Real Estate",
            "subcategory":"Real Estate Agent",
            "type":"Services"
        }
    ],
    "sg:phone":"+1 818 841 8989",
    "sg:postcode":"91506",
    "sg:province":"CA",
    "wof:name":"Enrique Borges",
    "wof:placetype":"venue"
},
  "geometry": {"coordinates":[-118.333681,34.172298],"type":"Point"}
}