{
  "type": "Feature",
  "properties": {
    "addr:full":"6994 El Camino Real Ste 203 Carlsbad CA 92009",
    "addr:housenumber":"6994",
    "addr:postcode":"92009",
    "addr:street":"El Camino Real Ste 203",
    "iso:country":"US",
    "sg:address":"6994 El Camino Real Ste 203",
    "sg:city":"Carlsbad",
    "sg:classifiers":[
        {
            "category":"Insurance",
            "subcategory":"Insurance Agent",
            "type":"Services"
        },
        {
            "category":"Insurance",
            "subcategory":"Hazard Insurance",
            "type":"Services"
        },
        {
            "category":"Insurance",
            "subcategory":"Title Insurance",
            "type":"Services"
        }
    ],
    "sg:phone":"+1 760 634 0801",
    "sg:postcode":"92009",
    "sg:province":"CA",
    "sg:tags":[
        "auto",
        "commercial",
        "renter",
        "business",
        "homeowner"
    ],
    "sg:website":"http://www.reinhardt-insurance.com",
    "wof:name":"Reinhardt Insurance Service",
    "wof:placetype":"venue"
},
  "geometry": {"coordinates":[-117.266418,33.102367],"type":"Point"}
}