{
  "type": "Feature",
  "properties": {
    "addr:full":"8117 Ella Ct Citrus Heights CA 95610",
    "addr:housenumber":"8117",
    "addr:postcode":"95610",
    "addr:street":"Ella Ct",
    "iso:country":"US",
    "sg:address":"8117 Ella Ct",
    "sg:city":"Citrus Heights",
    "sg:classifiers":[
        {
            "category":"Utilities",
            "subcategory":"Telephone",
            "type":"Services"
        }
    ],
    "sg:phone":"+1 916 729 7999",
    "sg:postcode":"95610",
    "sg:province":"CA",
    "sg:tags":[
        "telecommunication"
    ],
    "wof:name":"GTS Telecom",
    "wof:placetype":"venue"
},
  "geometry": {"coordinates":[-121.274973,38.71333],"type":"Point"}
}