{
  "type": "Feature",
  "properties": {
    "iso:country":"US",
    "sg:address":"15938 Los Serranos Country Club Dr",
    "sg:city":"Chino Hills",
    "sg:classifiers":[
        {
            "category":"Cinema",
            "subcategory":"Movie Rental",
            "type":"Entertainment"
        }
    ],
    "sg:phone":"+1 909 606 7789",
    "sg:postcode":"91709",
    "sg:province":"CA",
    "sg:tags":[
        "leasing",
        "video",
        "disc",
        "tape"
    ],
    "wof:name":"Blockbuster Video",
    "wof:placetype":"venue"
},
  "geometry": {"coordinates":[-117.695146,33.963098],"type":"Point"}
}