{
  "type": "Feature",
  "properties": {
    "addr:full":"3490 Palmer Dr Cameron Park CA 95682",
    "addr:housenumber":"3490",
    "addr:postcode":"95682",
    "addr:street":"Palmer Dr",
    "iso:country":"US",
    "sg:address":"3490 Palmer Dr",
    "sg:city":"Cameron Park",
    "sg:classifiers":[
        {
            "category":"Real Estate",
            "subcategory":"Real Estate Agent",
            "type":"Services"
        }
    ],
    "sg:phone":"+1 530 672 7300",
    "sg:postcode":"95682",
    "sg:province":"CA",
    "wof:name":"Help-U-Sell Progressive Realty",
    "wof:placetype":"venue"
},
  "geometry": {"coordinates":[-120.963621,38.660793],"type":"Point"}
}