{
  "type": "Feature",
  "properties": {
    "iso:country":"US",
    "sg:address":"135 W Main St",
    "sg:city":"Alhambra",
    "sg:classifiers":[
        {
            "category":"Shopping",
            "subcategory":"Comic Books",
            "type":"Retail Goods"
        }
    ],
    "sg:phone":"+1 626 570 8743",
    "sg:postcode":"91801",
    "sg:province":"CA",
    "wof:name":"Comic Cellar",
    "wof:placetype":"venue"
},
  "geometry": {"coordinates":[-118.12868,34.094343],"type":"Point"}
}