{
  "type": "Feature",
  "properties": {
    "iso:country":"US",
    "sg:address":"1042 N Mountain Ave",
    "sg:city":"Upland",
    "sg:classifiers":[
        {
            "category":"Structure",
            "subcategory":"Office Building",
            "type":"Public Place"
        }
    ],
    "sg:phone":"+1 909 261 4810",
    "sg:postcode":"91786",
    "sg:province":"CA",
    "sg:tags":[
        "park"
    ],
    "wof:name":"Tap Properties",
    "wof:placetype":"venue"
},
  "geometry": {"coordinates":[-117.670197,34.107543],"type":"Point"}
}