{
  "type": "Feature",
  "properties": {
    "addr:full":"6011 Whittier Boulevard Los Angeles CA 90022",
    "addr:housenumber":"6011",
    "addr:postcode":"90022",
    "addr:street":"Whittier Boulevard",
    "iso:country":"US",
    "sg:address":"6011 Whittier Boulevard",
    "sg:city":"Los Angeles",
    "sg:classifiers":[
        {
            "category":"Food & Beverages",
            "subcategory":"Groceries & Convenience Stores",
            "type":"Retail Goods"
        }
    ],
    "sg:phone":"+1 323 724 6111",
    "sg:postcode":"90022",
    "sg:province":"CA",
    "wof:name":"Junior's Mini Mart",
    "wof:placetype":"venue"
},
  "geometry": {"coordinates":[-118.14167500000001,34.017232],"type":"Point"}
}