{
  "type": "Feature",
  "properties": {
    "iso:country":"US",
    "sg:address":"2976 Burton Dr",
    "sg:city":"Cambria",
    "sg:classifiers":[
        {
            "category":"Communications",
            "subcategory":"Radio Station",
            "type":"Services"
        }
    ],
    "sg:phone":"+1 805 927 7079",
    "sg:postcode":"93428",
    "sg:province":"CA",
    "sg:tags":[
        "company",
        "broadcasting"
    ],
    "wof:name":"KTEA",
    "wof:placetype":"venue"
},
  "geometry": {"coordinates":[-121.07724399999999,35.558128],"type":"Point"}
}