{
  "type": "Feature",
  "properties": {
    "iso:country":"US",
    "sg:address":"388 W Huntington Dr",
    "sg:city":"Arcadia",
    "sg:classifiers":[
        {
            "category":"Organizations",
            "subcategory":"Professional Association",
            "type":"Services"
        }
    ],
    "sg:phone":"+1 626 447 2159",
    "sg:postcode":"91007",
    "sg:province":"CA",
    "sg:tags":[
        "chambers",
        "commerce"
    ],
    "wof:name":"Arcadia Chamber Of Commerce",
    "wof:placetype":"venue"
},
  "geometry": {"coordinates":[-118.043964,34.133209],"type":"Point"}
}