{
  "type": "Feature",
  "properties": {
    "iso:country":"US",
    "sg:address":"2721 School St",
    "sg:city":"Oakland",
    "sg:classifiers":[
        {
            "category":"Social Services",
            "subcategory":"Child Care",
            "type":"Services"
        }
    ],
    "sg:phone":"+1 510 536 4824",
    "sg:postcode":"94602",
    "sg:province":"CA",
    "wof:name":"Lau's Family Day Care",
    "wof:placetype":"venue"
},
  "geometry": {"coordinates":[-122.216853,37.79555],"type":"Point"}
}