{
  "type": "Feature",
  "properties": {
    "iso:country":"US",
    "sg:address":"910 Valley Oak Dr",
    "sg:city":"Hollister",
    "sg:classifiers":[
        {
            "category":"Recreation",
            "type":"Entertainment"
        }
    ],
    "sg:phone":"+1 831 637 7789",
    "sg:postcode":"95023",
    "sg:province":"CA",
    "sg:tags":[
        "club",
        "membership"
    ],
    "wof:name":"Bolado Golf Club",
    "wof:placetype":"venue"
},
  "geometry": {"coordinates":[-121.37600500000001,36.820468],"type":"Point"}
}