{
  "type": "Feature",
  "properties": {
    "addr:full":"421 N Main St Santa Ana CA 92701",
    "addr:housenumber":"421",
    "addr:postcode":"92701",
    "addr:street":"N Main St",
    "iso:country":"US",
    "sg:address":"421 N Main St",
    "sg:city":"Santa Ana",
    "sg:classifiers":[
        {
            "category":"Banks & Credit Unions",
            "subcategory":"Bank",
            "type":"Services"
        }
    ],
    "sg:phone":"+1 714 647 2777",
    "sg:postcode":"92701",
    "sg:province":"CA",
    "sg:tags":[
        "company",
        "trust"
    ],
    "sg:website":"www.firstamtrust.com",
    "wof:name":"First American Trust FSB",
    "wof:placetype":"venue"
},
  "geometry": {"coordinates":[-117.867563,33.74871],"type":"Point"}
}