{
  "type": "Feature",
  "properties": {
    "addr:full":"10724 Bloomfield Ave Santa Fe Springs CA 90670",
    "addr:housenumber":"10724",
    "addr:postcode":"90670",
    "addr:street":"Bloomfield Ave",
    "iso:country":"US",
    "sg:address":"10724 Bloomfield Ave",
    "sg:city":"Santa Fe Springs",
    "sg:classifiers":[
        {
            "category":"Wholesale",
            "subcategory":"Metals & Minerals",
            "type":"Manufacturing & Wholesale Goods"
        }
    ],
    "sg:phone":"+1 562 906 2489",
    "sg:postcode":"90670",
    "sg:province":"CA",
    "sg:tags":[
        "product",
        "laminated",
        "structural"
    ],
    "wof:name":"West Coast Laminating",
    "wof:placetype":"venue"
},
  "geometry": {"coordinates":[-118.063892,33.935477],"type":"Point"}
}