{
  "type": "Feature",
  "properties": {
    "addr:full":"1771 Wesley Street Banning CA 92220",
    "addr:housenumber":"1771",
    "addr:postcode":"92220",
    "addr:street":"Wesley Street",
    "iso:country":"US",
    "sg:address":"1771 Wesley Street",
    "sg:city":"Banning",
    "sg:classifiers":[
        {
            "category":"Retail",
            "subcategory":"Pet Boarding",
            "type":"Services"
        }
    ],
    "sg:phone":"+1 951 922 9709",
    "sg:postcode":"92220",
    "sg:province":"CA",
    "sg:tags":[
        "boarding/pet",
        "sitting"
    ],
    "sg:website":"www.luckydogranch.net",
    "wof:name":"Lucky Dog Ranch",
    "wof:placetype":"venue"
},
  "geometry": {"coordinates":[-116.857523,33.913841],"type":"Point"}
}