{
  "type": "Feature",
  "properties": {
    "iso:country":"US",
    "sg:address":"700 Harvest Park Road",
    "sg:city":"Brentwood",
    "sg:classifiers":[
        {
            "category":"Arts & Performance",
            "subcategory":"Art Gallery",
            "type":"Entertainment"
        }
    ],
    "sg:phone":"+1 925 634 7742",
    "sg:postcode":"94513",
    "sg:province":"CA",
    "wof:name":"Weber Gallery",
    "wof:placetype":"venue"
},
  "geometry": {"coordinates":[-121.68347,37.924149],"type":"Point"}
}