{
  "type": "Feature",
  "properties": {
    "addr:full":"221 W Winton Ave Hayward CA 94544",
    "addr:housenumber":"221",
    "addr:postcode":"94544",
    "addr:street":"W Winton Ave",
    "iso:country":"US",
    "sg:address":"221 W Winton Ave",
    "sg:city":"Hayward",
    "sg:classifiers":[
        {
            "category":"Utilities",
            "subcategory":"Telephone",
            "type":"Services"
        }
    ],
    "sg:phone":"+1 510 784 3129",
    "sg:postcode":"94544",
    "sg:province":"CA",
    "sg:tags":[
        "communications"
    ],
    "wof:name":"SBC",
    "wof:placetype":"venue"
},
  "geometry": {"coordinates":[-122.09584099999999,37.658778],"type":"Point"}
}