{
  "type": "Feature",
  "properties": {
    "iso:country":"US",
    "sg:address":"7453 Santa Domingo Way",
    "sg:city":"Buena Park",
    "sg:classifiers":[
        {
            "category":"Building & Trades",
            "subcategory":"Electrical",
            "type":"Services"
        }
    ],
    "sg:phone":"+1 714 527 1555",
    "sg:postcode":"90620",
    "sg:province":"CA",
    "sg:tags":[
        "electrical",
        "contractor"
    ],
    "wof:name":"Globe Electric",
    "wof:placetype":"venue"
},
  "geometry": {"coordinates":[-118.003219,33.840905],"type":"Point"}
}