{
  "type": "Feature",
  "properties": {
    "addr:full":"450 N Bedford Drive Suite 306 Beverly Hills CA 90210",
    "addr:housenumber":"450",
    "addr:postcode":"90210",
    "addr:street":"N Bedford Drive Suite 306;Hills Ca",
    "iso:country":"US",
    "sg:address":"450 N Bedford Drive Suite 306",
    "sg:city":"Beverly Hills",
    "sg:classifiers":[
        {
            "category":"Health Services",
            "subcategory":"Doctor",
            "type":"Services"
        }
    ],
    "sg:phone":"+1 310 276 1474",
    "sg:postcode":"90210",
    "sg:province":"CA",
    "sg:tags":[
        "psychiatrist"
    ],
    "wof:name":"Dorman Danl MD",
    "wof:placetype":"venue"
},
  "geometry": {"coordinates":[-118.405974,34.068871],"type":"Point"}
}