{
  "type": "Feature",
  "properties": {
    "addr:full":"2407 J St Sacramento CA 95816",
    "addr:housenumber":"2407",
    "addr:postcode":"95816",
    "addr:street":"J St",
    "iso:country":"US",
    "sg:address":"2407 J St",
    "sg:city":"Sacramento",
    "sg:classifiers":[
        {
            "category":"Banks & Credit Unions",
            "subcategory":"Bank",
            "type":"Services"
        }
    ],
    "sg:phone":"+1 916 442 5683",
    "sg:postcode":"95816",
    "sg:province":"CA",
    "sg:tags":[
        "loan",
        "mortgage",
        "real estate"
    ],
    "wof:name":"Cladianos Company Mortgage",
    "wof:placetype":"venue"
},
  "geometry": {"coordinates":[-121.47324999999999,38.575002],"type":"Point"}
}