{
  "type": "Feature",
  "properties": {
    "iso:country":"US",
    "sg:address":"11701 Wilshire Blvd",
    "sg:city":"Los Angeles",
    "sg:classifiers":[
        {
            "category":"Wholesale",
            "subcategory":"Non-durable Goods",
            "type":"Manufacturing & Wholesale Goods"
        }
    ],
    "sg:phone":"+1 310 914 5035",
    "sg:postcode":"90025",
    "sg:province":"CA",
    "sg:tags":[
        "novelty"
    ],
    "wof:name":"A Balloon World",
    "wof:placetype":"venue"
},
  "geometry": {"coordinates":[-118.460921,34.049408],"type":"Point"}
}