{
  "type": "Feature",
  "properties": {
    "addr:full":"1403 W Adams Boulevard Los Angeles CA 90007",
    "addr:housenumber":"1403",
    "addr:postcode":"90007",
    "addr:street":"W Adams Boulevard",
    "iso:country":"US",
    "sg:address":"1403 W Adams Boulevard",
    "sg:city":"Los Angeles",
    "sg:classifiers":[
        {
            "category":"Autos & Motor Vehicles",
            "subcategory":"Fuel & Gas Station",
            "type":"Retail Goods"
        }
    ],
    "sg:phone":"+1 323 731 6120",
    "sg:postcode":"90007",
    "sg:province":"CA",
    "wof:name":"Ls Union 76",
    "wof:placetype":"venue"
},
  "geometry": {"coordinates":[-118.291873,34.032637],"type":"Point"}
}