{
  "type": "Feature",
  "properties": {
    "addr:full":"40336 Homeridge Dr Palmdale CA 93551",
    "addr:postcode":"40336;ca 93551",
    "addr:street":"Homeridge Dr",
    "iso:country":"US",
    "sg:address":"40336 Homeridge Dr",
    "sg:city":"Palmdale",
    "sg:classifiers":[
        {
            "category":"Building & Trades",
            "subcategory":"Landscaping Services",
            "type":"Services"
        }
    ],
    "sg:phone":"+1 661 722 5655",
    "sg:postcode":"93551",
    "sg:province":"CA",
    "wof:name":"Alberto Diaz",
    "wof:placetype":"venue"
},
  "geometry": {"coordinates":[-118.200456,34.615293],"type":"Point"}
}