{
  "type": "Feature",
  "properties": {
    "addr:full":"4932 Newport Ave San Diego CA 92107",
    "addr:housenumber":"4932",
    "addr:postcode":"92107",
    "addr:street":"Newport Ave",
    "iso:country":"US",
    "sg:address":"4932 Newport Ave",
    "sg:city":"San Diego",
    "sg:classifiers":[
        {
            "category":"Professional",
            "subcategory":"Art Services",
            "type":"Services"
        }
    ],
    "sg:phone":"+1 619 226 3545",
    "sg:postcode":"92107",
    "sg:province":"CA",
    "sg:tags":[
        "photographer"
    ],
    "wof:name":"Carter Birdie Photography",
    "wof:placetype":"venue"
},
  "geometry": {"coordinates":[-117.25048700000001,32.746566],"type":"Point"}
}