{
  "type": "Feature",
  "properties": {
    "iso:country":"US",
    "sg:address":"1022 Maple Ave",
    "sg:city":"Los Angeles",
    "sg:classifiers":[
        {
            "category":"Manufacturing",
            "subcategory":"Chemicals & Compounds",
            "type":"Manufacturing & Wholesale Goods"
        },
        {
            "category":"Shopping",
            "subcategory":"Beauty & Cosmetics",
            "type":"Retail Goods"
        }
    ],
    "sg:phone":"+1 213 746 7299",
    "sg:postcode":"90015",
    "sg:province":"CA",
    "sg:tags":[
        "preparation",
        "toilet",
        "mfg",
        "merchandise",
        "perfume"
    ],
    "wof:name":"Perfume Expo",
    "wof:placetype":"venue"
},
  "geometry": {"coordinates":[-118.254877,34.037379],"type":"Point"}
}