{
  "type": "Feature",
  "properties": {
    "addr:full":"1285 Parallel Dr Lakeport CA 95453",
    "addr:housenumber":"1285",
    "addr:postcode":"95453",
    "addr:street":"Parallel Dr",
    "iso:country":"US",
    "sg:address":"1285 Parallel Dr",
    "sg:city":"Lakeport",
    "sg:classifiers":[
        {
            "category":"Restaurant",
            "type":"Food & Drink"
        }
    ],
    "sg:menulink":"http://www.allmenus.com/ca/lakeport/213216-taco-bell/menu/",
    "sg:phone":"+1 707 263 4507",
    "sg:postcode":"95453",
    "sg:province":"CA",
    "sg:tags":[
        "mexican"
    ],
    "wof:name":"Taco Bell",
    "wof:placetype":"venue"
},
  "geometry": {"coordinates":[-122.92514,39.033541],"type":"Point"}
}