{
  "type": "Feature",
  "properties": {
    "iso:country":"US",
    "sg:address":"5105 W Shaw Ave",
    "sg:city":"Fresno",
    "sg:classifiers":[
        {
            "category":"Personal",
            "subcategory":"Nail Salon",
            "type":"Services"
        }
    ],
    "sg:phone":"+1 559 277 3952",
    "sg:postcode":"93722",
    "sg:province":"CA",
    "wof:name":"Kwik Nails",
    "wof:placetype":"venue"
},
  "geometry": {"coordinates":[-119.882822,36.808139],"type":"Point"}
}