{
  "type": "Feature",
  "properties": {
    "iso:country":"US",
    "sg:address":"101 J St",
    "sg:city":"Sacramento",
    "sg:classifiers":[
        {
            "category":"Government",
            "subcategory":"Office",
            "type":"Public Place"
        }
    ],
    "sg:phone":"+1 916 445 7373",
    "sg:postcode":"95814",
    "sg:province":"CA",
    "sg:tags":[
        "conservation"
    ],
    "wof:name":"Goldrush Dist Office",
    "wof:placetype":"venue"
},
  "geometry": {"coordinates":[-121.504783,38.583332],"type":"Point"}
}