{
  "type": "Feature",
  "properties": {
    "iso:country":"US",
    "sg:address":"118 W 25th Ave",
    "sg:city":"San Mateo",
    "sg:classifiers":[
        {
            "category":"Shopping",
            "subcategory":"Mobile Phones",
            "type":"Retail Goods"
        },
        {
            "category":"Professional",
            "subcategory":"Computer Services",
            "type":"Services"
        }
    ],
    "sg:phone":"+1 650 964 8500",
    "sg:postcode":"94403",
    "sg:province":"CA",
    "sg:tags":[
        "repair"
    ],
    "sg:website":"www.mobilekangaroo.com",
    "wof:name":"Mobile Kangaroo",
    "wof:placetype":"venue"
},
  "geometry": {"coordinates":[-122.30742499999999,37.54373],"type":"Point"}
}