{
  "type": "Feature",
  "properties": {
    "iso:country":"US",
    "sg:address":"1360 Broadway Ave",
    "sg:city":"Burlingame",
    "sg:classifiers":[
        {
            "category":"Personal",
            "subcategory":"Day Spa",
            "type":"Services"
        }
    ],
    "sg:phone":"+1 650 342 0858",
    "sg:postcode":"94010",
    "sg:province":"CA",
    "sg:website":"www.kimsperfectskin.com",
    "wof:name":"Kim's Perfect Skin",
    "wof:placetype":"venue"
},
  "geometry": {"coordinates":[-117.16289399999999,32.7148],"type":"Point"}
}