{
  "type": "Feature",
  "properties": {
    "iso:country":"US",
    "sg:address":"25 E Napa St",
    "sg:city":"Sonoma",
    "sg:classifiers":[
        {
            "category":"Shopping",
            "subcategory":"Used Merchandise",
            "type":"Retail Goods"
        }
    ],
    "sg:phone":"+1 707 996 0986",
    "sg:postcode":"95476",
    "sg:province":"CA",
    "sg:tags":[
        "antique"
    ],
    "wof:name":"Kathryn Stevens Antiques",
    "wof:placetype":"venue"
},
  "geometry": {"coordinates":[-122.456991,38.291795],"type":"Point"}
}