{
  "type": "Feature",
  "properties": {
    "iso:country":"US",
    "sg:address":"46 Sutherland Dr",
    "sg:city":"Auburn",
    "sg:classifiers":[
        {
            "category":"Professional",
            "type":"Services"
        }
    ],
    "sg:phone":"+1 530 823 3773",
    "sg:postcode":"95603",
    "sg:province":"CA",
    "wof:name":"Stephen J Jordan",
    "wof:placetype":"venue"
},
  "geometry": {"coordinates":[-121.062614,38.917926],"type":"Point"}
}