{
  "type": "Feature",
  "properties": {
    "addr:full":"1801 W Romneya Dr Anaheim CA 92801",
    "addr:housenumber":"1801",
    "addr:postcode":"92801",
    "addr:street":"W Romneya Dr",
    "iso:country":"US",
    "sg:address":"1801 W Romneya Dr",
    "sg:city":"Anaheim",
    "sg:classifiers":[
        {
            "category":"Restaurant",
            "type":"Food & Drink"
        }
    ],
    "sg:phone":"+1 714 772 5010",
    "sg:postcode":"92801",
    "sg:province":"CA",
    "sg:tags":[
        "chinese"
    ],
    "wof:name":"One Stop Snack Shop",
    "wof:placetype":"venue"
},
  "geometry": {"coordinates":[-117.945463,33.850839],"type":"Point"}
}