{
  "type": "Feature",
  "properties": {
    "addr:full":"218 Ridgewood Dr San Rafael CA 94901",
    "addr:housenumber":"218",
    "addr:postcode":"94901",
    "addr:street":"Ridgewood Dr",
    "iso:country":"US",
    "sg:address":"218 Ridgewood Dr",
    "sg:city":"San Rafael",
    "sg:classifiers":[
        {
            "category":"Professional",
            "subcategory":"Management & Consulting",
            "type":"Services"
        }
    ],
    "sg:phone":"+1 415 459 5101",
    "sg:postcode":"94901",
    "sg:province":"CA",
    "sg:tags":[
        "counselor",
        "public",
        "relations"
    ],
    "wof:name":"P R Communications",
    "wof:placetype":"venue"
},
  "geometry": {"coordinates":[-122.547319,37.988362],"type":"Point"}
}