{
  "type": "Feature",
  "properties": {
    "addr:full":"3961 Strickland Mine Rd Placerville CA 95667",
    "addr:housenumber":"3961",
    "addr:postcode":"95667",
    "addr:street":"Strickland Mine Rd",
    "iso:country":"US",
    "sg:address":"3961 Strickland Mine Rd",
    "sg:city":"Placerville",
    "sg:classifiers":[
        {
            "category":"Professional",
            "subcategory":"Engineering",
            "type":"Services"
        }
    ],
    "sg:phone":"+1 530 622 4039",
    "sg:postcode":"95667",
    "sg:province":"CA",
    "sg:tags":[
        "engineer"
    ],
    "sg:website":"www.frontierco.com",
    "wof:name":"FRONTIER Systems",
    "wof:placetype":"venue"
},
  "geometry": {"coordinates":[-120.866697,38.699837],"type":"Point"}
}