{
  "type": "Feature",
  "properties": {
    "addr:full":"147 N Sierra Ave Oakdale CA 95361",
    "addr:housenumber":"147",
    "addr:postcode":"95361",
    "addr:street":"N Sierra Ave",
    "iso:country":"US",
    "sg:address":"147 N Sierra Ave",
    "sg:city":"Oakdale",
    "sg:classifiers":[
        {
            "category":"Home & Garden",
            "subcategory":"Hardware",
            "type":"Retail Goods"
        }
    ],
    "sg:phone":"+1 209 847 0395",
    "sg:postcode":"95361",
    "sg:province":"CA",
    "wof:name":"Keith Brown Building Materials",
    "wof:placetype":"venue"
},
  "geometry": {"coordinates":[-120.84644400000001,37.767719],"type":"Point"}
}