{
  "type": "Feature",
  "properties": {
    "iso:country":"US",
    "sg:address":"600 W 15th St",
    "sg:city":"Long Beach",
    "sg:classifiers":[
        {
            "category":"Home & Garden",
            "subcategory":"Household Appliances",
            "type":"Retail Goods"
        }
    ],
    "sg:phone":"+1 562 628 0071",
    "sg:postcode":"90813",
    "sg:province":"CA",
    "sg:tags":[
        "cleaning",
        "vacuum"
    ],
    "sg:website":"www.zmd.com",
    "wof:name":"ZMD Intl",
    "wof:placetype":"venue"
},
  "geometry": {"coordinates":[-118.200982,33.785847],"type":"Point"}
}