{
  "type": "Feature",
  "properties": {
    "iso:country":"US",
    "sg:address":"3850 Costa Bella Dr",
    "sg:city":"La Mesa",
    "sg:classifiers":[
        {
            "category":"Real Estate",
            "subcategory":"Real Estate Agent",
            "type":"Services"
        }
    ],
    "sg:phone":"+1 619 466 0136",
    "sg:postcode":"91941",
    "sg:province":"CA",
    "wof:name":"Multi National Properties",
    "wof:placetype":"venue"
},
  "geometry": {"coordinates":[-117.02924899999999,32.747892],"type":"Point"}
}