{
  "type": "Feature",
  "properties": {
    "iso:country":"US",
    "sg:address":"949 Carmelita Dr",
    "sg:city":"Salinas",
    "sg:classifiers":[
        {
            "category":"Home & Garden",
            "subcategory":"Household Appliances",
            "type":"Retail Goods"
        }
    ],
    "sg:phone":"+1 831 758 8988",
    "sg:postcode":"93901",
    "sg:province":"CA",
    "wof:name":"Jeff Miller's Appliance Svc",
    "wof:placetype":"venue"
},
  "geometry": {"coordinates":[-121.676371,36.669138],"type":"Point"}
}