{
  "type": "Feature",
  "properties": {
    "iso:country":"US",
    "sg:address":"1027 S Bascom Ave",
    "sg:city":"San Jose",
    "sg:classifiers":[
        {
            "category":"Personal",
            "subcategory":"Beauty Salon",
            "type":"Services"
        }
    ],
    "sg:phone":"+1 408 298 9888",
    "sg:postcode":"95128",
    "sg:province":"CA",
    "sg:tags":[
        "hair"
    ],
    "wof:name":"Julie Beauty Salon",
    "wof:placetype":"venue"
},
  "geometry": {"coordinates":[-121.931695,37.306947],"type":"Point"}
}