{
  "type": "Feature",
  "properties": {
    "addr:full":"43821 60th St W Lancaster CA 93536",
    "addr:housenumber":"43821",
    "addr:postcode":"93536",
    "addr:street":"60Th St W",
    "iso:country":"US",
    "sg:address":"43821 60th St W",
    "sg:city":"Lancaster",
    "sg:classifiers":[
        {
            "category":"Manufacturing",
            "subcategory":"Tools & Machinery",
            "type":"Manufacturing & Wholesale Goods"
        }
    ],
    "sg:phone":"+1 661 722 3199",
    "sg:postcode":"93536",
    "sg:province":"CA",
    "wof:name":"Rommel Machinging Service",
    "wof:placetype":"venue"
},
  "geometry": {"coordinates":[-118.236537,34.681647],"type":"Point"}
}