{
  "type": "Feature",
  "properties": {
    "addr:full":"1041 Main St Colusa CA 95932",
    "addr:housenumber":"1041",
    "addr:postcode":"95932",
    "addr:street":"Main St",
    "iso:country":"US",
    "sg:address":"1041 Main St",
    "sg:city":"Colusa",
    "sg:classifiers":[
        {
            "category":"Professional",
            "subcategory":"Computer Services",
            "type":"Services"
        }
    ],
    "sg:phone":"+1 530 458 7766",
    "sg:postcode":"95932",
    "sg:province":"CA",
    "sg:tags":[
        "internet"
    ],
    "sg:website":"www.mikewest.net",
    "wof:name":"Colusa Net",
    "wof:placetype":"venue"
},
  "geometry": {"coordinates":[-122.015361,39.216666],"type":"Point"}
}