{
  "type": "Feature",
  "properties": {
    "addr:full":"2787 Sapra St Thousand Oaks CA 91362",
    "addr:housenumber":"2787",
    "addr:postcode":"91362",
    "addr:street":"Sapra St",
    "iso:country":"US",
    "sg:address":"2787 Sapra St",
    "sg:city":"Thousand Oaks",
    "sg:classifiers":[
        {
            "category":"Real Estate",
            "subcategory":"Architect",
            "type":"Services"
        }
    ],
    "sg:phone":"+1 805 496 6301",
    "sg:postcode":"91362",
    "sg:province":"CA",
    "wof:name":"Daniel L Witting",
    "wof:placetype":"venue"
},
  "geometry": {"coordinates":[-118.836392,34.193481],"type":"Point"}
}