{
  "type": "Feature",
  "properties": {
    "iso:country":"US",
    "sg:address":"8527 Alondra Blvd",
    "sg:city":"Paramount",
    "sg:classifiers":[
        {
            "category":"Insurance",
            "subcategory":"Insurance Agent",
            "type":"Services"
        },
        {
            "category":"Insurance",
            "subcategory":"Hazard Insurance",
            "type":"Services"
        },
        {
            "category":"Insurance",
            "subcategory":"Title Insurance",
            "type":"Services"
        },
        {
            "category":"Insurance",
            "subcategory":"Life Insurance",
            "type":"Services"
        }
    ],
    "sg:phone":"+1 562 663 6830",
    "sg:postcode":"90723",
    "sg:province":"CA",
    "sg:tags":[
        "business",
        "auto",
        "commercial",
        "homeowner",
        "motorcycle",
        "renter"
    ],
    "wof:name":"Allstate Insurance Company - Rahmat Shirazi",
    "wof:placetype":"venue"
},
  "geometry": {"coordinates":[-118.15074799999999,33.889292],"type":"Point"}
}