{
  "type": "Feature",
  "properties": {
    "iso:country":"US",
    "sg:address":"1251 Pomona Rd",
    "sg:city":"Corona",
    "sg:classifiers":[
        {
            "category":"Professional",
            "subcategory":"Art Services",
            "type":"Services"
        }
    ],
    "sg:phone":"+1 951 549 1515",
    "sg:postcode":"92882",
    "sg:province":"CA",
    "sg:tags":[
        "graphic",
        "designer"
    ],
    "wof:name":"J Brenlin Design",
    "wof:placetype":"venue"
},
  "geometry": {"coordinates":[-117.590045,33.882583],"type":"Point"}
}