{
  "type": "Feature",
  "properties": {
    "iso:country":"US",
    "sg:address":"22634 Normandie Ave",
    "sg:city":"Torrance",
    "sg:classifiers":[
        {
            "category":"Wholesale",
            "subcategory":"Durable Goods & Equipment",
            "type":"Manufacturing & Wholesale Goods"
        }
    ],
    "sg:phone":"+1 310 320 4387",
    "sg:postcode":"90502",
    "sg:province":"CA",
    "wof:name":"La Captivative Corp",
    "wof:placetype":"venue"
},
  "geometry": {"coordinates":[-118.29809899999999,33.819104],"type":"Point"}
}