{
  "type": "Feature",
  "properties": {
    "iso:country":"US",
    "sg:address":"1400 10th Street",
    "sg:city":"Modesto",
    "sg:classifiers":[
        {
            "category":"Recreation",
            "subcategory":"Fishing",
            "type":"Entertainment"
        }
    ],
    "sg:phone":"+1 209 566 9516",
    "sg:postcode":"95354",
    "sg:province":"CA",
    "sg:tags":[
        "tackle",
        "bait"
    ],
    "wof:name":"Grandsons Bait And Tackle",
    "wof:placetype":"venue"
},
  "geometry": {"coordinates":[-121.006269,37.63796],"type":"Point"}
}