{
  "type": "Feature",
  "properties": {
    "iso:country":"US",
    "sg:address":"1980 Union St",
    "sg:city":"San Francisco",
    "sg:classifiers":[
        {
            "category":"Professional",
            "type":"Services"
        }
    ],
    "sg:phone":"+1 415 409 0150",
    "sg:postcode":"94123",
    "sg:province":"CA",
    "wof:name":"U Street",
    "wof:placetype":"venue"
},
  "geometry": {"coordinates":[-122.431848,37.79764],"type":"Point"}
}