{
  "type": "Feature",
  "properties": {
    "addr:full":"22975 Ashwood Lake Forest CA 92630",
    "addr:housenumber":"22975",
    "addr:postcode":"92630",
    "addr:street":"Ashwood",
    "iso:country":"US",
    "sg:address":"22975 Ashwood",
    "sg:city":"Lake Forest",
    "sg:classifiers":[
        {
            "category":"Professional",
            "subcategory":"Engineering",
            "type":"Services"
        }
    ],
    "sg:phone":"+1 949 859 2450",
    "sg:postcode":"92630",
    "sg:province":"CA",
    "sg:tags":[
        "engineer"
    ],
    "wof:name":"Alliance Engineering Group Inc",
    "wof:placetype":"venue"
},
  "geometry": {"coordinates":[-117.68568399999999,33.628832],"type":"Point"}
}