{
  "type": "Feature",
  "properties": {
    "addr:full":"1927 Artesia Blvd Redondo Beach CA 90278",
    "addr:housenumber":"1927",
    "addr:postcode":"90278",
    "addr:street":"Artesia Blvd",
    "iso:country":"US",
    "sg:address":"1927 Artesia Blvd",
    "sg:city":"Redondo Beach",
    "sg:classifiers":[
        {
            "category":"Wholesale",
            "subcategory":"Electrical",
            "type":"Manufacturing & Wholesale Goods"
        }
    ],
    "sg:phone":"+1 323 589 4202",
    "sg:postcode":"90278",
    "sg:province":"CA",
    "sg:tags":[
        "radio"
    ],
    "wof:name":"Pageman",
    "wof:placetype":"venue"
},
  "geometry": {"coordinates":[-118.379453,33.872906],"type":"Point"}
}