{
  "type": "Feature",
  "properties": {
    "addr:full":"1388 Longfellow Ave Chico CA 95926",
    "addr:housenumber":"1388",
    "addr:postcode":"95926",
    "addr:street":"Longfellow Ave",
    "iso:country":"US",
    "sg:address":"1388 Longfellow Ave",
    "sg:city":"Chico",
    "sg:phone":"+1 530 894 5670",
    "sg:postcode":"95926",
    "sg:province":"CA",
    "sg:tags":[
        "farm",
        "grain",
        "cash"
    ],
    "wof:name":"Maxwell Partners",
    "wof:placetype":"venue"
},
  "geometry": {"coordinates":[-121.82492000000001,39.750623],"type":"Point"}
}