{
  "type": "Feature",
  "properties": {
    "iso:country":"US",
    "sg:address":"475 S Arrowhead Ave",
    "sg:city":"San Bernardino",
    "sg:classifiers":[
        {
            "category":"Freight",
            "type":"Transportation"
        },
        {
            "category":"Autos & Motor Vehicles",
            "subcategory":"Motorcycle Sales",
            "type":"Retail Goods"
        }
    ],
    "sg:phone":"+1 909 889 3010",
    "sg:postcode":"92408",
    "sg:province":"CA",
    "sg:tags":[
        "scooter"
    ],
    "wof:name":"Tom Morgan Racing",
    "wof:placetype":"venue"
},
  "geometry": {"coordinates":[-117.289597,34.093493],"type":"Point"}
}