{
  "type": "Feature",
  "properties": {
    "addr:full":"1401 I St Modesto CA 95354",
    "addr:housenumber":"1401",
    "addr:postcode":"ca 95354",
    "addr:street":"I St",
    "iso:country":"US",
    "sg:address":"1401 I St",
    "sg:city":"Modesto",
    "sg:classifiers":[
        {
            "category":"Real Estate",
            "subcategory":"Real Estate Services",
            "type":"Services"
        }
    ],
    "sg:phone":"+1 209 529 8550",
    "sg:postcode":"95354",
    "sg:province":"CA",
    "sg:tags":[
        "company",
        "title"
    ],
    "sg:website":"www.stewartmodesto.com",
    "wof:name":"Stewart Title Co",
    "wof:placetype":"venue"
},
  "geometry": {"coordinates":[-120.99436300000001,37.643116],"type":"Point"}
}