{
  "type": "Feature",
  "properties": {
    "iso:country":"US",
    "sg:address":"115 S Topanga Canyon Blvd",
    "sg:city":"Topanga",
    "sg:classifiers":[
        {
            "category":"Retail",
            "subcategory":"Veterinary Services",
            "type":"Services"
        }
    ],
    "sg:phone":"+1 310 455 1330",
    "sg:postcode":"90290",
    "sg:province":"CA",
    "wof:name":"Animal Clinic",
    "wof:placetype":"venue"
},
  "geometry": {"coordinates":[-118.60433,34.08938],"type":"Point"}
}