{
  "type": "Feature",
  "properties": {
    "iso:country":"US",
    "sg:address":"714 N Humboldt Ave",
    "sg:city":"Willows",
    "sg:classifiers":[
        {
            "category":"Organizations",
            "subcategory":"Non-profit Organization",
            "type":"Services"
        }
    ],
    "sg:phone":"+1 530 934 3535",
    "sg:postcode":"95988",
    "sg:province":"CA",
    "wof:name":"President John F Kennedy Manor",
    "wof:placetype":"venue"
},
  "geometry": {"coordinates":[-122.21198,39.529286],"type":"Point"}
}