{
  "type": "Feature",
  "properties": {
    "iso:country":"US",
    "sg:address":"10 Rollins Rd",
    "sg:city":"Millbrae",
    "sg:classifiers":[
        {
            "category":"Social Services",
            "subcategory":"Job Training",
            "type":"Services"
        }
    ],
    "sg:phone":"+1 650 652 7858",
    "sg:postcode":"94030",
    "sg:province":"CA",
    "sg:tags":[
        "rehab",
        "government"
    ],
    "sg:website":"www.pennetsmc.com",
    "wof:name":"Pennet",
    "wof:placetype":"venue"
},
  "geometry": {"coordinates":[-122.382833,37.599494],"type":"Point"}
}