{
  "type": "Feature",
  "properties": {
    "addr:full":"600 S Williams Rd Palm Springs CA 92264",
    "addr:housenumber":"600",
    "addr:postcode":"92264",
    "addr:street":"S Williams Rd",
    "iso:country":"US",
    "sg:address":"600 S Williams Rd",
    "sg:city":"Palm Springs",
    "sg:classifiers":[
        {
            "category":"Autos & Motor Vehicles",
            "subcategory":"Auto Supplies",
            "type":"Retail Goods"
        }
    ],
    "sg:phone":"+1 760 325 3757",
    "sg:postcode":"92264",
    "sg:province":"CA",
    "sg:tags":[
        "glass"
    ],
    "wof:name":"Lg Auto Glass Service",
    "wof:placetype":"venue"
},
  "geometry": {"coordinates":[-116.495003,33.813702],"type":"Point"}
}