{
  "type": "Feature",
  "properties": {
    "addr:full":"50950 Madison St Indio CA 92201",
    "addr:housenumber":"50950",
    "addr:postcode":"92201",
    "addr:street":"Madison St",
    "iso:country":"US",
    "sg:address":"50950 Madison St",
    "sg:city":"Indio",
    "sg:classifiers":[
        {
            "category":"Recreation",
            "type":"Entertainment"
        }
    ],
    "sg:phone":"+1 760 342 2223",
    "sg:postcode":"92201",
    "sg:province":"CA",
    "sg:tags":[
        "organization",
        "horse"
    ],
    "wof:name":"Eldorado Polo Club Inc",
    "wof:placetype":"venue"
},
  "geometry": {"coordinates":[-116.25124599999999,33.672385],"type":"Point"}
}