{
  "type": "Feature",
  "properties": {
    "iso:country":"US",
    "sg:address":"415 4th St",
    "sg:city":"Marysville",
    "sg:classifiers":[
        {
            "category":"Restaurant",
            "type":"Food & Drink"
        }
    ],
    "sg:phone":"+1 530 743 6378",
    "sg:postcode":"95901",
    "sg:province":"CA",
    "wof:name":"Mama's Restaurant-Chinese Food",
    "wof:placetype":"venue"
},
  "geometry": {"coordinates":[-121.590357,39.139105],"type":"Point"}
}