{
  "type": "Feature",
  "properties": {
    "iso:country":"US",
    "sg:address":"20103 Harlan Ave",
    "sg:city":"Carson",
    "sg:classifiers":[
        {
            "category":"Real Estate",
            "subcategory":"Real Estate Agent",
            "type":"Services"
        }
    ],
    "sg:phone":"+1 310 639 1160",
    "sg:postcode":"90746",
    "sg:province":"CA",
    "wof:name":"Deangelo Real Estate",
    "wof:placetype":"venue"
},
  "geometry": {"coordinates":[-118.24292,33.848748],"type":"Point"}
}