{
  "type": "Feature",
  "properties": {
    "iso:country":"US",
    "sg:address":"3535 E Coast Hwy",
    "sg:city":"Corona Del Mar",
    "sg:classifiers":[
        {
            "category":"Real Estate",
            "subcategory":"Real Estate Operator",
            "type":"Services"
        }
    ],
    "sg:phone":"+1 949 283 0206",
    "sg:postcode":"92625",
    "sg:province":"CA",
    "sg:tags":[
        "building",
        "nonresidential"
    ],
    "wof:name":"Turtle Ridge Properties",
    "wof:placetype":"venue"
},
  "geometry": {"coordinates":[-117.86893000000001,33.594742],"type":"Point"}
}