{
  "type": "Feature",
  "properties": {
    "iso:country":"US",
    "sg:address":"7880 Airway Rd",
    "sg:city":"San Diego",
    "sg:classifiers":[
        {
            "category":"Shopping",
            "subcategory":"Used Merchandise",
            "type":"Retail Goods"
        }
    ],
    "sg:phone":"+1 619 710 2547",
    "sg:postcode":"92154",
    "sg:province":"CA",
    "wof:name":"Appliance Distribution LLC",
    "wof:placetype":"venue"
},
  "geometry": {"coordinates":[-116.97518100000001,32.560703],"type":"Point"}
}