{
  "type": "Feature",
  "properties": {
    "addr:full":"5791 Mountain View Ave Yorba Linda CA 92886",
    "addr:housenumber":"5791",
    "addr:postcode":"92886",
    "addr:street":"Mountain View Ave",
    "iso:country":"US",
    "sg:address":"5791 Mountain View Ave",
    "sg:city":"Yorba Linda",
    "sg:classifiers":[
        {
            "category":"Professional",
            "type":"Services"
        }
    ],
    "sg:phone":"+1 714 779 6095",
    "sg:postcode":"92886",
    "sg:province":"CA",
    "wof:name":"Lamar Saunders Inc",
    "wof:placetype":"venue"
},
  "geometry": {"coordinates":[-117.797042,33.877953],"type":"Point"}
}