{
  "type": "Feature",
  "properties": {
    "addr:full":"46321 Nandina Ct Indian Wells CA 92210",
    "addr:housenumber":"46321",
    "addr:postcode":"92210",
    "addr:street":"Nandina Ct",
    "iso:country":"US",
    "sg:address":"46321 Nandina Ct",
    "sg:city":"Indian Wells",
    "sg:classifiers":[
        {
            "category":"Professional",
            "type":"Services"
        }
    ],
    "sg:phone":"+1 760 862 2435",
    "sg:postcode":"92210",
    "sg:province":"CA",
    "sg:tags":[
        "establishment"
    ],
    "wof:name":"Epstein & Epstein",
    "wof:placetype":"venue"
},
  "geometry": {"coordinates":[-116.3627,33.709379],"type":"Point"}
}