{
  "type": "Feature",
  "properties": {
    "iso:country":"US",
    "sg:address":"6380 Silverado Trl",
    "sg:city":"Napa",
    "sg:classifiers":[
        {
            "category":"Travel",
            "subcategory":"Hotels & Motels",
            "type":"Entertainment"
        },
        {
            "category":"Travel",
            "subcategory":"Bed & Breakfast",
            "type":"Entertainment"
        }
    ],
    "sg:phone":"+1 707 944 0646",
    "sg:postcode":"94558",
    "sg:province":"CA",
    "sg:tags":[
        "inn",
        "lodging"
    ],
    "wof:name":"Poetry Inn",
    "wof:placetype":"venue"
},
  "geometry": {"coordinates":[-122.340536,38.426992],"type":"Point"}
}