{
  "type": "Feature",
  "properties": {
    "addr:full":"3675 Barnard Dr Oceanside CA 92056",
    "addr:housenumber":"3675",
    "addr:postcode":"92056",
    "addr:street":"Barnard Dr",
    "iso:country":"US",
    "sg:address":"3675 Barnard Dr",
    "sg:city":"Oceanside",
    "sg:classifiers":[
        {
            "category":"Real Estate",
            "subcategory":"Real Estate Operator",
            "type":"Services"
        }
    ],
    "sg:phone":"+1 760 757 9260",
    "sg:postcode":"92056",
    "sg:province":"CA",
    "sg:tags":[
        "apartment"
    ],
    "wof:name":"Terra Pacifica LLC",
    "wof:placetype":"venue"
},
  "geometry": {"coordinates":[-117.297448,33.1867],"type":"Point"}
}