{
  "type": "Feature",
  "properties": {
    "iso:country":"US",
    "sg:address":"2643 W Williams St",
    "sg:city":"Banning",
    "sg:classifiers":[
        {
            "category":"Government",
            "subcategory":"Office",
            "type":"Public Place"
        }
    ],
    "sg:phone":"+1 951 849 3929",
    "sg:postcode":"92220",
    "sg:province":"CA",
    "wof:name":"Casa De San Bernardino Inc",
    "wof:placetype":"venue"
},
  "geometry": {"coordinates":[-116.905632,33.927341],"type":"Point"}
}