{
  "type": "Feature",
  "properties": {
    "addr:full":"1510 Sweetwater Rd National City CA 91950",
    "addr:housenumber":"1510",
    "addr:postcode":"91950",
    "addr:street":"Sweetwater Rd",
    "iso:country":"US",
    "sg:address":"1510 Sweetwater Rd",
    "sg:city":"National City",
    "sg:classifiers":[
        {
            "category":"Shopping",
            "subcategory":"Discount & Variety Stores",
            "type":"Retail Goods"
        }
    ],
    "sg:phone":"+1 619 477 0827",
    "sg:postcode":"91950",
    "sg:province":"CA",
    "wof:name":"Dollar Store Plus",
    "wof:placetype":"venue"
},
  "geometry": {"coordinates":[-117.083544,32.661122],"type":"Point"}
}