{
  "type": "Feature",
  "properties": {
    "addr:full":"5743 Rhodes Ave Valley Village CA 91607",
    "addr:housenumber":"5743",
    "addr:postcode":"91607",
    "addr:street":"Rhodes Ave",
    "iso:country":"US",
    "sg:address":"5743 Rhodes Ave",
    "sg:city":"Valley Village",
    "sg:classifiers":[
        {
            "category":"Professional",
            "subcategory":"Research",
            "type":"Services"
        }
    ],
    "sg:phone":"+1 818 762 9046",
    "sg:postcode":"91607",
    "sg:province":"CA",
    "wof:name":"Solow Research & Development",
    "wof:placetype":"venue"
},
  "geometry": {"coordinates":[-118.403192,34.174587],"type":"Point"}
}