{
  "type": "Feature",
  "properties": {
    "iso:country":"US",
    "sg:address":"8330 S Gate Ave",
    "sg:city":"South Gate",
    "sg:classifiers":[
        {
            "category":"Restaurant",
            "type":"Food & Drink"
        }
    ],
    "sg:phone":"+1 323 582 1700",
    "sg:postcode":"90280",
    "sg:province":"CA",
    "wof:name":"Subway Sandwiches & Salads",
    "wof:placetype":"venue"
},
  "geometry": {"coordinates":[-118.213228,33.963099],"type":"Point"}
}