{
  "type": "Feature",
  "properties": {
    "iso:country":"US",
    "sg:address":"311 W Main St",
    "sg:city":"San Jacinto",
    "sg:classifiers":[
        {
            "category":"Organizations",
            "subcategory":"Religious Organization",
            "type":"Services"
        }
    ],
    "sg:phone":"+1 951 654 6118",
    "sg:postcode":"92583",
    "sg:province":"CA",
    "sg:tags":[
        "church"
    ],
    "wof:name":"New Life Chapel",
    "wof:placetype":"venue"
},
  "geometry": {"coordinates":[-116.96130599999999,33.783979],"type":"Point"}
}