{
  "type": "Feature",
  "properties": {
    "iso:country":"US",
    "sg:address":"375 Oyster Point Blvd",
    "sg:city":"S San Francisco",
    "sg:classifiers":[
        {
            "category":"Manufacturing",
            "subcategory":"Tools & Machinery",
            "type":"Manufacturing & Wholesale Goods"
        }
    ],
    "sg:phone":"+1 650 871 5866",
    "sg:postcode":"94080",
    "sg:province":"CA",
    "sg:tags":[
        "contractor"
    ],
    "wof:name":"Safeworks",
    "wof:placetype":"venue"
},
  "geometry": {"coordinates":[-122.386009,37.662691],"type":"Point"}
}