{
  "type": "Feature",
  "properties": {
    "iso:country":"US",
    "sg:address":"870 Market St",
    "sg:city":"San Francisco",
    "sg:classifiers":[
        {
            "category":"Professional",
            "subcategory":"Engineering",
            "type":"Services"
        }
    ],
    "sg:phone":"+1 415 433 4848",
    "sg:postcode":"94102",
    "sg:province":"CA",
    "sg:tags":[
        "engineer"
    ],
    "wof:name":"Schaaf & Wheeler",
    "wof:placetype":"venue"
},
  "geometry": {"coordinates":[-122.406645,37.785415],"type":"Point"}
}