{
  "type": "Feature",
  "properties": {
    "iso:country":"US",
    "sg:address":"603 S Mariposa Ave",
    "sg:city":"Los Angeles",
    "sg:classifiers":[
        {
            "category":"Shopping",
            "type":"Retail Goods"
        }
    ],
    "sg:phone":"+1 213 365 9394",
    "sg:postcode":"90005",
    "sg:province":"CA",
    "sg:tags":[
        "art",
        "gallery",
        "dealer"
    ],
    "wof:name":"Hunam Galleria",
    "wof:placetype":"venue"
},
  "geometry": {"coordinates":[-118.299268,34.062425],"type":"Point"}
}