{
  "type": "Feature",
  "properties": {
    "addr:full":"1167 N Fair Oaks Ave Sunnyvale CA 94089",
    "addr:housenumber":"1167",
    "addr:postcode":"94089",
    "addr:street":"N Fair Oaks Ave",
    "iso:country":"US",
    "sg:address":"1167 N Fair Oaks Ave",
    "sg:city":"Sunnyvale",
    "sg:classifiers":[
        {
            "category":"Wholesale",
            "subcategory":"Computers",
            "type":"Manufacturing & Wholesale Goods"
        }
    ],
    "sg:phone":"+1 408 907 3900",
    "sg:postcode":"94089",
    "sg:province":"CA",
    "wof:name":"Empire Tech",
    "wof:placetype":"venue"
},
  "geometry": {"coordinates":[-122.01028100000001,37.403777],"type":"Point"}
}