{
  "type": "Feature",
  "properties": {
    "addr:full":"5022 Orrville Ave Woodland Hills CA 91367",
    "addr:postcode":"5022;91367",
    "addr:street":"Orrville Ave",
    "iso:country":"US",
    "sg:address":"5022 Orrville Ave",
    "sg:city":"Woodland Hills",
    "sg:classifiers":[
        {
            "category":"Professional",
            "subcategory":"Business Services",
            "type":"Services"
        }
    ],
    "sg:phone":"+1 818 703 7108",
    "sg:postcode":"91367",
    "sg:province":"CA",
    "sg:tags":[
        "personal",
        "credit",
        "institution"
    ],
    "wof:name":"Commercial Financial Resources",
    "wof:placetype":"venue"
},
  "geometry": {"coordinates":[-118.643393,34.162487],"type":"Point"}
}