{
  "type": "Feature",
  "properties": {
    "iso:country":"US",
    "sg:address":"7822 Foothill Blvd",
    "sg:city":"Sunland",
    "sg:classifiers":[
        {
            "category":"Restaurant",
            "type":"Food & Drink"
        }
    ],
    "sg:phone":"+1 818 353 8948",
    "sg:postcode":"91040",
    "sg:province":"CA",
    "sg:tags":[
        "style",
        "chinese",
        "family",
        "asian",
        "pan"
    ],
    "wof:name":"Chor's Chinese Cuisine",
    "wof:placetype":"venue"
},
  "geometry": {"coordinates":[-118.303577,34.259554],"type":"Point"}
}