{
  "type": "Feature",
  "properties": {
    "addr:full":"645 5th Street San Francisco CA 94107",
    "addr:housenumber":"645",
    "addr:postcode":"94107",
    "addr:street":"5Th Street",
    "iso:country":"US",
    "sg:address":"645 5th Street",
    "sg:city":"San Francisco",
    "sg:classifiers":[
        {
            "category":"Health Services",
            "subcategory":"Health Practitioner",
            "type":"Services"
        }
    ],
    "sg:phone":"+1 415 777 5009",
    "sg:postcode":"94107",
    "sg:province":"CA",
    "sg:tags":[
        "therapy",
        "physical"
    ],
    "sg:website":"www.acephysicaltherapysf.com",
    "wof:name":"Ace Physical Therapy And Sports Medicine",
    "wof:placetype":"venue"
},
  "geometry": {"coordinates":[-122.397682,37.77679],"type":"Point"}
}