{
  "type": "Feature",
  "properties": {
    "addr:full":"333 N Plumas St Willows CA 95988",
    "addr:housenumber":"333",
    "addr:postcode":"95988",
    "addr:street":"N Plumas St",
    "iso:country":"US",
    "sg:address":"333 N Plumas St",
    "sg:city":"Willows",
    "sg:classifiers":[
        {
            "category":"Professional",
            "subcategory":"Lawyer & Legal Services",
            "type":"Services"
        }
    ],
    "sg:phone":"+1 530 934 3680",
    "sg:postcode":"95988",
    "sg:province":"CA",
    "sg:tags":[
        "attorney"
    ],
    "wof:name":"David R Nelson Law Office",
    "wof:placetype":"venue"
},
  "geometry": {"coordinates":[-122.19817999999999,39.524169],"type":"Point"}
}