{
  "type": "Feature",
  "properties": {
    "iso:country":"US",
    "sg:address":"855 S Wildflower Ln",
    "sg:city":"Anaheim",
    "sg:classifiers":[
        {
            "category":"Wholesale",
            "subcategory":"Auto Parts",
            "type":"Manufacturing & Wholesale Goods"
        }
    ],
    "sg:phone":"+1 714 998 6581",
    "sg:postcode":"92808",
    "sg:province":"CA",
    "wof:name":"Nuetech",
    "wof:placetype":"venue"
},
  "geometry": {"coordinates":[-117.73535099999999,33.858757],"type":"Point"}
}