{
  "type": "Feature",
  "properties": {
    "addr:full":"6016 Pony Express Trail Pollock Pines CA 95726",
    "addr:housenumber":"6016",
    "addr:postcode":"95726",
    "addr:street":"Pony Express Trail",
    "iso:country":"US",
    "sg:address":"6016 Pony Express Trail",
    "sg:city":"Pollock Pines",
    "sg:classifiers":[
        {
            "category":"Retail",
            "subcategory":"Auto Repair",
            "type":"Services"
        },
        {
            "category":"Government",
            "subcategory":"Office",
            "type":"Public Place"
        }
    ],
    "sg:phone":"+1 530 644 7900",
    "sg:postcode":"95726",
    "sg:province":"CA",
    "sg:tags":[
        "smog",
        "check"
    ],
    "sg:website":"www.atozautomotiveonline.com/con...",
    "wof:name":"A to Z Automotive",
    "wof:placetype":"venue"
},
  "geometry": {"coordinates":[-120.595597,38.756235],"type":"Point"}
}