{
  "type": "Feature",
  "properties": {
    "iso:country":"US",
    "sg:address":"9140 Highland Ave",
    "sg:city":"Alta Loma",
    "sg:classifiers":[
        {
            "category":"Manufacturing",
            "subcategory":"Retail Goods",
            "type":"Manufacturing & Wholesale Goods"
        }
    ],
    "sg:phone":"+1 909 989 4973",
    "sg:postcode":"91701",
    "sg:province":"CA",
    "sg:tags":[
        "assembly",
        "fabricating"
    ],
    "wof:name":"Complete Fabrication Svc",
    "wof:placetype":"venue"
},
  "geometry": {"coordinates":[-117.603685,34.135673],"type":"Point"}
}