{
  "type": "Feature",
  "properties": {
    "iso:country":"US",
    "sg:address":"1122 Sutherland Ln Apt 3",
    "sg:city":"Capitola",
    "sg:classifiers":[
        {
            "category":"Home & Garden",
            "subcategory":"Carpets & Floor Coverings",
            "type":"Retail Goods"
        }
    ],
    "sg:phone":"+1 888 285 3397",
    "sg:postcode":"95010",
    "sg:province":"CA",
    "sg:tags":[
        "hardwood"
    ],
    "wof:name":"Hardwood Maniac",
    "wof:placetype":"venue"
},
  "geometry": {"coordinates":[-121.93941,36.982568],"type":"Point"}
}