{
  "type": "Feature",
  "properties": {
    "addr:full":"9560 Topanga Canyon Blvd Chatsworth CA 91311",
    "addr:housenumber":"9560",
    "addr:postcode":"91311",
    "addr:street":"Topanga Canyon Blvd",
    "iso:country":"US",
    "sg:address":"9560 Topanga Canyon Blvd",
    "sg:city":"Chatsworth",
    "sg:classifiers":[
        {
            "category":"Manufacturing",
            "subcategory":"Rubber & Plastics",
            "type":"Manufacturing & Wholesale Goods"
        },
        {
            "category":"Shopping",
            "subcategory":"Party Supplies",
            "type":"Retail Goods"
        },
        {
            "category":"Personal",
            "type":"Services"
        }
    ],
    "sg:phone":"+1 818 349 3374",
    "sg:postcode":"91311",
    "sg:province":"CA",
    "sg:tags":[
        "balloon",
        "delivery",
        "balloons-retail",
        "toy-wholesale",
        "balloons-novelty",
        "decorator",
        "manufacturer"
    ],
    "wof:name":"Boulevard Balloons",
    "wof:placetype":"venue"
},
  "geometry": {"coordinates":[-118.60651900000001,34.24324],"type":"Point"}
}