{
  "type": "Feature",
  "properties": {
    "iso:country":"US",
    "sg:address":"1 Sansome St",
    "sg:city":"San Francisco",
    "sg:classifiers":[
        {
            "category":"Professional",
            "type":"Services"
        }
    ],
    "sg:phone":"+1 415 984 3142",
    "sg:postcode":"94104",
    "sg:province":"CA",
    "sg:tags":[
        "establishment"
    ],
    "wof:name":"Signal Capital Corp",
    "wof:placetype":"venue"
},
  "geometry": {"coordinates":[-122.400744,37.791177],"type":"Point"}
}