{
  "type": "Feature",
  "properties": {
    "iso:country":"US",
    "sg:address":"956 Ralston Ave",
    "sg:city":"Belmont",
    "sg:classifiers":[
        {
            "category":"Professional",
            "type":"Services"
        }
    ],
    "sg:phone":"+1 650 771 4332",
    "sg:postcode":"94002",
    "sg:province":"CA",
    "sg:tags":[
        "caterer"
    ],
    "sg:website":"www.grissinicatering.com",
    "wof:name":"Grissini Catering",
    "wof:placetype":"venue"
},
  "geometry": {"coordinates":[-122.277112,37.519444],"type":"Point"}
}