{
  "type": "Feature",
  "properties": {
    "iso:country":"US",
    "sg:address":"2946 College Ave",
    "sg:city":"Berkeley",
    "sg:classifiers":[
        {
            "category":"Personal",
            "subcategory":"Beauty Salon",
            "type":"Services"
        }
    ],
    "sg:phone":"+1 510 548 1588",
    "sg:postcode":"94705",
    "sg:province":"CA",
    "wof:name":"Great Lengths",
    "wof:placetype":"venue"
},
  "geometry": {"coordinates":[-122.253257,37.858202],"type":"Point"}
}