{
  "type": "Feature",
  "properties": {
    "addr:full":"22803 Hawthorne Blvd Torrance CA 90505",
    "addr:housenumber":"22803",
    "addr:postcode":"90505",
    "addr:street":"Hawthorne Blvd",
    "iso:country":"US",
    "sg:address":"22803 Hawthorne Blvd",
    "sg:city":"Torrance",
    "sg:classifiers":[
        {
            "category":"Banks & Credit Unions",
            "subcategory":"Bank",
            "type":"Services"
        },
        {
            "category":"Banks & Credit Unions",
            "subcategory":"Financial Services",
            "type":"Services"
        }
    ],
    "sg:phone":"+1 310 465 0226",
    "sg:postcode":"90505",
    "sg:province":"CA",
    "sg:tags":[
        "broker",
        "mortgage"
    ],
    "sg:website":"www.chase.com",
    "wof:name":"Washington Mutual Finance",
    "wof:placetype":"venue"
},
  "geometry": {"coordinates":[-118.350998,33.8209],"type":"Point"}
}