{
  "type": "Feature",
  "properties": {
    "iso:country":"US",
    "sg:address":"8105 Capwell Dr",
    "sg:city":"Oakland",
    "sg:classifiers":[
        {
            "category":"Organizations",
            "subcategory":"Community Association",
            "type":"Services"
        }
    ],
    "sg:phone":"+1 510 568 1711",
    "sg:postcode":"94621",
    "sg:province":"CA",
    "sg:tags":[
        "housing",
        "student",
        "fraternal"
    ],
    "wof:name":"Mecca Shrine Club",
    "wof:placetype":"venue"
},
  "geometry": {"coordinates":[-122.202744,37.738377],"type":"Point"}
}