{
  "type": "Feature",
  "properties": {
    "addr:full":"111 E 11th St Merced CA 95341",
    "addr:housenumber":"111",
    "addr:postcode":"95341",
    "addr:street":"E 11Th St",
    "iso:country":"US",
    "sg:address":"111 E 11th St",
    "sg:city":"Merced",
    "sg:classifiers":[
        {
            "category":"Bars & Pubs",
            "type":"Food & Drink"
        }
    ],
    "sg:phone":"+1 209 722 8519",
    "sg:postcode":"95341",
    "sg:province":"CA",
    "wof:name":"Club Morelos",
    "wof:placetype":"venue"
},
  "geometry": {"coordinates":[-120.478077,37.291853],"type":"Point"}
}