{
  "type": "Feature",
  "properties": {
    "addr:full":"1224 Santa Anita Ave South El Monte CA 91733",
    "addr:housenumber":"1224",
    "addr:postcode":"91733",
    "addr:street":"Santa Anita Ave",
    "iso:country":"US",
    "sg:address":"1224 Santa Anita Ave",
    "sg:city":"South El Monte",
    "sg:classifiers":[
        {
            "category":"Manufacturing",
            "subcategory":"Printing",
            "type":"Manufacturing & Wholesale Goods"
        }
    ],
    "sg:phone":"+1 626 575 1331",
    "sg:postcode":"91733",
    "sg:province":"CA",
    "sg:tags":[
        "lithographic",
        "commercial"
    ],
    "wof:name":"Golden Century Printing Inc",
    "wof:placetype":"venue"
},
  "geometry": {"coordinates":[-118.046317,34.043809],"type":"Point"}
}