{
  "type": "Feature",
  "properties": {
    "addr:full":"1729 E Florence Ave Los Angeles CA 90001",
    "addr:housenumber":"1729",
    "addr:postcode":"90001",
    "addr:street":"E Florence Ave",
    "iso:country":"US",
    "sg:address":"1729 E Florence Ave",
    "sg:city":"Los Angeles",
    "sg:classifiers":[
        {
            "category":"Autos & Motor Vehicles",
            "subcategory":"Auto Supplies",
            "type":"Retail Goods"
        }
    ],
    "sg:phone":"+1 323 582 3600",
    "sg:postcode":"90001",
    "sg:province":"CA",
    "sg:tags":[
        "tire"
    ],
    "wof:name":"Alvarado's Tire Shop No 2",
    "wof:placetype":"venue"
},
  "geometry": {"coordinates":[-118.241997,33.974899],"type":"Point"}
}