{
  "type": "Feature",
  "properties": {
    "iso:country":"US",
    "sg:address":"3755 el Camino Dr",
    "sg:city":"San Bernardino",
    "sg:classifiers":[
        {
            "category":"Building & Trades",
            "subcategory":"Construction",
            "type":"Services"
        }
    ],
    "sg:phone":"+1 909 881 5241",
    "sg:postcode":"92404",
    "sg:province":"CA",
    "sg:tags":[
        "designer"
    ],
    "sg:website":"www.timberwolfsiren.com",
    "wof:name":"Class One Design",
    "wof:placetype":"venue"
},
  "geometry": {"coordinates":[-117.25317699999999,34.1566],"type":"Point"}
}