{
  "type": "Feature",
  "properties": {
    "addr:full":"16007 Kaplan Ave City Of Industry CA 91744",
    "addr:housenumber":"16007",
    "addr:postcode":"91744",
    "addr:street":"Kaplan Ave",
    "iso:country":"US",
    "sg:address":"16007 Kaplan Ave",
    "sg:city":"City Of Industry",
    "sg:classifiers":[
        {
            "category":"Wholesale",
            "subcategory":"Electrical",
            "type":"Manufacturing & Wholesale Goods"
        }
    ],
    "sg:phone":"+1 626 369 1971",
    "sg:postcode":"91744",
    "sg:province":"CA",
    "sg:tags":[
        "equipment",
        "electronic",
        "supply"
    ],
    "wof:name":"Best Grand Electronic U S A",
    "wof:placetype":"venue"
},
  "geometry": {"coordinates":[-117.93588699999999,34.034913],"type":"Point"}
}