{
  "type": "Feature",
  "properties": {
    "addr:full":"6818 Concert Way Sacramento CA 95842",
    "addr:postcode":"6818;95842",
    "addr:street":"Concert Way",
    "iso:country":"US",
    "sg:address":"6818 Concert Way",
    "sg:city":"Sacramento",
    "sg:classifiers":[
        {
            "category":"Education",
            "subcategory":"Special Training",
            "type":"Public Place"
        }
    ],
    "sg:phone":"+1 916 338 5735",
    "sg:postcode":"95842",
    "sg:province":"CA",
    "sg:tags":[
        "school",
        "computer",
        "technology"
    ],
    "wof:name":"Sun City Soft",
    "wof:placetype":"venue"
},
  "geometry": {"coordinates":[-121.342361,38.690403],"type":"Point"}
}