{
  "type": "Feature",
  "properties": {
    "addr:full":"22429 Bloomfld Hawaiian Gardens CA 90716",
    "addr:housenumber":"22429",
    "addr:postcode":"90716",
    "addr:street":"Bloomfld Hawaiian Gardens",
    "iso:country":"US",
    "sg:address":"22429 Bloomfld",
    "sg:city":"Hawaiian Gardens",
    "sg:classifiers":[
        {
            "category":"Food & Beverages",
            "subcategory":"Liquor & Beverages",
            "type":"Retail Goods"
        },
        {
            "category":"Food & Beverages",
            "subcategory":"Groceries & Convenience Stores",
            "type":"Retail Goods"
        }
    ],
    "sg:phone":"+1 562 431 4833",
    "sg:postcode":"90716",
    "sg:province":"CA",
    "sg:tags":[
        "beer",
        "spirit",
        "wine"
    ],
    "wof:name":"Quick Shop Liquor",
    "wof:placetype":"venue"
},
  "geometry": {"coordinates":[-118.06999999999999,33.830601],"type":"Point"}
}