{
  "type": "Feature",
  "properties": {
    "addr:full":"1147 E Colorado St Glendale CA 91205",
    "addr:housenumber":"1147",
    "addr:postcode":"91205",
    "addr:street":"E Colorado St",
    "iso:country":"US",
    "sg:address":"1147 E Colorado St",
    "sg:city":"Glendale",
    "sg:classifiers":[
        {
            "category":"Food & Beverages",
            "subcategory":"Bakery",
            "type":"Retail Goods"
        }
    ],
    "sg:phone":"+1 818 500 1363",
    "sg:postcode":"91205",
    "sg:province":"CA",
    "sg:tags":[
        "donut",
        "doughnut"
    ],
    "wof:name":"Foster's Donuts",
    "wof:placetype":"venue"
},
  "geometry": {"coordinates":[-118.239998,34.142799],"type":"Point"}
}