{
  "type": "Feature",
  "properties": {
    "iso:country":"US",
    "sg:address":"1926 Doreen Ave",
    "sg:city":"South El Monte",
    "sg:classifiers":[
        {
            "category":"Social Services",
            "type":"Services"
        }
    ],
    "sg:phone":"+1 626 442 4273",
    "sg:postcode":"91733",
    "sg:province":"CA",
    "sg:tags":[
        "organization",
        "welfare"
    ],
    "wof:name":"God Provides Ministry",
    "wof:placetype":"venue"
},
  "geometry": {"coordinates":[-118.044656,34.050119],"type":"Point"}
}