{
  "type": "Feature",
  "properties": {
    "addr:full":"1541 Rademacher Way Ridgecrest CA 93555",
    "addr:housenumber":"1541",
    "addr:postcode":"93555",
    "addr:street":"Rademacher Way",
    "iso:country":"US",
    "sg:address":"1541 Rademacher Way",
    "sg:city":"Ridgecrest",
    "sg:classifiers":[
        {
            "category":"Utilities",
            "subcategory":"Fuel Oil & Lpg",
            "type":"Services"
        }
    ],
    "sg:phone":"+1 760 375 5419",
    "sg:postcode":"93555",
    "sg:province":"CA",
    "sg:tags":[
        "dealer"
    ],
    "wof:name":"Woodchuck Express Firewood Co",
    "wof:placetype":"venue"
},
  "geometry": {"coordinates":[-117.681999,35.596087],"type":"Point"}
}