{
  "type": "Feature",
  "properties": {
    "addr:full":"3754 Electro Way Redding CA 96002",
    "addr:housenumber":"3754",
    "addr:postcode":"96002",
    "addr:street":"Electro Way",
    "iso:country":"US",
    "sg:address":"3754 Electro Way",
    "sg:city":"Redding",
    "sg:phone":"+1 530 223 7400",
    "sg:postcode":"96002",
    "sg:province":"CA",
    "sg:tags":[
        "equipment",
        "station"
    ],
    "sg:website":"www.phil-tite.com",
    "wof:name":"Phil-Tite Enterprises",
    "wof:placetype":"venue"
},
  "geometry": {"coordinates":[-122.300116,40.530125],"type":"Point"}
}