{
  "type": "Feature",
  "properties": {
    "addr:full":"610 W Betteravia Rd Ste A Santa Maria CA 93455",
    "addr:housenumber":"610",
    "addr:postcode":"93455",
    "addr:street":"W Betteravia Rd Ste A",
    "iso:country":"US",
    "sg:address":"610 W Betteravia Rd Ste A",
    "sg:city":"Santa Maria",
    "sg:classifiers":[
        {
            "category":"Insurance",
            "subcategory":"Health Insurance",
            "type":"Services"
        }
    ],
    "sg:phone":"+1 805 922 5718",
    "sg:postcode":"93455",
    "sg:province":"CA",
    "sg:tags":[
        "market"
    ],
    "wof:name":"Entenmann's Oroweat Baking Company",
    "wof:placetype":"venue"
},
  "geometry": {"coordinates":[-120.442763,34.918574],"type":"Point"}
}