{
  "type": "Feature",
  "properties": {
    "addr:full":"1826 E Mauretania St Wilmington CA 90744",
    "addr:housenumber":"1826",
    "addr:postcode":"90744",
    "addr:street":"E Mauretania St",
    "iso:country":"US",
    "sg:address":"1826 E Mauretania St",
    "sg:city":"Wilmington",
    "sg:classifiers":[
        {
            "category":"Wholesale",
            "subcategory":"Auto Parts",
            "type":"Manufacturing & Wholesale Goods"
        }
    ],
    "sg:phone":"+1 310 549 8252",
    "sg:postcode":"90744",
    "sg:province":"CA",
    "sg:tags":[
        "automobile"
    ],
    "wof:name":"PCH Auto Reconditioning",
    "wof:placetype":"venue"
},
  "geometry": {"coordinates":[-118.24008600000001,33.790385],"type":"Point"}
}