{
  "type": "Feature",
  "properties": {
    "addr:full":"4119 Santo Tomas Dr Los Angeles CA 90008",
    "addr:housenumber":"4119",
    "addr:postcode":"90008",
    "addr:street":"Santo Tomas Dr",
    "iso:country":"US",
    "sg:address":"4119 Santo Tomas Dr",
    "sg:city":"Los Angeles",
    "sg:classifiers":[
        {
            "category":"Social Services",
            "type":"Services"
        }
    ],
    "sg:phone":"+1 323 294 7411",
    "sg:postcode":"90008",
    "sg:province":"CA",
    "sg:tags":[
        "information",
        "cancer"
    ],
    "wof:name":"Real Men Cook Foundation",
    "wof:placetype":"venue"
},
  "geometry": {"coordinates":[-118.345415,34.010313],"type":"Point"}
}