{
  "type": "Feature",
  "properties": {
    "addr:full":"4721 Kelton Way # A Sacramento CA 95838",
    "addr:housenumber":"4721",
    "addr:postcode":"95838",
    "addr:street":"Kelton Way # A",
    "iso:country":"US",
    "sg:address":"4721 Kelton Way # A",
    "sg:city":"Sacramento",
    "sg:classifiers":[
        {
            "category":"Personal",
            "type":"Services"
        }
    ],
    "sg:phone":"+1 916 332 0151",
    "sg:postcode":"95838",
    "sg:province":"CA",
    "sg:tags":[
        "mover"
    ],
    "wof:name":"N American Van Lines-Valley Relocation & Storage",
    "wof:placetype":"venue"
},
  "geometry": {"coordinates":[-121.466003,38.653801],"type":"Point"}
}