{
  "type": "Feature",
  "properties": {
    "iso:country":"US",
    "sg:address":"8740 Park St",
    "sg:city":"Bellflower",
    "sg:classifiers":[
        {
            "category":"Retail",
            "subcategory":"Auto Repair",
            "type":"Services"
        }
    ],
    "sg:phone":"+1 562 529 7195",
    "sg:postcode":"90706",
    "sg:province":"CA",
    "sg:tags":[
        "body",
        "automobile",
        "painting"
    ],
    "wof:name":"Tino's Bodywork",
    "wof:placetype":"venue"
},
  "geometry": {"coordinates":[-118.147333,33.878294],"type":"Point"}
}