{
  "type": "Feature",
  "properties": {
    "iso:country":"US",
    "sg:address":"2098 E Main St",
    "sg:city":"Quincy",
    "sg:classifiers":[
        {
            "category":"Professional",
            "subcategory":"Accounting & Tax Preparation",
            "type":"Services"
        }
    ],
    "sg:phone":"+1 530 283 0825",
    "sg:postcode":"95971",
    "sg:province":"CA",
    "sg:tags":[
        "return",
        "filing"
    ],
    "wof:name":"H & R Block Tax Svc",
    "wof:placetype":"venue"
},
  "geometry": {"coordinates":[-120.898447,39.93393],"type":"Point"}
}