{
  "type": "Feature",
  "properties": {
    "iso:country":"US",
    "sg:address":"1450 Neotomas Ave",
    "sg:city":"Santa Rosa",
    "sg:classifiers":[
        {
            "category":"Government",
            "subcategory":"Office",
            "type":"Public Place"
        }
    ],
    "sg:phone":"+1 707 573 6300",
    "sg:postcode":"95405",
    "sg:province":"CA",
    "sg:tags":[
        "state",
        "resource"
    ],
    "wof:name":"Compensation Insurance Fund",
    "wof:placetype":"venue"
},
  "geometry": {"coordinates":[-122.687651,38.433752],"type":"Point"}
}