{
  "type": "Feature",
  "properties": {
    "addr:full":"4110 West Riverside Drive Burbank CA 91502",
    "addr:housenumber":"4110",
    "addr:postcode":"91502",
    "addr:street":"West Riverside Drive",
    "iso:country":"US",
    "sg:address":"4110 West Riverside Drive",
    "sg:city":"Burbank",
    "sg:classifiers":[
        {
            "category":"Personal",
            "subcategory":"Beauty Salon",
            "type":"Services"
        },
        {
            "category":"Personal",
            "subcategory":"Tanning Parlor",
            "type":"Services"
        }
    ],
    "sg:phone":"+1 818 599 8015",
    "sg:postcode":"91502",
    "sg:province":"CA",
    "sg:tags":[
        "hair",
        "eyelash"
    ],
    "sg:website":"michellebouse.com/",
    "wof:name":"Michelle Bouse Beauty Boutique",
    "wof:placetype":"venue"
},
  "geometry": {"coordinates":[-118.344601,34.151757],"type":"Point"}
}