{
  "type": "Feature",
  "properties": {
    "addr:full":"110 W Channel Islands Blvd Oxnard CA 93033",
    "addr:housenumber":"110",
    "addr:postcode":"93033",
    "addr:street":"W Channel Islands Blvd",
    "iso:country":"US",
    "sg:address":"110 W Channel Islands Blvd",
    "sg:city":"Oxnard",
    "sg:classifiers":[
        {
            "category":"Personal",
            "subcategory":"Nail Salon",
            "type":"Services"
        }
    ],
    "sg:phone":"+1 805 486 9407",
    "sg:postcode":"93033",
    "sg:province":"CA",
    "wof:name":"Starlite Nails",
    "wof:placetype":"venue"
},
  "geometry": {"coordinates":[-119.17819,34.17345],"type":"Point"}
}