{
  "type": "Feature",
  "properties": {
    "addr:full":"6398 E Cam Grande Anaheim CA 92807",
    "addr:housenumber":"6398",
    "addr:postcode":"92807",
    "addr:street":"E Cam Grande",
    "iso:country":"US",
    "sg:address":"6398 E Cam Grande",
    "sg:city":"Anaheim",
    "sg:classifiers":[
        {
            "category":"Real Estate",
            "subcategory":"Real Estate Agent",
            "type":"Services"
        }
    ],
    "sg:phone":"+1 714 282 8036",
    "sg:postcode":"92807",
    "sg:province":"CA",
    "sg:tags":[
        "appraiser"
    ],
    "wof:name":"Appraisal Department",
    "wof:placetype":"venue"
},
  "geometry": {"coordinates":[-117.7662,33.83498],"type":"Point"}
}