{
  "type": "Feature",
  "properties": {
    "iso:country":"US",
    "sg:address":"1830 N Cherokee Ave",
    "sg:city":"Los Angeles",
    "sg:classifiers":[
        {
            "category":"Real Estate",
            "subcategory":"Real Estate Operator",
            "type":"Services"
        }
    ],
    "sg:phone":"+1 323 957 2753",
    "sg:postcode":"90028",
    "sg:province":"CA",
    "sg:tags":[
        "apartment"
    ],
    "wof:name":"Commodore Apartments-Hollyoowd",
    "wof:placetype":"venue"
},
  "geometry": {"coordinates":[-118.334689,34.104579],"type":"Point"}
}