{
  "type": "Feature",
  "properties": {
    "iso:country":"US",
    "sg:address":"5820 N Figueroa St",
    "sg:city":"Los Angeles",
    "sg:classifiers":[
        {
            "category":"Health Services",
            "subcategory":"Chiropractor",
            "type":"Services"
        }
    ],
    "sg:phone":"+1 323 257 8211",
    "sg:postcode":"90042",
    "sg:province":"CA",
    "wof:name":"American Chiropractic Clinic",
    "wof:placetype":"venue"
},
  "geometry": {"coordinates":[-118.191078,34.110339],"type":"Point"}
}