{
  "type": "Feature",
  "properties": {
    "iso:country":"US",
    "sg:address":"9 Rancho Diablo Rd",
    "sg:city":"Lafayette",
    "sg:classifiers":[
        {
            "category":"Education",
            "subcategory":"Special Training",
            "type":"Public Place"
        }
    ],
    "sg:phone":"+1 925 283 9944",
    "sg:postcode":"94549",
    "sg:province":"CA",
    "sg:tags":[
        "tutoring"
    ],
    "wof:name":"Chinn Workshops & Sat Prep",
    "wof:placetype":"venue"
},
  "geometry": {"coordinates":[-122.155579,37.904369],"type":"Point"}
}