{
  "type": "Feature",
  "properties": {
    "addr:full":"2723 W Vernon Ave Los Angeles CA 90008",
    "addr:housenumber":"2723",
    "addr:postcode":"90008",
    "addr:street":"W Vernon Ave",
    "iso:country":"US",
    "sg:address":"2723 W Vernon Ave",
    "sg:city":"Los Angeles",
    "sg:classifiers":[
        {
            "category":"Food & Beverages",
            "subcategory":"Groceries & Convenience Stores",
            "type":"Retail Goods"
        }
    ],
    "sg:phone":"+1 323 508 2434",
    "sg:postcode":"90008",
    "sg:province":"CA",
    "wof:name":"Nkems Market II",
    "wof:placetype":"venue"
},
  "geometry": {"coordinates":[-118.322998,34.003601],"type":"Point"}
}