{
  "type": "Feature",
  "properties": {
    "addr:full":"1693 Garden Rd Durham CA 95938",
    "addr:housenumber":"1693",
    "addr:postcode":"95938",
    "addr:street":"Garden Rd",
    "iso:country":"US",
    "sg:address":"1693 Garden Rd",
    "sg:city":"Durham",
    "sg:classifiers":[
        {
            "category":"Farming",
            "subcategory":"Crops",
            "type":"Manufacturing & Wholesale Goods"
        }
    ],
    "sg:phone":"+1 530 343 7165",
    "sg:postcode":"95938",
    "sg:province":"CA",
    "sg:tags":[
        "grove",
        "nut",
        "tree",
        "nuts-edible"
    ],
    "wof:name":"Lowell Stringfellow",
    "wof:placetype":"venue"
},
  "geometry": {"coordinates":[-121.769046,39.664283],"type":"Point"}
}