{
  "type": "Feature",
  "properties": {
    "iso:country":"US",
    "sg:address":"13252 Garden Grove Blvd",
    "sg:city":"Garden Grove",
    "sg:classifiers":[
        {
            "category":"Professional",
            "subcategory":"Management & Consulting",
            "type":"Services"
        }
    ],
    "sg:phone":"+1 714 750 0721",
    "sg:postcode":"92843",
    "sg:province":"CA",
    "sg:tags":[
        "consultant",
        "business"
    ],
    "wof:name":"Estate Planning Svc",
    "wof:placetype":"venue"
},
  "geometry": {"coordinates":[-117.903032,33.774445],"type":"Point"}
}