{
  "type": "Feature",
  "properties": {
    "iso:country":"US",
    "sg:address":"80 E Sir Francis Drake Blvd",
    "sg:city":"Larkspur",
    "sg:classifiers":[
        {
            "category":"Banks & Credit Unions",
            "subcategory":"Investment Brokerage",
            "type":"Services"
        },
        {
            "category":"Banks & Credit Unions",
            "subcategory":"Financial Services",
            "type":"Services"
        }
    ],
    "sg:phone":"+1 415 925 2340",
    "sg:postcode":"94939",
    "sg:province":"CA",
    "sg:tags":[
        "advisory",
        "management",
        "planner"
    ],
    "wof:name":"Trais Fluors Investments Service",
    "wof:placetype":"venue"
},
  "geometry": {"coordinates":[-122.512333,37.945321],"type":"Point"}
}