{
  "type": "Feature",
  "properties": {
    "addr:full":"2482 Erringer Rd Simi Valley CA 93065",
    "addr:postcode":"2482;93065",
    "addr:street":"Erringer Rd",
    "iso:country":"US",
    "sg:address":"2482 Erringer Rd",
    "sg:city":"Simi Valley",
    "sg:classifiers":[
        {
            "category":"Professional",
            "type":"Services"
        }
    ],
    "sg:phone":"+1 805 306 1136",
    "sg:postcode":"93065",
    "sg:province":"CA",
    "wof:name":"Ship Me Quick",
    "wof:placetype":"venue"
},
  "geometry": {"coordinates":[-118.761287,34.280289],"type":"Point"}
}