{
  "type": "Feature",
  "properties": {
    "addr:full":"800 S Rochester Ave Ontario CA 91761",
    "addr:housenumber":"800",
    "addr:postcode":"91761",
    "addr:street":"S Rochester Ave",
    "iso:country":"US",
    "sg:address":"800 S Rochester Ave",
    "sg:city":"Ontario",
    "sg:classifiers":[
        {
            "category":"Manufacturing",
            "subcategory":"Printing",
            "type":"Manufacturing & Wholesale Goods"
        }
    ],
    "sg:phone":"+1 909 597 1269",
    "sg:postcode":"91761",
    "sg:province":"CA",
    "sg:tags":[
        "publisher",
        "commercial",
        "periodical"
    ],
    "wof:name":"West Coast Media",
    "wof:placetype":"venue"
},
  "geometry": {"coordinates":[-117.54757600000001,34.055322],"type":"Point"}
}