{
  "type": "Feature",
  "properties": {
    "iso:country":"US",
    "sg:address":"800 S Rochester Ave",
    "sg:city":"Ontario",
    "sg:classifiers":[
        {
            "category":"Manufacturing",
            "subcategory":"Printing",
            "type":"Manufacturing & Wholesale Goods"
        }
    ],
    "sg:phone":"+1 909 597 1269",
    "sg:postcode":"91761",
    "sg:province":"CA",
    "sg:tags":[
        "publisher",
        "commercial",
        "periodical"
    ],
    "wof:name":"West Coast Media",
    "wof:placetype":"venue"
},
  "geometry": {"coordinates":[-117.547576,34.055322],"type":"Point"}
}