{
  "type": "Feature",
  "properties": {
    "addr:full":"320 N Glendale Ave Glendale CA 91206",
    "addr:housenumber":"320",
    "addr:postcode":"91206",
    "addr:street":"N Glendale Ave",
    "iso:country":"US",
    "sg:address":"320 N Glendale Ave",
    "sg:city":"Glendale",
    "sg:classifiers":[
        {
            "category":"Shopping",
            "type":"Retail Goods"
        }
    ],
    "sg:phone":"+1 818 243 7661",
    "sg:postcode":"91206",
    "sg:province":"CA",
    "sg:tags":[
        "picture",
        "frame",
        "art",
        "supply"
    ],
    "sg:website":"www.aaronbrothers.com",
    "wof:name":"Aaron Brothers",
    "wof:placetype":"venue"
},
  "geometry": {"coordinates":[-118.245003,34.151001],"type":"Point"}
}