{
  "type": "Feature",
  "properties": {
    "iso:country":"US",
    "sg:address":"4704 E Home Ave",
    "sg:city":"Fresno",
    "sg:classifiers":[
        {
            "category":"Wholesale",
            "subcategory":"Electrical",
            "type":"Manufacturing & Wholesale Goods"
        }
    ],
    "sg:phone":"+1 559 251 6683",
    "sg:postcode":"93703",
    "sg:province":"CA",
    "sg:tags":[
        "generator"
    ],
    "wof:name":"W W Generators",
    "wof:placetype":"venue"
},
  "geometry": {"coordinates":[-119.73805400000001,36.763669],"type":"Point"}
}