{
  "type": "Feature",
  "properties": {
    "addr:full":"18002 Irvine Blvd Tustin CA 92780",
    "addr:housenumber":"18002",
    "addr:postcode":"92780",
    "addr:street":"Irvine Blvd",
    "iso:country":"US",
    "sg:address":"18002 Irvine Blvd",
    "sg:city":"Tustin",
    "sg:classifiers":[
        {
            "category":"Building & Trades",
            "subcategory":"Construction",
            "type":"Services"
        }
    ],
    "sg:phone":"+1 714 669 4559",
    "sg:postcode":"92780",
    "sg:province":"CA",
    "sg:tags":[
        "interior",
        "design"
    ],
    "wof:name":"Commercial & Residential Design Services-C R D S",
    "wof:placetype":"venue"
},
  "geometry": {"coordinates":[-117.819,33.748199],"type":"Point"}
}