{
  "type": "Feature",
  "properties": {
    "addr:full":"12252 Bangor St Garden Grove CA 92840",
    "addr:housenumber":"12252",
    "addr:postcode":"92840",
    "addr:street":"Bangor St",
    "iso:country":"US",
    "sg:address":"12252 Bangor St",
    "sg:city":"Garden Grove",
    "sg:classifiers":[
        {
            "category":"Professional",
            "type":"Services"
        }
    ],
    "sg:phone":"+1 714 750 0594",
    "sg:postcode":"92840",
    "sg:province":"CA",
    "wof:name":"Mexihammocks",
    "wof:placetype":"venue"
},
  "geometry": {"coordinates":[-117.912272,33.785139],"type":"Point"}
}