{
  "type": "Feature",
  "properties": {
    "iso:country":"US",
    "sg:address":"1574 Cll Enrique",
    "sg:city":"Pleasanton",
    "sg:classifiers":[
        {
            "category":"Professional",
            "type":"Services"
        }
    ],
    "sg:phone":"+1 925 462 7703",
    "sg:postcode":"94566",
    "sg:province":"CA",
    "wof:name":"Steel Show",
    "wof:placetype":"venue"
},
  "geometry": {"coordinates":[-121.88681099999999,37.667839],"type":"Point"}
}