{
  "type": "Feature",
  "properties": {
    "addr:full":"225 Linwood Ave Unit F Monrovia CA 91016",
    "addr:housenumber":"225",
    "addr:postcode":"91016",
    "addr:street":"Linwood Ave Unit F",
    "iso:country":"US",
    "sg:address":"225 Linwood Ave Unit F",
    "sg:city":"Monrovia",
    "sg:classifiers":[
        {
            "category":"Wholesale",
            "subcategory":"Vending Machines",
            "type":"Manufacturing & Wholesale Goods"
        }
    ],
    "sg:phone":"+1 626 303 3400",
    "sg:postcode":"91016",
    "sg:province":"CA",
    "sg:tags":[
        "merchandise"
    ],
    "wof:name":"Sierra Vending",
    "wof:placetype":"venue"
},
  "geometry": {"coordinates":[-118.003699,34.150131],"type":"Point"}
}