{
  "type": "Feature",
  "properties": {
    "addr:full":"4420 Hotel Circle Ct San Diego CA 92108",
    "addr:housenumber":"4420",
    "addr:postcode":"92108",
    "addr:street":"Hotel Circle Ct",
    "iso:country":"US",
    "sg:address":"4420 Hotel Circle Ct",
    "sg:city":"San Diego",
    "sg:classifiers":[
        {
            "category":"Health Services",
            "subcategory":"Health Practitioner",
            "type":"Services"
        }
    ],
    "sg:phone":"+1 619 298 4116",
    "sg:postcode":"92108",
    "sg:province":"CA",
    "sg:tags":[
        "therapist",
        "physical"
    ],
    "wof:name":"Ola Grimsby Institute",
    "wof:placetype":"venue"
},
  "geometry": {"coordinates":[-117.17209200000001,32.760501],"type":"Point"}
}