{
  "type": "Feature",
  "properties": {
    "iso:country":"US",
    "sg:address":"1626 Centinela Ave",
    "sg:city":"Inglewood",
    "sg:classifiers":[
        {
            "category":"Shopping",
            "subcategory":"Computers & Home Electronics",
            "type":"Retail Goods"
        }
    ],
    "sg:phone":"+1 310 410 9624",
    "sg:postcode":"90302",
    "sg:province":"CA",
    "sg:tags":[
        "parts",
        "supply"
    ],
    "wof:name":"Computer Specialties Tech",
    "wof:placetype":"venue"
},
  "geometry": {"coordinates":[-118.368153,33.977205],"type":"Point"}
}