{
  "type": "Feature",
  "properties": {
    "iso:country":"US",
    "sg:address":"4901 W Rosecrans Ave",
    "sg:city":"Hawthorne",
    "sg:classifiers":[
        {
            "category":"Building & Trades",
            "subcategory":"Cleaning & Sanitation",
            "type":"Services"
        }
    ],
    "sg:phone":"+1 323 772 0293",
    "sg:postcode":"90250",
    "sg:province":"CA",
    "sg:tags":[
        "janitor"
    ],
    "wof:name":"Hygenic Restroom Svc",
    "wof:placetype":"venue"
},
  "geometry": {"coordinates":[-118.367057,33.901733],"type":"Point"}
}