{
  "type": "Feature",
  "properties": {
    "addr:full":"212 Ford Ave Pomona CA 91768",
    "addr:housenumber":"212",
    "addr:postcode":"91768",
    "addr:street":"Ford Ave",
    "iso:country":"US",
    "sg:address":"212 Ford Ave",
    "sg:city":"Pomona",
    "sg:classifiers":[
        {
            "category":"Building & Trades",
            "subcategory":"Landscaping Services",
            "type":"Services"
        }
    ],
    "sg:phone":"+1 909 709 6369",
    "sg:postcode":"91768",
    "sg:province":"CA",
    "wof:name":"Rithas Lawn Grooming & Svcs",
    "wof:placetype":"venue"
},
  "geometry": {"coordinates":[-117.75524799999999,34.084835],"type":"Point"}
}