{
  "type": "Feature",
  "properties": {
    "iso:country":"US",
    "sg:address":"12582 Garden Grove Blvd",
    "sg:city":"Garden Grove",
    "sg:classifiers":[
        {
            "category":"Health Services",
            "subcategory":"Doctor",
            "type":"Services"
        }
    ],
    "sg:phone":"+1 714 534 0744",
    "sg:postcode":"92843",
    "sg:province":"CA",
    "wof:name":"Choi Junghwan MD",
    "wof:placetype":"venue"
},
  "geometry": {"coordinates":[-117.913212,33.774201],"type":"Point"}
}