{
  "type": "Feature",
  "properties": {
    "addr:full":"2706 Lassen Dr Bakersfield CA 93312",
    "addr:housenumber":"2706",
    "addr:postcode":"93312",
    "addr:street":"Lassen Dr",
    "iso:country":"US",
    "sg:address":"2706 Lassen Dr",
    "sg:city":"Bakersfield",
    "sg:classifiers":[
        {
            "category":"Building & Trades",
            "subcategory":"Construction",
            "type":"Services"
        }
    ],
    "sg:phone":"+1 661 589 3599",
    "sg:postcode":"93312",
    "sg:province":"CA",
    "sg:tags":[
        "plastering",
        "contractor"
    ],
    "wof:name":"Javier Sanchez Lath & Plaster",
    "wof:placetype":"venue"
},
  "geometry": {"coordinates":[-119.138803,35.383794],"type":"Point"}
}