{
  "type": "Feature",
  "properties": {
    "iso:country":"US",
    "sg:address":"15315 Turner Rd",
    "sg:city":"Victorville",
    "sg:classifiers":[
        {
            "category":"Wholesale",
            "subcategory":"Construction Materials",
            "type":"Manufacturing & Wholesale Goods"
        }
    ],
    "sg:phone":"+1 760 246 8333",
    "sg:postcode":"92394",
    "sg:province":"CA",
    "sg:tags":[
        "rock"
    ],
    "wof:name":"V & L Trucking",
    "wof:placetype":"venue"
},
  "geometry": {"coordinates":[-117.323808,34.571845],"type":"Point"}
}