{
  "type": "Feature",
  "properties": {
    "addr:full":"9 Commercial Blvd Novato CA 94949",
    "addr:housenumber":"9",
    "addr:postcode":"94949",
    "addr:street":"Commercial Blvd",
    "iso:country":"US",
    "sg:address":"9 Commercial Blvd",
    "sg:city":"Novato",
    "sg:classifiers":[
        {
            "category":"Banks & Credit Unions",
            "subcategory":"Bank",
            "type":"Services"
        }
    ],
    "sg:phone":"+1 415 884 4580",
    "sg:postcode":"94949",
    "sg:province":"CA",
    "sg:tags":[
        "state",
        "commercial"
    ],
    "wof:name":"Bank of Marin",
    "wof:placetype":"venue"
},
  "geometry": {"coordinates":[-122.532792,38.068639],"type":"Point"}
}