{
  "type": "Feature",
  "properties": {
    "addr:full":"962 Happy Valley Rd Pleasanton CA 94566",
    "addr:housenumber":"962",
    "addr:postcode":"94566",
    "addr:street":"Happy Valley Rd",
    "iso:country":"US",
    "sg:address":"962 Happy Valley Rd",
    "sg:city":"Pleasanton",
    "sg:classifiers":[
        {
            "category":"Farming",
            "subcategory":"Farm & Veterinary Services",
            "type":"Manufacturing & Wholesale Goods"
        }
    ],
    "sg:phone":"+1 925 600 0997",
    "sg:postcode":"94566",
    "sg:province":"CA",
    "sg:tags":[
        "control",
        "weed"
    ],
    "wof:name":"IMHOF Tractor Svc",
    "wof:placetype":"venue"
},
  "geometry": {"coordinates":[-121.872286,37.633118],"type":"Point"}
}