{
  "type": "Feature",
  "properties": {
    "addr:full":"50 Post Street San Francisco CA 94104",
    "addr:housenumber":"50",
    "addr:postcode":"94104",
    "addr:street":"Post Street",
    "iso:country":"US",
    "sg:address":"50 Post Street",
    "sg:city":"San Francisco",
    "sg:classifiers":[
        {
            "category":"Food & Beverages",
            "subcategory":"Candy",
            "type":"Retail Goods"
        }
    ],
    "sg:phone":"+1 415 398 4847",
    "sg:postcode":"94104",
    "sg:province":"CA",
    "sg:tags":[
        "store"
    ],
    "wof:name":"The Galleria Newsstand",
    "wof:placetype":"venue"
},
  "geometry": {"coordinates":[-122.40300000000001,37.789101],"type":"Point"}
}