{
  "type": "Feature",
  "properties": {
    "addr:full":"7550 Laurel Canyon Blvd North Hollywood CA 91605",
    "addr:housenumber":"7550",
    "addr:postcode":"91605",
    "addr:street":"Laurel Canyon Blvd",
    "iso:country":"US",
    "sg:address":"7550 Laurel Canyon Blvd",
    "sg:city":"North Hollywood",
    "sg:classifiers":[
        {
            "category":"Restaurant",
            "type":"Food & Drink"
        }
    ],
    "sg:phone":"+1 818 982 3352",
    "sg:postcode":"91605",
    "sg:province":"CA",
    "sg:tags":[
        "mexican"
    ],
    "wof:name":"Leo's Mexican Food",
    "wof:placetype":"venue"
},
  "geometry": {"coordinates":[-118.396004,34.207401],"type":"Point"}
}