{
  "type": "Feature",
  "properties": {
    "iso:country":"US",
    "sg:address":"2550 Mariposa St",
    "sg:city":"Fresno",
    "sg:classifiers":[
        {
            "category":"Government",
            "subcategory":"Office",
            "type":"Public Place"
        }
    ],
    "sg:phone":"+1 559 445 5084",
    "sg:postcode":"93721",
    "sg:province":"CA",
    "sg:tags":[
        "governmental"
    ],
    "wof:name":"Building & Property Management",
    "wof:placetype":"venue"
},
  "geometry": {"coordinates":[-119.785393,36.738747],"type":"Point"}
}