{
  "type": "Feature",
  "properties": {
    "iso:country":"US",
    "sg:address":"725 Gotham Dr",
    "sg:city":"Stockton",
    "sg:classifiers":[
        {
            "category":"Freight",
            "type":"Transportation"
        }
    ],
    "sg:phone":"+1 209 477 8440",
    "sg:postcode":"95210",
    "sg:province":"CA",
    "sg:tags":[
        "operator",
        "local",
        "trucking"
    ],
    "wof:name":"Cisneras Trucking",
    "wof:placetype":"venue"
},
  "geometry": {"coordinates":[-121.302869,38.026512],"type":"Point"}
}