{
  "type": "Feature",
  "properties": {
    "addr:full":"3445 Fifth Ave San Diego CA 92103",
    "addr:housenumber":"3445",
    "addr:postcode":"92103",
    "addr:street":"Fifth Ave",
    "iso:country":"US",
    "sg:address":"3445 Fifth Ave",
    "sg:city":"San Diego",
    "sg:classifiers":[
        {
            "category":"Personal",
            "subcategory":"Beauty Salon",
            "type":"Services"
        },
        {
            "category":"Personal",
            "subcategory":"Skin Care",
            "type":"Services"
        }
    ],
    "sg:phone":"+1 619 322 8006",
    "sg:postcode":"92103",
    "sg:province":"CA",
    "sg:tags":[
        "hair"
    ],
    "wof:name":"Salon Starr Darling of Mayte Hatoum studios",
    "wof:placetype":"venue"
},
  "geometry": {"coordinates":[-117.16024,32.7416],"type":"Point"}
}