{
  "type": "Feature",
  "properties": {
    "iso:country":"US",
    "sg:address":"4444 42nd St",
    "sg:city":"San Diego",
    "sg:classifiers":[
        {
            "category":"Professional",
            "type":"Services"
        }
    ],
    "sg:phone":"+1 858 455 6549",
    "sg:postcode":"92116",
    "sg:province":"CA",
    "wof:name":"Sara Poldmae Hhp",
    "wof:placetype":"venue"
},
  "geometry": {"coordinates":[-117.105082,32.758057],"type":"Point"}
}