{
  "type": "Feature",
  "properties": {
    "addr:full":"3673 Justine Dr San Jose CA 95124",
    "addr:housenumber":"3673",
    "addr:postcode":"95124",
    "addr:street":"Justine Dr",
    "iso:country":"US",
    "sg:address":"3673 Justine Dr",
    "sg:city":"San Jose",
    "sg:classifiers":[
        {
            "category":"Manufacturing",
            "subcategory":"Printing",
            "type":"Manufacturing & Wholesale Goods"
        }
    ],
    "sg:phone":"+1 408 267 7344",
    "sg:postcode":"95124",
    "sg:province":"CA",
    "sg:tags":[
        "publishing"
    ],
    "wof:name":"M N Media",
    "wof:placetype":"venue"
},
  "geometry": {"coordinates":[-121.914175,37.261476],"type":"Point"}
}