{
  "type": "Feature",
  "properties": {
    "addr:full":"940 W Highland Ave San Bernardino CA 92405",
    "addr:housenumber":"940",
    "addr:postcode":"92405",
    "addr:street":"W Highland Ave",
    "iso:country":"US",
    "sg:address":"940 W Highland Ave",
    "sg:city":"San Bernardino",
    "sg:classifiers":[
        {
            "category":"Restaurant",
            "type":"Food & Drink"
        }
    ],
    "sg:phone":"+1 909 881 1992",
    "sg:postcode":"92405",
    "sg:province":"CA",
    "wof:name":"Michael's Burgers",
    "wof:placetype":"venue"
},
  "geometry": {"coordinates":[-117.304558,34.136124],"type":"Point"}
}