{
  "type": "Feature",
  "properties": {
    "addr:full":"516 E Williams St Barstow CA 92311",
    "addr:housenumber":"516",
    "addr:postcode":"92311",
    "addr:street":"E Williams St",
    "iso:country":"US",
    "sg:address":"516 E Williams St",
    "sg:city":"Barstow",
    "sg:classifiers":[
        {
            "category":"Organizations",
            "subcategory":"Non-profit Organization",
            "type":"Services"
        }
    ],
    "sg:phone":"+1 760 256 9328",
    "sg:postcode":"92311",
    "sg:province":"CA",
    "sg:tags":[
        "action",
        "agency",
        "community"
    ],
    "wof:name":"American Red Cross Barstow Svc",
    "wof:placetype":"venue"
},
  "geometry": {"coordinates":[-117.02270300000001,34.897551],"type":"Point"}
}