{
  "type": "Feature",
  "properties": {
    "addr:full":"7547 Watt Ave North Highlands CA 95660",
    "addr:housenumber":"7547",
    "addr:postcode":"95660",
    "addr:street":"Watt Ave",
    "iso:country":"US",
    "sg:address":"7547 Watt Ave",
    "sg:city":"North Highlands",
    "sg:classifiers":[
        {
            "category":"Food & Beverages",
            "subcategory":"Groceries & Convenience Stores",
            "type":"Retail Goods"
        }
    ],
    "sg:phone":"+1 916 334 0111",
    "sg:postcode":"95660",
    "sg:province":"CA",
    "wof:name":"S R Food Store",
    "wof:placetype":"venue"
},
  "geometry": {"coordinates":[-121.382879,38.703605],"type":"Point"}
}