{
  "type": "Feature",
  "properties": {
    "iso:country":"US",
    "sg:address":"1139 W Santa Ana Blvd",
    "sg:city":"Santa Ana",
    "sg:classifiers":[
        {
            "category":"Food & Beverages",
            "subcategory":"Groceries & Convenience Stores",
            "type":"Retail Goods"
        }
    ],
    "sg:phone":"+1 714 835 2231",
    "sg:postcode":"92703",
    "sg:province":"CA",
    "wof:name":"Wm Market",
    "wof:placetype":"venue"
},
  "geometry": {"coordinates":[-117.88200399999999,33.747898],"type":"Point"}
}