{
  "type": "Feature",
  "properties": {
    "addr:full":"814 N Kenilworth Ave Glendale CA 91203",
    "addr:housenumber":"814",
    "addr:postcode":"91203",
    "addr:street":"N Kenilworth Ave",
    "iso:country":"US",
    "sg:address":"814 N Kenilworth Ave",
    "sg:city":"Glendale",
    "sg:classifiers":[
        {
            "category":"Shopping",
            "type":"Retail Goods"
        }
    ],
    "sg:phone":"+1 818 243 5240",
    "sg:postcode":"91203",
    "sg:province":"CA",
    "sg:tags":[
        "trophy",
        "medal",
        "award"
    ],
    "wof:name":"A & A Golden W Trophy Award Co",
    "wof:placetype":"venue"
},
  "geometry": {"coordinates":[-118.26682599999999,34.158223],"type":"Point"}
}