{
  "type": "Feature",
  "properties": {
    "iso:country":"US",
    "sg:address":"22115 Martinez St",
    "sg:city":"Woodland Hills",
    "sg:classifiers":[
        {
            "category":"Professional",
            "subcategory":"Art Services",
            "type":"Services"
        }
    ],
    "sg:phone":"+1 917 573 7357",
    "sg:postcode":"91364",
    "sg:province":"CA",
    "sg:tags":[
        "photographer"
    ],
    "sg:website":"www.farrellconlan.com",
    "wof:name":"Farrell Conlan",
    "wof:placetype":"venue"
},
  "geometry": {"coordinates":[-118.609414,34.163097],"type":"Point"}
}