{
  "type": "Feature",
  "properties": {
    "iso:country":"US",
    "sg:address":"1655 W Kavanagh Ave",
    "sg:city":"Tracy",
    "sg:classifiers":[
        {
            "category":"Manufacturing",
            "subcategory":"Jewelry",
            "type":"Manufacturing & Wholesale Goods"
        }
    ],
    "sg:phone":"+1 209 835 9291",
    "sg:postcode":"95376",
    "sg:province":"CA",
    "sg:tags":[
        "precious",
        "metal",
        "mfg"
    ],
    "wof:name":"Born To Bead",
    "wof:placetype":"venue"
},
  "geometry": {"coordinates":[-121.445573,37.757769],"type":"Point"}
}