{
  "type": "Feature",
  "properties": {
    "iso:country":"US",
    "sg:address":"22555 Nadine Cir",
    "sg:city":"Torrance",
    "sg:classifiers":[
        {
            "category":"Professional",
            "subcategory":"Management & Consulting",
            "type":"Services"
        }
    ],
    "sg:phone":"+1 310 325 8827",
    "sg:postcode":"90505",
    "sg:province":"CA",
    "sg:tags":[
        "consultant",
        "business"
    ],
    "wof:name":"Ikezawa Food Specialist Inc",
    "wof:placetype":"venue"
},
  "geometry": {"coordinates":[-118.341059,33.822453],"type":"Point"}
}