{
  "type": "Feature",
  "properties": {
    "iso:country":"US",
    "sg:address":"711 4th St",
    "sg:city":"Coronado",
    "sg:classifiers":[
        {
            "category":"Food & Beverages",
            "subcategory":"Groceries & Convenience Stores",
            "type":"Retail Goods"
        }
    ],
    "sg:phone":"+1 619 435 2219",
    "sg:postcode":"92118",
    "sg:province":"CA",
    "sg:tags":[
        "grocer"
    ],
    "wof:name":"New Island Market",
    "wof:placetype":"venue"
},
  "geometry": {"coordinates":[-117.179166,32.69638],"type":"Point"}
}