{
  "type": "Feature",
  "properties": {
    "addr:full":"2151 Las Posas Rd Camarillo CA 93010",
    "addr:housenumber":"2151",
    "addr:postcode":"93010",
    "addr:street":"Las Posas Rd",
    "iso:country":"US",
    "sg:address":"2151 Las Posas Rd",
    "sg:city":"Camarillo",
    "sg:phone":"+1 805 389 5488",
    "sg:postcode":"93010",
    "sg:province":"CA",
    "wof:name":"Camarillo Auto Repair",
    "wof:placetype":"venue"
},
  "geometry": {"coordinates":[-119.041515,34.235997],"type":"Point"}
}