{
  "type": "Feature",
  "properties": {
    "addr:full":"3451 Santa Ana St Huntington Park CA 90255",
    "addr:housenumber":"3451",
    "addr:postcode":"90255",
    "addr:street":"Santa Ana St;Park",
    "iso:country":"US",
    "sg:address":"3451 Santa Ana St",
    "sg:city":"Huntington Park",
    "sg:classifiers":[
        {
            "category":"Social Services",
            "subcategory":"Adult Care",
            "type":"Services"
        }
    ],
    "sg:phone":"+1 323 587 8726",
    "sg:postcode":"90255",
    "sg:province":"CA",
    "sg:tags":[
        "home",
        "residential"
    ],
    "wof:name":"Lisa Marie Rest Home",
    "wof:placetype":"venue"
},
  "geometry": {"coordinates":[-118.20552000000001,33.963038],"type":"Point"}
}