{
  "type": "Feature",
  "properties": {
    "addr:full":"3525 Loma Vista Rd Ventura CA 93003",
    "addr:housenumber":"3525",
    "addr:postcode":"93003",
    "addr:street":"Loma Vista Rd",
    "iso:country":"US",
    "sg:address":"3525 Loma Vista Rd",
    "sg:city":"Ventura",
    "sg:classifiers":[
        {
            "category":"Health Services",
            "subcategory":"Doctor",
            "type":"Services"
        }
    ],
    "sg:phone":"+1 805 641 6415",
    "sg:postcode":"93003",
    "sg:province":"CA",
    "sg:tags":[
        "physician",
        "surgeon",
        "orthopedics",
        "surgeons"
    ],
    "sg:website":"http://www.venturaorthopedic.com",
    "wof:name":"Ventura Orthopedics",
    "wof:placetype":"venue"
},
  "geometry": {"coordinates":[-119.248245,34.276756],"type":"Point"}
}