{
  "type": "Feature",
  "properties": {
    "iso:country":"US",
    "sg:address":"23 S Hope Ave",
    "sg:city":"Santa Barbara",
    "sg:classifiers":[
        {
            "category":"Insurance",
            "subcategory":"Insurance Agent",
            "type":"Services"
        }
    ],
    "sg:phone":"+1 805 682 4998",
    "sg:postcode":"93105",
    "sg:province":"CA",
    "wof:name":"Marsh Private Client Svc",
    "wof:placetype":"venue"
},
  "geometry": {"coordinates":[-119.746638,34.438423],"type":"Point"}
}