{
  "type": "Feature",
  "properties": {
    "addr:full":"6740 Compton Ave Los Angeles CA 90001",
    "addr:housenumber":"6740",
    "addr:postcode":"90001",
    "addr:street":"Compton Ave",
    "iso:country":"US",
    "sg:address":"6740 Compton Ave",
    "sg:city":"Los Angeles",
    "sg:classifiers":[
        {
            "category":"Food & Beverages",
            "subcategory":"Groceries & Convenience Stores",
            "type":"Retail Goods"
        }
    ],
    "sg:phone":"+1 323 588 4964",
    "sg:postcode":"90001",
    "sg:province":"CA",
    "sg:tags":[
        "grocer"
    ],
    "wof:name":"La Fuente De Oro",
    "wof:placetype":"venue"
},
  "geometry": {"coordinates":[-118.248001,33.9785],"type":"Point"}
}