{
  "type": "Feature",
  "properties": {
    "addr:full":"55 Mountain View Pl San Mateo CA 94402",
    "addr:housenumber":"55",
    "addr:postcode":"94402",
    "addr:street":"Mountain View Pl",
    "iso:country":"US",
    "sg:address":"55 Mountain View Pl",
    "sg:city":"San Mateo",
    "sg:classifiers":[
        {
            "category":"Manufacturing",
            "subcategory":"Tools & Machinery",
            "type":"Manufacturing & Wholesale Goods"
        }
    ],
    "sg:phone":"+1 650 572 8450",
    "sg:postcode":"94402",
    "sg:province":"CA",
    "sg:tags":[
        "electrical",
        "mfg"
    ],
    "wof:name":"Applied Science & Technology",
    "wof:placetype":"venue"
},
  "geometry": {"coordinates":[-122.337631,37.52361],"type":"Point"}
}