{
  "type": "Feature",
  "properties": {
    "iso:country":"US",
    "sg:address":"165 N Luring Dr",
    "sg:city":"Palm Springs",
    "sg:classifiers":[
        {
            "category":"Real Estate",
            "subcategory":"Architect",
            "type":"Services"
        }
    ],
    "sg:phone":"+1 760 327 6800",
    "sg:postcode":"92262",
    "sg:province":"CA",
    "sg:website":"www.urrutiaarchitects.com",
    "wof:name":"Urrutia Architects",
    "wof:placetype":"venue"
},
  "geometry": {"coordinates":[-116.52719500000001,33.824182],"type":"Point"}
}