{
  "type": "Feature",
  "properties": {
    "iso:country":"US",
    "sg:address":"1470 Canal St",
    "sg:city":"Auburn",
    "sg:classifiers":[
        {
            "category":"Shopping",
            "subcategory":"Used Merchandise",
            "type":"Retail Goods"
        }
    ],
    "sg:phone":"+1 530 885 3113",
    "sg:postcode":"95603",
    "sg:province":"CA",
    "wof:name":"Sampler Antiques",
    "wof:placetype":"venue"
},
  "geometry": {"coordinates":[-121.084215,38.926917],"type":"Point"}
}