{
  "type": "Feature",
  "properties": {
    "addr:full":"6925 Aragon Cir Ste 24 Buena Park CA 90620",
    "addr:housenumber":"6925",
    "addr:postcode":"90620",
    "addr:street":"Aragon Cir Ste 24",
    "iso:country":"US",
    "sg:address":"6925 Aragon Cir Ste 24",
    "sg:city":"Buena Park",
    "sg:classifiers":[
        {
            "category":"Shopping",
            "subcategory":"Computers & Home Electronics",
            "type":"Retail Goods"
        }
    ],
    "sg:phone":"+1 562 531 0551",
    "sg:postcode":"90620",
    "sg:province":"CA",
    "wof:name":"Pacific Stero",
    "wof:placetype":"venue"
},
  "geometry": {"coordinates":[-118.021004,33.862099],"type":"Point"}
}