{
  "type": "Feature",
  "properties": {
    "iso:country":"US",
    "sg:address":"485 Corporate Dr",
    "sg:city":"Escondido",
    "sg:classifiers":[
        {
            "category":"Building & Trades",
            "subcategory":"Construction",
            "type":"Services"
        }
    ],
    "sg:phone":"+1 760 738 9798",
    "sg:postcode":"92029",
    "sg:province":"CA",
    "sg:tags":[
        "contractor",
        "general",
        "heating",
        "con",
        "air"
    ],
    "sg:website":"www.rjlincco.com",
    "wof:name":"Rj Lanthier Co Inc",
    "wof:placetype":"venue"
},
  "geometry": {"coordinates":[-117.128564,33.125072],"type":"Point"}
}