{
  "type": "Feature",
  "properties": {
    "addr:full":"18584 Main St Huntington Beach CA 92648",
    "addr:housenumber":"18584",
    "addr:postcode":"92648",
    "addr:street":"Main St",
    "iso:country":"US",
    "sg:address":"18584 Main St",
    "sg:city":"Huntington Beach",
    "sg:classifiers":[
        {
            "category":"Professional",
            "subcategory":"Engineering",
            "type":"Services"
        }
    ],
    "sg:phone":"+1 714 848 4899",
    "sg:postcode":"92648",
    "sg:province":"CA",
    "sg:tags":[
        "general",
        "contractor"
    ],
    "wof:name":"Collections Traders Co",
    "wof:placetype":"venue"
},
  "geometry": {"coordinates":[-117.989873,33.693434],"type":"Point"}
}