{
  "type": "Feature",
  "properties": {
    "addr:full":"1500 Orange Ave Coronado CA 92118",
    "addr:housenumber":"1500",
    "addr:postcode":"92118",
    "addr:street":"Orange Ave",
    "iso:country":"US",
    "sg:address":"1500 Orange Ave",
    "sg:city":"Coronado",
    "sg:classifiers":[
        {
            "category":"Shopping",
            "subcategory":"Jewelry",
            "type":"Retail Goods"
        }
    ],
    "sg:phone":"+1 619 437 4606",
    "sg:postcode":"92118",
    "sg:province":"CA",
    "sg:tags":[
        "jeweler"
    ],
    "wof:name":"Mythic Gold",
    "wof:placetype":"venue"
},
  "geometry": {"coordinates":[-117.178074,32.682188],"type":"Point"}
}