{
  "type": "Feature",
  "properties": {
    "iso:country":"US",
    "sg:address":"6222 Gage Ave",
    "sg:city":"Bell Gardens",
    "sg:classifiers":[
        {
            "category":"Personal",
            "subcategory":"Beauty Salon",
            "type":"Services"
        }
    ],
    "sg:phone":"+1 323 560 5572",
    "sg:postcode":"90201",
    "sg:province":"CA",
    "wof:name":"Beauty Salon El Buen Gusto",
    "wof:placetype":"venue"
},
  "geometry": {"coordinates":[-118.152057,33.974282],"type":"Point"}
}