{
  "type": "Feature",
  "properties": {
    "iso:country":"US",
    "sg:address":"100 Hamilton Ave",
    "sg:city":"Palo Alto",
    "sg:classifiers":[
        {
            "category":"Professional",
            "type":"Services"
        }
    ],
    "sg:phone":"+1 650 321 4635",
    "sg:postcode":"94301",
    "sg:province":"CA",
    "wof:name":"Jonathan Noble",
    "wof:placetype":"venue"
},
  "geometry": {"coordinates":[-122.16211,37.44328],"type":"Point"}
}