{
  "type": "Feature",
  "properties": {
    "iso:country":"US",
    "sg:address":"12908 S Normandie Ave",
    "sg:city":"Gardena",
    "sg:classifiers":[
        {
            "category":"Wholesale",
            "subcategory":"Machinery & Supplies",
            "type":"Manufacturing & Wholesale Goods"
        }
    ],
    "sg:phone":"+1 310 965 0486",
    "sg:postcode":"90249",
    "sg:province":"CA",
    "sg:tags":[
        "machine",
        "cutting",
        "paper",
        "drilling"
    ],
    "wof:name":"Foamco",
    "wof:placetype":"venue"
},
  "geometry": {"coordinates":[-118.30028799999999,33.915569],"type":"Point"}
}