{
  "type": "Feature",
  "properties": {
    "addr:full":"1269 N Davis Rd Salinas CA 93907",
    "addr:housenumber":"1269",
    "addr:postcode":"93907",
    "addr:street":"N Davis Rd",
    "iso:country":"US",
    "sg:address":"1269 N Davis Rd",
    "sg:city":"Salinas",
    "sg:classifiers":[
        {
            "category":"Shopping",
            "subcategory":"Beauty & Cosmetics",
            "type":"Retail Goods"
        }
    ],
    "sg:phone":"+1 831 771 9401",
    "sg:postcode":"93907",
    "sg:province":"CA",
    "sg:tags":[
        "supply"
    ],
    "wof:name":"Majestic Beauty Supplies",
    "wof:placetype":"venue"
},
  "geometry": {"coordinates":[-121.667,36.702202],"type":"Point"}
}