{
  "type": "Feature",
  "properties": {
    "addr:full":"4600 Adeline St Emeryville CA 94608",
    "addr:housenumber":"4600",
    "addr:postcode":"94608",
    "addr:street":"Adeline St",
    "iso:country":"US",
    "sg:address":"4600 Adeline St",
    "sg:city":"Emeryville",
    "sg:classifiers":[
        {
            "category":"Real Estate",
            "subcategory":"Real Estate Operator",
            "type":"Services"
        }
    ],
    "sg:phone":"+1 510 653 2385",
    "sg:postcode":"94608",
    "sg:province":"CA",
    "sg:tags":[
        "apartment"
    ],
    "sg:website":"www.bakerylofts.com",
    "wof:name":"Bakery Lofts",
    "wof:placetype":"venue"
},
  "geometry": {"coordinates":[-122.27663,37.835428],"type":"Point"}
}