{
  "type": "Feature",
  "properties": {
    "iso:country":"US",
    "sg:address":"9819 National Blvd",
    "sg:city":"Los Angeles",
    "sg:classifiers":[
        {
            "category":"Wholesale",
            "subcategory":"Durable Goods & Equipment",
            "type":"Manufacturing & Wholesale Goods"
        }
    ],
    "sg:phone":"+1 310 559 3526",
    "sg:postcode":"90034",
    "sg:province":"CA",
    "wof:name":"Vision Imports",
    "wof:placetype":"venue"
},
  "geometry": {"coordinates":[-118.400398,34.031465],"type":"Point"}
}