{
  "type": "Feature",
  "properties": {
    "iso:country":"US",
    "sg:address":"11600 Riverside Dr",
    "sg:city":"Mira Loma",
    "sg:classifiers":[
        {
            "category":"Freight",
            "type":"Transportation"
        }
    ],
    "sg:phone":"+1 951 727 0344",
    "sg:postcode":"91752",
    "sg:province":"CA",
    "sg:tags":[
        "trucking"
    ],
    "wof:name":"Swift Transportation Co",
    "wof:placetype":"venue"
},
  "geometry": {"coordinates":[-117.53456,34.017374],"type":"Point"}
}