{
  "type": "Feature",
  "properties": {
    "iso:country":"US",
    "sg:address":"1341 W 141st St",
    "sg:city":"Gardena",
    "sg:classifiers":[
        {
            "category":"Home & Garden",
            "subcategory":"Garden Supply",
            "type":"Retail Goods"
        }
    ],
    "sg:phone":"+1 310 323 8208",
    "sg:postcode":"90247",
    "sg:province":"CA",
    "sg:tags":[
        "nursery",
        "gardening"
    ],
    "wof:name":"Nakayama Lloyd T",
    "wof:placetype":"venue"
},
  "geometry": {"coordinates":[-118.2996,33.903917],"type":"Point"}
}