{
  "type": "Feature",
  "properties": {
    "iso:country":"US",
    "sg:address":"9360 Wilshire Blvd",
    "sg:city":"Beverly Hills",
    "sg:classifiers":[
        {
            "category":"Travel",
            "subcategory":"Hotels & Motels",
            "type":"Entertainment"
        }
    ],
    "sg:phone":"+1 310 273 1400",
    "sg:postcode":"90212",
    "sg:province":"CA",
    "wof:name":"Best Western Beverly Pavilion Hotel",
    "wof:placetype":"venue"
},
  "geometry": {"coordinates":[-118.397003,34.0672],"type":"Point"}
}