{
  "type": "Feature",
  "properties": {
    "addr:full":"6640 Bougainvillea Ct Etiwanda CA 91739",
    "addr:housenumber":"6640",
    "addr:postcode":"91739",
    "addr:street":"Bougainvillea Ct",
    "iso:country":"US",
    "sg:address":"6640 Bougainvillea Ct",
    "sg:city":"Etiwanda",
    "sg:classifiers":[
        {
            "category":"Professional",
            "subcategory":"Management & Consulting",
            "type":"Services"
        }
    ],
    "sg:phone":"+1 909 730 8246",
    "sg:postcode":"91739",
    "sg:province":"CA",
    "sg:tags":[
        "consultant",
        "business"
    ],
    "wof:name":"Tool Motorsports",
    "wof:placetype":"venue"
},
  "geometry": {"coordinates":[-117.530052,34.133274],"type":"Point"}
}