{
  "type": "Feature",
  "properties": {
    "iso:country":"US",
    "sg:address":"4222 W Alamos Ave",
    "sg:city":"Fresno",
    "sg:classifiers":[
        {
            "category":"Health Services",
            "subcategory":"Health Practitioner",
            "type":"Services"
        }
    ],
    "sg:phone":"+1 559 275 6838",
    "sg:postcode":"93722",
    "sg:province":"CA",
    "sg:tags":[
        "nutritionist"
    ],
    "wof:name":"Framax",
    "wof:placetype":"venue"
},
  "geometry": {"coordinates":[-119.866852,36.805523],"type":"Point"}
}