{
  "type": "Feature",
  "properties": {
    "iso:country":"US",
    "sg:address":"2040 S 4th St",
    "sg:city":"El Centro",
    "sg:classifiers":[
        {
            "category":"Insurance",
            "subcategory":"Insurance Agent",
            "type":"Services"
        }
    ],
    "sg:phone":"+1 760 353 5400",
    "sg:postcode":"92243",
    "sg:province":"CA",
    "wof:name":"Gene Araujo Payless Auto",
    "wof:placetype":"venue"
},
  "geometry": {"coordinates":[-115.55235500000001,32.775987],"type":"Point"}
}