{
  "type": "Feature",
  "properties": {
    "iso:country":"US",
    "sg:address":"4707 Auburn Blvd",
    "sg:city":"Sacramento",
    "sg:classifiers":[
        {
            "category":"Autos & Motor Vehicles",
            "subcategory":"Automobile Sales",
            "type":"Retail Goods"
        }
    ],
    "sg:phone":"+1 916 283 4775",
    "sg:postcode":"95841",
    "sg:province":"CA",
    "sg:tags":[
        "car",
        "used"
    ],
    "wof:name":"ASB Auto Wholesale",
    "wof:placetype":"venue"
},
  "geometry": {"coordinates":[-121.35453800000001,38.653751],"type":"Point"}
}