{
  "type": "Feature",
  "properties": {
    "addr:full":"550 Lakeside Dr Ste 4 Sunnyvale CA 94085",
    "addr:housenumber":"550",
    "addr:postcode":"94085",
    "addr:street":"Lakeside Dr Ste 4",
    "iso:country":"US",
    "sg:address":"550 Lakeside Dr Ste 4",
    "sg:city":"Sunnyvale",
    "sg:classifiers":[
        {
            "category":"Personal",
            "subcategory":"Beauty Salon",
            "type":"Services"
        },
        {
            "category":"Personal",
            "subcategory":"Nail Salon",
            "type":"Services"
        }
    ],
    "sg:phone":"+1 408 733 5783",
    "sg:postcode":"94085",
    "sg:province":"CA",
    "wof:name":"A Touch of Silk Nail Care",
    "wof:placetype":"venue"
},
  "geometry": {"coordinates":[-121.993326,37.385726],"type":"Point"}
}