{
  "type": "Feature",
  "properties": {
    "iso:country":"US",
    "sg:address":"301 Mission",
    "sg:city":"San Francisco",
    "sg:classifiers":[
        {
            "category":"Building & Trades",
            "subcategory":"Construction",
            "type":"Services"
        }
    ],
    "sg:phone":"+1 650 823 3646",
    "sg:postcode":"94105",
    "sg:province":"CA",
    "sg:tags":[
        "handyman"
    ],
    "wof:name":"Patrick Griffin and Son",
    "wof:placetype":"venue"
},
  "geometry": {"coordinates":[-122.396252,37.790506],"type":"Point"}
}