{
  "type": "Feature",
  "properties": {
    "addr:full":"2623 W 74th St Los Angeles CA 90043",
    "addr:housenumber":"2623",
    "addr:postcode":"90043",
    "addr:street":"W 74Th St",
    "iso:country":"US",
    "sg:address":"2623 W 74th St",
    "sg:city":"Los Angeles",
    "sg:classifiers":[
        {
            "category":"Wholesale",
            "subcategory":"Non-durable Goods",
            "type":"Manufacturing & Wholesale Goods"
        }
    ],
    "sg:phone":"+1 323 750 2812",
    "sg:postcode":"90043",
    "sg:province":"CA",
    "wof:name":"Solo Foods Distributor",
    "wof:placetype":"venue"
},
  "geometry": {"coordinates":[-118.324153,33.972835],"type":"Point"}
}