{
  "type": "Feature",
  "properties": {
    "iso:country":"US",
    "sg:address":"3305 N Gill Rd",
    "sg:city":"Exeter",
    "sg:classifiers":[
        {
            "category":"Farming",
            "subcategory":"Farm",
            "type":"Manufacturing & Wholesale Goods"
        }
    ],
    "sg:phone":"+1 559 592 9393",
    "sg:postcode":"93221",
    "sg:province":"CA",
    "sg:tags":[
        "crop",
        "general"
    ],
    "wof:name":"Ferrara Railroad Ranch",
    "wof:placetype":"venue"
},
  "geometry": {"coordinates":[-119.126061,36.3254],"type":"Point"}
}