{
  "type": "Feature",
  "properties": {
    "iso:country":"US",
    "sg:address":"24682 Northern Dancer Dr",
    "sg:city":"Moreno Valley",
    "sg:classifiers":[
        {
            "category":"Manufacturing",
            "subcategory":"Chemicals & Compounds",
            "type":"Manufacturing & Wholesale Goods"
        }
    ],
    "sg:phone":"+1 951 243 1980",
    "sg:postcode":"92551",
    "sg:province":"CA",
    "sg:tags":[
        "preparation",
        "toilet",
        "mfg"
    ],
    "wof:name":"Kathie Denham",
    "wof:placetype":"venue"
},
  "geometry": {"coordinates":[-117.232783,33.877855],"type":"Point"}
}