{
  "type": "Feature",
  "properties": {
    "iso:country":"US",
    "sg:address":"615 Sanford Ave",
    "sg:city":"Wilmington",
    "sg:classifiers":[
        {
            "category":"Manufacturing",
            "subcategory":"Building Materials",
            "type":"Manufacturing & Wholesale Goods"
        }
    ],
    "sg:phone":"+1 310 830 2352",
    "sg:postcode":"90744",
    "sg:province":"CA",
    "sg:tags":[
        "cabinet"
    ],
    "wof:name":"V & R Cabinet Shop",
    "wof:placetype":"venue"
},
  "geometry": {"coordinates":[-118.250668,33.778942],"type":"Point"}
}