{
  "type": "Feature",
  "properties": {
    "addr:full":"1205 Stannage Ave Albany CA 94706",
    "addr:housenumber":"1205",
    "addr:postcode":"94706",
    "addr:street":"Stannage Ave",
    "iso:country":"US",
    "sg:address":"1205 Stannage Ave",
    "sg:city":"Albany",
    "sg:classifiers":[
        {
            "category":"Insurance",
            "subcategory":"Insurance Agent",
            "type":"Services"
        }
    ],
    "sg:phone":"+1 510 526 2783",
    "sg:postcode":"94706",
    "sg:province":"CA",
    "sg:tags":[
        "teach"
    ],
    "wof:name":"Louise Berman Pre-Retirement",
    "wof:placetype":"venue"
},
  "geometry": {"coordinates":[-122.293994,37.880895],"type":"Point"}
}