{
  "type": "Feature",
  "properties": {
    "addr:full":"2456 S El Camino Real San Mateo CA 94403",
    "addr:housenumber":"2456",
    "addr:postcode":"94403",
    "addr:street":"S El Camino Real",
    "iso:country":"US",
    "sg:address":"2456 S El Camino Real",
    "sg:city":"San Mateo",
    "sg:classifiers":[
        {
            "category":"Restaurant",
            "type":"Food & Drink"
        }
    ],
    "sg:phone":"+1 650 572 8822",
    "sg:postcode":"94403",
    "sg:province":"CA",
    "sg:tags":[
        "vietnamese"
    ],
    "wof:name":"Mama's Vietnamese Cuisine",
    "wof:placetype":"venue"
},
  "geometry": {"coordinates":[-122.305887,37.544371],"type":"Point"}
}