{
  "type": "Feature",
  "properties": {
    "addr:full":"2621 Skyline Dr Eureka CA 95503",
    "addr:housenumber":"2621",
    "addr:postcode":"95503",
    "addr:street":"Skyline Dr",
    "iso:country":"US",
    "sg:address":"2621 Skyline Dr",
    "sg:city":"Eureka",
    "sg:classifiers":[
        {
            "category":"Retail",
            "subcategory":"Laundry & Dry Cleaning",
            "type":"Services"
        }
    ],
    "sg:phone":"+1 707 443 9468",
    "sg:postcode":"95503",
    "sg:province":"CA",
    "sg:tags":[
        "cleaners",
        "rug",
        "carpet"
    ],
    "wof:name":"Professional Cleaning Svc",
    "wof:placetype":"venue"
},
  "geometry": {"coordinates":[-124.198305,40.719848],"type":"Point"}
}