{
  "type": "Feature",
  "properties": {
    "iso:country":"US",
    "sg:address":"4065 Ball Rd",
    "sg:city":"Cypress",
    "sg:classifiers":[
        {
            "category":"Restaurant",
            "type":"Food & Drink"
        }
    ],
    "sg:phone":"+1 714 827 4230",
    "sg:postcode":"90630",
    "sg:province":"CA",
    "sg:tags":[
        "pizza",
        "italian"
    ],
    "sg:website":"www.pizzahut.com",
    "wof:name":"Pizza Hut",
    "wof:placetype":"venue"
},
  "geometry": {"coordinates":[-118.25995,33.817784],"type":"Point"}
}