{
  "type": "Feature",
  "properties": {
    "iso:country":"US",
    "sg:address":"337 S Cedros Ave",
    "sg:city":"Solana Beach",
    "sg:classifiers":[
        {
            "category":"Personal",
            "subcategory":"Beauty Salon",
            "type":"Services"
        }
    ],
    "sg:phone":"+1 858 792 9466",
    "sg:postcode":"92075",
    "sg:province":"CA",
    "sg:tags":[
        "manicuring"
    ],
    "wof:name":"Polished & Beyond",
    "wof:placetype":"venue"
},
  "geometry": {"coordinates":[-117.270427,32.991189],"type":"Point"}
}