{
  "type": "Feature",
  "properties": {
    "addr:full":"2086 Costa Vista Way Oceanside CA 92054",
    "addr:housenumber":"2086",
    "addr:postcode":"92054",
    "addr:street":"Costa Vista Way",
    "iso:country":"US",
    "sg:address":"2086 Costa Vista Way",
    "sg:city":"Oceanside",
    "sg:classifiers":[
        {
            "category":"Autos & Motor Vehicles",
            "subcategory":"Automobile Sales",
            "type":"Retail Goods"
        }
    ],
    "sg:phone":"+1 760 435 1469",
    "sg:postcode":"92054",
    "sg:province":"CA",
    "sg:tags":[
        "car",
        "dealer"
    ],
    "wof:name":"Big Dave's USA Motors",
    "wof:placetype":"venue"
},
  "geometry": {"coordinates":[-117.33164600000001,33.190772],"type":"Point"}
}