{
  "type": "Feature",
  "properties": {
    "addr:full":"4640 Columbia River Ct San Jose CA 95136",
    "addr:housenumber":"4640",
    "addr:postcode":"95136",
    "addr:street":"Columbia River Ct",
    "iso:country":"US",
    "sg:address":"4640 Columbia River Ct",
    "sg:city":"San Jose",
    "sg:classifiers":[
        {
            "category":"Banks & Credit Unions",
            "subcategory":"Bank",
            "type":"Services"
        }
    ],
    "sg:phone":"+1 408 266 2228",
    "sg:postcode":"95136",
    "sg:province":"CA",
    "sg:tags":[
        "savings",
        "institution"
    ],
    "wof:name":"Gibraltar Diversified Service",
    "wof:placetype":"venue"
},
  "geometry": {"coordinates":[-121.864323,37.26444],"type":"Point"}
}