{
  "type": "Feature",
  "properties": {
    "iso:country":"US",
    "sg:address":"1560 Evergreen Ln",
    "sg:city":"Corona",
    "sg:classifiers":[
        {
            "category":"Professional",
            "subcategory":"Art Services",
            "type":"Services"
        }
    ],
    "sg:phone":"+1 951 371 3489",
    "sg:postcode":"92879",
    "sg:province":"CA",
    "sg:tags":[
        "artist"
    ],
    "sg:website":"www.justfinedesigns.com",
    "wof:name":"Just Fine Designs",
    "wof:placetype":"venue"
},
  "geometry": {"coordinates":[-117.55616000000001,33.864176],"type":"Point"}
}