{
  "type": "Feature",
  "properties": {
    "iso:country":"US",
    "sg:address":"9297 G Ave",
    "sg:city":"Hesperia",
    "sg:classifiers":[
        {
            "category":"Restaurant",
            "type":"Food & Drink"
        }
    ],
    "sg:phone":"+1 760 949 6617",
    "sg:postcode":"92345",
    "sg:province":"CA",
    "wof:name":"Wendy's",
    "wof:placetype":"venue"
},
  "geometry": {"coordinates":[-117.286998,34.422817],"type":"Point"}
}