{
  "type": "Feature",
  "properties": {
    "iso:country":"US",
    "sg:address":"320 8th St",
    "sg:city":"Oakland",
    "sg:classifiers":[
        {
            "category":"Health Services",
            "subcategory":"Doctor",
            "type":"Services"
        }
    ],
    "sg:phone":"+1 510 832 8819",
    "sg:postcode":"94607",
    "sg:province":"CA",
    "sg:tags":[
        "physician",
        "family",
        "practice",
        "surgeons",
        "medicine",
        "surgeon"
    ],
    "wof:name":"Lim Medical Clinic",
    "wof:placetype":"venue"
},
  "geometry": {"coordinates":[-122.270662,37.798976],"type":"Point"}
}