{
  "type": "Feature",
  "properties": {
    "iso:country":"US",
    "sg:address":"3320 Industrial Dr",
    "sg:city":"Santa Rosa",
    "sg:classifiers":[
        {
            "category":"Government",
            "subcategory":"Office",
            "type":"Public Place"
        }
    ],
    "sg:phone":"+1 707 523 7900",
    "sg:postcode":"95403",
    "sg:province":"CA",
    "sg:tags":[
        "program",
        "administrative"
    ],
    "wof:name":"Redwood Empire Food Bank",
    "wof:placetype":"venue"
},
  "geometry": {"coordinates":[-122.74010199999999,38.474306],"type":"Point"}
}