{
  "type": "Feature",
  "properties": {
    "addr:full":"780 Mc Donell Dr S San Francisco CA 94080",
    "addr:housenumber":"780",
    "addr:postcode":"94080",
    "addr:street":"Mc Donell Dr S",
    "iso:country":"US",
    "sg:address":"780 Mc Donell Dr",
    "sg:city":"S San Francisco",
    "sg:classifiers":[
        {
            "category":"Retail",
            "subcategory":"Auto Rental",
            "type":"Services"
        }
    ],
    "sg:phone":"+1 650 616 2400",
    "sg:postcode":"94080",
    "sg:province":"CA",
    "sg:tags":[
        "renting",
        "automobile"
    ],
    "wof:name":"Alamo Rent-A-Car",
    "wof:placetype":"venue"
},
  "geometry": {"coordinates":[-122.45103899999999,37.663409],"type":"Point"}
}