{
  "type": "Feature",
  "properties": {
    "iso:country":"US",
    "sg:address":"2211 Corinth Ave",
    "sg:city":"Los Angeles",
    "sg:classifiers":[
        {
            "category":"Health Services",
            "subcategory":"Health Practitioner",
            "type":"Services"
        }
    ],
    "sg:phone":"+1 310 445 2171",
    "sg:postcode":"90064",
    "sg:province":"CA",
    "sg:tags":[
        "pathologist",
        "speech"
    ],
    "wof:name":"Linda F Diamond",
    "wof:placetype":"venue"
},
  "geometry": {"coordinates":[-118.44110000000001,34.036241],"type":"Point"}
}