{
  "type": "Feature",
  "properties": {
    "addr:full":"3285 S Higuera St San Luis Obispo CA 93401",
    "addr:housenumber":"3285",
    "addr:postcode":"93401",
    "addr:street":"S Higuera St",
    "iso:country":"US",
    "sg:address":"3285 S Higuera St",
    "sg:city":"San Luis Obispo",
    "sg:classifiers":[
        {
            "category":"Shopping",
            "subcategory":"Bicycles & Sporting Goods",
            "type":"Retail Goods"
        }
    ],
    "sg:phone":"+1 805 543 5154",
    "sg:postcode":"93401",
    "sg:province":"CA",
    "sg:tags":[
        "skating",
        "equipment",
        "supply"
    ],
    "sg:website":"www.ppiskates.com",
    "wof:name":"Powerplay In-Line",
    "wof:placetype":"venue"
},
  "geometry": {"coordinates":[-120.668736,35.255152],"type":"Point"}
}