{
  "type": "Feature",
  "properties": {
    "iso:country":"US",
    "sg:address":"5656 N Paramount Blvd",
    "sg:city":"Long Beach",
    "sg:classifiers":[
        {
            "category":"Home & Garden",
            "subcategory":"Furniture",
            "type":"Retail Goods"
        }
    ],
    "sg:phone":"+1 562 630 0719",
    "sg:postcode":"90805",
    "sg:province":"CA",
    "wof:name":"Cindy's Furniture",
    "wof:placetype":"venue"
},
  "geometry": {"coordinates":[-118.1598,33.858748],"type":"Point"}
}