{
  "type": "Feature",
  "properties": {
    "iso:country":"US",
    "sg:address":"185 W F Street",
    "sg:city":"San Diego",
    "sg:classifiers":[
        {
            "category":"Professional",
            "subcategory":"Lawyer & Legal Services",
            "type":"Services"
        }
    ],
    "sg:phone":"+1 619 696 7881",
    "sg:postcode":"92101",
    "sg:province":"CA",
    "wof:name":"Garcia Robert Atty",
    "wof:placetype":"venue"
},
  "geometry": {"coordinates":[-117.164421,32.7136],"type":"Point"}
}