{
  "type": "Feature",
  "properties": {
    "iso:country":"US",
    "sg:address":"2410 California St",
    "sg:city":"San Francisco",
    "sg:classifiers":[
        {
            "category":"Sports & Exercise",
            "subcategory":"Gym",
            "type":"Entertainment"
        }
    ],
    "sg:phone":"+1 415 775 0570",
    "sg:postcode":"94101",
    "sg:province":"CA",
    "sg:tags":[
        "yoga"
    ],
    "sg:website":"www.calyogacompany.com",
    "wof:name":"California Yoga Company",
    "wof:placetype":"venue"
},
  "geometry": {"coordinates":[-122.434383,37.788936],"type":"Point"}
}