{
  "type": "Feature",
  "properties": {
    "iso:country":"US",
    "sg:address":"7171 Rich Ave",
    "sg:city":"Newark",
    "sg:classifiers":[
        {
            "category":"Shopping",
            "subcategory":"Music",
            "type":"Retail Goods"
        }
    ],
    "sg:phone":"+1 510 796 5525",
    "sg:postcode":"94560",
    "sg:province":"CA",
    "sg:tags":[
        "video",
        "disc",
        "tape",
        "cassette"
    ],
    "wof:name":"Adult Book Nook",
    "wof:placetype":"venue"
},
  "geometry": {"coordinates":[-122.03633600000001,37.530075],"type":"Point"}
}