{
  "type": "Feature",
  "properties": {
    "iso:country":"US",
    "sg:address":"6400 Canoga Ave",
    "sg:city":"Woodland Hills",
    "sg:classifiers":[
        {
            "category":"Professional",
            "subcategory":"Lawyer & Legal Services",
            "type":"Services"
        }
    ],
    "sg:phone":"+1 818 716 1444",
    "sg:postcode":"91367",
    "sg:province":"CA",
    "sg:tags":[
        "divorce",
        "law",
        "family"
    ],
    "wof:name":"Lenske Stephen A Atty",
    "wof:placetype":"venue"
},
  "geometry": {"coordinates":[-118.59699999999999,34.1866],"type":"Point"}
}