{
  "type": "Feature",
  "properties": {
    "iso:country":"US",
    "sg:address":"4915 Via del Cerro",
    "sg:city":"Yorba Linda",
    "sg:classifiers":[
        {
            "category":"Shopping",
            "subcategory":"Gifts & Souvenirs",
            "type":"Retail Goods"
        }
    ],
    "sg:phone":"+1 714 695 0111",
    "sg:postcode":"92887",
    "sg:province":"CA",
    "wof:name":"Princess Candy & Gift Baskets",
    "wof:placetype":"venue"
},
  "geometry": {"coordinates":[-117.75955999999999,33.89041],"type":"Point"}
}