{
  "type": "Feature",
  "properties": {
    "iso:country":"US",
    "sg:address":"4750 Norris Canyon Rd",
    "sg:city":"San Ramon",
    "sg:classifiers":[
        {
            "category":"Shopping",
            "type":"Retail Goods"
        }
    ],
    "sg:phone":"+1 925 242 0249",
    "sg:postcode":"94583",
    "sg:province":"CA",
    "sg:tags":[
        "miscellaneous",
        "store"
    ],
    "wof:name":"Gemini Gems",
    "wof:placetype":"venue"
},
  "geometry": {"coordinates":[-121.96202,37.776436],"type":"Point"}
}