{
  "type": "Feature",
  "properties": {
    "addr:full":"29220 Pacific St Hayward CA 94544",
    "addr:housenumber":"29220",
    "addr:postcode":"94544",
    "addr:street":"Pacific St",
    "iso:country":"US",
    "sg:address":"29220 Pacific St",
    "sg:city":"Hayward",
    "sg:classifiers":[
        {
            "category":"Bus Charters",
            "type":"Transportation"
        }
    ],
    "sg:phone":"+1 510 728 1500",
    "sg:postcode":"94544",
    "sg:province":"CA",
    "sg:tags":[
        "rental"
    ],
    "sg:website":"www.eldoradobussales.com",
    "wof:name":"El Dorado Bus Sales",
    "wof:placetype":"venue"
},
  "geometry": {"coordinates":[-122.05499399999999,37.629035],"type":"Point"}
}