{
  "type": "Feature",
  "properties": {
    "addr:full":"4319 N Figueroa St Los Angeles CA 90065",
    "addr:housenumber":"4319",
    "addr:postcode":"90065",
    "addr:street":"N Figueroa St",
    "iso:country":"US",
    "sg:address":"4319 N Figueroa St",
    "sg:city":"Los Angeles",
    "sg:classifiers":[
        {
            "category":"Sports & Exercise",
            "subcategory":"Gym",
            "type":"Entertainment"
        }
    ],
    "sg:phone":"+1 323 224 0044",
    "sg:postcode":"90065",
    "sg:province":"CA",
    "sg:tags":[
        "club",
        "health",
        "studio",
        "gymnasium"
    ],
    "wof:name":"Curves For Women",
    "wof:placetype":"venue"
},
  "geometry": {"coordinates":[-118.208099,34.095099],"type":"Point"}
}