{
  "type": "Feature",
  "properties": {
    "iso:country":"US",
    "sg:address":"1825 Coast Blvd",
    "sg:city":"Del Mar",
    "sg:classifiers":[
        {
            "category":"Communications",
            "subcategory":"Film & Video Production",
            "type":"Services"
        }
    ],
    "sg:phone":"+1 858 755 8544",
    "sg:postcode":"92014",
    "sg:province":"CA",
    "sg:tags":[
        "taping"
    ],
    "sg:website":"www.bptv.com",
    "wof:name":"Barnstromer Productions",
    "wof:placetype":"venue"
},
  "geometry": {"coordinates":[-117.267264,32.964436],"type":"Point"}
}