{
  "type": "Feature",
  "properties": {
    "iso:country":"US",
    "sg:address":"13886 Campo Rd",
    "sg:city":"Jamul",
    "sg:classifiers":[
        {
            "category":"Retail",
            "subcategory":"Auto Repair",
            "type":"Services"
        }
    ],
    "sg:phone":"+1 619 669 9886",
    "sg:postcode":"91935",
    "sg:province":"CA",
    "sg:tags":[
        "automobile",
        "lubrication"
    ],
    "wof:name":"Jamul Quik Lube",
    "wof:placetype":"venue"
},
  "geometry": {"coordinates":[-116.87639799999999,32.717073],"type":"Point"}
}