{
  "type": "Feature",
  "properties": {
    "addr:full":"337 Main St Ferndale CA 95536",
    "addr:housenumber":"337",
    "addr:postcode":"95536",
    "addr:street":"Main St",
    "iso:country":"US",
    "sg:address":"337 Main St",
    "sg:city":"Ferndale",
    "sg:classifiers":[
        {
            "category":"Food & Beverages",
            "subcategory":"Liquor & Beverages",
            "type":"Retail Goods"
        }
    ],
    "sg:phone":"+1 707 786 4555",
    "sg:postcode":"95536",
    "sg:province":"CA",
    "wof:name":"J & W Liquors",
    "wof:placetype":"venue"
},
  "geometry": {"coordinates":[-124.264245,40.576059],"type":"Point"}
}