{
  "type": "Feature",
  "properties": {
    "addr:full":"4201 Holly Knoll Los Angeles CA 90015",
    "addr:housenumber":"4201",
    "addr:postcode":"90015",
    "addr:street":"Holly Knoll",
    "iso:country":"US",
    "sg:address":"4201 Holly Knoll",
    "sg:city":"Los Angeles",
    "sg:classifiers":[
        {
            "category":"Shopping",
            "subcategory":"Clothing, Apparel, & Fashions",
            "type":"Retail Goods"
        }
    ],
    "sg:phone":"+1 323 584 4400",
    "sg:postcode":"90015",
    "sg:province":"CA",
    "sg:tags":[
        "clothing",
        "women's"
    ],
    "sg:website":"grassla.com/",
    "wof:name":"Grass Jeans",
    "wof:placetype":"venue"
},
  "geometry": {"coordinates":[-118.281998,34.106701],"type":"Point"}
}