{
  "type": "Feature",
  "properties": {
    "iso:country":"US",
    "sg:address":"2021 N Western Ave",
    "sg:city":"Los Angeles",
    "sg:classifiers":[
        {
            "category":"Professional",
            "type":"Services"
        }
    ],
    "sg:phone":"+1 323 856 7612",
    "sg:postcode":"90027",
    "sg:province":"CA",
    "wof:name":"Bamboo Productions",
    "wof:placetype":"venue"
},
  "geometry": {"coordinates":[-118.309367,34.106812],"type":"Point"}
}