{
  "type": "Feature",
  "properties": {
    "addr:full":"100 N Glendora Ave Glendora CA 91741",
    "addr:housenumber":"100",
    "addr:postcode":"91741",
    "addr:street":"N Glendora Ave",
    "iso:country":"US",
    "sg:address":"100 N Glendora Ave",
    "sg:city":"Glendora",
    "sg:classifiers":[
        {
            "category":"Professional",
            "subcategory":"Management & Consulting",
            "type":"Services"
        }
    ],
    "sg:phone":"+1 626 852 5929",
    "sg:postcode":"91741",
    "sg:province":"CA",
    "sg:tags":[
        "consultant",
        "telecommunication"
    ],
    "wof:name":"Jim Falco",
    "wof:placetype":"venue"
},
  "geometry": {"coordinates":[-117.86544000000001,34.136678],"type":"Point"}
}