{
  "type": "Feature",
  "properties": {
    "addr:full":"2525 Michigan Ave Santa Monica CA 90404",
    "addr:housenumber":"2525",
    "addr:postcode":"90404",
    "addr:street":"Michigan Ave",
    "iso:country":"US",
    "sg:address":"2525 Michigan Ave",
    "sg:city":"Santa Monica",
    "sg:classifiers":[
        {
            "category":"Cafe",
            "type":"Food & Drink"
        },
        {
            "category":"Restaurant",
            "type":"Food & Drink"
        }
    ],
    "sg:menulink":"http://www.allmenus.com/ca/santa-monica/278912-bergamot-cafe/menu/",
    "sg:phone":"+1 310 828 4001",
    "sg:postcode":"90404",
    "sg:province":"CA",
    "sg:tags":[
        "american",
        "sandwich"
    ],
    "wof:name":"Bergamot Cafe",
    "wof:placetype":"venue"
},
  "geometry": {"coordinates":[-118.468591,34.027106],"type":"Point"}
}