{
  "type": "Feature",
  "properties": {
    "addr:full":"2425 E Clinton Ave Fresno CA 93703",
    "addr:housenumber":"2425",
    "addr:postcode":"93703",
    "addr:street":"E Clinton Ave",
    "iso:country":"US",
    "sg:address":"2425 E Clinton Ave",
    "sg:city":"Fresno",
    "sg:classifiers":[
        {
            "category":"Autos & Motor Vehicles",
            "subcategory":"Automobile Sales",
            "type":"Retail Goods"
        }
    ],
    "sg:phone":"+1 559 226 2845",
    "sg:postcode":"93703",
    "sg:province":"CA",
    "sg:tags":[
        "car",
        "dealer"
    ],
    "wof:name":"Calif Trading Co",
    "wof:placetype":"venue"
},
  "geometry": {"coordinates":[-119.781873,36.772337],"type":"Point"}
}