{
  "type": "Feature",
  "properties": {
    "addr:full":"3102 Industrial Blvd West Sacramento CA 95691",
    "addr:housenumber":"3102",
    "addr:postcode":"95691",
    "addr:street":"Industrial Blvd",
    "iso:country":"US",
    "sg:address":"3102 Industrial Blvd",
    "sg:city":"West Sacramento",
    "sg:classifiers":[
        {
            "category":"Professional",
            "subcategory":"Research",
            "type":"Services"
        }
    ],
    "sg:phone":"+1 916 375 6700",
    "sg:postcode":"95691",
    "sg:province":"CA",
    "sg:tags":[
        "engineering",
        "consulting"
    ],
    "wof:name":"Matriscope Engrg Lbrtories Inc",
    "wof:placetype":"venue"
},
  "geometry": {"coordinates":[-121.551286,38.570469],"type":"Point"}
}