{
  "type": "Feature",
  "properties": {
    "addr:full":"1150 Concord Ave Ste 180 Concord CA 94520",
    "addr:housenumber":"1150",
    "addr:postcode":"94520",
    "addr:street":"Concord Ave Ste 180",
    "iso:country":"US",
    "sg:address":"1150 Concord Ave Ste 180",
    "sg:city":"Concord",
    "sg:classifiers":[
        {
            "category":"Home & Garden",
            "subcategory":"Furniture",
            "type":"Retail Goods"
        }
    ],
    "sg:phone":"+1 925 825 5202",
    "sg:postcode":"94520",
    "sg:province":"CA",
    "sg:tags":[
        "store"
    ],
    "wof:name":"Arizona Leather Co",
    "wof:placetype":"venue"
},
  "geometry": {"coordinates":[-122.057771,37.979484],"type":"Point"}
}