{
  "type": "Feature",
  "properties": {
    "addr:full":"2512 Artesia Blvd Redondo Beach CA 90278",
    "addr:housenumber":"2512",
    "addr:postcode":"90278",
    "addr:street":"Artesia Blvd",
    "iso:country":"US",
    "sg:address":"2512 Artesia Blvd",
    "sg:city":"Redondo Beach",
    "sg:classifiers":[
        {
            "category":"Wholesale",
            "subcategory":"Medical Equipment & Supplies",
            "type":"Manufacturing & Wholesale Goods"
        }
    ],
    "sg:phone":"+1 310 318 2726",
    "sg:postcode":"90278",
    "sg:province":"CA",
    "sg:tags":[
        "alarm"
    ],
    "wof:name":"American Medical Alert Corp",
    "wof:placetype":"venue"
},
  "geometry": {"coordinates":[-118.36450600000001,33.872776],"type":"Point"}
}