{
  "type": "Feature",
  "properties": {
    "addr:full":"900 Gateway Blvd South San Francisco CA 94080",
    "addr:housenumber":"900",
    "addr:postcode":"94080",
    "addr:street":"Gateway Blvd",
    "iso:country":"US",
    "sg:address":"900 Gateway Blvd",
    "sg:city":"South San Francisco",
    "sg:classifiers":[
        {
            "category":"Personal",
            "type":"Services"
        }
    ],
    "sg:postcode":"94080",
    "sg:province":"CA",
    "sg:tags":[
        "local"
    ],
    "sg:website":"www.fedex.com",
    "wof:name":"Fed Ex Express Ship Center",
    "wof:placetype":"venue"
},
  "geometry": {"coordinates":[-122.395906,37.662136],"type":"Point"}
}