{
  "type": "Feature",
  "properties": {
    "iso:country":"US",
    "sg:address":"189 Bernardo Avenue",
    "sg:city":"Mountain View",
    "sg:classifiers":[
        {
            "category":"Professional",
            "subcategory":"Computer Services",
            "type":"Services"
        }
    ],
    "sg:phone":"+1 650 230 5000",
    "sg:postcode":"94043",
    "sg:province":"CA",
    "wof:name":"Handspring",
    "wof:placetype":"venue"
},
  "geometry": {"coordinates":[-122.04816,37.390189],"type":"Point"}
}