{
  "type": "Feature",
  "properties": {
    "addr:full":"2210 W Redondo Beach Boulevard Gardena CA 90247",
    "addr:housenumber":"2210",
    "addr:postcode":"90247",
    "addr:street":"W Redondo Beach Boulevard",
    "iso:country":"US",
    "sg:address":"2210 W Redondo Beach Boulevard",
    "sg:city":"Gardena",
    "sg:classifiers":[
        {
            "category":"Restaurant",
            "type":"Food & Drink"
        }
    ],
    "sg:phone":"+1 310 323 1472",
    "sg:postcode":"90247",
    "sg:province":"CA",
    "wof:name":"Carl's Jr Restaurants",
    "wof:placetype":"venue"
},
  "geometry": {"coordinates":[-118.292928,33.892455],"type":"Point"}
}