{
  "type": "Feature",
  "properties": {
    "iso:country":"US",
    "sg:address":"8 Porter Dr",
    "sg:city":"Watsonville",
    "sg:classifiers":[
        {
            "category":"Manufacturing",
            "subcategory":"Motor Vehicles & Parts",
            "type":"Manufacturing & Wholesale Goods"
        }
    ],
    "sg:phone":"+1 831 728 4554",
    "sg:postcode":"95076",
    "sg:province":"CA",
    "sg:tags":[
        "automobile",
        "supply"
    ],
    "wof:name":"Ken's Auto Parts",
    "wof:placetype":"venue"
},
  "geometry": {"coordinates":[-121.749279,36.903289],"type":"Point"}
}