{
  "type": "Feature",
  "properties": {
    "addr:full":"411 Blue Ravine Rd Folsom CA 95630",
    "addr:housenumber":"411",
    "addr:postcode":"95630",
    "addr:street":"Blue Ravine Rd",
    "iso:country":"US",
    "sg:address":"411 Blue Ravine Rd",
    "sg:city":"Folsom",
    "sg:classifiers":[
        {
            "category":"Restaurant",
            "type":"Food & Drink"
        }
    ],
    "sg:phone":"+1 916 983 0900",
    "sg:postcode":"95630",
    "sg:province":"CA",
    "sg:tags":[
        "delicatessen"
    ],
    "sg:website":"www.beachousedeli.com",
    "wof:name":"Beachouse Deli",
    "wof:placetype":"venue"
},
  "geometry": {"coordinates":[-121.151155,38.671024],"type":"Point"}
}