{
  "type": "Feature",
  "properties": {
    "iso:country":"US",
    "sg:address":"750 N Midway Dr",
    "sg:city":"Escondido",
    "sg:classifiers":[
        {
            "category":"Insurance",
            "subcategory":"Hazard Insurance",
            "type":"Services"
        }
    ],
    "sg:phone":"+1 760 480 8555",
    "sg:postcode":"92027",
    "sg:province":"CA",
    "sg:tags":[
        "bond"
    ],
    "wof:name":"Pineda Insurance Income Taxes",
    "wof:placetype":"venue"
},
  "geometry": {"coordinates":[-117.055877,33.143967],"type":"Point"}
}