{
  "type": "Feature",
  "properties": {
    "iso:country":"US",
    "sg:address":"2001 N Pacific Ave",
    "sg:city":"Stockton",
    "sg:classifiers":[
        {
            "category":"Shopping",
            "subcategory":"Florist",
            "type":"Retail Goods"
        }
    ],
    "sg:phone":"+1 209 466 4973",
    "sg:postcode":"95204",
    "sg:province":"CA",
    "wof:name":"San Francisco Floral Co",
    "wof:placetype":"venue"
},
  "geometry": {"coordinates":[-121.299444,37.970213],"type":"Point"}
}