{
  "type": "Feature",
  "properties": {
    "iso:country":"US",
    "sg:address":"14721 Sisson Rd",
    "sg:city":"Penn Valley",
    "sg:classifiers":[
        {
            "category":"Professional",
            "type":"Services"
        }
    ],
    "sg:phone":"+1 530 432 3516",
    "sg:postcode":"95946",
    "sg:province":"CA",
    "wof:name":"Marti A Mott",
    "wof:placetype":"venue"
},
  "geometry": {"coordinates":[-121.216052,39.259655],"type":"Point"}
}