{
  "type": "Feature",
  "properties": {
    "iso:country":"US",
    "sg:address":"2333 Pacific Ave",
    "sg:city":"Long Beach",
    "sg:classifiers":[
        {
            "category":"Health Services",
            "subcategory":"Doctor",
            "type":"Services"
        }
    ],
    "sg:phone":"+1 562 427 7443",
    "sg:postcode":"90806",
    "sg:province":"CA",
    "sg:tags":[
        "podiatrist"
    ],
    "sg:website":"memorialpodiatrygroup.com/",
    "wof:name":"Hubbard Eric R DPM",
    "wof:placetype":"venue"
},
  "geometry": {"coordinates":[-118.194051,33.799592],"type":"Point"}
}