{
  "type": "Feature",
  "properties": {
    "addr:full":"225 Main St Chico CA 95928",
    "addr:housenumber":"225",
    "addr:postcode":"95928",
    "addr:street":"Main St",
    "iso:country":"US",
    "sg:address":"225 Main St",
    "sg:city":"Chico",
    "sg:classifiers":[
        {
            "category":"Shopping",
            "type":"Retail Goods"
        }
    ],
    "sg:phone":"+1 530 899 3753",
    "sg:postcode":"95928",
    "sg:province":"CA",
    "sg:tags":[
        "african"
    ],
    "wof:name":"African Connection & Cultural",
    "wof:placetype":"venue"
},
  "geometry": {"coordinates":[-121.839755,39.729768],"type":"Point"}
}