{
  "type": "Feature",
  "properties": {
    "iso:country":"US",
    "sg:address":"65 S Lassen St",
    "sg:city":"Susanville",
    "sg:classifiers":[
        {
            "category":"Real Estate",
            "subcategory":"Real Estate Services",
            "type":"Services"
        }
    ],
    "sg:phone":"+1 530 257 4161",
    "sg:postcode":"96130",
    "sg:province":"CA",
    "sg:tags":[
        "company",
        "title"
    ],
    "wof:name":"Chicago Title Co",
    "wof:placetype":"venue"
},
  "geometry": {"coordinates":[-120.66201,40.417939],"type":"Point"}
}