{
  "type": "Feature",
  "properties": {
    "addr:full":"1522 Swallow Way Roseville CA 95661",
    "addr:housenumber":"1522",
    "addr:postcode":"95661",
    "addr:street":"Swallow Way",
    "iso:country":"US",
    "sg:address":"1522 Swallow Way",
    "sg:city":"Roseville",
    "sg:classifiers":[
        {
            "category":"Professional",
            "subcategory":"Accounting & Tax Preparation",
            "type":"Services"
        }
    ],
    "sg:phone":"+1 916 723 3111",
    "sg:postcode":"95661",
    "sg:province":"CA",
    "sg:tags":[
        "return",
        "filing"
    ],
    "wof:name":"Gift & Long Inc",
    "wof:placetype":"venue"
},
  "geometry": {"coordinates":[-121.255655,38.737225],"type":"Point"}
}