{
  "type": "Feature",
  "properties": {
    "addr:full":"2614 Elden Ave Costa Mesa CA 92627",
    "addr:housenumber":"2614",
    "addr:postcode":"92627",
    "addr:street":"Elden Ave",
    "iso:country":"US",
    "sg:address":"2614 Elden Ave",
    "sg:city":"Costa Mesa",
    "sg:classifiers":[
        {
            "category":"Shopping",
            "subcategory":"Clothing, Apparel, & Fashions",
            "type":"Retail Goods"
        }
    ],
    "sg:phone":"+1 949 515 3571",
    "sg:postcode":"92627",
    "sg:province":"CA",
    "sg:tags":[
        "baby",
        "accessory"
    ],
    "wof:name":"Child Proof",
    "wof:placetype":"venue"
},
  "geometry": {"coordinates":[-117.894801,33.662196],"type":"Point"}
}