{
  "type": "Feature",
  "properties": {
    "addr:full":"11032 Magnolia St Garden Grove CA 92841",
    "addr:housenumber":"11032",
    "addr:postcode":"92841",
    "addr:street":"Magnolia St",
    "iso:country":"US",
    "sg:address":"11032 Magnolia St",
    "sg:city":"Garden Grove",
    "sg:classifiers":[
        {
            "category":"Insurance",
            "subcategory":"Insurance Agent",
            "type":"Services"
        }
    ],
    "sg:phone":"+1 714 995 7730",
    "sg:postcode":"92841",
    "sg:province":"CA",
    "wof:name":"Arca Insurance & Svc",
    "wof:placetype":"venue"
},
  "geometry": {"coordinates":[-117.975555,33.802599],"type":"Point"}
}