{
  "type": "Feature",
  "properties": {
    "iso:country":"US",
    "sg:address":"4130 Shawn St",
    "sg:city":"Bakersfield",
    "sg:classifiers":[
        {
            "category":"Building & Trades",
            "subcategory":"Cleaning & Sanitation",
            "type":"Services"
        }
    ],
    "sg:phone":"+1 661 589 8081",
    "sg:postcode":"93312",
    "sg:province":"CA",
    "sg:tags":[
        "janitor"
    ],
    "wof:name":"Divine Janitorial",
    "wof:placetype":"venue"
},
  "geometry": {"coordinates":[-119.121403,35.39766],"type":"Point"}
}