{
  "type": "Feature",
  "properties": {
    "addr:full":"11133 Charnock Rd Los Angeles CA 90034",
    "addr:housenumber":"11133",
    "addr:postcode":"90034",
    "addr:street":"Charnock Rd",
    "iso:country":"US",
    "sg:address":"11133 Charnock Rd",
    "sg:city":"Los Angeles",
    "sg:classifiers":[
        {
            "category":"Education",
            "subcategory":"School",
            "type":"Public Place"
        }
    ],
    "sg:phone":"+1 310 838 6110",
    "sg:postcode":"90034",
    "sg:province":"CA",
    "sg:tags":[
        "elementary"
    ],
    "sg:website":"www.lausd.k12.ca.us",
    "wof:name":"Charnock Road Elementary School",
    "wof:placetype":"venue"
},
  "geometry": {"coordinates":[-118.418999,34.017399],"type":"Point"}
}