{
  "type": "Feature",
  "properties": {
    "addr:full":"245 N Puente Ave La Puente CA 91746",
    "addr:housenumber":"245",
    "addr:postcode":"91746",
    "addr:street":"N Puente Ave",
    "iso:country":"US",
    "sg:address":"245 N Puente Ave",
    "sg:city":"La Puente",
    "sg:classifiers":[
        {
            "category":"Recreation",
            "type":"Entertainment"
        }
    ],
    "sg:phone":"+1 626 968 2666",
    "sg:postcode":"91746",
    "sg:province":"CA",
    "sg:tags":[
        "parks"
    ],
    "wof:name":"San Angelo Park",
    "wof:placetype":"venue"
},
  "geometry": {"coordinates":[-117.98796400000001,34.044793],"type":"Point"}
}