{
  "type": "Feature",
  "properties": {
    "addr:full":"1204 W Collins Ave Orange CA 92867",
    "addr:housenumber":"1204",
    "addr:postcode":"92867",
    "addr:street":"W Collins Ave",
    "iso:country":"US",
    "sg:address":"1204 W Collins Ave",
    "sg:city":"Orange",
    "sg:classifiers":[
        {
            "category":"Arts & Performance",
            "subcategory":"Theater",
            "type":"Entertainment"
        }
    ],
    "sg:phone":"+1 714 771 1981",
    "sg:postcode":"92867",
    "sg:province":"CA",
    "sg:tags":[
        "entertainer",
        "business"
    ],
    "wof:name":"K F Enterprises",
    "wof:placetype":"venue"
},
  "geometry": {"coordinates":[-117.866097,33.802339],"type":"Point"}
}