{
  "type": "Feature",
  "properties": {
    "addr:full":"501 S Chinowth St Visalia CA 93277",
    "addr:housenumber":"501",
    "addr:postcode":"93277",
    "addr:street":"S Chinowth St",
    "iso:country":"US",
    "sg:address":"501 S Chinowth St",
    "sg:city":"Visalia",
    "sg:classifiers":[
        {
            "category":"Restaurant",
            "type":"Food & Drink"
        }
    ],
    "sg:menulink":"http://www.allmenus.com/ca/visalia/171247-carls-jr/menu/",
    "sg:phone":"+1 559 739 1342",
    "sg:postcode":"93277",
    "sg:province":"CA",
    "sg:tags":[
        "burger",
        "american"
    ],
    "wof:name":"Carl's Jr.",
    "wof:placetype":"venue"
},
  "geometry": {"coordinates":[-119.33633399999999,36.326244],"type":"Point"}
}