{
  "type": "Feature",
  "properties": {
    "addr:full":"361 S Main St Willits CA 95490",
    "addr:housenumber":"361",
    "addr:postcode":"95490",
    "addr:street":"S Main St",
    "iso:country":"US",
    "sg:address":"361 S Main St",
    "sg:city":"Willits",
    "sg:classifiers":[
        {
            "category":"Health Services",
            "subcategory":"Doctor",
            "type":"Services"
        }
    ],
    "sg:phone":"+1 707 459 6103",
    "sg:postcode":"95490",
    "sg:province":"CA",
    "sg:tags":[
        "dentist"
    ],
    "wof:name":"Henry W Rued Inc",
    "wof:placetype":"venue"
},
  "geometry": {"coordinates":[-123.352689,39.40807],"type":"Point"}
}