{
  "type": "Feature",
  "properties": {
    "addr:full":"1707 Vine St Los Angeles CA 90028",
    "addr:housenumber":"1707",
    "addr:postcode":"90028",
    "addr:street":"Vine St",
    "iso:country":"US",
    "sg:address":"1707 Vine St",
    "sg:city":"Los Angeles",
    "sg:classifiers":[
        {
            "category":"Bars & Pubs",
            "subcategory":"Nightclub",
            "type":"Food & Drink"
        }
    ],
    "sg:phone":"+1 323 464 4937",
    "sg:postcode":"90028",
    "sg:province":"CA",
    "sg:tags":[
        "nightlife"
    ],
    "wof:name":"Basque",
    "wof:placetype":"venue"
},
  "geometry": {"coordinates":[-118.32684500000001,34.101756],"type":"Point"}
}