{
  "type": "Feature",
  "properties": {
    "addr:full":"10983 Bluffside Dr Studio City CA 91604",
    "addr:housenumber":"10983",
    "addr:postcode":"91604",
    "addr:street":"Bluffside Dr",
    "iso:country":"US",
    "sg:address":"10983 Bluffside Dr",
    "sg:city":"Studio City",
    "sg:classifiers":[
        {
            "category":"Health Services",
            "subcategory":"Doctor",
            "type":"Services"
        }
    ],
    "sg:phone":"+1 818 755 1735",
    "sg:postcode":"91604",
    "sg:province":"CA",
    "sg:tags":[
        "physician",
        "surgeon"
    ],
    "wof:name":"Plaza Health Care Med Group",
    "wof:placetype":"venue"
},
  "geometry": {"coordinates":[-118.367357,34.140724],"type":"Point"}
}