{
  "type": "Feature",
  "properties": {
    "iso:country":"US",
    "sg:address":"2220 Sleepy Hollow Dr",
    "sg:city":"Shingle Springs",
    "sg:classifiers":[
        {
            "category":"Professional",
            "type":"Services"
        }
    ],
    "sg:phone":"+1 530 919 7497",
    "sg:postcode":"95682",
    "sg:province":"CA",
    "wof:name":"Brannon Computing",
    "wof:placetype":"venue"
},
  "geometry": {"coordinates":[-120.927693,38.707004],"type":"Point"}
}