{
  "type": "Feature",
  "properties": {
    "iso:country":"US",
    "sg:address":"415 N Camden Dr",
    "sg:city":"Beverly Hills",
    "sg:classifiers":[
        {
            "category":"Professional",
            "subcategory":"Lawyer & Legal Services",
            "type":"Services"
        }
    ],
    "sg:phone":"+1 310 276 0640",
    "sg:postcode":"90210",
    "sg:province":"CA",
    "wof:name":"Newman John P Law Office",
    "wof:placetype":"venue"
},
  "geometry": {"coordinates":[-118.403999,34.0686],"type":"Point"}
}