{
  "type": "Feature",
  "properties": {
    "addr:full":"650 Cambria Ct Vacaville CA 95687",
    "addr:housenumber":"650",
    "addr:postcode":"95687",
    "addr:street":"Cambria Ct",
    "iso:country":"US",
    "sg:address":"650 Cambria Ct",
    "sg:city":"Vacaville",
    "sg:classifiers":[
        {
            "category":"Building & Trades",
            "subcategory":"Pest Control",
            "type":"Services"
        }
    ],
    "sg:phone":"+1 707 428 5155",
    "sg:postcode":"95687",
    "sg:province":"CA",
    "wof:name":"Just The Finest Pest Mgmt",
    "wof:placetype":"venue"
},
  "geometry": {"coordinates":[-121.961449,38.338534],"type":"Point"}
}