{
  "type": "Feature",
  "properties": {
    "addr:full":"226 Vernon St Roseville CA 95678",
    "addr:housenumber":"226",
    "addr:postcode":"95678",
    "addr:street":"Vernon St",
    "iso:country":"US",
    "sg:address":"226 Vernon St",
    "sg:city":"Roseville",
    "sg:classifiers":[
        {
            "category":"Shopping",
            "subcategory":"Used Merchandise",
            "type":"Retail Goods"
        }
    ],
    "sg:phone":"+1 916 786 0146",
    "sg:postcode":"95678",
    "sg:province":"CA",
    "wof:name":"Davis Calkins Antiques",
    "wof:placetype":"venue"
},
  "geometry": {"coordinates":[-121.283827,38.749247],"type":"Point"}
}