{
  "type": "Feature",
  "properties": {
    "iso:country":"US",
    "sg:address":"1020 B St",
    "sg:city":"Fillmore",
    "sg:classifiers":[
        {
            "category":"Wholesale",
            "subcategory":"Construction Materials",
            "type":"Manufacturing & Wholesale Goods"
        },
        {
            "category":"Manufacturing",
            "subcategory":"Glass & Minerals",
            "type":"Manufacturing & Wholesale Goods"
        }
    ],
    "sg:phone":"+1 805 524 0223",
    "sg:postcode":"93015",
    "sg:province":"CA",
    "sg:tags":[
        "product",
        "concrete",
        "mfg",
        "l",
        "equipment",
        "pole",
        "lighting"
    ],
    "wof:name":"Ameron Pole Products & Systems",
    "wof:placetype":"venue"
},
  "geometry": {"coordinates":[-118.925669,34.412043],"type":"Point"}
}