{
  "type": "Feature",
  "properties": {
    "addr:full":"8942 Burton Way Beverly Hills CA 90211",
    "addr:housenumber":"8942",
    "addr:postcode":"90211",
    "addr:street":"Burton Way",
    "iso:country":"US",
    "sg:address":"8942 Burton Way",
    "sg:city":"Beverly Hills",
    "sg:classifiers":[
        {
            "category":"Communications",
            "subcategory":"Film & Video Production",
            "type":"Services"
        }
    ],
    "sg:phone":"+1 310 276 2149",
    "sg:postcode":"90211",
    "sg:province":"CA",
    "sg:tags":[
        "motion",
        "picture"
    ],
    "wof:name":"Importadora Inc",
    "wof:placetype":"venue"
},
  "geometry": {"coordinates":[-118.387241,34.07201],"type":"Point"}
}