{
  "type": "Feature",
  "properties": {
    "iso:country":"US",
    "sg:address":"1721 E San Bernardino Ave",
    "sg:city":"San Bernardino",
    "sg:classifiers":[
        {
            "category":"Farming",
            "subcategory":"Farm & Veterinary Services",
            "type":"Manufacturing & Wholesale Goods"
        }
    ],
    "sg:phone":"+1 909 793 2511",
    "sg:postcode":"92408",
    "sg:province":"CA",
    "sg:tags":[
        "management"
    ],
    "wof:name":"Redlands Farming Co",
    "wof:placetype":"venue"
},
  "geometry": {"coordinates":[-117.250913,34.077481],"type":"Point"}
}