{
  "type": "Feature",
  "properties": {
    "addr:full":"333 Thomsen Way Ramona CA 92065",
    "addr:housenumber":"333",
    "addr:postcode":"92065",
    "addr:street":"Thomsen Way",
    "iso:country":"US",
    "sg:address":"333 Thomsen Way",
    "sg:city":"Ramona",
    "sg:classifiers":[
        {
            "category":"Manufacturing",
            "subcategory":"Buildings",
            "type":"Manufacturing & Wholesale Goods"
        },
        {
            "category":"Building & Trades",
            "subcategory":"Construction",
            "type":"Services"
        }
    ],
    "sg:phone":"+1 760 789 0952",
    "sg:postcode":"92065",
    "sg:province":"CA",
    "sg:tags":[
        "excavation",
        "home",
        "builder",
        "contractor"
    ],
    "wof:name":"Big Heart Homes",
    "wof:placetype":"venue"
},
  "geometry": {"coordinates":[-116.854952,33.052099],"type":"Point"}
}