{
  "type": "Feature",
  "properties": {
    "iso:country":"US",
    "sg:address":"1160 N Vermont Ave",
    "sg:city":"Los Angeles",
    "sg:classifiers":[
        {
            "category":"Travel",
            "subcategory":"Hotels & Motels",
            "type":"Entertainment"
        }
    ],
    "sg:phone":"+1 323 660 1788",
    "sg:postcode":"90029",
    "sg:province":"CA",
    "wof:name":"Hollywood Hotel & Conference",
    "wof:placetype":"venue"
},
  "geometry": {"coordinates":[-118.291667,34.093232],"type":"Point"}
}