{
  "type": "Feature",
  "properties": {
    "iso:country":"US",
    "sg:address":"1158 G St",
    "sg:city":"Reedley",
    "sg:classifiers":[
        {
            "category":"Social Services",
            "type":"Services"
        }
    ],
    "sg:phone":"+1 559 638 1405",
    "sg:postcode":"93654",
    "sg:province":"CA",
    "sg:tags":[
        "counselor",
        "marriage",
        "family"
    ],
    "wof:name":"J David Bennett PHD",
    "wof:placetype":"venue"
},
  "geometry": {"coordinates":[-119.450288,36.596022],"type":"Point"}
}