{
  "type": "Feature",
  "properties": {
    "iso:country":"US",
    "sg:address":"1818 6th Ave",
    "sg:city":"San Diego",
    "sg:classifiers":[
        {
            "category":"Freight",
            "type":"Transportation"
        }
    ],
    "sg:phone":"+1 619 347 1571",
    "sg:postcode":"92101",
    "sg:province":"CA",
    "wof:name":"Stan Tenmohs Transportation",
    "wof:placetype":"venue"
},
  "geometry": {"coordinates":[-117.159503,32.72492],"type":"Point"}
}