{
  "type": "Feature",
  "properties": {
    "addr:full":"740 Jackson St. San Francisco CA 94133",
    "addr:housenumber":"740",
    "addr:postcode":"94133",
    "addr:street":"Jackson St.",
    "iso:country":"US",
    "sg:address":"740 Jackson St.",
    "sg:city":"San Francisco",
    "sg:classifiers":[
        {
            "category":"Banks & Credit Unions",
            "subcategory":"Financial Services",
            "type":"Services"
        }
    ],
    "sg:phone":"+1 415 956 3588",
    "sg:postcode":"94133",
    "sg:province":"CA",
    "wof:name":"Ming Y. Wu E. A.",
    "wof:placetype":"venue"
},
  "geometry": {"coordinates":[-122.407646,37.795937],"type":"Point"}
}