{
  "type": "Feature",
  "properties": {
    "addr:full":"1336 Park St Alameda CA 94501",
    "addr:housenumber":"1336",
    "addr:postcode":"94501",
    "addr:street":"Park St",
    "iso:country":"US",
    "sg:address":"1336 Park St",
    "sg:city":"Alameda",
    "sg:classifiers":[
        {
            "category":"Banks & Credit Unions",
            "subcategory":"Financial Services",
            "type":"Services"
        }
    ],
    "sg:phone":"+1 510 522 4046",
    "sg:postcode":"94501",
    "sg:province":"CA",
    "sg:tags":[
        "company",
        "holding"
    ],
    "wof:name":"Real American Restaurants",
    "wof:placetype":"venue"
},
  "geometry": {"coordinates":[-122.242796,37.764073],"type":"Point"}
}