{
  "type": "Feature",
  "properties": {
    "iso:country":"US",
    "sg:address":"115 S Taylor Ave",
    "sg:city":"Montebello",
    "sg:classifiers":[
        {
            "category":"Social Services",
            "subcategory":"Adult Care",
            "type":"Services"
        }
    ],
    "sg:phone":"+1 323 720 1079",
    "sg:postcode":"90640",
    "sg:province":"CA",
    "sg:tags":[
        "organization",
        "senior",
        "citizen"
    ],
    "wof:name":"Casa Maravilla Senior Citizens",
    "wof:placetype":"venue"
},
  "geometry": {"coordinates":[-118.114524,34.009706],"type":"Point"}
}