{
  "type": "Feature",
  "properties": {
    "addr:full":"1309 N Blackstone Ave Fresno CA 93704",
    "addr:housenumber":"1309",
    "addr:postcode":"93704",
    "addr:street":"N Blackstone Ave",
    "iso:country":"US",
    "sg:address":"1309 N Blackstone Ave",
    "sg:city":"Fresno",
    "sg:classifiers":[
        {
            "category":"Wholesale",
            "subcategory":"Hardware",
            "type":"Manufacturing & Wholesale Goods"
        }
    ],
    "sg:phone":"+1 559 497 6920",
    "sg:postcode":"93704",
    "sg:province":"CA",
    "sg:tags":[
        "refrigerating"
    ],
    "wof:name":"Glacier Refrigeration & Air",
    "wof:placetype":"venue"
},
  "geometry": {"coordinates":[-119.79061299999999,36.761231],"type":"Point"}
}