{
  "type": "Feature",
  "properties": {
    "iso:country":"US",
    "sg:address":"835 N Hacienda Blvd",
    "sg:city":"La Puente",
    "sg:classifiers":[
        {
            "category":"Health Services",
            "subcategory":"Doctor",
            "type":"Services"
        }
    ],
    "sg:phone":"+1 626 333 3384",
    "sg:postcode":"91744",
    "sg:province":"CA",
    "sg:tags":[
        "dentist"
    ],
    "wof:name":"Western Dental Ctr",
    "wof:placetype":"venue"
},
  "geometry": {"coordinates":[-117.95034,34.033748],"type":"Point"}
}