{
  "type": "Feature",
  "properties": {
    "iso:country":"US",
    "sg:address":"5077 Tifton Way",
    "sg:city":"San Jose",
    "sg:classifiers":[
        {
            "category":"Building & Trades",
            "subcategory":"Construction",
            "type":"Services"
        }
    ],
    "sg:phone":"+1 408 266 5859",
    "sg:postcode":"95118",
    "sg:province":"CA",
    "sg:tags":[
        "dry wall",
        "contractor"
    ],
    "wof:name":"A-1 Mechanical Drywall",
    "wof:placetype":"venue"
},
  "geometry": {"coordinates":[-121.886624,37.255975],"type":"Point"}
}