{
  "type": "Feature",
  "properties": {
    "iso:country":"US",
    "sg:address":"1651 Placentia Ave",
    "sg:city":"Costa Mesa",
    "sg:classifiers":[
        {
            "category":"Personal",
            "type":"Services"
        }
    ],
    "sg:phone":"+1 714 409 0495",
    "sg:postcode":"92627",
    "sg:province":"CA",
    "sg:tags":[
        "mover"
    ],
    "wof:name":"Sam Movers",
    "wof:placetype":"venue"
},
  "geometry": {"coordinates":[-117.9325,33.634527],"type":"Point"}
}