{
  "type": "Feature",
  "properties": {
    "addr:full":"2810 Azevedo Dr Sacramento CA 95833",
    "addr:housenumber":"2810",
    "addr:postcode":"95833",
    "addr:street":"Azevedo Dr",
    "iso:country":"US",
    "sg:address":"2810 Azevedo Dr",
    "sg:city":"Sacramento",
    "sg:classifiers":[
        {
            "category":"Autos & Motor Vehicles",
            "subcategory":"Automobile Sales",
            "type":"Retail Goods"
        }
    ],
    "sg:phone":"+1 916 929 2917",
    "sg:postcode":"95833",
    "sg:province":"CA",
    "sg:tags":[
        "car",
        "used",
        "cars-wholesale",
        "dealers-used"
    ],
    "wof:name":"Mason Auto Sales",
    "wof:placetype":"venue"
},
  "geometry": {"coordinates":[-121.506668,38.616637],"type":"Point"}
}