{
  "type": "Feature",
  "properties": {
    "iso:country":"US",
    "sg:address":"9454 Wilshire Boulevard Ph",
    "sg:city":"Beverly Hills",
    "sg:classifiers":[
        {
            "category":"Professional",
            "subcategory":"Lawyer & Legal Services",
            "type":"Services"
        }
    ],
    "sg:phone":"+1 310 859 1502",
    "sg:postcode":"90212",
    "sg:province":"CA",
    "wof:name":"Bell Louis I A Professional Corporation. Atty",
    "wof:placetype":"venue"
},
  "geometry": {"coordinates":[-118.39938600000001,34.067108],"type":"Point"}
}