{
  "type": "Feature",
  "properties": {
    "addr:full":"910 Camarillo Center Dr Ste 800 Camarillo CA 93010",
    "addr:housenumber":"910",
    "addr:postcode":"93010",
    "addr:street":"Camarillo Center Dr Ste 800",
    "iso:country":"US",
    "sg:address":"910 Camarillo Center Dr Ste 800",
    "sg:city":"Camarillo",
    "sg:classifiers":[
        {
            "category":"Shopping",
            "subcategory":"Computers & Home Electronics",
            "type":"Retail Goods"
        }
    ],
    "sg:phone":"+1 805 389 9592",
    "sg:postcode":"93010",
    "sg:province":"CA",
    "wof:name":"Sony Electronics Inc.",
    "wof:placetype":"venue"
},
  "geometry": {"coordinates":[-119.062945,34.215154],"type":"Point"}
}