{
  "type": "Feature",
  "properties": {
    "addr:full":"2687 Park Ave. Ste E Tustin CA 92782",
    "addr:housenumber":"2687",
    "addr:postcode":"92782",
    "addr:street":"Park Ave. Ste E",
    "iso:country":"US",
    "sg:address":"2687 Park Ave. Ste E",
    "sg:city":"Tustin",
    "sg:classifiers":[
        {
            "category":"Shopping",
            "subcategory":"Computers & Home Electronics",
            "type":"Retail Goods"
        }
    ],
    "sg:phone":"+1 714 258 8870",
    "sg:postcode":"92782",
    "sg:province":"CA",
    "sg:website":"www.verizonwireless.com/b2c/disp...",
    "wof:name":"Verizon Store",
    "wof:placetype":"venue"
},
  "geometry": {"coordinates":[-117.82517199999999,33.698017],"type":"Point"}
}