{
  "type": "Feature",
  "properties": {
    "addr:full":"4903 E Kings Canyon Rd Fresno CA 93727",
    "addr:housenumber":"4903",
    "addr:postcode":"93727",
    "addr:street":"E Kings Canyon Rd",
    "iso:country":"US",
    "sg:address":"4903 E Kings Canyon Rd",
    "sg:city":"Fresno",
    "sg:classifiers":[
        {
            "category":"Restaurant",
            "type":"Food & Drink"
        },
        {
            "category":"Food & Beverages",
            "subcategory":"Ethnic Foods",
            "type":"Retail Goods"
        }
    ],
    "sg:phone":"+1 559 454 1762",
    "sg:postcode":"93727",
    "sg:province":"CA",
    "sg:tags":[
        "style",
        "pan",
        "asian",
        "family",
        "vietnamese"
    ],
    "wof:name":"Pho Phuong Nine Restaurant",
    "wof:placetype":"venue"
},
  "geometry": {"coordinates":[-119.731408,36.736005],"type":"Point"}
}