{
  "type": "Feature",
  "properties": {
    "addr:full":"95 Alameda St Vallejo CA 94590",
    "addr:housenumber":"95",
    "addr:postcode":"94590",
    "addr:street":"Alameda St",
    "iso:country":"US",
    "sg:address":"95 Alameda St",
    "sg:city":"Vallejo",
    "sg:classifiers":[
        {
            "category":"Local Transit",
            "type":"Transportation"
        }
    ],
    "sg:phone":"+1 707 552 9900",
    "sg:postcode":"94590",
    "sg:province":"CA",
    "wof:name":"Vallejo Airport Shuttle",
    "wof:placetype":"venue"
},
  "geometry": {"coordinates":[-122.24847200000001,38.096606],"type":"Point"}
}