{
  "type": "Feature",
  "properties": {
    "addr:full":"501 Geary St San Francisco CA 94102",
    "addr:housenumber":"501",
    "addr:postcode":"94102",
    "addr:street":"Geary St",
    "iso:country":"US",
    "sg:address":"501 Geary St",
    "sg:city":"San Francisco",
    "sg:classifiers":[
        {
            "category":"Real Estate",
            "subcategory":"Real Estate Services",
            "type":"Services"
        }
    ],
    "sg:postcode":"94102",
    "sg:province":"CA",
    "sg:website":"tenantscreeningbackgroundcheck.com/",
    "wof:name":"Tenant Background Check",
    "wof:placetype":"venue"
},
  "geometry": {"coordinates":[-122.411591,37.786763],"type":"Point"}
}