{
  "type": "Feature",
  "properties": {
    "iso:country":"US",
    "sg:address":"4201 Manzanita Ave",
    "sg:city":"Carmichael",
    "sg:classifiers":[
        {
            "category":"Shopping",
            "subcategory":"Clothing, Apparel, & Fashions",
            "type":"Retail Goods"
        }
    ],
    "sg:phone":"+1 916 485 9422",
    "sg:postcode":"95608",
    "sg:province":"CA",
    "sg:tags":[
        "children's",
        "clothing"
    ],
    "wof:name":"Baby Bazaar",
    "wof:placetype":"venue"
},
  "geometry": {"coordinates":[-121.328003,38.6408],"type":"Point"}
}