{
  "type": "Feature",
  "properties": {
    "addr:full":"35 S Raymond Ave Pasadena CA 91105",
    "addr:housenumber":"35",
    "addr:postcode":"91105",
    "addr:street":"S Raymond Ave",
    "iso:country":"US",
    "sg:address":"35 S Raymond Ave",
    "sg:city":"Pasadena",
    "sg:classifiers":[
        {
            "category":"Building & Trades",
            "subcategory":"Construction",
            "type":"Services"
        }
    ],
    "sg:phone":"+1 626 796 7462",
    "sg:postcode":"91105",
    "sg:province":"CA",
    "sg:tags":[
        "contractor"
    ],
    "wof:name":"Howard Building Corp",
    "wof:placetype":"venue"
},
  "geometry": {"coordinates":[-118.149035,34.144971],"type":"Point"}
}