{
  "type": "Feature",
  "properties": {
    "addr:full":"28615 Matadero Creek Ct Los Altos Hills CA 94022",
    "addr:postcode":"28615;94022",
    "addr:street":"Matadero Creek Ct",
    "iso:country":"US",
    "sg:address":"28615 Matadero Creek Ct",
    "sg:city":"Los Altos Hills",
    "sg:classifiers":[
        {
            "category":"Professional",
            "subcategory":"Business Services",
            "type":"Services"
        }
    ],
    "sg:phone":"+1 650 949 1414",
    "sg:postcode":"94022",
    "sg:province":"CA",
    "sg:tags":[
        "interior",
        "consultant",
        "design",
        "decorator"
    ],
    "wof:name":"Pamela Kapoor Interiors",
    "wof:placetype":"venue"
},
  "geometry": {"coordinates":[-122.162131,37.370423],"type":"Point"}
}