{
  "type": "Feature",
  "properties": {
    "iso:country":"US",
    "sg:address":"11678 W Olympic Blvd",
    "sg:city":"Los Angeles",
    "sg:classifiers":[
        {
            "category":"Restaurant",
            "type":"Food & Drink"
        }
    ],
    "sg:phone":"+1 310 478 3090",
    "sg:postcode":"90064",
    "sg:province":"CA",
    "sg:tags":[
        "japanese"
    ],
    "wof:name":"Raku Restaurant",
    "wof:placetype":"venue"
},
  "geometry": {"coordinates":[-118.44764499999999,34.034363],"type":"Point"}
}