{
  "type": "Feature",
  "properties": {
    "addr:full":"331 N Oakhurst Dr Beverly Hills CA 90210",
    "addr:housenumber":"331",
    "addr:postcode":"90210",
    "addr:street":"N Oakhurst Dr",
    "iso:country":"US",
    "sg:address":"331 N Oakhurst Dr",
    "sg:city":"Beverly Hills",
    "sg:classifiers":[
        {
            "category":"Recreation",
            "type":"Entertainment"
        }
    ],
    "sg:phone":"+1 310 859 9724",
    "sg:postcode":"90210",
    "sg:province":"CA",
    "sg:tags":[
        "instruction",
        "yoga"
    ],
    "wof:name":"Maui Yoga",
    "wof:placetype":"venue"
},
  "geometry": {"coordinates":[-118.39103,34.075195],"type":"Point"}
}