{
  "type": "Feature",
  "properties": {
    "iso:country":"US",
    "sg:address":"2824 Illinois Ave",
    "sg:city":"Modesto",
    "sg:classifiers":[
        {
            "category":"Farming",
            "subcategory":"Livestock Farm",
            "type":"Manufacturing & Wholesale Goods"
        }
    ],
    "sg:phone":"+1 209 529 6650",
    "sg:postcode":"95358",
    "sg:province":"CA",
    "sg:tags":[
        "animal",
        "general"
    ],
    "wof:name":"Hi River Ranch",
    "wof:placetype":"venue"
},
  "geometry": {"coordinates":[-121.066755,37.603589],"type":"Point"}
}