{
  "type": "Feature",
  "properties": {
    "addr:full":"2520 W West View Street Los Angeles CA 90016",
    "addr:housenumber":"2520",
    "addr:postcode":"90016",
    "addr:street":"W West View Street",
    "iso:country":"US",
    "sg:address":"2520 W West View Street",
    "sg:city":"Los Angeles",
    "sg:classifiers":[
        {
            "category":"Arts & Performance",
            "subcategory":"Art Gallery",
            "type":"Entertainment"
        }
    ],
    "sg:phone":"+1 323 734 1164",
    "sg:postcode":"90016",
    "sg:province":"CA",
    "wof:name":"William Grant Still Community Arts Center",
    "wof:placetype":"venue"
},
  "geometry": {"coordinates":[-118.348292,34.03306],"type":"Point"}
}