{
  "type": "Feature",
  "properties": {
    "addr:full":"2400 W Coast Hwy Ste 10 Newport Beach CA 92663",
    "addr:housenumber":"2400",
    "addr:postcode":"92663",
    "addr:street":"W Coast Hwy Ste 10",
    "iso:country":"US",
    "sg:address":"2400 W Coast Hwy Ste 10",
    "sg:city":"Newport Beach",
    "sg:classifiers":[
        {
            "category":"Building & Trades",
            "subcategory":"Construction",
            "type":"Services"
        }
    ],
    "sg:phone":"+1 949 645 5666",
    "sg:postcode":"92663",
    "sg:province":"CA",
    "sg:tags":[
        "contractor"
    ],
    "wof:name":"General Contractor",
    "wof:placetype":"venue"
},
  "geometry": {"coordinates":[-117.921578,33.61923],"type":"Point"}
}