{
  "type": "Feature",
  "properties": {
    "addr:full":"8826 W Olympic Boulevard Beverly Hills CA 90211",
    "addr:housenumber":"8826",
    "addr:postcode":"90211",
    "addr:street":"W Olympic Boulevard",
    "iso:country":"US",
    "sg:address":"8826 W Olympic Boulevard",
    "sg:city":"Beverly Hills",
    "sg:classifiers":[
        {
            "category":"Real Estate",
            "subcategory":"Real Estate Services",
            "type":"Services"
        }
    ],
    "sg:phone":"+1 310 273 5213",
    "sg:postcode":"90211",
    "sg:province":"CA",
    "sg:tags":[
        "management",
        "property"
    ],
    "wof:name":"Green Acres Investments",
    "wof:placetype":"venue"
},
  "geometry": {"coordinates":[-118.384522,34.059491],"type":"Point"}
}