{
  "type": "Feature",
  "properties": {
    "iso:country":"US",
    "sg:address":"7244 East Pkwy",
    "sg:city":"Sacramento",
    "sg:classifiers":[
        {
            "category":"Real Estate",
            "subcategory":"Real Estate Operator",
            "type":"Services"
        }
    ],
    "sg:phone":"+1 916 428 4398",
    "sg:postcode":"95823",
    "sg:province":"CA",
    "sg:tags":[
        "apartment"
    ],
    "wof:name":"Townhouse South Apartments",
    "wof:placetype":"venue"
},
  "geometry": {"coordinates":[-121.451396,38.495883],"type":"Point"}
}