{
  "type": "Feature",
  "properties": {
    "addr:full":"165 Parson Ln Oroville CA 95966",
    "addr:housenumber":"165",
    "addr:postcode":"95966",
    "addr:street":"Parson Ln",
    "iso:country":"US",
    "sg:address":"165 Parson Ln",
    "sg:city":"Oroville",
    "sg:classifiers":[
        {
            "category":"Real Estate",
            "subcategory":"Real Estate Agent",
            "type":"Services"
        }
    ],
    "sg:phone":"+1 530 532 4693",
    "sg:postcode":"95966",
    "sg:province":"CA",
    "wof:name":"Benchmark of California",
    "wof:placetype":"venue"
},
  "geometry": {"coordinates":[-121.504306,39.495222],"type":"Point"}
}