{
  "type": "Feature",
  "properties": {
    "iso:country":"US",
    "sg:address":"922 Capri Dr",
    "sg:city":"Vista",
    "sg:classifiers":[
        {
            "category":"Insurance",
            "subcategory":"Insurance Agent",
            "type":"Services"
        }
    ],
    "sg:phone":"+1 760 941 9465",
    "sg:postcode":"92084",
    "sg:province":"CA",
    "wof:name":"Emerald Discount Medical",
    "wof:placetype":"venue"
},
  "geometry": {"coordinates":[-117.230144,33.207522],"type":"Point"}
}