{
  "type": "Feature",
  "properties": {
    "addr:full":"800 N Blackstone Ave Fresno CA 93701",
    "addr:housenumber":"800",
    "addr:postcode":"93701",
    "addr:street":"N Blackstone Ave",
    "iso:country":"US",
    "sg:address":"800 N Blackstone Ave",
    "sg:city":"Fresno",
    "sg:classifiers":[
        {
            "category":"Freight",
            "type":"Transportation"
        }
    ],
    "sg:phone":"+1 559 233 3022",
    "sg:postcode":"93701",
    "sg:province":"CA",
    "sg:tags":[
        "general"
    ],
    "wof:name":"Harvey Storage",
    "wof:placetype":"venue"
},
  "geometry": {"coordinates":[-119.79053500000001,36.754066],"type":"Point"}
}