{
  "type": "Feature",
  "properties": {
    "iso:country":"US",
    "sg:address":"23343 Mulholland Dr",
    "sg:city":"Woodland Hills",
    "sg:classifiers":[
        {
            "category":"Home & Garden",
            "subcategory":"Home Furnishings",
            "type":"Retail Goods"
        }
    ],
    "sg:phone":"+1 818 222 2724",
    "sg:postcode":"91364",
    "sg:province":"CA",
    "sg:tags":[
        "glass",
        "bedding",
        "stained",
        "window"
    ],
    "wof:name":"Sgo Design",
    "wof:placetype":"venue"
},
  "geometry": {"coordinates":[-118.632503,34.153493],"type":"Point"}
}