{
  "type": "Feature",
  "properties": {
    "addr:full":"21012 Lacebark Ln Mission Viejo CA 92691",
    "addr:postcode":"21012;92691",
    "addr:street":"Lacebark Ln",
    "iso:country":"US",
    "sg:address":"21012 Lacebark Ln",
    "sg:city":"Mission Viejo",
    "sg:classifiers":[
        {
            "category":"Personal",
            "type":"Services"
        }
    ],
    "sg:phone":"+1 949 637 7222",
    "sg:postcode":"92691",
    "sg:province":"CA",
    "sg:tags":[
        "home"
    ],
    "wof:name":"Top Crew Construction",
    "wof:placetype":"venue"
},
  "geometry": {"coordinates":[-117.64347100000001,33.658083],"type":"Point"}
}