{
  "type": "Feature",
  "properties": {
    "addr:full":"489 Muerer St Folsom CA 95630",
    "addr:housenumber":"489",
    "addr:postcode":"95630",
    "addr:street":"Muerer St",
    "iso:country":"US",
    "sg:address":"489 Muerer St",
    "sg:city":"Folsom",
    "sg:classifiers":[
        {
            "category":"Professional",
            "subcategory":"Secretarial Services",
            "type":"Services"
        }
    ],
    "sg:phone":"+1 916 355 8698",
    "sg:postcode":"95630",
    "sg:province":"CA",
    "sg:tags":[
        "reporting",
        "court"
    ],
    "wof:name":"Cooper Business Svc",
    "wof:placetype":"venue"
},
  "geometry": {"coordinates":[-121.152889,38.655992],"type":"Point"}
}