{
  "type": "Feature",
  "properties": {
    "iso:country":"US",
    "sg:address":"1000 8th St",
    "sg:city":"Monterey",
    "sg:classifiers":[
        {
            "category":"Building & Trades",
            "subcategory":"Landscaping Services",
            "type":"Services"
        }
    ],
    "sg:phone":"+1 831 646 0900",
    "sg:postcode":"93940",
    "sg:province":"CA",
    "sg:tags":[
        "designer",
        "landscape"
    ],
    "wof:name":"Richard Murray Associates",
    "wof:placetype":"venue"
},
  "geometry": {"coordinates":[-121.880855,36.594181],"type":"Point"}
}