{
  "type": "Feature",
  "properties": {
    "iso:country":"US",
    "sg:address":"428 E 2nd St",
    "sg:city":"Los Angeles",
    "sg:classifiers":[
        {
            "category":"Bars & Pubs",
            "type":"Food & Drink"
        },
        {
            "category":"Bars & Pubs",
            "subcategory":"Wine Bar",
            "type":"Food & Drink"
        }
    ],
    "sg:phone":"+1 213 628 8877",
    "sg:postcode":"90012",
    "sg:province":"CA",
    "sg:tags":[
        "tapa"
    ],
    "sg:website":"www.barc.biz",
    "wof:name":"Tapas and Wine Bar C",
    "wof:placetype":"venue"
},
  "geometry": {"coordinates":[-118.239006,34.04747],"type":"Point"}
}