{
  "type": "Feature",
  "properties": {
    "addr:full":"268 Manfre Rd Watsonville CA 95076",
    "addr:housenumber":"268",
    "addr:postcode":"95076",
    "addr:street":"Manfre Rd",
    "iso:country":"US",
    "sg:address":"268 Manfre Rd",
    "sg:city":"Watsonville",
    "sg:classifiers":[
        {
            "category":"Freight",
            "type":"Transportation"
        }
    ],
    "sg:phone":"+1 831 768 8057",
    "sg:postcode":"95076",
    "sg:province":"CA",
    "wof:name":"Nunez Transportation",
    "wof:placetype":"venue"
},
  "geometry": {"coordinates":[-121.797765,36.937416],"type":"Point"}
}