{
  "type": "Feature",
  "properties": {
    "iso:country":"US",
    "sg:address":"23 Kentucky St",
    "sg:city":"Petaluma",
    "sg:classifiers":[
        {
            "category":"Restaurant",
            "type":"Food & Drink"
        }
    ],
    "sg:menulink":"http://www.allmenus.com/ca/petaluma/54366-preferred-sonoma-caterers/menu/",
    "sg:phone":"+1 707 769 7208",
    "sg:postcode":"94952",
    "sg:province":"CA",
    "sg:tags":[
        "american"
    ],
    "wof:name":"Preferred Sonoma Caterers",
    "wof:placetype":"venue"
},
  "geometry": {"coordinates":[-122.640775,38.233163],"type":"Point"}
}