{
  "type": "Feature",
  "properties": {
    "iso:country":"US",
    "sg:address":"100 W Glenoaks Blvd",
    "sg:city":"Glendale",
    "sg:classifiers":[
        {
            "category":"Restaurant",
            "type":"Food & Drink"
        }
    ],
    "sg:phone":"+1 818 551 4074",
    "sg:postcode":"91202",
    "sg:province":"CA",
    "sg:tags":[
        "steakhouse"
    ],
    "sg:website":"www1.hilton.com/en_US/hi/hotel/B...",
    "wof:name":"Porter's Prime Steakhouse",
    "wof:placetype":"venue"
},
  "geometry": {"coordinates":[-118.25528300000001,34.15927],"type":"Point"}
}