{
  "type": "Feature",
  "properties": {
    "addr:full":"6800 Mowry Ave Newark CA 94560",
    "addr:housenumber":"6800",
    "addr:postcode":"94560",
    "addr:street":"Mowry Ave",
    "iso:country":"US",
    "sg:address":"6800 Mowry Ave",
    "sg:city":"Newark",
    "sg:classifiers":[
        {
            "category":"Government",
            "subcategory":"Office",
            "type":"Public Place"
        }
    ],
    "sg:phone":"+1 510 742 4400",
    "sg:postcode":"94560",
    "sg:province":"CA",
    "sg:tags":[
        "village"
    ],
    "wof:name":"George M Silliman Family Aqtc",
    "wof:placetype":"venue"
},
  "geometry": {"coordinates":[-122.012103,37.515625],"type":"Point"}
}