{
  "type": "Feature",
  "properties": {
    "addr:full":"4225 Prunedale Ave Gilroy CA 95020",
    "addr:postcode":"4225;95020",
    "addr:street":"Prunedale Ave",
    "iso:country":"US",
    "sg:address":"4225 Prunedale Ave",
    "sg:city":"Gilroy",
    "sg:classifiers":[
        {
            "category":"Wholesale",
            "subcategory":"Farm Supplies",
            "type":"Manufacturing & Wholesale Goods"
        }
    ],
    "sg:phone":"+1 650 851 4666",
    "sg:postcode":"95020",
    "sg:province":"CA",
    "sg:tags":[
        "feed"
    ],
    "wof:name":"Horse's Mouth",
    "wof:placetype":"venue"
},
  "geometry": {"coordinates":[-121.487494,36.999842],"type":"Point"}
}