{
  "type": "Feature",
  "properties": {
    "iso:country":"US",
    "sg:address":"407 S Tehama St",
    "sg:city":"Willows",
    "sg:classifiers":[
        {
            "category":"Personal",
            "subcategory":"Beauty Salon",
            "type":"Services"
        }
    ],
    "sg:phone":"+1 530 934 7674",
    "sg:postcode":"95988",
    "sg:province":"CA",
    "wof:name":"Benamati J & S",
    "wof:placetype":"venue"
},
  "geometry": {"coordinates":[-122.193871,39.516732],"type":"Point"}
}