{
  "type": "Feature",
  "properties": {
    "addr:full":"155 Steuart St San Francisco CA 94105",
    "addr:housenumber":"155",
    "addr:postcode":"94105",
    "addr:street":"Steuart St",
    "iso:country":"US",
    "sg:address":"155 Steuart St",
    "sg:city":"San Francisco",
    "sg:classifiers":[
        {
            "category":"Travel",
            "subcategory":"Hotels & Motels",
            "type":"Entertainment"
        }
    ],
    "sg:phone":"+1 415 495 2100",
    "sg:postcode":"94105",
    "sg:province":"CA",
    "sg:website":"www.hotelgriffon.com",
    "wof:name":"Hotel Griffon",
    "wof:placetype":"venue"
},
  "geometry": {"coordinates":[-122.392206,37.792878],"type":"Point"}
}