{
  "type": "Feature",
  "properties": {
    "addr:full":"22 E 25th Ave San Mateo CA 94403",
    "addr:housenumber":"22",
    "addr:postcode":"94403",
    "addr:street":"E 25Th Ave",
    "iso:country":"US",
    "sg:address":"22 E 25th Ave",
    "sg:city":"San Mateo",
    "sg:classifiers":[
        {
            "category":"Shopping",
            "subcategory":"Books",
            "type":"Retail Goods"
        }
    ],
    "sg:phone":"+1 650 574 5377",
    "sg:postcode":"94403",
    "sg:province":"CA",
    "sg:tags":[
        "bookstore"
    ],
    "wof:name":"Books Unlimited",
    "wof:placetype":"venue"
},
  "geometry": {"coordinates":[-122.305342,37.544696],"type":"Point"}
}