{
  "type": "Feature",
  "properties": {
    "iso:country":"US",
    "sg:address":"6101 Enterprise Dr",
    "sg:city":"Diamond Springs",
    "sg:classifiers":[
        {
            "category":"Manufacturing",
            "subcategory":"Tools & Machinery",
            "type":"Manufacturing & Wholesale Goods"
        }
    ],
    "sg:phone":"+1 530 626 3520",
    "sg:postcode":"95619",
    "sg:province":"CA",
    "sg:tags":[
        "machine",
        "shop"
    ],
    "wof:name":"Bravo Machining",
    "wof:placetype":"venue"
},
  "geometry": {"coordinates":[-120.83030599999999,38.694158],"type":"Point"}
}