{
  "type": "Feature",
  "properties": {
    "iso:country":"US",
    "sg:address":"20543 Gunstock Rd",
    "sg:city":"Grass Valley",
    "sg:classifiers":[
        {
            "category":"Building & Trades",
            "subcategory":"Construction",
            "type":"Services"
        }
    ],
    "sg:phone":"+1 530 346 9796",
    "sg:postcode":"95949",
    "sg:province":"CA",
    "sg:tags":[
        "splicing",
        "cable"
    ],
    "wof:name":"All Power Electric",
    "wof:placetype":"venue"
},
  "geometry": {"coordinates":[-121.008138,39.075356],"type":"Point"}
}