{
  "type": "Feature",
  "properties": {
    "iso:country":"US",
    "sg:address":"141 S Elm St",
    "sg:city":"Arroyo Grande",
    "sg:classifiers":[
        {
            "category":"Professional",
            "subcategory":"Engineering",
            "type":"Services"
        }
    ],
    "sg:phone":"+1 805 489 1321",
    "sg:postcode":"93420",
    "sg:province":"CA",
    "sg:tags":[
        "engineer"
    ],
    "wof:name":"Garing Taylor & Assoc Inc",
    "wof:placetype":"venue"
},
  "geometry": {"coordinates":[-120.600366,35.119019],"type":"Point"}
}