{
  "type": "Feature",
  "properties": {
    "iso:country":"US",
    "sg:address":"2303 E Florence Avenue",
    "sg:city":"Huntington Park",
    "sg:classifiers":[
        {
            "category":"Restaurant",
            "type":"Food & Drink"
        }
    ],
    "sg:phone":"+1 323 587 2449",
    "sg:postcode":"90255",
    "sg:province":"CA",
    "wof:name":"McDonald's Restaurants",
    "wof:placetype":"venue"
},
  "geometry": {"coordinates":[-118.231145,33.974876],"type":"Point"}
}