{
  "type": "Feature",
  "properties": {
    "iso:country":"US",
    "sg:address":"1259 N San Gorgonio Ave",
    "sg:city":"Banning",
    "sg:classifiers":[
        {
            "category":"Building & Trades",
            "subcategory":"Construction",
            "type":"Services"
        }
    ],
    "sg:phone":"+1 951 922 8171",
    "sg:postcode":"92220",
    "sg:province":"CA",
    "sg:tags":[
        "tile",
        "dealer"
    ],
    "wof:name":"Capps Tile",
    "wof:placetype":"venue"
},
  "geometry": {"coordinates":[-116.876856,33.936771],"type":"Point"}
}