{
  "type": "Feature",
  "properties": {
    "iso:country":"US",
    "sg:address":"400 Main St",
    "sg:city":"Pleasanton",
    "sg:classifiers":[
        {
            "category":"Wholesale",
            "subcategory":"Non-durable Goods",
            "type":"Manufacturing & Wholesale Goods"
        }
    ],
    "sg:phone":"+1 925 846 1127",
    "sg:postcode":"94566",
    "sg:province":"CA",
    "sg:tags":[
        "advertising"
    ],
    "wof:name":"Classic Promotions",
    "wof:placetype":"venue"
},
  "geometry": {"coordinates":[-121.875866,37.6605],"type":"Point"}
}