{
  "type": "Feature",
  "properties": {
    "iso:country":"US",
    "sg:address":"9205 Folsom Blvd",
    "sg:city":"Sacramento",
    "sg:classifiers":[
        {
            "category":"Restaurant",
            "type":"Food & Drink"
        }
    ],
    "sg:phone":"+1 916 364 7811",
    "sg:postcode":"95826",
    "sg:province":"CA",
    "wof:name":"Mi Rak Restaurant",
    "wof:placetype":"venue"
},
  "geometry": {"coordinates":[-121.354342,38.563531],"type":"Point"}
}