{
  "type": "Feature",
  "properties": {
    "iso:country":"US",
    "sg:address":"7533 W Goshen Ave",
    "sg:city":"Visalia",
    "sg:classifiers":[
        {
            "category":"Building & Trades",
            "subcategory":"Construction",
            "type":"Services"
        }
    ],
    "sg:phone":"+1 559 635 0300",
    "sg:postcode":"93291",
    "sg:province":"CA",
    "sg:tags":[
        "contractor",
        "nonresidential"
    ],
    "wof:name":"Tricon Building Solutions Inc",
    "wof:placetype":"venue"
},
  "geometry": {"coordinates":[-119.39845099999999,36.341949],"type":"Point"}
}