{
  "type": "Feature",
  "properties": {
    "iso:country":"US",
    "sg:address":"705 University Ave",
    "sg:city":"Sacramento",
    "sg:classifiers":[
        {
            "category":"Professional",
            "subcategory":"Lawyer & Legal Services",
            "type":"Services"
        }
    ],
    "sg:phone":"+1 916 568 6000",
    "sg:postcode":"95825",
    "sg:province":"CA",
    "wof:name":"Bernstein Richard P Wanland & Bernsten Lw Offcs of",
    "wof:placetype":"venue"
},
  "geometry": {"coordinates":[-121.418999,38.566502],"type":"Point"}
}