{
  "type": "Feature",
  "properties": {
    "addr:full":"2619 Balls Ferry Rd Anderson CA 96007",
    "addr:housenumber":"2619",
    "addr:postcode":"96007",
    "addr:street":"Balls Ferry Rd",
    "iso:country":"US",
    "sg:address":"2619 Balls Ferry Rd",
    "sg:city":"Anderson",
    "sg:classifiers":[
        {
            "category":"Shopping",
            "subcategory":"Tobacco",
            "type":"Retail Goods"
        }
    ],
    "sg:phone":"+1 530 365 1626",
    "sg:postcode":"96007",
    "sg:province":"CA",
    "sg:tags":[
        "cigarette",
        "cigar",
        "dealer"
    ],
    "wof:name":"Tobacco & More",
    "wof:placetype":"venue"
},
  "geometry": {"coordinates":[-122.282731,40.456647],"type":"Point"}
}