{
  "type": "Feature",
  "properties": {
    "addr:full":"4835 Van Nuys Blvd Sherman Oaks CA 91403",
    "addr:housenumber":"4835",
    "addr:postcode":"91403",
    "addr:street":"Van Nuys Blvd",
    "iso:country":"US",
    "sg:address":"4835 Van Nuys Blvd",
    "sg:city":"Sherman Oaks",
    "sg:classifiers":[
        {
            "category":"Health Services",
            "subcategory":"Doctor",
            "type":"Services"
        }
    ],
    "sg:phone":"+1 818 906 9805",
    "sg:postcode":"91403",
    "sg:province":"CA",
    "sg:tags":[
        "physician",
        "surgeon"
    ],
    "wof:name":"Salila Sharma MD",
    "wof:placetype":"venue"
},
  "geometry": {"coordinates":[-118.44877200000001,34.159135],"type":"Point"}
}