{
  "type": "Feature",
  "properties": {
    "iso:country":"US",
    "sg:address":"9108 Laguna Main St",
    "sg:city":"Elk Grove",
    "sg:classifiers":[
        {
            "category":"Health Services",
            "subcategory":"Podiatrist",
            "type":"Services"
        }
    ],
    "sg:phone":"+1 916 683 1287",
    "sg:postcode":"95758",
    "sg:province":"CA",
    "wof:name":"Godfrey F Mix DPM",
    "wof:placetype":"venue"
},
  "geometry": {"coordinates":[-121.47011500000001,38.425312],"type":"Point"}
}