{
  "type": "Feature",
  "properties": {
    "addr:full":"8939 S Sepulveda Blvd Ste 102 Los Angeles CA 90045",
    "addr:housenumber":"8939",
    "addr:postcode":"90045",
    "addr:street":"S Sepulveda Blvd Ste 102",
    "iso:country":"US",
    "sg:address":"8939 S Sepulveda Blvd Ste 102",
    "sg:city":"Los Angeles",
    "sg:classifiers":[
        {
            "category":"Banks & Credit Unions",
            "subcategory":"Financial Services",
            "type":"Services"
        }
    ],
    "sg:phone":"+1 323 264 4651",
    "sg:postcode":"90045",
    "sg:province":"CA",
    "wof:name":"Miago Enterprises Inc",
    "wof:placetype":"venue"
},
  "geometry": {"coordinates":[-118.396507,33.954874],"type":"Point"}
}