{
  "type": "Feature",
  "properties": {
    "iso:country":"US",
    "sg:address":"19742 MacArthur Boulevard",
    "sg:city":"Irvine",
    "sg:classifiers":[
        {
            "category":"Organizations",
            "subcategory":"Religious Organization",
            "type":"Services"
        }
    ],
    "sg:phone":"+1 949 955 2220",
    "sg:postcode":"92612",
    "sg:province":"CA",
    "wof:name":"Tirabassi Roger Pastoral Counselor",
    "wof:placetype":"venue"
},
  "geometry": {"coordinates":[-117.862617,33.657456],"type":"Point"}
}