{
  "type": "Feature",
  "properties": {
    "iso:country":"US",
    "sg:address":"500 N Azusa Ave",
    "sg:city":"West Covina",
    "sg:classifiers":[
        {
            "category":"Shopping",
            "type":"Retail Goods"
        }
    ],
    "sg:phone":"+1 626 331 3322",
    "sg:postcode":"91791",
    "sg:province":"CA",
    "sg:tags":[
        "telephone",
        "cellular"
    ],
    "wof:name":"IPCS Sprint",
    "wof:placetype":"venue"
},
  "geometry": {"coordinates":[-117.907742,34.079186],"type":"Point"}
}