{
  "type": "Feature",
  "properties": {
    "iso:country":"US",
    "sg:address":"5550 Telegraph Rd",
    "sg:city":"Ventura",
    "sg:classifiers":[
        {
            "category":"Professional",
            "subcategory":"Lawyer & Legal Services",
            "type":"Services"
        }
    ],
    "sg:phone":"+1 805 644 9523",
    "sg:postcode":"93003",
    "sg:province":"CA",
    "sg:tags":[
        "attorney"
    ],
    "wof:name":"Cathy Bozek",
    "wof:placetype":"venue"
},
  "geometry": {"coordinates":[-119.220035,34.277065],"type":"Point"}
}