{
  "type": "Feature",
  "properties": {
    "addr:full":"3516 W Slauson Ave Los Angeles CA 90043",
    "addr:housenumber":"3516",
    "addr:postcode":"90043",
    "addr:street":"W Slauson Ave",
    "iso:country":"US",
    "sg:address":"3516 W Slauson Ave",
    "sg:city":"Los Angeles",
    "sg:classifiers":[
        {
            "category":"Retail",
            "subcategory":"Auto Repair",
            "type":"Services"
        }
    ],
    "sg:phone":"+1 323 293 7067",
    "sg:postcode":"90043",
    "sg:province":"CA",
    "wof:name":"C C Auto Service",
    "wof:placetype":"venue"
},
  "geometry": {"coordinates":[-118.334,33.989101],"type":"Point"}
}