{
  "type": "Feature",
  "properties": {
    "addr:full":"816 Marguerite Way Petaluma CA 94954",
    "addr:housenumber":"816",
    "addr:postcode":"94954",
    "addr:street":"Marguerite Way",
    "iso:country":"US",
    "sg:address":"816 Marguerite Way",
    "sg:city":"Petaluma",
    "sg:classifiers":[
        {
            "category":"Wholesale",
            "subcategory":"Medical Equipment & Supplies",
            "type":"Manufacturing & Wholesale Goods"
        },
        {
            "category":"Retail",
            "subcategory":"Repair Shop",
            "type":"Services"
        }
    ],
    "sg:phone":"+1 707 315 8604",
    "sg:postcode":"94954",
    "sg:province":"CA",
    "sg:tags":[
        "physician",
        "surgeon",
        "refinishing",
        "equipment-repairing"
    ],
    "wof:name":"Harris Medical",
    "wof:placetype":"venue"
},
  "geometry": {"coordinates":[-122.60960300000001,38.246929],"type":"Point"}
}