{
  "type": "Feature",
  "properties": {
    "iso:country":"US",
    "sg:address":"2505 E Cesar E Chavez Avenue",
    "sg:city":"Los Angeles",
    "sg:classifiers":[
        {
            "category":"Health Services",
            "subcategory":"Chiropractor",
            "type":"Services"
        }
    ],
    "sg:phone":"+1 323 265 3503",
    "sg:postcode":"90033",
    "sg:province":"CA",
    "wof:name":"Chacon Manuel DC",
    "wof:placetype":"venue"
},
  "geometry": {"coordinates":[-118.205601,34.045959],"type":"Point"}
}