{
  "type": "Feature",
  "properties": {
    "iso:country":"US",
    "sg:address":"3516 W 3rd St",
    "sg:city":"Los Angeles",
    "sg:classifiers":[
        {
            "category":"Personal",
            "subcategory":"Beauty Salon",
            "type":"Services"
        }
    ],
    "sg:phone":"+1 213 388 6751",
    "sg:postcode":"90020",
    "sg:province":"CA",
    "wof:name":"Myo Beauty Salon",
    "wof:placetype":"venue"
},
  "geometry": {"coordinates":[-118.29243700000001,34.068974],"type":"Point"}
}