{
  "type": "Feature",
  "properties": {
    "iso:country":"US",
    "sg:address":"3250 Lomita Blvd",
    "sg:city":"Torrance",
    "sg:classifiers":[
        {
            "category":"Health Services",
            "subcategory":"Doctor",
            "type":"Services"
        }
    ],
    "sg:phone":"+1 310 534 8110",
    "sg:postcode":"90505",
    "sg:province":"CA",
    "sg:tags":[
        "physician",
        "surgeon"
    ],
    "wof:name":"David S Ruderman Inc",
    "wof:placetype":"venue"
},
  "geometry": {"coordinates":[-118.34433199999999,33.812794],"type":"Point"}
}