{
  "type": "Feature",
  "properties": {
    "addr:full":"24714 Crenshaw Blvd Torrance CA 90505",
    "addr:housenumber":"24714",
    "addr:postcode":"90505",
    "addr:street":"Crenshaw Blvd",
    "iso:country":"US",
    "sg:address":"24714 Crenshaw Blvd",
    "sg:city":"Torrance",
    "sg:classifiers":[
        {
            "category":"Retail",
            "subcategory":"Auto Repair",
            "type":"Services"
        }
    ],
    "sg:phone":"+1 310 326 7470",
    "sg:postcode":"90505",
    "sg:province":"CA",
    "sg:tags":[
        "wheel",
        "axle",
        "alignment"
    ],
    "wof:name":"H & H Wheel Alignment & Brake",
    "wof:placetype":"venue"
},
  "geometry": {"coordinates":[-118.328219,33.800291],"type":"Point"}
}