{
  "type": "Feature",
  "properties": {
    "addr:full":"7530 Orangethorpe Ave Buena Park CA 90621",
    "addr:housenumber":"7530",
    "addr:postcode":"90621",
    "addr:street":"Orangethorpe Ave",
    "iso:country":"US",
    "sg:address":"7530 Orangethorpe Ave",
    "sg:city":"Buena Park",
    "sg:classifiers":[
        {
            "category":"Health Services",
            "subcategory":"Chiropractor",
            "type":"Services"
        }
    ],
    "sg:phone":"+1 714 994 5242",
    "sg:postcode":"90621",
    "sg:province":"CA",
    "wof:name":"The Chiropractic Medical Rehabilitation Center",
    "wof:placetype":"venue"
},
  "geometry": {"coordinates":[-118.00091,33.857341],"type":"Point"}
}