{
  "type": "Feature",
  "properties": {
    "addr:full":"3934 Mount Ainsworth Ave San Diego CA 92111",
    "addr:housenumber":"3934",
    "addr:postcode":"92111",
    "addr:street":"Mount Ainsworth Ave",
    "iso:country":"US",
    "sg:address":"3934 Mount Ainsworth Ave",
    "sg:city":"San Diego",
    "sg:classifiers":[
        {
            "category":"Wholesale",
            "subcategory":"Vending Machines",
            "type":"Manufacturing & Wholesale Goods"
        }
    ],
    "sg:phone":"+1 858 573 0776",
    "sg:postcode":"92111",
    "sg:province":"CA",
    "sg:tags":[
        "operator"
    ],
    "wof:name":"Lanuzo & Assoc Vending",
    "wof:placetype":"venue"
},
  "geometry": {"coordinates":[-117.174689,32.816054],"type":"Point"}
}