{
  "type": "Feature",
  "properties": {
    "addr:full":"52655 Ave Velasco La Quinta CA 92253",
    "addr:housenumber":"52655",
    "addr:postcode":"92253",
    "addr:street":"Ave Velasco",
    "iso:country":"US",
    "sg:address":"52655 Ave Velasco",
    "sg:city":"La Quinta",
    "sg:classifiers":[
        {
            "category":"Building & Trades",
            "subcategory":"Construction",
            "type":"Services"
        }
    ],
    "sg:phone":"+1 760 771 9244",
    "sg:postcode":"92253",
    "sg:province":"CA",
    "sg:tags":[
        "dry wall",
        "contractor"
    ],
    "wof:name":"LA Roca Drywall Inc",
    "wof:placetype":"venue"
},
  "geometry": {"coordinates":[-116.30902,33.666596],"type":"Point"}
}