{
  "type": "Feature",
  "properties": {
    "iso:country":"US",
    "sg:address":"101 5th St",
    "sg:city":"Hollister",
    "sg:classifiers":[
        {
            "category":"Professional",
            "subcategory":"Accounting & Tax Preparation",
            "type":"Services"
        }
    ],
    "sg:phone":"+1 831 637 2353",
    "sg:postcode":"95023",
    "sg:province":"CA",
    "sg:tags":[
        "accountant"
    ],
    "wof:name":"Thomas E Olsen CPA",
    "wof:placetype":"venue"
},
  "geometry": {"coordinates":[-121.40105,36.851431],"type":"Point"}
}