{
  "type": "Feature",
  "properties": {
    "addr:full":"1401 7th Ave San Francisco CA 94122",
    "addr:housenumber":"1401",
    "addr:postcode":"94122",
    "addr:street":"7Th Ave",
    "iso:country":"US",
    "sg:address":"1401 7th Ave",
    "sg:city":"San Francisco",
    "sg:classifiers":[
        {
            "category":"Professional",
            "subcategory":"Lawyer & Legal Services",
            "type":"Services"
        }
    ],
    "sg:phone":"+1 415 564 2480",
    "sg:postcode":"94122",
    "sg:province":"CA",
    "sg:tags":[
        "notary"
    ],
    "sg:website":"www.InnerSunsetNotary.com",
    "wof:name":"Ruth L. Moffatt -Notary Public",
    "wof:placetype":"venue"
},
  "geometry": {"coordinates":[-122.464326,37.762112],"type":"Point"}
}