{
  "type": "Feature",
  "properties": {
    "addr:full":"100 1st St San Francisco CA 94105",
    "addr:housenumber":"100",
    "addr:postcode":"94105",
    "addr:street":"1St St",
    "iso:country":"US",
    "sg:address":"100 1st St",
    "sg:city":"San Francisco",
    "sg:classifiers":[
        {
            "category":"Professional",
            "subcategory":"Computer Services",
            "type":"Services"
        }
    ],
    "sg:phone":"+1 415 288 9470",
    "sg:postcode":"94105",
    "sg:province":"CA",
    "sg:tags":[
        "repair"
    ],
    "sg:website":"www.sweetmemory.com",
    "wof:name":"SWEET Memory",
    "wof:placetype":"venue"
},
  "geometry": {"coordinates":[-122.397035,37.789333],"type":"Point"}
}