{
  "type": "Feature",
  "properties": {
    "addr:full":"1300 S Euclid St Anaheim CA 92802",
    "addr:housenumber":"1300",
    "addr:postcode":"92802",
    "addr:street":"S Euclid St",
    "iso:country":"US",
    "sg:address":"1300 S Euclid St",
    "sg:city":"Anaheim",
    "sg:classifiers":[
        {
            "category":"Shopping",
            "subcategory":"Music",
            "type":"Retail Goods"
        }
    ],
    "sg:phone":"+1 714 991 8678",
    "sg:postcode":"92802",
    "sg:province":"CA",
    "sg:tags":[
        "dvd's"
    ],
    "wof:name":"D F Records Fiebre Musical",
    "wof:placetype":"venue"
},
  "geometry": {"coordinates":[-117.941002,33.816101],"type":"Point"}
}