{
  "type": "Feature",
  "properties": {
    "addr:full":"1123 G St Reedley CA 93654",
    "addr:housenumber":"1123",
    "addr:postcode":"93654",
    "addr:street":"G St",
    "iso:country":"US",
    "sg:address":"1123 G St",
    "sg:city":"Reedley",
    "sg:classifiers":[
        {
            "category":"Education",
            "subcategory":"Dance Studio",
            "type":"Public Place"
        }
    ],
    "sg:phone":"+1 559 638 9828",
    "sg:postcode":"93654",
    "sg:province":"CA",
    "sg:tags":[
        "instruction",
        "dancing"
    ],
    "wof:name":"Reedley Ballet & Arts Studio",
    "wof:placetype":"venue"
},
  "geometry": {"coordinates":[-119.45008799999999,36.595556],"type":"Point"}
}