{
  "type": "Feature",
  "properties": {
    "addr:full":"14701 Burbank Blvd Sherman Oaks CA 91411",
    "addr:housenumber":"14701",
    "addr:postcode":"91411",
    "addr:street":"Burbank Blvd",
    "iso:country":"US",
    "sg:address":"14701 Burbank Blvd",
    "sg:city":"Sherman Oaks",
    "sg:classifiers":[
        {
            "category":"Social Services",
            "subcategory":"Child Care",
            "type":"Services"
        }
    ],
    "sg:phone":"+1 818 781 2327",
    "sg:postcode":"91411",
    "sg:province":"CA",
    "sg:website":"www.happybearschool.com",
    "wof:name":"Happy Bear School",
    "wof:placetype":"venue"
},
  "geometry": {"coordinates":[-118.454162,34.172114],"type":"Point"}
}