{
  "type": "Feature",
  "properties": {
    "addr:full":"796 E. Washington Blvd. Los Angeles CA 90021",
    "addr:housenumber":"796",
    "addr:postcode":"90021",
    "addr:street":"E. Washington Blvd.",
    "iso:country":"US",
    "sg:address":"796 E. Washington Blvd.",
    "sg:city":"Los Angeles",
    "sg:classifiers":[
        {
            "category":"Building & Trades",
            "subcategory":"Cleaning & Sanitation",
            "type":"Services"
        }
    ],
    "sg:phone":"+1 213 745 9955",
    "sg:postcode":"90021",
    "sg:province":"CA",
    "sg:tags":[
        "home"
    ],
    "sg:website":"www.mollymaid.com/local-house-cl...",
    "wof:name":"Molly Maid",
    "wof:placetype":"venue"
},
  "geometry": {"coordinates":[-118.254689,34.026061],"type":"Point"}
}