{
  "type": "Feature",
  "properties": {
    "addr:full":"1351 E. Hatch Rd. Modesto CA 95351",
    "addr:housenumber":"1351",
    "addr:postcode":"ca 95351",
    "addr:street":"E. Hatch Rd.",
    "iso:country":"US",
    "sg:address":"1351 E. Hatch Rd.",
    "sg:city":"Modesto",
    "sg:classifiers":[
        {
            "category":"Shopping",
            "subcategory":"Department Store",
            "type":"Retail Goods"
        }
    ],
    "sg:phone":"+1 209 521 9610",
    "sg:postcode":"95351",
    "sg:province":"CA",
    "sg:website":"www.kmart.com/",
    "wof:name":"Kmart",
    "wof:placetype":"venue"
},
  "geometry": {"coordinates":[-120.972966,37.610341],"type":"Point"}
}