{
  "type": "Feature",
  "properties": {
    "addr:full":"2382 Faraday Ave Ste 160 Carlsbad CA 92008",
    "addr:housenumber":"2382",
    "addr:postcode":"92008",
    "addr:street":"Faraday Ave Ste 160",
    "iso:country":"US",
    "sg:address":"2382 Faraday Ave Ste 160",
    "sg:city":"Carlsbad",
    "sg:classifiers":[
        {
            "category":"Real Estate",
            "subcategory":"Real Estate Agent",
            "type":"Services"
        }
    ],
    "sg:phone":"+1 760 828 4400",
    "sg:postcode":"92008",
    "sg:province":"CA",
    "sg:website":"www.century21award.com",
    "wof:name":"CENTURY 21 Award - Carlsbad",
    "wof:placetype":"venue"
},
  "geometry": {"coordinates":[-117.274841,33.136475],"type":"Point"}
}