{
  "type": "Feature",
  "properties": {
    "iso:country":"US",
    "sg:address":"8081 Larson Ave",
    "sg:city":"Garden Grove",
    "sg:classifiers":[
        {
            "category":"Professional",
            "type":"Services"
        }
    ],
    "sg:phone":"+1 714 926 6220",
    "sg:postcode":"92844",
    "sg:province":"CA",
    "wof:name":"Mario D Judy",
    "wof:placetype":"venue"
},
  "geometry": {"coordinates":[-117.98622899999999,33.772095],"type":"Point"}
}