{
  "type": "Feature",
  "properties": {
    "addr:full":"23367 Mulholland Dr Woodland Hills CA 91364",
    "addr:housenumber":"23367",
    "addr:postcode":"91364",
    "addr:street":"Mulholland Dr",
    "iso:country":"US",
    "sg:address":"23367 Mulholland Dr",
    "sg:city":"Woodland Hills",
    "sg:classifiers":[
        {
            "category":"Shopping",
            "subcategory":"Pets & Pet Supplies",
            "type":"Retail Goods"
        }
    ],
    "sg:phone":"+1 818 222 9119",
    "sg:postcode":"91364",
    "sg:province":"CA",
    "sg:tags":[
        "store"
    ],
    "wof:name":"Pet Life",
    "wof:placetype":"venue"
},
  "geometry": {"coordinates":[-118.636002,34.158199],"type":"Point"}
}