{
  "type": "Feature",
  "properties": {
    "iso:country":"US",
    "sg:address":"2266 Davie Ave",
    "sg:city":"Los Angeles",
    "sg:classifiers":[
        {
            "category":"Professional",
            "subcategory":"Business Services",
            "type":"Services"
        }
    ],
    "sg:phone":"+1 323 720 5000",
    "sg:postcode":"90040",
    "sg:province":"CA",
    "wof:name":"Vasquez Richard M",
    "wof:placetype":"venue"
},
  "geometry": {"coordinates":[-118.135667,34.002023],"type":"Point"}
}