{
  "type": "Feature",
  "properties": {
    "iso:country":"US",
    "sg:address":"3640 Lomita Blvd",
    "sg:city":"Torrance",
    "sg:classifiers":[
        {
            "category":"Health Services",
            "subcategory":"Doctor",
            "type":"Services"
        }
    ],
    "sg:phone":"+1 310 791 4100",
    "sg:postcode":"90505",
    "sg:province":"CA",
    "sg:tags":[
        "dentist"
    ],
    "wof:name":"Jerry T Clement Inc",
    "wof:placetype":"venue"
},
  "geometry": {"coordinates":[-118.350982,33.815868],"type":"Point"}
}