{
  "type": "Feature",
  "properties": {
    "iso:country":"US",
    "sg:address":"1333 Lincoln Ave",
    "sg:city":"Calistoga",
    "sg:classifiers":[
        {
            "category":"Shopping",
            "type":"Retail Goods"
        }
    ],
    "sg:phone":"+1 707 942 6347",
    "sg:postcode":"94515",
    "sg:province":"CA",
    "sg:tags":[
        "art",
        "gallery",
        "dealer"
    ],
    "wof:name":"Main Element",
    "wof:placetype":"venue"
},
  "geometry": {"coordinates":[-122.579176,38.578356],"type":"Point"}
}