{
  "type": "Feature",
  "properties": {
    "iso:country":"US",
    "sg:address":"1680 The Alameda",
    "sg:city":"San Jose",
    "sg:classifiers":[
        {
            "category":"Health Services",
            "subcategory":"Chiropractor",
            "type":"Services"
        }
    ],
    "sg:phone":"+1 408 872 0858",
    "sg:postcode":"95126",
    "sg:province":"CA",
    "wof:name":"Saratoga Healing Arts Ctr",
    "wof:placetype":"venue"
},
  "geometry": {"coordinates":[-121.918171,37.336729],"type":"Point"}
}