{
  "type": "Feature",
  "properties": {
    "iso:country":"US",
    "sg:address":"325 Santa Barbara Ave",
    "sg:city":"Modesto",
    "sg:classifiers":[
        {
            "category":"Professional",
            "subcategory":"Research",
            "type":"Services"
        }
    ],
    "sg:phone":"+1 510 266 0966",
    "sg:postcode":"95354",
    "sg:province":"CA",
    "sg:tags":[
        "environmental",
        "ecological"
    ],
    "wof:name":"Vironex Environmental Field",
    "wof:placetype":"venue"
},
  "geometry": {"coordinates":[-120.975522,37.643066],"type":"Point"}
}