{
  "type": "Feature",
  "properties": {
    "iso:country":"US",
    "sg:address":"227 E Arrellaga St",
    "sg:city":"Santa Barbara",
    "sg:classifiers":[
        {
            "category":"Utilities",
            "subcategory":"Telephone",
            "type":"Services"
        }
    ],
    "sg:phone":"+1 805 966 2377",
    "sg:postcode":"93101",
    "sg:province":"CA",
    "sg:tags":[
        "company"
    ],
    "wof:name":"Meditation By Phone",
    "wof:placetype":"venue"
},
  "geometry": {"coordinates":[-119.706479,34.430044],"type":"Point"}
}