{
  "type": "Feature",
  "properties": {
    "addr:full":"355 Troon Way Half Moon Bay CA 94019",
    "addr:housenumber":"355",
    "addr:postcode":"94019",
    "addr:street":"Troon Way",
    "iso:country":"US",
    "sg:address":"355 Troon Way",
    "sg:city":"Half Moon Bay",
    "sg:classifiers":[
        {
            "category":"Shopping",
            "subcategory":"Computers & Home Electronics",
            "type":"Retail Goods"
        }
    ],
    "sg:phone":"+1 650 560 9397",
    "sg:postcode":"94019",
    "sg:province":"CA",
    "sg:tags":[
        "publishing"
    ],
    "sg:website":"www.marynelson.com",
    "wof:name":"Mary Nelson Documents/Graphics",
    "wof:placetype":"venue"
},
  "geometry": {"coordinates":[-122.42733200000001,37.432233],"type":"Point"}
}