{
  "type": "Feature",
  "properties": {
    "iso:country":"US",
    "sg:address":"109 Ainsworth Way",
    "sg:city":"Folsom",
    "sg:classifiers":[
        {
            "category":"Building & Trades",
            "subcategory":"Electrical",
            "type":"Services"
        }
    ],
    "sg:phone":"+1 916 984 2169",
    "sg:postcode":"95630",
    "sg:province":"CA",
    "sg:tags":[
        "electrical",
        "electric",
        "contractor"
    ],
    "wof:name":"Electrical Service Specialties",
    "wof:placetype":"venue"
},
  "geometry": {"coordinates":[-121.135048,38.6731],"type":"Point"}
}