{
  "type": "Feature",
  "properties": {
    "iso:country":"US",
    "sg:address":"950 S Coast Dr Ste 204",
    "sg:city":"Costa Mesa",
    "sg:classifiers":[
        {
            "category":"Health Services",
            "subcategory":"Doctor",
            "type":"Services"
        }
    ],
    "sg:phone":"+1 714 556 5004",
    "sg:postcode":"92626",
    "sg:province":"CA",
    "sg:website":"www.areymd.com",
    "wof:name":"Britton Ashley Arey, MD, MBA",
    "wof:placetype":"venue"
},
  "geometry": {"coordinates":[-117.896502,33.6899],"type":"Point"}
}