{
  "type": "Feature",
  "properties": {
    "addr:full":"120 N L St Tulare CA 93274",
    "addr:housenumber":"120",
    "addr:postcode":"93274",
    "addr:street":"N L St",
    "iso:country":"US",
    "sg:address":"120 N L St",
    "sg:city":"Tulare",
    "sg:classifiers":[
        {
            "category":"Social Services",
            "type":"Services"
        }
    ],
    "sg:phone":"+1 559 303 3636",
    "sg:postcode":"93274",
    "sg:province":"CA",
    "sg:tags":[
        "counselor",
        "marriage",
        "family"
    ],
    "wof:name":"Scott Underwood",
    "wof:placetype":"venue"
},
  "geometry": {"coordinates":[-119.345004,36.209237],"type":"Point"}
}