{
  "type": "Feature",
  "properties": {
    "addr:full":"888 S Disneyland Dr Ste 500 Anaheim CA 92802",
    "addr:housenumber":"888",
    "addr:postcode":"92802",
    "addr:street":"S Disneyland Dr Ste 500",
    "iso:country":"US",
    "sg:address":"888 S Disneyland Dr Ste 500",
    "sg:city":"Anaheim",
    "sg:classifiers":[
        {
            "category":"Banks & Credit Unions",
            "subcategory":"Bank",
            "type":"Services"
        }
    ],
    "sg:phone":"+1 323 890 9946",
    "sg:postcode":"92802",
    "sg:province":"CA",
    "sg:website":"www.bancopopular.com",
    "wof:name":"Banco Popular",
    "wof:placetype":"venue"
},
  "geometry": {"coordinates":[-117.922479,33.819921],"type":"Point"}
}