{
  "type": "Feature",
  "properties": {
    "iso:country":"US",
    "sg:address":"2416 Telegraph Ave",
    "sg:city":"Berkeley",
    "sg:classifiers":[
        {
            "category":"Shopping",
            "type":"Retail Goods"
        }
    ],
    "sg:phone":"+1 510 841 6187",
    "sg:postcode":"94704",
    "sg:province":"CA",
    "sg:tags":[
        "shop",
        "gift",
        "adult",
        "incense"
    ],
    "sg:website":"www.AnnapurnaLive.com",
    "wof:name":"Annapurna",
    "wof:placetype":"venue"
},
  "geometry": {"coordinates":[-122.258724,37.866532],"type":"Point"}
}