{
  "type": "Feature",
  "properties": {
    "iso:country":"US",
    "sg:address":"405 N Muller St",
    "sg:city":"Anaheim",
    "sg:classifiers":[
        {
            "category":"Manufacturing",
            "subcategory":"Tools & Machinery",
            "type":"Manufacturing & Wholesale Goods"
        }
    ],
    "sg:phone":"+1 714 956 6000",
    "sg:postcode":"92801",
    "sg:province":"CA",
    "sg:tags":[
        "computer",
        "maintenance",
        "sales",
        "related",
        "mfg"
    ],
    "wof:name":"H N Bull Information Systems",
    "wof:placetype":"venue"
},
  "geometry": {"coordinates":[-117.950253,33.837428],"type":"Point"}
}