{
  "type": "Feature",
  "properties": {
    "addr:full":"6151 W Century Blvd Los Angeles CA 90045",
    "addr:housenumber":"6151",
    "addr:postcode":"90045",
    "addr:street":"W Century Blvd",
    "iso:country":"US",
    "sg:address":"6151 W Century Blvd",
    "sg:city":"Los Angeles",
    "sg:classifiers":[
        {
            "category":"Professional",
            "subcategory":"Management & Consulting",
            "type":"Services"
        }
    ],
    "sg:phone":"+1 310 670 1400",
    "sg:postcode":"90045",
    "sg:province":"CA",
    "sg:tags":[
        "consultant",
        "business"
    ],
    "sg:website":"www.bradleylambert.com",
    "wof:name":"Bradley-Lambert Inc",
    "wof:placetype":"venue"
},
  "geometry": {"coordinates":[-118.39211,33.945638],"type":"Point"}
}