{
  "type": "Feature",
  "properties": {
    "addr:full":"425 W 8th Street Los Angeles CA 90014",
    "addr:housenumber":"425",
    "addr:postcode":"90014",
    "addr:street":"W 8Th Street",
    "iso:country":"US",
    "sg:address":"425 W 8th Street",
    "sg:city":"Los Angeles",
    "sg:classifiers":[
        {
            "category":"Retail",
            "subcategory":"Event Space",
            "type":"Services"
        }
    ],
    "sg:phone":"+1 213 623 4607",
    "sg:postcode":"90014",
    "sg:province":"CA",
    "sg:tags":[
        "venue"
    ],
    "wof:name":"El Gaucho",
    "wof:placetype":"venue"
},
  "geometry": {"coordinates":[-118.256455,34.044773],"type":"Point"}
}