{
  "type": "Feature",
  "properties": {
    "iso:country":"US",
    "sg:address":"1744 6th Ave",
    "sg:city":"San Diego",
    "sg:classifiers":[
        {
            "category":"Professional",
            "subcategory":"Lawyer & Legal Services",
            "type":"Services"
        }
    ],
    "sg:phone":"+1 619 231 9323",
    "sg:postcode":"92101",
    "sg:province":"CA",
    "wof:name":"Kretzschmar Leigh Law Office of",
    "wof:placetype":"venue"
},
  "geometry": {"coordinates":[-117.159673,32.723477],"type":"Point"}
}