{
  "type": "Feature",
  "properties": {
    "iso:country":"US",
    "sg:address":"2823 Helm Ave",
    "sg:city":"Clovis",
    "sg:classifiers":[
        {
            "category":"Organizations",
            "subcategory":"Community Association",
            "type":"Services"
        }
    ],
    "sg:phone":"+1 559 294 1946",
    "sg:postcode":"93612",
    "sg:province":"CA",
    "sg:tags":[
        "fraternal"
    ],
    "wof:name":"Independent Order-Odd Fellows",
    "wof:placetype":"venue"
},
  "geometry": {"coordinates":[-119.722603,36.800809],"type":"Point"}
}