{
  "type": "Feature",
  "properties": {
    "addr:full":"9200 Gazette Ave Chatsworth CA 91311",
    "addr:housenumber":"9200",
    "addr:postcode":"91311",
    "addr:street":"Gazette Ave",
    "iso:country":"US",
    "sg:address":"9200 Gazette Ave",
    "sg:city":"Chatsworth",
    "sg:classifiers":[
        {
            "category":"Manufacturing",
            "subcategory":"Glass & Minerals",
            "type":"Manufacturing & Wholesale Goods"
        }
    ],
    "sg:phone":"+1 818 772 7744",
    "sg:postcode":"91311",
    "sg:province":"CA",
    "sg:tags":[
        "structural"
    ],
    "sg:website":"www.ultraglas.com",
    "wof:name":"Ultraglas Inc",
    "wof:placetype":"venue"
},
  "geometry": {"coordinates":[-118.58708799999999,34.237784],"type":"Point"}
}