{
  "type": "Feature",
  "properties": {
    "iso:country":"US",
    "sg:address":"7 Three Sevens Ln",
    "sg:city":"Chico",
    "sg:classifiers":[
        {
            "category":"Manufacturing",
            "subcategory":"Food",
            "type":"Manufacturing & Wholesale Goods"
        }
    ],
    "sg:phone":"+1 530 894 6048",
    "sg:postcode":"95973",
    "sg:province":"CA",
    "sg:tags":[
        "desert",
        "ice",
        "mfg"
    ],
    "wof:name":"Frozen Gourmet Inc",
    "wof:placetype":"venue"
},
  "geometry": {"coordinates":[-121.887717,39.785285],"type":"Point"}
}