{
  "type": "Feature",
  "properties": {
    "iso:country":"US",
    "sg:address":"1592 S Imperial Ave",
    "sg:city":"El Centro",
    "sg:classifiers":[
        {
            "category":"Health Services",
            "subcategory":"Doctor",
            "type":"Services"
        }
    ],
    "sg:phone":"+1 760 351 3633",
    "sg:postcode":"92243",
    "sg:province":"CA",
    "sg:tags":[
        "physician",
        "surgeon"
    ],
    "wof:name":"Edgar A Gamboa MD",
    "wof:placetype":"venue"
},
  "geometry": {"coordinates":[-115.569696,32.779483],"type":"Point"}
}