{
  "type": "Feature",
  "properties": {
    "addr:full":"23142 Gainford St Woodland Hills CA 91364",
    "addr:housenumber":"23142",
    "addr:postcode":"91364",
    "addr:street":"Gainford St",
    "iso:country":"US",
    "sg:address":"23142 Gainford St",
    "sg:city":"Woodland Hills",
    "sg:classifiers":[
        {
            "category":"Wholesale",
            "subcategory":"Home Furnishings",
            "type":"Manufacturing & Wholesale Goods"
        }
    ],
    "sg:phone":"+1 818 222 1988",
    "sg:postcode":"91364",
    "sg:province":"CA",
    "wof:name":"Arnolds Custom Interior",
    "wof:placetype":"venue"
},
  "geometry": {"coordinates":[-118.628868,34.160429],"type":"Point"}
}