{
  "type": "Feature",
  "properties": {
    "iso:country":"US",
    "sg:address":"9338 S Painter Ave",
    "sg:city":"Whittier",
    "sg:classifiers":[
        {
            "category":"Government",
            "subcategory":"City Hall",
            "type":"Public Place"
        }
    ],
    "sg:phone":"+1 800 777 0133",
    "sg:postcode":"90605",
    "sg:province":"CA",
    "sg:website":"www.dmv.ca.gov",
    "wof:name":"Department of Motor Vehicles",
    "wof:placetype":"venue"
},
  "geometry": {"coordinates":[-118.043478,33.952572],"type":"Point"}
}