{
  "type": "Feature",
  "properties": {
    "addr:full":"2740 S Bristol St Ste 107 Santa Ana CA 92704",
    "addr:housenumber":"2740",
    "addr:postcode":"92704",
    "addr:street":"S Bristol St Ste 107",
    "iso:country":"US",
    "sg:address":"2740 S Bristol St Ste 107",
    "sg:city":"Santa Ana",
    "sg:classifiers":[
        {
            "category":"Health Services",
            "subcategory":"Dentist",
            "type":"Services"
        }
    ],
    "sg:phone":"+1 714 556 7000",
    "sg:postcode":"92704",
    "sg:province":"CA",
    "wof:name":"South Coast Oral Surgery",
    "wof:placetype":"venue"
},
  "geometry": {"coordinates":[-117.885566,33.710627],"type":"Point"}
}