{
  "type": "Feature",
  "properties": {
    "iso:country":"US",
    "sg:address":"635 Bair Island Rd",
    "sg:city":"Redwood City",
    "sg:classifiers":[
        {
            "category":"Manufacturing",
            "subcategory":"Pottery",
            "type":"Manufacturing & Wholesale Goods"
        },
        {
            "category":"Shopping",
            "subcategory":"Gifts & Souvenirs",
            "type":"Retail Goods"
        }
    ],
    "sg:phone":"+1 650 366 0677",
    "sg:postcode":"94063",
    "sg:province":"CA",
    "sg:tags":[
        "basket",
        "product",
        "parcel",
        "mfg"
    ],
    "wof:name":"Traychic",
    "wof:placetype":"venue"
},
  "geometry": {"coordinates":[-122.223975,37.497193],"type":"Point"}
}