{
  "type": "Feature",
  "properties": {
    "addr:full":"6001 Sonoma Hwy Santa Rosa CA 95409",
    "addr:housenumber":"6001",
    "addr:postcode":"95409",
    "addr:street":"Sonoma Hwy",
    "iso:country":"US",
    "sg:address":"6001 Sonoma Hwy",
    "sg:city":"Santa Rosa",
    "sg:classifiers":[
        {
            "category":"Building & Trades",
            "subcategory":"Equipment Rental",
            "type":"Services"
        }
    ],
    "sg:phone":"+1 707 537 6917",
    "sg:postcode":"95409",
    "sg:province":"CA",
    "sg:tags":[
        "yard"
    ],
    "wof:name":"Rental Place",
    "wof:placetype":"venue"
},
  "geometry": {"coordinates":[-122.62598,38.455035],"type":"Point"}
}