{
  "type": "Feature",
  "properties": {
    "iso:country":"US",
    "sg:address":"14435 Sherman Way",
    "sg:city":"Van Nuys",
    "sg:classifiers":[
        {
            "category":"Wholesale",
            "subcategory":"Medical Equipment & Supplies",
            "type":"Manufacturing & Wholesale Goods"
        }
    ],
    "sg:phone":"+1 818 787 2827",
    "sg:postcode":"91405",
    "sg:province":"CA",
    "sg:tags":[
        "physician",
        "surgeon"
    ],
    "wof:name":"ITC Medical Supply",
    "wof:placetype":"venue"
},
  "geometry": {"coordinates":[-118.44837200000001,34.201267],"type":"Point"}
}