{
  "type": "Feature",
  "properties": {
    "addr:full":"800 Madison St Oakland CA 94607",
    "addr:housenumber":"800",
    "addr:postcode":"94607",
    "addr:street":"Madison St",
    "iso:country":"US",
    "sg:address":"800 Madison St",
    "sg:city":"Oakland",
    "sg:classifiers":[
        {
            "category":"Local Transit",
            "type":"Transportation"
        }
    ],
    "sg:phone":"+1 510 465 2278",
    "sg:postcode":"94607",
    "sg:province":"CA",
    "sg:tags":[
        "line"
    ],
    "wof:name":"Rapid Transit District",
    "wof:placetype":"venue"
},
  "geometry": {"coordinates":[-122.266237,37.798089],"type":"Point"}
}