{
  "type": "Feature",
  "properties": {
    "addr:full":"21740 Co Rd 88 Winters CA 95694",
    "addr:housenumber":"21740;88",
    "addr:postcode":"95694",
    "addr:street":"Co Rd",
    "iso:country":"US",
    "sg:address":"21740 Co Rd 88",
    "sg:city":"Winters",
    "sg:phone":"+1 530 662 4570",
    "sg:postcode":"95694",
    "sg:province":"CA",
    "sg:tags":[
        "grass",
        "grows",
        "native"
    ],
    "wof:name":"Hedgerow Farms",
    "wof:placetype":"venue"
},
  "geometry": {"coordinates":[-121.989906,38.623905],"type":"Point"}
}