{
  "type": "Feature",
  "properties": {
    "addr:full":"455 Canyon del Rey Blvd Monterey CA 93940",
    "addr:housenumber":"455",
    "addr:postcode":"93940",
    "addr:street":"Canyon Del Rey Blvd",
    "iso:country":"US",
    "sg:address":"455 Canyon del Rey Blvd",
    "sg:city":"Monterey",
    "sg:classifiers":[
        {
            "category":"Professional",
            "subcategory":"Advertising",
            "type":"Services"
        }
    ],
    "sg:phone":"+1 831 583 9000",
    "sg:postcode":"93940",
    "sg:province":"CA",
    "sg:tags":[
        "mailing",
        "shipping"
    ],
    "wof:name":"UPS Store",
    "wof:placetype":"venue"
},
  "geometry": {"coordinates":[-121.82995,36.584872],"type":"Point"}
}