{
  "type": "Feature",
  "properties": {
    "addr:full":"39200 S Highway 1 Gualala CA 95445",
    "addr:housenumber":"39200",
    "addr:postcode":"95445",
    "addr:street":"S Highway 1",
    "iso:country":"US",
    "sg:address":"39200 S Highway 1",
    "sg:city":"Gualala",
    "sg:classifiers":[
        {
            "category":"Shopping",
            "subcategory":"Clothing, Apparel, & Fashions",
            "type":"Retail Goods"
        },
        {
            "category":"Shopping",
            "subcategory":"Gifts & Souvenirs",
            "type":"Retail Goods"
        }
    ],
    "sg:phone":"+1 707 884 1320",
    "sg:postcode":"95445",
    "sg:province":"CA",
    "sg:tags":[
        "shop",
        "apparel",
        "clothing",
        "boys'",
        "women's"
    ],
    "wof:name":"Noma",
    "wof:placetype":"venue"
},
  "geometry": {"coordinates":[-123.529732,38.767529],"type":"Point"}
}