{
  "type": "Feature",
  "properties": {
    "iso:country":"US",
    "sg:address":"800 S. Fairmount Ave. Ste.312",
    "sg:city":"Pasadena",
    "sg:classifiers":[
        {
            "category":"Health Services",
            "subcategory":"Clinic",
            "type":"Services"
        }
    ],
    "sg:phone":"+1 626 568 8838",
    "sg:postcode":"91105",
    "sg:province":"CA",
    "sg:tags":[
        "medical"
    ],
    "wof:name":"Retina Institute Of California",
    "wof:placetype":"venue"
},
  "geometry": {"coordinates":[-118.15178899999999,34.132807],"type":"Point"}
}