{
  "type": "Feature",
  "properties": {
    "addr:full":"653 Avenue Of The Flags Buellton CA 93427",
    "addr:housenumber":"653",
    "addr:postcode":"93427",
    "addr:street":"Avenue Of",
    "iso:country":"US",
    "sg:address":"653 Avenue Of The Flags",
    "sg:city":"Buellton",
    "sg:classifiers":[
        {
            "category":"Retail",
            "subcategory":"Auto Rental",
            "type":"Services"
        },
        {
            "category":"Travel",
            "subcategory":"Travel Agent",
            "type":"Entertainment"
        },
        {
            "category":"Autos & Motor Vehicles",
            "subcategory":"Recreational Vehicle Sales",
            "type":"Retail Goods"
        }
    ],
    "sg:phone":"+1 805 693 1260",
    "sg:postcode":"93427",
    "sg:province":"CA",
    "sg:tags":[
        "homes-rent",
        "agency",
        "services-commercial",
        "campers-rent",
        "lease"
    ],
    "sg:website":"http://www.cruiseamerica.com",
    "wof:name":"Cruise America Motorhome Rentl",
    "wof:placetype":"venue"
},
  "geometry": {"coordinates":[-120.190262,34.61987],"type":"Point"}
}