{
  "type": "Feature",
  "properties": {
    "addr:full":"4400 Horner St Union City CA 94587",
    "addr:housenumber":"4400",
    "addr:postcode":"94587",
    "addr:street":"Horner St",
    "iso:country":"US",
    "sg:address":"4400 Horner St",
    "sg:city":"Union City",
    "sg:classifiers":[
        {
            "category":"Freight",
            "type":"Transportation"
        }
    ],
    "sg:phone":"+1 510 489 4747",
    "sg:postcode":"94587",
    "sg:province":"CA",
    "sg:tags":[
        "mini",
        "commercial",
        "storage"
    ],
    "wof:name":"Diamond Mine Mini Storage",
    "wof:placetype":"venue"
},
  "geometry": {"coordinates":[-122.084222,37.595425],"type":"Point"}
}