{
  "type": "Feature",
  "properties": {
    "addr:full":"20282 Riverside Dr Newport Beach CA 92660",
    "addr:housenumber":"20282",
    "addr:postcode":"92660",
    "addr:street":"Riverside Dr",
    "iso:country":"US",
    "sg:address":"20282 Riverside Dr",
    "sg:city":"Newport Beach",
    "sg:classifiers":[
        {
            "category":"Retail",
            "subcategory":"Animal Services",
            "type":"Services"
        }
    ],
    "sg:phone":"+1 714 540 3021",
    "sg:postcode":"92660",
    "sg:province":"CA",
    "sg:tags":[
        "pet",
        "boarding/pet",
        "sitting"
    ],
    "wof:name":"Bellvue Collies",
    "wof:placetype":"venue"
},
  "geometry": {"coordinates":[-117.883087,33.661541],"type":"Point"}
}