{
  "type": "Feature",
  "properties": {
    "addr:full":"728 Geer Rd Turlock CA 95380",
    "addr:housenumber":"728",
    "addr:postcode":"95380",
    "addr:street":"Geer Rd",
    "iso:country":"US",
    "sg:address":"728 Geer Rd",
    "sg:city":"Turlock",
    "sg:classifiers":[
        {
            "category":"Retail",
            "subcategory":"Repair Shop",
            "type":"Services"
        }
    ],
    "sg:phone":"+1 209 656 8700",
    "sg:postcode":"95380",
    "sg:province":"CA",
    "sg:tags":[
        "lock",
        "locksmith"
    ],
    "wof:name":"All City Auto Sales",
    "wof:placetype":"venue"
},
  "geometry": {"coordinates":[-120.84876300000001,37.499726],"type":"Point"}
}