{
  "type": "Feature",
  "properties": {
    "iso:country":"US",
    "sg:address":"5681 Redwood Dr",
    "sg:city":"Rohnert Park",
    "sg:classifiers":[
        {
            "category":"Shopping",
            "subcategory":"Computers & Home Electronics",
            "type":"Retail Goods"
        }
    ],
    "sg:phone":"+1 707 585 7344",
    "sg:postcode":"94928",
    "sg:province":"CA",
    "sg:tags":[
        "equipment",
        "electronic",
        "supply"
    ],
    "wof:name":"HSC Electronic Supply",
    "wof:placetype":"venue"
},
  "geometry": {"coordinates":[-122.713611,38.35687],"type":"Point"}
}