{
  "type": "Feature",
  "properties": {
    "addr:full":"585 W 20th St Upland CA 91784",
    "addr:housenumber":"585",
    "addr:postcode":"91784",
    "addr:street":"W 20Th St",
    "iso:country":"US",
    "sg:address":"585 W 20th St",
    "sg:city":"Upland",
    "sg:classifiers":[
        {
            "category":"Professional",
            "subcategory":"Business Services",
            "type":"Services"
        }
    ],
    "sg:phone":"+1 909 982 9796",
    "sg:postcode":"91784",
    "sg:province":"CA",
    "sg:tags":[
        "equipment",
        "industrial"
    ],
    "wof:name":"Turbine Technical Services",
    "wof:placetype":"venue"
},
  "geometry": {"coordinates":[-117.659679,34.136108],"type":"Point"}
}