{
  "type": "Feature",
  "properties": {
    "addr:full":"110 W Spain St Sonoma CA 95476",
    "addr:housenumber":"110",
    "addr:postcode":"95476",
    "addr:street":"W Spain St",
    "iso:country":"US",
    "sg:address":"110 W Spain St",
    "sg:city":"Sonoma",
    "sg:phone":"+1 707 938 3634",
    "sg:postcode":"95476",
    "sg:province":"CA",
    "sg:website":"http://www.thegirlandthefig.com",
    "wof:name":"The Girl & The Fig Restaurant",
    "wof:placetype":"venue"
},
  "geometry": {"coordinates":[-122.45859900000001,38.293784],"type":"Point"}
}