{
  "type": "Feature",
  "properties": {
    "iso:country":"US",
    "sg:address":"714 Grant Dr",
    "sg:city":"Bakersfield",
    "sg:classifiers":[
        {
            "category":"Recreation",
            "type":"Entertainment"
        }
    ],
    "sg:phone":"+1 661 854 6446",
    "sg:postcode":"93308",
    "sg:province":"CA",
    "sg:tags":[
        "paint",
        "ball",
        "sport"
    ],
    "wof:name":"Target Zone Paintball",
    "wof:placetype":"venue"
},
  "geometry": {"coordinates":[-119.03657699999999,35.413531],"type":"Point"}
}