{
  "type": "Feature",
  "properties": {
    "iso:country":"US",
    "sg:address":"825 N Harper Ave",
    "sg:city":"Los Angeles",
    "sg:classifiers":[
        {
            "category":"Professional",
            "type":"Services"
        }
    ],
    "sg:phone":"+1 323 852 0936",
    "sg:postcode":"90046",
    "sg:province":"CA",
    "wof:name":"Ggrc Inc",
    "wof:placetype":"venue"
},
  "geometry": {"coordinates":[-118.36915999999999,34.086689],"type":"Point"}
}