{
  "type": "Feature",
  "properties": {
    "iso:country":"US",
    "sg:address":"1622 Gramercy Ave",
    "sg:city":"Torrance",
    "sg:classifiers":[
        {
            "category":"Building & Trades",
            "subcategory":"Construction",
            "type":"Services"
        }
    ],
    "sg:phone":"+1 310 328 0078",
    "sg:postcode":"90501",
    "sg:province":"CA",
    "sg:tags":[
        "site",
        "clean"
    ],
    "wof:name":"Christian Brothers Co",
    "wof:placetype":"venue"
},
  "geometry": {"coordinates":[-118.31491200000001,33.832767],"type":"Point"}
}