{
  "type": "Feature",
  "properties": {
    "iso:country":"US",
    "sg:address":"35 Rankin Ave",
    "sg:city":"San Jose",
    "sg:classifiers":[
        {
            "category":"Banks & Credit Unions",
            "subcategory":"Financial Services",
            "type":"Services"
        }
    ],
    "sg:phone":"+1 408 295 6552",
    "sg:postcode":"95110",
    "sg:province":"CA",
    "sg:tags":[
        "broker",
        "mortgage"
    ],
    "sg:website":"www.vendomeproperties.com",
    "wof:name":"Vendome Properties",
    "wof:placetype":"venue"
},
  "geometry": {"coordinates":[-121.898577,37.345996],"type":"Point"}
}