{
  "type": "Feature",
  "properties": {
    "addr:full":"2815 California St San Francisco CA 94115",
    "addr:housenumber":"2815",
    "addr:postcode":"94115",
    "addr:street":"California St",
    "iso:country":"US",
    "sg:address":"2815 California St",
    "sg:city":"San Francisco",
    "sg:classifiers":[
        {
            "category":"Restaurant",
            "type":"Food & Drink"
        }
    ],
    "sg:phone":"+1 415 447 6182",
    "sg:postcode":"94115",
    "sg:province":"CA",
    "wof:name":"Subway Sandwiches & Salads",
    "wof:placetype":"venue"
},
  "geometry": {"coordinates":[-122.44190999999999,37.787812],"type":"Point"}
}