{
  "type": "Feature",
  "properties": {
    "iso:country":"US",
    "sg:address":"8930 Eden Oaks Ave",
    "sg:city":"Orangevale",
    "sg:classifiers":[
        {
            "category":"Wholesale",
            "subcategory":"Home Furnishings",
            "type":"Manufacturing & Wholesale Goods"
        }
    ],
    "sg:phone":"+1 916 990 0442",
    "sg:postcode":"95662",
    "sg:province":"CA",
    "sg:tags":[
        "retail",
        "floor",
        "covering"
    ],
    "wof:name":"Shaw Industries Inc",
    "wof:placetype":"venue"
},
  "geometry": {"coordinates":[-121.222298,38.703876],"type":"Point"}
}