{
  "type": "Feature",
  "properties": {
    "addr:full":"11455 Hydraulic Dr Rancho Cordova CA 95742",
    "addr:housenumber":"11455",
    "addr:postcode":"95742",
    "addr:street":"Hydraulic Dr",
    "iso:country":"US",
    "sg:address":"11455 Hydraulic Dr",
    "sg:city":"Rancho Cordova",
    "sg:classifiers":[
        {
            "category":"Manufacturing",
            "subcategory":"Rubber & Plastics",
            "type":"Manufacturing & Wholesale Goods"
        }
    ],
    "sg:phone":"+1 916 638 1515",
    "sg:postcode":"95742",
    "sg:province":"CA",
    "wof:name":"Scribner Plastics",
    "wof:placetype":"venue"
},
  "geometry": {"coordinates":[-121.25731,38.584141],"type":"Point"}
}