{
  "type": "Feature",
  "properties": {
    "addr:full":"1500 Solano Ave Albany CA 94707",
    "addr:housenumber":"1500",
    "addr:postcode":"94707",
    "addr:street":"Solano Ave",
    "iso:country":"US",
    "sg:address":"1500 Solano Ave",
    "sg:city":"Albany",
    "sg:classifiers":[
        {
            "category":"Food & Beverages",
            "subcategory":"Groceries & Convenience Stores",
            "type":"Retail Goods"
        }
    ],
    "sg:phone":"+1 510 525 4107",
    "sg:postcode":"94707",
    "sg:province":"CA",
    "sg:tags":[
        "supermarket"
    ],
    "sg:website":"www.safeway.com",
    "wof:name":"Safeway",
    "wof:placetype":"venue"
},
  "geometry": {"coordinates":[-122.287205,37.890454],"type":"Point"}
}