{
  "type": "Feature",
  "properties": {
    "iso:country":"US",
    "sg:address":"2240 Yosemite Pkwy",
    "sg:city":"Merced",
    "sg:classifiers":[
        {
            "category":"Real Estate",
            "subcategory":"Real Estate Operator",
            "type":"Services"
        }
    ],
    "sg:phone":"+1 209 722 3411",
    "sg:postcode":"95341",
    "sg:province":"CA",
    "sg:tags":[
        "mobile",
        "home",
        "community"
    ],
    "wof:name":"Sierra Portal Mobile Estates",
    "wof:placetype":"venue"
},
  "geometry": {"coordinates":[-120.44628299999999,37.295054],"type":"Point"}
}