{
  "type": "Feature",
  "properties": {
    "addr:full":"1451 Fruitdale Ave San Jose CA 95128",
    "addr:housenumber":"1451",
    "addr:postcode":"95128",
    "addr:street":"Fruitdale Ave",
    "iso:country":"US",
    "sg:address":"1451 Fruitdale Ave",
    "sg:city":"San Jose",
    "sg:classifiers":[
        {
            "category":"Professional",
            "type":"Services"
        }
    ],
    "sg:phone":"+1 408 869 2828",
    "sg:postcode":"95128",
    "sg:province":"CA",
    "sg:tags":[
        "establishment"
    ],
    "wof:name":"Human Connect",
    "wof:placetype":"venue"
},
  "geometry": {"coordinates":[-121.91740799999999,37.310705],"type":"Point"}
}