{
  "type": "Feature",
  "properties": {
    "iso:country":"US",
    "sg:address":"18961 Mora Kai Ln",
    "sg:city":"Huntington Beach",
    "sg:classifiers":[
        {
            "category":"Restaurant",
            "type":"Food & Drink"
        }
    ],
    "sg:phone":"+1 949 307 8939",
    "sg:postcode":"92646",
    "sg:province":"CA",
    "sg:tags":[
        "eating"
    ],
    "wof:name":"Step Aside Catering Inc",
    "wof:placetype":"venue"
},
  "geometry": {"coordinates":[-117.985655,33.68727],"type":"Point"}
}