{
  "type": "Feature",
  "properties": {
    "iso:country":"US",
    "sg:address":"2459 Flora St",
    "sg:city":"Napa",
    "sg:classifiers":[
        {
            "category":"Wholesale",
            "subcategory":"Durable Goods & Equipment",
            "type":"Manufacturing & Wholesale Goods"
        }
    ],
    "sg:phone":"+1 707 253 2514",
    "sg:postcode":"94558",
    "sg:province":"CA",
    "wof:name":"Keep Touch",
    "wof:placetype":"venue"
},
  "geometry": {"coordinates":[-122.332515,38.33036],"type":"Point"}
}