{
  "type": "Feature",
  "properties": {
    "addr:full":"1515 Griffith Park Blvd Los Angeles CA 90026",
    "addr:housenumber":"1515",
    "addr:postcode":"90026",
    "addr:street":"Griffith Park Blvd",
    "iso:country":"US",
    "sg:address":"1515 Griffith Park Blvd",
    "sg:city":"Los Angeles",
    "sg:classifiers":[
        {
            "category":"Bakery",
            "type":"Food & Drink"
        }
    ],
    "sg:phone":"+1 323 661 0037",
    "sg:postcode":"90026",
    "sg:province":"CA",
    "wof:name":"United Bread & Pastry Inc",
    "wof:placetype":"venue"
},
  "geometry": {"coordinates":[-118.277,34.090302],"type":"Point"}
}