{
  "type": "Feature",
  "properties": {
    "addr:full":"2310 N Larkin Ave Fresno CA 93727",
    "addr:housenumber":"2310",
    "addr:postcode":"93727",
    "addr:street":"N Larkin Ave",
    "iso:country":"US",
    "sg:address":"2310 N Larkin Ave",
    "sg:city":"Fresno",
    "sg:classifiers":[
        {
            "category":"Professional",
            "subcategory":"Engineering",
            "type":"Services"
        },
        {
            "category":"Building & Trades",
            "subcategory":"Construction",
            "type":"Services"
        }
    ],
    "sg:phone":"+1 559 348 1488",
    "sg:postcode":"93727",
    "sg:province":"CA",
    "sg:tags":[
        "repair",
        "management",
        "energy",
        "systems-service",
        "equipment",
        "solar",
        "engineer"
    ],
    "wof:name":"Solarcity Inc.",
    "wof:placetype":"venue"
},
  "geometry": {"coordinates":[-119.696923,36.770736],"type":"Point"}
}