{
  "type": "Feature",
  "properties": {
    "iso:country":"US",
    "sg:address":"2005 N Glenoaks Blvd",
    "sg:city":"Burbank",
    "sg:classifiers":[
        {
            "category":"Autos & Motor Vehicles",
            "subcategory":"Fuel & Gas Station",
            "type":"Retail Goods"
        },
        {
            "category":"Retail",
            "subcategory":"Auto Repair",
            "type":"Services"
        }
    ],
    "sg:phone":"+1 818 842 8786",
    "sg:postcode":"91504",
    "sg:province":"CA",
    "wof:name":"A to Z Service Station",
    "wof:placetype":"venue"
},
  "geometry": {"coordinates":[-118.325312,34.196825],"type":"Point"}
}