{
  "type": "Feature",
  "properties": {
    "iso:country":"US",
    "sg:address":"1313 W 11th Pl",
    "sg:city":"Los Angeles",
    "sg:classifiers":[
        {
            "category":"Manufacturing",
            "subcategory":"Printing",
            "type":"Manufacturing & Wholesale Goods"
        }
    ],
    "sg:phone":"+1 213 749 4045",
    "sg:postcode":"90015",
    "sg:province":"CA",
    "sg:tags":[
        "lithographic"
    ],
    "wof:name":"Convention Center Printing",
    "wof:placetype":"venue"
},
  "geometry": {"coordinates":[-118.27245600000001,34.045637],"type":"Point"}
}