{
  "type": "Feature",
  "properties": {
    "iso:country":"US",
    "sg:address":"4184 Woodruff Ave",
    "sg:city":"Lakewood",
    "sg:classifiers":[
        {
            "category":"Food & Beverages",
            "subcategory":"Bakery",
            "type":"Retail Goods"
        }
    ],
    "sg:phone":"+1 562 421 2631",
    "sg:postcode":"90713",
    "sg:province":"CA",
    "sg:tags":[
        "donut",
        "doughnut"
    ],
    "wof:name":"Donut Center the",
    "wof:placetype":"venue"
},
  "geometry": {"coordinates":[-118.11599699999999,33.8339],"type":"Point"}
}