{
  "type": "Feature",
  "properties": {
    "iso:country":"US",
    "sg:address":"2229 Newbury Cir",
    "sg:city":"Lodi",
    "sg:classifiers":[
        {
            "category":"Freight",
            "type":"Transportation"
        }
    ],
    "sg:phone":"+1 209 948 1598",
    "sg:postcode":"95240",
    "sg:province":"CA",
    "sg:tags":[
        "arrangement"
    ],
    "wof:name":"J I B International",
    "wof:placetype":"venue"
},
  "geometry": {"coordinates":[-121.28530499999999,38.106394],"type":"Point"}
}