{
  "type": "Feature",
  "properties": {
    "addr:full":"788 Stern Ave Palo Alto CA 94303",
    "addr:housenumber":"788",
    "addr:postcode":"94303",
    "addr:street":"Stern Ave",
    "iso:country":"US",
    "sg:address":"788 Stern Ave",
    "sg:city":"Palo Alto",
    "sg:classifiers":[
        {
            "category":"Professional",
            "subcategory":"Computer Services",
            "type":"Services"
        }
    ],
    "sg:phone":"+1 650 856 2586",
    "sg:postcode":"94303",
    "sg:province":"CA",
    "sg:tags":[
        "electronics"
    ],
    "wof:name":"MHD Instruments",
    "wof:placetype":"venue"
},
  "geometry": {"coordinates":[-122.12262800000001,37.432093],"type":"Point"}
}