{
  "type": "Feature",
  "properties": {
    "iso:country":"US",
    "sg:address":"1083 E Bedmar St",
    "sg:city":"Carson",
    "sg:classifiers":[
        {
            "category":"Professional",
            "type":"Services"
        }
    ],
    "sg:phone":"+1 310 603 0700",
    "sg:postcode":"90746",
    "sg:province":"CA",
    "sg:tags":[
        "establishment"
    ],
    "sg:website":"www.ifyi.com",
    "wof:name":"International FYI",
    "wof:placetype":"venue"
},
  "geometry": {"coordinates":[-118.255889,33.842352],"type":"Point"}
}