{
  "type": "Feature",
  "properties": {
    "iso:country":"US",
    "sg:address":"777 B St",
    "sg:city":"Hayward",
    "sg:classifiers":[
        {
            "category":"Government",
            "subcategory":"Office",
            "type":"Public Place"
        }
    ],
    "sg:phone":"+1 510 583 4500",
    "sg:postcode":"94541",
    "sg:province":"CA",
    "sg:tags":[
        "village"
    ],
    "wof:name":"Hayward Human Resources Dept",
    "wof:placetype":"venue"
},
  "geometry": {"coordinates":[-122.08503399999999,37.671409],"type":"Point"}
}