{
  "type": "Feature",
  "properties": {
    "iso:country":"US",
    "sg:address":"2101 Webster St Ste 1835",
    "sg:city":"Oakland",
    "sg:classifiers":[
        {
            "category":"Professional",
            "subcategory":"Lawyer & Legal Services",
            "type":"Services"
        }
    ],
    "sg:phone":"+1 510 302 6600",
    "sg:postcode":"94612",
    "sg:province":"CA",
    "sg:tags":[
        "divorce",
        "law",
        "family"
    ],
    "sg:website":"www.ljklawgroup.com",
    "wof:name":"LJK Law Group, LLP",
    "wof:placetype":"venue"
},
  "geometry": {"coordinates":[-122.26585300000001,37.810257],"type":"Point"}
}