{
  "type": "Feature",
  "properties": {
    "addr:full":"1537 Pacific Ave Santa Cruz CA 95060",
    "addr:housenumber":"1537",
    "addr:postcode":"95060",
    "addr:street":"Pacific Ave",
    "iso:country":"US",
    "sg:address":"1537 Pacific Ave",
    "sg:city":"Santa Cruz",
    "sg:classifiers":[
        {
            "category":"Government",
            "subcategory":"Office",
            "type":"Public Place"
        }
    ],
    "sg:phone":"+1 831 425 4030",
    "sg:postcode":"95060",
    "sg:province":"CA",
    "wof:name":"Women's Crisis Support Defensa",
    "wof:placetype":"venue"
},
  "geometry": {"coordinates":[-122.02691299999999,36.976332],"type":"Point"}
}