{
  "type": "Feature",
  "properties": {
    "iso:country":"US",
    "sg:address":"454 Auzerais Ave",
    "sg:city":"San Jose",
    "sg:classifiers":[
        {
            "category":"Government",
            "subcategory":"Fire Station",
            "type":"Public Place"
        }
    ],
    "sg:phone":"+1 408 277 4071",
    "sg:postcode":"95126",
    "sg:province":"CA",
    "sg:tags":[
        "department"
    ],
    "wof:name":"San Jose Fire Dept",
    "wof:placetype":"venue"
},
  "geometry": {"coordinates":[-121.895593,37.32537],"type":"Point"}
}