{
  "type": "Feature",
  "properties": {
    "iso:country":"US",
    "sg:address":"4455 Torrance Blvd",
    "sg:city":"Torrance",
    "sg:classifiers":[
        {
            "category":"Home & Garden",
            "subcategory":"Home Furnishings",
            "type":"Retail Goods"
        }
    ],
    "sg:phone":"+1 310 371 2000",
    "sg:postcode":"90503",
    "sg:province":"CA",
    "sg:tags":[
        "curtain",
        "made",
        "drapery"
    ],
    "wof:name":"Flamingo Drapery Co",
    "wof:placetype":"venue"
},
  "geometry": {"coordinates":[-118.362071,33.837662],"type":"Point"}
}