{
  "type": "Feature",
  "properties": {
    "iso:country":"US",
    "sg:address":"1327 S Hazelwood Blvd",
    "sg:city":"Fresno",
    "sg:classifiers":[
        {
            "category":"Personal",
            "subcategory":"Beauty Salon",
            "type":"Services"
        }
    ],
    "sg:phone":"+1 559 497 0350",
    "sg:postcode":"93702",
    "sg:province":"CA",
    "wof:name":"Dpelos Beauty Salon",
    "wof:placetype":"venue"
},
  "geometry": {"coordinates":[-119.768562,36.729065],"type":"Point"}
}