{
  "type": "Feature",
  "properties": {
    "iso:country":"US",
    "sg:address":"21945 Grovepark Dr",
    "sg:city":"Santa Clarita",
    "sg:classifiers":[
        {
            "category":"Professional",
            "subcategory":"Accounting & Tax Preparation",
            "type":"Services"
        }
    ],
    "sg:phone":"+1 661 977 5038",
    "sg:postcode":"91350",
    "sg:province":"CA",
    "sg:tags":[
        "accountant"
    ],
    "sg:website":"www.nuvelsolutions.com",
    "wof:name":"Nuvel Business Solutions",
    "wof:placetype":"venue"
},
  "geometry": {"coordinates":[-118.519544,34.447249],"type":"Point"}
}