{
  "type": "Feature",
  "properties": {
    "iso:country":"US",
    "sg:address":"361 Forest Ave",
    "sg:city":"Laguna Beach",
    "sg:classifiers":[
        {
            "category":"Professional",
            "subcategory":"Lawyer & Legal Services",
            "type":"Services"
        }
    ],
    "sg:phone":"+1 949 494 4744",
    "sg:postcode":"92651",
    "sg:province":"CA",
    "sg:tags":[
        "attorney"
    ],
    "wof:name":"Geniene Stillwell Law Offices",
    "wof:placetype":"venue"
},
  "geometry": {"coordinates":[-117.781991,33.543895],"type":"Point"}
}