{
  "type": "Feature",
  "properties": {
    "addr:full":"1103 S San Gabriel Blvd San Gabriel CA 91776",
    "addr:housenumber":"1103",
    "addr:postcode":"91776",
    "addr:street":"S San Gabriel Blvd",
    "iso:country":"US",
    "sg:address":"1103 S San Gabriel Blvd",
    "sg:city":"San Gabriel",
    "sg:classifiers":[
        {
            "category":"Shopping",
            "subcategory":"Music",
            "type":"Retail Goods"
        }
    ],
    "sg:phone":"+1 626 286 0650",
    "sg:postcode":"91776",
    "sg:province":"CA",
    "sg:tags":[
        "video",
        "disc",
        "tape",
        "cassette"
    ],
    "wof:name":"Thai Video",
    "wof:placetype":"venue"
},
  "geometry": {"coordinates":[-118.09086000000001,34.08626],"type":"Point"}
}