{
  "type": "Feature",
  "properties": {
    "addr:full":"12499 N Tully Rd Lodi CA 95240",
    "addr:housenumber":"12499",
    "addr:postcode":"95240",
    "addr:street":"N Tully Rd",
    "iso:country":"US",
    "sg:address":"12499 N Tully Rd",
    "sg:city":"Lodi",
    "sg:classifiers":[
        {
            "category":"Farming",
            "subcategory":"Farm",
            "type":"Manufacturing & Wholesale Goods"
        }
    ],
    "sg:phone":"+1 209 931 1809",
    "sg:postcode":"95240",
    "sg:province":"CA",
    "sg:tags":[
        "crop",
        "general"
    ],
    "wof:name":"Vernon Hansen",
    "wof:placetype":"venue"
},
  "geometry": {"coordinates":[-121.12414800000001,38.089852],"type":"Point"}
}