{
  "type": "Feature",
  "properties": {
    "iso:country":"US",
    "sg:address":"1149 N Hacienda Blvd",
    "sg:city":"La Puente",
    "sg:classifiers":[
        {
            "category":"Retail",
            "subcategory":"Auto Repair",
            "type":"Services"
        }
    ],
    "sg:phone":"+1 626 918 8113",
    "sg:postcode":"91744",
    "sg:province":"CA",
    "sg:tags":[
        "repairing",
        "automobile"
    ],
    "wof:name":"LA Puente Specializing-Nissan",
    "wof:placetype":"venue"
},
  "geometry": {"coordinates":[-117.949536,34.04197],"type":"Point"}
}