{
  "type": "Feature",
  "properties": {
    "iso:country":"US",
    "sg:address":"28000 Blackberry Way",
    "sg:city":"Yorba Linda",
    "sg:classifiers":[
        {
            "category":"Retail",
            "subcategory":"Repair Shop",
            "type":"Services"
        }
    ],
    "sg:phone":"+1 714 694 1494",
    "sg:postcode":"92887",
    "sg:province":"CA",
    "sg:tags":[
        "lock",
        "locksmith"
    ],
    "wof:name":"A Plus Locksmith",
    "wof:placetype":"venue"
},
  "geometry": {"coordinates":[-117.706358,33.877846],"type":"Point"}
}