{
  "type": "Feature",
  "properties": {
    "addr:full":"49346 Rd 426 Oakhurst CA 93644",
    "addr:postcode":"49346;93644",
    "addr:street":"Rd 426",
    "iso:country":"US",
    "sg:address":"49346 Rd 426",
    "sg:city":"Oakhurst",
    "sg:classifiers":[
        {
            "category":"Social Services",
            "type":"Services"
        }
    ],
    "sg:phone":"+1 559 683 7298",
    "sg:postcode":"93644",
    "sg:province":"CA",
    "sg:tags":[
        "counselor",
        "marriage",
        "family"
    ],
    "wof:name":"Reyna Center",
    "wof:placetype":"venue"
},
  "geometry": {"coordinates":[-119.64776999999999,37.327853],"type":"Point"}
}