{
  "type": "Feature",
  "properties": {
    "addr:full":"22797 Bayview Ave Hayward CA 94541",
    "addr:housenumber":"22797",
    "addr:postcode":"94541",
    "addr:street":"Bayview Ave",
    "iso:country":"US",
    "sg:address":"22797 Bayview Ave",
    "sg:city":"Hayward",
    "sg:classifiers":[
        {
            "category":"Banks & Credit Unions",
            "subcategory":"Bank",
            "type":"Services"
        }
    ],
    "sg:phone":"+1 510 889 7567",
    "sg:postcode":"94541",
    "sg:province":"CA",
    "sg:tags":[
        "mortgage",
        "agency",
        "broker",
        "real estate"
    ],
    "wof:name":"American Financial",
    "wof:placetype":"venue"
},
  "geometry": {"coordinates":[-122.05964400000001,37.686267],"type":"Point"}
}