{
  "type": "Feature",
  "properties": {
    "iso:country":"US",
    "sg:address":"6091 W Pico Boulevard",
    "sg:city":"Los Angeles",
    "sg:classifiers":[
        {
            "category":"Health Services",
            "subcategory":"Doctor",
            "type":"Services"
        }
    ],
    "sg:phone":"+1 323 935 1178",
    "sg:postcode":"90035",
    "sg:province":"CA",
    "wof:name":"Women's Medical Group On Pico",
    "wof:placetype":"venue"
},
  "geometry": {"coordinates":[-118.373927,34.05279],"type":"Point"}
}