{
  "type": "Feature",
  "properties": {
    "iso:country":"US",
    "sg:address":"317 Parker St",
    "sg:city":"Vacaville",
    "sg:classifiers":[
        {
            "category":"Shopping",
            "subcategory":"Gifts & Souvenirs",
            "type":"Retail Goods"
        }
    ],
    "sg:phone":"+1 707 448 8278",
    "sg:postcode":"95688",
    "sg:province":"CA",
    "sg:tags":[
        "shop"
    ],
    "wof:name":"Yellow Brick Road",
    "wof:placetype":"venue"
},
  "geometry": {"coordinates":[-121.989862,38.355277],"type":"Point"}
}