{
  "type": "Feature",
  "properties": {
    "iso:country":"US",
    "sg:address":"1200 Pacific Ave",
    "sg:city":"Santa Cruz",
    "sg:classifiers":[
        {
            "category":"Coffee & Tea",
            "type":"Food & Drink"
        },
        {
            "category":"Shopping",
            "subcategory":"Books",
            "type":"Retail Goods"
        }
    ],
    "sg:phone":"+1 831 466 9644",
    "sg:postcode":"95060",
    "sg:province":"CA",
    "sg:tags":[
        "mags",
        "video",
        "books",
        "music"
    ],
    "sg:website":"www.borders.com",
    "wof:name":"Borders",
    "wof:placetype":"venue"
},
  "geometry": {"coordinates":[-122.02600099999999,36.973],"type":"Point"}
}