{
  "type": "Feature",
  "properties": {
    "addr:full":"1439 Henrietta St Redlands CA 92373",
    "addr:housenumber":"1439",
    "addr:postcode":"92373",
    "addr:street":"Henrietta St",
    "iso:country":"US",
    "sg:address":"1439 Henrietta St",
    "sg:city":"Redlands",
    "sg:classifiers":[
        {
            "category":"Professional",
            "type":"Services"
        }
    ],
    "sg:phone":"+1 909 792 0556",
    "sg:postcode":"92373",
    "sg:province":"CA",
    "wof:name":"Janet Rabinowitz Wallen",
    "wof:placetype":"venue"
},
  "geometry": {"coordinates":[-117.165131,34.03472],"type":"Point"}
}