{
  "type": "Feature",
  "properties": {
    "addr:full":"3130 Branch Street Sacramento CA 95815",
    "addr:housenumber":"3130",
    "addr:postcode":"95815",
    "addr:street":"Branch Street",
    "iso:country":"US",
    "sg:address":"3130 Branch Street",
    "sg:city":"Sacramento",
    "sg:classifiers":[
        {
            "category":"Restaurant",
            "type":"Food & Drink"
        }
    ],
    "sg:postcode":"95815",
    "sg:province":"CA",
    "sg:tags":[
        "flavor",
        "local"
    ],
    "wof:name":"Ruggles Warehouse",
    "wof:placetype":"venue"
},
  "geometry": {"coordinates":[-121.443434,38.624324],"type":"Point"}
}