{
  "type": "Feature",
  "properties": {
    "addr:full":"96 Tundra Way Sacramento CA 95834",
    "addr:housenumber":"96",
    "addr:postcode":"95834",
    "addr:street":"Tundra Way",
    "iso:country":"US",
    "sg:address":"96 Tundra Way",
    "sg:city":"Sacramento",
    "sg:classifiers":[
        {
            "category":"Travel",
            "subcategory":"Travel Agent",
            "type":"Entertainment"
        }
    ],
    "sg:phone":"+1 530 666 2474",
    "sg:postcode":"95834",
    "sg:province":"CA",
    "sg:tags":[
        "agency",
        "bureau"
    ],
    "wof:name":"Cache Creek Travel",
    "wof:placetype":"venue"
},
  "geometry": {"coordinates":[-121.488338,38.628407],"type":"Point"}
}