{
  "type": "Feature",
  "properties": {
    "addr:full":"5750 Sunrise Blvd Citrus Heights CA 95610",
    "addr:housenumber":"5750",
    "addr:postcode":"95610",
    "addr:street":"Sunrise Blvd",
    "iso:country":"US",
    "sg:address":"5750 Sunrise Blvd",
    "sg:city":"Citrus Heights",
    "sg:classifiers":[
        {
            "category":"Insurance",
            "subcategory":"Insurance Agent",
            "type":"Services"
        }
    ],
    "sg:phone":"+1 916 966 8672",
    "sg:postcode":"95610",
    "sg:province":"CA",
    "wof:name":"Automotive Aftermarket Svc",
    "wof:placetype":"venue"
},
  "geometry": {"coordinates":[-121.271415,38.673699],"type":"Point"}
}