{
  "type": "Feature",
  "properties": {
    "iso:country":"US",
    "sg:address":"774 N Highland St",
    "sg:city":"Orange",
    "sg:classifiers":[
        {
            "category":"Autos & Motor Vehicles",
            "subcategory":"Auto Supplies",
            "type":"Retail Goods"
        }
    ],
    "sg:phone":"+1 714 289 1855",
    "sg:postcode":"92867",
    "sg:province":"CA",
    "sg:tags":[
        "automobile",
        "parts"
    ],
    "wof:name":"Corteco Gasket",
    "wof:placetype":"venue"
},
  "geometry": {"coordinates":[-117.83213600000001,33.799476],"type":"Point"}
}