{
  "type": "Feature",
  "properties": {
    "iso:country":"US",
    "sg:address":"18219 Gale Ave",
    "sg:city":"City Of Industry",
    "sg:classifiers":[
        {
            "category":"Home & Garden",
            "subcategory":"Furniture",
            "type":"Retail Goods"
        }
    ],
    "sg:phone":"+1 626 839 8333",
    "sg:postcode":"91748",
    "sg:province":"CA",
    "wof:name":"Moda Furnishings",
    "wof:placetype":"venue"
},
  "geometry": {"coordinates":[-117.909941,33.995046],"type":"Point"}
}