{
  "type": "Feature",
  "properties": {
    "iso:country":"US",
    "sg:address":"24374 Michelson St",
    "sg:city":"Hayward",
    "sg:classifiers":[
        {
            "category":"Shopping",
            "subcategory":"Computers & Home Electronics",
            "type":"Retail Goods"
        }
    ],
    "sg:phone":"+1 510 732 1840",
    "sg:postcode":"94545",
    "sg:province":"CA",
    "sg:tags":[
        "software"
    ],
    "wof:name":"Bailey & Assoc Inc",
    "wof:placetype":"venue"
},
  "geometry": {"coordinates":[-122.117148,37.644186],"type":"Point"}
}