{
  "type": "Feature",
  "properties": {
    "addr:full":"3330 Rosecrans Street San Diego CA 92110",
    "addr:housenumber":"3330",
    "addr:postcode":"92110",
    "addr:street":"Rosecrans Street",
    "iso:country":"US",
    "sg:address":"3330 Rosecrans Street",
    "sg:city":"San Diego",
    "sg:classifiers":[
        {
            "category":"Travel",
            "subcategory":"Hotels & Motels",
            "type":"Entertainment"
        }
    ],
    "sg:phone":"+1 619 224 8266",
    "sg:postcode":"92110",
    "sg:province":"CA",
    "sg:website":"www.howardjohnsonsandiego.com",
    "wof:name":"Howard Johnson-San Diego-Sea World",
    "wof:placetype":"venue"
},
  "geometry": {"coordinates":[-117.20773,32.748027],"type":"Point"}
}