{
  "type": "Feature",
  "properties": {
    "addr:full":"21 Orinda Way Ste E Orinda CA 94563",
    "addr:housenumber":"21",
    "addr:postcode":"94563",
    "addr:street":"Orinda Way Ste E",
    "iso:country":"US",
    "sg:address":"21 Orinda Way Ste E",
    "sg:city":"Orinda",
    "sg:classifiers":[
        {
            "category":"Shopping",
            "subcategory":"Used Merchandise",
            "type":"Retail Goods"
        }
    ],
    "sg:phone":"+1 925 254 4442",
    "sg:postcode":"94563",
    "sg:province":"CA",
    "sg:tags":[
        "vintage",
        "consignment"
    ],
    "wof:name":"Cheryl's Closet",
    "wof:placetype":"venue"
},
  "geometry": {"coordinates":[-122.18699599999999,37.881802],"type":"Point"}
}