{
  "type": "Feature",
  "properties": {
    "iso:country":"US",
    "sg:address":"654 K St",
    "sg:city":"Los Banos",
    "sg:classifiers":[
        {
            "category":"Professional",
            "subcategory":"Lawyer & Legal Services",
            "type":"Services"
        }
    ],
    "sg:phone":"+1 209 826 4911",
    "sg:postcode":"93635",
    "sg:province":"CA",
    "sg:tags":[
        "attorney"
    ],
    "wof:name":"Linneman Burgess Telles",
    "wof:placetype":"venue"
},
  "geometry": {"coordinates":[-120.84848,37.058699],"type":"Point"}
}