{
  "type": "Feature",
  "properties": {
    "addr:full":"7406 Santa Monica Blvd Los Angeles CA 90046",
    "addr:housenumber":"7406",
    "addr:postcode":"90046",
    "addr:street":"Santa Monica Blvd",
    "iso:country":"US",
    "sg:address":"7406 Santa Monica Blvd",
    "sg:city":"Los Angeles",
    "sg:classifiers":[
        {
            "category":"Wholesale",
            "subcategory":"Medical Equipment & Supplies",
            "type":"Manufacturing & Wholesale Goods"
        }
    ],
    "sg:phone":"+1 323 469 2255",
    "sg:postcode":"90046",
    "sg:province":"CA",
    "wof:name":"Vine Medical Supplies",
    "wof:placetype":"venue"
},
  "geometry": {"coordinates":[-118.352653,34.090691],"type":"Point"}
}