{
  "type": "Feature",
  "properties": {
    "iso:country":"US",
    "sg:address":"13145 Sherman Way Unit 16",
    "sg:city":"North Hollywood",
    "sg:classifiers":[
        {
            "category":"Retail",
            "subcategory":"Auto Repair",
            "type":"Services"
        }
    ],
    "sg:phone":"+1 818 982 6600",
    "sg:postcode":"91605",
    "sg:province":"CA",
    "wof:name":"Autobahn Automotive Center",
    "wof:placetype":"venue"
},
  "geometry": {"coordinates":[-118.418999,34.201199],"type":"Point"}
}