{
  "type": "Feature",
  "properties": {
    "addr:full":"2299 E Stewart St Stockton CA 95205",
    "addr:housenumber":"2299",
    "addr:postcode":"95205",
    "addr:street":"E Stewart St",
    "iso:country":"US",
    "sg:address":"2299 E Stewart St",
    "sg:city":"Stockton",
    "sg:classifiers":[
        {
            "category":"Professional",
            "subcategory":"Business Services",
            "type":"Services"
        },
        {
            "category":"Wholesale",
            "subcategory":"Non-durable Goods",
            "type":"Manufacturing & Wholesale Goods"
        }
    ],
    "sg:phone":"+1 209 463 8787",
    "sg:postcode":"95205",
    "sg:province":"CA",
    "sg:tags":[
        "packaging"
    ],
    "wof:name":"Seaca Packaging Inc",
    "wof:placetype":"venue"
},
  "geometry": {"coordinates":[-121.26767100000001,37.980045],"type":"Point"}
}