{
  "type": "Feature",
  "properties": {
    "addr:full":"1250 San Carlos Ave San Carlos CA 94070",
    "addr:housenumber":"1250",
    "addr:postcode":"94070",
    "addr:street":"San Carlos Ave",
    "iso:country":"US",
    "sg:address":"1250 San Carlos Ave",
    "sg:city":"San Carlos",
    "sg:classifiers":[
        {
            "category":"Insurance",
            "subcategory":"Title Insurance",
            "type":"Services"
        }
    ],
    "sg:phone":"+1 650 620 3400",
    "sg:postcode":"94070",
    "sg:province":"CA",
    "wof:name":"Chicago Title Insurance Co",
    "wof:placetype":"venue"
},
  "geometry": {"coordinates":[-122.261788,37.506246],"type":"Point"}
}