{
  "type": "Feature",
  "properties": {
    "addr:full":"9579 Hultberg Rd Hilmar CA 95324",
    "addr:housenumber":"9579",
    "addr:postcode":"95324",
    "addr:street":"Hultberg Rd",
    "iso:country":"US",
    "sg:address":"9579 Hultberg Rd",
    "sg:city":"Hilmar",
    "sg:classifiers":[
        {
            "category":"Farming",
            "subcategory":"Dairy Farm",
            "type":"Manufacturing & Wholesale Goods"
        }
    ],
    "sg:phone":"+1 209 667 1781",
    "sg:postcode":"95324",
    "sg:province":"CA",
    "wof:name":"B & D Dairy",
    "wof:placetype":"venue"
},
  "geometry": {"coordinates":[-120.89544100000001,37.427491],"type":"Point"}
}