{
  "type": "Feature",
  "properties": {
    "addr:full":"1234 Polk St San Francisco CA 94109",
    "addr:housenumber":"1234",
    "addr:postcode":"94109",
    "addr:street":"Polk St",
    "iso:country":"US",
    "sg:address":"1234 Polk St",
    "sg:city":"San Francisco",
    "sg:classifiers":[
        {
            "category":"Restaurant",
            "type":"Food & Drink"
        }
    ],
    "sg:menulink":"http://www.allmenus.com/ca/san-francisco/44627-quetzal/menu/",
    "sg:phone":"+1 415 673 4181",
    "sg:postcode":"94109",
    "sg:province":"CA",
    "sg:tags":[
        "american"
    ],
    "wof:name":"Quetzal",
    "wof:placetype":"venue"
},
  "geometry": {"coordinates":[-122.420239,37.788266],"type":"Point"}
}