{
  "type": "Feature",
  "properties": {
    "iso:country":"US",
    "sg:address":"19375 Soledad Canyon Rd",
    "sg:city":"Santa Clarita",
    "sg:classifiers":[
        {
            "category":"Retail",
            "subcategory":"Laundry & Dry Cleaning",
            "type":"Services"
        }
    ],
    "sg:phone":"+1 661 252 6200",
    "sg:postcode":"91351",
    "sg:province":"CA",
    "sg:website":"www.santaclaritalaundry.com",
    "wof:name":"Santa Clarita Laundry Center",
    "wof:placetype":"venue"
},
  "geometry": {"coordinates":[-118.473516,34.415796],"type":"Point"}
}