{
  "type": "Feature",
  "properties": {
    "addr:full":"5960 Inglewood Dr Pleasanton CA 94588",
    "addr:housenumber":"5960",
    "addr:postcode":"94588",
    "addr:street":"Inglewood Dr",
    "iso:country":"US",
    "sg:address":"5960 Inglewood Dr",
    "sg:city":"Pleasanton",
    "sg:classifiers":[
        {
            "category":"Professional",
            "subcategory":"Computer Services",
            "type":"Services"
        }
    ],
    "sg:phone":"+1 925 469 4000",
    "sg:postcode":"94588",
    "sg:province":"CA",
    "sg:tags":[
        "prepackaged",
        "custom",
        "programming",
        "software"
    ],
    "wof:name":"BMC Software Distribution",
    "wof:placetype":"venue"
},
  "geometry": {"coordinates":[-121.90135100000001,37.688372],"type":"Point"}
}