{
  "type": "Feature",
  "properties": {
    "iso:country":"US",
    "sg:address":"8131 Wing Ave",
    "sg:city":"El Cajon",
    "sg:classifiers":[
        {
            "category":"Retail",
            "subcategory":"Auto Repair",
            "type":"Services"
        }
    ],
    "sg:phone":"+1 619 440 4774",
    "sg:postcode":"92020",
    "sg:province":"CA",
    "sg:tags":[
        "body",
        "automobile",
        "painting"
    ],
    "wof:name":"Collision Repair Specialists",
    "wof:placetype":"venue"
},
  "geometry": {"coordinates":[-116.96498800000001,32.821872],"type":"Point"}
}