{
  "type": "Feature",
  "properties": {
    "iso:country":"US",
    "sg:address":"712 Fair Oaks",
    "sg:city":"South Pasadena",
    "sg:classifiers":[
        {
            "category":"Shopping",
            "subcategory":"Mobile Phones",
            "type":"Retail Goods"
        }
    ],
    "sg:phone":"+1 626 799 7499",
    "sg:postcode":"91030",
    "sg:province":"CA",
    "wof:name":"AT&T Authorized Retailer",
    "wof:placetype":"venue"
},
  "geometry": {"coordinates":[-118.150263,34.118543],"type":"Point"}
}