{
  "type": "Feature",
  "properties": {
    "iso:country":"US",
    "sg:address":"12845 Towne Center Dr",
    "sg:city":"Cerritos",
    "sg:classifiers":[
        {
            "category":"Shopping",
            "subcategory":"Mobile Phones",
            "type":"Retail Goods"
        }
    ],
    "sg:phone":"+1 562 402 2014",
    "sg:postcode":"90703",
    "sg:province":"CA",
    "wof:name":"Affordable Portables",
    "wof:placetype":"venue"
},
  "geometry": {"coordinates":[-118.058998,33.868301],"type":"Point"}
}