{
  "type": "Feature",
  "properties": {
    "addr:full":"2296 Woolsey Rd Fulton CA 95439",
    "addr:housenumber":"2296",
    "addr:postcode":"95439",
    "addr:street":"Woolsey Rd",
    "iso:country":"US",
    "sg:address":"2296 Woolsey Rd",
    "sg:city":"Fulton",
    "sg:classifiers":[
        {
            "category":"Organizations",
            "subcategory":"Community Association",
            "type":"Services"
        }
    ],
    "sg:phone":"+1 707 526 7699",
    "sg:postcode":"95439",
    "sg:province":"CA",
    "sg:tags":[
        "club"
    ],
    "wof:name":"North Bay Motorcycle Club",
    "wof:placetype":"venue"
},
  "geometry": {"coordinates":[-122.78876,38.487562],"type":"Point"}
}