{
  "type": "Feature",
  "properties": {
    "addr:full":"50 E Santa Ana Ave Fresno CA 93704",
    "addr:housenumber":"50",
    "addr:postcode":"93704",
    "addr:street":"E Santa Ana Ave",
    "iso:country":"US",
    "sg:address":"50 E Santa Ana Ave",
    "sg:city":"Fresno",
    "sg:classifiers":[
        {
            "category":"Organizations",
            "subcategory":"Religious Organization",
            "type":"Services"
        }
    ],
    "sg:phone":"+1 559 226 8300",
    "sg:postcode":"93704",
    "sg:province":"CA",
    "sg:tags":[
        "church"
    ],
    "sg:website":"www.westminsterpc.com",
    "wof:name":"Westminster Presbyterian Chr",
    "wof:placetype":"venue"
},
  "geometry": {"coordinates":[-119.811723,36.804652],"type":"Point"}
}