{
  "type": "Feature",
  "properties": {
    "addr:full":"7520 Pivot St Downey CA 90241",
    "addr:housenumber":"7520",
    "addr:postcode":"90241",
    "addr:street":"Pivot St",
    "iso:country":"US",
    "sg:address":"7520 Pivot St",
    "sg:city":"Downey",
    "sg:classifiers":[
        {
            "category":"Professional",
            "type":"Services"
        }
    ],
    "sg:phone":"+1 562 806 2853",
    "sg:postcode":"90241",
    "sg:province":"CA",
    "wof:name":"Infinitetechnology Co",
    "wof:placetype":"venue"
},
  "geometry": {"coordinates":[-118.14736000000001,33.945759],"type":"Point"}
}