{
  "type": "Feature",
  "properties": {
    "iso:country":"US",
    "sg:address":"512 Capitola Ave",
    "sg:city":"Capitola",
    "sg:classifiers":[
        {
            "category":"Banks & Credit Unions",
            "subcategory":"Investment Brokerage",
            "type":"Services"
        }
    ],
    "sg:phone":"+1 831 462 0663",
    "sg:postcode":"95010",
    "sg:province":"CA",
    "sg:tags":[
        "funds",
        "mutual"
    ],
    "sg:website":"www.ncm.net",
    "wof:name":"Niemann Capital Management",
    "wof:placetype":"venue"
},
  "geometry": {"coordinates":[-121.953362,36.97687],"type":"Point"}
}