{
  "type": "Feature",
  "properties": {
    "addr:full":"13010 S Elm Ave Caruthers CA 93609",
    "addr:housenumber":"13010",
    "addr:postcode":"93609",
    "addr:street":"S Elm Ave",
    "iso:country":"US",
    "sg:address":"13010 S Elm Ave",
    "sg:city":"Caruthers",
    "sg:classifiers":[
        {
            "category":"Personal",
            "type":"Services"
        }
    ],
    "sg:phone":"+1 559 864 2509",
    "sg:postcode":"93609",
    "sg:province":"CA",
    "sg:tags":[
        "towing"
    ],
    "wof:name":"Caruthers Towing",
    "wof:placetype":"venue"
},
  "geometry": {"coordinates":[-119.791,36.547199],"type":"Point"}
}