{
  "type": "Feature",
  "properties": {
    "addr:full":"1727 E 28th St Signal Hill CA 90755",
    "addr:housenumber":"1727",
    "addr:postcode":"90755",
    "addr:street":"E 28Th St",
    "iso:country":"US",
    "sg:address":"1727 E 28th St",
    "sg:city":"Signal Hill",
    "sg:classifiers":[
        {
            "category":"Building & Trades",
            "subcategory":"Construction",
            "type":"Services"
        }
    ],
    "sg:phone":"+1 562 426 3837",
    "sg:postcode":"90755",
    "sg:province":"CA",
    "sg:tags":[
        "bathroom",
        "remodeling"
    ],
    "wof:name":"Dial One Bath Masters",
    "wof:placetype":"venue"
},
  "geometry": {"coordinates":[-118.170051,33.808125],"type":"Point"}
}