{
  "type": "Feature",
  "properties": {
    "addr:full":"18174 Verano Dr San Diego CA 92128",
    "addr:housenumber":"18174",
    "addr:postcode":"92128",
    "addr:street":"Verano Dr",
    "iso:country":"US",
    "sg:address":"18174 Verano Dr",
    "sg:city":"San Diego",
    "sg:classifiers":[
        {
            "category":"Shopping",
            "subcategory":"Computers & Home Electronics",
            "type":"Retail Goods"
        }
    ],
    "sg:phone":"+1 858 673 9473",
    "sg:postcode":"92128",
    "sg:province":"CA",
    "wof:name":"Lunas Music",
    "wof:placetype":"venue"
},
  "geometry": {"coordinates":[-117.06836199999999,33.04113],"type":"Point"}
}