{
  "type": "Feature",
  "properties": {
    "addr:full":"10907 Dixon Rd Oakdale CA 95361",
    "addr:housenumber":"10907",
    "addr:postcode":"95361",
    "addr:street":"Dixon Rd",
    "iso:country":"US",
    "sg:address":"10907 Dixon Rd",
    "sg:city":"Oakdale",
    "sg:classifiers":[
        {
            "category":"Retail",
            "subcategory":"Repair Shop",
            "type":"Services"
        }
    ],
    "sg:phone":"+1 209 847 9200",
    "sg:postcode":"95361",
    "sg:province":"CA",
    "sg:tags":[
        "ornamental",
        "work-supplies",
        "iron",
        "ironwork"
    ],
    "sg:website":"http://www.IdeasInIron.com",
    "wof:name":"Ideas In Iron",
    "wof:placetype":"venue"
},
  "geometry": {"coordinates":[-120.79508800000001,37.780036],"type":"Point"}
}