{
  "type": "Feature",
  "properties": {
    "addr:full":"5657 Wilshire Blvd Los Angeles CA 90036",
    "addr:housenumber":"5657",
    "addr:postcode":"90036",
    "addr:street":"Wilshire Blvd",
    "iso:country":"US",
    "sg:address":"5657 Wilshire Blvd",
    "sg:city":"Los Angeles",
    "sg:classifiers":[
        {
            "category":"Restaurant",
            "type":"Food & Drink"
        }
    ],
    "sg:phone":"+1 323 933 1976",
    "sg:postcode":"90036",
    "sg:province":"CA",
    "sg:tags":[
        "tea",
        "coffee"
    ],
    "sg:website":"www.blackdogcoffee.com",
    "wof:name":"Black Dog Coffee",
    "wof:placetype":"venue"
},
  "geometry": {"coordinates":[-118.35187000000001,34.062765],"type":"Point"}
}