{
  "type": "Feature",
  "properties": {
    "iso:country":"US",
    "sg:address":"14900 S Western Ave",
    "sg:city":"Gardena",
    "sg:classifiers":[
        {
            "category":"Building & Trades",
            "subcategory":"Construction",
            "type":"Services"
        }
    ],
    "sg:phone":"+1 310 323 5518",
    "sg:postcode":"90249",
    "sg:province":"CA",
    "sg:tags":[
        "nonresidential"
    ],
    "wof:name":"Bel Air Sun Rooms & Patio Room",
    "wof:placetype":"venue"
},
  "geometry": {"coordinates":[-118.309123,33.896299],"type":"Point"}
}