{
  "type": "Feature",
  "properties": {
    "iso:country":"US",
    "sg:address":"4858 Mercury St",
    "sg:city":"San Diego",
    "sg:classifiers":[
        {
            "category":"Professional",
            "subcategory":"Accounting & Tax Preparation",
            "type":"Services"
        }
    ],
    "sg:phone":"+1 858 560 1040",
    "sg:postcode":"92111",
    "sg:province":"CA",
    "sg:tags":[
        "return",
        "filing"
    ],
    "wof:name":"Andrew G Malkin",
    "wof:placetype":"venue"
},
  "geometry": {"coordinates":[-117.148916,32.829824],"type":"Point"}
}