{
  "type": "Feature",
  "properties": {
    "iso:country":"US",
    "sg:address":"PO Box 113",
    "sg:city":"El Cerrito",
    "sg:classifiers":[
        {
            "category":"Building & Trades",
            "subcategory":"Construction",
            "type":"Services"
        }
    ],
    "sg:phone":"+1 510 525 7430",
    "sg:postcode":"94530",
    "sg:province":"CA",
    "sg:tags":[
        "contractor"
    ],
    "wof:name":"Crystal Construction",
    "wof:placetype":"venue"
},
  "geometry": {"coordinates":[-122.30500000000001,37.919601],"type":"Point"}
}