{
  "type": "Feature",
  "properties": {
    "iso:country":"US",
    "sg:address":"1209 Isabel St",
    "sg:city":"Burbank",
    "sg:classifiers":[
        {
            "category":"Shopping",
            "subcategory":"Gifts & Souvenirs",
            "type":"Retail Goods"
        }
    ],
    "sg:phone":"+1 818 840 0574",
    "sg:postcode":"91506",
    "sg:province":"CA",
    "sg:tags":[
        "party",
        "supply"
    ],
    "sg:website":"www.ntd-60.com",
    "wof:name":"Lighting Decor Group",
    "wof:placetype":"venue"
},
  "geometry": {"coordinates":[-118.32214999999999,34.182896],"type":"Point"}
}