{
  "type": "Feature",
  "properties": {
    "iso:country":"US",
    "sg:address":"5722 W 4th St",
    "sg:city":"Los Angeles",
    "sg:classifiers":[
        {
            "category":"Shopping",
            "subcategory":"Clothing, Apparel, & Fashions",
            "type":"Retail Goods"
        }
    ],
    "sg:phone":"+1 323 932 1845",
    "sg:postcode":"90036",
    "sg:province":"CA",
    "sg:tags":[
        "t"
    ],
    "wof:name":"G Rated",
    "wof:placetype":"venue"
},
  "geometry": {"coordinates":[-118.345763,34.066806],"type":"Point"}
}