{
  "type": "Feature",
  "properties": {
    "iso:country":"US",
    "sg:address":"1687 W Chateau Pl",
    "sg:city":"Anaheim",
    "sg:classifiers":[
        {
            "category":"Shopping",
            "subcategory":"Pets & Pet Supplies",
            "type":"Retail Goods"
        }
    ],
    "sg:phone":"+1 714 520 0566",
    "sg:postcode":"92802",
    "sg:province":"CA",
    "sg:tags":[
        "store"
    ],
    "wof:name":"Pompous Pet Carriers & Accessories",
    "wof:placetype":"venue"
},
  "geometry": {"coordinates":[-117.941002,33.820801],"type":"Point"}
}