{
  "type": "Feature",
  "properties": {
    "iso:country":"US",
    "sg:address":"601 Van Ness Ave",
    "sg:city":"San Francisco",
    "sg:classifiers":[
        {
            "category":"Professional",
            "subcategory":"Detective & Security Services",
            "type":"Services"
        }
    ],
    "sg:phone":"+1 415 440 9100",
    "sg:postcode":"94102",
    "sg:province":"CA",
    "sg:tags":[
        "investigator"
    ],
    "sg:website":"www.probusresearch.com",
    "wof:name":"Probus Research",
    "wof:placetype":"venue"
},
  "geometry": {"coordinates":[-122.42062300000001,37.781493],"type":"Point"}
}