{
  "type": "Feature",
  "properties": {
    "addr:full":"3603 M St Merced CA 95348",
    "addr:housenumber":"3603",
    "addr:postcode":"95348",
    "addr:street":"M St",
    "iso:country":"US",
    "sg:address":"3603 M St",
    "sg:city":"Merced",
    "sg:classifiers":[
        {
            "category":"Organizations",
            "subcategory":"Religious Organization",
            "type":"Services"
        }
    ],
    "sg:phone":"+1 209 383 6662",
    "sg:postcode":"95348",
    "sg:province":"CA",
    "sg:tags":[
        "church"
    ],
    "wof:name":"Sierra Presbyterian Church",
    "wof:placetype":"venue"
},
  "geometry": {"coordinates":[-120.478486,37.333505],"type":"Point"}
}