{
  "type": "Feature",
  "properties": {
    "addr:full":"2863 el Camino Real Merced CA 95340",
    "addr:housenumber":"2863",
    "addr:postcode":"95340",
    "addr:street":"El Camino Real",
    "iso:country":"US",
    "sg:address":"2863 el Camino Real",
    "sg:city":"Merced",
    "sg:classifiers":[
        {
            "category":"Farming",
            "subcategory":"Crops",
            "type":"Manufacturing & Wholesale Goods"
        }
    ],
    "sg:phone":"+1 209 722 6429",
    "sg:postcode":"95340",
    "sg:province":"CA",
    "sg:tags":[
        "grove",
        "nut",
        "tree"
    ],
    "wof:name":"James Tanioka Farms",
    "wof:placetype":"venue"
},
  "geometry": {"coordinates":[-120.455474,37.310378],"type":"Point"}
}