{
  "type": "Feature",
  "properties": {
    "addr:full":"12955 Kittridge St North Hollywood CA 91606",
    "addr:housenumber":"12955",
    "addr:postcode":"91606",
    "addr:street":"Kittridge St",
    "iso:country":"US",
    "sg:address":"12955 Kittridge St",
    "sg:city":"North Hollywood",
    "sg:classifiers":[
        {
            "category":"Building & Trades",
            "subcategory":"Landscaping Services",
            "type":"Services"
        }
    ],
    "sg:phone":"+1 818 980 9017",
    "sg:postcode":"91606",
    "sg:province":"CA",
    "wof:name":"Buis Gardening",
    "wof:placetype":"venue"
},
  "geometry": {"coordinates":[-118.415707,34.190388],"type":"Point"}
}