{
  "type": "Feature",
  "properties": {
    "addr:full":"17991 Cowan Irvine CA 92614",
    "addr:housenumber":"17991",
    "addr:postcode":"92614",
    "addr:street":"Cowan",
    "iso:country":"US",
    "sg:address":"17991 Cowan",
    "sg:city":"Irvine",
    "sg:classifiers":[
        {
            "category":"Professional",
            "subcategory":"Lawyer & Legal Services",
            "type":"Services"
        }
    ],
    "sg:phone":"+1 949 261 2500",
    "sg:postcode":"92614",
    "sg:province":"CA",
    "wof:name":"Horizon Group",
    "wof:placetype":"venue"
},
  "geometry": {"coordinates":[-117.86582199999999,33.691772],"type":"Point"}
}