{
  "type": "Feature",
  "properties": {
    "iso:country":"US",
    "sg:address":"1720 Joe Crosson Dr",
    "sg:city":"El Cajon",
    "sg:classifiers":[
        {
            "category":"Airport",
            "type":"Transportation"
        }
    ],
    "sg:phone":"+1 619 562 2535",
    "sg:postcode":"92020",
    "sg:province":"CA",
    "wof:name":"Gillespie Field Partners",
    "wof:placetype":"venue"
},
  "geometry": {"coordinates":[-116.969827,32.820026],"type":"Point"}
}