{
  "type": "Feature",
  "properties": {
    "iso:country":"US",
    "sg:address":"11444 Village Ridge Rd",
    "sg:city":"San Diego",
    "sg:classifiers":[
        {
            "category":"Shopping",
            "type":"Retail Goods"
        }
    ],
    "sg:phone":"+1 858 831 0978",
    "sg:postcode":"92131",
    "sg:province":"CA",
    "sg:tags":[
        "equipment",
        "care",
        "health",
        "home"
    ],
    "wof:name":"Home Medical Svc",
    "wof:placetype":"venue"
},
  "geometry": {"coordinates":[-117.08524,32.934771],"type":"Point"}
}