{
  "type": "Feature",
  "properties": {
    "addr:full":"2408 Golden Ct Mariposa CA 95338",
    "addr:housenumber":"2408",
    "addr:postcode":"95338",
    "addr:street":"Golden Ct",
    "iso:country":"US",
    "sg:address":"2408 Golden Ct",
    "sg:city":"Mariposa",
    "sg:classifiers":[
        {
            "category":"Building & Trades",
            "subcategory":"Construction",
            "type":"Services"
        }
    ],
    "sg:phone":"+1 209 966 4996",
    "sg:postcode":"95338",
    "sg:province":"CA",
    "sg:tags":[
        "system",
        "specialty",
        "heating",
        "contractor",
        "air conditioning"
    ],
    "wof:name":"Mitchell Heating A C",
    "wof:placetype":"venue"
},
  "geometry": {"coordinates":[-119.734689,37.471858],"type":"Point"}
}