{
  "type": "Feature",
  "properties": {
    "addr:full":"1356 Garnet Avenue San Diego CA 92109",
    "addr:housenumber":"1356",
    "addr:postcode":"92109",
    "addr:street":"Garnet Avenue",
    "iso:country":"US",
    "sg:address":"1356 Garnet Avenue",
    "sg:city":"San Diego",
    "sg:classifiers":[
        {
            "category":"Personal",
            "subcategory":"Hair Removal",
            "type":"Services"
        },
        {
            "category":"Personal",
            "subcategory":"Skin Care",
            "type":"Services"
        }
    ],
    "sg:phone":"+1 858 272 8482",
    "sg:postcode":"92109",
    "sg:province":"CA",
    "sg:website":"www.vivabrazilsd.com",
    "wof:name":"Viva Brazil!",
    "wof:placetype":"venue"
},
  "geometry": {"coordinates":[-117.245243,32.799118],"type":"Point"}
}