{
  "type": "Feature",
  "properties": {
    "iso:country":"US",
    "sg:address":"2305 Fay Dr",
    "sg:city":"Atwater",
    "sg:classifiers":[
        {
            "category":"Restaurant",
            "type":"Food & Drink"
        }
    ],
    "sg:phone":"+1 209 358 1668",
    "sg:postcode":"95301",
    "sg:province":"CA",
    "sg:tags":[
        "caterer"
    ],
    "wof:name":"Corvelo Catering Co",
    "wof:placetype":"venue"
},
  "geometry": {"coordinates":[-120.618338,37.358795],"type":"Point"}
}