{
  "type": "Feature",
  "properties": {
    "iso:country":"US",
    "sg:address":"14530 Rattlesnake Rd",
    "sg:city":"Grass Valley",
    "sg:classifiers":[
        {
            "category":"Health Services",
            "subcategory":"Optometrist",
            "type":"Services"
        }
    ],
    "sg:phone":"+1 530 273 6000",
    "sg:postcode":"95945",
    "sg:province":"CA",
    "wof:name":"Alfred Gabler OD",
    "wof:placetype":"venue"
},
  "geometry": {"coordinates":[-121.03132600000001,39.172284],"type":"Point"}
}