{
  "type": "Feature",
  "properties": {
    "addr:full":"3852 Pine Ave Long Beach CA 90807",
    "addr:housenumber":"3852",
    "addr:postcode":"90807",
    "addr:street":"Pine Ave",
    "iso:country":"US",
    "sg:address":"3852 Pine Ave",
    "sg:city":"Long Beach",
    "sg:classifiers":[
        {
            "category":"Real Estate",
            "subcategory":"Surveying",
            "type":"Services"
        }
    ],
    "sg:phone":"+1 562 595 8287",
    "sg:postcode":"90807",
    "sg:province":"CA",
    "sg:tags":[
        "surveyor"
    ],
    "wof:name":"Dave Rath Marine Surveyors",
    "wof:placetype":"venue"
},
  "geometry": {"coordinates":[-118.193243,33.827768],"type":"Point"}
}