{
  "type": "Feature",
  "properties": {
    "iso:country":"US",
    "sg:address":"12195 Dunlap Pl",
    "sg:city":"Chino",
    "sg:classifiers":[
        {
            "category":"Professional",
            "type":"Services"
        }
    ],
    "sg:phone":"+1 909 465 9606",
    "sg:postcode":"91710",
    "sg:province":"CA",
    "sg:tags":[
        "technical",
        "preparation",
        "manual"
    ],
    "wof:name":"Metron Corp",
    "wof:placetype":"venue"
},
  "geometry": {"coordinates":[-117.696327,34.032014],"type":"Point"}
}