{
  "type": "Feature",
  "properties": {
    "addr:full":"1609 E Main St Visalia CA 93292",
    "addr:housenumber":"1609",
    "addr:postcode":"93292",
    "addr:street":"E Main St",
    "iso:country":"US",
    "sg:address":"1609 E Main St",
    "sg:city":"Visalia",
    "sg:classifiers":[
        {
            "category":"Home & Garden",
            "subcategory":"Building Materials",
            "type":"Retail Goods"
        }
    ],
    "sg:phone":"+1 559 741 0144",
    "sg:postcode":"93292",
    "sg:province":"CA",
    "sg:tags":[
        "glass",
        "window",
        "plate"
    ],
    "wof:name":"Jim's Auto Glass",
    "wof:placetype":"venue"
},
  "geometry": {"coordinates":[-119.277101,36.330139],"type":"Point"}
}