{
  "type": "Feature",
  "properties": {
    "addr:full":"1685 Sequoia St Apt 7 Redding CA 96001",
    "addr:housenumber":"1685;7",
    "addr:postcode":"96001",
    "addr:street":"Sequoia St Apt",
    "iso:country":"US",
    "sg:address":"1685 Sequoia St Apt 7",
    "sg:city":"Redding",
    "sg:classifiers":[
        {
            "category":"Personal",
            "type":"Services"
        },
        {
            "category":"Professional",
            "subcategory":"Art Services",
            "type":"Services"
        }
    ],
    "sg:phone":"+1 530 605 1125",
    "sg:postcode":"96001",
    "sg:province":"CA",
    "sg:tags":[
        "photography",
        "videography",
        "wedding"
    ],
    "wof:name":"Christopher Aguirre's Photography",
    "wof:placetype":"venue"
},
  "geometry": {"coordinates":[-122.381626,40.584615],"type":"Point"}
}