{
  "type": "Feature",
  "properties": {
    "addr:full":"305 Swanton Rd Davenport CA 95017",
    "addr:housenumber":"305",
    "addr:postcode":"95017",
    "addr:street":"Swanton Rd",
    "iso:country":"US",
    "sg:address":"305 Swanton Rd",
    "sg:city":"Davenport",
    "sg:classifiers":[
        {
            "category":"Professional",
            "type":"Services"
        }
    ],
    "sg:phone":"+1 831 420 0444",
    "sg:postcode":"95017",
    "sg:province":"CA",
    "wof:name":"Bevirt Joeben",
    "wof:placetype":"venue"
},
  "geometry": {"coordinates":[-122.226653,37.063195],"type":"Point"}
}