{
  "type": "Feature",
  "properties": {
    "addr:full":"310 N Tustin Ave Ste D Santa Ana CA 92705",
    "addr:housenumber":"310",
    "addr:postcode":"92705",
    "addr:street":"N Tustin Ave Ste D",
    "iso:country":"US",
    "sg:address":"310 N Tustin Ave Ste D",
    "sg:city":"Santa Ana",
    "sg:classifiers":[
        {
            "category":"Professional",
            "subcategory":"Employment Agencies",
            "type":"Services"
        }
    ],
    "sg:phone":"+1 714 953 5944",
    "sg:postcode":"92705",
    "sg:province":"CA",
    "wof:name":"All Star",
    "wof:placetype":"venue"
},
  "geometry": {"coordinates":[-117.834304,33.747423],"type":"Point"}
}