{
  "type": "Feature",
  "properties": {
    "addr:full":"148 Standish St Monrovia CA 91016",
    "addr:housenumber":"148",
    "addr:postcode":"91016",
    "addr:street":"Standish St",
    "iso:country":"US",
    "sg:address":"148 Standish St",
    "sg:city":"Monrovia",
    "sg:classifiers":[
        {
            "category":"Building & Trades",
            "subcategory":"Construction",
            "type":"Services"
        }
    ],
    "sg:phone":"+1 626 359 4427",
    "sg:postcode":"91016",
    "sg:province":"CA",
    "sg:tags":[
        "contractor"
    ],
    "wof:name":"Larry Kendrick Construction",
    "wof:placetype":"venue"
},
  "geometry": {"coordinates":[-118.602307,34.124812],"type":"Point"}
}