{
  "type": "Feature",
  "properties": {
    "addr:full":"516 Parker Rd Travis Afb CA 94535",
    "addr:housenumber":"516",
    "addr:postcode":"94535",
    "addr:street":"Parker Rd",
    "iso:country":"US",
    "sg:address":"516 Parker Rd",
    "sg:city":"Travis Afb",
    "sg:classifiers":[
        {
            "category":"Retail",
            "subcategory":"Auto Rental",
            "type":"Services"
        }
    ],
    "sg:phone":"+1 707 437 7300",
    "sg:postcode":"94535",
    "sg:province":"CA",
    "sg:tags":[
        "renting",
        "automobile",
        "passenger",
        "car"
    ],
    "wof:name":"Enterprise Rent-A-Car",
    "wof:placetype":"venue"
},
  "geometry": {"coordinates":[-121.95264299999999,38.272427],"type":"Point"}
}