{
  "type": "Feature",
  "properties": {
    "addr:full":"430 Central Ave Upland CA 91786",
    "addr:housenumber":"430",
    "addr:postcode":"91786",
    "addr:street":"Central Ave",
    "iso:country":"US",
    "sg:address":"430 Central Ave",
    "sg:city":"Upland",
    "sg:classifiers":[
        {
            "category":"Restaurant",
            "type":"Food & Drink"
        }
    ],
    "sg:phone":"+1 909 981 7711",
    "sg:postcode":"91786",
    "sg:province":"CA",
    "wof:name":"Everest Restaurant",
    "wof:placetype":"venue"
},
  "geometry": {"coordinates":[-117.689565,34.097565],"type":"Point"}
}