{
  "type": "Feature",
  "properties": {
    "iso:country":"US",
    "sg:address":"9733 Topanga Canyon Blvd",
    "sg:city":"Chatsworth",
    "sg:classifiers":[
        {
            "category":"Real Estate",
            "subcategory":"Real Estate Services",
            "type":"Services"
        },
        {
            "category":"Real Estate",
            "subcategory":"Real Estate Operator",
            "type":"Services"
        }
    ],
    "sg:phone":"+1 818 882 3317",
    "sg:postcode":"91311",
    "sg:province":"CA",
    "sg:tags":[
        "vacancy",
        "apartment",
        "rental",
        "listing"
    ],
    "wof:name":"Coventry",
    "wof:placetype":"venue"
},
  "geometry": {"coordinates":[-118.60669799999999,34.247431],"type":"Point"}
}