{
  "type": "Feature",
  "properties": {
    "addr:full":"3300 Auburn Blvd Sacramento CA 95821",
    "addr:housenumber":"3300",
    "addr:postcode":"95821",
    "addr:street":"Auburn Blvd",
    "iso:country":"US",
    "sg:address":"3300 Auburn Blvd",
    "sg:city":"Sacramento",
    "sg:classifiers":[
        {
            "category":"Autos & Motor Vehicles",
            "subcategory":"Automobile Sales",
            "type":"Retail Goods"
        }
    ],
    "sg:phone":"+1 916 723 4472",
    "sg:postcode":"95821",
    "sg:province":"CA",
    "sg:tags":[
        "used"
    ],
    "wof:name":"Red Line Classics",
    "wof:placetype":"venue"
},
  "geometry": {"coordinates":[-121.38429600000001,38.636538],"type":"Point"}
}