{
  "type": "Feature",
  "properties": {
    "addr:full":"1521 S Vermont Ave Los Angeles CA 90006",
    "addr:housenumber":"1521",
    "addr:postcode":"90006",
    "addr:street":"S Vermont Ave",
    "iso:country":"US",
    "sg:address":"1521 S Vermont Ave",
    "sg:city":"Los Angeles",
    "sg:classifiers":[
        {
            "category":"Personal",
            "subcategory":"Beauty Salon",
            "type":"Services"
        }
    ],
    "sg:phone":"+1 213 381 6098",
    "sg:postcode":"90006",
    "sg:province":"CA",
    "wof:name":"Salon Lolita's",
    "wof:placetype":"venue"
},
  "geometry": {"coordinates":[-118.291669,34.046468],"type":"Point"}
}