{
  "type": "Feature",
  "properties": {
    "addr:full":"500 Argonaut Ln Jackson CA 95642",
    "addr:housenumber":"500",
    "addr:postcode":"95642",
    "addr:street":"Argonaut Ln",
    "iso:country":"US",
    "sg:address":"500 Argonaut Ln",
    "sg:city":"Jackson",
    "sg:classifiers":[
        {
            "category":"Government",
            "subcategory":"Court House",
            "type":"Public Place"
        }
    ],
    "sg:phone":"+1 209 223 6463",
    "sg:postcode":"95642",
    "sg:province":"CA",
    "sg:tags":[
        "county"
    ],
    "wof:name":"Amador County Superior Court",
    "wof:placetype":"venue"
},
  "geometry": {"coordinates":[-120.79074199999999,38.357107],"type":"Point"}
}