{
  "type": "Feature",
  "properties": {
    "addr:full":"3242 Congressional Cir Fairfield CA 94534",
    "addr:housenumber":"3242",
    "addr:postcode":"94534",
    "addr:street":"Congressional Cir",
    "iso:country":"US",
    "sg:address":"3242 Congressional Cir",
    "sg:city":"Fairfield",
    "sg:classifiers":[
        {
            "category":"Home & Garden",
            "subcategory":"Building Materials",
            "type":"Retail Goods"
        }
    ],
    "sg:phone":"+1 707 426 1989",
    "sg:postcode":"94534",
    "sg:province":"CA",
    "sg:tags":[
        "energy",
        "conservation",
        "prod"
    ],
    "wof:name":"G & R People Power Svc",
    "wof:placetype":"venue"
},
  "geometry": {"coordinates":[-122.07290500000001,38.287936],"type":"Point"}
}