{
  "type": "Feature",
  "properties": {
    "iso:country":"US",
    "sg:address":"549 N Golden State Blvd",
    "sg:city":"Turlock",
    "sg:classifiers":[
        {
            "category":"Restaurant",
            "type":"Food & Drink"
        }
    ],
    "sg:phone":"+1 209 667 6511",
    "sg:postcode":"95380",
    "sg:province":"CA",
    "wof:name":"Lee's Buffet",
    "wof:placetype":"venue"
},
  "geometry": {"coordinates":[-120.850343,37.499759],"type":"Point"}
}