{
  "type": "Feature",
  "properties": {
    "iso:country":"US",
    "sg:address":"720 Capitola Ave",
    "sg:city":"Capitola",
    "sg:classifiers":[
        {
            "category":"Retail",
            "subcategory":"Portrait Studio",
            "type":"Services"
        },
        {
            "category":"Professional",
            "subcategory":"Art Services",
            "type":"Services"
        }
    ],
    "sg:phone":"+1 831 462 0600",
    "sg:postcode":"95010",
    "sg:province":"CA",
    "sg:tags":[
        "photographer",
        "photography",
        "store"
    ],
    "wof:name":"Clark Dave Photographer",
    "wof:placetype":"venue"
},
  "geometry": {"coordinates":[-121.953003,36.979801],"type":"Point"}
}