{
  "type": "Feature",
  "properties": {
    "addr:full":"3939 Crenshaw Blvd Ste D Los Angeles CA 90008",
    "addr:housenumber":"3939",
    "addr:postcode":"90008",
    "addr:street":"Crenshaw Blvd Ste D",
    "iso:country":"US",
    "sg:address":"3939 Crenshaw Blvd Ste D",
    "sg:city":"Los Angeles",
    "sg:classifiers":[
        {
            "category":"Shopping",
            "subcategory":"Beauty & Cosmetics",
            "type":"Retail Goods"
        }
    ],
    "sg:phone":"+1 323 295 9927",
    "sg:postcode":"90008",
    "sg:province":"CA",
    "sg:tags":[
        "supply"
    ],
    "sg:website":"www.sallybeauty.com",
    "wof:name":"Sally Beauty Supply",
    "wof:placetype":"venue"
},
  "geometry": {"coordinates":[-118.334999,34.013901],"type":"Point"}
}