{
  "type": "Feature",
  "properties": {
    "iso:country":"US",
    "sg:address":"3234 Ettrick St",
    "sg:city":"Los Angeles",
    "sg:classifiers":[
        {
            "category":"Professional",
            "type":"Services"
        }
    ],
    "sg:phone":"+1 323 665 0696",
    "sg:postcode":"90027",
    "sg:province":"CA",
    "wof:name":"Stephen Hamilton ARC",
    "wof:placetype":"venue"
},
  "geometry": {"coordinates":[-118.271922,34.112811],"type":"Point"}
}