{
  "type": "Feature",
  "properties": {
    "iso:country":"US",
    "sg:address":"2627 W Orangethorpe Ave",
    "sg:city":"Fullerton",
    "sg:classifiers":[
        {
            "category":"Restaurant",
            "type":"Food & Drink"
        }
    ],
    "sg:menulink":"http://www.allmenus.com/ca/anaheim-santa-ana-garden-grove/57814-subway/menu/",
    "sg:phone":"+1 714 441 0035",
    "sg:postcode":"92833",
    "sg:province":"CA",
    "sg:tags":[
        "american",
        "sandwich"
    ],
    "wof:name":"Subway",
    "wof:placetype":"venue"
},
  "geometry": {"coordinates":[-117.972984,33.85914],"type":"Point"}
}