{
  "type": "Feature",
  "properties": {
    "iso:country":"US",
    "sg:address":"239 E 12th St",
    "sg:city":"Los Angeles",
    "sg:classifiers":[
        {
            "category":"Shopping",
            "subcategory":"Jewelry",
            "type":"Retail Goods"
        }
    ],
    "sg:phone":"+1 213 746 2836",
    "sg:postcode":"90015",
    "sg:province":"CA",
    "sg:tags":[
        "watch"
    ],
    "wof:name":"Happy",
    "wof:placetype":"venue"
},
  "geometry": {"coordinates":[-118.257605,34.036596],"type":"Point"}
}