{
  "type": "Feature",
  "properties": {
    "addr:full":"6 Hutton Centre Dr Santa Ana CA 92707",
    "addr:housenumber":"6",
    "addr:postcode":"92707",
    "addr:street":"Hutton Centre Dr",
    "iso:country":"US",
    "sg:address":"6 Hutton Centre Dr",
    "sg:city":"Santa Ana",
    "sg:classifiers":[
        {
            "category":"Professional",
            "subcategory":"Lawyer & Legal Services",
            "type":"Services"
        }
    ],
    "sg:phone":"+1 714 662 4990",
    "sg:postcode":"92707",
    "sg:province":"CA",
    "wof:name":"Sanders Brian M Law Clk",
    "wof:placetype":"venue"
},
  "geometry": {"coordinates":[-117.86799600000001,33.706001],"type":"Point"}
}