{
  "type": "Feature",
  "properties": {
    "addr:full":"4855 Ruffner St San Diego CA 92111",
    "addr:housenumber":"4855",
    "addr:postcode":"92111",
    "addr:street":"Ruffner St",
    "iso:country":"US",
    "sg:address":"4855 Ruffner St",
    "sg:city":"San Diego",
    "sg:classifiers":[
        {
            "category":"Retail",
            "subcategory":"Auto Repair",
            "type":"Services"
        }
    ],
    "sg:phone":"+1 858 565 6145",
    "sg:postcode":"92111",
    "sg:province":"CA",
    "sg:tags":[
        "repairing",
        "automobile"
    ],
    "wof:name":"Kennedy Auto Electric",
    "wof:placetype":"venue"
},
  "geometry": {"coordinates":[-117.158598,32.829826],"type":"Point"}
}