{
  "type": "Feature",
  "properties": {
    "iso:country":"US",
    "sg:address":"10201 Trademark St",
    "sg:city":"Rancho Cucamonga",
    "sg:classifiers":[
        {
            "category":"Organizations",
            "subcategory":"Labor Organization",
            "type":"Services"
        }
    ],
    "sg:phone":"+1 909 980 8736",
    "sg:postcode":"91730",
    "sg:province":"CA",
    "sg:website":"www.cruzandassociates.com",
    "wof:name":"Cruz & Assoc Inc",
    "wof:placetype":"venue"
},
  "geometry": {"coordinates":[-117.58210099999999,34.080588],"type":"Point"}
}