{
  "type": "Feature",
  "properties": {
    "addr:full":"1309 Brookside Ave Redlands CA 92373",
    "addr:housenumber":"1309",
    "addr:postcode":"92373",
    "addr:street":"Brookside Ave",
    "iso:country":"US",
    "sg:address":"1309 Brookside Ave",
    "sg:city":"Redlands",
    "sg:classifiers":[
        {
            "category":"Personal",
            "type":"Services"
        }
    ],
    "sg:phone":"+1 909 307 8463",
    "sg:postcode":"92373",
    "sg:province":"CA",
    "sg:tags":[
        "therapist",
        "massage"
    ],
    "wof:name":"Joe's Massage Therapy",
    "wof:placetype":"venue"
},
  "geometry": {"coordinates":[-117.202319,34.046082],"type":"Point"}
}