{
  "type": "Feature",
  "properties": {
    "addr:full":"1500 E 17th St Santa Ana CA 92705",
    "addr:housenumber":"1500",
    "addr:postcode":"92705",
    "addr:street":"E 17Th St",
    "iso:country":"US",
    "sg:address":"1500 E 17th St",
    "sg:city":"Santa Ana",
    "sg:classifiers":[
        {
            "category":"Organizations",
            "subcategory":"Religious Organization",
            "type":"Services"
        }
    ],
    "sg:phone":"+1 714 835 8271",
    "sg:postcode":"92705",
    "sg:province":"CA",
    "wof:name":"First Church of the Nazarene Santa Ana",
    "wof:placetype":"venue"
},
  "geometry": {"coordinates":[-117.84699999999999,33.759899],"type":"Point"}
}