{
  "type": "Feature",
  "properties": {
    "iso:country":"US",
    "sg:address":"13640 Imperial Hwy",
    "sg:city":"Santa Fe Springs",
    "sg:classifiers":[
        {
            "category":"Wholesale",
            "subcategory":"Medical Equipment & Supplies",
            "type":"Manufacturing & Wholesale Goods"
        }
    ],
    "sg:phone":"+1 562 926 4954",
    "sg:postcode":"90670",
    "sg:province":"CA",
    "sg:tags":[
        "sun",
        "goggles",
        "sunglasses"
    ],
    "sg:website":"www.lawholesaledist.com",
    "wof:name":"L A Wholesale Distributors",
    "wof:placetype":"venue"
},
  "geometry": {"coordinates":[-118.04189700000001,33.916886],"type":"Point"}
}