{
  "type": "Feature",
  "properties": {
    "iso:country":"US",
    "sg:address":"2150 Vista Way",
    "sg:city":"Oceanside",
    "sg:classifiers":[
        {
            "category":"Shopping",
            "subcategory":"Stationery & Office Supplies",
            "type":"Retail Goods"
        },
        {
            "category":"Professional",
            "subcategory":"Printing & Photocopies",
            "type":"Services"
        }
    ],
    "sg:phone":"+1 760 754 5110",
    "sg:postcode":"92054",
    "sg:province":"CA",
    "sg:tags":[
        "equipment"
    ],
    "wof:name":"Staples",
    "wof:placetype":"venue"
},
  "geometry": {"coordinates":[-117.337997,33.182899],"type":"Point"}
}