{
  "type": "Feature",
  "properties": {
    "addr:full":"601 Ferry St Martinez CA 94553",
    "addr:housenumber":"601",
    "addr:postcode":"94553",
    "addr:street":"Ferry St",
    "iso:country":"US",
    "sg:address":"601 Ferry St",
    "sg:city":"Martinez",
    "sg:classifiers":[
        {
            "category":"Professional",
            "subcategory":"Business Services",
            "type":"Services"
        }
    ],
    "sg:phone":"+1 925 372 8295",
    "sg:postcode":"94553",
    "sg:province":"CA",
    "sg:tags":[
        "trade",
        "fair",
        "show"
    ],
    "wof:name":"First Night Martinez",
    "wof:placetype":"venue"
},
  "geometry": {"coordinates":[-122.135723,38.01773],"type":"Point"}
}