{
  "type": "Feature",
  "properties": {
    "addr:full":"16191 Construction Cir W Irvine CA 92606",
    "addr:housenumber":"16191",
    "addr:postcode":"92606",
    "addr:street":"Construction Cir W",
    "iso:country":"US",
    "sg:address":"16191 Construction Cir W",
    "sg:city":"Irvine",
    "sg:classifiers":[
        {
            "category":"Manufacturing",
            "subcategory":"Food",
            "type":"Manufacturing & Wholesale Goods"
        }
    ],
    "sg:phone":"+1 949 551 2588",
    "sg:postcode":"92606",
    "sg:province":"CA",
    "sg:tags":[
        "coffee",
        "mfg",
        "grocery",
        "roasted"
    ],
    "wof:name":"Specialty Coffee Services",
    "wof:placetype":"venue"
},
  "geometry": {"coordinates":[-117.823108,33.694961],"type":"Point"}
}