{
  "type": "Feature",
  "properties": {
    "iso:country":"US",
    "sg:address":"420 S Grand Ave",
    "sg:city":"Los Angeles",
    "sg:classifiers":[
        {
            "category":"Manufacturing",
            "subcategory":"Glass & Minerals",
            "type":"Manufacturing & Wholesale Goods"
        }
    ],
    "sg:phone":"+1 818 980 7880",
    "sg:postcode":"90071",
    "sg:province":"CA",
    "sg:tags":[
        "structural"
    ],
    "wof:name":"Architectural Glass Products",
    "wof:placetype":"venue"
},
  "geometry": {"coordinates":[-118.25307599999999,34.050991],"type":"Point"}
}