{
  "type": "Feature",
  "properties": {
    "iso:country":"US",
    "sg:address":"16935 Vanowen St",
    "sg:city":"Van Nuys",
    "sg:classifiers":[
        {
            "category":"Professional",
            "subcategory":"Management & Consulting",
            "type":"Services"
        }
    ],
    "sg:phone":"+1 818 343 2869",
    "sg:postcode":"91406",
    "sg:province":"CA",
    "sg:tags":[
        "retail",
        "direct",
        "sales"
    ],
    "wof:name":"Purified Waters",
    "wof:placetype":"venue"
},
  "geometry": {"coordinates":[-118.504861,34.19396],"type":"Point"}
}