{
  "type": "Feature",
  "properties": {
    "iso:country":"US",
    "sg:address":"21616 Western Ave.",
    "sg:city":"Torrance",
    "sg:classifiers":[
        {
            "category":"Restaurant",
            "type":"Food & Drink"
        },
        {
            "category":"Food & Beverages",
            "subcategory":"Groceries & Convenience Stores",
            "type":"Retail Goods"
        }
    ],
    "sg:phone":"+1 310 782 0335",
    "sg:postcode":"90501",
    "sg:province":"CA",
    "sg:tags":[
        "sushi",
        "bar"
    ],
    "wof:name":"Daikichi Mitsuwa",
    "wof:placetype":"venue"
},
  "geometry": {"coordinates":[-118.308984,33.832372],"type":"Point"}
}