{
  "type": "Feature",
  "properties": {
    "iso:country":"US",
    "sg:address":"156 S Park St",
    "sg:city":"San Francisco",
    "sg:classifiers":[
        {
            "category":"Real Estate",
            "subcategory":"Architect",
            "type":"Services"
        }
    ],
    "sg:phone":"+1 415 495 7889",
    "sg:postcode":"94107",
    "sg:province":"CA",
    "sg:website":"www.zackdevito.com",
    "wof:name":"Zack de Vito Architecture",
    "wof:placetype":"venue"
},
  "geometry": {"coordinates":[-122.394865,37.781349],"type":"Point"}
}