{
  "type": "Feature",
  "properties": {
    "iso:country":"US",
    "sg:address":"127 N Main St",
    "sg:city":"Manteca",
    "sg:classifiers":[
        {
            "category":"Shopping",
            "subcategory":"Clothing, Apparel, & Fashions",
            "type":"Retail Goods"
        }
    ],
    "sg:phone":"+1 209 239 5537",
    "sg:postcode":"95336",
    "sg:province":"CA",
    "sg:tags":[
        "baby",
        "accessory"
    ],
    "wof:name":"Tammy's Baby Shoppe",
    "wof:placetype":"venue"
},
  "geometry": {"coordinates":[-121.216447,37.797395],"type":"Point"}
}