{
  "type": "Feature",
  "properties": {
    "addr:full":"400 Underhill Dr Napa CA 94558",
    "addr:housenumber":"400",
    "addr:postcode":"94558",
    "addr:street":"Underhill Dr",
    "iso:country":"US",
    "sg:address":"400 Underhill Dr",
    "sg:city":"Napa",
    "sg:classifiers":[
        {
            "category":"Social Services",
            "subcategory":"Adult Care",
            "type":"Services"
        }
    ],
    "sg:phone":"+1 707 252 9791",
    "sg:postcode":"94558",
    "sg:province":"CA",
    "sg:tags":[
        "home",
        "residential"
    ],
    "wof:name":"Hill View Care Home",
    "wof:placetype":"venue"
},
  "geometry": {"coordinates":[-122.30503,38.287101],"type":"Point"}
}