{
  "type": "Feature",
  "properties": {
    "addr:full":"5552 Monterey Hwy San Jose CA 95138",
    "addr:housenumber":"5552",
    "addr:postcode":"95138",
    "addr:street":"Monterey Hwy",
    "iso:country":"US",
    "sg:address":"5552 Monterey Hwy",
    "sg:city":"San Jose",
    "sg:classifiers":[
        {
            "category":"Professional",
            "subcategory":"Accounting & Tax Preparation",
            "type":"Services"
        }
    ],
    "sg:phone":"+1 408 229 1650",
    "sg:postcode":"95138",
    "sg:province":"CA",
    "sg:tags":[
        "return",
        "filing"
    ],
    "wof:name":"H & R Block Tax Svc",
    "wof:placetype":"venue"
},
  "geometry": {"coordinates":[-121.79536400000001,37.251633],"type":"Point"}
}