{
  "type": "Feature",
  "properties": {
    "addr:full":"7263 Birdview Ave Malibu CA 90265",
    "addr:housenumber":"7263",
    "addr:postcode":"90265",
    "addr:street":"Birdview Ave",
    "iso:country":"US",
    "sg:address":"7263 Birdview Ave",
    "sg:city":"Malibu",
    "sg:classifiers":[
        {
            "category":"Farming",
            "subcategory":"Livestock Farm",
            "type":"Manufacturing & Wholesale Goods"
        }
    ],
    "sg:phone":"+1 310 589 0017",
    "sg:postcode":"90265",
    "sg:province":"CA",
    "sg:tags":[
        "ranch"
    ],
    "wof:name":"Malibu Ranch Treatment Ctr",
    "wof:placetype":"venue"
},
  "geometry": {"coordinates":[-118.810084,34.006284],"type":"Point"}
}