{
  "type": "Feature",
  "properties": {
    "addr:full":"Westfield Mission Valley 1640 Camino del Rio N San Diego CA 92108",
    "addr:housenumber":"1640",
    "addr:postcode":"92108",
    "addr:street":"Mission;Camino Del Rio N",
    "iso:country":"US",
    "sg:address":"Westfield Mission Valley 1640 Camino del Rio N",
    "sg:city":"San Diego",
    "sg:classifiers":[
        {
            "category":"Shopping",
            "subcategory":"Jewelry",
            "type":"Retail Goods"
        }
    ],
    "sg:phone":"+1 619 296 6375",
    "sg:postcode":"92108",
    "sg:province":"CA",
    "wof:name":"Icing By Claire's",
    "wof:placetype":"venue"
},
  "geometry": {"coordinates":[-117.14796,32.767194],"type":"Point"}
}