{
  "type": "Feature",
  "properties": {
    "addr:full":"1010 Cass St. Suite D8 Monterey CA 93940",
    "addr:housenumber":"1010",
    "addr:postcode":"93940",
    "addr:street":"Cass St. Suite D8",
    "iso:country":"US",
    "sg:address":"1010 Cass St. Suite D8",
    "sg:city":"Monterey",
    "sg:classifiers":[
        {
            "category":"Real Estate",
            "subcategory":"Real Estate Services",
            "type":"Services"
        },
        {
            "category":"Real Estate",
            "subcategory":"Real Estate Agent",
            "type":"Services"
        }
    ],
    "sg:phone":"+1 831 645 1000",
    "sg:postcode":"93940",
    "sg:province":"CA",
    "sg:tags":[
        "buyer",
        "consultant",
        "broker"
    ],
    "sg:website":"http://www.deervalleyproperties.com",
    "wof:name":"John Filighera of John Filighera and Associates, Inc.",
    "wof:placetype":"venue"
},
  "geometry": {"coordinates":[-121.89649799999999,36.592204],"type":"Point"}
}