{
  "type": "Feature",
  "properties": {
    "iso:country":"US",
    "sg:address":"847 W Roseburg Ave",
    "sg:city":"Modesto",
    "sg:classifiers":[
        {
            "category":"Shopping",
            "subcategory":"Used Merchandise",
            "type":"Retail Goods"
        }
    ],
    "sg:phone":"+1 209 529 4612",
    "sg:postcode":"95350",
    "sg:province":"CA",
    "sg:tags":[
        "shop",
        "consignment"
    ],
    "wof:name":"Ann's Consignment Shop",
    "wof:placetype":"venue"
},
  "geometry": {"coordinates":[-121.004887,37.660332],"type":"Point"}
}