{
  "type": "Feature",
  "properties": {
    "iso:country":"US",
    "sg:address":"1198 Oakdale St",
    "sg:city":"Chico",
    "sg:classifiers":[
        {
            "category":"Health Services",
            "subcategory":"Health Practitioner",
            "type":"Services"
        }
    ],
    "sg:phone":"+1 530 345 7994",
    "sg:postcode":"95928",
    "sg:province":"CA",
    "sg:tags":[
        "midwife"
    ],
    "wof:name":"Birthdance-Midwifery",
    "wof:placetype":"venue"
},
  "geometry": {"coordinates":[-121.833066,39.723607],"type":"Point"}
}