{
  "type": "Feature",
  "properties": {
    "addr:full":"828 N Virgil Ave Los Angeles CA 90029",
    "addr:housenumber":"828",
    "addr:postcode":"90029",
    "addr:street":"N Virgil Ave",
    "iso:country":"US",
    "sg:address":"828 N Virgil Ave",
    "sg:city":"Los Angeles",
    "sg:classifiers":[
        {
            "category":"Wholesale",
            "subcategory":"Machinery & Supplies",
            "type":"Manufacturing & Wholesale Goods"
        }
    ],
    "sg:phone":"+1 323 662 1771",
    "sg:postcode":"90029",
    "sg:province":"CA",
    "sg:tags":[
        "dyer",
        "cleaners",
        "equipment"
    ],
    "wof:name":"K H Machinery Co",
    "wof:placetype":"venue"
},
  "geometry": {"coordinates":[-118.286781,34.085939],"type":"Point"}
}