{
  "type": "Feature",
  "properties": {
    "iso:country":"US",
    "sg:address":"618 E 11th St",
    "sg:city":"Oakland",
    "sg:classifiers":[
        {
            "category":"Home & Garden",
            "subcategory":"Furniture",
            "type":"Retail Goods"
        }
    ],
    "sg:phone":"+1 510 763 1326",
    "sg:postcode":"94606",
    "sg:province":"CA",
    "wof:name":"Don Braden Designs",
    "wof:placetype":"venue"
},
  "geometry": {"coordinates":[-122.254179,37.793096],"type":"Point"}
}