{
  "type": "Feature",
  "properties": {
    "addr:full":"7312 Macarthur Blvd Oakland CA 94605",
    "addr:housenumber":"7312",
    "addr:postcode":"94605",
    "addr:street":"Macarthur Blvd",
    "iso:country":"US",
    "sg:address":"7312 Macarthur Blvd",
    "sg:city":"Oakland",
    "sg:classifiers":[
        {
            "category":"Restaurant",
            "type":"Food & Drink"
        }
    ],
    "sg:phone":"+1 510 969 7295",
    "sg:postcode":"94605",
    "sg:province":"CA",
    "sg:tags":[
        "seafood"
    ],
    "wof:name":"Off The Hook 20",
    "wof:placetype":"venue"
},
  "geometry": {"coordinates":[-122.17193899999999,37.76907],"type":"Point"}
}