{
  "type": "Feature",
  "properties": {
    "iso:country":"US",
    "sg:address":"14852 Ventura Blvd",
    "sg:city":"Sherman Oaks",
    "sg:classifiers":[
        {
            "category":"Shopping",
            "type":"Retail Goods"
        }
    ],
    "sg:phone":"+1 818 986 6655",
    "sg:postcode":"91403",
    "sg:province":"CA",
    "sg:tags":[
        "merchandise",
        "supply"
    ],
    "wof:name":"Treasure Memories Inc",
    "wof:placetype":"venue"
},
  "geometry": {"coordinates":[-118.457272,34.152255],"type":"Point"}
}