{
  "type": "Feature",
  "properties": {
    "addr:full":"14418 Hawthorne Boulevard Lawndale CA 90260",
    "addr:housenumber":"14418",
    "addr:postcode":"ca 90260",
    "addr:street":"Hawthorne Boulevard",
    "iso:country":"US",
    "sg:address":"14418 Hawthorne Boulevard",
    "sg:city":"Lawndale",
    "sg:classifiers":[
        {
            "category":"Restaurant",
            "type":"Food & Drink"
        }
    ],
    "sg:phone":"+1 310 644 4007",
    "sg:postcode":"90260",
    "sg:province":"CA",
    "wof:name":"Number One Buffet",
    "wof:placetype":"venue"
},
  "geometry": {"coordinates":[-118.352479,33.900231],"type":"Point"}
}