{
  "type": "Feature",
  "properties": {
    "addr:full":"1900 S Del Mar Ave San Gabriel CA 91776",
    "addr:housenumber":"1900",
    "addr:postcode":"91776",
    "addr:street":"S Del Mar Ave",
    "iso:country":"US",
    "sg:address":"1900 S Del Mar Ave",
    "sg:city":"San Gabriel",
    "sg:classifiers":[
        {
            "category":"Coffee & Tea",
            "type":"Food & Drink"
        }
    ],
    "sg:phone":"+1 626 573 8846",
    "sg:postcode":"91776",
    "sg:province":"CA",
    "wof:name":"Jazz Cafe",
    "wof:placetype":"venue"
},
  "geometry": {"coordinates":[-118.099998,34.075401],"type":"Point"}
}