{
  "type": "Feature",
  "properties": {
    "iso:country":"US",
    "sg:address":"229 Main St",
    "sg:city":"Sierra City",
    "sg:classifiers":[
        {
            "category":"Government",
            "subcategory":"Fire Station",
            "type":"Public Place"
        }
    ],
    "sg:phone":"+1 530 862 1558",
    "sg:postcode":"96125",
    "sg:province":"CA",
    "sg:tags":[
        "protection"
    ],
    "wof:name":"Sierra City Fire District",
    "wof:placetype":"venue"
},
  "geometry": {"coordinates":[-120.6292,39.567512],"type":"Point"}
}