{
  "type": "Feature",
  "properties": {
    "addr:full":"11054 W Pico Blvd Los Angeles CA 90064",
    "addr:housenumber":"11054",
    "addr:postcode":"90064",
    "addr:street":"W Pico Blvd",
    "iso:country":"US",
    "sg:address":"11054 W Pico Blvd",
    "sg:city":"Los Angeles",
    "sg:classifiers":[
        {
            "category":"Utilities",
            "subcategory":"Mobile Phone",
            "type":"Services"
        }
    ],
    "sg:phone":"+1 310 481 0444",
    "sg:postcode":"90064",
    "sg:province":"CA",
    "sg:tags":[
        "telephone",
        "cellular"
    ],
    "wof:name":"Nationwide Wireless Svc",
    "wof:placetype":"venue"
},
  "geometry": {"coordinates":[-118.433454,34.037742],"type":"Point"}
}