{
  "type": "Feature",
  "properties": {
    "iso:country":"US",
    "sg:address":"1180 S Miramar Ave",
    "sg:city":"Anaheim",
    "sg:classifiers":[
        {
            "category":"Professional",
            "type":"Services"
        }
    ],
    "sg:phone":"+1 714 280 8348",
    "sg:postcode":"92808",
    "sg:province":"CA",
    "wof:name":"Dorthy A Markovsky",
    "wof:placetype":"venue"
},
  "geometry": {"coordinates":[-117.740278,33.850022],"type":"Point"}
}