{
  "type": "Feature",
  "properties": {
    "iso:country":"US",
    "sg:address":"6402 Hollywood Blvd",
    "sg:city":"Los Angeles",
    "sg:classifiers":[
        {
            "category":"Shopping",
            "subcategory":"Clothing, Apparel, & Fashions",
            "type":"Retail Goods"
        }
    ],
    "sg:phone":"+1 323 871 0223",
    "sg:postcode":"90028",
    "sg:province":"CA",
    "sg:tags":[
        "baby",
        "accessory"
    ],
    "wof:name":"Tie Collection",
    "wof:placetype":"venue"
},
  "geometry": {"coordinates":[-118.331011,34.101519],"type":"Point"}
}