{
  "type": "Feature",
  "properties": {
    "addr:full":"8650 Genesee Ave San Diego CA 92122",
    "addr:housenumber":"8650",
    "addr:postcode":"92122",
    "addr:street":"Genesee Ave",
    "iso:country":"US",
    "sg:address":"8650 Genesee Ave",
    "sg:city":"San Diego",
    "sg:classifiers":[
        {
            "category":"Restaurant",
            "type":"Food & Drink"
        }
    ],
    "sg:phone":"+1 858 404 9898",
    "sg:postcode":"92122",
    "sg:province":"CA",
    "wof:name":"Sammy's California Woodfired",
    "wof:placetype":"venue"
},
  "geometry": {"coordinates":[-117.214083,32.868301],"type":"Point"}
}