{
  "type": "Feature",
  "properties": {
    "addr:full":"3912 Portola Dr Santa Cruz CA 95062",
    "addr:housenumber":"3912",
    "addr:postcode":"95062",
    "addr:street":"Portola Dr",
    "iso:country":"US",
    "sg:address":"3912 Portola Dr",
    "sg:city":"Santa Cruz",
    "sg:classifiers":[
        {
            "category":"Home & Garden",
            "subcategory":"Mobile Homes",
            "type":"Retail Goods"
        }
    ],
    "sg:phone":"+1 831 475 0489",
    "sg:postcode":"95062",
    "sg:province":"CA",
    "wof:name":"Far West Trailer Sales",
    "wof:placetype":"venue"
},
  "geometry": {"coordinates":[-121.96653999999999,36.96334],"type":"Point"}
}