{
  "type": "Feature",
  "properties": {
    "iso:country":"US",
    "sg:address":"425 W Junipero St",
    "sg:city":"Santa Barbara",
    "sg:classifiers":[
        {
            "category":"Health Services",
            "subcategory":"Doctor",
            "type":"Services"
        }
    ],
    "sg:phone":"+1 805 682 7751",
    "sg:postcode":"93105",
    "sg:province":"CA",
    "sg:tags":[
        "physician",
        "surgeon"
    ],
    "sg:website":"www.amgsb.com",
    "wof:name":"Anesthesia Medical Group",
    "wof:placetype":"venue"
},
  "geometry": {"coordinates":[-119.725408,34.429271],"type":"Point"}
}