{
  "type": "Feature",
  "properties": {
    "addr:full":"2835 Sebastopol Rd Santa Rosa CA 95407",
    "addr:housenumber":"2835",
    "addr:postcode":"95407",
    "addr:street":"Sebastopol Rd",
    "iso:country":"US",
    "sg:address":"2835 Sebastopol Rd",
    "sg:city":"Santa Rosa",
    "sg:classifiers":[
        {
            "category":"Retail",
            "subcategory":"Auto Repair",
            "type":"Services"
        }
    ],
    "sg:phone":"+1 707 578 1592",
    "sg:postcode":"95407",
    "sg:province":"CA",
    "sg:tags":[
        "repairing",
        "automobile"
    ],
    "sg:website":"www.amvolvos.com",
    "wof:name":"Angel Motors",
    "wof:placetype":"venue"
},
  "geometry": {"coordinates":[-122.74837100000001,38.42631],"type":"Point"}
}