{
  "type": "Feature",
  "properties": {
    "addr:full":"360 Mobil Ave Camarillo CA 93010",
    "addr:postcode":"93010",
    "addr:street":"Ave",
    "iso:country":"US",
    "sg:address":"360 Mobil Ave",
    "sg:city":"Camarillo",
    "sg:classifiers":[
        {
            "category":"Professional",
            "subcategory":"Lawyer & Legal Services",
            "type":"Services"
        }
    ],
    "sg:phone":"+1 805 484 0453",
    "sg:postcode":"93010",
    "sg:province":"CA",
    "sg:tags":[
        "personal",
        "injury"
    ],
    "wof:name":"Schulner Keith A",
    "wof:placetype":"venue"
},
  "geometry": {"coordinates":[-119.04299899999999,34.2202],"type":"Point"}
}