{
  "type": "Feature",
  "properties": {
    "iso:country":"US",
    "sg:address":"17081 Hwy 116",
    "sg:city":"Guerneville",
    "sg:classifiers":[
        {
            "category":"Utilities",
            "subcategory":"Water",
            "type":"Services"
        }
    ],
    "sg:phone":"+1 707 869 4000",
    "sg:postcode":"95446",
    "sg:province":"CA",
    "sg:tags":[
        "company",
        "sewage"
    ],
    "sg:website":"www.sweetwatersprings.com",
    "wof:name":"Sweetwater Springs Water Distr",
    "wof:placetype":"venue"
},
  "geometry": {"coordinates":[-123.007621,38.495799],"type":"Point"}
}