{
  "type": "Feature",
  "properties": {
    "addr:full":"625 Cherry St Santa Rosa CA 95404",
    "addr:housenumber":"625",
    "addr:postcode":"95404",
    "addr:street":"Cherry St",
    "iso:country":"US",
    "sg:address":"625 Cherry St",
    "sg:city":"Santa Rosa",
    "sg:classifiers":[
        {
            "category":"Health Services",
            "subcategory":"Health Practitioner",
            "type":"Services"
        }
    ],
    "sg:phone":"+1 707 571 8586",
    "sg:postcode":"95404",
    "sg:province":"CA",
    "sg:tags":[
        "psychologist"
    ],
    "wof:name":"Shirley Peeke PHD",
    "wof:placetype":"venue"
},
  "geometry": {"coordinates":[-122.71533599999999,38.444689],"type":"Point"}
}