{
  "type": "Feature",
  "properties": {
    "iso:country":"US",
    "sg:address":"11933 Santa Monica Blvd",
    "sg:city":"Los Angeles",
    "sg:classifiers":[
        {
            "category":"Food & Beverages",
            "subcategory":"Groceries & Convenience Stores",
            "type":"Retail Goods"
        }
    ],
    "sg:phone":"+1 310 996 1066",
    "sg:postcode":"90025",
    "sg:province":"CA",
    "sg:tags":[
        "market"
    ],
    "wof:name":"LA Zandunga Meat Market",
    "wof:placetype":"venue"
},
  "geometry": {"coordinates":[-118.460729,34.041826],"type":"Point"}
}