{
  "type": "Feature",
  "properties": {
    "addr:full":"19300 Beach Boulevard Huntington Beach CA 92648",
    "addr:housenumber":"19300",
    "addr:postcode":"92648",
    "addr:street":"Beach Boulevard",
    "iso:country":"US",
    "sg:address":"19300 Beach Boulevard",
    "sg:city":"Huntington Beach",
    "sg:classifiers":[
        {
            "category":"Autos & Motor Vehicles",
            "subcategory":"Auto Supplies",
            "type":"Retail Goods"
        },
        {
            "category":"Retail",
            "subcategory":"Auto Repair",
            "type":"Services"
        }
    ],
    "sg:phone":"+1 714 593 4094",
    "sg:postcode":"92648",
    "sg:province":"CA",
    "sg:tags":[
        "tire"
    ],
    "wof:name":"Schmidty's Garage",
    "wof:placetype":"venue"
},
  "geometry": {"coordinates":[-117.988586,33.682112],"type":"Point"}
}