{
  "type": "Feature",
  "properties": {
    "iso:country":"US",
    "sg:address":"728 N 12th St",
    "sg:city":"El Centro",
    "sg:classifiers":[
        {
            "category":"Shopping",
            "subcategory":"Discount & Variety Stores",
            "type":"Retail Goods"
        }
    ],
    "sg:phone":"+1 760 336 0394",
    "sg:postcode":"92243",
    "sg:province":"CA",
    "sg:tags":[
        "merchandise",
        "general"
    ],
    "wof:name":"Cactus Thrift Shop",
    "wof:placetype":"venue"
},
  "geometry": {"coordinates":[-115.565713,32.799042],"type":"Point"}
}