{
  "type": "Feature",
  "properties": {
    "addr:full":"2408 Lascar Pl Suite 7 San Jose CA 95124",
    "addr:postcode":"2408;95124",
    "addr:street":"Lascar Pl Suite 7",
    "iso:country":"US",
    "sg:address":"2408 Lascar Pl Suite 7",
    "sg:city":"San Jose",
    "sg:classifiers":[
        {
            "category":"Banks & Credit Unions",
            "subcategory":"Financial Services",
            "type":"Services"
        }
    ],
    "sg:phone":"+1 408 626 7930",
    "sg:postcode":"95124",
    "sg:province":"CA",
    "sg:tags":[
        "broker",
        "mortgage"
    ],
    "sg:website":"www.giuffreproperties.com",
    "wof:name":"Giuffre Properties",
    "wof:placetype":"venue"
},
  "geometry": {"coordinates":[-121.94859700000001,37.256364],"type":"Point"}
}