{
  "type": "Feature",
  "properties": {
    "addr:full":"14230 Victory Blvd Van Nuys CA 91401",
    "addr:housenumber":"14230",
    "addr:postcode":"91401",
    "addr:street":"Victory Blvd",
    "iso:country":"US",
    "sg:address":"14230 Victory Blvd",
    "sg:city":"Van Nuys",
    "sg:classifiers":[
        {
            "category":"Real Estate",
            "subcategory":"Real Estate Operator",
            "type":"Services"
        }
    ],
    "sg:phone":"+1 818 994 0675",
    "sg:postcode":"91401",
    "sg:province":"CA",
    "sg:tags":[
        "apartment"
    ],
    "wof:name":"Victory Associates",
    "wof:placetype":"venue"
},
  "geometry": {"coordinates":[-118.44379600000001,34.186588],"type":"Point"}
}