{
  "type": "Feature",
  "properties": {
    "addr:full":"1141 Howard Richmond CA 94804",
    "addr:housenumber":"1141",
    "addr:postcode":"94804",
    "addr:street":"Howard",
    "iso:country":"US",
    "sg:address":"1141 Howard",
    "sg:city":"Richmond",
    "sg:classifiers":[
        {
            "category":"Shopping",
            "subcategory":"Mobile Phones",
            "type":"Retail Goods"
        }
    ],
    "sg:phone":"+1 510 525 8988",
    "sg:postcode":"94804",
    "sg:province":"CA",
    "wof:name":"Impact Communication Service",
    "wof:placetype":"venue"
},
  "geometry": {"coordinates":[-122.339996,37.924],"type":"Point"}
}