{
  "type": "Feature",
  "properties": {
    "addr:full":"1601 Bayside Drive Corona Del Mar CA 92625",
    "addr:housenumber":"1601",
    "addr:postcode":"92625",
    "addr:street":"Bayside Drive",
    "iso:country":"US",
    "sg:address":"1601 Bayside Drive",
    "sg:city":"Corona Del Mar",
    "sg:classifiers":[
        {
            "category":"Recreation",
            "subcategory":"Boat Charter",
            "type":"Entertainment"
        }
    ],
    "sg:phone":"+1 949 644 9530",
    "sg:postcode":"92625",
    "sg:province":"CA",
    "sg:tags":[
        "boating"
    ],
    "wof:name":"Bahia Corinthian Yacht Club",
    "wof:placetype":"venue"
},
  "geometry": {"coordinates":[-117.88457,33.607217],"type":"Point"}
}