{
  "type": "Feature",
  "properties": {
    "addr:full":"5242 Lincoln Ave Cypress CA 90630",
    "addr:housenumber":"5242",
    "addr:postcode":"90630",
    "addr:street":"Lincoln Ave",
    "iso:country":"US",
    "sg:address":"5242 Lincoln Ave",
    "sg:city":"Cypress",
    "sg:classifiers":[
        {
            "category":"Real Estate",
            "subcategory":"Real Estate Agent",
            "type":"Services"
        }
    ],
    "sg:phone":"+1 714 527 7557",
    "sg:postcode":"90630",
    "sg:province":"CA",
    "wof:name":"Colannino Realty Inc",
    "wof:placetype":"venue"
},
  "geometry": {"coordinates":[-118.03921200000001,33.831706],"type":"Point"}
}