{
  "type": "Feature",
  "properties": {
    "iso:country":"US",
    "sg:address":"5713 Bulford Pl",
    "sg:city":"Lancaster",
    "sg:classifiers":[
        {
            "category":"Building & Trades",
            "subcategory":"Construction",
            "type":"Services"
        }
    ],
    "sg:phone":"+1 661 718 0238",
    "sg:postcode":"93536",
    "sg:province":"CA",
    "sg:tags":[
        "contractor"
    ],
    "wof:name":"Cannon Construction",
    "wof:placetype":"venue"
},
  "geometry": {"coordinates":[-118.23318399999999,34.638808],"type":"Point"}
}