{
  "type": "Feature",
  "properties": {
    "addr:full":"230 N Bush St Santa Ana CA 92701",
    "addr:housenumber":"230",
    "addr:postcode":"92701",
    "addr:street":"N Bush St",
    "iso:country":"US",
    "sg:address":"230 N Bush St",
    "sg:city":"Santa Ana",
    "sg:classifiers":[
        {
            "category":"Professional",
            "subcategory":"Lawyer & Legal Services",
            "type":"Services"
        }
    ],
    "sg:phone":"+1 714 835 5585",
    "sg:postcode":"92701",
    "sg:province":"CA",
    "sg:tags":[
        "attorney"
    ],
    "wof:name":"Fernando Leone Law Offices",
    "wof:placetype":"venue"
},
  "geometry": {"coordinates":[-117.866685,33.74694],"type":"Point"}
}