{
  "type": "Feature",
  "properties": {
    "iso:country":"US",
    "sg:address":"520 E McGlincey Ln",
    "sg:city":"Campbell",
    "sg:classifiers":[
        {
            "category":"Wholesale",
            "subcategory":"Construction Materials",
            "type":"Manufacturing & Wholesale Goods"
        }
    ],
    "sg:phone":"+1 408 265 7940",
    "sg:postcode":"95008",
    "sg:province":"CA",
    "sg:tags":[
        "marble"
    ],
    "wof:name":"Marble Dimensions Co",
    "wof:placetype":"venue"
},
  "geometry": {"coordinates":[-121.942641,37.276148],"type":"Point"}
}