{
  "type": "Feature",
  "properties": {
    "addr:full":"252 Florence Way San Jose CA 95110",
    "addr:housenumber":"252",
    "addr:postcode":"95110",
    "addr:street":"Florence Way",
    "iso:country":"US",
    "sg:address":"252 Florence Way",
    "sg:city":"San Jose",
    "sg:classifiers":[
        {
            "category":"Building & Trades",
            "subcategory":"Plumbing",
            "type":"Services"
        }
    ],
    "sg:phone":"+1 408 409 4701",
    "sg:postcode":"95110",
    "sg:province":"CA",
    "sg:website":"plumbingsanjose.net",
    "wof:name":"AAA Pros Plumbing & Rooter",
    "wof:placetype":"venue"
},
  "geometry": {"coordinates":[-121.898691,37.327483],"type":"Point"}
}