{
  "type": "Feature",
  "properties": {
    "addr:full":"704 Ocean Ave Seal Beach CA 90740",
    "addr:housenumber":"704",
    "addr:postcode":"90740",
    "addr:street":"Ocean Ave",
    "iso:country":"US",
    "sg:address":"704 Ocean Ave",
    "sg:city":"Seal Beach",
    "sg:classifiers":[
        {
            "category":"Professional",
            "type":"Services"
        }
    ],
    "sg:phone":"+1 562 431 4836",
    "sg:postcode":"90740",
    "sg:province":"CA",
    "wof:name":"Daniel P Mundy",
    "wof:placetype":"venue"
},
  "geometry": {"coordinates":[-118.106848,33.740273],"type":"Point"}
}