{
  "type": "Feature",
  "properties": {
    "iso:country":"US",
    "sg:address":"10855 Venice Boulevard",
    "sg:city":"Los Angeles",
    "sg:classifiers":[
        {
            "category":"Restaurant",
            "type":"Food & Drink"
        }
    ],
    "sg:phone":"+1 310 559 8891",
    "sg:postcode":"90034",
    "sg:province":"CA",
    "sg:tags":[
        "mexican"
    ],
    "wof:name":"Fidel's",
    "wof:placetype":"venue"
},
  "geometry": {"coordinates":[-118.41028,34.016815],"type":"Point"}
}