{
  "type": "Feature",
  "properties": {
    "addr:full":"1303 High St Alameda CA 94501",
    "addr:housenumber":"1303",
    "addr:postcode":"94501",
    "addr:street":"High St",
    "iso:country":"US",
    "sg:address":"1303 High St",
    "sg:city":"Alameda",
    "sg:classifiers":[
        {
            "category":"Restaurant",
            "type":"Food & Drink"
        },
        {
            "category":"Coffee & Tea",
            "type":"Food & Drink"
        },
        {
            "category":"Arts & Performance",
            "subcategory":"Music",
            "type":"Entertainment"
        }
    ],
    "sg:phone":"+1 510 995 8049",
    "sg:postcode":"94501",
    "sg:province":"CA",
    "sg:tags":[
        "style",
        "family",
        "espresso",
        "venue",
        "american",
        "new",
        "cafeteria"
    ],
    "sg:website":"www.highstreetstationcafe.com",
    "wof:name":"High Street Station",
    "wof:placetype":"venue"
},
  "geometry": {"coordinates":[-122.2342,37.756472],"type":"Point"}
}