{
  "type": "Feature",
  "properties": {
    "iso:country":"US",
    "sg:address":"1700 N Chester Ave",
    "sg:city":"Bakersfield",
    "sg:classifiers":[
        {
            "category":"Real Estate",
            "subcategory":"Surveying",
            "type":"Services"
        }
    ],
    "sg:phone":"+1 661 399 9006",
    "sg:postcode":"93308",
    "sg:province":"CA",
    "sg:tags":[
        "surveyor"
    ],
    "wof:name":"Nelms Surveying",
    "wof:placetype":"venue"
},
  "geometry": {"coordinates":[-119.021197,35.422232],"type":"Point"}
}