{
  "type": "Feature",
  "properties": {
    "iso:country":"US",
    "sg:address":"10829 S Etiwanda Ave",
    "sg:city":"Fontana",
    "sg:classifiers":[
        {
            "category":"Wholesale",
            "subcategory":"Machinery & Supplies",
            "type":"Manufacturing & Wholesale Goods"
        }
    ],
    "sg:phone":"+1 909 829 4000",
    "sg:postcode":"92337",
    "sg:province":"CA",
    "sg:tags":[
        "equipment",
        "industrial"
    ],
    "wof:name":"Industrial Cases Inc",
    "wof:placetype":"venue"
},
  "geometry": {"coordinates":[-117.524126,34.062205],"type":"Point"}
}