{
  "type": "Feature",
  "properties": {
    "addr:full":"6659 Topanga Canyon Blvd Woodland Hills CA 91303",
    "addr:housenumber":"6659",
    "addr:postcode":"91303",
    "addr:street":"Topanga Canyon Blvd",
    "iso:country":"US",
    "sg:address":"6659 Topanga Canyon Blvd",
    "sg:city":"Woodland Hills",
    "sg:classifiers":[
        {
            "category":"Home & Garden",
            "subcategory":"Furniture",
            "type":"Retail Goods"
        }
    ],
    "sg:phone":"+1 818 346 8085",
    "sg:postcode":"91303",
    "sg:province":"CA",
    "sg:tags":[
        "mattress"
    ],
    "wof:name":"Leeds Mattress Stores",
    "wof:placetype":"venue"
},
  "geometry": {"coordinates":[-118.606003,34.191601],"type":"Point"}
}