{
  "type": "Feature",
  "properties": {
    "addr:full":"2429 Roosevelt Ave Berkeley CA 94703",
    "addr:housenumber":"2429",
    "addr:postcode":"94703",
    "addr:street":"Roosevelt Ave",
    "iso:country":"US",
    "sg:address":"2429 Roosevelt Ave",
    "sg:city":"Berkeley",
    "sg:classifiers":[
        {
            "category":"Professional",
            "subcategory":"Research",
            "type":"Services"
        }
    ],
    "sg:phone":"+1 510 841 0959",
    "sg:postcode":"94703",
    "sg:province":"CA",
    "sg:tags":[
        "educational"
    ],
    "sg:website":"http://www.johncallawaymusic.com",
    "wof:name":"John C Callaway",
    "wof:placetype":"venue"
},
  "geometry": {"coordinates":[-122.27564,37.864203],"type":"Point"}
}