{
  "type": "Feature",
  "properties": {
    "iso:country":"US",
    "sg:address":"13003 Barton Rd",
    "sg:city":"Whittier",
    "sg:classifiers":[
        {
            "category":"Building & Trades",
            "subcategory":"Landscaping Services",
            "type":"Services"
        }
    ],
    "sg:phone":"+1 562 944 2059",
    "sg:postcode":"90605",
    "sg:province":"CA",
    "sg:tags":[
        "supply"
    ],
    "wof:name":"Kay Kayasuga",
    "wof:placetype":"venue"
},
  "geometry": {"coordinates":[-118.052206,33.948525],"type":"Point"}
}