{
  "type": "Feature",
  "properties": {
    "iso:country":"US",
    "sg:address":"2911 4th St",
    "sg:city":"Santa Monica",
    "sg:classifiers":[
        {
            "category":"Professional",
            "subcategory":"Business Services",
            "type":"Services"
        }
    ],
    "sg:phone":"+1 310 392 7373",
    "sg:postcode":"90405",
    "sg:province":"CA",
    "wof:name":"Randle Squeezebox Productions",
    "wof:placetype":"venue"
},
  "geometry": {"coordinates":[-118.477922,34.000588],"type":"Point"}
}