{
  "type": "Feature",
  "properties": {
    "addr:full":"3756 Grand Ave Oakland CA 94610",
    "addr:housenumber":"3756",
    "addr:postcode":"94610",
    "addr:street":"Grand Ave",
    "iso:country":"US",
    "sg:address":"3756 Grand Ave",
    "sg:city":"Oakland",
    "sg:classifiers":[
        {
            "category":"Real Estate",
            "subcategory":"Surveying",
            "type":"Services"
        }
    ],
    "sg:phone":"+1 510 839 8078",
    "sg:postcode":"94610",
    "sg:province":"CA",
    "sg:tags":[
        "surveyor",
        "land"
    ],
    "wof:name":"Maes John Rm",
    "wof:placetype":"venue"
},
  "geometry": {"coordinates":[-122.245279,37.817009],"type":"Point"}
}