{
  "type": "Feature",
  "properties": {
    "iso:country":"US",
    "sg:address":"3116 Pacific Coast Highway",
    "sg:city":"Torrance",
    "sg:classifiers":[
        {
            "category":"Professional",
            "subcategory":"Printing & Photocopies",
            "type":"Services"
        }
    ],
    "sg:phone":"+1 310 325 5271",
    "sg:postcode":"90505",
    "sg:province":"CA",
    "wof:name":"Minuteman Press South Torrance",
    "wof:placetype":"venue"
},
  "geometry": {"coordinates":[-118.340771,33.797902],"type":"Point"}
}