{
  "type": "Feature",
  "properties": {
    "iso:country":"US",
    "sg:address":"9 Pigeon Hollow Rd",
    "sg:city":"San Rafael",
    "sg:classifiers":[
        {
            "category":"Communications",
            "subcategory":"Film & Video Production",
            "type":"Services"
        }
    ],
    "sg:phone":"+1 415 497 3494",
    "sg:postcode":"94901",
    "sg:province":"CA",
    "sg:tags":[
        "motion",
        "picture",
        "studio",
        "producer"
    ],
    "wof:name":"Blast Off Productions",
    "wof:placetype":"venue"
},
  "geometry": {"coordinates":[-122.504476,37.972113],"type":"Point"}
}