{
  "type": "Feature",
  "properties": {
    "iso:country":"US",
    "sg:address":"540 N Marengo Ave",
    "sg:city":"Pasadena",
    "sg:classifiers":[
        {
            "category":"Health Services",
            "subcategory":"Doctor",
            "type":"Services"
        }
    ],
    "sg:phone":"+1 626 356 4681",
    "sg:postcode":"91101",
    "sg:province":"CA",
    "sg:tags":[
        "medicine",
        "physician",
        "practice",
        "surgeons",
        "family"
    ],
    "wof:name":"The Family Imperial Center",
    "wof:placetype":"venue"
},
  "geometry": {"coordinates":[-118.146011,34.154946],"type":"Point"}
}