{
  "type": "Feature",
  "properties": {
    "addr:full":"936 E Pico Blvd Los Angeles CA 90021",
    "addr:housenumber":"936",
    "addr:postcode":"90021",
    "addr:street":"E Pico Blvd",
    "iso:country":"US",
    "sg:address":"936 E Pico Blvd",
    "sg:city":"Los Angeles",
    "sg:classifiers":[
        {
            "category":"Wholesale",
            "subcategory":"Apparel",
            "type":"Manufacturing & Wholesale Goods"
        }
    ],
    "sg:phone":"+1 213 748 2618",
    "sg:postcode":"90021",
    "sg:province":"CA",
    "sg:tags":[
        "textile"
    ],
    "wof:name":"21st Century Textile",
    "wof:placetype":"venue"
},
  "geometry": {"coordinates":[-118.248728,34.030451],"type":"Point"}
}