{
  "type": "Feature",
  "properties": {
    "addr:full":"16216 Greenwood Rd Los Gatos CA 95030",
    "addr:housenumber":"16216",
    "addr:postcode":"95030",
    "addr:street":"Greenwood Rd",
    "iso:country":"US",
    "sg:address":"16216 Greenwood Rd",
    "sg:city":"Los Gatos",
    "sg:classifiers":[
        {
            "category":"Professional",
            "type":"Services"
        }
    ],
    "sg:phone":"+1 408 395 0774",
    "sg:postcode":"95030",
    "sg:province":"CA",
    "wof:name":"Tricoter",
    "wof:placetype":"venue"
},
  "geometry": {"coordinates":[-121.998718,37.232341],"type":"Point"}
}