{
  "type": "Feature",
  "properties": {
    "addr:full":"725 N Broadway Ave Stockton CA 95205",
    "addr:housenumber":"725",
    "addr:postcode":"95205",
    "addr:street":"N Broadway Ave",
    "iso:country":"US",
    "sg:address":"725 N Broadway Ave",
    "sg:city":"Stockton",
    "sg:classifiers":[
        {
            "category":"Communications",
            "subcategory":"Film & Video Production",
            "type":"Services"
        },
        {
            "category":"Retail",
            "subcategory":"Laundry & Dry Cleaning",
            "type":"Services"
        },
        {
            "category":"Home & Garden",
            "subcategory":"Household Appliances",
            "type":"Retail Goods"
        },
        {
            "category":"Building & Trades",
            "subcategory":"Cleaning & Sanitation",
            "type":"Services"
        },
        {
            "category":"Building & Trades",
            "subcategory":"Construction",
            "type":"Services"
        }
    ],
    "sg:phone":"+1 209 463 2349",
    "sg:postcode":"95205",
    "sg:province":"CA",
    "sg:tags":[
        "cleaner",
        "duct",
        "house",
        "scene",
        "crime",
        "curtain",
        "carpet",
        "damage",
        "contractor",
        "cleaning-industrial",
        "board",
        "trauma",
        "drapery",
        "fire",
        "rug",
        "water",
        "restoration",
        "vacuum",
        "upholstery",
        "air",
        "ventilation",
        "clean"
    ],
    "sg:website":"http://www.servicemasterclean.com/reslf/smclean_leadform.asp?url=http://www.servicemasterclean.com/reslf/smclean_leadform.asp&partnerName=YellowPages.com&adName=yptl&HGProp=SMClean",
    "wof:name":"ServiceMaster Clean",
    "wof:placetype":"venue"
},
  "geometry": {"coordinates":[-121.249359,37.969358],"type":"Point"}
}