{
  "type": "Feature",
  "properties": {
    "addr:full":"632 Cottonwood St Woodland CA 95695",
    "addr:housenumber":"632",
    "addr:postcode":"95695",
    "addr:street":"Cottonwood St",
    "iso:country":"US",
    "sg:address":"632 Cottonwood St",
    "sg:city":"Woodland",
    "sg:classifiers":[
        {
            "category":"Food & Beverages",
            "subcategory":"Liquor & Beverages",
            "type":"Retail Goods"
        }
    ],
    "sg:phone":"+1 530 666 4705",
    "sg:postcode":"95695",
    "sg:province":"CA",
    "wof:name":"Bob's Food & Liquor",
    "wof:placetype":"venue"
},
  "geometry": {"coordinates":[-121.79345600000001,38.672671],"type":"Point"}
}