{
  "type": "Feature",
  "properties": {
    "iso:country":"US",
    "sg:address":"1324 W Jefferson Blvd",
    "sg:city":"Los Angeles",
    "sg:classifiers":[
        {
            "category":"Shopping",
            "subcategory":"Clothing, Apparel, & Fashions",
            "type":"Retail Goods"
        }
    ],
    "sg:phone":"+1 323 733 1962",
    "sg:postcode":"90007",
    "sg:province":"CA",
    "wof:name":"Cats 1 Dollar World",
    "wof:placetype":"venue"
},
  "geometry": {"coordinates":[-118.295467,34.025431],"type":"Point"}
}