{
  "type": "Feature",
  "properties": {
    "addr:full":"134 Cameron St Santa Paula CA 93060",
    "addr:housenumber":"134",
    "addr:postcode":"93060",
    "addr:street":"Cameron St",
    "iso:country":"US",
    "sg:address":"134 Cameron St",
    "sg:city":"Santa Paula",
    "sg:classifiers":[
        {
            "category":"Professional",
            "type":"Services"
        }
    ],
    "sg:phone":"+1 805 525 5326",
    "sg:postcode":"93060",
    "sg:province":"CA",
    "sg:tags":[
        "establishment"
    ],
    "wof:name":"Villa Del Sol",
    "wof:placetype":"venue"
},
  "geometry": {"coordinates":[-119.08417799999999,34.347402],"type":"Point"}
}