{
  "type": "Feature",
  "properties": {
    "addr:full":"108 Laidley St San Francisco CA 94131",
    "addr:housenumber":"108",
    "addr:postcode":"94131",
    "addr:street":"Laidley St",
    "iso:country":"US",
    "sg:address":"108 Laidley St",
    "sg:city":"San Francisco",
    "sg:classifiers":[
        {
            "category":"Building & Trades",
            "subcategory":"Construction",
            "type":"Services"
        }
    ],
    "sg:phone":"+1 415 643 4320",
    "sg:postcode":"94131",
    "sg:province":"CA",
    "sg:tags":[
        "contractor"
    ],
    "wof:name":"Original Construction",
    "wof:placetype":"venue"
},
  "geometry": {"coordinates":[-122.430741,37.740424],"type":"Point"}
}