{
  "type": "Feature",
  "properties": {
    "addr:full":"2870 State St Carlsbad CA 92008",
    "addr:housenumber":"2870",
    "addr:postcode":"92008",
    "addr:street":"State St",
    "iso:country":"US",
    "sg:address":"2870 State St",
    "sg:city":"Carlsbad",
    "sg:classifiers":[
        {
            "category":"Shopping",
            "subcategory":"Clothing, Apparel, & Fashions",
            "type":"Retail Goods"
        }
    ],
    "sg:phone":"+1 760 720 3600",
    "sg:postcode":"92008",
    "sg:province":"CA",
    "wof:name":"It's Charming",
    "wof:placetype":"venue"
},
  "geometry": {"coordinates":[-117.349847,33.161146],"type":"Point"}
}