{
  "type": "Feature",
  "properties": {
    "addr:full":"343 Quail Dr Woodland CA 95695",
    "addr:housenumber":"343",
    "addr:postcode":"95695",
    "addr:street":"Quail Dr",
    "iso:country":"US",
    "sg:address":"343 Quail Dr",
    "sg:city":"Woodland",
    "sg:classifiers":[
        {
            "category":"Utilities",
            "subcategory":"Fuel Oil & Lpg",
            "type":"Services"
        }
    ],
    "sg:phone":"+1 530 666 5561",
    "sg:postcode":"95695",
    "sg:province":"CA",
    "sg:tags":[
        "firewood"
    ],
    "wof:name":"Felkins Firewood",
    "wof:placetype":"venue"
},
  "geometry": {"coordinates":[-121.799274,38.693965],"type":"Point"}
}