{
  "type": "Feature",
  "properties": {
    "addr:full":"1325 Mountain View Ln Mentone CA 92359",
    "addr:housenumber":"1325",
    "addr:postcode":"92359",
    "addr:street":"Mountain View Ln",
    "iso:country":"US",
    "sg:address":"1325 Mountain View Ln",
    "sg:city":"Mentone",
    "sg:classifiers":[
        {
            "category":"Building & Trades",
            "subcategory":"Construction",
            "type":"Services"
        }
    ],
    "sg:phone":"+1 909 794 2291",
    "sg:postcode":"92359",
    "sg:province":"CA",
    "sg:tags":[
        "material",
        "contractor"
    ],
    "wof:name":"McCall Sandblasting",
    "wof:placetype":"venue"
},
  "geometry": {"coordinates":[-117.097762,34.072439],"type":"Point"}
}