{
  "type": "Feature",
  "properties": {
    "iso:country":"US",
    "sg:address":"2827 S Rodeo Gulch Rd",
    "sg:city":"Soquel",
    "sg:classifiers":[
        {
            "category":"Wholesale",
            "subcategory":"Electrical",
            "type":"Manufacturing & Wholesale Goods"
        }
    ],
    "sg:phone":"+1 831 465 9200",
    "sg:postcode":"95073",
    "sg:province":"CA",
    "sg:tags":[
        "equipment",
        "radar",
        "supply"
    ],
    "sg:website":"www.radar-digital.com",
    "wof:name":"Radar Digital Systems",
    "wof:placetype":"venue"
},
  "geometry": {"coordinates":[-121.969652,36.987459],"type":"Point"}
}