{
  "type": "Feature",
  "properties": {
    "addr:full":"2231 S el Camino Real Oceanside CA 92054",
    "addr:housenumber":"2231",
    "addr:postcode":"92054",
    "addr:street":"S El Camino Real",
    "iso:country":"US",
    "sg:address":"2231 S el Camino Real",
    "sg:city":"Oceanside",
    "sg:classifiers":[
        {
            "category":"Health Services",
            "subcategory":"Hospital",
            "type":"Services"
        }
    ],
    "sg:phone":"+1 760 754 6110",
    "sg:postcode":"92054",
    "sg:province":"CA",
    "wof:name":"Children's Hospital",
    "wof:placetype":"venue"
},
  "geometry": {"coordinates":[-117.32825099999999,33.186515],"type":"Point"}
}