{
  "type": "Feature",
  "properties": {
    "addr:full":"23825 Mobile St West Hills CA 91307",
    "addr:postcode":"23825;91307",
    "addr:street":"Mobile St",
    "iso:country":"US",
    "sg:address":"23825 Mobile St",
    "sg:city":"West Hills",
    "sg:classifiers":[
        {
            "category":"Professional",
            "subcategory":"Advertising",
            "type":"Services"
        }
    ],
    "sg:phone":"+1 818 592 0555",
    "sg:postcode":"91307",
    "sg:province":"CA",
    "sg:tags":[
        "counselor"
    ],
    "wof:name":"Ad Power Marketing",
    "wof:placetype":"venue"
},
  "geometry": {"coordinates":[-118.648287,34.187764],"type":"Point"}
}