{
  "type": "Feature",
  "properties": {
    "addr:full":"1521 W Beverly Blvd Montebello CA 90640",
    "addr:housenumber":"1521",
    "addr:postcode":"90640",
    "addr:street":"W Beverly Blvd",
    "iso:country":"US",
    "sg:address":"1521 W Beverly Blvd",
    "sg:city":"Montebello",
    "sg:classifiers":[
        {
            "category":"Shopping",
            "subcategory":"Department Store",
            "type":"Retail Goods"
        }
    ],
    "sg:phone":"+1 323 724 9900",
    "sg:postcode":"90640",
    "sg:province":"CA",
    "sg:tags":[
        "shop"
    ],
    "wof:name":"99 Cents Only Store",
    "wof:placetype":"venue"
},
  "geometry": {"coordinates":[-118.115844,34.019119],"type":"Point"}
}