{
  "type": "Feature",
  "properties": {
    "iso:country":"US",
    "sg:address":"29091 Canyon Vista Dr",
    "sg:city":"Trabuco Canyon",
    "sg:classifiers":[
        {
            "category":"Real Estate",
            "subcategory":"Real Estate Agent",
            "type":"Services"
        }
    ],
    "sg:phone":"+1 949 589 9150",
    "sg:postcode":"92679",
    "sg:province":"CA",
    "wof:name":"Greg Hughes",
    "wof:placetype":"venue"
},
  "geometry": {"coordinates":[-117.624336,33.679529],"type":"Point"}
}