{
  "type": "Feature",
  "properties": {
    "addr:full":"966 N Plumas St Willows CA 95988",
    "addr:housenumber":"966",
    "addr:postcode":"95988",
    "addr:street":"N Plumas St",
    "iso:country":"US",
    "sg:address":"966 N Plumas St",
    "sg:city":"Willows",
    "sg:phone":"+1 530 934 7045",
    "sg:postcode":"95988",
    "sg:province":"CA",
    "sg:tags":[
        "farm",
        "rice"
    ],
    "wof:name":"Alice J Montz Farms",
    "wof:placetype":"venue"
},
  "geometry": {"coordinates":[-122.198171,39.534543],"type":"Point"}
}