{
  "type": "Feature",
  "properties": {
    "iso:country":"US",
    "sg:address":"16027 Ventura Blvd",
    "sg:city":"Encino",
    "sg:classifiers":[
        {
            "category":"Banks & Credit Unions",
            "subcategory":"Investment Brokerage",
            "type":"Services"
        }
    ],
    "sg:phone":"+1 818 380 0025",
    "sg:postcode":"91436",
    "sg:province":"CA",
    "sg:tags":[
        "retirement",
        "planning"
    ],
    "wof:name":"Alexander Fried",
    "wof:placetype":"venue"
},
  "geometry": {"coordinates":[-118.483125,34.156364],"type":"Point"}
}