{
  "type": "Feature",
  "properties": {
    "iso:country":"US",
    "sg:address":"2408 Mandela",
    "sg:city":"Oakland",
    "sg:classifiers":[
        {
            "category":"Retail",
            "subcategory":"Auto Repair",
            "type":"Services"
        }
    ],
    "sg:phone":"+1 510 208 3226",
    "sg:postcode":"94607",
    "sg:province":"CA",
    "sg:tags":[
        "body",
        "shop"
    ],
    "sg:website":"www.cleangreencollision.com",
    "wof:name":"Clean Green Collision",
    "wof:placetype":"venue"
},
  "geometry": {"coordinates":[-122.28901500000001,37.819113],"type":"Point"}
}