{
  "type": "Feature",
  "properties": {
    "addr:full":"15525 Lofty Trail Ct San Diego CA 92127",
    "addr:housenumber":"15525",
    "addr:postcode":"92127",
    "addr:street":"Lofty Trail Ct",
    "iso:country":"US",
    "sg:address":"15525 Lofty Trail Ct",
    "sg:city":"San Diego",
    "sg:classifiers":[
        {
            "category":"Manufacturing",
            "subcategory":"Metals",
            "type":"Manufacturing & Wholesale Goods"
        }
    ],
    "sg:phone":"+1 858 829 1754",
    "sg:postcode":"92127",
    "sg:province":"CA",
    "sg:tags":[
        "fabrication",
        "structural"
    ],
    "wof:name":"Bombshell Cstm Met Fabrication",
    "wof:placetype":"venue"
},
  "geometry": {"coordinates":[-117.08434,32.99949],"type":"Point"}
}