{
  "type": "Feature",
  "properties": {
    "iso:country":"US",
    "sg:address":"545 Meridian Ave",
    "sg:city":"San Jose",
    "sg:classifiers":[
        {
            "category":"Shopping",
            "subcategory":"Clothing, Apparel, & Fashions",
            "type":"Retail Goods"
        }
    ],
    "sg:phone":"+1 408 293 8633",
    "sg:postcode":"95126",
    "sg:province":"CA",
    "sg:tags":[
        "sewing",
        "alteration",
        "uniform"
    ],
    "wof:name":"Summit Uniform",
    "wof:placetype":"venue"
},
  "geometry": {"coordinates":[-121.913742,37.318368],"type":"Point"}
}