{
  "type": "Feature",
  "properties": {
    "addr:full":"250 Sunol St San Jose CA 95126",
    "addr:housenumber":"250",
    "addr:postcode":"95126",
    "addr:street":"Sunol St",
    "iso:country":"US",
    "sg:address":"250 Sunol St",
    "sg:city":"San Jose",
    "sg:classifiers":[
        {
            "category":"Building & Trades",
            "subcategory":"Construction",
            "type":"Services"
        }
    ],
    "sg:phone":"+1 408 297 4768",
    "sg:postcode":"95126",
    "sg:province":"CA",
    "sg:tags":[
        "maker",
        "cabinet"
    ],
    "wof:name":"Perez Woodworking & Constr",
    "wof:placetype":"venue"
},
  "geometry": {"coordinates":[-121.906088,37.325679],"type":"Point"}
}