{
  "type": "Feature",
  "properties": {
    "iso:country":"US",
    "sg:address":"915 Industrial Way",
    "sg:city":"San Jacinto",
    "sg:classifiers":[
        {
            "category":"Manufacturing",
            "subcategory":"Tools & Machinery",
            "type":"Manufacturing & Wholesale Goods"
        }
    ],
    "sg:phone":"+1 951 654 2333",
    "sg:postcode":"92582",
    "sg:province":"CA",
    "sg:tags":[
        "physician",
        "surgeon"
    ],
    "wof:name":"Tiburon Medical Enterprises",
    "wof:placetype":"venue"
},
  "geometry": {"coordinates":[-116.975768,33.784521],"type":"Point"}
}