{
  "type": "Feature",
  "properties": {
    "addr:full":"4144 N Business St Long Beach CA 90807",
    "addr:housenumber":"4144",
    "addr:postcode":"90807",
    "addr:street":"N Business St",
    "iso:country":"US",
    "sg:address":"4144 N Business St",
    "sg:city":"Long Beach",
    "sg:classifiers":[
        {
            "category":"Banks & Credit Unions",
            "subcategory":"Bank",
            "type":"Services"
        }
    ],
    "sg:phone":"+1 562 988 7700",
    "sg:postcode":"90807",
    "sg:province":"CA",
    "sg:tags":[
        "loan"
    ],
    "wof:name":"Sevarg Financial Svc",
    "wof:placetype":"venue"
},
  "geometry": {"coordinates":[-118.188712,33.834206],"type":"Point"}
}