{
  "type": "Feature",
  "properties": {
    "addr:full":"2100 5th Street Berkeley CA 94710",
    "addr:housenumber":"2100",
    "addr:postcode":"94710",
    "addr:street":"5Th Street",
    "iso:country":"US",
    "sg:address":"2100 5th Street",
    "sg:city":"Berkeley",
    "sg:classifiers":[
        {
            "category":"Manufacturing",
            "subcategory":"Leather Goods",
            "type":"Manufacturing & Wholesale Goods"
        }
    ],
    "sg:phone":"+1 510 843 9177",
    "sg:postcode":"94710",
    "sg:province":"CA",
    "wof:name":"Libaire Leather",
    "wof:placetype":"venue"
},
  "geometry": {"coordinates":[-122.297997,37.8661],"type":"Point"}
}