{
  "type": "Feature",
  "properties": {
    "addr:full":"8914 Painter Ave Whittier CA 90602",
    "addr:housenumber":"8914",
    "addr:postcode":"90602",
    "addr:street":"Painter Ave",
    "iso:country":"US",
    "sg:address":"8914 Painter Ave",
    "sg:city":"Whittier",
    "sg:classifiers":[
        {
            "category":"Building & Trades",
            "subcategory":"Construction",
            "type":"Services"
        }
    ],
    "sg:phone":"+1 562 699 2117",
    "sg:postcode":"90602",
    "sg:province":"CA",
    "sg:tags":[
        "roofing",
        "contractor"
    ],
    "wof:name":"Moderne Kraft Roofing Co",
    "wof:placetype":"venue"
},
  "geometry": {"coordinates":[-118.039342,33.956585],"type":"Point"}
}