{
  "type": "Feature",
  "properties": {
    "iso:country":"US",
    "sg:address":"71460 Gardess Rd",
    "sg:city":"Rancho Mirage",
    "sg:classifiers":[
        {
            "category":"Health Services",
            "subcategory":"Clinic",
            "type":"Services"
        }
    ],
    "sg:phone":"+1 760 340 3414",
    "sg:postcode":"92270",
    "sg:province":"CA",
    "sg:tags":[
        "medical",
        "group"
    ],
    "wof:name":"Louise White & Assoc",
    "wof:placetype":"venue"
},
  "geometry": {"coordinates":[-116.417704,33.735161],"type":"Point"}
}