{
  "type": "Feature",
  "properties": {
    "addr:full":"2777 Cleveland Ave Santa Rosa CA 95403",
    "addr:housenumber":"2777",
    "addr:postcode":"95403",
    "addr:street":"Cleveland Ave",
    "iso:country":"US",
    "sg:address":"2777 Cleveland Ave",
    "sg:city":"Santa Rosa",
    "sg:classifiers":[
        {
            "category":"Professional",
            "subcategory":"Lawyer & Legal Services",
            "type":"Services"
        }
    ],
    "sg:phone":"+1 707 544 2600",
    "sg:postcode":"95403",
    "sg:province":"CA",
    "sg:tags":[
        "attorney"
    ],
    "wof:name":"Gilbert Dorame Law Office",
    "wof:placetype":"venue"
},
  "geometry": {"coordinates":[-122.728476,38.465724],"type":"Point"}
}