{
  "type": "Feature",
  "properties": {
    "iso:country":"US",
    "sg:address":"500 John Daly Blvd",
    "sg:city":"Daly City",
    "sg:classifiers":[
        {
            "category":"Transit Center",
            "subcategory":"Passenger",
            "type":"Transportation"
        }
    ],
    "sg:postcode":"94014",
    "sg:province":"CA",
    "sg:website":"www.bart.gov",
    "wof:name":"Daly City BART Station",
    "wof:placetype":"venue"
},
  "geometry": {"coordinates":[-122.469002,37.705299],"type":"Point"}
}