{
  "type": "Feature",
  "properties": {
    "addr:full":"43844 Brookside Rd Miramonte CA 93641",
    "addr:housenumber":"43844",
    "addr:postcode":"93641",
    "addr:street":"Brookside Rd",
    "iso:country":"US",
    "sg:address":"43844 Brookside Rd",
    "sg:city":"Miramonte",
    "sg:classifiers":[
        {
            "category":"Shopping",
            "type":"Retail Goods"
        }
    ],
    "sg:phone":"+1 559 336 2629",
    "sg:postcode":"93641",
    "sg:province":"CA",
    "sg:tags":[
        "merchandise"
    ],
    "wof:name":"Edwards Pets & Pals",
    "wof:placetype":"venue"
},
  "geometry": {"coordinates":[-119.083459,36.702529],"type":"Point"}
}