{
  "type": "Feature",
  "properties": {
    "addr:full":"100 Volcano Ct Vallejo CA 94589",
    "addr:housenumber":"100",
    "addr:postcode":"94589",
    "addr:street":"Volcano Ct",
    "iso:country":"US",
    "sg:address":"100 Volcano Ct",
    "sg:city":"Vallejo",
    "sg:classifiers":[
        {
            "category":"Freight",
            "type":"Transportation"
        }
    ],
    "sg:phone":"+1 707 980 2821",
    "sg:postcode":"94589",
    "sg:province":"CA",
    "sg:tags":[
        "consultant"
    ],
    "wof:name":"Forex Cargo Vallejo",
    "wof:placetype":"venue"
},
  "geometry": {"coordinates":[-122.26739999999999,38.151744],"type":"Point"}
}