{
  "type": "Feature",
  "properties": {
    "addr:full":"3007 Huntington Dr Pasadena CA 91107",
    "addr:housenumber":"3007",
    "addr:postcode":"91107",
    "addr:street":"Huntington Dr",
    "iso:country":"US",
    "sg:address":"3007 Huntington Dr",
    "sg:city":"Pasadena",
    "sg:classifiers":[
        {
            "category":"Ice Cream",
            "type":"Food & Drink"
        }
    ],
    "sg:menulink":"http://www.allmenus.com/ca/pasadena/242460-baskin-robbins/menu/",
    "sg:phone":"+1 626 229 0631",
    "sg:postcode":"91107",
    "sg:province":"CA",
    "sg:tags":[
        "american"
    ],
    "wof:name":"Baskin-Robbins",
    "wof:placetype":"venue"
},
  "geometry": {"coordinates":[-118.09101800000001,34.12775],"type":"Point"}
}