{
  "type": "Feature",
  "properties": {
    "iso:country":"US",
    "sg:address":"40336 Brick Yard Dr",
    "sg:city":"Madera",
    "sg:classifiers":[
        {
            "category":"Local Transit",
            "type":"Transportation"
        }
    ],
    "sg:phone":"+1 559 438 5466",
    "sg:postcode":"93638",
    "sg:province":"CA",
    "sg:tags":[
        "passenger"
    ],
    "wof:name":"Touch Class Limousine Service",
    "wof:placetype":"venue"
},
  "geometry": {"coordinates":[-119.81259900000001,36.896078],"type":"Point"}
}