{
  "type": "Feature",
  "properties": {
    "addr:full":"2148 Harbor Blvd Ventura CA 93001",
    "addr:housenumber":"2148",
    "addr:postcode":"93001",
    "addr:street":"Harbor Blvd",
    "iso:country":"US",
    "sg:address":"2148 Harbor Blvd",
    "sg:city":"Ventura",
    "sg:classifiers":[
        {
            "category":"Restaurant",
            "type":"Food & Drink"
        }
    ],
    "sg:menulink":"http://www.allmenus.com/ca/ventura/8886-dennys/menu/",
    "sg:phone":"+1 805 643 3414",
    "sg:postcode":"93001",
    "sg:province":"CA",
    "sg:tags":[
        "american",
        "diner"
    ],
    "wof:name":"Denny's",
    "wof:placetype":"venue"
},
  "geometry": {"coordinates":[-119.272291,34.266817],"type":"Point"}
}