{
  "type": "Feature",
  "properties": {
    "addr:full":"4720 Vineta Ave La Canada Fltrdg CA 91011",
    "addr:housenumber":"4720",
    "addr:postcode":"91011",
    "addr:street":"Vineta Ave La",
    "iso:country":"US",
    "sg:address":"4720 Vineta Ave",
    "sg:city":"La Canada Fltrdg",
    "sg:classifiers":[
        {
            "category":"Health Services",
            "subcategory":"Doctor",
            "type":"Services"
        }
    ],
    "sg:phone":"+1 818 952 8446",
    "sg:postcode":"91011",
    "sg:province":"CA",
    "sg:tags":[
        "physician",
        "surgeon"
    ],
    "wof:name":"Edward A Dietz MD",
    "wof:placetype":"venue"
},
  "geometry": {"coordinates":[-118.18764400000001,34.201847],"type":"Point"}
}