{
  "type": "Feature",
  "properties": {
    "iso:country":"US",
    "sg:address":"477 Roland Way",
    "sg:city":"Oakland",
    "sg:classifiers":[
        {
            "category":"Food & Beverages",
            "subcategory":"Specialty",
            "type":"Retail Goods"
        }
    ],
    "sg:phone":"+1 510 383 8890",
    "sg:postcode":"94621",
    "sg:province":"CA",
    "sg:tags":[
        "water",
        "bulk",
        "company"
    ],
    "wof:name":"U-STOR H2o",
    "wof:placetype":"venue"
},
  "geometry": {"coordinates":[-122.201378,37.743304],"type":"Point"}
}