{
  "type": "Feature",
  "properties": {
    "addr:full":"1507 W Beverly Blvd Montebello CA 90640",
    "addr:housenumber":"1507",
    "addr:postcode":"90640",
    "addr:street":"W Beverly Blvd",
    "iso:country":"US",
    "sg:address":"1507 W Beverly Blvd",
    "sg:city":"Montebello",
    "sg:classifiers":[
        {
            "category":"Restaurant",
            "type":"Food & Drink"
        }
    ],
    "sg:phone":"+1 323 727 7187",
    "sg:postcode":"90640",
    "sg:province":"CA",
    "sg:tags":[
        "hawaiian"
    ],
    "wof:name":"Aloha Hawaiian BBQ",
    "wof:placetype":"venue"
},
  "geometry": {"coordinates":[-118.114942,34.019049],"type":"Point"}
}