{
  "type": "Feature",
  "properties": {
    "iso:country":"US",
    "sg:address":"7020 Melrose Ave",
    "sg:city":"Los Angeles",
    "sg:classifiers":[
        {
            "category":"Arts & Performance",
            "subcategory":"Art Gallery",
            "type":"Entertainment"
        }
    ],
    "sg:phone":"+1 323 937 7088",
    "sg:postcode":"90038",
    "sg:province":"CA",
    "sg:website":"www.nineteeneightyeight.com",
    "wof:name":"Gallery 1988",
    "wof:placetype":"venue"
},
  "geometry": {"coordinates":[-118.3435,34.083403],"type":"Point"}
}