{
  "type": "Feature",
  "properties": {
    "addr:full":"1450 Frazee Road Suite 300 San Diego CA 92108",
    "addr:housenumber":"1450",
    "addr:postcode":"92108",
    "addr:street":"Frazee Road Suite 300",
    "iso:country":"US",
    "sg:address":"1450 Frazee Road Suite 300",
    "sg:city":"San Diego",
    "sg:classifiers":[
        {
            "category":"Health Services",
            "subcategory":"Optometrist",
            "type":"Services"
        },
        {
            "category":"Shopping",
            "subcategory":"Optician",
            "type":"Retail Goods"
        }
    ],
    "sg:phone":"+1 619 297 6881",
    "sg:postcode":"92108",
    "sg:province":"CA",
    "sg:tags":[
        "eyewear"
    ],
    "sg:website":"www.optometricexpress.net",
    "wof:name":"Optometric Express",
    "wof:placetype":"venue"
},
  "geometry": {"coordinates":[-117.15926899999999,32.773326],"type":"Point"}
}