{
  "type": "Feature",
  "properties": {
    "addr:full":"359 Bel Marin Keys Blvd Novato CA 94949",
    "addr:housenumber":"359",
    "addr:postcode":"94949",
    "addr:street":"Bel Marin Keys Blvd",
    "iso:country":"US",
    "sg:address":"359 Bel Marin Keys Blvd",
    "sg:city":"Novato",
    "sg:classifiers":[
        {
            "category":"Insurance",
            "subcategory":"Insurance Agent",
            "type":"Services"
        }
    ],
    "sg:phone":"+1 415 382 7699",
    "sg:postcode":"94949",
    "sg:province":"CA",
    "wof:name":"Judith K Gronski",
    "wof:placetype":"venue"
},
  "geometry": {"coordinates":[-122.537989,38.074825],"type":"Point"}
}