{
  "type": "Feature",
  "properties": {
    "addr:full":"5427 Santa Monica Blvd Los Angeles CA 90029",
    "addr:housenumber":"5427",
    "addr:postcode":"90029",
    "addr:street":"Santa Monica Blvd",
    "iso:country":"US",
    "sg:address":"5427 Santa Monica Blvd",
    "sg:city":"Los Angeles",
    "sg:classifiers":[
        {
            "category":"Personal",
            "subcategory":"Beauty Salon",
            "type":"Services"
        }
    ],
    "sg:phone":"+1 323 461 1779",
    "sg:postcode":"90029",
    "sg:province":"CA",
    "wof:name":"Nunez Beauty Salon",
    "wof:placetype":"venue"
},
  "geometry": {"coordinates":[-118.306945,34.090784],"type":"Point"}
}