{
  "type": "Feature",
  "properties": {
    "addr:full":"673 Airport Way Modesto CA 95354",
    "addr:housenumber":"673",
    "addr:postcode":"ca 95354",
    "addr:street":"Airport Way",
    "iso:country":"US",
    "sg:address":"673 Airport Way",
    "sg:city":"Modesto",
    "sg:classifiers":[
        {
            "category":"Professional",
            "type":"Services"
        }
    ],
    "sg:phone":"+1 209 526 4939",
    "sg:postcode":"95354",
    "sg:province":"CA",
    "sg:tags":[
        "establishment"
    ],
    "wof:name":"Barton ATC Intl",
    "wof:placetype":"venue"
},
  "geometry": {"coordinates":[-120.948719,37.625548],"type":"Point"}
}