{
  "type": "Feature",
  "properties": {
    "addr:full":"7627 Pacific Ave Stockton CA 95207",
    "addr:housenumber":"7627",
    "addr:postcode":"95207",
    "addr:street":"Pacific Ave",
    "iso:country":"US",
    "sg:address":"7627 Pacific Ave",
    "sg:city":"Stockton",
    "sg:classifiers":[
        {
            "category":"Retail",
            "subcategory":"Self-service Laundry",
            "type":"Services"
        }
    ],
    "sg:phone":"+1 209 477 6996",
    "sg:postcode":"95207",
    "sg:province":"CA",
    "wof:name":"Launderland",
    "wof:placetype":"venue"
},
  "geometry": {"coordinates":[-121.323786,38.018925],"type":"Point"}
}