{
  "type": "Feature",
  "properties": {
    "addr:full":"11820 Abilene Way Santa Clarita CA 91390",
    "addr:housenumber":"11820",
    "addr:postcode":"91390",
    "addr:street":"Abilene Way",
    "iso:country":"US",
    "sg:address":"11820 Abilene Way",
    "sg:city":"Santa Clarita",
    "sg:classifiers":[
        {
            "category":"Wholesale",
            "subcategory":"Chemicals & Plastics",
            "type":"Manufacturing & Wholesale Goods"
        }
    ],
    "sg:phone":"+1 661 268 0090",
    "sg:postcode":"91390",
    "sg:province":"CA",
    "wof:name":"Bear Laboratories Inc",
    "wof:placetype":"venue"
},
  "geometry": {"coordinates":[-118.340147,34.498237],"type":"Point"}
}