{
  "type": "Feature",
  "properties": {
    "addr:full":"3830 Saco Rd Bakersfield CA 93306",
    "addr:housenumber":"3830",
    "addr:postcode":"93306",
    "addr:street":"Saco Rd",
    "iso:country":"US",
    "sg:address":"3830 Saco Rd",
    "sg:city":"Bakersfield",
    "sg:classifiers":[
        {
            "category":"Autos & Motor Vehicles",
            "subcategory":"Recreational Vehicle Sales",
            "type":"Retail Goods"
        }
    ],
    "sg:phone":"+1 661 393 8862",
    "sg:postcode":"93306",
    "sg:province":"CA",
    "sg:website":"www.campingworld.com",
    "wof:name":"National Supply Co",
    "wof:placetype":"venue"
},
  "geometry": {"coordinates":[-119.081812,35.441866],"type":"Point"}
}