{
  "type": "Feature",
  "properties": {
    "iso:country":"US",
    "sg:address":"1079 Lombard St",
    "sg:city":"San Francisco",
    "sg:classifiers":[
        {
            "category":"Professional",
            "subcategory":"Management & Consulting",
            "type":"Services"
        }
    ],
    "sg:phone":"+1 415 928 7105",
    "sg:postcode":"94109",
    "sg:province":"CA",
    "sg:tags":[
        "retail",
        "direct",
        "sales"
    ],
    "wof:name":"William F Stepka & Associates",
    "wof:placetype":"venue"
},
  "geometry": {"coordinates":[-122.419346,37.802006],"type":"Point"}
}