{
  "type": "Feature",
  "properties": {
    "addr:full":"620 Hacienda Dr Vista CA 92081",
    "addr:housenumber":"620",
    "addr:postcode":"92081",
    "addr:street":"Hacienda Dr",
    "iso:country":"US",
    "sg:address":"620 Hacienda Dr",
    "sg:city":"Vista",
    "sg:classifiers":[
        {
            "category":"Restaurant",
            "type":"Food & Drink"
        }
    ],
    "sg:phone":"+1 760 305 1233",
    "sg:postcode":"92081",
    "sg:province":"CA",
    "sg:tags":[
        "mexican"
    ],
    "sg:website":"www.rubios.com",
    "wof:name":"Rubio's Fresh Mexican Grill",
    "wof:placetype":"venue"
},
  "geometry": {"coordinates":[-117.25453,33.192581],"type":"Point"}
}