{
  "type": "Feature",
  "properties": {
    "addr:full":"905 Loma Vista Dr Beverly Hills CA 90210",
    "addr:housenumber":"905",
    "addr:postcode":"90210",
    "addr:street":"Loma Vista Dr",
    "iso:country":"US",
    "sg:address":"905 Loma Vista Dr",
    "sg:city":"Beverly Hills",
    "sg:classifiers":[
        {
            "category":"Restaurant",
            "type":"Food & Drink"
        }
    ],
    "sg:phone":"+1 310 550 4796",
    "sg:postcode":"90210",
    "sg:province":"CA",
    "sg:tags":[
        "flavor",
        "local"
    ],
    "wof:name":"Greystone Mansion",
    "wof:placetype":"venue"
},
  "geometry": {"coordinates":[-118.399826,34.092224],"type":"Point"}
}