{
  "type": "Feature",
  "properties": {
    "addr:full":"1205 Oak St San Francisco CA 94117",
    "addr:housenumber":"1205",
    "addr:postcode":"94117",
    "addr:street":"Oak St",
    "iso:country":"US",
    "sg:address":"1205 Oak St",
    "sg:city":"San Francisco",
    "sg:classifiers":[
        {
            "category":"Travel",
            "subcategory":"Travel Agent",
            "type":"Entertainment"
        }
    ],
    "sg:phone":"+1 415 552 8321",
    "sg:postcode":"94117",
    "sg:province":"CA",
    "sg:tags":[
        "agency"
    ],
    "wof:name":"Over Rainbow Travel",
    "wof:placetype":"venue"
},
  "geometry": {"coordinates":[-122.44067,37.772647],"type":"Point"}
}