{
  "type": "Feature",
  "properties": {
    "addr:full":"3750 Etiwanda Ave Mira Loma CA 91752",
    "addr:housenumber":"3750",
    "addr:postcode":"91752",
    "addr:street":"Etiwanda Ave",
    "iso:country":"US",
    "sg:address":"3750 Etiwanda Ave",
    "sg:city":"Mira Loma",
    "sg:classifiers":[
        {
            "category":"Freight",
            "type":"Transportation"
        }
    ],
    "sg:phone":"+1 951 681 4037",
    "sg:postcode":"91752",
    "sg:province":"CA",
    "sg:tags":[
        "general"
    ],
    "wof:name":"Statewide Ministorage",
    "wof:placetype":"venue"
},
  "geometry": {"coordinates":[-117.524379,34.018962],"type":"Point"}
}