{
  "type": "Feature",
  "properties": {
    "addr:full":"800 Lake Tahoe Blvd South Lake Tahoe CA 96150",
    "addr:housenumber":"800",
    "addr:postcode":"96150",
    "addr:street":"Lake Tahoe Blvd",
    "iso:country":"US",
    "sg:address":"800 Lake Tahoe Blvd",
    "sg:city":"South Lake Tahoe",
    "sg:classifiers":[
        {
            "category":"Home & Garden",
            "subcategory":"Household Appliances",
            "type":"Retail Goods"
        }
    ],
    "sg:phone":"+1 530 544 3090",
    "sg:postcode":"96150",
    "sg:province":"CA",
    "wof:name":"Pioneer Appliance Repair",
    "wof:placetype":"venue"
},
  "geometry": {"coordinates":[-120.038974,38.883856],"type":"Point"}
}