{
  "type": "Feature",
  "properties": {
    "addr:full":"851 Cherry Ave San Bruno CA 94066",
    "addr:housenumber":"851",
    "addr:postcode":"94066",
    "addr:street":"Cherry Ave",
    "iso:country":"US",
    "sg:address":"851 Cherry Ave",
    "sg:city":"San Bruno",
    "sg:classifiers":[
        {
            "category":"Shopping",
            "subcategory":"Pharmacy",
            "type":"Retail Goods"
        }
    ],
    "sg:phone":"+1 650 873 9522",
    "sg:postcode":"94066",
    "sg:province":"CA",
    "sg:tags":[
        "drugstore"
    ],
    "sg:website":"www.cvs.com",
    "wof:name":"CVS pharmacy",
    "wof:placetype":"venue"
},
  "geometry": {"coordinates":[-122.42571599999999,37.627784],"type":"Point"}
}