{
  "type": "Feature",
  "properties": {
    "addr:full":"8690 Washington Blvd Culver City CA 90232",
    "addr:housenumber":"8690",
    "addr:postcode":"90232",
    "addr:street":"Washington Blvd",
    "iso:country":"US",
    "sg:address":"8690 Washington Blvd",
    "sg:city":"Culver City",
    "sg:classifiers":[
        {
            "category":"Education",
            "subcategory":"Special Training",
            "type":"Public Place"
        }
    ],
    "sg:phone":"+1 310 842 9702",
    "sg:postcode":"90232",
    "sg:province":"CA",
    "sg:tags":[
        "school",
        "cooking"
    ],
    "sg:website":"www.newschoolofcooking.com",
    "wof:name":"The New School of Cooking",
    "wof:placetype":"venue"
},
  "geometry": {"coordinates":[-118.383556,34.029823],"type":"Point"}
}