{
  "type": "Feature",
  "properties": {
    "addr:full":"3401 Cherry Ave Long Beach CA 90807",
    "addr:housenumber":"3401",
    "addr:postcode":"90807",
    "addr:street":"Cherry Ave",
    "iso:country":"US",
    "sg:address":"3401 Cherry Ave",
    "sg:city":"Long Beach",
    "sg:classifiers":[
        {
            "category":"Coffee & Tea",
            "type":"Food & Drink"
        }
    ],
    "sg:menulink":"http://www.allmenus.com/ca/long-beach-lakewood/109498-starbucks-coffee/menu/",
    "sg:phone":"+1 562 424 1788",
    "sg:postcode":"90807",
    "sg:province":"CA",
    "sg:tags":[
        "american"
    ],
    "wof:name":"Starbucks Coffee",
    "wof:placetype":"venue"
},
  "geometry": {"coordinates":[-118.168046,33.819194],"type":"Point"}
}