{
  "type": "Feature",
  "properties": {
    "iso:country":"US",
    "sg:address":"15415 Pioneer Blvd",
    "sg:city":"Norwalk",
    "sg:classifiers":[
        {
            "category":"Education",
            "subcategory":"School",
            "type":"Public Place"
        }
    ],
    "sg:phone":"+1 562 868 2893",
    "sg:postcode":"90650",
    "sg:province":"CA",
    "sg:website":"www.nlmusd.k12.ca.us",
    "wof:name":"Norwalk-La Mirada Unified School District",
    "wof:placetype":"venue"
},
  "geometry": {"coordinates":[-118.26152,33.890981],"type":"Point"}
}