{
  "type": "Feature",
  "properties": {
    "addr:full":"1536 Ironside Dr Modesto CA 95358",
    "addr:housenumber":"1536",
    "addr:postcode":"ca 95358",
    "addr:street":"Ironside Dr",
    "iso:country":"US",
    "sg:address":"1536 Ironside Dr",
    "sg:city":"Modesto",
    "sg:classifiers":[
        {
            "category":"Retail",
            "subcategory":"Repair Shop",
            "type":"Services"
        }
    ],
    "sg:phone":"+1 209 402 3101",
    "sg:postcode":"95358",
    "sg:province":"CA",
    "wof:name":"Inspection & Cleaning",
    "wof:placetype":"venue"
},
  "geometry": {"coordinates":[-121.013255,37.602567],"type":"Point"}
}