{
  "type": "Feature",
  "properties": {
    "addr:full":"1960 10th Ave San Francisco CA 94116",
    "addr:housenumber":"1960",
    "addr:postcode":"94116",
    "addr:street":"10Th Ave",
    "iso:country":"US",
    "sg:address":"1960 10th Ave",
    "sg:city":"San Francisco",
    "sg:classifiers":[
        {
            "category":"Real Estate",
            "subcategory":"Real Estate Agent",
            "type":"Services"
        }
    ],
    "sg:phone":"+1 415 661 4853",
    "sg:postcode":"94116",
    "sg:province":"CA",
    "wof:name":"Devine Realtor George",
    "wof:placetype":"venue"
},
  "geometry": {"coordinates":[-122.466458,37.752084],"type":"Point"}
}