{
  "type": "Feature",
  "properties": {
    "iso:country":"US",
    "sg:address":"10524 W Pico Blvd",
    "sg:city":"Los Angeles",
    "sg:classifiers":[
        {
            "category":"Real Estate",
            "subcategory":"Architect",
            "type":"Services"
        }
    ],
    "sg:phone":"+1 310 559 9701",
    "sg:postcode":"90064",
    "sg:province":"CA",
    "wof:name":"Lojdl Milan",
    "wof:placetype":"venue"
},
  "geometry": {"coordinates":[-118.41963,34.464984],"type":"Point"}
}