{
  "type": "Feature",
  "properties": {
    "addr:full":"45300 Seaside School Rd Gualala CA 95445",
    "addr:housenumber":"45300",
    "addr:postcode":"95445",
    "addr:street":"Seaside School Rd",
    "iso:country":"US",
    "sg:address":"45300 Seaside School Rd",
    "sg:city":"Gualala",
    "sg:classifiers":[
        {
            "category":"Real Estate",
            "subcategory":"Real Estate Agent",
            "type":"Services"
        }
    ],
    "sg:phone":"+1 707 884 4559",
    "sg:postcode":"95445",
    "sg:province":"CA",
    "wof:name":"Campiformio & Co",
    "wof:placetype":"venue"
},
  "geometry": {"coordinates":[-123.544603,38.80753],"type":"Point"}
}