{
  "type": "Feature",
  "properties": {
    "addr:full":"4812 Stratos Way Modesto CA 95356",
    "addr:postcode":"4812;ca 95356",
    "addr:street":"Stratos Way",
    "iso:country":"US",
    "sg:address":"4812 Stratos Way",
    "sg:city":"Modesto",
    "sg:classifiers":[
        {
            "category":"Wholesale",
            "subcategory":"Construction Materials",
            "type":"Manufacturing & Wholesale Goods"
        }
    ],
    "sg:phone":"+1 209 579 9194",
    "sg:postcode":"95356",
    "sg:province":"CA",
    "sg:tags":[
        "marble"
    ],
    "wof:name":"Stone Face Granite & Marble",
    "wof:placetype":"venue"
},
  "geometry": {"coordinates":[-121.000137,37.709807],"type":"Point"}
}