{
  "type": "Feature",
  "properties": {
    "addr:full":"12901 Sherman Way North Hollywood CA 91605",
    "addr:housenumber":"12901",
    "addr:postcode":"91605",
    "addr:street":"Sherman Way",
    "iso:country":"US",
    "sg:address":"12901 Sherman Way",
    "sg:city":"North Hollywood",
    "sg:classifiers":[
        {
            "category":"Manufacturing",
            "subcategory":"Printing",
            "type":"Manufacturing & Wholesale Goods"
        }
    ],
    "sg:phone":"+1 818 255 5444",
    "sg:postcode":"91605",
    "sg:province":"CA",
    "sg:tags":[
        "lithographic",
        "commercial"
    ],
    "wof:name":"Armati Printing LLC",
    "wof:placetype":"venue"
},
  "geometry": {"coordinates":[-118.41597400000001,34.201193],"type":"Point"}
}