{
  "type": "Feature",
  "properties": {
    "addr:full":"3195 Danville Blvd Alamo CA 94507",
    "addr:housenumber":"3195",
    "addr:postcode":"94507",
    "addr:street":"Danville Blvd",
    "iso:country":"US",
    "sg:address":"3195 Danville Blvd",
    "sg:city":"Alamo",
    "sg:classifiers":[
        {
            "category":"Real Estate",
            "subcategory":"Real Estate Services",
            "type":"Services"
        },
        {
            "category":"Real Estate",
            "subcategory":"Real Estate Agent",
            "type":"Services"
        }
    ],
    "sg:phone":"+1 925 820 6700",
    "sg:postcode":"94507",
    "sg:province":"CA",
    "sg:tags":[
        "buyer",
        "management",
        "commercial",
        "broker"
    ],
    "wof:name":"California Commercial Properties",
    "wof:placetype":"venue"
},
  "geometry": {"coordinates":[-122.03233,37.849991],"type":"Point"}
}