{
  "type": "Feature",
  "properties": {
    "iso:country":"US",
    "sg:address":"1095 Lombard St",
    "sg:city":"San Francisco",
    "sg:classifiers":[
        {
            "category":"Manufacturing",
            "subcategory":"Retail Goods",
            "type":"Manufacturing & Wholesale Goods"
        }
    ],
    "sg:phone":"+1 415 749 1337",
    "sg:postcode":"94109",
    "sg:province":"CA",
    "sg:tags":[
        "product",
        "mfg"
    ],
    "wof:name":"Hillyard Industries",
    "wof:placetype":"venue"
},
  "geometry": {"coordinates":[-122.419023,37.802067],"type":"Point"}
}