{
  "type": "Feature",
  "properties": {
    "iso:country":"US",
    "sg:address":"10475 S De Anza Blvd",
    "sg:city":"Cupertino",
    "sg:classifiers":[
        {
            "category":"Personal",
            "subcategory":"Beauty Salon",
            "type":"Services"
        }
    ],
    "sg:phone":"+1 408 255 0059",
    "sg:postcode":"95014",
    "sg:province":"CA",
    "sg:tags":[
        "hair"
    ],
    "sg:website":"www.paizleys.com",
    "wof:name":"Paizleys Salon and Spa",
    "wof:placetype":"venue"
},
  "geometry": {"coordinates":[-122.032402,37.316168],"type":"Point"}
}