{
  "type": "Feature",
  "properties": {
    "addr:full":"10952 Eastside Rd Healdsburg CA 95448",
    "addr:housenumber":"10952",
    "addr:postcode":"95448",
    "addr:street":"Eastside Rd",
    "iso:country":"US",
    "sg:address":"10952 Eastside Rd",
    "sg:city":"Healdsburg",
    "sg:classifiers":[
        {
            "category":"Professional",
            "type":"Services"
        }
    ],
    "sg:phone":"+1 707 433 5466",
    "sg:postcode":"95448",
    "sg:province":"CA",
    "wof:name":"Robert Herman",
    "wof:placetype":"venue"
},
  "geometry": {"coordinates":[-122.844506,38.566141],"type":"Point"}
}