{
  "type": "Feature",
  "properties": {
    "iso:country":"US",
    "sg:address":"1206 G St",
    "sg:city":"Fresno",
    "sg:classifiers":[
        {
            "category":"Professional",
            "subcategory":"Lawyer & Legal Services",
            "type":"Services"
        }
    ],
    "sg:phone":"+1 559 237 8383",
    "sg:postcode":"93706",
    "sg:province":"CA",
    "sg:tags":[
        "naturalization",
        "immigration"
    ],
    "wof:name":"International Immigration Svc",
    "wof:placetype":"venue"
},
  "geometry": {"coordinates":[-119.797041,36.734117],"type":"Point"}
}