{
  "type": "Feature",
  "properties": {
    "addr:full":"7 S Quarantina St Santa Barbara CA 93103",
    "addr:housenumber":"7",
    "addr:postcode":"93103",
    "addr:street":"S Quarantina St",
    "iso:country":"US",
    "sg:address":"7 S Quarantina St",
    "sg:city":"Santa Barbara",
    "sg:classifiers":[
        {
            "category":"Professional",
            "subcategory":"Business Services",
            "type":"Services"
        }
    ],
    "sg:phone":"+1 805 965 4983",
    "sg:postcode":"93103",
    "sg:province":"CA",
    "sg:tags":[
        "recording",
        "studio"
    ],
    "wof:name":"7 So Studios",
    "wof:placetype":"venue"
},
  "geometry": {"coordinates":[-119.680522,34.419129],"type":"Point"}
}