{
  "type": "Feature",
  "properties": {
    "iso:country":"US",
    "sg:address":"21040 Ambushers St",
    "sg:city":"Diamond Bar",
    "sg:classifiers":[
        {
            "category":"Professional",
            "subcategory":"Management & Consulting",
            "type":"Services"
        }
    ],
    "sg:phone":"+1 909 860 2557",
    "sg:postcode":"91765",
    "sg:province":"CA",
    "sg:tags":[
        "travel",
        "planning"
    ],
    "wof:name":"Kenneth A Porter Notary Public",
    "wof:placetype":"venue"
},
  "geometry": {"coordinates":[-117.846414,33.965533],"type":"Point"}
}