{
  "type": "Feature",
  "properties": {
    "addr:full":"7390 W Perigord Ct Tujunga CA 91042",
    "addr:housenumber":"7390",
    "addr:postcode":"91042",
    "addr:street":"W Perigord Ct",
    "iso:country":"US",
    "sg:address":"7390 W Perigord Ct",
    "sg:city":"Tujunga",
    "sg:classifiers":[
        {
            "category":"Professional",
            "type":"Services"
        }
    ],
    "sg:phone":"+1 818 353 6563",
    "sg:postcode":"91042",
    "sg:province":"CA",
    "wof:name":"Musnam Inc",
    "wof:placetype":"venue"
},
  "geometry": {"coordinates":[-118.293842,34.271516],"type":"Point"}
}