{
  "type": "Feature",
  "properties": {
    "addr:full":"116 S Buena Vista St Burbank CA 91505",
    "addr:housenumber":"116",
    "addr:postcode":"91505",
    "addr:street":"S Buena Vista St",
    "iso:country":"US",
    "sg:address":"116 S Buena Vista St",
    "sg:city":"Burbank",
    "sg:classifiers":[
        {
            "category":"Retail",
            "subcategory":"Portrait Studio",
            "type":"Services"
        },
        {
            "category":"Professional",
            "subcategory":"Art Services",
            "type":"Services"
        }
    ],
    "sg:phone":"+1 818 237 3942",
    "sg:postcode":"91505",
    "sg:province":"CA",
    "sg:tags":[
        "photographer",
        "photography",
        "store"
    ],
    "wof:name":"Jbg Photo Inc",
    "wof:placetype":"venue"
},
  "geometry": {"coordinates":[-118.32913000000001,34.160686],"type":"Point"}
}