{
  "type": "Feature",
  "properties": {
    "addr:full":"39256 10th St W Palmdale CA 93551",
    "addr:housenumber":"39256",
    "addr:postcode":"ca 93551",
    "addr:street":"10Th St W",
    "iso:country":"US",
    "sg:address":"39256 10th St W",
    "sg:city":"Palmdale",
    "sg:classifiers":[
        {
            "category":"Food & Beverages",
            "subcategory":"Specialty",
            "type":"Retail Goods"
        }
    ],
    "sg:phone":"+1 661 273 9864",
    "sg:postcode":"93551",
    "sg:province":"CA",
    "sg:tags":[
        "vitamin"
    ],
    "wof:name":"Vitamin Shoppe",
    "wof:placetype":"venue"
},
  "geometry": {"coordinates":[-118.147522,34.597345],"type":"Point"}
}