{
  "type": "Feature",
  "properties": {
    "iso:country":"US",
    "sg:address":"1514 Minturn St",
    "sg:city":"Alameda",
    "sg:classifiers":[
        {
            "category":"Home & Garden",
            "subcategory":"Building Materials",
            "type":"Retail Goods"
        }
    ],
    "sg:phone":"+1 925 988 9990",
    "sg:postcode":"94501",
    "sg:province":"CA",
    "sg:tags":[
        "paint"
    ],
    "wof:name":"Grand Finishes",
    "wof:placetype":"venue"
},
  "geometry": {"coordinates":[-122.25448400000001,37.772186],"type":"Point"}
}