{
  "type": "Feature",
  "properties": {
    "iso:country":"US",
    "sg:address":"2500 Hoover Ave",
    "sg:city":"National City",
    "sg:classifiers":[
        {
            "category":"Arts & Performance",
            "subcategory":"Theater",
            "type":"Entertainment"
        }
    ],
    "sg:phone":"+1 619 437 6050",
    "sg:postcode":"91950",
    "sg:province":"CA",
    "wof:name":"Lamb's Storage",
    "wof:placetype":"venue"
},
  "geometry": {"coordinates":[-117.103801,32.65898],"type":"Point"}
}