{
  "type": "Feature",
  "properties": {
    "addr:full":"319 Madonna Rd San Luis Obispo CA 93405",
    "addr:housenumber":"319",
    "addr:postcode":"93405",
    "addr:street":"Madonna Rd",
    "iso:country":"US",
    "sg:address":"319 Madonna Rd",
    "sg:city":"San Luis Obispo",
    "sg:classifiers":[
        {
            "category":"Shopping",
            "subcategory":"Shoes",
            "type":"Retail Goods"
        }
    ],
    "sg:phone":"+1 805 786 4514",
    "sg:postcode":"93405",
    "sg:province":"CA",
    "sg:website":"www.famousfootwear.com",
    "wof:name":"Famous Footwear",
    "wof:placetype":"venue"
},
  "geometry": {"coordinates":[-120.678445,35.262419],"type":"Point"}
}