{
  "type": "Feature",
  "properties": {
    "addr:full":"660 Gisler Way Hayward CA 94544",
    "addr:housenumber":"660",
    "addr:postcode":"94544",
    "addr:street":"Gisler Way",
    "iso:country":"US",
    "sg:address":"660 Gisler Way",
    "sg:city":"Hayward",
    "sg:classifiers":[
        {
            "category":"Professional",
            "subcategory":"Detective & Security Services",
            "type":"Services"
        }
    ],
    "sg:phone":"+1 510 889 8986",
    "sg:postcode":"94544",
    "sg:province":"CA",
    "sg:tags":[
        "information",
        "bureau"
    ],
    "wof:name":"White Glove Services",
    "wof:placetype":"venue"
},
  "geometry": {"coordinates":[-122.041753,37.629201],"type":"Point"}
}