{
  "type": "Feature",
  "properties": {
    "addr:full":"6896 Magnolia Ave Riverside CA 92506",
    "addr:housenumber":"6896",
    "addr:postcode":"92506",
    "addr:street":"Magnolia Ave",
    "iso:country":"US",
    "sg:address":"6896 Magnolia Ave",
    "sg:city":"Riverside",
    "sg:classifiers":[
        {
            "category":"Health Services",
            "subcategory":"Doctor",
            "type":"Services"
        }
    ],
    "sg:phone":"+1 951 787 4885",
    "sg:postcode":"92506",
    "sg:province":"CA",
    "sg:tags":[
        "physician",
        "surgeon"
    ],
    "wof:name":"Riverside City Med Assoc",
    "wof:placetype":"venue"
},
  "geometry": {"coordinates":[-117.399367,33.94874],"type":"Point"}
}