{
  "type": "Feature",
  "properties": {
    "iso:country":"US",
    "sg:address":"1765 E Main St",
    "sg:city":"El Cajon",
    "sg:classifiers":[
        {
            "category":"Wholesale",
            "subcategory":"Sporting Goods",
            "type":"Manufacturing & Wholesale Goods"
        }
    ],
    "sg:phone":"+1 619 440 6445",
    "sg:postcode":"92021",
    "sg:province":"CA",
    "sg:tags":[
        "equipment",
        "pool",
        "swimming"
    ],
    "wof:name":"East Mountain Pool & Patio",
    "wof:placetype":"venue"
},
  "geometry": {"coordinates":[-116.917451,32.813583],"type":"Point"}
}