{
  "type": "Feature",
  "properties": {
    "addr:full":"141 S El Camino Real # B Encinitas CA 92024",
    "addr:housenumber":"141",
    "addr:postcode":"92024",
    "addr:street":"S El Camino Real # B",
    "iso:country":"US",
    "sg:address":"141 S El Camino Real # B",
    "sg:city":"Encinitas",
    "sg:classifiers":[
        {
            "category":"Personal",
            "subcategory":"Nail Salon",
            "type":"Services"
        }
    ],
    "sg:phone":"+1 760 634 7670",
    "sg:postcode":"92024",
    "sg:province":"CA",
    "wof:name":"Nail Lounge",
    "wof:placetype":"venue"
},
  "geometry": {"coordinates":[-117.258116,33.043757],"type":"Point"}
}