{
  "type": "Feature",
  "properties": {
    "iso:country":"US",
    "sg:address":"20 Light Sky Ct",
    "sg:city":"Sacramento",
    "sg:classifiers":[
        {
            "category":"Building & Trades",
            "subcategory":"Construction",
            "type":"Services"
        }
    ],
    "sg:phone":"+1 916 388 9500",
    "sg:postcode":"95828",
    "sg:province":"CA",
    "sg:tags":[
        "roofing",
        "contractor"
    ],
    "sg:website":"www.petersendean.com",
    "wof:name":"Petersen & Dean Inc",
    "wof:placetype":"venue"
},
  "geometry": {"coordinates":[-121.380392,38.513577],"type":"Point"}
}