{
  "type": "Feature",
  "properties": {
    "iso:country":"US",
    "sg:address":"1416 N La Brea Ave",
    "sg:city":"Hollywood",
    "sg:classifiers":[
        {
            "category":"Museum",
            "type":"Entertainment"
        }
    ],
    "sg:postcode":"90028",
    "sg:province":"CA",
    "sg:website":"www.henson.com",
    "wof:name":"The Jim Henson Studio",
    "wof:placetype":"venue"
},
  "geometry": {"coordinates":[-118.343425,34.096414],"type":"Point"}
}