{
  "type": "Feature",
  "properties": {
    "addr:full":"445 March Ave Healdsburg CA 95448",
    "addr:housenumber":"445",
    "addr:postcode":"95448",
    "addr:street":"March Ave",
    "iso:country":"US",
    "sg:address":"445 March Ave",
    "sg:city":"Healdsburg",
    "sg:classifiers":[
        {
            "category":"Health Services",
            "subcategory":"Doctor",
            "type":"Services"
        }
    ],
    "sg:phone":"+1 650 321 1430",
    "sg:postcode":"95448",
    "sg:province":"CA",
    "sg:tags":[
        "dentist"
    ],
    "wof:name":"Healdsburg Orthodontic Ctr",
    "wof:placetype":"venue"
},
  "geometry": {"coordinates":[-122.864755,38.625992],"type":"Point"}
}