{
  "type": "Feature",
  "properties": {
    "addr:full":"534 N La Cienega Boulevard West Hollywood CA 90048",
    "addr:housenumber":"534",
    "addr:postcode":"90048",
    "addr:street":"N La Cienega Boulevard",
    "iso:country":"US",
    "sg:address":"534 N La Cienega Boulevard",
    "sg:city":"West Hollywood",
    "sg:classifiers":[
        {
            "category":"Shopping",
            "subcategory":"Antiques",
            "type":"Retail Goods"
        }
    ],
    "sg:phone":"+1 310 652 3395",
    "sg:postcode":"90048",
    "sg:province":"CA",
    "wof:name":"Parviz Solainani Specialty & Antiques",
    "wof:placetype":"venue"
},
  "geometry": {"coordinates":[-118.37641000000001,34.080977],"type":"Point"}
}