{
  "type": "Feature",
  "properties": {
    "addr:full":"2029 Century Park E Los Angeles CA 90067",
    "addr:housenumber":"2029",
    "addr:postcode":"90067",
    "addr:street":"Century Park E",
    "iso:country":"US",
    "sg:address":"2029 Century Park E",
    "sg:city":"Los Angeles",
    "sg:classifiers":[
        {
            "category":"Health Services",
            "subcategory":"Clinic",
            "type":"Services"
        }
    ],
    "sg:phone":"+1 800 815 7322",
    "sg:postcode":"90067",
    "sg:province":"CA",
    "sg:tags":[
        "medical"
    ],
    "sg:website":"www.foreversmokefree.com",
    "wof:name":"Stop Smoking Hypnosis - Forever Smokefree",
    "wof:placetype":"venue"
},
  "geometry": {"coordinates":[-118.413144,34.05969],"type":"Point"}
}