{
  "type": "Feature",
  "properties": {
    "iso:country":"US",
    "sg:address":"796 E 14th St",
    "sg:city":"San Leandro",
    "sg:classifiers":[
        {
            "category":"Food & Beverages",
            "subcategory":"Groceries & Convenience Stores",
            "type":"Retail Goods"
        }
    ],
    "sg:phone":"+1 510 632 7650",
    "sg:postcode":"94577",
    "sg:province":"CA",
    "wof:name":"Gonzales D Meat Market",
    "wof:placetype":"venue"
},
  "geometry": {"coordinates":[-122.158997,37.729099],"type":"Point"}
}