{
  "type": "Feature",
  "properties": {
    "addr:full":"33699 Puma Ln Squaw Valley CA 93675",
    "addr:postcode":"33699;93675",
    "addr:street":"Puma Ln",
    "iso:country":"US",
    "sg:address":"33699 Puma Ln",
    "sg:city":"Squaw Valley",
    "sg:classifiers":[
        {
            "category":"Professional",
            "subcategory":"Computer Services",
            "type":"Services"
        }
    ],
    "sg:phone":"+1 559 332 2452",
    "sg:postcode":"93675",
    "sg:province":"CA",
    "sg:tags":[
        "consultant",
        "designer"
    ],
    "wof:name":"Sierra Consulting",
    "wof:placetype":"venue"
},
  "geometry": {"coordinates":[-119.24619199999999,36.69121],"type":"Point"}
}