{
  "type": "Feature",
  "properties": {
    "addr:full":"3880 Kilroy Airport Way Long Beach CA 90806",
    "addr:housenumber":"3880",
    "addr:postcode":"90806",
    "addr:street":"Kilroy Airport Way",
    "iso:country":"US",
    "sg:address":"3880 Kilroy Airport Way",
    "sg:city":"Long Beach",
    "sg:classifiers":[
        {
            "category":"Education",
            "subcategory":"University",
            "type":"Public Place"
        }
    ],
    "sg:phone":"+1 562 427 4162",
    "sg:postcode":"90806",
    "sg:province":"CA",
    "sg:tags":[
        "college"
    ],
    "wof:name":"Devry Institute of Technology",
    "wof:placetype":"venue"
},
  "geometry": {"coordinates":[-118.144997,33.808201],"type":"Point"}
}