{
  "type": "Feature",
  "properties": {
    "addr:full":"817 W Hammer Ln Stockton CA 95210",
    "addr:housenumber":"817",
    "addr:postcode":"95210",
    "addr:street":"W Hammer Ln",
    "iso:country":"US",
    "sg:address":"817 W Hammer Ln",
    "sg:city":"Stockton",
    "sg:classifiers":[
        {
            "category":"Restaurant",
            "type":"Food & Drink"
        }
    ],
    "sg:menulink":"http://www.allmenus.com/ca/stockton/165794-del-taco/menu/",
    "sg:phone":"+1 209 476 0500",
    "sg:postcode":"95210",
    "sg:province":"CA",
    "sg:tags":[
        "american",
        "mexican",
        "tex-mex"
    ],
    "wof:name":"Del Taco",
    "wof:placetype":"venue"
},
  "geometry": {"coordinates":[-121.322253,38.021479],"type":"Point"}
}