{
  "type": "Feature",
  "properties": {
    "iso:country":"US",
    "sg:address":"5881 S Los Angeles St",
    "sg:city":"Los Angeles",
    "sg:classifiers":[
        {
            "category":"Home & Garden",
            "subcategory":"Furniture",
            "type":"Retail Goods"
        }
    ],
    "sg:phone":"+1 323 234 6810",
    "sg:postcode":"90003",
    "sg:province":"CA",
    "sg:tags":[
        "builder",
        "custom"
    ],
    "wof:name":"Custom Design Furniture",
    "wof:placetype":"venue"
},
  "geometry": {"coordinates":[-118.270602,33.987125],"type":"Point"}
}