{
  "type": "Feature",
  "properties": {
    "addr:full":"5478 College Ave Oakland CA 94618",
    "addr:housenumber":"5478",
    "addr:postcode":"94618",
    "addr:street":"College Ave",
    "iso:country":"US",
    "sg:address":"5478 College Ave",
    "sg:city":"Oakland",
    "sg:phone":"+1 510 655 6469",
    "sg:postcode":"94618",
    "sg:province":"CA",
    "sg:website":"http://www.acoterestaurant.com/",
    "wof:name":"A Cote Restaurant",
    "wof:placetype":"venue"
},
  "geometry": {"coordinates":[-122.25151200000001,37.841896],"type":"Point"}
}