{
  "type": "Feature",
  "properties": {
    "iso:country":"US",
    "sg:address":"870 Market Street",
    "sg:city":"San Francisco",
    "sg:classifiers":[
        {
            "category":"Professional",
            "subcategory":"Employment Agencies",
            "type":"Services"
        }
    ],
    "sg:phone":"+1 415 397 5051",
    "sg:postcode":"94102",
    "sg:province":"CA",
    "sg:website":"www.unsworthpersonnel.com",
    "wof:name":"Unsworth Personnel",
    "wof:placetype":"venue"
},
  "geometry": {"coordinates":[-122.406998,37.784698],"type":"Point"}
}