{
  "type": "Feature",
  "properties": {
    "addr:full":"412 22nd St Oakland CA 94612",
    "addr:housenumber":"412",
    "addr:postcode":"94612",
    "addr:street":"22Nd St",
    "iso:country":"US",
    "sg:address":"412 22nd St",
    "sg:city":"Oakland",
    "sg:classifiers":[
        {
            "category":"Professional",
            "subcategory":"Art Services",
            "type":"Services"
        }
    ],
    "sg:phone":"+1 510 625 0123",
    "sg:postcode":"94612",
    "sg:province":"CA",
    "sg:tags":[
        "framing"
    ],
    "sg:website":"www.kuhlframes.com",
    "wof:name":"Kuhl Frames",
    "wof:placetype":"venue"
},
  "geometry": {"coordinates":[-122.266417,37.810903],"type":"Point"}
}