{
  "type": "Feature",
  "properties": {
    "addr:full":"1230 Los Osos Valley Rd Los Osos CA 93402",
    "addr:housenumber":"1230",
    "addr:postcode":"93402",
    "addr:street":"Los Osos Valley Rd",
    "iso:country":"US",
    "sg:address":"1230 Los Osos Valley Rd",
    "sg:city":"Los Osos",
    "sg:classifiers":[
        {
            "category":"Health Services",
            "subcategory":"Clinic",
            "type":"Services"
        }
    ],
    "sg:phone":"+1 805 781 7688",
    "sg:postcode":"93402",
    "sg:province":"CA",
    "sg:website":"www.supplementdirect.com",
    "wof:name":"Supplement Direct Superstore",
    "wof:placetype":"venue"
},
  "geometry": {"coordinates":[-120.828275,35.31071],"type":"Point"}
}