{
  "type": "Feature",
  "properties": {
    "iso:country":"US",
    "sg:address":"1 1st St",
    "sg:city":"Quincy",
    "sg:classifiers":[
        {
            "category":"Railroad",
            "type":"Transportation"
        }
    ],
    "sg:phone":"+1 530 281 6580",
    "sg:postcode":"95971",
    "sg:province":"CA",
    "wof:name":"Union Pacific Railroad Company",
    "wof:placetype":"venue"
},
  "geometry": {"coordinates":[-120.898447,39.93393],"type":"Point"}
}