{
  "type": "Feature",
  "properties": {
    "iso:country":"US",
    "sg:address":"576 Grand Ave",
    "sg:city":"Oakland",
    "sg:classifiers":[
        {
            "category":"Social Services",
            "type":"Services"
        }
    ],
    "sg:phone":"+1 510 268 8780",
    "sg:postcode":"94610",
    "sg:province":"CA",
    "wof:name":"A Diversified Family",
    "wof:placetype":"venue"
},
  "geometry": {"coordinates":[-122.25078999999999,37.808663],"type":"Point"}
}