{
  "type": "Feature",
  "properties": {
    "addr:full":"727 E Compton Blvd Compton CA 90222",
    "addr:housenumber":"727",
    "addr:postcode":"90222",
    "addr:street":"E Compton Blvd",
    "iso:country":"US",
    "sg:address":"727 E Compton Blvd",
    "sg:city":"Compton",
    "sg:classifiers":[
        {
            "category":"Shopping",
            "subcategory":"Discount & Variety Stores",
            "type":"Retail Goods"
        }
    ],
    "sg:phone":"+1 310 487 0849",
    "sg:postcode":"90222",
    "sg:province":"CA",
    "sg:tags":[
        "wholesale",
        "outlet"
    ],
    "wof:name":"Covert Skate Shop",
    "wof:placetype":"venue"
},
  "geometry": {"coordinates":[-118.21524599999999,33.896281],"type":"Point"}
}