{
  "type": "Feature",
  "properties": {
    "addr:full":"2171 Junipero Serra Blvd San Francisco CA 94102",
    "addr:housenumber":"2171",
    "addr:postcode":"94102",
    "addr:street":"Junipero Serra Blvd",
    "iso:country":"US",
    "sg:address":"2171 Junipero Serra Blvd",
    "sg:city":"San Francisco",
    "sg:classifiers":[
        {
            "category":"Professional",
            "subcategory":"Lawyer & Legal Services",
            "type":"Services"
        }
    ],
    "sg:phone":"+1 650 991 4700",
    "sg:postcode":"94102",
    "sg:province":"CA",
    "sg:tags":[
        "divorce",
        "law",
        "family"
    ],
    "wof:name":"Manetas Peter Atty At Law",
    "wof:placetype":"venue"
},
  "geometry": {"coordinates":[-122.472019,37.721652],"type":"Point"}
}