{
  "type": "Feature",
  "properties": {
    "addr:full":"10869 Oxnard St North Hollywood CA 91606",
    "addr:housenumber":"10869",
    "addr:postcode":"91606",
    "addr:street":"Oxnard St",
    "iso:country":"US",
    "sg:address":"10869 Oxnard St",
    "sg:city":"North Hollywood",
    "sg:classifiers":[
        {
            "category":"Insurance",
            "subcategory":"Insurance Agent",
            "type":"Services"
        }
    ],
    "sg:phone":"+1 818 763 9733",
    "sg:postcode":"91606",
    "sg:province":"CA",
    "wof:name":"Mercy Insurance Svc",
    "wof:placetype":"venue"
},
  "geometry": {"coordinates":[-118.36778099999999,34.179499],"type":"Point"}
}