{
  "type": "Feature",
  "properties": {
    "iso:country":"US",
    "sg:address":"17795 Ave 280",
    "sg:city":"Exeter",
    "sg:classifiers":[
        {
            "category":"Education",
            "subcategory":"Special Training",
            "type":"Public Place"
        }
    ],
    "sg:phone":"+1 559 284 8638",
    "sg:postcode":"93221",
    "sg:province":"CA",
    "sg:tags":[
        "educational"
    ],
    "wof:name":"Children Learning About Wldlf",
    "wof:placetype":"venue"
},
  "geometry": {"coordinates":[-119.174682,36.297523],"type":"Point"}
}