{
  "type": "Feature",
  "properties": {
    "iso:country":"US",
    "sg:address":"1342 E 27th St",
    "sg:city":"Oakland",
    "sg:classifiers":[
        {
            "category":"Building & Trades",
            "subcategory":"Landscaping Services",
            "type":"Services"
        }
    ],
    "sg:phone":"+1 510 535 0611",
    "sg:postcode":"94606",
    "sg:province":"CA",
    "sg:tags":[
        "aged",
        "homes-institutional"
    ],
    "wof:name":"Orchards Womens Recovery Ctr",
    "wof:placetype":"venue"
},
  "geometry": {"coordinates":[-122.234746,37.797655],"type":"Point"}
}