{
  "type": "Feature",
  "properties": {
    "addr:full":"150 N Jackson Ave Ste 204 San Jose CA 95173",
    "addr:housenumber":"150",
    "addr:postcode":"95173",
    "addr:street":"N Jackson Ave Ste 204",
    "iso:country":"US",
    "sg:address":"150 N Jackson Ave Ste 204",
    "sg:city":"San Jose",
    "sg:classifiers":[
        {
            "category":"Health Services",
            "subcategory":"Dentist",
            "type":"Services"
        }
    ],
    "sg:phone":"+1 408 259 4515",
    "sg:postcode":"95173",
    "sg:province":"CA",
    "wof:name":"Don A. Stevenson DDS",
    "wof:placetype":"venue"
},
  "geometry": {"coordinates":[-121.846951,37.361998],"type":"Point"}
}