{
  "type": "Feature",
  "properties": {
    "iso:country":"US",
    "sg:address":"2667 Pacific Coast Hwy",
    "sg:city":"Torrance",
    "sg:classifiers":[
        {
            "category":"Insurance",
            "subcategory":"Health Insurance",
            "type":"Services"
        }
    ],
    "sg:phone":"+1 310 534 8494",
    "sg:postcode":"90505",
    "sg:province":"CA",
    "sg:tags":[
        "market"
    ],
    "wof:name":"Great Earth Vitamins",
    "wof:placetype":"venue"
},
  "geometry": {"coordinates":[-118.333,33.791901],"type":"Point"}
}