{
  "type": "Feature",
  "properties": {
    "iso:country":"US",
    "sg:address":"1017 University Avenue Suite 203",
    "sg:city":"Berkeley",
    "sg:classifiers":[
        {
            "category":"Building & Trades",
            "subcategory":"Construction",
            "type":"Services"
        }
    ],
    "sg:phone":"+1 510 665 9224",
    "sg:postcode":"94710",
    "sg:province":"CA",
    "sg:tags":[
        "contractor"
    ],
    "wof:name":"Struct-Tech Group",
    "wof:placetype":"venue"
},
  "geometry": {"coordinates":[-122.29299899999999,37.8689],"type":"Point"}
}