{
  "type": "Feature",
  "properties": {
    "addr:full":"12921 Evalyn Pl Poway CA 92064",
    "addr:housenumber":"12921",
    "addr:postcode":"ca 92064",
    "addr:street":"Evalyn Pl",
    "iso:country":"US",
    "sg:address":"12921 Evalyn Pl",
    "sg:city":"Poway",
    "sg:classifiers":[
        {
            "category":"Shopping",
            "subcategory":"Department Store",
            "type":"Retail Goods"
        }
    ],
    "sg:phone":"+1 858 748 7515",
    "sg:postcode":"92064",
    "sg:province":"CA",
    "sg:tags":[
        "variety"
    ],
    "wof:name":"Wight Trust 12 02 97 Dva",
    "wof:placetype":"venue"
},
  "geometry": {"coordinates":[-117.071494,32.951201],"type":"Point"}
}