{
  "type": "Feature",
  "properties": {
    "iso:country":"US",
    "sg:address":"495 E 17th St",
    "sg:city":"Costa Mesa",
    "sg:classifiers":[
        {
            "category":"Shopping",
            "subcategory":"Computers & Home Electronics",
            "type":"Retail Goods"
        }
    ],
    "sg:phone":"+1 949 631 7531",
    "sg:postcode":"92627",
    "sg:province":"CA",
    "sg:website":"www.directv.com",
    "wof:name":"DIRECTV",
    "wof:placetype":"venue"
},
  "geometry": {"coordinates":[-117.908968,33.628381],"type":"Point"}
}