{
  "type": "Feature",
  "properties": {
    "addr:full":"1241 Condor Way San Jacinto CA 92583",
    "addr:housenumber":"1241",
    "addr:postcode":"92583",
    "addr:street":"Condor Way",
    "iso:country":"US",
    "sg:address":"1241 Condor Way",
    "sg:city":"San Jacinto",
    "sg:classifiers":[
        {
            "category":"Shopping",
            "subcategory":"Gifts & Souvenirs",
            "type":"Retail Goods"
        }
    ],
    "sg:phone":"+1 951 487 1018",
    "sg:postcode":"92583",
    "sg:province":"CA",
    "wof:name":"Vineyard Gifts & Garden",
    "wof:placetype":"venue"
},
  "geometry": {"coordinates":[-116.937792,33.776177],"type":"Point"}
}