{
  "type": "Feature",
  "properties": {
    "addr:full":"8036 3rd St Ste 103 Downey CA 90241",
    "addr:housenumber":"8036",
    "addr:postcode":"90241",
    "addr:street":"3Rd St Ste 103",
    "iso:country":"US",
    "sg:address":"8036 3rd St Ste 103",
    "sg:city":"Downey",
    "sg:classifiers":[
        {
            "category":"Health Services",
            "subcategory":"Health Practitioner",
            "type":"Services"
        },
        {
            "category":"Health Services",
            "subcategory":"Chiropractor",
            "type":"Services"
        }
    ],
    "sg:phone":"+1 562 658 7956",
    "sg:postcode":"90241",
    "sg:province":"CA",
    "sg:tags":[
        "acupuncture",
        "traditional",
        "medicine",
        "chinese"
    ],
    "sg:website":"www.downeyintegrativewellness.com/",
    "wof:name":"Downey Integrative Wellness Center",
    "wof:placetype":"venue"
},
  "geometry": {"coordinates":[-118.135893,33.943994],"type":"Point"}
}