{
  "type": "Feature",
  "properties": {
    "addr:full":"8491 Bell Dr Atwater CA 95301",
    "addr:housenumber":"8491",
    "addr:postcode":"95301",
    "addr:street":"Bell Dr",
    "iso:country":"US",
    "sg:address":"8491 Bell Dr",
    "sg:city":"Atwater",
    "sg:classifiers":[
        {
            "category":"Farming",
            "subcategory":"Crops",
            "type":"Manufacturing & Wholesale Goods"
        }
    ],
    "sg:phone":"+1 209 358 9636",
    "sg:postcode":"95301",
    "sg:province":"CA",
    "sg:tags":[
        "grove",
        "nut",
        "tree"
    ],
    "wof:name":"James Glaus",
    "wof:placetype":"venue"
},
  "geometry": {"coordinates":[-120.641282,37.34571],"type":"Point"}
}