{
  "type": "Feature",
  "properties": {
    "addr:full":"1523 W Stowell Rd Santa Maria CA 93458",
    "addr:housenumber":"1523",
    "addr:postcode":"93458",
    "addr:street":"W Stowell Rd",
    "iso:country":"US",
    "sg:address":"1523 W Stowell Rd",
    "sg:city":"Santa Maria",
    "sg:classifiers":[
        {
            "category":"Shopping",
            "subcategory":"Gifts & Souvenirs",
            "type":"Retail Goods"
        }
    ],
    "sg:phone":"+1 805 346 6474",
    "sg:postcode":"93458",
    "sg:province":"CA",
    "wof:name":"Lucky Gifts & Things",
    "wof:placetype":"venue"
},
  "geometry": {"coordinates":[-120.462453,34.93883],"type":"Point"}
}