{
  "type": "Feature",
  "properties": {
    "addr:full":"7871 Mission Grove Pkwy S Riverside CA 92508",
    "addr:housenumber":"7871",
    "addr:postcode":"92508",
    "addr:street":"Mission Grove Pkwy S",
    "iso:country":"US",
    "sg:address":"7871 Mission Grove Pkwy S",
    "sg:city":"Riverside",
    "sg:classifiers":[
        {
            "category":"Real Estate",
            "subcategory":"Real Estate Operator",
            "type":"Services"
        }
    ],
    "sg:phone":"+1 951 776 1400",
    "sg:postcode":"92508",
    "sg:province":"CA",
    "sg:tags":[
        "apartment"
    ],
    "wof:name":"Estancia Apartments Homes",
    "wof:placetype":"venue"
},
  "geometry": {"coordinates":[-117.32358600000001,33.91091],"type":"Point"}
}