{
  "type": "Feature",
  "properties": {
    "addr:full":"37390 Fremont Blvd Fremont CA 94536",
    "addr:housenumber":"37390",
    "addr:postcode":"94536",
    "addr:street":"Fremont Blvd",
    "iso:country":"US",
    "sg:address":"37390 Fremont Blvd",
    "sg:city":"Fremont",
    "sg:classifiers":[
        {
            "category":"Shopping",
            "subcategory":"Jewelry",
            "type":"Retail Goods"
        }
    ],
    "sg:phone":"+1 510 796 1440",
    "sg:postcode":"94536",
    "sg:province":"CA",
    "sg:tags":[
        "clocks"
    ],
    "wof:name":"Traditional Era Clocks",
    "wof:placetype":"venue"
},
  "geometry": {"coordinates":[-122.007133,37.558298],"type":"Point"}
}