{
  "type": "Feature",
  "properties": {
    "iso:country":"US",
    "sg:address":"220 S Livermore Ave",
    "sg:city":"Livermore",
    "sg:classifiers":[
        {
            "category":"Government",
            "subcategory":"Post Office",
            "type":"Public Place"
        }
    ],
    "sg:phone":"+1 925 000 1111",
    "sg:postcode":"94550",
    "sg:province":"CA",
    "wof:name":"US Post Office",
    "wof:placetype":"venue"
},
  "geometry": {"coordinates":[-121.766694,37.680989],"type":"Point"}
}