{
  "type": "Feature",
  "properties": {
    "iso:country":"US",
    "sg:address":"4926 La Cuenta Drive",
    "sg:city":"San Diego",
    "sg:classifiers":[
        {
            "category":"Professional",
            "subcategory":"Lawyer & Legal Services",
            "type":"Services"
        }
    ],
    "sg:phone":"+1 858 560 0776",
    "sg:postcode":"92124",
    "sg:province":"CA",
    "wof:name":"Law Office of Haisha-De Forest Diane",
    "wof:placetype":"venue"
},
  "geometry": {"coordinates":[-117.099341,32.820576],"type":"Point"}
}