{
  "type": "Feature",
  "properties": {
    "iso:country":"US",
    "sg:address":"17324 Parthenia St",
    "sg:city":"Northridge",
    "sg:classifiers":[
        {
            "category":"Professional",
            "subcategory":"Accounting & Tax Preparation",
            "type":"Services"
        }
    ],
    "sg:phone":"+1 818 700 8711",
    "sg:postcode":"91325",
    "sg:province":"CA",
    "sg:tags":[
        "accountant"
    ],
    "wof:name":"Richard N Sirott Acct Corp",
    "wof:placetype":"venue"
},
  "geometry": {"coordinates":[-118.511831,34.228481],"type":"Point"}
}