{
  "type": "Feature",
  "properties": {
    "addr:full":"10759 Magnolia Ave Riverside CA 92505",
    "addr:housenumber":"10759",
    "addr:postcode":"92505",
    "addr:street":"Magnolia Ave",
    "iso:country":"US",
    "sg:address":"10759 Magnolia Ave",
    "sg:city":"Riverside",
    "sg:classifiers":[
        {
            "category":"Retail",
            "subcategory":"Repair Shop",
            "type":"Services"
        }
    ],
    "sg:phone":"+1 951 352 3177",
    "sg:postcode":"92505",
    "sg:province":"CA",
    "sg:tags":[
        "clocks",
        "parts",
        "jewelry"
    ],
    "wof:name":"Alexander Clocks & Watches",
    "wof:placetype":"venue"
},
  "geometry": {"coordinates":[-117.47244600000001,33.905753],"type":"Point"}
}