{
  "type": "Feature",
  "properties": {
    "addr:full":"Three Embarcadero Center Suite 1610 San Francisco CA 94111",
    "addr:housenumber":"suite 1610",
    "addr:postcode":"94111",
    "addr:street":"Three",
    "iso:country":"US",
    "sg:address":"Three Embarcadero Center Suite 1610",
    "sg:city":"San Francisco",
    "sg:classifiers":[
        {
            "category":"Insurance",
            "subcategory":"Hazard Insurance",
            "type":"Services"
        }
    ],
    "sg:phone":"+1 415 781 8800",
    "sg:postcode":"94111",
    "sg:province":"CA",
    "sg:website":"www.fpins.com",
    "wof:name":"Fort Point Insurance Services",
    "wof:placetype":"venue"
},
  "geometry": {"coordinates":[-122.39729800000001,37.794948],"type":"Point"}
}