{
  "type": "Feature",
  "properties": {
    "iso:country":"US",
    "sg:address":"790 E Bonita Ave",
    "sg:city":"Pomona",
    "sg:classifiers":[
        {
            "category":"Health Services",
            "subcategory":"Doctor",
            "type":"Services"
        }
    ],
    "sg:phone":"+1 909 620 7222",
    "sg:postcode":"91767",
    "sg:province":"CA",
    "sg:tags":[
        "physician",
        "surgeon"
    ],
    "wof:name":"Sarvotham K Reddy MD",
    "wof:placetype":"venue"
},
  "geometry": {"coordinates":[-117.74050699999999,34.096187],"type":"Point"}
}