{
  "type": "Feature",
  "properties": {
    "addr:full":"1762 Newport Blvd Costa Mesa CA 92627",
    "addr:housenumber":"1762",
    "addr:postcode":"92627",
    "addr:street":"Newport Blvd Costa",
    "iso:country":"US",
    "sg:address":"1762 Newport Blvd",
    "sg:city":"Costa Mesa",
    "sg:classifiers":[
        {
            "category":"Autos & Motor Vehicles",
            "subcategory":"Auto Supplies",
            "type":"Retail Goods"
        }
    ],
    "sg:phone":"+1 949 646 5019",
    "sg:postcode":"92627",
    "sg:province":"CA",
    "sg:tags":[
        "automobile",
        "parts"
    ],
    "wof:name":"Global Tires & Wheels",
    "wof:placetype":"venue"
},
  "geometry": {"coordinates":[-117.920548,33.639176],"type":"Point"}
}