{
  "type": "Feature",
  "properties": {
    "iso:country":"US",
    "sg:address":"65 El Gavilan Rd",
    "sg:city":"Orinda",
    "sg:classifiers":[
        {
            "category":"Food & Beverages",
            "subcategory":"Specialty",
            "type":"Retail Goods"
        }
    ],
    "sg:phone":"+1 925 254 6447",
    "sg:postcode":"94563",
    "sg:province":"CA",
    "sg:tags":[
        "grocers-specialty"
    ],
    "wof:name":"Continental West Sales Company Inc",
    "wof:placetype":"venue"
},
  "geometry": {"coordinates":[-122.177318,37.90003],"type":"Point"}
}