{
  "type": "Feature",
  "properties": {
    "addr:full":"9073 Nemo St Los Angeles CA 90069",
    "addr:housenumber":"9073",
    "addr:postcode":"90069",
    "addr:street":"Nemo St",
    "iso:country":"US",
    "sg:address":"9073 Nemo St",
    "sg:city":"Los Angeles",
    "sg:classifiers":[
        {
            "category":"Real Estate",
            "subcategory":"Real Estate Agent",
            "type":"Services"
        }
    ],
    "sg:phone":"+1 323 272 6617",
    "sg:postcode":"90069",
    "sg:province":"CA",
    "sg:website":"www.carlylegroupinc.com",
    "wof:name":"Carlyle Group",
    "wof:placetype":"venue"
},
  "geometry": {"coordinates":[-118.388823,34.082348],"type":"Point"}
}