{
  "type": "Feature",
  "properties": {
    "iso:country":"US",
    "sg:address":"17800 Rowland St",
    "sg:city":"Rowland Heights",
    "sg:classifiers":[
        {
            "category":"Manufacturing",
            "subcategory":"Signs",
            "type":"Manufacturing & Wholesale Goods"
        }
    ],
    "sg:phone":"+1 626 810 4206",
    "sg:postcode":"91748",
    "sg:province":"CA",
    "sg:tags":[
        "specialty",
        "mfg"
    ],
    "wof:name":"Deco Neon Lighting USA Inc",
    "wof:placetype":"venue"
},
  "geometry": {"coordinates":[-117.91701,34.001448],"type":"Point"}
}