{
  "type": "Feature",
  "properties": {
    "iso:country":"US",
    "sg:address":"136 N Ocean Ave",
    "sg:city":"Cayucos",
    "sg:classifiers":[
        {
            "category":"Sports & Exercise",
            "subcategory":"Bicycle Rental",
            "type":"Entertainment"
        }
    ],
    "sg:phone":"+1 805 995 1993",
    "sg:postcode":"93430",
    "sg:province":"CA",
    "sg:tags":[
        "wear"
    ],
    "wof:name":"Good Clean Fun Surf and Sport",
    "wof:placetype":"venue"
},
  "geometry": {"coordinates":[-120.903999,35.4487],"type":"Point"}
}