{
  "type": "Feature",
  "properties": {
    "iso:country":"US",
    "sg:address":"5559 Rock Tree Dr",
    "sg:city":"Agoura Hills",
    "sg:classifiers":[
        {
            "category":"Manufacturing",
            "subcategory":"Tools & Machinery",
            "type":"Manufacturing & Wholesale Goods"
        }
    ],
    "sg:phone":"+1 818 292 0298",
    "sg:postcode":"91301",
    "sg:province":"CA",
    "sg:tags":[
        "computer",
        "component"
    ],
    "wof:name":"A Systems Plus",
    "wof:placetype":"venue"
},
  "geometry": {"coordinates":[-118.757305,34.152165],"type":"Point"}
}