{
  "type": "Feature",
  "properties": {
    "addr:full":"6508 N Wishon Ave Fresno CA 93704",
    "addr:housenumber":"6508",
    "addr:postcode":"93704",
    "addr:street":"N Wishon Ave",
    "iso:country":"US",
    "sg:address":"6508 N Wishon Ave",
    "sg:city":"Fresno",
    "sg:classifiers":[
        {
            "category":"Health Services",
            "subcategory":"Medical Lab",
            "type":"Services"
        }
    ],
    "sg:phone":"+1 559 432 8908",
    "sg:postcode":"93704",
    "sg:province":"CA",
    "sg:tags":[
        "laboratory"
    ],
    "wof:name":"Northside Dental Laboratory",
    "wof:placetype":"venue"
},
  "geometry": {"coordinates":[-119.80161,36.832284],"type":"Point"}
}