{
  "type": "Feature",
  "properties": {
    "addr:full":"6380 Gallal Way Yorba Linda CA 92887",
    "addr:postcode":"6380;92887",
    "addr:street":"Gallal Way",
    "iso:country":"US",
    "sg:address":"6380 Gallal Way",
    "sg:city":"Yorba Linda",
    "sg:classifiers":[
        {
            "category":"Health Services",
            "subcategory":"Nursing And Care Facility",
            "type":"Services"
        }
    ],
    "sg:phone":"+1 714 996 2196",
    "sg:postcode":"92887",
    "sg:province":"CA",
    "sg:tags":[
        "home",
        "retirement",
        "community"
    ],
    "sg:website":"www.autumnhill.com",
    "wof:name":"Autumn Hill Care Homes Inc",
    "wof:placetype":"venue"
},
  "geometry": {"coordinates":[-117.779036,33.870033],"type":"Point"}
}