{
  "type": "Feature",
  "properties": {
    "addr:full":"651 W Lambert Rd La Habra CA 90631",
    "addr:housenumber":"651",
    "addr:postcode":"90631",
    "addr:street":"W Lambert Rd",
    "iso:country":"US",
    "sg:address":"651 W Lambert Rd",
    "sg:city":"La Habra",
    "sg:classifiers":[
        {
            "category":"Retail",
            "subcategory":"Auto Repair",
            "type":"Services"
        }
    ],
    "sg:phone":"+1 562 690 7301",
    "sg:postcode":"90631",
    "sg:province":"CA",
    "sg:tags":[
        "body",
        "automobile",
        "painting"
    ],
    "wof:name":"M1 Auto Collision Repair",
    "wof:placetype":"venue"
},
  "geometry": {"coordinates":[-117.95186200000001,33.924661],"type":"Point"}
}