{
  "type": "Feature",
  "properties": {
    "iso:country":"US",
    "sg:address":"2892 N Bellflower Blvd",
    "sg:city":"Long Beach",
    "sg:classifiers":[
        {
            "category":"Professional",
            "subcategory":"Employment Agencies",
            "type":"Services"
        }
    ],
    "sg:phone":"+1 562 377 5600",
    "sg:postcode":"90815",
    "sg:province":"CA",
    "wof:name":"Decision Toolbox",
    "wof:placetype":"venue"
},
  "geometry": {"coordinates":[-118.125159,33.808746],"type":"Point"}
}