{
  "type": "Feature",
  "properties": {
    "addr:full":"607 Main St Redwood City CA 94063",
    "addr:housenumber":"607",
    "addr:postcode":"94063",
    "addr:street":"Main St",
    "iso:country":"US",
    "sg:address":"607 Main St",
    "sg:city":"Redwood City",
    "sg:classifiers":[
        {
            "category":"Retail",
            "subcategory":"Repair Shop",
            "type":"Services"
        }
    ],
    "sg:phone":"+1 650 596 2846",
    "sg:postcode":"94063",
    "sg:province":"CA",
    "sg:tags":[
        "upholsterer"
    ],
    "wof:name":"R Upholstery",
    "wof:placetype":"venue"
},
  "geometry": {"coordinates":[-122.22632,37.487732],"type":"Point"}
}