{
  "type": "Feature",
  "properties": {
    "iso:country":"US",
    "sg:address":"19 S Stewart St",
    "sg:city":"Sonora",
    "sg:classifiers":[
        {
            "category":"Shopping",
            "subcategory":"Bicycles & Sporting Goods",
            "type":"Retail Goods"
        }
    ],
    "sg:phone":"+1 209 532 8388",
    "sg:postcode":"95370",
    "sg:province":"CA",
    "sg:tags":[
        "apparel",
        "bowling",
        "accessory"
    ],
    "wof:name":"Goody Locker",
    "wof:placetype":"venue"
},
  "geometry": {"coordinates":[-120.38256,37.985354],"type":"Point"}
}