{
  "type": "Feature",
  "properties": {
    "iso:country":"US",
    "sg:address":"26400 Aric Ln",
    "sg:city":"Los Altos Hills",
    "sg:classifiers":[
        {
            "category":"Professional",
            "subcategory":"Management & Consulting",
            "type":"Services"
        }
    ],
    "sg:phone":"+1 650 941 7432",
    "sg:postcode":"94022",
    "sg:province":"CA",
    "sg:tags":[
        "consultant",
        "business"
    ],
    "sg:website":"www.brinc.com",
    "wof:name":"Business Reengineering Inc",
    "wof:placetype":"venue"
},
  "geometry": {"coordinates":[-122.141735,37.389777],"type":"Point"}
}