{
  "type": "Feature",
  "properties": {
    "addr:full":"201 E Pacific Coast Hwy Wilmington CA 90744",
    "addr:housenumber":"201",
    "addr:postcode":"90744",
    "addr:street":"E Pacific Coast Hwy",
    "iso:country":"US",
    "sg:address":"201 E Pacific Coast Hwy",
    "sg:city":"Wilmington",
    "sg:classifiers":[
        {
            "category":"Shopping",
            "subcategory":"Shoes",
            "type":"Retail Goods"
        }
    ],
    "sg:phone":"+1 310 549 9154",
    "sg:postcode":"90744",
    "sg:province":"CA",
    "sg:tags":[
        "store"
    ],
    "wof:name":"Warehouse Shoe Sales",
    "wof:placetype":"venue"
},
  "geometry": {"coordinates":[-118.261002,33.791401],"type":"Point"}
}