{
  "type": "Feature",
  "properties": {
    "iso:country":"US",
    "sg:address":"42145 Lyndie Ln",
    "sg:city":"Temecula",
    "sg:classifiers":[
        {
            "category":"Social Services",
            "type":"Services"
        }
    ],
    "sg:phone":"+1 951 694 0695",
    "sg:postcode":"92591",
    "sg:province":"CA",
    "sg:tags":[
        "counselor",
        "marriage",
        "family"
    ],
    "wof:name":"Novell & Novell Counseling Svc",
    "wof:placetype":"venue"
},
  "geometry": {"coordinates":[-117.143052,33.507412],"type":"Point"}
}