{
  "type": "Feature",
  "properties": {
    "addr:full":"4345 Samoset Ave San Diego CA 92117",
    "addr:housenumber":"4345",
    "addr:postcode":"92117",
    "addr:street":"Samoset Ave",
    "iso:country":"US",
    "sg:address":"4345 Samoset Ave",
    "sg:city":"San Diego",
    "sg:classifiers":[
        {
            "category":"Home & Garden",
            "subcategory":"Building Materials",
            "type":"Retail Goods"
        }
    ],
    "sg:phone":"+1 858 274 4771",
    "sg:postcode":"92117",
    "sg:province":"CA",
    "sg:tags":[
        "glass",
        "window",
        "plate"
    ],
    "wof:name":"Aaron Glass",
    "wof:placetype":"venue"
},
  "geometry": {"coordinates":[-117.20008799999999,32.827992],"type":"Point"}
}