{
  "type": "Feature",
  "properties": {
    "iso:country":"US",
    "sg:address":"3550 Somerset Ave",
    "sg:city":"Castro Valley",
    "sg:classifiers":[
        {
            "category":"Food & Beverages",
            "subcategory":"Groceries & Convenience Stores",
            "type":"Retail Goods"
        }
    ],
    "sg:phone":"+1 510 582 6625",
    "sg:postcode":"94546",
    "sg:province":"CA",
    "sg:tags":[
        "shop",
        "grocer",
        "meat"
    ],
    "wof:name":"Al's Food Market",
    "wof:placetype":"venue"
},
  "geometry": {"coordinates":[-122.083,37.701599],"type":"Point"}
}