{
  "type": "Feature",
  "properties": {
    "addr:full":"997 Mesa Rd Point Reyes Sta CA 94956",
    "addr:housenumber":"997",
    "addr:postcode":"94956",
    "addr:street":"Mesa Rd;Reyes Sta",
    "iso:country":"US",
    "sg:address":"997 Mesa Rd",
    "sg:city":"Point Reyes Sta",
    "sg:classifiers":[
        {
            "category":"Restaurant",
            "type":"Food & Drink"
        }
    ],
    "sg:phone":"+1 415 663 8464",
    "sg:postcode":"94956",
    "sg:province":"CA",
    "sg:tags":[
        "delicatessen"
    ],
    "wof:name":"Whale Of A Deli",
    "wof:placetype":"venue"
},
  "geometry": {"coordinates":[-122.80425,38.067088],"type":"Point"}
}