{
  "type": "Feature",
  "properties": {
    "iso:country":"US",
    "sg:address":"824 5th Ave",
    "sg:city":"San Rafael",
    "sg:classifiers":[
        {
            "category":"Real Estate",
            "subcategory":"Real Estate Agent",
            "type":"Services"
        }
    ],
    "sg:phone":"+1 415 457 6644",
    "sg:postcode":"94901",
    "sg:province":"CA",
    "sg:tags":[
        "appraiser"
    ],
    "wof:name":"Marsh & Assoc",
    "wof:placetype":"venue"
},
  "geometry": {"coordinates":[-122.523844,37.973496],"type":"Point"}
}