{
  "type": "Feature",
  "properties": {
    "addr:full":"17275 Voorhes Ln Ramona CA 92065",
    "addr:housenumber":"17275",
    "addr:postcode":"92065",
    "addr:street":"Voorhes Ln",
    "iso:country":"US",
    "sg:address":"17275 Voorhes Ln",
    "sg:city":"Ramona",
    "sg:classifiers":[
        {
            "category":"Farming",
            "subcategory":"Farm",
            "type":"Manufacturing & Wholesale Goods"
        }
    ],
    "sg:phone":"+1 760 789 3119",
    "sg:postcode":"92065",
    "sg:province":"CA",
    "wof:name":"Double D Ranch",
    "wof:placetype":"venue"
},
  "geometry": {"coordinates":[-116.926123,33.022716],"type":"Point"}
}