{
  "type": "Feature",
  "properties": {
    "iso:country":"US",
    "sg:address":"514 S Broadway",
    "sg:city":"Santa Ana",
    "sg:classifiers":[
        {
            "category":"Retail",
            "subcategory":"Auto Repair",
            "type":"Services"
        }
    ],
    "sg:phone":"+1 714 612 7550",
    "sg:postcode":"92701",
    "sg:province":"CA",
    "wof:name":"Japanese Automotive Design",
    "wof:placetype":"venue"
},
  "geometry": {"coordinates":[-117.86991399999999,33.740545],"type":"Point"}
}