{
  "type": "Feature",
  "properties": {
    "iso:country":"US",
    "sg:address":"263 Bowline Dr",
    "sg:city":"Vacaville",
    "sg:classifiers":[
        {
            "category":"Professional",
            "subcategory":"Accounting & Tax Preparation",
            "type":"Services"
        }
    ],
    "sg:phone":"+1 707 448 0786",
    "sg:postcode":"95687",
    "sg:province":"CA",
    "sg:tags":[
        "return",
        "filing"
    ],
    "wof:name":"Little Bear Tax Svc",
    "wof:placetype":"venue"
},
  "geometry": {"coordinates":[-121.982926,38.347793],"type":"Point"}
}