{
  "type": "Feature",
  "properties": {
    "addr:full":"1750 Cesar Chavez Ste G San Francisco CA 94124",
    "addr:housenumber":"1750",
    "addr:postcode":"94124",
    "addr:street":"Cesar Chavez Ste G",
    "iso:country":"US",
    "sg:address":"1750 Cesar Chavez Ste G",
    "sg:city":"San Francisco",
    "sg:classifiers":[
        {
            "category":"Professional",
            "subcategory":"Business Services",
            "type":"Services"
        },
        {
            "category":"Government",
            "subcategory":"Post Office",
            "type":"Public Place"
        }
    ],
    "sg:phone":"+1 800 976 7824",
    "sg:postcode":"94124",
    "sg:province":"CA",
    "sg:tags":[
        "delivery",
        "courier"
    ],
    "sg:website":"www.mailitright.com",
    "wof:name":"Mail It Right",
    "wof:placetype":"venue"
},
  "geometry": {"coordinates":[-122.394375,37.749923],"type":"Point"}
}