{
  "type": "Feature",
  "properties": {
    "iso:country":"US",
    "sg:address":"3000 Saint Louis Rd",
    "sg:city":"Arcata",
    "sg:classifiers":[
        {
            "category":"Manufacturing",
            "subcategory":"Chemicals & Compounds",
            "type":"Manufacturing & Wholesale Goods"
        }
    ],
    "sg:phone":"+1 707 822 4119",
    "sg:postcode":"95521",
    "sg:province":"CA",
    "sg:tags":[
        "compost"
    ],
    "wof:name":"North Coast Quality Compost",
    "wof:placetype":"venue"
},
  "geometry": {"coordinates":[-124.081815,40.88671],"type":"Point"}
}