{
  "type": "Feature",
  "properties": {
    "iso:country":"US",
    "sg:address":"11490 Burbank Blvd",
    "sg:city":"North Hollywood",
    "sg:classifiers":[
        {
            "category":"Professional",
            "type":"Services"
        }
    ],
    "sg:phone":"+1 818 508 8244",
    "sg:postcode":"91601",
    "sg:province":"CA",
    "sg:tags":[
        "caterer"
    ],
    "wof:name":"Queen Catering & Party Rentals",
    "wof:placetype":"venue"
},
  "geometry": {"coordinates":[-118.381952,34.172032],"type":"Point"}
}