{
  "type": "Feature",
  "properties": {
    "addr:full":"1745 Sessums Dr Redlands CA 92374",
    "addr:housenumber":"1745",
    "addr:postcode":"92374",
    "addr:street":"Sessums Dr",
    "iso:country":"US",
    "sg:address":"1745 Sessums Dr",
    "sg:city":"Redlands",
    "sg:classifiers":[
        {
            "category":"Airport",
            "type":"Transportation"
        }
    ],
    "sg:phone":"+1 909 794 3244",
    "sg:postcode":"92374",
    "sg:province":"CA",
    "wof:name":"Red Aero",
    "wof:placetype":"venue"
},
  "geometry": {"coordinates":[-117.14449500000001,34.083521],"type":"Point"}
}