{
  "type": "Feature",
  "properties": {
    "iso:country":"US",
    "sg:address":"1049 38th St",
    "sg:city":"Sacramento",
    "sg:classifiers":[
        {
            "category":"Professional",
            "subcategory":"Advertising",
            "type":"Services"
        }
    ],
    "sg:phone":"+1 916 457 4682",
    "sg:postcode":"95816",
    "sg:province":"CA",
    "sg:tags":[
        "agency"
    ],
    "wof:name":"Martis & Partners Advertising",
    "wof:placetype":"venue"
},
  "geometry": {"coordinates":[-121.456715,38.568086],"type":"Point"}
}