{
  "type": "Feature",
  "properties": {
    "addr:full":"4536 French Creek Rd Shingle Springs CA 95682",
    "addr:housenumber":"4536",
    "addr:postcode":"95682",
    "addr:street":"French Creek Rd",
    "iso:country":"US",
    "sg:address":"4536 French Creek Rd",
    "sg:city":"Shingle Springs",
    "sg:classifiers":[
        {
            "category":"Professional",
            "subcategory":"Engineering",
            "type":"Services"
        }
    ],
    "sg:phone":"+1 530 677 4308",
    "sg:postcode":"95682",
    "sg:province":"CA",
    "sg:tags":[
        "engineer"
    ],
    "wof:name":"Neil Moore & Assoc",
    "wof:placetype":"venue"
},
  "geometry": {"coordinates":[-120.920928,38.650232],"type":"Point"}
}