{
  "type": "Feature",
  "properties": {
    "iso:country":"US",
    "sg:address":"3663 Buchanan Ave",
    "sg:city":"Riverside",
    "sg:classifiers":[
        {
            "category":"Education",
            "subcategory":"Vocational School",
            "type":"Public Place"
        }
    ],
    "sg:phone":"+1 951 272 8707",
    "sg:postcode":"92503",
    "sg:province":"CA",
    "sg:tags":[
        "equipment",
        "material",
        "industrial",
        "handling"
    ],
    "wof:name":"Usa Fork Lift",
    "wof:placetype":"venue"
},
  "geometry": {"coordinates":[-117.496773,33.88866],"type":"Point"}
}