{
  "type": "Feature",
  "properties": {
    "iso:country":"US",
    "sg:address":"161 S Orange St",
    "sg:city":"Orange",
    "sg:classifiers":[
        {
            "category":"Organizations",
            "subcategory":"Religious Organization",
            "type":"Services"
        }
    ],
    "sg:phone":"+1 714 532 6363",
    "sg:postcode":"92866",
    "sg:province":"CA",
    "wof:name":"United Methodist Churches",
    "wof:placetype":"venue"
},
  "geometry": {"coordinates":[-117.851997,33.7869],"type":"Point"}
}