{
  "type": "Feature",
  "properties": {
    "iso:country":"US",
    "sg:address":"5503 Reseda Blvd",
    "sg:city":"Tarzana",
    "sg:classifiers":[
        {
            "category":"Utilities",
            "subcategory":"Mobile Phone",
            "type":"Services"
        }
    ],
    "sg:phone":"+1 818 264 7744",
    "sg:postcode":"91356",
    "sg:province":"CA",
    "sg:tags":[
        "telephone",
        "cellular"
    ],
    "wof:name":"PCS",
    "wof:placetype":"venue"
},
  "geometry": {"coordinates":[-118.536072,34.169865],"type":"Point"}
}