{
  "type": "Feature",
  "properties": {
    "iso:country":"US",
    "sg:address":"436 14th Street Suite 920",
    "sg:city":"Oakland",
    "sg:classifiers":[
        {
            "category":"Education",
            "subcategory":"Special Training",
            "type":"Public Place"
        }
    ],
    "sg:phone":"+1 510 891 0150",
    "sg:postcode":"94612",
    "sg:province":"CA",
    "sg:tags":[
        "adult"
    ],
    "sg:website":"www.techskills.edu",
    "wof:name":"Techskills",
    "wof:placetype":"venue"
},
  "geometry": {"coordinates":[-122.27067700000001,37.804436],"type":"Point"}
}