{
  "type": "Feature",
  "properties": {
    "iso:country":"US",
    "sg:address":"1529 W Manchester Avenue",
    "sg:city":"Los Angeles",
    "sg:classifiers":[
        {
            "category":"Shopping",
            "subcategory":"Party Supplies",
            "type":"Retail Goods"
        }
    ],
    "sg:phone":"+1 323 759 8144",
    "sg:postcode":"90047",
    "sg:province":"CA",
    "wof:name":"All Party Supply",
    "wof:placetype":"venue"
},
  "geometry": {"coordinates":[-118.303803,33.959884],"type":"Point"}
}