{
  "type": "Feature",
  "properties": {
    "addr:full":"11906 Wilshire Blvd Los Angeles CA 90025",
    "addr:housenumber":"11906",
    "addr:postcode":"90025",
    "addr:street":"Wilshire Blvd",
    "iso:country":"US",
    "sg:address":"11906 Wilshire Blvd",
    "sg:city":"Los Angeles",
    "sg:classifiers":[
        {
            "category":"Local Transit",
            "type":"Transportation"
        }
    ],
    "sg:phone":"+1 818 905 1010",
    "sg:postcode":"90025",
    "sg:province":"CA",
    "sg:tags":[
        "passenger"
    ],
    "wof:name":"My Limousine Service",
    "wof:placetype":"venue"
},
  "geometry": {"coordinates":[-118.46502700000001,34.046],"type":"Point"}
}