{
  "type": "Feature",
  "properties": {
    "addr:full":"554 S Blackstone St Tulare CA 93274",
    "addr:housenumber":"554",
    "addr:postcode":"93274",
    "addr:street":"S Blackstone St",
    "iso:country":"US",
    "sg:address":"554 S Blackstone St",
    "sg:city":"Tulare",
    "sg:classifiers":[
        {
            "category":"Organizations",
            "subcategory":"Religious Organization",
            "type":"Services"
        }
    ],
    "sg:phone":"+1 559 685 1976",
    "sg:postcode":"93274",
    "sg:province":"CA",
    "sg:tags":[
        "place",
        "worship",
        "church"
    ],
    "sg:website":"http://www.vcftulare.org",
    "wof:name":"Vineyard Christian Fellowship",
    "wof:placetype":"venue"
},
  "geometry": {"coordinates":[-119.331018,36.202967],"type":"Point"}
}