{
  "type": "Feature",
  "properties": {
    "iso:country":"US",
    "sg:address":"1401 Exposition Blvd",
    "sg:city":"Los Angeles",
    "sg:classifiers":[
        {
            "category":"Food & Beverages",
            "subcategory":"Groceries & Convenience Stores",
            "type":"Retail Goods"
        }
    ],
    "sg:phone":"+1 323 737 4657",
    "sg:postcode":"90018",
    "sg:province":"CA",
    "wof:name":"Exposition Market Place",
    "wof:placetype":"venue"
},
  "geometry": {"coordinates":[-118.303988,34.018386],"type":"Point"}
}