{
  "type": "Feature",
  "properties": {
    "iso:country":"US",
    "sg:address":"1160 E Brantley Ct",
    "sg:city":"Upland",
    "sg:classifiers":[
        {
            "category":"Real Estate",
            "subcategory":"Real Estate Agent",
            "type":"Services"
        }
    ],
    "sg:phone":"+1 909 946 3619",
    "sg:postcode":"91786",
    "sg:province":"CA",
    "sg:tags":[
        "appraiser"
    ],
    "wof:name":"Appraisals Plus",
    "wof:placetype":"venue"
},
  "geometry": {"coordinates":[-117.635278,34.111422],"type":"Point"}
}