{
  "type": "Feature",
  "properties": {
    "addr:full":"1834 Newport Blvd Ste C Costa Mesa CA 92627",
    "addr:housenumber":"1834",
    "addr:postcode":"92627",
    "addr:street":"Newport Blvd Ste C",
    "iso:country":"US",
    "sg:address":"1834 Newport Blvd Ste C",
    "sg:city":"Costa Mesa",
    "sg:classifiers":[
        {
            "category":"Home & Garden",
            "subcategory":"Household Appliances",
            "type":"Retail Goods"
        },
        {
            "category":"Building & Trades",
            "subcategory":"Plumbing",
            "type":"Services"
        }
    ],
    "sg:phone":"+1 949 515 8500",
    "sg:postcode":"92627",
    "sg:province":"CA",
    "sg:tags":[
        "repair"
    ],
    "wof:name":"Newport Tankless",
    "wof:placetype":"venue"
},
  "geometry": {"coordinates":[-117.917945,33.641267],"type":"Point"}
}