{
  "type": "Feature",
  "properties": {
    "addr:full":"3851 S Bear St Santa Ana CA 92704",
    "addr:housenumber":"3851",
    "addr:postcode":"92704",
    "addr:street":"S Bear St",
    "iso:country":"US",
    "sg:address":"3851 S Bear St",
    "sg:city":"Santa Ana",
    "sg:classifiers":[
        {
            "category":"Arts & Performance",
            "subcategory":"Art Gallery",
            "type":"Entertainment"
        }
    ],
    "sg:phone":"+1 714 540 6430",
    "sg:postcode":"92704",
    "sg:province":"CA",
    "wof:name":"Showcase Gallery",
    "wof:placetype":"venue"
},
  "geometry": {"coordinates":[-117.891998,33.695202],"type":"Point"}
}