{
  "type": "Feature",
  "properties": {
    "addr:full":"796 W Wahl Rd El Centro CA 92243",
    "addr:housenumber":"796",
    "addr:postcode":"92243",
    "addr:street":"W Wahl Rd",
    "iso:country":"US",
    "sg:address":"796 W Wahl Rd",
    "sg:city":"El Centro",
    "sg:classifiers":[
        {
            "category":"Restaurant",
            "type":"Food & Drink"
        }
    ],
    "sg:phone":"+1 760 352 5810",
    "sg:postcode":"92243",
    "sg:province":"CA",
    "wof:name":"Camacho's Place",
    "wof:placetype":"venue"
},
  "geometry": {"coordinates":[-115.602259,32.723335],"type":"Point"}
}