{
  "type": "Feature",
  "properties": {
    "iso:country":"US",
    "sg:address":"512 N Isabel St Apt B",
    "sg:city":"Glendale",
    "sg:classifiers":[
        {
            "category":"Cinema",
            "subcategory":"Movie Rental",
            "type":"Entertainment"
        },
        {
            "category":"Building & Trades",
            "subcategory":"Construction",
            "type":"Services"
        }
    ],
    "sg:phone":"+1 818 242 1720",
    "sg:postcode":"91206",
    "sg:province":"CA",
    "sg:tags":[
        "game",
        "video",
        "contractor"
    ],
    "wof:name":"Y P Construction Co",
    "wof:placetype":"venue"
},
  "geometry": {"coordinates":[-118.236,34.1558],"type":"Point"}
}