{
  "type": "Feature",
  "properties": {
    "addr:full":"1925 Turpen St Olivehurst CA 95961",
    "addr:housenumber":"1925",
    "addr:postcode":"ca 95961",
    "addr:street":"Turpen St",
    "iso:country":"US",
    "sg:address":"1925 Turpen St",
    "sg:city":"Olivehurst",
    "sg:classifiers":[
        {
            "category":"Freight",
            "type":"Transportation"
        }
    ],
    "sg:phone":"+1 530 749 1450",
    "sg:postcode":"95961",
    "sg:province":"CA",
    "sg:tags":[
        "commercial",
        "storage",
        "general"
    ],
    "wof:name":"Powerline Mini Storage",
    "wof:placetype":"venue"
},
  "geometry": {"coordinates":[-121.54816,39.096604],"type":"Point"}
}