{
  "type": "Feature",
  "properties": {
    "iso:country":"US",
    "sg:address":"7308 Hollywood Blvd",
    "sg:city":"West Hollywood",
    "sg:classifiers":[
        {
            "category":"Retail",
            "subcategory":"Laundry & Dry Cleaning",
            "type":"Services"
        }
    ],
    "sg:phone":"+1 323 876 8257",
    "sg:postcode":"90046",
    "sg:province":"CA",
    "sg:tags":[
        "cleaners"
    ],
    "wof:name":"Panda Bell Cleaners",
    "wof:placetype":"venue"
},
  "geometry": {"coordinates":[-118.349666,34.101551],"type":"Point"}
}