{
  "type": "Feature",
  "properties": {
    "iso:country":"US",
    "sg:address":"6730 Santa Rita Rd",
    "sg:city":"Pleasanton",
    "sg:classifiers":[
        {
            "category":"Restaurant",
            "type":"Food & Drink"
        }
    ],
    "sg:phone":"+1 925 463 3557",
    "sg:postcode":"94588",
    "sg:province":"CA",
    "wof:name":"Caffino",
    "wof:placetype":"venue"
},
  "geometry": {"coordinates":[-121.8721,37.699988],"type":"Point"}
}