{
  "type": "Feature",
  "properties": {
    "iso:country":"US",
    "sg:address":"1035 N Armando St",
    "sg:city":"Anaheim",
    "sg:classifiers":[
        {
            "category":"Professional",
            "subcategory":"Computer Services",
            "type":"Services"
        }
    ],
    "sg:phone":"+1 714 632 2900",
    "sg:postcode":"92806",
    "sg:province":"CA",
    "sg:tags":[
        "related"
    ],
    "wof:name":"Empire Duct Cleaning",
    "wof:placetype":"venue"
},
  "geometry": {"coordinates":[-117.860029,33.848935],"type":"Point"}
}