{
  "type": "Feature",
  "properties": {
    "addr:full":"235 Mark Twain Ave Tulare CA 93274",
    "addr:housenumber":"235",
    "addr:postcode":"93274",
    "addr:street":"Mark Twain Ave",
    "iso:country":"US",
    "sg:address":"235 Mark Twain Ave",
    "sg:city":"Tulare",
    "sg:classifiers":[
        {
            "category":"Education",
            "subcategory":"Dance Studio",
            "type":"Public Place"
        }
    ],
    "sg:phone":"+1 559 688 1144",
    "sg:postcode":"93274",
    "sg:province":"CA",
    "sg:tags":[
        "instruction",
        "dancing"
    ],
    "wof:name":"Tulare Dance Works",
    "wof:placetype":"venue"
},
  "geometry": {"coordinates":[-119.35027100000001,36.23323],"type":"Point"}
}