{
  "type": "Feature",
  "properties": {
    "addr:full":"15000 Crenshaw Boulevard Gardena CA 90249",
    "addr:housenumber":"15000",
    "addr:postcode":"90249",
    "addr:street":"Crenshaw Boulevard",
    "iso:country":"US",
    "sg:address":"15000 Crenshaw Boulevard",
    "sg:city":"Gardena",
    "sg:classifiers":[
        {
            "category":"Shopping",
            "subcategory":"Clothing, Apparel, & Fashions",
            "type":"Retail Goods"
        },
        {
            "category":"Shopping",
            "subcategory":"Crafts & Fabrics",
            "type":"Retail Goods"
        }
    ],
    "sg:phone":"+1 310 323 0805",
    "sg:postcode":"90249",
    "sg:province":"CA",
    "sg:tags":[
        "shop",
        "clothing",
        "women's",
        "knit",
        "accessory"
    ],
    "wof:name":"Christina Knit",
    "wof:placetype":"venue"
},
  "geometry": {"coordinates":[-118.326469,33.895581],"type":"Point"}
}