{
  "type": "Feature",
  "properties": {
    "iso:country":"US",
    "sg:address":"1624 Starr Dr",
    "sg:city":"Yuba City",
    "sg:classifiers":[
        {
            "category":"Social Services",
            "type":"Services"
        }
    ],
    "sg:phone":"+1 530 755 4880",
    "sg:postcode":"95993",
    "sg:province":"CA",
    "sg:tags":[
        "counselor",
        "marriage",
        "family"
    ],
    "wof:name":"Elizabeth B Blake",
    "wof:placetype":"venue"
},
  "geometry": {"coordinates":[-121.645404,39.143431],"type":"Point"}
}