{
  "type": "Feature",
  "properties": {
    "addr:full":"6251 Schaefer Ave Chino CA 91710",
    "addr:housenumber":"6251",
    "addr:postcode":"91710",
    "addr:street":"Schaefer Ave",
    "iso:country":"US",
    "sg:address":"6251 Schaefer Ave",
    "sg:city":"Chino",
    "sg:classifiers":[
        {
            "category":"Professional",
            "subcategory":"Research",
            "type":"Services"
        }
    ],
    "sg:phone":"+1 909 464 1898",
    "sg:postcode":"91710",
    "sg:province":"CA",
    "sg:tags":[
        "development",
        "marketing",
        "product"
    ],
    "wof:name":"Innovations USA",
    "wof:placetype":"venue"
},
  "geometry": {"coordinates":[-117.66902399999999,34.004638],"type":"Point"}
}