{
  "type": "Feature",
  "properties": {
    "iso:country":"US",
    "sg:address":"3131 Foothill Blvd",
    "sg:city":"La Crescenta",
    "sg:classifiers":[
        {
            "category":"Education",
            "subcategory":"Special Training",
            "type":"Public Place"
        }
    ],
    "sg:phone":"+1 818 541 0106",
    "sg:postcode":"91214",
    "sg:province":"CA",
    "sg:tags":[
        "instruction",
        "music"
    ],
    "wof:name":"Tchaikovsky Piano Academy",
    "wof:placetype":"venue"
},
  "geometry": {"coordinates":[-118.246633,34.228324],"type":"Point"}
}