{
  "type": "Feature",
  "properties": {
    "iso:country":"US",
    "sg:address":"1838 Redcliff St",
    "sg:city":"Los Angeles",
    "sg:classifiers":[
        {
            "category":"Real Estate",
            "subcategory":"Real Estate Agent",
            "type":"Services"
        }
    ],
    "sg:phone":"+1 323 662 5653",
    "sg:postcode":"90026",
    "sg:province":"CA",
    "sg:tags":[
        "consultant"
    ],
    "wof:name":"Ridgecrest Capital Inc",
    "wof:placetype":"venue"
},
  "geometry": {"coordinates":[-118.27101500000001,34.092576],"type":"Point"}
}