{
  "type": "Feature",
  "properties": {
    "addr:full":"32225 State Hwy 79 S Temecula CA 92592",
    "addr:housenumber":"32225",
    "addr:postcode":"92592",
    "addr:street":"State Hwy 79 S",
    "iso:country":"US",
    "sg:address":"32225 State Hwy 79 S",
    "sg:city":"Temecula",
    "sg:classifiers":[
        {
            "category":"Retail",
            "subcategory":"Portrait Studio",
            "type":"Services"
        }
    ],
    "sg:phone":"+1 951 303 9906",
    "sg:postcode":"92592",
    "sg:province":"CA",
    "sg:tags":[
        "photographer"
    ],
    "wof:name":"Wal-Mart Portrait Studio",
    "wof:placetype":"venue"
},
  "geometry": {"coordinates":[-117.100672,33.480537],"type":"Point"}
}