{
  "type": "Feature",
  "properties": {
    "addr:full":"10105 S Doty Ave Inglewood CA 90303",
    "addr:housenumber":"10105",
    "addr:postcode":"90303",
    "addr:street":"S Doty Ave",
    "iso:country":"US",
    "sg:address":"10105 S Doty Ave",
    "sg:city":"Inglewood",
    "sg:classifiers":[
        {
            "category":"Freight",
            "type":"Transportation"
        }
    ],
    "sg:phone":"+1 310 673 9937",
    "sg:postcode":"90303",
    "sg:province":"CA",
    "sg:tags":[
        "arrangement"
    ],
    "wof:name":"Outstanding International",
    "wof:placetype":"venue"
},
  "geometry": {"coordinates":[-118.33982399999999,33.944606],"type":"Point"}
}