{
  "type": "Feature",
  "properties": {
    "addr:full":"1350 Columbia S Ste 603 San Diego CA 92101",
    "addr:housenumber":"1350",
    "addr:postcode":"92101",
    "addr:street":"Columbia S Ste 603",
    "iso:country":"US",
    "sg:address":"1350 Columbia S Ste 603",
    "sg:city":"San Diego",
    "sg:classifiers":[
        {
            "category":"Real Estate",
            "subcategory":"Architect",
            "type":"Services"
        }
    ],
    "sg:phone":"+1 619 299 3917",
    "sg:postcode":"92101",
    "sg:province":"CA",
    "sg:website":"www.sfeirarch.com",
    "wof:name":"Sfeir Architecture",
    "wof:placetype":"venue"
},
  "geometry": {"coordinates":[-117.167835,32.719404],"type":"Point"}
}