{
  "type": "Feature",
  "properties": {
    "iso:country":"US",
    "sg:address":"606 H St",
    "sg:city":"Union City",
    "sg:classifiers":[
        {
            "category":"Organizations",
            "subcategory":"Religious Organization",
            "type":"Services"
        }
    ],
    "sg:phone":"+1 510 429 8446",
    "sg:postcode":"94587",
    "sg:province":"CA",
    "sg:tags":[
        "church"
    ],
    "wof:name":"Community Seventh-Day Church",
    "wof:placetype":"venue"
},
  "geometry": {"coordinates":[-122.019056,37.599059],"type":"Point"}
}