{
  "type": "Feature",
  "properties": {
    "addr:full":"7738 Sierra Ave Fontana CA 92336",
    "addr:housenumber":"7738",
    "addr:postcode":"92336",
    "addr:street":"Sierra Ave",
    "iso:country":"US",
    "sg:address":"7738 Sierra Ave",
    "sg:city":"Fontana",
    "sg:classifiers":[
        {
            "category":"Organizations",
            "subcategory":"Religious Organization",
            "type":"Services"
        }
    ],
    "sg:phone":"+1 909 823 1900",
    "sg:postcode":"92336",
    "sg:province":"CA",
    "sg:tags":[
        "church"
    ],
    "wof:name":"Jehovah's Witnesses",
    "wof:placetype":"venue"
},
  "geometry": {"coordinates":[-117.43592200000001,34.113076],"type":"Point"}
}