{
  "type": "Feature",
  "properties": {
    "addr:full":"20477 Green Acres Dr Sonora CA 95370",
    "addr:housenumber":"20477",
    "addr:postcode":"95370",
    "addr:street":"Green Acres Dr",
    "iso:country":"US",
    "sg:address":"20477 Green Acres Dr",
    "sg:city":"Sonora",
    "sg:classifiers":[
        {
            "category":"Building & Trades",
            "subcategory":"Plumbing",
            "type":"Services"
        }
    ],
    "sg:phone":"+1 209 532 0125",
    "sg:postcode":"95370",
    "sg:province":"CA",
    "sg:tags":[
        "plumber",
        "industrial",
        "contractors-commercial"
    ],
    "wof:name":"Ferrell Plumbing",
    "wof:placetype":"venue"
},
  "geometry": {"coordinates":[-120.27871500000001,37.994601],"type":"Point"}
}