{
  "type": "Feature",
  "properties": {
    "addr:full":"11656 Wilshire Blvd Los Angeles CA 90025",
    "addr:housenumber":"11656",
    "addr:postcode":"90025",
    "addr:street":"Wilshire Blvd",
    "iso:country":"US",
    "sg:address":"11656 Wilshire Blvd",
    "sg:city":"Los Angeles",
    "sg:classifiers":[
        {
            "category":"Food & Beverages",
            "subcategory":"Groceries & Convenience Stores",
            "type":"Retail Goods"
        }
    ],
    "sg:phone":"+1 310 478 5976",
    "sg:postcode":"90025",
    "sg:province":"CA",
    "wof:name":"7-Eleven",
    "wof:placetype":"venue"
},
  "geometry": {"coordinates":[-118.460196,34.04992],"type":"Point"}
}