{
  "type": "Feature",
  "properties": {
    "iso:country":"US",
    "sg:address":"910 E Stowell Rd",
    "sg:city":"Santa Maria",
    "sg:classifiers":[
        {
            "category":"Professional",
            "subcategory":"Employment Agencies",
            "type":"Services"
        }
    ],
    "sg:phone":"+1 805 922 0472",
    "sg:postcode":"93454",
    "sg:province":"CA",
    "sg:tags":[
        "leasing"
    ],
    "wof:name":"Staff Construction Inc",
    "wof:placetype":"venue"
},
  "geometry": {"coordinates":[-120.424328,34.938264],"type":"Point"}
}