{
  "type": "Feature",
  "properties": {
    "addr:full":"254 Church St San Francisco CA 94114",
    "addr:housenumber":"254",
    "addr:postcode":"94114",
    "addr:street":"Church St",
    "iso:country":"US",
    "sg:address":"254 Church St",
    "sg:city":"San Francisco",
    "sg:classifiers":[
        {
            "category":"Health Services",
            "subcategory":"Health Practitioner",
            "type":"Services"
        }
    ],
    "sg:phone":"+1 415 846 1238",
    "sg:postcode":"94114",
    "sg:province":"CA",
    "sg:tags":[
        "acupuncture"
    ],
    "sg:website":"www.enlightenedmedicine.com",
    "wof:name":"Don Reznicek, MS LAc CMT",
    "wof:placetype":"venue"
},
  "geometry": {"coordinates":[-122.428895,37.766486],"type":"Point"}
}