{
  "type": "Feature",
  "properties": {
    "iso:country":"US",
    "sg:address":"30211 Ave de Las Banderas",
    "sg:city":"Rcho Sta Marg",
    "sg:classifiers":[
        {
            "category":"Banks & Credit Unions",
            "subcategory":"Bank",
            "type":"Services"
        }
    ],
    "sg:phone":"+1 949 766 6706",
    "sg:postcode":"92688",
    "sg:province":"CA",
    "sg:tags":[
        "financing"
    ],
    "wof:name":"Auto Benefits Corp",
    "wof:placetype":"venue"
},
  "geometry": {"coordinates":[-117.603272,33.634444],"type":"Point"}
}