{
  "type": "Feature",
  "properties": {
    "iso:country":"US",
    "sg:address":"25963 Brodiaea Ave",
    "sg:city":"Moreno Valley",
    "sg:classifiers":[
        {
            "category":"Building & Trades",
            "subcategory":"Construction",
            "type":"Services"
        }
    ],
    "sg:phone":"+1 951 243 3039",
    "sg:postcode":"92553",
    "sg:province":"CA",
    "sg:tags":[
        "excavation",
        "contractor"
    ],
    "wof:name":"A3 Backhoe Service",
    "wof:placetype":"venue"
},
  "geometry": {"coordinates":[-117.20895899999999,33.913709],"type":"Point"}
}