{
  "type": "Feature",
  "properties": {
    "iso:country":"US",
    "sg:address":"3310 W Shaw Ave",
    "sg:city":"Fresno",
    "sg:classifiers":[
        {
            "category":"Food & Beverages",
            "subcategory":"Candy",
            "type":"Retail Goods"
        }
    ],
    "sg:phone":"+1 559 277 0624",
    "sg:postcode":"93711",
    "sg:province":"CA",
    "sg:tags":[
        "confectionery"
    ],
    "wof:name":"See's Candies",
    "wof:placetype":"venue"
},
  "geometry": {"coordinates":[-119.850858,36.808349],"type":"Point"}
}