{
  "type": "Feature",
  "properties": {
    "iso:country":"US",
    "sg:address":"9229 del Mar Dr",
    "sg:city":"Pico Rivera",
    "sg:classifiers":[
        {
            "category":"Freight",
            "type":"Transportation"
        }
    ],
    "sg:phone":"+1 562 699 5607",
    "sg:postcode":"90660",
    "sg:province":"CA",
    "sg:tags":[
        "operator",
        "local",
        "trucking"
    ],
    "wof:name":"Galindo Brothers Trucking",
    "wof:placetype":"venue"
},
  "geometry": {"coordinates":[-118.074309,34.017662],"type":"Point"}
}