{
  "type": "Feature",
  "properties": {
    "addr:full":"31540 Corte Salinas Temecula CA 92592",
    "addr:housenumber":"31540",
    "addr:postcode":"92592",
    "addr:street":"Corte Salinas",
    "iso:country":"US",
    "sg:address":"31540 Corte Salinas",
    "sg:city":"Temecula",
    "sg:classifiers":[
        {
            "category":"Professional",
            "subcategory":"Secretarial Services",
            "type":"Services"
        }
    ],
    "sg:phone":"+1 951 506 3081",
    "sg:postcode":"92592",
    "sg:province":"CA",
    "sg:tags":[
        "transcription",
        "medical"
    ],
    "wof:name":"Melissa Horton",
    "wof:placetype":"venue"
},
  "geometry": {"coordinates":[-117.107827,33.511009],"type":"Point"}
}