{
  "type": "Feature",
  "properties": {
    "addr:full":"601 E Glenoaks Blvd Ste 204 Glendale CA 91207",
    "addr:housenumber":"601",
    "addr:postcode":"91207",
    "addr:street":"E Glenoaks Blvd Ste 204",
    "iso:country":"US",
    "sg:address":"601 E Glenoaks Blvd Ste 204",
    "sg:city":"Glendale",
    "sg:classifiers":[
        {
            "category":"Professional",
            "subcategory":"Lawyer & Legal Services",
            "type":"Services"
        }
    ],
    "sg:phone":"+1 323 245 8919",
    "sg:postcode":"91207",
    "sg:province":"CA",
    "wof:name":"Nelson Eric A Atty",
    "wof:placetype":"venue"
},
  "geometry": {"coordinates":[-118.24880899999999,34.158411],"type":"Point"}
}