{
  "type": "Feature",
  "properties": {
    "addr:full":"815 Lincoln Way Auburn CA 95603",
    "addr:housenumber":"815",
    "addr:postcode":"ca 95603",
    "addr:street":"Lincoln Way",
    "iso:country":"US",
    "sg:address":"815 Lincoln Way",
    "sg:city":"Auburn",
    "sg:classifiers":[
        {
            "category":"Shopping",
            "subcategory":"Pharmacy",
            "type":"Retail Goods"
        }
    ],
    "sg:phone":"+1 530 885 6524",
    "sg:postcode":"95603",
    "sg:province":"CA",
    "wof:name":"Auburn Drug Co",
    "wof:placetype":"venue"
},
  "geometry": {"coordinates":[-121.068608,38.900111],"type":"Point"}
}