{
  "type": "Feature",
  "properties": {
    "iso:country":"US",
    "sg:address":"259 S Padre Juan Ave",
    "sg:city":"Ojai",
    "sg:classifiers":[
        {
            "category":"Professional",
            "subcategory":"Accounting & Tax Preparation",
            "type":"Services"
        }
    ],
    "sg:phone":"+1 805 646 7126",
    "sg:postcode":"93023",
    "sg:province":"CA",
    "sg:tags":[
        "bookkeeping",
        "billing"
    ],
    "wof:name":"Robertson Bookkeeping Solutions",
    "wof:placetype":"venue"
},
  "geometry": {"coordinates":[-119.27908499999999,34.446364],"type":"Point"}
}