{
  "type": "Feature",
  "properties": {
    "iso:country":"US",
    "sg:address":"521 E Main St",
    "sg:city":"Visalia",
    "sg:classifiers":[
        {
            "category":"Manufacturing",
            "subcategory":"Signs",
            "type":"Manufacturing & Wholesale Goods"
        }
    ],
    "sg:phone":"+1 559 625 4095",
    "sg:postcode":"93292",
    "sg:province":"CA",
    "sg:tags":[
        "specialty",
        "mfg"
    ],
    "wof:name":"CA Sign Permits",
    "wof:placetype":"venue"
},
  "geometry": {"coordinates":[-119.285675,36.330109],"type":"Point"}
}