{
  "type": "Feature",
  "properties": {
    "addr:full":"20110 Pioneer Blvd Cerritos CA 90703",
    "addr:housenumber":"20110",
    "addr:postcode":"ca 90703",
    "addr:street":"Pioneer Blvd",
    "iso:country":"US",
    "sg:address":"20110 Pioneer Blvd",
    "sg:city":"Cerritos",
    "sg:classifiers":[
        {
            "category":"Real Estate",
            "subcategory":"Real Estate Agent",
            "type":"Services"
        }
    ],
    "sg:phone":"+1 562 246 1300",
    "sg:postcode":"90703",
    "sg:province":"CA",
    "wof:name":"One Century Realty",
    "wof:placetype":"venue"
},
  "geometry": {"coordinates":[-118.08200600000001,33.848355],"type":"Point"}
}