{
  "type": "Feature",
  "properties": {
    "iso:country":"US",
    "sg:address":"1955 N St",
    "sg:city":"Newman",
    "sg:classifiers":[
        {
            "category":"Fast Food",
            "type":"Food & Drink"
        },
        {
            "category":"Restaurant",
            "type":"Food & Drink"
        }
    ],
    "sg:phone":"+1 209 862 0160",
    "sg:postcode":"95360",
    "sg:province":"CA",
    "sg:tags":[
        "american",
        "hot",
        "hamburger",
        "dog"
    ],
    "sg:website":"http://www.bk.com",
    "wof:name":"Burger King",
    "wof:placetype":"venue"
},
  "geometry": {"coordinates":[-121.01864399999999,37.308513],"type":"Point"}
}