{
  "type": "Feature",
  "properties": {
    "addr:full":"11053 Santa Monica Blvd Los Angeles CA 90025",
    "addr:housenumber":"11053",
    "addr:postcode":"90025",
    "addr:street":"Santa Monica Blvd",
    "iso:country":"US",
    "sg:address":"11053 Santa Monica Blvd",
    "sg:city":"Los Angeles",
    "sg:classifiers":[
        {
            "category":"Health Services",
            "subcategory":"Clinic",
            "type":"Services"
        },
        {
            "category":"Personal",
            "subcategory":"Hair Removal",
            "type":"Services"
        }
    ],
    "sg:phone":"+1 310 312 1231",
    "sg:postcode":"90025",
    "sg:province":"CA",
    "sg:tags":[
        "spa",
        "medical",
        "laser"
    ],
    "sg:website":"tattoomdla.com",
    "wof:name":"Tattoo MD",
    "wof:placetype":"venue"
},
  "geometry": {"coordinates":[-118.44320399999999,34.048024],"type":"Point"}
}