{
  "type": "Feature",
  "properties": {
    "addr:full":"7625 Sunrise Blvd Citrus Heights CA 95610",
    "addr:housenumber":"7625",
    "addr:postcode":"95610",
    "addr:street":"Sunrise Blvd",
    "iso:country":"US",
    "sg:address":"7625 Sunrise Blvd",
    "sg:city":"Citrus Heights",
    "sg:classifiers":[
        {
            "category":"Real Estate",
            "subcategory":"Real Estate Agent",
            "type":"Services"
        }
    ],
    "sg:phone":"+1 916 723 3166",
    "sg:postcode":"95610",
    "sg:province":"CA",
    "sg:tags":[
        "management"
    ],
    "wof:name":"Landmark Limited",
    "wof:placetype":"venue"
},
  "geometry": {"coordinates":[-121.271879,38.704325],"type":"Point"}
}