{
  "type": "Feature",
  "properties": {
    "iso:country":"US",
    "sg:address":"11610 1/2 South Street",
    "sg:city":"Artesia",
    "sg:classifiers":[
        {
            "category":"Restaurant",
            "type":"Food & Drink"
        }
    ],
    "sg:phone":"+1 562 809 8369",
    "sg:postcode":"90701",
    "sg:province":"CA",
    "sg:tags":[
        "taiwanese"
    ],
    "wof:name":"Canaan Restaurant",
    "wof:placetype":"venue"
},
  "geometry": {"coordinates":[-118.086411,33.85836],"type":"Point"}
}