{
  "type": "Feature",
  "properties": {
    "iso:country":"US",
    "sg:address":"4346 Cogswell Rd",
    "sg:city":"El Monte",
    "sg:classifiers":[
        {
            "category":"Health Services",
            "subcategory":"Podiatrist",
            "type":"Services"
        }
    ],
    "sg:phone":"+1 626 442 7455",
    "sg:postcode":"91732",
    "sg:province":"CA",
    "wof:name":"Michael A Alberico DPM",
    "wof:placetype":"venue"
},
  "geometry": {"coordinates":[-118.010143,34.080543],"type":"Point"}
}