{
  "type": "Feature",
  "properties": {
    "iso:country":"US",
    "sg:address":"619 W Covina Blvd",
    "sg:city":"San Dimas",
    "sg:classifiers":[
        {
            "category":"Manufacturing",
            "subcategory":"Printing",
            "type":"Manufacturing & Wholesale Goods"
        }
    ],
    "sg:phone":"+1 909 394 2044",
    "sg:postcode":"91773",
    "sg:province":"CA",
    "sg:tags":[
        "typesetting"
    ],
    "wof:name":"Type & Print",
    "wof:placetype":"venue"
},
  "geometry": {"coordinates":[-117.817595,34.09943],"type":"Point"}
}