{
  "type": "Feature",
  "properties": {
    "iso:country":"US",
    "sg:address":"1811 Muirfield Dr",
    "sg:city":"Oxnard",
    "sg:classifiers":[
        {
            "category":"Building & Trades",
            "subcategory":"Construction",
            "type":"Services"
        }
    ],
    "sg:phone":"+1 805 981 3077",
    "sg:postcode":"93036",
    "sg:province":"CA",
    "sg:tags":[
        "restoration",
        "cleaning",
        "patio",
        "deck"
    ],
    "wof:name":"Anacapa Water Blasting Inc",
    "wof:placetype":"venue"
},
  "geometry": {"coordinates":[-119.197255,34.228855],"type":"Point"}
}