{
  "type": "Feature",
  "properties": {
    "iso:country":"US",
    "sg:address":"1100 E Main St",
    "sg:city":"Barstow",
    "sg:classifiers":[
        {
            "category":"Autos & Motor Vehicles",
            "subcategory":"Automobile Sales",
            "type":"Retail Goods"
        }
    ],
    "sg:phone":"+1 760 256 2827",
    "sg:postcode":"92311",
    "sg:province":"CA",
    "sg:tags":[
        "car",
        "dealer"
    ],
    "wof:name":"Specialty Car Co",
    "wof:placetype":"venue"
},
  "geometry": {"coordinates":[-117.011662,34.898419],"type":"Point"}
}