{
  "type": "Feature",
  "properties": {
    "iso:country":"US",
    "sg:address":"24980 Lake St",
    "sg:city":"Hemet",
    "sg:classifiers":[
        {
            "category":"Professional",
            "type":"Services"
        }
    ],
    "sg:phone":"+1 951 306 0192",
    "sg:postcode":"92544",
    "sg:province":"CA",
    "wof:name":"Sonja D Strausser",
    "wof:placetype":"venue"
},
  "geometry": {"coordinates":[-116.914852,33.75473],"type":"Point"}
}