{
  "type": "Feature",
  "properties": {
    "iso:country":"US",
    "sg:address":"5620 Franklin Blvd",
    "sg:city":"Sacramento",
    "sg:classifiers":[
        {
            "category":"Food & Beverages",
            "subcategory":"Liquor & Beverages",
            "type":"Retail Goods"
        }
    ],
    "sg:phone":"+1 916 421 1517",
    "sg:postcode":"95824",
    "sg:province":"CA",
    "sg:tags":[
        "beer",
        "wine",
        "spirit",
        "alcoholic"
    ],
    "wof:name":"Chuck's Bottle Shop",
    "wof:placetype":"venue"
},
  "geometry": {"coordinates":[-121.47199999999999,38.524399],"type":"Point"}
}