{
  "type": "Feature",
  "properties": {
    "addr:full":"333 S San Pedro St Los Angeles CA 90013",
    "addr:housenumber":"333",
    "addr:postcode":"90013",
    "addr:street":"S San Pedro St",
    "iso:country":"US",
    "sg:address":"333 S San Pedro St",
    "sg:city":"Los Angeles",
    "sg:classifiers":[
        {
            "category":"Professional",
            "type":"Services"
        }
    ],
    "sg:phone":"+1 213 626 6036",
    "sg:postcode":"90013",
    "sg:province":"CA",
    "sg:tags":[
        "establishment"
    ],
    "wof:name":"Crescendo Network Inc",
    "wof:placetype":"venue"
},
  "geometry": {"coordinates":[-118.24302,34.045996],"type":"Point"}
}