{
  "type": "Feature",
  "properties": {
    "addr:full":"2215 E Cesar E Chavez Ave Los Angeles CA 90033",
    "addr:housenumber":"2215",
    "addr:postcode":"90033",
    "addr:street":"E Cesar E Chavez Ave",
    "iso:country":"US",
    "sg:address":"2215 E Cesar E Chavez Ave",
    "sg:city":"Los Angeles",
    "sg:classifiers":[
        {
            "category":"Personal",
            "subcategory":"Beauty Salon",
            "type":"Services"
        }
    ],
    "sg:phone":"+1 323 266 4054",
    "sg:postcode":"90033",
    "sg:province":"CA",
    "wof:name":"Cheri Nails",
    "wof:placetype":"venue"
},
  "geometry": {"coordinates":[-118.20895299999999,34.047323],"type":"Point"}
}