{
  "type": "Feature",
  "properties": {
    "iso:country":"US",
    "sg:address":"2204 W Magnolia Blvd",
    "sg:city":"Burbank",
    "sg:classifiers":[
        {
            "category":"Manufacturing",
            "subcategory":"Printing",
            "type":"Manufacturing & Wholesale Goods"
        }
    ],
    "sg:phone":"+1 818 566 8910",
    "sg:postcode":"91506",
    "sg:province":"CA",
    "sg:tags":[
        "printer"
    ],
    "wof:name":"Envelope Express",
    "wof:placetype":"venue"
},
  "geometry": {"coordinates":[-118.332593,34.172587],"type":"Point"}
}