{
  "type": "Feature",
  "properties": {
    "addr:full":"3966 Missouri Flat Rd Placerville CA 95667",
    "addr:housenumber":"3966",
    "addr:postcode":"95667",
    "addr:street":"Missouri Flat Rd",
    "iso:country":"US",
    "sg:address":"3966 Missouri Flat Rd",
    "sg:city":"Placerville",
    "sg:classifiers":[
        {
            "category":"Shopping",
            "subcategory":"Jewelry",
            "type":"Retail Goods"
        }
    ],
    "sg:phone":"+1 530 622 5967",
    "sg:postcode":"95667",
    "sg:province":"CA",
    "sg:tags":[
        "jeweler"
    ],
    "wof:name":"Crescent Jewelers",
    "wof:placetype":"venue"
},
  "geometry": {"coordinates":[-120.841785,38.712934],"type":"Point"}
}