{
  "type": "Feature",
  "properties": {
    "iso:country":"US",
    "sg:address":"1679 E Main St",
    "sg:city":"El Cajon",
    "sg:classifiers":[
        {
            "category":"Health Services",
            "subcategory":"Doctor",
            "type":"Services"
        }
    ],
    "sg:phone":"+1 619 588 6566",
    "sg:postcode":"92021",
    "sg:province":"CA",
    "sg:tags":[
        "physician",
        "surgeon"
    ],
    "wof:name":"Primary Care For Women",
    "wof:placetype":"venue"
},
  "geometry": {"coordinates":[-116.921105,32.808499],"type":"Point"}
}