{
  "type": "Feature",
  "properties": {
    "addr:full":"330 Zachary St Moorpark CA 93021",
    "addr:housenumber":"330",
    "addr:postcode":"ca 93021",
    "addr:street":"Zachary St",
    "iso:country":"US",
    "sg:address":"330 Zachary St",
    "sg:city":"Moorpark",
    "sg:classifiers":[
        {
            "category":"Real Estate",
            "subcategory":"Architect",
            "type":"Services"
        }
    ],
    "sg:phone":"+1 805 529 9129",
    "sg:postcode":"93021",
    "sg:province":"CA",
    "sg:website":"www.pswcgroup.com",
    "wof:name":"PSWC Group",
    "wof:placetype":"venue"
},
  "geometry": {"coordinates":[-118.871442,34.283171],"type":"Point"}
}