{
  "type": "Feature",
  "properties": {
    "iso:country":"US",
    "sg:address":"1845 Oak Rd",
    "sg:city":"Simi Valley",
    "sg:classifiers":[
        {
            "category":"Social Services",
            "subcategory":"Child Care",
            "type":"Services"
        }
    ],
    "sg:phone":"+1 805 526 0136",
    "sg:postcode":"93063",
    "sg:province":"CA",
    "sg:tags":[
        "kindergarten",
        "academic",
        "school"
    ],
    "sg:website":"www.phoenixranch.org",
    "wof:name":"Phoenix Ranch School",
    "wof:placetype":"venue"
},
  "geometry": {"coordinates":[-118.676231,34.268662],"type":"Point"}
}