{
  "type": "Feature",
  "properties": {
    "addr:full":"114 E Washington Blvd Crescent City CA 95531",
    "addr:housenumber":"114",
    "addr:postcode":"95531",
    "addr:street":"E Washington Blvd Crescent",
    "iso:country":"US",
    "sg:address":"114 E Washington Blvd",
    "sg:city":"Crescent City",
    "sg:classifiers":[
        {
            "category":"Building & Trades",
            "subcategory":"Construction",
            "type":"Services"
        }
    ],
    "sg:phone":"+1 707 464 1213",
    "sg:postcode":"95531",
    "sg:province":"CA",
    "sg:tags":[
        "carpentry",
        "contractor"
    ],
    "wof:name":"Crescent Cabinets",
    "wof:placetype":"venue"
},
  "geometry": {"coordinates":[-124.20268900000001,41.772834],"type":"Point"}
}