{
  "type": "Feature",
  "properties": {
    "addr:full":"4730 W Telephone Rd Ventura CA 93003",
    "addr:housenumber":"4730",
    "addr:postcode":"93003",
    "addr:street":"W Telephone Rd",
    "iso:country":"US",
    "sg:address":"4730 W Telephone Rd",
    "sg:city":"Ventura",
    "sg:classifiers":[
        {
            "category":"Health Services",
            "subcategory":"Hospital",
            "type":"Services"
        },
        {
            "category":"Health Services",
            "subcategory":"Doctor",
            "type":"Services"
        }
    ],
    "sg:phone":"+1 805 677 4955",
    "sg:postcode":"93003",
    "sg:province":"CA",
    "sg:tags":[
        "clinic",
        "general"
    ],
    "wof:name":"CMH Center For Family Health",
    "wof:placetype":"venue"
},
  "geometry": {"coordinates":[-119.227435,34.263055],"type":"Point"}
}