{
  "type": "Feature",
  "properties": {
    "iso:country":"US",
    "sg:address":"1395 San Carlos Ave",
    "sg:city":"San Carlos",
    "sg:classifiers":[
        {
            "category":"Professional",
            "subcategory":"Advertising",
            "type":"Services"
        }
    ],
    "sg:phone":"+1 650 610 9099",
    "sg:postcode":"94070",
    "sg:province":"CA",
    "wof:name":"Arami Design",
    "wof:placetype":"venue"
},
  "geometry": {"coordinates":[-122.26216599999999,37.505752],"type":"Point"}
}