{
  "type": "Feature",
  "properties": {
    "iso:country":"US",
    "sg:address":"845 Russell Ave",
    "sg:city":"Santa Rosa",
    "sg:classifiers":[
        {
            "category":"Food & Beverages",
            "subcategory":"Bakery",
            "type":"Retail Goods"
        }
    ],
    "sg:phone":"+1 707 523 2383",
    "sg:postcode":"95403",
    "sg:province":"CA",
    "sg:tags":[
        "baker"
    ],
    "wof:name":"Yellow Moon Bakery",
    "wof:placetype":"venue"
},
  "geometry": {"coordinates":[-122.731238,38.469215],"type":"Point"}
}