{
  "type": "Feature",
  "properties": {
    "addr:full":"77 Maiden Ln San Francisco CA 94108",
    "addr:housenumber":"77",
    "addr:postcode":"94108",
    "addr:street":"Maiden Ln",
    "iso:country":"US",
    "sg:address":"77 Maiden Ln",
    "sg:city":"San Francisco",
    "sg:classifiers":[
        {
            "category":"Professional",
            "subcategory":"Management & Consulting",
            "type":"Services"
        }
    ],
    "sg:phone":"+1 415 593 8400",
    "sg:postcode":"94108",
    "sg:province":"CA",
    "sg:tags":[
        "firm",
        "public",
        "relations"
    ],
    "wof:name":"Text 100 Public Relations",
    "wof:placetype":"venue"
},
  "geometry": {"coordinates":[-122.404169,37.788309],"type":"Point"}
}