{
  "type": "Feature",
  "properties": {
    "addr:full":"1200 Arizona St Redlands CA 92374",
    "addr:housenumber":"1200",
    "addr:postcode":"92374",
    "addr:street":"Arizona St",
    "iso:country":"US",
    "sg:address":"1200 Arizona St",
    "sg:city":"Redlands",
    "sg:classifiers":[
        {
            "category":"Restaurant",
            "type":"Food & Drink"
        }
    ],
    "sg:phone":"+1 909 335 2782",
    "sg:postcode":"92374",
    "sg:province":"CA",
    "wof:name":"Muay Thai Kickboxing",
    "wof:placetype":"venue"
},
  "geometry": {"coordinates":[-117.207521,34.068445],"type":"Point"}
}