{
  "type": "Feature",
  "properties": {
    "iso:country":"US",
    "sg:address":"1825 South Grant St Suite 400",
    "sg:city":"San Mateo",
    "sg:classifiers":[
        {
            "category":"Professional",
            "subcategory":"Computer Services",
            "type":"Services"
        }
    ],
    "sg:phone":"+1 650 212 1535",
    "sg:postcode":"94402",
    "sg:province":"CA",
    "sg:tags":[
        "secondary-market",
        "secondary",
        "securities",
        "shares",
        "capital",
        "fundraising"
    ],
    "sg:website":"http://www.xpertfinancial.com",
    "wof:name":"Xpert Financial",
    "wof:placetype":"venue"
},
  "geometry": {"coordinates":[-122.30549999999999,37.559843],"type":"Point"}
}