{
  "type": "Feature",
  "properties": {
    "iso:country":"US",
    "sg:address":"1048 W Alameda Ave",
    "sg:city":"Burbank",
    "sg:classifiers":[
        {
            "category":"Shopping",
            "subcategory":"Optician",
            "type":"Retail Goods"
        }
    ],
    "sg:phone":"+1 818 556 6200",
    "sg:postcode":"91506",
    "sg:province":"CA",
    "sg:tags":[
        "eyewear"
    ],
    "wof:name":"Eclipse Eyewear",
    "wof:placetype":"venue"
},
  "geometry": {"coordinates":[-118.31354899999999,34.162949],"type":"Point"}
}