{
  "type": "Feature",
  "properties": {
    "iso:country":"US",
    "sg:address":"4022 Phelan Rd",
    "sg:city":"Phelan",
    "sg:classifiers":[
        {
            "category":"Banks & Credit Unions",
            "subcategory":"Bank",
            "type":"Services"
        }
    ],
    "sg:phone":"+1 760 868 2222",
    "sg:postcode":"92371",
    "sg:province":"CA",
    "wof:name":"Business Bank Of California",
    "wof:placetype":"venue"
},
  "geometry": {"coordinates":[-117.574238,34.426403],"type":"Point"}
}