{
  "type": "Feature",
  "properties": {
    "addr:full":"701 Kings Row San Jose CA 95112",
    "addr:housenumber":"701",
    "addr:postcode":"95112",
    "addr:street":"Kings Row",
    "iso:country":"US",
    "sg:address":"701 Kings Row",
    "sg:city":"San Jose",
    "sg:classifiers":[
        {
            "category":"Building & Trades",
            "subcategory":"Plumbing",
            "type":"Services"
        }
    ],
    "sg:phone":"+1 408 437 1507",
    "sg:postcode":"95112",
    "sg:province":"CA",
    "sg:website":"www.championplumbingpro.com",
    "wof:name":"Champion Plumbing",
    "wof:placetype":"venue"
},
  "geometry": {"coordinates":[-121.898883,37.373222],"type":"Point"}
}