{
  "type": "Feature",
  "properties": {
    "iso:country":"US",
    "sg:address":"4161 Oceanside Blvd #101",
    "sg:city":"Oceanside",
    "sg:classifiers":[
        {
            "category":"Education",
            "subcategory":"School",
            "type":"Public Place"
        }
    ],
    "sg:phone":"+1 760 631 6000",
    "sg:postcode":"92056",
    "sg:province":"CA",
    "wof:name":"Syvlan Learning Center Oceanside",
    "wof:placetype":"venue"
},
  "geometry": {"coordinates":[-117.28648099999999,33.205775],"type":"Point"}
}