{
  "type": "Feature",
  "properties": {
    "addr:full":"3147 Juniper St San Diego CA 92104",
    "addr:housenumber":"3147",
    "addr:postcode":"92104",
    "addr:street":"Juniper St",
    "iso:country":"US",
    "sg:address":"3147 Juniper St",
    "sg:city":"San Diego",
    "sg:classifiers":[
        {
            "category":"Transit Center",
            "subcategory":"Passenger",
            "type":"Transportation"
        },
        {
            "category":"Taxi",
            "type":"Transportation"
        },
        {
            "category":"Airline",
            "type":"Transportation"
        }
    ],
    "sg:phone":"+1 619 269 7397",
    "sg:postcode":"92104",
    "sg:province":"CA",
    "sg:tags":[
        "shuttle",
        "airport"
    ],
    "sg:website":"www.terramoto.net",
    "wof:name":"Terramoto Transportation Inc.",
    "wof:placetype":"venue"
},
  "geometry": {"coordinates":[-117.12637599999999,32.729618],"type":"Point"}
}