{
  "type": "Feature",
  "properties": {
    "iso:country":"US",
    "sg:address":"430 S Hobart Blvd",
    "sg:city":"Los Angeles",
    "sg:classifiers":[
        {
            "category":"Travel",
            "subcategory":"Travel Agent",
            "type":"Entertainment"
        }
    ],
    "sg:phone":"+1 213 739 1002",
    "sg:postcode":"90020",
    "sg:province":"CA",
    "sg:tags":[
        "agency"
    ],
    "wof:name":"New Star Travel Services Inc",
    "wof:placetype":"venue"
},
  "geometry": {"coordinates":[-118.305285,34.065911],"type":"Point"}
}