{
  "type": "Feature",
  "properties": {
    "iso:country":"US",
    "sg:address":"1742 Garnet Ave",
    "sg:city":"San Diego",
    "sg:classifiers":[
        {
            "category":"Personal",
            "subcategory":"Beauty Salon",
            "type":"Services"
        }
    ],
    "sg:phone":"+1 858 272 9977",
    "sg:postcode":"92109",
    "sg:province":"CA",
    "sg:tags":[
        "nail",
        "manicuring"
    ],
    "wof:name":"Christine's Nails",
    "wof:placetype":"venue"
},
  "geometry": {"coordinates":[-117.237999,32.800301],"type":"Point"}
}