{
  "type": "Feature",
  "properties": {
    "addr:full":"1608 4th St Berkeley CA 94710",
    "addr:housenumber":"1608",
    "addr:postcode":"94710",
    "addr:street":"4Th St",
    "iso:country":"US",
    "sg:address":"1608 4th St",
    "sg:city":"Berkeley",
    "sg:classifiers":[
        {
            "category":"Manufacturing",
            "subcategory":"Chemicals & Compounds",
            "type":"Manufacturing & Wholesale Goods"
        }
    ],
    "sg:phone":"+1 510 526 1525",
    "sg:postcode":"94710",
    "sg:province":"CA",
    "sg:tags":[
        "sealant",
        "mfg"
    ],
    "wof:name":"P P G Arspc P R C De Soto Intl",
    "wof:placetype":"venue"
},
  "geometry": {"coordinates":[-122.301389,37.87203],"type":"Point"}
}