{
  "type": "Feature",
  "properties": {
    "addr:full":"1198 N Winton Way Atwater CA 95301",
    "addr:housenumber":"1198",
    "addr:postcode":"95301",
    "addr:street":"N Winton Way",
    "iso:country":"US",
    "sg:address":"1198 N Winton Way",
    "sg:city":"Atwater",
    "sg:classifiers":[
        {
            "category":"Autos & Motor Vehicles",
            "subcategory":"Fuel & Gas Station",
            "type":"Retail Goods"
        }
    ],
    "sg:phone":"+1 209 357 0829",
    "sg:postcode":"95301",
    "sg:province":"CA",
    "sg:tags":[
        "oil"
    ],
    "wof:name":"Atwater Shell",
    "wof:placetype":"venue"
},
  "geometry": {"coordinates":[-120.612638,37.348704],"type":"Point"}
}