{
  "type": "Feature",
  "properties": {
    "addr:full":"13617 Midland Rd Poway CA 92064",
    "addr:housenumber":"13617",
    "addr:postcode":"ca 92064",
    "addr:street":"Midland Rd",
    "iso:country":"US",
    "sg:address":"13617 Midland Rd",
    "sg:city":"Poway",
    "sg:classifiers":[
        {
            "category":"Education",
            "subcategory":"School",
            "type":"Public Place"
        }
    ],
    "sg:phone":"+1 858 748 5880",
    "sg:postcode":"92064",
    "sg:province":"CA",
    "wof:name":"Cornerstone Christian School",
    "wof:placetype":"venue"
},
  "geometry": {"coordinates":[-117.036179,32.961542],"type":"Point"}
}