{
  "type": "Feature",
  "properties": {
    "addr:full":"22542 Shannon Cir Lake Forest CA 92630",
    "addr:housenumber":"22542",
    "addr:postcode":"92630",
    "addr:street":"Shannon Cir",
    "iso:country":"US",
    "sg:address":"22542 Shannon Cir",
    "sg:city":"Lake Forest",
    "sg:classifiers":[
        {
            "category":"Wholesale",
            "subcategory":"Machinery & Supplies",
            "type":"Manufacturing & Wholesale Goods"
        }
    ],
    "sg:phone":"+1 949 951 8827",
    "sg:postcode":"92630",
    "sg:province":"CA",
    "sg:tags":[
        "equipment",
        "irrigation",
        "nursery",
        "gardening",
        "system"
    ],
    "sg:website":"www.hydro-scape.com",
    "wof:name":"Hydro-Scape Products",
    "wof:placetype":"venue"
},
  "geometry": {"coordinates":[-117.712036,33.635074],"type":"Point"}
}