{
  "type": "Feature",
  "properties": {
    "iso:country":"US",
    "sg:address":"2937 Promontory Cir",
    "sg:city":"San Ramon",
    "sg:classifiers":[
        {
            "category":"Manufacturing",
            "subcategory":"Food",
            "type":"Manufacturing & Wholesale Goods"
        }
    ],
    "sg:phone":"+1 925 208 0000",
    "sg:postcode":"94583",
    "sg:province":"CA",
    "sg:tags":[
        "tea",
        "specialty",
        "mfg"
    ],
    "wof:name":"Bonkers Tea",
    "wof:placetype":"venue"
},
  "geometry": {"coordinates":[-121.988889,37.777451],"type":"Point"}
}