{
  "type": "Feature",
  "properties": {
    "iso:country":"US",
    "sg:address":"100 World Way",
    "sg:city":"Los Angeles",
    "sg:classifiers":[
        {
            "category":"Shopping",
            "subcategory":"Gifts & Souvenirs",
            "type":"Retail Goods"
        }
    ],
    "sg:phone":"+1 310 641 1182",
    "sg:postcode":"90045",
    "sg:province":"CA",
    "sg:tags":[
        "flower"
    ],
    "wof:name":"Hudson Group",
    "wof:placetype":"venue"
},
  "geometry": {"coordinates":[-118.39973,33.945457],"type":"Point"}
}