{
  "type": "Feature",
  "properties": {
    "addr:full":"2999 Mission St San Francisco CA 94110",
    "addr:housenumber":"2999",
    "addr:postcode":"94110",
    "addr:street":"Mission St",
    "iso:country":"US",
    "sg:address":"2999 Mission St",
    "sg:city":"San Francisco",
    "sg:classifiers":[
        {
            "category":"Shopping",
            "subcategory":"Music",
            "type":"Retail Goods"
        }
    ],
    "sg:phone":"+1 415 647 6767",
    "sg:postcode":"94110",
    "sg:province":"CA",
    "sg:tags":[
        "video",
        "disc",
        "tape",
        "cassette"
    ],
    "sg:website":"www.soulvideo.com",
    "wof:name":"Midnight Video",
    "wof:placetype":"venue"
},
  "geometry": {"coordinates":[-122.418288,37.75064],"type":"Point"}
}