{
  "type": "Feature",
  "properties": {
    "iso:country":"US",
    "sg:address":"535 Monterey St",
    "sg:city":"Hollister",
    "sg:classifiers":[
        {
            "category":"Professional",
            "subcategory":"Lawyer & Legal Services",
            "type":"Services"
        }
    ],
    "sg:phone":"+1 831 637 0071",
    "sg:postcode":"95023",
    "sg:province":"CA",
    "sg:tags":[
        "attorney",
        "practice"
    ],
    "wof:name":"Balbas And Tiffanys Attorney At Law Inc",
    "wof:placetype":"venue"
},
  "geometry": {"coordinates":[-121.403862,36.850971],"type":"Point"}
}