{
  "type": "Feature",
  "properties": {
    "iso:country":"US",
    "sg:address":"14235 Oxnard St",
    "sg:city":"Van Nuys",
    "sg:classifiers":[
        {
            "category":"Professional",
            "subcategory":"Accounting & Tax Preparation",
            "type":"Services"
        }
    ],
    "sg:phone":"+1 818 904 0992",
    "sg:postcode":"91401",
    "sg:province":"CA",
    "sg:tags":[
        "bookkeeping",
        "general"
    ],
    "wof:name":"Bookkeepers Unlimited",
    "wof:placetype":"venue"
},
  "geometry": {"coordinates":[-118.44376800000001,34.179468],"type":"Point"}
}