{
  "type": "Feature",
  "properties": {
    "iso:country":"US",
    "sg:address":"8290 Vickers St",
    "sg:city":"San Diego",
    "sg:classifiers":[
        {
            "category":"Retail",
            "subcategory":"Repair Shop",
            "type":"Services"
        }
    ],
    "sg:phone":"+1 858 565 1211",
    "sg:postcode":"92111",
    "sg:province":"CA",
    "sg:tags":[
        "refinishing",
        "furniture"
    ],
    "wof:name":"Craftsman Furniture Rstrtn",
    "wof:placetype":"venue"
},
  "geometry": {"coordinates":[-117.14683599999999,32.827352],"type":"Point"}
}