{
  "type": "Feature",
  "properties": {
    "addr:full":"4360 Mills Cir Ontario CA 91764",
    "addr:housenumber":"4360",
    "addr:postcode":"91764",
    "addr:street":"Mills Cir",
    "iso:country":"US",
    "sg:address":"4360 Mills Cir",
    "sg:city":"Ontario",
    "sg:classifiers":[
        {
            "category":"Bakery",
            "type":"Food & Drink"
        }
    ],
    "sg:menulink":"http://www.allmenus.com/ca/ontario/218696-cocos-bakery-restaurant/menu/",
    "sg:phone":"+1 909 481 8644",
    "sg:postcode":"91764",
    "sg:province":"CA",
    "sg:tags":[
        "sandwich",
        "salad",
        "soup",
        "american",
        "pastry",
        "wrap",
        "wing"
    ],
    "wof:name":"Coco's Bakery Restaurant",
    "wof:placetype":"venue"
},
  "geometry": {"coordinates":[-117.55642,34.071319],"type":"Point"}
}