{
  "type": "Feature",
  "properties": {
    "iso:country":"US",
    "sg:address":"425 Delphine Pl",
    "sg:city":"Fullerton",
    "sg:classifiers":[
        {
            "category":"Professional",
            "type":"Services"
        }
    ],
    "sg:phone":"+1 714 680 9894",
    "sg:postcode":"92833",
    "sg:province":"CA",
    "wof:name":"Girlfriday USA Ltd",
    "wof:placetype":"venue"
},
  "geometry": {"coordinates":[-117.954681,33.875019],"type":"Point"}
}