{
  "type": "Feature",
  "properties": {
    "addr:full":"885 S Orange Grove Blvd Pasadena CA 91105",
    "addr:housenumber":"885",
    "addr:postcode":"91105",
    "addr:street":"S Orange Grove Blvd",
    "iso:country":"US",
    "sg:address":"885 S Orange Grove Blvd",
    "sg:city":"Pasadena",
    "sg:classifiers":[
        {
            "category":"Professional",
            "type":"Services"
        }
    ],
    "sg:phone":"+1 626 403 9536",
    "sg:postcode":"91105",
    "sg:province":"CA",
    "wof:name":"Westfall Co",
    "wof:placetype":"venue"
},
  "geometry": {"coordinates":[-118.158562,34.130172],"type":"Point"}
}