{
  "type": "Feature",
  "properties": {
    "iso:country":"US",
    "sg:address":"111 W Orangethorpe Ave",
    "sg:city":"Fullerton",
    "sg:classifiers":[
        {
            "category":"Health Services",
            "subcategory":"Chiropractor",
            "type":"Services"
        }
    ],
    "sg:phone":"+1 714 738 5080",
    "sg:postcode":"92832",
    "sg:province":"CA",
    "sg:website":"www.fullertonchiro.com/",
    "wof:name":"Hsuan Wang, Chiropractic Inc.",
    "wof:placetype":"venue"
},
  "geometry": {"coordinates":[-117.925084,33.859555],"type":"Point"}
}