{
  "type": "Feature",
  "properties": {
    "addr:full":"1473 W Linden St Riverside CA 92507",
    "addr:housenumber":"1473",
    "addr:postcode":"92507",
    "addr:street":"W Linden St",
    "iso:country":"US",
    "sg:address":"1473 W Linden St",
    "sg:city":"Riverside",
    "sg:classifiers":[
        {
            "category":"Arts & Performance",
            "subcategory":"Theater",
            "type":"Entertainment"
        }
    ],
    "sg:phone":"+1 951 369 0852",
    "sg:postcode":"92507",
    "sg:province":"CA",
    "sg:tags":[
        "musician"
    ],
    "sg:website":"www.thebellrays.com",
    "wof:name":"Bell Ray",
    "wof:placetype":"venue"
},
  "geometry": {"coordinates":[-117.343416,33.979448],"type":"Point"}
}