{
  "type": "Feature",
  "properties": {
    "iso:country":"US",
    "sg:address":"1543 Ambergrove Dr",
    "sg:city":"San Jose",
    "sg:classifiers":[
        {
            "category":"Real Estate",
            "subcategory":"Real Estate Operator",
            "type":"Services"
        }
    ],
    "sg:phone":"+1 408 453 8011",
    "sg:postcode":"95131",
    "sg:province":"CA",
    "sg:tags":[
        "apartment"
    ],
    "wof:name":"Amberwood Apartments",
    "wof:placetype":"venue"
},
  "geometry": {"coordinates":[-121.88099699999999,37.381302],"type":"Point"}
}