{
  "type": "Feature",
  "properties": {
    "iso:country":"US",
    "sg:address":"432 Lexington St",
    "sg:city":"Delano",
    "sg:classifiers":[
        {
            "category":"Health Services",
            "subcategory":"Doctor",
            "type":"Services"
        }
    ],
    "sg:phone":"+1 661 725 6266",
    "sg:postcode":"93215",
    "sg:province":"CA",
    "sg:tags":[
        "physician",
        "surgeon"
    ],
    "wof:name":"Dilbagh Gehlawat Inc",
    "wof:placetype":"venue"
},
  "geometry": {"coordinates":[-119.240756,35.762693],"type":"Point"}
}