{
  "type": "Feature",
  "properties": {
    "addr:full":"31555 Rd 144 Visalia CA 93292",
    "addr:postcode":"31555;93292",
    "addr:street":"Rd 144",
    "iso:country":"US",
    "sg:address":"31555 Rd 144",
    "sg:city":"Visalia",
    "sg:classifiers":[
        {
            "category":"Wholesale",
            "subcategory":"Machinery & Supplies",
            "type":"Manufacturing & Wholesale Goods"
        }
    ],
    "sg:phone":"+1 559 798 0546",
    "sg:postcode":"93292",
    "sg:province":"CA",
    "sg:tags":[
        "equipment",
        "hydraulic"
    ],
    "wof:name":"Steve's Mobile Hydraulic Hoses",
    "wof:placetype":"venue"
},
  "geometry": {"coordinates":[-119.25200599999999,36.362527],"type":"Point"}
}