{
  "type": "Feature",
  "properties": {
    "iso:country":"US",
    "sg:address":"149 N Glendora Ave",
    "sg:city":"Glendora",
    "sg:classifiers":[
        {
            "category":"Shopping",
            "subcategory":"Clothing, Apparel, & Fashions",
            "type":"Retail Goods"
        }
    ],
    "sg:phone":"+1 626 914 4998",
    "sg:postcode":"91741",
    "sg:province":"CA",
    "wof:name":"Ciao Bella Boutique",
    "wof:placetype":"venue"
},
  "geometry": {"coordinates":[-117.865479,34.137834],"type":"Point"}
}