{
  "type": "Feature",
  "properties": {
    "addr:full":"125 N Maryland Ave Glendale CA 91206",
    "addr:housenumber":"125",
    "addr:postcode":"91206",
    "addr:street":"N Maryland Ave",
    "iso:country":"US",
    "sg:address":"125 N Maryland Ave",
    "sg:city":"Glendale",
    "sg:classifiers":[
        {
            "category":"Personal",
            "subcategory":"Beauty Salon",
            "type":"Services"
        }
    ],
    "sg:phone":"+1 818 246 3399",
    "sg:postcode":"91206",
    "sg:province":"CA",
    "sg:tags":[
        "loss",
        "center",
        "weight"
    ],
    "sg:website":"www.slimmerbodyca.com/",
    "wof:name":"Slimmer Body",
    "wof:placetype":"venue"
},
  "geometry": {"coordinates":[-118.25398199999999,34.147234],"type":"Point"}
}