{
  "type": "Feature",
  "properties": {
    "addr:full":"4541 Irving St. San Francisco CA 94122",
    "addr:housenumber":"4541",
    "addr:postcode":"94122",
    "addr:street":"Irving St.",
    "iso:country":"US",
    "sg:address":"4541 Irving St.",
    "sg:city":"San Francisco",
    "sg:classifiers":[
        {
            "category":"Arts & Performance",
            "subcategory":"Dance",
            "type":"Entertainment"
        }
    ],
    "sg:phone":"+1 415 385 5929",
    "sg:postcode":"94122",
    "sg:province":"CA",
    "sg:tags":[
        "school"
    ],
    "sg:website":"www.avenuedancestudio.com",
    "wof:name":"Avenue Dance Studio",
    "wof:placetype":"venue"
},
  "geometry": {"coordinates":[-122.50675,37.762008],"type":"Point"}
}