{
  "type": "Feature",
  "properties": {
    "addr:full":"555 9th St Suite B5 San Francisco CA 94103",
    "addr:housenumber":"555",
    "addr:postcode":"94103",
    "addr:street":"9Th St Suite B5",
    "iso:country":"US",
    "sg:address":"555 9th St Suite B5",
    "sg:city":"San Francisco",
    "sg:classifiers":[
        {
            "category":"Coffee & Tea",
            "type":"Food & Drink"
        }
    ],
    "sg:postcode":"94103",
    "sg:province":"CA",
    "sg:website":"www.peets.com",
    "wof:name":"Peet's Coffee & Tea",
    "wof:placetype":"venue"
},
  "geometry": {"coordinates":[-122.40772200000001,37.770639],"type":"Point"}
}