{
  "type": "Feature",
  "properties": {
    "addr:full":"2259 Logan Ave San Diego CA 92113",
    "addr:housenumber":"2259",
    "addr:postcode":"92113",
    "addr:street":"Logan Ave",
    "iso:country":"US",
    "sg:address":"2259 Logan Ave",
    "sg:city":"San Diego",
    "sg:classifiers":[
        {
            "category":"Food & Beverages",
            "subcategory":"Groceries & Convenience Stores",
            "type":"Retail Goods"
        }
    ],
    "sg:phone":"+1 619 233 4884",
    "sg:postcode":"92113",
    "sg:province":"CA",
    "sg:tags":[
        "grocer"
    ],
    "wof:name":"Lucky's Market",
    "wof:placetype":"venue"
},
  "geometry": {"coordinates":[-117.138288,32.697227],"type":"Point"}
}