{
  "type": "Feature",
  "properties": {
    "addr:full":"1425 Frazee Rd San Diego CA 92108",
    "addr:housenumber":"1425",
    "addr:postcode":"92108",
    "addr:street":"Frazee Rd",
    "iso:country":"US",
    "sg:address":"1425 Frazee Rd",
    "sg:city":"San Diego",
    "sg:classifiers":[
        {
            "category":"Personal",
            "subcategory":"Beauty Salon",
            "type":"Services"
        }
    ],
    "sg:phone":"+1 619 962 4306",
    "sg:postcode":"92108",
    "sg:province":"CA",
    "wof:name":"Adriana Skin Care",
    "wof:placetype":"venue"
},
  "geometry": {"coordinates":[-117.15816100000001,32.773284],"type":"Point"}
}