{
  "type": "Feature",
  "properties": {
    "addr:full":"4842 E Kings Canyon Rd Fresno CA 93727",
    "addr:housenumber":"4842",
    "addr:postcode":"93727",
    "addr:street":"E Kings Canyon Rd",
    "iso:country":"US",
    "sg:address":"4842 E Kings Canyon Rd",
    "sg:city":"Fresno",
    "sg:classifiers":[
        {
            "category":"Shopping",
            "subcategory":"Clothing, Apparel, & Fashions",
            "type":"Retail Goods"
        }
    ],
    "sg:phone":"+1 559 252 1010",
    "sg:postcode":"93727",
    "sg:province":"CA",
    "wof:name":"Divas",
    "wof:placetype":"venue"
},
  "geometry": {"coordinates":[-119.736037,36.735846],"type":"Point"}
}