{
  "type": "Feature",
  "properties": {
    "iso:country":"US",
    "sg:address":"7210 Melrose Avenue",
    "sg:city":"Los Angeles",
    "sg:classifiers":[
        {
            "category":"Personal",
            "subcategory":"Barber",
            "type":"Services"
        }
    ],
    "sg:phone":"+1 323 933 4500",
    "sg:postcode":"90046",
    "sg:province":"CA",
    "wof:name":"General Barber Shop",
    "wof:placetype":"venue"
},
  "geometry": {"coordinates":[-118.346665,34.083591],"type":"Point"}
}