{
  "type": "Feature",
  "properties": {
    "iso:country":"US",
    "sg:address":"513 Valencia St Ste 6",
    "sg:city":"San Francisco",
    "sg:classifiers":[
        {
            "category":"Personal",
            "subcategory":"Massage",
            "type":"Services"
        },
        {
            "category":"Health Services",
            "subcategory":"Health Practitioner",
            "type":"Services"
        }
    ],
    "sg:phone":"+1 415 518 3503",
    "sg:postcode":"94110",
    "sg:province":"CA",
    "sg:tags":[
        "acupuncture"
    ],
    "sg:website":"www.citypulseacupuncture.com",
    "wof:name":"City Pulse Acupuncture",
    "wof:placetype":"venue"
},
  "geometry": {"coordinates":[-122.421761,37.764621],"type":"Point"}
}