{
  "type": "Feature",
  "properties": {
    "addr:full":"4266 Walnut Ave Chino CA 91710",
    "addr:housenumber":"4266",
    "addr:postcode":"91710",
    "addr:street":"Walnut Ave",
    "iso:country":"US",
    "sg:address":"4266 Walnut Ave",
    "sg:city":"Chino",
    "sg:classifiers":[
        {
            "category":"Social Services",
            "subcategory":"Child Care",
            "type":"Services"
        },
        {
            "category":"Education",
            "subcategory":"Preschool",
            "type":"Public Place"
        }
    ],
    "sg:phone":"+1 909 627 7428",
    "sg:postcode":"91710",
    "sg:province":"CA",
    "sg:tags":[
        "kindergarten",
        "nursery",
        "day"
    ],
    "sg:website":"http://www.kanyonkids.com",
    "wof:name":"Kanyon Kids",
    "wof:placetype":"venue"
},
  "geometry": {"coordinates":[-117.71178999999999,34.026138],"type":"Point"}
}