{
  "type": "Feature",
  "properties": {
    "iso:country":"US",
    "sg:address":"1578 N Batavia St",
    "sg:city":"Orange",
    "sg:classifiers":[
        {
            "category":"Building & Trades",
            "subcategory":"Pest Control",
            "type":"Services"
        }
    ],
    "sg:phone":"+1 714 638 7844",
    "sg:postcode":"92867",
    "sg:province":"CA",
    "sg:website":"www.terminix.com",
    "wof:name":"Termite & Pest Constrol",
    "wof:placetype":"venue"
},
  "geometry": {"coordinates":[-117.862379,33.809188],"type":"Point"}
}