{
  "type": "Feature",
  "properties": {
    "addr:full":"419 N Oak St Inglewood CA 90302",
    "addr:housenumber":"419",
    "addr:postcode":"90302",
    "addr:street":"N Oak St",
    "iso:country":"US",
    "sg:address":"419 N Oak St",
    "sg:city":"Inglewood",
    "sg:classifiers":[
        {
            "category":"Freight",
            "type":"Transportation"
        }
    ],
    "sg:phone":"+1 310 419 8833",
    "sg:postcode":"90302",
    "sg:province":"CA",
    "sg:tags":[
        "forwarder"
    ],
    "wof:name":"Ao Freight Corporation",
    "wof:placetype":"venue"
},
  "geometry": {"coordinates":[-118.365728,33.967997],"type":"Point"}
}