{
  "type": "Feature",
  "properties": {
    "addr:full":"3600 W Pomona Blvd Pomona CA 91768",
    "addr:housenumber":"3600",
    "addr:postcode":"91768",
    "addr:street":"W Pomona Blvd",
    "iso:country":"US",
    "sg:address":"3600 W Pomona Blvd",
    "sg:city":"Pomona",
    "sg:classifiers":[
        {
            "category":"Building & Trades",
            "subcategory":"Construction",
            "type":"Services"
        }
    ],
    "sg:phone":"+1 909 444 9105",
    "sg:postcode":"91768",
    "sg:province":"CA",
    "sg:tags":[
        "general",
        "contractor"
    ],
    "wof:name":"Yeager Skanska",
    "wof:placetype":"venue"
},
  "geometry": {"coordinates":[-117.815534,34.043882],"type":"Point"}
}