{
  "type": "Feature",
  "properties": {
    "iso:country":"US",
    "sg:address":"5454 Etiwanda Ave",
    "sg:city":"Mira Loma",
    "sg:classifiers":[
        {
            "category":"Food & Beverages",
            "subcategory":"Liquor & Beverages",
            "type":"Retail Goods"
        }
    ],
    "sg:phone":"+1 951 685 2244",
    "sg:postcode":"91752",
    "sg:province":"CA",
    "wof:name":"Sky Country Liquor",
    "wof:placetype":"venue"
},
  "geometry": {"coordinates":[-117.523272,33.988203],"type":"Point"}
}