{
  "type": "Feature",
  "properties": {
    "iso:country":"US",
    "sg:address":"201 S McClure Rd",
    "sg:city":"Modesto",
    "sg:classifiers":[
        {
            "category":"Manufacturing",
            "subcategory":"Motor Vehicles & Parts",
            "type":"Manufacturing & Wholesale Goods"
        }
    ],
    "sg:phone":"+1 209 527 6000",
    "sg:postcode":"95357",
    "sg:province":"CA",
    "sg:tags":[
        "mfg",
        "trimming"
    ],
    "wof:name":"Trim Masters Inc",
    "wof:placetype":"venue"
},
  "geometry": {"coordinates":[-120.929978,37.636112],"type":"Point"}
}