{
  "type": "Feature",
  "properties": {
    "iso:country":"US",
    "sg:address":"2565 E Perrin Ave",
    "sg:city":"Fresno",
    "sg:classifiers":[
        {
            "category":"Shopping",
            "subcategory":"Stationery & Office Supplies",
            "type":"Retail Goods"
        }
    ],
    "sg:phone":"+1 559 297 7154",
    "sg:postcode":"93720",
    "sg:province":"CA",
    "sg:tags":[
        "register",
        "cash"
    ],
    "wof:name":"Sncr California Inc.",
    "wof:placetype":"venue"
},
  "geometry": {"coordinates":[-119.739163,36.873916],"type":"Point"}
}