{
  "type": "Feature",
  "properties": {
    "addr:full":"122 E Fir St Fort Bragg CA 95437",
    "addr:housenumber":"122",
    "addr:postcode":"95437",
    "addr:street":"E Fir St",
    "iso:country":"US",
    "sg:address":"122 E Fir St",
    "sg:city":"Fort Bragg",
    "sg:classifiers":[
        {
            "category":"Retail",
            "subcategory":"Animal Services",
            "type":"Services"
        }
    ],
    "sg:phone":"+1 707 961 0917",
    "sg:postcode":"95437",
    "sg:province":"CA",
    "sg:tags":[
        "pet",
        "grooming",
        "washing"
    ],
    "wof:name":"Canine Designs",
    "wof:placetype":"venue"
},
  "geometry": {"coordinates":[-123.805599,39.447953],"type":"Point"}
}