{
  "type": "Feature",
  "properties": {
    "addr:full":"360 Langton Street San Francisco CA 94103",
    "addr:housenumber":"360",
    "addr:postcode":"94103",
    "addr:street":"Langton Street",
    "iso:country":"US",
    "sg:address":"360 Langton Street",
    "sg:city":"San Francisco",
    "sg:classifiers":[
        {
            "category":"Real Estate",
            "subcategory":"Architect",
            "type":"Services"
        }
    ],
    "sg:phone":"+1 415 863 4134",
    "sg:postcode":"94103",
    "sg:province":"CA",
    "sg:website":"www.andrewmannarchitect.com",
    "wof:name":"Andrew H. Mann, Architect",
    "wof:placetype":"venue"
},
  "geometry": {"coordinates":[-122.416,37.773701],"type":"Point"}
}