{
  "type": "Feature",
  "properties": {
    "iso:country":"US",
    "sg:address":"555 Abrego St",
    "sg:city":"Monterey",
    "sg:classifiers":[
        {
            "category":"Banks & Credit Unions",
            "subcategory":"Bank",
            "type":"Services"
        }
    ],
    "sg:phone":"+1 831 649 3694",
    "sg:postcode":"93940",
    "sg:province":"CA",
    "sg:tags":[
        "loan",
        "real estate"
    ],
    "wof:name":"Charles B Hawley",
    "wof:placetype":"venue"
},
  "geometry": {"coordinates":[-121.892283,36.596893],"type":"Point"}
}