{
  "type": "Feature",
  "properties": {
    "iso:country":"US",
    "sg:address":"4244 Christian Dr",
    "sg:city":"San Jose",
    "sg:classifiers":[
        {
            "category":"Professional",
            "subcategory":"Computer Services",
            "type":"Services"
        }
    ],
    "sg:phone":"+1 408 224 6514",
    "sg:postcode":"95135",
    "sg:province":"CA",
    "sg:tags":[
        "consultant",
        "designer"
    ],
    "sg:website":"www.digitalfiesta.com",
    "wof:name":"B & B Systems Inc",
    "wof:placetype":"venue"
},
  "geometry": {"coordinates":[-121.77128999999999,37.3055],"type":"Point"}
}