{
  "type": "Feature",
  "properties": {
    "iso:country":"US",
    "sg:address":"514 Foothill Blvd",
    "sg:city":"La Canada Fltrdg",
    "sg:classifiers":[
        {
            "category":"Building & Trades",
            "subcategory":"Construction",
            "type":"Services"
        }
    ],
    "sg:phone":"+1 818 790 9882",
    "sg:postcode":"91011",
    "sg:province":"CA",
    "sg:tags":[
        "designer",
        "dealer",
        "pool",
        "swimming"
    ],
    "sg:website":"www.lacanadapoolandpatio.com",
    "wof:name":"LA Canada Pool & Patio",
    "wof:placetype":"venue"
},
  "geometry": {"coordinates":[-118.189662,34.199448],"type":"Point"}
}