{
  "type": "Feature",
  "properties": {
    "iso:country":"US",
    "sg:address":"40 Page St",
    "sg:city":"San Francisco",
    "sg:classifiers":[
        {
            "category":"Sports & Exercise",
            "subcategory":"Gym",
            "type":"Entertainment"
        }
    ],
    "sg:phone":"+1 415 248 9348",
    "sg:postcode":"94102",
    "sg:province":"CA",
    "sg:tags":[
        "pilate"
    ],
    "wof:name":"Pilates On Page",
    "wof:placetype":"venue"
},
  "geometry": {"coordinates":[-122.42128700000001,37.774285],"type":"Point"}
}