{
  "type": "Feature",
  "properties": {
    "addr:full":"1205 Devlin Dr Vallejo CA 94591",
    "addr:housenumber":"1205",
    "addr:postcode":"94591",
    "addr:street":"Devlin Dr",
    "iso:country":"US",
    "sg:address":"1205 Devlin Dr",
    "sg:city":"Vallejo",
    "sg:classifiers":[
        {
            "category":"Social Services",
            "subcategory":"Child Care",
            "type":"Services"
        }
    ],
    "sg:phone":"+1 707 647 3976",
    "sg:postcode":"94591",
    "sg:province":"CA",
    "wof:name":"Village Childcare",
    "wof:placetype":"venue"
},
  "geometry": {"coordinates":[-122.201206,38.09329],"type":"Point"}
}