{
  "type": "Feature",
  "properties": {
    "iso:country":"US",
    "sg:address":"2450 Samaritan Dr",
    "sg:city":"San Jose",
    "sg:classifiers":[
        {
            "category":"Health Services",
            "subcategory":"Doctor",
            "type":"Services"
        }
    ],
    "sg:phone":"+1 408 358 1855",
    "sg:postcode":"95124",
    "sg:province":"CA",
    "sg:tags":[
        "physician",
        "surgeon"
    ],
    "wof:name":"Surgery Associates",
    "wof:placetype":"venue"
},
  "geometry": {"coordinates":[-121.946484,37.251027],"type":"Point"}
}