{
  "type": "Feature",
  "properties": {
    "iso:country":"US",
    "sg:address":"9680 W Chapman Ave",
    "sg:city":"Garden Grove",
    "sg:classifiers":[
        {
            "category":"Personal",
            "subcategory":"Beauty Salon",
            "type":"Services"
        }
    ],
    "sg:phone":"+1 714 534 2696",
    "sg:postcode":"92841",
    "sg:province":"CA",
    "sg:tags":[
        "manicuring"
    ],
    "wof:name":"J & J Nails",
    "wof:placetype":"venue"
},
  "geometry": {"coordinates":[-117.959167,33.78851],"type":"Point"}
}