{
  "type": "Feature",
  "properties": {
    "addr:full":"420 3rd St Oakland CA 94607",
    "addr:housenumber":"420",
    "addr:postcode":"94607",
    "addr:street":"3Rd St",
    "iso:country":"US",
    "sg:address":"420 3rd St",
    "sg:city":"Oakland",
    "sg:phone":"+1 510 764 9723",
    "sg:postcode":"94607",
    "sg:province":"CA",
    "wof:name":"Prime Mgmt. Inc.",
    "wof:placetype":"venue"
},
  "geometry": {"coordinates":[-122.275211,37.796464],"type":"Point"}
}