{
  "type": "Feature",
  "properties": {
    "iso:country":"US",
    "sg:address":"5630 E Huntington Ave",
    "sg:city":"Fresno",
    "sg:classifiers":[
        {
            "category":"Real Estate",
            "subcategory":"Real Estate Operator",
            "type":"Services"
        }
    ],
    "sg:phone":"+1 559 255 0410",
    "sg:postcode":"93727",
    "sg:province":"CA",
    "sg:tags":[
        "apartment"
    ],
    "wof:name":"Huntington Court Apartments",
    "wof:placetype":"venue"
},
  "geometry": {"coordinates":[-119.698686,36.739831],"type":"Point"}
}