{
  "type": "Feature",
  "properties": {
    "addr:full":"14500 Big Basin Way Saratoga CA 95070",
    "addr:housenumber":"14500",
    "addr:postcode":"95070",
    "addr:street":"Big Basin Way",
    "iso:country":"US",
    "sg:address":"14500 Big Basin Way",
    "sg:city":"Saratoga",
    "sg:classifiers":[
        {
            "category":"Shopping",
            "subcategory":"Clothing, Apparel, & Fashions",
            "type":"Retail Goods"
        }
    ],
    "sg:phone":"+1 408 741 1666",
    "sg:postcode":"95070",
    "sg:province":"CA",
    "wof:name":"Exclusively Yours Boutique",
    "wof:placetype":"venue"
},
  "geometry": {"coordinates":[-122.03467999999999,37.25671],"type":"Point"}
}