{
  "type": "Feature",
  "properties": {
    "addr:full":"150 S Wood Ave Oakdale CA 95361",
    "addr:housenumber":"150",
    "addr:postcode":"95361",
    "addr:street":"S Wood Ave",
    "iso:country":"US",
    "sg:address":"150 S Wood Ave",
    "sg:city":"Oakdale",
    "sg:classifiers":[
        {
            "category":"Real Estate",
            "subcategory":"Real Estate Operator",
            "type":"Services"
        }
    ],
    "sg:phone":"+1 209 847 8548",
    "sg:postcode":"95361",
    "sg:province":"CA",
    "sg:tags":[
        "apartment"
    ],
    "wof:name":"Harvest Apartments",
    "wof:placetype":"venue"
},
  "geometry": {"coordinates":[-120.85965,37.760685],"type":"Point"}
}