{
  "type": "Feature",
  "properties": {
    "addr:full":"8232 Sunland Blvd Sun Valley CA 91352",
    "addr:housenumber":"8232",
    "addr:postcode":"91352",
    "addr:street":"Sunland Blvd",
    "iso:country":"US",
    "sg:address":"8232 Sunland Blvd",
    "sg:city":"Sun Valley",
    "sg:classifiers":[
        {
            "category":"Shopping",
            "subcategory":"Tobacco",
            "type":"Retail Goods"
        }
    ],
    "sg:phone":"+1 818 252 6565",
    "sg:postcode":"91352",
    "sg:province":"CA",
    "sg:tags":[
        "shop"
    ],
    "wof:name":"Valley Tobacco Wholessale",
    "wof:placetype":"venue"
},
  "geometry": {"coordinates":[-118.367909,34.220195],"type":"Point"}
}