{
  "type": "Feature",
  "properties": {
    "iso:country":"US",
    "sg:address":"23490 N Jack Tone Rd",
    "sg:city":"Acampo",
    "sg:classifiers":[
        {
            "category":"Farming",
            "subcategory":"Dairy Farm",
            "type":"Manufacturing & Wholesale Goods"
        }
    ],
    "sg:phone":"+1 209 334 9688",
    "sg:postcode":"95220",
    "sg:province":"CA",
    "wof:name":"Silva Tony & Sons Dairy Inc",
    "wof:placetype":"venue"
},
  "geometry": {"coordinates":[-121.151972,38.197019],"type":"Point"}
}