{
  "type": "Feature",
  "properties": {
    "iso:country":"US",
    "sg:address":"17176 Norlene Way",
    "sg:city":"Grass Valley",
    "sg:classifiers":[
        {
            "category":"Professional",
            "subcategory":"Lawyer & Legal Services",
            "type":"Services"
        }
    ],
    "sg:phone":"+1 530 272 8478",
    "sg:postcode":"95949",
    "sg:province":"CA",
    "sg:tags":[
        "attorney"
    ],
    "wof:name":"James Chandler",
    "wof:placetype":"venue"
},
  "geometry": {"coordinates":[-121.056223,39.127128],"type":"Point"}
}