{
  "type": "Feature",
  "properties": {
    "addr:full":"256 E Stowell St Upland CA 91786",
    "addr:housenumber":"256",
    "addr:postcode":"91786",
    "addr:street":"E Stowell St",
    "iso:country":"US",
    "sg:address":"256 E Stowell St",
    "sg:city":"Upland",
    "sg:classifiers":[
        {
            "category":"Autos & Motor Vehicles",
            "subcategory":"Auto Supplies",
            "type":"Retail Goods"
        }
    ],
    "sg:phone":"+1 909 931 3232",
    "sg:postcode":"91786",
    "sg:province":"CA",
    "sg:tags":[
        "automobile",
        "parts"
    ],
    "wof:name":"Baker's Automotive Outlet",
    "wof:placetype":"venue"
},
  "geometry": {"coordinates":[-117.647958,34.093927],"type":"Point"}
}