{
  "type": "Feature",
  "properties": {
    "iso:country":"US",
    "sg:address":"585 Cannery Row",
    "sg:city":"Monterey",
    "sg:classifiers":[
        {
            "category":"Real Estate",
            "subcategory":"Developer",
            "type":"Services"
        }
    ],
    "sg:phone":"+1 831 372 2972",
    "sg:postcode":"93940",
    "sg:province":"CA",
    "wof:name":"Shake Enterprises",
    "wof:placetype":"venue"
},
  "geometry": {"coordinates":[-121.898877,36.614053],"type":"Point"}
}