{
  "type": "Feature",
  "properties": {
    "addr:full":"1117 Grantland Ct Modesto CA 95350",
    "addr:housenumber":"1117",
    "addr:postcode":"ca 95350",
    "addr:street":"Grantland Ct",
    "iso:country":"US",
    "sg:address":"1117 Grantland Ct",
    "sg:city":"Modesto",
    "sg:classifiers":[
        {
            "category":"Building & Trades",
            "subcategory":"Construction",
            "type":"Services"
        }
    ],
    "sg:phone":"+1 209 604 4122",
    "sg:postcode":"95350",
    "sg:province":"CA",
    "sg:tags":[
        "contractor"
    ],
    "wof:name":"Al & Sons General Contracting",
    "wof:placetype":"venue"
},
  "geometry": {"coordinates":[-120.97719499999999,37.650608],"type":"Point"}
}