{
  "type": "Feature",
  "properties": {
    "addr:full":"22900 River Rd Geyserville CA 95441",
    "addr:housenumber":"22900",
    "addr:postcode":"95441",
    "addr:street":"River Rd",
    "iso:country":"US",
    "sg:address":"22900 River Rd",
    "sg:city":"Geyserville",
    "sg:classifiers":[
        {
            "category":"Retail",
            "subcategory":"Animal Services",
            "type":"Services"
        }
    ],
    "sg:phone":"+1 707 857 3513",
    "sg:postcode":"95441",
    "sg:province":"CA",
    "sg:tags":[
        "horse",
        "training"
    ],
    "wof:name":"Ed Vanoni Ranches",
    "wof:placetype":"venue"
},
  "geometry": {"coordinates":[-122.91652000000001,38.736013],"type":"Point"}
}