{
  "type": "Feature",
  "properties": {
    "iso:country":"US",
    "sg:address":"617 E Lincoln St",
    "sg:city":"Carson",
    "sg:classifiers":[
        {
            "category":"Personal",
            "subcategory":"Beauty Salon",
            "type":"Services"
        }
    ],
    "sg:phone":"+1 310 830 1021",
    "sg:postcode":"90745",
    "sg:province":"CA",
    "wof:name":"Georges Pool & Spa Inc",
    "wof:placetype":"venue"
},
  "geometry": {"coordinates":[-118.26375899999999,33.807433],"type":"Point"}
}