{
  "type": "Feature",
  "properties": {
    "iso:country":"US",
    "sg:address":"9339 Main St",
    "sg:city":"Plymouth",
    "sg:classifiers":[
        {
            "category":"Personal",
            "subcategory":"Barber",
            "type":"Services"
        }
    ],
    "sg:phone":"+1 209 245 3674",
    "sg:postcode":"95669",
    "sg:province":"CA",
    "wof:name":"Main Street Barbershop",
    "wof:placetype":"venue"
},
  "geometry": {"coordinates":[-120.849273,38.480882],"type":"Point"}
}