{
  "type": "Feature",
  "properties": {
    "iso:country":"US",
    "sg:address":"1740 W Katella Ave Ste M",
    "sg:city":"Orange",
    "sg:classifiers":[
        {
            "category":"Autos & Motor Vehicles",
            "subcategory":"Auto Supplies",
            "type":"Retail Goods"
        }
    ],
    "sg:phone":"+1 714 282 1147",
    "sg:postcode":"92867",
    "sg:province":"CA",
    "sg:tags":[
        "tire"
    ],
    "wof:name":"Toyo Tires Pre Audit",
    "wof:placetype":"venue"
},
  "geometry": {"coordinates":[-117.871284,33.806127],"type":"Point"}
}