{
  "type": "Feature",
  "properties": {
    "iso:country":"US",
    "sg:address":"2495 Natomas Park Drive",
    "sg:city":"Sacramento",
    "sg:classifiers":[
        {
            "category":"Real Estate",
            "subcategory":"Architect",
            "type":"Services"
        }
    ],
    "sg:phone":"+1 916 568 3500",
    "sg:postcode":"95833",
    "sg:province":"CA",
    "wof:name":"Nadel Architects",
    "wof:placetype":"venue"
},
  "geometry": {"coordinates":[-121.506547,38.610357],"type":"Point"}
}