{
  "type": "Feature",
  "properties": {
    "addr:full":"12103 Celome Ln San Diego CA 92129",
    "addr:housenumber":"12103",
    "addr:postcode":"92129",
    "addr:street":"Celome Ln",
    "iso:country":"US",
    "sg:address":"12103 Celome Ln",
    "sg:city":"San Diego",
    "sg:classifiers":[
        {
            "category":"Manufacturing",
            "subcategory":"Retail Goods",
            "type":"Manufacturing & Wholesale Goods"
        }
    ],
    "sg:phone":"+1 858 538 3019",
    "sg:postcode":"92129",
    "sg:province":"CA",
    "sg:tags":[
        "lead",
        "mfg"
    ],
    "wof:name":"Tree Arts",
    "wof:placetype":"venue"
},
  "geometry": {"coordinates":[-117.16654800000001,32.938992],"type":"Point"}
}