{
  "type": "Feature",
  "properties": {
    "iso:country":"US",
    "sg:address":"2233 Santa Clara Ave Ste 7",
    "sg:city":"Alameda",
    "sg:classifiers":[
        {
            "category":"Professional",
            "subcategory":"Lawyer & Legal Services",
            "type":"Services"
        }
    ],
    "sg:phone":"+1 510 521 9500",
    "sg:postcode":"94501",
    "sg:province":"CA",
    "sg:tags":[
        "divorce",
        "law",
        "family"
    ],
    "sg:website":"www.gfalzonelaw.com",
    "wof:name":"Law Offices Of Gerard A. Falzone",
    "wof:placetype":"venue"
},
  "geometry": {"coordinates":[-122.24473,37.767029],"type":"Point"}
}