{
  "type": "Feature",
  "properties": {
    "iso:country":"US",
    "sg:address":"582 Marlin Ct",
    "sg:city":"Redwood City",
    "sg:classifiers":[
        {
            "category":"Manufacturing",
            "subcategory":"Toys & Sporting Goods",
            "type":"Manufacturing & Wholesale Goods"
        }
    ],
    "sg:phone":"+1 650 302 3426",
    "sg:postcode":"94065",
    "sg:province":"CA",
    "sg:tags":[
        "production",
        "interactive",
        "entertainment"
    ],
    "wof:name":"Slam Dunk Productions LLC",
    "wof:placetype":"venue"
},
  "geometry": {"coordinates":[-122.25164700000001,37.533608],"type":"Point"}
}