{
  "type": "Feature",
  "properties": {
    "addr:full":"22316 Main St Hayward CA 94541",
    "addr:housenumber":"22316",
    "addr:postcode":"94541",
    "addr:street":"Main St",
    "iso:country":"US",
    "sg:address":"22316 Main St",
    "sg:city":"Hayward",
    "sg:classifiers":[
        {
            "category":"Health Services",
            "subcategory":"Health Practitioner",
            "type":"Services"
        }
    ],
    "sg:phone":"+1 510 886 3886",
    "sg:postcode":"94541",
    "sg:province":"CA",
    "sg:tags":[
        "acupuncture"
    ],
    "wof:name":"Eastbay Acupuncture & Acprssr",
    "wof:placetype":"venue"
},
  "geometry": {"coordinates":[-122.084806,37.675278],"type":"Point"}
}