{
  "type": "Feature",
  "properties": {
    "addr:full":"881 Production Place Newport Beach CA 92663",
    "addr:housenumber":"881",
    "addr:postcode":"92663",
    "addr:street":"Production Place",
    "iso:country":"US",
    "sg:address":"881 Production Place",
    "sg:city":"Newport Beach",
    "sg:classifiers":[
        {
            "category":"Building & Trades",
            "subcategory":"Construction",
            "type":"Services"
        }
    ],
    "sg:phone":"+1 949 650 0310",
    "sg:postcode":"92663",
    "sg:province":"CA",
    "sg:tags":[
        "interior",
        "design"
    ],
    "wof:name":"Pompanette",
    "wof:placetype":"venue"
},
  "geometry": {"coordinates":[-117.933907,33.631017],"type":"Point"}
}