{
  "type": "Feature",
  "properties": {
    "iso:country":"US",
    "sg:address":"14901 Ventura Blvd",
    "sg:city":"Sherman Oaks",
    "sg:classifiers":[
        {
            "category":"Food & Beverages",
            "subcategory":"Liquor & Beverages",
            "type":"Retail Goods"
        }
    ],
    "sg:phone":"+1 818 981 1566",
    "sg:postcode":"91403",
    "sg:province":"CA",
    "sg:tags":[
        "wine"
    ],
    "wof:name":"Valley Beverage",
    "wof:placetype":"venue"
},
  "geometry": {"coordinates":[-118.459602,34.152722],"type":"Point"}
}