{
  "type": "Feature",
  "properties": {
    "iso:country":"US",
    "sg:address":"7460 Watt Ave",
    "sg:city":"North Highlands",
    "sg:classifiers":[
        {
            "category":"Retail",
            "subcategory":"Auto Repair",
            "type":"Services"
        }
    ],
    "sg:phone":"+1 916 332 9900",
    "sg:postcode":"95660",
    "sg:province":"CA",
    "sg:tags":[
        "automobile",
        "smog"
    ],
    "wof:name":"Smog Depot",
    "wof:placetype":"venue"
},
  "geometry": {"coordinates":[-121.38273599999999,38.701482],"type":"Point"}
}