{
  "type": "Feature",
  "properties": {
    "iso:country":"US",
    "sg:address":"18355 Colima Rd",
    "sg:city":"Rowland Heights",
    "sg:classifiers":[
        {
            "category":"Manufacturing",
            "subcategory":"Textiles",
            "type":"Manufacturing & Wholesale Goods"
        },
        {
            "category":"Manufacturing",
            "subcategory":"Apparel",
            "type":"Manufacturing & Wholesale Goods"
        }
    ],
    "sg:phone":"+1 626 965 7711",
    "sg:postcode":"91748",
    "sg:province":"CA",
    "sg:tags":[
        "underwear",
        "mfg"
    ],
    "wof:name":"Body Guard U S A",
    "wof:placetype":"venue"
},
  "geometry": {"coordinates":[-117.904832,33.988453],"type":"Point"}
}