{
  "type": "Feature",
  "properties": {
    "addr:full":"850 Montgomery St San Francisco CA 94133",
    "addr:housenumber":"850",
    "addr:postcode":"94133",
    "addr:street":"Montgomery St",
    "iso:country":"US",
    "sg:address":"850 Montgomery St",
    "sg:city":"San Francisco",
    "sg:classifiers":[
        {
            "category":"Banks & Credit Unions",
            "subcategory":"Investment Brokerage",
            "type":"Services"
        }
    ],
    "sg:phone":"+1 415 982 1985",
    "sg:postcode":"94133",
    "sg:province":"CA",
    "sg:tags":[
        "security"
    ],
    "wof:name":"Fire Online Training",
    "wof:placetype":"venue"
},
  "geometry": {"coordinates":[-122.403549,37.796671],"type":"Point"}
}