{
  "type": "Feature",
  "properties": {
    "addr:full":"9000 Freeman Ct Gilroy CA 95020",
    "addr:housenumber":"9000",
    "addr:postcode":"95020",
    "addr:street":"Freeman Ct",
    "iso:country":"US",
    "sg:address":"9000 Freeman Ct",
    "sg:city":"Gilroy",
    "sg:classifiers":[
        {
            "category":"Shopping",
            "subcategory":"Clothing, Apparel, & Fashions",
            "type":"Retail Goods"
        }
    ],
    "sg:phone":"+1 408 842 5941",
    "sg:postcode":"95020",
    "sg:province":"CA",
    "wof:name":"Marena's Charter & Tours",
    "wof:placetype":"venue"
},
  "geometry": {"coordinates":[-121.5802,37.02814],"type":"Point"}
}