{
  "type": "Feature",
  "properties": {
    "addr:full":"354 Bel Marin Keys Blvd Novato CA 94949",
    "addr:housenumber":"354",
    "addr:postcode":"94949",
    "addr:street":"Bel Marin Keys Blvd",
    "iso:country":"US",
    "sg:address":"354 Bel Marin Keys Blvd",
    "sg:city":"Novato",
    "sg:classifiers":[
        {
            "category":"Manufacturing",
            "subcategory":"Jewelry",
            "type":"Manufacturing & Wholesale Goods"
        }
    ],
    "sg:phone":"+1 415 382 6789",
    "sg:postcode":"94949",
    "sg:province":"CA",
    "wof:name":"Tabra Designs",
    "wof:placetype":"venue"
},
  "geometry": {"coordinates":[-122.537842,38.074908],"type":"Point"}
}