{
  "type": "Feature",
  "properties": {
    "iso:country":"US",
    "sg:address":"1 Montgomery St",
    "sg:city":"San Francisco",
    "sg:classifiers":[
        {
            "category":"Banks & Credit Unions",
            "subcategory":"Investment Brokerage",
            "type":"Services"
        }
    ],
    "sg:phone":"+1 415 248 1021",
    "sg:postcode":"94104",
    "sg:province":"CA",
    "sg:tags":[
        "management"
    ],
    "wof:name":"Basix Capital",
    "wof:placetype":"venue"
},
  "geometry": {"coordinates":[-122.40218900000001,37.790039],"type":"Point"}
}