{
  "type": "Feature",
  "properties": {
    "addr:full":"7059 Reseda Blvd Reseda CA 91335",
    "addr:housenumber":"7059",
    "addr:postcode":"91335",
    "addr:street":"Reseda Blvd",
    "iso:country":"US",
    "sg:address":"7059 Reseda Blvd",
    "sg:city":"Reseda",
    "sg:classifiers":[
        {
            "category":"Home & Garden",
            "subcategory":"Furniture",
            "type":"Retail Goods"
        }
    ],
    "sg:phone":"+1 818 345 4475",
    "sg:postcode":"91335",
    "sg:province":"CA",
    "sg:tags":[
        "mattress"
    ],
    "wof:name":"Marshall's Sleep Ctr",
    "wof:placetype":"venue"
},
  "geometry": {"coordinates":[-118.536118,34.19833],"type":"Point"}
}