{
  "type": "Feature",
  "properties": {
    "addr:full":"411 E Huntington Dr Arcadia CA 91006",
    "addr:housenumber":"411",
    "addr:postcode":"91006",
    "addr:street":"E Huntington Dr",
    "iso:country":"US",
    "sg:address":"411 E Huntington Dr",
    "sg:city":"Arcadia",
    "sg:classifiers":[
        {
            "category":"Professional",
            "subcategory":"Accounting & Tax Preparation",
            "type":"Services"
        }
    ],
    "sg:phone":"+1 626 446 5700",
    "sg:postcode":"91006",
    "sg:province":"CA",
    "sg:tags":[
        "billing"
    ],
    "wof:name":"Medical Electronic Data Proc",
    "wof:placetype":"venue"
},
  "geometry": {"coordinates":[-118.02179099999999,34.140243],"type":"Point"}
}