{
  "type": "Feature",
  "properties": {
    "addr:full":"40 Union Way Vacaville CA 95687",
    "addr:housenumber":"40",
    "addr:postcode":"95687",
    "addr:street":"Union Way",
    "iso:country":"US",
    "sg:address":"40 Union Way",
    "sg:city":"Vacaville",
    "sg:classifiers":[
        {
            "category":"Building & Trades",
            "subcategory":"Plumbing",
            "type":"Services"
        }
    ],
    "sg:phone":"+1 707 452 8887",
    "sg:postcode":"95687",
    "sg:province":"CA",
    "sg:tags":[
        "conditioning",
        "contractor",
        "system",
        "air"
    ],
    "wof:name":"Energy Source Heating & Air Co",
    "wof:placetype":"venue"
},
  "geometry": {"coordinates":[-121.934028,38.352239],"type":"Point"}
}