{
  "type": "Feature",
  "properties": {
    "iso:country":"US",
    "sg:address":"6943 Wilson Way",
    "sg:city":"El Cerrito",
    "sg:classifiers":[
        {
            "category":"Building & Trades",
            "subcategory":"Cleaning & Sanitation",
            "type":"Services"
        }
    ],
    "sg:phone":"+1 510 575 5225",
    "sg:postcode":"94530",
    "sg:province":"CA",
    "sg:tags":[
        "home"
    ],
    "wof:name":"A. C's Cleaning Services",
    "wof:placetype":"venue"
},
  "geometry": {"coordinates":[-122.30983999999999,37.928805],"type":"Point"}
}