{
  "type": "Feature",
  "properties": {
    "iso:country":"US",
    "sg:address":"1123 W 223rd St",
    "sg:city":"Torrance",
    "sg:classifiers":[
        {
            "category":"Professional",
            "subcategory":"Management & Consulting",
            "type":"Services"
        }
    ],
    "sg:phone":"+1 310 781 1780",
    "sg:postcode":"90502",
    "sg:province":"CA",
    "sg:tags":[
        "construction"
    ],
    "wof:name":"Edessa Construction",
    "wof:placetype":"venue"
},
  "geometry": {"coordinates":[-118.297369,33.824584],"type":"Point"}
}