{
  "type": "Feature",
  "properties": {
    "addr:full":"2706 Park Blvd Oakland CA 94606",
    "addr:housenumber":"2706",
    "addr:postcode":"94606",
    "addr:street":"Park Blvd",
    "iso:country":"US",
    "sg:address":"2706 Park Blvd",
    "sg:city":"Oakland",
    "sg:classifiers":[
        {
            "category":"Personal",
            "type":"Services"
        }
    ],
    "sg:phone":"+1 510 645 1101",
    "sg:postcode":"94606",
    "sg:province":"CA",
    "sg:tags":[
        "program",
        "physical",
        "exercise",
        "fitness"
    ],
    "wof:name":"Curves Trestle Glen",
    "wof:placetype":"venue"
},
  "geometry": {"coordinates":[-122.239864,37.802526],"type":"Point"}
}