{
  "type": "Feature",
  "properties": {
    "iso:country":"US",
    "sg:address":"512 E 3rd Ave",
    "sg:city":"San Mateo",
    "sg:classifiers":[
        {
            "category":"Wholesale",
            "subcategory":"Durable Goods & Equipment",
            "type":"Manufacturing & Wholesale Goods"
        }
    ],
    "sg:phone":"+1 650 347 5803",
    "sg:postcode":"94401",
    "sg:province":"CA",
    "wof:name":"Salamanca Enterprise Corp",
    "wof:placetype":"venue"
},
  "geometry": {"coordinates":[-122.320083,37.567006],"type":"Point"}
}