{
  "type": "Feature",
  "properties": {
    "iso:country":"US",
    "sg:address":"2660 Calhoun St",
    "sg:city":"San Diego",
    "sg:classifiers":[
        {
            "category":"Travel",
            "subcategory":"Hotels & Motels",
            "type":"Entertainment"
        },
        {
            "category":"Restaurant",
            "type":"Food & Drink"
        }
    ],
    "sg:phone":"+1 619 297 1874",
    "sg:postcode":"92110",
    "sg:province":"CA",
    "sg:website":"www.oldtowncosmopolitan.com",
    "wof:name":"Cosmopolitan Hotel and Restaurant",
    "wof:placetype":"venue"
},
  "geometry": {"coordinates":[-117.196147,32.75426],"type":"Point"}
}