{
  "type": "Feature",
  "properties": {
    "addr:full":"1120 Dewey Way Ste A Upland CA 91786",
    "addr:housenumber":"1120",
    "addr:postcode":"91786",
    "addr:street":"Dewey Way Ste A",
    "iso:country":"US",
    "sg:address":"1120 Dewey Way Ste A",
    "sg:city":"Upland",
    "sg:classifiers":[
        {
            "category":"Social Services",
            "subcategory":"Job Training",
            "type":"Services"
        },
        {
            "category":"Education",
            "subcategory":"School",
            "type":"Public Place"
        },
        {
            "category":"Sports & Exercise",
            "subcategory":"Playing Field",
            "type":"Entertainment"
        }
    ],
    "sg:phone":"+1 800 628 3253",
    "sg:postcode":"91786",
    "sg:province":"CA",
    "sg:tags":[
        "personal",
        "consultant",
        "development"
    ],
    "sg:website":"http://www.dalecarnegie.com",
    "wof:name":"Dale Carnegie Training",
    "wof:placetype":"venue"
},
  "geometry": {"coordinates":[-117.693938,34.106863],"type":"Point"}
}