{
  "type": "Feature",
  "properties": {
    "addr:full":"2000 Harbor Blvd Costa Mesa CA 92627",
    "addr:housenumber":"2000",
    "addr:postcode":"92627",
    "addr:street":"Harbor Blvd Costa",
    "iso:country":"US",
    "sg:address":"2000 Harbor Blvd",
    "sg:city":"Costa Mesa",
    "sg:classifiers":[
        {
            "category":"Personal",
            "subcategory":"Beauty Salon",
            "type":"Services"
        }
    ],
    "sg:phone":"+1 949 646 6044",
    "sg:postcode":"92627",
    "sg:province":"CA",
    "wof:name":"Jack's Hair Fashions",
    "wof:placetype":"venue"
},
  "geometry": {"coordinates":[-117.91901,33.64628],"type":"Point"}
}