{
  "type": "Feature",
  "properties": {
    "addr:full":"2324 8th St Encinitas CA 92024",
    "addr:housenumber":"2324",
    "addr:postcode":"92024",
    "addr:street":"8Th St",
    "iso:country":"US",
    "sg:address":"2324 8th St",
    "sg:city":"Encinitas",
    "sg:classifiers":[
        {
            "category":"Manufacturing",
            "subcategory":"Toys & Sporting Goods",
            "type":"Manufacturing & Wholesale Goods"
        }
    ],
    "sg:phone":"+1 760 943 1236",
    "sg:postcode":"92024",
    "sg:province":"CA",
    "sg:tags":[
        "mfg"
    ],
    "wof:name":"Bob Litzlbeck Ali or",
    "wof:placetype":"venue"
},
  "geometry": {"coordinates":[-117.23418100000001,33.045687],"type":"Point"}
}