{
  "type": "Feature",
  "properties": {
    "addr:full":"514 S Stewart St Sonora CA 95370",
    "addr:housenumber":"514",
    "addr:postcode":"95370",
    "addr:street":"S Stewart St",
    "iso:country":"US",
    "sg:address":"514 S Stewart St",
    "sg:city":"Sonora",
    "sg:classifiers":[
        {
            "category":"Social Services",
            "type":"Services"
        }
    ],
    "sg:phone":"+1 209 533 3401",
    "sg:postcode":"95370",
    "sg:province":"CA",
    "sg:tags":[
        "crisis",
        "intervention"
    ],
    "sg:website":"www.mountainwomen.org",
    "wof:name":"Mountain Women's Resource Ctr",
    "wof:placetype":"venue"
},
  "geometry": {"coordinates":[-120.38006799999999,37.978454],"type":"Point"}
}