{
  "type": "Feature",
  "properties": {
    "iso:country":"US",
    "sg:address":"4741 E Palm Canyon Dr",
    "sg:city":"Palm Springs",
    "sg:classifiers":[
        {
            "category":"Shopping",
            "subcategory":"Clothing, Apparel, & Fashions",
            "type":"Retail Goods"
        }
    ],
    "sg:phone":"+1 760 321 4900",
    "sg:postcode":"92264",
    "sg:province":"CA",
    "sg:tags":[
        "shop",
        "bridal"
    ],
    "wof:name":"Tina's Toppers",
    "wof:placetype":"venue"
},
  "geometry": {"coordinates":[-116.49610800000001,33.793517],"type":"Point"}
}