{
  "type": "Feature",
  "properties": {
    "iso:country":"US",
    "sg:address":"25 Technology Dr",
    "sg:city":"Irvine",
    "sg:classifiers":[
        {
            "category":"Manufacturing",
            "subcategory":"Electronics",
            "type":"Manufacturing & Wholesale Goods"
        }
    ],
    "sg:phone":"+1 949 450 0370",
    "sg:postcode":"92618",
    "sg:province":"CA",
    "sg:tags":[
        "component",
        "comm",
        "electronic",
        "mfg"
    ],
    "sg:website":"www.futureelectronics.com",
    "wof:name":"Future Electronics",
    "wof:placetype":"venue"
},
  "geometry": {"coordinates":[-117.737681,33.650984],"type":"Point"}
}