{
  "type": "Feature",
  "properties": {
    "addr:full":"201 W 15th St Santa Ana CA 92706",
    "addr:housenumber":"201",
    "addr:postcode":"92706",
    "addr:street":"W 15Th St",
    "iso:country":"US",
    "sg:address":"201 W 15th St",
    "sg:city":"Santa Ana",
    "sg:classifiers":[
        {
            "category":"Health Services",
            "subcategory":"Doctor",
            "type":"Services"
        }
    ],
    "sg:phone":"+1 714 542 0251",
    "sg:postcode":"92706",
    "sg:province":"CA",
    "sg:tags":[
        "dentist"
    ],
    "wof:name":"Kerry Jack Krause DDS",
    "wof:placetype":"venue"
},
  "geometry": {"coordinates":[-117.86968,33.757837],"type":"Point"}
}