{
  "type": "Feature",
  "properties": {
    "iso:country":"US",
    "sg:address":"1337 N H St",
    "sg:city":"Lompoc",
    "sg:classifiers":[
        {
            "category":"Autos & Motor Vehicles",
            "subcategory":"Fuel & Gas Station",
            "type":"Retail Goods"
        }
    ],
    "sg:phone":"+1 805 735 2177",
    "sg:postcode":"93436",
    "sg:province":"CA",
    "sg:tags":[
        "oil"
    ],
    "wof:name":"Lou's North H Street Chevron",
    "wof:placetype":"venue"
},
  "geometry": {"coordinates":[-120.457788,34.658263],"type":"Point"}
}