{
  "type": "Feature",
  "properties": {
    "iso:country":"US",
    "sg:address":"2125 Milvia St",
    "sg:city":"Berkeley",
    "sg:classifiers":[
        {
            "category":"Government",
            "subcategory":"Office",
            "type":"Public Place"
        }
    ],
    "sg:phone":"+1 510 644 6128",
    "sg:postcode":"94704",
    "sg:province":"CA",
    "sg:tags":[
        "apartment",
        "manpower",
        "program",
        "administration",
        "social"
    ],
    "sg:website":"www.ci.berkeley.ca.us/rent/",
    "wof:name":"Berkeley Rent Stabilization Board",
    "wof:placetype":"venue"
},
  "geometry": {"coordinates":[-122.270644,37.8704],"type":"Point"}
}