{
  "type": "Feature",
  "properties": {
    "iso:country":"US",
    "sg:address":"2027 Forest Ave",
    "sg:city":"Chico",
    "sg:classifiers":[
        {
            "category":"Restaurant",
            "type":"Food & Drink"
        }
    ],
    "sg:menulink":"http://www.allmenus.com/ca/chico/135453-jamba-juice/menu/",
    "sg:phone":"+1 530 891 5901",
    "sg:postcode":"95928",
    "sg:province":"CA",
    "sg:tags":[
        "smoothy",
        "juice",
        "american"
    ],
    "wof:name":"Jamba Juice",
    "wof:placetype":"venue"
},
  "geometry": {"coordinates":[-121.80120599999999,39.72517],"type":"Point"}
}