{
  "type": "Feature",
  "properties": {
    "iso:country":"US",
    "sg:address":"2220 Villa Ave",
    "sg:city":"Clovis",
    "sg:classifiers":[
        {
            "category":"Real Estate",
            "subcategory":"Real Estate Operator",
            "type":"Services"
        }
    ],
    "sg:phone":"+1 559 292 1251",
    "sg:postcode":"93612",
    "sg:province":"CA",
    "sg:tags":[
        "apartment"
    ],
    "wof:name":"Vineyard Apartments",
    "wof:placetype":"venue"
},
  "geometry": {"coordinates":[-119.71372,36.807879],"type":"Point"}
}