{
  "type": "Feature",
  "properties": {
    "iso:country":"US",
    "sg:address":"26950 Weyerhauser Way",
    "sg:city":"Canyon Cntry",
    "sg:classifiers":[
        {
            "category":"Retail",
            "subcategory":"Storage",
            "type":"Services"
        }
    ],
    "sg:phone":"+1 661 250 3975",
    "sg:postcode":"91351",
    "sg:province":"CA",
    "sg:tags":[
        "self"
    ],
    "wof:name":"Highway Self Storage",
    "wof:placetype":"venue"
},
  "geometry": {"coordinates":[-118.469002,34.407501],"type":"Point"}
}