{
  "type": "Feature",
  "properties": {
    "addr:full":"4975 Clairemont Mesa Blvd San Diego CA 92117",
    "addr:housenumber":"4975",
    "addr:postcode":"92117",
    "addr:street":"Clairemont Mesa Blvd",
    "iso:country":"US",
    "sg:address":"4975 Clairemont Mesa Blvd",
    "sg:city":"San Diego",
    "sg:classifiers":[
        {
            "category":"Professional",
            "type":"Services"
        }
    ],
    "sg:phone":"+1 858 565 9134",
    "sg:postcode":"92117",
    "sg:province":"CA",
    "sg:tags":[
        "arts",
        "artist"
    ],
    "wof:name":"Gorman Fine Arts",
    "wof:placetype":"venue"
},
  "geometry": {"coordinates":[-117.186494,32.834384],"type":"Point"}
}