{
  "type": "Feature",
  "properties": {
    "addr:full":"10250 Waterman Rd Elk Grove CA 95624",
    "addr:housenumber":"10250",
    "addr:postcode":"95624",
    "addr:street":"Waterman Rd",
    "iso:country":"US",
    "sg:address":"10250 Waterman Rd",
    "sg:city":"Elk Grove",
    "sg:classifiers":[
        {
            "category":"Retail",
            "subcategory":"Auto Repair",
            "type":"Services"
        },
        {
            "category":"Wholesale",
            "subcategory":"Auto Parts",
            "type":"Manufacturing & Wholesale Goods"
        }
    ],
    "sg:phone":"+1 916 685 2583",
    "sg:postcode":"95624",
    "sg:province":"CA",
    "sg:tags":[
        "body",
        "automobile",
        "used",
        "wrecking"
    ],
    "wof:name":"Elk Grove Auto Dismantlers",
    "wof:placetype":"venue"
},
  "geometry": {"coordinates":[-121.352863,38.382529],"type":"Point"}
}