{
  "type": "Feature",
  "properties": {
    "iso:country":"US",
    "sg:address":"212 W Tedrow Dr",
    "sg:city":"Glendora",
    "sg:classifiers":[
        {
            "category":"Building & Trades",
            "subcategory":"Electrical",
            "type":"Services"
        }
    ],
    "sg:phone":"+1 626 914 3269",
    "sg:postcode":"91740",
    "sg:province":"CA",
    "sg:tags":[
        "electrical",
        "contractor"
    ],
    "wof:name":"Workman Construction Inc",
    "wof:placetype":"venue"
},
  "geometry": {"coordinates":[-117.866303,34.12183],"type":"Point"}
}