{
  "type": "Feature",
  "properties": {
    "addr:full":"700 N Central Ave Ste 310 Glendale CA 91203",
    "addr:housenumber":"700",
    "addr:postcode":"91203",
    "addr:street":"N Central Ave Ste 310",
    "iso:country":"US",
    "sg:address":"700 N Central Ave Ste 310",
    "sg:city":"Glendale",
    "sg:classifiers":[
        {
            "category":"Professional",
            "subcategory":"Accounting & Tax Preparation",
            "type":"Services"
        }
    ],
    "sg:phone":"+1 818 543 7446",
    "sg:postcode":"91203",
    "sg:province":"CA",
    "sg:tags":[
        "accountant"
    ],
    "wof:name":"Ferguson Michael CPA",
    "wof:placetype":"venue"
},
  "geometry": {"coordinates":[-118.258003,34.156799],"type":"Point"}
}