{
  "type": "Feature",
  "properties": {
    "iso:country":"US",
    "sg:address":"816 Donna Way",
    "sg:city":"Montebello",
    "sg:classifiers":[
        {
            "category":"Education",
            "subcategory":"School",
            "type":"Public Place"
        }
    ],
    "sg:phone":"+1 323 728 1833",
    "sg:postcode":"90640",
    "sg:province":"CA",
    "sg:tags":[
        "high",
        "middle",
        "elementary"
    ],
    "sg:website":"www.montebello.k12.ca.us",
    "wof:name":"Wilcox Elementary School",
    "wof:placetype":"venue"
},
  "geometry": {"coordinates":[-118.124001,34.0252],"type":"Point"}
}