{
  "type": "Feature",
  "properties": {
    "addr:full":"2916 Jamacha Rd El Cajon CA 92019",
    "addr:housenumber":"2916",
    "addr:postcode":"92019",
    "addr:street":"Jamacha Rd",
    "iso:country":"US",
    "sg:address":"2916 Jamacha Rd",
    "sg:city":"El Cajon",
    "sg:classifiers":[
        {
            "category":"Building & Trades",
            "subcategory":"Construction",
            "type":"Services"
        }
    ],
    "sg:phone":"+1 619 670 1786",
    "sg:postcode":"92019",
    "sg:province":"CA",
    "sg:tags":[
        "coping",
        "plastering",
        "tiling",
        "pool",
        "swimming"
    ],
    "wof:name":"Leslie's Swimming Pool Supply",
    "wof:placetype":"venue"
},
  "geometry": {"coordinates":[-116.9421,32.73962],"type":"Point"}
}