{
  "type": "Feature",
  "properties": {
    "iso:country":"US",
    "sg:address":"27177 State Highway 189",
    "sg:city":"Blue Jay",
    "sg:classifiers":[
        {
            "category":"Cinema",
            "subcategory":"Movie Rental",
            "type":"Entertainment"
        },
        {
            "category":"Retail",
            "subcategory":"Portrait Studio",
            "type":"Services"
        }
    ],
    "sg:phone":"+1 909 337 8334",
    "sg:postcode":"92317",
    "sg:province":"CA",
    "sg:tags":[
        "photography",
        "video",
        "game",
        "store"
    ],
    "wof:name":"Blue Jay Village Video & Photo",
    "wof:placetype":"venue"
},
  "geometry": {"coordinates":[-117.212997,34.250599],"type":"Point"}
}