{
  "type": "Feature",
  "properties": {
    "iso:country":"US",
    "sg:address":"9057 Arrow Rte",
    "sg:city":"Rancho Cucamonga",
    "sg:classifiers":[
        {
            "category":"Shopping",
            "subcategory":"Pharmacy",
            "type":"Retail Goods"
        }
    ],
    "sg:phone":"+1 909 466 6701",
    "sg:postcode":"91730",
    "sg:province":"CA",
    "wof:name":"Medco Health Care",
    "wof:placetype":"venue"
},
  "geometry": {"coordinates":[-117.607865,34.099271],"type":"Point"}
}