{
  "type": "Feature",
  "properties": {
    "iso:country":"US",
    "sg:address":"1701 Fortune Dr",
    "sg:city":"San Jose",
    "sg:classifiers":[
        {
            "category":"Manufacturing",
            "subcategory":"Metals",
            "type":"Manufacturing & Wholesale Goods"
        }
    ],
    "sg:phone":"+1 408 526 9026",
    "sg:postcode":"95131",
    "sg:province":"CA",
    "sg:tags":[
        "production",
        "grinding"
    ],
    "wof:name":"D & D Precision Grinding",
    "wof:placetype":"venue"
},
  "geometry": {"coordinates":[-121.898204,37.400788],"type":"Point"}
}