{
  "type": "Feature",
  "properties": {
    "iso:country":"US",
    "sg:address":"8675 N Lake Blvd",
    "sg:city":"Kings Beach",
    "sg:classifiers":[
        {
            "category":"Food & Beverages",
            "subcategory":"Bakery",
            "type":"Retail Goods"
        }
    ],
    "sg:phone":"+1 530 546 2725",
    "sg:postcode":"96143",
    "sg:province":"CA",
    "sg:tags":[
        "pet",
        "baker",
        "store"
    ],
    "sg:website":"www.scrapsdogbakery.net/",
    "wof:name":"Scraps Dog Bakery",
    "wof:placetype":"venue"
},
  "geometry": {"coordinates":[-120.019997,39.2355],"type":"Point"}
}