{
  "type": "Feature",
  "properties": {
    "addr:full":"495 N Westwind Dr El Cajon CA 92020",
    "addr:housenumber":"495",
    "addr:postcode":"92020",
    "addr:street":"N Westwind Dr",
    "iso:country":"US",
    "sg:address":"495 N Westwind Dr",
    "sg:city":"El Cajon",
    "sg:classifiers":[
        {
            "category":"Professional",
            "subcategory":"Management & Consulting",
            "type":"Services"
        }
    ],
    "sg:phone":"+1 619 590 1820",
    "sg:postcode":"92020",
    "sg:province":"CA",
    "sg:tags":[
        "construction"
    ],
    "wof:name":"Aanda Inc",
    "wof:placetype":"venue"
},
  "geometry": {"coordinates":[-116.99369,32.801181],"type":"Point"}
}