{
  "type": "Feature",
  "properties": {
    "iso:country":"US",
    "sg:address":"1020 E Florida Ave",
    "sg:city":"Hemet",
    "sg:classifiers":[
        {
            "category":"Personal",
            "subcategory":"Beauty Salon",
            "type":"Services"
        }
    ],
    "sg:phone":"+1 951 766 8900",
    "sg:postcode":"92543",
    "sg:province":"CA",
    "wof:name":"Illusions",
    "wof:placetype":"venue"
},
  "geometry": {"coordinates":[-116.961978,33.747677],"type":"Point"}
}