{
  "type": "Feature",
  "properties": {
    "iso:country":"US",
    "sg:address":"20436 Brian Way",
    "sg:city":"Tehachapi",
    "sg:classifiers":[
        {
            "category":"Social Services",
            "type":"Services"
        }
    ],
    "sg:phone":"+1 661 822 7805",
    "sg:postcode":"93561",
    "sg:province":"CA",
    "sg:tags":[
        "organization",
        "welfare"
    ],
    "wof:name":"Help & Hope",
    "wof:placetype":"venue"
},
  "geometry": {"coordinates":[-118.492964,35.125087],"type":"Point"}
}