{
  "type": "Feature",
  "properties": {
    "iso:country":"US",
    "sg:address":"20807 Higgins Ct",
    "sg:city":"Torrance",
    "sg:classifiers":[
        {
            "category":"Retail",
            "subcategory":"Auto Repair",
            "type":"Services"
        }
    ],
    "sg:phone":"+1 310 320 2277",
    "sg:postcode":"90501",
    "sg:province":"CA",
    "sg:website":"www.rceng.com/",
    "wof:name":"R C Engineering Inc",
    "wof:placetype":"venue"
},
  "geometry": {"coordinates":[-118.30999799999999,33.841499],"type":"Point"}
}