{
  "type": "Feature",
  "properties": {
    "addr:full":"274 40th Street Way Oakland CA 94611",
    "addr:housenumber":"274",
    "addr:postcode":"94611",
    "addr:street":"40Th Street Way",
    "iso:country":"US",
    "sg:address":"274 40th Street Way",
    "sg:city":"Oakland",
    "sg:classifiers":[
        {
            "category":"Wholesale",
            "subcategory":"Motor Vehicles",
            "type":"Manufacturing & Wholesale Goods"
        }
    ],
    "sg:phone":"+1 510 594 0926",
    "sg:postcode":"94611",
    "sg:province":"CA",
    "wof:name":"Singh Tarlok",
    "wof:placetype":"venue"
},
  "geometry": {"coordinates":[-122.25625700000001,37.827485],"type":"Point"}
}