{
  "type": "Feature",
  "properties": {
    "addr:full":"1555 S Western Ave Los Angeles CA 90006",
    "addr:housenumber":"1555",
    "addr:postcode":"90006",
    "addr:street":"S Western Ave",
    "iso:country":"US",
    "sg:address":"1555 S Western Ave",
    "sg:city":"Los Angeles",
    "sg:classifiers":[
        {
            "category":"Restaurant",
            "type":"Food & Drink"
        }
    ],
    "sg:menulink":"http://www.allmenus.com/ca/los-angeles/78690-pizza-hut/menu/",
    "sg:phone":"+1 323 734 7713",
    "sg:postcode":"90006",
    "sg:province":"CA",
    "sg:tags":[
        "american",
        "pizza"
    ],
    "wof:name":"Pizza Hut",
    "wof:placetype":"venue"
},
  "geometry": {"coordinates":[-118.30902500000001,34.044208],"type":"Point"}
}