{
  "type": "Feature",
  "properties": {
    "addr:full":"13666 Hawthorne Blvd Hawthorne CA 90250",
    "addr:housenumber":"13666",
    "addr:postcode":"90250",
    "addr:street":"Hawthorne Blvd",
    "iso:country":"US",
    "sg:address":"13666 Hawthorne Blvd",
    "sg:city":"Hawthorne",
    "sg:classifiers":[
        {
            "category":"Real Estate",
            "subcategory":"Real Estate Agent",
            "type":"Services"
        }
    ],
    "sg:phone":"+1 310 349 8129",
    "sg:postcode":"90250",
    "sg:province":"CA",
    "wof:name":"Remax Training",
    "wof:placetype":"venue"
},
  "geometry": {"coordinates":[-118.35240899999999,33.90798],"type":"Point"}
}