{
  "type": "Feature",
  "properties": {
    "iso:country":"US",
    "sg:address":"572 W Ventura St",
    "sg:city":"Fillmore",
    "sg:classifiers":[
        {
            "category":"Restaurant",
            "type":"Food & Drink"
        }
    ],
    "sg:menulink":"http://www.allmenus.com/ca/fillmore-piru/172204-burger-king/menu/",
    "sg:phone":"+1 760 728 0434",
    "sg:postcode":"93015",
    "sg:province":"CA",
    "sg:tags":[
        "burger",
        "american"
    ],
    "wof:name":"Burger King",
    "wof:placetype":"venue"
},
  "geometry": {"coordinates":[-118.91471,34.396253],"type":"Point"}
}