{
  "type": "Feature",
  "properties": {
    "iso:country":"US",
    "sg:address":"2010 W Pico Blvd",
    "sg:city":"Los Angeles",
    "sg:classifiers":[
        {
            "category":"Wholesale",
            "subcategory":"Electrical",
            "type":"Manufacturing & Wholesale Goods"
        }
    ],
    "sg:phone":"+1 213 487 0425",
    "sg:postcode":"90006",
    "sg:province":"CA",
    "sg:tags":[
        "electronic"
    ],
    "wof:name":"Heidi Electronic",
    "wof:placetype":"venue"
},
  "geometry": {"coordinates":[-118.282619,34.047126],"type":"Point"}
}