{
  "type": "Feature",
  "properties": {
    "addr:full":"931 Venice Blvd Los Angeles CA 90015",
    "addr:housenumber":"931",
    "addr:postcode":"90015",
    "addr:street":"Venice Blvd",
    "iso:country":"US",
    "sg:address":"931 Venice Blvd",
    "sg:city":"Los Angeles",
    "sg:classifiers":[
        {
            "category":"Retail",
            "subcategory":"Funeral Services",
            "type":"Services"
        }
    ],
    "sg:phone":"+1 213 747 9121",
    "sg:postcode":"90015",
    "sg:province":"CA",
    "sg:tags":[
        "cemetery"
    ],
    "wof:name":"Armstrong Family",
    "wof:placetype":"venue"
},
  "geometry": {"coordinates":[-118.27600099999999,34.040199],"type":"Point"}
}