{
  "type": "Feature",
  "properties": {
    "iso:country":"US",
    "sg:address":"911 Arches Ct",
    "sg:city":"Tracy",
    "sg:classifiers":[
        {
            "category":"Manufacturing",
            "subcategory":"Tools & Machinery",
            "type":"Manufacturing & Wholesale Goods"
        }
    ],
    "sg:phone":"+1 209 835 9722",
    "sg:postcode":"95376",
    "sg:province":"CA",
    "sg:tags":[
        "machine",
        "automatic",
        "vending"
    ],
    "wof:name":"M&R Enterprises",
    "wof:placetype":"venue"
},
  "geometry": {"coordinates":[-121.4523,37.721983],"type":"Point"}
}