{
  "type": "Feature",
  "properties": {
    "addr:full":"470 Gianni St Santa Clara CA 95054",
    "addr:housenumber":"470",
    "addr:postcode":"95054",
    "addr:street":"Gianni St",
    "iso:country":"US",
    "sg:address":"470 Gianni St",
    "sg:city":"Santa Clara",
    "sg:classifiers":[
        {
            "category":"Manufacturing",
            "subcategory":"Tools & Machinery",
            "type":"Manufacturing & Wholesale Goods"
        }
    ],
    "sg:phone":"+1 408 988 6133",
    "sg:postcode":"95054",
    "sg:province":"CA",
    "sg:tags":[
        "machine",
        "shop"
    ],
    "wof:name":"Darko Precision Inc",
    "wof:placetype":"venue"
},
  "geometry": {"coordinates":[-121.945055,37.379929],"type":"Point"}
}