{
  "type": "Feature",
  "properties": {
    "iso:country":"US",
    "sg:address":"1016 S Grevillea Ave",
    "sg:city":"Inglewood",
    "sg:classifiers":[
        {
            "category":"Building & Trades",
            "subcategory":"Construction",
            "type":"Services"
        }
    ],
    "sg:phone":"+1 310 412 1737",
    "sg:postcode":"90301",
    "sg:province":"CA",
    "sg:tags":[
        "sewer",
        "contractor"
    ],
    "wof:name":"Drain Pro Plumbing Heating",
    "wof:placetype":"venue"
},
  "geometry": {"coordinates":[-118.354855,33.949377],"type":"Point"}
}