{
  "type": "Feature",
  "properties": {
    "addr:full":"12707 Foothill Blvd Sylmar CA 91342",
    "addr:housenumber":"12707",
    "addr:postcode":"91342",
    "addr:street":"Foothill Blvd",
    "iso:country":"US",
    "sg:address":"12707 Foothill Blvd",
    "sg:city":"Sylmar",
    "sg:classifiers":[
        {
            "category":"Manufacturing",
            "subcategory":"Tools & Machinery",
            "type":"Manufacturing & Wholesale Goods"
        },
        {
            "category":"Retail",
            "subcategory":"Repair Shop",
            "type":"Services"
        },
        {
            "category":"Retail",
            "subcategory":"Auto Repair",
            "type":"Services"
        }
    ],
    "sg:phone":"+1 818 837 1307",
    "sg:postcode":"91342",
    "sg:province":"CA",
    "sg:tags":[
        "machine",
        "automobile",
        "machinery-rebuild"
    ],
    "wof:name":"Valle Production & Deburring",
    "wof:placetype":"venue"
},
  "geometry": {"coordinates":[-118.411828,34.290339],"type":"Point"}
}