{
  "type": "Feature",
  "properties": {
    "addr:full":"170 Commerce St Lodi CA 95240",
    "addr:housenumber":"170",
    "addr:postcode":"95240",
    "addr:street":"Commerce St",
    "iso:country":"US",
    "sg:address":"170 Commerce St",
    "sg:city":"Lodi",
    "sg:classifiers":[
        {
            "category":"Wholesale",
            "subcategory":"Medical Equipment & Supplies",
            "type":"Manufacturing & Wholesale Goods"
        }
    ],
    "sg:phone":"+1 209 333 4690",
    "sg:postcode":"95240",
    "sg:province":"CA",
    "sg:tags":[
        "physician",
        "surgeon"
    ],
    "wof:name":"MHCS Medical Homecare Svc",
    "wof:placetype":"venue"
},
  "geometry": {"coordinates":[-121.249228,38.132116],"type":"Point"}
}