{
  "type": "Feature",
  "properties": {
    "iso:country":"US",
    "sg:address":"18487 Grand Ave",
    "sg:city":"Lake Elsinore",
    "sg:classifiers":[
        {
            "category":"Building & Trades",
            "subcategory":"Electrical",
            "type":"Services"
        }
    ],
    "sg:phone":"+1 951 678 2195",
    "sg:postcode":"92530",
    "sg:province":"CA",
    "sg:tags":[
        "electrician",
        "electric",
        "contractor"
    ],
    "wof:name":"Valley Electric",
    "wof:placetype":"venue"
},
  "geometry": {"coordinates":[-117.33000199999999,33.629902],"type":"Point"}
}