{
  "type": "Feature",
  "properties": {
    "iso:country":"US",
    "sg:address":"20370 Town Center Lane",
    "sg:city":"Cupertino",
    "sg:classifiers":[
        {
            "category":"Wholesale",
            "subcategory":"Computers",
            "type":"Manufacturing & Wholesale Goods"
        }
    ],
    "sg:phone":"+1 408 973 0104",
    "sg:postcode":"95014",
    "sg:province":"CA",
    "wof:name":"Epairs",
    "wof:placetype":"venue"
},
  "geometry": {"coordinates":[-122.030283,37.318374],"type":"Point"}
}