{
  "type": "Feature",
  "properties": {
    "addr:full":"5710 66th Ave Ofc Sacramento CA 95823",
    "addr:housenumber":"5710",
    "addr:postcode":"95823",
    "addr:street":"66Th Ave",
    "iso:country":"US",
    "sg:address":"5710 66th Ave Ofc",
    "sg:city":"Sacramento",
    "sg:classifiers":[
        {
            "category":"Building & Trades",
            "subcategory":"Landscaping Services",
            "type":"Services"
        }
    ],
    "sg:phone":"+1 916 391 2292",
    "sg:postcode":"95823",
    "sg:province":"CA",
    "sg:tags":[
        "aged",
        "homes-institutional"
    ],
    "wof:name":"Retirement Housing",
    "wof:placetype":"venue"
},
  "geometry": {"coordinates":[-121.439291,38.492446],"type":"Point"}
}