{
  "type": "Feature",
  "properties": {
    "addr:full":"101 Terry a Francois St San Francisco CA 94158",
    "addr:housenumber":"101;a",
    "addr:postcode":"94158",
    "addr:street":"Terry;Francois St",
    "iso:country":"US",
    "sg:address":"101 Terry a Francois St",
    "sg:city":"San Francisco",
    "sg:classifiers":[
        {
            "category":"Park",
            "type":"Public Place"
        }
    ],
    "sg:postcode":"94158",
    "sg:province":"CA",
    "wof:name":"China Basin Park",
    "wof:placetype":"venue"
},
  "geometry": {"coordinates":[-122.389922,37.776354],"type":"Point"}
}