{
  "type": "Feature",
  "properties": {
    "addr:full":"6200 Eastside Rd Ukiah CA 95482",
    "addr:housenumber":"6200",
    "addr:postcode":"ca 95482",
    "addr:street":"Eastside Rd",
    "iso:country":"US",
    "sg:address":"6200 Eastside Rd",
    "sg:city":"Ukiah",
    "sg:classifiers":[
        {
            "category":"Manufacturing",
            "subcategory":"Food",
            "type":"Manufacturing & Wholesale Goods"
        }
    ],
    "sg:phone":"+1 707 462 6355",
    "sg:postcode":"95482",
    "sg:province":"CA",
    "sg:tags":[
        "winery"
    ],
    "wof:name":"Whaler Vineyard",
    "wof:placetype":"venue"
},
  "geometry": {"coordinates":[-123.159633,39.079682],"type":"Point"}
}