{
  "type": "Feature",
  "properties": {
    "iso:country":"US",
    "sg:address":"144 N Claremont St",
    "sg:city":"San Mateo",
    "sg:classifiers":[
        {
            "category":"Social Services",
            "type":"Services"
        }
    ],
    "sg:phone":"+1 650 344 0928",
    "sg:postcode":"94401",
    "sg:province":"CA",
    "sg:tags":[
        "counselor",
        "marriage",
        "family"
    ],
    "wof:name":"Sharon A Carberry",
    "wof:placetype":"venue"
},
  "geometry": {"coordinates":[-122.32584900000001,37.571244],"type":"Point"}
}