{
  "type": "Feature",
  "properties": {
    "iso:country":"US",
    "sg:address":"1901 Westcliff Dr",
    "sg:city":"Newport Beach",
    "sg:classifiers":[
        {
            "category":"Health Services",
            "subcategory":"Doctor",
            "type":"Services"
        }
    ],
    "sg:phone":"+1 949 642 2300",
    "sg:postcode":"92660",
    "sg:province":"CA",
    "wof:name":"James F Flores DDS",
    "wof:placetype":"venue"
},
  "geometry": {"coordinates":[-117.90775,33.627605],"type":"Point"}
}