{
  "type": "Feature",
  "properties": {
    "iso:country":"US",
    "sg:address":"424 Kentucky St",
    "sg:city":"Bakersfield",
    "sg:classifiers":[
        {
            "category":"Home & Garden",
            "subcategory":"Carpets & Floor Coverings",
            "type":"Retail Goods"
        }
    ],
    "sg:phone":"+1 661 325 5841",
    "sg:postcode":"93305",
    "sg:province":"CA",
    "sg:tags":[
        "dealer",
        "rug"
    ],
    "wof:name":"Jeannette's Carpet",
    "wof:placetype":"venue"
},
  "geometry": {"coordinates":[-118.995559,35.379759],"type":"Point"}
}