{
  "type": "Feature",
  "properties": {
    "iso:country":"US",
    "sg:address":"6661 Markley Way",
    "sg:city":"Carmichael",
    "sg:classifiers":[
        {
            "category":"Professional",
            "type":"Services"
        }
    ],
    "sg:phone":"+1 916 721 7903",
    "sg:postcode":"95608",
    "sg:province":"CA",
    "wof:name":"Philip's Design",
    "wof:placetype":"venue"
},
  "geometry": {"coordinates":[-121.310069,38.664491],"type":"Point"}
}