{
  "type": "Feature",
  "properties": {
    "iso:country":"US",
    "sg:address":"15060 Ventura Blvd",
    "sg:city":"Sherman Oaks",
    "sg:classifiers":[
        {
            "category":"Wholesale",
            "subcategory":"Furniture",
            "type":"Manufacturing & Wholesale Goods"
        }
    ],
    "sg:phone":"+1 818 461 0450",
    "sg:postcode":"91403",
    "sg:province":"CA",
    "wof:name":"Total Office Interiors",
    "wof:placetype":"venue"
},
  "geometry": {"coordinates":[-118.460617,34.152779],"type":"Point"}
}