{
  "type": "Feature",
  "properties": {
    "addr:full":"18552 MacArthur Boulevard Irvine CA 92612",
    "addr:housenumber":"18552",
    "addr:postcode":"92612",
    "addr:street":"Macarthur Boulevard",
    "iso:country":"US",
    "sg:address":"18552 MacArthur Boulevard",
    "sg:city":"Irvine",
    "sg:classifiers":[
        {
            "category":"Banks & Credit Unions",
            "subcategory":"Financial Services",
            "type":"Services"
        }
    ],
    "sg:phone":"+1 949 955 2595",
    "sg:postcode":"92612",
    "sg:province":"CA",
    "sg:tags":[
        "broker",
        "mortgage"
    ],
    "wof:name":"Platomac",
    "wof:placetype":"venue"
},
  "geometry": {"coordinates":[-117.859836,33.678429],"type":"Point"}
}