{
  "type": "Feature",
  "properties": {
    "iso:country":"US",
    "sg:address":"15036 Hesperian Blvd",
    "sg:city":"San Leandro",
    "sg:classifiers":[
        {
            "category":"Personal",
            "subcategory":"Beauty Salon",
            "type":"Services"
        },
        {
            "category":"Personal",
            "subcategory":"Nail Salon",
            "type":"Services"
        }
    ],
    "sg:phone":"+1 510 317 8849",
    "sg:postcode":"94578",
    "sg:province":"CA",
    "sg:tags":[
        "hair"
    ],
    "wof:name":"Kim Hair & Nails",
    "wof:placetype":"venue"
},
  "geometry": {"coordinates":[-122.129937,37.703963],"type":"Point"}
}