{
  "type": "Feature",
  "properties": {
    "addr:full":"2690 E Florence Ave Huntington Park CA 90255",
    "addr:housenumber":"2690",
    "addr:postcode":"90255",
    "addr:street":"E Florence Ave;Park",
    "iso:country":"US",
    "sg:address":"2690 E Florence Ave",
    "sg:city":"Huntington Park",
    "sg:classifiers":[
        {
            "category":"Food & Beverages",
            "subcategory":"Specialty",
            "type":"Retail Goods"
        }
    ],
    "sg:phone":"+1 323 588 7200",
    "sg:postcode":"90255",
    "sg:province":"CA",
    "sg:tags":[
        "herb"
    ],
    "wof:name":"Botanica Nueva Vida",
    "wof:placetype":"venue"
},
  "geometry": {"coordinates":[-118.222855,33.973899],"type":"Point"}
}