{
  "type": "Feature",
  "properties": {
    "addr:full":"10622 Bryant St Spc 88 Yucaipa CA 92399",
    "addr:housenumber":"10622;88",
    "addr:postcode":"92399",
    "addr:street":"Bryant St",
    "iso:country":"US",
    "sg:address":"10622 Bryant St Spc 88",
    "sg:city":"Yucaipa",
    "sg:classifiers":[
        {
            "category":"Building & Trades",
            "subcategory":"Construction",
            "type":"Services"
        }
    ],
    "sg:phone":"+1 909 790 2302",
    "sg:postcode":"92399",
    "sg:province":"CA",
    "sg:tags":[
        "repair",
        "handyman",
        "maintenance",
        "home"
    ],
    "wof:name":"Gary E Lewis",
    "wof:placetype":"venue"
},
  "geometry": {"coordinates":[-117.034462,34.060719],"type":"Point"}
}