{
  "type": "Feature",
  "properties": {
    "iso:country":"US",
    "sg:address":"1116 N Crescent Heights Blv",
    "sg:city":"West Hollywood",
    "sg:classifiers":[
        {
            "category":"Building & Trades",
            "subcategory":"Locksmith",
            "type":"Services"
        }
    ],
    "sg:phone":"+1 323 863 4317",
    "sg:postcode":"90046",
    "sg:province":"CA",
    "sg:tags":[
        "key"
    ],
    "wof:name":"All Day 24 Hour Locks & Locksmith",
    "wof:placetype":"venue"
},
  "geometry": {"coordinates":[-118.365807,34.091654],"type":"Point"}
}