{
  "type": "Feature",
  "properties": {
    "addr:full":"105 Juanita Ln El Cajon CA 92021",
    "addr:housenumber":"105",
    "addr:postcode":"92021",
    "addr:street":"Juanita Ln",
    "iso:country":"US",
    "sg:address":"105 Juanita Ln",
    "sg:city":"El Cajon",
    "sg:classifiers":[
        {
            "category":"Real Estate",
            "subcategory":"Real Estate Agent",
            "type":"Services"
        }
    ],
    "sg:phone":"+1 619 441 8754",
    "sg:postcode":"92021",
    "sg:province":"CA",
    "wof:name":"Valerie J Samson",
    "wof:placetype":"venue"
},
  "geometry": {"coordinates":[-116.86685300000001,32.804029],"type":"Point"}
}