{
  "type": "Feature",
  "properties": {
    "addr:full":"909 Weddell Ct Sunnyvale CA 94089",
    "addr:housenumber":"909",
    "addr:postcode":"94089",
    "addr:street":"Weddell Ct",
    "iso:country":"US",
    "sg:address":"909 Weddell Ct",
    "sg:city":"Sunnyvale",
    "sg:classifiers":[
        {
            "category":"Professional",
            "subcategory":"Advertising",
            "type":"Services"
        }
    ],
    "sg:phone":"+1 408 744 6671",
    "sg:postcode":"94089",
    "sg:province":"CA",
    "sg:tags":[
        "counselor"
    ],
    "wof:name":"Design 2 Market",
    "wof:placetype":"venue"
},
  "geometry": {"coordinates":[-122.02103700000001,37.398345],"type":"Point"}
}