{
  "type": "Feature",
  "properties": {
    "iso:country":"US",
    "sg:address":"44218 Walnut St",
    "sg:city":"Mcarthur",
    "sg:classifiers":[
        {
            "category":"Restaurant",
            "type":"Food & Drink"
        }
    ],
    "sg:phone":"+1 530 336 6855",
    "sg:postcode":"96056",
    "sg:province":"CA",
    "wof:name":"Bulldog Bite",
    "wof:placetype":"venue"
},
  "geometry": {"coordinates":[-121.39957699999999,41.046602],"type":"Point"}
}