{
  "type": "Feature",
  "properties": {
    "addr:full":"608 Hailey Ct Simi Valley CA 93065",
    "addr:housenumber":"608",
    "addr:postcode":"93065",
    "addr:street":"Hailey Ct",
    "iso:country":"US",
    "sg:address":"608 Hailey Ct",
    "sg:city":"Simi Valley",
    "sg:classifiers":[
        {
            "category":"Professional",
            "subcategory":"Research",
            "type":"Services"
        }
    ],
    "sg:phone":"+1 805 526 6532",
    "sg:postcode":"93065",
    "sg:province":"CA",
    "sg:tags":[
        "environmental",
        "ecological"
    ],
    "wof:name":"Geoscience Analytical Inc",
    "wof:placetype":"venue"
},
  "geometry": {"coordinates":[-118.754586,34.250165],"type":"Point"}
}