{
  "type": "Feature",
  "properties": {
    "iso:country":"US",
    "sg:address":"7890 E Spring St",
    "sg:city":"Long Beach",
    "sg:classifiers":[
        {
            "category":"Building & Trades",
            "subcategory":"Construction",
            "type":"Services"
        }
    ],
    "sg:phone":"+1 562 431 3348",
    "sg:postcode":"90815",
    "sg:province":"CA",
    "sg:tags":[
        "roofing",
        "contractor"
    ],
    "wof:name":"R C Roofing",
    "wof:placetype":"venue"
},
  "geometry": {"coordinates":[-118.07944,33.810393],"type":"Point"}
}