{
  "type": "Feature",
  "properties": {
    "addr:full":"2761 Mataro St Pasadena CA 91107",
    "addr:housenumber":"2761",
    "addr:postcode":"91107",
    "addr:street":"Mataro St",
    "iso:country":"US",
    "sg:address":"2761 Mataro St",
    "sg:city":"Pasadena",
    "sg:classifiers":[
        {
            "category":"Building & Trades",
            "subcategory":"Electrical",
            "type":"Services"
        }
    ],
    "sg:phone":"+1 626 584 1303",
    "sg:postcode":"91107",
    "sg:province":"CA",
    "sg:tags":[
        "repair",
        "electrical",
        "contractor"
    ],
    "wof:name":"Elias Electric",
    "wof:placetype":"venue"
},
  "geometry": {"coordinates":[-118.093777,34.150877],"type":"Point"}
}