{
  "type": "Feature",
  "properties": {
    "iso:country":"US",
    "sg:address":"5020 Mountain Lakes Blvd",
    "sg:city":"Redding",
    "sg:classifiers":[
        {
            "category":"Manufacturing",
            "subcategory":"Printing",
            "type":"Manufacturing & Wholesale Goods"
        }
    ],
    "sg:phone":"+1 800 303 6405",
    "sg:postcode":"96003",
    "sg:province":"CA",
    "sg:tags":[
        "form",
        "bus",
        "commercial",
        "direct",
        "fulfillment",
        "mail"
    ],
    "wof:name":"Harvest Communication",
    "wof:placetype":"venue"
},
  "geometry": {"coordinates":[-122.381743,40.632273],"type":"Point"}
}