{
  "type": "Feature",
  "properties": {
    "iso:country":"US",
    "sg:address":"14470 Walnut Grove-Thornton Rd",
    "sg:city":"Walnut Grove",
    "sg:classifiers":[
        {
            "category":"Wholesale",
            "subcategory":"Machinery & Supplies",
            "type":"Manufacturing & Wholesale Goods"
        }
    ],
    "sg:phone":"+1 916 776 1735",
    "sg:postcode":"95690",
    "sg:province":"CA",
    "sg:tags":[
        "farm",
        "equipment"
    ],
    "wof:name":"Mid Cal Tractor",
    "wof:placetype":"venue"
},
  "geometry": {"coordinates":[-121.512723,38.227696],"type":"Point"}
}