{
  "type": "Feature",
  "properties": {
    "addr:full":"5546 Westmont Rd Whittier CA 90601",
    "addr:housenumber":"5546",
    "addr:postcode":"90601",
    "addr:street":"Westmont Rd",
    "iso:country":"US",
    "sg:address":"5546 Westmont Rd",
    "sg:city":"Whittier",
    "sg:classifiers":[
        {
            "category":"Retail",
            "subcategory":"Repair Shop",
            "type":"Services"
        }
    ],
    "sg:phone":"+1 562 695 4682",
    "sg:postcode":"90601",
    "sg:province":"CA",
    "sg:tags":[
        "repairing",
        "piano",
        "refinishing"
    ],
    "wof:name":"Max Cutler",
    "wof:placetype":"venue"
},
  "geometry": {"coordinates":[-118.05282200000001,33.99291],"type":"Point"}
}