{
  "type": "Feature",
  "properties": {
    "addr:full":"790 Los Palos Mnr Lafayette CA 94549",
    "addr:housenumber":"790",
    "addr:postcode":"94549",
    "addr:street":"Los Palos Mnr",
    "iso:country":"US",
    "sg:address":"790 Los Palos Mnr",
    "sg:city":"Lafayette",
    "sg:classifiers":[
        {
            "category":"Real Estate",
            "subcategory":"Developer",
            "type":"Services"
        }
    ],
    "sg:phone":"+1 925 283 0971",
    "sg:postcode":"94549",
    "sg:province":"CA",
    "wof:name":"Town Park Investment Inc",
    "wof:placetype":"venue"
},
  "geometry": {"coordinates":[-122.098781,37.880058],"type":"Point"}
}