{
  "type": "Feature",
  "properties": {
    "addr:full":"1635 E Prosperity Ave Tulare CA 93274",
    "addr:housenumber":"1635",
    "addr:postcode":"93274",
    "addr:street":"E Prosperity Ave",
    "iso:country":"US",
    "sg:address":"1635 E Prosperity Ave",
    "sg:city":"Tulare",
    "sg:classifiers":[
        {
            "category":"Insurance",
            "subcategory":"Insurance Agent",
            "type":"Services"
        }
    ],
    "sg:phone":"+1 559 685 1000",
    "sg:postcode":"93274",
    "sg:province":"CA",
    "wof:name":"State Farm Insurance",
    "wof:placetype":"venue"
},
  "geometry": {"coordinates":[-119.32574700000001,36.225757],"type":"Point"}
}