{
  "type": "Feature",
  "properties": {
    "addr:full":"4202 Jessup Rd Ceres CA 95307",
    "addr:housenumber":"4202",
    "addr:postcode":"95307",
    "addr:street":"Jessup Rd",
    "iso:country":"US",
    "sg:address":"4202 Jessup Rd",
    "sg:city":"Ceres",
    "sg:classifiers":[
        {
            "category":"Manufacturing",
            "subcategory":"Metals",
            "type":"Manufacturing & Wholesale Goods"
        },
        {
            "category":"Building & Trades",
            "subcategory":"Construction",
            "type":"Services"
        }
    ],
    "sg:phone":"+1 209 632 9956",
    "sg:postcode":"95307",
    "sg:province":"CA",
    "sg:tags":[
        "steel",
        "detailers",
        "metal-wholesale",
        "welder",
        "manufacturer",
        "structural"
    ],
    "sg:website":"http://www.designmetals.com",
    "wof:name":"Design Metals",
    "wof:placetype":"venue"
},
  "geometry": {"coordinates":[-120.919178,37.551038],"type":"Point"}
}