{
  "type": "Feature",
  "properties": {
    "addr:full":"6314 E Abbeywood Rd Orange CA 92867",
    "addr:housenumber":"6314",
    "addr:postcode":"92867",
    "addr:street":"E Abbeywood Rd",
    "iso:country":"US",
    "sg:address":"6314 E Abbeywood Rd",
    "sg:city":"Orange",
    "sg:classifiers":[
        {
            "category":"Banks & Credit Unions",
            "subcategory":"Investment Brokerage",
            "type":"Services"
        }
    ],
    "sg:phone":"+1 714 637 9048",
    "sg:postcode":"92867",
    "sg:province":"CA",
    "sg:tags":[
        "advisory",
        "financial"
    ],
    "wof:name":"K P Financial Svc",
    "wof:placetype":"venue"
},
  "geometry": {"coordinates":[-117.786224,33.826973],"type":"Point"}
}