{
  "type": "Feature",
  "properties": {
    "addr:full":"4949 District Blvd Vernon CA 90058",
    "addr:postcode":"4949;90058",
    "addr:street":"District Blvd",
    "iso:country":"US",
    "sg:address":"4949 District Blvd",
    "sg:city":"Vernon",
    "sg:classifiers":[
        {
            "category":"Shopping",
            "subcategory":"Used Merchandise",
            "type":"Retail Goods"
        }
    ],
    "sg:phone":"+1 323 589 8488",
    "sg:postcode":"90058",
    "sg:province":"CA",
    "sg:tags":[
        "clothing"
    ],
    "wof:name":"Born Again Clothing Inc",
    "wof:placetype":"venue"
},
  "geometry": {"coordinates":[-118.18894,33.997349],"type":"Point"}
}