{
  "type": "Feature",
  "properties": {
    "iso:country":"US",
    "sg:address":"9225 Carlton Hills Blvd Ste 1",
    "sg:city":"Santee",
    "sg:classifiers":[
        {
            "category":"Shopping",
            "subcategory":"Crafts & Fabrics",
            "type":"Retail Goods"
        }
    ],
    "sg:phone":"+1 619 562 0991",
    "sg:postcode":"92071",
    "sg:province":"CA",
    "sg:tags":[
        "art"
    ],
    "sg:website":"www.scrappinattack.com",
    "wof:name":"Scrappin' Attack",
    "wof:placetype":"venue"
},
  "geometry": {"coordinates":[-116.997237,32.845584],"type":"Point"}
}