{
  "type": "Feature",
  "properties": {
    "addr:full":"3330 E Florida Ave Hemet CA 92544",
    "addr:housenumber":"3330",
    "addr:postcode":"92544",
    "addr:street":"E Florida Ave",
    "iso:country":"US",
    "sg:address":"3330 E Florida Ave",
    "sg:city":"Hemet",
    "sg:classifiers":[
        {
            "category":"Home & Garden",
            "subcategory":"Furniture",
            "type":"Retail Goods"
        }
    ],
    "sg:phone":"+1 951 925 4722",
    "sg:postcode":"92544",
    "sg:province":"CA",
    "wof:name":"Cozy Home Furn & Mattress",
    "wof:placetype":"venue"
},
  "geometry": {"coordinates":[-116.93285,33.747801],"type":"Point"}
}