{
  "type": "Feature",
  "properties": {
    "iso:country":"US",
    "sg:address":"20 Fairbanks",
    "sg:city":"Irvine",
    "sg:classifiers":[
        {
            "category":"Wholesale",
            "subcategory":"Medical Equipment & Supplies",
            "type":"Manufacturing & Wholesale Goods"
        }
    ],
    "sg:phone":"+1 949 581 9988",
    "sg:postcode":"92618",
    "sg:province":"CA",
    "sg:tags":[
        "dental"
    ],
    "sg:website":"www.amdencorp.com",
    "wof:name":"Amden Corp",
    "wof:placetype":"venue"
},
  "geometry": {"coordinates":[-117.708094,33.660867],"type":"Point"}
}