{
  "type": "Feature",
  "properties": {
    "addr:full":"8820 S Sepulveda Blvd Los Angeles CA 90045",
    "addr:housenumber":"8820",
    "addr:postcode":"90045",
    "addr:street":"S Sepulveda Blvd",
    "iso:country":"US",
    "sg:address":"8820 S Sepulveda Blvd",
    "sg:city":"Los Angeles",
    "sg:classifiers":[
        {
            "category":"Professional",
            "subcategory":"Management & Consulting",
            "type":"Services"
        }
    ],
    "sg:phone":"+1 310 215 0800",
    "sg:postcode":"90045",
    "sg:province":"CA",
    "sg:tags":[
        "counselor",
        "public",
        "relations"
    ],
    "wof:name":"Dimaggio Westfield Public",
    "wof:placetype":"venue"
},
  "geometry": {"coordinates":[-118.39604,33.956099],"type":"Point"}
}