{
  "type": "Feature",
  "properties": {
    "iso:country":"US",
    "sg:address":"408 Aldo Ave",
    "sg:city":"Santa Clara",
    "sg:classifiers":[
        {
            "category":"Manufacturing",
            "subcategory":"Metals",
            "type":"Manufacturing & Wholesale Goods"
        }
    ],
    "sg:phone":"+1 408 727 3226",
    "sg:postcode":"95054",
    "sg:province":"CA",
    "sg:website":"www.precision-laser.com",
    "wof:name":"Precision Laser Cutting",
    "wof:placetype":"venue"
},
  "geometry": {"coordinates":[-121.940176,37.387267],"type":"Point"}
}