{
  "type": "Feature",
  "properties": {
    "addr:full":"408 Aldo Ave Santa Clara CA 95054",
    "addr:housenumber":"408",
    "addr:postcode":"95054",
    "addr:street":"Aldo Ave",
    "iso:country":"US",
    "sg:address":"408 Aldo Ave",
    "sg:city":"Santa Clara",
    "sg:classifiers":[
        {
            "category":"Manufacturing",
            "subcategory":"Metals",
            "type":"Manufacturing & Wholesale Goods"
        }
    ],
    "sg:phone":"+1 408 727 3226",
    "sg:postcode":"95054",
    "sg:province":"CA",
    "sg:website":"www.precision-laser.com",
    "wof:name":"Precision Laser Cutting",
    "wof:placetype":"venue"
},
  "geometry": {"coordinates":[-121.94017599999999,37.387267],"type":"Point"}
}