{
  "type": "Feature",
  "properties": {
    "iso:country":"US",
    "sg:address":"1741 N Maple St",
    "sg:city":"Burbank",
    "sg:classifiers":[
        {
            "category":"Personal",
            "subcategory":"Day Spa",
            "type":"Services"
        }
    ],
    "sg:phone":"+1 818 559 9632",
    "sg:postcode":"91505",
    "sg:province":"CA",
    "wof:name":"Spa Post Cards Dot Com",
    "wof:placetype":"venue"
},
  "geometry": {"coordinates":[-118.353786,34.180084],"type":"Point"}
}