{
  "type": "Feature",
  "properties": {
    "iso:country":"US",
    "sg:address":"7150 Sierra Ponds Ln",
    "sg:city":"Granite Bay",
    "sg:classifiers":[
        {
            "category":"Social Services",
            "subcategory":"Job Training",
            "type":"Services"
        }
    ],
    "sg:phone":"+1 916 791 7067",
    "sg:postcode":"95746",
    "sg:province":"CA",
    "sg:tags":[
        "rehabilitation"
    ],
    "wof:name":"Sierra Gates Of Sacramento",
    "wof:placetype":"venue"
},
  "geometry": {"coordinates":[-121.169651,38.762945],"type":"Point"}
}