{
  "type": "Feature",
  "properties": {
    "iso:country":"US",
    "sg:address":"5060 N Harbor Drive",
    "sg:city":"San Diego",
    "sg:classifiers":[
        {
            "category":"Professional",
            "subcategory":"Lawyer & Legal Services",
            "type":"Services"
        }
    ],
    "sg:phone":"+1 619 224 7778",
    "sg:postcode":"92106",
    "sg:province":"CA",
    "wof:name":"Rockwood & Noziska Llp",
    "wof:placetype":"venue"
},
  "geometry": {"coordinates":[-117.22580600000001,32.725409],"type":"Point"}
}