{
  "type": "Feature",
  "properties": {
    "addr:full":"1145 Wabash St Pasadena CA 91103",
    "addr:housenumber":"1145",
    "addr:postcode":"91103",
    "addr:street":"Wabash St",
    "iso:country":"US",
    "sg:address":"1145 Wabash St",
    "sg:city":"Pasadena",
    "sg:classifiers":[
        {
            "category":"Professional",
            "type":"Services"
        }
    ],
    "sg:phone":"+1 626 447 4086",
    "sg:postcode":"91103",
    "sg:province":"CA",
    "wof:name":"Kwerks",
    "wof:placetype":"venue"
},
  "geometry": {"coordinates":[-118.175366,34.164635],"type":"Point"}
}