{
  "type": "Feature",
  "properties": {
    "addr:full":"340 5th St Lakeport CA 95453",
    "addr:housenumber":"340",
    "addr:postcode":"95453",
    "addr:street":"5Th St",
    "iso:country":"US",
    "sg:address":"340 5th St",
    "sg:city":"Lakeport",
    "sg:classifiers":[
        {
            "category":"Retail",
            "subcategory":"Laundry & Dry Cleaning",
            "type":"Services"
        }
    ],
    "sg:phone":"+1 707 263 5467",
    "sg:postcode":"95453",
    "sg:province":"CA",
    "sg:tags":[
        "cleaners",
        "rug",
        "carpet"
    ],
    "wof:name":"A B Carpet Cleaning",
    "wof:placetype":"venue"
},
  "geometry": {"coordinates":[-122.917689,39.045393],"type":"Point"}
}