{
  "type": "Feature",
  "properties": {
    "iso:country":"US",
    "sg:address":"2320 Pso de Las Americas",
    "sg:city":"San Diego",
    "sg:classifiers":[
        {
            "category":"Manufacturing",
            "subcategory":"Metals",
            "type":"Manufacturing & Wholesale Goods"
        }
    ],
    "sg:phone":"+1 619 661 8389",
    "sg:postcode":"92154",
    "sg:province":"CA",
    "sg:tags":[
        "steel",
        "auto",
        "parts",
        "speaker",
        "mfg"
    ],
    "wof:name":"Kamiita International Inc",
    "wof:placetype":"venue"
},
  "geometry": {"coordinates":[-116.935979,32.554879],"type":"Point"}
}