{
  "type": "Feature",
  "properties": {
    "addr:full":"9088 Blair River Cir Fountain Valley CA 92708",
    "addr:housenumber":"9088",
    "addr:postcode":"92708",
    "addr:street":"Blair River Cir",
    "iso:country":"US",
    "sg:address":"9088 Blair River Cir",
    "sg:city":"Fountain Valley",
    "sg:classifiers":[
        {
            "category":"Freight",
            "type":"Transportation"
        }
    ],
    "sg:phone":"+1 714 963 4486",
    "sg:postcode":"92708",
    "sg:province":"CA",
    "sg:tags":[
        "sea",
        "foreign"
    ],
    "wof:name":"Puyuan Inc",
    "wof:placetype":"venue"
},
  "geometry": {"coordinates":[-117.969908,33.696041],"type":"Point"}
}