{
  "type": "Feature",
  "properties": {
    "iso:country":"US",
    "sg:address":"906 W Sierra Dr",
    "sg:city":"Santa Ana",
    "sg:classifiers":[
        {
            "category":"Professional",
            "type":"Services"
        }
    ],
    "sg:phone":"+1 714 540 1129",
    "sg:postcode":"92707",
    "sg:province":"CA",
    "wof:name":"US Equity Resources",
    "wof:placetype":"venue"
},
  "geometry": {"coordinates":[-117.87789100000001,33.703759],"type":"Point"}
}