{
  "type": "Feature",
  "properties": {
    "iso:country":"US",
    "sg:address":"4319 Admirable Dr",
    "sg:city":"Rancho Pls Vrds",
    "sg:classifiers":[
        {
            "category":"Education",
            "subcategory":"Special Training",
            "type":"Public Place"
        }
    ],
    "sg:phone":"+1 310 541 5643",
    "sg:postcode":"90275",
    "sg:province":"CA",
    "sg:tags":[
        "instruction",
        "music"
    ],
    "wof:name":"Jeannine Mc Daniel",
    "wof:placetype":"venue"
},
  "geometry": {"coordinates":[-118.354479,33.736508],"type":"Point"}
}