{
  "type": "Feature",
  "properties": {
    "addr:full":"255 9th St San Francisco CA 94103",
    "addr:housenumber":"255",
    "addr:postcode":"94103",
    "addr:street":"9Th St",
    "iso:country":"US",
    "sg:address":"255 9th St",
    "sg:city":"San Francisco",
    "sg:classifiers":[
        {
            "category":"Professional",
            "subcategory":"Business Services",
            "type":"Services"
        }
    ],
    "sg:phone":"+1 415 552 2911",
    "sg:postcode":"94103",
    "sg:province":"CA",
    "wof:name":"Ceasar Chavez Holiday Parade",
    "wof:placetype":"venue"
},
  "geometry": {"coordinates":[-122.41169600000001,37.773957],"type":"Point"}
}