{
  "type": "Feature",
  "properties": {
    "iso:country":"US",
    "sg:address":"1025 Dara Ct",
    "sg:city":"Redding",
    "sg:classifiers":[
        {
            "category":"Social Services",
            "subcategory":"Adult Care",
            "type":"Services"
        }
    ],
    "sg:phone":"+1 530 246 4553",
    "sg:postcode":"96003",
    "sg:province":"CA",
    "sg:tags":[
        "home",
        "residential"
    ],
    "wof:name":"Dara Care Homes I & II",
    "wof:placetype":"venue"
},
  "geometry": {"coordinates":[-122.405409,40.622109],"type":"Point"}
}