{
  "type": "Feature",
  "properties": {
    "iso:country":"US",
    "sg:address":"1493 Main St",
    "sg:city":"Watsonville",
    "sg:classifiers":[
        {
            "category":"Health Services",
            "subcategory":"Doctor",
            "type":"Services"
        }
    ],
    "sg:phone":"+1 831 722 7228",
    "sg:postcode":"95076",
    "sg:province":"CA",
    "sg:tags":[
        "dentist"
    ],
    "wof:name":"Watsonville Family Dentistry",
    "wof:placetype":"venue"
},
  "geometry": {"coordinates":[-121.77193,36.916504],"type":"Point"}
}