{
  "type": "Feature",
  "properties": {
    "iso:country":"US",
    "sg:address":"5000 E Fremont St",
    "sg:city":"Stockton",
    "sg:classifiers":[
        {
            "category":"Freight",
            "type":"Transportation"
        }
    ],
    "sg:phone":"+1 209 943 5000",
    "sg:postcode":"95215",
    "sg:province":"CA",
    "sg:tags":[
        "trucking"
    ],
    "wof:name":"Panella Trucking Inc",
    "wof:placetype":"venue"
},
  "geometry": {"coordinates":[-121.235578,37.97306],"type":"Point"}
}