{
  "type": "Feature",
  "properties": {
    "iso:country":"US",
    "sg:address":"595 Buckingham Way",
    "sg:city":"San Francisco",
    "sg:classifiers":[
        {
            "category":"Health Services",
            "subcategory":"Doctor",
            "type":"Services"
        }
    ],
    "sg:phone":"+1 415 661 8777",
    "sg:postcode":"94132",
    "sg:province":"CA",
    "sg:tags":[
        "dentist"
    ],
    "wof:name":"Gayle A Chin DDS",
    "wof:placetype":"venue"
},
  "geometry": {"coordinates":[-122.47927900000001,37.725908],"type":"Point"}
}