{
  "type": "Feature",
  "properties": {
    "addr:full":"1400 Longmeadow Dr Gilroy CA 95020",
    "addr:housenumber":"1400",
    "addr:postcode":"95020",
    "addr:street":"Longmeadow Dr",
    "iso:country":"US",
    "sg:address":"1400 Longmeadow Dr",
    "sg:city":"Gilroy",
    "sg:classifiers":[
        {
            "category":"Professional",
            "type":"Services"
        }
    ],
    "sg:phone":"+1 408 842 9794",
    "sg:postcode":"95020",
    "sg:province":"CA",
    "sg:tags":[
        "establishment"
    ],
    "wof:name":"Waaay Too Busy",
    "wof:placetype":"venue"
},
  "geometry": {"coordinates":[-121.60930999999999,37.02818],"type":"Point"}
}