{
  "type": "Feature",
  "properties": {
    "iso:country":"US",
    "sg:address":"7530 Van Nuys Blvd",
    "sg:city":"Van Nuys",
    "sg:classifiers":[
        {
            "category":"Insurance",
            "subcategory":"Health Insurance",
            "type":"Services"
        }
    ],
    "sg:phone":"+1 818 787 2414",
    "sg:postcode":"91405",
    "sg:province":"CA",
    "sg:tags":[
        "carrier",
        "plan"
    ],
    "wof:name":"Cal Best Insurance",
    "wof:placetype":"venue"
},
  "geometry": {"coordinates":[-118.448689,34.208156],"type":"Point"}
}