{
  "type": "Feature",
  "properties": {
    "iso:country":"US",
    "sg:address":"1407 Verde Dr",
    "sg:city":"Gustine",
    "sg:classifiers":[
        {
            "category":"Farming",
            "subcategory":"Farm",
            "type":"Manufacturing & Wholesale Goods"
        }
    ],
    "sg:phone":"+1 209 854 6593",
    "sg:postcode":"95322",
    "sg:province":"CA",
    "sg:tags":[
        "crop",
        "general"
    ],
    "wof:name":"Manzo Farms",
    "wof:placetype":"venue"
},
  "geometry": {"coordinates":[-121.009156,37.254521],"type":"Point"}
}