{
  "type": "Feature",
  "properties": {
    "iso:country":"US",
    "sg:address":"2129 Pleasant Grove Rd",
    "sg:city":"Encinitas",
    "sg:classifiers":[
        {
            "category":"Professional",
            "type":"Services"
        }
    ],
    "sg:phone":"+1 760 635 7910",
    "sg:postcode":"92024",
    "sg:province":"CA",
    "wof:name":"Felipe Belman & Son",
    "wof:placetype":"venue"
},
  "geometry": {"coordinates":[-117.243168,33.041256],"type":"Point"}
}