{
  "type": "Feature",
  "properties": {
    "iso:country":"US",
    "sg:address":"967 Grand Ave",
    "sg:city":"Grover Beach",
    "sg:classifiers":[
        {
            "category":"Restaurant",
            "type":"Food & Drink"
        }
    ],
    "sg:phone":"+1 805 489 7284",
    "sg:postcode":"93433",
    "sg:province":"CA",
    "wof:name":"Peking Low Restaurant",
    "wof:placetype":"venue"
},
  "geometry": {"coordinates":[-120.61955399999999,35.121555],"type":"Point"}
}