{
  "type": "Feature",
  "properties": {
    "addr:full":"3445 Benton St Santa Clara CA 95050",
    "addr:housenumber":"3445",
    "addr:postcode":"95050",
    "addr:street":"Benton St",
    "iso:country":"US",
    "sg:address":"3445 Benton St",
    "sg:city":"Santa Clara",
    "sg:classifiers":[
        {
            "category":"Sports & Exercise",
            "subcategory":"Gym",
            "type":"Entertainment"
        },
        {
            "category":"Education",
            "subcategory":"School",
            "type":"Public Place"
        },
        {
            "category":"Sports & Exercise",
            "subcategory":"Swimming Pool",
            "type":"Entertainment"
        }
    ],
    "sg:phone":"+1 408 984 5183",
    "sg:postcode":"95050",
    "sg:province":"CA",
    "sg:website":"www.calsportscenter.com",
    "wof:name":"California Sports Center",
    "wof:placetype":"venue"
},
  "geometry": {"coordinates":[-121.98993400000001,37.345092],"type":"Point"}
}