{
  "type": "Feature",
  "properties": {
    "iso:country":"US",
    "sg:address":"3639 18th St",
    "sg:city":"San Francisco",
    "sg:classifiers":[
        {
            "category":"Food & Beverages",
            "subcategory":"Specialty",
            "type":"Retail Goods"
        }
    ],
    "sg:phone":"+1 415 241 9760",
    "sg:postcode":"94110",
    "sg:province":"CA",
    "sg:tags":[
        "gourmet",
        "shop"
    ],
    "sg:website":"www.biritemarket.com",
    "wof:name":"Bi-Rite Market",
    "wof:placetype":"venue"
},
  "geometry": {"coordinates":[-122.42468,37.761285],"type":"Point"}
}