{
  "type": "Feature",
  "properties": {
    "addr:full":"8460 Waverly Dr Buena Park CA 90621",
    "addr:housenumber":"8460",
    "addr:postcode":"90621",
    "addr:street":"Waverly Dr",
    "iso:country":"US",
    "sg:address":"8460 Waverly Dr",
    "sg:city":"Buena Park",
    "sg:classifiers":[
        {
            "category":"Professional",
            "subcategory":"Lawyer & Legal Services",
            "type":"Services"
        }
    ],
    "sg:phone":"+1 714 522 0420",
    "sg:postcode":"90621",
    "sg:province":"CA",
    "wof:name":"Jack F King",
    "wof:placetype":"venue"
},
  "geometry": {"coordinates":[-117.986603,33.892605],"type":"Point"}
}