{
  "type": "Feature",
  "properties": {
    "iso:country":"US",
    "sg:address":"2550 Park Ave",
    "sg:city":"Concord",
    "sg:classifiers":[
        {
            "category":"Health Services",
            "subcategory":"Doctor",
            "type":"Services"
        }
    ],
    "sg:phone":"+1 925 686 4110",
    "sg:postcode":"94520",
    "sg:province":"CA",
    "sg:tags":[
        "dentist"
    ],
    "wof:name":"Benjamin Chan DDS",
    "wof:placetype":"venue"
},
  "geometry": {"coordinates":[-122.033547,37.984117],"type":"Point"}
}