{
  "type": "Feature",
  "properties": {
    "iso:country":"US",
    "sg:address":"3500 N Sepulveda Blvd",
    "sg:city":"Manhattan Beach",
    "sg:classifiers":[
        {
            "category":"Health Services",
            "subcategory":"Doctor",
            "type":"Services"
        }
    ],
    "sg:phone":"+1 310 546 9711",
    "sg:postcode":"90266",
    "sg:province":"CA",
    "sg:tags":[
        "dentist"
    ],
    "wof:name":"Arthur Natvig DDS",
    "wof:placetype":"venue"
},
  "geometry": {"coordinates":[-118.396159,33.900413],"type":"Point"}
}