{
  "type": "Feature",
  "properties": {
    "iso:country":"US",
    "sg:address":"2 Monte Vista Way",
    "sg:city":"Gilroy",
    "sg:classifiers":[
        {
            "category":"Real Estate",
            "subcategory":"Real Estate Services",
            "type":"Services"
        }
    ],
    "sg:phone":"+1 408 842 3459",
    "sg:postcode":"95020",
    "sg:province":"CA",
    "sg:tags":[
        "vacancy",
        "rental",
        "listing"
    ],
    "wof:name":"Kennedy Family Ltd",
    "wof:placetype":"venue"
},
  "geometry": {"coordinates":[-121.579773,37.007141],"type":"Point"}
}