{
  "type": "Feature",
  "properties": {
    "iso:country":"US",
    "sg:address":"1633 Bayshore Hwy Suite 125",
    "sg:city":"Burlingame",
    "sg:classifiers":[
        {
            "category":"Professional",
            "subcategory":"Accounting & Tax Preparation",
            "type":"Services"
        }
    ],
    "sg:phone":"+1 650 697 7736",
    "sg:postcode":"94010",
    "sg:province":"CA",
    "sg:tags":[
        "accountant"
    ],
    "wof:name":"Goode Ann M CPA",
    "wof:placetype":"venue"
},
  "geometry": {"coordinates":[-122.368189,37.599914],"type":"Point"}
}