{
  "type": "Feature",
  "properties": {
    "addr:full":"119 Main St Seal Beach CA 90740",
    "addr:housenumber":"119",
    "addr:postcode":"90740",
    "addr:street":"Main St",
    "iso:country":"US",
    "sg:address":"119 Main St",
    "sg:city":"Seal Beach",
    "sg:classifiers":[
        {
            "category":"Shopping",
            "type":"Retail Goods"
        }
    ],
    "sg:phone":"+1 562 594 4848",
    "sg:postcode":"90740",
    "sg:province":"CA",
    "sg:tags":[
        "art",
        "gallery",
        "dealer"
    ],
    "sg:website":"www.artimagesgallery.com",
    "wof:name":"Art Images",
    "wof:placetype":"venue"
},
  "geometry": {"coordinates":[-118.104957,33.741229],"type":"Point"}
}