{
  "type": "Feature",
  "properties": {
    "iso:country":"US",
    "sg:address":"728 S Hill St",
    "sg:city":"Los Angeles",
    "sg:classifiers":[
        {
            "category":"Shopping",
            "subcategory":"Jewelry",
            "type":"Retail Goods"
        }
    ],
    "sg:phone":"+1 213 622 0867",
    "sg:postcode":"90014",
    "sg:province":"CA",
    "sg:tags":[
        "diamond",
        "setter"
    ],
    "wof:name":"GAT Diamond Setting",
    "wof:placetype":"venue"
},
  "geometry": {"coordinates":[-118.255409,34.044834],"type":"Point"}
}