{
  "type": "Feature",
  "properties": {
    "addr:full":"15632 Pomerado Rd Poway CA 92064",
    "addr:housenumber":"15632",
    "addr:postcode":"ca 92064",
    "addr:street":"Pomerado Rd",
    "iso:country":"US",
    "sg:address":"15632 Pomerado Rd",
    "sg:city":"Poway",
    "sg:classifiers":[
        {
            "category":"Health Services",
            "subcategory":"Nursing And Care Facility",
            "type":"Services"
        }
    ],
    "sg:phone":"+1 858 485 5153",
    "sg:postcode":"92064",
    "sg:province":"CA",
    "sg:tags":[
        "skilled"
    ],
    "wof:name":"Manorcare Health Services",
    "wof:placetype":"venue"
},
  "geometry": {"coordinates":[-117.057957,32.995381],"type":"Point"}
}