{
  "type": "Feature",
  "properties": {
    "iso:country":"US",
    "sg:address":"737 N Lake St",
    "sg:city":"Burbank",
    "sg:classifiers":[
        {
            "category":"Building & Trades",
            "subcategory":"Construction",
            "type":"Services"
        }
    ],
    "sg:phone":"+1 818 953 2856",
    "sg:postcode":"91502",
    "sg:province":"CA",
    "sg:tags":[
        "interior",
        "design"
    ],
    "wof:name":"Galindo's Interior Services",
    "wof:placetype":"venue"
},
  "geometry": {"coordinates":[-118.319,34.181599],"type":"Point"}
}