{
  "type": "Feature",
  "properties": {
    "addr:full":"23004 Frisca Dr Valencia CA 91354",
    "addr:postcode":"23004;91354",
    "addr:street":"Frisca Dr",
    "iso:country":"US",
    "sg:address":"23004 Frisca Dr",
    "sg:city":"Valencia",
    "sg:classifiers":[
        {
            "category":"Wholesale",
            "subcategory":"Seafood",
            "type":"Manufacturing & Wholesale Goods"
        }
    ],
    "sg:phone":"+1 661 296 5999",
    "sg:postcode":"91354",
    "sg:province":"CA",
    "wof:name":"Natco Worldwide Representatives",
    "wof:placetype":"venue"
},
  "geometry": {"coordinates":[-118.53800200000001,34.4366],"type":"Point"}
}