{
  "type": "Feature",
  "properties": {
    "addr:full":"5625 College Ave Oakland CA 94618",
    "addr:housenumber":"5625",
    "addr:postcode":"94618",
    "addr:street":"College Ave",
    "iso:country":"US",
    "sg:address":"5625 College Ave",
    "sg:city":"Oakland",
    "sg:classifiers":[
        {
            "category":"Health Services",
            "subcategory":"Health Practitioner",
            "type":"Services"
        }
    ],
    "sg:phone":"+1 510 528 9903",
    "sg:postcode":"94618",
    "sg:province":"CA",
    "sg:tags":[
        "psychotherapist"
    ],
    "wof:name":"Cheryl Jacques",
    "wof:placetype":"venue"
},
  "geometry": {"coordinates":[-122.25182100000001,37.843777],"type":"Point"}
}