{
  "type": "Feature",
  "properties": {
    "addr:full":"1724 Hooper Rd Yuba City CA 95993",
    "addr:housenumber":"1724",
    "addr:postcode":"95993",
    "addr:street":"Hooper Rd",
    "iso:country":"US",
    "sg:address":"1724 Hooper Rd",
    "sg:city":"Yuba City",
    "sg:classifiers":[
        {
            "category":"Organizations",
            "subcategory":"Religious Organization",
            "type":"Services"
        }
    ],
    "sg:phone":"+1 530 674 5394",
    "sg:postcode":"95993",
    "sg:province":"CA",
    "sg:tags":[
        "church"
    ],
    "wof:name":"First Missionary Baptist Chr",
    "wof:placetype":"venue"
},
  "geometry": {"coordinates":[-121.667225,39.15336],"type":"Point"}
}