{
  "type": "Feature",
  "properties": {
    "iso:country":"US",
    "sg:address":"1819 Novato Blvd",
    "sg:city":"Novato",
    "sg:classifiers":[
        {
            "category":"Retail",
            "subcategory":"Veterinary Services",
            "type":"Services"
        }
    ],
    "sg:phone":"+1 415 892 2400",
    "sg:postcode":"94947",
    "sg:province":"CA",
    "wof:name":"Maas Sandra L Dvm",
    "wof:placetype":"venue"
},
  "geometry": {"coordinates":[-122.586186,38.109466],"type":"Point"}
}