{
  "type": "Feature",
  "properties": {
    "addr:full":"6114 La Salle Ave Oakland CA 94611",
    "addr:housenumber":"6114",
    "addr:postcode":"94611",
    "addr:street":"La Salle Ave",
    "iso:country":"US",
    "sg:address":"6114 La Salle Ave",
    "sg:city":"Oakland",
    "sg:classifiers":[
        {
            "category":"Professional",
            "subcategory":"Lawyer & Legal Services",
            "type":"Services"
        }
    ],
    "sg:phone":"+1 510 451 7222",
    "sg:postcode":"94611",
    "sg:province":"CA",
    "wof:name":"Lawrence Noel M Attorney At Law",
    "wof:placetype":"venue"
},
  "geometry": {"coordinates":[-122.23200199999999,37.8284],"type":"Point"}
}