{
  "type": "Feature",
  "properties": {
    "addr:full":"16422 Ventura Blvd Encino CA 91436",
    "addr:housenumber":"16422",
    "addr:postcode":"91436",
    "addr:street":"Ventura Blvd",
    "iso:country":"US",
    "sg:address":"16422 Ventura Blvd",
    "sg:city":"Encino",
    "sg:classifiers":[
        {
            "category":"Retail",
            "subcategory":"Laundry & Dry Cleaning",
            "type":"Services"
        }
    ],
    "sg:phone":"+1 818 501 2266",
    "sg:postcode":"91436",
    "sg:province":"CA",
    "sg:tags":[
        "drycleaning",
        "plant"
    ],
    "wof:name":"Hill Top Cleaners",
    "wof:placetype":"venue"
},
  "geometry": {"coordinates":[-118.491951,34.157423],"type":"Point"}
}