{
  "type": "Feature",
  "properties": {
    "addr:full":"223 W Rosecrans Avenue Gardena CA 90248",
    "addr:housenumber":"223",
    "addr:postcode":"90248",
    "addr:street":"W Rosecrans Avenue",
    "iso:country":"US",
    "sg:address":"223 W Rosecrans Avenue",
    "sg:city":"Gardena",
    "sg:classifiers":[
        {
            "category":"Shopping",
            "subcategory":"Clothing, Apparel, & Fashions",
            "type":"Retail Goods"
        }
    ],
    "sg:phone":"+1 310 768 3333",
    "sg:postcode":"90248",
    "sg:province":"CA",
    "sg:tags":[
        "clothing",
        "women's"
    ],
    "wof:name":"K & K Apparel",
    "wof:placetype":"venue"
},
  "geometry": {"coordinates":[-118.27724600000001,33.902067],"type":"Point"}
}