{
  "type": "Feature",
  "properties": {
    "addr:full":"4417 La Jolla Village Drive San Diego CA 92122",
    "addr:housenumber":"4417",
    "addr:postcode":"92122",
    "addr:street":"La Jolla Village Drive",
    "iso:country":"US",
    "sg:address":"4417 La Jolla Village Drive",
    "sg:city":"San Diego",
    "sg:classifiers":[
        {
            "category":"Shopping Center",
            "type":"Public Place"
        }
    ],
    "sg:phone":"+1 858 558 8166",
    "sg:postcode":"92122",
    "sg:province":"CA",
    "wof:name":"Steeplechase Polo & Nautica Sportswear",
    "wof:placetype":"venue"
},
  "geometry": {"coordinates":[-117.21145,32.873146],"type":"Point"}
}