{
  "type": "Feature",
  "properties": {
    "addr:full":"9171 Wilshire Boulevard Suite A Beverly Hills CA 90210",
    "addr:housenumber":"9171",
    "addr:postcode":"90210",
    "addr:street":"Wilshire Boulevard Suite A Beverly Hills Ca",
    "iso:country":"US",
    "sg:address":"9171 Wilshire Boulevard Suite A",
    "sg:city":"Beverly Hills",
    "sg:classifiers":[
        {
            "category":"Restaurant",
            "type":"Food & Drink"
        }
    ],
    "sg:phone":"+1 310 278 6491",
    "sg:postcode":"90210",
    "sg:province":"CA",
    "wof:name":"Cafe Connection",
    "wof:placetype":"venue"
},
  "geometry": {"coordinates":[-118.391999,34.067137],"type":"Point"}
}