{
  "type": "Feature",
  "properties": {
    "iso:country":"US",
    "sg:address":"1999 Harrison Street #101",
    "sg:city":"San Francisco",
    "sg:classifiers":[
        {
            "category":"Professional",
            "subcategory":"Business Services",
            "type":"Services"
        }
    ],
    "sg:phone":"+1 404 869 2500",
    "sg:postcode":"94612",
    "sg:province":"CA",
    "sg:tags":[
        "unified-communications",
        "hosted-unfied-communications",
        "unified-communications-as-a-service",
        "ucaas",
        "hosted-voip",
        "voip",
        "telecommunications",
        "telephony",
        "microsoft-ocs"
    ],
    "sg:website":"http://www.cypresscom.net",
    "wof:name":"Cypress Communications",
    "wof:placetype":"venue"
},
  "geometry": {"coordinates":[-122.264563,37.807945],"type":"Point"}
}