{
  "type": "Feature",
  "properties": {
    "iso:country":"US",
    "sg:address":"6776 Avenue 416",
    "sg:city":"Dinuba",
    "sg:classifiers":[
        {
            "category":"Farming",
            "subcategory":"Nursery",
            "type":"Manufacturing & Wholesale Goods"
        }
    ],
    "sg:phone":"+1 559 651 1400",
    "sg:postcode":"93618",
    "sg:province":"CA",
    "sg:tags":[
        "tree",
        "nurseries-plants"
    ],
    "wof:name":"Mt Hood Pools",
    "wof:placetype":"venue"
},
  "geometry": {"coordinates":[-119.42552000000001,36.546176],"type":"Point"}
}