{
  "type": "Feature",
  "properties": {
    "iso:country":"US",
    "sg:address":"3060 State St",
    "sg:city":"Santa Barbara",
    "sg:classifiers":[
        {
            "category":"Autos & Motor Vehicles",
            "subcategory":"Fuel & Gas Station",
            "type":"Retail Goods"
        }
    ],
    "sg:phone":"+1 805 563 1001",
    "sg:postcode":"93105",
    "sg:province":"CA",
    "sg:tags":[
        "oil"
    ],
    "wof:name":"State Shell",
    "wof:placetype":"venue"
},
  "geometry": {"coordinates":[-119.730746,34.440436],"type":"Point"}
}