{
  "type": "Feature",
  "properties": {
    "iso:country":"US",
    "sg:address":"4111 State St",
    "sg:city":"Santa Barbara",
    "sg:classifiers":[
        {
            "category":"Travel",
            "subcategory":"Hotels & Motels",
            "type":"Entertainment"
        }
    ],
    "sg:phone":"+1 805 967 2901",
    "sg:postcode":"93110",
    "sg:province":"CA",
    "wof:name":"Hope Ranch Inn",
    "wof:placetype":"venue"
},
  "geometry": {"coordinates":[-119.758703,34.440396],"type":"Point"}
}