{
  "type": "Feature",
  "properties": {
    "iso:country":"US",
    "sg:address":"581 McCray St",
    "sg:city":"Hollister",
    "sg:classifiers":[
        {
            "category":"Personal",
            "subcategory":"Beauty Salon",
            "type":"Services"
        }
    ],
    "sg:phone":"+1 831 636 3623",
    "sg:postcode":"95023",
    "sg:province":"CA",
    "wof:name":"Simply Skin",
    "wof:placetype":"venue"
},
  "geometry": {"coordinates":[-121.397521,36.850382],"type":"Point"}
}