{
  "type": "Feature",
  "properties": {
    "iso:country":"US",
    "sg:address":"4279 Genesee Avenue",
    "sg:city":"San Diego",
    "sg:classifiers":[
        {
            "category":"Shopping",
            "subcategory":"Shoes",
            "type":"Retail Goods"
        }
    ],
    "sg:phone":"+1 858 277 0566",
    "sg:postcode":"92117",
    "sg:province":"CA",
    "sg:tags":[
        "store"
    ],
    "wof:name":"Payless Shoe Source",
    "wof:placetype":"venue"
},
  "geometry": {"coordinates":[-117.182779,32.820956],"type":"Point"}
}