{
  "type": "Feature",
  "properties": {
    "addr:full":"22492 Bayberry Mission Viejo CA 92692",
    "addr:housenumber":"22492",
    "addr:postcode":"92692",
    "addr:street":"Bayberry",
    "iso:country":"US",
    "sg:address":"22492 Bayberry",
    "sg:city":"Mission Viejo",
    "sg:classifiers":[
        {
            "category":"Professional",
            "subcategory":"Engineering",
            "type":"Services"
        }
    ],
    "sg:phone":"+1 949 830 9140",
    "sg:postcode":"92692",
    "sg:province":"CA",
    "wof:name":"Practical Enginuity",
    "wof:placetype":"venue"
},
  "geometry": {"coordinates":[-117.634134,33.636265],"type":"Point"}
}