{
  "type": "Feature",
  "properties": {
    "iso:country":"US",
    "sg:address":"653 Cam de Los Mares",
    "sg:city":"San Clemente",
    "sg:classifiers":[
        {
            "category":"Health Services",
            "subcategory":"Doctor",
            "type":"Services"
        }
    ],
    "sg:phone":"+1 949 248 7772",
    "sg:postcode":"92673",
    "sg:province":"CA",
    "sg:tags":[
        "dentist"
    ],
    "wof:name":"Sachiko V Fukuman DDS",
    "wof:placetype":"venue"
},
  "geometry": {"coordinates":[-117.647021,33.457075],"type":"Point"}
}