{
  "type": "Feature",
  "properties": {
    "addr:full":"2701 20th St Bakersfield CA 93301",
    "addr:housenumber":"2701",
    "addr:postcode":"93301",
    "addr:street":"20Th St",
    "iso:country":"US",
    "sg:address":"2701 20th St",
    "sg:city":"Bakersfield",
    "sg:classifiers":[
        {
            "category":"Professional",
            "subcategory":"Employment Agencies",
            "type":"Services"
        }
    ],
    "sg:phone":"+1 661 634 9228",
    "sg:postcode":"93301",
    "sg:province":"CA",
    "sg:tags":[
        "employer"
    ],
    "sg:website":"http://www.sercal.org",
    "wof:name":"Society For Ecological Restoration",
    "wof:placetype":"venue"
},
  "geometry": {"coordinates":[-119.03280599999999,35.377232],"type":"Point"}
}