{
  "type": "Feature",
  "properties": {
    "iso:country":"US",
    "sg:address":"1429 Broadway",
    "sg:city":"Sacramento",
    "sg:classifiers":[
        {
            "category":"Juice Bar",
            "subcategory":"None",
            "type":"Food & Drink"
        }
    ],
    "sg:phone":"+1 916 447 3752",
    "sg:postcode":"95818",
    "sg:province":"CA",
    "sg:tags":[
        "smoothy"
    ],
    "sg:website":"www.jambajuice.com/",
    "wof:name":"Jamba Juice",
    "wof:placetype":"venue"
},
  "geometry": {"coordinates":[-121.49388,38.562366],"type":"Point"}
}