{
  "type": "Feature",
  "properties": {
    "addr:full":"19334 Victory Blvd Reseda CA 91335",
    "addr:housenumber":"19334",
    "addr:postcode":"91335",
    "addr:street":"Victory Blvd",
    "iso:country":"US",
    "sg:address":"19334 Victory Blvd",
    "sg:city":"Reseda",
    "sg:classifiers":[
        {
            "category":"Building & Trades",
            "subcategory":"Construction",
            "type":"Services"
        }
    ],
    "sg:phone":"+1 818 757 0041",
    "sg:postcode":"91335",
    "sg:province":"CA",
    "sg:tags":[
        "contractor",
        "nonresidential"
    ],
    "wof:name":"California Engineering Inc",
    "wof:placetype":"venue"
},
  "geometry": {"coordinates":[-118.557535,34.186494],"type":"Point"}
}