{
  "type": "Feature",
  "properties": {
    "addr:full":"580 US Hwy 395 Olancha CA 93549",
    "addr:housenumber":"580",
    "addr:postcode":"93549",
    "addr:street":"Us Hwy 395",
    "iso:country":"US",
    "sg:address":"580 US Hwy 395",
    "sg:city":"Olancha",
    "sg:classifiers":[
        {
            "category":"Wholesale",
            "subcategory":"Meat",
            "type":"Manufacturing & Wholesale Goods"
        }
    ],
    "sg:phone":"+1 760 764 2822",
    "sg:postcode":"93549",
    "sg:province":"CA",
    "sg:tags":[
        "product"
    ],
    "wof:name":"Gus's Fresh Jerky",
    "wof:placetype":"venue"
},
  "geometry": {"coordinates":[-118.012754,36.288624],"type":"Point"}
}