{
  "type": "Feature",
  "properties": {
    "addr:full":"15466 Los Gatos Blvd Los Gatos CA 95032",
    "addr:housenumber":"15466",
    "addr:postcode":"95032",
    "addr:street":"Los Gatos Blvd",
    "iso:country":"US",
    "sg:address":"15466 Los Gatos Blvd",
    "sg:city":"Los Gatos",
    "sg:classifiers":[
        {
            "category":"Retail",
            "subcategory":"Laundry & Dry Cleaning",
            "type":"Services"
        }
    ],
    "sg:postcode":"95032",
    "sg:province":"CA",
    "wof:name":"Vasona Cleaners",
    "wof:placetype":"venue"
},
  "geometry": {"coordinates":[-121.95801400000001,37.244484],"type":"Point"}
}