{
  "type": "Feature",
  "properties": {
    "addr:full":"160 S Old Springs Rd Anaheim CA 92808",
    "addr:housenumber":"160",
    "addr:postcode":"92808",
    "addr:street":"S Old Springs Rd",
    "iso:country":"US",
    "sg:address":"160 S Old Springs Rd",
    "sg:city":"Anaheim",
    "sg:classifiers":[
        {
            "category":"Professional",
            "subcategory":"Employment Agencies",
            "type":"Services"
        }
    ],
    "sg:phone":"+1 714 846 3227",
    "sg:postcode":"92808",
    "sg:province":"CA",
    "wof:name":"Abigail Abbott Staffing Services",
    "wof:placetype":"venue"
},
  "geometry": {"coordinates":[-117.741997,33.864201],"type":"Point"}
}