{
  "type": "Feature",
  "properties": {
    "iso:country":"US",
    "sg:address":"5284 Eastgate Mall",
    "sg:city":"San Diego",
    "sg:classifiers":[
        {
            "category":"Professional",
            "type":"Services"
        }
    ],
    "sg:phone":"+1 858 622 1055",
    "sg:postcode":"92121",
    "sg:province":"CA",
    "sg:tags":[
        "caterer"
    ],
    "sg:website":"www.californiaquivers.com",
    "wof:name":"California Quivers",
    "wof:placetype":"venue"
},
  "geometry": {"coordinates":[-117.193973,32.882644],"type":"Point"}
}