{
  "type": "Feature",
  "properties": {
    "addr:full":"42444 23rd St W Lancaster CA 93536",
    "addr:housenumber":"42444",
    "addr:postcode":"93536",
    "addr:street":"23Rd St W",
    "iso:country":"US",
    "sg:address":"42444 23rd St W",
    "sg:city":"Lancaster",
    "sg:classifiers":[
        {
            "category":"Shopping",
            "type":"Retail Goods"
        },
        {
            "category":"Retail",
            "subcategory":"Animal Services",
            "type":"Services"
        }
    ],
    "sg:phone":"+1 661 943 1764",
    "sg:postcode":"93536",
    "sg:province":"CA",
    "sg:tags":[
        "pet",
        "shop"
    ],
    "wof:name":"Magic Mirror Pet Grooming",
    "wof:placetype":"venue"
},
  "geometry": {"coordinates":[-118.172172,34.655856],"type":"Point"}
}