{
  "type": "Feature",
  "properties": {
    "iso:country":"US",
    "sg:address":"853 E Valley Blvd",
    "sg:city":"San Gabriel",
    "sg:classifiers":[
        {
            "category":"Professional",
            "subcategory":"Accounting & Tax Preparation",
            "type":"Services"
        }
    ],
    "sg:phone":"+1 626 288 9906",
    "sg:postcode":"91776",
    "sg:province":"CA",
    "sg:tags":[
        "accountant"
    ],
    "wof:name":"Incorporation Co",
    "wof:placetype":"venue"
},
  "geometry": {"coordinates":[-118.08899700000001,34.0802],"type":"Point"}
}