{
  "type": "Feature",
  "properties": {
    "addr:full":"580 Ash St Brentwood CA 94513",
    "addr:housenumber":"580",
    "addr:postcode":"ca 94513",
    "addr:street":"Ash St",
    "iso:country":"US",
    "sg:address":"580 Ash St",
    "sg:city":"Brentwood",
    "sg:classifiers":[
        {
            "category":"Shopping",
            "subcategory":"Pets & Pet Supplies",
            "type":"Retail Goods"
        }
    ],
    "sg:phone":"+1 925 513 0649",
    "sg:postcode":"94513",
    "sg:province":"CA",
    "sg:tags":[
        "furnishing",
        "dog",
        "store",
        "cat"
    ],
    "wof:name":"Play Pals Pet Services",
    "wof:placetype":"venue"
},
  "geometry": {"coordinates":[-121.68600499999999,37.92822],"type":"Point"}
}