{
  "type": "Feature",
  "properties": {
    "iso:country":"US",
    "sg:address":"258 Barber Ct",
    "sg:city":"Milpitas",
    "sg:classifiers":[
        {
            "category":"Banks & Credit Unions",
            "subcategory":"Bank",
            "type":"Services"
        }
    ],
    "sg:phone":"+1 408 955 7288",
    "sg:postcode":"95035",
    "sg:province":"CA",
    "wof:name":"China Trust Bank",
    "wof:placetype":"venue"
},
  "geometry": {"coordinates":[-121.918999,37.423401],"type":"Point"}
}