{
  "type": "Feature",
  "properties": {
    "iso:country":"US",
    "sg:address":"3434 Midway Dr",
    "sg:city":"San Diego",
    "sg:classifiers":[
        {
            "category":"Health Services",
            "subcategory":"Doctor",
            "type":"Services"
        }
    ],
    "sg:phone":"+1 619 226 6685",
    "sg:postcode":"92110",
    "sg:province":"CA",
    "sg:tags":[
        "physician",
        "surgeon"
    ],
    "wof:name":"Artemis Internal Medicine",
    "wof:placetype":"venue"
},
  "geometry": {"coordinates":[-117.212965,32.750865],"type":"Point"}
}