{
  "type": "Feature",
  "properties": {
    "addr:full":"245 N 8th St Brawley CA 92227",
    "addr:housenumber":"245",
    "addr:postcode":"92227",
    "addr:street":"N 8Th St",
    "iso:country":"US",
    "sg:address":"245 N 8th St",
    "sg:city":"Brawley",
    "sg:classifiers":[
        {
            "category":"Home & Garden",
            "subcategory":"Building Materials",
            "type":"Retail Goods"
        }
    ],
    "sg:phone":"+1 760 344 1250",
    "sg:postcode":"92227",
    "sg:province":"CA",
    "sg:tags":[
        "lumber"
    ],
    "wof:name":"Valley Ace Lumber & Hardware",
    "wof:placetype":"venue"
},
  "geometry": {"coordinates":[-115.530002,32.9804],"type":"Point"}
}