{
  "type": "Feature",
  "properties": {
    "addr:full":"676 S. State College Blvd. Suite 103 Anaheim CA 92806",
    "addr:housenumber":"676",
    "addr:postcode":"92806",
    "addr:street":"S. State College Blvd. Suite 103",
    "iso:country":"US",
    "sg:address":"676 S. State College Blvd. Suite 103",
    "sg:city":"Anaheim",
    "sg:classifiers":[
        {
            "category":"Restaurant",
            "type":"Food & Drink"
        }
    ],
    "sg:phone":"+1 714 774 1243",
    "sg:postcode":"92806",
    "sg:province":"CA",
    "sg:tags":[
        "barbeque"
    ],
    "sg:website":"www.smokehousebbqribs.com",
    "wof:name":"Smokehouse Barbecue",
    "wof:placetype":"venue"
},
  "geometry": {"coordinates":[-117.888868,33.833034],"type":"Point"}
}