{
  "type": "Feature",
  "properties": {
    "iso:country":"US",
    "sg:address":"2839 Wilshire Blvd",
    "sg:city":"Santa Monica",
    "sg:classifiers":[
        {
            "category":"Shopping",
            "subcategory":"Jewelry",
            "type":"Retail Goods"
        }
    ],
    "sg:phone":"+1 310 829 0605",
    "sg:postcode":"90403",
    "sg:province":"CA",
    "sg:tags":[
        "jeweler"
    ],
    "wof:name":"Yale Jewelers",
    "wof:placetype":"venue"
},
  "geometry": {"coordinates":[-118.475037,34.038053],"type":"Point"}
}