{
  "type": "Feature",
  "properties": {
    "iso:country":"US",
    "sg:address":"7363 Sunset Blvd",
    "sg:city":"Los Angeles",
    "sg:classifiers":[
        {
            "category":"Restaurant",
            "type":"Food & Drink"
        }
    ],
    "sg:phone":"+1 323 876 5959",
    "sg:postcode":"90046",
    "sg:province":"CA",
    "sg:tags":[
        "thai",
        "vegetarian"
    ],
    "wof:name":"Sanzab Restaurant",
    "wof:placetype":"venue"
},
  "geometry": {"coordinates":[-118.35052,34.09803],"type":"Point"}
}