{
  "type": "Feature",
  "properties": {
    "addr:full":"10040 Lurline Ave Chatsworth CA 91311",
    "addr:housenumber":"10040",
    "addr:postcode":"91311",
    "addr:street":"Lurline Ave",
    "iso:country":"US",
    "sg:address":"10040 Lurline Ave",
    "sg:city":"Chatsworth",
    "sg:classifiers":[
        {
            "category":"Shopping",
            "subcategory":"Catalog Store",
            "type":"Retail Goods"
        }
    ],
    "sg:phone":"+1 818 576 0085",
    "sg:postcode":"91311",
    "sg:province":"CA",
    "sg:tags":[
        "antique",
        "mail",
        "house"
    ],
    "wof:name":"Collectible First",
    "wof:placetype":"venue"
},
  "geometry": {"coordinates":[-118.584187,34.252541],"type":"Point"}
}