{
  "type": "Feature",
  "properties": {
    "iso:country":"US",
    "sg:address":"884 Bodega Ave",
    "sg:city":"Petaluma",
    "sg:classifiers":[
        {
            "category":"Wholesale",
            "subcategory":"Non-durable Goods",
            "type":"Manufacturing & Wholesale Goods"
        }
    ],
    "sg:phone":"+1 707 763 0285",
    "sg:postcode":"94952",
    "sg:province":"CA",
    "wof:name":"Coastal Bait",
    "wof:placetype":"venue"
},
  "geometry": {"coordinates":[-122.659816,38.234707],"type":"Point"}
}