{
  "type": "Feature",
  "properties": {
    "addr:full":"3415 Cerritos Ave Los Alamitos CA 90720",
    "addr:housenumber":"3415",
    "addr:postcode":"90720",
    "addr:street":"Cerritos Ave",
    "iso:country":"US",
    "sg:address":"3415 Cerritos Ave",
    "sg:city":"Los Alamitos",
    "sg:classifiers":[
        {
            "category":"Professional",
            "subcategory":"Accounting & Tax Preparation",
            "type":"Services"
        }
    ],
    "sg:phone":"+1 562 799 4975",
    "sg:postcode":"90720",
    "sg:province":"CA",
    "sg:tags":[
        "accountant"
    ],
    "wof:name":"Liewald Accounting & Consulting Corp",
    "wof:placetype":"venue"
},
  "geometry": {"coordinates":[-118.06999999999999,33.810501],"type":"Point"}
}