{
  "type": "Feature",
  "properties": {
    "addr:full":"1710 S Amphlett Blvd San Mateo CA 94402",
    "addr:housenumber":"1710",
    "addr:postcode":"94402",
    "addr:street":"S Amphlett Blvd",
    "iso:country":"US",
    "sg:address":"1710 S Amphlett Blvd",
    "sg:city":"San Mateo",
    "sg:classifiers":[
        {
            "category":"Shopping",
            "subcategory":"Catalog Store",
            "type":"Retail Goods"
        }
    ],
    "sg:phone":"+1 650 578 6500",
    "sg:postcode":"94402",
    "sg:province":"CA",
    "sg:tags":[
        "e"
    ],
    "wof:name":"VIP Tone Inc",
    "wof:placetype":"venue"
},
  "geometry": {"coordinates":[-122.30103800000001,37.557898],"type":"Point"}
}