{
  "type": "Feature",
  "properties": {
    "addr:full":"30 E San Joaquin St Salinas CA 93901",
    "addr:housenumber":"30",
    "addr:postcode":"93901",
    "addr:street":"E San Joaquin St",
    "iso:country":"US",
    "sg:address":"30 E San Joaquin St",
    "sg:city":"Salinas",
    "sg:classifiers":[
        {
            "category":"Insurance",
            "subcategory":"Hazard Insurance",
            "type":"Services"
        }
    ],
    "sg:phone":"+1 831 758 8222",
    "sg:postcode":"93901",
    "sg:province":"CA",
    "wof:name":"Aflac",
    "wof:placetype":"venue"
},
  "geometry": {"coordinates":[-121.658171,36.658669],"type":"Point"}
}