{
  "type": "Feature",
  "properties": {
    "addr:full":"19435 Soledad Canyon Rd Santa Clarita CA 91351",
    "addr:housenumber":"19435",
    "addr:postcode":"91351",
    "addr:street":"Soledad Canyon Rd",
    "iso:country":"US",
    "sg:address":"19435 Soledad Canyon Rd",
    "sg:city":"Santa Clarita",
    "sg:classifiers":[
        {
            "category":"Restaurant",
            "type":"Food & Drink"
        }
    ],
    "sg:phone":"+1 661 299 6710",
    "sg:postcode":"91351",
    "sg:province":"CA",
    "sg:tags":[
        "shop",
        "tea",
        "coffee"
    ],
    "sg:website":"starbucks.com",
    "wof:name":"Starbucks",
    "wof:placetype":"venue"
},
  "geometry": {"coordinates":[-118.47512,34.415802],"type":"Point"}
}