{
  "type": "Feature",
  "properties": {
    "addr:full":"18835 State Rte 65 Bakersfield CA 93308",
    "addr:housenumber":"18835",
    "addr:postcode":"ca 93308",
    "addr:street":"State Rte 65",
    "iso:country":"US",
    "sg:address":"18835 State Rte 65",
    "sg:city":"Bakersfield",
    "sg:classifiers":[
        {
            "category":"Mining & Drilling",
            "type":"Manufacturing & Wholesale Goods"
        }
    ],
    "sg:phone":"+1 661 399 0621",
    "sg:postcode":"93308",
    "sg:province":"CA",
    "sg:tags":[
        "field",
        "exploration"
    ],
    "wof:name":"Dawson Production Services",
    "wof:placetype":"venue"
},
  "geometry": {"coordinates":[-119.074575,35.465849],"type":"Point"}
}