{
  "type": "Feature",
  "properties": {
    "iso:country":"US",
    "sg:address":"720 W Whittier Blvd",
    "sg:city":"Montebello",
    "sg:classifiers":[
        {
            "category":"Utilities",
            "subcategory":"Mobile Phone",
            "type":"Services"
        },
        {
            "category":"Shopping",
            "subcategory":"Mobile Phones",
            "type":"Retail Goods"
        },
        {
            "category":"Communications",
            "type":"Services"
        },
        {
            "category":"Internet Cafe",
            "subcategory":"None",
            "type":"Food & Drink"
        }
    ],
    "sg:phone":"+1 323 724 8601",
    "sg:postcode":"90640",
    "sg:province":"CA",
    "sg:tags":[
        "supply",
        "telephone",
        "wireless",
        "equipment",
        "paging",
        "signaling",
        "cellular",
        "provider"
    ],
    "sg:website":"http://www.att.com",
    "wof:name":"AT&T",
    "wof:placetype":"venue"
},
  "geometry": {"coordinates":[-118.10770100000001,34.009958],"type":"Point"}
}