{
  "type": "Feature",
  "properties": {
    "iso:country":"US",
    "sg:address":"7562 Ellis Ave",
    "sg:city":"Huntington Beach",
    "sg:classifiers":[
        {
            "category":"Retail",
            "subcategory":"Auto Repair",
            "type":"Services"
        }
    ],
    "sg:phone":"+1 714 841 1008",
    "sg:postcode":"92648",
    "sg:province":"CA",
    "sg:tags":[
        "automobile",
        "customizing"
    ],
    "wof:name":"American Roadster",
    "wof:placetype":"venue"
},
  "geometry": {"coordinates":[-117.997543,33.693487],"type":"Point"}
}