{
  "type": "Feature",
  "properties": {
    "addr:full":"6970 el Cajon Blvd San Diego CA 92115",
    "addr:housenumber":"6970",
    "addr:postcode":"92115",
    "addr:street":"El Cajon Blvd",
    "iso:country":"US",
    "sg:address":"6970 el Cajon Blvd",
    "sg:city":"San Diego",
    "sg:classifiers":[
        {
            "category":"Retail",
            "subcategory":"Auto Repair",
            "type":"Services"
        }
    ],
    "sg:phone":"+1 619 433 3729",
    "sg:postcode":"92115",
    "sg:province":"CA",
    "sg:tags":[
        "wrecker"
    ],
    "wof:name":"Anywhere Towing",
    "wof:placetype":"venue"
},
  "geometry": {"coordinates":[-117.048455,32.768742],"type":"Point"}
}