{
  "type": "Feature",
  "properties": {
    "addr:full":"8554 Gibson Ranch Rd Elverta CA 95626",
    "addr:housenumber":"8554",
    "addr:postcode":"ca 95626",
    "addr:street":"Gibson Ranch Rd",
    "iso:country":"US",
    "sg:address":"8554 Gibson Ranch Rd",
    "sg:city":"Elverta",
    "sg:classifiers":[
        {
            "category":"Recreation",
            "type":"Entertainment"
        }
    ],
    "sg:phone":"+1 916 875 6961",
    "sg:postcode":"95626",
    "sg:province":"CA",
    "sg:tags":[
        "center"
    ],
    "wof:name":"Gibson Ranch County Park",
    "wof:placetype":"venue"
},
  "geometry": {"coordinates":[-121.402804,38.728314],"type":"Point"}
}