{
  "type": "Feature",
  "properties": {
    "iso:country":"US",
    "sg:address":"318 W Redondo Beach Blvd",
    "sg:city":"Gardena",
    "sg:classifiers":[
        {
            "category":"Autos & Motor Vehicles",
            "subcategory":"Automobile Sales",
            "type":"Retail Goods"
        }
    ],
    "sg:phone":"+1 310 677 3798",
    "sg:postcode":"90248",
    "sg:province":"CA",
    "sg:tags":[
        "used",
        "car",
        "dealers-used",
        "new",
        "cars-wholesale"
    ],
    "wof:name":"Gus' Auto & Motorcycle Sales",
    "wof:placetype":"venue"
},
  "geometry": {"coordinates":[-118.27932,33.892838],"type":"Point"}
}