{
  "type": "Feature",
  "properties": {
    "iso:country":"US",
    "sg:address":"1360 White Oaks Rd",
    "sg:city":"Campbell",
    "sg:classifiers":[
        {
            "category":"Home & Garden",
            "subcategory":"Home Furnishings",
            "type":"Retail Goods"
        },
        {
            "category":"Building & Trades",
            "subcategory":"Construction",
            "type":"Services"
        }
    ],
    "sg:phone":"+1 408 559 7606",
    "sg:postcode":"95008",
    "sg:province":"CA",
    "sg:tags":[
        "interior",
        "decor",
        "design"
    ],
    "sg:website":"www.greennsilk.com",
    "wof:name":"Green N' Silk",
    "wof:placetype":"venue"
},
  "geometry": {"coordinates":[-121.946949,37.267708],"type":"Point"}
}