{
  "type": "Feature",
  "properties": {
    "iso:country":"US",
    "sg:address":"26202 Heritage Union Ln",
    "sg:city":"Murrieta",
    "sg:classifiers":[
        {
            "category":"Professional",
            "subcategory":"Business Services",
            "type":"Services"
        }
    ],
    "sg:phone":"+1 951 461 8500",
    "sg:postcode":"92563",
    "sg:province":"CA",
    "sg:tags":[
        "appraiser"
    ],
    "wof:name":"Greenlight Appraisals",
    "wof:placetype":"venue"
},
  "geometry": {"coordinates":[-117.15657899999999,33.553449],"type":"Point"}
}