{
  "type": "Feature",
  "properties": {
    "iso:country":"US",
    "sg:address":"10306 Mills Station Rd",
    "sg:city":"Rancho Cordova",
    "sg:classifiers":[
        {
            "category":"Professional",
            "type":"Services"
        }
    ],
    "sg:phone":"+1 916 363 9554",
    "sg:postcode":"95670",
    "sg:province":"CA",
    "wof:name":"Marina Mitsura",
    "wof:placetype":"venue"
},
  "geometry": {"coordinates":[-121.306555,38.585634],"type":"Point"}
}