{
  "type": "Feature",
  "properties": {
    "iso:country":"US",
    "sg:address":"960 S 1st St Ste A",
    "sg:city":"San Jose",
    "sg:classifiers":[
        {
            "category":"Restaurant",
            "type":"Food & Drink"
        }
    ],
    "sg:phone":"+1 408 283 1219",
    "sg:postcode":"95110",
    "sg:province":"CA",
    "sg:tags":[
        "mexican"
    ],
    "wof:name":"El Pike",
    "wof:placetype":"venue"
},
  "geometry": {"coordinates":[-121.872091,37.314458],"type":"Point"}
}