{
  "type": "Feature",
  "properties": {
    "addr:full":"11189 Walnut St Bloomington CA 92316",
    "addr:housenumber":"11189",
    "addr:postcode":"92316",
    "addr:street":"Walnut St",
    "iso:country":"US",
    "sg:address":"11189 Walnut St",
    "sg:city":"Bloomington",
    "sg:classifiers":[
        {
            "category":"Building & Trades",
            "subcategory":"Construction",
            "type":"Services"
        }
    ],
    "sg:phone":"+1 909 877 0451",
    "sg:postcode":"92316",
    "sg:province":"CA",
    "sg:tags":[
        "masonry",
        "contractor"
    ],
    "wof:name":"Musgrove Construction",
    "wof:placetype":"venue"
},
  "geometry": {"coordinates":[-117.385468,34.049726],"type":"Point"}
}