{
  "type": "Feature",
  "properties": {
    "addr:full":"422 Colin Kelly Dr Roseville CA 95747",
    "addr:housenumber":"422",
    "addr:postcode":"95747",
    "addr:street":"Colin Kelly Dr",
    "iso:country":"US",
    "sg:address":"422 Colin Kelly Dr",
    "sg:city":"Roseville",
    "sg:classifiers":[
        {
            "category":"Freight",
            "type":"Transportation"
        }
    ],
    "sg:phone":"+1 916 771 0367",
    "sg:postcode":"95747",
    "sg:province":"CA",
    "sg:tags":[
        "operator",
        "trucking"
    ],
    "wof:name":"Fred Collins",
    "wof:placetype":"venue"
},
  "geometry": {"coordinates":[-121.35842100000001,38.726498],"type":"Point"}
}