{
  "type": "Feature",
  "properties": {
    "addr:full":"1850 Union Street #6 San Francisco CA 94123",
    "addr:housenumber":"1850",
    "addr:postcode":"94123",
    "addr:street":"Union Street # 6",
    "iso:country":"US",
    "sg:address":"1850 Union Street #6",
    "sg:city":"San Francisco",
    "sg:classifiers":[
        {
            "category":"Health Services",
            "subcategory":"Clinic",
            "type":"Services"
        }
    ],
    "sg:phone":"+1 415 613 6507",
    "sg:postcode":"94123",
    "sg:province":"CA",
    "sg:tags":[
        "counseling",
        "medical",
        "mental",
        "spa"
    ],
    "sg:website":"www.thehealingreunion.com",
    "wof:name":"Body-Mind-Movement",
    "wof:placetype":"venue"
},
  "geometry": {"coordinates":[-122.429703,37.798251],"type":"Point"}
}