{
  "type": "Feature",
  "properties": {
    "addr:full":"71680 Highway 111 Rancho Mirage CA 92270",
    "addr:housenumber":"71680",
    "addr:postcode":"92270",
    "addr:street":"Highway 111",
    "iso:country":"US",
    "sg:address":"71680 Highway 111",
    "sg:city":"Rancho Mirage",
    "sg:classifiers":[
        {
            "category":"Personal",
            "subcategory":"Nail Salon",
            "type":"Services"
        }
    ],
    "sg:phone":"+1 760 341 0654",
    "sg:postcode":"92270",
    "sg:province":"CA",
    "wof:name":"Fashion Nails",
    "wof:placetype":"venue"
},
  "geometry": {"coordinates":[-116.412003,33.741199],"type":"Point"}
}