{
  "type": "Feature",
  "properties": {
    "addr:full":"1210 E Hammer Ln Stockton CA 95210",
    "addr:housenumber":"1210",
    "addr:postcode":"95210",
    "addr:street":"E Hammer Ln",
    "iso:country":"US",
    "sg:address":"1210 E Hammer Ln",
    "sg:city":"Stockton",
    "sg:classifiers":[
        {
            "category":"Mining & Drilling",
            "type":"Manufacturing & Wholesale Goods"
        }
    ],
    "sg:phone":"+1 209 477 3111",
    "sg:postcode":"95210",
    "sg:province":"CA",
    "sg:tags":[
        "oil",
        "gas",
        "producer"
    ],
    "wof:name":"Beacon",
    "wof:placetype":"venue"
},
  "geometry": {"coordinates":[-121.29691800000001,38.020842],"type":"Point"}
}