{
  "type": "Feature",
  "properties": {
    "iso:country":"US",
    "sg:address":"1231 Wilshire Blvd",
    "sg:city":"Santa Monica",
    "sg:classifiers":[
        {
            "category":"Bakery",
            "type":"Food & Drink"
        }
    ],
    "sg:menulink":"http://www.allmenus.com/ca/santa-monica/114352-krispy-kreme/menu/",
    "sg:phone":"+1 310 393 8319",
    "sg:postcode":"90403",
    "sg:province":"CA",
    "sg:tags":[
        "american",
        "pastry"
    ],
    "wof:name":"Krispy Kreme",
    "wof:placetype":"venue"
},
  "geometry": {"coordinates":[-118.49004600000001,34.025797],"type":"Point"}
}