{
  "type": "Feature",
  "properties": {
    "iso:country":"US",
    "sg:address":"180 Coombs St",
    "sg:city":"Napa",
    "sg:classifiers":[
        {
            "category":"Building & Trades",
            "subcategory":"Construction",
            "type":"Services"
        }
    ],
    "sg:phone":"+1 707 255 8090",
    "sg:postcode":"94559",
    "sg:province":"CA",
    "sg:tags":[
        "roofing",
        "contractor"
    ],
    "sg:website":"www.modernmethodroofing.com",
    "wof:name":"Modern Method Roofing Co",
    "wof:placetype":"venue"
},
  "geometry": {"coordinates":[-122.286772,38.28775],"type":"Point"}
}