{
  "type": "Feature",
  "properties": {
    "addr:full":"11934 Foothill Blvd Sylmar CA 91342",
    "addr:housenumber":"11934",
    "addr:postcode":"91342",
    "addr:street":"Foothill Blvd",
    "iso:country":"US",
    "sg:address":"11934 Foothill Blvd",
    "sg:city":"Sylmar",
    "sg:classifiers":[
        {
            "category":"Personal",
            "subcategory":"Barber",
            "type":"Services"
        }
    ],
    "sg:phone":"+1 818 834 9965",
    "sg:postcode":"91342",
    "sg:province":"CA",
    "wof:name":"James's House Of Style",
    "wof:placetype":"venue"
},
  "geometry": {"coordinates":[-118.39829,34.277329],"type":"Point"}
}