{
  "type": "Feature",
  "properties": {
    "addr:full":"1380 el Camino Real Menlo Park CA 94025",
    "addr:housenumber":"1380",
    "addr:postcode":"94025",
    "addr:street":"El Camino Real",
    "iso:country":"US",
    "sg:address":"1380 el Camino Real",
    "sg:city":"Menlo Park",
    "sg:classifiers":[
        {
            "category":"Autos & Motor Vehicles",
            "subcategory":"Fuel & Gas Station",
            "type":"Retail Goods"
        }
    ],
    "sg:phone":"+1 650 328 9726",
    "sg:postcode":"94025",
    "sg:province":"CA",
    "sg:tags":[
        "oil"
    ],
    "wof:name":"George & Bob's Svc",
    "wof:placetype":"venue"
},
  "geometry": {"coordinates":[-122.18514,37.454692],"type":"Point"}
}