{
  "type": "Feature",
  "properties": {
    "addr:full":"10760 Valley Spring Ln North Hollywood CA 91602",
    "addr:housenumber":"10760",
    "addr:postcode":"91602",
    "addr:street":"Valley Spring Ln",
    "iso:country":"US",
    "sg:address":"10760 Valley Spring Ln",
    "sg:city":"North Hollywood",
    "sg:classifiers":[
        {
            "category":"Shopping",
            "subcategory":"Music",
            "type":"Retail Goods"
        }
    ],
    "sg:phone":"+1 818 763 1689",
    "sg:postcode":"91602",
    "sg:province":"CA",
    "wof:name":"QED Communications",
    "wof:placetype":"venue"
},
  "geometry": {"coordinates":[-118.36585100000001,34.146666],"type":"Point"}
}