{
  "type": "Feature",
  "properties": {
    "addr:full":"7130 Valeriana Ave Citrus Heights CA 95621",
    "addr:postcode":"7130;95621",
    "addr:street":"Valeriana Ave",
    "iso:country":"US",
    "sg:address":"7130 Valeriana Ave",
    "sg:city":"Citrus Heights",
    "sg:classifiers":[
        {
            "category":"Retail",
            "subcategory":"Laundry & Dry Cleaning",
            "type":"Services"
        }
    ],
    "sg:phone":"+1 916 727 3578",
    "sg:postcode":"95621",
    "sg:province":"CA",
    "sg:tags":[
        "cleaners",
        "rug",
        "carpet"
    ],
    "wof:name":"Nelson's Carpet & Upholstery",
    "wof:placetype":"venue"
},
  "geometry": {"coordinates":[-121.30177999999999,38.705627],"type":"Point"}
}