{
  "type": "Feature",
  "properties": {
    "iso:country":"US",
    "sg:address":"3rd and Vermont",
    "sg:city":"Los Angeles",
    "sg:classifiers":[
        {
            "category":"Restaurant",
            "type":"Food & Drink"
        }
    ],
    "sg:postcode":"90020",
    "sg:province":"CA",
    "sg:tags":[
        "mexican"
    ],
    "wof:name":"Julio's Taco Truck",
    "wof:placetype":"venue"
},
  "geometry": {"coordinates":[-118.291645,34.06904],"type":"Point"}
}