{
  "type": "Feature",
  "properties": {
    "addr:full":"2191 Zanker Rd San Jose CA 95134",
    "addr:housenumber":"2191",
    "addr:postcode":"95134",
    "addr:street":"Zanker Rd",
    "iso:country":"US",
    "sg:address":"2191 Zanker Rd",
    "sg:city":"San Jose",
    "sg:classifiers":[
        {
            "category":"Wholesale",
            "subcategory":"Electrical",
            "type":"Manufacturing & Wholesale Goods"
        }
    ],
    "sg:phone":"+1 408 750 2500",
    "sg:postcode":"95134",
    "sg:province":"CA",
    "sg:tags":[
        "communication",
        "radio",
        "system"
    ],
    "sg:website":"www.rfmd.com",
    "wof:name":"Rf Micro Devices Inc",
    "wof:placetype":"venue"
},
  "geometry": {"coordinates":[-121.91345699999999,37.377458],"type":"Point"}
}