{
  "type": "Feature",
  "properties": {
    "addr:full":"1826 S School St Lodi CA 95240",
    "addr:housenumber":"1826",
    "addr:postcode":"95240",
    "addr:street":"S School St",
    "iso:country":"US",
    "sg:address":"1826 S School St",
    "sg:city":"Lodi",
    "sg:classifiers":[
        {
            "category":"Building & Trades",
            "subcategory":"Construction",
            "type":"Services"
        }
    ],
    "sg:phone":"+1 209 367 9405",
    "sg:postcode":"95240",
    "sg:province":"CA",
    "sg:tags":[
        "repairing",
        "remodeling",
        "contractor"
    ],
    "wof:name":"JWS Construction",
    "wof:placetype":"venue"
},
  "geometry": {"coordinates":[-121.275021,38.112795],"type":"Point"}
}