{
  "type": "Feature",
  "properties": {
    "addr:full":"Ocean & San Carlos Carmel-by-the-Sea CA 93922",
    "addr:postcode":"93922",
    "iso:country":"US",
    "sg:address":"Ocean & San Carlos",
    "sg:city":"Carmel-by-the-Sea",
    "sg:classifiers":[
        {
            "category":"Real Estate",
            "subcategory":"Real Estate Services",
            "type":"Services"
        }
    ],
    "sg:phone":"+1 831 625 5217",
    "sg:postcode":"93922",
    "sg:province":"CA",
    "sg:website":"www.carmelrentals.net",
    "wof:name":"Carmel Rentals",
    "wof:placetype":"venue"
},
  "geometry": {"coordinates":[-121.921807,36.5551],"type":"Point"}
}