{
  "type": "Feature",
  "properties": {
    "iso:country":"US",
    "sg:address":"5020 Baltimore Dr",
    "sg:city":"La Mesa",
    "sg:classifiers":[
        {
            "category":"Insurance",
            "subcategory":"Insurance Agent",
            "type":"Services"
        }
    ],
    "sg:phone":"+1 619 337 2724",
    "sg:postcode":"91941",
    "sg:province":"CA",
    "sg:tags":[
        "adjuster"
    ],
    "wof:name":"California Casualty Insur Co",
    "wof:placetype":"venue"
},
  "geometry": {"coordinates":[-117.026788,32.77192],"type":"Point"}
}