{
  "type": "Feature",
  "properties": {
    "iso:country":"US",
    "sg:address":"13505 Hawthorne Blvd",
    "sg:city":"Hawthorne",
    "sg:classifiers":[
        {
            "category":"Health Services",
            "subcategory":"Dentist",
            "type":"Services"
        }
    ],
    "sg:phone":"+1 310 970 0584",
    "sg:postcode":"90250",
    "sg:province":"CA",
    "wof:name":"Schnierow Burton DDS",
    "wof:placetype":"venue"
},
  "geometry": {"coordinates":[-118.352915,33.909729],"type":"Point"}
}