{
  "type": "Feature",
  "properties": {
    "iso:country":"US",
    "sg:address":"5961 Fiddletown Pl",
    "sg:city":"San Jose",
    "sg:classifiers":[
        {
            "category":"Professional",
            "subcategory":"Management & Consulting",
            "type":"Services"
        }
    ],
    "sg:phone":"+1 408 268 6810",
    "sg:postcode":"95120",
    "sg:province":"CA",
    "sg:tags":[
        "consultant",
        "construction"
    ],
    "wof:name":"Bearden Len Construction",
    "wof:placetype":"venue"
},
  "geometry": {"coordinates":[-121.882667,37.233263],"type":"Point"}
}