{
  "type": "Feature",
  "properties": {
    "addr:full":"8400 Melrose Pl Los Angeles CA 90069",
    "addr:housenumber":"8400",
    "addr:postcode":"90069",
    "addr:street":"Melrose Pl",
    "iso:country":"US",
    "sg:address":"8400 Melrose Pl",
    "sg:city":"Los Angeles",
    "sg:classifiers":[
        {
            "category":"Shopping",
            "subcategory":"Used Merchandise",
            "type":"Retail Goods"
        }
    ],
    "sg:phone":"+1 323 655 6969",
    "sg:postcode":"90069",
    "sg:province":"CA",
    "sg:tags":[
        "antique"
    ],
    "wof:name":"Rosh Antique Galleries",
    "wof:placetype":"venue"
},
  "geometry": {"coordinates":[-118.373555,34.083631],"type":"Point"}
}