{
  "type": "Feature",
  "properties": {
    "iso:country":"US",
    "sg:address":"4601 E Main St",
    "sg:city":"Stockton",
    "sg:classifiers":[
        {
            "category":"Organizations",
            "subcategory":"Religious Organization",
            "type":"Services"
        }
    ],
    "sg:phone":"+1 209 465 4400",
    "sg:postcode":"95215",
    "sg:province":"CA",
    "sg:tags":[
        "church"
    ],
    "wof:name":"Jehovah's Witnesses",
    "wof:placetype":"venue"
},
  "geometry": {"coordinates":[-121.228501,37.955397],"type":"Point"}
}