{
  "type": "Feature",
  "properties": {
    "iso:country":"US",
    "sg:address":"2732 Mission St",
    "sg:city":"San Francisco",
    "sg:classifiers":[
        {
            "category":"Restaurant",
            "type":"Food & Drink"
        }
    ],
    "sg:menulink":"http://www.allmenus.com/ca/san-francisco/63177-china-express-deli/menu/",
    "sg:phone":"+1 415 821 3375",
    "sg:postcode":"94110",
    "sg:province":"CA",
    "sg:tags":[
        "asian",
        "chinese"
    ],
    "wof:name":"China Express Deli",
    "wof:placetype":"venue"
},
  "geometry": {"coordinates":[-122.418572,37.753315],"type":"Point"}
}