{
  "type": "Feature",
  "properties": {
    "addr:full":"16624 Marquez Ave Pacific Plsds CA 90272",
    "addr:housenumber":"16624",
    "addr:postcode":"90272",
    "addr:street":"Marquez Ave",
    "iso:country":"US",
    "sg:address":"16624 Marquez Ave",
    "sg:city":"Pacific Plsds",
    "sg:classifiers":[
        {
            "category":"Health Services",
            "subcategory":"Chiropractor",
            "type":"Services"
        }
    ],
    "sg:phone":"+1 310 230 1899",
    "sg:postcode":"90272",
    "sg:province":"CA",
    "sg:website":"www.innatechiropractic.net",
    "wof:name":"Innate Chiropractic Ctr",
    "wof:placetype":"venue"
},
  "geometry": {"coordinates":[-118.54453700000001,34.048045],"type":"Point"}
}