{
  "type": "Feature",
  "properties": {
    "iso:country":"US",
    "sg:address":"36441 Turner Dr",
    "sg:city":"Palmdale",
    "sg:classifiers":[
        {
            "category":"Building & Trades",
            "subcategory":"Plumbing",
            "type":"Services"
        }
    ],
    "sg:phone":"+1 661 274 8865",
    "sg:postcode":"93550",
    "sg:province":"CA",
    "sg:tags":[
        "conditioning",
        "air",
        "system",
        "contractor"
    ],
    "wof:name":"Pierce Heating & Air Cond Co",
    "wof:placetype":"venue"
},
  "geometry": {"coordinates":[-118.079356,34.543679],"type":"Point"}
}