{
  "type": "Feature",
  "properties": {
    "iso:country":"US",
    "sg:address":"45846 Flower St",
    "sg:city":"Indio",
    "sg:classifiers":[
        {
            "category":"Building & Trades",
            "subcategory":"Construction",
            "type":"Services"
        }
    ],
    "sg:phone":"+1 760 775 4755",
    "sg:postcode":"92201",
    "sg:province":"CA",
    "sg:tags":[
        "tile",
        "dealer"
    ],
    "wof:name":"De Jager Ceramic Tile Images",
    "wof:placetype":"venue"
},
  "geometry": {"coordinates":[-116.211747,33.716967],"type":"Point"}
}