{
  "type": "Feature",
  "properties": {
    "addr:full":"9814 Magnolia Ave Riverside CA 92503",
    "addr:housenumber":"9814",
    "addr:postcode":"92503",
    "addr:street":"Magnolia Ave",
    "iso:country":"US",
    "sg:address":"9814 Magnolia Ave",
    "sg:city":"Riverside",
    "sg:phone":"+1 951 687 4882",
    "sg:postcode":"92503",
    "sg:province":"CA",
    "wof:name":"Gerard's French Restaurant",
    "wof:placetype":"venue"
},
  "geometry": {"coordinates":[-117.452297,33.916992],"type":"Point"}
}