{
  "type": "Feature",
  "properties": {
    "iso:country":"US",
    "sg:address":"16776 Lakeshore Dr",
    "sg:city":"Lake Elsinore",
    "sg:classifiers":[
        {
            "category":"Home & Garden",
            "subcategory":"Household Appliances",
            "type":"Retail Goods"
        }
    ],
    "sg:phone":"+1 951 676 2754",
    "sg:postcode":"92530",
    "sg:province":"CA",
    "sg:tags":[
        "repair"
    ],
    "wof:name":"Appliance Quick Service",
    "wof:placetype":"venue"
},
  "geometry": {"coordinates":[-117.36799600000001,33.6852],"type":"Point"}
}