{
  "type": "Feature",
  "properties": {
    "addr:full":"932 Holly Ave Rohnert Park CA 94928",
    "addr:housenumber":"932",
    "addr:postcode":"94928",
    "addr:street":"Holly Ave",
    "iso:country":"US",
    "sg:address":"932 Holly Ave",
    "sg:city":"Rohnert Park",
    "sg:classifiers":[
        {
            "category":"Building & Trades",
            "subcategory":"Plumbing",
            "type":"Services"
        }
    ],
    "sg:phone":"+1 707 584 5837",
    "sg:postcode":"94928",
    "sg:province":"CA",
    "sg:tags":[
        "fire",
        "installation",
        "sprinkler",
        "contractor"
    ],
    "wof:name":"Plumbers Plus Inc",
    "wof:placetype":"venue"
},
  "geometry": {"coordinates":[-122.695993,38.371793],"type":"Point"}
}