{
  "type": "Feature",
  "properties": {
    "addr:full":"9915 Whitaker Ave Sepulveda CA 91343",
    "addr:housenumber":"9915",
    "addr:postcode":"91343",
    "addr:street":"Whitaker Ave",
    "iso:country":"US",
    "sg:address":"9915 Whitaker Ave",
    "sg:city":"Sepulveda",
    "sg:classifiers":[
        {
            "category":"Building & Trades",
            "subcategory":"Construction",
            "type":"Services"
        }
    ],
    "sg:phone":"+1 818 892 8568",
    "sg:postcode":"91343",
    "sg:province":"CA",
    "sg:tags":[
        "contractor"
    ],
    "wof:name":"Stafford's General Contracting",
    "wof:placetype":"venue"
},
  "geometry": {"coordinates":[-118.499135,34.250624],"type":"Point"}
}