{
  "type": "Feature",
  "properties": {
    "addr:full":"2570 West El Camino Real Suite 230 Mountain View CA 94040 ",
    "addr:housenumber":"2570",
    "addr:postcode":"94040",
    "addr:street":"West El Camino Real Suite 230",
    "iso:country":"US",
    "sg:address":"2570 West El Camino Real Suite 230",
    "sg:city":"Mountain View",
    "sg:classifiers":[
        {
            "category":"Professional",
            "subcategory":"Computer Services",
            "type":"Services"
        }
    ],
    "sg:phone":"+1 877 310 2224",
    "sg:postcode":"94040 ",
    "sg:province":"CA",
    "sg:website":"http://www.atlantiscomputing.com",
    "wof:name":"Atlantis Computing",
    "wof:placetype":"venue"
},
  "geometry": {"coordinates":[-122.112236,37.400553],"type":"Point"}
}