{
  "type": "Feature",
  "properties": {
    "addr:full":"1435 E Cotati Ave Rohnert Park CA 94928",
    "addr:housenumber":"1435",
    "addr:postcode":"94928",
    "addr:street":"E Cotati Ave",
    "iso:country":"US",
    "sg:address":"1435 E Cotati Ave",
    "sg:city":"Rohnert Park",
    "sg:classifiers":[
        {
            "category":"Food & Beverages",
            "subcategory":"Groceries & Convenience Stores",
            "type":"Retail Goods"
        }
    ],
    "sg:phone":"+1 707 664 1639",
    "sg:postcode":"94928",
    "sg:province":"CA",
    "sg:tags":[
        "grocer"
    ],
    "wof:name":"A & L Market",
    "wof:placetype":"venue"
},
  "geometry": {"coordinates":[-122.68841999999999,38.333944],"type":"Point"}
}