{
  "type": "Feature",
  "properties": {
    "addr:full":"2941 El Camino Real Tustin CA 92782",
    "addr:housenumber":"2941",
    "addr:postcode":"92782",
    "addr:street":"El Camino Real",
    "iso:country":"US",
    "sg:address":"2941 El Camino Real",
    "sg:city":"Tustin",
    "sg:classifiers":[
        {
            "category":"Food & Beverages",
            "subcategory":"Bakery",
            "type":"Retail Goods"
        }
    ],
    "sg:phone":"+1 714 730 9338",
    "sg:postcode":"92782",
    "sg:province":"CA",
    "sg:tags":[
        "sandwich"
    ],
    "sg:website":"www.sandwichworld.net",
    "wof:name":"Sandwich World",
    "wof:placetype":"venue"
},
  "geometry": {"coordinates":[-117.79299899999999,33.723301],"type":"Point"}
}