{
  "type": "Feature",
  "properties": {
    "iso:country":"US",
    "sg:address":"1700 W Gardena Blvd",
    "sg:city":"Gardena",
    "sg:classifiers":[
        {
            "category":"Health Services",
            "subcategory":"Dentist",
            "type":"Services"
        }
    ],
    "sg:phone":"+1 310 323 3111",
    "sg:postcode":"90247",
    "sg:province":"CA",
    "wof:name":"Dote Michael DDS Inc",
    "wof:placetype":"venue"
},
  "geometry": {"coordinates":[-118.30696,33.881812],"type":"Point"}
}