{
  "type": "Feature",
  "properties": {
    "iso:country":"US",
    "sg:address":"1502 N St",
    "sg:city":"Franklin",
    "sg:classifiers":[
        {
            "category":"Real Estate",
            "subcategory":"Real Estate Services",
            "type":"Services"
        }
    ],
    "sg:phone":"+1 308 425 8821",
    "sg:postcode":"68939",
    "sg:province":"NE",
    "wof:name":"Sharon Freeland Real Estate",
    "wof:placetype":"venue"
},
  "geometry": {"coordinates":[-122.423566,37.788315],"type":"Point"}
}