{
  "type": "Feature",
  "properties": {
    "iso:country":"US",
    "sg:address":"259 3rd Ave",
    "sg:city":"Chula Vista",
    "sg:classifiers":[
        {
            "category":"Professional",
            "subcategory":"Lawyer & Legal Services",
            "type":"Services"
        }
    ],
    "sg:phone":"+1 619 420 1600",
    "sg:postcode":"91910",
    "sg:province":"CA",
    "sg:tags":[
        "divorce",
        "law",
        "family"
    ],
    "sg:website":"www.neillmarangi.net",
    "wof:name":"Marangi Neill",
    "wof:placetype":"venue"
},
  "geometry": {"coordinates":[-117.08000199999999,32.642799],"type":"Point"}
}