{
  "type": "Feature",
  "properties": {
    "iso:country":"US",
    "sg:address":"250 E 5th St",
    "sg:city":"Holtville",
    "sg:classifiers":[
        {
            "category":"Farming",
            "subcategory":"Farm & Veterinary Services",
            "type":"Manufacturing & Wholesale Goods"
        }
    ],
    "sg:phone":"+1 760 356 2914",
    "sg:postcode":"92250",
    "sg:province":"CA",
    "sg:tags":[
        "seed",
        "grain",
        "cleaning"
    ],
    "wof:name":"Imperial Valley Milling Co",
    "wof:placetype":"venue"
},
  "geometry": {"coordinates":[-115.378353,32.8109],"type":"Point"}
}