{
  "type": "Feature",
  "properties": {
    "addr:full":"1582 Ardenwood Dr San Jose CA 95129",
    "addr:housenumber":"1582",
    "addr:postcode":"95129",
    "addr:street":"Ardenwood Dr",
    "iso:country":"US",
    "sg:address":"1582 Ardenwood Dr",
    "sg:city":"San Jose",
    "sg:classifiers":[
        {
            "category":"Professional",
            "subcategory":"Computer Services",
            "type":"Services"
        }
    ],
    "sg:phone":"+1 408 517 0429",
    "sg:postcode":"95129",
    "sg:province":"CA",
    "sg:tags":[
        "hardware",
        "provider",
        "internet",
        "software"
    ],
    "wof:name":"Himmath Technologies Inc",
    "wof:placetype":"venue"
},
  "geometry": {"coordinates":[-122.022476,37.295128],"type":"Point"}
}