{
  "type": "Feature",
  "properties": {
    "iso:country":"US",
    "sg:address":"28200 Hwy 189 Ste F-100",
    "sg:city":"Lake Arrowhead",
    "sg:classifiers":[
        {
            "category":"Shopping",
            "subcategory":"Clothing, Apparel, & Fashions",
            "type":"Retail Goods"
        }
    ],
    "sg:phone":"+1 909 336 4860",
    "sg:postcode":"92321",
    "sg:province":"CA",
    "sg:tags":[
        "men's",
        "clothing",
        "accessory",
        "women's"
    ],
    "sg:website":"www.pendleton-usa.com/",
    "wof:name":"Pendleton Woolen Mills",
    "wof:placetype":"venue"
},
  "geometry": {"coordinates":[-117.189915,34.249443],"type":"Point"}
}