{
  "type": "Feature",
  "properties": {
    "iso:country":"US",
    "sg:address":"2953 Bunker Hill Lane Suite# 201",
    "sg:city":"Santa Clara",
    "sg:classifiers":[
        {
            "category":"Professional",
            "subcategory":"Computer Services",
            "type":"Services"
        }
    ],
    "sg:phone":"+1 408 834 8895",
    "sg:postcode":"95054",
    "sg:province":"CA",
    "sg:website":"http://www.haileo.com",
    "wof:name":"Haileo",
    "wof:placetype":"venue"
},
  "geometry": {"coordinates":[-121.98013,37.405699],"type":"Point"}
}