{
  "type": "Feature",
  "properties": {
    "addr:full":"74197 el Paseo Palm Desert CA 92260",
    "addr:housenumber":"74197",
    "addr:postcode":"ca 92260",
    "addr:street":"El Paseo",
    "iso:country":"US",
    "sg:address":"74197 el Paseo",
    "sg:city":"Palm Desert",
    "sg:classifiers":[
        {
            "category":"Real Estate",
            "subcategory":"Real Estate Agent",
            "type":"Services"
        }
    ],
    "sg:phone":"+1 760 779 5284",
    "sg:postcode":"92260",
    "sg:province":"CA",
    "wof:name":"Tarbell Financial Corp",
    "wof:placetype":"venue"
},
  "geometry": {"coordinates":[-116.37075400000001,33.721283],"type":"Point"}
}