{
  "type": "Feature",
  "properties": {
    "addr:full":"3341 Dye Rd Ramona CA 92065",
    "addr:housenumber":"3341",
    "addr:postcode":"92065",
    "addr:street":"Dye Rd",
    "iso:country":"US",
    "sg:address":"3341 Dye Rd",
    "sg:city":"Ramona",
    "sg:classifiers":[
        {
            "category":"Farming",
            "subcategory":"Nursery",
            "type":"Manufacturing & Wholesale Goods"
        }
    ],
    "sg:phone":"+1 760 788 0236",
    "sg:postcode":"92065",
    "sg:province":"CA",
    "sg:tags":[
        "ornamental"
    ],
    "wof:name":"Tropic Tree Products",
    "wof:placetype":"venue"
},
  "geometry": {"coordinates":[-116.90652900000001,33.011079],"type":"Point"}
}