{
  "type": "Feature",
  "properties": {
    "iso:country":"US",
    "sg:address":"4109 24th St",
    "sg:city":"San Francisco",
    "sg:classifiers":[
        {
            "category":"Restaurant",
            "type":"Food & Drink"
        }
    ],
    "sg:menulink":"http://www.allmenus.com/ca/san-francisco/275930-lupa-trattoria/menu/",
    "sg:phone":"+1 415 282 5872",
    "sg:postcode":"94114",
    "sg:province":"CA",
    "sg:tags":[
        "italian"
    ],
    "wof:name":"Lupa Trattoria",
    "wof:placetype":"venue"
},
  "geometry": {"coordinates":[-122.434439,37.751142],"type":"Point"}
}