{
  "type": "Feature",
  "properties": {
    "addr:full":"2377 Gold Meadow Way Gold River CA 95670",
    "addr:housenumber":"2377",
    "addr:postcode":"95670",
    "addr:street":"Gold Meadow Way",
    "iso:country":"US",
    "sg:address":"2377 Gold Meadow Way",
    "sg:city":"Gold River",
    "sg:classifiers":[
        {
            "category":"Building & Trades",
            "subcategory":"Electrical",
            "type":"Services"
        }
    ],
    "sg:phone":"+1 916 526 2692",
    "sg:postcode":"95670",
    "sg:province":"CA",
    "sg:tags":[
        "installation"
    ],
    "wof:name":"Network Installation Corp",
    "wof:placetype":"venue"
},
  "geometry": {"coordinates":[-121.261115,38.622],"type":"Point"}
}