{
  "type": "Feature",
  "properties": {
    "addr:full":"25156 Sage Crest Cir Stevenson Ranch CA 91381",
    "addr:housenumber":"25156",
    "addr:postcode":"91381",
    "addr:street":"Sage Crest Cir",
    "iso:country":"US",
    "sg:address":"25156 Sage Crest Cir",
    "sg:city":"Stevenson Ranch",
    "sg:classifiers":[
        {
            "category":"Building & Trades",
            "subcategory":"Construction",
            "type":"Services"
        }
    ],
    "sg:phone":"+1 661 254 7259",
    "sg:postcode":"91381",
    "sg:province":"CA",
    "sg:tags":[
        "contractor"
    ],
    "wof:name":"Eric Parde Construction",
    "wof:placetype":"venue"
},
  "geometry": {"coordinates":[-118.570663,34.376163],"type":"Point"}
}