{
  "type": "Feature",
  "properties": {
    "addr:full":"931 I St Los Banos CA 93635",
    "addr:housenumber":"931",
    "addr:postcode":"93635",
    "addr:street":"I St",
    "iso:country":"US",
    "sg:address":"931 I St",
    "sg:city":"Los Banos",
    "sg:classifiers":[
        {
            "category":"Professional",
            "subcategory":"Management & Consulting",
            "type":"Services"
        }
    ],
    "sg:phone":"+1 209 826 0130",
    "sg:postcode":"93635",
    "sg:province":"CA",
    "sg:tags":[
        "agricultural",
        "consultant"
    ],
    "wof:name":"Agri-Consultants",
    "wof:placetype":"venue"
},
  "geometry": {"coordinates":[-120.843281,37.058722],"type":"Point"}
}