{
  "type": "Feature",
  "properties": {
    "iso:country":"US",
    "sg:address":"3835 E Thousand Oaks Blvd",
    "sg:city":"Westlake Village",
    "sg:classifiers":[
        {
            "category":"Shopping",
            "subcategory":"News",
            "type":"Retail Goods"
        }
    ],
    "sg:phone":"+1 805 495 7076",
    "sg:postcode":"91362",
    "sg:province":"CA",
    "sg:tags":[
        "magazine"
    ],
    "sg:website":"www.thenewsstand.com",
    "wof:name":"Newstand",
    "wof:placetype":"venue"
},
  "geometry": {"coordinates":[-118.824499,34.161852],"type":"Point"}
}