{
  "type": "Feature",
  "properties": {
    "iso:country":"US",
    "sg:address":"5471 Ferguson Dr",
    "sg:city":"Los Angeles",
    "sg:classifiers":[
        {
            "category":"Wholesale",
            "subcategory":"Groceries",
            "type":"Manufacturing & Wholesale Goods"
        }
    ],
    "sg:phone":"+1 323 721 2522",
    "sg:postcode":"90022",
    "sg:province":"CA",
    "sg:tags":[
        "food",
        "product"
    ],
    "wof:name":"General Mills",
    "wof:placetype":"venue"
},
  "geometry": {"coordinates":[-118.156966,34.010676],"type":"Point"}
}