{
  "type": "Feature",
  "properties": {
    "addr:full":"201 Lombard St Oxnard CA 93030",
    "addr:housenumber":"201",
    "addr:postcode":"93030",
    "addr:street":"Lombard St",
    "iso:country":"US",
    "sg:address":"201 Lombard St",
    "sg:city":"Oxnard",
    "sg:classifiers":[
        {
            "category":"Manufacturing",
            "subcategory":"Signs",
            "type":"Manufacturing & Wholesale Goods"
        },
        {
            "category":"Professional",
            "subcategory":"Business Services",
            "type":"Services"
        }
    ],
    "sg:phone":"+1 805 983 6603",
    "sg:postcode":"93030",
    "sg:province":"CA",
    "sg:tags":[
        "specialty",
        "mfg"
    ],
    "wof:name":"Ron's Signs",
    "wof:placetype":"venue"
},
  "geometry": {"coordinates":[-119.148871,34.203362],"type":"Point"}
}