{
  "type": "Feature",
  "properties": {
    "addr:full":"379 W Artesia St Pomona CA 91768",
    "addr:housenumber":"379",
    "addr:postcode":"91768",
    "addr:street":"W Artesia St",
    "iso:country":"US",
    "sg:address":"379 W Artesia St",
    "sg:city":"Pomona",
    "sg:classifiers":[
        {
            "category":"Real Estate",
            "subcategory":"Real Estate Services",
            "type":"Services"
        },
        {
            "category":"Building & Trades",
            "subcategory":"Cleaning & Sanitation",
            "type":"Services"
        }
    ],
    "sg:phone":"+1 909 620 7137",
    "sg:postcode":"91768",
    "sg:province":"CA",
    "sg:tags":[
        "maintenance",
        "cleaners-interior"
    ],
    "wof:name":"Proclean Building Maintenance",
    "wof:placetype":"venue"
},
  "geometry": {"coordinates":[-117.758117,34.079256],"type":"Point"}
}