{
  "type": "Feature",
  "properties": {
    "addr:full":"1741 Gratton St Riverside CA 92504",
    "addr:housenumber":"1741",
    "addr:postcode":"92504",
    "addr:street":"Gratton St",
    "iso:country":"US",
    "sg:address":"1741 Gratton St",
    "sg:city":"Riverside",
    "sg:classifiers":[
        {
            "category":"Building & Trades",
            "subcategory":"Plumbing",
            "type":"Services"
        }
    ],
    "sg:phone":"+1 951 780 4313",
    "sg:postcode":"92504",
    "sg:province":"CA",
    "sg:tags":[
        "conditioning",
        "air",
        "system",
        "contractor"
    ],
    "wof:name":"Brennan's Central Air Cond",
    "wof:placetype":"venue"
},
  "geometry": {"coordinates":[-117.40319599999999,33.899231],"type":"Point"}
}