{
  "type": "Feature",
  "properties": {
    "addr:full":"238 Petaluma Ave Sebastopol CA 95472",
    "addr:housenumber":"238",
    "addr:postcode":"95472",
    "addr:street":"Petaluma Ave",
    "iso:country":"US",
    "sg:address":"238 Petaluma Ave",
    "sg:city":"Sebastopol",
    "sg:classifiers":[
        {
            "category":"Professional",
            "subcategory":"Management & Consulting",
            "type":"Services"
        }
    ],
    "sg:phone":"+1 707 829 3861",
    "sg:postcode":"95472",
    "sg:province":"CA",
    "sg:tags":[
        "town",
        "city",
        "regional",
        "planner"
    ],
    "wof:name":"Pas & Assoc",
    "wof:placetype":"venue"
},
  "geometry": {"coordinates":[-122.822705,38.401659],"type":"Point"}
}