{
  "type": "Feature",
  "properties": {
    "iso:country":"US",
    "sg:address":"11040 Santa Monica Blvd Ste 410",
    "sg:city":"Los Angeles",
    "sg:classifiers":[
        {
            "category":"Education",
            "subcategory":"Special Training",
            "type":"Public Place"
        }
    ],
    "sg:phone":"+1 310 475 5330",
    "sg:postcode":"90025",
    "sg:province":"CA",
    "sg:tags":[
        "tutor",
        "educational",
        "tutoring",
        "private"
    ],
    "sg:website":"theendresult.com",
    "wof:name":"The End Result, Tutoring for Success",
    "wof:placetype":"venue"
},
  "geometry": {"coordinates":[-118.442482,34.047764],"type":"Point"}
}