{
  "type": "Feature",
  "properties": {
    "addr:full":"27 Bear River Dr Loleta CA 95551",
    "addr:housenumber":"27",
    "addr:postcode":"95551",
    "addr:street":"Bear River Dr",
    "iso:country":"US",
    "sg:address":"27 Bear River Dr",
    "sg:city":"Loleta",
    "sg:classifiers":[
        {
            "category":"Organizations",
            "subcategory":"Political Organization",
            "type":"Services"
        },
        {
            "category":"Government",
            "subcategory":"Office",
            "type":"Public Place"
        }
    ],
    "sg:phone":"+1 707 733 1900",
    "sg:postcode":"95551",
    "sg:province":"CA",
    "sg:tags":[
        "reservation",
        "indian",
        "combined"
    ],
    "wof:name":"Bear River Band Rohnerville",
    "wof:placetype":"venue"
},
  "geometry": {"coordinates":[-124.203845,40.630691],"type":"Point"}
}