{
  "type": "Feature",
  "properties": {
    "addr:full":"900 Newport Center Dr Newport Beach CA 92660",
    "addr:housenumber":"900",
    "addr:postcode":"92660",
    "addr:street":"Newport Center Dr",
    "iso:country":"US",
    "sg:address":"900 Newport Center Dr",
    "sg:city":"Newport Beach",
    "sg:classifiers":[
        {
            "category":"Restaurant",
            "type":"Food & Drink"
        }
    ],
    "sg:phone":"+1 949 729 6900",
    "sg:postcode":"92660",
    "sg:province":"CA",
    "sg:tags":[
        "new",
        "american",
        "steakhouse"
    ],
    "sg:website":"www.samandharrys.com",
    "wof:name":"Sam and Harry's",
    "wof:placetype":"venue"
},
  "geometry": {"coordinates":[-117.878883,33.617085],"type":"Point"}
}