{
  "type": "Feature",
  "properties": {
    "iso:country":"US",
    "sg:address":"11 W Laurel Dr",
    "sg:city":"Salinas",
    "sg:classifiers":[
        {
            "category":"Health Services",
            "subcategory":"Hospital",
            "type":"Services"
        }
    ],
    "sg:phone":"+1 831 442 1494",
    "sg:postcode":"93906",
    "sg:province":"CA",
    "sg:tags":[
        "specialty"
    ],
    "wof:name":"Daniel Maestro",
    "wof:placetype":"venue"
},
  "geometry": {"coordinates":[-121.652986,36.699122],"type":"Point"}
}