{
  "type": "Feature",
  "properties": {
    "addr:full":"867 N 15th St San Jose CA 95112",
    "addr:housenumber":"867",
    "addr:postcode":"95112",
    "addr:street":"N 15Th St",
    "iso:country":"US",
    "sg:address":"867 N 15th St",
    "sg:city":"San Jose",
    "sg:classifiers":[
        {
            "category":"Wholesale",
            "subcategory":"Non-durable Goods",
            "type":"Manufacturing & Wholesale Goods"
        }
    ],
    "sg:phone":"+1 408 294 7206",
    "sg:postcode":"95112",
    "sg:province":"CA",
    "wof:name":"J&M Imports",
    "wof:placetype":"venue"
},
  "geometry": {"coordinates":[-121.888893,37.359778],"type":"Point"}
}