{
  "type": "Feature",
  "properties": {
    "iso:country":"US",
    "sg:address":"2666 W Foothill Blvd",
    "sg:city":"San Bernardino",
    "sg:classifiers":[
        {
            "category":"Manufacturing",
            "subcategory":"Food",
            "type":"Manufacturing & Wholesale Goods"
        },
        {
            "category":"Food & Beverages",
            "subcategory":"Bakery",
            "type":"Retail Goods"
        }
    ],
    "sg:phone":"+1 909 889 9861",
    "sg:postcode":"92410",
    "sg:province":"CA",
    "sg:tags":[
        "product",
        "doughnut",
        "mfg"
    ],
    "wof:name":"Howard's Donuts",
    "wof:placetype":"venue"
},
  "geometry": {"coordinates":[-117.345431,34.106877],"type":"Point"}
}