{
  "type": "Feature",
  "properties": {
    "addr:full":"501 Old County Road Belmont CA 94002",
    "addr:housenumber":"501",
    "addr:postcode":"94002",
    "addr:street":"Old County Road",
    "iso:country":"US",
    "sg:address":"501 Old County Road",
    "sg:city":"Belmont",
    "sg:classifiers":[
        {
            "category":"Retail",
            "subcategory":"Veterinary Services",
            "type":"Services"
        }
    ],
    "sg:phone":"+1 650 593 0969",
    "sg:postcode":"94002",
    "sg:province":"CA",
    "sg:tags":[
        "veterinarian"
    ],
    "wof:name":"Ambulatory Equine Medicine & Surgery",
    "wof:placetype":"venue"
},
  "geometry": {"coordinates":[-122.28178,37.526157],"type":"Point"}
}