{
  "type": "Feature",
  "properties": {
    "addr:full":"933 S Main St Santa Ana CA 92701",
    "addr:housenumber":"933",
    "addr:postcode":"92701",
    "addr:street":"S Main St",
    "iso:country":"US",
    "sg:address":"933 S Main St",
    "sg:city":"Santa Ana",
    "sg:classifiers":[
        {
            "category":"Food & Beverages",
            "subcategory":"Specialty",
            "type":"Retail Goods"
        }
    ],
    "sg:phone":"+1 714 541 9877",
    "sg:postcode":"92701",
    "sg:province":"CA",
    "sg:website":"www.botanicaoaxaca.com",
    "wof:name":"Botanica Oaxaca",
    "wof:placetype":"venue"
},
  "geometry": {"coordinates":[-117.86765200000001,33.736235],"type":"Point"}
}