{
  "type": "Feature",
  "properties": {
    "iso:country":"US",
    "sg:address":"79431 Country Club Dr",
    "sg:city":"Bermuda Dunes",
    "sg:classifiers":[
        {
            "category":"Building & Trades",
            "subcategory":"Construction",
            "type":"Services"
        }
    ],
    "sg:phone":"+1 760 345 9933",
    "sg:postcode":"92201",
    "sg:province":"CA",
    "sg:tags":[
        "tile",
        "dealer"
    ],
    "wof:name":"KDI Stoneworks & Design",
    "wof:placetype":"venue"
},
  "geometry": {"coordinates":[-116.27099800000001,33.74824],"type":"Point"}
}