{
  "type": "Feature",
  "properties": {
    "addr:full":"1875 S Bascom Ave Campbell CA 95008",
    "addr:housenumber":"1875",
    "addr:postcode":"95008",
    "addr:street":"S Bascom Ave",
    "iso:country":"US",
    "sg:address":"1875 S Bascom Ave",
    "sg:city":"Campbell",
    "sg:phone":"+1 408 559 3544",
    "sg:postcode":"95008",
    "sg:province":"CA",
    "wof:name":"Gemcraft",
    "wof:placetype":"venue"
},
  "geometry": {"coordinates":[-121.931793,37.28971],"type":"Point"}
}