{
  "type": "Feature",
  "properties": {
    "iso:country":"US",
    "sg:address":"3190 Vista Way",
    "sg:city":"Oceanside",
    "sg:classifiers":[
        {
            "category":"Travel",
            "subcategory":"Hotels & Motels",
            "type":"Entertainment"
        }
    ],
    "sg:phone":"+1 760 439 1499",
    "sg:postcode":"92056",
    "sg:province":"CA",
    "sg:website":"www.extendedstayamerica.com/mini...",
    "wof:name":"Extended Stay America",
    "wof:placetype":"venue"
},
  "geometry": {"coordinates":[-117.320604,33.182074],"type":"Point"}
}