{
  "type": "Feature",
  "properties": {
    "addr:full":"199 C St Hayward CA 94541",
    "addr:housenumber":"199",
    "addr:postcode":"94541",
    "addr:street":"C St",
    "iso:country":"US",
    "sg:address":"199 C St",
    "sg:city":"Hayward",
    "sg:classifiers":[
        {
            "category":"Freight",
            "type":"Transportation"
        }
    ],
    "sg:phone":"+1 510 732 6401",
    "sg:postcode":"94541",
    "sg:province":"CA",
    "sg:tags":[
        "trucking"
    ],
    "wof:name":"BMW Transportation Inc",
    "wof:placetype":"venue"
},
  "geometry": {"coordinates":[-122.095777,37.666118],"type":"Point"}
}