{
  "type": "Feature",
  "properties": {
    "iso:country":"US",
    "sg:address":"1444 Pollard Rd",
    "sg:city":"Los Gatos",
    "sg:classifiers":[
        {
            "category":"Ice Cream",
            "type":"Food & Drink"
        }
    ],
    "sg:menulink":"http://www.allmenus.com/ca/san-jose/242312-baskin-robbins/menu/",
    "sg:phone":"+1 408 871 7778",
    "sg:postcode":"95032",
    "sg:province":"CA",
    "sg:tags":[
        "american"
    ],
    "wof:name":"Baskin-Robbins",
    "wof:placetype":"venue"
},
  "geometry": {"coordinates":[-121.981278,37.264716],"type":"Point"}
}