{
  "type": "Feature",
  "properties": {
    "addr:full":"2240 McHenry Ave Modesto CA 95350",
    "addr:housenumber":"2240",
    "addr:postcode":"ca 95350",
    "addr:street":"Mchenry Ave",
    "iso:country":"US",
    "sg:address":"2240 McHenry Ave",
    "sg:city":"Modesto",
    "sg:classifiers":[
        {
            "category":"Restaurant",
            "type":"Food & Drink"
        }
    ],
    "sg:phone":"+1 209 527 2140",
    "sg:postcode":"95350",
    "sg:province":"CA",
    "sg:tags":[
        "chinese"
    ],
    "wof:name":"China Express",
    "wof:placetype":"venue"
},
  "geometry": {"coordinates":[-120.99400300000001,37.674301],"type":"Point"}
}