{
  "type": "Feature",
  "properties": {
    "addr:full":"420 Walnut Ave San Diego CA 92103",
    "addr:housenumber":"420",
    "addr:postcode":"92103",
    "addr:street":"Walnut Ave",
    "iso:country":"US",
    "sg:address":"420 Walnut Ave",
    "sg:city":"San Diego",
    "sg:classifiers":[
        {
            "category":"Professional",
            "subcategory":"Art Services",
            "type":"Services"
        }
    ],
    "sg:phone":"+1 619 298 1445",
    "sg:postcode":"92103",
    "sg:province":"CA",
    "sg:tags":[
        "graphic",
        "designer"
    ],
    "sg:website":"www.mdgworks.com",
    "wof:name":"Marketing Design Group",
    "wof:placetype":"venue"
},
  "geometry": {"coordinates":[-117.16097000000001,32.741472],"type":"Point"}
}