{
  "type": "Feature",
  "properties": {
    "addr:full":"46041 Rd 415 Coarsegold CA 93614",
    "addr:postcode":"46041;93614",
    "addr:street":"Rd 415",
    "iso:country":"US",
    "sg:address":"46041 Rd 415",
    "sg:city":"Coarsegold",
    "sg:classifiers":[
        {
            "category":"Real Estate",
            "subcategory":"Real Estate Operator",
            "type":"Services"
        }
    ],
    "sg:phone":"+1 559 683 5393",
    "sg:postcode":"93614",
    "sg:province":"CA",
    "sg:tags":[
        "mobile",
        "home",
        "community"
    ],
    "wof:name":"Oak Creek Community",
    "wof:placetype":"venue"
},
  "geometry": {"coordinates":[-119.70968000000001,37.262653],"type":"Point"}
}