{
  "type": "Feature",
  "properties": {
    "addr:full":"6 S Portola Laguna Beach CA 92651",
    "addr:housenumber":"6",
    "addr:postcode":"92651",
    "addr:street":"S",
    "iso:country":"US",
    "sg:address":"6 S Portola",
    "sg:city":"Laguna Beach",
    "sg:classifiers":[
        {
            "category":"Professional",
            "subcategory":"Employment Agencies",
            "type":"Services"
        }
    ],
    "sg:phone":"+1 949 499 0917",
    "sg:postcode":"92651",
    "sg:province":"CA",
    "sg:tags":[
        "consultant",
        "search",
        "executive"
    ],
    "sg:website":"www.donzeeassociates.com",
    "wof:name":"Don Zee Assoc",
    "wof:placetype":"venue"
},
  "geometry": {"coordinates":[-117.734887,33.490677],"type":"Point"}
}