{
  "type": "Feature",
  "properties": {
    "iso:country":"US",
    "sg:address":"74601 Hwy 111",
    "sg:city":"Palm Desert",
    "sg:classifiers":[
        {
            "category":"Restaurant",
            "type":"Food & Drink"
        }
    ],
    "sg:phone":"+1 760 346 3352",
    "sg:postcode":"92260",
    "sg:province":"CA",
    "wof:name":"John's Restaurant",
    "wof:placetype":"venue"
},
  "geometry": {"coordinates":[-116.361368,33.721363],"type":"Point"}
}