{
  "type": "Feature",
  "properties": {
    "iso:country":"US",
    "sg:address":"1560 N Effie St",
    "sg:city":"Fresno",
    "sg:classifiers":[
        {
            "category":"Retail",
            "subcategory":"Auto Repair",
            "type":"Services"
        }
    ],
    "sg:phone":"+1 559 499 1090",
    "sg:postcode":"93703",
    "sg:province":"CA",
    "sg:tags":[
        "body",
        "automobile",
        "painting"
    ],
    "wof:name":"Mando's Collision & Paint",
    "wof:placetype":"venue"
},
  "geometry": {"coordinates":[-119.7882,36.763864],"type":"Point"}
}