{
  "type": "Feature",
  "properties": {
    "iso:country":"US",
    "sg:address":"2105 Whittier Blvd",
    "sg:city":"La Habra",
    "sg:classifiers":[
        {
            "category":"Shopping",
            "subcategory":"Used Merchandise",
            "type":"Retail Goods"
        }
    ],
    "sg:postcode":"90631",
    "sg:province":"CA",
    "sg:tags":[
        "vintage",
        "consignment"
    ],
    "wof:name":"Simple Man Boardshop",
    "wof:placetype":"venue"
},
  "geometry": {"coordinates":[-117.970217,33.939875],"type":"Point"}
}