{
  "type": "Feature",
  "properties": {
    "iso:country":"US",
    "sg:address":"2440 5th St",
    "sg:city":"Eureka",
    "sg:classifiers":[
        {
            "category":"Government",
            "subcategory":"Court House",
            "type":"Public Place"
        }
    ],
    "sg:phone":"+1 707 441 3200",
    "sg:postcode":"95501",
    "sg:province":"CA",
    "sg:tags":[
        "county",
        "counsel"
    ],
    "wof:name":"Humboldt County Dist Attorney",
    "wof:placetype":"venue"
},
  "geometry": {"coordinates":[-124.14469699999999,40.804204],"type":"Point"}
}