{
  "type": "Feature",
  "properties": {
    "addr:full":"610 Eubanks Ct Vacaville CA 95688",
    "addr:housenumber":"610",
    "addr:postcode":"95688",
    "addr:street":"Eubanks Ct",
    "iso:country":"US",
    "sg:address":"610 Eubanks Ct",
    "sg:city":"Vacaville",
    "sg:classifiers":[
        {
            "category":"Social Services",
            "subcategory":"Adult Care",
            "type":"Services"
        }
    ],
    "sg:phone":"+1 818 895 2104",
    "sg:postcode":"95688",
    "sg:province":"CA",
    "sg:tags":[
        "foster"
    ],
    "wof:name":"Moss Beach Homes",
    "wof:placetype":"venue"
},
  "geometry": {"coordinates":[-121.96131099999999,38.395892],"type":"Point"}
}