{
  "type": "Feature",
  "properties": {
    "addr:full":"3521 Gulf St Bakersfield CA 93308",
    "addr:housenumber":"3521",
    "addr:postcode":"93308",
    "addr:street":"Gulf St",
    "iso:country":"US",
    "sg:address":"3521 Gulf St",
    "sg:city":"Bakersfield",
    "sg:classifiers":[
        {
            "category":"Manufacturing",
            "subcategory":"Tools & Machinery",
            "type":"Manufacturing & Wholesale Goods"
        }
    ],
    "sg:phone":"+1 661 324 2213",
    "sg:postcode":"93308",
    "sg:province":"CA",
    "sg:tags":[
        "machine",
        "shop"
    ],
    "wof:name":"Chancellor Oil Tool Inc",
    "wof:placetype":"venue"
},
  "geometry": {"coordinates":[-119.047426,35.394301],"type":"Point"}
}