{
  "type": "Feature",
  "properties": {
    "addr:full":"16934 Saint Andrews Dr Poway CA 92064",
    "addr:housenumber":"16934",
    "addr:postcode":"ca 92064",
    "addr:street":"Saint Andrews Dr",
    "iso:country":"US",
    "sg:address":"16934 Saint Andrews Dr",
    "sg:city":"Poway",
    "sg:classifiers":[
        {
            "category":"Building & Trades",
            "subcategory":"Construction",
            "type":"Services"
        }
    ],
    "sg:phone":"+1 858 487 6942",
    "sg:postcode":"92064",
    "sg:province":"CA",
    "sg:tags":[
        "house"
    ],
    "wof:name":"Bakan Home Improvements",
    "wof:placetype":"venue"
},
  "geometry": {"coordinates":[-117.043795,33.020375],"type":"Point"}
}