{
  "type": "Feature",
  "properties": {
    "addr:full":"7876 Butts Canyon Rd Pope Valley CA 94567",
    "addr:housenumber":"7876",
    "addr:postcode":"94567",
    "addr:street":"Butts Canyon Rd",
    "iso:country":"US",
    "sg:address":"7876 Butts Canyon Rd",
    "sg:city":"Pope Valley",
    "sg:classifiers":[
        {
            "category":"Education",
            "subcategory":"Special Training",
            "type":"Public Place"
        }
    ],
    "sg:phone":"+1 707 965 0400",
    "sg:postcode":"94567",
    "sg:province":"CA",
    "sg:tags":[
        "school",
        "interest"
    ],
    "sg:website":"www.jaffeinstitute.org",
    "wof:name":"Jaffe Institute",
    "wof:placetype":"venue"
},
  "geometry": {"coordinates":[-122.445776,38.682548],"type":"Point"}
}