{
  "type": "Feature",
  "properties": {
    "iso:country":"US",
    "sg:address":"1650 Ivar Ave",
    "sg:city":"Los Angeles",
    "sg:classifiers":[
        {
            "category":"Shopping",
            "subcategory":"Adult",
            "type":"Retail Goods"
        },
        {
            "category":"Personal",
            "subcategory":"Day Spa",
            "type":"Services"
        }
    ],
    "sg:phone":"+1 323 464 0445",
    "sg:postcode":"90028",
    "sg:province":"CA",
    "sg:tags":[
        "entertainment"
    ],
    "wof:name":"The Hollywood Spa",
    "wof:placetype":"venue"
},
  "geometry": {"coordinates":[-118.328003,34.100399],"type":"Point"}
}