{
  "type": "Feature",
  "properties": {
    "iso:country":"US",
    "sg:address":"8387 W 3rd St",
    "sg:city":"Los Angeles",
    "sg:classifiers":[
        {
            "category":"Shopping",
            "subcategory":"Used Merchandise",
            "type":"Retail Goods"
        }
    ],
    "sg:phone":"+1 323 655 4571",
    "sg:postcode":"90048",
    "sg:province":"CA",
    "sg:tags":[
        "furniture"
    ],
    "wof:name":"Memory Lane Antique Cllctbl",
    "wof:placetype":"venue"
},
  "geometry": {"coordinates":[-118.372551,34.073007],"type":"Point"}
}