{
  "type": "Feature",
  "properties": {
    "iso:country":"US",
    "sg:address":"3316 Laverne Ave",
    "sg:city":"Bakersfield",
    "sg:classifiers":[
        {
            "category":"Organizations",
            "subcategory":"Non-profit Organization",
            "type":"Services"
        }
    ],
    "sg:phone":"+1 661 832 8504",
    "sg:postcode":"93309",
    "sg:province":"CA",
    "sg:tags":[
        "information",
        "alcoholism",
        "treatment"
    ],
    "wof:name":"Jason's Retreat Capistrano",
    "wof:placetype":"venue"
},
  "geometry": {"coordinates":[-119.040091,35.342793],"type":"Point"}
}