{
  "type": "Feature",
  "properties": {
    "addr:full":"675 W Middle Ave Morgan Hill CA 95037",
    "addr:housenumber":"675",
    "addr:postcode":"95037",
    "addr:street":"W Middle Ave",
    "iso:country":"US",
    "sg:address":"675 W Middle Ave",
    "sg:city":"Morgan Hill",
    "sg:classifiers":[
        {
            "category":"Building & Trades",
            "subcategory":"Construction",
            "type":"Services"
        }
    ],
    "sg:phone":"+1 408 782 1117",
    "sg:postcode":"95037",
    "sg:province":"CA",
    "sg:tags":[
        "dry wall",
        "contractor"
    ],
    "wof:name":"MTD Tomasello Dry Wall",
    "wof:placetype":"venue"
},
  "geometry": {"coordinates":[-121.63561,37.09429],"type":"Point"}
}