{
  "type": "Feature",
  "properties": {
    "iso:country":"US",
    "sg:address":"2609 S Hill St",
    "sg:city":"Los Angeles",
    "sg:classifiers":[
        {
            "category":"Professional",
            "subcategory":"Business Services",
            "type":"Services"
        }
    ],
    "sg:phone":"+1 213 749 5558",
    "sg:postcode":"90007",
    "sg:province":"CA",
    "sg:tags":[
        "packaging"
    ],
    "wof:name":"World Tape",
    "wof:placetype":"venue"
},
  "geometry": {"coordinates":[-118.271517,34.024911],"type":"Point"}
}