{
  "type": "Feature",
  "properties": {
    "iso:country":"US",
    "sg:address":"623 E F St",
    "sg:city":"Oakdale",
    "sg:classifiers":[
        {
            "category":"Travel",
            "subcategory":"Hotels & Motels",
            "type":"Entertainment"
        }
    ],
    "sg:phone":"+1 209 847 0206",
    "sg:postcode":"95361",
    "sg:province":"CA",
    "wof:name":"Jerry's Motel",
    "wof:placetype":"venue"
},
  "geometry": {"coordinates":[-120.843604,37.768],"type":"Point"}
}