{
  "type": "Feature",
  "properties": {
    "addr:full":"4041 N 1st Ave San Bernardino CA 92407",
    "addr:housenumber":"4041",
    "addr:postcode":"92407",
    "addr:street":"N 1St Ave",
    "iso:country":"US",
    "sg:address":"4041 N 1st Ave",
    "sg:city":"San Bernardino",
    "sg:classifiers":[
        {
            "category":"Building & Trades",
            "subcategory":"Construction",
            "type":"Services"
        }
    ],
    "sg:phone":"+1 909 883 3778",
    "sg:postcode":"92407",
    "sg:province":"CA",
    "sg:tags":[
        "coping",
        "plastering",
        "tiling",
        "pool",
        "swimming"
    ],
    "wof:name":"Chris' Quality Pool Repair",
    "wof:placetype":"venue"
},
  "geometry": {"coordinates":[-117.296055,34.166802],"type":"Point"}
}