{
  "type": "Feature",
  "properties": {
    "addr:full":"33 el Prisma Rancho Santa Margarita CA 92688",
    "addr:housenumber":"33",
    "addr:postcode":"92688",
    "addr:street":"El Prisma",
    "iso:country":"US",
    "sg:address":"33 el Prisma",
    "sg:city":"Rancho Santa Margarita",
    "sg:classifiers":[
        {
            "category":"Wholesale",
            "subcategory":"Groceries",
            "type":"Manufacturing & Wholesale Goods"
        }
    ],
    "sg:phone":"+1 949 766 0070",
    "sg:postcode":"92688",
    "sg:province":"CA",
    "sg:tags":[
        "import",
        "tea"
    ],
    "wof:name":"Q Trade International Corp",
    "wof:placetype":"venue"
},
  "geometry": {"coordinates":[-117.619606,33.657137],"type":"Point"}
}