{
  "type": "Feature",
  "properties": {
    "iso:country":"US",
    "sg:address":"1375 Poli St",
    "sg:city":"Ventura",
    "sg:classifiers":[
        {
            "category":"Manufacturing",
            "subcategory":"Printing",
            "type":"Manufacturing & Wholesale Goods"
        }
    ],
    "sg:phone":"+1 805 643 6279",
    "sg:postcode":"93001",
    "sg:province":"CA",
    "sg:tags":[
        "publishing"
    ],
    "wof:name":"Seaview Publishing",
    "wof:placetype":"venue"
},
  "geometry": {"coordinates":[-119.280301,34.281991],"type":"Point"}
}