{
  "type": "Feature",
  "properties": {
    "iso:country":"US",
    "sg:address":"8552 Erinbrook Way",
    "sg:city":"Sacramento",
    "sg:classifiers":[
        {
            "category":"Professional",
            "subcategory":"Computer Services",
            "type":"Services"
        }
    ],
    "sg:phone":"+1 916 201 1824",
    "sg:postcode":"95826",
    "sg:province":"CA",
    "sg:tags":[
        "repair"
    ],
    "sg:website":"www.eastsaccomputerrepair.com/",
    "wof:name":"East Sac Computer Repair",
    "wof:placetype":"venue"
},
  "geometry": {"coordinates":[-121.388008,38.561651],"type":"Point"}
}