{
  "type": "Feature",
  "properties": {
    "addr:full":"9550 Crenshaw Blvd Inglewood CA 90305",
    "addr:housenumber":"9550",
    "addr:postcode":"90305",
    "addr:street":"Crenshaw Blvd",
    "iso:country":"US",
    "sg:address":"9550 Crenshaw Blvd",
    "sg:city":"Inglewood",
    "sg:classifiers":[
        {
            "category":"Shopping",
            "subcategory":"Books",
            "type":"Retail Goods"
        }
    ],
    "sg:phone":"+1 323 755 6193",
    "sg:postcode":"90305",
    "sg:province":"CA",
    "sg:tags":[
        "professional",
        "equipment"
    ],
    "wof:name":"Book Nook",
    "wof:placetype":"venue"
},
  "geometry": {"coordinates":[-118.32639899999999,33.950462],"type":"Point"}
}