{
  "type": "Feature",
  "properties": {
    "addr:full":"27 Cloud Walk Milpitas CA 95035",
    "addr:housenumber":"27",
    "addr:postcode":"95035",
    "addr:street":"Cloud Walk",
    "iso:country":"US",
    "sg:address":"27 Cloud Walk",
    "sg:city":"Milpitas",
    "sg:classifiers":[
        {
            "category":"Education",
            "subcategory":"Dance Studio",
            "type":"Public Place"
        }
    ],
    "sg:phone":"+1 408 263 7888",
    "sg:postcode":"95035",
    "sg:province":"CA",
    "sg:tags":[
        "instruction",
        "dancing"
    ],
    "wof:name":"Stephanie Dance Shoes Inc",
    "wof:placetype":"venue"
},
  "geometry": {"coordinates":[-121.90222,37.418057],"type":"Point"}
}