{
  "type": "Feature",
  "properties": {
    "addr:full":"2820 Townsgate Rd Westlake Village CA 91361",
    "addr:housenumber":"2820",
    "addr:postcode":"91361",
    "addr:street":"Townsgate Rd",
    "iso:country":"US",
    "sg:address":"2820 Townsgate Rd",
    "sg:city":"Westlake Village",
    "sg:classifiers":[
        {
            "category":"Insurance",
            "subcategory":"Insurance Agent",
            "type":"Services"
        }
    ],
    "sg:phone":"+1 805 496 9646",
    "sg:postcode":"91361",
    "sg:province":"CA",
    "wof:name":"Harvest Insurance",
    "wof:placetype":"venue"
},
  "geometry": {"coordinates":[-118.821046,34.151132],"type":"Point"}
}