{
  "type": "Feature",
  "properties": {
    "iso:country":"US",
    "sg:address":"8543 Rosemead Blvd",
    "sg:city":"Pico Rivera",
    "sg:classifiers":[
        {
            "category":"Health Services",
            "subcategory":"Doctor",
            "type":"Services"
        }
    ],
    "sg:phone":"+1 562 904 0400",
    "sg:postcode":"90660",
    "sg:province":"CA",
    "sg:tags":[
        "dentist"
    ],
    "wof:name":"Telegraph Dental Group",
    "wof:placetype":"venue"
},
  "geometry": {"coordinates":[-118.109149,33.962977],"type":"Point"}
}