{
  "type": "Feature",
  "properties": {
    "addr:full":"4741 Eagle Rock Blvd Los Angeles CA 90041",
    "addr:housenumber":"4741",
    "addr:postcode":"90041",
    "addr:street":"Eagle Rock Blvd",
    "iso:country":"US",
    "sg:address":"4741 Eagle Rock Blvd",
    "sg:city":"Los Angeles",
    "sg:classifiers":[
        {
            "category":"Restaurant",
            "type":"Food & Drink"
        }
    ],
    "sg:phone":"+1 323 256 2562",
    "sg:postcode":"90041",
    "sg:province":"CA",
    "sg:tags":[
        "sushi",
        "bar"
    ],
    "sg:website":"www.mia-sushi.com/",
    "wof:name":"Mia Sushi",
    "wof:placetype":"venue"
},
  "geometry": {"coordinates":[-118.21700300000001,34.131302],"type":"Point"}
}