{
  "type": "Feature",
  "properties": {
    "addr:full":"13625 Bechard Ave Norwalk CA 90650",
    "addr:housenumber":"13625",
    "addr:postcode":"90650",
    "addr:street":"Bechard Ave",
    "iso:country":"US",
    "sg:address":"13625 Bechard Ave",
    "sg:city":"Norwalk",
    "sg:classifiers":[
        {
            "category":"Manufacturing",
            "subcategory":"Glass & Minerals",
            "type":"Manufacturing & Wholesale Goods"
        }
    ],
    "sg:phone":"+1 562 653 0189",
    "sg:postcode":"90650",
    "sg:province":"CA",
    "sg:tags":[
        "glass-wholesale",
        "shape",
        "circle",
        "special",
        "manufacturer"
    ],
    "wof:name":"Oakden Door & Glass",
    "wof:placetype":"venue"
},
  "geometry": {"coordinates":[-118.06231699999999,33.907233],"type":"Point"}
}