{
  "type": "Feature",
  "properties": {
    "iso:country":"US",
    "sg:address":"4902 Sandyland Rd",
    "sg:city":"Carpinteria",
    "sg:classifiers":[
        {
            "category":"Retail",
            "subcategory":"Animal Services",
            "type":"Services"
        }
    ],
    "sg:phone":"+1 805 563 0163",
    "sg:postcode":"93013",
    "sg:province":"CA",
    "wof:name":"Preppy Puppy",
    "wof:placetype":"venue"
},
  "geometry": {"coordinates":[-119.524456,34.394002],"type":"Point"}
}