{
  "type": "Feature",
  "properties": {
    "addr:full":"13550 State Hwy 20 Clearlake Oaks CA 95423",
    "addr:housenumber":"13550",
    "addr:postcode":"95423",
    "addr:street":"State Hwy 20 Clearlake",
    "iso:country":"US",
    "sg:address":"13550 State Hwy 20",
    "sg:city":"Clearlake Oaks",
    "sg:classifiers":[
        {
            "category":"Building & Trades",
            "subcategory":"Construction",
            "type":"Services"
        }
    ],
    "sg:phone":"+1 707 998 1993",
    "sg:postcode":"95423",
    "sg:province":"CA",
    "sg:tags":[
        "roofing",
        "contractor"
    ],
    "wof:name":"Dennis West Roofing",
    "wof:placetype":"venue"
},
  "geometry": {"coordinates":[-122.65989399999999,39.025448],"type":"Point"}
}