{
  "type": "Feature",
  "properties": {
    "addr:full":"4383 Clayton Rd Concord CA 94521",
    "addr:housenumber":"4383",
    "addr:postcode":"94521",
    "addr:street":"Clayton Rd",
    "iso:country":"US",
    "sg:address":"4383 Clayton Rd",
    "sg:city":"Concord",
    "sg:classifiers":[
        {
            "category":"Cinema",
            "subcategory":"Movie Rental",
            "type":"Entertainment"
        }
    ],
    "sg:phone":"+1 925 692 1139",
    "sg:postcode":"94521",
    "sg:province":"CA",
    "sg:tags":[
        "leasing",
        "video",
        "disc",
        "tape"
    ],
    "sg:website":"www.real.com",
    "wof:name":"Hollywood Video",
    "wof:placetype":"venue"
},
  "geometry": {"coordinates":[-121.990155,37.963995],"type":"Point"}
}