{
  "type": "Feature",
  "properties": {
    "addr:full":"175 Kern St Salinas CA 93905",
    "addr:housenumber":"175",
    "addr:postcode":"93905",
    "addr:street":"Kern St",
    "iso:country":"US",
    "sg:address":"175 Kern St",
    "sg:city":"Salinas",
    "sg:classifiers":[
        {
            "category":"Travel",
            "subcategory":"Hotels & Motels",
            "type":"Entertainment"
        }
    ],
    "sg:phone":"+1 831 784 0176",
    "sg:postcode":"93905",
    "sg:province":"CA",
    "sg:tags":[
        "lodging"
    ],
    "sg:website":"http://book.bestwestern.com/bestwestern/priceAvail.do?propertyCode=05569&cm_mmc=IYP-_-YP-_-property-_-5569",
    "wof:name":"Best Western Salinas Monterey",
    "wof:placetype":"venue"
},
  "geometry": {"coordinates":[-121.64058300000001,36.680811],"type":"Point"}
}