{
  "type": "Feature",
  "properties": {
    "iso:country":"US",
    "sg:address":"8524 Commerce Ave",
    "sg:city":"San Diego",
    "sg:classifiers":[
        {
            "category":"Shopping",
            "subcategory":"Bicycles & Sporting Goods",
            "type":"Retail Goods"
        },
        {
            "category":"Manufacturing",
            "subcategory":"Toys & Sporting Goods",
            "type":"Manufacturing & Wholesale Goods"
        }
    ],
    "sg:phone":"+1 858 689 9616",
    "sg:postcode":"92121",
    "sg:province":"CA",
    "sg:tags":[
        "surfboard",
        "mfg"
    ],
    "wof:name":"Custom Surf and Sail",
    "wof:placetype":"venue"
},
  "geometry": {"coordinates":[-117.1678,32.88173],"type":"Point"}
}