{
  "type": "Feature",
  "properties": {
    "addr:full":"1914 S Pacific Coast Hwy Ste 210 Redondo Beach CA 90277",
    "addr:housenumber":"1914",
    "addr:postcode":"90277",
    "addr:street":"S Pacific Coast Hwy Ste 210",
    "iso:country":"US",
    "sg:address":"1914 S Pacific Coast Hwy Ste 210",
    "sg:city":"Redondo Beach",
    "sg:classifiers":[
        {
            "category":"Banks & Credit Unions",
            "subcategory":"Financial Services",
            "type":"Services"
        }
    ],
    "sg:phone":"+1 310 698 4663",
    "sg:postcode":"90277",
    "sg:province":"CA",
    "sg:tags":[
        "broker",
        "mortgage"
    ],
    "wof:name":"Mortgage Island",
    "wof:placetype":"venue"
},
  "geometry": {"coordinates":[-118.376076,33.816317],"type":"Point"}
}