{
  "type": "Feature",
  "properties": {
    "addr:full":"508 Contra Costa Blvd Pleasant Hill CA 94523",
    "addr:housenumber":"508",
    "addr:postcode":"94523",
    "addr:street":"Contra Costa Blvd",
    "iso:country":"US",
    "sg:address":"508 Contra Costa Blvd",
    "sg:city":"Pleasant Hill",
    "sg:classifiers":[
        {
            "category":"Retail",
            "subcategory":"Laundry & Dry Cleaning",
            "type":"Services"
        }
    ],
    "sg:phone":"+1 925 671 2388",
    "sg:postcode":"94523",
    "sg:province":"CA",
    "sg:tags":[
        "cleaners"
    ],
    "wof:name":"One Hour Cleaners",
    "wof:placetype":"venue"
},
  "geometry": {"coordinates":[-122.065853,37.978078],"type":"Point"}
}