{
  "type": "Feature",
  "properties": {
    "iso:country":"US",
    "sg:address":"26871 Hobie Cir",
    "sg:city":"Murrieta",
    "sg:classifiers":[
        {
            "category":"Building & Trades",
            "subcategory":"Construction",
            "type":"Services"
        }
    ],
    "sg:phone":"+1 951 677 0015",
    "sg:postcode":"92562",
    "sg:province":"CA",
    "sg:tags":[
        "home",
        "builder"
    ],
    "wof:name":"Future Home Systems",
    "wof:placetype":"venue"
},
  "geometry": {"coordinates":[-117.172602,33.530234],"type":"Point"}
}