{
  "type": "Feature",
  "properties": {
    "addr:full":"111 N Atlantic Blvd Ste 352 Monterey Park CA 91754",
    "addr:housenumber":"111",
    "addr:postcode":"91754",
    "addr:street":"N Atlantic Blvd Ste 352",
    "iso:country":"US",
    "sg:address":"111 N Atlantic Blvd Ste 352",
    "sg:city":"Monterey Park",
    "sg:classifiers":[
        {
            "category":"Professional",
            "subcategory":"Lawyer & Legal Services",
            "type":"Services"
        }
    ],
    "sg:phone":"+1 626 571 6697",
    "sg:postcode":"91754",
    "sg:province":"CA",
    "wof:name":"Strauss Jeffrey E Atty",
    "wof:placetype":"venue"
},
  "geometry": {"coordinates":[-118.134423,34.062799],"type":"Point"}
}