{
  "type": "Feature",
  "properties": {
    "addr:full":"510 Creekside Ct Paso Robles CA 93446",
    "addr:housenumber":"510",
    "addr:postcode":"93446",
    "addr:street":"Creekside Ct",
    "iso:country":"US",
    "sg:address":"510 Creekside Ct",
    "sg:city":"Paso Robles",
    "sg:classifiers":[
        {
            "category":"Building & Trades",
            "subcategory":"Construction",
            "type":"Services"
        }
    ],
    "sg:phone":"+1 805 239 2988",
    "sg:postcode":"93446",
    "sg:province":"CA",
    "sg:tags":[
        "concrete",
        "contractor"
    ],
    "wof:name":"K Brush Concrete",
    "wof:placetype":"venue"
},
  "geometry": {"coordinates":[-120.649219,35.605366],"type":"Point"}
}