{
  "type": "Feature",
  "properties": {
    "iso:country":"US",
    "sg:address":"1495 Railroad Ave",
    "sg:city":"Clovis",
    "sg:classifiers":[
        {
            "category":"Building & Trades",
            "subcategory":"Construction",
            "type":"Services"
        }
    ],
    "sg:phone":"+1 559 297 9600",
    "sg:postcode":"93612",
    "sg:province":"CA",
    "sg:tags":[
        "insulation",
        "heat",
        "contractor"
    ],
    "wof:name":"Sundowner Insulation Co",
    "wof:placetype":"venue"
},
  "geometry": {"coordinates":[-119.699685,36.813004],"type":"Point"}
}