{
  "type": "Feature",
  "properties": {
    "iso:country":"US",
    "sg:address":"6410 E Pacific Coast Hwy",
    "sg:city":"Long Beach",
    "sg:classifiers":[
        {
            "category":"Personal",
            "subcategory":"Beauty Salon",
            "type":"Services"
        }
    ],
    "sg:phone":"+1 562 597 2225",
    "sg:postcode":"90803",
    "sg:province":"CA",
    "sg:tags":[
        "manicuring"
    ],
    "wof:name":"Images Nails",
    "wof:placetype":"venue"
},
  "geometry": {"coordinates":[-118.112386,33.759292],"type":"Point"}
}