{
  "type": "Feature",
  "properties": {
    "iso:country":"US",
    "sg:address":"11141 Osborne St",
    "sg:city":"Lake View Ter",
    "sg:classifiers":[
        {
            "category":"Shopping",
            "type":"Retail Goods"
        }
    ],
    "sg:phone":"+1 818 896 1999",
    "sg:postcode":"91342",
    "sg:province":"CA",
    "sg:tags":[
        "religious"
    ],
    "wof:name":"Terrace Christian Book Shoppe",
    "wof:placetype":"venue"
},
  "geometry": {"coordinates":[-118.374907,34.279741],"type":"Point"}
}