{
  "type": "Feature",
  "properties": {
    "addr:full":"3280 Main St San Diego CA 92113",
    "addr:housenumber":"3280",
    "addr:postcode":"92113",
    "addr:street":"Main St",
    "iso:country":"US",
    "sg:address":"3280 Main St",
    "sg:city":"San Diego",
    "sg:classifiers":[
        {
            "category":"Real Estate",
            "subcategory":"Real Estate Agent",
            "type":"Services"
        }
    ],
    "sg:phone":"+1 619 239 3320",
    "sg:postcode":"92113",
    "sg:province":"CA",
    "sg:tags":[
        "management"
    ],
    "wof:name":"Property Management & Mntnc",
    "wof:placetype":"venue"
},
  "geometry": {"coordinates":[-117.12416,32.691728],"type":"Point"}
}