{
  "type": "Feature",
  "properties": {
    "iso:country":"US",
    "sg:address":"3000 Mall View Rd",
    "sg:city":"Bakersfield",
    "sg:classifiers":[
        {
            "category":"Shopping",
            "subcategory":"Clothing, Apparel, & Fashions",
            "type":"Retail Goods"
        }
    ],
    "sg:phone":"+1 661 873 8070",
    "sg:postcode":"93306",
    "sg:province":"CA",
    "sg:tags":[
        "shop",
        "bridal"
    ],
    "wof:name":"Primavera Dreams",
    "wof:placetype":"venue"
},
  "geometry": {"coordinates":[-118.959902,35.39336],"type":"Point"}
}