{
  "type": "Feature",
  "properties": {
    "addr:full":"3055 Gough St #304 San Francisco CA 94123",
    "addr:housenumber":"3055",
    "addr:postcode":"94123",
    "addr:street":"Gough St # 304",
    "iso:country":"US",
    "sg:address":"3055 Gough St #304",
    "sg:city":"San Francisco",
    "sg:classifiers":[
        {
            "category":"Health Services",
            "subcategory":"Clinic",
            "type":"Services"
        }
    ],
    "sg:phone":"+1 415 885 1002",
    "sg:postcode":"94123",
    "sg:province":"CA",
    "sg:tags":[
        "medical"
    ],
    "wof:name":"You & Eye Health Consultations",
    "wof:placetype":"venue"
},
  "geometry": {"coordinates":[-122.428179,37.801609],"type":"Point"}
}