{
  "type": "Feature",
  "properties": {
    "addr:full":"104 S. Main St Templeton CA 93465",
    "addr:housenumber":"104",
    "addr:postcode":"93465",
    "addr:street":"S. Main St",
    "iso:country":"US",
    "sg:address":"104 S. Main St",
    "sg:city":"Templeton",
    "sg:phone":"+1 760 560 6385",
    "sg:postcode":"93465",
    "sg:province":"CA",
    "sg:website":"http://www.blabelbeauty.9f.com",
    "wof:name":"B-label Beauty",
    "wof:placetype":"venue"
},
  "geometry": {"coordinates":[-120.70274999999999,35.552216],"type":"Point"}
}