{
  "type": "Feature",
  "properties": {
    "addr:full":"10471 Grant Line Rd Elk Grove CA 95624",
    "addr:housenumber":"10471",
    "addr:postcode":"95624",
    "addr:street":"Grant Line Rd",
    "iso:country":"US",
    "sg:address":"10471 Grant Line Rd",
    "sg:city":"Elk Grove",
    "sg:classifiers":[
        {
            "category":"Building & Trades",
            "subcategory":"Construction",
            "type":"Services"
        }
    ],
    "sg:phone":"+1 916 714 0900",
    "sg:postcode":"95624",
    "sg:province":"CA",
    "sg:tags":[
        "tile",
        "dealer"
    ],
    "wof:name":"Tile Outlet",
    "wof:placetype":"venue"
},
  "geometry": {"coordinates":[-121.358512,38.378551],"type":"Point"}
}