{
  "type": "Feature",
  "properties": {
    "addr:full":"13727 San Antonio Dr Norwalk CA 90650",
    "addr:housenumber":"13727",
    "addr:postcode":"90650",
    "addr:street":"San Antonio Dr",
    "iso:country":"US",
    "sg:address":"13727 San Antonio Dr",
    "sg:city":"Norwalk",
    "sg:classifiers":[
        {
            "category":"Professional",
            "subcategory":"Lawyer & Legal Services",
            "type":"Services"
        }
    ],
    "sg:phone":"+1 562 863 1558",
    "sg:postcode":"90650",
    "sg:province":"CA",
    "sg:tags":[
        "attorney"
    ],
    "wof:name":"Daniel M Chesnut Law Offices",
    "wof:placetype":"venue"
},
  "geometry": {"coordinates":[-118.078459,33.90611],"type":"Point"}
}