{
  "type": "Feature",
  "properties": {
    "iso:country":"US",
    "sg:address":"116 N Robertson Blvd",
    "sg:city":"Los Angeles",
    "sg:classifiers":[
        {
            "category":"Health Services",
            "subcategory":"Doctor",
            "type":"Services"
        }
    ],
    "sg:phone":"+1 310 657 3540",
    "sg:postcode":"90048",
    "sg:province":"CA",
    "sg:tags":[
        "physician",
        "surgeon",
        "psychiatrist"
    ],
    "wof:name":"Weisberg Louis W MD",
    "wof:placetype":"venue"
},
  "geometry": {"coordinates":[-118.383734,34.075929],"type":"Point"}
}