{
  "type": "Feature",
  "properties": {
    "addr:full":"1274 S Waterman Ave San Bernardino CA 92408",
    "addr:housenumber":"1274",
    "addr:postcode":"92408",
    "addr:street":"S Waterman Ave",
    "iso:country":"US",
    "sg:address":"1274 S Waterman Ave",
    "sg:city":"San Bernardino",
    "sg:classifiers":[
        {
            "category":"Autos & Motor Vehicles",
            "subcategory":"Automobile Sales",
            "type":"Retail Goods"
        }
    ],
    "sg:phone":"+1 909 890 9229",
    "sg:postcode":"92408",
    "sg:province":"CA",
    "sg:tags":[
        "car",
        "dealer"
    ],
    "wof:name":"Tolery Auto Sales",
    "wof:placetype":"venue"
},
  "geometry": {"coordinates":[-117.278803,34.078679],"type":"Point"}
}