{
  "type": "Feature",
  "properties": {
    "addr:full":"8375 Arroyo Cir Gilroy CA 95020",
    "addr:housenumber":"8375",
    "addr:postcode":"95020",
    "addr:street":"Arroyo Cir",
    "iso:country":"US",
    "sg:address":"8375 Arroyo Cir",
    "sg:city":"Gilroy",
    "sg:classifiers":[
        {
            "category":"Shopping",
            "type":"Retail Goods"
        }
    ],
    "sg:phone":"+1 408 847 5272",
    "sg:postcode":"95020",
    "sg:province":"CA",
    "sg:tags":[
        "perfume"
    ],
    "wof:name":"Perfumania",
    "wof:placetype":"venue"
},
  "geometry": {"coordinates":[-121.56240699999999,37.021355],"type":"Point"}
}