{
  "type": "Feature",
  "properties": {
    "addr:full":"4237 E Airport Dr Ontario CA 91761",
    "addr:housenumber":"4237",
    "addr:postcode":"91761",
    "addr:street":"E Airport Dr",
    "iso:country":"US",
    "sg:address":"4237 E Airport Dr",
    "sg:city":"Ontario",
    "sg:classifiers":[
        {
            "category":"Wholesale",
            "subcategory":"Apparel",
            "type":"Manufacturing & Wholesale Goods"
        }
    ],
    "sg:phone":"+1 909 937 3699",
    "sg:postcode":"91761",
    "sg:province":"CA",
    "sg:tags":[
        "shoes"
    ],
    "wof:name":"Hunkers Footwear USA Inc",
    "wof:placetype":"venue"
},
  "geometry": {"coordinates":[-117.5607,34.062502],"type":"Point"}
}