{
  "type": "Feature",
  "properties": {
    "iso:country":"US",
    "sg:address":"37417 Niles Blvd",
    "sg:city":"Fremont",
    "sg:classifiers":[
        {
            "category":"Wholesale",
            "subcategory":"Jewelry",
            "type":"Manufacturing & Wholesale Goods"
        }
    ],
    "sg:phone":"+1 510 794 7465",
    "sg:postcode":"94536",
    "sg:province":"CA",
    "sg:tags":[
        "beads"
    ],
    "wof:name":"Kiowa Rose",
    "wof:placetype":"venue"
},
  "geometry": {"coordinates":[-121.980251,37.577196],"type":"Point"}
}