{
  "type": "Feature",
  "properties": {
    "addr:full":"2222 Kansas Ave Riverside CA 92507",
    "addr:housenumber":"2222",
    "addr:postcode":"92507",
    "addr:street":"Kansas Ave",
    "iso:country":"US",
    "sg:address":"2222 Kansas Ave",
    "sg:city":"Riverside",
    "sg:classifiers":[
        {
            "category":"Freight",
            "type":"Transportation"
        }
    ],
    "sg:phone":"+1 951 328 9911",
    "sg:postcode":"92507",
    "sg:province":"CA",
    "sg:tags":[
        "trucking"
    ],
    "wof:name":"Pacific Transportation Svc",
    "wof:placetype":"venue"
},
  "geometry": {"coordinates":[-117.357263,33.990928],"type":"Point"}
}