{
  "type": "Feature",
  "properties": {
    "addr:full":"129 W Wilson Street Suite 200 Costa Mesa CA 92627",
    "addr:housenumber":"129",
    "addr:postcode":"92627",
    "addr:street":"W Wilson Street Suite 200",
    "iso:country":"US",
    "sg:address":"129 W Wilson Street Suite 200",
    "sg:city":"Costa Mesa",
    "sg:classifiers":[
        {
            "category":"Professional",
            "subcategory":"Lawyer & Legal Services",
            "type":"Services"
        }
    ],
    "sg:phone":"+1 949 722 7500",
    "sg:postcode":"92627",
    "sg:province":"CA",
    "sg:website":"www.fewel-associates.com",
    "wof:name":"Concolino & Associates",
    "wof:placetype":"venue"
},
  "geometry": {"coordinates":[-117.90573500000001,33.656285],"type":"Point"}
}