{
  "type": "Feature",
  "properties": {
    "addr:full":"293 S Washington St Sonora CA 95370",
    "addr:housenumber":"293",
    "addr:postcode":"95370",
    "addr:street":"S Washington St",
    "iso:country":"US",
    "sg:address":"293 S Washington St",
    "sg:city":"Sonora",
    "sg:classifiers":[
        {
            "category":"Restaurant",
            "type":"Food & Drink"
        }
    ],
    "sg:phone":"+1 209 532 6442",
    "sg:postcode":"95370",
    "sg:province":"CA",
    "wof:name":"Nan King Chinese Food",
    "wof:placetype":"venue"
},
  "geometry": {"coordinates":[-120.382105,37.981422],"type":"Point"}
}