{
  "type": "Feature",
  "properties": {
    "iso:country":"US",
    "sg:address":"6200 Van Buren Blvd",
    "sg:city":"Riverside",
    "sg:classifiers":[
        {
            "category":"Insurance",
            "subcategory":"Insurance Agent",
            "type":"Services"
        }
    ],
    "sg:phone":"+1 951 710 1100",
    "sg:postcode":"92503",
    "sg:province":"CA",
    "wof:name":"Adriana's Insurance",
    "wof:placetype":"venue"
},
  "geometry": {"coordinates":[-117.45398,33.944296],"type":"Point"}
}