{
  "type": "Feature",
  "properties": {
    "addr:full":"7540 Batavia Rd Dixon CA 95620",
    "addr:housenumber":"7540",
    "addr:postcode":"95620",
    "addr:street":"Batavia Rd",
    "iso:country":"US",
    "sg:address":"7540 Batavia Rd",
    "sg:city":"Dixon",
    "sg:classifiers":[
        {
            "category":"Real Estate",
            "subcategory":"Real Estate Operator",
            "type":"Services"
        }
    ],
    "sg:phone":"+1 707 678 5227",
    "sg:postcode":"95620",
    "sg:province":"CA",
    "sg:tags":[
        "property",
        "lessor"
    ],
    "wof:name":"Achilles E Panizza Inc",
    "wof:placetype":"venue"
},
  "geometry": {"coordinates":[-121.85870300000001,38.444526],"type":"Point"}
}