{
  "type": "Feature",
  "properties": {
    "addr:full":"2445 Morena Boulevard San Diego CA 92110",
    "addr:housenumber":"2445",
    "addr:postcode":"92110",
    "addr:street":"Morena Boulevard",
    "iso:country":"US",
    "sg:address":"2445 Morena Boulevard",
    "sg:city":"San Diego",
    "sg:classifiers":[
        {
            "category":"Real Estate",
            "subcategory":"Real Estate Services",
            "type":"Services"
        }
    ],
    "sg:phone":"+1 619 275 3455",
    "sg:postcode":"92110",
    "sg:province":"CA",
    "sg:tags":[
        "management",
        "property"
    ],
    "wof:name":"Juno Property Management",
    "wof:placetype":"venue"
},
  "geometry": {"coordinates":[-117.20601600000001,32.787737],"type":"Point"}
}