{
  "type": "Feature",
  "properties": {
    "addr:full":"3210 W Center St Anderson CA 96007",
    "addr:housenumber":"3210",
    "addr:postcode":"96007",
    "addr:street":"W Center St",
    "iso:country":"US",
    "sg:address":"3210 W Center St",
    "sg:city":"Anderson",
    "sg:classifiers":[
        {
            "category":"Organizations",
            "subcategory":"Non-profit Organization",
            "type":"Services"
        }
    ],
    "sg:phone":"+1 530 365 9650",
    "sg:postcode":"96007",
    "sg:province":"CA",
    "wof:name":"Veterans Of Foreign Wars",
    "wof:placetype":"venue"
},
  "geometry": {"coordinates":[-122.30502199999999,40.452468],"type":"Point"}
}