{
  "type": "Feature",
  "properties": {
    "addr:full":"1545 E Locust St Ontario CA 91761",
    "addr:housenumber":"1545",
    "addr:postcode":"91761",
    "addr:street":"E Locust St",
    "iso:country":"US",
    "sg:address":"1545 E Locust St",
    "sg:city":"Ontario",
    "sg:classifiers":[
        {
            "category":"Shopping",
            "subcategory":"Clothing, Apparel, & Fashions",
            "type":"Retail Goods"
        }
    ],
    "sg:phone":"+1 909 395 5140",
    "sg:postcode":"91761",
    "sg:province":"CA",
    "wof:name":"Sharper Image",
    "wof:placetype":"venue"
},
  "geometry": {"coordinates":[-117.62016800000001,34.044957],"type":"Point"}
}