{
  "type": "Feature",
  "properties": {
    "addr:full":"8451 Miralani Dr San Diego CA 92126",
    "addr:housenumber":"8451",
    "addr:postcode":"92126",
    "addr:street":"Miralani Dr",
    "iso:country":"US",
    "sg:address":"8451 Miralani Dr",
    "sg:city":"San Diego",
    "sg:classifiers":[
        {
            "category":"Building & Trades",
            "subcategory":"Construction",
            "type":"Services"
        }
    ],
    "sg:phone":"+1 858 566 9266",
    "sg:postcode":"92126",
    "sg:province":"CA",
    "sg:tags":[
        "resurfacing",
        "laying",
        "refinishing",
        "floor"
    ],
    "wof:name":"Discount Hardwood Flooring",
    "wof:placetype":"venue"
},
  "geometry": {"coordinates":[-117.140372,32.896024],"type":"Point"}
}