{
  "type": "Feature",
  "properties": {
    "addr:full":"15179 Hesperian Blvd San Leandro CA 94578",
    "addr:housenumber":"15179",
    "addr:postcode":"94578",
    "addr:street":"Hesperian Blvd",
    "iso:country":"US",
    "sg:address":"15179 Hesperian Blvd",
    "sg:city":"San Leandro",
    "sg:classifiers":[
        {
            "category":"Fast Food",
            "type":"Food & Drink"
        }
    ],
    "sg:phone":"+1 510 276 7666",
    "sg:postcode":"94578",
    "sg:province":"CA",
    "wof:name":"KFC",
    "wof:placetype":"venue"
},
  "geometry": {"coordinates":[-122.129997,37.698799],"type":"Point"}
}