{
  "type": "Feature",
  "properties": {
    "addr:full":"8120 Tianna Rd Los Angeles CA 90046",
    "addr:housenumber":"8120",
    "addr:postcode":"90046",
    "addr:street":"Tianna Rd",
    "iso:country":"US",
    "sg:address":"8120 Tianna Rd",
    "sg:city":"Los Angeles",
    "sg:classifiers":[
        {
            "category":"Travel",
            "subcategory":"Travel Agent",
            "type":"Entertainment"
        }
    ],
    "sg:phone":"+1 323 650 0255",
    "sg:postcode":"90046",
    "sg:province":"CA",
    "sg:tags":[
        "operator",
        "tour"
    ],
    "wof:name":"Jazz Dagen Tours",
    "wof:placetype":"venue"
},
  "geometry": {"coordinates":[-118.375782,34.115729],"type":"Point"}
}