{
  "type": "Feature",
  "properties": {
    "iso:country":"US",
    "sg:address":"1623 5th St",
    "sg:city":"Davis",
    "sg:classifiers":[
        {
            "category":"Communications",
            "subcategory":"Film & Video Production",
            "type":"Services"
        }
    ],
    "sg:phone":"+1 530 756 0603",
    "sg:postcode":"95616",
    "sg:province":"CA",
    "sg:tags":[
        "taping"
    ],
    "sg:website":"www.cinnabarvideo.com",
    "wof:name":"Cinnabar Video Productions",
    "wof:placetype":"venue"
},
  "geometry": {"coordinates":[-121.730127,38.54879],"type":"Point"}
}