{
  "type": "Feature",
  "properties": {
    "addr:full":"6413 Plaquemines Dr Bakersfield CA 93309",
    "addr:housenumber":"6413",
    "addr:postcode":"93309",
    "addr:street":"Plaquemines Dr",
    "iso:country":"US",
    "sg:address":"6413 Plaquemines Dr",
    "sg:city":"Bakersfield",
    "sg:classifiers":[
        {
            "category":"Retail",
            "subcategory":"Animal Services",
            "type":"Services"
        }
    ],
    "sg:phone":"+1 661 322 4542",
    "sg:postcode":"93309",
    "sg:province":"CA",
    "sg:tags":[
        "pet",
        "grooming",
        "washing"
    ],
    "wof:name":"Proud Pooch",
    "wof:placetype":"venue"
},
  "geometry": {"coordinates":[-119.075885,35.320035],"type":"Point"}
}