{
  "type": "Feature",
  "properties": {
    "addr:full":"73330 El Paseo Ste D Palm Desert CA 92260",
    "addr:housenumber":"73330",
    "addr:postcode":"ca 92260",
    "addr:street":"El Paseo Ste D",
    "iso:country":"US",
    "sg:address":"73330 El Paseo Ste D",
    "sg:city":"Palm Desert",
    "sg:classifiers":[
        {
            "category":"Arts & Performance",
            "subcategory":"Arts Center",
            "type":"Entertainment"
        }
    ],
    "sg:phone":"+1 760 773 2380",
    "sg:postcode":"92260",
    "sg:province":"CA",
    "sg:tags":[
        "performing"
    ],
    "wof:name":"SHARON ARDELLE",
    "wof:placetype":"venue"
},
  "geometry": {"coordinates":[-116.385488,33.719963],"type":"Point"}
}