{
  "type": "Feature",
  "properties": {
    "iso:country":"US",
    "sg:address":"13320 Riverside Dr",
    "sg:city":"Sherman Oaks",
    "sg:classifiers":[
        {
            "category":"Health Services",
            "subcategory":"Doctor",
            "type":"Services"
        }
    ],
    "sg:phone":"+1 818 728 4889",
    "sg:postcode":"91423",
    "sg:province":"CA",
    "sg:tags":[
        "physician",
        "surgeon"
    ],
    "wof:name":"Michael Franco & Assoc",
    "wof:placetype":"venue"
},
  "geometry": {"coordinates":[-118.42336400000001,34.157537],"type":"Point"}
}