{
  "type": "Feature",
  "properties": {
    "addr:full":"19106 S Normandie Ave Torrance CA 90510",
    "addr:housenumber":"19106",
    "addr:postcode":"90510",
    "addr:street":"S Normandie Ave",
    "iso:country":"US",
    "sg:address":"19106 S Normandie Ave",
    "sg:city":"Torrance",
    "sg:classifiers":[
        {
            "category":"Restaurant",
            "type":"Food & Drink"
        }
    ],
    "sg:postcode":"90510",
    "sg:province":"CA",
    "sg:tags":[
        "breakfast",
        "brunch"
    ],
    "sg:website":"www.saxbyscoffee.com",
    "wof:name":"Saxbys Coffee",
    "wof:placetype":"venue"
},
  "geometry": {"coordinates":[-118.29956900000001,33.863794],"type":"Point"}
}