{
  "type": "Feature",
  "properties": {
    "addr:full":"151 N Sunrise Ave Roseville CA 95661",
    "addr:housenumber":"151",
    "addr:postcode":"95661",
    "addr:street":"N Sunrise Ave",
    "iso:country":"US",
    "sg:address":"151 N Sunrise Ave",
    "sg:city":"Roseville",
    "sg:classifiers":[
        {
            "category":"Health Services",
            "subcategory":"Chiropractor",
            "type":"Services"
        }
    ],
    "sg:phone":"+1 916 781 8022",
    "sg:postcode":"95661",
    "sg:province":"CA",
    "wof:name":"Dame Chiropractic",
    "wof:placetype":"venue"
},
  "geometry": {"coordinates":[-121.265781,38.747258],"type":"Point"}
}