{
  "type": "Feature",
  "properties": {
    "addr:full":"10908 Technology Place San Diego CA 92127",
    "addr:housenumber":"10908",
    "addr:postcode":"92127",
    "addr:street":"Technology Place",
    "iso:country":"US",
    "sg:address":"10908 Technology Place",
    "sg:city":"San Diego",
    "sg:classifiers":[
        {
            "category":"Manufacturing",
            "subcategory":"Electronics",
            "type":"Manufacturing & Wholesale Goods"
        }
    ],
    "sg:phone":"+1 858 385 5131",
    "sg:postcode":"92127",
    "sg:province":"CA",
    "wof:name":"Tarari",
    "wof:placetype":"venue"
},
  "geometry": {"coordinates":[-117.09263,33.008658],"type":"Point"}
}