{
  "type": "Feature",
  "properties": {
    "addr:full":"8871 Lawrence Ave Westminster CA 92683",
    "addr:housenumber":"8871",
    "addr:postcode":"92683",
    "addr:street":"Lawrence Ave",
    "iso:country":"US",
    "sg:address":"8871 Lawrence Ave",
    "sg:city":"Westminster",
    "sg:classifiers":[
        {
            "category":"Building & Trades",
            "subcategory":"Construction",
            "type":"Services"
        }
    ],
    "sg:phone":"+1 714 841 9795",
    "sg:postcode":"92683",
    "sg:province":"CA",
    "sg:tags":[
        "painter"
    ],
    "wof:name":"A-Cal Wall Coverings",
    "wof:placetype":"venue"
},
  "geometry": {"coordinates":[-117.974701,33.729775],"type":"Point"}
}