{
  "type": "Feature",
  "properties": {
    "addr:full":"1052 N Hacienda Blvd La Puente CA 91744",
    "addr:housenumber":"1052",
    "addr:postcode":"91744",
    "addr:street":"N Hacienda Blvd",
    "iso:country":"US",
    "sg:address":"1052 N Hacienda Blvd",
    "sg:city":"La Puente",
    "sg:classifiers":[
        {
            "category":"Personal",
            "subcategory":"Beauty Salon",
            "type":"Services"
        }
    ],
    "sg:phone":"+1 626 917 4042",
    "sg:postcode":"91744",
    "sg:province":"CA",
    "wof:name":"Daisy Skin Clinic",
    "wof:placetype":"venue"
},
  "geometry": {"coordinates":[-117.94984100000001,34.037252],"type":"Point"}
}