{
  "type": "Feature",
  "properties": {
    "iso:country":"US",
    "sg:address":"500 San Ramon Valley Blvd",
    "sg:city":"Danville",
    "sg:classifiers":[
        {
            "category":"Government",
            "subcategory":"Post Office",
            "type":"Public Place"
        }
    ],
    "sg:phone":"+1 925 362 0374",
    "sg:postcode":"94526",
    "sg:province":"CA",
    "sg:tags":[
        "mail",
        "voice",
        "system",
        "messaging"
    ],
    "wof:name":"International Video Conferenci",
    "wof:placetype":"venue"
},
  "geometry": {"coordinates":[-121.996582,37.818199],"type":"Point"}
}