{
  "type": "Feature",
  "properties": {
    "iso:country":"US",
    "sg:address":"2340 Palma Dr",
    "sg:city":"Ventura",
    "sg:classifiers":[
        {
            "category":"Professional",
            "subcategory":"Engineering",
            "type":"Services"
        }
    ],
    "sg:phone":"+1 805 642 3636",
    "sg:postcode":"93003",
    "sg:province":"CA",
    "sg:tags":[
        "engineer"
    ],
    "wof:name":"DBS Engineering Inc",
    "wof:placetype":"venue"
},
  "geometry": {"coordinates":[-119.227297,34.252278],"type":"Point"}
}