{
  "type": "Feature",
  "properties": {
    "addr:full":"2707 N Glenoaks Blvd Burbank CA 91504",
    "addr:housenumber":"2707",
    "addr:postcode":"91504",
    "addr:street":"N Glenoaks Blvd",
    "iso:country":"US",
    "sg:address":"2707 N Glenoaks Blvd",
    "sg:city":"Burbank",
    "sg:phone":"+1 818 842 5103",
    "sg:postcode":"91504",
    "sg:province":"CA",
    "wof:name":"First Presbyterian Church",
    "wof:placetype":"venue"
},
  "geometry": {"coordinates":[-118.333459,34.20259],"type":"Point"}
}