{
  "type": "Feature",
  "properties": {
    "iso:country":"US",
    "sg:address":"4823 Canyon Trail Way",
    "sg:city":"San Jose",
    "sg:classifiers":[
        {
            "category":"Professional",
            "type":"Services"
        }
    ],
    "sg:phone":"+1 408 227 2383",
    "sg:postcode":"95136",
    "sg:province":"CA",
    "wof:name":"Smartplastic",
    "wof:placetype":"venue"
},
  "geometry": {"coordinates":[-121.823319,37.265918],"type":"Point"}
}