{
  "type": "Feature",
  "properties": {
    "addr:full":"5930 W Coast Hwy Newport Beach CA 92663",
    "addr:housenumber":"5930",
    "addr:postcode":"92663",
    "addr:street":"W Coast Hwy",
    "iso:country":"US",
    "sg:address":"5930 W Coast Hwy",
    "sg:city":"Newport Beach",
    "sg:classifiers":[
        {
            "category":"Restaurant",
            "type":"Food & Drink"
        }
    ],
    "sg:phone":"+1 949 646 4202",
    "sg:postcode":"92663",
    "sg:province":"CA",
    "wof:name":"Cappy's Cafe",
    "wof:placetype":"venue"
},
  "geometry": {"coordinates":[-117.94699900000001,33.625599],"type":"Point"}
}