{
  "type": "Feature",
  "properties": {
    "addr:full":"3407 Glendale Blvd Los Angeles CA 90189",
    "addr:housenumber":"3407",
    "addr:postcode":"90189",
    "addr:street":"Glendale Blvd",
    "iso:country":"US",
    "sg:address":"3407 Glendale Blvd",
    "sg:city":"Los Angeles",
    "sg:classifiers":[
        {
            "category":"Arts & Performance",
            "subcategory":"Arts Center",
            "type":"Entertainment"
        },
        {
            "category":"Education",
            "subcategory":"School",
            "type":"Public Place"
        }
    ],
    "sg:phone":"+1 323 660 4556",
    "sg:postcode":"90189",
    "sg:province":"CA",
    "sg:tags":[
        "performing"
    ],
    "sg:website":"www.dancegardenla.com",
    "wof:name":"DanceGarden",
    "wof:placetype":"venue"
},
  "geometry": {"coordinates":[-118.258712,34.120111],"type":"Point"}
}