{
  "type": "Feature",
  "properties": {
    "addr:full":"682 Ridgeview Ter Fremont CA 94536",
    "addr:housenumber":"682",
    "addr:postcode":"94536",
    "addr:street":"Ridgeview Ter",
    "iso:country":"US",
    "sg:address":"682 Ridgeview Ter",
    "sg:city":"Fremont",
    "sg:classifiers":[
        {
            "category":"Professional",
            "subcategory":"Computer Services",
            "type":"Services"
        }
    ],
    "sg:phone":"+1 510 713 9868",
    "sg:postcode":"94536",
    "sg:province":"CA",
    "sg:tags":[
        "graphics"
    ],
    "wof:name":"Digital Lightwave",
    "wof:placetype":"venue"
},
  "geometry": {"coordinates":[-121.971161,37.564478],"type":"Point"}
}