{
  "type": "Feature",
  "properties": {
    "addr:full":"68703 Perez Rd Cathedral City CA 92234",
    "addr:housenumber":"68703",
    "addr:postcode":"92234",
    "addr:street":"Perez Rd",
    "iso:country":"US",
    "sg:address":"68703 Perez Rd",
    "sg:city":"Cathedral City",
    "sg:classifiers":[
        {
            "category":"Professional",
            "type":"Services"
        },
        {
            "category":"Professional",
            "subcategory":"Accounting & Tax Preparation",
            "type":"Services"
        }
    ],
    "sg:phone":"+1 760 328 3166",
    "sg:postcode":"92234",
    "sg:province":"CA",
    "sg:tags":[
        "billing"
    ],
    "wof:name":"Med Bill & Prosessionals",
    "wof:placetype":"venue"
},
  "geometry": {"coordinates":[-116.46526299999999,33.784799],"type":"Point"}
}