{
  "type": "Feature",
  "properties": {
    "iso:country":"US",
    "sg:address":"23131 Lake Center Dr",
    "sg:city":"Lake Forest",
    "sg:classifiers":[
        {
            "category":"Personal",
            "type":"Services"
        }
    ],
    "sg:phone":"+1 949 472 0075",
    "sg:postcode":"92630",
    "sg:province":"CA",
    "sg:tags":[
        "spa",
        "therapist",
        "day",
        "massage"
    ],
    "sg:website":"www.bodycentredayspa.com",
    "wof:name":"BodyCentre Day Spa",
    "wof:placetype":"venue"
},
  "geometry": {"coordinates":[-117.716559,33.626539],"type":"Point"}
}