{
  "type": "Feature",
  "properties": {
    "addr:full":"413 N Green St Tehachapi CA 93561",
    "addr:housenumber":"413",
    "addr:postcode":"93561",
    "addr:street":"N Green St",
    "iso:country":"US",
    "sg:address":"413 N Green St",
    "sg:city":"Tehachapi",
    "sg:classifiers":[
        {
            "category":"Banks & Credit Unions",
            "subcategory":"Financial Services",
            "type":"Services"
        }
    ],
    "sg:phone":"+1 661 822 0320",
    "sg:postcode":"93561",
    "sg:province":"CA",
    "sg:tags":[
        "international",
        "trade"
    ],
    "wof:name":"Lec World Traders",
    "wof:placetype":"venue"
},
  "geometry": {"coordinates":[-118.44656999999999,35.136412],"type":"Point"}
}