{
  "type": "Feature",
  "properties": {
    "addr:full":"2101 Corporate Center Drive Thousand Oaks CA 91320",
    "addr:housenumber":"2101",
    "addr:postcode":"91320",
    "addr:street":"Corporate Center Drive",
    "iso:country":"US",
    "sg:address":"2101 Corporate Center Drive",
    "sg:city":"Thousand Oaks",
    "sg:classifiers":[
        {
            "category":"Professional",
            "subcategory":"Computer Services",
            "type":"Services"
        }
    ],
    "sg:phone":"+1 805 262 1600",
    "sg:postcode":"91320",
    "sg:province":"CA",
    "sg:website":"http://www.xirrus.com/",
    "wof:name":"Xirrus",
    "wof:placetype":"venue"
},
  "geometry": {"coordinates":[-118.927288,34.196997],"type":"Point"}
}