{
  "type": "Feature",
  "properties": {
    "iso:country":"US",
    "sg:address":"845 S Broadway",
    "sg:city":"Los Angeles",
    "sg:classifiers":[
        {
            "category":"Food & Beverages",
            "subcategory":"Groceries & Convenience Stores",
            "type":"Retail Goods"
        }
    ],
    "sg:phone":"+1 213 488 9971",
    "sg:postcode":"90014",
    "sg:province":"CA",
    "sg:tags":[
        "grocer"
    ],
    "wof:name":"Hola Market",
    "wof:placetype":"venue"
},
  "geometry": {"coordinates":[-118.255616,34.043023],"type":"Point"}
}