{
  "type": "Feature",
  "properties": {
    "addr:full":"40155 Enterprise Dr Oakhurst CA 93644",
    "addr:housenumber":"40155",
    "addr:postcode":"93644",
    "addr:street":"Enterprise Dr",
    "iso:country":"US",
    "sg:address":"40155 Enterprise Dr",
    "sg:city":"Oakhurst",
    "sg:classifiers":[
        {
            "category":"Wholesale",
            "subcategory":"Construction Materials",
            "type":"Manufacturing & Wholesale Goods"
        }
    ],
    "sg:phone":"+1 559 642 4283",
    "sg:postcode":"93644",
    "sg:province":"CA",
    "sg:tags":[
        "gates",
        "trade",
        "contractor"
    ],
    "wof:name":"Dunham's Classic Gates",
    "wof:placetype":"venue"
},
  "geometry": {"coordinates":[-119.66257899999999,37.332712],"type":"Point"}
}