{
  "type": "Feature",
  "properties": {
    "addr:full":"999 N Tustin Ave Ste Tustin CA 92780",
    "addr:housenumber":"999",
    "addr:postcode":"92780",
    "addr:street":"N Tustin Ave Ste",
    "iso:country":"US",
    "sg:address":"999 N Tustin Ave Ste",
    "sg:city":"Tustin",
    "sg:classifiers":[
        {
            "category":"Health Services",
            "subcategory":"Doctor",
            "type":"Services"
        }
    ],
    "sg:phone":"+1 714 543 9927",
    "sg:postcode":"92780",
    "sg:province":"CA",
    "wof:name":"West Coast Breast Center",
    "wof:placetype":"venue"
},
  "geometry": {"coordinates":[-117.82399700000001,33.740898],"type":"Point"}
}