{
  "type": "Feature",
  "properties": {
    "addr:full":"6606 Seville Ave Huntington Park CA 90255",
    "addr:housenumber":"6606",
    "addr:postcode":"90255",
    "addr:street":"Seville Ave;Park",
    "iso:country":"US",
    "sg:address":"6606 Seville Ave",
    "sg:city":"Huntington Park",
    "sg:classifiers":[
        {
            "category":"Government",
            "subcategory":"Post Office",
            "type":"Public Place"
        }
    ],
    "sg:phone":"+1 323 000 1111",
    "sg:postcode":"90255",
    "sg:province":"CA",
    "wof:name":"US Post Office",
    "wof:placetype":"venue"
},
  "geometry": {"coordinates":[-118.222407,33.976952],"type":"Point"}
}