{
  "type": "Feature",
  "properties": {
    "iso:country":"US",
    "sg:address":"4203 Smith Grade",
    "sg:city":"Santa Cruz",
    "sg:classifiers":[
        {
            "category":"Manufacturing",
            "subcategory":"Aerospace",
            "type":"Manufacturing & Wholesale Goods"
        }
    ],
    "sg:phone":"+1 831 425 6000",
    "sg:postcode":"95060",
    "sg:province":"CA",
    "sg:tags":[
        "aircraft",
        "mfg"
    ],
    "wof:name":"Lockheed Martin",
    "wof:placetype":"venue"
},
  "geometry": {"coordinates":[-122.133126,37.023891],"type":"Point"}
}