{
  "type": "Feature",
  "properties": {
    "addr:full":"13204 Norris Ave Sylmar CA 91342",
    "addr:housenumber":"13204",
    "addr:postcode":"91342",
    "addr:street":"Norris Ave",
    "iso:country":"US",
    "sg:address":"13204 Norris Ave",
    "sg:city":"Sylmar",
    "sg:classifiers":[
        {
            "category":"Professional",
            "subcategory":"Accounting & Tax Preparation",
            "type":"Services"
        }
    ],
    "sg:phone":"+1 818 362 2485",
    "sg:postcode":"91342",
    "sg:province":"CA",
    "sg:tags":[
        "return",
        "filing"
    ],
    "wof:name":"Enoch Martinez Tax Svc",
    "wof:placetype":"venue"
},
  "geometry": {"coordinates":[-118.46409800000001,34.311352],"type":"Point"}
}