{
  "type": "Feature",
  "properties": {
    "addr:full":"528 Larkin St San Francisco CA 94102",
    "addr:housenumber":"528",
    "addr:postcode":"94102",
    "addr:street":"Larkin St",
    "iso:country":"US",
    "sg:address":"528 Larkin St",
    "sg:city":"San Francisco",
    "sg:classifiers":[
        {
            "category":"Professional",
            "subcategory":"Printing & Photocopies",
            "type":"Services"
        }
    ],
    "sg:phone":"+1 415 343 3777",
    "sg:postcode":"94102",
    "sg:province":"CA",
    "sg:tags":[
        "duplicating",
        "copying"
    ],
    "wof:name":"K K Copying & Printing",
    "wof:placetype":"venue"
},
  "geometry": {"coordinates":[-122.417412,37.783057],"type":"Point"}
}