{
  "type": "Feature",
  "properties": {
    "iso:country":"US",
    "sg:address":"8634 Holloway Dr",
    "sg:city":"West Hollywood",
    "sg:classifiers":[
        {
            "category":"Place Of Worship",
            "subcategory":"Church",
            "type":"Public Place"
        }
    ],
    "sg:phone":"+1 310 652 6477",
    "sg:postcode":"90069",
    "sg:province":"CA",
    "wof:name":"St Victor West Hollywood",
    "wof:placetype":"venue"
},
  "geometry": {"coordinates":[-118.379997,34.090698],"type":"Point"}
}