{
  "type": "Feature",
  "properties": {
    "addr:full":"42455 Washington St Palm Desert CA 92211",
    "addr:housenumber":"42455",
    "addr:postcode":"92211",
    "addr:street":"Washington St",
    "iso:country":"US",
    "sg:address":"42455 Washington St",
    "sg:city":"Palm Desert",
    "sg:classifiers":[
        {
            "category":"Real Estate",
            "subcategory":"Real Estate Operator",
            "type":"Services"
        }
    ],
    "sg:phone":"+1 760 345 2547",
    "sg:postcode":"92211",
    "sg:province":"CA",
    "sg:tags":[
        "apartment"
    ],
    "wof:name":"Palm Desert Country Village",
    "wof:placetype":"venue"
},
  "geometry": {"coordinates":[-116.303855,33.739608],"type":"Point"}
}