{
  "type": "Feature",
  "properties": {
    "addr:full":"3332 Balzac St Alhambra CA 91803",
    "addr:housenumber":"3332",
    "addr:postcode":"91803",
    "addr:street":"Balzac St",
    "iso:country":"US",
    "sg:address":"3332 Balzac St",
    "sg:city":"Alhambra",
    "sg:classifiers":[
        {
            "category":"Retail",
            "subcategory":"Repair Shop",
            "type":"Services"
        }
    ],
    "sg:phone":"+1 626 286 1214",
    "sg:postcode":"91803",
    "sg:province":"CA",
    "sg:tags":[
        "plumbing",
        "drain",
        "cleaning",
        "sewer"
    ],
    "wof:name":"Rapid Rooter",
    "wof:placetype":"venue"
},
  "geometry": {"coordinates":[-118.162481,34.063576],"type":"Point"}
}