{
  "type": "Feature",
  "properties": {
    "iso:country":"US",
    "sg:address":"1819 Ave Feliciano",
    "sg:city":"Rancho Pls Vrds",
    "sg:classifiers":[
        {
            "category":"Home & Garden",
            "subcategory":"Home Furnishings",
            "type":"Retail Goods"
        }
    ],
    "sg:phone":"+1 310 833 1485",
    "sg:postcode":"90275",
    "sg:province":"CA",
    "sg:tags":[
        "linen"
    ],
    "wof:name":"Linen Closet",
    "wof:placetype":"venue"
},
  "geometry": {"coordinates":[-118.310535,33.769301],"type":"Point"}
}