{
  "type": "Feature",
  "properties": {
    "iso:country":"US",
    "sg:address":"1122 Branham Ln",
    "sg:city":"San Jose",
    "sg:classifiers":[
        {
            "category":"Shopping",
            "subcategory":"Beauty & Cosmetics",
            "type":"Retail Goods"
        }
    ],
    "sg:phone":"+1 408 978 4775",
    "sg:postcode":"95118",
    "sg:province":"CA",
    "sg:tags":[
        "supply"
    ],
    "wof:name":"Beauty 101",
    "wof:placetype":"venue"
},
  "geometry": {"coordinates":[-121.87821,37.262483],"type":"Point"}
}