{
  "type": "Feature",
  "properties": {
    "addr:full":"870 Oceanside St Wilmington CA 90744",
    "addr:housenumber":"870",
    "addr:postcode":"90744",
    "addr:street":"Oceanside St",
    "iso:country":"US",
    "sg:address":"870 Oceanside St",
    "sg:city":"Wilmington",
    "sg:classifiers":[
        {
            "category":"Government",
            "subcategory":"Office",
            "type":"Public Place"
        }
    ],
    "sg:phone":"+1 310 549 7392",
    "sg:postcode":"90744",
    "sg:province":"CA",
    "sg:tags":[
        "executive"
    ],
    "wof:name":"National Assoc of Governm",
    "wof:placetype":"venue"
},
  "geometry": {"coordinates":[-118.258498,33.803033],"type":"Point"}
}