{
  "type": "Feature",
  "properties": {
    "iso:country":"US",
    "sg:address":"19950 Kings Creek Rd",
    "sg:city":"Boulder Creek",
    "sg:classifiers":[
        {
            "category":"Personal",
            "type":"Services"
        }
    ],
    "sg:phone":"+1 831 338 2637",
    "sg:postcode":"95006",
    "sg:province":"CA",
    "sg:tags":[
        "miscellaneous"
    ],
    "wof:name":"Healthful Cooking & Massage",
    "wof:placetype":"venue"
},
  "geometry": {"coordinates":[-122.119135,37.200088],"type":"Point"}
}