{
  "type": "Feature",
  "properties": {
    "addr:full":"7131 Pacific Boulevard Huntington Park CA 90255",
    "addr:housenumber":"7131",
    "addr:postcode":"90255",
    "addr:street":"Pacific Boulevard;Park",
    "iso:country":"US",
    "sg:address":"7131 Pacific Boulevard",
    "sg:city":"Huntington Park",
    "sg:classifiers":[
        {
            "category":"Shopping",
            "subcategory":"Shoes",
            "type":"Retail Goods"
        }
    ],
    "sg:phone":"+1 323 589 0121",
    "sg:postcode":"90255",
    "sg:province":"CA",
    "sg:tags":[
        "store"
    ],
    "wof:name":"Jumping Shoes & Socks",
    "wof:placetype":"venue"
},
  "geometry": {"coordinates":[-118.225099,33.974546],"type":"Point"}
}