{
  "type": "Feature",
  "properties": {
    "addr:full":"3215 N Alameda St Compton CA 90222",
    "addr:housenumber":"3215",
    "addr:postcode":"90222",
    "addr:street":"N Alameda St",
    "iso:country":"US",
    "sg:address":"3215 N Alameda St",
    "sg:city":"Compton",
    "sg:classifiers":[
        {
            "category":"Home & Garden",
            "subcategory":"Carpets & Floor Coverings",
            "type":"Retail Goods"
        }
    ],
    "sg:phone":"+1 310 223 1766",
    "sg:postcode":"90222",
    "sg:province":"CA",
    "sg:tags":[
        "installation",
        "rug"
    ],
    "wof:name":"V T P Inc.",
    "wof:placetype":"venue"
},
  "geometry": {"coordinates":[-118.223894,33.921493],"type":"Point"}
}