{
  "type": "Feature",
  "properties": {
    "addr:full":"68 E Younger Ave San Jose CA 95112",
    "addr:housenumber":"68",
    "addr:postcode":"95112",
    "addr:street":"E Younger Ave",
    "iso:country":"US",
    "sg:address":"68 E Younger Ave",
    "sg:city":"San Jose",
    "sg:classifiers":[
        {
            "category":"Building & Trades",
            "subcategory":"Construction",
            "type":"Services"
        }
    ],
    "sg:phone":"+1 408 292 5066",
    "sg:postcode":"95112",
    "sg:province":"CA",
    "sg:tags":[
        "contractor"
    ],
    "wof:name":"Benning Construction & Dev",
    "wof:placetype":"venue"
},
  "geometry": {"coordinates":[-121.902929,37.355892],"type":"Point"}
}