{
  "type": "Feature",
  "properties": {
    "addr:full":"24301 Grass St Lake Forest CA 92630",
    "addr:housenumber":"24301",
    "addr:postcode":"92630",
    "addr:street":"Grass St",
    "iso:country":"US",
    "sg:address":"24301 Grass St",
    "sg:city":"Lake Forest",
    "sg:classifiers":[
        {
            "category":"Retail",
            "subcategory":"Car Wash",
            "type":"Services"
        }
    ],
    "sg:phone":"+1 949 285 7517",
    "sg:postcode":"92630",
    "sg:province":"CA",
    "sg:tags":[
        "polishing",
        "washing"
    ],
    "wof:name":"Clean Clean Car Wash",
    "wof:placetype":"venue"
},
  "geometry": {"coordinates":[-117.69457800000001,33.609575],"type":"Point"}
}