{
  "type": "Feature",
  "properties": {
    "addr:full":"7168 Archibald Ave Alta Loma CA 91701",
    "addr:housenumber":"7168",
    "addr:postcode":"91701",
    "addr:street":"Archibald Ave",
    "iso:country":"US",
    "sg:address":"7168 Archibald Ave",
    "sg:city":"Alta Loma",
    "sg:classifiers":[
        {
            "category":"Real Estate",
            "subcategory":"Real Estate Agent",
            "type":"Services"
        }
    ],
    "sg:phone":"+1 909 945 3137",
    "sg:postcode":"91701",
    "sg:province":"CA",
    "wof:name":"Realty Exectives",
    "wof:placetype":"venue"
},
  "geometry": {"coordinates":[-117.593569,34.122174],"type":"Point"}
}