{
  "type": "Feature",
  "properties": {
    "addr:full":"2805 Taraval St San Francisco CA 94116",
    "addr:housenumber":"2805",
    "addr:postcode":"94116",
    "addr:street":"Taraval St",
    "iso:country":"US",
    "sg:address":"2805 Taraval St",
    "sg:city":"San Francisco",
    "sg:classifiers":[
        {
            "category":"Shopping",
            "type":"Retail Goods"
        }
    ],
    "sg:phone":"+1 415 681 8746",
    "sg:postcode":"94116",
    "sg:province":"CA",
    "sg:tags":[
        "merchandise"
    ],
    "wof:name":"Little Bargain Corner",
    "wof:placetype":"venue"
},
  "geometry": {"coordinates":[-122.497077,37.742031],"type":"Point"}
}