{
  "type": "Feature",
  "properties": {
    "addr:full":"10307 Saint Andrews Dr Oakdale CA 95361",
    "addr:housenumber":"10307",
    "addr:postcode":"95361",
    "addr:street":"Saint Andrews Dr",
    "iso:country":"US",
    "sg:address":"10307 Saint Andrews Dr",
    "sg:city":"Oakdale",
    "sg:classifiers":[
        {
            "category":"Real Estate",
            "subcategory":"Real Estate Agent",
            "type":"Services"
        }
    ],
    "sg:phone":"+1 209 847 0029",
    "sg:postcode":"95361",
    "sg:province":"CA",
    "wof:name":"Anthony J Dossi",
    "wof:placetype":"venue"
},
  "geometry": {"coordinates":[-120.80712699999999,37.778743],"type":"Point"}
}