{
  "type": "Feature",
  "properties": {
    "addr:full":"1926 Gomez Ct Tulare CA 93274",
    "addr:housenumber":"1926",
    "addr:postcode":"93274",
    "addr:street":"Gomez Ct",
    "iso:country":"US",
    "sg:address":"1926 Gomez Ct",
    "sg:city":"Tulare",
    "sg:classifiers":[
        {
            "category":"Food & Beverages",
            "subcategory":"Bakery",
            "type":"Retail Goods"
        }
    ],
    "sg:phone":"+1 559 685 0461",
    "sg:postcode":"93274",
    "sg:province":"CA",
    "sg:tags":[
        "doughnut"
    ],
    "wof:name":"Donut Factory",
    "wof:placetype":"venue"
},
  "geometry": {"coordinates":[-119.314116,36.205585],"type":"Point"}
}