{
  "type": "Feature",
  "properties": {
    "addr:full":"9260 Old Redwood Hwy Penngrove CA 94951",
    "addr:housenumber":"9260",
    "addr:postcode":"94951",
    "addr:street":"Old Redwood Hwy",
    "iso:country":"US",
    "sg:address":"9260 Old Redwood Hwy",
    "sg:city":"Penngrove",
    "sg:classifiers":[
        {
            "category":"Building & Trades",
            "subcategory":"Plumbing",
            "type":"Services"
        }
    ],
    "sg:phone":"+1 707 794 7262",
    "sg:postcode":"94951",
    "sg:province":"CA",
    "sg:tags":[
        "heating",
        "contractor"
    ],
    "wof:name":"Browne Heating & Metal Works",
    "wof:placetype":"venue"
},
  "geometry": {"coordinates":[-122.69351899999999,38.313488],"type":"Point"}
}