{
  "type": "Feature",
  "properties": {
    "addr:full":"11401 Davenport Rd Los Alamitos CA 90720",
    "addr:housenumber":"11401",
    "addr:postcode":"90720",
    "addr:street":"Davenport Rd",
    "iso:country":"US",
    "sg:address":"11401 Davenport Rd",
    "sg:city":"Los Alamitos",
    "sg:classifiers":[
        {
            "category":"Building & Trades",
            "subcategory":"Construction",
            "type":"Services"
        }
    ],
    "sg:phone":"+1 562 431 8661",
    "sg:postcode":"90720",
    "sg:province":"CA",
    "sg:tags":[
        "contractor"
    ],
    "wof:name":"Fe Cusick Company General Contractors",
    "wof:placetype":"venue"
},
  "geometry": {"coordinates":[-118.072845,33.796983],"type":"Point"}
}