{
  "type": "Feature",
  "properties": {
    "addr:full":"520 Foothill Blvd La Canada Flintridge CA 91011",
    "addr:housenumber":"520",
    "addr:postcode":"91011",
    "addr:street":"Foothill Blvd",
    "iso:country":"US",
    "sg:address":"520 Foothill Blvd",
    "sg:city":"La Canada Flintridge",
    "sg:classifiers":[
        {
            "category":"Cinema",
            "subcategory":"Movie Rental",
            "type":"Entertainment"
        }
    ],
    "sg:phone":"+1 818 790 4050",
    "sg:postcode":"91011",
    "sg:province":"CA",
    "sg:tags":[
        "video",
        "game",
        "disc",
        "leasing",
        "tape"
    ],
    "wof:name":"La Canada Video",
    "wof:placetype":"venue"
},
  "geometry": {"coordinates":[-118.19000200000001,34.199902],"type":"Point"}
}