{
  "type": "Feature",
  "properties": {
    "addr:full":"951 Cll Negocio San Clemente CA 92673",
    "addr:housenumber":"951",
    "addr:postcode":"92673",
    "addr:street":"Cll Negocio",
    "iso:country":"US",
    "sg:address":"951 Cll Negocio",
    "sg:city":"San Clemente",
    "sg:classifiers":[
        {
            "category":"Wholesale",
            "subcategory":"Electrical",
            "type":"Manufacturing & Wholesale Goods"
        }
    ],
    "sg:phone":"+1 949 498 4000",
    "sg:postcode":"92673",
    "sg:province":"CA",
    "sg:tags":[
        "semiconductor"
    ],
    "wof:name":"ASQ Technology Inc",
    "wof:placetype":"venue"
},
  "geometry": {"coordinates":[-117.604938,33.452112],"type":"Point"}
}