{
  "type": "Feature",
  "properties": {
    "addr:full":"14104 Orange Ave Paramount CA 90723",
    "addr:housenumber":"14104",
    "addr:postcode":"90723",
    "addr:street":"Orange Ave",
    "iso:country":"US",
    "sg:address":"14104 Orange Ave",
    "sg:city":"Paramount",
    "sg:classifiers":[
        {
            "category":"Professional",
            "subcategory":"Testing Lab",
            "type":"Services"
        }
    ],
    "sg:phone":"+1 562 633 4824",
    "sg:postcode":"90723",
    "sg:province":"CA",
    "sg:tags":[
        "laboratory"
    ],
    "wof:name":"Ramtech Laboratories",
    "wof:placetype":"venue"
},
  "geometry": {"coordinates":[-118.177121,33.90598],"type":"Point"}
}