{
  "type": "Feature",
  "properties": {
    "iso:country":"US",
    "sg:address":"4035 Grass Valley Hwy",
    "sg:city":"Auburn",
    "sg:classifiers":[
        {
            "category":"Home & Garden",
            "subcategory":"Home Furnishings",
            "type":"Retail Goods"
        }
    ],
    "sg:phone":"+1 530 885 1857",
    "sg:postcode":"95602",
    "sg:province":"CA",
    "wof:name":"Euro Pewter Casting & Mfrs",
    "wof:placetype":"venue"
},
  "geometry": {"coordinates":[-121.101465,38.95714],"type":"Point"}
}