{
  "type": "Feature",
  "properties": {
    "iso:country":"US",
    "sg:address":"9950 Foothill Blvd",
    "sg:city":"Rancho Cucamonga",
    "sg:classifiers":[
        {
            "category":"Food & Beverages",
            "subcategory":"Bakery",
            "type":"Retail Goods"
        }
    ],
    "sg:phone":"+1 909 944 7472",
    "sg:postcode":"91730",
    "sg:province":"CA",
    "sg:tags":[
        "doughnut"
    ],
    "wof:name":"Fresh Donuts",
    "wof:placetype":"venue"
},
  "geometry": {"coordinates":[-117.58572700000001,34.106719],"type":"Point"}
}