{
  "type": "Feature",
  "properties": {
    "iso:country":"US",
    "sg:address":"17789 Sierra Hwy",
    "sg:city":"Canyon Country",
    "sg:classifiers":[
        {
            "category":"Building & Trades",
            "subcategory":"Construction",
            "type":"Services"
        }
    ],
    "sg:phone":"+1 661 298 9233",
    "sg:postcode":"91351",
    "sg:province":"CA",
    "sg:tags":[
        "house"
    ],
    "wof:name":"Barrette Contruction Company",
    "wof:placetype":"venue"
},
  "geometry": {"coordinates":[-118.444686,34.429178],"type":"Point"}
}