{
  "type": "Feature",
  "properties": {
    "iso:country":"US",
    "sg:address":"150 E Main St",
    "sg:city":"Tustin",
    "sg:classifiers":[
        {
            "category":"Shopping",
            "subcategory":"Clothing, Apparel, & Fashions",
            "type":"Retail Goods"
        },
        {
            "category":"Home & Garden",
            "subcategory":"Home Furnishings",
            "type":"Retail Goods"
        }
    ],
    "sg:phone":"+1 714 730 2182",
    "sg:postcode":"92780",
    "sg:province":"CA",
    "sg:tags":[
        "children's",
        "decor",
        "clothing"
    ],
    "sg:website":"www.idreamoffrance.com",
    "wof:name":"I Dream of France",
    "wof:placetype":"venue"
},
  "geometry": {"coordinates":[-117.82306699999999,33.742071],"type":"Point"}
}