{
  "type": "Feature",
  "properties": {
    "iso:country":"US",
    "sg:address":"616 Shrode Ave",
    "sg:city":"Duarte",
    "sg:classifiers":[
        {
            "category":"Personal",
            "subcategory":"Beauty Salon",
            "type":"Services"
        }
    ],
    "sg:phone":"+1 626 358 0743",
    "sg:postcode":"91010",
    "sg:province":"CA",
    "sg:tags":[
        "manicuring"
    ],
    "wof:name":"Laurle Nail Shop",
    "wof:placetype":"venue"
},
  "geometry": {"coordinates":[-117.992966,34.12138],"type":"Point"}
}