{
  "type": "Feature",
  "properties": {
    "addr:full":"106 E 17th St Los Angeles CA 90015",
    "addr:housenumber":"106",
    "addr:postcode":"90015",
    "addr:street":"E 17Th St",
    "iso:country":"US",
    "sg:address":"106 E 17th St",
    "sg:city":"Los Angeles",
    "sg:classifiers":[
        {
            "category":"Wholesale",
            "subcategory":"Apparel",
            "type":"Manufacturing & Wholesale Goods"
        }
    ],
    "sg:phone":"+1 213 746 3525",
    "sg:postcode":"90015",
    "sg:province":"CA",
    "sg:tags":[
        "net"
    ],
    "wof:name":"Playerz 69",
    "wof:placetype":"venue"
},
  "geometry": {"coordinates":[-118.26221,34.032271],"type":"Point"}
}