{
  "type": "Feature",
  "properties": {
    "iso:country":"US",
    "sg:address":"207 2nd St Ste A",
    "sg:city":"Sausalito",
    "sg:classifiers":[
        {
            "category":"Professional",
            "subcategory":"Lawyer & Legal Services",
            "type":"Services"
        }
    ],
    "sg:phone":"+1 415 331 6464",
    "sg:postcode":"94965",
    "sg:province":"CA",
    "wof:name":"Lava Leslie M Law Offices Of",
    "wof:placetype":"venue"
},
  "geometry": {"coordinates":[-122.480931,37.848994],"type":"Point"}
}