{
  "type": "Feature",
  "properties": {
    "addr:full":"11429 Donner Pass Rd Truckee CA 96161",
    "addr:housenumber":"11429",
    "addr:postcode":"96161",
    "addr:street":"Donner Pass Rd",
    "iso:country":"US",
    "sg:address":"11429 Donner Pass Rd",
    "sg:city":"Truckee",
    "sg:classifiers":[
        {
            "category":"Banks & Credit Unions",
            "subcategory":"Bank",
            "type":"Services"
        }
    ],
    "sg:phone":"+1 530 587 4111",
    "sg:postcode":"96161",
    "sg:province":"CA",
    "sg:tags":[
        "loan"
    ],
    "sg:website":"www.tahoeloans.com",
    "wof:name":"Lake Tahoe Mortgage Corp",
    "wof:placetype":"venue"
},
  "geometry": {"coordinates":[-120.210661,39.326035],"type":"Point"}
}