{
  "type": "Feature",
  "properties": {
    "iso:country":"US",
    "sg:address":"1035 S Prairie Ave",
    "sg:city":"Inglewood",
    "sg:classifiers":[
        {
            "category":"Personal",
            "subcategory":"Beauty Salon",
            "type":"Services"
        }
    ],
    "sg:phone":"+1 323 753 5042",
    "sg:postcode":"90301",
    "sg:province":"CA",
    "sg:tags":[
        "manicuring"
    ],
    "wof:name":"Wonder Nails",
    "wof:placetype":"venue"
},
  "geometry": {"coordinates":[-118.343908,33.949072],"type":"Point"}
}