{
  "type": "Feature",
  "properties": {
    "iso:country":"US",
    "sg:address":"28121 Crown Valley Pkwy",
    "sg:city":"Laguna Niguel",
    "sg:classifiers":[
        {
            "category":"Home & Garden",
            "subcategory":"Carpets & Floor Coverings",
            "type":"Retail Goods"
        }
    ],
    "sg:phone":"+1 949 425 8500",
    "sg:postcode":"92677",
    "sg:province":"CA",
    "sg:tags":[
        "dealer",
        "rug"
    ],
    "wof:name":"Orange Carpet & Flooring",
    "wof:placetype":"venue"
},
  "geometry": {"coordinates":[-117.691574,33.543533],"type":"Point"}
}