{
  "type": "Feature",
  "properties": {
    "addr:full":"3501 W Burbank Blvd Burbank CA 91505",
    "addr:housenumber":"3501",
    "addr:postcode":"91505",
    "addr:street":"W Burbank Blvd",
    "iso:country":"US",
    "sg:address":"3501 W Burbank Blvd",
    "sg:city":"Burbank",
    "sg:classifiers":[
        {
            "category":"Shopping",
            "subcategory":"Bicycles & Sporting Goods",
            "type":"Retail Goods"
        }
    ],
    "sg:phone":"+1 818 840 0997",
    "sg:postcode":"91505",
    "sg:province":"CA",
    "sg:tags":[
        "equipment",
        "skateboard"
    ],
    "wof:name":"Fast Lane Boardshop",
    "wof:placetype":"venue"
},
  "geometry": {"coordinates":[-118.348249,34.17535],"type":"Point"}
}