{
  "type": "Feature",
  "properties": {
    "addr:full":"2103 Shirley Rd Belmont CA 94002",
    "addr:housenumber":"2103",
    "addr:postcode":"94002",
    "addr:street":"Shirley Rd",
    "iso:country":"US",
    "sg:address":"2103 Shirley Rd",
    "sg:city":"Belmont",
    "sg:classifiers":[
        {
            "category":"Shopping",
            "subcategory":"Books",
            "type":"Retail Goods"
        }
    ],
    "sg:phone":"+1 650 595 5492",
    "sg:postcode":"94002",
    "sg:province":"CA",
    "wof:name":"Book Caravan",
    "wof:placetype":"venue"
},
  "geometry": {"coordinates":[-122.302812,37.521178],"type":"Point"}
}