{
  "type": "Feature",
  "properties": {
    "addr:full":"5777 Madison Ave Sacramento CA 95841",
    "addr:housenumber":"5777",
    "addr:postcode":"95841",
    "addr:street":"Madison Ave",
    "iso:country":"US",
    "sg:address":"5777 Madison Ave",
    "sg:city":"Sacramento",
    "sg:classifiers":[
        {
            "category":"Professional",
            "subcategory":"Lawyer & Legal Services",
            "type":"Services"
        }
    ],
    "sg:phone":"+1 916 332 3777",
    "sg:postcode":"95841",
    "sg:province":"CA",
    "wof:name":"Disability Rep & Legal Svc",
    "wof:placetype":"venue"
},
  "geometry": {"coordinates":[-121.32879800000001,38.660727],"type":"Point"}
}