{
  "type": "Feature",
  "properties": {
    "addr:full":"565 Higuera St San Luis Obispo CA 93401",
    "addr:housenumber":"565",
    "addr:postcode":"93401",
    "addr:street":"Higuera St",
    "iso:country":"US",
    "sg:address":"565 Higuera St",
    "sg:city":"San Luis Obispo",
    "sg:classifiers":[
        {
            "category":"Retail",
            "subcategory":"Car Wash",
            "type":"Services"
        }
    ],
    "sg:phone":"+1 805 215 2564",
    "sg:postcode":"93401",
    "sg:province":"CA",
    "sg:tags":[
        "automobile",
        "detail",
        "clean"
    ],
    "wof:name":"Lendale's & L J's Custom Dtlng",
    "wof:placetype":"venue"
},
  "geometry": {"coordinates":[-120.66724499999999,35.27692],"type":"Point"}
}