{
  "type": "Feature",
  "properties": {
    "iso:country":"US",
    "sg:address":"616 Santa Barbara Ave",
    "sg:city":"Millbrae",
    "sg:classifiers":[
        {
            "category":"Shopping",
            "type":"Retail Goods"
        }
    ],
    "sg:phone":"+1 650 589 6732",
    "sg:postcode":"94030",
    "sg:province":"CA",
    "sg:tags":[
        "merchandise"
    ],
    "wof:name":"Silver Wheel Music",
    "wof:placetype":"venue"
},
  "geometry": {"coordinates":[-122.414613,37.608199],"type":"Point"}
}