{
  "type": "Feature",
  "properties": {
    "addr:full":"1840 E Holt Blvd Ontario CA 91761",
    "addr:housenumber":"1840",
    "addr:postcode":"91761",
    "addr:street":"E Holt Blvd",
    "iso:country":"US",
    "sg:address":"1840 E Holt Blvd",
    "sg:city":"Ontario",
    "sg:classifiers":[
        {
            "category":"Restaurant",
            "type":"Food & Drink"
        }
    ],
    "sg:menulink":"http://www.allmenus.com/ca/ontario/178684-jack-in-the-box/menu/",
    "sg:phone":"+1 909 395 9987",
    "sg:postcode":"91761",
    "sg:province":"CA",
    "sg:tags":[
        "burger",
        "american"
    ],
    "wof:name":"Jack in the Box",
    "wof:placetype":"venue"
},
  "geometry": {"coordinates":[-117.612067,34.063007],"type":"Point"}
}