{
  "type": "Feature",
  "properties": {
    "addr:full":"3500 Grassotti Ct Ste 21 Bakersfield CA 93309",
    "addr:postcode":"3500;ca 93309",
    "addr:street":"Grassotti Ct Ste 21",
    "iso:country":"US",
    "sg:address":"3500 Grassotti Ct Ste 21",
    "sg:city":"Bakersfield",
    "sg:classifiers":[
        {
            "category":"Real Estate",
            "subcategory":"Real Estate Services",
            "type":"Services"
        }
    ],
    "sg:phone":"+1 661 832 2365",
    "sg:postcode":"93309",
    "sg:province":"CA",
    "sg:tags":[
        "management"
    ],
    "wof:name":"Stacy Park Manor",
    "wof:placetype":"venue"
},
  "geometry": {"coordinates":[-119.040269,35.329842],"type":"Point"}
}