{
  "type": "Feature",
  "properties": {
    "iso:country":"US",
    "sg:address":"4946 Buckboard Way",
    "sg:city":"El Sobrante",
    "sg:classifiers":[
        {
            "category":"Building & Trades",
            "subcategory":"Cleaning & Sanitation",
            "type":"Services"
        }
    ],
    "sg:phone":"+1 510 222 6243",
    "sg:postcode":"94803",
    "sg:province":"CA",
    "sg:tags":[
        "house"
    ],
    "wof:name":"Unique Housekeeping Referral",
    "wof:placetype":"venue"
},
  "geometry": {"coordinates":[-122.25114499999999,37.964598],"type":"Point"}
}