{
  "type": "Feature",
  "properties": {
    "addr:full":"35 Stillman St San Francisco CA 94107",
    "addr:housenumber":"35",
    "addr:postcode":"94107",
    "addr:street":"Stillman St",
    "iso:country":"US",
    "sg:address":"35 Stillman St",
    "sg:city":"San Francisco",
    "sg:classifiers":[
        {
            "category":"Building & Trades",
            "subcategory":"Construction",
            "type":"Services"
        }
    ],
    "sg:phone":"+1 415 543 0750",
    "sg:postcode":"94107",
    "sg:province":"CA",
    "sg:tags":[
        "masonry",
        "contractor"
    ],
    "wof:name":"Sullivan Masonry & Restoration",
    "wof:placetype":"venue"
},
  "geometry": {"coordinates":[-122.39571599999999,37.782305],"type":"Point"}
}