{
  "type": "Feature",
  "properties": {
    "addr:full":"383 W Bonita Ave Claremont CA 91711",
    "addr:housenumber":"383",
    "addr:postcode":"91711",
    "addr:street":"W Bonita Ave",
    "iso:country":"US",
    "sg:address":"383 W Bonita Ave",
    "sg:city":"Claremont",
    "sg:classifiers":[
        {
            "category":"Restaurant",
            "type":"Food & Drink"
        }
    ],
    "sg:menulink":"http://www.allmenus.com/ca/east-san-gabriel-valley/123687-quiznos-sub/menu/",
    "sg:phone":"+1 909 621 9051",
    "sg:postcode":"91711",
    "sg:province":"CA",
    "sg:tags":[
        "wrap",
        "american",
        "sandwich"
    ],
    "wof:name":"Quiznos Sub",
    "wof:placetype":"venue"
},
  "geometry": {"coordinates":[-117.719082,34.096649],"type":"Point"}
}