{
  "type": "Feature",
  "properties": {
    "addr:full":"15495 Arnold Dr Glen Ellen CA 95442",
    "addr:housenumber":"15495",
    "addr:postcode":"95442",
    "addr:street":"Arnold Dr",
    "iso:country":"US",
    "sg:address":"15495 Arnold Dr",
    "sg:city":"Glen Ellen",
    "sg:classifiers":[
        {
            "category":"Shopping",
            "type":"Retail Goods"
        },
        {
            "category":"Recreation",
            "type":"Entertainment"
        }
    ],
    "sg:phone":"+1 707 996 1326",
    "sg:postcode":"95442",
    "sg:province":"CA",
    "sg:tags":[
        "art",
        "gallery",
        "merchandise",
        "dealer"
    ],
    "wof:name":"Arlene's Art Gallery & Studio",
    "wof:placetype":"venue"
},
  "geometry": {"coordinates":[-122.513211,38.34054],"type":"Point"}
}