{
  "type": "Feature",
  "properties": {
    "iso:country":"US",
    "sg:address":"4755 Hayter Ave",
    "sg:city":"Lakewood",
    "sg:classifiers":[
        {
            "category":"Wholesale",
            "subcategory":"Non-durable Goods",
            "type":"Manufacturing & Wholesale Goods"
        }
    ],
    "sg:phone":"+1 562 496 0060",
    "sg:postcode":"90712",
    "sg:province":"CA",
    "sg:tags":[
        "figurine",
        "gift"
    ],
    "wof:name":"Ehlers",
    "wof:placetype":"venue"
},
  "geometry": {"coordinates":[-118.146321,33.843811],"type":"Point"}
}