{
  "type": "Feature",
  "properties": {
    "addr:full":"9504 Elk Grove Florin Rd Elk Grove CA 95624",
    "addr:housenumber":"9504",
    "addr:postcode":"95624",
    "addr:street":"Elk Grove Florin Rd",
    "iso:country":"US",
    "sg:address":"9504 Elk Grove Florin Rd",
    "sg:city":"Elk Grove",
    "sg:classifiers":[
        {
            "category":"Real Estate",
            "subcategory":"Real Estate Operator",
            "type":"Services"
        }
    ],
    "sg:phone":"+1 916 685 4338",
    "sg:postcode":"95624",
    "sg:province":"CA",
    "sg:tags":[
        "apartment"
    ],
    "wof:name":"Whispering Oaks",
    "wof:placetype":"venue"
},
  "geometry": {"coordinates":[-121.371639,38.41429],"type":"Point"}
}