{
  "type": "Feature",
  "properties": {
    "addr:full":"580 N Rengstorff Ave Mountain View CA 94043",
    "addr:housenumber":"580",
    "addr:postcode":"94043",
    "addr:street":"N Rengstorff Ave",
    "iso:country":"US",
    "sg:address":"580 N Rengstorff Ave",
    "sg:city":"Mountain View",
    "sg:classifiers":[
        {
            "category":"Food & Beverages",
            "subcategory":"Groceries & Convenience Stores",
            "type":"Retail Goods"
        }
    ],
    "sg:phone":"+1 650 967 8037",
    "sg:postcode":"94043",
    "sg:province":"CA",
    "sg:tags":[
        "supermarket"
    ],
    "wof:name":"Albertsons 7164",
    "wof:placetype":"venue"
},
  "geometry": {"coordinates":[-122.092844,37.411053],"type":"Point"}
}