{
  "type": "Feature",
  "properties": {
    "iso:country":"US",
    "sg:address":"1120 Monument St",
    "sg:city":"Pacific Palisades",
    "sg:classifiers":[
        {
            "category":"Professional",
            "type":"Services"
        }
    ],
    "sg:phone":"+1 310 454 4525",
    "sg:postcode":"90272",
    "sg:province":"CA",
    "wof:name":"Orlando T Gatto",
    "wof:placetype":"venue"
},
  "geometry": {"coordinates":[-118.524963,34.050657],"type":"Point"}
}