{
  "type": "Feature",
  "properties": {
    "addr:full":"7459 Rd 26 Madera CA 93637",
    "addr:housenumber":"7459",
    "addr:postcode":"93637",
    "addr:street":"Rd 26",
    "iso:country":"US",
    "sg:address":"7459 Rd 26",
    "sg:city":"Madera",
    "sg:classifiers":[
        {
            "category":"Professional",
            "type":"Services"
        }
    ],
    "sg:phone":"+1 559 661 4856",
    "sg:postcode":"93637",
    "sg:province":"CA",
    "wof:name":"Klar Skhrjnder S Klwant K Husb",
    "wof:placetype":"venue"
},
  "geometry": {"coordinates":[-120.073948,36.854262],"type":"Point"}
}