{
  "type": "Feature",
  "properties": {
    "iso:country":"US",
    "sg:address":"466 Ridgeview Ct",
    "sg:city":"Bonita",
    "sg:classifiers":[
        {
            "category":"Shopping",
            "subcategory":"Bicycles & Sporting Goods",
            "type":"Retail Goods"
        }
    ],
    "sg:phone":"+1 619 397 5570",
    "sg:postcode":"91902",
    "sg:province":"CA",
    "wof:name":"Gearbox",
    "wof:placetype":"venue"
},
  "geometry": {"coordinates":[-117.12741,32.654225],"type":"Point"}
}