{
  "type": "Feature",
  "properties": {
    "iso:country":"US",
    "sg:address":"5936 E Whitmore Ave",
    "sg:city":"Hughson",
    "sg:classifiers":[
        {
            "category":"Farming",
            "subcategory":"Farm",
            "type":"Manufacturing & Wholesale Goods"
        }
    ],
    "sg:phone":"+1 209 883 0158",
    "sg:postcode":"95326",
    "sg:province":"CA",
    "sg:tags":[
        "crop",
        "general"
    ],
    "wof:name":"J Hopper",
    "wof:placetype":"venue"
},
  "geometry": {"coordinates":[-120.882312,37.594717],"type":"Point"}
}