{
  "type": "Feature",
  "properties": {
    "iso:country":"US",
    "sg:address":"15912 Shellie Marie Ave",
    "sg:city":"Bakersfield",
    "sg:classifiers":[
        {
            "category":"Building & Trades",
            "subcategory":"Construction",
            "type":"Services"
        }
    ],
    "sg:phone":"+1 661 589 4128",
    "sg:postcode":"93314",
    "sg:province":"CA",
    "sg:tags":[
        "excavation",
        "contractor"
    ],
    "wof:name":"Prewett Investment & Cnstr",
    "wof:placetype":"venue"
},
  "geometry": {"coordinates":[-119.178534,35.388999],"type":"Point"}
}