{
  "type": "Feature",
  "properties": {
    "addr:full":"4645 1/2 Venice Blvd Los Angeles CA 90019",
    "addr:housenumber":"4645 1 / 2",
    "addr:postcode":"90019",
    "addr:street":"Venice Blvd",
    "iso:country":"US",
    "sg:address":"4645 1/2 Venice Blvd",
    "sg:city":"Los Angeles",
    "sg:classifiers":[
        {
            "category":"Sports & Exercise",
            "subcategory":"Ice Rink",
            "type":"Entertainment"
        }
    ],
    "sg:phone":"+1 323 933 5170",
    "sg:postcode":"90019",
    "sg:province":"CA",
    "sg:tags":[
        "skating"
    ],
    "sg:website":"www.amfworldonwheels.com/worldon...",
    "wof:name":"World On Wheels",
    "wof:placetype":"venue"
},
  "geometry": {"coordinates":[-118.338351,34.047554],"type":"Point"}
}