{
  "type": "Feature",
  "properties": {
    "iso:country":"US",
    "sg:address":"599 Macarthur Blvd",
    "sg:city":"San Leandro",
    "sg:classifiers":[
        {
            "category":"Professional",
            "type":"Services"
        }
    ],
    "sg:phone":"+1 510 638 9403",
    "sg:postcode":"94577",
    "sg:province":"CA",
    "sg:tags":[
        "establishment"
    ],
    "wof:name":"Freddie's Showcase",
    "wof:placetype":"venue"
},
  "geometry": {"coordinates":[-122.144843,37.739014],"type":"Point"}
}