{
  "type": "Feature",
  "properties": {
    "iso:country":"US",
    "sg:address":"1409 W Redlands Blvd",
    "sg:city":"Redlands",
    "sg:classifiers":[
        {
            "category":"Real Estate",
            "subcategory":"Real Estate Operator",
            "type":"Services"
        }
    ],
    "sg:phone":"+1 909 792 9639",
    "sg:postcode":"92373",
    "sg:province":"CA",
    "sg:tags":[
        "mobile",
        "home",
        "community"
    ],
    "wof:name":"Royal Trailer Park",
    "wof:placetype":"venue"
},
  "geometry": {"coordinates":[-117.204689,34.062027],"type":"Point"}
}