{
  "type": "Feature",
  "properties": {
    "iso:country":"US",
    "sg:address":"2701 Plz del Amo",
    "sg:city":"Torrance",
    "sg:classifiers":[
        {
            "category":"Wholesale",
            "subcategory":"Electrical",
            "type":"Manufacturing & Wholesale Goods"
        }
    ],
    "sg:phone":"+1 310 618 1151",
    "sg:postcode":"90503",
    "sg:province":"CA",
    "sg:tags":[
        "electronic",
        "representative"
    ],
    "wof:name":"Intersource OEM",
    "wof:placetype":"venue"
},
  "geometry": {"coordinates":[-118.210348,33.846406],"type":"Point"}
}