{
  "type": "Feature",
  "properties": {
    "acgov:api":"806.0",
    "acgov:type":"HS",
    "addr:full":"603 Key Route Boulevard Albany CA",
    "wof:categories":[
        "education_and_religion:education=school"
    ],
    "wof:name":"Albany High",
    "wof:placetype":"venue"
},
  "geometry": {"coordinates":[-122.29246900638145,37.89665043557589],"type":"Point"}
}