{
  "type": "Feature",
  "properties": {
    "iso:country":"US",
    "sg:address":"6095 Steele Canyon Rd",
    "sg:city":"Napa",
    "sg:classifiers":[
        {
            "category":"Utilities",
            "subcategory":"Refuse",
            "type":"Services"
        }
    ],
    "sg:phone":"+1 707 226 9543",
    "sg:postcode":"94558",
    "sg:province":"CA",
    "sg:tags":[
        "system"
    ],
    "wof:name":"Berryessa Garbage Service Inc",
    "wof:placetype":"venue"
},
  "geometry": {"coordinates":[-122.193278,38.514964],"type":"Point"}
}