{
  "type": "Feature",
  "properties": {
    "addr:full":"231 10th St Tracy CA 95376",
    "addr:housenumber":"231",
    "addr:postcode":"95376",
    "addr:street":"10Th St",
    "iso:country":"US",
    "sg:address":"231 10th St",
    "sg:city":"Tracy",
    "sg:classifiers":[
        {
            "category":"Manufacturing",
            "subcategory":"Printing",
            "type":"Manufacturing & Wholesale Goods"
        }
    ],
    "sg:phone":"+1 209 833 1140",
    "sg:postcode":"95376",
    "sg:province":"CA",
    "sg:tags":[
        "newspaper"
    ],
    "wof:name":"Stockton Record",
    "wof:placetype":"venue"
},
  "geometry": {"coordinates":[-121.429261,37.738496],"type":"Point"}
}