{
  "type": "Feature",
  "properties": {
    "iso:country":"US",
    "sg:address":"944 Blossom Hill Rd",
    "sg:city":"San Jose",
    "sg:classifiers":[
        {
            "category":"Home & Garden",
            "subcategory":"Furniture",
            "type":"Retail Goods"
        }
    ],
    "sg:phone":"+1 408 226 9088",
    "sg:postcode":"95123",
    "sg:province":"CA",
    "sg:tags":[
        "store"
    ],
    "sg:website":"www.jenniferfurniture.com",
    "wof:name":"Jennifer Convertibles",
    "wof:placetype":"venue"
},
  "geometry": {"coordinates":[-121.86555199999999,37.250308],"type":"Point"}
}