{
  "type": "Feature",
  "properties": {
    "iso:country":"US",
    "sg:address":"333 Escuela Ave # 122.",
    "sg:city":"Mountain View",
    "sg:classifiers":[
        {
            "category":"Taxi",
            "type":"Transportation"
        }
    ],
    "sg:phone":"+1 650 254 2000",
    "sg:postcode":"94041",
    "sg:province":"CA",
    "sg:website":"www.a1americancab.com/",
    "wof:name":"A1 American Cab & Limo",
    "wof:placetype":"venue"
},
  "geometry": {"coordinates":[-122.093552,37.39764],"type":"Point"}
}