{
  "type": "Feature",
  "properties": {
    "addr:full":"1105 5th St Los Banos CA 93635",
    "addr:housenumber":"1105",
    "addr:postcode":"93635",
    "addr:street":"5Th St",
    "iso:country":"US",
    "sg:address":"1105 5th St",
    "sg:city":"Los Banos",
    "sg:classifiers":[
        {
            "category":"Museum",
            "type":"Entertainment"
        }
    ],
    "sg:phone":"+1 209 827 4126",
    "sg:postcode":"93635",
    "sg:province":"CA",
    "sg:tags":[
        "organization",
        "arts",
        "information"
    ],
    "wof:name":"Los Banos Arts Council",
    "wof:placetype":"venue"
},
  "geometry": {"coordinates":[-120.850767,37.059642],"type":"Point"}
}