{
  "type": "Feature",
  "properties": {
    "addr:full":"18041 Gale Ave City Of Industry CA 91748",
    "addr:housenumber":"18041",
    "addr:postcode":"91748",
    "addr:street":"Gale Ave",
    "iso:country":"US",
    "sg:address":"18041 Gale Ave",
    "sg:city":"City Of Industry",
    "sg:classifiers":[
        {
            "category":"Shopping",
            "subcategory":"Stationery & Office Supplies",
            "type":"Retail Goods"
        }
    ],
    "sg:phone":"+1 626 810 8821",
    "sg:postcode":"91748",
    "sg:province":"CA",
    "wof:name":"Office Depot",
    "wof:placetype":"venue"
},
  "geometry": {"coordinates":[-117.916048,33.995461],"type":"Point"}
}