{
  "type": "Feature",
  "properties": {
    "iso:country":"US",
    "sg:address":"2141 California St",
    "sg:city":"Concord",
    "sg:classifiers":[
        {
            "category":"Professional",
            "type":"Services"
        }
    ],
    "sg:phone":"+1 925 798 8195",
    "sg:postcode":"94520",
    "sg:province":"CA",
    "sg:tags":[
        "establishment"
    ],
    "wof:name":"East Bay Services-Independent",
    "wof:placetype":"venue"
},
  "geometry": {"coordinates":[-122.04068700000001,37.976628],"type":"Point"}
}