{
  "type": "Feature",
  "properties": {
    "iso:country":"US",
    "sg:address":"1333 Camino Del Rio South Suite 201B",
    "sg:city":"San Diego",
    "sg:classifiers":[
        {
            "category":"Health Services",
            "subcategory":"Clinic",
            "type":"Services"
        },
        {
            "category":"Organizations",
            "subcategory":"Non-profit Organization",
            "type":"Services"
        }
    ],
    "sg:phone":"+1 619 298 3500",
    "sg:postcode":"92108",
    "sg:province":"CA",
    "sg:tags":[
        "cannabis",
        "service/non-profit",
        "community"
    ],
    "sg:website":"www.sdmc420.com#cid=yelp",
    "wof:name":"San Diego Medical Collectives",
    "wof:placetype":"venue"
},
  "geometry": {"coordinates":[-117.15148600000001,32.765677],"type":"Point"}
}