{
  "type": "Feature",
  "properties": {
    "iso:country":"US",
    "sg:address":"19730 Ventura Blvd",
    "sg:city":"Woodland Hills",
    "sg:classifiers":[
        {
            "category":"Health Services",
            "subcategory":"Chiropractor",
            "type":"Services"
        }
    ],
    "sg:phone":"+1 818 994 9494",
    "sg:postcode":"91364",
    "sg:province":"CA",
    "wof:name":"Southern California Injury Tre",
    "wof:placetype":"venue"
},
  "geometry": {"coordinates":[-118.5634,34.172419],"type":"Point"}
}