{
  "type": "Feature",
  "properties": {
    "addr:full":"1906 Fort Jones Rd Yreka CA 96097",
    "addr:housenumber":"1906",
    "addr:postcode":"96097",
    "addr:street":"Fort Jones Rd",
    "iso:country":"US",
    "sg:address":"1906 Fort Jones Rd",
    "sg:city":"Yreka",
    "sg:classifiers":[
        {
            "category":"Professional",
            "subcategory":"Accounting & Tax Preparation",
            "type":"Services"
        }
    ],
    "sg:phone":"+1 530 841 0615",
    "sg:postcode":"96097",
    "sg:province":"CA",
    "sg:tags":[
        "return",
        "filing"
    ],
    "wof:name":"H & R Block Tax Svc",
    "wof:placetype":"venue"
},
  "geometry": {"coordinates":[-122.64615999999999,41.700936],"type":"Point"}
}