{
  "type": "Feature",
  "properties": {
    "iso:country":"US",
    "sg:address":"16010 Bloomfield Ave",
    "sg:city":"Cerritos",
    "sg:classifiers":[
        {
            "category":"Retail",
            "subcategory":"Auto Repair",
            "type":"Services"
        }
    ],
    "sg:phone":"+1 562 802 3311",
    "sg:postcode":"90703",
    "sg:province":"CA",
    "sg:tags":[
        "repairing",
        "automobile"
    ],
    "wof:name":"Alba Performance Wheels",
    "wof:placetype":"venue"
},
  "geometry": {"coordinates":[-118.063986,33.885943],"type":"Point"}
}