{
  "type": "Feature",
  "properties": {
    "addr:full":"1350 Dell Ave Campbell CA 95008",
    "addr:housenumber":"1350",
    "addr:postcode":"95008",
    "addr:street":"Dell Ave",
    "iso:country":"US",
    "sg:address":"1350 Dell Ave",
    "sg:city":"Campbell",
    "sg:classifiers":[
        {
            "category":"Manufacturing",
            "subcategory":"Rubber & Plastics",
            "type":"Manufacturing & Wholesale Goods"
        }
    ],
    "sg:phone":"+1 408 540 0320",
    "sg:postcode":"95008",
    "sg:province":"CA",
    "sg:tags":[
        "plastics-finished-wholesale",
        "manufacturer"
    ],
    "wof:name":"Cm Solutions",
    "wof:placetype":"venue"
},
  "geometry": {"coordinates":[-121.954058,37.267147],"type":"Point"}
}