{
  "type": "Feature",
  "properties": {
    "addr:full":"9099 Soquel Dr Aptos CA 95003",
    "addr:housenumber":"9099",
    "addr:postcode":"ca 95003",
    "addr:street":"Soquel Dr",
    "iso:country":"US",
    "sg:address":"9099 Soquel Dr",
    "sg:city":"Aptos",
    "sg:classifiers":[
        {
            "category":"Health Services",
            "subcategory":"Health Practitioner",
            "type":"Services"
        }
    ],
    "sg:phone":"+1 831 688 5010",
    "sg:postcode":"95003",
    "sg:province":"CA",
    "sg:tags":[
        "psychologist"
    ],
    "wof:name":"Professional Counseling/Stress",
    "wof:placetype":"venue"
},
  "geometry": {"coordinates":[-121.885614,36.976474],"type":"Point"}
}