{
  "type": "Feature",
  "properties": {
    "addr:full":"12841 Lucille Ave Garden Grove CA 92841",
    "addr:housenumber":"12841",
    "addr:postcode":"92841",
    "addr:street":"Lucille Ave",
    "iso:country":"US",
    "sg:address":"12841 Lucille Ave",
    "sg:city":"Garden Grove",
    "sg:classifiers":[
        {
            "category":"Building & Trades",
            "subcategory":"Landscaping Services",
            "type":"Services"
        }
    ],
    "sg:phone":"+1 714 530 7026",
    "sg:postcode":"92841",
    "sg:province":"CA",
    "sg:tags":[
        "landscape",
        "contractor"
    ],
    "wof:name":"Martin Juarez Landscaping",
    "wof:placetype":"venue"
},
  "geometry": {"coordinates":[-117.973004,33.775423],"type":"Point"}
}