{
  "type": "Feature",
  "properties": {
    "iso:country":"US",
    "sg:address":"1339 Yosemite Ave",
    "sg:city":"San Francisco",
    "sg:classifiers":[
        {
            "category":"Home & Garden",
            "subcategory":"Building Materials",
            "type":"Retail Goods"
        }
    ],
    "sg:phone":"+1 415 822 2500",
    "sg:postcode":"94124",
    "sg:province":"CA",
    "wof:name":"Thunder's Mill",
    "wof:placetype":"venue"
},
  "geometry": {"coordinates":[-122.387305,37.724213],"type":"Point"}
}