{
  "type": "Feature",
  "properties": {
    "iso:country":"US",
    "sg:address":"425 N 4th Street",
    "sg:city":"San Jose",
    "sg:classifiers":[
        {
            "category":"Organizations",
            "subcategory":"Non-profit Organization",
            "type":"Services"
        }
    ],
    "sg:phone":"+1 408 293 7122",
    "sg:postcode":"95112",
    "sg:province":"CA",
    "sg:tags":[
        "service/non-profit",
        "community"
    ],
    "sg:website":"www.iahfsj.org",
    "wof:name":"Italian American Heritage Foundation",
    "wof:placetype":"venue"
},
  "geometry": {"coordinates":[-121.89274899999999,37.344675],"type":"Point"}
}