{
  "type": "Feature",
  "properties": {
    "iso:country":"US",
    "sg:address":"4560 Admiralty Way",
    "sg:city":"Marina Del Rey",
    "sg:classifiers":[
        {
            "category":"Health Services",
            "subcategory":"Chiropractor",
            "type":"Services"
        }
    ],
    "sg:phone":"+1 310 578 9333",
    "sg:postcode":"90292",
    "sg:province":"CA",
    "wof:name":"Klishevich C Walter",
    "wof:placetype":"venue"
},
  "geometry": {"coordinates":[-118.442001,33.983101],"type":"Point"}
}