{
  "type": "Feature",
  "properties": {
    "addr:full":"23745 Placentia Ave Perris CA 92570",
    "addr:housenumber":"23745",
    "addr:postcode":"92570",
    "addr:street":"Placentia Ave",
    "iso:country":"US",
    "sg:address":"23745 Placentia Ave",
    "sg:city":"Perris",
    "sg:classifiers":[
        {
            "category":"Autos & Motor Vehicles",
            "subcategory":"Fuel & Gas Station",
            "type":"Retail Goods"
        },
        {
            "category":"Wholesale",
            "subcategory":"Motor Vehicles",
            "type":"Manufacturing & Wholesale Goods"
        }
    ],
    "sg:phone":"+1 951 940 4012",
    "sg:postcode":"92570",
    "sg:province":"CA",
    "sg:tags":[
        "station",
        "gasoline",
        "trailer"
    ],
    "wof:name":"A-1 Mobile Tire & Axl Company",
    "wof:placetype":"venue"
},
  "geometry": {"coordinates":[-117.248876,33.823021],"type":"Point"}
}