{
  "type": "Feature",
  "properties": {
    "iso:country":"US",
    "sg:address":"4962 Robert J Mathews Pkwy",
    "sg:city":"El Dorado Hills",
    "sg:classifiers":[
        {
            "category":"Wholesale",
            "subcategory":"Toys & Hobbies",
            "type":"Manufacturing & Wholesale Goods"
        }
    ],
    "sg:phone":"+1 916 941 9655",
    "sg:postcode":"95762",
    "sg:province":"CA",
    "sg:tags":[
        "wholesaler"
    ],
    "wof:name":"GRC Whole Sale",
    "wof:placetype":"venue"
},
  "geometry": {"coordinates":[-121.05833,38.622739],"type":"Point"}
}