{
  "type": "Feature",
  "properties": {
    "iso:country":"US",
    "sg:address":"614 Williams Rd",
    "sg:city":"Salinas",
    "sg:classifiers":[
        {
            "category":"Banks & Credit Unions",
            "subcategory":"Bank",
            "type":"Services"
        }
    ],
    "sg:phone":"+1 831 758 4181",
    "sg:postcode":"93905",
    "sg:province":"CA",
    "sg:tags":[
        "money",
        "order"
    ],
    "wof:name":"Giromex",
    "wof:placetype":"venue"
},
  "geometry": {"coordinates":[-121.60526900000001,36.680504],"type":"Point"}
}