{
  "type": "Feature",
  "properties": {
    "addr:full":"2500 Stanley Blvd Pleasanton CA 94566",
    "addr:housenumber":"2500",
    "addr:postcode":"94566",
    "addr:street":"Stanley Blvd",
    "iso:country":"US",
    "sg:address":"2500 Stanley Blvd",
    "sg:city":"Pleasanton",
    "sg:classifiers":[
        {
            "category":"Recreation",
            "type":"Entertainment"
        }
    ],
    "sg:phone":"+1 925 846 3000",
    "sg:postcode":"94566",
    "sg:province":"CA",
    "sg:tags":[
        "playground"
    ],
    "sg:website":"www.ebparks.org",
    "wof:name":"Shadow Cliff Recreation Area",
    "wof:placetype":"venue"
},
  "geometry": {"coordinates":[-121.854463,37.670815],"type":"Point"}
}