{
  "type": "Feature",
  "properties": {
    "iso:country":"US",
    "sg:address":"2038 Vine St",
    "sg:city":"Berkeley",
    "sg:classifiers":[
        {
            "category":"Communications",
            "type":"Services"
        }
    ],
    "sg:phone":"+1 510 528 1696",
    "sg:postcode":"94709",
    "sg:province":"CA",
    "sg:tags":[
        "consultant",
        "engineer"
    ],
    "wof:name":"Avery Coaching",
    "wof:placetype":"venue"
},
  "geometry": {"coordinates":[-122.270267,37.880096],"type":"Point"}
}