{
  "type": "Feature",
  "properties": {
    "addr:full":"16834 E Tudor St Covina CA 91722",
    "addr:housenumber":"16834",
    "addr:postcode":"91722",
    "addr:street":"E Tudor St",
    "iso:country":"US",
    "sg:address":"16834 E Tudor St",
    "sg:city":"Covina",
    "sg:classifiers":[
        {
            "category":"Building & Trades",
            "subcategory":"Construction",
            "type":"Services"
        }
    ],
    "sg:phone":"+1 626 858 6604",
    "sg:postcode":"91722",
    "sg:province":"CA",
    "sg:tags":[
        "contractor"
    ],
    "wof:name":"Sosa Masonry",
    "wof:placetype":"venue"
},
  "geometry": {"coordinates":[-117.918718,34.101722],"type":"Point"}
}