{
  "type": "Feature",
  "properties": {
    "addr:full":"33888 Alvarado Niles Rd Union City CA 94587",
    "addr:housenumber":"33888",
    "addr:postcode":"94587",
    "addr:street":"Alvarado Niles Rd",
    "iso:country":"US",
    "sg:address":"33888 Alvarado Niles Rd",
    "sg:city":"Union City",
    "sg:classifiers":[
        {
            "category":"Shopping",
            "subcategory":"Florist",
            "type":"Retail Goods"
        }
    ],
    "sg:phone":"+1 510 489 2727",
    "sg:postcode":"94587",
    "sg:province":"CA",
    "wof:name":"Union City Florist",
    "wof:placetype":"venue"
},
  "geometry": {"coordinates":[-122.03210900000001,37.590196],"type":"Point"}
}