{
  "type": "Feature",
  "properties": {
    "iso:country":"US",
    "sg:address":"12058 Saticoy St",
    "sg:city":"North Hollywood",
    "sg:classifiers":[
        {
            "category":"Restaurant",
            "type":"Food & Drink"
        }
    ],
    "sg:phone":"+1 818 759 0103",
    "sg:postcode":"91605",
    "sg:province":"CA",
    "wof:name":"El Rincon Salvadoreno",
    "wof:placetype":"venue"
},
  "geometry": {"coordinates":[-118.394997,34.208599],"type":"Point"}
}