{
  "type": "Feature",
  "properties": {
    "addr:full":"1930 Park Ave San Jose CA 95126",
    "addr:housenumber":"1930",
    "addr:postcode":"95126",
    "addr:street":"Park Ave",
    "iso:country":"US",
    "sg:address":"1930 Park Ave",
    "sg:city":"San Jose",
    "sg:classifiers":[
        {
            "category":"Professional",
            "type":"Services"
        }
    ],
    "sg:phone":"+1 408 655 8989",
    "sg:postcode":"95126",
    "sg:province":"CA",
    "wof:name":"Ran Dhawa Airporter",
    "wof:placetype":"venue"
},
  "geometry": {"coordinates":[-121.92834000000001,37.337534],"type":"Point"}
}