{
  "type": "Feature",
  "properties": {
    "iso:country":"US",
    "sg:address":"160 Glendale Blvd",
    "sg:city":"Los Angeles",
    "sg:classifiers":[
        {
            "category":"Wholesale",
            "subcategory":"Metals & Minerals",
            "type":"Manufacturing & Wholesale Goods"
        }
    ],
    "sg:phone":"+1 213 250 0646",
    "sg:postcode":"90026",
    "sg:province":"CA",
    "sg:tags":[
        "die",
        "casting",
        "center"
    ],
    "wof:name":"Fast Die",
    "wof:placetype":"venue"
},
  "geometry": {"coordinates":[-118.259755,34.063612],"type":"Point"}
}