{
  "type": "Feature",
  "properties": {
    "iso:country":"US",
    "sg:address":"16795 Von Karman Ave",
    "sg:city":"Irvine",
    "sg:classifiers":[
        {
            "category":"Professional",
            "subcategory":"Engineering",
            "type":"Services"
        }
    ],
    "sg:phone":"+1 949 474 1960",
    "sg:postcode":"92606",
    "sg:province":"CA",
    "sg:tags":[
        "engineer"
    ],
    "sg:website":"www.fuscoe.com",
    "wof:name":"Fuscoe Engineering Inc",
    "wof:placetype":"venue"
},
  "geometry": {"coordinates":[-117.835898,33.696405],"type":"Point"}
}