{
  "type": "Feature",
  "properties": {
    "iso:country":"US",
    "sg:address":"1500 W Houston Ave",
    "sg:city":"Visalia",
    "sg:classifiers":[
        {
            "category":"Shopping",
            "subcategory":"Jewelry",
            "type":"Retail Goods"
        }
    ],
    "sg:phone":"+1 559 732 3208",
    "sg:postcode":"93291",
    "sg:province":"CA",
    "sg:tags":[
        "jeweler"
    ],
    "wof:name":"Joyeria Sujei",
    "wof:placetype":"venue"
},
  "geometry": {"coordinates":[-119.308949,36.341893],"type":"Point"}
}