{
  "type": "Feature",
  "properties": {
    "addr:full":"2811 Beverly Blvd Los Angeles CA 90057",
    "addr:housenumber":"2811",
    "addr:postcode":"90057",
    "addr:street":"Beverly Blvd",
    "iso:country":"US",
    "sg:address":"2811 Beverly Blvd",
    "sg:city":"Los Angeles",
    "sg:classifiers":[
        {
            "category":"Government",
            "subcategory":"Office",
            "type":"Public Place"
        }
    ],
    "sg:phone":"+1 213 738 7255",
    "sg:postcode":"90057",
    "sg:province":"CA",
    "sg:tags":[
        "smog",
        "check"
    ],
    "wof:name":"Good One Test Only Center",
    "wof:placetype":"venue"
},
  "geometry": {"coordinates":[-118.27945699999999,34.079268],"type":"Point"}
}