{
  "type": "Feature",
  "properties": {
    "addr:full":"2186 Knoll Dr Ventura CA 93003",
    "addr:housenumber":"2186",
    "addr:postcode":"93003",
    "addr:street":"Knoll Dr",
    "iso:country":"US",
    "sg:address":"2186 Knoll Dr",
    "sg:city":"Ventura",
    "sg:classifiers":[
        {
            "category":"Retail",
            "subcategory":"Repair Shop",
            "type":"Services"
        }
    ],
    "sg:phone":"+1 805 644 1522",
    "sg:postcode":"93003",
    "sg:province":"CA",
    "sg:tags":[
        "welding"
    ],
    "wof:name":"Maguire's Shopweld",
    "wof:placetype":"venue"
},
  "geometry": {"coordinates":[-119.21916899999999,34.251891],"type":"Point"}
}