{
  "type": "Feature",
  "properties": {
    "iso:country":"US",
    "sg:address":"320 Broadway St",
    "sg:city":"King City",
    "sg:classifiers":[
        {
            "category":"Personal",
            "subcategory":"Beauty Salon",
            "type":"Services"
        }
    ],
    "sg:phone":"+1 831 385 0281",
    "sg:postcode":"93930",
    "sg:province":"CA",
    "wof:name":"Delia's Beauty Salon",
    "wof:placetype":"venue"
},
  "geometry": {"coordinates":[-121.126597,36.212818],"type":"Point"}
}