{
  "type": "Feature",
  "properties": {
    "addr:full":"28 Nopalitos Way Santa Barbara CA 93103",
    "addr:housenumber":"28",
    "addr:postcode":"93103",
    "addr:street":"Nopalitos Way",
    "iso:country":"US",
    "sg:address":"28 Nopalitos Way",
    "sg:city":"Santa Barbara",
    "sg:classifiers":[
        {
            "category":"Building & Trades",
            "subcategory":"Construction",
            "type":"Services"
        }
    ],
    "sg:phone":"+1 805 560 6640",
    "sg:postcode":"93103",
    "sg:province":"CA",
    "sg:tags":[
        "tile",
        "dealer"
    ],
    "wof:name":"Hollywood Tile",
    "wof:placetype":"venue"
},
  "geometry": {"coordinates":[-119.679739,34.419734],"type":"Point"}
}