{
  "type": "Feature",
  "properties": {
    "iso:country":"US",
    "sg:address":"1 Boardwalk Ave",
    "sg:city":"Thousand Oaks",
    "sg:classifiers":[
        {
            "category":"Banks & Credit Unions",
            "subcategory":"Investment Brokerage",
            "type":"Services"
        }
    ],
    "sg:phone":"+1 805 494 1825",
    "sg:postcode":"91360",
    "sg:province":"CA",
    "sg:tags":[
        "consultant",
        "planning",
        "financial"
    ],
    "wof:name":"Strategic Financial",
    "wof:placetype":"venue"
},
  "geometry": {"coordinates":[-118.872824,34.180431],"type":"Point"}
}