{
  "type": "Feature",
  "properties": {
    "addr:full":"4775 Goodwater Ave Redding CA 96002",
    "addr:housenumber":"4775",
    "addr:postcode":"96002",
    "addr:street":"Goodwater Ave",
    "iso:country":"US",
    "sg:address":"4775 Goodwater Ave",
    "sg:city":"Redding",
    "sg:classifiers":[
        {
            "category":"Professional",
            "type":"Services"
        }
    ],
    "sg:phone":"+1 530 222 3102",
    "sg:postcode":"96002",
    "sg:province":"CA",
    "wof:name":"Cleo Picard",
    "wof:placetype":"venue"
},
  "geometry": {"coordinates":[-122.31455800000001,40.540533],"type":"Point"}
}