{
  "type": "Feature",
  "properties": {
    "addr:full":"15888 Main St Hesperia CA 92345",
    "addr:housenumber":"15888",
    "addr:postcode":"92345",
    "addr:street":"Main St",
    "iso:country":"US",
    "sg:address":"15888 Main St",
    "sg:city":"Hesperia",
    "sg:classifiers":[
        {
            "category":"Real Estate",
            "subcategory":"Real Estate Services",
            "type":"Services"
        },
        {
            "category":"Banks & Credit Unions",
            "subcategory":"Financial Services",
            "type":"Services"
        }
    ],
    "sg:phone":"+1 760 949 2391",
    "sg:postcode":"92345",
    "sg:province":"CA",
    "sg:tags":[
        "loan",
        "processing"
    ],
    "wof:name":"Rudy Santiago",
    "wof:placetype":"venue"
},
  "geometry": {"coordinates":[-117.315894,34.423654],"type":"Point"}
}