{
  "type": "Feature",
  "properties": {
    "iso:country":"US",
    "sg:address":"7050 Village Dr",
    "sg:city":"Buena Park",
    "sg:classifiers":[
        {
            "category":"Shopping",
            "subcategory":"Computers & Home Electronics",
            "type":"Retail Goods"
        }
    ],
    "sg:phone":"+1 714 994 8673",
    "sg:postcode":"90621",
    "sg:province":"CA",
    "sg:website":"www.dishnetwork.com",
    "wof:name":"DISH Network",
    "wof:placetype":"venue"
},
  "geometry": {"coordinates":[-118.027601,33.87028],"type":"Point"}
}