{
  "type": "Feature",
  "properties": {
    "iso:country":"US",
    "sg:address":"2008 S Sepulveda Blvd",
    "sg:city":"Los Angeles",
    "sg:classifiers":[
        {
            "category":"Home & Garden",
            "subcategory":"Furniture",
            "type":"Retail Goods"
        },
        {
            "category":"Wholesale",
            "subcategory":"Furniture",
            "type":"Manufacturing & Wholesale Goods"
        }
    ],
    "sg:phone":"+1 310 477 1936",
    "sg:postcode":"90025",
    "sg:province":"CA",
    "wof:name":"El Paso Import Company",
    "wof:placetype":"venue"
},
  "geometry": {"coordinates":[-118.439102,34.041731],"type":"Point"}
}