{
  "type": "Feature",
  "properties": {
    "iso:country":"US",
    "sg:address":"1710 Carleton Street",
    "sg:city":"Berkeley",
    "sg:classifiers":[
        {
            "category":"Place Of Worship",
            "subcategory":"Church",
            "type":"Public Place"
        }
    ],
    "sg:phone":"+1 510 848 4680",
    "sg:postcode":"94703",
    "sg:province":"CA",
    "wof:name":"Berkeley Methodist United Church",
    "wof:placetype":"venue"
},
  "geometry": {"coordinates":[-122.27600099999999,37.8601],"type":"Point"}
}