{
  "type": "Feature",
  "properties": {
    "iso:country":"US",
    "sg:address":"2611 Vista Way",
    "sg:city":"Oceanside",
    "sg:classifiers":[
        {
            "category":"Restaurant",
            "type":"Food & Drink"
        }
    ],
    "sg:menulink":"http://www.allmenus.com/ca/oceanside-escondido/28797-chipotle/menu/",
    "sg:phone":"+1 760 721 6904",
    "sg:postcode":"92054",
    "sg:province":"CA",
    "sg:tags":[
        "mexican"
    ],
    "wof:name":"Chipotle",
    "wof:placetype":"venue"
},
  "geometry": {"coordinates":[-117.331019,33.183229],"type":"Point"}
}