{
  "type": "Feature",
  "properties": {
    "addr:full":"1315 S Grand Ave 200 Glendora CA 91740",
    "addr:housenumber":"1315;200",
    "addr:postcode":"91740",
    "addr:street":"S Grand Ave",
    "iso:country":"US",
    "sg:address":"1315 S Grand Ave 200",
    "sg:city":"Glendora",
    "sg:classifiers":[
        {
            "category":"Building & Trades",
            "subcategory":"Landscaping Services",
            "type":"Services"
        }
    ],
    "sg:phone":"+1 626 914 7500",
    "sg:postcode":"91740",
    "sg:province":"CA",
    "sg:tags":[
        "landscape",
        "contractor"
    ],
    "wof:name":"Best Landscaping Inc",
    "wof:placetype":"venue"
},
  "geometry": {"coordinates":[-117.87270700000001,34.115022],"type":"Point"}
}