{
  "type": "Feature",
  "properties": {
    "addr:full":"4447 Cowell Blvd Davis CA 95618",
    "addr:housenumber":"4447",
    "addr:postcode":"95618",
    "addr:street":"Cowell Blvd",
    "iso:country":"US",
    "sg:address":"4447 Cowell Blvd",
    "sg:city":"Davis",
    "sg:classifiers":[
        {
            "category":"Professional",
            "type":"Services"
        }
    ],
    "sg:phone":"+1 530 758 8244",
    "sg:postcode":"95618",
    "sg:province":"CA",
    "wof:name":"Robin A Keisper",
    "wof:placetype":"venue"
},
  "geometry": {"coordinates":[-121.694335,38.548777],"type":"Point"}
}