{
  "type": "Feature",
  "properties": {
    "addr:full":"1610 Oak St Solvang CA 93463",
    "addr:housenumber":"1610",
    "addr:postcode":"93463",
    "addr:street":"Oak St",
    "iso:country":"US",
    "sg:address":"1610 Oak St",
    "sg:city":"Solvang",
    "sg:classifiers":[
        {
            "category":"Professional",
            "subcategory":"Computer Services",
            "type":"Services"
        }
    ],
    "sg:phone":"+1 805 686 0854",
    "sg:postcode":"93463",
    "sg:province":"CA",
    "sg:tags":[
        "processing",
        "datum"
    ],
    "sg:website":"www.rdpwest.com",
    "wof:name":"Resort Data Processing",
    "wof:placetype":"venue"
},
  "geometry": {"coordinates":[-120.142211,34.593921],"type":"Point"}
}