{
  "type": "Feature",
  "properties": {
    "iso:country":"US",
    "sg:address":"703 Pier Ave",
    "sg:city":"Hermosa Beach",
    "sg:classifiers":[
        {
            "category":"Shopping",
            "type":"Retail Goods"
        }
    ],
    "sg:phone":"+1 310 374 0003",
    "sg:postcode":"90254",
    "sg:province":"CA",
    "sg:tags":[
        "cosmetic",
        "perfume"
    ],
    "wof:name":"Hermosa Beauty Ctr",
    "wof:placetype":"venue"
},
  "geometry": {"coordinates":[-118.393388,33.864806],"type":"Point"}
}