{
  "type": "Feature",
  "properties": {
    "iso:country":"US",
    "sg:address":"2226 E 3rd St",
    "sg:city":"Los Angeles",
    "sg:classifiers":[
        {
            "category":"Education",
            "subcategory":"School",
            "type":"Public Place"
        }
    ],
    "sg:phone":"+1 323 269 4343",
    "sg:postcode":"90033",
    "sg:province":"CA",
    "sg:tags":[
        "elementary"
    ],
    "wof:name":"Breed Street Elementary School",
    "wof:placetype":"venue"
},
  "geometry": {"coordinates":[-118.212997,34.042099],"type":"Point"}
}