{
  "type": "Feature",
  "properties": {
    "iso:country":"US",
    "sg:address":"220 N Andreason Dr",
    "sg:city":"Escondido",
    "sg:classifiers":[
        {
            "category":"Building & Trades",
            "subcategory":"Pest Control",
            "type":"Services"
        }
    ],
    "sg:phone":"+1 760 747 8169",
    "sg:postcode":"92029",
    "sg:province":"CA",
    "wof:name":"Statewide Fumigation",
    "wof:placetype":"venue"
},
  "geometry": {"coordinates":[-117.10916899999999,33.119],"type":"Point"}
}