{
  "type": "Feature",
  "properties": {
    "addr:full":"826 E 17th St Santa Ana CA 92701",
    "addr:housenumber":"826",
    "addr:postcode":"92701",
    "addr:street":"E 17Th St",
    "iso:country":"US",
    "sg:address":"826 E 17th St",
    "sg:city":"Santa Ana",
    "sg:classifiers":[
        {
            "category":"Professional",
            "subcategory":"Accounting & Tax Preparation",
            "type":"Services"
        }
    ],
    "sg:phone":"+1 714 558 0257",
    "sg:postcode":"92701",
    "sg:province":"CA",
    "sg:tags":[
        "return",
        "filing"
    ],
    "wof:name":"Rodriguez Tax Svc",
    "wof:placetype":"venue"
},
  "geometry": {"coordinates":[-117.85919699999999,33.759897],"type":"Point"}
}