{
  "type": "Feature",
  "properties": {
    "iso:country":"US",
    "sg:address":"502 N Vermont Ave",
    "sg:city":"Glendora",
    "sg:classifiers":[
        {
            "category":"Building & Trades",
            "subcategory":"Construction",
            "type":"Services"
        }
    ],
    "sg:phone":"+1 626 963 5311",
    "sg:postcode":"91741",
    "sg:province":"CA",
    "sg:tags":[
        "coping",
        "plastering",
        "tiling",
        "pool",
        "swimming"
    ],
    "wof:name":"Blue Aqua Tech",
    "wof:placetype":"venue"
},
  "geometry": {"coordinates":[-117.866653,34.14391],"type":"Point"}
}