{
  "type": "Feature",
  "properties": {
    "addr:full":"862 Cll la Prada Camarillo CA 93010",
    "addr:housenumber":"862",
    "addr:postcode":"93010",
    "addr:street":"Cll La Prada",
    "iso:country":"US",
    "sg:address":"862 Cll la Prada",
    "sg:city":"Camarillo",
    "sg:classifiers":[
        {
            "category":"Building & Trades",
            "subcategory":"Construction",
            "type":"Services"
        }
    ],
    "sg:phone":"+1 805 388 0348",
    "sg:postcode":"93010",
    "sg:province":"CA",
    "sg:tags":[
        "fence",
        "contractor"
    ],
    "wof:name":"Bob Mc Casland Fence Instlltn",
    "wof:placetype":"venue"
},
  "geometry": {"coordinates":[-119.068247,34.224794],"type":"Point"}
}