{
  "type": "Feature",
  "properties": {
    "addr:full":"13651 Magnolia St Garden Grove CA 92844",
    "addr:housenumber":"13651",
    "addr:postcode":"92844",
    "addr:street":"Magnolia St",
    "iso:country":"US",
    "sg:address":"13651 Magnolia St",
    "sg:city":"Garden Grove",
    "sg:classifiers":[
        {
            "category":"Donuts",
            "subcategory":"None",
            "type":"Food & Drink"
        }
    ],
    "sg:phone":"+1 714 894 5521",
    "sg:postcode":"92844",
    "sg:province":"CA",
    "wof:name":"Donut Maker the",
    "wof:placetype":"venue"
},
  "geometry": {"coordinates":[-117.97199999999999,33.765499],"type":"Point"}
}