{
  "type": "Feature",
  "properties": {
    "addr:full":"3570 Calevero Ln Oceanside CA 92056",
    "addr:postcode":"3570;92056",
    "addr:street":"Calevero Ln",
    "iso:country":"US",
    "sg:address":"3570 Calevero Ln",
    "sg:city":"Oceanside",
    "sg:classifiers":[
        {
            "category":"Building & Trades",
            "subcategory":"Construction",
            "type":"Services"
        }
    ],
    "sg:phone":"+1 760 724 0053",
    "sg:postcode":"92056",
    "sg:province":"CA",
    "sg:tags":[
        "manufactured",
        "housing-communities"
    ],
    "wof:name":"Rancho Calevero Mobile Home Pk",
    "wof:placetype":"venue"
},
  "geometry": {"coordinates":[-117.279309,33.178799],"type":"Point"}
}