{
  "type": "Feature",
  "properties": {
    "iso:country":"US",
    "sg:address":"2227 Mariner Square Loop Mariner Square Athletic Club",
    "sg:city":"Alameda",
    "sg:classifiers":[
        {
            "category":"Food & Beverages",
            "subcategory":"Bakery",
            "type":"Retail Goods"
        }
    ],
    "sg:phone":"+1 510 523 7797",
    "sg:postcode":"94501",
    "sg:province":"CA",
    "sg:tags":[
        "sandwich"
    ],
    "wof:name":"The Feel Good Cafe",
    "wof:placetype":"venue"
},
  "geometry": {"coordinates":[-122.279155,37.785352],"type":"Point"}
}