{
  "type": "Feature",
  "properties": {
    "iso:country":"US",
    "sg:address":"6505 Channing Dr",
    "sg:city":"North Highlands",
    "sg:classifiers":[
        {
            "category":"Building & Trades",
            "subcategory":"Construction",
            "type":"Services"
        }
    ],
    "sg:phone":"+1 916 334 8596",
    "sg:postcode":"95660",
    "sg:province":"CA",
    "sg:tags":[
        "resurfacing",
        "laying",
        "refinishing",
        "floor"
    ],
    "wof:name":"Big Valley Floorcovering",
    "wof:placetype":"venue"
},
  "geometry": {"coordinates":[-121.382725,38.685738],"type":"Point"}
}