{
  "type": "Feature",
  "properties": {
    "iso:country":"US",
    "sg:address":"6310 Monterey Rd",
    "sg:city":"Gilroy",
    "sg:classifiers":[
        {
            "category":"Autos & Motor Vehicles",
            "subcategory":"Automobile Sales",
            "type":"Retail Goods"
        }
    ],
    "sg:phone":"+1 408 848 3448",
    "sg:postcode":"95020",
    "sg:province":"CA",
    "sg:tags":[
        "used"
    ],
    "wof:name":"Used Car Outlet",
    "wof:placetype":"venue"
},
  "geometry": {"coordinates":[-121.56578,37.00026],"type":"Point"}
}