{
  "type": "Feature",
  "properties": {
    "addr:full":"16635 Pacific Coast Hwy Huntington Beach CA 92649",
    "addr:housenumber":"16635",
    "addr:postcode":"92649",
    "addr:street":"Pacific Coast Hwy",
    "iso:country":"US",
    "sg:address":"16635 Pacific Coast Hwy",
    "sg:city":"Huntington Beach",
    "sg:classifiers":[
        {
            "category":"Food & Beverages",
            "subcategory":"Liquor & Beverages",
            "type":"Retail Goods"
        }
    ],
    "sg:phone":"+1 562 592 0900",
    "sg:postcode":"92649",
    "sg:province":"CA",
    "sg:tags":[
        "wine"
    ],
    "wof:name":"A Taste Of Napa",
    "wof:placetype":"venue"
},
  "geometry": {"coordinates":[-118.07342800000001,33.720236],"type":"Point"}
}