{
  "type": "Feature",
  "properties": {
    "addr:full":"1706 Newport Blvd Costa Mesa CA 92627",
    "addr:housenumber":"1706",
    "addr:postcode":"92627",
    "addr:street":"Newport Blvd Costa",
    "iso:country":"US",
    "sg:address":"1706 Newport Blvd",
    "sg:city":"Costa Mesa",
    "sg:classifiers":[
        {
            "category":"Professional",
            "subcategory":"Lawyer & Legal Services",
            "type":"Services"
        }
    ],
    "sg:phone":"+1 949 650 3328",
    "sg:postcode":"92627",
    "sg:province":"CA",
    "wof:name":"Coleman Hillary C Attorney And counselor At Law",
    "wof:placetype":"venue"
},
  "geometry": {"coordinates":[-117.921386,33.637625],"type":"Point"}
}