{
  "type": "Feature",
  "properties": {
    "addr:full":"1753 S Hill Street Los Angeles CA 90015",
    "addr:housenumber":"1753",
    "addr:postcode":"90015",
    "addr:street":"S Hill Street",
    "iso:country":"US",
    "sg:address":"1753 S Hill Street",
    "sg:city":"Los Angeles",
    "sg:classifiers":[
        {
            "category":"Restaurant",
            "type":"Food & Drink"
        }
    ],
    "sg:phone":"+1 213 749 1001",
    "sg:postcode":"90015",
    "sg:province":"CA",
    "wof:name":"Down Town Pho",
    "wof:placetype":"venue"
},
  "geometry": {"coordinates":[-118.265653,34.033554],"type":"Point"}
}