{
  "type": "Feature",
  "properties": {
    "addr:full":"1235 Naturewood Dr Colfax CA 95722",
    "addr:housenumber":"1235",
    "addr:postcode":"95722",
    "addr:street":"Naturewood Dr",
    "iso:country":"US",
    "sg:address":"1235 Naturewood Dr",
    "sg:city":"Colfax",
    "sg:classifiers":[
        {
            "category":"Professional",
            "subcategory":"Management & Consulting",
            "type":"Services"
        }
    ],
    "sg:phone":"+1 916 223 6466",
    "sg:postcode":"95722",
    "sg:province":"CA",
    "sg:tags":[
        "consultant",
        "training"
    ],
    "wof:name":"Success Connection",
    "wof:placetype":"venue"
},
  "geometry": {"coordinates":[-121.003894,39.028869],"type":"Point"}
}