{
  "type": "Feature",
  "properties": {
    "iso:country":"US",
    "sg:address":"3300 Balboa St",
    "sg:city":"San Francisco",
    "sg:classifiers":[
        {
            "category":"Education",
            "subcategory":"Preschool",
            "type":"Public Place"
        },
        {
            "category":"Education",
            "subcategory":"School",
            "type":"Public Place"
        }
    ],
    "sg:phone":"+1 415 668 3300",
    "sg:postcode":"94121",
    "sg:province":"CA",
    "sg:tags":[
        "elementary"
    ],
    "wof:name":"Multicultural Preschool",
    "wof:placetype":"venue"
},
  "geometry": {"coordinates":[-122.494299,37.776099],"type":"Point"}
}