{
  "type": "Feature",
  "properties": {
    "addr:full":"90 Icon El Toro CA 92610",
    "addr:housenumber":"90",
    "addr:postcode":"92610",
    "addr:street":"Icon El Toro",
    "iso:country":"US",
    "sg:address":"90 Icon",
    "sg:city":"El Toro",
    "sg:classifiers":[
        {
            "category":"Wholesale",
            "subcategory":"Medical Equipment & Supplies",
            "type":"Manufacturing & Wholesale Goods"
        }
    ],
    "sg:phone":"+1 949 580 1555",
    "sg:postcode":"92610",
    "sg:province":"CA",
    "sg:tags":[
        "electronic"
    ],
    "wof:name":"Nihon Kohden America Inc",
    "wof:placetype":"venue"
},
  "geometry": {"coordinates":[-117.646478,33.669309],"type":"Point"}
}