{
  "type": "Feature",
  "properties": {
    "iso:country":"US",
    "sg:address":"6200 E Pacific Coast Hwy",
    "sg:city":"Long Beach",
    "sg:classifiers":[
        {
            "category":"Banks & Credit Unions",
            "subcategory":"Bank",
            "type":"Services"
        }
    ],
    "sg:phone":"+1 562 494 4009",
    "sg:postcode":"90803",
    "sg:province":"CA",
    "wof:name":"First Bank & Trust",
    "wof:placetype":"venue"
},
  "geometry": {"coordinates":[-118.115423,33.763708],"type":"Point"}
}