{
  "type": "Feature",
  "properties": {
    "addr:full":"11550 Whittier Blvd Whittier CA 90601",
    "addr:housenumber":"11550",
    "addr:postcode":"90601",
    "addr:street":"Whittier Blvd",
    "iso:country":"US",
    "sg:address":"11550 Whittier Blvd",
    "sg:city":"Whittier",
    "sg:classifiers":[
        {
            "category":"Restaurant",
            "type":"Food & Drink"
        }
    ],
    "sg:menulink":"http://www.allmenus.com/ca/whittier/78737-pizza-hut/menu/",
    "sg:phone":"+1 562 699 4000",
    "sg:postcode":"90601",
    "sg:province":"CA",
    "sg:tags":[
        "american",
        "pizza"
    ],
    "wof:name":"Pizza Hut",
    "wof:placetype":"venue"
},
  "geometry": {"coordinates":[-118.05424600000001,33.982983],"type":"Point"}
}