{
  "type": "Feature",
  "properties": {
    "addr:full":"416 Middle Creek Dr Chico CA 95973",
    "addr:housenumber":"416",
    "addr:postcode":"95973",
    "addr:street":"Middle Creek Dr",
    "iso:country":"US",
    "sg:address":"416 Middle Creek Dr",
    "sg:city":"Chico",
    "sg:classifiers":[
        {
            "category":"Building & Trades",
            "subcategory":"Construction",
            "type":"Services"
        }
    ],
    "sg:phone":"+1 530 893 2034",
    "sg:postcode":"95973",
    "sg:province":"CA",
    "sg:tags":[
        "dry wall",
        "contractor"
    ],
    "wof:name":"Affordable Drywall",
    "wof:placetype":"venue"
},
  "geometry": {"coordinates":[-121.88214000000001,39.765893],"type":"Point"}
}