{
  "type": "Feature",
  "properties": {
    "addr:full":"909 N Manhattan Ave Manhattan Beach CA 90266",
    "addr:housenumber":"909",
    "addr:postcode":"90266",
    "addr:street":"N Manhattan Ave",
    "iso:country":"US",
    "sg:address":"909 N Manhattan Ave",
    "sg:city":"Manhattan Beach",
    "sg:classifiers":[
        {
            "category":"Building & Trades",
            "subcategory":"Cleaning & Sanitation",
            "type":"Services"
        }
    ],
    "sg:phone":"+1 310 579 2855",
    "sg:postcode":"90266",
    "sg:province":"CA",
    "sg:tags":[
        "carpet"
    ],
    "wof:name":"Citrus Fresh Carpet Cleaning",
    "wof:placetype":"venue"
},
  "geometry": {"coordinates":[-118.40982700000001,33.883024],"type":"Point"}
}