{
  "type": "Feature",
  "properties": {
    "addr:full":"12711 Ramona Blvd Irwindale CA 91706",
    "addr:housenumber":"12711",
    "addr:postcode":"91706",
    "addr:street":"Ramona Blvd",
    "iso:country":"US",
    "sg:address":"12711 Ramona Blvd",
    "sg:city":"Irwindale",
    "sg:classifiers":[
        {
            "category":"Health Services",
            "subcategory":"Doctor",
            "type":"Services"
        }
    ],
    "sg:phone":"+1 626 856 3944",
    "sg:postcode":"91706",
    "sg:province":"CA",
    "sg:tags":[
        "clinic"
    ],
    "wof:name":"FMC Dialysis Svc-Irwindale",
    "wof:placetype":"venue"
},
  "geometry": {"coordinates":[-117.993486,34.0787],"type":"Point"}
}