{
  "type": "Feature",
  "properties": {
    "addr:full":"3334 Victor Ct Santa Clara CA 95054",
    "addr:housenumber":"3334",
    "addr:postcode":"95054",
    "addr:street":"Victor Ct",
    "iso:country":"US",
    "sg:address":"3334 Victor Ct",
    "sg:city":"Santa Clara",
    "sg:classifiers":[
        {
            "category":"Professional",
            "subcategory":"Testing Lab",
            "type":"Services"
        }
    ],
    "sg:phone":"+1 408 588 0200",
    "sg:postcode":"95054",
    "sg:province":"CA",
    "sg:tags":[
        "laboratory"
    ],
    "sg:website":"www.entechlabs.com",
    "wof:name":"Entech Analytical Labs Inc",
    "wof:placetype":"venue"
},
  "geometry": {"coordinates":[-121.93858400000001,37.386018],"type":"Point"}
}