{
  "type": "Feature",
  "properties": {
    "addr:full":"4637 Sunset Dr Sacramento CA 95822",
    "addr:housenumber":"4637",
    "addr:postcode":"95822",
    "addr:street":"Sunset Dr",
    "iso:country":"US",
    "sg:address":"4637 Sunset Dr",
    "sg:city":"Sacramento",
    "sg:classifiers":[
        {
            "category":"Retail",
            "subcategory":"Repair Shop",
            "type":"Services"
        }
    ],
    "sg:phone":"+1 916 448 4668",
    "sg:postcode":"95822",
    "sg:province":"CA",
    "sg:tags":[
        "equipment",
        "conditioning",
        "air"
    ],
    "wof:name":"Oshita Refrigeration & AC",
    "wof:placetype":"venue"
},
  "geometry": {"coordinates":[-121.50995399999999,38.531891],"type":"Point"}
}