{
  "type": "Feature",
  "properties": {
    "iso:country":"US",
    "sg:address":"3004 El Camino Real",
    "sg:city":"Santa Clara",
    "sg:classifiers":[
        {
            "category":"Retail",
            "subcategory":"Laundry & Dry Cleaning",
            "type":"Services"
        }
    ],
    "sg:phone":"+1 408 246 3110",
    "sg:postcode":"95051",
    "sg:province":"CA",
    "wof:name":"Tiffany's Cleaners",
    "wof:placetype":"venue"
},
  "geometry": {"coordinates":[-121.980791,37.35241],"type":"Point"}
}