{
  "type": "Feature",
  "properties": {
    "addr:full":"10170 Croydon Way Ste G Sacramento CA 95827",
    "addr:housenumber":"10170",
    "addr:postcode":"95827",
    "addr:street":"Croydon Way Ste G",
    "iso:country":"US",
    "sg:address":"10170 Croydon Way Ste G",
    "sg:city":"Sacramento",
    "sg:classifiers":[
        {
            "category":"Home & Garden",
            "subcategory":"Building Materials",
            "type":"Retail Goods"
        }
    ],
    "sg:phone":"+1 916 626 3000",
    "sg:postcode":"95827",
    "sg:province":"CA",
    "sg:tags":[
        "energy",
        "conservation",
        "product"
    ],
    "wof:name":"Ez-Clone",
    "wof:placetype":"venue"
},
  "geometry": {"coordinates":[-121.31085899999999,38.582015],"type":"Point"}
}