{
  "type": "Feature",
  "properties": {
    "iso:country":"US",
    "sg:address":"10724 Palm Ave",
    "sg:city":"Bakersfield",
    "sg:classifiers":[
        {
            "category":"Insurance",
            "subcategory":"Insurance Agent",
            "type":"Services"
        }
    ],
    "sg:phone":"+1 661 587 5183",
    "sg:postcode":"93312",
    "sg:province":"CA",
    "wof:name":"Bill Novickas Insurance",
    "wof:placetype":"venue"
},
  "geometry": {"coordinates":[-119.124701,35.376247],"type":"Point"}
}