{
  "type": "Feature",
  "properties": {
    "iso:country":"US",
    "sg:address":"3001 el Camino Ave",
    "sg:city":"Sacramento",
    "sg:classifiers":[
        {
            "category":"Banks & Credit Unions",
            "subcategory":"Bank",
            "type":"Services"
        }
    ],
    "sg:phone":"+1 916 974 6873",
    "sg:postcode":"95821",
    "sg:province":"CA",
    "sg:tags":[
        "loan",
        "real estate"
    ],
    "wof:name":"Windsor Capital",
    "wof:placetype":"venue"
},
  "geometry": {"coordinates":[-121.393282,38.610561],"type":"Point"}
}