{
  "type": "Feature",
  "properties": {
    "addr:full":"2310 E Ponderosa Dr Camarillo CA 93010",
    "addr:housenumber":"2310",
    "addr:postcode":"93010",
    "addr:street":"E Ponderosa Dr",
    "iso:country":"US",
    "sg:address":"2310 E Ponderosa Dr",
    "sg:city":"Camarillo",
    "sg:classifiers":[
        {
            "category":"Travel",
            "subcategory":"Travel Agent",
            "type":"Entertainment"
        }
    ],
    "sg:phone":"+1 805 484 2863",
    "sg:postcode":"93010",
    "sg:province":"CA",
    "sg:tags":[
        "agency",
        "bureau"
    ],
    "wof:name":"Camarillo Travel",
    "wof:placetype":"venue"
},
  "geometry": {"coordinates":[-119.039005,34.223451],"type":"Point"}
}