{
  "type": "Feature",
  "properties": {
    "addr:full":"944 A St Ramona CA 92065",
    "addr:housenumber":"944",
    "addr:postcode":"92065",
    "addr:street":"A St",
    "iso:country":"US",
    "sg:address":"944 A St",
    "sg:city":"Ramona",
    "sg:classifiers":[
        {
            "category":"Retail",
            "subcategory":"Auto Repair",
            "type":"Services"
        }
    ],
    "sg:phone":"+1 760 788 9605",
    "sg:postcode":"92065",
    "sg:province":"CA",
    "sg:tags":[
        "body",
        "repairing",
        "painting",
        "automobile"
    ],
    "wof:name":"Basel's Body & Frame",
    "wof:placetype":"venue"
},
  "geometry": {"coordinates":[-116.868702,33.044457],"type":"Point"}
}