{
  "type": "Feature",
  "properties": {
    "iso:country":"US",
    "sg:address":"533 W Foothill Blvd",
    "sg:city":"Glendora",
    "sg:classifiers":[
        {
            "category":"Food & Beverages",
            "subcategory":"Supermarket",
            "type":"Retail Goods"
        }
    ],
    "sg:phone":"+1 800 745 8423",
    "sg:postcode":"91741",
    "sg:province":"CA",
    "sg:tags":[
        "super",
        "store"
    ],
    "wof:name":"California Day-Fresh Foods",
    "wof:placetype":"venue"
},
  "geometry": {"coordinates":[-117.873795,34.13604],"type":"Point"}
}