{
  "type": "Feature",
  "properties": {
    "iso:country":"US",
    "sg:address":"6409 S Newmark Ave",
    "sg:city":"Parlier",
    "sg:classifiers":[
        {
            "category":"Professional",
            "subcategory":"Detective & Security Services",
            "type":"Services"
        }
    ],
    "sg:phone":"+1 559 452 0484",
    "sg:postcode":"93648",
    "sg:province":"CA",
    "sg:tags":[
        "investigator"
    ],
    "wof:name":"Vang Investigations",
    "wof:placetype":"venue"
},
  "geometry": {"coordinates":[-119.529666,36.639827],"type":"Point"}
}