{
  "type": "Feature",
  "properties": {
    "iso:country":"US",
    "sg:address":"550 S Winchester Blvd Ste 500",
    "sg:city":"San Jose",
    "sg:classifiers":[
        {
            "category":"Restaurant",
            "type":"Food & Drink"
        }
    ],
    "sg:phone":"+1 408 241 0158",
    "sg:postcode":"95128",
    "sg:province":"CA",
    "sg:tags":[
        "tex-mex"
    ],
    "sg:website":"www.chevys.com/",
    "wof:name":"Chevy's Fresh Mex",
    "wof:placetype":"venue"
},
  "geometry": {"coordinates":[-121.949455,37.317689],"type":"Point"}
}