{
  "type": "Feature",
  "properties": {
    "iso:country":"US",
    "sg:address":"2606 Main St",
    "sg:city":"Cambria",
    "sg:classifiers":[
        {
            "category":"Professional",
            "subcategory":"Accounting & Tax Preparation",
            "type":"Services"
        }
    ],
    "sg:phone":"+1 805 927 1225",
    "sg:postcode":"93428",
    "sg:province":"CA",
    "sg:tags":[
        "accountant"
    ],
    "wof:name":"Cambria Tax & Financial Svc",
    "wof:placetype":"venue"
},
  "geometry": {"coordinates":[-121.07691800000001,35.566562],"type":"Point"}
}