{
  "type": "Feature",
  "properties": {
    "iso:country":"US",
    "sg:address":"12532 Jackson Hill Ln",
    "sg:city":"El Cajon",
    "sg:classifiers":[
        {
            "category":"Banks & Credit Unions",
            "subcategory":"Financial Services",
            "type":"Services"
        }
    ],
    "sg:phone":"+1 619 390 9305",
    "sg:postcode":"92021",
    "sg:province":"CA",
    "sg:tags":[
        "trust",
        "management"
    ],
    "wof:name":"Cranford Revocable Family",
    "wof:placetype":"venue"
},
  "geometry": {"coordinates":[-116.91973400000001,32.827611],"type":"Point"}
}