{
  "type": "Feature",
  "properties": {
    "iso:country":"US",
    "sg:address":"4610 Northgate Blvd.",
    "sg:city":"Sacramento",
    "sg:classifiers":[
        {
            "category":"Professional",
            "subcategory":"Detective & Security Services",
            "type":"Services"
        },
        {
            "category":"Building & Trades",
            "subcategory":"Locksmith",
            "type":"Services"
        }
    ],
    "sg:phone":"+1 916 535 0012",
    "sg:postcode":"95834",
    "sg:province":"CA",
    "sg:tags":[
        "system",
        "key"
    ],
    "sg:website":"burgarelloalarm.com",
    "wof:name":"Burgarello Alarm",
    "wof:placetype":"venue"
},
  "geometry": {"coordinates":[-121.477655,38.652134],"type":"Point"}
}