{
  "type": "Feature",
  "properties": {
    "addr:full":"9310 Pioneer Dr Bakersfield CA 93306",
    "addr:housenumber":"9310",
    "addr:postcode":"93306",
    "addr:street":"Pioneer Dr",
    "iso:country":"US",
    "sg:address":"9310 Pioneer Dr",
    "sg:city":"Bakersfield",
    "sg:classifiers":[
        {
            "category":"Building & Trades",
            "subcategory":"Landscaping Services",
            "type":"Services"
        }
    ],
    "sg:phone":"+1 661 578 4350",
    "sg:postcode":"93306",
    "sg:province":"CA",
    "sg:tags":[
        "lawn",
        "tree",
        "arborist",
        "maintenance"
    ],
    "wof:name":"Safety Tree Service",
    "wof:placetype":"venue"
},
  "geometry": {"coordinates":[-118.900727,35.369018],"type":"Point"}
}