{
  "type": "Feature",
  "properties": {
    "addr:full":"2411 Cunningham Ln Coleville CA 96107",
    "addr:housenumber":"2411",
    "addr:postcode":"96107",
    "addr:street":"Cunningham Ln",
    "iso:country":"US",
    "sg:address":"2411 Cunningham Ln",
    "sg:city":"Coleville",
    "sg:classifiers":[
        {
            "category":"Building & Trades",
            "subcategory":"Construction",
            "type":"Services"
        }
    ],
    "sg:phone":"+1 530 495 2772",
    "sg:postcode":"96107",
    "sg:province":"CA",
    "sg:tags":[
        "general",
        "contractor"
    ],
    "wof:name":"A & A Construction Inc",
    "wof:placetype":"venue"
},
  "geometry": {"coordinates":[-119.47125200000001,38.578633],"type":"Point"}
}