{
  "type": "Feature",
  "properties": {
    "iso:country":"US",
    "sg:address":"419 Main St Ste 486",
    "sg:city":"Huntington Beach",
    "sg:classifiers":[
        {
            "category":"Building & Trades",
            "subcategory":"Construction",
            "type":"Services"
        }
    ],
    "sg:phone":"+1 714 960 8285",
    "sg:postcode":"92648",
    "sg:province":"CA",
    "sg:tags":[
        "handyman"
    ],
    "sg:website":"www.hammershandyman.com",
    "wof:name":"Hammers Handyman Services",
    "wof:placetype":"venue"
},
  "geometry": {"coordinates":[-117.999199,33.660685],"type":"Point"}
}