{
  "type": "Feature",
  "properties": {
    "addr:full":"2833 Leonis Blvd Los Angeles CA 90058",
    "addr:housenumber":"2833",
    "addr:postcode":"90058",
    "addr:street":"Leonis Blvd",
    "iso:country":"US",
    "sg:address":"2833 Leonis Blvd",
    "sg:city":"Los Angeles",
    "sg:classifiers":[
        {
            "category":"Freight",
            "type":"Transportation"
        }
    ],
    "sg:phone":"+1 323 584 1175",
    "sg:postcode":"90058",
    "sg:province":"CA",
    "sg:tags":[
        "arrangement"
    ],
    "wof:name":"Mexam International Inc",
    "wof:placetype":"venue"
},
  "geometry": {"coordinates":[-118.21361899999999,34.000205],"type":"Point"}
}