{
  "type": "Feature",
  "properties": {
    "iso:country":"US",
    "sg:address":"13045 Tom White Way",
    "sg:city":"Norwalk",
    "sg:classifiers":[
        {
            "category":"Manufacturing",
            "subcategory":"Tools & Machinery",
            "type":"Manufacturing & Wholesale Goods"
        }
    ],
    "sg:phone":"+1 562 926 7184",
    "sg:postcode":"90650",
    "sg:province":"CA",
    "sg:tags":[
        "industrial",
        "mfg"
    ],
    "wof:name":"Toms Machining Service",
    "wof:placetype":"venue"
},
  "geometry": {"coordinates":[-118.053466,33.905239],"type":"Point"}
}