{
  "type": "Feature",
  "properties": {
    "iso:country":"US",
    "sg:address":"25495 Whitesell St",
    "sg:city":"Hayward",
    "sg:classifiers":[
        {
            "category":"Wholesale",
            "subcategory":"Medical Equipment & Supplies",
            "type":"Manufacturing & Wholesale Goods"
        }
    ],
    "sg:phone":"+1 510 783 1112",
    "sg:postcode":"94545",
    "sg:province":"CA",
    "sg:tags":[
        "pharmaceutical",
        "products-wholesale",
        "manufacturer"
    ],
    "sg:website":"http://www.elimbio.com",
    "wof:name":"Elim Biopharmaceuticals Inc.",
    "wof:placetype":"venue"
},
  "geometry": {"coordinates":[-122.128781,37.630315],"type":"Point"}
}