{
  "type": "Feature",
  "properties": {
    "addr:full":"2441 Park Ave Tustin CA 92781",
    "addr:housenumber":"2441",
    "addr:postcode":"92781",
    "addr:street":"Park Ave",
    "iso:country":"US",
    "sg:address":"2441 Park Ave",
    "sg:city":"Tustin",
    "sg:classifiers":[
        {
            "category":"Sports & Exercise",
            "subcategory":"Bicycle Rental",
            "type":"Entertainment"
        }
    ],
    "sg:phone":"+1 714 259 1098",
    "sg:postcode":"92781",
    "sg:province":"CA",
    "sg:tags":[
        "wear"
    ],
    "wof:name":"The Finish Line",
    "wof:placetype":"venue"
},
  "geometry": {"coordinates":[-117.873564,33.768996],"type":"Point"}
}