{
  "type": "Feature",
  "properties": {
    "addr:full":"5224 Bell Ct Chino CA 91710",
    "addr:housenumber":"5224",
    "addr:postcode":"91710",
    "addr:street":"Bell Ct",
    "iso:country":"US",
    "sg:address":"5224 Bell Ct",
    "sg:city":"Chino",
    "sg:classifiers":[
        {
            "category":"Building & Trades",
            "subcategory":"Construction",
            "type":"Services"
        }
    ],
    "sg:phone":"+1 909 902 5333",
    "sg:postcode":"91710",
    "sg:province":"CA",
    "sg:tags":[
        "contractor"
    ],
    "sg:website":"www.proteamconstruction.com",
    "wof:name":"Pro-Team Construction",
    "wof:placetype":"venue"
},
  "geometry": {"coordinates":[-117.689682,33.995172],"type":"Point"}
}