{
  "type": "Feature",
  "properties": {
    "addr:full":"5500 Trabuco Road Suite 150 Irvine CA 92620",
    "addr:housenumber":"5500",
    "addr:postcode":"92620",
    "addr:street":"Trabuco Road Suite 150",
    "iso:country":"US",
    "sg:address":"5500 Trabuco Road Suite 150",
    "sg:city":"Irvine",
    "sg:classifiers":[
        {
            "category":"Professional",
            "subcategory":"Lawyer & Legal Services",
            "type":"Services"
        }
    ],
    "sg:phone":"+1 949 679 9787",
    "sg:postcode":"92620",
    "sg:province":"CA",
    "wof:name":"Law Offices of Hal W Wolowski & Assoc",
    "wof:placetype":"venue"
},
  "geometry": {"coordinates":[-117.764464,33.697971],"type":"Point"}
}