{
  "type": "Feature",
  "properties": {
    "addr:full":"489 Saratoga Ave San Jose CA 95129",
    "addr:housenumber":"489",
    "addr:postcode":"95129",
    "addr:street":"Saratoga Ave",
    "iso:country":"US",
    "sg:address":"489 Saratoga Ave",
    "sg:city":"San Jose",
    "sg:classifiers":[
        {
            "category":"Retail",
            "subcategory":"Photofinishing",
            "type":"Services"
        }
    ],
    "sg:phone":"+1 408 983 2477",
    "sg:postcode":"95129",
    "sg:province":"CA",
    "sg:tags":[
        "photograph",
        "developer"
    ],
    "wof:name":"One Hour Photo",
    "wof:placetype":"venue"
},
  "geometry": {"coordinates":[-121.973857,37.318495],"type":"Point"}
}