{
  "type": "Feature",
  "properties": {
    "iso:country":"US",
    "sg:address":"9555 Owensmouth Ave",
    "sg:city":"Chatsworth",
    "sg:classifiers":[
        {
            "category":"Shopping",
            "subcategory":"Clothing, Apparel, & Fashions",
            "type":"Retail Goods"
        }
    ],
    "sg:phone":"+1 818 718 5600",
    "sg:postcode":"91311",
    "sg:province":"CA",
    "wof:name":"Lounge Fly",
    "wof:placetype":"venue"
},
  "geometry": {"coordinates":[-118.60179599999999,34.24652],"type":"Point"}
}