{
  "type": "Feature",
  "properties": {
    "iso:country":"US",
    "sg:address":"523 Yerba Buena St",
    "sg:city":"Morro Bay",
    "sg:classifiers":[
        {
            "category":"Shopping",
            "subcategory":"Used Merchandise",
            "type":"Retail Goods"
        }
    ],
    "sg:phone":"+1 805 772 4403",
    "sg:postcode":"93442",
    "sg:province":"CA",
    "sg:tags":[
        "computer",
        "reseller"
    ],
    "wof:name":"Jed Enterprises",
    "wof:placetype":"venue"
},
  "geometry": {"coordinates":[-120.86431399999999,35.406764],"type":"Point"}
}