{
  "type": "Feature",
  "properties": {
    "addr:full":"1230 N Walnut St La Habra CA 90631",
    "addr:housenumber":"1230",
    "addr:postcode":"90631",
    "addr:street":"N Walnut St",
    "iso:country":"US",
    "sg:address":"1230 N Walnut St",
    "sg:city":"La Habra",
    "sg:classifiers":[
        {
            "category":"Building & Trades",
            "subcategory":"Plumbing",
            "type":"Services"
        }
    ],
    "sg:phone":"+1 562 691 3035",
    "sg:postcode":"90631",
    "sg:province":"CA",
    "sg:tags":[
        "contractor"
    ],
    "wof:name":"Terrance C Brown AC Tech",
    "wof:placetype":"venue"
},
  "geometry": {"coordinates":[-117.950468,33.942453],"type":"Point"}
}