{
  "type": "Feature",
  "properties": {
    "iso:country":"US",
    "sg:address":"4485 Woodley Ave",
    "sg:city":"Encino",
    "sg:classifiers":[
        {
            "category":"Wholesale",
            "subcategory":"Hardware",
            "type":"Manufacturing & Wholesale Goods"
        }
    ],
    "sg:phone":"+1 818 788 9840",
    "sg:postcode":"91436",
    "sg:province":"CA",
    "sg:tags":[
        "tool",
        "power",
        "hand"
    ],
    "wof:name":"Chicago Industrial Tool Co",
    "wof:placetype":"venue"
},
  "geometry": {"coordinates":[-118.483488,34.151624],"type":"Point"}
}