{
  "type": "Feature",
  "properties": {
    "addr:full":"3033 Coffee Rd Modesto CA 95355",
    "addr:housenumber":"3033",
    "addr:postcode":"ca 95355",
    "addr:street":"Coffee Rd",
    "iso:country":"US",
    "sg:address":"3033 Coffee Rd",
    "sg:city":"Modesto",
    "sg:classifiers":[
        {
            "category":"Manufacturing",
            "subcategory":"Retail Goods",
            "type":"Manufacturing & Wholesale Goods"
        }
    ],
    "sg:phone":"+1 209 522 9399",
    "sg:postcode":"95355",
    "sg:province":"CA",
    "sg:tags":[
        "product",
        "mfg"
    ],
    "wof:name":"Moss Manufacturing",
    "wof:placetype":"venue"
},
  "geometry": {"coordinates":[-120.976049,37.683509],"type":"Point"}
}