{
  "type": "Feature",
  "properties": {
    "addr:full":"30048 Mission Boulevard Suite 131 Hayward CA 94544",
    "addr:housenumber":"30048",
    "addr:postcode":"94544",
    "addr:street":"Mission Boulevard Suite 131",
    "iso:country":"US",
    "sg:address":"30048 Mission Boulevard Suite 131",
    "sg:city":"Hayward",
    "sg:classifiers":[
        {
            "category":"Communications",
            "type":"Services"
        }
    ],
    "sg:phone":"+1 510 477 9377",
    "sg:postcode":"94544",
    "sg:province":"CA",
    "sg:tags":[
        "recording",
        "rehearsal",
        "studio"
    ],
    "sg:website":"www.perfecttimingmusic.com",
    "wof:name":"Perfect Timing Music Studio",
    "wof:placetype":"venue"
},
  "geometry": {"coordinates":[-122.04194,37.625467],"type":"Point"}
}