{
  "type": "Feature",
  "properties": {
    "iso:country":"US",
    "sg:address":"228 W Bonita Ave",
    "sg:city":"Claremont",
    "sg:classifiers":[
        {
            "category":"Professional",
            "subcategory":"Management & Consulting",
            "type":"Services"
        }
    ],
    "sg:phone":"+1 909 399 0601",
    "sg:postcode":"91711",
    "sg:province":"CA",
    "sg:tags":[
        "consultant",
        "energy",
        "conservation"
    ],
    "wof:name":"Internaional Energy Group",
    "wof:placetype":"venue"
},
  "geometry": {"coordinates":[-117.71679399999999,34.096542],"type":"Point"}
}