{
  "type": "Feature",
  "properties": {
    "addr:full":"400 W Firebaugh Ave Exeter CA 93221",
    "addr:housenumber":"400",
    "addr:postcode":"93221",
    "addr:street":"W Firebaugh Ave",
    "iso:country":"US",
    "sg:address":"400 W Firebaugh Ave",
    "sg:city":"Exeter",
    "sg:classifiers":[
        {
            "category":"Freight",
            "type":"Transportation"
        }
    ],
    "sg:phone":"+1 559 592 4482",
    "sg:postcode":"93221",
    "sg:province":"CA",
    "sg:tags":[
        "general"
    ],
    "wof:name":"Quality Self Storage",
    "wof:placetype":"venue"
},
  "geometry": {"coordinates":[-119.14429699999999,36.289977],"type":"Point"}
}