{
  "type": "Feature",
  "properties": {
    "addr:full":"1085 Longridge Rd Oakland CA 94610",
    "addr:housenumber":"1085",
    "addr:postcode":"94610",
    "addr:street":"Longridge Rd",
    "iso:country":"US",
    "sg:address":"1085 Longridge Rd",
    "sg:city":"Oakland",
    "sg:classifiers":[
        {
            "category":"Banks & Credit Unions",
            "subcategory":"Financial Services",
            "type":"Services"
        }
    ],
    "sg:phone":"+1 510 444 1668",
    "sg:postcode":"94610",
    "sg:province":"CA",
    "sg:tags":[
        "trust",
        "nonprofit",
        "management"
    ],
    "wof:name":"International Foundation For C",
    "wof:placetype":"venue"
},
  "geometry": {"coordinates":[-122.230301,37.81015],"type":"Point"}
}