{
  "type": "Feature",
  "properties": {
    "iso:country":"US",
    "sg:address":"3903 W Sunset Blvd",
    "sg:city":"Los Angeles",
    "sg:classifiers":[
        {
            "category":"Retail",
            "subcategory":"Self-service Laundry",
            "type":"Services"
        }
    ],
    "sg:phone":"+1 323 661 5241",
    "sg:postcode":"90029",
    "sg:province":"CA",
    "wof:name":"Sunset Launderland",
    "wof:placetype":"venue"
},
  "geometry": {"coordinates":[-118.28030099999999,34.092496],"type":"Point"}
}