{
  "type": "Feature",
  "properties": {
    "iso:country":"US",
    "sg:address":"1820 Scott Ave",
    "sg:city":"Corning",
    "sg:classifiers":[
        {
            "category":"Manufacturing",
            "subcategory":"Metals",
            "type":"Manufacturing & Wholesale Goods"
        }
    ],
    "sg:phone":"+1 530 567 5258",
    "sg:postcode":"96021",
    "sg:province":"CA",
    "wof:name":"Gonzalez Art Polishing",
    "wof:placetype":"venue"
},
  "geometry": {"coordinates":[-122.189182,39.924813],"type":"Point"}
}