{
  "type": "Feature",
  "properties": {
    "iso:country":"US",
    "sg:address":"2605 9th Ave",
    "sg:city":"Oakland",
    "sg:classifiers":[
        {
            "category":"Communications",
            "subcategory":"Newspaper",
            "type":"Services"
        }
    ],
    "sg:phone":"+1 510 419 0262",
    "sg:postcode":"94606",
    "sg:province":"CA",
    "wof:name":"The San Antonio Unity Newspaper",
    "wof:placetype":"venue"
},
  "geometry": {"coordinates":[-122.239728,37.800497],"type":"Point"}
}