{
  "type": "Feature",
  "properties": {
    "addr:full":"70 Hobson St San Jose CA 95110",
    "addr:housenumber":"70",
    "addr:postcode":"95110",
    "addr:street":"Hobson St",
    "iso:country":"US",
    "sg:address":"70 Hobson St",
    "sg:city":"San Jose",
    "sg:classifiers":[
        {
            "category":"Real Estate",
            "subcategory":"Real Estate Agent",
            "type":"Services"
        }
    ],
    "sg:phone":"+1 408 292 9491",
    "sg:postcode":"95110",
    "sg:province":"CA",
    "wof:name":"Childress Appraisal",
    "wof:placetype":"venue"
},
  "geometry": {"coordinates":[-121.89972299999999,37.346049],"type":"Point"}
}