{
  "type": "Feature",
  "properties": {
    "iso:country":"US",
    "sg:address":"501 New Stine Rd",
    "sg:city":"Bakersfield",
    "sg:classifiers":[
        {
            "category":"Professional",
            "subcategory":"Business Services",
            "type":"Services"
        }
    ],
    "sg:phone":"+1 661 834 1761",
    "sg:postcode":"93309",
    "sg:province":"CA",
    "sg:tags":[
        "drafting"
    ],
    "wof:name":"Mike Geissel Drafting",
    "wof:placetype":"venue"
},
  "geometry": {"coordinates":[-119.061221,35.349792],"type":"Point"}
}