{
  "type": "Feature",
  "properties": {
    "addr:full":"1200 Maple St Madera CA 93637",
    "addr:housenumber":"1200",
    "addr:postcode":"93637",
    "addr:street":"Maple St",
    "iso:country":"US",
    "sg:address":"1200 Maple St",
    "sg:city":"Madera",
    "sg:classifiers":[
        {
            "category":"Social Services",
            "subcategory":"Child Care",
            "type":"Services"
        }
    ],
    "sg:phone":"+1 800 505 0404",
    "sg:postcode":"93637",
    "sg:province":"CA",
    "wof:name":"Madera County Action Committee Resource and Referral",
    "wof:placetype":"venue"
},
  "geometry": {"coordinates":[-120.072166,36.950069],"type":"Point"}
}