{
  "type": "Feature",
  "properties": {
    "iso:country":"US",
    "sg:address":"14337 Garfield Ave",
    "sg:city":"Paramount",
    "sg:classifiers":[
        {
            "category":"Food & Beverages",
            "subcategory":"Bakery",
            "type":"Retail Goods"
        }
    ],
    "sg:phone":"+1 562 633 7775",
    "sg:postcode":"90723",
    "sg:province":"CA",
    "sg:tags":[
        "baker"
    ],
    "wof:name":"J & J Distributing",
    "wof:placetype":"venue"
},
  "geometry": {"coordinates":[-118.16882699999999,33.902657],"type":"Point"}
}