{
  "type": "Feature",
  "properties": {
    "addr:full":"1729 Stewart St Oceanside CA 92054",
    "addr:housenumber":"1729",
    "addr:postcode":"92054",
    "addr:street":"Stewart St",
    "iso:country":"US",
    "sg:address":"1729 Stewart St",
    "sg:city":"Oceanside",
    "sg:classifiers":[
        {
            "category":"Freight",
            "type":"Transportation"
        }
    ],
    "sg:phone":"+1 760 439 8153",
    "sg:postcode":"92054",
    "sg:province":"CA",
    "sg:tags":[
        "courier"
    ],
    "wof:name":"Rancho Courier Svc",
    "wof:placetype":"venue"
},
  "geometry": {"coordinates":[-117.35736300000001,33.179997],"type":"Point"}
}