{
  "type": "Feature",
  "properties": {
    "iso:country":"US",
    "sg:address":"115 Town and Country",
    "sg:city":"Sunnyvale",
    "sg:classifiers":[
        {
            "category":"Shopping",
            "subcategory":"Florist",
            "type":"Retail Goods"
        }
    ],
    "sg:phone":"+1 408 732 2876",
    "sg:postcode":"94086",
    "sg:province":"CA",
    "wof:name":"A-Song's Flowers & Gifts",
    "wof:placetype":"venue"
},
  "geometry": {"coordinates":[-122.031452,37.37651],"type":"Point"}
}