{
  "type": "Feature",
  "properties": {
    "iso:country":"US",
    "sg:address":"39 Parker Suite 100",
    "sg:city":"Irvine",
    "sg:classifiers":[
        {
            "category":"Manufacturing",
            "subcategory":"Electronics",
            "type":"Manufacturing & Wholesale Goods"
        }
    ],
    "sg:phone":"+1 714 805 9283",
    "sg:postcode":"92618",
    "sg:province":"CA",
    "sg:website":"http://www.greenwavereality.com/",
    "wof:name":"GreenWave Reality",
    "wof:placetype":"venue"
},
  "geometry": {"coordinates":[-117.704672,33.656874],"type":"Point"}
}