{
  "type": "Feature",
  "properties": {
    "addr:full":"1515 Cherokee Ln Lodi CA 95240",
    "addr:housenumber":"1515",
    "addr:postcode":"95240",
    "addr:street":"Cherokee Ln",
    "iso:country":"US",
    "sg:address":"1515 Cherokee Ln",
    "sg:city":"Lodi",
    "sg:classifiers":[
        {
            "category":"Retail",
            "subcategory":"Repair Shop",
            "type":"Services"
        }
    ],
    "sg:phone":"+1 209 368 2808",
    "sg:postcode":"95240",
    "sg:province":"CA",
    "sg:tags":[
        "welding"
    ],
    "wof:name":"Aluminum Welding & Fabrication",
    "wof:placetype":"venue"
},
  "geometry": {"coordinates":[-121.26024099999999,38.112553],"type":"Point"}
}