{
  "type": "Feature",
  "properties": {
    "addr:full":"829 Rosemarie Ln Stockton CA 95207",
    "addr:housenumber":"829",
    "addr:postcode":"95207",
    "addr:street":"Rosemarie Ln",
    "iso:country":"US",
    "sg:address":"829 Rosemarie Ln",
    "sg:city":"Stockton",
    "sg:classifiers":[
        {
            "category":"Social Services",
            "type":"Services"
        }
    ],
    "sg:phone":"+1 209 474 8794",
    "sg:postcode":"95207",
    "sg:province":"CA",
    "sg:tags":[
        "organization",
        "welfare"
    ],
    "wof:name":"Victim Offender Reconciliation",
    "wof:placetype":"venue"
},
  "geometry": {"coordinates":[-121.313748,37.988407],"type":"Point"}
}