{
  "type": "Feature",
  "properties": {
    "addr:full":"14419 Rios Canyon Rd El Cajon CA 92021",
    "addr:housenumber":"14419",
    "addr:postcode":"92021",
    "addr:street":"Rios Canyon Rd",
    "iso:country":"US",
    "sg:address":"14419 Rios Canyon Rd",
    "sg:city":"El Cajon",
    "sg:classifiers":[
        {
            "category":"Professional",
            "type":"Services"
        },
        {
            "category":"Building & Trades",
            "subcategory":"Equipment Rental",
            "type":"Services"
        }
    ],
    "sg:phone":"+1 619 443 9034",
    "sg:postcode":"92021",
    "sg:province":"CA",
    "sg:tags":[
        "contractor"
    ],
    "wof:name":"Laxson Equipment Inc",
    "wof:placetype":"venue"
},
  "geometry": {"coordinates":[-116.873096,32.836743],"type":"Point"}
}