{
  "type": "Feature",
  "properties": {
    "iso:country":"US",
    "sg:address":"8484 Florin Rd Ste 20",
    "sg:city":"Sacramento",
    "sg:classifiers":[
        {
            "category":"Food & Beverages",
            "subcategory":"Liquor & Beverages",
            "type":"Retail Goods"
        },
        {
            "category":"Food & Beverages",
            "subcategory":"Groceries & Convenience Stores",
            "type":"Retail Goods"
        }
    ],
    "sg:phone":"+1 916 387 0448",
    "sg:postcode":"95828",
    "sg:province":"CA",
    "wof:name":"G K Discount Liquor",
    "wof:placetype":"venue"
},
  "geometry": {"coordinates":[-121.391468,38.496094],"type":"Point"}
}