{
  "type": "Feature",
  "properties": {
    "iso:country":"US",
    "sg:address":"4231 Crows Landing Rd",
    "sg:city":"Modesto",
    "sg:classifiers":[
        {
            "category":"Wholesale",
            "subcategory":"Auto Parts",
            "type":"Manufacturing & Wholesale Goods"
        }
    ],
    "sg:phone":"+1 209 531 2900",
    "sg:postcode":"95358",
    "sg:province":"CA",
    "sg:tags":[
        "automobile"
    ],
    "wof:name":"67 72 Chevy Trucks & Parts",
    "wof:placetype":"venue"
},
  "geometry": {"coordinates":[-120.993741,37.577317],"type":"Point"}
}