{
  "type": "Feature",
  "properties": {
    "addr:full":"6051 Mack Rd Ste D Sacramento CA 95823",
    "addr:housenumber":"6051",
    "addr:postcode":"95823",
    "addr:street":"Mack Rd Ste D",
    "iso:country":"US",
    "sg:address":"6051 Mack Rd Ste D",
    "sg:city":"Sacramento",
    "sg:classifiers":[
        {
            "category":"Bakery",
            "type":"Food & Drink"
        }
    ],
    "sg:phone":"+1 916 399 1833",
    "sg:postcode":"95823",
    "sg:province":"CA",
    "sg:tags":[
        "cake",
        "pastry",
        "wedding"
    ],
    "wof:name":"Valerio's Tropical Bake Shop",
    "wof:placetype":"venue"
},
  "geometry": {"coordinates":[-121.42932500000001,38.474307],"type":"Point"}
}