{
  "type": "Feature",
  "properties": {
    "addr:full":"4001 W Alameda Ave Burbank CA 91505",
    "addr:housenumber":"4001",
    "addr:postcode":"91505",
    "addr:street":"W Alameda Ave",
    "iso:country":"US",
    "sg:address":"4001 W Alameda Ave",
    "sg:city":"Burbank",
    "sg:classifiers":[
        {
            "category":"Communications",
            "subcategory":"Film & Video Production",
            "type":"Services"
        }
    ],
    "sg:phone":"+1 818 842 6966",
    "sg:postcode":"91505",
    "sg:province":"CA",
    "sg:tags":[
        "motion",
        "picture",
        "studio",
        "producer"
    ],
    "wof:name":"Marathon Pictures LLC",
    "wof:placetype":"venue"
},
  "geometry": {"coordinates":[-118.34401800000001,34.152985],"type":"Point"}
}