{
  "type": "Feature",
  "properties": {
    "addr:full":"145 W Main Ave Morgan Hill CA 95037",
    "addr:housenumber":"145",
    "addr:postcode":"95037",
    "addr:street":"W Main Ave",
    "iso:country":"US",
    "sg:address":"145 W Main Ave",
    "sg:city":"Morgan Hill",
    "sg:classifiers":[
        {
            "category":"Banks & Credit Unions",
            "subcategory":"Bank",
            "type":"Services"
        }
    ],
    "sg:phone":"+1 408 782 1230",
    "sg:postcode":"95037",
    "sg:province":"CA",
    "sg:tags":[
        "financing"
    ],
    "wof:name":"Carson Capitol Funding Group",
    "wof:placetype":"venue"
},
  "geometry": {"coordinates":[-121.657538,37.128772],"type":"Point"}
}