{
  "type": "Feature",
  "properties": {
    "addr:full":"2295 Streblow Dr Napa CA 94558",
    "addr:housenumber":"2295",
    "addr:postcode":"94558",
    "addr:street":"Streblow Dr",
    "iso:country":"US",
    "sg:address":"2295 Streblow Dr",
    "sg:city":"Napa",
    "sg:classifiers":[
        {
            "category":"Sports & Exercise",
            "subcategory":"Golf",
            "type":"Entertainment"
        }
    ],
    "sg:phone":"+1 707 255 4333",
    "sg:postcode":"94558",
    "sg:province":"CA",
    "sg:tags":[
        "course"
    ],
    "wof:name":"Napa Golf Course",
    "wof:placetype":"venue"
},
  "geometry": {"coordinates":[-122.280164,38.269101],"type":"Point"}
}