{
  "type": "Feature",
  "properties": {
    "iso:country":"US",
    "sg:address":"34 28th Ave",
    "sg:city":"San Mateo",
    "sg:classifiers":[
        {
            "category":"Shopping",
            "subcategory":"Catalog Store",
            "type":"Retail Goods"
        }
    ],
    "sg:phone":"+1 650 574 2225",
    "sg:postcode":"94403",
    "sg:province":"CA",
    "sg:tags":[
        "mail",
        "order"
    ],
    "wof:name":"Winns",
    "wof:placetype":"venue"
},
  "geometry": {"coordinates":[-122.305229,37.540766],"type":"Point"}
}