{
  "type": "Feature",
  "properties": {
    "addr:full":"921 E Compton Blvd Compton CA 90221",
    "addr:housenumber":"921",
    "addr:postcode":"90221",
    "addr:street":"E Compton Blvd",
    "iso:country":"US",
    "sg:address":"921 E Compton Blvd",
    "sg:city":"Compton",
    "sg:classifiers":[
        {
            "category":"Government",
            "subcategory":"Office",
            "type":"Public Place"
        }
    ],
    "sg:phone":"+1 310 668 6800",
    "sg:postcode":"90221",
    "sg:province":"CA",
    "wof:name":"Los Angeles County Mental Hlth",
    "wof:placetype":"venue"
},
  "geometry": {"coordinates":[-118.212828,33.8961],"type":"Point"}
}