{
  "type": "Feature",
  "properties": {
    "addr:full":"641 Indian Hill Blvd Pomona CA 91767",
    "addr:housenumber":"641",
    "addr:postcode":"91767",
    "addr:street":"Indian Hill Blvd",
    "iso:country":"US",
    "sg:address":"641 Indian Hill Blvd",
    "sg:city":"Pomona",
    "sg:classifiers":[
        {
            "category":"Utilities",
            "subcategory":"Mobile Phone",
            "type":"Services"
        },
        {
            "category":"Shopping",
            "subcategory":"Mobile Phones",
            "type":"Retail Goods"
        },
        {
            "category":"Communications",
            "type":"Services"
        },
        {
            "category":"Internet Cafe",
            "subcategory":"None",
            "type":"Food & Drink"
        }
    ],
    "sg:phone":"+1 909 620 6249",
    "sg:postcode":"91767",
    "sg:province":"CA",
    "sg:tags":[
        "supply",
        "telephone",
        "wireless",
        "equipment",
        "paging",
        "signaling",
        "cellular",
        "provider"
    ],
    "sg:website":"http://www.att.com",
    "wof:name":"AT&T",
    "wof:placetype":"venue"
},
  "geometry": {"coordinates":[-117.7192,34.064637],"type":"Point"}
}