{
  "type": "Feature",
  "properties": {
    "addr:full":"12401 Folsom Blvd Rancho Cordova CA 95742",
    "addr:housenumber":"12401",
    "addr:postcode":"95742",
    "addr:street":"Folsom Blvd",
    "iso:country":"US",
    "sg:address":"12401 Folsom Blvd",
    "sg:city":"Rancho Cordova",
    "sg:classifiers":[
        {
            "category":"Manufacturing",
            "subcategory":"Printing",
            "type":"Manufacturing & Wholesale Goods"
        }
    ],
    "sg:phone":"+1 916 357 5950",
    "sg:postcode":"95742",
    "sg:province":"CA",
    "sg:tags":[
        "publishing"
    ],
    "wof:name":"Publication Printer Corp",
    "wof:placetype":"venue"
},
  "geometry": {"coordinates":[-121.22405999999999,38.62694],"type":"Point"}
}