{
  "type": "Feature",
  "properties": {
    "iso:country":"US",
    "sg:address":"760 Bryant St",
    "sg:city":"San Francisco",
    "sg:classifiers":[
        {
            "category":"Wholesale",
            "subcategory":"Non-durable Goods",
            "type":"Manufacturing & Wholesale Goods"
        }
    ],
    "sg:phone":"+1 415 348 1656",
    "sg:postcode":"94107",
    "sg:province":"CA",
    "wof:name":"US Pacific Imports",
    "wof:placetype":"venue"
},
  "geometry": {"coordinates":[-122.401893,37.776661],"type":"Point"}
}