{
  "type": "Feature",
  "properties": {
    "iso:country":"US",
    "sg:address":"7875 Tamarind Ave",
    "sg:city":"Fontana",
    "sg:classifiers":[
        {
            "category":"Organizations",
            "subcategory":"Religious Organization",
            "type":"Services"
        }
    ],
    "sg:phone":"+1 909 854 6899",
    "sg:postcode":"92336",
    "sg:province":"CA",
    "sg:tags":[
        "church"
    ],
    "wof:name":"Victorious Baptist Fellowship",
    "wof:placetype":"venue"
},
  "geometry": {"coordinates":[-117.42270499999999,34.111229],"type":"Point"}
}