{
  "type": "Feature",
  "properties": {
    "addr:full":"751 Black Rd Santa Maria CA 93458",
    "addr:housenumber":"751",
    "addr:postcode":"93458",
    "addr:street":"Black Rd",
    "iso:country":"US",
    "sg:address":"751 Black Rd",
    "sg:city":"Santa Maria",
    "sg:classifiers":[
        {
            "category":"Organizations",
            "subcategory":"Membership Organization",
            "type":"Services"
        }
    ],
    "sg:phone":"+1 805 349 3435",
    "sg:postcode":"93458",
    "sg:province":"CA",
    "sg:tags":[
        "society",
        "humane"
    ],
    "wof:name":"Santa Maria Valley Humane Scty",
    "wof:placetype":"venue"
},
  "geometry": {"coordinates":[-120.48976,34.947906],"type":"Point"}
}