{
  "type": "Feature",
  "properties": {
    "iso:country":"US",
    "sg:address":"776 Via del Sol",
    "sg:city":"Livermore",
    "sg:classifiers":[
        {
            "category":"Professional",
            "subcategory":"Computer Services",
            "type":"Services"
        }
    ],
    "sg:phone":"+1 925 443 2870",
    "sg:postcode":"94550",
    "sg:province":"CA",
    "sg:tags":[
        "home",
        "consulting",
        "page",
        "dev",
        "internet"
    ],
    "wof:name":"White Rose Web Design",
    "wof:placetype":"venue"
},
  "geometry": {"coordinates":[-121.787885,37.661325],"type":"Point"}
}