{
  "type": "Feature",
  "properties": {
    "addr:full":"9952 Golden West Ln Santee CA 92071",
    "addr:housenumber":"9952",
    "addr:postcode":"92071",
    "addr:street":"Golden West Ln",
    "iso:country":"US",
    "sg:address":"9952 Golden West Ln",
    "sg:city":"Santee",
    "sg:classifiers":[
        {
            "category":"Building & Trades",
            "subcategory":"Construction",
            "type":"Services"
        }
    ],
    "sg:phone":"+1 619 562 4912",
    "sg:postcode":"92071",
    "sg:province":"CA",
    "sg:tags":[
        "coping",
        "plastering",
        "tiling",
        "pool",
        "swimming"
    ],
    "wof:name":"Central Pool Svc",
    "wof:placetype":"venue"
},
  "geometry": {"coordinates":[-116.980924,32.861336],"type":"Point"}
}