{
  "type": "Feature",
  "properties": {
    "iso:country":"US",
    "sg:address":"564 S Dora St",
    "sg:city":"Ukiah",
    "sg:classifiers":[
        {
            "category":"Health Services",
            "subcategory":"Health Practitioner",
            "type":"Services"
        }
    ],
    "sg:phone":"+1 707 467 0335",
    "sg:postcode":"95482",
    "sg:province":"CA",
    "sg:tags":[
        "acupuncture"
    ],
    "wof:name":"Daowave Clinic",
    "wof:placetype":"venue"
},
  "geometry": {"coordinates":[-123.21165000000001,39.145745],"type":"Point"}
}