{
  "type": "Feature",
  "properties": {
    "addr:full":"720 University Ave Palo Alto CA 94301",
    "addr:housenumber":"720",
    "addr:postcode":"94301",
    "addr:street":"University Ave",
    "iso:country":"US",
    "sg:address":"720 University Ave",
    "sg:city":"Palo Alto",
    "sg:classifiers":[
        {
            "category":"Professional",
            "type":"Services"
        }
    ],
    "sg:phone":"+1 650 324 3479",
    "sg:postcode":"94301",
    "sg:province":"CA",
    "sg:tags":[
        "establishment"
    ],
    "wof:name":"KTB-Venture Capital",
    "wof:placetype":"venue"
},
  "geometry": {"coordinates":[-122.15638199999999,37.450982],"type":"Point"}
}