{
  "type": "Feature",
  "properties": {
    "iso:country":"US",
    "sg:address":"500 N Anaheim Blvd",
    "sg:city":"Anaheim",
    "sg:classifiers":[
        {
            "category":"Wholesale",
            "subcategory":"Auto Parts",
            "type":"Manufacturing & Wholesale Goods"
        }
    ],
    "sg:phone":"+1 714 774 1161",
    "sg:postcode":"92805",
    "sg:province":"CA",
    "wof:name":"Hals-Hal N Hibbard Repr Rads",
    "wof:placetype":"venue"
},
  "geometry": {"coordinates":[-117.915631,33.840788],"type":"Point"}
}