{
  "type": "Feature",
  "properties": {
    "iso:country":"US",
    "sg:address":"17385 Trinity Dr",
    "sg:city":"Hesperia",
    "sg:classifiers":[
        {
            "category":"Building & Trades",
            "subcategory":"Electrical",
            "type":"Services"
        }
    ],
    "sg:phone":"+1 760 662 1909",
    "sg:postcode":"92345",
    "sg:province":"CA",
    "sg:tags":[
        "electrician"
    ],
    "wof:name":"De Leon Electric",
    "wof:placetype":"venue"
},
  "geometry": {"coordinates":[-117.28461900000001,34.464425],"type":"Point"}
}