{
  "type": "Feature",
  "properties": {
    "iso:country":"US",
    "sg:address":"28793 Mark Rd",
    "sg:city":"Moreno Valley",
    "sg:classifiers":[
        {
            "category":"Education",
            "subcategory":"Special Training",
            "type":"Public Place"
        }
    ],
    "sg:phone":"+1 951 786 7890",
    "sg:postcode":"92555",
    "sg:province":"CA",
    "sg:tags":[
        "tutoring"
    ],
    "wof:name":"Southern California Reading",
    "wof:placetype":"venue"
},
  "geometry": {"coordinates":[-117.163133,33.957888],"type":"Point"}
}