{
  "type": "Feature",
  "properties": {
    "addr:full":"2436 Evergreen St Sacramento CA 95815",
    "addr:housenumber":"2436",
    "addr:postcode":"95815",
    "addr:street":"Evergreen St",
    "iso:country":"US",
    "sg:address":"2436 Evergreen St",
    "sg:city":"Sacramento",
    "sg:classifiers":[
        {
            "category":"Retail",
            "subcategory":"Car Wash",
            "type":"Services"
        }
    ],
    "sg:phone":"+1 916 400 4163",
    "sg:postcode":"95815",
    "sg:province":"CA",
    "wof:name":"Lon'c Auto Detailing",
    "wof:placetype":"venue"
},
  "geometry": {"coordinates":[-121.44386799999999,38.609982],"type":"Point"}
}