{
  "type": "Feature",
  "properties": {
    "iso:country":"US",
    "sg:address":"2300 Central Ave",
    "sg:city":"Duarte",
    "sg:classifiers":[
        {
            "category":"Building & Trades",
            "subcategory":"Cleaning & Sanitation",
            "type":"Services"
        }
    ],
    "sg:phone":"+1 626 359 5062",
    "sg:postcode":"91010",
    "sg:province":"CA",
    "sg:tags":[
        "janitor"
    ],
    "wof:name":"TDH Gold Cleaning",
    "wof:placetype":"venue"
},
  "geometry": {"coordinates":[-117.95564,34.136094],"type":"Point"}
}