{
  "type": "Feature",
  "properties": {
    "iso:country":"US",
    "sg:address":"7100 N Financial Dr",
    "sg:city":"Fresno",
    "sg:classifiers":[
        {
            "category":"Insurance",
            "subcategory":"Insurance Agent",
            "type":"Services"
        }
    ],
    "sg:phone":"+1 559 448 9020",
    "sg:postcode":"93720",
    "sg:province":"CA",
    "sg:website":"www.farmersinsurance.com",
    "wof:name":"Farmers Insurance Group",
    "wof:placetype":"venue"
},
  "geometry": {"coordinates":[-119.771506,36.840571],"type":"Point"}
}