{
  "type": "Feature",
  "properties": {
    "iso:country":"US",
    "sg:address":"200 Harbor Dr",
    "sg:city":"Sausalito",
    "sg:classifiers":[
        {
            "category":"Shopping",
            "subcategory":"Bicycles & Sporting Goods",
            "type":"Retail Goods"
        }
    ],
    "sg:phone":"+1 415 331 0904",
    "sg:postcode":"94965",
    "sg:province":"CA",
    "sg:tags":[
        "equipment",
        "diver",
        "supply"
    ],
    "sg:website":"http://www.harbordive.com",
    "wof:name":"Harbor Dive & Kayak Center",
    "wof:placetype":"venue"
},
  "geometry": {"coordinates":[-122.499427,37.867909],"type":"Point"}
}