{
  "type": "Feature",
  "properties": {
    "addr:full":"9514 Winter Gardens Blvd Lakeside CA 92040",
    "addr:housenumber":"9514",
    "addr:postcode":"92040",
    "addr:street":"Winter Gardens Blvd",
    "iso:country":"US",
    "sg:address":"9514 Winter Gardens Blvd",
    "sg:city":"Lakeside",
    "sg:classifiers":[
        {
            "category":"Manufacturing",
            "subcategory":"Tools & Machinery",
            "type":"Manufacturing & Wholesale Goods"
        }
    ],
    "sg:phone":"+1 619 443 0880",
    "sg:postcode":"92040",
    "sg:province":"CA",
    "sg:tags":[
        "industrial",
        "mfg"
    ],
    "wof:name":"Fullarton Industries",
    "wof:placetype":"venue"
},
  "geometry": {"coordinates":[-116.93115,32.850162],"type":"Point"}
}