{
  "type": "Feature",
  "properties": {
    "addr:full":"924 Westwood Blvd Ste 620 Los Angeles CA 90024",
    "addr:housenumber":"924",
    "addr:postcode":"90024",
    "addr:street":"Westwood Blvd Ste 620",
    "iso:country":"US",
    "sg:address":"924 Westwood Blvd Ste 620",
    "sg:city":"Los Angeles",
    "sg:classifiers":[
        {
            "category":"Health Services",
            "subcategory":"Doctor",
            "type":"Services"
        }
    ],
    "sg:phone":"+1 310 824 1126",
    "sg:postcode":"90024",
    "sg:province":"CA",
    "wof:name":"Young Susan R MD",
    "wof:placetype":"venue"
},
  "geometry": {"coordinates":[-118.44499999999999,34.0634],"type":"Point"}
}