{
  "type": "Feature",
  "properties": {
    "addr:full":"275 N McDowell Blvd Petaluma CA 94954",
    "addr:housenumber":"275",
    "addr:postcode":"94954",
    "addr:street":"N Mcdowell Blvd",
    "iso:country":"US",
    "sg:address":"275 N McDowell Blvd",
    "sg:city":"Petaluma",
    "sg:classifiers":[
        {
            "category":"Shopping",
            "subcategory":"Music",
            "type":"Retail Goods"
        }
    ],
    "sg:phone":"+1 707 775 2410",
    "sg:postcode":"94954",
    "sg:province":"CA",
    "sg:tags":[
        "compact",
        "record",
        "disc",
        "tape"
    ],
    "wof:name":"Video Tepa Musica",
    "wof:placetype":"venue"
},
  "geometry": {"coordinates":[-122.629886,38.25145],"type":"Point"}
}