{
  "type": "Feature",
  "properties": {
    "iso:country":"US",
    "sg:address":"1020 W Ball Rd",
    "sg:city":"Anaheim",
    "sg:classifiers":[
        {
            "category":"Wholesale",
            "subcategory":"Toys & Hobbies",
            "type":"Manufacturing & Wholesale Goods"
        }
    ],
    "sg:phone":"+1 714 781 4565",
    "sg:postcode":"92802",
    "sg:province":"CA",
    "sg:tags":[
        "supply"
    ],
    "wof:name":"Disneyland",
    "wof:placetype":"venue"
},
  "geometry": {"coordinates":[-117.918666,33.817997],"type":"Point"}
}