{
  "type": "Feature",
  "properties": {
    "addr:full":"1030 Saratoga Ave San Jose CA 95129",
    "addr:housenumber":"1030",
    "addr:postcode":"95129",
    "addr:street":"Saratoga Ave",
    "iso:country":"US",
    "sg:address":"1030 Saratoga Ave",
    "sg:city":"San Jose",
    "sg:classifiers":[
        {
            "category":"Retail",
            "subcategory":"Auto Repair",
            "type":"Services"
        }
    ],
    "sg:phone":"+1 408 260 7894",
    "sg:postcode":"95129",
    "sg:province":"CA",
    "sg:tags":[
        "automotive",
        "automobile",
        "lubrication"
    ],
    "sg:website":"www.jiffylube.com",
    "wof:name":"Jiffy Lube",
    "wof:placetype":"venue"
},
  "geometry": {"coordinates":[-121.97767899999999,37.307712],"type":"Point"}
}