{
  "type": "Feature",
  "properties": {
    "iso:country":"US",
    "sg:address":"10812 el Paso Ave",
    "sg:city":"Fountain Valley",
    "sg:classifiers":[
        {
            "category":"Professional",
            "subcategory":"Business Services",
            "type":"Services"
        }
    ],
    "sg:phone":"+1 714 968 7754",
    "sg:postcode":"92708",
    "sg:province":"CA",
    "sg:tags":[
        "house",
        "construction"
    ],
    "wof:name":"Papillon An Interior Design Co",
    "wof:placetype":"venue"
},
  "geometry": {"coordinates":[-117.93962000000001,33.712369],"type":"Point"}
}