{
  "type": "Feature",
  "properties": {
    "iso:country":"US",
    "sg:address":"370 N Robertson Blvd",
    "sg:city":"West Hollywood",
    "sg:classifiers":[
        {
            "category":"Shopping",
            "type":"Retail Goods"
        }
    ],
    "sg:phone":"+1 310 854 0001",
    "sg:postcode":"90048",
    "sg:province":"CA",
    "wof:name":"Between the Sheets",
    "wof:placetype":"venue"
},
  "geometry": {"coordinates":[-118.383802,34.078498],"type":"Point"}
}