{
  "type": "Feature",
  "properties": {
    "addr:full":"5314 Arlington Ave Los Angeles CA 90043",
    "addr:housenumber":"5314",
    "addr:postcode":"90043",
    "addr:street":"Arlington Ave",
    "iso:country":"US",
    "sg:address":"5314 Arlington Ave",
    "sg:city":"Los Angeles",
    "sg:classifiers":[
        {
            "category":"Building & Trades",
            "subcategory":"Cleaning & Sanitation",
            "type":"Services"
        }
    ],
    "sg:phone":"+1 323 291 0171",
    "sg:postcode":"90043",
    "sg:province":"CA",
    "sg:tags":[
        "house"
    ],
    "wof:name":"Perrys Cleaning Svc",
    "wof:placetype":"venue"
},
  "geometry": {"coordinates":[-118.318085,33.994933],"type":"Point"}
}