{
  "type": "Feature",
  "properties": {
    "addr:full":"1201 E Buoy Ave Orange CA 92865",
    "addr:housenumber":"1201",
    "addr:postcode":"92865",
    "addr:street":"E Buoy Ave",
    "iso:country":"US",
    "sg:address":"1201 E Buoy Ave",
    "sg:city":"Orange",
    "sg:classifiers":[
        {
            "category":"Building & Trades",
            "subcategory":"Plumbing",
            "type":"Services"
        }
    ],
    "sg:phone":"+1 714 685 0460",
    "sg:postcode":"92865",
    "sg:province":"CA",
    "sg:website":"www.kcsplumbing.com",
    "wof:name":"KC's 23 1-2 Hour Plumbing",
    "wof:placetype":"venue"
},
  "geometry": {"coordinates":[-117.84164199999999,33.833447],"type":"Point"}
}