{
  "type": "Feature",
  "properties": {
    "addr:full":"1101 Princeton Ave Bakersfield CA 93305",
    "addr:housenumber":"1101",
    "addr:postcode":"93305",
    "addr:street":"Princeton Ave",
    "iso:country":"US",
    "sg:address":"1101 Princeton Ave",
    "sg:city":"Bakersfield",
    "sg:classifiers":[
        {
            "category":"Professional",
            "subcategory":"Engineering",
            "type":"Services"
        }
    ],
    "sg:phone":"+1 661 716 7443",
    "sg:postcode":"93305",
    "sg:province":"CA",
    "sg:tags":[
        "civil",
        "contractor",
        "engineer"
    ],
    "wof:name":"Afinar, Inc.",
    "wof:placetype":"venue"
},
  "geometry": {"coordinates":[-118.98232299999999,35.40781],"type":"Point"}
}