{
  "type": "Feature",
  "properties": {
    "addr:full":"1419 Colton St Los Angeles CA 90026",
    "addr:housenumber":"1419",
    "addr:postcode":"90026",
    "addr:street":"Colton St",
    "iso:country":"US",
    "sg:address":"1419 Colton St",
    "sg:city":"Los Angeles",
    "sg:classifiers":[
        {
            "category":"Sports & Exercise",
            "subcategory":"Swimming Pool",
            "type":"Entertainment"
        }
    ],
    "sg:phone":"+1 213 481 2640",
    "sg:postcode":"90026",
    "sg:province":"CA",
    "sg:website":"www.laparks.org/dos/aquatic/faci...",
    "wof:name":"Echo Park Deep Pool",
    "wof:placetype":"venue"
},
  "geometry": {"coordinates":[-118.25939700000001,34.064137],"type":"Point"}
}