{
  "type": "Feature",
  "properties": {
    "iso:country":"US",
    "sg:address":"11426 Calvert St",
    "sg:city":"North Hollywood",
    "sg:classifiers":[
        {
            "category":"Social Services",
            "type":"Services"
        }
    ],
    "sg:phone":"+1 818 763 9157",
    "sg:postcode":"91606",
    "sg:province":"CA",
    "sg:tags":[
        "housing",
        "assistance"
    ],
    "wof:name":"Glass No 6",
    "wof:placetype":"venue"
},
  "geometry": {"coordinates":[-118.38040700000001,34.181166],"type":"Point"}
}