{
  "type": "Feature",
  "properties": {
    "addr:full":"1223 N Davis Rd Salinas CA 93907",
    "addr:housenumber":"1223",
    "addr:postcode":"93907",
    "addr:street":"N Davis Rd",
    "iso:country":"US",
    "sg:address":"1223 N Davis Rd",
    "sg:city":"Salinas",
    "sg:classifiers":[
        {
            "category":"Food & Beverages",
            "subcategory":"Groceries & Convenience Stores",
            "type":"Retail Goods"
        }
    ],
    "sg:phone":"+1 831 753 7300",
    "sg:postcode":"93907",
    "sg:province":"CA",
    "sg:tags":[
        "grocer"
    ],
    "sg:website":"www.albertsons.com",
    "wof:name":"Albertsons",
    "wof:placetype":"venue"
},
  "geometry": {"coordinates":[-121.666929,36.702102],"type":"Point"}
}