{
  "type": "Feature",
  "properties": {
    "addr:full":"165 Blossom Hill Rd San Jose CA 95123",
    "addr:housenumber":"165",
    "addr:postcode":"95123",
    "addr:street":"Blossom Hill Rd",
    "iso:country":"US",
    "sg:address":"165 Blossom Hill Rd",
    "sg:city":"San Jose",
    "sg:classifiers":[
        {
            "category":"Building & Trades",
            "subcategory":"Landscaping Services",
            "type":"Services"
        }
    ],
    "sg:phone":"+1 408 281 7227",
    "sg:postcode":"95123",
    "sg:province":"CA",
    "wof:name":"Ledeit Landscape Maintenance",
    "wof:placetype":"venue"
},
  "geometry": {"coordinates":[-121.807958,37.251834],"type":"Point"}
}