{
  "type": "Feature",
  "properties": {
    "addr:full":"573 Ashton Ave Palo Alto CA 94306",
    "addr:housenumber":"573",
    "addr:postcode":"94306",
    "addr:street":"Ashton Ave",
    "iso:country":"US",
    "sg:address":"573 Ashton Ave",
    "sg:city":"Palo Alto",
    "sg:classifiers":[
        {
            "category":"Professional",
            "type":"Services"
        }
    ],
    "sg:phone":"+1 650 424 0416",
    "sg:postcode":"94306",
    "sg:province":"CA",
    "wof:name":"Volpe Foundation Inc",
    "wof:placetype":"venue"
},
  "geometry": {"coordinates":[-122.120172,37.424591],"type":"Point"}
}