{
  "type": "Feature",
  "properties": {
    "addr:full":"14403 Hatteras St Van Nuys CA 91401",
    "addr:housenumber":"14403",
    "addr:postcode":"91401",
    "addr:street":"Hatteras St",
    "iso:country":"US",
    "sg:address":"14403 Hatteras St",
    "sg:city":"Van Nuys",
    "sg:classifiers":[
        {
            "category":"Building & Trades",
            "subcategory":"Pest Control",
            "type":"Services"
        }
    ],
    "sg:phone":"+1 818 782 0485",
    "sg:postcode":"91401",
    "sg:province":"CA",
    "sg:website":"www.citadelpestelimination.com",
    "wof:name":"Citadel Pest Elimination Inc",
    "wof:placetype":"venue"
},
  "geometry": {"coordinates":[-118.44699900000001,34.175598],"type":"Point"}
}