{
  "type": "Feature",
  "properties": {
    "addr:full":"367 Nevada St Auburn CA 95603",
    "addr:housenumber":"367",
    "addr:postcode":"ca 95603",
    "addr:street":"Nevada St",
    "iso:country":"US",
    "sg:address":"367 Nevada St",
    "sg:city":"Auburn",
    "sg:classifiers":[
        {
            "category":"Personal",
            "subcategory":"Beauty Salon",
            "type":"Services"
        }
    ],
    "sg:phone":"+1 530 885 9887",
    "sg:postcode":"95603",
    "sg:province":"CA",
    "wof:name":"Jill Ricci Hair Stylist",
    "wof:placetype":"venue"
},
  "geometry": {"coordinates":[-121.081029,38.911011],"type":"Point"}
}