{
  "type": "Feature",
  "properties": {
    "iso:country":"US",
    "sg:address":"24222 Sylvan Glen Rd",
    "sg:city":"Diamond Bar",
    "sg:classifiers":[
        {
            "category":"Home & Garden",
            "subcategory":"Building Materials",
            "type":"Retail Goods"
        }
    ],
    "sg:phone":"+1 909 869 6113",
    "sg:postcode":"91765",
    "sg:province":"CA",
    "sg:tags":[
        "mixed",
        "concrete"
    ],
    "wof:name":"Superior Short Load",
    "wof:placetype":"venue"
},
  "geometry": {"coordinates":[-117.79479,34.029429],"type":"Point"}
}