{
  "type": "Feature",
  "properties": {
    "addr:full":"5030 Hollister Ave Santa Barbara CA 93111",
    "addr:housenumber":"5030",
    "addr:postcode":"93111",
    "addr:street":"Hollister Ave",
    "iso:country":"US",
    "sg:address":"5030 Hollister Ave",
    "sg:city":"Santa Barbara",
    "sg:classifiers":[
        {
            "category":"Manufacturing",
            "subcategory":"Lumber",
            "type":"Manufacturing & Wholesale Goods"
        }
    ],
    "sg:phone":"+1 805 967 1039",
    "sg:postcode":"93111",
    "sg:province":"CA",
    "sg:tags":[
        "product",
        "forest",
        "gathering"
    ],
    "wof:name":"McCloskey Nursery",
    "wof:placetype":"venue"
},
  "geometry": {"coordinates":[-119.798062,34.435043],"type":"Point"}
}