{
  "type": "Feature",
  "properties": {
    "addr:full":"11408 Pomering Rd Downey CA 90241",
    "addr:housenumber":"11408",
    "addr:postcode":"90241",
    "addr:street":"Pomering Rd",
    "iso:country":"US",
    "sg:address":"11408 Pomering Rd",
    "sg:city":"Downey",
    "sg:classifiers":[
        {
            "category":"Building & Trades",
            "subcategory":"Construction",
            "type":"Services"
        }
    ],
    "sg:phone":"+1 562 928 2382",
    "sg:postcode":"90241",
    "sg:province":"CA",
    "sg:tags":[
        "contractor"
    ],
    "wof:name":"Murguias Construction",
    "wof:placetype":"venue"
},
  "geometry": {"coordinates":[-118.147373,33.945319],"type":"Point"}
}