{
  "type": "Feature",
  "properties": {
    "addr:full":"601 del Norte Blvd Oxnard CA 93030",
    "addr:housenumber":"601",
    "addr:postcode":"93030",
    "addr:street":"Del Norte Blvd",
    "iso:country":"US",
    "sg:address":"601 del Norte Blvd",
    "sg:city":"Oxnard",
    "sg:classifiers":[
        {
            "category":"Real Estate",
            "subcategory":"Real Estate Services",
            "type":"Services"
        }
    ],
    "sg:phone":"+1 805 485 7309",
    "sg:postcode":"93030",
    "sg:province":"CA",
    "sg:tags":[
        "inspection"
    ],
    "wof:name":"Villafana Engineering & Construction",
    "wof:placetype":"venue"
},
  "geometry": {"coordinates":[-119.127195,34.206908],"type":"Point"}
}