{
  "type": "Feature",
  "properties": {
    "addr:full":"244 W Harding Way Stockton CA 95204",
    "addr:housenumber":"244",
    "addr:postcode":"95204",
    "addr:street":"W Harding Way",
    "iso:country":"US",
    "sg:address":"244 W Harding Way",
    "sg:city":"Stockton",
    "sg:classifiers":[
        {
            "category":"Food & Beverages",
            "subcategory":"Groceries & Convenience Stores",
            "type":"Retail Goods"
        }
    ],
    "sg:phone":"+1 209 948 8001",
    "sg:postcode":"95204",
    "sg:province":"CA",
    "wof:name":"Fast & Easy",
    "wof:placetype":"venue"
},
  "geometry": {"coordinates":[-121.298592,37.966637],"type":"Point"}
}