{
  "type": "Feature",
  "properties": {
    "iso:country":"US",
    "sg:address":"667 Plumas St",
    "sg:city":"Yuba City",
    "sg:classifiers":[
        {
            "category":"Shopping",
            "subcategory":"Used Merchandise",
            "type":"Retail Goods"
        }
    ],
    "sg:phone":"+1 530 790 6884",
    "sg:postcode":"95991",
    "sg:province":"CA",
    "wof:name":"Sterling Antiques & Decor",
    "wof:placetype":"venue"
},
  "geometry": {"coordinates":[-121.616163,39.137425],"type":"Point"}
}