{
  "type": "Feature",
  "properties": {
    "iso:country":"US",
    "sg:address":"4508 Wawona Street",
    "sg:city":"Los Angeles",
    "sg:classifiers":[
        {
            "category":"Health Services",
            "subcategory":"Doctor",
            "type":"Services"
        }
    ],
    "sg:phone":"+1 323 254 8797",
    "sg:postcode":"90065",
    "sg:province":"CA",
    "wof:name":"Jimenez Lina E MD",
    "wof:placetype":"venue"
},
  "geometry": {"coordinates":[-118.225924,34.133465],"type":"Point"}
}