{
  "type": "Feature",
  "properties": {
    "iso:country":"US",
    "sg:address":"1170 Cll Joaquin",
    "sg:city":"San Luis Obispo",
    "sg:classifiers":[
        {
            "category":"Government",
            "subcategory":"Office",
            "type":"Public Place"
        }
    ],
    "sg:phone":"+1 805 543 6222",
    "sg:postcode":"93405",
    "sg:province":"CA",
    "sg:tags":[
        "federal",
        "affairs"
    ],
    "wof:name":"US Border Patrol",
    "wof:placetype":"venue"
},
  "geometry": {"coordinates":[-120.678868,35.250627],"type":"Point"}
}