{
  "type": "Feature",
  "properties": {
    "addr:full":"476 Pardee Ave Susanville CA 96130",
    "addr:housenumber":"476",
    "addr:postcode":"96130",
    "addr:street":"Pardee Ave",
    "iso:country":"US",
    "sg:address":"476 Pardee Ave",
    "sg:city":"Susanville",
    "sg:classifiers":[
        {
            "category":"Freight",
            "type":"Transportation"
        }
    ],
    "sg:phone":"+1 530 257 8614",
    "sg:postcode":"96130",
    "sg:province":"CA",
    "sg:tags":[
        "operator",
        "local",
        "trucking"
    ],
    "wof:name":"Mick Rose Trucking",
    "wof:placetype":"venue"
},
  "geometry": {"coordinates":[-120.656795,40.410099],"type":"Point"}
}