{
  "type": "Feature",
  "properties": {
    "iso:country":"US",
    "sg:address":"801 I St Rm 229",
    "sg:city":"Sacramento",
    "sg:classifiers":[
        {
            "category":"Government",
            "subcategory":"Office",
            "type":"Public Place"
        }
    ],
    "sg:phone":"+1 916 498 5332",
    "sg:postcode":"95814",
    "sg:province":"CA",
    "sg:tags":[
        "security",
        "homeland"
    ],
    "wof:name":"Office Cmplaint Investigations",
    "wof:placetype":"venue"
},
  "geometry": {"coordinates":[-121.495667,38.582111],"type":"Point"}
}