{
  "type": "Feature",
  "properties": {
    "addr:full":"28953 Miller Rd Valley Center CA 92082",
    "addr:housenumber":"28953",
    "addr:postcode":"92082",
    "addr:street":"Miller Rd",
    "iso:country":"US",
    "sg:address":"28953 Miller Rd",
    "sg:city":"Valley Center",
    "sg:classifiers":[
        {
            "category":"Real Estate",
            "subcategory":"Developer",
            "type":"Services"
        }
    ],
    "sg:phone":"+1 760 749 1186",
    "sg:postcode":"92082",
    "sg:province":"CA",
    "sg:tags":[
        "cemetery"
    ],
    "wof:name":"Valley Center Cemetery Dist",
    "wof:placetype":"venue"
},
  "geometry": {"coordinates":[-117.032811,33.238164],"type":"Point"}
}