{
  "type": "Feature",
  "properties": {
    "addr:full":"2700 W el Camino Real Mountain View CA 94040",
    "addr:housenumber":"2700",
    "addr:postcode":"94040",
    "addr:street":"W El Camino Real",
    "iso:country":"US",
    "sg:address":"2700 W el Camino Real",
    "sg:city":"Mountain View",
    "sg:classifiers":[
        {
            "category":"Travel",
            "subcategory":"Hotels & Motels",
            "type":"Entertainment"
        }
    ],
    "sg:phone":"+1 650 559 9115",
    "sg:postcode":"94040",
    "sg:province":"CA",
    "wof:name":"Holiday Inn Express Mtn View",
    "wof:placetype":"venue"
},
  "geometry": {"coordinates":[-122.113592,37.401255],"type":"Point"}
}