{
  "type": "Feature",
  "properties": {
    "addr:full":"6515 Garfield Ave Bell Gardens CA 90201",
    "addr:housenumber":"6515",
    "addr:postcode":"90201",
    "addr:street":"Garfield Ave",
    "iso:country":"US",
    "sg:address":"6515 Garfield Ave",
    "sg:city":"Bell Gardens",
    "sg:classifiers":[
        {
            "category":"Wholesale",
            "subcategory":"Durable Goods & Equipment",
            "type":"Manufacturing & Wholesale Goods"
        }
    ],
    "sg:phone":"+1 562 927 2636",
    "sg:postcode":"90201",
    "sg:province":"CA",
    "sg:tags":[
        "representative",
        "manufacturer"
    ],
    "wof:name":"Stark Sales",
    "wof:placetype":"venue"
},
  "geometry": {"coordinates":[-118.148427,33.971117],"type":"Point"}
}