{
  "type": "Feature",
  "properties": {
    "addr:full":"2993 College Ave Berkeley CA 94705",
    "addr:housenumber":"2993",
    "addr:postcode":"94705",
    "addr:street":"College Ave",
    "iso:country":"US",
    "sg:address":"2993 College Ave",
    "sg:city":"Berkeley",
    "sg:classifiers":[
        {
            "category":"Restaurant",
            "type":"Food & Drink"
        }
    ],
    "sg:phone":"+1 510 704 1474",
    "sg:postcode":"94705",
    "sg:province":"CA",
    "sg:tags":[
        "style",
        "family",
        "italian"
    ],
    "sg:website":"www.trattorialasiciliana.com",
    "wof:name":"Trattoria La Siciliana",
    "wof:placetype":"venue"
},
  "geometry": {"coordinates":[-122.252944,37.856187],"type":"Point"}
}