{
  "type": "Feature",
  "properties": {
    "addr:full":"4700 Escobedo Dr Woodland Hills CA 91364",
    "addr:postcode":"4700;91364",
    "addr:street":"Escobedo Dr",
    "iso:country":"US",
    "sg:address":"4700 Escobedo Dr",
    "sg:city":"Woodland Hills",
    "sg:classifiers":[
        {
            "category":"Building & Trades",
            "subcategory":"Locksmith",
            "type":"Services"
        }
    ],
    "sg:phone":"+1 818 961 5800",
    "sg:postcode":"91364",
    "sg:province":"CA",
    "sg:tags":[
        "key"
    ],
    "wof:name":"A-1 Elite Solutions Inc",
    "wof:placetype":"venue"
},
  "geometry": {"coordinates":[-118.589946,34.156085],"type":"Point"}
}