{
  "type": "Feature",
  "properties": {
    "addr:full":"19118 Pioneer Blvd Cerritos CA 90703",
    "addr:housenumber":"19118",
    "addr:postcode":"ca 90703",
    "addr:street":"Pioneer Blvd",
    "iso:country":"US",
    "sg:address":"19118 Pioneer Blvd",
    "sg:city":"Cerritos",
    "sg:classifiers":[
        {
            "category":"Manufacturing",
            "subcategory":"Tools & Machinery",
            "type":"Manufacturing & Wholesale Goods"
        }
    ],
    "sg:phone":"+1 562 809 9191",
    "sg:postcode":"90703",
    "sg:province":"CA",
    "sg:tags":[
        "equipment",
        "fixture",
        "lighting"
    ],
    "wof:name":"Universal Lighting Supply Co",
    "wof:placetype":"venue"
},
  "geometry": {"coordinates":[-118.08200100000001,33.8573],"type":"Point"}
}