{
  "type": "Feature",
  "properties": {
    "addr:full":"Ayres Hotel And Suites 325 Bristol St Costa Mesa CA 92626",
    "addr:housenumber":"325",
    "addr:postcode":"92626",
    "addr:street":"Bristol St",
    "iso:country":"US",
    "sg:address":"Ayres Hotel And Suites 325 Bristol St",
    "sg:city":"Costa Mesa",
    "sg:classifiers":[
        {
            "category":"Restaurant",
            "type":"Food & Drink"
        }
    ],
    "sg:phone":"+1 714 549 0300",
    "sg:postcode":"92626",
    "sg:province":"CA",
    "sg:tags":[
        "new",
        "american"
    ],
    "sg:website":"www.ayreshotels.com",
    "wof:name":"Le Chateau Garden Bistro",
    "wof:placetype":"venue"
},
  "geometry": {"coordinates":[-117.881901,33.665486],"type":"Point"}
}