{
  "type": "Feature",
  "properties": {
    "iso:country":"US",
    "sg:address":"519 Nebraska Ave",
    "sg:city":"Modesto",
    "sg:classifiers":[
        {
            "category":"Farming",
            "subcategory":"Crops",
            "type":"Manufacturing & Wholesale Goods"
        }
    ],
    "sg:phone":"+1 209 523 2089",
    "sg:postcode":"95358",
    "sg:province":"CA",
    "sg:tags":[
        "grove",
        "nut",
        "tree"
    ],
    "wof:name":"Bill D Robbins",
    "wof:placetype":"venue"
},
  "geometry": {"coordinates":[-121.049109,37.637584],"type":"Point"}
}