{
  "type": "Feature",
  "properties": {
    "addr:full":"7655 Convoy Ct San Diego CA 92111",
    "addr:housenumber":"7655",
    "addr:postcode":"92111",
    "addr:street":"Convoy Ct",
    "iso:country":"US",
    "sg:address":"7655 Convoy Ct",
    "sg:city":"San Diego",
    "sg:classifiers":[
        {
            "category":"Professional",
            "type":"Services"
        }
    ],
    "sg:phone":"+1 858 974 6500",
    "sg:postcode":"92111",
    "sg:province":"CA",
    "wof:name":"Pacific Rim Mechanical",
    "wof:placetype":"venue"
},
  "geometry": {"coordinates":[-117.154736,32.834731],"type":"Point"}
}