{
  "type": "Feature",
  "properties": {
    "addr:full":"6355 Pine Cone Ct Foresthill CA 95631",
    "addr:housenumber":"6355",
    "addr:postcode":"95631",
    "addr:street":"Pine Cone Ct",
    "iso:country":"US",
    "sg:address":"6355 Pine Cone Ct",
    "sg:city":"Foresthill",
    "sg:classifiers":[
        {
            "category":"Shopping",
            "subcategory":"Beauty & Cosmetics",
            "type":"Retail Goods"
        },
        {
            "category":"Personal",
            "subcategory":"Beauty Salon",
            "type":"Services"
        }
    ],
    "sg:phone":"+1 530 320 2674",
    "sg:postcode":"95631",
    "sg:province":"CA",
    "sg:tags":[
        "perfume",
        "salons-equipment",
        "supply"
    ],
    "wof:name":"Mary Kay Cosmetics",
    "wof:placetype":"venue"
},
  "geometry": {"coordinates":[-120.879062,38.981674],"type":"Point"}
}