{
  "type": "Feature",
  "properties": {
    "addr:full":"5259 W Los Altos Ave Fresno CA 93722",
    "addr:housenumber":"5259",
    "addr:postcode":"93722",
    "addr:street":"W Los Altos Ave",
    "iso:country":"US",
    "sg:address":"5259 W Los Altos Ave",
    "sg:city":"Fresno",
    "sg:classifiers":[
        {
            "category":"Building & Trades",
            "subcategory":"Landscaping Services",
            "type":"Services"
        }
    ],
    "sg:phone":"+1 559 274 9142",
    "sg:postcode":"93722",
    "sg:province":"CA",
    "sg:tags":[
        "landscape",
        "contractor"
    ],
    "wof:name":"Western Lawn Care",
    "wof:placetype":"venue"
},
  "geometry": {"coordinates":[-119.88503900000001,36.83263],"type":"Point"}
}