{
  "type": "Feature",
  "properties": {
    "addr:full":"1725 Las Vegas St Modesto CA 95358",
    "addr:housenumber":"1725",
    "addr:postcode":"ca 95358",
    "addr:street":"Las Vegas St",
    "iso:country":"US",
    "sg:address":"1725 Las Vegas St",
    "sg:city":"Modesto",
    "sg:classifiers":[
        {
            "category":"Education",
            "subcategory":"School",
            "type":"Public Place"
        }
    ],
    "sg:phone":"+1 209 576 4719",
    "sg:postcode":"95358",
    "sg:province":"CA",
    "sg:tags":[
        "high",
        "middle",
        "elementary",
        "k-",
        "private"
    ],
    "sg:website":"http://www.monet.k12.ca.us",
    "wof:name":"Hanshaw Middle School",
    "wof:placetype":"venue"
},
  "geometry": {"coordinates":[-121.00299800000001,37.6045],"type":"Point"}
}