{
  "type": "Feature",
  "properties": {
    "addr:full":"10335 S Vermont Ave Los Angeles CA 90044",
    "addr:housenumber":"10335",
    "addr:postcode":"90044",
    "addr:street":"S Vermont Ave",
    "iso:country":"US",
    "sg:address":"10335 S Vermont Ave",
    "sg:city":"Los Angeles",
    "sg:classifiers":[
        {
            "category":"Retail",
            "subcategory":"Funeral Services",
            "type":"Services"
        }
    ],
    "sg:phone":"+1 323 757 7717",
    "sg:postcode":"90044",
    "sg:province":"CA",
    "sg:tags":[
        "information"
    ],
    "wof:name":"Trinity Management LLC",
    "wof:placetype":"venue"
},
  "geometry": {"coordinates":[-118.291903,33.942621],"type":"Point"}
}