{
  "type": "Feature",
  "properties": {
    "iso:country":"US",
    "sg:address":"4635 Driftwood Cir",
    "sg:city":"Carlsbad",
    "sg:classifiers":[
        {
            "category":"Home & Garden",
            "subcategory":"Carpets & Floor Coverings",
            "type":"Retail Goods"
        }
    ],
    "sg:phone":"+1 760 612 2533",
    "sg:postcode":"92008",
    "sg:province":"CA",
    "sg:tags":[
        "dealer",
        "rug"
    ],
    "wof:name":"Dan's Carpets",
    "wof:placetype":"venue"
},
  "geometry": {"coordinates":[-117.314689,33.154353],"type":"Point"}
}