{
  "type": "Feature",
  "properties": {
    "addr:full":"1438 N Steven Ave Reedley CA 93654",
    "addr:housenumber":"1438",
    "addr:postcode":"93654",
    "addr:street":"N Steven Ave",
    "iso:country":"US",
    "sg:address":"1438 N Steven Ave",
    "sg:city":"Reedley",
    "sg:classifiers":[
        {
            "category":"Building & Trades",
            "subcategory":"Landscaping Services",
            "type":"Services"
        }
    ],
    "sg:phone":"+1 866 427 9031",
    "sg:postcode":"93654",
    "sg:province":"CA",
    "sg:tags":[
        "lawn",
        "tree",
        "contractor",
        "arborist",
        "landscape"
    ],
    "wof:name":"Tree Care Concepts",
    "wof:placetype":"venue"
},
  "geometry": {"coordinates":[-119.440747,36.608793],"type":"Point"}
}