{
  "type": "Feature",
  "properties": {
    "addr:full":"3924 E Anaheim St Long Beach CA 90804",
    "addr:housenumber":"3924",
    "addr:postcode":"90804",
    "addr:street":"E Anaheim St",
    "iso:country":"US",
    "sg:address":"3924 E Anaheim St",
    "sg:city":"Long Beach",
    "sg:classifiers":[
        {
            "category":"Personal",
            "subcategory":"Tanning Parlor",
            "type":"Services"
        }
    ],
    "sg:phone":"+1 562 494 7151",
    "sg:postcode":"90804",
    "sg:province":"CA",
    "sg:tags":[
        "salon"
    ],
    "sg:website":"www.clubtans.com/",
    "wof:name":"Club Tan Tanning Salon",
    "wof:placetype":"venue"
},
  "geometry": {"coordinates":[-118.146434,33.782453],"type":"Point"}
}