{
  "type": "Feature",
  "properties": {
    "addr:full":"6928 Owensmouth Ave Fl 2 Canoga Park CA 91303",
    "addr:housenumber":"6928;2",
    "addr:postcode":"91303",
    "addr:street":"Owensmouth Ave Fl",
    "iso:country":"US",
    "sg:address":"6928 Owensmouth Ave Fl 2",
    "sg:city":"Canoga Park",
    "sg:classifiers":[
        {
            "category":"Professional",
            "subcategory":"Lawyer & Legal Services",
            "type":"Services"
        }
    ],
    "sg:phone":"+1 818 883 4224",
    "sg:postcode":"91303",
    "sg:province":"CA",
    "wof:name":"Tropio & Morlan",
    "wof:placetype":"venue"
},
  "geometry": {"coordinates":[-118.601997,34.196098],"type":"Point"}
}