{
  "type": "Feature",
  "properties": {
    "addr:full":"16375 Monterey St Morgan Hill CA 95037",
    "addr:housenumber":"16375",
    "addr:postcode":"95037",
    "addr:street":"Monterey St",
    "iso:country":"US",
    "sg:address":"16375 Monterey St",
    "sg:city":"Morgan Hill",
    "sg:classifiers":[
        {
            "category":"Personal",
            "subcategory":"Beauty Salon",
            "type":"Services"
        }
    ],
    "sg:phone":"+1 408 776 6737",
    "sg:postcode":"95037",
    "sg:province":"CA",
    "sg:tags":[
        "manicuring"
    ],
    "wof:name":"Natural Nails By Lisa",
    "wof:placetype":"venue"
},
  "geometry": {"coordinates":[-121.646096,37.118138],"type":"Point"}
}