{
  "type": "Feature",
  "properties": {
    "addr:full":"3435 Cesar Chavez San Francisco CA 94110",
    "addr:housenumber":"3435",
    "addr:postcode":"94110",
    "addr:street":"Cesar Chavez",
    "iso:country":"US",
    "sg:address":"3435 Cesar Chavez",
    "sg:city":"San Francisco",
    "sg:classifiers":[
        {
            "category":"Manufacturing",
            "subcategory":"Apparel",
            "type":"Manufacturing & Wholesale Goods"
        }
    ],
    "sg:phone":"+1 415 641 7439",
    "sg:postcode":"94110",
    "sg:province":"CA",
    "sg:tags":[
        "mfg",
        "coat",
        "woman",
        "miss",
        "suit"
    ],
    "wof:name":"G M Shepatin",
    "wof:placetype":"venue"
},
  "geometry": {"coordinates":[-122.418319,37.748264],"type":"Point"}
}