{
  "type": "Feature",
  "properties": {
    "addr:full":"2605 E 18th St National City CA 91950",
    "addr:housenumber":"2605",
    "addr:postcode":"91950",
    "addr:street":"E 18Th St",
    "iso:country":"US",
    "sg:address":"2605 E 18th St",
    "sg:city":"National City",
    "sg:classifiers":[
        {
            "category":"Food & Beverages",
            "subcategory":"Liquor & Beverages",
            "type":"Retail Goods"
        }
    ],
    "sg:phone":"+1 619 470 1272",
    "sg:postcode":"91950",
    "sg:province":"CA",
    "wof:name":"George's Liquor Store",
    "wof:placetype":"venue"
},
  "geometry": {"coordinates":[-117.075992,32.675],"type":"Point"}
}