{
  "type": "Feature",
  "properties": {
    "addr:full":"677 Miramonte Dr Santa Barbara CA 93109",
    "addr:housenumber":"677",
    "addr:postcode":"93109",
    "addr:street":"Miramonte Dr",
    "iso:country":"US",
    "sg:address":"677 Miramonte Dr",
    "sg:city":"Santa Barbara",
    "sg:classifiers":[
        {
            "category":"Professional",
            "type":"Services"
        }
    ],
    "sg:phone":"+1 805 965 1985",
    "sg:postcode":"93109",
    "sg:province":"CA",
    "wof:name":"Fred M Benko",
    "wof:placetype":"venue"
},
  "geometry": {"coordinates":[-119.70665200000001,34.408055],"type":"Point"}
}