{
  "type": "Feature",
  "properties": {
    "addr:full":"509 N Eureka St Redlands CA 92374",
    "addr:housenumber":"509",
    "addr:postcode":"92374",
    "addr:street":"N Eureka St",
    "iso:country":"US",
    "sg:address":"509 N Eureka St",
    "sg:city":"Redlands",
    "sg:classifiers":[
        {
            "category":"Restaurant",
            "type":"Food & Drink"
        }
    ],
    "sg:phone":"+1 909 792 5436",
    "sg:postcode":"92374",
    "sg:province":"CA",
    "sg:tags":[
        "caterer"
    ],
    "sg:website":"www.michelles-bakery.com",
    "wof:name":"Michelle's",
    "wof:placetype":"venue"
},
  "geometry": {"coordinates":[-117.18651199999999,34.061222],"type":"Point"}
}