{
  "type": "Feature",
  "properties": {
    "addr:full":"334 E Ojai Ave Ste B Ojai CA 93023",
    "addr:housenumber":"334",
    "addr:postcode":"93023",
    "addr:street":"E Ojai Ave Ste B",
    "iso:country":"US",
    "sg:address":"334 E Ojai Ave Ste B",
    "sg:city":"Ojai",
    "sg:classifiers":[
        {
            "category":"Shopping",
            "subcategory":"Clothing, Apparel, & Fashions",
            "type":"Retail Goods"
        },
        {
            "category":"Shopping",
            "type":"Retail Goods"
        }
    ],
    "sg:phone":"+1 805 646 0677",
    "sg:postcode":"93023",
    "sg:province":"CA",
    "sg:tags":[
        "apparel",
        "item",
        "boutique",
        "accessory",
        "women's"
    ],
    "wof:name":"Studio Sauvageau",
    "wof:placetype":"venue"
},
  "geometry": {"coordinates":[-119.243875,34.447915],"type":"Point"}
}