{
  "type": "Feature",
  "properties": {
    "iso:country":"US",
    "sg:address":"3500 5th Ave",
    "sg:city":"San Diego",
    "sg:classifiers":[
        {
            "category":"Organizations",
            "subcategory":"Non-profit Organization",
            "type":"Services"
        }
    ],
    "sg:phone":"+1 619 574 6643",
    "sg:postcode":"92103",
    "sg:province":"CA",
    "wof:name":"Pro Peninsula",
    "wof:placetype":"venue"
},
  "geometry": {"coordinates":[-117.16037799999999,32.742117],"type":"Point"}
}