{
  "type": "Feature",
  "properties": {
    "iso:country":"US",
    "sg:address":"2116 S Central Ave",
    "sg:city":"Los Angeles",
    "sg:classifiers":[
        {
            "category":"Personal",
            "subcategory":"Barber",
            "type":"Services"
        }
    ],
    "sg:phone":"+1 213 749 9793",
    "sg:postcode":"90011",
    "sg:province":"CA",
    "wof:name":"Economy Barber Shop",
    "wof:placetype":"venue"
},
  "geometry": {"coordinates":[-118.253073,34.021574],"type":"Point"}
}