{
  "type": "Feature",
  "properties": {
    "iso:country":"US",
    "sg:address":"566 S San Vicente Boulevard",
    "sg:city":"Los Angeles",
    "sg:classifiers":[
        {
            "category":"Health Services",
            "subcategory":"Doctor",
            "type":"Services"
        }
    ],
    "sg:phone":"+1 323 651 4520",
    "sg:postcode":"90048",
    "sg:province":"CA",
    "wof:name":"Berkowitz Steven PHD",
    "wof:placetype":"venue"
},
  "geometry": {"coordinates":[-118.373574,34.066914],"type":"Point"}
}