{
  "type": "Feature",
  "properties": {
    "addr:full":"1209 Chestnut St Burbank CA 91506",
    "addr:housenumber":"1209",
    "addr:postcode":"91506",
    "addr:street":"Chestnut St",
    "iso:country":"US",
    "sg:address":"1209 Chestnut St",
    "sg:city":"Burbank",
    "sg:classifiers":[
        {
            "category":"Wholesale",
            "subcategory":"Machinery & Supplies",
            "type":"Manufacturing & Wholesale Goods"
        }
    ],
    "sg:phone":"+1 323 849 5170",
    "sg:postcode":"91506",
    "sg:province":"CA",
    "sg:tags":[
        "abrasive"
    ],
    "sg:website":"www.matzrubber.com",
    "wof:name":"Matz Rubber Co Inc",
    "wof:placetype":"venue"
},
  "geometry": {"coordinates":[-118.32186299999999,34.181797],"type":"Point"}
}