{
  "type": "Feature",
  "properties": {
    "iso:country":"US",
    "sg:address":"1218 Boulevard Way",
    "sg:city":"Walnut Creek",
    "sg:classifiers":[
        {
            "category":"Restaurant",
            "type":"Food & Drink"
        }
    ],
    "sg:phone":"+1 925 939 2426",
    "sg:postcode":"94595",
    "sg:province":"CA",
    "sg:tags":[
        "delicatessen"
    ],
    "wof:name":"Morucci's Si Mangia Bene",
    "wof:placetype":"venue"
},
  "geometry": {"coordinates":[-122.074961,37.894285],"type":"Point"}
}