{
  "type": "Feature",
  "properties": {
    "addr:full":"1307 E Compton Blvd Compton CA 90221",
    "addr:housenumber":"1307",
    "addr:postcode":"90221",
    "addr:street":"E Compton Blvd",
    "iso:country":"US",
    "sg:address":"1307 E Compton Blvd",
    "sg:city":"Compton",
    "sg:classifiers":[
        {
            "category":"Recreation",
            "type":"Entertainment"
        }
    ],
    "sg:phone":"+1 310 763 0747",
    "sg:postcode":"90221",
    "sg:province":"CA",
    "sg:tags":[
        "club",
        "membership"
    ],
    "wof:name":"Yard Sale Club",
    "wof:placetype":"venue"
},
  "geometry": {"coordinates":[-118.20857700000001,33.89611],"type":"Point"}
}