{
  "type": "Feature",
  "properties": {
    "addr:full":"2615 Centennial Cir Corona CA 92882",
    "addr:housenumber":"2615",
    "addr:postcode":"92882",
    "addr:street":"Centennial Cir",
    "iso:country":"US",
    "sg:address":"2615 Centennial Cir",
    "sg:city":"Corona",
    "sg:classifiers":[
        {
            "category":"Manufacturing",
            "subcategory":"Printing",
            "type":"Manufacturing & Wholesale Goods"
        }
    ],
    "sg:phone":"+1 951 549 0350",
    "sg:postcode":"92882",
    "sg:province":"CA",
    "sg:tags":[
        "commercial"
    ],
    "wof:name":"California Screen Printing",
    "wof:placetype":"venue"
},
  "geometry": {"coordinates":[-117.601687,33.852842],"type":"Point"}
}