{
  "type": "Feature",
  "properties": {
    "iso:country":"US",
    "sg:address":"5880 Commerce Blvd",
    "sg:city":"Rohnert Park",
    "sg:classifiers":[
        {
            "category":"Professional",
            "subcategory":"Credit Reporting & Collection",
            "type":"Services"
        }
    ],
    "sg:phone":"+1 707 584 4225",
    "sg:postcode":"94928",
    "sg:province":"CA",
    "sg:tags":[
        "agency"
    ],
    "wof:name":"Transworld Systems Inc",
    "wof:placetype":"venue"
},
  "geometry": {"coordinates":[-122.712444,38.356063],"type":"Point"}
}