{
  "type": "Feature",
  "properties": {
    "iso:country":"US",
    "sg:address":"1535 Seabright Ave",
    "sg:city":"Santa Cruz",
    "sg:classifiers":[
        {
            "category":"Personal",
            "type":"Services"
        }
    ],
    "sg:phone":"+1 831 459 6750",
    "sg:postcode":"95062",
    "sg:province":"CA",
    "sg:tags":[
        "trainer",
        "program",
        "fitness",
        "exercise",
        "physical"
    ],
    "sg:website":"www.pacificmovementcenter.com",
    "wof:name":"Pacific Movement Center",
    "wof:placetype":"venue"
},
  "geometry": {"coordinates":[-122.010002,36.978001],"type":"Point"}
}