{
  "type": "Feature",
  "properties": {
    "addr:full":"8946 W Pico Blvd Los Angeles CA 90035",
    "addr:housenumber":"8946",
    "addr:postcode":"90035",
    "addr:street":"W Pico Blvd",
    "iso:country":"US",
    "sg:address":"8946 W Pico Blvd",
    "sg:city":"Los Angeles",
    "sg:classifiers":[
        {
            "category":"Ice Cream",
            "type":"Food & Drink"
        }
    ],
    "sg:phone":"+1 310 550 8668",
    "sg:postcode":"90035",
    "sg:province":"CA",
    "sg:tags":[
        "frozen",
        "yogurt"
    ],
    "sg:website":"www.SweetTOOT.com",
    "wof:name":"SweetTOOT",
    "wof:placetype":"venue"
},
  "geometry": {"coordinates":[-118.38714299999999,34.055051],"type":"Point"}
}