{
  "type": "Feature",
  "properties": {
    "iso:country":"US",
    "sg:address":"434 Main St",
    "sg:city":"Watsonville",
    "sg:classifiers":[
        {
            "category":"Professional",
            "subcategory":"Accounting & Tax Preparation",
            "type":"Services"
        }
    ],
    "sg:phone":"+1 831 761 5997",
    "sg:postcode":"95076",
    "sg:province":"CA",
    "sg:tags":[
        "return",
        "filing"
    ],
    "wof:name":"H & R Block Tax Svc",
    "wof:placetype":"venue"
},
  "geometry": {"coordinates":[-121.757862,36.911169],"type":"Point"}
}