{
  "type": "Feature",
  "properties": {
    "addr:full":"2501 Moorehead Rd Crescent City CA 95531",
    "addr:housenumber":"2501",
    "addr:postcode":"95531",
    "addr:street":"Moorehead Rd Crescent",
    "iso:country":"US",
    "sg:address":"2501 Moorehead Rd",
    "sg:city":"Crescent City",
    "sg:classifiers":[
        {
            "category":"Personal",
            "subcategory":"Beauty Salon",
            "type":"Services"
        }
    ],
    "sg:phone":"+1 707 487 7045",
    "sg:postcode":"95531",
    "sg:province":"CA",
    "wof:name":"Bonnie's Beauty Salon",
    "wof:placetype":"venue"
},
  "geometry": {"coordinates":[-124.15645499999999,41.865751],"type":"Point"}
}