{
  "type": "Feature",
  "properties": {
    "addr:full":"219 E Maude Ave Sunnyvale CA 94085",
    "addr:housenumber":"219",
    "addr:postcode":"94085",
    "addr:street":"E Maude Ave",
    "iso:country":"US",
    "sg:address":"219 E Maude Ave",
    "sg:city":"Sunnyvale",
    "sg:classifiers":[
        {
            "category":"Shopping",
            "subcategory":"Music",
            "type":"Retail Goods"
        }
    ],
    "sg:phone":"+1 408 738 6999",
    "sg:postcode":"94085",
    "sg:province":"CA",
    "sg:tags":[
        "video",
        "disc",
        "tape",
        "cassette"
    ],
    "wof:name":"Video Mexico",
    "wof:placetype":"venue"
},
  "geometry": {"coordinates":[-122.022622,37.387217],"type":"Point"}
}