{
  "type": "Feature",
  "properties": {
    "iso:country":"US",
    "sg:address":"1136 Saranap Ave",
    "sg:city":"Walnut Creek",
    "sg:classifiers":[
        {
            "category":"Building & Trades",
            "subcategory":"Construction",
            "type":"Services"
        }
    ],
    "sg:phone":"+1 925 934 0666",
    "sg:postcode":"94595",
    "sg:province":"CA",
    "sg:tags":[
        "resurfacing",
        "laying",
        "refinishing",
        "floor"
    ],
    "wof:name":"Premium Hardwood Floor",
    "wof:placetype":"venue"
},
  "geometry": {"coordinates":[-122.07773299999999,37.895576],"type":"Point"}
}