{
  "type": "Feature",
  "properties": {
    "addr:full":"14419 Hamlin St Van Nuys CA 91401",
    "addr:housenumber":"14419",
    "addr:postcode":"91401",
    "addr:street":"Hamlin St",
    "iso:country":"US",
    "sg:address":"14419 Hamlin St",
    "sg:city":"Van Nuys",
    "sg:classifiers":[
        {
            "category":"Health Services",
            "subcategory":"Doctor",
            "type":"Services"
        }
    ],
    "sg:phone":"+1 818 902 0630",
    "sg:postcode":"91401",
    "sg:province":"CA",
    "sg:tags":[
        "surgeon",
        "oral"
    ],
    "wof:name":"Tom Elbert DDS",
    "wof:placetype":"venue"
},
  "geometry": {"coordinates":[-118.44699900000001,34.188599],"type":"Point"}
}