{
  "type": "Feature",
  "properties": {
    "iso:country":"US",
    "sg:address":"39045 Mount Vernon Ave",
    "sg:city":"Fremont",
    "sg:classifiers":[
        {
            "category":"Building & Trades",
            "subcategory":"Construction",
            "type":"Services"
        }
    ],
    "sg:phone":"+1 510 793 8844",
    "sg:postcode":"94538",
    "sg:province":"CA",
    "sg:tags":[
        "equipment",
        "installation"
    ],
    "wof:name":"D & M Transfer",
    "wof:placetype":"venue"
},
  "geometry": {"coordinates":[-121.985061,37.550926],"type":"Point"}
}