{
  "type": "Feature",
  "properties": {
    "iso:country":"US",
    "sg:address":"223 Loretta Way",
    "sg:city":"Calimesa",
    "sg:classifiers":[
        {
            "category":"Utilities",
            "subcategory":"Refuse",
            "type":"Services"
        }
    ],
    "sg:phone":"+1 909 795 5639",
    "sg:postcode":"92320",
    "sg:province":"CA",
    "sg:tags":[
        "recycling",
        "organic"
    ],
    "wof:name":"CST Organic Recycling",
    "wof:placetype":"venue"
},
  "geometry": {"coordinates":[-117.033876,34.000819],"type":"Point"}
}