{
  "type": "Feature",
  "properties": {
    "iso:country":"US",
    "sg:address":"1550 Palisades Beach Rd",
    "sg:city":"Santa Monica",
    "sg:classifiers":[
        {
            "category":"Professional",
            "type":"Services"
        }
    ],
    "sg:phone":"+1 310 576 1946",
    "sg:postcode":"90401",
    "sg:province":"CA",
    "wof:name":"Cavalia LLC",
    "wof:placetype":"venue"
},
  "geometry": {"coordinates":[-118.49589,34.010945],"type":"Point"}
}