{
  "type": "Feature",
  "properties": {
    "addr:full":"11652 Mc Bean Dr El Monte CA 91732",
    "addr:housenumber":"11652",
    "addr:postcode":"91732",
    "addr:street":"Mc Bean Dr",
    "iso:country":"US",
    "sg:address":"11652 Mc Bean Dr",
    "sg:city":"El Monte",
    "sg:classifiers":[
        {
            "category":"Manufacturing",
            "subcategory":"Tools & Machinery",
            "type":"Manufacturing & Wholesale Goods"
        }
    ],
    "sg:phone":"+1 626 279 2855",
    "sg:postcode":"91732",
    "sg:province":"CA",
    "sg:tags":[
        "machine",
        "shop"
    ],
    "wof:name":"JRD Screw Machines",
    "wof:placetype":"venue"
},
  "geometry": {"coordinates":[-118.006942,34.099631],"type":"Point"}
}