{
  "type": "Feature",
  "properties": {
    "iso:country":"US",
    "sg:address":"24309 Narbonne Ave",
    "sg:city":"Lomita",
    "sg:classifiers":[
        {
            "category":"Utilities",
            "subcategory":"Telephone",
            "type":"Services"
        }
    ],
    "sg:phone":"+1 310 517 8278",
    "sg:postcode":"90717",
    "sg:province":"CA",
    "sg:tags":[
        "communications",
        "merchandise"
    ],
    "wof:name":"Robo Tel",
    "wof:placetype":"venue"
},
  "geometry": {"coordinates":[-118.320018,33.80333],"type":"Point"}
}