{
  "type": "Feature",
  "properties": {
    "addr:full":"9605 Las Tunas Dr Temple City CA 91780",
    "addr:housenumber":"9605",
    "addr:postcode":"91780",
    "addr:street":"Las Tunas Dr",
    "iso:country":"US",
    "sg:address":"9605 Las Tunas Dr",
    "sg:city":"Temple City",
    "sg:classifiers":[
        {
            "category":"Shopping",
            "subcategory":"Shoes",
            "type":"Retail Goods"
        }
    ],
    "sg:phone":"+1 626 451 9802",
    "sg:postcode":"91780",
    "sg:province":"CA",
    "sg:tags":[
        "store"
    ],
    "wof:name":"OMG Shoes",
    "wof:placetype":"venue"
},
  "geometry": {"coordinates":[-118.06061699999999,34.106761],"type":"Point"}
}