{
  "type": "Feature",
  "properties": {
    "addr:full":"3700 Delta Fair Blvd # 212 Antioch CA 94509",
    "addr:housenumber":"3700",
    "addr:postcode":"ca 94509",
    "addr:street":"Delta Fair Blvd # 212",
    "iso:country":"US",
    "sg:address":"3700 Delta Fair Blvd # 212",
    "sg:city":"Antioch",
    "sg:classifiers":[
        {
            "category":"Social Services",
            "type":"Services"
        }
    ],
    "sg:phone":"+1 925 778 8277",
    "sg:postcode":"94509",
    "sg:province":"CA",
    "sg:tags":[
        "consulting",
        "geriatric"
    ],
    "wof:name":"Community Vlenteers For Eldrly",
    "wof:placetype":"venue"
},
  "geometry": {"coordinates":[-121.844688,38.003819],"type":"Point"}
}