{
  "type": "Feature",
  "properties": {
    "iso:country":"US",
    "sg:address":"28032 Lakehurst Ave",
    "sg:city":"Canyon Country",
    "sg:classifiers":[
        {
            "category":"Professional",
            "subcategory":"Advertising",
            "type":"Services"
        }
    ],
    "sg:phone":"+1 661 251 0359",
    "sg:postcode":"91351",
    "sg:province":"CA",
    "sg:tags":[
        "counselor"
    ],
    "wof:name":"Intrepid Arts Advertising",
    "wof:placetype":"venue"
},
  "geometry": {"coordinates":[-118.486588,34.436468],"type":"Point"}
}