{
  "type": "Feature",
  "properties": {
    "addr:full":"6601 Westminster Blvd Westminster CA 92683",
    "addr:housenumber":"6601",
    "addr:postcode":"92683",
    "addr:street":"Westminster Blvd",
    "iso:country":"US",
    "sg:address":"6601 Westminster Blvd",
    "sg:city":"Westminster",
    "sg:classifiers":[
        {
            "category":"Travel",
            "subcategory":"Hotels & Motels",
            "type":"Entertainment"
        }
    ],
    "sg:phone":"+1 714 898 5598",
    "sg:postcode":"92683",
    "sg:province":"CA",
    "sg:website":"www.knightsinn.com/",
    "wof:name":"Knights Inn",
    "wof:placetype":"venue"
},
  "geometry": {"coordinates":[-118.014999,33.759201],"type":"Point"}
}