{
  "type": "Feature",
  "properties": {
    "iso:country":"US",
    "sg:address":"420 N Pine St",
    "sg:city":"Portola",
    "sg:classifiers":[
        {
            "category":"Social Services",
            "subcategory":"Child Care",
            "type":"Services"
        }
    ],
    "sg:phone":"+1 530 832 5678",
    "sg:postcode":"96122",
    "sg:province":"CA",
    "sg:tags":[
        "nursery",
        "day"
    ],
    "wof:name":"Portola Kids Inc.",
    "wof:placetype":"venue"
},
  "geometry": {"coordinates":[-120.46968699999999,39.813636],"type":"Point"}
}