{
  "type": "Feature",
  "properties": {
    "iso:country":"US",
    "sg:address":"16225 Sally Ln",
    "sg:city":"Riverside",
    "sg:classifiers":[
        {
            "category":"Building & Trades",
            "subcategory":"Construction",
            "type":"Services"
        }
    ],
    "sg:phone":"+1 951 780 1777",
    "sg:postcode":"92504",
    "sg:province":"CA",
    "sg:tags":[
        "concrete",
        "cutting",
        "breaking",
        "sawing"
    ],
    "wof:name":"Bonnett Construction",
    "wof:placetype":"venue"
},
  "geometry": {"coordinates":[-117.395984,33.884588],"type":"Point"}
}