{
  "type": "Feature",
  "properties": {
    "addr:full":"46775 Washington St La Quinta CA 92253",
    "addr:housenumber":"46775",
    "addr:postcode":"92253",
    "addr:street":"Washington St",
    "iso:country":"US",
    "sg:address":"46775 Washington St",
    "sg:city":"La Quinta",
    "sg:classifiers":[
        {
            "category":"Health Services",
            "subcategory":"Health Practitioner",
            "type":"Services"
        }
    ],
    "sg:phone":"+1 760 564 5668",
    "sg:postcode":"92253",
    "sg:province":"CA",
    "sg:tags":[
        "nurse",
        "registry"
    ],
    "wof:name":"CLP Leonard Pollard",
    "wof:placetype":"venue"
},
  "geometry": {"coordinates":[-116.29479499999999,33.711503],"type":"Point"}
}