{
  "type": "Feature",
  "properties": {
    "iso:country":"US",
    "sg:address":"16157 Brookhurst St",
    "sg:city":"Fountain Valley",
    "sg:classifiers":[
        {
            "category":"Real Estate",
            "subcategory":"Real Estate Operator",
            "type":"Services"
        }
    ],
    "sg:phone":"+1 714 775 2190",
    "sg:postcode":"92708",
    "sg:province":"CA",
    "sg:tags":[
        "building",
        "nonresidential"
    ],
    "wof:name":"Fountain Valley Town Center",
    "wof:placetype":"venue"
},
  "geometry": {"coordinates":[-117.95464200000001,33.730068],"type":"Point"}
}