{
  "type": "Feature",
  "properties": {
    "addr:full":"150 Clearlake Ave Lakeport CA 95453",
    "addr:housenumber":"150",
    "addr:postcode":"95453",
    "addr:street":"Clearlake Ave",
    "iso:country":"US",
    "sg:address":"150 Clearlake Ave",
    "sg:city":"Lakeport",
    "sg:classifiers":[
        {
            "category":"Travel",
            "subcategory":"Hotels & Motels",
            "type":"Entertainment"
        }
    ],
    "sg:phone":"+1 707 263 6444",
    "sg:postcode":"95453",
    "sg:province":"CA",
    "sg:tags":[
        "breakfast",
        "accommodation",
        "bed"
    ],
    "wof:name":"Arbor House Inn",
    "wof:placetype":"venue"
},
  "geometry": {"coordinates":[-122.915711,39.050012],"type":"Point"}
}