{
  "type": "Feature",
  "properties": {
    "addr:full":"4267 Marina City Dr Marina Del Rey CA 90292",
    "addr:housenumber":"4267",
    "addr:postcode":"90292",
    "addr:street":"Marina City Dr",
    "iso:country":"US",
    "sg:address":"4267 Marina City Dr",
    "sg:city":"Marina Del Rey",
    "sg:classifiers":[
        {
            "category":"Shopping",
            "subcategory":"Bicycles & Sporting Goods",
            "type":"Retail Goods"
        }
    ],
    "sg:phone":"+1 310 301 7090",
    "sg:postcode":"90292",
    "sg:province":"CA",
    "wof:name":"Golf Accessories Plus",
    "wof:placetype":"venue"
},
  "geometry": {"coordinates":[-118.452833,33.984583],"type":"Point"}
}