{
  "type": "Feature",
  "properties": {
    "iso:country":"US",
    "sg:address":"2386 E Main St",
    "sg:city":"Stockton",
    "sg:classifiers":[
        {
            "category":"Shopping",
            "type":"Retail Goods"
        }
    ],
    "sg:phone":"+1 209 547 0142",
    "sg:postcode":"95205",
    "sg:province":"CA",
    "sg:tags":[
        "telephone",
        "cellular"
    ],
    "wof:name":"Universal Cellular",
    "wof:placetype":"venue"
},
  "geometry": {"coordinates":[-121.25433099999999,37.954967],"type":"Point"}
}