{
  "type": "Feature",
  "properties": {
    "addr:full":"329 N Main St Salinas CA 93901",
    "addr:housenumber":"329",
    "addr:postcode":"93901",
    "addr:street":"N Main St",
    "iso:country":"US",
    "sg:address":"329 N Main St",
    "sg:city":"Salinas",
    "sg:classifiers":[
        {
            "category":"Social Services",
            "type":"Services"
        },
        {
            "category":"Place Of Worship",
            "subcategory":"Church",
            "type":"Public Place"
        },
        {
            "category":"Place Of Worship",
            "type":"Public Place"
        },
        {
            "category":"Shopping",
            "subcategory":"Thrift Store",
            "type":"Retail Goods"
        }
    ],
    "sg:phone":"+1 800 728 7825",
    "sg:postcode":"93901",
    "sg:province":"CA",
    "sg:tags":[
        "shop",
        "churches-salvation",
        "army"
    ],
    "sg:website":"http://www.salvationarmyusa.org/",
    "wof:name":"Salvation Army Family Store",
    "wof:placetype":"venue"
},
  "geometry": {"coordinates":[-121.653594,36.682238],"type":"Point"}
}