{
  "type": "Feature",
  "properties": {
    "addr:full":"820 N Lincoln Way Galt CA 95632",
    "addr:housenumber":"820",
    "addr:postcode":"95632",
    "addr:street":"N Lincoln Way",
    "iso:country":"US",
    "sg:address":"820 N Lincoln Way",
    "sg:city":"Galt",
    "sg:classifiers":[
        {
            "category":"Real Estate",
            "subcategory":"Real Estate Operator",
            "type":"Services"
        }
    ],
    "sg:phone":"+1 209 745 3010",
    "sg:postcode":"95632",
    "sg:province":"CA",
    "sg:tags":[
        "mobile",
        "home",
        "community"
    ],
    "wof:name":"Galt Mobile Estates",
    "wof:placetype":"venue"
},
  "geometry": {"coordinates":[-121.302559,38.269833],"type":"Point"}
}