{
  "type": "Feature",
  "properties": {
    "addr:full":"2012 Shattuck Avenue Berkeley CA 94704",
    "addr:housenumber":"2012",
    "addr:postcode":"94704",
    "addr:street":"Shattuck Avenue",
    "iso:country":"US",
    "sg:address":"2012 Shattuck Avenue",
    "sg:city":"Berkeley",
    "sg:classifiers":[
        {
            "category":"Food & Beverages",
            "subcategory":"Groceries & Convenience Stores",
            "type":"Retail Goods"
        }
    ],
    "sg:phone":"+1 510 848 9700",
    "sg:postcode":"94704",
    "sg:province":"CA",
    "wof:name":"Food Mart",
    "wof:placetype":"venue"
},
  "geometry": {"coordinates":[-122.26836400000001,37.87174],"type":"Point"}
}