{
  "type": "Feature",
  "properties": {
    "iso:country":"US",
    "sg:address":"900 E 20th St",
    "sg:city":"Merced",
    "sg:classifiers":[
        {
            "category":"Education",
            "subcategory":"School",
            "type":"Public Place"
        }
    ],
    "sg:phone":"+1 209 385 6615",
    "sg:postcode":"95340",
    "sg:province":"CA",
    "wof:name":"Charles Wright Elementary Schl",
    "wof:placetype":"venue"
},
  "geometry": {"coordinates":[-120.463034,37.297588],"type":"Point"}
}