{
  "type": "Feature",
  "properties": {
    "iso:country":"US",
    "sg:address":"404 S Cochran Avenue",
    "sg:city":"Los Angeles",
    "sg:classifiers":[
        {
            "category":"Real Estate",
            "subcategory":"Real Estate Operator",
            "type":"Services"
        }
    ],
    "sg:phone":"+1 323 549 0328",
    "sg:postcode":"90036",
    "sg:province":"CA",
    "sg:tags":[
        "apartment"
    ],
    "wof:name":"Miracle Mile Senior Housing",
    "wof:placetype":"venue"
},
  "geometry": {"coordinates":[-118.35012,34.068398],"type":"Point"}
}