{
  "type": "Feature",
  "properties": {
    "addr:full":"29424 Auberry Rd Prather CA 93651",
    "addr:postcode":"29424;93651",
    "addr:street":"Auberry Rd",
    "iso:country":"US",
    "sg:address":"29424 Auberry Rd",
    "sg:city":"Prather",
    "sg:classifiers":[
        {
            "category":"Restaurant",
            "type":"Food & Drink"
        }
    ],
    "sg:phone":"+1 559 855 2800",
    "sg:postcode":"93651",
    "sg:province":"CA",
    "sg:tags":[
        "pizza"
    ],
    "wof:name":"Pizza Factory",
    "wof:placetype":"venue"
},
  "geometry": {"coordinates":[-119.513744,37.037347],"type":"Point"}
}