{
  "type": "Feature",
  "properties": {
    "addr:full":"2350 Turk Boulevard San Francisco CA 94117",
    "addr:housenumber":"2350",
    "addr:postcode":"94117",
    "addr:street":"Turk Boulevard",
    "iso:country":"US",
    "sg:address":"2350 Turk Boulevard",
    "sg:city":"San Francisco",
    "sg:classifiers":[
        {
            "category":"Arts & Performance",
            "subcategory":"Arts Center",
            "type":"Entertainment"
        }
    ],
    "sg:phone":"+1 415 422 2434",
    "sg:postcode":"94117",
    "sg:province":"CA",
    "sg:tags":[
        "performing"
    ],
    "sg:website":"www.usfca.edu/presentationtheater/",
    "wof:name":"USF Presentation Theater",
    "wof:placetype":"venue"
},
  "geometry": {"coordinates":[-122.44755499999999,37.778605],"type":"Point"}
}