{
  "type": "Feature",
  "properties": {
    "iso:country":"US",
    "sg:address":"2920 E Nees Ave",
    "sg:city":"Fresno",
    "sg:classifiers":[
        {
            "category":"Home & Garden",
            "subcategory":"Furniture",
            "type":"Retail Goods"
        }
    ],
    "sg:phone":"+1 559 299 2380",
    "sg:postcode":"93720",
    "sg:province":"CA",
    "sg:tags":[
        "store"
    ],
    "wof:name":"Jonathan Sterling Home Elegance Inc",
    "wof:placetype":"venue"
},
  "geometry": {"coordinates":[-119.73151300000001,36.852217],"type":"Point"}
}