{
  "type": "Feature",
  "properties": {
    "addr:full":"5835 Four Oaks Ln Clayton CA 94517",
    "addr:housenumber":"5835",
    "addr:postcode":"94517",
    "addr:street":"Four Oaks Ln",
    "iso:country":"US",
    "sg:address":"5835 Four Oaks Ln",
    "sg:city":"Clayton",
    "sg:classifiers":[
        {
            "category":"Building & Trades",
            "subcategory":"Construction",
            "type":"Services"
        }
    ],
    "sg:phone":"+1 925 672 2777",
    "sg:postcode":"94517",
    "sg:province":"CA",
    "sg:tags":[
        "wallcoverings-installation",
        "wallpaper",
        "painting",
        "contractor"
    ],
    "wof:name":"Lonnie Rice Painting",
    "wof:placetype":"venue"
},
  "geometry": {"coordinates":[-121.94210200000001,37.942084],"type":"Point"}
}