{
  "type": "Feature",
  "properties": {
    "addr:full":"795 Skyway Rd San Carlos CA 94070",
    "addr:housenumber":"795",
    "addr:postcode":"94070",
    "addr:street":"Skyway Rd",
    "iso:country":"US",
    "sg:address":"795 Skyway Rd",
    "sg:city":"San Carlos",
    "sg:classifiers":[
        {
            "category":"Autos & Motor Vehicles",
            "subcategory":"Automobile Sales",
            "type":"Retail Goods"
        }
    ],
    "sg:phone":"+1 650 592 3292",
    "sg:postcode":"94070",
    "sg:province":"CA",
    "sg:tags":[
        "aircraft"
    ],
    "wof:name":"Small Hope Airlines",
    "wof:placetype":"venue"
},
  "geometry": {"coordinates":[-122.24987400000001,37.509253],"type":"Point"}
}