{
  "type": "Feature",
  "properties": {
    "iso:country":"US",
    "sg:address":"13050 E Tulare Ave",
    "sg:city":"Sanger",
    "sg:classifiers":[
        {
            "category":"Building & Trades",
            "subcategory":"Construction",
            "type":"Services"
        }
    ],
    "sg:phone":"+1 559 876 1205",
    "sg:postcode":"93657",
    "sg:province":"CA",
    "sg:tags":[
        "general",
        "contractor"
    ],
    "wof:name":"Arrow Construction",
    "wof:placetype":"venue"
},
  "geometry": {"coordinates":[-119.545402,36.743058],"type":"Point"}
}