{
  "type": "Feature",
  "properties": {
    "addr:full":"7960 Soquel Dr Aptos CA 95003",
    "addr:housenumber":"7960",
    "addr:postcode":"ca 95003",
    "addr:street":"Soquel Dr",
    "iso:country":"US",
    "sg:address":"7960 Soquel Dr",
    "sg:city":"Aptos",
    "sg:classifiers":[
        {
            "category":"Sports & Exercise",
            "subcategory":"Gym",
            "type":"Entertainment"
        }
    ],
    "sg:postcode":"95003",
    "sg:province":"CA",
    "sg:tags":[
        "yoga"
    ],
    "sg:website":"www.bikramyogaaptos.com/",
    "wof:name":"Bikram Yoga Aptos",
    "wof:placetype":"venue"
},
  "geometry": {"coordinates":[-121.90572899999999,36.976443],"type":"Point"}
}