{
  "type": "Feature",
  "properties": {
    "addr:full":"844 W E St Ontario CA 91762",
    "addr:housenumber":"844",
    "addr:postcode":"91762",
    "addr:street":"W E St",
    "iso:country":"US",
    "sg:address":"844 W E St",
    "sg:city":"Ontario",
    "sg:classifiers":[
        {
            "category":"Professional",
            "subcategory":"Computer Services",
            "type":"Services"
        }
    ],
    "sg:phone":"+1 909 460 0726",
    "sg:postcode":"91762",
    "sg:province":"CA",
    "sg:tags":[
        "consultant",
        "designer"
    ],
    "wof:name":"N W Strabley Consulting",
    "wof:placetype":"venue"
},
  "geometry": {"coordinates":[-117.664418,34.068045],"type":"Point"}
}