{
  "type": "Feature",
  "properties": {
    "addr:full":"130 Lincoln Ave Sutter Creek CA 95695",
    "addr:housenumber":"130",
    "addr:postcode":"95695",
    "addr:street":"Lincoln Ave",
    "iso:country":"US",
    "sg:address":"130 Lincoln Ave",
    "sg:city":"Sutter Creek",
    "sg:classifiers":[
        {
            "category":"Sports & Exercise",
            "subcategory":"Gym",
            "type":"Entertainment"
        }
    ],
    "sg:phone":"+1 209 267 0008",
    "sg:postcode":"95695",
    "sg:province":"CA",
    "sg:tags":[
        "club",
        "health",
        "studio",
        "gymnasium"
    ],
    "wof:name":"Amador Gym & Fitness Ctr",
    "wof:placetype":"venue"
},
  "geometry": {"coordinates":[-121.780654,38.675621],"type":"Point"}
}