{
  "type": "Feature",
  "properties": {
    "iso:country":"US",
    "sg:address":"2600 Garden Rd",
    "sg:city":"Monterey",
    "sg:classifiers":[
        {
            "category":"Building & Trades",
            "subcategory":"Landscaping Services",
            "type":"Services"
        }
    ],
    "sg:phone":"+1 831 373 2020",
    "sg:postcode":"93940",
    "sg:province":"CA",
    "sg:tags":[
        "landscape",
        "contractor"
    ],
    "wof:name":"Alpha Landscaping",
    "wof:placetype":"venue"
},
  "geometry": {"coordinates":[-121.85059699999999,36.585649],"type":"Point"}
}