{
  "type": "Feature",
  "properties": {
    "iso:country":"US",
    "sg:address":"306 San Fernando St",
    "sg:city":"San Diego",
    "sg:classifiers":[
        {
            "category":"Health Services",
            "subcategory":"Doctor",
            "type":"Services"
        }
    ],
    "sg:phone":"+1 619 222 7513",
    "sg:postcode":"92106",
    "sg:province":"CA",
    "sg:tags":[
        "physician",
        "surgeon"
    ],
    "sg:website":"www.ahlering.com",
    "wof:name":"John R Ahlering & Assoc",
    "wof:placetype":"venue"
},
  "geometry": {"coordinates":[-117.241159,32.708894],"type":"Point"}
}