{
  "type": "Feature",
  "properties": {
    "addr:full":"8101 Tampa Ave Reseda CA 91335",
    "addr:housenumber":"8101",
    "addr:postcode":"91335",
    "addr:street":"Tampa Ave",
    "iso:country":"US",
    "sg:address":"8101 Tampa Ave",
    "sg:city":"Reseda",
    "sg:classifiers":[
        {
            "category":"Recreation",
            "type":"Entertainment"
        }
    ],
    "sg:phone":"+1 818 341 2770",
    "sg:postcode":"91335",
    "sg:province":"CA",
    "sg:tags":[
        "riding",
        "academy"
    ],
    "wof:name":"Pony Country",
    "wof:placetype":"venue"
},
  "geometry": {"coordinates":[-118.553551,34.219251],"type":"Point"}
}