{
  "type": "Feature",
  "properties": {
    "iso:country":"US",
    "sg:address":"1833 S La Cienega Boulevard",
    "sg:city":"Los Angeles",
    "sg:classifiers":[
        {
            "category":"Shopping",
            "subcategory":"Stationery & Office Supplies",
            "type":"Retail Goods"
        }
    ],
    "sg:phone":"+1 310 202 5343",
    "sg:postcode":"90035",
    "sg:province":"CA",
    "sg:tags":[
        "equipment"
    ],
    "wof:name":"Staples Copy & Print Centers",
    "wof:placetype":"venue"
},
  "geometry": {"coordinates":[-118.376777,34.043871],"type":"Point"}
}