{
  "type": "Feature",
  "properties": {
    "iso:country":"US",
    "sg:address":"519 17th St",
    "sg:city":"Oakland",
    "sg:classifiers":[
        {
            "category":"Education",
            "subcategory":"School",
            "type":"Public Place"
        }
    ],
    "sg:phone":"+1 510 645 9932",
    "sg:postcode":"94612",
    "sg:province":"CA",
    "wof:name":"Willow Education Bay Area Tech",
    "wof:placetype":"venue"
},
  "geometry": {"coordinates":[-122.27152,37.806925],"type":"Point"}
}