{
  "type": "Feature",
  "properties": {
    "addr:full":"3421 Newport Blvd Newport Beach CA 92663",
    "addr:housenumber":"3421",
    "addr:postcode":"92663",
    "addr:street":"Newport Blvd",
    "iso:country":"US",
    "sg:address":"3421 Newport Blvd",
    "sg:city":"Newport Beach",
    "sg:classifiers":[
        {
            "category":"Shopping",
            "subcategory":"Optician",
            "type":"Retail Goods"
        }
    ],
    "sg:phone":"+1 949 645 4527",
    "sg:postcode":"92663",
    "sg:province":"CA",
    "sg:tags":[
        "eyewear"
    ],
    "wof:name":"Newport Beach Sunglass Co",
    "wof:placetype":"venue"
},
  "geometry": {"coordinates":[-117.93000000000001,33.617901],"type":"Point"}
}