{
  "type": "Feature",
  "properties": {
    "iso:country":"US",
    "sg:address":"1104 S Seaward Ave",
    "sg:city":"Ventura",
    "sg:classifiers":[
        {
            "category":"Personal",
            "subcategory":"Beauty Salon",
            "type":"Services"
        }
    ],
    "sg:phone":"+1 805 656 3248",
    "sg:postcode":"93001",
    "sg:province":"CA",
    "wof:name":"Studio Sea Hair Designers",
    "wof:placetype":"venue"
},
  "geometry": {"coordinates":[-119.272756,34.263803],"type":"Point"}
}