{
  "type": "Feature",
  "properties": {
    "addr:full":"46165 Dillon Rd Coachella CA 92236",
    "addr:housenumber":"46165",
    "addr:postcode":"92236",
    "addr:street":"Dillon Rd",
    "iso:country":"US",
    "sg:address":"46165 Dillon Rd",
    "sg:city":"Coachella",
    "sg:classifiers":[
        {
            "category":"Retail",
            "subcategory":"Car Wash",
            "type":"Services"
        }
    ],
    "sg:phone":"+1 760 775 3644",
    "sg:postcode":"92236",
    "sg:province":"CA",
    "sg:tags":[
        "truck",
        "cleaning"
    ],
    "sg:website":"www.eagletruckwash.com",
    "wof:name":"Eagle Truck Wash",
    "wof:placetype":"venue"
},
  "geometry": {"coordinates":[-116.170383,33.717246],"type":"Point"}
}