{
  "type": "Feature",
  "properties": {
    "iso:country":"US",
    "sg:address":"39400 Murrieta Hot Springs Rd",
    "sg:city":"Murrieta",
    "sg:classifiers":[
        {
            "category":"Restaurant",
            "type":"Food & Drink"
        }
    ],
    "sg:menulink":"http://www.allmenus.com/ca/murrieta/67785-foxs-pizza-den/menu/",
    "sg:phone":"+1 951 677 4321",
    "sg:postcode":"92563",
    "sg:province":"CA",
    "sg:tags":[
        "american",
        "pizza"
    ],
    "wof:name":"Fox's Pizza Den",
    "wof:placetype":"venue"
},
  "geometry": {"coordinates":[-117.154329,33.556309],"type":"Point"}
}