{
  "type": "Feature",
  "properties": {
    "iso:country":"US",
    "sg:address":"1340 W McFadden Ave",
    "sg:city":"Santa Ana",
    "sg:classifiers":[
        {
            "category":"Wholesale",
            "subcategory":"Auto Parts",
            "type":"Manufacturing & Wholesale Goods"
        }
    ],
    "sg:phone":"+1 714 708 3434",
    "sg:postcode":"92704",
    "sg:province":"CA",
    "sg:tags":[
        "supply"
    ],
    "wof:name":"Chihuahua Auto Accessories",
    "wof:placetype":"venue"
},
  "geometry": {"coordinates":[-117.886646,33.734395],"type":"Point"}
}