{
  "type": "Feature",
  "properties": {
    "iso:country":"US",
    "sg:address":"724 Medical Center Dr E",
    "sg:city":"Clovis",
    "sg:classifiers":[
        {
            "category":"Organizations",
            "subcategory":"Non-profit Organization",
            "type":"Services"
        }
    ],
    "sg:phone":"+1 559 323 4495",
    "sg:postcode":"93611",
    "sg:province":"CA",
    "sg:tags":[
        "information",
        "alcoholism",
        "treatment"
    ],
    "wof:name":"Touchstone Medical Group",
    "wof:placetype":"venue"
},
  "geometry": {"coordinates":[-119.658757,36.842997],"type":"Point"}
}