{
  "type": "Feature",
  "properties": {
    "iso:country":"US",
    "sg:address":"5610 York Blvd",
    "sg:city":"Los Angeles",
    "sg:classifiers":[
        {
            "category":"Shopping",
            "subcategory":"Department Store",
            "type":"Retail Goods"
        }
    ],
    "sg:phone":"+1 323 256 4622",
    "sg:postcode":"90042",
    "sg:province":"CA",
    "sg:tags":[
        "shop"
    ],
    "wof:name":"Big Lots",
    "wof:placetype":"venue"
},
  "geometry": {"coordinates":[-118.195482,34.119118],"type":"Point"}
}