{
  "type": "Feature",
  "properties": {
    "addr:full":"1068 8th St Imperial Beach CA 91932",
    "addr:housenumber":"1068",
    "addr:postcode":"91932",
    "addr:street":"8Th St",
    "iso:country":"US",
    "sg:address":"1068 8th St",
    "sg:city":"Imperial Beach",
    "sg:classifiers":[
        {
            "category":"Freight",
            "type":"Transportation"
        }
    ],
    "sg:phone":"+1 619 424 5674",
    "sg:postcode":"91932",
    "sg:province":"CA",
    "sg:tags":[
        "local",
        "storage",
        "trucking"
    ],
    "wof:name":"Delgado & Sons",
    "wof:placetype":"venue"
},
  "geometry": {"coordinates":[-117.116613,32.577028],"type":"Point"}
}