{
  "type": "Feature",
  "properties": {
    "iso:country":"US",
    "sg:address":"1733 S Douglass Rd",
    "sg:city":"Anaheim",
    "sg:classifiers":[
        {
            "category":"Professional",
            "subcategory":"Art Services",
            "type":"Services"
        }
    ],
    "sg:phone":"+1 714 978 0552",
    "sg:postcode":"92806",
    "sg:province":"CA",
    "sg:tags":[
        "graphic",
        "designer"
    ],
    "sg:website":"www.grafixstop.com",
    "wof:name":"Grafix Stop",
    "wof:placetype":"venue"
},
  "geometry": {"coordinates":[-117.87880800000001,33.802723],"type":"Point"}
}