{
  "type": "Feature",
  "properties": {
    "addr:full":"1107 S King Rd San Jose CA 95122",
    "addr:housenumber":"1107",
    "addr:postcode":"95122",
    "addr:street":"S King Rd",
    "iso:country":"US",
    "sg:address":"1107 S King Rd",
    "sg:city":"San Jose",
    "sg:classifiers":[
        {
            "category":"Banks & Credit Unions",
            "subcategory":"Financial Services",
            "type":"Services"
        }
    ],
    "sg:postcode":"95122",
    "sg:province":"CA",
    "wof:name":"Bank of America",
    "wof:placetype":"venue"
},
  "geometry": {"coordinates":[-121.842479,37.339119],"type":"Point"}
}