{
  "type": "Feature",
  "properties": {
    "iso:country":"US",
    "sg:address":"2159 Central Ave",
    "sg:city":"Alameda",
    "sg:classifiers":[
        {
            "category":"Personal",
            "subcategory":"Beauty Salon",
            "type":"Services"
        }
    ],
    "sg:phone":"+1 925 962 2639",
    "sg:postcode":"94501",
    "sg:province":"CA",
    "wof:name":"Beautiful Skin & Body",
    "wof:placetype":"venue"
},
  "geometry": {"coordinates":[-122.248102,37.766503],"type":"Point"}
}