{
  "type": "Feature",
  "properties": {
    "addr:full":"4502 Wyngate Cir Irvine CA 92604",
    "addr:housenumber":"4502",
    "addr:postcode":"92604",
    "addr:street":"Wyngate Cir",
    "iso:country":"US",
    "sg:address":"4502 Wyngate Cir",
    "sg:city":"Irvine",
    "sg:classifiers":[
        {
            "category":"Professional",
            "type":"Services"
        }
    ],
    "sg:phone":"+1 949 559 8423",
    "sg:postcode":"92604",
    "sg:province":"CA",
    "wof:name":"Chase Shirleen",
    "wof:placetype":"venue"
},
  "geometry": {"coordinates":[-117.782178,33.698767],"type":"Point"}
}