{
  "type": "Feature",
  "properties": {
    "addr:full":"2016 Forest Ave Ste 7 San Jose CA 95128",
    "addr:housenumber":"2016",
    "addr:postcode":"95128",
    "addr:street":"Forest Ave Ste 7",
    "iso:country":"US",
    "sg:address":"2016 Forest Ave Ste 7",
    "sg:city":"San Jose",
    "sg:classifiers":[
        {
            "category":"Health Services",
            "subcategory":"Doctor",
            "type":"Services"
        }
    ],
    "sg:phone":"+1 408 294 5734",
    "sg:postcode":"95128",
    "sg:province":"CA",
    "sg:tags":[
        "obstetrician",
        "gynecologist"
    ],
    "wof:name":"Sanfilippo Philip R MD",
    "wof:placetype":"venue"
},
  "geometry": {"coordinates":[-121.932999,37.327],"type":"Point"}
}