{
  "type": "Feature",
  "properties": {
    "iso:country":"US",
    "sg:address":"424 E H St",
    "sg:city":"Benicia",
    "sg:classifiers":[
        {
            "category":"Wholesale",
            "subcategory":"Vending Machines",
            "type":"Manufacturing & Wholesale Goods"
        }
    ],
    "sg:phone":"+1 707 745 6560",
    "sg:postcode":"94510",
    "sg:province":"CA",
    "wof:name":"Cyclops Enterprises",
    "wof:placetype":"venue"
},
  "geometry": {"coordinates":[-122.150225,38.047034],"type":"Point"}
}