{
  "type": "Feature",
  "properties": {
    "addr:full":"750 1st St Livingston CA 95334",
    "addr:housenumber":"750",
    "addr:postcode":"95334",
    "addr:street":"1St St",
    "iso:country":"US",
    "sg:address":"750 1st St",
    "sg:city":"Livingston",
    "sg:classifiers":[
        {
            "category":"Professional",
            "subcategory":"Business Services",
            "type":"Services"
        }
    ],
    "sg:phone":"+1 209 394 4317",
    "sg:postcode":"95334",
    "sg:province":"CA",
    "sg:tags":[
        "water",
        "treatment"
    ],
    "wof:name":"J M Movile",
    "wof:placetype":"venue"
},
  "geometry": {"coordinates":[-120.72559200000001,37.383835],"type":"Point"}
}