{
  "type": "Feature",
  "properties": {
    "iso:country":"US",
    "sg:address":"638 Groton Dr",
    "sg:city":"Burbank",
    "sg:classifiers":[
        {
            "category":"Building & Trades",
            "subcategory":"Construction",
            "type":"Services"
        }
    ],
    "sg:phone":"+1 818 558 1677",
    "sg:postcode":"91504",
    "sg:province":"CA",
    "sg:tags":[
        "house"
    ],
    "wof:name":"Thoughtful Builders Inc",
    "wof:placetype":"venue"
},
  "geometry": {"coordinates":[-118.321795,34.202437],"type":"Point"}
}