{
  "type": "Feature",
  "properties": {
    "addr:full":"16315 Whittier Blvd Whittier CA 90603",
    "addr:housenumber":"16315",
    "addr:postcode":"90603",
    "addr:street":"Whittier Blvd",
    "iso:country":"US",
    "sg:address":"16315 Whittier Blvd",
    "sg:city":"Whittier",
    "sg:classifiers":[
        {
            "category":"Shopping",
            "type":"Retail Goods"
        }
    ],
    "sg:phone":"+1 562 943 7181",
    "sg:postcode":"90603",
    "sg:province":"CA",
    "sg:tags":[
        "hearing",
        "equipment",
        "supply",
        "impaired"
    ],
    "wof:name":"Advantage Hearing Aid Pros",
    "wof:placetype":"venue"
},
  "geometry": {"coordinates":[-117.982229,33.940182],"type":"Point"}
}