{
  "type": "Feature",
  "properties": {
    "addr:full":"4483 Stevens Creek Blvd Santa Clara CA 95051",
    "addr:housenumber":"4483",
    "addr:postcode":"95051",
    "addr:street":"Stevens Creek Blvd",
    "iso:country":"US",
    "sg:address":"4483 Stevens Creek Blvd",
    "sg:city":"Santa Clara",
    "sg:classifiers":[
        {
            "category":"Personal",
            "subcategory":"Beauty Salon",
            "type":"Services"
        },
        {
            "category":"Personal",
            "subcategory":"Skin Care",
            "type":"Services"
        },
        {
            "category":"Shopping",
            "subcategory":"Beauty & Cosmetics",
            "type":"Retail Goods"
        }
    ],
    "sg:phone":"+1 408 984 0989",
    "sg:postcode":"95051",
    "sg:province":"CA",
    "sg:tags":[
        "hair",
        "makeup",
        "artist",
        "supply"
    ],
    "sg:website":"www.allansalon.com",
    "wof:name":"Allan's Salon",
    "wof:placetype":"venue"
},
  "geometry": {"coordinates":[-121.981151,37.323145],"type":"Point"}
}