{
  "type": "Feature",
  "properties": {
    "iso:country":"US",
    "sg:address":"3420 Arden Rd",
    "sg:city":"Hayward",
    "sg:classifiers":[
        {
            "category":"Professional",
            "type":"Services"
        }
    ],
    "sg:phone":"+1 510 265 1682",
    "sg:postcode":"94545",
    "sg:province":"CA",
    "wof:name":"Spmg Company",
    "wof:placetype":"venue"
},
  "geometry": {"coordinates":[-122.112788,37.621738],"type":"Point"}
}