{
  "type": "Feature",
  "properties": {
    "addr:full":"14895 E 14th St San Leandro CA 94578",
    "addr:housenumber":"14895",
    "addr:postcode":"94578",
    "addr:street":"E 14Th St",
    "iso:country":"US",
    "sg:address":"14895 E 14th St",
    "sg:city":"San Leandro",
    "sg:classifiers":[
        {
            "category":"Professional",
            "subcategory":"Lawyer & Legal Services",
            "type":"Services"
        }
    ],
    "sg:phone":"+1 510 347 5600",
    "sg:postcode":"94578",
    "sg:province":"CA",
    "sg:tags":[
        "attorney"
    ],
    "wof:name":"Frank J De Benedetto Law Ofcs",
    "wof:placetype":"venue"
},
  "geometry": {"coordinates":[-122.131692,37.707468],"type":"Point"}
}