{
  "type": "Feature",
  "properties": {
    "iso:country":"US",
    "sg:address":"10945 Cozycroft Ave",
    "sg:city":"Chatsworth",
    "sg:classifiers":[
        {
            "category":"Wholesale",
            "subcategory":"Non-durable Goods",
            "type":"Manufacturing & Wholesale Goods"
        }
    ],
    "sg:phone":"+1 818 718 1949",
    "sg:postcode":"91311",
    "sg:province":"CA",
    "sg:tags":[
        "fabric",
        "merchandise",
        "general"
    ],
    "wof:name":"Highview Ltd",
    "wof:placetype":"venue"
},
  "geometry": {"coordinates":[-118.58149899999999,34.270443],"type":"Point"}
}