{
  "type": "Feature",
  "properties": {
    "addr:full":"600 Roble Ave Pinole CA 94564",
    "addr:housenumber":"600",
    "addr:postcode":"94564",
    "addr:street":"Roble Ave",
    "iso:country":"US",
    "sg:address":"600 Roble Ave",
    "sg:city":"Pinole",
    "sg:classifiers":[
        {
            "category":"Education",
            "subcategory":"Vocational School",
            "type":"Public Place"
        }
    ],
    "sg:phone":"+1 510 724 3200",
    "sg:postcode":"94564",
    "sg:province":"CA",
    "sg:tags":[
        "apprenticeship",
        "management",
        "labor"
    ],
    "wof:name":"Painting Decortng Joint Apprnt",
    "wof:placetype":"venue"
},
  "geometry": {"coordinates":[-122.30119500000001,38.004246],"type":"Point"}
}