{
  "type": "Feature",
  "properties": {
    "addr:full":"1537 Oakview Ave Albany CA 94706",
    "addr:housenumber":"1537",
    "addr:postcode":"94706",
    "addr:street":"Oakview Ave",
    "iso:country":"US",
    "sg:address":"1537 Oakview Ave",
    "sg:city":"Albany",
    "sg:classifiers":[
        {
            "category":"Professional",
            "subcategory":"Accounting & Tax Preparation",
            "type":"Services"
        }
    ],
    "sg:phone":"+1 510 526 7526",
    "sg:postcode":"94706",
    "sg:province":"CA",
    "sg:tags":[
        "return",
        "filing"
    ],
    "wof:name":"J C Armstrong Co",
    "wof:placetype":"venue"
},
  "geometry": {"coordinates":[-122.287468,37.899549],"type":"Point"}
}