{
  "type": "Feature",
  "properties": {
    "addr:full":"2116 Jayhawk Dr Lodi CA 95240",
    "addr:housenumber":"2116",
    "addr:postcode":"95240",
    "addr:street":"Jayhawk Dr",
    "iso:country":"US",
    "sg:address":"2116 Jayhawk Dr",
    "sg:city":"Lodi",
    "sg:classifiers":[
        {
            "category":"Building & Trades",
            "subcategory":"Landscaping Services",
            "type":"Services"
        }
    ],
    "sg:phone":"+1 209 712 1866",
    "sg:postcode":"95240",
    "sg:province":"CA",
    "sg:tags":[
        "lawn",
        "maintenance"
    ],
    "wof:name":"Cabrillas Lawn Maintenance",
    "wof:placetype":"venue"
},
  "geometry": {"coordinates":[-121.26564500000001,38.10689],"type":"Point"}
}