{
  "type": "Feature",
  "properties": {
    "addr:full":"855 Scaroni Rd Calexico CA 92231",
    "addr:housenumber":"855",
    "addr:postcode":"92231",
    "addr:street":"Scaroni Rd",
    "iso:country":"US",
    "sg:address":"855 Scaroni Rd",
    "sg:city":"Calexico",
    "sg:classifiers":[
        {
            "category":"Freight",
            "type":"Transportation"
        }
    ],
    "sg:phone":"+1 760 353 4717",
    "sg:postcode":"92231",
    "sg:province":"CA",
    "sg:tags":[
        "commercial",
        "storage"
    ],
    "wof:name":"El Ranchito Mini Storage",
    "wof:placetype":"venue"
},
  "geometry": {"coordinates":[-115.500249,32.709634],"type":"Point"}
}