{
  "type": "Feature",
  "properties": {
    "iso:country":"US",
    "sg:address":"1285 E Madison Ave",
    "sg:city":"El Cajon",
    "sg:classifiers":[
        {
            "category":"Restaurant",
            "type":"Food & Drink"
        }
    ],
    "sg:menulink":"http://www.allmenus.com/ca/san-diego/213451-taco-bell/menu/",
    "sg:phone":"+1 619 442 3515",
    "sg:postcode":"92021",
    "sg:province":"CA",
    "sg:tags":[
        "mexican"
    ],
    "wof:name":"Taco Bell",
    "wof:placetype":"venue"
},
  "geometry": {"coordinates":[-116.936697,32.800176],"type":"Point"}
}