{
  "type": "Feature",
  "properties": {
    "iso:country":"US",
    "sg:address":"3355 Taylor Rd",
    "sg:city":"Loomis",
    "sg:classifiers":[
        {
            "category":"Personal",
            "subcategory":"Beauty Salon",
            "type":"Services"
        }
    ],
    "sg:phone":"+1 916 652 7823",
    "sg:postcode":"95650",
    "sg:province":"CA",
    "wof:name":"Yamie's Beauty Shop",
    "wof:placetype":"venue"
},
  "geometry": {"coordinates":[-121.189705,38.827166],"type":"Point"}
}