{
  "type": "Feature",
  "properties": {
    "addr:full":"107 Harbor Way Santa Barbara CA 93109",
    "addr:housenumber":"107",
    "addr:postcode":"93109",
    "addr:street":"Harbor Way",
    "iso:country":"US",
    "sg:address":"107 Harbor Way",
    "sg:city":"Santa Barbara",
    "sg:classifiers":[
        {
            "category":"Restaurant",
            "type":"Food & Drink"
        }
    ],
    "sg:phone":"+1 805 965 1557",
    "sg:postcode":"93109",
    "sg:province":"CA",
    "wof:name":"Breakwater Restaurant",
    "wof:placetype":"venue"
},
  "geometry": {"coordinates":[-119.693168,34.403758],"type":"Point"}
}