{
  "type": "Feature",
  "properties": {
    "addr:full":"417 Main St Huntington Beach CA 92648",
    "addr:housenumber":"417",
    "addr:postcode":"92648",
    "addr:street":"Main St",
    "iso:country":"US",
    "sg:address":"417 Main St",
    "sg:city":"Huntington Beach",
    "sg:classifiers":[
        {
            "category":"Personal",
            "subcategory":"Beauty Salon",
            "type":"Services"
        }
    ],
    "sg:phone":"+1 714 969 0907",
    "sg:postcode":"92648",
    "sg:province":"CA",
    "sg:tags":[
        "hair"
    ],
    "wof:name":"Mood Swings",
    "wof:placetype":"venue"
},
  "geometry": {"coordinates":[-117.999139,33.660527],"type":"Point"}
}