{
  "type": "Feature",
  "properties": {
    "addr:full":"30852 Marilyn Dr Laguna Beach CA 92651",
    "addr:postcode":"30852;92651",
    "addr:street":"Marilyn Dr",
    "iso:country":"US",
    "sg:address":"30852 Marilyn Dr",
    "sg:city":"Laguna Beach",
    "sg:classifiers":[
        {
            "category":"Professional",
            "type":"Services"
        }
    ],
    "sg:phone":"+1 949 494 2501",
    "sg:postcode":"92651",
    "sg:province":"CA",
    "wof:name":"Richard O Moore Inc",
    "wof:placetype":"venue"
},
  "geometry": {"coordinates":[-117.754152,33.515303],"type":"Point"}
}