{
  "type": "Feature",
  "properties": {
    "addr:full":"105 Vernon St Roseville CA 95678",
    "addr:housenumber":"105",
    "addr:postcode":"95678",
    "addr:street":"Vernon St",
    "iso:country":"US",
    "sg:address":"105 Vernon St",
    "sg:city":"Roseville",
    "sg:classifiers":[
        {
            "category":"Social Services",
            "type":"Services"
        }
    ],
    "sg:phone":"+1 916 782 3202",
    "sg:postcode":"95678",
    "sg:province":"CA",
    "sg:tags":[
        "youth",
        "organization",
        "center"
    ],
    "wof:name":"Roseville Science & Technology",
    "wof:placetype":"venue"
},
  "geometry": {"coordinates":[-121.28276099999999,38.749878],"type":"Point"}
}