{
  "type": "Feature",
  "properties": {
    "addr:full":"5 Oak Crest Ct Novato CA 94947",
    "addr:housenumber":"5",
    "addr:postcode":"94947",
    "addr:street":"Oak Crest Ct",
    "iso:country":"US",
    "sg:address":"5 Oak Crest Ct",
    "sg:city":"Novato",
    "sg:classifiers":[
        {
            "category":"Wholesale",
            "subcategory":"Non-durable Goods",
            "type":"Manufacturing & Wholesale Goods"
        }
    ],
    "sg:phone":"+1 415 893 1160",
    "sg:postcode":"94947",
    "sg:province":"CA",
    "wof:name":"Planet & Earth Herbal Care",
    "wof:placetype":"venue"
},
  "geometry": {"coordinates":[-122.55383999999999,38.085932],"type":"Point"}
}