{
  "type": "Feature",
  "properties": {
    "addr:full":"1836 Union Street San Francisco CA 94123",
    "addr:housenumber":"1836",
    "addr:postcode":"94123",
    "addr:street":"Union Street",
    "iso:country":"US",
    "sg:address":"1836 Union Street",
    "sg:city":"San Francisco",
    "sg:classifiers":[
        {
            "category":"Building & Trades",
            "subcategory":"Construction",
            "type":"Services"
        }
    ],
    "sg:phone":"+1 415 614 9700",
    "sg:postcode":"94123",
    "sg:province":"CA",
    "sg:tags":[
        "interior",
        "design"
    ],
    "wof:name":"Studio G Design",
    "wof:placetype":"venue"
},
  "geometry": {"coordinates":[-122.43000000000001,37.798],"type":"Point"}
}