{
  "type": "Feature",
  "properties": {
    "iso:country":"US",
    "sg:address":"1395 E Washington Blvd",
    "sg:city":"Pasadena",
    "sg:classifiers":[
        {
            "category":"Shopping",
            "subcategory":"Used Merchandise",
            "type":"Retail Goods"
        }
    ],
    "sg:phone":"+1 626 798 4438",
    "sg:postcode":"91104",
    "sg:province":"CA",
    "sg:tags":[
        "stationery",
        "book",
        "rare",
        "dealer"
    ],
    "sg:website":"www.mitchellbooks.com",
    "wof:name":"Mitchell Books",
    "wof:placetype":"venue"
},
  "geometry": {"coordinates":[-118.12263,34.16913],"type":"Point"}
}