{
  "type": "Feature",
  "properties": {
    "iso:country":"US",
    "sg:address":"1026 Wall St",
    "sg:city":"Los Angeles",
    "sg:classifiers":[
        {
            "category":"Real Estate",
            "subcategory":"Real Estate Services",
            "type":"Services"
        }
    ],
    "sg:phone":"+1 213 745 6900",
    "sg:postcode":"90015",
    "sg:province":"CA",
    "sg:tags":[
        "management",
        "property"
    ],
    "sg:website":"www.quantum-associates.com",
    "wof:name":"Quantum Associates",
    "wof:placetype":"venue"
},
  "geometry": {"coordinates":[-118.253998,34.0369],"type":"Point"}
}