{
  "type": "Feature",
  "properties": {
    "addr:full":"18564 State Hwy 18 Apple Valley CA 92307",
    "addr:housenumber":"18564",
    "addr:postcode":"92307",
    "addr:street":"State Hwy 18",
    "iso:country":"US",
    "sg:address":"18564 State Hwy 18",
    "sg:city":"Apple Valley",
    "sg:classifiers":[
        {
            "category":"Health Services",
            "subcategory":"Clinic",
            "type":"Services"
        }
    ],
    "sg:phone":"+1 760 242 7009",
    "sg:postcode":"92307",
    "sg:province":"CA",
    "sg:tags":[
        "home"
    ],
    "wof:name":"Green Valley Hm Health Svc Inc",
    "wof:placetype":"venue"
},
  "geometry": {"coordinates":[-117.259336,34.539135],"type":"Point"}
}