{
  "type": "Feature",
  "properties": {
    "addr:full":"3299 Bennett Ln Calistoga CA 94515",
    "addr:housenumber":"3299",
    "addr:postcode":"94515",
    "addr:street":"Bennett Ln",
    "iso:country":"US",
    "sg:address":"3299 Bennett Ln",
    "sg:city":"Calistoga",
    "sg:classifiers":[
        {
            "category":"Winery",
            "type":"Food & Drink"
        },
        {
            "category":"Retail",
            "subcategory":"Event Space",
            "type":"Services"
        }
    ],
    "sg:phone":"+1 800 224 4090",
    "sg:postcode":"94515",
    "sg:province":"CA",
    "sg:tags":[
        "venue"
    ],
    "sg:website":"www.atalon.com",
    "wof:name":"Atalon Winery",
    "wof:placetype":"venue"
},
  "geometry": {"coordinates":[-122.611019,38.598802],"type":"Point"}
}