{
  "type": "Feature",
  "properties": {
    "addr:full":"492 9th St Ste 360 Oakland CA 94607",
    "addr:housenumber":"492",
    "addr:postcode":"94607",
    "addr:street":"9Th St Ste 360",
    "iso:country":"US",
    "sg:address":"492 9th St Ste 360",
    "sg:city":"Oakland",
    "sg:classifiers":[
        {
            "category":"Government",
            "subcategory":"Department Of Motor Vehicles",
            "type":"Public Place"
        }
    ],
    "sg:phone":"+1 510 763 5000",
    "sg:postcode":"94607",
    "sg:province":"CA",
    "sg:tags":[
        "service-transportation",
        "permit"
    ],
    "sg:website":"http://www.macro.com",
    "wof:name":"Macro Corporation",
    "wof:placetype":"venue"
},
  "geometry": {"coordinates":[-122.274413,37.801306],"type":"Point"}
}