{
  "type": "Feature",
  "properties": {
    "iso:country":"US",
    "sg:address":"12239 Seal Beach Blvd",
    "sg:city":"Seal Beach",
    "sg:classifiers":[
        {
            "category":"Autos & Motor Vehicles",
            "subcategory":"Auto Supplies",
            "type":"Retail Goods"
        }
    ],
    "sg:phone":"+1 562 430 3548",
    "sg:postcode":"90740",
    "sg:province":"CA",
    "sg:tags":[
        "tire"
    ],
    "sg:website":"www.goodyear.com",
    "wof:name":"Goodyear Tire Centers",
    "wof:placetype":"venue"
},
  "geometry": {"coordinates":[-118.071999,33.784599],"type":"Point"}
}