{
  "type": "Feature",
  "properties": {
    "addr:full":"7929 Emerson Ave Los Angeles CA 90045",
    "addr:housenumber":"7929",
    "addr:postcode":"90045",
    "addr:street":"Emerson Ave",
    "iso:country":"US",
    "sg:address":"7929 Emerson Ave",
    "sg:city":"Los Angeles",
    "sg:classifiers":[
        {
            "category":"Professional",
            "type":"Services"
        }
    ],
    "sg:phone":"+1 310 645 6887",
    "sg:postcode":"90045",
    "sg:province":"CA",
    "wof:name":"Fortunuts",
    "wof:placetype":"venue"
},
  "geometry": {"coordinates":[-118.40714,33.970858],"type":"Point"}
}