{
  "type": "Feature",
  "properties": {
    "iso:country":"US",
    "sg:address":"3183 Collins Dr",
    "sg:city":"Merced",
    "sg:classifiers":[
        {
            "category":"Local Transit",
            "type":"Transportation"
        }
    ],
    "sg:phone":"+1 209 725 7929",
    "sg:postcode":"95348",
    "sg:province":"CA",
    "sg:tags":[
        "limousine"
    ],
    "wof:name":"VIP Limousine",
    "wof:placetype":"venue"
},
  "geometry": {"coordinates":[-120.476484,37.32014],"type":"Point"}
}