{
  "type": "Feature",
  "properties": {
    "addr:full":"704 Houston St West Sacramento CA 95691",
    "addr:housenumber":"704",
    "addr:postcode":"95691",
    "addr:street":"Houston St",
    "iso:country":"US",
    "sg:address":"704 Houston St",
    "sg:city":"West Sacramento",
    "sg:classifiers":[
        {
            "category":"Wholesale",
            "subcategory":"Auto Parts",
            "type":"Manufacturing & Wholesale Goods"
        }
    ],
    "sg:phone":"+1 916 371 3332",
    "sg:postcode":"95691",
    "sg:province":"CA",
    "sg:tags":[
        "shaft",
        "drive"
    ],
    "sg:website":"www.drive-lines.com",
    "wof:name":"Drive Line Svc Of Sacramento",
    "wof:placetype":"venue"
},
  "geometry": {"coordinates":[-121.549919,38.58391],"type":"Point"}
}