{
  "type": "Feature",
  "properties": {
    "addr:full":"4800 Harris Rd Bakersfield CA 93313",
    "addr:housenumber":"4800",
    "addr:postcode":"93313",
    "addr:street":"Harris Rd",
    "iso:country":"US",
    "sg:address":"4800 Harris Rd",
    "sg:city":"Bakersfield",
    "sg:classifiers":[
        {
            "category":"Building & Trades",
            "subcategory":"Construction",
            "type":"Services"
        }
    ],
    "sg:phone":"+1 661 397 9575",
    "sg:postcode":"93313",
    "sg:province":"CA",
    "sg:tags":[
        "steel",
        "erectors"
    ],
    "sg:website":"www.qsbi.com",
    "wof:name":"Quality Steel Builders",
    "wof:placetype":"venue"
},
  "geometry": {"coordinates":[-119.055955,35.303301],"type":"Point"}
}