{
  "type": "Feature",
  "properties": {
    "iso:country":"US",
    "sg:address":"6489 47th St",
    "sg:city":"Sacramento",
    "sg:classifiers":[
        {
            "category":"Organizations",
            "subcategory":"Religious Organization",
            "type":"Services"
        }
    ],
    "sg:phone":"+1 916 422 4962",
    "sg:postcode":"95823",
    "sg:province":"CA",
    "sg:tags":[
        "church"
    ],
    "wof:name":"Pentecost Fellowship Ministrie",
    "wof:placetype":"venue"
},
  "geometry": {"coordinates":[-121.450586,38.508902],"type":"Point"}
}