{
  "type": "Feature",
  "properties": {
    "addr:full":"3126 Spring St Paso Robles CA 93446",
    "addr:housenumber":"3126",
    "addr:postcode":"93446",
    "addr:street":"Spring St",
    "iso:country":"US",
    "sg:address":"3126 Spring St",
    "sg:city":"Paso Robles",
    "sg:classifiers":[
        {
            "category":"Manufacturing",
            "subcategory":"Printing",
            "type":"Manufacturing & Wholesale Goods"
        }
    ],
    "sg:phone":"+1 805 239 1632",
    "sg:postcode":"93446",
    "sg:province":"CA",
    "sg:tags":[
        "printer"
    ],
    "sg:website":"www.slocodata.com",
    "wof:name":"Sloco Data Inc",
    "wof:placetype":"venue"
},
  "geometry": {"coordinates":[-120.69291200000001,35.646164],"type":"Point"}
}