{
  "type": "Feature",
  "properties": {
    "addr:full":"3927 24th St San Francisco CA 94114",
    "addr:housenumber":"3927",
    "addr:postcode":"94114",
    "addr:street":"24Th St",
    "iso:country":"US",
    "sg:address":"3927 24th St",
    "sg:city":"San Francisco",
    "sg:classifiers":[
        {
            "category":"Shopping",
            "subcategory":"Gifts & Souvenirs",
            "type":"Retail Goods"
        }
    ],
    "sg:phone":"+1 415 648 2414",
    "sg:postcode":"94114",
    "sg:province":"CA",
    "sg:tags":[
        "shop"
    ],
    "wof:name":"Panetti's",
    "wof:placetype":"venue"
},
  "geometry": {"coordinates":[-122.431406,37.751397],"type":"Point"}
}