{
  "type": "Feature",
  "properties": {
    "iso:country":"US",
    "sg:address":"10323 Macarthur Blvd",
    "sg:city":"Oakland",
    "sg:classifiers":[
        {
            "category":"Building & Trades",
            "subcategory":"Construction",
            "type":"Services"
        }
    ],
    "sg:phone":"+1 510 562 2154",
    "sg:postcode":"94605",
    "sg:province":"CA",
    "sg:tags":[
        "site",
        "clean"
    ],
    "wof:name":"A Green Shrubbery Svc",
    "wof:placetype":"venue"
},
  "geometry": {"coordinates":[-122.15303900000001,37.743383],"type":"Point"}
}