{
  "type": "Feature",
  "properties": {
    "iso:country":"US",
    "sg:address":"9604 Artesia Blvd Ste 104",
    "sg:city":"Bellflower",
    "sg:classifiers":[
        {
            "category":"Health Services",
            "subcategory":"Doctor",
            "type":"Services"
        }
    ],
    "sg:phone":"+1 562 804 1333",
    "sg:postcode":"90706",
    "sg:province":"CA",
    "wof:name":"Ling Arnold MD",
    "wof:placetype":"venue"
},
  "geometry": {"coordinates":[-118.12894900000001,33.874668],"type":"Point"}
}