{
  "type": "Feature",
  "properties": {
    "addr:full":"8772 Beverly Blvd West Hollywood CA 90048",
    "addr:housenumber":"8772",
    "addr:postcode":"90048",
    "addr:street":"Beverly Blvd",
    "iso:country":"US",
    "sg:address":"8772 Beverly Blvd",
    "sg:city":"West Hollywood",
    "sg:classifiers":[
        {
            "category":"Home & Garden",
            "subcategory":"Furniture",
            "type":"Retail Goods"
        }
    ],
    "sg:phone":"+1 310 289 6868",
    "sg:postcode":"90048",
    "sg:province":"CA",
    "sg:tags":[
        "builder",
        "custom"
    ],
    "wof:name":"Phyllis Morris",
    "wof:placetype":"venue"
},
  "geometry": {"coordinates":[-118.382411,34.076773],"type":"Point"}
}