{
  "type": "Feature",
  "properties": {
    "addr:full":"4200 18th St Ste 203 San Francisco CA 94114",
    "addr:housenumber":"4200",
    "addr:postcode":"94114",
    "addr:street":"18Th St Ste 203",
    "iso:country":"US",
    "sg:address":"4200 18th St Ste 203",
    "sg:city":"San Francisco",
    "sg:classifiers":[
        {
            "category":"Personal",
            "subcategory":"Day Spa",
            "type":"Services"
        }
    ],
    "sg:phone":"+1 415 255 8338",
    "sg:postcode":"94114",
    "sg:province":"CA",
    "wof:name":"Tao Boutique Day Spa",
    "wof:placetype":"venue"
},
  "geometry": {"coordinates":[-122.436142,37.760839],"type":"Point"}
}