{
  "type": "Feature",
  "properties": {
    "iso:country":"US",
    "sg:address":"222 W 6th St",
    "sg:city":"San Pedro",
    "sg:classifiers":[
        {
            "category":"Real Estate",
            "subcategory":"Real Estate Operator",
            "type":"Services"
        }
    ],
    "sg:phone":"+1 310 514 2745",
    "sg:postcode":"90731",
    "sg:province":"CA",
    "sg:tags":[
        "building",
        "parks"
    ],
    "wof:name":"Pacific Place Assoc",
    "wof:placetype":"venue"
},
  "geometry": {"coordinates":[-118.281354,33.738734],"type":"Point"}
}