{
  "type": "Feature",
  "properties": {
    "addr:full":"1308 Gladstone Dr Sacramento CA 95864",
    "addr:housenumber":"1308",
    "addr:postcode":"95864",
    "addr:street":"Gladstone Dr",
    "iso:country":"US",
    "sg:address":"1308 Gladstone Dr",
    "sg:city":"Sacramento",
    "sg:classifiers":[
        {
            "category":"Building & Trades",
            "subcategory":"Construction",
            "type":"Services"
        }
    ],
    "sg:phone":"+1 916 359 6106",
    "sg:postcode":"95864",
    "sg:province":"CA",
    "sg:tags":[
        "wallcoverings-installation",
        "wallpaper",
        "painting",
        "contractor"
    ],
    "wof:name":"Finishing Touch Painting",
    "wof:placetype":"venue"
},
  "geometry": {"coordinates":[-121.386589,38.588609],"type":"Point"}
}