{
  "type": "Feature",
  "properties": {
    "addr:full":"515 Cabrillo Park Dr Santa Ana CA 92701",
    "addr:housenumber":"515",
    "addr:postcode":"92701",
    "addr:street":"Cabrillo Park Dr",
    "iso:country":"US",
    "sg:address":"515 Cabrillo Park Dr",
    "sg:city":"Santa Ana",
    "sg:classifiers":[
        {
            "category":"Shopping",
            "subcategory":"Computers & Home Electronics",
            "type":"Retail Goods"
        }
    ],
    "sg:phone":"+1 714 285 0501",
    "sg:postcode":"92701",
    "sg:province":"CA",
    "sg:tags":[
        "equipment",
        "dealer"
    ],
    "wof:name":"Construction Industry Tchnlgs",
    "wof:placetype":"venue"
},
  "geometry": {"coordinates":[-117.840451,33.748798],"type":"Point"}
}