{
  "type": "Feature",
  "properties": {
    "addr:full":"601 State Hwy 124 Ione CA 95640",
    "addr:housenumber":"601",
    "addr:postcode":"ca 95640",
    "addr:street":"State Hwy 124",
    "iso:country":"US",
    "sg:address":"601 State Hwy 124",
    "sg:city":"Ione",
    "sg:classifiers":[
        {
            "category":"Building & Trades",
            "subcategory":"Construction",
            "type":"Services"
        }
    ],
    "sg:phone":"+1 209 274 2446",
    "sg:postcode":"95640",
    "sg:province":"CA",
    "sg:tags":[
        "excavation",
        "operator",
        "contractor",
        "local",
        "trucking"
    ],
    "wof:name":"Kreth Inc",
    "wof:placetype":"venue"
},
  "geometry": {"coordinates":[-120.932534,38.348326],"type":"Point"}
}