{
  "type": "Feature",
  "properties": {
    "addr:full":"2517 White Ln Bakersfield CA 93304",
    "addr:housenumber":"2517",
    "addr:postcode":"93304",
    "addr:street":"White Ln",
    "iso:country":"US",
    "sg:address":"2517 White Ln",
    "sg:city":"Bakersfield",
    "sg:classifiers":[
        {
            "category":"Retail",
            "subcategory":"Auto Rental",
            "type":"Services"
        }
    ],
    "sg:phone":"+1 661 832 5368",
    "sg:postcode":"93304",
    "sg:province":"CA",
    "sg:tags":[
        "renting",
        "truck",
        "leasing"
    ],
    "wof:name":"U-Haul Co",
    "wof:placetype":"venue"
},
  "geometry": {"coordinates":[-119.030085,35.317672],"type":"Point"}
}