{
  "type": "Feature",
  "properties": {
    "addr:full":"232 N Sutter St Stockton CA 95202",
    "addr:housenumber":"232",
    "addr:postcode":"95202",
    "addr:street":"N Sutter St",
    "iso:country":"US",
    "sg:address":"232 N Sutter St",
    "sg:city":"Stockton",
    "sg:classifiers":[
        {
            "category":"Personal",
            "subcategory":"Barber",
            "type":"Services"
        }
    ],
    "sg:phone":"+1 209 463 5207",
    "sg:postcode":"95202",
    "sg:province":"CA",
    "wof:name":"Sutter Barber Shop",
    "wof:placetype":"venue"
},
  "geometry": {"coordinates":[-121.28653,37.956033],"type":"Point"}
}