{
  "type": "Feature",
  "properties": {
    "iso:country":"US",
    "sg:address":"674 County Square Dr Ste 101",
    "sg:city":"Ventura",
    "sg:classifiers":[
        {
            "category":"Professional",
            "subcategory":"Lawyer & Legal Services",
            "type":"Services"
        }
    ],
    "sg:phone":"+1 805 754 0587",
    "sg:postcode":"93003",
    "sg:province":"CA",
    "sg:tags":[
        "attorney",
        "law",
        "personal",
        "real estate",
        "property"
    ],
    "sg:website":"http://www.nyznyklaw.com",
    "wof:name":"Nyznyk, Richard Anthony Atty At Law",
    "wof:placetype":"venue"
},
  "geometry": {"coordinates":[-119.21493599999999,34.269339],"type":"Point"}
}