{
  "type": "Feature",
  "properties": {
    "addr:full":"2723 8th Street Berkeley CA 94710",
    "addr:housenumber":"2723",
    "addr:postcode":"94710",
    "addr:street":"8Th Street",
    "iso:country":"US",
    "sg:address":"2723 8th Street",
    "sg:city":"Berkeley",
    "sg:classifiers":[
        {
            "category":"Real Estate",
            "subcategory":"Architect",
            "type":"Services"
        }
    ],
    "sg:phone":"+1 510 848 5250",
    "sg:postcode":"94710",
    "sg:province":"CA",
    "wof:name":"Burton Tahara Architects",
    "wof:placetype":"venue"
},
  "geometry": {"coordinates":[-122.292,37.856899],"type":"Point"}
}