{
  "type": "Feature",
  "properties": {
    "addr:full":"12000 Saratoga Sunnyvale Rd Saratoga CA 95070",
    "addr:housenumber":"12000",
    "addr:postcode":"95070",
    "addr:street":"Saratoga Sunnyvale Rd",
    "iso:country":"US",
    "sg:address":"12000 Saratoga Sunnyvale Rd",
    "sg:city":"Saratoga",
    "sg:classifiers":[
        {
            "category":"Banks & Credit Unions",
            "subcategory":"Bank",
            "type":"Services"
        }
    ],
    "sg:phone":"+1 408 973 1111",
    "sg:postcode":"95070",
    "sg:province":"CA",
    "wof:name":"San Jose National Bank",
    "wof:placetype":"venue"
},
  "geometry": {"coordinates":[-122.032264,37.293853],"type":"Point"}
}