{
  "type": "Feature",
  "properties": {
    "iso:country":"US",
    "sg:address":"245 Chandler Ct",
    "sg:city":"Woodland",
    "sg:classifiers":[
        {
            "category":"Building & Trades",
            "subcategory":"Landscaping Services",
            "type":"Services"
        }
    ],
    "sg:phone":"+1 530 666 0114",
    "sg:postcode":"95695",
    "sg:province":"CA",
    "sg:tags":[
        "landscape",
        "contractor"
    ],
    "wof:name":"Woodland Landscaping",
    "wof:placetype":"venue"
},
  "geometry": {"coordinates":[-121.771539,38.690286],"type":"Point"}
}