{
  "type": "Feature",
  "properties": {
    "addr:full":"2241 Alvarado Ave Santa Rosa CA 95404",
    "addr:housenumber":"2241",
    "addr:postcode":"95404",
    "addr:street":"Alvarado Ave",
    "iso:country":"US",
    "sg:address":"2241 Alvarado Ave",
    "sg:city":"Santa Rosa",
    "sg:classifiers":[
        {
            "category":"Wholesale",
            "subcategory":"Home Furnishings",
            "type":"Manufacturing & Wholesale Goods"
        }
    ],
    "sg:phone":"+1 707 579 2220",
    "sg:postcode":"95404",
    "sg:province":"CA",
    "wof:name":"Carpet Brokers",
    "wof:placetype":"venue"
},
  "geometry": {"coordinates":[-122.691231,38.43833],"type":"Point"}
}