{
  "type": "Feature",
  "properties": {
    "addr:full":"200 Pine St San Francisco CA 94104",
    "addr:housenumber":"200",
    "addr:postcode":"94104",
    "addr:street":"Pine St",
    "iso:country":"US",
    "sg:address":"200 Pine St",
    "sg:city":"San Francisco",
    "sg:classifiers":[
        {
            "category":"Organizations",
            "subcategory":"Professional Association",
            "type":"Services"
        }
    ],
    "sg:phone":"+1 415 981 6600",
    "sg:postcode":"94104",
    "sg:province":"CA",
    "sg:tags":[
        "business",
        "trade"
    ],
    "sg:website":"www.bayareacouncil.org",
    "wof:name":"Bay Area Council",
    "wof:placetype":"venue"
},
  "geometry": {"coordinates":[-122.40093299999999,37.792108],"type":"Point"}
}