{
  "type": "Feature",
  "properties": {
    "iso:country":"US",
    "sg:address":"234 S Figueroa St",
    "sg:city":"Los Angeles",
    "sg:classifiers":[
        {
            "category":"Professional",
            "type":"Services"
        }
    ],
    "sg:phone":"+1 213 621 2621",
    "sg:postcode":"90012",
    "sg:province":"CA",
    "wof:name":"Ashley Moffatt Art Consultant",
    "wof:placetype":"venue"
},
  "geometry": {"coordinates":[-118.254024,34.05557],"type":"Point"}
}