{
  "type": "Feature",
  "properties": {
    "addr:full":"640 Janopaul Ln Modesto CA 95351",
    "addr:housenumber":"640",
    "addr:postcode":"ca 95351",
    "addr:street":"Janopaul Ln",
    "iso:country":"US",
    "sg:address":"640 Janopaul Ln",
    "sg:city":"Modesto",
    "sg:classifiers":[
        {
            "category":"Retail",
            "subcategory":"Repair Shop",
            "type":"Services"
        }
    ],
    "sg:phone":"+1 209 544 8219",
    "sg:postcode":"95351",
    "sg:province":"CA",
    "sg:tags":[
        "welding"
    ],
    "wof:name":"Sierra Design & Mfg",
    "wof:placetype":"venue"
},
  "geometry": {"coordinates":[-120.987588,37.618811],"type":"Point"}
}