{
  "type": "Feature",
  "properties": {
    "iso:country":"US",
    "sg:address":"5525 Oakdale Ave",
    "sg:city":"Woodland Hills",
    "sg:classifiers":[
        {
            "category":"Professional",
            "subcategory":"Lawyer & Legal Services",
            "type":"Services"
        }
    ],
    "sg:phone":"+1 818 348 5200",
    "sg:postcode":"91364",
    "sg:province":"CA",
    "wof:name":"Goldberg Steven P ESQ",
    "wof:placetype":"venue"
},
  "geometry": {"coordinates":[-118.566002,34.171001],"type":"Point"}
}