{
  "type": "Feature",
  "properties": {
    "iso:country":"US",
    "sg:address":"7208 Bandini Blvd",
    "sg:city":"Los Angeles",
    "sg:classifiers":[
        {
            "category":"Manufacturing",
            "subcategory":"Paper Products",
            "type":"Manufacturing & Wholesale Goods"
        }
    ],
    "sg:phone":"+1 323 727 1187",
    "sg:postcode":"90040",
    "sg:province":"CA",
    "sg:tags":[
        "converted",
        "mfg"
    ],
    "wof:name":"Eagle Paper Converting",
    "wof:placetype":"venue"
},
  "geometry": {"coordinates":[-118.132957,33.983522],"type":"Point"}
}