{
  "type": "Feature",
  "properties": {
    "addr:full":"1128 Madison Ln Salinas CA 93907",
    "addr:housenumber":"1128",
    "addr:postcode":"93907",
    "addr:street":"Madison Ln",
    "iso:country":"US",
    "sg:address":"1128 Madison Ln",
    "sg:city":"Salinas",
    "sg:classifiers":[
        {
            "category":"Retail",
            "subcategory":"Repair Shop",
            "type":"Services"
        }
    ],
    "sg:phone":"+1 831 422 3279",
    "sg:postcode":"93907",
    "sg:province":"CA",
    "sg:tags":[
        "liquid",
        "sewer",
        "transportation",
        "cleaning",
        "w"
    ],
    "wof:name":"L F & G W Corporation",
    "wof:placetype":"venue"
},
  "geometry": {"coordinates":[-121.67612800000001,36.69369],"type":"Point"}
}