{
  "type": "Feature",
  "properties": {
    "iso:country":"US",
    "sg:address":"2107 W Manchester Ave",
    "sg:city":"Los Angeles",
    "sg:classifiers":[
        {
            "category":"Health Services",
            "subcategory":"Health Practitioner",
            "type":"Services"
        }
    ],
    "sg:phone":"+1 818 891 0799",
    "sg:postcode":"90047",
    "sg:province":"CA",
    "sg:tags":[
        "nurse",
        "registry"
    ],
    "wof:name":"Smiling Nurse Svc",
    "wof:placetype":"venue"
},
  "geometry": {"coordinates":[-118.316002,33.960045],"type":"Point"}
}