{
  "type": "Feature",
  "properties": {
    "addr:full":"3333 Kimber Dr Ste D Newbury Park CA 91320",
    "addr:housenumber":"3333",
    "addr:postcode":"91320",
    "addr:street":"Kimber Dr Ste D",
    "iso:country":"US",
    "sg:address":"3333 Kimber Dr Ste D",
    "sg:city":"Newbury Park",
    "sg:classifiers":[
        {
            "category":"Retail",
            "subcategory":"Veterinary Services",
            "type":"Services"
        }
    ],
    "sg:phone":"+1 805 498 6694",
    "sg:postcode":"91320",
    "sg:province":"CA",
    "sg:tags":[
        "veterinarian"
    ],
    "wof:name":"Midtown Veterinary Clinic",
    "wof:placetype":"venue"
},
  "geometry": {"coordinates":[-118.947998,34.174999],"type":"Point"}
}