{
  "type": "Feature",
  "properties": {
    "addr:full":"2490 Callender Rd Arroyo Grande CA 93420",
    "addr:postcode":"2490;93420",
    "addr:street":"Callender Rd",
    "iso:country":"US",
    "sg:address":"2490 Callender Rd",
    "sg:city":"Arroyo Grande",
    "sg:classifiers":[
        {
            "category":"Wholesale",
            "subcategory":"Plants",
            "type":"Manufacturing & Wholesale Goods"
        }
    ],
    "sg:phone":"+1 805 343 1285",
    "sg:postcode":"93420",
    "sg:province":"CA",
    "sg:tags":[
        "nursery",
        "tree"
    ],
    "wof:name":"Mesa Magic Nursery",
    "wof:placetype":"venue"
},
  "geometry": {"coordinates":[-120.59127100000001,35.054565],"type":"Point"}
}