{
  "type": "Feature",
  "properties": {
    "addr:full":"5329 San Pablo Dam Rd El Sobrante CA 94803",
    "addr:housenumber":"5329",
    "addr:postcode":"94803",
    "addr:street":"San Pablo Dam Rd",
    "iso:country":"US",
    "sg:address":"5329 San Pablo Dam Rd",
    "sg:city":"El Sobrante",
    "sg:classifiers":[
        {
            "category":"Restaurant",
            "type":"Food & Drink"
        }
    ],
    "sg:phone":"+1 510 758 0189",
    "sg:postcode":"94803",
    "sg:province":"CA",
    "wof:name":"Subway Sandwiches & Salads",
    "wof:placetype":"venue"
},
  "geometry": {"coordinates":[-122.283506,37.960359],"type":"Point"}
}