{
  "type": "Feature",
  "properties": {
    "iso:country":"US",
    "sg:address":"869 Rose Blossom Dr",
    "sg:city":"Cupertino",
    "sg:classifiers":[
        {
            "category":"Wholesale",
            "subcategory":"Wine & Distilled Alcoholic Beverages",
            "type":"Manufacturing & Wholesale Goods"
        }
    ],
    "sg:phone":"+1 408 973 1638",
    "sg:postcode":"95014",
    "sg:province":"CA",
    "wof:name":"United Distillers Usa Inc",
    "wof:placetype":"venue"
},
  "geometry": {"coordinates":[-122.044001,37.314192],"type":"Point"}
}