{
  "type": "Feature",
  "properties": {
    "addr:full":"532 8th St Oakland CA 94607",
    "addr:housenumber":"532",
    "addr:postcode":"94607",
    "addr:street":"8Th St",
    "iso:country":"US",
    "sg:address":"532 8th St",
    "sg:city":"Oakland",
    "sg:classifiers":[
        {
            "category":"Organizations",
            "subcategory":"Religious Organization",
            "type":"Services"
        }
    ],
    "sg:phone":"+1 510 893 1369",
    "sg:postcode":"94607",
    "sg:province":"CA",
    "wof:name":"Chinese Christian Herald Crusades",
    "wof:placetype":"venue"
},
  "geometry": {"coordinates":[-122.27578,37.800976],"type":"Point"}
}