{
  "type": "Feature",
  "properties": {
    "addr:full":"2041 Saybrook Ave Los Angeles CA 90040",
    "addr:housenumber":"2041",
    "addr:postcode":"90040",
    "addr:street":"Saybrook Ave",
    "iso:country":"US",
    "sg:address":"2041 Saybrook Ave",
    "sg:city":"Los Angeles",
    "sg:classifiers":[
        {
            "category":"Wholesale",
            "subcategory":"Machinery & Supplies",
            "type":"Manufacturing & Wholesale Goods"
        }
    ],
    "sg:phone":"+1 323 728 0281",
    "sg:postcode":"90040",
    "sg:province":"CA",
    "sg:tags":[
        "bearing"
    ],
    "sg:website":"www.motionmro.com",
    "wof:name":"Motion Industries Inc",
    "wof:placetype":"venue"
},
  "geometry": {"coordinates":[-118.13742999999999,34.00588],"type":"Point"}
}