{
  "type": "Feature",
  "properties": {
    "addr:full":"1049 4th Ave Chula Vista CA 91911",
    "addr:housenumber":"1049",
    "addr:postcode":"91911",
    "addr:street":"4Th Ave",
    "iso:country":"US",
    "sg:address":"1049 4th Ave",
    "sg:city":"Chula Vista",
    "sg:classifiers":[
        {
            "category":"Real Estate",
            "subcategory":"Real Estate Operator",
            "type":"Services"
        }
    ],
    "sg:phone":"+1 619 585 0852",
    "sg:postcode":"91911",
    "sg:province":"CA",
    "sg:tags":[
        "apartment"
    ],
    "wof:name":"South Bay Manor Apartments",
    "wof:placetype":"venue"
},
  "geometry": {"coordinates":[-117.07399700000001,32.614498],"type":"Point"}
}