{
  "type": "Feature",
  "properties": {
    "iso:country":"US",
    "sg:address":"38585 Rd 36",
    "sg:city":"Kingsburg",
    "sg:classifiers":[
        {
            "category":"Professional",
            "subcategory":"Business Services",
            "type":"Services"
        }
    ],
    "sg:phone":"+1 559 859 7421",
    "sg:postcode":"93631",
    "sg:province":"CA",
    "sg:tags":[
        "notary"
    ],
    "wof:name":"On The Go Notary",
    "wof:placetype":"venue"
},
  "geometry": {"coordinates":[-119.493889,36.495226],"type":"Point"}
}