{
  "type": "Feature",
  "properties": {
    "iso:country":"US",
    "sg:address":"1601 Broadway St",
    "sg:city":"Eureka",
    "sg:classifiers":[
        {
            "category":"Retail",
            "subcategory":"Repair Shop",
            "type":"Services"
        }
    ],
    "sg:phone":"+1 707 445 3093",
    "sg:postcode":"95501",
    "sg:province":"CA",
    "sg:tags":[
        "scooter",
        "motorcycle",
        "motor"
    ],
    "wof:name":"Eureka Motor Sports Ctr",
    "wof:placetype":"venue"
},
  "geometry": {"coordinates":[-124.17756199999999,40.79287],"type":"Point"}
}