{
  "type": "Feature",
  "properties": {
    "iso:country":"US",
    "sg:address":"3657 Mission St",
    "sg:city":"San Francisco",
    "sg:classifiers":[
        {
            "category":"Wholesale",
            "subcategory":"Machinery & Supplies",
            "type":"Manufacturing & Wholesale Goods"
        }
    ],
    "sg:phone":"+1 415 285 3792",
    "sg:postcode":"94110",
    "sg:province":"CA",
    "sg:tags":[
        "janitor"
    ],
    "wof:name":"Andrew's Janitorial Equipment",
    "wof:placetype":"venue"
},
  "geometry": {"coordinates":[-122.423938,37.737813],"type":"Point"}
}