{
  "type": "Feature",
  "properties": {
    "addr:full":"2519 W Shaw Ave Fresno CA 93711",
    "addr:housenumber":"2519",
    "addr:postcode":"93711",
    "addr:street":"W Shaw Ave",
    "iso:country":"US",
    "sg:address":"2519 W Shaw Ave",
    "sg:city":"Fresno",
    "sg:classifiers":[
        {
            "category":"Insurance",
            "subcategory":"Insurance Agent",
            "type":"Services"
        }
    ],
    "sg:phone":"+1 559 224 9300",
    "sg:postcode":"93711",
    "sg:province":"CA",
    "wof:name":"Cobb Insurance Svc",
    "wof:placetype":"venue"
},
  "geometry": {"coordinates":[-119.83791100000001,36.808221],"type":"Point"}
}