{
  "type": "Feature",
  "properties": {
    "iso:country":"US",
    "sg:address":"12107 Piuma Ave",
    "sg:city":"Norwalk",
    "sg:classifiers":[
        {
            "category":"Government",
            "subcategory":"Office",
            "type":"Public Place"
        }
    ],
    "sg:phone":"+1 562 929 6139",
    "sg:postcode":"90650",
    "sg:province":"CA",
    "sg:tags":[
        "township",
        "government-city",
        "village"
    ],
    "wof:name":"Vega On Town",
    "wof:placetype":"venue"
},
  "geometry": {"coordinates":[-118.105499,33.922523],"type":"Point"}
}