{
  "type": "Feature",
  "properties": {
    "addr:full":"11533 W Pico Blvd Los Angeles CA 90064",
    "addr:housenumber":"11533",
    "addr:postcode":"90064",
    "addr:street":"W Pico Blvd",
    "iso:country":"US",
    "sg:address":"11533 W Pico Blvd",
    "sg:city":"Los Angeles",
    "sg:classifiers":[
        {
            "category":"Education",
            "subcategory":"Dance Studio",
            "type":"Public Place"
        }
    ],
    "sg:phone":"+1 310 478 7866",
    "sg:postcode":"90064",
    "sg:province":"CA",
    "sg:tags":[
        "instruction",
        "dancing"
    ],
    "wof:name":"Cafe Danssa",
    "wof:placetype":"venue"
},
  "geometry": {"coordinates":[-118.44306899999999,34.033118],"type":"Point"}
}