{
  "type": "Feature",
  "properties": {
    "addr:full":"22781 San Joaquin Dr E Canyon Lake CA 92587",
    "addr:housenumber":"22781",
    "addr:postcode":"92587",
    "addr:street":"San Joaquin Dr E",
    "iso:country":"US",
    "sg:address":"22781 San Joaquin Dr E",
    "sg:city":"Canyon Lake",
    "sg:classifiers":[
        {
            "category":"Manufacturing",
            "subcategory":"Signs",
            "type":"Manufacturing & Wholesale Goods"
        }
    ],
    "sg:phone":"+1 951 244 8676",
    "sg:postcode":"92587",
    "sg:province":"CA",
    "wof:name":"All Signs Graphics & Designs",
    "wof:placetype":"venue"
},
  "geometry": {"coordinates":[-117.262199,33.69737],"type":"Point"}
}