{
  "type": "Feature",
  "properties": {
    "addr:full":"1480 W San Carlos St San Jose CA 95110",
    "addr:housenumber":"1480",
    "addr:postcode":"95110",
    "addr:street":"W San Carlos St",
    "iso:country":"US",
    "sg:address":"1480 W San Carlos St",
    "sg:city":"San Jose",
    "sg:classifiers":[
        {
            "category":"Autos & Motor Vehicles",
            "subcategory":"Automobile Sales",
            "type":"Retail Goods"
        }
    ],
    "sg:phone":"+1 408 286 2500",
    "sg:postcode":"95110",
    "sg:province":"CA",
    "sg:tags":[
        "car",
        "dealer"
    ],
    "wof:name":"Top Notch Auto Sales",
    "wof:placetype":"venue"
},
  "geometry": {"coordinates":[-121.915496,37.323479],"type":"Point"}
}