{
  "type": "Feature",
  "properties": {
    "iso:country":"US",
    "sg:address":"1520 Lakeside Dr",
    "sg:city":"Oakland",
    "sg:classifiers":[
        {
            "category":"Restaurant",
            "type":"Food & Drink"
        }
    ],
    "sg:phone":"+1 510 208 5253",
    "sg:postcode":"94612",
    "sg:province":"CA",
    "sg:tags":[
        "new",
        "seafood",
        "american"
    ],
    "sg:website":"www.thelakechalet.com",
    "wof:name":"Lake Chalet Seafood Bar and Grill",
    "wof:placetype":"venue"
},
  "geometry": {"coordinates":[-122.26153600000001,37.803179],"type":"Point"}
}