{
  "type": "Feature",
  "properties": {
    "addr:full":"7326 Jordan Ave Canoga Park CA 91303",
    "addr:housenumber":"7326",
    "addr:postcode":"91303",
    "addr:street":"Jordan Ave",
    "iso:country":"US",
    "sg:address":"7326 Jordan Ave",
    "sg:city":"Canoga Park",
    "sg:classifiers":[
        {
            "category":"Park",
            "type":"Public Place"
        }
    ],
    "sg:phone":"+1 818 340 2633",
    "sg:postcode":"91303",
    "sg:province":"CA",
    "wof:name":"Canoga Park",
    "wof:placetype":"venue"
},
  "geometry": {"coordinates":[-118.602997,34.2033],"type":"Point"}
}