{
  "type": "Feature",
  "properties": {
    "iso:country":"US",
    "sg:address":"5332 Maui Way",
    "sg:city":"Fair Oaks",
    "sg:classifiers":[
        {
            "category":"Professional",
            "subcategory":"Accounting & Tax Preparation",
            "type":"Services"
        }
    ],
    "sg:phone":"+1 916 863 7221",
    "sg:postcode":"95628",
    "sg:province":"CA",
    "sg:tags":[
        "bookkeeping",
        "general"
    ],
    "wof:name":"Fair Oaks Bookkeeping",
    "wof:placetype":"venue"
},
  "geometry": {"coordinates":[-121.256377,38.661993],"type":"Point"}
}