{
  "type": "Feature",
  "properties": {
    "iso:country":"US",
    "sg:address":"5600 Folsom Blvd",
    "sg:city":"Sacramento",
    "sg:classifiers":[
        {
            "category":"Food & Beverages",
            "subcategory":"Groceries & Convenience Stores",
            "type":"Retail Goods"
        }
    ],
    "sg:phone":"+1 916 456 3862",
    "sg:postcode":"95857",
    "sg:province":"CA",
    "sg:website":"www.savemart.com/",
    "wof:name":"Save Mart Supermarkets",
    "wof:placetype":"venue"
},
  "geometry": {"coordinates":[-121.43825200000001,38.558528],"type":"Point"}
}