{
  "type": "Feature",
  "properties": {
    "addr:full":"191 Rankin St San Francisco CA 94124",
    "addr:housenumber":"191",
    "addr:postcode":"94124",
    "addr:street":"Rankin St",
    "iso:country":"US",
    "sg:address":"191 Rankin St",
    "sg:city":"San Francisco",
    "sg:classifiers":[
        {
            "category":"Manufacturing",
            "subcategory":"Paper Products",
            "type":"Manufacturing & Wholesale Goods"
        }
    ],
    "sg:phone":"+1 415 282 4291",
    "sg:postcode":"94124",
    "sg:province":"CA",
    "sg:tags":[
        "manufacture",
        "exhibit",
        "display"
    ],
    "sg:website":"www.sanfordexhibits.com",
    "wof:name":"Sanford Exhibits Inc",
    "wof:placetype":"venue"
},
  "geometry": {"coordinates":[-122.391149,37.746268],"type":"Point"}
}