{
  "type": "Feature",
  "properties": {
    "iso:country":"US",
    "sg:address":"758 Pacific Ave",
    "sg:city":"San Francisco",
    "sg:classifiers":[
        {
            "category":"Restaurant",
            "type":"Food & Drink"
        }
    ],
    "sg:phone":"+1 415 956 8533",
    "sg:postcode":"94133",
    "sg:province":"CA",
    "wof:name":"Golden Kimtar",
    "wof:placetype":"venue"
},
  "geometry": {"coordinates":[-122.40828500000001,37.796803],"type":"Point"}
}