{
  "type": "Feature",
  "properties": {
    "addr:full":"3746 McCall Ave Selma CA 93662",
    "addr:housenumber":"3746",
    "addr:postcode":"93662",
    "addr:street":"Mccall Ave",
    "iso:country":"US",
    "sg:address":"3746 McCall Ave",
    "sg:city":"Selma",
    "sg:classifiers":[
        {
            "category":"Food & Beverages",
            "subcategory":"Liquor & Beverages",
            "type":"Retail Goods"
        }
    ],
    "sg:phone":"+1 559 896 1170",
    "sg:postcode":"93662",
    "sg:province":"CA",
    "wof:name":"Liquor Locker",
    "wof:placetype":"venue"
},
  "geometry": {"coordinates":[-119.610536,36.589166],"type":"Point"}
}