{
  "type": "Feature",
  "properties": {
    "addr:full":"7854 Cll Juela La Jolla CA 92037",
    "addr:housenumber":"7854",
    "addr:postcode":"92037",
    "addr:street":"Cll Juela",
    "iso:country":"US",
    "sg:address":"7854 Cll Juela",
    "sg:city":"La Jolla",
    "sg:classifiers":[
        {
            "category":"Shopping",
            "subcategory":"Clothing, Apparel, & Fashions",
            "type":"Retail Goods"
        }
    ],
    "sg:phone":"+1 858 551 4226",
    "sg:postcode":"92037",
    "sg:province":"CA",
    "wof:name":"Melange",
    "wof:placetype":"venue"
},
  "geometry": {"coordinates":[-117.25506300000001,32.849839],"type":"Point"}
}