{
  "type": "Feature",
  "properties": {
    "addr:full":"1648 Tully Road San Jose CA 95122",
    "addr:housenumber":"1648",
    "addr:postcode":"95122",
    "addr:street":"Tully Road",
    "iso:country":"US",
    "sg:address":"1648 Tully Road",
    "sg:city":"San Jose",
    "sg:classifiers":[
        {
            "category":"Banks & Credit Unions",
            "subcategory":"Bank",
            "type":"Services"
        }
    ],
    "sg:phone":"+1 408 270 1500",
    "sg:postcode":"95122",
    "sg:province":"CA",
    "wof:name":"The Summit National Bank",
    "wof:placetype":"venue"
},
  "geometry": {"coordinates":[-121.831918,37.323352],"type":"Point"}
}