{
  "type": "Feature",
  "properties": {
    "addr:full":"4896 Highview St Chino Hills CA 91709",
    "addr:housenumber":"4896",
    "addr:postcode":"91709",
    "addr:street":"Highview St",
    "iso:country":"US",
    "sg:address":"4896 Highview St",
    "sg:city":"Chino Hills",
    "sg:classifiers":[
        {
            "category":"Real Estate",
            "subcategory":"Real Estate Agent",
            "type":"Services"
        }
    ],
    "sg:phone":"+1 909 606 0894",
    "sg:postcode":"91709",
    "sg:province":"CA",
    "wof:name":"Keller Williams Real Estate",
    "wof:placetype":"venue"
},
  "geometry": {"coordinates":[-117.694833,33.947802],"type":"Point"}
}