{
  "type": "Feature",
  "properties": {
    "addr:full":"6333 Wilshire Boulevard Suite 300 Los Angeles CA 90048",
    "addr:housenumber":"6333",
    "addr:postcode":"90048",
    "addr:street":"Wilshire Boulevard Suite 300",
    "iso:country":"US",
    "sg:address":"6333 Wilshire Boulevard Suite 300",
    "sg:city":"Los Angeles",
    "sg:classifiers":[
        {
            "category":"Health Services",
            "subcategory":"Dentist",
            "type":"Services"
        }
    ],
    "sg:phone":"+1 323 653 6672",
    "sg:postcode":"90048",
    "sg:province":"CA",
    "wof:name":"Noris Ann DDS",
    "wof:placetype":"venue"
},
  "geometry": {"coordinates":[-118.366308,34.063563],"type":"Point"}
}