{
  "type": "Feature",
  "properties": {
    "iso:country":"US",
    "sg:address":"530 University Ave",
    "sg:city":"Palo Alto",
    "sg:classifiers":[
        {
            "category":"Personal",
            "subcategory":"Beauty Salon",
            "type":"Services"
        }
    ],
    "sg:phone":"+1 650 321 8117",
    "sg:postcode":"94301",
    "sg:province":"CA",
    "wof:name":"Aroma Skin & Laser Ctr",
    "wof:placetype":"venue"
},
  "geometry": {"coordinates":[-122.159077,37.448292],"type":"Point"}
}