{
  "type": "Feature",
  "properties": {
    "addr:full":"2200 McClure Subdivision Rd Ukiah CA 95482",
    "addr:housenumber":"2200",
    "addr:postcode":"ca 95482",
    "addr:street":"Mcclure Subdivision Rd",
    "iso:country":"US",
    "sg:address":"2200 McClure Subdivision Rd",
    "sg:city":"Ukiah",
    "sg:classifiers":[
        {
            "category":"Professional",
            "type":"Services"
        }
    ],
    "sg:phone":"+1 707 462 7346",
    "sg:postcode":"95482",
    "sg:province":"CA",
    "wof:name":"Carroll Benjamin Kohler",
    "wof:placetype":"venue"
},
  "geometry": {"coordinates":[-123.16128,39.138985],"type":"Point"}
}