{
  "type": "Feature",
  "properties": {
    "addr:full":"5850 Gloria Way Livermore CA 94550",
    "addr:housenumber":"5850",
    "addr:postcode":"94550",
    "addr:street":"Gloria Way",
    "iso:country":"US",
    "sg:address":"5850 Gloria Way",
    "sg:city":"Livermore",
    "sg:classifiers":[
        {
            "category":"Insurance",
            "subcategory":"Insurance Agent",
            "type":"Services"
        }
    ],
    "sg:phone":"+1 925 373 3273",
    "sg:postcode":"94550",
    "sg:province":"CA",
    "wof:name":"Blue Shield Of California",
    "wof:placetype":"venue"
},
  "geometry": {"coordinates":[-121.720737,37.685617],"type":"Point"}
}