{
  "type": "Feature",
  "properties": {
    "iso:country":"US",
    "sg:address":"887 57th St #B",
    "sg:city":"Sacramento",
    "sg:classifiers":[
        {
            "category":"Sports & Exercise",
            "subcategory":"Gym",
            "type":"Entertainment"
        }
    ],
    "sg:phone":"+1 916 383 7933",
    "sg:postcode":"95816",
    "sg:province":"CA",
    "sg:tags":[
        "yoga"
    ],
    "sg:website":"theyogasolution.net",
    "wof:name":"The Yoga Solution",
    "wof:placetype":"venue"
},
  "geometry": {"coordinates":[-121.433339,38.565609],"type":"Point"}
}