{
  "type": "Feature",
  "properties": {
    "addr:full":"611 E Main St Santa Maria CA 93454",
    "addr:housenumber":"611",
    "addr:postcode":"93454",
    "addr:street":"E Main St",
    "iso:country":"US",
    "sg:address":"611 E Main St",
    "sg:city":"Santa Maria",
    "sg:classifiers":[
        {
            "category":"Home & Garden",
            "subcategory":"Household Appliances",
            "type":"Retail Goods"
        }
    ],
    "sg:phone":"+1 805 925 7616",
    "sg:postcode":"93454",
    "sg:province":"CA",
    "sg:website":"www.keesappliance.com",
    "wof:name":"Kee's Appliances Inc",
    "wof:placetype":"venue"
},
  "geometry": {"coordinates":[-120.425872,34.953263],"type":"Point"}
}