{
  "type": "Feature",
  "properties": {
    "addr:full":"1328 22nd St Santa Monica CA 90404",
    "addr:housenumber":"1328",
    "addr:postcode":"90404",
    "addr:street":"22Nd St",
    "iso:country":"US",
    "sg:address":"1328 22nd St",
    "sg:city":"Santa Monica",
    "sg:classifiers":[
        {
            "category":"Organizations",
            "subcategory":"Non-profit Organization",
            "type":"Services"
        }
    ],
    "sg:phone":"+1 310 829 8905",
    "sg:postcode":"90404",
    "sg:province":"CA",
    "sg:tags":[
        "information",
        "alcoholism",
        "treatment"
    ],
    "wof:name":"St John's Chem Dependency Ctr",
    "wof:placetype":"venue"
},
  "geometry": {"coordinates":[-118.479592,34.03104],"type":"Point"}
}