{
  "type": "Feature",
  "properties": {
    "addr:full":"5804 E Slauson Ave Los Angeles CA 90040",
    "addr:housenumber":"5804",
    "addr:postcode":"90040",
    "addr:street":"E Slauson Ave",
    "iso:country":"US",
    "sg:address":"5804 E Slauson Ave",
    "sg:city":"Los Angeles",
    "sg:classifiers":[
        {
            "category":"Manufacturing",
            "subcategory":"Apparel",
            "type":"Manufacturing & Wholesale Goods"
        }
    ],
    "sg:phone":"+1 323 725 5516",
    "sg:postcode":"90040",
    "sg:province":"CA",
    "sg:tags":[
        "design",
        "mfg"
    ],
    "wof:name":"Innovo Group Inc",
    "wof:placetype":"venue"
},
  "geometry": {"coordinates":[-118.158446,33.985453],"type":"Point"}
}