{
  "type": "Feature",
  "properties": {
    "addr:full":"2537 Malone Pl Santa Clara CA 95050",
    "addr:housenumber":"2537",
    "addr:postcode":"95050",
    "addr:street":"Malone Pl",
    "iso:country":"US",
    "sg:address":"2537 Malone Pl",
    "sg:city":"Santa Clara",
    "sg:classifiers":[
        {
            "category":"Real Estate",
            "subcategory":"Real Estate Agent",
            "type":"Services"
        }
    ],
    "sg:phone":"+1 408 984 7470",
    "sg:postcode":"95050",
    "sg:province":"CA",
    "wof:name":"Michael Bell Enterprises",
    "wof:placetype":"venue"
},
  "geometry": {"coordinates":[-121.967941,37.337961],"type":"Point"}
}