{
  "type": "Feature",
  "properties": {
    "addr:full":"601 Capitola Ave Capitola CA 95010",
    "addr:housenumber":"601",
    "addr:postcode":"95010",
    "addr:street":"Capitola Ave",
    "iso:country":"US",
    "sg:address":"601 Capitola Ave",
    "sg:city":"Capitola",
    "sg:classifiers":[
        {
            "category":"Real Estate",
            "subcategory":"Real Estate Agent",
            "type":"Services"
        }
    ],
    "sg:phone":"+1 831 462 3366",
    "sg:postcode":"95010",
    "sg:province":"CA",
    "wof:name":"Don M Stewart Real Estate",
    "wof:placetype":"venue"
},
  "geometry": {"coordinates":[-121.95317799999999,36.978449],"type":"Point"}
}