{
  "type": "Feature",
  "properties": {
    "iso:country":"US",
    "sg:address":"824 S Mountain Ave",
    "sg:city":"Ontario",
    "sg:classifiers":[
        {
            "category":"Cinema",
            "subcategory":"Movie Rental",
            "type":"Entertainment"
        }
    ],
    "sg:phone":"+1 909 986 4888",
    "sg:postcode":"91762",
    "sg:province":"CA",
    "sg:tags":[
        "leasing",
        "video",
        "disc",
        "tape"
    ],
    "wof:name":"Video Plus",
    "wof:placetype":"venue"
},
  "geometry": {"coordinates":[-117.66992399999999,34.054716],"type":"Point"}
}