{
  "type": "Feature",
  "properties": {
    "addr:full":"917 Sunset Dr Antioch CA 94509",
    "addr:housenumber":"917",
    "addr:postcode":"ca 94509",
    "addr:street":"Sunset Dr",
    "iso:country":"US",
    "sg:address":"917 Sunset Dr",
    "sg:city":"Antioch",
    "sg:classifiers":[
        {
            "category":"Manufacturing",
            "subcategory":"Tools & Machinery",
            "type":"Manufacturing & Wholesale Goods"
        }
    ],
    "sg:phone":"+1 925 706 1507",
    "sg:postcode":"94509",
    "sg:province":"CA",
    "sg:tags":[
        "machine",
        "shop",
        "industrial",
        "mfg"
    ],
    "wof:name":"Genesis Tool & Die & Mfg Co",
    "wof:placetype":"venue"
},
  "geometry": {"coordinates":[-121.790603,37.997676],"type":"Point"}
}