{
  "type": "Feature",
  "properties": {
    "iso:country":"US",
    "sg:address":"5517 Guadalupe Ct",
    "sg:city":"Concord",
    "sg:classifiers":[
        {
            "category":"Travel",
            "subcategory":"Travel Agent",
            "type":"Entertainment"
        }
    ],
    "sg:phone":"+1 925 672 5605",
    "sg:postcode":"94521",
    "sg:province":"CA",
    "sg:tags":[
        "agency"
    ],
    "wof:name":"Walnut Crek Uniglob Travel",
    "wof:placetype":"venue"
},
  "geometry": {"coordinates":[-121.94777499999999,37.952305],"type":"Point"}
}