{
  "type": "Feature",
  "properties": {
    "addr:full":"931 Howe Ave Sacramento CA 95825",
    "addr:housenumber":"931",
    "addr:postcode":"95825",
    "addr:street":"Howe Ave",
    "iso:country":"US",
    "sg:address":"931 Howe Ave",
    "sg:city":"Sacramento",
    "sg:classifiers":[
        {
            "category":"Farming",
            "subcategory":"Farm & Veterinary Services",
            "type":"Manufacturing & Wholesale Goods"
        }
    ],
    "sg:phone":"+1 530 622 2835",
    "sg:postcode":"95825",
    "sg:province":"CA",
    "sg:tags":[
        "management",
        "beef",
        "feedlot",
        "cattle"
    ],
    "wof:name":"Bacchi Valley Industries",
    "wof:placetype":"venue"
},
  "geometry": {"coordinates":[-121.415396,38.584595],"type":"Point"}
}