{
  "type": "Feature",
  "properties": {
    "addr:full":"3613 State St Santa Barbara CA 93105",
    "addr:housenumber":"3613",
    "addr:postcode":"93105",
    "addr:street":"State St",
    "iso:country":"US",
    "sg:address":"3613 State St",
    "sg:city":"Santa Barbara",
    "sg:classifiers":[
        {
            "category":"Restaurant",
            "type":"Food & Drink"
        }
    ],
    "sg:menulink":"http://www.allmenus.com/ca/santa-barbara/150489-subway/menu/",
    "sg:phone":"+1 805 682 1921",
    "sg:postcode":"93105",
    "sg:province":"CA",
    "sg:tags":[
        "american",
        "sandwich"
    ],
    "wof:name":"Subway",
    "wof:placetype":"venue"
},
  "geometry": {"coordinates":[-119.740864,34.440388],"type":"Point"}
}