{
  "type": "Feature",
  "properties": {
    "addr:full":"Roosevelt Ave & Allston Way Berkeley CA 94703",
    "addr:postcode":"94703",
    "addr:street":"Roosevelt Ave & Allston Way",
    "iso:country":"US",
    "sg:address":"Roosevelt Ave & Allston Way",
    "sg:city":"Berkeley",
    "sg:classifiers":[
        {
            "category":"Education",
            "subcategory":"Special Training",
            "type":"Public Place"
        }
    ],
    "sg:phone":"+1 510 435 7183",
    "sg:postcode":"94703",
    "sg:province":"CA",
    "sg:tags":[
        "tutoring"
    ],
    "wof:name":"Your French Center",
    "wof:placetype":"venue"
},
  "geometry": {"coordinates":[-122.276095,37.868351],"type":"Point"}
}