{
  "type": "Feature",
  "properties": {
    "iso:country":"US",
    "sg:address":"2525 Dominic Dr",
    "sg:city":"Chico",
    "sg:classifiers":[
        {
            "category":"Education",
            "subcategory":"Special Training",
            "type":"Public Place"
        }
    ],
    "sg:phone":"+1 530 345 1199",
    "sg:postcode":"95928",
    "sg:province":"CA",
    "sg:tags":[
        "instruction",
        "driving"
    ],
    "wof:name":"A Top Driver School",
    "wof:placetype":"venue"
},
  "geometry": {"coordinates":[-121.788118,39.713866],"type":"Point"}
}