{
  "type": "Feature",
  "properties": {
    "iso:country":"US",
    "sg:address":"1032 Ticonderoga Dr",
    "sg:city":"Sunnyvale",
    "sg:classifiers":[
        {
            "category":"Shopping",
            "subcategory":"Pharmacy",
            "type":"Retail Goods"
        }
    ],
    "sg:phone":"+1 408 735 0915",
    "sg:postcode":"94087",
    "sg:province":"CA",
    "wof:name":"Santa Clara County Pharmacists",
    "wof:placetype":"venue"
},
  "geometry": {"coordinates":[-122.056187,37.354396],"type":"Point"}
}