{
  "type": "Feature",
  "properties": {
    "iso:country":"US",
    "sg:address":"150 W Gabilan St",
    "sg:city":"Salinas",
    "sg:classifiers":[
        {
            "category":"Professional",
            "subcategory":"Lawyer & Legal Services",
            "type":"Services"
        }
    ],
    "sg:phone":"+1 831 373 4338",
    "sg:postcode":"93901",
    "sg:province":"CA",
    "sg:tags":[
        "attorney"
    ],
    "wof:name":"Mel Grimes Jr",
    "wof:placetype":"venue"
},
  "geometry": {"coordinates":[-121.660081,36.67506],"type":"Point"}
}