{
  "type": "Feature",
  "properties": {
    "addr:full":"17391 Lido Ln Huntington Beach CA 92647",
    "addr:postcode":"17391;92647",
    "addr:street":"Lido Ln",
    "iso:country":"US",
    "sg:address":"17391 Lido Ln",
    "sg:city":"Huntington Beach",
    "sg:classifiers":[
        {
            "category":"Wholesale",
            "subcategory":"Home Furnishings",
            "type":"Manufacturing & Wholesale Goods"
        }
    ],
    "sg:phone":"+1 714 847 1831",
    "sg:postcode":"92647",
    "sg:province":"CA",
    "wof:name":"Debi Wise",
    "wof:placetype":"venue"
},
  "geometry": {"coordinates":[-118.01875200000001,33.708693],"type":"Point"}
}