{
  "type": "Feature",
  "properties": {
    "addr:full":"840 11th St Paso Robles CA 93446",
    "addr:housenumber":"840",
    "addr:postcode":"93446",
    "addr:street":"11Th St",
    "iso:country":"US",
    "sg:address":"840 11th St",
    "sg:city":"Paso Robles",
    "sg:classifiers":[
        {
            "category":"Personal",
            "subcategory":"Barber",
            "type":"Services"
        }
    ],
    "sg:phone":"+1 805 238 0280",
    "sg:postcode":"93446",
    "sg:province":"CA",
    "wof:name":"Continental Barber Shop",
    "wof:placetype":"venue"
},
  "geometry": {"coordinates":[-120.68868399999999,35.625847],"type":"Point"}
}