{
  "type": "Feature",
  "properties": {
    "iso:country":"US",
    "sg:address":"2615 Marine Ave",
    "sg:city":"Gardena",
    "sg:classifiers":[
        {
            "category":"Health Services",
            "subcategory":"Health Practitioner",
            "type":"Services"
        }
    ],
    "sg:phone":"+1 310 538 8881",
    "sg:postcode":"90249",
    "sg:province":"CA",
    "sg:tags":[
        "acupuncture"
    ],
    "wof:name":"Ling's Acupuncture & Herbs",
    "wof:placetype":"venue"
},
  "geometry": {"coordinates":[-118.32199900000001,33.8946],"type":"Point"}
}