{
  "type": "Feature",
  "properties": {
    "addr:full":"451 Montgomery St San Francisco CA 94104",
    "addr:housenumber":"451",
    "addr:postcode":"94104",
    "addr:street":"Montgomery St",
    "iso:country":"US",
    "sg:address":"451 Montgomery St",
    "sg:city":"San Francisco",
    "sg:classifiers":[
        {
            "category":"Banks & Credit Unions",
            "subcategory":"Financial Services",
            "type":"Services"
        }
    ],
    "sg:phone":"+1 415 441 2580",
    "sg:postcode":"94104",
    "sg:province":"CA",
    "sg:tags":[
        "venture",
        "capitalist"
    ],
    "wof:name":"Dan Corp",
    "wof:placetype":"venue"
},
  "geometry": {"coordinates":[-122.40295399999999,37.793294],"type":"Point"}
}