{
  "type": "Feature",
  "properties": {
    "addr:full":"2330 Fair Oaks Blvd Sacramento CA 95825",
    "addr:housenumber":"2330",
    "addr:postcode":"95825",
    "addr:street":"Fair Oaks Blvd",
    "iso:country":"US",
    "sg:address":"2330 Fair Oaks Blvd",
    "sg:city":"Sacramento",
    "sg:classifiers":[
        {
            "category":"Recreation",
            "type":"Entertainment"
        }
    ],
    "sg:phone":"+1 916 925 6322",
    "sg:postcode":"95825",
    "sg:province":"CA",
    "sg:tags":[
        "club",
        "bridge"
    ],
    "wof:name":"Bridge Center Of Sacramento",
    "wof:placetype":"venue"
},
  "geometry": {"coordinates":[-121.40958500000001,38.574428],"type":"Point"}
}