{
  "type": "Feature",
  "properties": {
    "iso:country":"US",
    "sg:address":"1617 Canyon Dr",
    "sg:city":"Pinole",
    "sg:classifiers":[
        {
            "category":"Professional",
            "type":"Services"
        }
    ],
    "sg:phone":"+1 510 724 4437",
    "sg:postcode":"94564",
    "sg:province":"CA",
    "sg:tags":[
        "establishment"
    ],
    "wof:name":"NCS Credit Network Inc",
    "wof:placetype":"venue"
},
  "geometry": {"coordinates":[-122.301633,37.995383],"type":"Point"}
}