{
  "type": "Feature",
  "properties": {
    "addr:full":"641 W Main St Brawley CA 92227",
    "addr:housenumber":"641",
    "addr:postcode":"92227",
    "addr:street":"W Main St",
    "iso:country":"US",
    "sg:address":"641 W Main St",
    "sg:city":"Brawley",
    "sg:classifiers":[
        {
            "category":"Social Services",
            "type":"Services"
        }
    ],
    "sg:phone":"+1 760 344 5913",
    "sg:postcode":"92227",
    "sg:province":"CA",
    "sg:tags":[
        "organization",
        "welfare"
    ],
    "wof:name":"Volunteers Of America",
    "wof:placetype":"venue"
},
  "geometry": {"coordinates":[-115.55378399999999,32.978658],"type":"Point"}
}