{
  "type": "Feature",
  "properties": {
    "iso:country":"US",
    "sg:address":"2346 Westwood Blvd",
    "sg:city":"Los Angeles",
    "sg:classifiers":[
        {
            "category":"Health Services",
            "subcategory":"Dentist",
            "type":"Services"
        }
    ],
    "sg:phone":"+1 310 441 0848",
    "sg:postcode":"90064",
    "sg:province":"CA",
    "wof:name":"Tabib Kamran DDS",
    "wof:placetype":"venue"
},
  "geometry": {"coordinates":[-118.429552,34.161146],"type":"Point"}
}