{
  "type": "Feature",
  "properties": {
    "iso:country":"US",
    "sg:address":"416 N Fairfax Ave.",
    "sg:city":"Los Angeles",
    "sg:classifiers":[
        {
            "category":"Shopping",
            "subcategory":"Beauty & Cosmetics",
            "type":"Retail Goods"
        }
    ],
    "sg:phone":"+1 323 655 2330",
    "sg:postcode":"90036",
    "sg:province":"CA",
    "sg:tags":[
        "supply"
    ],
    "sg:website":"www.ballbeauty.com/",
    "wof:name":"Ball Beauty Supply",
    "wof:placetype":"venue"
},
  "geometry": {"coordinates":[-118.361303,34.078733],"type":"Point"}
}