{
  "type": "Feature",
  "properties": {
    "iso:country":"US",
    "sg:address":"1634 Golden Gate Ave",
    "sg:city":"Dos Palos",
    "sg:classifiers":[
        {
            "category":"Farming",
            "subcategory":"Livestock Farm",
            "type":"Manufacturing & Wholesale Goods"
        }
    ],
    "sg:phone":"+1 209 392 2352",
    "sg:postcode":"93620",
    "sg:province":"CA",
    "sg:tags":[
        "animal",
        "general"
    ],
    "sg:website":"www.miadavis.com",
    "wof:name":"Dino Lorenzetti Ranch Inc",
    "wof:placetype":"venue"
},
  "geometry": {"coordinates":[-120.627864,36.984422],"type":"Point"}
}