{
  "type": "Feature",
  "properties": {
    "addr:full":"528 El Camino Real Tustin CA 92780",
    "addr:housenumber":"528",
    "addr:postcode":"92780",
    "addr:street":"El Camino Real",
    "iso:country":"US",
    "sg:address":"528 El Camino Real",
    "sg:city":"Tustin",
    "sg:classifiers":[
        {
            "category":"Home & Garden",
            "subcategory":"Kitchen Supply",
            "type":"Retail Goods"
        },
        {
            "category":"Home & Garden",
            "subcategory":"Building Materials",
            "type":"Retail Goods"
        },
        {
            "category":"Building & Trades",
            "subcategory":"Construction",
            "type":"Services"
        },
        {
            "category":"Home & Garden",
            "subcategory":"Furniture",
            "type":"Retail Goods"
        }
    ],
    "sg:phone":"+1 714 544 8822",
    "sg:postcode":"92780",
    "sg:province":"CA",
    "sg:tags":[
        "bathroom",
        "equipment-household",
        "accessory",
        "planning",
        "fixtures",
        "cabinet",
        "remodeling"
    ],
    "sg:website":"http://www.jmcokitchenandbath.com",
    "wof:name":"JM Co. Kitchen & Bath Showroom Inc.",
    "wof:placetype":"venue"
},
  "geometry": {"coordinates":[-117.823667,33.740775],"type":"Point"}
}