{
  "type": "Feature",
  "properties": {
    "iso:country":"US",
    "sg:address":"26190 Thacker Dr",
    "sg:city":"Hemet",
    "sg:classifiers":[
        {
            "category":"Professional",
            "type":"Services"
        }
    ],
    "sg:phone":"+1 951 927 8686",
    "sg:postcode":"92544",
    "sg:province":"CA",
    "wof:name":"Southwestern Interconnect",
    "wof:placetype":"venue"
},
  "geometry": {"coordinates":[-116.88994099999999,33.741503],"type":"Point"}
}