{
  "type": "Feature",
  "properties": {
    "iso:country":"US",
    "sg:address":"2416 18th St Ste D",
    "sg:city":"Sacramento",
    "sg:classifiers":[
        {
            "category":"Professional",
            "subcategory":"Art Services",
            "type":"Services"
        }
    ],
    "sg:phone":"+1 916 201 3012",
    "sg:postcode":"95818",
    "sg:province":"CA",
    "sg:tags":[
        "photographer"
    ],
    "sg:website":"www.pinupweddings.com",
    "wof:name":"Pin Up Weddings",
    "wof:placetype":"venue"
},
  "geometry": {"coordinates":[-121.48969099999999,38.56145],"type":"Point"}
}