{
  "type": "Feature",
  "properties": {
    "addr:full":"560 Tres Pinos Rd Hollister CA 95023",
    "addr:housenumber":"560",
    "addr:postcode":"hollister ca 95023",
    "addr:street":"Tres Pinos Rd",
    "iso:country":"US",
    "sg:address":"560 Tres Pinos Rd",
    "sg:city":"Hollister",
    "sg:classifiers":[
        {
            "category":"Freight",
            "type":"Transportation"
        }
    ],
    "sg:phone":"+1 831 637 7423",
    "sg:postcode":"95023",
    "sg:province":"CA",
    "sg:tags":[
        "courier"
    ],
    "wof:name":"Package Express Center",
    "wof:placetype":"venue"
},
  "geometry": {"coordinates":[-121.393563,36.839501],"type":"Point"}
}