{
  "type": "Feature",
  "properties": {
    "iso:country":"US",
    "sg:address":"125 E Wilshire Ave",
    "sg:city":"Fullerton",
    "sg:classifiers":[
        {
            "category":"Food & Beverages",
            "subcategory":"Farmers Market",
            "type":"Retail Goods"
        }
    ],
    "sg:postcode":"92832",
    "sg:province":"CA",
    "wof:name":"Downtown Fullerton Market",
    "wof:placetype":"venue"
},
  "geometry": {"coordinates":[-117.92312099999999,33.872705],"type":"Point"}
}