{
  "type": "Feature",
  "properties": {
    "addr:full":"18715 S Western Ave Gardena CA 90248",
    "addr:housenumber":"18715",
    "addr:postcode":"90248",
    "addr:street":"S Western Ave",
    "iso:country":"US",
    "sg:address":"18715 S Western Ave",
    "sg:city":"Gardena",
    "sg:classifiers":[
        {
            "category":"Home & Garden",
            "subcategory":"Garden Supply",
            "type":"Retail Goods"
        }
    ],
    "sg:phone":"+1 310 324 1514",
    "sg:postcode":"90248",
    "sg:province":"CA",
    "sg:tags":[
        "nursery",
        "gardening"
    ],
    "wof:name":"Okada Nursery",
    "wof:placetype":"venue"
},
  "geometry": {"coordinates":[-118.308998,33.861401],"type":"Point"}
}