{
  "type": "Feature",
  "properties": {
    "addr:full":"18541 Via Princessa Canyon Cntry CA 91387",
    "addr:housenumber":"18541",
    "addr:postcode":"91387",
    "addr:street":"Via Princessa",
    "iso:country":"US",
    "sg:address":"18541 Via Princessa",
    "sg:city":"Canyon Cntry",
    "sg:classifiers":[
        {
            "category":"Personal",
            "subcategory":"Barber",
            "type":"Services"
        }
    ],
    "sg:phone":"+1 661 299 1694",
    "sg:postcode":"91387",
    "sg:province":"CA",
    "wof:name":"Cut and Go Barber Shop",
    "wof:placetype":"venue"
},
  "geometry": {"coordinates":[-118.452003,34.4058],"type":"Point"}
}