{
  "type": "Feature",
  "properties": {
    "iso:country":"US",
    "sg:address":"14818 Stonehedge Ln",
    "sg:city":"Westminster",
    "sg:classifiers":[
        {
            "category":"Manufacturing",
            "subcategory":"Lumber",
            "type":"Manufacturing & Wholesale Goods"
        }
    ],
    "sg:phone":"+1 714 791 1261",
    "sg:postcode":"92683",
    "sg:province":"CA",
    "sg:tags":[
        "hardwood",
        "mill"
    ],
    "wof:name":"Bunwood USA",
    "wof:placetype":"venue"
},
  "geometry": {"coordinates":[-117.965593,33.748193],"type":"Point"}
}