{
  "type": "Feature",
  "properties": {
    "iso:country":"US",
    "sg:address":"624 Exeter Pl",
    "sg:city":"Danville",
    "sg:classifiers":[
        {
            "category":"Professional",
            "type":"Services"
        }
    ],
    "sg:phone":"+1 925 736 5785",
    "sg:postcode":"94506",
    "sg:province":"CA",
    "wof:name":"Hallock Tool",
    "wof:placetype":"venue"
},
  "geometry": {"coordinates":[-121.909752,37.802216],"type":"Point"}
}