{
  "type": "Feature",
  "properties": {
    "iso:country":"US",
    "sg:address":"8072 16th St",
    "sg:city":"Westminster",
    "sg:classifiers":[
        {
            "category":"Wholesale",
            "subcategory":"Home Furnishings",
            "type":"Manufacturing & Wholesale Goods"
        }
    ],
    "sg:phone":"+1 714 799 9265",
    "sg:postcode":"92683",
    "sg:province":"CA",
    "sg:tags":[
        "waterbeds"
    ],
    "wof:name":"Visions Bedrooms & Waterbeds",
    "wof:placetype":"venue"
},
  "geometry": {"coordinates":[-117.988822,33.75835],"type":"Point"}
}