{
  "type": "Feature",
  "properties": {
    "addr:full":"345 Montford Ave Mill Valley CA 94941",
    "addr:housenumber":"345",
    "addr:postcode":"94941",
    "addr:street":"Montford Ave",
    "iso:country":"US",
    "sg:address":"345 Montford Ave",
    "sg:city":"Mill Valley",
    "sg:classifiers":[
        {
            "category":"Personal",
            "type":"Services"
        }
    ],
    "sg:phone":"+1 415 388 1165",
    "sg:postcode":"94941",
    "sg:province":"CA",
    "sg:tags":[
        "shopping"
    ],
    "wof:name":"Interiors By Mattalyn",
    "wof:placetype":"venue"
},
  "geometry": {"coordinates":[-122.54356,37.896933],"type":"Point"}
}