{
  "type": "Feature",
  "properties": {
    "iso:country":"US",
    "sg:address":"9748 Glenoaks Blvd",
    "sg:city":"Sun Valley",
    "sg:classifiers":[
        {
            "category":"Food & Beverages",
            "subcategory":"Liquor & Beverages",
            "type":"Retail Goods"
        }
    ],
    "sg:phone":"+1 818 767 3178",
    "sg:postcode":"91352",
    "sg:province":"CA",
    "wof:name":"Glenoaks Liquors",
    "wof:placetype":"venue"
},
  "geometry": {"coordinates":[-118.38670500000001,34.249079],"type":"Point"}
}