{
  "type": "Feature",
  "properties": {
    "addr:full":"16301 Garfield Ave Paramount CA 90723",
    "addr:housenumber":"16301",
    "addr:postcode":"90723",
    "addr:street":"Garfield Ave",
    "iso:country":"US",
    "sg:address":"16301 Garfield Ave",
    "sg:city":"Paramount",
    "sg:classifiers":[
        {
            "category":"Retail",
            "subcategory":"Veterinary Services",
            "type":"Services"
        },
        {
            "category":"Retail",
            "subcategory":"Pet Boarding",
            "type":"Services"
        }
    ],
    "sg:phone":"+1 562 630 2082",
    "sg:postcode":"90723",
    "sg:province":"CA",
    "sg:tags":[
        "veterinarian",
        "boarding/pet",
        "sitting"
    ],
    "wof:name":"Ashiq Muhammad DVM",
    "wof:placetype":"venue"
},
  "geometry": {"coordinates":[-118.168999,33.886101],"type":"Point"}
}