{
  "type": "Feature",
  "properties": {
    "addr:full":"1055 38th Ave Santa Cruz CA 95062",
    "addr:housenumber":"1055",
    "addr:postcode":"95062",
    "addr:street":"38Th Ave",
    "iso:country":"US",
    "sg:address":"1055 38th Ave",
    "sg:city":"Santa Cruz",
    "sg:classifiers":[
        {
            "category":"Shopping",
            "subcategory":"Clothing, Apparel, & Fashions",
            "type":"Retail Goods"
        }
    ],
    "sg:phone":"+1 831 479 9040",
    "sg:postcode":"95062",
    "sg:province":"CA",
    "sg:tags":[
        "infant",
        "wear"
    ],
    "sg:website":"www.comfykid.com",
    "wof:name":"COMFYKID.COM",
    "wof:placetype":"venue"
},
  "geometry": {"coordinates":[-121.967457,36.967036],"type":"Point"}
}