{
  "type": "Feature",
  "properties": {
    "addr:full":"60 Elm Ave Long Beach CA 90802",
    "addr:housenumber":"60",
    "addr:postcode":"90802",
    "addr:street":"Elm Ave",
    "iso:country":"US",
    "sg:address":"60 Elm Ave",
    "sg:city":"Long Beach",
    "sg:classifiers":[
        {
            "category":"Professional",
            "subcategory":"Lawyer & Legal Services",
            "type":"Services"
        }
    ],
    "sg:phone":"+1 562 491 4644",
    "sg:postcode":"90802",
    "sg:province":"CA",
    "sg:tags":[
        "attorney"
    ],
    "sg:website":"www.intermodallaw.com",
    "wof:name":"Coniglio & Uthoff",
    "wof:placetype":"venue"
},
  "geometry": {"coordinates":[-118.18800400000001,33.767502],"type":"Point"}
}