{
  "type": "Feature",
  "properties": {
    "addr:full":"1290 oakmead parkway, suite 107 Sunnyvale CA 94085",
    "addr:housenumber":"1290",
    "addr:postcode":"94085",
    "addr:street":"Oakmead Parkway Suite 107",
    "iso:country":"US",
    "sg:address":"1290 oakmead parkway, suite 107",
    "sg:city":"Sunnyvale",
    "sg:classifiers":[
        {
            "category":"Professional",
            "subcategory":"Computer Services",
            "type":"Services"
        }
    ],
    "sg:phone":"+1 408 739 2880",
    "sg:postcode":"94085",
    "sg:province":"CA",
    "sg:tags":[
        "real-life-gaming",
        "mobile-games",
        "augmented-reality",
        "interest-recognition",
        "mobile-social-network",
        "photo-sharing",
        "visual-checkin",
        "location-services",
        "location-aware-games",
        "stratego",
        "local-advertising",
        "hyperlocal",
        "mobile-context"
    ],
    "sg:website":"http://www.vufind.com",
    "wof:name":"vufind",
    "wof:placetype":"venue"
},
  "geometry": {"coordinates":[-121.99296,37.386705],"type":"Point"}
}