{
  "type": "Feature",
  "properties": {
    "addr:full":"1700 S Santa Fe Ave Los Angeles CA 90021",
    "addr:housenumber":"1700",
    "addr:postcode":"90021",
    "addr:street":"S Santa Fe Ave",
    "iso:country":"US",
    "sg:address":"1700 S Santa Fe Ave",
    "sg:city":"Los Angeles",
    "sg:classifiers":[
        {
            "category":"Manufacturing",
            "subcategory":"Apparel",
            "type":"Manufacturing & Wholesale Goods"
        }
    ],
    "sg:phone":"+1 213 629 2821",
    "sg:postcode":"90021",
    "sg:province":"CA",
    "sg:tags":[
        "sewing",
        "contractor"
    ],
    "wof:name":"Cierra Sewing Inc",
    "wof:placetype":"venue"
},
  "geometry": {"coordinates":[-118.22990900000001,34.024648],"type":"Point"}
}