{
  "type": "Feature",
  "properties": {
    "addr:full":"930 Colorado Boulevard Suite 4 Los Angeles CA 90041",
    "addr:housenumber":"930",
    "addr:postcode":"90041",
    "addr:street":"Colorado Boulevard Suite 4",
    "iso:country":"US",
    "sg:address":"930 Colorado Boulevard Suite 4",
    "sg:city":"Los Angeles",
    "sg:classifiers":[
        {
            "category":"Professional",
            "subcategory":"Accounting & Tax Preparation",
            "type":"Services"
        }
    ],
    "sg:phone":"+1 323 341 5005",
    "sg:postcode":"90041",
    "sg:province":"CA",
    "sg:tags":[
        "accountant"
    ],
    "wof:name":"Matlock Richard E CPA",
    "wof:placetype":"venue"
},
  "geometry": {"coordinates":[-118.185813,34.138964],"type":"Point"}
}