{
  "type": "Feature",
  "properties": {
    "addr:full":"26131 Wren St Apple Valley CA 92307",
    "addr:housenumber":"26131",
    "addr:postcode":"92307",
    "addr:street":"Wren St",
    "iso:country":"US",
    "sg:address":"26131 Wren St",
    "sg:city":"Apple Valley",
    "sg:classifiers":[
        {
            "category":"Farming",
            "subcategory":"Orchard",
            "type":"Manufacturing & Wholesale Goods"
        }
    ],
    "sg:phone":"+1 760 247 9445",
    "sg:postcode":"92307",
    "sg:province":"CA",
    "sg:tags":[
        "fruit",
        "tree"
    ],
    "wof:name":"Raymond Baldridge",
    "wof:placetype":"venue"
},
  "geometry": {"coordinates":[-117.103568,34.450236],"type":"Point"}
}