{
  "type": "Feature",
  "properties": {
    "addr:full":"3252 Louise St Simi Valley CA 93063",
    "addr:housenumber":"3252",
    "addr:postcode":"93063",
    "addr:street":"Louise St",
    "iso:country":"US",
    "sg:address":"3252 Louise St",
    "sg:city":"Simi Valley",
    "sg:classifiers":[
        {
            "category":"Freight",
            "type":"Transportation"
        }
    ],
    "sg:phone":"+1 805 583 3383",
    "sg:postcode":"93063",
    "sg:province":"CA",
    "sg:tags":[
        "haulage",
        "truck",
        "dump"
    ],
    "wof:name":"Espinosa Orestes Trucking",
    "wof:placetype":"venue"
},
  "geometry": {"coordinates":[-118.73423699999999,34.28498],"type":"Point"}
}