{
  "type": "Feature",
  "properties": {
    "addr:full":"884 Portola Rd Portola Valley CA 94028",
    "addr:housenumber":"884",
    "addr:postcode":"94028",
    "addr:street":"Portola Rd",
    "iso:country":"US",
    "sg:address":"884 Portola Rd",
    "sg:city":"Portola Valley",
    "sg:classifiers":[
        {
            "category":"Retail",
            "subcategory":"Veterinary Services",
            "type":"Services"
        }
    ],
    "sg:phone":"+1 650 851 3244",
    "sg:postcode":"94028",
    "sg:province":"CA",
    "sg:tags":[
        "veterinarian"
    ],
    "wof:name":"Village Square Veterinary Hosp",
    "wof:placetype":"venue"
},
  "geometry": {"coordinates":[-122.234408,37.384078],"type":"Point"}
}