{
  "type": "Feature",
  "properties": {
    "iso:country":"US",
    "sg:address":"464 Maple Ln",
    "sg:city":"Garberville",
    "sg:classifiers":[
        {
            "category":"Health Services",
            "subcategory":"Nursing And Care Facility",
            "type":"Services"
        }
    ],
    "sg:phone":"+1 707 923 7276",
    "sg:postcode":"95542",
    "sg:province":"CA",
    "sg:tags":[
        "hospice"
    ],
    "wof:name":"Heart Of The Redwoods Cmnty",
    "wof:placetype":"venue"
},
  "geometry": {"coordinates":[-123.79365199999999,40.099967],"type":"Point"}
}