{
  "type": "Feature",
  "properties": {
    "iso:country":"US",
    "sg:address":"5113 W Walnut Ave",
    "sg:city":"Visalia",
    "sg:classifiers":[
        {
            "category":"Restaurant",
            "type":"Food & Drink"
        }
    ],
    "sg:phone":"+1 559 636 6091",
    "sg:postcode":"93277",
    "sg:province":"CA",
    "wof:name":"Three & Three Investments Inc",
    "wof:placetype":"venue"
},
  "geometry": {"coordinates":[-119.346541,36.312705],"type":"Point"}
}