{
  "type": "Feature",
  "properties": {
    "iso:country":"US",
    "sg:address":"8443 Whirlaway St",
    "sg:city":"Alta Loma",
    "sg:classifiers":[
        {
            "category":"Manufacturing",
            "subcategory":"Tools & Machinery",
            "type":"Manufacturing & Wholesale Goods"
        }
    ],
    "sg:phone":"+1 909 948 1234",
    "sg:postcode":"91701",
    "sg:province":"CA",
    "sg:tags":[
        "machine",
        "shop",
        "mfg",
        "accessory"
    ],
    "wof:name":"Sharp Rite Tool Inc",
    "wof:placetype":"venue"
},
  "geometry": {"coordinates":[-117.621506,34.15717],"type":"Point"}
}