{
  "type": "Feature",
  "properties": {
    "iso:country":"US",
    "sg:address":"2372 Northgate Blvd",
    "sg:city":"Sacramento",
    "sg:classifiers":[
        {
            "category":"Sports & Exercise",
            "subcategory":"Bicycle Rental",
            "type":"Entertainment"
        }
    ],
    "sg:phone":"+1 916 925 2017",
    "sg:postcode":"95833",
    "sg:province":"CA",
    "sg:tags":[
        "wear"
    ],
    "wof:name":"Desportes Janitxio",
    "wof:placetype":"venue"
},
  "geometry": {"coordinates":[-121.47520900000001,38.609966],"type":"Point"}
}