{
  "type": "Feature",
  "properties": {
    "iso:country":"US",
    "sg:address":"PO Box 10517",
    "sg:city":"Santa Ana",
    "sg:classifiers":[
        {
            "category":"Professional",
            "subcategory":"Lawyer & Legal Services",
            "type":"Services"
        }
    ],
    "sg:phone":"+1 714 953 0187",
    "sg:postcode":"92711",
    "sg:province":"CA",
    "wof:name":"Hull-Richter R N Atty",
    "wof:placetype":"venue"
},
  "geometry": {"coordinates":[-117.851997,33.758999],"type":"Point"}
}