{
  "type": "Feature",
  "properties": {
    "iso:country":"US",
    "sg:address":"24025 Race Track Rd",
    "sg:city":"Foresthill",
    "sg:classifiers":[
        {
            "category":"Banks & Credit Unions",
            "subcategory":"Bank",
            "type":"Services"
        }
    ],
    "sg:phone":"+1 530 367 2284",
    "sg:postcode":"95631",
    "sg:province":"CA",
    "wof:name":"Placer Sierra Bank",
    "wof:placetype":"venue"
},
  "geometry": {"coordinates":[-120.822186,39.020196],"type":"Point"}
}