{
  "type": "Feature",
  "properties": {
    "addr:full":"23718 Western Ave Harbor City CA 90710",
    "addr:housenumber":"23718",
    "addr:postcode":"90710",
    "addr:street":"Western Ave",
    "iso:country":"US",
    "sg:address":"23718 Western Ave",
    "sg:city":"Harbor City",
    "sg:classifiers":[
        {
            "category":"Shopping",
            "subcategory":"Pets & Pet Supplies",
            "type":"Retail Goods"
        }
    ],
    "sg:phone":"+1 310 539 6748",
    "sg:postcode":"90710",
    "sg:province":"CA",
    "sg:tags":[
        "store"
    ],
    "wof:name":"Happy Hounds",
    "wof:placetype":"venue"
},
  "geometry": {"coordinates":[-118.307999,33.809502],"type":"Point"}
}