{
  "type": "Feature",
  "properties": {
    "iso:country":"US",
    "sg:address":"9860 Summerset Ct",
    "sg:city":"Granite Bay",
    "sg:classifiers":[
        {
            "category":"Shopping",
            "subcategory":"Used Merchandise",
            "type":"Retail Goods"
        }
    ],
    "sg:phone":"+1 916 791 5244",
    "sg:postcode":"95746",
    "sg:province":"CA",
    "wof:name":"Ann Thornton",
    "wof:placetype":"venue"
},
  "geometry": {"coordinates":[-121.20958,38.718513],"type":"Point"}
}