{
  "type": "Feature",
  "properties": {
    "iso:country":"US",
    "sg:address":"5070 N 6th St",
    "sg:city":"Fresno",
    "sg:classifiers":[
        {
            "category":"Social Services",
            "subcategory":"Job Training",
            "type":"Services"
        }
    ],
    "sg:phone":"+1 559 224 5652",
    "sg:postcode":"93710",
    "sg:province":"CA",
    "sg:tags":[
        "rehabilitation"
    ],
    "wof:name":"CSUF Rehabilitation Cnslng",
    "wof:placetype":"venue"
},
  "geometry": {"coordinates":[-119.763164,36.810962],"type":"Point"}
}