{
  "type": "Feature",
  "properties": {
    "addr:full":"940 W Washington Blvd Los Angeles CA 90015",
    "addr:housenumber":"940",
    "addr:postcode":"90015",
    "addr:street":"W Washington Blvd",
    "iso:country":"US",
    "sg:address":"940 W Washington Blvd",
    "sg:city":"Los Angeles",
    "sg:classifiers":[
        {
            "category":"Shopping",
            "subcategory":"Clothing, Apparel, & Fashions",
            "type":"Retail Goods"
        }
    ],
    "sg:phone":"+1 213 745 2250",
    "sg:postcode":"90015",
    "sg:province":"CA",
    "wof:name":"Mocha Fashion",
    "wof:placetype":"venue"
},
  "geometry": {"coordinates":[-118.279072,34.03747],"type":"Point"}
}