{
  "type": "Feature",
  "properties": {
    "iso:country":"US",
    "sg:address":"5733 E Pitt Ave",
    "sg:city":"Fresno",
    "sg:classifiers":[
        {
            "category":"Building & Trades",
            "subcategory":"Cleaning & Sanitation",
            "type":"Services"
        }
    ],
    "sg:phone":"+1 559 430 9402",
    "sg:postcode":"93727",
    "sg:province":"CA",
    "sg:tags":[
        "janitorial"
    ],
    "wof:name":"Cabuto's Professional Janitorial",
    "wof:placetype":"venue"
},
  "geometry": {"coordinates":[-119.694322,36.717776],"type":"Point"}
}