{
  "type": "Feature",
  "properties": {
    "addr:full":"2901 Bergamo Way Sacramento CA 95833",
    "addr:housenumber":"2901",
    "addr:postcode":"95833",
    "addr:street":"Bergamo Way",
    "iso:country":"US",
    "sg:address":"2901 Bergamo Way",
    "sg:city":"Sacramento",
    "sg:classifiers":[
        {
            "category":"Insurance",
            "subcategory":"Hazard Insurance",
            "type":"Services"
        }
    ],
    "sg:phone":"+1 916 979 7850",
    "sg:postcode":"95833",
    "sg:province":"CA",
    "sg:tags":[
        "commercial",
        "business"
    ],
    "wof:name":"Froude Insurance",
    "wof:placetype":"venue"
},
  "geometry": {"coordinates":[-121.526749,38.61235],"type":"Point"}
}