{
  "type": "Feature",
  "properties": {
    "addr:full":"16530 Ventura Blvd Encino CA 91436",
    "addr:housenumber":"16530",
    "addr:postcode":"91436",
    "addr:street":"Ventura Blvd",
    "iso:country":"US",
    "sg:address":"16530 Ventura Blvd",
    "sg:city":"Encino",
    "sg:classifiers":[
        {
            "category":"Professional",
            "subcategory":"Management & Consulting",
            "type":"Services"
        }
    ],
    "sg:phone":"+1 714 847 4446",
    "sg:postcode":"91436",
    "sg:province":"CA",
    "sg:tags":[
        "personnel",
        "consultant"
    ],
    "wof:name":"Inter-Nurse Of California",
    "wof:placetype":"venue"
},
  "geometry": {"coordinates":[-118.49373799999999,34.157664],"type":"Point"}
}