{
  "type": "Feature",
  "properties": {
    "addr:full":"9373 Felipe Ave Montclair CA 91763",
    "addr:housenumber":"9373",
    "addr:postcode":"91763",
    "addr:street":"Felipe Ave",
    "iso:country":"US",
    "sg:address":"9373 Felipe Ave",
    "sg:city":"Montclair",
    "sg:classifiers":[
        {
            "category":"Retail",
            "subcategory":"Laundry & Dry Cleaning",
            "type":"Services"
        }
    ],
    "sg:phone":"+1 909 625 2091",
    "sg:postcode":"91763",
    "sg:province":"CA",
    "wof:name":"Saleh Corporation",
    "wof:placetype":"venue"
},
  "geometry": {"coordinates":[-117.704239,34.084161],"type":"Point"}
}