{
  "type": "Feature",
  "properties": {
    "addr:full":"45800 Northport Loop West Fremont CA 94538",
    "addr:postcode":"45800;94538",
    "addr:street":"Northport Loop West",
    "iso:country":"US",
    "sg:address":"45800 Northport Loop West",
    "sg:city":"Fremont",
    "sg:classifiers":[
        {
            "category":"Wholesale",
            "subcategory":"Computers",
            "type":"Manufacturing & Wholesale Goods"
        }
    ],
    "sg:phone":"+1 888 736 4846",
    "sg:postcode":"94538",
    "sg:province":"CA",
    "sg:website":"www.penguincomputing.com",
    "wof:name":"Penguin Computing",
    "wof:placetype":"venue"
},
  "geometry": {"coordinates":[-121.955963,37.491761],"type":"Point"}
}