{
  "type": "Feature",
  "properties": {
    "iso:country":"US",
    "sg:address":"68363 E Palm Canyon Dr",
    "sg:city":"Cathedral City",
    "sg:classifiers":[
        {
            "category":"Food & Beverages",
            "subcategory":"Meat & Fish",
            "type":"Retail Goods"
        }
    ],
    "sg:phone":"+1 760 321 5417",
    "sg:postcode":"92234",
    "sg:province":"CA",
    "sg:tags":[
        "shop"
    ],
    "wof:name":"Rancho Meat Market 4",
    "wof:placetype":"venue"
},
  "geometry": {"coordinates":[-116.469002,33.7812],"type":"Point"}
}