{
  "type": "Feature",
  "properties": {
    "iso:country":"US",
    "sg:address":"17042 Devonshire St",
    "sg:city":"Northridge",
    "sg:classifiers":[
        {
            "category":"Insurance",
            "subcategory":"Insurance Agent",
            "type":"Services"
        }
    ],
    "sg:phone":"+1 818 366 5677",
    "sg:postcode":"91325",
    "sg:province":"CA",
    "wof:name":"North Hills Insurance Svc Inc",
    "wof:placetype":"venue"
},
  "geometry": {"coordinates":[-118.505573,34.257459],"type":"Point"}
}