{
  "type": "Feature",
  "properties": {
    "addr:full":"600 S Lake Ave Ste 103 Pasadena CA 91106",
    "addr:housenumber":"600",
    "addr:postcode":"91106",
    "addr:street":"S Lake Ave Ste 103",
    "iso:country":"US",
    "sg:address":"600 S Lake Ave Ste 103",
    "sg:city":"Pasadena",
    "sg:classifiers":[
        {
            "category":"Health Services",
            "subcategory":"Chiropractor",
            "type":"Services"
        }
    ],
    "sg:phone":"+1 626 793 6780",
    "sg:postcode":"91106",
    "sg:province":"CA",
    "wof:name":"Pires A Brian DC",
    "wof:placetype":"venue"
},
  "geometry": {"coordinates":[-118.13200399999999,34.135502],"type":"Point"}
}