{
  "type": "Feature",
  "properties": {
    "addr:full":"230 Winston St Los Angeles CA 90013",
    "addr:housenumber":"230",
    "addr:postcode":"90013",
    "addr:street":"Winston St",
    "iso:country":"US",
    "sg:address":"230 Winston St",
    "sg:city":"Los Angeles",
    "sg:classifiers":[
        {
            "category":"Wholesale",
            "subcategory":"Electrical",
            "type":"Manufacturing & Wholesale Goods"
        }
    ],
    "sg:phone":"+1 213 689 9533",
    "sg:postcode":"90013",
    "sg:province":"CA",
    "sg:tags":[
        "control",
        "security",
        "system"
    ],
    "wof:name":"Solutions To Security",
    "wof:placetype":"venue"
},
  "geometry": {"coordinates":[-118.245886,34.045687],"type":"Point"}
}