{
  "type": "Feature",
  "properties": {
    "iso:country":"US",
    "sg:address":"133 N Carl Dr",
    "sg:city":"Visalia",
    "sg:classifiers":[
        {
            "category":"Building & Trades",
            "subcategory":"Landscaping Services",
            "type":"Services"
        }
    ],
    "sg:phone":"+1 559 733 7657",
    "sg:postcode":"93291",
    "sg:province":"CA",
    "sg:tags":[
        "concrete"
    ],
    "wof:name":"Concrete Surface Solutions Inc",
    "wof:placetype":"venue"
},
  "geometry": {"coordinates":[-119.337216,36.329542],"type":"Point"}
}