{
  "type": "Feature",
  "properties": {
    "addr:full":"2114 Macarthur Blvd Oakland CA 94602",
    "addr:housenumber":"2114",
    "addr:postcode":"94602",
    "addr:street":"Macarthur Blvd",
    "iso:country":"US",
    "sg:address":"2114 Macarthur Blvd",
    "sg:city":"Oakland",
    "sg:classifiers":[
        {
            "category":"Cinema",
            "subcategory":"Movie Rental",
            "type":"Entertainment"
        }
    ],
    "sg:phone":"+1 510 482 4300",
    "sg:postcode":"94602",
    "sg:province":"CA",
    "sg:tags":[
        "leasing",
        "video",
        "disc",
        "tape"
    ],
    "wof:name":"Blockbuster Video",
    "wof:placetype":"venue"
},
  "geometry": {"coordinates":[-122.216729,37.800547],"type":"Point"}
}