{
  "type": "Feature",
  "properties": {
    "addr:full":"301 Dickson Hill Rd Fairfield CA 94533",
    "addr:housenumber":"301",
    "addr:postcode":"94533",
    "addr:street":"Dickson Hill Rd",
    "iso:country":"US",
    "sg:address":"301 Dickson Hill Rd",
    "sg:city":"Fairfield",
    "sg:classifiers":[
        {
            "category":"Professional",
            "subcategory":"Lawyer & Legal Services",
            "type":"Services"
        }
    ],
    "sg:phone":"+1 707 447 4403",
    "sg:postcode":"94533",
    "sg:province":"CA",
    "sg:tags":[
        "attorney"
    ],
    "wof:name":"Wright & Falls",
    "wof:placetype":"venue"
},
  "geometry": {"coordinates":[-122.033911,38.290686],"type":"Point"}
}