{
  "type": "Feature",
  "properties": {
    "addr:full":"10032 Beech Ave Fontana CA 92335",
    "addr:housenumber":"10032",
    "addr:postcode":"92335",
    "addr:street":"Beech Ave",
    "iso:country":"US",
    "sg:address":"10032 Beech Ave",
    "sg:city":"Fontana",
    "sg:classifiers":[
        {
            "category":"Shopping",
            "type":"Retail Goods"
        }
    ],
    "sg:phone":"+1 909 428 7190",
    "sg:postcode":"92335",
    "sg:province":"CA",
    "sg:tags":[
        "farm",
        "merchandise",
        "supply"
    ],
    "wof:name":"Pats Place",
    "wof:placetype":"venue"
},
  "geometry": {"coordinates":[-117.471298,34.071301],"type":"Point"}
}