{
  "type": "Feature",
  "properties": {
    "addr:full":"33450 Little Valley Rd Fort Bragg CA 95437",
    "addr:housenumber":"33450",
    "addr:postcode":"95437",
    "addr:street":"Little Valley Rd",
    "iso:country":"US",
    "sg:address":"33450 Little Valley Rd",
    "sg:city":"Fort Bragg",
    "sg:classifiers":[
        {
            "category":"Wholesale",
            "subcategory":"Plants",
            "type":"Manufacturing & Wholesale Goods"
        }
    ],
    "sg:phone":"+1 707 964 7971",
    "sg:postcode":"95437",
    "sg:province":"CA",
    "sg:tags":[
        "supply"
    ],
    "wof:name":"Iris Gallery",
    "wof:placetype":"venue"
},
  "geometry": {"coordinates":[-123.74563999999999,39.504045],"type":"Point"}
}