{
  "type": "Feature",
  "properties": {
    "iso:country":"US",
    "sg:address":"7758 W 91st St",
    "sg:city":"Playa Del Rey",
    "sg:classifiers":[
        {
            "category":"Shopping",
            "subcategory":"Gifts & Souvenirs",
            "type":"Retail Goods"
        }
    ],
    "sg:phone":"+1 310 305 2041",
    "sg:postcode":"90293",
    "sg:province":"CA",
    "wof:name":"Erikas Gifts & Gift Baskets",
    "wof:placetype":"venue"
},
  "geometry": {"coordinates":[-118.432433,33.95654],"type":"Point"}
}