{
  "type": "Feature",
  "properties": {
    "addr:full":"1279 Produce Row Los Angeles CA 90021",
    "addr:housenumber":"1279",
    "addr:postcode":"90021",
    "addr:street":"Produce Row",
    "iso:country":"US",
    "sg:address":"1279 Produce Row",
    "sg:city":"Los Angeles",
    "sg:classifiers":[
        {
            "category":"Wholesale",
            "subcategory":"Fruits & Vegetables",
            "type":"Manufacturing & Wholesale Goods"
        }
    ],
    "sg:phone":"+1 213 624 7985",
    "sg:postcode":"90021",
    "sg:province":"CA",
    "wof:name":"Mercado Latino",
    "wof:placetype":"venue"
},
  "geometry": {"coordinates":[-118.24381700000001,34.033506],"type":"Point"}
}