{
  "type": "Feature",
  "properties": {
    "iso:country":"US",
    "sg:address":"31 W 25th Ave",
    "sg:city":"San Mateo",
    "sg:classifiers":[
        {
            "category":"Recreation",
            "type":"Entertainment"
        }
    ],
    "sg:phone":"+1 650 570 5991",
    "sg:postcode":"94403",
    "sg:province":"CA",
    "sg:tags":[
        "martial art",
        "instruction"
    ],
    "wof:name":"Kuk Sool Won",
    "wof:placetype":"venue"
},
  "geometry": {"coordinates":[-122.306,37.544102],"type":"Point"}
}