{
  "type": "Feature",
  "properties": {
    "iso:country":"US",
    "sg:address":"316 E Las Tunas Dr",
    "sg:city":"San Gabriel",
    "sg:classifiers":[
        {
            "category":"Health Services",
            "subcategory":"Clinic",
            "type":"Services"
        }
    ],
    "sg:phone":"+1 626 287 7798",
    "sg:postcode":"91776",
    "sg:province":"CA",
    "sg:tags":[
        "home",
        "care"
    ],
    "wof:name":"New Star Home Health Services",
    "wof:placetype":"venue"
},
  "geometry": {"coordinates":[-118.096648,34.103069],"type":"Point"}
}