{
  "type": "Feature",
  "properties": {
    "addr:full":"7595 Vickers St San Diego CA 92111",
    "addr:housenumber":"7595",
    "addr:postcode":"92111",
    "addr:street":"Vickers St",
    "iso:country":"US",
    "sg:address":"7595 Vickers St",
    "sg:city":"San Diego",
    "sg:classifiers":[
        {
            "category":"Wholesale",
            "subcategory":"Seafood",
            "type":"Manufacturing & Wholesale Goods"
        }
    ],
    "sg:phone":"+1 858 467 9055",
    "sg:postcode":"92111",
    "sg:province":"CA",
    "wof:name":"Ochoa Reynaldo",
    "wof:placetype":"venue"
},
  "geometry": {"coordinates":[-117.154113,32.828051],"type":"Point"}
}