{
  "type": "Feature",
  "properties": {
    "addr:full":"12672 Gun Ave Chino CA 91710",
    "addr:housenumber":"12672",
    "addr:postcode":"91710",
    "addr:street":"Gun Ave",
    "iso:country":"US",
    "sg:address":"12672 Gun Ave",
    "sg:city":"Chino",
    "sg:classifiers":[
        {
            "category":"Home & Garden",
            "subcategory":"Building Materials",
            "type":"Retail Goods"
        }
    ],
    "sg:phone":"+1 714 638 0776",
    "sg:postcode":"91710",
    "sg:province":"CA",
    "sg:tags":[
        "door"
    ],
    "wof:name":"Getz Overhead Garage Doors",
    "wof:placetype":"venue"
},
  "geometry": {"coordinates":[-117.712097,34.021929],"type":"Point"}
}