{
  "type": "Feature",
  "properties": {
    "addr:full":"7013 Via Padilla Carlsbad CA 92009",
    "addr:housenumber":"7013",
    "addr:postcode":"92009",
    "addr:street":"Via Padilla",
    "iso:country":"US",
    "sg:address":"7013 Via Padilla",
    "sg:city":"Carlsbad",
    "sg:classifiers":[
        {
            "category":"Professional",
            "subcategory":"Business Services",
            "type":"Services"
        }
    ],
    "sg:phone":"+1 760 692 1081",
    "sg:postcode":"92009",
    "sg:province":"CA",
    "sg:tags":[
        "water",
        "treatment"
    ],
    "wof:name":"Environmental Management",
    "wof:placetype":"venue"
},
  "geometry": {"coordinates":[-117.254344,33.099857],"type":"Point"}
}