{
  "type": "Feature",
  "properties": {
    "iso:country":"US",
    "sg:address":"825 Cordova St",
    "sg:city":"Pasadena",
    "sg:classifiers":[
        {
            "category":"Personal",
            "subcategory":"Tanning Parlor",
            "type":"Services"
        }
    ],
    "sg:phone":"+1 818 434 5766",
    "sg:postcode":"91101",
    "sg:province":"CA",
    "sg:website":"www.liquidsuntans.com",
    "wof:name":"Liquid Sun Tans",
    "wof:placetype":"venue"
},
  "geometry": {"coordinates":[-118.133323,34.142541],"type":"Point"}
}