{
  "type": "Feature",
  "properties": {
    "iso:country":"US",
    "sg:address":"219 E Canon Perdido St",
    "sg:city":"Santa Barbara",
    "sg:classifiers":[
        {
            "category":"Shopping",
            "type":"Retail Goods"
        }
    ],
    "sg:phone":"+1 805 962 0114",
    "sg:postcode":"93101",
    "sg:province":"CA",
    "sg:tags":[
        "art",
        "gallery",
        "merchandise",
        "dealer"
    ],
    "wof:name":"Suman Alvaro A Art Studio",
    "wof:placetype":"venue"
},
  "geometry": {"coordinates":[-119.69801699999999,34.422988],"type":"Point"}
}