{
  "type": "Feature",
  "properties": {
    "addr:full":"666 Baker Street Costa Mesa CA 92626",
    "addr:housenumber":"666",
    "addr:postcode":"92626",
    "addr:street":"Baker Street",
    "iso:country":"US",
    "sg:address":"666 Baker Street",
    "sg:city":"Costa Mesa",
    "sg:classifiers":[
        {
            "category":"Professional",
            "subcategory":"Accounting & Tax Preparation",
            "type":"Services"
        }
    ],
    "sg:phone":"+1 714 966 1212",
    "sg:postcode":"92626",
    "sg:province":"CA",
    "sg:tags":[
        "accountant"
    ],
    "sg:website":"www.nationaltaxinstitute.com",
    "wof:name":"National Tax Institute",
    "wof:placetype":"venue"
},
  "geometry": {"coordinates":[-117.88369,33.6801],"type":"Point"}
}