{
  "type": "Feature",
  "properties": {
    "iso:country":"US",
    "sg:address":"589 River Oaks Dr",
    "sg:city":"Redding",
    "sg:classifiers":[
        {
            "category":"Professional",
            "type":"Services"
        }
    ],
    "sg:phone":"+1 530 241 3323",
    "sg:postcode":"96001",
    "sg:province":"CA",
    "wof:name":"Landeffects",
    "wof:placetype":"venue"
},
  "geometry": {"coordinates":[-122.417911,40.590259],"type":"Point"}
}