{
  "type": "Feature",
  "properties": {
    "addr:full":"8880 Valley View St Buena Park CA 90620",
    "addr:housenumber":"8880",
    "addr:postcode":"90620",
    "addr:street":"Valley View St",
    "iso:country":"US",
    "sg:address":"8880 Valley View St",
    "sg:city":"Buena Park",
    "sg:classifiers":[
        {
            "category":"Banks & Credit Unions",
            "subcategory":"Bank",
            "type":"Services"
        }
    ],
    "sg:phone":"+1 714 533 4470",
    "sg:postcode":"90620",
    "sg:province":"CA",
    "wof:name":"Bank Of America",
    "wof:placetype":"venue"
},
  "geometry": {"coordinates":[-118.02818499999999,33.832773],"type":"Point"}
}