{
  "type": "Feature",
  "properties": {
    "iso:country":"US",
    "sg:address":"610 Auburn Ravine Rd",
    "sg:city":"Auburn",
    "sg:classifiers":[
        {
            "category":"Health Services",
            "subcategory":"Health Practitioner",
            "type":"Services"
        }
    ],
    "sg:phone":"+1 530 888 0960",
    "sg:postcode":"95603",
    "sg:province":"CA",
    "sg:tags":[
        "psychotherapist"
    ],
    "wof:name":"M Rynda Norsell",
    "wof:placetype":"venue"
},
  "geometry": {"coordinates":[-121.074518,38.910947],"type":"Point"}
}