{
  "type": "Feature",
  "properties": {
    "addr:full":"535 S Market St San Jose CA 95113",
    "addr:housenumber":"535",
    "addr:postcode":"95113",
    "addr:street":"S Market St",
    "iso:country":"US",
    "sg:address":"535 S Market St",
    "sg:city":"San Jose",
    "sg:classifiers":[
        {
            "category":"Real Estate",
            "subcategory":"Real Estate Operator",
            "type":"Services"
        }
    ],
    "sg:phone":"+1 408 993 9595",
    "sg:postcode":"95113",
    "sg:province":"CA",
    "sg:tags":[
        "apartment"
    ],
    "wof:name":"Market Gateway Apartments",
    "wof:placetype":"venue"
},
  "geometry": {"coordinates":[-121.88508899999999,37.328079],"type":"Point"}
}