{
  "type": "Feature",
  "properties": {
    "iso:country":"US",
    "sg:address":"410 San Diego St",
    "sg:city":"Oceanside",
    "sg:classifiers":[
        {
            "category":"Restaurant",
            "type":"Food & Drink"
        }
    ],
    "sg:phone":"+1 760 757 6565",
    "sg:postcode":"92058",
    "sg:province":"CA",
    "sg:tags":[
        "mexican"
    ],
    "sg:website":"www.elnopalitoofca.com/",
    "wof:name":"El Nopalito",
    "wof:placetype":"venue"
},
  "geometry": {"coordinates":[-117.36979700000001,33.203153],"type":"Point"}
}