{
  "type": "Feature",
  "properties": {
    "iso:country":"US",
    "sg:address":"700 World Way",
    "sg:city":"Los Angeles",
    "sg:classifiers":[
        {
            "category":"Airline",
            "type":"Transportation"
        }
    ],
    "sg:phone":"+1 310 646 3107",
    "sg:postcode":"90045",
    "sg:province":"CA",
    "sg:tags":[
        "club",
        "membership"
    ],
    "wof:name":"United",
    "wof:placetype":"venue"
},
  "geometry": {"coordinates":[-118.39860899999999,33.943213],"type":"Point"}
}