{
  "type": "Feature",
  "properties": {
    "iso:country":"US",
    "sg:address":"349 W Highland Ave",
    "sg:city":"San Bernardino",
    "sg:classifiers":[
        {
            "category":"Personal",
            "subcategory":"Barber",
            "type":"Services"
        }
    ],
    "sg:phone":"+1 909 475 8002",
    "sg:postcode":"92405",
    "sg:province":"CA",
    "wof:name":"What's Happening Now Barber",
    "wof:placetype":"venue"
},
  "geometry": {"coordinates":[-117.290931,34.135895],"type":"Point"}
}