{
  "type": "Feature",
  "properties": {
    "addr:full":"20501 Ventura Blvd Ste 225 Woodland Hills CA 91364",
    "addr:housenumber":"20501",
    "addr:postcode":"91364",
    "addr:street":"Ventura Blvd Ste 225",
    "iso:country":"US",
    "sg:address":"20501 Ventura Blvd Ste 225",
    "sg:city":"Woodland Hills",
    "sg:classifiers":[
        {
            "category":"Professional",
            "subcategory":"Accounting & Tax Preparation",
            "type":"Services"
        }
    ],
    "sg:phone":"+1 818 713 8060",
    "sg:postcode":"91364",
    "sg:province":"CA",
    "sg:tags":[
        "accountant"
    ],
    "wof:name":"Berkson Steven M CPA",
    "wof:placetype":"venue"
},
  "geometry": {"coordinates":[-118.602997,34.1576],"type":"Point"}
}