{
  "type": "Feature",
  "properties": {
    "iso:country":"US",
    "sg:address":"15760 Ventura Blvd Ste 1520",
    "sg:city":"Encino",
    "sg:classifiers":[
        {
            "category":"Professional",
            "subcategory":"Lawyer & Legal Services",
            "type":"Services"
        }
    ],
    "sg:phone":"+1 818 501 0113",
    "sg:postcode":"91436",
    "sg:province":"CA",
    "sg:tags":[
        "divorce",
        "attorney",
        "practice",
        "family",
        "law"
    ],
    "sg:website":"http://www.gantmanlaw.com",
    "wof:name":"Law Offices of Robert Gantman",
    "wof:placetype":"venue"
},
  "geometry": {"coordinates":[-118.476219,34.155341],"type":"Point"}
}