{
  "type": "Feature",
  "properties": {
    "addr:full":"14850 Burbank Blvd Sherman Oaks CA 91411",
    "addr:housenumber":"14850",
    "addr:postcode":"91411",
    "addr:street":"Burbank Blvd",
    "iso:country":"US",
    "sg:address":"14850 Burbank Blvd",
    "sg:city":"Sherman Oaks",
    "sg:classifiers":[
        {
            "category":"Autos & Motor Vehicles",
            "subcategory":"Fuel & Gas Station",
            "type":"Retail Goods"
        }
    ],
    "sg:phone":"+1 818 786 8507",
    "sg:postcode":"91411",
    "sg:province":"CA",
    "sg:tags":[
        "oil"
    ],
    "wof:name":"Chevron",
    "wof:placetype":"venue"
},
  "geometry": {"coordinates":[-118.457087,34.172037],"type":"Point"}
}