{
  "type": "Feature",
  "properties": {
    "iso:country":"US",
    "sg:address":"821 Janelle Ct",
    "sg:city":"Ridgecrest",
    "sg:classifiers":[
        {
            "category":"Professional",
            "type":"Services"
        }
    ],
    "sg:phone":"+1 760 375 7798",
    "sg:postcode":"93555",
    "sg:province":"CA",
    "wof:name":"Kirk Winterly",
    "wof:placetype":"venue"
},
  "geometry": {"coordinates":[-117.686971,35.613085],"type":"Point"}
}