{
  "type": "Feature",
  "properties": {
    "addr:full":"2480 Oakvale Dr Shingle Springs CA 95682",
    "addr:postcode":"2480;95682",
    "addr:street":"Oakvale Dr",
    "iso:country":"US",
    "sg:address":"2480 Oakvale Dr",
    "sg:city":"Shingle Springs",
    "sg:classifiers":[
        {
            "category":"Wholesale",
            "subcategory":"Vending Machines",
            "type":"Manufacturing & Wholesale Goods"
        }
    ],
    "sg:phone":"+1 530 391 0895",
    "sg:postcode":"95682",
    "sg:province":"CA",
    "sg:tags":[
        "operator"
    ],
    "wof:name":"Jr Vending",
    "wof:placetype":"venue"
},
  "geometry": {"coordinates":[-120.930655,38.710688],"type":"Point"}
}