{
  "type": "Feature",
  "properties": {
    "addr:full":"71 E. 4th Avenue San Mateo CA 94401",
    "addr:housenumber":"71",
    "addr:postcode":"94401",
    "addr:street":"E. 4Th Avenue",
    "iso:country":"US",
    "sg:address":"71 E. 4th Avenue",
    "sg:city":"San Mateo",
    "sg:classifiers":[
        {
            "category":"Restaurant",
            "type":"Food & Drink"
        }
    ],
    "sg:phone":"+1 650 347 5777",
    "sg:postcode":"94401",
    "sg:province":"CA",
    "sg:tags":[
        "japanese"
    ],
    "wof:name":"Kaz Teriyaki Grill",
    "wof:placetype":"venue"
},
  "geometry": {"coordinates":[-122.32399700000001,37.563301],"type":"Point"}
}