{
  "type": "Feature",
  "properties": {
    "addr:full":"347 Wright Brothers Ave Livermore CA 94551",
    "addr:housenumber":"347",
    "addr:postcode":"94551",
    "addr:street":"Wright Brothers Ave",
    "iso:country":"US",
    "sg:address":"347 Wright Brothers Ave",
    "sg:city":"Livermore",
    "sg:classifiers":[
        {
            "category":"Professional",
            "subcategory":"Engineering",
            "type":"Services"
        },
        {
            "category":"Home & Garden",
            "subcategory":"Building Materials",
            "type":"Retail Goods"
        },
        {
            "category":"Building & Trades",
            "subcategory":"Construction",
            "type":"Services"
        }
    ],
    "sg:phone":"+1 925 828 1022",
    "sg:postcode":"94551",
    "sg:province":"CA",
    "sg:tags":[
        "system",
        "specialty",
        "heating",
        "equipment",
        "contractor",
        "air conditioning"
    ],
    "sg:website":"http://find.trane.com/tcs-dealer-528535?utm_source=YP&utm_medium=banner&utm_campaign=TL",
    "wof:name":"Superior Mechanical Services, Inc.",
    "wof:placetype":"venue"
},
  "geometry": {"coordinates":[-121.797574,37.689814],"type":"Point"}
}