{
  "type": "Feature",
  "properties": {
    "iso:country":"US",
    "sg:address":"3636 Old Santa Rita Rd",
    "sg:city":"Pleasanton",
    "sg:classifiers":[
        {
            "category":"Retail",
            "subcategory":"Auto Rental",
            "type":"Services"
        }
    ],
    "sg:phone":"+1 925 463 1320",
    "sg:postcode":"94588",
    "sg:province":"CA",
    "sg:tags":[
        "leasing",
        "tractor"
    ],
    "wof:name":"Bar Tractor Co",
    "wof:placetype":"venue"
},
  "geometry": {"coordinates":[-121.878698,37.696126],"type":"Point"}
}