{
  "type": "Feature",
  "properties": {
    "addr:full":"1903 Adelaide Way San Jose CA 95124",
    "addr:housenumber":"1903",
    "addr:postcode":"95124",
    "addr:street":"Adelaide Way",
    "iso:country":"US",
    "sg:address":"1903 Adelaide Way",
    "sg:city":"San Jose",
    "sg:classifiers":[
        {
            "category":"Building & Trades",
            "subcategory":"Electrical",
            "type":"Services"
        }
    ],
    "sg:phone":"+1 408 371 5308",
    "sg:postcode":"95124",
    "sg:province":"CA",
    "sg:tags":[
        "electrician"
    ],
    "wof:name":"Solex Electric",
    "wof:placetype":"venue"
},
  "geometry": {"coordinates":[-121.924004,37.244099],"type":"Point"}
}