{
  "type": "Feature",
  "properties": {
    "addr:full":"98 Discovery Irvine CA 92618",
    "addr:housenumber":"98",
    "addr:postcode":"92618",
    "addr:street":"Discovery",
    "iso:country":"US",
    "sg:address":"98 Discovery",
    "sg:city":"Irvine",
    "sg:classifiers":[
        {
            "category":"Professional",
            "subcategory":"Lawyer & Legal Services",
            "type":"Services"
        }
    ],
    "sg:phone":"+1 949 453 8881",
    "sg:postcode":"92618",
    "sg:province":"CA",
    "wof:name":"Takeuchi Law Office",
    "wof:placetype":"venue"
},
  "geometry": {"coordinates":[-117.75987499999999,33.661891],"type":"Point"}
}