{
  "type": "Feature",
  "properties": {
    "iso:country":"US",
    "sg:address":"325 Marion Ave",
    "sg:city":"Ben Lomond",
    "sg:classifiers":[
        {
            "category":"Education",
            "subcategory":"School",
            "type":"Public Place"
        }
    ],
    "sg:phone":"+1 831 336 9672",
    "sg:postcode":"95005",
    "sg:province":"CA",
    "wof:name":"San Lorenzo Valleyschool Dist",
    "wof:placetype":"venue"
},
  "geometry": {"coordinates":[-122.074212,37.0832],"type":"Point"}
}