{
  "type": "Feature",
  "properties": {
    "addr:full":"4806 W 1st St Santa Ana CA 92703",
    "addr:housenumber":"4806",
    "addr:postcode":"92703",
    "addr:street":"W 1St St",
    "iso:country":"US",
    "sg:address":"4806 W 1st St",
    "sg:city":"Santa Ana",
    "sg:classifiers":[
        {
            "category":"Professional",
            "subcategory":"Lawyer & Legal Services",
            "type":"Services"
        }
    ],
    "sg:phone":"+1 714 839 8951",
    "sg:postcode":"92703",
    "sg:province":"CA",
    "sg:tags":[
        "attorney"
    ],
    "wof:name":"AM Tam Legal Svc",
    "wof:placetype":"venue"
},
  "geometry": {"coordinates":[-117.93268500000001,33.744995],"type":"Point"}
}