{
  "type": "Feature",
  "properties": {
    "iso:country":"US",
    "sg:address":"29 N Milpas St",
    "sg:city":"Santa Barbara",
    "sg:classifiers":[
        {
            "category":"Restaurant",
            "type":"Food & Drink"
        }
    ],
    "sg:menulink":"http://www.allmenus.com/ca/santa-barbara/216294-mcdonalds/menu/",
    "sg:postcode":"93103",
    "sg:province":"CA",
    "sg:tags":[
        "burger",
        "american"
    ],
    "wof:name":"McDonald's",
    "wof:placetype":"venue"
},
  "geometry": {"coordinates":[-119.680205,34.422037],"type":"Point"}
}