{
  "type": "Feature",
  "properties": {
    "addr:full":"15554 Roscoe Blvd Van Nuys CA 91406",
    "addr:housenumber":"15554",
    "addr:postcode":"91406",
    "addr:street":"Roscoe Blvd",
    "iso:country":"US",
    "sg:address":"15554 Roscoe Blvd",
    "sg:city":"Van Nuys",
    "sg:classifiers":[
        {
            "category":"Restaurant",
            "type":"Food & Drink"
        }
    ],
    "sg:menulink":"http://www.allmenus.com/ca/san-fernando-valley/171790-burger-king/menu/",
    "sg:phone":"+1 818 892 5411",
    "sg:postcode":"91406",
    "sg:province":"CA",
    "sg:tags":[
        "burger",
        "american"
    ],
    "wof:name":"Burger King",
    "wof:placetype":"venue"
},
  "geometry": {"coordinates":[-118.471622,34.220897],"type":"Point"}
}