{
  "type": "Feature",
  "properties": {
    "iso:country":"US",
    "sg:address":"149 W Badillo St",
    "sg:city":"Covina",
    "sg:classifiers":[
        {
            "category":"Building & Trades",
            "subcategory":"Construction",
            "type":"Services"
        },
        {
            "category":"Manufacturing",
            "subcategory":"Building Materials",
            "type":"Manufacturing & Wholesale Goods"
        },
        {
            "category":"Home & Garden",
            "subcategory":"Carpets & Floor Coverings",
            "type":"Retail Goods"
        }
    ],
    "sg:phone":"+1 626 915 3131",
    "sg:postcode":"91723",
    "sg:province":"CA",
    "sg:tags":[
        "tile-contractors",
        "rug",
        "marble-cultured"
    ],
    "sg:website":"http://www.expressdesigncenter.com",
    "wof:name":"Express Flooring Design Center",
    "wof:placetype":"venue"
},
  "geometry": {"coordinates":[-117.89174,34.086261],"type":"Point"}
}