{
  "type": "Feature",
  "properties": {
    "addr:full":"1810 Professional Drive Sacramento CA 95825",
    "addr:housenumber":"1810",
    "addr:postcode":"95825",
    "addr:street":"Professional Drive",
    "iso:country":"US",
    "sg:address":"1810 Professional Drive",
    "sg:city":"Sacramento",
    "sg:classifiers":[
        {
            "category":"Health Services",
            "subcategory":"Dentist",
            "type":"Services"
        }
    ],
    "sg:phone":"+1 916 971 3461",
    "sg:postcode":"95825",
    "sg:province":"CA",
    "sg:website":"www.capitolperiodontal.com",
    "wof:name":"Roberts Judson R DDS",
    "wof:placetype":"venue"
},
  "geometry": {"coordinates":[-121.387004,38.597474],"type":"Point"}
}