{
  "type": "Feature",
  "properties": {
    "addr:full":"45 Mitchell Blvd San Rafael CA 94903",
    "addr:housenumber":"45",
    "addr:postcode":"94903",
    "addr:street":"Mitchell Blvd",
    "iso:country":"US",
    "sg:address":"45 Mitchell Blvd",
    "sg:city":"San Rafael",
    "sg:classifiers":[
        {
            "category":"Banks & Credit Unions",
            "subcategory":"Bank",
            "type":"Services"
        }
    ],
    "sg:phone":"+1 415 492 9284",
    "sg:postcode":"94903",
    "sg:province":"CA",
    "sg:tags":[
        "loan",
        "real estate"
    ],
    "wof:name":"Farhad Nawab",
    "wof:placetype":"venue"
},
  "geometry": {"coordinates":[-122.538984,38.017152],"type":"Point"}
}