{
  "type": "Feature",
  "properties": {
    "addr:full":"3714 Co Rd 99W Orland CA 95963",
    "addr:housenumber":"3714;99w",
    "addr:postcode":"95963",
    "addr:street":"Co Rd",
    "iso:country":"US",
    "sg:address":"3714 Co Rd 99W",
    "sg:city":"Orland",
    "sg:classifiers":[
        {
            "category":"Retail",
            "subcategory":"Animal Services",
            "type":"Services"
        }
    ],
    "sg:phone":"+1 530 865 3367",
    "sg:postcode":"95963",
    "sg:province":"CA",
    "sg:tags":[
        "pet",
        "grooming",
        "washing"
    ],
    "wof:name":"Dog House",
    "wof:placetype":"venue"
},
  "geometry": {"coordinates":[-122.19661600000001,39.689015],"type":"Point"}
}