{
  "type": "Feature",
  "properties": {
    "iso:country":"US",
    "sg:address":"1341 Coldwell Ave",
    "sg:city":"Modesto",
    "sg:classifiers":[
        {
            "category":"Restaurant",
            "type":"Food & Drink"
        }
    ],
    "sg:phone":"+1 209 522 8476",
    "sg:postcode":"95350",
    "sg:province":"CA",
    "sg:tags":[
        "mexican"
    ],
    "wof:name":"Senor Campos Restaurant",
    "wof:placetype":"venue"
},
  "geometry": {"coordinates":[-121.01300000000001,37.653099],"type":"Point"}
}