{
  "type": "Feature",
  "properties": {
    "iso:country":"US",
    "sg:address":"3720 Sonoma Blvd",
    "sg:city":"Vallejo",
    "sg:classifiers":[
        {
            "category":"Restaurant",
            "type":"Food & Drink"
        }
    ],
    "sg:phone":"+1 707 558 9236",
    "sg:postcode":"94589",
    "sg:province":"CA",
    "wof:name":"Tapioca Express",
    "wof:placetype":"venue"
},
  "geometry": {"coordinates":[-122.255417,38.126829],"type":"Point"}
}