{
  "type": "Feature",
  "properties": {
    "iso:country":"US",
    "sg:address":"7341 N 1st St",
    "sg:city":"Fresno",
    "sg:classifiers":[
        {
            "category":"Health Services",
            "subcategory":"Health Practitioner",
            "type":"Services"
        }
    ],
    "sg:phone":"+1 559 431 8893",
    "sg:postcode":"93720",
    "sg:province":"CA",
    "sg:tags":[
        "psychologist"
    ],
    "wof:name":"Bar Psychological Group",
    "wof:placetype":"venue"
},
  "geometry": {"coordinates":[-119.774745,36.844296],"type":"Point"}
}