{
  "type": "Feature",
  "properties": {
    "iso:country":"US",
    "sg:address":"8532 Cleta St",
    "sg:city":"Downey",
    "sg:classifiers":[
        {
            "category":"Professional",
            "subcategory":"Computer Services",
            "type":"Services"
        }
    ],
    "sg:phone":"+1 562 869 4435",
    "sg:postcode":"90241",
    "sg:province":"CA",
    "sg:tags":[
        "repair"
    ],
    "wof:name":"P C Help Desk the",
    "wof:placetype":"venue"
},
  "geometry": {"coordinates":[-118.132004,33.932701],"type":"Point"}
}