{
  "type": "Feature",
  "properties": {
    "iso:country":"US",
    "sg:address":"264 Fowles St",
    "sg:city":"Oceanside",
    "sg:classifiers":[
        {
            "category":"Building & Trades",
            "subcategory":"Construction",
            "type":"Services"
        }
    ],
    "sg:phone":"+1 760 433 0989",
    "sg:postcode":"92054",
    "sg:province":"CA",
    "sg:tags":[
        "hanging",
        "contractor"
    ],
    "wof:name":"Jj Painting N Decorating",
    "wof:placetype":"venue"
},
  "geometry": {"coordinates":[-117.34468200000001,33.206287],"type":"Point"}
}