{
  "type": "Feature",
  "properties": {
    "iso:country":"US",
    "sg:address":"7800 Pacific Blvd",
    "sg:city":"Huntington Park",
    "sg:classifiers":[
        {
            "category":"Utilities",
            "type":"Services"
        }
    ],
    "sg:phone":"+1 323 581 7169",
    "sg:postcode":"90255",
    "sg:province":"CA",
    "sg:tags":[
        "sweeping"
    ],
    "wof:name":"MAG Sweeping",
    "wof:placetype":"venue"
},
  "geometry": {"coordinates":[-118.22520900000001,33.967515],"type":"Point"}
}