{
  "type": "Feature",
  "properties": {
    "addr:full":"1919 Laguna St Santa Barbara CA 93101",
    "addr:housenumber":"1919",
    "addr:postcode":"93101",
    "addr:street":"Laguna St",
    "iso:country":"US",
    "sg:address":"1919 Laguna St",
    "sg:city":"Santa Barbara",
    "sg:classifiers":[
        {
            "category":"Education",
            "subcategory":"School",
            "type":"Public Place"
        }
    ],
    "sg:phone":"+1 805 563 6739",
    "sg:postcode":"93101",
    "sg:province":"CA",
    "wof:name":"Roosevelt Children's Ctr",
    "wof:placetype":"venue"
},
  "geometry": {"coordinates":[-119.709351,34.434544],"type":"Point"}
}