{
  "type": "Feature",
  "properties": {
    "iso:country":"US",
    "sg:address":"105 Frontier Dr",
    "sg:city":"Jackson",
    "sg:classifiers":[
        {
            "category":"Building & Trades",
            "subcategory":"Electrical",
            "type":"Services"
        }
    ],
    "sg:phone":"+1 209 223 1875",
    "sg:postcode":"95642",
    "sg:province":"CA",
    "sg:tags":[
        "electrical",
        "contractor"
    ],
    "wof:name":"Scapuzzi Electric",
    "wof:placetype":"venue"
},
  "geometry": {"coordinates":[-120.75976300000001,38.342009],"type":"Point"}
}