{
  "type": "Feature",
  "properties": {
    "addr:full":"1315 Van Ness Ave Fresno CA 93721",
    "addr:housenumber":"1315",
    "addr:postcode":"93721",
    "addr:street":"Van Ness Ave",
    "iso:country":"US",
    "sg:address":"1315 Van Ness Ave",
    "sg:city":"Fresno",
    "sg:classifiers":[
        {
            "category":"Manufacturing",
            "subcategory":"Printing",
            "type":"Manufacturing & Wholesale Goods"
        }
    ],
    "sg:phone":"+1 559 490 3425",
    "sg:postcode":"93721",
    "sg:province":"CA",
    "sg:tags":[
        "newspaper"
    ],
    "wof:name":"Northview Newspaper",
    "wof:placetype":"venue"
},
  "geometry": {"coordinates":[-119.793418,36.738426],"type":"Point"}
}