{
  "type": "Feature",
  "properties": {
    "iso:country":"US",
    "sg:address":"9431 Slauson Ave",
    "sg:city":"Pico Rivera",
    "sg:classifiers":[
        {
            "category":"Restaurant",
            "type":"Food & Drink"
        }
    ],
    "sg:menulink":"http://www.allmenus.com/ca/whittier/168817-el-pollo-loco/menu/",
    "sg:phone":"+1 562 942 2567",
    "sg:postcode":"90660",
    "sg:province":"CA",
    "sg:tags":[
        "american",
        "mexican",
        "tex-mex"
    ],
    "wof:name":"El Pollo Loco",
    "wof:placetype":"venue"
},
  "geometry": {"coordinates":[-118.095826,33.968258],"type":"Point"}
}