{
  "type": "Feature",
  "properties": {
    "addr:full":"17630 E Millburgh Ave Azusa CA 91702",
    "addr:housenumber":"17630",
    "addr:postcode":"91702",
    "addr:street":"E Millburgh Ave",
    "iso:country":"US",
    "sg:address":"17630 E Millburgh Ave",
    "sg:city":"Azusa",
    "sg:classifiers":[
        {
            "category":"Building & Trades",
            "subcategory":"Construction",
            "type":"Services"
        }
    ],
    "sg:phone":"+1 626 334 2430",
    "sg:postcode":"91702",
    "sg:province":"CA",
    "sg:tags":[
        "roofing",
        "contractor"
    ],
    "wof:name":"Amigo Roofing",
    "wof:placetype":"venue"
},
  "geometry": {"coordinates":[-117.904681,34.108006],"type":"Point"}
}