{
  "type": "Feature",
  "properties": {
    "iso:country":"US",
    "sg:address":"4660 American Ave",
    "sg:city":"Bakersfield",
    "sg:classifiers":[
        {
            "category":"Real Estate",
            "subcategory":"Architect",
            "type":"Services"
        }
    ],
    "sg:phone":"+1 661 834 1331",
    "sg:postcode":"93309",
    "sg:province":"CA",
    "sg:website":"www.ksagrouparchitects.com",
    "wof:name":"KSA Group Architects",
    "wof:placetype":"venue"
},
  "geometry": {"coordinates":[-119.053697,35.339847],"type":"Point"}
}