{
  "type": "Feature",
  "properties": {
    "addr:full":"312 Mission Ave Oceanside CA 92054",
    "addr:housenumber":"312",
    "addr:postcode":"92054",
    "addr:street":"Mission Ave",
    "iso:country":"US",
    "sg:address":"312 Mission Ave",
    "sg:city":"Oceanside",
    "sg:classifiers":[
        {
            "category":"Real Estate",
            "subcategory":"Real Estate Services",
            "type":"Services"
        }
    ],
    "sg:phone":"+1 760 967 0435",
    "sg:postcode":"92054",
    "sg:province":"CA",
    "sg:tags":[
        "home",
        "inspector"
    ],
    "wof:name":"Award Group the",
    "wof:placetype":"venue"
},
  "geometry": {"coordinates":[-117.38099699999999,33.195202],"type":"Point"}
}