{
  "type": "Feature",
  "properties": {
    "iso:country":"US",
    "sg:address":"12302 Inglewood Ave",
    "sg:city":"Hawthorne",
    "sg:classifiers":[
        {
            "category":"Wholesale",
            "subcategory":"Computers",
            "type":"Manufacturing & Wholesale Goods"
        }
    ],
    "sg:phone":"+1 310 973 7084",
    "sg:postcode":"90250",
    "sg:province":"CA",
    "sg:tags":[
        "clothing"
    ],
    "wof:name":"Krave International",
    "wof:placetype":"venue"
},
  "geometry": {"coordinates":[-118.361201,33.920075],"type":"Point"}
}