{
  "type": "Feature",
  "properties": {
    "iso:country":"US",
    "sg:address":"1551 Shelter Island Dr",
    "sg:city":"San Diego",
    "sg:classifiers":[
        {
            "category":"Travel",
            "subcategory":"Hotels & Motels",
            "type":"Entertainment"
        }
    ],
    "sg:phone":"+1 800 566 2524",
    "sg:postcode":"92106",
    "sg:province":"CA",
    "sg:website":"resortkonakai.com/",
    "wof:name":"Kona Kai Resort, Spa, & Marina",
    "wof:placetype":"venue"
},
  "geometry": {"coordinates":[-117.231283,32.710503],"type":"Point"}
}