{
  "type": "Feature",
  "properties": {
    "addr:full":"3851 Crowell Rd Turlock CA 95382",
    "addr:housenumber":"3851",
    "addr:postcode":"95382",
    "addr:street":"Crowell Rd",
    "iso:country":"US",
    "sg:address":"3851 Crowell Rd",
    "sg:city":"Turlock",
    "sg:classifiers":[
        {
            "category":"Restaurant",
            "type":"Food & Drink"
        }
    ],
    "sg:phone":"+1 209 667 1010",
    "sg:postcode":"95382",
    "sg:province":"CA",
    "sg:tags":[
        "pizza"
    ],
    "wof:name":"Vito's Restaurante & Pizzaria",
    "wof:placetype":"venue"
},
  "geometry": {"coordinates":[-120.862999,37.527901],"type":"Point"}
}