{
  "type": "Feature",
  "properties": {
    "addr:full":"900 Alamo Dr Vacaville CA 95688",
    "addr:housenumber":"900",
    "addr:postcode":"95688",
    "addr:street":"Alamo Dr",
    "iso:country":"US",
    "sg:address":"900 Alamo Dr",
    "sg:city":"Vacaville",
    "sg:classifiers":[
        {
            "category":"Food & Beverages",
            "subcategory":"Bakery",
            "type":"Retail Goods"
        }
    ],
    "sg:phone":"+1 707 446 4481",
    "sg:postcode":"95688",
    "sg:province":"CA",
    "sg:tags":[
        "baker"
    ],
    "wof:name":"Solano Baking Co",
    "wof:placetype":"venue"
},
  "geometry": {"coordinates":[-121.998636,38.348375],"type":"Point"}
}