{
  "type": "Feature",
  "properties": {
    "iso:country":"US",
    "sg:address":"1726 N Main St",
    "sg:city":"Manteca",
    "sg:classifiers":[
        {
            "category":"Building & Trades",
            "subcategory":"Pest Control",
            "type":"Services"
        }
    ],
    "sg:phone":"+1 209 334 1952",
    "sg:postcode":"95336",
    "sg:province":"CA",
    "wof:name":"Consumer Choice Pest Control",
    "wof:placetype":"venue"
},
  "geometry": {"coordinates":[-121.21737899999999,37.822706],"type":"Point"}
}