{
  "type": "Feature",
  "properties": {
    "addr:full":"2930 Broadway Eureka CA 95501",
    "addr:housenumber":"2930",
    "addr:postcode":"95501",
    "addr:street":"Broadway",
    "iso:country":"US",
    "sg:address":"2930 Broadway",
    "sg:city":"Eureka",
    "sg:classifiers":[
        {
            "category":"Utilities",
            "subcategory":"Electric",
            "type":"Services"
        },
        {
            "category":"Building & Trades",
            "subcategory":"Construction",
            "type":"Services"
        },
        {
            "category":"Building & Trades",
            "subcategory":"Electrical",
            "type":"Services"
        },
        {
            "category":"Building & Trades",
            "subcategory":"Plumbing",
            "type":"Services"
        },
        {
            "category":"Home & Garden",
            "subcategory":"Building Materials",
            "type":"Retail Goods"
        },
        {
            "category":"Building & Trades",
            "subcategory":"Cleaning & Sanitation",
            "type":"Services"
        }
    ],
    "sg:phone":"+1 707 445 1435",
    "sg:postcode":"95501",
    "sg:province":"CA",
    "sg:tags":[
        "heater",
        "plumber",
        "industrial",
        "specialty",
        "repair",
        "systems-repairing",
        "system",
        "contractor",
        "water",
        "equipment",
        "furnaces-heating",
        "furnaces-repairing",
        "contractors-commercial",
        "ventilating",
        "heating",
        "air conditioning",
        "engineer"
    ],
    "sg:website":"http://www.evansmechanical.com",
    "wof:name":"Evans Mechanical",
    "wof:placetype":"venue"
},
  "geometry": {"coordinates":[-124.18498200000001,40.781081],"type":"Point"}
}