{
  "type": "Feature",
  "properties": {
    "addr:full":"122 De Anza Blvd San Mateo CA 94402",
    "addr:housenumber":"122",
    "addr:postcode":"94402",
    "addr:street":"De Anza Blvd",
    "iso:country":"US",
    "sg:address":"122 De Anza Blvd",
    "sg:city":"San Mateo",
    "sg:classifiers":[
        {
            "category":"Retail",
            "subcategory":"Veterinary Services",
            "type":"Services"
        }
    ],
    "sg:phone":"+1 650 341 3438",
    "sg:postcode":"94402",
    "sg:province":"CA",
    "sg:tags":[
        "veterinarian"
    ],
    "sg:website":"www.crystalspringsph.com",
    "wof:name":"Crystal Springs Veterinary",
    "wof:placetype":"venue"
},
  "geometry": {"coordinates":[-122.337344,37.520793],"type":"Point"}
}