{
  "type": "Feature",
  "properties": {
    "iso:country":"US",
    "sg:address":"319 S Arroyo Pkwy Ste 9",
    "sg:city":"Pasadena",
    "sg:classifiers":[
        {
            "category":"Restaurant",
            "type":"Food & Drink"
        }
    ],
    "sg:phone":"+1 626 683 9865",
    "sg:postcode":"91105",
    "sg:province":"CA",
    "sg:tags":[
        "korean",
        "japanese"
    ],
    "sg:website":"www.teriandyaki.com",
    "wof:name":"Teri & Yaki",
    "wof:placetype":"venue"
},
  "geometry": {"coordinates":[-118.14748400000001,34.140142],"type":"Point"}
}