{
  "type": "Feature",
  "properties": {
    "iso:country":"US",
    "sg:address":"3371 16th St",
    "sg:city":"San Francisco",
    "sg:classifiers":[
        {
            "category":"Education",
            "subcategory":"School",
            "type":"Public Place"
        }
    ],
    "sg:phone":"+1 415 861 7673",
    "sg:postcode":"94114",
    "sg:province":"CA",
    "sg:tags":[
        "elementary"
    ],
    "sg:website":"www.missiondolores.org",
    "wof:name":"Mission Dolores School",
    "wof:placetype":"venue"
},
  "geometry": {"coordinates":[-122.427797,37.76459],"type":"Point"}
}