{
  "type": "Feature",
  "properties": {
    "iso:country":"US",
    "sg:address":"15 Van Dyke St",
    "sg:city":"Thousand Oaks",
    "sg:classifiers":[
        {
            "category":"Recreation",
            "type":"Entertainment"
        }
    ],
    "sg:phone":"+1 805 495 8687",
    "sg:postcode":"91360",
    "sg:province":"CA",
    "sg:tags":[
        "tennis",
        "court"
    ],
    "wof:name":"Horizon View Club",
    "wof:placetype":"venue"
},
  "geometry": {"coordinates":[-118.878026,34.208759],"type":"Point"}
}