{
  "type": "Feature",
  "properties": {
    "iso:country":"US",
    "sg:address":"5400 W Hillsdale Ave",
    "sg:city":"Visalia",
    "sg:classifiers":[
        {
            "category":"Health Services",
            "subcategory":"Doctor",
            "type":"Services"
        }
    ],
    "sg:phone":"+1 559 738 7583",
    "sg:postcode":"93291",
    "sg:province":"CA",
    "sg:tags":[
        "physician",
        "clinic",
        "surgeon"
    ],
    "wof:name":"Visalia Medical Clinic",
    "wof:placetype":"venue"
},
  "geometry": {"coordinates":[-119.352918,36.32954],"type":"Point"}
}