{
  "type": "Feature",
  "properties": {
    "iso:country":"US",
    "sg:address":"6705 Barberry Pl",
    "sg:city":"Carlsbad",
    "sg:classifiers":[
        {
            "category":"Wholesale",
            "subcategory":"Chemicals & Plastics",
            "type":"Manufacturing & Wholesale Goods"
        }
    ],
    "sg:phone":"+1 760 431 9934",
    "sg:postcode":"92011",
    "sg:province":"CA",
    "sg:tags":[
        "adhesive",
        "glue"
    ],
    "wof:name":"K R Anderson Inc",
    "wof:placetype":"venue"
},
  "geometry": {"coordinates":[-117.300397,33.11295],"type":"Point"}
}