{
  "type": "Feature",
  "properties": {
    "addr:full":"1402 Mallard Way Sunnyvale CA 94087",
    "addr:housenumber":"1402",
    "addr:postcode":"94087",
    "addr:street":"Mallard Way",
    "iso:country":"US",
    "sg:address":"1402 Mallard Way",
    "sg:city":"Sunnyvale",
    "sg:classifiers":[
        {
            "category":"Social Services",
            "subcategory":"Adult Care",
            "type":"Services"
        }
    ],
    "sg:phone":"+1 408 737 8055",
    "sg:postcode":"94087",
    "sg:province":"CA",
    "sg:tags":[
        "home",
        "residential"
    ],
    "wof:name":"Serenity Homes",
    "wof:placetype":"venue"
},
  "geometry": {"coordinates":[-122.01510500000001,37.348083],"type":"Point"}
}