{
  "type": "Feature",
  "properties": {
    "iso:country":"US",
    "sg:address":"11220 Clairemont Mesa Blvd Tierrasanta Recreation Center",
    "sg:city":"San Diego",
    "sg:classifiers":[
        {
            "category":"Arts & Performance",
            "subcategory":"Dance",
            "type":"Entertainment"
        }
    ],
    "sg:phone":"+1 858 876 5327",
    "sg:postcode":"92124",
    "sg:province":"CA",
    "sg:tags":[
        "school"
    ],
    "sg:website":"dancetoevolve.com",
    "wof:name":"EvOLvE Dance",
    "wof:placetype":"venue"
},
  "geometry": {"coordinates":[-117.08189,32.826855],"type":"Point"}
}