{
  "type": "Feature",
  "properties": {
    "addr:full":"7059 Village Pkwy Dublin CA 94568",
    "addr:housenumber":"7059",
    "addr:postcode":"94568",
    "addr:street":"Village Pkwy",
    "iso:country":"US",
    "sg:address":"7059 Village Pkwy",
    "sg:city":"Dublin",
    "sg:classifiers":[
        {
            "category":"Personal",
            "subcategory":"Beauty Salon",
            "type":"Services"
        }
    ],
    "sg:phone":"+1 925 895 6154",
    "sg:postcode":"94568",
    "sg:province":"CA",
    "sg:tags":[
        "manicuring"
    ],
    "wof:name":"Erica Miller",
    "wof:placetype":"venue"
},
  "geometry": {"coordinates":[-121.925776,37.708649],"type":"Point"}
}