{
  "type": "Feature",
  "properties": {
    "addr:full":"540 N Grant St Stockton CA 95202",
    "addr:housenumber":"540",
    "addr:postcode":"95202",
    "addr:street":"N Grant St",
    "iso:country":"US",
    "sg:address":"540 N Grant St",
    "sg:city":"Stockton",
    "sg:classifiers":[
        {
            "category":"Shopping",
            "subcategory":"Hobbies, Toys, & Games",
            "type":"Retail Goods"
        }
    ],
    "sg:phone":"+1 209 948 1544",
    "sg:postcode":"95202",
    "sg:province":"CA",
    "wof:name":"Sam Sambath",
    "wof:placetype":"venue"
},
  "geometry": {"coordinates":[-121.282134,37.959856],"type":"Point"}
}