{
  "type": "Feature",
  "properties": {
    "addr:full":"2580 Springs Rd Vallejo CA 94591",
    "addr:postcode":"2580;94591",
    "addr:street":"Springs Rd",
    "iso:country":"US",
    "sg:address":"2580 Springs Rd",
    "sg:city":"Vallejo",
    "sg:classifiers":[
        {
            "category":"Food & Beverages",
            "subcategory":"Groceries & Convenience Stores",
            "type":"Retail Goods"
        }
    ],
    "sg:phone":"+1 707 648 3058",
    "sg:postcode":"94591",
    "sg:province":"CA",
    "sg:tags":[
        "money",
        "order"
    ],
    "sg:website":"http://www.7-eleven.com",
    "wof:name":"7-Eleven",
    "wof:placetype":"venue"
},
  "geometry": {"coordinates":[-122.209278,38.105936],"type":"Point"}
}