{
  "type": "Feature",
  "properties": {
    "addr:full":"5010 Avenue 216 Tulare CA 93274",
    "addr:housenumber":"5010",
    "addr:postcode":"93274",
    "addr:street":"Avenue 216",
    "iso:country":"US",
    "sg:address":"5010 Avenue 216",
    "sg:city":"Tulare",
    "sg:classifiers":[
        {
            "category":"Manufacturing",
            "subcategory":"Food",
            "type":"Manufacturing & Wholesale Goods"
        },
        {
            "category":"Farming",
            "subcategory":"Farm",
            "type":"Manufacturing & Wholesale Goods"
        }
    ],
    "sg:phone":"+1 559 688 7042",
    "sg:postcode":"93274",
    "sg:province":"CA",
    "sg:tags":[
        "corn",
        "product"
    ],
    "wof:name":"Watte Cousins Farms",
    "wof:placetype":"venue"
},
  "geometry": {"coordinates":[-119.458281,36.181088],"type":"Point"}
}