{
  "type": "Feature",
  "properties": {
    "addr:full":"3300 Newport Blvd Newport Beach CA 92663",
    "addr:housenumber":"3300",
    "addr:postcode":"92663",
    "addr:street":"Newport Blvd",
    "iso:country":"US",
    "sg:address":"3300 Newport Blvd",
    "sg:city":"Newport Beach",
    "sg:classifiers":[
        {
            "category":"Restaurant",
            "type":"Food & Drink"
        }
    ],
    "sg:postcode":"92663",
    "sg:province":"CA",
    "sg:tags":[
        "mexican"
    ],
    "wof:name":"KJeh Hoo-Hah Taco Truck",
    "wof:placetype":"venue"
},
  "geometry": {"coordinates":[-117.93047900000001,33.616498],"type":"Point"}
}