{
  "type": "Feature",
  "properties": {
    "iso:country":"US",
    "sg:address":"1782 D St",
    "sg:city":"Hayward",
    "sg:classifiers":[
        {
            "category":"Real Estate",
            "subcategory":"Real Estate Operator",
            "type":"Services"
        }
    ],
    "sg:phone":"+1 510 886 8495",
    "sg:postcode":"94541",
    "sg:province":"CA",
    "sg:tags":[
        "apartment"
    ],
    "wof:name":"Ridgecrest Apartments",
    "wof:placetype":"venue"
},
  "geometry": {"coordinates":[-122.066002,37.677799],"type":"Point"}
}