{
  "type": "Feature",
  "properties": {
    "addr:full":"3904 Convoy St Ste 105 San Diego CA 92111",
    "addr:housenumber":"3904",
    "addr:postcode":"92111",
    "addr:street":"Convoy St Ste 105",
    "iso:country":"US",
    "sg:address":"3904 Convoy St Ste 105",
    "sg:city":"San Diego",
    "sg:classifiers":[
        {
            "category":"Restaurant",
            "type":"Food & Drink"
        }
    ],
    "sg:phone":"+1 858 565 8861",
    "sg:postcode":"92111",
    "sg:province":"CA",
    "sg:tags":[
        "thai"
    ],
    "wof:name":"Chilies Thai Gourmet",
    "wof:placetype":"venue"
},
  "geometry": {"coordinates":[-117.152818,32.813667],"type":"Point"}
}