{
  "type": "Feature",
  "properties": {
    "addr:full":"2280 Ward Ave Simi Valley CA 93065",
    "addr:housenumber":"2280",
    "addr:postcode":"93065",
    "addr:street":"Ward Ave",
    "iso:country":"US",
    "sg:address":"2280 Ward Ave",
    "sg:city":"Simi Valley",
    "sg:classifiers":[
        {
            "category":"Wholesale",
            "subcategory":"Durable Goods & Equipment",
            "type":"Manufacturing & Wholesale Goods"
        }
    ],
    "sg:phone":"+1 805 579 1200",
    "sg:postcode":"93065",
    "sg:province":"CA",
    "sg:tags":[
        "prerecorded",
        "record",
        "tape"
    ],
    "wof:name":"Cinram Inc",
    "wof:placetype":"venue"
},
  "geometry": {"coordinates":[-118.785252,34.275464],"type":"Point"}
}