{
  "type": "Feature",
  "properties": {
    "addr:full":"15329 Vose St Van Nuys CA 91406",
    "addr:postcode":"15329;91406",
    "addr:street":"Vose St",
    "iso:country":"US",
    "sg:address":"15329 Vose St",
    "sg:city":"Van Nuys",
    "sg:classifiers":[
        {
            "category":"Shopping",
            "type":"Retail Goods"
        }
    ],
    "sg:phone":"+1 818 901 6930",
    "sg:postcode":"91406",
    "sg:province":"CA",
    "sg:tags":[
        "merchandise"
    ],
    "wof:name":"Africway",
    "wof:placetype":"venue"
},
  "geometry": {"coordinates":[-118.46785800000001,34.198525],"type":"Point"}
}