{
  "type": "Feature",
  "properties": {
    "addr:full":"952 Atlantic Blvd B Los Angeles CA 90022",
    "addr:housenumber":"952",
    "addr:postcode":"90022",
    "addr:street":"Atlantic Blvd B",
    "iso:country":"US",
    "sg:address":"952 Atlantic Blvd B",
    "sg:city":"Los Angeles",
    "sg:classifiers":[
        {
            "category":"Professional",
            "subcategory":"Computer Services",
            "type":"Services"
        }
    ],
    "sg:phone":"+1 323 526 1858",
    "sg:postcode":"90022",
    "sg:province":"CA",
    "sg:tags":[
        "repair"
    ],
    "wof:name":"Power PC Solutions",
    "wof:placetype":"venue"
},
  "geometry": {"coordinates":[-118.157397,34.018921],"type":"Point"}
}