{
  "type": "Feature",
  "properties": {
    "addr:full":"1355 Lawrence Dr Newbury Park CA 91320",
    "addr:housenumber":"1355",
    "addr:postcode":"91320",
    "addr:street":"Lawrence Dr",
    "iso:country":"US",
    "sg:address":"1355 Lawrence Dr",
    "sg:city":"Newbury Park",
    "sg:classifiers":[
        {
            "category":"Retail",
            "subcategory":"Auto Repair",
            "type":"Services"
        }
    ],
    "sg:phone":"+1 805 375 8411",
    "sg:postcode":"91320",
    "sg:province":"CA",
    "sg:tags":[
        "transmission"
    ],
    "wof:name":"Advanced Trans Transmissions",
    "wof:placetype":"venue"
},
  "geometry": {"coordinates":[-118.9299,34.195289],"type":"Point"}
}