{
  "type": "Feature",
  "properties": {
    "addr:full":"8330 Beverly Blvd Los Angeles CA 90048",
    "addr:housenumber":"8330",
    "addr:postcode":"90048",
    "addr:street":"Beverly Blvd",
    "iso:country":"US",
    "sg:address":"8330 Beverly Blvd",
    "sg:city":"Los Angeles",
    "sg:classifiers":[
        {
            "category":"Shopping",
            "subcategory":"Bicycles & Sporting Goods",
            "type":"Retail Goods"
        },
        {
            "category":"Sports & Exercise",
            "subcategory":"Bicycle Rental",
            "type":"Entertainment"
        }
    ],
    "sg:phone":"+1 323 653 6900",
    "sg:postcode":"90048",
    "sg:province":"CA",
    "sg:tags":[
        "bike"
    ],
    "sg:website":"www.imartin.com",
    "wof:name":"I Martin Bicycles",
    "wof:placetype":"venue"
},
  "geometry": {"coordinates":[-118.371336,34.075772],"type":"Point"}
}