{
  "type": "Feature",
  "properties": {
    "iso:country":"US",
    "sg:address":"2373 Sundance Cir",
    "sg:city":"Oceanside",
    "sg:classifiers":[
        {
            "category":"Building & Trades",
            "subcategory":"Construction",
            "type":"Services"
        }
    ],
    "sg:phone":"+1 760 941 5671",
    "sg:postcode":"92056",
    "sg:province":"CA",
    "sg:tags":[
        "contractor"
    ],
    "wof:name":"Huston Builders",
    "wof:placetype":"venue"
},
  "geometry": {"coordinates":[-117.273788,33.207632],"type":"Point"}
}