{
  "type": "Feature",
  "properties": {
    "addr:full":"14114 Sherman Way Van Nuys CA 91405",
    "addr:housenumber":"14114",
    "addr:postcode":"91405",
    "addr:street":"Sherman Way",
    "iso:country":"US",
    "sg:address":"14114 Sherman Way",
    "sg:city":"Van Nuys",
    "sg:classifiers":[
        {
            "category":"Restaurant",
            "type":"Food & Drink"
        }
    ],
    "sg:phone":"+1 818 902 0528",
    "sg:postcode":"91405",
    "sg:province":"CA",
    "wof:name":"LA Playita To Go",
    "wof:placetype":"venue"
},
  "geometry": {"coordinates":[-118.442914,34.20112],"type":"Point"}
}