{
  "type": "Feature",
  "properties": {
    "iso:country":"US",
    "sg:address":"20626 Ritanna Ct",
    "sg:city":"Saratoga",
    "sg:classifiers":[
        {
            "category":"Shopping",
            "subcategory":"Computers & Home Electronics",
            "type":"Retail Goods"
        }
    ],
    "sg:phone":"+1 408 255 1444",
    "sg:postcode":"95070",
    "sg:province":"CA",
    "sg:tags":[
        "software"
    ],
    "wof:name":"Swift Tech Software",
    "wof:placetype":"venue"
},
  "geometry": {"coordinates":[-122.034778,37.291853],"type":"Point"}
}