{
  "type": "Feature",
  "properties": {
    "iso:country":"US",
    "sg:address":"328 W Elk Ave",
    "sg:city":"Glendale",
    "sg:classifiers":[
        {
            "category":"Professional",
            "type":"Services"
        }
    ],
    "sg:phone":"+1 818 662 5107",
    "sg:postcode":"91204",
    "sg:province":"CA",
    "wof:name":"Azat Grigoryan",
    "wof:placetype":"venue"
},
  "geometry": {"coordinates":[-118.260165,34.141598],"type":"Point"}
}