{
  "type": "Feature",
  "properties": {
    "addr:full":"2166 E Mountain St Pasadena CA 91104",
    "addr:housenumber":"2166",
    "addr:postcode":"91104",
    "addr:street":"E Mountain St",
    "iso:country":"US",
    "sg:address":"2166 E Mountain St",
    "sg:city":"Pasadena",
    "sg:classifiers":[
        {
            "category":"Restaurant",
            "type":"Food & Drink"
        }
    ],
    "sg:phone":"+1 626 398 1507",
    "sg:postcode":"91104",
    "sg:province":"CA",
    "wof:name":"Colonial Kitchen Rstrnt Food",
    "wof:placetype":"venue"
},
  "geometry": {"coordinates":[-118.10361399999999,34.161435],"type":"Point"}
}