{
  "type": "Feature",
  "properties": {
    "addr:full":"3903 Pacific Coast Highway Torrance CA 90505",
    "addr:housenumber":"3903",
    "addr:postcode":"90505",
    "addr:street":"Pacific Coast Highway",
    "iso:country":"US",
    "sg:address":"3903 Pacific Coast Highway",
    "sg:city":"Torrance",
    "sg:classifiers":[
        {
            "category":"Personal",
            "subcategory":"Beauty Salon",
            "type":"Services"
        }
    ],
    "sg:phone":"+1 310 488 3659",
    "sg:postcode":"90505",
    "sg:province":"CA",
    "sg:tags":[
        "hair"
    ],
    "sg:website":"chez-charpentier.com",
    "wof:name":"Chez Charpentier",
    "wof:placetype":"venue"
},
  "geometry": {"coordinates":[-118.354551,33.806476],"type":"Point"}
}