{
  "type": "Feature",
  "properties": {
    "addr:full":"25942 Domingo Ave Capistrano Beach CA 92624",
    "addr:housenumber":"25942",
    "addr:postcode":"92624",
    "addr:street":"Domingo Ave",
    "iso:country":"US",
    "sg:address":"25942 Domingo Ave",
    "sg:city":"Capistrano Beach",
    "sg:classifiers":[
        {
            "category":"Building & Trades",
            "subcategory":"Landscaping Services",
            "type":"Services"
        }
    ],
    "sg:phone":"+1 949 248 4349",
    "sg:postcode":"92624",
    "sg:province":"CA",
    "wof:name":"Dave & Associates Landscape",
    "wof:placetype":"venue"
},
  "geometry": {"coordinates":[-117.67628999999999,33.464631],"type":"Point"}
}