{
  "type": "Feature",
  "properties": {
    "iso:country":"US",
    "sg:address":"11 T St",
    "sg:city":"Eureka",
    "sg:classifiers":[
        {
            "category":"Manufacturing",
            "subcategory":"Metals",
            "type":"Manufacturing & Wholesale Goods"
        }
    ],
    "sg:phone":"+1 707 443 1681",
    "sg:postcode":"95501",
    "sg:province":"CA",
    "sg:tags":[
        "fabricated",
        "structural"
    ],
    "wof:name":"Eureka Boiler Works",
    "wof:placetype":"venue"
},
  "geometry": {"coordinates":[-124.151321,40.807862],"type":"Point"}
}