{
  "type": "Feature",
  "properties": {
    "iso:country":"US",
    "sg:address":"19772 Wheaton Dr",
    "sg:city":"Cupertino",
    "sg:classifiers":[
        {
            "category":"Education",
            "subcategory":"Special Training",
            "type":"Public Place"
        }
    ],
    "sg:phone":"+1 408 777 9796",
    "sg:postcode":"95014",
    "sg:province":"CA",
    "sg:tags":[
        "instruction",
        "music"
    ],
    "wof:name":"Vocal & Piano Studio",
    "wof:placetype":"venue"
},
  "geometry": {"coordinates":[-122.019186,37.324364],"type":"Point"}
}