{
  "type": "Feature",
  "properties": {
    "addr:full":"2275 Huntington Dr San Marino CA 91108",
    "addr:housenumber":"2275",
    "addr:postcode":"91108",
    "addr:street":"Huntington Dr",
    "iso:country":"US",
    "sg:address":"2275 Huntington Dr",
    "sg:city":"San Marino",
    "sg:classifiers":[
        {
            "category":"Building & Trades",
            "subcategory":"Electrical",
            "type":"Services"
        }
    ],
    "sg:phone":"+1 626 945 7782",
    "sg:postcode":"91108",
    "sg:province":"CA",
    "sg:tags":[
        "electrical",
        "contractor"
    ],
    "wof:name":"Shellhart Co",
    "wof:placetype":"venue"
},
  "geometry": {"coordinates":[-118.10554,34.122122],"type":"Point"}
}