{
  "type": "Feature",
  "properties": {
    "addr:full":"1525 Timberhill Rd Santa Rosa CA 95401",
    "addr:housenumber":"1525",
    "addr:postcode":"95401",
    "addr:street":"Timberhill Rd",
    "iso:country":"US",
    "sg:address":"1525 Timberhill Rd",
    "sg:city":"Santa Rosa",
    "sg:classifiers":[
        {
            "category":"Retail",
            "subcategory":"Laundry & Dry Cleaning",
            "type":"Services"
        }
    ],
    "sg:phone":"+1 707 829 3115",
    "sg:postcode":"95401",
    "sg:province":"CA",
    "sg:tags":[
        "cleaners",
        "rug",
        "carpet"
    ],
    "wof:name":"Carpet Cleaning For Less",
    "wof:placetype":"venue"
},
  "geometry": {"coordinates":[-122.838352,38.455377],"type":"Point"}
}