{
  "type": "Feature",
  "properties": {
    "iso:country":"US",
    "sg:address":"9346 Vallejo Dr",
    "sg:city":"Orangevale",
    "sg:classifiers":[
        {
            "category":"Mining & Drilling",
            "type":"Manufacturing & Wholesale Goods"
        }
    ],
    "sg:phone":"+1 916 989 4423",
    "sg:postcode":"95662",
    "sg:province":"CA",
    "sg:tags":[
        "company"
    ],
    "wof:name":"Vaughn's Drilling",
    "wof:placetype":"venue"
},
  "geometry": {"coordinates":[-121.20363500000001,38.689008],"type":"Point"}
}