{
  "type": "Feature",
  "properties": {
    "iso:country":"US",
    "sg:address":"30470 Whipple Rd",
    "sg:city":"Union City",
    "sg:classifiers":[
        {
            "category":"Wholesale",
            "subcategory":"Machinery & Supplies",
            "type":"Manufacturing & Wholesale Goods"
        }
    ],
    "sg:phone":"+1 510 429 4999",
    "sg:postcode":"94587",
    "sg:province":"CA",
    "sg:tags":[
        "baker"
    ],
    "wof:name":"JBS Bake Svc",
    "wof:placetype":"venue"
},
  "geometry": {"coordinates":[-122.084546,37.605596],"type":"Point"}
}