{
  "type": "Feature",
  "properties": {
    "addr:full":"10350 Barnes Canyon Rd San Diego CA 92121",
    "addr:housenumber":"10350",
    "addr:postcode":"92121",
    "addr:street":"Barnes Canyon Rd",
    "iso:country":"US",
    "sg:address":"10350 Barnes Canyon Rd",
    "sg:city":"San Diego",
    "sg:classifiers":[
        {
            "category":"Professional",
            "subcategory":"Computer Services",
            "type":"Services"
        }
    ],
    "sg:phone":"+1 858 410 6929",
    "sg:postcode":"92121",
    "sg:province":"CA",
    "sg:tags":[
        "software",
        "internet",
        "developer"
    ],
    "wof:name":"Abacus Computers",
    "wof:placetype":"venue"
},
  "geometry": {"coordinates":[-117.195797,32.90017],"type":"Point"}
}