{
  "type": "Feature",
  "properties": {
    "iso:country":"US",
    "sg:address":"252 N Skyline Dr",
    "sg:city":"Thousand Oaks",
    "sg:classifiers":[
        {
            "category":"Retail",
            "subcategory":"Auto Rental",
            "type":"Services"
        }
    ],
    "sg:phone":"+1 805 497 3724",
    "sg:postcode":"91362",
    "sg:province":"CA",
    "sg:tags":[
        "renting",
        "truck",
        "leasing"
    ],
    "sg:website":"www.lister.com",
    "wof:name":"Lister Rents Inc",
    "wof:placetype":"venue"
},
  "geometry": {"coordinates":[-118.835611,34.172724],"type":"Point"}
}