{
  "type": "Feature",
  "properties": {
    "iso:country":"US",
    "sg:address":"10810 Inland Ave",
    "sg:city":"Mira Loma",
    "sg:classifiers":[
        {
            "category":"Wholesale",
            "subcategory":"Beer",
            "type":"Manufacturing & Wholesale Goods"
        }
    ],
    "sg:phone":"+1 951 681 8600",
    "sg:postcode":"91752",
    "sg:province":"CA",
    "sg:tags":[
        "spirits",
        "distilled"
    ],
    "wof:name":"Le Vecke Group",
    "wof:placetype":"venue"
},
  "geometry": {"coordinates":[-117.518388,34.030386],"type":"Point"}
}