{
  "type": "Feature",
  "properties": {
    "addr:full":"2618 College Ave Berkeley CA 94704",
    "addr:housenumber":"2618",
    "addr:postcode":"94704",
    "addr:street":"College Ave",
    "iso:country":"US",
    "sg:address":"2618 College Ave",
    "sg:city":"Berkeley",
    "sg:classifiers":[
        {
            "category":"Professional",
            "subcategory":"Art Services",
            "type":"Services"
        }
    ],
    "sg:phone":"+1 510 540 1983",
    "sg:postcode":"94704",
    "sg:province":"CA",
    "sg:tags":[
        "graphic",
        "design"
    ],
    "sg:website":"www.malmquistdesign.com",
    "wof:name":"Malmquist Design",
    "wof:placetype":"venue"
},
  "geometry": {"coordinates":[-122.254002,37.862896],"type":"Point"}
}