{
  "type": "Feature",
  "properties": {
    "addr:full":"3037 W Seeger Ave Visalia CA 93277",
    "addr:housenumber":"3037",
    "addr:postcode":"93277",
    "addr:street":"W Seeger Ave",
    "iso:country":"US",
    "sg:address":"3037 W Seeger Ave",
    "sg:city":"Visalia",
    "sg:classifiers":[
        {
            "category":"Building & Trades",
            "subcategory":"Construction",
            "type":"Services"
        }
    ],
    "sg:phone":"+1 559 733 0768",
    "sg:postcode":"93277",
    "sg:province":"CA",
    "sg:tags":[
        "hanging",
        "painter",
        "contractor"
    ],
    "wof:name":"Jim Pace Painting",
    "wof:placetype":"venue"
},
  "geometry": {"coordinates":[-119.32364,36.310641],"type":"Point"}
}