{
  "type": "Feature",
  "properties": {
    "addr:full":"805 S Fremont Ave Alhambra CA 91803",
    "addr:housenumber":"805",
    "addr:postcode":"91803",
    "addr:street":"S Fremont Ave",
    "iso:country":"US",
    "sg:address":"805 S Fremont Ave",
    "sg:city":"Alhambra",
    "sg:classifiers":[
        {
            "category":"Home & Garden",
            "subcategory":"Household Appliances",
            "type":"Retail Goods"
        },
        {
            "category":"Building & Trades",
            "subcategory":"Construction",
            "type":"Services"
        }
    ],
    "sg:phone":"+1 626 293 5710",
    "sg:postcode":"91803",
    "sg:province":"CA",
    "sg:tags":[
        "repair",
        "conditioning/hvac",
        "heating",
        "air"
    ],
    "sg:website":"www.merced-ac.com/",
    "wof:name":"Merced Air Conditioning Equipment Service",
    "wof:placetype":"venue"
},
  "geometry": {"coordinates":[-118.152,34.0849],"type":"Point"}
}