{
  "type": "Feature",
  "properties": {
    "iso:country":"US",
    "sg:address":"2100 Portola Ave",
    "sg:city":"Livermore",
    "sg:classifiers":[
        {
            "category":"Restaurant",
            "type":"Food & Drink"
        }
    ],
    "sg:menulink":"http://www.allmenus.com/ca/livermore-pleasanton/239908-panda-express/menu/",
    "sg:phone":"+1 925 961 0168",
    "sg:postcode":"94551",
    "sg:province":"CA",
    "sg:tags":[
        "asian",
        "chinese"
    ],
    "wof:name":"Panda Express",
    "wof:placetype":"venue"
},
  "geometry": {"coordinates":[-121.774119,37.691174],"type":"Point"}
}