{
  "type": "Feature",
  "properties": {
    "addr:full":"2355 McKee Rd San Jose CA 95127",
    "addr:housenumber":"2355",
    "addr:postcode":"95127",
    "addr:street":"Mckee Rd",
    "iso:country":"US",
    "sg:address":"2355 McKee Rd",
    "sg:city":"San Jose",
    "sg:classifiers":[
        {
            "category":"Wholesale",
            "subcategory":"Machinery & Supplies",
            "type":"Manufacturing & Wholesale Goods"
        }
    ],
    "sg:phone":"+1 408 251 3302",
    "sg:postcode":"95127",
    "sg:province":"CA",
    "sg:tags":[
        "equipment",
        "salon",
        "establishment",
        "beauty"
    ],
    "wof:name":"C P Beauty Supply",
    "wof:placetype":"venue"
},
  "geometry": {"coordinates":[-121.849977,37.365406],"type":"Point"}
}