{
  "type": "Feature",
  "properties": {
    "iso:country":"US",
    "sg:address":"14 W Cross St Ofc",
    "sg:city":"Woodland",
    "sg:classifiers":[
        {
            "category":"Real Estate",
            "subcategory":"Real Estate Services",
            "type":"Services"
        },
        {
            "category":"Real Estate",
            "subcategory":"Real Estate Operator",
            "type":"Services"
        }
    ],
    "sg:phone":"+1 530 666 2241",
    "sg:postcode":"95695",
    "sg:province":"CA",
    "sg:tags":[
        "vacancy",
        "apartment",
        "rental",
        "listing"
    ],
    "wof:name":"Franciscan Apartments",
    "wof:placetype":"venue"
},
  "geometry": {"coordinates":[-121.784085,38.672082],"type":"Point"}
}