{
  "type": "Feature",
  "properties": {
    "iso:country":"US",
    "sg:address":"1820 Marron Rd",
    "sg:city":"Carlsbad",
    "sg:classifiers":[
        {
            "category":"Banks & Credit Unions",
            "subcategory":"Bank",
            "type":"Services"
        }
    ],
    "sg:phone":"+1 760 720 3121",
    "sg:postcode":"92008",
    "sg:province":"CA",
    "sg:tags":[
        "loan",
        "real estate"
    ],
    "wof:name":"Countrywide Home Loans",
    "wof:placetype":"venue"
},
  "geometry": {"coordinates":[-117.339946,33.177369],"type":"Point"}
}