{
  "type": "Feature",
  "properties": {
    "addr:full":"336 Race St San Jose CA 95126",
    "addr:housenumber":"336",
    "addr:postcode":"95126",
    "addr:street":"Race St",
    "iso:country":"US",
    "sg:address":"336 Race St",
    "sg:city":"San Jose",
    "sg:classifiers":[
        {
            "category":"Sports & Exercise",
            "subcategory":"Gym",
            "type":"Entertainment"
        },
        {
            "category":"Education",
            "subcategory":"School",
            "type":"Public Place"
        },
        {
            "category":"Sports & Exercise",
            "subcategory":"Swimming Pool",
            "type":"Entertainment"
        }
    ],
    "sg:phone":"+1 408 280 5437",
    "sg:postcode":"95126",
    "sg:province":"CA",
    "sg:website":"www.calsportscenter.com",
    "wof:name":"California Sports Center",
    "wof:placetype":"venue"
},
  "geometry": {"coordinates":[-121.91100299999999,37.322498],"type":"Point"}
}