{
  "type": "Feature",
  "properties": {
    "iso:country":"US",
    "sg:address":"930 N Vermont Avenue",
    "sg:city":"Los Angeles",
    "sg:classifiers":[
        {
            "category":"Government",
            "subcategory":"Office",
            "type":"Public Place"
        }
    ],
    "sg:phone":"+1 323 666 2252",
    "sg:postcode":"90029",
    "sg:province":"CA",
    "sg:tags":[
        "smog",
        "check"
    ],
    "wof:name":"Crown Auto Smog",
    "wof:placetype":"venue"
},
  "geometry": {"coordinates":[-118.291585,34.088345],"type":"Point"}
}