{
  "type": "Feature",
  "properties": {
    "iso:country":"US",
    "sg:address":"2461 Holly Dr",
    "sg:city":"Tracy",
    "sg:classifiers":[
        {
            "category":"Retail",
            "subcategory":"Auto Repair",
            "type":"Services"
        }
    ],
    "sg:phone":"+1 209 835 1648",
    "sg:postcode":"95376",
    "sg:province":"CA",
    "sg:tags":[
        "repairing",
        "automobile"
    ],
    "wof:name":"Jim's Automotive",
    "wof:placetype":"venue"
},
  "geometry": {"coordinates":[-121.426025,37.755678],"type":"Point"}
}