{
  "type": "Feature",
  "properties": {
    "addr:full":"1340 Reynolds Avenue Irvine CA 92614",
    "addr:housenumber":"1340",
    "addr:postcode":"92614",
    "addr:street":"Reynolds Avenue",
    "iso:country":"US",
    "sg:address":"1340 Reynolds Avenue",
    "sg:city":"Irvine",
    "sg:classifiers":[
        {
            "category":"Professional",
            "type":"Services"
        }
    ],
    "sg:phone":"+1 949 975 8410",
    "sg:postcode":"92614",
    "sg:province":"CA",
    "sg:website":"www.iristechnology.org/",
    "wof:name":"Iris Technology Corporation",
    "wof:placetype":"venue"
},
  "geometry": {"coordinates":[-117.855316,33.696524],"type":"Point"}
}