{
  "type": "Feature",
  "properties": {
    "iso:country":"US",
    "sg:address":"2738 Alton Pkwy Ste 113",
    "sg:city":"Irvine",
    "sg:classifiers":[
        {
            "category":"Ice Cream",
            "type":"Food & Drink"
        }
    ],
    "sg:phone":"+1 949 757 0138",
    "sg:postcode":"92614",
    "sg:province":"CA",
    "sg:tags":[
        "frozen",
        "yogurt"
    ],
    "sg:website":"www.yogurt-land.com/",
    "wof:name":"Yogurtland",
    "wof:placetype":"venue"
},
  "geometry": {"coordinates":[-117.83238299999999,33.688633],"type":"Point"}
}