{
  "type": "Feature",
  "properties": {
    "iso:country":"US",
    "sg:address":"5628 Rosemead Blvd",
    "sg:city":"Temple City",
    "sg:classifiers":[
        {
            "category":"Arena",
            "subcategory":"Sports Club",
            "type":"Entertainment"
        }
    ],
    "sg:phone":"+1 626 287 0808",
    "sg:postcode":"91780",
    "sg:province":"CA",
    "sg:tags":[
        "martial art"
    ],
    "wof:name":"TKD Academy",
    "wof:placetype":"venue"
},
  "geometry": {"coordinates":[-118.329438,34.101828],"type":"Point"}
}