{
  "type": "Feature",
  "properties": {
    "addr:full":"1250 Howe Avenue Sacramento CA 95825",
    "addr:housenumber":"1250",
    "addr:postcode":"95825",
    "addr:street":"Howe Avenue",
    "iso:country":"US",
    "sg:address":"1250 Howe Avenue",
    "sg:city":"Sacramento",
    "sg:classifiers":[
        {
            "category":"Shopping",
            "subcategory":"Clothing, Apparel, & Fashions",
            "type":"Retail Goods"
        }
    ],
    "sg:phone":"+1 916 921 2173",
    "sg:postcode":"95825",
    "sg:province":"CA",
    "sg:tags":[
        "accessory",
        "clothing",
        "women's"
    ],
    "wof:name":"Avenue 221",
    "wof:placetype":"venue"
},
  "geometry": {"coordinates":[-121.415237,38.588025],"type":"Point"}
}