{
  "type": "Feature",
  "properties": {
    "iso:country":"US",
    "sg:address":"14917 Lemoli Ave",
    "sg:city":"Gardena",
    "sg:classifiers":[
        {
            "category":"Home & Garden",
            "subcategory":"Furniture",
            "type":"Retail Goods"
        }
    ],
    "sg:phone":"+1 310 675 8839",
    "sg:postcode":"90249",
    "sg:province":"CA",
    "sg:tags":[
        "store"
    ],
    "wof:name":"Furniture Discount Market",
    "wof:placetype":"venue"
},
  "geometry": {"coordinates":[-118.330872,33.895324],"type":"Point"}
}