{
  "type": "Feature",
  "properties": {
    "addr:full":"514 E Palmer Ave Glendale CA 91205",
    "addr:housenumber":"514",
    "addr:postcode":"91205",
    "addr:street":"E Palmer Ave",
    "iso:country":"US",
    "sg:address":"514 E Palmer Ave",
    "sg:city":"Glendale",
    "sg:classifiers":[
        {
            "category":"Wholesale",
            "subcategory":"Durable Goods & Equipment",
            "type":"Manufacturing & Wholesale Goods"
        }
    ],
    "sg:phone":"+1 818 749 4749",
    "sg:postcode":"91205",
    "sg:province":"CA",
    "wof:name":"Vbg Interprise",
    "wof:placetype":"venue"
},
  "geometry": {"coordinates":[-118.249681,34.132579],"type":"Point"}
}