{
  "type": "Feature",
  "properties": {
    "addr:full":"6817 Franklin Ave Los Angeles CA 90028",
    "addr:housenumber":"6817",
    "addr:postcode":"90028",
    "addr:street":"Franklin Ave",
    "iso:country":"US",
    "sg:address":"6817 Franklin Ave",
    "sg:city":"Los Angeles",
    "sg:classifiers":[
        {
            "category":"Organizations",
            "subcategory":"Religious Organization",
            "type":"Services"
        }
    ],
    "sg:phone":"+1 323 874 2104",
    "sg:postcode":"90028",
    "sg:province":"CA",
    "sg:tags":[
        "church"
    ],
    "sg:website":"www.hollywoodumc.org/",
    "wof:name":"Hollywood United Methodist Church",
    "wof:placetype":"venue"
},
  "geometry": {"coordinates":[-118.33899700000001,34.104],"type":"Point"}
}