{
  "type": "Feature",
  "properties": {
    "addr:full":"21275 Burbank Blvd Woodland Hills CA 91367",
    "addr:housenumber":"21275",
    "addr:postcode":"91367",
    "addr:street":"Burbank Blvd",
    "iso:country":"US",
    "sg:address":"21275 Burbank Blvd",
    "sg:city":"Woodland Hills",
    "sg:classifiers":[
        {
            "category":"Retail",
            "subcategory":"Car Wash",
            "type":"Services"
        }
    ],
    "sg:phone":"+1 818 884 0668",
    "sg:postcode":"91367",
    "sg:province":"CA",
    "wof:name":"Deluxe Detail",
    "wof:placetype":"venue"
},
  "geometry": {"coordinates":[-118.59334800000001,34.173437],"type":"Point"}
}