{
  "type": "Feature",
  "properties": {
    "iso:country":"US",
    "sg:address":"1625 Tierra Buena Rd",
    "sg:city":"Yuba City",
    "sg:classifiers":[
        {
            "category":"Manufacturing",
            "subcategory":"Building Materials",
            "type":"Manufacturing & Wholesale Goods"
        }
    ],
    "sg:phone":"+1 530 673 6517",
    "sg:postcode":"95993",
    "sg:province":"CA",
    "sg:tags":[
        "molding"
    ],
    "wof:name":"Eagle Moulding Co",
    "wof:placetype":"venue"
},
  "geometry": {"coordinates":[-121.66234799999999,39.152685],"type":"Point"}
}