{
  "type": "Feature",
  "properties": {
    "iso:country":"US",
    "sg:address":"1850 Monterey St",
    "sg:city":"San Luis Obispo",
    "sg:classifiers":[
        {
            "category":"Restaurant",
            "type":"Food & Drink"
        }
    ],
    "sg:phone":"+1 805 543 2526",
    "sg:postcode":"93401",
    "sg:province":"CA",
    "sg:website":"www.quarterdeck.com",
    "wof:name":"Quarterdeck",
    "wof:placetype":"venue"
},
  "geometry": {"coordinates":[-120.650306,35.289806],"type":"Point"}
}