{
  "type": "Feature",
  "properties": {
    "iso:country":"US",
    "sg:address":"2606 Mandela Pkwy",
    "sg:city":"Oakland",
    "sg:classifiers":[
        {
            "category":"Personal",
            "type":"Services"
        }
    ],
    "sg:phone":"+1 510 891 9675",
    "sg:postcode":"94607",
    "sg:province":"CA",
    "sg:tags":[
        "local"
    ],
    "wof:name":"Tork Systems",
    "wof:placetype":"venue"
},
  "geometry": {"coordinates":[-122.290001,37.819099],"type":"Point"}
}