{
  "type": "Feature",
  "properties": {
    "iso:country":"US",
    "sg:address":"7481 Magnolia Ave",
    "sg:city":"Riverside",
    "sg:classifiers":[
        {
            "category":"Real Estate",
            "subcategory":"Real Estate Operator",
            "type":"Services"
        }
    ],
    "sg:phone":"+1 951 688 9608",
    "sg:postcode":"92504",
    "sg:province":"CA",
    "sg:tags":[
        "apartment"
    ],
    "wof:name":"De Capri Apartments",
    "wof:placetype":"venue"
},
  "geometry": {"coordinates":[-117.407563,33.942628],"type":"Point"}
}