{
  "type": "Feature",
  "properties": {
    "addr:full":"545 N Mountain Ave Upland CA 91786",
    "addr:housenumber":"545",
    "addr:postcode":"91786",
    "addr:street":"N Mountain Ave",
    "iso:country":"US",
    "sg:address":"545 N Mountain Ave",
    "sg:city":"Upland",
    "sg:classifiers":[
        {
            "category":"Building & Trades",
            "subcategory":"Plumbing",
            "type":"Services"
        }
    ],
    "sg:phone":"+1 909 591 2344",
    "sg:postcode":"91786",
    "sg:province":"CA",
    "sg:tags":[
        "plumbing",
        "contractor"
    ],
    "wof:name":"California Rooter Svc",
    "wof:placetype":"venue"
},
  "geometry": {"coordinates":[-117.67026199999999,34.10319],"type":"Point"}
}