{
  "type": "Feature",
  "properties": {
    "iso:country":"US",
    "sg:address":"20121 Alisu Ct",
    "sg:city":"Walnut",
    "sg:classifiers":[
        {
            "category":"Social Services",
            "subcategory":"Child Care",
            "type":"Services"
        }
    ],
    "sg:phone":"+1 909 598 1379",
    "sg:postcode":"91789",
    "sg:province":"CA",
    "sg:website":"www.childrensworld.com",
    "wof:name":"Children's World Learning Ctr",
    "wof:placetype":"venue"
},
  "geometry": {"coordinates":[-117.862514,34.011895],"type":"Point"}
}