{
  "type": "Feature",
  "properties": {
    "iso:country":"US",
    "sg:address":"20 Bentley Rd",
    "sg:city":"Rancho Mirage",
    "sg:classifiers":[
        {
            "category":"Professional",
            "type":"Services"
        }
    ],
    "sg:phone":"+1 760 202 4484",
    "sg:postcode":"92270",
    "sg:province":"CA",
    "wof:name":"David H Tang Mda Professional",
    "wof:placetype":"venue"
},
  "geometry": {"coordinates":[-116.410149,33.788473],"type":"Point"}
}