{
  "type": "Feature",
  "properties": {
    "iso:country":"US",
    "sg:address":"8201 4th St",
    "sg:city":"Downey",
    "sg:classifiers":[
        {
            "category":"Building & Trades",
            "subcategory":"Construction",
            "type":"Services"
        }
    ],
    "sg:phone":"+1 562 923 7251",
    "sg:postcode":"90241",
    "sg:province":"CA",
    "sg:tags":[
        "contractor"
    ],
    "wof:name":"Very Important Properties",
    "wof:placetype":"venue"
},
  "geometry": {"coordinates":[-118.133003,33.9436],"type":"Point"}
}