{
  "type": "Feature",
  "properties": {
    "addr:full":"2040 W Jefferson Blvd Los Angeles CA 90018",
    "addr:housenumber":"2040",
    "addr:postcode":"90018",
    "addr:street":"W Jefferson Blvd",
    "iso:country":"US",
    "sg:address":"2040 W Jefferson Blvd",
    "sg:city":"Los Angeles",
    "sg:classifiers":[
        {
            "category":"Organizations",
            "subcategory":"Religious Organization",
            "type":"Services"
        }
    ],
    "sg:phone":"+1 323 733 4527",
    "sg:postcode":"90018",
    "sg:province":"CA",
    "sg:tags":[
        "church"
    ],
    "wof:name":"L A Council Of Churches",
    "wof:placetype":"venue"
},
  "geometry": {"coordinates":[-118.31703,34.025467],"type":"Point"}
}