{
  "type": "Feature",
  "properties": {
    "addr:full":"4970 Windplay Dr El Dorado Hills CA 95762",
    "addr:housenumber":"4970",
    "addr:postcode":"95762",
    "addr:street":"Windplay Dr",
    "iso:country":"US",
    "sg:address":"4970 Windplay Dr",
    "sg:city":"El Dorado Hills",
    "sg:classifiers":[
        {
            "category":"Travel",
            "subcategory":"Hotels & Motels",
            "type":"Entertainment"
        }
    ],
    "sg:phone":"+1 916 941 7970",
    "sg:postcode":"95762",
    "sg:province":"CA",
    "sg:website":"www.calsuites.com",
    "wof:name":"California Suites",
    "wof:placetype":"venue"
},
  "geometry": {"coordinates":[-121.071077,38.637508],"type":"Point"}
}