{
  "type": "Feature",
  "properties": {
    "iso:country":"US",
    "sg:address":"1535 E Orangewood Ave",
    "sg:city":"Anaheim",
    "sg:classifiers":[
        {
            "category":"Social Services",
            "type":"Services"
        }
    ],
    "sg:phone":"+1 714 937 4500",
    "sg:postcode":"92805",
    "sg:province":"CA",
    "wof:name":"Probation Dept",
    "wof:placetype":"venue"
},
  "geometry": {"coordinates":[-117.89190499999999,33.796202],"type":"Point"}
}