{
  "type": "Feature",
  "properties": {
    "iso:country":"US",
    "sg:address":"1000 Sunrise Ave",
    "sg:city":"Roseville",
    "sg:classifiers":[
        {
            "category":"Shopping",
            "subcategory":"Photographic Equipment",
            "type":"Retail Goods"
        }
    ],
    "sg:phone":"+1 916 786 2288",
    "sg:postcode":"95661",
    "sg:province":"CA",
    "sg:tags":[
        "supply"
    ],
    "sg:website":"www.actioncamera.com",
    "wof:name":"Action Camera",
    "wof:placetype":"venue"
},
  "geometry": {"coordinates":[-121.272069,38.727157],"type":"Point"}
}