{
  "type": "Feature",
  "properties": {
    "addr:full":"17 S Mentor Ave Pasadena CA 91106",
    "addr:housenumber":"17",
    "addr:postcode":"91106",
    "addr:street":"S Mentor Ave",
    "iso:country":"US",
    "sg:address":"17 S Mentor Ave",
    "sg:city":"Pasadena",
    "sg:classifiers":[
        {
            "category":"Personal",
            "subcategory":"Barber",
            "type":"Services"
        }
    ],
    "sg:phone":"+1 626 463 1317",
    "sg:postcode":"91106",
    "sg:province":"CA",
    "wof:name":"Mentor Style Salon",
    "wof:placetype":"venue"
},
  "geometry": {"coordinates":[-118.13099699999999,34.145802],"type":"Point"}
}