{
  "type": "Feature",
  "properties": {
    "iso:country":"US",
    "sg:address":"251 E Hackett Rd",
    "sg:city":"Modesto",
    "sg:classifiers":[
        {
            "category":"Government",
            "subcategory":"Office",
            "type":"Public Place"
        }
    ],
    "sg:phone":"+1 209 558 2637",
    "sg:postcode":"95358",
    "sg:province":"CA",
    "sg:tags":[
        "administrative",
        "program",
        "health"
    ],
    "wof:name":"Adult Protective Services S",
    "wof:placetype":"venue"
},
  "geometry": {"coordinates":[-120.98743899999999,37.587696],"type":"Point"}
}