{
  "type": "Feature",
  "properties": {
    "iso:country":"US",
    "sg:address":"667 E Walnut St",
    "sg:city":"Pasadena",
    "sg:classifiers":[
        {
            "category":"Professional",
            "subcategory":"Business Services",
            "type":"Services"
        }
    ],
    "sg:phone":"+1 626 564 8113",
    "sg:postcode":"91101",
    "sg:province":"CA",
    "sg:tags":[
        "repair"
    ],
    "wof:name":"Elite Upholstery",
    "wof:placetype":"venue"
},
  "geometry": {"coordinates":[-118.13555599999999,34.149646],"type":"Point"}
}