{
  "type": "Feature",
  "properties": {
    "addr:full":"7280 N Rosemead Blvd San Gabriel CA 91775",
    "addr:housenumber":"7280",
    "addr:postcode":"91775",
    "addr:street":"N Rosemead Blvd",
    "iso:country":"US",
    "sg:address":"7280 N Rosemead Blvd",
    "sg:city":"San Gabriel",
    "sg:classifiers":[
        {
            "category":"Autos & Motor Vehicles",
            "subcategory":"Fuel & Gas Station",
            "type":"Retail Goods"
        }
    ],
    "sg:phone":"+1 626 287 8972",
    "sg:postcode":"91775",
    "sg:province":"CA",
    "sg:website":"www.shell.com",
    "wof:name":"Shell Gas Station",
    "wof:placetype":"venue"
},
  "geometry": {"coordinates":[-118.07282600000001,34.129994],"type":"Point"}
}