{
  "type": "Feature",
  "properties": {
    "addr:full":"333 W Broadway Long Beach CA 90802",
    "addr:housenumber":"333",
    "addr:postcode":"90802",
    "addr:street":"W Broadway",
    "iso:country":"US",
    "sg:address":"333 W Broadway",
    "sg:city":"Long Beach",
    "sg:classifiers":[
        {
            "category":"Professional",
            "subcategory":"Lawyer & Legal Services",
            "type":"Services"
        }
    ],
    "sg:phone":"+1 562 437 0556",
    "sg:postcode":"90802",
    "sg:province":"CA",
    "sg:tags":[
        "attorney"
    ],
    "sg:website":"www.georgetkelly.com",
    "wof:name":"George Kelly Law Offices",
    "wof:placetype":"venue"
},
  "geometry": {"coordinates":[-118.196297,33.769368],"type":"Point"}
}