{
  "type": "Feature",
  "properties": {
    "addr:full":"3512 Ottawa Ave San Diego CA 92117",
    "addr:housenumber":"3512",
    "addr:postcode":"92117",
    "addr:street":"Ottawa Ave",
    "iso:country":"US",
    "sg:address":"3512 Ottawa Ave",
    "sg:city":"San Diego",
    "sg:classifiers":[
        {
            "category":"Home & Garden",
            "subcategory":"Home Furnishings",
            "type":"Retail Goods"
        }
    ],
    "sg:phone":"+1 858 483 5428",
    "sg:postcode":"92117",
    "sg:province":"CA",
    "wof:name":"Kf Designs",
    "wof:placetype":"venue"
},
  "geometry": {"coordinates":[-117.201779,32.805465],"type":"Point"}
}