{
  "type": "Feature",
  "properties": {
    "addr:full":"9020 Siempre Viva Rd San Diego CA 92154",
    "addr:housenumber":"9020",
    "addr:postcode":"92154",
    "addr:street":"Siempre Viva Rd",
    "iso:country":"US",
    "sg:address":"9020 Siempre Viva Rd",
    "sg:city":"San Diego",
    "sg:classifiers":[
        {
            "category":"Freight",
            "type":"Transportation"
        }
    ],
    "sg:phone":"+1 619 671 7077",
    "sg:postcode":"92154",
    "sg:province":"CA",
    "sg:tags":[
        "arrangement"
    ],
    "wof:name":"S C Raub",
    "wof:placetype":"venue"
},
  "geometry": {"coordinates":[-116.945183,32.553064],"type":"Point"}
}