{
  "type": "Feature",
  "properties": {
    "iso:country":"US",
    "sg:address":"3605 Long Beach Blvd Ste 300",
    "sg:city":"Long Beach",
    "sg:classifiers":[
        {
            "category":"Professional",
            "subcategory":"Lawyer & Legal Services",
            "type":"Services"
        },
        {
            "category":"Banks & Credit Unions",
            "subcategory":"Atm",
            "type":"Services"
        }
    ],
    "sg:phone":"+1 562 988 0885",
    "sg:postcode":"90807",
    "sg:province":"CA",
    "sg:tags":[
        "divorce",
        "law",
        "family",
        "bankruptcy"
    ],
    "sg:website":"www.attorneyald.com",
    "wof:name":"ATTORNEY AID DIVORCE AND BANKRUPTCY CENTER INC.",
    "wof:placetype":"venue"
},
  "geometry": {"coordinates":[-118.189496,33.822389],"type":"Point"}
}