{
  "type": "Feature",
  "properties": {
    "iso:country":"US",
    "sg:address":"9945 Lower Sacramento Rd",
    "sg:city":"Stockton",
    "sg:classifiers":[
        {
            "category":"Building & Trades",
            "subcategory":"Electrical",
            "type":"Services"
        }
    ],
    "sg:phone":"+1 209 957 0626",
    "sg:postcode":"95210",
    "sg:province":"CA",
    "sg:tags":[
        "electric",
        "contractor"
    ],
    "wof:name":"Grider Electric",
    "wof:placetype":"venue"
},
  "geometry": {"coordinates":[-121.321319,38.044332],"type":"Point"}
}