{
  "type": "Feature",
  "properties": {
    "iso:country":"US",
    "sg:address":"3015 E Ana St",
    "sg:city":"Compton",
    "sg:classifiers":[
        {
            "category":"Manufacturing",
            "subcategory":"Textiles",
            "type":"Manufacturing & Wholesale Goods"
        }
    ],
    "sg:phone":"+1 310 898 1686",
    "sg:postcode":"90221",
    "sg:province":"CA",
    "sg:tags":[
        "dyeing",
        "fabric",
        "mfg",
        "knitted",
        "ind",
        "finishing",
        "clothing"
    ],
    "wof:name":"Pacific Continentals Textile",
    "wof:placetype":"venue"
},
  "geometry": {"coordinates":[-118.21022600000001,33.86061],"type":"Point"}
}