{
  "type": "Feature",
  "properties": {
    "addr:full":"1200 Esplanade Redondo Beach CA 90277",
    "addr:housenumber":"1200",
    "addr:postcode":"90277",
    "addr:street":"Esplanade",
    "iso:country":"US",
    "sg:address":"1200 Esplanade",
    "sg:city":"Redondo Beach",
    "sg:classifiers":[
        {
            "category":"Shopping",
            "subcategory":"Music",
            "type":"Retail Goods"
        }
    ],
    "sg:phone":"+1 818 968 3824",
    "sg:postcode":"90277",
    "sg:province":"CA",
    "wof:name":"Hard Eight Records",
    "wof:placetype":"venue"
},
  "geometry": {"coordinates":[-118.389871,33.823425],"type":"Point"}
}