{
  "type": "Feature",
  "properties": {
    "addr:full":"250 E Lambert Rd Brea CA 92821",
    "addr:housenumber":"250",
    "addr:postcode":"92821",
    "addr:street":"E Lambert Rd",
    "iso:country":"US",
    "sg:address":"250 E Lambert Rd",
    "sg:city":"Brea",
    "sg:classifiers":[
        {
            "category":"Restaurant",
            "type":"Food & Drink"
        }
    ],
    "sg:menulink":"http://www.allmenus.com/ca/anaheim-santa-ana-garden-grove/164264-wienerschnitzel/menu/",
    "sg:phone":"+1 714 529 9211",
    "sg:postcode":"92821",
    "sg:province":"CA",
    "sg:tags":[
        "sandwich",
        "dog",
        "burger",
        "hot",
        "wrap",
        "american"
    ],
    "wof:name":"Wienerschnitzel",
    "wof:placetype":"venue"
},
  "geometry": {"coordinates":[-117.89431399999999,33.92448],"type":"Point"}
}