{
  "type": "Feature",
  "properties": {
    "iso:country":"US",
    "sg:address":"505 San Marin Dr",
    "sg:city":"Novato",
    "sg:classifiers":[
        {
            "category":"Professional",
            "subcategory":"Computer Services",
            "type":"Services"
        }
    ],
    "sg:phone":"+1 415 892 6420",
    "sg:postcode":"94945",
    "sg:province":"CA",
    "sg:tags":[
        "consultant",
        "designer"
    ],
    "wof:name":"E C Brands Corp",
    "wof:placetype":"venue"
},
  "geometry": {"coordinates":[-122.584756,38.121607],"type":"Point"}
}