{
  "type": "Feature",
  "properties": {
    "addr:full":"14034 Poway Rd Ste A/B Poway CA 92064",
    "addr:housenumber":"14034;b",
    "addr:postcode":"ca 92064",
    "addr:street":"Poway Rd Ste A /",
    "iso:country":"US",
    "sg:address":"14034 Poway Rd Ste A/B",
    "sg:city":"Poway",
    "sg:phone":"+1 858 513 4227",
    "sg:postcode":"92064",
    "sg:province":"CA",
    "wof:name":"Jimmy's Brick Pit BBQ",
    "wof:placetype":"venue"
},
  "geometry": {"coordinates":[-117.027242,32.956358],"type":"Point"}
}