{
  "type": "Feature",
  "properties": {
    "addr:full":"222 S Harbor Blvd Anaheim CA 92805",
    "addr:housenumber":"222",
    "addr:postcode":"92805",
    "addr:street":"S Harbor Blvd",
    "iso:country":"US",
    "sg:address":"222 S Harbor Blvd",
    "sg:city":"Anaheim",
    "sg:classifiers":[
        {
            "category":"Banks & Credit Unions",
            "subcategory":"Bank",
            "type":"Services"
        }
    ],
    "sg:phone":"+1 714 772 7985",
    "sg:postcode":"92805",
    "sg:province":"CA",
    "sg:tags":[
        "national",
        "commercial"
    ],
    "wof:name":"Wells Fargo",
    "wof:placetype":"venue"
},
  "geometry": {"coordinates":[-117.91913599999999,33.833083],"type":"Point"}
}