{
  "type": "Feature",
  "properties": {
    "addr:full":"3803 MacDonald Ave Richmond CA 94805",
    "addr:housenumber":"3803",
    "addr:postcode":"94805",
    "addr:street":"Macdonald Ave",
    "iso:country":"US",
    "sg:address":"3803 MacDonald Ave",
    "sg:city":"Richmond",
    "sg:classifiers":[
        {
            "category":"Personal",
            "subcategory":"Nail Salon",
            "type":"Services"
        }
    ],
    "sg:phone":"+1 510 236 1726",
    "sg:postcode":"94805",
    "sg:province":"CA",
    "wof:name":"London Nail Salon",
    "wof:placetype":"venue"
},
  "geometry": {"coordinates":[-122.333097,37.933923],"type":"Point"}
}