{
  "type": "Feature",
  "properties": {
    "iso:country":"US",
    "sg:address":"3069 Travis Blvd",
    "sg:city":"Fairfield",
    "sg:classifiers":[
        {
            "category":"Ice Cream",
            "type":"Food & Drink"
        }
    ],
    "sg:menulink":"http://www.allmenus.com/ca/fairfield-suisun-city/242462-baskin-robbins/menu/",
    "sg:phone":"+1 707 428 3131",
    "sg:postcode":"94534",
    "sg:province":"CA",
    "sg:tags":[
        "american"
    ],
    "wof:name":"Baskin-Robbins",
    "wof:placetype":"venue"
},
  "geometry": {"coordinates":[-122.06704999999999,38.258328],"type":"Point"}
}