{
  "type": "Feature",
  "properties": {
    "addr:full":"9260 Alcosta Blvd San Ramon CA 94583",
    "addr:housenumber":"9260",
    "addr:postcode":"94583",
    "addr:street":"Alcosta Blvd",
    "iso:country":"US",
    "sg:address":"9260 Alcosta Blvd",
    "sg:city":"San Ramon",
    "sg:classifiers":[
        {
            "category":"Insurance",
            "subcategory":"Insurance Agent",
            "type":"Services"
        }
    ],
    "sg:phone":"+1 925 828 0630",
    "sg:postcode":"94583",
    "sg:province":"CA",
    "wof:name":"Mc Manus & Assoc Insurance Svc",
    "wof:placetype":"venue"
},
  "geometry": {"coordinates":[-121.928748,37.731188],"type":"Point"}
}