{
  "type": "Feature",
  "properties": {
    "addr:full":"1415 4th St Santa Monica CA 90401",
    "addr:housenumber":"1415",
    "addr:postcode":"90401",
    "addr:street":"4Th St",
    "iso:country":"US",
    "sg:address":"1415 4th St",
    "sg:city":"Santa Monica",
    "sg:classifiers":[
        {
            "category":"Personal",
            "type":"Services"
        }
    ],
    "sg:phone":"+1 310 393 4844",
    "sg:postcode":"90401",
    "sg:province":"CA",
    "sg:tags":[
        "child",
        "care"
    ],
    "wof:name":"Bright Child",
    "wof:placetype":"venue"
},
  "geometry": {"coordinates":[-118.49388999999999,34.01549],"type":"Point"}
}