{
  "type": "Feature",
  "properties": {
    "addr:full":"222 Mountain Vista Pkwy Livermore CA 94551",
    "addr:housenumber":"222",
    "addr:postcode":"94551",
    "addr:street":"Mountain Vista Pkwy",
    "iso:country":"US",
    "sg:address":"222 Mountain Vista Pkwy",
    "sg:city":"Livermore",
    "sg:classifiers":[
        {
            "category":"Professional",
            "type":"Services"
        }
    ],
    "sg:phone":"+1 925 373 3200",
    "sg:postcode":"94551",
    "sg:province":"CA",
    "sg:tags":[
        "establishment"
    ],
    "sg:website":"www.bmgseltec.com",
    "wof:name":"BMG Seltec",
    "wof:placetype":"venue"
},
  "geometry": {"coordinates":[-121.701249,37.712529],"type":"Point"}
}