{
  "type": "Feature",
  "properties": {
    "iso:country":"US",
    "sg:address":"1006 Hollywood Ave",
    "sg:city":"Oakland",
    "sg:classifiers":[
        {
            "category":"Shopping",
            "subcategory":"Computers & Home Electronics",
            "type":"Retail Goods"
        }
    ],
    "sg:phone":"+1 510 530 1238",
    "sg:postcode":"94602",
    "sg:province":"CA",
    "sg:tags":[
        "professional",
        "software"
    ],
    "sg:website":"www.vital-assets.com",
    "wof:name":"Vital Assets",
    "wof:placetype":"venue"
},
  "geometry": {"coordinates":[-122.218074,37.812712],"type":"Point"}
}