{
  "type": "Feature",
  "properties": {
    "iso:country":"US",
    "sg:address":"25 San Ramon Dr",
    "sg:city":"Chico",
    "sg:classifiers":[
        {
            "category":"Real Estate",
            "subcategory":"Real Estate Agent",
            "type":"Services"
        }
    ],
    "sg:phone":"+1 530 899 4020",
    "sg:postcode":"95973",
    "sg:province":"CA",
    "wof:name":"Oak Valley Homes",
    "wof:placetype":"venue"
},
  "geometry": {"coordinates":[-121.840371,39.763704],"type":"Point"}
}