{
  "type": "Feature",
  "properties": {
    "iso:country":"US",
    "sg:address":"11837 Dublin Blvd",
    "sg:city":"Dublin",
    "sg:classifiers":[
        {
            "category":"Shopping",
            "subcategory":"Bicycles & Sporting Goods",
            "type":"Retail Goods"
        }
    ],
    "sg:phone":"+1 925 551 4171",
    "sg:postcode":"94568",
    "sg:province":"CA",
    "sg:tags":[
        "equipment",
        "playground"
    ],
    "sg:website":"www.woodplay1.com",
    "wof:name":"Backyard Factory",
    "wof:placetype":"venue"
},
  "geometry": {"coordinates":[-121.939806,37.700887],"type":"Point"}
}