{
  "type": "Feature",
  "properties": {
    "iso:country":"US",
    "sg:address":"175 Stonewood Street",
    "sg:city":"Downey",
    "sg:classifiers":[
        {
            "category":"Shopping",
            "subcategory":"Shoes",
            "type":"Retail Goods"
        }
    ],
    "sg:phone":"+1 562 622 8008",
    "sg:postcode":"90241",
    "sg:province":"CA",
    "sg:tags":[
        "store"
    ],
    "wof:name":"Magic Step",
    "wof:placetype":"venue"
},
  "geometry": {"coordinates":[-118.121025,33.938181],"type":"Point"}
}