{
  "type": "Feature",
  "properties": {
    "addr:full":"1570 I St Petaluma CA 94952",
    "addr:housenumber":"1570",
    "addr:postcode":"94952",
    "addr:street":"I St",
    "iso:country":"US",
    "sg:address":"1570 I St",
    "sg:city":"Petaluma",
    "sg:classifiers":[
        {
            "category":"Professional",
            "subcategory":"Management & Consulting",
            "type":"Services"
        }
    ],
    "sg:phone":"+1 707 338 0926",
    "sg:postcode":"94952",
    "sg:province":"CA",
    "sg:tags":[
        "consultant",
        "educational"
    ],
    "wof:name":"Kam Consulting",
    "wof:placetype":"venue"
},
  "geometry": {"coordinates":[-122.631721,38.217897],"type":"Point"}
}