{
  "type": "Feature",
  "properties": {
    "addr:full":"1731 E 4th St Long Beach CA 90802",
    "addr:housenumber":"1731",
    "addr:postcode":"90802",
    "addr:street":"E 4Th St",
    "iso:country":"US",
    "sg:address":"1731 E 4th St",
    "sg:city":"Long Beach",
    "sg:classifiers":[
        {
            "category":"Restaurant",
            "type":"Food & Drink"
        }
    ],
    "sg:phone":"+1 562 436 7643",
    "sg:postcode":"90802",
    "sg:province":"CA",
    "wof:name":"Ashley's",
    "wof:placetype":"venue"
},
  "geometry": {"coordinates":[-118.170101,33.771784],"type":"Point"}
}