{
  "type": "Feature",
  "properties": {
    "iso:country":"US",
    "sg:address":"23710 el Toro Rd",
    "sg:city":"Lake Forest",
    "sg:classifiers":[
        {
            "category":"Real Estate",
            "subcategory":"Real Estate Agent",
            "type":"Services"
        }
    ],
    "sg:phone":"+1 949 837 6265",
    "sg:postcode":"92630",
    "sg:province":"CA",
    "wof:name":"Delano Real Estate",
    "wof:placetype":"venue"
},
  "geometry": {"coordinates":[-117.703041,33.618391],"type":"Point"}
}