{
  "type": "Feature",
  "properties": {
    "iso:country":"US",
    "sg:address":"2111 Whitehall Pl",
    "sg:city":"Alameda",
    "sg:classifiers":[
        {
            "category":"Health Services",
            "subcategory":"Doctor",
            "type":"Services"
        }
    ],
    "sg:phone":"+1 510 523 7842",
    "sg:postcode":"94501",
    "sg:province":"CA",
    "sg:tags":[
        "orthopedist"
    ],
    "wof:name":"Stehr Jack H MD",
    "wof:placetype":"venue"
},
  "geometry": {"coordinates":[-122.254221,37.759614],"type":"Point"}
}