{
  "type": "Feature",
  "properties": {
    "iso:country":"US",
    "sg:address":"1405 Lofgren Rd",
    "sg:city":"Richvale",
    "sg:classifiers":[
        {
            "category":"Farming",
            "subcategory":"Livestock Farm",
            "type":"Manufacturing & Wholesale Goods"
        }
    ],
    "sg:phone":"+1 530 882 4237",
    "sg:postcode":"95965",
    "sg:province":"CA",
    "sg:tags":[
        "ranch"
    ],
    "wof:name":"Josiassen Farm",
    "wof:placetype":"venue"
},
  "geometry": {"coordinates":[-121.763429,39.48648],"type":"Point"}
}