{
  "type": "Feature",
  "properties": {
    "addr:full":"1243 Marilla Ave San Jose CA 95129",
    "addr:housenumber":"1243",
    "addr:postcode":"95129",
    "addr:street":"Marilla Ave",
    "iso:country":"US",
    "sg:address":"1243 Marilla Ave",
    "sg:city":"San Jose",
    "sg:classifiers":[
        {
            "category":"Professional",
            "subcategory":"Management & Consulting",
            "type":"Services"
        }
    ],
    "sg:phone":"+1 408 257 8330",
    "sg:postcode":"95129",
    "sg:province":"CA",
    "sg:tags":[
        "consultant",
        "business"
    ],
    "wof:name":"Tac Tec",
    "wof:placetype":"venue"
},
  "geometry": {"coordinates":[-121.984855,37.302547],"type":"Point"}
}