{
  "type": "Feature",
  "properties": {
    "addr:full":"7119 W Sunset Blvd Ste #315 Los Angeles CA 90046",
    "addr:housenumber":"7119",
    "addr:postcode":"90046",
    "addr:street":"W Sunset Blvd Ste # 315",
    "iso:country":"US",
    "sg:address":"7119 W Sunset Blvd Ste #315",
    "sg:city":"Los Angeles",
    "sg:classifiers":[
        {
            "category":"Building & Trades",
            "subcategory":"Construction",
            "type":"Services"
        }
    ],
    "sg:phone":"+1 800 915 9677",
    "sg:postcode":"90046",
    "sg:province":"CA",
    "sg:tags":[
        "contractor"
    ],
    "sg:website":"www.asapgaragedoorandgate.com/",
    "wof:name":"ASAP Garage Door & Gates",
    "wof:placetype":"venue"
},
  "geometry": {"coordinates":[-118.34507000000001,34.098],"type":"Point"}
}