{
  "type": "Feature",
  "properties": {
    "addr:full":"3600 Wilshire Boulevard Suite 220 Los Angeles CA 90010",
    "addr:housenumber":"3600",
    "addr:postcode":"90010",
    "addr:street":"Wilshire Boulevard Suite 220",
    "iso:country":"US",
    "sg:address":"3600 Wilshire Boulevard Suite 220",
    "sg:city":"Los Angeles",
    "sg:classifiers":[
        {
            "category":"Health Services",
            "subcategory":"Dentist",
            "type":"Services"
        }
    ],
    "sg:phone":"+1 213 384 7767",
    "sg:postcode":"90010",
    "sg:province":"CA",
    "wof:name":"Smile World Orthodontics",
    "wof:placetype":"venue"
},
  "geometry": {"coordinates":[-118.30561899999999,34.061709],"type":"Point"}
}