{
  "type": "Feature",
  "properties": {
    "iso:country":"US",
    "sg:address":"4234 Atlantic Ave",
    "sg:city":"Long Beach",
    "sg:classifiers":[
        {
            "category":"Shopping",
            "subcategory":"Computers & Home Electronics",
            "type":"Retail Goods"
        }
    ],
    "sg:phone":"+1 562 427 6683",
    "sg:postcode":"90807",
    "sg:province":"CA",
    "sg:tags":[
        "machine",
        "dj",
        "tape",
        "karaoke"
    ],
    "sg:website":"www.karaokeyoucansing.com",
    "wof:name":"Karaoke You Can Sing",
    "wof:placetype":"venue"
},
  "geometry": {"coordinates":[-118.18499799999999,33.8335],"type":"Point"}
}