{
  "type": "Feature",
  "properties": {
    "iso:country":"US",
    "sg:address":"195 S Center St",
    "sg:city":"Westmorland",
    "sg:classifiers":[
        {
            "category":"Wholesale",
            "subcategory":"Painting Supplies",
            "type":"Manufacturing & Wholesale Goods"
        },
        {
            "category":"Home & Garden",
            "subcategory":"Garden Supply",
            "type":"Retail Goods"
        },
        {
            "category":"Wholesale",
            "subcategory":"Construction Materials",
            "type":"Manufacturing & Wholesale Goods"
        },
        {
            "category":"Home & Garden",
            "subcategory":"Hardware",
            "type":"Retail Goods"
        }
    ],
    "sg:phone":"+1 760 344 1572",
    "sg:postcode":"92281",
    "sg:province":"CA",
    "sg:tags":[
        "lawn",
        "paint",
        "equipment",
        "part",
        "plumbing",
        "fixtures",
        "store"
    ],
    "sg:website":"http://www.truevalue.com",
    "wof:name":"Westmorland True Value Hardware",
    "wof:placetype":"venue"
},
  "geometry": {"coordinates":[-115.621591,33.036304],"type":"Point"}
}