{
  "type": "Feature",
  "properties": {
    "iso:country":"US",
    "sg:address":"885 Russell Blvd",
    "sg:city":"Davis",
    "sg:classifiers":[
        {
            "category":"Health Services",
            "subcategory":"Doctor",
            "type":"Services"
        }
    ],
    "sg:phone":"+1 530 750 7660",
    "sg:postcode":"95616",
    "sg:province":"CA",
    "sg:tags":[
        "physician",
        "surgeon"
    ],
    "wof:name":"Radiological Associates",
    "wof:placetype":"venue"
},
  "geometry": {"coordinates":[-121.75906500000001,38.546352],"type":"Point"}
}