{
  "type": "Feature",
  "properties": {
    "iso:country":"US",
    "sg:address":"1764 Miramonte Ave",
    "sg:city":"Mountain View",
    "sg:classifiers":[
        {
            "category":"Retail",
            "subcategory":"Animal Services",
            "type":"Services"
        }
    ],
    "sg:phone":"+1 650 988 9274",
    "sg:postcode":"94040",
    "sg:province":"CA",
    "sg:tags":[
        "pet"
    ],
    "wof:name":"Country Pet Wash",
    "wof:placetype":"venue"
},
  "geometry": {"coordinates":[-122.08699799999999,37.372299],"type":"Point"}
}