{
  "type": "Feature",
  "properties": {
    "iso:country":"US",
    "sg:address":"1745 el Camino Real",
    "sg:city":"Atascadero",
    "sg:classifiers":[
        {
            "category":"Building & Trades",
            "subcategory":"Landscaping Services",
            "type":"Services"
        }
    ],
    "sg:phone":"+1 805 461 1052",
    "sg:postcode":"93422",
    "sg:province":"CA",
    "sg:tags":[
        "landscape",
        "contractor"
    ],
    "wof:name":"Good News Harmony Gardening",
    "wof:placetype":"venue"
},
  "geometry": {"coordinates":[-120.699132,35.515743],"type":"Point"}
}