{
  "type": "Feature",
  "properties": {
    "addr:full":"24901 Stagecoach Dr Laguna Hills CA 92653",
    "addr:housenumber":"24901",
    "addr:postcode":"92653",
    "addr:street":"Stagecoach Dr",
    "iso:country":"US",
    "sg:address":"24901 Stagecoach Dr",
    "sg:city":"Laguna Hills",
    "sg:classifiers":[
        {
            "category":"Retail",
            "subcategory":"Auto Repair",
            "type":"Services"
        }
    ],
    "sg:phone":"+1 949 768 6056",
    "sg:postcode":"92653",
    "sg:province":"CA",
    "sg:tags":[
        "repairing",
        "automobile"
    ],
    "wof:name":"British Performance",
    "wof:placetype":"venue"
},
  "geometry": {"coordinates":[-117.68546000000001,33.59926],"type":"Point"}
}