{
  "type": "Feature",
  "properties": {
    "addr:full":"611 5th St Colusa CA 95932",
    "addr:housenumber":"611",
    "addr:postcode":"95932",
    "addr:street":"5Th St",
    "iso:country":"US",
    "sg:address":"611 5th St",
    "sg:city":"Colusa",
    "sg:classifiers":[
        {
            "category":"Autos & Motor Vehicles",
            "subcategory":"Automobile Sales",
            "type":"Retail Goods"
        }
    ],
    "sg:phone":"+1 530 476 2261",
    "sg:postcode":"95932",
    "sg:province":"CA",
    "sg:tags":[
        "car",
        "dealer"
    ],
    "wof:name":"Bingaman Motors",
    "wof:placetype":"venue"
},
  "geometry": {"coordinates":[-122.00931799999999,39.210338],"type":"Point"}
}