{
  "type": "Feature",
  "properties": {
    "iso:country":"US",
    "sg:address":"611 5th St",
    "sg:city":"Colusa",
    "sg:classifiers":[
        {
            "category":"Autos & Motor Vehicles",
            "subcategory":"Automobile Sales",
            "type":"Retail Goods"
        }
    ],
    "sg:phone":"+1 530 476 2261",
    "sg:postcode":"95932",
    "sg:province":"CA",
    "sg:tags":[
        "car",
        "dealer"
    ],
    "wof:name":"Bingaman Motors",
    "wof:placetype":"venue"
},
  "geometry": {"coordinates":[-122.009318,39.210338],"type":"Point"}
}