{
  "type": "Feature",
  "properties": {
    "iso:country":"US",
    "sg:address":"1357 el Rey Ave",
    "sg:city":"El Cajon",
    "sg:classifiers":[
        {
            "category":"Manufacturing",
            "subcategory":"Tools & Machinery",
            "type":"Manufacturing & Wholesale Goods"
        }
    ],
    "sg:phone":"+1 619 590 0846",
    "sg:postcode":"92021",
    "sg:province":"CA",
    "sg:tags":[
        "machine",
        "shop",
        "job"
    ],
    "wof:name":"B&A Wire EDM",
    "wof:placetype":"venue"
},
  "geometry": {"coordinates":[-116.933177,32.815296],"type":"Point"}
}