{
  "type": "Feature",
  "properties": {
    "iso:country":"US",
    "sg:address":"8301 Hollister Ave",
    "sg:city":"Goleta",
    "sg:phone":"+1 805 968 0100",
    "sg:postcode":"93117",
    "sg:province":"CA",
    "wof:name":"Bacara Resort and Spa",
    "wof:placetype":"venue"
},
  "geometry": {"coordinates":[-119.90572400000001,34.431],"type":"Point"}
}