{
  "type": "Feature",
  "properties": {
    "addr:full":"1656 Shattuck Ave Berkeley CA 94701",
    "addr:housenumber":"1656",
    "addr:postcode":"94701",
    "addr:street":"Shattuck Ave",
    "iso:country":"US",
    "sg:address":"1656 Shattuck Ave",
    "sg:city":"Berkeley",
    "sg:classifiers":[
        {
            "category":"Real Estate",
            "subcategory":"Real Estate Agent",
            "type":"Services"
        }
    ],
    "sg:phone":"+1 510 848 1950",
    "sg:postcode":"94701",
    "sg:province":"CA",
    "sg:website":"www.thornwallproperties.com/",
    "wof:name":"Martha Becker at Thornwall Properties",
    "wof:placetype":"venue"
},
  "geometry": {"coordinates":[-122.269156,37.877244],"type":"Point"}
}