{
  "type": "Feature",
  "properties": {
    "addr:full":"1250 Oakmead Pkwy Sunnyvale CA 94085",
    "addr:housenumber":"1250",
    "addr:postcode":"94085",
    "addr:street":"Oakmead Pkwy",
    "iso:country":"US",
    "sg:address":"1250 Oakmead Pkwy",
    "sg:city":"Sunnyvale",
    "sg:classifiers":[
        {
            "category":"Manufacturing",
            "subcategory":"Tools & Machinery",
            "type":"Manufacturing & Wholesale Goods"
        }
    ],
    "sg:phone":"+1 408 730 2651",
    "sg:postcode":"94085",
    "sg:province":"CA",
    "sg:tags":[
        "equipment",
        "lighting",
        "mfg"
    ],
    "wof:name":"United States Lighting Inc",
    "wof:placetype":"venue"
},
  "geometry": {"coordinates":[-121.989942,37.386779],"type":"Point"}
}