{
  "type": "Feature",
  "properties": {
    "iso:country":"US",
    "sg:address":"8380 Miramar Mall Ste 228",
    "sg:city":"San Diego",
    "sg:classifiers":[
        {
            "category":"Communications",
            "type":"Services"
        }
    ],
    "sg:phone":"+1 858 550 3926",
    "sg:postcode":"92121",
    "sg:province":"CA",
    "sg:tags":[
        "web",
        "design"
    ],
    "sg:website":"www.remedyone.com",
    "wof:name":"Remedyone",
    "wof:placetype":"venue"
},
  "geometry": {"coordinates":[-117.183797,32.879944],"type":"Point"}
}