{
  "type": "Feature",
  "properties": {
    "iso:country":"US",
    "sg:address":"420 N Lakeview Ave",
    "sg:city":"Anaheim",
    "sg:classifiers":[
        {
            "category":"Restaurant",
            "type":"Food & Drink"
        }
    ],
    "sg:phone":"+1 714 282 5482",
    "sg:postcode":"92807",
    "sg:province":"CA",
    "wof:name":"Far East Garden",
    "wof:placetype":"venue"
},
  "geometry": {"coordinates":[-117.816002,33.8526],"type":"Point"}
}