{
  "type": "Feature",
  "properties": {
    "iso:country":"US",
    "sg:address":"14 Heron Dr",
    "sg:city":"Mill Valley",
    "sg:classifiers":[
        {
            "category":"Professional",
            "subcategory":"Management & Consulting",
            "type":"Services"
        }
    ],
    "sg:phone":"+1 415 380 8561",
    "sg:postcode":"94941",
    "sg:province":"CA",
    "sg:tags":[
        "consultant",
        "business"
    ],
    "wof:name":"Strategies For Business",
    "wof:placetype":"venue"
},
  "geometry": {"coordinates":[-122.496686,37.878579],"type":"Point"}
}