{
  "type": "Feature",
  "properties": {
    "iso:country":"US",
    "sg:address":"2054 Zanker Rd",
    "sg:city":"San Jose",
    "sg:classifiers":[
        {
            "category":"Professional",
            "subcategory":"Business Services",
            "type":"Services"
        }
    ],
    "sg:phone":"+1 408 436 1701",
    "sg:postcode":"95134",
    "sg:province":"CA",
    "sg:tags":[
        "record",
        "document"
    ],
    "wof:name":"SOURCECORP Healthserve",
    "wof:placetype":"venue"
},
  "geometry": {"coordinates":[-121.91583199999999,37.380051],"type":"Point"}
}