{
  "type": "Feature",
  "properties": {
    "addr:full":"3199 N Beecher Rd Stockton CA 95215",
    "addr:housenumber":"3199",
    "addr:postcode":"95215",
    "addr:street":"N Beecher Rd",
    "iso:country":"US",
    "sg:address":"3199 N Beecher Rd",
    "sg:city":"Stockton",
    "sg:classifiers":[
        {
            "category":"Professional",
            "subcategory":"Management & Consulting",
            "type":"Services"
        }
    ],
    "sg:phone":"+1 209 886 5618",
    "sg:postcode":"95215",
    "sg:province":"CA",
    "sg:tags":[
        "consultant"
    ],
    "wof:name":"Valley Pearl Marketing",
    "wof:placetype":"venue"
},
  "geometry": {"coordinates":[-121.168037,38.003528],"type":"Point"}
}