{
  "type": "Feature",
  "properties": {
    "addr:full":"825 E Belmont Ave Fresno CA 93701",
    "addr:housenumber":"825",
    "addr:postcode":"93701",
    "addr:street":"E Belmont Ave",
    "iso:country":"US",
    "sg:address":"825 E Belmont Ave",
    "sg:city":"Fresno",
    "sg:classifiers":[
        {
            "category":"Autos & Motor Vehicles",
            "subcategory":"Auto Supplies",
            "type":"Retail Goods"
        }
    ],
    "sg:phone":"+1 559 485 0720",
    "sg:postcode":"93701",
    "sg:province":"CA",
    "sg:tags":[
        "automobile",
        "rebuilt",
        "part",
        "supplies-used"
    ],
    "wof:name":"V and V Automotive Rebuilders",
    "wof:placetype":"venue"
},
  "geometry": {"coordinates":[-119.800995,36.750414],"type":"Point"}
}