{
  "type": "Feature",
  "properties": {
    "addr:full":"4517 Blackburn Ct Concord CA 94518",
    "addr:housenumber":"4517",
    "addr:postcode":"94518",
    "addr:street":"Blackburn Ct",
    "iso:country":"US",
    "sg:address":"4517 Blackburn Ct",
    "sg:city":"Concord",
    "sg:classifiers":[
        {
            "category":"Manufacturing",
            "subcategory":"Food",
            "type":"Manufacturing & Wholesale Goods"
        }
    ],
    "sg:phone":"+1 925 680 4807",
    "sg:postcode":"94518",
    "sg:province":"CA",
    "sg:tags":[
        "malt",
        "beverage",
        "mfg"
    ],
    "wof:name":"Custom Brews & Smokes",
    "wof:placetype":"venue"
},
  "geometry": {"coordinates":[-121.995043,37.948165],"type":"Point"}
}