{
  "type": "Feature",
  "properties": {
    "iso:country":"US",
    "sg:address":"10942 Ramona Blvd",
    "sg:city":"El Monte",
    "sg:classifiers":[
        {
            "category":"Health Services",
            "subcategory":"Doctor",
            "type":"Services"
        }
    ],
    "sg:phone":"+1 626 442 2929",
    "sg:postcode":"91731",
    "sg:province":"CA",
    "wof:name":"Comprehensive Medical Group Of Southern California",
    "wof:placetype":"venue"
},
  "geometry": {"coordinates":[-118.702663,34.188434],"type":"Point"}
}