{
  "type": "Feature",
  "properties": {
    "iso:country":"US",
    "sg:address":"7211 Cozycroft Ave",
    "sg:city":"Winnekta",
    "sg:classifiers":[
        {
            "category":"Professional",
            "subcategory":"Art Services",
            "type":"Services"
        }
    ],
    "sg:phone":"+1 818 731 0675",
    "sg:postcode":"91306",
    "sg:province":"CA",
    "sg:tags":[
        "graphic",
        "design"
    ],
    "wof:name":"LongImage",
    "wof:placetype":"venue"
},
  "geometry": {"coordinates":[-118.582424,34.201568],"type":"Point"}
}