{
  "type": "Feature",
  "properties": {
    "addr:full":"2432 E 18th St National City CA 91950",
    "addr:housenumber":"2432",
    "addr:postcode":"91950",
    "addr:street":"E 18Th St",
    "iso:country":"US",
    "sg:address":"2432 E 18th St",
    "sg:city":"National City",
    "sg:classifiers":[
        {
            "category":"Education",
            "subcategory":"Preschool",
            "type":"Public Place"
        },
        {
            "category":"Education",
            "subcategory":"School",
            "type":"Public Place"
        }
    ],
    "sg:phone":"+1 619 470 0720",
    "sg:postcode":"91950",
    "sg:province":"CA",
    "sg:tags":[
        "elementary"
    ],
    "wof:name":"National City Head Start",
    "wof:placetype":"venue"
},
  "geometry": {"coordinates":[-117.078003,32.674198],"type":"Point"}
}