{
  "type": "Feature",
  "properties": {
    "iso:country":"US",
    "sg:address":"150 Executive Park Blvd",
    "sg:city":"San Francisco",
    "sg:classifiers":[
        {
            "category":"Wholesale",
            "subcategory":"Computers",
            "type":"Manufacturing & Wholesale Goods"
        }
    ],
    "sg:phone":"+1 415 656 1909",
    "sg:postcode":"94134",
    "sg:province":"CA",
    "sg:tags":[
        "software"
    ],
    "sg:website":"www.optima-us.com",
    "wof:name":"Optima Distribution Inc",
    "wof:placetype":"venue"
},
  "geometry": {"coordinates":[-122.39381400000001,37.711211],"type":"Point"}
}