{
  "type": "Feature",
  "properties": {
    "iso:country":"US",
    "sg:address":"650 Presidio Ave",
    "sg:city":"San Francisco",
    "sg:classifiers":[
        {
            "category":"Organizations",
            "subcategory":"Professional Association",
            "type":"Services"
        }
    ],
    "sg:phone":"+1 415 346 4176",
    "sg:postcode":"94115",
    "sg:province":"CA",
    "wof:name":"Presidio Homeowners Assn",
    "wof:placetype":"venue"
},
  "geometry": {"coordinates":[-122.44642399999999,37.785857],"type":"Point"}
}