{
  "type": "Feature",
  "properties": {
    "addr:full":"24342 Parkside Dr E Laguna Niguel CA 92677",
    "addr:housenumber":"24342",
    "addr:postcode":"92677",
    "addr:street":"Parkside Dr E",
    "iso:country":"US",
    "sg:address":"24342 Parkside Dr E",
    "sg:city":"Laguna Niguel",
    "sg:classifiers":[
        {
            "category":"Professional",
            "type":"Services"
        }
    ],
    "sg:phone":"+1 949 395 1750",
    "sg:postcode":"92677",
    "sg:province":"CA",
    "sg:tags":[
        "establishment"
    ],
    "wof:name":"Phoenix Scientific",
    "wof:placetype":"venue"
},
  "geometry": {"coordinates":[-117.70485100000001,33.532666],"type":"Point"}
}