{
  "type": "Feature",
  "properties": {
    "iso:country":"US",
    "sg:address":"11581 Potrero Rd",
    "sg:city":"Banning",
    "sg:classifiers":[
        {
            "category":"Government",
            "subcategory":"Fire Station",
            "type":"Public Place"
        }
    ],
    "sg:phone":"+1 951 849 7194",
    "sg:postcode":"92220",
    "sg:province":"CA",
    "sg:tags":[
        "protection"
    ],
    "wof:name":"Fire Dept- Station 278",
    "wof:placetype":"venue"
},
  "geometry": {"coordinates":[-116.82902900000001,33.952726],"type":"Point"}
}