{
  "type": "Feature",
  "properties": {
    "iso:country":"US",
    "sg:address":"12673 Simple Justice Creek Rd",
    "sg:city":"Penn Valley",
    "sg:classifiers":[
        {
            "category":"Professional",
            "type":"Services"
        }
    ],
    "sg:phone":"+1 530 477 7728",
    "sg:postcode":"95946",
    "sg:province":"CA",
    "wof:name":"Aaxiom Resources LLC",
    "wof:placetype":"venue"
},
  "geometry": {"coordinates":[-121.15388,39.173233],"type":"Point"}
}