{
  "type": "Feature",
  "properties": {
    "iso:country":"US",
    "sg:address":"7219 Deering Ave",
    "sg:city":"Canoga Park",
    "sg:classifiers":[
        {
            "category":"Government",
            "subcategory":"Office",
            "type":"Public Place"
        }
    ],
    "sg:phone":"+1 818 961 0336",
    "sg:postcode":"91303",
    "sg:province":"CA",
    "sg:tags":[
        "smog",
        "check"
    ],
    "wof:name":"Mc Auto",
    "wof:placetype":"venue"
},
  "geometry": {"coordinates":[-118.597021,34.201594],"type":"Point"}
}