{
  "type": "Feature",
  "properties": {
    "iso:country":"US",
    "sg:address":"7916 W 80th St",
    "sg:city":"Playa Del Rey",
    "sg:classifiers":[
        {
            "category":"Professional",
            "type":"Services"
        }
    ],
    "sg:phone":"+1 310 821 3073",
    "sg:postcode":"90293",
    "sg:province":"CA",
    "wof:name":"John S Doyon",
    "wof:placetype":"venue"
},
  "geometry": {"coordinates":[-118.435615,33.960833],"type":"Point"}
}