{
  "type": "Feature",
  "properties": {
    "addr:full":"1080 E Washington St Colton CA 92324",
    "addr:housenumber":"1080",
    "addr:postcode":"92324",
    "addr:street":"E Washington St",
    "iso:country":"US",
    "sg:address":"1080 E Washington St",
    "sg:city":"Colton",
    "sg:classifiers":[
        {
            "category":"Health Services",
            "subcategory":"Medical Lab",
            "type":"Services"
        }
    ],
    "sg:phone":"+1 909 825 7268",
    "sg:postcode":"92324",
    "sg:province":"CA",
    "wof:name":"Quest Diagnostics",
    "wof:placetype":"venue"
},
  "geometry": {"coordinates":[-117.310059,34.048291],"type":"Point"}
}