{
  "type": "Feature",
  "properties": {
    "addr:full":"6154 Bollinger Rd San Jose CA 95129",
    "addr:housenumber":"6154",
    "addr:postcode":"95129",
    "addr:street":"Bollinger Rd",
    "iso:country":"US",
    "sg:address":"6154 Bollinger Rd",
    "sg:city":"San Jose",
    "sg:classifiers":[
        {
            "category":"Restaurant",
            "type":"Food & Drink"
        }
    ],
    "sg:menulink":"http://www.allmenus.com/ca/san-jose/277351-chef-woo-chinese-restaurant/menu/",
    "sg:phone":"+1 408 255 7520",
    "sg:postcode":"95129",
    "sg:province":"CA",
    "sg:tags":[
        "taiwanese",
        "asian",
        "chinese"
    ],
    "wof:name":"Chef Woo Chinese Restaurant",
    "wof:placetype":"venue"
},
  "geometry": {"coordinates":[-122.01170399999999,37.310352],"type":"Point"}
}