{
  "type": "Feature",
  "properties": {
    "addr:full":"5920 San Pablo Ave Oakland CA 94608",
    "addr:housenumber":"5920",
    "addr:postcode":"94608",
    "addr:street":"San Pablo Ave",
    "iso:country":"US",
    "sg:address":"5920 San Pablo Ave",
    "sg:city":"Oakland",
    "sg:classifiers":[
        {
            "category":"Professional",
            "subcategory":"Management & Consulting",
            "type":"Services"
        }
    ],
    "sg:phone":"+1 510 658 3909",
    "sg:postcode":"94608",
    "sg:province":"CA",
    "sg:tags":[
        "consultant",
        "business"
    ],
    "wof:name":"Inpartnership Consulting Inc",
    "wof:placetype":"venue"
},
  "geometry": {"coordinates":[-122.283528,37.842275],"type":"Point"}
}