{
  "type": "Feature",
  "properties": {
    "addr:full":"1391 Rosewood Ln Napa CA 94558",
    "addr:housenumber":"1391",
    "addr:postcode":"94558",
    "addr:street":"Rosewood Ln",
    "iso:country":"US",
    "sg:address":"1391 Rosewood Ln",
    "sg:city":"Napa",
    "sg:classifiers":[
        {
            "category":"Professional",
            "subcategory":"Management & Consulting",
            "type":"Services"
        }
    ],
    "sg:phone":"+1 707 217 9990",
    "sg:postcode":"94558",
    "sg:province":"CA",
    "wof:name":"Napa Valley Destinations",
    "wof:placetype":"venue"
},
  "geometry": {"coordinates":[-122.29685600000001,38.334436],"type":"Point"}
}