{
  "type": "Feature",
  "properties": {
    "addr:full":"5314 Nez Perce Way Antioch CA 94531",
    "addr:housenumber":"5314",
    "addr:postcode":"ca 94531",
    "addr:street":"Nez Perce Way",
    "iso:country":"US",
    "sg:address":"5314 Nez Perce Way",
    "sg:city":"Antioch",
    "sg:classifiers":[
        {
            "category":"Real Estate",
            "subcategory":"Real Estate Services",
            "type":"Services"
        }
    ],
    "sg:phone":"+1 925 565 9014",
    "sg:postcode":"94531",
    "sg:province":"CA",
    "sg:tags":[
        "management"
    ],
    "wof:name":"C & A Real Estate and Property Management",
    "wof:placetype":"venue"
},
  "geometry": {"coordinates":[-121.770483,37.956528],"type":"Point"}
}