{
  "type": "Feature",
  "properties": {
    "addr:full":"6910 San Fernando Rd Glendale CA 91201",
    "addr:housenumber":"6910",
    "addr:postcode":"91201",
    "addr:street":"San Fernando Rd",
    "iso:country":"US",
    "sg:address":"6910 San Fernando Rd",
    "sg:city":"Glendale",
    "sg:classifiers":[
        {
            "category":"Wholesale",
            "subcategory":"Hardware",
            "type":"Manufacturing & Wholesale Goods"
        }
    ],
    "sg:phone":"+1 818 842 2159",
    "sg:postcode":"91201",
    "sg:province":"CA",
    "sg:tags":[
        "plumbing"
    ],
    "wof:name":"Ocean Plumbing Supply",
    "wof:placetype":"venue"
},
  "geometry": {"coordinates":[-118.29812699999999,34.173219],"type":"Point"}
}