{
  "type": "Feature",
  "properties": {
    "iso:country":"US",
    "sg:address":"21 Brookline",
    "sg:city":"Aliso Viejo",
    "sg:classifiers":[
        {
            "category":"Professional",
            "type":"Services"
        }
    ],
    "sg:phone":"+1 949 389 5737",
    "sg:postcode":"92656",
    "sg:province":"CA",
    "wof:name":"Sharpplace Co",
    "wof:placetype":"venue"
},
  "geometry": {"coordinates":[-117.73040399999999,33.590148],"type":"Point"}
}