{
  "type": "Feature",
  "properties": {
    "iso:country":"US",
    "sg:address":"15155 Fawndale Rd",
    "sg:city":"Redding",
    "sg:classifiers":[
        {
            "category":"Recreation",
            "subcategory":"Marina",
            "type":"Entertainment"
        }
    ],
    "sg:phone":"+1 530 275 2455",
    "sg:postcode":"96003",
    "sg:province":"CA",
    "sg:tags":[
        "storage",
        "boat"
    ],
    "wof:name":"Shasta Lake Boat Storage",
    "wof:placetype":"venue"
},
  "geometry": {"coordinates":[-122.320833,40.728483],"type":"Point"}
}