{
  "type": "Feature",
  "properties": {
    "iso:country":"US",
    "sg:address":"405 Primrose Rd",
    "sg:city":"Burlingame",
    "sg:classifiers":[
        {
            "category":"Real Estate",
            "subcategory":"Real Estate Services",
            "type":"Services"
        }
    ],
    "sg:phone":"+1 650 348 8261",
    "sg:postcode":"94010",
    "sg:province":"CA",
    "sg:tags":[
        "company",
        "title"
    ],
    "wof:name":"Fidelity National Title",
    "wof:placetype":"venue"
},
  "geometry": {"coordinates":[-122.35014200000001,37.579341],"type":"Point"}
}