{
  "type": "Feature",
  "properties": {
    "iso:country":"US",
    "sg:address":"189 The Grove Dr",
    "sg:city":"Los Angeles",
    "sg:classifiers":[
        {
            "category":"Restaurant",
            "type":"Food & Drink"
        }
    ],
    "sg:menulink":"http://www.allmenus.com/ca/los-angeles/41505-the-cheesecake-factory/menu/",
    "sg:phone":"+1 323 634 0511",
    "sg:postcode":"90036",
    "sg:province":"CA",
    "sg:tags":[
        "new",
        "american"
    ],
    "wof:name":"The Cheesecake Factory",
    "wof:placetype":"venue"
},
  "geometry": {"coordinates":[-118.356343,34.072218],"type":"Point"}
}