{
  "type": "Feature",
  "properties": {
    "addr:full":"2117 Delaware Ave Santa Cruz CA 95060",
    "addr:housenumber":"2117",
    "addr:postcode":"95060",
    "addr:street":"Delaware Ave",
    "iso:country":"US",
    "sg:address":"2117 Delaware Ave",
    "sg:city":"Santa Cruz",
    "sg:classifiers":[
        {
            "category":"Wholesale",
            "subcategory":"Toys & Hobbies",
            "type":"Manufacturing & Wholesale Goods"
        }
    ],
    "sg:phone":"+1 831 429 8658",
    "sg:postcode":"95060",
    "sg:province":"CA",
    "sg:tags":[
        "balloon"
    ],
    "sg:website":"www.silverglate.com",
    "wof:name":"Rhino Toys",
    "wof:placetype":"venue"
},
  "geometry": {"coordinates":[-122.054102,36.955008],"type":"Point"}
}