{
  "type": "Feature",
  "properties": {
    "iso:country":"US",
    "sg:address":"5280 Pacheco Blvd",
    "sg:city":"Pacheco",
    "sg:classifiers":[
        {
            "category":"Retail",
            "subcategory":"Veterinary Services",
            "type":"Services"
        }
    ],
    "sg:phone":"+1 925 686 0683",
    "sg:postcode":"94553",
    "sg:province":"CA",
    "sg:tags":[
        "veterinarian"
    ],
    "wof:name":"Montecito Animal Clinic",
    "wof:placetype":"venue"
},
  "geometry": {"coordinates":[-122.073668,37.991713],"type":"Point"}
}