{
  "type": "Feature",
  "properties": {
    "addr:full":"9153 Dupont Way Sacramento CA 95826",
    "addr:housenumber":"9153",
    "addr:postcode":"95826",
    "addr:street":"Dupont Way",
    "iso:country":"US",
    "sg:address":"9153 Dupont Way",
    "sg:city":"Sacramento",
    "sg:classifiers":[
        {
            "category":"Manufacturing",
            "subcategory":"Printing",
            "type":"Manufacturing & Wholesale Goods"
        }
    ],
    "sg:phone":"+1 916 362 1940",
    "sg:postcode":"95826",
    "sg:province":"CA",
    "sg:tags":[
        "agency",
        "advertising",
        "periodical"
    ],
    "wof:name":"Charter Publishing Group",
    "wof:placetype":"venue"
},
  "geometry": {"coordinates":[-121.358862,38.5536],"type":"Point"}
}