{
  "type": "Feature",
  "properties": {
    "iso:country":"US",
    "sg:address":"2009 Sheridan Rd",
    "sg:city":"Encinitas",
    "sg:classifiers":[
        {
            "category":"Farming",
            "subcategory":"Nursery",
            "type":"Manufacturing & Wholesale Goods"
        }
    ],
    "sg:phone":"+1 760 942 5001",
    "sg:postcode":"92024",
    "sg:province":"CA",
    "sg:tags":[
        "greenhouse"
    ],
    "wof:name":"Erwin Mojonnier Enterprises",
    "wof:placetype":"venue"
},
  "geometry": {"coordinates":[-117.303045,33.0859],"type":"Point"}
}