{
  "type": "Feature",
  "properties": {
    "iso:country":"US",
    "sg:address":"10363 Cochran Ave",
    "sg:city":"Riverside",
    "sg:classifiers":[
        {
            "category":"Shopping",
            "subcategory":"Gifts & Souvenirs",
            "type":"Retail Goods"
        }
    ],
    "sg:phone":"+1 951 637 0588",
    "sg:postcode":"92505",
    "sg:province":"CA",
    "wof:name":"Dons Fine Gifts",
    "wof:placetype":"venue"
},
  "geometry": {"coordinates":[-117.46868600000001,33.913092],"type":"Point"}
}