{
  "type": "Feature",
  "properties": {
    "addr:full":"5101 E La Palma Ave Ste 104 Anaheim CA 92807",
    "addr:housenumber":"5101",
    "addr:postcode":"92807",
    "addr:street":"E La Palma Ave Ste 104",
    "iso:country":"US",
    "sg:address":"5101 E La Palma Ave Ste 104",
    "sg:city":"Anaheim",
    "sg:classifiers":[
        {
            "category":"Professional",
            "subcategory":"Accounting & Tax Preparation",
            "type":"Services"
        }
    ],
    "sg:phone":"+1 714 970 9099",
    "sg:postcode":"92807",
    "sg:province":"CA",
    "sg:tags":[
        "accountant"
    ],
    "wof:name":"McCorkle Robt E CPA",
    "wof:placetype":"venue"
},
  "geometry": {"coordinates":[-117.806071,33.859495],"type":"Point"}
}