{
  "type": "Feature",
  "properties": {
    "addr:full":"920 Rancheros Dr San Marcos CA 92069",
    "addr:housenumber":"920",
    "addr:postcode":"92069",
    "addr:street":"Rancheros Dr",
    "iso:country":"US",
    "sg:address":"920 Rancheros Dr",
    "sg:city":"San Marcos",
    "sg:classifiers":[
        {
            "category":"Manufacturing",
            "subcategory":"Tools & Machinery",
            "type":"Manufacturing & Wholesale Goods"
        }
    ],
    "sg:phone":"+1 760 743 6113",
    "sg:postcode":"92069",
    "sg:province":"CA",
    "sg:tags":[
        "equipment",
        "mfg"
    ],
    "wof:name":"Plastic Injection Molding",
    "wof:placetype":"venue"
},
  "geometry": {"coordinates":[-117.13021000000001,33.135482],"type":"Point"}
}