{
  "type": "Feature",
  "properties": {
    "addr:full":"16916 Hawthorne Blvd Lawndale CA 90260",
    "addr:housenumber":"16916",
    "addr:postcode":"ca 90260",
    "addr:street":"Hawthorne Blvd",
    "iso:country":"US",
    "sg:address":"16916 Hawthorne Blvd",
    "sg:city":"Lawndale",
    "sg:classifiers":[
        {
            "category":"Banks & Credit Unions",
            "subcategory":"Bank",
            "type":"Services"
        }
    ],
    "sg:phone":"+1 310 370 0255",
    "sg:postcode":"90260",
    "sg:province":"CA",
    "sg:tags":[
        "cashing",
        "check"
    ],
    "wof:name":"LCS",
    "wof:placetype":"venue"
},
  "geometry": {"coordinates":[-118.352284,33.876976],"type":"Point"}
}