{
  "type": "Feature",
  "properties": {
    "addr:full":"Westfield Century City 10250 Santa Monica Blvd., Lower Level Los Angeles CA 90067",
    "addr:postcode":"10250;90067",
    "addr:street":"Santa Monica Blvd. Lower Level",
    "iso:country":"US",
    "sg:address":"Westfield Century City 10250 Santa Monica Blvd., Lower Level",
    "sg:city":"Los Angeles",
    "sg:classifiers":[
        {
            "category":"Food & Beverages",
            "subcategory":"Candy",
            "type":"Retail Goods"
        },
        {
            "category":"Ice Cream",
            "type":"Food & Drink"
        }
    ],
    "sg:phone":"+1 310 788 9682",
    "sg:postcode":"90067",
    "sg:province":"CA",
    "sg:tags":[
        "frozen",
        "dessert",
        "yogurt"
    ],
    "sg:website":"www.benjerry.com",
    "wof:name":"Ben & Jerry's Ice Cream",
    "wof:placetype":"venue"
},
  "geometry": {"coordinates":[-118.420822,34.059464],"type":"Point"}
}