{
  "type": "Feature",
  "properties": {
    "iso:country":"US",
    "sg:address":"18031 Chanera Ave",
    "sg:city":"Torrance",
    "sg:classifiers":[
        {
            "category":"Manufacturing",
            "subcategory":"Tools & Machinery",
            "type":"Manufacturing & Wholesale Goods"
        }
    ],
    "sg:phone":"+1 310 637 9713",
    "sg:postcode":"90504",
    "sg:province":"CA",
    "sg:tags":[
        "dental",
        "mfg"
    ],
    "wof:name":"Rodney Guyton",
    "wof:placetype":"venue"
},
  "geometry": {"coordinates":[-118.32467,33.866371],"type":"Point"}
}