{
  "type": "Feature",
  "properties": {
    "addr:full":"436 N Canal St South San Francisco CA 94080",
    "addr:housenumber":"436",
    "addr:postcode":"94080",
    "addr:street":"N Canal St",
    "iso:country":"US",
    "sg:address":"436 N Canal St",
    "sg:city":"South San Francisco",
    "sg:classifiers":[
        {
            "category":"Coffee & Tea",
            "type":"Food & Drink"
        }
    ],
    "sg:phone":"+1 650 589 8500",
    "sg:postcode":"94080",
    "sg:province":"CA",
    "sg:website":"www.freedscoffeetea.com",
    "wof:name":"Freed Teller & Freed",
    "wof:placetype":"venue"
},
  "geometry": {"coordinates":[-122.415851,37.651185],"type":"Point"}
}