{
  "type": "Feature",
  "properties": {
    "addr:full":"23805 Stuart Ranch Rd Malibu CA 90265",
    "addr:housenumber":"23805",
    "addr:postcode":"90265",
    "addr:street":"Stuart Ranch Rd",
    "iso:country":"US",
    "sg:address":"23805 Stuart Ranch Rd",
    "sg:city":"Malibu",
    "sg:classifiers":[
        {
            "category":"Professional",
            "subcategory":"Lawyer & Legal Services",
            "type":"Services"
        }
    ],
    "sg:phone":"+1 310 456 3663",
    "sg:postcode":"90265",
    "sg:province":"CA",
    "sg:tags":[
        "attorney"
    ],
    "wof:name":"William A KERR Corp",
    "wof:placetype":"venue"
},
  "geometry": {"coordinates":[-118.69249000000001,34.038033],"type":"Point"}
}