{
  "type": "Feature",
  "properties": {
    "iso:country":"US",
    "sg:address":"3006 Sepulveda Blvd",
    "sg:city":"Torrance",
    "sg:classifiers":[
        {
            "category":"Autos & Motor Vehicles",
            "subcategory":"Fuel & Gas Station",
            "type":"Retail Goods"
        },
        {
            "category":"Retail",
            "subcategory":"Auto Repair",
            "type":"Services"
        }
    ],
    "sg:phone":"+1 310 534 0241",
    "sg:postcode":"90505",
    "sg:province":"CA",
    "wof:name":"Mas's Mobil Products Service",
    "wof:placetype":"venue"
},
  "geometry": {"coordinates":[-118.339996,33.824299],"type":"Point"}
}