{
  "type": "Feature",
  "properties": {
    "iso:country":"US",
    "sg:address":"805 N Orchard Ave",
    "sg:city":"Vacaville",
    "sg:classifiers":[
        {
            "category":"Education",
            "subcategory":"School",
            "type":"Public Place"
        }
    ],
    "sg:phone":"+1 707 453 6255",
    "sg:postcode":"95688",
    "sg:province":"CA",
    "wof:name":"Orchard Elementary School",
    "wof:placetype":"venue"
},
  "geometry": {"coordinates":[-122.004513,38.375195],"type":"Point"}
}