{
  "type": "Feature",
  "properties": {
    "addr:full":"9209 Coulter Ct Bakersfield CA 93311",
    "addr:housenumber":"9209",
    "addr:postcode":"93311",
    "addr:street":"Coulter Ct",
    "iso:country":"US",
    "sg:address":"9209 Coulter Ct",
    "sg:city":"Bakersfield",
    "sg:classifiers":[
        {
            "category":"Freight",
            "type":"Transportation"
        }
    ],
    "sg:phone":"+1 661 664 7363",
    "sg:postcode":"93311",
    "sg:province":"CA",
    "sg:tags":[
        "local",
        "trucking"
    ],
    "wof:name":"Mike Rose Trucking",
    "wof:placetype":"venue"
},
  "geometry": {"coordinates":[-119.104201,35.31127],"type":"Point"}
}