{
  "type": "Feature",
  "properties": {
    "addr:full":"5700 Lankershim Blvd North Hollywood CA 91601",
    "addr:postcode":"5700;91601",
    "addr:street":"Lankershim Blvd",
    "iso:country":"US",
    "sg:address":"5700 Lankershim Blvd",
    "sg:city":"North Hollywood",
    "sg:classifiers":[
        {
            "category":"Professional",
            "type":"Services"
        }
    ],
    "sg:phone":"+1 818 508 8462",
    "sg:postcode":"91601",
    "sg:province":"CA",
    "wof:name":"Max Yu",
    "wof:placetype":"venue"
},
  "geometry": {"coordinates":[-118.380689,34.174921],"type":"Point"}
}