{
  "type": "Feature",
  "properties": {
    "iso:country":"US",
    "sg:address":"3262 Lansdown Ln",
    "sg:city":"Ramona",
    "sg:classifiers":[
        {
            "category":"Building & Trades",
            "subcategory":"Electrical",
            "type":"Services"
        }
    ],
    "sg:phone":"+1 760 789 2902",
    "sg:postcode":"92065",
    "sg:province":"CA",
    "sg:tags":[
        "electric",
        "contractor"
    ],
    "wof:name":"D W Electric Inc",
    "wof:placetype":"venue"
},
  "geometry": {"coordinates":[-116.905456,33.010706],"type":"Point"}
}