{
  "type": "Feature",
  "properties": {
    "iso:country":"US",
    "sg:address":"608 University Ave",
    "sg:city":"Sacramento",
    "sg:classifiers":[
        {
            "category":"Professional",
            "subcategory":"Lawyer & Legal Services",
            "type":"Services"
        }
    ],
    "sg:phone":"+1 916 649 2214",
    "sg:postcode":"95825",
    "sg:province":"CA",
    "sg:tags":[
        "personal",
        "injury"
    ],
    "sg:website":"www.sbhlawoffice.com",
    "wof:name":"Sacino Bertolino & Hallissy Law Offices",
    "wof:placetype":"venue"
},
  "geometry": {"coordinates":[-121.418654,38.567543],"type":"Point"}
}