{
  "type": "Feature",
  "properties": {
    "iso:country":"US",
    "sg:address":"2383 Lomita Blvd Unit 101",
    "sg:city":"Lomita",
    "sg:classifiers":[
        {
            "category":"Restaurant",
            "type":"Food & Drink"
        }
    ],
    "sg:phone":"+1 310 530 4661",
    "sg:postcode":"90717",
    "sg:province":"CA",
    "sg:tags":[
        "japanese"
    ],
    "sg:website":"oumisasaya.com",
    "wof:name":"Oumi Sasaya",
    "wof:placetype":"venue"
},
  "geometry": {"coordinates":[-118.324898,33.804517],"type":"Point"}
}