{
  "type": "Feature",
  "properties": {
    "addr:full":"1221 S Tegner Rd Turlock CA 95380",
    "addr:housenumber":"1221",
    "addr:postcode":"95380",
    "addr:street":"S Tegner Rd",
    "iso:country":"US",
    "sg:address":"1221 S Tegner Rd",
    "sg:city":"Turlock",
    "sg:classifiers":[
        {
            "category":"Wholesale",
            "subcategory":"Farm Supplies",
            "type":"Manufacturing & Wholesale Goods"
        },
        {
            "category":"Manufacturing",
            "subcategory":"Metals",
            "type":"Manufacturing & Wholesale Goods"
        },
        {
            "category":"Building & Trades",
            "subcategory":"Construction",
            "type":"Services"
        }
    ],
    "sg:phone":"+1 209 668 9378",
    "sg:postcode":"95380",
    "sg:province":"CA",
    "sg:tags":[
        "equipment",
        "crane",
        "tank",
        "dairy"
    ],
    "wof:name":"West Coast Equipment",
    "wof:placetype":"venue"
},
  "geometry": {"coordinates":[-120.885426,37.481127],"type":"Point"}
}