{
  "type": "Feature",
  "properties": {
    "iso:country":"US",
    "sg:address":"1196 Boulevard Way",
    "sg:city":"Walnut Creek",
    "sg:classifiers":[
        {
            "category":"Insurance",
            "subcategory":"Insurance Agent",
            "type":"Services"
        }
    ],
    "sg:phone":"+1 925 930 9464",
    "sg:postcode":"94595",
    "sg:province":"CA",
    "wof:name":"Stout Insurance Brokers Inc",
    "wof:placetype":"venue"
},
  "geometry": {"coordinates":[-122.07532,37.894123],"type":"Point"}
}