{
  "type": "Feature",
  "properties": {
    "addr:full":"50 California St San Francisco CA 94111",
    "addr:housenumber":"50",
    "addr:postcode":"94111",
    "addr:street":"California St",
    "iso:country":"US",
    "sg:address":"50 California St",
    "sg:city":"San Francisco",
    "sg:classifiers":[
        {
            "category":"Real Estate",
            "subcategory":"Architect",
            "type":"Services"
        }
    ],
    "sg:phone":"+1 415 394 1212",
    "sg:postcode":"94111",
    "sg:province":"CA",
    "sg:website":"www.huntsmanag.com",
    "wof:name":"Huntsman Architectural Group",
    "wof:placetype":"venue"
},
  "geometry": {"coordinates":[-122.397138,37.793661],"type":"Point"}
}