{
  "type": "Feature",
  "properties": {
    "iso:country":"US",
    "sg:address":"500 N State College Blvd Ste 1100",
    "sg:city":"Orange",
    "sg:classifiers":[
        {
            "category":"Professional",
            "subcategory":"Accounting & Tax Preparation",
            "type":"Services"
        }
    ],
    "sg:phone":"+1 714 634 2318",
    "sg:postcode":"92868",
    "sg:province":"CA",
    "sg:tags":[
        "accountant"
    ],
    "wof:name":"Kampa Consulting",
    "wof:placetype":"venue"
},
  "geometry": {"coordinates":[-117.889832,33.795708],"type":"Point"}
}