{
  "type": "Feature",
  "properties": {
    "iso:country":"US",
    "sg:address":"1225 Abbot Kinney Blvd",
    "sg:city":"Venice",
    "sg:classifiers":[
        {
            "category":"Professional",
            "type":"Services"
        }
    ],
    "sg:phone":"+1 310 399 0040",
    "sg:postcode":"90291",
    "sg:province":"CA",
    "sg:tags":[
        "establishment"
    ],
    "wof:name":"Pearce",
    "wof:placetype":"venue"
},
  "geometry": {"coordinates":[-118.468309,33.991311],"type":"Point"}
}