{
  "type": "Feature",
  "properties": {
    "addr:full":"19190 6th Ave Stevinson CA 95374",
    "addr:housenumber":"19190",
    "addr:postcode":"95374",
    "addr:street":"6Th Ave",
    "iso:country":"US",
    "sg:address":"19190 6th Ave",
    "sg:city":"Stevinson",
    "sg:classifiers":[
        {
            "category":"Farming",
            "subcategory":"Farm",
            "type":"Manufacturing & Wholesale Goods"
        }
    ],
    "sg:phone":"+1 559 585 1576",
    "sg:postcode":"95374",
    "sg:province":"CA",
    "wof:name":"Hansen Farms",
    "wof:placetype":"venue"
},
  "geometry": {"coordinates":[-120.839082,37.305888],"type":"Point"}
}