{
  "type": "Feature",
  "properties": {
    "iso:country":"US",
    "sg:address":"222 Trinity Lake Blvd",
    "sg:city":"Weaverville",
    "sg:classifiers":[
        {
            "category":"Education",
            "subcategory":"School",
            "type":"Public Place"
        }
    ],
    "sg:phone":"+1 530 623 5980",
    "sg:postcode":"96093",
    "sg:province":"CA",
    "sg:website":"www.shastaheadstart.org",
    "wof:name":"Shasta Headstart Weaverville",
    "wof:placetype":"venue"
},
  "geometry": {"coordinates":[-122.935413,40.733949],"type":"Point"}
}