{
  "type": "Feature",
  "properties": {
    "iso:country":"US",
    "sg:address":"1646 N Spring St",
    "sg:city":"Los Angeles",
    "sg:classifiers":[
        {
            "category":"Professional",
            "type":"Services"
        }
    ],
    "sg:phone":"+1 323 227 7100",
    "sg:postcode":"90012",
    "sg:province":"CA",
    "sg:tags":[
        "gift"
    ],
    "wof:name":"ATABOY Magnets",
    "wof:placetype":"venue"
},
  "geometry": {"coordinates":[-118.227599,34.069332],"type":"Point"}
}