{
  "type": "Feature",
  "properties": {
    "iso:country":"US",
    "sg:address":"4049 N el Dorado St",
    "sg:city":"Stockton",
    "sg:classifiers":[
        {
            "category":"Health Services",
            "subcategory":"Doctor",
            "type":"Services"
        }
    ],
    "sg:phone":"+1 209 946 0374",
    "sg:postcode":"95204",
    "sg:province":"CA",
    "sg:tags":[
        "dentist"
    ],
    "wof:name":"Jacqueline Lee DDS",
    "wof:placetype":"venue"
},
  "geometry": {"coordinates":[-121.30162,37.985445],"type":"Point"}
}