{
  "type": "Feature",
  "properties": {
    "iso:country":"US",
    "sg:address":"2613 E Ashlan Ave",
    "sg:city":"Fresno",
    "sg:classifiers":[
        {
            "category":"Shopping",
            "subcategory":"Florist",
            "type":"Retail Goods"
        }
    ],
    "sg:phone":"+1 559 224 7777",
    "sg:postcode":"93726",
    "sg:province":"CA",
    "wof:name":"Flowers & Balloons To Go",
    "wof:placetype":"venue"
},
  "geometry": {"coordinates":[-119.780252,36.794159],"type":"Point"}
}