{
  "type": "Feature",
  "properties": {
    "addr:full":"415 S Topanga Canyon Ste #130 Topanga CA 90290",
    "addr:housenumber":"415",
    "addr:postcode":"90290",
    "addr:street":"S Topanga;Ste # 130",
    "iso:country":"US",
    "sg:address":"415 S Topanga Canyon Ste #130",
    "sg:city":"Topanga",
    "sg:classifiers":[
        {
            "category":"Personal",
            "subcategory":"Massage",
            "type":"Services"
        }
    ],
    "sg:phone":"+1 310 806 0831",
    "sg:postcode":"90290",
    "sg:province":"CA",
    "sg:website":"www.themassageexpress.com/",
    "wof:name":"The Massage Express Co.",
    "wof:placetype":"venue"
},
  "geometry": {"coordinates":[-118.59936,34.083917],"type":"Point"}
}