{
  "type": "Feature",
  "properties": {
    "iso:country":"US",
    "sg:address":"5252 W Century Blvd",
    "sg:city":"Los Angeles",
    "sg:classifiers":[
        {
            "category":"Shopping",
            "subcategory":"Computers & Home Electronics",
            "type":"Retail Goods"
        }
    ],
    "sg:phone":"+1 310 649 1025",
    "sg:postcode":"90045",
    "sg:province":"CA",
    "sg:tags":[
        "equipment",
        "dealer"
    ],
    "wof:name":"Versadata Inc",
    "wof:placetype":"venue"
},
  "geometry": {"coordinates":[-118.370334,33.945345],"type":"Point"}
}