{
  "type": "Feature",
  "properties": {
    "iso:country":"US",
    "sg:address":"4325 N Golden State Blvd",
    "sg:city":"Fresno",
    "sg:classifiers":[
        {
            "category":"Professional",
            "subcategory":"Management & Consulting",
            "type":"Services"
        }
    ],
    "sg:phone":"+1 559 275 8095",
    "sg:postcode":"93722",
    "sg:province":"CA",
    "sg:tags":[
        "agricultural",
        "consultant"
    ],
    "wof:name":"California Agquest Consulting",
    "wof:placetype":"venue"
},
  "geometry": {"coordinates":[-119.867411,36.798647],"type":"Point"}
}