{
  "type": "Feature",
  "properties": {
    "addr:full":"3217 E Cesar E Chavez Ave Los Angeles CA 90063",
    "addr:housenumber":"3217",
    "addr:postcode":"90063",
    "addr:street":"E Cesar E Chavez Ave",
    "iso:country":"US",
    "sg:address":"3217 E Cesar E Chavez Ave",
    "sg:city":"Los Angeles",
    "sg:classifiers":[
        {
            "category":"Retail",
            "subcategory":"Auto Repair",
            "type":"Services"
        }
    ],
    "sg:phone":"+1 323 269 9851",
    "sg:postcode":"90063",
    "sg:province":"CA",
    "sg:tags":[
        "body",
        "shop"
    ],
    "wof:name":"Ray's Auto Paint & Body Shop Supplies",
    "wof:placetype":"venue"
},
  "geometry": {"coordinates":[-118.195999,34.041599],"type":"Point"}
}