{
  "type": "Feature",
  "properties": {
    "addr:full":"21521 San Gabriel Dr Tehachapi CA 93561",
    "addr:housenumber":"21521",
    "addr:postcode":"93561",
    "addr:street":"San Gabriel Dr",
    "iso:country":"US",
    "sg:address":"21521 San Gabriel Dr",
    "sg:city":"Tehachapi",
    "sg:classifiers":[
        {
            "category":"Building & Trades",
            "subcategory":"Plumbing",
            "type":"Services"
        }
    ],
    "sg:phone":"+1 661 822 3561",
    "sg:postcode":"93561",
    "sg:province":"CA",
    "sg:tags":[
        "conditioning",
        "air",
        "system",
        "contractor"
    ],
    "wof:name":"RNS Heating & Air Cond",
    "wof:placetype":"venue"
},
  "geometry": {"coordinates":[-118.484514,35.131468],"type":"Point"}
}