{
  "type": "Feature",
  "properties": {
    "addr:full":"786 E Foothill Blvd Rialto CA 92376",
    "addr:housenumber":"786",
    "addr:postcode":"92376",
    "addr:street":"E Foothill Blvd",
    "iso:country":"US",
    "sg:address":"786 E Foothill Blvd",
    "sg:city":"Rialto",
    "sg:classifiers":[
        {
            "category":"Health Services",
            "subcategory":"Doctor",
            "type":"Services"
        }
    ],
    "sg:phone":"+1 909 874 7870",
    "sg:postcode":"92376",
    "sg:province":"CA",
    "sg:tags":[
        "dentist"
    ],
    "wof:name":"Family Dentistry",
    "wof:placetype":"venue"
},
  "geometry": {"coordinates":[-117.354118,34.10687],"type":"Point"}
}