{
  "type": "Feature",
  "properties": {
    "addr:full":"906 Hillcroft Cir Oakland CA 94610",
    "addr:housenumber":"906",
    "addr:postcode":"94610",
    "addr:street":"Hillcroft Cir",
    "iso:country":"US",
    "sg:address":"906 Hillcroft Cir",
    "sg:city":"Oakland",
    "sg:classifiers":[
        {
            "category":"Health Services",
            "subcategory":"Medical Lab",
            "type":"Services"
        }
    ],
    "sg:phone":"+1 510 835 3441",
    "sg:postcode":"94610",
    "sg:province":"CA",
    "sg:tags":[
        "laboratory"
    ],
    "wof:name":"Royal Crown Dental Lab",
    "wof:placetype":"venue"
},
  "geometry": {"coordinates":[-122.23191300000001,37.808413],"type":"Point"}
}