{
  "type": "Feature",
  "properties": {
    "iso:country":"US",
    "sg:address":"4720 Lincoln Blvd",
    "sg:city":"Marina Del Rey",
    "sg:classifiers":[
        {
            "category":"Local Transit",
            "type":"Transportation"
        }
    ],
    "sg:phone":"+1 310 822 4845",
    "sg:postcode":"90292",
    "sg:province":"CA",
    "sg:tags":[
        "limousine"
    ],
    "wof:name":"Malibu Limousine Service",
    "wof:placetype":"venue"
},
  "geometry": {"coordinates":[-118.438527,33.980322],"type":"Point"}
}