{
  "type": "Feature",
  "properties": {
    "iso:country":"US",
    "sg:address":"6170 Cornerstone Ct",
    "sg:city":"San Diego",
    "sg:classifiers":[
        {
            "category":"Utilities",
            "subcategory":"Mobile Phone",
            "type":"Services"
        }
    ],
    "sg:phone":"+1 858 597 5351",
    "sg:postcode":"92121",
    "sg:province":"CA",
    "sg:tags":[
        "telephone",
        "cellular"
    ],
    "wof:name":"Cingular Wireless San Diego",
    "wof:placetype":"venue"
},
  "geometry": {"coordinates":[-117.188578,32.896729],"type":"Point"}
}