{
  "type": "Feature",
  "properties": {
    "iso:country":"US",
    "sg:address":"425 W Cypress St",
    "sg:city":"Glendale",
    "sg:classifiers":[
        {
            "category":"Manufacturing",
            "subcategory":"Printing",
            "type":"Manufacturing & Wholesale Goods"
        }
    ],
    "sg:phone":"+1 818 552 2531",
    "sg:postcode":"91204",
    "sg:province":"CA",
    "sg:tags":[
        "screen"
    ],
    "sg:website":"www.adinsportswear.com",
    "wof:name":"Adin Of California",
    "wof:placetype":"venue"
},
  "geometry": {"coordinates":[-118.261785,34.129337],"type":"Point"}
}