{
  "type": "Feature",
  "properties": {
    "iso:country":"US",
    "sg:address":"1027 del Norte Ave",
    "sg:city":"Menlo Park",
    "sg:classifiers":[
        {
            "category":"Professional",
            "subcategory":"Engineering",
            "type":"Services"
        }
    ],
    "sg:phone":"+1 650 321 6939",
    "sg:postcode":"94025",
    "sg:province":"CA",
    "sg:tags":[
        "engineer"
    ],
    "wof:name":"Fred Webster",
    "wof:placetype":"venue"
},
  "geometry": {"coordinates":[-122.168644,37.475479],"type":"Point"}
}