{
  "type": "Feature",
  "properties": {
    "iso:country":"US",
    "sg:address":"21632 Hanakai Ln",
    "sg:city":"Huntington Beach",
    "sg:classifiers":[
        {
            "category":"Real Estate",
            "subcategory":"Real Estate Operator",
            "type":"Services"
        }
    ],
    "sg:phone":"+1 714 962 9680",
    "sg:postcode":"92646",
    "sg:province":"CA",
    "sg:tags":[
        "building",
        "apartment"
    ],
    "wof:name":"Earl L Brashears",
    "wof:placetype":"venue"
},
  "geometry": {"coordinates":[-117.964108,33.649173],"type":"Point"}
}