{
  "type": "Feature",
  "properties": {
    "iso:country":"US",
    "sg:address":"909 Hyde St",
    "sg:city":"San Francisco",
    "sg:classifiers":[
        {
            "category":"Health Services",
            "subcategory":"Doctor",
            "type":"Services"
        }
    ],
    "sg:phone":"+1 415 771 4366",
    "sg:postcode":"94109",
    "sg:province":"CA",
    "sg:tags":[
        "medicine",
        "internal"
    ],
    "wof:name":"Sankaran Sujatha MD",
    "wof:placetype":"venue"
},
  "geometry": {"coordinates":[-122.41719500000001,37.789167],"type":"Point"}
}