{
  "type": "Feature",
  "properties": {
    "addr:full":"3878 6th St Riverside CA 92501",
    "addr:housenumber":"3878",
    "addr:postcode":"92501",
    "addr:street":"6Th St",
    "iso:country":"US",
    "sg:address":"3878 6th St",
    "sg:city":"Riverside",
    "sg:classifiers":[
        {
            "category":"Place Of Worship",
            "type":"Public Place"
        }
    ],
    "sg:phone":"+1 951 341 5055",
    "sg:postcode":"92501",
    "sg:province":"CA",
    "sg:tags":[
        "church"
    ],
    "wof:name":"Riverside City Mission",
    "wof:placetype":"venue"
},
  "geometry": {"coordinates":[-117.37531300000001,33.984927],"type":"Point"}
}