{
  "type": "Feature",
  "properties": {
    "addr:full":"245 S Humboldt St Willits CA 95490",
    "addr:housenumber":"245",
    "addr:postcode":"95490",
    "addr:street":"S Humboldt St",
    "iso:country":"US",
    "sg:address":"245 S Humboldt St",
    "sg:city":"Willits",
    "sg:classifiers":[
        {
            "category":"Social Services",
            "type":"Services"
        }
    ],
    "sg:phone":"+1 707 459 5673",
    "sg:postcode":"95490",
    "sg:province":"CA",
    "sg:tags":[
        "counselor",
        "marriage",
        "family"
    ],
    "wof:name":"Robin Goldner",
    "wof:placetype":"venue"
},
  "geometry": {"coordinates":[-123.35319800000001,39.410012],"type":"Point"}
}