{
  "type": "Feature",
  "properties": {
    "addr:full":"675 Gateway Center Dr San Diego CA 92102",
    "addr:housenumber":"675",
    "addr:postcode":"92102",
    "addr:street":"Gateway Center Dr",
    "iso:country":"US",
    "sg:address":"675 Gateway Center Dr",
    "sg:city":"San Diego",
    "sg:classifiers":[
        {
            "category":"Manufacturing",
            "subcategory":"Apparel",
            "type":"Manufacturing & Wholesale Goods"
        }
    ],
    "sg:phone":"+1 619 262 9202",
    "sg:postcode":"92102",
    "sg:province":"CA",
    "sg:tags":[
        "distribution",
        "hosiery"
    ],
    "wof:name":"High Knitting",
    "wof:placetype":"venue"
},
  "geometry": {"coordinates":[-117.114439,32.714422],"type":"Point"}
}