{
  "type": "Feature",
  "properties": {
    "iso:country":"US",
    "sg:address":"1080 Arcadia Ave",
    "sg:city":"Vista",
    "sg:classifiers":[
        {
            "category":"Personal",
            "subcategory":"Beauty Salon",
            "type":"Services"
        }
    ],
    "sg:phone":"+1 760 941 4202",
    "sg:postcode":"92084",
    "sg:province":"CA",
    "wof:name":"Elegant Lady Beauty Salon",
    "wof:placetype":"venue"
},
  "geometry": {"coordinates":[-117.228111,33.224992],"type":"Point"}
}