{
  "type": "Feature",
  "properties": {
    "iso:country":"US",
    "sg:address":"5301 E Centralia St",
    "sg:city":"Long Beach",
    "sg:classifiers":[
        {
            "category":"Education",
            "subcategory":"School",
            "type":"Public Place"
        }
    ],
    "sg:phone":"+1 562 425 7461",
    "sg:postcode":"90808",
    "sg:province":"CA",
    "sg:tags":[
        "high",
        "middle",
        "elementary"
    ],
    "sg:website":"www.lbusd.k12.ca.us",
    "wof:name":"Bancroft Hubert H Middle School",
    "wof:placetype":"venue"
},
  "geometry": {"coordinates":[-118.128998,33.839699],"type":"Point"}
}