{
  "type": "Feature",
  "properties": {
    "addr:full":"65 Jefferson St San Francisco CA 94133",
    "addr:housenumber":"65",
    "addr:postcode":"94133",
    "addr:street":"Jefferson St",
    "iso:country":"US",
    "sg:address":"65 Jefferson St",
    "sg:city":"San Francisco",
    "sg:classifiers":[
        {
            "category":"Manufacturing",
            "subcategory":"Food",
            "type":"Manufacturing & Wholesale Goods"
        }
    ],
    "sg:phone":"+1 415 314 1823",
    "sg:postcode":"94133",
    "sg:province":"CA",
    "sg:tags":[
        "mfg"
    ],
    "wof:name":"Rky Mtn Choc Factory",
    "wof:placetype":"venue"
},
  "geometry": {"coordinates":[-122.41330600000001,37.80848],"type":"Point"}
}