{
  "type": "Feature",
  "properties": {
    "addr:full":"1200 W Imperial Hwy La Habra CA 90631",
    "addr:housenumber":"1200",
    "addr:postcode":"90631",
    "addr:street":"W Imperial Hwy",
    "iso:country":"US",
    "sg:address":"1200 W Imperial Hwy",
    "sg:city":"La Habra",
    "sg:classifiers":[
        {
            "category":"Autos & Motor Vehicles",
            "subcategory":"Auto Supplies",
            "type":"Retail Goods"
        }
    ],
    "sg:phone":"+1 562 694 5337",
    "sg:postcode":"90631",
    "sg:province":"CA",
    "sg:tags":[
        "automobile",
        "parts"
    ],
    "wof:name":"Autozone",
    "wof:placetype":"venue"
},
  "geometry": {"coordinates":[-117.95994399999999,33.917246],"type":"Point"}
}