{
  "type": "Feature",
  "properties": {
    "iso:country":"US",
    "sg:address":"3005 E Palmdale Blvd",
    "sg:city":"Palmdale",
    "sg:classifiers":[
        {
            "category":"Wholesale",
            "subcategory":"Sporting Goods",
            "type":"Manufacturing & Wholesale Goods"
        }
    ],
    "sg:phone":"+1 661 265 0899",
    "sg:postcode":"93550",
    "sg:province":"CA",
    "sg:tags":[
        "equipment",
        "pool",
        "swimming"
    ],
    "wof:name":"Palmdale Pool Supply",
    "wof:placetype":"venue"
},
  "geometry": {"coordinates":[-118.076114,34.580293],"type":"Point"}
}