{
  "type": "Feature",
  "properties": {
    "addr:full":"15241 W Sunset Blvd Pacific Plsds CA 90272",
    "addr:housenumber":"15241",
    "addr:postcode":"90272",
    "addr:street":"W Sunset Blvd",
    "iso:country":"US",
    "sg:address":"15241 W Sunset Blvd",
    "sg:city":"Pacific Plsds",
    "sg:classifiers":[
        {
            "category":"Shopping",
            "subcategory":"Gifts & Souvenirs",
            "type":"Retail Goods"
        }
    ],
    "sg:phone":"+1 310 573 9777",
    "sg:postcode":"90272",
    "sg:province":"CA",
    "sg:tags":[
        "shop"
    ],
    "wof:name":"Nest Eggs",
    "wof:placetype":"venue"
},
  "geometry": {"coordinates":[-118.52445299999999,34.046263],"type":"Point"}
}