{
  "type": "Feature",
  "properties": {
    "iso:country":"US",
    "sg:address":"300 S Highland Springs Ave",
    "sg:city":"Banning",
    "sg:classifiers":[
        {
            "category":"Health Services",
            "subcategory":"Clinic",
            "type":"Services"
        }
    ],
    "sg:phone":"+1 951 769 5378",
    "sg:postcode":"92220",
    "sg:province":"CA",
    "sg:tags":[
        "welfare"
    ],
    "wof:name":"Epic Medical",
    "wof:placetype":"venue"
},
  "geometry": {"coordinates":[-116.94673899999999,33.923908],"type":"Point"}
}