{
  "type": "Feature",
  "properties": {
    "addr:full":"123 N Acacia Ave Fullerton CA 92831",
    "addr:housenumber":"123",
    "addr:postcode":"92831",
    "addr:street":"N Acacia Ave",
    "iso:country":"US",
    "sg:address":"123 N Acacia Ave",
    "sg:city":"Fullerton",
    "sg:classifiers":[
        {
            "category":"Wholesale",
            "subcategory":"Office Equipment",
            "type":"Manufacturing & Wholesale Goods"
        }
    ],
    "sg:phone":"+1 714 579 7969",
    "sg:postcode":"92831",
    "sg:province":"CA",
    "wof:name":"American Merchant Services",
    "wof:placetype":"venue"
},
  "geometry": {"coordinates":[-117.898365,33.870827],"type":"Point"}
}