{
  "type": "Feature",
  "properties": {
    "addr:full":"3250 W Olympic Boulevard Los Angeles CA 90006",
    "addr:housenumber":"3250",
    "addr:postcode":"90006",
    "addr:street":"W Olympic Boulevard",
    "iso:country":"US",
    "sg:address":"3250 W Olympic Boulevard",
    "sg:city":"Los Angeles",
    "sg:classifiers":[
        {
            "category":"Restaurant",
            "type":"Food & Drink"
        }
    ],
    "sg:phone":"+1 323 731 9770",
    "sg:postcode":"90006",
    "sg:province":"CA",
    "sg:tags":[
        "japanese"
    ],
    "wof:name":"Mikami Japanese Restaurant",
    "wof:placetype":"venue"
},
  "geometry": {"coordinates":[-118.30741399999999,34.052613],"type":"Point"}
}