{
  "type": "Feature",
  "properties": {
    "iso:country":"US",
    "sg:address":"2059 3rd St",
    "sg:city":"Livermore",
    "sg:classifiers":[
        {
            "category":"Health Services",
            "subcategory":"Clinic",
            "type":"Services"
        }
    ],
    "sg:phone":"+1 925 961 9016",
    "sg:postcode":"94550",
    "sg:province":"CA",
    "wof:name":"Internal Harmony",
    "wof:placetype":"venue"
},
  "geometry": {"coordinates":[-121.769992,37.679496],"type":"Point"}
}