{
  "type": "Feature",
  "properties": {
    "iso:country":"US",
    "sg:address":"20501 Ventura Blvd",
    "sg:city":"Woodland Hills",
    "sg:classifiers":[
        {
            "category":"Manufacturing",
            "subcategory":"Tools & Machinery",
            "type":"Manufacturing & Wholesale Goods"
        }
    ],
    "sg:phone":"+1 818 713 8997",
    "sg:postcode":"91364",
    "sg:province":"CA",
    "sg:tags":[
        "mfg"
    ],
    "wof:name":"Bye Bye Mold",
    "wof:placetype":"venue"
},
  "geometry": {"coordinates":[-118.580224,34.16792],"type":"Point"}
}