{
  "type": "Feature",
  "properties": {
    "addr:full":"928 Broadway Cir San Diego CA 92101",
    "addr:housenumber":"928",
    "addr:postcode":"92101",
    "addr:street":"Broadway Cir",
    "iso:country":"US",
    "sg:address":"928 Broadway Cir",
    "sg:city":"San Diego",
    "sg:classifiers":[
        {
            "category":"Social Services",
            "subcategory":"Adult Care",
            "type":"Services"
        }
    ],
    "sg:phone":"+1 619 235 6538",
    "sg:postcode":"92101",
    "sg:province":"CA",
    "sg:tags":[
        "organization",
        "senior",
        "citizen"
    ],
    "wof:name":"Senior Community Ctr-San Diego",
    "wof:placetype":"venue"
},
  "geometry": {"coordinates":[-117.162065,32.715418],"type":"Point"}
}