{
  "type": "Feature",
  "properties": {
    "addr:full":"3140 Alpine Rd Portola Valley CA 94028",
    "addr:housenumber":"3140",
    "addr:postcode":"94028",
    "addr:street":"Alpine Rd",
    "iso:country":"US",
    "sg:address":"3140 Alpine Rd",
    "sg:city":"Portola Valley",
    "sg:classifiers":[
        {
            "category":"Restaurant",
            "type":"Food & Drink"
        }
    ],
    "sg:phone":"+1 650 851 4254",
    "sg:postcode":"94028",
    "sg:province":"CA",
    "sg:tags":[
        "delicatessen"
    ],
    "wof:name":"Ladera Country Delicatessen",
    "wof:placetype":"venue"
},
  "geometry": {"coordinates":[-122.192672,37.402338],"type":"Point"}
}