{
  "type": "Feature",
  "properties": {
    "iso:country":"US",
    "sg:address":"8045 Vineyard Ave",
    "sg:city":"Rancho Cucamonga",
    "sg:classifiers":[
        {
            "category":"Health Services",
            "subcategory":"Chiropractor",
            "type":"Services"
        }
    ],
    "sg:phone":"+1 909 945 0515",
    "sg:postcode":"91730",
    "sg:province":"CA",
    "wof:name":"Sunrise Massage Ctr",
    "wof:placetype":"venue"
},
  "geometry": {"coordinates":[-117.610985,34.107713],"type":"Point"}
}