{
  "type": "Feature",
  "properties": {
    "iso:country":"US",
    "sg:address":"21350 Hawthorne Blvd",
    "sg:city":"Torrance",
    "sg:classifiers":[
        {
            "category":"Health Services",
            "subcategory":"Doctor",
            "type":"Services"
        }
    ],
    "sg:phone":"+1 310 543 1391",
    "sg:postcode":"90503",
    "sg:province":"CA",
    "wof:name":"Kageyama H Paul MD",
    "wof:placetype":"venue"
},
  "geometry": {"coordinates":[-118.35281,33.834461],"type":"Point"}
}