{
  "type": "Feature",
  "properties": {
    "addr:full":"4909 Auburn Blvd Sacramento CA 95841",
    "addr:housenumber":"4909",
    "addr:postcode":"95841",
    "addr:street":"Auburn Blvd",
    "iso:country":"US",
    "sg:address":"4909 Auburn Blvd",
    "sg:city":"Sacramento",
    "sg:classifiers":[
        {
            "category":"Shopping",
            "subcategory":"Department Store",
            "type":"Retail Goods"
        },
        {
            "category":"Shopping",
            "subcategory":"Discount & Variety Stores",
            "type":"Retail Goods"
        }
    ],
    "sg:phone":"+1 916 334 4412",
    "sg:postcode":"95841",
    "sg:province":"CA",
    "sg:website":"http://www.bargainw.com",
    "wof:name":"99 Cents Only Stores",
    "wof:placetype":"venue"
},
  "geometry": {"coordinates":[-121.35053499999999,38.657567],"type":"Point"}
}