{
  "type": "Feature",
  "properties": {
    "addr:full":"4656 Waterloo Rd Stockton CA 95215",
    "addr:housenumber":"4656",
    "addr:postcode":"95215",
    "addr:street":"Waterloo Rd",
    "iso:country":"US",
    "sg:address":"4656 Waterloo Rd",
    "sg:city":"Stockton",
    "sg:classifiers":[
        {
            "category":"Mining & Drilling",
            "type":"Manufacturing & Wholesale Goods"
        }
    ],
    "sg:phone":"+1 209 931 3331",
    "sg:postcode":"95215",
    "sg:province":"CA",
    "sg:tags":[
        "pipe",
        "inspection"
    ],
    "wof:name":"Pipeline Services",
    "wof:placetype":"venue"
},
  "geometry": {"coordinates":[-121.243611,37.988564],"type":"Point"}
}