{
  "type": "Feature",
  "properties": {
    "addr:full":"927 E Main St El Cajon CA 92021",
    "addr:housenumber":"927",
    "addr:postcode":"92021",
    "addr:street":"E Main St",
    "iso:country":"US",
    "sg:address":"927 E Main St",
    "sg:city":"El Cajon",
    "sg:classifiers":[
        {
            "category":"Travel",
            "subcategory":"Travel Agent",
            "type":"Entertainment"
        }
    ],
    "sg:phone":"+1 619 444 2141",
    "sg:postcode":"92021",
    "sg:province":"CA",
    "sg:tags":[
        "agency"
    ],
    "wof:name":"El Cajon Travel Inc",
    "wof:placetype":"venue"
},
  "geometry": {"coordinates":[-116.950022,32.794844],"type":"Point"}
}