{
  "type": "Feature",
  "properties": {
    "addr:full":"2033 Elwin Way Modesto CA 95350",
    "addr:housenumber":"2033",
    "addr:postcode":"ca 95350",
    "addr:street":"Elwin Way",
    "iso:country":"US",
    "sg:address":"2033 Elwin Way",
    "sg:city":"Modesto",
    "sg:classifiers":[
        {
            "category":"Organizations",
            "subcategory":"Professional Association",
            "type":"Services"
        }
    ],
    "sg:phone":"+1 209 529 9522",
    "sg:postcode":"95350",
    "sg:province":"CA",
    "wof:name":"National Rifle Assn",
    "wof:placetype":"venue"
},
  "geometry": {"coordinates":[-121.028299,37.686239],"type":"Point"}
}