{
  "type": "Feature",
  "properties": {
    "iso:country":"US",
    "sg:address":"331 Taraval St",
    "sg:city":"San Francisco",
    "sg:classifiers":[
        {
            "category":"Shopping",
            "subcategory":"Discount & Variety Stores",
            "type":"Retail Goods"
        }
    ],
    "sg:phone":"+1 415 681 7786",
    "sg:postcode":"94116",
    "sg:province":"CA",
    "sg:tags":[
        "merchandise",
        "general"
    ],
    "wof:name":"Kilgour Enterprises",
    "wof:placetype":"venue"
},
  "geometry": {"coordinates":[-122.469972,37.743229],"type":"Point"}
}