{
  "type": "Feature",
  "properties": {
    "iso:country":"US",
    "sg:address":"125 Bellam Blvd",
    "sg:city":"San Rafael",
    "sg:classifiers":[
        {
            "category":"Shopping",
            "subcategory":"Jewelry",
            "type":"Retail Goods"
        }
    ],
    "sg:phone":"+1 415 454 2939",
    "sg:postcode":"94901",
    "sg:province":"CA",
    "sg:tags":[
        "jeweler"
    ],
    "wof:name":"Reyes Jewelers",
    "wof:placetype":"venue"
},
  "geometry": {"coordinates":[-122.504328,37.960892],"type":"Point"}
}