{
  "type": "Feature",
  "properties": {
    "iso:country":"US",
    "sg:address":"3696 S Bristol St",
    "sg:city":"Santa Ana",
    "sg:classifiers":[
        {
            "category":"Cinema",
            "subcategory":"Movie Rental",
            "type":"Entertainment"
        },
        {
            "category":"Shopping",
            "subcategory":"Music",
            "type":"Retail Goods"
        },
        {
            "category":"Professional",
            "subcategory":"Computer Services",
            "type":"Services"
        }
    ],
    "sg:phone":"+1 714 549 0402",
    "sg:postcode":"92704",
    "sg:province":"CA",
    "sg:tags":[
        "repair",
        "game",
        "video",
        "dvd's"
    ],
    "wof:name":"DVD Zone",
    "wof:placetype":"venue"
},
  "geometry": {"coordinates":[-117.88560699999999,33.698146],"type":"Point"}
}