{
  "type": "Feature",
  "properties": {
    "addr:full":"263 Carpenteria Rd Aromas CA 95004",
    "addr:housenumber":"263",
    "addr:postcode":"ca 95004",
    "addr:street":"Carpenteria Rd",
    "iso:country":"US",
    "sg:address":"263 Carpenteria Rd",
    "sg:city":"Aromas",
    "sg:classifiers":[
        {
            "category":"Social Services",
            "subcategory":"Child Care",
            "type":"Services"
        }
    ],
    "sg:phone":"+1 831 726 2357",
    "sg:postcode":"95004",
    "sg:province":"CA",
    "sg:tags":[
        "kindergarten",
        "academic",
        "school"
    ],
    "wof:name":"ABC Preschool",
    "wof:placetype":"venue"
},
  "geometry": {"coordinates":[-121.643191,36.889374],"type":"Point"}
}