{
  "type": "Feature",
  "properties": {
    "addr:full":"25 N 14th Street Suite 860 San Jose CA 95112",
    "addr:housenumber":"25",
    "addr:postcode":"95112",
    "addr:street":"N 14Th Street Suite 860",
    "iso:country":"US",
    "sg:address":"25 N 14th Street Suite 860",
    "sg:city":"San Jose",
    "sg:classifiers":[
        {
            "category":"Health Services",
            "subcategory":"Dentist",
            "type":"Services"
        }
    ],
    "sg:phone":"+1 408 293 3215",
    "sg:postcode":"95112",
    "sg:province":"CA",
    "wof:name":"Huang Raymond S DMD",
    "wof:placetype":"venue"
},
  "geometry": {"coordinates":[-121.88101,37.340699],"type":"Point"}
}