{
  "type": "Feature",
  "properties": {
    "addr:full":"2438 Mccall Ave Selma CA 93662",
    "addr:housenumber":"2438",
    "addr:postcode":"93662",
    "addr:street":"Mccall Ave",
    "iso:country":"US",
    "sg:address":"2438 Mccall Ave",
    "sg:city":"Selma",
    "sg:classifiers":[
        {
            "category":"Restaurant",
            "type":"Food & Drink"
        }
    ],
    "sg:menulink":"http://www.allmenus.com/ca/selma/197729-kfc---kentucky-fried-chicken/menu/",
    "sg:phone":"+1 559 896 5871",
    "sg:postcode":"93662",
    "sg:province":"CA",
    "sg:tags":[
        "american",
        "chicken"
    ],
    "wof:name":"KFC - Kentucky Fried Chicken",
    "wof:placetype":"venue"
},
  "geometry": {"coordinates":[-119.610643,36.569451],"type":"Point"}
}