{
  "type": "Feature",
  "properties": {
    "iso:country":"US",
    "sg:address":"310 W Charter Way",
    "sg:city":"Stockton",
    "sg:classifiers":[
        {
            "category":"Food & Beverages",
            "subcategory":"Groceries & Convenience Stores",
            "type":"Retail Goods"
        }
    ],
    "sg:phone":"+1 209 465 2706",
    "sg:postcode":"95206",
    "sg:province":"CA",
    "sg:tags":[
        "grocer"
    ],
    "wof:name":"Centro-Mart Inc",
    "wof:placetype":"venue"
},
  "geometry": {"coordinates":[-121.292402,37.937675],"type":"Point"}
}