{
  "type": "Feature",
  "properties": {
    "iso:country":"US",
    "sg:address":"4754 Durfee Ave",
    "sg:city":"Pico Rivera",
    "sg:classifiers":[
        {
            "category":"Wholesale",
            "subcategory":"Non-durable Goods",
            "type":"Manufacturing & Wholesale Goods"
        }
    ],
    "sg:phone":"+1 562 695 2825",
    "sg:postcode":"90660",
    "sg:province":"CA",
    "wof:name":"Hedy Knits of California",
    "wof:placetype":"venue"
},
  "geometry": {"coordinates":[-118.078113,34.003262],"type":"Point"}
}