{
  "type": "Feature",
  "properties": {
    "iso:country":"US",
    "sg:address":"679 Rd 152",
    "sg:city":"Delano",
    "sg:classifiers":[
        {
            "category":"Freight",
            "type":"Transportation"
        }
    ],
    "sg:phone":"+1 661 725 3929",
    "sg:postcode":"93219",
    "sg:province":"CA",
    "wof:name":"J L Transportation",
    "wof:placetype":"venue"
},
  "geometry": {"coordinates":[-119.232513,35.798893],"type":"Point"}
}