{
  "type": "Feature",
  "properties": {
    "addr:full":"7865 Rush River Dr Sacramento CA 95831",
    "addr:housenumber":"7865",
    "addr:postcode":"95831",
    "addr:street":"Rush River Dr",
    "iso:country":"US",
    "sg:address":"7865 Rush River Dr",
    "sg:city":"Sacramento",
    "sg:classifiers":[
        {
            "category":"Utilities",
            "subcategory":"Telephone",
            "type":"Services"
        }
    ],
    "sg:phone":"+1 916 391 7750",
    "sg:postcode":"95831",
    "sg:province":"CA",
    "sg:tags":[
        "communications"
    ],
    "wof:name":"Triadnet",
    "wof:placetype":"venue"
},
  "geometry": {"coordinates":[-121.52213,38.483656],"type":"Point"}
}