{
  "type": "Feature",
  "properties": {
    "addr:full":"915 Fordham Dr Davis CA 95616",
    "addr:housenumber":"915",
    "addr:postcode":"95616",
    "addr:street":"Fordham Dr",
    "iso:country":"US",
    "sg:address":"915 Fordham Dr",
    "sg:city":"Davis",
    "sg:classifiers":[
        {
            "category":"Real Estate",
            "subcategory":"Real Estate Operator",
            "type":"Services"
        }
    ],
    "sg:phone":"+1 530 756 3457",
    "sg:postcode":"95616",
    "sg:province":"CA",
    "sg:tags":[
        "farm",
        "management",
        "property",
        "lessor"
    ],
    "wof:name":"Lott Enterprises",
    "wof:placetype":"venue"
},
  "geometry": {"coordinates":[-121.760554,38.557536],"type":"Point"}
}