{
  "type": "Feature",
  "properties": {
    "iso:country":"US",
    "sg:address":"14350 Bear Valley Rd",
    "sg:city":"Victorville",
    "sg:classifiers":[
        {
            "category":"Sports & Exercise",
            "subcategory":"Gym",
            "type":"Entertainment"
        }
    ],
    "sg:phone":"+1 760 955 8777",
    "sg:postcode":"92392",
    "sg:province":"CA",
    "sg:tags":[
        "club",
        "health",
        "studio",
        "gymnasium"
    ],
    "wof:name":"Ladies Workout Express",
    "wof:placetype":"venue"
},
  "geometry": {"coordinates":[-117.35636100000001,34.470373],"type":"Point"}
}