{
  "type": "Feature",
  "properties": {
    "addr:full":"3726 Laurel Canyon Blvd Studio City CA 91604",
    "addr:housenumber":"3726",
    "addr:postcode":"91604",
    "addr:street":"Laurel Canyon Blvd",
    "iso:country":"US",
    "sg:address":"3726 Laurel Canyon Blvd",
    "sg:city":"Studio City",
    "sg:classifiers":[
        {
            "category":"Arts & Performance",
            "subcategory":"Theater",
            "type":"Entertainment"
        }
    ],
    "sg:phone":"+1 818 766 8100",
    "sg:postcode":"91604",
    "sg:province":"CA",
    "sg:tags":[
        "bureau"
    ],
    "wof:name":"Hispanic Entertainment",
    "wof:placetype":"venue"
},
  "geometry": {"coordinates":[-118.39312200000001,34.137883],"type":"Point"}
}