{
  "type": "Feature",
  "properties": {
    "addr:full":"719 W Roseburg Ave Modesto CA 95350",
    "addr:housenumber":"719",
    "addr:postcode":"ca 95350",
    "addr:street":"W Roseburg Ave",
    "iso:country":"US",
    "sg:address":"719 W Roseburg Ave",
    "sg:city":"Modesto",
    "sg:classifiers":[
        {
            "category":"Professional",
            "subcategory":"Art Services",
            "type":"Services"
        }
    ],
    "sg:phone":"+1 209 521 8146",
    "sg:postcode":"95350",
    "sg:province":"CA",
    "sg:tags":[
        "photographer"
    ],
    "wof:name":"W C Wood Photography",
    "wof:placetype":"venue"
},
  "geometry": {"coordinates":[-121.002736,37.660286],"type":"Point"}
}