{
  "type": "Feature",
  "properties": {
    "iso:country":"US",
    "sg:address":"2715 W Coast Hwy",
    "sg:city":"Newport Beach",
    "sg:classifiers":[
        {
            "category":"Banks & Credit Unions",
            "subcategory":"Investment Brokerage",
            "type":"Services"
        }
    ],
    "sg:phone":"+1 949 631 8599",
    "sg:postcode":"92663",
    "sg:province":"CA",
    "sg:tags":[
        "investing",
        "advisory"
    ],
    "wof:name":"Westerly Investments Inc",
    "wof:placetype":"venue"
},
  "geometry": {"coordinates":[-117.924004,33.619999],"type":"Point"}
}