{
  "type": "Feature",
  "properties": {
    "iso:country":"US",
    "sg:address":"4785 Blue Mountain Dr",
    "sg:city":"Yorba Linda",
    "sg:classifiers":[
        {
            "category":"Wholesale",
            "subcategory":"Seafood",
            "type":"Manufacturing & Wholesale Goods"
        }
    ],
    "sg:phone":"+1 714 693 2549",
    "sg:postcode":"92887",
    "sg:province":"CA",
    "wof:name":"Three Star Smoked Fish Co",
    "wof:placetype":"venue"
},
  "geometry": {"coordinates":[-117.75715700000001,33.892376],"type":"Point"}
}