{
  "type": "Feature",
  "properties": {
    "addr:full":"1404 W 11th St Alturas CA 96101",
    "addr:housenumber":"1404",
    "addr:postcode":"96101",
    "addr:street":"W 11Th St",
    "iso:country":"US",
    "sg:address":"1404 W 11th St",
    "sg:city":"Alturas",
    "sg:classifiers":[
        {
            "category":"Building & Trades",
            "subcategory":"Pest Control",
            "type":"Services"
        }
    ],
    "sg:phone":"+1 530 233 2016",
    "sg:postcode":"96101",
    "sg:province":"CA",
    "wof:name":"Porter Go Forth April",
    "wof:placetype":"venue"
},
  "geometry": {"coordinates":[-120.562561,41.493821],"type":"Point"}
}