{
  "type": "Feature",
  "properties": {
    "addr:full":"200 State Rte 12 Valley Springs CA 95252",
    "addr:housenumber":"200",
    "addr:postcode":"95252",
    "addr:street":"State Rte 12",
    "iso:country":"US",
    "sg:address":"200 State Rte 12",
    "sg:city":"Valley Springs",
    "sg:classifiers":[
        {
            "category":"Personal",
            "type":"Services"
        }
    ],
    "sg:phone":"+1 209 772 8690",
    "sg:postcode":"95252",
    "sg:province":"CA",
    "sg:tags":[
        "florist"
    ],
    "wof:name":"Floral Expressions",
    "wof:placetype":"venue"
},
  "geometry": {"coordinates":[-120.822181,38.19329],"type":"Point"}
}