{
  "type": "Feature",
  "properties": {
    "iso:country":"US",
    "sg:address":"894 Julian St",
    "sg:city":"Turlock",
    "sg:classifiers":[
        {
            "category":"Building & Trades",
            "subcategory":"Landscaping Services",
            "type":"Services"
        }
    ],
    "sg:phone":"+1 209 667 9118",
    "sg:postcode":"95380",
    "sg:province":"CA",
    "wof:name":"Ayalas Lawn & Gardening",
    "wof:placetype":"venue"
},
  "geometry": {"coordinates":[-120.858659,37.497761],"type":"Point"}
}