{
  "type": "Feature",
  "properties": {
    "addr:full":"2215 Twin Hills Dr Santa Cruz CA 95065",
    "addr:housenumber":"2215",
    "addr:postcode":"95065",
    "addr:street":"Twin Hills Dr",
    "iso:country":"US",
    "sg:address":"2215 Twin Hills Dr",
    "sg:city":"Santa Cruz",
    "sg:classifiers":[
        {
            "category":"Professional",
            "type":"Services"
        }
    ],
    "sg:phone":"+1 831 724 2553",
    "sg:postcode":"95065",
    "sg:province":"CA",
    "wof:name":"Astro Electronics Tech",
    "wof:placetype":"venue"
},
  "geometry": {"coordinates":[-121.976983,36.992353],"type":"Point"}
}