{
  "type": "Feature",
  "properties": {
    "addr:full":"1305 S San Gabriel Blvd San Gabriel CA 91776",
    "addr:housenumber":"1305",
    "addr:postcode":"91776",
    "addr:street":"S San Gabriel Blvd",
    "iso:country":"US",
    "sg:address":"1305 S San Gabriel Blvd",
    "sg:city":"San Gabriel",
    "sg:classifiers":[
        {
            "category":"Building & Trades",
            "subcategory":"Pest Control",
            "type":"Services"
        }
    ],
    "sg:phone":"+1 310 860 8983",
    "sg:postcode":"91776",
    "sg:province":"CA",
    "sg:website":"www.advancepestcontrol.com",
    "wof:name":"Advance Pest Control",
    "wof:placetype":"venue"
},
  "geometry": {"coordinates":[-118.09082600000001,34.082898],"type":"Point"}
}