{
  "type": "Feature",
  "properties": {
    "iso:country":"US",
    "sg:address":"23975 Park Sorrento Ste 120",
    "sg:city":"Calabasas",
    "sg:classifiers":[
        {
            "category":"Personal",
            "subcategory":"Massage",
            "type":"Services"
        },
        {
            "category":"Personal",
            "subcategory":"Day Spa",
            "type":"Services"
        }
    ],
    "sg:phone":"+1 818 591 0046",
    "sg:postcode":"91302",
    "sg:province":"CA",
    "sg:website":"www.ZenSpa.Biz",
    "wof:name":"ZenSpa",
    "wof:placetype":"venue"
},
  "geometry": {"coordinates":[-118.64852399999999,34.152372],"type":"Point"}
}