{
  "type": "Feature",
  "properties": {
    "addr:full":"3108 5th Avenue Suite B San Diego CA 92103",
    "addr:housenumber":"3108",
    "addr:postcode":"92103",
    "addr:street":"5Th Avenue Suite B",
    "iso:country":"US",
    "sg:address":"3108 5th Avenue Suite B",
    "sg:city":"San Diego",
    "sg:classifiers":[
        {
            "category":"Organizations",
            "subcategory":"Non-profit Organization",
            "type":"Services"
        }
    ],
    "sg:phone":"+1 619 298 2541",
    "sg:postcode":"92103",
    "sg:province":"CA",
    "sg:tags":[
        "service/non-profit",
        "community"
    ],
    "sg:website":"www.uptownpartnership.org",
    "wof:name":"Uptown Partnership",
    "wof:placetype":"venue"
},
  "geometry": {"coordinates":[-117.160635,32.738001],"type":"Point"}
}