{
  "type": "Feature",
  "properties": {
    "iso:country":"US",
    "sg:address":"19925 Stevens Creek Blvd",
    "sg:city":"Cupertino",
    "sg:classifiers":[
        {
            "category":"Professional",
            "subcategory":"Employment Agencies",
            "type":"Services"
        }
    ],
    "sg:phone":"+1 408 973 7299",
    "sg:postcode":"95014",
    "sg:province":"CA",
    "sg:website":"www.omnixl.com",
    "wof:name":"Omnixl",
    "wof:placetype":"venue"
},
  "geometry": {"coordinates":[-122.02157,37.32364],"type":"Point"}
}