{
  "type": "Feature",
  "properties": {
    "addr:full":"12752 Garden Grove Blvd Garden Grove CA 92843",
    "addr:housenumber":"12752",
    "addr:postcode":"92843",
    "addr:street":"Garden Grove Blvd",
    "iso:country":"US",
    "sg:address":"12752 Garden Grove Blvd",
    "sg:city":"Garden Grove",
    "sg:classifiers":[
        {
            "category":"Education",
            "subcategory":"Special Training",
            "type":"Public Place"
        }
    ],
    "sg:phone":"+1 714 534 0085",
    "sg:postcode":"92843",
    "sg:province":"CA",
    "sg:tags":[
        "adult"
    ],
    "sg:website":"www.vetassistant.com/",
    "wof:name":"Professional Veterinary Assistant School",
    "wof:placetype":"venue"
},
  "geometry": {"coordinates":[-117.910004,33.7743],"type":"Point"}
}