{
  "type": "Feature",
  "properties": {
    "addr:full":"2536 S Imperial Pl Ontario CA 91761",
    "addr:housenumber":"2536",
    "addr:postcode":"91761",
    "addr:street":"S Imperial Pl",
    "iso:country":"US",
    "sg:address":"2536 S Imperial Pl",
    "sg:city":"Ontario",
    "sg:classifiers":[
        {
            "category":"Wholesale",
            "subcategory":"Auto Parts",
            "type":"Manufacturing & Wholesale Goods"
        }
    ],
    "sg:phone":"+1 909 489 6007",
    "sg:postcode":"91761",
    "sg:province":"CA",
    "wof:name":"Snap-On Tools",
    "wof:placetype":"venue"
},
  "geometry": {"coordinates":[-117.62239,34.027708],"type":"Point"}
}