{
  "type": "Feature",
  "properties": {
    "iso:country":"US",
    "sg:address":"2082 E Canal Dr",
    "sg:city":"Turlock",
    "sg:classifiers":[
        {
            "category":"Shopping",
            "subcategory":"Clothing, Apparel, & Fashions",
            "type":"Retail Goods"
        }
    ],
    "sg:phone":"+1 209 668 8816",
    "sg:postcode":"95380",
    "sg:province":"CA",
    "sg:tags":[
        "shop",
        "bridal"
    ],
    "wof:name":"Adore Bridal",
    "wof:placetype":"venue"
},
  "geometry": {"coordinates":[-120.824489,37.500048],"type":"Point"}
}