{
  "type": "Feature",
  "properties": {
    "iso:country":"US",
    "sg:address":"1289 Furneaux Rd",
    "sg:city":"Marysville",
    "sg:classifiers":[
        {
            "category":"Freight",
            "type":"Transportation"
        }
    ],
    "sg:phone":"+1 530 742 6974",
    "sg:postcode":"95961",
    "sg:province":"CA",
    "sg:tags":[
        "mobile",
        "home"
    ],
    "wof:name":"Ernie's Mobile Home Transport",
    "wof:placetype":"venue"
},
  "geometry": {"coordinates":[-121.561128,39.107219],"type":"Point"}
}