{
  "type": "Feature",
  "properties": {
    "addr:full":"6080 Center Dr Los Angeles CA 90045",
    "addr:housenumber":"6080",
    "addr:postcode":"90045",
    "addr:street":"Center Dr",
    "iso:country":"US",
    "sg:address":"6080 Center Dr",
    "sg:city":"Los Angeles",
    "sg:classifiers":[
        {
            "category":"Banks & Credit Unions",
            "subcategory":"Investment Brokerage",
            "type":"Services"
        }
    ],
    "sg:phone":"+1 310 242 6756",
    "sg:postcode":"90045",
    "sg:province":"CA",
    "sg:tags":[
        "advisory",
        "financial"
    ],
    "wof:name":"Roberts Persley & Morris Fnncl",
    "wof:placetype":"venue"
},
  "geometry": {"coordinates":[-118.392377,33.977761],"type":"Point"}
}