{
  "type": "Feature",
  "properties": {
    "addr:full":"1456 State St Alviso CA 95002",
    "addr:housenumber":"1456",
    "addr:postcode":"95002",
    "addr:street":"State St",
    "iso:country":"US",
    "sg:address":"1456 State St",
    "sg:city":"Alviso",
    "sg:classifiers":[
        {
            "category":"Building & Trades",
            "subcategory":"Landscaping Services",
            "type":"Services"
        }
    ],
    "sg:phone":"+1 650 961 7700",
    "sg:postcode":"95002",
    "sg:province":"CA",
    "sg:tags":[
        "architect",
        "landscape"
    ],
    "sg:website":"www.wemcolandscapes.com",
    "wof:name":"Wemco Landscapes",
    "wof:placetype":"venue"
},
  "geometry": {"coordinates":[-121.972905,37.432059],"type":"Point"}
}