{
  "type": "Feature",
  "properties": {
    "iso:country":"US",
    "sg:address":"21550 Burbank Blvd",
    "sg:city":"Woodland Hills",
    "sg:classifiers":[
        {
            "category":"Banks & Credit Unions",
            "subcategory":"Financial Services",
            "type":"Services"
        }
    ],
    "sg:phone":"+1 818 710 8008",
    "sg:postcode":"91367",
    "sg:province":"CA",
    "sg:tags":[
        "broker",
        "mortgage"
    ],
    "wof:name":"Papillon Mortgage",
    "wof:placetype":"venue"
},
  "geometry": {"coordinates":[-118.59965699999999,34.173147],"type":"Point"}
}