{
  "type": "Feature",
  "properties": {
    "iso:country":"US",
    "sg:address":"301 Figueroa St",
    "sg:city":"Wilmington",
    "sg:classifiers":[
        {
            "category":"Manufacturing",
            "subcategory":"Metals",
            "type":"Manufacturing & Wholesale Goods"
        }
    ],
    "sg:phone":"+1 310 518 1410",
    "sg:postcode":"90744",
    "sg:province":"CA",
    "sg:tags":[
        "product",
        "wire",
        "fabricated"
    ],
    "sg:website":"www.sunpros.com",
    "wof:name":"Sunshine Products",
    "wof:placetype":"venue"
},
  "geometry": {"coordinates":[-118.278607,33.771898],"type":"Point"}
}