{
  "type": "Feature",
  "properties": {
    "iso:country":"US",
    "sg:address":"1354 Margo St",
    "sg:city":"Los Angeles",
    "sg:classifiers":[
        {
            "category":"Wholesale",
            "subcategory":"Non-durable Goods",
            "type":"Manufacturing & Wholesale Goods"
        },
        {
            "category":"Wholesale",
            "subcategory":"Durable Goods & Equipment",
            "type":"Manufacturing & Wholesale Goods"
        }
    ],
    "sg:phone":"+1 213 746 8088",
    "sg:postcode":"90015",
    "sg:province":"CA",
    "sg:tags":[
        "importer"
    ],
    "wof:name":"Sam's Trade Development Corp",
    "wof:placetype":"venue"
},
  "geometry": {"coordinates":[-118.264425,34.037846],"type":"Point"}
}