{
  "type": "Feature",
  "properties": {
    "addr:full":"2750 Kurtz St San Diego CA 92110",
    "addr:housenumber":"2750",
    "addr:postcode":"92110",
    "addr:street":"Kurtz St",
    "iso:country":"US",
    "sg:address":"2750 Kurtz St",
    "sg:city":"San Diego",
    "sg:classifiers":[
        {
            "category":"Freight",
            "type":"Transportation"
        }
    ],
    "sg:phone":"+1 619 990 8770",
    "sg:postcode":"92110",
    "sg:province":"CA",
    "wof:name":"Public Shuttle of San Diego",
    "wof:placetype":"venue"
},
  "geometry": {"coordinates":[-117.20385400000001,32.752293],"type":"Point"}
}