{
  "type": "Feature",
  "properties": {
    "iso:country":"US",
    "sg:address":"4700 Woodbridge Way",
    "sg:city":"Antioch",
    "sg:classifiers":[
        {
            "category":"Professional",
            "type":"Services"
        }
    ],
    "sg:phone":"+1 925 756 1244",
    "sg:postcode":"94531",
    "sg:province":"CA",
    "wof:name":"Jbm International",
    "wof:placetype":"venue"
},
  "geometry": {"coordinates":[-121.757685,37.969159],"type":"Point"}
}