{
  "type": "Feature",
  "properties": {
    "addr:full":"163 W Cascade Dr Rialto CA 92376",
    "addr:housenumber":"163",
    "addr:postcode":"92376",
    "addr:street":"W Cascade Dr",
    "iso:country":"US",
    "sg:address":"163 W Cascade Dr",
    "sg:city":"Rialto",
    "sg:classifiers":[
        {
            "category":"Home & Garden",
            "subcategory":"Carpets & Floor Coverings",
            "type":"Retail Goods"
        }
    ],
    "sg:phone":"+1 909 873 2984",
    "sg:postcode":"92376",
    "sg:province":"CA",
    "sg:tags":[
        "rug"
    ],
    "wof:name":"Art Carpet Service",
    "wof:placetype":"venue"
},
  "geometry": {"coordinates":[-117.371465,34.126374],"type":"Point"}
}