{
  "type": "Feature",
  "properties": {
    "addr:full":"15 Daffodil Ln San Carlos CA 94070",
    "addr:housenumber":"15",
    "addr:postcode":"94070",
    "addr:street":"Daffodil Ln",
    "iso:country":"US",
    "sg:address":"15 Daffodil Ln",
    "sg:city":"San Carlos",
    "sg:classifiers":[
        {
            "category":"Professional",
            "subcategory":"Business Services",
            "type":"Services"
        }
    ],
    "sg:phone":"+1 650 591 1151",
    "sg:postcode":"94070",
    "sg:province":"CA",
    "sg:tags":[
        "appraiser"
    ],
    "wof:name":"Allied Appraisers",
    "wof:placetype":"venue"
},
  "geometry": {"coordinates":[-122.293598,37.49289],"type":"Point"}
}