{
  "type": "Feature",
  "properties": {
    "addr:full":"2331 San Miguel Canyon Rd Salinas CA 93907",
    "addr:housenumber":"2331",
    "addr:postcode":"93907",
    "addr:street":"San Miguel Canyon Rd",
    "iso:country":"US",
    "sg:address":"2331 San Miguel Canyon Rd",
    "sg:city":"Salinas",
    "sg:classifiers":[
        {
            "category":"Shopping",
            "type":"Retail Goods"
        },
        {
            "category":"Food & Beverages",
            "subcategory":"Groceries & Convenience Stores",
            "type":"Retail Goods"
        }
    ],
    "sg:phone":"+1 831 663 2331",
    "sg:postcode":"93907",
    "sg:province":"CA",
    "sg:tags":[
        "merchandise"
    ],
    "wof:name":"Glenn's General Store",
    "wof:placetype":"venue"
},
  "geometry": {"coordinates":[-121.666815,36.802803],"type":"Point"}
}