{
  "type": "Feature",
  "properties": {
    "addr:full":"580 Ahwanee Avenue Ofc Sunnyvale CA 94085",
    "addr:housenumber":"580",
    "addr:postcode":"94085",
    "addr:street":"Ahwanee Avenue",
    "iso:country":"US",
    "sg:address":"580 Ahwanee Avenue Ofc",
    "sg:city":"Sunnyvale",
    "sg:classifiers":[
        {
            "category":"Building & Trades",
            "subcategory":"Cleaning & Sanitation",
            "type":"Services"
        }
    ],
    "sg:phone":"+1 408 530 9161",
    "sg:postcode":"94085",
    "sg:province":"CA",
    "sg:tags":[
        "home"
    ],
    "wof:name":"Eddie's House Cleaning",
    "wof:placetype":"venue"
},
  "geometry": {"coordinates":[-122.013909,37.394588],"type":"Point"}
}