{
  "type": "Feature",
  "properties": {
    "addr:full":"18633 Pioneer Blvd Artesia CA 90701",
    "addr:housenumber":"18633",
    "addr:postcode":"90701",
    "addr:street":"Pioneer Blvd",
    "iso:country":"US",
    "sg:address":"18633 Pioneer Blvd",
    "sg:city":"Artesia",
    "sg:classifiers":[
        {
            "category":"Wholesale",
            "subcategory":"Books, Periodicals, & Newspapers",
            "type":"Manufacturing & Wholesale Goods"
        },
        {
            "category":"Recreation",
            "type":"Entertainment"
        }
    ],
    "sg:phone":"+1 562 865 5292",
    "sg:postcode":"90701",
    "sg:province":"CA",
    "sg:tags":[
        "henna",
        "tobacco",
        "amusement"
    ],
    "wof:name":"India Entertainment Center",
    "wof:placetype":"venue"
},
  "geometry": {"coordinates":[-118.08221500000001,33.861839],"type":"Point"}
}