{
  "type": "Feature",
  "properties": {
    "iso:country":"US",
    "sg:address":"2600 Greenmeadow Rd",
    "sg:city":"Lakewood",
    "sg:classifiers":[
        {
            "category":"Government",
            "subcategory":"Fire Station",
            "type":"Public Place"
        }
    ],
    "sg:phone":"+1 562 421 7713",
    "sg:postcode":"90712",
    "sg:province":"CA",
    "sg:tags":[
        "department"
    ],
    "wof:name":"Lakewood Fire Dept",
    "wof:placetype":"venue"
},
  "geometry": {"coordinates":[-118.16014699999999,33.833934],"type":"Point"}
}