{
  "type": "Feature",
  "properties": {
    "addr:full":"3454 E Anaheim St Long Beach CA 90804",
    "addr:housenumber":"3454",
    "addr:postcode":"90804",
    "addr:street":"E Anaheim St",
    "iso:country":"US",
    "sg:address":"3454 E Anaheim St",
    "sg:city":"Long Beach",
    "sg:classifiers":[
        {
            "category":"Professional",
            "subcategory":"Lawyer & Legal Services",
            "type":"Services"
        }
    ],
    "sg:phone":"+1 562 494 1010",
    "sg:postcode":"90804",
    "sg:province":"CA",
    "sg:website":"www.janispetersonlord.com",
    "wof:name":"The Law Office of Janis Peterson-Lord",
    "wof:placetype":"venue"
},
  "geometry": {"coordinates":[-118.15173900000001,33.782601],"type":"Point"}
}