{
  "type": "Feature",
  "properties": {
    "addr:full":"313 Dawson Dr Camarillo CA 93012",
    "addr:housenumber":"313",
    "addr:postcode":"93012",
    "addr:street":"Dawson Dr",
    "iso:country":"US",
    "sg:address":"313 Dawson Dr",
    "sg:city":"Camarillo",
    "sg:classifiers":[
        {
            "category":"Building & Trades",
            "subcategory":"Cleaning & Sanitation",
            "type":"Services"
        }
    ],
    "sg:phone":"+1 805 389 1974",
    "sg:postcode":"93012",
    "sg:province":"CA",
    "sg:tags":[
        "janitor"
    ],
    "wof:name":"Global Building Maintenance",
    "wof:placetype":"venue"
},
  "geometry": {"coordinates":[-119.036444,34.212595],"type":"Point"}
}