{
  "type": "Feature",
  "properties": {
    "iso:country":"US",
    "sg:address":"13754 Erwin St",
    "sg:city":"Van Nuys",
    "sg:classifiers":[
        {
            "category":"Professional",
            "subcategory":"Business Services",
            "type":"Services"
        }
    ],
    "sg:phone":"+1 818 501 5264",
    "sg:postcode":"91401",
    "sg:province":"CA",
    "sg:tags":[
        "interior",
        "consultant",
        "design",
        "decorator"
    ],
    "wof:name":"Mia Bella Design",
    "wof:placetype":"venue"
},
  "geometry": {"coordinates":[-118.433263,34.182964],"type":"Point"}
}