{
  "type": "Feature",
  "properties": {
    "iso:country":"US",
    "sg:address":"9916 Bolsa Ave",
    "sg:city":"Westminster",
    "sg:classifiers":[
        {
            "category":"Manufacturing",
            "subcategory":"Printing",
            "type":"Manufacturing & Wholesale Goods"
        }
    ],
    "sg:phone":"+1 714 839 2680",
    "sg:postcode":"92683",
    "sg:province":"CA",
    "sg:tags":[
        "lithographic",
        "industrial",
        "commercial"
    ],
    "wof:name":"Franks Printing",
    "wof:placetype":"venue"
},
  "geometry": {"coordinates":[-117.955206,33.744858],"type":"Point"}
}