{
  "type": "Feature",
  "properties": {
    "addr:full":"100 E Mineral King Ave Visalia CA 93291",
    "addr:housenumber":"100",
    "addr:postcode":"93291",
    "addr:street":"E Mineral King Ave",
    "iso:country":"US",
    "sg:address":"100 E Mineral King Ave",
    "sg:city":"Visalia",
    "sg:classifiers":[
        {
            "category":"Autos & Motor Vehicles",
            "subcategory":"Fuel & Gas Station",
            "type":"Retail Goods"
        }
    ],
    "sg:phone":"+1 559 733 9474",
    "sg:postcode":"93291",
    "sg:province":"CA",
    "wof:name":"Lenny Tailors Station",
    "wof:placetype":"venue"
},
  "geometry": {"coordinates":[-119.29231299999999,36.327438],"type":"Point"}
}