{
  "type": "Feature",
  "properties": {
    "iso:country":"US",
    "sg:address":"928 W El Camino Real",
    "sg:city":"Sunnyvale",
    "sg:classifiers":[
        {
            "category":"Retail",
            "subcategory":"Auto Repair",
            "type":"Services"
        }
    ],
    "sg:phone":"+1 650 494 8272",
    "sg:postcode":"94087",
    "sg:province":"CA",
    "wof:name":"George's Auto Repair Service",
    "wof:placetype":"venue"
},
  "geometry": {"coordinates":[-122.046997,37.371601],"type":"Point"}
}