{
  "type": "Feature",
  "properties": {
    "addr:full":"537 Abbott St Salinas CA 93901",
    "addr:housenumber":"537",
    "addr:postcode":"93901",
    "addr:street":"Abbott St",
    "iso:country":"US",
    "sg:address":"537 Abbott St",
    "sg:city":"Salinas",
    "sg:classifiers":[
        {
            "category":"Retail",
            "subcategory":"Car Wash",
            "type":"Services"
        }
    ],
    "sg:phone":"+1 831 422 3332",
    "sg:postcode":"93901",
    "sg:province":"CA",
    "sg:tags":[
        "polishing",
        "washing"
    ],
    "wof:name":"Acme Car Wash",
    "wof:placetype":"venue"
},
  "geometry": {"coordinates":[-121.642163,36.663299],"type":"Point"}
}