{
  "type": "Feature",
  "properties": {
    "addr:full":"Ingomar St & Valley Circle Blvd Los Angeles CA 91304",
    "addr:postcode":"91304",
    "addr:street":"Ingomar St & Valley Circle Blvd",
    "iso:country":"US",
    "sg:address":"Ingomar St & Valley Circle Blvd",
    "sg:city":"Los Angeles",
    "sg:classifiers":[
        {
            "category":"Park",
            "type":"Public Place"
        }
    ],
    "sg:phone":"+1 818 883 3637",
    "sg:postcode":"91304",
    "sg:province":"CA",
    "wof:name":"Lazy J Ranch Park",
    "wof:placetype":"venue"
},
  "geometry": {"coordinates":[-118.64651000000001,34.211781],"type":"Point"}
}