{
  "type": "Feature",
  "properties": {
    "iso:country":"US",
    "sg:address":"25011 Cll Arenal",
    "sg:city":"Lake Forest",
    "sg:classifiers":[
        {
            "category":"Insurance",
            "subcategory":"Life Insurance",
            "type":"Services"
        }
    ],
    "sg:phone":"+1 949 456 9509",
    "sg:postcode":"92630",
    "sg:province":"CA",
    "sg:tags":[
        "marketing",
        "company"
    ],
    "wof:name":"Mbp Insurance Services Inc",
    "wof:placetype":"venue"
},
  "geometry": {"coordinates":[-117.693603,33.655095],"type":"Point"}
}