{
  "type": "Feature",
  "properties": {
    "addr:full":"111 Palm Street Newport Beach CA 92661",
    "addr:housenumber":"111",
    "addr:postcode":"92661",
    "addr:street":"Palm Street",
    "iso:country":"US",
    "sg:address":"111 Palm Street",
    "sg:city":"Newport Beach",
    "sg:classifiers":[
        {
            "category":"Arts & Performance",
            "subcategory":"Art Gallery",
            "type":"Entertainment"
        }
    ],
    "sg:phone":"+1 949 723 2906",
    "sg:postcode":"92661",
    "sg:province":"CA",
    "sg:website":"www.tylerco.net",
    "wof:name":"Tylerco",
    "wof:placetype":"venue"
},
  "geometry": {"coordinates":[-117.901308,33.602297],"type":"Point"}
}