{
  "type": "Feature",
  "properties": {
    "iso:country":"US",
    "sg:address":"1711 Hamilton Ave",
    "sg:city":"San Jose",
    "sg:classifiers":[
        {
            "category":"Health Services",
            "subcategory":"Medical Lab",
            "type":"Services"
        }
    ],
    "sg:phone":"+1 408 448 7279",
    "sg:postcode":"95125",
    "sg:province":"CA",
    "sg:tags":[
        "laboratory"
    ],
    "wof:name":"Yamasaki Crown & Bridge Lab",
    "wof:placetype":"venue"
},
  "geometry": {"coordinates":[-121.91792,37.294477],"type":"Point"}
}