{
  "type": "Feature",
  "properties": {
    "iso:country":"US",
    "sg:address":"583 Newport Center Dr",
    "sg:city":"Newport Beach",
    "sg:classifiers":[
        {
            "category":"Shopping",
            "subcategory":"Optician",
            "type":"Retail Goods"
        }
    ],
    "sg:phone":"+1 949 640 8230",
    "sg:postcode":"92660",
    "sg:province":"CA",
    "sg:tags":[
        "eyewear"
    ],
    "wof:name":"Optical Shop of Aspen",
    "wof:placetype":"venue"
},
  "geometry": {"coordinates":[-117.87255999999999,33.617129],"type":"Point"}
}