{
  "type": "Feature",
  "properties": {
    "addr:full":"13741 Danielson St Poway CA 92064",
    "addr:housenumber":"13741",
    "addr:postcode":"ca 92064",
    "addr:street":"Danielson St",
    "iso:country":"US",
    "sg:address":"13741 Danielson St",
    "sg:city":"Poway",
    "sg:classifiers":[
        {
            "category":"Social Services",
            "subcategory":"Job Training",
            "type":"Services"
        }
    ],
    "sg:phone":"+1 858 486 4504",
    "sg:postcode":"92064",
    "sg:province":"CA",
    "sg:tags":[
        "employment"
    ],
    "wof:name":"Manpower Training Ctr",
    "wof:placetype":"venue"
},
  "geometry": {"coordinates":[-117.03110599999999,32.939716],"type":"Point"}
}