{
  "type": "Feature",
  "properties": {
    "iso:country":"US",
    "sg:address":"4031 Cll Isabella",
    "sg:city":"San Clemente",
    "sg:classifiers":[
        {
            "category":"Utilities",
            "subcategory":"Telephone",
            "type":"Services"
        }
    ],
    "sg:phone":"+1 949 361 9355",
    "sg:postcode":"92672",
    "sg:province":"CA",
    "sg:tags":[
        "marketing",
        "internet"
    ],
    "wof:name":"New Talkies Productions",
    "wof:placetype":"venue"
},
  "geometry": {"coordinates":[-117.595829,33.394333],"type":"Point"}
}