{
  "type": "Feature",
  "properties": {
    "addr:full":"345 Eleana Dr Ben Lomond CA 95005",
    "addr:housenumber":"345",
    "addr:postcode":"95005",
    "addr:street":"Eleana Dr",
    "iso:country":"US",
    "sg:address":"345 Eleana Dr",
    "sg:city":"Ben Lomond",
    "sg:classifiers":[
        {
            "category":"Building & Trades",
            "subcategory":"Construction",
            "type":"Services"
        }
    ],
    "sg:phone":"+1 831 336 2187",
    "sg:postcode":"95005",
    "sg:province":"CA",
    "sg:tags":[
        "contractor"
    ],
    "wof:name":"Robert Beardsley",
    "wof:placetype":"venue"
},
  "geometry": {"coordinates":[-122.074378,37.076531],"type":"Point"}
}