{
  "type": "Feature",
  "properties": {
    "addr:full":"1690 Tiburon Blvd Belvedere Tibrn CA 94920",
    "addr:housenumber":"1690",
    "addr:postcode":"94920",
    "addr:street":"Tiburon Blvd",
    "iso:country":"US",
    "sg:address":"1690 Tiburon Blvd",
    "sg:city":"Belvedere Tibrn",
    "sg:classifiers":[
        {
            "category":"Shopping",
            "subcategory":"Bicycles & Sporting Goods",
            "type":"Retail Goods"
        }
    ],
    "sg:phone":"+1 415 435 5111",
    "sg:postcode":"94920",
    "sg:province":"CA",
    "wof:name":"Demo Sport",
    "wof:placetype":"venue"
},
  "geometry": {"coordinates":[-122.45670800000001,37.873981],"type":"Point"}
}