{
  "type": "Feature",
  "properties": {
    "addr:full":"4020 W Sunset Blvd Los Angeles CA 90029",
    "addr:housenumber":"4020",
    "addr:postcode":"90029",
    "addr:street":"W Sunset Blvd",
    "iso:country":"US",
    "sg:address":"4020 W Sunset Blvd",
    "sg:city":"Los Angeles",
    "sg:phone":"+1 323 722 5757",
    "sg:postcode":"90029",
    "sg:province":"CA",
    "sg:tags":[
        "packaging",
        "marketing",
        "oil",
        "motor",
        "blending"
    ],
    "wof:name":"Pennzoil - Quaker State Co",
    "wof:placetype":"venue"
},
  "geometry": {"coordinates":[-118.281037,34.09294],"type":"Point"}
}