{
  "type": "Feature",
  "properties": {
    "addr:full":"8029 Alondra Blvd Compton CA 90221",
    "addr:housenumber":"8029",
    "addr:postcode":"90221",
    "addr:street":"Alondra Blvd",
    "iso:country":"US",
    "sg:address":"8029 Alondra Blvd",
    "sg:city":"Compton",
    "sg:classifiers":[
        {
            "category":"Restaurant",
            "type":"Food & Drink"
        }
    ],
    "sg:phone":"+1 562 529 3900",
    "sg:postcode":"90221",
    "sg:province":"CA",
    "sg:tags":[
        "pizza"
    ],
    "wof:name":"Pizza Hut",
    "wof:placetype":"venue"
},
  "geometry": {"coordinates":[-118.20500199999999,33.896],"type":"Point"}
}