{
  "type": "Feature",
  "properties": {
    "iso:country":"US",
    "sg:address":"217 S Sacramento St",
    "sg:city":"Lodi",
    "sg:classifiers":[
        {
            "category":"Building & Trades",
            "subcategory":"Construction",
            "type":"Services"
        },
        {
            "category":"Building & Trades",
            "subcategory":"Electrical",
            "type":"Services"
        },
        {
            "category":"Building & Trades",
            "subcategory":"Plumbing",
            "type":"Services"
        },
        {
            "category":"Home & Garden",
            "subcategory":"Building Materials",
            "type":"Retail Goods"
        },
        {
            "category":"Building & Trades",
            "subcategory":"Cleaning & Sanitation",
            "type":"Services"
        },
        {
            "category":"Manufacturing",
            "subcategory":"Building Materials",
            "type":"Manufacturing & Wholesale Goods"
        }
    ],
    "sg:phone":"+1 209 369 3671",
    "sg:postcode":"95240",
    "sg:province":"CA",
    "sg:tags":[
        "heater",
        "plumber",
        "sheet",
        "cleaner",
        "repairer",
        "work",
        "metal",
        "specialty",
        "system",
        "water",
        "furnaces-heating",
        "heating",
        "contractor",
        "air conditioning",
        "sewer"
    ],
    "sg:website":"http://www.hendersonslodi.com",
    "wof:name":"Henderson Bros Co. Inc.",
    "wof:placetype":"venue"
},
  "geometry": {"coordinates":[-121.272459,38.131513],"type":"Point"}
}