{
  "type": "Feature",
  "properties": {
    "iso:country":"US",
    "sg:address":"2601 Deerbrook St",
    "sg:city":"Bakersfield",
    "sg:classifiers":[
        {
            "category":"Professional",
            "subcategory":"Business Services",
            "type":"Services"
        }
    ],
    "sg:phone":"+1 661 392 0795",
    "sg:postcode":"93308",
    "sg:province":"CA",
    "sg:tags":[
        "notary"
    ],
    "wof:name":"Sharon Askew-Mobile Northwest",
    "wof:placetype":"venue"
},
  "geometry": {"coordinates":[-119.031598,35.430893],"type":"Point"}
}