{
  "type": "Feature",
  "properties": {
    "addr:full":"375 W Arenas Rd Palm Springs CA 92262",
    "addr:housenumber":"375",
    "addr:postcode":"92262",
    "addr:street":"W Arenas Rd",
    "iso:country":"US",
    "sg:address":"375 W Arenas Rd",
    "sg:city":"Palm Springs",
    "sg:classifiers":[
        {
            "category":"Travel",
            "subcategory":"Hotels & Motels",
            "type":"Entertainment"
        }
    ],
    "sg:phone":"+1 877 897 7100",
    "sg:postcode":"92262",
    "sg:province":"CA",
    "sg:website":"sangiulianohotel.com/",
    "wof:name":"San Giuliano Hotel",
    "wof:placetype":"venue"
},
  "geometry": {"coordinates":[-116.54980500000001,33.82097],"type":"Point"}
}