{
  "type": "Feature",
  "properties": {
    "addr:full":"1164 Old Bayshore Hwy San Jose CA 95112",
    "addr:housenumber":"1164",
    "addr:postcode":"95112",
    "addr:street":"Old Bayshore Hwy",
    "iso:country":"US",
    "sg:address":"1164 Old Bayshore Hwy",
    "sg:city":"San Jose",
    "sg:classifiers":[
        {
            "category":"Autos & Motor Vehicles",
            "subcategory":"Auto Supplies",
            "type":"Retail Goods"
        }
    ],
    "sg:phone":"+1 408 286 9200",
    "sg:postcode":"95112",
    "sg:province":"CA",
    "sg:tags":[
        "automobile",
        "parts"
    ],
    "wof:name":"B & A Friction Materials Inc",
    "wof:placetype":"venue"
},
  "geometry": {"coordinates":[-121.89519900000001,37.363864],"type":"Point"}
}