{
  "type": "Feature",
  "properties": {
    "addr:full":"2555 Industry Way Lynwood CA 90262",
    "addr:housenumber":"2555",
    "addr:postcode":"90262",
    "addr:street":"Industry Way",
    "iso:country":"US",
    "sg:address":"2555 Industry Way",
    "sg:city":"Lynwood",
    "sg:classifiers":[
        {
            "category":"Home & Garden",
            "subcategory":"Carpets & Floor Coverings",
            "type":"Retail Goods"
        }
    ],
    "sg:phone":"+1 323 249 4036",
    "sg:postcode":"90262",
    "sg:province":"CA",
    "sg:tags":[
        "mattress"
    ],
    "wof:name":"Genin Home Fashion",
    "wof:placetype":"venue"
},
  "geometry": {"coordinates":[-118.226997,33.924599],"type":"Point"}
}