{
  "type": "Feature",
  "properties": {
    "iso:country":"US",
    "sg:address":"8129 Arroyo Dr",
    "sg:city":"Rosemead",
    "sg:classifiers":[
        {
            "category":"Food & Beverages",
            "subcategory":"Bakery",
            "type":"Retail Goods"
        }
    ],
    "sg:phone":"+1 626 288 0778",
    "sg:postcode":"91770",
    "sg:province":"CA",
    "sg:tags":[
        "doughnut"
    ],
    "wof:name":"Arroyo Donuts",
    "wof:placetype":"venue"
},
  "geometry": {"coordinates":[-118.091891,34.04171],"type":"Point"}
}