{
  "type": "Feature",
  "properties": {
    "addr:full":"4168 Douglas Blvd Granite Bay CA 95746",
    "addr:housenumber":"4168",
    "addr:postcode":"95746",
    "addr:street":"Douglas Blvd",
    "iso:country":"US",
    "sg:address":"4168 Douglas Blvd",
    "sg:city":"Granite Bay",
    "sg:classifiers":[
        {
            "category":"Real Estate",
            "subcategory":"Real Estate Agent",
            "type":"Services"
        }
    ],
    "sg:phone":"+1 916 773 0700",
    "sg:postcode":"95746",
    "sg:province":"CA",
    "sg:tags":[
        "investment"
    ],
    "wof:name":"Sierra Crest Equities",
    "wof:placetype":"venue"
},
  "geometry": {"coordinates":[-121.218267,38.743647],"type":"Point"}
}