{
  "type": "Feature",
  "properties": {
    "iso:country":"US",
    "sg:address":"16300 Sand Canyon Ave Ste 811",
    "sg:city":"Irvine",
    "sg:classifiers":[
        {
            "category":"Health Services",
            "subcategory":"Doctor",
            "type":"Services"
        }
    ],
    "sg:phone":"+1 949 753 9000",
    "sg:postcode":"92618",
    "sg:province":"CA",
    "sg:tags":[
        "pediatrician"
    ],
    "sg:website":"www.irvinepediatrics.com",
    "wof:name":"Peggy Tse MD",
    "wof:placetype":"venue"
},
  "geometry": {"coordinates":[-117.77325500000001,33.660353],"type":"Point"}
}