{
  "type": "Feature",
  "properties": {
    "iso:country":"US",
    "sg:address":"22865 Lake Forest Dr",
    "sg:city":"Lake Forest",
    "sg:classifiers":[
        {
            "category":"Health Services",
            "subcategory":"Doctor",
            "type":"Services"
        }
    ],
    "sg:phone":"+1 949 660 5188",
    "sg:postcode":"92630",
    "sg:province":"CA",
    "sg:tags":[
        "physician",
        "surgeon"
    ],
    "wof:name":"Tony T King MD",
    "wof:placetype":"venue"
},
  "geometry": {"coordinates":[-117.700941,33.641313],"type":"Point"}
}