{
  "type": "Feature",
  "properties": {
    "addr:full":"5810 Mission Rd Sunol CA 94586",
    "addr:housenumber":"5810",
    "addr:postcode":"94586",
    "addr:street":"Mission Rd",
    "iso:country":"US",
    "sg:address":"5810 Mission Rd",
    "sg:city":"Sunol",
    "sg:classifiers":[
        {
            "category":"Sports & Exercise",
            "subcategory":"Stables",
            "type":"Entertainment"
        }
    ],
    "sg:phone":"+1 925 862 2529",
    "sg:postcode":"94586",
    "sg:province":"CA",
    "sg:tags":[
        "horse"
    ],
    "wof:name":"Arriba Vista Ranch",
    "wof:placetype":"venue"
},
  "geometry": {"coordinates":[-121.894249,37.570808],"type":"Point"}
}