{
  "type": "Feature",
  "properties": {
    "iso:country":"US",
    "sg:address":"43300 Elkhorn Trl",
    "sg:city":"Palm Desert",
    "sg:classifiers":[
        {
            "category":"Shopping",
            "subcategory":"Stationery & Office Supplies",
            "type":"Retail Goods"
        }
    ],
    "sg:phone":"+1 760 345 7235",
    "sg:postcode":"92211",
    "sg:province":"CA",
    "sg:tags":[
        "stationer"
    ],
    "wof:name":"Calendars Etc",
    "wof:placetype":"venue"
},
  "geometry": {"coordinates":[-116.316336,33.732434],"type":"Point"}
}