{
  "type": "Feature",
  "properties": {
    "addr:full":"980 David Rd Burlingame CA 94010",
    "addr:housenumber":"980",
    "addr:postcode":"94010",
    "addr:street":"David Rd",
    "iso:country":"US",
    "sg:address":"980 David Rd",
    "sg:city":"Burlingame",
    "sg:classifiers":[
        {
            "category":"Shopping",
            "subcategory":"Florist",
            "type":"Retail Goods"
        }
    ],
    "sg:phone":"+1 650 652 9009",
    "sg:postcode":"94010",
    "sg:province":"CA",
    "sg:website":"www.plandecor.com",
    "wof:name":"Plan Decor",
    "wof:placetype":"venue"
},
  "geometry": {"coordinates":[-122.370813,37.593655],"type":"Point"}
}