{
  "type": "Feature",
  "properties": {
    "addr:full":"2245 Fenton Parkway Suite 101 San Diego CA 92108",
    "addr:housenumber":"2245",
    "addr:postcode":"92108",
    "addr:street":"Fenton Parkway Suite 101",
    "iso:country":"US",
    "sg:address":"2245 Fenton Parkway Suite 101",
    "sg:city":"San Diego",
    "sg:classifiers":[
        {
            "category":"Restaurant",
            "type":"Food & Drink"
        }
    ],
    "sg:phone":"+1 619 640 2710",
    "sg:postcode":"92108",
    "sg:province":"CA",
    "sg:tags":[
        "pizza"
    ],
    "wof:name":"Stuft Pizza & Brewing Company",
    "wof:placetype":"venue"
},
  "geometry": {"coordinates":[-117.128979,32.779542],"type":"Point"}
}