{
  "type": "Feature",
  "properties": {
    "addr:full":"4408 Murietta Ave Sherman Oaks CA 91423",
    "addr:housenumber":"4408",
    "addr:postcode":"91423",
    "addr:street":"Murietta Ave",
    "iso:country":"US",
    "sg:address":"4408 Murietta Ave",
    "sg:city":"Sherman Oaks",
    "sg:classifiers":[
        {
            "category":"Real Estate",
            "subcategory":"Real Estate Services",
            "type":"Services"
        },
        {
            "category":"Home & Garden",
            "subcategory":"Furniture",
            "type":"Retail Goods"
        }
    ],
    "sg:phone":"+1 818 788 0985",
    "sg:postcode":"91423",
    "sg:province":"CA",
    "sg:tags":[
        "management",
        "property",
        "store"
    ],
    "wof:name":"Harlor Management",
    "wof:placetype":"venue"
},
  "geometry": {"coordinates":[-118.43800400000001,34.1506],"type":"Point"}
}