{
  "type": "Feature",
  "properties": {
    "addr:full":"2 Williamson Ct Novato CA 94947",
    "addr:housenumber":"2",
    "addr:postcode":"94947",
    "addr:street":"Williamson Ct",
    "iso:country":"US",
    "sg:address":"2 Williamson Ct",
    "sg:city":"Novato",
    "sg:classifiers":[
        {
            "category":"Professional",
            "subcategory":"Lawyer & Legal Services",
            "type":"Services"
        }
    ],
    "sg:phone":"+1 415 898 4123",
    "sg:postcode":"94947",
    "sg:province":"CA",
    "sg:tags":[
        "plan"
    ],
    "wof:name":"Fleckles William G",
    "wof:placetype":"venue"
},
  "geometry": {"coordinates":[-122.599609,38.106071],"type":"Point"}
}