{
  "type": "Feature",
  "properties": {
    "iso:country":"US",
    "sg:address":"107 S Broadway",
    "sg:city":"Los Angeles",
    "sg:classifiers":[
        {
            "category":"Government",
            "subcategory":"Office",
            "type":"Public Place"
        }
    ],
    "sg:phone":"+1 213 897 3590",
    "sg:postcode":"90015",
    "sg:province":"CA",
    "sg:tags":[
        "registered",
        "agency",
        "nursing",
        "for"
    ],
    "wof:name":"Board of Registered Nurses",
    "wof:placetype":"venue"
},
  "geometry": {"coordinates":[-118.246678,34.052517],"type":"Point"}
}