{
  "type": "Feature",
  "properties": {
    "addr:full":"850 E Greenwich Pl Palo Alto CA 94303",
    "addr:housenumber":"850",
    "addr:postcode":"94303",
    "addr:street":"E Greenwich Pl",
    "iso:country":"US",
    "sg:address":"850 E Greenwich Pl",
    "sg:city":"Palo Alto",
    "sg:classifiers":[
        {
            "category":"Professional",
            "subcategory":"Business Services",
            "type":"Services"
        }
    ],
    "sg:phone":"+1 650 473 0262",
    "sg:postcode":"94303",
    "sg:province":"CA",
    "sg:tags":[
        "interior",
        "consultant",
        "design",
        "decorator"
    ],
    "wof:name":"Frotm Start To Finish",
    "wof:placetype":"venue"
},
  "geometry": {"coordinates":[-122.135291,37.440856],"type":"Point"}
}