{
  "type": "Feature",
  "properties": {
    "addr:full":"351 Lincoln Ave San Jose CA 95126",
    "addr:housenumber":"351",
    "addr:postcode":"95126",
    "addr:street":"Lincoln Ave",
    "iso:country":"US",
    "sg:address":"351 Lincoln Ave",
    "sg:city":"San Jose",
    "sg:classifiers":[
        {
            "category":"Retail",
            "subcategory":"Auto Repair",
            "type":"Services"
        }
    ],
    "sg:phone":"+1 408 293 4689",
    "sg:postcode":"95126",
    "sg:province":"CA",
    "wof:name":"Precision Frame & Axle Service",
    "wof:placetype":"venue"
},
  "geometry": {"coordinates":[-121.909136,37.321939],"type":"Point"}
}