{
  "type": "Feature",
  "properties": {
    "iso:country":"US",
    "sg:address":"2109 Van Ness Ave",
    "sg:city":"San Francisco",
    "sg:classifiers":[
        {
            "category":"Personal",
            "subcategory":"Beauty Salon",
            "type":"Services"
        }
    ],
    "sg:phone":"+1 415 474 3152",
    "sg:postcode":"94109",
    "sg:province":"CA",
    "wof:name":"Delli Gatti Hair Designs",
    "wof:placetype":"venue"
},
  "geometry": {"coordinates":[-122.423517,37.795699],"type":"Point"}
}