{
  "type": "Feature",
  "properties": {
    "addr:full":"330 Eliseo Dr Greenbrae CA 94904",
    "addr:housenumber":"330",
    "addr:postcode":"94904",
    "addr:street":"Eliseo Dr",
    "iso:country":"US",
    "sg:address":"330 Eliseo Dr",
    "sg:city":"Greenbrae",
    "sg:classifiers":[
        {
            "category":"Professional",
            "subcategory":"Engineering",
            "type":"Services"
        }
    ],
    "sg:phone":"+1 415 924 5011",
    "sg:postcode":"94904",
    "sg:province":"CA",
    "sg:tags":[
        "house",
        "product",
        "designer",
        "designing",
        "developing"
    ],
    "wof:name":"Robert Symons & Associates",
    "wof:placetype":"venue"
},
  "geometry": {"coordinates":[-122.514048,37.951955],"type":"Point"}
}