{
  "type": "Feature",
  "properties": {
    "iso:country":"US",
    "sg:address":"41689 Enterprise Cir N",
    "sg:city":"Temecula",
    "sg:classifiers":[
        {
            "category":"Organizations",
            "subcategory":"Non-profit Organization",
            "type":"Services"
        }
    ],
    "sg:phone":"+1 951 296 9639",
    "sg:postcode":"92590",
    "sg:province":"CA",
    "wof:name":"Temecula Associates",
    "wof:placetype":"venue"
},
  "geometry": {"coordinates":[-117.169466,33.519583],"type":"Point"}
}