{
  "type": "Feature",
  "properties": {
    "addr:full":"2800 Empire Ave Brentwood CA 94513",
    "addr:housenumber":"2800",
    "addr:postcode":"ca 94513",
    "addr:street":"Empire Ave",
    "iso:country":"US",
    "sg:address":"2800 Empire Ave",
    "sg:city":"Brentwood",
    "sg:classifiers":[
        {
            "category":"Home & Garden",
            "subcategory":"Garden Supply",
            "type":"Retail Goods"
        }
    ],
    "sg:phone":"+1 925 757 5179",
    "sg:postcode":"94513",
    "sg:province":"CA",
    "sg:tags":[
        "landscape"
    ],
    "sg:website":"www.orfanos.net",
    "wof:name":"Helios Farms Nursery",
    "wof:placetype":"venue"
},
  "geometry": {"coordinates":[-121.732467,37.965912],"type":"Point"}
}