{
  "type": "Feature",
  "properties": {
    "iso:country":"US",
    "sg:address":"901 King St",
    "sg:city":"Oakland",
    "sg:classifiers":[
        {
            "category":"Wholesale",
            "subcategory":"Groceries",
            "type":"Manufacturing & Wholesale Goods"
        }
    ],
    "sg:phone":"+1 510 436 4537",
    "sg:postcode":"94606",
    "sg:province":"CA",
    "sg:tags":[
        "baker"
    ],
    "wof:name":"Sara Lee Bakery Group",
    "wof:placetype":"venue"
},
  "geometry": {"coordinates":[-122.240337,37.779114],"type":"Point"}
}