{
  "type": "Feature",
  "properties": {
    "addr:full":"505 Montgomery Street San Francisco CA 94111",
    "addr:housenumber":"505",
    "addr:postcode":"94111",
    "addr:street":"Montgomery Street",
    "iso:country":"US",
    "sg:address":"505 Montgomery Street",
    "sg:city":"San Francisco",
    "sg:classifiers":[
        {
            "category":"Professional",
            "subcategory":"Lawyer & Legal Services",
            "type":"Services"
        }
    ],
    "sg:phone":"+1 415 391 3333",
    "sg:postcode":"94111",
    "sg:province":"CA",
    "wof:name":"Kato Allen M Associate",
    "wof:placetype":"venue"
},
  "geometry": {"coordinates":[-122.40295,37.793855],"type":"Point"}
}