{
  "type": "Feature",
  "properties": {
    "addr:full":"101 Avington Rd Alameda CA 94502",
    "addr:housenumber":"101",
    "addr:postcode":"94502",
    "addr:street":"Avington Rd",
    "iso:country":"US",
    "sg:address":"101 Avington Rd",
    "sg:city":"Alameda",
    "sg:classifiers":[
        {
            "category":"Professional",
            "subcategory":"Art Services",
            "type":"Services"
        }
    ],
    "sg:phone":"+1 510 388 8141",
    "sg:postcode":"94502",
    "sg:province":"CA",
    "sg:tags":[
        "photographer"
    ],
    "sg:website":"www.paulqphotography.com/",
    "wof:name":"Paul Q Photography",
    "wof:placetype":"venue"
},
  "geometry": {"coordinates":[-122.247062,37.747338],"type":"Point"}
}