{
  "type": "Feature",
  "properties": {
    "addr:full":"974 Valencia St, San Francisco, CA, USA, 94110",
    "addr:housenumber":974,
    "addr:postcode":"94110",
    "addr:street":"Valencia St",
    "addr:website":"http://www.lolosf.com/",
    "iso:country":"US",
    "name:eng_x_preferred":[
        "Lolo"
    ],
    "wof:name":"Lolo",
    "wof:placetype":"venue"
},
  "geometry": {"coordinates":[-122.421496,37.757358],"type":"Point"}
}