{
  "type": "Feature",
  "properties": {
    "addr:full":"24054 San Fernando Rd Newhall CA 91321",
    "addr:housenumber":"24054",
    "addr:postcode":"91321",
    "addr:street":"San Fernando Rd",
    "iso:country":"US",
    "sg:address":"24054 San Fernando Rd",
    "sg:city":"Newhall",
    "sg:classifiers":[
        {
            "category":"Banks & Credit Unions",
            "subcategory":"Bank",
            "type":"Services"
        }
    ],
    "sg:phone":"+1 661 253 0972",
    "sg:postcode":"91321",
    "sg:province":"CA",
    "sg:tags":[
        "loan"
    ],
    "wof:name":"Newhall Loans Pawnshop",
    "wof:placetype":"venue"
},
  "geometry": {"coordinates":[-118.523634,34.375229],"type":"Point"}
}