{
  "type": "Feature",
  "properties": {
    "addr:full":"17804 Pine Ct Carson CA 90746",
    "addr:housenumber":"17804",
    "addr:postcode":"90746",
    "addr:street":"Pine Ct",
    "iso:country":"US",
    "sg:address":"17804 Pine Ct",
    "sg:city":"Carson",
    "sg:classifiers":[
        {
            "category":"Shopping",
            "subcategory":"Clothing, Apparel, & Fashions",
            "type":"Retail Goods"
        }
    ],
    "sg:phone":"+1 310 701 5776",
    "sg:postcode":"90746",
    "sg:province":"CA",
    "sg:tags":[
        "family"
    ],
    "wof:name":"Third Degree Clothing",
    "wof:placetype":"venue"
},
  "geometry": {"coordinates":[-118.25111,33.867863],"type":"Point"}
}