{
  "type": "Feature",
  "properties": {
    "addr:full":"635 Marina Vista Ave Martinez CA 94553",
    "addr:housenumber":"635",
    "addr:postcode":"94553",
    "addr:street":"Marina Vista Ave",
    "iso:country":"US",
    "sg:address":"635 Marina Vista Ave",
    "sg:city":"Martinez",
    "sg:classifiers":[
        {
            "category":"Manufacturing",
            "subcategory":"Printing",
            "type":"Manufacturing & Wholesale Goods"
        }
    ],
    "sg:phone":"+1 925 370 0507",
    "sg:postcode":"94553",
    "sg:province":"CA",
    "sg:tags":[
        "printer"
    ],
    "wof:name":"Print Center",
    "wof:placetype":"venue"
},
  "geometry": {"coordinates":[-122.13846599999999,38.018081],"type":"Point"}
}