{
  "type": "Feature",
  "properties": {
    "addr:full":"4429 S Broadway Los Angeles CA 90037",
    "addr:housenumber":"4429",
    "addr:postcode":"90037",
    "addr:street":"S Broadway",
    "iso:country":"US",
    "sg:address":"4429 S Broadway",
    "sg:city":"Los Angeles",
    "sg:classifiers":[
        {
            "category":"Professional",
            "type":"Services"
        }
    ],
    "sg:phone":"+1 323 846 1560",
    "sg:postcode":"90037",
    "sg:province":"CA",
    "wof:name":"People Coordinated Svc",
    "wof:placetype":"venue"
},
  "geometry": {"coordinates":[-118.278412,34.003144],"type":"Point"}
}