{
  "type": "Feature",
  "properties": {
    "iso:country":"US",
    "sg:address":"353 N Pass Ave",
    "sg:city":"Burbank",
    "sg:classifiers":[
        {
            "category":"Restaurant",
            "type":"Food & Drink"
        }
    ],
    "sg:phone":"+1 818 563 2233",
    "sg:postcode":"91505",
    "sg:province":"CA",
    "wof:name":"Santa Fe Cafe",
    "wof:placetype":"venue"
},
  "geometry": {"coordinates":[-118.346026,34.155937],"type":"Point"}
}