{
  "type": "Feature",
  "properties": {
    "addr:full":"11355 Dismantle Ct Rancho Cordova CA 95742",
    "addr:housenumber":"11355",
    "addr:postcode":"95742",
    "addr:street":"Dismantle Ct",
    "iso:country":"US",
    "sg:address":"11355 Dismantle Ct",
    "sg:city":"Rancho Cordova",
    "sg:classifiers":[
        {
            "category":"Autos & Motor Vehicles",
            "subcategory":"Automobile Sales",
            "type":"Retail Goods"
        }
    ],
    "sg:phone":"+1 916 638 4866",
    "sg:postcode":"95742",
    "sg:province":"CA",
    "sg:tags":[
        "car",
        "dealer"
    ],
    "wof:name":"K & G Auto Dismantler",
    "wof:placetype":"venue"
},
  "geometry": {"coordinates":[-121.261551,38.572479],"type":"Point"}
}