{
  "type": "Feature",
  "properties": {
    "addr:full":"1700 Royal Crest Dr Lodi CA 95242",
    "addr:housenumber":"1700",
    "addr:postcode":"95242",
    "addr:street":"Royal Crest Dr",
    "iso:country":"US",
    "sg:address":"1700 Royal Crest Dr",
    "sg:city":"Lodi",
    "sg:classifiers":[
        {
            "category":"Travel",
            "subcategory":"Travel Agent",
            "type":"Entertainment"
        }
    ],
    "sg:phone":"+1 209 334 2868",
    "sg:postcode":"95242",
    "sg:province":"CA",
    "sg:tags":[
        "consultant",
        "transportation"
    ],
    "wof:name":"Transportation By Regulation",
    "wof:placetype":"venue"
},
  "geometry": {"coordinates":[-121.29418200000001,38.11972],"type":"Point"}
}