{
  "type": "Feature",
  "properties": {
    "addr:full":"37 Rio Robles E San Jose CA 95134",
    "addr:housenumber":"37",
    "addr:postcode":"95134",
    "addr:street":"Rio Robles E",
    "iso:country":"US",
    "sg:address":"37 Rio Robles E",
    "sg:city":"San Jose",
    "sg:classifiers":[
        {
            "category":"Food & Beverages",
            "subcategory":"Bakery",
            "type":"Retail Goods"
        }
    ],
    "sg:phone":"+1 408 577 0300",
    "sg:postcode":"95134",
    "sg:province":"CA",
    "sg:tags":[
        "sandwich"
    ],
    "sg:website":"www.quiznos.com",
    "wof:name":"Quizno's Subs",
    "wof:placetype":"venue"
},
  "geometry": {"coordinates":[-121.942786,37.405958],"type":"Point"}
}