{
  "type": "Feature",
  "properties": {
    "iso:country":"US",
    "sg:address":"3764 W 118th St",
    "sg:city":"Hawthorne",
    "sg:classifiers":[
        {
            "category":"Building & Trades",
            "subcategory":"Landscaping Services",
            "type":"Services"
        }
    ],
    "sg:phone":"+1 310 644 7077",
    "sg:postcode":"90250",
    "sg:province":"CA",
    "wof:name":"Rudy Gardening Service",
    "wof:placetype":"venue"
},
  "geometry": {"coordinates":[-118.339345,33.927224],"type":"Point"}
}