{
  "type": "Feature",
  "properties": {
    "iso:country":"US",
    "sg:address":"1416 Electric Ave",
    "sg:city":"Venice",
    "sg:classifiers":[
        {
            "category":"Arts & Performance",
            "subcategory":"Theater",
            "type":"Entertainment"
        }
    ],
    "sg:phone":"+1 310 306 1854",
    "sg:postcode":"90291",
    "sg:province":"CA",
    "sg:website":"www.electriclodge.org",
    "wof:name":"Electric Lodge",
    "wof:placetype":"venue"
},
  "geometry": {"coordinates":[-118.464748,33.990971],"type":"Point"}
}