{
  "type": "Feature",
  "properties": {
    "addr:full":"642 Palomar St Ste 406-241 Chula Vista CA 91911",
    "addr:housenumber":"642",
    "addr:postcode":"91911",
    "addr:street":"Palomar St Ste 406-241",
    "iso:country":"US",
    "sg:address":"642 Palomar St Ste 406-241",
    "sg:city":"Chula Vista",
    "sg:classifiers":[
        {
            "category":"Professional",
            "subcategory":"Art Services",
            "type":"Services"
        },
        {
            "category":"Professional",
            "subcategory":"Printing & Photocopies",
            "type":"Services"
        },
        {
            "category":"Communications",
            "type":"Services"
        }
    ],
    "sg:phone":"+1 800 215 2030",
    "sg:postcode":"91911",
    "sg:province":"CA",
    "sg:tags":[
        "web",
        "graphic",
        "design"
    ],
    "sg:website":"printandgraphicsusa.com",
    "wof:name":"Quality Printing and Graphics USA",
    "wof:placetype":"venue"
},
  "geometry": {"coordinates":[-117.080787,32.603535],"type":"Point"}
}