{
  "type": "Feature",
  "properties": {
    "iso:country":"US",
    "sg:address":"2863 Mandela Pkwy",
    "sg:city":"Emeryville",
    "sg:classifiers":[
        {
            "category":"Professional",
            "type":"Services"
        }
    ],
    "sg:phone":"+1 510 832 3573",
    "sg:postcode":"94608",
    "sg:province":"CA",
    "wof:name":"West Coast Rail & Transload",
    "wof:placetype":"venue"
},
  "geometry": {"coordinates":[-122.28879,37.823087],"type":"Point"}
}