{
  "type": "Feature",
  "properties": {
    "addr:full":"449 N Main St Manteca CA 95336",
    "addr:housenumber":"449",
    "addr:postcode":"95336",
    "addr:street":"N Main St",
    "iso:country":"US",
    "sg:address":"449 N Main St",
    "sg:city":"Manteca",
    "sg:classifiers":[
        {
            "category":"Restaurant",
            "type":"Food & Drink"
        }
    ],
    "sg:phone":"+1 209 239 2395",
    "sg:postcode":"95336",
    "sg:province":"CA",
    "sg:tags":[
        "pizza"
    ],
    "wof:name":"Patti's Pizza",
    "wof:placetype":"venue"
},
  "geometry": {"coordinates":[-121.21684500000001,37.803483],"type":"Point"}
}