{
  "type": "Feature",
  "properties": {
    "iso:country":"US",
    "sg:address":"9605 Scranton Rd",
    "sg:city":"San Diego",
    "sg:classifiers":[
        {
            "category":"Wholesale",
            "subcategory":"Electrical",
            "type":"Manufacturing & Wholesale Goods"
        }
    ],
    "sg:phone":"+1 858 550 3820",
    "sg:postcode":"92121",
    "sg:province":"CA",
    "sg:tags":[
        "telecommunication"
    ],
    "wof:name":"Ethertronics Inc",
    "wof:placetype":"venue"
},
  "geometry": {"coordinates":[-117.202502,32.898696],"type":"Point"}
}