{
  "type": "Feature",
  "properties": {
    "iso:country":"US",
    "sg:address":"239 Laurel St",
    "sg:city":"San Diego",
    "sg:classifiers":[
        {
            "category":"Health Services",
            "subcategory":"Medical Lab",
            "type":"Services"
        }
    ],
    "sg:phone":"+1 619 230 1142",
    "sg:postcode":"92101",
    "sg:province":"CA",
    "sg:tags":[
        "laboratory"
    ],
    "wof:name":"Biolos Dental Ceramics",
    "wof:placetype":"venue"
},
  "geometry": {"coordinates":[-117.162443,32.731301],"type":"Point"}
}