{
  "type": "Feature",
  "properties": {
    "iso:country":"US",
    "sg:address":"253 Walnut St",
    "sg:city":"Napa",
    "sg:classifiers":[
        {
            "category":"Wholesale",
            "subcategory":"Machinery & Supplies",
            "type":"Manufacturing & Wholesale Goods"
        }
    ],
    "sg:phone":"+1 707 224 7447",
    "sg:postcode":"94559",
    "sg:province":"CA",
    "sg:tags":[
        "industrial",
        "merchandise"
    ],
    "wof:name":"Cartons & Crates Shipping Co",
    "wof:placetype":"venue"
},
  "geometry": {"coordinates":[-122.300313,38.288531],"type":"Point"}
}