{
  "type": "Feature",
  "properties": {
    "iso:country":"US",
    "sg:address":"2129 W Edinger Ave",
    "sg:city":"Santa Ana",
    "sg:classifiers":[
        {
            "category":"Social Services",
            "subcategory":"Child Care",
            "type":"Services"
        },
        {
            "category":"Education",
            "subcategory":"Preschool",
            "type":"Public Place"
        },
        {
            "category":"Education",
            "subcategory":"School",
            "type":"Public Place"
        }
    ],
    "sg:phone":"+1 714 979 7422",
    "sg:postcode":"92704",
    "sg:province":"CA",
    "sg:tags":[
        "high",
        "middle",
        "day",
        "elementary"
    ],
    "wof:name":"Westport School",
    "wof:placetype":"venue"
},
  "geometry": {"coordinates":[-117.898003,33.7271],"type":"Point"}
}