{
  "type": "Feature",
  "properties": {
    "addr:full":"37122 Nason Rd Carmel Valley CA 93924",
    "addr:postcode":"37122;93924",
    "addr:street":"Nason Rd",
    "iso:country":"US",
    "sg:address":"37122 Nason Rd",
    "sg:city":"Carmel Valley",
    "sg:classifiers":[
        {
            "category":"Real Estate",
            "subcategory":"Real Estate Agent",
            "type":"Services"
        }
    ],
    "sg:phone":"+1 831 659 4990",
    "sg:postcode":"93924",
    "sg:province":"CA",
    "sg:tags":[
        "inspection"
    ],
    "wof:name":"Hubbard Home Inspection",
    "wof:placetype":"venue"
},
  "geometry": {"coordinates":[-121.657978,36.401086],"type":"Point"}
}