{
  "type": "Feature",
  "properties": {
    "addr:full":"2167 Winchester Blvd Campbell CA 95008",
    "addr:housenumber":"2167",
    "addr:postcode":"95008",
    "addr:street":"Winchester Blvd",
    "iso:country":"US",
    "sg:address":"2167 Winchester Blvd",
    "sg:city":"Campbell",
    "sg:classifiers":[
        {
            "category":"Personal",
            "subcategory":"Beauty Salon",
            "type":"Services"
        }
    ],
    "sg:phone":"+1 408 406 1420",
    "sg:postcode":"95008",
    "sg:province":"CA",
    "wof:name":"Amante 2 Salon",
    "wof:placetype":"venue"
},
  "geometry": {"coordinates":[-121.94979499999999,37.284762],"type":"Point"}
}