{
  "type": "Feature",
  "properties": {
    "addr:full":"13485 Green Valley Rd Sebastopol CA 95472",
    "addr:housenumber":"13485",
    "addr:postcode":"95472",
    "addr:street":"Green Valley Rd",
    "iso:country":"US",
    "sg:address":"13485 Green Valley Rd",
    "sg:city":"Sebastopol",
    "sg:classifiers":[
        {
            "category":"Travel",
            "subcategory":"Campground",
            "type":"Entertainment"
        }
    ],
    "sg:phone":"+1 707 823 4508",
    "sg:postcode":"95472",
    "sg:province":"CA",
    "sg:tags":[
        "camp"
    ],
    "sg:website":"www.mtgilead.org",
    "wof:name":"Mt Gilead Bible Conference",
    "wof:placetype":"venue"
},
  "geometry": {"coordinates":[-122.936463,38.461265],"type":"Point"}
}