{
  "type": "Feature",
  "properties": {
    "addr:full":"3442 30th St San Diego CA 92104",
    "addr:housenumber":"3442",
    "addr:postcode":"92104",
    "addr:street":"30Th St",
    "iso:country":"US",
    "sg:address":"3442 30th St",
    "sg:city":"San Diego",
    "sg:classifiers":[
        {
            "category":"Food & Beverages",
            "subcategory":"Fruits & Vegetables",
            "type":"Retail Goods"
        }
    ],
    "sg:phone":"+1 619 297 0252",
    "sg:postcode":"92104",
    "sg:province":"CA",
    "sg:tags":[
        "produce"
    ],
    "wof:name":"El Inca",
    "wof:placetype":"venue"
},
  "geometry": {"coordinates":[-117.130149,32.741689],"type":"Point"}
}