{
  "type": "Feature",
  "properties": {
    "iso:country":"US",
    "sg:address":"535 Foam St",
    "sg:city":"Monterey",
    "sg:classifiers":[
        {
            "category":"Professional",
            "subcategory":"Computer Services",
            "type":"Services"
        }
    ],
    "sg:phone":"+1 831 646 1093",
    "sg:postcode":"93940",
    "sg:province":"CA",
    "sg:tags":[
        "consulting",
        "retail"
    ],
    "wof:name":"Passa Tempo",
    "wof:placetype":"venue"
},
  "geometry": {"coordinates":[-121.900709,36.613618],"type":"Point"}
}