{
  "type": "Feature",
  "properties": {
    "addr:full":"3277 Bernard St Riverside CA 92504",
    "addr:housenumber":"3277",
    "addr:postcode":"92504",
    "addr:street":"Bernard St",
    "iso:country":"US",
    "sg:address":"3277 Bernard St",
    "sg:city":"Riverside",
    "sg:classifiers":[
        {
            "category":"Building & Trades",
            "subcategory":"Landscaping Services",
            "type":"Services"
        }
    ],
    "sg:phone":"+1 951 688 3243",
    "sg:postcode":"92504",
    "sg:province":"CA",
    "sg:tags":[
        "lawn",
        "maintenance"
    ],
    "wof:name":"Albano's Lawn Maintenance Svc",
    "wof:placetype":"venue"
},
  "geometry": {"coordinates":[-117.4234,33.92209],"type":"Point"}
}