{
  "type": "Feature",
  "properties": {
    "addr:full":"200 W Willow St Long Beach CA 90806",
    "addr:housenumber":"200",
    "addr:postcode":"90806",
    "addr:street":"W Willow St",
    "iso:country":"US",
    "sg:address":"200 W Willow St",
    "sg:city":"Long Beach",
    "sg:classifiers":[
        {
            "category":"Food & Beverages",
            "subcategory":"Liquor & Beverages",
            "type":"Retail Goods"
        }
    ],
    "sg:phone":"+1 562 988 3200",
    "sg:postcode":"90806",
    "sg:province":"CA",
    "sg:tags":[
        "beer",
        "spirit",
        "wine"
    ],
    "wof:name":"KBC Liquor & Food Inc",
    "wof:placetype":"venue"
},
  "geometry": {"coordinates":[-118.19377,33.804182],"type":"Point"}
}