{
  "type": "Feature",
  "properties": {
    "iso:country":"US",
    "sg:address":"201 California St",
    "sg:city":"San Francisco",
    "sg:classifiers":[
        {
            "category":"Real Estate",
            "subcategory":"Real Estate Agent",
            "type":"Services"
        }
    ],
    "sg:phone":"+1 415 765 9975",
    "sg:postcode":"94111",
    "sg:province":"CA",
    "wof:name":"Equity Office Properties Trust",
    "wof:placetype":"venue"
},
  "geometry": {"coordinates":[-122.399959,37.793209],"type":"Point"}
}