{
  "type": "Feature",
  "properties": {
    "addr:full":"920 N Ventura Ave Ventura CA 93001",
    "addr:housenumber":"920",
    "addr:postcode":"93001",
    "addr:street":"N Ventura Ave",
    "iso:country":"US",
    "sg:address":"920 N Ventura Ave",
    "sg:city":"Ventura",
    "sg:classifiers":[
        {
            "category":"Restaurant",
            "type":"Food & Drink"
        }
    ],
    "sg:phone":"+1 805 641 3682",
    "sg:postcode":"93001",
    "sg:province":"CA",
    "wof:name":"Costa Del Sol Restaurant",
    "wof:placetype":"venue"
},
  "geometry": {"coordinates":[-119.297409,34.292261],"type":"Point"}
}