{
  "type": "Feature",
  "properties": {
    "iso:country":"US",
    "sg:address":"11890 Old Redwood Hwy",
    "sg:city":"Healdsburg",
    "sg:classifiers":[
        {
            "category":"Bars & Pubs",
            "type":"Food & Drink"
        }
    ],
    "sg:phone":"+1 707 433 6804",
    "sg:postcode":"95448",
    "sg:province":"CA",
    "sg:tags":[
        "lounge",
        "cocktail"
    ],
    "wof:name":"El Paso Cantina",
    "wof:placetype":"venue"
},
  "geometry": {"coordinates":[-122.843543,38.578382],"type":"Point"}
}