{
  "type": "Feature",
  "properties": {
    "iso:country":"US",
    "sg:address":"3350 N State St",
    "sg:city":"Ukiah",
    "sg:classifiers":[
        {
            "category":"Wholesale",
            "subcategory":"Metals & Minerals",
            "type":"Manufacturing & Wholesale Goods"
        }
    ],
    "sg:phone":"+1 707 462 0567",
    "sg:postcode":"95482",
    "sg:province":"CA",
    "sg:tags":[
        "rope",
        "wire"
    ],
    "sg:website":"www.acmerigging.com",
    "wof:name":"Acme Rigging & Supply Co",
    "wof:placetype":"venue"
},
  "geometry": {"coordinates":[-123.206676,39.19476],"type":"Point"}
}