{
  "type": "Feature",
  "properties": {
    "addr:full":"890 S Ocean Ave Cayucos CA 93430",
    "addr:housenumber":"890",
    "addr:postcode":"93430",
    "addr:street":"S Ocean Ave",
    "iso:country":"US",
    "sg:address":"890 S Ocean Ave",
    "sg:city":"Cayucos",
    "sg:classifiers":[
        {
            "category":"Shopping",
            "subcategory":"Antiques",
            "type":"Retail Goods"
        }
    ],
    "sg:phone":"+1 805 995 0832",
    "sg:postcode":"93430",
    "sg:province":"CA",
    "wof:name":"American Pie Antiques",
    "wof:placetype":"venue"
},
  "geometry": {"coordinates":[-120.894997,35.444],"type":"Point"}
}