{
  "type": "Feature",
  "properties": {
    "addr:full":"16791 McFadden Ave Tustin CA 92780",
    "addr:housenumber":"16791",
    "addr:postcode":"92780",
    "addr:street":"Mcfadden Ave",
    "iso:country":"US",
    "sg:address":"16791 McFadden Ave",
    "sg:city":"Tustin",
    "sg:classifiers":[
        {
            "category":"Food & Beverages",
            "subcategory":"Groceries & Convenience Stores",
            "type":"Retail Goods"
        }
    ],
    "sg:phone":"+1 714 543 8835",
    "sg:postcode":"92780",
    "sg:province":"CA",
    "wof:name":"7-Eleven",
    "wof:placetype":"venue"
},
  "geometry": {"coordinates":[-117.83628400000001,33.733895],"type":"Point"}
}