{
  "type": "Feature",
  "properties": {
    "iso:country":"US",
    "sg:address":"3090 Merced Falls Rd",
    "sg:city":"La Grange",
    "sg:classifiers":[
        {
            "category":"Education",
            "subcategory":"School",
            "type":"Public Place"
        }
    ],
    "sg:phone":"+1 209 852 2864",
    "sg:postcode":"95329",
    "sg:province":"CA",
    "wof:name":"Don Pedro High School",
    "wof:placetype":"venue"
},
  "geometry": {"coordinates":[-120.322852,37.682664],"type":"Point"}
}