{
  "type": "Feature",
  "properties": {
    "addr:full":"1114 Sutherland Ln Apt 2 Capitola CA 95010",
    "addr:housenumber":"1114;2",
    "addr:postcode":"95010",
    "addr:street":"Sutherland Ln Apt",
    "iso:country":"US",
    "sg:address":"1114 Sutherland Ln Apt 2",
    "sg:city":"Capitola",
    "sg:classifiers":[
        {
            "category":"Professional",
            "subcategory":"Art Services",
            "type":"Services"
        }
    ],
    "sg:phone":"+1 831 475 1061",
    "sg:postcode":"95010",
    "sg:province":"CA",
    "sg:tags":[
        "graphic",
        "commercial",
        "designer",
        "artist"
    ],
    "wof:name":"Pc Productions",
    "wof:placetype":"venue"
},
  "geometry": {"coordinates":[-121.939477,36.982365],"type":"Point"}
}