{
  "type": "Feature",
  "properties": {
    "addr:full":"89 Pso Hermoso Salinas CA 93908",
    "addr:housenumber":"89",
    "addr:postcode":"93908",
    "addr:street":"Pso Hermoso",
    "iso:country":"US",
    "sg:address":"89 Pso Hermoso",
    "sg:city":"Salinas",
    "sg:classifiers":[
        {
            "category":"Building & Trades",
            "subcategory":"Construction",
            "type":"Services"
        }
    ],
    "sg:phone":"+1 831 484 1739",
    "sg:postcode":"93908",
    "sg:province":"CA",
    "sg:tags":[
        "house"
    ],
    "wof:name":"Team Builders",
    "wof:placetype":"venue"
},
  "geometry": {"coordinates":[-121.718138,36.574036],"type":"Point"}
}