{
  "type": "Feature",
  "properties": {
    "iso:country":"US",
    "sg:address":"1978 Muirfield Ave",
    "sg:city":"Upland",
    "sg:classifiers":[
        {
            "category":"Building & Trades",
            "subcategory":"Landscaping Services",
            "type":"Services"
        }
    ],
    "sg:phone":"+1 909 949 9748",
    "sg:postcode":"91784",
    "sg:province":"CA",
    "sg:tags":[
        "landscape",
        "contractor"
    ],
    "wof:name":"Future Landscape Maintenance",
    "wof:placetype":"venue"
},
  "geometry": {"coordinates":[-117.67796,34.135123],"type":"Point"}
}