{
  "type": "Feature",
  "properties": {
    "iso:country":"US",
    "sg:address":"2372 Belmont Ave",
    "sg:city":"Long Beach",
    "sg:classifiers":[
        {
            "category":"Building & Trades",
            "subcategory":"Construction",
            "type":"Services"
        }
    ],
    "sg:phone":"+1 562 498 5788",
    "sg:postcode":"90815",
    "sg:province":"CA",
    "sg:tags":[
        "steam",
        "cleaning"
    ],
    "wof:name":"A & A Steam Cleaning Svc",
    "wof:placetype":"venue"
},
  "geometry": {"coordinates":[-118.14428100000001,33.801341],"type":"Point"}
}