{
  "type": "Feature",
  "properties": {
    "iso:country":"US",
    "sg:address":"25012 Narbonne Ave",
    "sg:city":"Lomita",
    "sg:classifiers":[
        {
            "category":"Professional",
            "subcategory":"Computer Services",
            "type":"Services"
        }
    ],
    "sg:phone":"+1 310 530 2022",
    "sg:postcode":"90717",
    "sg:province":"CA",
    "sg:tags":[
        "repair"
    ],
    "wof:name":"Markon Computer Science Inc",
    "wof:placetype":"venue"
},
  "geometry": {"coordinates":[-118.319875,33.797845],"type":"Point"}
}