{
  "type": "Feature",
  "properties": {
    "addr:full":"2271 Michael Dr Newbury Park CA 91320",
    "addr:housenumber":"2271",
    "addr:postcode":"91320",
    "addr:street":"Michael Dr",
    "iso:country":"US",
    "sg:address":"2271 Michael Dr",
    "sg:city":"Newbury Park",
    "sg:classifiers":[
        {
            "category":"Restaurant",
            "type":"Food & Drink"
        }
    ],
    "sg:menulink":"http://www.allmenus.com/ca/thousand-oaks/213381-taco-bell/menu/",
    "sg:phone":"+1 805 499 4605",
    "sg:postcode":"91320",
    "sg:province":"CA",
    "sg:tags":[
        "mexican"
    ],
    "wof:name":"Taco Bell",
    "wof:placetype":"venue"
},
  "geometry": {"coordinates":[-118.92634200000001,34.181503],"type":"Point"}
}