{
  "type": "Feature",
  "properties": {
    "addr:full":"9298 Madison Ave Orangevale CA 95662",
    "addr:housenumber":"9298",
    "addr:postcode":"95662",
    "addr:street":"Madison Ave",
    "iso:country":"US",
    "sg:address":"9298 Madison Ave",
    "sg:city":"Orangevale",
    "sg:classifiers":[
        {
            "category":"Building & Trades",
            "subcategory":"Construction",
            "type":"Services"
        }
    ],
    "sg:phone":"+1 916 988 7933",
    "sg:postcode":"95662",
    "sg:province":"CA",
    "sg:tags":[
        "residential"
    ],
    "wof:name":"Mann Co",
    "wof:placetype":"venue"
},
  "geometry": {"coordinates":[-121.20794100000001,38.669771],"type":"Point"}
}