{
  "type": "Feature",
  "properties": {
    "iso:country":"US",
    "sg:address":"63 Partridge Dr",
    "sg:city":"Novato",
    "sg:classifiers":[
        {
            "category":"Professional",
            "type":"Services"
        }
    ],
    "sg:phone":"+1 415 898 0095",
    "sg:postcode":"94945",
    "sg:province":"CA",
    "wof:name":"Marty Allen",
    "wof:placetype":"venue"
},
  "geometry": {"coordinates":[-122.584873,38.124185],"type":"Point"}
}