{
  "type": "Feature",
  "properties": {
    "addr:full":"305 McHenry Ave Modesto CA 95354",
    "addr:housenumber":"305",
    "addr:postcode":"ca 95354",
    "addr:street":"Mchenry Ave",
    "iso:country":"US",
    "sg:address":"305 McHenry Ave",
    "sg:city":"Modesto",
    "sg:classifiers":[
        {
            "category":"Utilities",
            "subcategory":"Mobile Phone",
            "type":"Services"
        }
    ],
    "sg:phone":"+1 209 526 8896",
    "sg:postcode":"95354",
    "sg:province":"CA",
    "sg:tags":[
        "telephone",
        "cellular"
    ],
    "wof:name":"World Page Wireless",
    "wof:placetype":"venue"
},
  "geometry": {"coordinates":[-120.99400300000001,37.648201],"type":"Point"}
}