{
  "type": "Feature",
  "properties": {
    "addr:full":"220 Huff St Vista CA 92083",
    "addr:housenumber":"220",
    "addr:postcode":"92083",
    "addr:street":"Huff St",
    "iso:country":"US",
    "sg:address":"220 Huff St",
    "sg:city":"Vista",
    "sg:classifiers":[
        {
            "category":"Retail",
            "subcategory":"Storage",
            "type":"Services"
        }
    ],
    "sg:phone":"+1 760 726 4006",
    "sg:postcode":"92083",
    "sg:province":"CA",
    "sg:tags":[
        "self"
    ],
    "wof:name":"Emerald At 78 Self Storage",
    "wof:placetype":"venue"
},
  "geometry": {"coordinates":[-117.277,33.1936],"type":"Point"}
}