{
  "type": "Feature",
  "properties": {
    "addr:full":"5248 W 142nd Pl Hawthorne CA 90250",
    "addr:housenumber":"5248",
    "addr:postcode":"90250",
    "addr:street":"W 142Nd Pl",
    "iso:country":"US",
    "sg:address":"5248 W 142nd Pl",
    "sg:city":"Hawthorne",
    "sg:classifiers":[
        {
            "category":"Autos & Motor Vehicles",
            "subcategory":"Auto Supplies",
            "type":"Retail Goods"
        }
    ],
    "sg:phone":"+1 949 235 2484",
    "sg:postcode":"90250",
    "sg:province":"CA",
    "wof:name":"Bullit Motorsports",
    "wof:placetype":"venue"
},
  "geometry": {"coordinates":[-118.37227,33.903014],"type":"Point"}
}