{
  "type": "Feature",
  "properties": {
    "iso:country":"US",
    "sg:address":"1485 Spruce St",
    "sg:city":"Riverside",
    "sg:classifiers":[
        {
            "category":"Real Estate",
            "subcategory":"Real Estate Agent",
            "type":"Services"
        }
    ],
    "sg:phone":"+1 951 686 7000",
    "sg:postcode":"92507",
    "sg:province":"CA",
    "wof:name":"Landpro",
    "wof:placetype":"venue"
},
  "geometry": {"coordinates":[-117.34267,33.990365],"type":"Point"}
}