{
  "type": "Feature",
  "properties": {
    "iso:country":"US",
    "sg:address":"34274 Co Rd 20",
    "sg:city":"Woodland",
    "sg:classifiers":[
        {
            "category":"Recreation",
            "type":"Entertainment"
        },
        {
            "category":"Retail",
            "subcategory":"Animal Services",
            "type":"Services"
        }
    ],
    "sg:phone":"+1 530 661 1358",
    "sg:postcode":"95695",
    "sg:province":"CA",
    "sg:tags":[
        "stable"
    ],
    "sg:website":"www.woodlandstallion.com",
    "wof:name":"Woodland Stallion Station",
    "wof:placetype":"venue"
},
  "geometry": {"coordinates":[-121.869538,38.691457],"type":"Point"}
}