{
  "type": "Feature",
  "properties": {
    "addr:full":"3701 Stevens Creek Boulevard Santa Clara CA 95051",
    "addr:housenumber":"3701",
    "addr:postcode":"95051",
    "addr:street":"Stevens Creek Boulevard",
    "iso:country":"US",
    "sg:address":"3701 Stevens Creek Boulevard",
    "sg:city":"Santa Clara",
    "sg:classifiers":[
        {
            "category":"Retail",
            "subcategory":"Auto Rental",
            "type":"Services"
        }
    ],
    "sg:phone":"+1 408 241 4453",
    "sg:postcode":"95051",
    "sg:province":"CA",
    "sg:tags":[
        "car"
    ],
    "wof:name":"Ford Rent-A-Car Systems",
    "wof:placetype":"venue"
},
  "geometry": {"coordinates":[-121.964631,37.323209],"type":"Point"}
}