{
  "type": "Feature",
  "properties": {
    "iso:country":"US",
    "sg:address":"9581 Slauson Ave",
    "sg:city":"Pico Rivera",
    "sg:classifiers":[
        {
            "category":"Wholesale",
            "subcategory":"Medical Equipment & Supplies",
            "type":"Manufacturing & Wholesale Goods"
        }
    ],
    "sg:phone":"+1 562 949 6665",
    "sg:postcode":"90660",
    "sg:province":"CA",
    "sg:tags":[
        "physician",
        "surgeon"
    ],
    "wof:name":"Mora Medical Distributors",
    "wof:placetype":"venue"
},
  "geometry": {"coordinates":[-118.094498,33.967729],"type":"Point"}
}