{
  "type": "Feature",
  "properties": {
    "addr:full":"13006 Halldale Ave Gardena CA 90249",
    "addr:housenumber":"13006",
    "addr:postcode":"90249",
    "addr:street":"Halldale Ave",
    "iso:country":"US",
    "sg:address":"13006 Halldale Ave",
    "sg:city":"Gardena",
    "sg:classifiers":[
        {
            "category":"Wholesale",
            "subcategory":"Durable Goods & Equipment",
            "type":"Manufacturing & Wholesale Goods"
        }
    ],
    "sg:phone":"+1 310 516 9947",
    "sg:postcode":"90249",
    "sg:province":"CA",
    "sg:tags":[
        "importer"
    ],
    "sg:website":"www.royaltrend.com",
    "wof:name":"Royal Trend Inc",
    "wof:placetype":"venue"
},
  "geometry": {"coordinates":[-118.30221400000001,33.912697],"type":"Point"}
}