{
  "type": "Feature",
  "properties": {
    "iso:country":"US",
    "sg:address":"11150 Santa Monica Blvd",
    "sg:city":"Los Angeles",
    "sg:classifiers":[
        {
            "category":"Banks & Credit Unions",
            "subcategory":"Investment Brokerage",
            "type":"Services"
        }
    ],
    "sg:phone":"+1 310 914 7799",
    "sg:postcode":"90025",
    "sg:province":"CA",
    "sg:tags":[
        "security"
    ],
    "wof:name":"Rbc Dain Rauscher Corporation",
    "wof:placetype":"venue"
},
  "geometry": {"coordinates":[-118.445194,34.047377],"type":"Point"}
}