{
  "type": "Feature",
  "properties": {
    "iso:country":"US",
    "sg:address":"2725 Center Ave",
    "sg:city":"Richmond",
    "sg:classifiers":[
        {
            "category":"Building & Trades",
            "subcategory":"Construction",
            "type":"Services"
        }
    ],
    "sg:phone":"+1 510 932 6945",
    "sg:postcode":"94804",
    "sg:province":"CA",
    "sg:tags":[
        "repair",
        "handyman",
        "maintenance",
        "home"
    ],
    "wof:name":"West Island Handyman",
    "wof:placetype":"venue"
},
  "geometry": {"coordinates":[-122.344138,37.930191],"type":"Point"}
}