{
  "type": "Feature",
  "properties": {
    "iso:country":"US",
    "sg:address":"46 Peninsula Center",
    "sg:city":"Rolling Hills Estate",
    "sg:classifiers":[
        {
            "category":"Coffee & Tea",
            "type":"Food & Drink"
        }
    ],
    "sg:phone":"+1 310 544 3942",
    "sg:postcode":"90274",
    "sg:province":"CA",
    "wof:name":"Starbucks Coffee",
    "wof:placetype":"venue"
},
  "geometry": {"coordinates":[-118.37599400000001,33.775042],"type":"Point"}
}