{
  "type": "Feature",
  "properties": {
    "addr:full":"1135 N Summit Ave Pasadena CA 91103",
    "addr:housenumber":"1135",
    "addr:postcode":"91103",
    "addr:street":"N Summit Ave",
    "iso:country":"US",
    "sg:address":"1135 N Summit Ave",
    "sg:city":"Pasadena",
    "sg:classifiers":[
        {
            "category":"Food & Beverages",
            "subcategory":"Groceries & Convenience Stores",
            "type":"Retail Goods"
        }
    ],
    "sg:phone":"+1 626 296 0238",
    "sg:postcode":"91103",
    "sg:province":"CA",
    "sg:tags":[
        "grocer"
    ],
    "wof:name":"LA Bodeguita Mini Market",
    "wof:placetype":"venue"
},
  "geometry": {"coordinates":[-118.147706,34.166924],"type":"Point"}
}