{
  "type": "Feature",
  "properties": {
    "iso:country":"US",
    "sg:address":"2234 Honolulu Ave",
    "sg:city":"Montrose",
    "sg:classifiers":[
        {
            "category":"Personal",
            "subcategory":"Beauty Salon",
            "type":"Services"
        }
    ],
    "sg:phone":"+1 818 249 3966",
    "sg:postcode":"91020",
    "sg:province":"CA",
    "sg:tags":[
        "hair"
    ],
    "wof:name":"Expressions For Hair & Nails",
    "wof:placetype":"venue"
},
  "geometry": {"coordinates":[-118.225998,34.205299],"type":"Point"}
}