{
  "type": "Feature",
  "properties": {
    "addr:full":"716 W Richbrook Dr Claremont CA 91711",
    "addr:housenumber":"716",
    "addr:postcode":"91711",
    "addr:street":"W Richbrook Dr",
    "iso:country":"US",
    "sg:address":"716 W Richbrook Dr",
    "sg:city":"Claremont",
    "sg:classifiers":[
        {
            "category":"Food & Beverages",
            "subcategory":"Groceries & Convenience Stores",
            "type":"Retail Goods"
        }
    ],
    "sg:phone":"+1 626 335 1068",
    "sg:postcode":"91711",
    "sg:province":"CA",
    "sg:tags":[
        "grocer"
    ],
    "wof:name":"Finkbiners Market",
    "wof:placetype":"venue"
},
  "geometry": {"coordinates":[-117.737531,34.105598],"type":"Point"}
}