{
  "type": "Feature",
  "properties": {
    "addr:full":"11227 Amboy Ave San Fernando CA 91340",
    "addr:housenumber":"11227",
    "addr:postcode":"91340",
    "addr:street":"Amboy Ave",
    "iso:country":"US",
    "sg:address":"11227 Amboy Ave",
    "sg:city":"San Fernando",
    "sg:classifiers":[
        {
            "category":"Building & Trades",
            "subcategory":"Cleaning & Sanitation",
            "type":"Services"
        }
    ],
    "sg:phone":"+1 818 898 2290",
    "sg:postcode":"91340",
    "sg:province":"CA",
    "sg:tags":[
        "janitor"
    ],
    "wof:name":"Royal Building Janitorial Svc",
    "wof:placetype":"venue"
},
  "geometry": {"coordinates":[-118.444654,34.273841],"type":"Point"}
}