{
  "type": "Feature",
  "properties": {
    "addr:full":"745 Cherry St Chico CA 95928",
    "addr:housenumber":"745",
    "addr:postcode":"95928",
    "addr:street":"Cherry St",
    "iso:country":"US",
    "sg:address":"745 Cherry St",
    "sg:city":"Chico",
    "sg:classifiers":[
        {
            "category":"Home & Garden",
            "subcategory":"Home Furnishings",
            "type":"Retail Goods"
        },
        {
            "category":"Building & Trades",
            "subcategory":"Construction",
            "type":"Services"
        },
        {
            "category":"Home & Garden",
            "subcategory":"Building Materials",
            "type":"Retail Goods"
        },
        {
            "category":"Retail",
            "subcategory":"Auto Repair",
            "type":"Services"
        },
        {
            "category":"Manufacturing",
            "subcategory":"Glass & Minerals",
            "type":"Manufacturing & Wholesale Goods"
        },
        {
            "category":"Manufacturing",
            "subcategory":"Building Materials",
            "type":"Manufacturing & Wholesale Goods"
        }
    ],
    "sg:phone":"+1 530 343 7934",
    "sg:postcode":"95928",
    "sg:province":"CA",
    "sg:tags":[
        "plate",
        "installation",
        "windows-repair",
        "screen",
        "glass-auto",
        "doors-vinyl",
        "shower",
        "window",
        "mirror",
        "door",
        "windshield",
        "enclosure",
        "replacement"
    ],
    "sg:website":"http://millerglass.com/",
    "wof:name":"Miller Glass Inc.",
    "wof:placetype":"venue"
},
  "geometry": {"coordinates":[-121.84258699999999,39.722219],"type":"Point"}
}