{
  "type": "Feature",
  "properties": {
    "addr:full":"1783 N Victory Pl Burbank CA 91504",
    "addr:housenumber":"1783",
    "addr:postcode":"91504",
    "addr:street":"N Victory Pl",
    "iso:country":"US",
    "sg:address":"1783 N Victory Pl",
    "sg:city":"Burbank",
    "sg:classifiers":[
        {
            "category":"Shopping",
            "subcategory":"Hobbies, Toys, & Games",
            "type":"Retail Goods"
        },
        {
            "category":"Cinema",
            "subcategory":"Movie Rental",
            "type":"Entertainment"
        },
        {
            "category":"Shopping",
            "subcategory":"Computers & Home Electronics",
            "type":"Retail Goods"
        }
    ],
    "sg:phone":"+1 818 565 0409",
    "sg:postcode":"91504",
    "sg:province":"CA",
    "sg:tags":[
        "toy",
        "video",
        "store"
    ],
    "sg:website":"www.gamestop.com",
    "wof:name":"Game Stop",
    "wof:placetype":"venue"
},
  "geometry": {"coordinates":[-118.32912399999999,34.191882],"type":"Point"}
}