{
  "type": "Feature",
  "properties": {
    "iso:country":"US",
    "sg:address":"902 Carmel Avenue",
    "sg:city":"Albany",
    "sg:classifiers":[
        {
            "category":"Health Services",
            "subcategory":"Clinic",
            "type":"Services"
        }
    ],
    "sg:phone":"+1 510 277 0456",
    "sg:postcode":"94706",
    "sg:province":"CA",
    "sg:tags":[
        "counseling",
        "mental"
    ],
    "sg:website":"LaDouceurMFT.com",
    "wof:name":"Pat LaDouceur, MFT",
    "wof:placetype":"venue"
},
  "geometry": {"coordinates":[-122.289883,37.890394],"type":"Point"}
}