{
  "type": "Feature",
  "properties": {
    "addr:full":"2218 E 92nd St Los Angeles CA 90002",
    "addr:housenumber":"2218",
    "addr:postcode":"90002",
    "addr:street":"E 92Nd St",
    "iso:country":"US",
    "sg:address":"2218 E 92nd St",
    "sg:city":"Los Angeles",
    "sg:classifiers":[
        {
            "category":"Autos & Motor Vehicles",
            "subcategory":"Auto Supplies",
            "type":"Retail Goods"
        }
    ],
    "sg:phone":"+1 323 564 1457",
    "sg:postcode":"90002",
    "sg:province":"CA",
    "sg:tags":[
        "automotive",
        "part",
        "used",
        "new"
    ],
    "wof:name":"All Toyota Auto",
    "wof:placetype":"venue"
},
  "geometry": {"coordinates":[-118.23197399999999,33.952942],"type":"Point"}
}