{
  "type": "Feature",
  "properties": {
    "iso:country":"US",
    "sg:address":"28 Arden Ct",
    "sg:city":"Redwood City",
    "sg:classifiers":[
        {
            "category":"Building & Trades",
            "subcategory":"Construction",
            "type":"Services"
        }
    ],
    "sg:phone":"+1 650 556 9780",
    "sg:postcode":"94061",
    "sg:province":"CA",
    "sg:tags":[
        "contractor"
    ],
    "wof:name":"Oks Raingutter Service",
    "wof:placetype":"venue"
},
  "geometry": {"coordinates":[-122.22926,37.472194],"type":"Point"}
}