{
  "type": "Feature",
  "properties": {
    "addr:full":"823 Wall St Los Angeles CA 90014",
    "addr:housenumber":"823",
    "addr:postcode":"90014",
    "addr:street":"Wall St",
    "iso:country":"US",
    "sg:address":"823 Wall St",
    "sg:city":"Los Angeles",
    "sg:classifiers":[
        {
            "category":"Home & Garden",
            "subcategory":"Carpets & Floor Coverings",
            "type":"Retail Goods"
        }
    ],
    "sg:phone":"+1 213 489 2231",
    "sg:postcode":"90014",
    "sg:province":"CA",
    "sg:tags":[
        "dealer",
        "rug"
    ],
    "wof:name":"Angel Rugs",
    "wof:placetype":"venue"
},
  "geometry": {"coordinates":[-118.251671,34.039094],"type":"Point"}
}