{
  "type": "Feature",
  "properties": {
    "addr:full":"15792 Washington Ave San Lorenzo CA 94580",
    "addr:housenumber":"15792",
    "addr:postcode":"94580",
    "addr:street":"Washington Ave",
    "iso:country":"US",
    "sg:address":"15792 Washington Ave",
    "sg:city":"San Lorenzo",
    "sg:classifiers":[
        {
            "category":"Freight",
            "type":"Transportation"
        }
    ],
    "sg:phone":"+1 510 232 3471",
    "sg:postcode":"94580",
    "sg:province":"CA",
    "sg:tags":[
        "trucking"
    ],
    "wof:name":"Crossroad Trucking & Transport",
    "wof:placetype":"venue"
},
  "geometry": {"coordinates":[-122.13696299999999,37.679748],"type":"Point"}
}