{
  "type": "Feature",
  "properties": {
    "iso:country":"US",
    "sg:address":"5303 Lankershim Blvd",
    "sg:city":"North Hollywood",
    "sg:classifiers":[
        {
            "category":"Health Services",
            "subcategory":"Clinic",
            "type":"Services"
        }
    ],
    "sg:phone":"+1 818 505 0976",
    "sg:postcode":"91601",
    "sg:province":"CA",
    "wof:name":"Sensual Health Inst & Clinic",
    "wof:placetype":"venue"
},
  "geometry": {"coordinates":[-118.376614,34.168018],"type":"Point"}
}