{
  "type": "Feature",
  "properties": {
    "iso:country":"US",
    "sg:address":"1225 S Bon View Ave",
    "sg:city":"Ontario",
    "sg:classifiers":[
        {
            "category":"Manufacturing",
            "subcategory":"Tools & Machinery",
            "type":"Manufacturing & Wholesale Goods"
        }
    ],
    "sg:phone":"+1 909 923 5311",
    "sg:postcode":"91761",
    "sg:province":"CA",
    "sg:tags":[
        "machine",
        "shop"
    ],
    "wof:name":"Ogaz Enterprises Inc",
    "wof:placetype":"venue"
},
  "geometry": {"coordinates":[-117.637291,34.051251],"type":"Point"}
}