{
  "type": "Feature",
  "properties": {
    "iso:country":"US",
    "sg:address":"2236 Oak Grove Rd",
    "sg:city":"Walnut Creek",
    "sg:classifiers":[
        {
            "category":"Manufacturing",
            "subcategory":"Printing",
            "type":"Manufacturing & Wholesale Goods"
        }
    ],
    "sg:phone":"+1 925 932 6107",
    "sg:postcode":"94598",
    "sg:province":"CA",
    "sg:tags":[
        "lithographic",
        "commercial"
    ],
    "wof:name":"We Can Do It Printing",
    "wof:placetype":"venue"
},
  "geometry": {"coordinates":[-122.016296,37.929376],"type":"Point"}
}