{
  "type": "Feature",
  "properties": {
    "addr:full":"845 E Fern Ave Fresno CA 93728",
    "addr:housenumber":"845",
    "addr:postcode":"93728",
    "addr:street":"E Fern Ave",
    "iso:country":"US",
    "sg:address":"845 E Fern Ave",
    "sg:city":"Fresno",
    "sg:classifiers":[
        {
            "category":"Shopping",
            "subcategory":"Books",
            "type":"Retail Goods"
        }
    ],
    "sg:phone":"+1 559 441 7107",
    "sg:postcode":"93728",
    "sg:province":"CA",
    "sg:tags":[
        "dealer"
    ],
    "wof:name":"Brass Unicorn Inc",
    "wof:placetype":"venue"
},
  "geometry": {"coordinates":[-119.80014199999999,36.758776],"type":"Point"}
}