{
  "type": "Feature",
  "properties": {
    "addr:full":"5723 Byron Ct Rocklin CA 95765",
    "addr:housenumber":"5723",
    "addr:postcode":"95765",
    "addr:street":"Byron Ct",
    "iso:country":"US",
    "sg:address":"5723 Byron Ct",
    "sg:city":"Rocklin",
    "sg:classifiers":[
        {
            "category":"Building & Trades",
            "subcategory":"Landscaping Services",
            "type":"Services"
        }
    ],
    "sg:phone":"+1 916 632 2339",
    "sg:postcode":"95765",
    "sg:province":"CA",
    "sg:tags":[
        "landscape"
    ],
    "wof:name":"Valenzuela Landscape",
    "wof:placetype":"venue"
},
  "geometry": {"coordinates":[-121.26632600000001,38.808918],"type":"Point"}
}