{
  "type": "Feature",
  "properties": {
    "iso:country":"US",
    "sg:address":"177 Webster St",
    "sg:city":"Monterey",
    "sg:classifiers":[
        {
            "category":"Insurance",
            "subcategory":"Hazard Insurance",
            "type":"Services"
        }
    ],
    "sg:phone":"+1 831 394 9201",
    "sg:postcode":"93940",
    "sg:province":"CA",
    "sg:tags":[
        "bond"
    ],
    "wof:name":"John Davis Bail Bonds",
    "wof:placetype":"venue"
},
  "geometry": {"coordinates":[-121.894138,36.596169],"type":"Point"}
}