{
  "type": "Feature",
  "properties": {
    "iso:country":"US",
    "sg:address":"16 Technology Dr Ste 165",
    "sg:city":"Irvine",
    "sg:classifiers":[
        {
            "category":"Retail",
            "subcategory":"Repair Shop",
            "type":"Services"
        },
        {
            "category":"Shopping",
            "subcategory":"Music",
            "type":"Retail Goods"
        }
    ],
    "sg:phone":"+1 949 885 0624",
    "sg:postcode":"92618",
    "sg:province":"CA",
    "sg:tags":[
        "electronics",
        "dvd's"
    ],
    "sg:website":"www.rhousemedia.com",
    "wof:name":"Rhousemedia",
    "wof:placetype":"venue"
},
  "geometry": {"coordinates":[-117.73680899999999,33.649851],"type":"Point"}
}