{
  "type": "Feature",
  "properties": {
    "iso:country":"US",
    "sg:address":"100 Wilshire Blvd",
    "sg:city":"Santa Monica",
    "sg:classifiers":[
        {
            "category":"Professional",
            "subcategory":"Computer Services",
            "type":"Services"
        }
    ],
    "sg:phone":"+1 310 260 5001",
    "sg:postcode":"90401",
    "sg:province":"CA",
    "sg:tags":[
        "home",
        "consulting",
        "page",
        "dev",
        "internet"
    ],
    "wof:name":"Web Choice TV",
    "wof:placetype":"venue"
},
  "geometry": {"coordinates":[-118.500187,34.017575],"type":"Point"}
}