{
  "type": "Feature",
  "properties": {
    "iso:country":"US",
    "sg:address":"245 Fischer Ave",
    "sg:city":"Costa Mesa",
    "sg:classifiers":[
        {
            "category":"Insurance",
            "subcategory":"Insurance Agent",
            "type":"Services"
        }
    ],
    "sg:phone":"+1 714 444 3359",
    "sg:postcode":"92626",
    "sg:province":"CA",
    "sg:website":"www.cmgis.com",
    "wof:name":"Clarke Garvey Insurance Svc",
    "wof:placetype":"venue"
},
  "geometry": {"coordinates":[-117.87963000000001,33.675803],"type":"Point"}
}