{
  "type": "Feature",
  "properties": {
    "addr:full":"3858 Fruitvale Ave Bakersfield CA 93308",
    "addr:housenumber":"3858",
    "addr:postcode":"93308",
    "addr:street":"Fruitvale Ave",
    "iso:country":"US",
    "sg:address":"3858 Fruitvale Ave",
    "sg:city":"Bakersfield",
    "sg:classifiers":[
        {
            "category":"Professional",
            "subcategory":"Business Services",
            "type":"Services"
        }
    ],
    "sg:phone":"+1 661 588 6933",
    "sg:postcode":"93308",
    "sg:province":"CA",
    "sg:tags":[
        "development",
        "product",
        "designers-industrial",
        "marketing",
        "commercial",
        "design"
    ],
    "wof:name":"Design Group",
    "wof:placetype":"venue"
},
  "geometry": {"coordinates":[-119.07435099999999,35.394655],"type":"Point"}
}