{
  "type": "Feature",
  "properties": {
    "addr:full":"8474 W 3rd St Los Angeles CA 90048",
    "addr:housenumber":"8474",
    "addr:postcode":"90048",
    "addr:street":"W 3Rd St",
    "iso:country":"US",
    "sg:address":"8474 W 3rd St",
    "sg:city":"Los Angeles",
    "sg:classifiers":[
        {
            "category":"Restaurant",
            "type":"Food & Drink"
        }
    ],
    "sg:phone":"+1 323 852 8900",
    "sg:postcode":"90048",
    "sg:province":"CA",
    "sg:tags":[
        "indian"
    ],
    "sg:website":"www.holycowindianexpress.com",
    "wof:name":"Holy Cow",
    "wof:placetype":"venue"
},
  "geometry": {"coordinates":[-118.375421,34.072935],"type":"Point"}
}