{
  "type": "Feature",
  "properties": {
    "iso:country":"US",
    "sg:address":"19919 Van Exel Rd",
    "sg:city":"Lodi",
    "sg:phone":"+1 209 369 3371",
    "sg:postcode":"95242",
    "sg:province":"CA",
    "sg:tags":[
        "farm",
        "corn",
        "cash",
        "crop",
        "field",
        "grain"
    ],
    "wof:name":"Van Exel Farms Inc",
    "wof:placetype":"venue"
},
  "geometry": {"coordinates":[-121.400361,38.161055],"type":"Point"}
}