{
  "type": "Feature",
  "properties": {
    "addr:full":"651 Brannan St Ste 410 San Francisco CA 94110",
    "addr:housenumber":"651",
    "addr:postcode":"94110",
    "addr:street":"Brannan St Ste 410",
    "iso:country":"US",
    "sg:address":"651 Brannan St Ste 410",
    "sg:city":"San Francisco",
    "sg:classifiers":[
        {
            "category":"Communications",
            "subcategory":"Film & Video Production",
            "type":"Services"
        },
        {
            "category":"Organizations",
            "subcategory":"Non-profit Organization",
            "type":"Services"
        }
    ],
    "sg:phone":"+1 415 356 8383",
    "sg:postcode":"94110",
    "sg:province":"CA",
    "sg:tags":[
        "video/film",
        "service/non-profit",
        "community"
    ],
    "sg:website":"www.itvs.org",
    "wof:name":"Independent Television Service",
    "wof:placetype":"venue"
},
  "geometry": {"coordinates":[-122.40086599999999,37.774873],"type":"Point"}
}