{
  "type": "Feature",
  "properties": {
    "addr:full":"2313 el Cajon Blvd San Diego CA 92104",
    "addr:housenumber":"2313",
    "addr:postcode":"92104",
    "addr:street":"El Cajon Blvd",
    "iso:country":"US",
    "sg:address":"2313 el Cajon Blvd",
    "sg:city":"San Diego",
    "sg:classifiers":[
        {
            "category":"Health Services",
            "subcategory":"Clinic",
            "type":"Services"
        }
    ],
    "sg:phone":"+1 619 718 6401",
    "sg:postcode":"92104",
    "sg:province":"CA",
    "sg:tags":[
        "aids",
        "testing",
        "information"
    ],
    "wof:name":"Holistic Aids Response Program",
    "wof:placetype":"venue"
},
  "geometry": {"coordinates":[-117.138949,32.7552],"type":"Point"}
}