{
  "type": "Feature",
  "properties": {
    "addr:full":"4304 Crenshaw Blvd Los Angeles CA 90008",
    "addr:housenumber":"4304",
    "addr:postcode":"90008",
    "addr:street":"Crenshaw Blvd",
    "iso:country":"US",
    "sg:address":"4304 Crenshaw Blvd",
    "sg:city":"Los Angeles",
    "sg:classifiers":[
        {
            "category":"Insurance",
            "subcategory":"Insurance Agent",
            "type":"Services"
        }
    ],
    "sg:phone":"+1 323 295 4458",
    "sg:postcode":"90008",
    "sg:province":"CA",
    "wof:name":"Budget Insurance",
    "wof:placetype":"venue"
},
  "geometry": {"coordinates":[-118.332688,34.004368],"type":"Point"}
}