{
  "type": "Feature",
  "properties": {
    "addr:full":"3800 Griffith Avenue Los Angeles CA 90011",
    "addr:housenumber":"3800",
    "addr:postcode":"90011",
    "addr:street":"Griffith Avenue",
    "iso:country":"US",
    "sg:address":"3800 Griffith Avenue",
    "sg:city":"Los Angeles",
    "sg:classifiers":[
        {
            "category":"Building & Trades",
            "subcategory":"Plumbing",
            "type":"Services"
        }
    ],
    "sg:phone":"+1 323 233 9436",
    "sg:postcode":"90011",
    "sg:province":"CA",
    "wof:name":"M Brothers Plumbing & Maintenance",
    "wof:placetype":"venue"
},
  "geometry": {"coordinates":[-118.262677,34.011949],"type":"Point"}
}