{
  "type": "Feature",
  "properties": {
    "iso:country":"US",
    "sg:address":"1320 Deerpark Dr Apt 18",
    "sg:city":"Fullerton",
    "sg:classifiers":[
        {
            "category":"Place Of Worship",
            "type":"Public Place"
        },
        {
            "category":"Education",
            "subcategory":"School",
            "type":"Public Place"
        },
        {
            "category":"Organizations",
            "subcategory":"Community Association",
            "type":"Services"
        }
    ],
    "sg:phone":"+1 714 223 6918",
    "sg:postcode":"92831",
    "sg:province":"CA",
    "sg:tags":[
        "consultant",
        "spiritual",
        "religious",
        "interest",
        "church"
    ],
    "wof:name":"Grace Revival Ctr Church",
    "wof:placetype":"venue"
},
  "geometry": {"coordinates":[-117.878117,33.884217],"type":"Point"}
}