{
  "type": "Feature",
  "properties": {
    "iso:country":"US",
    "sg:address":"301 Van Ness Ave",
    "sg:city":"Fresno",
    "sg:classifiers":[
        {
            "category":"Professional",
            "type":"Services"
        },
        {
            "category":"Personal",
            "type":"Services"
        }
    ],
    "sg:phone":"+1 866 761 6402",
    "sg:postcode":"93721",
    "sg:province":"CA",
    "sg:tags":[
        "industrial",
        "organ",
        "material",
        "storage",
        "movers-commercial",
        "full",
        "moving",
        "services-labor",
        "mover",
        "piano"
    ],
    "sg:website":"https://ecom-bekins-com.netsolads.com/householdmove/action/autoSelectAgent.do?leadSourceCode=35&_nsag=31476",
    "wof:name":"Fresno Bekins",
    "wof:placetype":"venue"
},
  "geometry": {"coordinates":[-119.781487,36.72768],"type":"Point"}
}