{
  "type": "Feature",
  "properties": {
    "iso:country":"US",
    "sg:address":"4565 N Golden State Blvd",
    "sg:city":"Fresno",
    "sg:classifiers":[
        {
            "category":"Education",
            "subcategory":"Special Training",
            "type":"Public Place"
        }
    ],
    "sg:phone":"+1 559 276 1220",
    "sg:postcode":"93722",
    "sg:province":"CA",
    "sg:website":"www.wptruckschool.com",
    "wof:name":"Western Pacific Truck School",
    "wof:placetype":"venue"
},
  "geometry": {"coordinates":[-119.869996,36.801279],"type":"Point"}
}