{
  "type": "Feature",
  "properties": {
    "iso:country":"US",
    "sg:address":"1809 Verdugo Blvd Ste 220",
    "sg:city":"Glendale",
    "sg:classifiers":[
        {
            "category":"Health Services",
            "subcategory":"Doctor",
            "type":"Services"
        }
    ],
    "sg:phone":"+1 818 790 1844",
    "sg:postcode":"91208",
    "sg:province":"CA",
    "sg:tags":[
        "surgeon",
        "oral"
    ],
    "wof:name":"Webber Kenneth W DDS",
    "wof:placetype":"venue"
},
  "geometry": {"coordinates":[-118.214996,34.2057],"type":"Point"}
}