{
  "type": "Feature",
  "properties": {
    "iso:country":"US",
    "sg:address":"2102 W 17th St",
    "sg:city":"Santa Ana",
    "sg:classifiers":[
        {
            "category":"Food & Beverages",
            "subcategory":"Liquor & Beverages",
            "type":"Retail Goods"
        },
        {
            "category":"Food & Beverages",
            "subcategory":"Groceries & Convenience Stores",
            "type":"Retail Goods"
        }
    ],
    "sg:phone":"+1 714 835 5655",
    "sg:postcode":"92706",
    "sg:province":"CA",
    "sg:tags":[
        "beer",
        "spirit",
        "wine"
    ],
    "wof:name":"King Food Store",
    "wof:placetype":"venue"
},
  "geometry": {"coordinates":[-117.899002,33.759701],"type":"Point"}
}