{
  "type": "Feature",
  "properties": {
    "iso:country":"US",
    "sg:address":"7547 Louise Ave",
    "sg:city":"Van Nuys",
    "sg:classifiers":[
        {
            "category":"Wholesale",
            "subcategory":"Jewelry",
            "type":"Manufacturing & Wholesale Goods"
        }
    ],
    "sg:phone":"+1 213 628 0252",
    "sg:postcode":"91406",
    "sg:province":"CA",
    "sg:tags":[
        "clocks"
    ],
    "sg:website":"www.ctclock.com",
    "wof:name":"Continental Time Clock Co",
    "wof:placetype":"venue"
},
  "geometry": {"coordinates":[-118.50993699999999,34.206305],"type":"Point"}
}