{
  "type": "Feature",
  "properties": {
    "addr:full":"3500 Garrett Dr Santa Clara CA 95054",
    "addr:housenumber":"3500",
    "addr:postcode":"95054",
    "addr:street":"Garrett Dr",
    "iso:country":"US",
    "sg:address":"3500 Garrett Dr",
    "sg:city":"Santa Clara",
    "sg:classifiers":[
        {
            "category":"Manufacturing",
            "subcategory":"Chemicals & Compounds",
            "type":"Manufacturing & Wholesale Goods"
        }
    ],
    "sg:phone":"+1 408 962 2000",
    "sg:postcode":"95054",
    "sg:province":"CA",
    "sg:tags":[
        "inorganic",
        "industrial",
        "mfg"
    ],
    "wof:name":"Honeywell",
    "wof:placetype":"venue"
},
  "geometry": {"coordinates":[-121.98538499999999,37.382248],"type":"Point"}
}