{
  "type": "Feature",
  "properties": {
    "iso:country":"US",
    "sg:address":"34 New Dawn Cir",
    "sg:city":"Chico",
    "sg:classifiers":[
        {
            "category":"Building & Trades",
            "subcategory":"Landscaping Services",
            "type":"Services"
        }
    ],
    "sg:phone":"+1 530 892 8845",
    "sg:postcode":"95928",
    "sg:province":"CA",
    "sg:tags":[
        "lawn",
        "maintenance"
    ],
    "wof:name":"Sequoia Lawn & Landscape",
    "wof:placetype":"venue"
},
  "geometry": {"coordinates":[-121.794298,39.722857],"type":"Point"}
}