{
  "type": "Feature",
  "properties": {
    "addr:full":"18802 Ambler Ave Carson CA 90746",
    "addr:housenumber":"18802",
    "addr:postcode":"90746",
    "addr:street":"Ambler Ave",
    "iso:country":"US",
    "sg:address":"18802 Ambler Ave",
    "sg:city":"Carson",
    "sg:classifiers":[
        {
            "category":"Wholesale",
            "subcategory":"Construction Materials",
            "type":"Manufacturing & Wholesale Goods"
        },
        {
            "category":"Home & Garden",
            "subcategory":"Building Materials",
            "type":"Retail Goods"
        }
    ],
    "sg:phone":"+1 310 864 2483",
    "sg:postcode":"90746",
    "sg:province":"CA",
    "sg:tags":[
        "windows-wholesale",
        "window",
        "manufacturer"
    ],
    "wof:name":"Chuy's Mobile Window Tint",
    "wof:placetype":"venue"
},
  "geometry": {"coordinates":[-118.269612,33.859877],"type":"Point"}
}