{
  "type": "Feature",
  "properties": {
    "addr:full":"201 N San Vicente Blvd Beverly Hills CA 90211",
    "addr:housenumber":"201",
    "addr:postcode":"90211",
    "addr:street":"N San Vicente Blvd",
    "iso:country":"US",
    "sg:address":"201 N San Vicente Blvd",
    "sg:city":"Beverly Hills",
    "sg:classifiers":[
        {
            "category":"Retail",
            "subcategory":"Auto Repair",
            "type":"Services"
        }
    ],
    "sg:phone":"+1 323 653 2823",
    "sg:postcode":"90211",
    "sg:province":"CA",
    "sg:tags":[
        "body",
        "automobile",
        "painting"
    ],
    "wof:name":"Beverly Hills Auto Body",
    "wof:placetype":"venue"
},
  "geometry": {"coordinates":[-118.375426,34.069294],"type":"Point"}
}