{
  "type": "Feature",
  "properties": {
    "iso:country":"US",
    "sg:address":"1335 E 6th St",
    "sg:city":"Corona",
    "sg:classifiers":[
        {
            "category":"Professional",
            "subcategory":"Business Services",
            "type":"Services"
        }
    ],
    "sg:phone":"+1 951 273 1521",
    "sg:postcode":"92879",
    "sg:province":"CA",
    "sg:tags":[
        "commercial",
        "designers-industrial"
    ],
    "sg:website":"http://www.vintagedesigns.com",
    "wof:name":"Vintage Design Inc",
    "wof:placetype":"venue"
},
  "geometry": {"coordinates":[-117.544061,33.874327],"type":"Point"}
}