{
  "type": "Feature",
  "properties": {
    "addr:full":"55 Executive Ave Rohnert Park CA 94928",
    "addr:housenumber":"55",
    "addr:postcode":"94928",
    "addr:street":"Executive Ave",
    "iso:country":"US",
    "sg:address":"55 Executive Ave",
    "sg:city":"Rohnert Park",
    "sg:classifiers":[
        {
            "category":"Building & Trades",
            "subcategory":"Pest Control",
            "type":"Services"
        }
    ],
    "sg:phone":"+1 707 584 5758",
    "sg:postcode":"94928",
    "sg:province":"CA",
    "wof:name":"Aaron's Army Pest Patrol",
    "wof:placetype":"venue"
},
  "geometry": {"coordinates":[-122.709172,38.355358],"type":"Point"}
}