{
  "type": "Feature",
  "properties": {
    "addr:full":"19626 Green Mountain Dr Newhall CA 91321",
    "addr:housenumber":"19626",
    "addr:postcode":"91321",
    "addr:street":"Green Mountain Dr",
    "iso:country":"US",
    "sg:address":"19626 Green Mountain Dr",
    "sg:city":"Newhall",
    "sg:classifiers":[
        {
            "category":"Recreation",
            "type":"Entertainment"
        }
    ],
    "sg:phone":"+1 661 367 6962",
    "sg:postcode":"91321",
    "sg:province":"CA",
    "sg:tags":[
        "entertainers-family",
        "business"
    ],
    "wof:name":"Green Entertainment Technologies",
    "wof:placetype":"venue"
},
  "geometry": {"coordinates":[-118.478228,34.394088],"type":"Point"}
}