{
  "type": "Feature",
  "properties": {
    "iso:country":"US",
    "sg:address":"18 E Main St",
    "sg:city":"Los Gatos",
    "sg:classifiers":[
        {
            "category":"Real Estate",
            "subcategory":"Real Estate Services",
            "type":"Services"
        }
    ],
    "sg:phone":"+1 408 395 3122",
    "sg:postcode":"95030",
    "sg:province":"CA",
    "wof:name":"Maas Cliff Realtor",
    "wof:placetype":"venue"
},
  "geometry": {"coordinates":[-121.98200199999999,37.221199],"type":"Point"}
}