{
  "type": "Feature",
  "properties": {
    "addr:full":"4000 Rio Rd Apt 45 Carmel CA 93923",
    "addr:housenumber":"4000;45",
    "addr:postcode":"93923",
    "addr:street":"Rio Rd Apt",
    "iso:country":"US",
    "sg:address":"4000 Rio Rd Apt 45",
    "sg:city":"Carmel",
    "sg:classifiers":[
        {
            "category":"Building & Trades",
            "subcategory":"Construction",
            "type":"Services"
        }
    ],
    "sg:phone":"+1 831 625 2034",
    "sg:postcode":"93923",
    "sg:province":"CA",
    "sg:tags":[
        "repair",
        "handyman",
        "maintenance",
        "home"
    ],
    "wof:name":"Daniel Harnish Handyman",
    "wof:placetype":"venue"
},
  "geometry": {"coordinates":[-121.903282,36.538132],"type":"Point"}
}