{
  "type": "Feature",
  "properties": {
    "addr:full":"154 Berth Wilmington CA 90744",
    "addr:housenumber":"154",
    "addr:postcode":"90744",
    "addr:street":"Berth",
    "iso:country":"US",
    "sg:address":"154 Berth",
    "sg:city":"Wilmington",
    "sg:classifiers":[
        {
            "category":"Freight",
            "type":"Transportation"
        }
    ],
    "sg:phone":"+1 310 513 6680",
    "sg:postcode":"90744",
    "sg:province":"CA",
    "sg:tags":[
        "terminal",
        "operations",
        "marine"
    ],
    "wof:name":"Marine Terminals Corporation",
    "wof:placetype":"venue"
},
  "geometry": {"coordinates":[-118.261898,33.761445],"type":"Point"}
}