{
  "type": "Feature",
  "properties": {
    "iso:country":"US",
    "sg:address":"22840 Antelope Blvd",
    "sg:city":"Red Bluff",
    "sg:classifiers":[
        {
            "category":"Government",
            "subcategory":"Office",
            "type":"Public Place"
        }
    ],
    "sg:phone":"+1 530 527 9416",
    "sg:postcode":"96080",
    "sg:province":"CA",
    "sg:tags":[
        "county",
        "resource"
    ],
    "wof:name":"Tehama County Child Protective",
    "wof:placetype":"venue"
},
  "geometry": {"coordinates":[-122.189392,40.185768],"type":"Point"}
}