{
  "type": "Feature",
  "properties": {
    "addr:full":"6433 Alondra Blvd Paramount CA 90723",
    "addr:housenumber":"6433",
    "addr:postcode":"90723",
    "addr:street":"Alondra Blvd",
    "iso:country":"US",
    "sg:address":"6433 Alondra Blvd",
    "sg:city":"Paramount",
    "sg:classifiers":[
        {
            "category":"Shopping",
            "subcategory":"Beauty & Cosmetics",
            "type":"Retail Goods"
        }
    ],
    "sg:phone":"+1 562 531 8054",
    "sg:postcode":"90723",
    "sg:province":"CA",
    "sg:tags":[
        "supply"
    ],
    "wof:name":"Kum Kang Trading USA Inc",
    "wof:placetype":"venue"
},
  "geometry": {"coordinates":[-118.18499799999999,33.889301],"type":"Point"}
}