{
  "type": "Feature",
  "properties": {
    "addr:full":"406 Main St Watsonville CA 95076",
    "addr:housenumber":"406",
    "addr:postcode":"95076",
    "addr:street":"Main St",
    "iso:country":"US",
    "sg:address":"406 Main St",
    "sg:city":"Watsonville",
    "sg:classifiers":[
        {
            "category":"Social Services",
            "type":"Services"
        }
    ],
    "sg:phone":"+1 831 761 3973",
    "sg:postcode":"95076",
    "sg:province":"CA",
    "sg:tags":[
        "information",
        "cancer"
    ],
    "wof:name":"Women Care-Ente Nosopras",
    "wof:placetype":"venue"
},
  "geometry": {"coordinates":[-121.75827,36.911553],"type":"Point"}
}