{
  "type": "Feature",
  "properties": {
    "iso:country":"US",
    "sg:address":"4020 A 7th St",
    "sg:city":"Long Beach",
    "sg:classifiers":[
        {
            "category":"Sports & Exercise",
            "subcategory":"Gym",
            "type":"Entertainment"
        }
    ],
    "sg:phone":"+1 562 856 5848",
    "sg:postcode":"90804",
    "sg:province":"CA",
    "sg:tags":[
        "trainer"
    ],
    "sg:website":"www.AccelFit.com",
    "wof:name":"Accel Fitness",
    "wof:placetype":"venue"
},
  "geometry": {"coordinates":[-118.145076,33.774969],"type":"Point"}
}