{
  "type": "Feature",
  "properties": {
    "iso:country":"US",
    "sg:address":"6804 N Huntington Dr",
    "sg:city":"San Bernardino",
    "sg:classifiers":[
        {
            "category":"Arts & Performance",
            "subcategory":"Theater",
            "type":"Entertainment"
        }
    ],
    "sg:phone":"+1 909 887 6913",
    "sg:postcode":"92407",
    "sg:province":"CA",
    "sg:tags":[
        "musician"
    ],
    "wof:name":"Inland Empire Live Music LTD",
    "wof:placetype":"venue"
},
  "geometry": {"coordinates":[-117.350872,34.203718],"type":"Point"}
}