{
  "type": "Feature",
  "properties": {
    "addr:full":"3313 E South Bear Creek Dr Merced CA 95340",
    "addr:housenumber":"3313 e",
    "addr:postcode":"95340",
    "addr:street":"South Bear Creek Dr",
    "iso:country":"US",
    "sg:address":"3313 E South Bear Creek Dr",
    "sg:city":"Merced",
    "sg:classifiers":[
        {
            "category":"Professional",
            "subcategory":"Advertising",
            "type":"Services"
        }
    ],
    "sg:phone":"+1 209 723 1009",
    "sg:postcode":"95340",
    "sg:province":"CA",
    "sg:tags":[
        "counselor"
    ],
    "wof:name":"Go Media Group",
    "wof:placetype":"venue"
},
  "geometry": {"coordinates":[-120.435272,37.308961],"type":"Point"}
}