{
  "type": "Feature",
  "properties": {
    "iso:country":"US",
    "sg:address":"3699 Wilshire Blvd Suite 700",
    "sg:city":"Los Angeles",
    "sg:classifiers":[
        {
            "category":"Professional",
            "subcategory":"Accounting & Tax Preparation",
            "type":"Services"
        },
        {
            "category":"Professional",
            "subcategory":"Lawyer & Legal Services",
            "type":"Services"
        },
        {
            "category":"Banks & Credit Unions",
            "subcategory":"Financial Services",
            "type":"Services"
        }
    ],
    "sg:phone":"+1 800 896 5536",
    "sg:postcode":"90010",
    "sg:province":"CA",
    "sg:tags":[
        "accountant",
        "advising"
    ],
    "sg:website":"www.JKHarris.com",
    "wof:name":"JK Harris & Company",
    "wof:placetype":"venue"
},
  "geometry": {"coordinates":[-118.306146,34.061779],"type":"Point"}
}