{
  "type": "Feature",
  "properties": {
    "addr:full":"4001 J Street Sacramento CA 95819",
    "addr:housenumber":"4001",
    "addr:postcode":"95819",
    "addr:street":"J Street",
    "iso:country":"US",
    "sg:address":"4001 J Street",
    "sg:city":"Sacramento",
    "sg:classifiers":[
        {
            "category":"Health Services",
            "subcategory":"Doctor",
            "type":"Services"
        }
    ],
    "sg:phone":"+1 916 453 4414",
    "sg:postcode":"95819",
    "sg:province":"CA",
    "wof:name":"Nicol Ronald F MD",
    "wof:placetype":"venue"
},
  "geometry": {"coordinates":[-121.452502,38.56952],"type":"Point"}
}