{
  "type": "Feature",
  "properties": {
    "iso:country":"US",
    "sg:address":"14520 Friar St",
    "sg:city":"Van Nuys",
    "sg:classifiers":[
        {
            "category":"Shopping",
            "subcategory":"Books",
            "type":"Retail Goods"
        }
    ],
    "sg:phone":"+1 818 785 9478",
    "sg:postcode":"91411",
    "sg:province":"CA",
    "sg:tags":[
        "dealer"
    ],
    "wof:name":"Fuente De Los Milagros",
    "wof:placetype":"venue"
},
  "geometry": {"coordinates":[-118.45052800000001,34.185595],"type":"Point"}
}