{
  "type": "Feature",
  "properties": {
    "iso:country":"US",
    "sg:address":"1314 Westwood Blvd",
    "sg:city":"Los Angeles",
    "sg:classifiers":[
        {
            "category":"Health Services",
            "subcategory":"Health Practitioner",
            "type":"Services"
        }
    ],
    "sg:phone":"+1 310 441 9550",
    "sg:postcode":"90024",
    "sg:province":"CA",
    "sg:tags":[
        "psychotherapist"
    ],
    "wof:name":"Haleh Eghrari",
    "wof:placetype":"venue"
},
  "geometry": {"coordinates":[-118.442313,34.056458],"type":"Point"}
}