{
  "type": "Feature",
  "properties": {
    "iso:country":"US",
    "sg:address":"7185 Lincoln Ave",
    "sg:city":"Buena Park",
    "sg:classifiers":[
        {
            "category":"Restaurant",
            "type":"Food & Drink"
        }
    ],
    "sg:phone":"+1 714 226 9100",
    "sg:postcode":"90620",
    "sg:province":"CA",
    "sg:tags":[
        "sushi",
        "bar"
    ],
    "wof:name":"Joe's Sushi",
    "wof:placetype":"venue"
},
  "geometry": {"coordinates":[-118.00900300000001,33.8321],"type":"Point"}
}