{
  "type": "Feature",
  "properties": {
    "iso:country":"US",
    "sg:address":"755 US Hwy 395",
    "sg:city":"Standish",
    "sg:classifiers":[
        {
            "category":"Travel",
            "subcategory":"Campground",
            "type":"Entertainment"
        }
    ],
    "sg:phone":"+1 530 254 1094",
    "sg:postcode":"96130",
    "sg:province":"CA",
    "wof:name":"Days End Rv Park",
    "wof:placetype":"venue"
},
  "geometry": {"coordinates":[-120.435693,40.36509],"type":"Point"}
}