{
  "type": "Feature",
  "properties": {
    "iso:country":"US",
    "sg:address":"2901 Whittier Blvd",
    "sg:city":"Los Angeles",
    "sg:classifiers":[
        {
            "category":"Wholesale",
            "subcategory":"Meat",
            "type":"Manufacturing & Wholesale Goods"
        }
    ],
    "sg:phone":"+1 323 526 4550",
    "sg:postcode":"90023",
    "sg:province":"CA",
    "wof:name":"Danilos",
    "wof:placetype":"venue"
},
  "geometry": {"coordinates":[-118.208448,34.031317],"type":"Point"}
}