{
  "type": "Feature",
  "properties": {
    "iso:country":"US",
    "sg:address":"6670 Flotilla St",
    "sg:city":"City Of Commerce",
    "sg:classifiers":[
        {
            "category":"Shopping",
            "subcategory":"Clothing, Apparel, & Fashions",
            "type":"Retail Goods"
        }
    ],
    "sg:phone":"+1 323 727 2005",
    "sg:postcode":"90040",
    "sg:province":"CA",
    "sg:tags":[
        "t"
    ],
    "sg:website":"www.bellainc.com",
    "wof:name":"Color Image",
    "wof:placetype":"venue"
},
  "geometry": {"coordinates":[-118.128618,34.005453],"type":"Point"}
}