{
  "type": "Feature",
  "properties": {
    "addr:full":"3251 Laguna Canyon Rd Laguna Beach CA 92651",
    "addr:housenumber":"3251",
    "addr:postcode":"92651",
    "addr:street":"Laguna Canyon Rd",
    "iso:country":"US",
    "sg:address":"3251 Laguna Canyon Rd",
    "sg:city":"Laguna Beach",
    "sg:classifiers":[
        {
            "category":"Shopping",
            "type":"Retail Goods"
        }
    ],
    "sg:phone":"+1 949 376 9493",
    "sg:postcode":"92651",
    "sg:province":"CA",
    "sg:tags":[
        "mural"
    ],
    "sg:website":"www.classicmurals.com",
    "wof:name":"Classic Murals",
    "wof:placetype":"venue"
},
  "geometry": {"coordinates":[-117.78122399999999,33.549031],"type":"Point"}
}