{
  "type": "Feature",
  "properties": {
    "addr:full":"29 E 17th St National City CA 91950",
    "addr:housenumber":"29",
    "addr:postcode":"91950",
    "addr:street":"E 17Th St",
    "iso:country":"US",
    "sg:address":"29 E 17th St",
    "sg:city":"National City",
    "sg:classifiers":[
        {
            "category":"Retail",
            "subcategory":"Auto Repair",
            "type":"Services"
        }
    ],
    "sg:phone":"+1 619 477 1123",
    "sg:postcode":"91950",
    "sg:province":"CA",
    "sg:tags":[
        "repairing",
        "automobile"
    ],
    "wof:name":"Double J Auto & Muffler Shop",
    "wof:placetype":"venue"
},
  "geometry": {"coordinates":[-117.10364800000001,32.668195],"type":"Point"}
}