{
  "type": "Feature",
  "properties": {
    "addr:full":"1113 Douglas St Los Angeles CA 90026",
    "addr:housenumber":"1113",
    "addr:postcode":"90026",
    "addr:street":"Douglas St",
    "iso:country":"US",
    "sg:address":"1113 Douglas St",
    "sg:city":"Los Angeles",
    "sg:classifiers":[
        {
            "category":"Shopping",
            "subcategory":"Clothing, Apparel, & Fashions",
            "type":"Retail Goods"
        }
    ],
    "sg:phone":"+1 213 250 8360",
    "sg:postcode":"90026",
    "sg:province":"CA",
    "sg:tags":[
        "accessory",
        "clothing",
        "women's"
    ],
    "wof:name":"American Apparel",
    "wof:placetype":"venue"
},
  "geometry": {"coordinates":[-118.25326200000001,34.072702],"type":"Point"}
}