{
  "type": "Feature",
  "properties": {
    "iso:country":"US",
    "sg:address":"8734 Nevada Rd",
    "sg:city":"Phelan",
    "sg:classifiers":[
        {
            "category":"Shopping",
            "subcategory":"Gifts & Souvenirs",
            "type":"Retail Goods"
        }
    ],
    "sg:phone":"+1 760 868 0742",
    "sg:postcode":"92371",
    "sg:province":"CA",
    "sg:tags":[
        "shop"
    ],
    "wof:name":"Krismar Enterprises",
    "wof:placetype":"venue"
},
  "geometry": {"coordinates":[-117.507664,34.411475],"type":"Point"}
}