{
  "type": "Feature",
  "properties": {
    "addr:full":"16055 Heron Ave La Mirada CA 90638",
    "addr:housenumber":"16055",
    "addr:postcode":"90638",
    "addr:street":"Heron Ave",
    "iso:country":"US",
    "sg:address":"16055 Heron Ave",
    "sg:city":"La Mirada",
    "sg:classifiers":[
        {
            "category":"Personal",
            "type":"Services"
        }
    ],
    "sg:phone":"+1 714 690 9344",
    "sg:postcode":"90638",
    "sg:province":"CA",
    "sg:tags":[
        "mover"
    ],
    "sg:website":"www.precisionrelocation.com/",
    "wof:name":"Precision Relocation",
    "wof:placetype":"venue"
},
  "geometry": {"coordinates":[-118.02563000000001,33.885638],"type":"Point"}
}