{
  "type": "Feature",
  "properties": {
    "iso:country":"US",
    "sg:address":"22622 Vanowen",
    "sg:city":"Van Nuys",
    "sg:classifiers":[
        {
            "category":"Place Of Worship",
            "subcategory":"Synagogue",
            "type":"Public Place"
        }
    ],
    "sg:phone":"+1 818 464 3300",
    "sg:postcode":"91401",
    "sg:province":"CA",
    "wof:name":"West Valley Jewish Community Center",
    "wof:placetype":"venue"
},
  "geometry": {"coordinates":[-118.431,34.178501],"type":"Point"}
}