{
  "type": "Feature",
  "properties": {
    "addr:full":"21777 Panoche Rd Apple Valley CA 92308",
    "addr:housenumber":"21777",
    "addr:postcode":"92308",
    "addr:street":"Panoche Rd",
    "iso:country":"US",
    "sg:address":"21777 Panoche Rd",
    "sg:city":"Apple Valley",
    "sg:classifiers":[
        {
            "category":"Shopping",
            "type":"Retail Goods"
        }
    ],
    "sg:phone":"+1 760 240 3618",
    "sg:postcode":"92308",
    "sg:province":"CA",
    "sg:tags":[
        "merchandise"
    ],
    "wof:name":"Candle Alley",
    "wof:placetype":"venue"
},
  "geometry": {"coordinates":[-117.188625,34.445674],"type":"Point"}
}