{
  "type": "Feature",
  "properties": {
    "iso:country":"US",
    "sg:address":"1227 W Brooks St",
    "sg:city":"Ontario",
    "sg:classifiers":[
        {
            "category":"Retail",
            "subcategory":"Auto Repair",
            "type":"Services"
        }
    ],
    "sg:phone":"+1 909 635 0152",
    "sg:postcode":"91762",
    "sg:province":"CA",
    "sg:tags":[
        "repairing",
        "automobile"
    ],
    "wof:name":"Arods Automotive Svc",
    "wof:placetype":"venue"
},
  "geometry": {"coordinates":[-117.67418000000001,34.061875],"type":"Point"}
}