{
  "type": "Feature",
  "properties": {
    "addr:full":"502 E 23rd St Los Angeles CA 90011",
    "addr:housenumber":"502",
    "addr:postcode":"90011",
    "addr:street":"E 23Rd St",
    "iso:country":"US",
    "sg:address":"502 E 23rd St",
    "sg:city":"Los Angeles",
    "sg:classifiers":[
        {
            "category":"Real Estate",
            "subcategory":"Real Estate Agent",
            "type":"Services"
        }
    ],
    "sg:phone":"+1 213 742 1975",
    "sg:postcode":"90011",
    "sg:province":"CA",
    "sg:tags":[
        "management"
    ],
    "wof:name":"United Management Properties",
    "wof:placetype":"venue"
},
  "geometry": {"coordinates":[-118.261899,34.024894],"type":"Point"}
}