{
  "type": "Feature",
  "properties": {
    "iso:country":"US",
    "sg:address":"13701 Marina Pointe Drive",
    "sg:city":"Marina del Rey",
    "sg:classifiers":[
        {
            "category":"Real Estate",
            "subcategory":"Real Estate Operator",
            "type":"Services"
        }
    ],
    "sg:phone":"+1 310 822 0255",
    "sg:postcode":"90292",
    "sg:province":"CA",
    "sg:tags":[
        "apartment"
    ],
    "sg:website":"www.mirabellaapts.com/",
    "wof:name":"Mirabella Apartments",
    "wof:placetype":"venue"
},
  "geometry": {"coordinates":[-118.445028,33.985068],"type":"Point"}
}