{
  "type": "Feature",
  "properties": {
    "addr:full":"555 W Ash St San Diego CA 92101",
    "addr:housenumber":"555",
    "addr:postcode":"92101",
    "addr:street":"W Ash St",
    "iso:country":"US",
    "sg:address":"555 W Ash St",
    "sg:city":"San Diego",
    "sg:classifiers":[
        {
            "category":"Travel",
            "subcategory":"Hotels & Motels",
            "type":"Entertainment"
        }
    ],
    "sg:phone":"+1 619 233 7500",
    "sg:postcode":"92101",
    "sg:province":"CA",
    "sg:website":"www.bestwesterncalifornia.com/ho...",
    "wof:name":"Best Western Bayside Inn",
    "wof:placetype":"venue"
},
  "geometry": {"coordinates":[-117.167835,32.719609],"type":"Point"}
}