{
  "type": "Feature",
  "properties": {
    "addr:full":"2500 Carson Street Lakewood CA 90712",
    "addr:housenumber":"2500",
    "addr:postcode":"90712",
    "addr:street":"Carson Street",
    "iso:country":"US",
    "sg:address":"2500 Carson Street",
    "sg:city":"Lakewood",
    "sg:classifiers":[
        {
            "category":"Ice Cream",
            "type":"Food & Drink"
        }
    ],
    "sg:phone":"+1 562 429 9000",
    "sg:postcode":"90712",
    "sg:province":"CA",
    "sg:tags":[
        "frozen",
        "yogurt"
    ],
    "sg:website":"tfyogurt.net/",
    "wof:name":"Tutti Frutti Frozen Yogurt",
    "wof:placetype":"venue"
},
  "geometry": {"coordinates":[-118.16226899999999,33.832329],"type":"Point"}
}