{
  "type": "Feature",
  "properties": {
    "addr:full":"23071 Ave 204 Strathmore CA 93267",
    "addr:housenumber":"23071",
    "addr:postcode":"93267",
    "addr:street":"Ave 204",
    "iso:country":"US",
    "sg:address":"23071 Ave 204",
    "sg:city":"Strathmore",
    "sg:classifiers":[
        {
            "category":"Building & Trades",
            "subcategory":"Construction",
            "type":"Services"
        }
    ],
    "sg:phone":"+1 559 568 1378",
    "sg:postcode":"93267",
    "sg:province":"CA",
    "sg:tags":[
        "coping",
        "plastering",
        "tiling",
        "pool",
        "swimming"
    ],
    "wof:name":"Anderson Pool Svc",
    "wof:placetype":"venue"
},
  "geometry": {"coordinates":[-119.055661,36.15998],"type":"Point"}
}