{
  "type": "Feature",
  "properties": {
    "iso:country":"US",
    "sg:address":"28079 Smyth Dr",
    "sg:city":"Valencia",
    "sg:classifiers":[
        {
            "category":"Recreation",
            "type":"Entertainment"
        }
    ],
    "sg:phone":"+1 661 702 8585",
    "sg:postcode":"91355",
    "sg:province":"CA",
    "sg:tags":[
        "instruction",
        "swimming"
    ],
    "wof:name":"Academy Swim Club",
    "wof:placetype":"venue"
},
  "geometry": {"coordinates":[-118.57378,34.444602],"type":"Point"}
}