{
  "type": "Feature",
  "properties": {
    "addr:full":"26072 Merit Cir Laguna Hills CA 92653",
    "addr:postcode":"26072;92653",
    "addr:street":"Merit Cir",
    "iso:country":"US",
    "sg:address":"26072 Merit Cir",
    "sg:city":"Laguna Hills",
    "sg:classifiers":[
        {
            "category":"Professional",
            "subcategory":"Engineering",
            "type":"Services"
        }
    ],
    "sg:phone":"+1 949 348 2882",
    "sg:postcode":"92653",
    "sg:province":"CA",
    "sg:tags":[
        "engineer"
    ],
    "wof:name":"Lti Civil Engineers & Land Srv",
    "wof:placetype":"venue"
},
  "geometry": {"coordinates":[-117.674542,33.574012],"type":"Point"}
}