{
  "type": "Feature",
  "properties": {
    "addr:full":"201 E 12th St Los Angeles CA 90015",
    "addr:housenumber":"201",
    "addr:postcode":"90015",
    "addr:street":"E 12Th St",
    "iso:country":"US",
    "sg:address":"201 E 12th St",
    "sg:city":"Los Angeles",
    "sg:classifiers":[
        {
            "category":"Wholesale",
            "subcategory":"Apparel",
            "type":"Manufacturing & Wholesale Goods"
        }
    ],
    "sg:phone":"+1 213 749 1819",
    "sg:postcode":"90015",
    "sg:province":"CA",
    "wof:name":"Via Metro",
    "wof:placetype":"venue"
},
  "geometry": {"coordinates":[-118.25733099999999,34.036287],"type":"Point"}
}