{
  "type": "Feature",
  "properties": {
    "addr:full":"5946 Manchester Dr Berkeley CA 94618",
    "addr:housenumber":"5946",
    "addr:postcode":"94618",
    "addr:street":"Manchester Dr",
    "iso:country":"US",
    "sg:address":"5946 Manchester Dr",
    "sg:city":"Berkeley",
    "sg:classifiers":[
        {
            "category":"Real Estate",
            "subcategory":"Real Estate Services",
            "type":"Services"
        }
    ],
    "sg:phone":"+1 510 526 0900",
    "sg:postcode":"94618",
    "sg:province":"CA",
    "wof:name":"Bidgoli Fae Crs Gri",
    "wof:placetype":"venue"
},
  "geometry": {"coordinates":[-122.239435,37.845],"type":"Point"}
}