{
  "type": "Feature",
  "properties": {
    "addr:full":"21101 Norwalk Blvd Hawaiian Gardens CA 90716",
    "addr:housenumber":"21101",
    "addr:postcode":"90716",
    "addr:street":"Norwalk Blvd",
    "iso:country":"US",
    "sg:address":"21101 Norwalk Blvd",
    "sg:city":"Hawaiian Gardens",
    "sg:classifiers":[
        {
            "category":"Government",
            "subcategory":"Post Office",
            "type":"Public Place"
        }
    ],
    "sg:phone":"+1 562 809 8729",
    "sg:postcode":"90716",
    "sg:province":"CA",
    "sg:tags":[
        "postal",
        "u"
    ],
    "sg:website":"www.usps.com",
    "wof:name":"US Post Office",
    "wof:placetype":"venue"
},
  "geometry": {"coordinates":[-118.072789,33.838175],"type":"Point"}
}