{
  "type": "Feature",
  "properties": {
    "addr:full":"5031 Franklin Ave Los Angeles CA 90027",
    "addr:housenumber":"5031",
    "addr:postcode":"90027",
    "addr:street":"Franklin Ave",
    "iso:country":"US",
    "sg:address":"5031 Franklin Ave",
    "sg:city":"Los Angeles",
    "sg:classifiers":[
        {
            "category":"Professional",
            "type":"Services"
        }
    ],
    "sg:phone":"+1 323 664 1036",
    "sg:postcode":"90027",
    "sg:province":"CA",
    "wof:name":"Laura Harrington Inc",
    "wof:placetype":"venue"
},
  "geometry": {"coordinates":[-118.300556,34.105385],"type":"Point"}
}