{
  "type": "Feature",
  "properties": {
    "addr:full":"998 Marshall Rd Vacaville CA 95687",
    "addr:housenumber":"998",
    "addr:postcode":"95687",
    "addr:street":"Marshall Rd",
    "iso:country":"US",
    "sg:address":"998 Marshall Rd",
    "sg:city":"Vacaville",
    "sg:classifiers":[
        {
            "category":"Government",
            "subcategory":"Police Station",
            "type":"Public Place"
        }
    ],
    "sg:phone":"+1 707 449 6086",
    "sg:postcode":"95687",
    "sg:province":"CA",
    "sg:tags":[
        "department"
    ],
    "wof:name":"Vacaville Police Dept-Youth",
    "wof:placetype":"venue"
},
  "geometry": {"coordinates":[-121.97522499999999,38.345861],"type":"Point"}
}