{
  "type": "Feature",
  "properties": {
    "addr:full":"416 N H St San Bernardino CA 92410",
    "addr:housenumber":"416",
    "addr:postcode":"92410",
    "addr:street":"N H St",
    "iso:country":"US",
    "sg:address":"416 N H St",
    "sg:city":"San Bernardino",
    "sg:classifiers":[
        {
            "category":"Professional",
            "subcategory":"Advertising",
            "type":"Services"
        }
    ],
    "sg:phone":"+1 909 381 9500",
    "sg:postcode":"92410",
    "sg:province":"CA",
    "sg:tags":[
        "guide"
    ],
    "wof:name":"Yellow Book USA",
    "wof:placetype":"venue"
},
  "geometry": {"coordinates":[-117.300961,34.107013],"type":"Point"}
}