{
  "type": "Feature",
  "properties": {
    "iso:country":"US",
    "sg:address":"22 Roache Rd",
    "sg:city":"Freedom",
    "sg:classifiers":[
        {
            "category":"Manufacturing",
            "subcategory":"Tools & Machinery",
            "type":"Manufacturing & Wholesale Goods"
        }
    ],
    "sg:phone":"+1 831 724 7000",
    "sg:postcode":"95019",
    "sg:province":"CA",
    "sg:tags":[
        "model",
        "maker"
    ],
    "wof:name":"GRP Model Yachts",
    "wof:placetype":"venue"
},
  "geometry": {"coordinates":[-121.777338,36.936302],"type":"Point"}
}