{
  "type": "Feature",
  "properties": {
    "iso:country":"US",
    "sg:address":"8446 Garfield Ave",
    "sg:city":"Bell",
    "sg:classifiers":[
        {
            "category":"Professional",
            "subcategory":"Business Services",
            "type":"Services"
        }
    ],
    "sg:phone":"+1 562 927 5570",
    "sg:postcode":"90201",
    "sg:province":"CA",
    "sg:tags":[
        "fixed",
        "motor",
        "freight",
        "facility"
    ],
    "wof:name":"Losangeles Inspection Service",
    "wof:placetype":"venue"
},
  "geometry": {"coordinates":[-118.162619,33.954397],"type":"Point"}
}