{
  "type": "Feature",
  "properties": {
    "iso:country":"US",
    "sg:address":"911 Bern Ct Ste 130",
    "sg:city":"San Jose",
    "sg:classifiers":[
        {
            "category":"Professional",
            "subcategory":"Detective & Security Services",
            "type":"Services"
        }
    ],
    "sg:phone":"+1 408 318 6182",
    "sg:postcode":"95112",
    "sg:province":"CA",
    "sg:tags":[
        "system"
    ],
    "sg:website":"www.wcsecurity.com",
    "wof:name":"West Coast Security, Inc.",
    "wof:placetype":"venue"
},
  "geometry": {"coordinates":[-121.893714,37.376326],"type":"Point"}
}