{
  "type": "Feature",
  "properties": {
    "addr:full":"140 W Orangethorpe Ave Apt 22 Placentia CA 92870",
    "addr:housenumber":"140;22",
    "addr:postcode":"ca 92870",
    "addr:street":"W Orangethorpe Ave Apt",
    "iso:country":"US",
    "sg:address":"140 W Orangethorpe Ave Apt 22",
    "sg:city":"Placentia",
    "sg:classifiers":[
        {
            "category":"Real Estate",
            "subcategory":"Real Estate Services",
            "type":"Services"
        },
        {
            "category":"Real Estate",
            "subcategory":"Real Estate Operator",
            "type":"Services"
        }
    ],
    "sg:phone":"+1 714 524 3401",
    "sg:postcode":"92870",
    "sg:province":"CA",
    "sg:tags":[
        "vacancy",
        "apartment",
        "rental",
        "listing"
    ],
    "sg:website":"www.placentiameadows.com",
    "wof:name":"Placentia Meadows",
    "wof:placetype":"venue"
},
  "geometry": {"coordinates":[-117.873001,33.862499],"type":"Point"}
}