{
  "type": "Feature",
  "properties": {
    "iso:country":"US",
    "sg:address":"1500 Green Island Rd",
    "sg:city":"American Canyon",
    "sg:classifiers":[
        {
            "category":"Professional",
            "subcategory":"Management & Consulting",
            "type":"Services"
        }
    ],
    "sg:phone":"+1 707 554 1800",
    "sg:postcode":"94503",
    "sg:province":"CA",
    "sg:tags":[
        "consultant",
        "construction"
    ],
    "wof:name":"Fraser Edwards Co",
    "wof:placetype":"venue"
},
  "geometry": {"coordinates":[-122.281255,38.197102],"type":"Point"}
}