{
  "type": "Feature",
  "properties": {
    "addr:full":"6733 S Sepulveda Blvd Los Angeles CA 90045",
    "addr:housenumber":"6733",
    "addr:postcode":"90045",
    "addr:street":"S Sepulveda Blvd",
    "iso:country":"US",
    "sg:address":"6733 S Sepulveda Blvd",
    "sg:city":"Los Angeles",
    "sg:classifiers":[
        {
            "category":"Professional",
            "subcategory":"Lawyer & Legal Services",
            "type":"Services"
        }
    ],
    "sg:phone":"+1 310 641 8300",
    "sg:postcode":"90045",
    "sg:province":"CA",
    "sg:tags":[
        "attorney"
    ],
    "wof:name":"Nelson & Natale Law Offices",
    "wof:placetype":"venue"
},
  "geometry": {"coordinates":[-118.394046,33.974945],"type":"Point"}
}