{
  "type": "Feature",
  "properties": {
    "addr:full":"6012 Beckwith Rd Modesto CA 95358",
    "addr:housenumber":"6012",
    "addr:postcode":"ca 95358",
    "addr:street":"Beckwith Rd",
    "iso:country":"US",
    "sg:address":"6012 Beckwith Rd",
    "sg:city":"Modesto",
    "sg:classifiers":[
        {
            "category":"Farming",
            "subcategory":"Crops",
            "type":"Manufacturing & Wholesale Goods"
        }
    ],
    "sg:phone":"+1 209 545 0043",
    "sg:postcode":"95358",
    "sg:province":"CA",
    "sg:tags":[
        "grove",
        "nut",
        "tree"
    ],
    "wof:name":"Jack Ishida",
    "wof:placetype":"venue"
},
  "geometry": {"coordinates":[-121.12263299999999,37.681314],"type":"Point"}
}