{
  "type": "Feature",
  "properties": {
    "iso:country":"US",
    "sg:address":"2239 Highland Ave",
    "sg:city":"National City",
    "sg:classifiers":[
        {
            "category":"Food & Beverages",
            "subcategory":"Groceries & Convenience Stores",
            "type":"Retail Goods"
        }
    ],
    "sg:phone":"+1 619 477 0865",
    "sg:postcode":"91950",
    "sg:province":"CA",
    "sg:tags":[
        "grocer"
    ],
    "wof:name":"Lupita's Meat Market",
    "wof:placetype":"venue"
},
  "geometry": {"coordinates":[-117.093714,32.66555],"type":"Point"}
}