{
  "type": "Feature",
  "properties": {
    "addr:full":"38 Burnham Pl Fremont CA 94539",
    "addr:housenumber":"38",
    "addr:postcode":"94539",
    "addr:street":"Burnham Pl",
    "iso:country":"US",
    "sg:address":"38 Burnham Pl",
    "sg:city":"Fremont",
    "sg:classifiers":[
        {
            "category":"Shopping",
            "subcategory":"Catalog Store",
            "type":"Retail Goods"
        }
    ],
    "sg:phone":"+1 510 745 8928",
    "sg:postcode":"94539",
    "sg:province":"CA",
    "sg:tags":[
        "mail",
        "house"
    ],
    "wof:name":"Kmbc Ventures",
    "wof:placetype":"venue"
},
  "geometry": {"coordinates":[-121.95821599999999,37.562751],"type":"Point"}
}