{
  "type": "Feature",
  "properties": {
    "iso:country":"US",
    "sg:address":"20015 Gilbert Dr",
    "sg:city":"Canyon Country",
    "sg:classifiers":[
        {
            "category":"Professional",
            "type":"Services"
        }
    ],
    "sg:phone":"+1 661 250 0698",
    "sg:postcode":"91351",
    "sg:province":"CA",
    "sg:tags":[
        "establishment"
    ],
    "wof:name":"Wagstaff & Wagstaff",
    "wof:placetype":"venue"
},
  "geometry": {"coordinates":[-118.484223,34.416607],"type":"Point"}
}