{
  "type": "Feature",
  "properties": {
    "addr:full":"23 Hitchcock Way Santa Barbara CA 93105",
    "addr:housenumber":"23",
    "addr:postcode":"93105",
    "addr:street":"Hitchcock Way",
    "iso:country":"US",
    "sg:address":"23 Hitchcock Way",
    "sg:city":"Santa Barbara",
    "sg:classifiers":[
        {
            "category":"Personal",
            "type":"Services"
        }
    ],
    "sg:phone":"+1 805 682 4627",
    "sg:postcode":"93105",
    "sg:province":"CA",
    "sg:tags":[
        "electrologist"
    ],
    "wof:name":"Tortoise Press",
    "wof:placetype":"venue"
},
  "geometry": {"coordinates":[-119.744546,34.43985],"type":"Point"}
}