{
  "type": "Feature",
  "properties": {
    "iso:country":"US",
    "sg:address":"1232 Hooper Ave",
    "sg:city":"Los Angeles",
    "sg:classifiers":[
        {
            "category":"Manufacturing",
            "subcategory":"Apparel",
            "type":"Manufacturing & Wholesale Goods"
        }
    ],
    "sg:phone":"+1 213 749 0252",
    "sg:postcode":"90021",
    "sg:province":"CA",
    "wof:name":"Stitch Master",
    "wof:placetype":"venue"
},
  "geometry": {"coordinates":[-118.242028,34.02795],"type":"Point"}
}