{
  "type": "Feature",
  "properties": {
    "addr:full":"3428 Polaris St Modesto CA 95350",
    "addr:housenumber":"3428",
    "addr:postcode":"ca 95350",
    "addr:street":"Polaris St",
    "iso:country":"US",
    "sg:address":"3428 Polaris St",
    "sg:city":"Modesto",
    "sg:classifiers":[
        {
            "category":"Retail",
            "subcategory":"Auto Repair",
            "type":"Services"
        }
    ],
    "sg:phone":"+1 209 575 2624",
    "sg:postcode":"95350",
    "sg:province":"CA",
    "sg:tags":[
        "glass",
        "coating",
        "tinting"
    ],
    "wof:name":"Advanced Tinting",
    "wof:placetype":"venue"
},
  "geometry": {"coordinates":[-121.001668,37.689133],"type":"Point"}
}