{
  "type": "Feature",
  "properties": {
    "addr:full":"4547 W Telephone Rd Ventura CA 93003",
    "addr:housenumber":"4547",
    "addr:postcode":"93003",
    "addr:street":"W Telephone Rd",
    "iso:country":"US",
    "sg:address":"4547 W Telephone Rd",
    "sg:city":"Ventura",
    "sg:classifiers":[
        {
            "category":"Autos & Motor Vehicles",
            "subcategory":"Auto Supplies",
            "type":"Retail Goods"
        }
    ],
    "sg:phone":"+1 805 642 6472",
    "sg:postcode":"93003",
    "sg:province":"CA",
    "sg:tags":[
        "tire"
    ],
    "wof:name":"C & S Tires Inc",
    "wof:placetype":"venue"
},
  "geometry": {"coordinates":[-119.225579,34.26353],"type":"Point"}
}