{
  "type": "Feature",
  "properties": {
    "iso:country":"US",
    "sg:address":"11549 F Ave",
    "sg:city":"Auburn",
    "sg:classifiers":[
        {
            "category":"Social Services",
            "subcategory":"Job Training",
            "type":"Services"
        }
    ],
    "sg:phone":"+1 530 823 4631",
    "sg:postcode":"95603",
    "sg:province":"CA",
    "sg:tags":[
        "rehab",
        "government"
    ],
    "sg:website":"www.goldensierra.com",
    "wof:name":"Golden Sierra Job Training",
    "wof:placetype":"venue"
},
  "geometry": {"coordinates":[-121.10206599999999,38.937053],"type":"Point"}
}