{
  "type": "Feature",
  "properties": {
    "addr:full":"390 Inverness Dr Pacifica CA 94044",
    "addr:housenumber":"390",
    "addr:postcode":"94044",
    "addr:street":"Inverness Dr",
    "iso:country":"US",
    "sg:address":"390 Inverness Dr",
    "sg:city":"Pacifica",
    "sg:classifiers":[
        {
            "category":"Organizations",
            "subcategory":"Religious Organization",
            "type":"Services"
        }
    ],
    "sg:phone":"+1 650 355 0522",
    "sg:postcode":"94044",
    "sg:province":"CA",
    "sg:tags":[
        "church"
    ],
    "wof:name":"Westside Baptist Church",
    "wof:placetype":"venue"
},
  "geometry": {"coordinates":[-122.477636,37.651341],"type":"Point"}
}