{
  "type": "Feature",
  "properties": {
    "addr:full":"PO Box 53 San Mateo CA 94401",
    "addr:housenumber":"po box 53",
    "addr:postcode":"94401",
    "iso:country":"US",
    "sg:address":"PO Box 53",
    "sg:city":"San Mateo",
    "sg:classifiers":[
        {
            "category":"Building & Trades",
            "subcategory":"Construction",
            "type":"Services"
        }
    ],
    "sg:phone":"+1 650 344 6800",
    "sg:postcode":"94401",
    "sg:province":"CA",
    "sg:tags":[
        "interior",
        "design"
    ],
    "wof:name":"Emlay Leslie Interiors",
    "wof:placetype":"venue"
},
  "geometry": {"coordinates":[-122.321634,37.571445],"type":"Point"}
}