{
  "type": "Feature",
  "properties": {
    "iso:country":"US",
    "sg:address":"919 el Cajon Blvd",
    "sg:city":"El Cajon",
    "sg:classifiers":[
        {
            "category":"Wholesale",
            "subcategory":"Auto Parts",
            "type":"Manufacturing & Wholesale Goods"
        }
    ],
    "sg:phone":"+1 619 447 0110",
    "sg:postcode":"92020",
    "sg:province":"CA",
    "sg:tags":[
        "equipment",
        "truck"
    ],
    "sg:website":"www.rizeind.com",
    "wof:name":"Rize Industries LLC",
    "wof:placetype":"venue"
},
  "geometry": {"coordinates":[-116.978404,32.784046],"type":"Point"}
}