{
  "type": "Feature",
  "properties": {
    "addr:full":"3915 W Riverside Dr Burbank CA 91505",
    "addr:housenumber":"3915",
    "addr:postcode":"91505",
    "addr:street":"W Riverside Dr",
    "iso:country":"US",
    "sg:address":"3915 W Riverside Dr",
    "sg:city":"Burbank",
    "sg:classifiers":[
        {
            "category":"Professional",
            "subcategory":"Printing & Photocopies",
            "type":"Services"
        }
    ],
    "sg:phone":"+1 818 746 2177",
    "sg:postcode":"91505",
    "sg:province":"CA",
    "sg:tags":[
        "duplicating",
        "copying"
    ],
    "sg:website":"http://www.capital-print.com",
    "wof:name":"Capital Printing Enterprises",
    "wof:placetype":"venue"
},
  "geometry": {"coordinates":[-118.342,34.152291],"type":"Point"}
}