{
  "type": "Feature",
  "properties": {
    "addr:full":"101 Madeline Dr Aptos CA 95003",
    "addr:housenumber":"101",
    "addr:postcode":"ca 95003",
    "addr:street":"Madeline Dr",
    "iso:country":"US",
    "sg:address":"101 Madeline Dr",
    "sg:city":"Aptos",
    "sg:classifiers":[
        {
            "category":"Government",
            "subcategory":"Office",
            "type":"Public Place"
        }
    ],
    "sg:phone":"+1 831 688 3241",
    "sg:postcode":"95003",
    "sg:province":"CA",
    "sg:tags":[
        "presently",
        "for",
        "being",
        "developed",
        "state",
        "not",
        "open",
        "yet"
    ],
    "wof:name":"Parks and Recreation CA Dept",
    "wof:placetype":"venue"
},
  "geometry": {"coordinates":[-121.917428,36.984425],"type":"Point"}
}