{
  "type": "Feature",
  "properties": {
    "addr:full":"703 5th St Taft CA 93268",
    "addr:housenumber":"703",
    "addr:postcode":"93268",
    "addr:street":"5Th St",
    "iso:country":"US",
    "sg:address":"703 5th St",
    "sg:city":"Taft",
    "sg:classifiers":[
        {
            "category":"Organizations",
            "subcategory":"Religious Organization",
            "type":"Services"
        }
    ],
    "sg:phone":"+1 661 765 2378",
    "sg:postcode":"93268",
    "sg:province":"CA",
    "sg:tags":[
        "church"
    ],
    "wof:name":"St Andrew's Episcopal Church",
    "wof:placetype":"venue"
},
  "geometry": {"coordinates":[-119.45648,35.146307],"type":"Point"}
}