{
  "type": "Feature",
  "properties": {
    "iso:country":"US",
    "sg:address":"3485 Earl Dr",
    "sg:city":"Santa Clara",
    "sg:classifiers":[
        {
            "category":"Professional",
            "subcategory":"Engineering",
            "type":"Services"
        }
    ],
    "sg:phone":"+1 408 985 6923",
    "sg:postcode":"95051",
    "sg:province":"CA",
    "wof:name":"Ernestro R Estrella",
    "wof:placetype":"venue"
},
  "geometry": {"coordinates":[-121.99224599999999,37.362775],"type":"Point"}
}