{
  "type": "Feature",
  "properties": {
    "iso:country":"US",
    "sg:address":"2630 E Weldon Ave",
    "sg:city":"Fresno",
    "sg:classifiers":[
        {
            "category":"Organizations",
            "subcategory":"Membership Organization",
            "type":"Services"
        }
    ],
    "sg:phone":"+1 559 485 2432",
    "sg:postcode":"93703",
    "sg:province":"CA",
    "wof:name":"Progressive Home Club",
    "wof:placetype":"venue"
},
  "geometry": {"coordinates":[-119.780546,36.768567],"type":"Point"}
}