{
  "type": "Feature",
  "properties": {
    "iso:country":"US",
    "sg:address":"13404 Harrison Grade Pl",
    "sg:city":"Sebastopol",
    "sg:classifiers":[
        {
            "category":"Home & Garden",
            "subcategory":"Garden Supply",
            "type":"Retail Goods"
        }
    ],
    "sg:phone":"+1 707 874 2233",
    "sg:postcode":"95472",
    "sg:province":"CA",
    "sg:tags":[
        "nursery",
        "gardening"
    ],
    "wof:name":"Miniature Plant Kingdom",
    "wof:placetype":"venue"
},
  "geometry": {"coordinates":[-122.91300200000001,38.444401],"type":"Point"}
}