{
  "type": "Feature",
  "properties": {
    "iso:country":"US",
    "sg:address":"2720 Calhoun St",
    "sg:city":"San Diego",
    "sg:classifiers":[
        {
            "category":"Food & Beverages",
            "subcategory":"Specialty",
            "type":"Retail Goods"
        }
    ],
    "sg:phone":"+1 619 298 7443",
    "sg:postcode":"92110",
    "sg:province":"CA",
    "sg:tags":[
        "gourmet",
        "shop"
    ],
    "wof:name":"Alvarado Provisions",
    "wof:placetype":"venue"
},
  "geometry": {"coordinates":[-117.197872,32.755208],"type":"Point"}
}