{
  "type": "Feature",
  "properties": {
    "addr:full":"215 N Broadway Santa Ana CA 92701",
    "addr:housenumber":"215",
    "addr:postcode":"92701",
    "addr:street":"N Broadway",
    "iso:country":"US",
    "sg:address":"215 N Broadway",
    "sg:city":"Santa Ana",
    "sg:classifiers":[
        {
            "category":"Professional",
            "subcategory":"Engineering",
            "type":"Services"
        }
    ],
    "sg:phone":"+1 714 647 9848",
    "sg:postcode":"92701",
    "sg:province":"CA",
    "sg:tags":[
        "engineer"
    ],
    "wof:name":"Canfield Consulting Structural",
    "wof:placetype":"venue"
},
  "geometry": {"coordinates":[-117.869665,33.747033],"type":"Point"}
}