{
  "type": "Feature",
  "properties": {
    "iso:country":"US",
    "sg:address":"355 N Lantana St",
    "sg:city":"Camarillo",
    "sg:classifiers":[
        {
            "category":"Retail",
            "subcategory":"Laundry & Dry Cleaning",
            "type":"Services"
        }
    ],
    "sg:phone":"+1 805 484 5009",
    "sg:postcode":"93010",
    "sg:province":"CA",
    "sg:tags":[
        "cleaners",
        "rug",
        "carpet"
    ],
    "wof:name":"Servpro",
    "wof:placetype":"venue"
},
  "geometry": {"coordinates":[-119.055184,34.21974],"type":"Point"}
}