{
  "type": "Feature",
  "properties": {
    "addr:full":"20133 Saticoy St Winnetka CA 91306",
    "addr:housenumber":"20133",
    "addr:postcode":"91306",
    "addr:street":"Saticoy St",
    "iso:country":"US",
    "sg:address":"20133 Saticoy St",
    "sg:city":"Winnetka",
    "sg:classifiers":[
        {
            "category":"Restaurant",
            "type":"Food & Drink"
        }
    ],
    "sg:phone":"+1 818 882 4747",
    "sg:postcode":"91306",
    "sg:province":"CA",
    "sg:tags":[
        "american",
        "latin"
    ],
    "sg:website":"www.lasdunasrestaurant.com/",
    "wof:name":"Las Dunas",
    "wof:placetype":"venue"
},
  "geometry": {"coordinates":[-118.57199900000001,34.208199],"type":"Point"}
}