{
  "type": "Feature",
  "properties": {
    "addr:full":"162 Prospect Ave Long Beach CA 90803",
    "addr:housenumber":"162",
    "addr:postcode":"90803",
    "addr:street":"Prospect Ave",
    "iso:country":"US",
    "sg:address":"162 Prospect Ave",
    "sg:city":"Long Beach",
    "sg:classifiers":[
        {
            "category":"Building & Trades",
            "subcategory":"Plumbing",
            "type":"Services"
        }
    ],
    "sg:phone":"+1 562 930 0614",
    "sg:postcode":"90803",
    "sg:province":"CA",
    "sg:tags":[
        "contractor"
    ],
    "wof:name":"Pacific Plumbing",
    "wof:placetype":"venue"
},
  "geometry": {"coordinates":[-118.14062199999999,33.761301],"type":"Point"}
}