{
  "type": "Feature",
  "properties": {
    "iso:country":"US",
    "sg:address":"3118 Depot Rd",
    "sg:city":"Hayward",
    "sg:classifiers":[
        {
            "category":"Building & Trades",
            "subcategory":"Pest Control",
            "type":"Services"
        }
    ],
    "sg:phone":"+1 510 786 0680",
    "sg:postcode":"94545",
    "sg:province":"CA",
    "sg:tags":[
        "industrial",
        "services-commercial"
    ],
    "sg:website":"http://www.thermionicscorp.com",
    "wof:name":"Tmpi",
    "wof:placetype":"venue"
},
  "geometry": {"coordinates":[-122.121196,37.638545],"type":"Point"}
}