{
  "type": "Feature",
  "properties": {
    "addr:full":"900 E Campbell Ave Campbell CA 95008",
    "addr:housenumber":"900",
    "addr:postcode":"95008",
    "addr:street":"E Campbell Ave",
    "iso:country":"US",
    "sg:address":"900 E Campbell Ave",
    "sg:city":"Campbell",
    "sg:classifiers":[
        {
            "category":"Restaurant",
            "type":"Food & Drink"
        }
    ],
    "sg:phone":"+1 408 371 3806",
    "sg:postcode":"95008",
    "sg:province":"CA",
    "sg:tags":[
        "consulting",
        "management",
        "eating"
    ],
    "wof:name":"Togos Eatery",
    "wof:placetype":"venue"
},
  "geometry": {"coordinates":[-121.93174999999999,37.28697],"type":"Point"}
}