{
  "type": "Feature",
  "properties": {
    "iso:country":"US",
    "sg:address":"9719 Glasgow Place",
    "sg:city":"Los Angeles",
    "sg:classifiers":[
        {
            "category":"Professional",
            "type":"Services"
        }
    ],
    "sg:phone":"+1 310 641 5105",
    "sg:postcode":"90045",
    "sg:province":"CA",
    "sg:tags":[
        "caterer"
    ],
    "wof:name":"Allen Tanika",
    "wof:placetype":"venue"
},
  "geometry": {"coordinates":[-118.37147400000001,33.94798],"type":"Point"}
}