{
  "type": "Feature",
  "properties": {
    "iso:country":"US",
    "sg:address":"101 Mount Hermon Rd",
    "sg:city":"Scotts Valley",
    "sg:classifiers":[
        {
            "category":"Autos & Motor Vehicles",
            "subcategory":"Auto Supplies",
            "type":"Retail Goods"
        }
    ],
    "sg:phone":"+1 831 439 6720",
    "sg:postcode":"95066",
    "sg:province":"CA",
    "sg:tags":[
        "battery"
    ],
    "wof:name":"Batteries Plus",
    "wof:placetype":"venue"
},
  "geometry": {"coordinates":[-122.02552799999999,37.04379],"type":"Point"}
}