{
  "type": "Feature",
  "properties": {
    "addr:full":"36675 Mojave Sage St Palm Desert CA 92211",
    "addr:postcode":"36675;92211",
    "addr:street":"Sage St",
    "iso:country":"US",
    "sg:address":"36675 Mojave Sage St",
    "sg:city":"Palm Desert",
    "sg:classifiers":[
        {
            "category":"Insurance",
            "subcategory":"Insurance Agent",
            "type":"Services"
        }
    ],
    "sg:phone":"+1 760 360 2001",
    "sg:postcode":"92211",
    "sg:province":"CA",
    "wof:name":"Gore & Assoc",
    "wof:placetype":"venue"
},
  "geometry": {"coordinates":[-116.296891,33.783745],"type":"Point"}
}