{
  "type": "Feature",
  "properties": {
    "addr:full":"2637 E Vernon Ave Los Angeles CA 90058",
    "addr:housenumber":"2637",
    "addr:postcode":"90058",
    "addr:street":"E Vernon Ave",
    "iso:country":"US",
    "sg:address":"2637 E Vernon Ave",
    "sg:city":"Los Angeles",
    "sg:classifiers":[
        {
            "category":"Food & Beverages",
            "subcategory":"Meat & Fish",
            "type":"Retail Goods"
        }
    ],
    "sg:phone":"+1 323 589 5271",
    "sg:postcode":"90058",
    "sg:province":"CA",
    "wof:name":"Choe Meat Co",
    "wof:placetype":"venue"
},
  "geometry": {"coordinates":[-118.22502299999999,34.005444],"type":"Point"}
}