{
  "type": "Feature",
  "properties": {
    "addr:full":"2764 Entrada Cir Antioch CA 94509",
    "addr:housenumber":"2764",
    "addr:postcode":"ca 94509",
    "addr:street":"Entrada Cir",
    "iso:country":"US",
    "sg:address":"2764 Entrada Cir",
    "sg:city":"Antioch",
    "sg:classifiers":[
        {
            "category":"Building & Trades",
            "subcategory":"Construction",
            "type":"Services"
        }
    ],
    "sg:phone":"+1 925 706 2695",
    "sg:postcode":"94509",
    "sg:province":"CA",
    "sg:tags":[
        "coping",
        "plastering",
        "tiling",
        "pool",
        "swimming"
    ],
    "wof:name":"Andy's Pool Svc",
    "wof:placetype":"venue"
},
  "geometry": {"coordinates":[-121.826922,37.999961],"type":"Point"}
}