{
  "type": "Feature",
  "properties": {
    "addr:full":"301 W Lake St Mount Shasta CA 96067",
    "addr:housenumber":"301",
    "addr:postcode":"96067",
    "addr:street":"W Lake St",
    "iso:country":"US",
    "sg:address":"301 W Lake St",
    "sg:city":"Mount Shasta",
    "sg:classifiers":[
        {
            "category":"Restaurant",
            "type":"Food & Drink"
        }
    ],
    "sg:menulink":"http://www.allmenus.com/ca/mount-shasta/197946-kfc---kentucky-fried-chicken/menu/",
    "sg:phone":"+1 530 926 6525",
    "sg:postcode":"96067",
    "sg:province":"CA",
    "sg:tags":[
        "american",
        "chicken"
    ],
    "wof:name":"KFC - Kentucky Fried Chicken",
    "wof:placetype":"venue"
},
  "geometry": {"coordinates":[-122.32226199999999,41.310512],"type":"Point"}
}