{
  "type": "Feature",
  "properties": {
    "iso:country":"US",
    "sg:address":"29307 Greenwood Rd",
    "sg:city":"Elk",
    "sg:classifiers":[
        {
            "category":"Manufacturing",
            "subcategory":"Lumber",
            "type":"Manufacturing & Wholesale Goods"
        }
    ],
    "sg:phone":"+1 707 877 3371",
    "sg:postcode":"95432",
    "sg:province":"CA",
    "sg:tags":[
        "forester"
    ],
    "wof:name":"Mendocino Forest Products Co",
    "wof:placetype":"venue"
},
  "geometry": {"coordinates":[-123.66202,39.138022],"type":"Point"}
}