{
  "type": "Feature",
  "properties": {
    "addr:full":"615 W East Ave Chico CA 95926",
    "addr:housenumber":"615",
    "addr:postcode":"95926",
    "addr:street":"W East Ave",
    "iso:country":"US",
    "sg:address":"615 W East Ave",
    "sg:city":"Chico",
    "sg:classifiers":[
        {
            "category":"Health Services",
            "subcategory":"Doctor",
            "type":"Services"
        }
    ],
    "sg:phone":"+1 530 895 1800",
    "sg:postcode":"95926",
    "sg:province":"CA",
    "sg:tags":[
        "clinic"
    ],
    "wof:name":"Chico Surgery Ctr",
    "wof:placetype":"venue"
},
  "geometry": {"coordinates":[-121.870941,39.750881],"type":"Point"}
}