{
  "type": "Feature",
  "properties": {
    "addr:full":"12111 Brookhurst St Garden Grove CA 92840",
    "addr:housenumber":"12111",
    "addr:postcode":"92840",
    "addr:street":"Brookhurst St",
    "iso:country":"US",
    "sg:address":"12111 Brookhurst St",
    "sg:city":"Garden Grove",
    "sg:classifiers":[
        {
            "category":"Restaurant",
            "type":"Food & Drink"
        }
    ],
    "sg:menulink":"http://www.allmenus.com/ca/anaheim-santa-ana-garden-grove/27709-co-la/menu/",
    "sg:phone":"+1 714 636 1188",
    "sg:postcode":"92840",
    "sg:province":"CA",
    "sg:tags":[
        "asian",
        "vietnamese"
    ],
    "wof:name":"Co La",
    "wof:placetype":"venue"
},
  "geometry": {"coordinates":[-117.95894800000001,33.787137],"type":"Point"}
}