{
  "type": "Feature",
  "properties": {
    "iso:country":"US",
    "sg:address":"106 S Robertson Boulevard",
    "sg:city":"Los Angeles",
    "sg:classifiers":[
        {
            "category":"Shopping",
            "subcategory":"Clothing, Apparel, & Fashions",
            "type":"Retail Goods"
        }
    ],
    "sg:phone":"+1 310 271 2727",
    "sg:postcode":"90048",
    "sg:province":"CA",
    "sg:tags":[
        "accessory",
        "clothing",
        "women's"
    ],
    "wof:name":"LF Stores",
    "wof:placetype":"venue"
},
  "geometry": {"coordinates":[-118.38387400000001,34.075001],"type":"Point"}
}