{
  "type": "Feature",
  "properties": {
    "addr:full":"1825 Powell St San Francisco CA 94133",
    "addr:housenumber":"1825",
    "addr:postcode":"94133",
    "addr:street":"Powell St",
    "iso:country":"US",
    "sg:address":"1825 Powell St",
    "sg:city":"San Francisco",
    "sg:classifiers":[
        {
            "category":"Real Estate",
            "subcategory":"Real Estate Agent",
            "type":"Services"
        }
    ],
    "sg:phone":"+1 415 765 9907",
    "sg:postcode":"94133",
    "sg:province":"CA",
    "sg:tags":[
        "manager"
    ],
    "wof:name":"King & Co Realstate Consultant",
    "wof:placetype":"venue"
},
  "geometry": {"coordinates":[-122.411241,37.801861],"type":"Point"}
}