{
  "type": "Feature",
  "properties": {
    "iso:country":"US",
    "sg:address":"861 Oak St",
    "sg:city":"San Francisco",
    "sg:classifiers":[
        {
            "category":"Manufacturing",
            "subcategory":"Printing",
            "type":"Manufacturing & Wholesale Goods"
        }
    ],
    "sg:phone":"+1 415 437 1586",
    "sg:postcode":"94117",
    "sg:province":"CA",
    "sg:tags":[
        "publishing"
    ],
    "wof:name":"Rockavelli Publishing",
    "wof:placetype":"venue"
},
  "geometry": {"coordinates":[-122.433303,37.773601],"type":"Point"}
}