{
  "type": "Feature",
  "properties": {
    "addr:full":"2550 E el Presidio St Long Beach CA 90810",
    "addr:housenumber":"2550",
    "addr:postcode":"90810",
    "addr:street":"E El Presidio St",
    "iso:country":"US",
    "sg:address":"2550 E el Presidio St",
    "sg:city":"Long Beach",
    "sg:classifiers":[
        {
            "category":"Wholesale",
            "subcategory":"Drugs",
            "type":"Manufacturing & Wholesale Goods"
        }
    ],
    "sg:phone":"+1 310 637 9566",
    "sg:postcode":"90810",
    "sg:province":"CA",
    "sg:tags":[
        "company",
        "holding"
    ],
    "wof:name":"Botanicals Intl Nutraceuticals",
    "wof:placetype":"venue"
},
  "geometry": {"coordinates":[-118.220754,33.842155],"type":"Point"}
}