{
  "type": "Feature",
  "properties": {
    "addr:full":"4155 Adams Ave San Diego CA 92116",
    "addr:housenumber":"4155",
    "addr:postcode":"92116",
    "addr:street":"Adams Ave",
    "iso:country":"US",
    "sg:address":"4155 Adams Ave",
    "sg:city":"San Diego",
    "sg:classifiers":[
        {
            "category":"Personal",
            "subcategory":"Beauty Salon",
            "type":"Services"
        }
    ],
    "sg:phone":"+1 619 280 3023",
    "sg:postcode":"92116",
    "sg:province":"CA",
    "sg:tags":[
        "hair"
    ],
    "sg:website":"www.clipartsalon.net",
    "wof:name":"Clip Art Salon",
    "wof:placetype":"venue"
},
  "geometry": {"coordinates":[-117.105639,32.763235],"type":"Point"}
}