{
  "type": "Feature",
  "properties": {
    "addr:full":"6266 Acadia Ave Agoura Hills CA 91301",
    "addr:housenumber":"6266",
    "addr:postcode":"91301",
    "addr:street":"Acadia Ave",
    "iso:country":"US",
    "sg:address":"6266 Acadia Ave",
    "sg:city":"Agoura Hills",
    "sg:classifiers":[
        {
            "category":"Building & Trades",
            "subcategory":"Electrical",
            "type":"Services"
        }
    ],
    "sg:phone":"+1 818 343 4710",
    "sg:postcode":"91301",
    "sg:province":"CA",
    "sg:tags":[
        "telecommunication",
        "contractor"
    ],
    "wof:name":"Safetech Electronics",
    "wof:placetype":"venue"
},
  "geometry": {"coordinates":[-118.756056,34.164679],"type":"Point"}
}