{
  "type": "Feature",
  "properties": {
    "addr:full":"5922 Big Horn Pl Fontana CA 92336",
    "addr:housenumber":"5922",
    "addr:postcode":"92336",
    "addr:street":"Big Horn Pl",
    "iso:country":"US",
    "sg:address":"5922 Big Horn Pl",
    "sg:city":"Fontana",
    "sg:classifiers":[
        {
            "category":"Real Estate",
            "subcategory":"Real Estate Services",
            "type":"Services"
        },
        {
            "category":"Real Estate",
            "subcategory":"Surveying",
            "type":"Services"
        }
    ],
    "sg:phone":"+1 909 438 3858",
    "sg:postcode":"92336",
    "sg:province":"CA",
    "sg:tags":[
        "industrial",
        "appraisers-commercial",
        "appraiser"
    ],
    "wof:name":"Quick Time Appraisals",
    "wof:placetype":"venue"
},
  "geometry": {"coordinates":[-117.44879400000001,34.14608],"type":"Point"}
}