{
  "type": "Feature",
  "properties": {
    "addr:full":"3 Park Plaza Irvine CA 92614",
    "addr:housenumber":"3",
    "addr:postcode":"92614",
    "addr:street":"Park Plaza",
    "iso:country":"US",
    "sg:address":"3 Park Plaza",
    "sg:city":"Irvine",
    "sg:classifiers":[
        {
            "category":"Professional",
            "subcategory":"Lawyer & Legal Services",
            "type":"Services"
        }
    ],
    "sg:phone":"+1 949 852 8200",
    "sg:postcode":"92614",
    "sg:province":"CA",
    "wof:name":"Feeley John E",
    "wof:placetype":"venue"
},
  "geometry": {"coordinates":[-117.8387,33.678582],"type":"Point"}
}