{
  "type": "Feature",
  "properties": {
    "iso:country":"US",
    "sg:address":"1266 W Barstow Ave",
    "sg:city":"Fresno",
    "sg:classifiers":[
        {
            "category":"Education",
            "subcategory":"School",
            "type":"Public Place"
        }
    ],
    "sg:phone":"+1 559 451 4500",
    "sg:postcode":"93711",
    "sg:province":"CA",
    "wof:name":"Gibson Elementary School",
    "wof:placetype":"venue"
},
  "geometry": {"coordinates":[-119.813619,36.815666],"type":"Point"}
}