{
  "type": "Feature",
  "properties": {
    "addr:full":"1811 Grand Canal Blvd Stockton CA 95207",
    "addr:housenumber":"1811",
    "addr:postcode":"95207",
    "addr:street":"Grand Canal Blvd",
    "iso:country":"US",
    "sg:address":"1811 Grand Canal Blvd",
    "sg:city":"Stockton",
    "sg:classifiers":[
        {
            "category":"Banks & Credit Unions",
            "subcategory":"Bank",
            "type":"Services"
        }
    ],
    "sg:phone":"+1 209 477 0216",
    "sg:postcode":"95207",
    "sg:province":"CA",
    "sg:tags":[
        "loan",
        "real estate"
    ],
    "sg:website":"www.homeloansolutions.com",
    "wof:name":"Home Loan Solutions",
    "wof:placetype":"venue"
},
  "geometry": {"coordinates":[-121.328002,37.986447],"type":"Point"}
}