{
  "type": "Feature",
  "properties": {
    "addr:full":"957 Lombard St San Francisco CA 94133",
    "addr:housenumber":"957",
    "addr:postcode":"94133",
    "addr:street":"Lombard St",
    "iso:country":"US",
    "sg:address":"957 Lombard St",
    "sg:city":"San Francisco",
    "sg:classifiers":[
        {
            "category":"Wholesale",
            "subcategory":"Machinery & Supplies",
            "type":"Manufacturing & Wholesale Goods"
        }
    ],
    "sg:phone":"+1 415 441 1318",
    "sg:postcode":"94133",
    "sg:province":"CA",
    "sg:tags":[
        "heavy",
        "equipment",
        "material",
        "handling"
    ],
    "wof:name":"Machinery Sales & Consulting",
    "wof:placetype":"venue"
},
  "geometry": {"coordinates":[-122.417213,37.802247],"type":"Point"}
}