{
  "type": "Feature",
  "properties": {
    "iso:country":"US",
    "sg:address":"13285 Tiverton Rd",
    "sg:city":"San Diego",
    "sg:classifiers":[
        {
            "category":"Professional",
            "subcategory":"Management & Consulting",
            "type":"Services"
        }
    ],
    "sg:phone":"+1 858 350 3403",
    "sg:postcode":"92130",
    "sg:province":"CA",
    "sg:tags":[
        "consultant"
    ],
    "wof:name":"MTS Advisors",
    "wof:placetype":"venue"
},
  "geometry": {"coordinates":[-117.235979,32.961402],"type":"Point"}
}