{
  "type": "Feature",
  "properties": {
    "iso:country":"US",
    "sg:address":"1 W Figueroa St",
    "sg:city":"Santa Barbara",
    "sg:classifiers":[
        {
            "category":"Building & Trades",
            "subcategory":"Construction",
            "type":"Services"
        }
    ],
    "sg:phone":"+1 805 899 4358",
    "sg:postcode":"93101",
    "sg:province":"CA",
    "sg:tags":[
        "tile",
        "dealer"
    ],
    "wof:name":"R G Menegon Tile Contr",
    "wof:placetype":"venue"
},
  "geometry": {"coordinates":[-119.704307,34.421336],"type":"Point"}
}