{
  "type": "Feature",
  "properties": {
    "addr:full":"2553 E 53rd St Huntington Park CA 90255",
    "addr:housenumber":"2553",
    "addr:postcode":"90255",
    "addr:street":"E 53Rd St;Park",
    "iso:country":"US",
    "sg:address":"2553 E 53rd St",
    "sg:city":"Huntington Park",
    "sg:classifiers":[
        {
            "category":"Freight",
            "type":"Transportation"
        }
    ],
    "sg:phone":"+1 323 589 6255",
    "sg:postcode":"90255",
    "sg:province":"CA",
    "sg:tags":[
        "trucking"
    ],
    "wof:name":"Rip Trucking Co",
    "wof:placetype":"venue"
},
  "geometry": {"coordinates":[-118.225196,33.994777],"type":"Point"}
}