{
  "type": "Feature",
  "properties": {
    "iso:country":"US",
    "sg:address":"100 Bush St",
    "sg:city":"San Francisco",
    "sg:classifiers":[
        {
            "category":"Personal",
            "type":"Services"
        }
    ],
    "sg:phone":"+1 415 291 0997",
    "sg:postcode":"94104",
    "sg:province":"CA",
    "sg:tags":[
        "concierge"
    ],
    "sg:website":"www.lesconcierges.com",
    "wof:name":"Les Concierges Inc",
    "wof:placetype":"venue"
},
  "geometry": {"coordinates":[-122.400744,37.791177],"type":"Point"}
}