{
  "type": "Feature",
  "properties": {
    "iso:country":"US",
    "sg:address":"23734 Valencia Blvd #204",
    "sg:city":"Valencia",
    "sg:classifiers":[
        {
            "category":"Health Services",
            "subcategory":"Clinic",
            "type":"Services"
        }
    ],
    "sg:phone":"+1 661 964 6350",
    "sg:postcode":"91355",
    "sg:province":"CA",
    "sg:tags":[
        "medical"
    ],
    "sg:website":"www.maximhealthcare.com",
    "wof:name":"Maxim Healthcare",
    "wof:placetype":"venue"
},
  "geometry": {"coordinates":[-118.549717,34.414854],"type":"Point"}
}