{
  "type": "Feature",
  "properties": {
    "iso:country":"US",
    "sg:address":"2565 Colonial Cir",
    "sg:city":"Watsonville",
    "sg:classifiers":[
        {
            "category":"Social Services",
            "type":"Services"
        }
    ],
    "sg:phone":"+1 831 761 1040",
    "sg:postcode":"95076",
    "sg:province":"CA",
    "sg:tags":[
        "psychologist"
    ],
    "wof:name":"Emdr Institute",
    "wof:placetype":"venue"
},
  "geometry": {"coordinates":[-121.759988,36.872625],"type":"Point"}
}