{
  "type": "Feature",
  "properties": {
    "addr:full":"444 Saratoga Ave Apt 39D Santa Clara CA 95050",
    "addr:housenumber":"444",
    "addr:postcode":"95050",
    "addr:street":"Saratoga Ave Apt 39D",
    "iso:country":"US",
    "sg:address":"444 Saratoga Ave Apt 39D",
    "sg:city":"Santa Clara",
    "sg:classifiers":[
        {
            "category":"Shopping",
            "subcategory":"Stationery & Office Supplies",
            "type":"Retail Goods"
        }
    ],
    "sg:phone":"+1 408 244 4466",
    "sg:postcode":"95050",
    "sg:province":"CA",
    "sg:tags":[
        "equipment"
    ],
    "wof:name":"Wright Line",
    "wof:placetype":"venue"
},
  "geometry": {"coordinates":[-121.960488,37.334761],"type":"Point"}
}