{
  "type": "Feature",
  "properties": {
    "addr:full":"3525 W Carson St Space 73 Torrance CA 90510",
    "addr:housenumber":"3525;73",
    "addr:postcode":"90510",
    "addr:street":"W Carson St",
    "iso:country":"US",
    "sg:address":"3525 W Carson St Space 73",
    "sg:city":"Torrance",
    "sg:classifiers":[
        {
            "category":"Cinema",
            "subcategory":"Movie Theater",
            "type":"Entertainment"
        }
    ],
    "sg:phone":"+1 310 921 2046",
    "sg:postcode":"90510",
    "sg:province":"CA",
    "sg:website":"www.amcentertainment.com/",
    "wof:name":"AMC Del Amo 18",
    "wof:placetype":"venue"
},
  "geometry": {"coordinates":[-118.348095,33.83326],"type":"Point"}
}