{
  "type": "Feature",
  "properties": {
    "addr:full":"1212 Broadway Oakland CA 94612",
    "addr:housenumber":"1212",
    "addr:postcode":"94612",
    "addr:street":"Broadway",
    "iso:country":"US",
    "sg:address":"1212 Broadway",
    "sg:city":"Oakland",
    "sg:classifiers":[
        {
            "category":"Professional",
            "subcategory":"Lawyer & Legal Services",
            "type":"Services"
        }
    ],
    "sg:phone":"+1 510 250 2588",
    "sg:postcode":"94612",
    "sg:province":"CA",
    "wof:name":"Law Offices of Gary S Abel",
    "wof:placetype":"venue"
},
  "geometry": {"coordinates":[-122.272003,37.803001],"type":"Point"}
}