{
  "type": "Feature",
  "properties": {
    "iso:country":"US",
    "sg:address":"14538 Nordhoff St",
    "sg:city":"Panorama City",
    "sg:classifiers":[
        {
            "category":"Shopping",
            "subcategory":"Gifts & Souvenirs",
            "type":"Retail Goods"
        }
    ],
    "sg:phone":"+1 818 893 5080",
    "sg:postcode":"91402",
    "sg:province":"CA",
    "wof:name":"Laras Toys and Gifts",
    "wof:placetype":"venue"
},
  "geometry": {"coordinates":[-118.448525,34.235322],"type":"Point"}
}