{
  "type": "Feature",
  "properties": {
    "iso:country":"US",
    "sg:address":"606 S Hill Street",
    "sg:city":"Los Angeles",
    "sg:classifiers":[
        {
            "category":"Shopping",
            "subcategory":"Jewelry",
            "type":"Retail Goods"
        }
    ],
    "sg:phone":"+1 213 627 5833",
    "sg:postcode":"90014",
    "sg:province":"CA",
    "wof:name":"B & S Jewelry",
    "wof:placetype":"venue"
},
  "geometry": {"coordinates":[-118.253147,34.047271],"type":"Point"}
}