{
  "type": "Feature",
  "properties": {
    "iso:country":"US",
    "sg:address":"450 Sansome St",
    "sg:city":"San Francisco",
    "sg:classifiers":[
        {
            "category":"Wholesale",
            "subcategory":"Groceries",
            "type":"Manufacturing & Wholesale Goods"
        }
    ],
    "sg:phone":"+1 415 981 3650",
    "sg:postcode":"94111",
    "sg:province":"CA",
    "sg:tags":[
        "food",
        "product"
    ],
    "wof:name":"Lawrence Export Trading",
    "wof:placetype":"venue"
},
  "geometry": {"coordinates":[-122.401488,37.794838],"type":"Point"}
}