{
  "type": "Feature",
  "properties": {
    "addr:full":"10182 Croydon Way Ste C Sacramento CA 95827",
    "addr:housenumber":"10182",
    "addr:postcode":"95827",
    "addr:street":"Croydon Way Ste C",
    "iso:country":"US",
    "sg:address":"10182 Croydon Way Ste C",
    "sg:city":"Sacramento",
    "sg:classifiers":[
        {
            "category":"Manufacturing",
            "subcategory":"Rubber & Plastics",
            "type":"Manufacturing & Wholesale Goods"
        },
        {
            "category":"Home & Garden",
            "subcategory":"Building Materials",
            "type":"Retail Goods"
        }
    ],
    "sg:phone":"+1 916 369 8885",
    "sg:postcode":"95827",
    "sg:province":"CA",
    "sg:tags":[
        "gaskets-manufacturers",
        "gasket"
    ],
    "wof:name":"Valley Rubber & Gasket Co Inc",
    "wof:placetype":"venue"
},
  "geometry": {"coordinates":[-121.31041500000001,38.582012],"type":"Point"}
}