{
  "type": "Feature",
  "properties": {
    "iso:country":"US",
    "sg:address":"4716 E Cesar Chavez Ave",
    "sg:city":"Los Angeles",
    "sg:classifiers":[
        {
            "category":"Government",
            "subcategory":"City Hall",
            "type":"Public Place"
        }
    ],
    "sg:phone":"+1 323 260 2991",
    "sg:postcode":"90022",
    "sg:province":"CA",
    "sg:website":"www.lavote.net/",
    "wof:name":"Los Angeles Registrar-Recorder/County Clerk",
    "wof:placetype":"venue"
},
  "geometry": {"coordinates":[-118.164516,34.040124],"type":"Point"}
}