{
  "type": "Feature",
  "properties": {
    "iso:country":"US",
    "sg:address":"13202 S Western Ave",
    "sg:city":"Gardena",
    "sg:classifiers":[
        {
            "category":"Shopping",
            "subcategory":"Clothing, Apparel, & Fashions",
            "type":"Retail Goods"
        }
    ],
    "sg:phone":"+1 310 217 0059",
    "sg:postcode":"90249",
    "sg:province":"CA",
    "sg:tags":[
        "handbag"
    ],
    "wof:name":"Armandi",
    "wof:placetype":"venue"
},
  "geometry": {"coordinates":[-118.309019,33.910834],"type":"Point"}
}