{
  "type": "Feature",
  "properties": {
    "addr:full":"2003 Yosemite Ave Simi Valley CA 93063",
    "addr:housenumber":"2003",
    "addr:postcode":"93063",
    "addr:street":"Yosemite Ave",
    "iso:country":"US",
    "sg:address":"2003 Yosemite Ave",
    "sg:city":"Simi Valley",
    "sg:classifiers":[
        {
            "category":"Social Services",
            "subcategory":"Child Care",
            "type":"Services"
        }
    ],
    "sg:phone":"+1 805 522 5321",
    "sg:postcode":"93063",
    "sg:province":"CA",
    "sg:website":"www.tutortime.com",
    "wof:name":"Tutor Time Learning Ctr",
    "wof:placetype":"venue"
},
  "geometry": {"coordinates":[-118.678448,34.272958],"type":"Point"}
}