{
  "type": "Feature",
  "properties": {
    "iso:country":"US",
    "sg:address":"18599 Sutter Blvd",
    "sg:city":"Morgan Hill",
    "sg:classifiers":[
        {
            "category":"Bakery",
            "type":"Food & Drink"
        }
    ],
    "sg:menulink":"http://www.allmenus.com/ca/san-jose/106766-marie-callenders/menu/",
    "sg:phone":"+1 408 778 7373",
    "sg:postcode":"95037",
    "sg:province":"CA",
    "sg:tags":[
        "american",
        "pastry"
    ],
    "wof:name":"Marie Callender's",
    "wof:placetype":"venue"
},
  "geometry": {"coordinates":[-121.657222,37.149049],"type":"Point"}
}