{
  "type": "Feature",
  "properties": {
    "addr:full":"111 New Montgomery San Francisco CA 94105",
    "addr:housenumber":"111",
    "addr:postcode":"94105",
    "addr:street":"new montgomery",
    "iso:country":"US",
    "name:eng_x_preferred":[
        "Mapzen"
    ],
    "name:eng_x_variant":[
        "Mapzen West"
    ],
    "wof:name":"Mapzen",
    "wof:placetype":"venue"
},
  "geometry": {"coordinates":[-122.400098,37.787221],"type":"Point"}
}