{
  "type": "Feature",
  "properties": {
    "iso:country":"US",
    "sg:address":"1626 S Mayflower Ave",
    "sg:city":"Monrovia",
    "sg:classifiers":[
        {
            "category":"Manufacturing",
            "subcategory":"Printing",
            "type":"Manufacturing & Wholesale Goods"
        }
    ],
    "sg:phone":"+1 626 358 7979",
    "sg:postcode":"91016",
    "sg:province":"CA",
    "sg:tags":[
        "commercial"
    ],
    "wof:name":"Polished Arrow",
    "wof:placetype":"venue"
},
  "geometry": {"coordinates":[-118.009407,34.134006],"type":"Point"}
}