{
  "type": "Feature",
  "properties": {
    "iso:country":"US",
    "sg:address":"3207 Roymar Rd",
    "sg:city":"Oceanside",
    "sg:classifiers":[
        {
            "category":"Home & Garden",
            "subcategory":"Hardware",
            "type":"Retail Goods"
        }
    ],
    "sg:phone":"+1 760 433 3111",
    "sg:postcode":"92058",
    "sg:province":"CA",
    "wof:name":"ACDCDOORHARDWARE.COM",
    "wof:placetype":"venue"
},
  "geometry": {"coordinates":[-117.350728,33.215882],"type":"Point"}
}