{
  "type": "Feature",
  "properties": {
    "iso:country":"US",
    "sg:address":"10485 Magnolia Ave",
    "sg:city":"Riverside",
    "sg:classifiers":[
        {
            "category":"Personal",
            "subcategory":"Beauty Salon",
            "type":"Services"
        }
    ],
    "sg:phone":"+1 951 637 1965",
    "sg:postcode":"92505",
    "sg:province":"CA",
    "wof:name":"Brockton Hair Corral",
    "wof:placetype":"venue"
},
  "geometry": {"coordinates":[-117.46194300000001,33.911699],"type":"Point"}
}