{
  "type": "Feature",
  "properties": {
    "addr:full":"162 N. Breed Street Los Angeles CA 90033",
    "addr:housenumber":"162",
    "addr:postcode":"90033",
    "addr:street":"N. Breed Street",
    "iso:country":"US",
    "sg:address":"162 N. Breed Street",
    "sg:city":"Los Angeles",
    "sg:classifiers":[
        {
            "category":"Restaurant",
            "type":"Food & Drink"
        }
    ],
    "sg:postcode":"90033",
    "sg:province":"CA",
    "sg:tags":[
        "seafood"
    ],
    "wof:name":"Cuyutlan Colima Marisco Truck",
    "wof:placetype":"venue"
},
  "geometry": {"coordinates":[-118.210171,34.0454],"type":"Point"}
}