{
  "type": "Feature",
  "properties": {
    "addr:full":"1304 Valencia Street San Francisco CA 94110",
    "addr:housenumber":"1304",
    "addr:postcode":"94110",
    "addr:street":"Valencia Street",
    "iso:country":"US",
    "sg:address":"1304 Valencia Street",
    "sg:city":"San Francisco",
    "sg:classifiers":[
        {
            "category":"Coffee & Tea",
            "type":"Food & Drink"
        }
    ],
    "sg:phone":"+1 415 647 7994",
    "sg:postcode":"94110",
    "sg:province":"CA",
    "sg:website":"www.muddywaterscoffeehouse.com/",
    "wof:name":"Muddy's Coffee House",
    "wof:placetype":"venue"
},
  "geometry": {"coordinates":[-122.420998,37.7519],"type":"Point"}
}