{
  "type": "Feature",
  "properties": {
    "iso:country":"US",
    "sg:address":"146 W Arrow Hwy",
    "sg:city":"San Dimas",
    "sg:classifiers":[
        {
            "category":"Social Services",
            "type":"Services"
        }
    ],
    "sg:phone":"+1 909 592 1184",
    "sg:postcode":"91773",
    "sg:province":"CA",
    "sg:tags":[
        "youth",
        "organization",
        "center"
    ],
    "wof:name":"San Dimas Scout House-Spanish",
    "wof:placetype":"venue"
},
  "geometry": {"coordinates":[-117.810892,34.102875],"type":"Point"}
}