{
  "type": "Feature",
  "properties": {
    "addr:full":"12189 5th St Yucaipa CA 92399",
    "addr:housenumber":"12189",
    "addr:postcode":"92399",
    "addr:street":"5Th St",
    "iso:country":"US",
    "sg:address":"12189 5th St",
    "sg:city":"Yucaipa",
    "sg:classifiers":[
        {
            "category":"Building & Trades",
            "subcategory":"Landscaping Services",
            "type":"Services"
        }
    ],
    "sg:phone":"+1 909 790 3807",
    "sg:postcode":"92399",
    "sg:province":"CA",
    "sg:tags":[
        "landscape"
    ],
    "wof:name":"B-West Landscape & Design",
    "wof:placetype":"venue"
},
  "geometry": {"coordinates":[-117.056088,34.030472],"type":"Point"}
}