{
  "type": "Feature",
  "properties": {
    "iso:country":"US",
    "sg:address":"2383 Lomita Blvd #104",
    "sg:city":"Lomita",
    "sg:classifiers":[
        {
            "category":"Bakery",
            "type":"Food & Drink"
        }
    ],
    "sg:phone":"+1 310 257 9454",
    "sg:postcode":"90717",
    "sg:province":"CA",
    "sg:website":"www.patisseriechantilly.com",
    "wof:name":"Patisserie Chantilly",
    "wof:placetype":"venue"
},
  "geometry": {"coordinates":[-118.324956,33.805044],"type":"Point"}
}