{
  "type": "Feature",
  "properties": {
    "addr:full":"6 Hutton Centre Santa Ana CA 92707",
    "addr:housenumber":"6",
    "addr:postcode":"92707",
    "addr:street":"Hutton Centre",
    "iso:country":"US",
    "sg:address":"6 Hutton Centre",
    "sg:city":"Santa Ana",
    "sg:classifiers":[
        {
            "category":"Professional",
            "subcategory":"Art Services",
            "type":"Services"
        },
        {
            "category":"Retail",
            "subcategory":"Animal Services",
            "type":"Services"
        }
    ],
    "sg:phone":"+1 714 333 0414",
    "sg:postcode":"92707",
    "sg:province":"CA",
    "sg:tags":[
        "pet",
        "photographer"
    ],
    "sg:website":"www.dogphotography.org/",
    "wof:name":"Dog & Pet Photography",
    "wof:placetype":"venue"
},
  "geometry": {"coordinates":[-117.865523,33.696003],"type":"Point"}
}