{
  "type": "Feature",
  "properties": {
    "addr:full":"356 Merchant St Vacaville CA 95688",
    "addr:housenumber":"356",
    "addr:postcode":"95688",
    "addr:street":"Merchant St",
    "iso:country":"US",
    "sg:address":"356 Merchant St",
    "sg:city":"Vacaville",
    "sg:classifiers":[
        {
            "category":"Professional",
            "subcategory":"Accounting & Tax Preparation",
            "type":"Services"
        }
    ],
    "sg:phone":"+1 707 469 8299",
    "sg:postcode":"95688",
    "sg:province":"CA",
    "sg:tags":[
        "bookkeeping",
        "general"
    ],
    "wof:name":"Tax Advantage",
    "wof:placetype":"venue"
},
  "geometry": {"coordinates":[-121.98948,38.355537],"type":"Point"}
}