{
  "type": "Feature",
  "properties": {
    "iso:country":"US",
    "sg:address":"26707 Oak Ave",
    "sg:city":"Santa Clarita",
    "sg:classifiers":[
        {
            "category":"Freight",
            "type":"Transportation"
        }
    ],
    "sg:phone":"+1 661 250 8040",
    "sg:postcode":"91351",
    "sg:province":"CA",
    "sg:tags":[
        "trucking"
    ],
    "wof:name":"American Theatrical Express",
    "wof:placetype":"venue"
},
  "geometry": {"coordinates":[-118.50048700000001,34.423446],"type":"Point"}
}