{
  "type": "Feature",
  "properties": {
    "addr:full":"1606 Imperial Ave Modesto CA 95358",
    "addr:housenumber":"1606",
    "addr:postcode":"ca 95358",
    "addr:street":"Imperial Ave",
    "iso:country":"US",
    "sg:address":"1606 Imperial Ave",
    "sg:city":"Modesto",
    "sg:classifiers":[
        {
            "category":"Organizations",
            "subcategory":"Religious Organization",
            "type":"Services"
        }
    ],
    "sg:phone":"+1 209 538 3318",
    "sg:postcode":"95358",
    "sg:province":"CA",
    "sg:tags":[
        "church"
    ],
    "wof:name":"St John Bosco Roman Catholic",
    "wof:placetype":"venue"
},
  "geometry": {"coordinates":[-121.015817,37.600822],"type":"Point"}
}