{
  "type": "Feature",
  "properties": {
    "addr:full":"1485 Bay Shore Blvd San Francisco CA 94124",
    "addr:housenumber":"1485",
    "addr:postcode":"94124",
    "addr:street":"Bay Shore Blvd",
    "iso:country":"US",
    "sg:address":"1485 Bay Shore Blvd",
    "sg:city":"San Francisco",
    "sg:classifiers":[
        {
            "category":"Education",
            "subcategory":"Vocational School",
            "type":"Public Place"
        }
    ],
    "sg:phone":"+1 415 467 7841",
    "sg:postcode":"94124",
    "sg:province":"CA",
    "wof:name":"Ideal Educational Concepts",
    "wof:placetype":"venue"
},
  "geometry": {"coordinates":[-122.401822,37.726775],"type":"Point"}
}