{
  "type": "Feature",
  "properties": {
    "iso:country":"US",
    "sg:address":"2915 Red Hill Avenue",
    "sg:city":"Costa Mesa",
    "sg:classifiers":[
        {
            "category":"Building & Trades",
            "subcategory":"Construction",
            "type":"Services"
        }
    ],
    "sg:phone":"+1 714 540 5959",
    "sg:postcode":"92626",
    "sg:province":"CA",
    "sg:tags":[
        "interior",
        "design"
    ],
    "wof:name":"Bastideaux Home Interiors",
    "wof:placetype":"venue"
},
  "geometry": {"coordinates":[-117.880703,33.667948],"type":"Point"}
}