{
  "type": "Feature",
  "properties": {
    "addr:full":"1735 83rd Ave Oakland CA 94621",
    "addr:housenumber":"1735",
    "addr:postcode":"94621",
    "addr:street":"83Rd Ave",
    "iso:country":"US",
    "sg:address":"1735 83rd Ave",
    "sg:city":"Oakland",
    "sg:classifiers":[
        {
            "category":"Social Services",
            "subcategory":"Child Care",
            "type":"Services"
        }
    ],
    "sg:phone":"+1 510 562 6834",
    "sg:postcode":"94621",
    "sg:province":"CA",
    "wof:name":"Little Angel Day Care",
    "wof:placetype":"venue"
},
  "geometry": {"coordinates":[-122.17368999999999,37.757464],"type":"Point"}
}