{
  "type": "Feature",
  "properties": {
    "iso:country":"US",
    "sg:address":"4655 Cass St Suite 404",
    "sg:city":"San Diego",
    "sg:classifiers":[
        {
            "category":"Real Estate",
            "subcategory":"Architect",
            "type":"Services"
        }
    ],
    "sg:phone":"+1 858 605 0937",
    "sg:postcode":"92109",
    "sg:province":"CA",
    "sg:website":"www.pattersoneng.com/",
    "wof:name":"Patterson Engineering, Inc",
    "wof:placetype":"venue"
},
  "geometry": {"coordinates":[-117.252199,32.799506],"type":"Point"}
}