{
  "type": "Feature",
  "properties": {
    "addr:full":"187 Mace St Chula Vista CA 91911",
    "addr:housenumber":"187",
    "addr:postcode":"91911",
    "addr:street":"Mace St",
    "iso:country":"US",
    "sg:address":"187 Mace St",
    "sg:city":"Chula Vista",
    "sg:classifiers":[
        {
            "category":"Freight",
            "type":"Transportation"
        }
    ],
    "sg:phone":"+1 619 498 0680",
    "sg:postcode":"91911",
    "sg:province":"CA",
    "sg:tags":[
        "trucking"
    ],
    "wof:name":"Landstar Ranger Inc",
    "wof:placetype":"venue"
},
  "geometry": {"coordinates":[-117.05362700000001,32.591731],"type":"Point"}
}