{
  "type": "Feature",
  "properties": {
    "iso:country":"US",
    "sg:address":"19536 Valley Ford Dr",
    "sg:city":"Cottonwood",
    "sg:classifiers":[
        {
            "category":"Freight",
            "type":"Transportation"
        }
    ],
    "sg:phone":"+1 530 347 5059",
    "sg:postcode":"96022",
    "sg:province":"CA",
    "sg:tags":[
        "trucking"
    ],
    "wof:name":"Fuller Trucking",
    "wof:placetype":"venue"
},
  "geometry": {"coordinates":[-122.211226,40.365155],"type":"Point"}
}