{
  "type": "Feature",
  "properties": {
    "addr:full":"2001 Bridgeway Sausalito CA 94965",
    "addr:housenumber":"2001",
    "addr:postcode":"94965",
    "addr:street":"Bridgeway",
    "iso:country":"US",
    "sg:address":"2001 Bridgeway",
    "sg:city":"Sausalito",
    "sg:classifiers":[
        {
            "category":"Health Services",
            "subcategory":"Chiropractor",
            "type":"Services"
        }
    ],
    "sg:phone":"+1 415 332 4304",
    "sg:postcode":"94965",
    "sg:province":"CA",
    "sg:tags":[
        "chiropractic"
    ],
    "wof:name":"Shaneyfelt, Dwight DC",
    "wof:placetype":"venue"
},
  "geometry": {"coordinates":[-122.494743,37.862068],"type":"Point"}
}