{
  "type": "Feature",
  "properties": {
    "addr:full":"1134 Soquel Ave., Santa Cruz, CA",
    "iso:country":"US",
    "name:eng_x_preferred":[
        "Crepe Place"
    ],
    "wof:name":"Crepe Place",
    "wof:placetype":"venue"
},
  "geometry": {"coordinates":[-122.01110243797,36.979543731057],"type":"Point"}
}