{
  "type": "Feature",
  "properties": {
    "iso:country":"US",
    "sg:address":"1647 Hollenbeck Ave",
    "sg:city":"Sunnyvale",
    "sg:classifiers":[
        {
            "category":"Restaurant",
            "type":"Food & Drink"
        }
    ],
    "sg:phone":"+1 408 735 1777",
    "sg:postcode":"94087",
    "sg:province":"CA",
    "sg:tags":[
        "sushi",
        "bar"
    ],
    "wof:name":"Bay Sushi",
    "wof:placetype":"venue"
},
  "geometry": {"coordinates":[-122.042,37.339401],"type":"Point"}
}