{
  "type": "Feature",
  "properties": {
    "addr:full":"12850 Saratoga-Sunnyvale Rd Saratoga CA 95070",
    "addr:housenumber":"12850",
    "addr:postcode":"95070",
    "addr:street":"Saratoga-Sunnyvale Rd",
    "iso:country":"US",
    "sg:address":"12850 Saratoga-Sunnyvale Rd",
    "sg:city":"Saratoga",
    "sg:classifiers":[
        {
            "category":"Coffee & Tea",
            "type":"Food & Drink"
        }
    ],
    "sg:phone":"+1 408 867 1732",
    "sg:postcode":"95070",
    "sg:province":"CA",
    "sg:website":"www.starbucks.com",
    "wof:name":"Starbucks",
    "wof:placetype":"venue"
},
  "geometry": {"coordinates":[-122.03230000000001,37.281763],"type":"Point"}
}