{
  "type": "Feature",
  "properties": {
    "addr:full":"1616 Parkwood Dr San Mateo CA 94403",
    "addr:housenumber":"1616",
    "addr:postcode":"94403",
    "addr:street":"Parkwood Dr",
    "iso:country":"US",
    "sg:address":"1616 Parkwood Dr",
    "sg:city":"San Mateo",
    "sg:classifiers":[
        {
            "category":"Building & Trades",
            "subcategory":"Construction",
            "type":"Services"
        },
        {
            "category":"Shopping",
            "subcategory":"Computers & Home Electronics",
            "type":"Retail Goods"
        },
        {
            "category":"Professional",
            "subcategory":"Computer Services",
            "type":"Services"
        }
    ],
    "sg:phone":"+1 650 280 5696",
    "sg:postcode":"94403",
    "sg:province":"CA",
    "sg:tags":[
        "repair",
        "contractor"
    ],
    "wof:name":"Wired Solutions",
    "wof:placetype":"venue"
},
  "geometry": {"coordinates":[-122.33076199999999,37.524418],"type":"Point"}
}