{
  "type": "Feature",
  "properties": {
    "iso:country":"US",
    "sg:address":"683 McAllister Street",
    "sg:city":"San Francisco",
    "sg:classifiers":[
        {
            "category":"Building & Trades",
            "subcategory":"Construction",
            "type":"Services"
        }
    ],
    "sg:phone":"+1 415 749 2700",
    "sg:postcode":"94102",
    "sg:province":"CA",
    "sg:tags":[
        "contractor"
    ],
    "wof:name":"Saarman Construction Ltd Hardi Products Installer",
    "wof:placetype":"venue"
},
  "geometry": {"coordinates":[-122.422997,37.779598],"type":"Point"}
}