{
  "type": "Feature",
  "properties": {
    "addr:full":"9533 Cameron St Rancho Cucamonga CA 91730",
    "addr:housenumber":"9533",
    "addr:postcode":"91730",
    "addr:street":"Cameron St",
    "iso:country":"US",
    "sg:address":"9533 Cameron St",
    "sg:city":"Rancho Cucamonga",
    "sg:classifiers":[
        {
            "category":"Building & Trades",
            "subcategory":"Plumbing",
            "type":"Services"
        }
    ],
    "sg:phone":"+1 909 980 5107",
    "sg:postcode":"91730",
    "sg:province":"CA",
    "sg:tags":[
        "contractor"
    ],
    "wof:name":"Er Air Conditioning & Heating",
    "wof:placetype":"venue"
},
  "geometry": {"coordinates":[-117.594532,34.086928],"type":"Point"}
}