{
  "type": "Feature",
  "properties": {
    "iso:country":"US",
    "sg:address":"8261 Crossoak Way",
    "sg:city":"Orangevale",
    "sg:classifiers":[
        {
            "category":"Building & Trades",
            "subcategory":"Electrical",
            "type":"Services"
        }
    ],
    "sg:phone":"+1 916 721 7021",
    "sg:postcode":"95662",
    "sg:province":"CA",
    "sg:tags":[
        "electrical",
        "contractor"
    ],
    "wof:name":"Pro Tech Communications",
    "wof:placetype":"venue"
},
  "geometry": {"coordinates":[-121.257643,38.693683],"type":"Point"}
}