{
  "type": "Feature",
  "properties": {
    "iso:country":"US",
    "sg:address":"10 Lombard St",
    "sg:city":"San Francisco",
    "sg:classifiers":[
        {
            "category":"Wholesale",
            "subcategory":"Seafood",
            "type":"Manufacturing & Wholesale Goods"
        }
    ],
    "sg:phone":"+1 415 788 3474",
    "sg:postcode":"94111",
    "sg:province":"CA",
    "sg:tags":[
        "fish"
    ],
    "wof:name":"Slade Gorton & Co",
    "wof:placetype":"venue"
},
  "geometry": {"coordinates":[-122.403267,37.804116],"type":"Point"}
}