{
  "type": "Feature",
  "properties": {
    "addr:full":"3227 Edward Ave Santa Clara CA 95054",
    "addr:housenumber":"3227",
    "addr:postcode":"95054",
    "addr:street":"Edward Ave",
    "iso:country":"US",
    "sg:address":"3227 Edward Ave",
    "sg:city":"Santa Clara",
    "sg:classifiers":[
        {
            "category":"Home & Garden",
            "subcategory":"Furniture",
            "type":"Retail Goods"
        }
    ],
    "sg:phone":"+1 408 980 1207",
    "sg:postcode":"95054",
    "sg:province":"CA",
    "sg:tags":[
        "top",
        "counter"
    ],
    "wof:name":"Superior Laminating",
    "wof:placetype":"venue"
},
  "geometry": {"coordinates":[-121.94076,37.384554],"type":"Point"}
}