{
  "type": "Feature",
  "properties": {
    "iso:country":"US",
    "sg:address":"22794 Elliot Rd",
    "sg:city":"Acampo",
    "sg:classifiers":[
        {
            "category":"Shopping",
            "subcategory":"Beauty & Cosmetics",
            "type":"Retail Goods"
        }
    ],
    "sg:phone":"+1 209 406 7537",
    "sg:postcode":"95220",
    "sg:province":"CA",
    "sg:tags":[
        "merchandise"
    ],
    "wof:name":"Michele Velasquez",
    "wof:placetype":"venue"
},
  "geometry": {"coordinates":[-121.170557,38.193878],"type":"Point"}
}