{
  "type": "Feature",
  "properties": {
    "addr:full":"3189 Hudson Dr Brentwood CA 94513",
    "addr:housenumber":"3189",
    "addr:postcode":"ca 94513",
    "addr:street":"Hudson Dr",
    "iso:country":"US",
    "sg:address":"3189 Hudson Dr",
    "sg:city":"Brentwood",
    "sg:classifiers":[
        {
            "category":"Professional",
            "subcategory":"Advertising",
            "type":"Services"
        }
    ],
    "sg:phone":"+1 925 954 5256",
    "sg:postcode":"94513",
    "sg:province":"CA",
    "sg:tags":[
        "marketing"
    ],
    "wof:name":"DoorJamb Productions",
    "wof:placetype":"venue"
},
  "geometry": {"coordinates":[-121.694222,37.923036],"type":"Point"}
}