{
  "type": "Feature",
  "properties": {
    "addr:full":"9265 Dowdy Dr San Diego CA 92126",
    "addr:housenumber":"9265",
    "addr:postcode":"92126",
    "addr:street":"Dowdy Dr",
    "iso:country":"US",
    "sg:address":"9265 Dowdy Dr",
    "sg:city":"San Diego",
    "sg:classifiers":[
        {
            "category":"Freight",
            "type":"Transportation"
        }
    ],
    "sg:phone":"+1 858 549 1045",
    "sg:postcode":"92126",
    "sg:province":"CA",
    "sg:tags":[
        "passe",
        "local",
        "help",
        "supply"
    ],
    "wof:name":"Santa Fe Medical Transport",
    "wof:placetype":"venue"
},
  "geometry": {"coordinates":[-117.145742,32.88868],"type":"Point"}
}