{
  "type": "Feature",
  "properties": {
    "iso:country":"US",
    "sg:address":"2519 Mallory St",
    "sg:city":"Los Angeles",
    "sg:classifiers":[
        {
            "category":"Wholesale",
            "subcategory":"Electrical",
            "type":"Manufacturing & Wholesale Goods"
        }
    ],
    "sg:phone":"+1 323 221 3067",
    "sg:postcode":"90032",
    "sg:province":"CA",
    "sg:tags":[
        "equipment"
    ],
    "wof:name":"Rock Solid Security Systems",
    "wof:placetype":"venue"
},
  "geometry": {"coordinates":[-118.177613,34.075081],"type":"Point"}
}