{
  "type": "Feature",
  "properties": {
    "iso:country":"US",
    "sg:address":"1200 el Camino Real",
    "sg:city":"Millbrae",
    "sg:classifiers":[
        {
            "category":"Health Services",
            "subcategory":"Doctor",
            "type":"Services"
        }
    ],
    "sg:phone":"+1 650 742 2511",
    "sg:postcode":"94030",
    "sg:province":"CA",
    "sg:tags":[
        "physician",
        "surgeon"
    ],
    "wof:name":"David S Duffy MD",
    "wof:placetype":"venue"
},
  "geometry": {"coordinates":[-122.399683,37.608543],"type":"Point"}
}