{
  "type": "Feature",
  "properties": {
    "iso:country":"US",
    "sg:address":"25655 Springbrook Ave Ste 4A",
    "sg:city":"Santa Clarita",
    "sg:classifiers":[
        {
            "category":"Building & Trades",
            "subcategory":"Construction",
            "type":"Services"
        },
        {
            "category":"Real Estate",
            "subcategory":"Architect",
            "type":"Services"
        }
    ],
    "sg:phone":"+1 661 260 1700",
    "sg:postcode":"91350",
    "sg:province":"CA",
    "sg:tags":[
        "contractor"
    ],
    "wof:name":"MK Design",
    "wof:placetype":"venue"
},
  "geometry": {"coordinates":[-118.53850199999999,34.40798],"type":"Point"}
}