{
  "type": "Feature",
  "properties": {
    "addr:full":"7000 Eastern Avenue Bell Gardens CA 90201",
    "addr:housenumber":"7000",
    "addr:postcode":"90201",
    "addr:street":"Eastern Avenue",
    "iso:country":"US",
    "sg:address":"7000 Eastern Avenue",
    "sg:city":"Bell Gardens",
    "sg:classifiers":[
        {
            "category":"Restaurant",
            "type":"Food & Drink"
        }
    ],
    "sg:phone":"+1 323 560 9020",
    "sg:postcode":"90201",
    "sg:province":"CA",
    "sg:tags":[
        "pizza"
    ],
    "wof:name":"Red Brick Pizza",
    "wof:placetype":"venue"
},
  "geometry": {"coordinates":[-118.164461,33.969374],"type":"Point"}
}