{
  "type": "Feature",
  "properties": {
    "addr:full":"640 W Brooks St Ontario CA 91762",
    "addr:housenumber":"640",
    "addr:postcode":"91762",
    "addr:street":"W Brooks St",
    "iso:country":"US",
    "sg:address":"640 W Brooks St",
    "sg:city":"Ontario",
    "sg:classifiers":[
        {
            "category":"Wholesale",
            "subcategory":"Auto Parts",
            "type":"Manufacturing & Wholesale Goods"
        }
    ],
    "sg:phone":"+1 909 983 2651",
    "sg:postcode":"91762",
    "sg:province":"CA",
    "sg:tags":[
        "automobile",
        "supply"
    ],
    "wof:name":"Parkway Automotive Warehouse",
    "wof:placetype":"venue"
},
  "geometry": {"coordinates":[-117.65770999999999,34.062498],"type":"Point"}
}