{
  "type": "Feature",
  "properties": {
    "addr:full":"1516 N San Fernando Blvd Suite 206 Burbank CA 91504",
    "addr:housenumber":"1516",
    "addr:postcode":"91504",
    "addr:street":"N San Fernando Blvd Suite 206",
    "iso:country":"US",
    "sg:address":"1516 N San Fernando Blvd Suite 206",
    "sg:city":"Burbank",
    "sg:classifiers":[
        {
            "category":"Autos & Motor Vehicles",
            "subcategory":"Automobile Sales",
            "type":"Retail Goods"
        }
    ],
    "sg:phone":"+1 888 422 7792",
    "sg:postcode":"91504",
    "sg:province":"CA",
    "sg:tags":[
        "car"
    ],
    "sg:website":"www.icars.net",
    "wof:name":"iCars Inc.",
    "wof:placetype":"venue"
},
  "geometry": {"coordinates":[-118.32258400000001,34.191311],"type":"Point"}
}