{
  "type": "Feature",
  "properties": {
    "iso:country":"US",
    "sg:address":"303 Water Street Suite 10",
    "sg:city":"Santa Cruz",
    "sg:classifiers":[
        {
            "category":"Professional",
            "subcategory":"Lawyer & Legal Services",
            "type":"Services"
        }
    ],
    "sg:phone":"+1 831 426 9232",
    "sg:postcode":"95060",
    "sg:province":"CA",
    "sg:tags":[
        "divorce",
        "law",
        "family"
    ],
    "wof:name":"Laberge Stephen Attorney",
    "wof:placetype":"venue"
},
  "geometry": {"coordinates":[-122.022975,36.979148],"type":"Point"}
}