{
  "type": "Feature",
  "properties": {
    "addr:full":"33 E Alisal St Salinas CA 93901",
    "addr:housenumber":"33",
    "addr:postcode":"93901",
    "addr:street":"E Alisal St",
    "iso:country":"US",
    "sg:address":"33 E Alisal St",
    "sg:city":"Salinas",
    "sg:classifiers":[
        {
            "category":"Government",
            "subcategory":"Office",
            "type":"Public Place"
        }
    ],
    "sg:phone":"+1 831 775 0884",
    "sg:postcode":"93901",
    "sg:province":"CA",
    "sg:tags":[
        "international",
        "affairs"
    ],
    "wof:name":"Alisal Immigration & Tax Svcs",
    "wof:placetype":"venue"
},
  "geometry": {"coordinates":[-121.653498,36.674079],"type":"Point"}
}