{
  "type": "Feature",
  "properties": {
    "iso:country":"US",
    "sg:address":"3715 W Rosecrans Ave",
    "sg:city":"Hawthorne",
    "sg:classifiers":[
        {
            "category":"Retail",
            "subcategory":"Laundry & Dry Cleaning",
            "type":"Services"
        }
    ],
    "sg:phone":"+1 310 675 8200",
    "sg:postcode":"90250",
    "sg:province":"CA",
    "sg:tags":[
        "linen",
        "supply"
    ],
    "wof:name":"Custom Linen",
    "wof:placetype":"venue"
},
  "geometry": {"coordinates":[-118.337935,33.901992],"type":"Point"}
}