{
  "type": "Feature",
  "properties": {
    "iso:country":"US",
    "sg:address":"2663 Canyon Springs Pkwy",
    "sg:city":"Riverside",
    "sg:classifiers":[
        {
            "category":"Health Services",
            "subcategory":"Optometrist",
            "type":"Services"
        }
    ],
    "sg:phone":"+1 951 656 7218",
    "sg:postcode":"92507",
    "sg:province":"CA",
    "wof:name":"Systems National Visioncare",
    "wof:placetype":"venue"
},
  "geometry": {"coordinates":[-117.283689,33.941638],"type":"Point"}
}