{
  "type": "Feature",
  "properties": {
    "addr:full":"1353 Broadway Placerville CA 95667",
    "addr:housenumber":"1353",
    "addr:postcode":"95667",
    "addr:street":"Broadway",
    "iso:country":"US",
    "sg:address":"1353 Broadway",
    "sg:city":"Placerville",
    "sg:classifiers":[
        {
            "category":"Real Estate",
            "subcategory":"Real Estate Agent",
            "type":"Services"
        }
    ],
    "sg:phone":"+1 530 622 5000",
    "sg:postcode":"95667",
    "sg:province":"CA",
    "wof:name":"Mother Lode Realty",
    "wof:placetype":"venue"
},
  "geometry": {"coordinates":[-120.780928,38.732156],"type":"Point"}
}