{
  "type": "Feature",
  "properties": {
    "iso:country":"US",
    "sg:address":"11500 Sheldon St",
    "sg:city":"Sun Valley",
    "sg:classifiers":[
        {
            "category":"Communications",
            "subcategory":"Film & Video Production",
            "type":"Services"
        }
    ],
    "sg:phone":"+1 818 768 3800",
    "sg:postcode":"91352",
    "sg:province":"CA",
    "sg:tags":[
        "motion",
        "picture",
        "studio",
        "producer"
    ],
    "wof:name":"Premiere Props",
    "wof:placetype":"venue"
},
  "geometry": {"coordinates":[-118.382104,34.247967],"type":"Point"}
}