{
  "type": "Feature",
  "properties": {
    "addr:full":"442 Ignacio Blvd Novato CA 94949",
    "addr:housenumber":"442",
    "addr:postcode":"94949",
    "addr:street":"Ignacio Blvd",
    "iso:country":"US",
    "sg:address":"442 Ignacio Blvd",
    "sg:city":"Novato",
    "sg:phone":"+1 800 615 7352",
    "sg:postcode":"94949",
    "sg:province":"CA",
    "sg:website":"http://sanfrancisco.citysearch.com/profile/external/40036262/novato_ca/curves.html?publisher=yellowpages&reference_id=1&placement=ypwebsitemip",
    "wof:name":"Curves",
    "wof:placetype":"venue"
},
  "geometry": {"coordinates":[-122.542283,38.066187],"type":"Point"}
}