{
  "type": "Feature",
  "properties": {
    "addr:full":"41658 Ivy St Murrieta CA 92562",
    "addr:housenumber":"41658",
    "addr:postcode":"92562",
    "addr:street":"Ivy St",
    "iso:country":"US",
    "sg:address":"41658 Ivy St",
    "sg:city":"Murrieta",
    "sg:classifiers":[
        {
            "category":"Personal",
            "subcategory":"Barber",
            "type":"Services"
        }
    ],
    "sg:phone":"+1 951 894 4331",
    "sg:postcode":"92562",
    "sg:province":"CA",
    "wof:name":"Payd 2 Fade Barber Shop",
    "wof:placetype":"venue"
},
  "geometry": {"coordinates":[-117.20631400000001,33.554595],"type":"Point"}
}