{
  "type": "Feature",
  "properties": {
    "addr:full":"526 I St Los Banos CA 93635",
    "addr:housenumber":"526",
    "addr:postcode":"93635",
    "addr:street":"I St",
    "iso:country":"US",
    "sg:address":"526 I St",
    "sg:city":"Los Banos",
    "sg:classifiers":[
        {
            "category":"Organizations",
            "subcategory":"Religious Organization",
            "type":"Services"
        }
    ],
    "sg:phone":"+1 209 826 1162",
    "sg:postcode":"93635",
    "sg:province":"CA",
    "sg:tags":[
        "church"
    ],
    "wof:name":"His Hands Extended Ministry",
    "wof:placetype":"venue"
},
  "geometry": {"coordinates":[-120.84899799999999,37.061463],"type":"Point"}
}