{
  "type": "Feature",
  "properties": {
    "iso:country":"US",
    "sg:address":"2530 Vista Way #F280",
    "sg:city":"Oceanside",
    "sg:classifiers":[
        {
            "category":"Insurance",
            "subcategory":"Hazard Insurance",
            "type":"Services"
        }
    ],
    "sg:phone":"+1 888 539 8885",
    "sg:postcode":"92054",
    "sg:province":"CA",
    "sg:website":"www.AmritaFinancial.com",
    "wof:name":"Amrita Financial",
    "wof:placetype":"venue"
},
  "geometry": {"coordinates":[-117.332142,33.183232],"type":"Point"}
}