{
  "type": "Feature",
  "properties": {
    "iso:country":"US",
    "sg:address":"114 Great Mall Dr",
    "sg:city":"Milpitas",
    "sg:classifiers":[
        {
            "category":"Shopping",
            "subcategory":"Clothing, Apparel, & Fashions",
            "type":"Retail Goods"
        }
    ],
    "sg:phone":"+1 408 586 9109",
    "sg:postcode":"95035",
    "sg:province":"CA",
    "wof:name":"Eiffel Handbags & Accessories",
    "wof:placetype":"venue"
},
  "geometry": {"coordinates":[-121.90183,37.418911],"type":"Point"}
}