{
  "type": "Feature",
  "properties": {
    "iso:country":"US",
    "sg:address":"123 Willow Creek Ct",
    "sg:city":"Watsonville",
    "sg:classifiers":[
        {
            "category":"Professional",
            "type":"Services"
        }
    ],
    "sg:phone":"+1 831 724 0978",
    "sg:postcode":"95076",
    "sg:province":"CA",
    "wof:name":"Jimmy Cannizzaro",
    "wof:placetype":"venue"
},
  "geometry": {"coordinates":[-121.775639,36.929263],"type":"Point"}
}