{
  "type": "Feature",
  "properties": {
    "iso:country":"US",
    "sg:address":"81 Mayhew Way",
    "sg:city":"Walnut Creek",
    "sg:classifiers":[
        {
            "category":"Real Estate",
            "subcategory":"Real Estate Operator",
            "type":"Services"
        }
    ],
    "sg:phone":"+1 925 939 3393",
    "sg:postcode":"94597",
    "sg:province":"CA",
    "sg:tags":[
        "apartment"
    ],
    "wof:name":"Walnut Creek Manor",
    "wof:placetype":"venue"
},
  "geometry": {"coordinates":[-122.05728999999999,37.936743],"type":"Point"}
}