{
  "type": "Feature",
  "properties": {
    "iso:country":"US",
    "sg:address":"16508 S Vermont Ave",
    "sg:city":"Gardena",
    "sg:classifiers":[
        {
            "category":"Shopping",
            "subcategory":"Gifts & Souvenirs",
            "type":"Retail Goods"
        }
    ],
    "sg:phone":"+1 310 719 9513",
    "sg:postcode":"90247",
    "sg:province":"CA",
    "sg:tags":[
        "shop"
    ],
    "wof:name":"Julia's Gifts",
    "wof:placetype":"venue"
},
  "geometry": {"coordinates":[-118.291192,33.88121],"type":"Point"}
}