{
  "type": "Feature",
  "properties": {
    "iso:country":"US",
    "sg:address":"489 S Robertson Blvd",
    "sg:city":"Beverly Hills",
    "sg:classifiers":[
        {
            "category":"Banks & Credit Unions",
            "subcategory":"Investment Brokerage",
            "type":"Services"
        }
    ],
    "sg:phone":"+1 310 550 1899",
    "sg:postcode":"90211",
    "sg:province":"CA",
    "sg:tags":[
        "advisory",
        "financial"
    ],
    "wof:name":"Star Trade World Inc",
    "wof:placetype":"venue"
},
  "geometry": {"coordinates":[-118.383534,34.062937],"type":"Point"}
}