{
  "type": "Feature",
  "properties": {
    "iso:country":"US",
    "sg:address":"1317 Oakdale Rd Ste 1110",
    "sg:city":"Modesto",
    "sg:classifiers":[
        {
            "category":"Real Estate",
            "subcategory":"Real Estate Services",
            "type":"Services"
        },
        {
            "category":"Real Estate",
            "subcategory":"Real Estate Agent",
            "type":"Services"
        }
    ],
    "sg:phone":"+1 209 576 1452",
    "sg:postcode":"95355",
    "sg:province":"CA",
    "sg:tags":[
        "management"
    ],
    "wof:name":"Choice Investments Realty",
    "wof:placetype":"venue"
},
  "geometry": {"coordinates":[-120.95755699999999,37.662329],"type":"Point"}
}