{
  "type": "Feature",
  "properties": {
    "iso:country":"US",
    "sg:address":"730 I St",
    "sg:city":"Sacramento",
    "sg:classifiers":[
        {
            "category":"Education",
            "subcategory":"Library",
            "type":"Public Place"
        }
    ],
    "sg:phone":"+1 916 264 2855",
    "sg:postcode":"95814",
    "sg:province":"CA",
    "wof:name":"Mobile Library",
    "wof:placetype":"venue"
},
  "geometry": {"coordinates":[-121.495996,38.582148],"type":"Point"}
}