{
  "type": "Feature",
  "properties": {
    "addr:full":"730 I St Sacramento CA 95814",
    "addr:housenumber":"730",
    "addr:postcode":"95814",
    "addr:street":"I St",
    "iso:country":"US",
    "sg:address":"730 I St",
    "sg:city":"Sacramento",
    "sg:classifiers":[
        {
            "category":"Education",
            "subcategory":"Library",
            "type":"Public Place"
        }
    ],
    "sg:phone":"+1 916 264 2855",
    "sg:postcode":"95814",
    "sg:province":"CA",
    "wof:name":"Mobile Library",
    "wof:placetype":"venue"
},
  "geometry": {"coordinates":[-121.49599600000001,38.582148],"type":"Point"}
}