{
  "type": "Feature",
  "properties": {
    "addr:full":"8194 Clover Way Buena Park CA 90620",
    "addr:housenumber":"8194",
    "addr:postcode":"90620",
    "addr:street":"Clover Way",
    "iso:country":"US",
    "sg:address":"8194 Clover Way",
    "sg:city":"Buena Park",
    "sg:classifiers":[
        {
            "category":"Personal",
            "type":"Services"
        }
    ],
    "sg:phone":"+1 714 334 1145",
    "sg:postcode":"90620",
    "sg:province":"CA",
    "sg:tags":[
        "local"
    ],
    "sg:website":"www.tmservicescompany.com",
    "wof:name":"TM Services Company",
    "wof:placetype":"venue"
},
  "geometry": {"coordinates":[-117.990105,33.850985],"type":"Point"}
}