{
  "type": "Feature",
  "properties": {
    "addr:full":"1156 Mc Kendrie St San Jose CA 95126",
    "addr:housenumber":"1156",
    "addr:postcode":"95126",
    "addr:street":"Mc Kendrie St",
    "iso:country":"US",
    "sg:address":"1156 Mc Kendrie St",
    "sg:city":"San Jose",
    "sg:classifiers":[
        {
            "category":"Building & Trades",
            "subcategory":"Construction",
            "type":"Services"
        }
    ],
    "sg:phone":"+1 408 264 7052",
    "sg:postcode":"95126",
    "sg:province":"CA",
    "sg:tags":[
        "steam",
        "cleaning"
    ],
    "wof:name":"Custom Steam Cleaners",
    "wof:placetype":"venue"
},
  "geometry": {"coordinates":[-121.924848,37.341164],"type":"Point"}
}