{
  "type": "Feature",
  "properties": {
    "addr:full":"435 4th Ave Gustine CA 95322",
    "addr:housenumber":"435",
    "addr:postcode":"95322",
    "addr:street":"4Th Ave",
    "iso:country":"US",
    "sg:address":"435 4th Ave",
    "sg:city":"Gustine",
    "sg:classifiers":[
        {
            "category":"Autos & Motor Vehicles",
            "subcategory":"Automobile Sales",
            "type":"Retail Goods"
        }
    ],
    "sg:phone":"+1 209 854 2433",
    "sg:postcode":"95322",
    "sg:province":"CA",
    "sg:tags":[
        "truck"
    ],
    "wof:name":"Depot Garage GMC",
    "wof:placetype":"venue"
},
  "geometry": {"coordinates":[-120.99927099999999,37.25619],"type":"Point"}
}