{
  "type": "Feature",
  "properties": {
    "iso:country":"US",
    "sg:address":"31880 Castaic Rd",
    "sg:city":"Castaic",
    "sg:classifiers":[
        {
            "category":"Restaurant",
            "type":"Food & Drink"
        }
    ],
    "sg:phone":"+1 661 607 0117",
    "sg:postcode":"91384",
    "sg:province":"CA",
    "sg:tags":[
        "chinese"
    ],
    "sg:website":"www.pandaexpress.com",
    "wof:name":"Panda Express",
    "wof:placetype":"venue"
},
  "geometry": {"coordinates":[-118.622393,34.496466],"type":"Point"}
}