{
  "type": "Feature",
  "properties": {
    "iso:country":"US",
    "sg:address":"123 Los Altos St",
    "sg:city":"Oxnard",
    "sg:classifiers":[
        {
            "category":"Professional",
            "type":"Services"
        }
    ],
    "sg:phone":"+1 805 815 4532",
    "sg:postcode":"93035",
    "sg:province":"CA",
    "sg:tags":[
        "establishment"
    ],
    "wof:name":"Sunny Coast Yachts",
    "wof:placetype":"venue"
},
  "geometry": {"coordinates":[-119.233019,34.17234],"type":"Point"}
}