{
  "type": "Feature",
  "properties": {
    "iso:country":"US",
    "sg:address":"5042 Wilshire Blvd",
    "sg:city":"Los Angeles",
    "sg:classifiers":[
        {
            "category":"Insurance",
            "subcategory":"Insurance Agent",
            "type":"Services"
        }
    ],
    "sg:phone":"+1 323 735 0449",
    "sg:postcode":"90036",
    "sg:province":"CA",
    "wof:name":"IMA",
    "wof:placetype":"venue"
},
  "geometry": {"coordinates":[-118.338814,34.062045],"type":"Point"}
}