{
  "type": "Feature",
  "properties": {
    "addr:full":"760 N Main St Orange CA 92868",
    "addr:housenumber":"760",
    "addr:postcode":"92868",
    "addr:street":"N Main St",
    "iso:country":"US",
    "sg:address":"760 N Main St",
    "sg:city":"Orange",
    "sg:classifiers":[
        {
            "category":"Building & Trades",
            "subcategory":"Construction",
            "type":"Services"
        }
    ],
    "sg:phone":"+1 714 771 4982",
    "sg:postcode":"92868",
    "sg:province":"CA",
    "sg:tags":[
        "contractor"
    ],
    "wof:name":"B & J Construction Co",
    "wof:placetype":"venue"
},
  "geometry": {"coordinates":[-117.866624,33.798553],"type":"Point"}
}