{
  "type": "Feature",
  "properties": {
    "iso:country":"US",
    "sg:address":"6230 Wilshire Blvd",
    "sg:city":"Los Angeles",
    "sg:classifiers":[
        {
            "category":"Wholesale",
            "subcategory":"Apparel",
            "type":"Manufacturing & Wholesale Goods"
        },
        {
            "category":"Professional",
            "subcategory":"Business Services",
            "type":"Services"
        }
    ],
    "sg:phone":"+1 323 931 1576",
    "sg:postcode":"90048",
    "sg:province":"CA",
    "sg:tags":[
        "interior",
        "consultant",
        "piece",
        "design",
        "decorator"
    ],
    "wof:name":"Jacques Bouvet Et Cie Ltd",
    "wof:placetype":"venue"
},
  "geometry": {"coordinates":[-118.364718,34.063258],"type":"Point"}
}