{
  "type": "Feature",
  "properties": {
    "iso:country":"US",
    "sg:address":"8382 Artesia Blvd",
    "sg:city":"Buena Park",
    "sg:classifiers":[
        {
            "category":"Building & Trades",
            "subcategory":"Construction",
            "type":"Services"
        }
    ],
    "sg:phone":"+1 714 521 7766",
    "sg:postcode":"90621",
    "sg:province":"CA",
    "sg:tags":[
        "contractor"
    ],
    "wof:name":"Advanced Display Solution",
    "wof:placetype":"venue"
},
  "geometry": {"coordinates":[-117.98563,33.873495],"type":"Point"}
}