{
  "type": "Feature",
  "properties": {
    "iso:country":"US",
    "sg:address":"786 W 17th St",
    "sg:city":"Costa Mesa",
    "sg:classifiers":[
        {
            "category":"Retail",
            "subcategory":"Auto Repair",
            "type":"Services"
        }
    ],
    "sg:phone":"+1 949 646 0710",
    "sg:postcode":"92627",
    "sg:province":"CA",
    "sg:tags":[
        "body",
        "automobile",
        "used"
    ],
    "wof:name":"Golden Paint & Body",
    "wof:placetype":"venue"
},
  "geometry": {"coordinates":[-117.928142,33.636218],"type":"Point"}
}