{
  "type": "Feature",
  "properties": {
    "iso:country":"US",
    "sg:address":"4911 Van Nuys Blvd",
    "sg:city":"Van Nuys",
    "sg:classifiers":[
        {
            "category":"Health Services",
            "subcategory":"Medical Lab",
            "type":"Services"
        }
    ],
    "sg:phone":"+1 818 990 3191",
    "sg:postcode":"91403",
    "sg:province":"CA",
    "sg:tags":[
        "laboratory"
    ],
    "wof:name":"Valley Open Mri Ctr",
    "wof:placetype":"venue"
},
  "geometry": {"coordinates":[-118.448773,34.161044],"type":"Point"}
}