{
  "type": "Feature",
  "properties": {
    "addr:full":"40326 Greenwood Way Oakhurst CA 93644",
    "addr:housenumber":"40326",
    "addr:postcode":"93644",
    "addr:street":"Greenwood Way",
    "iso:country":"US",
    "sg:address":"40326 Greenwood Way",
    "sg:city":"Oakhurst",
    "sg:classifiers":[
        {
            "category":"Sports & Exercise",
            "subcategory":"Race Track",
            "type":"Entertainment"
        }
    ],
    "sg:phone":"+1 559 683 0606",
    "sg:postcode":"93644",
    "sg:province":"CA",
    "wof:name":"Xtreme Off Road Racing",
    "wof:placetype":"venue"
},
  "geometry": {"coordinates":[-119.648363,37.334783],"type":"Point"}
}