{
  "type": "Feature",
  "properties": {
    "iso:country":"US",
    "sg:address":"535 Johnstonville Rd",
    "sg:city":"Susanville",
    "sg:classifiers":[
        {
            "category":"Farming",
            "subcategory":"Farm & Veterinary Services",
            "type":"Manufacturing & Wholesale Goods"
        }
    ],
    "sg:phone":"+1 530 257 8958",
    "sg:postcode":"96130",
    "sg:province":"CA",
    "sg:tags":[
        "livestock"
    ],
    "wof:name":"Bartley Ranch",
    "wof:placetype":"venue"
},
  "geometry": {"coordinates":[-120.624847,40.405266],"type":"Point"}
}