{
  "type": "Feature",
  "properties": {
    "iso:country":"US",
    "sg:address":"11840 Kittridge St",
    "sg:city":"North Hollywood",
    "sg:classifiers":[
        {
            "category":"Professional",
            "subcategory":"Business Services",
            "type":"Services"
        }
    ],
    "sg:phone":"+1 818 761 9545",
    "sg:postcode":"91606",
    "sg:province":"CA",
    "sg:tags":[
        "notary"
    ],
    "wof:name":"Frieda Valenski",
    "wof:placetype":"venue"
},
  "geometry": {"coordinates":[-118.391885,34.190229],"type":"Point"}
}