{
  "type": "Feature",
  "properties": {
    "addr:full":"110 Lower Lake Rd Redwood City CA 94062",
    "addr:housenumber":"110",
    "addr:postcode":"94062",
    "addr:street":"Lower Lake Rd",
    "iso:country":"US",
    "sg:address":"110 Lower Lake Rd",
    "sg:city":"Redwood City",
    "sg:classifiers":[
        {
            "category":"Organizations",
            "subcategory":"Community Association",
            "type":"Services"
        }
    ],
    "sg:phone":"+1 650 851 4160",
    "sg:postcode":"94062",
    "sg:province":"CA",
    "wof:name":"Kiwanis International Inc",
    "wof:placetype":"venue"
},
  "geometry": {"coordinates":[-122.244956,37.387138],"type":"Point"}
}