{
  "type": "Feature",
  "properties": {
    "addr:full":"2953 E Ventura Blvd Oxnard CA 93036",
    "addr:housenumber":"2953",
    "addr:postcode":"93036",
    "addr:street":"E Ventura Blvd",
    "iso:country":"US",
    "sg:address":"2953 E Ventura Blvd",
    "sg:city":"Oxnard",
    "sg:classifiers":[
        {
            "category":"Building & Trades",
            "subcategory":"Pest Control",
            "type":"Services"
        }
    ],
    "sg:phone":"+1 805 485 4449",
    "sg:postcode":"93036",
    "sg:province":"CA",
    "wof:name":"Western Exterminator Company",
    "wof:placetype":"venue"
},
  "geometry": {"coordinates":[-119.161744,34.226305],"type":"Point"}
}