{
  "type": "Feature",
  "properties": {
    "addr:full":"4308 Leafmont Way Sacramento CA 95826",
    "addr:housenumber":"4308",
    "addr:postcode":"95826",
    "addr:street":"Leafmont Way",
    "iso:country":"US",
    "sg:address":"4308 Leafmont Way",
    "sg:city":"Sacramento",
    "sg:classifiers":[
        {
            "category":"Insurance",
            "subcategory":"Hazard Insurance",
            "type":"Services"
        }
    ],
    "sg:phone":"+1 916 469 9962",
    "sg:postcode":"95826",
    "sg:province":"CA",
    "wof:name":"Blue Shield Of Ca O Butcher",
    "wof:placetype":"venue"
},
  "geometry": {"coordinates":[-121.345606,38.542177],"type":"Point"}
}