{
  "type": "Feature",
  "properties": {
    "iso:country":"US",
    "sg:address":"506 E 12th St",
    "sg:city":"Alturas",
    "sg:classifiers":[
        {
            "category":"Real Estate",
            "subcategory":"Real Estate Operator",
            "type":"Services"
        }
    ],
    "sg:phone":"+1 530 233 5511",
    "sg:postcode":"96101",
    "sg:province":"CA",
    "sg:tags":[
        "apartment"
    ],
    "wof:name":"Alturas Meadows Apartments",
    "wof:placetype":"venue"
},
  "geometry": {"coordinates":[-120.537277,41.494672],"type":"Point"}
}