{
  "type": "Feature",
  "properties": {
    "addr:full":"650 Cliffside Dr San Dimas CA 91773",
    "addr:housenumber":"650",
    "addr:postcode":"91773",
    "addr:street":"Cliffside Dr",
    "iso:country":"US",
    "sg:address":"650 Cliffside Dr",
    "sg:city":"San Dimas",
    "sg:classifiers":[
        {
            "category":"Wholesale",
            "subcategory":"Drugs",
            "type":"Manufacturing & Wholesale Goods"
        }
    ],
    "sg:phone":"+1 909 394 4000",
    "sg:postcode":"91773",
    "sg:province":"CA",
    "sg:tags":[
        "pharmaceutical",
        "product"
    ],
    "sg:website":"www.gilead.com",
    "wof:name":"Gilead Sciences Inc",
    "wof:placetype":"venue"
},
  "geometry": {"coordinates":[-117.817375,34.097699],"type":"Point"}
}