{
  "type": "Feature",
  "properties": {
    "addr:full":"1155 la Rosa Ct Turlock CA 95380",
    "addr:housenumber":"1155",
    "addr:postcode":"95380",
    "addr:street":"La Rosa Ct",
    "iso:country":"US",
    "sg:address":"1155 la Rosa Ct",
    "sg:city":"Turlock",
    "sg:phone":"+1 209 250 1700",
    "sg:postcode":"95380",
    "sg:province":"CA",
    "wof:name":"Fidelis Development",
    "wof:placetype":"venue"
},
  "geometry": {"coordinates":[-120.819495,37.503159],"type":"Point"}
}