{
  "type": "Feature",
  "properties": {
    "addr:full":"313 S Harbor Blvd Ste A Santa Ana CA 92704",
    "addr:housenumber":"313",
    "addr:postcode":"92704",
    "addr:street":"S Harbor Blvd Ste A",
    "iso:country":"US",
    "sg:address":"313 S Harbor Blvd Ste A",
    "sg:city":"Santa Ana",
    "sg:classifiers":[
        {
            "category":"Retail",
            "subcategory":"Auto Repair",
            "type":"Services"
        }
    ],
    "sg:phone":"+1 714 839 6675",
    "sg:postcode":"92704",
    "sg:province":"CA",
    "wof:name":"Bervette Diesel",
    "wof:placetype":"venue"
},
  "geometry": {"coordinates":[-117.91999800000001,33.742298],"type":"Point"}
}