{
  "type": "Feature",
  "properties": {
    "iso:country":"US",
    "sg:address":"11415 Folsom Blvd",
    "sg:city":"Rancho Cordova",
    "sg:classifiers":[
        {
            "category":"Organizations",
            "subcategory":"Religious Organization",
            "type":"Services"
        }
    ],
    "sg:phone":"+1 916 638 4700",
    "sg:postcode":"95742",
    "sg:province":"CA",
    "sg:tags":[
        "church"
    ],
    "wof:name":"Spectrum Christian Ctr",
    "wof:placetype":"venue"
},
  "geometry": {"coordinates":[-121.258311,38.610897],"type":"Point"}
}