{
  "type": "Feature",
  "properties": {
    "iso:country":"US",
    "sg:address":"1523 Crows Landing Rd",
    "sg:city":"Modesto",
    "sg:classifiers":[
        {
            "category":"Health Services",
            "subcategory":"Chiropractor",
            "type":"Services"
        }
    ],
    "sg:phone":"+1 209 538 2600",
    "sg:postcode":"95358",
    "sg:province":"CA",
    "wof:name":"Brother's Chiropractic",
    "wof:placetype":"venue"
},
  "geometry": {"coordinates":[-120.99368200000001,37.60895],"type":"Point"}
}