{
  "type": "Feature",
  "properties": {
    "iso:country":"US",
    "sg:address":"664 S Fairview Ave",
    "sg:city":"Goleta",
    "sg:classifiers":[
        {
            "category":"Retail",
            "subcategory":"Auto Repair",
            "type":"Services"
        }
    ],
    "sg:phone":"+1 805 964 1167",
    "sg:postcode":"93117",
    "sg:province":"CA",
    "sg:tags":[
        "repairing",
        "automobile"
    ],
    "wof:name":"Superior Brake & Alignment",
    "wof:placetype":"venue"
},
  "geometry": {"coordinates":[-119.830537,34.426469],"type":"Point"}
}