{
  "type": "Feature",
  "properties": {
    "addr:full":"905 S Atlantic Blvd Alhambra CA 91803",
    "addr:housenumber":"905",
    "addr:postcode":"91803",
    "addr:street":"S Atlantic Blvd",
    "iso:country":"US",
    "sg:address":"905 S Atlantic Blvd",
    "sg:city":"Alhambra",
    "sg:classifiers":[
        {
            "category":"Banks & Credit Unions",
            "subcategory":"Bank",
            "type":"Services"
        }
    ],
    "sg:phone":"+1 626 284 2114",
    "sg:postcode":"91803",
    "sg:province":"CA",
    "sg:tags":[
        "loan"
    ],
    "wof:name":"Business Owners Assn Intl",
    "wof:placetype":"venue"
},
  "geometry": {"coordinates":[-118.134586,34.079469],"type":"Point"}
}