{
  "type": "Feature",
  "properties": {
    "iso:country":"US",
    "sg:address":"20 W 3rd St",
    "sg:city":"Eureka",
    "sg:classifiers":[
        {
            "category":"Retail",
            "subcategory":"Auto Repair",
            "type":"Services"
        }
    ],
    "sg:phone":"+1 707 442 9995",
    "sg:postcode":"95501",
    "sg:province":"CA",
    "sg:tags":[
        "wrecker"
    ],
    "wof:name":"J & L Towing & Transport",
    "wof:placetype":"venue"
},
  "geometry": {"coordinates":[-124.171965,40.802716],"type":"Point"}
}