{
  "type": "Feature",
  "properties": {
    "addr:full":"1940 Bristol Ave Stockton CA 95204",
    "addr:housenumber":"1940",
    "addr:postcode":"95204",
    "addr:street":"Bristol Ave",
    "iso:country":"US",
    "sg:address":"1940 Bristol Ave",
    "sg:city":"Stockton",
    "sg:classifiers":[
        {
            "category":"Professional",
            "subcategory":"Management & Consulting",
            "type":"Services"
        }
    ],
    "sg:phone":"+1 209 944 0152",
    "sg:postcode":"95204",
    "sg:province":"CA",
    "sg:tags":[
        "sector",
        "commercial",
        "direct",
        "sales",
        "regulation",
        "retail"
    ],
    "wof:name":"No Left Turn Antiques",
    "wof:placetype":"venue"
},
  "geometry": {"coordinates":[-121.326071,37.969089],"type":"Point"}
}