{
  "type": "Feature",
  "properties": {
    "addr:full":"120 Kentucky St Petaluma CA 94952",
    "addr:housenumber":"120",
    "addr:postcode":"94952",
    "addr:street":"Kentucky St",
    "iso:country":"US",
    "sg:address":"120 Kentucky St",
    "sg:city":"Petaluma",
    "sg:classifiers":[
        {
            "category":"Home & Garden",
            "subcategory":"Home Furnishings",
            "type":"Retail Goods"
        }
    ],
    "sg:phone":"+1 707 762 6413",
    "sg:postcode":"94952",
    "sg:province":"CA",
    "sg:tags":[
        "housewares"
    ],
    "wof:name":"Bee's Housewares & Gifts",
    "wof:placetype":"venue"
},
  "geometry": {"coordinates":[-122.64127499999999,38.234124],"type":"Point"}
}