{
  "type": "Feature",
  "properties": {
    "addr:full":"2549 Chassella Way Rancho Cordova CA 95670",
    "addr:housenumber":"2549",
    "addr:postcode":"95670",
    "addr:street":"Chassella Way",
    "iso:country":"US",
    "sg:address":"2549 Chassella Way",
    "sg:city":"Rancho Cordova",
    "sg:classifiers":[
        {
            "category":"Recreation",
            "type":"Entertainment"
        }
    ],
    "sg:phone":"+1 916 363 0129",
    "sg:postcode":"95670",
    "sg:province":"CA",
    "wof:name":"Federspiel Pool",
    "wof:placetype":"venue"
},
  "geometry": {"coordinates":[-121.294076,38.599727],"type":"Point"}
}