{
  "type": "Feature",
  "properties": {
    "addr:full":"117 E Los Feliz Rd Glendale CA 91205",
    "addr:housenumber":"117",
    "addr:postcode":"91205",
    "addr:street":"E Los Feliz Rd",
    "iso:country":"US",
    "sg:address":"117 E Los Feliz Rd",
    "sg:city":"Glendale",
    "sg:classifiers":[
        {
            "category":"Organizations",
            "subcategory":"Professional Association",
            "type":"Services"
        }
    ],
    "sg:phone":"+1 818 242 3551",
    "sg:postcode":"91205",
    "sg:province":"CA",
    "sg:tags":[
        "business",
        "trade"
    ],
    "wof:name":"Lions Club",
    "wof:placetype":"venue"
},
  "geometry": {"coordinates":[-118.254656,34.128689],"type":"Point"}
}