{
  "type": "Feature",
  "properties": {
    "iso:country":"US",
    "sg:address":"19085 Colima Rd",
    "sg:city":"Rowland Heights",
    "sg:classifiers":[
        {
            "category":"Health Services",
            "subcategory":"Doctor",
            "type":"Services"
        }
    ],
    "sg:phone":"+1 626 964 5001",
    "sg:postcode":"91748",
    "sg:province":"CA",
    "sg:tags":[
        "clinic"
    ],
    "wof:name":"Park East Medical Ctr",
    "wof:placetype":"venue"
},
  "geometry": {"coordinates":[-117.886641,33.987431],"type":"Point"}
}