{
  "type": "Feature",
  "properties": {
    "iso:country":"US",
    "sg:address":"18620 Hatteras St",
    "sg:city":"Tarzana",
    "sg:classifiers":[
        {
            "category":"Shopping",
            "subcategory":"Clothing, Apparel, & Fashions",
            "type":"Retail Goods"
        }
    ],
    "sg:phone":"+1 818 881 1174",
    "sg:postcode":"91356",
    "sg:province":"CA",
    "sg:tags":[
        "family"
    ],
    "wof:name":"Lucky Star",
    "wof:placetype":"venue"
},
  "geometry": {"coordinates":[-118.539565,34.177052],"type":"Point"}
}