{
  "type": "Feature",
  "properties": {
    "iso:country":"US",
    "sg:address":"3215 Marysville Blvd",
    "sg:city":"Sacramento",
    "sg:classifiers":[
        {
            "category":"Professional",
            "type":"Services"
        }
    ],
    "sg:phone":"+1 916 564 0118",
    "sg:postcode":"95815",
    "sg:province":"CA",
    "wof:name":"Masscom",
    "wof:placetype":"venue"
},
  "geometry": {"coordinates":[-121.432892,38.626005],"type":"Point"}
}