{
  "type": "Feature",
  "properties": {
    "addr:full":"337 17th St Oakland CA 94612",
    "addr:housenumber":"337",
    "addr:postcode":"94612",
    "addr:street":"17Th St",
    "iso:country":"US",
    "sg:address":"337 17th St",
    "sg:city":"Oakland",
    "sg:classifiers":[
        {
            "category":"Arts & Performance",
            "subcategory":"Theater",
            "type":"Entertainment"
        }
    ],
    "sg:phone":"+1 510 893 9853",
    "sg:postcode":"94612",
    "sg:province":"CA",
    "wof:name":"Christmas Revels",
    "wof:placetype":"venue"
},
  "geometry": {"coordinates":[-122.266644,37.805289],"type":"Point"}
}