{
  "type": "Feature",
  "properties": {
    "iso:country":"US",
    "sg:address":"2311 Morena Blvd",
    "sg:city":"San Diego",
    "sg:classifiers":[
        {
            "category":"Shopping",
            "subcategory":"Clothing, Apparel, & Fashions",
            "type":"Retail Goods"
        }
    ],
    "sg:phone":"+1 858 581 2229",
    "sg:postcode":"92110",
    "sg:province":"CA",
    "sg:tags":[
        "baby",
        "accessory"
    ],
    "wof:name":"Meunbaby2",
    "wof:placetype":"venue"
},
  "geometry": {"coordinates":[-117.206154,32.787061],"type":"Point"}
}