{
  "type": "Feature",
  "properties": {
    "addr:full":"1135 S Hacienda Blvd Hacienda Heights CA 91745",
    "addr:housenumber":"1135",
    "addr:postcode":"91745",
    "addr:street":"S Hacienda Blvd",
    "iso:country":"US",
    "sg:address":"1135 S Hacienda Blvd",
    "sg:city":"Hacienda Heights",
    "sg:classifiers":[
        {
            "category":"Restaurant",
            "type":"Food & Drink"
        }
    ],
    "sg:menulink":"http://www.allmenus.com/ca/east-san-gabriel-valley/172245-burger-king/menu/",
    "sg:phone":"+1 626 961 4349",
    "sg:postcode":"91745",
    "sg:province":"CA",
    "sg:tags":[
        "burger",
        "american"
    ],
    "wof:name":"Burger King",
    "wof:placetype":"venue"
},
  "geometry": {"coordinates":[-117.963392,34.009869],"type":"Point"}
}