{
  "type": "Feature",
  "properties": {
    "iso:country":"US",
    "sg:address":"527 E Rowland St",
    "sg:city":"Covina",
    "sg:classifiers":[
        {
            "category":"Health Services",
            "subcategory":"Clinic",
            "type":"Services"
        }
    ],
    "sg:phone":"+1 626 967 8700",
    "sg:postcode":"91723",
    "sg:province":"CA",
    "sg:tags":[
        "mental",
        "specialty",
        "outpatient"
    ],
    "wof:name":"Sipra Sengupta & Katie",
    "wof:placetype":"venue"
},
  "geometry": {"coordinates":[-117.880442,34.078979],"type":"Point"}
}