{
  "type": "Feature",
  "properties": {
    "addr:full":"285 Blossom Hill Rd San Jose CA 95123",
    "addr:housenumber":"285",
    "addr:postcode":"95123",
    "addr:street":"Blossom Hill Rd",
    "iso:country":"US",
    "sg:address":"285 Blossom Hill Rd",
    "sg:city":"San Jose",
    "sg:classifiers":[
        {
            "category":"Education",
            "subcategory":"School",
            "type":"Public Place"
        }
    ],
    "sg:phone":"+1 408 347 6500",
    "sg:postcode":"95123",
    "sg:province":"CA",
    "sg:website":"og.ca.campusgrid.net/home",
    "wof:name":"Oak Grove High School",
    "wof:placetype":"venue"
},
  "geometry": {"coordinates":[-121.81983,37.251454],"type":"Point"}
}