{
  "type": "Feature",
  "properties": {
    "iso:country":"US",
    "sg:address":"900 Canterbury Pl",
    "sg:city":"Escondido",
    "sg:classifiers":[
        {
            "category":"Banks & Credit Unions",
            "subcategory":"Bank",
            "type":"Services"
        }
    ],
    "sg:phone":"+1 760 432 1350",
    "sg:postcode":"92025",
    "sg:province":"CA",
    "sg:tags":[
        "saving",
        "commercial"
    ],
    "sg:website":"http://www.pacificwesternbank.com",
    "wof:name":"Pacific Western Bank",
    "wof:placetype":"venue"
},
  "geometry": {"coordinates":[-117.09272799999999,33.10862],"type":"Point"}
}