{
  "type": "Feature",
  "properties": {
    "iso:country":"US",
    "sg:address":"3618 Dimond Ave",
    "sg:city":"Oakland",
    "sg:classifiers":[
        {
            "category":"Organizations",
            "subcategory":"Religious Organization",
            "type":"Services"
        }
    ],
    "sg:phone":"+1 510 530 6446",
    "sg:postcode":"94602",
    "sg:province":"CA",
    "sg:tags":[
        "church"
    ],
    "sg:website":"www.ag.org",
    "wof:name":"City of the Lord Zion Assembly of God",
    "wof:placetype":"venue"
},
  "geometry": {"coordinates":[-122.21700300000001,37.802299],"type":"Point"}
}