{
  "type": "Feature",
  "properties": {
    "iso:country":"US",
    "sg:address":"1 Holland",
    "sg:city":"Irvine",
    "sg:classifiers":[
        {
            "category":"Shopping",
            "subcategory":"Bicycles & Sporting Goods",
            "type":"Retail Goods"
        }
    ],
    "sg:phone":"+1 949 951 5003",
    "sg:postcode":"92618",
    "sg:province":"CA",
    "sg:tags":[
        "bike"
    ],
    "wof:name":"Shimano American",
    "wof:placetype":"venue"
},
  "geometry": {"coordinates":[-117.721486,33.647163],"type":"Point"}
}