{
  "type": "Feature",
  "properties": {
    "iso:country":"US",
    "sg:address":"607 S Hill St",
    "sg:city":"Los Angeles",
    "sg:classifiers":[
        {
            "category":"Wholesale",
            "subcategory":"Jewelry",
            "type":"Manufacturing & Wholesale Goods"
        }
    ],
    "sg:phone":"+1 213 623 3662",
    "sg:postcode":"90014",
    "sg:province":"CA",
    "sg:tags":[
        "diamond"
    ],
    "wof:name":"Nancy's Gems",
    "wof:placetype":"venue"
},
  "geometry": {"coordinates":[-118.254439,34.046043],"type":"Point"}
}