{
  "type": "Feature",
  "properties": {
    "iso:country":"US",
    "sg:address":"1824 Esplanade",
    "sg:city":"Chico",
    "sg:classifiers":[
        {
            "category":"Real Estate",
            "subcategory":"Real Estate Agent",
            "type":"Services"
        }
    ],
    "sg:phone":"+1 530 899 1602",
    "sg:postcode":"95926",
    "sg:province":"CA",
    "wof:name":"Alliance Real Estate Mgmt",
    "wof:placetype":"venue"
},
  "geometry": {"coordinates":[-121.851736,39.74625],"type":"Point"}
}