{
  "type": "Feature",
  "properties": {
    "iso:country":"US",
    "sg:address":"749 Blackmer Cir",
    "sg:city":"Sacramento",
    "sg:classifiers":[
        {
            "category":"Communications",
            "type":"Services"
        }
    ],
    "sg:phone":"+1 916 649 0829",
    "sg:postcode":"95825",
    "sg:province":"CA",
    "sg:tags":[
        "communication"
    ],
    "wof:name":"Jth Communications",
    "wof:placetype":"venue"
},
  "geometry": {"coordinates":[-121.413574,38.579329],"type":"Point"}
}