{
  "type": "Feature",
  "properties": {
    "addr:full":"4609 Convoy St San Diego CA 92111",
    "addr:housenumber":"4609",
    "addr:postcode":"92111",
    "addr:street":"Convoy St",
    "iso:country":"US",
    "sg:address":"4609 Convoy St",
    "sg:city":"San Diego",
    "sg:classifiers":[
        {
            "category":"Travel",
            "subcategory":"Travel Agent",
            "type":"Entertainment"
        }
    ],
    "sg:phone":"+1 858 278 4888",
    "sg:postcode":"92111",
    "sg:province":"CA",
    "sg:tags":[
        "agency",
        "bureau"
    ],
    "wof:name":"Sea & Sky Travel Inc",
    "wof:placetype":"venue"
},
  "geometry": {"coordinates":[-117.155058,32.825101],"type":"Point"}
}