{
  "type": "Feature",
  "properties": {
    "iso:country":"US",
    "sg:address":"42200 Moraga Rd",
    "sg:city":"Temecula",
    "sg:classifiers":[
        {
            "category":"Building & Trades",
            "subcategory":"Construction",
            "type":"Services"
        }
    ],
    "sg:phone":"+1 951 587 9591",
    "sg:postcode":"92591",
    "sg:province":"CA",
    "sg:tags":[
        "fire",
        "restoration",
        "damage"
    ],
    "wof:name":"G & D Flood & Water Damage",
    "wof:placetype":"venue"
},
  "geometry": {"coordinates":[-117.140396,33.508535],"type":"Point"}
}