{
  "type": "Feature",
  "properties": {
    "addr:full":"4221 Arlington Ave Sacramento CA 95820",
    "addr:housenumber":"4221",
    "addr:postcode":"95820",
    "addr:street":"Arlington Ave",
    "iso:country":"US",
    "sg:address":"4221 Arlington Ave",
    "sg:city":"Sacramento",
    "sg:classifiers":[
        {
            "category":"Manufacturing",
            "subcategory":"Printing",
            "type":"Manufacturing & Wholesale Goods"
        }
    ],
    "sg:phone":"+1 916 451 6371",
    "sg:postcode":"95820",
    "sg:province":"CA",
    "sg:tags":[
        "periodical"
    ],
    "wof:name":"Gold Rush Magazine",
    "wof:placetype":"venue"
},
  "geometry": {"coordinates":[-121.479161,38.53678],"type":"Point"}
}