{
  "type": "Feature",
  "properties": {
    "addr:full":"508 S San Vicente Blvd Los Angeles CA 90048",
    "addr:housenumber":"508",
    "addr:postcode":"90048",
    "addr:street":"S San Vicente Blvd",
    "iso:country":"US",
    "sg:address":"508 S San Vicente Blvd",
    "sg:city":"Los Angeles",
    "sg:classifiers":[
        {
            "category":"Communications",
            "subcategory":"Film & Video Production",
            "type":"Services"
        }
    ],
    "sg:phone":"+1 323 852 1046",
    "sg:postcode":"90048",
    "sg:province":"CA",
    "sg:tags":[
        "motion",
        "picture"
    ],
    "wof:name":"Sheila Manning Casting Inc",
    "wof:placetype":"venue"
},
  "geometry": {"coordinates":[-118.37441099999999,34.068264],"type":"Point"}
}