{
  "type": "Feature",
  "properties": {
    "iso:country":"US",
    "sg:address":"928 Middlefield Rd",
    "sg:city":"Redwood City",
    "sg:classifiers":[
        {
            "category":"Professional",
            "subcategory":"Lawyer & Legal Services",
            "type":"Services"
        }
    ],
    "sg:phone":"+1 650 366 8241",
    "sg:postcode":"94063",
    "sg:province":"CA",
    "sg:tags":[
        "attorney"
    ],
    "wof:name":"Wilson & Wilson",
    "wof:placetype":"venue"
},
  "geometry": {"coordinates":[-122.229147,37.48577],"type":"Point"}
}