{
  "type": "Feature",
  "properties": {
    "addr:full":"14801 Washington Ave San Leandro CA 94578",
    "addr:housenumber":"14801",
    "addr:postcode":"94578",
    "addr:street":"Washington Ave",
    "iso:country":"US",
    "sg:address":"14801 Washington Ave",
    "sg:city":"San Leandro",
    "sg:classifiers":[
        {
            "category":"Shopping",
            "subcategory":"Department Store",
            "type":"Retail Goods"
        }
    ],
    "sg:phone":"+1 510 357 5092",
    "sg:postcode":"94578",
    "sg:province":"CA",
    "sg:tags":[
        "shop",
        "thrift"
    ],
    "sg:website":"www.dollartree.com",
    "wof:name":"Dollar Tree",
    "wof:placetype":"venue"
},
  "geometry": {"coordinates":[-122.13924299999999,37.696441],"type":"Point"}
}