{
  "type": "Feature",
  "properties": {
    "acgov:api":"849.0",
    "acgov:type":"ES",
    "addr:full":"554 Jackson Avenue Livermore CA",
    "wof:categories":[
        "education_and_religion:education=school"
    ],
    "wof:name":"Jackson Avenue Elementary",
    "wof:placetype":"venue"
},
  "geometry": {"coordinates":[-121.74245264648187,37.68525579936867],"type":"Point"}
}