{
  "type": "Feature",
  "properties": {
    "iso:country":"US",
    "sg:address":"45405 Industrial Pl",
    "sg:city":"Fremont",
    "sg:classifiers":[
        {
            "category":"Retail",
            "subcategory":"Auto Repair",
            "type":"Services"
        }
    ],
    "sg:phone":"+1 510 656 9351",
    "sg:postcode":"94538",
    "sg:province":"CA",
    "sg:tags":[
        "machine",
        "automobile",
        "shop"
    ],
    "wof:name":"Amaral's Engine Parts & Mach",
    "wof:placetype":"venue"
},
  "geometry": {"coordinates":[-121.950207,37.495873],"type":"Point"}
}