{
  "type": "Feature",
  "properties": {
    "iso:country":"US",
    "sg:address":"1050 Borregas Ave",
    "sg:city":"Sunnyvale",
    "sg:classifiers":[
        {
            "category":"Wholesale",
            "subcategory":"Durable Goods & Equipment",
            "type":"Manufacturing & Wholesale Goods"
        }
    ],
    "sg:phone":"+1 408 745 1494",
    "sg:postcode":"94089",
    "sg:province":"CA",
    "sg:tags":[
        "magnet",
        "magnetic",
        "devices"
    ],
    "wof:name":"Kinney Associates",
    "wof:placetype":"venue"
},
  "geometry": {"coordinates":[-122.02199,37.399629],"type":"Point"}
}