{
  "type": "Feature",
  "properties": {
    "addr:full":"39195 Farwell Dr Fremont CA 94538",
    "addr:postcode":"39195;94538",
    "addr:street":"Farwell Dr",
    "iso:country":"US",
    "sg:address":"39195 Farwell Dr",
    "sg:city":"Fremont",
    "sg:classifiers":[
        {
            "category":"Restaurant",
            "type":"Food & Drink"
        }
    ],
    "sg:phone":"+1 510 791 8675",
    "sg:postcode":"94538",
    "sg:province":"CA",
    "sg:tags":[
        "eating"
    ],
    "wof:name":"Market Broiler",
    "wof:placetype":"venue"
},
  "geometry": {"coordinates":[-121.997039,37.531495],"type":"Point"}
}