{
  "type": "Feature",
  "properties": {
    "iso:country":"US",
    "sg:address":"233 Main St",
    "sg:city":"El Segundo",
    "sg:classifiers":[
        {
            "category":"Building & Trades",
            "subcategory":"Construction",
            "type":"Services"
        }
    ],
    "sg:phone":"+1 310 414 0016",
    "sg:postcode":"90245",
    "sg:province":"CA",
    "sg:tags":[
        "contractor"
    ],
    "wof:name":"JRO Construction",
    "wof:placetype":"venue"
},
  "geometry": {"coordinates":[-118.416009,33.919901],"type":"Point"}
}