{
  "type": "Feature",
  "properties": {
    "iso:country":"US",
    "sg:address":"24336 Crestlawn St",
    "sg:city":"Woodland Hills",
    "sg:classifiers":[
        {
            "category":"Professional",
            "subcategory":"Advertising",
            "type":"Services"
        }
    ],
    "sg:phone":"+1 818 943 6022",
    "sg:postcode":"91367",
    "sg:province":"CA",
    "wof:name":"Arash Advertising",
    "wof:placetype":"venue"
},
  "geometry": {"coordinates":[-118.657708,34.170269],"type":"Point"}
}