{
  "type": "Feature",
  "properties": {
    "addr:full":"1011 Camino Del Mar Del Mar CA 92014",
    "addr:housenumber":"1011",
    "addr:postcode":"92014",
    "addr:street":"Camino Del Mar",
    "iso:country":"US",
    "sg:address":"1011 Camino Del Mar",
    "sg:city":"Del Mar",
    "sg:classifiers":[
        {
            "category":"Health Services",
            "subcategory":"Chiropractor",
            "type":"Services"
        }
    ],
    "sg:phone":"+1 858 481 9003",
    "sg:postcode":"92014",
    "sg:province":"CA",
    "wof:name":"Lerner William E DC",
    "wof:placetype":"venue"
},
  "geometry": {"coordinates":[-117.26300000000001,32.954498],"type":"Point"}
}