{
  "type": "Feature",
  "properties": {
    "iso:country":"US",
    "sg:address":"1130 E Monte Vista Ave",
    "sg:city":"Vacaville",
    "sg:classifiers":[
        {
            "category":"Retail",
            "subcategory":"Auto Repair",
            "type":"Services"
        }
    ],
    "sg:phone":"+1 707 448 8542",
    "sg:postcode":"95688",
    "sg:province":"CA",
    "sg:tags":[
        "repairing",
        "automobile"
    ],
    "wof:name":"Auto Pro's",
    "wof:placetype":"venue"
},
  "geometry": {"coordinates":[-121.975275,38.360382],"type":"Point"}
}