{
  "type": "Feature",
  "properties": {
    "iso:country":"US",
    "sg:address":"6363 el Cajon Blvd",
    "sg:city":"San Diego",
    "sg:classifiers":[
        {
            "category":"Real Estate",
            "subcategory":"Developer",
            "type":"Services"
        }
    ],
    "sg:phone":"+1 619 286 1867",
    "sg:postcode":"92115",
    "sg:province":"CA",
    "sg:tags":[
        "cemetery"
    ],
    "wof:name":"Home Of Peace Cemetery",
    "wof:placetype":"venue"
},
  "geometry": {"coordinates":[-117.061014,32.764624],"type":"Point"}
}