{
  "type": "Feature",
  "properties": {
    "iso:country":"US",
    "sg:address":"9821 Bus Park Dr",
    "sg:city":"Sacramento",
    "sg:classifiers":[
        {
            "category":"Government",
            "subcategory":"Office",
            "type":"Public Place"
        }
    ],
    "sg:phone":"+1 916 255 4027",
    "sg:postcode":"95827",
    "sg:province":"CA",
    "sg:tags":[
        "state",
        "licensing",
        "board"
    ],
    "wof:name":"Northern District Office",
    "wof:placetype":"venue"
},
  "geometry": {"coordinates":[-121.33061499999999,38.570147],"type":"Point"}
}