{
  "type": "Feature",
  "properties": {
    "addr:full":"210 E Olympic Boulevard Los Angeles CA 90015",
    "addr:housenumber":"210",
    "addr:postcode":"90015",
    "addr:street":"E Olympic Boulevard",
    "iso:country":"US",
    "sg:address":"210 E Olympic Boulevard",
    "sg:city":"Los Angeles",
    "sg:classifiers":[
        {
            "category":"Shopping",
            "subcategory":"Clothing, Apparel, & Fashions",
            "type":"Retail Goods"
        }
    ],
    "sg:phone":"+1 213 747 6661",
    "sg:postcode":"90015",
    "sg:province":"CA",
    "sg:tags":[
        "accessory",
        "clothing",
        "women's"
    ],
    "wof:name":"A B M Global",
    "wof:placetype":"venue"
},
  "geometry": {"coordinates":[-118.27153800000001,34.039118],"type":"Point"}
}