{
  "type": "Feature",
  "properties": {
    "addr:full":"42018 Cll Pino Murrieta CA 92562",
    "addr:postcode":"42018;92562",
    "addr:street":"Cll Pino",
    "iso:country":"US",
    "sg:address":"42018 Cll Pino",
    "sg:city":"Murrieta",
    "sg:classifiers":[
        {
            "category":"Retail",
            "subcategory":"Animal Services",
            "type":"Services"
        }
    ],
    "sg:phone":"+1 951 677 7315",
    "sg:postcode":"92562",
    "sg:province":"CA",
    "wof:name":"Baron Of Bavaria Farms",
    "wof:placetype":"venue"
},
  "geometry": {"coordinates":[-117.318714,33.51822],"type":"Point"}
}