{
  "type": "Feature",
  "properties": {
    "iso:country":"US",
    "sg:address":"1520 Seminary St",
    "sg:city":"Napa",
    "sg:classifiers":[
        {
            "category":"Building & Trades",
            "subcategory":"Landscaping Services",
            "type":"Services"
        }
    ],
    "sg:phone":"+1 707 224 3229",
    "sg:postcode":"94559",
    "sg:province":"CA",
    "sg:tags":[
        "designer",
        "landscape"
    ],
    "wof:name":"Barbara Kent Stafford Lndscp",
    "wof:placetype":"venue"
},
  "geometry": {"coordinates":[-122.290156,38.301519],"type":"Point"}
}