{
  "type": "Feature",
  "properties": {
    "addr:full":"1461 E Conejo Ave Fresno CA 93725",
    "addr:housenumber":"1461",
    "addr:postcode":"93725",
    "addr:street":"E Conejo Ave",
    "iso:country":"US",
    "sg:address":"1461 E Conejo Ave",
    "sg:city":"Fresno",
    "sg:classifiers":[
        {
            "category":"Farming",
            "subcategory":"Vineyard",
            "type":"Manufacturing & Wholesale Goods"
        }
    ],
    "sg:phone":"+1 559 896 8585",
    "sg:postcode":"93725",
    "sg:province":"CA",
    "sg:tags":[
        "grape"
    ],
    "wof:name":"Ranjit S Bhullar Farms",
    "wof:placetype":"venue"
},
  "geometry": {"coordinates":[-119.763086,36.518267],"type":"Point"}
}