{
  "type": "Feature",
  "properties": {
    "iso:country":"US",
    "sg:address":"701 17th St",
    "sg:city":"Manhattan Beach",
    "sg:classifiers":[
        {
            "category":"Building & Trades",
            "subcategory":"Landscaping Services",
            "type":"Services"
        }
    ],
    "sg:phone":"+1 310 545 4178",
    "sg:postcode":"90266",
    "sg:province":"CA",
    "sg:tags":[
        "landscape"
    ],
    "wof:name":"Growing Great",
    "wof:placetype":"venue"
},
  "geometry": {"coordinates":[-118.407545,33.889926],"type":"Point"}
}