{
  "type": "Feature",
  "properties": {
    "iso:country":"US",
    "sg:address":"40 E Main St",
    "sg:city":"Quincy",
    "sg:classifiers":[
        {
            "category":"Coffee & Tea",
            "type":"Food & Drink"
        },
        {
            "category":"Restaurant",
            "type":"Food & Drink"
        }
    ],
    "sg:phone":"+1 530 283 0591",
    "sg:postcode":"95971",
    "sg:province":"CA",
    "sg:tags":[
        "espresso"
    ],
    "wof:name":"Plumas Cafe",
    "wof:placetype":"venue"
},
  "geometry": {"coordinates":[-120.931686,39.934534],"type":"Point"}
}