{
  "type": "Feature",
  "properties": {
    "addr:full":"9141 Elkmont Way Elk Grove CA 95624",
    "addr:housenumber":"9141",
    "addr:postcode":"95624",
    "addr:street":"Elkmont Way",
    "iso:country":"US",
    "sg:address":"9141 Elkmont Way",
    "sg:city":"Elk Grove",
    "sg:classifiers":[
        {
            "category":"Retail",
            "subcategory":"Auto Repair",
            "type":"Services"
        }
    ],
    "sg:phone":"+1 916 686 8454",
    "sg:postcode":"95624",
    "sg:province":"CA",
    "sg:tags":[
        "body",
        "automobile",
        "painting"
    ],
    "wof:name":"Hayes Brothers Collision",
    "wof:placetype":"venue"
},
  "geometry": {"coordinates":[-121.36311499999999,38.382455],"type":"Point"}
}