{
  "type": "Feature",
  "properties": {
    "iso:country":"US",
    "sg:address":"9146 Harbour Point Dr",
    "sg:city":"Elk Grove",
    "sg:classifiers":[
        {
            "category":"Restaurant",
            "type":"Food & Drink"
        }
    ],
    "sg:phone":"+1 916 665 9246",
    "sg:postcode":"95758",
    "sg:province":"CA",
    "wof:name":"Mc Donald's",
    "wof:placetype":"venue"
},
  "geometry": {"coordinates":[-121.480811,38.427783],"type":"Point"}
}