{
  "type": "Feature",
  "properties": {
    "iso:country":"US",
    "sg:address":"615 Alder Ln",
    "sg:city":"Walnut",
    "sg:classifiers":[
        {
            "category":"Wholesale",
            "subcategory":"Non-durable Goods",
            "type":"Manufacturing & Wholesale Goods"
        }
    ],
    "sg:phone":"+1 909 595 4069",
    "sg:postcode":"91789",
    "sg:province":"CA",
    "sg:tags":[
        "merchandise",
        "general"
    ],
    "wof:name":"Sunset Traders",
    "wof:placetype":"venue"
},
  "geometry": {"coordinates":[-117.840494,34.007579],"type":"Point"}
}