{
  "type": "Feature",
  "properties": {
    "addr:full":"4823 Santa Ana St Cudahy CA 90201",
    "addr:housenumber":"4823",
    "addr:postcode":"90201",
    "addr:street":"Santa Ana St",
    "iso:country":"US",
    "sg:address":"4823 Santa Ana St",
    "sg:city":"Cudahy",
    "sg:classifiers":[
        {
            "category":"Shopping",
            "subcategory":"Party Supplies",
            "type":"Retail Goods"
        }
    ],
    "sg:phone":"+1 323 778 6226",
    "sg:postcode":"90201",
    "sg:province":"CA",
    "wof:name":"Westside Party Supply & Rental",
    "wof:placetype":"venue"
},
  "geometry": {"coordinates":[-118.183324,33.960631],"type":"Point"}
}