{
  "type": "Feature",
  "properties": {
    "addr:full":"838 Bonita Dr Vista CA 92083",
    "addr:housenumber":"838",
    "addr:postcode":"92083",
    "addr:street":"Bonita Dr",
    "iso:country":"US",
    "sg:address":"838 Bonita Dr",
    "sg:city":"Vista",
    "sg:classifiers":[
        {
            "category":"Home & Garden",
            "subcategory":"Building Materials",
            "type":"Retail Goods"
        },
        {
            "category":"Building & Trades",
            "subcategory":"Construction",
            "type":"Services"
        }
    ],
    "sg:phone":"+1 760 732 5941",
    "sg:postcode":"92083",
    "sg:province":"CA",
    "sg:tags":[
        "concrete",
        "staining",
        "contractor"
    ],
    "wof:name":"Marvin Concrete",
    "wof:placetype":"venue"
},
  "geometry": {"coordinates":[-117.26432,33.205793],"type":"Point"}
}