{
  "type": "Feature",
  "properties": {
    "addr:full":"600 50th Ave Oakland CA 94601",
    "addr:housenumber":"600",
    "addr:postcode":"94601",
    "addr:street":"50Th Ave",
    "iso:country":"US",
    "sg:address":"600 50th Ave",
    "sg:city":"Oakland",
    "sg:classifiers":[
        {
            "category":"Wholesale",
            "subcategory":"Construction Materials",
            "type":"Manufacturing & Wholesale Goods"
        }
    ],
    "sg:phone":"+1 510 536 5600",
    "sg:postcode":"94601",
    "sg:province":"CA",
    "sg:tags":[
        "marble"
    ],
    "sg:website":"www.tsgbyinstone.com",
    "wof:name":"Stone Gallery",
    "wof:placetype":"venue"
},
  "geometry": {"coordinates":[-122.21447999999999,37.76403],"type":"Point"}
}