{
  "type": "Feature",
  "properties": {
    "addr:full":"3869 E Cesar E Chavez Ave Los Angeles CA 90063",
    "addr:housenumber":"3869",
    "addr:postcode":"90063",
    "addr:street":"E Cesar E Chavez Ave",
    "iso:country":"US",
    "sg:address":"3869 E Cesar E Chavez Ave",
    "sg:city":"Los Angeles",
    "sg:classifiers":[
        {
            "category":"Retail",
            "subcategory":"Repair Shop",
            "type":"Services"
        }
    ],
    "sg:phone":"+1 323 261 0066",
    "sg:postcode":"90063",
    "sg:province":"CA",
    "sg:tags":[
        "reupholstery",
        "furniture"
    ],
    "wof:name":"Raigoza Upholstering",
    "wof:placetype":"venue"
},
  "geometry": {"coordinates":[-118.181999,34.0406],"type":"Point"}
}