{
  "type": "Feature",
  "properties": {
    "addr:full":"1500 Davidson Ave Ste B San Francisco CA 94124",
    "addr:housenumber":"1500",
    "addr:postcode":"94124",
    "addr:street":"Davidson Ave Ste B",
    "iso:country":"US",
    "sg:address":"1500 Davidson Ave Ste B",
    "sg:city":"San Francisco",
    "sg:classifiers":[
        {
            "category":"Building & Trades",
            "subcategory":"Construction",
            "type":"Services"
        }
    ],
    "sg:phone":"+1 415 641 8622",
    "sg:postcode":"94124",
    "sg:province":"CA",
    "sg:tags":[
        "painter",
        "contractor"
    ],
    "sg:website":"www.magicbrush.net",
    "wof:name":"Magic Brush, Inc",
    "wof:placetype":"venue"
},
  "geometry": {"coordinates":[-122.389971,37.745085],"type":"Point"}
}