{
  "type": "Feature",
  "properties": {
    "addr:full":"545 S Shore Ctr W Alameda CA 94501",
    "addr:housenumber":"545",
    "addr:postcode":"94501",
    "addr:street":"S Shore Ctr W",
    "iso:country":"US",
    "sg:address":"545 S Shore Ctr W",
    "sg:city":"Alameda",
    "sg:classifiers":[
        {
            "category":"Retail",
            "subcategory":"Laundry & Dry Cleaning",
            "type":"Services"
        }
    ],
    "sg:phone":"+1 510 337 0769",
    "sg:postcode":"94501",
    "sg:province":"CA",
    "sg:tags":[
        "operated",
        "dryer",
        "laundries-self",
        "washer",
        "coin"
    ],
    "wof:name":"Launderland South Shore",
    "wof:placetype":"venue"
},
  "geometry": {"coordinates":[-122.251999,37.759602],"type":"Point"}
}