{
  "type": "Feature",
  "properties": {
    "addr:full":"2761 S Diamond Bar Blvd Diamond Bar CA 91765",
    "addr:housenumber":"2761",
    "addr:postcode":"91765",
    "addr:street":"S;Blvd",
    "iso:country":"US",
    "sg:address":"2761 S Diamond Bar Blvd",
    "sg:city":"Diamond Bar",
    "sg:classifiers":[
        {
            "category":"Personal",
            "subcategory":"Beauty Salon",
            "type":"Services"
        }
    ],
    "sg:phone":"+1 909 869 7798",
    "sg:postcode":"91765",
    "sg:province":"CA",
    "sg:tags":[
        "manicuring"
    ],
    "wof:name":"Ruby's Nails",
    "wof:placetype":"venue"
},
  "geometry": {"coordinates":[-117.837957,33.973839],"type":"Point"}
}