{
  "type": "Feature",
  "properties": {
    "addr:full":"3561 Homestead Rd Santa Clara CA 95051",
    "addr:housenumber":"3561",
    "addr:postcode":"95051",
    "addr:street":"Homestead Rd",
    "iso:country":"US",
    "sg:address":"3561 Homestead Rd",
    "sg:city":"Santa Clara",
    "sg:classifiers":[
        {
            "category":"Freight",
            "type":"Transportation"
        },
        {
            "category":"Professional",
            "subcategory":"Lawyer & Legal Services",
            "type":"Services"
        }
    ],
    "sg:phone":"+1 408 557 9401",
    "sg:postcode":"95051",
    "sg:province":"CA",
    "sg:tags":[
        "notary",
        "shipping"
    ],
    "sg:website":"www.postalannex.com/5006",
    "wof:name":"Postal Annex",
    "wof:placetype":"venue"
},
  "geometry": {"coordinates":[-121.994443,37.337842],"type":"Point"}
}