{
  "type": "Feature",
  "properties": {
    "addr:full":"104 Sugarloaf Dr Belvedere Tibrn CA 94920",
    "addr:housenumber":"104",
    "addr:postcode":"94920",
    "addr:street":"Sugarloaf Dr",
    "iso:country":"US",
    "sg:address":"104 Sugarloaf Dr",
    "sg:city":"Belvedere Tibrn",
    "sg:classifiers":[
        {
            "category":"Banks & Credit Unions",
            "subcategory":"Investment Brokerage",
            "type":"Services"
        }
    ],
    "sg:phone":"+1 415 789 0285",
    "sg:postcode":"94920",
    "sg:province":"CA",
    "sg:tags":[
        "consultant",
        "planning",
        "financial"
    ],
    "wof:name":"AIG Royal Alliance",
    "wof:placetype":"venue"
},
  "geometry": {"coordinates":[-122.460634,37.89032],"type":"Point"}
}