{
  "type": "Feature",
  "properties": {
    "iso:country":"US",
    "sg:address":"8517 Holloway Dr",
    "sg:city":"West Hollywood",
    "sg:classifiers":[
        {
            "category":"Banks & Credit Unions",
            "subcategory":"Investment Brokerage",
            "type":"Services"
        }
    ],
    "sg:phone":"+1 310 289 7772",
    "sg:postcode":"90069",
    "sg:province":"CA",
    "sg:tags":[
        "consultant",
        "planning",
        "financial"
    ],
    "wof:name":"Finance Network-Southern Ca",
    "wof:placetype":"venue"
},
  "geometry": {"coordinates":[-118.377312,34.09069],"type":"Point"}
}