{
  "type": "Feature",
  "properties": {
    "iso:country":"US",
    "sg:address":"22921 Ocean Ave",
    "sg:city":"Torrance",
    "sg:classifiers":[
        {
            "category":"Professional",
            "subcategory":"Employment Agencies",
            "type":"Services"
        },
        {
            "category":"Professional",
            "subcategory":"Lawyer & Legal Services",
            "type":"Services"
        }
    ],
    "sg:phone":"+1 310 373 1404",
    "sg:postcode":"90505",
    "sg:province":"CA",
    "sg:tags":[
        "convention",
        "secretarial",
        "reporters-court"
    ],
    "wof:name":"Dawe's Desktop",
    "wof:placetype":"venue"
},
  "geometry": {"coordinates":[-118.354416,33.819394],"type":"Point"}
}