{
  "type": "Feature",
  "properties": {
    "iso:country":"US",
    "sg:address":"1044 E Edna Pl",
    "sg:city":"Anaheim",
    "sg:classifiers":[
        {
            "category":"Professional",
            "subcategory":"Printing & Photocopies",
            "type":"Services"
        }
    ],
    "sg:phone":"+1 714 817 7447",
    "sg:postcode":"92801",
    "sg:province":"CA",
    "sg:website":"www.disccreations.com",
    "wof:name":"Disc Creations",
    "wof:placetype":"venue"
},
  "geometry": {"coordinates":[-117.891875,33.764004],"type":"Point"}
}