{
  "type": "Feature",
  "properties": {
    "addr:full":"300 Bonnie Ln Hollister CA 95023",
    "addr:housenumber":"300",
    "addr:postcode":"hollister ca 95023",
    "addr:street":"Bonnie Ln",
    "iso:country":"US",
    "sg:address":"300 Bonnie Ln",
    "sg:city":"Hollister",
    "sg:classifiers":[
        {
            "category":"Building & Trades",
            "subcategory":"Landscaping Services",
            "type":"Services"
        }
    ],
    "sg:phone":"+1 831 637 3800",
    "sg:postcode":"95023",
    "sg:province":"CA",
    "sg:tags":[
        "landscape",
        "contractor"
    ],
    "wof:name":"Blume & Lindsay's Landscape",
    "wof:placetype":"venue"
},
  "geometry": {"coordinates":[-121.352327,36.805941],"type":"Point"}
}