{
  "type": "Feature",
  "properties": {
    "addr:full":"2753 E Eastland Ctr Dr West Covina CA 91791",
    "addr:housenumber":"2753",
    "addr:postcode":"91791",
    "addr:street":"E Eastland Ctr Dr",
    "iso:country":"US",
    "sg:address":"2753 E Eastland Ctr Dr",
    "sg:city":"West Covina",
    "sg:classifiers":[
        {
            "category":"Shopping",
            "subcategory":"Clothing, Apparel, & Fashions",
            "type":"Retail Goods"
        }
    ],
    "sg:phone":"+1 626 966 7202",
    "sg:postcode":"91791",
    "sg:province":"CA",
    "sg:website":"www.oldnavy.com",
    "wof:name":"Old Navy",
    "wof:placetype":"venue"
},
  "geometry": {"coordinates":[-117.88793800000001,34.073078],"type":"Point"}
}