{
  "type": "Feature",
  "properties": {
    "addr:full":"1350 Donner Ave San Francisco CA 94124",
    "addr:housenumber":"1350",
    "addr:postcode":"94124",
    "addr:street":"Donner Ave",
    "iso:country":"US",
    "sg:address":"1350 Donner Ave",
    "sg:city":"San Francisco",
    "sg:classifiers":[
        {
            "category":"Home & Garden",
            "subcategory":"Furniture",
            "type":"Retail Goods"
        }
    ],
    "sg:phone":"+1 415 822 4206",
    "sg:postcode":"94124",
    "sg:province":"CA",
    "sg:tags":[
        "equipment",
        "kitchen",
        "cabinet"
    ],
    "sg:website":"www.bartlettcabinetry.com",
    "wof:name":"Bartlett Cabinetry",
    "wof:placetype":"venue"
},
  "geometry": {"coordinates":[-122.389393,37.72175],"type":"Point"}
}