{
  "type": "Feature",
  "properties": {
    "iso:country":"US",
    "sg:address":"16551 Randall Ave",
    "sg:city":"Fontana",
    "sg:classifiers":[
        {
            "category":"Freight",
            "type":"Transportation"
        }
    ],
    "sg:phone":"+1 909 429 7057",
    "sg:postcode":"92335",
    "sg:province":"CA",
    "sg:tags":[
        "operator",
        "delivery",
        "local",
        "trucking"
    ],
    "wof:name":"Bonilla Transportation Svcs",
    "wof:placetype":"venue"
},
  "geometry": {"coordinates":[-117.443253,34.084769],"type":"Point"}
}