{
  "type": "Feature",
  "properties": {
    "iso:country":"US",
    "sg:address":"567 N Sierra Way",
    "sg:city":"San Bernardino",
    "sg:classifiers":[
        {
            "category":"Organizations",
            "subcategory":"Community Association",
            "type":"Services"
        }
    ],
    "sg:phone":"+1 909 889 9536",
    "sg:postcode":"92410",
    "sg:province":"CA",
    "sg:tags":[
        "child",
        "day",
        "care"
    ],
    "wof:name":"YWCA-San Bernardino",
    "wof:placetype":"venue"
},
  "geometry": {"coordinates":[-117.285074,34.108926],"type":"Point"}
}