{
  "type": "Feature",
  "properties": {
    "addr:full":"1717 Junction Avenue San Jose CA 95112",
    "addr:housenumber":"1717",
    "addr:postcode":"95112",
    "addr:street":"Junction Avenue",
    "iso:country":"US",
    "sg:address":"1717 Junction Avenue",
    "sg:city":"San Jose",
    "sg:classifiers":[
        {
            "category":"Home & Garden",
            "subcategory":"Carpets & Floor Coverings",
            "type":"Retail Goods"
        }
    ],
    "sg:phone":"+1 408 452 8121",
    "sg:postcode":"95112",
    "sg:province":"CA",
    "sg:tags":[
        "flooring"
    ],
    "wof:name":"Unique Design Center",
    "wof:placetype":"venue"
},
  "geometry": {"coordinates":[-121.906198,37.374313],"type":"Point"}
}