{
  "type": "Feature",
  "properties": {
    "iso:country":"US",
    "sg:address":"6401 Balboa Avenue",
    "sg:city":"San Diego",
    "sg:classifiers":[
        {
            "category":"Restaurant",
            "type":"Food & Drink"
        }
    ],
    "sg:phone":"+1 858 279 2734",
    "sg:postcode":"92111",
    "sg:province":"CA",
    "wof:name":"Burger King",
    "wof:placetype":"venue"
},
  "geometry": {"coordinates":[-117.173231,32.820306],"type":"Point"}
}