{
  "type": "Feature",
  "properties": {
    "iso:country":"US",
    "sg:address":"360 Moncada Way",
    "sg:city":"San Francisco",
    "sg:classifiers":[
        {
            "category":"Building & Trades",
            "subcategory":"Construction",
            "type":"Services"
        }
    ],
    "sg:phone":"+1 415 929 9494",
    "sg:postcode":"94127",
    "sg:province":"CA",
    "sg:tags":[
        "roofing",
        "contractor"
    ],
    "wof:name":"Art General Roofing",
    "wof:placetype":"venue"
},
  "geometry": {"coordinates":[-122.46943400000001,37.729367],"type":"Point"}
}