{
  "type": "Feature",
  "properties": {
    "iso:country":"US",
    "sg:address":"2235 California St",
    "sg:city":"Mountain View",
    "sg:classifiers":[
        {
            "category":"Real Estate",
            "subcategory":"Real Estate Operator",
            "type":"Services"
        }
    ],
    "sg:phone":"+1 650 428 1154",
    "sg:postcode":"94040",
    "sg:province":"CA",
    "sg:tags":[
        "apartment"
    ],
    "wof:name":"Regal Palms Apts",
    "wof:placetype":"venue"
},
  "geometry": {"coordinates":[-122.10093999999999,37.399499],"type":"Point"}
}