{
  "type": "Feature",
  "properties": {
    "iso:country":"US",
    "sg:address":"10220 State Rte 99",
    "sg:city":"Stockton",
    "sg:classifiers":[
        {
            "category":"Retail",
            "subcategory":"Auto Rental",
            "type":"Services"
        }
    ],
    "sg:phone":"+1 209 931 1077",
    "sg:postcode":"95212",
    "sg:province":"CA",
    "sg:tags":[
        "renting",
        "automobile"
    ],
    "wof:name":"Budget Rent A Car",
    "wof:placetype":"venue"
},
  "geometry": {"coordinates":[-121.258899,38.051129],"type":"Point"}
}