{
  "type": "Feature",
  "properties": {
    "iso:country":"US",
    "sg:address":"5655 Lindero Canyon Rd",
    "sg:city":"Thousand Oaks",
    "sg:classifiers":[
        {
            "category":"Professional",
            "type":"Services"
        },
        {
            "category":"Professional",
            "subcategory":"Business Services",
            "type":"Services"
        }
    ],
    "sg:phone":"+1 818 706 1377",
    "sg:postcode":"91362",
    "sg:province":"CA",
    "sg:tags":[
        "appraiser"
    ],
    "wof:name":"Girbovan Inc",
    "wof:placetype":"venue"
},
  "geometry": {"coordinates":[-118.799442,34.153201],"type":"Point"}
}