{
  "type": "Feature",
  "properties": {
    "addr:full":"420 N Santa Cruz Ave Los Gatos CA 95030",
    "addr:housenumber":"420",
    "addr:postcode":"95030",
    "addr:street":"N Santa Cruz Ave",
    "iso:country":"US",
    "sg:address":"420 N Santa Cruz Ave",
    "sg:city":"Los Gatos",
    "sg:classifiers":[
        {
            "category":"Personal",
            "subcategory":"Beauty Salon",
            "type":"Services"
        }
    ],
    "sg:phone":"+1 408 395 2300",
    "sg:postcode":"95030",
    "sg:province":"CA",
    "wof:name":"Scandalous",
    "wof:placetype":"venue"
},
  "geometry": {"coordinates":[-121.97959,37.23145],"type":"Point"}
}