{
  "type": "Feature",
  "properties": {
    "addr:full":"510 Corona Mall Corona CA 92879",
    "addr:housenumber":"510",
    "addr:postcode":"92879",
    "addr:street":"Corona Mall",
    "iso:country":"US",
    "sg:address":"510 Corona Mall",
    "sg:city":"Corona",
    "sg:classifiers":[
        {
            "category":"Personal",
            "subcategory":"Beauty Salon",
            "type":"Services"
        }
    ],
    "sg:phone":"+1 951 735 0466",
    "sg:postcode":"92879",
    "sg:province":"CA",
    "sg:tags":[
        "treatment",
        "skin"
    ],
    "sg:website":"www.goshannon.com",
    "wof:name":"Shandar",
    "wof:placetype":"venue"
},
  "geometry": {"coordinates":[-117.56679699999999,33.876315],"type":"Point"}
}