{
  "type": "Feature",
  "properties": {
    "iso:country":"US",
    "sg:address":"299 Park Blvd",
    "sg:city":"Orange Cove",
    "sg:classifiers":[
        {
            "category":"Shopping",
            "subcategory":"Clothing, Apparel, & Fashions",
            "type":"Retail Goods"
        }
    ],
    "sg:phone":"+1 559 626 7271",
    "sg:postcode":"93646",
    "sg:province":"CA",
    "wof:name":"Fashion Xpress",
    "wof:placetype":"venue"
},
  "geometry": {"coordinates":[-119.30707,36.624452],"type":"Point"}
}