{
  "type": "Feature",
  "properties": {
    "iso:country":"US",
    "sg:address":"4930 Lake Blvd",
    "sg:city":"Oceanside",
    "sg:classifiers":[
        {
            "category":"Education",
            "subcategory":"School",
            "type":"Public Place"
        }
    ],
    "sg:phone":"+1 760 940 0176",
    "sg:postcode":"92056",
    "sg:province":"CA",
    "sg:tags":[
        "high",
        "middle",
        "elementary"
    ],
    "wof:name":"Vista Unified School District",
    "wof:placetype":"venue"
},
  "geometry": {"coordinates":[-117.25900300000001,33.173199],"type":"Point"}
}