{
  "type": "Feature",
  "properties": {
    "iso:country":"US",
    "sg:address":"463 N Midway Dr",
    "sg:city":"Escondido",
    "sg:classifiers":[
        {
            "category":"Social Services",
            "type":"Services"
        }
    ],
    "sg:phone":"+1 760 489 4951",
    "sg:postcode":"92027",
    "sg:province":"CA",
    "sg:tags":[
        "organization",
        "welfare"
    ],
    "wof:name":"Home Start Inc",
    "wof:placetype":"venue"
},
  "geometry": {"coordinates":[-117.051989,33.137638],"type":"Point"}
}