{
  "type": "Feature",
  "properties": {
    "addr:full":"13739 Riverside Dr Sherman Oaks CA 91423",
    "addr:housenumber":"13739",
    "addr:postcode":"91423",
    "addr:street":"Riverside Dr",
    "iso:country":"US",
    "sg:address":"13739 Riverside Dr",
    "sg:city":"Sherman Oaks",
    "sg:classifiers":[
        {
            "category":"Shopping",
            "subcategory":"Optical Goods",
            "type":"Retail Goods"
        }
    ],
    "sg:phone":"+1 818 995 7989",
    "sg:postcode":"91423",
    "sg:province":"CA",
    "sg:tags":[
        "sun",
        "goggles",
        "optician",
        "sunglass",
        "eyewear"
    ],
    "wof:name":"Fashion Optical",
    "wof:placetype":"venue"
},
  "geometry": {"coordinates":[-118.431999,34.1576],"type":"Point"}
}