{
  "type": "Feature",
  "properties": {
    "addr:full":"1009 S Hazelwood Blvd Fresno CA 93702",
    "addr:housenumber":"1009",
    "addr:postcode":"93702",
    "addr:street":"S Hazelwood Blvd",
    "iso:country":"US",
    "sg:address":"1009 S Hazelwood Blvd",
    "sg:city":"Fresno",
    "sg:classifiers":[
        {
            "category":"Organizations",
            "subcategory":"Religious Organization",
            "type":"Services"
        }
    ],
    "sg:phone":"+1 559 443 7107",
    "sg:postcode":"93702",
    "sg:province":"CA",
    "sg:tags":[
        "church"
    ],
    "wof:name":"Embassy International Life",
    "wof:placetype":"venue"
},
  "geometry": {"coordinates":[-119.770917,36.731725],"type":"Point"}
}