{
  "type": "Feature",
  "properties": {
    "addr:full":"399 Lighthouse Ave Monterey CA 93940",
    "addr:housenumber":"399",
    "addr:postcode":"93940",
    "addr:street":"Lighthouse Ave",
    "iso:country":"US",
    "sg:address":"399 Lighthouse Ave",
    "sg:city":"Monterey",
    "sg:classifiers":[
        {
            "category":"Sports & Exercise",
            "subcategory":"Golf",
            "type":"Entertainment"
        }
    ],
    "sg:phone":"+1 831 372 5516",
    "sg:postcode":"93940",
    "sg:province":"CA",
    "sg:tags":[
        "course"
    ],
    "wof:name":"Nevada Bob's",
    "wof:placetype":"venue"
},
  "geometry": {"coordinates":[-121.89943599999999,36.610907],"type":"Point"}
}