{
  "type": "Feature",
  "properties": {
    "addr:full":"60 N 3rd St Ofc San Jose CA 95112",
    "addr:housenumber":"60",
    "addr:postcode":"95112",
    "addr:street":"N 3Rd St",
    "iso:country":"US",
    "sg:address":"60 N 3rd St Ofc",
    "sg:city":"San Jose",
    "sg:classifiers":[
        {
            "category":"Real Estate",
            "subcategory":"Real Estate Operator",
            "type":"Services"
        }
    ],
    "sg:phone":"+1 408 288 8750",
    "sg:postcode":"95112",
    "sg:province":"CA",
    "sg:tags":[
        "apartment"
    ],
    "wof:name":"Town Park Towers",
    "wof:placetype":"venue"
},
  "geometry": {"coordinates":[-121.889,37.3381],"type":"Point"}
}