{
  "type": "Feature",
  "properties": {
    "addr:full":"11633 Hawthorne Blvd Hawthorne CA 90250",
    "addr:housenumber":"11633",
    "addr:postcode":"90250",
    "addr:street":"Hawthorne Blvd",
    "iso:country":"US",
    "sg:address":"11633 Hawthorne Blvd",
    "sg:city":"Hawthorne",
    "sg:classifiers":[
        {
            "category":"Insurance",
            "subcategory":"Insurance Agent",
            "type":"Services"
        }
    ],
    "sg:phone":"+1 310 856 5301",
    "sg:postcode":"90250",
    "sg:province":"CA",
    "wof:name":"West Coast Insurance",
    "wof:placetype":"venue"
},
  "geometry": {"coordinates":[-118.35254500000001,33.928759],"type":"Point"}
}