{
  "type": "Feature",
  "properties": {
    "addr:full":"645 Los Arboles Aptos CA 95003",
    "addr:housenumber":"645",
    "addr:postcode":"ca 95003",
    "addr:street":"Los Arboles",
    "iso:country":"US",
    "sg:address":"645 Los Arboles",
    "sg:city":"Aptos",
    "sg:classifiers":[
        {
            "category":"Health Services",
            "subcategory":"Health Practitioner",
            "type":"Services"
        }
    ],
    "sg:phone":"+1 831 688 5462",
    "sg:postcode":"95003",
    "sg:province":"CA",
    "sg:tags":[
        "psychologist"
    ],
    "wof:name":"Gary Shoemaker PHD",
    "wof:placetype":"venue"
},
  "geometry": {"coordinates":[-121.881889,36.991484],"type":"Point"}
}