{
  "type": "Feature",
  "properties": {
    "iso:country":"US",
    "sg:address":"848 W Huntington Dr",
    "sg:city":"Arcadia",
    "sg:classifiers":[
        {
            "category":"Food & Beverages",
            "subcategory":"Specialty",
            "type":"Retail Goods"
        }
    ],
    "sg:phone":"+1 626 574 8580",
    "sg:postcode":"91007",
    "sg:province":"CA",
    "wof:name":"Annia Networking Company",
    "wof:placetype":"venue"
},
  "geometry": {"coordinates":[-118.060609,34.131161],"type":"Point"}
}