{
  "type": "Feature",
  "properties": {
    "addr:full":"709 Petaluma Blvd N Petaluma CA 94952",
    "addr:housenumber":"709",
    "addr:postcode":"94952",
    "addr:street":"Petaluma Blvd N",
    "iso:country":"US",
    "sg:address":"709 Petaluma Blvd N",
    "sg:city":"Petaluma",
    "sg:classifiers":[
        {
            "category":"Personal",
            "type":"Services"
        }
    ],
    "sg:phone":"+1 707 763 0722",
    "sg:postcode":"94952",
    "sg:province":"CA",
    "sg:tags":[
        "therapist",
        "massage"
    ],
    "wof:name":"Rub Club",
    "wof:placetype":"venue"
},
  "geometry": {"coordinates":[-122.643974,38.242031],"type":"Point"}
}