{
  "type": "Feature",
  "properties": {
    "iso:country":"US",
    "sg:address":"2447 W Manchester Blvd",
    "sg:city":"Inglewood",
    "sg:classifiers":[
        {
            "category":"Banks & Credit Unions",
            "subcategory":"Bank",
            "type":"Services"
        }
    ],
    "sg:phone":"+1 323 758 8242",
    "sg:postcode":"90305",
    "sg:province":"CA",
    "sg:tags":[
        "real estate",
        "mortgage",
        "broker"
    ],
    "wof:name":"Legacy Realty",
    "wof:placetype":"venue"
},
  "geometry": {"coordinates":[-118.320604,33.960126],"type":"Point"}
}