{
  "type": "Feature",
  "properties": {
    "addr:full":"751 4th Ave San Diego CA 92101",
    "addr:housenumber":"751",
    "addr:postcode":"92101",
    "addr:street":"4Th Ave",
    "iso:country":"US",
    "sg:address":"751 4th Ave",
    "sg:city":"San Diego",
    "sg:classifiers":[
        {
            "category":"Shopping",
            "subcategory":"Music",
            "type":"Retail Goods"
        }
    ],
    "sg:phone":"+1 619 236 0841",
    "sg:postcode":"92101",
    "sg:province":"CA",
    "sg:tags":[
        "tape",
        "bookstore",
        "disc",
        "video",
        "cassette"
    ],
    "sg:website":"www.fstreet.com",
    "wof:name":"F Street Adult Video & Gifts",
    "wof:placetype":"venue"
},
  "geometry": {"coordinates":[-117.16104,32.713235],"type":"Point"}
}