{
  "type": "Feature",
  "properties": {
    "iso:country":"US",
    "sg:address":"7636 Hollywood Blvd",
    "sg:city":"West Hollywood",
    "sg:classifiers":[
        {
            "category":"Social Services",
            "type":"Services"
        }
    ],
    "sg:phone":"+1 323 650 8118",
    "sg:postcode":"90046",
    "sg:province":"CA",
    "sg:tags":[
        "care",
        "center",
        "day"
    ],
    "wof:name":"L'Chaim Daycare",
    "wof:placetype":"venue"
},
  "geometry": {"coordinates":[-118.355441,34.101589],"type":"Point"}
}