{
  "type": "Feature",
  "properties": {
    "addr:full":"314 W Main St Grass Valley CA 95945",
    "addr:housenumber":"314",
    "addr:postcode":"95945",
    "addr:street":"W Main St",
    "iso:country":"US",
    "sg:address":"314 W Main St",
    "sg:city":"Grass Valley",
    "sg:classifiers":[
        {
            "category":"Education",
            "subcategory":"Dance Studio",
            "type":"Public Place"
        }
    ],
    "sg:phone":"+1 530 477 7644",
    "sg:postcode":"95945",
    "sg:province":"CA",
    "sg:tags":[
        "instruction",
        "dancing"
    ],
    "wof:name":"Sierra Dance Institute",
    "wof:placetype":"venue"
},
  "geometry": {"coordinates":[-121.064533,39.219264],"type":"Point"}
}