{
  "type": "Feature",
  "properties": {
    "iso:country":"US",
    "sg:address":"39770 Garand Ln",
    "sg:city":"Palm Desert",
    "sg:classifiers":[
        {
            "category":"Wholesale",
            "subcategory":"Construction Materials",
            "type":"Manufacturing & Wholesale Goods"
        }
    ],
    "sg:phone":"+1 760 200 5004",
    "sg:postcode":"92211",
    "sg:province":"CA",
    "sg:tags":[
        "marble"
    ],
    "wof:name":"Import Stone",
    "wof:placetype":"venue"
},
  "geometry": {"coordinates":[-116.307956,33.75965],"type":"Point"}
}