{
  "type": "Feature",
  "properties": {
    "iso:country":"US",
    "sg:address":"719 Santa Monica Blvd",
    "sg:city":"Santa Monica",
    "sg:classifiers":[
        {
            "category":"Health Services",
            "subcategory":"Health Practitioner",
            "type":"Services"
        }
    ],
    "sg:phone":"+1 310 260 9039",
    "sg:postcode":"90401",
    "sg:province":"CA",
    "sg:tags":[
        "therapist",
        "physical"
    ],
    "sg:website":"www.physicaltherapyworks.com",
    "wof:name":"Physical Therapyworks",
    "wof:placetype":"venue"
},
  "geometry": {"coordinates":[-118.492037,34.019009],"type":"Point"}
}