{
  "type": "Feature",
  "properties": {
    "iso:country":"US",
    "sg:address":"3310 Truxtun Ave",
    "sg:city":"Bakersfield",
    "sg:classifiers":[
        {
            "category":"Personal",
            "subcategory":"Beauty Salon",
            "type":"Services"
        }
    ],
    "sg:phone":"+1 661 852 0976",
    "sg:postcode":"93301",
    "sg:province":"CA",
    "wof:name":"Protege Hair Designs",
    "wof:placetype":"venue"
},
  "geometry": {"coordinates":[-119.040296,35.37354],"type":"Point"}
}