{
  "type": "Feature",
  "properties": {
    "iso:country":"US",
    "sg:address":"2310 Placentia Ave",
    "sg:city":"Costa Mesa",
    "sg:classifiers":[
        {
            "category":"Sports & Exercise",
            "subcategory":"Golf",
            "type":"Entertainment"
        }
    ],
    "sg:phone":"+1 949 574 0278",
    "sg:postcode":"92627",
    "sg:province":"CA",
    "sg:website":"www.costamesacountryclub.com/",
    "wof:name":"Costa Mesa Country Club",
    "wof:placetype":"venue"
},
  "geometry": {"coordinates":[-117.931999,33.658001],"type":"Point"}
}