{
  "type": "Feature",
  "properties": {
    "iso:country":"US",
    "sg:address":"2662 Palm Ave",
    "sg:city":"Atwater",
    "sg:classifiers":[
        {
            "category":"Professional",
            "subcategory":"Accounting & Tax Preparation",
            "type":"Services"
        }
    ],
    "sg:phone":"+1 209 358 7400",
    "sg:postcode":"95301",
    "sg:province":"CA",
    "sg:tags":[
        "accountant"
    ],
    "wof:name":"E Eileen Duddy CPA",
    "wof:placetype":"venue"
},
  "geometry": {"coordinates":[-120.599288,37.359336],"type":"Point"}
}