{
  "type": "Feature",
  "properties": {
    "addr:full":"10325 Jefferson Boulevard Culver City CA 90232",
    "addr:housenumber":"10325",
    "addr:postcode":"90232",
    "addr:street":"Jefferson Boulevard",
    "iso:country":"US",
    "sg:address":"10325 Jefferson Boulevard",
    "sg:city":"Culver City",
    "sg:classifiers":[
        {
            "category":"Retail",
            "subcategory":"Portrait Studio",
            "type":"Services"
        }
    ],
    "sg:phone":"+1 310 204 3890",
    "sg:postcode":"90232",
    "sg:province":"CA",
    "sg:tags":[
        "photography",
        "store"
    ],
    "wof:name":"Prolab Custom Color Lab",
    "wof:placetype":"venue"
},
  "geometry": {"coordinates":[-118.39093,34.009125],"type":"Point"}
}