{
  "type": "Feature",
  "properties": {
    "addr:full":"833 Texas St Fairfield CA 94533",
    "addr:housenumber":"833",
    "addr:postcode":"94533",
    "addr:street":"Texas St",
    "iso:country":"US",
    "sg:address":"833 Texas St",
    "sg:city":"Fairfield",
    "sg:classifiers":[
        {
            "category":"Bars & Pubs",
            "type":"Food & Drink"
        }
    ],
    "sg:phone":"+1 707 422 2940",
    "sg:postcode":"94533",
    "sg:province":"CA",
    "sg:tags":[
        "lounge",
        "cocktail"
    ],
    "wof:name":"Harry's Sportman's Lounge",
    "wof:placetype":"venue"
},
  "geometry": {"coordinates":[-122.043649,38.249236],"type":"Point"}
}