{
  "type": "Feature",
  "properties": {
    "addr:full":"72060 Hwy 111 Rancho Mirage CA 92270",
    "addr:housenumber":"72060",
    "addr:postcode":"92270",
    "addr:street":"Hwy 111",
    "iso:country":"US",
    "sg:address":"72060 Hwy 111",
    "sg:city":"Rancho Mirage",
    "sg:classifiers":[
        {
            "category":"Shopping",
            "subcategory":"Clothing, Apparel, & Fashions",
            "type":"Retail Goods"
        }
    ],
    "sg:phone":"+1 760 340 6555",
    "sg:postcode":"92270",
    "sg:province":"CA",
    "wof:name":"Avenue",
    "wof:placetype":"venue"
},
  "geometry": {"coordinates":[-116.407808,33.735606],"type":"Point"}
}