{
  "type": "Feature",
  "properties": {
    "iso:country":"US",
    "sg:address":"1489 S San Jacinto Ave",
    "sg:city":"San Jacinto",
    "sg:classifiers":[
        {
            "category":"Utilities",
            "subcategory":"Mobile Phone",
            "type":"Services"
        }
    ],
    "sg:phone":"+1 951 487 6710",
    "sg:postcode":"92583",
    "sg:province":"CA",
    "sg:tags":[
        "communication",
        "radiotelephone"
    ],
    "wof:name":"Simar Cellular",
    "wof:placetype":"venue"
},
  "geometry": {"coordinates":[-116.95868900000001,33.770118],"type":"Point"}
}