{
  "type": "Feature",
  "properties": {
    "addr:full":"41063 Fremont Blvd Fremont CA 94538",
    "addr:housenumber":"41063",
    "addr:postcode":"94538",
    "addr:street":"Fremont Blvd",
    "iso:country":"US",
    "sg:address":"41063 Fremont Blvd",
    "sg:city":"Fremont",
    "sg:classifiers":[
        {
            "category":"Restaurant",
            "type":"Food & Drink"
        }
    ],
    "sg:phone":"+1 510 656 6908",
    "sg:postcode":"94538",
    "sg:province":"CA",
    "wof:name":"Hong Kong Buffet",
    "wof:placetype":"venue"
},
  "geometry": {"coordinates":[-121.95895299999999,37.53128],"type":"Point"}
}