{
  "type": "Feature",
  "properties": {
    "iso:country":"US",
    "sg:address":"696 San Ramon Valley Blvd",
    "sg:city":"Danville",
    "sg:classifiers":[
        {
            "category":"Building & Trades",
            "subcategory":"Cleaning & Sanitation",
            "type":"Services"
        }
    ],
    "sg:phone":"+1 925 473 9566",
    "sg:postcode":"94583",
    "sg:province":"CA",
    "sg:tags":[
        "window"
    ],
    "wof:name":"Advanced Window Cleaning",
    "wof:placetype":"venue"
},
  "geometry": {"coordinates":[-121.99585999999999,37.813943],"type":"Point"}
}