{
  "type": "Feature",
  "properties": {
    "iso:country":"US",
    "sg:address":"322 E Bennett Ave",
    "sg:city":"Glendora",
    "sg:classifiers":[
        {
            "category":"Retail",
            "subcategory":"Animal Services",
            "type":"Services"
        }
    ],
    "sg:phone":"+1 626 852 9992",
    "sg:postcode":"91741",
    "sg:province":"CA",
    "wof:name":"Live Oak Dog Obedience",
    "wof:placetype":"venue"
},
  "geometry": {"coordinates":[-117.862655,34.139611],"type":"Point"}
}