{
  "type": "Feature",
  "properties": {
    "addr:full":"1467 E Dinuba Ave Reedley CA 93654",
    "addr:housenumber":"1467",
    "addr:postcode":"93654",
    "addr:street":"E Dinuba Ave",
    "iso:country":"US",
    "sg:address":"1467 E Dinuba Ave",
    "sg:city":"Reedley",
    "sg:classifiers":[
        {
            "category":"Freight",
            "type":"Transportation"
        }
    ],
    "sg:phone":"+1 559 638 9281",
    "sg:postcode":"93654",
    "sg:province":"CA",
    "sg:tags":[
        "scale"
    ],
    "wof:name":"Reedley Public Scale",
    "wof:placetype":"venue"
},
  "geometry": {"coordinates":[-119.43499300000001,36.589587],"type":"Point"}
}