{
  "type": "Feature",
  "properties": {
    "addr:full":"3505 Hart Ave Ste 214 Rosemead CA 91770",
    "addr:housenumber":"3505",
    "addr:postcode":"91770",
    "addr:street":"Hart Ave Ste 214",
    "iso:country":"US",
    "sg:address":"3505 Hart Ave Ste 214",
    "sg:city":"Rosemead",
    "sg:classifiers":[
        {
            "category":"Real Estate",
            "subcategory":"Real Estate Services",
            "type":"Services"
        }
    ],
    "sg:phone":"+1 626 572 5101",
    "sg:postcode":"91770",
    "sg:province":"CA",
    "sg:tags":[
        "management",
        "property"
    ],
    "wof:name":"Beacon Property Management",
    "wof:placetype":"venue"
},
  "geometry": {"coordinates":[-118.069,34.072701],"type":"Point"}
}