{
  "type": "Feature",
  "properties": {
    "iso:country":"US",
    "sg:address":"32519 Mission Blvd",
    "sg:city":"Hayward",
    "sg:classifiers":[
        {
            "category":"Manufacturing",
            "subcategory":"Food",
            "type":"Manufacturing & Wholesale Goods"
        }
    ],
    "sg:phone":"+1 510 471 3750",
    "sg:postcode":"94544",
    "sg:province":"CA",
    "sg:tags":[
        "fluid",
        "milk"
    ],
    "wof:name":"Clarendon Foods",
    "wof:placetype":"venue"
},
  "geometry": {"coordinates":[-122.024956,37.610477],"type":"Point"}
}