{
  "type": "Feature",
  "properties": {
    "iso:country":"US",
    "sg:address":"195 N Coventry Ave",
    "sg:city":"Clovis",
    "sg:classifiers":[
        {
            "category":"Building & Trades",
            "subcategory":"Electrical",
            "type":"Services"
        }
    ],
    "sg:phone":"+1 559 355 7457",
    "sg:postcode":"93611",
    "sg:province":"CA",
    "sg:tags":[
        "industrial",
        "electrician",
        "contractors-commercial",
        "electric"
    ],
    "sg:website":"http://www.willdouglasselectric.com",
    "wof:name":"Will Douglass Electric",
    "wof:placetype":"venue"
},
  "geometry": {"coordinates":[-119.660055,36.833298],"type":"Point"}
}