{
  "type": "Feature",
  "properties": {
    "iso:country":"US",
    "sg:address":"39 W Main St",
    "sg:city":"Woodland",
    "sg:classifiers":[
        {
            "category":"Professional",
            "subcategory":"Employment Agencies",
            "type":"Services"
        }
    ],
    "sg:phone":"+1 530 662 8607",
    "sg:postcode":"95695",
    "sg:province":"CA",
    "sg:tags":[
        "help",
        "contractor"
    ],
    "wof:name":"Accustaff",
    "wof:placetype":"venue"
},
  "geometry": {"coordinates":[-121.78683,38.6775],"type":"Point"}
}