{
  "type": "Feature",
  "properties": {
    "iso:country":"US",
    "sg:address":"14291 Euclid St",
    "sg:city":"Garden Grove",
    "sg:classifiers":[
        {
            "category":"Banks & Credit Unions",
            "subcategory":"Financial Services",
            "type":"Services"
        }
    ],
    "sg:phone":"+1 714 210 3180",
    "sg:postcode":"92843",
    "sg:province":"CA",
    "sg:tags":[
        "broker",
        "mortgage"
    ],
    "wof:name":"Millennium Capital Mortgage",
    "wof:placetype":"venue"
},
  "geometry": {"coordinates":[-117.93800400000001,33.7607],"type":"Point"}
}