{
  "type": "Feature",
  "properties": {
    "iso:country":"US",
    "sg:address":"201 Alvarado St",
    "sg:city":"Monterey",
    "sg:classifiers":[
        {
            "category":"Personal",
            "subcategory":"Massage",
            "type":"Services"
        },
        {
            "category":"Personal",
            "subcategory":"Beauty Salon",
            "type":"Services"
        },
        {
            "category":"Shopping",
            "subcategory":"Party Supplies",
            "type":"Retail Goods"
        },
        {
            "category":"Personal",
            "subcategory":"Day Spa",
            "type":"Services"
        },
        {
            "category":"Personal",
            "subcategory":"Skin Care",
            "type":"Services"
        }
    ],
    "sg:phone":"+1 831 647 9000",
    "sg:postcode":"93940",
    "sg:province":"CA",
    "sg:tags":[
        "therapist",
        "wedding"
    ],
    "sg:website":"http://www.spaontheplaza.com",
    "wof:name":"Spa On The Plaza",
    "wof:placetype":"venue"
},
  "geometry": {"coordinates":[-121.893799,36.602131],"type":"Point"}
}