{
  "type": "Feature",
  "properties": {
    "iso:country":"US",
    "sg:address":"123 E California St",
    "sg:city":"Ontario",
    "sg:classifiers":[
        {
            "category":"Retail",
            "subcategory":"Auto Repair",
            "type":"Services"
        }
    ],
    "sg:phone":"+1 909 460 0288",
    "sg:postcode":"91761",
    "sg:province":"CA",
    "sg:tags":[
        "muffler",
        "exhaust",
        "system"
    ],
    "wof:name":"Durango",
    "wof:placetype":"venue"
},
  "geometry": {"coordinates":[-117.649882,34.055829],"type":"Point"}
}