{
  "type": "Feature",
  "properties": {
    "addr:full":"41917 Osgood Rd Fremont CA 94539",
    "addr:housenumber":"41917",
    "addr:postcode":"94539",
    "addr:street":"Osgood Rd",
    "iso:country":"US",
    "sg:address":"41917 Osgood Rd",
    "sg:city":"Fremont",
    "sg:classifiers":[
        {
            "category":"Wholesale",
            "subcategory":"Groceries",
            "type":"Manufacturing & Wholesale Goods"
        }
    ],
    "sg:phone":"+1 510 226 6186",
    "sg:postcode":"94539",
    "sg:province":"CA",
    "sg:tags":[
        "tea"
    ],
    "wof:name":"101 Tea Inc",
    "wof:placetype":"venue"
},
  "geometry": {"coordinates":[-121.952423,37.530639],"type":"Point"}
}