{
  "type": "Feature",
  "properties": {
    "addr:full":"948 Bauman Ct Suisun City CA 94585",
    "addr:housenumber":"948",
    "addr:postcode":"94585",
    "addr:street":"Bauman Ct",
    "iso:country":"US",
    "sg:address":"948 Bauman Ct",
    "sg:city":"Suisun City",
    "sg:classifiers":[
        {
            "category":"Professional",
            "subcategory":"Lawyer & Legal Services",
            "type":"Services"
        }
    ],
    "sg:phone":"+1 707 235 8285",
    "sg:postcode":"94585",
    "sg:province":"CA",
    "wof:name":"Nor Cal Legal Svc",
    "wof:placetype":"venue"
},
  "geometry": {"coordinates":[-122.01017400000001,38.241829],"type":"Point"}
}