{
  "type": "Feature",
  "properties": {
    "iso:country":"US",
    "sg:address":"582 Market Street",
    "sg:city":"San Francisco",
    "sg:classifiers":[
        {
            "category":"Professional",
            "subcategory":"Lawyer & Legal Services",
            "type":"Services"
        }
    ],
    "sg:phone":"+1 415 981 2680",
    "sg:postcode":"94104",
    "sg:province":"CA",
    "wof:name":"Hayes John A Attys",
    "wof:placetype":"venue"
},
  "geometry": {"coordinates":[-122.40122,37.789405],"type":"Point"}
}