{
  "type": "Feature",
  "properties": {
    "addr:full":"11420 Atlantic Ave Lynwood CA 90262",
    "addr:housenumber":"11420",
    "addr:postcode":"90262",
    "addr:street":"Atlantic Ave",
    "iso:country":"US",
    "sg:address":"11420 Atlantic Ave",
    "sg:city":"Lynwood",
    "sg:classifiers":[
        {
            "category":"Home & Garden",
            "subcategory":"Building Materials",
            "type":"Retail Goods"
        }
    ],
    "sg:phone":"+1 310 631 9920",
    "sg:postcode":"90262",
    "sg:province":"CA",
    "sg:tags":[
        "paint"
    ],
    "wof:name":"Best Color Supply",
    "wof:placetype":"venue"
},
  "geometry": {"coordinates":[-118.187744,33.920431],"type":"Point"}
}