{
  "type": "Feature",
  "properties": {
    "addr:full":"1889 W Commonwealth Ave Fullerton CA 92833",
    "addr:housenumber":"1889",
    "addr:postcode":"92833",
    "addr:street":"W Commonwealth Ave",
    "iso:country":"US",
    "sg:address":"1889 W Commonwealth Ave",
    "sg:city":"Fullerton",
    "sg:classifiers":[
        {
            "category":"Shopping",
            "subcategory":"Tobacco",
            "type":"Retail Goods"
        }
    ],
    "sg:phone":"+1 714 441 2740",
    "sg:postcode":"92833",
    "sg:province":"CA",
    "sg:tags":[
        "shop"
    ],
    "wof:name":"Worldwide Smoke Inc",
    "wof:placetype":"venue"
},
  "geometry": {"coordinates":[-117.963269,33.870236],"type":"Point"}
}