{
  "type": "Feature",
  "properties": {
    "addr:full":"15115 Ave 313 Visalia CA 93292",
    "addr:housenumber":"15115",
    "addr:postcode":"93292",
    "addr:street":"Ave 313",
    "iso:country":"US",
    "sg:address":"15115 Ave 313",
    "sg:city":"Visalia",
    "sg:classifiers":[
        {
            "category":"Professional",
            "type":"Services"
        }
    ],
    "sg:phone":"+1 559 798 6926",
    "sg:postcode":"93292",
    "sg:province":"CA",
    "wof:name":"Jiva Inst For Vaisnava Studies",
    "wof:placetype":"venue"
},
  "geometry": {"coordinates":[-119.24027700000001,36.358173],"type":"Point"}
}