{
  "type": "Feature",
  "properties": {
    "iso:country":"US",
    "sg:address":"1200 41st Ave Ste C",
    "sg:city":"Capitola",
    "sg:classifiers":[
        {
            "category":"Sports & Exercise",
            "subcategory":"Gym",
            "type":"Entertainment"
        }
    ],
    "sg:phone":"+1 831 462 2004",
    "sg:postcode":"95010",
    "sg:province":"CA",
    "wof:name":"Spa Fitness Centers Inc",
    "wof:placetype":"venue"
},
  "geometry": {"coordinates":[-121.964147,36.969112],"type":"Point"}
}