{
  "type": "Feature",
  "properties": {
    "iso:country":"US",
    "sg:address":"1190 N Glassell St",
    "sg:city":"Orange",
    "sg:classifiers":[
        {
            "category":"Food & Beverages",
            "subcategory":"Groceries & Convenience Stores",
            "type":"Retail Goods"
        }
    ],
    "sg:phone":"+1 714 289 9393",
    "sg:postcode":"92867",
    "sg:province":"CA",
    "sg:tags":[
        "grocer"
    ],
    "wof:name":"Unidos Nutrition",
    "wof:placetype":"venue"
},
  "geometry": {"coordinates":[-117.852997,33.807499],"type":"Point"}
}