{
  "type": "Feature",
  "properties": {
    "iso:country":"US",
    "sg:address":"1925 Alliance Rd",
    "sg:city":"Arcata",
    "sg:classifiers":[
        {
            "category":"Home & Garden",
            "subcategory":"Hardware",
            "type":"Retail Goods"
        }
    ],
    "sg:phone":"+1 707 822 2503",
    "sg:postcode":"95521",
    "sg:province":"CA",
    "sg:tags":[
        "saw"
    ],
    "wof:name":"North Coast Saw & Supply Co",
    "wof:placetype":"venue"
},
  "geometry": {"coordinates":[-124.09162000000001,40.877834],"type":"Point"}
}