{
  "type": "Feature",
  "properties": {
    "addr:full":"177 E College St Covina CA 91723",
    "addr:housenumber":"177",
    "addr:postcode":"91723",
    "addr:street":"E College St",
    "iso:country":"US",
    "sg:address":"177 E College St",
    "sg:city":"Covina",
    "sg:classifiers":[
        {
            "category":"Ice Cream",
            "type":"Food & Drink"
        }
    ],
    "sg:menulink":"http://www.allmenus.com/ca/east-san-gabriel-valley/242356-baskin-robbins/menu/",
    "sg:phone":"+1 626 332 2511",
    "sg:postcode":"91723",
    "sg:province":"CA",
    "sg:tags":[
        "american"
    ],
    "wof:name":"Baskin-Robbins",
    "wof:placetype":"venue"
},
  "geometry": {"coordinates":[-117.888147,34.087463],"type":"Point"}
}