{
  "type": "Feature",
  "properties": {
    "addr:full":"1341 Versailles Ave Alameda CA 94501",
    "addr:housenumber":"1341",
    "addr:postcode":"94501",
    "addr:street":"Versailles Ave",
    "iso:country":"US",
    "sg:address":"1341 Versailles Ave",
    "sg:city":"Alameda",
    "sg:classifiers":[
        {
            "category":"Wholesale",
            "subcategory":"Non-durable Goods",
            "type":"Manufacturing & Wholesale Goods"
        }
    ],
    "sg:phone":"+1 510 769 1475",
    "sg:postcode":"94501",
    "sg:province":"CA",
    "sg:tags":[
        "export",
        "gen",
        "merchandise"
    ],
    "wof:name":"Abbasi Enterprises Inc",
    "wof:placetype":"venue"
},
  "geometry": {"coordinates":[-122.237961,37.759801],"type":"Point"}
}