{
  "type": "Feature",
  "properties": {
    "iso:country":"US",
    "sg:address":"453 Nassau Ln",
    "sg:city":"Hayward",
    "sg:classifiers":[
        {
            "category":"Building & Trades",
            "subcategory":"Plumbing",
            "type":"Services"
        }
    ],
    "sg:phone":"+1 510 688 2597",
    "sg:postcode":"94544",
    "sg:province":"CA",
    "sg:website":"www.jcarrilloplumbinganddrains.com",
    "wof:name":"J. Carrillo Plumbing and Drains",
    "wof:placetype":"venue"
},
  "geometry": {"coordinates":[-122.039663,37.62193],"type":"Point"}
}