{
  "type": "Feature",
  "properties": {
    "addr:full":"108 Karina Ct San Jose CA 95131",
    "addr:housenumber":"108",
    "addr:postcode":"95131",
    "addr:street":"Karina Ct",
    "iso:country":"US",
    "sg:address":"108 Karina Ct",
    "sg:city":"San Jose",
    "sg:classifiers":[
        {
            "category":"Professional",
            "subcategory":"Business Services",
            "type":"Services"
        }
    ],
    "sg:phone":"+1 408 452 7447",
    "sg:postcode":"95131",
    "sg:province":"CA",
    "sg:tags":[
        "packaging",
        "shipping",
        "supply"
    ],
    "sg:website":"www.moveshop.com",
    "wof:name":"Handle With Care Packaging Str",
    "wof:placetype":"venue"
},
  "geometry": {"coordinates":[-121.921627,37.37387],"type":"Point"}
}