{
  "type": "Feature",
  "properties": {
    "iso:country":"US",
    "sg:address":"175 Pegord Ave",
    "sg:city":"Dixon",
    "sg:classifiers":[
        {
            "category":"Shopping",
            "subcategory":"Bicycles & Sporting Goods",
            "type":"Retail Goods"
        }
    ],
    "sg:phone":"+1 707 678 4510",
    "sg:postcode":"95620",
    "sg:province":"CA",
    "wof:name":"J R Humphrey Co",
    "wof:placetype":"venue"
},
  "geometry": {"coordinates":[-121.830006,38.445437],"type":"Point"}
}