{
  "type": "Feature",
  "properties": {
    "addr:full":"38309 State Highway 299 E Burney CA 96013",
    "addr:housenumber":"38309",
    "addr:postcode":"96013",
    "addr:street":"State Highway 299 E",
    "iso:country":"US",
    "sg:address":"38309 State Highway 299 E",
    "sg:city":"Burney",
    "sg:classifiers":[
        {
            "category":"Building & Trades",
            "subcategory":"Landscaping Services",
            "type":"Services"
        }
    ],
    "sg:phone":"+1 530 335 2886",
    "sg:postcode":"96013",
    "sg:province":"CA",
    "sg:tags":[
        "tree"
    ],
    "wof:name":"White's Shearing",
    "wof:placetype":"venue"
},
  "geometry": {"coordinates":[-121.61056600000001,40.93478],"type":"Point"}
}