{
  "type": "Feature",
  "properties": {
    "addr:full":"3596 Orcutt Rd Santa Maria CA 93455",
    "addr:housenumber":"3596",
    "addr:postcode":"93455",
    "addr:street":"Orcutt Rd",
    "iso:country":"US",
    "sg:address":"3596 Orcutt Rd",
    "sg:city":"Santa Maria",
    "sg:classifiers":[
        {
            "category":"Retail",
            "subcategory":"Auto Repair",
            "type":"Services"
        }
    ],
    "sg:phone":"+1 805 934 3447",
    "sg:postcode":"93455",
    "sg:province":"CA",
    "sg:tags":[
        "repairing",
        "automobile"
    ],
    "wof:name":"Santa Maria Muffler Svc",
    "wof:placetype":"venue"
},
  "geometry": {"coordinates":[-120.436196,34.894582],"type":"Point"}
}