{
  "type": "Feature",
  "properties": {
    "addr:full":"2101 Webster St Oakland CA 94612",
    "addr:housenumber":"2101",
    "addr:postcode":"94612",
    "addr:street":"Webster St",
    "iso:country":"US",
    "sg:address":"2101 Webster St",
    "sg:city":"Oakland",
    "sg:classifiers":[
        {
            "category":"Professional",
            "subcategory":"Lawyer & Legal Services",
            "type":"Services"
        }
    ],
    "sg:phone":"+1 510 208 6600",
    "sg:postcode":"94612",
    "sg:province":"CA",
    "sg:website":"www.leonandleon.com",
    "wof:name":"Vogel-Flores-Sahagun Susan",
    "wof:placetype":"venue"
},
  "geometry": {"coordinates":[-122.26585300000001,37.810257],"type":"Point"}
}