{
  "type": "Feature",
  "properties": {
    "iso:country":"US",
    "sg:address":"1534 Eastman Ave",
    "sg:city":"Ventura",
    "sg:classifiers":[
        {
            "category":"Professional",
            "subcategory":"Research",
            "type":"Services"
        }
    ],
    "sg:phone":"+1 805 650 1642",
    "sg:postcode":"93003",
    "sg:province":"CA",
    "sg:tags":[
        "environmental",
        "ecological"
    ],
    "wof:name":"Atmospheric Analysis",
    "wof:placetype":"venue"
},
  "geometry": {"coordinates":[-119.230103,34.257631],"type":"Point"}
}