{
  "type": "Feature",
  "properties": {
    "iso:country":"US",
    "sg:address":"367 Elmhurst Pl",
    "sg:city":"Fullerton",
    "sg:classifiers":[
        {
            "category":"Mining & Drilling",
            "type":"Manufacturing & Wholesale Goods"
        }
    ],
    "sg:phone":"+1 949 551 4169",
    "sg:postcode":"92835",
    "sg:province":"CA",
    "sg:tags":[
        "company"
    ],
    "wof:name":"K C Assoc",
    "wof:placetype":"venue"
},
  "geometry": {"coordinates":[-117.917607,33.8942],"type":"Point"}
}