{
  "type": "Feature",
  "properties": {
    "addr:full":"4510 E Thousand Oaks Blvd Westlake Village CA 91362",
    "addr:housenumber":"4510",
    "addr:postcode":"91362",
    "addr:street":"E Thousand Oaks Blvd",
    "iso:country":"US",
    "sg:address":"4510 E Thousand Oaks Blvd",
    "sg:city":"Westlake Village",
    "sg:classifiers":[
        {
            "category":"Organizations",
            "subcategory":"Non-profit Organization",
            "type":"Services"
        }
    ],
    "sg:phone":"+1 805 494 4545",
    "sg:postcode":"91362",
    "sg:province":"CA",
    "sg:tags":[
        "fund",
        "counselor",
        "raising"
    ],
    "wof:name":"Cash 2 Charities",
    "wof:placetype":"venue"
},
  "geometry": {"coordinates":[-118.813165,34.157258],"type":"Point"}
}