{
  "type": "Feature",
  "properties": {
    "addr:full":"7901 Stoneridge Dr Pleasanton CA 94588",
    "addr:housenumber":"7901",
    "addr:postcode":"94588",
    "addr:street":"Stoneridge Dr",
    "iso:country":"US",
    "sg:address":"7901 Stoneridge Dr",
    "sg:city":"Pleasanton",
    "sg:classifiers":[
        {
            "category":"Professional",
            "subcategory":"Lawyer & Legal Services",
            "type":"Services"
        }
    ],
    "sg:phone":"+1 925 225 1025",
    "sg:postcode":"94588",
    "sg:province":"CA",
    "sg:tags":[
        "attorney",
        "practice",
        "plan"
    ],
    "sg:website":"http://www.reedscottlaw.com",
    "wof:name":"Reed, Scott Law Offices",
    "wof:placetype":"venue"
},
  "geometry": {"coordinates":[-121.92926799999999,37.689098],"type":"Point"}
}