{
  "type": "Feature",
  "properties": {
    "addr:full":"5000 Campus Dr Newport Beach CA 92660",
    "addr:housenumber":"5000",
    "addr:postcode":"92660",
    "addr:street":"Campus Dr",
    "iso:country":"US",
    "sg:address":"5000 Campus Dr",
    "sg:city":"Newport Beach",
    "sg:classifiers":[
        {
            "category":"Professional",
            "subcategory":"Lawyer & Legal Services",
            "type":"Services"
        }
    ],
    "sg:phone":"+1 949 863 9999",
    "sg:postcode":"92660",
    "sg:province":"CA",
    "sg:tags":[
        "divorce",
        "law",
        "family"
    ],
    "wof:name":"Broad of Legal Spclztn Lw Offcs of Albrt M Grhm Jr",
    "wof:placetype":"venue"
},
  "geometry": {"coordinates":[-117.85700199999999,33.668098],"type":"Point"}
}