{
  "type": "Feature",
  "properties": {
    "addr:full":"3300 Powell St Ste 103 Emeryville CA 94608",
    "addr:housenumber":"3300",
    "addr:postcode":"94608",
    "addr:street":"Powell St Ste 103",
    "iso:country":"US",
    "sg:address":"3300 Powell St Ste 103",
    "sg:city":"Emeryville",
    "sg:classifiers":[
        {
            "category":"Banks & Credit Unions",
            "subcategory":"Financial Services",
            "type":"Services"
        }
    ],
    "sg:phone":"+1 510 428 1158",
    "sg:postcode":"94608",
    "sg:province":"CA",
    "sg:tags":[
        "broker",
        "mortgage"
    ],
    "wof:name":"Northern California Funding Inc",
    "wof:placetype":"venue"
},
  "geometry": {"coordinates":[-122.285004,37.838001],"type":"Point"}
}