{
  "type": "Feature",
  "properties": {
    "iso:country":"US",
    "sg:address":"2523 Bowdoin Pl",
    "sg:city":"Costa Mesa",
    "sg:classifiers":[
        {
            "category":"Building & Trades",
            "subcategory":"Construction",
            "type":"Services"
        }
    ],
    "sg:phone":"+1 714 549 5771",
    "sg:postcode":"92626",
    "sg:province":"CA",
    "sg:tags":[
        "contractor"
    ],
    "wof:name":"Blue Rose Enterprises",
    "wof:placetype":"venue"
},
  "geometry": {"coordinates":[-117.913426,33.663712],"type":"Point"}
}