{
  "type": "Feature",
  "properties": {
    "iso:country":"US",
    "sg:address":"19990 Skywest Dr",
    "sg:city":"Hayward",
    "sg:classifiers":[
        {
            "category":"Education",
            "subcategory":"Special Training",
            "type":"Public Place"
        }
    ],
    "sg:phone":"+1 510 782 5311",
    "sg:postcode":"94541",
    "sg:province":"CA",
    "sg:tags":[
        "aircraft",
        "school"
    ],
    "sg:website":"www.americanflyers.net",
    "wof:name":"American Flyers",
    "wof:placetype":"venue"
},
  "geometry": {"coordinates":[-122.119342,37.662775],"type":"Point"}
}