{
  "type": "Feature",
  "properties": {
    "iso:country":"US",
    "sg:address":"1093 Triunfo Canyon Rd",
    "sg:city":"Westlake Village",
    "sg:classifiers":[
        {
            "category":"Banks & Credit Unions",
            "subcategory":"Bank",
            "type":"Services"
        }
    ],
    "sg:phone":"+1 805 496 7664",
    "sg:postcode":"91361",
    "sg:province":"CA",
    "sg:tags":[
        "depository",
        "banking"
    ],
    "wof:name":"Legal Dept",
    "wof:placetype":"venue"
},
  "geometry": {"coordinates":[-118.840108,34.150736],"type":"Point"}
}