{
  "type": "Feature",
  "properties": {
    "iso:country":"US",
    "sg:address":"6068 Warner Ave",
    "sg:city":"Huntington Beach",
    "sg:classifiers":[
        {
            "category":"Arena",
            "subcategory":"Sports Club",
            "type":"Entertainment"
        }
    ],
    "sg:postcode":"92647",
    "sg:province":"CA",
    "sg:tags":[
        "martial art"
    ],
    "sg:website":"www.kingsmma.com",
    "wof:name":"Rafael Cordeiro's FIght Center",
    "wof:placetype":"venue"
},
  "geometry": {"coordinates":[-118.02310300000001,33.715359],"type":"Point"}
}