{
  "type": "Feature",
  "properties": {
    "iso:country":"US",
    "sg:address":"15328 Orange Ave Ofc",
    "sg:city":"Paramount",
    "sg:classifiers":[
        {
            "category":"Real Estate",
            "subcategory":"Real Estate Services",
            "type":"Services"
        },
        {
            "category":"Real Estate",
            "subcategory":"Real Estate Operator",
            "type":"Services"
        }
    ],
    "sg:phone":"+1 562 630 0496",
    "sg:postcode":"90723",
    "sg:province":"CA",
    "sg:tags":[
        "vacancy",
        "apartment",
        "rental",
        "finder",
        "listing"
    ],
    "wof:name":"San Marcos Village Apartments",
    "wof:placetype":"venue"
},
  "geometry": {"coordinates":[-118.177002,33.8936],"type":"Point"}
}