{
  "type": "Feature",
  "properties": {
    "iso:country":"US",
    "sg:address":"1492 N Harbor Dr",
    "sg:city":"San Diego",
    "sg:classifiers":[
        {
            "category":"Museum",
            "type":"Entertainment"
        }
    ],
    "sg:phone":"+1 619 234 9153",
    "sg:postcode":"92101",
    "sg:province":"CA",
    "wof:name":"Star of India",
    "wof:placetype":"venue"
},
  "geometry": {"coordinates":[-117.179925,32.727649],"type":"Point"}
}