{
  "type": "Feature",
  "properties": {
    "iso:country":"US",
    "sg:address":"5140 W 104th St",
    "sg:city":"Inglewood",
    "sg:classifiers":[
        {
            "category":"Freight",
            "type":"Transportation"
        }
    ],
    "sg:phone":"+1 310 649 2127",
    "sg:postcode":"90304",
    "sg:province":"CA",
    "sg:tags":[
        "operator",
        "trucking"
    ],
    "wof:name":"Straight Line Transportation",
    "wof:placetype":"venue"
},
  "geometry": {"coordinates":[-118.369896,33.941729],"type":"Point"}
}