{
  "type": "Feature",
  "properties": {
    "iso:country":"US",
    "sg:address":"1718 N Thorne Ave",
    "sg:city":"Fresno",
    "sg:classifiers":[
        {
            "category":"Building & Trades",
            "subcategory":"Construction",
            "type":"Services"
        }
    ],
    "sg:phone":"+1 559 237 2631",
    "sg:postcode":"93704",
    "sg:province":"CA",
    "sg:tags":[
        "remodeling",
        "contractor"
    ],
    "wof:name":"Smith & Son",
    "wof:placetype":"venue"
},
  "geometry": {"coordinates":[-119.813041,36.765582],"type":"Point"}
}