{
  "type": "Feature",
  "properties": {
    "iso:country":"US",
    "sg:address":"26504 Bouquet Canyon Rd",
    "sg:city":"Santa Clarita",
    "sg:classifiers":[
        {
            "category":"Professional",
            "subcategory":"Printing & Photocopies",
            "type":"Services"
        }
    ],
    "sg:phone":"+1 661 263 3110",
    "sg:postcode":"91350",
    "sg:province":"CA",
    "sg:website":"www.postnet.com/ca241",
    "wof:name":"PostNet",
    "wof:placetype":"venue"
},
  "geometry": {"coordinates":[-118.536402,34.42799],"type":"Point"}
}