{
  "type": "Feature",
  "properties": {
    "iso:country":"US",
    "sg:address":"8612 Van Nuys Blvd",
    "sg:city":"Panorama City",
    "sg:classifiers":[
        {
            "category":"Shopping",
            "subcategory":"Clothing, Apparel, & Fashions",
            "type":"Retail Goods"
        }
    ],
    "sg:phone":"+1 818 893 2202",
    "sg:postcode":"91402",
    "sg:province":"CA",
    "wof:name":"Vicky Fashions",
    "wof:placetype":"venue"
},
  "geometry": {"coordinates":[-118.449015,34.225582],"type":"Point"}
}