{
  "type": "Feature",
  "properties": {
    "addr:full":"5 Reed Rd Oakdale CA 95361",
    "addr:housenumber":"5",
    "addr:postcode":"95361",
    "addr:street":"Reed Rd",
    "iso:country":"US",
    "sg:address":"5 Reed Rd",
    "sg:city":"Oakdale",
    "sg:classifiers":[
        {
            "category":"Building & Trades",
            "subcategory":"Construction",
            "type":"Services"
        }
    ],
    "sg:phone":"+1 209 848 9515",
    "sg:postcode":"95361",
    "sg:province":"CA",
    "sg:tags":[
        "roofing",
        "contractor"
    ],
    "wof:name":"Chester Smith Roofing",
    "wof:placetype":"venue"
},
  "geometry": {"coordinates":[-120.87415300000001,37.758013],"type":"Point"}
}