{
  "type": "Feature",
  "properties": {
    "addr:full":"23 Oak Rd Orinda CA 94563",
    "addr:housenumber":"23",
    "addr:postcode":"94563",
    "addr:street":"Oak Rd",
    "iso:country":"US",
    "sg:address":"23 Oak Rd",
    "sg:city":"Orinda",
    "sg:classifiers":[
        {
            "category":"Building & Trades",
            "subcategory":"Construction",
            "type":"Services"
        }
    ],
    "sg:phone":"+1 925 253 4833",
    "sg:postcode":"94563",
    "sg:province":"CA",
    "sg:tags":[
        "specializing",
        "residence",
        "general",
        "remodeling",
        "contractor"
    ],
    "wof:name":"Clark Construction Co",
    "wof:placetype":"venue"
},
  "geometry": {"coordinates":[-122.18061400000001,37.872813],"type":"Point"}
}