{
  "type": "Feature",
  "properties": {
    "addr:full":"1017 San Julian Street Los Angeles CA 90015",
    "addr:housenumber":"1017",
    "addr:postcode":"90015",
    "addr:street":"San Julian Street",
    "iso:country":"US",
    "sg:address":"1017 San Julian Street",
    "sg:city":"Los Angeles",
    "sg:classifiers":[
        {
            "category":"Shopping",
            "subcategory":"Clothing, Apparel, & Fashions",
            "type":"Retail Goods"
        }
    ],
    "sg:phone":"+1 213 748 5045",
    "sg:postcode":"90015",
    "sg:province":"CA",
    "sg:tags":[
        "children's",
        "clothing"
    ],
    "wof:name":"Nina Piu",
    "wof:placetype":"venue"
},
  "geometry": {"coordinates":[-118.252765,34.036103],"type":"Point"}
}