{
  "type": "Feature",
  "properties": {
    "addr:full":"825 Columbia St Brea CA 92821",
    "addr:housenumber":"825",
    "addr:postcode":"92821",
    "addr:street":"Columbia",
    "iso:country":"US",
    "sg:address":"825 Columbia St",
    "sg:city":"Brea",
    "sg:classifiers":[
        {
            "category":"Manufacturing",
            "subcategory":"Metals",
            "type":"Manufacturing & Wholesale Goods"
        }
    ],
    "sg:phone":"+1 714 256 4700",
    "sg:postcode":"92821",
    "sg:province":"CA",
    "sg:tags":[
        "mfg",
        "metalwork",
        "sheet",
        "structural"
    ],
    "wof:name":"Metal Cabinet & Fixture",
    "wof:placetype":"venue"
},
  "geometry": {"coordinates":[-117.909282,33.930398],"type":"Point"}
}