{
  "type": "Feature",
  "properties": {
    "iso:country":"US",
    "sg:address":"1815 Purdue Ave",
    "sg:city":"Los Angeles",
    "sg:classifiers":[
        {
            "category":"Building & Trades",
            "subcategory":"Construction",
            "type":"Services"
        }
    ],
    "sg:phone":"+1 310 442 0775",
    "sg:postcode":"90025",
    "sg:province":"CA",
    "sg:tags":[
        "waterproofing",
        "contractor"
    ],
    "wof:name":"Advanced Deco Deck",
    "wof:placetype":"venue"
},
  "geometry": {"coordinates":[-118.447075,34.041506],"type":"Point"}
}