{
  "type": "Feature",
  "properties": {
    "iso:country":"US",
    "sg:address":"San Carlos Street and Fifth Avenue",
    "sg:city":"Carmel",
    "sg:classifiers":[
        {
            "category":"Travel",
            "subcategory":"Hotels & Motels",
            "type":"Entertainment"
        }
    ],
    "sg:phone":"+1 831 624 1255",
    "sg:postcode":"93921",
    "sg:province":"CA",
    "sg:website":"www.carmelbestwestern.com/",
    "wof:name":"Best Western Carmel's Townhouse Lodge",
    "wof:placetype":"venue"
},
  "geometry": {"coordinates":[-121.92182099999999,36.556902],"type":"Point"}
}