{
  "type": "Feature",
  "properties": {
    "iso:country":"US",
    "sg:address":"3851 Rosecrans Street",
    "sg:city":"San Diego",
    "sg:classifiers":[
        {
            "category":"Restaurant",
            "type":"Food & Drink"
        }
    ],
    "sg:phone":"+1 619 297 6460",
    "sg:postcode":"92110",
    "sg:province":"CA",
    "wof:name":"Jaspar's Cafe",
    "wof:placetype":"venue"
},
  "geometry": {"coordinates":[-117.202405,32.754198],"type":"Point"}
}