{
  "type": "Feature",
  "properties": {
    "iso:country":"US",
    "sg:address":"4067 18th Street",
    "sg:city":"San Francisco",
    "sg:classifiers":[
        {
            "category":"Bars & Pubs",
            "subcategory":"Gay Bar",
            "type":"Food & Drink"
        }
    ],
    "sg:phone":"+1 415 861 4186",
    "sg:postcode":"94114",
    "sg:province":"CA",
    "wof:name":"Midnight Sun",
    "wof:placetype":"venue"
},
  "geometry": {"coordinates":[-122.433998,37.760799],"type":"Point"}
}