{
  "type": "Feature",
  "properties": {
    "addr:full":"2211 N Wilson Way Stockton CA 95205",
    "addr:housenumber":"2211",
    "addr:postcode":"95205",
    "addr:street":"N Wilson Way",
    "iso:country":"US",
    "sg:address":"2211 N Wilson Way",
    "sg:city":"Stockton",
    "sg:classifiers":[
        {
            "category":"Restaurant",
            "type":"Food & Drink"
        }
    ],
    "sg:phone":"+1 209 463 4478",
    "sg:postcode":"95205",
    "sg:province":"CA",
    "wof:name":"Far East Restaurant",
    "wof:placetype":"venue"
},
  "geometry": {"coordinates":[-121.274029,37.978267],"type":"Point"}
}