{
  "type": "Feature",
  "properties": {
    "addr:full":"700 Roth Rd French Camp CA 95231",
    "addr:housenumber":"700",
    "addr:postcode":"95231",
    "addr:street":"Roth Rd",
    "iso:country":"US",
    "sg:address":"700 Roth Rd",
    "sg:city":"French Camp",
    "sg:classifiers":[
        {
            "category":"Wholesale",
            "subcategory":"Durable Goods & Equipment",
            "type":"Manufacturing & Wholesale Goods"
        }
    ],
    "sg:phone":"+1 209 547 8601",
    "sg:postcode":"95231",
    "sg:province":"CA",
    "wof:name":"US Federal Supply Depo",
    "wof:placetype":"venue"
},
  "geometry": {"coordinates":[-121.27082799999999,37.855601],"type":"Point"}
}