{
  "type": "Feature",
  "properties": {
    "addr:full":"1120 Sandhill Ave Carson CA 90746",
    "addr:housenumber":"1120",
    "addr:postcode":"90746",
    "addr:street":"Sandhill Ave",
    "iso:country":"US",
    "sg:address":"1120 Sandhill Ave",
    "sg:city":"Carson",
    "sg:classifiers":[
        {
            "category":"Manufacturing",
            "subcategory":"Paper Products",
            "type":"Manufacturing & Wholesale Goods"
        }
    ],
    "sg:phone":"+1 310 631 6170",
    "sg:postcode":"90746",
    "sg:province":"CA",
    "sg:tags":[
        "packaging",
        "bag",
        "material",
        "mfg"
    ],
    "wof:name":"Pacquet Oneida Inc",
    "wof:placetype":"venue"
},
  "geometry": {"coordinates":[-118.252098,33.878274],"type":"Point"}
}