{
  "type": "Feature",
  "properties": {
    "iso:country":"US",
    "sg:address":"1328 Main St",
    "sg:city":"Delano",
    "sg:classifiers":[
        {
            "category":"Personal",
            "subcategory":"Beauty Salon",
            "type":"Services"
        }
    ],
    "sg:phone":"+1 661 725 5181",
    "sg:postcode":"93215",
    "sg:province":"CA",
    "wof:name":"Reychells Salon",
    "wof:placetype":"venue"
},
  "geometry": {"coordinates":[-119.246644,35.77334],"type":"Point"}
}