{
  "type": "Feature",
  "properties": {
    "addr:full":"965 Mission St San Francisco CA 94103",
    "addr:housenumber":"965",
    "addr:postcode":"94103",
    "addr:street":"Mission St",
    "iso:country":"US",
    "sg:address":"965 Mission St",
    "sg:city":"San Francisco",
    "sg:classifiers":[
        {
            "category":"Social Services",
            "type":"Services"
        }
    ],
    "sg:phone":"+1 415 977 1980",
    "sg:postcode":"94103",
    "sg:province":"CA",
    "sg:tags":[
        "organization",
        "welfare"
    ],
    "sg:website":"www.cywd.org",
    "wof:name":"Center For Young Women's Dev",
    "wof:placetype":"venue"
},
  "geometry": {"coordinates":[-122.408117,37.781456],"type":"Point"}
}