{
  "type": "Feature",
  "properties": {
    "iso:country":"US",
    "sg:address":"12302 Harbor Blvd",
    "sg:city":"Garden Grove",
    "sg:classifiers":[
        {
            "category":"Ice Cream",
            "type":"Food & Drink"
        }
    ],
    "sg:phone":"+1 714 750 1076",
    "sg:postcode":"92840",
    "sg:province":"CA",
    "sg:tags":[
        "frozen",
        "yogurt"
    ],
    "sg:website":"www.joesice.com",
    "wof:name":"Joe's Italian Ice",
    "wof:placetype":"venue"
},
  "geometry": {"coordinates":[-117.915001,33.784199],"type":"Point"}
}