{
  "type": "Feature",
  "properties": {
    "addr:full":"251 Post St Ste 620 San Francisco CA 94108",
    "addr:housenumber":"251",
    "addr:postcode":"94108",
    "addr:street":"Post St Ste 620",
    "iso:country":"US",
    "sg:address":"251 Post St Ste 620",
    "sg:city":"San Francisco",
    "sg:classifiers":[
        {
            "category":"Arts & Performance",
            "subcategory":"Art Gallery",
            "type":"Entertainment"
        },
        {
            "category":"Real Estate",
            "subcategory":"Architect",
            "type":"Services"
        }
    ],
    "sg:phone":"+1 415 989 6400",
    "sg:postcode":"94108",
    "sg:province":"CA",
    "sg:website":"www.HilliardArchitects.com",
    "wof:name":"Hilliard Architects & Gallery",
    "wof:placetype":"venue"
},
  "geometry": {"coordinates":[-122.40604,37.78833],"type":"Point"}
}