{
  "type": "Feature",
  "properties": {
    "addr:full":"6124 Corbin Ave Tarzana CA 91356",
    "addr:housenumber":"6124",
    "addr:postcode":"91356",
    "addr:street":"Corbin Ave",
    "iso:country":"US",
    "sg:address":"6124 Corbin Ave",
    "sg:city":"Tarzana",
    "sg:classifiers":[
        {
            "category":"Wholesale",
            "subcategory":"Apparel",
            "type":"Manufacturing & Wholesale Goods"
        }
    ],
    "sg:phone":"+1 818 996 2740",
    "sg:postcode":"91356",
    "sg:province":"CA",
    "sg:tags":[
        "accessory"
    ],
    "sg:website":"www.hiddenheart.com",
    "wof:name":"Hidden Heart",
    "wof:placetype":"venue"
},
  "geometry": {"coordinates":[-118.562146,34.183621],"type":"Point"}
}