{
  "type": "Feature",
  "properties": {
    "addr:full":"4679 Telegraph Ave Oakland CA 94609",
    "addr:housenumber":"4679",
    "addr:postcode":"94609",
    "addr:street":"Telegraph Ave",
    "iso:country":"US",
    "sg:address":"4679 Telegraph Ave",
    "sg:city":"Oakland",
    "sg:classifiers":[
        {
            "category":"Personal",
            "subcategory":"Beauty Salon",
            "type":"Services"
        }
    ],
    "sg:phone":"+1 510 428 2032",
    "sg:postcode":"94609",
    "sg:province":"CA",
    "wof:name":"Something Unique Hair Design",
    "wof:placetype":"venue"
},
  "geometry": {"coordinates":[-122.263347,37.833835],"type":"Point"}
}