{
  "type": "Feature",
  "properties": {
    "iso:country":"US",
    "sg:address":"5265 State St",
    "sg:city":"Montclair",
    "sg:classifiers":[
        {
            "category":"Building & Trades",
            "subcategory":"Construction",
            "type":"Services"
        }
    ],
    "sg:phone":"+1 909 591 4208",
    "sg:postcode":"91763",
    "sg:province":"CA",
    "sg:tags":[
        "contractor"
    ],
    "wof:name":"Gold Star Roofing Co",
    "wof:placetype":"venue"
},
  "geometry": {"coordinates":[-117.69057,34.05972],"type":"Point"}
}