{
  "type": "Feature",
  "properties": {
    "addr:full":"13373 Perris Blvd Moreno Valley CA 92553",
    "addr:housenumber":"13373",
    "addr:postcode":"92553",
    "addr:street":"Perris Blvd",
    "iso:country":"US",
    "sg:address":"13373 Perris Blvd",
    "sg:city":"Moreno Valley",
    "sg:classifiers":[
        {
            "category":"Organizations",
            "subcategory":"Religious Organization",
            "type":"Services"
        }
    ],
    "sg:phone":"+1 951 486 9245",
    "sg:postcode":"92553",
    "sg:province":"CA",
    "sg:tags":[
        "church"
    ],
    "wof:name":"Spirit Dominion Praise",
    "wof:placetype":"venue"
},
  "geometry": {"coordinates":[-117.226353,33.926353],"type":"Point"}
}