{
  "type": "Feature",
  "properties": {
    "iso:country":"US",
    "sg:address":"1290 B St Ste 307",
    "sg:city":"Hayward",
    "sg:classifiers":[
        {
            "category":"Professional",
            "subcategory":"Lawyer & Legal Services",
            "type":"Services"
        }
    ],
    "sg:phone":"+1 510 582 9090",
    "sg:postcode":"94541",
    "sg:province":"CA",
    "wof:name":"Law Offices of Louis J Goodman",
    "wof:placetype":"venue"
},
  "geometry": {"coordinates":[-122.078003,37.676399],"type":"Point"}
}