{
  "type": "Feature",
  "properties": {
    "addr:full":"8681 Blue Lake Dr San Diego CA 92119",
    "addr:housenumber":"8681",
    "addr:postcode":"92119",
    "addr:street":"Blue Lake Dr",
    "iso:country":"US",
    "sg:address":"8681 Blue Lake Dr",
    "sg:city":"San Diego",
    "sg:classifiers":[
        {
            "category":"Building & Trades",
            "subcategory":"Construction",
            "type":"Services"
        }
    ],
    "sg:phone":"+1 619 463 3393",
    "sg:postcode":"92119",
    "sg:province":"CA",
    "sg:tags":[
        "contractor"
    ],
    "wof:name":"Philbrook Construction",
    "wof:placetype":"venue"
},
  "geometry": {"coordinates":[-117.01106299999999,32.791663],"type":"Point"}
}