{
  "type": "Feature",
  "properties": {
    "addr:full":"3334 N Fruit Ave Fresno CA 93705",
    "addr:housenumber":"3334",
    "addr:postcode":"93705",
    "addr:street":"N Fruit Ave",
    "iso:country":"US",
    "sg:address":"3334 N Fruit Ave",
    "sg:city":"Fresno",
    "sg:classifiers":[
        {
            "category":"Real Estate",
            "subcategory":"Real Estate Operator",
            "type":"Services"
        }
    ],
    "sg:phone":"+1 559 225 7642",
    "sg:postcode":"93705",
    "sg:province":"CA",
    "sg:tags":[
        "apartment"
    ],
    "wof:name":"North Fruit Place Apartments",
    "wof:placetype":"venue"
},
  "geometry": {"coordinates":[-119.81748899999999,36.780857],"type":"Point"}
}