{
  "type": "Feature",
  "properties": {
    "iso:country":"US",
    "sg:address":"1973 E Cromwell Ave",
    "sg:city":"Fresno",
    "sg:classifiers":[
        {
            "category":"Building & Trades",
            "subcategory":"Landscaping Services",
            "type":"Services"
        }
    ],
    "sg:phone":"+1 559 288 7270",
    "sg:postcode":"93720",
    "sg:province":"CA",
    "sg:tags":[
        "tree"
    ],
    "wof:name":"R & J Tree Svc",
    "wof:placetype":"venue"
},
  "geometry": {"coordinates":[-119.747962,36.846874],"type":"Point"}
}