{
  "type": "Feature",
  "properties": {
    "addr:full":"2750 Clement St San Francisco CA 94121",
    "addr:housenumber":"2750",
    "addr:postcode":"94121",
    "addr:street":"Clement St",
    "iso:country":"US",
    "sg:address":"2750 Clement St",
    "sg:city":"San Francisco",
    "sg:classifiers":[
        {
            "category":"Home & Garden",
            "subcategory":"Building Materials",
            "type":"Retail Goods"
        }
    ],
    "sg:phone":"+1 415 320 8050",
    "sg:postcode":"94121",
    "sg:province":"CA",
    "sg:tags":[
        "glass",
        "window",
        "plate"
    ],
    "wof:name":"Dougherty Glass",
    "wof:placetype":"venue"
},
  "geometry": {"coordinates":[-122.48872900000001,37.781924],"type":"Point"}
}