{
  "type": "Feature",
  "properties": {
    "iso:country":"US",
    "sg:address":"43141 Bus Center Pkwy",
    "sg:city":"Lancaster",
    "sg:classifiers":[
        {
            "category":"Recreation",
            "type":"Entertainment"
        }
    ],
    "sg:phone":"+1 661 942 4337",
    "sg:postcode":"93535",
    "sg:province":"CA",
    "sg:tags":[
        "amusement"
    ],
    "sg:website":"www.avcheer.com",
    "wof:name":"A V Cheer & Dance Dynamics",
    "wof:placetype":"venue"
},
  "geometry": {"coordinates":[-118.128833,34.666382],"type":"Point"}
}