{
  "type": "Feature",
  "properties": {
    "iso:country":"US",
    "sg:address":"909 Palm Ave",
    "sg:city":"West Hollywood",
    "sg:classifiers":[
        {
            "category":"Real Estate",
            "subcategory":"Real Estate Agent",
            "type":"Services"
        }
    ],
    "sg:phone":"+1 310 659 6706",
    "sg:postcode":"90069",
    "sg:province":"CA",
    "wof:name":"MZL Properties",
    "wof:placetype":"venue"
},
  "geometry": {"coordinates":[-118.382966,34.087624],"type":"Point"}
}