{
  "type": "Feature",
  "properties": {
    "iso:country":"US",
    "sg:address":"322 Culver Blvd",
    "sg:city":"Playa Del Rey",
    "sg:classifiers":[
        {
            "category":"Professional",
            "subcategory":"Advertising",
            "type":"Services"
        }
    ],
    "sg:phone":"+1 310 822 7855",
    "sg:postcode":"90293",
    "sg:province":"CA",
    "sg:tags":[
        "counselor"
    ],
    "wof:name":"1124 Design",
    "wof:placetype":"venue"
},
  "geometry": {"coordinates":[-118.44746,33.959373],"type":"Point"}
}