{
  "type": "Feature",
  "properties": {
    "addr:full":"1725 E Hilltop Ave Orange CA 92865",
    "addr:housenumber":"1725",
    "addr:postcode":"92865",
    "addr:street":"E Hilltop Ave",
    "iso:country":"US",
    "sg:address":"1725 E Hilltop Ave",
    "sg:city":"Orange",
    "sg:classifiers":[
        {
            "category":"Autos & Motor Vehicles",
            "subcategory":"Auto Supplies",
            "type":"Retail Goods"
        }
    ],
    "sg:phone":"+1 714 637 0954",
    "sg:postcode":"92865",
    "sg:province":"CA",
    "wof:name":"Muroc Carb & Equipment",
    "wof:placetype":"venue"
},
  "geometry": {"coordinates":[-117.83520900000001,33.84018],"type":"Point"}
}