{
  "type": "Feature",
  "properties": {
    "addr:full":"307 Vineyard Blvd Morgan Hill CA 95037",
    "addr:housenumber":"307",
    "addr:postcode":"95037",
    "addr:street":"Vineyard Blvd",
    "iso:country":"US",
    "sg:address":"307 Vineyard Blvd",
    "sg:city":"Morgan Hill",
    "sg:classifiers":[
        {
            "category":"Banks & Credit Unions",
            "subcategory":"Bank",
            "type":"Services"
        }
    ],
    "sg:phone":"+1 408 776 3404",
    "sg:postcode":"95037",
    "sg:province":"CA",
    "sg:tags":[
        "cashing",
        "check"
    ],
    "wof:name":"Check Into Cash",
    "wof:placetype":"venue"
},
  "geometry": {"coordinates":[-121.64134799999999,37.109776],"type":"Point"}
}