{
  "type": "Feature",
  "properties": {
    "iso:country":"US",
    "sg:address":"4419 Coldwater Canyon Ave Ste I",
    "sg:city":"Studio City",
    "sg:classifiers":[
        {
            "category":"Professional",
            "subcategory":"Lawyer & Legal Services",
            "type":"Services"
        }
    ],
    "sg:phone":"+1 818 781 0166",
    "sg:postcode":"91604",
    "sg:province":"CA",
    "wof:name":"Melodys S Hannes Law Offices of",
    "wof:placetype":"venue"
},
  "geometry": {"coordinates":[-118.414001,34.150902],"type":"Point"}
}