{
  "type": "Feature",
  "properties": {
    "iso:country":"US",
    "sg:address":"16760 Oak View Cir",
    "sg:city":"Morgan Hill",
    "sg:classifiers":[
        {
            "category":"Professional",
            "subcategory":"Engineering",
            "type":"Services"
        }
    ],
    "sg:phone":"+1 408 779 7901",
    "sg:postcode":"95037",
    "sg:province":"CA",
    "sg:tags":[
        "engineer"
    ],
    "wof:name":"Hans R Mulberg Inc",
    "wof:placetype":"venue"
},
  "geometry": {"coordinates":[-121.594954,37.142708],"type":"Point"}
}