{
  "type": "Feature",
  "properties": {
    "addr:full":"14867 Pomerado Rd Poway CA 92064",
    "addr:housenumber":"14867",
    "addr:postcode":"ca 92064",
    "addr:street":"Pomerado Rd",
    "iso:country":"US",
    "sg:address":"14867 Pomerado Rd",
    "sg:city":"Poway",
    "sg:classifiers":[
        {
            "category":"Utilities",
            "subcategory":"Mobile Phone",
            "type":"Services"
        }
    ],
    "sg:phone":"+1 858 413 1420",
    "sg:postcode":"92064",
    "sg:province":"CA",
    "sg:tags":[
        "telephone",
        "cellular"
    ],
    "wof:name":"Red Point Wireless",
    "wof:placetype":"venue"
},
  "geometry": {"coordinates":[-117.062241,32.981861],"type":"Point"}
}