{
  "type": "Feature",
  "properties": {
    "iso:country":"US",
    "sg:address":"545 W Hacienda Ave",
    "sg:city":"Campbell",
    "sg:classifiers":[
        {
            "category":"Shopping",
            "subcategory":"Clothing, Apparel, & Fashions",
            "type":"Retail Goods"
        }
    ],
    "sg:phone":"+1 408 378 7020",
    "sg:postcode":"95008",
    "sg:province":"CA",
    "wof:name":"Lulu Belle",
    "wof:placetype":"venue"
},
  "geometry": {"coordinates":[-121.958479,37.269216],"type":"Point"}
}