{
  "type": "Feature",
  "properties": {
    "addr:full":"7060 Sepulveda Blvd Van Nuys CA 91405",
    "addr:housenumber":"7060",
    "addr:postcode":"91405",
    "addr:street":"Sepulveda Blvd",
    "iso:country":"US",
    "sg:address":"7060 Sepulveda Blvd",
    "sg:city":"Van Nuys",
    "sg:classifiers":[
        {
            "category":"Banks & Credit Unions",
            "subcategory":"Bank",
            "type":"Services"
        }
    ],
    "sg:phone":"+1 818 997 4732",
    "sg:postcode":"91405",
    "sg:province":"CA",
    "sg:tags":[
        "national",
        "commercial"
    ],
    "wof:name":"Bank Of America",
    "wof:placetype":"venue"
},
  "geometry": {"coordinates":[-118.466116,34.199007],"type":"Point"}
}