{
  "type": "Feature",
  "properties": {
    "addr:full":"154 Capp St San Francisco CA 94110",
    "addr:housenumber":"154",
    "addr:postcode":"94110",
    "addr:street":"Capp St",
    "iso:country":"US",
    "sg:address":"154 Capp St",
    "sg:city":"San Francisco",
    "sg:classifiers":[
        {
            "category":"Manufacturing",
            "subcategory":"Apparel",
            "type":"Manufacturing & Wholesale Goods"
        }
    ],
    "sg:phone":"+1 415 558 8169",
    "sg:postcode":"94110",
    "sg:province":"CA",
    "sg:tags":[
        "sewing",
        "contractor"
    ],
    "wof:name":"Sau Ming Sewing",
    "wof:placetype":"venue"
},
  "geometry": {"coordinates":[-122.41868700000001,37.764373],"type":"Point"}
}