{
  "type": "Feature",
  "properties": {
    "addr:full":"1766 Miramonte Avenue Mountain View CA 94040",
    "addr:housenumber":"1766",
    "addr:postcode":"94040",
    "addr:street":"Miramonte Avenue",
    "iso:country":"US",
    "sg:address":"1766 Miramonte Avenue",
    "sg:city":"Mountain View",
    "sg:classifiers":[
        {
            "category":"Retail",
            "subcategory":"Veterinary Services",
            "type":"Services"
        }
    ],
    "sg:phone":"+1 650 962 8338",
    "sg:postcode":"94040",
    "sg:province":"CA",
    "sg:tags":[
        "veterinarian"
    ],
    "sg:website":"www.miramontevet.com",
    "wof:name":"Taylor Kenton DVM",
    "wof:placetype":"venue"
},
  "geometry": {"coordinates":[-122.08721300000001,37.372207],"type":"Point"}
}