{
  "type": "Feature",
  "properties": {
    "addr:full":"5737 Bertrand Ave Encino CA 91316",
    "addr:housenumber":"5737",
    "addr:postcode":"91316",
    "addr:street":"Bertrand Ave",
    "iso:country":"US",
    "sg:address":"5737 Bertrand Ave",
    "sg:city":"Encino",
    "sg:classifiers":[
        {
            "category":"Building & Trades",
            "subcategory":"Construction",
            "type":"Services"
        }
    ],
    "sg:phone":"+1 818 774 1008",
    "sg:postcode":"91316",
    "sg:province":"CA",
    "sg:tags":[
        "contractor"
    ],
    "wof:name":"Bernard & Assoc Construction",
    "wof:placetype":"venue"
},
  "geometry": {"coordinates":[-118.52545499999999,34.175444],"type":"Point"}
}