{
  "type": "Feature",
  "properties": {
    "addr:full":"7930 Normal Ave La Mesa CA 91941",
    "addr:housenumber":"7930",
    "addr:postcode":"91941",
    "addr:street":"Normal Ave",
    "iso:country":"US",
    "sg:address":"7930 Normal Ave",
    "sg:city":"La Mesa",
    "sg:classifiers":[
        {
            "category":"Insurance",
            "subcategory":"Insurance Agent",
            "type":"Services"
        }
    ],
    "sg:phone":"+1 619 460 8595",
    "sg:postcode":"91941",
    "sg:province":"CA",
    "wof:name":"Ed Kinnaman Realty",
    "wof:placetype":"venue"
},
  "geometry": {"coordinates":[-117.027053,32.76015],"type":"Point"}
}