{
  "type": "Feature",
  "properties": {
    "iso:country":"US",
    "sg:address":"1480 S Harbor Blvd",
    "sg:city":"Fullerton",
    "sg:classifiers":[
        {
            "category":"Government",
            "subcategory":"Office",
            "type":"Public Place"
        }
    ],
    "sg:phone":"+1 714 871 8886",
    "sg:postcode":"92832",
    "sg:province":"CA",
    "sg:tags":[
        "program",
        "administrative"
    ],
    "wof:name":"Harbor Mesa Medical",
    "wof:placetype":"venue"
},
  "geometry": {"coordinates":[-117.924215,33.856146],"type":"Point"}
}