{
  "type": "Feature",
  "properties": {
    "iso:country":"US",
    "sg:address":"1064 Elm St",
    "sg:city":"San Jose",
    "sg:classifiers":[
        {
            "category":"Home & Garden",
            "subcategory":"Building Materials",
            "type":"Retail Goods"
        }
    ],
    "sg:phone":"+1 408 984 7095",
    "sg:postcode":"95126",
    "sg:province":"CA",
    "sg:tags":[
        "windows"
    ],
    "wof:name":"A & B Doors Inc",
    "wof:placetype":"venue"
},
  "geometry": {"coordinates":[-121.92389,37.34614],"type":"Point"}
}