{
  "type": "Feature",
  "properties": {
    "iso:country":"US",
    "sg:address":"16792 Rd 15",
    "sg:city":"Madera",
    "sg:classifiers":[
        {
            "category":"Farming",
            "subcategory":"Dairy Farm",
            "type":"Manufacturing & Wholesale Goods"
        }
    ],
    "sg:phone":"+1 559 674 0617",
    "sg:postcode":"93637",
    "sg:province":"CA",
    "wof:name":"Costa View Farms",
    "wof:placetype":"venue"
},
  "geometry": {"coordinates":[-120.27425599999999,36.996426],"type":"Point"}
}