{
  "type": "Feature",
  "properties": {
    "addr:full":"1809 Verdugo Blvd Glendale CA 91208",
    "addr:housenumber":"1809",
    "addr:postcode":"91208",
    "addr:street":"Verdugo Blvd",
    "iso:country":"US",
    "sg:address":"1809 Verdugo Blvd",
    "sg:city":"Glendale",
    "sg:classifiers":[
        {
            "category":"Community Center",
            "type":"Public Place"
        }
    ],
    "sg:phone":"+1 866 867 0393",
    "sg:postcode":"91208",
    "sg:province":"CA",
    "sg:tags":[
        "medical"
    ],
    "wof:name":"Rapid Screenings",
    "wof:placetype":"venue"
},
  "geometry": {"coordinates":[-118.216167,34.205904],"type":"Point"}
}