{
  "type": "Feature",
  "properties": {
    "iso:country":"US",
    "sg:address":"11923 Cedar Ave",
    "sg:city":"Bloomington",
    "sg:classifiers":[
        {
            "category":"Autos & Motor Vehicles",
            "subcategory":"Automobile Sales",
            "type":"Retail Goods"
        }
    ],
    "sg:phone":"+1 951 274 0810",
    "sg:postcode":"92316",
    "sg:province":"CA",
    "sg:tags":[
        "car",
        "dealer"
    ],
    "wof:name":"J J Enterprises",
    "wof:placetype":"venue"
},
  "geometry": {"coordinates":[-117.39599,34.03748],"type":"Point"}
}