{
  "type": "Feature",
  "properties": {
    "addr:full":"7601 Laurel Canyon Blvd North Hollywood CA 91605",
    "addr:housenumber":"7601",
    "addr:postcode":"91605",
    "addr:street":"Laurel Canyon Blvd",
    "iso:country":"US",
    "sg:address":"7601 Laurel Canyon Blvd",
    "sg:city":"North Hollywood",
    "sg:classifiers":[
        {
            "category":"Autos & Motor Vehicles",
            "subcategory":"Automobile Sales",
            "type":"Retail Goods"
        }
    ],
    "sg:phone":"+1 818 503 9043",
    "sg:postcode":"91605",
    "sg:province":"CA",
    "sg:tags":[
        "automotive"
    ],
    "sg:website":"www.autozone.com",
    "wof:name":"AutoZone",
    "wof:placetype":"venue"
},
  "geometry": {"coordinates":[-118.397003,34.208599],"type":"Point"}
}