{
  "type": "Feature",
  "properties": {
    "iso:country":"US",
    "sg:address":"14120 Alondra Blvd",
    "sg:city":"Santa Fe Springs",
    "sg:classifiers":[
        {
            "category":"Professional",
            "subcategory":"Detective & Security Services",
            "type":"Services"
        }
    ],
    "sg:phone":"+1 562 229 0100",
    "sg:postcode":"90670",
    "sg:province":"CA",
    "sg:tags":[
        "ind",
        "equipment",
        "video",
        "system"
    ],
    "wof:name":"Vutek",
    "wof:placetype":"venue"
},
  "geometry": {"coordinates":[-118.031385,33.887921],"type":"Point"}
}