{
  "type": "Feature",
  "properties": {
    "iso:country":"US",
    "sg:address":"414 Colusa Ave",
    "sg:city":"El Cerrito",
    "sg:classifiers":[
        {
            "category":"Professional",
            "subcategory":"Computer Services",
            "type":"Services"
        }
    ],
    "sg:phone":"+1 510 367 0371",
    "sg:postcode":"94530",
    "sg:province":"CA",
    "sg:tags":[
        "peripheral",
        "related",
        "mfg"
    ],
    "wof:name":"Tree of Life Productions",
    "wof:placetype":"venue"
},
  "geometry": {"coordinates":[-122.292053,37.90624],"type":"Point"}
}