{
  "type": "Feature",
  "properties": {
    "iso:country":"US",
    "sg:address":"1429 Fulton Rd",
    "sg:city":"Santa Rosa",
    "sg:classifiers":[
        {
            "category":"Restaurant",
            "type":"Food & Drink"
        }
    ],
    "sg:phone":"+1 707 542 2372",
    "sg:postcode":"95403",
    "sg:province":"CA",
    "wof:name":"Taco Bell",
    "wof:placetype":"venue"
},
  "geometry": {"coordinates":[-122.76966899999999,38.463004],"type":"Point"}
}