{
  "type": "Feature",
  "properties": {
    "addr:full":"5578 34th St Apt 1 Riverside CA 92509",
    "addr:housenumber":"5578;1",
    "addr:postcode":"92509",
    "addr:street":"34Th St Apt",
    "iso:country":"US",
    "sg:address":"5578 34th St Apt 1",
    "sg:city":"Riverside",
    "sg:classifiers":[
        {
            "category":"Real Estate",
            "subcategory":"Real Estate Services",
            "type":"Services"
        },
        {
            "category":"Real Estate",
            "subcategory":"Real Estate Operator",
            "type":"Services"
        }
    ],
    "sg:phone":"+1 951 787 1115",
    "sg:postcode":"92509",
    "sg:province":"CA",
    "sg:tags":[
        "vacancy",
        "apartment",
        "rental",
        "finder",
        "listing"
    ],
    "wof:name":"Pacific Winds Apartments",
    "wof:placetype":"venue"
},
  "geometry": {"coordinates":[-117.403648,34.000739],"type":"Point"}
}