{
  "type": "Feature",
  "properties": {
    "addr:full":"109 2nd St Bieber CA 96009",
    "addr:housenumber":"109",
    "addr:postcode":"96009",
    "addr:street":"2Nd St",
    "iso:country":"US",
    "sg:address":"109 2nd St",
    "sg:city":"Bieber",
    "sg:classifiers":[
        {
            "category":"Home & Garden",
            "subcategory":"Garden Supply",
            "type":"Retail Goods"
        }
    ],
    "sg:phone":"+1 530 294 5541",
    "sg:postcode":"96009",
    "sg:province":"CA",
    "sg:tags":[
        "nurseryman"
    ],
    "wof:name":"Big Valley Nursery",
    "wof:placetype":"venue"
},
  "geometry": {"coordinates":[-121.14001500000001,41.121346],"type":"Point"}
}