{
  "type": "Feature",
  "properties": {
    "addr:full":"1528 Nelson St Redlands CA 92374",
    "addr:housenumber":"1528",
    "addr:postcode":"92374",
    "addr:street":"Nelson St",
    "iso:country":"US",
    "sg:address":"1528 Nelson St",
    "sg:city":"Redlands",
    "sg:classifiers":[
        {
            "category":"Building & Trades",
            "subcategory":"Construction",
            "type":"Services"
        }
    ],
    "sg:phone":"+1 909 227 5701",
    "sg:postcode":"92374",
    "sg:province":"CA",
    "sg:tags":[
        "painter"
    ],
    "wof:name":"Impact Painting",
    "wof:placetype":"venue"
},
  "geometry": {"coordinates":[-117.15839699999999,34.075194],"type":"Point"}
}