{
  "type": "Feature",
  "properties": {
    "addr:full":"1401 N Broadway Walnut Creek CA 94596",
    "addr:housenumber":"1401",
    "addr:postcode":"94596",
    "addr:street":"N Broadway",
    "iso:country":"US",
    "sg:address":"1401 N Broadway",
    "sg:city":"Walnut Creek",
    "sg:classifiers":[
        {
            "category":"Professional",
            "subcategory":"Art Services",
            "type":"Services"
        }
    ],
    "sg:phone":"+1 925 944 9500",
    "sg:postcode":"94596",
    "sg:province":"CA",
    "sg:tags":[
        "graphic",
        "designer"
    ],
    "sg:website":"www.mclean-design.com",
    "wof:name":"Mc Lean Design",
    "wof:placetype":"venue"
},
  "geometry": {"coordinates":[-122.059822,37.899674],"type":"Point"}
}