{
  "type": "Feature",
  "properties": {
    "addr:full":"1607 N Sycamore St Santa Ana CA 92701",
    "addr:housenumber":"1607",
    "addr:postcode":"92701",
    "addr:street":"N Sycamore St",
    "iso:country":"US",
    "sg:address":"1607 N Sycamore St",
    "sg:city":"Santa Ana",
    "sg:classifiers":[
        {
            "category":"Professional",
            "subcategory":"Lawyer & Legal Services",
            "type":"Services"
        }
    ],
    "sg:phone":"+1 714 834 9086",
    "sg:postcode":"92701",
    "sg:province":"CA",
    "wof:name":"Law Offices of Chas A Goldwasser",
    "wof:placetype":"venue"
},
  "geometry": {"coordinates":[-117.868093,33.759244],"type":"Point"}
}