{
  "type": "Feature",
  "properties": {
    "iso:country":"US",
    "sg:address":"560 Haight St",
    "sg:city":"San Francisco",
    "sg:classifiers":[
        {
            "category":"Professional",
            "subcategory":"Art Services",
            "type":"Services"
        }
    ],
    "sg:phone":"+1 415 227 4700",
    "sg:postcode":"94117",
    "sg:province":"CA",
    "sg:tags":[
        "graphic",
        "designer"
    ],
    "wof:name":"Hybird Design",
    "wof:placetype":"venue"
},
  "geometry": {"coordinates":[-122.431301,37.772099],"type":"Point"}
}