{
  "type": "Feature",
  "properties": {
    "addr:full":"5832 Garfield Ave Los Angeles CA 90040",
    "addr:housenumber":"5832",
    "addr:postcode":"90040",
    "addr:street":"Garfield Ave",
    "iso:country":"US",
    "sg:address":"5832 Garfield Ave",
    "sg:city":"Los Angeles",
    "sg:classifiers":[
        {
            "category":"Manufacturing",
            "subcategory":"Soap",
            "type":"Manufacturing & Wholesale Goods"
        }
    ],
    "sg:phone":"+1 323 723 3203",
    "sg:postcode":"90040",
    "sg:province":"CA",
    "sg:tags":[
        "detergent",
        "mfg"
    ],
    "wof:name":"Dial Corporation",
    "wof:placetype":"venue"
},
  "geometry": {"coordinates":[-118.142495,33.980603],"type":"Point"}
}