{
  "type": "Feature",
  "properties": {
    "iso:country":"US",
    "sg:address":"2549 A St",
    "sg:city":"La Verne",
    "sg:classifiers":[
        {
            "category":"Wholesale",
            "subcategory":"Hardware",
            "type":"Manufacturing & Wholesale Goods"
        },
        {
            "category":"Manufacturing",
            "subcategory":"Tools & Machinery",
            "type":"Manufacturing & Wholesale Goods"
        }
    ],
    "sg:phone":"+1 909 593 8069",
    "sg:postcode":"91750",
    "sg:province":"CA",
    "sg:tags":[
        "import",
        "furniture"
    ],
    "wof:name":"Infinity Hardware",
    "wof:placetype":"venue"
},
  "geometry": {"coordinates":[-117.775378,34.104018],"type":"Point"}
}