{
  "type": "Feature",
  "properties": {
    "iso:country":"US",
    "sg:address":"18090 Chatsworth St",
    "sg:city":"Granada Hills",
    "sg:classifiers":[
        {
            "category":"Restaurant",
            "type":"Food & Drink"
        }
    ],
    "sg:menulink":"http://www.allmenus.com/ca/san-fernando-valley/171001-carls-jr/menu/",
    "sg:phone":"+1 818 368 5177",
    "sg:postcode":"91344",
    "sg:province":"CA",
    "sg:tags":[
        "burger",
        "american"
    ],
    "wof:name":"Carl's Jr.",
    "wof:placetype":"venue"
},
  "geometry": {"coordinates":[-118.527092,34.264515],"type":"Point"}
}