{
  "type": "Feature",
  "properties": {
    "addr:full":"10524 S San Pedro St Los Angeles CA 90003",
    "addr:housenumber":"10524",
    "addr:postcode":"90003",
    "addr:street":"S San Pedro St",
    "iso:country":"US",
    "sg:address":"10524 S San Pedro St",
    "sg:city":"Los Angeles",
    "sg:classifiers":[
        {
            "category":"Shopping",
            "subcategory":"Discount & Variety Stores",
            "type":"Retail Goods"
        }
    ],
    "sg:phone":"+1 323 820 2029",
    "sg:postcode":"90003",
    "sg:province":"CA",
    "wof:name":"Doing The Best I Can",
    "wof:placetype":"venue"
},
  "geometry": {"coordinates":[-118.26943900000001,33.940372],"type":"Point"}
}