{
  "type": "Feature",
  "properties": {
    "addr:full":"40077 Enterprise Dr Oakhurst CA 93644",
    "addr:housenumber":"40077",
    "addr:postcode":"93644",
    "addr:street":"Enterprise Dr",
    "iso:country":"US",
    "sg:address":"40077 Enterprise Dr",
    "sg:city":"Oakhurst",
    "sg:classifiers":[
        {
            "category":"Building & Trades",
            "subcategory":"Construction",
            "type":"Services"
        }
    ],
    "sg:phone":"+1 559 683 3000",
    "sg:postcode":"93644",
    "sg:province":"CA",
    "sg:tags":[
        "paving",
        "contractor"
    ],
    "wof:name":"California Paving Co",
    "wof:placetype":"venue"
},
  "geometry": {"coordinates":[-119.660905,37.332288],"type":"Point"}
}