{
  "type": "Feature",
  "properties": {
    "iso:country":"US",
    "sg:address":"652 Williamson Ave",
    "sg:city":"Fullerton",
    "sg:classifiers":[
        {
            "category":"Retail",
            "subcategory":"Auto Repair",
            "type":"Services"
        }
    ],
    "sg:phone":"+1 714 526 2040",
    "sg:postcode":"92832",
    "sg:province":"CA",
    "sg:tags":[
        "wheel",
        "wheels-frame",
        "servicing-automotive",
        "balancing",
        "axle",
        "wheels-aligning",
        "alignment-frame",
        "servicing-equipment"
    ],
    "wof:name":"Baker Automotive",
    "wof:placetype":"venue"
},
  "geometry": {"coordinates":[-117.936307,33.869076],"type":"Point"}
}