{
  "type": "Feature",
  "properties": {
    "addr:full":"2510 E Gage Avenue Huntington Park CA 90255",
    "addr:housenumber":"2510",
    "addr:postcode":"90255",
    "addr:street":"E Gage Avenue;Park",
    "iso:country":"US",
    "sg:address":"2510 E Gage Avenue",
    "sg:city":"Huntington Park",
    "sg:classifiers":[
        {
            "category":"Health Services",
            "subcategory":"Health Practitioner",
            "type":"Services"
        }
    ],
    "sg:phone":"+1 323 589 2613",
    "sg:postcode":"90255",
    "sg:province":"CA",
    "sg:tags":[
        "nutritionist"
    ],
    "wof:name":"Kinder Nutrition No 2",
    "wof:placetype":"venue"
},
  "geometry": {"coordinates":[-118.22742,33.981569],"type":"Point"}
}