{
  "type": "Feature",
  "properties": {
    "iso:country":"US",
    "sg:address":"1226 W Imperial Hwy",
    "sg:city":"Los Angeles",
    "sg:classifiers":[
        {
            "category":"Real Estate",
            "subcategory":"Real Estate Operator",
            "type":"Services"
        }
    ],
    "sg:phone":"+1 323 242 8573",
    "sg:postcode":"90044",
    "sg:province":"CA",
    "sg:tags":[
        "mobile",
        "home",
        "community"
    ],
    "wof:name":"Friendly Trailer Park",
    "wof:placetype":"venue"
},
  "geometry": {"coordinates":[-118.296684,33.930907],"type":"Point"}
}