{
  "type": "Feature",
  "properties": {
    "addr:full":"193 S Washington St Sonora CA 95370",
    "addr:housenumber":"193",
    "addr:postcode":"95370",
    "addr:street":"S Washington St",
    "iso:country":"US",
    "sg:address":"193 S Washington St",
    "sg:city":"Sonora",
    "sg:classifiers":[
        {
            "category":"Home & Garden",
            "subcategory":"Furniture",
            "type":"Retail Goods"
        }
    ],
    "sg:phone":"+1 209 533 9969",
    "sg:postcode":"95370",
    "sg:province":"CA",
    "sg:tags":[
        "cabinet"
    ],
    "wof:name":"Cabinets N More",
    "wof:placetype":"venue"
},
  "geometry": {"coordinates":[-120.38199400000001,37.98298],"type":"Point"}
}