{
  "type": "Feature",
  "properties": {
    "iso:country":"US",
    "sg:address":"2967 E San Gabriel Ave",
    "sg:city":"Fresno",
    "sg:classifiers":[
        {
            "category":"Autos & Motor Vehicles",
            "subcategory":"Automobile Sales",
            "type":"Retail Goods"
        }
    ],
    "sg:phone":"+1 559 229 0115",
    "sg:postcode":"93726",
    "sg:province":"CA",
    "sg:tags":[
        "car",
        "dealer"
    ],
    "wof:name":"U Auto Call Ellie",
    "wof:placetype":"venue"
},
  "geometry": {"coordinates":[-119.775797,36.804258],"type":"Point"}
}