{
  "type": "Feature",
  "properties": {
    "addr:full":"7400 Rancho Verde Ln Loomis CA 95650",
    "addr:housenumber":"7400",
    "addr:postcode":"95650",
    "addr:street":"Rancho Verde Ln",
    "iso:country":"US",
    "sg:address":"7400 Rancho Verde Ln",
    "sg:city":"Loomis",
    "sg:classifiers":[
        {
            "category":"Autos & Motor Vehicles",
            "subcategory":"Auto Supplies",
            "type":"Retail Goods"
        }
    ],
    "sg:phone":"+1 916 652 7836",
    "sg:postcode":"95650",
    "sg:province":"CA",
    "sg:tags":[
        "lube",
        "oil"
    ],
    "wof:name":"Oil & Lube Express",
    "wof:placetype":"venue"
},
  "geometry": {"coordinates":[-121.16890100000001,38.81876],"type":"Point"}
}