{
  "type": "Feature",
  "properties": {
    "addr:full":"497 E Paige Ave Tulare CA 93274",
    "addr:housenumber":"497",
    "addr:postcode":"93274",
    "addr:street":"E Paige Ave",
    "iso:country":"US",
    "sg:address":"497 E Paige Ave",
    "sg:city":"Tulare",
    "sg:classifiers":[
        {
            "category":"Farming",
            "subcategory":"Farm & Veterinary Services",
            "type":"Manufacturing & Wholesale Goods"
        }
    ],
    "sg:phone":"+1 559 686 0962",
    "sg:postcode":"93274",
    "sg:province":"CA",
    "sg:tags":[
        "harvesting"
    ],
    "wof:name":"Evans & Sons Hay Harvesting",
    "wof:placetype":"venue"
},
  "geometry": {"coordinates":[-119.338463,36.182019],"type":"Point"}
}