{
  "type": "Feature",
  "properties": {
    "iso:country":"US",
    "sg:address":"604 Sanford Ave Ste 7",
    "sg:city":"Wilmington",
    "sg:classifiers":[
        {
            "category":"Home & Garden",
            "subcategory":"Home Furnishings",
            "type":"Retail Goods"
        },
        {
            "category":"Building & Trades",
            "subcategory":"Construction",
            "type":"Services"
        },
        {
            "category":"Manufacturing",
            "subcategory":"Building Materials",
            "type":"Manufacturing & Wholesale Goods"
        }
    ],
    "sg:phone":"+1 310 513 6069",
    "sg:postcode":"90744",
    "sg:province":"CA",
    "sg:tags":[
        "industrial",
        "cabinetmakers-commercial",
        "cabinet",
        "refacing",
        "resurfacing",
        "maker",
        "cabinets-refinishing",
        "kitchen"
    ],
    "wof:name":"Kitchen Guizar",
    "wof:placetype":"venue"
},
  "geometry": {"coordinates":[-118.250524,33.777749],"type":"Point"}
}