{
  "type": "Feature",
  "properties": {
    "addr:full":"504 E Charter Way Stockton CA 95206",
    "addr:housenumber":"504",
    "addr:postcode":"95206",
    "addr:street":"E Charter Way",
    "iso:country":"US",
    "sg:address":"504 E Charter Way",
    "sg:city":"Stockton",
    "sg:classifiers":[
        {
            "category":"Professional",
            "subcategory":"Accounting & Tax Preparation",
            "type":"Services"
        },
        {
            "category":"Insurance",
            "subcategory":"Hazard Insurance",
            "type":"Services"
        },
        {
            "category":"Professional",
            "subcategory":"Business Services",
            "type":"Services"
        }
    ],
    "sg:phone":"+1 209 939 1040",
    "sg:postcode":"95206",
    "sg:province":"CA",
    "sg:tags":[
        "commercial",
        "bookkeeping",
        "return",
        "public",
        "notary"
    ],
    "wof:name":"Tax Express / Cuevas Insurance Agency",
    "wof:placetype":"venue"
},
  "geometry": {"coordinates":[-121.28077,37.939779],"type":"Point"}
}