{
  "type": "Feature",
  "properties": {
    "iso:country":"US",
    "sg:address":"654 Barberry Ln",
    "sg:city":"San Rafael",
    "sg:classifiers":[
        {
            "category":"Professional",
            "subcategory":"Computer Services",
            "type":"Services"
        }
    ],
    "sg:phone":"+1 415 472 9100",
    "sg:postcode":"94903",
    "sg:province":"CA",
    "sg:tags":[
        "graphics"
    ],
    "wof:name":"Eyeland Media",
    "wof:placetype":"venue"
},
  "geometry": {"coordinates":[-122.562453,38.013521],"type":"Point"}
}