{
  "type": "Feature",
  "properties": {
    "addr:full":"4154 MacArthur Blvd Oakland CA 94619",
    "addr:housenumber":"4154",
    "addr:postcode":"94619",
    "addr:street":"Macarthur Blvd",
    "iso:country":"US",
    "sg:address":"4154 MacArthur Blvd",
    "sg:city":"Oakland",
    "sg:classifiers":[
        {
            "category":"Education",
            "subcategory":"Kindergarten",
            "type":"Public Place"
        },
        {
            "category":"Education",
            "subcategory":"School",
            "type":"Public Place"
        }
    ],
    "sg:phone":"+1 510 530 1938",
    "sg:postcode":"94619",
    "sg:province":"CA",
    "sg:tags":[
        "driving"
    ],
    "sg:website":"www.berkeleydrivingschool.com",
    "wof:name":"Berkeley Driving School",
    "wof:placetype":"venue"
},
  "geometry": {"coordinates":[-122.195851,37.7889],"type":"Point"}
}