{
  "type": "Feature",
  "properties": {
    "iso:country":"US",
    "sg:address":"633 E Grand Ave",
    "sg:city":"Escondido",
    "sg:classifiers":[
        {
            "category":"Health Services",
            "subcategory":"Chiropractor",
            "type":"Services"
        }
    ],
    "sg:phone":"+1 760 480 2229",
    "sg:postcode":"92025",
    "sg:province":"CA",
    "wof:name":"Steinhardt Jeffrey DC",
    "wof:placetype":"venue"
},
  "geometry": {"coordinates":[-117.38009700000001,33.124495],"type":"Point"}
}