{
  "type": "Feature",
  "properties": {
    "addr:full":"1943 Martin Luther King J # J Berkeley CA 94704",
    "addr:housenumber":"1943",
    "addr:postcode":"94704",
    "addr:street":"Martin Luther King J # J",
    "iso:country":"US",
    "sg:address":"1943 Martin Luther King J # J",
    "sg:city":"Berkeley",
    "sg:classifiers":[
        {
            "category":"Professional",
            "subcategory":"Accounting & Tax Preparation",
            "type":"Services"
        }
    ],
    "sg:phone":"+1 510 548 3800",
    "sg:postcode":"94704",
    "sg:province":"CA",
    "sg:tags":[
        "accountant"
    ],
    "wof:name":"Max & Company",
    "wof:placetype":"venue"
},
  "geometry": {"coordinates":[-122.273003,37.872101],"type":"Point"}
}