{
  "type": "Feature",
  "properties": {
    "addr:full":"2468 Whipple Rd Hayward CA 94544",
    "addr:housenumber":"2468",
    "addr:postcode":"94544",
    "addr:street":"Whipple Rd",
    "iso:country":"US",
    "sg:address":"2468 Whipple Rd",
    "sg:city":"Hayward",
    "sg:classifiers":[
        {
            "category":"Retail",
            "subcategory":"Auto Rental",
            "type":"Services"
        }
    ],
    "sg:phone":"+1 510 471 1931",
    "sg:postcode":"94544",
    "sg:province":"CA",
    "sg:tags":[
        "renting",
        "car",
        "leasing",
        "truck",
        "trailer"
    ],
    "wof:name":"U-Haul Co",
    "wof:placetype":"venue"
},
  "geometry": {"coordinates":[-122.063393,37.606946],"type":"Point"}
}