{
  "type": "Feature",
  "properties": {
    "addr:full":"16341 Grand Ave Apt 6 Lake Elsinore CA 92530",
    "addr:housenumber":"16341;6",
    "addr:postcode":"92530",
    "addr:street":"Grand Ave Apt",
    "iso:country":"US",
    "sg:address":"16341 Grand Ave Apt 6",
    "sg:city":"Lake Elsinore",
    "sg:classifiers":[
        {
            "category":"Real Estate",
            "subcategory":"Real Estate Operator",
            "type":"Services"
        }
    ],
    "sg:phone":"+1 951 678 7318",
    "sg:postcode":"92530",
    "sg:province":"CA",
    "sg:tags":[
        "apartment"
    ],
    "wof:name":"Copper Canyon Villas",
    "wof:placetype":"venue"
},
  "geometry": {"coordinates":[-117.363998,33.651001],"type":"Point"}
}