{
  "type": "Feature",
  "properties": {
    "iso:country":"US",
    "sg:address":"8132 Puesta del Sol",
    "sg:city":"Carpinteria",
    "sg:classifiers":[
        {
            "category":"Education",
            "subcategory":"Special Training",
            "type":"Public Place"
        }
    ],
    "sg:phone":"+1 805 684 2250",
    "sg:postcode":"93013",
    "sg:province":"CA",
    "sg:tags":[
        "tutoring"
    ],
    "wof:name":"Santa Barbara Writers Cnfrnc",
    "wof:placetype":"venue"
},
  "geometry": {"coordinates":[-119.474052,34.375132],"type":"Point"}
}