{
  "type": "Feature",
  "properties": {
    "iso:country":"US",
    "sg:address":"18840 Soledad Canyon Rd",
    "sg:city":"Canyon Country",
    "sg:classifiers":[
        {
            "category":"Manufacturing",
            "subcategory":"Food",
            "type":"Manufacturing & Wholesale Goods"
        }
    ],
    "sg:phone":"+1 661 424 9979",
    "sg:postcode":"91351",
    "sg:province":"CA",
    "sg:tags":[
        "bakery"
    ],
    "wof:name":"Interstate Brands West Corp",
    "wof:placetype":"venue"
},
  "geometry": {"coordinates":[-118.462585,34.415749],"type":"Point"}
}