{
  "type": "Feature",
  "properties": {
    "iso:country":"US",
    "sg:address":"6006 Wilshire Blvd",
    "sg:city":"Los Angeles",
    "sg:classifiers":[
        {
            "category":"Insurance",
            "subcategory":"Insurance Agent",
            "type":"Services"
        }
    ],
    "sg:phone":"+1 323 933 2425",
    "sg:postcode":"90036",
    "sg:province":"CA",
    "wof:name":"Primerica Financial Svc",
    "wof:placetype":"venue"
},
  "geometry": {"coordinates":[-118.36002499999999,34.06268],"type":"Point"}
}