{
  "type": "Feature",
  "properties": {
    "addr:full":"13078 Sunlit Ct Moreno Valley CA 92553",
    "addr:housenumber":"13078",
    "addr:postcode":"92553",
    "addr:street":"Sunlit Ct",
    "iso:country":"US",
    "sg:address":"13078 Sunlit Ct",
    "sg:city":"Moreno Valley",
    "sg:classifiers":[
        {
            "category":"Manufacturing",
            "subcategory":"Retail Goods",
            "type":"Manufacturing & Wholesale Goods"
        }
    ],
    "sg:phone":"+1 951 656 7085",
    "sg:postcode":"92553",
    "sg:province":"CA",
    "sg:tags":[
        "hair",
        "mfg",
        "accessory"
    ],
    "wof:name":"Designing Women Originals",
    "wof:placetype":"venue"
},
  "geometry": {"coordinates":[-117.251728,33.930445],"type":"Point"}
}