{
  "type": "Feature",
  "properties": {
    "addr:full":"8724 S Central Ave Los Angeles CA 90002",
    "addr:housenumber":"8724",
    "addr:postcode":"90002",
    "addr:street":"S Central Ave",
    "iso:country":"US",
    "sg:address":"8724 S Central Ave",
    "sg:city":"Los Angeles",
    "sg:classifiers":[
        {
            "category":"Organizations",
            "subcategory":"Religious Organization",
            "type":"Services"
        }
    ],
    "sg:phone":"+1 323 585 5939",
    "sg:postcode":"90002",
    "sg:province":"CA",
    "sg:tags":[
        "church"
    ],
    "sg:website":"www.bethelunspeakablejoy.org",
    "wof:name":"Bethel Unspeakable Joy",
    "wof:placetype":"venue"
},
  "geometry": {"coordinates":[-118.25632400000001,33.958809],"type":"Point"}
}