{
  "type": "Feature",
  "properties": {
    "addr:full":"141 E Willow St Long Beach CA 90806",
    "addr:housenumber":"141",
    "addr:postcode":"90806",
    "addr:street":"E Willow St",
    "iso:country":"US",
    "sg:address":"141 E Willow St",
    "sg:city":"Long Beach",
    "sg:classifiers":[
        {
            "category":"Shopping",
            "subcategory":"Shoes",
            "type":"Retail Goods"
        }
    ],
    "sg:phone":"+1 562 290 0911",
    "sg:postcode":"90806",
    "sg:province":"CA",
    "sg:tags":[
        "store"
    ],
    "wof:name":"Footlocker Corporate Svc Inc",
    "wof:placetype":"venue"
},
  "geometry": {"coordinates":[-118.19144,33.804582],"type":"Point"}
}