{
  "type": "Feature",
  "properties": {
    "addr:full":"5439 W San Fernando Rd Los Angeles CA 90039",
    "addr:housenumber":"5439",
    "addr:postcode":"ca 90039",
    "addr:street":"W San Fernando Rd",
    "iso:country":"US",
    "sg:address":"5439 W San Fernando Rd",
    "sg:city":"Los Angeles",
    "sg:classifiers":[
        {
            "category":"Freight",
            "type":"Transportation"
        }
    ],
    "sg:phone":"+1 323 525 9300",
    "sg:postcode":"90039",
    "sg:province":"CA",
    "sg:tags":[
        "general"
    ],
    "wof:name":"Lawson Screen Products Inc",
    "wof:placetype":"venue"
},
  "geometry": {"coordinates":[-118.27381800000001,34.149605],"type":"Point"}
}