{
  "type": "Feature",
  "properties": {
    "addr:full":"43170 Corte Landeros Temecula CA 92592",
    "addr:housenumber":"43170",
    "addr:postcode":"92592",
    "addr:street":"Corte Landeros",
    "iso:country":"US",
    "sg:address":"43170 Corte Landeros",
    "sg:city":"Temecula",
    "sg:classifiers":[
        {
            "category":"Building & Trades",
            "subcategory":"Cleaning & Sanitation",
            "type":"Services"
        }
    ],
    "sg:phone":"+1 951 302 9604",
    "sg:postcode":"92592",
    "sg:province":"CA",
    "sg:tags":[
        "janitor"
    ],
    "wof:name":"UBM",
    "wof:placetype":"venue"
},
  "geometry": {"coordinates":[-117.10607299999999,33.496694],"type":"Point"}
}