{
  "type": "Feature",
  "properties": {
    "addr:full":"1710 N Long Beach Blvd Compton CA 90221",
    "addr:housenumber":"1710",
    "addr:postcode":"90221",
    "addr:street":"N Long Beach Blvd",
    "iso:country":"US",
    "sg:address":"1710 N Long Beach Blvd",
    "sg:city":"Compton",
    "sg:classifiers":[
        {
            "category":"Personal",
            "subcategory":"Beauty Salon",
            "type":"Services"
        }
    ],
    "sg:phone":"+1 310 608 6787",
    "sg:postcode":"90221",
    "sg:province":"CA",
    "sg:tags":[
        "hair"
    ],
    "wof:name":"Pueblo Umidos Beauty Salon",
    "wof:placetype":"venue"
},
  "geometry": {"coordinates":[-118.208522,33.907117],"type":"Point"}
}