{
  "type": "Feature",
  "properties": {
    "addr:full":"271 Madison Ave San Bruno CA 94066",
    "addr:housenumber":"271",
    "addr:postcode":"94066",
    "addr:street":"Madison Ave",
    "iso:country":"US",
    "sg:address":"271 Madison Ave",
    "sg:city":"San Bruno",
    "sg:classifiers":[
        {
            "category":"Recreation",
            "type":"Entertainment"
        }
    ],
    "sg:phone":"+1 650 873 7321",
    "sg:postcode":"94066",
    "sg:province":"CA",
    "sg:tags":[
        "trainer",
        "sporting"
    ],
    "sg:website":"www.mitchellscuba.com/",
    "wof:name":"Mitchell Scuba College",
    "wof:placetype":"venue"
},
  "geometry": {"coordinates":[-122.43000000000001,37.613701],"type":"Point"}
}