{
  "type": "Feature",
  "properties": {
    "addr:full":"2855 Middlefield Rd Redwood City CA 94063",
    "addr:housenumber":"2855",
    "addr:postcode":"94063",
    "addr:street":"Middlefield Rd",
    "iso:country":"US",
    "sg:address":"2855 Middlefield Rd",
    "sg:city":"Redwood City",
    "sg:classifiers":[
        {
            "category":"Restaurant",
            "type":"Food & Drink"
        }
    ],
    "sg:phone":"+1 650 599 9891",
    "sg:postcode":"94063",
    "sg:province":"CA",
    "wof:name":"El Taco De Oro",
    "wof:placetype":"venue"
},
  "geometry": {"coordinates":[-122.20993,37.475876],"type":"Point"}
}