{
  "type": "Feature",
  "properties": {
    "addr:full":"801 S Grand Avenue Los Angeles CA 90017",
    "addr:housenumber":"801",
    "addr:postcode":"90017",
    "addr:street":"S Grand Avenue",
    "iso:country":"US",
    "sg:address":"801 S Grand Avenue",
    "sg:city":"Los Angeles",
    "sg:classifiers":[
        {
            "category":"Professional",
            "subcategory":"Lawyer & Legal Services",
            "type":"Services"
        }
    ],
    "sg:phone":"+1 213 629 2071",
    "sg:postcode":"90017",
    "sg:province":"CA",
    "wof:name":"The Law Ofc of Gideon Kracov",
    "wof:placetype":"venue"
},
  "geometry": {"coordinates":[-118.25794399999999,34.045853],"type":"Point"}
}