{
  "type": "Feature",
  "properties": {
    "iso:country":"US",
    "sg:address":"1800 Wyatt Dr",
    "sg:city":"Santa Clara",
    "sg:classifiers":[
        {
            "category":"Wholesale",
            "subcategory":"Computers",
            "type":"Manufacturing & Wholesale Goods"
        },
        {
            "category":"Wholesale",
            "subcategory":"Office Equipment",
            "type":"Manufacturing & Wholesale Goods"
        }
    ],
    "sg:phone":"+1 408 980 0558",
    "sg:postcode":"95054",
    "sg:province":"CA",
    "sg:tags":[
        "computerized",
        "manufacturer",
        "cash",
        "representative"
    ],
    "wof:name":"Senor Tech Inc",
    "wof:placetype":"venue"
},
  "geometry": {"coordinates":[-121.958079,37.389284],"type":"Point"}
}