{
  "type": "Feature",
  "properties": {
    "iso:country":"US",
    "sg:address":"2213 Tyler Ave",
    "sg:city":"South El Monte",
    "sg:classifiers":[
        {
            "category":"Wholesale",
            "subcategory":"Scrap",
            "type":"Manufacturing & Wholesale Goods"
        }
    ],
    "sg:phone":"+1 626 443 8921",
    "sg:postcode":"91733",
    "sg:province":"CA",
    "sg:tags":[
        "recycling",
        "center"
    ],
    "sg:website":"www.ptmetals.com",
    "wof:name":"P & T Metals Inc",
    "wof:placetype":"venue"
},
  "geometry": {"coordinates":[-118.035719,34.055108],"type":"Point"}
}