{
  "type": "Feature",
  "properties": {
    "addr:full":"73111 el Paseo Palm Desert CA 92260",
    "addr:housenumber":"73111",
    "addr:postcode":"ca 92260",
    "addr:street":"El Paseo",
    "iso:country":"US",
    "sg:address":"73111 el Paseo",
    "sg:city":"Palm Desert",
    "sg:classifiers":[
        {
            "category":"Shopping",
            "subcategory":"Clothing, Apparel, & Fashions",
            "type":"Retail Goods"
        }
    ],
    "sg:phone":"+1 760 776 6100",
    "sg:postcode":"92260",
    "sg:province":"CA",
    "wof:name":"Fe Zandi",
    "wof:placetype":"venue"
},
  "geometry": {"coordinates":[-116.387092,33.719697],"type":"Point"}
}