{
  "type": "Feature",
  "properties": {
    "iso:country":"US",
    "sg:address":"1230 High St",
    "sg:city":"Auburn",
    "sg:classifiers":[
        {
            "category":"Real Estate",
            "subcategory":"Real Estate Operator",
            "type":"Services"
        }
    ],
    "sg:phone":"+1 530 889 1788",
    "sg:postcode":"95603",
    "sg:province":"CA",
    "sg:tags":[
        "apartment"
    ],
    "wof:name":"Jeff Tremoureux",
    "wof:placetype":"venue"
},
  "geometry": {"coordinates":[-121.074303,38.89489],"type":"Point"}
}