{
  "type": "Feature",
  "properties": {
    "iso:country":"US",
    "sg:address":"2124 Kittredge St",
    "sg:city":"Berkeley",
    "sg:classifiers":[
        {
            "category":"Professional",
            "subcategory":"Business Services",
            "type":"Services"
        }
    ],
    "sg:phone":"+1 510 845 4004",
    "sg:postcode":"94704",
    "sg:province":"CA",
    "sg:tags":[
        "transcribing",
        "disc"
    ],
    "wof:name":"CRTT",
    "wof:placetype":"venue"
},
  "geometry": {"coordinates":[-122.26739499999999,37.868505],"type":"Point"}
}