{
  "type": "Feature",
  "properties": {
    "iso:country":"US",
    "sg:address":"12561 Lucille Ave",
    "sg:city":"Garden Grove",
    "sg:classifiers":[
        {
            "category":"Manufacturing",
            "subcategory":"Tools & Machinery",
            "type":"Manufacturing & Wholesale Goods"
        }
    ],
    "sg:phone":"+1 714 537 6359",
    "sg:postcode":"92841",
    "sg:province":"CA",
    "sg:tags":[
        "machine",
        "shop"
    ],
    "wof:name":"Van TC",
    "wof:placetype":"venue"
},
  "geometry": {"coordinates":[-117.97358,33.779199],"type":"Point"}
}