{
  "type": "Feature",
  "properties": {
    "addr:full":"127 S Olive St Orange CA 92866",
    "addr:housenumber":"127",
    "addr:postcode":"92866",
    "addr:street":"S Olive St",
    "iso:country":"US",
    "sg:address":"127 S Olive St",
    "sg:city":"Orange",
    "sg:classifiers":[
        {
            "category":"Personal",
            "subcategory":"Beauty Salon",
            "type":"Services"
        }
    ],
    "sg:phone":"+1 714 997 5599",
    "sg:postcode":"92866",
    "sg:province":"CA",
    "sg:tags":[
        "hair"
    ],
    "sg:website":"salonrebelle.com/",
    "wof:name":"Salon r?Belle",
    "wof:placetype":"venue"
},
  "geometry": {"coordinates":[-117.85396299999999,33.787364],"type":"Point"}
}