{
  "type": "Feature",
  "properties": {
    "addr:full":"2428 Foothill Blvd La Crescenta CA 91214",
    "addr:housenumber":"2428",
    "addr:postcode":"91214",
    "addr:street":"Foothill Blvd",
    "iso:country":"US",
    "sg:address":"2428 Foothill Blvd",
    "sg:city":"La Crescenta",
    "sg:classifiers":[
        {
            "category":"Insurance",
            "subcategory":"Insurance Agent",
            "type":"Services"
        }
    ],
    "sg:phone":"+1 818 249 3000",
    "sg:postcode":"91214",
    "sg:province":"CA",
    "wof:name":"Whitener Insurance",
    "wof:placetype":"venue"
},
  "geometry": {"coordinates":[-118.232101,34.219285],"type":"Point"}
}