{
  "type": "Feature",
  "properties": {
    "iso:country":"US",
    "sg:address":"172 N 34th St",
    "sg:city":"San Jose",
    "sg:classifiers":[
        {
            "category":"Personal",
            "type":"Services"
        }
    ],
    "sg:phone":"+1 408 421 8866",
    "sg:postcode":"95116",
    "sg:province":"CA",
    "sg:tags":[
        "mover"
    ],
    "sg:website":"www.aamovingservices.com",
    "wof:name":"AA Moving Services",
    "wof:placetype":"venue"
},
  "geometry": {"coordinates":[-121.857276,37.352014],"type":"Point"}
}