{
  "type": "Feature",
  "properties": {
    "iso:country":"US",
    "sg:address":"1750 E Arenas Rd",
    "sg:city":"Palm Springs",
    "sg:classifiers":[
        {
            "category":"Health Services",
            "subcategory":"Doctor",
            "type":"Services"
        }
    ],
    "sg:phone":"+1 760 323 2524",
    "sg:postcode":"92262",
    "sg:province":"CA",
    "wof:name":"Hromadko Gail A M A Psychotherapy & Mediation",
    "wof:placetype":"venue"
},
  "geometry": {"coordinates":[-116.526999,33.821714],"type":"Point"}
}