{
  "type": "Feature",
  "properties": {
    "addr:full":"Turk Family Center 8804 Balboa Ave San Diego CA 92123",
    "addr:housenumber":"8804",
    "addr:postcode":"92123",
    "addr:street":"Balboa Ave",
    "iso:country":"US",
    "sg:address":"Turk Family Center 8804 Balboa Ave",
    "sg:city":"San Diego",
    "sg:classifiers":[
        {
            "category":"Organizations",
            "subcategory":"Non-profit Organization",
            "type":"Services"
        }
    ],
    "sg:phone":"+1 858 637 3000",
    "sg:postcode":"92123",
    "sg:province":"CA",
    "sg:tags":[
        "service/non-profit",
        "community"
    ],
    "sg:website":"www.jfssd.org/",
    "wof:name":"Jewish Family Service of San Diego",
    "wof:placetype":"venue"
},
  "geometry": {"coordinates":[-117.13854600000001,32.821143],"type":"Point"}
}