{
  "type": "Feature",
  "properties": {
    "addr:full":"1669 E I St Wilmington CA 90744",
    "addr:housenumber":"1669",
    "addr:postcode":"90744",
    "addr:street":"E I St",
    "iso:country":"US",
    "sg:address":"1669 E I St",
    "sg:city":"Wilmington",
    "sg:classifiers":[
        {
            "category":"Freight",
            "type":"Transportation"
        }
    ],
    "sg:phone":"+1 310 513 6217",
    "sg:postcode":"90744",
    "sg:province":"CA",
    "sg:tags":[
        "trucking"
    ],
    "wof:name":"Pacific Regional Transport",
    "wof:placetype":"venue"
},
  "geometry": {"coordinates":[-118.24116600000001,33.782475],"type":"Point"}
}