{
  "type": "Feature",
  "properties": {
    "addr:full":"10651 San Fernando Rd Pacoima CA 91331",
    "addr:housenumber":"10651",
    "addr:postcode":"91331",
    "addr:street":"San Fernando Rd",
    "iso:country":"US",
    "sg:address":"10651 San Fernando Rd",
    "sg:city":"Pacoima",
    "sg:classifiers":[
        {
            "category":"Wholesale",
            "subcategory":"Auto Parts",
            "type":"Manufacturing & Wholesale Goods"
        }
    ],
    "sg:phone":"+1 818 834 2950",
    "sg:postcode":"91331",
    "sg:province":"CA",
    "wof:name":"El Toro Tires",
    "wof:placetype":"venue"
},
  "geometry": {"coordinates":[-118.421729,34.265529],"type":"Point"}
}