{
  "type": "Feature",
  "properties": {
    "addr:full":"5134 N Palm Ave Fresno CA 93704",
    "addr:housenumber":"5134",
    "addr:postcode":"93704",
    "addr:street":"N Palm Ave",
    "iso:country":"US",
    "sg:address":"5134 N Palm Ave",
    "sg:city":"Fresno",
    "sg:classifiers":[
        {
            "category":"Food & Beverages",
            "subcategory":"Liquor & Beverages",
            "type":"Retail Goods"
        }
    ],
    "sg:phone":"+1 559 230 0120",
    "sg:postcode":"93704",
    "sg:province":"CA",
    "sg:tags":[
        "wine"
    ],
    "wof:name":"Bailey-Cannon Wine Merchants",
    "wof:placetype":"venue"
},
  "geometry": {"coordinates":[-119.80834,36.809505],"type":"Point"}
}