{
  "type": "Feature",
  "properties": {
    "addr:full":"740 32nd St San Diego CA 92102",
    "addr:housenumber":"740",
    "addr:postcode":"92102",
    "addr:street":"32Nd St",
    "iso:country":"US",
    "sg:address":"740 32nd St",
    "sg:city":"San Diego",
    "sg:classifiers":[
        {
            "category":"Travel",
            "subcategory":"Hotels & Motels",
            "type":"Entertainment"
        }
    ],
    "sg:phone":"+1 619 234 1445",
    "sg:postcode":"92102",
    "sg:province":"CA",
    "wof:name":"Ebony Inn Motel",
    "wof:placetype":"venue"
},
  "geometry": {"coordinates":[-117.125,32.7132],"type":"Point"}
}