{
  "type": "Feature",
  "properties": {
    "addr:full":"2500 Cam Diablo Walnut Creek CA 94514",
    "addr:housenumber":"2500",
    "addr:postcode":"94514",
    "addr:street":"Cam Diablo",
    "iso:country":"US",
    "sg:address":"2500 Cam Diablo",
    "sg:city":"Walnut Creek",
    "sg:classifiers":[
        {
            "category":"Building & Trades",
            "subcategory":"Construction",
            "type":"Services"
        }
    ],
    "sg:phone":"+1 925 938 5432",
    "sg:postcode":"94514",
    "sg:province":"CA",
    "sg:tags":[
        "repairing",
        "remodeling",
        "contractor"
    ],
    "wof:name":"Sherrill RD General Contr",
    "wof:placetype":"venue"
},
  "geometry": {"coordinates":[-121.640221,37.867394],"type":"Point"}
}