{
  "type": "Feature",
  "properties": {
    "addr:full":"2315 S Bascom Ave Campbell CA 95008",
    "addr:housenumber":"2315",
    "addr:postcode":"95008",
    "addr:street":"S Bascom Ave",
    "iso:country":"US",
    "sg:address":"2315 S Bascom Ave",
    "sg:city":"Campbell",
    "sg:classifiers":[
        {
            "category":"Real Estate",
            "subcategory":"Real Estate Agent",
            "type":"Services"
        }
    ],
    "sg:phone":"+1 408 559 0507",
    "sg:postcode":"95008",
    "sg:province":"CA",
    "wof:name":"Cathy Rose",
    "wof:placetype":"venue"
},
  "geometry": {"coordinates":[-121.93172,37.280365],"type":"Point"}
}