{
  "type": "Feature",
  "properties": {
    "iso:country":"US",
    "sg:address":"9785 Alder Ave",
    "sg:city":"Bloomington",
    "sg:classifiers":[
        {
            "category":"Personal",
            "subcategory":"Beauty Salon",
            "type":"Services"
        },
        {
            "category":"Personal",
            "subcategory":"Barber",
            "type":"Services"
        }
    ],
    "sg:phone":"+1 909 421 8055",
    "sg:postcode":"92316",
    "sg:province":"CA",
    "sg:tags":[
        "hair",
        "stylist"
    ],
    "wof:name":"Haircut Plus",
    "wof:placetype":"venue"
},
  "geometry": {"coordinates":[-117.418251,34.075917],"type":"Point"}
}