{
  "type": "Feature",
  "properties": {
    "addr:full":"351 Shotwell St San Francisco CA 94110",
    "addr:housenumber":"351",
    "addr:postcode":"94110",
    "addr:street":"Shotwell St",
    "iso:country":"US",
    "sg:address":"351 Shotwell St",
    "sg:city":"San Francisco",
    "sg:classifiers":[
        {
            "category":"Recreation",
            "subcategory":"Dance Hall",
            "type":"Entertainment"
        }
    ],
    "sg:phone":"+1 662 736 8411",
    "sg:postcode":"94110",
    "sg:province":"CA",
    "sg:tags":[
        "club"
    ],
    "sg:website":"therentparty.com",
    "wof:name":"The Rent Party",
    "wof:placetype":"venue"
},
  "geometry": {"coordinates":[-122.416078,37.762733],"type":"Point"}
}