{
  "type": "Feature",
  "properties": {
    "iso:country":"US",
    "sg:address":"7901 Stoneridge Dr",
    "sg:city":"Pleasanton",
    "sg:classifiers":[
        {
            "category":"Professional",
            "subcategory":"Computer Services",
            "type":"Services"
        }
    ],
    "sg:phone":"+1 925 467 1300",
    "sg:postcode":"94588",
    "sg:province":"CA",
    "sg:tags":[
        "consultant",
        "designer"
    ],
    "wof:name":"Criterion Information Systems",
    "wof:placetype":"venue"
},
  "geometry": {"coordinates":[-121.930286,37.6888],"type":"Point"}
}