{
  "type": "Feature",
  "properties": {
    "iso:country":"US",
    "sg:address":"1177 Branham Ln Ste 266",
    "sg:city":"San Jose",
    "sg:classifiers":[
        {
            "category":"Building & Trades",
            "subcategory":"Construction",
            "type":"Services"
        }
    ],
    "sg:phone":"+1 800 560 0110",
    "sg:postcode":"95118",
    "sg:province":"CA",
    "sg:tags":[
        "contractor"
    ],
    "sg:website":"thewaterdamageexperts.com",
    "wof:name":"The Water Damage Experts, Inc",
    "wof:placetype":"venue"
},
  "geometry": {"coordinates":[-121.879431,37.262795],"type":"Point"}
}