{
  "type": "Feature",
  "properties": {
    "addr:full":"2084 E Francis St Ontario CA 91761",
    "addr:housenumber":"2084",
    "addr:postcode":"91761",
    "addr:street":"E Francis St",
    "iso:country":"US",
    "sg:address":"2084 E Francis St",
    "sg:city":"Ontario",
    "sg:classifiers":[
        {
            "category":"Professional",
            "subcategory":"Advertising",
            "type":"Services"
        }
    ],
    "sg:phone":"+1 909 930 5858",
    "sg:postcode":"91761",
    "sg:province":"CA",
    "sg:tags":[
        "designer",
        "display",
        "producer"
    ],
    "sg:website":"www.prodisplaysinc.com",
    "wof:name":"Professional Displays",
    "wof:placetype":"venue"
},
  "geometry": {"coordinates":[-117.608418,34.041135],"type":"Point"}
}