{
  "type": "Feature",
  "properties": {
    "addr:full":"22425 Ventura Blvd Ste 138 Los Angeles CA 91364",
    "addr:housenumber":"22425",
    "addr:postcode":"91364",
    "addr:street":"Ventura Blvd Ste 138",
    "iso:country":"US",
    "sg:address":"22425 Ventura Blvd Ste 138",
    "sg:city":"Los Angeles",
    "sg:classifiers":[
        {
            "category":"Professional",
            "subcategory":"Lawyer & Legal Services",
            "type":"Services"
        }
    ],
    "sg:phone":"+1 800 489 1984",
    "sg:postcode":"91364",
    "sg:province":"CA",
    "wof:name":"Goldfarb Luu PC",
    "wof:placetype":"venue"
},
  "geometry": {"coordinates":[-118.61552399999999,34.168495],"type":"Point"}
}