{
  "type": "Feature",
  "properties": {
    "addr:full":"385 Tully Road San Jose CA 95112",
    "addr:housenumber":"385",
    "addr:postcode":"95112",
    "addr:street":"Tully Road",
    "iso:country":"US",
    "sg:address":"385 Tully Road",
    "sg:city":"San Jose",
    "sg:classifiers":[
        {
            "category":"Home & Garden",
            "subcategory":"Furniture",
            "type":"Retail Goods"
        }
    ],
    "sg:phone":"+1 408 297 8216",
    "sg:postcode":"95112",
    "sg:province":"CA",
    "sg:tags":[
        "store"
    ],
    "wof:name":"Best Furniture",
    "wof:placetype":"venue"
},
  "geometry": {"coordinates":[-121.851333,37.306029],"type":"Point"}
}