{
  "type": "Feature",
  "properties": {
    "iso:country":"US",
    "sg:address":"8816 S San Pedro St",
    "sg:city":"Los Angeles",
    "sg:classifiers":[
        {
            "category":"Manufacturing",
            "subcategory":"Tools & Machinery",
            "type":"Manufacturing & Wholesale Goods"
        }
    ],
    "sg:phone":"+1 323 971 3668",
    "sg:postcode":"90003",
    "sg:province":"CA",
    "sg:tags":[
        "machine",
        "shop"
    ],
    "wof:name":"Vega's Machine Shop",
    "wof:placetype":"venue"
},
  "geometry": {"coordinates":[-118.269423,33.956812],"type":"Point"}
}