{
  "type": "Feature",
  "properties": {
    "iso:country":"US",
    "sg:address":"119 E Peralta Way",
    "sg:city":"Fresno",
    "sg:classifiers":[
        {
            "category":"Shopping",
            "type":"Retail Goods"
        }
    ],
    "sg:phone":"+1 559 497 5408",
    "sg:postcode":"93704",
    "sg:province":"CA",
    "sg:tags":[
        "cosmetic",
        "perfume"
    ],
    "wof:name":"Mary Kay",
    "wof:placetype":"venue"
},
  "geometry": {"coordinates":[-119.808745,36.765881],"type":"Point"}
}