{
  "type": "Feature",
  "properties": {
    "addr:full":"5116 Leon St Oceanside CA 92057",
    "addr:housenumber":"5116",
    "addr:postcode":"92057",
    "addr:street":"Leon St",
    "iso:country":"US",
    "sg:address":"5116 Leon St",
    "sg:city":"Oceanside",
    "sg:classifiers":[
        {
            "category":"Banks & Credit Unions",
            "subcategory":"Financial Services",
            "type":"Services"
        }
    ],
    "sg:phone":"+1 760 721 2580",
    "sg:postcode":"92057",
    "sg:province":"CA",
    "sg:tags":[
        "trust",
        "management"
    ],
    "wof:name":"Stoffel Family Trust",
    "wof:placetype":"venue"
},
  "geometry": {"coordinates":[-117.294845,33.260808],"type":"Point"}
}