{
  "type": "Feature",
  "properties": {
    "addr:full":"5214 Diamond Heights Blvd San Francisco CA 94131",
    "addr:housenumber":"5214",
    "addr:postcode":"94131",
    "addr:street":"Diamond Heights Blvd",
    "iso:country":"US",
    "sg:address":"5214 Diamond Heights Blvd",
    "sg:city":"San Francisco",
    "sg:classifiers":[
        {
            "category":"Manufacturing",
            "subcategory":"Printing",
            "type":"Manufacturing & Wholesale Goods"
        }
    ],
    "sg:phone":"+1 415 437 6744",
    "sg:postcode":"94131",
    "sg:province":"CA",
    "sg:tags":[
        "publisher",
        "software"
    ],
    "wof:name":"Nosh Productions",
    "wof:placetype":"venue"
},
  "geometry": {"coordinates":[-122.438087,37.743706],"type":"Point"}
}