{
  "type": "Feature",
  "properties": {
    "addr:full":"731 Sansome St San Francisco CA 94111",
    "addr:housenumber":"731",
    "addr:postcode":"94111",
    "addr:street":"Sansome St",
    "iso:country":"US",
    "sg:address":"731 Sansome St",
    "sg:city":"San Francisco",
    "sg:classifiers":[
        {
            "category":"Wholesale",
            "subcategory":"Electrical",
            "type":"Manufacturing & Wholesale Goods"
        }
    ],
    "sg:phone":"+1 415 675 7000",
    "sg:postcode":"94111",
    "sg:province":"CA",
    "sg:tags":[
        "equipment",
        "video"
    ],
    "wof:name":"Dina Digital Video Systems",
    "wof:placetype":"venue"
},
  "geometry": {"coordinates":[-122.40194700000001,37.796666],"type":"Point"}
}