{
  "type": "Feature",
  "properties": {
    "addr:full":"6750 el Camino Real Atascadero CA 93422",
    "addr:housenumber":"6750",
    "addr:postcode":"93422",
    "addr:street":"El Camino Real",
    "iso:country":"US",
    "sg:address":"6750 el Camino Real",
    "sg:city":"Atascadero",
    "sg:classifiers":[
        {
            "category":"Professional",
            "subcategory":"Accounting & Tax Preparation",
            "type":"Services"
        }
    ],
    "sg:phone":"+1 805 466 6060",
    "sg:postcode":"93422",
    "sg:province":"CA",
    "sg:tags":[
        "return",
        "filing"
    ],
    "wof:name":"A R Pete Reed Bookeeping & Tax",
    "wof:placetype":"venue"
},
  "geometry": {"coordinates":[-120.668187,35.488143],"type":"Point"}
}