{
  "type": "Feature",
  "properties": {
    "iso:country":"US",
    "sg:address":"1516 Potrero Ave",
    "sg:city":"Richmond",
    "sg:classifiers":[
        {
            "category":"Organizations",
            "subcategory":"Religious Organization",
            "type":"Services"
        }
    ],
    "sg:phone":"+1 510 235 8688",
    "sg:postcode":"94804",
    "sg:province":"CA",
    "wof:name":"Independent Holiness Church",
    "wof:placetype":"venue"
},
  "geometry": {"coordinates":[-122.354283,37.923903],"type":"Point"}
}