{
  "type": "Feature",
  "properties": {
    "addr:full":"11079 Barnett Valley Rd Sebastopol CA 95472",
    "addr:housenumber":"11079",
    "addr:postcode":"95472",
    "addr:street":"Barnett Valley Rd",
    "iso:country":"US",
    "sg:address":"11079 Barnett Valley Rd",
    "sg:city":"Sebastopol",
    "sg:classifiers":[
        {
            "category":"Banks & Credit Unions",
            "subcategory":"Bank",
            "type":"Services"
        }
    ],
    "sg:phone":"+1 707 824 8720",
    "sg:postcode":"95472",
    "sg:province":"CA",
    "sg:tags":[
        "loan",
        "real estate"
    ],
    "wof:name":"Corey Enterprises",
    "wof:placetype":"venue"
},
  "geometry": {"coordinates":[-122.888885,38.365607],"type":"Point"}
}