{
  "type": "Feature",
  "properties": {
    "addr:full":"16810 Placer Hills Rd Meadow Vista CA 95722",
    "addr:housenumber":"16810",
    "addr:postcode":"95722",
    "addr:street":"Placer Hills Rd",
    "iso:country":"US",
    "sg:address":"16810 Placer Hills Rd",
    "sg:city":"Meadow Vista",
    "sg:classifiers":[
        {
            "category":"Restaurant",
            "type":"Food & Drink"
        }
    ],
    "sg:menulink":"http://www.allmenus.com/ca/colfax-summit/69262-mountain-mikes-pizza/menu/",
    "sg:phone":"+1 530 878 1865",
    "sg:postcode":"95722",
    "sg:province":"CA",
    "sg:tags":[
        "american",
        "pizza"
    ],
    "wof:name":"Mountain Mike's Pizza",
    "wof:placetype":"venue"
},
  "geometry": {"coordinates":[-121.022909,38.996961],"type":"Point"}
}