{
  "type": "Feature",
  "properties": {
    "addr:full":"3741 5th Ave San Diego CA 92103",
    "addr:housenumber":"3741",
    "addr:postcode":"92103",
    "addr:street":"5Th Ave",
    "iso:country":"US",
    "sg:address":"3741 5th Ave",
    "sg:city":"San Diego",
    "sg:classifiers":[
        {
            "category":"Personal",
            "subcategory":"Tattoo Parlor",
            "type":"Services"
        }
    ],
    "sg:phone":"+1 619 497 0902",
    "sg:postcode":"92103",
    "sg:province":"CA",
    "sg:website":"sleepinggianttattoo.com/",
    "wof:name":"Sleeping Giant Tattoo",
    "wof:placetype":"venue"
},
  "geometry": {"coordinates":[-117.160392,32.745779],"type":"Point"}
}