{
  "type": "Feature",
  "properties": {
    "iso:country":"US",
    "sg:address":"4735 Mission Street",
    "sg:city":"San Francisco",
    "sg:classifiers":[
        {
            "category":"Building & Trades",
            "subcategory":"Plumbing",
            "type":"Services"
        }
    ],
    "sg:phone":"+1 415 333 8499",
    "sg:postcode":"94112",
    "sg:province":"CA",
    "wof:name":"Black Sea Corporation",
    "wof:placetype":"venue"
},
  "geometry": {"coordinates":[-122.435997,37.7225],"type":"Point"}
}