{
  "type": "Feature",
  "properties": {
    "addr:full":"5500 Bolsa Ave Huntington Beach CA 92649",
    "addr:housenumber":"5500",
    "addr:postcode":"92649",
    "addr:street":"Bolsa Ave",
    "iso:country":"US",
    "sg:address":"5500 Bolsa Ave",
    "sg:city":"Huntington Beach",
    "sg:classifiers":[
        {
            "category":"Travel",
            "subcategory":"Travel Agent",
            "type":"Entertainment"
        }
    ],
    "sg:phone":"+1 714 379 3755",
    "sg:postcode":"92649",
    "sg:province":"CA",
    "sg:tags":[
        "agency",
        "bureau"
    ],
    "wof:name":"Go With Jo Travel",
    "wof:placetype":"venue"
},
  "geometry": {"coordinates":[-118.03044199999999,33.744355],"type":"Point"}
}