{
  "type": "Feature",
  "properties": {
    "addr:full":"1076 Nidrah St El Cajon CA 92020",
    "addr:housenumber":"1076",
    "addr:postcode":"92020",
    "addr:street":"Nidrah St",
    "iso:country":"US",
    "sg:address":"1076 Nidrah St",
    "sg:city":"El Cajon",
    "sg:classifiers":[
        {
            "category":"Banks & Credit Unions",
            "subcategory":"Financial Services",
            "type":"Services"
        }
    ],
    "sg:phone":"+1 619 447 1193",
    "sg:postcode":"92020",
    "sg:province":"CA",
    "sg:tags":[
        "trust",
        "management"
    ],
    "wof:name":"Osborn Family Trust",
    "wof:placetype":"venue"
},
  "geometry": {"coordinates":[-116.976282,32.780718],"type":"Point"}
}