{
  "type": "Feature",
  "properties": {
    "addr:full":"623 S Glendale Ave Glendale CA 91205",
    "addr:housenumber":"623",
    "addr:postcode":"91205",
    "addr:street":"S Glendale Ave",
    "iso:country":"US",
    "sg:address":"623 S Glendale Ave",
    "sg:city":"Glendale",
    "sg:classifiers":[
        {
            "category":"Retail",
            "subcategory":"Auto Repair",
            "type":"Services"
        }
    ],
    "sg:phone":"+1 818 500 7988",
    "sg:postcode":"91205",
    "sg:province":"CA",
    "sg:tags":[
        "repairing",
        "automobile",
        "radiator"
    ],
    "wof:name":"L A Radiator & Automotive",
    "wof:placetype":"venue"
},
  "geometry": {"coordinates":[-118.25104399999999,34.138817],"type":"Point"}
}