{
  "type": "Feature",
  "properties": {
    "addr:full":"7785 N Fairfax Ave Firebaugh CA 93622",
    "addr:housenumber":"7785",
    "addr:postcode":"93622",
    "addr:street":"N Fairfax Ave",
    "iso:country":"US",
    "sg:address":"7785 N Fairfax Ave",
    "sg:city":"Firebaugh",
    "sg:classifiers":[
        {
            "category":"Freight",
            "type":"Transportation"
        }
    ],
    "sg:phone":"+1 559 659 8835",
    "sg:postcode":"93622",
    "sg:province":"CA",
    "sg:tags":[
        "trucking"
    ],
    "wof:name":"West Valley Module Movers",
    "wof:placetype":"venue"
},
  "geometry": {"coordinates":[-120.563283,36.841411],"type":"Point"}
}