{
  "type": "Feature",
  "properties": {
    "addr:full":"603 Oriole Ave Davis CA 95616",
    "addr:housenumber":"603",
    "addr:postcode":"95616",
    "addr:street":"Oriole Ave",
    "iso:country":"US",
    "sg:address":"603 Oriole Ave",
    "sg:city":"Davis",
    "sg:classifiers":[
        {
            "category":"Professional",
            "subcategory":"Management & Consulting",
            "type":"Services"
        }
    ],
    "sg:phone":"+1 530 756 7645",
    "sg:postcode":"95616",
    "sg:province":"CA",
    "sg:tags":[
        "consultant",
        "business"
    ],
    "sg:website":"www.stoebel.com",
    "wof:name":"David Stoebel & Assoc",
    "wof:placetype":"venue"
},
  "geometry": {"coordinates":[-121.756694,38.572477],"type":"Point"}
}