{
  "type": "Feature",
  "properties": {
    "addr:full":"2908 E Whitmore Ave Ste I Ceres CA 95307",
    "addr:housenumber":"2908",
    "addr:postcode":"95307",
    "addr:street":"E Whitmore Ave Ste I",
    "iso:country":"US",
    "sg:address":"2908 E Whitmore Ave Ste I",
    "sg:city":"Ceres",
    "sg:classifiers":[
        {
            "category":"Retail",
            "subcategory":"Laundry & Dry Cleaning",
            "type":"Services"
        }
    ],
    "sg:phone":"+1 209 537 6738",
    "sg:postcode":"95307",
    "sg:province":"CA",
    "wof:name":"French Cleaners",
    "wof:placetype":"venue"
},
  "geometry": {"coordinates":[-120.94000200000001,37.5947],"type":"Point"}
}