{
  "type": "Feature",
  "properties": {
    "iso:country":"US",
    "sg:address":"201 Eucalyptus Dr.",
    "sg:city":"San Francisco",
    "sg:classifiers":[
        {
            "category":"Sports & Exercise",
            "subcategory":"Playing Field",
            "type":"Entertainment"
        }
    ],
    "sg:phone":"+1 415 738 8776",
    "sg:postcode":"94132",
    "sg:province":"CA",
    "sg:tags":[
        "instruction",
        "fitness"
    ],
    "sg:website":"www.iaw-sanfrancisco.com",
    "wof:name":"Academy of WingChun",
    "wof:placetype":"venue"
},
  "geometry": {"coordinates":[-122.47599,37.731109],"type":"Point"}
}