{
  "type": "Feature",
  "properties": {
    "iso:country":"US",
    "sg:address":"9905 Campo Rd",
    "sg:city":"Spring Valley",
    "sg:classifiers":[
        {
            "category":"Wholesale",
            "subcategory":"Computers",
            "type":"Manufacturing & Wholesale Goods"
        }
    ],
    "sg:phone":"+1 619 303 7728",
    "sg:postcode":"91977",
    "sg:province":"CA",
    "wof:name":"Ms Computers",
    "wof:placetype":"venue"
},
  "geometry": {"coordinates":[-116.983172,32.747811],"type":"Point"}
}