{
  "type": "Feature",
  "properties": {
    "addr:full":"25662 Crown Valley Pkwy Ste H2 Ladera Ranch CA 92694",
    "addr:housenumber":"25662",
    "addr:postcode":"92694",
    "addr:street":"Crown Valley Pkwy Ste H2",
    "iso:country":"US",
    "sg:address":"25662 Crown Valley Pkwy Ste H2",
    "sg:city":"Ladera Ranch",
    "sg:classifiers":[
        {
            "category":"Sports & Exercise",
            "subcategory":"Bicycle Rental",
            "type":"Entertainment"
        }
    ],
    "sg:phone":"+1 949 429 7784",
    "sg:postcode":"92694",
    "sg:province":"CA",
    "sg:tags":[
        "bike"
    ],
    "wof:name":"Ladera & Cyclery",
    "wof:placetype":"venue"
},
  "geometry": {"coordinates":[-117.631114,33.565937],"type":"Point"}
}