{
  "type": "Feature",
  "properties": {
    "iso:country":"US",
    "sg:address":"23812 Via Fabricante",
    "sg:city":"Mission Viejo",
    "sg:classifiers":[
        {
            "category":"Building & Trades",
            "subcategory":"Construction",
            "type":"Services"
        }
    ],
    "sg:phone":"+1 888 302 9633",
    "sg:postcode":"92691",
    "sg:province":"CA",
    "sg:tags":[
        "window",
        "installation"
    ],
    "sg:website":"www.renaissancedoorsandwindows.c...",
    "wof:name":"Renaissance Doors and Windows",
    "wof:placetype":"venue"
},
  "geometry": {"coordinates":[-117.682081,33.616524],"type":"Point"}
}