{
  "type": "Feature",
  "properties": {
    "addr:full":"1310 El Camino Real Ste H San Bruno CA 94066",
    "addr:housenumber":"1310",
    "addr:postcode":"94066",
    "addr:street":"El Camino Real Ste H",
    "iso:country":"US",
    "sg:address":"1310 El Camino Real Ste H",
    "sg:city":"San Bruno",
    "sg:classifiers":[
        {
            "category":"Retail",
            "subcategory":"Laundry & Dry Cleaning",
            "type":"Services"
        }
    ],
    "sg:phone":"+1 650 871 8266",
    "sg:postcode":"94066",
    "sg:province":"CA",
    "wof:name":"Leader Cleaners",
    "wof:placetype":"venue"
},
  "geometry": {"coordinates":[-122.422588,37.640268],"type":"Point"}
}