{
  "type": "Feature",
  "properties": {
    "addr:full":"1224 E Katella Ave Orange CA 92867",
    "addr:housenumber":"1224",
    "addr:postcode":"92867",
    "addr:street":"E Katella Ave",
    "iso:country":"US",
    "sg:address":"1224 E Katella Ave",
    "sg:city":"Orange",
    "sg:classifiers":[
        {
            "category":"Banks & Credit Unions",
            "subcategory":"Bank",
            "type":"Services"
        }
    ],
    "sg:phone":"+1 714 744 6700",
    "sg:postcode":"92867",
    "sg:province":"CA",
    "sg:tags":[
        "loan",
        "real estate"
    ],
    "wof:name":"United American Mortgage",
    "wof:placetype":"venue"
},
  "geometry": {"coordinates":[-117.835919,33.809107],"type":"Point"}
}