{
  "type": "Feature",
  "properties": {
    "addr:full":"168 E Cole Rd Calexico CA 92231",
    "addr:housenumber":"168",
    "addr:postcode":"92231",
    "addr:street":"E Cole Rd",
    "iso:country":"US",
    "sg:address":"168 E Cole Rd",
    "sg:city":"Calexico",
    "sg:classifiers":[
        {
            "category":"Personal",
            "subcategory":"Beauty Salon",
            "type":"Services"
        }
    ],
    "sg:phone":"+1 760 768 9775",
    "sg:postcode":"92231",
    "sg:province":"CA",
    "wof:name":"A New Image",
    "wof:placetype":"venue"
},
  "geometry": {"coordinates":[-115.49613100000001,32.694065],"type":"Point"}
}