{
  "type": "Feature",
  "properties": {
    "addr:full":"724 N Brea Blvd Brea CA 92821",
    "addr:housenumber":"724",
    "addr:postcode":"92821",
    "addr:street":"N Brea Blvd",
    "iso:country":"US",
    "sg:address":"724 N Brea Blvd",
    "sg:city":"Brea",
    "sg:classifiers":[
        {
            "category":"Restaurant",
            "type":"Food & Drink"
        }
    ],
    "sg:phone":"+1 714 255 1178",
    "sg:postcode":"92821",
    "sg:province":"CA",
    "sg:tags":[
        "sushi",
        "bar",
        "japanese"
    ],
    "wof:name":"Shark Sushi",
    "wof:placetype":"venue"
},
  "geometry": {"coordinates":[-117.894417,33.930882],"type":"Point"}
}