{
  "type": "Feature",
  "properties": {
    "addr:full":"242 E Airport Dr San Bernardino CA 92408",
    "addr:housenumber":"242",
    "addr:postcode":"92408",
    "addr:street":"E Airport Dr",
    "iso:country":"US",
    "sg:address":"242 E Airport Dr",
    "sg:city":"San Bernardino",
    "sg:classifiers":[
        {
            "category":"Insurance",
            "subcategory":"Insurance Agent",
            "type":"Services"
        }
    ],
    "sg:phone":"+1 909 884 9224",
    "sg:postcode":"92408",
    "sg:province":"CA",
    "wof:name":"Golden State Mutual Life Ins",
    "wof:placetype":"venue"
},
  "geometry": {"coordinates":[-117.284085,34.067312],"type":"Point"}
}