{
  "type": "Feature",
  "properties": {
    "addr:full":"245 Church St San Francisco CA 94114",
    "addr:housenumber":"245",
    "addr:postcode":"94114",
    "addr:street":"Church St",
    "iso:country":"US",
    "sg:address":"245 Church St",
    "sg:city":"San Francisco",
    "sg:classifiers":[
        {
            "category":"Restaurant",
            "type":"Food & Drink"
        }
    ],
    "sg:phone":"+1 415 621 3020",
    "sg:postcode":"94114",
    "sg:province":"CA",
    "wof:name":"Red Jade Restaurant",
    "wof:placetype":"venue"
},
  "geometry": {"coordinates":[-122.42879000000001,37.766752],"type":"Point"}
}