{
  "type": "Feature",
  "properties": {
    "iso:country":"US",
    "sg:address":"4205 Amapola Way",
    "sg:city":"Sacramento",
    "sg:classifiers":[
        {
            "category":"Utilities",
            "subcategory":"Refuse",
            "type":"Services"
        }
    ],
    "sg:phone":"+1 916 955 0884",
    "sg:postcode":"95823",
    "sg:province":"CA",
    "sg:tags":[
        "garbage",
        "collection"
    ],
    "wof:name":"R & R Hauling",
    "wof:placetype":"venue"
},
  "geometry": {"coordinates":[-121.454067,38.46856],"type":"Point"}
}