{
  "type": "Feature",
  "properties": {
    "iso:country":"US",
    "sg:address":"11717 Lakewood Blvd.",
    "sg:city":"Downey",
    "sg:classifiers":[
        {
            "category":"Real Estate",
            "subcategory":"Real Estate Operator",
            "type":"Services"
        }
    ],
    "sg:phone":"+1 562 861 6197",
    "sg:postcode":"90241",
    "sg:province":"CA",
    "sg:tags":[
        "apartment"
    ],
    "wof:name":"Lakewood Apartments",
    "wof:placetype":"venue"
},
  "geometry": {"coordinates":[-118.128995,33.929411],"type":"Point"}
}