{
  "type": "Feature",
  "properties": {
    "addr:full":"2100 Webster St Ste 329 San Francisco CA 94115",
    "addr:housenumber":"2100",
    "addr:postcode":"94115",
    "addr:street":"Webster St Ste 329",
    "iso:country":"US",
    "sg:address":"2100 Webster St Ste 329",
    "sg:city":"San Francisco",
    "sg:classifiers":[
        {
            "category":"Health Services",
            "subcategory":"Doctor",
            "type":"Services"
        }
    ],
    "sg:phone":"+1 415 749 5779",
    "sg:postcode":"94115",
    "sg:province":"CA",
    "wof:name":"Charles C McDonald, MD",
    "wof:placetype":"venue"
},
  "geometry": {"coordinates":[-122.43248800000001,37.790701],"type":"Point"}
}