{
  "type": "Feature",
  "properties": {
    "addr:full":"6259 de Woody Ave Laton CA 93242",
    "addr:housenumber":"6259",
    "addr:postcode":"93242",
    "addr:street":"De Woody Ave",
    "iso:country":"US",
    "sg:address":"6259 de Woody Ave",
    "sg:city":"Laton",
    "sg:classifiers":[
        {
            "category":"Education",
            "subcategory":"School",
            "type":"Public Place"
        }
    ],
    "sg:phone":"+1 559 922 4015",
    "sg:postcode":"93242",
    "sg:province":"CA",
    "wof:name":"Laton Unified School District",
    "wof:placetype":"venue"
},
  "geometry": {"coordinates":[-119.685537,36.434549],"type":"Point"}
}