{
  "type": "Feature",
  "properties": {
    "iso:country":"US",
    "sg:address":"483 1st St W",
    "sg:city":"Sonoma",
    "sg:classifiers":[
        {
            "category":"Manufacturing",
            "subcategory":"Food",
            "type":"Manufacturing & Wholesale Goods"
        }
    ],
    "sg:phone":"+1 707 935 3848",
    "sg:postcode":"95476",
    "sg:province":"CA",
    "sg:tags":[
        "winery"
    ],
    "wof:name":"Charles Creek Tasting Room",
    "wof:placetype":"venue"
},
  "geometry": {"coordinates":[-122.458989,38.292323],"type":"Point"}
}