{
  "type": "Feature",
  "properties": {
    "addr:full":"2532 E Main St Stockton CA 95205",
    "addr:housenumber":"2532",
    "addr:postcode":"95205",
    "addr:street":"E Main St",
    "iso:country":"US",
    "sg:address":"2532 E Main St",
    "sg:city":"Stockton",
    "sg:classifiers":[
        {
            "category":"Food & Beverages",
            "subcategory":"Meat & Fish",
            "type":"Retail Goods"
        }
    ],
    "sg:phone":"+1 209 946 4051",
    "sg:postcode":"95205",
    "sg:province":"CA",
    "sg:tags":[
        "cutting"
    ],
    "wof:name":"LA Paloma Meat Market",
    "wof:placetype":"venue"
},
  "geometry": {"coordinates":[-121.250905,37.954721],"type":"Point"}
}