{
  "type": "Feature",
  "properties": {
    "addr:full":"15636 Larch Ave Lawndale CA 90260",
    "addr:housenumber":"15636",
    "addr:postcode":"ca 90260",
    "addr:street":"Larch Ave",
    "iso:country":"US",
    "sg:address":"15636 Larch Ave",
    "sg:city":"Lawndale",
    "sg:classifiers":[
        {
            "category":"Shopping",
            "subcategory":"Computers & Home Electronics",
            "type":"Retail Goods"
        }
    ],
    "sg:phone":"+1 310 404 4833",
    "sg:postcode":"90260",
    "sg:province":"CA",
    "sg:tags":[
        "high",
        "equipment-dealers",
        "fidelity",
        "stereophonic",
        "consumer"
    ],
    "wof:name":"Morales TV & Audio Repair",
    "wof:placetype":"venue"
},
  "geometry": {"coordinates":[-118.35030999999999,33.889268],"type":"Point"}
}