{
  "type": "Feature",
  "properties": {
    "addr:full":"420 Alameda del Prado Novato CA 94949",
    "addr:housenumber":"420",
    "addr:postcode":"94949",
    "addr:street":"Alameda Del Prado",
    "iso:country":"US",
    "sg:address":"420 Alameda del Prado",
    "sg:city":"Novato",
    "sg:classifiers":[
        {
            "category":"Real Estate",
            "subcategory":"Real Estate Operator",
            "type":"Services"
        }
    ],
    "sg:phone":"+1 415 883 5666",
    "sg:postcode":"94949",
    "sg:province":"CA",
    "sg:tags":[
        "apartment"
    ],
    "wof:name":"Ignacio Gardens Apartments",
    "wof:placetype":"venue"
},
  "geometry": {"coordinates":[-122.53790600000001,38.063927],"type":"Point"}
}