{
  "type": "Feature",
  "properties": {
    "iso:country":"US",
    "sg:address":"1906 S La Brea Avenue",
    "sg:city":"Los Angeles",
    "sg:classifiers":[
        {
            "category":"Personal",
            "subcategory":"Nail Salon",
            "type":"Services"
        }
    ],
    "sg:phone":"+1 323 939 0121",
    "sg:postcode":"90016",
    "sg:province":"CA",
    "wof:name":"Miny Nails",
    "wof:placetype":"venue"
},
  "geometry": {"coordinates":[-118.347827,34.040074],"type":"Point"}
}