{
  "type": "Feature",
  "properties": {
    "iso:country":"US",
    "sg:address":"400 S Baldwin Ave",
    "sg:city":"Arcadia",
    "sg:classifiers":[
        {
            "category":"Real Estate",
            "subcategory":"Real Estate Operator",
            "type":"Services"
        }
    ],
    "sg:phone":"+1 626 445 3116",
    "sg:postcode":"91007",
    "sg:province":"CA",
    "sg:tags":[
        "building",
        "nonresidential"
    ],
    "wof:name":"Santa Anita Fashion Park",
    "wof:placetype":"venue"
},
  "geometry": {"coordinates":[-118.054255,34.134837],"type":"Point"}
}