{
  "type": "Feature",
  "properties": {
    "iso:country":"US",
    "sg:address":"6250 Telegraph Rd",
    "sg:city":"Ventura",
    "sg:classifiers":[
        {
            "category":"Real Estate",
            "subcategory":"Real Estate Operator",
            "type":"Services"
        }
    ],
    "sg:phone":"+1 805 656 0236",
    "sg:postcode":"93003",
    "sg:province":"CA",
    "sg:tags":[
        "apartment"
    ],
    "wof:name":"Ventura Del Sol",
    "wof:placetype":"venue"
},
  "geometry": {"coordinates":[-119.20961,34.27864],"type":"Point"}
}