{
  "type": "Feature",
  "properties": {
    "addr:full":"25950 Ave 88 Terra Bella CA 93270",
    "addr:housenumber":"25950;88",
    "addr:postcode":"93270",
    "addr:street":"Ave",
    "iso:country":"US",
    "sg:address":"25950 Ave 88",
    "sg:city":"Terra Bella",
    "sg:classifiers":[
        {
            "category":"Wholesale",
            "subcategory":"Non-durable Goods",
            "type":"Manufacturing & Wholesale Goods"
        }
    ],
    "sg:phone":"+1 559 535 8558",
    "sg:postcode":"93270",
    "sg:province":"CA",
    "wof:name":"Sierra Nevada Distribution",
    "wof:placetype":"venue"
},
  "geometry": {"coordinates":[-118.993089,35.949761],"type":"Point"}
}