{
  "type": "Feature",
  "properties": {
    "addr:full":"1212 S Main St Angels Camp CA 95222",
    "addr:housenumber":"1212",
    "addr:postcode":"95222",
    "addr:street":"S Main St",
    "iso:country":"US",
    "sg:address":"1212 S Main St",
    "sg:city":"Angels Camp",
    "sg:classifiers":[
        {
            "category":"Insurance",
            "subcategory":"Health Insurance",
            "type":"Services"
        }
    ],
    "sg:phone":"+1 209 736 4666",
    "sg:postcode":"95222",
    "sg:province":"CA",
    "sg:tags":[
        "plan"
    ],
    "wof:name":"Arrowhead Insurance",
    "wof:placetype":"venue"
},
  "geometry": {"coordinates":[-120.540351,38.069598],"type":"Point"}
}