{
  "type": "Feature",
  "properties": {
    "iso:country":"US",
    "sg:address":"2512 River Plaza Dr",
    "sg:city":"Sacramento",
    "sg:classifiers":[
        {
            "category":"Real Estate",
            "subcategory":"Real Estate Agent",
            "type":"Services"
        }
    ],
    "sg:phone":"+1 916 921 1467",
    "sg:postcode":"95833",
    "sg:province":"CA",
    "wof:name":"Voit Real Estate Services",
    "wof:placetype":"venue"
},
  "geometry": {"coordinates":[-121.52073799999999,38.607428],"type":"Point"}
}