{
  "type": "Feature",
  "properties": {
    "addr:full":"15641 Loma Vista Ave Los Gatos CA 95032",
    "addr:housenumber":"15641",
    "addr:postcode":"95032",
    "addr:street":"Loma Vista Ave",
    "iso:country":"US",
    "sg:address":"15641 Loma Vista Ave",
    "sg:city":"Los Gatos",
    "sg:classifiers":[
        {
            "category":"Professional",
            "type":"Services"
        }
    ],
    "sg:phone":"+1 408 358 3280",
    "sg:postcode":"95032",
    "sg:province":"CA",
    "wof:name":"17 West Inc",
    "wof:placetype":"venue"
},
  "geometry": {"coordinates":[-121.95053,37.241185],"type":"Point"}
}