{
  "type": "Feature",
  "properties": {
    "addr:full":"2910 E Ana St E Rancho Dmngz CA 90221",
    "addr:housenumber":"2910",
    "addr:postcode":"90221",
    "addr:street":"E Ana St E",
    "iso:country":"US",
    "sg:address":"2910 E Ana St",
    "sg:city":"E Rancho Dmngz",
    "sg:classifiers":[
        {
            "category":"Freight",
            "type":"Transportation"
        }
    ],
    "sg:phone":"+1 310 830 4550",
    "sg:postcode":"90221",
    "sg:province":"CA",
    "sg:tags":[
        "warehouse",
        "self",
        "storage"
    ],
    "wof:name":"Advanced Cargo Svc",
    "wof:placetype":"venue"
},
  "geometry": {"coordinates":[-118.207522,33.861282],"type":"Point"}
}