{
  "type": "Feature",
  "properties": {
    "iso:country":"US",
    "sg:address":"2346 Newport Blvd Ste A5",
    "sg:city":"Costa Mesa",
    "sg:classifiers":[
        {
            "category":"Arts & Performance",
            "subcategory":"Arts Center",
            "type":"Entertainment"
        },
        {
            "category":"Education",
            "subcategory":"School",
            "type":"Public Place"
        }
    ],
    "sg:phone":"+1 949 646 6042",
    "sg:postcode":"92627",
    "sg:province":"CA",
    "sg:tags":[
        "performing"
    ],
    "sg:website":"www.newdaymusicstudios.com",
    "wof:name":"New Day Music Studios",
    "wof:placetype":"venue"
},
  "geometry": {"coordinates":[-117.903728,33.655745],"type":"Point"}
}