{
  "type": "Feature",
  "properties": {
    "addr:full":"2355 Ocean Ave San Francisco CA 94127",
    "addr:housenumber":"2355",
    "addr:postcode":"94127",
    "addr:street":"Ocean Ave",
    "iso:country":"US",
    "sg:address":"2355 Ocean Ave",
    "sg:city":"San Francisco",
    "sg:classifiers":[
        {
            "category":"Recreation",
            "type":"Entertainment"
        }
    ],
    "sg:phone":"+1 415 239 9602",
    "sg:postcode":"94127",
    "sg:province":"CA",
    "sg:tags":[
        "club",
        "membership"
    ],
    "wof:name":"Concordia Sport Club Inc",
    "wof:placetype":"venue"
},
  "geometry": {"coordinates":[-122.468485,37.729288],"type":"Point"}
}