{
  "type": "Feature",
  "properties": {
    "iso:country":"US",
    "sg:address":"12760 High Bluff Drive",
    "sg:city":"San Diego",
    "sg:classifiers":[
        {
            "category":"Professional",
            "subcategory":"Lawyer & Legal Services",
            "type":"Services"
        }
    ],
    "sg:phone":"+1 858 259 5009",
    "sg:postcode":"92130",
    "sg:province":"CA",
    "wof:name":"Wirtz Hellencamp Llp",
    "wof:placetype":"venue"
},
  "geometry": {"coordinates":[-117.23959600000001,32.949904],"type":"Point"}
}