{
  "type": "Feature",
  "properties": {
    "iso:country":"US",
    "sg:address":"62 Kim Louise Dr",
    "sg:city":"Campbell",
    "sg:classifiers":[
        {
            "category":"Professional",
            "type":"Services"
        }
    ],
    "sg:phone":"+1 408 378 6850",
    "sg:postcode":"95008",
    "sg:province":"CA",
    "wof:name":"Etiquette Etiquette",
    "wof:placetype":"venue"
},
  "geometry": {"coordinates":[-121.974553,37.285672],"type":"Point"}
}