{
  "type": "Feature",
  "properties": {
    "addr:full":"1237 E Main St Alhambra CA 91801",
    "addr:housenumber":"1237",
    "addr:postcode":"91801",
    "addr:street":"E Main St",
    "iso:country":"US",
    "sg:address":"1237 E Main St",
    "sg:city":"Alhambra",
    "sg:classifiers":[
        {
            "category":"Health Services",
            "subcategory":"Doctor",
            "type":"Services"
        }
    ],
    "sg:phone":"+1 626 576 0800",
    "sg:postcode":"91801",
    "sg:province":"CA",
    "sg:tags":[
        "family",
        "practice",
        "internal",
        "gynecologist",
        "medicine",
        "obstetrician"
    ],
    "wof:name":"Aldahl Denise G MD Alhambra Medical Clinic",
    "wof:placetype":"venue"
},
  "geometry": {"coordinates":[-118.113998,34.1012],"type":"Point"}
}