{
  "type": "Feature",
  "properties": {
    "iso:country":"US",
    "sg:address":"300 Water St",
    "sg:city":"Petaluma",
    "sg:classifiers":[
        {
            "category":"Manufacturing",
            "subcategory":"Furniture",
            "type":"Manufacturing & Wholesale Goods"
        }
    ],
    "sg:phone":"+1 707 782 0736",
    "sg:postcode":"94952",
    "sg:province":"CA",
    "sg:tags":[
        "builder",
        "designer",
        "custom"
    ],
    "wof:name":"Latour Barry",
    "wof:placetype":"venue"
},
  "geometry": {"coordinates":[-122.640694,38.236492],"type":"Point"}
}