{
  "type": "Feature",
  "properties": {
    "addr:full":"923 Santee St Los Angeles CA 90015",
    "addr:housenumber":"923",
    "addr:postcode":"90015",
    "addr:street":"Santee St",
    "iso:country":"US",
    "sg:address":"923 Santee St",
    "sg:city":"Los Angeles",
    "sg:classifiers":[
        {
            "category":"Professional",
            "subcategory":"Employment Agencies",
            "type":"Services"
        }
    ],
    "sg:phone":"+1 213 627 9695",
    "sg:postcode":"90015",
    "sg:province":"CA",
    "sg:tags":[
        "consultant",
        "search",
        "executive"
    ],
    "wof:name":"Rhinestone Express",
    "wof:placetype":"venue"
},
  "geometry": {"coordinates":[-118.254442,34.039436],"type":"Point"}
}