{
  "type": "Feature",
  "properties": {
    "addr:full":"24496 Valle del Oro Newhall CA 91321",
    "addr:housenumber":"24496",
    "addr:postcode":"91321",
    "addr:street":"Valle Del Oro",
    "iso:country":"US",
    "sg:address":"24496 Valle del Oro",
    "sg:city":"Newhall",
    "sg:classifiers":[
        {
            "category":"Building & Trades",
            "subcategory":"Construction",
            "type":"Services"
        }
    ],
    "sg:phone":"+1 661 287 9905",
    "sg:postcode":"91321",
    "sg:province":"CA",
    "sg:tags":[
        "painter"
    ],
    "wof:name":"Joe Chung Painting",
    "wof:placetype":"venue"
},
  "geometry": {"coordinates":[-118.508607,34.37738],"type":"Point"}
}