{
  "type": "Feature",
  "properties": {
    "iso:country":"US",
    "sg:address":"800 S Broadway",
    "sg:city":"Walnut Creek",
    "sg:classifiers":[
        {
            "category":"Professional",
            "type":"Services"
        }
    ],
    "sg:phone":"+1 925 938 8290",
    "sg:postcode":"94596",
    "sg:province":"CA",
    "sg:tags":[
        "establishment"
    ],
    "wof:name":"Stanley M Piller & Assoc",
    "wof:placetype":"venue"
},
  "geometry": {"coordinates":[-122.058686,37.894199],"type":"Point"}
}