{
  "type": "Feature",
  "properties": {
    "addr:full":"965 Santa Rosa Ave Santa Rosa CA 95404",
    "addr:housenumber":"965",
    "addr:postcode":"95404",
    "addr:street":"Santa Rosa Ave",
    "iso:country":"US",
    "sg:address":"965 Santa Rosa Ave",
    "sg:city":"Santa Rosa",
    "sg:classifiers":[
        {
            "category":"Autos & Motor Vehicles",
            "subcategory":"Automobile Sales",
            "type":"Retail Goods"
        }
    ],
    "sg:phone":"+1 707 376 1100",
    "sg:postcode":"95404",
    "sg:province":"CA",
    "sg:tags":[
        "full",
        "dealership"
    ],
    "wof:name":"Ukiah Mitsubishi",
    "wof:placetype":"venue"
},
  "geometry": {"coordinates":[-122.71253900000001,38.428265],"type":"Point"}
}