{
  "type": "Feature",
  "properties": {
    "addr:full":"21500 Lassen St Chatsworth CA 91311",
    "addr:housenumber":"21500",
    "addr:postcode":"91311",
    "addr:street":"Lassen St",
    "iso:country":"US",
    "sg:address":"21500 Lassen St",
    "sg:city":"Chatsworth",
    "sg:classifiers":[
        {
            "category":"Professional",
            "subcategory":"Management & Consulting",
            "type":"Services"
        }
    ],
    "sg:phone":"+1 818 709 5311",
    "sg:postcode":"91311",
    "sg:province":"CA",
    "sg:tags":[
        "construction"
    ],
    "wof:name":"LRO Tile",
    "wof:placetype":"venue"
},
  "geometry": {"coordinates":[-118.599102,34.249899],"type":"Point"}
}