{
  "type": "Feature",
  "properties": {
    "addr:full":"7990 Pasadena Ave La Mesa CA 91941",
    "addr:housenumber":"7990",
    "addr:postcode":"91941",
    "addr:street":"Pasadena Ave",
    "iso:country":"US",
    "sg:address":"7990 Pasadena Ave",
    "sg:city":"La Mesa",
    "sg:classifiers":[
        {
            "category":"Organizations",
            "subcategory":"Non-profit Organization",
            "type":"Services"
        }
    ],
    "sg:phone":"+1 619 469 6277",
    "sg:postcode":"91941",
    "sg:province":"CA",
    "sg:tags":[
        "social"
    ],
    "wof:name":"Aircraft Carrier Memorial",
    "wof:placetype":"venue"
},
  "geometry": {"coordinates":[-117.025448,32.760071],"type":"Point"}
}