{
  "type": "Feature",
  "properties": {
    "addr:full":"1085 Macarthur Blvd San Leandro CA 94577",
    "addr:housenumber":"1085",
    "addr:postcode":"94577",
    "addr:street":"Macarthur Blvd",
    "iso:country":"US",
    "sg:address":"1085 Macarthur Blvd",
    "sg:city":"San Leandro",
    "sg:classifiers":[
        {
            "category":"Personal",
            "subcategory":"Beauty Salon",
            "type":"Services"
        }
    ],
    "sg:phone":"+1 510 633 3049",
    "sg:postcode":"94577",
    "sg:province":"CA",
    "wof:name":"Plushchic' Styles & Cuts",
    "wof:placetype":"venue"
},
  "geometry": {"coordinates":[-122.139358,37.731085],"type":"Point"}
}