{
  "type": "Feature",
  "properties": {
    "iso:country":"US",
    "sg:address":"3775 Esplanade",
    "sg:city":"Chico",
    "sg:classifiers":[
        {
            "category":"Shopping",
            "subcategory":"Gifts & Souvenirs",
            "type":"Retail Goods"
        }
    ],
    "sg:phone":"+1 530 891 1564",
    "sg:postcode":"95973",
    "sg:province":"CA",
    "wof:name":"Cox Country Crafts & Gifts S",
    "wof:placetype":"venue"
},
  "geometry": {"coordinates":[-121.892651,39.786896],"type":"Point"}
}