{
  "type": "Feature",
  "properties": {
    "addr:full":"17655 Hawthorne Ave Fontana CA 92335",
    "addr:housenumber":"17655",
    "addr:postcode":"92335",
    "addr:street":"Hawthorne Ave",
    "iso:country":"US",
    "sg:address":"17655 Hawthorne Ave",
    "sg:city":"Fontana",
    "sg:classifiers":[
        {
            "category":"Wholesale",
            "subcategory":"Hardware",
            "type":"Manufacturing & Wholesale Goods"
        }
    ],
    "sg:phone":"+1 909 822 3643",
    "sg:postcode":"92335",
    "sg:province":"CA",
    "sg:tags":[
        "equipment",
        "energy",
        "solar"
    ],
    "wof:name":"Sunbelt Solar Of California",
    "wof:placetype":"venue"
},
  "geometry": {"coordinates":[-117.42026799999999,34.08127],"type":"Point"}
}