{
  "type": "Feature",
  "properties": {
    "addr:full":"14392 Acacia Dr Tustin CA 92780",
    "addr:housenumber":"14392",
    "addr:postcode":"92780",
    "addr:street":"Acacia Dr",
    "iso:country":"US",
    "sg:address":"14392 Acacia Dr",
    "sg:city":"Tustin",
    "sg:classifiers":[
        {
            "category":"Building & Trades",
            "subcategory":"Landscaping Services",
            "type":"Services"
        }
    ],
    "sg:phone":"+1 714 832 6546",
    "sg:postcode":"92780",
    "sg:province":"CA",
    "sg:tags":[
        "consultant",
        "lawn",
        "designer",
        "landscape",
        "contractor"
    ],
    "wof:name":"Davis Landscape",
    "wof:placetype":"venue"
},
  "geometry": {"coordinates":[-117.827003,33.753899],"type":"Point"}
}