{
  "type": "Feature",
  "properties": {
    "addr:full":"6423 Colby St Oakland CA 94618",
    "addr:housenumber":"6423",
    "addr:postcode":"94618",
    "addr:street":"Colby St",
    "iso:country":"US",
    "sg:address":"6423 Colby St",
    "sg:city":"Oakland",
    "sg:classifiers":[
        {
            "category":"Organizations",
            "subcategory":"Non-profit Organization",
            "type":"Services"
        }
    ],
    "sg:phone":"+1 510 658 1380",
    "sg:postcode":"94618",
    "sg:province":"CA",
    "sg:tags":[
        "service/non-profit",
        "community"
    ],
    "sg:website":"www.oakehouse.org",
    "wof:name":"Oakland Elizabeth House",
    "wof:placetype":"venue"
},
  "geometry": {"coordinates":[-122.25718000000001,37.851421],"type":"Point"}
}