{
  "type": "Feature",
  "properties": {
    "iso:country":"US",
    "sg:address":"13920 Foothill Blvd",
    "sg:city":"Sylmar",
    "sg:classifiers":[
        {
            "category":"Health Services",
            "subcategory":"Chiropractor",
            "type":"Services"
        }
    ],
    "sg:phone":"+1 818 367 1851",
    "sg:postcode":"91342",
    "sg:province":"CA",
    "sg:tags":[
        "chiropractic"
    ],
    "wof:name":"Sylmar Chiropractic Offices",
    "wof:placetype":"venue"
},
  "geometry": {"coordinates":[-118.436682,34.312388],"type":"Point"}
}