{
  "type": "Feature",
  "properties": {
    "addr:full":"35 Prado Rd San Luis Obispo CA 93401",
    "addr:housenumber":"35",
    "addr:postcode":"93401",
    "addr:street":"Prado Rd",
    "iso:country":"US",
    "sg:address":"35 Prado Rd",
    "sg:city":"San Luis Obispo",
    "sg:classifiers":[
        {
            "category":"Utilities",
            "subcategory":"Sewage",
            "type":"Services"
        }
    ],
    "sg:phone":"+1 805 781 7241",
    "sg:postcode":"93401",
    "sg:province":"CA",
    "sg:tags":[
        "system",
        "sewerage"
    ],
    "wof:name":"Water Reclamation Facility",
    "wof:placetype":"venue"
},
  "geometry": {"coordinates":[-120.673175,35.256109],"type":"Point"}
}