{
  "type": "Feature",
  "properties": {
    "iso:country":"US",
    "sg:address":"3065 Richmond Pkwy",
    "sg:city":"San Pablo",
    "sg:classifiers":[
        {
            "category":"Wholesale",
            "subcategory":"Medical Equipment & Supplies",
            "type":"Manufacturing & Wholesale Goods"
        }
    ],
    "sg:phone":"+1 510 243 1600",
    "sg:postcode":"94806",
    "sg:province":"CA",
    "sg:tags":[
        "hospital"
    ],
    "wof:name":"Brava Institute",
    "wof:placetype":"venue"
},
  "geometry": {"coordinates":[-122.330155,37.990082],"type":"Point"}
}