{
  "type": "Feature",
  "properties": {
    "addr:full":"598 Avalon St Morro Bay CA 93442",
    "addr:housenumber":"598",
    "addr:postcode":"93442",
    "addr:street":"Avalon St",
    "iso:country":"US",
    "sg:address":"598 Avalon St",
    "sg:city":"Morro Bay",
    "sg:classifiers":[
        {
            "category":"Building & Trades",
            "subcategory":"Construction",
            "type":"Services"
        }
    ],
    "sg:phone":"+1 805 772 1596",
    "sg:postcode":"93442",
    "sg:province":"CA",
    "sg:tags":[
        "contractor"
    ],
    "wof:name":"Luhr Design & Construction",
    "wof:placetype":"venue"
},
  "geometry": {"coordinates":[-120.853246,35.38622],"type":"Point"}
}