{
  "type": "Feature",
  "properties": {
    "iso:country":"US",
    "sg:address":"6900 Airport Blvd",
    "sg:city":"Sacramento",
    "sg:classifiers":[
        {
            "category":"Government",
            "subcategory":"Police Station",
            "type":"Public Place"
        }
    ],
    "sg:phone":"+1 916 874 0675",
    "sg:postcode":"95837",
    "sg:province":"CA",
    "sg:tags":[
        "protection"
    ],
    "wof:name":"Sheriffs Dept",
    "wof:placetype":"venue"
},
  "geometry": {"coordinates":[-121.59434899999999,38.690259],"type":"Point"}
}