{
  "type": "Feature",
  "properties": {
    "addr:full":"10190 Systems Pkwy - Suite 150 Sacramento CA 95827",
    "addr:housenumber":"10190",
    "addr:postcode":"95827",
    "addr:street":"Systems Pkwy Suite 150",
    "iso:country":"US",
    "sg:address":"10190 Systems Pkwy - Suite 150",
    "sg:city":"Sacramento",
    "sg:classifiers":[
        {
            "category":"Manufacturing",
            "subcategory":"Chemicals & Compounds",
            "type":"Manufacturing & Wholesale Goods"
        },
        {
            "category":"Animal Shelter",
            "type":"Public Place"
        },
        {
            "category":"Building & Trades",
            "subcategory":"Pest Control",
            "type":"Services"
        }
    ],
    "sg:phone":"+1 866 574 1660",
    "sg:postcode":"95827",
    "sg:province":"CA",
    "sg:tags":[
        "industrial",
        "supply",
        "services-commercial",
        "termite",
        "bee",
        "equipment",
        "mothproofing",
        "removal"
    ],
    "sg:website":"http://signup.orkin.com/orkin/res/fun-Standard-pph_pcb_tph_tsch.aspx?cm_mmc=yahoo-yellowpages-_-yahoo-local-_-WEBYL-_-_&utm_source=yahoo-yellowpages&utm_content=yahoo-local&utm_medium=internet-yellow-pages&utm_campaign=WEBYL",
    "wof:name":"Orkin Pest & Termite Control",
    "wof:placetype":"venue"
},
  "geometry": {"coordinates":[-121.31512499999999,38.564114],"type":"Point"}
}