{
  "type": "Feature",
  "properties": {
    "addr:full":"22730 Rancho Palomares Pl Castro Valley CA 94552",
    "addr:housenumber":"22730",
    "addr:postcode":"94552",
    "addr:street":"Rancho Palomares Pl",
    "iso:country":"US",
    "sg:address":"22730 Rancho Palomares Pl",
    "sg:city":"Castro Valley",
    "sg:classifiers":[
        {
            "category":"Railroad",
            "type":"Transportation"
        }
    ],
    "sg:phone":"+1 510 728 0422",
    "sg:postcode":"94552",
    "sg:province":"CA",
    "sg:tags":[
        "operator",
        "line"
    ],
    "wof:name":"CSX",
    "wof:placetype":"venue"
},
  "geometry": {"coordinates":[-122.041084,37.691748],"type":"Point"}
}