{
  "type": "Feature",
  "properties": {
    "iso:country":"US",
    "sg:address":"11467 Rosecrans Ave",
    "sg:city":"Norwalk",
    "sg:classifiers":[
        {
            "category":"Professional",
            "subcategory":"Accounting & Tax Preparation",
            "type":"Services"
        }
    ],
    "sg:phone":"+1 562 929 9936",
    "sg:postcode":"90650",
    "sg:province":"CA",
    "sg:tags":[
        "return",
        "filing"
    ],
    "wof:name":"H & R Block Tax Svc",
    "wof:placetype":"venue"
},
  "geometry": {"coordinates":[-118.089333,33.902178],"type":"Point"}
}