{
  "type": "Feature",
  "properties": {
    "addr:full":"Standard Pacific Homes 10001 Leavesly Trl Santee CA 92071",
    "addr:housenumber":"10001",
    "addr:postcode":"92071",
    "addr:street":"Leavesly Trl",
    "iso:country":"US",
    "sg:address":"Standard Pacific Homes 10001 Leavesly Trl",
    "sg:city":"Santee",
    "sg:classifiers":[
        {
            "category":"Real Estate",
            "subcategory":"Real Estate Agent",
            "type":"Services"
        }
    ],
    "sg:phone":"+1 619 328 0649",
    "sg:postcode":"92071",
    "sg:province":"CA",
    "sg:website":"www.standardpacifichomes.com",
    "wof:name":"Stoney Creek at Riverwalk",
    "wof:placetype":"venue"
},
  "geometry": {"coordinates":[-116.97954900000001,32.852254],"type":"Point"}
}