{
  "type": "Feature",
  "properties": {
    "iso:country":"US",
    "sg:address":"43723 20th St W",
    "sg:city":"Lancaster",
    "sg:classifiers":[
        {
            "category":"Insurance",
            "subcategory":"Insurance Agent",
            "type":"Services"
        }
    ],
    "sg:phone":"+1 661 942 6755",
    "sg:postcode":"93534",
    "sg:province":"CA",
    "sg:website":"www.gotlife.net",
    "wof:name":"Keene-Ulberg Insurance Svc",
    "wof:placetype":"venue"
},
  "geometry": {"coordinates":[-118.165686,34.677862],"type":"Point"}
}