{
  "type": "Feature",
  "properties": {
    "addr:full":"29826 Wilhite Ln Valley Center CA 92082",
    "addr:housenumber":"29826",
    "addr:postcode":"92082",
    "addr:street":"Wilhite Ln",
    "iso:country":"US",
    "sg:address":"29826 Wilhite Ln",
    "sg:city":"Valley Center",
    "sg:classifiers":[
        {
            "category":"Professional",
            "subcategory":"Accounting & Tax Preparation",
            "type":"Services"
        }
    ],
    "sg:phone":"+1 760 746 5553",
    "sg:postcode":"92082",
    "sg:province":"CA",
    "sg:tags":[
        "accountant"
    ],
    "wof:name":"Daniel Asmus CPA",
    "wof:placetype":"venue"
},
  "geometry": {"coordinates":[-117.01469899999999,33.2555],"type":"Point"}
}