{
  "type": "Feature",
  "properties": {
    "iso:country":"US",
    "sg:address":"8424 Telegraph Road",
    "sg:city":"Downey",
    "sg:classifiers":[
        {
            "category":"Personal",
            "subcategory":"Barber",
            "type":"Services"
        }
    ],
    "sg:phone":"+1 562 928 0880",
    "sg:postcode":"90240",
    "sg:province":"CA",
    "wof:name":"Danny's Barber Shop",
    "wof:placetype":"venue"
},
  "geometry": {"coordinates":[-118.112105,33.962737],"type":"Point"}
}