{
  "type": "Feature",
  "properties": {
    "iso:country":"US",
    "sg:address":"1407 Foothill Blvd",
    "sg:city":"La Verne",
    "sg:classifiers":[
        {
            "category":"Professional",
            "type":"Services"
        }
    ],
    "sg:phone":"+1 909 593 2620",
    "sg:postcode":"91750",
    "sg:province":"CA",
    "wof:name":"West Coast Waterfeatures",
    "wof:placetype":"venue"
},
  "geometry": {"coordinates":[-117.77580500000001,34.116921],"type":"Point"}
}