{
  "type": "Feature",
  "properties": {
    "addr:full":"3320 Ave 393 Kingsburg CA 93631",
    "addr:housenumber":"3320",
    "addr:postcode":"93631",
    "addr:street":"Ave 393",
    "iso:country":"US",
    "sg:address":"3320 Ave 393",
    "sg:city":"Kingsburg",
    "sg:classifiers":[
        {
            "category":"Farming",
            "subcategory":"Livestock Farm",
            "type":"Manufacturing & Wholesale Goods"
        }
    ],
    "sg:phone":"+1 559 897 1389",
    "sg:postcode":"93631",
    "sg:province":"CA",
    "sg:tags":[
        "specialty",
        "animal"
    ],
    "wof:name":"Marilyn's Birds & Things",
    "wof:placetype":"venue"
},
  "geometry": {"coordinates":[-119.5106,36.505182],"type":"Point"}
}