{
  "type": "Feature",
  "properties": {
    "addr:full":"11426 Old River School Rd Downey CA 90241",
    "addr:housenumber":"11426",
    "addr:postcode":"90241",
    "addr:street":"Old;School Rd",
    "iso:country":"US",
    "sg:address":"11426 Old River School Rd",
    "sg:city":"Downey",
    "sg:classifiers":[
        {
            "category":"Professional",
            "subcategory":"Computer Services",
            "type":"Services"
        }
    ],
    "sg:phone":"+1 562 927 7554",
    "sg:postcode":"90241",
    "sg:province":"CA",
    "sg:tags":[
        "repair"
    ],
    "wof:name":"Micro Computer Services",
    "wof:placetype":"venue"
},
  "geometry": {"coordinates":[-118.149568,33.946153],"type":"Point"}
}