{
  "type": "Feature",
  "properties": {
    "addr:full":"2100 E 25th St Los Angeles CA 90058",
    "addr:housenumber":"2100",
    "addr:postcode":"90058",
    "addr:street":"E 25Th St",
    "iso:country":"US",
    "sg:address":"2100 E 25th St",
    "sg:city":"Los Angeles",
    "sg:classifiers":[
        {
            "category":"Manufacturing",
            "subcategory":"Apparel",
            "type":"Manufacturing & Wholesale Goods"
        }
    ],
    "sg:phone":"+1 323 585 3133",
    "sg:postcode":"90058",
    "sg:province":"CA",
    "sg:tags":[
        "clothing"
    ],
    "wof:name":"ZRO",
    "wof:placetype":"venue"
},
  "geometry": {"coordinates":[-118.233113,34.014713],"type":"Point"}
}