{
  "type": "Feature",
  "properties": {
    "iso:country":"US",
    "sg:address":"18260 Fairfax Ave",
    "sg:city":"Lemoore",
    "sg:classifiers":[
        {
            "category":"Farming",
            "subcategory":"Dairy Farm",
            "type":"Manufacturing & Wholesale Goods"
        },
        {
            "category":"Farming",
            "subcategory":"Farm",
            "type":"Manufacturing & Wholesale Goods"
        },
        {
            "category":"Food & Beverages",
            "subcategory":"Dairy",
            "type":"Retail Goods"
        }
    ],
    "sg:phone":"+1 559 924 3136",
    "sg:postcode":"93245",
    "sg:province":"CA",
    "sg:tags":[
        "product"
    ],
    "wof:name":"Mendes & Toste Dairy",
    "wof:placetype":"venue"
},
  "geometry": {"coordinates":[-119.789957,36.34977],"type":"Point"}
}