{
  "type": "Feature",
  "properties": {
    "iso:country":"US",
    "sg:address":"7075 Cutting Blvd",
    "sg:city":"El Cerrito",
    "sg:classifiers":[
        {
            "category":"Organizations",
            "subcategory":"Religious Organization",
            "type":"Services"
        }
    ],
    "sg:phone":"+1 510 234 0110",
    "sg:postcode":"94530",
    "sg:province":"CA",
    "sg:tags":[
        "church"
    ],
    "wof:name":"Mira Vista United Church",
    "wof:placetype":"venue"
},
  "geometry": {"coordinates":[-122.311105,37.931665],"type":"Point"}
}