{
  "type": "Feature",
  "properties": {
    "iso:country":"US",
    "sg:address":"3233 N Chestnut Ave",
    "sg:city":"Fresno",
    "sg:classifiers":[
        {
            "category":"Wholesale",
            "subcategory":"Non-durable Goods",
            "type":"Manufacturing & Wholesale Goods"
        }
    ],
    "sg:phone":"+1 559 225 4261",
    "sg:postcode":"93726",
    "sg:province":"CA",
    "wof:name":"Diamond Exports",
    "wof:placetype":"venue"
},
  "geometry": {"coordinates":[-119.736339,36.779795],"type":"Point"}
}