{
  "type": "Feature",
  "properties": {
    "addr:full":"253 Blanchard Rd El Cajon CA 92020",
    "addr:housenumber":"253",
    "addr:postcode":"92020",
    "addr:street":"Blanchard Rd",
    "iso:country":"US",
    "sg:address":"253 Blanchard Rd",
    "sg:city":"El Cajon",
    "sg:classifiers":[
        {
            "category":"Building & Trades",
            "subcategory":"Construction",
            "type":"Services"
        }
    ],
    "sg:phone":"+1 619 466 3115",
    "sg:postcode":"92020",
    "sg:province":"CA",
    "sg:tags":[
        "fire",
        "restoration",
        "damage"
    ],
    "sg:website":"www.nettracing.com",
    "wof:name":"California Deflooding & Carpet",
    "wof:placetype":"venue"
},
  "geometry": {"coordinates":[-116.998802,32.795549],"type":"Point"}
}