{
  "type": "Feature",
  "properties": {
    "iso:country":"US",
    "sg:address":"3546 Highland Dr",
    "sg:city":"Carlsbad",
    "sg:classifiers":[
        {
            "category":"Building & Trades",
            "subcategory":"Construction",
            "type":"Services"
        }
    ],
    "sg:phone":"+1 760 434 4493",
    "sg:postcode":"92008",
    "sg:province":"CA",
    "sg:tags":[
        "stonework"
    ],
    "wof:name":"Stone Imagery",
    "wof:placetype":"venue"
},
  "geometry": {"coordinates":[-117.333247,33.159356],"type":"Point"}
}