{
  "type": "Feature",
  "properties": {
    "addr:full":"455 W 20th Ave San Mateo CA 94403",
    "addr:housenumber":"455",
    "addr:postcode":"94403",
    "addr:street":"W 20Th Ave",
    "iso:country":"US",
    "sg:address":"455 W 20th Ave",
    "sg:city":"San Mateo",
    "sg:classifiers":[
        {
            "category":"Organizations",
            "subcategory":"Religious Organization",
            "type":"Services"
        }
    ],
    "sg:phone":"+1 650 358 1569",
    "sg:postcode":"94403",
    "sg:province":"CA",
    "sg:tags":[
        "clergy"
    ],
    "wof:name":"Raymond Zohlen",
    "wof:placetype":"venue"
},
  "geometry": {"coordinates":[-122.318136,37.546175],"type":"Point"}
}