{
  "type": "Feature",
  "properties": {
    "addr:full":"8140 Sheldon Rd Elk Grove CA 95758",
    "addr:housenumber":"8140",
    "addr:postcode":"95758",
    "addr:street":"Sheldon Rd",
    "iso:country":"US",
    "sg:address":"8140 Sheldon Rd",
    "sg:city":"Elk Grove",
    "sg:classifiers":[
        {
            "category":"Restaurant",
            "type":"Food & Drink"
        }
    ],
    "sg:menulink":"http://www.allmenus.com/ca/sacramento/171360-carls-jr/menu/",
    "sg:phone":"+1 916 681 8923",
    "sg:postcode":"95758",
    "sg:province":"CA",
    "sg:tags":[
        "burger",
        "american"
    ],
    "wof:name":"Carl's Jr.",
    "wof:placetype":"venue"
},
  "geometry": {"coordinates":[-121.404652,38.437892],"type":"Point"}
}