{
  "type": "Feature",
  "properties": {
    "iso:country":"US",
    "sg:address":"670 S Pine St",
    "sg:city":"Madera",
    "sg:classifiers":[
        {
            "category":"Building & Trades",
            "subcategory":"Construction",
            "type":"Services"
        }
    ],
    "sg:phone":"+1 559 673 0074",
    "sg:postcode":"93637",
    "sg:province":"CA",
    "sg:tags":[
        "roofing",
        "contractor"
    ],
    "sg:website":"www.centralcoatingcompany.com",
    "wof:name":"Central Coating Co",
    "wof:placetype":"venue"
},
  "geometry": {"coordinates":[-120.074043,36.95146],"type":"Point"}
}