{
  "type": "Feature",
  "properties": {
    "addr:full":"400 S Victory Blvd Burbank CA 91502",
    "addr:housenumber":"400",
    "addr:postcode":"91502",
    "addr:street":"S Victory Blvd",
    "iso:country":"US",
    "sg:address":"400 S Victory Blvd",
    "sg:city":"Burbank",
    "sg:classifiers":[
        {
            "category":"Communications",
            "subcategory":"Film & Video Production",
            "type":"Services"
        }
    ],
    "sg:phone":"+1 818 848 0240",
    "sg:postcode":"91502",
    "sg:province":"CA",
    "sg:tags":[
        "motion",
        "picture",
        "studio",
        "producer"
    ],
    "sg:website":"www.rpgproductions.com",
    "wof:name":"RPG Film & Video Inc",
    "wof:placetype":"venue"
},
  "geometry": {"coordinates":[-118.314564,34.170184],"type":"Point"}
}