{
  "type": "Feature",
  "properties": {
    "addr:full":"1760 Ventura Blvd Camarillo CA 93010",
    "addr:housenumber":"1760",
    "addr:postcode":"93010",
    "addr:street":"Ventura Blvd",
    "iso:country":"US",
    "sg:address":"1760 Ventura Blvd",
    "sg:city":"Camarillo",
    "sg:classifiers":[
        {
            "category":"Home & Garden",
            "subcategory":"Carpets & Floor Coverings",
            "type":"Retail Goods"
        }
    ],
    "sg:phone":"+1 805 484 0933",
    "sg:postcode":"93010",
    "sg:province":"CA",
    "sg:tags":[
        "dealer",
        "rug"
    ],
    "wof:name":"Abbey Carpet Outlet",
    "wof:placetype":"venue"
},
  "geometry": {"coordinates":[-119.04738500000001,34.217231],"type":"Point"}
}