{
  "type": "Feature",
  "properties": {
    "iso:country":"US",
    "sg:address":"10690 Victor Pl",
    "sg:city":"Grass Valley",
    "sg:classifiers":[
        {
            "category":"Shopping",
            "subcategory":"Computers & Home Electronics",
            "type":"Retail Goods"
        }
    ],
    "sg:phone":"+1 530 477 6316",
    "sg:postcode":"95945",
    "sg:province":"CA",
    "wof:name":"Compcad",
    "wof:placetype":"venue"
},
  "geometry": {"coordinates":[-121.101849,39.217414],"type":"Point"}
}