{
  "type": "Feature",
  "properties": {
    "addr:full":"604 Sonora Ave Glendale CA 91201",
    "addr:housenumber":"604",
    "addr:postcode":"91201",
    "addr:street":"Sonora Ave",
    "iso:country":"US",
    "sg:address":"604 Sonora Ave",
    "sg:city":"Glendale",
    "sg:classifiers":[
        {
            "category":"Professional",
            "subcategory":"Employment Agencies",
            "type":"Services"
        }
    ],
    "sg:phone":"+1 818 502 5800",
    "sg:postcode":"91201",
    "sg:province":"CA",
    "sg:tags":[
        "opportunity"
    ],
    "sg:website":"www.teachersonreserve.com",
    "wof:name":"Teachers On Reserve",
    "wof:placetype":"venue"
},
  "geometry": {"coordinates":[-118.292254,34.161982],"type":"Point"}
}