{
  "type": "Feature",
  "properties": {
    "addr:full":"420 S Beverly Dr Ste 207 Beverly Hills CA 90212",
    "addr:housenumber":"420",
    "addr:postcode":"90212",
    "addr:street":"S Beverly Dr Ste 207;Hills Ca",
    "iso:country":"US",
    "sg:address":"420 S Beverly Dr Ste 207",
    "sg:city":"Beverly Hills",
    "sg:classifiers":[
        {
            "category":"Health Services",
            "subcategory":"Clinic",
            "type":"Services"
        }
    ],
    "sg:phone":"+1 310 474 4949",
    "sg:postcode":"90212",
    "sg:province":"CA",
    "sg:tags":[
        "counseling",
        "mental"
    ],
    "sg:website":"www.omidcounseling.com",
    "wof:name":"Sarah Omid, MFT",
    "wof:placetype":"venue"
},
  "geometry": {"coordinates":[-118.39750100000001,34.058748],"type":"Point"}
}