{
  "type": "Feature",
  "properties": {
    "addr:full":"10300 Lower Azusa Rd El Monte CA 91731",
    "addr:housenumber":"10300",
    "addr:postcode":"91731",
    "addr:street":"Lower Azusa Rd",
    "iso:country":"US",
    "sg:address":"10300 Lower Azusa Rd",
    "sg:city":"El Monte",
    "sg:classifiers":[
        {
            "category":"Restaurant",
            "type":"Food & Drink"
        }
    ],
    "sg:phone":"+1 626 442 7923",
    "sg:postcode":"91731",
    "sg:province":"CA",
    "sg:tags":[
        "pizza"
    ],
    "wof:name":"SIR Pizza'n'chicken",
    "wof:placetype":"venue"
},
  "geometry": {"coordinates":[-118.04299899999999,34.091499],"type":"Point"}
}