{
  "type": "Feature",
  "properties": {
    "addr:full":"3125 19th St Bakersfield CA 93301",
    "addr:housenumber":"3125",
    "addr:postcode":"93301",
    "addr:street":"19Th St",
    "iso:country":"US",
    "sg:address":"3125 19th St",
    "sg:city":"Bakersfield",
    "sg:classifiers":[
        {
            "category":"Insurance",
            "subcategory":"Insurance Agent",
            "type":"Services"
        }
    ],
    "sg:phone":"+1 661 322 9233",
    "sg:postcode":"93301",
    "sg:province":"CA",
    "wof:name":"Rick Isle",
    "wof:placetype":"venue"
},
  "geometry": {"coordinates":[-119.03745600000001,35.376228],"type":"Point"}
}