{
  "type": "Feature",
  "properties": {
    "iso:country":"US",
    "sg:address":"4437 Lankershim Blvd",
    "sg:city":"North Hollywood",
    "sg:classifiers":[
        {
            "category":"Autos & Motor Vehicles",
            "subcategory":"Automobile Sales",
            "type":"Retail Goods"
        }
    ],
    "sg:phone":"+1 323 877 1141",
    "sg:postcode":"91602",
    "sg:province":"CA",
    "sg:tags":[
        "car"
    ],
    "wof:name":"Mayberry Lincoln Mercury Inc",
    "wof:placetype":"venue"
},
  "geometry": {"coordinates":[-118.366997,34.151299],"type":"Point"}
}