{
  "type": "Feature",
  "properties": {
    "iso:country":"US",
    "sg:address":"3521 Arundell Cir",
    "sg:city":"Ventura",
    "sg:classifiers":[
        {
            "category":"Manufacturing",
            "subcategory":"Building Materials",
            "type":"Manufacturing & Wholesale Goods"
        },
        {
            "category":"Home & Garden",
            "subcategory":"Furniture",
            "type":"Retail Goods"
        }
    ],
    "sg:phone":"+1 805 644 8788",
    "sg:postcode":"93003",
    "sg:province":"CA",
    "sg:tags":[
        "mfg",
        "builder",
        "cabinet",
        "wood",
        "custom",
        "kitchen"
    ],
    "wof:name":"Cabinet Works",
    "wof:placetype":"venue"
},
  "geometry": {"coordinates":[-119.24672099999999,34.258842],"type":"Point"}
}