{
  "type": "Feature",
  "properties": {
    "addr:full":"524 Nathanson Creek Ln Sonoma CA 95476",
    "addr:housenumber":"524",
    "addr:postcode":"95476",
    "addr:street":"Nathanson Creek Ln",
    "iso:country":"US",
    "sg:address":"524 Nathanson Creek Ln",
    "sg:city":"Sonoma",
    "sg:classifiers":[
        {
            "category":"Professional",
            "type":"Services"
        }
    ],
    "sg:phone":"+1 707 935 3942",
    "sg:postcode":"95476",
    "sg:province":"CA",
    "wof:name":"Mary-Linn Benning",
    "wof:placetype":"venue"
},
  "geometry": {"coordinates":[-122.456008,38.291245],"type":"Point"}
}