{
  "type": "Feature",
  "properties": {
    "iso:country":"US",
    "sg:address":"41743 Enterprise Cir N",
    "sg:city":"Temecula",
    "sg:classifiers":[
        {
            "category":"Building & Trades",
            "subcategory":"Construction",
            "type":"Services"
        }
    ],
    "sg:phone":"+1 951 699 4898",
    "sg:postcode":"92590",
    "sg:province":"CA",
    "sg:tags":[
        "concrete",
        "contractor"
    ],
    "sg:website":"www.minegar.com",
    "wof:name":"Minegar Contracting",
    "wof:placetype":"venue"
},
  "geometry": {"coordinates":[-117.168733,33.520252],"type":"Point"}
}