{
  "type": "Feature",
  "properties": {
    "addr:full":"2737 Arden Way Sacramento CA 95825",
    "addr:housenumber":"2737",
    "addr:postcode":"95825",
    "addr:street":"Arden Way",
    "iso:country":"US",
    "sg:address":"2737 Arden Way",
    "sg:city":"Sacramento",
    "sg:classifiers":[
        {
            "category":"Restaurant",
            "type":"Food & Drink"
        }
    ],
    "sg:phone":"+1 916 488 8586",
    "sg:postcode":"95825",
    "sg:province":"CA",
    "wof:name":"Wienerschnitzel",
    "wof:placetype":"venue"
},
  "geometry": {"coordinates":[-121.39866600000001,38.59608],"type":"Point"}
}