{
  "type": "Feature",
  "properties": {
    "iso:country":"US",
    "sg:address":"5442 Ygnacio Valley Rd",
    "sg:city":"Concord",
    "sg:classifiers":[
        {
            "category":"Restaurant",
            "type":"Food & Drink"
        }
    ],
    "sg:phone":"+1 925 672 7200",
    "sg:postcode":"94521",
    "sg:province":"CA",
    "sg:tags":[
        "house",
        "steak"
    ],
    "wof:name":"Burger Road Concord",
    "wof:placetype":"venue"
},
  "geometry": {"coordinates":[-121.959433,37.950573],"type":"Point"}
}