{
  "type": "Feature",
  "properties": {
    "addr:full":"540 Vermont St Gridley CA 95948",
    "addr:housenumber":"540",
    "addr:postcode":"95948",
    "addr:street":"Vermont St",
    "iso:country":"US",
    "sg:address":"540 Vermont St",
    "sg:city":"Gridley",
    "sg:classifiers":[
        {
            "category":"Health Services",
            "subcategory":"Doctor",
            "type":"Services"
        }
    ],
    "sg:phone":"+1 530 846 3673",
    "sg:postcode":"95948",
    "sg:province":"CA",
    "sg:tags":[
        "dentist"
    ],
    "wof:name":"Gerald A Fillmore DDS",
    "wof:placetype":"venue"
},
  "geometry": {"coordinates":[-121.69881599999999,39.363744],"type":"Point"}
}