{
  "type": "Feature",
  "properties": {
    "iso:country":"US",
    "sg:address":"464 S Palm Ave",
    "sg:city":"Hemet",
    "sg:classifiers":[
        {
            "category":"Insurance",
            "subcategory":"Insurance Agent",
            "type":"Services"
        }
    ],
    "sg:phone":"+1 951 925 2105",
    "sg:postcode":"92543",
    "sg:province":"CA",
    "wof:name":"Beaver Insurance",
    "wof:placetype":"venue"
},
  "geometry": {"coordinates":[-116.98026,33.741419],"type":"Point"}
}