{
  "type": "Feature",
  "properties": {
    "iso:country":"US",
    "sg:address":"750 N Diamond Bar Blvd",
    "sg:city":"Diamond Bar",
    "sg:classifiers":[
        {
            "category":"Social Services",
            "type":"Services"
        }
    ],
    "sg:phone":"+1 909 861 4663",
    "sg:postcode":"91765",
    "sg:province":"CA",
    "sg:tags":[
        "counselor",
        "marriage",
        "family"
    ],
    "wof:name":"Diamond Bar Family Counseling",
    "wof:placetype":"venue"
},
  "geometry": {"coordinates":[-117.808099,34.032965],"type":"Point"}
}