{
  "type": "Feature",
  "properties": {
    "addr:full":"2429 W McFadden Ave Santa Ana CA 92704",
    "addr:housenumber":"2429",
    "addr:postcode":"92704",
    "addr:street":"W Mcfadden Ave",
    "iso:country":"US",
    "sg:address":"2429 W McFadden Ave",
    "sg:city":"Santa Ana",
    "sg:classifiers":[
        {
            "category":"Travel",
            "subcategory":"Travel Agent",
            "type":"Entertainment"
        }
    ],
    "sg:phone":"+1 714 836 5200",
    "sg:postcode":"92704",
    "sg:province":"CA",
    "sg:tags":[
        "agency"
    ],
    "wof:name":"Acapulco Travel & Tours Inc",
    "wof:placetype":"venue"
},
  "geometry": {"coordinates":[-117.902231,33.734575],"type":"Point"}
}