{
  "type": "Feature",
  "properties": {
    "addr:full":"1102 V V Williams Ave Calexico CA 92231",
    "addr:housenumber":"1102;v",
    "addr:postcode":"92231",
    "addr:street":"Williams Ave",
    "iso:country":"US",
    "sg:address":"1102 V V Williams Ave",
    "sg:city":"Calexico",
    "sg:classifiers":[
        {
            "category":"Banks & Credit Unions",
            "subcategory":"Bank",
            "type":"Services"
        },
        {
            "category":"Shopping",
            "subcategory":"Used Merchandise",
            "type":"Retail Goods"
        }
    ],
    "sg:phone":"+1 760 357 9020",
    "sg:postcode":"92231",
    "sg:province":"CA",
    "sg:tags":[
        "resale",
        "shop",
        "second",
        "hand"
    ],
    "wof:name":"Santo Thomas Swapmeet",
    "wof:placetype":"venue"
},
  "geometry": {"coordinates":[-115.50738,32.679487],"type":"Point"}
}