{
  "type": "Feature",
  "properties": {
    "iso:country":"US",
    "sg:address":"1300 Valley Vista Dr",
    "sg:city":"Diamond Bar",
    "sg:classifiers":[
        {
            "category":"Professional",
            "subcategory":"Management & Consulting",
            "type":"Services"
        }
    ],
    "sg:phone":"+1 909 861 6945",
    "sg:postcode":"91765",
    "sg:province":"CA",
    "sg:tags":[
        "fuel"
    ],
    "wof:name":"QTC Management",
    "wof:placetype":"venue"
},
  "geometry": {"coordinates":[-117.835237,33.998144],"type":"Point"}
}