{
  "type": "Feature",
  "properties": {
    "addr:full":"3802 Rosecrans St Ste 167 San Diego CA 92110",
    "addr:housenumber":"3802",
    "addr:postcode":"92110",
    "addr:street":"Rosecrans St Ste 167",
    "iso:country":"US",
    "sg:address":"3802 Rosecrans St Ste 167",
    "sg:city":"San Diego",
    "sg:classifiers":[
        {
            "category":"Health Services",
            "subcategory":"Clinic",
            "type":"Services"
        },
        {
            "category":"Personal",
            "type":"Services"
        }
    ],
    "sg:phone":"+1 619 954 1124",
    "sg:postcode":"92110",
    "sg:province":"CA",
    "sg:tags":[
        "medical",
        "local"
    ],
    "sg:website":"www.smartmedicaltransport.com/",
    "wof:name":"Smart Medical Transport",
    "wof:placetype":"venue"
},
  "geometry": {"coordinates":[-117.203025,32.753294],"type":"Point"}
}