{
  "type": "Feature",
  "properties": {
    "addr:full":"124 E Olympic Blvd Los Angeles CA 90015",
    "addr:housenumber":"124",
    "addr:postcode":"90015",
    "addr:street":"E Olympic Blvd",
    "iso:country":"US",
    "sg:address":"124 E Olympic Blvd",
    "sg:city":"Los Angeles",
    "sg:classifiers":[
        {
            "category":"Professional",
            "type":"Services"
        }
    ],
    "sg:phone":"+1 213 694 1896",
    "sg:postcode":"90015",
    "sg:province":"CA",
    "sg:tags":[
        "establishment"
    ],
    "wof:name":"Alley Bags",
    "wof:placetype":"venue"
},
  "geometry": {"coordinates":[-118.256075,34.039747],"type":"Point"}
}