{
  "type": "Feature",
  "properties": {
    "addr:full":"240 San Miguel Canyon Rd Watsonville CA 95076",
    "addr:housenumber":"240",
    "addr:postcode":"95076",
    "addr:street":"San Miguel Canyon Rd",
    "iso:country":"US",
    "sg:address":"240 San Miguel Canyon Rd",
    "sg:city":"Watsonville",
    "sg:classifiers":[
        {
            "category":"Building & Trades",
            "subcategory":"Construction",
            "type":"Services"
        }
    ],
    "sg:phone":"+1 831 818 2838",
    "sg:postcode":"95076",
    "sg:province":"CA",
    "sg:tags":[
        "general",
        "contractor"
    ],
    "wof:name":"Surf City Constructors",
    "wof:placetype":"venue"
},
  "geometry": {"coordinates":[-121.690411,36.891368],"type":"Point"}
}