{
  "type": "Feature",
  "properties": {
    "iso:country":"US",
    "sg:address":"22240 Burton St",
    "sg:city":"Canoga Park",
    "sg:classifiers":[
        {
            "category":"Professional",
            "type":"Services"
        }
    ],
    "sg:phone":"+1 818 704 1460",
    "sg:postcode":"91304",
    "sg:province":"CA",
    "wof:name":"Wonderland Nightmares",
    "wof:placetype":"venue"
},
  "geometry": {"coordinates":[-118.611681,34.218619],"type":"Point"}
}