{
  "type": "Feature",
  "properties": {
    "iso:country":"US",
    "sg:address":"2235 Browning Ave",
    "sg:city":"Clovis",
    "sg:classifiers":[
        {
            "category":"Manufacturing",
            "subcategory":"Tools & Machinery",
            "type":"Manufacturing & Wholesale Goods"
        }
    ],
    "sg:phone":"+1 559 298 6226",
    "sg:postcode":"93611",
    "sg:province":"CA",
    "sg:tags":[
        "electric",
        "mfg"
    ],
    "wof:name":"Aqua Touch 2000",
    "wof:placetype":"venue"
},
  "geometry": {"coordinates":[-119.670129,36.820525],"type":"Point"}
}