{
  "type": "Feature",
  "properties": {
    "addr:full":"547 Sutter St San Francisco CA 94102",
    "addr:housenumber":"547",
    "addr:postcode":"94102",
    "addr:street":"Sutter St",
    "iso:country":"US",
    "sg:address":"547 Sutter St",
    "sg:city":"San Francisco",
    "sg:classifiers":[
        {
            "category":"Shopping",
            "subcategory":"Clothing, Apparel, & Fashions",
            "type":"Retail Goods"
        }
    ],
    "sg:phone":"+1 415 398 4000",
    "sg:postcode":"94102",
    "sg:province":"CA",
    "wof:name":"Cicada Art Fashion & Bridal",
    "wof:placetype":"venue"
},
  "geometry": {"coordinates":[-122.40961900000001,37.789041],"type":"Point"}
}