{
  "type": "Feature",
  "properties": {
    "addr:full":"1737 Moreland Dr Alameda CA 94501",
    "addr:housenumber":"1737",
    "addr:postcode":"94501",
    "addr:street":"Moreland Dr",
    "iso:country":"US",
    "sg:address":"1737 Moreland Dr",
    "sg:city":"Alameda",
    "sg:classifiers":[
        {
            "category":"Utilities",
            "subcategory":"Telephone",
            "type":"Services"
        }
    ],
    "sg:phone":"+1 510 748 8145",
    "sg:postcode":"94501",
    "sg:province":"CA",
    "sg:tags":[
        "communications"
    ],
    "wof:name":"Wenotifynet",
    "wof:placetype":"venue"
},
  "geometry": {"coordinates":[-122.232568,37.765119],"type":"Point"}
}