{
  "type": "Feature",
  "properties": {
    "iso:country":"US",
    "sg:address":"720 Harbour Way S",
    "sg:city":"Richmond",
    "sg:classifiers":[
        {
            "category":"Professional",
            "subcategory":"Business Services",
            "type":"Services"
        }
    ],
    "sg:phone":"+1 510 234 5078",
    "sg:postcode":"94804",
    "sg:province":"CA",
    "sg:tags":[
        "delivery",
        "courier"
    ],
    "wof:name":"Good Moves",
    "wof:placetype":"venue"
},
  "geometry": {"coordinates":[-122.360001,37.922298],"type":"Point"}
}