{
  "type": "Feature",
  "properties": {
    "iso:country":"US",
    "sg:address":"6235 20th St",
    "sg:city":"Rio Linda",
    "sg:classifiers":[
        {
            "category":"Home & Garden",
            "subcategory":"Furniture",
            "type":"Retail Goods"
        }
    ],
    "sg:phone":"+1 916 991 6190",
    "sg:postcode":"95673",
    "sg:province":"CA",
    "sg:tags":[
        "equipment",
        "kitchen",
        "cabinet"
    ],
    "wof:name":"C H & Dc Spence Custom Ktchns",
    "wof:placetype":"venue"
},
  "geometry": {"coordinates":[-121.419933,38.682885],"type":"Point"}
}