{
  "type": "Feature",
  "properties": {
    "addr:full":"11733 Hadley St Whittier CA 90601",
    "addr:housenumber":"11733",
    "addr:postcode":"90601",
    "addr:street":"Hadley St",
    "iso:country":"US",
    "sg:address":"11733 Hadley St",
    "sg:city":"Whittier",
    "sg:classifiers":[
        {
            "category":"Personal",
            "subcategory":"Beauty Salon",
            "type":"Services"
        }
    ],
    "sg:phone":"+1 562 695 1407",
    "sg:postcode":"90601",
    "sg:province":"CA",
    "wof:name":"Kutting Krew",
    "wof:placetype":"venue"
},
  "geometry": {"coordinates":[-118.050274,33.982818],"type":"Point"}
}