{
  "type": "Feature",
  "properties": {
    "iso:country":"US",
    "sg:address":"8261 Stine Rd",
    "sg:city":"Bakersfield",
    "sg:classifiers":[
        {
            "category":"Farming",
            "subcategory":"Farm & Veterinary Services",
            "type":"Manufacturing & Wholesale Goods"
        }
    ],
    "sg:phone":"+1 661 834 0390",
    "sg:postcode":"93313",
    "sg:province":"CA",
    "sg:tags":[
        "labor",
        "contractor"
    ],
    "wof:name":"Manuel M Rodriquez Citrus",
    "wof:placetype":"venue"
},
  "geometry": {"coordinates":[-119.056744,35.279059],"type":"Point"}
}