{
  "type": "Feature",
  "properties": {
    "addr:full":"9500 Stockdale Hwy Bakersfield CA 93311",
    "addr:housenumber":"9500",
    "addr:postcode":"93311",
    "addr:street":"Stockdale Hwy",
    "iso:country":"US",
    "sg:address":"9500 Stockdale Hwy",
    "sg:city":"Bakersfield",
    "sg:classifiers":[
        {
            "category":"Health Services",
            "subcategory":"Doctor",
            "type":"Services"
        },
        {
            "category":"Health Services",
            "subcategory":"Clinic",
            "type":"Services"
        },
        {
            "category":"Community Center",
            "type":"Public Place"
        }
    ],
    "sg:phone":"+1 661 324 4747",
    "sg:postcode":"93311",
    "sg:province":"CA",
    "sg:tags":[
        "physician",
        "family",
        "medical",
        "practice",
        "surgeons",
        "medicine"
    ],
    "wof:name":"Mohawk Medical Group",
    "wof:placetype":"venue"
},
  "geometry": {"coordinates":[-119.105672,35.354494],"type":"Point"}
}