{
  "type": "Feature",
  "properties": {
    "iso:country":"US",
    "sg:address":"3133 Professional Dr",
    "sg:city":"Auburn",
    "sg:classifiers":[
        {
            "category":"Health Services",
            "subcategory":"Optometrist",
            "type":"Services"
        }
    ],
    "sg:phone":"+1 530 888 0670",
    "sg:postcode":"95603",
    "sg:province":"CA",
    "sg:website":"www.auburnfamilyoptometry.com",
    "wof:name":"Auburn Family Optometry",
    "wof:placetype":"venue"
},
  "geometry": {"coordinates":[-121.100945,38.941631],"type":"Point"}
}