{
  "type": "Feature",
  "properties": {
    "iso:country":"US",
    "sg:address":"4346 Lone Tree Way",
    "sg:city":"Antioch",
    "sg:classifiers":[
        {
            "category":"Fast Food",
            "type":"Food & Drink"
        },
        {
            "category":"Restaurant",
            "type":"Food & Drink"
        }
    ],
    "sg:phone":"+1 925 978 1132",
    "sg:postcode":"94531",
    "sg:province":"CA",
    "sg:tags":[
        "mexican"
    ],
    "sg:website":"http://www.tacobell.com",
    "wof:name":"Taco Bell",
    "wof:placetype":"venue"
},
  "geometry": {"coordinates":[-121.78393699999999,37.967263],"type":"Point"}
}