{
  "type": "Feature",
  "properties": {
    "addr:full":"202 N Spurgeon St Santa Ana CA 92701",
    "addr:housenumber":"202",
    "addr:postcode":"92701",
    "addr:street":"N Spurgeon St",
    "iso:country":"US",
    "sg:address":"202 N Spurgeon St",
    "sg:city":"Santa Ana",
    "sg:classifiers":[
        {
            "category":"Professional",
            "subcategory":"Lawyer & Legal Services",
            "type":"Services"
        }
    ],
    "sg:phone":"+1 714 565 2760",
    "sg:postcode":"92701",
    "sg:province":"CA",
    "wof:name":"Leyva & Night-Apc",
    "wof:placetype":"venue"
},
  "geometry": {"coordinates":[-117.866201,33.746999],"type":"Point"}
}