{
  "type": "Feature",
  "properties": {
    "addr:full":"1535 3rd Ave San Diego CA 92101",
    "addr:housenumber":"1535",
    "addr:postcode":"92101",
    "addr:street":"3Rd Ave",
    "iso:country":"US",
    "sg:address":"1535 3rd Ave",
    "sg:city":"San Diego",
    "sg:classifiers":[
        {
            "category":"Place Of Worship",
            "subcategory":"Church",
            "type":"Public Place"
        }
    ],
    "sg:phone":"+1 619 239 0229",
    "sg:postcode":"92101",
    "sg:province":"CA",
    "wof:name":"St Joseph's Cathedral",
    "wof:placetype":"venue"
},
  "geometry": {"coordinates":[-117.162003,32.7211],"type":"Point"}
}