{
  "type": "Feature",
  "properties": {
    "iso:country":"US",
    "sg:address":"37131 Main St",
    "sg:city":"Burney",
    "sg:classifiers":[
        {
            "category":"Banks & Credit Unions",
            "subcategory":"Bank",
            "type":"Services"
        }
    ],
    "sg:phone":"+1 530 335 4531",
    "sg:postcode":"96013",
    "sg:province":"CA",
    "wof:name":"US Bank",
    "wof:placetype":"venue"
},
  "geometry": {"coordinates":[-121.667225,40.881825],"type":"Point"}
}