{
  "type": "Feature",
  "properties": {
    "addr:full":"2700 Colusa Hwy Yuba City CA 95993",
    "addr:housenumber":"2700",
    "addr:postcode":"95993",
    "addr:street":"Colusa Hwy",
    "iso:country":"US",
    "sg:address":"2700 Colusa Hwy",
    "sg:city":"Yuba City",
    "sg:classifiers":[
        {
            "category":"Manufacturing",
            "subcategory":"Tools & Machinery",
            "type":"Manufacturing & Wholesale Goods"
        }
    ],
    "sg:phone":"+1 530 673 2822",
    "sg:postcode":"95993",
    "sg:province":"CA",
    "sg:tags":[
        "farm",
        "equipment"
    ],
    "sg:website":"www.shakermaker.com",
    "wof:name":"Orchard Machinery Corp",
    "wof:placetype":"venue"
},
  "geometry": {"coordinates":[-121.665397,39.141466],"type":"Point"}
}