{
  "type": "Feature",
  "properties": {
    "iso:country":"US",
    "sg:address":"27225 Camp Plenty Rd Suite 8",
    "sg:city":"Canyon Country",
    "sg:classifiers":[
        {
            "category":"Communications",
            "subcategory":"Radio Station",
            "type":"Services"
        }
    ],
    "sg:phone":"+1 661 298 1220",
    "sg:postcode":"91351",
    "sg:province":"CA",
    "sg:website":"www.hometownstation.com",
    "wof:name":"KHTS Radio - AM 1220",
    "wof:placetype":"venue"
},
  "geometry": {"coordinates":[-118.475677,34.416345],"type":"Point"}
}