{
  "type": "Feature",
  "properties": {
    "iso:country":"US",
    "sg:address":"1809 Elm St",
    "sg:city":"Alameda",
    "sg:classifiers":[
        {
            "category":"Professional",
            "subcategory":"Business Services",
            "type":"Services"
        }
    ],
    "sg:phone":"+1 510 864 1506",
    "sg:postcode":"94501",
    "sg:province":"CA",
    "sg:tags":[
        "consultant",
        "coach"
    ],
    "wof:name":"Proctor Consulting Group",
    "wof:placetype":"venue"
},
  "geometry": {"coordinates":[-122.243133,37.769882],"type":"Point"}
}