{
  "type": "Feature",
  "properties": {
    "iso:country":"US",
    "sg:address":"372 Euclid Ave",
    "sg:city":"Oakland",
    "sg:classifiers":[
        {
            "category":"Shopping",
            "subcategory":"Crafts & Fabrics",
            "type":"Retail Goods"
        }
    ],
    "sg:phone":"+1 510 628 0826",
    "sg:postcode":"94610",
    "sg:province":"CA",
    "sg:tags":[
        "material",
        "quilting",
        "quilt",
        "supply"
    ],
    "sg:website":"http://www.thequiltcomplex.com",
    "wof:name":"Quilt Complex",
    "wof:placetype":"venue"
},
  "geometry": {"coordinates":[-122.251983,37.812064],"type":"Point"}
}