{
  "type": "Feature",
  "properties": {
    "iso:country":"US",
    "sg:address":"3460 El Camino Ave",
    "sg:city":"Sacramento",
    "sg:classifiers":[
        {
            "category":"Restaurant",
            "type":"Food & Drink"
        }
    ],
    "sg:menulink":"http://www.allmenus.com/ca/sacramento/60026-subway/menu/",
    "sg:phone":"+1 916 482 7200",
    "sg:postcode":"95821",
    "sg:province":"CA",
    "sg:tags":[
        "american",
        "sandwich"
    ],
    "wof:name":"Subway",
    "wof:placetype":"venue"
},
  "geometry": {"coordinates":[-121.38395300000001,38.608679],"type":"Point"}
}