{
  "type": "Feature",
  "properties": {
    "iso:country":"US",
    "sg:address":"1373 N Oxford Ave",
    "sg:city":"Pasadena",
    "sg:classifiers":[
        {
            "category":"Building & Trades",
            "subcategory":"Construction",
            "type":"Services"
        }
    ],
    "sg:phone":"+1 626 683 3878",
    "sg:postcode":"91104",
    "sg:province":"CA",
    "sg:tags":[
        "contractor"
    ],
    "wof:name":"Prime Construction Co",
    "wof:placetype":"venue"
},
  "geometry": {"coordinates":[-118.116431,34.169109],"type":"Point"}
}