{
  "type": "Feature",
  "properties": {
    "addr:full":"937 E Main St Santa Maria CA 93454",
    "addr:housenumber":"937",
    "addr:postcode":"93454",
    "addr:street":"E Main St",
    "iso:country":"US",
    "sg:address":"937 E Main St",
    "sg:city":"Santa Maria",
    "sg:classifiers":[
        {
            "category":"Professional",
            "subcategory":"Business Services",
            "type":"Services"
        }
    ],
    "sg:phone":"+1 805 349 7858",
    "sg:postcode":"93454",
    "sg:province":"CA",
    "sg:tags":[
        "inventory"
    ],
    "wof:name":"RGIS Inventory Specialist",
    "wof:placetype":"venue"
},
  "geometry": {"coordinates":[-120.422056,34.953202],"type":"Point"}
}