{
  "type": "Feature",
  "properties": {
    "addr:full":"120 N Harvard Ave Claremont CA 91711",
    "addr:housenumber":"120",
    "addr:postcode":"91711",
    "addr:street":"N Harvard Ave",
    "iso:country":"US",
    "sg:address":"120 N Harvard Ave",
    "sg:city":"Claremont",
    "sg:classifiers":[
        {
            "category":"Personal",
            "subcategory":"Beauty Salon",
            "type":"Services"
        }
    ],
    "sg:phone":"+1 909 920 1096",
    "sg:postcode":"91711",
    "sg:province":"CA",
    "wof:name":"Michael's Hair Design",
    "wof:placetype":"venue"
},
  "geometry": {"coordinates":[-117.716331,34.09545],"type":"Point"}
}