{
  "type": "Feature",
  "properties": {
    "iso:country":"US",
    "sg:address":"2499 S Stockton St",
    "sg:city":"Lodi",
    "sg:classifiers":[
        {
            "category":"Autos & Motor Vehicles",
            "subcategory":"Auto Supplies",
            "type":"Retail Goods"
        }
    ],
    "sg:phone":"+1 209 368 5046",
    "sg:postcode":"95240",
    "sg:province":"CA",
    "sg:tags":[
        "absorber",
        "shock"
    ],
    "wof:name":"Custom Axis",
    "wof:placetype":"venue"
},
  "geometry": {"coordinates":[-121.269611,38.102865],"type":"Point"}
}