{
  "type": "Feature",
  "properties": {
    "addr:full":"1700 E 4th St Los Angeles CA 90033",
    "addr:housenumber":"1700",
    "addr:postcode":"90033",
    "addr:street":"E 4Th St",
    "iso:country":"US",
    "sg:address":"1700 E 4th St",
    "sg:city":"Los Angeles",
    "sg:classifiers":[
        {
            "category":"Building & Trades",
            "subcategory":"Construction",
            "type":"Services"
        }
    ],
    "sg:phone":"+1 323 415 6200",
    "sg:postcode":"90033",
    "sg:province":"CA",
    "sg:tags":[
        "general",
        "contractor"
    ],
    "wof:name":"Luther Construction Co",
    "wof:placetype":"venue"
},
  "geometry": {"coordinates":[-118.219627,34.043053],"type":"Point"}
}