{
  "type": "Feature",
  "properties": {
    "iso:country":"US",
    "sg:address":"1702 Oceanside Blvd",
    "sg:city":"Oceanside",
    "sg:classifiers":[
        {
            "category":"Food & Beverages",
            "subcategory":"Groceries & Convenience Stores",
            "type":"Retail Goods"
        }
    ],
    "sg:phone":"+1 760 721 4596",
    "sg:postcode":"92054",
    "sg:province":"CA",
    "sg:tags":[
        "supermarket"
    ],
    "wof:name":"Ralphs Grocery Store 109",
    "wof:placetype":"venue"
},
  "geometry": {"coordinates":[-117.358999,33.192279],"type":"Point"}
}