{
  "type": "Feature",
  "properties": {
    "addr:full":"100 E Yosemite Ave Madera CA 93638",
    "addr:housenumber":"100",
    "addr:postcode":"93638",
    "addr:street":"E Yosemite Ave",
    "iso:country":"US",
    "sg:address":"100 E Yosemite Ave",
    "sg:city":"Madera",
    "sg:classifiers":[
        {
            "category":"Home & Garden",
            "subcategory":"Furniture",
            "type":"Retail Goods"
        }
    ],
    "sg:phone":"+1 559 675 8007",
    "sg:postcode":"93638",
    "sg:province":"CA",
    "sg:tags":[
        "store"
    ],
    "wof:name":"Fantastic Furniture",
    "wof:placetype":"venue"
},
  "geometry": {"coordinates":[-120.05954699999999,36.961922],"type":"Point"}
}