{
  "type": "Feature",
  "properties": {
    "iso:country":"US",
    "sg:address":"263 Olivos Ln",
    "sg:city":"Nipomo",
    "sg:classifiers":[
        {
            "category":"Freight",
            "type":"Transportation"
        }
    ],
    "sg:phone":"+1 805 542 9198",
    "sg:postcode":"93444",
    "sg:province":"CA",
    "sg:tags":[
        "delivery"
    ],
    "sg:website":"www.allcountiesdelivery.com",
    "wof:name":"All Counties Delivery",
    "wof:placetype":"venue"
},
  "geometry": {"coordinates":[-120.493103,35.037724],"type":"Point"}
}