{
  "type": "Feature",
  "properties": {
    "addr:full":"15265 Poverty Rd Walnut Grove CA 95690",
    "addr:housenumber":"15265",
    "addr:postcode":"95690",
    "addr:street":"Poverty Rd",
    "iso:country":"US",
    "sg:address":"15265 Poverty Rd",
    "sg:city":"Walnut Grove",
    "sg:classifiers":[
        {
            "category":"Farming",
            "subcategory":"Farm",
            "type":"Manufacturing & Wholesale Goods"
        }
    ],
    "sg:phone":"+1 916 777 5022",
    "sg:postcode":"95690",
    "sg:province":"CA",
    "sg:tags":[
        "general"
    ],
    "wof:name":"Mc Dowell Farms Inc",
    "wof:placetype":"venue"
},
  "geometry": {"coordinates":[-121.595186,38.196858],"type":"Point"}
}