{
  "type": "Feature",
  "properties": {
    "iso:country":"US",
    "sg:address":"37 Quail Ct",
    "sg:city":"Walnut Creek",
    "sg:classifiers":[
        {
            "category":"Social Services",
            "type":"Services"
        }
    ],
    "sg:phone":"+1 415 440 9825",
    "sg:postcode":"94596",
    "sg:province":"CA",
    "sg:tags":[
        "counselor",
        "marriage",
        "family"
    ],
    "wof:name":"Lia Jones Mft",
    "wof:placetype":"venue"
},
  "geometry": {"coordinates":[-122.05521400000001,37.887847],"type":"Point"}
}