{
  "type": "Feature",
  "properties": {
    "addr:full":"9939 Hayward Way South El Monte CA 91733",
    "addr:housenumber":"9939",
    "addr:postcode":"91733",
    "addr:street":"Hayward Way",
    "iso:country":"US",
    "sg:address":"9939 Hayward Way",
    "sg:city":"South El Monte",
    "sg:classifiers":[
        {
            "category":"Manufacturing",
            "subcategory":"Furniture",
            "type":"Manufacturing & Wholesale Goods"
        }
    ],
    "sg:phone":"+1 626 442 9662",
    "sg:postcode":"91733",
    "sg:province":"CA",
    "wof:name":"A S Design Corp",
    "wof:placetype":"venue"
},
  "geometry": {"coordinates":[-118.05192099999999,34.049003],"type":"Point"}
}