{
  "type": "Feature",
  "properties": {
    "addr:full":"4220 Convoy Street San Diego CA 92111",
    "addr:housenumber":"4220",
    "addr:postcode":"92111",
    "addr:street":"Convoy Street",
    "iso:country":"US",
    "sg:address":"4220 Convoy Street",
    "sg:city":"San Diego",
    "sg:classifiers":[
        {
            "category":"Shopping",
            "subcategory":"Mobile Phones",
            "type":"Retail Goods"
        }
    ],
    "sg:phone":"+1 858 571 6010",
    "sg:postcode":"92111",
    "sg:province":"CA",
    "wof:name":"Elite Wireless",
    "wof:placetype":"venue"
},
  "geometry": {"coordinates":[-117.154774,32.818237],"type":"Point"}
}