{
  "type": "Feature",
  "properties": {
    "addr:full":"325 Enterprise Pl Pomona CA 91768",
    "addr:housenumber":"325",
    "addr:postcode":"91768",
    "addr:street":"Enterprise Pl",
    "iso:country":"US",
    "sg:address":"325 Enterprise Pl",
    "sg:city":"Pomona",
    "sg:classifiers":[
        {
            "category":"Manufacturing",
            "subcategory":"Metals",
            "type":"Manufacturing & Wholesale Goods"
        }
    ],
    "sg:phone":"+1 909 594 4687",
    "sg:postcode":"91768",
    "sg:province":"CA",
    "sg:tags":[
        "vessel"
    ],
    "wof:name":"Structural Composites Inds",
    "wof:placetype":"venue"
},
  "geometry": {"coordinates":[-117.807632,34.048857],"type":"Point"}
}