{
  "type": "Feature",
  "properties": {
    "addr:full":"4935 McConnell Ave Los Angeles CA 90066",
    "addr:housenumber":"4935",
    "addr:postcode":"90066",
    "addr:street":"Mcconnell Ave",
    "iso:country":"US",
    "sg:address":"4935 McConnell Ave",
    "sg:city":"Los Angeles",
    "sg:classifiers":[
        {
            "category":"Manufacturing",
            "subcategory":"Tools & Machinery",
            "type":"Manufacturing & Wholesale Goods"
        }
    ],
    "sg:phone":"+1 310 306 9332",
    "sg:postcode":"90066",
    "sg:province":"CA",
    "sg:tags":[
        "machine",
        "shop"
    ],
    "wof:name":"British Precision Engineering",
    "wof:placetype":"venue"
},
  "geometry": {"coordinates":[-118.42448899999999,33.984469],"type":"Point"}
}