{
  "type": "Feature",
  "properties": {
    "addr:full":"3249 Mt Diablo Blvd Lafayette CA 94549",
    "addr:housenumber":"3249",
    "addr:postcode":"94549",
    "addr:street":"Mt Diablo Blvd",
    "iso:country":"US",
    "sg:address":"3249 Mt Diablo Blvd",
    "sg:city":"Lafayette",
    "sg:classifiers":[
        {
            "category":"Professional",
            "subcategory":"Business Services",
            "type":"Services"
        }
    ],
    "sg:phone":"+1 925 286 8610",
    "sg:postcode":"94549",
    "sg:province":"CA",
    "sg:tags":[
        "notary"
    ],
    "wof:name":"Kazie Afsari",
    "wof:placetype":"venue"
},
  "geometry": {"coordinates":[-122.10020400000001,37.896744],"type":"Point"}
}