{
  "type": "Feature",
  "properties": {
    "addr:full":"11340 W Olympic Boulevard Los Angeles CA 90064",
    "addr:housenumber":"11340",
    "addr:postcode":"90064",
    "addr:street":"W Olympic Boulevard",
    "iso:country":"US",
    "sg:address":"11340 W Olympic Boulevard",
    "sg:city":"Los Angeles",
    "sg:classifiers":[
        {
            "category":"Professional",
            "subcategory":"Lawyer & Legal Services",
            "type":"Services"
        }
    ],
    "sg:phone":"+1 310 337 1222",
    "sg:postcode":"90064",
    "sg:province":"CA",
    "wof:name":"Law Office of Duchrow David",
    "wof:placetype":"venue"
},
  "geometry": {"coordinates":[-118.442053,34.037697],"type":"Point"}
}