{
  "type": "Feature",
  "properties": {
    "addr:full":"120 Knoll Rd San Marcos CA 92069",
    "addr:housenumber":"120",
    "addr:postcode":"92069",
    "addr:street":"Knoll Rd",
    "iso:country":"US",
    "sg:address":"120 Knoll Rd",
    "sg:city":"San Marcos",
    "sg:classifiers":[
        {
            "category":"Restaurant",
            "type":"Food & Drink"
        }
    ],
    "sg:menulink":"http://www.allmenus.com/ca/oceanside-escondido/170902-carls-jr/menu/",
    "sg:phone":"+1 760 752 4494",
    "sg:postcode":"92069",
    "sg:province":"CA",
    "sg:tags":[
        "burger",
        "american"
    ],
    "wof:name":"Carl's Jr.",
    "wof:placetype":"venue"
},
  "geometry": {"coordinates":[-117.175259,33.138774],"type":"Point"}
}