{
  "type": "Feature",
  "properties": {
    "addr:full":"1880 W 11th St Tracy CA 95376",
    "addr:housenumber":"1880",
    "addr:postcode":"95376",
    "addr:street":"W 11Th St",
    "iso:country":"US",
    "sg:address":"1880 W 11th St",
    "sg:city":"Tracy",
    "sg:classifiers":[
        {
            "category":"Shopping",
            "subcategory":"Clothing, Apparel, & Fashions",
            "type":"Retail Goods"
        }
    ],
    "sg:phone":"+1 209 833 1600",
    "sg:postcode":"95376",
    "sg:province":"CA",
    "sg:tags":[
        "tailor"
    ],
    "wof:name":"Tracy Valley Cleaners",
    "wof:placetype":"venue"
},
  "geometry": {"coordinates":[-121.44635100000001,37.739512],"type":"Point"}
}