{
  "type": "Feature",
  "properties": {
    "addr:full":"11246 Gold Express Dr Gold River CA 95670",
    "addr:housenumber":"11246",
    "addr:postcode":"95670",
    "addr:street":"Gold Express Dr",
    "iso:country":"US",
    "sg:address":"11246 Gold Express Dr",
    "sg:city":"Gold River",
    "sg:classifiers":[
        {
            "category":"Real Estate",
            "subcategory":"Architect",
            "type":"Services"
        }
    ],
    "sg:phone":"+1 916 635 6446",
    "sg:postcode":"95670",
    "sg:province":"CA",
    "sg:tags":[
        "home",
        "planning",
        "design"
    ],
    "wof:name":"Westwood Homes Design Ctr",
    "wof:placetype":"venue"
},
  "geometry": {"coordinates":[-121.264026,38.623291],"type":"Point"}
}