{
  "type": "Feature",
  "properties": {
    "addr:full":"863 N Mountain View Ave San Bernardino CA 92401",
    "addr:housenumber":"863",
    "addr:postcode":"92401",
    "addr:street":"N Mountain View Ave",
    "iso:country":"US",
    "sg:address":"863 N Mountain View Ave",
    "sg:city":"San Bernardino",
    "sg:classifiers":[
        {
            "category":"Organizations",
            "subcategory":"Religious Organization",
            "type":"Services"
        }
    ],
    "sg:phone":"+1 909 884 6489",
    "sg:postcode":"92401",
    "sg:province":"CA",
    "sg:tags":[
        "church"
    ],
    "sg:website":"www.fbfa.org",
    "wof:name":"First Assembly Of God",
    "wof:placetype":"venue"
},
  "geometry": {"coordinates":[-117.28734799999999,34.11463],"type":"Point"}
}