{
  "type": "Feature",
  "properties": {
    "addr:full":"6453 Gregory Ln Placerville CA 95667",
    "addr:housenumber":"6453",
    "addr:postcode":"95667",
    "addr:street":"Gregory Ln",
    "iso:country":"US",
    "sg:address":"6453 Gregory Ln",
    "sg:city":"Placerville",
    "sg:classifiers":[
        {
            "category":"Farming",
            "subcategory":"Farm",
            "type":"Manufacturing & Wholesale Goods"
        }
    ],
    "sg:phone":"+1 530 919 5656",
    "sg:postcode":"95667",
    "sg:province":"CA",
    "wof:name":"Big N Little Farm",
    "wof:placetype":"venue"
},
  "geometry": {"coordinates":[-120.711659,38.627832],"type":"Point"}
}