{
  "type": "Feature",
  "properties": {
    "addr:full":"2516 W 54th St Los Angeles CA 90043",
    "addr:housenumber":"2516",
    "addr:postcode":"90043",
    "addr:street":"W 54Th St",
    "iso:country":"US",
    "sg:address":"2516 W 54th St",
    "sg:city":"Los Angeles",
    "sg:classifiers":[
        {
            "category":"Professional",
            "subcategory":"Accounting & Tax Preparation",
            "type":"Services"
        }
    ],
    "sg:phone":"+1 323 296 9100",
    "sg:postcode":"90043",
    "sg:province":"CA",
    "sg:tags":[
        "return",
        "filing"
    ],
    "wof:name":"Services Unlimited",
    "wof:placetype":"venue"
},
  "geometry": {"coordinates":[-118.321287,33.993113],"type":"Point"}
}