{
  "type": "Feature",
  "properties": {
    "iso:country":"US",
    "sg:address":"3393 Mount Diablo Blvd",
    "sg:city":"Lafayette",
    "sg:classifiers":[
        {
            "category":"Autos & Motor Vehicles",
            "subcategory":"Auto Supplies",
            "type":"Retail Goods"
        }
    ],
    "sg:phone":"+1 925 284 1440",
    "sg:postcode":"94549",
    "sg:province":"CA",
    "sg:tags":[
        "automobile",
        "parts"
    ],
    "wof:name":"Lafayette Automotive Supply",
    "wof:placetype":"venue"
},
  "geometry": {"coordinates":[-122.108788,37.89392],"type":"Point"}
}