{
  "type": "Feature",
  "properties": {
    "iso:country":"US",
    "sg:address":"9659 Los Coches Rd",
    "sg:city":"Lakeside",
    "sg:classifiers":[
        {
            "category":"Professional",
            "subcategory":"Accounting & Tax Preparation",
            "type":"Services"
        }
    ],
    "sg:phone":"+1 619 561 2144",
    "sg:postcode":"92040",
    "sg:province":"CA",
    "sg:tags":[
        "billing"
    ],
    "wof:name":"Electronic Health Claims Mgmt",
    "wof:placetype":"venue"
},
  "geometry": {"coordinates":[-116.91907,32.854681],"type":"Point"}
}