{
  "type": "Feature",
  "properties": {
    "iso:country":"US",
    "sg:address":"2634 W Avenue K K A14 14 A",
    "sg:city":"Lancaster",
    "sg:classifiers":[
        {
            "category":"Banks & Credit Unions",
            "subcategory":"Investment Brokerage",
            "type":"Services"
        },
        {
            "category":"Real Estate",
            "subcategory":"Developer",
            "type":"Services"
        }
    ],
    "sg:phone":"+1 818 683 4059",
    "sg:postcode":"93536",
    "sg:province":"CA",
    "sg:tags":[
        "investing"
    ],
    "wof:name":"Elite Equity Investments Inc.",
    "wof:placetype":"venue"
},
  "geometry": {"coordinates":[-118.177693,34.67491],"type":"Point"}
}