{
  "type": "Feature",
  "properties": {
    "addr:full":"8013 Melrose Ave Los Angeles CA 90046",
    "addr:housenumber":"8013",
    "addr:postcode":"90046",
    "addr:street":"Melrose Ave",
    "iso:country":"US",
    "sg:address":"8013 Melrose Ave",
    "sg:city":"Los Angeles",
    "sg:classifiers":[
        {
            "category":"Shopping",
            "subcategory":"Clothing, Apparel, & Fashions",
            "type":"Retail Goods"
        },
        {
            "category":"Sports & Exercise",
            "subcategory":"Bicycle Rental",
            "type":"Entertainment"
        }
    ],
    "sg:phone":"+1 323 782 8333",
    "sg:postcode":"90046",
    "sg:province":"CA",
    "sg:tags":[
        "men's",
        "clothing",
        "wear"
    ],
    "sg:website":"www.antikdenim.com",
    "wof:name":"Antik Denim",
    "wof:placetype":"venue"
},
  "geometry": {"coordinates":[-118.364075,34.083805],"type":"Point"}
}