{
  "type": "Feature",
  "properties": {
    "addr:full":"233 Baurer Cir Folsom CA 95630",
    "addr:housenumber":"233",
    "addr:postcode":"95630",
    "addr:street":"Baurer Cir",
    "iso:country":"US",
    "sg:address":"233 Baurer Cir",
    "sg:city":"Folsom",
    "sg:classifiers":[
        {
            "category":"Professional",
            "subcategory":"Business Services",
            "type":"Services"
        }
    ],
    "sg:phone":"+1 916 984 0849",
    "sg:postcode":"95630",
    "sg:province":"CA",
    "sg:tags":[
        "environmental",
        "ecological",
        "product"
    ],
    "wof:name":"Toldot Research",
    "wof:placetype":"venue"
},
  "geometry": {"coordinates":[-121.12333,38.669621],"type":"Point"}
}