{
  "type": "Feature",
  "properties": {
    "iso:country":"US",
    "sg:address":"5821 E Beverly Blvd",
    "sg:city":"Los Angeles",
    "sg:classifiers":[
        {
            "category":"Home & Garden",
            "subcategory":"Building Materials",
            "type":"Retail Goods"
        }
    ],
    "sg:phone":"+1 323 723 3449",
    "sg:postcode":"90022",
    "sg:province":"CA",
    "sg:tags":[
        "glass",
        "window",
        "plate"
    ],
    "wof:name":"A To Z Glass & Mirror",
    "wof:placetype":"venue"
},
  "geometry": {"coordinates":[-118.143677,34.02623],"type":"Point"}
}