{
  "type": "Feature",
  "properties": {
    "iso:country":"US",
    "sg:address":"8987 Trenton Rd",
    "sg:city":"Forestville",
    "sg:classifiers":[
        {
            "category":"Professional",
            "subcategory":"Art Services",
            "type":"Services"
        }
    ],
    "sg:phone":"+1 707 887 1320",
    "sg:postcode":"95436",
    "sg:province":"CA",
    "sg:tags":[
        "commercial",
        "artist"
    ],
    "wof:name":"Robin Dorn Blgcal Illustration",
    "wof:placetype":"venue"
},
  "geometry": {"coordinates":[-122.89905899999999,38.494249],"type":"Point"}
}