{
  "type": "Feature",
  "properties": {
    "iso:country":"US",
    "sg:address":"29232 Edgewood Rd",
    "sg:city":"San Juan Capistrano",
    "sg:classifiers":[
        {
            "category":"Manufacturing",
            "subcategory":"Apparel",
            "type":"Manufacturing & Wholesale Goods"
        }
    ],
    "sg:phone":"+1 949 364 0374",
    "sg:postcode":"92675",
    "sg:province":"CA",
    "sg:tags":[
        "clothing",
        "mfg"
    ],
    "wof:name":"Ckm International",
    "wof:placetype":"venue"
},
  "geometry": {"coordinates":[-117.667326,33.538295],"type":"Point"}
}