{
  "type": "Feature",
  "properties": {
    "iso:country":"US",
    "sg:address":"7960 Soquel Dr",
    "sg:city":"Aptos",
    "sg:classifiers":[
        {
            "category":"Education",
            "subcategory":"Special Training",
            "type":"Public Place"
        }
    ],
    "sg:phone":"+1 831 687 0707",
    "sg:postcode":"95003",
    "sg:province":"CA",
    "sg:tags":[
        "tutoring"
    ],
    "wof:name":"Academic Trainers",
    "wof:placetype":"venue"
},
  "geometry": {"coordinates":[-121.904903,36.976462],"type":"Point"}
}