{
  "type": "Feature",
  "properties": {
    "addr:full":"2800 Palisades Dr Corona CA 92880",
    "addr:housenumber":"2800",
    "addr:postcode":"92880",
    "addr:street":"Palisades Dr",
    "iso:country":"US",
    "sg:address":"2800 Palisades Dr",
    "sg:city":"Corona",
    "sg:classifiers":[
        {
            "category":"Manufacturing",
            "subcategory":"Tools & Machinery",
            "type":"Manufacturing & Wholesale Goods"
        }
    ],
    "sg:phone":"+1 951 739 7000",
    "sg:postcode":"92880",
    "sg:province":"CA",
    "sg:website":"www.eslsys.com",
    "wof:name":"Electrical Syst LTD",
    "wof:placetype":"venue"
},
  "geometry": {"coordinates":[-117.640989,33.880827],"type":"Point"}
}