{
  "type": "Feature",
  "properties": {
    "addr:full":"6408 Lake Isabella Blvd Lake Isabella CA 93240",
    "addr:housenumber":"6408",
    "addr:postcode":"93240",
    "addr:street":"Lake Isabella Blvd",
    "iso:country":"US",
    "sg:address":"6408 Lake Isabella Blvd",
    "sg:city":"Lake Isabella",
    "sg:classifiers":[
        {
            "category":"Shopping",
            "subcategory":"Discount & Variety Stores",
            "type":"Retail Goods"
        }
    ],
    "sg:phone":"+1 760 379 2655",
    "sg:postcode":"93240",
    "sg:province":"CA",
    "sg:tags":[
        "merchandise",
        "general"
    ],
    "wof:name":"Southern Auto Supply",
    "wof:placetype":"venue"
},
  "geometry": {"coordinates":[-118.47301899999999,35.629866],"type":"Point"}
}