{
  "type": "Feature",
  "properties": {
    "iso:country":"US",
    "sg:address":"574 Sutton Way",
    "sg:city":"Grass Valley",
    "sg:classifiers":[
        {
            "category":"Restaurant",
            "type":"Food & Drink"
        }
    ],
    "sg:phone":"+1 530 274 3980",
    "sg:postcode":"95945",
    "sg:province":"CA",
    "wof:name":"Uptown Burrito",
    "wof:placetype":"venue"
},
  "geometry": {"coordinates":[-121.034039,39.227209],"type":"Point"}
}