{
  "type": "Feature",
  "properties": {
    "addr:full":"128 N 4th St Alhambra CA 91801",
    "addr:housenumber":"128",
    "addr:postcode":"91801",
    "addr:street":"N 4Th St",
    "iso:country":"US",
    "sg:address":"128 N 4th St",
    "sg:city":"Alhambra",
    "sg:classifiers":[
        {
            "category":"Health Services",
            "subcategory":"Nursing And Care Facility",
            "type":"Services"
        }
    ],
    "sg:phone":"+1 626 289 3017",
    "sg:postcode":"91801",
    "sg:province":"CA",
    "sg:tags":[
        "home",
        "retirement",
        "community"
    ],
    "wof:name":"My Ladies Guest Home",
    "wof:placetype":"venue"
},
  "geometry": {"coordinates":[-118.132417,34.095016],"type":"Point"}
}