{
  "type": "Feature",
  "properties": {
    "addr:full":"9951 San Pablo Ave El Cerrito CA 94530",
    "addr:housenumber":"9951",
    "addr:postcode":"94530",
    "addr:street":"San Pablo Ave",
    "iso:country":"US",
    "sg:address":"9951 San Pablo Ave",
    "sg:city":"El Cerrito",
    "sg:classifiers":[
        {
            "category":"Sports & Exercise",
            "subcategory":"Gym",
            "type":"Entertainment"
        },
        {
            "category":"Arena",
            "subcategory":"Sports Club",
            "type":"Entertainment"
        }
    ],
    "sg:phone":"+1 510 502 8517",
    "sg:postcode":"94530",
    "sg:province":"CA",
    "sg:tags":[
        "yoga",
        "martial art"
    ],
    "sg:website":"tatamima.com",
    "wof:name":"Tatami Multi Arts",
    "wof:placetype":"venue"
},
  "geometry": {"coordinates":[-122.30217500000001,37.899663],"type":"Point"}
}