{
  "type": "Feature",
  "properties": {
    "iso:country":"US",
    "sg:address":"2448 Presidio Dr",
    "sg:city":"San Diego",
    "sg:classifiers":[
        {
            "category":"Professional",
            "subcategory":"Management & Consulting",
            "type":"Services"
        }
    ],
    "sg:phone":"+1 619 296 8731",
    "sg:postcode":"92103",
    "sg:province":"CA",
    "sg:tags":[
        "marketing",
        "consultant"
    ],
    "wof:name":"Presidio Communications",
    "wof:placetype":"venue"
},
  "geometry": {"coordinates":[-117.191767,32.754834],"type":"Point"}
}