{
  "type": "Feature",
  "properties": {
    "iso:country":"US",
    "sg:address":"13411 Gold Pl",
    "sg:city":"Moreno Valley",
    "sg:classifiers":[
        {
            "category":"Building & Trades",
            "subcategory":"Pest Control",
            "type":"Services"
        }
    ],
    "sg:phone":"+1 951 486 9174",
    "sg:postcode":"92553",
    "sg:province":"CA",
    "wof:name":"Megga Bug Exterminator Co",
    "wof:placetype":"venue"
},
  "geometry": {"coordinates":[-117.218348,33.924974],"type":"Point"}
}