{
  "type": "Feature",
  "properties": {
    "iso:country":"US",
    "sg:address":"27464 Commerce Center Dr",
    "sg:city":"Temecula",
    "sg:classifiers":[
        {
            "category":"Building & Trades",
            "subcategory":"Electrical",
            "type":"Services"
        }
    ],
    "sg:phone":"+1 951 676 3904",
    "sg:postcode":"92590",
    "sg:province":"CA",
    "sg:tags":[
        "electrician"
    ],
    "wof:name":"Elite Electrical Service",
    "wof:placetype":"venue"
},
  "geometry": {"coordinates":[-117.16412,33.515573],"type":"Point"}
}