{
  "type": "Feature",
  "properties": {
    "iso:country":"US",
    "sg:address":"13560 San Antonio Dr",
    "sg:city":"Norwalk",
    "sg:classifiers":[
        {
            "category":"Health Services",
            "subcategory":"Doctor",
            "type":"Services"
        }
    ],
    "sg:phone":"+1 562 807 1877",
    "sg:postcode":"90650",
    "sg:province":"CA",
    "sg:tags":[
        "physician",
        "surgeon"
    ],
    "wof:name":"San Marcos Medical",
    "wof:placetype":"venue"
},
  "geometry": {"coordinates":[-118.076795,33.90754],"type":"Point"}
}