{
  "type": "Feature",
  "properties": {
    "addr:full":"575 S State St Ukiah CA 95482",
    "addr:housenumber":"575",
    "addr:postcode":"ca 95482",
    "addr:street":"S State St",
    "iso:country":"US",
    "sg:address":"575 S State St",
    "sg:city":"Ukiah",
    "sg:classifiers":[
        {
            "category":"Wholesale",
            "subcategory":"Jewelry",
            "type":"Manufacturing & Wholesale Goods"
        }
    ],
    "sg:phone":"+1 707 462 9210",
    "sg:postcode":"95482",
    "sg:province":"CA",
    "sg:tags":[
        "beads",
        "stone"
    ],
    "wof:name":"Beads N Stuff",
    "wof:placetype":"venue"
},
  "geometry": {"coordinates":[-123.206755,39.146203],"type":"Point"}
}