{
  "type": "Feature",
  "properties": {
    "iso:country":"US",
    "sg:address":"12560 San Pablo Ave",
    "sg:city":"Richmond",
    "sg:classifiers":[
        {
            "category":"Professional",
            "subcategory":"Accounting & Tax Preparation",
            "type":"Services"
        }
    ],
    "sg:phone":"+1 510 234 6386",
    "sg:postcode":"94805",
    "sg:province":"CA",
    "sg:tags":[
        "return",
        "filing"
    ],
    "wof:name":"Accounting",
    "wof:placetype":"venue"
},
  "geometry": {"coordinates":[-122.327661,37.940929],"type":"Point"}
}