{
  "type": "Feature",
  "properties": {
    "addr:full":"675 Colusa Ct Dixon CA 95620",
    "addr:housenumber":"675",
    "addr:postcode":"95620",
    "addr:street":"Colusa Ct",
    "iso:country":"US",
    "sg:address":"675 Colusa Ct",
    "sg:city":"Dixon",
    "sg:classifiers":[
        {
            "category":"Wholesale",
            "subcategory":"Toys & Hobbies",
            "type":"Manufacturing & Wholesale Goods"
        }
    ],
    "sg:phone":"+1 707 678 4040",
    "sg:postcode":"95620",
    "sg:province":"CA",
    "wof:name":"Rnz Modeles",
    "wof:placetype":"venue"
},
  "geometry": {"coordinates":[-121.830719,38.449999],"type":"Point"}
}