{
  "type": "Feature",
  "properties": {
    "addr:full":"3185 Thurber Ln Santa Cruz CA 95065",
    "addr:postcode":"3185;95065",
    "addr:street":"Thurber Ln",
    "iso:country":"US",
    "sg:address":"3185 Thurber Ln",
    "sg:city":"Santa Cruz",
    "sg:classifiers":[
        {
            "category":"Social Services",
            "subcategory":"Child Care",
            "type":"Services"
        }
    ],
    "sg:phone":"+1 831 476 6185",
    "sg:postcode":"95065",
    "sg:province":"CA",
    "wof:name":"Montessori Childrens Garden",
    "wof:placetype":"venue"
},
  "geometry": {"coordinates":[-121.978236,36.99212],"type":"Point"}
}