{
  "type": "Feature",
  "properties": {
    "addr:full":"3530 Orcutt Rd Santa Maria CA 93455",
    "addr:housenumber":"3530",
    "addr:postcode":"93455",
    "addr:street":"Orcutt Rd",
    "iso:country":"US",
    "sg:address":"3530 Orcutt Rd",
    "sg:city":"Santa Maria",
    "sg:classifiers":[
        {
            "category":"Recreation",
            "type":"Entertainment"
        }
    ],
    "sg:phone":"+1 805 937 2933",
    "sg:postcode":"93455",
    "sg:province":"CA",
    "sg:tags":[
        "martial",
        "arts",
        "instruction"
    ],
    "sg:website":"www.keichu.com",
    "wof:name":"Calvary Chapel Keichu Do",
    "wof:placetype":"venue"
},
  "geometry": {"coordinates":[-120.436114,34.897073],"type":"Point"}
}