{
  "type": "Feature",
  "properties": {
    "iso:country":"US",
    "sg:address":"21110 Nordhoff St",
    "sg:city":"Chatsworth",
    "sg:classifiers":[
        {
            "category":"Manufacturing",
            "subcategory":"Printing",
            "type":"Manufacturing & Wholesale Goods"
        }
    ],
    "sg:phone":"+1 818 886 6325",
    "sg:postcode":"91311",
    "sg:province":"CA",
    "sg:tags":[
        "commercial",
        "label"
    ],
    "wof:name":"Laser Lithograph",
    "wof:placetype":"venue"
},
  "geometry": {"coordinates":[-118.593888,34.235382],"type":"Point"}
}