{
  "type": "Feature",
  "properties": {
    "iso:country":"US",
    "sg:address":"1611 Oneel Dr",
    "sg:city":"Petaluma",
    "sg:classifiers":[
        {
            "category":"Building & Trades",
            "subcategory":"Construction",
            "type":"Services"
        }
    ],
    "sg:phone":"+1 415 435 5258",
    "sg:postcode":"94954",
    "sg:province":"CA",
    "sg:tags":[
        "masonry",
        "contractor"
    ],
    "wof:name":"Artisan Masonry",
    "wof:placetype":"venue"
},
  "geometry": {"coordinates":[-122.605056,38.24418],"type":"Point"}
}