{
  "type": "Feature",
  "properties": {
    "iso:country":"US",
    "sg:address":"5510 S Soto St",
    "sg:city":"Los Angeles",
    "sg:classifiers":[
        {
            "category":"Manufacturing",
            "subcategory":"Textiles",
            "type":"Manufacturing & Wholesale Goods"
        }
    ],
    "sg:phone":"+1 323 277 0860",
    "sg:postcode":"90058",
    "sg:province":"CA",
    "sg:tags":[
        "leather",
        "mfg",
        "belt"
    ],
    "wof:name":"Streets Ahead Inc",
    "wof:placetype":"venue"
},
  "geometry": {"coordinates":[-118.21933799999999,33.993053],"type":"Point"}
}