{
  "type": "Feature",
  "properties": {
    "iso:country":"US",
    "sg:address":"68449 Perez Rd",
    "sg:city":"Cathedral City",
    "sg:classifiers":[
        {
            "category":"Retail",
            "subcategory":"Repair Shop",
            "type":"Services"
        }
    ],
    "sg:phone":"+1 760 324 4099",
    "sg:postcode":"92234",
    "sg:province":"CA",
    "sg:tags":[
        "repairing",
        "lawn",
        "mower"
    ],
    "wof:name":"Morelia Lawnmower Shop",
    "wof:placetype":"venue"
},
  "geometry": {"coordinates":[-116.469679,33.785029],"type":"Point"}
}