{
  "type": "Feature",
  "properties": {
    "iso:country":"US",
    "sg:address":"3409 Grand Ave",
    "sg:city":"Oakland",
    "sg:classifiers":[
        {
            "category":"Real Estate",
            "subcategory":"Real Estate Agent",
            "type":"Services"
        }
    ],
    "sg:phone":"+1 510 444 5333",
    "sg:postcode":"94610",
    "sg:province":"CA",
    "wof:name":"Merrit Realty & Investment",
    "wof:placetype":"venue"
},
  "geometry": {"coordinates":[-122.24641200000001,37.814289],"type":"Point"}
}