{
  "type": "Feature",
  "properties": {
    "addr:full":"1502 Circa del Lago San Marcos CA 92078",
    "addr:housenumber":"1502",
    "addr:postcode":"92078",
    "addr:street":"Circa Del Lago",
    "iso:country":"US",
    "sg:address":"1502 Circa del Lago",
    "sg:city":"San Marcos",
    "sg:classifiers":[
        {
            "category":"Organizations",
            "subcategory":"Community Association",
            "type":"Services"
        }
    ],
    "sg:phone":"+1 760 471 0083",
    "sg:postcode":"92078",
    "sg:province":"CA",
    "wof:name":"Chateau Lake San Marcos",
    "wof:placetype":"venue"
},
  "geometry": {"coordinates":[-117.21087799999999,33.123538],"type":"Point"}
}