{
  "type": "Feature",
  "properties": {
    "addr:full":"2648 Jamacha Rd El Cajon CA 92019",
    "addr:housenumber":"2648",
    "addr:postcode":"92019",
    "addr:street":"Jamacha Rd",
    "iso:country":"US",
    "sg:address":"2648 Jamacha Rd",
    "sg:city":"El Cajon",
    "sg:classifiers":[
        {
            "category":"Restaurant",
            "type":"Food & Drink"
        }
    ],
    "sg:phone":"+1 619 660 8465",
    "sg:postcode":"92019",
    "sg:province":"CA",
    "wof:name":"Hilberto's Mexican Food",
    "wof:placetype":"venue"
},
  "geometry": {"coordinates":[-116.930722,32.744451],"type":"Point"}
}