{
  "type": "Feature",
  "properties": {
    "iso:country":"US",
    "sg:address":"2443 Dunn Rd",
    "sg:city":"Modesto",
    "sg:classifiers":[
        {
            "category":"Farming",
            "subcategory":"Crops",
            "type":"Manufacturing & Wholesale Goods"
        }
    ],
    "sg:phone":"+1 209 522 4134",
    "sg:postcode":"95358",
    "sg:province":"CA",
    "sg:tags":[
        "grove",
        "nut",
        "tree"
    ],
    "wof:name":"Alfred Quattrin",
    "wof:placetype":"venue"
},
  "geometry": {"coordinates":[-121.141258,37.677867],"type":"Point"}
}