{
  "type": "Feature",
  "properties": {
    "addr:full":"4800 Mascot St Los Angeles CA 90019",
    "addr:postcode":"4800;90019",
    "addr:street":"Mascot St",
    "iso:country":"US",
    "sg:address":"4800 Mascot St",
    "sg:city":"Los Angeles",
    "sg:classifiers":[
        {
            "category":"Professional",
            "type":"Services"
        }
    ],
    "sg:phone":"+1 323 549 0063",
    "sg:postcode":"90019",
    "sg:province":"CA",
    "wof:name":"Doggwear License To Style",
    "wof:placetype":"venue"
},
  "geometry": {"coordinates":[-118.34496799999999,34.040946],"type":"Point"}
}