{
  "type": "Feature",
  "properties": {
    "addr:full":"11961 Perris Blvd Moreno Valley CA 92557",
    "addr:housenumber":"11961",
    "addr:postcode":"92557",
    "addr:street":"Perris Blvd",
    "iso:country":"US",
    "sg:address":"11961 Perris Blvd",
    "sg:city":"Moreno Valley",
    "sg:classifiers":[
        {
            "category":"Social Services",
            "subcategory":"Child Care",
            "type":"Services"
        }
    ],
    "sg:phone":"+1 951 243 6558",
    "sg:postcode":"92557",
    "sg:province":"CA",
    "wof:name":"Kinder Care Learning Ctr",
    "wof:placetype":"venue"
},
  "geometry": {"coordinates":[-117.226493,33.947446],"type":"Point"}
}