{
  "type": "Feature",
  "properties": {
    "iso:country":"US",
    "sg:address":"13371 Ventura Blvd",
    "sg:city":"Sherman Oaks",
    "sg:classifiers":[
        {
            "category":"Health Services",
            "subcategory":"Chiropractor",
            "type":"Services"
        }
    ],
    "sg:phone":"+1 818 700 9900",
    "sg:postcode":"91423",
    "sg:province":"CA",
    "sg:website":"www.cioffichiropractic.com/",
    "wof:name":"Cioffi Chiropractic Center",
    "wof:placetype":"venue"
},
  "geometry": {"coordinates":[-118.42465300000001,34.146951],"type":"Point"}
}