{
  "type": "Feature",
  "properties": {
    "addr:full":"1251 E Pacheco Blvd Los Banos CA 93635",
    "addr:housenumber":"1251",
    "addr:postcode":"93635",
    "addr:street":"E Pacheco Blvd",
    "iso:country":"US",
    "sg:address":"1251 E Pacheco Blvd",
    "sg:city":"Los Banos",
    "sg:classifiers":[
        {
            "category":"Real Estate",
            "subcategory":"Real Estate Agent",
            "type":"Services"
        }
    ],
    "sg:phone":"+1 209 827 9000",
    "sg:postcode":"93635",
    "sg:province":"CA",
    "wof:name":"Dudley Real Estate",
    "wof:placetype":"venue"
},
  "geometry": {"coordinates":[-120.837761,37.056841],"type":"Point"}
}