{
  "type": "Feature",
  "properties": {
    "addr:full":"19278 Manila St Bloomington CA 92316",
    "addr:housenumber":"19278",
    "addr:postcode":"92316",
    "addr:street":"Manila St",
    "iso:country":"US",
    "sg:address":"19278 Manila St",
    "sg:city":"Bloomington",
    "sg:classifiers":[
        {
            "category":"Building & Trades",
            "subcategory":"Construction",
            "type":"Services"
        }
    ],
    "sg:phone":"+1 909 824 8705",
    "sg:postcode":"92316",
    "sg:province":"CA",
    "sg:tags":[
        "concrete",
        "cutting",
        "breaking",
        "sawing"
    ],
    "wof:name":"Roberts Concrete Cutting",
    "wof:placetype":"venue"
},
  "geometry": {"coordinates":[-117.387197,34.057844],"type":"Point"}
}