{
  "type": "Feature",
  "properties": {
    "addr:full":"9745 Foothill Blvd Rancho Cucamonga CA 91730",
    "addr:housenumber":"9745",
    "addr:postcode":"91730",
    "addr:street":"Foothill Blvd",
    "iso:country":"US",
    "sg:address":"9745 Foothill Blvd",
    "sg:city":"Rancho Cucamonga",
    "sg:classifiers":[
        {
            "category":"Building & Trades",
            "subcategory":"Construction",
            "type":"Services"
        }
    ],
    "sg:phone":"+1 909 980 2307",
    "sg:postcode":"91730",
    "sg:province":"CA",
    "sg:tags":[
        "glass"
    ],
    "wof:name":"Mountain View Glass & Mirror",
    "wof:placetype":"venue"
},
  "geometry": {"coordinates":[-117.590084,34.10655],"type":"Point"}
}