{
  "type": "Feature",
  "properties": {
    "addr:full":"525 Houston St West Sacramento CA 95691",
    "addr:housenumber":"525",
    "addr:postcode":"95691",
    "addr:street":"Houston St",
    "iso:country":"US",
    "sg:address":"525 Houston St",
    "sg:city":"West Sacramento",
    "sg:classifiers":[
        {
            "category":"Retail",
            "subcategory":"Auto Repair",
            "type":"Services"
        }
    ],
    "sg:phone":"+1 916 374 1833",
    "sg:postcode":"95691",
    "sg:province":"CA",
    "sg:tags":[
        "repairing",
        "automobile"
    ],
    "wof:name":"Golden River",
    "wof:placetype":"venue"
},
  "geometry": {"coordinates":[-121.550904,38.580701],"type":"Point"}
}