{
  "type": "Feature",
  "properties": {
    "iso:country":"US",
    "sg:address":"15125 Ventura Blvd",
    "sg:city":"Sherman Oaks",
    "sg:classifiers":[
        {
            "category":"Shopping",
            "type":"Retail Goods"
        }
    ],
    "sg:phone":"+1 818 788 7333",
    "sg:postcode":"91403",
    "sg:province":"CA",
    "sg:tags":[
        "telephone",
        "cellular"
    ],
    "wof:name":"Best Cellular Distr",
    "wof:placetype":"venue"
},
  "geometry": {"coordinates":[-118.46359699999999,34.153446],"type":"Point"}
}