{
  "type": "Feature",
  "properties": {
    "iso:country":"US",
    "sg:address":"6109 Cam Real",
    "sg:city":"Riverside",
    "sg:classifiers":[
        {
            "category":"Manufacturing",
            "subcategory":"Printing",
            "type":"Manufacturing & Wholesale Goods"
        }
    ],
    "sg:phone":"+1 951 681 2925",
    "sg:postcode":"92509",
    "sg:province":"CA",
    "sg:tags":[
        "newspaper"
    ],
    "wof:name":"Jurupa Press Enterprise",
    "wof:placetype":"venue"
},
  "geometry": {"coordinates":[-117.451476,33.978207],"type":"Point"}
}