{
  "type": "Feature",
  "properties": {
    "addr:full":"3203 W Jefferson Blvd Los Angeles CA 90018",
    "addr:housenumber":"3203",
    "addr:postcode":"90018",
    "addr:street":"W Jefferson Blvd",
    "iso:country":"US",
    "sg:address":"3203 W Jefferson Blvd",
    "sg:city":"Los Angeles",
    "sg:classifiers":[
        {
            "category":"Autos & Motor Vehicles",
            "subcategory":"Fuel & Gas Station",
            "type":"Retail Goods"
        }
    ],
    "sg:phone":"+1 323 735 8479",
    "sg:postcode":"90018",
    "sg:province":"CA",
    "wof:name":"J & J Auto Service Center",
    "wof:placetype":"venue"
},
  "geometry": {"coordinates":[-118.331001,34.025501],"type":"Point"}
}