{
  "type": "Feature",
  "properties": {
    "addr:full":"1670 Kettner Blvd Apt 319 San Diego CA 92101",
    "addr:housenumber":"1670;319",
    "addr:postcode":"92101",
    "addr:street":"Kettner Blvd Apt",
    "iso:country":"US",
    "sg:address":"1670 Kettner Blvd Apt 319",
    "sg:city":"San Diego",
    "sg:classifiers":[
        {
            "category":"Real Estate",
            "subcategory":"Real Estate Operator",
            "type":"Services"
        }
    ],
    "sg:phone":"+1 619 269 6792",
    "sg:postcode":"92101",
    "sg:province":"CA",
    "sg:tags":[
        "apartment"
    ],
    "wof:name":"Camden Tuscany",
    "wof:placetype":"venue"
},
  "geometry": {"coordinates":[-117.169144,32.722697],"type":"Point"}
}