{
  "type": "Feature",
  "properties": {
    "iso:country":"US",
    "sg:address":"5406 Whitsett Ave",
    "sg:city":"Valley Village",
    "sg:classifiers":[
        {
            "category":"Food & Beverages",
            "subcategory":"Groceries & Convenience Stores",
            "type":"Retail Goods"
        }
    ],
    "sg:phone":"+1 818 766 0779",
    "sg:postcode":"91607",
    "sg:province":"CA",
    "wof:name":"Fast Stop Mini Mart",
    "wof:placetype":"venue"
},
  "geometry": {"coordinates":[-118.404999,34.168999],"type":"Point"}
}