{
  "type": "Feature",
  "properties": {
    "iso:country":"US",
    "sg:address":"2431 Capitol Avenue",
    "sg:city":"Sacramento",
    "sg:classifiers":[
        {
            "category":"Professional",
            "subcategory":"Lawyer & Legal Services",
            "type":"Services"
        }
    ],
    "sg:phone":"+1 916 557 8007",
    "sg:postcode":"95816",
    "sg:province":"CA",
    "wof:name":"Slater Charles C Law Offices of",
    "wof:placetype":"venue"
},
  "geometry": {"coordinates":[-121.47488300000001,38.571763],"type":"Point"}
}