{
  "type": "Feature",
  "properties": {
    "iso:country":"US",
    "sg:address":"5226 E Olive Ave",
    "sg:city":"Fresno",
    "sg:classifiers":[
        {
            "category":"Real Estate",
            "subcategory":"Real Estate Operator",
            "type":"Services"
        }
    ],
    "sg:phone":"+1 559 255 5226",
    "sg:postcode":"93727",
    "sg:province":"CA",
    "sg:tags":[
        "apartment"
    ],
    "wof:name":"Olive Glen Apartments",
    "wof:placetype":"venue"
},
  "geometry": {"coordinates":[-119.71780800000001,36.75739],"type":"Point"}
}