{
  "type": "Feature",
  "properties": {
    "iso:country":"US",
    "sg:address":"1940 Garnet Ave Ste 220",
    "sg:city":"San Diego",
    "sg:classifiers":[
        {
            "category":"Professional",
            "subcategory":"Lawyer & Legal Services",
            "type":"Services"
        }
    ],
    "sg:phone":"+1 858 272 0227",
    "sg:postcode":"92109",
    "sg:province":"CA",
    "wof:name":"IP Legal Advisors",
    "wof:placetype":"venue"
},
  "geometry": {"coordinates":[-117.234613,32.801297],"type":"Point"}
}