{
  "type": "Feature",
  "properties": {
    "iso:country":"US",
    "sg:address":"32880 Nameless Ln",
    "sg:city":"Fort Bragg",
    "sg:classifiers":[
        {
            "category":"Health Services",
            "subcategory":"Chiropractor",
            "type":"Services"
        }
    ],
    "sg:phone":"+1 707 961 1472",
    "sg:postcode":"95437",
    "sg:province":"CA",
    "wof:name":"East West Healing Arts & Sci",
    "wof:placetype":"venue"
},
  "geometry": {"coordinates":[-123.777455,39.493427],"type":"Point"}
}