{
  "type": "Feature",
  "properties": {
    "iso:country":"US",
    "sg:address":"343 E Main St",
    "sg:city":"Stockton",
    "sg:classifiers":[
        {
            "category":"Professional",
            "subcategory":"Management & Consulting",
            "type":"Services"
        }
    ],
    "sg:phone":"+1 209 235 2408",
    "sg:postcode":"95202",
    "sg:province":"CA",
    "sg:tags":[
        "communications",
        "consultant"
    ],
    "sg:website":"www.chapinphd.com",
    "wof:name":"Charles Chapin & Assoc",
    "wof:placetype":"venue"
},
  "geometry": {"coordinates":[-121.28635199999999,37.953336],"type":"Point"}
}