{
  "type": "Feature",
  "properties": {
    "iso:country":"US",
    "sg:address":"27702 Homestead Rd",
    "sg:city":"Laguna Niguel",
    "sg:classifiers":[
        {
            "category":"Building & Trades",
            "subcategory":"Construction",
            "type":"Services"
        }
    ],
    "sg:phone":"+1 949 831 5460",
    "sg:postcode":"92677",
    "sg:province":"CA",
    "sg:tags":[
        "contractor"
    ],
    "wof:name":"S S Construction",
    "wof:placetype":"venue"
},
  "geometry": {"coordinates":[-117.700996,33.5602],"type":"Point"}
}