{
  "type": "Feature",
  "properties": {
    "addr:full":"2048 Dunlap Dr South Lake Tahoe CA 96150",
    "addr:housenumber":"2048",
    "addr:postcode":"96150",
    "addr:street":"Dunlap Dr",
    "iso:country":"US",
    "sg:address":"2048 Dunlap Dr",
    "sg:city":"South Lake Tahoe",
    "sg:classifiers":[
        {
            "category":"Travel",
            "subcategory":"Hotels & Motels",
            "type":"Entertainment"
        }
    ],
    "sg:phone":"+1 530 544 3234",
    "sg:postcode":"96150",
    "sg:province":"CA",
    "wof:name":"Lakeland Village Accomdtns",
    "wof:placetype":"venue"
},
  "geometry": {"coordinates":[-120.00395399999999,38.913959],"type":"Point"}
}