{
  "type": "Feature",
  "properties": {
    "addr:full":"3848 McHenry Ave Modesto CA 95356",
    "addr:housenumber":"3848",
    "addr:postcode":"ca 95356",
    "addr:street":"Mchenry Ave",
    "iso:country":"US",
    "sg:address":"3848 McHenry Ave",
    "sg:city":"Modesto",
    "sg:classifiers":[
        {
            "category":"Personal",
            "subcategory":"Beauty Salon",
            "type":"Services"
        }
    ],
    "sg:phone":"+1 209 577 4813",
    "sg:postcode":"95356",
    "sg:province":"CA",
    "sg:tags":[
        "manicuring"
    ],
    "wof:name":"Tip 2 Toe",
    "wof:placetype":"venue"
},
  "geometry": {"coordinates":[-120.994311,37.695073],"type":"Point"}
}