{
  "type": "Feature",
  "properties": {
    "addr:full":"825 Lincoln Way Auburn CA 95603",
    "addr:housenumber":"825",
    "addr:postcode":"ca 95603",
    "addr:street":"Lincoln Way",
    "iso:country":"US",
    "sg:address":"825 Lincoln Way",
    "sg:city":"Auburn",
    "sg:classifiers":[
        {
            "category":"Shopping",
            "subcategory":"Shoes",
            "type":"Retail Goods"
        }
    ],
    "sg:phone":"+1 530 885 2091",
    "sg:postcode":"95603",
    "sg:province":"CA",
    "wof:name":"Footpath",
    "wof:placetype":"venue"
},
  "geometry": {"coordinates":[-121.068388,38.900274],"type":"Point"}
}