{
  "type": "Feature",
  "properties": {
    "iso:country":"US",
    "sg:address":"555 Main St",
    "sg:city":"Chico",
    "sg:classifiers":[
        {
            "category":"Real Estate",
            "subcategory":"Architect",
            "type":"Services"
        }
    ],
    "sg:phone":"+1 530 891 1710",
    "sg:postcode":"95928",
    "sg:province":"CA",
    "sg:website":"www.nmrdesign.com",
    "wof:name":"Nichols Melburg & Rossetto",
    "wof:placetype":"venue"
},
  "geometry": {"coordinates":[-121.837601,39.727903],"type":"Point"}
}