{
  "type": "Feature",
  "properties": {
    "addr:full":"2027 E Florence Ave Los Angeles CA 90001",
    "addr:housenumber":"2027",
    "addr:postcode":"90001",
    "addr:street":"E Florence Ave",
    "iso:country":"US",
    "sg:address":"2027 E Florence Ave",
    "sg:city":"Los Angeles",
    "sg:classifiers":[
        {
            "category":"Retail",
            "subcategory":"Veterinary Services",
            "type":"Services"
        }
    ],
    "sg:phone":"+1 323 588 8968",
    "sg:postcode":"90001",
    "sg:province":"CA",
    "sg:tags":[
        "veterinarian"
    ],
    "wof:name":"V I P Veterinary Service",
    "wof:placetype":"venue"
},
  "geometry": {"coordinates":[-118.234629,33.974867],"type":"Point"}
}