{
  "type": "Feature",
  "properties": {
    "addr:full":"1584 Van Ness Ave Fresno CA 93721",
    "addr:housenumber":"1584",
    "addr:postcode":"93721",
    "addr:street":"Van Ness Ave",
    "iso:country":"US",
    "sg:address":"1584 Van Ness Ave",
    "sg:city":"Fresno",
    "sg:classifiers":[
        {
            "category":"Organizations",
            "subcategory":"Political Organization",
            "type":"Services"
        }
    ],
    "sg:phone":"+1 559 487 2515",
    "sg:postcode":"93721",
    "sg:province":"CA",
    "wof:name":"Peace Fresno",
    "wof:placetype":"venue"
},
  "geometry": {"coordinates":[-119.794687,36.7398],"type":"Point"}
}