{
  "type": "Feature",
  "properties": {
    "addr:full":"2430 Cypress Way Fullerton CA 92831",
    "addr:housenumber":"2430",
    "addr:postcode":"92831",
    "addr:street":"Cypress Way",
    "iso:country":"US",
    "sg:address":"2430 Cypress Way",
    "sg:city":"Fullerton",
    "sg:classifiers":[
        {
            "category":"Professional",
            "type":"Services"
        }
    ],
    "sg:phone":"+1 714 441 1527",
    "sg:postcode":"92831",
    "sg:province":"CA",
    "sg:website":"www.rohnermachinery.com",
    "wof:name":"Rohner Machinery Sales, Inc",
    "wof:placetype":"venue"
},
  "geometry": {"coordinates":[-117.88735699999999,33.860873],"type":"Point"}
}