{
  "type": "Feature",
  "properties": {
    "iso:country":"US",
    "sg:address":"1700 Colfax St",
    "sg:city":"Concord",
    "sg:classifiers":[
        {
            "category":"Building & Trades",
            "subcategory":"Construction",
            "type":"Services"
        }
    ],
    "sg:phone":"+1 925 676 1096",
    "sg:postcode":"94520",
    "sg:province":"CA",
    "sg:tags":[
        "roofing",
        "industrial",
        "contractors-commercial",
        "contractor"
    ],
    "wof:name":"Salgueras Roofing",
    "wof:placetype":"venue"
},
  "geometry": {"coordinates":[-122.030388,37.975868],"type":"Point"}
}