{
  "type": "Feature",
  "properties": {
    "addr:full":"4202 el Cajon Blvd San Diego CA 92105",
    "addr:housenumber":"4202",
    "addr:postcode":"92105",
    "addr:street":"El Cajon Blvd",
    "iso:country":"US",
    "sg:address":"4202 el Cajon Blvd",
    "sg:city":"San Diego",
    "sg:classifiers":[
        {
            "category":"Banks & Credit Unions",
            "subcategory":"Bank",
            "type":"Services"
        }
    ],
    "sg:phone":"+1 619 281 2274",
    "sg:postcode":"92105",
    "sg:province":"CA",
    "sg:tags":[
        "cashing",
        "check"
    ],
    "wof:name":"Money Express",
    "wof:placetype":"venue"
},
  "geometry": {"coordinates":[-117.104563,32.755218],"type":"Point"}
}