{
  "type": "Feature",
  "properties": {
    "addr:full":"1205 Coleman Ave Santa Clara CA 95110",
    "addr:housenumber":"1205",
    "addr:postcode":"95110",
    "addr:street":"Coleman Ave",
    "iso:country":"US",
    "sg:address":"1205 Coleman Ave",
    "sg:city":"Santa Clara",
    "sg:classifiers":[
        {
            "category":"Wholesale",
            "subcategory":"Durable Goods & Equipment",
            "type":"Manufacturing & Wholesale Goods"
        }
    ],
    "sg:phone":"+1 408 289 2781",
    "sg:postcode":"95110",
    "sg:province":"CA",
    "wof:name":"FMC Corporation",
    "wof:placetype":"venue"
},
  "geometry": {"coordinates":[-121.934664,37.356704],"type":"Point"}
}