{
  "type": "Feature",
  "properties": {
    "iso:country":"US",
    "sg:address":"827 S Santa Anita Ave",
    "sg:city":"San Marino",
    "sg:classifiers":[
        {
            "category":"Professional",
            "type":"Services"
        }
    ],
    "sg:phone":"+1 626 576 1936",
    "sg:postcode":"91108",
    "sg:province":"CA",
    "wof:name":"Upickhome Co",
    "wof:placetype":"venue"
},
  "geometry": {"coordinates":[-118.098938,34.131142],"type":"Point"}
}