{
  "type": "Feature",
  "properties": {
    "addr:full":"412 Alamatos Dr Danville CA 94526",
    "addr:housenumber":"412",
    "addr:postcode":"94526",
    "addr:street":"Alamatos Dr",
    "iso:country":"US",
    "sg:address":"412 Alamatos Dr",
    "sg:city":"Danville",
    "sg:classifiers":[
        {
            "category":"Shopping",
            "subcategory":"Computers & Home Electronics",
            "type":"Retail Goods"
        }
    ],
    "sg:phone":"+1 925 855 1818",
    "sg:postcode":"94526",
    "sg:province":"CA",
    "sg:tags":[
        "publishing"
    ],
    "wof:name":"Elana O'Loskey",
    "wof:placetype":"venue"
},
  "geometry": {"coordinates":[-121.990796,37.824869],"type":"Point"}
}