{
  "type": "Feature",
  "properties": {
    "addr:full":"1516 Westwood Blvd Los Angeles CA 90024",
    "addr:housenumber":"1516",
    "addr:postcode":"90024",
    "addr:street":"Westwood Blvd",
    "iso:country":"US",
    "sg:address":"1516 Westwood Blvd",
    "sg:city":"Los Angeles",
    "sg:classifiers":[
        {
            "category":"Professional",
            "subcategory":"Employment Agencies",
            "type":"Services"
        }
    ],
    "sg:phone":"+1 310 441 0304",
    "sg:postcode":"90024",
    "sg:province":"CA",
    "sg:tags":[
        "help",
        "contractor"
    ],
    "sg:website":"www.mcr4jobs.com",
    "wof:name":"Managed Care Resources",
    "wof:placetype":"venue"
},
  "geometry": {"coordinates":[-118.439718,34.053121],"type":"Point"}
}