{
  "type": "Feature",
  "properties": {
    "addr:full":"41 Hangar Way Watsonville CA 95076",
    "addr:housenumber":"41",
    "addr:postcode":"95076",
    "addr:street":"Hangar Way",
    "iso:country":"US",
    "sg:address":"41 Hangar Way",
    "sg:city":"Watsonville",
    "sg:classifiers":[
        {
            "category":"Restaurant",
            "type":"Food & Drink"
        }
    ],
    "sg:phone":"+1 831 724 5585",
    "sg:postcode":"95076",
    "sg:province":"CA",
    "sg:tags":[
        "caterer"
    ],
    "wof:name":"Sous City Catering",
    "wof:placetype":"venue"
},
  "geometry": {"coordinates":[-121.791123,36.930863],"type":"Point"}
}