{
  "type": "Feature",
  "properties": {
    "addr:full":"1091 N Shoreline Blvd Mountain View CA 94043",
    "addr:housenumber":"1091",
    "addr:postcode":"94043",
    "addr:street":"N Shoreline Blvd",
    "iso:country":"US",
    "sg:address":"1091 N Shoreline Blvd",
    "sg:city":"Mountain View",
    "sg:classifiers":[
        {
            "category":"Insurance",
            "subcategory":"Insurance Agent",
            "type":"Services"
        }
    ],
    "sg:phone":"+1 650 964 8000",
    "sg:postcode":"94043",
    "sg:province":"CA",
    "sg:website":"www.lawson-hawks.com",
    "wof:name":"Lawson-Hawks Insurance Assoc",
    "wof:placetype":"venue"
},
  "geometry": {"coordinates":[-122.078031,37.408636],"type":"Point"}
}