{
  "type": "Feature",
  "properties": {
    "addr:full":"15705 Condon Ave Lawndale CA 90260",
    "addr:postcode":"15705;ca 90260",
    "addr:street":"Condon Ave",
    "iso:country":"US",
    "sg:address":"15705 Condon Ave",
    "sg:city":"Lawndale",
    "sg:classifiers":[
        {
            "category":"Shopping",
            "subcategory":"Gifts & Souvenirs",
            "type":"Retail Goods"
        }
    ],
    "sg:phone":"+1 310 643 6329",
    "sg:postcode":"90260",
    "sg:province":"CA",
    "sg:tags":[
        "shop"
    ],
    "wof:name":"Dora Moda Gifts & Accessories",
    "wof:placetype":"venue"
},
  "geometry": {"coordinates":[-118.360072,33.889419],"type":"Point"}
}