{
  "type": "Feature",
  "properties": {
    "addr:full":"23770 S Western Ave Los Angeles CA 90710",
    "addr:housenumber":"23770",
    "addr:postcode":"90710",
    "addr:street":"S Western Ave",
    "iso:country":"US",
    "sg:address":"23770 S Western Ave",
    "sg:city":"Los Angeles",
    "sg:classifiers":[
        {
            "category":"Restaurant",
            "type":"Food & Drink"
        }
    ],
    "sg:phone":"+1 310 539 2742",
    "sg:postcode":"90710",
    "sg:province":"CA",
    "sg:tags":[
        "thai"
    ],
    "wof:name":"@First Taste Thai Fusion",
    "wof:placetype":"venue"
},
  "geometry": {"coordinates":[-118.30785400000001,33.808257],"type":"Point"}
}