{
  "type": "Feature",
  "properties": {
    "addr:full":"11018 Rosecrans Ave Norwalk CA 90650",
    "addr:housenumber":"11018",
    "addr:postcode":"90650",
    "addr:street":"Rosecrans Ave",
    "iso:country":"US",
    "sg:address":"11018 Rosecrans Ave",
    "sg:city":"Norwalk",
    "sg:classifiers":[
        {
            "category":"Building & Trades",
            "subcategory":"Plumbing",
            "type":"Services"
        }
    ],
    "sg:phone":"+1 714 271 3339",
    "sg:postcode":"90650",
    "sg:province":"CA",
    "sg:tags":[
        "contractor"
    ],
    "wof:name":"Js Rooter Plumbing",
    "wof:placetype":"venue"
},
  "geometry": {"coordinates":[-118.097751,33.901963],"type":"Point"}
}