{
  "type": "Feature",
  "properties": {
    "iso:country":"US",
    "sg:address":"738 Elizabeth St",
    "sg:city":"San Francisco",
    "sg:classifiers":[
        {
            "category":"Building & Trades",
            "subcategory":"Construction",
            "type":"Services"
        }
    ],
    "sg:phone":"+1 415 821 0407",
    "sg:postcode":"94114",
    "sg:province":"CA",
    "sg:tags":[
        "contractor"
    ],
    "sg:website":"jeffreygoffoconstruction.info",
    "wof:name":"Jeffrey Goffo Construction",
    "wof:placetype":"venue"
},
  "geometry": {"coordinates":[-122.437279,37.752151],"type":"Point"}
}