{
  "type": "Feature",
  "properties": {
    "addr:full":"359 E Main St Ventura CA 93001",
    "addr:housenumber":"359",
    "addr:postcode":"93001",
    "addr:street":"E Main St",
    "iso:country":"US",
    "sg:address":"359 E Main St",
    "sg:city":"Ventura",
    "sg:classifiers":[
        {
            "category":"Arts & Performance",
            "subcategory":"Theater",
            "type":"Entertainment"
        }
    ],
    "sg:phone":"+1 805 653 9068",
    "sg:postcode":"93001",
    "sg:province":"CA",
    "sg:tags":[
        "entertainer"
    ],
    "wof:name":"S B Books Inc",
    "wof:placetype":"venue"
},
  "geometry": {"coordinates":[-119.295405,34.280884],"type":"Point"}
}