{
  "type": "Feature",
  "properties": {
    "iso:country":"US",
    "sg:address":"2540 San Antonio Cres E",
    "sg:city":"Upland",
    "sg:classifiers":[
        {
            "category":"Manufacturing",
            "subcategory":"Tools & Machinery",
            "type":"Manufacturing & Wholesale Goods"
        }
    ],
    "sg:phone":"+1 909 985 5644",
    "sg:postcode":"91784",
    "sg:province":"CA",
    "sg:tags":[
        "copier",
        "manufacturer",
        "photographic",
        "supplies-wholesale",
        "mfg"
    ],
    "sg:website":"http://www.camforce.com",
    "wof:name":"Cam Force",
    "wof:placetype":"venue"
},
  "geometry": {"coordinates":[-117.655174,34.157369],"type":"Point"}
}