{
  "type": "Feature",
  "properties": {
    "iso:country":"US",
    "sg:address":"19 Park Ter",
    "sg:city":"Mill Valley",
    "sg:classifiers":[
        {
            "category":"Retail",
            "subcategory":"Repair Shop",
            "type":"Services"
        }
    ],
    "sg:phone":"+1 415 383 1054",
    "sg:postcode":"94941",
    "sg:province":"CA",
    "sg:tags":[
        "antique",
        "restoring"
    ],
    "wof:name":"Gepetto's",
    "wof:placetype":"venue"
},
  "geometry": {"coordinates":[-122.534379,37.897522],"type":"Point"}
}