{
  "type": "Feature",
  "properties": {
    "addr:full":"1001 S Main St Yreka CA 96097",
    "addr:housenumber":"1001",
    "addr:postcode":"96097",
    "addr:street":"S Main St",
    "iso:country":"US",
    "sg:address":"1001 S Main St",
    "sg:city":"Yreka",
    "sg:classifiers":[
        {
            "category":"Real Estate",
            "subcategory":"Real Estate Agent",
            "type":"Services"
        }
    ],
    "sg:phone":"+1 530 842 9300",
    "sg:postcode":"96097",
    "sg:province":"CA",
    "wof:name":"Remax Heritage Properties",
    "wof:placetype":"venue"
},
  "geometry": {"coordinates":[-122.638974,41.722902],"type":"Point"}
}