{
  "type": "Feature",
  "properties": {
    "iso:country":"US",
    "sg:address":"23943 Catamaran Way",
    "sg:city":"Laguna Niguel",
    "sg:classifiers":[
        {
            "category":"Real Estate",
            "subcategory":"Real Estate Agent",
            "type":"Services"
        }
    ],
    "sg:phone":"+1 949 212 1226",
    "sg:postcode":"92677",
    "sg:province":"CA",
    "sg:tags":[
        "inspection"
    ],
    "wof:name":"R Z Home Inspections",
    "wof:placetype":"venue"
},
  "geometry": {"coordinates":[-117.713157,33.494619],"type":"Point"}
}