{
  "type": "Feature",
  "properties": {
    "iso:country":"US",
    "sg:address":"23990 Hesperian Blvd",
    "sg:city":"Hayward",
    "sg:classifiers":[
        {
            "category":"Retail",
            "subcategory":"Auto Repair",
            "type":"Services"
        }
    ],
    "sg:phone":"+1 510 786 6500",
    "sg:postcode":"94541",
    "sg:province":"CA",
    "wof:name":"Winton Autotech Inc.",
    "wof:placetype":"venue"
},
  "geometry": {"coordinates":[-122.11002999999999,37.653475],"type":"Point"}
}