{
  "type": "Feature",
  "properties": {
    "addr:full":"10308 International Blvd Oakland CA 94603",
    "addr:housenumber":"10308",
    "addr:postcode":"94603",
    "addr:street":"International Blvd",
    "iso:country":"US",
    "sg:address":"10308 International Blvd",
    "sg:city":"Oakland",
    "sg:classifiers":[
        {
            "category":"Personal",
            "subcategory":"Beauty Salon",
            "type":"Services"
        }
    ],
    "sg:phone":"+1 510 638 6381",
    "sg:postcode":"94603",
    "sg:province":"CA",
    "sg:tags":[
        "hair"
    ],
    "wof:name":"Latina Salon",
    "wof:placetype":"venue"
},
  "geometry": {"coordinates":[-122.167,37.740101],"type":"Point"}
}