{
  "type": "Feature",
  "properties": {
    "addr:full":"3249 Fordham Street San Diego CA 92110",
    "addr:housenumber":"3249",
    "addr:postcode":"92110",
    "addr:street":"Fordham Street",
    "iso:country":"US",
    "sg:address":"3249 Fordham Street",
    "sg:city":"San Diego",
    "sg:classifiers":[
        {
            "category":"Education",
            "subcategory":"School",
            "type":"Public Place"
        }
    ],
    "sg:phone":"+1 858 490 8500",
    "sg:postcode":"92110",
    "sg:province":"CA",
    "sg:tags":[
        "high",
        "middle",
        "elementary"
    ],
    "wof:name":"San Diego Unified School District",
    "wof:placetype":"venue"
},
  "geometry": {"coordinates":[-117.21498,32.749867],"type":"Point"}
}