{
  "type": "Feature",
  "properties": {
    "addr:full":"10423 Valley Blvd Unit C El Monte CA 91731",
    "addr:housenumber":"10423",
    "addr:postcode":"91731",
    "addr:street":"Valley Blvd Unit C",
    "iso:country":"US",
    "sg:address":"10423 Valley Blvd Unit C",
    "sg:city":"El Monte",
    "sg:classifiers":[
        {
            "category":"Professional",
            "subcategory":"Computer Services",
            "type":"Services"
        }
    ],
    "sg:phone":"+1 626 450 0606",
    "sg:postcode":"91731",
    "sg:province":"CA",
    "sg:tags":[
        "repair"
    ],
    "sg:website":"www.computerguruofla.com",
    "wof:name":"Computer Guru",
    "wof:placetype":"venue"
},
  "geometry": {"coordinates":[-118.045343,34.07716],"type":"Point"}
}