{
  "type": "Feature",
  "properties": {
    "iso:country":"US",
    "sg:address":"222 Arc Ave",
    "sg:city":"Stockton",
    "sg:classifiers":[
        {
            "category":"Building & Trades",
            "subcategory":"Landscaping Services",
            "type":"Services"
        }
    ],
    "sg:phone":"+1 209 478 1668",
    "sg:postcode":"95210",
    "sg:province":"CA",
    "sg:tags":[
        "lawn",
        "maintenance",
        "grounds"
    ],
    "wof:name":"8-Correa-8 Gardening Svc",
    "wof:placetype":"venue"
},
  "geometry": {"coordinates":[-121.31931,38.021381],"type":"Point"}
}