{
  "type": "Feature",
  "properties": {
    "addr:full":"424 Wilson Dr Santa Maria CA 93455",
    "addr:housenumber":"424",
    "addr:postcode":"93455",
    "addr:street":"Wilson Dr",
    "iso:country":"US",
    "sg:address":"424 Wilson Dr",
    "sg:city":"Santa Maria",
    "sg:classifiers":[
        {
            "category":"Communications",
            "subcategory":"Radio Station",
            "type":"Services"
        }
    ],
    "sg:phone":"+1 805 938 0075",
    "sg:postcode":"93455",
    "sg:province":"CA",
    "sg:tags":[
        "broadcast"
    ],
    "wof:name":"Multiple Learng Syst",
    "wof:placetype":"venue"
},
  "geometry": {"coordinates":[-120.44132,34.868403],"type":"Point"}
}