{
  "type": "Feature",
  "properties": {
    "iso:country":"US",
    "sg:address":"505 Evergreen Ave",
    "sg:city":"Arcata",
    "sg:classifiers":[
        {
            "category":"Retail",
            "subcategory":"Portrait Studio",
            "type":"Services"
        }
    ],
    "sg:phone":"+1 707 822 8273",
    "sg:postcode":"95521",
    "sg:province":"CA",
    "sg:tags":[
        "photographer"
    ],
    "wof:name":"Eyelight Studio",
    "wof:placetype":"venue"
},
  "geometry": {"coordinates":[-124.07975,40.881005],"type":"Point"}
}