{
  "type": "Feature",
  "properties": {
    "addr:full":"704 Hindry Ave Inglewood CA 90301",
    "addr:housenumber":"704",
    "addr:postcode":"90301",
    "addr:street":"Hindry Ave",
    "iso:country":"US",
    "sg:address":"704 Hindry Ave",
    "sg:city":"Inglewood",
    "sg:classifiers":[
        {
            "category":"Airline",
            "type":"Transportation"
        }
    ],
    "sg:phone":"+1 310 216 4300",
    "sg:postcode":"90301",
    "sg:province":"CA",
    "sg:tags":[
        "cargo",
        "air"
    ],
    "wof:name":"Stevens Air Transport",
    "wof:placetype":"venue"
},
  "geometry": {"coordinates":[-118.373451,33.954733],"type":"Point"}
}