{
  "type": "Feature",
  "properties": {
    "iso:country":"US",
    "sg:address":"18730 8th St",
    "sg:city":"Bloomington",
    "sg:classifiers":[
        {
            "category":"Autos & Motor Vehicles",
            "subcategory":"Automobile Sales",
            "type":"Retail Goods"
        }
    ],
    "sg:phone":"+1 909 874 2277",
    "sg:postcode":"92316",
    "sg:province":"CA",
    "sg:tags":[
        "dealers-used",
        "car",
        "used",
        "cars-wholesale"
    ],
    "wof:name":"Select Imports",
    "wof:placetype":"venue"
},
  "geometry": {"coordinates":[-117.395703,34.041359],"type":"Point"}
}