{
  "type": "Feature",
  "properties": {
    "iso:country":"US",
    "sg:address":"204 E 4th St",
    "sg:city":"Santa Ana",
    "sg:classifiers":[
        {
            "category":"Professional",
            "subcategory":"Lawyer & Legal Services",
            "type":"Services"
        }
    ],
    "sg:phone":"+1 714 953 9920",
    "sg:postcode":"92701",
    "sg:province":"CA",
    "sg:tags":[
        "clinic"
    ],
    "wof:name":"M & H Latin Business Svc",
    "wof:placetype":"venue"
},
  "geometry": {"coordinates":[-117.865625,33.747925],"type":"Point"}
}