{
  "type": "Feature",
  "properties": {
    "addr:full":"24195 Hollyoak Aliso Viejo CA 92656",
    "addr:postcode":"24195;92656",
    "addr:street":"Hollyoak",
    "iso:country":"US",
    "sg:address":"24195 Hollyoak",
    "sg:city":"Aliso Viejo",
    "sg:classifiers":[
        {
            "category":"Wholesale",
            "subcategory":"Durable Goods & Equipment",
            "type":"Manufacturing & Wholesale Goods"
        }
    ],
    "sg:phone":"+1 949 831 0990",
    "sg:postcode":"92656",
    "sg:province":"CA",
    "wof:name":"Import Export Carpatia",
    "wof:placetype":"venue"
},
  "geometry": {"coordinates":[-117.71036100000001,33.577401],"type":"Point"}
}