{
  "type": "Feature",
  "properties": {
    "addr:full":"931 Hartz Way Ste 130 Danville CA 94526",
    "addr:housenumber":"931",
    "addr:postcode":"94526",
    "addr:street":"Hartz Way Ste 130",
    "iso:country":"US",
    "sg:address":"931 Hartz Way Ste 130",
    "sg:city":"Danville",
    "sg:classifiers":[
        {
            "category":"Professional",
            "subcategory":"Management & Consulting",
            "type":"Services"
        },
        {
            "category":"Education",
            "subcategory":"Special Training",
            "type":"Public Place"
        },
        {
            "category":"Shopping",
            "subcategory":"Books",
            "type":"Retail Goods"
        }
    ],
    "sg:phone":"+1 925 837 5575",
    "sg:postcode":"94526",
    "sg:province":"CA",
    "sg:tags":[
        "educational",
        "material",
        "consultant",
        "instruction",
        "system",
        "improvement",
        "equipment",
        "reading",
        "tutoring"
    ],
    "wof:name":"Educational Resource Consultants Inc.",
    "wof:placetype":"venue"
},
  "geometry": {"coordinates":[-121.99401899999999,37.819328],"type":"Point"}
}