{
  "type": "Feature",
  "properties": {
    "iso:country":"US",
    "sg:address":"128 E Las Tunas Dr",
    "sg:city":"San Gabriel",
    "sg:classifiers":[
        {
            "category":"Travel",
            "subcategory":"Travel Agent",
            "type":"Entertainment"
        }
    ],
    "sg:phone":"+1 626 292 6677",
    "sg:postcode":"91776",
    "sg:province":"CA",
    "sg:tags":[
        "agency"
    ],
    "wof:name":"Overseas Travel",
    "wof:placetype":"venue"
},
  "geometry": {"coordinates":[-118.098812,34.10282],"type":"Point"}
}