{
  "type": "Feature",
  "properties": {
    "addr:full":"2335 Market St San Francisco CA 94114",
    "addr:housenumber":"2335",
    "addr:postcode":"94114",
    "addr:street":"Market St",
    "iso:country":"US",
    "sg:address":"2335 Market St",
    "sg:city":"San Francisco",
    "sg:classifiers":[
        {
            "category":"Personal",
            "subcategory":"Massage",
            "type":"Services"
        },
        {
            "category":"Shopping",
            "subcategory":"Jewelry",
            "type":"Retail Goods"
        },
        {
            "category":"Shopping",
            "subcategory":"Books",
            "type":"Retail Goods"
        },
        {
            "category":"Health Services",
            "subcategory":"Chiropractor",
            "type":"Services"
        }
    ],
    "sg:phone":"+1 415 861 6511",
    "sg:postcode":"94114",
    "sg:province":"CA",
    "sg:tags":[
        "bookstore"
    ],
    "sg:website":"www.crystalway.com",
    "wof:name":"Crystal Way",
    "wof:placetype":"venue"
},
  "geometry": {"coordinates":[-122.43369,37.763691],"type":"Point"}
}