{
  "type": "Feature",
  "properties": {
    "addr:full":"679 E Easy St Simi Valley CA 93065",
    "addr:housenumber":"679",
    "addr:postcode":"93065",
    "addr:street":"E Easy St",
    "iso:country":"US",
    "sg:address":"679 E Easy St",
    "sg:city":"Simi Valley",
    "sg:classifiers":[
        {
            "category":"Shopping",
            "subcategory":"Computers & Home Electronics",
            "type":"Retail Goods"
        }
    ],
    "sg:phone":"+1 805 306 8055",
    "sg:postcode":"93065",
    "sg:province":"CA",
    "sg:tags":[
        "high",
        "fidelity",
        "stereophonic"
    ],
    "wof:name":"Aydn",
    "wof:placetype":"venue"
},
  "geometry": {"coordinates":[-118.784025,34.273727],"type":"Point"}
}