{
  "type": "Feature",
  "properties": {
    "iso:country":"US",
    "sg:address":"1861 Whitley Ave",
    "sg:city":"Los Angeles",
    "sg:classifiers":[
        {
            "category":"Communications",
            "subcategory":"Film & Video Production",
            "type":"Services"
        }
    ],
    "sg:phone":"+1 323 467 0886",
    "sg:postcode":"90028",
    "sg:province":"CA",
    "sg:tags":[
        "motion",
        "picture",
        "studio",
        "producer"
    ],
    "wof:name":"Skyway Productions Inc",
    "wof:placetype":"venue"
},
  "geometry": {"coordinates":[-118.333417,34.104214],"type":"Point"}
}