{
  "type": "Feature",
  "properties": {
    "iso:country":"US",
    "sg:address":"8010 Brentwood Blvd",
    "sg:city":"Brentwood",
    "sg:classifiers":[
        {
            "category":"Autos & Motor Vehicles",
            "subcategory":"Automobile Sales",
            "type":"Retail Goods"
        }
    ],
    "sg:phone":"+1 925 634 3591",
    "sg:postcode":"94513",
    "sg:province":"CA",
    "sg:tags":[
        "dealers-used",
        "car",
        "used",
        "cars-wholesale"
    ],
    "wof:name":"Bill Brandt Ford Used Cars",
    "wof:placetype":"venue"
},
  "geometry": {"coordinates":[-121.696228,37.939605],"type":"Point"}
}