{
  "type": "Feature",
  "properties": {
    "addr:full":"200 W China Grade Lp Bakersfield CA 93308",
    "addr:housenumber":"200",
    "addr:postcode":"93308",
    "addr:street":"W China",
    "iso:country":"US",
    "sg:address":"200 W China Grade Lp",
    "sg:city":"Bakersfield",
    "sg:classifiers":[
        {
            "category":"Education",
            "subcategory":"Library",
            "type":"Public Place"
        }
    ],
    "sg:phone":"+1 661 393 6431",
    "sg:postcode":"93308",
    "sg:province":"CA",
    "sg:tags":[
        "executive"
    ],
    "wof:name":"Public Library",
    "wof:placetype":"venue"
},
  "geometry": {"coordinates":[-119.021818,35.426822],"type":"Point"}
}