{
  "type": "Feature",
  "properties": {
    "addr:full":"1326 Castro St San Francisco CA 94114",
    "addr:housenumber":"1326",
    "addr:postcode":"94114",
    "addr:street":"Castro St",
    "iso:country":"US",
    "sg:address":"1326 Castro St",
    "sg:city":"San Francisco",
    "sg:classifiers":[
        {
            "category":"Insurance",
            "subcategory":"Insurance Agent",
            "type":"Services"
        }
    ],
    "sg:phone":"+1 415 642 6569",
    "sg:postcode":"94114",
    "sg:province":"CA",
    "wof:name":"Allstate Insurance",
    "wof:placetype":"venue"
},
  "geometry": {"coordinates":[-122.434099,37.750704],"type":"Point"}
}