{
  "type": "Feature",
  "properties": {
    "iso:country":"US",
    "sg:address":"26773 Bouquet Canyon Rd",
    "sg:city":"Saugus",
    "sg:classifiers":[
        {
            "category":"Shopping",
            "type":"Retail Goods"
        }
    ],
    "sg:phone":"+1 661 263 9392",
    "sg:postcode":"91350",
    "sg:province":"CA",
    "sg:tags":[
        "telephone",
        "cellular"
    ],
    "wof:name":"Best Phone Man",
    "wof:placetype":"venue"
},
  "geometry": {"coordinates":[-118.531553,34.433171],"type":"Point"}
}