{
  "type": "Feature",
  "properties": {
    "iso:country":"US",
    "sg:address":"860 E Carson St",
    "sg:city":"Carson",
    "sg:classifiers":[
        {
            "category":"Health Services",
            "subcategory":"Doctor",
            "type":"Services"
        }
    ],
    "sg:phone":"+1 310 522 9769",
    "sg:postcode":"90745",
    "sg:province":"CA",
    "sg:tags":[
        "dentist"
    ],
    "wof:name":"Leticia R Tolentino Inc",
    "wof:placetype":"venue"
},
  "geometry": {"coordinates":[-118.26090000000001,33.831529],"type":"Point"}
}