{
  "type": "Feature",
  "properties": {
    "addr:full":"1079 Carmel Dr Simi Valley CA 93065",
    "addr:housenumber":"1079",
    "addr:postcode":"93065",
    "addr:street":"Carmel Dr",
    "iso:country":"US",
    "sg:address":"1079 Carmel Dr",
    "sg:city":"Simi Valley",
    "sg:classifiers":[
        {
            "category":"Building & Trades",
            "subcategory":"Construction",
            "type":"Services"
        }
    ],
    "sg:phone":"+1 805 526 8365",
    "sg:postcode":"93065",
    "sg:province":"CA",
    "sg:tags":[
        "general",
        "contractor"
    ],
    "wof:name":"Wilk Construction",
    "wof:placetype":"venue"
},
  "geometry": {"coordinates":[-118.78998199999999,34.259122],"type":"Point"}
}