{
  "type": "Feature",
  "properties": {
    "addr:full":"4500 Etiwanda Ave Mira Loma CA 91752",
    "addr:housenumber":"4500",
    "addr:postcode":"91752",
    "addr:street":"Etiwanda Ave",
    "iso:country":"US",
    "sg:address":"4500 Etiwanda Ave",
    "sg:city":"Mira Loma",
    "sg:classifiers":[
        {
            "category":"Professional",
            "subcategory":"Advertising",
            "type":"Services"
        }
    ],
    "sg:phone":"+1 951 685 2568",
    "sg:postcode":"91752",
    "sg:province":"CA",
    "sg:tags":[
        "mailing",
        "shipping"
    ],
    "wof:name":"UPS",
    "wof:placetype":"venue"
},
  "geometry": {"coordinates":[-117.524407,34.006082],"type":"Point"}
}