{
  "type": "Feature",
  "properties": {
    "addr:full":"236 S B St San Mateo CA 94401",
    "addr:housenumber":"236",
    "addr:postcode":"94401",
    "addr:street":"S B St",
    "iso:country":"US",
    "sg:address":"236 S B St",
    "sg:city":"San Mateo",
    "sg:classifiers":[
        {
            "category":"Restaurant",
            "type":"Food & Drink"
        }
    ],
    "sg:phone":"+1 650 344 4604",
    "sg:postcode":"94401",
    "sg:province":"CA",
    "wof:name":"Latin Brothers LTD",
    "wof:placetype":"venue"
},
  "geometry": {"coordinates":[-122.32274099999999,37.56574],"type":"Point"}
}