{
  "type": "Feature",
  "properties": {
    "iso:country":"US",
    "sg:address":"1540 S Harbor Blvd",
    "sg:city":"Anaheim",
    "sg:classifiers":[
        {
            "category":"Restaurant",
            "type":"Food & Drink"
        }
    ],
    "sg:phone":"+1 714 778 8992",
    "sg:postcode":"92802",
    "sg:province":"CA",
    "sg:tags":[
        "pizza"
    ],
    "wof:name":"Cafasia",
    "wof:placetype":"venue"
},
  "geometry": {"coordinates":[-117.915001,33.809299],"type":"Point"}
}