{
  "type": "Feature",
  "properties": {
    "addr:full":"541 N Twin Oaks Valley Rd San Marcos CA 92069",
    "addr:housenumber":"541",
    "addr:postcode":"92069",
    "addr:street":"N Twin Oaks Valley Rd",
    "iso:country":"US",
    "sg:address":"541 N Twin Oaks Valley Rd",
    "sg:city":"San Marcos",
    "sg:classifiers":[
        {
            "category":"Real Estate",
            "subcategory":"Real Estate Agent",
            "type":"Services"
        }
    ],
    "sg:phone":"+1 760 744 1840",
    "sg:postcode":"92069",
    "sg:province":"CA",
    "sg:tags":[
        "management"
    ],
    "wof:name":"Hoover & Taylor Ind Rentals",
    "wof:placetype":"venue"
},
  "geometry": {"coordinates":[-117.162064,33.147791],"type":"Point"}
}