{
  "type": "Feature",
  "properties": {
    "addr:full":"1240 Alameda de Las Pulgas San Mateo CA 94402",
    "addr:housenumber":"1240",
    "addr:postcode":"94402",
    "addr:street":"Alameda De Las Pulgas",
    "iso:country":"US",
    "sg:address":"1240 Alameda de Las Pulgas",
    "sg:city":"San Mateo",
    "sg:classifiers":[
        {
            "category":"Real Estate",
            "subcategory":"Real Estate Operator",
            "type":"Services"
        }
    ],
    "sg:phone":"+1 650 591 9013",
    "sg:postcode":"94402",
    "sg:province":"CA",
    "sg:tags":[
        "apartment"
    ],
    "wof:name":"Alameda Apartments",
    "wof:placetype":"venue"
},
  "geometry": {"coordinates":[-122.32569599999999,37.549565],"type":"Point"}
}