{
  "type": "Feature",
  "properties": {
    "iso:country":"US",
    "sg:address":"10550 Cam Ruiz",
    "sg:city":"San Diego",
    "sg:classifiers":[
        {
            "category":"Insurance",
            "subcategory":"Insurance Agent",
            "type":"Services"
        }
    ],
    "sg:phone":"+1 858 566 0046",
    "sg:postcode":"92126",
    "sg:province":"CA",
    "wof:name":"Farmers Insurance",
    "wof:placetype":"venue"
},
  "geometry": {"coordinates":[-117.144753,32.90932],"type":"Point"}
}