{
  "type": "Feature",
  "properties": {
    "iso:country":"US",
    "sg:address":"9349 Mission Gorge Rd",
    "sg:city":"Santee",
    "sg:classifiers":[
        {
            "category":"Food & Beverages",
            "subcategory":"Groceries & Convenience Stores",
            "type":"Retail Goods"
        }
    ],
    "sg:phone":"+1 619 562 9990",
    "sg:postcode":"92071",
    "sg:province":"CA",
    "sg:tags":[
        "grocer"
    ],
    "wof:name":"Big Buy 99 Cents Store",
    "wof:placetype":"venue"
},
  "geometry": {"coordinates":[-116.995115,32.838596],"type":"Point"}
}