{
  "type": "Feature",
  "properties": {
    "iso:country":"US",
    "sg:address":"1032 W Bonnie Brae Ct",
    "sg:city":"Ontario",
    "sg:classifiers":[
        {
            "category":"Shopping",
            "subcategory":"Computers & Home Electronics",
            "type":"Retail Goods"
        }
    ],
    "sg:phone":"+1 909 268 3069",
    "sg:postcode":"91762",
    "sg:province":"CA",
    "sg:tags":[
        "manufacture",
        "personal"
    ],
    "wof:name":"Eagle Computer Systems",
    "wof:placetype":"venue"
},
  "geometry": {"coordinates":[-117.666073,34.082394],"type":"Point"}
}