{
  "type": "Feature",
  "properties": {
    "iso:country":"US",
    "sg:address":"15017 Crenshaw Boulevard",
    "sg:city":"Gardena",
    "sg:classifiers":[
        {
            "category":"Shopping",
            "subcategory":"Department Store",
            "type":"Retail Goods"
        },
        {
            "category":"Shopping",
            "subcategory":"Discount & Variety Stores",
            "type":"Retail Goods"
        }
    ],
    "sg:phone":"+1 310 676 4428",
    "sg:postcode":"90249",
    "sg:province":"CA",
    "wof:name":"Why Pay More",
    "wof:placetype":"venue"
},
  "geometry": {"coordinates":[-118.32636100000001,33.895357],"type":"Point"}
}