{
  "type": "Feature",
  "properties": {
    "addr:full":"719 S Los Angeles St Los Angeles CA 90014",
    "addr:housenumber":"719",
    "addr:postcode":"90014",
    "addr:street":"S Los Angeles St",
    "iso:country":"US",
    "sg:address":"719 S Los Angeles St",
    "sg:city":"Los Angeles",
    "sg:classifiers":[
        {
            "category":"Manufacturing",
            "subcategory":"Tools & Machinery",
            "type":"Manufacturing & Wholesale Goods"
        }
    ],
    "sg:phone":"+1 213 688 0362",
    "sg:postcode":"90014",
    "sg:province":"CA",
    "sg:tags":[
        "pattern",
        "industrial",
        "maker",
        "mfg"
    ],
    "wof:name":"Shin's Pattern",
    "wof:placetype":"venue"
},
  "geometry": {"coordinates":[-118.25205099999999,34.042206],"type":"Point"}
}