{
  "type": "Feature",
  "properties": {
    "addr:full":"2815 Yard St Oroville CA 95966",
    "addr:housenumber":"2815",
    "addr:postcode":"95966",
    "addr:street":"Yard St",
    "iso:country":"US",
    "sg:address":"2815 Yard St",
    "sg:city":"Oroville",
    "sg:classifiers":[
        {
            "category":"Manufacturing",
            "subcategory":"Printing",
            "type":"Manufacturing & Wholesale Goods"
        }
    ],
    "sg:phone":"+1 530 532 0157",
    "sg:postcode":"95966",
    "sg:province":"CA",
    "sg:tags":[
        "newspaper"
    ],
    "wof:name":"Senior Lifestyle Magazine",
    "wof:placetype":"venue"
},
  "geometry": {"coordinates":[-121.544033,39.513629],"type":"Point"}
}