{
  "type": "Feature",
  "properties": {
    "addr:full":"1214 E Colorado Blvd Ste 201 Pasadena CA 91106",
    "addr:housenumber":"1214",
    "addr:postcode":"91106",
    "addr:street":"E Colorado Blvd Ste 201",
    "iso:country":"US",
    "sg:address":"1214 E Colorado Blvd Ste 201",
    "sg:city":"Pasadena",
    "sg:classifiers":[
        {
            "category":"Arts & Performance",
            "subcategory":"Music",
            "type":"Entertainment"
        }
    ],
    "sg:phone":"+1 818 802 3249",
    "sg:postcode":"91106",
    "sg:province":"CA",
    "sg:tags":[
        "dj"
    ],
    "sg:website":"www.HyeFX.com",
    "wof:name":"Hye FX Entertainment",
    "wof:placetype":"venue"
},
  "geometry": {"coordinates":[-118.125247,34.145923],"type":"Point"}
}