{
  "type": "Feature",
  "properties": {
    "addr:full":"339 W 5th St San Dimas CA 91773",
    "addr:housenumber":"339",
    "addr:postcode":"91773",
    "addr:street":"W 5Th St",
    "iso:country":"US",
    "sg:address":"339 W 5th St",
    "sg:city":"San Dimas",
    "sg:classifiers":[
        {
            "category":"Building & Trades",
            "subcategory":"Equipment Rental",
            "type":"Services"
        }
    ],
    "sg:phone":"+1 909 592 7658",
    "sg:postcode":"91773",
    "sg:province":"CA",
    "sg:tags":[
        "leasing"
    ],
    "wof:name":"Maxwells Backhoe Inc",
    "wof:placetype":"venue"
},
  "geometry": {"coordinates":[-117.812029,34.111743],"type":"Point"}
}