{
  "type": "Feature",
  "properties": {
    "iso:country":"US",
    "sg:address":"1601 Arden Way",
    "sg:city":"Sacramento",
    "sg:classifiers":[
        {
            "category":"Health Services",
            "subcategory":"Optometrist",
            "type":"Services"
        }
    ],
    "sg:phone":"+1 916 923 2240",
    "sg:postcode":"95815",
    "sg:province":"CA",
    "wof:name":"Kim Nguyen & Assoc",
    "wof:placetype":"venue"
},
  "geometry": {"coordinates":[-121.429582,38.601044],"type":"Point"}
}