{
  "type": "Feature",
  "properties": {
    "iso:country":"US",
    "sg:address":"332 B St",
    "sg:city":"Ramona",
    "sg:classifiers":[
        {
            "category":"Retail",
            "subcategory":"Animal Services",
            "type":"Services"
        }
    ],
    "sg:phone":"+1 760 789 7722",
    "sg:postcode":"92065",
    "sg:province":"CA",
    "wof:name":"Rainbow Grooming Plus",
    "wof:placetype":"venue"
},
  "geometry": {"coordinates":[-116.859328,33.0483],"type":"Point"}
}