{
  "type": "Feature",
  "properties": {
    "iso:country":"US",
    "sg:address":"14762 Pieri Rd",
    "sg:city":"Bakersfield",
    "sg:classifiers":[
        {
            "category":"Manufacturing",
            "subcategory":"Chemicals & Compounds",
            "type":"Manufacturing & Wholesale Goods"
        }
    ],
    "sg:phone":"+1 661 831 3416",
    "sg:postcode":"93311",
    "sg:province":"CA",
    "sg:tags":[
        "fertilizer"
    ],
    "wof:name":"Buttonwillow Warehouse Co",
    "wof:placetype":"venue"
},
  "geometry": {"coordinates":[-119.206276,35.194303],"type":"Point"}
}