{
  "type": "Feature",
  "properties": {
    "iso:country":"US",
    "sg:address":"1620 S Carlos Ave",
    "sg:city":"Ontario",
    "sg:classifiers":[
        {
            "category":"Manufacturing",
            "subcategory":"Tools & Machinery",
            "type":"Manufacturing & Wholesale Goods"
        }
    ],
    "sg:phone":"+1 909 923 2112",
    "sg:postcode":"91761",
    "sg:province":"CA",
    "sg:tags":[
        "machine",
        "shop"
    ],
    "wof:name":"Acra Machining",
    "wof:placetype":"venue"
},
  "geometry": {"coordinates":[-117.606606,34.041277],"type":"Point"}
}