{
  "type": "Feature",
  "properties": {
    "iso:country":"US",
    "sg:address":"1128 Olympic Dr",
    "sg:city":"Corona",
    "sg:classifiers":[
        {
            "category":"Arts & Performance",
            "subcategory":"Dance",
            "type":"Entertainment"
        }
    ],
    "sg:phone":"+1 951 493 6753",
    "sg:postcode":"92881",
    "sg:province":"CA",
    "sg:tags":[
        "instruction",
        "dancing"
    ],
    "wof:name":"The Young Americans",
    "wof:placetype":"venue"
},
  "geometry": {"coordinates":[-117.543031,33.859517],"type":"Point"}
}