{
  "type": "Feature",
  "properties": {
    "addr:full":"11542 Purcell St Garden Grove CA 92840",
    "addr:housenumber":"11542",
    "addr:postcode":"92840",
    "addr:street":"Purcell St",
    "iso:country":"US",
    "sg:address":"11542 Purcell St",
    "sg:city":"Garden Grove",
    "sg:classifiers":[
        {
            "category":"Banks & Credit Unions",
            "subcategory":"Investment Brokerage",
            "type":"Services"
        }
    ],
    "sg:phone":"+1 714 530 1718",
    "sg:postcode":"92840",
    "sg:province":"CA",
    "sg:tags":[
        "security"
    ],
    "wof:name":"Groupe Hill International",
    "wof:placetype":"venue"
},
  "geometry": {"coordinates":[-117.95245799999999,33.794908],"type":"Point"}
}