{
  "type": "Feature",
  "properties": {
    "iso:country":"US",
    "sg:address":"3610 Banbury Dr",
    "sg:city":"Riverside",
    "sg:classifiers":[
        {
            "category":"Professional",
            "type":"Services"
        }
    ],
    "sg:phone":"+1 951 353 8392",
    "sg:postcode":"92505",
    "sg:province":"CA",
    "wof:name":"United Nigritian Society",
    "wof:placetype":"venue"
},
  "geometry": {"coordinates":[-117.462661,33.906545],"type":"Point"}
}