{
  "type": "Feature",
  "properties": {
    "addr:full":"1703 S Bon View Ave Ontario CA 91761",
    "addr:housenumber":"1703",
    "addr:postcode":"91761",
    "addr:street":"S Bon View Ave",
    "iso:country":"US",
    "sg:address":"1703 S Bon View Ave",
    "sg:city":"Ontario",
    "sg:classifiers":[
        {
            "category":"Professional",
            "subcategory":"Computer Services",
            "type":"Services"
        }
    ],
    "sg:phone":"+1 909 923 2244",
    "sg:postcode":"91761",
    "sg:province":"CA",
    "sg:tags":[
        "consultant",
        "designer"
    ],
    "wof:name":"Accu Build",
    "wof:placetype":"venue"
},
  "geometry": {"coordinates":[-117.637383,34.048641],"type":"Point"}
}