{
  "type": "Feature",
  "properties": {
    "iso:country":"US",
    "sg:address":"1959 Republic Ave",
    "sg:city":"San Leandro",
    "sg:classifiers":[
        {
            "category":"Wholesale",
            "subcategory":"Vending Machines",
            "type":"Manufacturing & Wholesale Goods"
        }
    ],
    "sg:phone":"+1 510 483 4870",
    "sg:postcode":"94577",
    "sg:province":"CA",
    "wof:name":"Canteen Corp",
    "wof:placetype":"venue"
},
  "geometry": {"coordinates":[-122.171978,37.704532],"type":"Point"}
}