{
  "type": "Feature",
  "properties": {
    "iso:country":"US",
    "sg:address":"261 N Bonnie Brae St",
    "sg:city":"Los Angeles",
    "sg:classifiers":[
        {
            "category":"Organizations",
            "subcategory":"Religious Organization",
            "type":"Services"
        }
    ],
    "sg:phone":"+1 213 413 8990",
    "sg:postcode":"90026",
    "sg:province":"CA",
    "sg:tags":[
        "church"
    ],
    "wof:name":"Iglesia Evangelica Shalom",
    "wof:placetype":"venue"
},
  "geometry": {"coordinates":[-118.267449,34.066149],"type":"Point"}
}