{
  "type": "Feature",
  "properties": {
    "iso:country":"US",
    "sg:address":"1981 Windemere Ln",
    "sg:city":"Sacramento",
    "sg:classifiers":[
        {
            "category":"Banks & Credit Unions",
            "subcategory":"Investment Brokerage",
            "type":"Services"
        }
    ],
    "sg:phone":"+1 916 359 6910",
    "sg:postcode":"95864",
    "sg:province":"CA",
    "sg:tags":[
        "advisory",
        "financial"
    ],
    "wof:name":"First Priority Financial",
    "wof:placetype":"venue"
},
  "geometry": {"coordinates":[-121.36599200000001,38.599566],"type":"Point"}
}