{
  "type": "Feature",
  "properties": {
    "iso:country":"US",
    "sg:address":"109 W 5th Street",
    "sg:city":"Los Angeles",
    "sg:classifiers":[
        {
            "category":"Arts & Performance",
            "subcategory":"Art Gallery",
            "type":"Entertainment"
        }
    ],
    "sg:phone":"+1 213 239 0417",
    "sg:postcode":"90013",
    "sg:province":"CA",
    "wof:name":"El Nopal Press-Fine Art Publishing",
    "wof:placetype":"venue"
},
  "geometry": {"coordinates":[-118.24879,34.046729],"type":"Point"}
}