{
  "type": "Feature",
  "properties": {
    "iso:country":"US",
    "sg:address":"17731 Cowan",
    "sg:city":"Irvine",
    "sg:classifiers":[
        {
            "category":"Professional",
            "type":"Services"
        }
    ],
    "sg:phone":"+1 714 543 8020",
    "sg:postcode":"92614",
    "sg:province":"CA",
    "wof:name":"Rand McNally",
    "wof:placetype":"venue"
},
  "geometry": {"coordinates":[-117.86538299999999,33.692129],"type":"Point"}
}