{
  "type": "Feature",
  "properties": {
    "addr:full":"952 Driscoll Rd Fremont CA 94539",
    "addr:housenumber":"952",
    "addr:postcode":"94539",
    "addr:street":"Driscoll Rd",
    "iso:country":"US",
    "sg:address":"952 Driscoll Rd",
    "sg:city":"Fremont",
    "sg:classifiers":[
        {
            "category":"Professional",
            "subcategory":"Computer Services",
            "type":"Services"
        }
    ],
    "sg:phone":"+1 510 656 1631",
    "sg:postcode":"94539",
    "sg:province":"CA",
    "sg:tags":[
        "consultant",
        "designer"
    ],
    "sg:website":"www.bali-i.com",
    "wof:name":"Bali I",
    "wof:placetype":"venue"
},
  "geometry": {"coordinates":[-121.94595200000001,37.543645],"type":"Point"}
}