{
  "type": "Feature",
  "properties": {
    "addr:full":"5241 Round Meadow Rd Hidden Hills CA 91302",
    "addr:housenumber":"5241",
    "addr:postcode":"91302",
    "addr:street":"Round Meadow Rd",
    "iso:country":"US",
    "sg:address":"5241 Round Meadow Rd",
    "sg:city":"Hidden Hills",
    "sg:classifiers":[
        {
            "category":"Shopping",
            "subcategory":"Used Merchandise",
            "type":"Retail Goods"
        }
    ],
    "sg:phone":"+1 818 703 0151",
    "sg:postcode":"91302",
    "sg:province":"CA",
    "sg:tags":[
        "clothing"
    ],
    "wof:name":"Beccas Chic Boutique",
    "wof:placetype":"venue"
},
  "geometry": {"coordinates":[-118.66485900000001,34.158183],"type":"Point"}
}