{
  "type": "Feature",
  "properties": {
    "addr:full":"1520 Stockton St San Francisco CA 94133",
    "addr:housenumber":"1520",
    "addr:postcode":"94133",
    "addr:street":"Stockton St",
    "iso:country":"US",
    "sg:address":"1520 Stockton St",
    "sg:city":"San Francisco",
    "sg:classifiers":[
        {
            "category":"Health Services",
            "subcategory":"Doctor",
            "type":"Services"
        }
    ],
    "sg:phone":"+1 415 391 9686",
    "sg:postcode":"94133",
    "sg:province":"CA",
    "wof:name":"Lee Simon MD",
    "wof:placetype":"venue"
},
  "geometry": {"coordinates":[-122.40886500000001,37.799754],"type":"Point"}
}