{
  "type": "Feature",
  "properties": {
    "iso:country":"US",
    "sg:address":"18401 Burbank Blvd # 106",
    "sg:city":"Tarzana",
    "sg:classifiers":[
        {
            "category":"Wholesale",
            "subcategory":"Medical Equipment & Supplies",
            "type":"Manufacturing & Wholesale Goods"
        }
    ],
    "sg:phone":"+1 818 757 3111",
    "sg:postcode":"91356",
    "sg:province":"CA",
    "sg:tags":[
        "assistive",
        "aid",
        "device",
        "hearing"
    ],
    "wof:name":"Hearing Solutions",
    "wof:placetype":"venue"
},
  "geometry": {"coordinates":[-118.53379099999999,34.17181],"type":"Point"}
}