{
  "type": "Feature",
  "properties": {
    "addr:full":"4142 Pacific Cir Ontario CA 91750",
    "addr:housenumber":"4142",
    "addr:postcode":"91750",
    "addr:street":"Pacific Cir",
    "iso:country":"US",
    "sg:address":"4142 Pacific Cir",
    "sg:city":"Ontario",
    "sg:classifiers":[
        {
            "category":"Shopping",
            "type":"Retail Goods"
        }
    ],
    "sg:phone":"+1 909 937 0180",
    "sg:postcode":"91750",
    "sg:province":"CA",
    "sg:tags":[
        "miscellaneous",
        "store"
    ],
    "wof:name":"Oscar Aerosol Inc",
    "wof:placetype":"venue"
},
  "geometry": {"coordinates":[-117.757109,34.115176],"type":"Point"}
}