{
  "type": "Feature",
  "properties": {
    "addr:full":"6100 Mack Rd Ste 200 Sacramento CA 95823",
    "addr:housenumber":"6100",
    "addr:postcode":"95823",
    "addr:street":"Mack Rd Ste 200",
    "iso:country":"US",
    "sg:address":"6100 Mack Rd Ste 200",
    "sg:city":"Sacramento",
    "sg:classifiers":[
        {
            "category":"Shopping",
            "subcategory":"Department Store",
            "type":"Retail Goods"
        }
    ],
    "sg:phone":"+1 916 266 2101",
    "sg:postcode":"95823",
    "sg:province":"CA",
    "sg:tags":[
        "variety"
    ],
    "wof:name":"National Stores Inc",
    "wof:placetype":"venue"
},
  "geometry": {"coordinates":[-121.43099100000001,38.474183],"type":"Point"}
}