{
  "type": "Feature",
  "properties": {
    "addr:full":"10831 Olson Dr Rancho Cordova CA 95670",
    "addr:housenumber":"10831",
    "addr:postcode":"95670",
    "addr:street":"Olson Dr",
    "iso:country":"US",
    "sg:address":"10831 Olson Dr",
    "sg:city":"Rancho Cordova",
    "sg:classifiers":[
        {
            "category":"Manufacturing",
            "subcategory":"Printing",
            "type":"Manufacturing & Wholesale Goods"
        }
    ],
    "sg:phone":"+1 916 858 1800",
    "sg:postcode":"95670",
    "sg:province":"CA",
    "sg:tags":[
        "printer"
    ],
    "wof:name":"Fed Ex Kinko's Ofc & Print Ctr",
    "wof:placetype":"venue"
},
  "geometry": {"coordinates":[-121.28094900000001,38.597724],"type":"Point"}
}