{
  "type": "Feature",
  "properties": {
    "iso:country":"US",
    "sg:address":"325 25th Ave",
    "sg:city":"San Francisco",
    "sg:classifiers":[
        {
            "category":"Wholesale",
            "subcategory":"Groceries",
            "type":"Manufacturing & Wholesale Goods"
        }
    ],
    "sg:phone":"+1 415 386 5050",
    "sg:postcode":"94121",
    "sg:province":"CA",
    "sg:tags":[
        "food",
        "broker"
    ],
    "wof:name":"Food Ambassadors Inc",
    "wof:placetype":"venue"
},
  "geometry": {"coordinates":[-122.48497500000001,37.782475],"type":"Point"}
}