{
  "type": "Feature",
  "properties": {
    "addr:full":"615 Flint Ave Wilmington CA 90744",
    "addr:housenumber":"615",
    "addr:postcode":"90744",
    "addr:street":"Flint Ave",
    "iso:country":"US",
    "sg:address":"615 Flint Ave",
    "sg:city":"Wilmington",
    "sg:classifiers":[
        {
            "category":"Autos & Motor Vehicles",
            "subcategory":"Auto Supplies",
            "type":"Retail Goods"
        }
    ],
    "sg:phone":"+1 310 513 8099",
    "sg:postcode":"90744",
    "sg:province":"CA",
    "sg:tags":[
        "tire"
    ],
    "wof:name":"Jpc Tire Service",
    "wof:placetype":"venue"
},
  "geometry": {"coordinates":[-118.24900100000001,33.777699],"type":"Point"}
}