{
  "type": "Feature",
  "properties": {
    "addr:full":"3010 W Lincoln Avenue Anaheim CA 92804",
    "addr:housenumber":"3010",
    "addr:postcode":"92804",
    "addr:street":"W Lincoln Avenue",
    "iso:country":"US",
    "sg:address":"3010 W Lincoln Avenue",
    "sg:city":"Anaheim",
    "sg:classifiers":[
        {
            "category":"Bars & Pubs",
            "type":"Food & Drink"
        },
        {
            "category":"Restaurant",
            "type":"Food & Drink"
        },
        {
            "category":"Bars & Pubs",
            "subcategory":"Lounge",
            "type":"Food & Drink"
        }
    ],
    "sg:postcode":"92804",
    "sg:province":"CA",
    "sg:tags":[
        "korean",
        "karaoke"
    ],
    "wof:name":"2NE1",
    "wof:placetype":"venue"
},
  "geometry": {"coordinates":[-117.994157,33.831964],"type":"Point"}
}