{
  "type": "Feature",
  "properties": {
    "addr:full":"10265 Folsom Blvd Rancho Cordova CA 95670",
    "addr:housenumber":"10265",
    "addr:postcode":"95670",
    "addr:street":"Folsom Blvd",
    "iso:country":"US",
    "sg:address":"10265 Folsom Blvd",
    "sg:city":"Rancho Cordova",
    "sg:classifiers":[
        {
            "category":"Retail",
            "subcategory":"Auto Repair",
            "type":"Services"
        }
    ],
    "sg:phone":"+1 916 361 8873",
    "sg:postcode":"95670",
    "sg:province":"CA",
    "sg:website":"www.jiffylubeca.com",
    "wof:name":"Jiffy Lube",
    "wof:placetype":"venue"
},
  "geometry": {"coordinates":[-121.309749,38.586052],"type":"Point"}
}