{
  "type": "Feature",
  "properties": {
    "addr:full":"8110 Westwood Dr Gilroy CA 95020",
    "addr:housenumber":"8110",
    "addr:postcode":"95020",
    "addr:street":"Westwood Dr",
    "iso:country":"US",
    "sg:address":"8110 Westwood Dr",
    "sg:city":"Gilroy",
    "sg:classifiers":[
        {
            "category":"Food & Beverages",
            "subcategory":"Groceries & Convenience Stores",
            "type":"Retail Goods"
        }
    ],
    "sg:phone":"+1 408 847 4696",
    "sg:postcode":"95020",
    "sg:province":"CA",
    "wof:name":"Qwik Mart",
    "wof:placetype":"venue"
},
  "geometry": {"coordinates":[-121.59375300000001,37.014515],"type":"Point"}
}