{
  "type": "Feature",
  "properties": {
    "addr:full":"31375 San Miguelito Dr Thousand Palms CA 92276",
    "addr:housenumber":"31375",
    "addr:postcode":"92276",
    "addr:street":"San Miguelito Dr",
    "iso:country":"US",
    "sg:address":"31375 San Miguelito Dr",
    "sg:city":"Thousand Palms",
    "sg:classifiers":[
        {
            "category":"Building & Trades",
            "subcategory":"Landscaping Services",
            "type":"Services"
        }
    ],
    "sg:phone":"+1 760 343 1884",
    "sg:postcode":"92276",
    "sg:province":"CA",
    "wof:name":"Leon Landscaping Inc",
    "wof:placetype":"venue"
},
  "geometry": {"coordinates":[-116.38639499999999,33.820907],"type":"Point"}
}