{
  "type": "Feature",
  "properties": {
    "iso:country":"US",
    "sg:address":"275 Sawyer St",
    "sg:city":"Auburn",
    "sg:classifiers":[
        {
            "category":"Wholesale",
            "subcategory":"Vending Machines",
            "type":"Manufacturing & Wholesale Goods"
        }
    ],
    "sg:phone":"+1 530 889 2668",
    "sg:postcode":"95603",
    "sg:province":"CA",
    "sg:tags":[
        "operator"
    ],
    "wof:name":"Charlie Beans Vending",
    "wof:placetype":"venue"
},
  "geometry": {"coordinates":[-121.07636599999999,38.901109],"type":"Point"}
}