{
  "type": "Feature",
  "properties": {
    "addr:full":"1309 W Glenoaks Blvd Glendale CA 91201",
    "addr:housenumber":"1309",
    "addr:postcode":"91201",
    "addr:street":"W Glenoaks Blvd",
    "iso:country":"US",
    "sg:address":"1309 W Glenoaks Blvd",
    "sg:city":"Glendale",
    "sg:classifiers":[
        {
            "category":"Restaurant",
            "type":"Food & Drink"
        }
    ],
    "sg:phone":"+1 818 240 3663",
    "sg:postcode":"91201",
    "sg:province":"CA",
    "sg:tags":[
        "pizza"
    ],
    "wof:name":"Nino's Pizza Italian Restaurant",
    "wof:placetype":"venue"
},
  "geometry": {"coordinates":[-118.283997,34.166599],"type":"Point"}
}