{
  "type": "Feature",
  "properties": {
    "iso:country":"US",
    "sg:address":"1515 E Pacific Coast Hwy",
    "sg:city":"Wilmington",
    "sg:classifiers":[
        {
            "category":"Shopping",
            "subcategory":"Computers & Home Electronics",
            "type":"Retail Goods"
        }
    ],
    "sg:phone":"+1 310 830 1536",
    "sg:postcode":"90744",
    "sg:province":"CA",
    "wof:name":"Estereos Vasquez",
    "wof:placetype":"venue"
},
  "geometry": {"coordinates":[-118.244929,33.791223],"type":"Point"}
}