{
  "type": "Feature",
  "properties": {
    "iso:country":"US",
    "sg:address":"40711 Murrieta Hot Springs Rd",
    "sg:city":"Murrieta",
    "sg:classifiers":[
        {
            "category":"Personal",
            "subcategory":"Beauty Salon",
            "type":"Services"
        }
    ],
    "sg:phone":"+1 951 698 8100",
    "sg:postcode":"92562",
    "sg:province":"CA",
    "wof:name":"Salon O",
    "wof:placetype":"venue"
},
  "geometry": {"coordinates":[-117.188114,33.555036],"type":"Point"}
}