{
  "type": "Feature",
  "properties": {
    "iso:country":"US",
    "sg:address":"516 Ballard St",
    "sg:city":"El Cajon",
    "sg:classifiers":[
        {
            "category":"Retail",
            "subcategory":"Auto Repair",
            "type":"Services"
        }
    ],
    "sg:phone":"+1 619 660 0886",
    "sg:postcode":"92019",
    "sg:province":"CA",
    "sg:tags":[
        "road"
    ],
    "wof:name":"Going Towing",
    "wof:placetype":"venue"
},
  "geometry": {"coordinates":[-116.941425,32.790332],"type":"Point"}
}