{
  "type": "Feature",
  "properties": {
    "iso:country":"US",
    "sg:address":"1360 The Alameda",
    "sg:city":"San Jose",
    "sg:classifiers":[
        {
            "category":"Cinema",
            "subcategory":"Movie Rental",
            "type":"Entertainment"
        }
    ],
    "sg:phone":"+1 408 292 6239",
    "sg:postcode":"95126",
    "sg:province":"CA",
    "sg:tags":[
        "leasing",
        "video",
        "disc",
        "tape"
    ],
    "wof:name":"Blockbuster Video",
    "wof:placetype":"venue"
},
  "geometry": {"coordinates":[-121.912924,37.332325],"type":"Point"}
}