{
  "type": "Feature",
  "properties": {
    "addr:full":"210 W 4th St Santa Ana CA 92701",
    "addr:housenumber":"210",
    "addr:postcode":"92701",
    "addr:street":"W 4Th St",
    "iso:country":"US",
    "sg:address":"210 W 4th St",
    "sg:city":"Santa Ana",
    "sg:classifiers":[
        {
            "category":"Utilities",
            "subcategory":"Mobile Phone",
            "type":"Services"
        }
    ],
    "sg:phone":"+1 714 834 1009",
    "sg:postcode":"92701",
    "sg:province":"CA",
    "sg:tags":[
        "telephone",
        "cellular"
    ],
    "wof:name":"Fast Wireless",
    "wof:placetype":"venue"
},
  "geometry": {"coordinates":[-117.869649,33.747926],"type":"Point"}
}