{
  "type": "Feature",
  "properties": {
    "iso:country":"US",
    "sg:address":"19420 Bus Center Dr",
    "sg:city":"Chatsworth",
    "sg:classifiers":[
        {
            "category":"Insurance",
            "subcategory":"Insurance Agent",
            "type":"Services"
        }
    ],
    "sg:phone":"+1 818 773 7411",
    "sg:postcode":"91324",
    "sg:province":"CA",
    "wof:name":"Frontier Valley Insurance Svcs",
    "wof:placetype":"venue"
},
  "geometry": {"coordinates":[-118.556367,34.231337],"type":"Point"}
}