{
  "type": "Feature",
  "properties": {
    "iso:country":"US",
    "sg:address":"20026 Austin Ln",
    "sg:city":"Castro Valley",
    "sg:classifiers":[
        {
            "category":"Building & Trades",
            "subcategory":"Construction",
            "type":"Services"
        }
    ],
    "sg:phone":"+1 510 886 3572",
    "sg:postcode":"94546",
    "sg:province":"CA",
    "sg:tags":[
        "dry wall",
        "contractor"
    ],
    "wof:name":"Hector's Drywall",
    "wof:placetype":"venue"
},
  "geometry": {"coordinates":[-122.09464199999999,37.697581],"type":"Point"}
}