{
  "type": "Feature",
  "properties": {
    "addr:full":"2421 Kingsland Ave Oakland CA 94601",
    "addr:housenumber":"2421",
    "addr:postcode":"94601",
    "addr:street":"Kingsland Ave",
    "iso:country":"US",
    "sg:address":"2421 Kingsland Ave",
    "sg:city":"Oakland",
    "sg:classifiers":[
        {
            "category":"Social Services",
            "subcategory":"Child Care",
            "type":"Services"
        }
    ],
    "sg:phone":"+1 510 534 4545",
    "sg:postcode":"94601",
    "sg:province":"CA",
    "sg:tags":[
        "day"
    ],
    "wof:name":"Auntie Carla's Child Care",
    "wof:placetype":"venue"
},
  "geometry": {"coordinates":[-122.197003,37.773856],"type":"Point"}
}