{
  "type": "Feature",
  "properties": {
    "addr:full":"650 Manchester Ave Burbank CA 91501",
    "addr:housenumber":"650",
    "addr:postcode":"91501",
    "addr:street":"Manchester Ave",
    "iso:country":"US",
    "sg:address":"650 Manchester Ave",
    "sg:city":"Burbank",
    "sg:classifiers":[
        {
            "category":"Education",
            "subcategory":"Kindergarten",
            "type":"Public Place"
        }
    ],
    "sg:phone":"+1 818 415 3416",
    "sg:postcode":"91501",
    "sg:province":"CA",
    "sg:tags":[
        "school",
        "driving"
    ],
    "wof:name":"COMMUNITIES IN SCHOOLS",
    "wof:placetype":"venue"
},
  "geometry": {"coordinates":[-121.925353,37.294197],"type":"Point"}
}