{
  "type": "Feature",
  "properties": {
    "iso:country":"US",
    "sg:address":"538 12th St",
    "sg:city":"Imperial Beach",
    "sg:classifiers":[
        {
            "category":"Retail",
            "subcategory":"Veterinary Services",
            "type":"Services"
        }
    ],
    "sg:phone":"+1 619 424 3961",
    "sg:postcode":"91932",
    "sg:province":"CA",
    "sg:tags":[
        "veterinarian"
    ],
    "wof:name":"Imperial Beach Pet Hospital",
    "wof:placetype":"venue"
},
  "geometry": {"coordinates":[-117.10847200000001,32.587299],"type":"Point"}
}