{
  "type": "Feature",
  "properties": {
    "addr:full":"11936 Ratner St North Hollywood CA 91605",
    "addr:housenumber":"11936",
    "addr:postcode":"91605",
    "addr:street":"Ratner St",
    "iso:country":"US",
    "sg:address":"11936 Ratner St",
    "sg:city":"North Hollywood",
    "sg:classifiers":[
        {
            "category":"Real Estate",
            "subcategory":"Architect",
            "type":"Services"
        }
    ],
    "sg:phone":"+1 818 768 0788",
    "sg:postcode":"91605",
    "sg:province":"CA",
    "sg:website":"www.sarahweardesign.com",
    "wof:name":"Wear House Design",
    "wof:placetype":"venue"
},
  "geometry": {"coordinates":[-118.39349199999999,34.216514],"type":"Point"}
}