{
  "type": "Feature",
  "properties": {
    "iso:country":"US",
    "sg:address":"4538 Cass St",
    "sg:city":"San Diego",
    "sg:classifiers":[
        {
            "category":"Real Estate",
            "subcategory":"Real Estate Agent",
            "type":"Services"
        }
    ],
    "sg:phone":"+1 619 224 3466",
    "sg:postcode":"92109",
    "sg:province":"CA",
    "sg:tags":[
        "appraiser"
    ],
    "wof:name":"Osborne Appraisal Svc",
    "wof:placetype":"venue"
},
  "geometry": {"coordinates":[-117.251942,32.797451],"type":"Point"}
}