{
  "type": "Feature",
  "properties": {
    "addr:full":"2661 Oswell St Bakersfield CA 93306",
    "addr:housenumber":"2661",
    "addr:postcode":"93306",
    "addr:street":"Oswell St",
    "iso:country":"US",
    "sg:address":"2661 Oswell St",
    "sg:city":"Bakersfield",
    "sg:classifiers":[
        {
            "category":"Shopping",
            "type":"Retail Goods"
        }
    ],
    "sg:phone":"+1 661 873 1092",
    "sg:postcode":"93306",
    "sg:province":"CA",
    "sg:tags":[
        "merchandise",
        "animal"
    ],
    "sg:website":"www.petsmart.com",
    "wof:name":"Petsmart",
    "wof:placetype":"venue"
},
  "geometry": {"coordinates":[-118.94970000000001,35.39406],"type":"Point"}
}