{
  "type": "Feature",
  "properties": {
    "addr:full":"1709 S California Ave Monrovia CA 91016",
    "addr:housenumber":"1709",
    "addr:postcode":"91016",
    "addr:street":"S California Ave",
    "iso:country":"US",
    "sg:address":"1709 S California Ave",
    "sg:city":"Monrovia",
    "sg:classifiers":[
        {
            "category":"Manufacturing",
            "subcategory":"Toys & Sporting Goods",
            "type":"Manufacturing & Wholesale Goods"
        }
    ],
    "sg:phone":"+1 909 223 6860",
    "sg:postcode":"91016",
    "sg:province":"CA",
    "sg:tags":[
        "mfg"
    ],
    "wof:name":"Gen X Global Inc",
    "wof:placetype":"venue"
},
  "geometry": {"coordinates":[-117.995103,34.132564],"type":"Point"}
}