{
  "type": "Feature",
  "properties": {
    "iso:country":"US",
    "sg:address":"1229 Vine St",
    "sg:city":"Paso Robles",
    "sg:classifiers":[
        {
            "category":"Professional",
            "type":"Services"
        }
    ],
    "sg:phone":"+1 805 227 1212",
    "sg:postcode":"93446",
    "sg:province":"CA",
    "sg:tags":[
        "establishment"
    ],
    "wof:name":"Cassabon Mc Ilhatton Assoc LLP",
    "wof:placetype":"venue"
},
  "geometry": {"coordinates":[-120.694034,35.626771],"type":"Point"}
}