{
  "type": "Feature",
  "properties": {
    "iso:country":"US",
    "sg:address":"2760 Hidden Hills Way",
    "sg:city":"Corona",
    "sg:classifiers":[
        {
            "category":"Professional",
            "type":"Services"
        }
    ],
    "sg:phone":"+1 951 738 8403",
    "sg:postcode":"92882",
    "sg:province":"CA",
    "wof:name":"Ahlclips Inc",
    "wof:placetype":"venue"
},
  "geometry": {"coordinates":[-117.62658500000001,33.865427],"type":"Point"}
}