{
  "type": "Feature",
  "properties": {
    "addr:full":"1557 Pacific Ave Suite-A Alameda CA 94501",
    "addr:housenumber":"1557",
    "addr:postcode":"94501",
    "addr:street":"Pacific Ave",
    "iso:country":"US",
    "sg:address":"1557 Pacific Ave Suite-A",
    "sg:city":"Alameda",
    "sg:classifiers":[
        {
            "category":"Food & Beverages",
            "subcategory":"Liquor & Beverages",
            "type":"Retail Goods"
        },
        {
            "category":"Food & Beverages",
            "subcategory":"Groceries & Convenience Stores",
            "type":"Retail Goods"
        }
    ],
    "sg:phone":"+1 510 227 5722",
    "sg:postcode":"94501",
    "sg:province":"CA",
    "sg:tags":[
        "latin",
        "natural",
        "bottler",
        "beverages-distributors",
        "juice",
        "american",
        "mexican"
    ],
    "sg:website":"http://www.squidoo.com/delprado",
    "wof:name":"Mapa Imports, LLC",
    "wof:placetype":"venue"
},
  "geometry": {"coordinates":[-122.258392,37.775188],"type":"Point"}
}