{
  "type": "Feature",
  "properties": {
    "addr:full":"404 State Rte 3 Etna CA 96027",
    "addr:housenumber":"404",
    "addr:postcode":"96027",
    "addr:street":"State Rte 3",
    "iso:country":"US",
    "sg:address":"404 State Rte 3",
    "sg:city":"Etna",
    "sg:classifiers":[
        {
            "category":"Restaurant",
            "type":"Food & Drink"
        }
    ],
    "sg:phone":"+1 530 467 3303",
    "sg:postcode":"96027",
    "sg:province":"CA",
    "sg:tags":[
        "out"
    ],
    "wof:name":"Dotty's Korner Kitchen",
    "wof:placetype":"venue"
},
  "geometry": {"coordinates":[-122.881754,41.458139],"type":"Point"}
}