{
  "type": "Feature",
  "properties": {
    "iso:country":"US",
    "sg:address":"5735 el Camino Real",
    "sg:city":"Atascadero",
    "sg:classifiers":[
        {
            "category":"Utilities",
            "subcategory":"Mobile Phone",
            "type":"Services"
        }
    ],
    "sg:phone":"+1 805 461 0529",
    "sg:postcode":"93422",
    "sg:province":"CA",
    "sg:tags":[
        "communication",
        "telephone",
        "cellular",
        "radiotelephone"
    ],
    "wof:name":"Hot Wireless",
    "wof:placetype":"venue"
},
  "geometry": {"coordinates":[-120.674021,35.491213],"type":"Point"}
}