{
  "type": "Feature",
  "properties": {
    "iso:country":"US",
    "sg:address":"7046 Homewood Dr",
    "sg:city":"Oakland",
    "sg:classifiers":[
        {
            "category":"Professional",
            "subcategory":"Computer Services",
            "type":"Services"
        }
    ],
    "sg:phone":"+1 510 338 1222",
    "sg:postcode":"94611",
    "sg:province":"CA",
    "sg:tags":[
        "graphics"
    ],
    "wof:name":"Bluelight Animations",
    "wof:placetype":"venue"
},
  "geometry": {"coordinates":[-122.195707,37.835466],"type":"Point"}
}