{
  "type": "Feature",
  "properties": {
    "iso:country":"US",
    "sg:address":"3992 Horner St",
    "sg:city":"Union City",
    "sg:classifiers":[
        {
            "category":"Home & Garden",
            "subcategory":"Building Materials",
            "type":"Retail Goods"
        }
    ],
    "sg:phone":"+1 510 487 6557",
    "sg:postcode":"94587",
    "sg:province":"CA",
    "sg:tags":[
        "glass",
        "window",
        "plate"
    ],
    "wof:name":"J & G Union City Glass",
    "wof:placetype":"venue"
},
  "geometry": {"coordinates":[-122.07999,37.59535],"type":"Point"}
}