{
  "type": "Feature",
  "properties": {
    "addr:full":"9317 Firestone Blvd Downey CA 90241",
    "addr:housenumber":"9317",
    "addr:postcode":"90241",
    "addr:street":"Firestone Blvd",
    "iso:country":"US",
    "sg:address":"9317 Firestone Blvd",
    "sg:city":"Downey",
    "sg:classifiers":[
        {
            "category":"Banks & Credit Unions",
            "subcategory":"Bank",
            "type":"Services"
        }
    ],
    "sg:phone":"+1 562 862 8600",
    "sg:postcode":"90241",
    "sg:province":"CA",
    "sg:tags":[
        "mortgage",
        "loan",
        "broker",
        "real estate"
    ],
    "sg:website":"www.powerhousemortgage.com",
    "wof:name":"Powerhouse Mortgage Inc",
    "wof:placetype":"venue"
},
  "geometry": {"coordinates":[-118.117132,33.93239],"type":"Point"}
}