{
  "type": "Feature",
  "properties": {
    "addr:full":"4618 Blue Gum Ave Modesto CA 95358",
    "addr:housenumber":"4618",
    "addr:postcode":"ca 95358",
    "addr:street":"Blue Gum Ave",
    "iso:country":"US",
    "sg:address":"4618 Blue Gum Ave",
    "sg:city":"Modesto",
    "sg:classifiers":[
        {
            "category":"Farming",
            "subcategory":"Crops",
            "type":"Manufacturing & Wholesale Goods"
        }
    ],
    "sg:phone":"+1 209 524 7580",
    "sg:postcode":"95358",
    "sg:province":"CA",
    "sg:tags":[
        "grove",
        "nut",
        "tree"
    ],
    "wof:name":"Beverley Bettencourt",
    "wof:placetype":"venue"
},
  "geometry": {"coordinates":[-121.076936,37.659912],"type":"Point"}
}