{
  "type": "Feature",
  "properties": {
    "iso:country":"US",
    "sg:address":"6167 Bristol Pkwy",
    "sg:city":"Culver City",
    "sg:classifiers":[
        {
            "category":"Professional",
            "subcategory":"Employment Agencies",
            "type":"Services"
        }
    ],
    "sg:phone":"+1 310 570 0092",
    "sg:postcode":"90230",
    "sg:province":"CA",
    "sg:tags":[
        "help",
        "supply"
    ],
    "wof:name":"Surgical Staff South",
    "wof:placetype":"venue"
},
  "geometry": {"coordinates":[-118.389813,33.984567],"type":"Point"}
}