{
  "type": "Feature",
  "properties": {
    "addr:full":"820 Yorkshire Way Corona CA 92879",
    "addr:housenumber":"820",
    "addr:postcode":"92879",
    "addr:street":"Yorkshire Way",
    "iso:country":"US",
    "sg:address":"820 Yorkshire Way",
    "sg:city":"Corona",
    "sg:classifiers":[
        {
            "category":"Manufacturing",
            "subcategory":"Tools & Machinery",
            "type":"Manufacturing & Wholesale Goods"
        }
    ],
    "sg:phone":"+1 951 272 1147",
    "sg:postcode":"92879",
    "sg:province":"CA",
    "sg:tags":[
        "construction",
        "mfg"
    ],
    "wof:name":"Shamalta Construction",
    "wof:placetype":"venue"
},
  "geometry": {"coordinates":[-117.552438,33.852642],"type":"Point"}
}