{
  "type": "Feature",
  "properties": {
    "addr:full":"525 Doyle Park Dr Santa Rosa CA 95405",
    "addr:housenumber":"525",
    "addr:postcode":"95405",
    "addr:street":"Doyle Park Dr",
    "iso:country":"US",
    "sg:address":"525 Doyle Park Dr",
    "sg:city":"Santa Rosa",
    "sg:classifiers":[
        {
            "category":"Health Services",
            "subcategory":"Doctor",
            "type":"Services"
        }
    ],
    "sg:phone":"+1 707 523 1873",
    "sg:postcode":"95405",
    "sg:province":"CA",
    "sg:tags":[
        "physician",
        "surgeon"
    ],
    "wof:name":"North Bay Neurosurgical Assoc",
    "wof:placetype":"venue"
},
  "geometry": {"coordinates":[-122.698623,38.442466],"type":"Point"}
}