{
  "type": "Feature",
  "properties": {
    "iso:country":"US",
    "sg:address":"373 E Foothill Blvd",
    "sg:city":"Upland",
    "sg:classifiers":[
        {
            "category":"Coffee & Tea",
            "type":"Food & Drink"
        },
        {
            "category":"Restaurant",
            "type":"Food & Drink"
        }
    ],
    "sg:phone":"+1 909 946 0898",
    "sg:postcode":"91786",
    "sg:province":"CA",
    "sg:tags":[
        "espresso"
    ],
    "wof:name":"Cococup Cafe",
    "wof:placetype":"venue"
},
  "geometry": {"coordinates":[-117.64592,34.107192],"type":"Point"}
}