{
  "type": "Feature",
  "properties": {
    "addr:full":"3817 184th St Torrance CA 90504",
    "addr:housenumber":"3817",
    "addr:postcode":"90504",
    "addr:street":"184Th St",
    "iso:country":"US",
    "sg:address":"3817 184th St",
    "sg:city":"Torrance",
    "sg:classifiers":[
        {
            "category":"Freight",
            "type":"Transportation"
        }
    ],
    "sg:phone":"+1 310 329 4600",
    "sg:postcode":"90504",
    "sg:province":"CA",
    "wof:name":"Yamatrans Logistics Co",
    "wof:placetype":"venue"
},
  "geometry": {"coordinates":[-118.343586,33.864026],"type":"Point"}
}