{
  "type": "Feature",
  "properties": {
    "addr:full":"311 Broadway Oakland CA 94607",
    "addr:housenumber":"311",
    "addr:postcode":"94607",
    "addr:street":"Broadway",
    "iso:country":"US",
    "sg:address":"311 Broadway",
    "sg:city":"Oakland",
    "sg:classifiers":[
        {
            "category":"Recreation",
            "type":"Entertainment"
        }
    ],
    "sg:phone":"+1 510 836 2334",
    "sg:postcode":"94607",
    "sg:province":"CA",
    "sg:tags":[
        "psychic",
        "medium"
    ],
    "wof:name":"Jackie-Fortune Teller",
    "wof:placetype":"venue"
},
  "geometry": {"coordinates":[-122.276073,37.796811],"type":"Point"}
}