{
  "type": "Feature",
  "properties": {
    "iso:country":"US",
    "sg:address":"9437 E 14th St",
    "sg:city":"Oakland",
    "sg:classifiers":[
        {
            "category":"Organizations",
            "subcategory":"Non-profit Organization",
            "type":"Services"
        }
    ],
    "sg:phone":"+1 510 632 4357",
    "sg:postcode":"94603",
    "sg:province":"CA",
    "wof:name":"Elmhurst Food Pantry",
    "wof:placetype":"venue"
},
  "geometry": {"coordinates":[-122.17223199999999,37.746731],"type":"Point"}
}