{
  "type": "Feature",
  "properties": {
    "addr:full":"12390 el Camino Real San Diego CA 92130",
    "addr:housenumber":"12390",
    "addr:postcode":"92130",
    "addr:street":"El Camino Real",
    "iso:country":"US",
    "sg:address":"12390 el Camino Real",
    "sg:city":"San Diego",
    "sg:classifiers":[
        {
            "category":"Professional",
            "subcategory":"Lawyer & Legal Services",
            "type":"Services"
        }
    ],
    "sg:phone":"+1 858 678 5070",
    "sg:postcode":"92130",
    "sg:province":"CA",
    "sg:tags":[
        "attorney"
    ],
    "sg:website":"www.fr.com",
    "wof:name":"Fish & Richardson",
    "wof:placetype":"venue"
},
  "geometry": {"coordinates":[-117.236679,32.9339],"type":"Point"}
}