{
  "type": "Feature",
  "properties": {
    "iso:country":"US",
    "sg:address":"40439 Oakhurst View Ct",
    "sg:city":"Oakhurst",
    "sg:classifiers":[
        {
            "category":"Professional",
            "subcategory":"Business Services",
            "type":"Services"
        }
    ],
    "sg:phone":"+1 559 641 7594",
    "sg:postcode":"93644",
    "sg:province":"CA",
    "sg:tags":[
        "information",
        "referral"
    ],
    "wof:name":"Showbiz Kidz",
    "wof:placetype":"venue"
},
  "geometry": {"coordinates":[-119.62322899999999,37.334874],"type":"Point"}
}