{
  "type": "Feature",
  "properties": {
    "addr:full":"4561 Park Blvd San Diego CA 92116",
    "addr:housenumber":"4561",
    "addr:postcode":"92116",
    "addr:street":"Park Blvd",
    "iso:country":"US",
    "sg:address":"4561 Park Blvd",
    "sg:city":"San Diego",
    "sg:classifiers":[
        {
            "category":"Personal",
            "subcategory":"Beauty Salon",
            "type":"Services"
        }
    ],
    "sg:phone":"+1 619 299 2953",
    "sg:postcode":"92116",
    "sg:province":"CA",
    "sg:tags":[
        "hair"
    ],
    "sg:website":"www.axlehairlabor.com",
    "wof:name":"Axle Hair Labor",
    "wof:placetype":"venue"
},
  "geometry": {"coordinates":[-117.146123,32.760289],"type":"Point"}
}