{
  "type": "Feature",
  "properties": {
    "iso:country":"US",
    "sg:address":"23172 Alcalde Dr",
    "sg:city":"Laguna Hills",
    "sg:classifiers":[
        {
            "category":"Wholesale",
            "subcategory":"Toys & Hobbies",
            "type":"Manufacturing & Wholesale Goods"
        }
    ],
    "sg:phone":"+1 949 583 7371",
    "sg:postcode":"92653",
    "sg:province":"CA",
    "sg:tags":[
        "balloon"
    ],
    "wof:name":"Suzuki Latex USA",
    "wof:placetype":"venue"
},
  "geometry": {"coordinates":[-117.72514200000001,33.62309],"type":"Point"}
}