{
  "type": "Feature",
  "properties": {
    "iso:country":"US",
    "sg:address":"461 N Grand Ave",
    "sg:city":"Covina",
    "sg:classifiers":[
        {
            "category":"Utilities",
            "subcategory":"Refuse",
            "type":"Services"
        }
    ],
    "sg:phone":"+1 626 732 9899",
    "sg:postcode":"91724",
    "sg:province":"CA",
    "sg:tags":[
        "system"
    ],
    "wof:name":"Sp Recycling Corporation",
    "wof:placetype":"venue"
},
  "geometry": {"coordinates":[-117.872458,34.091329],"type":"Point"}
}