{
  "type": "Feature",
  "properties": {
    "addr:full":"1749 W 13th St Upland CA 91786",
    "addr:housenumber":"1749",
    "addr:postcode":"91786",
    "addr:street":"W 13Th St",
    "iso:country":"US",
    "sg:address":"1749 W 13th St",
    "sg:city":"Upland",
    "sg:classifiers":[
        {
            "category":"Professional",
            "type":"Services"
        }
    ],
    "sg:phone":"+1 909 985 3379",
    "sg:postcode":"91786",
    "sg:province":"CA",
    "sg:tags":[
        "establishment"
    ],
    "wof:name":"Pre-Flite Inc",
    "wof:placetype":"venue"
},
  "geometry": {"coordinates":[-117.682317,34.110596],"type":"Point"}
}