{
  "type": "Feature",
  "properties": {
    "iso:country":"US",
    "sg:address":"6259 W 87th St",
    "sg:city":"Los Angeles",
    "sg:classifiers":[
        {
            "category":"Wholesale",
            "subcategory":"Electrical",
            "type":"Manufacturing & Wholesale Goods"
        }
    ],
    "sg:phone":"+1 310 568 0518",
    "sg:postcode":"90045",
    "sg:province":"CA",
    "sg:tags":[
        "equipment",
        "electronic",
        "supply"
    ],
    "sg:website":"www.comptronics.net",
    "wof:name":"Ic Quest",
    "wof:placetype":"venue"
},
  "geometry": {"coordinates":[-118.394138,33.958635],"type":"Point"}
}