{
  "type": "Feature",
  "properties": {
    "iso:country":"US",
    "sg:address":"998 Valencia St",
    "sg:city":"San Francisco",
    "sg:classifiers":[
        {
            "category":"Arts & Performance",
            "subcategory":"Music",
            "type":"Entertainment"
        },
        {
            "category":"Shopping",
            "subcategory":"Antiques",
            "type":"Retail Goods"
        }
    ],
    "sg:phone":"+1 415 374 7048",
    "sg:postcode":"94110",
    "sg:province":"CA",
    "sg:tags":[
        "venue"
    ],
    "sg:website":"www.viracochasf.com/",
    "wof:name":"Viracocha",
    "wof:placetype":"venue"
},
  "geometry": {"coordinates":[-122.421431,37.75704],"type":"Point"}
}