{
  "type": "Feature",
  "properties": {
    "addr:full":"20211 Rockville Ct Yorba Linda CA 92886",
    "addr:housenumber":"20211",
    "addr:postcode":"92886",
    "addr:street":"Rockville Ct",
    "iso:country":"US",
    "sg:address":"20211 Rockville Ct",
    "sg:city":"Yorba Linda",
    "sg:classifiers":[
        {
            "category":"Manufacturing",
            "subcategory":"Chemicals & Compounds",
            "type":"Manufacturing & Wholesale Goods"
        }
    ],
    "sg:phone":"+1 949 608 3878",
    "sg:postcode":"92886",
    "sg:province":"CA",
    "sg:tags":[
        "mfg"
    ],
    "wof:name":"G&L Enterprise",
    "wof:placetype":"venue"
},
  "geometry": {"coordinates":[-117.781666,33.865851],"type":"Point"}
}