{
  "type": "Feature",
  "properties": {
    "addr:full":"2072 Lucretia Ave San Jose CA 95122",
    "addr:postcode":"2072;95122",
    "addr:street":"Lucretia Ave",
    "iso:country":"US",
    "sg:address":"2072 Lucretia Ave",
    "sg:city":"San Jose",
    "sg:classifiers":[
        {
            "category":"Recreation",
            "type":"Entertainment"
        }
    ],
    "sg:phone":"+1 408 277 3317",
    "sg:postcode":"95122",
    "sg:province":"CA",
    "sg:tags":[
        "club",
        "membership"
    ],
    "wof:name":"Recreation & Community Svcs",
    "wof:placetype":"venue"
},
  "geometry": {"coordinates":[-121.84686499999999,37.31958],"type":"Point"}
}