{
  "type": "Feature",
  "properties": {
    "addr:full":"17300 E 17th Street Tustin CA 92780",
    "addr:housenumber":"17300",
    "addr:postcode":"92780",
    "addr:street":"E 17Th Street",
    "iso:country":"US",
    "sg:address":"17300 E 17th Street",
    "sg:city":"Tustin",
    "sg:classifiers":[
        {
            "category":"Home & Garden",
            "subcategory":"Home Furnishings",
            "type":"Retail Goods"
        }
    ],
    "sg:phone":"+1 714 731 5959",
    "sg:postcode":"92780",
    "sg:province":"CA",
    "sg:tags":[
        "decor",
        "bath",
        "kitchen"
    ],
    "sg:website":"www.myutot.com",
    "wof:name":"Under the Olive Tree",
    "wof:placetype":"venue"
},
  "geometry": {"coordinates":[-117.828684,33.759716],"type":"Point"}
}