{
  "type": "Feature",
  "properties": {
    "addr:full":"1882 E el Norte Pkwy Escondido CA 92027",
    "addr:housenumber":"1882",
    "addr:postcode":"92027",
    "addr:street":"E El Norte Pkwy",
    "iso:country":"US",
    "sg:address":"1882 E el Norte Pkwy",
    "sg:city":"Escondido",
    "sg:classifiers":[
        {
            "category":"Shopping",
            "subcategory":"Books",
            "type":"Retail Goods"
        }
    ],
    "sg:phone":"+1 760 546 0490",
    "sg:postcode":"92027",
    "sg:province":"CA",
    "sg:tags":[
        "dealer"
    ],
    "wof:name":"Craftsman Book Co",
    "wof:placetype":"venue"
},
  "geometry": {"coordinates":[-117.06553,33.149688],"type":"Point"}
}