{
  "type": "Feature",
  "properties": {
    "addr:full":"14784 Magnolia Dr Magalia CA 95954",
    "addr:housenumber":"14784",
    "addr:postcode":"95954",
    "addr:street":"Magnolia Dr Magalia",
    "iso:country":"US",
    "sg:address":"14784 Magnolia Dr",
    "sg:city":"Magalia",
    "sg:classifiers":[
        {
            "category":"Personal",
            "type":"Services"
        }
    ],
    "sg:phone":"+1 530 873 1326",
    "sg:postcode":"95954",
    "sg:province":"CA",
    "sg:tags":[
        "consultant",
        "wedding"
    ],
    "wof:name":"Forever After Bridal Cnslntng",
    "wof:placetype":"venue"
},
  "geometry": {"coordinates":[-121.58705399999999,39.846897],"type":"Point"}
}