{
  "type": "Feature",
  "properties": {
    "iso:country":"US",
    "sg:address":"13450 Maxella Ave Ste 240",
    "sg:city":"Marina Dl Rey",
    "sg:classifiers":[
        {
            "category":"Shopping Center",
            "type":"Public Place"
        }
    ],
    "sg:phone":"+1 310 305 9180",
    "sg:postcode":"90292",
    "sg:province":"CA",
    "wof:name":"Villa Marina Marketplace",
    "wof:placetype":"venue"
},
  "geometry": {"coordinates":[-118.441456,33.986554],"type":"Point"}
}