{
  "type": "Feature",
  "properties": {
    "iso:country":"US",
    "sg:address":"13717 Victory Blvd",
    "sg:city":"Van Nuys",
    "sg:classifiers":[
        {
            "category":"Personal",
            "type":"Services"
        },
        {
            "category":"Retail",
            "subcategory":"Storage",
            "type":"Services"
        }
    ],
    "sg:phone":"+1 818 977 7542",
    "sg:postcode":"91401",
    "sg:province":"CA",
    "sg:tags":[
        "mover",
        "self"
    ],
    "wof:name":"Budget Rent A Car System Inc",
    "wof:placetype":"venue"
},
  "geometry": {"coordinates":[-118.431999,34.186699],"type":"Point"}
}