{
  "type": "Feature",
  "properties": {
    "addr:full":"27174 Ortega Hwy San Juan Cpstrno CA 92675",
    "addr:housenumber":"27174",
    "addr:postcode":"92675",
    "addr:street":"Ortega Hwy",
    "iso:country":"US",
    "sg:address":"27174 Ortega Hwy",
    "sg:city":"San Juan Cpstrno",
    "sg:classifiers":[
        {
            "category":"Professional",
            "subcategory":"Accounting & Tax Preparation",
            "type":"Services"
        }
    ],
    "sg:phone":"+1 949 240 2055",
    "sg:postcode":"92675",
    "sg:province":"CA",
    "sg:tags":[
        "bookkeeping",
        "general"
    ],
    "wof:name":"Gorman Co",
    "wof:placetype":"venue"
},
  "geometry": {"coordinates":[-117.65667999999999,33.503059],"type":"Point"}
}