{
  "type": "Feature",
  "properties": {
    "addr:full":"2414 Edsel Dr Milpitas CA 95035",
    "addr:housenumber":"2414",
    "addr:postcode":"95035",
    "addr:street":"Edsel Dr",
    "iso:country":"US",
    "sg:address":"2414 Edsel Dr",
    "sg:city":"Milpitas",
    "sg:classifiers":[
        {
            "category":"Wholesale",
            "subcategory":"Computers",
            "type":"Manufacturing & Wholesale Goods"
        }
    ],
    "sg:phone":"+1 408 942 5092",
    "sg:postcode":"95035",
    "sg:province":"CA",
    "sg:tags":[
        "services-wholesale",
        "software",
        "accessory"
    ],
    "wof:name":"T W Enterprises",
    "wof:placetype":"venue"
},
  "geometry": {"coordinates":[-121.865487,37.432097],"type":"Point"}
}