{
  "type": "Feature",
  "properties": {
    "addr:full":"650 Priddy Dr Dixon CA 95620",
    "addr:housenumber":"650",
    "addr:postcode":"95620",
    "addr:street":"Priddy Dr",
    "iso:country":"US",
    "sg:address":"650 Priddy Dr",
    "sg:city":"Dixon",
    "sg:classifiers":[
        {
            "category":"Professional",
            "type":"Services"
        }
    ],
    "sg:phone":"+1 707 678 9322",
    "sg:postcode":"95620",
    "sg:province":"CA",
    "wof:name":"Rudy Rocha",
    "wof:placetype":"venue"
},
  "geometry": {"coordinates":[-121.814156,38.45217],"type":"Point"}
}