{
  "type": "Feature",
  "properties": {
    "iso:country":"US",
    "sg:address":"10100 Gaviota Ave",
    "sg:city":"North Hills",
    "sg:classifiers":[
        {
            "category":"Manufacturing",
            "subcategory":"Printing",
            "type":"Manufacturing & Wholesale Goods"
        }
    ],
    "sg:phone":"+1 818 895 1901",
    "sg:postcode":"91343",
    "sg:province":"CA",
    "sg:tags":[
        "publishing"
    ],
    "wof:name":"McClam Publishing Co",
    "wof:placetype":"venue"
},
  "geometry": {"coordinates":[-118.48266,34.256457],"type":"Point"}
}