{
  "type": "Feature",
  "properties": {
    "addr:full":"10620 Daines Dr Temple City CA 91780",
    "addr:housenumber":"10620",
    "addr:postcode":"91780",
    "addr:street":"Daines Dr",
    "iso:country":"US",
    "sg:address":"10620 Daines Dr",
    "sg:city":"Temple City",
    "sg:classifiers":[
        {
            "category":"Travel",
            "subcategory":"Hotels & Motels",
            "type":"Entertainment"
        }
    ],
    "sg:phone":"+1 626 453 3571",
    "sg:postcode":"91780",
    "sg:province":"CA",
    "sg:tags":[
        "operation"
    ],
    "wof:name":"Raymond Tam",
    "wof:placetype":"venue"
},
  "geometry": {"coordinates":[-118.03902600000001,34.102279],"type":"Point"}
}