{
  "type": "Feature",
  "properties": {
    "iso:country":"US",
    "sg:address":"1436 Ayala Dr",
    "sg:city":"Rialto",
    "sg:classifiers":[
        {
            "category":"Shopping",
            "type":"Retail Goods"
        }
    ],
    "sg:phone":"+1 909 873 2710",
    "sg:postcode":"92376",
    "sg:province":"CA",
    "sg:tags":[
        "church",
        "supply"
    ],
    "wof:name":"Jubilee Project Operation Blsg",
    "wof:placetype":"venue"
},
  "geometry": {"coordinates":[-117.393206,34.126424],"type":"Point"}
}