{
  "type": "Feature",
  "properties": {
    "iso:country":"US",
    "sg:address":"226 Bayview St",
    "sg:city":"San Rafael",
    "sg:classifiers":[
        {
            "category":"Manufacturing",
            "subcategory":"Tools & Machinery",
            "type":"Manufacturing & Wholesale Goods"
        }
    ],
    "sg:phone":"+1 415 453 6950",
    "sg:postcode":"94901",
    "sg:province":"CA",
    "sg:tags":[
        "machine",
        "automotive",
        "shop"
    ],
    "wof:name":"Meyer Advanced Engineering",
    "wof:placetype":"venue"
},
  "geometry": {"coordinates":[-122.534539,37.967917],"type":"Point"}
}