{
  "type": "Feature",
  "properties": {
    "addr:full":"1758 S Miramonte Ave Ontario CA 91761",
    "addr:housenumber":"1758",
    "addr:postcode":"91761",
    "addr:street":"S Miramonte Ave",
    "iso:country":"US",
    "sg:address":"1758 S Miramonte Ave",
    "sg:city":"Ontario",
    "sg:classifiers":[
        {
            "category":"Building & Trades",
            "subcategory":"Cleaning & Sanitation",
            "type":"Services"
        }
    ],
    "sg:phone":"+1 909 983 3421",
    "sg:postcode":"91761",
    "sg:province":"CA",
    "sg:tags":[
        "janitor"
    ],
    "wof:name":"Andrew Wynn's Janitorial Svc",
    "wof:placetype":"venue"
},
  "geometry": {"coordinates":[-117.64263699999999,34.041661],"type":"Point"}
}