{
  "type": "Feature",
  "properties": {
    "addr:full":"2830 E Philadelphia St Ontario CA 91761",
    "addr:housenumber":"2830 e",
    "addr:postcode":"91761",
    "addr:street":"Philadelphia St",
    "iso:country":"US",
    "sg:address":"2830 E Philadelphia St",
    "sg:city":"Ontario",
    "sg:classifiers":[
        {
            "category":"Wholesale",
            "subcategory":"Furniture",
            "type":"Manufacturing & Wholesale Goods"
        }
    ],
    "sg:phone":"+1 909 930 2989",
    "sg:postcode":"91761",
    "sg:province":"CA",
    "wof:name":"Accousa",
    "wof:placetype":"venue"
},
  "geometry": {"coordinates":[-117.588041,34.033657],"type":"Point"}
}