{
  "type": "Feature",
  "properties": {
    "iso:country":"US",
    "sg:address":"1059 Di Giulio Ave",
    "sg:city":"Santa Clara",
    "sg:classifiers":[
        {
            "category":"Professional",
            "subcategory":"Engineering",
            "type":"Services"
        }
    ],
    "sg:phone":"+1 408 496 0021",
    "sg:postcode":"95050",
    "sg:province":"CA",
    "sg:tags":[
        "engineer"
    ],
    "wof:name":"Waltec Engineering",
    "wof:placetype":"venue"
},
  "geometry": {"coordinates":[-121.950732,37.3611],"type":"Point"}
}