{
  "type": "Feature",
  "properties": {
    "iso:country":"US",
    "sg:address":"2007 Lakehurst Cir",
    "sg:city":"Alameda",
    "sg:classifiers":[
        {
            "category":"Arts & Performance",
            "subcategory":"Theater",
            "type":"Entertainment"
        }
    ],
    "sg:phone":"+1 510 865 2064",
    "sg:postcode":"94501",
    "sg:province":"CA",
    "sg:tags":[
        "live",
        "music"
    ],
    "wof:name":"Wall Of Blues",
    "wof:placetype":"venue"
},
  "geometry": {"coordinates":[-122.285883,37.788804],"type":"Point"}
}