{
  "type": "Feature",
  "properties": {
    "addr:full":"18591 Colima Rd Rowland Heights CA 91748",
    "addr:housenumber":"18591",
    "addr:postcode":"91748",
    "addr:street":"Colima Rd",
    "iso:country":"US",
    "sg:address":"18591 Colima Rd",
    "sg:city":"Rowland Heights",
    "sg:classifiers":[
        {
            "category":"Professional",
            "subcategory":"Computer Services",
            "type":"Services"
        }
    ],
    "sg:phone":"+1 626 617 7334",
    "sg:postcode":"91748",
    "sg:province":"CA",
    "wof:name":"James Computer Solutions",
    "wof:placetype":"venue"
},
  "geometry": {"coordinates":[-117.89917199999999,33.988141],"type":"Point"}
}