{
  "type": "Feature",
  "properties": {
    "iso:country":"US",
    "sg:address":"9206 Rosecrans Ave",
    "sg:city":"Bellflower",
    "sg:classifiers":[
        {
            "category":"Building & Trades",
            "subcategory":"Construction",
            "type":"Services"
        }
    ],
    "sg:phone":"+1 562 529 8054",
    "sg:postcode":"90706",
    "sg:province":"CA",
    "sg:tags":[
        "concrete",
        "cutting",
        "breaking",
        "sawing"
    ],
    "wof:name":"West Coast Concrete Cutting",
    "wof:placetype":"venue"
},
  "geometry": {"coordinates":[-118.135926,33.903981],"type":"Point"}
}