{
  "type": "Feature",
  "properties": {
    "iso:country":"US",
    "sg:address":"1112 S Vine St",
    "sg:city":"Fallbrook",
    "sg:classifiers":[
        {
            "category":"Farming",
            "subcategory":"Farm",
            "type":"Manufacturing & Wholesale Goods"
        }
    ],
    "sg:phone":"+1 760 728 8597",
    "sg:postcode":"92028",
    "sg:province":"CA",
    "wof:name":"Lorridanna Farms",
    "wof:placetype":"venue"
},
  "geometry": {"coordinates":[-117.250731,33.372346],"type":"Point"}
}