{
  "type": "Feature",
  "properties": {
    "addr:full":"167 Tharp Dr Moraga CA 94556",
    "addr:housenumber":"167",
    "addr:postcode":"94556",
    "addr:street":"Tharp Dr",
    "iso:country":"US",
    "sg:address":"167 Tharp Dr",
    "sg:city":"Moraga",
    "sg:classifiers":[
        {
            "category":"Wholesale",
            "subcategory":"Non-durable Goods",
            "type":"Manufacturing & Wholesale Goods"
        }
    ],
    "sg:phone":"+1 925 376 1625",
    "sg:postcode":"94556",
    "sg:province":"CA",
    "sg:tags":[
        "product",
        "specialty"
    ],
    "wof:name":"Phayer Ideas",
    "wof:placetype":"venue"
},
  "geometry": {"coordinates":[-122.122151,37.817434],"type":"Point"}
}