{
  "type": "Feature",
  "properties": {
    "iso:country":"US",
    "sg:address":"1415 11th St",
    "sg:city":"Modesto",
    "sg:classifiers":[
        {
            "category":"Professional",
            "subcategory":"Art Services",
            "type":"Services"
        }
    ],
    "sg:phone":"+1 209 521 2266",
    "sg:postcode":"95354",
    "sg:province":"CA",
    "sg:tags":[
        "photographer"
    ],
    "wof:name":"Don Schneider Photography",
    "wof:placetype":"venue"
},
  "geometry": {"coordinates":[-121.004785,37.645712],"type":"Point"}
}