{
  "type": "Feature",
  "properties": {
    "addr:full":"1059 A St Hayward CA 94541",
    "addr:housenumber":"1059",
    "addr:postcode":"94541",
    "addr:street":"A St",
    "iso:country":"US",
    "sg:address":"1059 A St",
    "sg:city":"Hayward",
    "sg:classifiers":[
        {
            "category":"Health Services",
            "subcategory":"Chiropractor",
            "type":"Services"
        }
    ],
    "sg:phone":"+1 510 889 9198",
    "sg:postcode":"94541",
    "sg:province":"CA",
    "wof:name":"Peter K Yattaw DC",
    "wof:placetype":"venue"
},
  "geometry": {"coordinates":[-122.082071,37.6751],"type":"Point"}
}