{
  "type": "Feature",
  "properties": {
    "addr:full":"4012 Broadway Oakland CA 94611",
    "addr:housenumber":"4012",
    "addr:postcode":"94611",
    "addr:street":"Broadway",
    "iso:country":"US",
    "sg:address":"4012 Broadway",
    "sg:city":"Oakland",
    "sg:classifiers":[
        {
            "category":"Restaurant",
            "type":"Food & Drink"
        }
    ],
    "sg:phone":"+1 510 547 7600",
    "sg:postcode":"94611",
    "sg:province":"CA",
    "sg:tags":[
        "breakfast",
        "brunch"
    ],
    "sg:website":"www.mamasroyalcafeoakland.com",
    "wof:name":"Mama's Royal Cafe",
    "wof:placetype":"venue"
},
  "geometry": {"coordinates":[-122.25599699999999,37.827599],"type":"Point"}
}