{
  "type": "Feature",
  "properties": {
    "iso:country":"US",
    "sg:address":"1640 Lafayette Street",
    "sg:city":"Santa Clara",
    "sg:classifiers":[
        {
            "category":"Professional",
            "subcategory":"Lawyer & Legal Services",
            "type":"Services"
        }
    ],
    "sg:phone":"+1 408 248 3509",
    "sg:postcode":"95050",
    "sg:province":"CA",
    "wof:name":"Hae Young Lee Atty",
    "wof:placetype":"venue"
},
  "geometry": {"coordinates":[-121.946366,37.356011],"type":"Point"}
}