{
  "type": "Feature",
  "properties": {
    "iso:country":"US",
    "sg:address":"3219 Ida Dr",
    "sg:city":"Concord",
    "sg:classifiers":[
        {
            "category":"Building & Trades",
            "subcategory":"Construction",
            "type":"Services"
        }
    ],
    "sg:phone":"+1 510 768 0442",
    "sg:postcode":"94519",
    "sg:province":"CA",
    "sg:tags":[
        "home",
        "maintenance",
        "repair"
    ],
    "wof:name":"Espinoza Tile",
    "wof:placetype":"venue"
},
  "geometry": {"coordinates":[-122.03218699999999,37.989568],"type":"Point"}
}