{
  "type": "Feature",
  "properties": {
    "iso:country":"US",
    "sg:address":"420 N McKinley St",
    "sg:city":"Corona",
    "sg:classifiers":[
        {
            "category":"Wholesale",
            "subcategory":"Medical Equipment & Supplies",
            "type":"Manufacturing & Wholesale Goods"
        }
    ],
    "sg:phone":"+1 951 278 1385",
    "sg:postcode":"92879",
    "sg:province":"CA",
    "wof:name":"Prosperties Enterprises",
    "wof:placetype":"venue"
},
  "geometry": {"coordinates":[-117.519879,33.888716],"type":"Point"}
}