{
  "type": "Feature",
  "properties": {
    "addr:full":"5390 Harter Ln La Canada Fltrdg CA 91011",
    "addr:postcode":"5390;91011",
    "addr:street":"Harter Ln La",
    "iso:country":"US",
    "sg:address":"5390 Harter Ln",
    "sg:city":"La Canada Fltrdg",
    "sg:classifiers":[
        {
            "category":"Health Services",
            "subcategory":"Clinic",
            "type":"Services"
        }
    ],
    "sg:phone":"+1 818 790 7951",
    "sg:postcode":"91011",
    "sg:province":"CA",
    "wof:name":"Excel Managed Healthcare",
    "wof:placetype":"venue"
},
  "geometry": {"coordinates":[-118.195436,34.224028],"type":"Point"}
}