{
  "type": "Feature",
  "properties": {
    "addr:full":"2408 F St Bakersfield CA 93301",
    "addr:housenumber":"2408",
    "addr:postcode":"93301",
    "addr:street":"F St",
    "iso:country":"US",
    "sg:address":"2408 F St",
    "sg:city":"Bakersfield",
    "sg:classifiers":[
        {
            "category":"Food & Beverages",
            "subcategory":"Liquor & Beverages",
            "type":"Retail Goods"
        }
    ],
    "sg:phone":"+1 661 323 0503",
    "sg:postcode":"93301",
    "sg:province":"CA",
    "wof:name":"Westchester Liquors",
    "wof:placetype":"venue"
},
  "geometry": {"coordinates":[-119.02340700000001,35.382846],"type":"Point"}
}