{
  "type": "Feature",
  "properties": {
    "addr:full":"12439 Magnolia Blvd., Ste. 214 North Hollywood CA 91607",
    "addr:housenumber":"12439",
    "addr:postcode":"91607",
    "addr:street":"Magnolia Blvd. Ste. 214",
    "iso:country":"US",
    "sg:address":"12439 Magnolia Blvd., Ste. 214",
    "sg:city":"North Hollywood",
    "sg:classifiers":[
        {
            "category":"Personal",
            "type":"Services"
        }
    ],
    "sg:phone":"+1 888 900 0555",
    "sg:postcode":"91607",
    "sg:province":"CA",
    "sg:tags":[
        "mover"
    ],
    "sg:website":"www.antmoving.com",
    "wof:name":"Ant Moving",
    "wof:placetype":"venue"
},
  "geometry": {"coordinates":[-118.40449599999999,34.1649],"type":"Point"}
}