{
  "type": "Feature",
  "properties": {
    "iso:country":"US",
    "sg:address":"290 California Drive",
    "sg:city":"Burlingame",
    "sg:classifiers":[
        {
            "category":"Transit Center",
            "subcategory":"Passenger",
            "type":"Transportation"
        }
    ],
    "sg:phone":"+1 800 660 4287",
    "sg:postcode":"94010",
    "sg:province":"CA",
    "sg:website":"www.caltrain.com",
    "wof:name":"Burlingame Caltrain Station",
    "wof:placetype":"venue"
},
  "geometry": {"coordinates":[-122.345223,37.579747],"type":"Point"}
}