{
  "type": "Feature",
  "properties": {
    "addr:full":"842 W Palmdale Blvd Palmdale CA 93551",
    "addr:housenumber":"842",
    "addr:postcode":"ca 93551",
    "addr:street":"W Palmdale Blvd",
    "iso:country":"US",
    "sg:address":"842 W Palmdale Blvd",
    "sg:city":"Palmdale",
    "sg:classifiers":[
        {
            "category":"Shopping",
            "subcategory":"Used Merchandise",
            "type":"Retail Goods"
        }
    ],
    "sg:phone":"+1 661 274 1431",
    "sg:postcode":"93551",
    "sg:province":"CA",
    "sg:tags":[
        "book",
        "rare",
        "dealer"
    ],
    "wof:name":"Li'l Book Bug",
    "wof:placetype":"venue"
},
  "geometry": {"coordinates":[-118.146474,34.586942],"type":"Point"}
}