{
  "type": "Feature",
  "properties": {
    "iso:country":"US",
    "sg:address":"4710 Mountain Lakes Blvd",
    "sg:city":"Redding",
    "sg:classifiers":[
        {
            "category":"Utilities",
            "subcategory":"Telephone",
            "type":"Services"
        }
    ],
    "sg:phone":"+1 530 244 8937",
    "sg:postcode":"96003",
    "sg:province":"CA",
    "sg:tags":[
        "communications"
    ],
    "wof:name":"Pacbell Trini Hudson",
    "wof:placetype":"venue"
},
  "geometry": {"coordinates":[-122.37602,40.629159],"type":"Point"}
}