{
  "type": "Feature",
  "properties": {
    "iso:country":"US",
    "sg:address":"1136 Saranap Ave",
    "sg:city":"Walnut Creek",
    "sg:classifiers":[
        {
            "category":"Organizations",
            "subcategory":"Non-profit Organization",
            "type":"Services"
        }
    ],
    "sg:phone":"+1 925 210 0268",
    "sg:postcode":"94595",
    "sg:province":"CA",
    "sg:website":"www.ccmt.org",
    "wof:name":"Contra Costa Musical Theatre",
    "wof:placetype":"venue"
},
  "geometry": {"coordinates":[-122.07773299999999,37.895576],"type":"Point"}
}