{
  "type": "Feature",
  "properties": {
    "iso:country":"US",
    "sg:address":"21604 Ventura Blvd",
    "sg:city":"Woodland Hills",
    "sg:classifiers":[
        {
            "category":"Deli",
            "type":"Food & Drink"
        },
        {
            "category":"Restaurant",
            "type":"Food & Drink"
        }
    ],
    "sg:phone":"+1 818 719 0003",
    "sg:postcode":"91364",
    "sg:province":"CA",
    "sg:tags":[
        "pizza"
    ],
    "sg:website":"www.zanospizza.com",
    "wof:name":"Zanos Pizza",
    "wof:placetype":"venue"
},
  "geometry": {"coordinates":[-118.59899900000001,34.168301],"type":"Point"}
}