{
  "type": "Feature",
  "properties": {
    "iso:country":"US",
    "sg:address":"1259 Merkley Ave",
    "sg:city":"West Sacramento",
    "sg:classifiers":[
        {
            "category":"Restaurant",
            "type":"Food & Drink"
        }
    ],
    "sg:phone":"+1 916 452 9999",
    "sg:postcode":"95691",
    "sg:province":"CA",
    "sg:tags":[
        "caterer"
    ],
    "sg:website":"www.jealousycatering.com",
    "wof:name":"Jealousy Catering",
    "wof:placetype":"venue"
},
  "geometry": {"coordinates":[-121.525138,38.579439],"type":"Point"}
}