{
  "type": "Feature",
  "properties": {
    "iso:country":"US",
    "sg:address":"3328 Downie Rd",
    "sg:city":"Denair",
    "sg:classifiers":[
        {
            "category":"Farming",
            "subcategory":"Poultry Farm",
            "type":"Manufacturing & Wholesale Goods"
        }
    ],
    "sg:phone":"+1 209 667 5708",
    "sg:postcode":"95316",
    "sg:province":"CA",
    "sg:tags":[
        "egg"
    ],
    "wof:name":"Richard Medeiros",
    "wof:placetype":"venue"
},
  "geometry": {"coordinates":[-120.773805,37.594263],"type":"Point"}
}