{
  "type": "Feature",
  "properties": {
    "iso:country":"US",
    "sg:address":"18 Gazania Ter",
    "sg:city":"Fremont",
    "sg:classifiers":[
        {
            "category":"Local Transit",
            "type":"Transportation"
        }
    ],
    "sg:phone":"+1 510 797 4884",
    "sg:postcode":"94536",
    "sg:province":"CA",
    "sg:tags":[
        "limousine"
    ],
    "wof:name":"A One Airport Transportation",
    "wof:placetype":"venue"
},
  "geometry": {"coordinates":[-121.96417700000001,37.567863],"type":"Point"}
}