{
  "type": "Feature",
  "properties": {
    "iso:country":"US",
    "sg:address":"125 E Tahquitz Canyon Way Ste 100",
    "sg:city":"Palm Springs",
    "sg:classifiers":[
        {
            "category":"Arts & Performance",
            "subcategory":"Art Gallery",
            "type":"Entertainment"
        },
        {
            "category":"Professional",
            "subcategory":"Printing & Photocopies",
            "type":"Services"
        },
        {
            "category":"Home & Garden",
            "subcategory":"Furniture",
            "type":"Retail Goods"
        }
    ],
    "sg:phone":"+1 760 322 5777",
    "sg:postcode":"92262",
    "sg:province":"CA",
    "sg:tags":[
        "store"
    ],
    "sg:website":"www.thewrightimagegallery.com",
    "wof:name":"Wright Image Gallery",
    "wof:placetype":"venue"
},
  "geometry": {"coordinates":[-116.546184,33.823102],"type":"Point"}
}