{
  "type": "Feature",
  "properties": {
    "iso:country":"US",
    "sg:address":"60 Garden Ct",
    "sg:city":"Monterey",
    "sg:classifiers":[
        {
            "category":"Professional",
            "subcategory":"Management & Consulting",
            "type":"Services"
        },
        {
            "category":"Manufacturing",
            "subcategory":"Printing",
            "type":"Manufacturing & Wholesale Goods"
        }
    ],
    "sg:phone":"+1 831 649 8384",
    "sg:postcode":"93940",
    "sg:province":"CA",
    "sg:tags":[
        "educational",
        "consultant",
        "training",
        "publishing",
        "text"
    ],
    "sg:website":"www.dsink.com",
    "wof:name":"Darryl L Sink & Associates",
    "wof:placetype":"venue"
},
  "geometry": {"coordinates":[-121.855179,36.585498],"type":"Point"}
}