{
  "type": "Feature",
  "properties": {
    "addr:full":"1677 E 6th St Beaumont CA 92223",
    "addr:housenumber":"1677",
    "addr:postcode":"92223",
    "addr:street":"E 6Th St",
    "iso:country":"US",
    "sg:address":"1677 E 6th St",
    "sg:city":"Beaumont",
    "sg:classifiers":[
        {
            "category":"Personal",
            "subcategory":"Beauty Salon",
            "type":"Services"
        }
    ],
    "sg:phone":"+1 951 769 0777",
    "sg:postcode":"92223",
    "sg:province":"CA",
    "wof:name":"Chez Lee's Salon Decouiffue",
    "wof:placetype":"venue"
},
  "geometry": {"coordinates":[-116.948272,33.92931],"type":"Point"}
}