{
  "type": "Feature",
  "properties": {
    "iso:country":"US",
    "sg:address":"2717 Roeding Rd Ofc",
    "sg:city":"Ceres",
    "sg:classifiers":[
        {
            "category":"Real Estate",
            "subcategory":"Real Estate Operator",
            "type":"Services"
        }
    ],
    "sg:phone":"+1 209 538 6344",
    "sg:postcode":"95307",
    "sg:province":"CA",
    "sg:tags":[
        "apartment"
    ],
    "wof:name":"Windmere Apartments",
    "wof:placetype":"venue"
},
  "geometry": {"coordinates":[-120.958,37.584801],"type":"Point"}
}