{
  "type": "Feature",
  "properties": {
    "addr:full":"9360 Telegraph Rd Downey CA 90240",
    "addr:housenumber":"9360",
    "addr:postcode":"90240",
    "addr:street":"Telegraph Rd",
    "iso:country":"US",
    "sg:address":"9360 Telegraph Rd",
    "sg:city":"Downey",
    "sg:classifiers":[
        {
            "category":"Health Services",
            "subcategory":"Doctor",
            "type":"Services"
        },
        {
            "category":"Health Services",
            "subcategory":"Hospital",
            "type":"Services"
        }
    ],
    "sg:phone":"+1 562 869 0180",
    "sg:postcode":"90240",
    "sg:province":"CA",
    "sg:tags":[
        "sleep",
        "treatment",
        "disorders-information"
    ],
    "wof:name":"Clinica Mi Pueblo",
    "wof:placetype":"venue"
},
  "geometry": {"coordinates":[-118.10325400000001,33.95609],"type":"Point"}
}