{
  "type": "Feature",
  "properties": {
    "iso:country":"US",
    "sg:address":"4787 Old Redwood Hwy",
    "sg:city":"Santa Rosa",
    "sg:classifiers":[
        {
            "category":"Retail",
            "subcategory":"Auto Rental",
            "type":"Services"
        }
    ],
    "sg:phone":"+1 707 527 9999",
    "sg:postcode":"95403",
    "sg:province":"CA",
    "sg:tags":[
        "passenger",
        "car"
    ],
    "wof:name":"Enterprise Rent-A-Car",
    "wof:placetype":"venue"
},
  "geometry": {"coordinates":[-122.75058300000001,38.500582],"type":"Point"}
}