{
  "type": "Feature",
  "properties": {
    "addr:full":"2552 W Avenue 31 Los Angeles CA 90065",
    "addr:housenumber":"2552;31",
    "addr:postcode":"90065",
    "addr:street":"W Avenue",
    "iso:country":"US",
    "sg:address":"2552 W Avenue 31",
    "sg:city":"Los Angeles",
    "sg:classifiers":[
        {
            "category":"Communications",
            "subcategory":"Newspaper",
            "type":"Services"
        }
    ],
    "sg:phone":"+1 323 221 5851",
    "sg:postcode":"90065",
    "sg:province":"CA",
    "sg:tags":[
        "print",
        "medium"
    ],
    "wof:name":"Thoi Luan News",
    "wof:placetype":"venue"
},
  "geometry": {"coordinates":[-118.238998,34.1091],"type":"Point"}
}