{
  "type": "Feature",
  "properties": {
    "iso:country":"US",
    "sg:address":"1605 S Melrose Dr Ste C",
    "sg:city":"Vista",
    "sg:classifiers":[
        {
            "category":"Sports & Exercise",
            "subcategory":"Gym",
            "type":"Entertainment"
        }
    ],
    "sg:phone":"+1 760 734 4400",
    "sg:postcode":"92081",
    "sg:province":"CA",
    "sg:tags":[
        "instruction",
        "gymnastics"
    ],
    "wof:name":"J W Tumbles",
    "wof:placetype":"venue"
},
  "geometry": {"coordinates":[-117.246908,33.166347],"type":"Point"}
}