{
  "type": "Feature",
  "properties": {
    "addr:full":"9819 Glenoaks Blvd Sun Valley CA 91352",
    "addr:housenumber":"9819",
    "addr:postcode":"91352",
    "addr:street":"Glenoaks Blvd",
    "iso:country":"US",
    "sg:address":"9819 Glenoaks Blvd",
    "sg:city":"Sun Valley",
    "sg:classifiers":[
        {
            "category":"Real Estate",
            "subcategory":"Real Estate Agent",
            "type":"Services"
        }
    ],
    "sg:phone":"+1 818 683 8100",
    "sg:postcode":"91352",
    "sg:province":"CA",
    "sg:tags":[
        "relocation"
    ],
    "wof:name":"Eden Relocation",
    "wof:placetype":"venue"
},
  "geometry": {"coordinates":[-118.385496,34.247468],"type":"Point"}
}