{
  "type": "Feature",
  "properties": {
    "iso:country":"US",
    "sg:address":"8590 Church St",
    "sg:city":"Gilroy",
    "sg:classifiers":[
        {
            "category":"Personal",
            "type":"Services"
        }
    ],
    "sg:phone":"+1 408 847 7096",
    "sg:postcode":"95020",
    "sg:province":"CA",
    "sg:tags":[
        "therapist",
        "massage"
    ],
    "wof:name":"Sports Massage Therapy Ctr",
    "wof:placetype":"venue"
},
  "geometry": {"coordinates":[-121.579707,37.022595],"type":"Point"}
}