{
  "type": "Feature",
  "properties": {
    "iso:country":"US",
    "sg:address":"295 Mortimer Ave",
    "sg:city":"Fremont",
    "sg:classifiers":[
        {
            "category":"Professional",
            "type":"Services"
        }
    ],
    "sg:phone":"+1 510 818 9417",
    "sg:postcode":"94536",
    "sg:province":"CA",
    "wof:name":"Eveon Inc",
    "wof:placetype":"venue"
},
  "geometry": {"coordinates":[-121.9671,37.565694],"type":"Point"}
}