{
  "type": "Feature",
  "properties": {
    "addr:full":"1020 N Euclid St Anaheim CA 92801",
    "addr:housenumber":"1020",
    "addr:postcode":"92801",
    "addr:street":"N Euclid St",
    "iso:country":"US",
    "sg:address":"1020 N Euclid St",
    "sg:city":"Anaheim",
    "sg:classifiers":[
        {
            "category":"Shopping",
            "subcategory":"Pharmacy",
            "type":"Retail Goods"
        },
        {
            "category":"Food & Beverages",
            "subcategory":"Groceries & Convenience Stores",
            "type":"Retail Goods"
        }
    ],
    "sg:phone":"+1 714 535 9016",
    "sg:postcode":"92801",
    "sg:province":"CA",
    "sg:tags":[
        "drugstore"
    ],
    "wof:name":"Ralphs Grocery Company",
    "wof:placetype":"venue"
},
  "geometry": {"coordinates":[-117.942001,33.846901],"type":"Point"}
}