{
  "type": "Feature",
  "properties": {
    "iso:country":"US",
    "sg:address":"1701 Divisadero Street",
    "sg:city":"San Francisco",
    "sg:classifiers":[
        {
            "category":"Health Services",
            "subcategory":"Doctor",
            "type":"Services"
        }
    ],
    "sg:phone":"+1 415 353 7870",
    "sg:postcode":"94115",
    "sg:province":"CA",
    "sg:tags":[
        "dermatologist"
    ],
    "wof:name":"Maibach Howard I MD",
    "wof:placetype":"venue"
},
  "geometry": {"coordinates":[-122.44000200000001,37.785599],"type":"Point"}
}