{
  "type": "Feature",
  "properties": {
    "addr:full":"1117 Englander St San Pedro CA 90731",
    "addr:housenumber":"1117",
    "addr:postcode":"90731",
    "addr:street":"Englander St",
    "iso:country":"US",
    "sg:address":"1117 Englander St",
    "sg:city":"San Pedro",
    "sg:classifiers":[
        {
            "category":"Wholesale",
            "subcategory":"Poultry",
            "type":"Manufacturing & Wholesale Goods"
        }
    ],
    "sg:phone":"+1 310 833 9436",
    "sg:postcode":"90731",
    "sg:province":"CA",
    "wof:name":"Tyson Foods Inc",
    "wof:placetype":"venue"
},
  "geometry": {"coordinates":[-118.301086,33.764844],"type":"Point"}
}