{
  "type": "Feature",
  "properties": {
    "addr:full":"1921 W 35th St Los Angeles CA 90018",
    "addr:housenumber":"1921",
    "addr:postcode":"90018",
    "addr:street":"W 35Th St",
    "iso:country":"US",
    "sg:address":"1921 W 35th St",
    "sg:city":"Los Angeles",
    "sg:classifiers":[
        {
            "category":"Building & Trades",
            "subcategory":"Construction",
            "type":"Services"
        }
    ],
    "sg:phone":"+1 323 733 7802",
    "sg:postcode":"90018",
    "sg:province":"CA",
    "sg:tags":[
        "general",
        "contractor"
    ],
    "wof:name":"Hector's Construction Co",
    "wof:placetype":"venue"
},
  "geometry": {"coordinates":[-118.31527800000001,34.024643],"type":"Point"}
}