{
  "type": "Feature",
  "properties": {
    "iso:country":"US",
    "sg:address":"1526 E Main St",
    "sg:city":"Visalia",
    "sg:classifiers":[
        {
            "category":"Wholesale",
            "subcategory":"Auto Parts",
            "type":"Manufacturing & Wholesale Goods"
        }
    ],
    "sg:phone":"+1 559 625 1248",
    "sg:postcode":"93292",
    "sg:province":"CA",
    "sg:tags":[
        "equipment",
        "truck"
    ],
    "wof:name":"California Truck Engineering",
    "wof:placetype":"venue"
},
  "geometry": {"coordinates":[-119.276382,36.330289],"type":"Point"}
}