{
  "type": "Feature",
  "properties": {
    "iso:country":"US",
    "sg:address":"1414 Cameo Dr",
    "sg:city":"Del Mar",
    "sg:classifiers":[
        {
            "category":"Shopping",
            "subcategory":"Clothing, Apparel, & Fashions",
            "type":"Retail Goods"
        }
    ],
    "sg:phone":"+1 858 792 1359",
    "sg:postcode":"92026",
    "sg:province":"CA",
    "wof:name":"Julie's Beach Wear",
    "wof:placetype":"venue"
},
  "geometry": {"coordinates":[-117.086122,33.144894],"type":"Point"}
}