{
  "type": "Feature",
  "properties": {
    "addr:full":"5736 McDonie Ave Woodland Hills CA 91367",
    "addr:housenumber":"5736",
    "addr:postcode":"91367",
    "addr:street":"Mcdonie Ave",
    "iso:country":"US",
    "sg:address":"5736 McDonie Ave",
    "sg:city":"Woodland Hills",
    "sg:classifiers":[
        {
            "category":"Manufacturing",
            "subcategory":"Aerospace",
            "type":"Manufacturing & Wholesale Goods"
        }
    ],
    "sg:phone":"+1 818 348 2148",
    "sg:postcode":"91367",
    "sg:province":"CA",
    "sg:tags":[
        "measuring",
        "i",
        "aircraft",
        "electrical",
        "mfg"
    ],
    "wof:name":"Control Products Co",
    "wof:placetype":"venue"
},
  "geometry": {"coordinates":[-118.57266199999999,34.177474],"type":"Point"}
}