{
  "type": "Feature",
  "properties": {
    "addr:full":"2742 17th St San Francisco CA 94110",
    "addr:housenumber":"2742",
    "addr:postcode":"94110",
    "addr:street":"17Th St",
    "iso:country":"US",
    "sg:address":"2742 17th St",
    "sg:city":"San Francisco",
    "sg:classifiers":[
        {
            "category":"Professional",
            "subcategory":"Engineering",
            "type":"Services"
        }
    ],
    "sg:phone":"+1 415 626 6864",
    "sg:postcode":"94110",
    "sg:province":"CA",
    "sg:tags":[
        "engineer"
    ],
    "wof:name":"Keen Engineering",
    "wof:placetype":"venue"
},
  "geometry": {"coordinates":[-122.411008,37.764352],"type":"Point"}
}