{
  "type": "Feature",
  "properties": {
    "addr:full":"274 Sterling Ave Pacifica CA 94044",
    "addr:housenumber":"274",
    "addr:postcode":"94044",
    "addr:street":"Sterling Ave",
    "iso:country":"US",
    "sg:address":"274 Sterling Ave",
    "sg:city":"Pacifica",
    "sg:classifiers":[
        {
            "category":"Travel",
            "subcategory":"Travel Agent",
            "type":"Entertainment"
        }
    ],
    "sg:phone":"+1 650 359 3839",
    "sg:postcode":"94044",
    "sg:province":"CA",
    "sg:tags":[
        "agency"
    ],
    "wof:name":"Continental Russia Travel",
    "wof:placetype":"venue"
},
  "geometry": {"coordinates":[-122.510109,37.59378],"type":"Point"}
}