{
  "type": "Feature",
  "properties": {
    "addr:full":"7046 Hollywood Blvd Los Angeles CA 90028",
    "addr:housenumber":"7046",
    "addr:postcode":"90028",
    "addr:street":"Hollywood Blvd",
    "iso:country":"US",
    "sg:address":"7046 Hollywood Blvd",
    "sg:city":"Los Angeles",
    "sg:classifiers":[
        {
            "category":"Shopping",
            "subcategory":"Gifts & Souvenirs",
            "type":"Retail Goods"
        }
    ],
    "sg:phone":"+1 323 466 7046",
    "sg:postcode":"90028",
    "sg:province":"CA",
    "sg:tags":[
        "novelty"
    ],
    "wof:name":"International Love Boutiques",
    "wof:placetype":"venue"
},
  "geometry": {"coordinates":[-118.34207499999999,34.101463],"type":"Point"}
}