{
  "type": "Feature",
  "properties": {
    "iso:country":"US",
    "sg:address":"198 S Myrtle Ave",
    "sg:city":"Monrovia",
    "sg:classifiers":[
        {
            "category":"Personal",
            "subcategory":"Beauty Salon",
            "type":"Services"
        }
    ],
    "sg:phone":"+1 626 357 1886",
    "sg:postcode":"91016",
    "sg:province":"CA",
    "sg:website":"http://www.fashioncuts.net",
    "wof:name":"Alen at Fashion Cuts Hair Salon",
    "wof:placetype":"venue"
},
  "geometry": {"coordinates":[-118.001027,34.150271],"type":"Point"}
}