{
  "type": "Feature",
  "properties": {
    "iso:country":"US",
    "sg:address":"2777 Newton Ave",
    "sg:city":"San Diego",
    "sg:classifiers":[
        {
            "category":"Retail",
            "subcategory":"Repair Shop",
            "type":"Services"
        }
    ],
    "sg:phone":"+1 619 232 7619",
    "sg:postcode":"92113",
    "sg:province":"CA",
    "sg:tags":[
        "marine",
        "product",
        "catching",
        "electrical"
    ],
    "wof:name":"Alioa Electric",
    "wof:placetype":"venue"
},
  "geometry": {"coordinates":[-117.13552199999999,32.694787],"type":"Point"}
}