{
  "type": "Feature",
  "properties": {
    "iso:country":"US",
    "sg:address":"3335 Homestead Rd",
    "sg:city":"Santa Clara",
    "sg:classifiers":[
        {
            "category":"Shopping",
            "subcategory":"Beauty & Cosmetics",
            "type":"Retail Goods"
        }
    ],
    "sg:phone":"+1 408 243 4152",
    "sg:postcode":"95051",
    "sg:province":"CA",
    "sg:tags":[
        "merchandise"
    ],
    "wof:name":"Dashevska Marina",
    "wof:placetype":"venue"
},
  "geometry": {"coordinates":[-121.989519,37.337939],"type":"Point"}
}