{
  "type": "Feature",
  "properties": {
    "iso:country":"US",
    "sg:address":"3701 W Jefferson Blvd",
    "sg:city":"Los Angeles",
    "sg:classifiers":[
        {
            "category":"Restaurant",
            "type":"Food & Drink"
        }
    ],
    "sg:phone":"+1 323 735 7470",
    "sg:postcode":"90016",
    "sg:province":"CA",
    "sg:tags":[
        "southern"
    ],
    "wof:name":"Pete's Louisiana Style Hot Links",
    "wof:placetype":"venue"
},
  "geometry": {"coordinates":[-118.336521,34.025862],"type":"Point"}
}