{
  "type": "Feature",
  "properties": {
    "addr:full":"830 W Avenue L Lancaster CA 93534",
    "addr:housenumber":"830",
    "addr:postcode":"93534",
    "addr:street":"W Avenue L",
    "iso:country":"US",
    "sg:address":"830 W Avenue L",
    "sg:city":"Lancaster",
    "sg:phone":"+1 661 974 7995",
    "sg:postcode":"93534",
    "sg:province":"CA",
    "wof:name":"Jackies Cafe",
    "wof:placetype":"venue"
},
  "geometry": {"coordinates":[-118.145923,34.660339],"type":"Point"}
}