{
  "type": "Feature",
  "properties": {
    "addr:full":"2020 Ridgecrest Pl Escondido CA 92029",
    "addr:housenumber":"2020",
    "addr:postcode":"92029",
    "addr:street":"Ridgecrest Pl",
    "iso:country":"US",
    "sg:address":"2020 Ridgecrest Pl",
    "sg:city":"Escondido",
    "sg:classifiers":[
        {
            "category":"Manufacturing",
            "subcategory":"Electronics",
            "type":"Manufacturing & Wholesale Goods"
        }
    ],
    "sg:phone":"+1 760 432 8490",
    "sg:postcode":"92029",
    "sg:province":"CA",
    "sg:tags":[
        "electronic",
        "component",
        "mfg"
    ],
    "wof:name":"C M L Engineering Sales Inc",
    "wof:placetype":"venue"
},
  "geometry": {"coordinates":[-117.107399,33.093587],"type":"Point"}
}