{
  "type": "Feature",
  "properties": {
    "addr:full":"203 Boyd St Los Angeles CA 90013",
    "addr:housenumber":"203",
    "addr:postcode":"90013",
    "addr:street":"Boyd St",
    "iso:country":"US",
    "sg:address":"203 Boyd St",
    "sg:city":"Los Angeles",
    "sg:classifiers":[
        {
            "category":"Wholesale",
            "subcategory":"Toys & Hobbies",
            "type":"Manufacturing & Wholesale Goods"
        }
    ],
    "sg:phone":"+1 213 620 1319",
    "sg:postcode":"90013",
    "sg:province":"CA",
    "sg:tags":[
        "wholesaler"
    ],
    "wof:name":"USA Closeout Intl",
    "wof:placetype":"venue"
},
  "geometry": {"coordinates":[-118.24423,34.047272],"type":"Point"}
}