{
  "type": "Feature",
  "properties": {
    "iso:country":"US",
    "sg:address":"9670 Beachwood Dr",
    "sg:city":"Orangevale",
    "sg:classifiers":[
        {
            "category":"Professional",
            "type":"Services"
        }
    ],
    "sg:phone":"+1 916 987 9670",
    "sg:postcode":"95662",
    "sg:province":"CA",
    "wof:name":"Fiore Fantastico",
    "wof:placetype":"venue"
},
  "geometry": {"coordinates":[-121.194239,38.673499],"type":"Point"}
}