{
  "type": "Feature",
  "properties": {
    "addr:full":"439 N Beverly Dr Beverly Hills CA 90210",
    "addr:housenumber":"439",
    "addr:postcode":"90210",
    "addr:street":"N Beverly Dr",
    "iso:country":"US",
    "sg:address":"439 N Beverly Dr",
    "sg:city":"Beverly Hills",
    "sg:classifiers":[
        {
            "category":"Restaurant",
            "type":"Food & Drink"
        }
    ],
    "sg:phone":"+1 310 273 5578",
    "sg:postcode":"90210",
    "sg:province":"CA",
    "sg:tags":[
        "new",
        "american"
    ],
    "sg:website":"www.thefarmofbeverlyhills.com",
    "wof:name":"The Farm of Beverly Hills",
    "wof:placetype":"venue"
},
  "geometry": {"coordinates":[-118.40300000000001,34.070499],"type":"Point"}
}