{
  "type": "Feature",
  "properties": {
    "addr:full":"1865 Manhattan Beach Blvd Manhattan Beach CA 90266",
    "addr:housenumber":"1865",
    "addr:postcode":"90266",
    "addr:street":"Manhattan Beach Blvd",
    "iso:country":"US",
    "sg:address":"1865 Manhattan Beach Blvd",
    "sg:city":"Manhattan Beach",
    "sg:classifiers":[
        {
            "category":"Professional",
            "type":"Services"
        }
    ],
    "sg:phone":"+1 310 374 0527",
    "sg:postcode":"90266",
    "sg:province":"CA",
    "wof:name":"Ventus Networks",
    "wof:placetype":"venue"
},
  "geometry": {"coordinates":[-118.379789,33.88743],"type":"Point"}
}