{
  "type": "Feature",
  "properties": {
    "addr:full":"3713 Highland Avenue Manhattan Beach CA 90266",
    "addr:housenumber":"3713",
    "addr:postcode":"90266",
    "addr:street":"Highland Avenue",
    "iso:country":"US",
    "sg:address":"3713 Highland Avenue",
    "sg:city":"Manhattan Beach",
    "sg:classifiers":[
        {
            "category":"Personal",
            "subcategory":"Beauty Salon",
            "type":"Services"
        },
        {
            "category":"Personal",
            "subcategory":"Barber",
            "type":"Services"
        }
    ],
    "sg:phone":"+1 310 545 9031",
    "sg:postcode":"90266",
    "sg:province":"CA",
    "sg:tags":[
        "hair"
    ],
    "sg:website":"thenorthendsalon.com/",
    "wof:name":"North End Men & Women's Hairstyling",
    "wof:placetype":"venue"
},
  "geometry": {"coordinates":[-118.417942,33.90131],"type":"Point"}
}