{
  "type": "Feature",
  "properties": {
    "addr:full":"1735 W Katella Ave Orange CA 92867",
    "addr:housenumber":"1735",
    "addr:postcode":"92867",
    "addr:street":"W Katella Ave",
    "iso:country":"US",
    "sg:address":"1735 W Katella Ave",
    "sg:city":"Orange",
    "sg:classifiers":[
        {
            "category":"Shopping",
            "subcategory":"Books",
            "type":"Retail Goods"
        }
    ],
    "sg:phone":"+1 714 997 0135",
    "sg:postcode":"92867",
    "sg:province":"CA",
    "sg:tags":[
        "comic"
    ],
    "sg:website":"www.animebooks.com",
    "wof:name":"ANIMEBOOKS.COM",
    "wof:placetype":"venue"
},
  "geometry": {"coordinates":[-117.869061,33.808057],"type":"Point"}
}