{
  "type": "Feature",
  "properties": {
    "iso:country":"US",
    "sg:address":"155 Manor Dr",
    "sg:city":"Mill Valley",
    "sg:classifiers":[
        {
            "category":"Wholesale",
            "subcategory":"Computers",
            "type":"Manufacturing & Wholesale Goods"
        }
    ],
    "sg:phone":"+1 415 381 0191",
    "sg:postcode":"94941",
    "sg:province":"CA",
    "wof:name":"Macxcel Assoc",
    "wof:placetype":"venue"
},
  "geometry": {"coordinates":[-122.536451,37.907763],"type":"Point"}
}