{
  "type": "Feature",
  "properties": {
    "addr:full":"353 E Angeleno Ave Burbank CA 91501",
    "addr:housenumber":"353",
    "addr:postcode":"91501",
    "addr:street":"E Angeleno Ave",
    "iso:country":"US",
    "sg:address":"353 E Angeleno Ave",
    "sg:city":"Burbank",
    "sg:classifiers":[
        {
            "category":"Social Services",
            "type":"Services"
        }
    ],
    "sg:phone":"+1 818 556 6067",
    "sg:postcode":"91501",
    "sg:province":"CA",
    "sg:tags":[
        "counselor",
        "marriage",
        "family"
    ],
    "wof:name":"Buena Vista Counseling Svc",
    "wof:placetype":"venue"
},
  "geometry": {"coordinates":[-118.305871,34.181876],"type":"Point"}
}