{
  "type": "Feature",
  "properties": {
    "addr:full":"9636 Tierra Grande St San Diego CA 92126",
    "addr:housenumber":"9636",
    "addr:postcode":"92126",
    "addr:street":"Tierra Grande St",
    "iso:country":"US",
    "sg:address":"9636 Tierra Grande St",
    "sg:city":"San Diego",
    "sg:classifiers":[
        {
            "category":"Professional",
            "subcategory":"Management & Consulting",
            "type":"Services"
        }
    ],
    "sg:phone":"+1 858 566 4111",
    "sg:postcode":"92126",
    "sg:province":"CA",
    "sg:tags":[
        "promotion",
        "sales"
    ],
    "sg:website":"www.cssales.com",
    "wof:name":"C & S Sales Inc",
    "wof:placetype":"venue"
},
  "geometry": {"coordinates":[-117.120632,32.895132],"type":"Point"}
}