{
  "type": "Feature",
  "properties": {
    "addr:full":"8851 Garden Grove Blvd Ste 102 Garden Grove CA 92844",
    "addr:housenumber":"8851",
    "addr:postcode":"92844",
    "addr:street":"Garden Grove Blvd Ste 102",
    "iso:country":"US",
    "sg:address":"8851 Garden Grove Blvd Ste 102",
    "sg:city":"Garden Grove",
    "sg:classifiers":[
        {
            "category":"Health Services",
            "subcategory":"Doctor",
            "type":"Services"
        },
        {
            "category":"Arena",
            "subcategory":"Sports Club",
            "type":"Entertainment"
        }
    ],
    "sg:phone":"+1 714 534 4600",
    "sg:postcode":"92844",
    "sg:province":"CA",
    "sg:tags":[
        "martial art"
    ],
    "wof:name":"Five Star Tae Kwon DO",
    "wof:placetype":"venue"
},
  "geometry": {"coordinates":[-117.977997,33.773998],"type":"Point"}
}