{
  "type": "Feature",
  "properties": {
    "iso:country":"US",
    "sg:address":"928 E Olive Ave",
    "sg:city":"Fresno",
    "sg:classifiers":[
        {
            "category":"Arts & Performance",
            "subcategory":"Theater",
            "type":"Entertainment"
        },
        {
            "category":"Restaurant",
            "type":"Food & Drink"
        }
    ],
    "sg:phone":"+1 559 266 0660",
    "sg:postcode":"93728",
    "sg:province":"CA",
    "wof:name":"Second Space Theatre",
    "wof:placetype":"venue"
},
  "geometry": {"coordinates":[-119.798848,36.75767],"type":"Point"}
}