{
  "type": "Feature",
  "properties": {
    "addr:full":"732 N St Davis CA 95616",
    "addr:housenumber":"732",
    "addr:postcode":"95616",
    "addr:street":"N St",
    "iso:country":"US",
    "sg:address":"732 N St",
    "sg:city":"Davis",
    "sg:classifiers":[
        {
            "category":"Professional",
            "type":"Services"
        }
    ],
    "sg:phone":"+1 530 792 7043",
    "sg:postcode":"95616",
    "sg:province":"CA",
    "wof:name":"Jeffrey Maurer",
    "wof:placetype":"venue"
},
  "geometry": {"coordinates":[-121.730772,38.551643],"type":"Point"}
}