{
  "type": "Feature",
  "properties": {
    "addr:full":"240 France Cir Ojai CA 93023",
    "addr:housenumber":"240",
    "addr:postcode":"93023",
    "addr:street":"France Cir",
    "iso:country":"US",
    "sg:address":"240 France Cir",
    "sg:city":"Ojai",
    "sg:classifiers":[
        {
            "category":"Farming",
            "subcategory":"Vineyard",
            "type":"Manufacturing & Wholesale Goods"
        }
    ],
    "sg:phone":"+1 805 640 6833",
    "sg:postcode":"93023",
    "sg:province":"CA",
    "sg:tags":[
        "grape"
    ],
    "wof:name":"Chief Peak Vineyards",
    "wof:placetype":"venue"
},
  "geometry": {"coordinates":[-119.245508,34.455868],"type":"Point"}
}