{
  "type": "Feature",
  "properties": {
    "iso:country":"US",
    "sg:address":"811 Commercial St",
    "sg:city":"San Jose",
    "sg:classifiers":[
        {
            "category":"Building & Trades",
            "subcategory":"Equipment Rental",
            "type":"Services"
        }
    ],
    "sg:phone":"+1 408 441 1353",
    "sg:postcode":"95112",
    "sg:province":"CA",
    "sg:tags":[
        "scaffolding"
    ],
    "wof:name":"Brand Scaffold Svc",
    "wof:placetype":"venue"
},
  "geometry": {"coordinates":[-121.88843300000001,37.366755],"type":"Point"}
}