{
  "type": "Feature",
  "properties": {
    "iso:country":"US",
    "sg:address":"13005 Columbet Ave",
    "sg:city":"San Martin",
    "sg:classifiers":[
        {
            "category":"Building & Trades",
            "subcategory":"Construction",
            "type":"Services"
        }
    ],
    "sg:phone":"+1 408 683 2498",
    "sg:postcode":"95046",
    "sg:province":"CA",
    "sg:tags":[
        "concrete",
        "contractor"
    ],
    "wof:name":"Roman Concrete Inc",
    "wof:placetype":"venue"
},
  "geometry": {"coordinates":[-121.590021,37.087687],"type":"Point"}
}