{
  "type": "Feature",
  "properties": {
    "iso:country":"US",
    "sg:address":"2199 Addison St",
    "sg:city":"Berkeley",
    "sg:classifiers":[
        {
            "category":"Education",
            "subcategory":"College",
            "type":"Public Place"
        }
    ],
    "sg:phone":"+1 510 642 1524",
    "sg:postcode":"94704",
    "sg:province":"CA",
    "wof:name":"Residntial Stdents Svc Program",
    "wof:placetype":"venue"
},
  "geometry": {"coordinates":[-122.267251,37.871313],"type":"Point"}
}