{
  "type": "Feature",
  "properties": {
    "addr:full":"2018 E Jackman St Lancaster CA 93535",
    "addr:housenumber":"2018",
    "addr:postcode":"93535",
    "addr:street":"E Jackman St",
    "iso:country":"US",
    "sg:address":"2018 E Jackman St",
    "sg:city":"Lancaster",
    "sg:classifiers":[
        {
            "category":"Professional",
            "type":"Services"
        }
    ],
    "sg:phone":"+1 661 946 7716",
    "sg:postcode":"93535",
    "sg:province":"CA",
    "wof:name":"John J Moylan",
    "wof:placetype":"venue"
},
  "geometry": {"coordinates":[-118.09370199999999,34.702057],"type":"Point"}
}