{
  "type": "Feature",
  "properties": {
    "addr:full":"125 Vineland Ave City Of Industry CA 91746",
    "addr:housenumber":"125",
    "addr:postcode":"91746",
    "addr:street":"Vineland Ave",
    "iso:country":"US",
    "sg:address":"125 Vineland Ave",
    "sg:city":"City Of Industry",
    "sg:classifiers":[
        {
            "category":"Professional",
            "subcategory":"Advertising",
            "type":"Services"
        }
    ],
    "sg:phone":"+1 626 968 3673",
    "sg:postcode":"91746",
    "sg:province":"CA",
    "sg:tags":[
        "mail"
    ],
    "sg:website":"www.fordprintingnmailing.com",
    "wof:name":"Ford Printing & Mailing Inc",
    "wof:placetype":"venue"
},
  "geometry": {"coordinates":[-117.992628,34.047804],"type":"Point"}
}