{
  "type": "Feature",
  "properties": {
    "addr:full":"333 Main St Red Bluff CA 96080",
    "addr:housenumber":"333",
    "addr:postcode":"96080",
    "addr:street":"Main St",
    "iso:country":"US",
    "sg:address":"333 Main St",
    "sg:city":"Red Bluff",
    "sg:classifiers":[
        {
            "category":"Food & Beverages",
            "subcategory":"Specialty",
            "type":"Retail Goods"
        }
    ],
    "sg:phone":"+1 530 528 2930",
    "sg:postcode":"96080",
    "sg:province":"CA",
    "wof:name":"Herb Chris Shop",
    "wof:placetype":"venue"
},
  "geometry": {"coordinates":[-122.232529,40.174543],"type":"Point"}
}