{
  "type": "Feature",
  "properties": {
    "addr:full":"5225 Hazel Ave Fair Oaks CA 95628",
    "addr:housenumber":"5225",
    "addr:postcode":"95628",
    "addr:street":"Hazel Ave",
    "iso:country":"US",
    "sg:address":"5225 Hazel Ave",
    "sg:city":"Fair Oaks",
    "sg:classifiers":[
        {
            "category":"Wholesale",
            "subcategory":"Sporting Goods",
            "type":"Manufacturing & Wholesale Goods"
        }
    ],
    "sg:phone":"+1 916 966 6790",
    "sg:postcode":"95628",
    "sg:province":"CA",
    "sg:tags":[
        "equipment",
        "pool",
        "swimming"
    ],
    "wof:name":"Leslie's Swimming Pool Supply",
    "wof:placetype":"venue"
},
  "geometry": {"coordinates":[-121.225775,38.662162],"type":"Point"}
}