{
  "type": "Feature",
  "properties": {
    "addr:full":"1215 Portland Ave Los Altos CA 94024",
    "addr:housenumber":"1215",
    "addr:postcode":"94024",
    "addr:street":"Portland Ave",
    "iso:country":"US",
    "sg:address":"1215 Portland Ave",
    "sg:city":"Los Altos",
    "sg:classifiers":[
        {
            "category":"Professional",
            "subcategory":"Computer Services",
            "type":"Services"
        }
    ],
    "sg:phone":"+1 650 465 3362",
    "sg:postcode":"94024",
    "sg:province":"CA",
    "sg:tags":[
        "repair"
    ],
    "sg:website":"www.computer-smith.biz",
    "wof:name":"Computer Smith",
    "wof:placetype":"venue"
},
  "geometry": {"coordinates":[-122.080406,37.360187],"type":"Point"}
}