{
  "type": "Feature",
  "properties": {
    "addr:full":"22492 Ralston Pl Hayward CA 94541",
    "addr:housenumber":"22492",
    "addr:postcode":"94541",
    "addr:street":"Ralston Pl",
    "iso:country":"US",
    "sg:address":"22492 Ralston Pl",
    "sg:city":"Hayward",
    "sg:classifiers":[
        {
            "category":"Building & Trades",
            "subcategory":"Landscaping Services",
            "type":"Services"
        }
    ],
    "sg:phone":"+1 510 538 7620",
    "sg:postcode":"94541",
    "sg:province":"CA",
    "wof:name":"Blue Sky Tree Service",
    "wof:placetype":"venue"
},
  "geometry": {"coordinates":[-122.056684,37.689292],"type":"Point"}
}