{
  "type": "Feature",
  "properties": {
    "iso:country":"US",
    "sg:address":"920 Rio Dell Ave",
    "sg:city":"Rio Dell",
    "sg:classifiers":[
        {
            "category":"Manufacturing",
            "subcategory":"Tools & Machinery",
            "type":"Manufacturing & Wholesale Goods"
        }
    ],
    "sg:phone":"+1 707 764 5602",
    "sg:postcode":"95562",
    "sg:province":"CA",
    "sg:tags":[
        "surgical",
        "dental",
        "mfg"
    ],
    "wof:name":"Pacific Implant Inc",
    "wof:placetype":"venue"
},
  "geometry": {"coordinates":[-124.108194,40.503063],"type":"Point"}
}