{
  "type": "Feature",
  "properties": {
    "iso:country":"US",
    "sg:address":"313 E Caldwell Ave",
    "sg:city":"Visalia",
    "sg:classifiers":[
        {
            "category":"Professional",
            "subcategory":"Accounting & Tax Preparation",
            "type":"Services"
        }
    ],
    "sg:phone":"+1 559 627 2725",
    "sg:postcode":"93277",
    "sg:province":"CA",
    "sg:tags":[
        "public",
        "accountants-certified"
    ],
    "sg:website":"http://www.ghtcpa.com",
    "wof:name":"Gilman, Harris, & Travioli Inc",
    "wof:placetype":"venue"
},
  "geometry": {"coordinates":[-119.28999,36.298147],"type":"Point"}
}