{
  "type": "Feature",
  "properties": {
    "iso:country":"US",
    "sg:address":"2222 Grand Canal Blvd",
    "sg:city":"Stockton",
    "sg:classifiers":[
        {
            "category":"Shopping",
            "subcategory":"Computers & Home Electronics",
            "type":"Retail Goods"
        }
    ],
    "sg:phone":"+1 209 472 2999",
    "sg:postcode":"95207",
    "sg:province":"CA",
    "sg:tags":[
        "r"
    ],
    "sg:website":"www.computernetusa.net",
    "wof:name":"Computer Net",
    "wof:placetype":"venue"
},
  "geometry": {"coordinates":[-121.333371,37.984428],"type":"Point"}
}