{
  "type": "Feature",
  "properties": {
    "addr:full":"16 Lyndon Avenue Suite 100 Los Gatos CA 95030",
    "addr:housenumber":"16",
    "addr:postcode":"95030",
    "addr:street":"Lyndon Avenue Suite 100",
    "iso:country":"US",
    "sg:address":"16 Lyndon Avenue Suite 100",
    "sg:city":"Los Gatos",
    "sg:classifiers":[
        {
            "category":"Professional",
            "subcategory":"Accounting & Tax Preparation",
            "type":"Services"
        }
    ],
    "sg:phone":"+1 408 395 4545",
    "sg:postcode":"95030",
    "sg:province":"CA",
    "sg:tags":[
        "accountant"
    ],
    "wof:name":"Tax Networks",
    "wof:placetype":"venue"
},
  "geometry": {"coordinates":[-121.98520600000001,37.223279],"type":"Point"}
}