{
  "type": "Feature",
  "properties": {
    "addr:full":"1015 W Collins Ave Orange CA 92867",
    "addr:housenumber":"1015",
    "addr:postcode":"92867",
    "addr:street":"W Collins Ave",
    "iso:country":"US",
    "sg:address":"1015 W Collins Ave",
    "sg:city":"Orange",
    "sg:classifiers":[
        {
            "category":"Autos & Motor Vehicles",
            "subcategory":"Auto Supplies",
            "type":"Retail Goods"
        }
    ],
    "sg:phone":"+1 714 997 1362",
    "sg:postcode":"92867",
    "sg:province":"CA",
    "sg:tags":[
        "equipment",
        "racing",
        "car",
        "automobile"
    ],
    "wof:name":"Fast Eddie's Race Cars",
    "wof:placetype":"venue"
},
  "geometry": {"coordinates":[-117.862921,33.802477],"type":"Point"}
}