{
  "type": "Feature",
  "properties": {
    "iso:country":"US",
    "sg:address":"3413 Delmar Dr",
    "sg:city":"Beale Afb",
    "sg:classifiers":[
        {
            "category":"Professional",
            "type":"Services"
        }
    ],
    "sg:phone":"+1 530 788 9198",
    "sg:postcode":"95903",
    "sg:province":"CA",
    "wof:name":"Heidi Lee Kulp",
    "wof:placetype":"venue"
},
  "geometry": {"coordinates":[-121.338528,39.104176],"type":"Point"}
}