{
  "type": "Feature",
  "properties": {
    "iso:country":"US",
    "sg:address":"3199 E Foothill Blvd",
    "sg:city":"Pasadena",
    "sg:phone":"+1 626 356 9304",
    "sg:postcode":"91107",
    "sg:province":"CA",
    "sg:website":"http://www.blvdbar.com",
    "wof:name":"Boulevard",
    "wof:placetype":"venue"
},
  "geometry": {"coordinates":[-118.084332,34.150053],"type":"Point"}
}