{
  "type": "Feature",
  "properties": {
    "iso:country":"US",
    "sg:address":"628 20th St",
    "sg:city":"San Francisco",
    "sg:classifiers":[
        {
            "category":"Bars & Pubs",
            "type":"Food & Drink"
        }
    ],
    "sg:phone":"+1 415 552 3603",
    "sg:postcode":"94107",
    "sg:province":"CA",
    "sg:tags":[
        "lounge",
        "cocktail"
    ],
    "wof:name":"Sublounge",
    "wof:placetype":"venue"
},
  "geometry": {"coordinates":[-122.388339,37.760582],"type":"Point"}
}