{
  "type": "Feature",
  "properties": {
    "addr:full":"Golden Gate Ave and Laguna St San Francisco CA 94115",
    "addr:postcode":"94115",
    "addr:street":"Golden Gate Ave And Laguna St",
    "iso:country":"US",
    "sg:address":"Golden Gate Ave and Laguna St",
    "sg:city":"San Francisco",
    "sg:classifiers":[
        {
            "category":"Sports & Exercise",
            "subcategory":"Tennis Court",
            "type":"Entertainment"
        }
    ],
    "sg:postcode":"94115",
    "sg:province":"CA",
    "sg:website":"www.sfgov.org/site/uploadedfiles...",
    "wof:name":"Margaret Hayward Tennis Courts",
    "wof:placetype":"venue"
},
  "geometry": {"coordinates":[-122.427024,37.780187],"type":"Point"}
}