{
  "type": "Feature",
  "properties": {
    "addr:full":"3666 S Bagley Ave Fresno CA 93725",
    "addr:housenumber":"3666",
    "addr:postcode":"93725",
    "addr:street":"S Bagley Ave",
    "iso:country":"US",
    "sg:address":"3666 S Bagley Ave",
    "sg:city":"Fresno",
    "sg:classifiers":[
        {
            "category":"Autos & Motor Vehicles",
            "subcategory":"Auto Supplies",
            "type":"Retail Goods"
        }
    ],
    "sg:phone":"+1 559 233 2946",
    "sg:postcode":"93725",
    "sg:province":"CA",
    "sg:tags":[
        "tire"
    ],
    "wof:name":"Delray Tire & Retreading",
    "wof:placetype":"venue"
},
  "geometry": {"coordinates":[-119.741286,36.679954],"type":"Point"}
}