{
  "type": "Feature",
  "properties": {
    "addr:full":"2439 Hilltop Mall Rd San Pablo CA 94806",
    "addr:housenumber":"2439",
    "addr:postcode":"94806",
    "addr:street":"Hilltop Mall Rd",
    "iso:country":"US",
    "sg:address":"2439 Hilltop Mall Rd",
    "sg:city":"San Pablo",
    "sg:classifiers":[
        {
            "category":"Restaurant",
            "type":"Food & Drink"
        }
    ],
    "sg:menulink":"http://www.allmenus.com/ca/west-contra-costa/238319-the-great-steak--potato-co/menu/",
    "sg:phone":"+1 510 262 0606",
    "sg:postcode":"94806",
    "sg:province":"CA",
    "sg:tags":[
        "cheesesteaks",
        "american"
    ],
    "wof:name":"The Great Steak & Potato Co.",
    "wof:placetype":"venue"
},
  "geometry": {"coordinates":[-122.328035,37.983242],"type":"Point"}
}