{
  "type": "Feature",
  "properties": {
    "addr:full":"1675 N Gem St Tulare CA 93274",
    "addr:housenumber":"1675",
    "addr:postcode":"93274",
    "addr:street":"N Gem St",
    "iso:country":"US",
    "sg:address":"1675 N Gem St",
    "sg:city":"Tulare",
    "sg:classifiers":[
        {
            "category":"Sports & Exercise",
            "subcategory":"Gym",
            "type":"Entertainment"
        }
    ],
    "sg:phone":"+1 559 685 9030",
    "sg:postcode":"93274",
    "sg:province":"CA",
    "sg:tags":[
        "club",
        "health",
        "studio",
        "gymnasium"
    ],
    "wof:name":"Tulare Fun & Fitness Ctr",
    "wof:placetype":"venue"
},
  "geometry": {"coordinates":[-119.33993599999999,36.229155],"type":"Point"}
}