{
  "type": "Feature",
  "properties": {
    "addr:full":"1754 Martina Ave Torrance CA 90501",
    "addr:postcode":"1754;90501",
    "addr:street":"Martina Ave",
    "iso:country":"US",
    "sg:address":"1754 Martina Ave",
    "sg:city":"Torrance",
    "sg:classifiers":[
        {
            "category":"Shopping",
            "subcategory":"Books",
            "type":"Retail Goods"
        }
    ],
    "sg:phone":"+1 323 960 1000",
    "sg:postcode":"90501",
    "sg:province":"CA",
    "sg:tags":[
        "comic"
    ],
    "wof:name":"Global Pop Culture",
    "wof:placetype":"venue"
},
  "geometry": {"coordinates":[-118.318726,33.830542],"type":"Point"}
}