{
  "type": "Feature",
  "properties": {
    "addr:full":"2030 Addison St Berkeley CA 94704",
    "addr:housenumber":"2030",
    "addr:postcode":"94704",
    "addr:street":"Addison St",
    "iso:country":"US",
    "sg:address":"2030 Addison St",
    "sg:city":"Berkeley",
    "sg:classifiers":[
        {
            "category":"Manufacturing",
            "subcategory":"Printing",
            "type":"Manufacturing & Wholesale Goods"
        }
    ],
    "sg:phone":"+1 510 540 7612",
    "sg:postcode":"94704",
    "sg:province":"CA",
    "sg:tags":[
        "publisher",
        "software"
    ],
    "wof:name":"Berkeley Transportation System",
    "wof:placetype":"venue"
},
  "geometry": {"coordinates":[-122.26902,37.871004],"type":"Point"}
}