{
  "type": "Feature",
  "properties": {
    "iso:country":"US",
    "sg:address":"19629 Deerhorn Valley Rd",
    "sg:city":"Jamul",
    "sg:classifiers":[
        {
            "category":"Building & Trades",
            "subcategory":"Construction",
            "type":"Services"
        }
    ],
    "sg:phone":"+1 619 468 3379",
    "sg:postcode":"91935",
    "sg:province":"CA",
    "sg:tags":[
        "road",
        "contractor"
    ],
    "wof:name":"F & D Bennett Contracting Inc",
    "wof:placetype":"venue"
},
  "geometry": {"coordinates":[-116.72381300000001,32.676252],"type":"Point"}
}