{
  "type": "Feature",
  "properties": {
    "iso:country":"US",
    "sg:address":"304 N 6th St",
    "sg:city":"San Jose",
    "sg:classifiers":[
        {
            "category":"Organizations",
            "subcategory":"Non-profit Organization",
            "type":"Services"
        }
    ],
    "sg:phone":"+1 408 297 7638",
    "sg:postcode":"95112",
    "sg:province":"CA",
    "sg:tags":[
        "service/non-profit",
        "community"
    ],
    "wof:name":"Ethiopian Community Services",
    "wof:placetype":"venue"
},
  "geometry": {"coordinates":[-121.889,37.343399],"type":"Point"}
}