{
  "type": "Feature",
  "properties": {
    "iso:country":"US",
    "sg:address":"3166 E Palmdale Blvd",
    "sg:city":"Palmdale",
    "sg:classifiers":[
        {
            "category":"Insurance",
            "subcategory":"Insurance Agent",
            "type":"Services"
        }
    ],
    "sg:phone":"+1 661 266 2022",
    "sg:postcode":"93550",
    "sg:province":"CA",
    "wof:name":"Top Notch Insurance Svc",
    "wof:placetype":"venue"
},
  "geometry": {"coordinates":[-118.072149,34.580207],"type":"Point"}
}