{
  "type": "Feature",
  "properties": {
    "addr:full":"3 Plateau Ct Hercules CA 94547",
    "addr:housenumber":"3",
    "addr:postcode":"94547",
    "addr:street":"Plateau Ct",
    "iso:country":"US",
    "sg:address":"3 Plateau Ct",
    "sg:city":"Hercules",
    "sg:classifiers":[
        {
            "category":"Wholesale",
            "subcategory":"Drugs",
            "type":"Manufacturing & Wholesale Goods"
        }
    ],
    "sg:phone":"+1 510 367 2898",
    "sg:postcode":"94547",
    "sg:province":"CA",
    "sg:tags":[
        "aids",
        "beauty"
    ],
    "wof:name":"Icheveuxcom",
    "wof:placetype":"venue"
},
  "geometry": {"coordinates":[-122.263171,38.007956],"type":"Point"}
}