{
  "type": "Feature",
  "properties": {
    "iso:country":"US",
    "sg:address":"800 Alhambra Ave",
    "sg:city":"Martinez",
    "sg:phone":"+1 925 372 8536",
    "sg:postcode":"94553",
    "sg:province":"CA",
    "wof:name":"DDM Cylinder Head & Engine Machining",
    "wof:placetype":"venue"
},
  "geometry": {"coordinates":[-122.137619,38.01581],"type":"Point"}
}