{
  "type": "Feature",
  "properties": {
    "addr:full":"1365 Ahart St Simi Valley CA 93065",
    "addr:housenumber":"1365",
    "addr:postcode":"93065",
    "addr:street":"Ahart St",
    "iso:country":"US",
    "sg:address":"1365 Ahart St",
    "sg:city":"Simi Valley",
    "sg:classifiers":[
        {
            "category":"Professional",
            "subcategory":"Management & Consulting",
            "type":"Services"
        }
    ],
    "sg:phone":"+1 805 527 8676",
    "sg:postcode":"93065",
    "sg:province":"CA",
    "sg:tags":[
        "construction"
    ],
    "wof:name":"Top Notch Construction",
    "wof:placetype":"venue"
},
  "geometry": {"coordinates":[-118.775414,34.27762],"type":"Point"}
}