{
  "type": "Feature",
  "properties": {
    "addr:full":"John Wayne Airport SNA Food Court Santa Ana CA 92707",
    "addr:postcode":"92707",
    "iso:country":"US",
    "sg:address":"John Wayne Airport SNA Food Court",
    "sg:city":"Santa Ana",
    "sg:classifiers":[
        {
            "category":"Coffee & Tea",
            "type":"Food & Drink"
        }
    ],
    "sg:phone":"+1 949 252 6125",
    "sg:postcode":"92707",
    "sg:province":"CA",
    "sg:website":"www.starbucks.com",
    "wof:name":"Starbucks Coffee",
    "wof:placetype":"venue"
},
  "geometry": {"coordinates":[-117.86749500000001,33.677147],"type":"Point"}
}