{
  "type": "Feature",
  "properties": {
    "iso:country":"US",
    "sg:address":"1107 Front St",
    "sg:city":"Sacramento",
    "sg:classifiers":[
        {
            "category":"Shopping",
            "subcategory":"Antiques",
            "type":"Retail Goods"
        }
    ],
    "sg:phone":"+1 916 448 3338",
    "sg:postcode":"95814",
    "sg:province":"CA",
    "wof:name":"Good the Bad and the Ugly Antiques & Collectibles",
    "wof:placetype":"venue"
},
  "geometry": {"coordinates":[-121.50599699999999,38.582001],"type":"Point"}
}