{
  "type": "Feature",
  "properties": {
    "iso:country":"US",
    "sg:address":"1613 N Orangethorpe Way",
    "sg:city":"Anaheim",
    "sg:classifiers":[
        {
            "category":"Wholesale",
            "subcategory":"Machinery & Supplies",
            "type":"Manufacturing & Wholesale Goods"
        }
    ],
    "sg:phone":"+1 714 871 0430",
    "sg:postcode":"92801",
    "sg:province":"CA",
    "sg:tags":[
        "repairing"
    ],
    "wof:name":"Austol Inc",
    "wof:placetype":"venue"
},
  "geometry": {"coordinates":[-117.916338,33.858101],"type":"Point"}
}