{
  "type": "Feature",
  "properties": {
    "addr:full":"912 11th Ave Delano CA 93215",
    "addr:housenumber":"912",
    "addr:postcode":"93215",
    "addr:street":"11Th Ave",
    "iso:country":"US",
    "sg:address":"912 11th Ave",
    "sg:city":"Delano",
    "sg:classifiers":[
        {
            "category":"Personal",
            "subcategory":"Beauty Salon",
            "type":"Services"
        }
    ],
    "sg:phone":"+1 661 725 8515",
    "sg:postcode":"93215",
    "sg:province":"CA",
    "wof:name":"Studio Dibelleza",
    "wof:placetype":"venue"
},
  "geometry": {"coordinates":[-119.245786,35.770385],"type":"Point"}
}