{
  "type": "Feature",
  "properties": {
    "iso:country":"US",
    "sg:address":"5070 E Clinton Way",
    "sg:city":"Fresno",
    "sg:classifiers":[
        {
            "category":"Professional",
            "type":"Services"
        }
    ],
    "sg:phone":"+1 559 454 0554",
    "sg:postcode":"93727",
    "sg:province":"CA",
    "sg:tags":[
        "establishment"
    ],
    "wof:name":"Austin Family LTD Prtnrshp",
    "wof:placetype":"venue"
},
  "geometry": {"coordinates":[-119.725566,36.772136],"type":"Point"}
}