{
  "type": "Feature",
  "properties": {
    "addr:full":"2646 Appian Way Pinole CA 94564",
    "addr:housenumber":"2646",
    "addr:postcode":"94564",
    "addr:street":"Appian Way",
    "iso:country":"US",
    "sg:address":"2646 Appian Way",
    "sg:city":"Pinole",
    "sg:classifiers":[
        {
            "category":"Building & Trades",
            "subcategory":"Construction",
            "type":"Services"
        },
        {
            "category":"Home & Garden",
            "subcategory":"Hardware",
            "type":"Retail Goods"
        },
        {
            "category":"Building & Trades",
            "subcategory":"Plumbing",
            "type":"Services"
        },
        {
            "category":"Home & Garden",
            "subcategory":"Building Materials",
            "type":"Retail Goods"
        },
        {
            "category":"Building & Trades",
            "subcategory":"Cleaning & Sanitation",
            "type":"Services"
        },
        {
            "category":"Utilities",
            "subcategory":"Sewage",
            "type":"Services"
        }
    ],
    "sg:phone":"+1 510 222 7608",
    "sg:postcode":"94564",
    "sg:province":"CA",
    "sg:tags":[
        "repair",
        "plumber",
        "heater",
        "repairer",
        "contractor",
        "water",
        "piping",
        "maintenance",
        "plumbing-drain",
        "cleaner",
        "sewer"
    ],
    "sg:website":"http://www.superiorplumbinganddrain.com",
    "wof:name":"Superior Plumbing and Drain Cleaning Services",
    "wof:placetype":"venue"
},
  "geometry": {"coordinates":[-122.29891600000001,37.987879],"type":"Point"}
}