{
  "type": "Feature",
  "properties": {
    "iso:country":"US",
    "sg:address":"736 Cary Dr",
    "sg:city":"San Leandro",
    "sg:classifiers":[
        {
            "category":"Banks & Credit Unions",
            "subcategory":"Bank",
            "type":"Services"
        }
    ],
    "sg:phone":"+1 510 357 1390",
    "sg:postcode":"94577",
    "sg:province":"CA",
    "sg:tags":[
        "loan",
        "broker"
    ],
    "wof:name":"Windsor Capital Mortgage",
    "wof:placetype":"venue"
},
  "geometry": {"coordinates":[-122.143815,37.730859],"type":"Point"}
}