{
  "type": "Feature",
  "properties": {
    "addr:full":"84 S Fair Oaks Ave Pasadena CA 91105",
    "addr:housenumber":"84",
    "addr:postcode":"91105",
    "addr:street":"S Fair Oaks Ave",
    "iso:country":"US",
    "sg:address":"84 S Fair Oaks Ave",
    "sg:city":"Pasadena",
    "sg:classifiers":[
        {
            "category":"Coffee & Tea",
            "type":"Food & Drink"
        },
        {
            "category":"Food & Beverages",
            "subcategory":"Bakery",
            "type":"Retail Goods"
        }
    ],
    "sg:phone":"+1 626 578 7779",
    "sg:postcode":"91105",
    "sg:province":"CA",
    "sg:tags":[
        "sandwich"
    ],
    "wof:name":"Cafe Alibi",
    "wof:placetype":"venue"
},
  "geometry": {"coordinates":[-118.150445,34.143989],"type":"Point"}
}