{
  "type": "Feature",
  "properties": {
    "addr:full":"190 San Marin Dr Novato CA 94945",
    "addr:housenumber":"190",
    "addr:postcode":"94945",
    "addr:street":"San Marin Dr",
    "iso:country":"US",
    "sg:address":"190 San Marin Dr",
    "sg:city":"Novato",
    "sg:classifiers":[
        {
            "category":"Health Services",
            "subcategory":"Doctor",
            "type":"Services"
        }
    ],
    "sg:phone":"+1 415 897 6877",
    "sg:postcode":"94945",
    "sg:province":"CA",
    "sg:tags":[
        "dentist"
    ],
    "wof:name":"Perry & Perry Dental",
    "wof:placetype":"venue"
},
  "geometry": {"coordinates":[-122.602114,38.121907],"type":"Point"}
}