{
  "type": "Feature",
  "properties": {
    "iso:country":"US",
    "sg:address":"3230 Harrison Ave",
    "sg:city":"Eureka",
    "sg:classifiers":[
        {
            "category":"Organizations",
            "subcategory":"Religious Organization",
            "type":"Services"
        }
    ],
    "sg:phone":"+1 707 445 0671",
    "sg:postcode":"95503",
    "sg:province":"CA",
    "sg:tags":[
        "church"
    ],
    "wof:name":"Immanuel Lutheran Church",
    "wof:placetype":"venue"
},
  "geometry": {"coordinates":[-124.139644,40.779254],"type":"Point"}
}