{
  "type": "Feature",
  "properties": {
    "iso:country":"US",
    "sg:address":"13812 Newport Ave Ste 101",
    "sg:city":"Tustin",
    "sg:classifiers":[
        {
            "category":"Health Services",
            "subcategory":"Dentist",
            "type":"Services"
        }
    ],
    "sg:phone":"+1 714 838 8881",
    "sg:postcode":"92780",
    "sg:province":"CA",
    "wof:name":"Elido Marilou DMD",
    "wof:placetype":"venue"
},
  "geometry": {"coordinates":[-117.81999999999999,33.740299],"type":"Point"}
}