{
  "type": "Feature",
  "properties": {
    "addr:full":"5555 Oberlin Dr San Diego CA 92121",
    "addr:housenumber":"5555",
    "addr:postcode":"92121",
    "addr:street":"Oberlin Dr",
    "iso:country":"US",
    "sg:address":"5555 Oberlin Dr",
    "sg:city":"San Diego",
    "sg:classifiers":[
        {
            "category":"Manufacturing",
            "subcategory":"Tools & Machinery",
            "type":"Manufacturing & Wholesale Goods"
        }
    ],
    "sg:phone":"+1 858 200 0200",
    "sg:postcode":"92121",
    "sg:province":"CA",
    "sg:tags":[
        "equipment",
        "hospital",
        "supply"
    ],
    "wof:name":"Dex Com Inc",
    "wof:placetype":"venue"
},
  "geometry": {"coordinates":[-117.19835,32.891553],"type":"Point"}
}