{
  "type": "Feature",
  "properties": {
    "addr:full":"280 S Beverly Dr Beverly Hills CA 90212",
    "addr:housenumber":"280",
    "addr:postcode":"90212",
    "addr:street":"S Beverly Dr",
    "iso:country":"US",
    "sg:address":"280 S Beverly Dr",
    "sg:city":"Beverly Hills",
    "sg:classifiers":[
        {
            "category":"Professional",
            "subcategory":"Accounting & Tax Preparation",
            "type":"Services"
        }
    ],
    "sg:phone":"+1 310 858 7777",
    "sg:postcode":"90212",
    "sg:province":"CA",
    "sg:tags":[
        "accountant"
    ],
    "wof:name":"Starr & Co",
    "wof:placetype":"venue"
},
  "geometry": {"coordinates":[-118.39899200000001,34.064471],"type":"Point"}
}