{
  "type": "Feature",
  "properties": {
    "addr:full":"2767 Olive Hwy Oroville CA 95966",
    "addr:housenumber":"2767",
    "addr:postcode":"95966",
    "addr:street":"Olive Hwy",
    "iso:country":"US",
    "sg:address":"2767 Olive Hwy",
    "sg:city":"Oroville",
    "sg:classifiers":[
        {
            "category":"Health Services",
            "subcategory":"Hospital",
            "type":"Services"
        }
    ],
    "sg:phone":"+1 530 532 8512",
    "sg:postcode":"95966",
    "sg:province":"CA",
    "wof:name":"Extended Care Unit",
    "wof:placetype":"venue"
},
  "geometry": {"coordinates":[-121.542081,39.504546],"type":"Point"}
}