{
  "type": "Feature",
  "properties": {
    "iso:country":"US",
    "sg:address":"541 Jefferson St",
    "sg:city":"Red Bluff",
    "sg:classifiers":[
        {
            "category":"Local Transit",
            "type":"Transportation"
        }
    ],
    "sg:phone":"+1 530 527 4760",
    "sg:postcode":"96080",
    "sg:province":"CA",
    "sg:tags":[
        "ambulance"
    ],
    "wof:name":"Emergency Svc Foundation",
    "wof:placetype":"venue"
},
  "geometry": {"coordinates":[-122.235981,40.175201],"type":"Point"}
}