{
  "type": "Feature",
  "properties": {
    "addr:full":"125 Larkspur St San Rafael CA 94901",
    "addr:housenumber":"125",
    "addr:postcode":"94901",
    "addr:street":"Larkspur St",
    "iso:country":"US",
    "sg:address":"125 Larkspur St",
    "sg:city":"San Rafael",
    "sg:classifiers":[
        {
            "category":"Professional",
            "subcategory":"Management & Consulting",
            "type":"Services"
        }
    ],
    "sg:phone":"+1 415 381 6328",
    "sg:postcode":"94901",
    "sg:province":"CA",
    "sg:tags":[
        "consultant",
        "energy",
        "conservation"
    ],
    "wof:name":"Lifestyle Resources",
    "wof:placetype":"venue"
},
  "geometry": {"coordinates":[-122.50705000000001,37.965217],"type":"Point"}
}