{
  "type": "Feature",
  "properties": {
    "addr:full":"25091 5th St San Bernardino CA 92410",
    "addr:housenumber":"25091",
    "addr:postcode":"92410",
    "addr:street":"5Th St",
    "iso:country":"US",
    "sg:address":"25091 5th St",
    "sg:city":"San Bernardino",
    "sg:classifiers":[
        {
            "category":"Building & Trades",
            "subcategory":"Plumbing",
            "type":"Services"
        }
    ],
    "sg:phone":"+1 909 888 5911",
    "sg:postcode":"92410",
    "sg:province":"CA",
    "sg:tags":[
        "tank",
        "septic"
    ],
    "sg:website":"www.goddardsnazcoseptic.com",
    "wof:name":"Goddard's-Nazco Svc",
    "wof:placetype":"venue"
},
  "geometry": {"coordinates":[-117.253911,34.108422],"type":"Point"}
}