{
  "type": "Feature",
  "properties": {
    "iso:country":"US",
    "sg:address":"5115 Commercial Way",
    "sg:city":"Arnold",
    "sg:classifiers":[
        {
            "category":"Building & Trades",
            "subcategory":"Construction",
            "type":"Services"
        }
    ],
    "sg:phone":"+1 209 795 0302",
    "sg:postcode":"95224",
    "sg:province":"CA",
    "sg:tags":[
        "paving",
        "contractor"
    ],
    "wof:name":"Donniker Construction Inc",
    "wof:placetype":"venue"
},
  "geometry": {"coordinates":[-120.365532,38.195865],"type":"Point"}
}