{
  "type": "Feature",
  "properties": {
    "addr:full":"1310 N 10th St San Jose CA 95112",
    "addr:housenumber":"1310",
    "addr:postcode":"95112",
    "addr:street":"N 10Th St",
    "iso:country":"US",
    "sg:address":"1310 N 10th St",
    "sg:city":"San Jose",
    "sg:classifiers":[
        {
            "category":"Retail",
            "subcategory":"Auto Repair",
            "type":"Services"
        }
    ],
    "sg:phone":"+1 408 288 8398",
    "sg:postcode":"95112",
    "sg:province":"CA",
    "sg:tags":[
        "body",
        "automobile",
        "painting"
    ],
    "wof:name":"Peter Auto Body",
    "wof:placetype":"venue"
},
  "geometry": {"coordinates":[-121.899809,37.365944],"type":"Point"}
}