{
  "type": "Feature",
  "properties": {
    "iso:country":"US",
    "sg:address":"1125 S Vega St",
    "sg:city":"Alhambra",
    "sg:classifiers":[
        {
            "category":"Professional",
            "type":"Services"
        }
    ],
    "sg:phone":"+1 626 293 8521",
    "sg:postcode":"91801",
    "sg:province":"CA",
    "wof:name":"Max Click Inc",
    "wof:placetype":"venue"
},
  "geometry": {"coordinates":[-118.111383,34.08323],"type":"Point"}
}