{
  "type": "Feature",
  "properties": {
    "iso:country":"US",
    "sg:address":"27068 La Paz road, suite 160",
    "sg:city":"Aliso Viejo",
    "sg:classifiers":[
        {
            "category":"Professional",
            "subcategory":"Business Services",
            "type":"Services"
        }
    ],
    "sg:phone":"+1 949 394 5710",
    "sg:postcode":"92656",
    "sg:province":"CA",
    "sg:tags":[
        "voice",
        "data--internet-offerings---"
    ],
    "sg:website":"http://www.CommAdvisors.com",
    "wof:name":"CommAdvisors",
    "wof:placetype":"venue"
},
  "geometry": {"coordinates":[-117.81441700000001,33.679255],"type":"Point"}
}