{
  "type": "Feature",
  "properties": {
    "addr:full":"442 Haight St San Francisco CA 94117",
    "addr:housenumber":"442",
    "addr:postcode":"94117",
    "addr:street":"Haight St",
    "iso:country":"US",
    "sg:address":"442 Haight St",
    "sg:city":"San Francisco",
    "sg:classifiers":[
        {
            "category":"Professional",
            "type":"Services"
        }
    ],
    "sg:phone":"+1 415 864 1300",
    "sg:postcode":"94117",
    "sg:province":"CA",
    "sg:tags":[
        "establishment"
    ],
    "wof:name":"AHHS",
    "wof:placetype":"venue"
},
  "geometry": {"coordinates":[-122.429892,37.772271],"type":"Point"}
}