{
  "type": "Feature",
  "properties": {
    "addr:full":"679 Hickey Blvd Pacifica CA 94044",
    "addr:housenumber":"679",
    "addr:postcode":"94044",
    "addr:street":"Hickey Blvd",
    "iso:country":"US",
    "sg:address":"679 Hickey Blvd",
    "sg:city":"Pacifica",
    "sg:classifiers":[
        {
            "category":"Wholesale",
            "subcategory":"Machinery & Supplies",
            "type":"Manufacturing & Wholesale Goods"
        }
    ],
    "sg:phone":"+1 650 359 1959",
    "sg:postcode":"94044",
    "sg:province":"CA",
    "sg:tags":[
        "industrial"
    ],
    "wof:name":"G & J Acquisitions",
    "wof:placetype":"venue"
},
  "geometry": {"coordinates":[-122.478379,37.659381],"type":"Point"}
}