{
  "type": "Feature",
  "properties": {
    "addr:full":"11333 Moorpark St Studio City CA 91602",
    "addr:housenumber":"11333",
    "addr:postcode":"91602",
    "addr:street":"Moorpark St",
    "iso:country":"US",
    "sg:address":"11333 Moorpark St",
    "sg:city":"Studio City",
    "sg:classifiers":[
        {
            "category":"Professional",
            "type":"Services"
        }
    ],
    "sg:phone":"+1 818 509 2552",
    "sg:postcode":"91602",
    "sg:province":"CA",
    "sg:tags":[
        "establishment"
    ],
    "sg:website":"www.sporthings.com",
    "wof:name":"Sporthings",
    "wof:placetype":"venue"
},
  "geometry": {"coordinates":[-118.37691100000001,34.150372],"type":"Point"}
}