{
  "type": "Feature",
  "properties": {
    "addr:full":"7705 Atlantic Ave Cudahy CA 90201",
    "addr:housenumber":"7705",
    "addr:postcode":"90201",
    "addr:street":"Atlantic Ave",
    "iso:country":"US",
    "sg:address":"7705 Atlantic Ave",
    "sg:city":"Cudahy",
    "sg:classifiers":[
        {
            "category":"Shopping",
            "type":"Retail Goods"
        },
        {
            "category":"Shopping",
            "subcategory":"Books",
            "type":"Retail Goods"
        }
    ],
    "sg:phone":"+1 323 771 7546",
    "sg:postcode":"90201",
    "sg:province":"CA",
    "sg:tags":[
        "religious",
        "dealer"
    ],
    "wof:name":"Nueva Jerusalem Christian Book",
    "wof:placetype":"venue"
},
  "geometry": {"coordinates":[-118.186819,33.965117],"type":"Point"}
}