{
  "type": "Feature",
  "properties": {
    "iso:country":"US",
    "sg:address":"20001 Brookhurst St",
    "sg:city":"Huntington Beach",
    "sg:classifiers":[
        {
            "category":"Autos & Motor Vehicles",
            "subcategory":"Fuel & Gas Station",
            "type":"Retail Goods"
        }
    ],
    "sg:phone":"+1 714 963 4541",
    "sg:postcode":"92646",
    "sg:province":"CA",
    "wof:name":"Gilbert's Shell Service",
    "wof:placetype":"venue"
},
  "geometry": {"coordinates":[-117.954002,33.672001],"type":"Point"}
}