{
  "type": "Feature",
  "properties": {
    "iso:country":"US",
    "sg:address":"204 E Washington Ave",
    "sg:city":"Santa Ana",
    "sg:classifiers":[
        {
            "category":"Wholesale",
            "subcategory":"Durable Goods & Equipment",
            "type":"Manufacturing & Wholesale Goods"
        }
    ],
    "sg:phone":"+1 714 738 6139",
    "sg:postcode":"92701",
    "sg:province":"CA",
    "wof:name":"Pool Tables Wholesale",
    "wof:placetype":"venue"
},
  "geometry": {"coordinates":[-117.865532,33.75555],"type":"Point"}
}