{
  "type": "Feature",
  "properties": {
    "addr:full":"3229 Lakeshore Ave Oakland CA 94610",
    "addr:housenumber":"3229",
    "addr:postcode":"94610",
    "addr:street":"Lakeshore Ave",
    "iso:country":"US",
    "sg:address":"3229 Lakeshore Ave",
    "sg:city":"Oakland",
    "sg:classifiers":[
        {
            "category":"Sports & Exercise",
            "subcategory":"Gym",
            "type":"Entertainment"
        }
    ],
    "sg:phone":"+1 510 832 9642",
    "sg:postcode":"94610",
    "sg:province":"CA",
    "sg:tags":[
        "instruction",
        "yoga"
    ],
    "wof:name":"Namaste Yoga And Wellness",
    "wof:placetype":"venue"
},
  "geometry": {"coordinates":[-122.24457200000001,37.810585],"type":"Point"}
}