{
  "type": "Feature",
  "properties": {
    "iso:country":"US",
    "sg:address":"256 Kingsbury Grade Rd",
    "sg:city":"Stateline",
    "sg:classifiers":[
        {
            "category":"Professional",
            "subcategory":"Engineering",
            "type":"Services"
        }
    ],
    "sg:phone":"+1 775 588 2440",
    "sg:postcode":"89449",
    "sg:province":"CA",
    "sg:tags":[
        "engineer"
    ],
    "wof:name":"Parsons Corp",
    "wof:placetype":"venue"
},
  "geometry": {"coordinates":[-119.929547,38.968288],"type":"Point"}
}