{
  "type": "Feature",
  "properties": {
    "addr:full":"814 E St Antioch CA 94509",
    "addr:housenumber":"814",
    "addr:postcode":"ca 94509",
    "addr:street":"E St",
    "iso:country":"US",
    "sg:address":"814 E St",
    "sg:city":"Antioch",
    "sg:classifiers":[
        {
            "category":"Organizations",
            "subcategory":"Religious Organization",
            "type":"Services"
        }
    ],
    "sg:phone":"+1 925 755 8184",
    "sg:postcode":"94509",
    "sg:province":"CA",
    "sg:tags":[
        "church"
    ],
    "wof:name":"Ombudsman Services Antioch",
    "wof:placetype":"venue"
},
  "geometry": {"coordinates":[-121.811353,38.01201],"type":"Point"}
}