{
  "type": "Feature",
  "properties": {
    "iso:country":"US",
    "sg:address":"620 Santa Monica Blvd",
    "sg:city":"Santa Monica",
    "sg:classifiers":[
        {
            "category":"Restaurant",
            "type":"Food & Drink"
        }
    ],
    "sg:menulink":"http://www.allmenus.com/ca/santa-monica/20866-la-botte-ristorante/menu/",
    "sg:phone":"+1 310 576 3072",
    "sg:postcode":"90401",
    "sg:province":"CA",
    "sg:tags":[
        "italian"
    ],
    "wof:name":"La Botte Ristorante",
    "wof:placetype":"venue"
},
  "geometry": {"coordinates":[-118.493044,34.018123],"type":"Point"}
}