{
  "type": "Feature",
  "properties": {
    "iso:country":"US",
    "sg:address":"680 W Tennyson Rd",
    "sg:city":"Hayward",
    "sg:classifiers":[
        {
            "category":"Health Services",
            "subcategory":"Doctor",
            "type":"Services"
        }
    ],
    "sg:phone":"+1 510 782 4470",
    "sg:postcode":"94544",
    "sg:province":"CA",
    "wof:name":"Silva Pediatric Clinic the",
    "wof:placetype":"venue"
},
  "geometry": {"coordinates":[-122.069,37.631901],"type":"Point"}
}