{
  "type": "Feature",
  "properties": {
    "iso:country":"US",
    "sg:address":"1026 N Sycamore Ave",
    "sg:city":"Los Angeles",
    "sg:classifiers":[
        {
            "category":"Manufacturing",
            "subcategory":"Apparel",
            "type":"Manufacturing & Wholesale Goods"
        }
    ],
    "sg:phone":"+1 323 656 5933",
    "sg:postcode":"90038",
    "sg:province":"CA",
    "sg:tags":[
        "canvas",
        "product",
        "related"
    ],
    "wof:name":"American Awning & Blind Co",
    "wof:placetype":"venue"
},
  "geometry": {"coordinates":[-118.342709,34.090221],"type":"Point"}
}