{
  "type": "Feature",
  "properties": {
    "iso:country":"US",
    "sg:address":"7373 Fallenleaf Ln",
    "sg:city":"Cupertino",
    "sg:classifiers":[
        {
            "category":"Real Estate",
            "subcategory":"Real Estate Operator",
            "type":"Services"
        }
    ],
    "sg:phone":"+1 866 674 2320",
    "sg:postcode":"95014",
    "sg:province":"CA",
    "sg:tags":[
        "apartment"
    ],
    "wof:name":"Sahara Sands Apartments",
    "wof:placetype":"venue"
},
  "geometry": {"coordinates":[-122.03368500000001,37.30835],"type":"Point"}
}