{
  "type": "Feature",
  "properties": {
    "iso:country":"US",
    "sg:address":"1301 McKenzie Ave",
    "sg:city":"Los Altos",
    "sg:classifiers":[
        {
            "category":"Professional",
            "subcategory":"Computer Services",
            "type":"Services"
        }
    ],
    "sg:phone":"+1 650 965 9102",
    "sg:postcode":"94024",
    "sg:province":"CA",
    "sg:tags":[
        "consultant",
        "designer"
    ],
    "wof:name":"Database International",
    "wof:placetype":"venue"
},
  "geometry": {"coordinates":[-122.08481999999999,37.35678],"type":"Point"}
}