{
  "type": "Feature",
  "properties": {
    "addr:full":"2964 W Ball Rd Anaheim CA 92804",
    "addr:housenumber":"2964",
    "addr:postcode":"92804",
    "addr:street":"W Ball Rd",
    "iso:country":"US",
    "sg:address":"2964 W Ball Rd",
    "sg:city":"Anaheim",
    "sg:classifiers":[
        {
            "category":"Autos & Motor Vehicles",
            "subcategory":"Auto Supplies",
            "type":"Retail Goods"
        }
    ],
    "sg:phone":"+1 714 527 2006",
    "sg:postcode":"92804",
    "sg:province":"CA",
    "sg:tags":[
        "automobile",
        "parts"
    ],
    "wof:name":"Express Auto Parts",
    "wof:placetype":"venue"
},
  "geometry": {"coordinates":[-117.991688,33.81736],"type":"Point"}
}