{
  "type": "Feature",
  "properties": {
    "iso:country":"US",
    "sg:address":"2461 W Whittier Blvd",
    "sg:city":"Montebello",
    "sg:classifiers":[
        {
            "category":"Shopping",
            "subcategory":"Jewelry",
            "type":"Retail Goods"
        }
    ],
    "sg:phone":"+1 323 720 9758",
    "sg:postcode":"90640",
    "sg:province":"CA",
    "sg:tags":[
        "jeweler"
    ],
    "wof:name":"Origel Jewelers",
    "wof:placetype":"venue"
},
  "geometry": {"coordinates":[-118.129863,34.014489],"type":"Point"}
}