{
  "type": "Feature",
  "properties": {
    "iso:country":"US",
    "sg:address":"2901 State Hwy 16",
    "sg:city":"Plymouth",
    "sg:classifiers":[
        {
            "category":"Freight",
            "type":"Transportation"
        },
        {
            "category":"Wholesale",
            "subcategory":"Chemicals & Plastics",
            "type":"Manufacturing & Wholesale Goods"
        }
    ],
    "sg:phone":"+1 209 245 6977",
    "sg:postcode":"95669",
    "sg:province":"CA",
    "sg:tags":[
        "storage",
        "general",
        "explosive",
        "warehousing"
    ],
    "wof:name":"Golden State Explosives Inc",
    "wof:placetype":"venue"
},
  "geometry": {"coordinates":[-120.98966,38.476743],"type":"Point"}
}