{
  "type": "Feature",
  "properties": {
    "addr:full":"12935 Foothill Blvd Sylmar CA 91342",
    "addr:housenumber":"12935",
    "addr:postcode":"91342",
    "addr:street":"Foothill Blvd",
    "iso:country":"US",
    "sg:address":"12935 Foothill Blvd",
    "sg:city":"Sylmar",
    "sg:classifiers":[
        {
            "category":"Transit Center",
            "subcategory":"Freight",
            "type":"Transportation"
        }
    ],
    "sg:phone":"+1 818 361 1228",
    "sg:postcode":"91342",
    "sg:province":"CA",
    "sg:tags":[
        "container",
        "broker"
    ],
    "wof:name":"Airborne Instrument & Avi",
    "wof:placetype":"venue"
},
  "geometry": {"coordinates":[-118.41661499999999,34.294832],"type":"Point"}
}