{
  "type": "Feature",
  "properties": {
    "iso:country":"US",
    "sg:address":"10870 San Leon Ave",
    "sg:city":"Fountain Valley",
    "sg:classifiers":[
        {
            "category":"Professional",
            "type":"Services"
        }
    ],
    "sg:phone":"+1 714 963 3356",
    "sg:postcode":"92708",
    "sg:province":"CA",
    "wof:name":"Hong Xue",
    "wof:placetype":"venue"
},
  "geometry": {"coordinates":[-117.93802599999999,33.704106],"type":"Point"}
}