{
  "type": "Feature",
  "properties": {
    "addr:full":"6728 Mineral Drive San Diego CA 92119",
    "addr:housenumber":"6728",
    "addr:postcode":"92119",
    "addr:street":"Mineral Drive",
    "iso:country":"US",
    "sg:address":"6728 Mineral Drive",
    "sg:city":"San Diego",
    "sg:classifiers":[
        {
            "category":"Professional",
            "subcategory":"Lawyer & Legal Services",
            "type":"Services"
        }
    ],
    "sg:phone":"+1 619 461 8456",
    "sg:postcode":"92119",
    "sg:province":"CA",
    "sg:tags":[
        "notary"
    ],
    "sg:website":"www.allstatenotary.com",
    "wof:name":"Allstate Notary Preparation",
    "wof:placetype":"venue"
},
  "geometry": {"coordinates":[-117.01837399999999,32.806097],"type":"Point"}
}