{
  "type": "Feature",
  "properties": {
    "iso:country":"US",
    "sg:address":"181 Martinvale Ln",
    "sg:city":"San Jose",
    "sg:classifiers":[
        {
            "category":"Wholesale",
            "subcategory":"Computers",
            "type":"Manufacturing & Wholesale Goods"
        }
    ],
    "sg:phone":"+1 408 365 0609",
    "sg:postcode":"95119",
    "sg:province":"CA",
    "wof:name":"Canary Communications Inc.",
    "wof:placetype":"venue"
},
  "geometry": {"coordinates":[-121.77970500000001,37.22957],"type":"Point"}
}