{
  "type": "Feature",
  "properties": {
    "addr:full":"1090 N Imperial Ave El Centro CA 92243",
    "addr:housenumber":"1090",
    "addr:postcode":"92243",
    "addr:street":"N Imperial Ave",
    "iso:country":"US",
    "sg:address":"1090 N Imperial Ave",
    "sg:city":"El Centro",
    "sg:classifiers":[
        {
            "category":"Shopping",
            "subcategory":"Jewelry",
            "type":"Retail Goods"
        }
    ],
    "sg:phone":"+1 760 353 2550",
    "sg:postcode":"92243",
    "sg:province":"CA",
    "sg:tags":[
        "jeweler"
    ],
    "wof:name":"Zales Jewelers",
    "wof:placetype":"venue"
},
  "geometry": {"coordinates":[-115.570004,32.799968],"type":"Point"}
}