{
  "type": "Feature",
  "properties": {
    "addr:full":"1 Scripps Drive Sacramento CA 95825",
    "addr:housenumber":"1",
    "addr:postcode":"95825",
    "addr:street":"Scripps Drive",
    "iso:country":"US",
    "sg:address":"1 Scripps Drive",
    "sg:city":"Sacramento",
    "sg:classifiers":[
        {
            "category":"Health Services",
            "subcategory":"Doctor",
            "type":"Services"
        },
        {
            "category":"Health Services",
            "subcategory":"Chiropractor",
            "type":"Services"
        }
    ],
    "sg:phone":"+1 916 568 5000",
    "sg:postcode":"95825",
    "sg:province":"CA",
    "sg:tags":[
        "practice",
        "family"
    ],
    "wof:name":"Wallace James D DC PA-C",
    "wof:placetype":"venue"
},
  "geometry": {"coordinates":[-121.412317,38.573099],"type":"Point"}
}