{
  "type": "Feature",
  "properties": {
    "addr:full":"621 W Poplar St Compton CA 90220",
    "addr:housenumber":"621",
    "addr:postcode":"90220",
    "addr:street":"W Poplar St",
    "iso:country":"US",
    "sg:address":"621 W Poplar St",
    "sg:city":"Compton",
    "sg:classifiers":[
        {
            "category":"Education",
            "subcategory":"School",
            "type":"Public Place"
        }
    ],
    "sg:phone":"+1 310 898 6020",
    "sg:postcode":"90220",
    "sg:province":"CA",
    "sg:tags":[
        "elementary"
    ],
    "wof:name":"Davis Middle School",
    "wof:placetype":"venue"
},
  "geometry": {"coordinates":[-118.235001,33.899899],"type":"Point"}
}