{
  "type": "Feature",
  "properties": {
    "addr:full":"4866 W Washington Boulevard Los Angeles CA 90016",
    "addr:housenumber":"4866",
    "addr:postcode":"90016",
    "addr:street":"W Washington Boulevard",
    "iso:country":"US",
    "sg:address":"4866 W Washington Boulevard",
    "sg:city":"Los Angeles",
    "sg:classifiers":[
        {
            "category":"Organizations",
            "subcategory":"Religious Organization",
            "type":"Services"
        }
    ],
    "sg:phone":"+1 323 931 3089",
    "sg:postcode":"90016",
    "sg:province":"CA",
    "wof:name":"True Light Baptist Church",
    "wof:placetype":"venue"
},
  "geometry": {"coordinates":[-118.34585,34.040106],"type":"Point"}
}