{
  "type": "Feature",
  "properties": {
    "iso:country":"US",
    "sg:address":"529 Central Ave",
    "sg:city":"Pacific Grove",
    "sg:classifiers":[
        {
            "category":"Banks & Credit Unions",
            "subcategory":"Bank",
            "type":"Services"
        }
    ],
    "sg:phone":"+1 831 648 0200",
    "sg:postcode":"93950",
    "sg:province":"CA",
    "sg:tags":[
        "loan",
        "real estate"
    ],
    "wof:name":"American Residential Funding",
    "wof:placetype":"venue"
},
  "geometry": {"coordinates":[-121.91546,36.621753],"type":"Point"}
}