{
  "type": "Feature",
  "properties": {
    "iso:country":"US",
    "sg:address":"1790 Marina Blvd",
    "sg:city":"San Leandro",
    "sg:classifiers":[
        {
            "category":"Autos & Motor Vehicles",
            "subcategory":"Fuel & Gas Station",
            "type":"Retail Goods"
        }
    ],
    "sg:phone":"+1 510 351 7210",
    "sg:postcode":"94577",
    "sg:province":"CA",
    "wof:name":"One Stop No 23",
    "wof:placetype":"venue"
},
  "geometry": {"coordinates":[-122.175003,37.707199],"type":"Point"}
}