{
  "type": "Feature",
  "properties": {
    "addr:full":"1328 W Betteravia Rd Santa Maria CA 93455",
    "addr:housenumber":"1328",
    "addr:postcode":"93455",
    "addr:street":"W Betteravia Rd",
    "iso:country":"US",
    "sg:address":"1328 W Betteravia Rd",
    "sg:city":"Santa Maria",
    "sg:classifiers":[
        {
            "category":"Shopping",
            "subcategory":"Florist",
            "type":"Retail Goods"
        }
    ],
    "sg:phone":"+1 805 925 1250",
    "sg:postcode":"93455",
    "sg:province":"CA",
    "wof:name":"Jenny's Flowers",
    "wof:placetype":"venue"
},
  "geometry": {"coordinates":[-120.458793,34.920567],"type":"Point"}
}