{
  "type": "Feature",
  "properties": {
    "iso:country":"US",
    "sg:address":"1284 Andover Rd",
    "sg:city":"El Cajon",
    "sg:classifiers":[
        {
            "category":"Farming",
            "subcategory":"Poultry Farm",
            "type":"Manufacturing & Wholesale Goods"
        }
    ],
    "sg:phone":"+1 619 444 5813",
    "sg:postcode":"92019",
    "sg:province":"CA",
    "sg:tags":[
        "chicken",
        "egg"
    ],
    "wof:name":"La Posta Springs Ranch",
    "wof:placetype":"venue"
},
  "geometry": {"coordinates":[-116.936234,32.78909],"type":"Point"}
}