{
  "type": "Feature",
  "properties": {
    "addr:full":"1117 Symphony Way Modesto CA 95351",
    "addr:housenumber":"1117",
    "addr:postcode":"ca 95351",
    "addr:street":"Symphony Way",
    "iso:country":"US",
    "sg:address":"1117 Symphony Way",
    "sg:city":"Modesto",
    "sg:classifiers":[
        {
            "category":"Building & Trades",
            "subcategory":"Plumbing",
            "type":"Services"
        }
    ],
    "sg:phone":"+1 209 544 0892",
    "sg:postcode":"95351",
    "sg:province":"CA",
    "sg:tags":[
        "conditioning",
        "air",
        "system",
        "contractor"
    ],
    "wof:name":"Electro-Air 2000",
    "wof:placetype":"venue"
},
  "geometry": {"coordinates":[-120.977474,37.621349],"type":"Point"}
}