{
  "type": "Feature",
  "properties": {
    "addr:full":"2480 Washington Ave Ste C San Leandro CA 94577",
    "addr:housenumber":"2480",
    "addr:postcode":"94577",
    "addr:street":"Washington Ave Ste C",
    "iso:country":"US",
    "sg:address":"2480 Washington Ave Ste C",
    "sg:city":"San Leandro",
    "sg:classifiers":[
        {
            "category":"Wholesale",
            "subcategory":"Home Furnishings",
            "type":"Manufacturing & Wholesale Goods"
        },
        {
            "category":"Home & Garden",
            "subcategory":"Carpets & Floor Coverings",
            "type":"Retail Goods"
        }
    ],
    "sg:phone":"+1 510 483 6563",
    "sg:postcode":"94577",
    "sg:province":"CA",
    "sg:tags":[
        "blind",
        "shade",
        "carpeting"
    ],
    "sg:website":"www.aaadraperyco.com",
    "wof:name":"AAA Drapery Co",
    "wof:placetype":"venue"
},
  "geometry": {"coordinates":[-122.14804700000001,37.713094],"type":"Point"}
}