{
  "type": "Feature",
  "properties": {
    "addr:full":"4616 Willis Ave Sherman Oaks CA 91403",
    "addr:housenumber":"4616",
    "addr:postcode":"91403",
    "addr:street":"Willis Ave",
    "iso:country":"US",
    "sg:address":"4616 Willis Ave",
    "sg:city":"Sherman Oaks",
    "sg:classifiers":[
        {
            "category":"Real Estate",
            "subcategory":"Real Estate Agent",
            "type":"Services"
        }
    ],
    "sg:phone":"+1 818 986 9700",
    "sg:postcode":"91403",
    "sg:province":"CA",
    "sg:tags":[
        "management"
    ],
    "wof:name":"Regency At Sherman Oaks",
    "wof:placetype":"venue"
},
  "geometry": {"coordinates":[-118.455242,34.157528],"type":"Point"}
}