{
  "type": "Feature",
  "properties": {
    "iso:country":"US",
    "sg:address":"524 Bear Mountain Blvd",
    "sg:city":"Arvin",
    "sg:classifiers":[
        {
            "category":"Restaurant",
            "type":"Food & Drink"
        }
    ],
    "sg:menulink":"http://www.allmenus.com/ca/arvin-lamont/87692-little-caesars-pizza/menu/",
    "sg:phone":"+1 661 854 8888",
    "sg:postcode":"93203",
    "sg:province":"CA",
    "sg:tags":[
        "american",
        "pizza"
    ],
    "wof:name":"Little Caesar's Pizza",
    "wof:placetype":"venue"
},
  "geometry": {"coordinates":[-118.831435,35.209137],"type":"Point"}
}