{
  "type": "Feature",
  "properties": {
    "addr:full":"46 Traynor St Hayward CA 94544",
    "addr:housenumber":"46",
    "addr:postcode":"94544",
    "addr:street":"Traynor St",
    "iso:country":"US",
    "sg:address":"46 Traynor St",
    "sg:city":"Hayward",
    "sg:classifiers":[
        {
            "category":"Retail",
            "subcategory":"Repair Shop",
            "type":"Services"
        }
    ],
    "sg:phone":"+1 510 346 0773",
    "sg:postcode":"94544",
    "sg:province":"CA",
    "sg:tags":[
        "refinishing",
        "furniture"
    ],
    "wof:name":"TLH Finishes",
    "wof:placetype":"venue"
},
  "geometry": {"coordinates":[-122.085972,37.657235],"type":"Point"}
}