{
  "type": "Feature",
  "properties": {
    "iso:country":"US",
    "sg:address":"313 E Palmdale Blvd",
    "sg:city":"Palmdale",
    "sg:classifiers":[
        {
            "category":"Travel",
            "subcategory":"Travel Agent",
            "type":"Entertainment"
        }
    ],
    "sg:phone":"+1 661 274 8034",
    "sg:postcode":"93550",
    "sg:province":"CA",
    "sg:tags":[
        "agency"
    ],
    "wof:name":"Latco Travel",
    "wof:placetype":"venue"
},
  "geometry": {"coordinates":[-118.12464,34.57993],"type":"Point"}
}