{
  "type": "Feature",
  "properties": {
    "addr:full":"11526 Lyster Ave Northridge CA 91326",
    "addr:housenumber":"11526",
    "addr:postcode":"91326",
    "addr:street":"Lyster Ave",
    "iso:country":"US",
    "sg:address":"11526 Lyster Ave",
    "sg:city":"Northridge",
    "sg:classifiers":[
        {
            "category":"Professional",
            "type":"Services"
        }
    ],
    "sg:phone":"+1 818 366 2192",
    "sg:postcode":"91326",
    "sg:province":"CA",
    "wof:name":"Steven E McKenzie Inc",
    "wof:placetype":"venue"
},
  "geometry": {"coordinates":[-118.54176,34.282098],"type":"Point"}
}