{
  "type": "Feature",
  "properties": {
    "addr:full":"14709 Carmenita Rd Norwalk CA 90650",
    "addr:postcode":"14709;90650",
    "addr:street":"Carmenita Rd",
    "iso:country":"US",
    "sg:address":"14709 Carmenita Rd",
    "sg:city":"Norwalk",
    "sg:classifiers":[
        {
            "category":"Wholesale",
            "subcategory":"Machinery & Supplies",
            "type":"Manufacturing & Wholesale Goods"
        }
    ],
    "sg:phone":"+1 562 926 3737",
    "sg:postcode":"90650",
    "sg:province":"CA",
    "sg:tags":[
        "machine",
        "embroidering"
    ],
    "wof:name":"Aemco Embroidery Machine",
    "wof:placetype":"venue"
},
  "geometry": {"coordinates":[-118.046661,33.898168],"type":"Point"}
}