{
  "type": "Feature",
  "properties": {
    "iso:country":"US",
    "sg:address":"341 Cherry Tree Ln",
    "sg:city":"Newport Beach",
    "sg:classifiers":[
        {
            "category":"Organizations",
            "subcategory":"Non-profit Organization",
            "type":"Services"
        }
    ],
    "sg:phone":"+1 949 650 8746",
    "sg:postcode":"92660",
    "sg:province":"CA",
    "wof:name":"Sushi Cats Feline Fanciers",
    "wof:placetype":"venue"
},
  "geometry": {"coordinates":[-117.895602,33.65041],"type":"Point"}
}