{
  "type": "Feature",
  "properties": {
    "addr:full":"4600 N Pershing Ave Stockton CA 95207",
    "addr:housenumber":"4600",
    "addr:postcode":"95207",
    "addr:street":"N Pershing Ave",
    "iso:country":"US",
    "sg:address":"4600 N Pershing Ave",
    "sg:city":"Stockton",
    "sg:classifiers":[
        {
            "category":"Real Estate",
            "subcategory":"Real Estate Agent",
            "type":"Services"
        }
    ],
    "sg:phone":"+1 209 478 5900",
    "sg:postcode":"95207",
    "sg:province":"CA",
    "sg:tags":[
        "broker"
    ],
    "wof:name":"G M A C Real Estate",
    "wof:placetype":"venue"
},
  "geometry": {"coordinates":[-121.32112100000001,37.987329],"type":"Point"}
}