{
  "type": "Feature",
  "properties": {
    "addr:full":"1660 N Wilton Pl Los Angeles CA 90028",
    "addr:housenumber":"1660",
    "addr:postcode":"90028",
    "addr:street":"N Wilton Pl",
    "iso:country":"US",
    "sg:address":"1660 N Wilton Pl",
    "sg:city":"Los Angeles",
    "sg:classifiers":[
        {
            "category":"Social Services",
            "subcategory":"Child Care",
            "type":"Services"
        }
    ],
    "sg:phone":"+1 323 462 0578",
    "sg:postcode":"90028",
    "sg:province":"CA",
    "sg:tags":[
        "day"
    ],
    "wof:name":"Jammie's Day Care",
    "wof:placetype":"venue"
},
  "geometry": {"coordinates":[-118.31345399999999,34.100995],"type":"Point"}
}