{
  "type": "Feature",
  "properties": {
    "addr:full":"2702 Qualtrough St San Diego CA 92106",
    "addr:housenumber":"2702",
    "addr:postcode":"92106",
    "addr:street":"Qualtrough St",
    "iso:country":"US",
    "sg:address":"2702 Qualtrough St",
    "sg:city":"San Diego",
    "sg:classifiers":[
        {
            "category":"Recreation",
            "type":"Entertainment"
        }
    ],
    "sg:phone":"+1 619 222 0438",
    "sg:postcode":"92106",
    "sg:province":"CA",
    "sg:tags":[
        "club",
        "membership",
        "yacht"
    ],
    "wof:name":"Southwestern Yacht Club Inc",
    "wof:placetype":"venue"
},
  "geometry": {"coordinates":[-117.233875,32.714876],"type":"Point"}
}