{
  "type": "Feature",
  "properties": {
    "iso:country":"US",
    "sg:address":"9111 Valley View St, Ste #115",
    "sg:city":"Cypress",
    "sg:classifiers":[
        {
            "category":"Professional",
            "type":"Services"
        }
    ],
    "sg:phone":"+1 714 995 7323",
    "sg:postcode":"90630",
    "sg:province":"CA",
    "sg:website":"www.tutoringclub.com",
    "wof:name":"Tutoring Club",
    "wof:placetype":"venue"
},
  "geometry": {"coordinates":[-118.029037,33.830387],"type":"Point"}
}