{
  "type": "Feature",
  "properties": {
    "addr:full":"3690 Maria Ln Carlsbad CA 92008",
    "addr:postcode":"3690;92008",
    "addr:street":"Maria Ln",
    "iso:country":"US",
    "sg:address":"3690 Maria Ln",
    "sg:city":"Carlsbad",
    "sg:classifiers":[
        {
            "category":"Shopping",
            "subcategory":"Gifts & Souvenirs",
            "type":"Retail Goods"
        }
    ],
    "sg:phone":"+1 760 729 0640",
    "sg:postcode":"92008",
    "sg:province":"CA",
    "wof:name":"Tiki Man",
    "wof:placetype":"venue"
},
  "geometry": {"coordinates":[-117.322261,33.164266],"type":"Point"}
}