{
  "type": "Feature",
  "properties": {
    "iso:country":"US",
    "sg:address":"24004 Lake Dr",
    "sg:city":"Crestline",
    "sg:classifiers":[
        {
            "category":"Personal",
            "subcategory":"Beauty Salon",
            "type":"Services"
        }
    ],
    "sg:phone":"+1 909 338 3383",
    "sg:postcode":"92325",
    "sg:province":"CA",
    "sg:tags":[
        "hair",
        "stylist"
    ],
    "wof:name":"Marlo's Flair for Hair",
    "wof:placetype":"venue"
},
  "geometry": {"coordinates":[-117.27972800000001,34.243402],"type":"Point"}
}