{
  "type": "Feature",
  "properties": {
    "addr:full":"521 W Vernon Avenue Los Angeles CA 90037",
    "addr:housenumber":"521",
    "addr:postcode":"90037",
    "addr:street":"W Vernon Avenue",
    "iso:country":"US",
    "sg:address":"521 W Vernon Avenue",
    "sg:city":"Los Angeles",
    "sg:classifiers":[
        {
            "category":"Building & Trades",
            "subcategory":"Construction",
            "type":"Services"
        }
    ],
    "sg:phone":"+1 323 232 7290",
    "sg:postcode":"90037",
    "sg:province":"CA",
    "sg:tags":[
        "roofing",
        "painter"
    ],
    "sg:website":"www.victoryrnp.com/",
    "wof:name":"Victory Painting & Roofing",
    "wof:placetype":"venue"
},
  "geometry": {"coordinates":[-118.282918,34.003649],"type":"Point"}
}