{
  "type": "Feature",
  "properties": {
    "iso:country":"US",
    "sg:address":"17633 Lassen St",
    "sg:city":"Northridge",
    "sg:classifiers":[
        {
            "category":"Education",
            "subcategory":"School",
            "type":"Public Place"
        }
    ],
    "sg:phone":"+1 818 886 7922",
    "sg:postcode":"91325",
    "sg:province":"CA",
    "wof:name":"Casa Montessori Inc",
    "wof:placetype":"venue"
},
  "geometry": {"coordinates":[-118.51853300000001,34.250435],"type":"Point"}
}