{
  "type": "Feature",
  "properties": {
    "addr:full":"17005 Yukon Ave Torrance CA 90504",
    "addr:housenumber":"17005",
    "addr:postcode":"90504",
    "addr:street":"Yukon Ave",
    "iso:country":"US",
    "sg:address":"17005 Yukon Ave",
    "sg:city":"Torrance",
    "sg:classifiers":[
        {
            "category":"Real Estate",
            "subcategory":"Real Estate Operator",
            "type":"Services"
        }
    ],
    "sg:phone":"+1 310 527 7208",
    "sg:postcode":"90504",
    "sg:province":"CA",
    "sg:tags":[
        "apartment"
    ],
    "wof:name":"Yukon Plaza Apartments",
    "wof:placetype":"venue"
},
  "geometry": {"coordinates":[-118.334999,33.876099],"type":"Point"}
}