{
  "type": "Feature",
  "properties": {
    "iso:country":"US",
    "sg:address":"150 E El Camino Real",
    "sg:city":"Mountain View",
    "sg:classifiers":[
        {
            "category":"Autos & Motor Vehicles",
            "subcategory":"Automobile Sales",
            "type":"Retail Goods"
        }
    ],
    "sg:phone":"+1 650 943 1000",
    "sg:postcode":"94041",
    "sg:province":"CA",
    "sg:tags":[
        "car"
    ],
    "sg:website":"www.bmwofmountainview.com/",
    "wof:name":"BMW of Mountain View",
    "wof:placetype":"venue"
},
  "geometry": {"coordinates":[-122.071479,37.380467],"type":"Point"}
}