{
  "type": "Feature",
  "properties": {
    "iso:country":"US",
    "sg:address":"1240 Luther Way",
    "sg:city":"Salinas",
    "sg:classifiers":[
        {
            "category":"Shopping",
            "subcategory":"Gifts & Souvenirs",
            "type":"Retail Goods"
        }
    ],
    "sg:phone":"+1 831 757 3798",
    "sg:postcode":"93901",
    "sg:province":"CA",
    "wof:name":"Custom Card & Embroidery",
    "wof:placetype":"venue"
},
  "geometry": {"coordinates":[-121.67351600000001,36.661626],"type":"Point"}
}