{
  "type": "Feature",
  "properties": {
    "iso:country":"US",
    "sg:address":"3860 Chanson Dr",
    "sg:city":"Los Angeles",
    "sg:classifiers":[
        {
            "category":"Building & Trades",
            "subcategory":"Electrical",
            "type":"Services"
        }
    ],
    "sg:phone":"+1 323 292 0905",
    "sg:postcode":"90043",
    "sg:province":"CA",
    "sg:tags":[
        "electrical",
        "electric",
        "contractor"
    ],
    "wof:name":"Hooks Electric Co",
    "wof:placetype":"venue"
},
  "geometry": {"coordinates":[-118.342663,33.996329],"type":"Point"}
}