{
  "type": "Feature",
  "properties": {
    "addr:full":"29561 Miller Rd Valley Center CA 92082",
    "addr:housenumber":"29561",
    "addr:postcode":"92082",
    "addr:street":"Miller Rd",
    "iso:country":"US",
    "sg:address":"29561 Miller Rd",
    "sg:city":"Valley Center",
    "sg:classifiers":[
        {
            "category":"Wholesale",
            "subcategory":"Toys & Hobbies",
            "type":"Manufacturing & Wholesale Goods"
        }
    ],
    "sg:phone":"+1 760 749 2261",
    "sg:postcode":"92082",
    "sg:province":"CA",
    "wof:name":"Royal Threads",
    "wof:placetype":"venue"
},
  "geometry": {"coordinates":[-117.03184400000001,33.248076],"type":"Point"}
}