{
  "type": "Feature",
  "properties": {
    "addr:full":"333 W 6th St San Pedro CA 90731",
    "addr:housenumber":"333",
    "addr:postcode":"90731",
    "addr:street":"W 6Th St",
    "iso:country":"US",
    "sg:address":"333 W 6th St",
    "sg:city":"San Pedro",
    "sg:classifiers":[
        {
            "category":"Professional",
            "subcategory":"Computer Services",
            "type":"Services"
        }
    ],
    "sg:phone":"+1 310 519 8344",
    "sg:postcode":"90731",
    "sg:province":"CA",
    "sg:tags":[
        "consultant",
        "designer"
    ],
    "wof:name":"Citezens Computer Intl",
    "wof:placetype":"venue"
},
  "geometry": {"coordinates":[-118.284614,33.73882],"type":"Point"}
}