{
  "type": "Feature",
  "properties": {
    "addr:full":"833 N Anaheim Blvd Anaheim CA 92805",
    "addr:housenumber":"833",
    "addr:postcode":"92805",
    "addr:street":"N Anaheim Blvd",
    "iso:country":"US",
    "sg:address":"833 N Anaheim Blvd",
    "sg:city":"Anaheim",
    "sg:classifiers":[
        {
            "category":"Wholesale",
            "subcategory":"Auto Parts",
            "type":"Manufacturing & Wholesale Goods"
        }
    ],
    "sg:phone":"+1 714 774 6491",
    "sg:postcode":"92805",
    "sg:province":"CA",
    "sg:tags":[
        "truck",
        "accessory"
    ],
    "wof:name":"Arma Coating Of Anaheim",
    "wof:placetype":"venue"
},
  "geometry": {"coordinates":[-117.916922,33.844929],"type":"Point"}
}