{
  "type": "Feature",
  "properties": {
    "addr:full":"120 N 11th St Montague CA 96064",
    "addr:housenumber":"120",
    "addr:postcode":"96064",
    "addr:street":"N 11Th St",
    "iso:country":"US",
    "sg:address":"120 N 11th St",
    "sg:city":"Montague",
    "sg:classifiers":[
        {
            "category":"Restaurant",
            "type":"Food & Drink"
        }
    ],
    "sg:phone":"+1 530 459 3439",
    "sg:postcode":"96064",
    "sg:province":"CA",
    "wof:name":"Ms Lynn's Tea",
    "wof:placetype":"venue"
},
  "geometry": {"coordinates":[-122.526901,41.729392],"type":"Point"}
}