{
  "type": "Feature",
  "properties": {
    "iso:country":"US",
    "sg:address":"4400 Coldwater Canyon Ave",
    "sg:city":"Studio City",
    "sg:classifiers":[
        {
            "category":"Professional",
            "subcategory":"Computer Services",
            "type":"Services"
        }
    ],
    "sg:phone":"+1 818 985 5678",
    "sg:postcode":"91604",
    "sg:province":"CA",
    "sg:website":"www.homerunmedia.net",
    "wof:name":"Home Run Media",
    "wof:placetype":"venue"
},
  "geometry": {"coordinates":[-118.413774,34.151803],"type":"Point"}
}