{
  "type": "Feature",
  "properties": {
    "addr:full":"1640 Sherwood Village Cir Placentia CA 92870",
    "addr:housenumber":"1640",
    "addr:postcode":"ca 92870",
    "addr:street":"Sherwood Village Cir",
    "iso:country":"US",
    "sg:address":"1640 Sherwood Village Cir",
    "sg:city":"Placentia",
    "sg:classifiers":[
        {
            "category":"Building & Trades",
            "subcategory":"Landscaping Services",
            "type":"Services"
        }
    ],
    "sg:phone":"+1 714 524 9134",
    "sg:postcode":"92870",
    "sg:province":"CA",
    "sg:tags":[
        "landscape"
    ],
    "wof:name":"Dave McCauley & Assoc",
    "wof:placetype":"venue"
},
  "geometry": {"coordinates":[-117.845477,33.892889],"type":"Point"}
}