{
  "type": "Feature",
  "properties": {
    "addr:full":"10705 Balboa Blvd Granada Hills CA 91344",
    "addr:housenumber":"10705",
    "addr:postcode":"91344",
    "addr:street":"Balboa Blvd",
    "iso:country":"US",
    "sg:address":"10705 Balboa Blvd",
    "sg:city":"Granada Hills",
    "sg:classifiers":[
        {
            "category":"Shopping",
            "subcategory":"Tobacco",
            "type":"Retail Goods"
        }
    ],
    "sg:phone":"+1 818 832 8378",
    "sg:postcode":"91344",
    "sg:province":"CA",
    "sg:tags":[
        "shop",
        "smoke",
        "supply"
    ],
    "wof:name":"Red Eye",
    "wof:placetype":"venue"
},
  "geometry": {"coordinates":[-118.502332,34.265952],"type":"Point"}
}