{
  "type": "Feature",
  "properties": {
    "iso:country":"US",
    "sg:address":"4100 W Pico Blvd",
    "sg:city":"Los Angeles",
    "sg:classifiers":[
        {
            "category":"Food & Beverages",
            "subcategory":"Ethnic Foods",
            "type":"Retail Goods"
        }
    ],
    "sg:phone":"+1 323 373 0650",
    "sg:postcode":"90019",
    "sg:province":"CA",
    "wof:name":"Kim Chi House",
    "wof:placetype":"venue"
},
  "geometry": {"coordinates":[-118.32457700000001,34.047617],"type":"Point"}
}