{
  "type": "Feature",
  "properties": {
    "iso:country":"US",
    "sg:address":"22915 Saticoy St",
    "sg:city":"Canoga Park",
    "sg:classifiers":[
        {
            "category":"Retail",
            "subcategory":"Repair Shop",
            "type":"Services"
        }
    ],
    "sg:phone":"+1 818 340 6050",
    "sg:postcode":"91304",
    "sg:province":"CA",
    "sg:tags":[
        "appliance"
    ],
    "wof:name":"Baker Appliance Svc",
    "wof:placetype":"venue"
},
  "geometry": {"coordinates":[-118.626882,34.208318],"type":"Point"}
}