{
  "type": "Feature",
  "properties": {
    "iso:country":"US",
    "sg:address":"1833 Dana St",
    "sg:city":"Glendale",
    "sg:classifiers":[
        {
            "category":"Building & Trades",
            "subcategory":"Cleaning & Sanitation",
            "type":"Services"
        }
    ],
    "sg:phone":"+1 818 543 3930",
    "sg:postcode":"91201",
    "sg:province":"CA",
    "sg:tags":[
        "carpet"
    ],
    "wof:name":"Aeroscopic Environmental",
    "wof:placetype":"venue"
},
  "geometry": {"coordinates":[-118.297549,34.169223],"type":"Point"}
}