{
  "type": "Feature",
  "properties": {
    "iso:country":"US",
    "sg:address":"489 6th St",
    "sg:city":"San Francisco",
    "sg:classifiers":[
        {
            "category":"Professional",
            "subcategory":"Art Services",
            "type":"Services"
        }
    ],
    "sg:phone":"+1 415 777 0887",
    "sg:postcode":"94103",
    "sg:province":"CA",
    "sg:tags":[
        "photographer"
    ],
    "wof:name":"Bill Acheson & Co",
    "wof:placetype":"venue"
},
  "geometry": {"coordinates":[-122.40276799999999,37.776392],"type":"Point"}
}