{
  "type": "Feature",
  "properties": {
    "iso:country":"US",
    "sg:address":"780 Chadbourne Rd",
    "sg:city":"Fairfield",
    "sg:classifiers":[
        {
            "category":"Professional",
            "subcategory":"Research",
            "type":"Services"
        }
    ],
    "sg:phone":"+1 707 421 2500",
    "sg:postcode":"94534",
    "sg:province":"CA",
    "sg:tags":[
        "environmental",
        "ecological"
    ],
    "wof:name":"Moju Environmental Techs",
    "wof:placetype":"venue"
},
  "geometry": {"coordinates":[-122.08372900000001,38.231877],"type":"Point"}
}