{
  "type": "Feature",
  "properties": {
    "addr:full":"11761 Carson St Lakewood CA 90715",
    "addr:housenumber":"11761",
    "addr:postcode":"90715",
    "addr:street":"Carson St",
    "iso:country":"US",
    "sg:address":"11761 Carson St",
    "sg:city":"Lakewood",
    "sg:classifiers":[
        {
            "category":"Food & Beverages",
            "subcategory":"Groceries & Convenience Stores",
            "type":"Retail Goods"
        }
    ],
    "sg:phone":"+1 562 924 7353",
    "sg:postcode":"90715",
    "sg:province":"CA",
    "wof:name":"7-Eleven",
    "wof:placetype":"venue"
},
  "geometry": {"coordinates":[-118.258529,33.831657],"type":"Point"}
}