{
  "type": "Feature",
  "properties": {
    "addr:full":"724 Avon St Modesto CA 95351",
    "addr:housenumber":"724",
    "addr:postcode":"ca 95351",
    "addr:street":"Avon St",
    "iso:country":"US",
    "sg:address":"724 Avon St",
    "sg:city":"Modesto",
    "sg:classifiers":[
        {
            "category":"Freight",
            "type":"Transportation"
        }
    ],
    "sg:phone":"+1 209 238 0993",
    "sg:postcode":"95351",
    "sg:province":"CA",
    "sg:tags":[
        "trucking"
    ],
    "wof:name":"A B Carrier",
    "wof:placetype":"venue"
},
  "geometry": {"coordinates":[-120.979257,37.618536],"type":"Point"}
}