{
  "type": "Feature",
  "properties": {
    "iso:country":"US",
    "sg:address":"45 S Sanborn Rd",
    "sg:city":"Salinas",
    "sg:classifiers":[
        {
            "category":"Banks & Credit Unions",
            "subcategory":"Bank",
            "type":"Services"
        }
    ],
    "sg:phone":"+1 831 753 2274",
    "sg:postcode":"93905",
    "sg:province":"CA",
    "sg:tags":[
        "cashing",
        "check"
    ],
    "wof:name":"Fast Cash Check Cashing",
    "wof:placetype":"venue"
},
  "geometry": {"coordinates":[-121.627363,36.67275],"type":"Point"}
}