{
  "type": "Feature",
  "properties": {
    "addr:full":"1623 Boyd St Santa Ana CA 92705",
    "addr:housenumber":"1623",
    "addr:postcode":"92705",
    "addr:street":"Boyd St",
    "iso:country":"US",
    "sg:address":"1623 Boyd St",
    "sg:city":"Santa Ana",
    "sg:classifiers":[
        {
            "category":"Wholesale",
            "subcategory":"Machinery & Supplies",
            "type":"Manufacturing & Wholesale Goods"
        }
    ],
    "sg:phone":"+1 714 259 0828",
    "sg:postcode":"92705",
    "sg:province":"CA",
    "sg:tags":[
        "equipment",
        "industrial"
    ],
    "wof:name":"Ideal Cycle Machinery Corp",
    "wof:placetype":"venue"
},
  "geometry": {"coordinates":[-117.837873,33.725671],"type":"Point"}
}