{
  "type": "Feature",
  "properties": {
    "addr:full":"953 Reece St San Bernardino CA 92411",
    "addr:housenumber":"953",
    "addr:postcode":"92411",
    "addr:street":"Reece St",
    "iso:country":"US",
    "sg:address":"953 Reece St",
    "sg:city":"San Bernardino",
    "sg:classifiers":[
        {
            "category":"Professional",
            "subcategory":"Research",
            "type":"Services"
        }
    ],
    "sg:phone":"+1 909 884 7424",
    "sg:postcode":"92411",
    "sg:province":"CA",
    "sg:tags":[
        "environmental",
        "ecological"
    ],
    "wof:name":"Environmental Contractors Inc",
    "wof:placetype":"venue"
},
  "geometry": {"coordinates":[-117.30550599999999,34.122226],"type":"Point"}
}