{
  "type": "Feature",
  "properties": {
    "addr:full":"320 Vista Grande Greenbrae CA 94904",
    "addr:housenumber":"320",
    "addr:postcode":"94904",
    "addr:street":"Vista Grande",
    "iso:country":"US",
    "sg:address":"320 Vista Grande",
    "sg:city":"Greenbrae",
    "sg:classifiers":[
        {
            "category":"Place Of Worship",
            "subcategory":"Church",
            "type":"Public Place"
        },
        {
            "category":"Arts & Performance",
            "subcategory":"Music",
            "type":"Entertainment"
        },
        {
            "category":"Recreation",
            "type":"Entertainment"
        }
    ],
    "sg:phone":"+1 415 461 2200",
    "sg:postcode":"94904",
    "sg:province":"CA",
    "sg:tags":[
        "ceremony",
        "orchestra",
        "band",
        "marriage",
        "wedding",
        "chapel"
    ],
    "wof:name":"All Stars Music",
    "wof:placetype":"venue"
},
  "geometry": {"coordinates":[-122.528758,37.954427],"type":"Point"}
}