{
  "type": "Feature",
  "properties": {
    "addr:full":"1160 W Flint St Lake Elsinore CA 92530",
    "addr:housenumber":"1160",
    "addr:postcode":"92530",
    "addr:street":"W Flint St",
    "iso:country":"US",
    "sg:address":"1160 W Flint St",
    "sg:city":"Lake Elsinore",
    "sg:classifiers":[
        {
            "category":"Manufacturing",
            "subcategory":"Tools & Machinery",
            "type":"Manufacturing & Wholesale Goods"
        }
    ],
    "sg:phone":"+1 951 674 1276",
    "sg:postcode":"92530",
    "sg:province":"CA",
    "sg:tags":[
        "machine",
        "shop"
    ],
    "wof:name":"Cougar Tools Corp",
    "wof:placetype":"venue"
},
  "geometry": {"coordinates":[-117.33719600000001,33.678443],"type":"Point"}
}