{
  "type": "Feature",
  "properties": {
    "iso:country":"US",
    "sg:address":"2490 Ash St",
    "sg:city":"Vista",
    "sg:classifiers":[
        {
            "category":"Wholesale",
            "subcategory":"Sporting Goods",
            "type":"Manufacturing & Wholesale Goods"
        }
    ],
    "sg:phone":"+1 760 734 1111",
    "sg:postcode":"92081",
    "sg:province":"CA",
    "wof:name":"Extreme Sports Inc",
    "wof:placetype":"venue"
},
  "geometry": {"coordinates":[-117.218523,33.149345],"type":"Point"}
}