{
  "type": "Feature",
  "properties": {
    "addr:full":"3016 Prospect Ave La Crescenta CA 91214",
    "addr:housenumber":"3016",
    "addr:postcode":"91214",
    "addr:street":"Prospect Ave",
    "iso:country":"US",
    "sg:address":"3016 Prospect Ave",
    "sg:city":"La Crescenta",
    "sg:classifiers":[
        {
            "category":"Local Transit",
            "type":"Transportation"
        }
    ],
    "sg:phone":"+1 818 236 2100",
    "sg:postcode":"91214",
    "sg:province":"CA",
    "sg:tags":[
        "airport"
    ],
    "sg:website":"www.lacanadalimo.com",
    "wof:name":"LA Canada Airport Car Svc",
    "wof:placetype":"venue"
},
  "geometry": {"coordinates":[-118.246448,34.225368],"type":"Point"}
}