{
  "type": "Feature",
  "properties": {
    "addr:full":"2801 Cohasset Rd Chico CA 95973",
    "addr:housenumber":"2801",
    "addr:postcode":"95973",
    "addr:street":"Cohasset Rd",
    "iso:country":"US",
    "sg:address":"2801 Cohasset Rd",
    "sg:city":"Chico",
    "sg:classifiers":[
        {
            "category":"Personal",
            "subcategory":"Beauty Salon",
            "type":"Services"
        }
    ],
    "sg:phone":"+1 530 898 0238",
    "sg:postcode":"95973",
    "sg:province":"CA",
    "wof:name":"Karen's KUT & KURL",
    "wof:placetype":"venue"
},
  "geometry": {"coordinates":[-121.84359499999999,39.766746],"type":"Point"}
}