{
  "type": "Feature",
  "properties": {
    "iso:country":"US",
    "sg:address":"2842 Story Rd",
    "sg:city":"San Jose",
    "sg:classifiers":[
        {
            "category":"Building & Trades",
            "subcategory":"Equipment Rental",
            "type":"Services"
        }
    ],
    "sg:phone":"+1 408 272 3629",
    "sg:postcode":"95127",
    "sg:province":"CA",
    "sg:tags":[
        "disabled",
        "person",
        "supply"
    ],
    "wof:name":"Greater Opportunities",
    "wof:placetype":"venue"
},
  "geometry": {"coordinates":[-121.822958,37.353475],"type":"Point"}
}