{
  "type": "Feature",
  "properties": {
    "addr:full":"924 Riesling Dr Pleasanton CA 94566",
    "addr:housenumber":"924",
    "addr:postcode":"94566",
    "addr:street":"Riesling Dr",
    "iso:country":"US",
    "sg:address":"924 Riesling Dr",
    "sg:city":"Pleasanton",
    "sg:classifiers":[
        {
            "category":"Building & Trades",
            "subcategory":"Landscaping Services",
            "type":"Services"
        }
    ],
    "sg:phone":"+1 925 461 8708",
    "sg:postcode":"94566",
    "sg:province":"CA",
    "sg:tags":[
        "designer",
        "landscape"
    ],
    "wof:name":"Jeff Wortham & Assoc",
    "wof:placetype":"venue"
},
  "geometry": {"coordinates":[-121.853275,37.656547],"type":"Point"}
}