{
  "type": "Feature",
  "properties": {
    "iso:country":"US",
    "sg:address":"1612 Hillsdale Rd",
    "sg:city":"El Cajon",
    "sg:classifiers":[
        {
            "category":"Wholesale",
            "subcategory":"Plants",
            "type":"Manufacturing & Wholesale Goods"
        }
    ],
    "sg:phone":"+1 619 440 4839",
    "sg:postcode":"92019",
    "sg:province":"CA",
    "sg:tags":[
        "supply"
    ],
    "wof:name":"Chocolate Moose Growers",
    "wof:placetype":"venue"
},
  "geometry": {"coordinates":[-116.92773,32.762168],"type":"Point"}
}