{
  "type": "Feature",
  "properties": {
    "addr:full":"2934 E Imperial Hwy Lynwood CA 90262",
    "addr:housenumber":"2934",
    "addr:postcode":"90262",
    "addr:street":"E Imperial Hwy",
    "iso:country":"US",
    "sg:address":"2934 E Imperial Hwy",
    "sg:city":"Lynwood",
    "sg:classifiers":[
        {
            "category":"Manufacturing",
            "subcategory":"Glass & Minerals",
            "type":"Manufacturing & Wholesale Goods"
        }
    ],
    "sg:phone":"+1 310 898 3100",
    "sg:postcode":"90262",
    "sg:province":"CA",
    "sg:tags":[
        "plate",
        "shape",
        "glass-wholesale",
        "window",
        "special",
        "circle",
        "glass-auto",
        "manufacturer"
    ],
    "wof:name":"Import Glass Co",
    "wof:placetype":"venue"
},
  "geometry": {"coordinates":[-118.219701,33.930705],"type":"Point"}
}