{
  "type": "Feature",
  "properties": {
    "iso:country":"US",
    "sg:address":"1432 Alegria Loop",
    "sg:city":"San Jose",
    "sg:classifiers":[
        {
            "category":"Wholesale",
            "subcategory":"Computers",
            "type":"Manufacturing & Wholesale Goods"
        }
    ],
    "sg:phone":"+1 408 293 0149",
    "sg:postcode":"95128",
    "sg:province":"CA",
    "sg:website":"www.bluebonepc.com",
    "wof:name":"Blue Bone",
    "wof:placetype":"venue"
},
  "geometry": {"coordinates":[-121.929827,37.30118],"type":"Point"}
}