{
  "type": "Feature",
  "properties": {
    "iso:country":"US",
    "sg:address":"1716 N Sunset Ln",
    "sg:city":"Fullerton",
    "sg:classifiers":[
        {
            "category":"Manufacturing",
            "subcategory":"Glass & Minerals",
            "type":"Manufacturing & Wholesale Goods"
        }
    ],
    "sg:phone":"+1 714 680 3245",
    "sg:postcode":"92833",
    "sg:province":"CA",
    "sg:tags":[
        "flat",
        "mfg"
    ],
    "wof:name":"Creations By Gilda",
    "wof:placetype":"venue"
},
  "geometry": {"coordinates":[-117.964168,33.890494],"type":"Point"}
}