{
  "type": "Feature",
  "properties": {
    "addr:full":"600 E 5th St Azusa CA 91702",
    "addr:housenumber":"600",
    "addr:postcode":"91702",
    "addr:street":"E 5Th St",
    "iso:country":"US",
    "sg:address":"600 E 5th St",
    "sg:city":"Azusa",
    "sg:classifiers":[
        {
            "category":"Food & Beverages",
            "subcategory":"Dairy",
            "type":"Retail Goods"
        }
    ],
    "sg:phone":"+1 626 334 4370",
    "sg:postcode":"91702",
    "sg:province":"CA",
    "sg:tags":[
        "product"
    ],
    "wof:name":"Foothill Dairy",
    "wof:placetype":"venue"
},
  "geometry": {"coordinates":[-117.899612,34.129791],"type":"Point"}
}