{
  "type": "Feature",
  "properties": {
    "addr:full":"672 Baker Dr Paradise CA 95969",
    "addr:housenumber":"672",
    "addr:postcode":"95969",
    "addr:street":"Baker Dr",
    "iso:country":"US",
    "sg:address":"672 Baker Dr",
    "sg:city":"Paradise",
    "sg:classifiers":[
        {
            "category":"Professional",
            "type":"Services"
        }
    ],
    "sg:phone":"+1 530 877 4392",
    "sg:postcode":"95969",
    "sg:province":"CA",
    "wof:name":"Dennis King",
    "wof:placetype":"venue"
},
  "geometry": {"coordinates":[-121.626182,39.767633],"type":"Point"}
}