{
  "type": "Feature",
  "properties": {
    "addr:full":"27574 Commerce Center Dr Temecula CA 92590",
    "addr:housenumber":"27574",
    "addr:postcode":"92590",
    "addr:street":"Commerce Center Dr",
    "iso:country":"US",
    "sg:address":"27574 Commerce Center Dr",
    "sg:city":"Temecula",
    "sg:classifiers":[
        {
            "category":"Building & Trades",
            "subcategory":"Cleaning & Sanitation",
            "type":"Services"
        }
    ],
    "sg:phone":"+1 951 699 5620",
    "sg:postcode":"92590",
    "sg:province":"CA",
    "sg:tags":[
        "janitor"
    ],
    "wof:name":"Hygafem Southern California",
    "wof:placetype":"venue"
},
  "geometry": {"coordinates":[-117.160479,33.511595],"type":"Point"}
}