{
  "type": "Feature",
  "properties": {
    "iso:country":"US",
    "sg:address":"18349 S Figueroa St",
    "sg:city":"Gardena",
    "sg:classifiers":[
        {
            "category":"Organizations",
            "subcategory":"Labor Organization",
            "type":"Services"
        }
    ],
    "sg:phone":"+1 310 515 9054",
    "sg:postcode":"90248",
    "sg:province":"CA",
    "wof:name":"UA-Agc Journeyman Training",
    "wof:placetype":"venue"
},
  "geometry": {"coordinates":[-118.281633,33.86318],"type":"Point"}
}