{
  "type": "Feature",
  "properties": {
    "iso:country":"US",
    "sg:address":"4420 Mission Street",
    "sg:city":"San Francisco",
    "sg:classifiers":[
        {
            "category":"Retail",
            "subcategory":"Auto Repair",
            "type":"Services"
        }
    ],
    "sg:phone":"+1 415 585 1046",
    "sg:postcode":"94112",
    "sg:province":"CA",
    "wof:name":"Claudio's Auto Repair",
    "wof:placetype":"venue"
},
  "geometry": {"coordinates":[-122.43342699999999,37.726983],"type":"Point"}
}