{
  "type": "Feature",
  "properties": {
    "iso:country":"US",
    "sg:address":"44835 Deep Canyon Rd",
    "sg:city":"Palm Desert",
    "sg:classifiers":[
        {
            "category":"Building & Trades",
            "subcategory":"Construction",
            "type":"Services"
        }
    ],
    "sg:phone":"+1 760 346 3228",
    "sg:postcode":"92260",
    "sg:province":"CA",
    "sg:tags":[
        "contractor"
    ],
    "wof:name":"Andrew Pierce Corp",
    "wof:placetype":"venue"
},
  "geometry": {"coordinates":[-116.364998,33.722198],"type":"Point"}
}