{
  "type": "Feature",
  "properties": {
    "addr:full":"21340 Baechtel Rd Willits CA 95490",
    "addr:postcode":"21340;95490",
    "addr:street":"Baechtel Rd",
    "iso:country":"US",
    "sg:address":"21340 Baechtel Rd",
    "sg:city":"Willits",
    "sg:classifiers":[
        {
            "category":"Government",
            "subcategory":"Office",
            "type":"Public Place"
        }
    ],
    "sg:phone":"+1 707 459 2218",
    "sg:postcode":"95490",
    "sg:province":"CA",
    "sg:tags":[
        "state",
        "program"
    ],
    "wof:name":"Transportation Dept",
    "wof:placetype":"venue"
},
  "geometry": {"coordinates":[-123.344048,39.389627],"type":"Point"}
}