{
  "type": "Feature",
  "properties": {
    "iso:country":"US",
    "sg:address":"22834 Rd 211",
    "sg:city":"Friant",
    "sg:classifiers":[
        {
            "category":"Farming",
            "subcategory":"Livestock Farm",
            "type":"Manufacturing & Wholesale Goods"
        }
    ],
    "sg:phone":"+1 559 868 3610",
    "sg:postcode":"93626",
    "sg:province":"CA",
    "sg:tags":[
        "fish",
        "beef",
        "feedlot",
        "cattle"
    ],
    "wof:name":"Jones Ranch",
    "wof:placetype":"venue"
},
  "geometry": {"coordinates":[-119.69616000000001,37.089294],"type":"Point"}
}