{
  "type": "Feature",
  "properties": {
    "iso:country":"US",
    "sg:address":"5625 N Figueroa St",
    "sg:city":"Los Angeles",
    "sg:classifiers":[
        {
            "category":"Retail",
            "subcategory":"Portrait Studio",
            "type":"Services"
        }
    ],
    "sg:phone":"+1 323 255 1527",
    "sg:postcode":"90042",
    "sg:province":"CA",
    "sg:tags":[
        "photographer"
    ],
    "wof:name":"Modern Studio Of Photography",
    "wof:placetype":"venue"
},
  "geometry": {"coordinates":[-118.193121,34.109493],"type":"Point"}
}