{
  "type": "Feature",
  "properties": {
    "iso:country":"US",
    "sg:address":"40874 Cienega Pl",
    "sg:city":"Bermuda Dunes",
    "sg:classifiers":[
        {
            "category":"Building & Trades",
            "subcategory":"Construction",
            "type":"Services"
        }
    ],
    "sg:phone":"+1 760 345 5210",
    "sg:postcode":"92203",
    "sg:province":"CA",
    "sg:tags":[
        "fire",
        "restoration",
        "damage"
    ],
    "wof:name":"Servpro",
    "wof:placetype":"venue"
},
  "geometry": {"coordinates":[-116.29152499999999,33.752236],"type":"Point"}
}