{
  "type": "Feature",
  "properties": {
    "addr:full":"7701 White Ln Bakersfield CA 93309",
    "addr:housenumber":"7701",
    "addr:postcode":"93309",
    "addr:street":"White Ln",
    "iso:country":"US",
    "sg:address":"7701 White Ln",
    "sg:city":"Bakersfield",
    "sg:classifiers":[
        {
            "category":"Bars & Pubs",
            "type":"Food & Drink"
        }
    ],
    "sg:phone":"+1 661 397 6709",
    "sg:postcode":"93309",
    "sg:province":"CA",
    "wof:name":"Shear Sports",
    "wof:placetype":"venue"
},
  "geometry": {"coordinates":[-119.08775,35.318157],"type":"Point"}
}