{
  "type": "Feature",
  "properties": {
    "addr:full":"23736 Fambrough St Newhall CA 91321",
    "addr:postcode":"23736;91321",
    "addr:street":"Fambrough St",
    "iso:country":"US",
    "sg:address":"23736 Fambrough St",
    "sg:city":"Newhall",
    "sg:classifiers":[
        {
            "category":"Freight",
            "type":"Transportation"
        }
    ],
    "sg:phone":"+1 661 255 5762",
    "sg:postcode":"91321",
    "sg:province":"CA",
    "sg:tags":[
        "trucking"
    ],
    "wof:name":"Galloway Trucking",
    "wof:placetype":"venue"
},
  "geometry": {"coordinates":[-118.549504,34.367477],"type":"Point"}
}