{
  "type": "Feature",
  "properties": {
    "addr:full":"23 Wrangler Ct Trabuco Canyon CA 92679",
    "addr:housenumber":"23",
    "addr:postcode":"92679",
    "addr:street":"Wrangler Ct",
    "iso:country":"US",
    "sg:address":"23 Wrangler Ct",
    "sg:city":"Trabuco Canyon",
    "sg:classifiers":[
        {
            "category":"Wholesale",
            "subcategory":"Medical Equipment & Supplies",
            "type":"Manufacturing & Wholesale Goods"
        }
    ],
    "sg:phone":"+1 949 888 8385",
    "sg:postcode":"92679",
    "sg:province":"CA",
    "wof:name":"Harper Enterprises",
    "wof:placetype":"venue"
},
  "geometry": {"coordinates":[-117.59407400000001,33.588539],"type":"Point"}
}