{
  "type": "Feature",
  "properties": {
    "iso:country":"US",
    "sg:address":"4444 W Riverside Dr Ste 301",
    "sg:city":"Burbank",
    "sg:classifiers":[
        {
            "category":"Organizations",
            "subcategory":"Religious Organization",
            "type":"Services"
        },
        {
            "category":"Landmark",
            "subcategory":"Tourist Information",
            "type":"Public Place"
        }
    ],
    "sg:phone":"+1 818 848 9449",
    "sg:postcode":"91505",
    "sg:province":"CA",
    "sg:tags":[
        "tour"
    ],
    "sg:website":"www.catholictravelcentre.com",
    "wof:name":"Catholic Travel Centre",
    "wof:placetype":"venue"
},
  "geometry": {"coordinates":[-118.34899900000001,34.152199],"type":"Point"}
}