{
  "type": "Feature",
  "properties": {
    "iso:country":"US",
    "sg:address":"1170W National Dr",
    "sg:city":"Sacramento",
    "sg:classifiers":[
        {
            "category":"Building & Trades",
            "subcategory":"Pest Control",
            "type":"Services"
        }
    ],
    "sg:phone":"+1 916 928 1208",
    "sg:postcode":"95834",
    "sg:province":"CA",
    "sg:tags":[
        "industrial",
        "services-commercial"
    ],
    "sg:website":"www.pestdefense.com",
    "wof:name":"HomeTeam Pest Defense",
    "wof:placetype":"venue"
},
  "geometry": {"coordinates":[-121.48742300000001,38.644508],"type":"Point"}
}