{
  "type": "Feature",
  "properties": {
    "addr:full":"567 Floresta Blvd San Leandro CA 94578",
    "addr:housenumber":"567",
    "addr:postcode":"94578",
    "addr:street":"Floresta Blvd",
    "iso:country":"US",
    "sg:address":"567 Floresta Blvd",
    "sg:city":"San Leandro",
    "sg:classifiers":[
        {
            "category":"Health Services",
            "subcategory":"Chiropractor",
            "type":"Services"
        }
    ],
    "sg:phone":"+1 510 346 0711",
    "sg:postcode":"94578",
    "sg:province":"CA",
    "wof:name":"Spine & Sportcare Assoc",
    "wof:placetype":"venue"
},
  "geometry": {"coordinates":[-122.14156199999999,37.701842],"type":"Point"}
}