{
  "type": "Feature",
  "properties": {
    "addr:full":"7094 Miramar Rd San Diego CA 92121",
    "addr:housenumber":"7094",
    "addr:postcode":"92121",
    "addr:street":"Miramar Rd",
    "iso:country":"US",
    "sg:address":"7094 Miramar Rd",
    "sg:city":"San Diego",
    "sg:classifiers":[
        {
            "category":"Cafe",
            "type":"Food & Drink"
        }
    ],
    "sg:menulink":"http://www.allmenus.com/ca/san-diego/32467-j-js-deli--cafe/menu/",
    "sg:phone":"+1 858 693 8881",
    "sg:postcode":"92121",
    "sg:province":"CA",
    "sg:tags":[
        "american"
    ],
    "wof:name":"J J's Deli & Cafe",
    "wof:placetype":"venue"
},
  "geometry": {"coordinates":[-117.161845,32.879114],"type":"Point"}
}