{
  "type": "Feature",
  "properties": {
    "addr:full":"3 Laurelglen Irvine CA 92614",
    "addr:housenumber":"3",
    "addr:postcode":"92614",
    "addr:street":"Laurelglen",
    "iso:country":"US",
    "sg:address":"3 Laurelglen",
    "sg:city":"Irvine",
    "sg:classifiers":[
        {
            "category":"Shopping",
            "subcategory":"Hobbies, Toys, & Games",
            "type":"Retail Goods"
        }
    ],
    "sg:phone":"+1 949 733 1374",
    "sg:postcode":"92614",
    "sg:province":"CA",
    "wof:name":"Joyce Memories",
    "wof:placetype":"venue"
},
  "geometry": {"coordinates":[-117.801215,33.670801],"type":"Point"}
}