{
  "type": "Feature",
  "properties": {
    "addr:full":"6670 Amador Plaza Rd Dublin CA 94568",
    "addr:housenumber":"6670",
    "addr:postcode":"94568",
    "addr:street":"Amador Plaza Rd",
    "iso:country":"US",
    "sg:address":"6670 Amador Plaza Rd",
    "sg:city":"Dublin",
    "sg:classifiers":[
        {
            "category":"Manufacturing",
            "subcategory":"Tools & Machinery",
            "type":"Manufacturing & Wholesale Goods"
        }
    ],
    "sg:phone":"+1 415 828 8525",
    "sg:postcode":"94568",
    "sg:province":"CA",
    "sg:tags":[
        "electrical",
        "mfg"
    ],
    "wof:name":"Authentication Technologies",
    "wof:placetype":"venue"
},
  "geometry": {"coordinates":[-121.926152,37.703399],"type":"Point"}
}