{
  "type": "Feature",
  "properties": {
    "addr:full":"7015 Oak Forest Ct Bakersfield CA 93313",
    "addr:housenumber":"7015",
    "addr:postcode":"93313",
    "addr:street":"Oak Forest Ct",
    "iso:country":"US",
    "sg:address":"7015 Oak Forest Ct",
    "sg:city":"Bakersfield",
    "sg:classifiers":[
        {
            "category":"Freight",
            "type":"Transportation"
        }
    ],
    "sg:phone":"+1 661 201 3163",
    "sg:postcode":"93313",
    "sg:province":"CA",
    "sg:tags":[
        "operator",
        "local",
        "trucking"
    ],
    "wof:name":"N & S Trucking",
    "wof:placetype":"venue"
},
  "geometry": {"coordinates":[-119.04825700000001,35.291018],"type":"Point"}
}