{
  "type": "Feature",
  "properties": {
    "iso:country":"US",
    "sg:address":"281 E Hamilton Ave",
    "sg:city":"Campbell",
    "sg:classifiers":[
        {
            "category":"Wholesale",
            "subcategory":"Computers",
            "type":"Manufacturing & Wholesale Goods"
        }
    ],
    "sg:phone":"+1 408 376 3950",
    "sg:postcode":"95008",
    "sg:province":"CA",
    "wof:name":"Teac America Inc",
    "wof:placetype":"venue"
},
  "geometry": {"coordinates":[-121.946363,37.29424],"type":"Point"}
}