{
  "type": "Feature",
  "properties": {
    "iso:country":"US",
    "sg:address":"1513 W Sepulveda Blvd Unit A",
    "sg:city":"Torrance",
    "sg:classifiers":[
        {
            "category":"Recreation",
            "type":"Entertainment"
        }
    ],
    "sg:phone":"+1 310 534 9600",
    "sg:postcode":"90501",
    "sg:province":"CA",
    "sg:tags":[
        "active",
        "life"
    ],
    "sg:website":"www.robofit.net/",
    "wof:name":"RoboFit Table Tennis Center",
    "wof:placetype":"venue"
},
  "geometry": {"coordinates":[-118.304323,33.815432],"type":"Point"}
}