{
  "type": "Feature",
  "properties": {
    "addr:full":"899 Grand Ave Grover Beach CA 93433",
    "addr:housenumber":"899",
    "addr:postcode":"93433",
    "addr:street":"Grand Ave",
    "iso:country":"US",
    "sg:address":"899 Grand Ave",
    "sg:city":"Grover Beach",
    "sg:classifiers":[
        {
            "category":"Banks & Credit Unions",
            "subcategory":"Bank",
            "type":"Services"
        }
    ],
    "sg:phone":"+1 805 489 1336",
    "sg:postcode":"93433",
    "sg:province":"CA",
    "sg:website":"www.msb.com",
    "wof:name":"Mid-State Bank & Trust",
    "wof:placetype":"venue"
},
  "geometry": {"coordinates":[-120.620231,35.121519],"type":"Point"}
}