{
  "type": "Feature",
  "properties": {
    "iso:country":"US",
    "sg:address":"1326 W Hillsdale Blvd",
    "sg:city":"San Mateo",
    "sg:classifiers":[
        {
            "category":"Restaurant",
            "type":"Food & Drink"
        }
    ],
    "sg:phone":"+1 650 349 6464",
    "sg:postcode":"94403",
    "sg:province":"CA",
    "sg:tags":[
        "mexican"
    ],
    "sg:website":"www.laurelwoodcenter.com",
    "wof:name":"Laurelwood Shopping Center",
    "wof:placetype":"venue"
},
  "geometry": {"coordinates":[-122.327091,37.533164],"type":"Point"}
}