{
  "type": "Feature",
  "properties": {
    "addr:full":"2757 Melendy Dr San Carlos CA 94070",
    "addr:housenumber":"2757",
    "addr:postcode":"94070",
    "addr:street":"Melendy Dr",
    "iso:country":"US",
    "sg:address":"2757 Melendy Dr",
    "sg:city":"San Carlos",
    "sg:classifiers":[
        {
            "category":"Education",
            "subcategory":"School",
            "type":"Public Place"
        }
    ],
    "sg:phone":"+1 650 508 7303",
    "sg:postcode":"94070",
    "sg:province":"CA",
    "wof:name":"Heather School",
    "wof:placetype":"venue"
},
  "geometry": {"coordinates":[-122.275097,37.49301],"type":"Point"}
}