{
  "type": "Feature",
  "properties": {
    "iso:country":"US",
    "sg:address":"326 Phelan Ave",
    "sg:city":"San Jose",
    "sg:classifiers":[
        {
            "category":"Building & Trades",
            "subcategory":"Plumbing",
            "type":"Services"
        }
    ],
    "sg:phone":"+1 408 282 7020",
    "sg:postcode":"95112",
    "sg:province":"CA",
    "sg:tags":[
        "plumbing",
        "contractor"
    ],
    "wof:name":"All Star Plumbing",
    "wof:placetype":"venue"
},
  "geometry": {"coordinates":[-121.864444,37.314175],"type":"Point"}
}