{
  "type": "Feature",
  "properties": {
    "addr:full":"750 S Sanderson Ave Hemet CA 92545",
    "addr:housenumber":"750",
    "addr:postcode":"92545",
    "addr:street":"S Sanderson Ave",
    "iso:country":"US",
    "sg:address":"750 S Sanderson Ave",
    "sg:city":"Hemet",
    "sg:classifiers":[
        {
            "category":"Freight",
            "type":"Transportation"
        }
    ],
    "sg:phone":"+1 951 652 2222",
    "sg:postcode":"92545",
    "sg:province":"CA",
    "sg:tags":[
        "paper",
        "general"
    ],
    "wof:name":"Storage USA",
    "wof:placetype":"venue"
},
  "geometry": {"coordinates":[-117.00657200000001,33.735243],"type":"Point"}
}