{
  "type": "Feature",
  "properties": {
    "iso:country":"US",
    "sg:address":"3140 Bear St",
    "sg:city":"Costa Mesa",
    "sg:classifiers":[
        {
            "category":"Health Services",
            "subcategory":"Chiropractor",
            "type":"Services"
        }
    ],
    "sg:phone":"+1 714 432 7777",
    "sg:postcode":"92626",
    "sg:province":"CA",
    "wof:name":"Wood Gregory DC",
    "wof:placetype":"venue"
},
  "geometry": {"coordinates":[-117.891998,33.685398],"type":"Point"}
}