{
  "type": "Feature",
  "properties": {
    "iso:country":"US",
    "sg:address":"Noe St and 25th St",
    "sg:city":"San Francisco",
    "sg:classifiers":[
        {
            "category":"Banks & Credit Unions",
            "subcategory":"Financial Services",
            "type":"Services"
        }
    ],
    "sg:phone":"+1 415 425 1615",
    "sg:postcode":"94114",
    "sg:province":"CA",
    "sg:tags":[
        "advising"
    ],
    "sg:website":"unconditionalfinancialserenity.w...",
    "wof:name":"Unconditional Financial Serenity",
    "wof:placetype":"venue"
},
  "geometry": {"coordinates":[-122.43172199999999,37.749835],"type":"Point"}
}