{
  "type": "Feature",
  "properties": {
    "iso:country":"US",
    "sg:address":"950 Northgate Dr",
    "sg:city":"San Rafael",
    "sg:classifiers":[
        {
            "category":"Professional",
            "subcategory":"Lawyer & Legal Services",
            "type":"Services"
        }
    ],
    "sg:phone":"+1 415 491 9500",
    "sg:postcode":"94903",
    "sg:province":"CA",
    "sg:tags":[
        "attorney"
    ],
    "wof:name":"William P Lynch Jr",
    "wof:placetype":"venue"
},
  "geometry": {"coordinates":[-122.54555000000001,38.007356],"type":"Point"}
}