{
  "type": "Feature",
  "properties": {
    "iso:country":"US",
    "sg:address":"1441 Stockton St",
    "sg:city":"San Francisco",
    "sg:classifiers":[
        {
            "category":"Coffee & Tea",
            "type":"Food & Drink"
        }
    ],
    "sg:phone":"+1 415 421 4219",
    "sg:postcode":"94133",
    "sg:province":"CA",
    "sg:website":"cavallicafe.com",
    "wof:name":"Cavalli Caffe & Imports",
    "wof:placetype":"venue"
},
  "geometry": {"coordinates":[-122.40917399999999,37.799105],"type":"Point"}
}