{
  "type": "Feature",
  "properties": {
    "iso:country":"US",
    "sg:address":"260 S Motor Ave",
    "sg:city":"Azusa",
    "sg:classifiers":[
        {
            "category":"Retail",
            "subcategory":"Repair Shop",
            "type":"Services"
        }
    ],
    "sg:phone":"+1 626 833 3415",
    "sg:postcode":"91702",
    "sg:province":"CA",
    "sg:tags":[
        "welding"
    ],
    "wof:name":"Mobile Weld",
    "wof:placetype":"venue"
},
  "geometry": {"coordinates":[-117.934816,34.11877],"type":"Point"}
}