{
  "type": "Feature",
  "properties": {
    "addr:full":"2200 Grand Ave Sacramento CA 95838",
    "addr:housenumber":"2200",
    "addr:postcode":"95838",
    "addr:street":"Grand Ave",
    "iso:country":"US",
    "sg:address":"2200 Grand Ave",
    "sg:city":"Sacramento",
    "sg:classifiers":[
        {
            "category":"Autos & Motor Vehicles",
            "subcategory":"Automobile Sales",
            "type":"Retail Goods"
        }
    ],
    "sg:phone":"+1 916 801 4891",
    "sg:postcode":"95838",
    "sg:province":"CA",
    "sg:tags":[
        "car",
        "dealer"
    ],
    "wof:name":"A Few Good Cars",
    "wof:placetype":"venue"
},
  "geometry": {"coordinates":[-121.413777,38.636451],"type":"Point"}
}