{
  "type": "Feature",
  "properties": {
    "addr:full":"634 25th Street San Diego CA 92102",
    "addr:housenumber":"634",
    "addr:postcode":"92102",
    "addr:street":"25Th Street",
    "iso:country":"US",
    "sg:address":"634 25th Street",
    "sg:city":"San Diego",
    "sg:classifiers":[
        {
            "category":"Personal",
            "subcategory":"Barber",
            "type":"Services"
        }
    ],
    "sg:phone":"+1 619 231 1245",
    "sg:postcode":"92102",
    "sg:province":"CA",
    "wof:name":"Maricela Beauty Salon",
    "wof:placetype":"venue"
},
  "geometry": {"coordinates":[-117.140114,32.712428],"type":"Point"}
}