{
  "type": "Feature",
  "properties": {
    "addr:full":"3321 Foothill Blvd Oakland CA 94620",
    "addr:housenumber":"3321",
    "addr:postcode":"94620",
    "addr:street":"Foothill Blvd",
    "iso:country":"US",
    "sg:address":"3321 Foothill Blvd",
    "sg:city":"Oakland",
    "sg:classifiers":[
        {
            "category":"Food & Beverages",
            "subcategory":"Groceries & Convenience Stores",
            "type":"Retail Goods"
        }
    ],
    "sg:phone":"+1 510 533 3888",
    "sg:postcode":"94620",
    "sg:province":"CA",
    "wof:name":"East Bay Supermarket",
    "wof:placetype":"venue"
},
  "geometry": {"coordinates":[-122.249509,37.794862],"type":"Point"}
}