{
  "type": "Feature",
  "properties": {
    "iso:country":"US",
    "sg:address":"37275 Dondero Way",
    "sg:city":"Fremont",
    "sg:classifiers":[
        {
            "category":"Building & Trades",
            "subcategory":"Construction",
            "type":"Services"
        }
    ],
    "sg:phone":"+1 510 742 9701",
    "sg:postcode":"94536",
    "sg:province":"CA",
    "sg:tags":[
        "builder",
        "deck"
    ],
    "wof:name":"David William Arkley Handyman",
    "wof:placetype":"venue"
},
  "geometry": {"coordinates":[-122.020077,37.54928],"type":"Point"}
}