{
  "type": "Feature",
  "properties": {
    "iso:country":"US",
    "sg:address":"2891 Brandeis Dr",
    "sg:city":"Oceanside",
    "sg:classifiers":[
        {
            "category":"Organizations",
            "subcategory":"Professional Association",
            "type":"Services"
        }
    ],
    "sg:phone":"+1 760 722 1959",
    "sg:postcode":"92056",
    "sg:province":"CA",
    "wof:name":"International Evangelism Assn",
    "wof:placetype":"venue"
},
  "geometry": {"coordinates":[-117.302989,33.195603],"type":"Point"}
}