{
  "type": "Feature",
  "properties": {
    "addr:full":"3856 Wilson Ave Castro Valley CA 94546",
    "addr:housenumber":"3856",
    "addr:postcode":"94546",
    "addr:street":"Wilson Ave",
    "iso:country":"US",
    "sg:address":"3856 Wilson Ave",
    "sg:city":"Castro Valley",
    "sg:classifiers":[
        {
            "category":"Professional",
            "type":"Services"
        }
    ],
    "sg:phone":"+1 510 538 3400",
    "sg:postcode":"94546",
    "sg:province":"CA",
    "wof:name":"PCL",
    "wof:placetype":"venue"
},
  "geometry": {"coordinates":[-122.081243,37.707977],"type":"Point"}
}