{
  "type": "Feature",
  "properties": {
    "iso:country":"US",
    "sg:address":"523 4th St",
    "sg:city":"San Rafael",
    "sg:classifiers":[
        {
            "category":"Banks & Credit Unions",
            "subcategory":"Bank",
            "type":"Services"
        }
    ],
    "sg:phone":"+1 415 451 4888",
    "sg:postcode":"94901",
    "sg:province":"CA",
    "sg:tags":[
        "loan",
        "real estate"
    ],
    "wof:name":"California Mortgage Advisors",
    "wof:placetype":"venue"
},
  "geometry": {"coordinates":[-122.520253,37.972088],"type":"Point"}
}