{
  "type": "Feature",
  "properties": {
    "addr:full":"721 Colorado Ave Palo Alto CA 94303",
    "addr:housenumber":"721",
    "addr:postcode":"94303",
    "addr:street":"Colorado Ave",
    "iso:country":"US",
    "sg:address":"721 Colorado Ave",
    "sg:city":"Palo Alto",
    "sg:classifiers":[
        {
            "category":"Professional",
            "subcategory":"Lawyer & Legal Services",
            "type":"Services"
        }
    ],
    "sg:phone":"+1 650 321 1400",
    "sg:postcode":"94303",
    "sg:province":"CA",
    "sg:tags":[
        "attorney"
    ],
    "wof:name":"Brooks & Raub",
    "wof:placetype":"venue"
},
  "geometry": {"coordinates":[-122.128231,37.433227],"type":"Point"}
}