{
  "type": "Feature",
  "properties": {
    "iso:country":"US",
    "sg:address":"2924 E Cesar E Chavez Avenue",
    "sg:city":"Los Angeles",
    "sg:classifiers":[
        {
            "category":"Restaurant",
            "type":"Food & Drink"
        }
    ],
    "sg:phone":"+1 323 263 9949",
    "sg:postcode":"90033",
    "sg:province":"CA",
    "sg:tags":[
        "pizza"
    ],
    "sg:website":"www.lapizzaloca.com",
    "wof:name":"La Pizza Loca",
    "wof:placetype":"venue"
},
  "geometry": {"coordinates":[-118.200873,34.043632],"type":"Point"}
}