{
  "type": "Feature",
  "properties": {
    "addr:full":"149 Grove St Watsonville CA 95076",
    "addr:housenumber":"149",
    "addr:postcode":"95076",
    "addr:street":"Grove St",
    "iso:country":"US",
    "sg:address":"149 Grove St",
    "sg:city":"Watsonville",
    "sg:classifiers":[
        {
            "category":"Manufacturing",
            "subcategory":"Glass & Minerals",
            "type":"Manufacturing & Wholesale Goods"
        }
    ],
    "sg:phone":"+1 831 722 2241",
    "sg:postcode":"95076",
    "sg:province":"CA",
    "sg:tags":[
        "product",
        "marble"
    ],
    "wof:name":"Riva Marble & Granite",
    "wof:placetype":"venue"
},
  "geometry": {"coordinates":[-121.754707,36.904671],"type":"Point"}
}