{
  "type": "Feature",
  "properties": {
    "iso:country":"US",
    "sg:address":"942 E Holt Ave",
    "sg:city":"Pomona",
    "sg:classifiers":[
        {
            "category":"Professional",
            "subcategory":"Accounting & Tax Preparation",
            "type":"Services"
        }
    ],
    "sg:phone":"+1 909 620 6762",
    "sg:postcode":"91767",
    "sg:province":"CA",
    "sg:tags":[
        "travel",
        "agency",
        "return",
        "immigration",
        "se"
    ],
    "wof:name":"Zamora Services",
    "wof:placetype":"venue"
},
  "geometry": {"coordinates":[-117.732705,34.062733],"type":"Point"}
}