{
  "type": "Feature",
  "properties": {
    "iso:country":"US",
    "sg:address":"4212 Windgate Dr",
    "sg:city":"Denair",
    "sg:classifiers":[
        {
            "category":"Professional",
            "type":"Services"
        }
    ],
    "sg:phone":"+1 209 667 6139",
    "sg:postcode":"95316",
    "sg:province":"CA",
    "wof:name":"Angel One",
    "wof:placetype":"venue"
},
  "geometry": {"coordinates":[-120.80101500000001,37.532135],"type":"Point"}
}