{
  "type": "Feature",
  "properties": {
    "addr:full":"3463 Ocean View Blvd Glendale CA 91208",
    "addr:housenumber":"3463",
    "addr:postcode":"91208",
    "addr:street":"Ocean View Blvd",
    "iso:country":"US",
    "sg:address":"3463 Ocean View Blvd",
    "sg:city":"Glendale",
    "sg:classifiers":[
        {
            "category":"Building & Trades",
            "subcategory":"Construction",
            "type":"Services"
        }
    ],
    "sg:phone":"+1 818 236 3999",
    "sg:postcode":"91208",
    "sg:province":"CA",
    "sg:tags":[
        "contractor"
    ],
    "wof:name":"Cousens Construction Inc",
    "wof:placetype":"venue"
},
  "geometry": {"coordinates":[-118.227997,34.200802],"type":"Point"}
}