{
  "type": "Feature",
  "properties": {
    "iso:country":"US",
    "sg:address":"1237 Prospect St Ste W",
    "sg:city":"La Jolla",
    "sg:classifiers":[
        {
            "category":"Arts & Performance",
            "subcategory":"Art Gallery",
            "type":"Entertainment"
        }
    ],
    "sg:phone":"+1 858 551 4555",
    "sg:postcode":"92037",
    "sg:province":"CA",
    "wof:name":"Derissi Design Studio & Art Gallery",
    "wof:placetype":"venue"
},
  "geometry": {"coordinates":[-117.271691,32.848766],"type":"Point"}
}