{
  "type": "Feature",
  "properties": {
    "addr:full":"3100 N Demaree St Visalia CA 93291",
    "addr:housenumber":"3100",
    "addr:postcode":"93291",
    "addr:street":"N Demaree St",
    "iso:country":"US",
    "sg:address":"3100 N Demaree St",
    "sg:city":"Visalia",
    "sg:classifiers":[
        {
            "category":"Personal",
            "subcategory":"Nail Salon",
            "type":"Services"
        }
    ],
    "sg:phone":"+1 559 733 8888",
    "sg:postcode":"93291",
    "sg:province":"CA",
    "wof:name":"Hand 2 Love",
    "wof:placetype":"venue"
},
  "geometry": {"coordinates":[-119.33203899999999,36.357406],"type":"Point"}
}