{
  "type": "Feature",
  "properties": {
    "addr:full":"Conversely, Inc.  395 Page Mill Rd Palo Alto CA 94306",
    "addr:housenumber":"395",
    "addr:postcode":"94306",
    "addr:street":"Page Mill Rd",
    "iso:country":"US",
    "sg:address":"Conversely, Inc.  395 Page Mill Rd",
    "sg:city":"Palo Alto",
    "sg:classifiers":[
        {
            "category":"Professional",
            "subcategory":"Computer Services",
            "type":"Services"
        }
    ],
    "sg:phone":"+1 650 427 0678",
    "sg:postcode":"94306",
    "sg:province":"CA",
    "sg:tags":[
        "social-media",
        "analytics",
        "social-media-marketing",
        "twitter",
        "social-media-optimization"
    ],
    "sg:website":"http://crowdbooster.com",
    "wof:name":"Crowdbooster",
    "wof:placetype":"venue"
},
  "geometry": {"coordinates":[-122.13959,37.42584],"type":"Point"}
}