{
  "type": "Feature",
  "properties": {
    "addr:full":"17515 Hwy 116 Guerneville CA 95446",
    "addr:housenumber":"17515",
    "addr:postcode":"95446",
    "addr:street":"Hwy 116",
    "iso:country":"US",
    "sg:address":"17515 Hwy 116",
    "sg:city":"Guerneville",
    "sg:classifiers":[
        {
            "category":"Travel",
            "subcategory":"Hotels & Motels",
            "type":"Entertainment"
        }
    ],
    "sg:phone":"+1 415 606 2737",
    "sg:postcode":"95446",
    "sg:province":"CA",
    "sg:tags":[
        "house",
        "guest"
    ],
    "sg:website":"www.vrbo.com/303089",
    "wof:name":"Your Russian River House",
    "wof:placetype":"venue"
},
  "geometry": {"coordinates":[-123.01508,38.492287],"type":"Point"}
}