{
  "type": "Feature",
  "properties": {
    "iso:country":"US",
    "sg:address":"22724 Hawthorne Blvd",
    "sg:city":"Torrance",
    "sg:classifiers":[
        {
            "category":"Education",
            "subcategory":"School",
            "type":"Public Place"
        }
    ],
    "sg:phone":"+1 310 791 5655",
    "sg:postcode":"90505",
    "sg:province":"CA",
    "sg:tags":[
        "high",
        "middle",
        "elementary"
    ],
    "wof:name":"Mr SAT",
    "wof:placetype":"venue"
},
  "geometry": {"coordinates":[-118.350808,33.822],"type":"Point"}
}