{
  "type": "Feature",
  "properties": {
    "iso:country":"US",
    "sg:address":"9020 Beverly Blvd",
    "sg:city":"Los Angeles",
    "sg:classifiers":[
        {
            "category":"Home & Garden",
            "subcategory":"Furniture",
            "type":"Retail Goods"
        }
    ],
    "sg:phone":"+1 310 385 8645",
    "sg:postcode":"90048",
    "sg:province":"CA",
    "sg:tags":[
        "store"
    ],
    "sg:website":"www.dkvogue.com",
    "wof:name":"dkVogue",
    "wof:placetype":"venue"
},
  "geometry": {"coordinates":[-118.3888,34.07717],"type":"Point"}
}