{
  "type": "Feature",
  "properties": {
    "iso:country":"US",
    "sg:address":"16225 Alum Rock Ave",
    "sg:city":"San Jose",
    "sg:classifiers":[
        {
            "category":"Personal",
            "type":"Services"
        },
        {
            "category":"Education",
            "subcategory":"School",
            "type":"Public Place"
        },
        {
            "category":"Recreation",
            "type":"Entertainment"
        }
    ],
    "sg:phone":"+1 408 887 4573",
    "sg:postcode":"95127",
    "sg:province":"CA",
    "sg:tags":[
        "active",
        "life",
        "local"
    ],
    "wof:name":"Alum Rock Riding Academy",
    "wof:placetype":"venue"
},
  "geometry": {"coordinates":[-121.81740600000001,37.39229],"type":"Point"}
}