{
  "type": "Feature",
  "properties": {
    "addr:full":"12755 Van Nuys Blvd Pacoima CA 91331",
    "addr:housenumber":"12755",
    "addr:postcode":"91331",
    "addr:street":"Van Nuys Blvd",
    "iso:country":"US",
    "sg:address":"12755 Van Nuys Blvd",
    "sg:city":"Pacoima",
    "sg:classifiers":[
        {
            "category":"Shopping",
            "subcategory":"Discount & Variety Stores",
            "type":"Retail Goods"
        }
    ],
    "sg:phone":"+1 818 834 7440",
    "sg:postcode":"91331",
    "sg:province":"CA",
    "sg:tags":[
        "merchandise",
        "general"
    ],
    "wof:name":"General Discount",
    "wof:placetype":"venue"
},
  "geometry": {"coordinates":[-118.41024,34.275061],"type":"Point"}
}