{
  "type": "Feature",
  "properties": {
    "iso:country":"US",
    "sg:address":"1106 Alameda de Las Pulgas",
    "sg:city":"San Carlos",
    "sg:classifiers":[
        {
            "category":"Organizations",
            "subcategory":"Religious Organization",
            "type":"Services"
        }
    ],
    "sg:phone":"+1 650 593 8226",
    "sg:postcode":"94070",
    "sg:province":"CA",
    "sg:tags":[
        "church"
    ],
    "sg:website":"www.trinity-pres.org",
    "wof:name":"Trinity Presbyterian Church",
    "wof:placetype":"venue"
},
  "geometry": {"coordinates":[-122.264608,37.490282],"type":"Point"}
}