{
  "type": "Feature",
  "properties": {
    "addr:full":"4125 Temescal St Fair Oaks CA 95628",
    "addr:housenumber":"4125",
    "addr:postcode":"95628",
    "addr:street":"Temescal St",
    "iso:country":"US",
    "sg:address":"4125 Temescal St",
    "sg:city":"Fair Oaks",
    "sg:classifiers":[
        {
            "category":"Real Estate",
            "subcategory":"Developer",
            "type":"Services"
        },
        {
            "category":"Building & Trades",
            "subcategory":"Construction",
            "type":"Services"
        }
    ],
    "sg:phone":"+1 916 961 9300",
    "sg:postcode":"95628",
    "sg:province":"CA",
    "sg:tags":[
        "affordable",
        "housing",
        "an",
        "to",
        "low",
        "income"
    ],
    "wof:name":"Affordable Home Solutions",
    "wof:placetype":"venue"
},
  "geometry": {"coordinates":[-121.268652,38.640427],"type":"Point"}
}