{
  "type": "Feature",
  "properties": {
    "iso:country":"US",
    "sg:address":"416 Oak St",
    "sg:city":"Laguna Beach",
    "sg:classifiers":[
        {
            "category":"Manufacturing",
            "subcategory":"Food",
            "type":"Manufacturing & Wholesale Goods"
        },
        {
            "category":"Wholesale",
            "subcategory":"Groceries",
            "type":"Manufacturing & Wholesale Goods"
        }
    ],
    "sg:phone":"+1 949 494 5800",
    "sg:postcode":"92651",
    "sg:province":"CA",
    "sg:tags":[
        "confectionery",
        "candy"
    ],
    "wof:name":"Ted's Treats",
    "wof:placetype":"venue"
},
  "geometry": {"coordinates":[-117.773387,33.536106],"type":"Point"}
}