{
  "type": "Feature",
  "properties": {
    "addr:full":"121 Broadway Ste 334 San Diego CA 92101",
    "addr:housenumber":"121",
    "addr:postcode":"92101",
    "addr:street":"Broadway Ste 334",
    "iso:country":"US",
    "sg:address":"121 Broadway Ste 334",
    "sg:city":"San Diego",
    "sg:classifiers":[
        {
            "category":"Shopping",
            "subcategory":"Florist",
            "type":"Retail Goods"
        }
    ],
    "sg:phone":"+1 619 677 4471",
    "sg:postcode":"92101",
    "sg:province":"CA",
    "sg:website":"www.sandiegocityflorist.com",
    "wof:name":"San Diego City Florist",
    "wof:placetype":"venue"
},
  "geometry": {"coordinates":[-117.163352,32.715022],"type":"Point"}
}