{
  "type": "Feature",
  "properties": {
    "iso:country":"US",
    "sg:address":"22455 Maple Ct",
    "sg:city":"Hayward",
    "sg:classifiers":[
        {
            "category":"Professional",
            "subcategory":"Accounting & Tax Preparation",
            "type":"Services"
        }
    ],
    "sg:phone":"+1 510 889 8885",
    "sg:postcode":"94541",
    "sg:province":"CA",
    "sg:tags":[
        "return",
        "filing"
    ],
    "wof:name":"Eva Smith & Assoc",
    "wof:placetype":"venue"
},
  "geometry": {"coordinates":[-122.083359,37.675753],"type":"Point"}
}