{
  "type": "Feature",
  "properties": {
    "addr:full":"700 Balra Dr El Cerrito CA 94530",
    "addr:housenumber":"700",
    "addr:postcode":"94530",
    "addr:street":"Balra Dr",
    "iso:country":"US",
    "sg:address":"700 Balra Dr",
    "sg:city":"El Cerrito",
    "sg:classifiers":[
        {
            "category":"Communications",
            "type":"Services"
        }
    ],
    "sg:phone":"+1 510 524 9327",
    "sg:postcode":"94530",
    "sg:province":"CA",
    "sg:tags":[
        "web",
        "design"
    ],
    "wof:name":"CG Media EC",
    "wof:placetype":"venue"
},
  "geometry": {"coordinates":[-122.29179600000001,37.909886],"type":"Point"}
}