{
  "type": "Feature",
  "properties": {
    "addr:full":"233 E Harris Ave South San Francisco CA 94080",
    "addr:housenumber":"233",
    "addr:postcode":"94080",
    "addr:street":"E Harris Ave",
    "iso:country":"US",
    "sg:address":"233 E Harris Ave",
    "sg:city":"South San Francisco",
    "sg:classifiers":[
        {
            "category":"Manufacturing",
            "subcategory":"Food",
            "type":"Manufacturing & Wholesale Goods"
        }
    ],
    "sg:phone":"+1 650 875 1200",
    "sg:postcode":"94080",
    "sg:province":"CA",
    "sg:tags":[
        "a",
        "line",
        "beverage",
        "syrup",
        "flavored"
    ],
    "wof:name":"Torani Specility Beverages",
    "wof:placetype":"venue"
},
  "geometry": {"coordinates":[-122.39977,37.650573],"type":"Point"}
}