{
  "type": "Feature",
  "properties": {
    "iso:country":"US",
    "sg:address":"5215 Green River Rd",
    "sg:city":"Corona",
    "sg:phone":"+1 951 737 7393",
    "sg:postcode":"92880",
    "sg:province":"CA",
    "sg:website":"http://www.playgreenriver.com",
    "wof:name":"Green River Golf Club",
    "wof:placetype":"venue"
},
  "geometry": {"coordinates":[-117.670603,33.87046],"type":"Point"}
}