{
  "type": "Feature",
  "properties": {
    "addr:full":"1511 Offshore St Oxnard CA 93035",
    "addr:housenumber":"1511",
    "addr:postcode":"93035",
    "addr:street":"Offshore St",
    "iso:country":"US",
    "sg:address":"1511 Offshore St",
    "sg:city":"Oxnard",
    "sg:classifiers":[
        {
            "category":"Health Services",
            "subcategory":"Nursing And Care Facility",
            "type":"Services"
        }
    ],
    "sg:phone":"+1 805 985 5995",
    "sg:postcode":"93035",
    "sg:province":"CA",
    "sg:tags":[
        "home",
        "convalescent"
    ],
    "wof:name":"Las Posas Care Homes",
    "wof:placetype":"venue"
},
  "geometry": {"coordinates":[-119.214623,34.185518],"type":"Point"}
}