{
  "type": "Feature",
  "properties": {
    "addr:full":"708 E Manchester Blvd Inglewood CA 90301",
    "addr:housenumber":"708",
    "addr:postcode":"90301",
    "addr:street":"E Manchester Blvd",
    "iso:country":"US",
    "sg:address":"708 E Manchester Blvd",
    "sg:city":"Inglewood",
    "sg:classifiers":[
        {
            "category":"Real Estate",
            "subcategory":"Real Estate Agent",
            "type":"Services"
        }
    ],
    "sg:phone":"+1 310 330 0208",
    "sg:postcode":"90301",
    "sg:province":"CA",
    "wof:name":"Novo Realty",
    "wof:placetype":"venue"
},
  "geometry": {"coordinates":[-118.34626400000001,33.959926],"type":"Point"}
}