{
  "type": "Feature",
  "properties": {
    "iso:country":"US",
    "sg:address":"2249 Irving St",
    "sg:city":"San Francisco",
    "sg:classifiers":[
        {
            "category":"Restaurant",
            "type":"Food & Drink"
        }
    ],
    "sg:menulink":"http://www.allmenus.com/ca/san-francisco/44901-happy-bakery/menu/",
    "sg:phone":"+1 415 661 1386",
    "sg:postcode":"94122",
    "sg:province":"CA",
    "sg:tags":[
        "dim",
        "sum",
        "asian"
    ],
    "wof:name":"Happy Bakery",
    "wof:placetype":"venue"
},
  "geometry": {"coordinates":[-122.48199,37.76341],"type":"Point"}
}