{
  "type": "Feature",
  "properties": {
    "iso:country":"US",
    "sg:address":"3355 Via Lido",
    "sg:city":"Newport Beach",
    "sg:classifiers":[
        {
            "category":"Personal",
            "subcategory":"Barber",
            "type":"Services"
        }
    ],
    "sg:phone":"+1 949 673 2022",
    "sg:postcode":"92663",
    "sg:province":"CA",
    "wof:name":"Californian Men's Hair Designs",
    "wof:placetype":"venue"
},
  "geometry": {"coordinates":[-117.92800099999999,33.617199],"type":"Point"}
}