{
  "type": "Feature",
  "properties": {
    "iso:country":"US",
    "sg:address":"1553 W 8th Street",
    "sg:city":"Los Angeles",
    "sg:classifiers":[
        {
            "category":"Food & Beverages",
            "subcategory":"Liquor & Beverages",
            "type":"Retail Goods"
        }
    ],
    "sg:phone":"+1 213 483 3422",
    "sg:postcode":"90017",
    "sg:province":"CA",
    "sg:tags":[
        "beer",
        "spirit",
        "wine"
    ],
    "wof:name":"J & Y Liquor",
    "wof:placetype":"venue"
},
  "geometry": {"coordinates":[-118.272122,34.052183],"type":"Point"}
}