{
  "type": "Feature",
  "properties": {
    "iso:country":"US",
    "sg:address":"1631 4th St",
    "sg:city":"Eureka",
    "sg:classifiers":[
        {
            "category":"Home & Garden",
            "subcategory":"Furniture",
            "type":"Retail Goods"
        }
    ],
    "sg:phone":"+1 707 442 4510",
    "sg:postcode":"95501",
    "sg:province":"CA",
    "wof:name":"Delta Mattress & Sofa Outl Str",
    "wof:placetype":"venue"
},
  "geometry": {"coordinates":[-124.153907,40.804775],"type":"Point"}
}