{
  "type": "Feature",
  "properties": {
    "iso:country":"US",
    "sg:address":"17870 Rowland St",
    "sg:city":"Rowland Heights",
    "sg:classifiers":[
        {
            "category":"Wholesale",
            "subcategory":"Machinery & Supplies",
            "type":"Manufacturing & Wholesale Goods"
        }
    ],
    "sg:phone":"+1 626 912 8606",
    "sg:postcode":"91748",
    "sg:province":"CA",
    "sg:tags":[
        "steel",
        "cord"
    ],
    "wof:name":"Ping Ya Corporation",
    "wof:placetype":"venue"
},
  "geometry": {"coordinates":[-117.915215,34.001292],"type":"Point"}
}