{
  "type": "Feature",
  "properties": {
    "iso:country":"US",
    "sg:address":"10600 S Vermont Ave",
    "sg:city":"Los Angeles",
    "sg:classifiers":[
        {
            "category":"Retail",
            "subcategory":"Repair Shop",
            "type":"Services"
        }
    ],
    "sg:phone":"+1 323 846 9588",
    "sg:postcode":"90044",
    "sg:province":"CA",
    "sg:tags":[
        "related"
    ],
    "wof:name":"L & H Auto Repair",
    "wof:placetype":"venue"
},
  "geometry": {"coordinates":[-118.291639,33.939056],"type":"Point"}
}