{
  "type": "Feature",
  "properties": {
    "iso:country":"US",
    "sg:address":"9681 Laughlin Way",
    "sg:city":"Redwood Valley",
    "sg:classifiers":[
        {
            "category":"Social Services",
            "subcategory":"Child Care",
            "type":"Services"
        }
    ],
    "sg:phone":"+1 707 485 5819",
    "sg:postcode":"95470",
    "sg:province":"CA",
    "wof:name":"Kathy's Playroom Childcare",
    "wof:placetype":"venue"
},
  "geometry": {"coordinates":[-123.23397199999999,39.278589],"type":"Point"}
}