{
  "type": "Feature",
  "properties": {
    "iso:country":"US",
    "sg:address":"15242 Saticoy St",
    "sg:city":"Van Nuys",
    "sg:classifiers":[
        {
            "category":"Restaurant",
            "type":"Food & Drink"
        }
    ],
    "sg:phone":"+1 818 787 2260",
    "sg:postcode":"91405",
    "sg:province":"CA",
    "wof:name":"Meno's Daughters Restaurant",
    "wof:placetype":"venue"
},
  "geometry": {"coordinates":[-118.465425,34.208371],"type":"Point"}
}