{
  "type": "Feature",
  "properties": {
    "addr:full":"2148 Springs Rd Vallejo CA 94591",
    "addr:housenumber":"2148",
    "addr:postcode":"94591",
    "addr:street":"Springs Rd",
    "iso:country":"US",
    "sg:address":"2148 Springs Rd",
    "sg:city":"Vallejo",
    "sg:classifiers":[
        {
            "category":"Shopping",
            "subcategory":"Clothing, Apparel, & Fashions",
            "type":"Retail Goods"
        }
    ],
    "sg:phone":"+1 707 553 8258",
    "sg:postcode":"94591",
    "sg:province":"CA",
    "sg:tags":[
        "furnishing"
    ],
    "wof:name":"My Style",
    "wof:placetype":"venue"
},
  "geometry": {"coordinates":[-122.217736,38.106017],"type":"Point"}
}