{
  "type": "Feature",
  "properties": {
    "addr:full":"550 Orange Grove Blvd Pasadena CA 91105",
    "addr:housenumber":"550",
    "addr:postcode":"91105",
    "addr:street":"Orange Grove Blvd",
    "iso:country":"US",
    "sg:address":"550 Orange Grove Blvd",
    "sg:city":"Pasadena",
    "sg:classifiers":[
        {
            "category":"Shopping",
            "subcategory":"Pets & Pet Supplies",
            "type":"Retail Goods"
        },
        {
            "category":"Retail",
            "subcategory":"Pet Boarding",
            "type":"Services"
        }
    ],
    "sg:phone":"+1 626 616 0034",
    "sg:postcode":"91105",
    "sg:province":"CA",
    "sg:tags":[
        "walker",
        "dog",
        "boarding/pet",
        "sitting"
    ],
    "sg:website":"www.fourpawsrunning.net",
    "wof:name":"Four Paws Running",
    "wof:placetype":"venue"
},
  "geometry": {"coordinates":[-118.158552,34.136389],"type":"Point"}
}