{
  "type": "Feature",
  "properties": {
    "addr:full":"1850 W 169th St Gardena CA 90247",
    "addr:housenumber":"1850",
    "addr:postcode":"90247",
    "addr:street":"W 169Th St",
    "iso:country":"US",
    "sg:address":"1850 W 169th St",
    "sg:city":"Gardena",
    "sg:classifiers":[
        {
            "category":"Shopping",
            "subcategory":"Computers & Home Electronics",
            "type":"Retail Goods"
        }
    ],
    "sg:phone":"+1 310 329 7704",
    "sg:postcode":"90247",
    "sg:province":"CA",
    "sg:tags":[
        "equipment",
        "dealer"
    ],
    "wof:name":"Media Info",
    "wof:placetype":"venue"
},
  "geometry": {"coordinates":[-118.312179,33.87824],"type":"Point"}
}