{
  "type": "Feature",
  "properties": {
    "addr:full":"31305 Tick Canyon Rd Canyon Country CA 91387",
    "addr:postcode":"31305;91387",
    "addr:street":"Tick Canyon Rd",
    "iso:country":"US",
    "sg:address":"31305 Tick Canyon Rd",
    "sg:city":"Canyon Country",
    "sg:classifiers":[
        {
            "category":"Wholesale",
            "subcategory":"Photographic Equipment",
            "type":"Manufacturing & Wholesale Goods"
        }
    ],
    "sg:phone":"+1 661 250 0329",
    "sg:postcode":"91387",
    "sg:province":"CA",
    "sg:tags":[
        "photo"
    ],
    "wof:name":"Hollywood Animals Inc",
    "wof:placetype":"venue"
},
  "geometry": {"coordinates":[-118.371047,34.467306],"type":"Point"}
}