{
  "type": "Feature",
  "properties": {
    "addr:full":"20780 Warren Rd Perris CA 92570",
    "addr:housenumber":"20780",
    "addr:postcode":"92570",
    "addr:street":"Warren Rd",
    "iso:country":"US",
    "sg:address":"20780 Warren Rd",
    "sg:city":"Perris",
    "sg:classifiers":[
        {
            "category":"Farming",
            "subcategory":"Livestock Farm",
            "type":"Manufacturing & Wholesale Goods"
        }
    ],
    "sg:phone":"+1 951 943 2819",
    "sg:postcode":"92570",
    "sg:province":"CA",
    "sg:tags":[
        "insect"
    ],
    "sg:website":"www.benemite.com",
    "wof:name":"Biotactics Inc",
    "wof:placetype":"venue"
},
  "geometry": {"coordinates":[-117.296548,33.8623],"type":"Point"}
}