{
  "type": "Feature",
  "properties": {
    "iso:country":"US",
    "sg:address":"5044 Madison Ave",
    "sg:city":"Sacramento",
    "sg:classifiers":[
        {
            "category":"Utilities",
            "subcategory":"Mobile Phone",
            "type":"Services"
        }
    ],
    "sg:phone":"+1 916 334 4900",
    "sg:postcode":"95841",
    "sg:province":"CA",
    "sg:tags":[
        "telephone",
        "cellular"
    ],
    "sg:website":"www.bazoing.com/_ALL_USERS/Cellu...",
    "wof:name":"Cellular Showcase",
    "wof:placetype":"venue"
},
  "geometry": {"coordinates":[-121.346836,38.660486],"type":"Point"}
}