{
  "type": "Feature",
  "properties": {
    "iso:country":"US",
    "sg:address":"3264 Villa Ln",
    "sg:city":"Napa",
    "sg:classifiers":[
        {
            "category":"Manufacturing",
            "subcategory":"Rubber & Plastics",
            "type":"Manufacturing & Wholesale Goods"
        }
    ],
    "sg:phone":"+1 707 265 0742",
    "sg:postcode":"94558",
    "sg:province":"CA",
    "sg:tags":[
        "polyethylene",
        "material",
        "prod"
    ],
    "wof:name":"Poly Optimun Inc",
    "wof:placetype":"venue"
},
  "geometry": {"coordinates":[-122.292901,38.323124],"type":"Point"}
}