{
  "type": "Feature",
  "properties": {
    "addr:full":"824 L St Arcata CA 95521",
    "addr:housenumber":"824",
    "addr:postcode":"95521",
    "addr:street":"L St",
    "iso:country":"US",
    "sg:address":"824 L St",
    "sg:city":"Arcata",
    "sg:classifiers":[
        {
            "category":"Arts & Performance",
            "subcategory":"Theater",
            "type":"Entertainment"
        }
    ],
    "sg:phone":"+1 707 822 4947",
    "sg:postcode":"95521",
    "sg:province":"CA",
    "sg:tags":[
        "dance",
        "company"
    ],
    "wof:name":"Academy Of Ballet Arts",
    "wof:placetype":"venue"
},
  "geometry": {"coordinates":[-124.091076,40.869756],"type":"Point"}
}