{
  "type": "Feature",
  "properties": {
    "addr:full":"4992 Lincoln Ave Cypress CA 90630",
    "addr:housenumber":"4992",
    "addr:postcode":"90630",
    "addr:street":"Lincoln Ave",
    "iso:country":"US",
    "sg:address":"4992 Lincoln Ave",
    "sg:city":"Cypress",
    "sg:classifiers":[
        {
            "category":"Restaurant",
            "type":"Food & Drink"
        }
    ],
    "sg:menulink":"http://www.allmenus.com/ca/anaheim-santa-ana-garden-grove/150118-subway/menu/",
    "sg:phone":"+1 714 484 8782",
    "sg:postcode":"90630",
    "sg:province":"CA",
    "sg:tags":[
        "american",
        "sandwich"
    ],
    "wof:name":"Subway",
    "wof:placetype":"venue"
},
  "geometry": {"coordinates":[-118.046108,33.831391],"type":"Point"}
}