{
  "type": "Feature",
  "properties": {
    "addr:full":"3801 W Burbank Blvd Burbank CA 91505",
    "addr:housenumber":"3801",
    "addr:postcode":"91505",
    "addr:street":"W Burbank Blvd",
    "iso:country":"US",
    "sg:address":"3801 W Burbank Blvd",
    "sg:city":"Burbank",
    "sg:classifiers":[
        {
            "category":"Retail",
            "subcategory":"Repair Shop",
            "type":"Services"
        }
    ],
    "sg:phone":"+1 818 840 0004",
    "sg:postcode":"91505",
    "sg:province":"CA",
    "sg:tags":[
        "lock",
        "locksmith"
    ],
    "wof:name":"24 Hour 101 Locksmith",
    "wof:placetype":"venue"
},
  "geometry": {"coordinates":[-118.352198,34.174026],"type":"Point"}
}