{
  "type": "Feature",
  "properties": {
    "addr:full":"2598 N Associated Rd Fullerton CA 92835",
    "addr:housenumber":"2598",
    "addr:postcode":"92835",
    "addr:street":"N Associated Rd",
    "iso:country":"US",
    "sg:address":"2598 N Associated Rd",
    "sg:city":"Fullerton",
    "sg:classifiers":[
        {
            "category":"Real Estate",
            "subcategory":"Real Estate Operator",
            "type":"Services"
        }
    ],
    "sg:phone":"+1 714 870 4567",
    "sg:postcode":"92835",
    "sg:province":"CA",
    "sg:tags":[
        "apartment"
    ],
    "wof:name":"Las Palmas Apartments",
    "wof:placetype":"venue"
},
  "geometry": {"coordinates":[-117.883312,33.898275],"type":"Point"}
}