{
  "type": "Feature",
  "properties": {
    "iso:country":"US",
    "sg:address":"13725 Pipeline Ave",
    "sg:city":"Chino",
    "sg:classifiers":[
        {
            "category":"Freight",
            "type":"Transportation"
        }
    ],
    "sg:phone":"+1 909 548 2030",
    "sg:postcode":"91710",
    "sg:province":"CA",
    "sg:tags":[
        "warehouse"
    ],
    "wof:name":"OTC Inc",
    "wof:placetype":"venue"
},
  "geometry": {"coordinates":[-117.715212,34.003578],"type":"Point"}
}