{
  "type": "Feature",
  "properties": {
    "addr:full":"941 S Vermont Ave Los Angeles CA 90006",
    "addr:housenumber":"941",
    "addr:postcode":"90006",
    "addr:street":"S Vermont Ave",
    "iso:country":"US",
    "sg:address":"941 S Vermont Ave",
    "sg:city":"Los Angeles",
    "sg:classifiers":[
        {
            "category":"Building & Trades",
            "subcategory":"Construction",
            "type":"Services"
        }
    ],
    "sg:phone":"+1 213 365 8870",
    "sg:postcode":"90006",
    "sg:province":"CA",
    "sg:tags":[
        "contractor"
    ],
    "wof:name":"C W Roofing Co",
    "wof:placetype":"venue"
},
  "geometry": {"coordinates":[-118.291687,34.052604],"type":"Point"}
}