{
  "type": "Feature",
  "properties": {
    "addr:full":"7517 State St Huntington Park CA 90255",
    "addr:housenumber":"7517",
    "addr:postcode":"90255",
    "addr:street":"State St;Park",
    "iso:country":"US",
    "sg:address":"7517 State St",
    "sg:city":"Huntington Park",
    "sg:classifiers":[
        {
            "category":"Shopping",
            "subcategory":"Clothing, Apparel, & Fashions",
            "type":"Retail Goods"
        }
    ],
    "sg:phone":"+1 323 587 5033",
    "sg:postcode":"90255",
    "sg:province":"CA",
    "sg:tags":[
        "lady",
        "wear",
        "accessory"
    ],
    "wof:name":"D E Fashions",
    "wof:placetype":"venue"
},
  "geometry": {"coordinates":[-118.209999,33.969601],"type":"Point"}
}