{
  "type": "Feature",
  "properties": {
    "iso:country":"US",
    "sg:address":"393 Arneill Rd",
    "sg:city":"Camarillo",
    "sg:classifiers":[
        {
            "category":"Freight",
            "type":"Transportation"
        },
        {
            "category":"Professional",
            "subcategory":"Printing & Photocopies",
            "type":"Services"
        }
    ],
    "sg:phone":"+1 805 482 3364",
    "sg:postcode":"93010",
    "sg:province":"CA",
    "sg:tags":[
        "shipping"
    ],
    "sg:website":"www.fedex.com/us/office/",
    "wof:name":"FedEx Office Print & Ship Center",
    "wof:placetype":"venue"
},
  "geometry": {"coordinates":[-119.039264,34.220711],"type":"Point"}
}