{
  "type": "Feature",
  "properties": {
    "iso:country":"US",
    "sg:address":"11935 E Princeton Ave",
    "sg:city":"Sanger",
    "sg:classifiers":[
        {
            "category":"Building & Trades",
            "subcategory":"Construction",
            "type":"Services"
        }
    ],
    "sg:phone":"+1 559 876 3162",
    "sg:postcode":"93657",
    "sg:province":"CA",
    "sg:tags":[
        "heavy"
    ],
    "wof:name":"Roca Green Inc",
    "wof:placetype":"venue"
},
  "geometry": {"coordinates":[-119.575664,36.77519],"type":"Point"}
}