{
  "type": "Feature",
  "properties": {
    "addr:full":"12734 Carob Ct Chino CA 91710",
    "addr:housenumber":"12734",
    "addr:postcode":"91710",
    "addr:street":"Carob Ct",
    "iso:country":"US",
    "sg:address":"12734 Carob Ct",
    "sg:city":"Chino",
    "sg:classifiers":[
        {
            "category":"Freight",
            "type":"Transportation"
        }
    ],
    "sg:phone":"+1 909 627 9007",
    "sg:postcode":"91710",
    "sg:province":"CA",
    "sg:tags":[
        "hay"
    ],
    "wof:name":"Dirksen & Company",
    "wof:placetype":"venue"
},
  "geometry": {"coordinates":[-117.665279,34.021759],"type":"Point"}
}