{
  "type": "Feature",
  "properties": {
    "addr:full":"7520 el Cajon Blvd La Mesa CA 91941",
    "addr:housenumber":"7520",
    "addr:postcode":"91941",
    "addr:street":"El Cajon Blvd",
    "iso:country":"US",
    "sg:address":"7520 el Cajon Blvd",
    "sg:city":"La Mesa",
    "sg:classifiers":[
        {
            "category":"Utilities",
            "subcategory":"Mobile Phone",
            "type":"Services"
        }
    ],
    "sg:phone":"+1 619 337 1800",
    "sg:postcode":"91941",
    "sg:province":"CA",
    "sg:tags":[
        "telephone",
        "cellular"
    ],
    "wof:name":"Nextel",
    "wof:placetype":"venue"
},
  "geometry": {"coordinates":[-117.035439,32.768121],"type":"Point"}
}