{
  "type": "Feature",
  "properties": {
    "addr:full":"21271 Burbank Blvd Woodland Hills CA 91367",
    "addr:housenumber":"21271",
    "addr:postcode":"91367",
    "addr:street":"Burbank Blvd",
    "iso:country":"US",
    "sg:address":"21271 Burbank Blvd",
    "sg:city":"Woodland Hills",
    "sg:classifiers":[
        {
            "category":"Professional",
            "subcategory":"Lawyer & Legal Services",
            "type":"Services"
        }
    ],
    "sg:phone":"+1 818 712 9800",
    "sg:postcode":"91367",
    "sg:province":"CA",
    "wof:name":"Bremer & Whyte",
    "wof:placetype":"venue"
},
  "geometry": {"coordinates":[-118.595001,34.173302],"type":"Point"}
}