{
  "type": "Feature",
  "properties": {
    "iso:country":"US",
    "sg:address":"833 Cypress Ave",
    "sg:city":"Hermosa Beach",
    "sg:classifiers":[
        {
            "category":"Professional",
            "type":"Services"
        }
    ],
    "sg:phone":"+1 310 376 2595",
    "sg:postcode":"90254",
    "sg:province":"CA",
    "sg:tags":[
        "establishment"
    ],
    "wof:name":"Surfsend",
    "wof:placetype":"venue"
},
  "geometry": {"coordinates":[-118.39589599999999,33.860402],"type":"Point"}
}