{
  "type": "Feature",
  "properties": {
    "iso:country":"US",
    "sg:address":"354 Pine St",
    "sg:city":"San Francisco",
    "sg:classifiers":[
        {
            "category":"Real Estate",
            "subcategory":"Real Estate Agent",
            "type":"Services"
        }
    ],
    "sg:phone":"+1 415 394 7027",
    "sg:postcode":"94104",
    "sg:province":"CA",
    "wof:name":"Group I",
    "wof:placetype":"venue"
},
  "geometry": {"coordinates":[-122.40212099999999,37.792035],"type":"Point"}
}