{
  "type": "Feature",
  "properties": {
    "addr:full":"770 el Margarita Rd Yuba City CA 95993",
    "addr:housenumber":"770",
    "addr:postcode":"95993",
    "addr:street":"El Margarita Rd",
    "iso:country":"US",
    "sg:address":"770 el Margarita Rd",
    "sg:city":"Yuba City",
    "sg:classifiers":[
        {
            "category":"Wholesale",
            "subcategory":"Hardware",
            "type":"Manufacturing & Wholesale Goods"
        }
    ],
    "sg:phone":"+1 530 671 4700",
    "sg:postcode":"95993",
    "sg:province":"CA",
    "sg:tags":[
        "tool"
    ],
    "wof:name":"Snap-On Tools Co",
    "wof:placetype":"venue"
},
  "geometry": {"coordinates":[-121.662503,39.131008],"type":"Point"}
}