{
  "type": "Feature",
  "properties": {
    "addr:full":"400 W 2nd St Alturas CA 96101",
    "addr:housenumber":"400",
    "addr:postcode":"96101",
    "addr:street":"W 2Nd St",
    "iso:country":"US",
    "sg:address":"400 W 2nd St",
    "sg:city":"Alturas",
    "sg:classifiers":[
        {
            "category":"Retail",
            "subcategory":"Funeral Services",
            "type":"Services"
        }
    ],
    "sg:phone":"+1 530 233 3930",
    "sg:postcode":"96101",
    "sg:province":"CA",
    "sg:tags":[
        "director"
    ],
    "wof:name":"KERR Mortuary",
    "wof:placetype":"venue"
},
  "geometry": {"coordinates":[-120.54642200000001,41.484915],"type":"Point"}
}