{
  "type": "Feature",
  "properties": {
    "addr:full":"10508 E Central Ave Del Rey CA 93616",
    "addr:housenumber":"10508",
    "addr:postcode":"93616",
    "addr:street":"E Central Ave",
    "iso:country":"US",
    "sg:address":"10508 E Central Ave",
    "sg:city":"Del Rey",
    "sg:classifiers":[
        {
            "category":"Manufacturing",
            "subcategory":"Pet Food",
            "type":"Manufacturing & Wholesale Goods"
        }
    ],
    "sg:phone":"+1 559 888 2187",
    "sg:postcode":"93616",
    "sg:province":"CA",
    "sg:tags":[
        "feed"
    ],
    "wof:name":"Economy Stock Feed Inc",
    "wof:placetype":"venue"
},
  "geometry": {"coordinates":[-119.60110299999999,36.677709],"type":"Point"}
}