{
  "type": "Feature",
  "properties": {
    "addr:full":"2218 Cotner Ave Los Angeles CA 90064",
    "addr:postcode":"2218;90064",
    "addr:street":"Cotner Ave",
    "iso:country":"US",
    "sg:address":"2218 Cotner Ave",
    "sg:city":"Los Angeles",
    "sg:classifiers":[
        {
            "category":"Recreation",
            "type":"Entertainment"
        }
    ],
    "sg:phone":"+1 310 479 2730",
    "sg:postcode":"90064",
    "sg:province":"CA",
    "sg:tags":[
        "instruction",
        "gymnastic"
    ],
    "wof:name":"Junior Gym",
    "wof:placetype":"venue"
},
  "geometry": {"coordinates":[-118.438329,34.038291],"type":"Point"}
}