{
  "type": "Feature",
  "properties": {
    "iso:country":"US",
    "sg:address":"11938 Ventura Blvd",
    "sg:city":"Studio City",
    "sg:classifiers":[
        {
            "category":"Bars & Pubs",
            "type":"Food & Drink"
        }
    ],
    "sg:phone":"+1 818 506 0777",
    "sg:postcode":"91604",
    "sg:province":"CA",
    "sg:tags":[
        "gastropubs"
    ],
    "sg:website":"www.laureltavern.net/",
    "wof:name":"Laurel Tavern",
    "wof:placetype":"venue"
},
  "geometry": {"coordinates":[-118.392107,34.142957],"type":"Point"}
}