{
  "type": "Feature",
  "properties": {
    "addr:full":"312 Georgia St Vallejo CA 94590",
    "addr:housenumber":"312",
    "addr:postcode":"94590",
    "addr:street":"Georgia St",
    "iso:country":"US",
    "sg:address":"312 Georgia St",
    "sg:city":"Vallejo",
    "sg:classifiers":[
        {
            "category":"Professional",
            "subcategory":"Lawyer & Legal Services",
            "type":"Services"
        }
    ],
    "sg:phone":"+1 707 552 2234",
    "sg:postcode":"94590",
    "sg:province":"CA",
    "sg:tags":[
        "attorney"
    ],
    "wof:name":"David R Fischer",
    "wof:placetype":"venue"
},
  "geometry": {"coordinates":[-122.256801,38.101196],"type":"Point"}
}