{
  "type": "Feature",
  "properties": {
    "iso:country":"US",
    "sg:address":"13704 Main St",
    "sg:city":"Hesperia",
    "sg:classifiers":[
        {
            "category":"Restaurant",
            "type":"Food & Drink"
        }
    ],
    "sg:menulink":"http://www.allmenus.com/ca/barstow-victorville/224419-in--out-burger/menu/",
    "sg:postcode":"92345",
    "sg:province":"CA",
    "sg:tags":[
        "burger",
        "american"
    ],
    "wof:name":"In & Out Burger",
    "wof:placetype":"venue"
},
  "geometry": {"coordinates":[-117.36588399999999,34.426739],"type":"Point"}
}