{
  "type": "Feature",
  "properties": {
    "addr:full":"2582 Goldin Ave Simi Valley CA 93065",
    "addr:postcode":"2582;93065",
    "addr:street":"Goldin Ave",
    "iso:country":"US",
    "sg:address":"2582 Goldin Ave",
    "sg:city":"Simi Valley",
    "sg:classifiers":[
        {
            "category":"Insurance",
            "subcategory":"Insurance Agent",
            "type":"Services"
        }
    ],
    "sg:phone":"+1 805 581 3838",
    "sg:postcode":"93065",
    "sg:province":"CA",
    "wof:name":"Transamerica Occidental Life",
    "wof:placetype":"venue"
},
  "geometry": {"coordinates":[-118.752118,34.280509],"type":"Point"}
}