{
  "type": "Feature",
  "properties": {
    "addr:full":"350 California St San Francisco CA 94104",
    "addr:housenumber":"350",
    "addr:postcode":"94104",
    "addr:street":"California St",
    "iso:country":"US",
    "sg:address":"350 California St",
    "sg:city":"San Francisco",
    "sg:classifiers":[
        {
            "category":"Home & Garden",
            "subcategory":"Carpets & Floor Coverings",
            "type":"Retail Goods"
        }
    ],
    "sg:phone":"+1 415 955 1920",
    "sg:postcode":"94104",
    "sg:province":"CA",
    "sg:tags":[
        "dealer",
        "rug"
    ],
    "sg:website":"www.shawcontractgroup.com",
    "wof:name":"Shaw Contract Group",
    "wof:placetype":"venue"
},
  "geometry": {"coordinates":[-122.400667,37.79321],"type":"Point"}
}