{
  "type": "Feature",
  "properties": {
    "addr:full":"4045 W Garden Grove Blvd Orange CA 92868",
    "addr:housenumber":"4045",
    "addr:postcode":"92868",
    "addr:street":"W Garden Grove Blvd",
    "iso:country":"US",
    "sg:address":"4045 W Garden Grove Blvd",
    "sg:city":"Orange",
    "sg:classifiers":[
        {
            "category":"Food & Beverages",
            "subcategory":"Groceries & Convenience Stores",
            "type":"Retail Goods"
        }
    ],
    "sg:phone":"+1 714 703 1271",
    "sg:postcode":"92868",
    "sg:province":"CA",
    "sg:website":"www.7-eleven.com",
    "wof:name":"7-Eleven",
    "wof:placetype":"venue"
},
  "geometry": {"coordinates":[-117.896331,33.774667],"type":"Point"}
}