{
  "type": "Feature",
  "properties": {
    "iso:country":"US",
    "sg:address":"2090 Kittredge St",
    "sg:city":"Berkeley",
    "sg:classifiers":[
        {
            "category":"Education",
            "subcategory":"Library",
            "type":"Public Place"
        }
    ],
    "sg:phone":"+1 510 981 6100",
    "sg:postcode":"94704",
    "sg:province":"CA",
    "sg:website":"www.berkeleypubliclibrary.org",
    "wof:name":"Berkeley Public Library",
    "wof:placetype":"venue"
},
  "geometry": {"coordinates":[-122.26817800000001,37.868473],"type":"Point"}
}