{
  "type": "Feature",
  "properties": {
    "iso:country":"US",
    "sg:address":"24803 Laurelcrest Ln",
    "sg:city":"Stevenson Ranch",
    "sg:classifiers":[
        {
            "category":"Wholesale",
            "subcategory":"Metals & Minerals",
            "type":"Manufacturing & Wholesale Goods"
        }
    ],
    "sg:phone":"+1 661 834 9933",
    "sg:postcode":"91381",
    "sg:province":"CA",
    "sg:tags":[
        "center"
    ],
    "wof:name":"Coors Recycling Center",
    "wof:placetype":"venue"
},
  "geometry": {"coordinates":[-118.568717,34.375035],"type":"Point"}
}