{
  "type": "Feature",
  "properties": {
    "iso:country":"US",
    "sg:address":"7441 Henefer Ave",
    "sg:city":"Los Angeles",
    "sg:classifiers":[
        {
            "category":"Building & Trades",
            "subcategory":"Construction",
            "type":"Services"
        }
    ],
    "sg:phone":"+1 310 641 6800",
    "sg:postcode":"90045",
    "sg:province":"CA",
    "sg:tags":[
        "contractor"
    ],
    "wof:name":"Jacobs Marshal Co Inc",
    "wof:placetype":"venue"
},
  "geometry": {"coordinates":[-118.40341600000001,33.974762],"type":"Point"}
}