{
  "type": "Feature",
  "properties": {
    "addr:full":"1156 N McCadden Pl Los Angeles CA 90038",
    "addr:housenumber":"1156",
    "addr:postcode":"90038",
    "addr:street":"N Mccadden Pl",
    "iso:country":"US",
    "sg:address":"1156 N McCadden Pl",
    "sg:city":"Los Angeles",
    "sg:classifiers":[
        {
            "category":"Manufacturing",
            "subcategory":"Metals",
            "type":"Manufacturing & Wholesale Goods"
        }
    ],
    "sg:phone":"+1 323 465 6565",
    "sg:postcode":"90038",
    "sg:province":"CA",
    "sg:tags":[
        "plumbing",
        "fixture",
        "supply"
    ],
    "wof:name":"Ferguson Enterprises Inc",
    "wof:placetype":"venue"
},
  "geometry": {"coordinates":[-118.337371,34.091512],"type":"Point"}
}