{
  "type": "Feature",
  "properties": {
    "addr:full":"1602 Whitmore St Hanford CA 93230",
    "addr:housenumber":"1602",
    "addr:postcode":"ca 93230",
    "addr:street":"Whitmore St",
    "iso:country":"US",
    "sg:address":"1602 Whitmore St",
    "sg:city":"Hanford",
    "sg:classifiers":[
        {
            "category":"Banks & Credit Unions",
            "subcategory":"Investment Brokerage",
            "type":"Services"
        }
    ],
    "sg:phone":"+1 559 582 4688",
    "sg:postcode":"93230",
    "sg:province":"CA",
    "sg:tags":[
        "consultant",
        "planning",
        "financial"
    ],
    "wof:name":"Eiland Associates",
    "wof:placetype":"venue"
},
  "geometry": {"coordinates":[-119.653738,36.34246],"type":"Point"}
}