{
  "type": "Feature",
  "properties": {
    "iso:country":"US",
    "sg:address":"1370 Brea Blvd",
    "sg:city":"Fullerton",
    "sg:classifiers":[
        {
            "category":"Social Services",
            "type":"Services"
        },
        {
            "category":"Personal",
            "type":"Services"
        }
    ],
    "sg:phone":"+1 714 526 8433",
    "sg:postcode":"92835",
    "sg:province":"CA",
    "sg:tags":[
        "counseling",
        "therapist",
        "marriage",
        "family"
    ],
    "wof:name":"Land Joan MFT",
    "wof:placetype":"venue"
},
  "geometry": {"coordinates":[-117.924149,33.884361],"type":"Point"}
}