{
  "type": "Feature",
  "properties": {
    "addr:full":"3721S. El Camino Real San Mateo CA 94403",
    "addr:housenumber":"3721s",
    "addr:postcode":"94403",
    "addr:street":"El Camino Real",
    "iso:country":"US",
    "sg:address":"3721S. El Camino Real",
    "sg:city":"San Mateo",
    "sg:classifiers":[
        {
            "category":"Autos & Motor Vehicles",
            "subcategory":"Motorcycle Sales",
            "type":"Retail Goods"
        },
        {
            "category":"Retail",
            "subcategory":"Auto Repair",
            "type":"Services"
        }
    ],
    "sg:phone":"+1 650 312 1777",
    "sg:postcode":"94403",
    "sg:province":"CA",
    "sg:website":"www.city-powersports.com",
    "wof:name":"City PowerSports",
    "wof:placetype":"venue"
},
  "geometry": {"coordinates":[-122.294346,37.534332],"type":"Point"}
}