{
  "type": "Feature",
  "properties": {
    "addr:full":"5801 Lincoln Ave Ste C Buena Park CA 90620",
    "addr:housenumber":"5801",
    "addr:postcode":"90620",
    "addr:street":"Lincoln Ave Ste C",
    "iso:country":"US",
    "sg:address":"5801 Lincoln Ave Ste C",
    "sg:city":"Buena Park",
    "sg:classifiers":[
        {
            "category":"Cinema",
            "subcategory":"Movie Rental",
            "type":"Entertainment"
        }
    ],
    "sg:phone":"+1 714 761 2456",
    "sg:postcode":"90620",
    "sg:province":"CA",
    "sg:tags":[
        "game",
        "video"
    ],
    "wof:name":"Lincoln Video",
    "wof:placetype":"venue"
},
  "geometry": {"coordinates":[-117.994874,33.841019],"type":"Point"}
}