{
  "type": "Feature",
  "properties": {
    "addr:full":"55 N Baldwin Ave Sierra Madre CA 91024",
    "addr:housenumber":"55",
    "addr:postcode":"91024",
    "addr:street":"N Baldwin Ave",
    "iso:country":"US",
    "sg:address":"55 N Baldwin Ave",
    "sg:city":"Sierra Madre",
    "sg:classifiers":[
        {
            "category":"Shopping",
            "subcategory":"Department Store",
            "type":"Retail Goods"
        }
    ],
    "sg:phone":"+1 626 355 8500",
    "sg:postcode":"91024",
    "sg:province":"CA",
    "wof:name":"Coquette",
    "wof:placetype":"venue"
},
  "geometry": {"coordinates":[-118.27920899999999,34.162851],"type":"Point"}
}