{
  "type": "Feature",
  "properties": {
    "iso:country":"US",
    "sg:address":"8788 Elk Grove Blvd",
    "sg:city":"Elk Grove",
    "sg:classifiers":[
        {
            "category":"Banks & Credit Unions",
            "subcategory":"Investment Brokerage",
            "type":"Services"
        }
    ],
    "sg:phone":"+1 916 685 1814",
    "sg:postcode":"95624",
    "sg:province":"CA",
    "sg:tags":[
        "retirement",
        "planning"
    ],
    "wof:name":"Djw Benefits & Planning",
    "wof:placetype":"venue"
},
  "geometry": {"coordinates":[-121.378443,38.408989],"type":"Point"}
}