{
  "type": "Feature",
  "properties": {
    "addr:full":"8215 Avalon Blvd Los Angeles CA 90003",
    "addr:housenumber":"8215",
    "addr:postcode":"90003",
    "addr:street":"Avalon Blvd",
    "iso:country":"US",
    "sg:address":"8215 Avalon Blvd",
    "sg:city":"Los Angeles",
    "sg:classifiers":[
        {
            "category":"Building & Trades",
            "subcategory":"Equipment Rental",
            "type":"Services"
        }
    ],
    "sg:phone":"+1 323 971 5096",
    "sg:postcode":"90003",
    "sg:province":"CA",
    "sg:tags":[
        "player",
        "recorder",
        "video"
    ],
    "wof:name":"John's Videos",
    "wof:placetype":"venue"
},
  "geometry": {"coordinates":[-118.26520499999999,33.963889],"type":"Point"}
}