{
  "type": "Feature",
  "properties": {
    "addr:full":"966 W. Dana Street Mountain View CA 94041",
    "addr:housenumber":"966",
    "addr:postcode":"94041",
    "addr:street":"W. Dana Street",
    "iso:country":"US",
    "sg:address":"966 W. Dana Street",
    "sg:city":"Mountain View",
    "sg:classifiers":[
        {
            "category":"Retail",
            "subcategory":"Auto Repair",
            "type":"Services"
        }
    ],
    "sg:phone":"+1 650 965 8400",
    "sg:postcode":"94041",
    "sg:province":"CA",
    "sg:tags":[
        "body",
        "shop"
    ],
    "wof:name":"Dunn's Automotive Inc.",
    "wof:placetype":"venue"
},
  "geometry": {"coordinates":[-122.08160700000001,37.393285],"type":"Point"}
}