{
  "type": "Feature",
  "properties": {
    "iso:country":"US",
    "sg:address":"18970 Ventura Blvd",
    "sg:city":"Tarzana",
    "sg:classifiers":[
        {
            "category":"Restaurant",
            "type":"Food & Drink"
        }
    ],
    "sg:phone":"+1 818 708 8986",
    "sg:postcode":"91356",
    "sg:province":"CA",
    "wof:name":"Sasoon Restaurant",
    "wof:placetype":"venue"
},
  "geometry": {"coordinates":[-118.546893,34.172488],"type":"Point"}
}