{
  "type": "Feature",
  "properties": {
    "iso:country":"US",
    "sg:address":"1230 Mountain View Alviso Rd",
    "sg:city":"Sunnyvale",
    "sg:classifiers":[
        {
            "category":"Manufacturing",
            "subcategory":"Tools & Machinery",
            "type":"Manufacturing & Wholesale Goods"
        }
    ],
    "sg:phone":"+1 408 734 0705",
    "sg:postcode":"94089",
    "sg:province":"CA",
    "sg:tags":[
        "industrial",
        "mfg"
    ],
    "wof:name":"W B Manufacturing",
    "wof:placetype":"venue"
},
  "geometry": {"coordinates":[-121.990019,37.411154],"type":"Point"}
}