{
  "type": "Feature",
  "properties": {
    "addr:full":"198 E Elm Ave Coalinga CA 93210",
    "addr:housenumber":"198",
    "addr:postcode":"93210",
    "addr:street":"E Elm Ave",
    "iso:country":"US",
    "sg:address":"198 E Elm Ave",
    "sg:city":"Coalinga",
    "sg:classifiers":[
        {
            "category":"Health Services",
            "subcategory":"Doctor",
            "type":"Services"
        }
    ],
    "sg:phone":"+1 559 935 2368",
    "sg:postcode":"93210",
    "sg:province":"CA",
    "sg:tags":[
        "dentist"
    ],
    "wof:name":"Rusdy Murni DDS",
    "wof:placetype":"venue"
},
  "geometry": {"coordinates":[-120.360283,36.139722],"type":"Point"}
}