{
  "type": "Feature",
  "properties": {
    "addr:full":"401 College Ave Santa Rosa CA 95401",
    "addr:housenumber":"401",
    "addr:postcode":"95401",
    "addr:street":"College Ave",
    "iso:country":"US",
    "sg:address":"401 College Ave",
    "sg:city":"Santa Rosa",
    "sg:classifiers":[
        {
            "category":"Organizations",
            "subcategory":"Labor Organization",
            "type":"Services"
        }
    ],
    "sg:phone":"+1 707 575 8461",
    "sg:postcode":"95401",
    "sg:province":"CA",
    "wof:name":"Staff Nurses Assn",
    "wof:placetype":"venue"
},
  "geometry": {"coordinates":[-122.717698,38.44551],"type":"Point"}
}