{
  "type": "Feature",
  "properties": {
    "addr:full":"745 Portola Dr San Francisco CA 94127",
    "addr:housenumber":"745",
    "addr:postcode":"94127",
    "addr:street":"Portola Dr",
    "iso:country":"US",
    "sg:address":"745 Portola Dr",
    "sg:city":"San Francisco",
    "sg:classifiers":[
        {
            "category":"Banks & Credit Unions",
            "subcategory":"Bank",
            "type":"Services"
        }
    ],
    "sg:phone":"+1 415 242 0730",
    "sg:postcode":"94127",
    "sg:province":"CA",
    "sg:tags":[
        "mortgage",
        "loan",
        "broker",
        "real estate"
    ],
    "sg:website":"www.pacificbayfinancial.com",
    "wof:name":"Pacific Bay Financial Corp",
    "wof:placetype":"venue"
},
  "geometry": {"coordinates":[-122.45357799999999,37.743842],"type":"Point"}
}