{
  "type": "Feature",
  "properties": {
    "iso:country":"US",
    "sg:address":"1900 Mowry Ave",
    "sg:city":"Fremont",
    "sg:classifiers":[
        {
            "category":"Health Services",
            "subcategory":"Doctor",
            "type":"Services"
        }
    ],
    "sg:phone":"+1 510 790 2202",
    "sg:postcode":"94538",
    "sg:province":"CA",
    "sg:tags":[
        "physician",
        "surgeon"
    ],
    "wof:name":"Pacific Cardiology Assoc",
    "wof:placetype":"venue"
},
  "geometry": {"coordinates":[-121.97991500000001,37.559031],"type":"Point"}
}