{
  "type": "Feature",
  "properties": {
    "addr:full":"2225 W Ball Rd Anaheim CA 92804",
    "addr:housenumber":"2225",
    "addr:postcode":"92804",
    "addr:street":"W Ball Rd",
    "iso:country":"US",
    "sg:address":"2225 W Ball Rd",
    "sg:city":"Anaheim",
    "sg:classifiers":[
        {
            "category":"Restaurant",
            "type":"Food & Drink"
        }
    ],
    "sg:phone":"+1 714 776 5100",
    "sg:postcode":"92804",
    "sg:province":"CA",
    "sg:tags":[
        "fish",
        "chip"
    ],
    "wof:name":"London Tower Fish & Chips",
    "wof:placetype":"venue"
},
  "geometry": {"coordinates":[-117.95700100000001,33.817799],"type":"Point"}
}