{
  "type": "Feature",
  "properties": {
    "iso:country":"US",
    "sg:address":"3300 Delta Fair Blvd",
    "sg:city":"Antioch",
    "sg:classifiers":[
        {
            "category":"Shopping",
            "subcategory":"Bicycles & Sporting Goods",
            "type":"Retail Goods"
        }
    ],
    "sg:phone":"+1 925 757 5424",
    "sg:postcode":"94509",
    "sg:province":"CA",
    "sg:tags":[
        "apparel",
        "bowling",
        "accessory"
    ],
    "wof:name":"Delta Bowl",
    "wof:placetype":"venue"
},
  "geometry": {"coordinates":[-121.840126,38.00297],"type":"Point"}
}