{
  "type": "Feature",
  "properties": {
    "iso:country":"US",
    "sg:address":"12110 Walnut St",
    "sg:city":"Norwalk",
    "sg:classifiers":[
        {
            "category":"Mining & Drilling",
            "type":"Manufacturing & Wholesale Goods"
        }
    ],
    "sg:phone":"+1 562 863 3183",
    "sg:postcode":"90650",
    "sg:province":"CA",
    "sg:tags":[
        "stone"
    ],
    "wof:name":"Stone Soup",
    "wof:placetype":"venue"
},
  "geometry": {"coordinates":[-118.07463799999999,33.903694],"type":"Point"}
}