{
  "type": "Feature",
  "properties": {
    "iso:country":"US",
    "sg:address":"1365 D St",
    "sg:city":"Hayward",
    "sg:classifiers":[
        {
            "category":"Real Estate",
            "subcategory":"Real Estate Operator",
            "type":"Services"
        }
    ],
    "sg:phone":"+1 510 537 2882",
    "sg:postcode":"94541",
    "sg:province":"CA",
    "sg:tags":[
        "apartment"
    ],
    "wof:name":"Valle Verde Apts",
    "wof:placetype":"venue"
},
  "geometry": {"coordinates":[-122.07399700000001,37.674999],"type":"Point"}
}