{
  "type": "Feature",
  "properties": {
    "addr:full":"521 Parnassus Ave San Francisco CA 94199",
    "addr:housenumber":"521",
    "addr:postcode":"94199",
    "addr:street":"Parnassus Ave",
    "iso:country":"US",
    "sg:address":"521 Parnassus Ave",
    "sg:city":"San Francisco",
    "sg:classifiers":[
        {
            "category":"Education",
            "subcategory":"University",
            "type":"Public Place"
        }
    ],
    "sg:postcode":"94199",
    "sg:province":"CA",
    "sg:tags":[
        "college"
    ],
    "wof:name":"UCSF School of Nursing",
    "wof:placetype":"venue"
},
  "geometry": {"coordinates":[-122.459666,37.762946],"type":"Point"}
}