{
  "type": "Feature",
  "properties": {
    "iso:country":"US",
    "sg:address":"128 E 6th St",
    "sg:city":"Los Angeles",
    "sg:classifiers":[
        {
            "category":"Bars & Pubs",
            "subcategory":"Wine Bar",
            "type":"Food & Drink"
        }
    ],
    "sg:phone":"+1 213 489 0131",
    "sg:postcode":"90014",
    "sg:province":"CA",
    "sg:website":"www.mignonla.com/",
    "wof:name":"Mignon",
    "wof:placetype":"venue"
},
  "geometry": {"coordinates":[-118.249765,34.045132],"type":"Point"}
}