{
  "type": "Feature",
  "properties": {
    "iso:country":"US",
    "sg:address":"1786 18th St",
    "sg:city":"San Francisco",
    "sg:classifiers":[
        {
            "category":"Professional",
            "subcategory":"Business Services",
            "type":"Services"
        }
    ],
    "sg:phone":"+1 415 487 6907",
    "sg:postcode":"94107",
    "sg:province":"CA",
    "sg:tags":[
        "interior",
        "consultant",
        "design",
        "decorator"
    ],
    "wof:name":"Gordon Design Group",
    "wof:placetype":"venue"
},
  "geometry": {"coordinates":[-122.399693,37.762473],"type":"Point"}
}