{
  "type": "Feature",
  "properties": {
    "addr:full":"1717 17th San Francisco CA 94102",
    "addr:housenumber":"1717",
    "addr:postcode":"94102",
    "addr:street":"17Th",
    "iso:country":"US",
    "sg:address":"1717 17th",
    "sg:city":"San Francisco",
    "sg:classifiers":[
        {
            "category":"Building & Trades",
            "subcategory":"Construction",
            "type":"Services"
        }
    ],
    "sg:phone":"+1 415 252 1900",
    "sg:postcode":"94102",
    "sg:province":"CA",
    "sg:tags":[
        "contractor"
    ],
    "wof:name":"Residential Builders Association",
    "wof:placetype":"venue"
},
  "geometry": {"coordinates":[-122.40078699999999,37.764803],"type":"Point"}
}