{
  "type": "Feature",
  "properties": {
    "addr:full":"4368 Avalon Blvd Los Angeles CA 90011",
    "addr:housenumber":"4368",
    "addr:postcode":"90011",
    "addr:street":"Avalon Blvd",
    "iso:country":"US",
    "sg:address":"4368 Avalon Blvd",
    "sg:city":"Los Angeles",
    "sg:classifiers":[
        {
            "category":"Wholesale",
            "subcategory":"Auto Parts",
            "type":"Manufacturing & Wholesale Goods"
        },
        {
            "category":"Retail",
            "subcategory":"Auto Repair",
            "type":"Services"
        }
    ],
    "sg:phone":"+1 323 231 9900",
    "sg:postcode":"90011",
    "sg:province":"CA",
    "sg:tags":[
        "control",
        "automobile",
        "smog",
        "device",
        "check"
    ],
    "wof:name":"Avalon Smog Center",
    "wof:placetype":"venue"
},
  "geometry": {"coordinates":[-118.264999,34.004101],"type":"Point"}
}