{
  "type": "Feature",
  "properties": {
    "iso:country":"US",
    "sg:address":"945 4th Avenue",
    "sg:city":"San Diego",
    "sg:classifiers":[
        {
            "category":"Professional",
            "subcategory":"Lawyer & Legal Services",
            "type":"Services"
        }
    ],
    "sg:phone":"+1 619 233 1888",
    "sg:postcode":"92101",
    "sg:province":"CA",
    "wof:name":"McKee Kathleen J",
    "wof:placetype":"venue"
},
  "geometry": {"coordinates":[-117.161205,32.715055],"type":"Point"}
}