{
  "type": "Feature",
  "properties": {
    "iso:country":"US",
    "sg:address":"4157 Redondo Beach Blvd",
    "sg:city":"Lawndale",
    "sg:classifiers":[
        {
            "category":"Personal",
            "subcategory":"Beauty Salon",
            "type":"Services"
        }
    ],
    "sg:phone":"+1 310 370 8696",
    "sg:postcode":"90260",
    "sg:province":"CA",
    "wof:name":"Rosie's Hair Salon",
    "wof:placetype":"venue"
},
  "geometry": {"coordinates":[-118.345355,33.876916],"type":"Point"}
}