{
  "type": "Feature",
  "properties": {
    "iso:country":"US",
    "sg:address":"24141 Humphries Rd",
    "sg:city":"Tecate",
    "sg:classifiers":[
        {
            "category":"Manufacturing",
            "subcategory":"Glass & Minerals",
            "type":"Manufacturing & Wholesale Goods"
        }
    ],
    "sg:phone":"+1 619 478 5881",
    "sg:postcode":"91980",
    "sg:province":"CA",
    "wof:name":"Glass By Salazar Inc",
    "wof:placetype":"venue"
},
  "geometry": {"coordinates":[-116.632535,32.582561],"type":"Point"}
}