{
  "type": "Feature",
  "properties": {
    "iso:country":"US",
    "sg:address":"403 S Fairfax Ave",
    "sg:city":"Los Angeles",
    "sg:classifiers":[
        {
            "category":"Health Services",
            "subcategory":"Clinic",
            "type":"Services"
        },
        {
            "category":"Personal",
            "subcategory":"Beauty Salon",
            "type":"Services"
        }
    ],
    "sg:phone":"+1 323 655 8385",
    "sg:postcode":"90036",
    "sg:province":"CA",
    "sg:tags":[
        "spa",
        "medical"
    ],
    "sg:website":"www.aquarianwellness.com",
    "wof:name":"Aquarian Wellness",
    "wof:placetype":"venue"
},
  "geometry": {"coordinates":[-118.36157,34.069756],"type":"Point"}
}