{
  "type": "Feature",
  "properties": {
    "addr:full":"40414 California Oaks Rd Murrieta CA 92562",
    "addr:housenumber":"40414",
    "addr:postcode":"92562",
    "addr:street":"California Oaks Rd",
    "iso:country":"US",
    "sg:address":"40414 California Oaks Rd",
    "sg:city":"Murrieta",
    "sg:classifiers":[
        {
            "category":"Wholesale",
            "subcategory":"Medical Equipment & Supplies",
            "type":"Manufacturing & Wholesale Goods"
        }
    ],
    "sg:phone":"+1 951 600 1635",
    "sg:postcode":"92562",
    "sg:province":"CA",
    "sg:tags":[
        "physician",
        "surgeon"
    ],
    "wof:name":"Health & Mobility",
    "wof:placetype":"venue"
},
  "geometry": {"coordinates":[-117.200958,33.577034],"type":"Point"}
}