{
  "type": "Feature",
  "properties": {
    "iso:country":"US",
    "sg:address":"3075 Los Feliz Dr",
    "sg:city":"Thousand Oaks",
    "sg:classifiers":[
        {
            "category":"Retail",
            "subcategory":"Auto Repair",
            "type":"Services"
        }
    ],
    "sg:phone":"+1 805 379 3411",
    "sg:postcode":"91362",
    "sg:province":"CA",
    "sg:tags":[
        "body",
        "automobile",
        "painting"
    ],
    "wof:name":"North Ranch Body Craft",
    "wof:placetype":"venue"
},
  "geometry": {"coordinates":[-118.83425699999999,34.170823],"type":"Point"}
}