{
  "type": "Feature",
  "properties": {
    "addr:full":"7349 Madison Avenue Citrus Heights CA 95621",
    "addr:housenumber":"7349",
    "addr:postcode":"95621",
    "addr:street":"Madison Avenue",
    "iso:country":"US",
    "sg:address":"7349 Madison Avenue",
    "sg:city":"Citrus Heights",
    "sg:classifiers":[
        {
            "category":"Restaurant",
            "type":"Food & Drink"
        }
    ],
    "sg:phone":"+1 916 436 2666",
    "sg:postcode":"95621",
    "sg:province":"CA",
    "sg:tags":[
        "mexican"
    ],
    "wof:name":"Jimboys Tacos",
    "wof:placetype":"venue"
},
  "geometry": {"coordinates":[-121.293735,38.663799],"type":"Point"}
}