{
  "type": "Feature",
  "properties": {
    "iso:country":"US",
    "sg:address":"10138 Rush St",
    "sg:city":"South El Monte",
    "sg:classifiers":[
        {
            "category":"Shopping",
            "subcategory":"Shoes",
            "type":"Retail Goods"
        }
    ],
    "sg:phone":"+1 626 442 3912",
    "sg:postcode":"91733",
    "sg:province":"CA",
    "wof:name":"China Shoes Co",
    "wof:placetype":"venue"
},
  "geometry": {"coordinates":[-118.048714,34.051761],"type":"Point"}
}