{
  "type": "Feature",
  "properties": {
    "iso:country":"US",
    "sg:address":"305 Durley Ave",
    "sg:city":"Camarillo",
    "sg:phone":"+1 805 388 6411",
    "sg:postcode":"93010",
    "sg:province":"CA",
    "sg:tags":[
        "fuel",
        "aviation"
    ],
    "wof:name":"Valley Oil",
    "wof:placetype":"venue"
},
  "geometry": {"coordinates":[-119.07731099999999,34.208743],"type":"Point"}
}