{
  "type": "Feature",
  "properties": {
    "iso:country":"US",
    "sg:address":"860 E Remington Dr",
    "sg:city":"Sunnyvale",
    "sg:classifiers":[
        {
            "category":"Health Services",
            "subcategory":"Doctor",
            "type":"Services"
        }
    ],
    "sg:phone":"+1 408 245 3410",
    "sg:postcode":"94087",
    "sg:province":"CA",
    "sg:tags":[
        "dentist"
    ],
    "wof:name":"Bruce Schwartz DDS",
    "wof:placetype":"venue"
},
  "geometry": {"coordinates":[-122.025306,37.36037],"type":"Point"}
}