{
  "type": "Feature",
  "properties": {
    "addr:full":"572 Praderia Cir Fremont CA 94539",
    "addr:housenumber":"572",
    "addr:postcode":"94539",
    "addr:street":"Praderia Cir",
    "iso:country":"US",
    "sg:address":"572 Praderia Cir",
    "sg:city":"Fremont",
    "sg:classifiers":[
        {
            "category":"Professional",
            "type":"Services"
        }
    ],
    "sg:phone":"+1 510 651 2388",
    "sg:postcode":"94539",
    "sg:province":"CA",
    "wof:name":"Victor Lam",
    "wof:placetype":"venue"
},
  "geometry": {"coordinates":[-121.922409,37.519695],"type":"Point"}
}