{
  "type": "Feature",
  "properties": {
    "addr:full":"6310 la Mesa St Corona CA 92880",
    "addr:housenumber":"6310",
    "addr:postcode":"92880",
    "addr:street":"La Mesa St",
    "iso:country":"US",
    "sg:address":"6310 la Mesa St",
    "sg:city":"Corona",
    "sg:classifiers":[
        {
            "category":"Building & Trades",
            "subcategory":"Plumbing",
            "type":"Services"
        },
        {
            "category":"Building & Trades",
            "subcategory":"Construction",
            "type":"Services"
        }
    ],
    "sg:phone":"+1 951 520 8881",
    "sg:postcode":"92880",
    "sg:province":"CA",
    "sg:tags":[
        "plumber",
        "industrial",
        "system",
        "specialty",
        "heating",
        "contractors-commercial",
        "contractor",
        "air conditioning"
    ],
    "wof:name":"Worldwide Plumbing Heating & Air Conditioning",
    "wof:placetype":"venue"
},
  "geometry": {"coordinates":[-117.58278900000001,33.972919],"type":"Point"}
}