{
  "type": "Feature",
  "properties": {
    "addr:full":"525 Berry St San Francisco CA 94107",
    "addr:housenumber":"525",
    "addr:postcode":"94107",
    "addr:street":"Berry St",
    "iso:country":"US",
    "sg:address":"525 Berry St",
    "sg:city":"San Francisco",
    "sg:classifiers":[
        {
            "category":"Utilities",
            "subcategory":"Refuse",
            "type":"Services"
        }
    ],
    "sg:phone":"+1 415 621 3841",
    "sg:postcode":"94107",
    "sg:province":"CA",
    "sg:tags":[
        "equipment",
        "industrial",
        "system"
    ],
    "wof:name":"Spa Debris Box Service",
    "wof:placetype":"venue"
},
  "geometry": {"coordinates":[-122.40129399999999,37.769483],"type":"Point"}
}