{
  "type": "Feature",
  "properties": {
    "iso:country":"US",
    "sg:address":"1802 Lacey Blvd",
    "sg:city":"Hanford",
    "sg:classifiers":[
        {
            "category":"Building & Trades",
            "subcategory":"Cleaning & Sanitation",
            "type":"Services"
        }
    ],
    "sg:phone":"+1 559 585 1239",
    "sg:postcode":"93230",
    "sg:province":"CA",
    "sg:tags":[
        "property",
        "maintenance"
    ],
    "wof:name":"Pan Pacific Retail Properties",
    "wof:placetype":"venue"
},
  "geometry": {"coordinates":[-119.4872,36.328037],"type":"Point"}
}