{
  "type": "Feature",
  "properties": {
    "iso:country":"US",
    "sg:address":"401 W Radio Rd",
    "sg:city":"Palm Springs",
    "sg:classifiers":[
        {
            "category":"Retail",
            "subcategory":"Car Wash",
            "type":"Services"
        }
    ],
    "sg:phone":"+1 760 416 3073",
    "sg:postcode":"92262",
    "sg:province":"CA",
    "sg:tags":[
        "polishing",
        "washing"
    ],
    "wof:name":"Robert's Auto Detail",
    "wof:placetype":"venue"
},
  "geometry": {"coordinates":[-116.550003,33.862301],"type":"Point"}
}