{
  "type": "Feature",
  "properties": {
    "iso:country":"US",
    "sg:address":"1156 Story Rd",
    "sg:city":"San Jose",
    "sg:classifiers":[
        {
            "category":"Restaurant",
            "type":"Food & Drink"
        }
    ],
    "sg:phone":"+1 408 279 9947",
    "sg:postcode":"95122",
    "sg:province":"CA",
    "sg:tags":[
        "vegetarian"
    ],
    "wof:name":"Dong Phuong Tofu",
    "wof:placetype":"venue"
},
  "geometry": {"coordinates":[-121.853593,37.332615],"type":"Point"}
}