{
  "type": "Feature",
  "properties": {
    "iso:country":"US",
    "sg:address":"17220 Saticoy St",
    "sg:city":"Van Nuys",
    "sg:classifiers":[
        {
            "category":"Retail",
            "subcategory":"Laundry & Dry Cleaning",
            "type":"Services"
        }
    ],
    "sg:phone":"+1 818 881 3130",
    "sg:postcode":"91406",
    "sg:province":"CA",
    "sg:tags":[
        "cleaners"
    ],
    "wof:name":"Daisy Fresh Cleaners",
    "wof:placetype":"venue"
},
  "geometry": {"coordinates":[-118.507676,34.208339],"type":"Point"}
}