{
  "type": "Feature",
  "properties": {
    "addr:full":"1001 Colorado Ave Santa Monica CA 90401",
    "addr:housenumber":"1001",
    "addr:postcode":"90401",
    "addr:street":"Colorado Ave",
    "iso:country":"US",
    "sg:address":"1001 Colorado Ave",
    "sg:city":"Santa Monica",
    "sg:classifiers":[
        {
            "category":"Arts & Performance",
            "subcategory":"Theater",
            "type":"Entertainment"
        }
    ],
    "sg:phone":"+1 323 871 1200",
    "sg:postcode":"90401",
    "sg:province":"CA",
    "sg:tags":[
        "television",
        "program",
        "producer"
    ],
    "wof:name":"Gary Smith Co",
    "wof:placetype":"venue"
},
  "geometry": {"coordinates":[-118.48588100000001,34.018761],"type":"Point"}
}