{
  "type": "Feature",
  "properties": {
    "addr:full":"1611 E Capitol Expy 202 San Jose CA 95121",
    "addr:housenumber":"1611;202",
    "addr:postcode":"95121",
    "addr:street":"E Capitol Expy",
    "iso:country":"US",
    "sg:address":"1611 E Capitol Expy 202",
    "sg:city":"San Jose",
    "sg:classifiers":[
        {
            "category":"Ice Cream",
            "type":"Food & Drink"
        }
    ],
    "sg:phone":"+1 408 270 8388",
    "sg:postcode":"95121",
    "sg:province":"CA",
    "sg:tags":[
        "frozen",
        "yogurt"
    ],
    "wof:name":"Toppings Frozen Yogurt",
    "wof:placetype":"venue"
},
  "geometry": {"coordinates":[-121.812755,37.306259],"type":"Point"}
}