{
  "type": "Feature",
  "properties": {
    "iso:country":"US",
    "sg:address":"2310 E Orangethorpe Ave",
    "sg:city":"Anaheim",
    "sg:classifiers":[
        {
            "category":"Wholesale",
            "subcategory":"Computers",
            "type":"Manufacturing & Wholesale Goods"
        }
    ],
    "sg:phone":"+1 714 738 6194",
    "sg:postcode":"92806",
    "sg:province":"CA",
    "wof:name":"Card Locks Unlimited",
    "wof:placetype":"venue"
},
  "geometry": {"coordinates":[-117.86188,33.865001],"type":"Point"}
}