{
  "type": "Feature",
  "properties": {
    "iso:country":"US",
    "sg:address":"3769 Peralta Blvd",
    "sg:city":"Fremont",
    "sg:classifiers":[
        {
            "category":"Banks & Credit Unions",
            "subcategory":"Investment Brokerage",
            "type":"Services"
        }
    ],
    "sg:phone":"+1 510 795 7978",
    "sg:postcode":"94536",
    "sg:province":"CA",
    "sg:tags":[
        "advisory",
        "financial"
    ],
    "wof:name":"American Investors Co",
    "wof:placetype":"venue"
},
  "geometry": {"coordinates":[-122.00621599999999,37.558978],"type":"Point"}
}