{
  "type": "Feature",
  "properties": {
    "addr:full":"19901 1st St Hilmar CA 95324",
    "addr:housenumber":"19901",
    "addr:postcode":"95324",
    "addr:street":"1St St",
    "iso:country":"US",
    "sg:address":"19901 1st St",
    "sg:city":"Hilmar",
    "sg:classifiers":[
        {
            "category":"Freight",
            "type":"Transportation"
        }
    ],
    "sg:phone":"+1 209 634 4991",
    "sg:postcode":"95324",
    "sg:province":"CA",
    "sg:tags":[
        "commercial",
        "storage"
    ],
    "wof:name":"Hilmar Mini Storage",
    "wof:placetype":"venue"
},
  "geometry": {"coordinates":[-120.84817099999999,37.407799],"type":"Point"}
}