{
  "type": "Feature",
  "properties": {
    "iso:country":"US",
    "sg:address":"4342 Tujunga Ave",
    "sg:city":"Studio City",
    "sg:classifiers":[
        {
            "category":"Shopping",
            "subcategory":"Jewelry",
            "type":"Retail Goods"
        }
    ],
    "sg:phone":"+1 818 763 0111",
    "sg:postcode":"91604",
    "sg:province":"CA",
    "wof:name":"Trinkets & Treasures",
    "wof:placetype":"venue"
},
  "geometry": {"coordinates":[-118.378998,34.1493],"type":"Point"}
}