{
  "type": "Feature",
  "properties": {
    "addr:full":"9122 W Pico Blvd Los Angeles CA 90035",
    "addr:housenumber":"9122",
    "addr:postcode":"90035",
    "addr:street":"W Pico Blvd",
    "iso:country":"US",
    "sg:address":"9122 W Pico Blvd",
    "sg:city":"Los Angeles",
    "sg:classifiers":[
        {
            "category":"Shopping",
            "subcategory":"Gifts & Souvenirs",
            "type":"Retail Goods"
        }
    ],
    "sg:phone":"+1 310 550 3919",
    "sg:postcode":"90035",
    "sg:province":"CA",
    "wof:name":"Cadeau",
    "wof:placetype":"venue"
},
  "geometry": {"coordinates":[-118.390113,34.055187],"type":"Point"}
}