{
  "type": "Feature",
  "properties": {
    "addr:full":"221 S Mooney Blvd Visalia CA 93291",
    "addr:housenumber":"221",
    "addr:postcode":"93291",
    "addr:street":"S Mooney Blvd",
    "iso:country":"US",
    "sg:address":"221 S Mooney Blvd",
    "sg:city":"Visalia",
    "sg:classifiers":[
        {
            "category":"Government",
            "subcategory":"Court House",
            "type":"Public Place"
        },
        {
            "category":"Government",
            "subcategory":"Office",
            "type":"Public Place"
        }
    ],
    "sg:phone":"+1 559 733 6377",
    "sg:postcode":"93291",
    "sg:province":"CA",
    "sg:tags":[
        "recorder",
        "deeds"
    ],
    "wof:name":"Tulare County Recorder Deeds",
    "wof:placetype":"venue"
},
  "geometry": {"coordinates":[-119.3141,36.32909],"type":"Point"}
}