{
  "type": "Feature",
  "properties": {
    "addr:full":"9300 Toledo Way Irvine CA 92630",
    "addr:housenumber":"9300",
    "addr:postcode":"92630",
    "addr:street":"Toledo Way",
    "iso:country":"US",
    "sg:address":"9300 Toledo Way",
    "sg:city":"Irvine",
    "sg:classifiers":[
        {
            "category":"Wholesale",
            "subcategory":"Groceries",
            "type":"Manufacturing & Wholesale Goods"
        }
    ],
    "sg:phone":"+1 949 855 9400",
    "sg:postcode":"92630",
    "sg:province":"CA",
    "sg:tags":[
        "grocer"
    ],
    "wof:name":"Albertsons Distribution Ctr",
    "wof:placetype":"venue"
},
  "geometry": {"coordinates":[-117.714299,33.657793],"type":"Point"}
}