{
  "type": "Feature",
  "properties": {
    "iso:country":"US",
    "sg:address":"400 Cambridge Ave",
    "sg:city":"Palo Alto",
    "sg:classifiers":[
        {
            "category":"Professional",
            "subcategory":"Lawyer & Legal Services",
            "type":"Services"
        }
    ],
    "sg:phone":"+1 650 321 2610",
    "sg:postcode":"94306",
    "sg:province":"CA",
    "sg:tags":[
        "attorney"
    ],
    "wof:name":"David G Harvey",
    "wof:placetype":"venue"
},
  "geometry": {"coordinates":[-122.145512,37.427212],"type":"Point"}
}