{
  "type": "Feature",
  "properties": {
    "iso:country":"US",
    "sg:address":"1055 Mellow Ln",
    "sg:city":"Simi Valley",
    "sg:classifiers":[
        {
            "category":"Real Estate",
            "subcategory":"Real Estate Agent",
            "type":"Services"
        }
    ],
    "sg:phone":"+1 805 527 0736",
    "sg:postcode":"93065",
    "sg:province":"CA",
    "wof:name":"REO Resources",
    "wof:placetype":"venue"
},
  "geometry": {"coordinates":[-118.780652,34.24802],"type":"Point"}
}