{
  "type": "Feature",
  "properties": {
    "iso:country":"US",
    "sg:address":"9800 San Fernando Rd",
    "sg:city":"Pacoima",
    "sg:classifiers":[
        {
            "category":"Autos & Motor Vehicles",
            "subcategory":"Automobile Sales",
            "type":"Retail Goods"
        },
        {
            "category":"Autos & Motor Vehicles",
            "subcategory":"Auto Supplies",
            "type":"Retail Goods"
        },
        {
            "category":"Wholesale",
            "subcategory":"Auto Parts",
            "type":"Manufacturing & Wholesale Goods"
        }
    ],
    "sg:phone":"+1 818 890 0506",
    "sg:postcode":"91331",
    "sg:province":"CA",
    "sg:tags":[
        "car",
        "accessory",
        "rebuilt-wholesale",
        "supplies-used",
        "new",
        "manufacturer"
    ],
    "wof:name":"Jeep Only Auto Parts",
    "wof:placetype":"venue"
},
  "geometry": {"coordinates":[-118.402832,34.248508],"type":"Point"}
}