{
  "type": "Feature",
  "properties": {
    "iso:country":"US",
    "sg:address":"505 Ironwood Rd",
    "sg:city":"Alameda",
    "sg:classifiers":[
        {
            "category":"Real Estate",
            "subcategory":"Real Estate Agent",
            "type":"Services"
        }
    ],
    "sg:phone":"+1 510 749 0780",
    "sg:postcode":"94502",
    "sg:province":"CA",
    "wof:name":"Lena Sazo Real Estate",
    "wof:placetype":"venue"
},
  "geometry": {"coordinates":[-122.24473,37.738944],"type":"Point"}
}