{
  "type": "Feature",
  "properties": {
    "addr:full":"20900 Clarin St Woodland Hills CA 91364",
    "addr:postcode":"20900;91364",
    "addr:street":"Clarin St",
    "iso:country":"US",
    "sg:address":"20900 Clarin St",
    "sg:city":"Woodland Hills",
    "sg:classifiers":[
        {
            "category":"Utilities",
            "subcategory":"Mobile Phone",
            "type":"Services"
        }
    ],
    "sg:phone":"+1 818 414 4445",
    "sg:postcode":"91364",
    "sg:province":"CA",
    "sg:tags":[
        "communication",
        "radiotelephone"
    ],
    "wof:name":"Cellular Stuff",
    "wof:placetype":"venue"
},
  "geometry": {"coordinates":[-118.589113,34.157627],"type":"Point"}
}