{
  "type": "Feature",
  "properties": {
    "addr:full":"5285 W. Pico Blvd. West Hollywood CA 90019",
    "addr:housenumber":"5285",
    "addr:postcode":"90019",
    "addr:street":"W. Pico Blvd.",
    "iso:country":"US",
    "sg:address":"5285 W. Pico Blvd.",
    "sg:city":"West Hollywood",
    "sg:classifiers":[
        {
            "category":"Shopping",
            "subcategory":"Clothing, Apparel, & Fashions",
            "type":"Retail Goods"
        }
    ],
    "sg:phone":"+1 310 659 1177",
    "sg:postcode":"90019",
    "sg:province":"CA",
    "sg:website":"visionaryboutique.com",
    "wof:name":"Visionary by Wildchild Wear",
    "wof:placetype":"venue"
},
  "geometry": {"coordinates":[-118.353595,34.048305],"type":"Point"}
}