{
  "type": "Feature",
  "properties": {
    "addr:full":"6807 Woodman Ave Van Nuys CA 91405",
    "addr:housenumber":"6807",
    "addr:postcode":"91405",
    "addr:street":"Woodman Ave",
    "iso:country":"US",
    "sg:address":"6807 Woodman Ave",
    "sg:city":"Van Nuys",
    "sg:classifiers":[
        {
            "category":"Food & Beverages",
            "subcategory":"Meat & Fish",
            "type":"Retail Goods"
        }
    ],
    "sg:phone":"+1 818 786 4703",
    "sg:postcode":"91405",
    "sg:province":"CA",
    "sg:tags":[
        "shop",
        "mexican"
    ],
    "wof:name":"Carniceria Vallarta No 2",
    "wof:placetype":"venue"
},
  "geometry": {"coordinates":[-118.431,34.194599],"type":"Point"}
}