{
  "type": "Feature",
  "properties": {
    "iso:country":"US",
    "sg:address":"217 H St",
    "sg:city":"Bakersfield",
    "sg:classifiers":[
        {
            "category":"Personal",
            "subcategory":"Massage",
            "type":"Services"
        }
    ],
    "sg:phone":"+1 661 342 5033",
    "sg:postcode":"93304",
    "sg:province":"CA",
    "wof:name":"Natural Healing",
    "wof:placetype":"venue"
},
  "geometry": {"coordinates":[-119.021299,35.356986],"type":"Point"}
}