{
  "type": "Feature",
  "properties": {
    "iso:country":"US",
    "sg:address":"2315 Chico Ave Ste 2",
    "sg:city":"South El Monte",
    "sg:classifiers":[
        {
            "category":"Home & Garden",
            "subcategory":"Garden Supply",
            "type":"Retail Goods"
        }
    ],
    "sg:phone":"+1 626 350 1768",
    "sg:postcode":"91733",
    "sg:province":"CA",
    "sg:tags":[
        "nursery",
        "gardening"
    ],
    "sg:website":"www.jiameigarden.com",
    "wof:name":"Jiamei Garden USA Inc",
    "wof:placetype":"venue"
},
  "geometry": {"coordinates":[-118.06161,34.054429],"type":"Point"}
}