{
  "type": "Feature",
  "properties": {
    "iso:country":"US",
    "sg:address":"1800 E Tahquitz Canyon Way",
    "sg:city":"Palm Springs",
    "sg:classifiers":[
        {
            "category":"Professional",
            "subcategory":"Lawyer & Legal Services",
            "type":"Services"
        }
    ],
    "sg:phone":"+1 760 322 2275",
    "sg:postcode":"92262",
    "sg:province":"CA",
    "wof:name":"Gilstrap Mary E Atty",
    "wof:placetype":"venue"
},
  "geometry": {"coordinates":[-116.526573,33.82341],"type":"Point"}
}