{
  "type": "Feature",
  "properties": {
    "addr:full":"6260 Commodore Sloat Drive Los Angeles CA 90048",
    "addr:housenumber":"6260",
    "addr:postcode":"90048",
    "addr:street":"Commodore Sloat Drive",
    "iso:country":"US",
    "sg:address":"6260 Commodore Sloat Drive",
    "sg:city":"Los Angeles",
    "sg:classifiers":[
        {
            "category":"Professional",
            "subcategory":"Lawyer & Legal Services",
            "type":"Services"
        }
    ],
    "sg:phone":"+1 323 933 7823",
    "sg:postcode":"90048",
    "sg:province":"CA",
    "wof:name":"Anthony J",
    "wof:placetype":"venue"
},
  "geometry": {"coordinates":[-118.36703900000001,34.059607],"type":"Point"}
}