{
  "type": "Feature",
  "properties": {
    "iso:country":"US",
    "sg:address":"2650 Foothill Blvd",
    "sg:city":"La Crescenta",
    "sg:classifiers":[
        {
            "category":"Restaurant",
            "type":"Food & Drink"
        }
    ],
    "sg:phone":"+1 818 248 8500",
    "sg:postcode":"91214",
    "sg:province":"CA",
    "sg:tags":[
        "sushi",
        "bar"
    ],
    "wof:name":"Sushi Zen Bistro",
    "wof:placetype":"venue"
},
  "geometry": {"coordinates":[-118.237026,34.221935],"type":"Point"}
}