{
  "type": "Feature",
  "properties": {
    "iso:country":"US",
    "sg:address":"2014 Earl St",
    "sg:city":"San Diego",
    "sg:classifiers":[
        {
            "category":"Building & Trades",
            "subcategory":"Construction",
            "type":"Services"
        }
    ],
    "sg:phone":"+1 619 263 7391",
    "sg:postcode":"92113",
    "sg:province":"CA",
    "sg:tags":[
        "painter"
    ],
    "wof:name":"Felipes Painting",
    "wof:placetype":"venue"
},
  "geometry": {"coordinates":[-117.10887700000001,32.684949],"type":"Point"}
}