{
  "type": "Feature",
  "properties": {
    "iso:country":"US",
    "sg:address":"Haight St and Divisadero St",
    "sg:city":"San Francisco",
    "sg:classifiers":[
        {
            "category":"Health Services",
            "subcategory":"Clinic",
            "type":"Services"
        }
    ],
    "sg:phone":"+1 415 431 3220",
    "sg:postcode":"94117",
    "sg:province":"CA",
    "sg:tags":[
        "counseling",
        "mental"
    ],
    "sg:website":"truthandcompassion.com",
    "wof:name":"Dave Cooperberg, MFT",
    "wof:placetype":"venue"
},
  "geometry": {"coordinates":[-122.43702,37.771277],"type":"Point"}
}