{
  "type": "Feature",
  "properties": {
    "iso:country":"US",
    "sg:address":"740 Broadway St",
    "sg:city":"Chico",
    "sg:classifiers":[
        {
            "category":"Professional",
            "type":"Services"
        }
    ],
    "sg:phone":"+1 530 892 2693",
    "sg:postcode":"95928",
    "sg:province":"CA",
    "sg:tags":[
        "establishment"
    ],
    "wof:name":"Index Enterprises",
    "wof:placetype":"venue"
},
  "geometry": {"coordinates":[-121.836922,39.72583],"type":"Point"}
}