{
  "type": "Feature",
  "properties": {
    "addr:full":"9941 Horn Rd Ste E Sacramento CA 95827",
    "addr:housenumber":"9941",
    "addr:postcode":"95827",
    "addr:street":"Horn Rd Ste E",
    "iso:country":"US",
    "sg:address":"9941 Horn Rd Ste E",
    "sg:city":"Sacramento",
    "sg:classifiers":[
        {
            "category":"Manufacturing",
            "subcategory":"Textiles",
            "type":"Manufacturing & Wholesale Goods"
        },
        {
            "category":"Building & Trades",
            "subcategory":"Construction",
            "type":"Services"
        },
        {
            "category":"Home & Garden",
            "subcategory":"Carpets & Floor Coverings",
            "type":"Retail Goods"
        }
    ],
    "sg:phone":"+1 916 362 8300",
    "sg:postcode":"95827",
    "sg:province":"CA",
    "sg:tags":[
        "tile-wholesale",
        "material",
        "manufacturer",
        "tile-contractors"
    ],
    "wof:name":"Tile Outlet",
    "wof:placetype":"venue"
},
  "geometry": {"coordinates":[-121.32434600000001,38.576291],"type":"Point"}
}