{
  "type": "Feature",
  "properties": {
    "iso:country":"US",
    "sg:address":"5864 E Ramona Ave",
    "sg:city":"Fresno",
    "sg:classifiers":[
        {
            "category":"Personal",
            "subcategory":"Beauty Salon",
            "type":"Services"
        }
    ],
    "sg:phone":"+1 559 292 3968",
    "sg:postcode":"93727",
    "sg:province":"CA",
    "sg:tags":[
        "clothing",
        "family"
    ],
    "wof:name":"Kalolas Hawaiian Fashions",
    "wof:placetype":"venue"
},
  "geometry": {"coordinates":[-119.68841,36.785158],"type":"Point"}
}