{
  "type": "Feature",
  "properties": {
    "addr:full":"202 Avon Ln Fillmore CA 93015",
    "addr:housenumber":"202",
    "addr:postcode":"93015",
    "addr:street":"Avon Ln",
    "iso:country":"US",
    "sg:address":"202 Avon Ln",
    "sg:city":"Fillmore",
    "sg:classifiers":[
        {
            "category":"Professional",
            "type":"Services"
        }
    ],
    "sg:phone":"+1 805 524 7497",
    "sg:postcode":"93015",
    "sg:province":"CA",
    "wof:name":"Bernardo Montelongo",
    "wof:placetype":"venue"
},
  "geometry": {"coordinates":[-118.926276,34.395131],"type":"Point"}
}