{
  "type": "Feature",
  "properties": {
    "addr:full":"505 N Brand Blvd Ste 1460 Glendale CA 91203",
    "addr:housenumber":"505",
    "addr:postcode":"91203",
    "addr:street":"N Brand Blvd Ste 1460",
    "iso:country":"US",
    "sg:address":"505 N Brand Blvd Ste 1460",
    "sg:city":"Glendale",
    "sg:classifiers":[
        {
            "category":"Professional",
            "subcategory":"Lawyer & Legal Services",
            "type":"Services"
        }
    ],
    "sg:phone":"+1 818 552 2626",
    "sg:postcode":"91203",
    "sg:province":"CA",
    "wof:name":"Law Offices Of Abraham Chaparian",
    "wof:placetype":"venue"
},
  "geometry": {"coordinates":[-118.255246,34.153027],"type":"Point"}
}