{
  "type": "Feature",
  "properties": {
    "iso:country":"US",
    "sg:address":"5500 Oswald Rd",
    "sg:city":"Yuba City",
    "sg:phone":"+1 530 673 8624",
    "sg:postcode":"95993",
    "sg:province":"CA",
    "sg:tags":[
        "farm",
        "rice"
    ],
    "wof:name":"Shannon Ranches",
    "wof:placetype":"venue"
},
  "geometry": {"coordinates":[-121.717564,39.069007],"type":"Point"}
}