{
  "type": "Feature",
  "properties": {
    "addr:full":"1828 N Milpitas Boulevard Milpitas CA 95035",
    "addr:housenumber":"1828",
    "addr:postcode":"95035",
    "addr:street":"N Milpitas Boulevard",
    "iso:country":"US",
    "sg:address":"1828 N Milpitas Boulevard",
    "sg:city":"Milpitas",
    "sg:classifiers":[
        {
            "category":"Restaurant",
            "type":"Food & Drink"
        }
    ],
    "sg:phone":"+1 408 942 1685",
    "sg:postcode":"95035",
    "sg:province":"CA",
    "sg:tags":[
        "chinese"
    ],
    "wof:name":"New China Station Bbq Restaurant",
    "wof:placetype":"venue"
},
  "geometry": {"coordinates":[-121.911045,37.456433],"type":"Point"}
}