{
  "type": "Feature",
  "properties": {
    "iso:country":"US",
    "sg:address":"201 N Los Angeles St",
    "sg:city":"Los Angeles",
    "sg:classifiers":[
        {
            "category":"Utilities",
            "subcategory":"Mobile Phone",
            "type":"Services"
        }
    ],
    "sg:phone":"+1 213 626 1467",
    "sg:postcode":"90012",
    "sg:province":"CA",
    "sg:tags":[
        "telephone",
        "cellular"
    ],
    "wof:name":"Visual Wireless",
    "wof:placetype":"venue"
},
  "geometry": {"coordinates":[-118.241676,34.052412],"type":"Point"}
}