{
  "type": "Feature",
  "properties": {
    "iso:country":"US",
    "sg:address":"5938 Florence Ave",
    "sg:city":"Bell Gardens",
    "sg:classifiers":[
        {
            "category":"Retail",
            "subcategory":"Animal Services",
            "type":"Services"
        }
    ],
    "sg:phone":"+1 323 771 7587",
    "sg:postcode":"90201",
    "sg:province":"CA",
    "sg:tags":[
        "pet",
        "grooming",
        "washing"
    ],
    "wof:name":"Mr G's Pride & Groom",
    "wof:placetype":"venue"
},
  "geometry": {"coordinates":[-118.16387,33.967743],"type":"Point"}
}