{
  "type": "Feature",
  "properties": {
    "addr:full":"2074 Oldham Pl Manteca CA 95336",
    "addr:housenumber":"2074",
    "addr:postcode":"95336",
    "addr:street":"Oldham Pl",
    "iso:country":"US",
    "sg:address":"2074 Oldham Pl",
    "sg:city":"Manteca",
    "sg:classifiers":[
        {
            "category":"Retail",
            "subcategory":"Animal Services",
            "type":"Services"
        }
    ],
    "sg:phone":"+1 209 823 7589",
    "sg:postcode":"95336",
    "sg:province":"CA",
    "wof:name":"California Zoo",
    "wof:placetype":"venue"
},
  "geometry": {"coordinates":[-121.231661,37.825369],"type":"Point"}
}