{
  "type": "Feature",
  "properties": {
    "iso:country":"US",
    "sg:address":"17671 Metzler Ln Ste A1",
    "sg:city":"Huntington Beach",
    "sg:classifiers":[
        {
            "category":"Retail",
            "subcategory":"Auto Repair",
            "type":"Services"
        }
    ],
    "sg:phone":"+1 714 842 0042",
    "sg:postcode":"92647",
    "sg:province":"CA",
    "wof:name":"Eagleton's Custom Auto Paint & Body",
    "wof:placetype":"venue"
},
  "geometry": {"coordinates":[-117.99870900000001,33.705898],"type":"Point"}
}