{
  "type": "Feature",
  "properties": {
    "iso:country":"US",
    "sg:address":"479 Boquest Blvd",
    "sg:city":"Paradise",
    "sg:classifiers":[
        {
            "category":"Building & Trades",
            "subcategory":"Construction",
            "type":"Services"
        }
    ],
    "sg:phone":"+1 530 876 0369",
    "sg:postcode":"95969",
    "sg:province":"CA",
    "sg:tags":[
        "mobile",
        "home"
    ],
    "wof:name":"Jerry's Mobile Home Svc",
    "wof:placetype":"venue"
},
  "geometry": {"coordinates":[-121.62875,39.758251],"type":"Point"}
}