{
  "type": "Feature",
  "properties": {
    "iso:country":"US",
    "sg:address":"22555 Allview Ter",
    "sg:city":"Laguna Beach",
    "sg:classifiers":[
        {
            "category":"Professional",
            "subcategory":"Lawyer & Legal Services",
            "type":"Services"
        }
    ],
    "sg:phone":"+1 949 720 1975",
    "sg:postcode":"92651",
    "sg:province":"CA",
    "sg:tags":[
        "attorney"
    ],
    "wof:name":"Kaufman & Morgan Law Offices",
    "wof:placetype":"venue"
},
  "geometry": {"coordinates":[-117.790128,33.550128],"type":"Point"}
}