{
  "type": "Feature",
  "properties": {
    "iso:country":"US",
    "sg:address":"990 el Camino Ave",
    "sg:city":"Sacramento",
    "sg:classifiers":[
        {
            "category":"Wholesale",
            "subcategory":"Auto Parts",
            "type":"Manufacturing & Wholesale Goods"
        }
    ],
    "sg:phone":"+1 916 920 8879",
    "sg:postcode":"95815",
    "sg:province":"CA",
    "wof:name":"Quality Tire & Wheels",
    "wof:placetype":"venue"
},
  "geometry": {"coordinates":[-121.44463500000001,38.611046],"type":"Point"}
}