{
  "type": "Feature",
  "properties": {
    "addr:full":"127 S San Pedro St Los Angeles CA 90012",
    "addr:housenumber":"127",
    "addr:postcode":"90012",
    "addr:street":"S San Pedro St",
    "iso:country":"US",
    "sg:address":"127 S San Pedro St",
    "sg:city":"Los Angeles",
    "sg:classifiers":[
        {
            "category":"Professional",
            "type":"Services"
        }
    ],
    "sg:phone":"+1 213 680 2899",
    "sg:postcode":"90012",
    "sg:province":"CA",
    "sg:tags":[
        "establishment"
    ],
    "wof:name":"Local Japan Inc",
    "wof:placetype":"venue"
},
  "geometry": {"coordinates":[-118.241795,34.049346],"type":"Point"}
}