{
  "type": "Feature",
  "properties": {
    "iso:country":"US",
    "sg:address":"1552 W Embassy St",
    "sg:city":"Anaheim",
    "sg:classifiers":[
        {
            "category":"Real Estate",
            "subcategory":"Architect",
            "type":"Services"
        }
    ],
    "sg:phone":"+1 714 758 1600",
    "sg:postcode":"92802",
    "sg:province":"CA",
    "wof:name":"Newport Foam",
    "wof:placetype":"venue"
},
  "geometry": {"coordinates":[-117.93602300000001,33.831272],"type":"Point"}
}