{
  "type": "Feature",
  "properties": {
    "addr:full":"1961 N Newcomb St Porterville CA 93257",
    "addr:housenumber":"1961",
    "addr:postcode":"93257",
    "addr:street":"N Newcomb St",
    "iso:country":"US",
    "sg:address":"1961 N Newcomb St",
    "sg:city":"Porterville",
    "sg:classifiers":[
        {
            "category":"Building & Trades",
            "subcategory":"Landscaping Services",
            "type":"Services"
        },
        {
            "category":"Home & Garden",
            "subcategory":"Garden Supply",
            "type":"Retail Goods"
        }
    ],
    "sg:phone":"+1 559 781 9312",
    "sg:postcode":"93257",
    "sg:province":"CA",
    "sg:tags":[
        "lawn",
        "installation",
        "sprinklers-garden",
        "contractor",
        "equipment",
        "landscape"
    ],
    "sg:website":"http://www.billstevensonlandscaping.com",
    "wof:name":"Stevenson Landscaping",
    "wof:placetype":"venue"
},
  "geometry": {"coordinates":[-119.053456,36.101636],"type":"Point"}
}