{
  "type": "Feature",
  "properties": {
    "iso:country":"US",
    "sg:address":"1151 Bay Blvd",
    "sg:city":"Chula Vista",
    "sg:classifiers":[
        {
            "category":"Shopping",
            "subcategory":"Department Store",
            "type":"Retail Goods"
        }
    ],
    "sg:phone":"+1 619 423 5999",
    "sg:postcode":"91911",
    "sg:province":"CA",
    "sg:tags":[
        "shop"
    ],
    "wof:name":"Pic & Pay 99 Cents",
    "wof:placetype":"venue"
},
  "geometry": {"coordinates":[-117.092095,32.608387],"type":"Point"}
}