{
  "type": "Feature",
  "properties": {
    "addr:full":"12751 Folsom Blvd Folsom CA 95630",
    "addr:housenumber":"12751",
    "addr:postcode":"95630",
    "addr:street":"Folsom Blvd",
    "iso:country":"US",
    "sg:address":"12751 Folsom Blvd",
    "sg:city":"Folsom",
    "sg:phone":"+1 916 353 2121",
    "sg:postcode":"95630",
    "sg:province":"CA",
    "sg:website":"http://www.folsomlakekia.com",
    "wof:name":"Folsom Lake Kia - New & Used Cars",
    "wof:placetype":"venue"
},
  "geometry": {"coordinates":[-121.20017199999999,38.63596],"type":"Point"}
}