{
  "type": "Feature",
  "properties": {
    "iso:country":"US",
    "sg:address":"217 N Sacramento St",
    "sg:city":"Lodi",
    "sg:classifiers":[
        {
            "category":"Retail",
            "subcategory":"Auto Repair",
            "type":"Services"
        }
    ],
    "sg:phone":"+1 209 369 4370",
    "sg:postcode":"95240",
    "sg:province":"CA",
    "sg:tags":[
        "repairing",
        "automobile"
    ],
    "wof:name":"Ehlers Auto",
    "wof:placetype":"venue"
},
  "geometry": {"coordinates":[-121.272037,38.137569],"type":"Point"}
}