{
  "type": "Feature",
  "properties": {
    "iso:country":"US",
    "sg:address":"7325 State St",
    "sg:city":"Huntington Park",
    "sg:classifiers":[
        {
            "category":"Building & Trades",
            "subcategory":"Landscaping Services",
            "type":"Services"
        }
    ],
    "sg:phone":"+1 323 582 1745",
    "sg:postcode":"90255",
    "sg:province":"CA",
    "wof:name":"Rake Inc",
    "wof:placetype":"venue"
},
  "geometry": {"coordinates":[-118.209808,33.971096],"type":"Point"}
}