{
  "type": "Feature",
  "properties": {
    "iso:country":"US",
    "sg:address":"260 S Los Robles Ave # 104",
    "sg:city":"Pasadena",
    "sg:classifiers":[
        {
            "category":"Professional",
            "subcategory":"Management & Consulting",
            "type":"Services"
        },
        {
            "category":"Banks & Credit Unions",
            "subcategory":"Investment Brokerage",
            "type":"Services"
        },
        {
            "category":"Banks & Credit Unions",
            "subcategory":"Financial Services",
            "type":"Services"
        }
    ],
    "sg:phone":"+1 626 796 2768",
    "sg:postcode":"91101",
    "sg:province":"CA",
    "sg:tags":[
        "planning",
        "advisory",
        "financing",
        "planner",
        "consultant"
    ],
    "wof:name":"J Aldric Burch Investments, Inc",
    "wof:placetype":"venue"
},
  "geometry": {"coordinates":[-118.141373,34.141215],"type":"Point"}
}