{
  "type": "Feature",
  "properties": {
    "addr:full":"1122 Santa Barbara St Santa Barbara CA 93101",
    "addr:housenumber":"1122",
    "addr:postcode":"93101",
    "addr:street":"Santa Barbara St",
    "iso:country":"US",
    "sg:address":"1122 Santa Barbara St",
    "sg:city":"Santa Barbara",
    "sg:classifiers":[
        {
            "category":"Government",
            "subcategory":"Police Station",
            "type":"Public Place"
        }
    ],
    "sg:phone":"+1 805 568 2900",
    "sg:postcode":"93101",
    "sg:province":"CA",
    "sg:tags":[
        "general"
    ],
    "wof:name":"Sheriffs Dept",
    "wof:placetype":"venue"
},
  "geometry": {"coordinates":[-119.701887,34.425338],"type":"Point"}
}