{
  "type": "Feature",
  "properties": {
    "iso:country":"US",
    "sg:address":"39176 Fremont Blvd",
    "sg:city":"Fremont",
    "sg:classifiers":[
        {
            "category":"Manufacturing",
            "subcategory":"Printing",
            "type":"Manufacturing & Wholesale Goods"
        }
    ],
    "sg:phone":"+1 510 795 7001",
    "sg:postcode":"94538",
    "sg:province":"CA",
    "sg:tags":[
        "commercial",
        "copy",
        "lithographic",
        "center"
    ],
    "wof:name":"Bay Central Prtg & Copy Ctr",
    "wof:placetype":"venue"
},
  "geometry": {"coordinates":[-121.987869,37.54837],"type":"Point"}
}