{
  "type": "Feature",
  "properties": {
    "addr:full":"235 Incline Ave Oroville CA 95966",
    "addr:housenumber":"235",
    "addr:postcode":"95966",
    "addr:street":"Incline Ave",
    "iso:country":"US",
    "sg:address":"235 Incline Ave",
    "sg:city":"Oroville",
    "sg:classifiers":[
        {
            "category":"Retail",
            "subcategory":"Repair Shop",
            "type":"Services"
        }
    ],
    "sg:phone":"+1 530 533 5296",
    "sg:postcode":"95966",
    "sg:province":"CA",
    "sg:tags":[
        "lock",
        "locksmith"
    ],
    "wof:name":"Accurate Lock & Key",
    "wof:placetype":"venue"
},
  "geometry": {"coordinates":[-121.534167,39.527731],"type":"Point"}
}