{
  "type": "Feature",
  "properties": {
    "iso:country":"US",
    "sg:address":"1232 Virginia Ave",
    "sg:city":"Bakersfield",
    "sg:classifiers":[
        {
            "category":"Retail",
            "subcategory":"Laundry & Dry Cleaning",
            "type":"Services"
        }
    ],
    "sg:phone":"+1 661 324 9519",
    "sg:postcode":"93307",
    "sg:province":"CA",
    "sg:tags":[
        "cleaners",
        "rug",
        "carpet"
    ],
    "wof:name":"Bj's Unique Carpet Cleaning",
    "wof:placetype":"venue"
},
  "geometry": {"coordinates":[-118.988866,35.361282],"type":"Point"}
}