{
  "type": "Feature",
  "properties": {
    "addr:full":"200 Rollingwood Dr Vallejo CA 94591",
    "addr:housenumber":"200",
    "addr:postcode":"94591",
    "addr:street":"Rollingwood Dr",
    "iso:country":"US",
    "sg:address":"200 Rollingwood Dr",
    "sg:city":"Vallejo",
    "sg:classifiers":[
        {
            "category":"Wholesale",
            "subcategory":"Motor Vehicles",
            "type":"Manufacturing & Wholesale Goods"
        }
    ],
    "sg:phone":"+1 707 552 3400",
    "sg:postcode":"94591",
    "sg:province":"CA",
    "wof:name":"Monterey Auction Company LLC",
    "wof:placetype":"venue"
},
  "geometry": {"coordinates":[-122.208186,38.090056],"type":"Point"}
}