{
  "type": "Feature",
  "properties": {
    "addr:full":"1301 S Main St Los Angeles CA 90015",
    "addr:housenumber":"1301",
    "addr:postcode":"90015",
    "addr:street":"S Main St",
    "iso:country":"US",
    "sg:address":"1301 S Main St",
    "sg:city":"Los Angeles",
    "sg:classifiers":[
        {
            "category":"Professional",
            "type":"Services"
        }
    ],
    "sg:phone":"+1 213 745 6132",
    "sg:postcode":"90015",
    "sg:province":"CA",
    "sg:tags":[
        "establishment"
    ],
    "wof:name":"Very Chic",
    "wof:placetype":"venue"
},
  "geometry": {"coordinates":[-118.26088799999999,34.035686],"type":"Point"}
}