{
  "type": "Feature",
  "properties": {
    "addr:full":"5580 La Jolla Blvd La Jolla CA 92037",
    "addr:housenumber":"5580",
    "addr:postcode":"92037",
    "addr:street":"La Jolla Blvd",
    "iso:country":"US",
    "sg:address":"5580 La Jolla Blvd",
    "sg:city":"La Jolla",
    "sg:classifiers":[
        {
            "category":"Home & Garden",
            "subcategory":"Household Appliances",
            "type":"Retail Goods"
        }
    ],
    "sg:phone":"+1 858 454 2324",
    "sg:postcode":"92037",
    "sg:province":"CA",
    "wof:name":"La Jolla Refrigeration Service",
    "wof:placetype":"venue"
},
  "geometry": {"coordinates":[-117.268997,32.813599],"type":"Point"}
}