{
  "type": "Feature",
  "properties": {
    "iso:country":"US",
    "sg:address":"5760 W 96th St",
    "sg:city":"Los Angeles",
    "sg:classifiers":[
        {
            "category":"Wholesale",
            "subcategory":"Drugs",
            "type":"Manufacturing & Wholesale Goods"
        }
    ],
    "sg:phone":"+1 310 216 2473",
    "sg:postcode":"90045",
    "sg:province":"CA",
    "wof:name":"Nutrina Co Inc",
    "wof:placetype":"venue"
},
  "geometry": {"coordinates":[-118.381851,33.949367],"type":"Point"}
}