{
  "type": "Feature",
  "properties": {
    "addr:full":"16731 Knott Ave La Mirada CA 90638",
    "addr:housenumber":"16731",
    "addr:postcode":"90638",
    "addr:street":"Knott Ave",
    "iso:country":"US",
    "sg:address":"16731 Knott Ave",
    "sg:city":"La Mirada",
    "sg:classifiers":[
        {
            "category":"Local Transit",
            "type":"Transportation"
        }
    ],
    "sg:phone":"+1 714 523 7500",
    "sg:postcode":"90638",
    "sg:province":"CA",
    "wof:name":"Dedicated Xpress",
    "wof:placetype":"venue"
},
  "geometry": {"coordinates":[-118.011509,33.879524],"type":"Point"}
}