{
  "type": "Feature",
  "properties": {
    "iso:country":"US",
    "sg:address":"1636 W 8th Street",
    "sg:city":"Los Angeles",
    "sg:classifiers":[
        {
            "category":"Taxi",
            "type":"Transportation"
        }
    ],
    "sg:phone":"+1 213 427 0606",
    "sg:postcode":"90017",
    "sg:province":"CA",
    "wof:name":"La Mix",
    "wof:placetype":"venue"
},
  "geometry": {"coordinates":[-118.272615,34.052503],"type":"Point"}
}