{
  "type": "Feature",
  "properties": {
    "addr:full":"15070 Ave of Science San Diego CA 92128",
    "addr:housenumber":"15070",
    "addr:postcode":"92128",
    "addr:street":"Ave Of Science",
    "iso:country":"US",
    "sg:address":"15070 Ave of Science",
    "sg:city":"San Diego",
    "sg:classifiers":[
        {
            "category":"Building & Trades",
            "subcategory":"Construction",
            "type":"Services"
        }
    ],
    "sg:phone":"+1 858 485 1374",
    "sg:postcode":"92128",
    "sg:province":"CA",
    "sg:tags":[
        "contractor"
    ],
    "wof:name":"Prevost Construction",
    "wof:placetype":"venue"
},
  "geometry": {"coordinates":[-117.081292,32.993647],"type":"Point"}
}