{
  "type": "Feature",
  "properties": {
    "addr:full":"566 E 5th St Azusa CA 91702",
    "addr:housenumber":"566",
    "addr:postcode":"91702",
    "addr:street":"E 5Th St",
    "iso:country":"US",
    "sg:address":"566 E 5th St",
    "sg:city":"Azusa",
    "sg:classifiers":[
        {
            "category":"Government",
            "subcategory":"Office",
            "type":"Public Place"
        }
    ],
    "sg:phone":"+1 626 334 8303",
    "sg:postcode":"91702",
    "sg:province":"CA",
    "sg:tags":[
        "general"
    ],
    "wof:name":"Japanese Amercn Citizens Leag",
    "wof:placetype":"venue"
},
  "geometry": {"coordinates":[-117.900463,34.129737],"type":"Point"}
}