{
  "type": "Feature",
  "properties": {
    "iso:country":"US",
    "sg:address":"80 E Hillcrest Dr",
    "sg:city":"Thousand Oaks",
    "sg:classifiers":[
        {
            "category":"Social Services",
            "type":"Services"
        }
    ],
    "sg:phone":"+1 805 496 1113",
    "sg:postcode":"91360",
    "sg:province":"CA",
    "sg:tags":[
        "counselor",
        "marriage",
        "family"
    ],
    "wof:name":"Catholic Charities",
    "wof:placetype":"venue"
},
  "geometry": {"coordinates":[-118.874754,34.181049],"type":"Point"}
}