{
  "type": "Feature",
  "properties": {
    "addr:full":"325 S Del Mar Ave San Gabriel CA 91776",
    "addr:housenumber":"325",
    "addr:postcode":"91776",
    "addr:street":"S Del Mar Ave",
    "iso:country":"US",
    "sg:address":"325 S Del Mar Ave",
    "sg:city":"San Gabriel",
    "sg:classifiers":[
        {
            "category":"Fast Food",
            "type":"Food & Drink"
        }
    ],
    "sg:phone":"+1 626 286 5555",
    "sg:postcode":"91776",
    "sg:province":"CA",
    "sg:tags":[
        "burger"
    ],
    "wof:name":"Lucky Burgers",
    "wof:placetype":"venue"
},
  "geometry": {"coordinates":[-118.099869,34.097907],"type":"Point"}
}