{
  "type": "Feature",
  "properties": {
    "iso:country":"US",
    "sg:address":"2200 Mission Blvd",
    "sg:city":"Santa Clara",
    "sg:classifiers":[
        {
            "category":"Museum",
            "type":"Entertainment"
        }
    ],
    "sg:phone":"+1 408 765 0503",
    "sg:postcode":"95054",
    "sg:province":"CA",
    "sg:website":"www.intel.com/museum",
    "wof:name":"Intel Museum",
    "wof:placetype":"venue"
},
  "geometry": {"coordinates":[-121.963438,37.388639],"type":"Point"}
}