{
  "type": "Feature",
  "properties": {
    "addr:full":"10847 Monte Vista Rd Phelan CA 92371",
    "addr:housenumber":"10847",
    "addr:postcode":"92371",
    "addr:street":"Monte Vista Rd",
    "iso:country":"US",
    "sg:address":"10847 Monte Vista Rd",
    "sg:city":"Phelan",
    "sg:classifiers":[
        {
            "category":"Farming",
            "subcategory":"Livestock Farm",
            "type":"Manufacturing & Wholesale Goods"
        }
    ],
    "sg:phone":"+1 760 868 9256",
    "sg:postcode":"92371",
    "sg:province":"CA",
    "sg:tags":[
        "animal",
        "general"
    ],
    "wof:name":"Awakening Ranch",
    "wof:placetype":"venue"
},
  "geometry": {"coordinates":[-117.55944599999999,34.447355],"type":"Point"}
}