{
  "type": "Feature",
  "properties": {
    "addr:full":"11137 National Blvd Los Angeles CA 90064",
    "addr:housenumber":"11137",
    "addr:postcode":"90064",
    "addr:street":"National Blvd",
    "iso:country":"US",
    "sg:address":"11137 National Blvd",
    "sg:city":"Los Angeles",
    "sg:classifiers":[
        {
            "category":"Retail",
            "subcategory":"Veterinary Services",
            "type":"Services"
        }
    ],
    "sg:phone":"+1 310 914 7374",
    "sg:postcode":"90064",
    "sg:province":"CA",
    "sg:tags":[
        "veterinarian"
    ],
    "wof:name":"Value Vet",
    "wof:placetype":"venue"
},
  "geometry": {"coordinates":[-118.42800099999999,34.027802],"type":"Point"}
}