{
  "type": "Feature",
  "properties": {
    "iso:country":"US",
    "sg:address":"44057 61st St W",
    "sg:city":"Lancaster",
    "sg:classifiers":[
        {
            "category":"Building & Trades",
            "subcategory":"Plumbing",
            "type":"Services"
        }
    ],
    "sg:phone":"+1 661 722 0525",
    "sg:postcode":"93536",
    "sg:province":"CA",
    "sg:tags":[
        "contractor"
    ],
    "wof:name":"E B Plumbing & Rooter",
    "wof:placetype":"venue"
},
  "geometry": {"coordinates":[-118.238688,34.683936],"type":"Point"}
}