{
  "type": "Feature",
  "properties": {
    "addr:full":"428 13th St Ste 200 Oakland CA 94612",
    "addr:housenumber":"428",
    "addr:postcode":"94612",
    "addr:street":"13Th St Ste 200",
    "iso:country":"US",
    "sg:address":"428 13th St Ste 200",
    "sg:city":"Oakland",
    "sg:classifiers":[
        {
            "category":"Education",
            "subcategory":"Special Training",
            "type":"Public Place"
        }
    ],
    "sg:phone":"+1 510 834 9455",
    "sg:postcode":"94612",
    "sg:province":"CA",
    "sg:tags":[
        "tutoring"
    ],
    "sg:website":"www.arcassociates.org/",
    "wof:name":"Arc Associates Inc",
    "wof:placetype":"venue"
},
  "geometry": {"coordinates":[-122.271055,37.803434],"type":"Point"}
}