{
  "type": "Feature",
  "properties": {
    "addr:full":"6185 Magnolia Ave Riverside CA 92506",
    "addr:housenumber":"6185",
    "addr:postcode":"92506",
    "addr:street":"Magnolia Ave",
    "iso:country":"US",
    "sg:address":"6185 Magnolia Ave",
    "sg:city":"Riverside",
    "sg:classifiers":[
        {
            "category":"Wholesale",
            "subcategory":"Machinery & Supplies",
            "type":"Manufacturing & Wholesale Goods"
        }
    ],
    "sg:phone":"+1 951 509 0456",
    "sg:postcode":"92506",
    "sg:province":"CA",
    "sg:tags":[
        "equipment",
        "industrial"
    ],
    "wof:name":"Reds Hot Concrete Pumping",
    "wof:placetype":"venue"
},
  "geometry": {"coordinates":[-117.39359899999999,33.958285],"type":"Point"}
}