{
  "type": "Feature",
  "properties": {
    "iso:country":"US",
    "sg:address":"821 N Spring St",
    "sg:city":"Los Angeles",
    "sg:classifiers":[
        {
            "category":"Shopping",
            "subcategory":"Clothing, Apparel, & Fashions",
            "type":"Retail Goods"
        }
    ],
    "sg:phone":"+1 213 626 8968",
    "sg:postcode":"90012",
    "sg:province":"CA",
    "sg:tags":[
        "accessory",
        "clothing",
        "women's"
    ],
    "wof:name":"Janies Fashion",
    "wof:placetype":"venue"
},
  "geometry": {"coordinates":[-118.23699999999999,34.0625],"type":"Point"}
}