{
  "type": "Feature",
  "properties": {
    "addr:full":"2250 Hayes St Ste 204 San Francisco CA 94117",
    "addr:housenumber":"2250",
    "addr:postcode":"94117",
    "addr:street":"Hayes St Ste 204",
    "iso:country":"US",
    "sg:address":"2250 Hayes St Ste 204",
    "sg:city":"San Francisco",
    "sg:classifiers":[
        {
            "category":"Health Services",
            "subcategory":"Doctor",
            "type":"Services"
        }
    ],
    "sg:phone":"+1 415 933 9100",
    "sg:postcode":"94117",
    "sg:province":"CA",
    "sg:tags":[
        "cardiologist"
    ],
    "wof:name":"Curran Peter J MD",
    "wof:placetype":"venue"
},
  "geometry": {"coordinates":[-122.45349299999999,37.773138],"type":"Point"}
}