{
  "type": "Feature",
  "properties": {
    "addr:full":"1400 W 10th St Antioch CA 94509",
    "addr:housenumber":"1400",
    "addr:postcode":"ca 94509",
    "addr:street":"W 10Th St",
    "iso:country":"US",
    "sg:address":"1400 W 10th St",
    "sg:city":"Antioch",
    "sg:classifiers":[
        {
            "category":"Autos & Motor Vehicles",
            "subcategory":"Automobile Sales",
            "type":"Retail Goods"
        }
    ],
    "sg:phone":"+1 925 757 1771",
    "sg:postcode":"94509",
    "sg:province":"CA",
    "sg:tags":[
        "car",
        "dealer"
    ],
    "wof:name":"Antioch Ford",
    "wof:placetype":"venue"
},
  "geometry": {"coordinates":[-121.82617,38.01182],"type":"Point"}
}