{
  "type": "Feature",
  "properties": {
    "iso:country":"US",
    "sg:address":"1901 E Alondra Boulevard",
    "sg:city":"Compton",
    "sg:classifiers":[
        {
            "category":"Autos & Motor Vehicles",
            "subcategory":"Auto Supplies",
            "type":"Retail Goods"
        }
    ],
    "sg:phone":"+1 310 763 1088",
    "sg:postcode":"90221",
    "sg:province":"CA",
    "sg:tags":[
        "tire"
    ],
    "wof:name":"Lopez Tire Shop",
    "wof:placetype":"venue"
},
  "geometry": {"coordinates":[-118.201951,33.888832],"type":"Point"}
}