{
  "type": "Feature",
  "properties": {
    "iso:country":"US",
    "sg:address":"650 Hobson Way",
    "sg:city":"Oxnard",
    "sg:classifiers":[
        {
            "category":"Health Services",
            "subcategory":"Chiropractor",
            "type":"Services"
        }
    ],
    "sg:phone":"+1 805 486 8867",
    "sg:postcode":"93030",
    "sg:province":"CA",
    "wof:name":"Pain Release Health Ctr",
    "wof:placetype":"venue"
},
  "geometry": {"coordinates":[-119.187841,34.197131],"type":"Point"}
}