{
  "type": "Feature",
  "properties": {
    "iso:country":"US",
    "sg:address":"1601 Dove St",
    "sg:city":"Newport Beach",
    "sg:classifiers":[
        {
            "category":"Health Services",
            "subcategory":"Doctor",
            "type":"Services"
        }
    ],
    "sg:phone":"+1 949 752 1671",
    "sg:postcode":"92660",
    "sg:province":"CA",
    "sg:tags":[
        "physician",
        "surgeon"
    ],
    "wof:name":"Don De Francisco MD",
    "wof:placetype":"venue"
},
  "geometry": {"coordinates":[-117.866117,33.664437],"type":"Point"}
}