{
  "type": "Feature",
  "properties": {
    "addr:full":"101 S Citrus Ave West Covina CA 91791",
    "addr:housenumber":"101",
    "addr:postcode":"91791",
    "addr:street":"S Citrus Ave",
    "iso:country":"US",
    "sg:address":"101 S Citrus Ave",
    "sg:city":"West Covina",
    "sg:classifiers":[
        {
            "category":"Banks & Credit Unions",
            "subcategory":"Bank",
            "type":"Services"
        }
    ],
    "sg:phone":"+1 626 915 1720",
    "sg:postcode":"91791",
    "sg:province":"CA",
    "sg:tags":[
        "loan",
        "real estate"
    ],
    "wof:name":"CSDI Financial",
    "wof:placetype":"venue"
},
  "geometry": {"coordinates":[-117.890085,34.071416],"type":"Point"}
}