{
  "type": "Feature",
  "properties": {
    "addr:full":"583 Moomjean Ave Merced CA 95340",
    "addr:housenumber":"583",
    "addr:postcode":"95340",
    "addr:street":"Moomjean Ave",
    "iso:country":"US",
    "sg:address":"583 Moomjean Ave",
    "sg:city":"Merced",
    "sg:classifiers":[
        {
            "category":"Freight",
            "type":"Transportation"
        }
    ],
    "sg:phone":"+1 209 723 0809",
    "sg:postcode":"95340",
    "sg:province":"CA",
    "sg:tags":[
        "operator",
        "delivery",
        "local",
        "trucking"
    ],
    "wof:name":"Lisa Bradley",
    "wof:placetype":"venue"
},
  "geometry": {"coordinates":[-120.42959500000001,37.295908],"type":"Point"}
}