{
  "type": "Feature",
  "properties": {
    "iso:country":"US",
    "sg:address":"17070 Walnut Village Pkwy",
    "sg:city":"Fontana",
    "sg:classifiers":[
        {
            "category":"Cinema",
            "subcategory":"Movie Rental",
            "type":"Entertainment"
        }
    ],
    "sg:phone":"+1 909 356 9293",
    "sg:postcode":"92336",
    "sg:province":"CA",
    "sg:tags":[
        "leasing",
        "video",
        "disc",
        "tape"
    ],
    "wof:name":"C & A Video",
    "wof:placetype":"venue"
},
  "geometry": {"coordinates":[-117.433091,34.128695],"type":"Point"}
}