{
  "type": "Feature",
  "properties": {
    "addr:full":"1944 Janet Ave San Jose CA 95124",
    "addr:housenumber":"1944",
    "addr:postcode":"95124",
    "addr:street":"Janet Ave",
    "iso:country":"US",
    "sg:address":"1944 Janet Ave",
    "sg:city":"San Jose",
    "sg:classifiers":[
        {
            "category":"Professional",
            "type":"Services"
        }
    ],
    "sg:phone":"+1 408 377 8562",
    "sg:postcode":"95124",
    "sg:province":"CA",
    "sg:tags":[
        "arts",
        "artist"
    ],
    "wof:name":"Robert K Semans Portraits",
    "wof:placetype":"venue"
},
  "geometry": {"coordinates":[-121.92715200000001,37.263124],"type":"Point"}
}