{
  "type": "Feature",
  "properties": {
    "iso:country":"US",
    "sg:address":"11717 Sorrento Valley Rd",
    "sg:city":"San Diego",
    "sg:classifiers":[
        {
            "category":"Professional",
            "subcategory":"Art Services",
            "type":"Services"
        }
    ],
    "sg:phone":"+1 858 481 0604",
    "sg:postcode":"92121",
    "sg:province":"CA",
    "sg:tags":[
        "underwater",
        "photography",
        "camera",
        "commercial",
        "mfg"
    ],
    "wof:name":"Marine Camera Distributors",
    "wof:placetype":"venue"
},
  "geometry": {"coordinates":[-117.228078,32.906294],"type":"Point"}
}