{
  "type": "Feature",
  "properties": {
    "addr:full":"415 S Sacramento St Lodi CA 95240",
    "addr:housenumber":"415",
    "addr:postcode":"95240",
    "addr:street":"S Sacramento St",
    "iso:country":"US",
    "sg:address":"415 S Sacramento St",
    "sg:city":"Lodi",
    "sg:classifiers":[
        {
            "category":"Social Services",
            "type":"Services"
        }
    ],
    "sg:phone":"+1 209 333 2605",
    "sg:postcode":"95240",
    "sg:province":"CA",
    "sg:tags":[
        "youth",
        "organization",
        "center"
    ],
    "wof:name":"Big Brothers & Big Sisters",
    "wof:placetype":"venue"
},
  "geometry": {"coordinates":[-121.27288900000001,38.127726],"type":"Point"}
}