{
  "type": "Feature",
  "properties": {
    "addr:full":"1579 Custer Ave San Francisco CA 94124",
    "addr:housenumber":"1579",
    "addr:postcode":"94124",
    "addr:street":"Custer Ave",
    "iso:country":"US",
    "sg:address":"1579 Custer Ave",
    "sg:city":"San Francisco",
    "sg:classifiers":[
        {
            "category":"Autos & Motor Vehicles",
            "subcategory":"Auto Supplies",
            "type":"Retail Goods"
        },
        {
            "category":"Retail",
            "subcategory":"Auto Repair",
            "type":"Services"
        }
    ],
    "sg:phone":"+1 415 336 4454",
    "sg:postcode":"94124",
    "sg:province":"CA",
    "sg:tags":[
        "glass"
    ],
    "sg:website":"www.sfcityglass.com",
    "wof:name":"San Francisco Auto Glass",
    "wof:placetype":"venue"
},
  "geometry": {"coordinates":[-122.39078499999999,37.746205],"type":"Point"}
}