{
  "type": "Feature",
  "properties": {
    "iso:country":"US",
    "sg:address":"711 W 17th St",
    "sg:city":"Costa Mesa",
    "sg:classifiers":[
        {
            "category":"Building & Trades",
            "subcategory":"Electrical",
            "type":"Services"
        }
    ],
    "sg:phone":"+1 949 574 8777",
    "sg:postcode":"92627",
    "sg:province":"CA",
    "sg:tags":[
        "communications",
        "specialization",
        "cable",
        "contractor"
    ],
    "wof:name":"Com Services Inc",
    "wof:placetype":"venue"
},
  "geometry": {"coordinates":[-117.931523,33.636041],"type":"Point"}
}