{
  "type": "Feature",
  "properties": {
    "addr:full":"905 S A St Oxnard CA 93030",
    "addr:housenumber":"905",
    "addr:postcode":"93030",
    "addr:street":"S A St",
    "iso:country":"US",
    "sg:address":"905 S A St",
    "sg:city":"Oxnard",
    "sg:classifiers":[
        {
            "category":"Banks & Credit Unions",
            "subcategory":"Bank",
            "type":"Services"
        }
    ],
    "sg:phone":"+1 805 486 1031",
    "sg:postcode":"93030",
    "sg:province":"CA",
    "sg:tags":[
        "loan",
        "real estate"
    ],
    "wof:name":"Georgina Rigonan",
    "wof:placetype":"venue"
},
  "geometry": {"coordinates":[-119.178741,34.190174],"type":"Point"}
}