{
  "type": "Feature",
  "properties": {
    "iso:country":"US",
    "sg:address":"763 Deodara Dr",
    "sg:city":"Altadena",
    "sg:classifiers":[
        {
            "category":"Wholesale",
            "subcategory":"Hardware",
            "type":"Manufacturing & Wholesale Goods"
        }
    ],
    "sg:phone":"+1 626 797 2202",
    "sg:postcode":"91001",
    "sg:province":"CA",
    "sg:tags":[
        "nut",
        "bolt"
    ],
    "wof:name":"B C Nut and Bolt",
    "wof:placetype":"venue"
},
  "geometry": {"coordinates":[-118.13441,34.187395],"type":"Point"}
}