{
  "type": "Feature",
  "properties": {
    "iso:country":"US",
    "sg:address":"1116 The Alameda",
    "sg:city":"Berkeley",
    "sg:classifiers":[
        {
            "category":"Communications",
            "type":"Services"
        }
    ],
    "sg:phone":"+1 510 528 8634",
    "sg:postcode":"94707",
    "sg:province":"CA",
    "sg:tags":[
        "translator",
        "interpreter"
    ],
    "wof:name":"Summit Institution",
    "wof:placetype":"venue"
},
  "geometry": {"coordinates":[-122.276128,37.887066],"type":"Point"}
}