{
  "type": "Feature",
  "properties": {
    "addr:full":"617 2nd St Davis CA 95616",
    "addr:housenumber":"617",
    "addr:postcode":"95616",
    "addr:street":"2Nd St",
    "iso:country":"US",
    "sg:address":"617 2nd St",
    "sg:city":"Davis",
    "sg:classifiers":[
        {
            "category":"Shopping",
            "subcategory":"Books",
            "type":"Retail Goods"
        }
    ],
    "sg:phone":"+1 530 758 4040",
    "sg:postcode":"95616",
    "sg:province":"CA",
    "sg:tags":[
        "dealer"
    ],
    "sg:website":"www.avidreaderbooks.com",
    "wof:name":"Avid Reader",
    "wof:placetype":"venue"
},
  "geometry": {"coordinates":[-121.74015199999999,38.543468],"type":"Point"}
}