{
  "type": "Feature",
  "properties": {
    "iso:country":"US",
    "sg:address":"617 2nd St",
    "sg:city":"Davis",
    "sg:classifiers":[
        {
            "category":"Shopping",
            "subcategory":"Books",
            "type":"Retail Goods"
        }
    ],
    "sg:phone":"+1 530 758 4040",
    "sg:postcode":"95616",
    "sg:province":"CA",
    "sg:tags":[
        "dealer"
    ],
    "sg:website":"www.avidreaderbooks.com",
    "wof:name":"Avid Reader",
    "wof:placetype":"venue"
},
  "geometry": {"coordinates":[-121.740152,38.543468],"type":"Point"}
}