{
  "type": "Feature",
  "properties": {
    "addr:full":"35367 Fircrest St Newark CA 94560",
    "addr:postcode":"35367;94560",
    "addr:street":"St",
    "iso:country":"US",
    "sg:address":"35367 Fircrest St",
    "sg:city":"Newark",
    "sg:classifiers":[
        {
            "category":"Manufacturing",
            "subcategory":"Tools & Machinery",
            "type":"Manufacturing & Wholesale Goods"
        },
        {
            "category":"Wholesale",
            "subcategory":"Machinery & Supplies",
            "type":"Manufacturing & Wholesale Goods"
        }
    ],
    "sg:phone":"+1 510 797 7000",
    "sg:postcode":"94560",
    "sg:province":"CA",
    "sg:tags":[
        "equipment",
        "industrial"
    ],
    "wof:name":"Bay Cities Tool & Supply Inc.",
    "wof:placetype":"venue"
},
  "geometry": {"coordinates":[-122.055176,37.544169],"type":"Point"}
}