{
  "type": "Feature",
  "properties": {
    "addr:full":"2585 Union St San Francisco CA 94123",
    "addr:housenumber":"2585",
    "addr:postcode":"94123",
    "addr:street":"Union St",
    "iso:country":"US",
    "sg:address":"2585 Union St",
    "sg:city":"San Francisco",
    "sg:classifiers":[
        {
            "category":"Professional",
            "subcategory":"Lawyer & Legal Services",
            "type":"Services"
        }
    ],
    "sg:phone":"+1 415 614 0139",
    "sg:postcode":"94123",
    "sg:province":"CA",
    "sg:tags":[
        "attorney"
    ],
    "sg:website":"www.barteltlaw.com",
    "wof:name":"BARTELTLAW.COM",
    "wof:placetype":"venue"
},
  "geometry": {"coordinates":[-122.44094800000001,37.796357],"type":"Point"}
}