{
  "type": "Feature",
  "properties": {
    "iso:country":"US",
    "sg:address":"383 W Joaquin Ave",
    "sg:city":"San Leandro",
    "sg:classifiers":[
        {
            "category":"Health Services",
            "subcategory":"Doctor",
            "type":"Services"
        }
    ],
    "sg:phone":"+1 510 483 0256",
    "sg:postcode":"94577",
    "sg:province":"CA",
    "sg:tags":[
        "surgeon",
        "oral"
    ],
    "wof:name":"Wells D Ronald DDS",
    "wof:placetype":"venue"
},
  "geometry": {"coordinates":[-122.15799699999999,37.723099],"type":"Point"}
}