{
  "type": "Feature",
  "properties": {
    "addr:full":"607 E Nocta St Ontario CA 91764",
    "addr:housenumber":"607",
    "addr:postcode":"91764",
    "addr:street":"E Nocta St",
    "iso:country":"US",
    "sg:address":"607 E Nocta St",
    "sg:city":"Ontario",
    "sg:classifiers":[
        {
            "category":"Building & Trades",
            "subcategory":"Landscaping Services",
            "type":"Services"
        }
    ],
    "sg:phone":"+1 909 988 7104",
    "sg:postcode":"91764",
    "sg:province":"CA",
    "sg:tags":[
        "landscape",
        "contractor"
    ],
    "wof:name":"Rudy's Landscaping Svc",
    "wof:placetype":"venue"
},
  "geometry": {"coordinates":[-117.64341400000001,34.065295],"type":"Point"}
}