{
  "type": "Feature",
  "properties": {
    "iso:country":"US",
    "sg:address":"969 Colorado Blvd",
    "sg:city":"Los Angeles",
    "sg:classifiers":[
        {
            "category":"Wholesale",
            "subcategory":"Apparel",
            "type":"Manufacturing & Wholesale Goods"
        }
    ],
    "sg:phone":"+1 323 982 9321",
    "sg:postcode":"90041",
    "sg:province":"CA",
    "wof:name":"Kumquat",
    "wof:placetype":"venue"
},
  "geometry": {"coordinates":[-118.186203,34.138887],"type":"Point"}
}