{
  "type": "Feature",
  "properties": {
    "iso:country":"US",
    "sg:address":"2450 W Whittier Blvd",
    "sg:city":"La Habra",
    "sg:classifiers":[
        {
            "category":"Donuts",
            "subcategory":"None",
            "type":"Food & Drink"
        }
    ],
    "sg:phone":"+1 562 697 1415",
    "sg:postcode":"90631",
    "sg:province":"CA",
    "wof:name":"Jax Donuts No 11",
    "wof:placetype":"venue"
},
  "geometry": {"coordinates":[-117.973999,33.939999],"type":"Point"}
}