{
  "type": "Feature",
  "properties": {
    "iso:country":"US",
    "sg:address":"311 F St",
    "sg:city":"Chula Vista",
    "sg:classifiers":[
        {
            "category":"Health Services",
            "subcategory":"Health Practitioner",
            "type":"Services"
        }
    ],
    "sg:phone":"+1 619 422 5315",
    "sg:postcode":"91910",
    "sg:province":"CA",
    "sg:tags":[
        "therapist",
        "physical"
    ],
    "wof:name":"E & L & Assoc Physical Therapy",
    "wof:placetype":"venue"
},
  "geometry": {"coordinates":[-117.080946,32.640983],"type":"Point"}
}