{
  "type": "Feature",
  "properties": {
    "addr:full":"561 Air Park Dr Oceano CA 93445",
    "addr:housenumber":"561",
    "addr:postcode":"93445",
    "addr:street":"Air Park Dr",
    "iso:country":"US",
    "sg:address":"561 Air Park Dr",
    "sg:city":"Oceano",
    "sg:classifiers":[
        {
            "category":"Building & Trades",
            "subcategory":"Equipment Rental",
            "type":"Services"
        }
    ],
    "sg:phone":"+1 805 474 6491",
    "sg:postcode":"93445",
    "sg:province":"CA",
    "sg:tags":[
        "aircraft",
        "leasing",
        "charter"
    ],
    "wof:name":"Bi-Plane Rides Banner Airways",
    "wof:placetype":"venue"
},
  "geometry": {"coordinates":[-120.624596,35.104403],"type":"Point"}
}