{
  "type": "Feature",
  "properties": {
    "iso:country":"US",
    "sg:address":"462 S Marengo Ave",
    "sg:city":"Pasadena",
    "sg:classifiers":[
        {
            "category":"Social Services",
            "type":"Services"
        }
    ],
    "sg:phone":"+1 626 440 1003",
    "sg:postcode":"91101",
    "sg:province":"CA",
    "sg:tags":[
        "counselor",
        "marriage",
        "family"
    ],
    "wof:name":"Lauryn Saylers Divers",
    "wof:placetype":"venue"
},
  "geometry": {"coordinates":[-118.14579000000001,34.136987],"type":"Point"}
}