{
  "type": "Feature",
  "properties": {
    "iso:country":"US",
    "sg:address":"2816 W Sunset Pl",
    "sg:city":"Los Angeles",
    "sg:classifiers":[
        {
            "category":"Travel",
            "subcategory":"Hotels & Motels",
            "type":"Entertainment"
        }
    ],
    "sg:phone":"+1 310 276 7356",
    "sg:postcode":"90005",
    "sg:province":"CA",
    "sg:website":"www.EssexManorLA.com",
    "wof:name":"Essex Manor Hotel Apartments",
    "wof:placetype":"venue"
},
  "geometry": {"coordinates":[-118.28486599999999,34.060509],"type":"Point"}
}