{
  "type": "Feature",
  "properties": {
    "addr:full":"420 N Puente Ave La Puente CA 91746",
    "addr:housenumber":"420",
    "addr:postcode":"91746",
    "addr:street":"N Puente Ave",
    "iso:country":"US",
    "sg:address":"420 N Puente Ave",
    "sg:city":"La Puente",
    "sg:classifiers":[
        {
            "category":"Wholesale",
            "subcategory":"Apparel",
            "type":"Manufacturing & Wholesale Goods"
        }
    ],
    "sg:phone":"+1 626 330 8651",
    "sg:postcode":"91746",
    "sg:province":"CA",
    "sg:tags":[
        "clothing"
    ],
    "wof:name":"L A Progres",
    "wof:placetype":"venue"
},
  "geometry": {"coordinates":[-117.98423,34.047814],"type":"Point"}
}