{
  "type": "Feature",
  "properties": {
    "iso:country":"US",
    "sg:address":"2315 E 1st St",
    "sg:city":"National City",
    "sg:classifiers":[
        {
            "category":"Retail",
            "subcategory":"Auto Repair",
            "type":"Services"
        }
    ],
    "sg:phone":"+1 619 708 9889",
    "sg:postcode":"91950",
    "sg:province":"CA",
    "sg:tags":[
        "towing"
    ],
    "wof:name":"Henry Towing",
    "wof:placetype":"venue"
},
  "geometry": {"coordinates":[-117.08660999999999,32.687602],"type":"Point"}
}