{
  "type": "Feature",
  "properties": {
    "iso:country":"US",
    "sg:address":"22865 Lake Forest Drive",
    "sg:city":"Lake Forest",
    "sg:classifiers":[
        {
            "category":"Banks & Credit Unions",
            "subcategory":"Financial Services",
            "type":"Services"
        }
    ],
    "sg:phone":"+1 949 597 9584",
    "sg:postcode":"92630",
    "sg:province":"CA",
    "sg:tags":[
        "broker",
        "mortgage"
    ],
    "wof:name":"Kauffman Mortgage",
    "wof:placetype":"venue"
},
  "geometry": {"coordinates":[-117.715808,33.629818],"type":"Point"}
}