{
  "type": "Feature",
  "properties": {
    "addr:full":"128 W 1st St Long Beach CA 90802",
    "addr:housenumber":"128",
    "addr:postcode":"90802",
    "addr:street":"W 1St St",
    "iso:country":"US",
    "sg:address":"128 W 1st St",
    "sg:city":"Long Beach",
    "sg:classifiers":[
        {
            "category":"Landmark",
            "subcategory":"Historic",
            "type":"Public Place"
        },
        {
            "category":"Education",
            "subcategory":"Library",
            "type":"Public Place"
        },
        {
            "category":"Retail",
            "subcategory":"Event Space",
            "type":"Services"
        },
        {
            "category":"Shopping Center",
            "type":"Public Place"
        },
        {
            "category":"Local Transit",
            "type":"Transportation"
        }
    ],
    "sg:phone":"+1 800 366 6883",
    "sg:postcode":"90802",
    "sg:province":"CA",
    "sg:tags":[
        "building",
        "venue",
        "historical"
    ],
    "sg:website":"www.mta.net",
    "wof:name":"Transit Mall Station",
    "wof:placetype":"venue"
},
  "geometry": {"coordinates":[-118.19280999999999,33.767966],"type":"Point"}
}