{
  "type": "Feature",
  "properties": {
    "iso:country":"US",
    "sg:address":"12576 Mabee Cir",
    "sg:city":"Garden Grove",
    "sg:classifiers":[
        {
            "category":"Building & Trades",
            "subcategory":"Cleaning & Sanitation",
            "type":"Services"
        }
    ],
    "sg:phone":"+1 714 534 2353",
    "sg:postcode":"92841",
    "sg:province":"CA",
    "sg:tags":[
        "window"
    ],
    "wof:name":"Huntington Beach Window",
    "wof:placetype":"venue"
},
  "geometry": {"coordinates":[-117.96828600000001,33.781227],"type":"Point"}
}