{
  "type": "Feature",
  "properties": {
    "addr:full":"7659 E Jensen Ave Fresno CA 93727",
    "addr:housenumber":"7659",
    "addr:postcode":"93727",
    "addr:street":"E Jensen Ave",
    "iso:country":"US",
    "sg:address":"7659 E Jensen Ave",
    "sg:city":"Fresno",
    "sg:classifiers":[
        {
            "category":"Farming",
            "subcategory":"Orchard",
            "type":"Manufacturing & Wholesale Goods"
        }
    ],
    "sg:phone":"+1 559 264 8758",
    "sg:postcode":"93727",
    "sg:province":"CA",
    "sg:tags":[
        "citrus",
        "grove",
        "fruit"
    ],
    "wof:name":"Fw Gerner Ranch",
    "wof:placetype":"venue"
},
  "geometry": {"coordinates":[-119.646907,36.707303],"type":"Point"}
}