{
  "type": "Feature",
  "properties": {
    "iso:country":"US",
    "sg:address":"578 Rio Lindo Ave",
    "sg:city":"Chico",
    "sg:classifiers":[
        {
            "category":"Social Services",
            "type":"Services"
        }
    ],
    "sg:phone":"+1 530 894 5585",
    "sg:postcode":"95926",
    "sg:province":"CA",
    "sg:tags":[
        "pregnancy",
        "counseling",
        "information"
    ],
    "wof:name":"Better Babies",
    "wof:placetype":"venue"
},
  "geometry": {"coordinates":[-121.847578,39.75363],"type":"Point"}
}