{
  "type": "Feature",
  "properties": {
    "iso:country":"US",
    "sg:address":"1 Front St",
    "sg:city":"San Francisco",
    "sg:classifiers":[
        {
            "category":"Banks & Credit Unions",
            "subcategory":"Investment Brokerage",
            "type":"Services"
        }
    ],
    "sg:phone":"+1 415 984 0170",
    "sg:postcode":"94111",
    "sg:province":"CA",
    "sg:tags":[
        "management"
    ],
    "sg:website":"www.sdrcm.com",
    "wof:name":"SDR Capital Management",
    "wof:placetype":"venue"
},
  "geometry": {"coordinates":[-122.398588,37.792408],"type":"Point"}
}