{
  "type": "Feature",
  "properties": {
    "iso:country":"US",
    "sg:address":"2738 Sepulveda Blvd",
    "sg:city":"Torrance",
    "sg:classifiers":[
        {
            "category":"Education",
            "subcategory":"Special Training",
            "type":"Public Place"
        }
    ],
    "sg:phone":"+1 310 326 7843",
    "sg:postcode":"90505",
    "sg:province":"CA",
    "sg:tags":[
        "tutoring",
        "center"
    ],
    "wof:name":"Kumon Central Torrance Center",
    "wof:placetype":"venue"
},
  "geometry": {"coordinates":[-118.333,33.8228],"type":"Point"}
}