{
  "type": "Feature",
  "properties": {
    "addr:full":"176 2nd St Los Altos CA 94022",
    "addr:housenumber":"176",
    "addr:postcode":"94022",
    "addr:street":"2Nd St",
    "iso:country":"US",
    "sg:address":"176 2nd St",
    "sg:city":"Los Altos",
    "sg:classifiers":[
        {
            "category":"Building & Trades",
            "subcategory":"Construction",
            "type":"Services"
        }
    ],
    "sg:phone":"+1 650 559 6100",
    "sg:postcode":"94022",
    "sg:province":"CA",
    "sg:tags":[
        "contractor"
    ],
    "wof:name":"Elemengard",
    "wof:placetype":"venue"
},
  "geometry": {"coordinates":[-122.11735400000001,37.379048],"type":"Point"}
}