{
  "type": "Feature",
  "properties": {
    "iso:country":"US",
    "sg:address":"1864 E Washington Blvd",
    "sg:city":"Pasadena",
    "sg:classifiers":[
        {
            "category":"Health Services",
            "subcategory":"Clinic",
            "type":"Services"
        }
    ],
    "sg:phone":"+1 626 398 5120",
    "sg:postcode":"91104",
    "sg:province":"CA",
    "sg:tags":[
        "home",
        "care"
    ],
    "wof:name":"International Nursing Registry",
    "wof:placetype":"venue"
},
  "geometry": {"coordinates":[-118.112572,34.169067],"type":"Point"}
}