{
  "type": "Feature",
  "properties": {
    "iso:country":"US",
    "sg:address":"763 Mabury Rd Ste 1",
    "sg:city":"San Jose",
    "sg:classifiers":[
        {
            "category":"Building & Trades",
            "subcategory":"Construction",
            "type":"Services"
        }
    ],
    "sg:phone":"+1 408 355 4282",
    "sg:postcode":"95133",
    "sg:province":"CA",
    "sg:tags":[
        "contractor"
    ],
    "sg:website":"www.granada-construction.com",
    "wof:name":"Granada Construction",
    "wof:placetype":"venue"
},
  "geometry": {"coordinates":[-121.890085,37.363379],"type":"Point"}
}