{
  "type": "Feature",
  "properties": {
    "iso:country":"US",
    "sg:address":"1121 Stockton St",
    "sg:city":"San Francisco",
    "sg:classifiers":[
        {
            "category":"Manufacturing",
            "subcategory":"Chemicals & Compounds",
            "type":"Manufacturing & Wholesale Goods"
        }
    ],
    "sg:phone":"+1 415 982 0258",
    "sg:postcode":"94133",
    "sg:province":"CA",
    "sg:tags":[
        "inorganic",
        "industrial",
        "mfg"
    ],
    "wof:name":"Huan Lin Mai",
    "wof:placetype":"venue"
},
  "geometry": {"coordinates":[-122.408476,37.796512],"type":"Point"}
}