{
  "type": "Feature",
  "properties": {
    "iso:country":"US",
    "sg:address":"2595 W Pico Blvd",
    "sg:city":"Los Angeles",
    "sg:classifiers":[
        {
            "category":"Home & Garden",
            "subcategory":"Building Materials",
            "type":"Retail Goods"
        }
    ],
    "sg:phone":"+1 213 388 5102",
    "sg:postcode":"90006",
    "sg:province":"CA",
    "sg:tags":[
        "plumbing",
        "fixture",
        "supply"
    ],
    "wof:name":"Pico Building Supply",
    "wof:placetype":"venue"
},
  "geometry": {"coordinates":[-118.294005,34.047326],"type":"Point"}
}