{
  "type": "Feature",
  "properties": {
    "iso:country":"US",
    "sg:address":"1919 W Gage Ave",
    "sg:city":"Los Angeles",
    "sg:classifiers":[
        {
            "category":"Manufacturing",
            "subcategory":"Paper Products",
            "type":"Manufacturing & Wholesale Goods"
        }
    ],
    "sg:phone":"+1 323 971 1875",
    "sg:postcode":"90047",
    "sg:province":"CA",
    "sg:tags":[
        "box"
    ],
    "wof:name":"Inpac Containers",
    "wof:placetype":"venue"
},
  "geometry": {"coordinates":[-118.31273899999999,33.981928],"type":"Point"}
}