{
  "type": "Feature",
  "properties": {
    "iso:country":"US",
    "sg:address":"155 E Campbell Ave",
    "sg:city":"Campbell",
    "sg:classifiers":[
        {
            "category":"Banks & Credit Unions",
            "subcategory":"Investment Brokerage",
            "type":"Services"
        }
    ],
    "sg:phone":"+1 408 374 2580",
    "sg:postcode":"95008",
    "sg:province":"CA",
    "sg:tags":[
        "consultant",
        "planning",
        "financial"
    ],
    "wof:name":"Whitehorse Financial",
    "wof:placetype":"venue"
},
  "geometry": {"coordinates":[-121.946078,37.287115],"type":"Point"}
}