{
  "type": "Feature",
  "properties": {
    "addr:full":"602 Frieda Dr Suisun City CA 94585",
    "addr:housenumber":"602",
    "addr:postcode":"94585",
    "addr:street":"Frieda Dr",
    "iso:country":"US",
    "sg:address":"602 Frieda Dr",
    "sg:city":"Suisun City",
    "sg:classifiers":[
        {
            "category":"Shopping",
            "type":"Retail Goods"
        }
    ],
    "sg:phone":"+1 707 425 4382",
    "sg:postcode":"94585",
    "sg:province":"CA",
    "sg:tags":[
        "metaphysical",
        "supply"
    ],
    "wof:name":"PSI Applications",
    "wof:placetype":"venue"
},
  "geometry": {"coordinates":[-122.007181,38.257494],"type":"Point"}
}