{
  "type": "Feature",
  "properties": {
    "iso:country":"US",
    "sg:address":"344 Plumosa Ave",
    "sg:city":"Vista",
    "sg:classifiers":[
        {
            "category":"Professional",
            "subcategory":"Lawyer & Legal Services",
            "type":"Services"
        }
    ],
    "sg:phone":"+1 760 734 1060",
    "sg:postcode":"92083",
    "sg:province":"CA",
    "sg:tags":[
        "attorney"
    ],
    "wof:name":"Geo Venture",
    "wof:placetype":"venue"
},
  "geometry": {"coordinates":[-117.208119,33.164873],"type":"Point"}
}