{
  "type": "Feature",
  "properties": {
    "iso:country":"US",
    "sg:address":"38080 Martha Ave",
    "sg:city":"Fremont",
    "sg:classifiers":[
        {
            "category":"Health Services",
            "subcategory":"Doctor",
            "type":"Services"
        }
    ],
    "sg:phone":"+1 510 797 7010",
    "sg:postcode":"94536",
    "sg:province":"CA",
    "sg:tags":[
        "dentist"
    ],
    "wof:name":"Scott M Hashimoto DDS",
    "wof:placetype":"venue"
},
  "geometry": {"coordinates":[-121.992318,37.561377],"type":"Point"}
}