{
  "type": "Feature",
  "properties": {
    "iso:country":"US",
    "sg:address":"8733 Elk Grove Blvd",
    "sg:city":"Elk Grove",
    "sg:classifiers":[
        {
            "category":"Personal",
            "subcategory":"Beauty Salon",
            "type":"Services"
        }
    ],
    "sg:phone":"+1 916 685 6181",
    "sg:postcode":"95624",
    "sg:province":"CA",
    "wof:name":"Dyer Perfection",
    "wof:placetype":"venue"
},
  "geometry": {"coordinates":[-121.381356,38.409063],"type":"Point"}
}