{
  "type": "Feature",
  "properties": {
    "addr:full":"6400 San Fernando Rd Glendale CA 91201",
    "addr:postcode":"6400;91201",
    "addr:street":"San Fernando Rd",
    "iso:country":"US",
    "sg:address":"6400 San Fernando Rd",
    "sg:city":"Glendale",
    "sg:classifiers":[
        {
            "category":"Banks & Credit Unions",
            "subcategory":"Bank",
            "type":"Services"
        },
        {
            "category":"Banks & Credit Unions",
            "subcategory":"Financial Services",
            "type":"Services"
        }
    ],
    "sg:phone":"+1 818 507 6700",
    "sg:postcode":"91201",
    "sg:province":"CA",
    "sg:tags":[
        "commercial",
        "loan",
        "internet",
        "saving",
        "banking"
    ],
    "sg:website":"https://www.bankofamerica.com/",
    "wof:name":"Bank of America",
    "wof:placetype":"venue"
},
  "geometry": {"coordinates":[-118.28830000000001,34.165958],"type":"Point"}
}