{
  "type": "Feature",
  "properties": {
    "iso:country":"US",
    "sg:address":"325 Chinquapin Ave",
    "sg:city":"Carlsbad",
    "sg:classifiers":[
        {
            "category":"Building & Trades",
            "subcategory":"Electrical",
            "type":"Services"
        }
    ],
    "sg:phone":"+1 858 663 5564",
    "sg:postcode":"92008",
    "sg:province":"CA",
    "sg:tags":[
        "electrician"
    ],
    "sg:website":"www.wheylandelectric.com",
    "wof:name":"Wheyland Electric",
    "wof:placetype":"venue"
},
  "geometry": {"coordinates":[-117.340811,33.147696],"type":"Point"}
}