{
  "type": "Feature",
  "properties": {
    "iso:country":"US",
    "sg:address":"8455 Utica Ave",
    "sg:city":"Rancho Cucamonga",
    "sg:classifiers":[
        {
            "category":"Wholesale",
            "subcategory":"Hardware",
            "type":"Manufacturing & Wholesale Goods"
        }
    ],
    "sg:phone":"+1 909 987 8234",
    "sg:postcode":"91730",
    "sg:province":"CA",
    "sg:tags":[
        "seal"
    ],
    "sg:website":"www.satoriseal.com",
    "wof:name":"Satori Seal Corp",
    "wof:placetype":"venue"
},
  "geometry": {"coordinates":[-117.572875,34.100436],"type":"Point"}
}