{
  "type": "Feature",
  "properties": {
    "iso:country":"US",
    "sg:address":"2191 Niles St",
    "sg:city":"Bakersfield",
    "sg:classifiers":[
        {
            "category":"Personal",
            "subcategory":"Beauty Salon",
            "type":"Services"
        }
    ],
    "sg:phone":"+1 661 323 6928",
    "sg:postcode":"93305",
    "sg:province":"CA",
    "wof:name":"Corona's Beauty Salon",
    "wof:placetype":"venue"
},
  "geometry": {"coordinates":[-118.970219,35.377101],"type":"Point"}
}