{
  "type": "Feature",
  "properties": {
    "iso:country":"US",
    "sg:address":"1250 Grand Ave",
    "sg:city":"Arroyo Grande",
    "sg:classifiers":[
        {
            "category":"Professional",
            "subcategory":"Business Services",
            "type":"Services"
        }
    ],
    "sg:phone":"+1 805 481 2699",
    "sg:postcode":"93420",
    "sg:province":"CA",
    "sg:tags":[
        "merchandise"
    ],
    "wof:name":"Boxx Express",
    "wof:placetype":"venue"
},
  "geometry": {"coordinates":[-120.602814,35.120708],"type":"Point"}
}