{
  "type": "Feature",
  "properties": {
    "addr:full":"2860 Artesia Blvd Redondo Beach CA 90278",
    "addr:postcode":"2860;90278",
    "addr:street":"Artesia Blvd",
    "iso:country":"US",
    "sg:address":"2860 Artesia Blvd",
    "sg:city":"Redondo Beach",
    "sg:classifiers":[
        {
            "category":"Autos & Motor Vehicles",
            "subcategory":"Auto Supplies",
            "type":"Retail Goods"
        }
    ],
    "sg:phone":"+1 310 542 7805",
    "sg:postcode":"90278",
    "sg:province":"CA",
    "sg:tags":[
        "automobile",
        "accessory"
    ],
    "wof:name":"Executive Class Automotive LTD",
    "wof:placetype":"venue"
},
  "geometry": {"coordinates":[-118.358644,33.872786],"type":"Point"}
}