{
  "type": "Feature",
  "properties": {
    "iso:country":"US",
    "sg:address":"10931 S Truro Ave",
    "sg:city":"Inglewood",
    "sg:classifiers":[
        {
            "category":"Wholesale",
            "subcategory":"Motor Vehicles",
            "type":"Manufacturing & Wholesale Goods"
        }
    ],
    "sg:phone":"+1 310 505 6731",
    "sg:postcode":"90304",
    "sg:province":"CA",
    "wof:name":"Pirate Auto Recovery Inc",
    "wof:placetype":"venue"
},
  "geometry": {"coordinates":[-118.358106,33.934995],"type":"Point"}
}