{
  "type": "Feature",
  "properties": {
    "iso:country":"US",
    "sg:address":"3032 W Avenue L",
    "sg:city":"Lancaster",
    "sg:classifiers":[
        {
            "category":"Shopping",
            "subcategory":"Beauty & Cosmetics",
            "type":"Retail Goods"
        },
        {
            "category":"Shopping",
            "subcategory":"Pharmacy",
            "type":"Retail Goods"
        },
        {
            "category":"Personal",
            "subcategory":"Beauty Salon",
            "type":"Services"
        }
    ],
    "sg:phone":"+1 661 718 8000",
    "sg:postcode":"93536",
    "sg:province":"CA",
    "sg:tags":[
        "cosmetics-wholesale",
        "medicines-patent",
        "manufacturer",
        "proprietary",
        "perfume"
    ],
    "wof:name":"Cristina Campbell Enterprises",
    "wof:placetype":"venue"
},
  "geometry": {"coordinates":[-118.184637,34.660268],"type":"Point"}
}