{
  "type": "Feature",
  "properties": {
    "iso:country":"US",
    "sg:address":"17832 Moro Rd",
    "sg:city":"Salinas",
    "sg:classifiers":[
        {
            "category":"Education",
            "subcategory":"School",
            "type":"Public Place"
        }
    ],
    "sg:phone":"+1 831 663 2700",
    "sg:postcode":"93907",
    "sg:province":"CA",
    "wof:name":"Hallmark",
    "wof:placetype":"venue"
},
  "geometry": {"coordinates":[-121.662493,36.803252],"type":"Point"}
}