{
  "type": "Feature",
  "properties": {
    "addr:full":"623 S A St Oxnard CA 93030",
    "addr:housenumber":"623",
    "addr:postcode":"93030",
    "addr:street":"S A St",
    "iso:country":"US",
    "sg:address":"623 S A St",
    "sg:city":"Oxnard",
    "sg:classifiers":[
        {
            "category":"Real Estate",
            "subcategory":"Developer",
            "type":"Services"
        }
    ],
    "sg:phone":"+1 805 240 2363",
    "sg:postcode":"93030",
    "sg:province":"CA",
    "sg:tags":[
        "cemetery"
    ],
    "wof:name":"Gvg Memorials",
    "wof:placetype":"venue"
},
  "geometry": {"coordinates":[-119.17865999999999,34.195327],"type":"Point"}
}