{
  "type": "Feature",
  "properties": {
    "addr:full":"1338 7th St Berkeley CA 94710",
    "addr:housenumber":"1338",
    "addr:postcode":"94710",
    "addr:street":"7Th St",
    "iso:country":"US",
    "sg:address":"1338 7th St",
    "sg:city":"Berkeley",
    "sg:classifiers":[
        {
            "category":"Wholesale",
            "subcategory":"Stationery",
            "type":"Manufacturing & Wholesale Goods"
        }
    ],
    "sg:phone":"+1 510 559 5545",
    "sg:postcode":"94710",
    "sg:province":"CA",
    "sg:tags":[
        "school",
        "supply"
    ],
    "wof:name":"Primary Concepts",
    "wof:placetype":"venue"
},
  "geometry": {"coordinates":[-122.30003499999999,37.878448],"type":"Point"}
}