{
  "type": "Feature",
  "properties": {
    "iso:country":"US",
    "sg:address":"1058 S Green Valley Rd",
    "sg:city":"Watsonville",
    "sg:classifiers":[
        {
            "category":"Banks & Credit Unions",
            "subcategory":"Investment Brokerage",
            "type":"Services"
        },
        {
            "category":"Insurance",
            "subcategory":"Hazard Insurance",
            "type":"Services"
        }
    ],
    "sg:phone":"+1 831 724 2284",
    "sg:postcode":"95076",
    "sg:province":"CA",
    "sg:tags":[
        "agent",
        "resume"
    ],
    "sg:website":"http://www.ortc.com",
    "wof:name":"Old Republic",
    "wof:placetype":"venue"
},
  "geometry": {"coordinates":[-121.78432599999999,36.917416],"type":"Point"}
}