{
  "type": "Feature",
  "properties": {
    "addr:full":"1600 N Grand Ave Ste A Santa Ana CA 92701",
    "addr:housenumber":"1600",
    "addr:postcode":"92701",
    "addr:street":"N Grand Ave Ste A",
    "iso:country":"US",
    "sg:address":"1600 N Grand Ave Ste A",
    "sg:city":"Santa Ana",
    "sg:classifiers":[
        {
            "category":"Retail",
            "subcategory":"Auto Repair",
            "type":"Services"
        }
    ],
    "sg:phone":"+1 714 542 0600",
    "sg:postcode":"92701",
    "sg:province":"CA",
    "sg:tags":[
        "body",
        "shop"
    ],
    "wof:name":"All Tune & Lube",
    "wof:placetype":"venue"
},
  "geometry": {"coordinates":[-117.851997,33.7589],"type":"Point"}
}