{
  "type": "Feature",
  "properties": {
    "addr:full":"1785 Voyager Ave Simi Valley CA 93063",
    "addr:housenumber":"1785",
    "addr:postcode":"93063",
    "addr:street":"Voyager Ave",
    "iso:country":"US",
    "sg:address":"1785 Voyager Ave",
    "sg:city":"Simi Valley",
    "sg:classifiers":[
        {
            "category":"Manufacturing",
            "subcategory":"Metals",
            "type":"Manufacturing & Wholesale Goods"
        }
    ],
    "sg:phone":"+1 805 584 4125",
    "sg:postcode":"93063",
    "sg:province":"CA",
    "sg:tags":[
        "tube",
        "fabricating"
    ],
    "wof:name":"Innovative Tube Design Inc",
    "wof:placetype":"venue"
},
  "geometry": {"coordinates":[-118.720921,34.269382],"type":"Point"}
}