{
  "type": "Feature",
  "properties": {
    "iso:country":"US",
    "sg:address":"5722 N Figueroa Street",
    "sg:city":"Los Angeles",
    "sg:classifiers":[
        {
            "category":"Shopping",
            "subcategory":"Stationery & Office Supplies",
            "type":"Retail Goods"
        }
    ],
    "sg:phone":"+1 323 256 2111",
    "sg:postcode":"90042",
    "sg:province":"CA",
    "sg:tags":[
        "equipment"
    ],
    "wof:name":"U S Office Machine Company",
    "wof:placetype":"venue"
},
  "geometry": {"coordinates":[-118.192107,34.109818],"type":"Point"}
}