{
  "type": "Feature",
  "properties": {
    "addr:full":"2855 Lone St Sacramento CA 95814",
    "addr:housenumber":"2855",
    "addr:postcode":"95814",
    "addr:street":"Lone St",
    "iso:country":"US",
    "sg:address":"2855 Lone St",
    "sg:city":"Sacramento",
    "sg:classifiers":[
        {
            "category":"Personal",
            "type":"Services"
        }
    ],
    "sg:phone":"+1 916 489 0176",
    "sg:postcode":"95814",
    "sg:province":"CA",
    "sg:tags":[
        "mover"
    ],
    "wof:name":"Coldwell Advanced Moving",
    "wof:placetype":"venue"
},
  "geometry": {"coordinates":[-121.491997,38.577599],"type":"Point"}
}