{
  "type": "Feature",
  "properties": {
    "iso:country":"US",
    "sg:address":"11367 Vernon Ave",
    "sg:city":"Chino",
    "sg:classifiers":[
        {
            "category":"Manufacturing",
            "subcategory":"Wood Products",
            "type":"Manufacturing & Wholesale Goods"
        }
    ],
    "sg:phone":"+1 909 590 7413",
    "sg:postcode":"91710",
    "sg:province":"CA",
    "sg:tags":[
        "container",
        "mfg"
    ],
    "wof:name":"Castle Crating & Third PA",
    "wof:placetype":"venue"
},
  "geometry": {"coordinates":[-117.68513900000001,34.047649],"type":"Point"}
}