{
  "type": "Feature",
  "properties": {
    "addr:full":"300 Myer Dr Apt 37 Chowchilla CA 93610",
    "addr:housenumber":"300;37",
    "addr:postcode":"93610",
    "addr:street":"Myer Dr Apt",
    "iso:country":"US",
    "sg:address":"300 Myer Dr Apt 37",
    "sg:city":"Chowchilla",
    "sg:classifiers":[
        {
            "category":"Real Estate",
            "subcategory":"Real Estate Operator",
            "type":"Services"
        }
    ],
    "sg:phone":"+1 559 665 1918",
    "sg:postcode":"93610",
    "sg:province":"CA",
    "sg:tags":[
        "apartment"
    ],
    "wof:name":"Chowchilla Garden Apartments",
    "wof:placetype":"venue"
},
  "geometry": {"coordinates":[-120.276353,37.110584],"type":"Point"}
}