{
  "type": "Feature",
  "properties": {
    "addr:full":"251 S Lake Ave Ste 920 Pasadena CA 91101",
    "addr:housenumber":"251",
    "addr:postcode":"91101",
    "addr:street":"S Lake Ave Ste 920",
    "iso:country":"US",
    "sg:address":"251 S Lake Ave Ste 920",
    "sg:city":"Pasadena",
    "sg:classifiers":[
        {
            "category":"Professional",
            "subcategory":"Lawyer & Legal Services",
            "type":"Services"
        }
    ],
    "sg:phone":"+1 626 792 0800",
    "sg:postcode":"91101",
    "sg:province":"CA",
    "sg:website":"www.immigrationlawoffice.com/",
    "wof:name":"Avedissian Lucy Attorney At Law",
    "wof:placetype":"venue"
},
  "geometry": {"coordinates":[-118.132535,34.141586],"type":"Point"}
}