{
  "type": "Feature",
  "properties": {
    "addr:full":"3085 W Capitol Ave West Sacramento CA 95691",
    "addr:housenumber":"3085",
    "addr:postcode":"95691",
    "addr:street":"W Capitol Ave",
    "iso:country":"US",
    "sg:address":"3085 W Capitol Ave",
    "sg:city":"West Sacramento",
    "sg:classifiers":[
        {
            "category":"Autos & Motor Vehicles",
            "subcategory":"Auto Supplies",
            "type":"Retail Goods"
        }
    ],
    "sg:phone":"+1 530 661 0724",
    "sg:postcode":"95691",
    "sg:province":"CA",
    "sg:tags":[
        "tire"
    ],
    "sg:website":"www.goodyear.com",
    "wof:name":"Goodyear Commercial Tire & Svc",
    "wof:placetype":"venue"
},
  "geometry": {"coordinates":[-121.548863,38.579238],"type":"Point"}
}