{
  "type": "Feature",
  "properties": {
    "addr:full":"254 W Fairview Ave San Gabriel CA 91776",
    "addr:housenumber":"254",
    "addr:postcode":"91776",
    "addr:street":"W Fairview Ave",
    "iso:country":"US",
    "sg:address":"254 W Fairview Ave",
    "sg:city":"San Gabriel",
    "sg:classifiers":[
        {
            "category":"Personal",
            "subcategory":"Barber",
            "type":"Services"
        }
    ],
    "sg:phone":"+1 626 576 7702",
    "sg:postcode":"91776",
    "sg:province":"CA",
    "wof:name":"Valley Square Barber Shop",
    "wof:placetype":"venue"
},
  "geometry": {"coordinates":[-118.102997,34.09],"type":"Point"}
}