{
  "type": "Feature",
  "properties": {
    "addr:full":"4260 Eight Mile Rd Camino CA 95709",
    "addr:housenumber":"4260",
    "addr:postcode":"95709",
    "addr:street":"Eight Mile Rd",
    "iso:country":"US",
    "sg:address":"4260 Eight Mile Rd",
    "sg:city":"Camino",
    "sg:classifiers":[
        {
            "category":"Government",
            "subcategory":"Office",
            "type":"Public Place"
        }
    ],
    "sg:phone":"+1 530 644 2324",
    "sg:postcode":"95709",
    "sg:province":"CA",
    "sg:tags":[
        "conservation"
    ],
    "wof:name":"Placervile Ranger District",
    "wof:placetype":"venue"
},
  "geometry": {"coordinates":[-120.664787,38.737539],"type":"Point"}
}