{
  "type": "Feature",
  "properties": {
    "addr:full":"18701 Gehricke Rd Sonoma CA 95476",
    "addr:postcode":"18701;95476",
    "addr:street":"Gehricke Rd",
    "iso:country":"US",
    "sg:address":"18701 Gehricke Rd",
    "sg:city":"Sonoma",
    "sg:classifiers":[
        {
            "category":"Manufacturing",
            "subcategory":"Food",
            "type":"Manufacturing & Wholesale Goods"
        }
    ],
    "sg:phone":"+1 707 938 1960",
    "sg:postcode":"95476",
    "sg:province":"CA",
    "sg:tags":[
        "mfg",
        "beverage",
        "alcoholic"
    ],
    "wof:name":"Ravenswood Winery",
    "wof:placetype":"venue"
},
  "geometry": {"coordinates":[-122.44359900000001,38.304372],"type":"Point"}
}