{
  "type": "Feature",
  "properties": {
    "iso:country":"US",
    "sg:address":"1740 Saviers Rd",
    "sg:city":"Oxnard",
    "sg:classifiers":[
        {
            "category":"Manufacturing",
            "subcategory":"Apparel",
            "type":"Manufacturing & Wholesale Goods"
        }
    ],
    "sg:phone":"+1 805 654 9932",
    "sg:postcode":"93033",
    "sg:province":"CA",
    "sg:tags":[
        "sewing",
        "contractor"
    ],
    "wof:name":"Thomas Street Designs",
    "wof:placetype":"venue"
},
  "geometry": {"coordinates":[-119.17739400000001,34.182237],"type":"Point"}
}