{
  "type": "Feature",
  "properties": {
    "iso:country":"US",
    "sg:address":"505 Oak ave # C",
    "sg:city":"Carlsbad",
    "sg:classifiers":[
        {
            "category":"Retail",
            "subcategory":"Auto Repair",
            "type":"Services"
        }
    ],
    "sg:phone":"+1 760 720 1448",
    "sg:postcode":"92008",
    "sg:province":"CA",
    "sg:tags":[
        "oil",
        "change"
    ],
    "wof:name":"Village automotive",
    "wof:placetype":"venue"
},
  "geometry": {"coordinates":[-117.347399,33.158445],"type":"Point"}
}