{
  "type": "Feature",
  "properties": {
    "iso:country":"US",
    "sg:address":"3979 Trust Way Suite 200",
    "sg:city":"Hayward",
    "sg:classifiers":[
        {
            "category":"Restaurant",
            "type":"Food & Drink"
        }
    ],
    "sg:postcode":"94545",
    "sg:province":"CA",
    "sg:tags":[
        "traditional",
        "american"
    ],
    "wof:name":"The City Bistro",
    "wof:placetype":"venue"
},
  "geometry": {"coordinates":[-122.12596600000001,37.623605],"type":"Point"}
}