{
  "type": "Feature",
  "properties": {
    "addr:full":"6239 College Ave Oakland CA 94618",
    "addr:housenumber":"6239",
    "addr:postcode":"94618",
    "addr:street":"College Ave",
    "iso:country":"US",
    "sg:address":"6239 College Ave",
    "sg:city":"Oakland",
    "sg:classifiers":[
        {
            "category":"Professional",
            "subcategory":"Engineering",
            "type":"Services"
        }
    ],
    "sg:phone":"+1 510 547 8205",
    "sg:postcode":"94618",
    "sg:province":"CA",
    "sg:tags":[
        "engineer"
    ],
    "wof:name":"Bracewell Engineering Inc.",
    "wof:placetype":"venue"
},
  "geometry": {"coordinates":[-122.252296,37.849535],"type":"Point"}
}