{
  "type": "Feature",
  "properties": {
    "iso:country":"US",
    "sg:address":"1531 I St Ste 2",
    "sg:city":"Sacramento",
    "sg:classifiers":[
        {
            "category":"Education",
            "subcategory":"University",
            "type":"Public Place"
        }
    ],
    "sg:phone":"+1 916 443 4760",
    "sg:postcode":"95814",
    "sg:province":"CA",
    "sg:tags":[
        "college"
    ],
    "wof:name":"University Of Sacramento",
    "wof:placetype":"venue"
},
  "geometry": {"coordinates":[-121.48567199999999,38.57946],"type":"Point"}
}