{
  "type": "Feature",
  "properties": {
    "iso:country":"US",
    "sg:address":"501 N Fairfax Ave",
    "sg:city":"Los Angeles",
    "sg:classifiers":[
        {
            "category":"Home & Garden",
            "subcategory":"Household Appliances",
            "type":"Retail Goods"
        }
    ],
    "sg:phone":"+1 323 654 6052",
    "sg:postcode":"90036",
    "sg:province":"CA",
    "sg:website":"www.usaappliances.net",
    "wof:name":"Arc & USA Appliance Service Inc",
    "wof:placetype":"venue"
},
  "geometry": {"coordinates":[-118.361787,34.080299],"type":"Point"}
}