{
  "type": "Feature",
  "properties": {
    "iso:country":"US",
    "sg:address":"505 Forest Ave",
    "sg:city":"Laguna Beach",
    "sg:classifiers":[
        {
            "category":"Recreation",
            "type":"Entertainment"
        }
    ],
    "sg:phone":"+1 949 497 0716",
    "sg:postcode":"92651",
    "sg:province":"CA",
    "sg:tags":[
        "parks"
    ],
    "wof:name":"Laguna Beach Recreation Svc",
    "wof:placetype":"venue"
},
  "geometry": {"coordinates":[-117.781835,33.546114],"type":"Point"}
}