{
  "type": "Feature",
  "properties": {
    "addr:full":"5933 20th St Rio Linda CA 95673",
    "addr:housenumber":"5933",
    "addr:postcode":"95673",
    "addr:street":"20Th St",
    "iso:country":"US",
    "sg:address":"5933 20th St",
    "sg:city":"Rio Linda",
    "sg:classifiers":[
        {
            "category":"Building & Trades",
            "subcategory":"Construction",
            "type":"Services"
        }
    ],
    "sg:phone":"+1 916 991 1212",
    "sg:postcode":"95673",
    "sg:province":"CA",
    "sg:tags":[
        "concrete",
        "cutting",
        "breaking",
        "sawing"
    ],
    "wof:name":"Alta Sierra Concrete Co",
    "wof:placetype":"venue"
},
  "geometry": {"coordinates":[-121.419949,38.67493],"type":"Point"}
}