{
  "type": "Feature",
  "properties": {
    "iso:country":"US",
    "sg:address":"1831 Sunset Cliffs Blvd",
    "sg:city":"San Diego",
    "sg:classifiers":[
        {
            "category":"Health Services",
            "subcategory":"Doctor",
            "type":"Services"
        }
    ],
    "sg:phone":"+1 619 225 1611",
    "sg:postcode":"92107",
    "sg:province":"CA",
    "sg:tags":[
        "dentist"
    ],
    "wof:name":"Richard P Mc Laughlin DDS",
    "wof:placetype":"venue"
},
  "geometry": {"coordinates":[-117.248337,32.74373],"type":"Point"}
}