{
  "type": "Feature",
  "properties": {
    "addr:full":"505 Central Ave Pacific Grove CA 93950",
    "addr:housenumber":"505",
    "addr:postcode":"93950",
    "addr:street":"Central Ave",
    "iso:country":"US",
    "sg:address":"505 Central Ave",
    "sg:city":"Pacific Grove",
    "sg:classifiers":[
        {
            "category":"Health Services",
            "subcategory":"Doctor",
            "type":"Services"
        }
    ],
    "sg:phone":"+1 831 645 9990",
    "sg:postcode":"93950",
    "sg:province":"CA",
    "sg:tags":[
        "physician",
        "surgeon"
    ],
    "wof:name":"Pacific Groves Medical Clinic",
    "wof:placetype":"venue"
},
  "geometry": {"coordinates":[-121.915222,36.621589],"type":"Point"}
}