{
  "type": "Feature",
  "properties": {
    "iso:country":"US",
    "sg:address":"4B Peninsula Center",
    "sg:city":"Rollng Hills Estates",
    "sg:classifiers":[
        {
            "category":"Shopping",
            "subcategory":"Bicycles & Sporting Goods",
            "type":"Retail Goods"
        }
    ],
    "sg:phone":"+1 310 377 7441",
    "sg:postcode":"90274",
    "sg:province":"CA",
    "sg:tags":[
        "bike"
    ],
    "sg:website":"www.pvbike.com",
    "wof:name":"PV Bicycle Center",
    "wof:placetype":"venue"
},
  "geometry": {"coordinates":[-118.376462,33.775957],"type":"Point"}
}