{
  "type": "Feature",
  "properties": {
    "iso:country":"US",
    "sg:address":"711 Van Ness Avenue",
    "sg:city":"San Francisco",
    "sg:classifiers":[
        {
            "category":"Banks & Credit Unions",
            "subcategory":"Bank",
            "type":"Services"
        }
    ],
    "sg:phone":"+1 415 929 6070",
    "sg:postcode":"94102",
    "sg:province":"CA",
    "wof:name":"United Commercial Bank",
    "wof:placetype":"venue"
},
  "geometry": {"coordinates":[-122.420998,37.782101],"type":"Point"}
}