{
  "type": "Feature",
  "properties": {
    "addr:full":"602 Van Ness Ave E3-208 San Francisco CA 94117",
    "addr:housenumber":"602",
    "addr:postcode":"94117",
    "addr:street":"Van Ness Ave",
    "iso:country":"US",
    "sg:address":"602 Van Ness Ave E3-208",
    "sg:city":"San Francisco",
    "sg:classifiers":[
        {
            "category":"Shopping",
            "subcategory":"Pets & Pet Supplies",
            "type":"Retail Goods"
        }
    ],
    "sg:phone":"+1 408 829 8049",
    "sg:postcode":"94117",
    "sg:province":"CA",
    "sg:tags":[
        "training"
    ],
    "sg:website":"www.kaygodog.com",
    "wof:name":"Kaygo Dog Training",
    "wof:placetype":"venue"
},
  "geometry": {"coordinates":[-122.42036,37.781096],"type":"Point"}
}