{
  "type": "Feature",
  "properties": {
    "iso:country":"US",
    "sg:address":"7824 Alondra Blvd",
    "sg:city":"Paramount",
    "sg:classifiers":[
        {
            "category":"Bars & Pubs",
            "subcategory":"Dive Bar",
            "type":"Food & Drink"
        }
    ],
    "sg:phone":"+1 562 634 9001",
    "sg:postcode":"90723",
    "sg:province":"CA",
    "wof:name":"Mr J's",
    "wof:placetype":"venue"
},
  "geometry": {"coordinates":[-118.162003,33.889],"type":"Point"}
}