{
  "type": "Feature",
  "properties": {
    "iso:country":"US",
    "sg:address":"827 24th St",
    "sg:city":"Paso Robles",
    "sg:classifiers":[
        {
            "category":"Freight",
            "type":"Transportation"
        }
    ],
    "sg:phone":"+1 805 239 0880",
    "sg:postcode":"93446",
    "sg:province":"CA",
    "sg:tags":[
        "commercial",
        "storage"
    ],
    "wof:name":"24th Street Mini Storage",
    "wof:placetype":"venue"
},
  "geometry": {"coordinates":[-120.689204,35.639421],"type":"Point"}
}