{
  "type": "Feature",
  "properties": {
    "addr:full":"300 Ave H Barstow CA 92311",
    "addr:housenumber":"300",
    "addr:postcode":"92311",
    "addr:street":"Ave H",
    "iso:country":"US",
    "sg:address":"300 Ave H",
    "sg:city":"Barstow",
    "sg:classifiers":[
        {
            "category":"Organizations",
            "subcategory":"Religious Organization",
            "type":"Services"
        }
    ],
    "sg:phone":"+1 760 256 3887",
    "sg:postcode":"92311",
    "sg:province":"CA",
    "sg:tags":[
        "church"
    ],
    "wof:name":"Living Waters Fellowship",
    "wof:placetype":"venue"
},
  "geometry": {"coordinates":[-117.047595,34.892515],"type":"Point"}
}