{
  "type": "Feature",
  "properties": {
    "iso:country":"US",
    "sg:address":"3424 Northgate Blvd",
    "sg:city":"Sacramento",
    "sg:classifiers":[
        {
            "category":"Retail",
            "subcategory":"Auto Repair",
            "type":"Services"
        }
    ],
    "sg:phone":"+1 916 920 4424",
    "sg:postcode":"95834",
    "sg:province":"CA",
    "sg:tags":[
        "automobile",
        "lubrication"
    ],
    "sg:website":"www.jiffylubeca.com",
    "wof:name":"Jiffy Lube",
    "wof:placetype":"venue"
},
  "geometry": {"coordinates":[-121.474998,38.629002],"type":"Point"}
}