{
  "type": "Feature",
  "properties": {
    "addr:city":"Ukiah",
    "addr:full":"431 S Main St Ukiah, Ca 95482",
    "addr:house_number":"431",
    "addr:housenumber":"431",
    "addr:phone":"+1 707-467-2836",
    "addr:postcode":"95482",
    "addr:road":"S Main St",
    "addr:state":"CA",
    "addr:street":"S Main St",
    "iso:country":"US",
    "sg:address":"431 S Main St",
    "sg:city":"Ukiah",
    "sg:classifiers":[
        {
            "category":"Museum",
            "type":"Entertainment"
        }
    ],
    "sg:phone":"+1 707 467 2836",
    "sg:postcode":"95482",
    "sg:province":"CA",
    "sg:website":"www.gracehudsonmuseum.org",
    "wof:name":"Grace Hudson Museum-Sun House",
    "wof:placetype":"venue"
},
  "geometry": {"coordinates":[-123.20574999999999,39.14704],"type":"Point"}
}