{
  "type": "Feature",
  "properties": {
    "iso:country":"US",
    "sg:address":"431 S Main St",
    "sg:city":"Ukiah",
    "sg:classifiers":[
        {
            "category":"Museum",
            "type":"Entertainment"
        }
    ],
    "sg:phone":"+1 707 467 2836",
    "sg:postcode":"95482",
    "sg:province":"CA",
    "sg:website":"www.gracehudsonmuseum.org",
    "wof:name":"Grace Hudson Museum-Sun House",
    "wof:placetype":"venue"
},
  "geometry": {"coordinates":[-123.206014,39.147878],"type":"Point"}
}