{
  "type": "Feature",
  "properties": {
    "iso:country":"US",
    "sg:address":"2325 Wilshire Blvd",
    "sg:city":"Santa Monica",
    "sg:classifiers":[
        {
            "category":"Real Estate",
            "subcategory":"Real Estate Agent",
            "type":"Services"
        }
    ],
    "sg:phone":"+1 310 828 5514",
    "sg:postcode":"90403",
    "sg:province":"CA",
    "sg:tags":[
        "manager",
        "general",
        "contractor"
    ],
    "wof:name":"Kanan Brothers Realty",
    "wof:placetype":"venue"
},
  "geometry": {"coordinates":[-118.480102,34.033927],"type":"Point"}
}