{
  "type": "Feature",
  "properties": {
    "addr:full":"8948 Bolsa Ave Westminster CA 92683",
    "addr:housenumber":"8948",
    "addr:postcode":"92683",
    "addr:street":"Bolsa Ave",
    "iso:country":"US",
    "sg:address":"8948 Bolsa Ave",
    "sg:city":"Westminster",
    "sg:classifiers":[
        {
            "category":"Restaurant",
            "type":"Food & Drink"
        },
        {
            "category":"Food & Beverages",
            "subcategory":"Bakery",
            "type":"Retail Goods"
        },
        {
            "category":"Bakery",
            "type":"Food & Drink"
        }
    ],
    "sg:phone":"+1 714 897 3927",
    "sg:postcode":"92683",
    "sg:province":"CA",
    "sg:tags":[
        "sandwich",
        "vietnamese"
    ],
    "wof:name":"Banh Mi & Che Cali Bakery",
    "wof:placetype":"venue"
},
  "geometry": {"coordinates":[-117.973,33.744701],"type":"Point"}
}