{
  "type": "Feature",
  "properties": {
    "iso:country":"US",
    "sg:address":"2443 Fillmore St Ste 537",
    "sg:city":"San Francisco",
    "sg:classifiers":[
        {
            "category":"Shopping",
            "subcategory":"Pets & Pet Supplies",
            "type":"Retail Goods"
        },
        {
            "category":"Retail",
            "subcategory":"Pet Boarding",
            "type":"Services"
        }
    ],
    "sg:phone":"+1 415 387 3647",
    "sg:postcode":"94115",
    "sg:province":"CA",
    "sg:tags":[
        "walker",
        "dog",
        "boarding/pet",
        "sitting"
    ],
    "sg:website":"www.dogwalks.com",
    "wof:name":"Dogwalks",
    "wof:placetype":"venue"
},
  "geometry": {"coordinates":[-122.43480599999999,37.792193],"type":"Point"}
}