{
  "type": "Feature",
  "properties": {
    "addr:full":"9314 Golden St Alta Loma CA 91737",
    "addr:housenumber":"9314",
    "addr:postcode":"91737",
    "addr:street":"Golden St",
    "iso:country":"US",
    "sg:address":"9314 Golden St",
    "sg:city":"Alta Loma",
    "sg:classifiers":[
        {
            "category":"Building & Trades",
            "subcategory":"Plumbing",
            "type":"Services"
        }
    ],
    "sg:phone":"+1 909 466 0203",
    "sg:postcode":"91737",
    "sg:province":"CA",
    "sg:tags":[
        "conditioning",
        "air",
        "system",
        "contractor"
    ],
    "wof:name":"Acr Engineering Inc",
    "wof:placetype":"venue"
},
  "geometry": {"coordinates":[-117.60173399999999,34.146925],"type":"Point"}
}