{
  "type": "Feature",
  "properties": {
    "iso:country":"US",
    "sg:address":"6132 Pacific Blvd",
    "sg:city":"Huntington Park",
    "sg:classifiers":[
        {
            "category":"Food & Beverages",
            "subcategory":"Bakery",
            "type":"Retail Goods"
        }
    ],
    "sg:phone":"+1 323 583 6872",
    "sg:postcode":"90255",
    "sg:province":"CA",
    "sg:tags":[
        "baker"
    ],
    "wof:name":"LA Reyna Bakery & Delicatessen",
    "wof:placetype":"venue"
},
  "geometry": {"coordinates":[-118.225102,33.985214],"type":"Point"}
}