{
  "type": "Feature",
  "properties": {
    "iso:country":"US",
    "sg:address":"15250 Hesperian Blvd",
    "sg:city":"San Leandro",
    "sg:classifiers":[
        {
            "category":"Real Estate",
            "subcategory":"Real Estate Services",
            "type":"Services"
        }
    ],
    "sg:phone":"+1 510 909 5579",
    "sg:postcode":"94578",
    "sg:province":"CA",
    "sg:website":"vickie4realestate.com/",
    "wof:name":"Victoria del Rosario - Area Pro Realty",
    "wof:placetype":"venue"
},
  "geometry": {"coordinates":[-122.12959499999999,37.697722],"type":"Point"}
}