{
  "type": "Feature",
  "properties": {
    "addr:full":"396 Martin Ave Santa Clara CA 95050",
    "addr:housenumber":"396",
    "addr:postcode":"95050",
    "addr:street":"Martin Ave",
    "iso:country":"US",
    "sg:address":"396 Martin Ave",
    "sg:city":"Santa Clara",
    "sg:classifiers":[
        {
            "category":"Communications",
            "type":"Services"
        }
    ],
    "sg:phone":"+1 408 855 9771",
    "sg:postcode":"95050",
    "sg:province":"CA",
    "wof:name":"Ajilon Communication Inc",
    "wof:placetype":"venue"
},
  "geometry": {"coordinates":[-121.941427,37.366402],"type":"Point"}
}