{
  "type": "Feature",
  "properties": {
    "iso:country":"US",
    "sg:address":"641 Cam de Los Mares",
    "sg:city":"San Clemente",
    "sg:classifiers":[
        {
            "category":"Banks & Credit Unions",
            "subcategory":"Bank",
            "type":"Services"
        }
    ],
    "sg:phone":"+1 949 248 5656",
    "sg:postcode":"92673",
    "sg:province":"CA",
    "sg:tags":[
        "commercial"
    ],
    "wof:name":"Bank of West",
    "wof:placetype":"venue"
},
  "geometry": {"coordinates":[-117.64863,33.45738],"type":"Point"}
}