{
  "type": "Feature",
  "properties": {
    "iso:country":"US",
    "sg:address":"10983 N Wolfe Rd",
    "sg:city":"Cupertino",
    "sg:classifiers":[
        {
            "category":"Wholesale",
            "subcategory":"Groceries",
            "type":"Manufacturing & Wholesale Goods"
        }
    ],
    "sg:phone":"+1 408 252 1330",
    "sg:postcode":"95014",
    "sg:province":"CA",
    "sg:tags":[
        "tea"
    ],
    "wof:name":"Young's Tea",
    "wof:placetype":"venue"
},
  "geometry": {"coordinates":[-122.014242,37.337378],"type":"Point"}
}