{
  "type": "Feature",
  "properties": {
    "iso:country":"US",
    "sg:address":"22424 13th St",
    "sg:city":"Newhall",
    "sg:classifiers":[
        {
            "category":"Wholesale",
            "subcategory":"Home Furnishings",
            "type":"Manufacturing & Wholesale Goods"
        },
        {
            "category":"Home & Garden",
            "subcategory":"Building Materials",
            "type":"Retail Goods"
        },
        {
            "category":"Building & Trades",
            "subcategory":"Construction",
            "type":"Services"
        },
        {
            "category":"Home & Garden",
            "subcategory":"Carpets & Floor Coverings",
            "type":"Retail Goods"
        }
    ],
    "sg:phone":"+1 661 255 2773",
    "sg:postcode":"91321",
    "sg:province":"CA",
    "sg:tags":[
        "granite",
        "tile-contractors",
        "terrazzo",
        "flooring",
        "contractor"
    ],
    "sg:website":"http://www.southerncaliforniatile.com",
    "wof:name":"So. California Tile & Home Center",
    "wof:placetype":"venue"
},
  "geometry": {"coordinates":[-118.52961500000001,34.385408],"type":"Point"}
}