{
  "type": "Feature",
  "properties": {
    "addr:full":"4756 Starbuck Ave Santa Rosa CA 95409",
    "addr:housenumber":"4756",
    "addr:postcode":"95409",
    "addr:street":"Starbuck Ave",
    "iso:country":"US",
    "sg:address":"4756 Starbuck Ave",
    "sg:city":"Santa Rosa",
    "sg:classifiers":[
        {
            "category":"Professional",
            "subcategory":"Engineering",
            "type":"Services"
        }
    ],
    "sg:phone":"+1 707 539 4756",
    "sg:postcode":"95409",
    "sg:province":"CA",
    "sg:tags":[
        "engineer"
    ],
    "wof:name":"Engineering Consulting",
    "wof:placetype":"venue"
},
  "geometry": {"coordinates":[-122.669073,38.464266],"type":"Point"}
}