{
  "type": "Feature",
  "properties": {
    "addr:full":"20520 Kittridge St Winnetka CA 91306",
    "addr:postcode":"20520;91306",
    "addr:street":"Kittridge St",
    "iso:country":"US",
    "sg:address":"20520 Kittridge St",
    "sg:city":"Winnetka",
    "sg:classifiers":[
        {
            "category":"Communications",
            "subcategory":"Film & Video Production",
            "type":"Services"
        }
    ],
    "sg:phone":"+1 818 347 1811",
    "sg:postcode":"91306",
    "sg:province":"CA",
    "sg:tags":[
        "motion"
    ],
    "wof:name":"Big Heart Prods",
    "wof:placetype":"venue"
},
  "geometry": {"coordinates":[-118.580882,34.190348],"type":"Point"}
}