{
  "type": "Feature",
  "properties": {
    "addr:full":"1300 Clay St Ste 600 Oakland CA 94612",
    "addr:housenumber":"1300",
    "addr:postcode":"94612",
    "addr:street":"Clay St Ste 600",
    "iso:country":"US",
    "sg:address":"1300 Clay St Ste 600",
    "sg:city":"Oakland",
    "sg:classifiers":[
        {
            "category":"Professional",
            "subcategory":"Lawyer & Legal Services",
            "type":"Services"
        }
    ],
    "sg:phone":"+1 510 734 3145",
    "sg:postcode":"94612",
    "sg:province":"CA",
    "sg:tags":[
        "litigation",
        "attorney",
        "criminal",
        "plan",
        "law"
    ],
    "sg:website":"http://eastbay.citysearch.com/profile/external/604419472/oakland_ca/choyce_law_firm.html?publisher=yellowpages&reference_id=1&placement=ypwebsitemip",
    "wof:name":"The Choyce Law Firm",
    "wof:placetype":"venue"
},
  "geometry": {"coordinates":[-122.273819,37.804715],"type":"Point"}
}