{
  "type": "Feature",
  "properties": {
    "addr:full":"300 Broadway Suite 23 San Francisco CA 94131",
    "addr:housenumber":"300;23",
    "addr:postcode":"94131",
    "addr:street":"Broadway Suite",
    "iso:country":"US",
    "sg:address":"300 Broadway Suite 23",
    "sg:city":"San Francisco",
    "sg:classifiers":[
        {
            "category":"Professional",
            "type":"Services"
        }
    ],
    "sg:phone":"+1 415 929 1581",
    "sg:postcode":"94131",
    "sg:province":"CA",
    "sg:website":"www.dvdcopycat.com",
    "wof:name":"DVD Copycat Inc.",
    "wof:placetype":"venue"
},
  "geometry": {"coordinates":[-122.40264000000001,37.798684],"type":"Point"}
}