{
  "type": "Feature",
  "properties": {
    "iso:country":"US",
    "sg:address":"10203 Lower Azusa Rd",
    "sg:city":"Temple City",
    "sg:classifiers":[
        {
            "category":"Real Estate",
            "subcategory":"Real Estate Agent",
            "type":"Services"
        }
    ],
    "sg:phone":"+1 626 292 6881",
    "sg:postcode":"91780",
    "sg:province":"CA",
    "wof:name":"Southern Pacific Realty",
    "wof:placetype":"venue"
},
  "geometry": {"coordinates":[-118.043707,34.091527],"type":"Point"}
}