{
  "type": "Feature",
  "properties": {
    "addr:full":"3036 Mather Field Rd Rancho Cordova CA 95670",
    "addr:housenumber":"3036",
    "addr:postcode":"95670",
    "addr:street":"Mather Field Rd",
    "iso:country":"US",
    "sg:address":"3036 Mather Field Rd",
    "sg:city":"Rancho Cordova",
    "sg:classifiers":[
        {
            "category":"Home & Garden",
            "subcategory":"Furniture",
            "type":"Retail Goods"
        }
    ],
    "sg:phone":"+1 916 364 7044",
    "sg:postcode":"95670",
    "sg:province":"CA",
    "sg:tags":[
        "including"
    ],
    "wof:name":"Homewood Furnishings",
    "wof:placetype":"venue"
},
  "geometry": {"coordinates":[-121.309968,38.582578],"type":"Point"}
}