{
  "type": "Feature",
  "properties": {
    "iso:country":"US",
    "sg:address":"11501 Dublin Blvd",
    "sg:city":"Dublin",
    "sg:classifiers":[
        {
            "category":"Insurance",
            "subcategory":"Title Insurance",
            "type":"Services"
        }
    ],
    "sg:phone":"+1 925 556 2000",
    "sg:postcode":"94568",
    "sg:province":"CA",
    "wof:name":"Ticor Title Insurance",
    "wof:placetype":"venue"
},
  "geometry": {"coordinates":[-121.94364299999999,37.699684],"type":"Point"}
}