{
  "type": "Feature",
  "properties": {
    "addr:full":"2421 Alamo Ave Chico CA 95926",
    "addr:housenumber":"2421",
    "addr:postcode":"95926",
    "addr:street":"Alamo Ave",
    "iso:country":"US",
    "sg:address":"2421 Alamo Ave",
    "sg:city":"Chico",
    "sg:phone":"+1 530 893 0144",
    "sg:postcode":"95926",
    "sg:province":"CA",
    "sg:tags":[
        "farm",
        "rice"
    ],
    "wof:name":"Custom Farming",
    "wof:placetype":"venue"
},
  "geometry": {"coordinates":[-121.873385,39.747105],"type":"Point"}
}