{
  "type": "Feature",
  "properties": {
    "addr:full":"584 Monterey Ave Morro Bay CA 93442",
    "addr:housenumber":"584",
    "addr:postcode":"93442",
    "addr:street":"Monterey Ave",
    "iso:country":"US",
    "sg:address":"584 Monterey Ave",
    "sg:city":"Morro Bay",
    "sg:classifiers":[
        {
            "category":"Building & Trades",
            "subcategory":"Construction",
            "type":"Services"
        }
    ],
    "sg:phone":"+1 805 433 9649",
    "sg:postcode":"93442",
    "sg:province":"CA",
    "sg:tags":[
        "contractor"
    ],
    "wof:name":"Woody & Assoc",
    "wof:placetype":"venue"
},
  "geometry": {"coordinates":[-120.848753,35.363368],"type":"Point"}
}