{
  "type": "Feature",
  "properties": {
    "iso:country":"US",
    "sg:address":"100 Bryant St",
    "sg:city":"Bridgeport",
    "sg:classifiers":[
        {
            "category":"Government",
            "subcategory":"Police Station",
            "type":"Public Place"
        }
    ],
    "sg:phone":"+1 760 932 5278",
    "sg:postcode":"93517",
    "sg:province":"CA",
    "sg:tags":[
        "sheriff"
    ],
    "wof:name":"Sheriff Office-Finance",
    "wof:placetype":"venue"
},
  "geometry": {"coordinates":[-119.225288,38.256869],"type":"Point"}
}