{
  "type": "Feature",
  "properties": {
    "iso:country":"US",
    "sg:address":"22427 Ventura Blvd",
    "sg:city":"Woodland Hills",
    "sg:classifiers":[
        {
            "category":"Health Services",
            "subcategory":"Health Practitioner",
            "type":"Services"
        }
    ],
    "sg:phone":"+1 818 888 8875",
    "sg:postcode":"91364",
    "sg:province":"CA",
    "sg:tags":[
        "acupuncture"
    ],
    "wof:name":"Happy Foot Health Center",
    "wof:placetype":"venue"
},
  "geometry": {"coordinates":[-118.615336,34.168658],"type":"Point"}
}