{
  "type": "Feature",
  "properties": {
    "iso:country":"US",
    "sg:address":"909 S La Verne Avenue",
    "sg:city":"Los Angeles",
    "sg:classifiers":[
        {
            "category":"Retail",
            "subcategory":"Laundry & Dry Cleaning",
            "type":"Services"
        }
    ],
    "sg:phone":"+1 323 264 3957",
    "sg:postcode":"90022",
    "sg:province":"CA",
    "wof:name":"New Express Dry Cleaners",
    "wof:placetype":"venue"
},
  "geometry": {"coordinates":[-118.16255099999999,34.021316],"type":"Point"}
}