{
  "type": "Feature",
  "properties": {
    "addr:full":"595 Millich Dr Ste 103 Campbell CA 95008",
    "addr:housenumber":"595",
    "addr:postcode":"95008",
    "addr:street":"Millich Dr Ste 103",
    "iso:country":"US",
    "sg:address":"595 Millich Dr Ste 103",
    "sg:city":"Campbell",
    "sg:classifiers":[
        {
            "category":"Health Services",
            "subcategory":"Health Practitioner",
            "type":"Services"
        }
    ],
    "sg:phone":"+1 408 370 6360",
    "sg:postcode":"95008",
    "sg:province":"CA",
    "sg:tags":[
        "home",
        "care"
    ],
    "sg:website":"www.homeinstead.com/136",
    "wof:name":"Home Instead Senior Care",
    "wof:placetype":"venue"
},
  "geometry": {"coordinates":[-121.96001800000001,37.295547],"type":"Point"}
}