{
  "type": "Feature",
  "properties": {
    "addr:full":"591 W Palo Alto Ave Fresno CA 93704",
    "addr:housenumber":"591",
    "addr:postcode":"93704",
    "addr:street":"W Palo Alto Ave",
    "iso:country":"US",
    "sg:address":"591 W Palo Alto Ave",
    "sg:city":"Fresno",
    "sg:classifiers":[
        {
            "category":"Local Transit",
            "type":"Transportation"
        }
    ],
    "sg:phone":"+1 559 228 1117",
    "sg:postcode":"93704",
    "sg:province":"CA",
    "sg:tags":[
        "passenger",
        "limousine"
    ],
    "wof:name":"Five Star Limousine & Trnsp",
    "wof:placetype":"venue"
},
  "geometry": {"coordinates":[-119.803876,36.833156],"type":"Point"}
}