{
  "type": "Feature",
  "properties": {
    "iso:country":"US",
    "sg:address":"334 W Washington St",
    "sg:city":"San Diego",
    "sg:classifiers":[
        {
            "category":"Restaurant",
            "type":"Food & Drink"
        }
    ],
    "sg:phone":"+1 619 574 6630",
    "sg:postcode":"92103",
    "sg:province":"CA",
    "sg:tags":[
        "fast"
    ],
    "sg:website":"www.riceking.com",
    "wof:name":"Rice King",
    "wof:placetype":"venue"
},
  "geometry": {"coordinates":[-117.167,32.75],"type":"Point"}
}