{
  "type": "Feature",
  "properties": {
    "addr:full":"5607 Market St Emeryville CA 94608",
    "addr:housenumber":"5607",
    "addr:postcode":"94608",
    "addr:street":"Market St",
    "iso:country":"US",
    "sg:address":"5607 Market St",
    "sg:city":"Emeryville",
    "sg:classifiers":[
        {
            "category":"Professional",
            "type":"Services"
        }
    ],
    "sg:phone":"+1 510 601 1930",
    "sg:postcode":"94608",
    "sg:province":"CA",
    "wof:name":"Osahar Jourdan",
    "wof:placetype":"venue"
},
  "geometry": {"coordinates":[-122.274518,37.841603],"type":"Point"}
}