{
  "type": "Feature",
  "properties": {
    "addr:full":"1150 Prospect St La Jolla CA 92037",
    "addr:housenumber":"1150",
    "addr:postcode":"92037",
    "addr:street":"Prospect St",
    "iso:country":"US",
    "sg:address":"1150 Prospect St",
    "sg:city":"La Jolla",
    "sg:classifiers":[
        {
            "category":"Coffee & Tea",
            "type":"Food & Drink"
        }
    ],
    "sg:menulink":"http://www.allmenus.com/ca/san-diego/119487-starbucks-coffee/menu/",
    "sg:phone":"+1 858 551 5526",
    "sg:postcode":"92037",
    "sg:province":"CA",
    "sg:tags":[
        "american"
    ],
    "wof:name":"Starbucks Coffee",
    "wof:placetype":"venue"
},
  "geometry": {"coordinates":[-117.27329,32.848773],"type":"Point"}
}