{
  "type": "Feature",
  "properties": {
    "iso:country":"US",
    "sg:address":"10640 Colima Rd",
    "sg:city":"Whittier",
    "sg:phone":"+1 888 236 0818",
    "sg:postcode":"90604",
    "sg:province":"CA",
    "sg:website":"http://www.forrent.com/apartment-community-profile/1025425.php?cmp=CAC-CSearchProfile",
    "wof:name":"Casa Colima",
    "wof:placetype":"venue"
},
  "geometry": {"coordinates":[-118.015134,33.937462],"type":"Point"}
}