{
  "type": "Feature",
  "properties": {
    "iso:country":"US",
    "sg:address":"510 Central Ave Ste A",
    "sg:city":"Alameda",
    "sg:classifiers":[
        {
            "category":"Social Services",
            "subcategory":"Retirement Home",
            "type":"Services"
        }
    ],
    "sg:phone":"+1 510 523 0113",
    "sg:postcode":"94501",
    "sg:province":"CA",
    "sg:website":"www.bayharbourcarehome.com/",
    "wof:name":"Bay Harbour Residential Care Home",
    "wof:placetype":"venue"
},
  "geometry": {"coordinates":[-122.28191700000001,37.771251],"type":"Point"}
}