{
  "type": "Feature",
  "properties": {
    "iso:country":"US",
    "sg:address":"4720 W Jennifer Ave",
    "sg:city":"Fresno",
    "sg:classifiers":[
        {
            "category":"Professional",
            "subcategory":"Management & Consulting",
            "type":"Services"
        }
    ],
    "sg:phone":"+1 559 271 1148",
    "sg:postcode":"93722",
    "sg:province":"CA",
    "sg:tags":[
        "construction"
    ],
    "wof:name":"Mark 1 Construction Management",
    "wof:placetype":"venue"
},
  "geometry": {"coordinates":[-119.877824,36.810935],"type":"Point"}
}