{
  "type": "Feature",
  "properties": {
    "iso:country":"US",
    "sg:address":"530 University Ave",
    "sg:city":"Palo Alto",
    "sg:classifiers":[
        {
            "category":"Manufacturing",
            "subcategory":"Printing",
            "type":"Manufacturing & Wholesale Goods"
        }
    ],
    "sg:phone":"+1 650 473 0160",
    "sg:postcode":"94301",
    "sg:province":"CA",
    "sg:tags":[
        "publisher",
        "book"
    ],
    "wof:name":"Warde Publishers Inc",
    "wof:placetype":"venue"
},
  "geometry": {"coordinates":[-122.159077,37.448292],"type":"Point"}
}