{
  "type": "Feature",
  "properties": {
    "iso:country":"US",
    "sg:address":"1944 N Tustin St Ste 121",
    "sg:city":"Orange",
    "sg:classifiers":[
        {
            "category":"Building & Trades",
            "subcategory":"Construction",
            "type":"Services"
        }
    ],
    "sg:phone":"+1 714 282 1766",
    "sg:postcode":"92865",
    "sg:province":"CA",
    "sg:tags":[
        "tile-contractors"
    ],
    "sg:website":"http://www.hardrocktilemarble.com",
    "wof:name":"Hardrock Tile & Marble",
    "wof:placetype":"venue"
},
  "geometry": {"coordinates":[-117.83599100000001,33.820285],"type":"Point"}
}