{
  "type": "Feature",
  "properties": {
    "addr:full":"362 E Puente St Covina CA 91723",
    "addr:housenumber":"362",
    "addr:postcode":"91723",
    "addr:street":"E Puente St",
    "iso:country":"US",
    "sg:address":"362 E Puente St",
    "sg:city":"Covina",
    "sg:classifiers":[
        {
            "category":"Building & Trades",
            "subcategory":"Construction",
            "type":"Services"
        }
    ],
    "sg:phone":"+1 626 826 3133",
    "sg:postcode":"91723",
    "sg:province":"CA",
    "sg:tags":[
        "concrete",
        "contractor"
    ],
    "wof:name":"Sammy DS Concrete",
    "wof:placetype":"venue"
},
  "geometry": {"coordinates":[-117.884716,34.08251],"type":"Point"}
}