{
  "type": "Feature",
  "properties": {
    "iso:country":"US",
    "sg:address":"1460 E Corson St",
    "sg:city":"Pasadena",
    "sg:classifiers":[
        {
            "category":"Real Estate",
            "subcategory":"Real Estate Agent",
            "type":"Services"
        }
    ],
    "sg:phone":"+1 626 585 1991",
    "sg:postcode":"91106",
    "sg:province":"CA",
    "wof:name":"L C Properties",
    "wof:placetype":"venue"
},
  "geometry": {"coordinates":[-118.1182,34.151718],"type":"Point"}
}