{
  "type": "Feature",
  "properties": {
    "addr:full":"861 6th Ave San Diego CA 92101",
    "addr:housenumber":"861",
    "addr:postcode":"92101",
    "addr:street":"6Th Ave",
    "iso:country":"US",
    "sg:address":"861 6th Ave",
    "sg:city":"San Diego",
    "sg:classifiers":[
        {
            "category":"Wholesale",
            "subcategory":"Jewelry",
            "type":"Manufacturing & Wholesale Goods"
        }
    ],
    "sg:phone":"+1 619 231 1188",
    "sg:postcode":"92101",
    "sg:province":"CA",
    "sg:tags":[
        "diamond"
    ],
    "wof:name":"Bruce Fine Watches Diamonds",
    "wof:placetype":"venue"
},
  "geometry": {"coordinates":[-117.159172,32.714028],"type":"Point"}
}