{
  "type": "Feature",
  "properties": {
    "addr:full":"401 E Campbell Ave Campbell CA 95008",
    "addr:housenumber":"401",
    "addr:postcode":"95008",
    "addr:street":"E Campbell Ave",
    "iso:country":"US",
    "sg:address":"401 E Campbell Ave",
    "sg:city":"Campbell",
    "sg:classifiers":[
        {
            "category":"Personal",
            "subcategory":"Beauty Salon",
            "type":"Services"
        }
    ],
    "sg:phone":"+1 408 374 2100",
    "sg:postcode":"95008",
    "sg:province":"CA",
    "wof:name":"C J Hair Design",
    "wof:placetype":"venue"
},
  "geometry": {"coordinates":[-121.942761,37.287105],"type":"Point"}
}