{
  "type": "Feature",
  "properties": {
    "addr:full":"8848 Lankershim Blvd Sun Valley CA 91352",
    "addr:housenumber":"8848",
    "addr:postcode":"91352",
    "addr:street":"Lankershim Blvd",
    "iso:country":"US",
    "sg:address":"8848 Lankershim Blvd",
    "sg:city":"Sun Valley",
    "sg:classifiers":[
        {
            "category":"Food & Beverages",
            "subcategory":"Groceries & Convenience Stores",
            "type":"Retail Goods"
        }
    ],
    "sg:phone":"+1 818 767 1408",
    "sg:postcode":"91352",
    "sg:province":"CA",
    "sg:tags":[
        "grocer"
    ],
    "wof:name":"Far East Market",
    "wof:placetype":"venue"
},
  "geometry": {"coordinates":[-118.38768899999999,34.228757],"type":"Point"}
}