{
  "type": "Feature",
  "properties": {
    "addr:full":"1855 41st Avenue Capitola CA 95010",
    "addr:housenumber":"1855",
    "addr:postcode":"95010",
    "addr:street":"41St Avenue",
    "iso:country":"US",
    "sg:address":"1855 41st Avenue",
    "sg:city":"Capitola",
    "sg:classifiers":[
        {
            "category":"Coffee & Tea",
            "type":"Food & Drink"
        }
    ],
    "sg:phone":"+1 831 479 9651",
    "sg:postcode":"95010",
    "sg:province":"CA",
    "wof:name":"Starbucks Coffee",
    "wof:placetype":"venue"
},
  "geometry": {"coordinates":[-121.96499300000001,36.976474],"type":"Point"}
}