{
  "type": "Feature",
  "properties": {
    "addr:full":"4705 Laurel Canyon Blvd Studio City CA 91607",
    "addr:housenumber":"4705",
    "addr:postcode":"91607",
    "addr:street":"Laurel Canyon Blvd",
    "iso:country":"US",
    "sg:address":"4705 Laurel Canyon Blvd",
    "sg:city":"Studio City",
    "sg:classifiers":[
        {
            "category":"Cinema",
            "subcategory":"Movie Theater",
            "type":"Entertainment"
        }
    ],
    "sg:phone":"+1 818 487 0077",
    "sg:postcode":"91607",
    "sg:province":"CA",
    "wof:name":"Technicolor Digital Cinema",
    "wof:placetype":"venue"
},
  "geometry": {"coordinates":[-118.396558,34.15684],"type":"Point"}
}