{
  "type": "Feature",
  "properties": {
    "addr:full":"13325 Everglade Blvd Clearlake Oaks CA 95423",
    "addr:housenumber":"13325",
    "addr:postcode":"95423",
    "addr:street":"Everglade Blvd Clearlake",
    "iso:country":"US",
    "sg:address":"13325 Everglade Blvd",
    "sg:city":"Clearlake Oaks",
    "sg:classifiers":[
        {
            "category":"Professional",
            "subcategory":"Business Services",
            "type":"Services"
        }
    ],
    "sg:phone":"+1 707 998 0224",
    "sg:postcode":"95423",
    "sg:province":"CA",
    "sg:tags":[
        "notary"
    ],
    "wof:name":"Susan Garrett",
    "wof:placetype":"venue"
},
  "geometry": {"coordinates":[-122.66221400000001,39.019201],"type":"Point"}
}