{
  "type": "Feature",
  "properties": {
    "addr:full":"2879 Winery Ave Clovis CA 93612",
    "addr:housenumber":"2879",
    "addr:postcode":"93612",
    "addr:street":"Winery Ave",
    "iso:country":"US",
    "sg:address":"2879 Winery Ave",
    "sg:city":"Clovis",
    "sg:classifiers":[
        {
            "category":"Professional",
            "subcategory":"Management & Consulting",
            "type":"Services"
        }
    ],
    "sg:phone":"+1 559 292 0618",
    "sg:postcode":"93612",
    "sg:province":"CA",
    "sg:tags":[
        "retail",
        "direct",
        "sales"
    ],
    "wof:name":"M B Craft Products",
    "wof:placetype":"venue"
},
  "geometry": {"coordinates":[-119.73161,36.801108],"type":"Point"}
}