{
  "type": "Feature",
  "properties": {
    "iso:country":"US",
    "sg:address":"2119 N Bellflower Blvd",
    "sg:city":"Long Beach",
    "sg:classifiers":[
        {
            "category":"Restaurant",
            "type":"Food & Drink"
        }
    ],
    "sg:phone":"+1 562 343 2651",
    "sg:postcode":"90815",
    "sg:province":"CA",
    "sg:tags":[
        "thai",
        "sushi",
        "bar"
    ],
    "sg:website":"www.BaiPluThaiAndSushi.com",
    "wof:name":"Bai Plu Restaurant & Sushi Bar",
    "wof:placetype":"venue"
},
  "geometry": {"coordinates":[-118.125422,33.794831],"type":"Point"}
}