{
  "type": "Feature",
  "properties": {
    "iso:country":"US",
    "sg:address":"3524 Atwater Blvd",
    "sg:city":"Atwater",
    "sg:classifiers":[
        {
            "category":"Building & Trades",
            "subcategory":"Electrical",
            "type":"Services"
        }
    ],
    "sg:phone":"+1 209 358 0112",
    "sg:postcode":"95301",
    "sg:province":"CA",
    "sg:tags":[
        "industrial",
        "electrician",
        "contractors-commercial",
        "electric"
    ],
    "wof:name":"Atwater Electric",
    "wof:placetype":"venue"
},
  "geometry": {"coordinates":[-120.58758400000001,37.33786],"type":"Point"}
}