{
  "type": "Feature",
  "properties": {
    "addr:full":"6100 Lankershim Blvd North Hollywood CA 91606",
    "addr:housenumber":"6100",
    "addr:postcode":"91606",
    "addr:street":"Lankershim Blvd",
    "iso:country":"US",
    "sg:address":"6100 Lankershim Blvd",
    "sg:city":"North Hollywood",
    "sg:classifiers":[
        {
            "category":"Professional",
            "subcategory":"Business Services",
            "type":"Services"
        }
    ],
    "sg:phone":"+1 818 505 6956",
    "sg:postcode":"91606",
    "sg:province":"CA",
    "sg:tags":[
        "water",
        "treatment"
    ],
    "wof:name":"Water Delite",
    "wof:placetype":"venue"
},
  "geometry": {"coordinates":[-118.38460600000001,34.181243],"type":"Point"}
}