{
  "type": "Feature",
  "properties": {
    "iso:country":"US",
    "sg:address":"6475 Sunnyslope Rd",
    "sg:city":"Phelan",
    "sg:classifiers":[
        {
            "category":"Professional",
            "type":"Services"
        }
    ],
    "sg:phone":"+1 760 868 2004",
    "sg:postcode":"92371",
    "sg:province":"CA",
    "wof:name":"Freight Advantage Sysems",
    "wof:placetype":"venue"
},
  "geometry": {"coordinates":[-117.524325,34.411947],"type":"Point"}
}