{
  "type": "Feature",
  "properties": {
    "addr:full":"246 Via Novella Aptos CA 95003",
    "addr:housenumber":"246",
    "addr:postcode":"ca 95003",
    "addr:street":"Via Novella",
    "iso:country":"US",
    "sg:address":"246 Via Novella",
    "sg:city":"Aptos",
    "sg:classifiers":[
        {
            "category":"Shopping",
            "subcategory":"Books",
            "type":"Retail Goods"
        }
    ],
    "sg:phone":"+1 831 685 1063",
    "sg:postcode":"95003",
    "sg:province":"CA",
    "sg:tags":[
        "dealer"
    ],
    "wof:name":"Info Hi Book Store",
    "wof:placetype":"venue"
},
  "geometry": {"coordinates":[-121.86941400000001,36.94641],"type":"Point"}
}