{
  "type": "Feature",
  "properties": {
    "iso:country":"US",
    "sg:address":"2281 Golden Cir",
    "sg:city":"Newport Beach",
    "sg:classifiers":[
        {
            "category":"Professional",
            "type":"Services"
        }
    ],
    "sg:phone":"+1 949 645 6919",
    "sg:postcode":"92660",
    "sg:province":"CA",
    "wof:name":"Phae Mon Khema Inc",
    "wof:placetype":"venue"
},
  "geometry": {"coordinates":[-117.882125,33.654926],"type":"Point"}
}