{
  "type": "Feature",
  "properties": {
    "iso:country":"US",
    "sg:address":"545 White Oak Dr",
    "sg:city":"Santa Rosa",
    "sg:classifiers":[
        {
            "category":"Organizations",
            "subcategory":"Religious Organization",
            "type":"Services"
        }
    ],
    "sg:phone":"+1 707 538 7540",
    "sg:postcode":"95409",
    "sg:province":"CA",
    "sg:tags":[
        "church"
    ],
    "wof:name":"Star Of The Valley Church",
    "wof:placetype":"venue"
},
  "geometry": {"coordinates":[-122.605293,38.440723],"type":"Point"}
}