{
  "type": "Feature",
  "properties": {
    "iso:country":"US",
    "sg:address":"1163 Cushman Ave",
    "sg:city":"San Diego",
    "sg:classifiers":[
        {
            "category":"Shopping",
            "subcategory":"Party Supplies",
            "type":"Retail Goods"
        }
    ],
    "sg:phone":"+1 858 427 4843",
    "sg:postcode":"92110",
    "sg:province":"CA",
    "sg:website":"www.socalbounce.com/",
    "wof:name":"So Cal Bounce",
    "wof:placetype":"venue"
},
  "geometry": {"coordinates":[-117.19914799999999,32.768175],"type":"Point"}
}