{
  "type": "Feature",
  "properties": {
    "iso:country":"US",
    "sg:address":"10255 Colima Rd",
    "sg:city":"Whittier",
    "sg:classifiers":[
        {
            "category":"Wholesale",
            "subcategory":"Construction Materials",
            "type":"Manufacturing & Wholesale Goods"
        }
    ],
    "sg:phone":"+1 562 906 4465",
    "sg:postcode":"90603",
    "sg:province":"CA",
    "wof:name":"Import Zeramic",
    "wof:placetype":"venue"
},
  "geometry": {"coordinates":[-118.01203099999999,33.941514],"type":"Point"}
}