{
  "type": "Feature",
  "properties": {
    "iso:country":"US",
    "sg:address":"2121 Peralta St",
    "sg:city":"Oakland",
    "sg:classifiers":[
        {
            "category":"Manufacturing",
            "subcategory":"Jewelry",
            "type":"Manufacturing & Wholesale Goods"
        },
        {
            "category":"Wholesale",
            "subcategory":"Jewelry",
            "type":"Manufacturing & Wholesale Goods"
        }
    ],
    "sg:phone":"+1 510 452 0065",
    "sg:postcode":"94607",
    "sg:province":"CA",
    "sg:tags":[
        "jeweler",
        "costume",
        "mfg"
    ],
    "wof:name":"Firefly",
    "wof:placetype":"venue"
},
  "geometry": {"coordinates":[-122.290299,37.816074],"type":"Point"}
}