{
  "type": "Feature",
  "properties": {
    "iso:country":"US",
    "sg:address":"422 S Western Ave",
    "sg:city":"Los Angeles",
    "sg:classifiers":[
        {
            "category":"Professional",
            "subcategory":"Art Services",
            "type":"Services"
        }
    ],
    "sg:phone":"+1 213 368 0308",
    "sg:postcode":"90020",
    "sg:province":"CA",
    "sg:tags":[
        "graphic",
        "designer"
    ],
    "wof:name":"G H Graphics",
    "wof:placetype":"venue"
},
  "geometry": {"coordinates":[-118.309026,34.065736],"type":"Point"}
}