{
  "type": "Feature",
  "properties": {
    "addr:full":"8609 Madison St Paramount CA 90723",
    "addr:housenumber":"8609",
    "addr:postcode":"90723",
    "addr:street":"Madison St",
    "iso:country":"US",
    "sg:address":"8609 Madison St",
    "sg:city":"Paramount",
    "sg:classifiers":[
        {
            "category":"Building & Trades",
            "subcategory":"Landscaping Services",
            "type":"Services"
        }
    ],
    "sg:phone":"+1 562 634 1633",
    "sg:postcode":"90723",
    "sg:province":"CA",
    "sg:tags":[
        "landscape"
    ],
    "wof:name":"Unlimited Landscape",
    "wof:placetype":"venue"
},
  "geometry": {"coordinates":[-118.14856,33.891203],"type":"Point"}
}