{
  "type": "Feature",
  "properties": {
    "iso:country":"US",
    "sg:address":"621 S Spring St",
    "sg:city":"Los Angeles",
    "sg:classifiers":[
        {
            "category":"Professional",
            "type":"Services"
        }
    ],
    "sg:phone":"+1 213 622 0244",
    "sg:postcode":"90014",
    "sg:province":"CA",
    "sg:tags":[
        "establishment"
    ],
    "wof:name":"Hyde Park Partners",
    "wof:placetype":"venue"
},
  "geometry": {"coordinates":[-118.252131,34.044861],"type":"Point"}
}