{
  "type": "Feature",
  "properties": {
    "iso:country":"US",
    "sg:address":"1315 Jacklin Rd",
    "sg:city":"Milpitas",
    "sg:classifiers":[
        {
            "category":"Personal",
            "subcategory":"Beauty Salon",
            "type":"Services"
        }
    ],
    "sg:phone":"+1 408 263 2313",
    "sg:postcode":"95035",
    "sg:province":"CA",
    "sg:tags":[
        "hair",
        "stylist"
    ],
    "wof:name":"Hair Expo",
    "wof:placetype":"venue"
},
  "geometry": {"coordinates":[-121.88718299999999,37.447884],"type":"Point"}
}