{
  "type": "Feature",
  "properties": {
    "addr:full":"447 E Amerige Ave Fullerton CA 92832",
    "addr:housenumber":"447",
    "addr:postcode":"92832",
    "addr:street":"E Amerige Ave",
    "iso:country":"US",
    "sg:address":"447 E Amerige Ave",
    "sg:city":"Fullerton",
    "sg:classifiers":[
        {
            "category":"Restaurant",
            "type":"Food & Drink"
        }
    ],
    "sg:phone":"+1 714 879 7517",
    "sg:postcode":"92832",
    "sg:province":"CA",
    "sg:tags":[
        "eating"
    ],
    "wof:name":"Tea Cupboard",
    "wof:placetype":"venue"
},
  "geometry": {"coordinates":[-117.916444,33.87151],"type":"Point"}
}