{
  "type": "Feature",
  "properties": {
    "addr:full":"641 Ralston Ave Belmont CA 94002",
    "addr:housenumber":"641",
    "addr:postcode":"94002",
    "addr:street":"Ralston Ave",
    "iso:country":"US",
    "sg:address":"641 Ralston Ave",
    "sg:city":"Belmont",
    "sg:classifiers":[
        {
            "category":"Professional",
            "type":"Services"
        }
    ],
    "sg:phone":"+1 650 594 2997",
    "sg:postcode":"94002",
    "sg:province":"CA",
    "wof:name":"Atm Cash Link",
    "wof:placetype":"venue"
},
  "geometry": {"coordinates":[-122.274878,37.521277],"type":"Point"}
}