{
  "type": "Feature",
  "properties": {
    "addr:full":"19690 San Jose Ave City Of Industry CA 91748",
    "addr:housenumber":"19690",
    "addr:postcode":"91748",
    "addr:street":"San Jose Ave",
    "iso:country":"US",
    "sg:address":"19690 San Jose Ave",
    "sg:city":"City Of Industry",
    "sg:classifiers":[
        {
            "category":"Wholesale",
            "subcategory":"Durable Goods & Equipment",
            "type":"Manufacturing & Wholesale Goods"
        }
    ],
    "sg:phone":"+1 909 468 2712",
    "sg:postcode":"91748",
    "sg:province":"CA",
    "sg:tags":[
        "importer"
    ],
    "wof:name":"Tree Import Export Corp",
    "wof:placetype":"venue"
},
  "geometry": {"coordinates":[-117.871844,34.001155],"type":"Point"}
}