{
  "type": "Feature",
  "properties": {
    "iso:country":"US",
    "sg:address":"101 Grant School Rd",
    "sg:city":"Healdsburg",
    "sg:classifiers":[
        {
            "category":"Wholesale",
            "subcategory":"Non-durable Goods",
            "type":"Manufacturing & Wholesale Goods"
        }
    ],
    "sg:phone":"+1 707 431 2225",
    "sg:postcode":"95448",
    "sg:province":"CA",
    "sg:tags":[
        "pet",
        "supply"
    ],
    "sg:website":"www.aquadine.com",
    "wof:name":"Aqua Dine",
    "wof:placetype":"venue"
},
  "geometry": {"coordinates":[-122.849545,38.591399],"type":"Point"}
}