{
  "type": "Feature",
  "properties": {
    "iso:country":"US",
    "sg:address":"1544 Klauber Ave",
    "sg:city":"San Diego",
    "sg:classifiers":[
        {
            "category":"Social Services",
            "subcategory":"Child Care",
            "type":"Services"
        }
    ],
    "sg:phone":"+1 619 262 5360",
    "sg:postcode":"92114",
    "sg:province":"CA",
    "wof:name":"Pepper Grove Childrens School",
    "wof:placetype":"venue"
},
  "geometry": {"coordinates":[-117.055797,32.722166],"type":"Point"}
}