{
  "type": "Feature",
  "properties": {
    "iso:country":"US",
    "sg:address":"4740 N Grand Ave",
    "sg:city":"Covina",
    "sg:classifiers":[
        {
            "category":"Organizations",
            "subcategory":"Non-profit Organization",
            "type":"Services"
        }
    ],
    "sg:phone":"+1 626 859 2089",
    "sg:postcode":"91724",
    "sg:province":"CA",
    "wof:name":"San Gabriel Children's Ctr",
    "wof:placetype":"venue"
},
  "geometry": {"coordinates":[-117.87247600000001,34.097346],"type":"Point"}
}