{
  "type": "Feature",
  "properties": {
    "addr:full":"8240 Calvine Rd Sacramento CA 95828",
    "addr:housenumber":"8240",
    "addr:postcode":"95828",
    "addr:street":"Calvine Rd",
    "iso:country":"US",
    "sg:address":"8240 Calvine Rd",
    "sg:city":"Sacramento",
    "sg:classifiers":[
        {
            "category":"Coffee & Tea",
            "type":"Food & Drink"
        }
    ],
    "sg:menulink":"http://www.allmenus.com/ca/elk-grove/108982-starbucks-coffee/menu/",
    "sg:phone":"+1 916 688 8505",
    "sg:postcode":"95828",
    "sg:province":"CA",
    "sg:tags":[
        "american"
    ],
    "wof:name":"Starbucks Coffee",
    "wof:placetype":"venue"
},
  "geometry": {"coordinates":[-121.404825,38.455521],"type":"Point"}
}