{
  "type": "Feature",
  "properties": {
    "addr:full":"7475 Anaconda Ave Garden Grove CA 92841",
    "addr:housenumber":"7475",
    "addr:postcode":"92841",
    "addr:street":"Anaconda Ave",
    "iso:country":"US",
    "sg:address":"7475 Anaconda Ave",
    "sg:city":"Garden Grove",
    "sg:classifiers":[
        {
            "category":"Manufacturing",
            "subcategory":"Printing",
            "type":"Manufacturing & Wholesale Goods"
        }
    ],
    "sg:phone":"+1 714 799 0333",
    "sg:postcode":"92841",
    "sg:province":"CA",
    "sg:tags":[
        "screen"
    ],
    "wof:name":"Pure Color Design & Screen",
    "wof:placetype":"venue"
},
  "geometry": {"coordinates":[-118.00530500000001,33.782556],"type":"Point"}
}