{
  "type": "Feature",
  "properties": {
    "addr:full":"12837 Gambusa Way San Diego CA 92129",
    "addr:housenumber":"12837",
    "addr:postcode":"92129",
    "addr:street":"Gambusa Way",
    "iso:country":"US",
    "sg:address":"12837 Gambusa Way",
    "sg:city":"San Diego",
    "sg:classifiers":[
        {
            "category":"Professional",
            "subcategory":"Management & Consulting",
            "type":"Services"
        }
    ],
    "sg:phone":"+1 858 538 5443",
    "sg:postcode":"92129",
    "sg:province":"CA",
    "sg:tags":[
        "marketing",
        "consultant"
    ],
    "wof:name":"Delta International Marketing",
    "wof:placetype":"venue"
},
  "geometry": {"coordinates":[-117.132715,32.950448],"type":"Point"}
}