{
  "type": "Feature",
  "properties": {
    "iso:country":"US",
    "sg:address":"25041 Southport St",
    "sg:city":"Laguna Hills",
    "sg:classifiers":[
        {
            "category":"Government",
            "subcategory":"Office",
            "type":"Public Place"
        }
    ],
    "sg:phone":"+1 760 725 7689",
    "sg:postcode":"92653",
    "sg:province":"CA",
    "sg:tags":[
        "national",
        "security"
    ],
    "wof:name":"Aliso Viejo Armed Forces",
    "wof:placetype":"venue"
},
  "geometry": {"coordinates":[-117.693619,33.598733],"type":"Point"}
}