{
  "type": "Feature",
  "properties": {
    "iso:country":"US",
    "sg:address":"2521 N Ventura Rd",
    "sg:city":"Port Hueneme",
    "sg:classifiers":[
        {
            "category":"Food & Beverages",
            "subcategory":"Liquor & Beverages",
            "type":"Retail Goods"
        }
    ],
    "sg:phone":"+1 805 984 7333",
    "sg:postcode":"93041",
    "sg:province":"CA",
    "sg:tags":[
        "wine"
    ],
    "wof:name":"Allan's Market Wine & Lotto",
    "wof:placetype":"venue"
},
  "geometry": {"coordinates":[-119.195004,34.177004],"type":"Point"}
}