{
  "type": "Feature",
  "properties": {
    "iso:country":"US",
    "sg:address":"13200 Kirkham Way",
    "sg:city":"Poway",
    "sg:classifiers":[
        {
            "category":"Wholesale",
            "subcategory":"Electrical",
            "type":"Manufacturing & Wholesale Goods"
        }
    ],
    "sg:phone":"+1 858 486 8386",
    "sg:postcode":"92064",
    "sg:province":"CA",
    "sg:tags":[
        "high",
        "fidelity",
        "stereophonic"
    ],
    "wof:name":"Harmonic Technologies",
    "wof:placetype":"venue"
},
  "geometry": {"coordinates":[-117.044668,32.935059],"type":"Point"}
}