{
  "type": "Feature",
  "properties": {
    "addr:full":"421 N Azusa Ave La Puente CA 91744",
    "addr:housenumber":"421",
    "addr:postcode":"91744",
    "addr:street":"N Azusa Ave",
    "iso:country":"US",
    "sg:address":"421 N Azusa Ave",
    "sg:city":"La Puente",
    "sg:classifiers":[
        {
            "category":"Personal",
            "subcategory":"Beauty Salon",
            "type":"Services"
        }
    ],
    "sg:phone":"+1 626 810 0200",
    "sg:postcode":"91744",
    "sg:province":"CA",
    "wof:name":"Helen's Beauty Salon",
    "wof:placetype":"venue"
},
  "geometry": {"coordinates":[-117.917531,34.025015],"type":"Point"}
}