{
  "type": "Feature",
  "properties": {
    "addr:full":"46695 Mission Blvd Fremont CA 94539",
    "addr:housenumber":"46695",
    "addr:postcode":"94539",
    "addr:street":"Mission Blvd",
    "iso:country":"US",
    "sg:address":"46695 Mission Blvd",
    "sg:city":"Fremont",
    "sg:classifiers":[
        {
            "category":"Personal",
            "subcategory":"Beauty Salon",
            "type":"Services"
        }
    ],
    "sg:phone":"+1 510 657 1371",
    "sg:postcode":"94539",
    "sg:province":"CA",
    "sg:tags":[
        "barber"
    ],
    "sg:website":"www.supercuts.com",
    "wof:name":"Supercuts",
    "wof:placetype":"venue"
},
  "geometry": {"coordinates":[-121.92800099999999,37.491199],"type":"Point"}
}