{
  "type": "Feature",
  "properties": {
    "iso:country":"US",
    "sg:address":"2644 Lake Tahoe Blvd",
    "sg:city":"South Lake Tahoe",
    "sg:classifiers":[
        {
            "category":"Travel",
            "subcategory":"Hotels & Motels",
            "type":"Entertainment"
        }
    ],
    "sg:phone":"+1 530 544 0770",
    "sg:postcode":"96150",
    "sg:province":"CA",
    "wof:name":"Sky Lake Lodge",
    "wof:placetype":"venue"
},
  "geometry": {"coordinates":[-119.98058399999999,38.929448],"type":"Point"}
}