{
  "type": "Feature",
  "properties": {
    "iso:country":"US",
    "sg:address":"6535 Fair Oaks Blvd",
    "sg:city":"Carmichael",
    "sg:classifiers":[
        {
            "category":"Manufacturing",
            "subcategory":"Petroleum Products",
            "type":"Manufacturing & Wholesale Goods"
        }
    ],
    "sg:phone":"+1 916 488 3666",
    "sg:postcode":"95608",
    "sg:province":"CA",
    "wof:name":"Lahaina Petroleum, Llc",
    "wof:placetype":"venue"
},
  "geometry": {"coordinates":[-121.32853299999999,38.619559],"type":"Point"}
}