{
  "type": "Feature",
  "properties": {
    "addr:full":"664 Pronto Dr San Jose CA 95123",
    "addr:housenumber":"664",
    "addr:postcode":"95123",
    "addr:street":"Pronto Dr",
    "iso:country":"US",
    "sg:address":"664 Pronto Dr",
    "sg:city":"San Jose",
    "sg:classifiers":[
        {
            "category":"Personal",
            "type":"Services"
        }
    ],
    "sg:phone":"+1 408 972 1545",
    "sg:postcode":"95123",
    "sg:province":"CA",
    "sg:tags":[
        "party",
        "planning",
        "event"
    ],
    "sg:website":"www.royaleventsinternational.com",
    "wof:name":"Royal Events International",
    "wof:placetype":"venue"
},
  "geometry": {"coordinates":[-121.850077,37.244501],"type":"Point"}
}