{
  "type": "Feature",
  "properties": {
    "addr:full":"4701 Patrick Henry Drive, Bldg. 9 Santa Clara CA 95054",
    "addr:housenumber":"4701",
    "addr:postcode":"95054",
    "addr:street":"Patrick Henry Drive Bldg.",
    "iso:country":"US",
    "sg:address":"4701 Patrick Henry Drive, Bldg. 9",
    "sg:city":"Santa Clara",
    "sg:classifiers":[
        {
            "category":"Education",
            "subcategory":"Music School",
            "type":"Public Place"
        }
    ],
    "sg:phone":"+1 408 343 0933",
    "sg:postcode":"95054",
    "sg:province":"CA",
    "sg:tags":[
        "instrument",
        "teacher",
        "musical"
    ],
    "sg:website":"www.longay.com/",
    "wof:name":"Longay Conservatory of Guitar",
    "wof:placetype":"venue"
},
  "geometry": {"coordinates":[-121.984683,37.398072],"type":"Point"}
}