{
  "type": "Feature",
  "properties": {
    "addr:full":"1106 S Main St Los Angeles CA 90015",
    "addr:housenumber":"1106",
    "addr:postcode":"90015",
    "addr:street":"S Main St",
    "iso:country":"US",
    "sg:address":"1106 S Main St",
    "sg:city":"Los Angeles",
    "sg:classifiers":[
        {
            "category":"Wholesale",
            "subcategory":"Apparel",
            "type":"Manufacturing & Wholesale Goods"
        }
    ],
    "sg:phone":"+1 213 748 8392",
    "sg:postcode":"90015",
    "sg:province":"CA",
    "sg:tags":[
        "clothing"
    ],
    "wof:name":"Young Bo Wholesale Co Inc",
    "wof:placetype":"venue"
},
  "geometry": {"coordinates":[-118.259226,34.037639],"type":"Point"}
}