{
  "type": "Feature",
  "properties": {
    "iso:country":"US",
    "sg:address":"200 7th Ave Ste 135 Oriental Medical Center",
    "sg:city":"Santa Cruz",
    "sg:classifiers":[
        {
            "category":"Health Services",
            "subcategory":"Clinic",
            "type":"Services"
        }
    ],
    "sg:phone":"+1 831 477 9355",
    "sg:postcode":"95062",
    "sg:province":"CA",
    "sg:tags":[
        "medical"
    ],
    "wof:name":"Maria Mitchell, LAC",
    "wof:placetype":"venue"
},
  "geometry": {"coordinates":[-121.99803900000001,36.964335],"type":"Point"}
}