{
  "type": "Feature",
  "properties": {
    "iso:country":"US",
    "sg:address":"9778 Katella Ave",
    "sg:city":"Anaheim",
    "sg:classifiers":[
        {
            "category":"Real Estate",
            "subcategory":"Real Estate Operator",
            "type":"Services"
        }
    ],
    "sg:phone":"+1 714 539 2200",
    "sg:postcode":"92804",
    "sg:province":"CA",
    "sg:tags":[
        "building",
        "property",
        "lessor",
        "nonresidential"
    ],
    "wof:name":"Katella Executive Suites",
    "wof:placetype":"venue"
},
  "geometry": {"coordinates":[-117.96114799999999,33.803028],"type":"Point"}
}