{
  "type": "Feature",
  "properties": {
    "addr:full":"1280 E J St Chula Vista CA 91910",
    "addr:housenumber":"1280",
    "addr:postcode":"91910",
    "addr:street":"E J St",
    "iso:country":"US",
    "sg:address":"1280 E J St",
    "sg:city":"Chula Vista",
    "sg:classifiers":[
        {
            "category":"Real Estate",
            "subcategory":"Real Estate Operator",
            "type":"Services"
        }
    ],
    "sg:phone":"+1 619 482 6840",
    "sg:postcode":"91910",
    "sg:province":"CA",
    "sg:tags":[
        "apartment"
    ],
    "wof:name":"Cordova Village",
    "wof:placetype":"venue"
},
  "geometry": {"coordinates":[-117.007532,32.630831],"type":"Point"}
}