{
  "type": "Feature",
  "properties": {
    "addr:full":"615 Solano Avenue Los Angeles CA 90012",
    "addr:housenumber":"615",
    "addr:postcode":"90012",
    "addr:street":"Solano Avenue",
    "iso:country":"US",
    "sg:address":"615 Solano Avenue",
    "sg:city":"Los Angeles",
    "sg:classifiers":[
        {
            "category":"Education",
            "subcategory":"School",
            "type":"Public Place"
        }
    ],
    "sg:phone":"+1 323 223 4291",
    "sg:postcode":"90012",
    "sg:province":"CA",
    "sg:tags":[
        "high",
        "middle",
        "elementary"
    ],
    "wof:name":"Solano Avenue Elementary School",
    "wof:placetype":"venue"
},
  "geometry": {"coordinates":[-118.232904,34.076271],"type":"Point"}
}