{
  "type": "Feature",
  "properties": {
    "iso:country":"US",
    "sg:address":"1931 N Gaffey St",
    "sg:city":"San Pedro",
    "sg:classifiers":[
        {
            "category":"Personal",
            "subcategory":"Beauty Salon",
            "type":"Services"
        }
    ],
    "sg:phone":"+1 310 831 3221",
    "sg:postcode":"90731",
    "sg:province":"CA",
    "wof:name":"Hairline Hair Design",
    "wof:placetype":"venue"
},
  "geometry": {"coordinates":[-118.292903,33.759935],"type":"Point"}
}