{
  "type": "Feature",
  "properties": {
    "addr:full":"14415 Imperial Hwy Whittier CA 90604",
    "addr:housenumber":"14415",
    "addr:postcode":"90604",
    "addr:street":"Imperial Hwy",
    "iso:country":"US",
    "sg:address":"14415 Imperial Hwy",
    "sg:city":"Whittier",
    "sg:classifiers":[
        {
            "category":"Organizations",
            "subcategory":"Religious Organization",
            "type":"Services"
        }
    ],
    "sg:phone":"+1 562 903 0111",
    "sg:postcode":"90604",
    "sg:province":"CA",
    "sg:tags":[
        "church"
    ],
    "wof:name":"Young Eun Korean Presbyterian",
    "wof:placetype":"venue"
},
  "geometry": {"coordinates":[-118.022954,33.917075],"type":"Point"}
}