{
  "type": "Feature",
  "properties": {
    "addr:full":"3 Circle Star Way San Carlos CA 94070",
    "addr:housenumber":"3",
    "addr:postcode":"94070",
    "addr:street":"Circle Star Way",
    "iso:country":"US",
    "sg:address":"3 Circle Star Way",
    "sg:city":"San Carlos",
    "sg:classifiers":[
        {
            "category":"Travel",
            "subcategory":"Hotels & Motels",
            "type":"Entertainment"
        }
    ],
    "sg:phone":"+1 650 368 2600",
    "sg:postcode":"94070",
    "sg:province":"CA",
    "sg:tags":[
        "operation"
    ],
    "wof:name":"Homestead Studio Suites Hotel",
    "wof:placetype":"venue"
},
  "geometry": {"coordinates":[-122.240312,37.498017],"type":"Point"}
}