{
  "type": "Feature",
  "properties": {
    "iso:country":"US",
    "sg:address":"36 Harold Ave",
    "sg:city":"San Jose",
    "sg:classifiers":[
        {
            "category":"Government",
            "subcategory":"Office",
            "type":"Public Place"
        }
    ],
    "sg:phone":"+1 408 879 9053",
    "sg:postcode":"95117",
    "sg:province":"CA",
    "sg:tags":[
        "management"
    ],
    "wof:name":"Leone Motors Import & Export",
    "wof:placetype":"venue"
},
  "geometry": {"coordinates":[-121.96217,37.32698],"type":"Point"}
}