{
  "type": "Feature",
  "properties": {
    "addr:full":"400 W 30th St Los Angeles CA 90007",
    "addr:housenumber":"400",
    "addr:postcode":"90007",
    "addr:street":"W 30Th St",
    "iso:country":"US",
    "sg:address":"400 W 30th St",
    "sg:city":"Los Angeles",
    "sg:classifiers":[
        {
            "category":"Wholesale",
            "subcategory":"Apparel",
            "type":"Manufacturing & Wholesale Goods"
        }
    ],
    "sg:phone":"+1 213 745 4312",
    "sg:postcode":"90007",
    "sg:province":"CA",
    "sg:tags":[
        "paper",
        "product",
        "converted",
        "mfg",
        "piece"
    ],
    "wof:name":"Total Label",
    "wof:placetype":"venue"
},
  "geometry": {"coordinates":[-118.275963,34.024139],"type":"Point"}
}