{
  "type": "Feature",
  "properties": {
    "addr:full":"4048 Via Rio Ave Oceanside CA 92057",
    "addr:housenumber":"4048",
    "addr:postcode":"92057",
    "addr:street":"Via Rio Ave",
    "iso:country":"US",
    "sg:address":"4048 Via Rio Ave",
    "sg:city":"Oceanside",
    "sg:classifiers":[
        {
            "category":"Building & Trades",
            "subcategory":"Construction",
            "type":"Services"
        }
    ],
    "sg:phone":"+1 760 721 6621",
    "sg:postcode":"92057",
    "sg:province":"CA",
    "sg:tags":[
        "contractor"
    ],
    "wof:name":"N P R Construction",
    "wof:placetype":"venue"
},
  "geometry": {"coordinates":[-117.31999999999999,33.2384],"type":"Point"}
}