{
  "type": "Feature",
  "properties": {
    "iso:country":"US",
    "sg:address":"300 E Walnut St",
    "sg:city":"Pasadena",
    "sg:classifiers":[
        {
            "category":"Government",
            "subcategory":"Court House",
            "type":"Public Place"
        }
    ],
    "sg:phone":"+1 626 356 5515",
    "sg:postcode":"91101",
    "sg:province":"CA",
    "sg:tags":[
        "county"
    ],
    "wof:name":"Superior Court-Probate Atty",
    "wof:placetype":"venue"
},
  "geometry": {"coordinates":[-118.143081,34.14946],"type":"Point"}
}