{
  "type": "Feature",
  "properties": {
    "iso:country":"US",
    "sg:address":"1370 2nd St",
    "sg:city":"Napa",
    "sg:classifiers":[
        {
            "category":"Professional",
            "subcategory":"Business Services",
            "type":"Services"
        }
    ],
    "sg:phone":"+1 707 252 6353",
    "sg:postcode":"94559",
    "sg:province":"CA",
    "sg:tags":[
        "used",
        "merchandise"
    ],
    "wof:name":"Antiques On Second",
    "wof:placetype":"venue"
},
  "geometry": {"coordinates":[-122.287509,38.297281],"type":"Point"}
}