{
  "type": "Feature",
  "properties": {
    "addr:full":"11417 Old River Rd Bakersfield CA 93311",
    "addr:housenumber":"11417",
    "addr:postcode":"93311",
    "addr:street":"Old River Rd",
    "iso:country":"US",
    "sg:address":"11417 Old River Rd",
    "sg:city":"Bakersfield",
    "sg:classifiers":[
        {
            "category":"Professional",
            "subcategory":"Research",
            "type":"Services"
        }
    ],
    "sg:phone":"+1 661 663 9916",
    "sg:postcode":"93311",
    "sg:province":"CA",
    "sg:tags":[
        "development",
        "laboratory"
    ],
    "wof:name":"Hypersonic",
    "wof:placetype":"venue"
},
  "geometry": {"coordinates":[-119.10987900000001,35.258322],"type":"Point"}
}