{
  "type": "Feature",
  "properties": {
    "iso:country":"US",
    "sg:address":"1322 Wellington St",
    "sg:city":"Oakland",
    "sg:classifiers":[
        {
            "category":"Communications",
            "type":"Services"
        }
    ],
    "sg:phone":"+1 510 530 4192",
    "sg:postcode":"94602",
    "sg:province":"CA",
    "sg:tags":[
        "communication"
    ],
    "wof:name":"Cthree Communications Inc",
    "wof:placetype":"venue"
},
  "geometry": {"coordinates":[-122.22108799999999,37.807494],"type":"Point"}
}