{
  "type": "Feature",
  "properties": {
    "iso:country":"US",
    "sg:address":"3737 Main St",
    "sg:city":"Kelseyville",
    "sg:classifiers":[
        {
            "category":"Autos & Motor Vehicles",
            "subcategory":"Automobile Sales",
            "type":"Retail Goods"
        }
    ],
    "sg:phone":"+1 707 279 2526",
    "sg:postcode":"95451",
    "sg:province":"CA",
    "sg:tags":[
        "car",
        "dealer"
    ],
    "wof:name":"Car Finders",
    "wof:placetype":"venue"
},
  "geometry": {"coordinates":[-122.841775,38.978291],"type":"Point"}
}