{
  "type": "Feature",
  "properties": {
    "addr:full":"1142 Mc Kendrie St San Jose CA 95126",
    "addr:housenumber":"1142",
    "addr:postcode":"95126",
    "addr:street":"Mc Kendrie St",
    "iso:country":"US",
    "sg:address":"1142 Mc Kendrie St",
    "sg:city":"San Jose",
    "sg:classifiers":[
        {
            "category":"Health Services",
            "subcategory":"Doctor",
            "type":"Services"
        }
    ],
    "sg:phone":"+1 408 244 6186",
    "sg:postcode":"95126",
    "sg:province":"CA",
    "sg:tags":[
        "physician",
        "surgeon"
    ],
    "wof:name":"Jennifer Lendl MD",
    "wof:placetype":"venue"
},
  "geometry": {"coordinates":[-121.92501799999999,37.341003],"type":"Point"}
}