{
  "type": "Feature",
  "properties": {
    "iso:country":"US",
    "sg:address":"2244 Sunrise Blvd",
    "sg:city":"Rancho Cordova",
    "sg:classifiers":[
        {
            "category":"Arena",
            "subcategory":"Sports Club",
            "type":"Entertainment"
        }
    ],
    "sg:phone":"+1 916 631 8887",
    "sg:postcode":"95670",
    "sg:province":"CA",
    "sg:tags":[
        "martial art"
    ],
    "wof:name":"Korean Ways",
    "wof:placetype":"venue"
},
  "geometry": {"coordinates":[-121.267177,38.621787],"type":"Point"}
}