{
  "type": "Feature",
  "properties": {
    "addr:full":"6725 8th St Buena Park CA 90620",
    "addr:housenumber":"6725",
    "addr:postcode":"90620",
    "addr:street":"8Th St",
    "iso:country":"US",
    "sg:address":"6725 8th St",
    "sg:city":"Buena Park",
    "sg:classifiers":[
        {
            "category":"Home & Garden",
            "subcategory":"Carpets & Floor Coverings",
            "type":"Retail Goods"
        }
    ],
    "sg:phone":"+1 714 522 4991",
    "sg:postcode":"90620",
    "sg:province":"CA",
    "sg:tags":[
        "mattress"
    ],
    "wof:name":"Sleep Comp West",
    "wof:placetype":"venue"
},
  "geometry": {"coordinates":[-118.014999,33.867298],"type":"Point"}
}