{
  "type": "Feature",
  "properties": {
    "iso:country":"US",
    "sg:address":"2000 Main St. Huntington Beach Civic Center",
    "sg:city":"Huntington Beach",
    "sg:classifiers":[
        {
            "category":"Deli",
            "type":"Food & Drink"
        }
    ],
    "sg:phone":"+1 714 536 5050",
    "sg:postcode":"92648",
    "sg:province":"CA",
    "sg:website":"www.citycafe-online.com",
    "wof:name":"City Cafe",
    "wof:placetype":"venue"
},
  "geometry": {"coordinates":[-118.001554,33.678591],"type":"Point"}
}