{
  "type": "Feature",
  "properties": {
    "iso:country":"US",
    "sg:address":"1025 Santa Barbara St",
    "sg:city":"Santa Barbara",
    "sg:classifiers":[
        {
            "category":"Home & Garden",
            "subcategory":"Furniture",
            "type":"Retail Goods"
        }
    ],
    "sg:phone":"+1 805 965 0011",
    "sg:postcode":"93101",
    "sg:province":"CA",
    "wof:name":"Hayward's-Santa Barbara",
    "wof:placetype":"venue"
},
  "geometry": {"coordinates":[-119.700677,34.424264],"type":"Point"}
}