{
  "type": "Feature",
  "properties": {
    "addr:full":"11231 Gold Express Dr Gold River CA 95670",
    "addr:housenumber":"11231",
    "addr:postcode":"95670",
    "addr:street":"Gold Express Dr",
    "iso:country":"US",
    "sg:address":"11231 Gold Express Dr",
    "sg:city":"Gold River",
    "sg:classifiers":[
        {
            "category":"Banks & Credit Unions",
            "subcategory":"Bank",
            "type":"Services"
        }
    ],
    "sg:phone":"+1 916 852 2930",
    "sg:postcode":"95670",
    "sg:province":"CA",
    "sg:tags":[
        "escrow"
    ],
    "wof:name":"North American Title Co",
    "wof:placetype":"venue"
},
  "geometry": {"coordinates":[-121.263943,38.6236],"type":"Point"}
}