{
  "type": "Feature",
  "properties": {
    "addr:full":"296 Valley St Daly City CA 94014",
    "addr:housenumber":"296",
    "addr:postcode":"94014",
    "addr:street":"Valley St",
    "iso:country":"US",
    "sg:address":"296 Valley St",
    "sg:city":"Daly City",
    "sg:classifiers":[
        {
            "category":"Freight",
            "type":"Transportation"
        }
    ],
    "sg:phone":"+1 510 872 3500",
    "sg:postcode":"94014",
    "sg:province":"CA",
    "sg:tags":[
        "operator",
        "local",
        "trucking"
    ],
    "wof:name":"Marchiorlatti Trucking Inc",
    "wof:placetype":"venue"
},
  "geometry": {"coordinates":[-122.463082,37.687811],"type":"Point"}
}