{
  "type": "Feature",
  "properties": {
    "addr:full":"2701 Eureka Way Redding CA 96001",
    "addr:housenumber":"2701",
    "addr:postcode":"96001",
    "addr:street":"Eureka Way",
    "iso:country":"US",
    "sg:address":"2701 Eureka Way",
    "sg:city":"Redding",
    "sg:classifiers":[
        {
            "category":"Social Services",
            "subcategory":"Job Training",
            "type":"Services"
        }
    ],
    "sg:phone":"+1 530 243 7544",
    "sg:postcode":"96001",
    "sg:province":"CA",
    "sg:tags":[
        "rehabilitation"
    ],
    "wof:name":"Tri-County Vocational Svc",
    "wof:placetype":"venue"
},
  "geometry": {"coordinates":[-122.409814,40.585951],"type":"Point"}
}