{
  "type": "Feature",
  "properties": {
    "iso:country":"US",
    "sg:address":"3855 Cll del Establo",
    "sg:city":"San Clemente",
    "sg:classifiers":[
        {
            "category":"Wholesale",
            "subcategory":"Machinery & Supplies",
            "type":"Manufacturing & Wholesale Goods"
        }
    ],
    "sg:phone":"+1 949 361 5867",
    "sg:postcode":"92672",
    "sg:province":"CA",
    "sg:tags":[
        "equipment",
        "industrial"
    ],
    "wof:name":"Cncsave Co",
    "wof:placetype":"venue"
},
  "geometry": {"coordinates":[-117.59760300000001,33.397379],"type":"Point"}
}