{
  "type": "Feature",
  "properties": {
    "addr:full":"511 1st St Encinitas CA 92024",
    "addr:housenumber":"511",
    "addr:postcode":"92024",
    "addr:street":"1St St",
    "iso:country":"US",
    "sg:address":"511 1st St",
    "sg:city":"Encinitas",
    "sg:classifiers":[
        {
            "category":"Building & Trades",
            "subcategory":"Landscaping Services",
            "type":"Services"
        }
    ],
    "sg:phone":"+1 760 436 0359",
    "sg:postcode":"92024",
    "sg:province":"CA",
    "sg:tags":[
        "landscape",
        "contractor"
    ],
    "wof:name":"Kimo's Landscaping",
    "wof:placetype":"venue"
},
  "geometry": {"coordinates":[-117.29360699999999,33.044817],"type":"Point"}
}