{
  "type": "Feature",
  "properties": {
    "addr:full":"32881 Yucaipa Blvd Yucaipa CA 92399",
    "addr:housenumber":"32881",
    "addr:postcode":"92399",
    "addr:street":"Yucaipa Blvd",
    "iso:country":"US",
    "sg:address":"32881 Yucaipa Blvd",
    "sg:city":"Yucaipa",
    "sg:classifiers":[
        {
            "category":"Building & Trades",
            "subcategory":"Cleaning & Sanitation",
            "type":"Services"
        }
    ],
    "sg:phone":"+1 909 797 8988",
    "sg:postcode":"92399",
    "sg:province":"CA",
    "sg:tags":[
        "maintenance"
    ],
    "wof:name":"Northeast Construction",
    "wof:placetype":"venue"
},
  "geometry": {"coordinates":[-117.08716699999999,34.033827],"type":"Point"}
}