{
  "type": "Feature",
  "properties": {
    "addr:full":"751 Arbutus Ave Chico CA 95926",
    "addr:housenumber":"751",
    "addr:postcode":"95926",
    "addr:street":"Arbutus Ave",
    "iso:country":"US",
    "sg:address":"751 Arbutus Ave",
    "sg:city":"Chico",
    "sg:classifiers":[
        {
            "category":"Shopping",
            "type":"Retail Goods"
        }
    ],
    "sg:phone":"+1 530 891 6226",
    "sg:postcode":"95926",
    "sg:province":"CA",
    "sg:tags":[
        "spa",
        "hot",
        "tub"
    ],
    "wof:name":"Sensible Spas",
    "wof:placetype":"venue"
},
  "geometry": {"coordinates":[-121.83179199999999,39.737037],"type":"Point"}
}