{
  "type": "Feature",
  "properties": {
    "addr:full":"5416 Santa Monica Blvd Los Angeles CA 90029",
    "addr:housenumber":"5416",
    "addr:postcode":"90029",
    "addr:street":"Santa Monica Blvd",
    "iso:country":"US",
    "sg:address":"5416 Santa Monica Blvd",
    "sg:city":"Los Angeles",
    "sg:classifiers":[
        {
            "category":"Retail",
            "subcategory":"Auto Repair",
            "type":"Services"
        }
    ],
    "sg:phone":"+1 323 464 1004",
    "sg:postcode":"90029",
    "sg:province":"CA",
    "sg:tags":[
        "body",
        "automobile",
        "painting"
    ],
    "wof:name":"New Earl Scheib Paint & Body",
    "wof:placetype":"venue"
},
  "geometry": {"coordinates":[-118.307644,34.090705],"type":"Point"}
}