{
  "type": "Feature",
  "properties": {
    "iso:country":"US",
    "sg:address":"2947 Lincoln Blvd",
    "sg:city":"Santa Monica",
    "sg:classifiers":[
        {
            "category":"Bars & Pubs",
            "type":"Food & Drink"
        }
    ],
    "sg:phone":"+1 310 399 9696",
    "sg:postcode":"90405",
    "sg:province":"CA",
    "sg:tags":[
        "lounge",
        "cocktail"
    ],
    "wof:name":"Cock N Bull Pub",
    "wof:placetype":"venue"
},
  "geometry": {"coordinates":[-118.472707,34.004347],"type":"Point"}
}