{
  "type": "Feature",
  "properties": {
    "addr:full":"2505 N Glenoaks Blvd Burbank CA 91504",
    "addr:housenumber":"2505",
    "addr:postcode":"91504",
    "addr:street":"N Glenoaks Blvd",
    "iso:country":"US",
    "sg:address":"2505 N Glenoaks Blvd",
    "sg:city":"Burbank",
    "sg:classifiers":[
        {
            "category":"Professional",
            "type":"Services"
        }
    ],
    "sg:phone":"+1 818 848 8877",
    "sg:postcode":"91504",
    "sg:province":"CA",
    "wof:name":"All Nations Lending Inc",
    "wof:placetype":"venue"
},
  "geometry": {"coordinates":[-118.332375,34.201773],"type":"Point"}
}