{
  "type": "Feature",
  "properties": {
    "addr:full":"525 Middlefield Rd Menlo Park CA 94025",
    "addr:housenumber":"525",
    "addr:postcode":"94025",
    "addr:street":"Middlefield Rd",
    "iso:country":"US",
    "sg:address":"525 Middlefield Rd",
    "sg:city":"Menlo Park",
    "sg:classifiers":[
        {
            "category":"Professional",
            "subcategory":"Lawyer & Legal Services",
            "type":"Services"
        }
    ],
    "sg:phone":"+1 650 322 8328",
    "sg:postcode":"94025",
    "sg:province":"CA",
    "sg:tags":[
        "attorney"
    ],
    "wof:name":"Finnan Fleischut & Assoc",
    "wof:placetype":"venue"
},
  "geometry": {"coordinates":[-122.16738100000001,37.456241],"type":"Point"}
}