{
  "type": "Feature",
  "properties": {
    "addr:full":"615 S Grand Ave Los Angeles CA 90017",
    "addr:housenumber":"615",
    "addr:postcode":"90017",
    "addr:street":"S Grand Ave",
    "iso:country":"US",
    "sg:address":"615 S Grand Ave",
    "sg:city":"Los Angeles",
    "sg:classifiers":[
        {
            "category":"Professional",
            "subcategory":"Management & Consulting",
            "type":"Services"
        }
    ],
    "sg:phone":"+1 213 996 1998",
    "sg:postcode":"90017",
    "sg:province":"CA",
    "sg:tags":[
        "telephone",
        "business"
    ],
    "wof:name":"Vertex Group Inc",
    "wof:placetype":"venue"
},
  "geometry": {"coordinates":[-118.255779,34.048352],"type":"Point"}
}