{
  "type": "Feature",
  "properties": {
    "iso:country":"US",
    "sg:address":"1777 Vine St",
    "sg:city":"Los Angeles",
    "sg:classifiers":[
        {
            "category":"Education",
            "subcategory":"Vocational School",
            "type":"Public Place"
        }
    ],
    "sg:phone":"+1 323 462 3211",
    "sg:postcode":"90028",
    "sg:province":"CA",
    "sg:website":"www.academypacific.com",
    "wof:name":"Academy Pacific Travel College",
    "wof:placetype":"venue"
},
  "geometry": {"coordinates":[-118.326761,34.102099],"type":"Point"}
}