{
  "type": "Feature",
  "properties": {
    "addr:full":"737 Russell Blvd Davis CA 95616",
    "addr:housenumber":"737",
    "addr:postcode":"95616",
    "addr:street":"Russell Blvd",
    "iso:country":"US",
    "sg:address":"737 Russell Blvd",
    "sg:city":"Davis",
    "sg:classifiers":[
        {
            "category":"Professional",
            "subcategory":"Management & Consulting",
            "type":"Services"
        }
    ],
    "sg:phone":"+1 530 750 7084",
    "sg:postcode":"95616",
    "sg:province":"CA",
    "sg:tags":[
        "consultant",
        "educational"
    ],
    "wof:name":"Sylvan Learning Ctr",
    "wof:placetype":"venue"
},
  "geometry": {"coordinates":[-121.761363,38.54642],"type":"Point"}
}