{
  "type": "Feature",
  "properties": {
    "iso:country":"US",
    "sg:address":"1900 Truxtun Ave Ste C",
    "sg:city":"Bakersfield",
    "sg:classifiers":[
        {
            "category":"Community Center",
            "type":"Public Place"
        }
    ],
    "sg:phone":"+1 866 873 0879",
    "sg:postcode":"93301",
    "sg:province":"CA",
    "sg:tags":[
        "medical"
    ],
    "sg:website":"http://www.rapidstdtesting.com",
    "wof:name":"Rapid STD/HIV Testing",
    "wof:placetype":"venue"
},
  "geometry": {"coordinates":[-119.02349100000001,35.37339],"type":"Point"}
}