{
  "type": "Feature",
  "properties": {
    "addr:full":"24160 Ave Rancheros Diamond Bar CA 91765",
    "addr:housenumber":"24160",
    "addr:postcode":"91765",
    "addr:street":"Ave Rancheros",
    "iso:country":"US",
    "sg:address":"24160 Ave Rancheros",
    "sg:city":"Diamond Bar",
    "sg:classifiers":[
        {
            "category":"Utilities",
            "subcategory":"Telephone",
            "type":"Services"
        },
        {
            "category":"Professional",
            "subcategory":"Computer Services",
            "type":"Services"
        }
    ],
    "sg:phone":"+1 909 861 7747",
    "sg:postcode":"91765",
    "sg:province":"CA",
    "sg:tags":[
        "communications",
        "internet"
    ],
    "sg:website":"www.wneta.com",
    "wof:name":"Wally Net Assoc",
    "wof:placetype":"venue"
},
  "geometry": {"coordinates":[-117.79351,34.037327],"type":"Point"}
}