{
  "type": "Feature",
  "properties": {
    "iso:country":"US",
    "sg:address":"55 N Union St Ste D",
    "sg:city":"Susanville",
    "sg:classifiers":[
        {
            "category":"Banks & Credit Unions",
            "subcategory":"Investment Brokerage",
            "type":"Services"
        },
        {
            "category":"Insurance",
            "subcategory":"Hazard Insurance",
            "type":"Services"
        },
        {
            "category":"Banks & Credit Unions",
            "subcategory":"Financial Services",
            "type":"Services"
        }
    ],
    "sg:phone":"+1 530 257 3461",
    "sg:postcode":"96130",
    "sg:province":"CA",
    "sg:tags":[
        "security",
        "management"
    ],
    "wof:name":"Solus Insurance-Financial Svc",
    "wof:placetype":"venue"
},
  "geometry": {"coordinates":[-120.659024,40.418548],"type":"Point"}
}