{
  "type": "Feature",
  "properties": {
    "iso:country":"US",
    "sg:address":"1201 University Ave",
    "sg:city":"Riverside",
    "sg:classifiers":[
        {
            "category":"Professional",
            "subcategory":"Computer Services",
            "type":"Services"
        }
    ],
    "sg:phone":"+1 951 328 0001",
    "sg:postcode":"92507",
    "sg:province":"CA",
    "sg:tags":[
        "graphics"
    ],
    "sg:website":"www.digi-empire.com",
    "wof:name":"Digital Empire",
    "wof:placetype":"venue"
},
  "geometry": {"coordinates":[-117.338634,33.975768],"type":"Point"}
}