{
  "type": "Feature",
  "properties": {
    "addr:full":"11899 Edgewood Rd Auburn CA 95603",
    "addr:housenumber":"11899",
    "addr:postcode":"ca 95603",
    "addr:street":"Edgewood Rd",
    "iso:country":"US",
    "sg:address":"11899 Edgewood Rd",
    "sg:city":"Auburn",
    "sg:classifiers":[
        {
            "category":"Freight",
            "type":"Transportation"
        }
    ],
    "sg:phone":"+1 530 889 8070",
    "sg:postcode":"95603",
    "sg:province":"CA",
    "sg:tags":[
        "self",
        "storage",
        "facility"
    ],
    "wof:name":"98 Folsom Partners LLC",
    "wof:placetype":"venue"
},
  "geometry": {"coordinates":[-121.082111,38.920448],"type":"Point"}
}