{
  "type": "Feature",
  "properties": {
    "addr:full":"13523 Ventura Blvd Sherman Oaks CA 91423",
    "addr:housenumber":"13523",
    "addr:postcode":"91423",
    "addr:street":"Ventura Blvd",
    "iso:country":"US",
    "sg:address":"13523 Ventura Blvd",
    "sg:city":"Sherman Oaks",
    "sg:classifiers":[
        {
            "category":"Insurance",
            "subcategory":"Insurance Agent",
            "type":"Services"
        }
    ],
    "sg:phone":"+1 818 995 1494",
    "sg:postcode":"91423",
    "sg:province":"CA",
    "wof:name":"Durham-Williams Kat Ins",
    "wof:placetype":"venue"
},
  "geometry": {"coordinates":[-118.427335,34.147431],"type":"Point"}
}