{
  "type": "Feature",
  "properties": {
    "addr:full":"1547 E Washington Blvd Los Angeles CA 90021",
    "addr:housenumber":"1547",
    "addr:postcode":"90021",
    "addr:street":"E Washington Blvd",
    "iso:country":"US",
    "sg:address":"1547 E Washington Blvd",
    "sg:city":"Los Angeles",
    "sg:classifiers":[
        {
            "category":"Wholesale",
            "subcategory":"Apparel",
            "type":"Manufacturing & Wholesale Goods"
        }
    ],
    "sg:phone":"+1 213 747 1785",
    "sg:postcode":"90021",
    "sg:province":"CA",
    "sg:tags":[
        "piece"
    ],
    "wof:name":"J & C Dyer",
    "wof:placetype":"venue"
},
  "geometry": {"coordinates":[-118.244238,34.020993],"type":"Point"}
}