{
  "type": "Feature",
  "properties": {
    "iso:country":"US",
    "sg:address":"4418 Alta Mesa Dr",
    "sg:city":"Redding",
    "sg:classifiers":[
        {
            "category":"Professional",
            "subcategory":"Engineering",
            "type":"Services"
        }
    ],
    "sg:phone":"+1 530 221 6777",
    "sg:postcode":"96002",
    "sg:province":"CA",
    "wof:name":"R A Martin Constructors Inc",
    "wof:placetype":"venue"
},
  "geometry": {"coordinates":[-122.33031,40.543916],"type":"Point"}
}