{
  "type": "Feature",
  "properties": {
    "iso:country":"US",
    "sg:address":"2279 W 26th Pl",
    "sg:city":"Los Angeles",
    "sg:classifiers":[
        {
            "category":"Health Services",
            "subcategory":"Clinic",
            "type":"Services"
        }
    ],
    "sg:phone":"+1 323 373 0230",
    "sg:postcode":"90018",
    "sg:province":"CA",
    "sg:tags":[
        "wellness",
        "program"
    ],
    "wof:name":"House Of Wellness Inc",
    "wof:placetype":"venue"
},
  "geometry": {"coordinates":[-118.31600899999999,34.03182],"type":"Point"}
}