{
  "type": "Feature",
  "properties": {
    "iso:country":"US",
    "sg:address":"8810 Cal Center Dr",
    "sg:city":"Sacramento",
    "sg:classifiers":[
        {
            "category":"Insurance",
            "subcategory":"Insurance Agent",
            "type":"Services"
        }
    ],
    "sg:phone":"+1 916 481 2222",
    "sg:postcode":"95826",
    "sg:province":"CA",
    "wof:name":"Equitable Life Assurance",
    "wof:placetype":"venue"
},
  "geometry": {"coordinates":[-121.375544,38.5563],"type":"Point"}
}