{
  "type": "Feature",
  "properties": {
    "addr:full":"1305 Simpson Way Escondido CA 92029",
    "addr:housenumber":"1305",
    "addr:postcode":"92029",
    "addr:street":"Simpson Way",
    "iso:country":"US",
    "sg:address":"1305 Simpson Way",
    "sg:city":"Escondido",
    "sg:classifiers":[
        {
            "category":"Restaurant",
            "type":"Food & Drink"
        }
    ],
    "sg:phone":"+1 760 746 5748",
    "sg:postcode":"92029",
    "sg:province":"CA",
    "sg:tags":[
        "delicatessen"
    ],
    "wof:name":"Deli Depo",
    "wof:placetype":"venue"
},
  "geometry": {"coordinates":[-117.10208299999999,33.119553],"type":"Point"}
}