{
  "type": "Feature",
  "properties": {
    "iso:country":"US",
    "sg:address":"1870 S Central St",
    "sg:city":"Visalia",
    "sg:classifiers":[
        {
            "category":"Professional",
            "subcategory":"Lawyer & Legal Services",
            "type":"Services"
        }
    ],
    "sg:phone":"+1 559 627 2044",
    "sg:postcode":"93277",
    "sg:province":"CA",
    "sg:tags":[
        "attorney"
    ],
    "wof:name":"Stanley M Michner",
    "wof:placetype":"venue"
},
  "geometry": {"coordinates":[-119.31198000000001,36.313611],"type":"Point"}
}