{
  "type": "Feature",
  "properties": {
    "addr:full":"1246 Great Mall Dr Milpitas CA 95035",
    "addr:housenumber":"1246",
    "addr:postcode":"95035",
    "addr:street":"Great Mall Dr",
    "iso:country":"US",
    "sg:address":"1246 Great Mall Dr",
    "sg:city":"Milpitas",
    "sg:classifiers":[
        {
            "category":"Restaurant",
            "type":"Food & Drink"
        }
    ],
    "sg:menulink":"http://www.allmenus.com/ca/san-jose/52950-outback-steakhouse/menu/",
    "sg:phone":"+1 408 263 5400",
    "sg:postcode":"95035",
    "sg:province":"CA",
    "sg:tags":[
        "american",
        "steakhouse"
    ],
    "wof:name":"Outback Steakhouse",
    "wof:placetype":"venue"
},
  "geometry": {"coordinates":[-121.897372,37.412829],"type":"Point"}
}