{
  "type": "Feature",
  "properties": {
    "addr:full":"26 H St San Rafael CA 94901",
    "addr:housenumber":"26",
    "addr:postcode":"94901",
    "addr:street":"H St",
    "iso:country":"US",
    "sg:address":"26 H St",
    "sg:city":"San Rafael",
    "sg:classifiers":[
        {
            "category":"Personal",
            "type":"Services"
        }
    ],
    "sg:phone":"+1 415 485 1817",
    "sg:postcode":"94901",
    "sg:province":"CA",
    "sg:tags":[
        "electrolysis"
    ],
    "wof:name":"KEAN & Yarish Registered Elec",
    "wof:placetype":"venue"
},
  "geometry": {"coordinates":[-122.538415,37.974924],"type":"Point"}
}