{
  "type": "Feature",
  "properties": {
    "addr:full":"1075 Vine St Healdsburg CA 95448",
    "addr:housenumber":"1075",
    "addr:postcode":"95448",
    "addr:street":"Vine St",
    "iso:country":"US",
    "sg:address":"1075 Vine St",
    "sg:city":"Healdsburg",
    "sg:classifiers":[
        {
            "category":"Coffee & Tea",
            "type":"Food & Drink"
        }
    ],
    "sg:menulink":"http://www.allmenus.com/ca/healdsburg/119484-starbucks-coffee/menu/",
    "sg:phone":"+1 707 431 0509",
    "sg:postcode":"95448",
    "sg:province":"CA",
    "sg:tags":[
        "american"
    ],
    "wof:name":"Starbucks Coffee",
    "wof:placetype":"venue"
},
  "geometry": {"coordinates":[-122.87189600000001,38.609282],"type":"Point"}
}