{
  "type": "Feature",
  "properties": {
    "addr:full":"167 Blossom Way Hayward CA 94541",
    "addr:housenumber":"167",
    "addr:postcode":"94541",
    "addr:street":"Blossom Way",
    "iso:country":"US",
    "sg:address":"167 Blossom Way",
    "sg:city":"Hayward",
    "sg:classifiers":[
        {
            "category":"Building & Trades",
            "subcategory":"Construction",
            "type":"Services"
        }
    ],
    "sg:phone":"+1 510 697 0266",
    "sg:postcode":"94541",
    "sg:province":"CA",
    "sg:tags":[
        "paving",
        "contractor"
    ],
    "wof:name":"A & E Asphalt Maintenance",
    "wof:placetype":"venue"
},
  "geometry": {"coordinates":[-122.109268,37.676491],"type":"Point"}
}