{
  "type": "Feature",
  "properties": {
    "iso:country":"US",
    "sg:address":"5199 E Pacific Coast Hwy Ste 204",
    "sg:city":"Long Beach",
    "sg:classifiers":[
        {
            "category":"Government",
            "subcategory":"City Hall",
            "type":"Public Place"
        },
        {
            "category":"Professional",
            "type":"Services"
        }
    ],
    "sg:phone":"+1 562 597 5029",
    "sg:postcode":"90804",
    "sg:province":"CA",
    "sg:website":"www.baljagat.org",
    "wof:name":"Bal Jagat - Children's World, Inc.",
    "wof:placetype":"venue"
},
  "geometry": {"coordinates":[-118.13261799999999,33.782751],"type":"Point"}
}