{
  "type": "Feature",
  "properties": {
    "iso:country":"US",
    "sg:address":"2700 S Main St",
    "sg:city":"Santa Ana",
    "sg:classifiers":[
        {
            "category":"Building & Trades",
            "subcategory":"Cleaning & Sanitation",
            "type":"Services"
        }
    ],
    "sg:phone":"+1 714 966 5325",
    "sg:postcode":"92707",
    "sg:province":"CA",
    "sg:tags":[
        "janitor"
    ],
    "sg:website":"www.cimservices.com",
    "wof:name":"Corporate Image Maintenance",
    "wof:placetype":"venue"
},
  "geometry": {"coordinates":[-117.86801,33.711249],"type":"Point"}
}