{
  "type": "Feature",
  "properties": {
    "addr:full":"1151 W 109th Street Los Angeles CA 90044",
    "addr:housenumber":"1151",
    "addr:postcode":"90044",
    "addr:street":"W 109Th Street",
    "iso:country":"US",
    "sg:address":"1151 W 109th Street",
    "sg:city":"Los Angeles",
    "sg:classifiers":[
        {
            "category":"Education",
            "subcategory":"School",
            "type":"Public Place"
        }
    ],
    "sg:phone":"+1 323 756 1371",
    "sg:postcode":"90044",
    "sg:province":"CA",
    "sg:tags":[
        "high",
        "middle",
        "elementary"
    ],
    "sg:website":"www.lausd.k12.ca.us",
    "wof:name":"Woodcrest Elementary School",
    "wof:placetype":"venue"
},
  "geometry": {"coordinates":[-118.297105,33.937233],"type":"Point"}
}