{
  "type": "Feature",
  "properties": {
    "addr:full":"495 10th Ave San Diego CA 92101",
    "addr:housenumber":"495",
    "addr:postcode":"92101",
    "addr:street":"10Th Ave",
    "iso:country":"US",
    "sg:address":"495 10th Ave",
    "sg:city":"San Diego",
    "sg:classifiers":[
        {
            "category":"Personal",
            "subcategory":"Beauty Salon",
            "type":"Services"
        },
        {
            "category":"Personal",
            "subcategory":"Skin Care",
            "type":"Services"
        }
    ],
    "sg:phone":"+1 619 987 5950",
    "sg:postcode":"92101",
    "sg:province":"CA",
    "sg:tags":[
        "makeup",
        "artist"
    ],
    "sg:website":"www.sdholisticskincare.com",
    "wof:name":"Studio Jeanne-Michelle",
    "wof:placetype":"venue"
},
  "geometry": {"coordinates":[-117.155556,32.710284],"type":"Point"}
}