{
  "type": "Feature",
  "properties": {
    "addr:full":"1875 Joe Crosson Dr El Cajon CA 92020",
    "addr:housenumber":"1875",
    "addr:postcode":"92020",
    "addr:street":"Joe Crosson Dr",
    "iso:country":"US",
    "sg:address":"1875 Joe Crosson Dr",
    "sg:city":"El Cajon",
    "sg:classifiers":[
        {
            "category":"Sports & Exercise",
            "subcategory":"Race Track",
            "type":"Entertainment"
        }
    ],
    "sg:phone":"+1 619 448 8900",
    "sg:postcode":"92020",
    "sg:province":"CA",
    "wof:name":"Cajon Speedway",
    "wof:placetype":"venue"
},
  "geometry": {"coordinates":[-116.969677,32.821028],"type":"Point"}
}