{
  "type": "Feature",
  "properties": {
    "iso:country":"US",
    "sg:address":"8916 W Pico Boulevard",
    "sg:city":"Los Angeles",
    "sg:classifiers":[
        {
            "category":"Insurance",
            "subcategory":"Health Insurance",
            "type":"Services"
        }
    ],
    "sg:phone":"+1 310 858 7661",
    "sg:postcode":"90035",
    "sg:province":"CA",
    "sg:tags":[
        "market"
    ],
    "wof:name":"Natural Path Nutrition",
    "wof:placetype":"venue"
},
  "geometry": {"coordinates":[-118.386215,34.055355],"type":"Point"}
}