{
  "type": "Feature",
  "properties": {
    "addr:full":"1201 S River Rd West Sacramento CA 95691",
    "addr:housenumber":"1201",
    "addr:postcode":"95691",
    "addr:street":"S River Rd",
    "iso:country":"US",
    "sg:address":"1201 S River Rd",
    "sg:city":"West Sacramento",
    "sg:classifiers":[
        {
            "category":"Wholesale",
            "subcategory":"Farm Supplies",
            "type":"Manufacturing & Wholesale Goods"
        }
    ],
    "sg:phone":"+1 916 373 7450",
    "sg:postcode":"95691",
    "sg:province":"CA",
    "sg:tags":[
        "feed",
        "grain"
    ],
    "sg:website":"www.pennynewman.com",
    "wof:name":"Penny Newman Grain Co",
    "wof:placetype":"venue"
},
  "geometry": {"coordinates":[-121.51996,38.572046],"type":"Point"}
}