{
  "type": "Feature",
  "properties": {
    "addr:full":"3674 S Western Ave Los Angeles CA 90018",
    "addr:housenumber":"3674",
    "addr:postcode":"90018",
    "addr:street":"S Western Ave",
    "iso:country":"US",
    "sg:address":"3674 S Western Ave",
    "sg:city":"Los Angeles",
    "sg:classifiers":[
        {
            "category":"Shopping",
            "subcategory":"Gifts & Souvenirs",
            "type":"Retail Goods"
        }
    ],
    "sg:phone":"+1 323 732 7880",
    "sg:postcode":"90018",
    "sg:province":"CA",
    "wof:name":"Three Sisters & Brother",
    "wof:placetype":"venue"
},
  "geometry": {"coordinates":[-118.308817,34.021546],"type":"Point"}
}