{
  "type": "Feature",
  "properties": {
    "addr:full":"3200 Adams Ln Redding CA 96002",
    "addr:housenumber":"3200",
    "addr:postcode":"96002",
    "addr:street":"Adams Ln",
    "iso:country":"US",
    "sg:address":"3200 Adams Ln",
    "sg:city":"Redding",
    "sg:classifiers":[
        {
            "category":"Education",
            "subcategory":"School",
            "type":"Public Place"
        }
    ],
    "sg:phone":"+1 530 224 3240",
    "sg:postcode":"96002",
    "sg:province":"CA",
    "wof:name":"Monte Vista School",
    "wof:placetype":"venue"
},
  "geometry": {"coordinates":[-122.35538,40.558403],"type":"Point"}
}