{
  "type": "Feature",
  "properties": {
    "addr:full":"2716 Webster Street Berkeley CA 94705",
    "addr:housenumber":"2716",
    "addr:postcode":"94705",
    "addr:street":"Webster Street",
    "iso:country":"US",
    "sg:address":"2716 Webster Street",
    "sg:city":"Berkeley",
    "sg:classifiers":[
        {
            "category":"Insurance",
            "subcategory":"Hazard Insurance",
            "type":"Services"
        },
        {
            "category":"Insurance",
            "subcategory":"Health Insurance",
            "type":"Services"
        }
    ],
    "sg:phone":"+1 510 845 6688",
    "sg:postcode":"94705",
    "sg:province":"CA",
    "sg:tags":[
        "plans-information",
        "benefit",
        "referral",
        "employee"
    ],
    "wof:name":"Sturges Jean Health Insurance Services",
    "wof:placetype":"venue"
},
  "geometry": {"coordinates":[-122.25299800000001,37.855801],"type":"Point"}
}