{
  "type": "Feature",
  "properties": {
    "iso:country":"US",
    "sg:address":"5025 York Blvd",
    "sg:city":"Los Angeles",
    "sg:classifiers":[
        {
            "category":"Arena",
            "subcategory":"Sports Club",
            "type":"Entertainment"
        }
    ],
    "sg:phone":"+1 323 573 1873",
    "sg:postcode":"90042",
    "sg:province":"CA",
    "sg:tags":[
        "martial art"
    ],
    "sg:website":"socalmmafitness.com",
    "wof:name":"SoCal MMA",
    "wof:placetype":"venue"
},
  "geometry": {"coordinates":[-118.205989,34.121318],"type":"Point"}
}