{
  "type": "Feature",
  "properties": {
    "addr:full":"260 E 16th St Costa Mesa CA 92627",
    "addr:housenumber":"260",
    "addr:postcode":"92627",
    "addr:street":"E 16Th St",
    "iso:country":"US",
    "sg:address":"260 E 16th St",
    "sg:city":"Costa Mesa",
    "sg:classifiers":[
        {
            "category":"Social Services",
            "subcategory":"Adult Care",
            "type":"Services"
        }
    ],
    "sg:phone":"+1 949 645 8234",
    "sg:postcode":"92627",
    "sg:province":"CA",
    "sg:tags":[
        "home",
        "residential"
    ],
    "wof:name":"Newport Heights Manor",
    "wof:placetype":"venue"
},
  "geometry": {"coordinates":[-117.918432,33.630578],"type":"Point"}
}