{
  "type": "Feature",
  "properties": {
    "iso:country":"US",
    "sg:address":"223 S State College Blvd",
    "sg:city":"Anaheim",
    "sg:classifiers":[
        {
            "category":"Personal",
            "subcategory":"Nail Salon",
            "type":"Services"
        }
    ],
    "sg:phone":"+1 714 956 2365",
    "sg:postcode":"92806",
    "sg:province":"CA",
    "wof:name":"Tina Nails",
    "wof:placetype":"venue"
},
  "geometry": {"coordinates":[-117.889,33.839298],"type":"Point"}
}