{
  "type": "Feature",
  "properties": {
    "addr:full":"1850 N Riverside Ave Rialto CA 92376",
    "addr:housenumber":"1850",
    "addr:postcode":"92376",
    "addr:street":"N Riverside Ave",
    "iso:country":"US",
    "sg:address":"1850 N Riverside Ave",
    "sg:city":"Rialto",
    "sg:classifiers":[
        {
            "category":"Health Services",
            "subcategory":"Doctor",
            "type":"Services"
        }
    ],
    "sg:phone":"+1 909 421 3040",
    "sg:postcode":"92376",
    "sg:province":"CA",
    "sg:tags":[
        "physician",
        "surgeon",
        "radiology",
        "surgeons",
        "pediatrics-radiology"
    ],
    "wof:name":"Palm Imaging Institute Inc",
    "wof:placetype":"venue"
},
  "geometry": {"coordinates":[-117.370435,34.13316],"type":"Point"}
}