{
  "type": "Feature",
  "properties": {
    "iso:country":"US",
    "sg:address":"450 Newport Center Drive",
    "sg:city":"Newport Beach",
    "sg:classifiers":[
        {
            "category":"Banks & Credit Unions",
            "subcategory":"Investment Brokerage",
            "type":"Services"
        }
    ],
    "sg:phone":"+1 949 219 0021",
    "sg:postcode":"92660",
    "sg:province":"CA",
    "sg:tags":[
        "investing"
    ],
    "wof:name":"Scalene Capital Management",
    "wof:placetype":"venue"
},
  "geometry": {"coordinates":[-117.872473,33.614637],"type":"Point"}
}