{
  "type": "Feature",
  "properties": {
    "addr:full":"2020 Redwood Hwy Greenbrae CA 94904",
    "addr:housenumber":"2020",
    "addr:postcode":"94904",
    "addr:street":"Redwood Hwy",
    "iso:country":"US",
    "sg:address":"2020 Redwood Hwy",
    "sg:city":"Greenbrae",
    "sg:classifiers":[
        {
            "category":"Food & Beverages",
            "subcategory":"Liquor & Beverages",
            "type":"Retail Goods"
        }
    ],
    "sg:phone":"+1 415 927 1228",
    "sg:postcode":"94904",
    "sg:province":"CA",
    "sg:tags":[
        "wine"
    ],
    "wof:name":"Bevmo",
    "wof:placetype":"venue"
},
  "geometry": {"coordinates":[-122.515822,37.936077],"type":"Point"}
}