{
  "type": "Feature",
  "properties": {
    "iso:country":"US",
    "sg:address":"1884 S Sepulveda Boulevard",
    "sg:city":"Los Angeles",
    "sg:classifiers":[
        {
            "category":"Building & Trades",
            "subcategory":"Locksmith",
            "type":"Services"
        }
    ],
    "sg:phone":"+1 310 405 6038",
    "sg:postcode":"90025",
    "sg:province":"CA",
    "sg:tags":[
        "key"
    ],
    "wof:name":"All City 24 Hour Locks & Locksmith",
    "wof:placetype":"venue"
},
  "geometry": {"coordinates":[-118.441995,34.044751],"type":"Point"}
}