{
  "type": "Feature",
  "properties": {
    "addr:full":"1890 Foothill Blvd La Canada Flintridge CA 91011",
    "addr:housenumber":"1890",
    "addr:postcode":"91011",
    "addr:street":"Foothill Blvd",
    "iso:country":"US",
    "sg:address":"1890 Foothill Blvd",
    "sg:city":"La Canada Flintridge",
    "sg:classifiers":[
        {
            "category":"Education",
            "subcategory":"Special Training",
            "type":"Public Place"
        }
    ],
    "sg:phone":"+1 818 790 1109",
    "sg:postcode":"91011",
    "sg:province":"CA",
    "sg:tags":[
        "tutoring"
    ],
    "wof:name":"Kumon Center",
    "wof:placetype":"venue"
},
  "geometry": {"coordinates":[-118.21700300000001,34.212502],"type":"Point"}
}