{
  "type": "Feature",
  "properties": {
    "iso:country":"US",
    "sg:address":"8544 E Chapman Ave",
    "sg:city":"Orange",
    "sg:classifiers":[
        {
            "category":"Retail",
            "subcategory":"Auto Repair",
            "type":"Services"
        }
    ],
    "sg:phone":"+1 714 744 6109",
    "sg:postcode":"92869",
    "sg:province":"CA",
    "wof:name":"Santiago Hills Auto",
    "wof:placetype":"venue"
},
  "geometry": {"coordinates":[-117.762001,33.792099],"type":"Point"}
}