{
  "type": "Feature",
  "properties": {
    "addr:full":"901 H St Sacramento CA 95814",
    "addr:housenumber":"901",
    "addr:postcode":"95814",
    "addr:street":"H St",
    "iso:country":"US",
    "sg:address":"901 H St",
    "sg:city":"Sacramento",
    "sg:classifiers":[
        {
            "category":"Professional",
            "subcategory":"Lawyer & Legal Services",
            "type":"Services"
        }
    ],
    "sg:phone":"+1 916 444 7100",
    "sg:postcode":"95814",
    "sg:province":"CA",
    "sg:tags":[
        "attorney",
        "practice"
    ],
    "wof:name":"Law Offices Of Preeti K Bajwa",
    "wof:placetype":"venue"
},
  "geometry": {"coordinates":[-121.49382,38.582859],"type":"Point"}
}