{
  "type": "Feature",
  "properties": {
    "addr:full":"305 N Capitol Avenue #A San Jose CA 95133",
    "addr:housenumber":"305",
    "addr:postcode":"95133",
    "addr:street":"N Capitol Avenue # A",
    "iso:country":"US",
    "sg:address":"305 N Capitol Avenue #A",
    "sg:city":"San Jose",
    "sg:classifiers":[
        {
            "category":"Personal",
            "subcategory":"Beauty Salon",
            "type":"Services"
        }
    ],
    "sg:phone":"+1 408 251 3020",
    "sg:postcode":"95133",
    "sg:province":"CA",
    "sg:tags":[
        "hair"
    ],
    "wof:name":"Schroeder's",
    "wof:placetype":"venue"
},
  "geometry": {"coordinates":[-121.843541,37.370535],"type":"Point"}
}