{
  "type": "Feature",
  "properties": {
    "addr:full":"6033 W Century Blvd Ste 1250 Los Angeles CA 90045",
    "addr:housenumber":"6033",
    "addr:postcode":"90045",
    "addr:street":"W Century Blvd Ste 1250",
    "iso:country":"US",
    "sg:address":"6033 W Century Blvd Ste 1250",
    "sg:city":"Los Angeles",
    "sg:classifiers":[
        {
            "category":"Travel",
            "subcategory":"Travel Agent",
            "type":"Entertainment"
        }
    ],
    "sg:phone":"+1 310 242 9234",
    "sg:postcode":"90045",
    "sg:province":"CA",
    "sg:website":"www.springboardvacations.com",
    "wof:name":"Springboard Vacations",
    "wof:placetype":"venue"
},
  "geometry": {"coordinates":[-118.389668,33.946125],"type":"Point"}
}