{
  "type": "Feature",
  "properties": {
    "iso:country":"US",
    "sg:address":"28782 Camino Capistrano",
    "sg:city":"Laguna Niguel",
    "sg:classifiers":[
        {
            "category":"Fast Food",
            "type":"Food & Drink"
        }
    ],
    "sg:phone":"+1 800 786 1000",
    "sg:postcode":"92677",
    "sg:province":"CA",
    "sg:tags":[
        "burger"
    ],
    "sg:website":"www.in-n-out.com",
    "wof:name":"In-N-Out Burger",
    "wof:placetype":"venue"
},
  "geometry": {"coordinates":[-117.673936,33.553757],"type":"Point"}
}