{
  "type": "Feature",
  "properties": {
    "addr:full":"4423 Cass St San Diego CA 92109",
    "addr:housenumber":"4423",
    "addr:postcode":"92109",
    "addr:street":"Cass St",
    "iso:country":"US",
    "sg:address":"4423 Cass St",
    "sg:city":"San Diego",
    "sg:classifiers":[
        {
            "category":"Real Estate",
            "subcategory":"Real Estate Agent",
            "type":"Services"
        }
    ],
    "sg:phone":"+1 858 270 2071",
    "sg:postcode":"92109",
    "sg:province":"CA",
    "sg:tags":[
        "management",
        "property"
    ],
    "sg:website":"www.delsolpm.com",
    "wof:name":"Del Sol Property Management",
    "wof:placetype":"venue"
},
  "geometry": {"coordinates":[-117.25099899999999,32.7957],"type":"Point"}
}