{
  "type": "Feature",
  "properties": {
    "addr:full":"17888 Wisteria St Hesperia CA 92345",
    "addr:housenumber":"17888",
    "addr:postcode":"92345",
    "addr:street":"Wisteria St",
    "iso:country":"US",
    "sg:address":"17888 Wisteria St",
    "sg:city":"Hesperia",
    "sg:classifiers":[
        {
            "category":"Freight",
            "type":"Transportation"
        }
    ],
    "sg:phone":"+1 760 244 1921",
    "sg:postcode":"92345",
    "sg:province":"CA",
    "sg:tags":[
        "operator",
        "trucking"
    ],
    "wof:name":"Nando Haase Co",
    "wof:placetype":"venue"
},
  "geometry": {"coordinates":[-117.27264599999999,34.443945],"type":"Point"}
}