{
  "type": "Feature",
  "properties": {
    "iso:country":"US",
    "sg:address":"3811 State Rte 175",
    "sg:city":"Hopland",
    "sg:classifiers":[
        {
            "category":"Manufacturing",
            "subcategory":"Food",
            "type":"Manufacturing & Wholesale Goods"
        }
    ],
    "sg:phone":"+1 707 744 1774",
    "sg:postcode":"95449",
    "sg:province":"CA",
    "sg:tags":[
        "winery"
    ],
    "sg:website":"www.mcdowellsyrah.com",
    "wof:name":"Mc Dowell Valley Vineyards",
    "wof:placetype":"venue"
},
  "geometry": {"coordinates":[-123.051826,38.97666],"type":"Point"}
}