{
  "type": "Feature",
  "properties": {
    "iso:country":"US",
    "sg:address":"15131 Clark Ave",
    "sg:city":"Hacienda Heights",
    "sg:classifiers":[
        {
            "category":"Wholesale",
            "subcategory":"Scrap",
            "type":"Manufacturing & Wholesale Goods"
        }
    ],
    "sg:phone":"+1 626 330 5799",
    "sg:postcode":"91745",
    "sg:province":"CA",
    "sg:tags":[
        "barrels",
        "drum"
    ],
    "wof:name":"AJS Filter Processing Inc",
    "wof:placetype":"venue"
},
  "geometry": {"coordinates":[-117.97422,34.018653],"type":"Point"}
}