{
  "type": "Feature",
  "properties": {
    "addr:full":"629 Argonaut St Stockton CA 95203",
    "addr:housenumber":"629",
    "addr:postcode":"95203",
    "addr:street":"Argonaut St",
    "iso:country":"US",
    "sg:address":"629 Argonaut St",
    "sg:city":"Stockton",
    "sg:classifiers":[
        {
            "category":"Professional",
            "type":"Services"
        }
    ],
    "sg:phone":"+1 209 946 0449",
    "sg:postcode":"95203",
    "sg:province":"CA",
    "wof:name":"Dann Angulo",
    "wof:placetype":"venue"
},
  "geometry": {"coordinates":[-121.308621,37.956507],"type":"Point"}
}