{
  "type": "Feature",
  "properties": {
    "iso:country":"US",
    "sg:address":"5180 Pacheco Blvd",
    "sg:city":"Pacheco",
    "sg:classifiers":[
        {
            "category":"Autos & Motor Vehicles",
            "subcategory":"Auto Supplies",
            "type":"Retail Goods"
        }
    ],
    "sg:phone":"+1 925 798 2201",
    "sg:postcode":"94553",
    "sg:province":"CA",
    "sg:tags":[
        "automobile",
        "part",
        "accessory"
    ],
    "wof:name":"Superior Auto Parts Warehouse",
    "wof:placetype":"venue"
},
  "geometry": {"coordinates":[-122.073532,37.991749],"type":"Point"}
}