{
  "type": "Feature",
  "properties": {
    "iso:country":"US",
    "sg:address":"10353 Torre Avenue",
    "sg:city":"Cupertino",
    "sg:classifiers":[
        {
            "category":"Health Services",
            "subcategory":"Doctor",
            "type":"Services"
        }
    ],
    "sg:phone":"+1 408 725 1777",
    "sg:postcode":"95014",
    "sg:province":"CA",
    "wof:name":"Patwardhan Manjul Doctor",
    "wof:placetype":"venue"
},
  "geometry": {"coordinates":[-122.029274,37.317196],"type":"Point"}
}