{
  "type": "Feature",
  "properties": {
    "addr:full":"2908 E Hullett St Long Beach CA 90805",
    "addr:housenumber":"2908",
    "addr:postcode":"90805",
    "addr:street":"E Hullett St",
    "iso:country":"US",
    "sg:address":"2908 E Hullett St",
    "sg:city":"Long Beach",
    "sg:classifiers":[
        {
            "category":"Building & Trades",
            "subcategory":"Construction",
            "type":"Services"
        }
    ],
    "sg:phone":"+1 562 408 0898",
    "sg:postcode":"90805",
    "sg:province":"CA",
    "sg:tags":[
        "contractor"
    ],
    "wof:name":"Keystone Archway Construction",
    "wof:placetype":"venue"
},
  "geometry": {"coordinates":[-118.158154,33.860921],"type":"Point"}
}