{
  "type": "Feature",
  "properties": {
    "addr:full":"23705 Madison St Torrance CA 90505",
    "addr:housenumber":"23705",
    "addr:postcode":"90505",
    "addr:street":"Madison St",
    "iso:country":"US",
    "sg:address":"23705 Madison St",
    "sg:city":"Torrance",
    "sg:classifiers":[
        {
            "category":"Retail",
            "subcategory":"Repair Shop",
            "type":"Services"
        }
    ],
    "sg:phone":"+1 310 373 5458",
    "sg:postcode":"90505",
    "sg:province":"CA",
    "sg:tags":[
        "refinishing",
        "furniture"
    ],
    "wof:name":"Palos Verdes Refinishing",
    "wof:placetype":"venue"
},
  "geometry": {"coordinates":[-118.34893700000001,33.807807],"type":"Point"}
}