{
  "type": "Feature",
  "properties": {
    "iso:country":"US",
    "sg:address":"1538 N Blackstone Ave",
    "sg:city":"Fresno",
    "sg:classifiers":[
        {
            "category":"Home & Garden",
            "subcategory":"Building Materials",
            "type":"Retail Goods"
        }
    ],
    "sg:phone":"+1 559 233 6603",
    "sg:postcode":"93704",
    "sg:province":"CA",
    "sg:tags":[
        "cement"
    ],
    "wof:name":"E-Z Haul Ready Mix",
    "wof:placetype":"venue"
},
  "geometry": {"coordinates":[-119.790465,36.764913],"type":"Point"}
}