{
  "type": "Feature",
  "properties": {
    "iso:country":"US",
    "sg:address":"1217 Haskell St",
    "sg:city":"Berkeley",
    "sg:classifiers":[
        {
            "category":"Personal",
            "subcategory":"Tattoo Parlor",
            "type":"Services"
        }
    ],
    "sg:phone":"+1 510 428 1115",
    "sg:postcode":"94702",
    "sg:province":"CA",
    "sg:tags":[
        "tattooing"
    ],
    "wof:name":"Smith Tattoo Shop",
    "wof:placetype":"venue"
},
  "geometry": {"coordinates":[-122.284997,37.850836],"type":"Point"}
}