{
  "type": "Feature",
  "properties": {
    "iso:country":"US",
    "sg:address":"2701 Pine St",
    "sg:city":"Bakersfield",
    "sg:classifiers":[
        {
            "category":"Building & Trades",
            "subcategory":"Landscaping Services",
            "type":"Services"
        }
    ],
    "sg:phone":"+1 661 324 4850",
    "sg:postcode":"93301",
    "sg:province":"CA",
    "sg:tags":[
        "lawn",
        "maintenance",
        "grounds"
    ],
    "wof:name":"Advanced Landscape Maintenance",
    "wof:placetype":"venue"
},
  "geometry": {"coordinates":[-119.02686199999999,35.388065],"type":"Point"}
}