{
  "type": "Feature",
  "properties": {
    "iso:country":"US",
    "sg:address":"Fashion Valley 7007 Friars Rd Ste 845a",
    "sg:city":"San Diego",
    "sg:classifiers":[
        {
            "category":"Shopping",
            "type":"Retail Goods"
        }
    ],
    "sg:phone":"+1 619 220 8190",
    "sg:postcode":"92108",
    "sg:province":"CA",
    "sg:website":"www.katespade.com",
    "wof:name":"kate spade",
    "wof:placetype":"venue"
},
  "geometry": {"coordinates":[-117.166011,32.767925],"type":"Point"}
}