{
  "type": "Feature",
  "properties": {
    "iso:country":"US",
    "sg:address":"67772 E Palm Canyon Dr",
    "sg:city":"Cathedral City",
    "sg:classifiers":[
        {
            "category":"Organizations",
            "subcategory":"Religious Organization",
            "type":"Services"
        }
    ],
    "sg:phone":"+1 760 202 1772",
    "sg:postcode":"92234",
    "sg:province":"CA",
    "wof:name":"Friends Of Jesus Christian",
    "wof:placetype":"venue"
},
  "geometry": {"coordinates":[-116.479072,33.786694],"type":"Point"}
}