{
  "type": "Feature",
  "properties": {
    "iso:country":"US",
    "sg:address":"28570 Marguerite Pkwy Ste 218",
    "sg:city":"Mission Viejo",
    "sg:classifiers":[
        {
            "category":"Banks & Credit Unions",
            "subcategory":"Financial Services",
            "type":"Services"
        }
    ],
    "sg:phone":"+1 949 481 1625",
    "sg:postcode":"92692",
    "sg:province":"CA",
    "sg:tags":[
        "broker",
        "mortgage"
    ],
    "wof:name":"Mortgage Link 1",
    "wof:placetype":"venue"
},
  "geometry": {"coordinates":[-117.670356,33.548492],"type":"Point"}
}