{
  "type": "Feature",
  "properties": {
    "iso:country":"US",
    "sg:address":"5051 E Lincoln",
    "sg:city":"Cypress",
    "sg:classifiers":[
        {
            "category":"Autos & Motor Vehicles",
            "subcategory":"Auto Supplies",
            "type":"Retail Goods"
        },
        {
            "category":"Retail",
            "subcategory":"Auto Repair",
            "type":"Services"
        }
    ],
    "sg:phone":"+1 714 995 5085",
    "sg:postcode":"90630",
    "sg:province":"CA",
    "sg:tags":[
        "tire"
    ],
    "sg:website":"www.discounttirecenters.com",
    "wof:name":"Discount Tire Centers",
    "wof:placetype":"venue"
},
  "geometry": {"coordinates":[-118.044672,33.832216],"type":"Point"}
}