{
  "type": "Feature",
  "properties": {
    "iso:country":"US",
    "sg:address":"910 Main St",
    "sg:city":"Red Bluff",
    "sg:classifiers":[
        {
            "category":"Banks & Credit Unions",
            "subcategory":"Bank",
            "type":"Services"
        }
    ],
    "sg:phone":"+1 530 527 7614",
    "sg:postcode":"96080",
    "sg:province":"CA",
    "sg:website":"www.midvalleybank.net",
    "wof:name":"Premier West Bank",
    "wof:placetype":"venue"
},
  "geometry": {"coordinates":[-122.237069,40.180088],"type":"Point"}
}