{
  "type": "Feature",
  "properties": {
    "addr:full":"3730 Mission St San Francisco CA 94110",
    "addr:housenumber":"3730",
    "addr:postcode":"94110",
    "addr:street":"Mission St",
    "iso:country":"US",
    "sg:address":"3730 Mission St",
    "sg:city":"San Francisco",
    "sg:classifiers":[
        {
            "category":"Retail",
            "subcategory":"Auto Repair",
            "type":"Services"
        }
    ],
    "sg:phone":"+1 415 647 6020",
    "sg:postcode":"94110",
    "sg:province":"CA",
    "sg:tags":[
        "repairing",
        "automobile"
    ],
    "wof:name":"Custom Car & Engine Care",
    "wof:placetype":"venue"
},
  "geometry": {"coordinates":[-122.424195,37.737172],"type":"Point"}
}