{
  "type": "Feature",
  "properties": {
    "iso:country":"US",
    "sg:address":"3730 Mission St",
    "sg:city":"San Francisco",
    "sg:classifiers":[
        {
            "category":"Retail",
            "subcategory":"Auto Repair",
            "type":"Services"
        }
    ],
    "sg:phone":"+1 415 647 6020",
    "sg:postcode":"94110",
    "sg:province":"CA",
    "sg:tags":[
        "repairing",
        "automobile"
    ],
    "wof:name":"Custom Car & Engine Care",
    "wof:placetype":"venue"
},
  "geometry": {"coordinates":[-122.424195,37.737172],"type":"Point"}
}