{
  "type": "Feature",
  "properties": {
    "iso:country":"US",
    "sg:address":"3885 Sonoma Blvd",
    "sg:city":"Vallejo",
    "sg:classifiers":[
        {
            "category":"Food & Beverages",
            "subcategory":"Bakery",
            "type":"Retail Goods"
        }
    ],
    "sg:phone":"+1 707 557 9977",
    "sg:postcode":"94589",
    "sg:province":"CA",
    "sg:tags":[
        "baker"
    ],
    "wof:name":"Goldilocks Bake Shop",
    "wof:placetype":"venue"
},
  "geometry": {"coordinates":[-122.255543,38.12387],"type":"Point"}
}