{
  "type": "Feature",
  "properties": {
    "addr:full":"219 Estates Dr Roseville CA 95678",
    "addr:housenumber":"219",
    "addr:postcode":"95678",
    "addr:street":"Estates Dr",
    "iso:country":"US",
    "sg:address":"219 Estates Dr",
    "sg:city":"Roseville",
    "sg:classifiers":[
        {
            "category":"Social Services",
            "type":"Services"
        }
    ],
    "sg:phone":"+1 916 786 3608",
    "sg:postcode":"95678",
    "sg:province":"CA",
    "sg:tags":[
        "counselor",
        "marriage",
        "family"
    ],
    "wof:name":"Brian P Cummings",
    "wof:placetype":"venue"
},
  "geometry": {"coordinates":[-121.272114,38.747333],"type":"Point"}
}