{
  "type": "Feature",
  "properties": {
    "iso:country":"US",
    "sg:address":"5720 Stoneridge Mall Rd Ste 240",
    "sg:city":"Pleasanton",
    "sg:classifiers":[
        {
            "category":"Health Services",
            "subcategory":"Doctor",
            "type":"Services"
        }
    ],
    "sg:phone":"+1 925 463 1234",
    "sg:postcode":"94588",
    "sg:province":"CA",
    "sg:tags":[
        "physician",
        "surgeon",
        "pediatrics",
        "surgeons"
    ],
    "wof:name":"Kerr, Anna R, Md - Bayside Medical Group",
    "wof:placetype":"venue"
},
  "geometry": {"coordinates":[-121.929626,37.692293],"type":"Point"}
}