{
  "type": "Feature",
  "properties": {
    "iso:country":"US",
    "sg:address":"14035 Palmdale Rd",
    "sg:city":"Victorville",
    "sg:classifiers":[
        {
            "category":"Autos & Motor Vehicles",
            "subcategory":"Automobile Sales",
            "type":"Retail Goods"
        },
        {
            "category":"Retail",
            "subcategory":"Auto Rental",
            "type":"Services"
        },
        {
            "category":"Building & Trades",
            "subcategory":"Equipment Rental",
            "type":"Services"
        }
    ],
    "sg:phone":"+1 760 245 1402",
    "sg:postcode":"92392",
    "sg:province":"CA",
    "sg:tags":[
        "truck",
        "used",
        "moving"
    ],
    "sg:website":"http://budgettruck.com/IYP_tl",
    "wof:name":"El Paisano Tire Shop DBA/Budget Truck Rental",
    "wof:placetype":"venue"
},
  "geometry": {"coordinates":[-117.356582,34.506693],"type":"Point"}
}