{
  "type": "Feature",
  "properties": {
    "addr:full":"945 Hornblend St San Diego CA 92109",
    "addr:housenumber":"945",
    "addr:postcode":"92109",
    "addr:street":"Hornblend St",
    "iso:country":"US",
    "sg:address":"945 Hornblend St",
    "sg:city":"San Diego",
    "sg:classifiers":[
        {
            "category":"Health Services",
            "subcategory":"Doctor",
            "type":"Services"
        }
    ],
    "sg:phone":"+1 858 270 6855",
    "sg:postcode":"92109",
    "sg:province":"CA",
    "sg:tags":[
        "dentist"
    ],
    "wof:name":"Alex B Berest DDS",
    "wof:placetype":"venue"
},
  "geometry": {"coordinates":[-117.252284,32.79619],"type":"Point"}
}