{
  "type": "Feature",
  "properties": {
    "addr:full":"2377 Linwood Street San Diego CA 92110",
    "addr:housenumber":"2377",
    "addr:postcode":"92110",
    "addr:street":"Linwood Street",
    "iso:country":"US",
    "sg:address":"2377 Linwood Street",
    "sg:city":"San Diego",
    "sg:classifiers":[
        {
            "category":"Real Estate",
            "subcategory":"Real Estate Services",
            "type":"Services"
        }
    ],
    "sg:phone":"+1 619 298 1145",
    "sg:postcode":"92110",
    "sg:province":"CA",
    "sg:tags":[
        "management",
        "property"
    ],
    "wof:name":"Commercial Property Services",
    "wof:placetype":"venue"
},
  "geometry": {"coordinates":[-117.193078,32.751651],"type":"Point"}
}