{
  "type": "Feature",
  "properties": {
    "iso:country":"US",
    "sg:address":"6857 Van Nuys Blvd",
    "sg:city":"Van Nuys",
    "sg:classifiers":[
        {
            "category":"Manufacturing",
            "subcategory":"Electronics",
            "type":"Manufacturing & Wholesale Goods"
        }
    ],
    "sg:phone":"+1 818 997 7944",
    "sg:postcode":"91405",
    "sg:province":"CA",
    "sg:tags":[
        "apparatus",
        "mfg"
    ],
    "wof:name":"Jet Peru",
    "wof:placetype":"venue"
},
  "geometry": {"coordinates":[-118.448797,34.197339],"type":"Point"}
}