{
  "type": "Feature",
  "properties": {
    "iso:country":"US",
    "sg:address":"4421 Springwood Ct",
    "sg:city":"Napa",
    "sg:classifiers":[
        {
            "category":"Wholesale",
            "subcategory":"Groceries",
            "type":"Manufacturing & Wholesale Goods"
        }
    ],
    "sg:phone":"+1 707 255 2610",
    "sg:postcode":"94558",
    "sg:province":"CA",
    "sg:tags":[
        "food",
        "product"
    ],
    "wof:name":"Fabb Co Inc Marketing & Dev",
    "wof:placetype":"venue"
},
  "geometry": {"coordinates":[-122.31811500000001,38.343134],"type":"Point"}
}