{
  "type": "Feature",
  "properties": {
    "addr:full":"2031 W Alameda Ave Ste 310 Burbank CA 91506",
    "addr:housenumber":"2031",
    "addr:postcode":"91506",
    "addr:street":"W Alameda Ave Ste 310",
    "iso:country":"US",
    "sg:address":"2031 W Alameda Ave Ste 310",
    "sg:city":"Burbank",
    "sg:classifiers":[
        {
            "category":"Health Services",
            "subcategory":"Doctor",
            "type":"Services"
        }
    ],
    "sg:phone":"+1 818 841 2880",
    "sg:postcode":"91506",
    "sg:province":"CA",
    "wof:name":"Schott Ronald E MD",
    "wof:placetype":"venue"
},
  "geometry": {"coordinates":[-118.32399700000001,34.171501],"type":"Point"}
}