{
  "type": "Feature",
  "properties": {
    "addr:full":"970 N Mountain Ave Ontario CA 91762",
    "addr:housenumber":"970",
    "addr:postcode":"91762",
    "addr:street":"N Mountain Ave",
    "iso:country":"US",
    "sg:address":"970 N Mountain Ave",
    "sg:city":"Ontario",
    "sg:classifiers":[
        {
            "category":"Shopping",
            "subcategory":"Clothing, Apparel, & Fashions",
            "type":"Retail Goods"
        }
    ],
    "sg:phone":"+1 909 391 2233",
    "sg:postcode":"91762",
    "sg:province":"CA",
    "wof:name":"Avenue",
    "wof:placetype":"venue"
},
  "geometry": {"coordinates":[-117.670022,34.075989],"type":"Point"}
}