{
  "type": "Feature",
  "properties": {
    "addr:full":"1800 Tully Rd Modesto CA 95350",
    "addr:housenumber":"1800",
    "addr:postcode":"ca 95350",
    "addr:street":"Tully Rd",
    "iso:country":"US",
    "sg:address":"1800 Tully Rd",
    "sg:city":"Modesto",
    "sg:classifiers":[
        {
            "category":"Health Services",
            "subcategory":"Health Practitioner",
            "type":"Services"
        }
    ],
    "sg:phone":"+1 209 524 7488",
    "sg:postcode":"95350",
    "sg:province":"CA",
    "sg:tags":[
        "therapist",
        "physical"
    ],
    "wof:name":"Biosport Physical Therapy",
    "wof:placetype":"venue"
},
  "geometry": {"coordinates":[-121.01225599999999,37.671946],"type":"Point"}
}