{
  "type": "Feature",
  "properties": {
    "iso:country":"US",
    "sg:address":"109 N McDowell Blvd",
    "sg:city":"Petaluma",
    "sg:classifiers":[
        {
            "category":"Restaurant",
            "type":"Food & Drink"
        }
    ],
    "sg:phone":"+1 707 773 1772",
    "sg:postcode":"94954",
    "sg:province":"CA",
    "sg:tags":[
        "delicatessen"
    ],
    "wof:name":"Sweets 4-U Bakery & Cafe",
    "wof:placetype":"venue"
},
  "geometry": {"coordinates":[-122.625958,38.249185],"type":"Point"}
}