{
  "type": "Feature",
  "properties": {
    "addr:full":"323 N.Crescent Dr. Beverly Hills CA 90210",
    "addr:housenumber":"323",
    "addr:postcode":"90210",
    "addr:street":"N.Crescent Dr.",
    "iso:country":"US",
    "sg:address":"323 N.Crescent Dr.",
    "sg:city":"Beverly Hills",
    "sg:classifiers":[
        {
            "category":"Building & Trades",
            "subcategory":"Cleaning & Sanitation",
            "type":"Services"
        }
    ],
    "sg:phone":"+1 310 402 0362",
    "sg:postcode":"90210",
    "sg:province":"CA",
    "sg:tags":[
        "home"
    ],
    "sg:website":"limousineserviceinbeverlyhills.info",
    "wof:name":"Emerald Limousine Service - Limousine Service in Beverly Hills",
    "wof:placetype":"venue"
},
  "geometry": {"coordinates":[-118.39876700000001,34.070175],"type":"Point"}
}