{
  "type": "Feature",
  "properties": {
    "iso:country":"US",
    "sg:address":"1521 University Ave Cal",
    "sg:city":"Berkeley",
    "sg:classifiers":[
        {
            "category":"Real Estate",
            "subcategory":"Real Estate Operator",
            "type":"Services"
        },
        {
            "category":"Social Services",
            "subcategory":"Retirement Home",
            "type":"Services"
        }
    ],
    "sg:phone":"+1 510 647 0700",
    "sg:postcode":"94703",
    "sg:province":"CA",
    "sg:tags":[
        "hotel",
        "apartment"
    ],
    "sg:website":"http://www.satellitehousing.org",
    "wof:name":"Satellite Senior Homes Inc",
    "wof:placetype":"venue"
},
  "geometry": {"coordinates":[-122.281463,37.870535],"type":"Point"}
}