{
  "type": "Feature",
  "properties": {
    "iso:country":"US",
    "sg:address":"Lifeline Chiropractic 2975 Fairview Rd",
    "sg:city":"Costa Mesa",
    "sg:classifiers":[
        {
            "category":"Health Services",
            "subcategory":"Chiropractor",
            "type":"Services"
        }
    ],
    "sg:phone":"+1 714 662 2142",
    "sg:postcode":"92626",
    "sg:province":"CA",
    "sg:website":"www.LifelinePower.com",
    "wof:name":"Brian Stanton, DC",
    "wof:placetype":"venue"
},
  "geometry": {"coordinates":[-117.907882,33.679533],"type":"Point"}
}