{
  "type": "Feature",
  "properties": {
    "iso:country":"US",
    "sg:address":"2985 Solano Ave",
    "sg:city":"Napa",
    "sg:classifiers":[
        {
            "category":"Personal",
            "subcategory":"Beauty Salon",
            "type":"Services"
        }
    ],
    "sg:phone":"+1 707 253 9183",
    "sg:postcode":"94558",
    "sg:province":"CA",
    "sg:tags":[
        "manicuring"
    ],
    "wof:name":"Julie's Nail Nook & Co",
    "wof:placetype":"venue"
},
  "geometry": {"coordinates":[-122.306946,38.312881],"type":"Point"}
}