{
  "type": "Feature",
  "properties": {
    "iso:country":"US",
    "sg:address":"198 N 2nd St",
    "sg:city":"Porterville",
    "sg:classifiers":[
        {
            "category":"Wholesale",
            "subcategory":"Machinery & Supplies",
            "type":"Manufacturing & Wholesale Goods"
        }
    ],
    "sg:phone":"+1 559 781 2203",
    "sg:postcode":"93257",
    "sg:province":"CA",
    "sg:tags":[
        "equipment",
        "salon",
        "establishment",
        "beauty"
    ],
    "wof:name":"Nail Garden Salon",
    "wof:placetype":"venue"
},
  "geometry": {"coordinates":[-119.015063,36.069166],"type":"Point"}
}