{
  "type": "Feature",
  "properties": {
    "iso:country":"US",
    "sg:address":"2832 Ronald St",
    "sg:city":"Riverside",
    "sg:classifiers":[
        {
            "category":"Building & Trades",
            "subcategory":"Landscaping Services",
            "type":"Services"
        }
    ],
    "sg:phone":"+1 951 683 7426",
    "sg:postcode":"92506",
    "sg:province":"CA",
    "sg:tags":[
        "lawn",
        "maintenance"
    ],
    "wof:name":"Eds Yard Care",
    "wof:placetype":"venue"
},
  "geometry": {"coordinates":[-117.38511099999999,33.935547],"type":"Point"}
}