{
  "type": "Feature",
  "properties": {
    "addr:full":"9668 E Ave Hesperia CA 92345",
    "addr:housenumber":"9668",
    "addr:postcode":"92345",
    "addr:street":"E Ave",
    "iso:country":"US",
    "sg:address":"9668 E Ave",
    "sg:city":"Hesperia",
    "sg:classifiers":[
        {
            "category":"Professional",
            "type":"Services"
        },
        {
            "category":"Personal",
            "type":"Services"
        },
        {
            "category":"Retail",
            "subcategory":"Storage",
            "type":"Services"
        },
        {
            "category":"Manufacturing",
            "subcategory":"Paper Products",
            "type":"Manufacturing & Wholesale Goods"
        }
    ],
    "sg:phone":"+1 760 244 4545",
    "sg:postcode":"92345",
    "sg:province":"CA",
    "sg:tags":[
        "fiber",
        "materials-wholesale",
        "material",
        "commercial",
        "packaging",
        "boxes-corrugated",
        "moving",
        "services-labor",
        "mover",
        "self",
        "household",
        "manufacturer"
    ],
    "sg:website":"http://www.hesperiastorage.net",
    "wof:name":"Hesperia Self Storage",
    "wof:placetype":"venue"
},
  "geometry": {"coordinates":[-117.29042,34.429952],"type":"Point"}
}