{
  "type": "Feature",
  "properties": {
    "addr:full":"633 N Central Ave Ste 203 Glendale CA 91203",
    "addr:housenumber":"633",
    "addr:postcode":"91203",
    "addr:street":"N Central Ave Ste 203",
    "iso:country":"US",
    "sg:address":"633 N Central Ave Ste 203",
    "sg:city":"Glendale",
    "sg:classifiers":[
        {
            "category":"Health Services",
            "subcategory":"Doctor",
            "type":"Services"
        }
    ],
    "sg:phone":"+1 818 240 9142",
    "sg:postcode":"91203",
    "sg:province":"CA",
    "sg:tags":[
        "surgeon",
        "oral"
    ],
    "wof:name":"Mark M \u00a0Deleon, DDS",
    "wof:placetype":"venue"
},
  "geometry": {"coordinates":[-118.25830999999999,34.155048],"type":"Point"}
}