{
  "type": "Feature",
  "properties": {
    "iso:country":"US",
    "sg:address":"17201 Crescent Dr",
    "sg:city":"Los Gatos",
    "sg:classifiers":[
        {
            "category":"Professional",
            "type":"Services"
        }
    ],
    "sg:phone":"+1 408 356 6367",
    "sg:postcode":"95030",
    "sg:province":"CA",
    "wof:name":"John A Uhl A Professional Corp",
    "wof:placetype":"venue"
},
  "geometry": {"coordinates":[-121.959429,37.21967],"type":"Point"}
}