{
  "type": "Feature",
  "properties": {
    "iso:country":"US",
    "sg:address":"4045 N Freeway Blvd",
    "sg:city":"Sacramento",
    "sg:classifiers":[
        {
            "category":"Professional",
            "subcategory":"Management & Consulting",
            "type":"Services"
        }
    ],
    "sg:phone":"+1 916 923 2820",
    "sg:postcode":"95834",
    "sg:province":"CA",
    "sg:tags":[
        "consultant",
        "business"
    ],
    "wof:name":"Diversified Mgmt Conslnts Inc",
    "wof:placetype":"venue"
},
  "geometry": {"coordinates":[-121.47866999999999,38.642044],"type":"Point"}
}