{
  "type": "Feature",
  "properties": {
    "addr:full":"PO Box 66335 Scotts Valley CA 95067",
    "addr:housenumber":"po box 66335",
    "addr:postcode":"95067",
    "iso:country":"US",
    "sg:address":"PO Box 66335",
    "sg:city":"Scotts Valley",
    "sg:classifiers":[
        {
            "category":"Building & Trades",
            "subcategory":"Plumbing",
            "type":"Services"
        }
    ],
    "sg:phone":"+1 831 438 4487",
    "sg:postcode":"95067",
    "sg:province":"CA",
    "wof:name":"Precision Plumbing",
    "wof:placetype":"venue"
},
  "geometry": {"coordinates":[-122.02824200000001,37.048666],"type":"Point"}
}