{
  "type": "Feature",
  "properties": {
    "iso:country":"US",
    "sg:address":"619 Paulin Ave Ste 103",
    "sg:city":"Calexico",
    "sg:classifiers":[
        {
            "category":"Home & Garden",
            "subcategory":"Furniture",
            "type":"Retail Goods"
        }
    ],
    "sg:phone":"+1 760 357 4356",
    "sg:postcode":"92231",
    "sg:province":"CA",
    "sg:tags":[
        "store"
    ],
    "wof:name":"Home Fashion Inc",
    "wof:placetype":"venue"
},
  "geometry": {"coordinates":[-115.49749799999999,32.67108],"type":"Point"}
}