{
  "type": "Feature",
  "properties": {
    "addr:full":"5125 Ladefonos Ct Sacramento CA 95842",
    "addr:housenumber":"5125",
    "addr:postcode":"95842",
    "addr:street":"Ladefonos Ct",
    "iso:country":"US",
    "sg:address":"5125 Ladefonos Ct",
    "sg:city":"Sacramento",
    "sg:classifiers":[
        {
            "category":"Shopping",
            "subcategory":"Books",
            "type":"Retail Goods"
        }
    ],
    "sg:phone":"+1 916 332 4516",
    "sg:postcode":"95842",
    "sg:province":"CA",
    "sg:tags":[
        "store"
    ],
    "wof:name":"Lauers Create A Book",
    "wof:placetype":"venue"
},
  "geometry": {"coordinates":[-121.34422600000001,38.697389],"type":"Point"}
}