{
  "type": "Feature",
  "properties": {
    "addr:full":"124 E Yorba Linda Blvd Placentia CA 92870",
    "addr:housenumber":"124",
    "addr:postcode":"ca 92870",
    "addr:street":"E Yorba Linda Blvd",
    "iso:country":"US",
    "sg:address":"124 E Yorba Linda Blvd",
    "sg:city":"Placentia",
    "sg:classifiers":[
        {
            "category":"Personal",
            "subcategory":"Beauty Salon",
            "type":"Services"
        }
    ],
    "sg:phone":"+1 714 524 8100",
    "sg:postcode":"92870",
    "sg:province":"CA",
    "wof:name":"Rea Perla",
    "wof:placetype":"venue"
},
  "geometry": {"coordinates":[-117.86432499999999,33.887699],"type":"Point"}
}