{
  "type": "Feature",
  "properties": {
    "addr:full":"351 Sprowl Creek Rd Garberville CA 95542",
    "addr:housenumber":"351",
    "addr:postcode":"95542",
    "addr:street":"Sprowl Creek Rd",
    "iso:country":"US",
    "sg:address":"351 Sprowl Creek Rd",
    "sg:city":"Garberville",
    "sg:classifiers":[
        {
            "category":"Professional",
            "subcategory":"Research",
            "type":"Services"
        }
    ],
    "sg:phone":"+1 707 923 4377",
    "sg:postcode":"95542",
    "sg:province":"CA",
    "sg:tags":[
        "environmental",
        "ecological"
    ],
    "sg:website":"www.treesfoundation.org",
    "wof:name":"Trees Foundation",
    "wof:placetype":"venue"
},
  "geometry": {"coordinates":[-123.79891600000001,40.097638],"type":"Point"}
}