{
  "type": "Feature",
  "properties": {
    "addr:full":"1011 Mason St Vacaville CA 95688",
    "addr:housenumber":"1011",
    "addr:postcode":"95688",
    "addr:street":"Mason St",
    "iso:country":"US",
    "sg:address":"1011 Mason St",
    "sg:city":"Vacaville",
    "sg:classifiers":[
        {
            "category":"Home & Garden",
            "subcategory":"Building Materials",
            "type":"Retail Goods"
        }
    ],
    "sg:phone":"+1 707 451 0900",
    "sg:postcode":"95688",
    "sg:province":"CA",
    "sg:tags":[
        "shower",
        "screen",
        "door",
        "window",
        "enclosure"
    ],
    "sg:website":"http://www.westernglassandmirror.com",
    "wof:name":"Western Glass & Mirror",
    "wof:placetype":"venue"
},
  "geometry": {"coordinates":[-121.978588,38.354553],"type":"Point"}
}