{
  "type": "Feature",
  "properties": {
    "addr:full":"1551 S Novato Blvd Novato CA 94947",
    "addr:housenumber":"1551",
    "addr:postcode":"94947",
    "addr:street":"S Novato Blvd",
    "iso:country":"US",
    "sg:address":"1551 S Novato Blvd",
    "sg:city":"Novato",
    "sg:classifiers":[
        {
            "category":"Food & Beverages",
            "subcategory":"Specialty",
            "type":"Retail Goods"
        }
    ],
    "sg:phone":"+1 415 892 8373",
    "sg:postcode":"94947",
    "sg:province":"CA",
    "sg:tags":[
        "tea",
        "coffee"
    ],
    "wof:name":"Daily Grind",
    "wof:placetype":"venue"
},
  "geometry": {"coordinates":[-122.57029300000001,38.0985],"type":"Point"}
}