{
  "type": "Feature",
  "properties": {
    "iso:country":"US",
    "sg:address":"16200 E. Amber Valley Dr.",
    "sg:city":"Whittier",
    "sg:classifiers":[
        {
            "category":"Education",
            "subcategory":"School",
            "type":"Public Place"
        },
        {
            "category":"Health Services",
            "subcategory":"Chiropractor",
            "type":"Services"
        }
    ],
    "sg:phone":"+1 562 943 7125",
    "sg:postcode":"90604",
    "sg:province":"CA",
    "sg:tags":[
        "massage"
    ],
    "wof:name":"SCU Health Sciences",
    "wof:placetype":"venue"
},
  "geometry": {"coordinates":[-117.983317,33.921083],"type":"Point"}
}