{
  "type": "Feature",
  "properties": {
    "addr:full":"830 Torrance Blvd. Redondo Beach CA 90277",
    "addr:housenumber":"830",
    "addr:postcode":"90277",
    "addr:street":"Torrance Blvd.",
    "iso:country":"US",
    "sg:address":"830 Torrance Blvd.",
    "sg:city":"Redondo Beach",
    "sg:classifiers":[
        {
            "category":"Health Services",
            "subcategory":"Chiropractor",
            "type":"Services"
        }
    ],
    "sg:phone":"+1 310 316 2806",
    "sg:postcode":"90277",
    "sg:province":"CA",
    "sg:website":"www.royalhealth.us",
    "wof:name":"Marie Cavanaugh, DC",
    "wof:placetype":"venue"
},
  "geometry": {"coordinates":[-118.378238,33.838377],"type":"Point"}
}