{
  "type": "Feature",
  "properties": {
    "addr:full":"800 N Haven Ave Ontario CA 91764",
    "addr:housenumber":"800",
    "addr:postcode":"91764",
    "addr:street":"N Haven Ave",
    "iso:country":"US",
    "sg:address":"800 N Haven Ave",
    "sg:city":"Ontario",
    "sg:classifiers":[
        {
            "category":"Professional",
            "subcategory":"Lawyer & Legal Services",
            "type":"Services"
        }
    ],
    "sg:phone":"+1 909 466 9589",
    "sg:postcode":"91764",
    "sg:province":"CA",
    "sg:tags":[
        "attorney"
    ],
    "wof:name":"Smith & Garfunkel",
    "wof:placetype":"venue"
},
  "geometry": {"coordinates":[-117.57573499999999,34.070183],"type":"Point"}
}