{
  "type": "Feature",
  "properties": {
    "addr:full":"26545 State Hwy 18 Rimforest CA 92378",
    "addr:housenumber":"26545",
    "addr:postcode":"92378",
    "addr:street":"State Hwy 18",
    "iso:country":"US",
    "sg:address":"26545 State Hwy 18",
    "sg:city":"Rimforest",
    "sg:classifiers":[
        {
            "category":"Restaurant",
            "type":"Food & Drink"
        }
    ],
    "sg:phone":"+1 909 337 1212",
    "sg:postcode":"92378",
    "sg:province":"CA",
    "sg:tags":[
        "italian",
        "pizza"
    ],
    "sg:website":"theoriginalcottage.blogspot.com/",
    "wof:name":"Original Cottage the Family Restaurant",
    "wof:placetype":"venue"
},
  "geometry": {"coordinates":[-117.224351,34.229644],"type":"Point"}
}