{
  "type": "Feature",
  "properties": {
    "addr:full":"23731 Califa St Woodland Hills CA 91367",
    "addr:housenumber":"23731",
    "addr:postcode":"91367",
    "addr:street":"Califa St",
    "iso:country":"US",
    "sg:address":"23731 Califa St",
    "sg:city":"Woodland Hills",
    "sg:classifiers":[
        {
            "category":"Professional",
            "type":"Services"
        }
    ],
    "sg:phone":"+1 818 347 2032",
    "sg:postcode":"91367",
    "sg:province":"CA",
    "wof:name":"AMC Distributors",
    "wof:placetype":"venue"
},
  "geometry": {"coordinates":[-118.644143,34.177939],"type":"Point"}
}