{
  "type": "Feature",
  "properties": {
    "iso:country":"US",
    "sg:address":"222 E San Bernardino Rd",
    "sg:city":"Covina",
    "sg:classifiers":[
        {
            "category":"Retail",
            "subcategory":"Veterinary Services",
            "type":"Services"
        }
    ],
    "sg:phone":"+1 626 331 5374",
    "sg:postcode":"91723",
    "sg:province":"CA",
    "sg:tags":[
        "veterinarian"
    ],
    "sg:website":"http://www.covinaanimalhosp.com",
    "wof:name":"Ortmayer R Annette Dvm",
    "wof:placetype":"venue"
},
  "geometry": {"coordinates":[-117.88702499999999,34.090395],"type":"Point"}
}