{
  "type": "Feature",
  "properties": {
    "iso:country":"US",
    "sg:address":"5609 W Sunset Boulevard",
    "sg:city":"Los Angeles",
    "sg:classifiers":[
        {
            "category":"Shopping",
            "subcategory":"Tobacco",
            "type":"Retail Goods"
        }
    ],
    "sg:phone":"+1 323 962 3030",
    "sg:postcode":"90028",
    "sg:province":"CA",
    "sg:tags":[
        "shop"
    ],
    "wof:name":"Z Tobacco Shop",
    "wof:placetype":"venue"
},
  "geometry": {"coordinates":[-118.31173699999999,34.097991],"type":"Point"}
}