{
  "type": "Feature",
  "properties": {
    "iso:country":"US",
    "sg:address":"5646 Tulane St",
    "sg:city":"San Diego",
    "sg:classifiers":[
        {
            "category":"Real Estate",
            "subcategory":"Real Estate Agent",
            "type":"Services"
        }
    ],
    "sg:phone":"+1 858 453 4577",
    "sg:postcode":"92122",
    "sg:province":"CA",
    "wof:name":"Fowler Ray R & Mary Grace Co",
    "wof:placetype":"venue"
},
  "geometry": {"coordinates":[-117.216204,32.848006],"type":"Point"}
}