{
  "type": "Feature",
  "properties": {
    "addr:full":"20863 Stevens Creek Blvd. Suite 275 Cupertino CA 95014 ",
    "addr:housenumber":"20863",
    "addr:postcode":"95014",
    "addr:street":"Stevens Creek Blvd. Suite 275",
    "iso:country":"US",
    "sg:address":"20863 Stevens Creek Blvd. Suite 275",
    "sg:city":"Cupertino",
    "sg:classifiers":[
        {
            "category":"Professional",
            "subcategory":"Computer Services",
            "type":"Services"
        }
    ],
    "sg:postcode":"95014 ",
    "sg:province":"CA",
    "sg:website":"http://www.scalemp.com",
    "wof:name":"ScaleMP ",
    "wof:placetype":"venue"
},
  "geometry": {"coordinates":[-122.03791099999999,37.322875],"type":"Point"}
}