{
  "type": "Feature",
  "properties": {
    "iso:country":"US",
    "sg:address":"115 W Victoria St",
    "sg:city":"Long Beach",
    "sg:classifiers":[
        {
            "category":"Shopping",
            "subcategory":"Mobile Phones",
            "type":"Retail Goods"
        }
    ],
    "sg:phone":"+1 310 604 1142",
    "sg:postcode":"90805",
    "sg:province":"CA",
    "wof:name":"Advanced Wireless Cellular",
    "wof:placetype":"venue"
},
  "geometry": {"coordinates":[-118.203003,33.864799],"type":"Point"}
}