{
  "type": "Feature",
  "properties": {
    "addr:full":"23658 Ave 95 Terra Bella CA 93270",
    "addr:housenumber":"23658;95",
    "addr:postcode":"93270",
    "addr:street":"Ave",
    "iso:country":"US",
    "sg:address":"23658 Ave 95",
    "sg:city":"Terra Bella",
    "sg:classifiers":[
        {
            "category":"Government",
            "subcategory":"Fire Station",
            "type":"Public Place"
        }
    ],
    "sg:phone":"+1 559 535 4411",
    "sg:postcode":"93270",
    "sg:province":"CA",
    "sg:tags":[
        "county",
        "protection"
    ],
    "wof:name":"Terra Bella Fire Station",
    "wof:placetype":"venue"
},
  "geometry": {"coordinates":[-119.042773,35.962519],"type":"Point"}
}