{
  "type": "Feature",
  "properties": {
    "addr:full":"1417 Marcelina Ave Torrance CA 90501",
    "addr:housenumber":"1417",
    "addr:postcode":"90501",
    "addr:street":"Marcelina Ave",
    "iso:country":"US",
    "sg:address":"1417 Marcelina Ave",
    "sg:city":"Torrance",
    "sg:classifiers":[
        {
            "category":"Retail",
            "subcategory":"Repair Shop",
            "type":"Services"
        }
    ],
    "sg:phone":"+1 310 320 3674",
    "sg:postcode":"90501",
    "sg:province":"CA",
    "sg:tags":[
        "lock",
        "key",
        "locksmith"
    ],
    "wof:name":"Frank's Lock & Key",
    "wof:placetype":"venue"
},
  "geometry": {"coordinates":[-118.31500200000001,33.834],"type":"Point"}
}