{
  "type": "Feature",
  "properties": {
    "addr:full":"9716 S Main St Los Angeles CA 90003",
    "addr:housenumber":"9716",
    "addr:postcode":"90003",
    "addr:street":"S Main St",
    "iso:country":"US",
    "sg:address":"9716 S Main St",
    "sg:city":"Los Angeles",
    "sg:classifiers":[
        {
            "category":"Food & Beverages",
            "subcategory":"Liquor & Beverages",
            "type":"Retail Goods"
        }
    ],
    "sg:phone":"+1 323 756 4101",
    "sg:postcode":"90003",
    "sg:province":"CA",
    "wof:name":"J T Liquor",
    "wof:placetype":"venue"
},
  "geometry": {"coordinates":[-118.273799,33.947586],"type":"Point"}
}