{
  "type": "Feature",
  "properties": {
    "addr:full":"460 Everett Ave Palo Alto CA 94301",
    "addr:housenumber":"460",
    "addr:postcode":"94301",
    "addr:street":"Everett Ave",
    "iso:country":"US",
    "sg:address":"460 Everett Ave",
    "sg:city":"Palo Alto",
    "sg:classifiers":[
        {
            "category":"Professional",
            "subcategory":"Art Services",
            "type":"Services"
        }
    ],
    "sg:phone":"+1 650 328 3499",
    "sg:postcode":"94301",
    "sg:province":"CA",
    "sg:tags":[
        "artist"
    ],
    "wof:name":"Steve Curl Illustration",
    "wof:placetype":"venue"
},
  "geometry": {"coordinates":[-122.16170700000001,37.449729],"type":"Point"}
}