{
  "type": "Feature",
  "properties": {
    "iso:country":"US",
    "sg:address":"460 Everett Ave",
    "sg:city":"Palo Alto",
    "sg:classifiers":[
        {
            "category":"Professional",
            "subcategory":"Art Services",
            "type":"Services"
        }
    ],
    "sg:phone":"+1 650 328 3499",
    "sg:postcode":"94301",
    "sg:province":"CA",
    "sg:tags":[
        "artist"
    ],
    "wof:name":"Steve Curl Illustration",
    "wof:placetype":"venue"
},
  "geometry": {"coordinates":[-122.161707,37.449729],"type":"Point"}
}