{
  "type": "Feature",
  "properties": {
    "addr:full":"9095 Fallbrook Canyon Dr Corona CA 92883",
    "addr:housenumber":"9095",
    "addr:postcode":"92883",
    "addr:street":"Fallbrook Canyon Dr",
    "iso:country":"US",
    "sg:address":"9095 Fallbrook Canyon Dr",
    "sg:city":"Corona",
    "sg:classifiers":[
        {
            "category":"Real Estate",
            "subcategory":"Architect",
            "type":"Services"
        }
    ],
    "sg:phone":"+1 951 277 1363",
    "sg:postcode":"92883",
    "sg:province":"CA",
    "wof:name":"Cadjoy Drafting",
    "wof:placetype":"venue"
},
  "geometry": {"coordinates":[-117.499859,33.780966],"type":"Point"}
}