{
  "type": "Feature",
  "properties": {
    "addr:full":"6117 Ledgewood Ter Dublin CA 94568",
    "addr:housenumber":"6117",
    "addr:postcode":"94568",
    "addr:street":"Ledgewood Ter",
    "iso:country":"US",
    "sg:address":"6117 Ledgewood Ter",
    "sg:city":"Dublin",
    "sg:classifiers":[
        {
            "category":"Building & Trades",
            "subcategory":"Plumbing",
            "type":"Services"
        }
    ],
    "sg:phone":"+1 925 551 8340",
    "sg:postcode":"94568",
    "sg:province":"CA",
    "sg:tags":[
        "contractor"
    ],
    "wof:name":"Golden Bay Mechanical Co",
    "wof:placetype":"venue"
},
  "geometry": {"coordinates":[-121.867368,37.725671],"type":"Point"}
}