{
  "type": "Feature",
  "properties": {
    "addr:full":"3360 Wilshire Blvd Los Angeles CA 90010",
    "addr:housenumber":"3360",
    "addr:postcode":"90010",
    "addr:street":"Wilshire Blvd",
    "iso:country":"US",
    "sg:address":"3360 Wilshire Blvd",
    "sg:city":"Los Angeles",
    "sg:classifiers":[
        {
            "category":"Wholesale",
            "subcategory":"Non-durable Goods",
            "type":"Manufacturing & Wholesale Goods"
        }
    ],
    "sg:phone":"+1 213 387 1190",
    "sg:postcode":"90010",
    "sg:province":"CA",
    "wof:name":"Raf International Inc",
    "wof:placetype":"venue"
},
  "geometry": {"coordinates":[-118.29584800000001,34.061695],"type":"Point"}
}