{
  "type": "Feature",
  "properties": {
    "addr:full":"4394 University Pkwy San Bernardino CA 92407",
    "addr:housenumber":"4394",
    "addr:postcode":"92407",
    "addr:street":"University Pkwy",
    "iso:country":"US",
    "sg:address":"4394 University Pkwy",
    "sg:city":"San Bernardino",
    "sg:classifiers":[
        {
            "category":"Shopping",
            "type":"Retail Goods"
        }
    ],
    "sg:phone":"+1 909 473 7999",
    "sg:postcode":"92407",
    "sg:province":"CA",
    "sg:tags":[
        "mobile",
        "phone",
        "telephone",
        "cellular"
    ],
    "wof:name":"Cingular Wireless",
    "wof:placetype":"venue"
},
  "geometry": {"coordinates":[-117.33200100000001,34.167198],"type":"Point"}
}