{
  "type": "Feature",
  "properties": {
    "iso:country":"US",
    "sg:address":"1418 Santa Anita St.",
    "sg:city":"Oceanside",
    "sg:classifiers":[
        {
            "category":"Social Services",
            "subcategory":"Child Care",
            "type":"Services"
        }
    ],
    "sg:phone":"+1 760 845 8476",
    "sg:postcode":"92058",
    "sg:province":"CA",
    "sg:tags":[
        "day"
    ],
    "sg:website":"www.pinkelephantsnannies.com",
    "wof:name":"Pink Elephants Nannies",
    "wof:placetype":"venue"
},
  "geometry": {"coordinates":[-117.373981,33.218612],"type":"Point"}
}