{
  "type": "Feature",
  "properties": {
    "addr:full":"1257 Camino Del Rio S San Diego CA 92108",
    "addr:housenumber":"1257",
    "addr:postcode":"92108",
    "addr:street":"Camino Del Rio S",
    "iso:country":"US",
    "sg:address":"1257 Camino Del Rio S",
    "sg:city":"San Diego",
    "sg:classifiers":[
        {
            "category":"Banks & Credit Unions",
            "subcategory":"Financial Services",
            "type":"Services"
        }
    ],
    "sg:phone":"+1 619 291 4555",
    "sg:postcode":"92108",
    "sg:province":"CA",
    "sg:tags":[
        "broker",
        "mortgage"
    ],
    "sg:website":"www.mfgbanking.com",
    "wof:name":"Manhattan Financial Group",
    "wof:placetype":"venue"
},
  "geometry": {"coordinates":[-117.15205899999999,32.765521],"type":"Point"}
}