{
  "type": "Feature",
  "properties": {
    "iso:country":"US",
    "sg:address":"22701 Wood Lake Ln",
    "sg:city":"Lake Forest",
    "sg:classifiers":[
        {
            "category":"Professional",
            "subcategory":"Management & Consulting",
            "type":"Services"
        }
    ],
    "sg:phone":"+1 949 770 5264",
    "sg:postcode":"92630",
    "sg:province":"CA",
    "sg:tags":[
        "consultant",
        "business"
    ],
    "wof:name":"National Institute-Prevention",
    "wof:placetype":"venue"
},
  "geometry": {"coordinates":[-117.707422,33.63294],"type":"Point"}
}