{
  "type": "Feature",
  "properties": {
    "addr:full":"1231 Palm Ave Imperial Beach CA 91932",
    "addr:housenumber":"1231",
    "addr:postcode":"91932",
    "addr:street":"Palm Ave",
    "iso:country":"US",
    "sg:address":"1231 Palm Ave",
    "sg:city":"Imperial Beach",
    "sg:classifiers":[
        {
            "category":"Shopping",
            "subcategory":"Used Merchandise",
            "type":"Retail Goods"
        }
    ],
    "sg:phone":"+1 619 424 3844",
    "sg:postcode":"91932",
    "sg:province":"CA",
    "sg:tags":[
        "pawnbroker"
    ],
    "wof:name":"Park 'n Pawn & Jewelry",
    "wof:placetype":"venue"
},
  "geometry": {"coordinates":[-117.10700300000001,32.583802],"type":"Point"}
}