{
  "type": "Feature",
  "properties": {
    "iso:country":"US",
    "sg:address":"1190 S Victoria Ave",
    "sg:city":"Ventura",
    "sg:classifiers":[
        {
            "category":"Real Estate",
            "subcategory":"Real Estate Agent",
            "type":"Services"
        }
    ],
    "sg:phone":"+1 805 648 5051",
    "sg:postcode":"93003",
    "sg:province":"CA",
    "sg:website":"www.cbsocal.com",
    "wof:name":"Coldwell Banker",
    "wof:placetype":"venue"
},
  "geometry": {"coordinates":[-119.212271,34.265234],"type":"Point"}
}