{
  "type": "Feature",
  "properties": {
    "iso:country":"US",
    "sg:address":"H-Mart Irvine 2600 Alton Pkwy",
    "sg:city":"Irvine",
    "sg:classifiers":[
        {
            "category":"Shopping",
            "subcategory":"Florist",
            "type":"Retail Goods"
        }
    ],
    "sg:postcode":"92606",
    "sg:province":"CA",
    "sg:website":"www.zengardensfloral.com",
    "wof:name":"Zen Gardens Floral",
    "wof:placetype":"venue"
},
  "geometry": {"coordinates":[-117.833653,33.689524],"type":"Point"}
}