{
  "type": "Feature",
  "properties": {
    "iso:country":"US",
    "sg:address":"220 W G St",
    "sg:city":"San Diego",
    "sg:classifiers":[
        {
            "category":"Building & Trades",
            "subcategory":"Plumbing",
            "type":"Services"
        }
    ],
    "sg:phone":"+1 619 237 7222",
    "sg:postcode":"92101",
    "sg:province":"CA",
    "sg:tags":[
        "plumbing"
    ],
    "wof:name":"Hps Mechanical  Inc",
    "wof:placetype":"venue"
},
  "geometry": {"coordinates":[-117.165414,32.712617],"type":"Point"}
}