{
  "type": "Feature",
  "properties": {
    "addr:full":"26893 Bouquet Canyon Rd Santa Clarita CA 91350",
    "addr:housenumber":"26893",
    "addr:postcode":"91350",
    "addr:street":"Bouquet Canyon Rd",
    "iso:country":"US",
    "sg:address":"26893 Bouquet Canyon Rd",
    "sg:city":"Santa Clarita",
    "sg:classifiers":[
        {
            "category":"Building & Trades",
            "subcategory":"Electrical",
            "type":"Services"
        }
    ],
    "sg:phone":"+1 661 219 3283",
    "sg:postcode":"91350",
    "sg:province":"CA",
    "sg:tags":[
        "electrician"
    ],
    "sg:website":"www.santaclaritaelectricianandpl...",
    "wof:name":"David Electric and Plumbing",
    "wof:placetype":"venue"
},
  "geometry": {"coordinates":[-118.527295,34.434097],"type":"Point"}
}