{
  "type": "Feature",
  "properties": {
    "iso:country":"US",
    "sg:address":"5800 W Sunset Blvd",
    "sg:city":"Los Angeles",
    "sg:classifiers":[
        {
            "category":"Utilities",
            "subcategory":"Cable",
            "type":"Services"
        }
    ],
    "sg:phone":"+1 323 460 3889",
    "sg:postcode":"90028",
    "sg:province":"CA",
    "sg:tags":[
        "television"
    ],
    "wof:name":"Wgn Superstation Inc",
    "wof:placetype":"venue"
},
  "geometry": {"coordinates":[-118.317958,34.098048],"type":"Point"}
}