{
  "type": "Feature",
  "properties": {
    "addr:full":"130 E Carrillo St Santa Barbara CA 93101",
    "addr:housenumber":"130",
    "addr:postcode":"93101",
    "addr:street":"E Carrillo St",
    "iso:country":"US",
    "sg:address":"130 E Carrillo St",
    "sg:city":"Santa Barbara",
    "sg:classifiers":[
        {
            "category":"Professional",
            "subcategory":"Lawyer & Legal Services",
            "type":"Services"
        }
    ],
    "sg:phone":"+1 805 963 8906",
    "sg:postcode":"93101",
    "sg:province":"CA",
    "sg:tags":[
        "attorney"
    ],
    "wof:name":"Egenolf Associates",
    "wof:placetype":"venue"
},
  "geometry": {"coordinates":[-119.700474,34.422616],"type":"Point"}
}