{
  "type": "Feature",
  "properties": {
    "iso:country":"US",
    "sg:address":"880 Marie Angela Dr",
    "sg:city":"Tracy",
    "sg:classifiers":[
        {
            "category":"Real Estate",
            "subcategory":"Real Estate Agent",
            "type":"Services"
        }
    ],
    "sg:phone":"+1 209 835 6345",
    "sg:postcode":"95377",
    "sg:province":"CA",
    "wof:name":"Ed Wertman Real Estate",
    "wof:placetype":"venue"
},
  "geometry": {"coordinates":[-121.460133,37.722569],"type":"Point"}
}