{
  "type": "Feature",
  "properties": {
    "addr:full":"2388 E Artesia Blvd Long Beach CA 90805",
    "addr:housenumber":"2388",
    "addr:postcode":"90805",
    "addr:street":"E Artesia Blvd",
    "iso:country":"US",
    "sg:address":"2388 E Artesia Blvd",
    "sg:city":"Long Beach",
    "sg:classifiers":[
        {
            "category":"Wholesale",
            "subcategory":"Auto Parts",
            "type":"Manufacturing & Wholesale Goods"
        }
    ],
    "sg:phone":"+1 562 422 9095",
    "sg:postcode":"90805",
    "sg:province":"CA",
    "sg:tags":[
        "rubber",
        "automobile",
        "plastic",
        "supply"
    ],
    "wof:name":"Linking Focus Inc",
    "wof:placetype":"venue"
},
  "geometry": {"coordinates":[-118.16033,33.874607],"type":"Point"}
}