{
  "type": "Feature",
  "properties": {
    "addr:full":"39 Peach Ct Santa Rosa CA 95407",
    "addr:housenumber":"39",
    "addr:postcode":"95407",
    "addr:street":"Peach Ct",
    "iso:country":"US",
    "sg:address":"39 Peach Ct",
    "sg:city":"Santa Rosa",
    "sg:classifiers":[
        {
            "category":"Building & Trades",
            "subcategory":"Construction",
            "type":"Services"
        }
    ],
    "sg:phone":"+1 707 546 5059",
    "sg:postcode":"95407",
    "sg:province":"CA",
    "sg:tags":[
        "remodeling",
        "general"
    ],
    "wof:name":"West Design Group",
    "wof:placetype":"venue"
},
  "geometry": {"coordinates":[-122.71836399999999,38.423944],"type":"Point"}
}