{
  "type": "Feature",
  "properties": {
    "addr:full":"275 S Prospectors Rd Diamond Bar CA 91765",
    "addr:housenumber":"275",
    "addr:postcode":"91765",
    "addr:street":"S Prospectors Rd",
    "iso:country":"US",
    "sg:address":"275 S Prospectors Rd",
    "sg:city":"Diamond Bar",
    "sg:classifiers":[
        {
            "category":"Freight",
            "type":"Transportation"
        }
    ],
    "sg:phone":"+1 909 860 3660",
    "sg:postcode":"91765",
    "sg:province":"CA",
    "sg:tags":[
        "paper",
        "general"
    ],
    "wof:name":"National Self Storage",
    "wof:placetype":"venue"
},
  "geometry": {"coordinates":[-117.81410099999999,34.020994],"type":"Point"}
}