{
  "type": "Feature",
  "properties": {
    "addr:full":"2770 Eaton Rd Chico CA 95973",
    "addr:housenumber":"2770",
    "addr:postcode":"95973",
    "addr:street":"Eaton Rd",
    "iso:country":"US",
    "sg:address":"2770 Eaton Rd",
    "sg:city":"Chico",
    "sg:classifiers":[
        {
            "category":"Real Estate",
            "subcategory":"Real Estate Operator",
            "type":"Services"
        }
    ],
    "sg:phone":"+1 530 343 2499",
    "sg:postcode":"95973",
    "sg:province":"CA",
    "sg:tags":[
        "apartment"
    ],
    "wof:name":"Eastwood Court Apartments",
    "wof:placetype":"venue"
},
  "geometry": {"coordinates":[-121.831379,39.76948],"type":"Point"}
}