{
  "type": "Feature",
  "properties": {
    "addr:full":"350 S Beverly Dr Ste 360 Beverly Hills CA 90212",
    "addr:housenumber":"350",
    "addr:postcode":"90212",
    "addr:street":"S Beverly Dr Ste 360;Hills Ca",
    "iso:country":"US",
    "sg:address":"350 S Beverly Dr Ste 360",
    "sg:city":"Beverly Hills",
    "sg:classifiers":[
        {
            "category":"Banks & Credit Unions",
            "subcategory":"Investment Brokerage",
            "type":"Services"
        }
    ],
    "sg:phone":"+1 424 239 1034",
    "sg:postcode":"90212",
    "sg:province":"CA",
    "sg:tags":[
        "investing"
    ],
    "wof:name":"Lourd Capital Management",
    "wof:placetype":"venue"
},
  "geometry": {"coordinates":[-118.39892399999999,34.073977],"type":"Point"}
}