{
  "type": "Feature",
  "properties": {
    "iso:country":"US",
    "sg:address":"8934 Frenchtown Exn",
    "sg:city":"Brownsville",
    "sg:classifiers":[
        {
            "category":"Professional",
            "subcategory":"Engineering",
            "type":"Services"
        }
    ],
    "sg:phone":"+1 530 675 2323",
    "sg:postcode":"95919",
    "sg:province":"CA",
    "sg:tags":[
        "general",
        "contractor"
    ],
    "wof:name":"Escheman Construction Co",
    "wof:placetype":"venue"
},
  "geometry": {"coordinates":[-121.284968,39.451458],"type":"Point"}
}