{
  "type": "Feature",
  "properties": {
    "addr:full":"8934 Frenchtown Exn Brownsville CA 95919",
    "addr:housenumber":"8934",
    "addr:postcode":"95919",
    "addr:street":"Frenchtown Exn",
    "iso:country":"US",
    "sg:address":"8934 Frenchtown Exn",
    "sg:city":"Brownsville",
    "sg:classifiers":[
        {
            "category":"Professional",
            "subcategory":"Engineering",
            "type":"Services"
        }
    ],
    "sg:phone":"+1 530 675 2323",
    "sg:postcode":"95919",
    "sg:province":"CA",
    "sg:tags":[
        "general",
        "contractor"
    ],
    "wof:name":"Escheman Construction Co",
    "wof:placetype":"venue"
},
  "geometry": {"coordinates":[-121.28496800000001,39.451458],"type":"Point"}
}