{
  "type": "Feature",
  "properties": {
    "addr:full":"28310 Industrial Blvd Hayward CA 94545",
    "addr:housenumber":"28310",
    "addr:postcode":"94545",
    "addr:street":"Industrial Blvd",
    "iso:country":"US",
    "sg:address":"28310 Industrial Blvd",
    "sg:city":"Hayward",
    "sg:classifiers":[
        {
            "category":"Wholesale",
            "subcategory":"Machinery & Supplies",
            "type":"Manufacturing & Wholesale Goods"
        }
    ],
    "sg:phone":"+1 510 782 5640",
    "sg:postcode":"94545",
    "sg:province":"CA",
    "sg:tags":[
        "sandblasting"
    ],
    "wof:name":"Gordon Sand Co",
    "wof:placetype":"venue"
},
  "geometry": {"coordinates":[-122.090166,37.616754],"type":"Point"}
}