{
  "type": "Feature",
  "properties": {
    "addr:full":"6046 el Tordo Rancho Santa Fe CA 92067",
    "addr:housenumber":"6046",
    "addr:postcode":"92067",
    "addr:street":"El Tordo",
    "iso:country":"US",
    "sg:address":"6046 el Tordo",
    "sg:city":"Rancho Santa Fe",
    "sg:classifiers":[
        {
            "category":"Real Estate",
            "subcategory":"Architect",
            "type":"Services"
        }
    ],
    "sg:phone":"+1 858 756 2526",
    "sg:postcode":"92067",
    "sg:province":"CA",
    "wof:name":"John Jensen",
    "wof:placetype":"venue"
},
  "geometry": {"coordinates":[-117.205589,33.019223],"type":"Point"}
}