{
  "type": "Feature",
  "properties": {
    "addr:full":"8386 Capwell Dr Oakland CA 94621",
    "addr:housenumber":"8386",
    "addr:postcode":"94621",
    "addr:street":"Capwell Dr",
    "iso:country":"US",
    "sg:address":"8386 Capwell Dr",
    "sg:city":"Oakland",
    "sg:classifiers":[
        {
            "category":"Wholesale",
            "subcategory":"Office Equipment",
            "type":"Manufacturing & Wholesale Goods"
        },
        {
            "category":"Professional",
            "subcategory":"Printing & Photocopies",
            "type":"Services"
        },
        {
            "category":"Shopping",
            "subcategory":"Computers & Home Electronics",
            "type":"Retail Goods"
        }
    ],
    "sg:phone":"+1 510 567 1600",
    "sg:postcode":"94621",
    "sg:province":"CA",
    "sg:tags":[
        "scanning",
        "printer",
        "supply",
        "screen",
        "plotting",
        "furniture"
    ],
    "sg:website":"http://www.clampswing.com",
    "wof:name":"Clamp Swing Pricing Co., Inc.",
    "wof:placetype":"venue"
},
  "geometry": {"coordinates":[-122.200592,37.735943],"type":"Point"}
}