{
  "type": "Feature",
  "properties": {
    "addr:full":"5867 Crocker St Los Angeles CA 90003",
    "addr:housenumber":"5867",
    "addr:postcode":"90003",
    "addr:street":"Crocker St",
    "iso:country":"US",
    "sg:address":"5867 Crocker St",
    "sg:city":"Los Angeles",
    "sg:classifiers":[
        {
            "category":"Manufacturing",
            "subcategory":"Printing",
            "type":"Manufacturing & Wholesale Goods"
        }
    ],
    "sg:phone":"+1 323 231 7225",
    "sg:postcode":"90003",
    "sg:province":"CA",
    "sg:tags":[
        "screen"
    ],
    "wof:name":"Chavez Factory",
    "wof:placetype":"venue"
},
  "geometry": {"coordinates":[-118.26859,33.987595],"type":"Point"}
}