{
  "type": "Feature",
  "properties": {
    "addr:full":"910 S Los Angeles St Los Angeles CA 90015",
    "addr:housenumber":"910",
    "addr:postcode":"90015",
    "addr:street":"S;Angeles St",
    "iso:country":"US",
    "sg:address":"910 S Los Angeles St",
    "sg:city":"Los Angeles",
    "sg:classifiers":[
        {
            "category":"Wholesale",
            "subcategory":"Apparel",
            "type":"Manufacturing & Wholesale Goods"
        }
    ],
    "sg:phone":"+1 213 488 0868",
    "sg:postcode":"90015",
    "sg:province":"CA",
    "wof:name":"Streetwise Sales",
    "wof:placetype":"venue"
},
  "geometry": {"coordinates":[-118.25565,34.03963],"type":"Point"}
}