{
  "type": "Feature",
  "properties": {
    "iso:country":"US",
    "sg:address":"502 E Mission Rd",
    "sg:city":"San Marcos",
    "sg:classifiers":[
        {
            "category":"Bars & Pubs",
            "type":"Food & Drink"
        }
    ],
    "sg:phone":"+1 760 471 2939",
    "sg:postcode":"92069",
    "sg:province":"CA",
    "sg:tags":[
        "lounge",
        "cocktail"
    ],
    "wof:name":"Cowshed",
    "wof:placetype":"venue"
},
  "geometry": {"coordinates":[-117.149843,33.144998],"type":"Point"}
}