{
  "type": "Feature",
  "properties": {
    "iso:country":"US",
    "sg:address":"1646 Stanford Ave",
    "sg:city":"Menlo Park",
    "sg:classifiers":[
        {
            "category":"Wholesale",
            "subcategory":"Chemicals & Plastics",
            "type":"Manufacturing & Wholesale Goods"
        }
    ],
    "sg:phone":"+1 650 723 6903",
    "sg:postcode":"94025",
    "sg:province":"CA",
    "sg:tags":[
        "conditioner",
        "tank",
        "septic"
    ],
    "wof:name":"Conkey & Co",
    "wof:placetype":"venue"
},
  "geometry": {"coordinates":[-122.191782,37.439206],"type":"Point"}
}