{
  "type": "Feature",
  "properties": {
    "addr:full":"1855 41st Ave Capitola CA 95010",
    "addr:housenumber":"1855",
    "addr:postcode":"95010",
    "addr:street":"41St Ave",
    "iso:country":"US",
    "sg:address":"1855 41st Ave",
    "sg:city":"Capitola",
    "sg:classifiers":[
        {
            "category":"Shopping",
            "subcategory":"Clothing, Apparel, & Fashions",
            "type":"Retail Goods"
        }
    ],
    "sg:phone":"+1 831 479 4971",
    "sg:postcode":"95010",
    "sg:province":"CA",
    "sg:tags":[
        "rental",
        "tuxedo",
        "men's",
        "sale",
        "wear",
        "clothing",
        "formal"
    ],
    "sg:website":"http://www.menswearhouse.com",
    "wof:name":"The Men's Wearhouse",
    "wof:placetype":"venue"
},
  "geometry": {"coordinates":[-121.965019,36.975535],"type":"Point"}
}