{
  "type": "Feature",
  "properties": {
    "iso:country":"US",
    "sg:address":"18120 Bollinger Canyon Rd",
    "sg:city":"San Ramon",
    "sg:classifiers":[
        {
            "category":"Autos & Motor Vehicles",
            "subcategory":"Automobile Sales",
            "type":"Retail Goods"
        }
    ],
    "sg:phone":"+1 925 838 7822",
    "sg:postcode":"94583",
    "sg:province":"CA",
    "wof:name":"Honest Bills Automotives",
    "wof:placetype":"venue"
},
  "geometry": {"coordinates":[-121.996765,37.775051],"type":"Point"}
}