{
  "type": "Feature",
  "properties": {
    "iso:country":"US",
    "sg:address":"5530 Dunsmuir Ave",
    "sg:city":"Dunsmuir",
    "sg:classifiers":[
        {
            "category":"Government",
            "subcategory":"Post Office",
            "type":"Public Place"
        }
    ],
    "sg:phone":"+1 530 235 0338",
    "sg:postcode":"96025",
    "sg:province":"CA",
    "wof:name":"US Post Office",
    "wof:placetype":"venue"
},
  "geometry": {"coordinates":[-122.271584,41.212868],"type":"Point"}
}