{
  "type": "Feature",
  "properties": {
    "addr:full":"11858 Mile Dr Nevada City CA 95959",
    "addr:housenumber":"11858",
    "addr:postcode":"95959",
    "addr:street":"Mile Dr",
    "iso:country":"US",
    "sg:address":"11858 Mile Dr",
    "sg:city":"Nevada City",
    "sg:classifiers":[
        {
            "category":"Professional",
            "subcategory":"Management & Consulting",
            "type":"Services"
        }
    ],
    "sg:phone":"+1 530 265 2022",
    "sg:postcode":"95959",
    "sg:province":"CA",
    "sg:tags":[
        "consultant",
        "business"
    ],
    "wof:name":"Half Moon Bay Technologies",
    "wof:placetype":"venue"
},
  "geometry": {"coordinates":[-120.8845,39.309045],"type":"Point"}
}