{
  "type": "Feature",
  "properties": {
    "addr:full":"39767 Big Bear Blvd Big Bear Lake CA 92315",
    "addr:housenumber":"39767",
    "addr:postcode":"92315",
    "addr:street":"Big Bear Blvd",
    "iso:country":"US",
    "sg:address":"39767 Big Bear Blvd",
    "sg:city":"Big Bear Lake",
    "sg:classifiers":[
        {
            "category":"Shopping",
            "subcategory":"Bicycles & Sporting Goods",
            "type":"Retail Goods"
        }
    ],
    "sg:phone":"+1 909 866 5924",
    "sg:postcode":"92315",
    "sg:province":"CA",
    "sg:tags":[
        "equipment",
        "skiing"
    ],
    "wof:name":"Johnny's Ski & Board House",
    "wof:placetype":"venue"
},
  "geometry": {"coordinates":[-116.93576,34.238457],"type":"Point"}
}