{
  "type": "Feature",
  "properties": {
    "iso:country":"US",
    "sg:address":"2400 Coffee Rd",
    "sg:city":"Modesto",
    "sg:classifiers":[
        {
            "category":"Food & Beverages",
            "subcategory":"Groceries & Convenience Stores",
            "type":"Retail Goods"
        }
    ],
    "sg:phone":"+1 209 530 9211",
    "sg:postcode":"95355",
    "sg:province":"CA",
    "wof:name":"R & N Stores Inc",
    "wof:placetype":"venue"
},
  "geometry": {"coordinates":[-120.975998,37.676399],"type":"Point"}
}