{
  "type": "Feature",
  "properties": {
    "iso:country":"US",
    "sg:address":"138 W Branch St",
    "sg:city":"Arroyo Grande",
    "sg:classifiers":[
        {
            "category":"Personal",
            "type":"Services"
        }
    ],
    "sg:phone":"+1 805 481 0200",
    "sg:postcode":"93420",
    "sg:province":"CA",
    "sg:tags":[
        "therapist",
        "massage"
    ],
    "wof:name":"Barbara Poulsen",
    "wof:placetype":"venue"
},
  "geometry": {"coordinates":[-120.579581,35.123061],"type":"Point"}
}