{
  "type": "Feature",
  "properties": {
    "iso:country":"US",
    "sg:address":"624 Mariposa Ave",
    "sg:city":"Oakland",
    "sg:classifiers":[
        {
            "category":"Building & Trades",
            "subcategory":"Electrical",
            "type":"Services"
        }
    ],
    "sg:phone":"+1 650 757 2967",
    "sg:postcode":"94610",
    "sg:province":"CA",
    "sg:tags":[
        "electric",
        "contractor"
    ],
    "wof:name":"Bay Electric",
    "wof:placetype":"venue"
},
  "geometry": {"coordinates":[-122.24915799999999,37.820559],"type":"Point"}
}