{
  "type": "Feature",
  "properties": {
    "addr:full":"8245 E Santa Ana Canyon Rd Anaheim CA 92808",
    "addr:housenumber":"8245",
    "addr:postcode":"92808",
    "addr:street":"E Santa Ana Canyon Rd",
    "iso:country":"US",
    "sg:address":"8245 E Santa Ana Canyon Rd",
    "sg:city":"Anaheim",
    "sg:classifiers":[
        {
            "category":"Restaurant",
            "type":"Food & Drink"
        }
    ],
    "sg:menulink":"http://www.allmenus.com/ca/anaheim-santa-ana-garden-grove/168808-el-pollo-loco/menu/",
    "sg:phone":"+1 714 921 4633",
    "sg:postcode":"92808",
    "sg:province":"CA",
    "sg:tags":[
        "american",
        "mexican",
        "tex-mex"
    ],
    "wof:name":"El Pollo Loco",
    "wof:placetype":"venue"
},
  "geometry": {"coordinates":[-117.745867,33.86737],"type":"Point"}
}