{
  "type": "Feature",
  "properties": {
    "iso:country":"US",
    "sg:address":"4070 Bridge St",
    "sg:city":"Fair Oaks",
    "sg:classifiers":[
        {
            "category":"Education",
            "subcategory":"Special Training",
            "type":"Public Place"
        }
    ],
    "sg:phone":"+1 916 967 0431",
    "sg:postcode":"95628",
    "sg:province":"CA",
    "sg:tags":[
        "self",
        "motivational",
        "improvement"
    ],
    "wof:name":"Whitefeather Basinger & Assoc",
    "wof:placetype":"venue"
},
  "geometry": {"coordinates":[-121.268006,38.639877],"type":"Point"}
}