{
  "type": "Feature",
  "properties": {
    "addr:full":"31 Geary Ave Fairfax CA 94930",
    "addr:housenumber":"31",
    "addr:postcode":"94930",
    "addr:street":"Geary Ave",
    "iso:country":"US",
    "sg:address":"31 Geary Ave",
    "sg:city":"Fairfax",
    "sg:classifiers":[
        {
            "category":"Building & Trades",
            "subcategory":"Landscaping Services",
            "type":"Services"
        }
    ],
    "sg:phone":"+1 415 302 0762",
    "sg:postcode":"94930",
    "sg:province":"CA",
    "wof:name":"Toms Tree Care",
    "wof:placetype":"venue"
},
  "geometry": {"coordinates":[-122.58748799999999,37.989454],"type":"Point"}
}