{
  "type": "Feature",
  "properties": {
    "iso:country":"US",
    "sg:address":"3304 W Burbank Blvd",
    "sg:city":"Burbank",
    "sg:classifiers":[
        {
            "category":"Freight",
            "type":"Transportation"
        }
    ],
    "sg:phone":"+1 818 566 1256",
    "sg:postcode":"91505",
    "sg:province":"CA",
    "sg:tags":[
        "courier"
    ],
    "sg:website":"www.icdelivers.com",
    "wof:name":"Independent Courier",
    "wof:placetype":"venue"
},
  "geometry": {"coordinates":[-118.346711,34.175793],"type":"Point"}
}