{
  "type": "Feature",
  "properties": {
    "iso:country":"US",
    "sg:address":"13925 Leadwell St",
    "sg:city":"Van Nuys",
    "sg:classifiers":[
        {
            "category":"Communications",
            "subcategory":"Film & Video Production",
            "type":"Services"
        }
    ],
    "sg:phone":"+1 818 563 2230",
    "sg:postcode":"91405",
    "sg:province":"CA",
    "sg:tags":[
        "editing",
        "tape"
    ],
    "wof:name":"Post Wanted",
    "wof:placetype":"venue"
},
  "geometry": {"coordinates":[-118.438609,34.203917],"type":"Point"}
}