{
  "type": "Feature",
  "properties": {
    "addr:full":"10801 National Blvd Ste 106 Los Angeles CA 90064",
    "addr:housenumber":"10801",
    "addr:postcode":"90064",
    "addr:street":"National Blvd Ste 106",
    "iso:country":"US",
    "sg:address":"10801 National Blvd Ste 106",
    "sg:city":"Los Angeles",
    "sg:classifiers":[
        {
            "category":"Professional",
            "subcategory":"Lawyer & Legal Services",
            "type":"Services"
        }
    ],
    "sg:phone":"+1 323 932 9320",
    "sg:postcode":"90064",
    "sg:province":"CA",
    "wof:name":"Law Offices of Gordon & Gordon",
    "wof:placetype":"venue"
},
  "geometry": {"coordinates":[-118.420362,34.031294],"type":"Point"}
}