{
  "type": "Feature",
  "properties": {
    "iso:country":"US",
    "sg:address":"13034 Los Nietos Rd",
    "sg:city":"Santa Fe Springs",
    "sg:classifiers":[
        {
            "category":"Manufacturing",
            "subcategory":"Printing",
            "type":"Manufacturing & Wholesale Goods"
        }
    ],
    "sg:phone":"+1 562 944 6548",
    "sg:postcode":"90670",
    "sg:province":"CA",
    "sg:tags":[
        "commercial"
    ],
    "wof:name":"Print Shop",
    "wof:placetype":"venue"
},
  "geometry": {"coordinates":[-118.054745,33.945994],"type":"Point"}
}