{
  "type": "Feature",
  "properties": {
    "addr:full":"2333 Shuttle Dr Atwater CA 95301",
    "addr:housenumber":"2333",
    "addr:postcode":"95301",
    "addr:street":"Shuttle Dr",
    "iso:country":"US",
    "sg:address":"2333 Shuttle Dr",
    "sg:city":"Atwater",
    "sg:classifiers":[
        {
            "category":"Professional",
            "subcategory":"Testing Lab",
            "type":"Services"
        }
    ],
    "sg:phone":"+1 209 384 2930",
    "sg:postcode":"95301",
    "sg:province":"CA",
    "sg:tags":[
        "laboratory"
    ],
    "wof:name":"Castle Analytical Laboratory",
    "wof:placetype":"venue"
},
  "geometry": {"coordinates":[-120.563636,37.359137],"type":"Point"}
}