{
  "type": "Feature",
  "properties": {
    "addr:full":"2300 16th St San Francisco CA 94103",
    "addr:housenumber":"2300",
    "addr:postcode":"94103",
    "addr:street":"16Th St",
    "iso:country":"US",
    "sg:address":"2300 16th St",
    "sg:city":"San Francisco",
    "sg:classifiers":[
        {
            "category":"Food & Beverages",
            "subcategory":"Bakery",
            "type":"Retail Goods"
        }
    ],
    "sg:phone":"+1 415 861 2802",
    "sg:postcode":"94103",
    "sg:province":"CA",
    "sg:tags":[
        "bagel"
    ],
    "wof:name":"Noah's Bagels",
    "wof:placetype":"venue"
},
  "geometry": {"coordinates":[-122.40997400000001,37.76572],"type":"Point"}
}