{
  "type": "Feature",
  "properties": {
    "addr:full":"103 W Harding Way Stockton CA 95204",
    "addr:housenumber":"103",
    "addr:postcode":"95204",
    "addr:street":"W Harding Way",
    "iso:country":"US",
    "sg:address":"103 W Harding Way",
    "sg:city":"Stockton",
    "sg:classifiers":[
        {
            "category":"Restaurant",
            "type":"Food & Drink"
        }
    ],
    "sg:phone":"+1 209 467 3825",
    "sg:postcode":"95204",
    "sg:province":"CA",
    "wof:name":"Duck Nook",
    "wof:placetype":"venue"
},
  "geometry": {"coordinates":[-121.297854,37.96691],"type":"Point"}
}