{
  "type": "Feature",
  "properties": {
    "iso:country":"US",
    "sg:address":"2595 N Fair Oaks Ave",
    "sg:city":"Altadena",
    "sg:classifiers":[
        {
            "category":"Arts & Performance",
            "subcategory":"Theater",
            "type":"Entertainment"
        }
    ],
    "sg:phone":"+1 626 797 5411",
    "sg:postcode":"91001",
    "sg:province":"CA",
    "sg:tags":[
        "equipment",
        "theatrical",
        "supply"
    ],
    "wof:name":"Gil Draper Prop",
    "wof:placetype":"venue"
},
  "geometry": {"coordinates":[-118.149742,34.1895],"type":"Point"}
}