{
  "type": "Feature",
  "properties": {
    "iso:country":"US",
    "sg:address":"660 S Joyce Ave",
    "sg:city":"Rialto",
    "sg:classifiers":[
        {
            "category":"Wholesale",
            "subcategory":"Computers",
            "type":"Manufacturing & Wholesale Goods"
        }
    ],
    "sg:phone":"+1 909 820 3132",
    "sg:postcode":"92376",
    "sg:province":"CA",
    "sg:tags":[
        "equipment"
    ],
    "wof:name":"Mendez Computers",
    "wof:placetype":"venue"
},
  "geometry": {"coordinates":[-117.362106,34.089014],"type":"Point"}
}