{
  "type": "Feature",
  "properties": {
    "iso:country":"US",
    "sg:address":"6676 Mission St",
    "sg:city":"Daly City",
    "sg:classifiers":[
        {
            "category":"Banks & Credit Unions",
            "subcategory":"Financial Services",
            "type":"Services"
        }
    ],
    "sg:phone":"+1 650 758 1435",
    "sg:postcode":"94014",
    "sg:province":"CA",
    "sg:tags":[
        "broker",
        "mortgage"
    ],
    "wof:name":"Capital Realty & Investme",
    "wof:placetype":"venue"
},
  "geometry": {"coordinates":[-122.462997,37.701698],"type":"Point"}
}