{
  "type": "Feature",
  "properties": {
    "iso:country":"US",
    "sg:address":"11020 Balboa Blvd",
    "sg:city":"Granada Hills",
    "sg:classifiers":[
        {
            "category":"Health Services",
            "subcategory":"Chiropractor",
            "type":"Services"
        }
    ],
    "sg:phone":"+1 818 360 1967",
    "sg:postcode":"91344",
    "sg:province":"CA",
    "wof:name":"Sovetky Chiropractic",
    "wof:placetype":"venue"
},
  "geometry": {"coordinates":[-118.502143,34.26984],"type":"Point"}
}