{
  "type": "Feature",
  "properties": {
    "iso:country":"US",
    "sg:address":"40869 Sierra Dr",
    "sg:city":"Three Rivers",
    "sg:classifiers":[
        {
            "category":"Restaurant",
            "type":"Food & Drink"
        }
    ],
    "sg:phone":"+1 559 561 7283",
    "sg:postcode":"93271",
    "sg:province":"CA",
    "wof:name":"Serrano's Mexican Restaurant",
    "wof:placetype":"venue"
},
  "geometry": {"coordinates":[-118.916645,36.421961],"type":"Point"}
}