{
  "type": "Feature",
  "properties": {
    "addr:full":"100 Glen Eagle Way Vacaville CA 95688",
    "addr:housenumber":"100",
    "addr:postcode":"95688",
    "addr:street":"Glen Eagle Way",
    "iso:country":"US",
    "sg:address":"100 Glen Eagle Way",
    "sg:city":"Vacaville",
    "sg:classifiers":[
        {
            "category":"Building & Trades",
            "subcategory":"Construction",
            "type":"Services"
        }
    ],
    "sg:phone":"+1 707 592 3072",
    "sg:postcode":"95688",
    "sg:province":"CA",
    "sg:tags":[
        "hanging",
        "contractor"
    ],
    "wof:name":"Custom Painting By Tim Fuller",
    "wof:placetype":"venue"
},
  "geometry": {"coordinates":[-121.977642,38.386905],"type":"Point"}
}