{
  "type": "Feature",
  "properties": {
    "iso:country":"US",
    "sg:address":"863 Cave Valley Rd",
    "sg:city":"Cool",
    "sg:classifiers":[
        {
            "category":"Place Of Worship",
            "subcategory":"Church",
            "type":"Public Place"
        },
        {
            "category":"Place Of Worship",
            "type":"Public Place"
        }
    ],
    "sg:phone":"+1 530 885 4385",
    "sg:postcode":"95614",
    "sg:province":"CA",
    "sg:tags":[
        "churches-non-denominational",
        "christ",
        "churches-community"
    ],
    "sg:website":"http://www.coolchurch.org",
    "wof:name":"Cool Community Church",
    "wof:placetype":"venue"
},
  "geometry": {"coordinates":[-121.02249,38.873243],"type":"Point"}
}