{
  "type": "Feature",
  "properties": {
    "addr:full":"558 Seminary St Napa CA 94559",
    "addr:housenumber":"558",
    "addr:postcode":"94559",
    "addr:street":"Seminary St",
    "iso:country":"US",
    "sg:address":"558 Seminary St",
    "sg:city":"Napa",
    "sg:classifiers":[
        {
            "category":"Building & Trades",
            "subcategory":"Construction",
            "type":"Services"
        }
    ],
    "sg:phone":"+1 707 334 7001",
    "sg:postcode":"94559",
    "sg:province":"CA",
    "sg:tags":[
        "contractor"
    ],
    "wof:name":"Norcal Masonry",
    "wof:placetype":"venue"
},
  "geometry": {"coordinates":[-122.29167,38.293081],"type":"Point"}
}