{
  "type": "Feature",
  "properties": {
    "addr:full":"15845 Tulsa St Granada Hills CA 91344",
    "addr:housenumber":"15845",
    "addr:postcode":"91344",
    "addr:street":"Tulsa St",
    "iso:country":"US",
    "sg:address":"15845 Tulsa St",
    "sg:city":"Granada Hills",
    "sg:classifiers":[
        {
            "category":"Banks & Credit Unions",
            "subcategory":"Bank",
            "type":"Services"
        }
    ],
    "sg:phone":"+1 818 832 0896",
    "sg:postcode":"91344",
    "sg:province":"CA",
    "sg:tags":[
        "loan",
        "processing",
        "center",
        "mortgage"
    ],
    "wof:name":"Lending Solutions",
    "wof:placetype":"venue"
},
  "geometry": {"coordinates":[-118.47803,34.268319],"type":"Point"}
}