{
  "type": "Feature",
  "properties": {
    "addr:full":"23091 Del Lago Dr Laguna Hills CA 92653",
    "addr:housenumber":"23091",
    "addr:postcode":"92653",
    "addr:street":"Del Lago Dr",
    "iso:country":"US",
    "sg:address":"23091 Del Lago Dr",
    "sg:city":"Laguna Hills",
    "sg:classifiers":[
        {
            "category":"Arts & Performance",
            "subcategory":"Arts Center",
            "type":"Entertainment"
        }
    ],
    "sg:phone":"+1 949 360 4233",
    "sg:postcode":"92653",
    "sg:province":"CA",
    "sg:tags":[
        "performing"
    ],
    "sg:website":"www.classicalballetacademy.com",
    "wof:name":"Dmitri Kulev Classical Ballet Academy",
    "wof:placetype":"venue"
},
  "geometry": {"coordinates":[-117.72714999999999,33.627127],"type":"Point"}
}