{
  "type": "Feature",
  "properties": {
    "addr:full":"14455 Ventura Blvd Sherman Oaks CA 91423",
    "addr:housenumber":"14455",
    "addr:postcode":"91423",
    "addr:street":"Ventura Blvd",
    "iso:country":"US",
    "sg:address":"14455 Ventura Blvd",
    "sg:city":"Sherman Oaks",
    "sg:classifiers":[
        {
            "category":"Professional",
            "subcategory":"Accounting & Tax Preparation",
            "type":"Services"
        }
    ],
    "sg:phone":"+1 818 981 4226",
    "sg:postcode":"91423",
    "sg:province":"CA",
    "sg:tags":[
        "accountant"
    ],
    "wof:name":"White Zuckerman & Warsavsky",
    "wof:placetype":"venue"
},
  "geometry": {"coordinates":[-118.447998,34.150799],"type":"Point"}
}