{
  "type": "Feature",
  "properties": {
    "iso:country":"US",
    "sg:address":"5324 Ekwill St",
    "sg:city":"Santa Barbara",
    "sg:classifiers":[
        {
            "category":"Organizations",
            "subcategory":"Religious Organization",
            "type":"Services"
        }
    ],
    "sg:phone":"+1 805 681 7494",
    "sg:postcode":"93111",
    "sg:province":"CA",
    "sg:tags":[
        "church"
    ],
    "sg:website":"www.sgi-usa.org",
    "wof:name":"Soka Gakkai Intl USA",
    "wof:placetype":"venue"
},
  "geometry": {"coordinates":[-119.81057699999999,34.43078],"type":"Point"}
}