{
  "type": "Feature",
  "properties": {
    "iso:country":"US",
    "sg:address":"24239 Hawthorne Blvd",
    "sg:city":"Torrance",
    "sg:classifiers":[
        {
            "category":"Personal",
            "subcategory":"Beauty Salon",
            "type":"Services"
        }
    ],
    "sg:phone":"+1 310 791 5116",
    "sg:postcode":"90505",
    "sg:province":"CA",
    "sg:website":"www.superpages.com",
    "wof:name":"D'Tangle Premier Full Svc Sln",
    "wof:placetype":"venue"
},
  "geometry": {"coordinates":[-118.35099599999999,33.803875],"type":"Point"}
}