{
  "type": "Feature",
  "properties": {
    "iso:country":"US",
    "sg:address":"6200 E Canyon Rim Rd",
    "sg:city":"Anaheim",
    "sg:classifiers":[
        {
            "category":"Health Services",
            "subcategory":"Doctor",
            "type":"Services"
        }
    ],
    "sg:phone":"+1 714 974 8130",
    "sg:postcode":"92807",
    "sg:province":"CA",
    "sg:tags":[
        "physician",
        "surgeon"
    ],
    "wof:name":"Anaheim Hills Internal Med",
    "wof:placetype":"venue"
},
  "geometry": {"coordinates":[-117.772648,33.84588],"type":"Point"}
}