{
  "type": "Feature",
  "properties": {
    "addr:full":"826 Virginia Ave Lodi CA 95242",
    "addr:housenumber":"826",
    "addr:postcode":"95242",
    "addr:street":"Virginia Ave",
    "iso:country":"US",
    "sg:address":"826 Virginia Ave",
    "sg:city":"Lodi",
    "sg:classifiers":[
        {
            "category":"Building & Trades",
            "subcategory":"Plumbing",
            "type":"Services"
        }
    ],
    "sg:phone":"+1 209 334 1146",
    "sg:postcode":"95242",
    "sg:province":"CA",
    "sg:tags":[
        "contractor"
    ],
    "wof:name":"H and H Plumbing & Constructn",
    "wof:placetype":"venue"
},
  "geometry": {"coordinates":[-121.29336499999999,38.124042],"type":"Point"}
}