{
  "type": "Feature",
  "properties": {
    "iso:country":"US",
    "sg:address":"10741 W Pico Blvd",
    "sg:city":"Los Angeles",
    "sg:classifiers":[
        {
            "category":"Personal",
            "subcategory":"Beauty Salon",
            "type":"Services"
        }
    ],
    "sg:phone":"+1 310 234 0341",
    "sg:postcode":"90064",
    "sg:province":"CA",
    "sg:tags":[
        "hair"
    ],
    "sg:website":"www.jacquesmichael.com/",
    "wof:name":"Jacques Michael Salon",
    "wof:placetype":"venue"
},
  "geometry": {"coordinates":[-118.426142,34.041272],"type":"Point"}
}