{
  "type": "Feature",
  "properties": {
    "addr:full":"47 Trinity Ave Chowchilla CA 93610",
    "addr:housenumber":"47",
    "addr:postcode":"93610",
    "addr:street":"Trinity Ave",
    "iso:country":"US",
    "sg:address":"47 Trinity Ave",
    "sg:city":"Chowchilla",
    "sg:classifiers":[
        {
            "category":"Organizations",
            "subcategory":"Religious Organization",
            "type":"Services"
        }
    ],
    "sg:phone":"+1 559 665 4851",
    "sg:postcode":"93610",
    "sg:province":"CA",
    "sg:tags":[
        "church"
    ],
    "wof:name":"Lighthouse Tabernacle",
    "wof:placetype":"venue"
},
  "geometry": {"coordinates":[-120.25768100000001,37.123086],"type":"Point"}
}