{
  "type": "Feature",
  "properties": {
    "iso:country":"US",
    "sg:address":"7707 Crenshaw Blvd",
    "sg:city":"Los Angeles",
    "sg:classifiers":[
        {
            "category":"Food & Beverages",
            "subcategory":"Liquor & Beverages",
            "type":"Retail Goods"
        }
    ],
    "sg:phone":"+1 323 778 2012",
    "sg:postcode":"90043",
    "sg:province":"CA",
    "sg:tags":[
        "beer",
        "spirit",
        "wine"
    ],
    "wof:name":"Vee's Liquor",
    "wof:placetype":"venue"
},
  "geometry": {"coordinates":[-118.331001,33.9697],"type":"Point"}
}