{
  "type": "Feature",
  "properties": {
    "iso:country":"US",
    "sg:address":"4927 Oak Leaf Cir",
    "sg:city":"Placerville",
    "sg:classifiers":[
        {
            "category":"Shopping",
            "subcategory":"Catalog Store",
            "type":"Retail Goods"
        }
    ],
    "sg:phone":"+1 530 644 6890",
    "sg:postcode":"95667",
    "sg:province":"CA",
    "sg:tags":[
        "house",
        "mail"
    ],
    "wof:name":"Avon",
    "wof:placetype":"venue"
},
  "geometry": {"coordinates":[-120.664351,38.674645],"type":"Point"}
}