{
  "type": "Feature",
  "properties": {
    "iso:country":"US",
    "sg:address":"2322 6th St",
    "sg:city":"Berkeley",
    "sg:classifiers":[
        {
            "category":"Manufacturing",
            "subcategory":"Tools & Machinery",
            "type":"Manufacturing & Wholesale Goods"
        }
    ],
    "sg:phone":"+1 510 982 3990",
    "sg:postcode":"94710",
    "sg:province":"CA",
    "sg:tags":[
        "lighting",
        "fixture"
    ],
    "wof:name":"Optic Arts Inc",
    "wof:placetype":"venue"
},
  "geometry": {"coordinates":[-122.296175,37.862919],"type":"Point"}
}