{
  "type": "Feature",
  "properties": {
    "addr:full":"6640 Telegraph Avenue Berkeley CA 94702",
    "addr:housenumber":"6640",
    "addr:postcode":"94702",
    "addr:street":"Telegraph Avenue",
    "iso:country":"US",
    "sg:address":"6640 Telegraph Avenue",
    "sg:city":"Berkeley",
    "sg:classifiers":[
        {
            "category":"Home & Garden",
            "subcategory":"Hardware",
            "type":"Retail Goods"
        }
    ],
    "sg:phone":"+1 510 849 3001",
    "sg:postcode":"94702",
    "sg:province":"CA",
    "sg:tags":[
        "store"
    ],
    "wof:name":"Eastern Supplies",
    "wof:placetype":"venue"
},
  "geometry": {"coordinates":[-122.285004,37.865398],"type":"Point"}
}