{
  "type": "Feature",
  "properties": {
    "iso:country":"US",
    "sg:address":"2888 Lynn Rd",
    "sg:city":"Sebastopol",
    "sg:classifiers":[
        {
            "category":"Wholesale",
            "subcategory":"Groceries",
            "type":"Manufacturing & Wholesale Goods"
        }
    ],
    "sg:phone":"+1 707 829 3881",
    "sg:postcode":"95472",
    "sg:province":"CA",
    "sg:tags":[
        "eating",
        "general"
    ],
    "wof:name":"Epicurean Specialty",
    "wof:placetype":"venue"
},
  "geometry": {"coordinates":[-122.862684,38.368404],"type":"Point"}
}