{
  "type": "Feature",
  "properties": {
    "iso:country":"US",
    "sg:address":"3798 Janes Rd",
    "sg:city":"Arcata",
    "sg:classifiers":[
        {
            "category":"Social Services",
            "type":"Services"
        }
    ],
    "sg:phone":"+1 707 822 9005",
    "sg:postcode":"95521",
    "sg:province":"CA",
    "sg:tags":[
        "counselor",
        "marriage",
        "family"
    ],
    "wof:name":"Michael J Paulus",
    "wof:placetype":"venue"
},
  "geometry": {"coordinates":[-124.09124199999999,40.902696],"type":"Point"}
}