{
  "type": "Feature",
  "properties": {
    "addr:full":"4199 Union Ave Bakersfield CA 93305",
    "addr:housenumber":"4199",
    "addr:postcode":"93305",
    "addr:street":"Union Ave",
    "iso:country":"US",
    "sg:address":"4199 Union Ave",
    "sg:city":"Bakersfield",
    "sg:classifiers":[
        {
            "category":"Autos & Motor Vehicles",
            "subcategory":"Automobile Sales",
            "type":"Retail Goods"
        }
    ],
    "sg:phone":"+1 661 323 2200",
    "sg:postcode":"93305",
    "sg:province":"CA",
    "sg:tags":[
        "car",
        "dealer"
    ],
    "wof:name":"Auto Maxx",
    "wof:placetype":"venue"
},
  "geometry": {"coordinates":[-119.002864,35.396443],"type":"Point"}
}