{
  "type": "Feature",
  "properties": {
    "iso:country":"US",
    "sg:address":"21980 Meekland Ave",
    "sg:city":"Hayward",
    "sg:classifiers":[
        {
            "category":"Autos & Motor Vehicles",
            "subcategory":"Auto Supplies",
            "type":"Retail Goods"
        },
        {
            "category":"Personal",
            "type":"Services"
        },
        {
            "category":"Retail",
            "subcategory":"Auto Repair",
            "type":"Services"
        }
    ],
    "sg:phone":"+1 510 266 3513",
    "sg:postcode":"94541",
    "sg:province":"CA",
    "sg:tags":[
        "towing",
        "tire"
    ],
    "wof:name":"MA Auto & Tires",
    "wof:placetype":"venue"
},
  "geometry": {"coordinates":[-122.103663,37.671063],"type":"Point"}
}