{
  "type": "Feature",
  "properties": {
    "addr:full":"673 W 5th St San Bernardino CA 92410",
    "addr:housenumber":"673",
    "addr:postcode":"92410",
    "addr:street":"W 5Th St",
    "iso:country":"US",
    "sg:address":"673 W 5th St",
    "sg:city":"San Bernardino",
    "sg:classifiers":[
        {
            "category":"Education",
            "subcategory":"College",
            "type":"Public Place"
        }
    ],
    "sg:phone":"+1 909 884 2719",
    "sg:postcode":"92410",
    "sg:province":"CA",
    "sg:tags":[
        "academic",
        "school"
    ],
    "wof:name":"Rosston Schools-Men's Hair",
    "wof:placetype":"venue"
},
  "geometry": {"coordinates":[-117.297219,34.108252],"type":"Point"}
}