{
  "type": "Feature",
  "properties": {
    "addr:full":"7631 Foothill Blvd Tujunga CA 91042",
    "addr:housenumber":"7631",
    "addr:postcode":"91042",
    "addr:street":"Foothill Blvd",
    "iso:country":"US",
    "sg:address":"7631 Foothill Blvd",
    "sg:city":"Tujunga",
    "sg:classifiers":[
        {
            "category":"Wholesale",
            "subcategory":"Medical Equipment & Supplies",
            "type":"Manufacturing & Wholesale Goods"
        }
    ],
    "sg:phone":"+1 818 353 8133",
    "sg:postcode":"91042",
    "sg:province":"CA",
    "wof:name":"Star Medical Supply",
    "wof:placetype":"venue"
},
  "geometry": {"coordinates":[-118.298739,34.255268],"type":"Point"}
}