{
  "type": "Feature",
  "properties": {
    "addr:full":"7059 W Sunset Blvd Los Angeles CA 90028",
    "addr:housenumber":"7059",
    "addr:postcode":"90028",
    "addr:street":"W Sunset Blvd",
    "iso:country":"US",
    "sg:address":"7059 W Sunset Blvd",
    "sg:city":"Los Angeles",
    "sg:classifiers":[
        {
            "category":"Utilities",
            "subcategory":"Mobile Phone",
            "type":"Services"
        }
    ],
    "sg:phone":"+1 323 993 0645",
    "sg:postcode":"90028",
    "sg:province":"CA",
    "sg:tags":[
        "telephone",
        "cellular"
    ],
    "wof:name":"Verizon",
    "wof:placetype":"venue"
},
  "geometry": {"coordinates":[-118.343485,34.098039],"type":"Point"}
}