{
  "type": "Feature",
  "properties": {
    "iso:country":"US",
    "sg:address":"7082 Crescent Ave",
    "sg:city":"Buena Park",
    "sg:classifiers":[
        {
            "category":"Education",
            "subcategory":"Preschool",
            "type":"Public Place"
        }
    ],
    "sg:phone":"+1 714 827 6440",
    "sg:postcode":"90620",
    "sg:province":"CA",
    "sg:website":"www.goodshepherdlcbp.org",
    "wof:name":"Good Shepherd Preschool",
    "wof:placetype":"venue"
},
  "geometry": {"coordinates":[-118.009003,33.839199],"type":"Point"}
}