{
  "type": "Feature",
  "properties": {
    "addr:full":"2843 San Pablo Avenue Berkeley CA 94702",
    "addr:housenumber":"2843",
    "addr:postcode":"94702",
    "addr:street":"San Pablo Avenue",
    "iso:country":"US",
    "sg:address":"2843 San Pablo Avenue",
    "sg:city":"Berkeley",
    "sg:classifiers":[
        {
            "category":"Food & Beverages",
            "subcategory":"Meat & Fish",
            "type":"Retail Goods"
        }
    ],
    "sg:phone":"+1 510 848 3460",
    "sg:postcode":"94702",
    "sg:province":"CA",
    "sg:tags":[
        "shop"
    ],
    "wof:name":"C & M Meat Company",
    "wof:placetype":"venue"
},
  "geometry": {"coordinates":[-122.287003,37.854301],"type":"Point"}
}