{
  "type": "Feature",
  "properties": {
    "addr:full":"1539 Humboldt St Santa Rosa CA 95404",
    "addr:housenumber":"1539",
    "addr:postcode":"ca 95404",
    "addr:street":"Humboldt St",
    "iso:country":"US",
    "sg:address":"1539 Humboldt St",
    "sg:city":"Santa Rosa",
    "sg:classifiers":[
        {
            "category":"Social Services",
            "type":"Services"
        }
    ],
    "sg:phone":"+1 707 526 3150",
    "sg:postcode":"95404",
    "sg:province":"CA",
    "sg:tags":[
        "organization",
        "welfare"
    ],
    "wof:name":"Athena House",
    "wof:placetype":"venue"
},
  "geometry": {"coordinates":[-122.714369,38.456139],"type":"Point"}
}