{
  "type": "Feature",
  "properties": {
    "iso:country":"US",
    "sg:address":"31410 McCray Rd",
    "sg:city":"Cloverdale",
    "sg:classifiers":[
        {
            "category":"Farming",
            "subcategory":"Farm & Veterinary Services",
            "type":"Manufacturing & Wholesale Goods"
        }
    ],
    "sg:phone":"+1 707 894 3567",
    "sg:postcode":"95425",
    "sg:province":"CA",
    "sg:tags":[
        "crop",
        "harvesting"
    ],
    "wof:name":"Braccialini Vineyards",
    "wof:placetype":"venue"
},
  "geometry": {"coordinates":[-123.016717,38.821268],"type":"Point"}
}