{
  "type": "Feature",
  "properties": {
    "addr:full":"2004 Bel Aire Dr Glendale CA 91201",
    "addr:postcode":"2004;91201",
    "addr:street":"Bel Aire Dr",
    "iso:country":"US",
    "sg:address":"2004 Bel Aire Dr",
    "sg:city":"Glendale",
    "sg:classifiers":[
        {
            "category":"Freight",
            "type":"Transportation"
        }
    ],
    "sg:phone":"+1 818 846 0272",
    "sg:postcode":"91201",
    "sg:province":"CA",
    "wof:name":"Tyler Transportation",
    "wof:placetype":"venue"
},
  "geometry": {"coordinates":[-118.28870000000001,34.182566],"type":"Point"}
}