{
  "type": "Feature",
  "properties": {
    "iso:country":"US",
    "sg:address":"8810 14th Ave",
    "sg:city":"Hanford",
    "sg:classifiers":[
        {
            "category":"Education",
            "subcategory":"School",
            "type":"Public Place"
        }
    ],
    "sg:phone":"+1 559 584 8831",
    "sg:postcode":"93230",
    "sg:province":"CA",
    "wof:name":"Pioneer Union Elementary Schl",
    "wof:placetype":"venue"
},
  "geometry": {"coordinates":[-119.708898,36.344463],"type":"Point"}
}