{
  "type": "Feature",
  "properties": {
    "addr:full":"3477 School St Lafayette CA 94549",
    "addr:housenumber":"3477",
    "addr:postcode":"94549",
    "addr:street":"School St",
    "iso:country":"US",
    "sg:address":"3477 School St",
    "sg:city":"Lafayette",
    "sg:classifiers":[
        {
            "category":"Education",
            "subcategory":"School",
            "type":"Public Place"
        }
    ],
    "sg:phone":"+1 925 284 7011",
    "sg:postcode":"94549",
    "sg:province":"CA",
    "wof:name":"Lafayette School District",
    "wof:placetype":"venue"
},
  "geometry": {"coordinates":[-122.116083,37.887707],"type":"Point"}
}