{
  "type": "Feature",
  "properties": {
    "iso:country":"US",
    "sg:address":"9080 Laguna Main St",
    "sg:city":"Elk Grove",
    "sg:classifiers":[
        {
            "category":"Restaurant",
            "type":"Food & Drink"
        }
    ],
    "sg:phone":"+1 916 691 1727",
    "sg:postcode":"95758",
    "sg:province":"CA",
    "wof:name":"Ella's Southern Catfish",
    "wof:placetype":"venue"
},
  "geometry": {"coordinates":[-121.470119,38.427951],"type":"Point"}
}