{
  "type": "Feature",
  "properties": {
    "addr:full":"234 E Colorado Blvd Pasadena CA 91101",
    "addr:housenumber":"234",
    "addr:postcode":"91101",
    "addr:street":"E Colorado Blvd",
    "iso:country":"US",
    "sg:address":"234 E Colorado Blvd",
    "sg:city":"Pasadena",
    "sg:classifiers":[
        {
            "category":"Shopping",
            "subcategory":"Mobile Phones",
            "type":"Retail Goods"
        }
    ],
    "sg:phone":"+1 626 356 0817",
    "sg:postcode":"91101",
    "sg:province":"CA",
    "wof:name":"Sym Technology Inc",
    "wof:placetype":"venue"
},
  "geometry": {"coordinates":[-118.145315,34.145681],"type":"Point"}
}