{
  "type": "Feature",
  "properties": {
    "iso:country":"US",
    "sg:address":"21950 Avalon Blvd",
    "sg:city":"Carson",
    "sg:classifiers":[
        {
            "category":"Personal",
            "subcategory":"Beauty Salon",
            "type":"Services"
        }
    ],
    "sg:phone":"+1 310 513 1813",
    "sg:postcode":"90745",
    "sg:province":"CA",
    "wof:name":"Illana Mc Kinney",
    "wof:placetype":"venue"
},
  "geometry": {"coordinates":[-118.26351699999999,33.828538],"type":"Point"}
}