{
  "type": "Feature",
  "properties": {
    "iso:country":"US",
    "sg:address":"2627 W Florida Ave",
    "sg:city":"Hemet",
    "sg:classifiers":[
        {
            "category":"Communications",
            "subcategory":"Radio Station",
            "type":"Services"
        }
    ],
    "sg:phone":"+1 951 658 3208",
    "sg:postcode":"92545",
    "sg:province":"CA",
    "wof:name":"Khye-FM & Khsj-AM",
    "wof:placetype":"venue"
},
  "geometry": {"coordinates":[-116.998931,33.747321],"type":"Point"}
}