{
  "type": "Feature",
  "properties": {
    "iso:country":"US",
    "sg:address":"1808 Aston Ave # 240",
    "sg:city":"Carlsbad",
    "sg:phone":"+1 760 603 9644",
    "sg:postcode":"92008",
    "sg:province":"CA",
    "wof:name":"Matthew P Rocco Law Offices",
    "wof:placetype":"venue"
},
  "geometry": {"coordinates":[-117.2912,33.132304],"type":"Point"}
}