{
  "type": "Feature",
  "properties": {
    "addr:full":"2 Serramonte Ctr Daly City CA 94015",
    "addr:housenumber":"2",
    "addr:postcode":"94015",
    "addr:street":"Serramonte Ctr",
    "iso:country":"US",
    "sg:address":"2 Serramonte Ctr",
    "sg:city":"Daly City",
    "sg:classifiers":[
        {
            "category":"Restaurant",
            "type":"Food & Drink"
        }
    ],
    "sg:menulink":"http://www.allmenus.com/ca/south-san-francisco/8235-dennys/menu/",
    "sg:phone":"+1 650 756 8544",
    "sg:postcode":"94015",
    "sg:province":"CA",
    "sg:tags":[
        "american",
        "diner"
    ],
    "wof:name":"Denny's",
    "wof:placetype":"venue"
},
  "geometry": {"coordinates":[-122.46734499999999,37.669376],"type":"Point"}
}