{
  "type": "Feature",
  "properties": {
    "addr:full":"700 S Winchester Blvd San Jose CA 95128",
    "addr:housenumber":"700",
    "addr:postcode":"95128",
    "addr:street":"S Winchester Blvd",
    "iso:country":"US",
    "sg:address":"700 S Winchester Blvd",
    "sg:city":"San Jose",
    "sg:classifiers":[
        {
            "category":"Personal",
            "subcategory":"Beauty Salon",
            "type":"Services"
        }
    ],
    "sg:phone":"+1 408 244 5087",
    "sg:postcode":"95128",
    "sg:province":"CA",
    "wof:name":"Pereira Estudio Design Full",
    "wof:placetype":"venue"
},
  "geometry": {"coordinates":[-121.950014,37.31382],"type":"Point"}
}