{
  "type": "Feature",
  "properties": {
    "addr:full":"615 15th St Modesto CA 95354",
    "addr:housenumber":"615",
    "addr:postcode":"ca 95354",
    "addr:street":"15Th St",
    "iso:country":"US",
    "sg:address":"615 15th St",
    "sg:city":"Modesto",
    "sg:classifiers":[
        {
            "category":"Health Services",
            "subcategory":"Doctor",
            "type":"Services"
        },
        {
            "category":"Health Services",
            "subcategory":"Clinic",
            "type":"Services"
        },
        {
            "category":"Personal",
            "type":"Services"
        },
        {
            "category":"Social Services",
            "type":"Services"
        }
    ],
    "sg:phone":"+1 209 527 4682",
    "sg:postcode":"95354",
    "sg:province":"CA",
    "sg:tags":[
        "mental",
        "family",
        "professional",
        "counselors-licensed",
        "psychologist",
        "individual",
        "marriage",
        "child",
        "counseling",
        "counselor"
    ],
    "wof:name":"Johnson Debra A PHD",
    "wof:placetype":"venue"
},
  "geometry": {"coordinates":[-120.991997,37.6408],"type":"Point"}
}