{
  "type": "Feature",
  "properties": {
    "iso:country":"US",
    "sg:address":"1416 W Twain Ave",
    "sg:city":"Fresno",
    "sg:classifiers":[
        {
            "category":"Health Services",
            "subcategory":"Nursing And Care Facility",
            "type":"Services"
        }
    ],
    "sg:phone":"+1 559 222 0793",
    "sg:postcode":"93711",
    "sg:province":"CA",
    "sg:tags":[
        "hospice"
    ],
    "wof:name":"Hinds Hospice Home",
    "wof:placetype":"venue"
},
  "geometry": {"coordinates":[-119.821595,36.809372],"type":"Point"}
}