{
  "type": "Feature",
  "properties": {
    "iso:country":"US",
    "sg:address":"900 W Santa Anita Ave",
    "sg:city":"San Gabriel",
    "sg:classifiers":[
        {
            "category":"Shopping",
            "type":"Retail Goods"
        }
    ],
    "sg:phone":"+1 626 458 3796",
    "sg:postcode":"91776",
    "sg:province":"CA",
    "sg:tags":[
        "art",
        "gallery",
        "dealer"
    ],
    "wof:name":"Smc Art & Deco",
    "wof:placetype":"venue"
},
  "geometry": {"coordinates":[-118.112191,34.094353],"type":"Point"}
}