{
  "type": "Feature",
  "properties": {
    "iso:country":"US",
    "sg:address":"18750 Colima Rd",
    "sg:city":"Rowland Heights",
    "sg:classifiers":[
        {
            "category":"Health Services",
            "subcategory":"Doctor",
            "type":"Services"
        }
    ],
    "sg:phone":"+1 626 965 2521",
    "sg:postcode":"91748",
    "sg:province":"CA",
    "sg:tags":[
        "dentist"
    ],
    "wof:name":"Star Dental Practice",
    "wof:placetype":"venue"
},
  "geometry": {"coordinates":[-117.89622300000001,33.987816],"type":"Point"}
}