{
  "type": "Feature",
  "properties": {
    "addr:full":"1468 Macarthur Blvd Oakland CA 94602",
    "addr:housenumber":"1468",
    "addr:postcode":"94602",
    "addr:street":"Macarthur Blvd",
    "iso:country":"US",
    "sg:address":"1468 Macarthur Blvd",
    "sg:city":"Oakland",
    "sg:classifiers":[
        {
            "category":"Banks & Credit Unions",
            "subcategory":"Financial Services",
            "type":"Services"
        }
    ],
    "sg:phone":"+1 510 812 4369",
    "sg:postcode":"94602",
    "sg:province":"CA",
    "sg:tags":[
        "trust",
        "investment",
        "real estate"
    ],
    "wof:name":"Williams Porperty Management",
    "wof:placetype":"venue"
},
  "geometry": {"coordinates":[-122.226204,37.801079],"type":"Point"}
}