{
  "type": "Feature",
  "properties": {
    "iso:country":"US",
    "sg:address":"132 Market Way",
    "sg:city":"Salinas",
    "sg:classifiers":[
        {
            "category":"Retail",
            "subcategory":"Auto Repair",
            "type":"Services"
        }
    ],
    "sg:phone":"+1 831 758 9654",
    "sg:postcode":"93901",
    "sg:province":"CA",
    "sg:tags":[
        "body",
        "repairing",
        "painting",
        "automobile"
    ],
    "wof:name":"Premium Collision Works",
    "wof:placetype":"venue"
},
  "geometry": {"coordinates":[-121.651764,36.678062],"type":"Point"}
}