{
  "type": "Feature",
  "properties": {
    "iso:country":"US",
    "sg:address":"12411 Poway Rd",
    "sg:city":"Poway",
    "sg:classifiers":[
        {
            "category":"Real Estate",
            "subcategory":"Real Estate Agent",
            "type":"Services"
        }
    ],
    "sg:phone":"+1 858 780 1726",
    "sg:postcode":"92064",
    "sg:province":"CA",
    "wof:name":"Sam Rasoul",
    "wof:placetype":"venue"
},
  "geometry": {"coordinates":[-117.06052800000001,32.951858],"type":"Point"}
}