{
  "type": "Feature",
  "properties": {
    "addr:full":"1617 N Carpenter Rd Modesto CA 95351",
    "addr:housenumber":"1617",
    "addr:postcode":"ca 95351",
    "addr:street":"N Carpenter Rd",
    "iso:country":"US",
    "sg:address":"1617 N Carpenter Rd",
    "sg:city":"Modesto",
    "sg:classifiers":[
        {
            "category":"Restaurant",
            "type":"Food & Drink"
        }
    ],
    "sg:menulink":"http://www.allmenus.com/ca/modesto/174446-wendys/menu/",
    "sg:phone":"+1 209 549 7835",
    "sg:postcode":"95351",
    "sg:province":"CA",
    "sg:tags":[
        "burger",
        "american",
        "soup"
    ],
    "wof:name":"Wendy's",
    "wof:placetype":"venue"
},
  "geometry": {"coordinates":[-121.031584,37.659101],"type":"Point"}
}