{
  "type": "Feature",
  "properties": {
    "addr:full":"27200 Tourney Rd Valencia CA 91355",
    "addr:housenumber":"27200",
    "addr:postcode":"91355",
    "addr:street":"Tourney Rd",
    "iso:country":"US",
    "sg:address":"27200 Tourney Rd",
    "sg:city":"Valencia",
    "sg:classifiers":[
        {
            "category":"Government",
            "subcategory":"Office",
            "type":"Public Place"
        }
    ],
    "sg:phone":"+1 661 253 7400",
    "sg:postcode":"91355",
    "sg:province":"CA",
    "sg:tags":[
        "sector",
        "regulation",
        "commercial"
    ],
    "wof:name":"Dept of Insurance California",
    "wof:placetype":"venue"
},
  "geometry": {"coordinates":[-118.578889,34.418973],"type":"Point"}
}