{
  "type": "Feature",
  "properties": {
    "iso:country":"US",
    "sg:address":"3900 Birch St",
    "sg:city":"Newport Beach",
    "sg:classifiers":[
        {
            "category":"Professional",
            "subcategory":"Accounting & Tax Preparation",
            "type":"Services"
        }
    ],
    "sg:phone":"+1 949 474 0211",
    "sg:postcode":"92660",
    "sg:province":"CA",
    "sg:tags":[
        "return",
        "filing"
    ],
    "wof:name":"RDA Financial Svc",
    "wof:placetype":"venue"
},
  "geometry": {"coordinates":[-117.86879399999999,33.665598],"type":"Point"}
}