{
  "type": "Feature",
  "properties": {
    "iso:country":"US",
    "sg:address":"4689 Santa Monica Ave",
    "sg:city":"San Diego",
    "sg:classifiers":[
        {
            "category":"Social Services",
            "subcategory":"Child Care",
            "type":"Services"
        }
    ],
    "sg:phone":"+1 619 222 8418",
    "sg:postcode":"92107",
    "sg:province":"CA",
    "wof:name":"Childrens Energy Ctr",
    "wof:placetype":"venue"
},
  "geometry": {"coordinates":[-117.243651,32.743489],"type":"Point"}
}