{
  "type": "Feature",
  "properties": {
    "addr:full":"1333 Research Park Dr Davis CA 95618",
    "addr:housenumber":"1333",
    "addr:postcode":"95618",
    "addr:street":"Research Park Dr",
    "iso:country":"US",
    "sg:address":"1333 Research Park Dr",
    "sg:city":"Davis",
    "sg:classifiers":[
        {
            "category":"Education",
            "subcategory":"University",
            "type":"Public Place"
        }
    ],
    "sg:phone":"+1 530 757 8667",
    "sg:postcode":"95618",
    "sg:province":"CA",
    "sg:tags":[
        "college"
    ],
    "sg:website":"http://www.kinghall.ucdavis.edu",
    "wof:name":"Uc Davis Extension",
    "wof:placetype":"venue"
},
  "geometry": {"coordinates":[-121.732938,38.538383],"type":"Point"}
}