{
  "type": "Feature",
  "properties": {
    "addr:full":"23962 Alessandro Blvd Moreno Valley CA 92553",
    "addr:housenumber":"23962",
    "addr:postcode":"92553",
    "addr:street":"Alessandro Blvd",
    "iso:country":"US",
    "sg:address":"23962 Alessandro Blvd",
    "sg:city":"Moreno Valley",
    "sg:classifiers":[
        {
            "category":"Insurance",
            "subcategory":"Insurance Agent",
            "type":"Services"
        }
    ],
    "sg:phone":"+1 951 656 2709",
    "sg:postcode":"92553",
    "sg:province":"CA",
    "wof:name":"Farmers Insurance Group",
    "wof:placetype":"venue"
},
  "geometry": {"coordinates":[-117.251614,33.917341],"type":"Point"}
}