{
  "type": "Feature",
  "properties": {
    "addr:full":"804 Main St Venice CA 90291",
    "addr:housenumber":"804",
    "addr:postcode":"90291",
    "addr:street":"Main St",
    "iso:country":"US",
    "sg:address":"804 Main St",
    "sg:city":"Venice",
    "sg:classifiers":[
        {
            "category":"Professional",
            "subcategory":"Computer Services",
            "type":"Services"
        }
    ],
    "sg:phone":"+1 310 399 1490",
    "sg:postcode":"90291",
    "sg:province":"CA",
    "sg:tags":[
        "processing",
        "datum"
    ],
    "sg:website":"www.processing-center.com",
    "wof:name":"Processing Ctr",
    "wof:placetype":"venue"
},
  "geometry": {"coordinates":[-118.474369,33.992565],"type":"Point"}
}