{
  "type": "Feature",
  "properties": {
    "iso:country":"US",
    "sg:address":"130 N Butte St",
    "sg:city":"Willows",
    "sg:classifiers":[
        {
            "category":"Sports & Exercise",
            "subcategory":"Gym",
            "type":"Entertainment"
        }
    ],
    "sg:phone":"+1 530 934 2660",
    "sg:postcode":"95988",
    "sg:province":"CA",
    "sg:tags":[
        "club",
        "health",
        "studio",
        "gymnasium"
    ],
    "wof:name":"Curves For Women",
    "wof:placetype":"venue"
},
  "geometry": {"coordinates":[-122.19525899999999,39.521443],"type":"Point"}
}