{
  "type": "Feature",
  "properties": {
    "addr:full":"34554 Alvarado Niles Rd Union City CA 94587",
    "addr:housenumber":"34554",
    "addr:postcode":"94587",
    "addr:street":"Alvarado Niles Rd",
    "iso:country":"US",
    "sg:address":"34554 Alvarado Niles Rd",
    "sg:city":"Union City",
    "sg:classifiers":[
        {
            "category":"Food & Beverages",
            "subcategory":"Bakery",
            "type":"Retail Goods"
        }
    ],
    "sg:phone":"+1 510 429 1358",
    "sg:postcode":"94587",
    "sg:province":"CA",
    "sg:tags":[
        "doughnut"
    ],
    "wof:name":"Donut Delight Oriental Pastry",
    "wof:placetype":"venue"
},
  "geometry": {"coordinates":[-122.018908,37.586522],"type":"Point"}
}