{
  "type": "Feature",
  "properties": {
    "iso:country":"US",
    "sg:address":"2551 San Ramon Valley Blvd",
    "sg:city":"San Ramon",
    "sg:classifiers":[
        {
            "category":"Insurance",
            "subcategory":"Insurance Agent",
            "type":"Services"
        }
    ],
    "sg:phone":"+1 925 820 3939",
    "sg:postcode":"94583",
    "sg:province":"CA",
    "wof:name":"Farmers Insurance Group",
    "wof:placetype":"venue"
},
  "geometry": {"coordinates":[-121.97820900000001,37.775929],"type":"Point"}
}