{
  "type": "Feature",
  "properties": {
    "addr:full":"2765 Santa Rosa Ave Santa Rosa CA 95407",
    "addr:housenumber":"2765",
    "addr:postcode":"95407",
    "addr:street":"Santa Rosa Ave",
    "iso:country":"US",
    "sg:address":"2765 Santa Rosa Ave",
    "sg:city":"Santa Rosa",
    "sg:classifiers":[
        {
            "category":"Shopping",
            "type":"Retail Goods"
        }
    ],
    "sg:phone":"+1 707 579 4863",
    "sg:postcode":"95407",
    "sg:province":"CA",
    "sg:tags":[
        "pet",
        "shop"
    ],
    "sg:website":"www.petco.com",
    "wof:name":"PETCO",
    "wof:placetype":"venue"
},
  "geometry": {"coordinates":[-122.713593,38.415099],"type":"Point"}
}