{
  "type": "Feature",
  "properties": {
    "addr:full":"4584 International Blvd Oakland CA 94601",
    "addr:housenumber":"4584",
    "addr:postcode":"94601",
    "addr:street":"International Blvd",
    "iso:country":"US",
    "sg:address":"4584 International Blvd",
    "sg:city":"Oakland",
    "sg:classifiers":[
        {
            "category":"Wholesale",
            "subcategory":"Plants",
            "type":"Manufacturing & Wholesale Goods"
        }
    ],
    "sg:phone":"+1 510 535 1108",
    "sg:postcode":"94601",
    "sg:province":"CA",
    "sg:tags":[
        "supply"
    ],
    "wof:name":"Creation Flower Leti",
    "wof:placetype":"venue"
},
  "geometry": {"coordinates":[-122.21266900000001,37.77146],"type":"Point"}
}