{
  "type": "Feature",
  "properties": {
    "addr:full":"9857 Vine St Bloomington CA 92316",
    "addr:housenumber":"9857",
    "addr:postcode":"92316",
    "addr:street":"Vine St",
    "iso:country":"US",
    "sg:address":"9857 Vine St",
    "sg:city":"Bloomington",
    "sg:classifiers":[
        {
            "category":"Retail",
            "subcategory":"Auto Repair",
            "type":"Services"
        }
    ],
    "sg:phone":"+1 951 283 7342",
    "sg:postcode":"92316",
    "sg:province":"CA",
    "sg:tags":[
        "wrecker"
    ],
    "wof:name":"E & J's Towing",
    "wof:placetype":"venue"
},
  "geometry": {"coordinates":[-117.393761,34.076237],"type":"Point"}
}