{
  "type": "Feature",
  "properties": {
    "iso:country":"US",
    "sg:address":"1025 Gilman Street",
    "sg:city":"Berkeley",
    "sg:classifiers":[
        {
            "category":"Shopping",
            "subcategory":"Stationery & Office Supplies",
            "type":"Retail Goods"
        },
        {
            "category":"Wholesale",
            "subcategory":"Computers",
            "type":"Manufacturing & Wholesale Goods"
        }
    ],
    "sg:phone":"+1 510 525 0176",
    "sg:postcode":"94710",
    "sg:province":"CA",
    "sg:tags":[
        "equipment"
    ],
    "wof:name":"Office Depot",
    "wof:placetype":"venue"
},
  "geometry": {"coordinates":[-122.296997,37.880299],"type":"Point"}
}