{
  "type": "Feature",
  "properties": {
    "addr:full":"150 G St Lincoln CA 95648",
    "addr:housenumber":"150",
    "addr:postcode":"95648",
    "addr:street":"G St",
    "iso:country":"US",
    "sg:address":"150 G St",
    "sg:city":"Lincoln",
    "sg:classifiers":[
        {
            "category":"Personal",
            "subcategory":"Beauty Salon",
            "type":"Services"
        }
    ],
    "sg:phone":"+1 916 645 0526",
    "sg:postcode":"95648",
    "sg:province":"CA",
    "wof:name":"Attitude",
    "wof:placetype":"venue"
},
  "geometry": {"coordinates":[-121.292856,38.887235],"type":"Point"}
}