{
  "type": "Feature",
  "properties": {
    "iso:country":"US",
    "sg:address":"27548-60 Tampa Ave",
    "sg:city":"Hayward",
    "sg:classifiers":[
        {
            "category":"Restaurant",
            "type":"Food & Drink"
        }
    ],
    "sg:postcode":"94544",
    "sg:province":"CA",
    "sg:tags":[
        "chinese"
    ],
    "wof:name":"China Gourmet",
    "wof:placetype":"venue"
},
  "geometry": {"coordinates":[-122.07575199999999,37.632341],"type":"Point"}
}