{
  "type": "Feature",
  "properties": {
    "iso:country":"US",
    "sg:address":"1086 Corte Barroso",
    "sg:city":"Camarillo",
    "sg:classifiers":[
        {
            "category":"Professional",
            "type":"Services"
        }
    ],
    "sg:phone":"+1 805 482 8896",
    "sg:postcode":"93010",
    "sg:province":"CA",
    "wof:name":"Joel Dobrin Inc",
    "wof:placetype":"venue"
},
  "geometry": {"coordinates":[-119.097891,34.227731],"type":"Point"}
}