{
  "type": "Feature",
  "properties": {
    "addr:full":"3321 Hyland Ave Costa Mesa CA 92626",
    "addr:housenumber":"3321",
    "addr:postcode":"92626",
    "addr:street":"Hyland Ave",
    "iso:country":"US",
    "sg:address":"3321 Hyland Ave",
    "sg:city":"Costa Mesa",
    "sg:classifiers":[
        {
            "category":"Bakery",
            "type":"Food & Drink"
        },
        {
            "category":"Shopping",
            "subcategory":"Bridal",
            "type":"Retail Goods"
        }
    ],
    "sg:phone":"+1 714 445 0189",
    "sg:postcode":"92626",
    "sg:province":"CA",
    "sg:website":"www.christophergarrens.com",
    "wof:name":"Christopher Garrens' Let Them Eat Cake",
    "wof:placetype":"venue"
},
  "geometry": {"coordinates":[-117.92484,33.692298],"type":"Point"}
}