{
  "type": "Feature",
  "properties": {
    "iso:country":"US",
    "sg:address":"1922 Pacific Coast Hwy",
    "sg:city":"Lomita",
    "sg:classifiers":[
        {
            "category":"Personal",
            "subcategory":"Massage",
            "type":"Services"
        },
        {
            "category":"Personal",
            "subcategory":"Beauty Salon",
            "type":"Services"
        },
        {
            "category":"Personal",
            "subcategory":"Day Spa",
            "type":"Services"
        }
    ],
    "sg:phone":"+1 310 530 8686",
    "sg:postcode":"90717",
    "sg:province":"CA",
    "sg:website":"www.pacificspa4u.com",
    "wof:name":"Pacific Spa",
    "wof:placetype":"venue"
},
  "geometry": {"coordinates":[-118.313034,33.789487],"type":"Point"}
}