{
  "type": "Feature",
  "properties": {
    "iso:country":"US",
    "sg:address":"23942 Lyons Ave",
    "sg:city":"Newhall",
    "sg:classifiers":[
        {
            "category":"Organizations",
            "subcategory":"Political Organization",
            "type":"Services"
        }
    ],
    "sg:phone":"+1 661 254 5957",
    "sg:postcode":"91321",
    "sg:province":"CA",
    "wof:name":"Democratic Hdqrts - Dem",
    "wof:placetype":"venue"
},
  "geometry": {"coordinates":[-118.553002,34.378928],"type":"Point"}
}