{
  "type": "Feature",
  "properties": {
    "addr:full":"23942 Lyons Ave Newhall CA 91321",
    "addr:housenumber":"23942",
    "addr:postcode":"91321",
    "addr:street":"Lyons Ave",
    "iso:country":"US",
    "sg:address":"23942 Lyons Ave",
    "sg:city":"Newhall",
    "sg:classifiers":[
        {
            "category":"Organizations",
            "subcategory":"Political Organization",
            "type":"Services"
        }
    ],
    "sg:phone":"+1 661 254 5957",
    "sg:postcode":"91321",
    "sg:province":"CA",
    "wof:name":"Democratic Hdqrts - Dem",
    "wof:placetype":"venue"
},
  "geometry": {"coordinates":[-118.55300200000001,34.378928],"type":"Point"}
}