{
  "type": "Feature",
  "properties": {
    "addr:full":"38 Metro Ln Sacramento CA 95816",
    "addr:housenumber":"38",
    "addr:postcode":"95816",
    "addr:street":"Metro Ln",
    "iso:country":"US",
    "sg:address":"38 Metro Ln",
    "sg:city":"Sacramento",
    "sg:classifiers":[
        {
            "category":"Banks & Credit Unions",
            "subcategory":"Investment Brokerage",
            "type":"Services"
        }
    ],
    "sg:phone":"+1 916 930 0607",
    "sg:postcode":"95816",
    "sg:province":"CA",
    "sg:tags":[
        "trust"
    ],
    "wof:name":"National Council Of Jewish Women, Sacramento Section",
    "wof:placetype":"venue"
},
  "geometry": {"coordinates":[-121.470254,38.576338],"type":"Point"}
}