{
  "type": "Feature",
  "properties": {
    "addr:full":"250 Cherry St San Francisco CA 94118",
    "addr:housenumber":"250",
    "addr:postcode":"94118",
    "addr:street":"Cherry St",
    "iso:country":"US",
    "sg:address":"250 Cherry St",
    "sg:city":"San Francisco",
    "sg:classifiers":[
        {
            "category":"Building & Trades",
            "subcategory":"Landscaping Services",
            "type":"Services"
        }
    ],
    "sg:phone":"+1 415 221 1129",
    "sg:postcode":"94118",
    "sg:province":"CA",
    "sg:tags":[
        "landscape"
    ],
    "wof:name":"Elizabeth Everdell Grdn Design",
    "wof:placetype":"venue"
},
  "geometry": {"coordinates":[-122.457055,37.788265],"type":"Point"}
}