{
  "type": "Feature",
  "properties": {
    "addr:full":"4110 Truxel Rd Ste C Sacramento CA 95834",
    "addr:postcode":"4110;95834",
    "addr:street":"Truxel Rd Ste C",
    "iso:country":"US",
    "sg:address":"4110 Truxel Rd Ste C",
    "sg:city":"Sacramento",
    "sg:classifiers":[
        {
            "category":"Professional",
            "subcategory":"Employment Agencies",
            "type":"Services"
        }
    ],
    "sg:phone":"+1 916 928 3742",
    "sg:postcode":"95834",
    "sg:province":"CA",
    "sg:website":"www.selectstaffing.com",
    "wof:name":"Select Personnel Services",
    "wof:placetype":"venue"
},
  "geometry": {"coordinates":[-121.508606,38.644291],"type":"Point"}
}