{
  "type": "Feature",
  "properties": {
    "iso:country":"US",
    "sg:address":"777 E Tahquitz Canyon Way Suite 200-34",
    "sg:city":"Palm Springs",
    "sg:classifiers":[
        {
            "category":"Professional",
            "subcategory":"Management & Consulting",
            "type":"Services"
        }
    ],
    "sg:phone":"+1 888 666 1570",
    "sg:postcode":"92262",
    "sg:province":"CA",
    "sg:website":"http://www.thinkquality.com/",
    "wof:name":"ThinkQ",
    "wof:placetype":"venue"
},
  "geometry": {"coordinates":[-116.541535,33.823053],"type":"Point"}
}