{
  "type": "Feature",
  "properties": {
    "iso:country":"US",
    "sg:address":"14792 Franklin Ave",
    "sg:city":"Tustin",
    "sg:classifiers":[
        {
            "category":"Manufacturing",
            "subcategory":"Tools & Machinery",
            "type":"Manufacturing & Wholesale Goods"
        }
    ],
    "sg:phone":"+1 714 734 0000",
    "sg:postcode":"92780",
    "sg:province":"CA",
    "sg:tags":[
        "el",
        "comm",
        "mfg"
    ],
    "wof:name":"Omohundro Co",
    "wof:placetype":"venue"
},
  "geometry": {"coordinates":[-117.810016,33.715372],"type":"Point"}
}