{
  "type": "Feature",
  "properties": {
    "addr:full":"5046 Newport Ave Ocean Beach CA 92107",
    "addr:housenumber":"5046",
    "addr:postcode":"92107",
    "addr:street":"Newport Ave",
    "iso:country":"US",
    "sg:address":"5046 Newport Ave",
    "sg:city":"Ocean Beach",
    "sg:classifiers":[
        {
            "category":"Bars & Pubs",
            "type":"Food & Drink"
        },
        {
            "category":"Restaurant",
            "type":"Food & Drink"
        }
    ],
    "sg:phone":"+1 619 222 5300",
    "sg:postcode":"92107",
    "sg:province":"CA",
    "sg:tags":[
        "irish"
    ],
    "sg:website":"www.gallagherspubob.com",
    "wof:name":"Gallagher's",
    "wof:placetype":"venue"
},
  "geometry": {"coordinates":[-117.251845,32.74747],"type":"Point"}
}