{
  "type": "Feature",
  "properties": {
    "addr:full":"1238 W El Camino Real Sunnyvale CA 94087",
    "addr:housenumber":"1238",
    "addr:postcode":"94087",
    "addr:street":"W El Camino Real",
    "iso:country":"US",
    "sg:address":"1238 W El Camino Real",
    "sg:city":"Sunnyvale",
    "sg:classifiers":[
        {
            "category":"Food & Beverages",
            "subcategory":"Candy",
            "type":"Retail Goods"
        }
    ],
    "sg:phone":"+1 408 720 0334",
    "sg:postcode":"94087",
    "sg:province":"CA",
    "sg:tags":[
        "store"
    ],
    "wof:name":"See's Candies",
    "wof:placetype":"venue"
},
  "geometry": {"coordinates":[-122.056999,37.374001],"type":"Point"}
}