{
  "type": "Feature",
  "properties": {
    "iso:country":"US",
    "sg:address":"960 Riverside Pkwy",
    "sg:city":"Broderick",
    "sg:classifiers":[
        {
            "category":"Building & Trades",
            "subcategory":"Construction",
            "type":"Services"
        }
    ],
    "sg:phone":"+1 916 372 1458",
    "sg:postcode":"95605",
    "sg:province":"CA",
    "sg:tags":[
        "elevator"
    ],
    "wof:name":"KONE Inc",
    "wof:placetype":"venue"
},
  "geometry": {"coordinates":[-121.563231,38.585703],"type":"Point"}
}