{
  "type": "Feature",
  "properties": {
    "iso:country":"US",
    "sg:address":"2030 Prince St",
    "sg:city":"Newman",
    "sg:classifiers":[
        {
            "category":"Real Estate",
            "subcategory":"Real Estate Operator",
            "type":"Services"
        }
    ],
    "sg:phone":"+1 209 862 2544",
    "sg:postcode":"95360",
    "sg:province":"CA",
    "sg:tags":[
        "building",
        "apartment"
    ],
    "wof:name":"Westside Vlg Senior Apartments",
    "wof:placetype":"venue"
},
  "geometry": {"coordinates":[-121.022064,37.310532],"type":"Point"}
}