{
  "type": "Feature",
  "properties": {
    "addr:full":"13413 Ventura Blvd Sherman Oaks CA 91423",
    "addr:housenumber":"13413",
    "addr:postcode":"91423",
    "addr:street":"Ventura Blvd",
    "iso:country":"US",
    "sg:address":"13413 Ventura Blvd",
    "sg:city":"Sherman Oaks",
    "sg:classifiers":[
        {
            "category":"Shopping",
            "subcategory":"Clothing, Apparel, & Fashions",
            "type":"Retail Goods"
        },
        {
            "category":"Shopping",
            "subcategory":"Hobbies, Toys, & Games",
            "type":"Retail Goods"
        }
    ],
    "sg:phone":"+1 818 817 6550",
    "sg:postcode":"91423",
    "sg:province":"CA",
    "sg:tags":[
        "children's",
        "toy",
        "clothing",
        "store"
    ],
    "sg:website":"www.rightstart.com/",
    "wof:name":"The Right Start",
    "wof:placetype":"venue"
},
  "geometry": {"coordinates":[-118.42538500000001,34.147072],"type":"Point"}
}