{
  "type": "Feature",
  "properties": {
    "iso:country":"US",
    "sg:address":"16500 Valley View Ave",
    "sg:city":"La Mirada",
    "sg:classifiers":[
        {
            "category":"Professional",
            "subcategory":"Printing & Photocopies",
            "type":"Services"
        }
    ],
    "sg:phone":"+1 714 739 1308",
    "sg:postcode":"90638",
    "sg:province":"CA",
    "sg:tags":[
        "duplicating",
        "copying"
    ],
    "wof:name":"Staples The Office Superstore",
    "wof:placetype":"venue"
},
  "geometry": {"coordinates":[-118.02885499999999,33.879484],"type":"Point"}
}