{
  "type": "Feature",
  "properties": {
    "iso:country":"US",
    "sg:address":"1984 Yount Mill Rd",
    "sg:city":"Napa",
    "sg:classifiers":[
        {
            "category":"Professional",
            "subcategory":"Management & Consulting",
            "type":"Services"
        }
    ],
    "sg:phone":"+1 707 287 6753",
    "sg:postcode":"94558",
    "sg:province":"CA",
    "sg:tags":[
        "consultant"
    ],
    "wof:name":"Go For Dea, Inc.",
    "wof:placetype":"venue"
},
  "geometry": {"coordinates":[-122.37036999999999,38.417691],"type":"Point"}
}