{
  "type": "Feature",
  "properties": {
    "addr:full":"1156 Pollock St Rosemead CA 91770",
    "addr:housenumber":"1156",
    "addr:postcode":"91770",
    "addr:street":"Pollock St",
    "iso:country":"US",
    "sg:address":"1156 Pollock St",
    "sg:city":"Rosemead",
    "sg:classifiers":[
        {
            "category":"Wholesale",
            "subcategory":"Electrical",
            "type":"Manufacturing & Wholesale Goods"
        }
    ],
    "sg:phone":"+1 626 307 9543",
    "sg:postcode":"91770",
    "sg:province":"CA",
    "sg:tags":[
        "equipment"
    ],
    "wof:name":"Deltronics",
    "wof:placetype":"venue"
},
  "geometry": {"coordinates":[-118.09187799999999,34.043583],"type":"Point"}
}