{
  "type": "Feature",
  "properties": {
    "addr:full":"192 Cedarwood Ave Duarte CA 91010",
    "addr:housenumber":"192",
    "addr:postcode":"91010",
    "addr:street":"Cedarwood Ave",
    "iso:country":"US",
    "sg:address":"192 Cedarwood Ave",
    "sg:city":"Duarte",
    "sg:classifiers":[
        {
            "category":"Organizations",
            "subcategory":"Non-profit Organization",
            "type":"Services"
        }
    ],
    "sg:phone":"+1 626 303 2244",
    "sg:postcode":"91010",
    "sg:province":"CA",
    "sg:tags":[
        "charitable",
        "institution"
    ],
    "sg:website":"www.bountifulharvest.org",
    "wof:name":"Bountiful Harvest",
    "wof:placetype":"venue"
},
  "geometry": {"coordinates":[-117.947233,34.153639],"type":"Point"}
}