{
  "type": "Feature",
  "properties": {
    "addr:full":"1140 E Ontario Ave Corona CA 92881",
    "addr:housenumber":"1140",
    "addr:postcode":"92881",
    "addr:street":"E Ontario Ave",
    "iso:country":"US",
    "sg:address":"1140 E Ontario Ave",
    "sg:city":"Corona",
    "sg:classifiers":[
        {
            "category":"Autos & Motor Vehicles",
            "subcategory":"Fuel & Gas Station",
            "type":"Retail Goods"
        }
    ],
    "sg:phone":"+1 951 278 4260",
    "sg:postcode":"92881",
    "sg:province":"CA",
    "sg:tags":[
        "oil"
    ],
    "wof:name":"Chevron",
    "wof:placetype":"venue"
},
  "geometry": {"coordinates":[-117.541819,33.847691],"type":"Point"}
}