{
  "type": "Feature",
  "properties": {
    "iso:country":"US",
    "sg:address":"30101 Agoura Ct",
    "sg:city":"Agoura Hills",
    "sg:classifiers":[
        {
            "category":"Education",
            "subcategory":"Special Training",
            "type":"Public Place"
        }
    ],
    "sg:phone":"+1 818 575 9673",
    "sg:postcode":"91301",
    "sg:province":"CA",
    "sg:tags":[
        "instruction",
        "driving"
    ],
    "wof:name":"On-Line Traffic School",
    "wof:placetype":"venue"
},
  "geometry": {"coordinates":[-118.776892,34.145509],"type":"Point"}
}