{
  "type": "Feature",
  "properties": {
    "addr:full":"4210 Holden St Emeryville CA 94608",
    "addr:housenumber":"4210",
    "addr:postcode":"94608",
    "addr:street":"Holden St",
    "iso:country":"US",
    "sg:address":"4210 Holden St",
    "sg:city":"Emeryville",
    "sg:classifiers":[
        {
            "category":"Professional",
            "type":"Services"
        }
    ],
    "sg:phone":"+1 510 601 6200",
    "sg:postcode":"94608",
    "sg:province":"CA",
    "sg:tags":[
        "establishment"
    ],
    "wof:name":"Mohlabane Namane",
    "wof:placetype":"venue"
},
  "geometry": {"coordinates":[-122.287257,37.832048],"type":"Point"}
}