{
  "type": "Feature",
  "properties": {
    "iso:country":"US",
    "sg:address":"150 N Jackson Ave",
    "sg:city":"San Jose",
    "sg:classifiers":[
        {
            "category":"Health Services",
            "subcategory":"Doctor",
            "type":"Services"
        }
    ],
    "sg:phone":"+1 408 259 4515",
    "sg:postcode":"95116",
    "sg:province":"CA",
    "sg:tags":[
        "dentist"
    ],
    "wof:name":"Don A Stevenson Inc",
    "wof:placetype":"venue"
},
  "geometry": {"coordinates":[-121.846977,37.362019],"type":"Point"}
}