{
  "type": "Feature",
  "properties": {
    "addr:full":"1103 Johnson Ave San Luis Obispo CA 93401",
    "addr:housenumber":"1103",
    "addr:postcode":"93401",
    "addr:street":"Johnson Ave",
    "iso:country":"US",
    "sg:address":"1103 Johnson Ave",
    "sg:city":"San Luis Obispo",
    "sg:classifiers":[
        {
            "category":"Professional",
            "subcategory":"Lawyer & Legal Services",
            "type":"Services"
        }
    ],
    "sg:phone":"+1 805 541 8700",
    "sg:postcode":"93401",
    "sg:province":"CA",
    "sg:tags":[
        "attorney"
    ],
    "wof:name":"R Kevin Owens",
    "wof:placetype":"venue"
},
  "geometry": {"coordinates":[-120.65658500000001,35.283542],"type":"Point"}
}