{
  "type": "Feature",
  "properties": {
    "iso:country":"US",
    "sg:address":"1103 Johnson Ave",
    "sg:city":"San Luis Obispo",
    "sg:classifiers":[
        {
            "category":"Professional",
            "subcategory":"Lawyer & Legal Services",
            "type":"Services"
        }
    ],
    "sg:phone":"+1 805 541 8700",
    "sg:postcode":"93401",
    "sg:province":"CA",
    "sg:tags":[
        "attorney"
    ],
    "wof:name":"R Kevin Owens",
    "wof:placetype":"venue"
},
  "geometry": {"coordinates":[-120.656585,35.283542],"type":"Point"}
}