{
  "type": "Feature",
  "properties": {
    "iso:country":"US",
    "sg:address":"414 Jackson St",
    "sg:city":"San Francisco",
    "sg:classifiers":[
        {
            "category":"Health Services",
            "subcategory":"Health Practitioner",
            "type":"Services"
        }
    ],
    "sg:phone":"+1 415 391 3993",
    "sg:postcode":"94111",
    "sg:province":"CA",
    "sg:tags":[
        "acupuncture"
    ],
    "wof:name":"CHENG ANGELI LAC",
    "wof:placetype":"venue"
},
  "geometry": {"coordinates":[-122.402224,37.796724],"type":"Point"}
}