{
  "type": "Feature",
  "properties": {
    "iso:country":"US",
    "sg:address":"5939 W Pico Blvd",
    "sg:city":"Los Angeles",
    "sg:classifiers":[
        {
            "category":"Building & Trades",
            "subcategory":"Construction",
            "type":"Services"
        }
    ],
    "sg:phone":"+1 323 938 6207",
    "sg:postcode":"90035",
    "sg:province":"CA",
    "sg:tags":[
        "repairing",
        "remodeling",
        "contractor"
    ],
    "wof:name":"So Cal Kitchen & Bath",
    "wof:placetype":"venue"
},
  "geometry": {"coordinates":[-118.368802,34.051989],"type":"Point"}
}