{
  "type": "Feature",
  "properties": {
    "addr:full":"722 Baker Street Costa Mesa CA 92626",
    "addr:housenumber":"722",
    "addr:postcode":"92626",
    "addr:street":"Baker Street",
    "iso:country":"US",
    "sg:address":"722 Baker Street",
    "sg:city":"Costa Mesa",
    "sg:classifiers":[
        {
            "category":"Health Services",
            "subcategory":"Doctor",
            "type":"Services"
        }
    ],
    "sg:phone":"+1 714 557 6300",
    "sg:postcode":"92626",
    "sg:province":"CA",
    "sg:tags":[
        "practice",
        "family"
    ],
    "wof:name":"Bristol Park Medical Group",
    "wof:placetype":"venue"
},
  "geometry": {"coordinates":[-117.885745,33.680189],"type":"Point"}
}