{
  "type": "Feature",
  "properties": {
    "addr:full":"601 Union St San Francisco CA 94133",
    "addr:housenumber":"601",
    "addr:postcode":"94133",
    "addr:street":"Union St",
    "iso:country":"US",
    "sg:address":"601 Union St",
    "sg:city":"San Francisco",
    "sg:classifiers":[
        {
            "category":"Restaurant",
            "type":"Food & Drink"
        }
    ],
    "sg:phone":"+1 415 986 1886",
    "sg:postcode":"94133",
    "sg:province":"CA",
    "sg:website":"www.fior.com",
    "wof:name":"Fior D'Italia Restaurant",
    "wof:placetype":"venue"
},
  "geometry": {"coordinates":[-122.410207,37.800315],"type":"Point"}
}