{
  "type": "Feature",
  "properties": {
    "addr:full":"595 N Arrowhead Ave San Bernardino CA 92401",
    "addr:housenumber":"595",
    "addr:postcode":"92401",
    "addr:street":"N Arrowhead Ave",
    "iso:country":"US",
    "sg:address":"595 N Arrowhead Ave",
    "sg:city":"San Bernardino",
    "sg:classifiers":[
        {
            "category":"Organizations",
            "subcategory":"Non-profit Organization",
            "type":"Services"
        }
    ],
    "sg:phone":"+1 909 381 6333",
    "sg:postcode":"92401",
    "sg:province":"CA",
    "sg:tags":[
        "info",
        "addiction",
        "abuse",
        "treatment",
        "drug"
    ],
    "wof:name":"Pride Program",
    "wof:placetype":"venue"
},
  "geometry": {"coordinates":[-117.289601,34.108399],"type":"Point"}
}