{
  "type": "Feature",
  "properties": {
    "addr:full":"1470 S Main St Willits CA 95490",
    "addr:housenumber":"1470",
    "addr:postcode":"95490",
    "addr:street":"S Main St",
    "iso:country":"US",
    "sg:address":"1470 S Main St",
    "sg:city":"Willits",
    "sg:classifiers":[
        {
            "category":"Personal",
            "subcategory":"Beauty Salon",
            "type":"Services"
        }
    ],
    "sg:phone":"+1 707 459 0398",
    "sg:postcode":"95490",
    "sg:province":"CA",
    "wof:name":"Tips & Toes Nail Salon",
    "wof:placetype":"venue"
},
  "geometry": {"coordinates":[-123.349311,39.395346],"type":"Point"}
}