{
  "type": "Feature",
  "properties": {
    "addr:full":"1030 N Mountain Ave Ontario CA 91762",
    "addr:housenumber":"1030",
    "addr:postcode":"91762",
    "addr:street":"N Mountain Ave",
    "iso:country":"US",
    "sg:address":"1030 N Mountain Ave",
    "sg:city":"Ontario",
    "sg:classifiers":[
        {
            "category":"Transit Center",
            "subcategory":"Freight",
            "type":"Transportation"
        },
        {
            "category":"Freight",
            "type":"Transportation"
        },
        {
            "category":"Taxi",
            "type":"Transportation"
        }
    ],
    "sg:phone":"+1 909 946 0616",
    "sg:postcode":"91762",
    "sg:province":"CA",
    "sg:tags":[
        "delivery",
        "local",
        "trucking-motor",
        "trucking"
    ],
    "wof:name":"Bullet Delivery",
    "wof:placetype":"venue"
},
  "geometry": {"coordinates":[-117.670102,34.07658],"type":"Point"}
}