{
  "type": "Feature",
  "properties": {
    "iso:country":"US",
    "sg:address":"19655 Stevens Creek Blvd",
    "sg:city":"Cupertino",
    "sg:classifiers":[
        {
            "category":"Personal",
            "subcategory":"Beauty Salon",
            "type":"Services"
        }
    ],
    "sg:phone":"+1 408 996 0673",
    "sg:postcode":"95014",
    "sg:province":"CA",
    "sg:tags":[
        "hair"
    ],
    "sg:website":"www.sassyhairsalon.com",
    "wof:name":"Sassy International Hair Salon",
    "wof:placetype":"venue"
},
  "geometry": {"coordinates":[-122.01799800000001,37.322899],"type":"Point"}
}