{
  "type": "Feature",
  "properties": {
    "addr:full":"5721 Lincoln Ave Ste B Cypress CA 90630",
    "addr:housenumber":"5721",
    "addr:postcode":"90630",
    "addr:street":"Lincoln Ave Ste B",
    "iso:country":"US",
    "sg:address":"5721 Lincoln Ave Ste B",
    "sg:city":"Cypress",
    "sg:classifiers":[
        {
            "category":"Food & Beverages",
            "subcategory":"Meat & Fish",
            "type":"Retail Goods"
        }
    ],
    "sg:phone":"+1 714 761 4031",
    "sg:postcode":"90630",
    "sg:province":"CA",
    "sg:tags":[
        "shop"
    ],
    "wof:name":"Martinez Meat Market",
    "wof:placetype":"venue"
},
  "geometry": {"coordinates":[-118.03299699999999,33.831799],"type":"Point"}
}