{
  "type": "Feature",
  "properties": {
    "iso:country":"US",
    "sg:address":"6614 School Circle Dr",
    "sg:city":"Riverside",
    "sg:classifiers":[
        {
            "category":"Real Estate",
            "subcategory":"Real Estate Agent",
            "type":"Services"
        }
    ],
    "sg:phone":"+1 951 341 0123",
    "sg:postcode":"92506",
    "sg:province":"CA",
    "wof:name":"Cornerstone Realtors",
    "wof:placetype":"venue"
},
  "geometry": {"coordinates":[-117.399654,33.95173],"type":"Point"}
}