{
  "type": "Feature",
  "properties": {
    "addr:full":"12131 Telegraph Rd Santa Fe Springs CA 90670",
    "addr:housenumber":"12131",
    "addr:postcode":"90670",
    "addr:street":"Telegraph Rd",
    "iso:country":"US",
    "sg:address":"12131 Telegraph Rd",
    "sg:city":"Santa Fe Springs",
    "sg:classifiers":[
        {
            "category":"Government",
            "subcategory":"Office",
            "type":"Public Place"
        }
    ],
    "sg:phone":"+1 562 347 4663",
    "sg:postcode":"90670",
    "sg:province":"CA",
    "sg:tags":[
        "executive"
    ],
    "wof:name":"Housing Authority of The Count",
    "wof:placetype":"venue"
},
  "geometry": {"coordinates":[-118.073483,33.942191],"type":"Point"}
}