{
  "type": "Feature",
  "properties": {
    "addr:full":"2425 Church Ln San Pablo CA 94806",
    "addr:housenumber":"2425",
    "addr:postcode":"94806",
    "addr:street":"Church Ln",
    "iso:country":"US",
    "sg:address":"2425 Church Ln",
    "sg:city":"San Pablo",
    "sg:classifiers":[
        {
            "category":"Real Estate",
            "subcategory":"Real Estate Operator",
            "type":"Services"
        }
    ],
    "sg:phone":"+1 510 234 2230",
    "sg:postcode":"94806",
    "sg:province":"CA",
    "sg:tags":[
        "mobile",
        "home",
        "community"
    ],
    "wof:name":"Gerken's Mobile Home Court",
    "wof:placetype":"venue"
},
  "geometry": {"coordinates":[-122.33668299999999,37.961682],"type":"Point"}
}