{
  "type": "Feature",
  "properties": {
    "addr:full":"2443 Sierra Nevada Rd Mammoth Lakes CA 93546",
    "addr:housenumber":"2443",
    "addr:postcode":"93546",
    "addr:street":"Sierra Nevada Rd",
    "iso:country":"US",
    "sg:address":"2443 Sierra Nevada Rd",
    "sg:city":"Mammoth Lakes",
    "sg:classifiers":[
        {
            "category":"Real Estate",
            "subcategory":"Real Estate Operator",
            "type":"Services"
        }
    ],
    "sg:phone":"+1 760 934 4990",
    "sg:postcode":"93546",
    "sg:province":"CA",
    "sg:tags":[
        "condominium"
    ],
    "wof:name":"LA Residence Iv",
    "wof:placetype":"venue"
},
  "geometry": {"coordinates":[-118.97179300000001,37.642017],"type":"Point"}
}