{
  "type": "Feature",
  "properties": {
    "addr:full":"10491 Magnolia Ave Riverside CA 92505",
    "addr:housenumber":"10491",
    "addr:postcode":"92505",
    "addr:street":"Magnolia Ave",
    "iso:country":"US",
    "sg:address":"10491 Magnolia Ave",
    "sg:city":"Riverside",
    "sg:classifiers":[
        {
            "category":"Shopping",
            "subcategory":"Stationery & Office Supplies",
            "type":"Retail Goods"
        }
    ],
    "sg:phone":"+1 951 343 3380",
    "sg:postcode":"92505",
    "sg:province":"CA",
    "sg:tags":[
        "rubber",
        "stamp",
        "plastic"
    ],
    "wof:name":"Stamp Shack",
    "wof:placetype":"venue"
},
  "geometry": {"coordinates":[-117.461867,33.911752],"type":"Point"}
}