{
  "type": "Feature",
  "properties": {
    "iso:country":"US",
    "sg:address":"8121 Madison Ave #G4",
    "sg:city":"Fair Oaks",
    "sg:classifiers":[
        {
            "category":"Restaurant",
            "type":"Food & Drink"
        }
    ],
    "sg:phone":"+1 916 967 1550",
    "sg:postcode":"95628",
    "sg:province":"CA",
    "sg:tags":[
        "indian"
    ],
    "sg:website":"www.naanindiagrill.com",
    "wof:name":"Naan India Grill",
    "wof:placetype":"venue"
},
  "geometry": {"coordinates":[-121.26029,38.664691],"type":"Point"}
}