{
  "type": "Feature",
  "properties": {
    "addr:full":"350 Crown Point Cir Grass Valley CA 95945",
    "addr:housenumber":"350",
    "addr:postcode":"95945",
    "addr:street":"Crown Point Cir",
    "iso:country":"US",
    "sg:address":"350 Crown Point Cir",
    "sg:city":"Grass Valley",
    "sg:classifiers":[
        {
            "category":"Professional",
            "subcategory":"Employment Agencies",
            "type":"Services"
        }
    ],
    "sg:phone":"+1 530 274 5601",
    "sg:postcode":"95945",
    "sg:province":"CA",
    "sg:tags":[
        "opportunity"
    ],
    "wof:name":"Nevada Sierra Regal IHSS",
    "wof:placetype":"venue"
},
  "geometry": {"coordinates":[-121.030046,39.220792],"type":"Point"}
}