{
  "type": "Feature",
  "properties": {
    "addr:full":"45 Franklin Street San Francisco CA 94102",
    "addr:housenumber":"45",
    "addr:postcode":"94102",
    "addr:street":"Franklin Street",
    "iso:country":"US",
    "sg:address":"45 Franklin Street",
    "sg:city":"San Francisco",
    "sg:classifiers":[
        {
            "category":"Health Services",
            "subcategory":"Clinic",
            "type":"Services"
        }
    ],
    "sg:phone":"+1 415 552 1540",
    "sg:postcode":"94102",
    "sg:province":"CA",
    "sg:tags":[
        "counseling",
        "mental"
    ],
    "wof:name":"Seaman Rosemary Mft",
    "wof:placetype":"venue"
},
  "geometry": {"coordinates":[-122.420998,37.774799],"type":"Point"}
}