{
  "type": "Feature",
  "properties": {
    "addr:full":"2089 Curtner Ave San Jose CA 95124",
    "addr:housenumber":"2089",
    "addr:postcode":"95124",
    "addr:street":"Curtner Ave",
    "iso:country":"US",
    "sg:address":"2089 Curtner Ave",
    "sg:city":"San Jose",
    "sg:classifiers":[
        {
            "category":"Manufacturing",
            "subcategory":"Printing",
            "type":"Manufacturing & Wholesale Goods"
        }
    ],
    "sg:phone":"+1 408 377 7856",
    "sg:postcode":"95124",
    "sg:province":"CA",
    "sg:tags":[
        "offset"
    ],
    "wof:name":"A & E Print Shop",
    "wof:placetype":"venue"
},
  "geometry": {"coordinates":[-121.934758,37.272621],"type":"Point"}
}