{
  "type": "Feature",
  "properties": {
    "iso:country":"US",
    "sg:address":"1181 Magnolia Ave",
    "sg:city":"Corona",
    "sg:classifiers":[
        {
            "category":"Personal",
            "type":"Services"
        }
    ],
    "sg:phone":"+1 951 735 6022",
    "sg:postcode":"92879",
    "sg:province":"CA",
    "sg:tags":[
        "mail",
        "receiving"
    ],
    "wof:name":"Pak Mail Bus Ctr Of Corona",
    "wof:placetype":"venue"
},
  "geometry": {"coordinates":[-117.546814,33.863377],"type":"Point"}
}