{
  "type": "Feature",
  "properties": {
    "addr:full":"28715 Los Alisos Blvd Ste 7 Mission Viejo CA 92692",
    "addr:housenumber":"28715",
    "addr:postcode":"92692",
    "addr:street":"Los Alisos Blvd Ste 7",
    "iso:country":"US",
    "sg:address":"28715 Los Alisos Blvd Ste 7",
    "sg:city":"Mission Viejo",
    "sg:classifiers":[
        {
            "category":"Professional",
            "subcategory":"Lawyer & Legal Services",
            "type":"Services"
        },
        {
            "category":"Professional",
            "subcategory":"Printing & Photocopies",
            "type":"Services"
        }
    ],
    "sg:phone":"+1 949 461 0034",
    "sg:postcode":"92692",
    "sg:province":"CA",
    "sg:tags":[
        "notary"
    ],
    "wof:name":"Aim Mail Center",
    "wof:placetype":"venue"
},
  "geometry": {"coordinates":[-117.633003,33.656399],"type":"Point"}
}