{
  "type": "Feature",
  "properties": {
    "iso:country":"US",
    "sg:address":"532 S Lorena St",
    "sg:city":"Los Angeles",
    "sg:classifiers":[
        {
            "category":"Restaurant",
            "type":"Food & Drink"
        }
    ],
    "sg:phone":"+1 323 261 0390",
    "sg:postcode":"90063",
    "sg:province":"CA",
    "sg:tags":[
        "mexican"
    ],
    "sg:website":"www.cemitaspoblanasjuquilita.com",
    "wof:name":"Juquilita Restaurant",
    "wof:placetype":"venue"
},
  "geometry": {"coordinates":[-118.198268,34.031375],"type":"Point"}
}