{
  "type": "Feature",
  "properties": {
    "iso:country":"US",
    "sg:address":"340 W K St",
    "sg:city":"Brawley",
    "sg:classifiers":[
        {
            "category":"Farming",
            "subcategory":"Farm & Veterinary Services",
            "type":"Manufacturing & Wholesale Goods"
        }
    ],
    "sg:phone":"+1 760 344 7410",
    "sg:postcode":"92227",
    "sg:province":"CA",
    "sg:tags":[
        "harvesting"
    ],
    "wof:name":"Southwest Leveling LLC",
    "wof:placetype":"venue"
},
  "geometry": {"coordinates":[-115.546603,32.973045],"type":"Point"}
}