{
  "type": "Feature",
  "properties": {
    "iso:country":"US",
    "sg:address":"1147 Hilltop Dr",
    "sg:city":"Redding",
    "sg:classifiers":[
        {
            "category":"Professional",
            "subcategory":"Accounting & Tax Preparation",
            "type":"Services"
        }
    ],
    "sg:phone":"+1 530 221 3343",
    "sg:postcode":"96003",
    "sg:province":"CA",
    "sg:tags":[
        "accountant"
    ],
    "wof:name":"NJMJ",
    "wof:placetype":"venue"
},
  "geometry": {"coordinates":[-122.358028,40.589881],"type":"Point"}
}