{
  "type": "Feature",
  "properties": {
    "addr:full":"18576 Prospect Rd Saratoga CA 95129",
    "addr:housenumber":"18576",
    "addr:postcode":"95129",
    "addr:street":"Prospect Rd",
    "iso:country":"US",
    "sg:address":"18576 Prospect Rd",
    "sg:city":"Saratoga",
    "sg:classifiers":[
        {
            "category":"Sports & Exercise",
            "subcategory":"Gym",
            "type":"Entertainment"
        }
    ],
    "sg:phone":"+1 408 725 0847",
    "sg:postcode":"95129",
    "sg:province":"CA",
    "sg:tags":[
        "club",
        "health",
        "studio",
        "gymnasium"
    ],
    "wof:name":"Shapexpress For Women",
    "wof:placetype":"venue"
},
  "geometry": {"coordinates":[-122.002377,37.292961],"type":"Point"}
}