{
  "type": "Feature",
  "properties": {
    "addr:full":"555 Canyon Rd Redwood City CA 94062",
    "addr:housenumber":"555",
    "addr:postcode":"94062",
    "addr:street":"Canyon Rd",
    "iso:country":"US",
    "sg:address":"555 Canyon Rd",
    "sg:city":"Redwood City",
    "sg:classifiers":[
        {
            "category":"Building & Trades",
            "subcategory":"Electrical",
            "type":"Services"
        }
    ],
    "sg:phone":"+1 650 365 4537",
    "sg:postcode":"94062",
    "sg:province":"CA",
    "sg:tags":[
        "electric",
        "contractor"
    ],
    "wof:name":"City Electric",
    "wof:placetype":"venue"
},
  "geometry": {"coordinates":[-122.260802,37.473653],"type":"Point"}
}