{
  "type": "Feature",
  "properties": {
    "iso:country":"US",
    "sg:address":"2515 Mission St",
    "sg:city":"San Francisco",
    "sg:classifiers":[
        {
            "category":"Travel",
            "subcategory":"Travel Agent",
            "type":"Entertainment"
        }
    ],
    "sg:phone":"+1 415 282 6944",
    "sg:postcode":"94110",
    "sg:province":"CA",
    "sg:website":"www.travelnetvacations.com",
    "wof:name":"TravelNet Vacations",
    "wof:placetype":"venue"
},
  "geometry": {"coordinates":[-122.418904,37.756819],"type":"Point"}
}