{
  "type": "Feature",
  "properties": {
    "addr:full":"4211 Admiralty Way Marina Del Rey CA 90292",
    "addr:housenumber":"4211",
    "addr:postcode":"90292",
    "addr:street":"Admiralty Way",
    "iso:country":"US",
    "sg:address":"4211 Admiralty Way",
    "sg:city":"Marina Del Rey",
    "sg:classifiers":[
        {
            "category":"Restaurant",
            "type":"Food & Drink"
        }
    ],
    "sg:phone":"+1 310 577 4558",
    "sg:postcode":"90292",
    "sg:province":"CA",
    "sg:website":"www.harborhouse-mdr.com",
    "wof:name":"Edie's Diner",
    "wof:placetype":"venue"
},
  "geometry": {"coordinates":[-118.45722499999999,33.983664],"type":"Point"}
}