{
  "type": "Feature",
  "properties": {
    "addr:full":"1521 Rugby Cir Thousand Oaks CA 91360",
    "addr:housenumber":"1521",
    "addr:postcode":"91360",
    "addr:street":"Rugby Cir",
    "iso:country":"US",
    "sg:address":"1521 Rugby Cir",
    "sg:city":"Thousand Oaks",
    "sg:classifiers":[
        {
            "category":"Professional",
            "subcategory":"Business Services",
            "type":"Services"
        }
    ],
    "sg:phone":"+1 818 706 7366",
    "sg:postcode":"91360",
    "sg:province":"CA",
    "wof:name":"JSI",
    "wof:placetype":"venue"
},
  "geometry": {"coordinates":[-118.874437,34.199567],"type":"Point"}
}