{
  "type": "Feature",
  "properties": {
    "iso:country":"US",
    "sg:address":"4133 Ave de la Plata",
    "sg:city":"Oceanside",
    "sg:classifiers":[
        {
            "category":"Professional",
            "subcategory":"Management & Consulting",
            "type":"Services"
        }
    ],
    "sg:phone":"+1 760 940 9455",
    "sg:postcode":"92057",
    "sg:province":"CA",
    "sg:tags":[
        "marketing",
        "program"
    ],
    "sg:website":"www.mailingjet.com",
    "wof:name":"Mailing House",
    "wof:placetype":"venue"
},
  "geometry": {"coordinates":[-117.29368,33.209173],"type":"Point"}
}