{
  "type": "Feature",
  "properties": {
    "addr:full":"575 Carmody Rd Petaluma CA 94952",
    "addr:housenumber":"575",
    "addr:postcode":"94952",
    "addr:street":"Carmody Rd",
    "iso:country":"US",
    "sg:address":"575 Carmody Rd",
    "sg:city":"Petaluma",
    "sg:classifiers":[
        {
            "category":"Farming",
            "subcategory":"Dairy Farm",
            "type":"Manufacturing & Wholesale Goods"
        }
    ],
    "sg:phone":"+1 707 762 3996",
    "sg:postcode":"94952",
    "sg:province":"CA",
    "wof:name":"Martinoni Dairy",
    "wof:placetype":"venue"
},
  "geometry": {"coordinates":[-122.841658,38.276634],"type":"Point"}
}