{
  "type": "Feature",
  "properties": {
    "iso:country":"US",
    "sg:address":"10777 Fenwick Rd",
    "sg:city":"San Diego",
    "sg:classifiers":[
        {
            "category":"Manufacturing",
            "subcategory":"Metals",
            "type":"Manufacturing & Wholesale Goods"
        }
    ],
    "sg:phone":"+1 858 693 3845",
    "sg:postcode":"92126",
    "sg:province":"CA",
    "sg:tags":[
        "tool",
        "mfg"
    ],
    "wof:name":"Le Palm Inc",
    "wof:placetype":"venue"
},
  "geometry": {"coordinates":[-117.151307,32.912924],"type":"Point"}
}