{
  "type": "Feature",
  "properties": {
    "iso:country":"US",
    "sg:address":"187 E Wilbur Rd",
    "sg:city":"Thousand Oaks",
    "sg:classifiers":[
        {
            "category":"Professional",
            "subcategory":"Lawyer & Legal Services",
            "type":"Services"
        }
    ],
    "sg:phone":"+1 805 230 2140",
    "sg:postcode":"91360",
    "sg:province":"CA",
    "sg:tags":[
        "attorney"
    ],
    "wof:name":"David E Rowe Law Offices",
    "wof:placetype":"venue"
},
  "geometry": {"coordinates":[-118.874589,34.186668],"type":"Point"}
}