{
  "type": "Feature",
  "properties": {
    "addr:full":"505 14th St Ste 500 Oakland CA 94612",
    "addr:housenumber":"505",
    "addr:postcode":"94612",
    "addr:street":"14Th St Ste 500",
    "iso:country":"US",
    "sg:address":"505 14th St Ste 500",
    "sg:city":"Oakland",
    "sg:classifiers":[
        {
            "category":"Health Services",
            "subcategory":"Doctor",
            "type":"Services"
        },
        {
            "category":"Health Services",
            "subcategory":"Hospital",
            "type":"Services"
        }
    ],
    "sg:phone":"+1 510 768 0066",
    "sg:postcode":"94612",
    "sg:province":"CA",
    "sg:tags":[
        "nursing",
        "consultant",
        "medical",
        "practice",
        "home"
    ],
    "sg:website":"http://www.healthcarefinancialsolutions.com",
    "wof:name":"Hfs Consultants",
    "wof:placetype":"venue"
},
  "geometry": {"coordinates":[-122.272536,37.804887],"type":"Point"}
}