{
  "type": "Feature",
  "properties": {
    "iso:country":"US",
    "sg:address":"31633 Thelma Ave",
    "sg:city":"Thousand Palms",
    "sg:classifiers":[
        {
            "category":"Building & Trades",
            "subcategory":"Landscaping Services",
            "type":"Services"
        }
    ],
    "sg:phone":"+1 760 343 0248",
    "sg:postcode":"92276",
    "sg:province":"CA",
    "wof:name":"Rafael Diaz Gardening Service",
    "wof:placetype":"venue"
},
  "geometry": {"coordinates":[-116.394364,33.819818],"type":"Point"}
}