{
  "type": "Feature",
  "properties": {
    "iso:country":"US",
    "sg:address":"10174 Old Grove Rd",
    "sg:city":"San Diego",
    "sg:classifiers":[
        {
            "category":"Professional",
            "type":"Services"
        }
    ],
    "sg:phone":"+1 858 586 7438",
    "sg:postcode":"92131",
    "sg:province":"CA",
    "wof:name":"Net Sift Inc",
    "wof:placetype":"venue"
},
  "geometry": {"coordinates":[-117.111817,32.899068],"type":"Point"}
}