{
  "type": "Feature",
  "properties": {
    "iso:country":"US",
    "sg:address":"1213 Center St",
    "sg:city":"Stockton",
    "sg:classifiers":[
        {
            "category":"Wholesale",
            "subcategory":"Durable Goods & Equipment",
            "type":"Manufacturing & Wholesale Goods"
        }
    ],
    "sg:phone":"+1 209 948 3010",
    "sg:postcode":"95202",
    "sg:province":"CA",
    "sg:tags":[
        "exporter"
    ],
    "wof:name":"Dario's Import & Export",
    "wof:placetype":"venue"
},
  "geometry": {"coordinates":[-121.294625,37.965171],"type":"Point"}
}