{
  "type": "Feature",
  "properties": {
    "iso:country":"US",
    "sg:address":"2190 W 190th St",
    "sg:city":"Torrance",
    "sg:classifiers":[
        {
            "category":"Building & Trades",
            "subcategory":"Electrical",
            "type":"Services"
        }
    ],
    "sg:phone":"+1 310 618 0355",
    "sg:postcode":"90504",
    "sg:province":"CA",
    "sg:tags":[
        "transmission",
        "equipment",
        "power"
    ],
    "wof:name":"Gc Protronics",
    "wof:placetype":"venue"
},
  "geometry": {"coordinates":[-118.317628,33.858332],"type":"Point"}
}