{
  "type": "Feature",
  "properties": {
    "iso:country":"US",
    "sg:address":"3330 E Hammer Ln Ste D",
    "sg:city":"Stockton",
    "sg:classifiers":[
        {
            "category":"Insurance",
            "subcategory":"Hazard Insurance",
            "type":"Services"
        }
    ],
    "sg:phone":"+1 209 235 7777",
    "sg:postcode":"95212",
    "sg:province":"CA",
    "wof:name":"Confidence Plus Insurance Services",
    "wof:placetype":"venue"
},
  "geometry": {"coordinates":[-121.27336200000001,38.021031],"type":"Point"}
}