{
  "type": "Feature",
  "properties": {
    "iso:country":"US",
    "sg:address":"17845 Sky Park Cir",
    "sg:city":"Irvine",
    "sg:classifiers":[
        {
            "category":"Professional",
            "type":"Services"
        }
    ],
    "sg:phone":"+1 949 387 0420",
    "sg:postcode":"92614",
    "sg:province":"CA",
    "wof:name":"Epassives",
    "wof:placetype":"venue"
},
  "geometry": {"coordinates":[-117.857322,33.691222],"type":"Point"}
}