{
  "type": "Feature",
  "properties": {
    "addr:full":"710 W Shaw Ave Fresno CA 93711",
    "addr:housenumber":"710",
    "addr:postcode":"93711",
    "addr:street":"W Shaw Ave",
    "iso:country":"US",
    "sg:address":"710 W Shaw Ave",
    "sg:city":"Fresno",
    "sg:classifiers":[
        {
            "category":"Shopping",
            "subcategory":"Clothing, Apparel, & Fashions",
            "type":"Retail Goods"
        }
    ],
    "sg:phone":"+1 559 227 3348",
    "sg:postcode":"93711",
    "sg:province":"CA",
    "wof:name":"Ann Taylor",
    "wof:placetype":"venue"
},
  "geometry": {"coordinates":[-119.804992,36.808477],"type":"Point"}
}