{
  "type": "Feature",
  "properties": {
    "addr:full":"7726 Girard Ave La Jolla CA 92039",
    "addr:housenumber":"7726",
    "addr:postcode":"92039",
    "addr:street":"Girard Ave",
    "iso:country":"US",
    "sg:address":"7726 Girard Ave",
    "sg:city":"La Jolla",
    "sg:classifiers":[
        {
            "category":"Home & Garden",
            "subcategory":"Home Furnishings",
            "type":"Retail Goods"
        },
        {
            "category":"Home & Garden",
            "subcategory":"Furniture",
            "type":"Retail Goods"
        }
    ],
    "sg:phone":"+1 858 454 3366",
    "sg:postcode":"92039",
    "sg:province":"CA",
    "sg:tags":[
        "decor",
        "store"
    ],
    "sg:website":"www.ligne-roset-usa.com",
    "wof:name":"Ligne Roset",
    "wof:placetype":"venue"
},
  "geometry": {"coordinates":[-117.274002,32.844002],"type":"Point"}
}