{
  "type": "Feature",
  "properties": {
    "addr:full":"21760 Stevens Creek Blvd Cupertino CA 95014",
    "addr:housenumber":"21760",
    "addr:postcode":"95014",
    "addr:street":"Stevens Creek Blvd",
    "iso:country":"US",
    "sg:address":"21760 Stevens Creek Blvd",
    "sg:city":"Cupertino",
    "sg:classifiers":[
        {
            "category":"Health Services",
            "subcategory":"Health Practitioner",
            "type":"Services"
        }
    ],
    "sg:phone":"+1 408 257 6881",
    "sg:postcode":"95014",
    "sg:province":"CA",
    "sg:tags":[
        "psychotherapist"
    ],
    "wof:name":"Bay Area Family Training Assoc",
    "wof:placetype":"venue"
},
  "geometry": {"coordinates":[-122.05445,37.322839],"type":"Point"}
}