{
  "type": "Feature",
  "properties": {
    "iso:country":"US",
    "sg:address":"12821 Newport Ave",
    "sg:city":"Tustin",
    "sg:classifiers":[
        {
            "category":"Personal",
            "type":"Services"
        }
    ],
    "sg:phone":"+1 714 505 0050",
    "sg:postcode":"92780",
    "sg:province":"CA",
    "sg:tags":[
        "party",
        "planning",
        "event"
    ],
    "wof:name":"Lux5 Events",
    "wof:placetype":"venue"
},
  "geometry": {"coordinates":[-117.809783,33.75073],"type":"Point"}
}