{
  "type": "Feature",
  "properties": {
    "iso:country":"US",
    "sg:address":"1201 Alhambra Blvd # 110",
    "sg:city":"Sacramento",
    "sg:classifiers":[
        {
            "category":"Health Services",
            "subcategory":"Clinic",
            "type":"Services"
        }
    ],
    "sg:phone":"+1 916 733 8222",
    "sg:postcode":"95816",
    "sg:province":"CA",
    "sg:tags":[
        "information",
        "outpatient",
        "alcoholism",
        "treatment"
    ],
    "sg:website":"http://www.eastportlandsurgery.com",
    "wof:name":"HealthSouth",
    "wof:placetype":"venue"
},
  "geometry": {"coordinates":[-121.46618700000001,38.57058],"type":"Point"}
}