{
  "type": "Feature",
  "properties": {
    "addr:full":"109 Martin Dr Novato CA 94949",
    "addr:housenumber":"109",
    "addr:postcode":"94949",
    "addr:street":"Martin Dr",
    "iso:country":"US",
    "sg:address":"109 Martin Dr",
    "sg:city":"Novato",
    "sg:classifiers":[
        {
            "category":"Wholesale",
            "subcategory":"Toys & Hobbies",
            "type":"Manufacturing & Wholesale Goods"
        }
    ],
    "sg:phone":"+1 415 382 0404",
    "sg:postcode":"94949",
    "sg:province":"CA",
    "wof:name":"Cheshire & Co",
    "wof:placetype":"venue"
},
  "geometry": {"coordinates":[-122.529743,38.058689],"type":"Point"}
}