{
  "type": "Feature",
  "properties": {
    "iso:country":"US",
    "sg:address":"702 Trancas St",
    "sg:city":"Napa",
    "sg:classifiers":[
        {
            "category":"Building & Trades",
            "subcategory":"Electrical",
            "type":"Services"
        }
    ],
    "sg:phone":"+1 707 224 8531",
    "sg:postcode":"94558",
    "sg:province":"CA",
    "sg:tags":[
        "communications",
        "contractor"
    ],
    "wof:name":"North Bay Media Systems",
    "wof:placetype":"venue"
},
  "geometry": {"coordinates":[-122.289768,38.324682],"type":"Point"}
}