{
  "type": "Feature",
  "properties": {
    "iso:country":"US",
    "sg:address":"6046 San Juan Avenue",
    "sg:city":"Citrus Heights",
    "sg:classifiers":[
        {
            "category":"Retail",
            "subcategory":"Auto Repair",
            "type":"Services"
        }
    ],
    "sg:phone":"+1 916 969 0194",
    "sg:postcode":"95610",
    "sg:province":"CA",
    "wof:name":"Capital Transmission Service Center",
    "wof:placetype":"venue"
},
  "geometry": {"coordinates":[-121.292278,38.676243],"type":"Point"}
}