{
  "type": "Feature",
  "properties": {
    "iso:country":"US",
    "sg:address":"1413 The Alameda",
    "sg:city":"San Jose",
    "sg:classifiers":[
        {
            "category":"Professional",
            "subcategory":"Lawyer & Legal Services",
            "type":"Services"
        }
    ],
    "sg:phone":"+1 408 294 1697",
    "sg:postcode":"95126",
    "sg:province":"CA",
    "wof:name":"Gale Peggy",
    "wof:placetype":"venue"
},
  "geometry": {"coordinates":[-121.914001,37.333199],"type":"Point"}
}