{
  "type": "Feature",
  "properties": {
    "iso:country":"US",
    "sg:address":"6653 Embarcadero Dr",
    "sg:city":"Stockton",
    "sg:classifiers":[
        {
            "category":"Organizations",
            "subcategory":"Religious Organization",
            "type":"Services"
        }
    ],
    "sg:phone":"+1 209 473 4243",
    "sg:postcode":"95219",
    "sg:province":"CA",
    "sg:tags":[
        "church"
    ],
    "wof:name":"Norcal Association",
    "wof:placetype":"venue"
},
  "geometry": {"coordinates":[-121.367095,38.001323],"type":"Point"}
}