{
  "type": "Feature",
  "properties": {
    "iso:country":"US",
    "sg:address":"3456 Yorktown Dr",
    "sg:city":"Yuba City",
    "sg:classifiers":[
        {
            "category":"Professional",
            "subcategory":"Advertising",
            "type":"Services"
        }
    ],
    "sg:phone":"+1 530 671 7982",
    "sg:postcode":"95993",
    "sg:province":"CA",
    "wof:name":"Absolute Pewter",
    "wof:placetype":"venue"
},
  "geometry": {"coordinates":[-121.679682,39.153517],"type":"Point"}
}