{
  "type": "Feature",
  "properties": {
    "iso:country":"US",
    "sg:address":"33 Armanino Ct",
    "sg:city":"Oakland",
    "sg:classifiers":[
        {
            "category":"Wholesale",
            "subcategory":"Medical Equipment & Supplies",
            "type":"Manufacturing & Wholesale Goods"
        }
    ],
    "sg:phone":"+1 415 672 2631",
    "sg:postcode":"94618",
    "sg:province":"CA",
    "sg:tags":[
        "instrument",
        "surgical"
    ],
    "wof:name":"Beacon Biomedical",
    "wof:placetype":"venue"
},
  "geometry": {"coordinates":[-122.251896,37.848945],"type":"Point"}
}