{
  "type": "Feature",
  "properties": {
    "addr:full":"6101 S Highway 1 Elk CA 95432",
    "addr:housenumber":"6101",
    "addr:postcode":"95432",
    "addr:street":"S Highway 1",
    "iso:country":"US",
    "sg:address":"6101 S Highway 1",
    "sg:city":"Elk",
    "sg:classifiers":[
        {
            "category":"Food & Beverages",
            "subcategory":"Specialty",
            "type":"Retail Goods"
        },
        {
            "category":"Food & Beverages",
            "subcategory":"Groceries & Convenience Stores",
            "type":"Retail Goods"
        }
    ],
    "sg:phone":"+1 707 877 3411",
    "sg:postcode":"95432",
    "sg:province":"CA",
    "sg:tags":[
        "grocers-specialty"
    ],
    "sg:website":"http://www.elkcoast.com",
    "wof:name":"Elk Store",
    "wof:placetype":"venue"
},
  "geometry": {"coordinates":[-123.741029,39.165665],"type":"Point"}
}