{
  "type": "Feature",
  "properties": {
    "addr:full":"876 N 3rd St Grover Beach CA 93433",
    "addr:housenumber":"876",
    "addr:postcode":"93433",
    "addr:street":"N 3Rd St",
    "iso:country":"US",
    "sg:address":"876 N 3rd St",
    "sg:city":"Grover Beach",
    "sg:classifiers":[
        {
            "category":"Wholesale",
            "subcategory":"Computers",
            "type":"Manufacturing & Wholesale Goods"
        }
    ],
    "sg:phone":"+1 805 489 8964",
    "sg:postcode":"93433",
    "sg:province":"CA",
    "wof:name":"Turbo Data Equipment Co",
    "wof:placetype":"venue"
},
  "geometry": {"coordinates":[-120.626999,35.129507],"type":"Point"}
}