{
  "type": "Feature",
  "properties": {
    "addr:full":"555 Springbrook N Irvine CA 92614",
    "addr:housenumber":"555",
    "addr:postcode":"92614",
    "addr:street":"Springbrook N",
    "iso:country":"US",
    "sg:address":"555 Springbrook N",
    "sg:city":"Irvine",
    "sg:classifiers":[
        {
            "category":"Wholesale",
            "subcategory":"Apparel",
            "type":"Manufacturing & Wholesale Goods"
        }
    ],
    "sg:phone":"+1 323 906 9209",
    "sg:postcode":"92614",
    "sg:province":"CA",
    "sg:tags":[
        "fashion",
        "whole",
        "accessory"
    ],
    "wof:name":"Nice Button Inc",
    "wof:placetype":"venue"
},
  "geometry": {"coordinates":[-117.794078,33.668795],"type":"Point"}
}