{
  "type": "Feature",
  "properties": {
    "iso:country":"US",
    "sg:address":"45 Bay St",
    "sg:city":"San Rafael",
    "sg:classifiers":[
        {
            "category":"Manufacturing",
            "subcategory":"Watercraft",
            "type":"Manufacturing & Wholesale Goods"
        }
    ],
    "sg:phone":"+1 415 257 6329",
    "sg:postcode":"94901",
    "sg:province":"CA",
    "sg:tags":[
        "boat"
    ],
    "wof:name":"W C Garvie Boat Builder",
    "wof:placetype":"venue"
},
  "geometry": {"coordinates":[-122.515156,37.967853],"type":"Point"}
}