{
  "type": "Feature",
  "properties": {
    "addr:full":"31112 Brooks St Laguna Beach CA 92651",
    "addr:housenumber":"31112",
    "addr:postcode":"92651",
    "addr:street":"Brooks St",
    "iso:country":"US",
    "sg:address":"31112 Brooks St",
    "sg:city":"Laguna Beach",
    "sg:classifiers":[
        {
            "category":"Personal",
            "subcategory":"Beauty Salon",
            "type":"Services"
        }
    ],
    "sg:phone":"+1 949 499 4406",
    "sg:postcode":"92651",
    "sg:province":"CA",
    "wof:name":"Pleasant Zindel",
    "wof:placetype":"venue"
},
  "geometry": {"coordinates":[-117.750383,33.511221],"type":"Point"}
}