{
  "type": "Feature",
  "properties": {
    "addr:full":"14460 Gas Point Rd Cottonwood CA 96022",
    "addr:housenumber":"14460",
    "addr:postcode":"96022",
    "addr:street":"Gas Point Rd",
    "iso:country":"US",
    "sg:address":"14460 Gas Point Rd",
    "sg:city":"Cottonwood",
    "sg:classifiers":[
        {
            "category":"Freight",
            "type":"Transportation"
        }
    ],
    "sg:phone":"+1 530 347 5507",
    "sg:postcode":"96022",
    "sg:province":"CA",
    "sg:tags":[
        "operator",
        "trucking"
    ],
    "wof:name":"F M B Trucking",
    "wof:placetype":"venue"
},
  "geometry": {"coordinates":[-122.518692,40.398904],"type":"Point"}
}