{
  "type": "Feature",
  "properties": {
    "addr:full":"2180 Tully Rd San Jose CA 95122",
    "addr:housenumber":"2180",
    "addr:postcode":"95122",
    "addr:street":"Tully Rd",
    "iso:country":"US",
    "sg:address":"2180 Tully Rd",
    "sg:city":"San Jose",
    "sg:classifiers":[
        {
            "category":"Health Services",
            "subcategory":"Optometrist",
            "type":"Services"
        }
    ],
    "sg:phone":"+1 408 531 1123",
    "sg:postcode":"95122",
    "sg:province":"CA",
    "wof:name":"Ja Steven, OD",
    "wof:placetype":"venue"
},
  "geometry": {"coordinates":[-121.81849200000001,37.327274],"type":"Point"}
}