{
  "type": "Feature",
  "properties": {
    "addr:full":"375 Camphor Ave Fremont CA 94539",
    "addr:housenumber":"375",
    "addr:postcode":"94539",
    "addr:street":"Camphor Ave",
    "iso:country":"US",
    "sg:address":"375 Camphor Ave",
    "sg:city":"Fremont",
    "sg:classifiers":[
        {
            "category":"Professional",
            "subcategory":"Lawyer & Legal Services",
            "type":"Services"
        }
    ],
    "sg:phone":"+1 510 657 7665",
    "sg:postcode":"94539",
    "sg:province":"CA",
    "sg:tags":[
        "plan"
    ],
    "wof:name":"Tripti S Sharma Law Offices",
    "wof:placetype":"venue"
},
  "geometry": {"coordinates":[-121.917619,37.4762],"type":"Point"}
}