{
  "type": "Feature",
  "properties": {
    "addr:full":"49978 US Hwy 111 Coachella CA 92236",
    "addr:housenumber":"49978",
    "addr:postcode":"92236",
    "addr:street":"Us Hwy 111",
    "iso:country":"US",
    "sg:address":"49978 US Hwy 111",
    "sg:city":"Coachella",
    "sg:classifiers":[
        {
            "category":"Wholesale",
            "subcategory":"Electrical",
            "type":"Manufacturing & Wholesale Goods"
        }
    ],
    "sg:phone":"+1 760 398 9994",
    "sg:postcode":"92236",
    "sg:province":"CA",
    "sg:tags":[
        "control",
        "security",
        "system"
    ],
    "wof:name":"Aldana 911 Professionals",
    "wof:placetype":"venue"
},
  "geometry": {"coordinates":[-116.169175,33.674556],"type":"Point"}
}