{
  "type": "Feature",
  "properties": {
    "iso:country":"US",
    "sg:address":"7080 Donlon Way",
    "sg:city":"Dublin",
    "sg:classifiers":[
        {
            "category":"Banks & Credit Unions",
            "subcategory":"Bank",
            "type":"Services"
        }
    ],
    "sg:phone":"+1 925 828 3337",
    "sg:postcode":"94568",
    "sg:province":"CA",
    "sg:tags":[
        "loan",
        "real estate"
    ],
    "wof:name":"Valley Capital Investment",
    "wof:placetype":"venue"
},
  "geometry": {"coordinates":[-121.939054,37.702161],"type":"Point"}
}