{
  "type": "Feature",
  "properties": {
    "addr:full":"7365 Carnelian St Rancho Cucamonga CA 91730",
    "addr:housenumber":"7365",
    "addr:postcode":"91730",
    "addr:street":"Carnelian St",
    "iso:country":"US",
    "sg:address":"7365 Carnelian St",
    "sg:city":"Rancho Cucamonga",
    "sg:classifiers":[
        {
            "category":"Professional",
            "subcategory":"Management & Consulting",
            "type":"Services"
        }
    ],
    "sg:phone":"+1 909 484 9221",
    "sg:postcode":"91730",
    "sg:province":"CA",
    "sg:tags":[
        "consultant",
        "safety"
    ],
    "sg:website":"www.industrialcompliancecorp.com",
    "wof:name":"Industrial Compliance Corp",
    "wof:placetype":"venue"
},
  "geometry": {"coordinates":[-117.61597500000001,34.119594],"type":"Point"}
}