{
  "type": "Feature",
  "properties": {
    "addr:full":"110 Commercial St Downieville CA 95936",
    "addr:housenumber":"110",
    "addr:postcode":"95936",
    "addr:street":"Commercial St",
    "iso:country":"US",
    "sg:address":"110 Commercial St",
    "sg:city":"Downieville",
    "sg:classifiers":[
        {
            "category":"Travel",
            "subcategory":"Hotels & Motels",
            "type":"Entertainment"
        }
    ],
    "sg:phone":"+1 530 289 3573",
    "sg:postcode":"95936",
    "sg:province":"CA",
    "wof:name":"Carriage House Inn",
    "wof:placetype":"venue"
},
  "geometry": {"coordinates":[-120.82801600000001,39.560362],"type":"Point"}
}