{
  "type": "Feature",
  "properties": {
    "addr:full":"3701 Sailboat Dr Byron CA 94505",
    "addr:housenumber":"3701",
    "addr:postcode":"94505",
    "addr:street":"Sailboat Dr",
    "iso:country":"US",
    "sg:address":"3701 Sailboat Dr",
    "sg:city":"Byron",
    "sg:classifiers":[
        {
            "category":"Manufacturing",
            "subcategory":"Chemicals & Compounds",
            "type":"Manufacturing & Wholesale Goods"
        }
    ],
    "sg:phone":"+1 925 240 6417",
    "sg:postcode":"94505",
    "sg:province":"CA",
    "sg:tags":[
        "preparation",
        "toilet",
        "mfg"
    ],
    "wof:name":"Beauticontrol Cosmet",
    "wof:placetype":"venue"
},
  "geometry": {"coordinates":[-118.05601799999999,35.215513],"type":"Point"}
}