{
  "type": "Feature",
  "properties": {
    "iso:country":"US",
    "sg:address":"74603 Leslie Ave",
    "sg:city":"Palm Desert",
    "sg:classifiers":[
        {
            "category":"Freight",
            "type":"Transportation"
        }
    ],
    "sg:phone":"+1 760 773 4475",
    "sg:postcode":"92260",
    "sg:province":"CA",
    "sg:tags":[
        "operator",
        "trucking"
    ],
    "wof:name":"Tom Harne Trucking",
    "wof:placetype":"venue"
},
  "geometry": {"coordinates":[-116.36275000000001,33.738771],"type":"Point"}
}