{
  "type": "Feature",
  "properties": {
    "addr:full":"1040 River St Santa Cruz CA 95060",
    "addr:housenumber":"1040",
    "addr:postcode":"95060",
    "addr:street":"River St",
    "iso:country":"US",
    "sg:address":"1040 River St",
    "sg:city":"Santa Cruz",
    "sg:classifiers":[
        {
            "category":"Professional",
            "subcategory":"Computer Services",
            "type":"Services"
        }
    ],
    "sg:phone":"+1 831 420 0493",
    "sg:postcode":"95060",
    "sg:province":"CA",
    "sg:tags":[
        "consultant",
        "designer"
    ],
    "wof:name":"Lighthouse Information Svc",
    "wof:placetype":"venue"
},
  "geometry": {"coordinates":[-122.030715,36.988973],"type":"Point"}
}