{
  "type": "Feature",
  "properties": {
    "addr:full":"3425 E 1st St Los Angeles CA 90063",
    "addr:housenumber":"3425",
    "addr:postcode":"90063",
    "addr:street":"E 1St St",
    "iso:country":"US",
    "sg:address":"3425 E 1st St",
    "sg:city":"Los Angeles",
    "sg:classifiers":[
        {
            "category":"Manufacturing",
            "subcategory":"Leather Goods",
            "type":"Manufacturing & Wholesale Goods"
        }
    ],
    "sg:phone":"+1 323 269 8551",
    "sg:postcode":"90063",
    "sg:province":"CA",
    "wof:name":"Marco's Leather Goods",
    "wof:placetype":"venue"
},
  "geometry": {"coordinates":[-118.19499999999999,34.037201],"type":"Point"}
}