{
  "type": "Feature",
  "properties": {
    "addr:full":"800 Lindberg Ln Petaluma CA 94952",
    "addr:housenumber":"800",
    "addr:postcode":"94952",
    "addr:street":"Lindberg Ln",
    "iso:country":"US",
    "sg:address":"800 Lindberg Ln",
    "sg:city":"Petaluma",
    "sg:classifiers":[
        {
            "category":"Wholesale",
            "subcategory":"Books, Periodicals, & Newspapers",
            "type":"Manufacturing & Wholesale Goods"
        }
    ],
    "sg:phone":"+1 707 778 1124",
    "sg:postcode":"94952",
    "sg:province":"CA",
    "sg:tags":[
        "publisher",
        "book"
    ],
    "wof:name":"World Trade Press",
    "wof:placetype":"venue"
},
  "geometry": {"coordinates":[-122.62404600000001,38.237309],"type":"Point"}
}