{
  "type": "Feature",
  "properties": {
    "addr:full":"2750 Saturn St Brea CA 92821",
    "addr:housenumber":"2750",
    "addr:postcode":"92821",
    "addr:street":"Saturn St",
    "iso:country":"US",
    "sg:address":"2750 Saturn St",
    "sg:city":"Brea",
    "sg:classifiers":[
        {
            "category":"Freight",
            "type":"Transportation"
        }
    ],
    "sg:phone":"+1 714 528 3511",
    "sg:postcode":"92821",
    "sg:province":"CA",
    "sg:tags":[
        "special",
        "merchandise"
    ],
    "wof:name":"Pacific Sales",
    "wof:placetype":"venue"
},
  "geometry": {"coordinates":[-117.857422,33.908954],"type":"Point"}
}