{
  "type": "Feature",
  "properties": {
    "addr:full":"650 Central Ave Alameda CA 94501",
    "addr:housenumber":"650",
    "addr:postcode":"94501",
    "addr:street":"Central Ave",
    "iso:country":"US",
    "sg:address":"650 Central Ave",
    "sg:city":"Alameda",
    "sg:classifiers":[
        {
            "category":"Retail",
            "subcategory":"Laundry & Dry Cleaning",
            "type":"Services"
        }
    ],
    "sg:phone":"+1 510 748 9988",
    "sg:postcode":"94501",
    "sg:province":"CA",
    "wof:name":"Laundry Time",
    "wof:placetype":"venue"
},
  "geometry": {"coordinates":[-122.27762300000001,37.770973],"type":"Point"}
}