{
  "type": "Feature",
  "properties": {
    "iso:country":"US",
    "sg:address":"1038 Sir William Ct",
    "sg:city":"Chico",
    "sg:classifiers":[
        {
            "category":"Shopping",
            "subcategory":"Jewelry",
            "type":"Retail Goods"
        }
    ],
    "sg:phone":"+1 530 897 0290",
    "sg:postcode":"95926",
    "sg:province":"CA",
    "wof:name":"Abarland Treasures",
    "wof:placetype":"venue"
},
  "geometry": {"coordinates":[-121.87786699999999,39.744133],"type":"Point"}
}