{
  "type": "Feature",
  "properties": {
    "addr:full":"7461 Beverly Boulevard Los Angeles CA 90036",
    "addr:housenumber":"7461",
    "addr:postcode":"90036",
    "addr:street":"Beverly Boulevard",
    "iso:country":"US",
    "sg:address":"7461 Beverly Boulevard",
    "sg:city":"Los Angeles",
    "sg:classifiers":[
        {
            "category":"Organizations",
            "subcategory":"Religious Organization",
            "type":"Services"
        }
    ],
    "sg:phone":"+1 323 931 0224",
    "sg:postcode":"90036",
    "sg:province":"CA",
    "sg:website":"www.tomcheishabbos.com",
    "wof:name":"Tomchei Shabbos",
    "wof:placetype":"venue"
},
  "geometry": {"coordinates":[-118.35012,34.068398],"type":"Point"}
}