{
  "type": "Feature",
  "properties": {
    "iso:country":"US",
    "sg:address":"1802 Alta Vista Dr",
    "sg:city":"Vista",
    "sg:classifiers":[
        {
            "category":"Personal",
            "type":"Services"
        }
    ],
    "sg:phone":"+1 760 806 4940",
    "sg:postcode":"92084",
    "sg:province":"CA",
    "sg:tags":[
        "therapist",
        "massage"
    ],
    "wof:name":"Body Dream",
    "wof:placetype":"venue"
},
  "geometry": {"coordinates":[-117.220923,33.198601],"type":"Point"}
}