{
  "type": "Feature",
  "properties": {
    "iso:country":"US",
    "sg:address":"755 Baywood Dr",
    "sg:city":"Petaluma",
    "sg:classifiers":[
        {
            "category":"Restaurant",
            "type":"Food & Drink"
        }
    ],
    "sg:phone":"+1 707 283 0500",
    "sg:postcode":"94954",
    "sg:province":"CA",
    "wof:name":"High Tech Burrito",
    "wof:placetype":"venue"
},
  "geometry": {"coordinates":[-122.61377400000001,38.231692],"type":"Point"}
}