{
  "type": "Feature",
  "properties": {
    "addr:full":"4025 1st St Livermore CA 94551",
    "addr:housenumber":"4025",
    "addr:postcode":"94551",
    "addr:street":"1St St",
    "iso:country":"US",
    "sg:address":"4025 1st St",
    "sg:city":"Livermore",
    "sg:classifiers":[
        {
            "category":"Manufacturing",
            "subcategory":"Rubber & Plastics",
            "type":"Manufacturing & Wholesale Goods"
        },
        {
            "category":"Autos & Motor Vehicles",
            "subcategory":"Auto Supplies",
            "type":"Retail Goods"
        },
        {
            "category":"Retail",
            "subcategory":"Auto Repair",
            "type":"Services"
        }
    ],
    "sg:phone":"+1 925 373 0660",
    "sg:postcode":"94551",
    "sg:province":"CA",
    "sg:tags":[
        "wheel",
        "oil",
        "tires-wholesale",
        "tire",
        "lube",
        "retread",
        "recap",
        "servicing-automotive",
        "balancing",
        "axle",
        "wheels-aligning",
        "alignment-frame",
        "brake",
        "manufacturer"
    ],
    "sg:website":"http://www.bigotires.com",
    "wof:name":"Big O Tires",
    "wof:placetype":"venue"
},
  "geometry": {"coordinates":[-121.749628,37.692702],"type":"Point"}
}