{
  "type": "Feature",
  "properties": {
    "addr:full":"13048 Bach Way Cerritos CA 90703",
    "addr:postcode":"13048;ca 90703",
    "addr:street":"Bach Way",
    "iso:country":"US",
    "sg:address":"13048 Bach Way",
    "sg:city":"Cerritos",
    "sg:classifiers":[
        {
            "category":"Freight",
            "type":"Transportation"
        }
    ],
    "sg:phone":"+1 562 926 7137",
    "sg:postcode":"90703",
    "sg:province":"CA",
    "sg:tags":[
        "arrangement"
    ],
    "wof:name":"B L N Express Co",
    "wof:placetype":"venue"
},
  "geometry": {"coordinates":[-118.05417199999999,33.879887],"type":"Point"}
}