{
  "type": "Feature",
  "properties": {
    "addr:full":"1056 Shafter Ave San Francisco CA 94124",
    "addr:housenumber":"1056",
    "addr:postcode":"94124",
    "addr:street":"Shafter Ave",
    "iso:country":"US",
    "sg:address":"1056 Shafter Ave",
    "sg:city":"San Francisco",
    "sg:classifiers":[
        {
            "category":"Building & Trades",
            "subcategory":"Construction",
            "type":"Services"
        }
    ],
    "sg:phone":"+1 415 822 3370",
    "sg:postcode":"94124",
    "sg:province":"CA",
    "sg:tags":[
        "roofing",
        "contractor"
    ],
    "wof:name":"Kim's Roofing Co",
    "wof:placetype":"venue"
},
  "geometry": {"coordinates":[-122.38048999999999,37.725192],"type":"Point"}
}