{
  "type": "Feature",
  "properties": {
    "iso:country":"US",
    "sg:address":"324 S Abel St",
    "sg:city":"Milpitas",
    "sg:classifiers":[
        {
            "category":"Real Estate",
            "subcategory":"Real Estate Agent",
            "type":"Services"
        }
    ],
    "sg:phone":"+1 408 586 9326",
    "sg:postcode":"95035",
    "sg:province":"CA",
    "wof:name":"Loan Express & Real Estate",
    "wof:placetype":"venue"
},
  "geometry": {"coordinates":[-121.90790699999999,37.427593],"type":"Point"}
}