{
  "type": "Feature",
  "properties": {
    "iso:country":"US",
    "sg:address":"9643 Boxwood Ave",
    "sg:city":"Fontana",
    "sg:classifiers":[
        {
            "category":"Building & Trades",
            "subcategory":"Construction",
            "type":"Services"
        }
    ],
    "sg:phone":"+1 909 823 8528",
    "sg:postcode":"92335",
    "sg:province":"CA",
    "sg:tags":[
        "contractor"
    ],
    "wof:name":"Ahumada Masonry",
    "wof:placetype":"venue"
},
  "geometry": {"coordinates":[-117.419307,34.078435],"type":"Point"}
}