{
  "type": "Feature",
  "properties": {
    "iso:country":"US",
    "sg:address":"10008 National Blvd Ste 403",
    "sg:city":"Los Angeles",
    "sg:classifiers":[
        {
            "category":"Building & Trades",
            "subcategory":"Electrical",
            "type":"Services"
        }
    ],
    "sg:phone":"+1 310 453 7774",
    "sg:postcode":"90034",
    "sg:province":"CA",
    "sg:tags":[
        "electrician"
    ],
    "wof:name":"Manzano Electric",
    "wof:placetype":"venue"
},
  "geometry": {"coordinates":[-118.40345000000001,34.029049],"type":"Point"}
}