{
  "type": "Feature",
  "properties": {
    "iso:country":"US",
    "sg:address":"2020 E Howell Ave Ste A",
    "sg:city":"Anaheim",
    "sg:classifiers":[
        {
            "category":"Home & Garden",
            "subcategory":"Carpets & Floor Coverings",
            "type":"Retail Goods"
        }
    ],
    "sg:phone":"+1 714 634 8222",
    "sg:postcode":"92806",
    "sg:province":"CA",
    "sg:tags":[
        "carpeting"
    ],
    "wof:name":"A-1 Vinyl Floor Coverings",
    "wof:placetype":"venue"
},
  "geometry": {"coordinates":[-117.889,33.806801],"type":"Point"}
}