{
  "type": "Feature",
  "properties": {
    "iso:country":"US",
    "sg:address":"515 Galveston Dr",
    "sg:city":"Redwood City",
    "sg:classifiers":[
        {
            "category":"Professional",
            "subcategory":"Research",
            "type":"Services"
        }
    ],
    "sg:phone":"+1 650 298 5300",
    "sg:postcode":"94063",
    "sg:province":"CA",
    "sg:tags":[
        "commercial",
        "physical"
    ],
    "sg:website":"www.maxygen.com",
    "wof:name":"Maxygen Inc",
    "wof:placetype":"venue"
},
  "geometry": {"coordinates":[-122.215495,37.498933],"type":"Point"}
}