{
  "type": "Feature",
  "properties": {
    "iso:country":"US",
    "sg:address":"833 W Torrance Blvd",
    "sg:city":"Torrance",
    "sg:classifiers":[
        {
            "category":"Wholesale",
            "subcategory":"Durable Goods & Equipment",
            "type":"Manufacturing & Wholesale Goods"
        },
        {
            "category":"Shopping",
            "subcategory":"Books",
            "type":"Retail Goods"
        }
    ],
    "sg:phone":"+1 310 327 6985",
    "sg:postcode":"90502",
    "sg:province":"CA",
    "sg:tags":[
        "magazine",
        "cassette",
        "importer"
    ],
    "wof:name":"Alpine Village Importers",
    "wof:placetype":"venue"
},
  "geometry": {"coordinates":[-118.288288,33.842116],"type":"Point"}
}