{
  "type": "Feature",
  "properties": {
    "iso:country":"US",
    "sg:address":"15727 Amar Rd",
    "sg:city":"La Puente",
    "sg:classifiers":[
        {
            "category":"Retail",
            "subcategory":"Self-service Laundry",
            "type":"Services"
        }
    ],
    "sg:phone":"+1 626 336 1816",
    "sg:postcode":"91744",
    "sg:province":"CA",
    "wof:name":"G E Coin Laundry",
    "wof:placetype":"venue"
},
  "geometry": {"coordinates":[-117.94136899999999,34.036597],"type":"Point"}
}