{
  "type": "Feature",
  "properties": {
    "iso:country":"US",
    "sg:address":"6170 Thornton Ave",
    "sg:city":"Newark",
    "sg:classifiers":[
        {
            "category":"Professional",
            "subcategory":"Computer Services",
            "type":"Services"
        }
    ],
    "sg:phone":"+1 510 795 9116",
    "sg:postcode":"94560",
    "sg:province":"CA",
    "sg:website":"www.welchbiz.com",
    "wof:name":"Welch Business Systems",
    "wof:placetype":"venue"
},
  "geometry": {"coordinates":[-122.031741,37.535372],"type":"Point"}
}