{
  "type": "Feature",
  "properties": {
    "addr:full":"100 California Dr Yountville CA 94599",
    "addr:housenumber":"100",
    "addr:postcode":"ca 94599",
    "addr:street":"California Dr",
    "iso:country":"US",
    "sg:address":"100 California Dr",
    "sg:city":"Yountville",
    "sg:classifiers":[
        {
            "category":"Coffee & Tea",
            "type":"Food & Drink"
        },
        {
            "category":"Restaurant",
            "type":"Food & Drink"
        }
    ],
    "sg:phone":"+1 707 945 0700",
    "sg:postcode":"94599",
    "sg:province":"CA",
    "sg:tags":[
        "espresso"
    ],
    "wof:name":"Hero's Cafe",
    "wof:placetype":"venue"
},
  "geometry": {"coordinates":[-122.361587,38.396405],"type":"Point"}
}