{
  "type": "Feature",
  "properties": {
    "iso:country":"US",
    "sg:address":"17107 S Figueroa Street",
    "sg:city":"Gardena",
    "sg:classifiers":[
        {
            "category":"Home & Garden",
            "subcategory":"Home Furnishings",
            "type":"Retail Goods"
        }
    ],
    "sg:phone":"+1 310 324 2625",
    "sg:postcode":"90248",
    "sg:province":"CA",
    "sg:tags":[
        "decor"
    ],
    "wof:name":"The Storage Space",
    "wof:placetype":"venue"
},
  "geometry": {"coordinates":[-118.282195,33.875738],"type":"Point"}
}