{
  "type": "Feature",
  "properties": {
    "addr:full":"8003 Pumpkin Ct Cupertino CA 95014",
    "addr:housenumber":"8003",
    "addr:postcode":"95014",
    "addr:street":"Pumpkin Ct",
    "iso:country":"US",
    "sg:address":"8003 Pumpkin Ct",
    "sg:city":"Cupertino",
    "sg:classifiers":[
        {
            "category":"Shopping",
            "subcategory":"Florist",
            "type":"Retail Goods"
        }
    ],
    "sg:phone":"+1 408 252 2094",
    "sg:postcode":"95014",
    "sg:province":"CA",
    "wof:name":"Cupertino Florist",
    "wof:placetype":"venue"
},
  "geometry": {"coordinates":[-122.049173,37.310496],"type":"Point"}
}