{
  "type": "Feature",
  "properties": {
    "iso:country":"US",
    "sg:address":"4575 Viewridge Ave",
    "sg:city":"San Diego",
    "sg:classifiers":[
        {
            "category":"Communications",
            "subcategory":"Television Station",
            "type":"Services"
        }
    ],
    "sg:phone":"+1 858 505 5120",
    "sg:postcode":"92123",
    "sg:province":"CA",
    "sg:website":"www.kusi.com",
    "wof:name":"KUSI News Cable 9 Channel 51",
    "wof:placetype":"venue"
},
  "geometry": {"coordinates":[-117.122837,32.823257],"type":"Point"}
}