{
  "type": "Feature",
  "properties": {
    "iso:country":"US",
    "sg:address":"413 W Las Tunas Dr",
    "sg:city":"San Gabriel",
    "sg:classifiers":[
        {
            "category":"Home & Garden",
            "subcategory":"Furniture",
            "type":"Retail Goods"
        }
    ],
    "sg:phone":"+1 626 308 7899",
    "sg:postcode":"91776",
    "sg:province":"CA",
    "sg:tags":[
        "equipment",
        "kitchen",
        "cabinet"
    ],
    "wof:name":"Cabinet City",
    "wof:placetype":"venue"
},
  "geometry": {"coordinates":[-118.10601200000001,34.102533],"type":"Point"}
}