{
  "type": "Feature",
  "properties": {
    "iso:country":"US",
    "sg:address":"901 Jeffrey Dr",
    "sg:city":"Pleasant Hill",
    "sg:classifiers":[
        {
            "category":"Home & Garden",
            "subcategory":"Building Materials",
            "type":"Retail Goods"
        }
    ],
    "sg:phone":"+1 925 676 8655",
    "sg:postcode":"94523",
    "sg:province":"CA",
    "wof:name":"Tom Viacava Wallpaper",
    "wof:placetype":"venue"
},
  "geometry": {"coordinates":[-122.064833,37.964736],"type":"Point"}
}