{
  "type": "Feature",
  "properties": {
    "iso:country":"US",
    "sg:address":"5634 Van Nuys Blvd",
    "sg:city":"Van Nuys",
    "sg:classifiers":[
        {
            "category":"Insurance",
            "subcategory":"Hazard Insurance",
            "type":"Services"
        }
    ],
    "sg:phone":"+1 818 334 5577",
    "sg:postcode":"91411",
    "sg:province":"CA",
    "sg:website":"www.askbarri.com",
    "wof:name":"Barri Lynn Hollander - State Farm",
    "wof:placetype":"venue"
},
  "geometry": {"coordinates":[-118.448685,34.173084],"type":"Point"}
}