{
  "type": "Feature",
  "properties": {
    "iso:country":"US",
    "sg:address":"5310 Vineland Ave",
    "sg:city":"North Hollywood",
    "sg:classifiers":[
        {
            "category":"Retail",
            "subcategory":"Storage",
            "type":"Services"
        }
    ],
    "sg:phone":"+1 818 284 6591",
    "sg:postcode":"91601",
    "sg:province":"CA",
    "sg:tags":[
        "self"
    ],
    "sg:website":"a1storage.com/self_storage/North...",
    "wof:name":"A-1 Self Storage",
    "wof:placetype":"venue"
},
  "geometry": {"coordinates":[-118.369941,34.167651],"type":"Point"}
}