{
  "type": "Feature",
  "properties": {
    "addr:full":"29090 Hook Creek Rd Lake Arrowhead CA 92352",
    "addr:housenumber":"29090",
    "addr:postcode":"92352",
    "addr:street":"Hook Creek Rd",
    "iso:country":"US",
    "sg:address":"29090 Hook Creek Rd",
    "sg:city":"Lake Arrowhead",
    "sg:classifiers":[
        {
            "category":"Restaurant",
            "type":"Food & Drink"
        },
        {
            "category":"Bars & Pubs",
            "subcategory":"Nightclub",
            "type":"Food & Drink"
        }
    ],
    "sg:phone":"+1 909 337 9037",
    "sg:postcode":"92352",
    "sg:province":"CA",
    "sg:tags":[
        "nightlife"
    ],
    "wof:name":"Tonys",
    "wof:placetype":"venue"
},
  "geometry": {"coordinates":[-117.193001,34.268299],"type":"Point"}
}