{
  "type": "Feature",
  "properties": {
    "iso:country":"US",
    "sg:address":"1400 N Bristol St",
    "sg:city":"Newport Beach",
    "sg:classifiers":[
        {
            "category":"Real Estate",
            "subcategory":"Developer",
            "type":"Services"
        }
    ],
    "sg:phone":"+1 949 476 6828",
    "sg:postcode":"92660",
    "sg:province":"CA",
    "wof:name":"R M Dalton Corp",
    "wof:placetype":"venue"
},
  "geometry": {"coordinates":[-117.867172,33.657602],"type":"Point"}
}