{
  "type": "Feature",
  "properties": {
    "iso:country":"US",
    "sg:address":"1200 Hamilton Ct",
    "sg:city":"Menlo Park",
    "sg:classifiers":[
        {
            "category":"Wholesale",
            "subcategory":"Durable Goods & Equipment",
            "type":"Manufacturing & Wholesale Goods"
        }
    ],
    "sg:phone":"+1 650 462 1188",
    "sg:postcode":"94025",
    "sg:province":"CA",
    "sg:tags":[
        "importer"
    ],
    "wof:name":"Pyromagic Enterprises Inc",
    "wof:placetype":"venue"
},
  "geometry": {"coordinates":[-122.148707,37.478488],"type":"Point"}
}