{
  "type": "Feature",
  "properties": {
    "iso:country":"US",
    "sg:address":"463 N Oak St",
    "sg:city":"Inglewood",
    "sg:classifiers":[
        {
            "category":"Freight",
            "type":"Transportation"
        }
    ],
    "sg:phone":"+1 310 671 6769",
    "sg:postcode":"90302",
    "sg:province":"CA",
    "wof:name":"Gc Logistics Inc",
    "wof:placetype":"venue"
},
  "geometry": {"coordinates":[-118.36447200000001,33.96856],"type":"Point"}
}