{
  "type": "Feature",
  "properties": {
    "addr:full":"821 W Santa Ana Ave Clovis CA 93612",
    "addr:housenumber":"821",
    "addr:postcode":"93612",
    "addr:street":"W Santa Ana Ave",
    "iso:country":"US",
    "sg:address":"821 W Santa Ana Ave",
    "sg:city":"Clovis",
    "sg:classifiers":[
        {
            "category":"Building & Trades",
            "subcategory":"Cleaning & Sanitation",
            "type":"Services"
        }
    ],
    "sg:phone":"+1 559 325 0111",
    "sg:postcode":"93612",
    "sg:province":"CA",
    "sg:tags":[
        "fireplace",
        "chimney"
    ],
    "wof:name":"Clovis Chimney",
    "wof:placetype":"venue"
},
  "geometry": {"coordinates":[-119.729246,36.804965],"type":"Point"}
}