{
  "type": "Feature",
  "properties": {
    "iso:country":"US",
    "sg:address":"5434 Thornwood Dr",
    "sg:city":"San Jose",
    "sg:classifiers":[
        {
            "category":"Sports & Exercise",
            "subcategory":"Gym",
            "type":"Entertainment"
        }
    ],
    "sg:phone":"+1 408 363 1010",
    "sg:postcode":"95123",
    "sg:province":"CA",
    "sg:website":"www.clubone.com",
    "wof:name":"Club One Fitness",
    "wof:placetype":"venue"
},
  "geometry": {"coordinates":[-121.860208,37.254378],"type":"Point"}
}