{
  "type": "Feature",
  "properties": {
    "addr:full":"22372 Whirlaway Ct Sun City CA 92587",
    "addr:postcode":"22372;92587",
    "addr:street":"Whirlaway Ct",
    "iso:country":"US",
    "sg:address":"22372 Whirlaway Ct",
    "sg:city":"Sun City",
    "sg:classifiers":[
        {
            "category":"Professional",
            "type":"Services"
        }
    ],
    "sg:phone":"+1 951 244 4091",
    "sg:postcode":"92587",
    "sg:province":"CA",
    "wof:name":"TW Equities LLC",
    "wof:placetype":"venue"
},
  "geometry": {"coordinates":[-117.27001,33.692439],"type":"Point"}
}