{
  "type": "Feature",
  "properties": {
    "addr:full":"7020 Wilson Avenue Los Angeles CA 90001",
    "addr:housenumber":"7020",
    "addr:postcode":"90001",
    "addr:street":"Wilson Avenue",
    "iso:country":"US",
    "sg:address":"7020 Wilson Avenue",
    "sg:city":"Los Angeles",
    "sg:classifiers":[
        {
            "category":"Shopping",
            "subcategory":"Crafts & Fabrics",
            "type":"Retail Goods"
        }
    ],
    "sg:phone":"+1 323 582 7684",
    "sg:postcode":"90001",
    "sg:province":"CA",
    "sg:tags":[
        "store"
    ],
    "sg:website":"www.noahlamport.com",
    "wof:name":"Noah Lamport",
    "wof:placetype":"venue"
},
  "geometry": {"coordinates":[-118.237804,33.976059],"type":"Point"}
}