{
  "type": "Feature",
  "properties": {
    "addr:full":"413 S Clara St Santa Ana CA 92703",
    "addr:housenumber":"413",
    "addr:postcode":"92703",
    "addr:street":"S Clara St",
    "iso:country":"US",
    "sg:address":"413 S Clara St",
    "sg:city":"Santa Ana",
    "sg:classifiers":[
        {
            "category":"Utilities",
            "subcategory":"Telephone",
            "type":"Services"
        }
    ],
    "sg:phone":"+1 714 543 5837",
    "sg:postcode":"92703",
    "sg:province":"CA",
    "sg:tags":[
        "communications"
    ],
    "wof:name":"Carplanetscom",
    "wof:placetype":"venue"
},
  "geometry": {"coordinates":[-117.900245,33.740498],"type":"Point"}
}