{
  "type": "Feature",
  "properties": {
    "iso:country":"US",
    "sg:address":"39925 Harveston Dr",
    "sg:city":"Temecula",
    "sg:classifiers":[
        {
            "category":"Education",
            "subcategory":"School",
            "type":"Public Place"
        }
    ],
    "sg:phone":"+1 951 296 5579",
    "sg:postcode":"92591",
    "sg:province":"CA",
    "sg:tags":[
        "elementary"
    ],
    "wof:name":"Ysabel Barnett Elementary School",
    "wof:placetype":"venue"
},
  "geometry": {"coordinates":[-117.152435,33.540896],"type":"Point"}
}