{
  "type": "Feature",
  "properties": {
    "iso:country":"US",
    "sg:address":"1172 S Main St",
    "sg:city":"Salinas",
    "sg:classifiers":[
        {
            "category":"Shopping",
            "subcategory":"Bicycles & Sporting Goods",
            "type":"Retail Goods"
        }
    ],
    "sg:phone":"+1 831 758 6061",
    "sg:postcode":"93901",
    "sg:province":"CA",
    "wof:name":"Hard Time Husslin",
    "wof:placetype":"venue"
},
  "geometry": {"coordinates":[-121.65942,36.658277],"type":"Point"}
}