{
  "type": "Feature",
  "properties": {
    "iso:country":"US",
    "sg:address":"5125 Business Center Dr",
    "sg:city":"Fairfield",
    "sg:classifiers":[
        {
            "category":"Retail",
            "subcategory":"Veterinary Services",
            "type":"Services"
        }
    ],
    "sg:phone":"+1 800 427 7973",
    "sg:postcode":"94534",
    "sg:province":"CA",
    "sg:tags":[
        "clinic",
        "hospital"
    ],
    "sg:website":"http://www.happypet.com",
    "wof:name":"VIP Petcare Services",
    "wof:placetype":"venue"
},
  "geometry": {"coordinates":[-122.143018,38.21498],"type":"Point"}
}