{
  "type": "Feature",
  "properties": {
    "addr:full":"10952 Klingerman St El Monte CA 91733",
    "addr:housenumber":"10952",
    "addr:postcode":"91733",
    "addr:street":"Klingerman St",
    "iso:country":"US",
    "sg:address":"10952 Klingerman St",
    "sg:city":"El Monte",
    "sg:classifiers":[
        {
            "category":"Wholesale",
            "subcategory":"Auto Parts",
            "type":"Manufacturing & Wholesale Goods"
        }
    ],
    "sg:phone":"+1 626 575 1232",
    "sg:postcode":"91733",
    "sg:province":"CA",
    "sg:tags":[
        "tire",
        "supply"
    ],
    "wof:name":"Tamayo Tires",
    "wof:placetype":"venue"
},
  "geometry": {"coordinates":[-118.035729,34.055957],"type":"Point"}
}