{
  "type": "Feature",
  "properties": {
    "iso:country":"US",
    "sg:address":"1049 Rudgear Rd",
    "sg:city":"Walnut Creek",
    "sg:classifiers":[
        {
            "category":"Professional",
            "type":"Services"
        }
    ],
    "sg:phone":"+1 925 932 1915",
    "sg:postcode":"94596",
    "sg:province":"CA",
    "wof:name":"Klar Corp",
    "wof:placetype":"venue"
},
  "geometry": {"coordinates":[-122.02095,37.874162],"type":"Point"}
}