{
  "type": "Feature",
  "properties": {
    "iso:country":"US",
    "sg:address":"2233 Alma St",
    "sg:city":"Palo Alto",
    "sg:classifiers":[
        {
            "category":"Health Services",
            "subcategory":"Doctor",
            "type":"Services"
        }
    ],
    "sg:phone":"+1 650 326 4466",
    "sg:postcode":"94301",
    "sg:province":"CA",
    "sg:tags":[
        "dentist"
    ],
    "wof:name":"Daniel B Armistead DDS",
    "wof:placetype":"venue"
},
  "geometry": {"coordinates":[-122.142207,37.429842],"type":"Point"}
}