{
  "type": "Feature",
  "properties": {
    "iso:country":"US",
    "sg:address":"923 Dana Dr",
    "sg:city":"Redding",
    "sg:classifiers":[
        {
            "category":"Insurance",
            "subcategory":"Insurance Agent",
            "type":"Services"
        },
        {
            "category":"Insurance",
            "subcategory":"Hazard Insurance",
            "type":"Services"
        },
        {
            "category":"Insurance",
            "subcategory":"Title Insurance",
            "type":"Services"
        },
        {
            "category":"Insurance",
            "subcategory":"Life Insurance",
            "type":"Services"
        }
    ],
    "sg:phone":"+1 530 222 2306",
    "sg:postcode":"96003",
    "sg:province":"CA",
    "sg:tags":[
        "business",
        "auto",
        "commercial",
        "homeowner",
        "motorcycle",
        "renter"
    ],
    "wof:name":"Allstate Insurance Company - Kevin Wall",
    "wof:placetype":"venue"
},
  "geometry": {"coordinates":[-122.355698,40.585972],"type":"Point"}
}