{
  "type": "Feature",
  "properties": {
    "iso:country":"US",
    "sg:address":"760 N Batavia St",
    "sg:city":"Orange",
    "sg:classifiers":[
        {
            "category":"Freight",
            "type":"Transportation"
        }
    ],
    "sg:phone":"+1 714 744 6390",
    "sg:postcode":"92868",
    "sg:province":"CA",
    "sg:tags":[
        "general"
    ],
    "wof:name":"Orange Rv Stables",
    "wof:placetype":"venue"
},
  "geometry": {"coordinates":[-117.86189,33.801066],"type":"Point"}
}