{
  "type": "Feature",
  "properties": {
    "addr:full":"1854 el Rey Rd San Pedro CA 90732",
    "addr:housenumber":"1854",
    "addr:postcode":"90732",
    "addr:street":"El Rey Rd",
    "iso:country":"US",
    "sg:address":"1854 el Rey Rd",
    "sg:city":"San Pedro",
    "sg:classifiers":[
        {
            "category":"Social Services",
            "subcategory":"Adult Care",
            "type":"Services"
        }
    ],
    "sg:phone":"+1 310 831 3742",
    "sg:postcode":"90732",
    "sg:province":"CA",
    "sg:tags":[
        "home",
        "residential"
    ],
    "wof:name":"SHANGRI-LA Miraleste Pines",
    "wof:placetype":"venue"
},
  "geometry": {"coordinates":[-118.315226,33.739976],"type":"Point"}
}