{
  "type": "Feature",
  "properties": {
    "addr:full":"1100 Carver Rd Frnt Modesto CA 95350",
    "addr:housenumber":"1100",
    "addr:postcode":"95350",
    "addr:street":"Carver Rd",
    "iso:country":"US",
    "sg:address":"1100 Carver Rd Frnt",
    "sg:city":"Modesto",
    "sg:classifiers":[
        {
            "category":"Food & Beverages",
            "subcategory":"Groceries & Convenience Stores",
            "type":"Retail Goods"
        }
    ],
    "sg:phone":"+1 209 579 5057",
    "sg:postcode":"95350",
    "sg:province":"CA",
    "wof:name":"Sam's Foods City",
    "wof:placetype":"venue"
},
  "geometry": {"coordinates":[-121.022003,37.659199],"type":"Point"}
}