{
  "type": "Feature",
  "properties": {
    "iso:country":"US",
    "sg:address":"228 S Brand Blvd",
    "sg:city":"Glendale",
    "sg:classifiers":[
        {
            "category":"Shopping",
            "subcategory":"Jewelry",
            "type":"Retail Goods"
        }
    ],
    "sg:phone":"+1 818 243 5290",
    "sg:postcode":"91204",
    "sg:province":"CA",
    "wof:name":"Pawn Shop",
    "wof:placetype":"venue"
},
  "geometry": {"coordinates":[-118.254997,34.1446],"type":"Point"}
}