{
  "type": "Feature",
  "properties": {
    "addr:full":"1990 N Imperial Ave El Centro CA 92243",
    "addr:housenumber":"1990",
    "addr:postcode":"92243",
    "addr:street":"N Imperial Ave",
    "iso:country":"US",
    "sg:address":"1990 N Imperial Ave",
    "sg:city":"El Centro",
    "sg:classifiers":[
        {
            "category":"Restaurant",
            "type":"Food & Drink"
        }
    ],
    "sg:menulink":"http://www.allmenus.com/ca/el-centro/213484-taco-bell/menu/",
    "sg:phone":"+1 760 352 7639",
    "sg:postcode":"92243",
    "sg:province":"CA",
    "sg:tags":[
        "mexican"
    ],
    "wof:name":"Taco Bell",
    "wof:placetype":"venue"
},
  "geometry": {"coordinates":[-115.56997200000001,32.808909],"type":"Point"}
}