{
  "type": "Feature",
  "properties": {
    "addr:full":"14122 Hubbard St Sylmar CA 91342",
    "addr:housenumber":"14122",
    "addr:postcode":"91342",
    "addr:street":"Hubbard St",
    "iso:country":"US",
    "sg:address":"14122 Hubbard St",
    "sg:city":"Sylmar",
    "sg:classifiers":[
        {
            "category":"Health Services",
            "subcategory":"Nursing And Care Facility",
            "type":"Services"
        }
    ],
    "sg:phone":"+1 818 361 0191",
    "sg:postcode":"91342",
    "sg:province":"CA",
    "sg:tags":[
        "home",
        "convalescent"
    ],
    "wof:name":"Pine Ridge Care Ctr",
    "wof:placetype":"venue"
},
  "geometry": {"coordinates":[-118.44009200000001,34.29871],"type":"Point"}
}