{
  "type": "Feature",
  "properties": {
    "iso:country":"US",
    "sg:address":"1553 San Altos Pl",
    "sg:city":"Lemon Grove",
    "sg:classifiers":[
        {
            "category":"Banks & Credit Unions",
            "subcategory":"Financial Services",
            "type":"Services"
        }
    ],
    "sg:phone":"+1 619 463 2822",
    "sg:postcode":"91945",
    "sg:province":"CA",
    "sg:tags":[
        "trust",
        "management"
    ],
    "wof:name":"Sumrall Dorothy Trust 09",
    "wof:placetype":"venue"
},
  "geometry": {"coordinates":[-117.043192,32.719982],"type":"Point"}
}