{
  "type": "Feature",
  "properties": {
    "addr:full":"5930 Temple City Blvd Temple City CA 91780",
    "addr:housenumber":"5930",
    "addr:postcode":"91780",
    "addr:street":"Temple City Blvd",
    "iso:country":"US",
    "sg:address":"5930 Temple City Blvd",
    "sg:city":"Temple City",
    "sg:classifiers":[
        {
            "category":"Professional",
            "type":"Services"
        }
    ],
    "sg:phone":"+1 626 286 5777",
    "sg:postcode":"91780",
    "sg:province":"CA",
    "wof:name":"YLF USA Inc",
    "wof:placetype":"venue"
},
  "geometry": {"coordinates":[-118.061097,34.107937],"type":"Point"}
}