{
  "type": "Feature",
  "properties": {
    "addr:full":"1726 S Grand Ave Santa Ana CA 92705",
    "addr:housenumber":"1726",
    "addr:postcode":"92705",
    "addr:street":"S Grand Ave",
    "iso:country":"US",
    "sg:address":"1726 S Grand Ave",
    "sg:city":"Santa Ana",
    "sg:classifiers":[
        {
            "category":"Wholesale",
            "subcategory":"Machinery & Supplies",
            "type":"Manufacturing & Wholesale Goods"
        }
    ],
    "sg:phone":"+1 714 543 6851",
    "sg:postcode":"92705",
    "sg:province":"CA",
    "sg:tags":[
        "hardware",
        "industrial"
    ],
    "wof:name":"Supreme Cutting Tools",
    "wof:placetype":"venue"
},
  "geometry": {"coordinates":[-117.85057399999999,33.723136],"type":"Point"}
}