{
  "type": "Feature",
  "properties": {
    "iso:country":"US",
    "sg:address":"101 W Victoria Street",
    "sg:city":"Gardena",
    "sg:classifiers":[
        {
            "category":"Utilities",
            "type":"Services"
        }
    ],
    "sg:phone":"+1 310 217 0203",
    "sg:postcode":"90248",
    "sg:province":"CA",
    "sg:tags":[
        "provider",
        "internet"
    ],
    "wof:name":"Edco Stations",
    "wof:placetype":"venue"
},
  "geometry": {"coordinates":[-118.275734,33.865345],"type":"Point"}
}