{
  "type": "Feature",
  "properties": {
    "iso:country":"US",
    "sg:address":"20445 Pacifica Dr Ste B",
    "sg:city":"Cupertino",
    "sg:classifiers":[
        {
            "category":"Health Services",
            "subcategory":"Dentist",
            "type":"Services"
        }
    ],
    "sg:phone":"+1 408 996 8595",
    "sg:postcode":"95014",
    "sg:province":"CA",
    "sg:website":"www.dentist-cupertino.com",
    "wof:name":"LA FROM RANDALL DDS",
    "wof:placetype":"venue"
},
  "geometry": {"coordinates":[-122.08049,37.31632],"type":"Point"}
}