{
  "type": "Feature",
  "properties": {
    "addr:full":"1780 Oak St Torrance CA 90501",
    "addr:housenumber":"1780",
    "addr:postcode":"90501",
    "addr:street":"Oak St",
    "iso:country":"US",
    "sg:address":"1780 Oak St",
    "sg:city":"Torrance",
    "sg:classifiers":[
        {
            "category":"Wholesale",
            "subcategory":"Electrical",
            "type":"Manufacturing & Wholesale Goods"
        }
    ],
    "sg:phone":"+1 310 782 7520",
    "sg:postcode":"90501",
    "sg:province":"CA",
    "sg:tags":[
        "electronic"
    ],
    "wof:name":"Melodic Devices",
    "wof:placetype":"venue"
},
  "geometry": {"coordinates":[-118.32670299999999,33.831245],"type":"Point"}
}