{
  "type": "Feature",
  "properties": {
    "iso:country":"US",
    "sg:address":"2309 Columbus Pkwy",
    "sg:city":"Vallejo",
    "sg:classifiers":[
        {
            "category":"Organizations",
            "subcategory":"Religious Organization",
            "type":"Services"
        }
    ],
    "sg:phone":"+1 707 643 3108",
    "sg:postcode":"94591",
    "sg:province":"CA",
    "sg:tags":[
        "church"
    ],
    "wof:name":"Wayside United Methodist Chr",
    "wof:placetype":"venue"
},
  "geometry": {"coordinates":[-122.19932,38.098852],"type":"Point"}
}