{
  "type": "Feature",
  "properties": {
    "iso:country":"US",
    "sg:address":"2170 Shattuck Ave",
    "sg:city":"Berkeley",
    "sg:classifiers":[
        {
            "category":"Ice Cream",
            "type":"Food & Drink"
        }
    ],
    "sg:phone":"+1 510 649 1888",
    "sg:postcode":"94704",
    "sg:province":"CA",
    "sg:tags":[
        "frozen",
        "yogurt"
    ],
    "sg:website":"www.almaregelato.com",
    "wof:name":"Almare Gelato Italiano",
    "wof:placetype":"venue"
},
  "geometry": {"coordinates":[-122.268036,37.869777],"type":"Point"}
}