{
  "type": "Feature",
  "properties": {
    "iso:country":"US",
    "sg:address":"3200 Wilshire Blvd Ste 502",
    "sg:city":"Los Angeles",
    "sg:classifiers":[
        {
            "category":"Professional",
            "subcategory":"Accounting & Tax Preparation",
            "type":"Services"
        }
    ],
    "sg:phone":"+1 213 380 3333",
    "sg:postcode":"90010",
    "sg:province":"CA",
    "sg:tags":[
        "accountant"
    ],
    "wof:name":"David S Choi CPA",
    "wof:placetype":"venue"
},
  "geometry": {"coordinates":[-118.292,34.061798],"type":"Point"}
}