{
  "type": "Feature",
  "properties": {
    "addr:full":"2705 K Street Sacramento CA 95816",
    "addr:housenumber":"2705",
    "addr:postcode":"95816",
    "addr:street":"K Street",
    "iso:country":"US",
    "sg:address":"2705 K Street",
    "sg:city":"Sacramento",
    "sg:classifiers":[
        {
            "category":"Professional",
            "subcategory":"Accounting & Tax Preparation",
            "type":"Services"
        }
    ],
    "sg:phone":"+1 916 441 1116",
    "sg:postcode":"95816",
    "sg:province":"CA",
    "sg:tags":[
        "accountant",
        "bookkeeping",
        "public",
        "accountants-certified"
    ],
    "wof:name":"Olin Bruce M CPA",
    "wof:placetype":"venue"
},
  "geometry": {"coordinates":[-121.47093099999999,38.573134],"type":"Point"}
}