{
  "type": "Feature",
  "properties": {
    "iso:country":"US",
    "sg:address":"24201 Valencia Blvd",
    "sg:city":"Valencia",
    "sg:classifiers":[
        {
            "category":"Personal",
            "subcategory":"Beauty Salon",
            "type":"Services"
        }
    ],
    "sg:phone":"+1 661 254 2800",
    "sg:postcode":"91355",
    "sg:province":"CA",
    "wof:name":"Brow Art",
    "wof:placetype":"venue"
},
  "geometry": {"coordinates":[-118.557388,34.413212],"type":"Point"}
}