{
  "type": "Feature",
  "properties": {
    "addr:full":"701 Roberts Ln Bakersfield CA 93308",
    "addr:housenumber":"701",
    "addr:postcode":"93308",
    "addr:street":"Roberts Ln",
    "iso:country":"US",
    "sg:address":"701 Roberts Ln",
    "sg:city":"Bakersfield",
    "sg:classifiers":[
        {
            "category":"Retail",
            "subcategory":"Auto Repair",
            "type":"Services"
        }
    ],
    "sg:phone":"+1 661 399 1757",
    "sg:postcode":"93308",
    "sg:province":"CA",
    "sg:tags":[
        "automobile",
        "smog"
    ],
    "wof:name":"Smog Master",
    "wof:placetype":"venue"
},
  "geometry": {"coordinates":[-119.035544,35.408617],"type":"Point"}
}