{
  "type": "Feature",
  "properties": {
    "addr:full":"3001 Red Hill Avenue Costa Mesa CA 92626",
    "addr:housenumber":"3001",
    "addr:postcode":"92626",
    "addr:street":"Red Hill Avenue",
    "iso:country":"US",
    "sg:address":"3001 Red Hill Avenue",
    "sg:city":"Costa Mesa",
    "sg:classifiers":[
        {
            "category":"Professional",
            "subcategory":"Accounting & Tax Preparation",
            "type":"Services"
        }
    ],
    "sg:phone":"+1 714 979 3108",
    "sg:postcode":"92626",
    "sg:province":"CA",
    "sg:tags":[
        "accountant"
    ],
    "wof:name":"Lamas Paul CPA",
    "wof:placetype":"venue"
},
  "geometry": {"coordinates":[-117.878648,33.672113],"type":"Point"}
}