{
  "type": "Feature",
  "properties": {
    "iso:country":"US",
    "sg:address":"10833 Le Conte Ave",
    "sg:city":"Los Angeles",
    "sg:classifiers":[
        {
            "category":"Health Services",
            "subcategory":"Clinic",
            "type":"Services"
        }
    ],
    "sg:phone":"+1 310 206 8232",
    "sg:postcode":"90024",
    "sg:province":"CA",
    "sg:tags":[
        "home",
        "care"
    ],
    "wof:name":"Hillel Laks",
    "wof:placetype":"venue"
},
  "geometry": {"coordinates":[-118.445273,34.063751],"type":"Point"}
}