{
  "type": "Feature",
  "properties": {
    "addr:full":"737 N La Brea Avenue Inglewood CA 90302",
    "addr:housenumber":"737",
    "addr:postcode":"90302",
    "addr:street":"N La Brea Avenue",
    "iso:country":"US",
    "sg:address":"737 N La Brea Avenue",
    "sg:city":"Inglewood",
    "sg:classifiers":[
        {
            "category":"Retail",
            "subcategory":"Auto Repair",
            "type":"Services"
        },
        {
            "category":"Government",
            "subcategory":"Office",
            "type":"Public Place"
        }
    ],
    "sg:phone":"+1 310 677 6157",
    "sg:postcode":"90302",
    "sg:province":"CA",
    "sg:tags":[
        "smog",
        "check"
    ],
    "wof:name":"A & B Auto Collision",
    "wof:placetype":"venue"
},
  "geometry": {"coordinates":[-118.35767300000001,33.972061],"type":"Point"}
}