{
  "type": "Feature",
  "properties": {
    "addr:full":"609 W Hyde Park Blvd Inglewood CA 90302",
    "addr:housenumber":"609",
    "addr:postcode":"90302",
    "addr:street":"W Hyde Park Blvd",
    "iso:country":"US",
    "sg:address":"609 W Hyde Park Blvd",
    "sg:city":"Inglewood",
    "sg:classifiers":[
        {
            "category":"Manufacturing",
            "subcategory":"Apparel",
            "type":"Manufacturing & Wholesale Goods"
        }
    ],
    "sg:phone":"+1 310 412 9060",
    "sg:postcode":"90302",
    "sg:province":"CA",
    "sg:tags":[
        "silk",
        "screen",
        "printing",
        "embroidery"
    ],
    "wof:name":"Buc Enterprises Inc",
    "wof:placetype":"venue"
},
  "geometry": {"coordinates":[-118.363225,33.970226],"type":"Point"}
}