{
  "type": "Feature",
  "properties": {
    "addr:full":"2912 Diamond St # 373 San Francisco CA 94131",
    "addr:housenumber":"2912",
    "addr:postcode":"94131",
    "addr:street":"Diamond St # 373",
    "iso:country":"US",
    "sg:address":"2912 Diamond St # 373",
    "sg:city":"San Francisco",
    "sg:classifiers":[
        {
            "category":"Banks & Credit Unions",
            "subcategory":"Atm",
            "type":"Services"
        }
    ],
    "sg:phone":"+1 415 951 4949",
    "sg:postcode":"94131",
    "sg:province":"CA",
    "sg:tags":[
        "bankruptcy"
    ],
    "sg:website":"sanfranbankruptcy.net?n=t&ubl=true",
    "wof:name":"Law Office Of James Michel",
    "wof:placetype":"venue"
},
  "geometry": {"coordinates":[-122.43436,37.73343],"type":"Point"}
}