{
  "type": "Feature",
  "properties": {
    "addr:full":"6444 E Spring St Long Beach CA 90815",
    "addr:housenumber":"6444",
    "addr:postcode":"90815",
    "addr:street":"E Spring St",
    "iso:country":"US",
    "sg:address":"6444 E Spring St",
    "sg:city":"Long Beach",
    "sg:classifiers":[
        {
            "category":"Professional",
            "subcategory":"Computer Services",
            "type":"Services"
        }
    ],
    "sg:phone":"+1 562 900 0862",
    "sg:postcode":"90815",
    "sg:province":"CA",
    "sg:tags":[
        "internet"
    ],
    "wof:name":"T Tech Consulting",
    "wof:placetype":"venue"
},
  "geometry": {"coordinates":[-118.105605,33.810401],"type":"Point"}
}