{
  "type": "Feature",
  "properties": {
    "addr:full":"135 Hi Grade Ln Freedom CA 95019",
    "addr:housenumber":"135",
    "addr:postcode":"95019",
    "addr:street":"Hi Grade Ln",
    "iso:country":"US",
    "sg:address":"135 Hi Grade Ln",
    "sg:city":"Freedom",
    "sg:classifiers":[
        {
            "category":"Shopping",
            "subcategory":"Computers & Home Electronics",
            "type":"Retail Goods"
        }
    ],
    "sg:phone":"+1 831 722 6434",
    "sg:postcode":"95019",
    "sg:province":"CA",
    "sg:tags":[
        "software"
    ],
    "wof:name":"Gss Geotechnical Software Svc",
    "wof:placetype":"venue"
},
  "geometry": {"coordinates":[-121.771734,36.938866],"type":"Point"}
}