{
  "type": "Feature",
  "properties": {
    "addr:full":"625 Market Street San Francisco CA 94105",
    "addr:housenumber":"625",
    "addr:postcode":"94105",
    "addr:street":"Market Street",
    "iso:country":"US",
    "sg:address":"625 Market Street",
    "sg:city":"San Francisco",
    "sg:classifiers":[
        {
            "category":"Professional",
            "subcategory":"Accounting & Tax Preparation",
            "type":"Services"
        }
    ],
    "sg:phone":"+1 415 495 3399",
    "sg:postcode":"94105",
    "sg:province":"CA",
    "sg:tags":[
        "accountant"
    ],
    "wof:name":"Haskins Pan CPA Ms",
    "wof:placetype":"venue"
},
  "geometry": {"coordinates":[-122.402,37.788799],"type":"Point"}
}