{
  "type": "Feature",
  "properties": {
    "iso:country":"US",
    "sg:address":"16162 Beach Boulevard",
    "sg:city":"Huntington Beach",
    "sg:classifiers":[
        {
            "category":"Professional",
            "subcategory":"Accounting & Tax Preparation",
            "type":"Services"
        }
    ],
    "sg:phone":"+1 714 668 8822",
    "sg:postcode":"92647",
    "sg:province":"CA",
    "sg:tags":[
        "accountant"
    ],
    "wof:name":"Kellogg & Andelson Accountancy Corporation",
    "wof:placetype":"venue"
},
  "geometry": {"coordinates":[-117.98913400000001,33.728239],"type":"Point"}
}