{
  "type": "Feature",
  "properties": {
    "iso:country":"US",
    "sg:address":"2365 Marconi Ct",
    "sg:city":"San Diego",
    "sg:classifiers":[
        {
            "category":"Wholesale",
            "subcategory":"Seafood",
            "type":"Manufacturing & Wholesale Goods"
        }
    ],
    "sg:phone":"+1 619 216 8024",
    "sg:postcode":"92154",
    "sg:province":"CA",
    "sg:tags":[
        "fish"
    ],
    "wof:name":"Alva Trading Co",
    "wof:placetype":"venue"
},
  "geometry": {"coordinates":[-116.93388400000001,32.55543],"type":"Point"}
}