{
  "type": "Feature",
  "properties": {
    "addr:full":"220 Sycamore Rd San Ysidro CA 92173",
    "addr:housenumber":"220",
    "addr:postcode":"92173",
    "addr:street":"Sycamore Rd",
    "iso:country":"US",
    "sg:address":"220 Sycamore Rd",
    "sg:city":"San Ysidro",
    "sg:classifiers":[
        {
            "category":"Autos & Motor Vehicles",
            "subcategory":"Fuel & Gas Station",
            "type":"Retail Goods"
        }
    ],
    "sg:phone":"+1 619 428 8807",
    "sg:postcode":"92173",
    "sg:province":"CA",
    "sg:tags":[
        "oil"
    ],
    "wof:name":"Cheveron Stations Inc",
    "wof:placetype":"venue"
},
  "geometry": {"coordinates":[-117.04510000000001,32.549762],"type":"Point"}
}