{
  "type": "Feature",
  "properties": {
    "addr:full":"1071 S De Anza Blvd San Jose CA 95129",
    "addr:housenumber":"1071",
    "addr:postcode":"95129",
    "addr:street":"S De Anza Blvd",
    "iso:country":"US",
    "sg:address":"1071 S De Anza Blvd",
    "sg:city":"San Jose",
    "sg:classifiers":[
        {
            "category":"Restaurant",
            "type":"Food & Drink"
        }
    ],
    "sg:menulink":"http://www.allmenus.com/ca/san-jose/52848-manna-tofu-house/menu/",
    "sg:phone":"+1 408 863 0707",
    "sg:postcode":"95129",
    "sg:province":"CA",
    "sg:tags":[
        "korean",
        "asian"
    ],
    "wof:name":"Manna Tofu House",
    "wof:placetype":"venue"
},
  "geometry": {"coordinates":[-122.03215899999999,37.306754],"type":"Point"}
}