{
  "type": "Feature",
  "properties": {
    "iso:country":"US",
    "sg:address":"13172 Peak Cir",
    "sg:city":"Westminster",
    "sg:classifiers":[
        {
            "category":"Professional",
            "type":"Services"
        }
    ],
    "sg:phone":"+1 714 892 0559",
    "sg:postcode":"92683",
    "sg:province":"CA",
    "wof:name":"Suene Tauanuu",
    "wof:placetype":"venue"
},
  "geometry": {"coordinates":[-118.012326,33.77043],"type":"Point"}
}