{
  "type": "Feature",
  "properties": {
    "addr:full":"7677 Oakport St Ste 1020 Oakland CA 94621",
    "addr:housenumber":"7677",
    "addr:postcode":"94621",
    "addr:street":"Oakport St Ste 1020",
    "iso:country":"US",
    "sg:address":"7677 Oakport St Ste 1020",
    "sg:city":"Oakland",
    "sg:classifiers":[
        {
            "category":"Professional",
            "subcategory":"Lawyer & Legal Services",
            "type":"Services"
        }
    ],
    "sg:phone":"+1 510 562 6800",
    "sg:postcode":"94621",
    "sg:province":"CA",
    "sg:tags":[
        "litigation",
        "attorney",
        "tort"
    ],
    "wof:name":"Von Rock , Hallie L. - Aiman-Smith & Mar",
    "wof:placetype":"venue"
},
  "geometry": {"coordinates":[-122.20039199999999,37.744568],"type":"Point"}
}