{
  "type": "Feature",
  "properties": {
    "iso:country":"US",
    "sg:address":"1325 S Broadway",
    "sg:city":"Los Angeles",
    "sg:classifiers":[
        {
            "category":"Mining & Drilling",
            "type":"Manufacturing & Wholesale Goods"
        }
    ],
    "sg:phone":"+1 213 748 3420",
    "sg:postcode":"90015",
    "sg:province":"CA",
    "sg:tags":[
        "owner",
        "operator",
        "site",
        "drill"
    ],
    "wof:name":"St James Oil Corporation",
    "wof:placetype":"venue"
},
  "geometry": {"coordinates":[-118.26150699999999,34.036938],"type":"Point"}
}