{
  "type": "Feature",
  "properties": {
    "iso:country":"US",
    "sg:address":"665 Cam de Los Mares",
    "sg:city":"San Clemente",
    "sg:classifiers":[
        {
            "category":"Health Services",
            "subcategory":"Doctor",
            "type":"Services"
        }
    ],
    "sg:phone":"+1 949 496 6770",
    "sg:postcode":"92673",
    "sg:province":"CA",
    "sg:tags":[
        "surgery",
        "cosmetic"
    ],
    "wof:name":"Facial Aesthetic Concepts",
    "wof:placetype":"venue"
},
  "geometry": {"coordinates":[-117.645679,33.456845],"type":"Point"}
}