{
  "type": "Feature",
  "properties": {
    "iso:country":"US",
    "sg:address":"558 Capp Street",
    "sg:city":"San Francisco",
    "sg:classifiers":[
        {
            "category":"Professional",
            "subcategory":"Lawyer & Legal Services",
            "type":"Services"
        }
    ],
    "sg:phone":"+1 415 282 9300",
    "sg:postcode":"94110",
    "sg:province":"CA",
    "wof:name":"Lederman Rachel Atty",
    "wof:placetype":"venue"
},
  "geometry": {"coordinates":[-122.41799899999999,37.757801],"type":"Point"}
}