{
  "type": "Feature",
  "properties": {
    "iso:country":"US",
    "sg:address":"10284 E Underwood Rd",
    "sg:city":"Acampo",
    "sg:classifiers":[
        {
            "category":"Home & Garden",
            "subcategory":"Building Materials",
            "type":"Retail Goods"
        },
        {
            "category":"Manufacturing",
            "subcategory":"Glass & Minerals",
            "type":"Manufacturing & Wholesale Goods"
        }
    ],
    "sg:phone":"+1 209 334 9234",
    "sg:postcode":"95220",
    "sg:province":"CA",
    "sg:tags":[
        "ready",
        "concrete",
        "mixed",
        "mfg"
    ],
    "wof:name":"Pearsons Concrete",
    "wof:placetype":"venue"
},
  "geometry": {"coordinates":[-121.196911,38.211362],"type":"Point"}
}