{
  "type": "Feature",
  "properties": {
    "addr:full":"9470 Stirrup St Riverside CA 92509",
    "addr:housenumber":"9470",
    "addr:postcode":"92509",
    "addr:street":"Stirrup St",
    "iso:country":"US",
    "sg:address":"9470 Stirrup St",
    "sg:city":"Riverside",
    "sg:classifiers":[
        {
            "category":"Building & Trades",
            "subcategory":"Landscaping Services",
            "type":"Services"
        }
    ],
    "sg:phone":"+1 951 961 2089",
    "sg:postcode":"92509",
    "sg:province":"CA",
    "sg:tags":[
        "landscape"
    ],
    "wof:name":"From Ground Up",
    "wof:placetype":"venue"
},
  "geometry": {"coordinates":[-117.492256,33.980002],"type":"Point"}
}