{
  "type": "Feature",
  "properties": {
    "addr:full":"10721 Avonbury Ave Whittier CA 90603",
    "addr:housenumber":"10721",
    "addr:postcode":"90603",
    "addr:street":"Avonbury Ave",
    "iso:country":"US",
    "sg:address":"10721 Avonbury Ave",
    "sg:city":"Whittier",
    "sg:classifiers":[
        {
            "category":"Manufacturing",
            "subcategory":"Metals",
            "type":"Manufacturing & Wholesale Goods"
        }
    ],
    "sg:phone":"+1 562 902 8675",
    "sg:postcode":"90603",
    "sg:province":"CA",
    "wof:name":"Silver Designs",
    "wof:placetype":"venue"
},
  "geometry": {"coordinates":[-117.990229,33.93656],"type":"Point"}
}