{
  "type": "Feature",
  "properties": {
    "addr:full":"1554 Lincoln Ave San Rafael CA 94901",
    "addr:housenumber":"1554",
    "addr:postcode":"94901",
    "addr:street":"Lincoln Ave",
    "iso:country":"US",
    "sg:address":"1554 Lincoln Ave",
    "sg:city":"San Rafael",
    "sg:classifiers":[
        {
            "category":"Insurance",
            "subcategory":"Insurance Agent",
            "type":"Services"
        }
    ],
    "sg:phone":"+1 415 456 7545",
    "sg:postcode":"94901",
    "sg:province":"CA",
    "wof:name":"State Farm Insurance",
    "wof:placetype":"venue"
},
  "geometry": {"coordinates":[-122.52310900000001,37.981494],"type":"Point"}
}