{
  "type": "Feature",
  "properties": {
    "addr:full":"36236 Plaza Dr Cathedral City CA 92234",
    "addr:housenumber":"36236",
    "addr:postcode":"92234",
    "addr:street":"Plaza Dr",
    "iso:country":"US",
    "sg:address":"36236 Plaza Dr",
    "sg:city":"Cathedral City",
    "sg:classifiers":[
        {
            "category":"Retail",
            "subcategory":"Auto Repair",
            "type":"Services"
        }
    ],
    "sg:phone":"+1 760 321 6500",
    "sg:postcode":"92234",
    "sg:province":"CA",
    "sg:tags":[
        "repairing",
        "automobile"
    ],
    "wof:name":"Stark's 2",
    "wof:placetype":"venue"
},
  "geometry": {"coordinates":[-116.46346,33.785521],"type":"Point"}
}