{
  "type": "Feature",
  "properties": {
    "iso:country":"US",
    "sg:address":"1898 Travertine Way",
    "sg:city":"Union City",
    "sg:classifiers":[
        {
            "category":"Professional",
            "type":"Services"
        }
    ],
    "sg:phone":"+1 510 324 0625",
    "sg:postcode":"94587",
    "sg:province":"CA",
    "sg:tags":[
        "establishment"
    ],
    "wof:name":"Ps Carrier",
    "wof:placetype":"venue"
},
  "geometry": {"coordinates":[-122.014312,37.58668],"type":"Point"}
}