{
  "type": "Feature",
  "properties": {
    "addr:full":"1062 S De Anza Blvd San Jose CA 95129",
    "addr:housenumber":"1062",
    "addr:postcode":"95129",
    "addr:street":"S De Anza Blvd",
    "iso:country":"US",
    "sg:address":"1062 S De Anza Blvd",
    "sg:city":"San Jose",
    "sg:classifiers":[
        {
            "category":"Health Services",
            "subcategory":"Dentist",
            "type":"Services"
        }
    ],
    "sg:phone":"+1 408 255 9666",
    "sg:postcode":"95129",
    "sg:province":"CA",
    "sg:website":"www.wendyludds.com",
    "wof:name":"Wendy Lu, DDS",
    "wof:placetype":"venue"
},
  "geometry": {"coordinates":[-122.031998,37.307999],"type":"Point"}
}