{
  "type": "Feature",
  "properties": {
    "addr:full":"6020 Channing Dr North Highlands CA 95660",
    "addr:housenumber":"6020",
    "addr:postcode":"95660",
    "addr:street":"Channing Dr",
    "iso:country":"US",
    "sg:address":"6020 Channing Dr",
    "sg:city":"North Highlands",
    "sg:classifiers":[
        {
            "category":"Retail",
            "subcategory":"Repair Shop",
            "type":"Services"
        }
    ],
    "sg:phone":"+1 916 470 2636",
    "sg:postcode":"95660",
    "sg:province":"CA",
    "sg:tags":[
        "taxidermist"
    ],
    "wof:name":"Eddie Bos Taxidermy",
    "wof:placetype":"venue"
},
  "geometry": {"coordinates":[-121.373627,38.676248],"type":"Point"}
}