{
  "type": "Feature",
  "properties": {
    "iso:country":"US",
    "sg:address":"2938 Scott Blvd",
    "sg:city":"Santa Clara",
    "sg:classifiers":[
        {
            "category":"Wholesale",
            "subcategory":"Medical Equipment & Supplies",
            "type":"Manufacturing & Wholesale Goods"
        }
    ],
    "sg:phone":"+1 408 988 9969",
    "sg:postcode":"95050",
    "sg:province":"CA",
    "sg:tags":[
        "physician",
        "surgeon"
    ],
    "wof:name":"New Abilities Systems Inc",
    "wof:placetype":"venue"
},
  "geometry": {"coordinates":[-121.959597,37.37562],"type":"Point"}
}