{
  "type": "Feature",
  "properties": {
    "addr:full":"724 Moorpark Ave Moorpark CA 93021",
    "addr:housenumber":"724",
    "addr:postcode":"ca 93021",
    "addr:street":"Moorpark Ave",
    "iso:country":"US",
    "sg:address":"724 Moorpark Ave",
    "sg:city":"Moorpark",
    "sg:classifiers":[
        {
            "category":"Health Services",
            "subcategory":"Dentist",
            "type":"Services"
        }
    ],
    "sg:phone":"+1 805 531 5432",
    "sg:postcode":"93021",
    "sg:province":"CA",
    "sg:website":"http://www.kidsdental.com",
    "wof:name":"Yee M James Dds",
    "wof:placetype":"venue"
},
  "geometry": {"coordinates":[-118.88215,34.286806],"type":"Point"}
}