{
  "type": "Feature",
  "properties": {
    "iso:country":"US",
    "sg:address":"1015 N Lake Ave",
    "sg:city":"Pasadena",
    "sg:classifiers":[
        {
            "category":"Insurance",
            "subcategory":"Insurance Agent",
            "type":"Services"
        }
    ],
    "sg:phone":"+1 626 794 8699",
    "sg:postcode":"91104",
    "sg:province":"CA",
    "sg:tags":[
        "broker"
    ],
    "wof:name":"Bert Porter Investigations",
    "wof:placetype":"venue"
},
  "geometry": {"coordinates":[-118.132525,34.164163],"type":"Point"}
}