{
  "type": "Feature",
  "properties": {
    "addr:full":"1428 N Pine St Orange CA 92867",
    "addr:housenumber":"1428",
    "addr:postcode":"92867",
    "addr:street":"N Pine St",
    "iso:country":"US",
    "sg:address":"1428 N Pine St",
    "sg:city":"Orange",
    "sg:classifiers":[
        {
            "category":"Building & Trades",
            "subcategory":"Construction",
            "type":"Services"
        }
    ],
    "sg:phone":"+1 714 997 3426",
    "sg:postcode":"92867",
    "sg:province":"CA",
    "sg:tags":[
        "residential",
        "commercial"
    ],
    "wof:name":"Mastain-Lee Builders",
    "wof:placetype":"venue"
},
  "geometry": {"coordinates":[-117.845977,33.8116],"type":"Point"}
}