{
  "type": "Feature",
  "properties": {
    "addr:full":"465 36th St Oakland CA 94609",
    "addr:housenumber":"465",
    "addr:postcode":"94609",
    "addr:street":"36Th St",
    "iso:country":"US",
    "sg:address":"465 36th St",
    "sg:city":"Oakland",
    "sg:classifiers":[
        {
            "category":"Bakery",
            "type":"Food & Drink"
        }
    ],
    "sg:phone":"+1 415 317 3937",
    "sg:postcode":"94609",
    "sg:province":"CA",
    "wof:name":"Pendragon Bakery",
    "wof:placetype":"venue"
},
  "geometry": {"coordinates":[-122.26439999999999,37.82432],"type":"Point"}
}