{
  "type": "Feature",
  "properties": {
    "iso:country":"US",
    "sg:address":"1155 Santa Luisa Dr.",
    "sg:city":"Solana Beach",
    "sg:classifiers":[
        {
            "category":"Education",
            "subcategory":"Special Training",
            "type":"Public Place"
        }
    ],
    "sg:phone":"+1 760 560 6116",
    "sg:postcode":"92075",
    "sg:province":"CA",
    "sg:tags":[
        "educational",
        "tutoring"
    ],
    "sg:website":"www.tutortutor.org",
    "wof:name":"Tutor Tutor",
    "wof:placetype":"venue"
},
  "geometry": {"coordinates":[-117.246528,33.005514],"type":"Point"}
}