{
  "type": "Feature",
  "properties": {
    "iso:country":"US",
    "sg:address":"6548 Miles Ave",
    "sg:city":"Huntington Park",
    "sg:classifiers":[
        {
            "category":"Government",
            "subcategory":"Court House",
            "type":"Public Place"
        }
    ],
    "sg:phone":"+1 323 586 6371",
    "sg:postcode":"90255",
    "sg:province":"CA",
    "wof:name":"Huntington Park Superior Court",
    "wof:placetype":"venue"
},
  "geometry": {"coordinates":[-118.218986,33.979568],"type":"Point"}
}