{
  "type": "Feature",
  "properties": {
    "addr:full":"9415 Culver Blvd Culver City CA 90232",
    "addr:housenumber":"9415",
    "addr:postcode":"90232",
    "addr:street":"Culver Blvd",
    "iso:country":"US",
    "sg:address":"9415 Culver Blvd",
    "sg:city":"Culver City",
    "sg:classifiers":[
        {
            "category":"Communications",
            "subcategory":"Film & Video Production",
            "type":"Services"
        }
    ],
    "sg:phone":"+1 310 838 2973",
    "sg:postcode":"90232",
    "sg:province":"CA",
    "sg:tags":[
        "duplication",
        "tape"
    ],
    "wof:name":"Interstreamer Media Svc",
    "wof:placetype":"venue"
},
  "geometry": {"coordinates":[-118.39473,34.023536],"type":"Point"}
}