{
  "type": "Feature",
  "properties": {
    "addr:full":"800 Beaumont Ave Beaumont CA 92223",
    "addr:housenumber":"800",
    "addr:postcode":"92223",
    "addr:street":"Beaumont Ave",
    "iso:country":"US",
    "sg:address":"800 Beaumont Ave",
    "sg:city":"Beaumont",
    "sg:classifiers":[
        {
            "category":"Restaurant",
            "type":"Food & Drink"
        },
        {
            "category":"Wholesale",
            "subcategory":"Machinery & Supplies",
            "type":"Manufacturing & Wholesale Goods"
        },
        {
            "category":"Retail",
            "subcategory":"Repair Shop",
            "type":"Services"
        },
        {
            "category":"Professional",
            "subcategory":"Engineering",
            "type":"Services"
        }
    ],
    "sg:phone":"+1 951 769 3514",
    "sg:postcode":"92223",
    "sg:province":"CA",
    "sg:tags":[
        "major",
        "equipment-commercial",
        "refinishing",
        "equipment",
        "appliance",
        "supplies-refrigeration",
        "industrial",
        "refrigeration",
        "small",
        "freezers-repair",
        "refrigerator",
        "engineer"
    ],
    "wof:name":"Airflow Refrigeration Co",
    "wof:placetype":"venue"
},
  "geometry": {"coordinates":[-116.977158,33.932449],"type":"Point"}
}