{
  "type": "Feature",
  "properties": {
    "iso:country":"US",
    "sg:address":"2301 Leota St",
    "sg:city":"Huntington Park",
    "sg:classifiers":[
        {
            "category":"Professional",
            "type":"Services"
        }
    ],
    "sg:phone":"+1 323 583 9276",
    "sg:postcode":"90255",
    "sg:province":"CA",
    "wof:name":"Decent LP",
    "wof:placetype":"venue"
},
  "geometry": {"coordinates":[-118.231234,33.968783],"type":"Point"}
}