{
  "type": "Feature",
  "properties": {
    "addr:full":"475 S Mathilda Ave Sunnyvale CA 94086",
    "addr:housenumber":"475",
    "addr:postcode":"94086",
    "addr:street":"S Mathilda Ave",
    "iso:country":"US",
    "sg:address":"475 S Mathilda Ave",
    "sg:city":"Sunnyvale",
    "sg:classifiers":[
        {
            "category":"Banks & Credit Unions",
            "subcategory":"Investment Brokerage",
            "type":"Services"
        }
    ],
    "sg:phone":"+1 408 733 0984",
    "sg:postcode":"94086",
    "sg:province":"CA",
    "sg:tags":[
        "discount",
        "security",
        "dealer"
    ],
    "wof:name":"Quick & Reilly 195",
    "wof:placetype":"venue"
},
  "geometry": {"coordinates":[-122.03590699999999,37.372998],"type":"Point"}
}