{
  "type": "Feature",
  "properties": {
    "addr:full":"333 6th St Williams CA 95987",
    "addr:housenumber":"333",
    "addr:postcode":"95987",
    "addr:street":"6Th St",
    "iso:country":"US",
    "sg:address":"333 6th St",
    "sg:city":"Williams",
    "sg:classifiers":[
        {
            "category":"Wholesale",
            "subcategory":"Construction Materials",
            "type":"Manufacturing & Wholesale Goods"
        },
        {
            "category":"Home & Garden",
            "subcategory":"Building Materials",
            "type":"Retail Goods"
        }
    ],
    "sg:phone":"+1 530 473 5341",
    "sg:postcode":"95987",
    "sg:province":"CA",
    "sg:tags":[
        "lumber",
        "supply"
    ],
    "wof:name":"Close Lumber",
    "wof:placetype":"venue"
},
  "geometry": {"coordinates":[-122.149548,39.156929],"type":"Point"}
}