{
  "type": "Feature",
  "properties": {
    "addr:full":"16010 Arrow Hwy Irwindale CA 91706",
    "addr:housenumber":"16010",
    "addr:postcode":"91706",
    "addr:street":"Arrow Hwy",
    "iso:country":"US",
    "sg:address":"16010 Arrow Hwy",
    "sg:city":"Irwindale",
    "sg:classifiers":[
        {
            "category":"Retail",
            "subcategory":"Laundry & Dry Cleaning",
            "type":"Services"
        }
    ],
    "sg:phone":"+1 626 813 7290",
    "sg:postcode":"91706",
    "sg:province":"CA",
    "sg:tags":[
        "cleaners"
    ],
    "wof:name":"Cleaning Place",
    "wof:placetype":"venue"
},
  "geometry": {"coordinates":[-117.933345,34.106918],"type":"Point"}
}