{
  "type": "Feature",
  "properties": {
    "addr:full":"301 Lighthouse Dr Vallejo CA 94590",
    "addr:housenumber":"301",
    "addr:postcode":"94590",
    "addr:street":"Lighthouse Dr",
    "iso:country":"US",
    "sg:address":"301 Lighthouse Dr",
    "sg:city":"Vallejo",
    "sg:classifiers":[
        {
            "category":"Real Estate",
            "subcategory":"Real Estate Agent",
            "type":"Services"
        }
    ],
    "sg:phone":"+1 707 554 4757",
    "sg:postcode":"94590",
    "sg:province":"CA",
    "wof:name":"Lighthouse Apts",
    "wof:placetype":"venue"
},
  "geometry": {"coordinates":[-122.273325,38.121128],"type":"Point"}
}