{
  "type": "Feature",
  "properties": {
    "addr:full":"6636 del Playa Dr Goleta CA 93117",
    "addr:housenumber":"6636",
    "addr:postcode":"93117",
    "addr:street":"Del Playa Dr",
    "iso:country":"US",
    "sg:address":"6636 del Playa Dr",
    "sg:city":"Goleta",
    "sg:classifiers":[
        {
            "category":"Professional",
            "type":"Services"
        }
    ],
    "sg:phone":"+1 805 968 3096",
    "sg:postcode":"93117",
    "sg:province":"CA",
    "wof:name":"Student Connection",
    "wof:placetype":"venue"
},
  "geometry": {"coordinates":[-119.86081,34.409847],"type":"Point"}
}