{
  "type": "Feature",
  "properties": {
    "addr:full":"735 E Ohio Ave Ste 202 Escondido CA 92025",
    "addr:housenumber":"735",
    "addr:postcode":"92025",
    "addr:street":"E Ohio Ave Ste 202",
    "iso:country":"US",
    "sg:address":"735 E Ohio Ave Ste 202",
    "sg:city":"Escondido",
    "sg:classifiers":[
        {
            "category":"Health Services",
            "subcategory":"Dentist",
            "type":"Services"
        }
    ],
    "sg:phone":"+1 760 294 7450",
    "sg:postcode":"92025",
    "sg:province":"CA",
    "wof:name":"Blair Fadem Dds Corp Inc",
    "wof:placetype":"venue"
},
  "geometry": {"coordinates":[-117.275109,33.125928],"type":"Point"}
}