{
  "type": "Feature",
  "properties": {
    "addr:full":"3837 Castro Valley Blvd Castro Valley CA 94546",
    "addr:housenumber":"3837",
    "addr:postcode":"94546",
    "addr:street":"Castro Valley Blvd",
    "iso:country":"US",
    "sg:address":"3837 Castro Valley Blvd",
    "sg:city":"Castro Valley",
    "sg:classifiers":[
        {
            "category":"Restaurant",
            "type":"Food & Drink"
        }
    ],
    "sg:phone":"+1 510 538 4400",
    "sg:postcode":"94546",
    "sg:province":"CA",
    "sg:tags":[
        "thai"
    ],
    "sg:website":"www.topthaicastrovalley.com",
    "wof:name":"Top Thai",
    "wof:placetype":"venue"
},
  "geometry": {"coordinates":[-122.068584,37.69377],"type":"Point"}
}