{
  "type": "Feature",
  "properties": {
    "addr:full":"1218 W Hillsdale Blvd San Mateo CA 94403",
    "addr:housenumber":"1218",
    "addr:postcode":"94403",
    "addr:street":"W Hillsdale Blvd",
    "iso:country":"US",
    "sg:address":"1218 W Hillsdale Blvd",
    "sg:city":"San Mateo",
    "sg:classifiers":[
        {
            "category":"Restaurant",
            "type":"Food & Drink"
        }
    ],
    "sg:phone":"+1 650 345 7850",
    "sg:postcode":"94403",
    "sg:province":"CA",
    "sg:tags":[
        "shop",
        "coffee"
    ],
    "wof:name":"Starbucks",
    "wof:placetype":"venue"
},
  "geometry": {"coordinates":[-122.329601,37.532752],"type":"Point"}
}