{
  "type": "Feature",
  "properties": {
    "iso:country":"US",
    "sg:address":"1452 Main St",
    "sg:city":"Newman",
    "sg:classifiers":[
        {
            "category":"Restaurant",
            "type":"Food & Drink"
        }
    ],
    "sg:phone":"+1 209 862 1912",
    "sg:postcode":"95360",
    "sg:province":"CA",
    "wof:name":"LA Fogata",
    "wof:placetype":"venue"
},
  "geometry": {"coordinates":[-121.022043,37.314067],"type":"Point"}
}