{
  "type": "Feature",
  "properties": {
    "addr:full":"21642 Marilla St Chatsworth CA 91311",
    "addr:housenumber":"21642",
    "addr:postcode":"91311",
    "addr:street":"Marilla St",
    "iso:country":"US",
    "sg:address":"21642 Marilla St",
    "sg:city":"Chatsworth",
    "sg:classifiers":[
        {
            "category":"Retail",
            "subcategory":"Auto Repair",
            "type":"Services"
        }
    ],
    "sg:phone":"+1 818 718 8600",
    "sg:postcode":"91311",
    "sg:province":"CA",
    "sg:tags":[
        "automobile",
        "customizing"
    ],
    "wof:name":"Styline Limited",
    "wof:placetype":"venue"
},
  "geometry": {"coordinates":[-118.600589,34.247527],"type":"Point"}
}