{
  "type": "Feature",
  "properties": {
    "iso:country":"US",
    "sg:address":"1240 E Main St",
    "sg:city":"Grass Valley",
    "sg:classifiers":[
        {
            "category":"Real Estate",
            "subcategory":"Real Estate Agent",
            "type":"Services"
        }
    ],
    "sg:phone":"+1 530 272 4278",
    "sg:postcode":"95945",
    "sg:province":"CA",
    "wof:name":"Roark Realty",
    "wof:placetype":"venue"
},
  "geometry": {"coordinates":[-121.050385,39.22949],"type":"Point"}
}