{
  "type": "Feature",
  "properties": {
    "iso:country":"US",
    "sg:address":"1100 Harbor St",
    "sg:city":"Pittsburg",
    "sg:classifiers":[
        {
            "category":"Professional",
            "type":"Services"
        }
    ],
    "sg:phone":"+1 925 439 7108",
    "sg:postcode":"94565",
    "sg:province":"CA",
    "wof:name":"Blank Slate Creations",
    "wof:placetype":"venue"
},
  "geometry": {"coordinates":[-121.879347,38.024286],"type":"Point"}
}