{
  "type": "Feature",
  "properties": {
    "iso:country":"US",
    "sg:address":"13336 Beach Ave",
    "sg:city":"Marina Del Rey",
    "sg:classifiers":[
        {
            "category":"Building & Trades",
            "subcategory":"Construction",
            "type":"Services"
        }
    ],
    "sg:phone":"+1 310 306 6477",
    "sg:postcode":"90292",
    "sg:province":"CA",
    "sg:tags":[
        "designer"
    ],
    "wof:name":"3D Industrial Design",
    "wof:placetype":"venue"
},
  "geometry": {"coordinates":[-118.44338,33.991731],"type":"Point"}
}