{
  "type": "Feature",
  "properties": {
    "iso:country":"US",
    "sg:address":"2614 Beverly Blvd",
    "sg:city":"Los Angeles",
    "sg:classifiers":[
        {
            "category":"Professional",
            "type":"Services"
        }
    ],
    "sg:phone":"+1 213 480 0332",
    "sg:postcode":"90057",
    "sg:province":"CA",
    "wof:name":"A Plus Minerals",
    "wof:placetype":"venue"
},
  "geometry": {"coordinates":[-118.277579,34.069741],"type":"Point"}
}