{
  "type": "Feature",
  "properties": {
    "addr:full":"8124 Loma Verde Ave Canoga Park CA 91304",
    "addr:housenumber":"8124",
    "addr:postcode":"91304",
    "addr:street":"Loma Verde Ave",
    "iso:country":"US",
    "sg:address":"8124 Loma Verde Ave",
    "sg:city":"Canoga Park",
    "sg:classifiers":[
        {
            "category":"Professional",
            "subcategory":"Research",
            "type":"Services"
        }
    ],
    "sg:phone":"+1 818 701 2990",
    "sg:postcode":"91304",
    "sg:province":"CA",
    "sg:tags":[
        "market",
        "analysis"
    ],
    "wof:name":"De Leon Research Intl",
    "wof:placetype":"venue"
},
  "geometry": {"coordinates":[-118.589541,34.218079],"type":"Point"}
}