{
  "type": "Feature",
  "properties": {
    "addr:full":"31364 Via Colinas Thousand Oaks CA 91362",
    "addr:housenumber":"31364",
    "addr:postcode":"91362",
    "addr:street":"Via Colinas",
    "iso:country":"US",
    "sg:address":"31364 Via Colinas",
    "sg:city":"Thousand Oaks",
    "sg:classifiers":[
        {
            "category":"Wholesale",
            "subcategory":"Electrical",
            "type":"Manufacturing & Wholesale Goods"
        }
    ],
    "sg:phone":"+1 818 874 9474",
    "sg:postcode":"91362",
    "sg:province":"CA",
    "wof:name":"Oasis Audio Systems Inc",
    "wof:placetype":"venue"
},
  "geometry": {"coordinates":[-118.80640699999999,34.157142],"type":"Point"}
}