{
  "type": "Feature",
  "properties": {
    "addr:full":"3866 Ingraham St San Diego CA 92109",
    "addr:housenumber":"3866",
    "addr:postcode":"92109",
    "addr:street":"Ingraham St",
    "iso:country":"US",
    "sg:address":"3866 Ingraham St",
    "sg:city":"San Diego",
    "sg:classifiers":[
        {
            "category":"Real Estate",
            "subcategory":"Real Estate Operator",
            "type":"Services"
        }
    ],
    "sg:phone":"+1 858 274 2780",
    "sg:postcode":"92109",
    "sg:province":"CA",
    "sg:tags":[
        "building",
        "manager",
        "apartment"
    ],
    "wof:name":"Oakwood Apts",
    "wof:placetype":"venue"
},
  "geometry": {"coordinates":[-117.23831800000001,32.791121],"type":"Point"}
}