{
  "type": "Feature",
  "properties": {
    "iso:country":"US",
    "sg:address":"31816 Avenue E",
    "sg:city":"Yucaipa",
    "sg:classifiers":[
        {
            "category":"Manufacturing",
            "subcategory":"Apparel",
            "type":"Manufacturing & Wholesale Goods"
        }
    ],
    "sg:phone":"+1 909 794 7023",
    "sg:postcode":"92399",
    "sg:province":"CA",
    "sg:tags":[
        "product",
        "mfg"
    ],
    "wof:name":"Designs In Plastic Canvas",
    "wof:placetype":"venue"
},
  "geometry": {"coordinates":[-117.107995,34.02673],"type":"Point"}
}