{
  "type": "Feature",
  "properties": {
    "addr:full":"1649 Claycord Ave Concord CA 94521",
    "addr:housenumber":"1649",
    "addr:postcode":"94521",
    "addr:street":"Claycord Ave",
    "iso:country":"US",
    "sg:address":"1649 Claycord Ave",
    "sg:city":"Concord",
    "sg:classifiers":[
        {
            "category":"Education",
            "subcategory":"Special Training",
            "type":"Public Place"
        },
        {
            "category":"Education",
            "subcategory":"Preschool",
            "type":"Public Place"
        },
        {
            "category":"Education",
            "subcategory":"School",
            "type":"Public Place"
        }
    ],
    "sg:phone":"+1 925 687 1150",
    "sg:postcode":"94521",
    "sg:province":"CA",
    "sg:tags":[
        "kindergarten",
        "elementary",
        "educational"
    ],
    "sg:website":"http://www.mdusd.k12.ca.us",
    "wof:name":"Silverwood Elementary School",
    "wof:placetype":"venue"
},
  "geometry": {"coordinates":[-121.971609,37.962621],"type":"Point"}
}