{
  "type": "Feature",
  "properties": {
    "iso:country":"US",
    "sg:address":"660 Bercut Dr",
    "sg:city":"Sacramento",
    "sg:classifiers":[
        {
            "category":"Wholesale",
            "subcategory":"Electrical",
            "type":"Manufacturing & Wholesale Goods"
        }
    ],
    "sg:phone":"+1 916 553 4444",
    "sg:postcode":"95811",
    "sg:province":"CA",
    "sg:tags":[
        "control"
    ],
    "sg:website":"www.siemens.com",
    "wof:name":"Siemens Building Technologies",
    "wof:placetype":"venue"
},
  "geometry": {"coordinates":[-121.502126,38.597872],"type":"Point"}
}