{
  "type": "Feature",
  "properties": {
    "iso:country":"US",
    "sg:address":"2615 Fair Oaks Ave",
    "sg:city":"Altadena",
    "sg:classifiers":[
        {
            "category":"Food & Beverages",
            "subcategory":"Liquor & Beverages",
            "type":"Retail Goods"
        }
    ],
    "sg:phone":"+1 626 794 9807",
    "sg:postcode":"91001",
    "sg:province":"CA",
    "sg:tags":[
        "beer",
        "spirit",
        "wine"
    ],
    "wof:name":"Johnny's Liquor",
    "wof:placetype":"venue"
},
  "geometry": {"coordinates":[-118.149002,34.190601],"type":"Point"}
}