{
  "type": "Feature",
  "properties": {
    "iso:country":"US",
    "sg:address":"7585 Ronson Rd",
    "sg:city":"San Diego",
    "sg:classifiers":[
        {
            "category":"Wholesale",
            "subcategory":"Electrical",
            "type":"Manufacturing & Wholesale Goods"
        }
    ],
    "sg:phone":"+1 858 278 5441",
    "sg:postcode":"92111",
    "sg:province":"CA",
    "sg:tags":[
        "electronic",
        "representative"
    ],
    "sg:website":"www.earleassociates.com",
    "wof:name":"Earle Associates Inc",
    "wof:placetype":"venue"
},
  "geometry": {"coordinates":[-117.155455,32.828944],"type":"Point"}
}