{
  "type": "Feature",
  "properties": {
    "iso:country":"US",
    "sg:address":"12750 Center Court Dr S",
    "sg:city":"Cerritos",
    "sg:classifiers":[
        {
            "category":"Professional",
            "type":"Services"
        }
    ],
    "sg:phone":"+1 562 860 5900",
    "sg:postcode":"90703",
    "sg:province":"CA",
    "sg:tags":[
        "establishment"
    ],
    "wof:name":"OIE America Inc",
    "wof:placetype":"venue"
},
  "geometry": {"coordinates":[-118.06010999999999,33.867861],"type":"Point"}
}