{
  "type": "Feature",
  "properties": {
    "iso:country":"US",
    "sg:address":"8200 Fair Oaks Blvd Ofc",
    "sg:city":"Carmichael",
    "sg:classifiers":[
        {
            "category":"Real Estate",
            "subcategory":"Real Estate Operator",
            "type":"Services"
        }
    ],
    "sg:phone":"+1 916 944 3233",
    "sg:postcode":"95608",
    "sg:province":"CA",
    "sg:tags":[
        "apartment"
    ],
    "wof:name":"Magnolia Place Apartments",
    "wof:placetype":"venue"
},
  "geometry": {"coordinates":[-121.310997,38.6366],"type":"Point"}
}