{
  "type": "Feature",
  "properties": {
    "iso:country":"US",
    "sg:address":"2785 Pacific Coast Hwy Ste 245",
    "sg:city":"Torrance",
    "sg:classifiers":[
        {
            "category":"Autos & Motor Vehicles",
            "subcategory":"Automobile Sales",
            "type":"Retail Goods"
        }
    ],
    "sg:phone":"+1 951 538 0768",
    "sg:postcode":"90505",
    "sg:province":"CA",
    "sg:tags":[
        "limo"
    ],
    "sg:website":"www.affordalimousine.com",
    "wof:name":"Affordable Limousines",
    "wof:placetype":"venue"
},
  "geometry": {"coordinates":[-118.335768,33.794033],"type":"Point"}
}