{
  "type": "Feature",
  "properties": {
    "addr:full":"2634 W Imperial Hwy Inglewood CA 90303",
    "addr:housenumber":"2634",
    "addr:postcode":"90303",
    "addr:street":"W Imperial Hwy",
    "iso:country":"US",
    "sg:address":"2634 W Imperial Hwy",
    "sg:city":"Inglewood",
    "sg:classifiers":[
        {
            "category":"Retail",
            "subcategory":"Laundry & Dry Cleaning",
            "type":"Services"
        }
    ],
    "sg:phone":"+1 323 779 6380",
    "sg:postcode":"90303",
    "sg:province":"CA",
    "wof:name":"Plaza One Hour Cleaners",
    "wof:placetype":"venue"
},
  "geometry": {"coordinates":[-118.32199900000001,33.931],"type":"Point"}
}