{
  "type": "Feature",
  "properties": {
    "iso:country":"US",
    "sg:address":"285 Industrial Way",
    "sg:city":"Woodland",
    "sg:classifiers":[
        {
            "category":"Building & Trades",
            "subcategory":"Construction",
            "type":"Services"
        }
    ],
    "sg:phone":"+1 530 661 3580",
    "sg:postcode":"95776",
    "sg:province":"CA",
    "sg:tags":[
        "fabricator",
        "metal"
    ],
    "sg:website":"www.westatesfire.com",
    "wof:name":"Precision Laser Tek",
    "wof:placetype":"venue"
},
  "geometry": {"coordinates":[-121.752864,38.679382],"type":"Point"}
}