{
  "type": "Feature",
  "properties": {
    "addr:full":"2602 34th St Santa Monica CA 90405",
    "addr:housenumber":"2602",
    "addr:postcode":"90405",
    "addr:street":"34Th St",
    "iso:country":"US",
    "sg:address":"2602 34th St",
    "sg:city":"Santa Monica",
    "sg:classifiers":[
        {
            "category":"Manufacturing",
            "subcategory":"Tools & Machinery",
            "type":"Manufacturing & Wholesale Goods"
        }
    ],
    "sg:phone":"+1 310 664 1600",
    "sg:postcode":"90405",
    "sg:province":"CA",
    "sg:tags":[
        "peripheral",
        "computer"
    ],
    "wof:name":"U S Micro Products",
    "wof:placetype":"venue"
},
  "geometry": {"coordinates":[-118.45111900000001,34.023658],"type":"Point"}
}