{
  "type": "Feature",
  "properties": {
    "addr:full":"3115 Garfield Ave Carmichael CA 95608",
    "addr:housenumber":"3115",
    "addr:postcode":"95608",
    "addr:street":"Garfield Ave",
    "iso:country":"US",
    "sg:address":"3115 Garfield Ave",
    "sg:city":"Carmichael",
    "sg:classifiers":[
        {
            "category":"Personal",
            "type":"Services"
        }
    ],
    "sg:phone":"+1 916 485 4941",
    "sg:postcode":"95608",
    "sg:province":"CA",
    "sg:tags":[
        "therapist",
        "massage"
    ],
    "wof:name":"Olga S Mosley European Bdywrks",
    "wof:placetype":"venue"
},
  "geometry": {"coordinates":[-121.336855,38.622414],"type":"Point"}
}