{
  "type": "Feature",
  "properties": {
    "addr:full":"420 E Kettleman Ln Lodi CA 95240",
    "addr:housenumber":"420",
    "addr:postcode":"95240",
    "addr:street":"E Kettleman Ln",
    "iso:country":"US",
    "sg:address":"420 E Kettleman Ln",
    "sg:city":"Lodi",
    "sg:classifiers":[
        {
            "category":"Restaurant",
            "type":"Food & Drink"
        }
    ],
    "sg:menulink":"http://www.allmenus.com/ca/lodi/150464-subway/menu/",
    "sg:phone":"+1 209 339 8571",
    "sg:postcode":"95240",
    "sg:province":"CA",
    "sg:tags":[
        "american",
        "sandwich"
    ],
    "wof:name":"Subway",
    "wof:placetype":"venue"
},
  "geometry": {"coordinates":[-121.264287,38.116112],"type":"Point"}
}