{
  "type": "Feature",
  "properties": {
    "iso:country":"US",
    "sg:address":"245 Center St",
    "sg:city":"Healdsburg",
    "sg:classifiers":[
        {
            "category":"Restaurant",
            "type":"Food & Drink"
        }
    ],
    "sg:phone":"+1 707 433 3818",
    "sg:postcode":"95448",
    "sg:province":"CA",
    "wof:name":"El Sombrero",
    "wof:placetype":"venue"
},
  "geometry": {"coordinates":[-122.869088,38.609465],"type":"Point"}
}