{
  "type": "Feature",
  "properties": {
    "addr:full":"29632 Tamarron Laguna Niguel CA 92677",
    "addr:postcode":"29632;92677",
    "addr:street":"Tamarron",
    "iso:country":"US",
    "sg:address":"29632 Tamarron",
    "sg:city":"Laguna Niguel",
    "sg:classifiers":[
        {
            "category":"Wholesale",
            "subcategory":"Home Furnishings",
            "type":"Manufacturing & Wholesale Goods"
        }
    ],
    "sg:phone":"+1 949 249 2835",
    "sg:postcode":"92677",
    "sg:province":"CA",
    "wof:name":"Carol Grey Designs",
    "wof:placetype":"venue"
},
  "geometry": {"coordinates":[-117.726118,33.532194],"type":"Point"}
}