{
  "type": "Feature",
  "properties": {
    "addr:full":"9430 W Olympic Blvd Beverly Hills CA 90212",
    "addr:housenumber":"9430",
    "addr:postcode":"90212",
    "addr:street":"W Olympic Blvd",
    "iso:country":"US",
    "sg:address":"9430 W Olympic Blvd",
    "sg:city":"Beverly Hills",
    "sg:classifiers":[
        {
            "category":"Manufacturing",
            "subcategory":"Retail Goods",
            "type":"Manufacturing & Wholesale Goods"
        }
    ],
    "sg:phone":"+1 310 203 8810",
    "sg:postcode":"90212",
    "sg:province":"CA",
    "sg:tags":[
        "product",
        "mfg"
    ],
    "wof:name":"Goldenaltfeld Industries LLC",
    "wof:placetype":"venue"
},
  "geometry": {"coordinates":[-118.398588,34.059629],"type":"Point"}
}