{
  "type": "Feature",
  "properties": {
    "addr:full":"22080 Commerce Way Grand Terrace CA 92313",
    "addr:housenumber":"22080",
    "addr:postcode":"92313",
    "addr:street":"Commerce Way",
    "iso:country":"US",
    "sg:address":"22080 Commerce Way",
    "sg:city":"Grand Terrace",
    "sg:classifiers":[
        {
            "category":"Professional",
            "subcategory":"Management & Consulting",
            "type":"Services"
        }
    ],
    "sg:phone":"+1 909 783 2342",
    "sg:postcode":"92313",
    "sg:province":"CA",
    "sg:tags":[
        "party",
        "planning"
    ],
    "sg:website":"www.calskategt.com",
    "wof:name":"California Skate Grand Terrace",
    "wof:placetype":"venue"
},
  "geometry": {"coordinates":[-117.32288,34.03285],"type":"Point"}
}