{
  "type": "Feature",
  "properties": {
    "addr:full":"11306 183rd St Cerritos CA 90703",
    "addr:housenumber":"11306",
    "addr:postcode":"ca 90703",
    "addr:street":"183Rd St",
    "iso:country":"US",
    "sg:address":"11306 183rd St",
    "sg:city":"Cerritos",
    "sg:classifiers":[
        {
            "category":"Professional",
            "type":"Services"
        }
    ],
    "sg:phone":"+1 562 865 4063",
    "sg:postcode":"90703",
    "sg:province":"CA",
    "wof:name":"First Century Bancorp",
    "wof:placetype":"venue"
},
  "geometry": {"coordinates":[-118.090991,33.865684],"type":"Point"}
}