{
  "type": "Feature",
  "properties": {
    "iso:country":"US",
    "sg:address":"1638 W Orange Grove Ave",
    "sg:city":"Pomona",
    "sg:classifiers":[
        {
            "category":"Organizations",
            "subcategory":"Religious Organization",
            "type":"Services"
        }
    ],
    "sg:phone":"+1 909 868 1034",
    "sg:postcode":"91768",
    "sg:province":"CA",
    "sg:tags":[
        "counseling"
    ],
    "wof:name":"True Buddha Society",
    "wof:placetype":"venue"
},
  "geometry": {"coordinates":[-117.78220899999999,34.063738],"type":"Point"}
}