{
  "type": "Feature",
  "properties": {
    "addr:full":"7552 Soquel Dr Aptos CA 95003",
    "addr:housenumber":"7552",
    "addr:postcode":"ca 95003",
    "addr:street":"Soquel Dr",
    "iso:country":"US",
    "sg:address":"7552 Soquel Dr",
    "sg:city":"Aptos",
    "sg:classifiers":[
        {
            "category":"Shopping",
            "subcategory":"Jewelry",
            "type":"Retail Goods"
        }
    ],
    "sg:phone":"+1 831 688 2799",
    "sg:postcode":"95003",
    "sg:province":"CA",
    "sg:tags":[
        "watch"
    ],
    "sg:website":"www.areiasjewelers.com",
    "wof:name":"Mark Areias Jewelers",
    "wof:placetype":"venue"
},
  "geometry": {"coordinates":[-121.91100299999999,36.981998],"type":"Point"}
}