{
  "type": "Feature",
  "properties": {
    "iso:country":"US",
    "sg:address":"829 27th Ave",
    "sg:city":"Oakland",
    "sg:classifiers":[
        {
            "category":"Banks & Credit Unions",
            "subcategory":"Investment Brokerage",
            "type":"Services"
        },
        {
            "category":"Banks & Credit Unions",
            "subcategory":"Financial Services",
            "type":"Services"
        }
    ],
    "sg:phone":"+1 510 261 0700",
    "sg:postcode":"94601",
    "sg:province":"CA",
    "sg:tags":[
        "advisory",
        "planner"
    ],
    "wof:name":"Pico Association",
    "wof:placetype":"venue"
},
  "geometry": {"coordinates":[-122.235619,37.776919],"type":"Point"}
}