{
  "type": "Feature",
  "properties": {
    "iso:country":"US",
    "sg:address":"588 Pearson Rd",
    "sg:city":"Paradise",
    "sg:classifiers":[
        {
            "category":"Education",
            "subcategory":"School",
            "type":"Public Place"
        }
    ],
    "sg:phone":"+1 530 872 6415",
    "sg:postcode":"95969",
    "sg:province":"CA",
    "wof:name":"Paradise Elementary School",
    "wof:placetype":"venue"
},
  "geometry": {"coordinates":[-121.612261,39.752224],"type":"Point"}
}