{
  "type": "Feature",
  "properties": {
    "addr:full":"350 E Sierra St Portola CA 96122",
    "addr:housenumber":"350",
    "addr:postcode":"96122",
    "addr:street":"E Sierra St",
    "iso:country":"US",
    "sg:address":"350 E Sierra St",
    "sg:city":"Portola",
    "sg:classifiers":[
        {
            "category":"Autos & Motor Vehicles",
            "subcategory":"Automobile Sales",
            "type":"Retail Goods"
        }
    ],
    "sg:phone":"+1 530 832 4860",
    "sg:postcode":"96122",
    "sg:province":"CA",
    "sg:tags":[
        "car",
        "dealer"
    ],
    "wof:name":"Sierra Valley Auto Mall",
    "wof:placetype":"venue"
},
  "geometry": {"coordinates":[-120.464945,39.811896],"type":"Point"}
}