{
  "type": "Feature",
  "properties": {
    "addr:full":"6335 el Cajon Blvd San Diego CA 92115",
    "addr:housenumber":"6335",
    "addr:postcode":"92115",
    "addr:street":"El Cajon Blvd",
    "iso:country":"US",
    "sg:address":"6335 el Cajon Blvd",
    "sg:city":"San Diego",
    "sg:classifiers":[
        {
            "category":"Shopping",
            "subcategory":"Clothing, Apparel, & Fashions",
            "type":"Retail Goods"
        }
    ],
    "sg:phone":"+1 619 229 9501",
    "sg:postcode":"92115",
    "sg:province":"CA",
    "sg:tags":[
        "family"
    ],
    "wof:name":"Modacom",
    "wof:placetype":"venue"
},
  "geometry": {"coordinates":[-117.062562,32.763759],"type":"Point"}
}