{
  "type": "Feature",
  "properties": {
    "iso:country":"US",
    "sg:address":"8118 W 3rd St",
    "sg:city":"Los Angeles",
    "sg:classifiers":[
        {
            "category":"Shopping",
            "subcategory":"Crafts & Fabrics",
            "type":"Retail Goods"
        }
    ],
    "sg:phone":"+1 323 655 6487",
    "sg:postcode":"90048",
    "sg:province":"CA",
    "sg:tags":[
        "art"
    ],
    "sg:website":"www.knitculture.com",
    "wof:name":"KnitCulture Stuido",
    "wof:placetype":"venue"
},
  "geometry": {"coordinates":[-118.36657200000001,34.072198],"type":"Point"}
}