{
  "type": "Feature",
  "properties": {
    "addr:full":"624 W Southwood Dr Woodland CA 95695",
    "addr:housenumber":"624",
    "addr:postcode":"95695",
    "addr:street":"W Southwood Dr",
    "iso:country":"US",
    "sg:address":"624 W Southwood Dr",
    "sg:city":"Woodland",
    "sg:classifiers":[
        {
            "category":"Education",
            "subcategory":"School",
            "type":"Public Place"
        }
    ],
    "sg:phone":"+1 530 662 2824",
    "sg:postcode":"95695",
    "sg:province":"CA",
    "wof:name":"T L Whitehead Elementary",
    "wof:placetype":"venue"
},
  "geometry": {"coordinates":[-121.795486,38.669315],"type":"Point"}
}