{
  "type": "Feature",
  "properties": {
    "iso:country":"US",
    "sg:address":"177 Post Street",
    "sg:city":"San Francisco",
    "sg:classifiers":[
        {
            "category":"Professional",
            "subcategory":"Lawyer & Legal Services",
            "type":"Services"
        }
    ],
    "sg:phone":"+1 415 421 7151",
    "sg:postcode":"94108",
    "sg:province":"CA",
    "wof:name":"Ortiz Victor M Attys",
    "wof:placetype":"venue"
},
  "geometry": {"coordinates":[-122.404951,37.788768],"type":"Point"}
}