{
  "type": "Feature",
  "properties": {
    "iso:country":"US",
    "sg:address":"1942 E 2nd Street",
    "sg:city":"Los Angeles",
    "sg:classifiers":[
        {
            "category":"Education",
            "subcategory":"School",
            "type":"Public Place"
        }
    ],
    "sg:phone":"+1 323 269 9401",
    "sg:postcode":"90033",
    "sg:province":"CA",
    "sg:tags":[
        "high",
        "middle",
        "elementary"
    ],
    "sg:website":"www.lausd.k12.ca.us",
    "wof:name":"Second Street Elementary School",
    "wof:placetype":"venue"
},
  "geometry": {"coordinates":[-118.21799300000001,34.045529],"type":"Point"}
}