{
  "type": "Feature",
  "properties": {
    "addr:full":"39493 Los Alamos Rd Murrieta CA 92563",
    "addr:housenumber":"39493",
    "addr:postcode":"92563",
    "addr:street":"Los Alamos Rd",
    "iso:country":"US",
    "sg:address":"39493 Los Alamos Rd",
    "sg:city":"Murrieta",
    "sg:classifiers":[
        {
            "category":"Government",
            "subcategory":"Office",
            "type":"Public Place"
        }
    ],
    "sg:phone":"+1 951 600 6100",
    "sg:postcode":"92563",
    "sg:province":"CA",
    "sg:tags":[
        "general"
    ],
    "wof:name":"Building & Safety Dept",
    "wof:placetype":"venue"
},
  "geometry": {"coordinates":[-117.177356,33.575173],"type":"Point"}
}