{
  "type": "Feature",
  "properties": {
    "addr:full":"28052 Cam Capistrano Laguna Niguel CA 92677",
    "addr:housenumber":"28052",
    "addr:postcode":"92677",
    "addr:street":"Cam Capistrano",
    "iso:country":"US",
    "sg:address":"28052 Cam Capistrano",
    "sg:city":"Laguna Niguel",
    "sg:classifiers":[
        {
            "category":"Local Transit",
            "type":"Transportation"
        },
        {
            "category":"Airport",
            "type":"Transportation"
        }
    ],
    "sg:phone":"+1 949 364 5000",
    "sg:postcode":"92677",
    "sg:province":"CA",
    "wof:name":"Superior Shuttle Inc",
    "wof:placetype":"venue"
},
  "geometry": {"coordinates":[-117.67387100000001,33.553162],"type":"Point"}
}