{
  "type": "Feature",
  "properties": {
    "iso:country":"US",
    "sg:address":"16200 Amber Valley Dr",
    "sg:city":"Whittier",
    "sg:classifiers":[
        {
            "category":"Health Services",
            "subcategory":"Chiropractor",
            "type":"Services"
        }
    ],
    "sg:phone":"+1 562 947 8755",
    "sg:postcode":"90604",
    "sg:province":"CA",
    "wof:name":"College of Acupuncture and Oriental Medicine",
    "wof:placetype":"venue"
},
  "geometry": {"coordinates":[-117.986,33.924801],"type":"Point"}
}