{
  "type": "Feature",
  "properties": {
    "iso:country":"US",
    "sg:address":"8218 W 3rd St",
    "sg:city":"Los Angeles",
    "sg:classifiers":[
        {
            "category":"Organizations",
            "subcategory":"Religious Organization",
            "type":"Services"
        }
    ],
    "sg:phone":"+1 323 653 9342",
    "sg:postcode":"90048",
    "sg:province":"CA",
    "sg:tags":[
        "church"
    ],
    "wof:name":"Shambala Meditation Ctr",
    "wof:placetype":"venue"
},
  "geometry": {"coordinates":[-118.368423,34.072383],"type":"Point"}
}