{
  "type": "Feature",
  "properties": {
    "iso:country":"US",
    "sg:address":"2525 Lincoln Blvd",
    "sg:city":"Venice",
    "sg:classifiers":[
        {
            "category":"Home & Garden",
            "subcategory":"Carpets & Floor Coverings",
            "type":"Retail Goods"
        }
    ],
    "sg:phone":"+1 310 306 0241",
    "sg:postcode":"90291",
    "sg:province":"CA",
    "sg:tags":[
        "dealer",
        "rug"
    ],
    "wof:name":"BIX Industries",
    "wof:placetype":"venue"
},
  "geometry": {"coordinates":[-118.449344,33.992141],"type":"Point"}
}