{
  "type": "Feature",
  "properties": {
    "iso:country":"US",
    "sg:address":"348 Quaking Aspen Ln",
    "sg:city":"Stateline",
    "sg:classifiers":[
        {
            "category":"Real Estate",
            "subcategory":"Real Estate Operator",
            "type":"Services"
        }
    ],
    "sg:phone":"+1 775 588 5014",
    "sg:postcode":"89449",
    "sg:province":"CA",
    "sg:tags":[
        "condominium"
    ],
    "wof:name":"Tahoe Village Owners",
    "wof:placetype":"venue"
},
  "geometry": {"coordinates":[-119.88507199999999,38.963761],"type":"Point"}
}