{
  "type": "Feature",
  "properties": {
    "addr:full":"2036 S Atlantic Blvd Monterey Park CA 91754",
    "addr:housenumber":"2036",
    "addr:postcode":"91754",
    "addr:street":"S Atlantic Blvd",
    "iso:country":"US",
    "sg:address":"2036 S Atlantic Blvd",
    "sg:city":"Monterey Park",
    "sg:classifiers":[
        {
            "category":"Shopping",
            "subcategory":"Mobile Phones",
            "type":"Retail Goods"
        }
    ],
    "sg:phone":"+1 323 724 4769",
    "sg:postcode":"91754",
    "sg:province":"CA",
    "sg:website":"www.radioshack.com",
    "wof:name":"Radioshack",
    "wof:placetype":"venue"
},
  "geometry": {"coordinates":[-118.14299800000001,34.039902],"type":"Point"}
}