{
  "type": "Feature",
  "properties": {
    "addr:full":"1846 Logan Ave San Diego CA 92113",
    "addr:housenumber":"1846",
    "addr:postcode":"92113",
    "addr:street":"Logan Ave",
    "iso:country":"US",
    "sg:address":"1846 Logan Ave",
    "sg:city":"San Diego",
    "sg:classifiers":[
        {
            "category":"Place Of Worship",
            "subcategory":"Church",
            "type":"Public Place"
        }
    ],
    "sg:phone":"+1 619 239 3012",
    "sg:postcode":"92113",
    "sg:province":"CA",
    "wof:name":"Ministerio de Oracion 24 Hrs",
    "wof:placetype":"venue"
},
  "geometry": {"coordinates":[-117.145053,32.702331],"type":"Point"}
}