{
  "type": "Feature",
  "properties": {
    "iso:country":"US",
    "sg:address":"2917 W Olive Ave",
    "sg:city":"Burbank",
    "sg:classifiers":[
        {
            "category":"Communications",
            "subcategory":"Film & Video Production",
            "type":"Services"
        }
    ],
    "sg:phone":"+1 818 845 9200",
    "sg:postcode":"91505",
    "sg:province":"CA",
    "sg:tags":[
        "video/film",
        "taping"
    ],
    "sg:website":"www.filmlook.com",
    "wof:name":"Filmlook Inc",
    "wof:placetype":"venue"
},
  "geometry": {"coordinates":[-118.333,34.157501],"type":"Point"}
}