{
  "type": "Feature",
  "properties": {
    "iso:country":"US",
    "sg:address":"1881 E 4th St",
    "sg:city":"Ontario",
    "sg:classifiers":[
        {
            "category":"Autos & Motor Vehicles",
            "subcategory":"Auto Supplies",
            "type":"Retail Goods"
        }
    ],
    "sg:phone":"+1 909 391 0485",
    "sg:postcode":"91764",
    "sg:province":"CA",
    "sg:tags":[
        "automobile",
        "parts"
    ],
    "sg:website":"www.autozone.com",
    "wof:name":"Autozone",
    "wof:placetype":"venue"
},
  "geometry": {"coordinates":[-117.61209599999999,34.077518],"type":"Point"}
}