{
  "type": "Feature",
  "properties": {
    "iso:country":"US",
    "sg:address":"9545 Kearny Villa Rd",
    "sg:city":"San Diego",
    "sg:classifiers":[
        {
            "category":"Retail",
            "subcategory":"Auto Repair",
            "type":"Services"
        }
    ],
    "sg:phone":"+1 858 271 4292",
    "sg:postcode":"92126",
    "sg:province":"CA",
    "sg:tags":[
        "repairing",
        "automobile"
    ],
    "wof:name":"Mc Henry's Auto Repair",
    "wof:placetype":"venue"
},
  "geometry": {"coordinates":[-117.12014499999999,32.895957],"type":"Point"}
}