{
  "type": "Feature",
  "properties": {
    "addr:full":"1555 S 7th St Ste A San Jose CA 95112",
    "addr:housenumber":"1555",
    "addr:postcode":"95112",
    "addr:street":"S 7Th St Ste A",
    "iso:country":"US",
    "sg:address":"1555 S 7th St Ste A",
    "sg:city":"San Jose",
    "sg:classifiers":[
        {
            "category":"Personal",
            "type":"Services"
        }
    ],
    "sg:phone":"+1 877 901 0109",
    "sg:postcode":"95112",
    "sg:province":"CA",
    "sg:tags":[
        "mover"
    ],
    "sg:website":"www.bartelsmoving.com",
    "wof:name":"Bartels Moving Systems Inc",
    "wof:placetype":"venue"
},
  "geometry": {"coordinates":[-121.86687999999999,37.315932],"type":"Point"}
}