{
  "type": "Feature",
  "properties": {
    "iso:country":"US",
    "sg:address":"439 N Main St",
    "sg:city":"Manteca",
    "sg:classifiers":[
        {
            "category":"Restaurant",
            "type":"Food & Drink"
        }
    ],
    "sg:phone":"+1 209 823 8660",
    "sg:postcode":"95336",
    "sg:province":"CA",
    "wof:name":"Ploy Thai Cuisine",
    "wof:placetype":"venue"
},
  "geometry": {"coordinates":[-121.216849,37.803607],"type":"Point"}
}