{
  "type": "Feature",
  "properties": {
    "iso:country":"US",
    "sg:address":"814 N Vermont Ave",
    "sg:city":"Los Angeles",
    "sg:classifiers":[
        {
            "category":"Restaurant",
            "type":"Food & Drink"
        }
    ],
    "sg:phone":"+1 323 667 2723",
    "sg:postcode":"90029",
    "sg:province":"CA",
    "sg:tags":[
        "pizza"
    ],
    "sg:website":"www.vitopizza.com",
    "wof:name":"Vito's Pizza",
    "wof:placetype":"venue"
},
  "geometry": {"coordinates":[-118.292,34.086498],"type":"Point"}
}