{
  "type": "Feature",
  "properties": {
    "iso:country":"US",
    "sg:address":"3760 4th Ave",
    "sg:city":"San Diego",
    "sg:classifiers":[
        {
            "category":"Professional",
            "subcategory":"Management & Consulting",
            "type":"Services"
        }
    ],
    "sg:phone":"+1 619 542 1802",
    "sg:postcode":"92103",
    "sg:province":"CA",
    "sg:tags":[
        "fire",
        "consultant",
        "protection"
    ],
    "wof:name":"Protection Design & Consulting",
    "wof:placetype":"venue"
},
  "geometry": {"coordinates":[-117.16166,32.745834],"type":"Point"}
}