{
  "type": "Feature",
  "properties": {
    "addr:full":"1600 Las Virgenes Cyn Rd Calabasas CA 91302",
    "addr:housenumber":"1600",
    "addr:postcode":"91302",
    "addr:street":"Las Virgenes Cyn Rd",
    "iso:country":"US",
    "sg:address":"1600 Las Virgenes Cyn Rd",
    "sg:city":"Calabasas",
    "sg:classifiers":[
        {
            "category":"Place Of Worship",
            "subcategory":"Church",
            "type":"Public Place"
        },
        {
            "category":"Place Of Worship",
            "subcategory":"Temple",
            "type":"Public Place"
        }
    ],
    "sg:phone":"+1 818 880 5552",
    "sg:postcode":"91302",
    "sg:province":"CA",
    "sg:tags":[
        "hindu"
    ],
    "wof:name":"Hindu Temple Society of So Calif",
    "wof:placetype":"venue"
},
  "geometry": {"coordinates":[-118.70700100000001,34.090599],"type":"Point"}
}