{
  "type": "Feature",
  "properties": {
    "iso:country":"US",
    "sg:address":"7716 Melrose Ave",
    "sg:city":"Los Angeles",
    "sg:classifiers":[
        {
            "category":"Shopping",
            "type":"Retail Goods"
        }
    ],
    "sg:phone":"+1 323 653 7716",
    "sg:postcode":"90046",
    "sg:province":"CA",
    "sg:website":"mycloset.it/",
    "wof:name":"MyCloset Italia",
    "wof:placetype":"venue"
},
  "geometry": {"coordinates":[-118.389645,34.080722],"type":"Point"}
}