{
  "type": "Feature",
  "properties": {
    "addr:full":"1327 Spruce Tree Dr Diamond Bar CA 91765",
    "addr:housenumber":"1327",
    "addr:postcode":"91765",
    "addr:street":"Spruce Tree Dr",
    "iso:country":"US",
    "sg:address":"1327 Spruce Tree Dr",
    "sg:city":"Diamond Bar",
    "sg:classifiers":[
        {
            "category":"Professional",
            "subcategory":"Engineering",
            "type":"Services"
        }
    ],
    "sg:phone":"+1 909 396 4525",
    "sg:postcode":"91765",
    "sg:province":"CA",
    "sg:tags":[
        "engineer"
    ],
    "wof:name":"Spectrum Inspection Engrng",
    "wof:placetype":"venue"
},
  "geometry": {"coordinates":[-117.81729300000001,33.996952],"type":"Point"}
}