{
  "type": "Feature",
  "properties": {
    "iso:country":"US",
    "sg:address":"8237 Blackburn Ave",
    "sg:city":"Los Angeles",
    "sg:classifiers":[
        {
            "category":"Manufacturing",
            "subcategory":"Jewelry",
            "type":"Manufacturing & Wholesale Goods"
        }
    ],
    "sg:phone":"+1 323 782 9035",
    "sg:postcode":"90048",
    "sg:province":"CA",
    "sg:tags":[
        "design",
        "mfg"
    ],
    "wof:name":"Designs By Marissa",
    "wof:placetype":"venue"
},
  "geometry": {"coordinates":[-118.36943599999999,34.071713],"type":"Point"}
}