{
  "type": "Feature",
  "properties": {
    "addr:full":"2597 Cll Adra Duarte CA 91010",
    "addr:housenumber":"2597",
    "addr:postcode":"91010",
    "addr:street":"Cll Adra",
    "iso:country":"US",
    "sg:address":"2597 Cll Adra",
    "sg:city":"Duarte",
    "sg:classifiers":[
        {
            "category":"Home & Garden",
            "subcategory":"Home Furnishings",
            "type":"Retail Goods"
        }
    ],
    "sg:phone":"+1 626 797 1487",
    "sg:postcode":"91010",
    "sg:province":"CA",
    "sg:tags":[
        "venetian",
        "blind"
    ],
    "wof:name":"Westcoast Blinds",
    "wof:placetype":"venue"
},
  "geometry": {"coordinates":[-117.948691,34.140648],"type":"Point"}
}