{
  "type": "Feature",
  "properties": {
    "iso:country":"US",
    "sg:address":"2850 Gateway Oaks Dr # 300",
    "sg:city":"Sacramento",
    "sg:classifiers":[
        {
            "category":"Government",
            "subcategory":"Court House",
            "type":"Public Place"
        }
    ],
    "sg:phone":"+1 916 263 1399",
    "sg:postcode":"95833",
    "sg:province":"CA",
    "sg:tags":[
        "justice"
    ],
    "sg:website":"http://www.youthcourt.org",
    "wof:name":"The Judicial Council Of California",
    "wof:placetype":"venue"
},
  "geometry": {"coordinates":[-121.519564,38.620383],"type":"Point"}
}