{
  "type": "Feature",
  "properties": {
    "addr:full":"110 Cassia Dr Walnut Creek CA 94544",
    "addr:housenumber":"110",
    "addr:postcode":"94544",
    "addr:street":"Cassia Dr",
    "iso:country":"US",
    "sg:address":"110 Cassia Dr",
    "sg:city":"Walnut Creek",
    "sg:classifiers":[
        {
            "category":"Health Services",
            "subcategory":"Chiropractor",
            "type":"Services"
        }
    ],
    "sg:phone":"+1 925 935 2070",
    "sg:postcode":"94544",
    "sg:province":"CA",
    "wof:name":"Arrhythmia Specialists Inc",
    "wof:placetype":"venue"
},
  "geometry": {"coordinates":[-122.066176,37.637727],"type":"Point"}
}