{
  "type": "Feature",
  "properties": {
    "iso:country":"US",
    "sg:address":"10410 Mission Gorge Rd",
    "sg:city":"Santee",
    "sg:phone":"+1 619 449 5740",
    "sg:postcode":"92071",
    "sg:province":"CA",
    "wof:name":"Sparkys Transmission",
    "wof:placetype":"venue"
},
  "geometry": {"coordinates":[-116.97057599999999,32.838421],"type":"Point"}
}