{
  "type": "Feature",
  "properties": {
    "iso:country":"US",
    "sg:address":"1520 20th St",
    "sg:city":"Bakersfield",
    "sg:classifiers":[
        {
            "category":"Professional",
            "type":"Services"
        }
    ],
    "sg:phone":"+1 661 325 0639",
    "sg:postcode":"93301",
    "sg:province":"CA",
    "sg:tags":[
        "establishment"
    ],
    "wof:name":"At&T Cits",
    "wof:placetype":"venue"
},
  "geometry": {"coordinates":[-119.01981499999999,35.377242],"type":"Point"}
}