{
  "type": "Feature",
  "properties": {
    "iso:country":"US",
    "sg:address":"1841 S Ninth St",
    "sg:city":"Anaheim",
    "sg:classifiers":[
        {
            "category":"Education",
            "subcategory":"School",
            "type":"Public Place"
        }
    ],
    "sg:phone":"+1 714 517 8959",
    "sg:postcode":"92802",
    "sg:province":"CA",
    "sg:tags":[
        "high",
        "middle",
        "elementary"
    ],
    "wof:name":"Stoddard Alexander J Elementary School",
    "wof:placetype":"venue"
},
  "geometry": {"coordinates":[-117.932999,33.802399],"type":"Point"}
}