{
  "type": "Feature",
  "properties": {
    "addr:full":"6301 De Soto Ave Woodland Hills CA 91367",
    "addr:housenumber":"6301",
    "addr:postcode":"91367",
    "addr:street":"De Soto Ave",
    "iso:country":"US",
    "sg:address":"6301 De Soto Ave",
    "sg:city":"Woodland Hills",
    "sg:classifiers":[
        {
            "category":"Personal",
            "subcategory":"Hair Removal",
            "type":"Services"
        }
    ],
    "sg:phone":"+1 818 884 0369",
    "sg:postcode":"91367",
    "sg:province":"CA",
    "wof:name":"Electrolysis by Gigi",
    "wof:placetype":"venue"
},
  "geometry": {"coordinates":[-118.58899700000001,34.184799],"type":"Point"}
}