{
  "type": "Feature",
  "properties": {
    "addr:full":"2141 Macarthur Blvd Oakland CA 94602",
    "addr:housenumber":"2141",
    "addr:postcode":"94602",
    "addr:street":"Macarthur Blvd",
    "iso:country":"US",
    "sg:address":"2141 Macarthur Blvd",
    "sg:city":"Oakland",
    "sg:classifiers":[
        {
            "category":"Restaurant",
            "type":"Food & Drink"
        }
    ],
    "sg:phone":"+1 510 482 1080",
    "sg:postcode":"94602",
    "sg:province":"CA",
    "wof:name":"Dimond Park Grill",
    "wof:placetype":"venue"
},
  "geometry": {"coordinates":[-122.216696,37.800398],"type":"Point"}
}