{
  "type": "Feature",
  "properties": {
    "addr:full":"179 S Madera Ave Kerman CA 93630",
    "addr:housenumber":"179",
    "addr:postcode":"93630",
    "addr:street":"S Madera Ave",
    "iso:country":"US",
    "sg:address":"179 S Madera Ave",
    "sg:city":"Kerman",
    "sg:classifiers":[
        {
            "category":"Professional",
            "subcategory":"Testing Lab",
            "type":"Services"
        },
        {
            "category":"Health Services",
            "subcategory":"Medical Lab",
            "type":"Services"
        }
    ],
    "sg:phone":"+1 559 846 7353",
    "sg:postcode":"93630",
    "sg:province":"CA",
    "sg:tags":[
        "analytical",
        "laboratory"
    ],
    "wof:name":"Unilab",
    "wof:placetype":"venue"
},
  "geometry": {"coordinates":[-120.06021200000001,36.73327],"type":"Point"}
}