{
  "type": "Feature",
  "properties": {
    "iso:country":"US",
    "sg:address":"312 S California Ave",
    "sg:city":"West Covina",
    "sg:classifiers":[
        {
            "category":"Shopping",
            "subcategory":"Department Store",
            "type":"Retail Goods"
        }
    ],
    "sg:phone":"+1 626 480 0231",
    "sg:postcode":"91790",
    "sg:province":"CA",
    "sg:tags":[
        "shop"
    ],
    "wof:name":"Q Bargain",
    "wof:placetype":"venue"
},
  "geometry": {"coordinates":[-117.930255,34.068762],"type":"Point"}
}