{
  "type": "Feature",
  "properties": {
    "addr:full":"1617 Shay Rd Big Bear City CA 92314",
    "addr:housenumber":"1617",
    "addr:postcode":"92314",
    "addr:street":"Shay Rd",
    "iso:country":"US",
    "sg:address":"1617 Shay Rd",
    "sg:city":"Big Bear City",
    "sg:classifiers":[
        {
            "category":"Manufacturing",
            "subcategory":"Electronics",
            "type":"Manufacturing & Wholesale Goods"
        }
    ],
    "sg:phone":"+1 909 585 0230",
    "sg:postcode":"92314",
    "sg:province":"CA",
    "sg:tags":[
        "devices",
        "mfg"
    ],
    "wof:name":"Corp Excess Reclamation Svc",
    "wof:placetype":"venue"
},
  "geometry": {"coordinates":[-116.80807799999999,34.263649],"type":"Point"}
}