{
  "type": "Feature",
  "properties": {
    "addr:full":"2502 Clay Street San Francisco CA 94115",
    "addr:housenumber":"2502",
    "addr:postcode":"94115",
    "addr:street":"Clay Street",
    "iso:country":"US",
    "sg:address":"2502 Clay Street",
    "sg:city":"San Francisco",
    "sg:classifiers":[
        {
            "category":"Retail",
            "subcategory":"Laundry & Dry Cleaning",
            "type":"Services"
        }
    ],
    "sg:phone":"+1 415 673 7525",
    "sg:postcode":"94115",
    "sg:province":"CA",
    "wof:name":"Italy Cleaners",
    "wof:placetype":"venue"
},
  "geometry": {"coordinates":[-122.434472,37.790795],"type":"Point"}
}