{
  "type": "Feature",
  "properties": {
    "iso:country":"US",
    "sg:address":"3751 Merced Dr",
    "sg:city":"Riverside",
    "sg:classifiers":[
        {
            "category":"Utilities",
            "subcategory":"Telephone",
            "type":"Services"
        }
    ],
    "sg:phone":"+1 951 687 6100",
    "sg:postcode":"92503",
    "sg:province":"CA",
    "sg:tags":[
        "distance",
        "local",
        "telecommunication",
        "long"
    ],
    "wof:name":"Competitive Companies Inc",
    "wof:placetype":"venue"
},
  "geometry": {"coordinates":[-117.489211,33.89518],"type":"Point"}
}