{
  "type": "Feature",
  "properties": {
    "addr:full":"367 S Sierra Way San Bernardino CA 92408",
    "addr:housenumber":"367",
    "addr:postcode":"92408",
    "addr:street":"S Sierra Way",
    "iso:country":"US",
    "sg:address":"367 S Sierra Way",
    "sg:city":"San Bernardino",
    "sg:classifiers":[
        {
            "category":"Home & Garden",
            "subcategory":"Building Materials",
            "type":"Retail Goods"
        }
    ],
    "sg:phone":"+1 909 885 0067",
    "sg:postcode":"92408",
    "sg:province":"CA",
    "sg:tags":[
        "paint"
    ],
    "wof:name":"Smitty's Auto Paints",
    "wof:placetype":"venue"
},
  "geometry": {"coordinates":[-117.28508100000001,34.092688],"type":"Point"}
}