{
  "type": "Feature",
  "properties": {
    "addr:full":"17420 Kenton Ln Cottonwood CA 96022",
    "addr:housenumber":"17420",
    "addr:postcode":"96022",
    "addr:street":"Kenton Ln",
    "iso:country":"US",
    "sg:address":"17420 Kenton Ln",
    "sg:city":"Cottonwood",
    "sg:classifiers":[
        {
            "category":"Building & Trades",
            "subcategory":"Landscaping Services",
            "type":"Services"
        }
    ],
    "sg:phone":"+1 530 347 6011",
    "sg:postcode":"96022",
    "sg:province":"CA",
    "sg:tags":[
        "landscape"
    ],
    "wof:name":"Vic Hannan Landscape Materials",
    "wof:placetype":"venue"
},
  "geometry": {"coordinates":[-122.41064900000001,40.40261],"type":"Point"}
}