{
  "type": "Feature",
  "properties": {
    "addr:full":"2221 S Sepulveda Blvd Los Angeles CA 90064",
    "addr:housenumber":"2221",
    "addr:postcode":"90064",
    "addr:street":"S Sepulveda Blvd",
    "iso:country":"US",
    "sg:address":"2221 S Sepulveda Blvd",
    "sg:city":"Los Angeles",
    "sg:classifiers":[
        {
            "category":"Home & Garden",
            "subcategory":"Furniture",
            "type":"Retail Goods"
        }
    ],
    "sg:phone":"+1 310 473 9322",
    "sg:postcode":"90064",
    "sg:province":"CA",
    "sg:tags":[
        "store"
    ],
    "sg:website":"www.atmosphereinteriors.com",
    "wof:name":"Atmosphere Interiors",
    "wof:placetype":"venue"
},
  "geometry": {"coordinates":[-118.437434,34.039062],"type":"Point"}
}