{
  "type": "Feature",
  "properties": {
    "iso:country":"US",
    "sg:address":"244 W Hobsonway",
    "sg:city":"Blythe",
    "sg:classifiers":[
        {
            "category":"Organizations",
            "subcategory":"Professional Association",
            "type":"Services"
        }
    ],
    "sg:phone":"+1 760 922 2795",
    "sg:postcode":"92225",
    "sg:province":"CA",
    "wof:name":"Elks Lodge",
    "wof:placetype":"venue"
},
  "geometry": {"coordinates":[-114.598764,33.610249],"type":"Point"}
}