{
  "type": "Feature",
  "properties": {
    "addr:full":"1511 W Holt Blvd Ontario CA 91762",
    "addr:housenumber":"1511",
    "addr:postcode":"91762",
    "addr:street":"W Holt Blvd",
    "iso:country":"US",
    "sg:address":"1511 W Holt Blvd",
    "sg:city":"Ontario",
    "sg:classifiers":[
        {
            "category":"Banks & Credit Unions",
            "subcategory":"Bank",
            "type":"Services"
        }
    ],
    "sg:phone":"+1 909 986 1644",
    "sg:postcode":"91762",
    "sg:province":"CA",
    "sg:tags":[
        "loan",
        "real estate"
    ],
    "wof:name":"New Century Mortgage",
    "wof:placetype":"venue"
},
  "geometry": {"coordinates":[-117.67868,34.063218],"type":"Point"}
}