{
  "type": "Feature",
  "properties": {
    "iso:country":"US",
    "sg:address":"814 Darling Way",
    "sg:city":"Roseville",
    "sg:classifiers":[
        {
            "category":"Education",
            "subcategory":"School",
            "type":"Public Place"
        }
    ],
    "sg:phone":"+1 916 783 5274",
    "sg:postcode":"95678",
    "sg:province":"CA",
    "wof:name":"Cirby Elementary School",
    "wof:placetype":"venue"
},
  "geometry": {"coordinates":[-121.280243,38.73656],"type":"Point"}
}