{
  "type": "Feature",
  "properties": {
    "addr:full":"481 N Fresno St Fresno CA 93701",
    "addr:housenumber":"481",
    "addr:postcode":"93701",
    "addr:street":"N Fresno",
    "iso:country":"US",
    "sg:address":"481 N Fresno St",
    "sg:city":"Fresno",
    "sg:classifiers":[
        {
            "category":"Bars & Pubs",
            "type":"Food & Drink"
        }
    ],
    "sg:phone":"+1 559 442 4834",
    "sg:postcode":"93701",
    "sg:province":"CA",
    "sg:tags":[
        "lounge",
        "cocktail"
    ],
    "wof:name":"Molino Rojo",
    "wof:placetype":"venue"
},
  "geometry": {"coordinates":[-119.781566,36.749896],"type":"Point"}
}