{
  "type": "Feature",
  "properties": {
    "iso:country":"US",
    "sg:address":"857 Collier Dr",
    "sg:city":"San Leandro",
    "sg:classifiers":[
        {
            "category":"Freight",
            "type":"Transportation"
        }
    ],
    "sg:phone":"+1 510 614 0468",
    "sg:postcode":"94577",
    "sg:province":"CA",
    "sg:tags":[
        "operator",
        "local",
        "trucking"
    ],
    "wof:name":"Mylenes Courier Service",
    "wof:placetype":"venue"
},
  "geometry": {"coordinates":[-122.14315499999999,37.729893],"type":"Point"}
}