{
  "type": "Feature",
  "properties": {
    "addr:full":"118 E Main St El Cajon CA 92020",
    "addr:housenumber":"118",
    "addr:postcode":"92020",
    "addr:street":"E Main St",
    "iso:country":"US",
    "sg:address":"118 E Main St",
    "sg:city":"El Cajon",
    "sg:classifiers":[
        {
            "category":"Manufacturing",
            "subcategory":"Jewelry",
            "type":"Manufacturing & Wholesale Goods"
        },
        {
            "category":"Wholesale",
            "subcategory":"Jewelry",
            "type":"Manufacturing & Wholesale Goods"
        }
    ],
    "sg:phone":"+1 619 444 6307",
    "sg:postcode":"92020",
    "sg:province":"CA",
    "sg:tags":[
        "supply",
        "stone",
        "mfg",
        "material",
        "jeweler",
        "re"
    ],
    "wof:name":"K's Tumblecraft",
    "wof:placetype":"venue"
},
  "geometry": {"coordinates":[-116.961178,32.795003],"type":"Point"}
}