{
  "type": "Feature",
  "properties": {
    "addr:full":"1031 E Watson Center Rd Carson CA 90745",
    "addr:housenumber":"1031",
    "addr:postcode":"90745",
    "addr:street":"E Watson Center Rd",
    "iso:country":"US",
    "sg:address":"1031 E Watson Center Rd",
    "sg:city":"Carson",
    "sg:classifiers":[
        {
            "category":"Freight",
            "type":"Transportation"
        }
    ],
    "sg:phone":"+1 310 522 9818",
    "sg:postcode":"90745",
    "sg:province":"CA",
    "sg:tags":[
        "forwarder"
    ],
    "wof:name":"Gs 21",
    "wof:placetype":"venue"
},
  "geometry": {"coordinates":[-118.257672,33.820189],"type":"Point"}
}