{
  "type": "Feature",
  "properties": {
    "iso:country":"US",
    "sg:address":"2465 E Palm Canyon Dr Ste 515",
    "sg:city":"Palm Springs",
    "sg:classifiers":[
        {
            "category":"Sports & Exercise",
            "subcategory":"Gym",
            "type":"Entertainment"
        }
    ],
    "sg:phone":"+1 760 320 9783",
    "sg:postcode":"92264",
    "sg:province":"CA",
    "wof:name":"Something Personal Health & Fitness Adventures",
    "wof:placetype":"venue"
},
  "geometry": {"coordinates":[-116.51969699999999,33.800885],"type":"Point"}
}