{
  "type": "Feature",
  "properties": {
    "iso:country":"US",
    "sg:address":"79375 US Hwy 111",
    "sg:city":"La Quinta",
    "sg:classifiers":[
        {
            "category":"Shopping",
            "type":"Retail Goods"
        }
    ],
    "sg:phone":"+1 760 771 4058",
    "sg:postcode":"92253",
    "sg:province":"CA",
    "sg:tags":[
        "pet",
        "shop"
    ],
    "wof:name":"Petsmart",
    "wof:placetype":"venue"
},
  "geometry": {"coordinates":[-116.27775099999999,33.707295],"type":"Point"}
}