{
  "type": "Feature",
  "properties": {
    "addr:full":"1515 K St Ste 600 Sacramento CA 95814",
    "addr:housenumber":"1515",
    "addr:postcode":"95814",
    "addr:street":"K St Ste 600",
    "iso:country":"US",
    "sg:address":"1515 K St Ste 600",
    "sg:city":"Sacramento",
    "sg:phone":"+1 916 445 4071",
    "sg:postcode":"95814",
    "sg:province":"CA",
    "wof:name":"Board Of Prison Terms",
    "wof:placetype":"venue"
},
  "geometry": {"coordinates":[-121.486862,38.577318],"type":"Point"}
}