{
  "type": "Feature",
  "properties": {
    "addr:full":"1819 Cooper St Selma CA 93662",
    "addr:housenumber":"1819",
    "addr:postcode":"93662",
    "addr:street":"Cooper St",
    "iso:country":"US",
    "sg:address":"1819 Cooper St",
    "sg:city":"Selma",
    "sg:classifiers":[
        {
            "category":"Building & Trades",
            "subcategory":"Construction",
            "type":"Services"
        }
    ],
    "sg:phone":"+1 559 647 2261",
    "sg:postcode":"93662",
    "sg:province":"CA",
    "sg:tags":[
        "welder"
    ],
    "wof:name":"M H Mobile Welding",
    "wof:placetype":"venue"
},
  "geometry": {"coordinates":[-119.608689,36.580872],"type":"Point"}
}