{
  "type": "Feature",
  "properties": {
    "iso:country":"US",
    "sg:address":"15827 Hawthorne Blvd",
    "sg:city":"Lawndale",
    "sg:classifiers":[
        {
            "category":"Sports & Exercise",
            "subcategory":"Race Track",
            "type":"Entertainment"
        }
    ],
    "sg:phone":"+1 323 772 3605",
    "sg:postcode":"90260",
    "sg:province":"CA",
    "wof:name":"Neely Motorsports",
    "wof:placetype":"venue"
},
  "geometry": {"coordinates":[-118.352442,33.886667],"type":"Point"}
}