{
  "type": "Feature",
  "properties": {
    "iso:country":"US",
    "sg:address":"765 Market St",
    "sg:city":"San Francisco",
    "sg:classifiers":[
        {
            "category":"Professional",
            "subcategory":"Management & Consulting",
            "type":"Services"
        }
    ],
    "sg:phone":"+1 415 344 0544",
    "sg:postcode":"94103",
    "sg:province":"CA",
    "sg:tags":[
        "town",
        "city",
        "regional",
        "planner"
    ],
    "wof:name":"Sedway Consulting",
    "wof:placetype":"venue"
},
  "geometry": {"coordinates":[-122.405429,37.785957],"type":"Point"}
}