{
  "type": "Feature",
  "properties": {
    "addr:full":"436 14th St Oakland CA 94612",
    "addr:housenumber":"436",
    "addr:postcode":"94612",
    "addr:street":"14Th St",
    "iso:country":"US",
    "sg:address":"436 14th St",
    "sg:city":"Oakland",
    "sg:classifiers":[
        {
            "category":"Retail",
            "subcategory":"Laundry & Dry Cleaning",
            "type":"Services"
        }
    ],
    "sg:phone":"+1 510 496 0070",
    "sg:postcode":"94612",
    "sg:province":"CA",
    "sg:tags":[
        "cleaner"
    ],
    "wof:name":"Crime Scene Cleaners",
    "wof:placetype":"venue"
},
  "geometry": {"coordinates":[-122.27070000000001,37.804275],"type":"Point"}
}