{
  "type": "Feature",
  "properties": {
    "iso:country":"US",
    "sg:address":"3809 Rock Hampton Dr",
    "sg:city":"Tarzana",
    "sg:classifiers":[
        {
            "category":"Health Services",
            "subcategory":"Clinic",
            "type":"Services"
        },
        {
            "category":"Community Center",
            "type":"Public Place"
        }
    ],
    "sg:phone":"+1 818 343 0299",
    "sg:postcode":"91356",
    "sg:province":"CA",
    "sg:tags":[
        "medical"
    ],
    "wof:name":"Howard S Finn Md Inc A Medical",
    "wof:placetype":"venue"
},
  "geometry": {"coordinates":[-118.533108,34.140276],"type":"Point"}
}