{
  "type": "Feature",
  "properties": {
    "addr:full":"9665 E Stockton Blvd Elk Grove CA 95624",
    "addr:housenumber":"9665",
    "addr:postcode":"95624",
    "addr:street":"E Stockton Blvd",
    "iso:country":"US",
    "sg:address":"9665 E Stockton Blvd",
    "sg:city":"Elk Grove",
    "sg:classifiers":[
        {
            "category":"Shopping",
            "subcategory":"Used Merchandise",
            "type":"Retail Goods"
        }
    ],
    "sg:phone":"+1 916 686 2747",
    "sg:postcode":"95624",
    "sg:province":"CA",
    "sg:tags":[
        "shop",
        "consignment"
    ],
    "sg:website":"www.featheryournest.com",
    "wof:name":"Feather Thy Nest",
    "wof:placetype":"venue"
},
  "geometry": {"coordinates":[-121.384657,38.408693],"type":"Point"}
}