{
  "type": "Feature",
  "properties": {
    "addr:full":"1437 W Arrow Hwy San Dimas CA 91773",
    "addr:housenumber":"1437",
    "addr:postcode":"91773",
    "addr:street":"W Arrow Hwy",
    "iso:country":"US",
    "sg:address":"1437 W Arrow Hwy",
    "sg:city":"San Dimas",
    "sg:classifiers":[
        {
            "category":"Professional",
            "type":"Services"
        }
    ],
    "sg:phone":"+1 909 305 6900",
    "sg:postcode":"91773",
    "sg:province":"CA",
    "wof:name":"ABC Smile Care Dental",
    "wof:placetype":"venue"
},
  "geometry": {"coordinates":[-117.836859,34.106679],"type":"Point"}
}