{
  "type": "Feature",
  "properties": {
    "addr:full":"35020 Cll Campo Temecula CA 92592",
    "addr:postcode":"35020;92592",
    "addr:street":"Cll Campo",
    "iso:country":"US",
    "sg:address":"35020 Cll Campo",
    "sg:city":"Temecula",
    "sg:classifiers":[
        {
            "category":"Farming",
            "subcategory":"Livestock Farm",
            "type":"Manufacturing & Wholesale Goods"
        }
    ],
    "sg:phone":"+1 951 699 6022",
    "sg:postcode":"92592",
    "sg:province":"CA",
    "sg:tags":[
        "equine"
    ],
    "wof:name":"Caboray Ranch",
    "wof:placetype":"venue"
},
  "geometry": {"coordinates":[-117.05042299999999,33.512831],"type":"Point"}
}