{
  "type": "Feature",
  "properties": {
    "iso:country":"US",
    "sg:address":"327 Industrial Dr",
    "sg:city":"Placerville",
    "sg:classifiers":[
        {
            "category":"Home & Garden",
            "subcategory":"Building Materials",
            "type":"Retail Goods"
        }
    ],
    "sg:phone":"+1 530 622 0116",
    "sg:postcode":"95667",
    "sg:province":"CA",
    "sg:tags":[
        "screen",
        "window"
    ],
    "wof:name":"Fancyline Screen Door Co",
    "wof:placetype":"venue"
},
  "geometry": {"coordinates":[-120.825112,38.698495],"type":"Point"}
}