{
  "type": "Feature",
  "properties": {
    "addr:full":"5001 Industrial Way Benicia CA 94510",
    "addr:housenumber":"5001",
    "addr:postcode":"94510",
    "addr:street":"Industrial Way",
    "iso:country":"US",
    "sg:address":"5001 Industrial Way",
    "sg:city":"Benicia",
    "sg:classifiers":[
        {
            "category":"Wholesale",
            "subcategory":"Machinery & Supplies",
            "type":"Manufacturing & Wholesale Goods"
        }
    ],
    "sg:phone":"+1 707 748 4800",
    "sg:postcode":"94510",
    "sg:province":"CA",
    "sg:tags":[
        "salon",
        "beauty"
    ],
    "sg:website":"www.westcoastbeauty.com",
    "wof:name":"West Coast Beauty Supply",
    "wof:placetype":"venue"
},
  "geometry": {"coordinates":[-122.11040300000001,38.082317],"type":"Point"}
}