{
  "type": "Feature",
  "properties": {
    "addr:full":"1814 W Foothill Blvd Upland CA 91786",
    "addr:housenumber":"1814",
    "addr:postcode":"91786",
    "addr:street":"W Foothill Blvd",
    "iso:country":"US",
    "sg:address":"1814 W Foothill Blvd",
    "sg:city":"Upland",
    "sg:classifiers":[
        {
            "category":"Bars & Pubs",
            "type":"Food & Drink"
        },
        {
            "category":"Travel",
            "subcategory":"Bed & Breakfast",
            "type":"Entertainment"
        }
    ],
    "sg:phone":"+1 909 981 5515",
    "sg:postcode":"91786",
    "sg:province":"CA",
    "sg:tags":[
        "brew",
        "inn"
    ],
    "wof:name":"Buffalo Inn",
    "wof:placetype":"venue"
},
  "geometry": {"coordinates":[-117.68709800000001,34.1068],"type":"Point"}
}