{
  "type": "Feature",
  "properties": {
    "addr:full":"6605 Hollywood Blvd Los Angeles CA 90028",
    "addr:housenumber":"6605",
    "addr:postcode":"90028",
    "addr:street":"Hollywood Blvd",
    "iso:country":"US",
    "sg:address":"6605 Hollywood Blvd",
    "sg:city":"Los Angeles",
    "sg:classifiers":[
        {
            "category":"Organizations",
            "subcategory":"Non-profit Organization",
            "type":"Services"
        },
        {
            "category":"Food & Beverages",
            "subcategory":"Groceries & Convenience Stores",
            "type":"Retail Goods"
        }
    ],
    "sg:phone":"+1 323 463 3171",
    "sg:postcode":"90028",
    "sg:province":"CA",
    "sg:tags":[
        "service/non-profit",
        "community"
    ],
    "sg:website":"www.hollywoodfarmersmarket.com",
    "wof:name":"Seela",
    "wof:placetype":"venue"
},
  "geometry": {"coordinates":[-118.333586,34.101707],"type":"Point"}
}