{
  "type": "Feature",
  "properties": {
    "iso:country":"US",
    "sg:address":"20865 Canada Rd",
    "sg:city":"El Toro",
    "sg:classifiers":[
        {
            "category":"Building & Trades",
            "subcategory":"Construction",
            "type":"Services"
        }
    ],
    "sg:phone":"+1 949 859 5731",
    "sg:postcode":"92630",
    "sg:province":"CA",
    "sg:tags":[
        "contractor"
    ],
    "wof:name":"Don Hess Construction",
    "wof:placetype":"venue"
},
  "geometry": {"coordinates":[-117.673504,33.65945],"type":"Point"}
}