{
  "type": "Feature",
  "properties": {
    "iso:country":"US",
    "sg:address":"2344 22nd Ave",
    "sg:city":"Sacramento",
    "sg:classifiers":[
        {
            "category":"Organizations",
            "subcategory":"Religious Organization",
            "type":"Services"
        }
    ],
    "sg:phone":"+1 916 457 1872",
    "sg:postcode":"95822",
    "sg:province":"CA",
    "sg:tags":[
        "church"
    ],
    "wof:name":"Latin American Church-Nazarene",
    "wof:placetype":"venue"
},
  "geometry": {"coordinates":[-121.483307,38.532775],"type":"Point"}
}