{
  "type": "Feature",
  "properties": {
    "addr:full":"321 Kansas Ave Modesto CA 95351",
    "addr:postcode":"ca 95351",
    "addr:street":"321 Kansas Ave",
    "iso:country":"US",
    "sg:address":"321 Kansas Ave",
    "sg:city":"Modesto",
    "sg:classifiers":[
        {
            "category":"Building & Trades",
            "subcategory":"Landscaping Services",
            "type":"Services"
        },
        {
            "category":"Home & Garden",
            "subcategory":"Garden Supply",
            "type":"Retail Goods"
        },
        {
            "category":"Wholesale",
            "subcategory":"Machinery & Supplies",
            "type":"Manufacturing & Wholesale Goods"
        },
        {
            "category":"Manufacturing",
            "subcategory":"Paper Products",
            "type":"Manufacturing & Wholesale Goods"
        }
    ],
    "sg:phone":"+1 209 544 9530",
    "sg:postcode":"95351",
    "sg:province":"CA",
    "sg:tags":[
        "lawn",
        "sprinklers-garden",
        "irrigation",
        "system",
        "equipment",
        "bamboo"
    ],
    "sg:website":"http://www.ewing1.com",
    "wof:name":"Ewing Irrigation-Golf-Indl",
    "wof:placetype":"venue"
},
  "geometry": {"coordinates":[-121.010544,37.645876],"type":"Point"}
}