{
  "type": "Feature",
  "properties": {
    "addr:full":"149 Los Vientos Dr Newbury Park CA 91320",
    "addr:housenumber":"149",
    "addr:postcode":"91320",
    "addr:street":"Los Vientos Dr",
    "iso:country":"US",
    "sg:address":"149 Los Vientos Dr",
    "sg:city":"Newbury Park",
    "sg:classifiers":[
        {
            "category":"Manufacturing",
            "subcategory":"Printing",
            "type":"Manufacturing & Wholesale Goods"
        }
    ],
    "sg:phone":"+1 805 498 7101",
    "sg:postcode":"91320",
    "sg:province":"CA",
    "sg:tags":[
        "publishing"
    ],
    "wof:name":"El Camino Publishing",
    "wof:placetype":"venue"
},
  "geometry": {"coordinates":[-118.960891,34.180079],"type":"Point"}
}