{
  "type": "Feature",
  "properties": {
    "iso:country":"US",
    "sg:address":"1835 Valota Rd",
    "sg:city":"Redwood City",
    "sg:classifiers":[
        {
            "category":"Social Services",
            "subcategory":"Child Care",
            "type":"Services"
        }
    ],
    "sg:phone":"+1 650 369 4151",
    "sg:postcode":"94061",
    "sg:province":"CA",
    "wof:name":"Playschool",
    "wof:placetype":"venue"
},
  "geometry": {"coordinates":[-122.226349,37.459771],"type":"Point"}
}