{
  "type": "Feature",
  "properties": {
    "addr:full":"5978 Quiet Slope Dr San Diego CA 92120",
    "addr:housenumber":"5978",
    "addr:postcode":"92120",
    "addr:street":"Quiet Slope Dr",
    "iso:country":"US",
    "sg:address":"5978 Quiet Slope Dr",
    "sg:city":"San Diego",
    "sg:classifiers":[
        {
            "category":"Building & Trades",
            "subcategory":"Construction",
            "type":"Services"
        }
    ],
    "sg:phone":"+1 619 287 2137",
    "sg:postcode":"92120",
    "sg:province":"CA",
    "sg:tags":[
        "heavy"
    ],
    "wof:name":"Ponds Waterfalls & Pond Filtrn",
    "wof:placetype":"venue"
},
  "geometry": {"coordinates":[-117.063789,32.802952],"type":"Point"}
}