{
  "type": "Feature",
  "properties": {
    "iso:country":"US",
    "sg:address":"3801 Mattei Rd",
    "sg:city":"Santa Ynez",
    "sg:classifiers":[
        {
            "category":"Building & Trades",
            "subcategory":"Construction",
            "type":"Services"
        }
    ],
    "sg:phone":"+1 805 688 8196",
    "sg:postcode":"93460",
    "sg:province":"CA",
    "sg:tags":[
        "plastering",
        "contractor"
    ],
    "wof:name":"Robert K Allton Plastering",
    "wof:placetype":"venue"
},
  "geometry": {"coordinates":[-120.075,34.647578],"type":"Point"}
}