{
  "type": "Feature",
  "properties": {
    "iso:country":"US",
    "sg:address":"2460 W Whittier Blvd",
    "sg:city":"Montebello",
    "sg:classifiers":[
        {
            "category":"Retail",
            "subcategory":"Repair Shop",
            "type":"Services"
        },
        {
            "category":"Professional",
            "subcategory":"Detective & Security Services",
            "type":"Services"
        }
    ],
    "sg:phone":"+1 626 280 4414",
    "sg:postcode":"90640",
    "sg:province":"CA",
    "sg:tags":[
        "skip",
        "tracing",
        "bail",
        "bond"
    ],
    "wof:name":"Community Bail Bonds",
    "wof:placetype":"venue"
},
  "geometry": {"coordinates":[-118.129196,34.014554],"type":"Point"}
}