{
  "type": "Feature",
  "properties": {
    "addr:full":"73 Brookwood Rd Orinda CA 94563",
    "addr:housenumber":"73",
    "addr:postcode":"94563",
    "addr:street":"Brookwood Rd",
    "iso:country":"US",
    "sg:address":"73 Brookwood Rd",
    "sg:city":"Orinda",
    "sg:classifiers":[
        {
            "category":"Wholesale",
            "subcategory":"Durable Goods & Equipment",
            "type":"Manufacturing & Wholesale Goods"
        }
    ],
    "sg:phone":"+1 925 253 0800",
    "sg:postcode":"94563",
    "sg:province":"CA",
    "sg:tags":[
        "importer"
    ],
    "wof:name":"Wilson Daniels",
    "wof:placetype":"venue"
},
  "geometry": {"coordinates":[-122.18509299999999,37.875514],"type":"Point"}
}