{
  "type": "Feature",
  "properties": {
    "iso:country":"US",
    "sg:address":"2570 Old 1st St",
    "sg:city":"Livermore",
    "sg:classifiers":[
        {
            "category":"Restaurant",
            "type":"Food & Drink"
        }
    ],
    "sg:phone":"+1 925 454 1244",
    "sg:postcode":"94551",
    "sg:province":"CA",
    "sg:tags":[
        "delicatessen"
    ],
    "wof:name":"Kelly's Deli & Catering",
    "wof:placetype":"venue"
},
  "geometry": {"coordinates":[-121.765558,37.684525],"type":"Point"}
}