{
  "type": "Feature",
  "properties": {
    "addr:full":"548 Union St San Francisco CA 94133",
    "addr:housenumber":"548",
    "addr:postcode":"94133",
    "addr:street":"Union St",
    "iso:country":"US",
    "sg:address":"548 Union St",
    "sg:city":"San Francisco",
    "sg:classifiers":[
        {
            "category":"Professional",
            "subcategory":"Computer Services",
            "type":"Services"
        }
    ],
    "sg:phone":"+1 415 393 9555",
    "sg:postcode":"94133",
    "sg:province":"CA",
    "sg:tags":[
        "website",
        "design"
    ],
    "wof:name":"Grafco",
    "wof:placetype":"venue"
},
  "geometry": {"coordinates":[-122.40800900000001,37.800587],"type":"Point"}
}