{
  "type": "Feature",
  "properties": {
    "addr:full":"7509 W. Sunset Blvd. Los Angeles CA 90046",
    "addr:housenumber":"7509",
    "addr:postcode":"90046",
    "addr:street":"W. Sunset Blvd.",
    "iso:country":"US",
    "sg:address":"7509 W. Sunset Blvd.",
    "sg:city":"Los Angeles",
    "sg:classifiers":[
        {
            "category":"Coffee & Tea",
            "type":"Food & Drink"
        },
        {
            "category":"Food & Beverages",
            "subcategory":"Bakery",
            "type":"Retail Goods"
        },
        {
            "category":"Bars & Pubs",
            "subcategory":"Nightclub",
            "type":"Food & Drink"
        }
    ],
    "sg:phone":"+1 323 963 5474",
    "sg:postcode":"90046",
    "sg:province":"CA",
    "sg:tags":[
        "sandwich",
        "nightlife"
    ],
    "sg:website":"www.thecoffeetbar.com",
    "wof:name":"The Coffee T Bar",
    "wof:placetype":"venue"
},
  "geometry": {"coordinates":[-118.353263,34.098343],"type":"Point"}
}