{
  "type": "Feature",
  "properties": {
    "iso:country":"US",
    "sg:address":"4900 Hopyard Rd",
    "sg:city":"Pleasanton",
    "sg:classifiers":[
        {
            "category":"Real Estate",
            "subcategory":"Real Estate Services",
            "type":"Services"
        }
    ],
    "sg:phone":"+1 925 460 0790",
    "sg:postcode":"94588",
    "sg:province":"CA",
    "sg:tags":[
        "company",
        "title"
    ],
    "wof:name":"First American Title Co",
    "wof:placetype":"venue"
},
  "geometry": {"coordinates":[-121.903582,37.694164],"type":"Point"}
}