{
  "type": "Feature",
  "properties": {
    "addr:full":"119 W Linden Ave Burbank CA 91502",
    "addr:housenumber":"119",
    "addr:postcode":"91502",
    "addr:street":"W Linden Ave",
    "iso:country":"US",
    "sg:address":"119 W Linden Ave",
    "sg:city":"Burbank",
    "sg:classifiers":[
        {
            "category":"Building & Trades",
            "subcategory":"Construction",
            "type":"Services"
        }
    ],
    "sg:phone":"+1 818 955 8152",
    "sg:postcode":"91502",
    "sg:province":"CA",
    "sg:tags":[
        "woodworker"
    ],
    "wof:name":"Johnson Rather Odd Custom Shop",
    "wof:placetype":"venue"
},
  "geometry": {"coordinates":[-118.30149299999999,34.168828],"type":"Point"}
}