{
  "type": "Feature",
  "properties": {
    "addr:full":"2855 Stevens Creek Blvd #1067 Santa Clara CA 95050",
    "addr:housenumber":"2855",
    "addr:postcode":"95050",
    "addr:street":"Stevens Creek Blvd # 1067",
    "iso:country":"US",
    "sg:address":"2855 Stevens Creek Blvd #1067",
    "sg:city":"Santa Clara",
    "sg:classifiers":[
        {
            "category":"Shopping",
            "subcategory":"Clothing, Apparel, & Fashions",
            "type":"Retail Goods"
        }
    ],
    "sg:phone":"+1 408 985 7172",
    "sg:postcode":"95050",
    "sg:province":"CA",
    "sg:tags":[
        "men's",
        "clothing",
        "women's"
    ],
    "sg:website":"www.guess.com",
    "wof:name":"Guess",
    "wof:placetype":"venue"
},
  "geometry": {"coordinates":[-121.947436,37.325371],"type":"Point"}
}