{
  "type": "Feature",
  "properties": {
    "iso:country":"US",
    "sg:address":"1142 W Collins Ave",
    "sg:city":"Orange",
    "sg:classifiers":[
        {
            "category":"Building & Trades",
            "subcategory":"Construction",
            "type":"Services"
        }
    ],
    "sg:phone":"+1 714 532 1639",
    "sg:postcode":"92867",
    "sg:province":"CA",
    "sg:tags":[
        "masonry",
        "contractor"
    ],
    "wof:name":"Jdj Construction Co",
    "wof:placetype":"venue"
},
  "geometry": {"coordinates":[-117.866434,33.802341],"type":"Point"}
}