{
  "type": "Feature",
  "properties": {
    "iso:country":"US",
    "sg:address":"225 N Chinowth St",
    "sg:city":"Visalia",
    "sg:classifiers":[
        {
            "category":"Health Services",
            "subcategory":"Doctor",
            "type":"Services"
        }
    ],
    "sg:phone":"+1 559 627 3222",
    "sg:postcode":"93291",
    "sg:province":"CA",
    "sg:tags":[
        "medical"
    ],
    "wof:name":"Valley Indus & Fmly Med Group",
    "wof:placetype":"venue"
},
  "geometry": {"coordinates":[-119.336291,36.331658],"type":"Point"}
}