{
  "type": "Feature",
  "properties": {
    "iso:country":"US",
    "sg:address":"1403 Pepper Dr",
    "sg:city":"El Cajon",
    "sg:classifiers":[
        {
            "category":"Shopping",
            "subcategory":"Gifts & Souvenirs",
            "type":"Retail Goods"
        }
    ],
    "sg:phone":"+1 619 442 9166",
    "sg:postcode":"92021",
    "sg:province":"CA",
    "sg:tags":[
        "party",
        "supply"
    ],
    "wof:name":"Jump For Joy",
    "wof:placetype":"venue"
},
  "geometry": {"coordinates":[-116.928706,32.820752],"type":"Point"}
}