{
  "type": "Feature",
  "properties": {
    "addr:full":"30451 Emperor Dr Sun City CA 92587",
    "addr:postcode":"30451;92587",
    "addr:street":"Emperor Dr",
    "iso:country":"US",
    "sg:address":"30451 Emperor Dr",
    "sg:city":"Sun City",
    "sg:classifiers":[
        {
            "category":"Banks & Credit Unions",
            "subcategory":"Bank",
            "type":"Services"
        }
    ],
    "sg:phone":"+1 951 244 8346",
    "sg:postcode":"92587",
    "sg:province":"CA",
    "sg:tags":[
        "broker",
        "mortgage"
    ],
    "wof:name":"S F C Financial",
    "wof:placetype":"venue"
},
  "geometry": {"coordinates":[-117.245891,33.678489],"type":"Point"}
}