{
  "type": "Feature",
  "properties": {
    "iso:country":"US",
    "sg:address":"1295 Santa Rita Rd",
    "sg:city":"Templeton",
    "sg:classifiers":[
        {
            "category":"Building & Trades",
            "subcategory":"Construction",
            "type":"Services"
        }
    ],
    "sg:phone":"+1 805 434 5171",
    "sg:postcode":"93465",
    "sg:province":"CA",
    "sg:tags":[
        "general",
        "contractor"
    ],
    "wof:name":"S C Custom Construction Inc",
    "wof:placetype":"venue"
},
  "geometry": {"coordinates":[-120.72695,35.539257],"type":"Point"}
}