{
  "type": "Feature",
  "properties": {
    "iso:country":"US",
    "sg:address":"100 Bush St",
    "sg:city":"San Francisco",
    "sg:classifiers":[
        {
            "category":"Professional",
            "subcategory":"Lawyer & Legal Services",
            "type":"Services"
        }
    ],
    "sg:phone":"+1 415 291 1997",
    "sg:postcode":"94104",
    "sg:province":"CA",
    "sg:tags":[
        "attorney"
    ],
    "wof:name":"Wiggins Robin & Richard",
    "wof:placetype":"venue"
},
  "geometry": {"coordinates":[-122.400744,37.791177],"type":"Point"}
}