{
  "type": "Feature",
  "properties": {
    "addr:full":"2980 College Avenue Suite 8 Berkeley CA 94705",
    "addr:housenumber":"2980",
    "addr:postcode":"94705",
    "addr:street":"College Avenue Suite 8",
    "iso:country":"US",
    "sg:address":"2980 College Avenue Suite 8",
    "sg:city":"Berkeley",
    "sg:classifiers":[
        {
            "category":"Banks & Credit Unions",
            "subcategory":"Bank",
            "type":"Services"
        }
    ],
    "sg:phone":"+1 510 548 2929",
    "sg:postcode":"94705",
    "sg:province":"CA",
    "wof:name":"State Farm Insurance Companies",
    "wof:placetype":"venue"
},
  "geometry": {"coordinates":[-122.25299800000001,37.856602],"type":"Point"}
}