{
  "type": "Feature",
  "properties": {
    "iso:country":"US",
    "sg:address":"512 Main St",
    "sg:city":"Diamond Springs",
    "sg:classifiers":[
        {
            "category":"Wholesale",
            "subcategory":"Jewelry",
            "type":"Manufacturing & Wholesale Goods"
        }
    ],
    "sg:phone":"+1 530 622 2339",
    "sg:postcode":"95694",
    "sg:province":"CA",
    "sg:tags":[
        "beads"
    ],
    "wof:name":"Basically Beads Craft Supply",
    "wof:placetype":"venue"
},
  "geometry": {"coordinates":[-121.98087200000001,38.519233],"type":"Point"}
}