{
  "type": "Feature",
  "properties": {
    "addr:full":"1340 E Colorado St Glendale CA 91205",
    "addr:housenumber":"1340",
    "addr:postcode":"91205",
    "addr:street":"E Colorado St",
    "iso:country":"US",
    "sg:address":"1340 E Colorado St",
    "sg:city":"Glendale",
    "sg:classifiers":[
        {
            "category":"Food & Beverages",
            "subcategory":"Groceries & Convenience Stores",
            "type":"Retail Goods"
        }
    ],
    "sg:phone":"+1 818 243 0918",
    "sg:postcode":"91205",
    "sg:province":"CA",
    "wof:name":"Ararat Daily Groceries",
    "wof:placetype":"venue"
},
  "geometry": {"coordinates":[-118.236,34.142601],"type":"Point"}
}