{
  "type": "Feature",
  "properties": {
    "iso:country":"US",
    "sg:address":"611 Brewington Ave",
    "sg:city":"Watsonville",
    "sg:classifiers":[
        {
            "category":"Communications",
            "subcategory":"Film & Video Production",
            "type":"Services"
        }
    ],
    "sg:phone":"+1 831 728 8949",
    "sg:postcode":"95076",
    "sg:province":"CA",
    "sg:tags":[
        "taping"
    ],
    "sg:website":"www.migrantmedia.com",
    "wof:name":"Migrant Media Productions",
    "wof:placetype":"venue"
},
  "geometry": {"coordinates":[-121.755556,36.923048],"type":"Point"}
}