{
  "type": "Feature",
  "properties": {
    "iso:country":"US",
    "sg:address":"5863 Hollister Ave",
    "sg:city":"Goleta",
    "sg:classifiers":[
        {
            "category":"Food & Beverages",
            "subcategory":"Groceries & Convenience Stores",
            "type":"Retail Goods"
        }
    ],
    "sg:phone":"+1 805 683 4417",
    "sg:postcode":"93117",
    "sg:province":"CA",
    "sg:tags":[
        "market"
    ],
    "wof:name":"Oriental Market",
    "wof:placetype":"venue"
},
  "geometry": {"coordinates":[-119.827814,34.435867],"type":"Point"}
}