{
  "type": "Feature",
  "properties": {
    "addr:full":"8837 N Grove Ave Rancho Cucamonga CA 91730",
    "addr:housenumber":"8837",
    "addr:postcode":"91730",
    "addr:street":"N Grove Ave",
    "iso:country":"US",
    "sg:address":"8837 N Grove Ave",
    "sg:city":"Rancho Cucamonga",
    "sg:classifiers":[
        {
            "category":"Home & Garden",
            "subcategory":"Building Materials",
            "type":"Retail Goods"
        }
    ],
    "sg:phone":"+1 909 286 1409",
    "sg:postcode":"91730",
    "sg:province":"CA",
    "sg:tags":[
        "glass",
        "window",
        "plate"
    ],
    "wof:name":"Glassman",
    "wof:placetype":"venue"
},
  "geometry": {"coordinates":[-117.628564,34.093987],"type":"Point"}
}