{
  "type": "Feature",
  "properties": {
    "addr:full":"2350 San Pablo Ave Pinole CA 94564",
    "addr:housenumber":"2350",
    "addr:postcode":"94564",
    "addr:street":"San Pablo Ave",
    "iso:country":"US",
    "sg:address":"2350 San Pablo Ave",
    "sg:city":"Pinole",
    "sg:classifiers":[
        {
            "category":"Food & Beverages",
            "subcategory":"Liquor & Beverages",
            "type":"Retail Goods"
        }
    ],
    "sg:phone":"+1 510 724 9740",
    "sg:postcode":"94564",
    "sg:province":"CA",
    "wof:name":"Bill's Liquors",
    "wof:placetype":"venue"
},
  "geometry": {"coordinates":[-122.290481,38.006036],"type":"Point"}
}