{
  "type": "Feature",
  "properties": {
    "addr:full":"7073 Vineland Ave North Hollywood CA 91605",
    "addr:housenumber":"7073",
    "addr:postcode":"91605",
    "addr:street":"Vineland Ave",
    "iso:country":"US",
    "sg:address":"7073 Vineland Ave",
    "sg:city":"North Hollywood",
    "sg:classifiers":[
        {
            "category":"Communications",
            "subcategory":"Film & Video Production",
            "type":"Services"
        }
    ],
    "sg:phone":"+1 818 982 8010",
    "sg:postcode":"91605",
    "sg:province":"CA",
    "sg:tags":[
        "taping"
    ],
    "wof:name":"Jet Set Productions",
    "wof:placetype":"venue"
},
  "geometry": {"coordinates":[-118.37038699999999,34.198502],"type":"Point"}
}