{
  "type": "Feature",
  "properties": {
    "addr:full":"2735 Porter St Soquel CA 95073",
    "addr:housenumber":"2735",
    "addr:postcode":"95073",
    "addr:street":"Porter St",
    "iso:country":"US",
    "sg:address":"2735 Porter St",
    "sg:city":"Soquel",
    "sg:classifiers":[
        {
            "category":"Real Estate",
            "subcategory":"Surveying",
            "type":"Services"
        }
    ],
    "sg:phone":"+1 831 479 1953",
    "sg:postcode":"95073",
    "sg:province":"CA",
    "sg:tags":[
        "surveyor",
        "land",
        "engineer"
    ],
    "sg:website":"http://www.mcgregorlandsurveys.com",
    "wof:name":"Mcgregor Land Surveys",
    "wof:placetype":"venue"
},
  "geometry": {"coordinates":[-121.95738,36.986145],"type":"Point"}
}