{
  "type": "Feature",
  "properties": {
    "iso:country":"US",
    "sg:address":"9732 Rush St",
    "sg:city":"South El Monte",
    "sg:classifiers":[
        {
            "category":"Wholesale",
            "subcategory":"Metals & Minerals",
            "type":"Manufacturing & Wholesale Goods"
        }
    ],
    "sg:phone":"+1 626 279 5022",
    "sg:postcode":"91733",
    "sg:province":"CA",
    "sg:tags":[
        "steel",
        "warehouse"
    ],
    "sg:website":"www.emerdex.com",
    "wof:name":"Emerdex Stainless Steel Inc",
    "wof:placetype":"venue"
},
  "geometry": {"coordinates":[-118.058515,34.051744],"type":"Point"}
}