{
  "type": "Feature",
  "properties": {
    "addr:full":"27913 Center Dr Mission Viejo CA 92692",
    "addr:housenumber":"27913",
    "addr:postcode":"92692",
    "addr:street":"Center Dr",
    "iso:country":"US",
    "sg:address":"27913 Center Dr",
    "sg:city":"Mission Viejo",
    "sg:classifiers":[
        {
            "category":"Autos & Motor Vehicles",
            "subcategory":"Auto Supplies",
            "type":"Retail Goods"
        },
        {
            "category":"Retail",
            "subcategory":"Auto Repair",
            "type":"Services"
        }
    ],
    "sg:phone":"+1 949 347 8340",
    "sg:postcode":"92692",
    "sg:province":"CA",
    "sg:tags":[
        "tire"
    ],
    "wof:name":"AAA Autocare",
    "wof:placetype":"venue"
},
  "geometry": {"coordinates":[-117.646004,33.612598],"type":"Point"}
}