{
  "type": "Feature",
  "properties": {
    "addr:full":"1325 Howard Ave Ste 145 Burlingame CA 94010",
    "addr:housenumber":"1325",
    "addr:postcode":"94010",
    "addr:street":"Howard Ave Ste 145",
    "iso:country":"US",
    "sg:address":"1325 Howard Ave Ste 145",
    "sg:city":"Burlingame",
    "sg:classifiers":[
        {
            "category":"Personal",
            "type":"Services"
        }
    ],
    "sg:phone":"+1 650 579 1778",
    "sg:postcode":"94010",
    "sg:province":"CA",
    "sg:tags":[
        "party",
        "planning",
        "event"
    ],
    "wof:name":"Seated Affairs",
    "wof:placetype":"venue"
},
  "geometry": {"coordinates":[-122.34592499999999,37.577074],"type":"Point"}
}