{
  "type": "Feature",
  "properties": {
    "addr:full":"5315 Ehrhardt Ave Sacramento CA 95823",
    "addr:housenumber":"5315",
    "addr:postcode":"95823",
    "addr:street":"Ehrhardt Ave",
    "iso:country":"US",
    "sg:address":"5315 Ehrhardt Ave",
    "sg:city":"Sacramento",
    "sg:classifiers":[
        {
            "category":"Manufacturing",
            "subcategory":"Soap",
            "type":"Manufacturing & Wholesale Goods"
        }
    ],
    "sg:phone":"+1 916 428 9150",
    "sg:postcode":"95823",
    "sg:province":"CA",
    "sg:tags":[
        "detergents-wholesale",
        "manufacturer"
    ],
    "wof:name":"Hair At Last",
    "wof:placetype":"venue"
},
  "geometry": {"coordinates":[-121.440996,38.459493],"type":"Point"}
}