{
  "type": "Feature",
  "properties": {
    "addr:full":"10610 Mill Station Rd Sebastopol CA 95472",
    "addr:housenumber":"10610",
    "addr:postcode":"95472",
    "addr:street":"Mill Station Rd",
    "iso:country":"US",
    "sg:address":"10610 Mill Station Rd",
    "sg:city":"Sebastopol",
    "sg:classifiers":[
        {
            "category":"Shopping",
            "subcategory":"Antiques",
            "type":"Retail Goods"
        }
    ],
    "sg:phone":"+1 707 829 6865",
    "sg:postcode":"95472",
    "sg:province":"CA",
    "sg:tags":[
        "dealers-wholesale"
    ],
    "wof:name":"Batemans Antiques",
    "wof:placetype":"venue"
},
  "geometry": {"coordinates":[-122.878992,38.426863],"type":"Point"}
}