{
  "type": "Feature",
  "properties": {
    "iso:country":"US",
    "sg:address":"14011 S Normandie Ave",
    "sg:city":"Gardena",
    "sg:classifiers":[
        {
            "category":"Manufacturing",
            "subcategory":"Printing",
            "type":"Manufacturing & Wholesale Goods"
        }
    ],
    "sg:phone":"+1 310 217 8883",
    "sg:postcode":"90249",
    "sg:province":"CA",
    "sg:tags":[
        "printer"
    ],
    "wof:name":"Volt Printing",
    "wof:placetype":"venue"
},
  "geometry": {"coordinates":[-118.30045800000001,33.904545],"type":"Point"}
}