{
  "type": "Feature",
  "properties": {
    "addr:full":"39802 Cedar Blvd Newark CA 94560",
    "addr:housenumber":"39802",
    "addr:postcode":"94560",
    "addr:street":"Cedar Blvd",
    "iso:country":"US",
    "sg:address":"39802 Cedar Blvd",
    "sg:city":"Newark",
    "sg:classifiers":[
        {
            "category":"Travel",
            "subcategory":"Hotels & Motels",
            "type":"Entertainment"
        }
    ],
    "sg:phone":"+1 510 657 4600",
    "sg:postcode":"94560",
    "sg:province":"CA",
    "sg:website":"http://ad.doubleclick.net/clk;227432790;51129303;z?http://www.marriott.com/hotels/travel/SJCTN",
    "wof:name":"TownePlace Newark",
    "wof:placetype":"venue"
},
  "geometry": {"coordinates":[-121.994851,37.519896],"type":"Point"}
}