{
  "type": "Feature",
  "properties": {
    "iso:country":"US",
    "sg:address":"2239 Larkspur Landing Cir",
    "sg:city":"Larkspur",
    "sg:classifiers":[
        {
            "category":"Retail",
            "subcategory":"Repair Shop",
            "type":"Services"
        }
    ],
    "sg:phone":"+1 415 461 6226",
    "sg:postcode":"94904",
    "sg:province":"CA",
    "sg:tags":[
        "lock",
        "locksmith"
    ],
    "wof:name":"Lark Key Svc",
    "wof:placetype":"venue"
},
  "geometry": {"coordinates":[-122.511443,37.947465],"type":"Point"}
}