{
  "type": "Feature",
  "properties": {
    "addr:full":"452 W Bedford Ave Fresno CA 93711",
    "addr:housenumber":"452",
    "addr:postcode":"93711",
    "addr:street":"W Bedford Ave",
    "iso:country":"US",
    "sg:address":"452 W Bedford Ave",
    "sg:city":"Fresno",
    "sg:phone":"+1 559 431 3794",
    "sg:postcode":"93711",
    "sg:province":"CA",
    "sg:tags":[
        "equipment",
        "retail",
        "supply"
    ],
    "wof:name":"Fesco",
    "wof:placetype":"venue"
},
  "geometry": {"coordinates":[-119.79871900000001,36.846065],"type":"Point"}
}