{
  "type": "Feature",
  "properties": {
    "iso:country":"US",
    "sg:address":"6200 Doyle St Apt 7",
    "sg:city":"Emeryville",
    "sg:classifiers":[
        {
            "category":"Retail",
            "subcategory":"Auto Rental",
            "type":"Services"
        }
    ],
    "sg:phone":"+1 510 654 7537",
    "sg:postcode":"94608",
    "sg:province":"CA",
    "sg:tags":[
        "car"
    ],
    "wof:name":"United Rent A Car",
    "wof:placetype":"venue"
},
  "geometry": {"coordinates":[-122.288612,37.84354],"type":"Point"}
}