{
  "type": "Feature",
  "properties": {
    "iso:country":"US",
    "sg:address":"333 Schwerin St",
    "sg:city":"San Francisco",
    "sg:classifiers":[
        {
            "category":"Organizations",
            "subcategory":"Community Association",
            "type":"Services"
        }
    ],
    "sg:phone":"+1 415 239 0146",
    "sg:postcode":"94134",
    "sg:province":"CA",
    "sg:tags":[
        "club"
    ],
    "wof:name":"San Francisco Boys & Girls Clb",
    "wof:placetype":"venue"
},
  "geometry": {"coordinates":[-122.412225,37.708488],"type":"Point"}
}