{
  "type": "Feature",
  "properties": {
    "iso:country":"US",
    "sg:address":"2227 Myers St",
    "sg:city":"Oroville",
    "sg:classifiers":[
        {
            "category":"Insurance",
            "subcategory":"Insurance Agent",
            "type":"Services"
        },
        {
            "category":"Insurance",
            "subcategory":"Hazard Insurance",
            "type":"Services"
        },
        {
            "category":"Insurance",
            "subcategory":"Title Insurance",
            "type":"Services"
        },
        {
            "category":"Insurance",
            "subcategory":"Life Insurance",
            "type":"Services"
        }
    ],
    "sg:phone":"+1 530 534 7222",
    "sg:postcode":"95966",
    "sg:province":"CA",
    "sg:tags":[
        "business",
        "auto",
        "commercial",
        "homeowner",
        "motorcycle",
        "renter"
    ],
    "wof:name":"Allstate Insurance Company - Charles Ott",
    "wof:placetype":"venue"
},
  "geometry": {"coordinates":[-121.551511,39.507251],"type":"Point"}
}