{
  "type": "Feature",
  "properties": {
    "addr:full":"841 W Brannan Island Rd Isleton CA 95641",
    "addr:housenumber":"841",
    "addr:postcode":"95641",
    "addr:street":"W Brannan Island Rd",
    "iso:country":"US",
    "sg:address":"841 W Brannan Island Rd",
    "sg:city":"Isleton",
    "sg:classifiers":[
        {
            "category":"Building & Trades",
            "subcategory":"Cleaning & Sanitation",
            "type":"Services"
        }
    ],
    "sg:phone":"+1 530 668 1699",
    "sg:postcode":"95641",
    "sg:province":"CA",
    "sg:tags":[
        "fireplace",
        "chimney",
        "maintenance"
    ],
    "wof:name":"Solano Chimney Sweep",
    "wof:placetype":"venue"
},
  "geometry": {"coordinates":[-121.601124,38.108368],"type":"Point"}
}