{
  "type": "Feature",
  "properties": {
    "addr:full":"500 E Carson Plaza Dr Carson CA 90746",
    "addr:housenumber":"500",
    "addr:postcode":"90746",
    "addr:street":"E;Plaza Dr",
    "iso:country":"US",
    "sg:address":"500 E Carson Plaza Dr",
    "sg:city":"Carson",
    "sg:classifiers":[
        {
            "category":"Banks & Credit Unions",
            "subcategory":"Bank",
            "type":"Services"
        }
    ],
    "sg:phone":"+1 310 323 6331",
    "sg:postcode":"90746",
    "sg:province":"CA",
    "sg:tags":[
        "loan",
        "real estate"
    ],
    "wof:name":"Stage One Mortgage & Realty",
    "wof:placetype":"venue"
},
  "geometry": {"coordinates":[-118.26436699999999,33.845233],"type":"Point"}
}