{
  "type": "Feature",
  "properties": {
    "iso:country":"US",
    "sg:address":"11509 Burbank Blvd",
    "sg:city":"North Hollywood",
    "sg:classifiers":[
        {
            "category":"Social Services",
            "type":"Services"
        }
    ],
    "sg:phone":"+1 818 752 3700",
    "sg:postcode":"91601",
    "sg:province":"CA",
    "sg:tags":[
        "counselor",
        "marriage",
        "family"
    ],
    "wof:name":"Robert Pierre",
    "wof:placetype":"venue"
},
  "geometry": {"coordinates":[-118.383116,34.172228],"type":"Point"}
}