{
  "type": "Feature",
  "properties": {
    "iso:country":"US",
    "sg:address":"2892 State Rte 49",
    "sg:city":"Angels Camp",
    "sg:classifiers":[
        {
            "category":"Shopping",
            "subcategory":"Bicycles & Sporting Goods",
            "type":"Retail Goods"
        }
    ],
    "sg:phone":"+1 209 736 4333",
    "sg:postcode":"95222",
    "sg:province":"CA",
    "sg:tags":[
        "tackle",
        "fishing"
    ],
    "sg:website":"www.gloryholesports.com",
    "wof:name":"Glory Hole Sports",
    "wof:placetype":"venue"
},
  "geometry": {"coordinates":[-120.516518,38.039148],"type":"Point"}
}