{
  "type": "Feature",
  "properties": {
    "addr:full":"3523 Mt Diablo Blvd Lafayette CA 94549",
    "addr:housenumber":"3523",
    "addr:postcode":"94549",
    "addr:street":"Mt Diablo Blvd",
    "iso:country":"US",
    "sg:address":"3523 Mt Diablo Blvd",
    "sg:city":"Lafayette",
    "sg:classifiers":[
        {
            "category":"Autos & Motor Vehicles",
            "subcategory":"Fuel & Gas Station",
            "type":"Retail Goods"
        }
    ],
    "sg:phone":"+1 925 299 0545",
    "sg:postcode":"94549",
    "sg:province":"CA",
    "wof:name":"Lafayette 76",
    "wof:placetype":"venue"
},
  "geometry": {"coordinates":[-122.118088,37.89209],"type":"Point"}
}