{
  "type": "Feature",
  "properties": {
    "addr:full":"116 W Main St Turlock CA 95380",
    "addr:housenumber":"116",
    "addr:postcode":"95380",
    "addr:street":"W Main St",
    "iso:country":"US",
    "sg:address":"116 W Main St",
    "sg:city":"Turlock",
    "sg:classifiers":[
        {
            "category":"Shopping",
            "subcategory":"Gifts & Souvenirs",
            "type":"Retail Goods"
        }
    ],
    "sg:phone":"+1 209 668 0227",
    "sg:postcode":"95380",
    "sg:province":"CA",
    "sg:tags":[
        "shop"
    ],
    "wof:name":"Lily's Emporium",
    "wof:placetype":"venue"
},
  "geometry": {"coordinates":[-120.847027,37.49372],"type":"Point"}
}