{
  "type": "Feature",
  "properties": {
    "iso:country":"US",
    "sg:address":"6652 E Mountain View Ave",
    "sg:city":"Selma",
    "sg:classifiers":[
        {
            "category":"Building & Trades",
            "subcategory":"Plumbing",
            "type":"Services"
        }
    ],
    "sg:phone":"+1 559 896 8733",
    "sg:postcode":"93662",
    "sg:province":"CA",
    "sg:tags":[
        "conditioning",
        "air",
        "system",
        "contractor"
    ],
    "wof:name":"Design Systems Air Conditionin",
    "wof:placetype":"venue"
},
  "geometry": {"coordinates":[-119.671674,36.547204],"type":"Point"}
}