{
  "type": "Feature",
  "properties": {
    "iso:country":"US",
    "sg:address":"690 Ventura Blvd Ste 142",
    "sg:city":"Camarillo",
    "sg:classifiers":[
        {
            "category":"Shopping",
            "subcategory":"Clothing, Apparel, & Fashions",
            "type":"Retail Goods"
        }
    ],
    "sg:phone":"+1 805 445 1482",
    "sg:postcode":"93010",
    "sg:province":"CA",
    "sg:tags":[
        "accessory",
        "clothing",
        "women's"
    ],
    "wof:name":"Bebe Inc",
    "wof:placetype":"venue"
},
  "geometry": {"coordinates":[-119.04499800000001,34.232101],"type":"Point"}
}