{
  "type": "Feature",
  "properties": {
    "iso:country":"US",
    "sg:address":"1875 Century Park E Suite 1770",
    "sg:city":"Los Angeles",
    "sg:classifiers":[
        {
            "category":"Professional",
            "subcategory":"Lawyer & Legal Services",
            "type":"Services"
        }
    ],
    "sg:phone":"+1 310 201 7635",
    "sg:postcode":"90067",
    "sg:province":"CA",
    "wof:name":"Law Office of Carl Simons",
    "wof:placetype":"venue"
},
  "geometry": {"coordinates":[-118.414089,34.060855],"type":"Point"}
}