{
  "type": "Feature",
  "properties": {
    "addr:full":"2707 Walker St Berkeley CA 94705",
    "addr:housenumber":"2707",
    "addr:postcode":"94705",
    "addr:street":"Walker St",
    "iso:country":"US",
    "sg:address":"2707 Walker St",
    "sg:city":"Berkeley",
    "sg:classifiers":[
        {
            "category":"Professional",
            "subcategory":"Art Services",
            "type":"Services"
        }
    ],
    "sg:phone":"+1 510 649 0336",
    "sg:postcode":"94705",
    "sg:province":"CA",
    "sg:tags":[
        "graphic",
        "designer"
    ],
    "wof:name":"Acme Art",
    "wof:placetype":"venue"
},
  "geometry": {"coordinates":[-122.265924,37.859637],"type":"Point"}
}