{
  "type": "Feature",
  "properties": {
    "addr:full":"1197 Valencia St San Francisco CA 94110",
    "addr:housenumber":"1197",
    "addr:postcode":"94110",
    "addr:street":"Valencia St",
    "iso:country":"US",
    "sg:address":"1197 Valencia St",
    "sg:city":"San Francisco",
    "sg:classifiers":[
        {
            "category":"Health Services",
            "subcategory":"Health Practitioner",
            "type":"Services"
        }
    ],
    "sg:phone":"+1 415 642 9580",
    "sg:postcode":"94110",
    "sg:province":"CA",
    "sg:tags":[
        "psychotherapist"
    ],
    "wof:name":"Karen Barnes",
    "wof:placetype":"venue"
},
  "geometry": {"coordinates":[-122.420855,37.755268],"type":"Point"}
}