{
  "type": "Feature",
  "properties": {
    "iso:country":"US",
    "sg:address":"2024 Monrovia Ave",
    "sg:city":"Costa Mesa",
    "sg:classifiers":[
        {
            "category":"Building & Trades",
            "subcategory":"Construction",
            "type":"Services"
        }
    ],
    "sg:phone":"+1 949 650 8529",
    "sg:postcode":"92627",
    "sg:province":"CA",
    "sg:tags":[
        "handyman"
    ],
    "wof:name":"A High-Rise Handyman",
    "wof:placetype":"venue"
},
  "geometry": {"coordinates":[-117.93591499999999,33.647522],"type":"Point"}
}