{
  "type": "Feature",
  "properties": {
    "iso:country":"US",
    "sg:address":"2709 del Oro Ct",
    "sg:city":"Sacramento",
    "sg:classifiers":[
        {
            "category":"Cinema",
            "subcategory":"Movie Rental",
            "type":"Entertainment"
        }
    ],
    "sg:phone":"+1 916 952 1571",
    "sg:postcode":"95826",
    "sg:province":"CA",
    "sg:tags":[
        "picture",
        "exchange",
        "motion",
        "distributor",
        "film"
    ],
    "wof:name":"Intense Productions",
    "wof:placetype":"venue"
},
  "geometry": {"coordinates":[-121.362791,38.56323],"type":"Point"}
}