{
  "type": "Feature",
  "properties": {
    "iso:country":"US",
    "sg:address":"8151 Walnut Hills Way",
    "sg:city":"Fair Oaks",
    "sg:classifiers":[
        {
            "category":"Professional",
            "subcategory":"Business Services",
            "type":"Services"
        }
    ],
    "sg:phone":"+1 916 536 9581",
    "sg:postcode":"95628",
    "sg:province":"CA",
    "wof:name":"George Kardous Corp",
    "wof:placetype":"venue"
},
  "geometry": {"coordinates":[-121.260884,38.671022],"type":"Point"}
}