{
  "type": "Feature",
  "properties": {
    "addr:full":"1815 Mt Diablo Blvd Walnut Creek CA 94596",
    "addr:housenumber":"1815",
    "addr:postcode":"94596",
    "addr:street":"Mt Diablo Blvd",
    "iso:country":"US",
    "sg:address":"1815 Mt Diablo Blvd",
    "sg:city":"Walnut Creek",
    "sg:classifiers":[
        {
            "category":"Personal",
            "subcategory":"Beauty Salon",
            "type":"Services"
        }
    ],
    "sg:phone":"+1 925 934 5013",
    "sg:postcode":"94596",
    "sg:province":"CA",
    "sg:tags":[
        "shop",
        "equipment",
        "establishment",
        "manicuring"
    ],
    "wof:name":"Capital Nails",
    "wof:placetype":"venue"
},
  "geometry": {"coordinates":[-122.06377000000001,37.897283],"type":"Point"}
}