{
  "type": "Feature",
  "properties": {
    "addr:full":"5218 Cll Cristobal Santa Barbara CA 93111",
    "addr:housenumber":"5218",
    "addr:postcode":"93111",
    "addr:street":"Cll Cristobal",
    "iso:country":"US",
    "sg:address":"5218 Cll Cristobal",
    "sg:city":"Santa Barbara",
    "sg:classifiers":[
        {
            "category":"Building & Trades",
            "subcategory":"Construction",
            "type":"Services"
        }
    ],
    "sg:phone":"+1 805 683 2006",
    "sg:postcode":"93111",
    "sg:province":"CA",
    "sg:tags":[
        "coping",
        "plastering",
        "tiling",
        "pool",
        "swimming"
    ],
    "wof:name":"Ben Georges Pool Svc",
    "wof:placetype":"venue"
},
  "geometry": {"coordinates":[-119.80445899999999,34.434274],"type":"Point"}
}