{
  "type": "Feature",
  "properties": {
    "addr:full":"14555 Valley View Ave Santa Fe Springs CA 90670",
    "addr:housenumber":"14555",
    "addr:postcode":"90670",
    "addr:street":"Valley View Ave",
    "iso:country":"US",
    "sg:address":"14555 Valley View Ave",
    "sg:city":"Santa Fe Springs",
    "sg:classifiers":[
        {
            "category":"Autos & Motor Vehicles",
            "subcategory":"Automobile Sales",
            "type":"Retail Goods"
        }
    ],
    "sg:phone":"+1 562 229 9899",
    "sg:postcode":"90670",
    "sg:province":"CA",
    "sg:tags":[
        "car",
        "dealer"
    ],
    "sg:website":"www.marketimportsusa.com",
    "wof:name":"Market Imports",
    "wof:placetype":"venue"
},
  "geometry": {"coordinates":[-118.02918,33.900654],"type":"Point"}
}