{
  "type": "Feature",
  "properties": {
    "addr:full":"3939 Monroe Ave Fremont CA 94536",
    "addr:housenumber":"3939",
    "addr:postcode":"94536",
    "addr:street":"Monroe Ave",
    "iso:country":"US",
    "sg:address":"3939 Monroe Ave",
    "sg:city":"Fremont",
    "sg:classifiers":[
        {
            "category":"Wholesale",
            "subcategory":"Durable Goods & Equipment",
            "type":"Manufacturing & Wholesale Goods"
        }
    ],
    "sg:phone":"+1 510 794 4989",
    "sg:postcode":"94536",
    "sg:province":"CA",
    "sg:tags":[
        "importer"
    ],
    "wof:name":"Brain Weavers Intl Inc",
    "wof:placetype":"venue"
},
  "geometry": {"coordinates":[-121.990111,37.550958],"type":"Point"}
}