{
  "type": "Feature",
  "properties": {
    "addr:full":"1000 S Euclid St Fullerton CA 92832",
    "addr:housenumber":"1000",
    "addr:postcode":"92832",
    "addr:street":"S Euclid St",
    "iso:country":"US",
    "sg:address":"1000 S Euclid St",
    "sg:city":"Fullerton",
    "sg:classifiers":[
        {
            "category":"Travel",
            "subcategory":"Hotels & Motels",
            "type":"Entertainment"
        }
    ],
    "sg:phone":"+1 714 871 7200",
    "sg:postcode":"92832",
    "sg:province":"CA",
    "wof:name":"Howard Johnson Express Inn",
    "wof:placetype":"venue"
},
  "geometry": {"coordinates":[-117.942001,33.861099],"type":"Point"}
}