{
  "type": "Feature",
  "properties": {
    "addr:full":"11344 Coloma Road Suite 205 Gold River CA 95670",
    "addr:housenumber":"11344",
    "addr:postcode":"95670",
    "addr:street":"Coloma Road Suite 205",
    "iso:country":"US",
    "sg:address":"11344 Coloma Road Suite 205",
    "sg:city":"Gold River",
    "sg:classifiers":[
        {
            "category":"Restaurant",
            "type":"Food & Drink"
        }
    ],
    "sg:phone":"+1 916 631 7297",
    "sg:postcode":"95670",
    "sg:province":"CA",
    "wof:name":"Coloma Cafe",
    "wof:placetype":"venue"
},
  "geometry": {"coordinates":[-121.25991399999999,38.621371],"type":"Point"}
}