{
  "type": "Feature",
  "properties": {
    "addr:full":"15349 Los Gatos Blvd Ste D Los Gatos CA 95032",
    "addr:housenumber":"15349",
    "addr:postcode":"95032",
    "addr:street":"Los Gatos Blvd Ste D",
    "iso:country":"US",
    "sg:address":"15349 Los Gatos Blvd Ste D",
    "sg:city":"Los Gatos",
    "sg:classifiers":[
        {
            "category":"Personal",
            "subcategory":"Nail Salon",
            "type":"Services"
        }
    ],
    "sg:phone":"+1 408 358 3996",
    "sg:postcode":"95032",
    "sg:province":"CA",
    "wof:name":"Nail Colours",
    "wof:placetype":"venue"
},
  "geometry": {"coordinates":[-121.95700100000001,37.247398],"type":"Point"}
}