{
  "type": "Feature",
  "properties": {
    "addr:full":"1141 E Broadway Glendale CA 91205",
    "addr:housenumber":"1141",
    "addr:postcode":"91205",
    "addr:street":"E Broadway",
    "iso:country":"US",
    "sg:address":"1141 E Broadway",
    "sg:city":"Glendale",
    "sg:classifiers":[
        {
            "category":"Donuts",
            "subcategory":"None",
            "type":"Food & Drink"
        }
    ],
    "sg:phone":"+1 818 956 1798",
    "sg:postcode":"91205",
    "sg:province":"CA",
    "wof:name":"Big Jim's Donuts",
    "wof:placetype":"venue"
},
  "geometry": {"coordinates":[-118.24091199999999,34.146244],"type":"Point"}
}