{
  "type": "Feature",
  "properties": {
    "iso:country":"US",
    "sg:address":"858 Cortez Ln",
    "sg:city":"Foster City",
    "sg:classifiers":[
        {
            "category":"Professional",
            "type":"Services"
        }
    ],
    "sg:phone":"+1 650 573 9899",
    "sg:postcode":"94404",
    "sg:province":"CA",
    "sg:tags":[
        "establishment"
    ],
    "wof:name":"Winston Square",
    "wof:placetype":"venue"
},
  "geometry": {"coordinates":[-122.2668,37.551134],"type":"Point"}
}