{
  "type": "Feature",
  "properties": {
    "iso:country":"US",
    "sg:address":"5811 Amaya Dr Ste 202",
    "sg:city":"La Mesa",
    "sg:classifiers":[
        {
            "category":"Professional",
            "subcategory":"Lawyer & Legal Services",
            "type":"Services"
        }
    ],
    "sg:phone":"+1 619 589 9333",
    "sg:postcode":"91942",
    "sg:province":"CA",
    "sg:tags":[
        "divorce",
        "law",
        "family"
    ],
    "wof:name":"Divorce Alternatives",
    "wof:placetype":"venue"
},
  "geometry": {"coordinates":[-116.994929,32.784895],"type":"Point"}
}