{
  "type": "Feature",
  "properties": {
    "iso:country":"US",
    "sg:address":"7520 Eads Ave",
    "sg:city":"La Jolla",
    "sg:classifiers":[
        {
            "category":"Arts & Performance",
            "subcategory":"Arts Center",
            "type":"Entertainment"
        }
    ],
    "sg:phone":"+1 858 551 5858",
    "sg:postcode":"92037",
    "sg:province":"CA",
    "sg:tags":[
        "performing"
    ],
    "wof:name":"Le Reve Dance",
    "wof:placetype":"venue"
},
  "geometry": {"coordinates":[-117.275177,32.84027],"type":"Point"}
}