{
  "type": "Feature",
  "properties": {
    "addr:full":"1345 Harkins Rd Salinas CA 93901",
    "addr:housenumber":"1345",
    "addr:postcode":"93901",
    "addr:street":"Harkins Rd",
    "iso:country":"US",
    "sg:address":"1345 Harkins Rd",
    "sg:city":"Salinas",
    "sg:classifiers":[
        {
            "category":"Manufacturing",
            "subcategory":"Paper Products",
            "type":"Manufacturing & Wholesale Goods"
        }
    ],
    "sg:phone":"+1 831 757 5381",
    "sg:postcode":"93901",
    "sg:province":"CA",
    "sg:tags":[
        "corrugated",
        "solid",
        "fiber",
        "box"
    ],
    "sg:website":"www.weyerhaeuser.com",
    "wof:name":"Weyerhaeuser Shipping Cntnrs",
    "wof:placetype":"venue"
},
  "geometry": {"coordinates":[-121.634005,36.645141],"type":"Point"}
}