{
  "type": "Feature",
  "properties": {
    "addr:full":"161 Island Ave Wilmington CA 90744",
    "addr:housenumber":"161",
    "addr:postcode":"90744",
    "addr:street":"Island Ave",
    "iso:country":"US",
    "sg:address":"161 Island Ave",
    "sg:city":"Wilmington",
    "sg:classifiers":[
        {
            "category":"Utilities",
            "subcategory":"Electric",
            "type":"Services"
        }
    ],
    "sg:phone":"+1 310 522 1750",
    "sg:postcode":"90744",
    "sg:province":"CA",
    "sg:tags":[
        "combination"
    ],
    "wof:name":"Harbor Generating Stn Pwr Stn",
    "wof:placetype":"venue"
},
  "geometry": {"coordinates":[-118.265719,33.770909],"type":"Point"}
}