{
  "type": "Feature",
  "properties": {
    "addr:full":"727 Western Ave Santa Barbara CA 93101",
    "addr:housenumber":"727",
    "addr:postcode":"93101",
    "addr:street":"Western Ave",
    "iso:country":"US",
    "sg:address":"727 Western Ave",
    "sg:city":"Santa Barbara",
    "sg:classifiers":[
        {
            "category":"Building & Trades",
            "subcategory":"Landscaping Services",
            "type":"Services"
        }
    ],
    "sg:phone":"+1 805 966 2042",
    "sg:postcode":"93101",
    "sg:province":"CA",
    "sg:tags":[
        "lawn",
        "maintenance",
        "grounds"
    ],
    "wof:name":"Rudy's Gardening Svc",
    "wof:placetype":"venue"
},
  "geometry": {"coordinates":[-119.71641200000001,34.417398],"type":"Point"}
}