{
  "type": "Feature",
  "properties": {
    "addr:full":"6370 Printwood Way San Diego CA 92117",
    "addr:housenumber":"6370",
    "addr:postcode":"92117",
    "addr:street":"Printwood Way",
    "iso:country":"US",
    "sg:address":"6370 Printwood Way",
    "sg:city":"San Diego",
    "sg:classifiers":[
        {
            "category":"Real Estate",
            "subcategory":"Architect",
            "type":"Services"
        }
    ],
    "sg:phone":"+1 858 292 1414",
    "sg:postcode":"92117",
    "sg:province":"CA",
    "wof:name":"Shape Architects",
    "wof:placetype":"venue"
},
  "geometry": {"coordinates":[-117.16798799999999,32.827687],"type":"Point"}
}