{
  "type": "Feature",
  "properties": {
    "iso:country":"US",
    "sg:address":"1 Toulon",
    "sg:city":"Newport Beach",
    "sg:classifiers":[
        {
            "category":"Professional",
            "subcategory":"Management & Consulting",
            "type":"Services"
        }
    ],
    "sg:phone":"+1 949 759 1645",
    "sg:postcode":"92660",
    "sg:province":"CA",
    "sg:tags":[
        "marketing",
        "consultant"
    ],
    "wof:name":"Strategic Solutions",
    "wof:placetype":"venue"
},
  "geometry": {"coordinates":[-117.849458,33.616672],"type":"Point"}
}