{
  "type": "Feature",
  "properties": {
    "addr:full":"504 Bridge View Ct Richmond CA 94801",
    "addr:housenumber":"504",
    "addr:postcode":"94801",
    "addr:street":"Bridge View Ct",
    "iso:country":"US",
    "sg:address":"504 Bridge View Ct",
    "sg:city":"Richmond",
    "sg:classifiers":[
        {
            "category":"Professional",
            "subcategory":"Computer Services",
            "type":"Services"
        }
    ],
    "sg:phone":"+1 510 964 4525",
    "sg:postcode":"94801",
    "sg:province":"CA",
    "sg:tags":[
        "web",
        "site",
        "hosting"
    ],
    "wof:name":"Simularity",
    "wof:placetype":"venue"
},
  "geometry": {"coordinates":[-122.373363,37.910973],"type":"Point"}
}