{
  "type": "Feature",
  "properties": {
    "addr:full":"1185 Laurel St San Carlos CA 94070",
    "addr:housenumber":"1185",
    "addr:postcode":"94070",
    "addr:street":"Laurel St",
    "iso:country":"US",
    "sg:address":"1185 Laurel St",
    "sg:city":"San Carlos",
    "sg:classifiers":[
        {
            "category":"Health Services",
            "subcategory":"Health Practitioner",
            "type":"Services"
        }
    ],
    "sg:phone":"+1 650 596 5685",
    "sg:postcode":"94070",
    "sg:province":"CA",
    "sg:tags":[
        "acupuncture"
    ],
    "wof:name":"Family Acupuncture Ctr",
    "wof:placetype":"venue"
},
  "geometry": {"coordinates":[-122.25309799999999,37.499896],"type":"Point"}
}