{
  "type": "Feature",
  "properties": {
    "addr:full":"3131 E Fremont St Stockton CA 95205",
    "addr:housenumber":"3131",
    "addr:postcode":"95205",
    "addr:street":"E Fremont St",
    "iso:country":"US",
    "sg:address":"3131 E Fremont St",
    "sg:city":"Stockton",
    "sg:classifiers":[
        {
            "category":"Wholesale",
            "subcategory":"Machinery & Supplies",
            "type":"Manufacturing & Wholesale Goods"
        }
    ],
    "sg:phone":"+1 209 933 0206",
    "sg:postcode":"95205",
    "sg:province":"CA",
    "sg:tags":[
        "truck"
    ],
    "sg:website":"www.wholesaleequipment.com",
    "wof:name":"Valley Forklift",
    "wof:placetype":"venue"
},
  "geometry": {"coordinates":[-121.249459,37.968493],"type":"Point"}
}