{
  "type": "Feature",
  "properties": {
    "addr:full":"4375 Prado Rd Corona CA 92880",
    "addr:housenumber":"4375",
    "addr:postcode":"92880",
    "addr:street":"Prado Rd",
    "iso:country":"US",
    "sg:address":"4375 Prado Rd",
    "sg:city":"Corona",
    "sg:classifiers":[
        {
            "category":"Wholesale",
            "subcategory":"Electrical",
            "type":"Manufacturing & Wholesale Goods"
        }
    ],
    "sg:phone":"+1 951 738 8222",
    "sg:postcode":"92880",
    "sg:province":"CA",
    "sg:tags":[
        "sound",
        "equipment",
        "system"
    ],
    "wof:name":"ASA Sound",
    "wof:placetype":"venue"
},
  "geometry": {"coordinates":[-117.650634,33.881667],"type":"Point"}
}