{
  "type": "Feature",
  "properties": {
    "iso:country":"US",
    "sg:address":"8762 Corbin Ave",
    "sg:city":"Northridge",
    "sg:classifiers":[
        {
            "category":"Home & Garden",
            "subcategory":"Home Furnishings",
            "type":"Retail Goods"
        }
    ],
    "sg:phone":"+1 818 709 1489",
    "sg:postcode":"91324",
    "sg:province":"CA",
    "sg:tags":[
        "linen"
    ],
    "sg:website":"www.annaslinens.com",
    "wof:name":"Anna's Linens",
    "wof:placetype":"venue"
},
  "geometry": {"coordinates":[-118.562229,34.230045],"type":"Point"}
}