{
  "type": "Feature",
  "properties": {
    "addr:full":"2525 W 10th St Antioch CA 94509",
    "addr:housenumber":"2525",
    "addr:postcode":"ca 94509",
    "addr:street":"W 10Th St",
    "iso:country":"US",
    "sg:address":"2525 W 10th St",
    "sg:city":"Antioch",
    "sg:classifiers":[
        {
            "category":"Manufacturing",
            "subcategory":"Printing",
            "type":"Manufacturing & Wholesale Goods"
        }
    ],
    "sg:phone":"+1 925 978 0080",
    "sg:postcode":"94509",
    "sg:province":"CA",
    "sg:tags":[
        "periodical"
    ],
    "wof:name":"Sierra Tahoe Publishing",
    "wof:placetype":"venue"
},
  "geometry": {"coordinates":[-121.826756,38.012026],"type":"Point"}
}