{
  "type": "Feature",
  "properties": {
    "iso:country":"US",
    "sg:address":"4140 Ardwell Way",
    "sg:city":"Sacramento",
    "sg:classifiers":[
        {
            "category":"Autos & Motor Vehicles",
            "subcategory":"Automobile Sales",
            "type":"Retail Goods"
        }
    ],
    "sg:phone":"+1 916 399 8895",
    "sg:postcode":"95823",
    "sg:province":"CA",
    "sg:tags":[
        "car",
        "dealer"
    ],
    "wof:name":"Betty Boop Auto Sales",
    "wof:placetype":"venue"
},
  "geometry": {"coordinates":[-121.456388,38.467535],"type":"Point"}
}