{
  "type": "Feature",
  "properties": {
    "iso:country":"US",
    "sg:address":"12921 Fern Street",
    "sg:city":"Garden Grove",
    "sg:classifiers":[
        {
            "category":"Restaurant",
            "type":"Food & Drink"
        }
    ],
    "sg:phone":"+1 714 379 9790",
    "sg:postcode":"92841",
    "sg:province":"CA",
    "sg:tags":[
        "korean"
    ],
    "wof:name":"An Ocean's Story",
    "wof:placetype":"venue"
},
  "geometry": {"coordinates":[-117.98866700000001,33.774588],"type":"Point"}
}