{
  "type": "Feature",
  "properties": {
    "addr:full":"3838 W 108th St Inglewood CA 90303",
    "addr:housenumber":"3838",
    "addr:postcode":"90303",
    "addr:street":"W 108Th St",
    "iso:country":"US",
    "sg:address":"3838 W 108th St",
    "sg:city":"Inglewood",
    "sg:classifiers":[
        {
            "category":"Health Services",
            "subcategory":"Hospital",
            "type":"Services"
        }
    ],
    "sg:phone":"+1 310 671 7777",
    "sg:postcode":"90303",
    "sg:province":"CA",
    "sg:tags":[
        "specialty"
    ],
    "wof:name":"Noble House Sober Living Home",
    "wof:placetype":"venue"
},
  "geometry": {"coordinates":[-118.34369599999999,33.937648],"type":"Point"}
}