{
  "type": "Feature",
  "properties": {
    "iso:country":"US",
    "sg:address":"2040 Cochran Rd",
    "sg:city":"Lodi",
    "sg:classifiers":[
        {
            "category":"Sports & Exercise",
            "subcategory":"Gym",
            "type":"Entertainment"
        }
    ],
    "sg:phone":"+1 209 334 4897",
    "sg:postcode":"95242",
    "sg:province":"CA",
    "sg:tags":[
        "club",
        "health",
        "studio",
        "gymnasium"
    ],
    "wof:name":"Twin Arbors Athletic Club",
    "wof:placetype":"venue"
},
  "geometry": {"coordinates":[-121.29892,38.124988],"type":"Point"}
}