{
  "type": "Feature",
  "properties": {
    "iso:country":"US",
    "sg:address":"7367 Bradshaw Rd",
    "sg:city":"Sacramento",
    "sg:classifiers":[
        {
            "category":"Building & Trades",
            "subcategory":"Landscaping Services",
            "type":"Services"
        }
    ],
    "sg:phone":"+1 916 854 2500",
    "sg:postcode":"95829",
    "sg:province":"CA",
    "sg:tags":[
        "landscape",
        "contractor"
    ],
    "wof:name":"Heede Landscape Co Inc",
    "wof:placetype":"venue"
},
  "geometry": {"coordinates":[-121.33485899999999,38.491925],"type":"Point"}
}