{
  "type": "Feature",
  "properties": {
    "addr:full":"27626 Mandarin Ave Hayward CA 94544",
    "addr:housenumber":"27626",
    "addr:postcode":"94544",
    "addr:street":"Mandarin Ave",
    "iso:country":"US",
    "sg:address":"27626 Mandarin Ave",
    "sg:city":"Hayward",
    "sg:classifiers":[
        {
            "category":"Health Services",
            "subcategory":"Nursing And Care Facility",
            "type":"Services"
        }
    ],
    "sg:phone":"+1 510 265 0843",
    "sg:postcode":"94544",
    "sg:province":"CA",
    "wof:name":"Gmaes Elderly Care",
    "wof:placetype":"venue"
},
  "geometry": {"coordinates":[-122.081875,37.630348],"type":"Point"}
}