{
  "type": "Feature",
  "properties": {
    "addr:full":"1645 Saratoga Ave San Jose CA 95129",
    "addr:housenumber":"1645",
    "addr:postcode":"95129",
    "addr:street":"Saratoga Ave",
    "iso:country":"US",
    "sg:address":"1645 Saratoga Ave",
    "sg:city":"San Jose",
    "sg:classifiers":[
        {
            "category":"Restaurant",
            "type":"Food & Drink"
        }
    ],
    "sg:menulink":"http://www.allmenus.com/ca/san-jose/171678-burger-king/menu/",
    "sg:phone":"+1 408 257 5411",
    "sg:postcode":"95129",
    "sg:province":"CA",
    "sg:tags":[
        "burger",
        "american"
    ],
    "wof:name":"Burger King",
    "wof:placetype":"venue"
},
  "geometry": {"coordinates":[-121.99109799999999,37.292682],"type":"Point"}
}