{
  "type": "Feature",
  "properties": {
    "addr:full":"7 Harris Pl Salinas CA 93901",
    "addr:housenumber":"7",
    "addr:postcode":"93901",
    "addr:street":"Harris Pl",
    "iso:country":"US",
    "sg:address":"7 Harris Pl",
    "sg:city":"Salinas",
    "sg:classifiers":[
        {
            "category":"Wholesale",
            "subcategory":"Farm Supplies",
            "type":"Manufacturing & Wholesale Goods"
        }
    ],
    "sg:phone":"+1 831 751 0937",
    "sg:postcode":"93901",
    "sg:province":"CA",
    "sg:tags":[
        "bulb",
        "seed"
    ],
    "sg:website":"www.enzasalinas.com",
    "wof:name":"Enza-Zaden",
    "wof:placetype":"venue"
},
  "geometry": {"coordinates":[-121.61149399999999,36.640832],"type":"Point"}
}