{
  "type": "Feature",
  "properties": {
    "addr:full":"4417 Pineview Dr Yreka CA 96097",
    "addr:housenumber":"4417",
    "addr:postcode":"96097",
    "addr:street":"Pineview Dr",
    "iso:country":"US",
    "sg:address":"4417 Pineview Dr",
    "sg:city":"Yreka",
    "sg:classifiers":[
        {
            "category":"Personal",
            "type":"Services"
        }
    ],
    "sg:phone":"+1 530 842 4620",
    "sg:postcode":"96097",
    "sg:province":"CA",
    "sg:tags":[
        "image",
        "consultants-personal"
    ],
    "wof:name":"Delores Image Improvement",
    "wof:placetype":"venue"
},
  "geometry": {"coordinates":[-122.635514,41.670001],"type":"Point"}
}