{
  "type": "Feature",
  "properties": {
    "iso:country":"US",
    "sg:address":"9606 Owensmouth Ave",
    "sg:city":"Chatsworth",
    "sg:classifiers":[
        {
            "category":"Wholesale",
            "subcategory":"Groceries",
            "type":"Manufacturing & Wholesale Goods"
        }
    ],
    "sg:phone":"+1 818 887 0892",
    "sg:postcode":"91311",
    "sg:province":"CA",
    "sg:tags":[
        "frozen",
        "food"
    ],
    "wof:name":"LTT Gourmet Foods",
    "wof:placetype":"venue"
},
  "geometry": {"coordinates":[-118.602294,34.245556],"type":"Point"}
}