{
  "type": "Feature",
  "properties": {
    "iso:country":"US",
    "sg:address":"335 Glen Ridge Ct",
    "sg:city":"El Dorado Hills",
    "sg:classifiers":[
        {
            "category":"Professional",
            "type":"Services"
        }
    ],
    "sg:phone":"+1 916 939 4460",
    "sg:postcode":"95762",
    "sg:province":"CA",
    "sg:tags":[
        "establishment"
    ],
    "wof:name":"Ignite Logic",
    "wof:placetype":"venue"
},
  "geometry": {"coordinates":[-121.088616,38.669346],"type":"Point"}
}