{
  "type": "Feature",
  "properties": {
    "iso:country":"US",
    "sg:address":"5351 Elkhorn Boulevard",
    "sg:city":"Sacramento",
    "sg:classifiers":[
        {
            "category":"Shopping",
            "subcategory":"Beauty & Cosmetics",
            "type":"Retail Goods"
        }
    ],
    "sg:phone":"+1 916 332 6032",
    "sg:postcode":"95842",
    "sg:province":"CA",
    "sg:tags":[
        "supply"
    ],
    "wof:name":"Sally Beauty Supply",
    "wof:placetype":"venue"
},
  "geometry": {"coordinates":[-121.339142,38.68495],"type":"Point"}
}