{
  "type": "Feature",
  "properties": {
    "addr:full":"3040 W Benjamin Holt Dr Stockton CA 95219",
    "addr:housenumber":"3040",
    "addr:postcode":"95219",
    "addr:street":"W Benjamin Holt Dr",
    "iso:country":"US",
    "sg:address":"3040 W Benjamin Holt Dr",
    "sg:city":"Stockton",
    "sg:classifiers":[
        {
            "category":"Food & Beverages",
            "subcategory":"Groceries & Convenience Stores",
            "type":"Retail Goods"
        }
    ],
    "sg:phone":"+1 209 478 3040",
    "sg:postcode":"95219",
    "sg:province":"CA",
    "wof:name":"7-Eleven",
    "wof:placetype":"venue"
},
  "geometry": {"coordinates":[-121.35279300000001,38.004679],"type":"Point"}
}