{
  "type": "Feature",
  "properties": {
    "addr:full":"4400 Del AMO Blvd Torrance CA 90503",
    "addr:housenumber":"4400",
    "addr:postcode":"90503",
    "addr:street":"Del Amo Blvd",
    "iso:country":"US",
    "sg:address":"4400 Del AMO Blvd",
    "sg:city":"Torrance",
    "sg:classifiers":[
        {
            "category":"Social Services",
            "subcategory":"Child Care",
            "type":"Services"
        },
        {
            "category":"Education",
            "subcategory":"Preschool",
            "type":"Public Place"
        },
        {
            "category":"Education",
            "subcategory":"School",
            "type":"Public Place"
        }
    ],
    "sg:phone":"+1 310 371 4503",
    "sg:postcode":"90503",
    "sg:province":"CA",
    "sg:tags":[
        "high",
        "middle",
        "day",
        "elementary"
    ],
    "sg:website":"www.adventist.org",
    "wof:name":"Discoveryland",
    "wof:placetype":"venue"
},
  "geometry": {"coordinates":[-118.361,33.848701],"type":"Point"}
}