{
  "type": "Feature",
  "properties": {
    "iso:country":"US",
    "sg:address":"5783 Mesa Verde Cir",
    "sg:city":"Rocklin",
    "sg:classifiers":[
        {
            "category":"Banks & Credit Unions",
            "subcategory":"Bank",
            "type":"Services"
        }
    ],
    "sg:phone":"+1 916 435 5000",
    "sg:postcode":"95677",
    "sg:province":"CA",
    "sg:tags":[
        "loan"
    ],
    "wof:name":"Countrywide Loan Solutions",
    "wof:placetype":"venue"
},
  "geometry": {"coordinates":[-121.25906000000001,38.786123],"type":"Point"}
}