{
  "type": "Feature",
  "properties": {
    "iso:country":"US",
    "sg:address":"706 Madrid St",
    "sg:city":"San Francisco",
    "sg:classifiers":[
        {
            "category":"Professional",
            "type":"Services"
        }
    ],
    "sg:phone":"+1 415 337 8947",
    "sg:postcode":"94112",
    "sg:province":"CA",
    "wof:name":"Omar Fuentes",
    "wof:placetype":"venue"
},
  "geometry": {"coordinates":[-122.436339,37.717087],"type":"Point"}
}