{
  "type": "Feature",
  "properties": {
    "addr:full":"5227 Hillen Dr Oakland CA 94619",
    "addr:housenumber":"5227",
    "addr:postcode":"94619",
    "addr:street":"Hillen Dr",
    "iso:country":"US",
    "sg:address":"5227 Hillen Dr",
    "sg:city":"Oakland",
    "sg:classifiers":[
        {
            "category":"Shopping",
            "subcategory":"Hobbies, Toys, & Games",
            "type":"Retail Goods"
        }
    ],
    "sg:phone":"+1 510 532 6289",
    "sg:postcode":"94619",
    "sg:province":"CA",
    "sg:tags":[
        "gun",
        "gunsmith"
    ],
    "wof:name":"Square G",
    "wof:placetype":"venue"
},
  "geometry": {"coordinates":[-122.19497,37.776745],"type":"Point"}
}