{
  "type": "Feature",
  "properties": {
    "addr:full":"1201 Larkspur Landing Cir Larkspur CA 94904",
    "addr:housenumber":"1201",
    "addr:postcode":"94904",
    "addr:street":"Larkspur Landing Cir",
    "iso:country":"US",
    "sg:address":"1201 Larkspur Landing Cir",
    "sg:city":"Larkspur",
    "sg:classifiers":[
        {
            "category":"Health Services",
            "subcategory":"Doctor",
            "type":"Services"
        }
    ],
    "sg:phone":"+1 415 461 6060",
    "sg:postcode":"94904",
    "sg:province":"CA",
    "sg:tags":[
        "dentist"
    ],
    "wof:name":"Timothy G Bricca DDS",
    "wof:placetype":"venue"
},
  "geometry": {"coordinates":[-122.50930200000001,37.94841],"type":"Point"}
}