{
  "type": "Feature",
  "properties": {
    "addr:full":"3000 Citrus Cir Walnut Creek CA 94598",
    "addr:housenumber":"3000",
    "addr:postcode":"94598",
    "addr:street":"Citrus Cir",
    "iso:country":"US",
    "sg:address":"3000 Citrus Cir",
    "sg:city":"Walnut Creek",
    "sg:classifiers":[
        {
            "category":"Social Services",
            "type":"Services"
        }
    ],
    "sg:phone":"+1 925 210 1414",
    "sg:postcode":"94598",
    "sg:province":"CA",
    "sg:tags":[
        "counselor",
        "marriage",
        "family"
    ],
    "wof:name":"Diablo Valley Counseling Ctr",
    "wof:placetype":"venue"
},
  "geometry": {"coordinates":[-122.01430999999999,37.930091],"type":"Point"}
}