{
  "type": "Feature",
  "properties": {
    "addr:full":"14809 Crenshaw Boulevard Gardena CA 90249",
    "addr:housenumber":"14809",
    "addr:postcode":"90249",
    "addr:street":"Crenshaw Boulevard",
    "iso:country":"US",
    "sg:address":"14809 Crenshaw Boulevard",
    "sg:city":"Gardena",
    "sg:classifiers":[
        {
            "category":"Government",
            "subcategory":"Office",
            "type":"Public Place"
        }
    ],
    "sg:phone":"+1 310 679 9790",
    "sg:postcode":"90249",
    "sg:province":"CA",
    "sg:tags":[
        "smog",
        "check"
    ],
    "wof:name":"Best Smog Test Only Center",
    "wof:placetype":"venue"
},
  "geometry": {"coordinates":[-118.32632700000001,33.897099],"type":"Point"}
}