{
  "type": "Feature",
  "properties": {
    "addr:full":"7285 Ridgeline Dr Riverside CA 92509",
    "addr:housenumber":"7285",
    "addr:postcode":"92509",
    "addr:street":"Ridgeline Dr",
    "iso:country":"US",
    "sg:address":"7285 Ridgeline Dr",
    "sg:city":"Riverside",
    "sg:classifiers":[
        {
            "category":"Wholesale",
            "subcategory":"Electrical",
            "type":"Manufacturing & Wholesale Goods"
        }
    ],
    "sg:phone":"+1 951 681 6835",
    "sg:postcode":"92509",
    "sg:province":"CA",
    "sg:tags":[
        "communication",
        "radio",
        "system"
    ],
    "wof:name":"Radio Communication Svc",
    "wof:placetype":"venue"
},
  "geometry": {"coordinates":[-117.44152099999999,33.989258],"type":"Point"}
}