{
  "type": "Feature",
  "properties": {
    "iso:country":"US",
    "sg:address":"3875 Wilshire Blvd",
    "sg:city":"Los Angeles",
    "sg:classifiers":[
        {
            "category":"Health Services",
            "subcategory":"Chiropractor",
            "type":"Services"
        }
    ],
    "sg:phone":"+1 213 382 8620",
    "sg:postcode":"90010",
    "sg:province":"CA",
    "wof:name":"Pine Clinic",
    "wof:placetype":"venue"
},
  "geometry": {"coordinates":[-118.31157,34.061693],"type":"Point"}
}