{
  "type": "Feature",
  "properties": {
    "iso:country":"US",
    "sg:address":"3075 Lakeshore Blvd",
    "sg:city":"Lakeport",
    "sg:classifiers":[
        {
            "category":"Wholesale",
            "subcategory":"Office Equipment",
            "type":"Manufacturing & Wholesale Goods"
        }
    ],
    "sg:phone":"+1 707 262 1010",
    "sg:postcode":"95453",
    "sg:province":"CA",
    "sg:tags":[
        "vault",
        "safe"
    ],
    "wof:name":"A 1 Alarm & Lock",
    "wof:placetype":"venue"
},
  "geometry": {"coordinates":[-122.91316500000001,39.073468],"type":"Point"}
}