{
  "type": "Feature",
  "properties": {
    "addr:full":"290 Division #403 San Francisco CA 94103",
    "addr:housenumber":"290",
    "addr:postcode":"94103",
    "addr:street":"Division # 403",
    "iso:country":"US",
    "sg:address":"290 Division #403",
    "sg:city":"San Francisco",
    "sg:classifiers":[
        {
            "category":"Professional",
            "subcategory":"Computer Services",
            "type":"Services"
        }
    ],
    "sg:postcode":"94103",
    "sg:province":"CA",
    "sg:tags":[
        "motionloft",
        "real-world",
        "analytics",
        "sensor"
    ],
    "sg:website":"http://www.motionloft.com",
    "wof:name":"MotionLoft",
    "wof:placetype":"venue"
},
  "geometry": {"coordinates":[-122.40987800000001,37.769183],"type":"Point"}
}