{
  "type": "Feature",
  "properties": {
    "iso:country":"US",
    "sg:address":"15416 Longworth Ave",
    "sg:city":"Norwalk",
    "sg:classifiers":[
        {
            "category":"Shopping",
            "subcategory":"Stationery & Office Supplies",
            "type":"Retail Goods"
        }
    ],
    "sg:phone":"+1 562 595 1296",
    "sg:postcode":"90650",
    "sg:province":"CA",
    "sg:tags":[
        "equipment"
    ],
    "wof:name":"Mercury Office Machines",
    "wof:placetype":"venue"
},
  "geometry": {"coordinates":[-118.092574,33.890727],"type":"Point"}
}