{
  "type": "Feature",
  "properties": {
    "addr:full":"5550 Balboa Arms Drive Ofc San Diego CA 92117",
    "addr:housenumber":"5550",
    "addr:postcode":"92117",
    "addr:street":"Balboa Arms Drive",
    "iso:country":"US",
    "sg:address":"5550 Balboa Arms Drive Ofc",
    "sg:city":"San Diego",
    "sg:classifiers":[
        {
            "category":"Real Estate",
            "subcategory":"Real Estate Operator",
            "type":"Services"
        }
    ],
    "sg:phone":"+1 858 279 6420",
    "sg:postcode":"92117",
    "sg:province":"CA",
    "sg:tags":[
        "apartment"
    ],
    "wof:name":"Chateau Apartments",
    "wof:placetype":"venue"
},
  "geometry": {"coordinates":[-117.177487,32.822436],"type":"Point"}
}