{
  "type": "Feature",
  "properties": {
    "addr:full":"9143 Paradise Park Dr Lakeside CA 92040",
    "addr:housenumber":"9143",
    "addr:postcode":"92040",
    "addr:street":"Paradise Park Dr",
    "iso:country":"US",
    "sg:address":"9143 Paradise Park Dr",
    "sg:city":"Lakeside",
    "sg:classifiers":[
        {
            "category":"Professional",
            "subcategory":"Art Services",
            "type":"Services"
        }
    ],
    "sg:phone":"+1 619 561 2596",
    "sg:postcode":"92040",
    "sg:province":"CA",
    "sg:tags":[
        "graphic",
        "designer"
    ],
    "wof:name":"Technical Arts",
    "wof:placetype":"venue"
},
  "geometry": {"coordinates":[-116.938603,32.839883],"type":"Point"}
}