{
  "type": "Feature",
  "properties": {
    "addr:full":"2920 23rd Ave San Francisco CA 94132",
    "addr:housenumber":"2920",
    "addr:postcode":"94132",
    "addr:street":"23Rd Ave",
    "iso:country":"US",
    "sg:address":"2920 23rd Ave",
    "sg:city":"San Francisco",
    "sg:classifiers":[
        {
            "category":"Professional",
            "type":"Services"
        }
    ],
    "sg:phone":"+1 415 759 9725",
    "sg:postcode":"94132",
    "sg:province":"CA",
    "wof:name":"Central Pump Station Trailer",
    "wof:placetype":"venue"
},
  "geometry": {"coordinates":[-122.479179,37.732963],"type":"Point"}
}