{
  "type": "Feature",
  "properties": {
    "addr:full":"225 S Lake Ave Fl 3 Pasadena CA 91101",
    "addr:housenumber":"225;3",
    "addr:postcode":"91101",
    "addr:street":"S Lake Ave Fl",
    "iso:country":"US",
    "sg:address":"225 S Lake Ave Fl 3",
    "sg:city":"Pasadena",
    "sg:classifiers":[
        {
            "category":"Professional",
            "subcategory":"Lawyer & Legal Services",
            "type":"Services"
        }
    ],
    "sg:phone":"+1 213 438 0800",
    "sg:postcode":"91101",
    "sg:province":"CA",
    "wof:name":"McNally & Bhavsar-Attys At Law",
    "wof:placetype":"venue"
},
  "geometry": {"coordinates":[-118.13200399999999,34.141899],"type":"Point"}
}