{
  "type": "Feature",
  "properties": {
    "addr:full":"14528 Bonelli St City Of Industry CA 91746",
    "addr:housenumber":"14528",
    "addr:postcode":"91746",
    "addr:street":"Bonelli St",
    "iso:country":"US",
    "sg:address":"14528 Bonelli St",
    "sg:city":"City Of Industry",
    "sg:classifiers":[
        {
            "category":"Autos & Motor Vehicles",
            "subcategory":"Auto Supplies",
            "type":"Retail Goods"
        }
    ],
    "sg:phone":"+1 626 961 5775",
    "sg:postcode":"91746",
    "sg:province":"CA",
    "sg:tags":[
        "automobile",
        "parts"
    ],
    "wof:name":"Centric Parts Inc",
    "wof:placetype":"venue"
},
  "geometry": {"coordinates":[-117.988871,34.027226],"type":"Point"}
}