{
  "type": "Feature",
  "properties": {
    "addr:full":"1666 Maryland St Redwood City CA 94061",
    "addr:housenumber":"1666",
    "addr:postcode":"94061",
    "addr:street":"Maryland St",
    "iso:country":"US",
    "sg:address":"1666 Maryland St",
    "sg:city":"Redwood City",
    "sg:classifiers":[
        {
            "category":"Manufacturing",
            "subcategory":"Metals",
            "type":"Manufacturing & Wholesale Goods"
        }
    ],
    "sg:phone":"+1 650 369 5896",
    "sg:postcode":"94061",
    "sg:province":"CA",
    "sg:tags":[
        "steel"
    ],
    "wof:name":"D W Haussler Specialties",
    "wof:placetype":"venue"
},
  "geometry": {"coordinates":[-122.237893,37.455373],"type":"Point"}
}