{
  "type": "Feature",
  "properties": {
    "addr:full":"1916 N Long Beach Blvd Compton CA 90221",
    "addr:housenumber":"1916",
    "addr:postcode":"90221",
    "addr:street":"N Long Beach Blvd",
    "iso:country":"US",
    "sg:address":"1916 N Long Beach Blvd",
    "sg:city":"Compton",
    "sg:classifiers":[
        {
            "category":"Shopping",
            "subcategory":"Discount & Variety Stores",
            "type":"Retail Goods"
        },
        {
            "category":"Food & Beverages",
            "subcategory":"Groceries & Convenience Stores",
            "type":"Retail Goods"
        }
    ],
    "sg:phone":"+1 310 639 3264",
    "sg:postcode":"90221",
    "sg:province":"CA",
    "sg:tags":[
        "grocer",
        "merchandise"
    ],
    "wof:name":"Ho's Gift",
    "wof:placetype":"venue"
},
  "geometry": {"coordinates":[-118.209,33.908798],"type":"Point"}
}