{
  "type": "Feature",
  "properties": {
    "addr:full":"718 University Ave Los Gatos CA 95032",
    "addr:housenumber":"718",
    "addr:postcode":"95032",
    "addr:street":"University Ave",
    "iso:country":"US",
    "sg:address":"718 University Ave",
    "sg:city":"Los Gatos",
    "sg:classifiers":[
        {
            "category":"Health Services",
            "subcategory":"Doctor",
            "type":"Services"
        }
    ],
    "sg:phone":"+1 408 354 2114",
    "sg:postcode":"95032",
    "sg:province":"CA",
    "wof:name":"Olson Allan MD",
    "wof:placetype":"venue"
},
  "geometry": {"coordinates":[-121.974998,37.238602],"type":"Point"}
}