{
  "type": "Feature",
  "properties": {
    "addr:full":"815 N Batavia St Orange CA 92868",
    "addr:housenumber":"815",
    "addr:postcode":"92868",
    "addr:street":"N Batavia St",
    "iso:country":"US",
    "sg:address":"815 N Batavia St",
    "sg:city":"Orange",
    "sg:classifiers":[
        {
            "category":"Personal",
            "type":"Services"
        }
    ],
    "sg:phone":"+1 714 288 1900",
    "sg:postcode":"92868",
    "sg:province":"CA",
    "sg:tags":[
        "towing"
    ],
    "wof:name":"A 1 Auto Recycling",
    "wof:placetype":"venue"
},
  "geometry": {"coordinates":[-117.86199999999999,33.801601],"type":"Point"}
}