{
  "type": "Feature",
  "properties": {
    "iso:country":"US",
    "sg:address":"14296 San Benito St",
    "sg:city":"Fontana",
    "sg:classifiers":[
        {
            "category":"Autos & Motor Vehicles",
            "subcategory":"Automobile Sales",
            "type":"Retail Goods"
        }
    ],
    "sg:phone":"+1 909 855 1376",
    "sg:postcode":"92336",
    "sg:province":"CA",
    "sg:tags":[
        "used"
    ],
    "wof:name":"A & A Auto Sales",
    "wof:placetype":"venue"
},
  "geometry": {"coordinates":[-117.49158,34.111581],"type":"Point"}
}