{
  "type": "Feature",
  "properties": {
    "addr:full":"5315 Ave 384 Dinuba CA 93618",
    "addr:housenumber":"384",
    "addr:postcode":"93618",
    "addr:street":"5315 Ave",
    "iso:country":"US",
    "sg:address":"5315 Ave 384",
    "sg:city":"Dinuba",
    "sg:classifiers":[
        {
            "category":"Health Services",
            "subcategory":"Health Practitioner",
            "type":"Services"
        }
    ],
    "sg:phone":"+1 559 638 1028",
    "sg:postcode":"93618",
    "sg:province":"CA",
    "sg:tags":[
        "psychologist"
    ],
    "wof:name":"Dean Kliewer PHD",
    "wof:placetype":"venue"
},
  "geometry": {"coordinates":[-119.454628,36.488392],"type":"Point"}
}