{
  "type": "Feature",
  "properties": {
    "addr:full":"707 W Hornet Ave Alameda CA 94501",
    "addr:housenumber":"707",
    "addr:postcode":"94501",
    "addr:street":"W Hornet Ave",
    "iso:country":"US",
    "sg:address":"707 W Hornet Ave",
    "sg:city":"Alameda",
    "sg:classifiers":[
        {
            "category":"Landmark",
            "subcategory":"Historic",
            "type":"Public Place"
        },
        {
            "category":"Retail",
            "subcategory":"Event Space",
            "type":"Services"
        },
        {
            "category":"Museum",
            "type":"Entertainment"
        }
    ],
    "sg:phone":"+1 510 521 8448",
    "sg:postcode":"94501",
    "sg:province":"CA",
    "sg:tags":[
        "building",
        "venue",
        "historical"
    ],
    "sg:website":"www.uss-hornet.org",
    "wof:name":"USS Hornet",
    "wof:placetype":"venue"
},
  "geometry": {"coordinates":[-122.299601,37.772306],"type":"Point"}
}