{
  "type": "Feature",
  "properties": {
    "addr:full":"2410 Roosevelt Berkeley CA 94703",
    "addr:housenumber":"2410",
    "addr:postcode":"94703",
    "addr:street":"Roosevelt",
    "iso:country":"US",
    "sg:address":"2410 Roosevelt",
    "sg:city":"Berkeley",
    "sg:classifiers":[
        {
            "category":"Home & Garden",
            "subcategory":"Building Materials",
            "type":"Retail Goods"
        }
    ],
    "sg:phone":"+1 510 222 4447",
    "sg:postcode":"94703",
    "sg:province":"CA",
    "sg:tags":[
        "equipment",
        "fixture",
        "lighting"
    ],
    "wof:name":"The Christmas Light Pros",
    "wof:placetype":"venue"
},
  "geometry": {"coordinates":[-122.276005,37.864255],"type":"Point"}
}