{
  "type": "Feature",
  "properties": {
    "iso:country":"US",
    "sg:address":"7220 S Central Ave",
    "sg:city":"Los Angeles",
    "sg:classifiers":[
        {
            "category":"Food & Beverages",
            "subcategory":"Groceries & Convenience Stores",
            "type":"Retail Goods"
        }
    ],
    "sg:phone":"+1 323 587 8438",
    "sg:postcode":"90001",
    "sg:province":"CA",
    "sg:tags":[
        "grocer"
    ],
    "wof:name":"Sunshine Markets",
    "wof:placetype":"venue"
},
  "geometry": {"coordinates":[-118.25632,33.974077],"type":"Point"}
}