{
  "type": "Feature",
  "properties": {
    "addr:full":"1725 Decoto Rd Union City CA 94587",
    "addr:housenumber":"1725",
    "addr:postcode":"94587",
    "addr:street":"Decoto Rd",
    "iso:country":"US",
    "sg:address":"1725 Decoto Rd",
    "sg:city":"Union City",
    "sg:classifiers":[
        {
            "category":"Wholesale",
            "subcategory":"Groceries",
            "type":"Manufacturing & Wholesale Goods"
        }
    ],
    "sg:phone":"+1 510 489 7788",
    "sg:postcode":"94587",
    "sg:province":"CA",
    "wof:name":"Chung Chou City Inc",
    "wof:placetype":"venue"
},
  "geometry": {"coordinates":[-122.021078,37.588877],"type":"Point"}
}