{
  "type": "Feature",
  "properties": {
    "iso:country":"US",
    "sg:address":"1980 Broadway",
    "sg:city":"Placerville",
    "sg:classifiers":[
        {
            "category":"Health Services",
            "subcategory":"Doctor",
            "type":"Services"
        },
        {
            "category":"Health Services",
            "subcategory":"Chiropractor",
            "type":"Services"
        }
    ],
    "sg:phone":"+1 530 622 3696",
    "sg:postcode":"95667",
    "sg:province":"CA",
    "sg:tags":[
        "orthopedist"
    ],
    "wof:name":"Advanced Spinal Decompression Center",
    "wof:placetype":"venue"
},
  "geometry": {"coordinates":[-120.756519,38.731672],"type":"Point"}
}