{
  "type": "Feature",
  "properties": {
    "addr:full":"2255 N Lakewood Blvd Long Beach CA 90815",
    "addr:housenumber":"2255",
    "addr:postcode":"90815",
    "addr:street":"N Lakewood Blvd",
    "iso:country":"US",
    "sg:address":"2255 N Lakewood Blvd",
    "sg:city":"Long Beach",
    "sg:classifiers":[
        {
            "category":"Health Services",
            "subcategory":"Doctor",
            "type":"Services"
        }
    ],
    "sg:phone":"+1 562 498 8000",
    "sg:postcode":"90815",
    "sg:province":"CA",
    "sg:tags":[
        "physician",
        "surgeon"
    ],
    "wof:name":"Ronald J Philipp DO",
    "wof:placetype":"venue"
},
  "geometry": {"coordinates":[-118.14276,33.79849],"type":"Point"}
}