{
  "type": "Feature",
  "properties": {
    "iso:country":"US",
    "sg:address":"1835 Newport Blvd",
    "sg:city":"Costa Mesa",
    "sg:classifiers":[
        {
            "category":"Building & Trades",
            "subcategory":"Construction",
            "type":"Services"
        }
    ],
    "sg:phone":"+1 949 566 8507",
    "sg:postcode":"92627",
    "sg:province":"CA",
    "sg:tags":[
        "contractor"
    ],
    "sg:website":"www.costamesaremodeling.net",
    "wof:name":"Best Remodeling",
    "wof:placetype":"venue"
},
  "geometry": {"coordinates":[-117.920119,33.642481],"type":"Point"}
}