{
  "type": "Feature",
  "properties": {
    "addr:full":"2929 Loma Vista Rd Ventura CA 93003",
    "addr:housenumber":"2929",
    "addr:postcode":"93003",
    "addr:street":"Loma Vista Rd",
    "iso:country":"US",
    "sg:address":"2929 Loma Vista Rd",
    "sg:city":"Ventura",
    "sg:classifiers":[
        {
            "category":"Health Services",
            "subcategory":"Doctor",
            "type":"Services"
        }
    ],
    "sg:phone":"+1 805 653 5741",
    "sg:postcode":"93003",
    "sg:province":"CA",
    "sg:tags":[
        "physician",
        "family",
        "practice",
        "surgeons",
        "medicine",
        "surgeon"
    ],
    "wof:name":"Thomas Mc Breen Md",
    "wof:placetype":"venue"
},
  "geometry": {"coordinates":[-119.25708400000001,34.275456],"type":"Point"}
}