{
  "type": "Feature",
  "properties": {
    "addr:full":"1120 Bayview Ave Napa CA 94559",
    "addr:housenumber":"1120",
    "addr:postcode":"94559",
    "addr:street":"Bayview Ave",
    "iso:country":"US",
    "sg:address":"1120 Bayview Ave",
    "sg:city":"Napa",
    "sg:classifiers":[
        {
            "category":"Farming",
            "subcategory":"Farm & Veterinary Services",
            "type":"Manufacturing & Wholesale Goods"
        }
    ],
    "sg:phone":"+1 707 226 8931",
    "sg:postcode":"94559",
    "sg:province":"CA",
    "sg:tags":[
        "management"
    ],
    "wof:name":"Fournier Vineyards",
    "wof:placetype":"venue"
},
  "geometry": {"coordinates":[-122.323736,38.234592],"type":"Point"}
}