{
  "type": "Feature",
  "properties": {
    "iso:country":"US",
    "sg:address":"35826 Panorama Dr",
    "sg:city":"Yucaipa",
    "sg:classifiers":[
        {
            "category":"Professional",
            "subcategory":"Computer Services",
            "type":"Services"
        }
    ],
    "sg:phone":"+1 909 797 7694",
    "sg:postcode":"92399",
    "sg:province":"CA",
    "sg:tags":[
        "scanning"
    ],
    "wof:name":"DSI Digital Sports Imaging",
    "wof:placetype":"venue"
},
  "geometry": {"coordinates":[-117.025486,34.043691],"type":"Point"}
}