{
  "type": "Feature",
  "properties": {
    "iso:country":"US",
    "sg:address":"245 Fairmount Ave",
    "sg:city":"Oakland",
    "sg:classifiers":[
        {
            "category":"Professional",
            "type":"Services"
        }
    ],
    "sg:phone":"+1 510 763 5677",
    "sg:postcode":"94611",
    "sg:province":"CA",
    "wof:name":"Agreenet LLC",
    "wof:placetype":"venue"
},
  "geometry": {"coordinates":[-122.25979,37.817906],"type":"Point"}
}