{
  "type": "Feature",
  "properties": {
    "iso:country":"US",
    "sg:address":"819 Santee St",
    "sg:city":"Los Angeles",
    "sg:classifiers":[
        {
            "category":"Wholesale",
            "subcategory":"Home Furnishings",
            "type":"Manufacturing & Wholesale Goods"
        }
    ],
    "sg:phone":"+1 213 683 8320",
    "sg:postcode":"90014",
    "sg:province":"CA",
    "wof:name":"Margaret Sarmast",
    "wof:placetype":"venue"
},
  "geometry": {"coordinates":[-118.25313800000001,34.040338],"type":"Point"}
}