{
  "type": "Feature",
  "properties": {
    "iso:country":"US",
    "sg:address":"101 E Chestnut Ave",
    "sg:city":"Lompoc",
    "sg:classifiers":[
        {
            "category":"Shopping",
            "subcategory":"Clothing, Apparel, & Fashions",
            "type":"Retail Goods"
        }
    ],
    "sg:phone":"+1 805 735 3464",
    "sg:postcode":"93436",
    "sg:province":"CA",
    "sg:tags":[
        "western"
    ],
    "wof:name":"Gracian Feed Pet & Western Wr",
    "wof:placetype":"venue"
},
  "geometry": {"coordinates":[-120.457172,34.642226],"type":"Point"}
}