{
  "type": "Feature",
  "properties": {
    "iso:country":"US",
    "sg:address":"225 Lotus Ln",
    "sg:city":"Modesto",
    "sg:classifiers":[
        {
            "category":"Building & Trades",
            "subcategory":"Plumbing",
            "type":"Services"
        }
    ],
    "sg:phone":"+1 209 526 6981",
    "sg:postcode":"95350",
    "sg:province":"CA",
    "sg:tags":[
        "contractor"
    ],
    "wof:name":"Thorington Plumbing",
    "wof:placetype":"venue"
},
  "geometry": {"coordinates":[-120.996686,37.672502],"type":"Point"}
}