{
  "type": "Feature",
  "properties": {
    "addr:full":"525 W 90th St Los Angeles CA 90044",
    "addr:housenumber":"525",
    "addr:postcode":"90044",
    "addr:street":"W 90Th St",
    "iso:country":"US",
    "sg:address":"525 W 90th St",
    "sg:city":"Los Angeles",
    "sg:classifiers":[
        {
            "category":"Manufacturing",
            "subcategory":"Printing",
            "type":"Manufacturing & Wholesale Goods"
        }
    ],
    "sg:phone":"+1 310 355 0850",
    "sg:postcode":"90044",
    "sg:province":"CA",
    "sg:tags":[
        "organization",
        "religious",
        "publishing"
    ],
    "wof:name":"Spiritual Pieces",
    "wof:placetype":"venue"
},
  "geometry": {"coordinates":[-118.28427600000001,33.955161],"type":"Point"}
}