{
  "type": "Feature",
  "properties": {
    "iso:country":"US",
    "sg:address":"525 W 90th St",
    "sg:city":"Los Angeles",
    "sg:classifiers":[
        {
            "category":"Manufacturing",
            "subcategory":"Printing",
            "type":"Manufacturing & Wholesale Goods"
        }
    ],
    "sg:phone":"+1 310 355 0850",
    "sg:postcode":"90044",
    "sg:province":"CA",
    "sg:tags":[
        "organization",
        "religious",
        "publishing"
    ],
    "wof:name":"Spiritual Pieces",
    "wof:placetype":"venue"
},
  "geometry": {"coordinates":[-118.284276,33.955161],"type":"Point"}
}