{
  "type": "Feature",
  "properties": {
    "addr:full":"79 Daily Drive #160 Camarillo CA 93010",
    "addr:housenumber":"79",
    "addr:postcode":"93010",
    "addr:street":"Daily Drive # 160",
    "iso:country":"US",
    "sg:address":"79 Daily Drive #160",
    "sg:city":"Camarillo",
    "sg:classifiers":[
        {
            "category":"Professional",
            "subcategory":"Art Services",
            "type":"Services"
        }
    ],
    "sg:phone":"+1 805 512 5200",
    "sg:postcode":"93010",
    "sg:province":"CA",
    "sg:tags":[
        "graphic",
        "design"
    ],
    "wof:name":"3 A.M. Graphics",
    "wof:placetype":"venue"
},
  "geometry": {"coordinates":[-119.068313,34.221813],"type":"Point"}
}