{
  "type": "Feature",
  "properties": {
    "iso:country":"US",
    "sg:address":"1007 S Railroad Ave",
    "sg:city":"San Mateo",
    "sg:classifiers":[
        {
            "category":"Autos & Motor Vehicles",
            "subcategory":"Auto Supplies",
            "type":"Retail Goods"
        }
    ],
    "sg:phone":"+1 650 287 2600",
    "sg:postcode":"94402",
    "sg:province":"CA",
    "sg:tags":[
        "glass"
    ],
    "wof:name":"Best Image",
    "wof:placetype":"venue"
},
  "geometry": {"coordinates":[-122.31556399999999,37.560773],"type":"Point"}
}