{
  "type": "Feature",
  "properties": {
    "addr:full":"56 E Holly St Pasadena CA 91103",
    "addr:housenumber":"56",
    "addr:postcode":"91103",
    "addr:street":"E Holly St",
    "iso:country":"US",
    "sg:address":"56 E Holly St",
    "sg:city":"Pasadena",
    "sg:classifiers":[
        {
            "category":"Professional",
            "type":"Services"
        }
    ],
    "sg:phone":"+1 626 796 7399",
    "sg:postcode":"91103",
    "sg:province":"CA",
    "wof:name":"Johnsons House Inc",
    "wof:placetype":"venue"
},
  "geometry": {"coordinates":[-118.149169,34.147578],"type":"Point"}
}