{
  "type": "Feature",
  "properties": {
    "iso:country":"US",
    "sg:address":"6740 Folkstone Way",
    "sg:city":"Elk Grove",
    "sg:classifiers":[
        {
            "category":"Health Services",
            "subcategory":"Health Practitioner",
            "type":"Services"
        }
    ],
    "sg:phone":"+1 916 684 5555",
    "sg:postcode":"95758",
    "sg:province":"CA",
    "sg:tags":[
        "therapist",
        "physical"
    ],
    "wof:name":"Physical Therapy Home Svc",
    "wof:placetype":"venue"
},
  "geometry": {"coordinates":[-121.424548,38.415091],"type":"Point"}
}