{
  "type": "Feature",
  "properties": {
    "iso:country":"US",
    "sg:address":"1420 Elsie St",
    "sg:city":"Modesto",
    "sg:classifiers":[
        {
            "category":"Real Estate",
            "subcategory":"Real Estate Operator",
            "type":"Services"
        }
    ],
    "sg:phone":"+1 209 521 6020",
    "sg:postcode":"95351",
    "sg:province":"CA",
    "sg:tags":[
        "boarding",
        "house"
    ],
    "wof:name":"Welcome Home Room & Board",
    "wof:placetype":"venue"
},
  "geometry": {"coordinates":[-121.011567,37.622377],"type":"Point"}
}