{
  "type": "Feature",
  "properties": {
    "iso:country":"US",
    "sg:address":"1013 Woodcrest Ave",
    "sg:city":"Brea",
    "sg:classifiers":[
        {
            "category":"Home & Garden",
            "subcategory":"Home Furnishings",
            "type":"Retail Goods"
        }
    ],
    "sg:phone":"+1 714 671 7872",
    "sg:postcode":"92821",
    "sg:province":"CA",
    "sg:tags":[
        "house",
        "decor"
    ],
    "sg:website":"http://www.asiageneral.com",
    "wof:name":"Asia General Corp",
    "wof:placetype":"venue"
},
  "geometry": {"coordinates":[-117.912043,33.945345],"type":"Point"}
}