{
  "type": "Feature",
  "properties": {
    "iso:country":"US",
    "sg:address":"534 Sunbeam Rd",
    "sg:city":"Lompoc",
    "sg:classifiers":[
        {
            "category":"Social Services",
            "subcategory":"Child Care",
            "type":"Services"
        }
    ],
    "sg:phone":"+1 805 733 4232",
    "sg:postcode":"93436",
    "sg:province":"CA",
    "sg:tags":[
        "nursery",
        "day"
    ],
    "wof:name":"Special Time Child Care",
    "wof:placetype":"venue"
},
  "geometry": {"coordinates":[-120.473237,34.696182],"type":"Point"}
}