{
  "type": "Feature",
  "properties": {
    "iso:country":"US",
    "sg:address":"804 Harbor Blvd",
    "sg:city":"West Sacramento",
    "sg:classifiers":[
        {
            "category":"Health Services",
            "subcategory":"Doctor",
            "type":"Services"
        }
    ],
    "sg:phone":"+1 916 371 1616",
    "sg:postcode":"95691",
    "sg:province":"CA",
    "wof:name":"Greenberg Arnold MD Inc",
    "wof:placetype":"venue"
},
  "geometry": {"coordinates":[-121.548925,38.579087],"type":"Point"}
}