{
  "type": "Feature",
  "properties": {
    "addr:full":"982 Barstow Ave Clovis CA 93612",
    "addr:housenumber":"982",
    "addr:postcode":"93612",
    "addr:street":"Barstow Ave",
    "iso:country":"US",
    "sg:address":"982 Barstow Ave",
    "sg:city":"Clovis",
    "sg:classifiers":[
        {
            "category":"Retail",
            "subcategory":"Auto Repair",
            "type":"Services"
        }
    ],
    "sg:phone":"+1 559 299 0685",
    "sg:postcode":"93612",
    "sg:province":"CA",
    "sg:tags":[
        "body",
        "automobile",
        "painting"
    ],
    "wof:name":"Bruce Williams Auto Body",
    "wof:placetype":"venue"
},
  "geometry": {"coordinates":[-119.696107,36.815699],"type":"Point"}
}