{
  "type": "Feature",
  "properties": {
    "addr:full":"1600-1612 3rd Ave Oakland CA 94606",
    "addr:housenumber":"1600-1612",
    "addr:postcode":"94606",
    "addr:street":"3Rd Ave",
    "iso:country":"US",
    "sg:address":"1600-1612 3rd Ave",
    "sg:city":"Oakland",
    "sg:classifiers":[
        {
            "category":"Real Estate",
            "subcategory":"Real Estate Operator",
            "type":"Services"
        }
    ],
    "sg:phone":"+1 510 444 1856",
    "sg:postcode":"94606",
    "sg:province":"CA",
    "sg:tags":[
        "apartment"
    ],
    "wof:name":"Vue De Lac Apartments",
    "wof:placetype":"venue"
},
  "geometry": {"coordinates":[-122.253457,37.798645],"type":"Point"}
}