{
  "type": "Feature",
  "properties": {
    "addr:full":"2218 Loma Vista Dr Sacramento CA 95825",
    "addr:housenumber":"2218",
    "addr:postcode":"95825",
    "addr:street":"Loma Vista Dr",
    "iso:country":"US",
    "sg:address":"2218 Loma Vista Dr",
    "sg:city":"Sacramento",
    "sg:classifiers":[
        {
            "category":"Professional",
            "subcategory":"Management & Consulting",
            "type":"Services"
        }
    ],
    "sg:phone":"+1 916 484 3560",
    "sg:postcode":"95825",
    "sg:province":"CA",
    "sg:tags":[
        "fuel"
    ],
    "wof:name":"Trust Management Svc",
    "wof:placetype":"venue"
},
  "geometry": {"coordinates":[-121.40048899999999,38.60564],"type":"Point"}
}