{
  "type": "Feature",
  "properties": {
    "addr:full":"650 Automall Dr Roseville CA 95661",
    "addr:housenumber":"650",
    "addr:postcode":"95661",
    "addr:street":"Automall Dr",
    "iso:country":"US",
    "sg:address":"650 Automall Dr",
    "sg:city":"Roseville",
    "sg:classifiers":[
        {
            "category":"Autos & Motor Vehicles",
            "subcategory":"Automobile Sales",
            "type":"Retail Goods"
        },
        {
            "category":"Retail",
            "subcategory":"Auto Repair",
            "type":"Services"
        }
    ],
    "sg:phone":"+1 916 969 3600",
    "sg:postcode":"95661",
    "sg:province":"CA",
    "sg:tags":[
        "car",
        "new"
    ],
    "wof:name":"Ford Authorized Sales/Service",
    "wof:placetype":"venue"
},
  "geometry": {"coordinates":[-121.254822,38.750083],"type":"Point"}
}