{
  "type": "Feature",
  "properties": {
    "iso:country":"US",
    "sg:address":"8523 Flight Ave",
    "sg:city":"Los Angeles",
    "sg:classifiers":[
        {
            "category":"Local Transit",
            "type":"Transportation"
        }
    ],
    "sg:phone":"+1 310 216 6911",
    "sg:postcode":"90045",
    "sg:province":"CA",
    "wof:name":"Metropolitan Express Shuttle",
    "wof:placetype":"venue"
},
  "geometry": {"coordinates":[-118.391379,33.960862],"type":"Point"}
}