{
  "type": "Feature",
  "properties": {
    "iso:country":"US",
    "sg:address":"1103 E Main St",
    "sg:city":"Alhambra",
    "sg:classifiers":[
        {
            "category":"Personal",
            "subcategory":"Beauty Salon",
            "type":"Services"
        }
    ],
    "sg:phone":"+1 626 291 5045",
    "sg:postcode":"91801",
    "sg:province":"CA",
    "wof:name":"Avenue Artist Coiffures",
    "wof:placetype":"venue"
},
  "geometry": {"coordinates":[-118.11494999999999,34.100905],"type":"Point"}
}