{
  "type": "Feature",
  "properties": {
    "iso:country":"US",
    "sg:address":"500 E San Jose Ave Apt E",
    "sg:city":"Burbank",
    "sg:classifiers":[
        {
            "category":"Wholesale",
            "subcategory":"Non-durable Goods",
            "type":"Manufacturing & Wholesale Goods"
        }
    ],
    "sg:phone":"+1 818 859 0675",
    "sg:postcode":"91501",
    "sg:province":"CA",
    "sg:tags":[
        "dry",
        "goods-wholesale"
    ],
    "wof:name":"Ams Wholesale Distribution",
    "wof:placetype":"venue"
},
  "geometry": {"coordinates":[-118.308971,34.187243],"type":"Point"}
}