{
  "type": "Feature",
  "properties": {
    "iso:country":"US",
    "sg:address":"5571 Sepulveda Blvd",
    "sg:city":"Culver City",
    "sg:classifiers":[
        {
            "category":"Bars & Pubs",
            "subcategory":"Sports Bar",
            "type":"Food & Drink"
        }
    ],
    "sg:phone":"+1 310 397 7317",
    "sg:postcode":"90230",
    "sg:province":"CA",
    "wof:name":"Leo's Sports Grill",
    "wof:placetype":"venue"
},
  "geometry": {"coordinates":[-118.395253,33.991171],"type":"Point"}
}