{
  "type": "Feature",
  "properties": {
    "addr:full":"9930 E McKinley Ave Fresno CA 93727",
    "addr:housenumber":"9930",
    "addr:postcode":"93727",
    "addr:street":"E Mckinley Ave",
    "iso:country":"US",
    "sg:address":"9930 E McKinley Ave",
    "sg:city":"Fresno",
    "sg:classifiers":[
        {
            "category":"Building & Trades",
            "subcategory":"Construction",
            "type":"Services"
        }
    ],
    "sg:phone":"+1 559 253 0227",
    "sg:postcode":"93727",
    "sg:province":"CA",
    "sg:tags":[
        "concrete",
        "pumping"
    ],
    "wof:name":"Kevin's Concrete Pumping",
    "wof:placetype":"venue"
},
  "geometry": {"coordinates":[-119.62188999999999,36.764814],"type":"Point"}
}