{
  "type": "Feature",
  "properties": {
    "addr:full":"1022 Mission Ave Oceanside CA 92054",
    "addr:housenumber":"1022",
    "addr:postcode":"92054",
    "addr:street":"Mission Ave",
    "iso:country":"US",
    "sg:address":"1022 Mission Ave",
    "sg:city":"Oceanside",
    "sg:classifiers":[
        {
            "category":"Arena",
            "subcategory":"Sports Club",
            "type":"Entertainment"
        }
    ],
    "sg:phone":"+1 760 722 3122",
    "sg:postcode":"92054",
    "sg:province":"CA",
    "sg:tags":[
        "martial art"
    ],
    "wof:name":"Team Quest Oceanside",
    "wof:placetype":"venue"
},
  "geometry": {"coordinates":[-117.375013,33.198499],"type":"Point"}
}