{
  "type": "Feature",
  "properties": {
    "addr:full":"3550 Wilshire Blvd Ste 1280 Los Angeles CA 90010",
    "addr:housenumber":"3550;1280",
    "addr:postcode":"90010",
    "addr:street":"Wilshire Blvd Ste",
    "iso:country":"US",
    "sg:address":"3550 Wilshire Blvd Ste 1280",
    "sg:city":"Los Angeles",
    "sg:classifiers":[
        {
            "category":"Banks & Credit Unions",
            "subcategory":"Investment Brokerage",
            "type":"Services"
        }
    ],
    "sg:phone":"+1 213 380 6388",
    "sg:postcode":"90010",
    "sg:province":"CA",
    "sg:tags":[
        "investing"
    ],
    "sg:website":"www.chkcapital.com",
    "wof:name":"Chk Capital Group",
    "wof:placetype":"venue"
},
  "geometry": {"coordinates":[-118.302002,34.061699],"type":"Point"}
}