{
  "type": "Feature",
  "properties": {
    "iso:country":"US",
    "sg:address":"11620 Garvey Ave",
    "sg:city":"El Monte",
    "sg:classifiers":[
        {
            "category":"Food & Beverages",
            "subcategory":"Specialty",
            "type":"Retail Goods"
        }
    ],
    "sg:phone":"+1 626 448 6865",
    "sg:postcode":"91732",
    "sg:province":"CA",
    "sg:tags":[
        "herb"
    ],
    "wof:name":"Botanica Natural",
    "wof:placetype":"venue"
},
  "geometry": {"coordinates":[-118.025678,34.062833],"type":"Point"}
}