{
  "type": "Feature",
  "properties": {
    "addr:full":"1401 E Mission Ave Escondido CA 92027",
    "addr:housenumber":"1401",
    "addr:postcode":"92027",
    "addr:street":"E Mission Ave",
    "iso:country":"US",
    "sg:address":"1401 E Mission Ave",
    "sg:city":"Escondido",
    "sg:classifiers":[
        {
            "category":"Social Services",
            "subcategory":"Adult Care",
            "type":"Services"
        }
    ],
    "sg:phone":"+1 760 747 1843",
    "sg:postcode":"92027",
    "sg:province":"CA",
    "sg:tags":[
        "home",
        "residential"
    ],
    "wof:name":"Mission Home Care",
    "wof:placetype":"venue"
},
  "geometry": {"coordinates":[-117.06483799999999,33.139412],"type":"Point"}
}