{
  "type": "Feature",
  "properties": {
    "addr:full":"9021 Melrose Ave West Hollywood CA 90069",
    "addr:housenumber":"9021",
    "addr:postcode":"90069",
    "addr:street":"Melrose Ave",
    "iso:country":"US",
    "sg:address":"9021 Melrose Ave",
    "sg:city":"West Hollywood",
    "sg:classifiers":[
        {
            "category":"Communications",
            "subcategory":"Film & Video Production",
            "type":"Services"
        }
    ],
    "sg:phone":"+1 310 274 5932",
    "sg:postcode":"90069",
    "sg:province":"CA",
    "sg:tags":[
        "motion",
        "picture",
        "studio",
        "producer"
    ],
    "wof:name":"Avery Pix",
    "wof:placetype":"venue"
},
  "geometry": {"coordinates":[-118.38888300000001,34.08084],"type":"Point"}
}