{
  "type": "Feature",
  "properties": {
    "addr:full":"11171 State Hwy 145 Madera CA 93637",
    "addr:housenumber":"11171",
    "addr:postcode":"93637",
    "addr:street":"State Hwy 145",
    "iso:country":"US",
    "sg:address":"11171 State Hwy 145",
    "sg:city":"Madera",
    "sg:classifiers":[
        {
            "category":"Farming",
            "subcategory":"Farm",
            "type":"Manufacturing & Wholesale Goods"
        }
    ],
    "sg:phone":"+1 559 674 7821",
    "sg:postcode":"93637",
    "sg:province":"CA",
    "sg:tags":[
        "crop",
        "general"
    ],
    "wof:name":"Harold Tamura",
    "wof:placetype":"venue"
},
  "geometry": {"coordinates":[-120.055961,36.914134],"type":"Point"}
}