{
  "type": "Feature",
  "properties": {
    "iso:country":"US",
    "sg:address":"2218 W Middlefield Rd",
    "sg:city":"Mountain View",
    "sg:classifiers":[
        {
            "category":"Building & Trades",
            "subcategory":"Construction",
            "type":"Services"
        },
        {
            "category":"Wholesale",
            "subcategory":"Motor Vehicles",
            "type":"Manufacturing & Wholesale Goods"
        }
    ],
    "sg:phone":"+1 650 964 8992",
    "sg:postcode":"94043",
    "sg:province":"CA",
    "sg:tags":[
        "residential",
        "used",
        "automobile"
    ],
    "wof:name":"Action Autos",
    "wof:placetype":"venue"
},
  "geometry": {"coordinates":[-122.097545,37.412066],"type":"Point"}
}