{
  "type": "Feature",
  "properties": {
    "iso:country":"US",
    "sg:address":"5120 Robinwood Rd Ste A11",
    "sg:city":"Bonita",
    "sg:classifiers":[
        {
            "category":"Food & Beverages",
            "subcategory":"Liquor & Beverages",
            "type":"Retail Goods"
        },
        {
            "category":"Wholesale",
            "subcategory":"Wine & Distilled Alcoholic Beverages",
            "type":"Manufacturing & Wholesale Goods"
        }
    ],
    "sg:phone":"+1 619 475 6596",
    "sg:postcode":"91902",
    "sg:province":"CA",
    "sg:tags":[
        "beer",
        "ale",
        "broker",
        "store"
    ],
    "wof:name":"Robinwood Liquor & Market",
    "wof:placetype":"venue"
},
  "geometry": {"coordinates":[-117.028964,32.680857],"type":"Point"}
}