{
  "type": "Feature",
  "properties": {
    "addr:full":"1717 Seabright Ave Santa Cruz CA 95062",
    "addr:housenumber":"1717",
    "addr:postcode":"95062",
    "addr:street":"Seabright Ave",
    "iso:country":"US",
    "sg:address":"1717 Seabright Ave",
    "sg:city":"Santa Cruz",
    "sg:classifiers":[
        {
            "category":"Real Estate",
            "subcategory":"Real Estate Agent",
            "type":"Services"
        }
    ],
    "sg:phone":"+1 831 438 9300",
    "sg:postcode":"95062",
    "sg:province":"CA",
    "sg:tags":[
        "appraiser"
    ],
    "wof:name":"Appraisal Resources",
    "wof:placetype":"venue"
},
  "geometry": {"coordinates":[-122.010895,36.981129],"type":"Point"}
}