{
  "type": "Feature",
  "properties": {
    "iso:country":"US",
    "sg:address":"2772 18th St",
    "sg:city":"Sacramento",
    "sg:classifiers":[
        {
            "category":"Wholesale",
            "subcategory":"Computers",
            "type":"Manufacturing & Wholesale Goods"
        }
    ],
    "sg:phone":"+1 916 492 0626",
    "sg:postcode":"95818",
    "sg:province":"CA",
    "sg:tags":[
        "equipment"
    ],
    "wof:name":"Elitecom",
    "wof:placetype":"venue"
},
  "geometry": {"coordinates":[-121.49200399999999,38.554299],"type":"Point"}
}