{
  "type": "Feature",
  "properties": {
    "iso:country":"US",
    "sg:address":"26571 Briarwood Ln",
    "sg:city":"San Juan Capistrano",
    "sg:classifiers":[
        {
            "category":"Shopping",
            "type":"Retail Goods"
        }
    ],
    "sg:phone":"+1 949 347 7635",
    "sg:postcode":"92675",
    "sg:province":"CA",
    "sg:tags":[
        "merchandise"
    ],
    "wof:name":"Gold Coast Enterprises",
    "wof:placetype":"venue"
},
  "geometry": {"coordinates":[-117.666908,33.538468],"type":"Point"}
}