{
  "type": "Feature",
  "properties": {
    "addr:full":"1409 East Briggsmore Modesto CA 95355",
    "addr:housenumber":"1409",
    "addr:postcode":"ca 95355",
    "addr:street":"East Briggsmore",
    "iso:country":"US",
    "sg:address":"1409 East Briggsmore",
    "sg:city":"Modesto",
    "sg:classifiers":[
        {
            "category":"Health Services",
            "subcategory":"Doctor",
            "type":"Services"
        }
    ],
    "sg:phone":"+1 209 550 4720",
    "sg:postcode":"95355",
    "sg:province":"CA",
    "wof:name":"Christopher Domush, MD",
    "wof:placetype":"venue"
},
  "geometry": {"coordinates":[-120.973704,37.667351],"type":"Point"}
}