{
  "type": "Feature",
  "properties": {
    "addr:full":"7209 Arlington Ave Riverside CA 92503",
    "addr:housenumber":"7209",
    "addr:postcode":"92503",
    "addr:street":"Arlington Ave",
    "iso:country":"US",
    "sg:address":"7209 Arlington Ave",
    "sg:city":"Riverside",
    "sg:classifiers":[
        {
            "category":"Wholesale",
            "subcategory":"Sporting Goods",
            "type":"Manufacturing & Wholesale Goods"
        }
    ],
    "sg:phone":"+1 951 637 0546",
    "sg:postcode":"92503",
    "sg:province":"CA",
    "wof:name":"Gexco Enterprises",
    "wof:placetype":"venue"
},
  "geometry": {"coordinates":[-117.45248599999999,33.945875],"type":"Point"}
}