{
  "type": "Feature",
  "properties": {
    "iso:country":"US",
    "sg:address":"10470 Reymouth Ave",
    "sg:city":"Rancho Cordova",
    "sg:classifiers":[
        {
            "category":"Education",
            "subcategory":"School",
            "type":"Public Place"
        }
    ],
    "sg:phone":"+1 916 362 8162",
    "sg:postcode":"95670",
    "sg:province":"CA",
    "wof:name":"Development Center-Handicapped",
    "wof:placetype":"venue"
},
  "geometry": {"coordinates":[-121.300414,38.578405],"type":"Point"}
}