{
  "type": "Feature",
  "properties": {
    "addr:full":"625 Robinson St Bakersfield CA 93305",
    "addr:housenumber":"625",
    "addr:postcode":"93305",
    "addr:street":"Robinson St",
    "iso:country":"US",
    "sg:address":"625 Robinson St",
    "sg:city":"Bakersfield",
    "sg:classifiers":[
        {
            "category":"Organizations",
            "subcategory":"Religious Organization",
            "type":"Services"
        }
    ],
    "sg:phone":"+1 661 327 3110",
    "sg:postcode":"93305",
    "sg:province":"CA",
    "sg:tags":[
        "church"
    ],
    "wof:name":"Christ First Ministries",
    "wof:placetype":"venue"
},
  "geometry": {"coordinates":[-118.98590799999999,35.372664],"type":"Point"}
}