{
  "type": "Feature",
  "properties": {
    "iso:country":"US",
    "sg:address":"3000 E Thousand Oaks Blvd",
    "sg:city":"Thousand Oaks",
    "sg:classifiers":[
        {
            "category":"Retail",
            "subcategory":"Auto Repair",
            "type":"Services"
        }
    ],
    "sg:phone":"+1 805 379 2537",
    "sg:postcode":"91362",
    "sg:province":"CA",
    "sg:tags":[
        "repairing",
        "automobile"
    ],
    "wof:name":"Cars Etc",
    "wof:placetype":"venue"
},
  "geometry": {"coordinates":[-118.836596,34.169475],"type":"Point"}
}