{
  "type": "Feature",
  "properties": {
    "iso:country":"US",
    "sg:address":"6944 San Miguel Ave",
    "sg:city":"Lemon Grove",
    "sg:classifiers":[
        {
            "category":"Manufacturing",
            "subcategory":"Food",
            "type":"Manufacturing & Wholesale Goods"
        }
    ],
    "sg:phone":"+1 619 697 0858",
    "sg:postcode":"91945",
    "sg:province":"CA",
    "sg:tags":[
        "desert",
        "ice",
        "mfg"
    ],
    "wof:name":"AAA Ice Cream Vendor",
    "wof:placetype":"venue"
},
  "geometry": {"coordinates":[-117.04706,32.735245],"type":"Point"}
}