{
  "type": "Feature",
  "properties": {
    "iso:country":"US",
    "sg:address":"8725 E Naomi Ave",
    "sg:city":"San Gabriel",
    "sg:classifiers":[
        {
            "category":"Wholesale",
            "subcategory":"Drugs",
            "type":"Manufacturing & Wholesale Goods"
        }
    ],
    "sg:phone":"+1 626 286 3742",
    "sg:postcode":"91775",
    "sg:province":"CA",
    "wof:name":"Angel Products",
    "wof:placetype":"venue"
},
  "geometry": {"coordinates":[-118.077045,34.120599],"type":"Point"}
}