{
  "type": "Feature",
  "properties": {
    "addr:full":"200 Allendale Rd Pasadena CA 91106",
    "addr:housenumber":"200",
    "addr:postcode":"91106",
    "addr:street":"Allendale Rd",
    "iso:country":"US",
    "sg:address":"200 Allendale Rd",
    "sg:city":"Pasadena",
    "sg:classifiers":[
        {
            "category":"Health Services",
            "subcategory":"Clinic",
            "type":"Services"
        }
    ],
    "sg:phone":"+1 626 441 8000",
    "sg:postcode":"91106",
    "sg:province":"CA",
    "wof:name":"Pasadena Health Career Academy",
    "wof:placetype":"venue"
},
  "geometry": {"coordinates":[-118.143936,34.125608],"type":"Point"}
}