{
  "type": "Feature",
  "properties": {
    "addr:full":"24426 Peppermill Dr Moreno Valley CA 92557",
    "addr:housenumber":"24426",
    "addr:postcode":"92557",
    "addr:street":"Peppermill Dr",
    "iso:country":"US",
    "sg:address":"24426 Peppermill Dr",
    "sg:city":"Moreno Valley",
    "sg:classifiers":[
        {
            "category":"Shopping",
            "subcategory":"Books",
            "type":"Retail Goods"
        }
    ],
    "sg:phone":"+1 951 242 9205",
    "sg:postcode":"92557",
    "sg:province":"CA",
    "wof:name":"Alicats Books",
    "wof:placetype":"venue"
},
  "geometry": {"coordinates":[-117.235184,33.968157],"type":"Point"}
}