{
  "type": "Feature",
  "properties": {
    "iso:country":"US",
    "sg:address":"7324 Elmo St",
    "sg:city":"Tujunga",
    "sg:classifiers":[
        {
            "category":"Manufacturing",
            "subcategory":"Tools & Machinery",
            "type":"Manufacturing & Wholesale Goods"
        }
    ],
    "sg:phone":"+1 818 352 3274",
    "sg:postcode":"91042",
    "sg:province":"CA",
    "sg:tags":[
        "physician",
        "surgeon"
    ],
    "sg:website":"www.kopfinstruments.com",
    "wof:name":"David Kopf Instruments",
    "wof:placetype":"venue"
},
  "geometry": {"coordinates":[-118.291802,34.251126],"type":"Point"}
}