{
  "type": "Feature",
  "properties": {
    "addr:full":"11515 W Pico Blvd Los Angeles CA 90064",
    "addr:housenumber":"11515",
    "addr:postcode":"90064",
    "addr:street":"W Pico Blvd",
    "iso:country":"US",
    "sg:address":"11515 W Pico Blvd",
    "sg:city":"Los Angeles",
    "sg:classifiers":[
        {
            "category":"Shopping",
            "subcategory":"Computers & Home Electronics",
            "type":"Retail Goods"
        }
    ],
    "sg:phone":"+1 310 473 0063",
    "sg:postcode":"90064",
    "sg:province":"CA",
    "sg:tags":[
        "equipment",
        "dealer"
    ],
    "wof:name":"CRT Info Systems Inc",
    "wof:placetype":"venue"
},
  "geometry": {"coordinates":[-118.443425,34.032873],"type":"Point"}
}