{
  "type": "Feature",
  "properties": {
    "addr:full":"432 S Palm Ave Hemet CA 92543",
    "addr:housenumber":"432",
    "addr:postcode":"92543",
    "addr:street":"S Palm Ave",
    "iso:country":"US",
    "sg:address":"432 S Palm Ave",
    "sg:city":"Hemet",
    "sg:classifiers":[
        {
            "category":"Arts & Performance",
            "subcategory":"Theater",
            "type":"Entertainment"
        }
    ],
    "sg:phone":"+1 951 658 5311",
    "sg:postcode":"92543",
    "sg:province":"CA",
    "sg:tags":[
        "band",
        "orchestra"
    ],
    "wof:name":"Santa Rosa BAND-Msn Indians",
    "wof:placetype":"venue"
},
  "geometry": {"coordinates":[-116.980259,33.740822],"type":"Point"}
}