{
  "type": "Feature",
  "properties": {
    "iso:country":"US",
    "sg:address":"44202 Division St",
    "sg:city":"Lancaster",
    "sg:classifiers":[
        {
            "category":"Organizations",
            "subcategory":"Religious Organization",
            "type":"Services"
        }
    ],
    "sg:phone":"+1 661 269 2702",
    "sg:postcode":"93535",
    "sg:province":"CA",
    "sg:tags":[
        "church"
    ],
    "wof:name":"Desert Streams Community Chr",
    "wof:placetype":"venue"
},
  "geometry": {"coordinates":[-118.130242,34.687588],"type":"Point"}
}