{
  "type": "Feature",
  "properties": {
    "iso:country":"US",
    "sg:address":"2463 Buckingham Way",
    "sg:city":"Clovis",
    "sg:classifiers":[
        {
            "category":"Shopping",
            "subcategory":"Bicycles & Sporting Goods",
            "type":"Retail Goods"
        }
    ],
    "sg:phone":"+1 559 294 1568",
    "sg:postcode":"93611",
    "sg:province":"CA",
    "wof:name":"Clovis Golf",
    "wof:placetype":"venue"
},
  "geometry": {"coordinates":[-119.666978,36.793329],"type":"Point"}
}