{
  "type": "Feature",
  "properties": {
    "iso:country":"US",
    "sg:address":"3275 Grande Vista Dr",
    "sg:city":"Newbury Park",
    "sg:classifiers":[
        {
            "category":"Wholesale",
            "subcategory":"Machinery & Supplies",
            "type":"Manufacturing & Wholesale Goods"
        }
    ],
    "sg:phone":"+1 805 375 7226",
    "sg:postcode":"91320",
    "sg:province":"CA",
    "sg:tags":[
        "equipment",
        "plastic"
    ],
    "wof:name":"Yudo Inc",
    "wof:placetype":"venue"
},
  "geometry": {"coordinates":[-118.947841,34.194287],"type":"Point"}
}