{
  "type": "Feature",
  "properties": {
    "iso:country":"US",
    "sg:address":"607 Trumpet Ave",
    "sg:city":"Placentia",
    "sg:classifiers":[
        {
            "category":"Wholesale",
            "subcategory":"Machinery & Supplies",
            "type":"Manufacturing & Wholesale Goods"
        }
    ],
    "sg:phone":"+1 714 996 7751",
    "sg:postcode":"92870",
    "sg:province":"CA",
    "sg:tags":[
        "equipment",
        "industrial",
        "contractor"
    ],
    "wof:name":"Stevens Supply Company",
    "wof:placetype":"venue"
},
  "geometry": {"coordinates":[-117.85358,33.893373],"type":"Point"}
}