{
  "type": "Feature",
  "properties": {
    "addr:full":"5483 Ranchito Way Santa Rosa CA 95403",
    "addr:housenumber":"5483",
    "addr:postcode":"95403",
    "addr:street":"Ranchito Way",
    "iso:country":"US",
    "sg:address":"5483 Ranchito Way",
    "sg:city":"Santa Rosa",
    "sg:classifiers":[
        {
            "category":"Retail",
            "subcategory":"Auto Repair",
            "type":"Services"
        }
    ],
    "sg:phone":"+1 707 528 8166",
    "sg:postcode":"95403",
    "sg:province":"CA",
    "sg:tags":[
        "automobile",
        "installation",
        "glass"
    ],
    "wof:name":"Safety Glass Windshield Repair",
    "wof:placetype":"venue"
},
  "geometry": {"coordinates":[-122.77070999999999,38.515191],"type":"Point"}
}