{
  "type": "Feature",
  "properties": {
    "iso:country":"US",
    "sg:address":"412 Healdsburg Ave",
    "sg:city":"Healdsburg",
    "sg:classifiers":[
        {
            "category":"Real Estate",
            "subcategory":"Real Estate Agent",
            "type":"Services"
        }
    ],
    "sg:phone":"+1 707 433 3397",
    "sg:postcode":"95448",
    "sg:province":"CA",
    "sg:website":"www.cbhealdsburg.com",
    "wof:name":"Coldwell Banker",
    "wof:placetype":"venue"
},
  "geometry": {"coordinates":[-122.87176100000001,38.61399],"type":"Point"}
}