{
  "type": "Feature",
  "properties": {
    "addr:full":"261 N 31st St San Jose CA 95116",
    "addr:housenumber":"261",
    "addr:postcode":"95116",
    "addr:street":"N 31St St",
    "iso:country":"US",
    "sg:address":"261 N 31st St",
    "sg:city":"San Jose",
    "sg:classifiers":[
        {
            "category":"Building & Trades",
            "subcategory":"Cleaning & Sanitation",
            "type":"Services"
        }
    ],
    "sg:phone":"+1 408 272 5656",
    "sg:postcode":"95116",
    "sg:province":"CA",
    "sg:tags":[
        "janitor"
    ],
    "sg:website":"www.faustinos.com",
    "wof:name":"Faustino's Janitorial Svc",
    "wof:placetype":"venue"
},
  "geometry": {"coordinates":[-121.86479199999999,37.354301],"type":"Point"}
}