{
  "type": "Feature",
  "properties": {
    "addr:full":"5911 Auburn Boulevard Citrus Heights CA 95621",
    "addr:housenumber":"5911",
    "addr:postcode":"95621",
    "addr:street":"Auburn Boulevard",
    "iso:country":"US",
    "sg:address":"5911 Auburn Boulevard",
    "sg:city":"Citrus Heights",
    "sg:classifiers":[
        {
            "category":"Personal",
            "subcategory":"Tanning Parlor",
            "type":"Services"
        }
    ],
    "sg:phone":"+1 916 334 7768",
    "sg:postcode":"95621",
    "sg:province":"CA",
    "wof:name":"Sun San Tanning Salon",
    "wof:placetype":"venue"
},
  "geometry": {"coordinates":[-121.327232,38.67373],"type":"Point"}
}