{
  "type": "Feature",
  "properties": {
    "iso:country":"US",
    "sg:address":"615 High Dr",
    "sg:city":"Laguna Beach",
    "sg:classifiers":[
        {
            "category":"Professional",
            "subcategory":"Advertising",
            "type":"Services"
        }
    ],
    "sg:phone":"+1 949 497 6325",
    "sg:postcode":"92651",
    "sg:province":"CA",
    "sg:tags":[
        "designer",
        "display",
        "producer"
    ],
    "wof:name":"Aby Inc",
    "wof:placetype":"venue"
},
  "geometry": {"coordinates":[-117.79276400000001,33.547592],"type":"Point"}
}