{
  "type": "Feature",
  "properties": {
    "addr:full":"2328 Telegraph Ave Oakland CA 94612",
    "addr:housenumber":"2328",
    "addr:postcode":"94612",
    "addr:street":"Telegraph Ave",
    "iso:country":"US",
    "sg:address":"2328 Telegraph Ave",
    "sg:city":"Oakland",
    "sg:classifiers":[
        {
            "category":"Shopping",
            "subcategory":"Discount & Variety Stores",
            "type":"Retail Goods"
        }
    ],
    "sg:phone":"+1 510 663 7476",
    "sg:postcode":"94612",
    "sg:province":"CA",
    "wof:name":"Telegraph Dollar Store",
    "wof:placetype":"venue"
},
  "geometry": {"coordinates":[-122.268726,37.812962],"type":"Point"}
}