{
  "type": "Feature",
  "properties": {
    "iso:country":"US",
    "sg:address":"116 N Halcyon Rd",
    "sg:city":"Arroyo Grande",
    "sg:classifiers":[
        {
            "category":"Health Services",
            "subcategory":"Doctor",
            "type":"Services"
        }
    ],
    "sg:phone":"+1 805 481 0800",
    "sg:postcode":"93420",
    "sg:province":"CA",
    "sg:tags":[
        "dentist"
    ],
    "wof:name":"William JW Calder Inc",
    "wof:placetype":"venue"
},
  "geometry": {"coordinates":[-120.59147400000001,35.119587],"type":"Point"}
}