{
  "type": "Feature",
  "properties": {
    "iso:country":"US",
    "sfac:artist":"Hoefer, Wade",
    "sfac:created_at":"01/01/1970 12:33:05 AM +0000",
    "sfac:credit_line":"Purchased by the San Francisco Art Commission for the San Francisco International Airport.",
    "sfac:display_dimensions":"64\" H X 120\" W",
    "sfac:location_description":"Airport : Terminal 2 : Gate 58 B",
    "sfac:medium":"Acrylic and sand on canvas",
    "sfac:revision":"2-2eade7175c260fa0e3e24351618e1788",
    "sfac:title":"The Peasant's Parade",
    "wof:name":"The Peasant's Parade",
    "wof:placetype":"venue"
},
  "geometry": {"coordinates":[-122.389979,37.615223],"type":"Point"}
}