{
  "type": "Feature",
  "properties": {
    "iso:country":"US",
    "sg:address":"1203 Preservation Park Way",
    "sg:city":"Oakland",
    "sg:classifiers":[
        {
            "category":"Social Services",
            "type":"Services"
        },
        {
            "category":"Organizations",
            "subcategory":"Non-profit Organization",
            "type":"Services"
        },
        {
            "category":"Science Facility",
            "type":"Public Place"
        }
    ],
    "sg:phone":"+1 510 451 7275",
    "sg:postcode":"94612",
    "sg:province":"CA",
    "sg:tags":[
        "development",
        "foundations-educational",
        "philanthropic",
        "laboratories-research",
        "research",
        "human",
        "charity"
    ],
    "sg:website":"http://www.alwaysdream.org",
    "wof:name":"Always Dream Foundation",
    "wof:placetype":"venue"
},
  "geometry": {"coordinates":[-122.27757099999999,37.805095],"type":"Point"}
}