{
  "type": "Feature",
  "properties": {
    "iso:country":"US",
    "sg:address":"3470 Wilshire Blvd",
    "sg:city":"Los Angeles",
    "sg:classifiers":[
        {
            "category":"Building & Trades",
            "subcategory":"Construction",
            "type":"Services"
        }
    ],
    "sg:phone":"+1 213 384 0444",
    "sg:postcode":"90010",
    "sg:province":"CA",
    "sg:tags":[
        "cabling",
        "wiring",
        "telecommunication"
    ],
    "wof:name":"Richard Communications",
    "wof:placetype":"venue"
},
  "geometry": {"coordinates":[-118.299933,34.061671],"type":"Point"}
}