{
  "type": "Feature",
  "properties": {
    "addr:full":"2389 Tripaldi Way Hayward CA 94545",
    "addr:housenumber":"2389",
    "addr:postcode":"94545",
    "addr:street":"Tripaldi Way",
    "iso:country":"US",
    "sg:address":"2389 Tripaldi Way",
    "sg:city":"Hayward",
    "sg:classifiers":[
        {
            "category":"Home & Garden",
            "subcategory":"Building Materials",
            "type":"Retail Goods"
        }
    ],
    "sg:phone":"+1 510 259 1270",
    "sg:postcode":"94545",
    "sg:province":"CA",
    "sg:tags":[
        "energy",
        "conservation",
        "prod"
    ],
    "wof:name":"Thermoguard California",
    "wof:placetype":"venue"
},
  "geometry": {"coordinates":[-122.084062,37.614589],"type":"Point"}
}