{
  "type": "Feature",
  "properties": {
    "iso:country":"US",
    "sg:address":"6752 Carthage St",
    "sg:city":"San Diego",
    "sg:classifiers":[
        {
            "category":"Manufacturing",
            "subcategory":"Jewelry",
            "type":"Manufacturing & Wholesale Goods"
        }
    ],
    "sg:phone":"+1 858 488 0952",
    "sg:postcode":"92120",
    "sg:province":"CA",
    "sg:tags":[
        "costume",
        "mfg"
    ],
    "wof:name":"Chriss Jewerly",
    "wof:placetype":"venue"
},
  "geometry": {"coordinates":[-117.07866,32.792325],"type":"Point"}
}