{
  "type": "Feature",
  "properties": {
    "iso:country":"US",
    "sg:address":"1105 2nd St",
    "sg:city":"Brentwood",
    "sg:classifiers":[
        {
            "category":"Restaurant",
            "type":"Food & Drink"
        }
    ],
    "sg:menulink":"http://www.allmenus.com/ca/east-contra-costa/172106-burger-king/menu/",
    "sg:phone":"+1 925 634 5739",
    "sg:postcode":"94513",
    "sg:province":"CA",
    "sg:tags":[
        "burger",
        "american"
    ],
    "wof:name":"Burger King",
    "wof:placetype":"venue"
},
  "geometry": {"coordinates":[-121.697294,37.936623],"type":"Point"}
}