{
  "type": "Feature",
  "properties": {
    "addr:full":"350 Bay Fair Mall San Leandro CA 94578",
    "addr:housenumber":"350",
    "addr:postcode":"94578",
    "addr:street":"Bay Fair Mall",
    "iso:country":"US",
    "sg:address":"350 Bay Fair Mall",
    "sg:city":"San Leandro",
    "sg:classifiers":[
        {
            "category":"Cinema",
            "subcategory":"Movie Theater",
            "type":"Entertainment"
        }
    ],
    "sg:phone":"+1 510 481 0123",
    "sg:postcode":"94578",
    "sg:province":"CA",
    "wof:name":"Century Theatres Bayfair",
    "wof:placetype":"venue"
},
  "geometry": {"coordinates":[-122.125,37.698627],"type":"Point"}
}