{
  "type": "Feature",
  "properties": {
    "iso:country":"US",
    "sg:address":"380 Diablo Rd",
    "sg:city":"Danville",
    "sg:classifiers":[
        {
            "category":"Real Estate",
            "subcategory":"Real Estate Services",
            "type":"Services"
        },
        {
            "category":"Real Estate",
            "subcategory":"Real Estate Agent",
            "type":"Services"
        }
    ],
    "sg:phone":"+1 925 831 2488",
    "sg:postcode":"94526",
    "sg:province":"CA",
    "sg:tags":[
        "buyer",
        "broker"
    ],
    "wof:name":"Peles Nina",
    "wof:placetype":"venue"
},
  "geometry": {"coordinates":[-121.995679,37.822979],"type":"Point"}
}