{
  "type": "Feature",
  "properties": {
    "iso:country":"US",
    "sg:address":"1400 Glorietta Blvd",
    "sg:city":"Coronado",
    "sg:classifiers":[
        {
            "category":"Retail",
            "subcategory":"Laundry & Dry Cleaning",
            "type":"Services"
        }
    ],
    "sg:phone":"+1 619 405 6441",
    "sg:postcode":"92118",
    "sg:province":"CA",
    "sg:tags":[
        "cleaners",
        "rug",
        "carpet"
    ],
    "wof:name":"Kings Carpet Care & Repair",
    "wof:placetype":"venue"
},
  "geometry": {"coordinates":[-117.17411800000001,32.683411],"type":"Point"}
}