{
  "type": "Feature",
  "properties": {
    "addr:full":"3535 Boyer Cir Lafayette CA 94549",
    "addr:housenumber":"3535",
    "addr:postcode":"94549",
    "addr:street":"Boyer Cir",
    "iso:country":"US",
    "sg:address":"3535 Boyer Cir",
    "sg:city":"Lafayette",
    "sg:classifiers":[
        {
            "category":"Manufacturing",
            "subcategory":"Tools & Machinery",
            "type":"Manufacturing & Wholesale Goods"
        }
    ],
    "sg:phone":"+1 925 283 0148",
    "sg:postcode":"94549",
    "sg:province":"CA",
    "sg:tags":[
        "equipment",
        "system",
        "vacuum"
    ],
    "wof:name":"Diamond Diablo",
    "wof:placetype":"venue"
},
  "geometry": {"coordinates":[-122.124048,37.885856],"type":"Point"}
}