{
  "type": "Feature",
  "properties": {
    "addr:full":"3708 W Slauson Ave Los Angeles CA 90043",
    "addr:housenumber":"3708",
    "addr:postcode":"90043",
    "addr:street":"W Slauson Ave",
    "iso:country":"US",
    "sg:address":"3708 W Slauson Ave",
    "sg:city":"Los Angeles",
    "sg:classifiers":[
        {
            "category":"Autos & Motor Vehicles",
            "subcategory":"Fuel & Gas Station",
            "type":"Retail Goods"
        }
    ],
    "sg:phone":"+1 323 290 0314",
    "sg:postcode":"90043",
    "sg:province":"CA",
    "sg:tags":[
        "oil"
    ],
    "wof:name":"ATM On Wheels",
    "wof:placetype":"venue"
},
  "geometry": {"coordinates":[-118.338587,33.988905],"type":"Point"}
}