{
  "type": "Feature",
  "properties": {
    "iso:country":"US",
    "sg:address":"2206 Pullman Ave",
    "sg:city":"Belmont",
    "sg:classifiers":[
        {
            "category":"Real Estate",
            "subcategory":"Developer",
            "type":"Services"
        }
    ],
    "sg:phone":"+1 650 654 4464",
    "sg:postcode":"94002",
    "sg:province":"CA",
    "wof:name":"Jet Black",
    "wof:placetype":"venue"
},
  "geometry": {"coordinates":[-122.297391,37.512079],"type":"Point"}
}