{
  "type": "Feature",
  "properties": {
    "addr:full":"9300 Flair Dr Ste 388 El Monte CA 91731",
    "addr:housenumber":"9300",
    "addr:postcode":"91731",
    "addr:street":"Flair Dr Ste 388",
    "iso:country":"US",
    "sg:address":"9300 Flair Dr Ste 388",
    "sg:city":"El Monte",
    "sg:classifiers":[
        {
            "category":"Health Services",
            "subcategory":"Clinic",
            "type":"Services"
        }
    ],
    "sg:phone":"+1 626 227 0220",
    "sg:postcode":"91731",
    "sg:province":"CA",
    "sg:tags":[
        "medical"
    ],
    "sg:website":"www.InfinityHomeCareProviders.com",
    "wof:name":"Infinity Home Care Providers",
    "wof:placetype":"venue"
},
  "geometry": {"coordinates":[-118.066265,34.071288],"type":"Point"}
}