{
  "type": "Feature",
  "properties": {
    "addr:full":"1769 Crows Landing Rd Modesto CA 95358",
    "addr:housenumber":"1769",
    "addr:postcode":"ca 95358",
    "addr:street":"Crows Landing Rd",
    "iso:country":"US",
    "sg:address":"1769 Crows Landing Rd",
    "sg:city":"Modesto",
    "sg:classifiers":[
        {
            "category":"Restaurant",
            "type":"Food & Drink"
        }
    ],
    "sg:phone":"+1 209 538 4427",
    "sg:postcode":"95358",
    "sg:province":"CA",
    "wof:name":"Tokyo Teriyaki House",
    "wof:placetype":"venue"
},
  "geometry": {"coordinates":[-120.99299600000001,37.605999],"type":"Point"}
}