{
  "type": "Feature",
  "properties": {
    "iso:country":"US",
    "sg:address":"45744 Corte Lobos",
    "sg:city":"Temecula",
    "sg:classifiers":[
        {
            "category":"Building & Trades",
            "subcategory":"Plumbing",
            "type":"Services"
        }
    ],
    "sg:phone":"+1 951 302 8125",
    "sg:postcode":"92592",
    "sg:province":"CA",
    "sg:tags":[
        "commercial",
        "installation"
    ],
    "wof:name":"Reeves Mechanical LP",
    "wof:placetype":"venue"
},
  "geometry": {"coordinates":[-117.095354,33.463306],"type":"Point"}
}