{
  "type": "Feature",
  "properties": {
    "addr:full":"698-295 Hill Creek Rd Susanville CA 96130",
    "addr:housenumber":"698-295",
    "addr:postcode":"96130",
    "addr:street":"Hill Creek Rd",
    "iso:country":"US",
    "sg:address":"698-295 Hill Creek Rd",
    "sg:city":"Susanville",
    "sg:classifiers":[
        {
            "category":"Insurance",
            "subcategory":"Hazard Insurance",
            "type":"Services"
        }
    ],
    "sg:phone":"+1 530 257 5502",
    "sg:postcode":"96130",
    "sg:province":"CA",
    "wof:name":"Sherry Dinsmoor",
    "wof:placetype":"venue"
},
  "geometry": {"coordinates":[-120.673855,40.358194],"type":"Point"}
}