{
  "type": "Feature",
  "properties": {
    "addr:full":"1144 E Holt Ave Pomona CA 91767",
    "addr:housenumber":"1144",
    "addr:postcode":"91767",
    "addr:street":"E Holt Ave",
    "iso:country":"US",
    "sg:address":"1144 E Holt Ave",
    "sg:city":"Pomona",
    "sg:classifiers":[
        {
            "category":"Autos & Motor Vehicles",
            "subcategory":"Automobile Sales",
            "type":"Retail Goods"
        }
    ],
    "sg:phone":"+1 909 397 9650",
    "sg:postcode":"91767",
    "sg:province":"CA",
    "sg:tags":[
        "used",
        "car",
        "dealers-used",
        "new",
        "cars-wholesale"
    ],
    "wof:name":"Pomona Valley Auto Sales",
    "wof:placetype":"venue"
},
  "geometry": {"coordinates":[-117.728404,34.06291],"type":"Point"}
}