{
  "type": "Feature",
  "properties": {
    "iso:country":"US",
    "sg:address":"4049 3rd St",
    "sg:city":"San Francisco",
    "sg:classifiers":[
        {
            "category":"Wholesale",
            "subcategory":"Non-durable Goods",
            "type":"Manufacturing & Wholesale Goods"
        }
    ],
    "sg:phone":"+1 415 643 3338",
    "sg:postcode":"94124",
    "sg:province":"CA",
    "wof:name":"K W 4049 Building Mtl & Cnstr",
    "wof:placetype":"venue"
},
  "geometry": {"coordinates":[-122.388508,37.740669],"type":"Point"}
}