{
  "type": "Feature",
  "properties": {
    "iso:country":"US",
    "sg:address":"520 13th St",
    "sg:city":"Modesto",
    "sg:classifiers":[
        {
            "category":"Professional",
            "subcategory":"Lawyer & Legal Services",
            "type":"Services"
        }
    ],
    "sg:phone":"+1 209 548 9014",
    "sg:postcode":"95354",
    "sg:province":"CA",
    "sg:tags":[
        "attorney"
    ],
    "wof:name":"Vangie Eidsvik-Garza",
    "wof:placetype":"venue"
},
  "geometry": {"coordinates":[-120.992604,37.638651],"type":"Point"}
}