{
  "type": "Feature",
  "properties": {
    "addr:full":"8902 Avalon Blvd Los Angeles CA 90003",
    "addr:housenumber":"8902",
    "addr:postcode":"90003",
    "addr:street":"Avalon Blvd",
    "iso:country":"US",
    "sg:address":"8902 Avalon Blvd",
    "sg:city":"Los Angeles",
    "sg:classifiers":[
        {
            "category":"Food & Beverages",
            "subcategory":"Groceries & Convenience Stores",
            "type":"Retail Goods"
        }
    ],
    "sg:phone":"+1 323 778 9969",
    "sg:postcode":"90003",
    "sg:province":"CA",
    "wof:name":"C & D Market",
    "wof:placetype":"venue"
},
  "geometry": {"coordinates":[-118.264999,33.955601],"type":"Point"}
}