{
  "type": "Feature",
  "properties": {
    "addr:full":"21638 Devonshire St Chatsworth CA 91311",
    "addr:housenumber":"21638",
    "addr:postcode":"91311",
    "addr:street":"Devonshire St",
    "iso:country":"US",
    "sg:address":"21638 Devonshire St",
    "sg:city":"Chatsworth",
    "sg:classifiers":[
        {
            "category":"Autos & Motor Vehicles",
            "subcategory":"Auto Supplies",
            "type":"Retail Goods"
        },
        {
            "category":"Retail",
            "subcategory":"Auto Repair",
            "type":"Services"
        }
    ],
    "sg:phone":"+1 818 882 7494",
    "sg:postcode":"91311",
    "sg:province":"CA",
    "sg:tags":[
        "body",
        "repairing",
        "transmission",
        "automobile",
        "wheels-aligning",
        "balancing",
        "equipment-service",
        "brake",
        "painting",
        "air conditioning"
    ],
    "wof:name":"Chatsworth Auto Repair",
    "wof:placetype":"venue"
},
  "geometry": {"coordinates":[-118.60035000000001,34.25724],"type":"Point"}
}