{
  "type": "Feature",
  "properties": {
    "iso:country":"US",
    "sg:address":"10699 Long Beach Blvd",
    "sg:city":"Lynwood",
    "sg:classifiers":[
        {
            "category":"Home & Garden",
            "subcategory":"Household Appliances",
            "type":"Retail Goods"
        }
    ],
    "sg:phone":"+1 323 567 4049",
    "sg:postcode":"90262",
    "sg:province":"CA",
    "wof:name":"Audio Systems & Alarms",
    "wof:placetype":"venue"
},
  "geometry": {"coordinates":[-118.21377200000001,33.937844],"type":"Point"}
}