{
  "type": "Feature",
  "properties": {
    "addr:full":"23504 Calabasas Rd Calabasas CA 91302",
    "addr:housenumber":"23504",
    "addr:postcode":"91302",
    "addr:street":"Calabasas Rd",
    "iso:country":"US",
    "sg:address":"23504 Calabasas Rd",
    "sg:city":"Calabasas",
    "sg:classifiers":[
        {
            "category":"Shopping",
            "subcategory":"Used Merchandise",
            "type":"Retail Goods"
        }
    ],
    "sg:phone":"+1 818 223 8696",
    "sg:postcode":"91302",
    "sg:province":"CA",
    "sg:tags":[
        "antique",
        "massage"
    ],
    "sg:website":"www.renewalspaandnails.com/",
    "wof:name":"Renewal Spa and Nail",
    "wof:placetype":"venue"
},
  "geometry": {"coordinates":[-118.63800000000001,34.1576],"type":"Point"}
}