{
  "type": "Feature",
  "properties": {
    "iso:country":"US",
    "sg:address":"4233 W Sierra Madre Ave",
    "sg:city":"Fresno",
    "sg:classifiers":[
        {
            "category":"Insurance",
            "subcategory":"Insurance Agent",
            "type":"Services"
        }
    ],
    "sg:phone":"+1 559 647 5677",
    "sg:postcode":"93722",
    "sg:province":"CA",
    "sg:tags":[
        "adjuster"
    ],
    "wof:name":"Nation Adjusting",
    "wof:placetype":"venue"
},
  "geometry": {"coordinates":[-119.867028,36.806707],"type":"Point"}
}