{
  "type": "Feature",
  "properties": {
    "addr:full":"3375 Sweet Dr Lafayette CA 94549",
    "addr:housenumber":"3375",
    "addr:postcode":"94549",
    "addr:street":"Sweet Dr",
    "iso:country":"US",
    "sg:address":"3375 Sweet Dr",
    "sg:city":"Lafayette",
    "sg:classifiers":[
        {
            "category":"Real Estate",
            "subcategory":"Real Estate Agent",
            "type":"Services"
        }
    ],
    "sg:phone":"+1 925 385 0210",
    "sg:postcode":"94549",
    "sg:province":"CA",
    "sg:tags":[
        "leasing",
        "agency",
        "rental"
    ],
    "wof:name":"Studio Instrumental Rentals",
    "wof:placetype":"venue"
},
  "geometry": {"coordinates":[-122.109973,37.879225],"type":"Point"}
}