{
  "type": "Feature",
  "properties": {
    "addr:full":"501 Valley Club Rd Santa Barbara CA 93108",
    "addr:housenumber":"501",
    "addr:postcode":"93108",
    "addr:street":"Valley Club Rd",
    "iso:country":"US",
    "sg:address":"501 Valley Club Rd",
    "sg:city":"Santa Barbara",
    "sg:classifiers":[
        {
            "category":"Professional",
            "type":"Services"
        }
    ],
    "sg:phone":"+1 805 969 7730",
    "sg:postcode":"93108",
    "sg:province":"CA",
    "sg:tags":[
        "establishment"
    ],
    "wof:name":"Stegall Co",
    "wof:placetype":"venue"
},
  "geometry": {"coordinates":[-119.614923,34.43842],"type":"Point"}
}