{
  "type": "Feature",
  "properties": {
    "addr:full":"6550 Caballero Blvd Buena Park CA 90620",
    "addr:housenumber":"6550",
    "addr:postcode":"90620",
    "addr:street":"Caballero Blvd",
    "iso:country":"US",
    "sg:address":"6550 Caballero Blvd",
    "sg:city":"Buena Park",
    "sg:classifiers":[
        {
            "category":"Manufacturing",
            "subcategory":"Metals",
            "type":"Manufacturing & Wholesale Goods"
        }
    ],
    "sg:phone":"+1 714 521 9800",
    "sg:postcode":"90620",
    "sg:province":"CA",
    "sg:tags":[
        "product",
        "aluminum",
        "mfg",
        "die",
        "m",
        "primary",
        "nonferrous"
    ],
    "sg:website":"www.alloydie.com",
    "wof:name":"Alloy Die Casting Co",
    "wof:placetype":"venue"
},
  "geometry": {"coordinates":[-118.011877,33.863141],"type":"Point"}
}