{
  "type": "Feature",
  "properties": {
    "iso:country":"US",
    "sg:address":"43332 Almond Ln",
    "sg:city":"Davis",
    "sg:classifiers":[
        {
            "category":"Taxi",
            "type":"Transportation"
        }
    ],
    "sg:phone":"+1 530 792 8000",
    "sg:postcode":"95618",
    "sg:province":"CA",
    "sg:tags":[
        "taxicab"
    ],
    "wof:name":"University Cab",
    "wof:placetype":"venue"
},
  "geometry": {"coordinates":[-121.702823,38.541634],"type":"Point"}
}