{
  "type": "Feature",
  "properties": {
    "iso:country":"US",
    "sg:address":"760 S Vail Ave",
    "sg:city":"Montebello",
    "sg:classifiers":[
        {
            "category":"Utilities",
            "type":"Services"
        }
    ],
    "sg:phone":"+1 323 721 2524",
    "sg:postcode":"90640",
    "sg:province":"CA",
    "sg:tags":[
        "oil",
        "up",
        "clean",
        "spill"
    ],
    "wof:name":"Cape Environmental",
    "wof:placetype":"venue"
},
  "geometry": {"coordinates":[-118.123634,34.003503],"type":"Point"}
}