{
  "type": "Feature",
  "properties": {
    "addr:full":"353 2nd St Davis CA 95616",
    "addr:housenumber":"353",
    "addr:postcode":"95616",
    "addr:street":"2Nd St",
    "iso:country":"US",
    "sg:address":"353 2nd St",
    "sg:city":"Davis",
    "sg:classifiers":[
        {
            "category":"Shopping",
            "subcategory":"Optical Goods",
            "type":"Retail Goods"
        },
        {
            "category":"Health Services",
            "subcategory":"Optometrist",
            "type":"Services"
        },
        {
            "category":"Personal",
            "subcategory":"Shoe Repair & Shine",
            "type":"Services"
        }
    ],
    "sg:phone":"+1 530 758 2122",
    "sg:postcode":"95616",
    "sg:province":"CA",
    "sg:tags":[
        "eyeglass",
        "optometry",
        "sunglass",
        "lens",
        "contact",
        "optometrists-od-pediatric"
    ],
    "sg:website":"http://www.helmusoptometry.com/",
    "wof:name":"Helmus, Mark R, Od - Helmus Optometry",
    "wof:placetype":"venue"
},
  "geometry": {"coordinates":[-121.74377200000001,38.542785],"type":"Point"}
}