{
  "type": "Feature",
  "properties": {
    "iso:country":"US",
    "sg:address":"2513 Charleston Rd",
    "sg:city":"Mountain View",
    "sg:classifiers":[
        {
            "category":"Professional",
            "subcategory":"Employment Agencies",
            "type":"Services"
        }
    ],
    "sg:phone":"+1 650 254 9000",
    "sg:postcode":"94043",
    "sg:province":"CA",
    "sg:website":"www.simplyhired.com",
    "wof:name":"Simply Hired, Inc",
    "wof:placetype":"venue"
},
  "geometry": {"coordinates":[-122.089719,37.422906],"type":"Point"}
}