{
  "type": "Feature",
  "properties": {
    "addr:full":"345 Spring St Paso Robles CA 93446",
    "addr:housenumber":"345",
    "addr:postcode":"93446",
    "addr:street":"Spring St",
    "iso:country":"US",
    "sg:address":"345 Spring St",
    "sg:city":"Paso Robles",
    "sg:classifiers":[
        {
            "category":"Health Services",
            "subcategory":"Chiropractor",
            "type":"Services"
        }
    ],
    "sg:phone":"+1 805 238 7250",
    "sg:postcode":"93446",
    "sg:province":"CA",
    "wof:name":"Community Health Ctr",
    "wof:placetype":"venue"
},
  "geometry": {"coordinates":[-120.690676,35.617617],"type":"Point"}
}