{
  "type": "Feature",
  "properties": {
    "addr:full":"205 N Hale Ave Escondido CA 92029",
    "addr:housenumber":"205",
    "addr:postcode":"92029",
    "addr:street":"N Hale Ave",
    "iso:country":"US",
    "sg:address":"205 N Hale Ave",
    "sg:city":"Escondido",
    "sg:classifiers":[
        {
            "category":"Autos & Motor Vehicles",
            "subcategory":"Auto Supplies",
            "type":"Retail Goods"
        },
        {
            "category":"Retail",
            "subcategory":"Auto Repair",
            "type":"Services"
        }
    ],
    "sg:phone":"+1 760 735 8100",
    "sg:postcode":"92029",
    "sg:province":"CA",
    "sg:tags":[
        "recap",
        "retread",
        "tire"
    ],
    "sg:website":"http://www.petesrs.com",
    "wof:name":"Pete's Road Service, Inc.",
    "wof:placetype":"venue"
},
  "geometry": {"coordinates":[-117.103435,33.116743],"type":"Point"}
}