{
  "type": "Feature",
  "properties": {
    "addr:full":"2133 Bedrock Way Antioch CA 94509",
    "addr:housenumber":"2133",
    "addr:postcode":"ca 94509",
    "addr:street":"Bedrock Way",
    "iso:country":"US",
    "sg:address":"2133 Bedrock Way",
    "sg:city":"Antioch",
    "sg:classifiers":[
        {
            "category":"Communications",
            "subcategory":"Film & Video Production",
            "type":"Services"
        }
    ],
    "sg:phone":"+1 925 755 7552",
    "sg:postcode":"94509",
    "sg:province":"CA",
    "sg:tags":[
        "taping"
    ],
    "sg:website":"www.dpick.com",
    "wof:name":"D Pickens Video Production",
    "wof:placetype":"venue"
},
  "geometry": {"coordinates":[-121.78863,37.982822],"type":"Point"}
}