{
  "type": "Feature",
  "properties": {
    "addr:full":"24530 State St Hemet CA 92543",
    "addr:housenumber":"24530",
    "addr:postcode":"92543",
    "addr:street":"State St",
    "iso:country":"US",
    "sg:address":"24530 State St",
    "sg:city":"Hemet",
    "sg:classifiers":[
        {
            "category":"Home & Garden",
            "subcategory":"Building Materials",
            "type":"Retail Goods"
        }
    ],
    "sg:phone":"+1 951 658 9225",
    "sg:postcode":"92543",
    "sg:province":"CA",
    "sg:tags":[
        "mixed",
        "concrete"
    ],
    "wof:name":"Hemet Redi Mix & Materials",
    "wof:placetype":"venue"
},
  "geometry": {"coordinates":[-116.971874,33.763679],"type":"Point"}
}