{
  "type": "Feature",
  "properties": {
    "addr:full":"33411 Turnstone Pl Fremont CA 94555",
    "addr:postcode":"33411;94555",
    "addr:street":"Turnstone Pl",
    "iso:country":"US",
    "sg:address":"33411 Turnstone Pl",
    "sg:city":"Fremont",
    "sg:classifiers":[
        {
            "category":"Professional",
            "type":"Services"
        }
    ],
    "sg:phone":"+1 510 793 7554",
    "sg:postcode":"94555",
    "sg:province":"CA",
    "sg:tags":[
        "establishment"
    ],
    "wof:name":"Tracewell Systems",
    "wof:placetype":"venue"
},
  "geometry": {"coordinates":[-122.045119,37.585723],"type":"Point"}
}