{
  "type": "Feature",
  "properties": {
    "addr:full":"205 California St Stockton CA 95202",
    "addr:housenumber":"205",
    "addr:postcode":"95202",
    "addr:street":"California St",
    "iso:country":"US",
    "sg:address":"205 California St",
    "sg:city":"Stockton",
    "sg:classifiers":[
        {
            "category":"Personal",
            "subcategory":"Beauty Salon",
            "type":"Services"
        }
    ],
    "sg:phone":"+1 209 463 2348",
    "sg:postcode":"95202",
    "sg:province":"CA",
    "wof:name":"Eclectic Chair",
    "wof:placetype":"venue"
},
  "geometry": {"coordinates":[-121.285448,37.956523],"type":"Point"}
}