{
  "type": "Feature",
  "properties": {
    "iso:country":"US",
    "sg:address":"4404 Manchester Ave",
    "sg:city":"Stockton",
    "sg:classifiers":[
        {
            "category":"Real Estate",
            "subcategory":"Real Estate Operator",
            "type":"Services"
        }
    ],
    "sg:phone":"+1 209 477 4655",
    "sg:postcode":"95207",
    "sg:province":"CA",
    "sg:tags":[
        "apartment"
    ],
    "wof:name":"Townhouse Pacific",
    "wof:placetype":"venue"
},
  "geometry": {"coordinates":[-121.316463,37.985345],"type":"Point"}
}