{
  "type": "Feature",
  "properties": {
    "iso:country":"US",
    "sg:address":"1290 Santa Rosa Ave",
    "sg:city":"Santa Rosa",
    "sg:classifiers":[
        {
            "category":"Retail",
            "subcategory":"Auto Repair",
            "type":"Services"
        }
    ],
    "sg:phone":"+1 707 545 7282",
    "sg:postcode":"95404",
    "sg:province":"CA",
    "sg:tags":[
        "truck"
    ],
    "wof:name":"Don's Truck Svc & Repair",
    "wof:placetype":"venue"
},
  "geometry": {"coordinates":[-122.713325,38.42672],"type":"Point"}
}