{
  "type": "Feature",
  "properties": {
    "iso:country":"US",
    "sg:address":"1010 Munras Ave",
    "sg:city":"Monterey",
    "sg:classifiers":[
        {
            "category":"Travel",
            "subcategory":"Hotels & Motels",
            "type":"Entertainment"
        }
    ],
    "sg:phone":"+1 831 646 9696",
    "sg:postcode":"93940",
    "sg:province":"CA",
    "sg:website":"www.munraslodge.com",
    "wof:name":"Munras Lodge",
    "wof:placetype":"venue"
},
  "geometry": {"coordinates":[-121.897703,36.588891],"type":"Point"}
}