{
  "type": "Feature",
  "properties": {
    "iso:country":"US",
    "sg:address":"843 E Ridgecrest Blvd",
    "sg:city":"Ridgecrest",
    "sg:classifiers":[
        {
            "category":"Food & Beverages",
            "subcategory":"Groceries & Convenience Stores",
            "type":"Retail Goods"
        }
    ],
    "sg:phone":"+1 760 375 4672",
    "sg:postcode":"93555",
    "sg:province":"CA",
    "sg:tags":[
        "grocer"
    ],
    "wof:name":"Minit Shop",
    "wof:placetype":"venue"
},
  "geometry": {"coordinates":[-117.653921,35.62236],"type":"Point"}
}