{
  "type": "Feature",
  "properties": {
    "iso:country":"US",
    "sg:address":"630 Cardiff",
    "sg:city":"Irvine",
    "sg:classifiers":[
        {
            "category":"Building & Trades",
            "subcategory":"Construction",
            "type":"Services"
        }
    ],
    "sg:phone":"+1 949 559 3656",
    "sg:postcode":"92606",
    "sg:province":"CA",
    "sg:tags":[
        "contractor"
    ],
    "wof:name":"Richards Factory Installation",
    "wof:placetype":"venue"
},
  "geometry": {"coordinates":[-117.80571,33.688644],"type":"Point"}
}