{
  "type": "Feature",
  "properties": {
    "iso:country":"US",
    "sg:address":"2736 W Lincoln Ave",
    "sg:city":"Anaheim",
    "sg:classifiers":[
        {
            "category":"Real Estate",
            "subcategory":"Real Estate Operator",
            "type":"Services"
        }
    ],
    "sg:phone":"+1 714 761 8580",
    "sg:postcode":"92801",
    "sg:province":"CA",
    "sg:tags":[
        "apartment"
    ],
    "wof:name":"Su Casa Park Place",
    "wof:placetype":"venue"
},
  "geometry": {"coordinates":[-117.98200199999999,33.8321],"type":"Point"}
}