{
  "type": "Feature",
  "properties": {
    "addr:full":"2705 5th St Sacramento CA 95818",
    "addr:housenumber":"2705",
    "addr:postcode":"95818",
    "addr:street":"5Th St",
    "iso:country":"US",
    "sg:address":"2705 5th St",
    "sg:city":"Sacramento",
    "sg:classifiers":[
        {
            "category":"Wholesale",
            "subcategory":"Groceries",
            "type":"Manufacturing & Wholesale Goods"
        }
    ],
    "sg:phone":"+1 916 444 6122",
    "sg:postcode":"95818",
    "sg:province":"CA",
    "sg:tags":[
        "food",
        "broker"
    ],
    "wof:name":"US Foodservice",
    "wof:placetype":"venue"
},
  "geometry": {"coordinates":[-121.508,38.563877],"type":"Point"}
}