{
  "type": "Feature",
  "properties": {
    "addr:full":"2015 S Encina St Visalia CA 93277",
    "addr:housenumber":"2015",
    "addr:postcode":"93277",
    "addr:street":"S Encina St",
    "iso:country":"US",
    "sg:address":"2015 S Encina St",
    "sg:city":"Visalia",
    "sg:classifiers":[
        {
            "category":"Social Services",
            "subcategory":"Child Care",
            "type":"Services"
        }
    ],
    "sg:phone":"+1 559 738 0111",
    "sg:postcode":"93277",
    "sg:province":"CA",
    "wof:name":"Raggedy Ann & Andy Preschool",
    "wof:placetype":"venue"
},
  "geometry": {"coordinates":[-119.29485200000001,36.312461],"type":"Point"}
}