{
  "type": "Feature",
  "properties": {
    "addr:full":"4918 3rd St San Francisco CA 94124",
    "addr:housenumber":"4918",
    "addr:postcode":"94124",
    "addr:street":"3Rd St",
    "iso:country":"US",
    "sg:address":"4918 3rd St",
    "sg:city":"San Francisco",
    "sg:classifiers":[
        {
            "category":"Social Services",
            "subcategory":"Child Care",
            "type":"Services"
        }
    ],
    "sg:phone":"+1 415 822 9144",
    "sg:postcode":"94124",
    "sg:province":"CA",
    "sg:tags":[
        "day"
    ],
    "wof:name":"Brighter Futures",
    "wof:placetype":"venue"
},
  "geometry": {"coordinates":[-122.391335,37.733396],"type":"Point"}
}