{
  "type": "Feature",
  "properties": {
    "addr:full":"3505 Cam del Rio S San Diego CA 92108",
    "addr:housenumber":"3505",
    "addr:postcode":"92108",
    "addr:street":"Cam Del Rio S",
    "iso:country":"US",
    "sg:address":"3505 Cam del Rio S",
    "sg:city":"San Diego",
    "sg:classifiers":[
        {
            "category":"Banks & Credit Unions",
            "subcategory":"Bank",
            "type":"Services"
        }
    ],
    "sg:phone":"+1 858 565 0244",
    "sg:postcode":"92108",
    "sg:province":"CA",
    "sg:tags":[
        "loan",
        "real estate"
    ],
    "wof:name":"Amerigroup Mortgage Corp",
    "wof:placetype":"venue"
},
  "geometry": {"coordinates":[-117.11765,32.777804],"type":"Point"}
}