{
  "type": "Feature",
  "properties": {
    "iso:country":"US",
    "sg:address":"3450 Baseline Ave",
    "sg:city":"Santa Ynez",
    "sg:classifiers":[
        {
            "category":"Shopping",
            "subcategory":"Used Merchandise",
            "type":"Retail Goods"
        }
    ],
    "sg:phone":"+1 805 688 3484",
    "sg:postcode":"93460",
    "sg:province":"CA",
    "sg:tags":[
        "book",
        "rare",
        "dealer"
    ],
    "wof:name":"Book Ends",
    "wof:placetype":"venue"
},
  "geometry": {"coordinates":[-120.084507,34.635513],"type":"Point"}
}