{
  "type": "Feature",
  "properties": {
    "addr:full":"10189 State Hwy 1 Point Reyes Sta CA 94956",
    "addr:housenumber":"10189",
    "addr:postcode":"94956",
    "addr:street":"State Hwy 1 Point Reyes",
    "iso:country":"US",
    "sg:address":"10189 State Hwy 1",
    "sg:city":"Point Reyes Sta",
    "sg:classifiers":[
        {
            "category":"Education",
            "subcategory":"Library",
            "type":"Public Place"
        }
    ],
    "sg:phone":"+1 415 663 1849",
    "sg:postcode":"94956",
    "sg:province":"CA",
    "wof:name":"Marin Literacy Program",
    "wof:placetype":"venue"
},
  "geometry": {"coordinates":[-122.805127,38.064247],"type":"Point"}
}