{
  "type": "Feature",
  "properties": {
    "iso:country":"US",
    "sg:address":"1440 9th St",
    "sg:city":"Fortuna",
    "sg:classifiers":[
        {
            "category":"Restaurant",
            "type":"Food & Drink"
        }
    ],
    "sg:phone":"+1 707 725 3254",
    "sg:postcode":"95540",
    "sg:province":"CA",
    "sg:tags":[
        "caterer"
    ],
    "wof:name":"Moonlight Catering",
    "wof:placetype":"venue"
},
  "geometry": {"coordinates":[-124.157277,40.603654],"type":"Point"}
}