{
  "type": "Feature",
  "properties": {
    "addr:full":"300 W Grand Ave Ste 301 Escondido CA 92025",
    "addr:housenumber":"300",
    "addr:postcode":"92025",
    "addr:street":"W Grand Ave Ste 301",
    "iso:country":"US",
    "sg:address":"300 W Grand Ave Ste 301",
    "sg:city":"Escondido",
    "sg:classifiers":[
        {
            "category":"Professional",
            "subcategory":"Lawyer & Legal Services",
            "type":"Services"
        }
    ],
    "sg:phone":"+1 760 990 1279",
    "sg:postcode":"92025",
    "sg:province":"CA",
    "sg:website":"www.bataraimmigrationlaw.com",
    "wof:name":"BATARA CARLOS",
    "wof:placetype":"venue"
},
  "geometry": {"coordinates":[-117.42954,33.120481],"type":"Point"}
}