{
  "type": "Feature",
  "properties": {
    "addr:full":"2440 Cam Ramon San Ramon CA 94583",
    "addr:housenumber":"2440",
    "addr:postcode":"ramon ca 94583",
    "addr:street":"Cam Ramon San",
    "iso:country":"US",
    "sg:address":"2440 Cam Ramon",
    "sg:city":"San Ramon",
    "sg:classifiers":[
        {
            "category":"Banks & Credit Unions",
            "subcategory":"Bank",
            "type":"Services"
        }
    ],
    "sg:phone":"+1 925 830 4777",
    "sg:postcode":"94583",
    "sg:province":"CA",
    "sg:tags":[
        "financing"
    ],
    "sg:website":"www.safefinancial.com",
    "wof:name":"SECURITY Alarm Financing Ent",
    "wof:placetype":"venue"
},
  "geometry": {"coordinates":[-121.963249,37.771869],"type":"Point"}
}