{
  "type": "Feature",
  "properties": {
    "iso:country":"US",
    "sg:address":"26487 State Hwy 99",
    "sg:city":"Tulare",
    "sg:classifiers":[
        {
            "category":"Farming",
            "subcategory":"Orchard",
            "type":"Manufacturing & Wholesale Goods"
        }
    ],
    "sg:phone":"+1 559 685 5463",
    "sg:postcode":"93274",
    "sg:province":"CA",
    "sg:tags":[
        "management",
        "pistachio",
        "farm",
        "almond",
        "process",
        "se"
    ],
    "wof:name":"A & P Growers Co-Op Inc",
    "wof:placetype":"venue"
},
  "geometry": {"coordinates":[-119.353941,36.251174],"type":"Point"}
}