{
  "type": "Feature",
  "properties": {
    "addr:full":"2730 Olive Hwy Oroville CA 95966",
    "addr:housenumber":"2730",
    "addr:postcode":"95966",
    "addr:street":"Olive Hwy",
    "iso:country":"US",
    "sg:address":"2730 Olive Hwy",
    "sg:city":"Oroville",
    "sg:classifiers":[
        {
            "category":"Restaurant",
            "type":"Food & Drink"
        }
    ],
    "sg:phone":"+1 530 534 0975",
    "sg:postcode":"95966",
    "sg:province":"CA",
    "wof:name":"Arby's",
    "wof:placetype":"venue"
},
  "geometry": {"coordinates":[-121.542676,39.504744],"type":"Point"}
}