{
  "type": "Feature",
  "properties": {
    "iso:country":"US",
    "sg:address":"1161 E Tulare Ave",
    "sg:city":"Tulare",
    "sg:phone":"+1 559 684 9152",
    "sg:postcode":"93274",
    "sg:province":"CA",
    "wof:name":"Ryan's Place",
    "wof:placetype":"venue"
},
  "geometry": {"coordinates":[-119.33036,36.209821],"type":"Point"}
}