{
  "type": "Feature",
  "properties": {
    "addr:full":"369 S Acacia Ave Fullerton CA 92831",
    "addr:housenumber":"369",
    "addr:postcode":"92831",
    "addr:street":"S Acacia Ave",
    "iso:country":"US",
    "sg:address":"369 S Acacia Ave",
    "sg:city":"Fullerton",
    "sg:classifiers":[
        {
            "category":"Sports & Exercise",
            "subcategory":"Sports Center",
            "type":"Entertainment"
        }
    ],
    "sg:phone":"+1 714 526 3772",
    "sg:postcode":"92831",
    "sg:province":"CA",
    "sg:tags":[
        "amateur",
        "team"
    ],
    "wof:name":"Fullerton Rangers Youth Soccer Club",
    "wof:placetype":"venue"
},
  "geometry": {"coordinates":[-117.899348,33.867466],"type":"Point"}
}