{
  "type": "Feature",
  "properties": {
    "iso:country":"US",
    "sg:address":"5335 Skyway Rd",
    "sg:city":"Paradise",
    "sg:classifiers":[
        {
            "category":"Retail",
            "subcategory":"Auto Repair",
            "type":"Services"
        }
    ],
    "sg:phone":"+1 530 872 4446",
    "sg:postcode":"95969",
    "sg:province":"CA",
    "sg:tags":[
        "repairing",
        "automobile"
    ],
    "wof:name":"Ken's Automotive Svc",
    "wof:placetype":"venue"
},
  "geometry": {"coordinates":[-121.637725,39.746274],"type":"Point"}
}