{
  "type": "Feature",
  "properties": {
    "iso:country":"US",
    "sg:address":"125 E 6th St",
    "sg:city":"Beaumont",
    "sg:classifiers":[
        {
            "category":"Retail",
            "subcategory":"Repair Shop",
            "type":"Services"
        }
    ],
    "sg:phone":"+1 951 845 3996",
    "sg:postcode":"92223",
    "sg:province":"CA",
    "sg:tags":[
        "welding"
    ],
    "sg:website":"www.hdrinfo.com",
    "wof:name":"Scott's Headers & Mufflers",
    "wof:placetype":"venue"
},
  "geometry": {"coordinates":[-116.981021,33.929344],"type":"Point"}
}