{
  "type": "Feature",
  "properties": {
    "addr:full":"Suite 100 San Francisco CA 94111",
    "addr:housenumber":"suite 100",
    "addr:postcode":"94111",
    "iso:country":"US",
    "sg:address":"Suite 100",
    "sg:city":"San Francisco",
    "sg:classifiers":[
        {
            "category":"Professional",
            "subcategory":"Computer Services",
            "type":"Services"
        }
    ],
    "sg:phone":"+1 415 503 8821",
    "sg:postcode":"94111",
    "sg:province":"CA",
    "sg:tags":[
        "iphone",
        "fitness",
        "smart-phone",
        "cycling-computer",
        "triathlon-training",
        "ant-wireless-sensors"
    ],
    "sg:website":"http://www.enkisports.com",
    "wof:name":"Enki Sports",
    "wof:placetype":"venue"
},
  "geometry": {"coordinates":[-122.39840700000001,37.799367],"type":"Point"}
}