{
  "type": "Feature",
  "properties": {
    "addr:full":"117 N Lomita Ave Ojai CA 93023",
    "addr:housenumber":"117",
    "addr:postcode":"93023",
    "addr:street":"N Lomita Ave",
    "iso:country":"US",
    "sg:address":"117 N Lomita Ave",
    "sg:city":"Ojai",
    "sg:classifiers":[
        {
            "category":"Retail",
            "subcategory":"Auto Repair",
            "type":"Services"
        }
    ],
    "sg:phone":"+1 805 646 2213",
    "sg:postcode":"93023",
    "sg:province":"CA",
    "sg:tags":[
        "repairing",
        "automobile"
    ],
    "wof:name":"Wilson Auto Svc",
    "wof:placetype":"venue"
},
  "geometry": {"coordinates":[-119.276071,34.449267],"type":"Point"}
}