{
  "type": "Feature",
  "properties": {
    "addr:full":"1261 Main St Weaverville CA 96093",
    "addr:housenumber":"1261",
    "addr:postcode":"96093",
    "addr:street":"Main St",
    "iso:country":"US",
    "sg:address":"1261 Main St",
    "sg:city":"Weaverville",
    "sg:classifiers":[
        {
            "category":"Government",
            "subcategory":"Office",
            "type":"Public Place"
        }
    ],
    "sg:phone":"+1 530 623 2059",
    "sg:postcode":"96093",
    "sg:province":"CA",
    "sg:tags":[
        "state",
        "program"
    ],
    "wof:name":"Motor Vehicle Dept",
    "wof:placetype":"venue"
},
  "geometry": {"coordinates":[-122.933025,40.725635],"type":"Point"}
}