{
  "type": "Feature",
  "properties": {
    "addr:full":"75 Russell Ave Susanville CA 96130",
    "addr:housenumber":"75",
    "addr:postcode":"96130",
    "addr:street":"Russell Ave",
    "iso:country":"US",
    "sg:address":"75 Russell Ave",
    "sg:city":"Susanville",
    "sg:classifiers":[
        {
            "category":"Home & Garden",
            "subcategory":"Furniture",
            "type":"Retail Goods"
        }
    ],
    "sg:phone":"+1 530 257 7352",
    "sg:postcode":"96130",
    "sg:province":"CA",
    "wof:name":"Keileys Custom Cabinets",
    "wof:placetype":"venue"
},
  "geometry": {"coordinates":[-120.63679500000001,40.411868],"type":"Point"}
}