{
  "type": "Feature",
  "properties": {
    "addr:full":"863 W Harbor Dr San Diego CA 92101",
    "addr:housenumber":"863",
    "addr:postcode":"92101",
    "addr:street":"W Harbor Dr",
    "iso:country":"US",
    "sg:address":"863 W Harbor Dr",
    "sg:city":"San Diego",
    "sg:classifiers":[
        {
            "category":"Home & Garden",
            "subcategory":"Home Furnishings",
            "type":"Retail Goods"
        }
    ],
    "sg:phone":"+1 619 233 4455",
    "sg:postcode":"92101",
    "sg:province":"CA",
    "sg:tags":[
        "mug"
    ],
    "wof:name":"Mugger",
    "wof:placetype":"venue"
},
  "geometry": {"coordinates":[-117.16952000000001,32.711397],"type":"Point"}
}