{
  "type": "Feature",
  "properties": {
    "iso:country":"US",
    "sg:address":"709 E Artesia Blvd",
    "sg:city":"Long Beach",
    "sg:classifiers":[
        {
            "category":"Organizations",
            "subcategory":"Religious Organization",
            "type":"Services"
        }
    ],
    "sg:phone":"+1 562 728 8179",
    "sg:postcode":"90805",
    "sg:province":"CA",
    "wof:name":"Beyond The 4 Walls",
    "wof:placetype":"venue"
},
  "geometry": {"coordinates":[-118.183801,33.874787],"type":"Point"}
}