{
  "type": "Feature",
  "properties": {
    "addr:full":"153 Bellview St San Andreas CA 95249",
    "addr:housenumber":"153",
    "addr:postcode":"95249",
    "addr:street":"Bellview St",
    "iso:country":"US",
    "sg:address":"153 Bellview St",
    "sg:city":"San Andreas",
    "sg:classifiers":[
        {
            "category":"Social Services",
            "type":"Services"
        }
    ],
    "sg:phone":"+1 209 754 4001",
    "sg:postcode":"95249",
    "sg:province":"CA",
    "sg:tags":[
        "organization",
        "welfare"
    ],
    "wof:name":"Association-Retarded Citizens",
    "wof:placetype":"venue"
},
  "geometry": {"coordinates":[-120.682711,38.196193],"type":"Point"}
}