{
  "type": "Feature",
  "properties": {
    "addr:full":"4226 21st St San Francisco CA 94114",
    "addr:housenumber":"4226",
    "addr:postcode":"94114",
    "addr:street":"21St St",
    "iso:country":"US",
    "sg:address":"4226 21st St",
    "sg:city":"San Francisco",
    "sg:classifiers":[
        {
            "category":"Building & Trades",
            "subcategory":"Landscaping Services",
            "type":"Services"
        }
    ],
    "sg:phone":"+1 415 821 3760",
    "sg:postcode":"94114",
    "sg:province":"CA",
    "sg:tags":[
        "landscape",
        "supply"
    ],
    "wof:name":"Janet Moyer Landscaping",
    "wof:placetype":"venue"
},
  "geometry": {"coordinates":[-122.438644,37.755537],"type":"Point"}
}