{
  "type": "Feature",
  "properties": {
    "iso:country":"US",
    "sg:address":"5651 Palmer Way",
    "sg:city":"Carlsbad",
    "sg:classifiers":[
        {
            "category":"Building & Trades",
            "subcategory":"Construction",
            "type":"Services"
        }
    ],
    "sg:phone":"+1 760 603 9204",
    "sg:postcode":"92008",
    "sg:province":"CA",
    "sg:tags":[
        "contractor"
    ],
    "wof:name":"Perini Building Co",
    "wof:placetype":"venue"
},
  "geometry": {"coordinates":[-117.272862,33.140806],"type":"Point"}
}