{
  "type": "Feature",
  "properties": {
    "addr:full":"447 Great Mall Dr Great Mall of the Bay Area Milpitas CA 95035",
    "addr:housenumber":"447",
    "addr:postcode":"95035",
    "addr:street":"Great Mall Dr Great Mall",
    "iso:country":"US",
    "sg:address":"447 Great Mall Dr Great Mall of the Bay Area",
    "sg:city":"Milpitas",
    "sg:classifiers":[
        {
            "category":"Shopping",
            "subcategory":"Clothing, Apparel, & Fashions",
            "type":"Retail Goods"
        },
        {
            "category":"Shopping",
            "subcategory":"Beauty & Cosmetics",
            "type":"Retail Goods"
        }
    ],
    "sg:phone":"+1 408 942 7598",
    "sg:postcode":"95035",
    "sg:province":"CA",
    "sg:tags":[
        "lingerie",
        "supply"
    ],
    "sg:website":"www.victoriassecret.com",
    "wof:name":"Victoria's Secret",
    "wof:placetype":"venue"
},
  "geometry": {"coordinates":[-121.89536200000001,37.417638],"type":"Point"}
}