{
  "type": "Feature",
  "properties": {
    "iso:country":"US",
    "sg:address":"2134 Park Ave",
    "sg:city":"Chico",
    "sg:classifiers":[
        {
            "category":"Wholesale",
            "subcategory":"Electrical",
            "type":"Manufacturing & Wholesale Goods"
        }
    ],
    "sg:phone":"+1 530 891 4641",
    "sg:postcode":"95928",
    "sg:province":"CA",
    "sg:tags":[
        "equipment",
        "electric",
        "supply"
    ],
    "wof:name":"Dan's Electrical Supply Co",
    "wof:placetype":"venue"
},
  "geometry": {"coordinates":[-121.820776,39.717876],"type":"Point"}
}