{
  "type": "Feature",
  "properties": {
    "addr:full":"2100 Tindall Ranch Rd Ukiah CA 95482",
    "addr:housenumber":"2100",
    "addr:postcode":"ca 95482",
    "addr:street":"Tindall Ranch Rd",
    "iso:country":"US",
    "sg:address":"2100 Tindall Ranch Rd",
    "sg:city":"Ukiah",
    "sg:classifiers":[
        {
            "category":"Manufacturing",
            "subcategory":"Jewelry",
            "type":"Manufacturing & Wholesale Goods"
        }
    ],
    "sg:phone":"+1 707 462 2728",
    "sg:postcode":"95482",
    "sg:province":"CA",
    "sg:tags":[
        "novelty"
    ],
    "wof:name":"Skiera Productions",
    "wof:placetype":"venue"
},
  "geometry": {"coordinates":[-123.1602,39.125303],"type":"Point"}
}