{
  "type": "Feature",
  "properties": {
    "iso:country":"US",
    "sg:address":"5731 Blue Gum Ave",
    "sg:city":"Modesto",
    "sg:classifiers":[
        {
            "category":"Wholesale",
            "subcategory":"Apparel",
            "type":"Manufacturing & Wholesale Goods"
        },
        {
            "category":"Shopping",
            "subcategory":"Crafts & Fabrics",
            "type":"Retail Goods"
        }
    ],
    "sg:phone":"+1 209 527 5710",
    "sg:postcode":"95358",
    "sg:province":"CA",
    "sg:tags":[
        "sewing"
    ],
    "wof:name":"Countryside Fabric Wholesale",
    "wof:placetype":"venue"
},
  "geometry": {"coordinates":[-121.09356,37.660013],"type":"Point"}
}