{
  "type": "Feature",
  "properties": {
    "iso:country":"US",
    "sg:address":"3932 Rockford Dr",
    "sg:city":"Antioch",
    "sg:classifiers":[
        {
            "category":"Professional",
            "type":"Services"
        }
    ],
    "sg:phone":"+1 925 207 8273",
    "sg:postcode":"94509",
    "sg:province":"CA",
    "wof:name":"Sol Pda",
    "wof:placetype":"venue"
},
  "geometry": {"coordinates":[-121.791447,37.98276],"type":"Point"}
}