{
  "type": "Feature",
  "properties": {
    "iso:country":"US",
    "sg:address":"Winston's Beach Club 1921 Bacon St",
    "sg:city":"San Diego",
    "sg:classifiers":[
        {
            "category":"Arts & Performance",
            "subcategory":"Comedy Club",
            "type":"Entertainment"
        }
    ],
    "sg:phone":"+1 619 222 6822",
    "sg:postcode":"92107",
    "sg:province":"CA",
    "sg:website":"www.myspace.com/oceanbeachcomedy",
    "wof:name":"Ocean Beach Comedy",
    "wof:placetype":"venue"
},
  "geometry": {"coordinates":[-117.25073,32.747248],"type":"Point"}
}