{
  "type": "Feature",
  "properties": {
    "addr:full":"6395 Pony Express Trl Pollock Pines CA 95726",
    "addr:housenumber":"6395",
    "addr:postcode":"95726",
    "addr:street":"Pony Express Trl",
    "iso:country":"US",
    "sg:address":"6395 Pony Express Trl",
    "sg:city":"Pollock Pines",
    "sg:classifiers":[
        {
            "category":"Wholesale",
            "subcategory":"Computers",
            "type":"Manufacturing & Wholesale Goods"
        }
    ],
    "sg:phone":"+1 530 644 2226",
    "sg:postcode":"95726",
    "sg:province":"CA",
    "sg:website":"www.radioshack.com",
    "wof:name":"Radioshack",
    "wof:placetype":"venue"
},
  "geometry": {"coordinates":[-120.58200100000001,38.762901],"type":"Point"}
}