{
  "type": "Feature",
  "properties": {
    "addr:full":"659 3rd Ave Ste D Chula Vista CA 91910",
    "addr:housenumber":"659",
    "addr:postcode":"91910",
    "addr:street":"3Rd Ave Ste D",
    "iso:country":"US",
    "sg:address":"659 3rd Ave Ste D",
    "sg:city":"Chula Vista",
    "sg:classifiers":[
        {
            "category":"Professional",
            "subcategory":"Lawyer & Legal Services",
            "type":"Services"
        }
    ],
    "sg:phone":"+1 619 498 0667",
    "sg:postcode":"91910",
    "sg:province":"CA",
    "wof:name":"Morell Frank Torres Attorney At Law",
    "wof:placetype":"venue"
},
  "geometry": {"coordinates":[-117.074997,32.628899],"type":"Point"}
}