{
  "type": "Feature",
  "properties": {
    "addr:full":"920 E Cooley Ave San Bernardino CA 92408",
    "addr:housenumber":"920",
    "addr:postcode":"92408",
    "addr:street":"E Cooley Ave",
    "iso:country":"US",
    "sg:address":"920 E Cooley Ave",
    "sg:city":"San Bernardino",
    "sg:classifiers":[
        {
            "category":"Professional",
            "subcategory":"Secretarial Services",
            "type":"Services"
        }
    ],
    "sg:phone":"+1 909 796 8883",
    "sg:postcode":"92408",
    "sg:province":"CA",
    "sg:tags":[
        "transcription",
        "medical"
    ],
    "wof:name":"Intelliquick Medical Trnscrptn",
    "wof:placetype":"venue"
},
  "geometry": {"coordinates":[-117.265247,34.076081],"type":"Point"}
}