{
  "type": "Feature",
  "properties": {
    "addr:full":"3851 State Rte 59 Merced CA 95348",
    "addr:housenumber":"3851",
    "addr:postcode":"95348",
    "addr:street":"State Rte 59",
    "iso:country":"US",
    "sg:address":"3851 State Rte 59",
    "sg:city":"Merced",
    "sg:classifiers":[
        {
            "category":"Food & Beverages",
            "subcategory":"Groceries & Convenience Stores",
            "type":"Retail Goods"
        }
    ],
    "sg:phone":"+1 209 726 9113",
    "sg:postcode":"95348",
    "sg:province":"CA",
    "wof:name":"ACS Mini Mart",
    "wof:placetype":"venue"
},
  "geometry": {"coordinates":[-120.504261,37.339744],"type":"Point"}
}