{
  "type": "Feature",
  "properties": {
    "iso:country":"US",
    "sg:address":"616 S Del Mar Ave Ste K",
    "sg:city":"San Gabriel",
    "sg:classifiers":[
        {
            "category":"Government",
            "subcategory":"Police Station",
            "type":"Public Place"
        },
        {
            "category":"Personal",
            "type":"Services"
        },
        {
            "category":"Professional",
            "subcategory":"Lawyer & Legal Services",
            "type":"Services"
        },
        {
            "category":"Banks & Credit Unions",
            "subcategory":"Financial Services",
            "type":"Services"
        }
    ],
    "sg:phone":"+1 626 287 2489",
    "sg:postcode":"91776",
    "sg:province":"CA",
    "sg:tags":[
        "department",
        "local"
    ],
    "sg:website":"www.citybailbonds.com",
    "wof:name":"CITY Bail Bonds",
    "wof:placetype":"venue"
},
  "geometry": {"coordinates":[-118.099559,34.094408],"type":"Point"}
}