{
  "type": "Feature",
  "properties": {
    "iso:country":"US",
    "sg:address":"5221 Deer Valley Rd",
    "sg:city":"Rescue",
    "sg:classifiers":[
        {
            "category":"Professional",
            "subcategory":"Business Services",
            "type":"Services"
        }
    ],
    "sg:phone":"+1 530 677 1868",
    "sg:postcode":"95672",
    "sg:province":"CA",
    "sg:tags":[
        "fire",
        "protection"
    ],
    "wof:name":"Rescue Fire Protection Dist",
    "wof:placetype":"venue"
},
  "geometry": {"coordinates":[-120.95207000000001,38.711511],"type":"Point"}
}