{
  "type": "Feature",
  "properties": {
    "addr:full":"144 E Emerson Ave Orange CA 92865",
    "addr:housenumber":"144",
    "addr:postcode":"92865",
    "addr:street":"E Emerson Ave",
    "iso:country":"US",
    "sg:address":"144 E Emerson Ave",
    "sg:city":"Orange",
    "sg:classifiers":[
        {
            "category":"Real Estate",
            "subcategory":"Real Estate Services",
            "type":"Services"
        }
    ],
    "sg:phone":"+1 714 974 7799",
    "sg:postcode":"92865",
    "sg:province":"CA",
    "wof:name":"Team Advantage Real Estate Owned",
    "wof:placetype":"venue"
},
  "geometry": {"coordinates":[-117.852503,33.82449],"type":"Point"}
}