{
  "type": "Feature",
  "properties": {
    "iso:country":"US",
    "sg:address":"2500 N Main St",
    "sg:city":"Walnut Creek",
    "sg:classifiers":[
        {
            "category":"Wholesale",
            "subcategory":"Jewelry",
            "type":"Manufacturing & Wholesale Goods"
        }
    ],
    "sg:phone":"+1 925 935 6600",
    "sg:postcode":"94597",
    "sg:province":"CA",
    "sg:tags":[
        "diamond"
    ],
    "wof:name":"Shane Co",
    "wof:placetype":"venue"
},
  "geometry": {"coordinates":[-122.06559799999999,37.917701],"type":"Point"}
}