{
  "type": "Feature",
  "properties": {
    "iso:country":"US",
    "sg:address":"2046 Mar Vista Drive",
    "sg:city":"Newport Beach",
    "sg:classifiers":[
        {
            "category":"Education",
            "subcategory":"School",
            "type":"Public Place"
        },
        {
            "category":"Organizations",
            "subcategory":"Religious Organization",
            "type":"Services"
        }
    ],
    "sg:phone":"+1 949 644 1166",
    "sg:postcode":"92660",
    "sg:province":"CA",
    "sg:tags":[
        "high",
        "middle",
        "elementary"
    ],
    "wof:name":"Our Lady Queen of Angels School",
    "wof:placetype":"venue"
},
  "geometry": {"coordinates":[-117.87898,33.632336],"type":"Point"}
}