{
  "type": "Feature",
  "properties": {
    "addr:full":"6005 El Camino Real Atascadero CA 93422",
    "addr:housenumber":"6005",
    "addr:postcode":"93422",
    "addr:street":"El Camino Real",
    "iso:country":"US",
    "sg:address":"6005 El Camino Real",
    "sg:city":"Atascadero",
    "sg:phone":"+1 805 461 5143",
    "sg:postcode":"93422",
    "sg:province":"CA",
    "wof:name":"Carlton Restaurant & Grill",
    "wof:placetype":"venue"
},
  "geometry": {"coordinates":[-120.670391,35.489362],"type":"Point"}
}