{
  "type": "Feature",
  "properties": {
    "iso:country":"US",
    "sg:address":"59465 State Hwy 74",
    "sg:city":"Mountain Center",
    "sg:classifiers":[
        {
            "category":"Real Estate",
            "subcategory":"Real Estate Agent",
            "type":"Services"
        }
    ],
    "sg:phone":"+1 951 659 5013",
    "sg:postcode":"92561",
    "sg:province":"CA",
    "wof:name":"Dyson & Dyson",
    "wof:placetype":"venue"
},
  "geometry": {"coordinates":[-116.62154,33.607733],"type":"Point"}
}