{
  "type": "Feature",
  "properties": {
    "iso:country":"US",
    "sg:address":"1523 Queens Ct",
    "sg:city":"Claremont",
    "sg:classifiers":[
        {
            "category":"Professional",
            "subcategory":"Lawyer & Legal Services",
            "type":"Services"
        }
    ],
    "sg:phone":"+1 909 621 9925",
    "sg:postcode":"91711",
    "sg:province":"CA",
    "sg:tags":[
        "convention",
        "reporters-court"
    ],
    "wof:name":"Clarece Peters English Offices",
    "wof:placetype":"venue"
},
  "geometry": {"coordinates":[-117.72575999999999,34.111534],"type":"Point"}
}