{
  "type": "Feature",
  "properties": {
    "iso:country":"US",
    "sg:address":"537 W Harding Way",
    "sg:city":"Stockton",
    "sg:classifiers":[
        {
            "category":"Professional",
            "subcategory":"Business Services",
            "type":"Services"
        }
    ],
    "sg:phone":"+1 209 464 9303",
    "sg:postcode":"95204",
    "sg:province":"CA",
    "sg:tags":[
        "consultant",
        "production",
        "music"
    ],
    "wof:name":"Platinum Plus Productions",
    "wof:placetype":"venue"
},
  "geometry": {"coordinates":[-121.302578,37.966114],"type":"Point"}
}