{
  "type": "Feature",
  "properties": {
    "addr:full":"9050 Carron Dr Pico Rivera CA 90660",
    "addr:postcode":"9050;90660",
    "addr:street":"Carron Dr",
    "iso:country":"US",
    "sg:address":"9050 Carron Dr",
    "sg:city":"Pico Rivera",
    "sg:classifiers":[
        {
            "category":"Shopping",
            "subcategory":"Discount & Variety Stores",
            "type":"Retail Goods"
        }
    ],
    "sg:phone":"+1 562 949 5948",
    "sg:postcode":"90660",
    "sg:province":"CA",
    "sg:tags":[
        "merchandise",
        "general"
    ],
    "wof:name":"Rostar Trading",
    "wof:placetype":"venue"
},
  "geometry": {"coordinates":[-118.093855,33.984374],"type":"Point"}
}