{
  "type": "Feature",
  "properties": {
    "addr:full":"1361 N Kraemer Blvd Anaheim CA 92806",
    "addr:housenumber":"1361",
    "addr:postcode":"92806",
    "addr:street":"N Kraemer Blvd",
    "iso:country":"US",
    "sg:address":"1361 N Kraemer Blvd",
    "sg:city":"Anaheim",
    "sg:classifiers":[
        {
            "category":"Retail",
            "subcategory":"Auto Repair",
            "type":"Services"
        }
    ],
    "sg:phone":"+1 714 630 8363",
    "sg:postcode":"92806",
    "sg:province":"CA",
    "sg:tags":[
        "body",
        "automobile",
        "painting",
        "repairing"
    ],
    "sg:website":"http://www.kraemercollision.com",
    "wof:name":"Kraemer Auto",
    "wof:placetype":"venue"
},
  "geometry": {"coordinates":[-117.86053800000001,33.860019],"type":"Point"}
}