{
  "type": "Feature",
  "properties": {
    "addr:full":"1307 N Texas St Fairfield CA 94533",
    "addr:housenumber":"1307",
    "addr:postcode":"94533",
    "addr:street":"N Texas St",
    "iso:country":"US",
    "sg:address":"1307 N Texas St",
    "sg:city":"Fairfield",
    "sg:classifiers":[
        {
            "category":"Autos & Motor Vehicles",
            "subcategory":"Automobile Sales",
            "type":"Retail Goods"
        }
    ],
    "sg:phone":"+1 707 429 8800",
    "sg:postcode":"94533",
    "sg:province":"CA",
    "sg:tags":[
        "new",
        "used",
        "boat"
    ],
    "wof:name":"Fairfield Auto Sales",
    "wof:placetype":"venue"
},
  "geometry": {"coordinates":[-122.03419100000001,38.254939],"type":"Point"}
}