{
  "type": "Feature",
  "properties": {
    "addr:full":"1810 Hillhurst Ave Los Angeles CA 90027",
    "addr:housenumber":"1810",
    "addr:postcode":"90027",
    "addr:street":"Hillhurst Ave",
    "iso:country":"US",
    "sg:address":"1810 Hillhurst Ave",
    "sg:city":"Los Angeles",
    "sg:classifiers":[
        {
            "category":"Personal",
            "subcategory":"Beauty Salon",
            "type":"Services"
        }
    ],
    "sg:phone":"+1 323 661 4370",
    "sg:postcode":"90027",
    "sg:province":"CA",
    "wof:name":"Glamour Technician",
    "wof:placetype":"venue"
},
  "geometry": {"coordinates":[-118.287336,34.104323],"type":"Point"}
}