{
  "type": "Feature",
  "properties": {
    "iso:country":"US",
    "sg:address":"13512 Harbor Blvd",
    "sg:city":"Garden Grove",
    "sg:classifiers":[
        {
            "category":"Restaurant",
            "type":"Food & Drink"
        }
    ],
    "sg:menulink":"http://www.allmenus.com/ca/anaheim-santa-ana-garden-grove/238809-yoshinoya/menu/",
    "sg:phone":"+1 714 534 4355",
    "sg:postcode":"92843",
    "sg:province":"CA",
    "sg:tags":[
        "korean",
        "noodle",
        "bar",
        "japanese",
        "asian"
    ],
    "wof:name":"Yoshinoya",
    "wof:placetype":"venue"
},
  "geometry": {"coordinates":[-117.919956,33.766787],"type":"Point"}
}