{
  "type": "Feature",
  "properties": {
    "iso:country":"US",
    "sg:address":"1905 Covillaud St Ste D",
    "sg:city":"Marysville",
    "sg:classifiers":[
        {
            "category":"Restaurant",
            "type":"Food & Drink"
        }
    ],
    "sg:phone":"+1 530 743 9507",
    "sg:postcode":"95901",
    "sg:province":"CA",
    "sg:tags":[
        "style",
        "family"
    ],
    "wof:name":"Hotdog Junction",
    "wof:placetype":"venue"
},
  "geometry": {"coordinates":[-121.577685,39.157006],"type":"Point"}
}