{
  "type": "Feature",
  "properties": {
    "iso:country":"US",
    "sg:address":"11720 Bartlett Ave",
    "sg:city":"Adelanto",
    "sg:classifiers":[
        {
            "category":"Personal",
            "subcategory":"Beauty Salon",
            "type":"Services"
        }
    ],
    "sg:phone":"+1 760 246 0393",
    "sg:postcode":"92301",
    "sg:province":"CA",
    "sg:tags":[
        "hair",
        "stylist"
    ],
    "wof:name":"Trendsetterz Hair Salon",
    "wof:placetype":"venue"
},
  "geometry": {"coordinates":[-117.409128,34.579233],"type":"Point"}
}