{
  "type": "Feature",
  "properties": {
    "iso:country":"US",
    "sg:address":"10311 S Vermont Ave",
    "sg:city":"Los Angeles",
    "sg:classifiers":[
        {
            "category":"Building & Trades",
            "subcategory":"Plumbing",
            "type":"Services"
        }
    ],
    "sg:phone":"+1 323 757 6993",
    "sg:postcode":"90044",
    "sg:province":"CA",
    "wof:name":"Greene & Son Plumbing Inc.",
    "wof:placetype":"venue"
},
  "geometry": {"coordinates":[-118.29161499999999,33.96003],"type":"Point"}
}