{
  "type": "Feature",
  "properties": {
    "addr:full":"5300 Soquel Ave Santa Cruz CA 95062",
    "addr:housenumber":"5300",
    "addr:postcode":"95062",
    "addr:street":"Soquel Ave",
    "iso:country":"US",
    "sg:address":"5300 Soquel Ave",
    "sg:city":"Santa Cruz",
    "sg:classifiers":[
        {
            "category":"Wholesale",
            "subcategory":"Jewelry",
            "type":"Manufacturing & Wholesale Goods"
        }
    ],
    "sg:phone":"+1 831 464 8950",
    "sg:postcode":"95062",
    "sg:province":"CA",
    "sg:tags":[
        "jeweler"
    ],
    "wof:name":"Flying Lizard Design",
    "wof:placetype":"venue"
},
  "geometry": {"coordinates":[-121.976392,36.984296],"type":"Point"}
}