{
  "type": "Feature",
  "properties": {
    "iso:country":"US",
    "sg:address":"340 S Farrell Dr Ste A208",
    "sg:city":"Palm Springs",
    "sg:classifiers":[
        {
            "category":"Health Services",
            "subcategory":"Doctor",
            "type":"Services"
        }
    ],
    "sg:phone":"+1 760 864 6566",
    "sg:postcode":"92262",
    "sg:province":"CA",
    "wof:name":"Verghese Vinita MD",
    "wof:placetype":"venue"
},
  "geometry": {"coordinates":[-116.517543,33.817881],"type":"Point"}
}