{
  "type": "Feature",
  "properties": {
    "addr:full":"305 W H St Brawley CA 92227",
    "addr:housenumber":"305",
    "addr:postcode":"92227",
    "addr:street":"W H St",
    "iso:country":"US",
    "sg:address":"305 W H St",
    "sg:city":"Brawley",
    "sg:classifiers":[
        {
            "category":"Place Of Worship",
            "subcategory":"Church",
            "type":"Public Place"
        },
        {
            "category":"Place Of Worship",
            "type":"Public Place"
        }
    ],
    "sg:phone":"+1 760 344 8806",
    "sg:postcode":"92227",
    "sg:province":"CA",
    "sg:tags":[
        "churches-episcopal-anglican",
        "churches-episcopal"
    ],
    "wof:name":"All Saints Episcopal Church",
    "wof:placetype":"venue"
},
  "geometry": {"coordinates":[-115.54730000000001,32.97641],"type":"Point"}
}