{
  "type": "Feature",
  "properties": {
    "addr:full":"3142 E State Hwy 140 Merced CA 95340",
    "addr:housenumber":"3142",
    "addr:postcode":"95340",
    "addr:street":"E State Hwy 140",
    "iso:country":"US",
    "sg:address":"3142 E State Hwy 140",
    "sg:city":"Merced",
    "sg:classifiers":[
        {
            "category":"Wholesale",
            "subcategory":"Electrical",
            "type":"Manufacturing & Wholesale Goods"
        }
    ],
    "sg:phone":"+1 209 722 3533",
    "sg:postcode":"95340",
    "sg:province":"CA",
    "sg:tags":[
        "electronic",
        "health",
        "o"
    ],
    "wof:name":"A & L Enterprises",
    "wof:placetype":"venue"
},
  "geometry": {"coordinates":[-120.433503,37.295091],"type":"Point"}
}