{
  "type": "Feature",
  "properties": {
    "addr:full":"1616 G St San Diego CA 92101",
    "addr:housenumber":"1616",
    "addr:postcode":"92101",
    "addr:street":"G St",
    "iso:country":"US",
    "sg:address":"1616 G St",
    "sg:city":"San Diego",
    "sg:classifiers":[
        {
            "category":"Personal",
            "type":"Services"
        }
    ],
    "sg:phone":"+1 619 302 4004",
    "sg:postcode":"92101",
    "sg:province":"CA",
    "sg:tags":[
        "local"
    ],
    "sg:website":"www.greenshredding.com",
    "wof:name":"Green Shredding",
    "wof:placetype":"venue"
},
  "geometry": {"coordinates":[-117.149412,32.712662],"type":"Point"}
}