{
  "type": "Feature",
  "properties": {
    "addr:full":"40234 Dutton St Cherry Valley CA 92223",
    "addr:housenumber":"40234",
    "addr:postcode":"92223",
    "addr:street":"Dutton St",
    "iso:country":"US",
    "sg:address":"40234 Dutton St",
    "sg:city":"Cherry Valley",
    "sg:classifiers":[
        {
            "category":"Wholesale",
            "subcategory":"Sporting Goods",
            "type":"Manufacturing & Wholesale Goods"
        }
    ],
    "sg:phone":"+1 951 769 1654",
    "sg:postcode":"92223",
    "sg:province":"CA",
    "sg:tags":[
        "bicycle"
    ],
    "wof:name":"Hope Technology USA",
    "wof:placetype":"venue"
},
  "geometry": {"coordinates":[-116.963415,33.974324],"type":"Point"}
}