{
  "type": "Feature",
  "properties": {
    "iso:country":"US",
    "sg:address":"7520 Allston Ct",
    "sg:city":"Sacramento",
    "sg:classifiers":[
        {
            "category":"Professional",
            "type":"Services"
        }
    ],
    "sg:phone":"+1 916 332 6389",
    "sg:postcode":"95842",
    "sg:province":"CA",
    "wof:name":"3fire",
    "wof:placetype":"venue"
},
  "geometry": {"coordinates":[-121.35884900000001,38.703129],"type":"Point"}
}