{
  "type": "Feature",
  "properties": {
    "addr:full":"1944 W Glenoaks Blvd Glendale CA 91201",
    "addr:housenumber":"1944",
    "addr:postcode":"91201",
    "addr:street":"W Glenoaks Blvd",
    "iso:country":"US",
    "sg:address":"1944 W Glenoaks Blvd",
    "sg:city":"Glendale",
    "sg:classifiers":[
        {
            "category":"Health Services",
            "subcategory":"Health Practitioner",
            "type":"Services"
        }
    ],
    "sg:phone":"+1 818 548 4450",
    "sg:postcode":"91201",
    "sg:province":"CA",
    "sg:tags":[
        "therapy",
        "physical"
    ],
    "wof:name":"Pon Physical Therapy Inc",
    "wof:placetype":"venue"
},
  "geometry": {"coordinates":[-118.29521200000001,34.17503],"type":"Point"}
}