{
  "type": "Feature",
  "properties": {
    "iso:country":"US",
    "sg:address":"118 S Cordova St",
    "sg:city":"Burbank",
    "sg:classifiers":[
        {
            "category":"Manufacturing",
            "subcategory":"Retail Goods",
            "type":"Manufacturing & Wholesale Goods"
        }
    ],
    "sg:phone":"+1 818 556 3493",
    "sg:postcode":"91505",
    "sg:province":"CA",
    "sg:tags":[
        "product",
        "mfg"
    ],
    "wof:name":"Phase 2 Sales International",
    "wof:placetype":"venue"
},
  "geometry": {"coordinates":[-118.337767,34.151097],"type":"Point"}
}