{
  "type": "Feature",
  "properties": {
    "iso:country":"US",
    "sg:address":"3820 del Amo Blvd",
    "sg:city":"Torrance",
    "sg:classifiers":[
        {
            "category":"Professional",
            "type":"Services"
        }
    ],
    "sg:phone":"+1 310 370 3134",
    "sg:postcode":"90503",
    "sg:province":"CA",
    "wof:name":"Praxis Computing",
    "wof:placetype":"venue"
},
  "geometry": {"coordinates":[-118.353612,33.84859],"type":"Point"}
}