{
  "type": "Feature",
  "properties": {
    "addr:full":"1155 Graves Ave El Cajon CA 92021",
    "addr:housenumber":"1155",
    "addr:postcode":"92021",
    "addr:street":"Graves Ave",
    "iso:country":"US",
    "sg:address":"1155 Graves Ave",
    "sg:city":"El Cajon",
    "sg:classifiers":[
        {
            "category":"Restaurant",
            "type":"Food & Drink"
        }
    ],
    "sg:phone":"+1 619 593 1155",
    "sg:postcode":"92021",
    "sg:province":"CA",
    "wof:name":"Boomers",
    "wof:placetype":"venue"
},
  "geometry": {"coordinates":[-116.96199799999999,32.810902],"type":"Point"}
}