{
  "type": "Feature",
  "properties": {
    "addr:full":"8854 Greenback Ln Ste 2 Orangevale CA 95662",
    "addr:housenumber":"8854",
    "addr:postcode":"95662",
    "addr:street":"Greenback Ln Ste 2",
    "iso:country":"US",
    "sg:address":"8854 Greenback Ln Ste 2",
    "sg:city":"Orangevale",
    "sg:classifiers":[
        {
            "category":"Personal",
            "subcategory":"Massage",
            "type":"Services"
        }
    ],
    "sg:phone":"+1 916 844 5064",
    "sg:postcode":"95662",
    "sg:province":"CA",
    "wof:name":"James Oates CMT",
    "wof:placetype":"venue"
},
  "geometry": {"coordinates":[-121.227802,38.678385],"type":"Point"}
}