{
  "type": "Feature",
  "properties": {
    "iso:country":"US",
    "sg:address":"3358 Lerwick Rd",
    "sg:city":"Sacramento",
    "sg:classifiers":[
        {
            "category":"Building & Trades",
            "subcategory":"Construction",
            "type":"Services"
        }
    ],
    "sg:phone":"+1 916 488 8280",
    "sg:postcode":"95821",
    "sg:province":"CA",
    "sg:tags":[
        "consultant",
        "management"
    ],
    "wof:name":"EPO Lerwick",
    "wof:placetype":"venue"
},
  "geometry": {"coordinates":[-121.38703599999999,38.633583],"type":"Point"}
}