{
  "type": "Feature",
  "properties": {
    "addr:full":"1850 W Silver Lake Dr Los Angeles CA 90026",
    "addr:housenumber":"1850",
    "addr:postcode":"90026",
    "addr:street":"W Silver Lake Dr",
    "iso:country":"US",
    "sg:address":"1850 W Silver Lake Dr",
    "sg:city":"Los Angeles",
    "sg:classifiers":[
        {
            "category":"Park",
            "type":"Public Place"
        }
    ],
    "sg:phone":"+1 323 644 3946",
    "sg:postcode":"90026",
    "sg:province":"CA",
    "sg:website":"www.laparks.org/dos/reccenter/fa...",
    "wof:name":"Silver Lake Recreation Center",
    "wof:placetype":"venue"
},
  "geometry": {"coordinates":[-118.26687800000001,34.092622],"type":"Point"}
}