{
  "type": "Feature",
  "properties": {
    "addr:full":"7920 Deering Ave Canoga Park CA 91304",
    "addr:housenumber":"7920",
    "addr:postcode":"91304",
    "addr:street":"Deering Ave",
    "iso:country":"US",
    "sg:address":"7920 Deering Ave",
    "sg:city":"Canoga Park",
    "sg:classifiers":[
        {
            "category":"Manufacturing",
            "subcategory":"Retail Goods",
            "type":"Manufacturing & Wholesale Goods"
        }
    ],
    "sg:phone":"+1 818 610 2400",
    "sg:postcode":"91304",
    "sg:province":"CA",
    "sg:tags":[
        "re",
        "manufacturer",
        "cartridge",
        "toner"
    ],
    "sg:website":"www.imagetechnologiesusa.com",
    "wof:name":"Image Technologies",
    "wof:placetype":"venue"
},
  "geometry": {"coordinates":[-118.59658399999999,34.208887],"type":"Point"}
}