{
  "type": "Feature",
  "properties": {
    "iso:country":"US",
    "sg:address":"22103 Vanowen St",
    "sg:city":"Canoga Park",
    "sg:classifiers":[
        {
            "category":"Education",
            "subcategory":"Preschool",
            "type":"Public Place"
        },
        {
            "category":"Education",
            "subcategory":"School",
            "type":"Public Place"
        }
    ],
    "sg:phone":"+1 818 884 9807",
    "sg:postcode":"91303",
    "sg:province":"CA",
    "sg:tags":[
        "elementary"
    ],
    "wof:name":"West Valley Christian Church",
    "wof:placetype":"venue"
},
  "geometry": {"coordinates":[-118.608002,34.1936],"type":"Point"}
}