{
  "type": "Feature",
  "properties": {
    "iso:country":"US",
    "sg:address":"2459 64th Ave",
    "sg:city":"Oakland",
    "sg:classifiers":[
        {
            "category":"Shopping",
            "subcategory":"Music",
            "type":"Retail Goods"
        }
    ],
    "sg:phone":"+1 510 632 5304",
    "sg:postcode":"94605",
    "sg:province":"CA",
    "wof:name":"Baugh Records",
    "wof:placetype":"venue"
},
  "geometry": {"coordinates":[-122.186954,37.768846],"type":"Point"}
}