{
  "type": "Feature",
  "properties": {
    "addr:full":"3831 Hughes Avenue Culver City CA 90232",
    "addr:housenumber":"3831",
    "addr:postcode":"90232",
    "addr:street":"Hughes Avenue",
    "iso:country":"US",
    "sg:address":"3831 Hughes Avenue",
    "sg:city":"Culver City",
    "sg:classifiers":[
        {
            "category":"Health Services",
            "subcategory":"Doctor",
            "type":"Services"
        }
    ],
    "sg:phone":"+1 310 202 8811",
    "sg:postcode":"90232",
    "sg:province":"CA",
    "wof:name":"Healy Michael D MD",
    "wof:placetype":"venue"
},
  "geometry": {"coordinates":[-118.398403,34.02277],"type":"Point"}
}