{
  "type": "Feature",
  "properties": {
    "iso:country":"US",
    "sg:address":"302 E Bard Rd",
    "sg:city":"Oxnard",
    "sg:classifiers":[
        {
            "category":"Wholesale",
            "subcategory":"Fruits & Vegetables",
            "type":"Manufacturing & Wholesale Goods"
        }
    ],
    "sg:phone":"+1 805 377 4612",
    "sg:postcode":"93033",
    "sg:province":"CA",
    "wof:name":"Royal Strawberries",
    "wof:placetype":"venue"
},
  "geometry": {"coordinates":[-119.175659,34.160895],"type":"Point"}
}