{
  "type": "Feature",
  "properties": {
    "addr:full":"411 N Broadway Santa Ana CA 92701",
    "addr:housenumber":"411",
    "addr:postcode":"92701",
    "addr:street":"N Broadway",
    "iso:country":"US",
    "sg:address":"411 N Broadway",
    "sg:city":"Santa Ana",
    "sg:classifiers":[
        {
            "category":"Banks & Credit Unions",
            "subcategory":"Bank",
            "type":"Services"
        }
    ],
    "sg:phone":"+1 714 972 0741",
    "sg:postcode":"92701",
    "sg:province":"CA",
    "sg:tags":[
        "money",
        "order"
    ],
    "wof:name":"Super Envios",
    "wof:placetype":"venue"
},
  "geometry": {"coordinates":[-117.869665,33.748808],"type":"Point"}
}