{
  "type": "Feature",
  "properties": {
    "iso:country":"US",
    "sg:address":"3916 22nd Ave",
    "sg:city":"Sacramento",
    "sg:classifiers":[
        {
            "category":"Manufacturing",
            "subcategory":"Furniture",
            "type":"Manufacturing & Wholesale Goods"
        }
    ],
    "sg:phone":"+1 916 454 1900",
    "sg:postcode":"95820",
    "sg:province":"CA",
    "sg:tags":[
        "household",
        "wood",
        "mfg"
    ],
    "wof:name":"Mobile Screen Service",
    "wof:placetype":"venue"
},
  "geometry": {"coordinates":[-121.462822,38.532989],"type":"Point"}
}