{
  "type": "Feature",
  "properties": {
    "iso:country":"US",
    "sg:address":"8687 Wilshire Blvd",
    "sg:city":"Beverly Hills",
    "sg:classifiers":[
        {
            "category":"Building & Trades",
            "subcategory":"Plumbing",
            "type":"Services"
        }
    ],
    "sg:phone":"+1 310 882 6327",
    "sg:postcode":"90211",
    "sg:province":"CA",
    "sg:website":"bit.ly/dyFTnB",
    "wof:name":"Five Stars Plumber Beverly Hills",
    "wof:placetype":"venue"
},
  "geometry": {"coordinates":[-118.381241,34.066473],"type":"Point"}
}