{
  "type": "Feature",
  "properties": {
    "iso:country":"US",
    "sg:address":"4225 Sanborn Avenue",
    "sg:city":"Lynwood",
    "sg:classifiers":[
        {
            "category":"Education",
            "subcategory":"School",
            "type":"Public Place"
        }
    ],
    "sg:phone":"+1 310 603 1513",
    "sg:postcode":"90262",
    "sg:province":"CA",
    "sg:tags":[
        "high",
        "middle",
        "elementary"
    ],
    "wof:name":"Lynwood Unified School District",
    "wof:placetype":"venue"
},
  "geometry": {"coordinates":[-118.19011,33.924635],"type":"Point"}
}