{
  "type": "Feature",
  "properties": {
    "addr:full":"30071 Ivy Glenn Dr Laguna Niguel CA 92677",
    "addr:housenumber":"30071",
    "addr:postcode":"92677",
    "addr:street":"Ivy Glenn Dr",
    "iso:country":"US",
    "sg:address":"30071 Ivy Glenn Dr",
    "sg:city":"Laguna Niguel",
    "sg:classifiers":[
        {
            "category":"Organizations",
            "subcategory":"Religious Organization",
            "type":"Services"
        }
    ],
    "sg:phone":"+1 949 249 1218",
    "sg:postcode":"92677",
    "sg:province":"CA",
    "sg:tags":[
        "church"
    ],
    "sg:website":"www.lnpc.org",
    "wof:name":"Laguna Niguel Presbyterian Chr",
    "wof:placetype":"venue"
},
  "geometry": {"coordinates":[-117.715328,33.527073],"type":"Point"}
}