{
  "type": "Feature",
  "properties": {
    "iso:country":"US",
    "sg:address":"38486 Cedar Blvd",
    "sg:city":"Newark",
    "sg:classifiers":[
        {
            "category":"Building & Trades",
            "subcategory":"Construction",
            "type":"Services"
        }
    ],
    "sg:phone":"+1 510 742 6865",
    "sg:postcode":"94560",
    "sg:province":"CA",
    "sg:tags":[
        "maker",
        "cabinet"
    ],
    "wof:name":"Cabinet Shop",
    "wof:placetype":"venue"
},
  "geometry": {"coordinates":[-122.011314,37.53336],"type":"Point"}
}