{
  "type": "Feature",
  "properties": {
    "iso:country":"US",
    "sg:address":"7119 Gerald Ave",
    "sg:city":"Van Nuys",
    "sg:classifiers":[
        {
            "category":"Wholesale",
            "subcategory":"Hardware",
            "type":"Manufacturing & Wholesale Goods"
        }
    ],
    "sg:phone":"+1 818 782 5454",
    "sg:postcode":"91406",
    "sg:province":"CA",
    "sg:tags":[
        "lock",
        "locksmith"
    ],
    "wof:name":"Coin Security Systems Inc",
    "wof:placetype":"venue"
},
  "geometry": {"coordinates":[-118.493557,34.199785],"type":"Point"}
}