{
  "type": "Feature",
  "properties": {
    "iso:country":"US",
    "sg:address":"1217 Wall St",
    "sg:city":"Los Angeles",
    "sg:classifiers":[
        {
            "category":"Restaurant",
            "type":"Food & Drink"
        }
    ],
    "sg:phone":"+1 213 746 5185",
    "sg:postcode":"90015",
    "sg:province":"CA",
    "sg:tags":[
        "sushi",
        "bar",
        "japanese"
    ],
    "wof:name":"Yakimaki",
    "wof:placetype":"venue"
},
  "geometry": {"coordinates":[-118.2555,34.034853],"type":"Point"}
}