{
  "type": "Feature",
  "properties": {
    "addr:full":"400 N Altadena Dr Pasadena CA 91107",
    "addr:housenumber":"400",
    "addr:postcode":"91107",
    "addr:street":"N Altadena Dr",
    "iso:country":"US",
    "sg:address":"400 N Altadena Dr",
    "sg:city":"Pasadena",
    "sg:classifiers":[
        {
            "category":"Wholesale",
            "subcategory":"Home Furnishings",
            "type":"Manufacturing & Wholesale Goods"
        }
    ],
    "sg:phone":"+1 626 795 6011",
    "sg:postcode":"91107",
    "sg:province":"CA",
    "wof:name":"Alden Unlimited Drapery & Vert",
    "wof:placetype":"venue"
},
  "geometry": {"coordinates":[-118.098455,34.153273],"type":"Point"}
}