{
  "type": "Feature",
  "properties": {
    "addr:full":"510 E Broadway Long Beach CA 90802",
    "addr:housenumber":"510",
    "addr:postcode":"90802",
    "addr:street":"E Broadway",
    "iso:country":"US",
    "sg:address":"510 E Broadway",
    "sg:city":"Long Beach",
    "sg:phone":"+1 562 612 1635",
    "sg:postcode":"90802",
    "sg:province":"CA",
    "sg:website":"www.chillcafelb.com",
    "wof:name":"Chill",
    "wof:placetype":"venue"
},
  "geometry": {"coordinates":[-118.186069,33.769278],"type":"Point"}
}