{
  "type": "Feature",
  "properties": {
    "addr:full":"760 Market St San Francisco CA 94102",
    "addr:housenumber":"760",
    "addr:postcode":"94102",
    "addr:street":"Market St",
    "iso:country":"US",
    "sg:address":"760 Market St",
    "sg:city":"San Francisco",
    "sg:classifiers":[
        {
            "category":"Manufacturing",
            "subcategory":"Jewelry",
            "type":"Manufacturing & Wholesale Goods"
        }
    ],
    "sg:phone":"+1 415 981 6158",
    "sg:postcode":"94102",
    "sg:province":"CA",
    "sg:tags":[
        "lapidary",
        "gem",
        "cutter"
    ],
    "sg:website":"www.concavefaceting.com",
    "wof:name":"Good Neighbor Gem & Lapidary",
    "wof:placetype":"venue"
},
  "geometry": {"coordinates":[-122.405405,37.786324],"type":"Point"}
}