{
  "type": "Feature",
  "properties": {
    "addr:full":"6433 Fallbrook Ave West Hills CA 91307",
    "addr:housenumber":"6433",
    "addr:postcode":"91307",
    "addr:street":"Fallbrook Ave",
    "iso:country":"US",
    "sg:address":"6433 Fallbrook Ave",
    "sg:city":"West Hills",
    "sg:classifiers":[
        {
            "category":"Cinema",
            "subcategory":"Movie Rental",
            "type":"Entertainment"
        }
    ],
    "sg:postcode":"91307",
    "sg:province":"CA",
    "sg:tags":[
        "game",
        "video"
    ],
    "sg:website":"www.redbox.com",
    "wof:name":"Redbox",
    "wof:placetype":"venue"
},
  "geometry": {"coordinates":[-118.625238,34.187627],"type":"Point"}
}