{
  "type": "Feature",
  "properties": {
    "addr:full":"7051 Motz St Paramount CA 90723",
    "addr:postcode":"7051;90723",
    "addr:street":"Motz St",
    "iso:country":"US",
    "sg:address":"7051 Motz St",
    "sg:city":"Paramount",
    "sg:classifiers":[
        {
            "category":"Shopping",
            "subcategory":"Bicycles & Sporting Goods",
            "type":"Retail Goods"
        }
    ],
    "sg:phone":"+1 562 602 1119",
    "sg:postcode":"90723",
    "sg:province":"CA",
    "wof:name":"Vizari Sport USA",
    "wof:placetype":"venue"
},
  "geometry": {"coordinates":[-118.175932,33.887428],"type":"Point"}
}