{
  "type": "Feature",
  "properties": {
    "iso:country":"US",
    "sg:address":"2136 Cotner Ave",
    "sg:city":"Los Angeles",
    "sg:classifiers":[
        {
            "category":"Personal",
            "type":"Services"
        }
    ],
    "sg:phone":"+1 310 474 1450",
    "sg:postcode":"90025",
    "sg:province":"CA",
    "sg:tags":[
        "local"
    ],
    "sg:website":"www.wallywine.com/t-winelockers....",
    "wof:name":"Cotner Wine Storage",
    "wof:placetype":"venue"
},
  "geometry": {"coordinates":[-118.439455,34.040024],"type":"Point"}
}