{
  "type": "Feature",
  "properties": {
    "addr:full":"2232 5th Avenue San Diego CA 92101",
    "addr:housenumber":"2232",
    "addr:postcode":"92101",
    "addr:street":"5Th Avenue",
    "iso:country":"US",
    "sg:address":"2232 5th Avenue",
    "sg:city":"San Diego",
    "sg:classifiers":[
        {
            "category":"Personal",
            "subcategory":"Beauty Salon",
            "type":"Services"
        }
    ],
    "sg:phone":"+1 619 595 0655",
    "sg:postcode":"92101",
    "sg:province":"CA",
    "sg:tags":[
        "hair"
    ],
    "wof:name":"Crane Donn Hair Stylist",
    "wof:placetype":"venue"
},
  "geometry": {"coordinates":[-117.160133,32.728782],"type":"Point"}
}