{
  "type": "Feature",
  "properties": {
    "iso:country":"US",
    "sg:address":"803 Rincon Ave",
    "sg:city":"Livermore",
    "sg:classifiers":[
        {
            "category":"Travel",
            "subcategory":"Travel Agent",
            "type":"Entertainment"
        }
    ],
    "sg:phone":"+1 925 606 7822",
    "sg:postcode":"94550",
    "sg:province":"CA",
    "sg:tags":[
        "agency",
        "bureau"
    ],
    "wof:name":"Jet Travel Livermore",
    "wof:placetype":"venue"
},
  "geometry": {"coordinates":[-121.783454,37.688271],"type":"Point"}
}