{
  "type": "Feature",
  "properties": {
    "addr:full":"1729 Cll Boca del Canon Santa Barbara CA 93101",
    "addr:housenumber":"1729",
    "addr:postcode":"93101",
    "addr:street":"Cll Boca Del Canon",
    "iso:country":"US",
    "sg:address":"1729 Cll Boca del Canon",
    "sg:city":"Santa Barbara",
    "sg:classifiers":[
        {
            "category":"Real Estate",
            "subcategory":"Developer",
            "type":"Services"
        }
    ],
    "sg:phone":"+1 805 569 1514",
    "sg:postcode":"93101",
    "sg:province":"CA",
    "wof:name":"Thomas Felkay",
    "wof:placetype":"venue"
},
  "geometry": {"coordinates":[-119.725767,34.415563],"type":"Point"}
}