{
  "type": "Feature",
  "properties": {
    "iso:country":"US",
    "sg:address":"3303 Kimber Dr Ste B",
    "sg:city":"Newbury Park",
    "sg:classifiers":[
        {
            "category":"Shopping",
            "subcategory":"Florist",
            "type":"Retail Goods"
        }
    ],
    "sg:phone":"+1 805 498 9602",
    "sg:postcode":"91320",
    "sg:province":"CA",
    "wof:name":"Newbury Park Florist",
    "wof:placetype":"venue"
},
  "geometry": {"coordinates":[-118.947998,34.174999],"type":"Point"}
}