{
  "type": "Feature",
  "properties": {
    "addr:full":"723 J St Woodland CA 95648",
    "addr:housenumber":"723",
    "addr:postcode":"95648",
    "addr:street":"J St",
    "iso:country":"US",
    "sg:address":"723 J St",
    "sg:city":"Woodland",
    "sg:classifiers":[
        {
            "category":"Insurance",
            "subcategory":"Hazard Insurance",
            "type":"Services"
        }
    ],
    "sg:phone":"+1 530 668 0666",
    "sg:postcode":"95648",
    "sg:province":"CA",
    "sg:tags":[
        "bond"
    ],
    "wof:name":"Atlantis Bail Bonds",
    "wof:placetype":"venue"
},
  "geometry": {"coordinates":[-121.29654600000001,38.894775],"type":"Point"}
}