{
  "type": "Feature",
  "properties": {
    "iso:country":"US",
    "sg:address":"1578 Colorado Blvd",
    "sg:city":"Los Angeles",
    "sg:classifiers":[
        {
            "category":"Education",
            "subcategory":"Vocational School",
            "type":"Public Place"
        }
    ],
    "sg:phone":"+1 323 259 0438",
    "sg:postcode":"90041",
    "sg:province":"CA",
    "sg:tags":[
        "nurse"
    ],
    "wof:name":"Regal Health Care School",
    "wof:placetype":"venue"
},
  "geometry": {"coordinates":[-118.200333,34.13952],"type":"Point"}
}