{
  "type": "Feature",
  "properties": {
    "iso:country":"US",
    "sg:address":"23025 Mobile St",
    "sg:city":"West Hills",
    "sg:classifiers":[
        {
            "category":"Manufacturing",
            "subcategory":"Retail Goods",
            "type":"Manufacturing & Wholesale Goods"
        }
    ],
    "sg:phone":"+1 818 879 9568",
    "sg:postcode":"91307",
    "sg:province":"CA",
    "sg:tags":[
        "manufacturer"
    ],
    "wof:name":"Petrell Industries",
    "wof:placetype":"venue"
},
  "geometry": {"coordinates":[-118.629968,34.188244],"type":"Point"}
}