{
  "type": "Feature",
  "properties": {
    "addr:full":"17870 Rowland St Rowland Heights CA 91748",
    "addr:housenumber":"17870",
    "addr:postcode":"91748",
    "addr:street":"Rowland St",
    "iso:country":"US",
    "sg:address":"17870 Rowland St",
    "sg:city":"Rowland Heights",
    "sg:classifiers":[
        {
            "category":"Professional",
            "type":"Services"
        }
    ],
    "sg:phone":"+1 626 428 8738",
    "sg:postcode":"91748",
    "sg:province":"CA",
    "wof:name":"Wangdi Industry USA Dev Co",
    "wof:placetype":"venue"
},
  "geometry": {"coordinates":[-117.915215,34.001292],"type":"Point"}
}