{
  "type": "Feature",
  "properties": {
    "iso:country":"US",
    "sg:address":"9353 E 8th St",
    "sg:city":"Rancho Cucamonga",
    "sg:classifiers":[
        {
            "category":"Manufacturing",
            "subcategory":"Signs",
            "type":"Manufacturing & Wholesale Goods"
        }
    ],
    "sg:phone":"+1 909 484 1805",
    "sg:postcode":"91730",
    "sg:province":"CA",
    "wof:name":"Discount Super Signs",
    "wof:placetype":"venue"
},
  "geometry": {"coordinates":[-117.59458600000001,34.091829],"type":"Point"}
}