{
  "type": "Feature",
  "properties": {
    "addr:full":"634 S San Pedro St Los Angeles CA 90014",
    "addr:housenumber":"634",
    "addr:postcode":"90014",
    "addr:street":"S San Pedro St",
    "iso:country":"US",
    "sg:address":"634 S San Pedro St",
    "sg:city":"Los Angeles",
    "sg:classifiers":[
        {
            "category":"Shopping",
            "subcategory":"Hobbies, Toys, & Games",
            "type":"Retail Goods"
        }
    ],
    "sg:phone":"+1 213 627 0566",
    "sg:postcode":"90014",
    "sg:province":"CA",
    "sg:tags":[
        "toy",
        "store"
    ],
    "wof:name":"A B C Toys",
    "wof:placetype":"venue"
},
  "geometry": {"coordinates":[-118.246002,34.042099],"type":"Point"}
}