{
  "type": "Feature",
  "properties": {
    "addr:full":"2510 N Grand Ave Ste 211 Santa Ana CA 92705",
    "addr:housenumber":"2510",
    "addr:postcode":"92705",
    "addr:street":"N Grand Ave Ste 211",
    "iso:country":"US",
    "sg:address":"2510 N Grand Ave Ste 211",
    "sg:city":"Santa Ana",
    "sg:classifiers":[
        {
            "category":"Banks & Credit Unions",
            "subcategory":"Financial Services",
            "type":"Services"
        }
    ],
    "sg:phone":"+1 714 628 0811",
    "sg:postcode":"92705",
    "sg:province":"CA",
    "sg:tags":[
        "broker",
        "mortgage"
    ],
    "wof:name":"Platinum Acceptance Corp",
    "wof:placetype":"venue"
},
  "geometry": {"coordinates":[-117.852251,33.770651],"type":"Point"}
}