{
  "type": "Feature",
  "properties": {
    "addr:full":"1781 Placentia Ave Costa Mesa CA 92627",
    "addr:housenumber":"1781",
    "addr:postcode":"92627",
    "addr:street":"Placentia Ave",
    "iso:country":"US",
    "sg:address":"1781 Placentia Ave",
    "sg:city":"Costa Mesa",
    "sg:classifiers":[
        {
            "category":"Wholesale",
            "subcategory":"Hardware",
            "type":"Manufacturing & Wholesale Goods"
        }
    ],
    "sg:phone":"+1 949 650 0646",
    "sg:postcode":"92627",
    "sg:province":"CA",
    "sg:tags":[
        "plumbing",
        "fixture",
        "supply"
    ],
    "wof:name":"Ferguson Enterprises Inc",
    "wof:placetype":"venue"
},
  "geometry": {"coordinates":[-117.93200299999999,33.638992],"type":"Point"}
}