{
  "type": "Feature",
  "properties": {
    "addr:full":"871 Carina Ln Foster City CA 94404",
    "addr:housenumber":"871",
    "addr:postcode":"94404",
    "addr:street":"Carina Ln",
    "iso:country":"US",
    "sg:address":"871 Carina Ln",
    "sg:city":"Foster City",
    "sg:classifiers":[
        {
            "category":"Professional",
            "subcategory":"Business Services",
            "type":"Services"
        }
    ],
    "sg:phone":"+1 650 522 8541",
    "sg:postcode":"94404",
    "sg:province":"CA",
    "sg:tags":[
        "information",
        "referral"
    ],
    "wof:name":"Facility Information Syst Inc",
    "wof:placetype":"venue"
},
  "geometry": {"coordinates":[-122.27418900000001,37.548596],"type":"Point"}
}