{
  "type": "Feature",
  "properties": {
    "addr:full":"1631 Siskiyou Dr Salinas CA 93906",
    "addr:housenumber":"1631",
    "addr:postcode":"93906",
    "addr:street":"Siskiyou Dr",
    "iso:country":"US",
    "sg:address":"1631 Siskiyou Dr",
    "sg:city":"Salinas",
    "sg:classifiers":[
        {
            "category":"Personal",
            "type":"Services"
        }
    ],
    "sg:phone":"+1 831 443 5143",
    "sg:postcode":"93906",
    "sg:province":"CA",
    "sg:tags":[
        "wedding",
        "chapel"
    ],
    "wof:name":"Serra Wedding & Svc",
    "wof:placetype":"venue"
},
  "geometry": {"coordinates":[-121.63500999999999,36.709801],"type":"Point"}
}