{
  "type": "Feature",
  "properties": {
    "iso:country":"US",
    "sg:address":"1211 K St",
    "sg:city":"Modesto",
    "sg:classifiers":[
        {
            "category":"Professional",
            "subcategory":"Lawyer & Legal Services",
            "type":"Services"
        }
    ],
    "sg:phone":"+1 209 529 5186",
    "sg:postcode":"95354",
    "sg:province":"CA",
    "sg:tags":[
        "attorney"
    ],
    "wof:name":"James J Milam",
    "wof:placetype":"venue"
},
  "geometry": {"coordinates":[-120.998724,37.643611],"type":"Point"}
}