{
  "type": "Feature",
  "properties": {
    "addr:full":"500 S Palm Canyon Dr Palm Springs CA 92264",
    "addr:housenumber":"500",
    "addr:postcode":"92264",
    "addr:street":"S Palm Canyon Dr",
    "iso:country":"US",
    "sg:address":"500 S Palm Canyon Dr",
    "sg:city":"Palm Springs",
    "sg:classifiers":[
        {
            "category":"Health Services",
            "subcategory":"Clinic",
            "type":"Services"
        }
    ],
    "sg:phone":"+1 760 325 4988",
    "sg:postcode":"92264",
    "sg:province":"CA",
    "sg:tags":[
        "hypnotherapy"
    ],
    "wof:name":"Power Hypnosis",
    "wof:placetype":"venue"
},
  "geometry": {"coordinates":[-116.54568,33.814102],"type":"Point"}
}