{
  "type": "Feature",
  "properties": {
    "addr:full":"319 Diablo Rd Danville CA 94526",
    "addr:housenumber":"319",
    "addr:postcode":"94526",
    "addr:street":"Diablo Rd",
    "iso:country":"US",
    "sg:address":"319 Diablo Rd",
    "sg:city":"Danville",
    "sg:classifiers":[
        {
            "category":"Professional",
            "subcategory":"Accounting & Tax Preparation",
            "type":"Services"
        }
    ],
    "sg:phone":"+1 925 743 9258",
    "sg:postcode":"94526",
    "sg:province":"CA",
    "sg:tags":[
        "accountant"
    ],
    "wof:name":"Robert Jurgenson CPA",
    "wof:placetype":"venue"
},
  "geometry": {"coordinates":[-121.994708,37.822863],"type":"Point"}
}