{
  "type": "Feature",
  "properties": {
    "addr:full":"705 W Cornell Ave Fresno CA 93705",
    "addr:housenumber":"705",
    "addr:postcode":"93705",
    "addr:street":"W Cornell Ave",
    "iso:country":"US",
    "sg:address":"705 W Cornell Ave",
    "sg:city":"Fresno",
    "sg:classifiers":[
        {
            "category":"Professional",
            "subcategory":"Research",
            "type":"Services"
        }
    ],
    "sg:phone":"+1 559 229 1957",
    "sg:postcode":"93705",
    "sg:province":"CA",
    "sg:tags":[
        "environmental",
        "ecological"
    ],
    "wof:name":"Environtech Consultants",
    "wof:placetype":"venue"
},
  "geometry": {"coordinates":[-119.817894,36.77742],"type":"Point"}
}