{
  "type": "Feature",
  "properties": {
    "addr:full":"284 Kearney Exd Watsonville CA 95076",
    "addr:housenumber":"284",
    "addr:postcode":"95076",
    "addr:street":"Kearney Exd",
    "iso:country":"US",
    "sg:address":"284 Kearney Exd",
    "sg:city":"Watsonville",
    "sg:classifiers":[
        {
            "category":"Manufacturing",
            "subcategory":"Food",
            "type":"Manufacturing & Wholesale Goods"
        }
    ],
    "sg:phone":"+1 831 722 4597",
    "sg:postcode":"95076",
    "sg:province":"CA",
    "sg:tags":[
        "packer",
        "fish",
        "mfg"
    ],
    "wof:name":"Aliotti Wholesale Fish Packing",
    "wof:placetype":"venue"
},
  "geometry": {"coordinates":[-121.76469299999999,36.908748],"type":"Point"}
}