{
  "type": "Feature",
  "properties": {
    "iso:country":"US",
    "sg:address":"2867 W Olympic Blvd",
    "sg:city":"Los Angeles",
    "sg:classifiers":[
        {
            "category":"Shopping",
            "subcategory":"Bicycles & Sporting Goods",
            "type":"Retail Goods"
        }
    ],
    "sg:phone":"+1 213 389 7007",
    "sg:postcode":"90006",
    "sg:province":"CA",
    "sg:website":"www.theolympicgolf.com",
    "wof:name":"Olympic Golf",
    "wof:placetype":"venue"
},
  "geometry": {"coordinates":[-118.296997,34.052502],"type":"Point"}
}