{
  "type": "Feature",
  "properties": {
    "addr:full":"6693 Sierra Ln Dublin CA 94568",
    "addr:housenumber":"6693",
    "addr:postcode":"94568",
    "addr:street":"Sierra Ln",
    "iso:country":"US",
    "sg:address":"6693 Sierra Ln",
    "sg:city":"Dublin",
    "sg:classifiers":[
        {
            "category":"Utilities",
            "subcategory":"Mobile Phone",
            "type":"Services"
        }
    ],
    "sg:phone":"+1 925 479 1700",
    "sg:postcode":"94568",
    "sg:province":"CA",
    "sg:tags":[
        "telephone",
        "cellular"
    ],
    "wof:name":"General Dynamics Wts",
    "wof:placetype":"venue"
},
  "geometry": {"coordinates":[-121.91195500000001,37.706033],"type":"Point"}
}