{
  "type": "Feature",
  "properties": {
    "addr:full":"6001 Oak Canyon Irvine CA 92618",
    "addr:housenumber":"6001",
    "addr:postcode":"92618",
    "addr:street":"Oak Canyon",
    "iso:country":"US",
    "sg:address":"6001 Oak Canyon",
    "sg:city":"Irvine",
    "sg:classifiers":[
        {
            "category":"Manufacturing",
            "subcategory":"Tools & Machinery",
            "type":"Manufacturing & Wholesale Goods"
        }
    ],
    "sg:phone":"+1 949 451 1450",
    "sg:postcode":"92618",
    "sg:province":"CA",
    "sg:tags":[
        "mfg",
        "telescope",
        "accessory"
    ],
    "wof:name":"Meade Instruments Corp",
    "wof:placetype":"venue"
},
  "geometry": {"coordinates":[-117.76901700000001,33.678073],"type":"Point"}
}