{
  "type": "Feature",
  "properties": {
    "addr:full":"1888 Broadway St Vallejo CA 94589",
    "addr:housenumber":"1888",
    "addr:postcode":"94589",
    "addr:street":"Broadway St",
    "iso:country":"US",
    "sg:address":"1888 Broadway St",
    "sg:city":"Vallejo",
    "sg:classifiers":[
        {
            "category":"Freight",
            "type":"Transportation"
        },
        {
            "category":"Home & Garden",
            "subcategory":"Garden Supply",
            "type":"Retail Goods"
        }
    ],
    "sg:phone":"+1 707 649 2243",
    "sg:postcode":"94589",
    "sg:province":"CA",
    "sg:tags":[
        "operator",
        "landscaping",
        "equipment",
        "trucking"
    ],
    "wof:name":"Crown Hill Materials Trucking",
    "wof:placetype":"venue"
},
  "geometry": {"coordinates":[-122.25219300000001,38.132273],"type":"Point"}
}