{
  "type": "Feature",
  "properties": {
    "iso:country":"US",
    "sg:address":"342 N Grant Street",
    "sg:city":"San Mateo",
    "sg:classifiers":[
        {
            "category":"Building & Trades",
            "subcategory":"Landscaping Services",
            "type":"Services"
        }
    ],
    "sg:phone":"+1 650 343 7806",
    "sg:postcode":"94401",
    "sg:province":"CA",
    "sg:tags":[
        "gardener"
    ],
    "wof:name":"Tino Landscaping",
    "wof:placetype":"venue"
},
  "geometry": {"coordinates":[-122.325227,37.576704],"type":"Point"}
}