{
  "type": "Feature",
  "properties": {
    "iso:country":"US",
    "sg:address":"3620 Oakes Dr",
    "sg:city":"Hayward",
    "sg:classifiers":[
        {
            "category":"Real Estate",
            "subcategory":"Developer",
            "type":"Services"
        }
    ],
    "sg:phone":"+1 510 247 1855",
    "sg:postcode":"94542",
    "sg:province":"CA",
    "wof:name":"Esau Development",
    "wof:placetype":"venue"
},
  "geometry": {"coordinates":[-122.037846,37.662933],"type":"Point"}
}