{
  "type": "Feature",
  "properties": {
    "addr:full":"835 Palm Ave National City CA 91950",
    "addr:housenumber":"835",
    "addr:postcode":"91950",
    "addr:street":"Palm Ave",
    "iso:country":"US",
    "sg:address":"835 Palm Ave",
    "sg:city":"National City",
    "sg:classifiers":[
        {
            "category":"Restaurant",
            "type":"Food & Drink"
        }
    ],
    "sg:phone":"+1 619 474 1682",
    "sg:postcode":"91950",
    "sg:province":"CA",
    "wof:name":"Los Nicos Taco Shop",
    "wof:placetype":"venue"
},
  "geometry": {"coordinates":[-117.090349,32.680178],"type":"Point"}
}