{
  "type": "Feature",
  "properties": {
    "iso:country":"US",
    "sg:address":"13026 Saticoy St Ste 16",
    "sg:city":"North Hollywood",
    "sg:classifiers":[
        {
            "category":"Shopping",
            "subcategory":"Computers & Home Electronics",
            "type":"Retail Goods"
        }
    ],
    "sg:phone":"+1 818 764 0621",
    "sg:postcode":"91605",
    "sg:province":"CA",
    "wof:name":"Atv Electronics",
    "wof:placetype":"venue"
},
  "geometry": {"coordinates":[-118.40100099999999,34.2066],"type":"Point"}
}