{
  "type": "Feature",
  "properties": {
    "iso:country":"US",
    "sg:address":"6926 Valjean Ave",
    "sg:city":"Van Nuys",
    "sg:classifiers":[
        {
            "category":"Manufacturing",
            "subcategory":"Textiles",
            "type":"Manufacturing & Wholesale Goods"
        }
    ],
    "sg:phone":"+1 818 563 1033",
    "sg:postcode":"91406",
    "sg:province":"CA",
    "sg:tags":[
        "curtain"
    ],
    "wof:name":"Danon Drapery Inc",
    "wof:placetype":"venue"
},
  "geometry": {"coordinates":[-118.48576199999999,34.195222],"type":"Point"}
}