{
  "type": "Feature",
  "properties": {
    "addr:full":"PO Box 620376 Orangevale CA 95662",
    "addr:housenumber":"po",
    "addr:postcode":"95662",
    "addr:street":"Box 620376",
    "iso:country":"US",
    "sg:address":"PO Box 620376",
    "sg:city":"Orangevale",
    "sg:classifiers":[
        {
            "category":"Professional",
            "subcategory":"Lawyer & Legal Services",
            "type":"Services"
        }
    ],
    "sg:phone":"+1 916 987 8929",
    "sg:postcode":"95662",
    "sg:province":"CA",
    "wof:name":"Stout Susan L Attorney At Law",
    "wof:placetype":"venue"
},
  "geometry": {"coordinates":[-121.227997,38.682701],"type":"Point"}
}