{
  "type": "Feature",
  "properties": {
    "addr:full":"2560 Lillie Ave Summerland CA 93067",
    "addr:housenumber":"2560",
    "addr:postcode":"93067",
    "addr:street":"Lillie Ave",
    "iso:country":"US",
    "sg:address":"2560 Lillie Ave",
    "sg:city":"Summerland",
    "sg:classifiers":[
        {
            "category":"Food & Beverages",
            "subcategory":"Groceries & Convenience Stores",
            "type":"Retail Goods"
        }
    ],
    "sg:phone":"+1 805 695 0655",
    "sg:postcode":"93067",
    "sg:province":"CA",
    "wof:name":"French Market The",
    "wof:placetype":"venue"
},
  "geometry": {"coordinates":[-119.592252,34.419127],"type":"Point"}
}