{
  "type": "Feature",
  "properties": {
    "addr:full":"9943 Tweedy Ln Apt B Downey CA 90240",
    "addr:housenumber":"9943",
    "addr:postcode":"90240",
    "addr:street":"Tweedy Ln Apt B",
    "iso:country":"US",
    "sg:address":"9943 Tweedy Ln Apt B",
    "sg:city":"Downey",
    "sg:classifiers":[
        {
            "category":"Building & Trades",
            "subcategory":"Construction",
            "type":"Services"
        }
    ],
    "sg:phone":"+1 323 497 9956",
    "sg:postcode":"90240",
    "sg:province":"CA",
    "sg:tags":[
        "wallcoverings-installation",
        "wallpaper",
        "painting",
        "contractor"
    ],
    "wof:name":"Rps Painting",
    "wof:placetype":"venue"
},
  "geometry": {"coordinates":[-118.130458,33.956037],"type":"Point"}
}