{
  "type": "Feature",
  "properties": {
    "addr:full":"10136 Rush St South El Monte CA 91733",
    "addr:housenumber":"10136",
    "addr:postcode":"91733",
    "addr:street":"Rush St",
    "iso:country":"US",
    "sg:address":"10136 Rush St",
    "sg:city":"South El Monte",
    "sg:classifiers":[
        {
            "category":"Manufacturing",
            "subcategory":"Apparel",
            "type":"Manufacturing & Wholesale Goods"
        }
    ],
    "sg:phone":"+1 626 575 8618",
    "sg:postcode":"91733",
    "sg:province":"CA",
    "wof:name":"Lucky Team Fashions",
    "wof:placetype":"venue"
},
  "geometry": {"coordinates":[-118.04867,34.051761],"type":"Point"}
}