{
  "type": "Feature",
  "properties": {
    "addr:full":"1200 Chamberlain Ave Bakersfield CA 93305",
    "addr:housenumber":"1200",
    "addr:postcode":"93305",
    "addr:street":"Chamberlain Ave",
    "iso:country":"US",
    "sg:address":"1200 Chamberlain Ave",
    "sg:city":"Bakersfield",
    "sg:classifiers":[
        {
            "category":"Autos & Motor Vehicles",
            "subcategory":"Auto Supplies",
            "type":"Retail Goods"
        }
    ],
    "sg:phone":"+1 661 325 2094",
    "sg:postcode":"93305",
    "sg:province":"CA",
    "sg:tags":[
        "tire"
    ],
    "wof:name":"Nayarit Tire Shop",
    "wof:placetype":"venue"
},
  "geometry": {"coordinates":[-118.970388,35.36903],"type":"Point"}
}