{
  "type": "Feature",
  "properties": {
    "iso:country":"US",
    "sg:address":"1501 16th St",
    "sg:city":"Sacramento",
    "sg:classifiers":[
        {
            "category":"Restaurant",
            "type":"Food & Drink"
        }
    ],
    "sg:menulink":"http://www.allmenus.com/ca/sacramento/163851-togos-eatery/menu/",
    "sg:phone":"+1 916 442 7670",
    "sg:postcode":"95814",
    "sg:province":"CA",
    "sg:tags":[
        "wrap",
        "american",
        "sandwich"
    ],
    "wof:name":"Togo's Eatery",
    "wof:placetype":"venue"
},
  "geometry": {"coordinates":[-121.487607,38.57258],"type":"Point"}
}