{
  "type": "Feature",
  "properties": {
    "addr:full":"35758 Date Palm Dr Cathedral City CA 92234",
    "addr:housenumber":"35758",
    "addr:postcode":"92234",
    "addr:street":"Date Palm Dr",
    "iso:country":"US",
    "sg:address":"35758 Date Palm Dr",
    "sg:city":"Cathedral City",
    "sg:classifiers":[
        {
            "category":"Shopping",
            "subcategory":"Pharmacy",
            "type":"Retail Goods"
        }
    ],
    "sg:phone":"+1 760 328 2115",
    "sg:postcode":"92234",
    "sg:province":"CA",
    "wof:name":"Sun Air Pharmacy",
    "wof:placetype":"venue"
},
  "geometry": {"coordinates":[-116.45803100000001,33.790851],"type":"Point"}
}