{
  "type": "Feature",
  "properties": {
    "iso:country":"US",
    "sg:address":"3713 W 3rd St",
    "sg:city":"Los Angeles",
    "sg:classifiers":[
        {
            "category":"Restaurant",
            "type":"Food & Drink"
        }
    ],
    "sg:phone":"+1 213 427 0668",
    "sg:postcode":"90020",
    "sg:province":"CA",
    "wof:name":"El Limeno Restaurant",
    "wof:placetype":"venue"
},
  "geometry": {"coordinates":[-118.29781199999999,34.069103],"type":"Point"}
}