{
  "type": "Feature",
  "properties": {
    "addr:full":"3359 Fletcher Dr Los Angeles CA 90065",
    "addr:housenumber":"3359",
    "addr:postcode":"90065",
    "addr:street":"Fletcher Dr",
    "iso:country":"US",
    "sg:address":"3359 Fletcher Dr",
    "sg:city":"Los Angeles",
    "sg:classifiers":[
        {
            "category":"Professional",
            "type":"Services"
        }
    ],
    "sg:phone":"+1 323 256 8378",
    "sg:postcode":"90065",
    "sg:province":"CA",
    "sg:tags":[
        "control",
        "system",
        "key"
    ],
    "wof:name":"Key Kontrol",
    "wof:placetype":"venue"
},
  "geometry": {"coordinates":[-118.240865,34.118342],"type":"Point"}
}