{
  "type": "Feature",
  "properties": {
    "addr:full":"2080 Vallejo St Apt 3 San Francisco CA 94123",
    "addr:housenumber":"2080;3",
    "addr:postcode":"94123",
    "addr:street":"Vallejo St Apt",
    "iso:country":"US",
    "sg:address":"2080 Vallejo St Apt 3",
    "sg:city":"San Francisco",
    "sg:classifiers":[
        {
            "category":"Building & Trades",
            "subcategory":"Construction",
            "type":"Services"
        }
    ],
    "sg:phone":"+1 415 626 7250",
    "sg:postcode":"94123",
    "sg:province":"CA",
    "sg:tags":[
        "interior",
        "design"
    ],
    "wof:name":"Marsho James Design",
    "wof:placetype":"venue"
},
  "geometry": {"coordinates":[-122.43153599999999,37.795966],"type":"Point"}
}