{
  "type": "Feature",
  "properties": {
    "iso:country":"US",
    "sg:address":"16489 Orange Way",
    "sg:city":"Fontana",
    "sg:classifiers":[
        {
            "category":"Social Services",
            "subcategory":"Adult Care",
            "type":"Services"
        }
    ],
    "sg:phone":"+1 909 350 4663",
    "sg:postcode":"92335",
    "sg:province":"CA",
    "sg:tags":[
        "crisis",
        "intervention"
    ],
    "wof:name":"Village Heritage Maint Hotline",
    "wof:placetype":"venue"
},
  "geometry": {"coordinates":[-117.44467899999999,34.095827],"type":"Point"}
}