{
  "type": "Feature",
  "properties": {
    "iso:country":"US",
    "sg:address":"1640 S Sepulveda Blvd Ste 210",
    "sg:city":"Los Angeles",
    "sg:classifiers":[
        {
            "category":"Place Of Worship",
            "subcategory":"Synagogue",
            "type":"Public Place"
        },
        {
            "category":"Organizations",
            "subcategory":"Non-profit Organization",
            "type":"Services"
        }
    ],
    "sg:phone":"+1 310 479 2468",
    "sg:postcode":"90025",
    "sg:province":"CA",
    "sg:tags":[
        "service/non-profit",
        "community"
    ],
    "sg:website":"www.laguardians.com/",
    "wof:name":"Guardians of the Jewish Home",
    "wof:placetype":"venue"
},
  "geometry": {"coordinates":[-118.445,34.048401],"type":"Point"}
}