{
  "type": "Feature",
  "properties": {
    "addr:full":"5035 Pacific St Rocklin CA 95677",
    "addr:housenumber":"5035",
    "addr:postcode":"95677",
    "addr:street":"Pacific St",
    "iso:country":"US",
    "sg:address":"5035 Pacific St",
    "sg:city":"Rocklin",
    "sg:classifiers":[
        {
            "category":"Education",
            "subcategory":"Dance Studio",
            "type":"Public Place"
        }
    ],
    "sg:phone":"+1 916 415 9502",
    "sg:postcode":"95677",
    "sg:province":"CA",
    "sg:tags":[
        "instruction",
        "dancing"
    ],
    "wof:name":"Dance Works",
    "wof:placetype":"venue"
},
  "geometry": {"coordinates":[-121.234666,38.792332],"type":"Point"}
}