{
  "type": "Feature",
  "properties": {
    "addr:full":"3655 West St Emeryville CA 94608",
    "addr:housenumber":"3655",
    "addr:postcode":"94608",
    "addr:street":"West St",
    "iso:country":"US",
    "sg:address":"3655 West St",
    "sg:city":"Emeryville",
    "sg:classifiers":[
        {
            "category":"Professional",
            "type":"Services"
        }
    ],
    "sg:phone":"+1 510 985 3006",
    "sg:postcode":"94608",
    "sg:province":"CA",
    "wof:name":"Windle D McNeal",
    "wof:placetype":"venue"
},
  "geometry": {"coordinates":[-122.27216199999999,37.826153],"type":"Point"}
}