{
  "type": "Feature",
  "properties": {
    "addr:full":"1510 Mission Street South Pasadena CA 91030",
    "addr:housenumber":"1510",
    "addr:postcode":"91030",
    "addr:street":"Mission Street",
    "iso:country":"US",
    "sg:address":"1510 Mission Street",
    "sg:city":"South Pasadena",
    "sg:classifiers":[
        {
            "category":"Shopping",
            "subcategory":"Hobbies, Toys, & Games",
            "type":"Retail Goods"
        }
    ],
    "sg:phone":"+1 626 441 2767",
    "sg:postcode":"91030",
    "sg:province":"CA",
    "sg:tags":[
        "toy",
        "store"
    ],
    "sg:website":"www.dinofarm.com",
    "wof:name":"The Dinosaur Farm",
    "wof:placetype":"venue"
},
  "geometry": {"coordinates":[-118.15106400000001,34.115868],"type":"Point"}
}