{
  "type": "Feature",
  "properties": {
    "addr:full":"5495 Mansion Ct La Verne CA 91750",
    "addr:housenumber":"5495",
    "addr:postcode":"91750",
    "addr:street":"Mansion Ct",
    "iso:country":"US",
    "sg:address":"5495 Mansion Ct",
    "sg:city":"La Verne",
    "sg:classifiers":[
        {
            "category":"Shopping",
            "type":"Retail Goods"
        }
    ],
    "sg:phone":"+1 909 357 2371",
    "sg:postcode":"91750",
    "sg:province":"CA",
    "sg:tags":[
        "awning",
        "canopy"
    ],
    "wof:name":"Payless Patio",
    "wof:placetype":"venue"
},
  "geometry": {"coordinates":[-117.773257,34.13024],"type":"Point"}
}