{
  "type": "Feature",
  "properties": {
    "iso:country":"US",
    "sg:address":"2624 Edinger Ave",
    "sg:city":"Sacramento",
    "sg:classifiers":[
        {
            "category":"Freight",
            "type":"Transportation"
        }
    ],
    "sg:phone":"+1 916 719 8228",
    "sg:postcode":"95822",
    "sg:province":"CA",
    "sg:tags":[
        "operator",
        "local",
        "trucking"
    ],
    "wof:name":"L&B Delivery",
    "wof:placetype":"venue"
},
  "geometry": {"coordinates":[-121.47686400000001,38.503371],"type":"Point"}
}