{
  "type": "Feature",
  "properties": {
    "addr:full":"146 Mercury Cir Pomona CA 91768",
    "addr:housenumber":"146",
    "addr:postcode":"91768",
    "addr:street":"Mercury Cir",
    "iso:country":"US",
    "sg:address":"146 Mercury Cir",
    "sg:city":"Pomona",
    "sg:classifiers":[
        {
            "category":"Home & Garden",
            "subcategory":"Furniture",
            "type":"Retail Goods"
        }
    ],
    "sg:phone":"+1 909 592 8813",
    "sg:postcode":"91768",
    "sg:province":"CA",
    "wof:name":"Ams Enterprise Inc",
    "wof:placetype":"venue"
},
  "geometry": {"coordinates":[-117.800797,34.055456],"type":"Point"}
}