{
  "type": "Feature",
  "properties": {
    "iso:country":"US",
    "sg:address":"1798 Excelsior Ave",
    "sg:city":"Oakland",
    "sg:classifiers":[
        {
            "category":"Health Services",
            "subcategory":"Doctor",
            "type":"Services"
        }
    ],
    "sg:phone":"+1 510 531 4241",
    "sg:postcode":"94602",
    "sg:province":"CA",
    "sg:tags":[
        "dentist"
    ],
    "wof:name":"Leticia C Medeiros DDS",
    "wof:placetype":"venue"
},
  "geometry": {"coordinates":[-122.220313,37.801323],"type":"Point"}
}