{
  "type": "Feature",
  "properties": {
    "iso:country":"US",
    "sg:address":"9353 Narnia Dr",
    "sg:city":"Riverside",
    "sg:classifiers":[
        {
            "category":"Building & Trades",
            "subcategory":"Plumbing",
            "type":"Services"
        }
    ],
    "sg:phone":"+1 951 687 6700",
    "sg:postcode":"92503",
    "sg:province":"CA",
    "sg:tags":[
        "plumber",
        "industrial",
        "contractors-commercial"
    ],
    "wof:name":"Haro Plumbing",
    "wof:placetype":"venue"
},
  "geometry": {"coordinates":[-117.438368,33.914616],"type":"Point"}
}