{
  "type": "Feature",
  "properties": {
    "addr:full":"1648 el Nido Way Sacramento CA 95864",
    "addr:housenumber":"1648",
    "addr:postcode":"95864",
    "addr:street":"El Nido Way",
    "iso:country":"US",
    "sg:address":"1648 el Nido Way",
    "sg:city":"Sacramento",
    "sg:classifiers":[
        {
            "category":"Building & Trades",
            "subcategory":"Landscaping Services",
            "type":"Services"
        }
    ],
    "sg:phone":"+1 916 487 5351",
    "sg:postcode":"95864",
    "sg:province":"CA",
    "sg:tags":[
        "designer",
        "landscape"
    ],
    "wof:name":"Barron's Co",
    "wof:placetype":"venue"
},
  "geometry": {"coordinates":[-121.379813,38.594266],"type":"Point"}
}