{
  "type": "Feature",
  "properties": {
    "addr:full":"1728 University Ave Berkeley CA 94701",
    "addr:housenumber":"1728",
    "addr:postcode":"94701",
    "addr:street":"University Ave",
    "iso:country":"US",
    "sg:address":"1728 University Ave",
    "sg:city":"Berkeley",
    "sg:classifiers":[
        {
            "category":"Personal",
            "subcategory":"Tattoo Parlor",
            "type":"Services"
        }
    ],
    "sg:phone":"+1 510 883 1083",
    "sg:postcode":"94701",
    "sg:province":"CA",
    "sg:website":"www.sacredrosetattoo.com",
    "wof:name":"Sacred Rose Tattoo II",
    "wof:placetype":"venue"
},
  "geometry": {"coordinates":[-122.277,37.870899],"type":"Point"}
}