{
  "type": "Feature",
  "properties": {
    "addr:full":"18430 Pacific St Fountain Valley CA 92708",
    "addr:housenumber":"18430",
    "addr:postcode":"92708",
    "addr:street":"Pacific St",
    "iso:country":"US",
    "sg:address":"18430 Pacific St",
    "sg:city":"Fountain Valley",
    "sg:classifiers":[
        {
            "category":"Wholesale",
            "subcategory":"Furniture",
            "type":"Manufacturing & Wholesale Goods"
        }
    ],
    "sg:phone":"+1 714 968 4228",
    "sg:postcode":"92708",
    "sg:province":"CA",
    "wof:name":"Wholesale Furniture",
    "wof:placetype":"venue"
},
  "geometry": {"coordinates":[-117.938558,33.696256],"type":"Point"}
}