{
  "type": "Feature",
  "properties": {
    "addr:full":"2258 Mesquite Dr Santa Rosa CA 95405",
    "addr:housenumber":"2258",
    "addr:postcode":"95405",
    "addr:street":"Mesquite Dr",
    "iso:country":"US",
    "sg:address":"2258 Mesquite Dr",
    "sg:city":"Santa Rosa",
    "sg:classifiers":[
        {
            "category":"Professional",
            "subcategory":"Business Services",
            "type":"Services"
        }
    ],
    "sg:phone":"+1 707 544 7700",
    "sg:postcode":"95405",
    "sg:province":"CA",
    "sg:website":"www.integrityshred.com",
    "wof:name":"Integrity Shred",
    "wof:placetype":"venue"
},
  "geometry": {"coordinates":[-122.67391600000001,38.429226],"type":"Point"}
}