{
  "type": "Feature",
  "properties": {
    "addr:full":"19113 Delano St Tarzana CA 91335",
    "addr:housenumber":"19113",
    "addr:postcode":"91335",
    "addr:street":"Delano St",
    "iso:country":"US",
    "sg:address":"19113 Delano St",
    "sg:city":"Tarzana",
    "sg:classifiers":[
        {
            "category":"Retail",
            "subcategory":"Auto Repair",
            "type":"Services"
        }
    ],
    "sg:phone":"+1 818 344 8340",
    "sg:postcode":"91335",
    "sg:province":"CA",
    "sg:tags":[
        "windshield"
    ],
    "wof:name":"B G Mobile Windshield Repair",
    "wof:placetype":"venue"
},
  "geometry": {"coordinates":[-118.548619,34.182518],"type":"Point"}
}