{
  "type": "Feature",
  "properties": {
    "addr:full":"345 S Figueroa St Los Angeles CA 90071",
    "addr:housenumber":"345",
    "addr:postcode":"90071",
    "addr:street":"S Figueroa St",
    "iso:country":"US",
    "sg:address":"345 S Figueroa St",
    "sg:city":"Los Angeles",
    "sg:classifiers":[
        {
            "category":"Local Transit",
            "type":"Transportation"
        }
    ],
    "sg:phone":"+1 213 626 5466",
    "sg:postcode":"90071",
    "sg:province":"CA",
    "sg:tags":[
        "limousine",
        "limo"
    ],
    "wof:name":"Sunshine Limo",
    "wof:placetype":"venue"
},
  "geometry": {"coordinates":[-118.25599699999999,34.053799],"type":"Point"}
}