{
  "type": "Feature",
  "properties": {
    "addr:full":"201 Taylor Way Blue Lake CA 95525",
    "addr:housenumber":"201",
    "addr:postcode":"95525",
    "addr:street":"Taylor Way",
    "iso:country":"US",
    "sg:address":"201 Taylor Way",
    "sg:city":"Blue Lake",
    "sg:classifiers":[
        {
            "category":"Wholesale",
            "subcategory":"Groceries",
            "type":"Manufacturing & Wholesale Goods"
        }
    ],
    "sg:phone":"+1 707 668 1868",
    "sg:postcode":"95525",
    "sg:province":"CA",
    "sg:tags":[
        "grocer"
    ],
    "wof:name":"Tomaso's Specialty Foods",
    "wof:placetype":"venue"
},
  "geometry": {"coordinates":[-123.998316,40.879874],"type":"Point"}
}