{
  "type": "Feature",
  "properties": {
    "iso:country":"US",
    "sg:address":"1016 Morse Ave",
    "sg:city":"Sunnyvale",
    "sg:classifiers":[
        {
            "category":"Building & Trades",
            "subcategory":"Construction",
            "type":"Services"
        },
        {
            "category":"Retail",
            "subcategory":"Auto Repair",
            "type":"Services"
        }
    ],
    "sg:phone":"+1 408 734 9663",
    "sg:postcode":"94086",
    "sg:province":"CA",
    "sg:tags":[
        "glass",
        "coating",
        "tinting",
        "contractor"
    ],
    "wof:name":"Professional Window Tint",
    "wof:placetype":"venue"
},
  "geometry": {"coordinates":[-122.01752,37.39698],"type":"Point"}
}