{
  "type": "Feature",
  "properties": {
    "addr:full":"6926 Lankershim Blvd North Hollywood CA 91605",
    "addr:housenumber":"6926",
    "addr:postcode":"91605",
    "addr:street":"Lankershim Blvd",
    "iso:country":"US",
    "sg:address":"6926 Lankershim Blvd",
    "sg:city":"North Hollywood",
    "sg:classifiers":[
        {
            "category":"Retail",
            "subcategory":"Auto Repair",
            "type":"Services"
        }
    ],
    "sg:phone":"+1 818 765 8500",
    "sg:postcode":"91605",
    "sg:province":"CA",
    "sg:tags":[
        "body",
        "shop"
    ],
    "wof:name":"Julians Towing & Auto Body",
    "wof:placetype":"venue"
},
  "geometry": {"coordinates":[-118.38800000000001,34.197102],"type":"Point"}
}