{
  "type": "Feature",
  "properties": {
    "iso:country":"US",
    "sg:address":"316 East H St",
    "sg:city":"Chula Vista",
    "sg:classifiers":[
        {
            "category":"Professional",
            "type":"Services"
        },
        {
            "category":"Personal",
            "subcategory":"Day Spa",
            "type":"Services"
        }
    ],
    "sg:phone":"+1 619 827 0550",
    "sg:postcode":"91910",
    "sg:province":"CA",
    "sg:website":"www.massageenvy.com",
    "wof:name":"Massage Envy",
    "wof:placetype":"venue"
},
  "geometry": {"coordinates":[-117.051804,32.639607],"type":"Point"}
}