{
  "type": "Feature",
  "properties": {
    "iso:country":"US",
    "sg:address":"2116 Main St",
    "sg:city":"Julian",
    "sg:classifiers":[
        {
            "category":"Restaurant",
            "type":"Food & Drink"
        }
    ],
    "sg:phone":"+1 760 765 2167",
    "sg:postcode":"92036",
    "sg:province":"CA",
    "wof:name":"Cowgirl Cafe",
    "wof:placetype":"venue"
},
  "geometry": {"coordinates":[-116.601573,33.078084],"type":"Point"}
}