{
  "type": "Feature",
  "properties": {
    "iso:country":"US",
    "sg:address":"19350 Nordhoff St",
    "sg:city":"Northridge",
    "sg:classifiers":[
        {
            "category":"Home & Garden",
            "subcategory":"Furniture",
            "type":"Retail Goods"
        }
    ],
    "sg:phone":"+1 818 993 1310",
    "sg:postcode":"91324",
    "sg:province":"CA",
    "wof:name":"Levitz Furniture",
    "wof:placetype":"venue"
},
  "geometry": {"coordinates":[-118.55389099999999,34.235407],"type":"Point"}
}