{
  "type": "Feature",
  "properties": {
    "addr:full":"4800 2nd Ave Ste 3010 Sacramento CA 95817",
    "addr:housenumber":"4800",
    "addr:postcode":"95817",
    "addr:street":"2Nd Ave Ste 3010",
    "iso:country":"US",
    "sg:address":"4800 2nd Ave Ste 3010",
    "sg:city":"Sacramento",
    "sg:classifiers":[
        {
            "category":"Community Center",
            "type":"Public Place"
        }
    ],
    "sg:phone":"+1 916 734 6570",
    "sg:postcode":"95817",
    "sg:province":"CA",
    "sg:tags":[
        "medical"
    ],
    "wof:name":"Uc Davis Medical Center",
    "wof:placetype":"venue"
},
  "geometry": {"coordinates":[-121.450249,38.550961],"type":"Point"}
}