{
  "type": "Feature",
  "properties": {
    "addr:full":"195 Main St Point Arena CA 95468",
    "addr:housenumber":"195",
    "addr:postcode":"95468",
    "addr:street":"Main St Point",
    "iso:country":"US",
    "sg:address":"195 Main St",
    "sg:city":"Point Arena",
    "sg:classifiers":[
        {
            "category":"Real Estate",
            "subcategory":"Real Estate Agent",
            "type":"Services"
        }
    ],
    "sg:phone":"+1 707 882 2434",
    "sg:postcode":"95468",
    "sg:province":"CA",
    "wof:name":"Cypress Properties",
    "wof:placetype":"venue"
},
  "geometry": {"coordinates":[-123.692474,38.910544],"type":"Point"}
}