{
  "type": "Feature",
  "properties": {
    "addr:full":"1201 Walnut Ave Ofc Tustin CA 92780",
    "addr:housenumber":"1201",
    "addr:postcode":"92780",
    "addr:street":"Walnut Ave",
    "iso:country":"US",
    "sg:address":"1201 Walnut Ave Ofc",
    "sg:city":"Tustin",
    "sg:classifiers":[
        {
            "category":"Real Estate",
            "subcategory":"Real Estate Operator",
            "type":"Services"
        }
    ],
    "sg:phone":"+1 714 838 8910",
    "sg:postcode":"92780",
    "sg:province":"CA",
    "sg:tags":[
        "apartment"
    ],
    "wof:name":"Walnut East Apartments",
    "wof:placetype":"venue"
},
  "geometry": {"coordinates":[-117.825996,33.731201],"type":"Point"}
}