{
  "type": "Feature",
  "properties": {
    "iso:country":"US",
    "sg:address":"1639 N Main St",
    "sg:city":"Los Angeles",
    "sg:classifiers":[
        {
            "category":"Shopping",
            "subcategory":"Hobbies, Toys, & Games",
            "type":"Retail Goods"
        }
    ],
    "sg:phone":"+1 323 221 9888",
    "sg:postcode":"90012",
    "sg:province":"CA",
    "wof:name":"Glt International Inc",
    "wof:placetype":"venue"
},
  "geometry": {"coordinates":[-118.227671,34.066665],"type":"Point"}
}