{
  "type": "Feature",
  "properties": {
    "addr:full":"427 W Pear St Beverly Hills CA 90222",
    "addr:housenumber":"427",
    "addr:postcode":"90222",
    "addr:street":"W Pear St",
    "iso:country":"US",
    "sg:address":"427 W Pear St",
    "sg:city":"Beverly Hills",
    "sg:classifiers":[
        {
            "category":"Professional",
            "type":"Services"
        }
    ],
    "sg:phone":"+1 310 275 3467",
    "sg:postcode":"90222",
    "sg:province":"CA",
    "wof:name":"Www Howwegottobehuman Co",
    "wof:placetype":"venue"
},
  "geometry": {"coordinates":[-118.232017,33.906704],"type":"Point"}
}