{
  "type": "Feature",
  "properties": {
    "addr:full":"1127 US Hwy 101 Crescent City CA 95531",
    "addr:housenumber":"1127",
    "addr:postcode":"95531",
    "addr:street":"Us Hwy 101 Crescent",
    "iso:country":"US",
    "sg:address":"1127 US Hwy 101",
    "sg:city":"Crescent City",
    "sg:classifiers":[
        {
            "category":"Shopping",
            "subcategory":"Gifts & Souvenirs",
            "type":"Retail Goods"
        }
    ],
    "sg:phone":"+1 707 464 4151",
    "sg:postcode":"95531",
    "sg:province":"CA",
    "sg:tags":[
        "shop"
    ],
    "wof:name":"Exotic Redword Bur Co",
    "wof:placetype":"venue"
},
  "geometry": {"coordinates":[-124.165093,41.741266],"type":"Point"}
}