{
  "type": "Feature",
  "properties": {
    "addr:full":"225 Mariposa Ave Vacaville CA 95687",
    "addr:housenumber":"225",
    "addr:postcode":"95687",
    "addr:street":"Mariposa Ave",
    "iso:country":"US",
    "sg:address":"225 Mariposa Ave",
    "sg:city":"Vacaville",
    "sg:classifiers":[
        {
            "category":"Shopping",
            "subcategory":"Gifts & Souvenirs",
            "type":"Retail Goods"
        }
    ],
    "sg:phone":"+1 707 469 6892",
    "sg:postcode":"95687",
    "sg:province":"CA",
    "wof:name":"Giftsr4ever",
    "wof:placetype":"venue"
},
  "geometry": {"coordinates":[-121.980141,38.335128],"type":"Point"}
}