{
  "type": "Feature",
  "properties": {
    "addr:full":"1562 Dolphin Dr Aptos CA 95003",
    "addr:housenumber":"1562",
    "addr:postcode":"ca 95003",
    "addr:street":"Dolphin Dr",
    "iso:country":"US",
    "sg:address":"1562 Dolphin Dr",
    "sg:city":"Aptos",
    "sg:classifiers":[
        {
            "category":"Shopping",
            "type":"Retail Goods"
        }
    ],
    "sg:phone":"+1 831 688 6951",
    "sg:postcode":"95003",
    "sg:province":"CA",
    "sg:tags":[
        "merchandise"
    ],
    "wof:name":"Pet Tie Co",
    "wof:placetype":"venue"
},
  "geometry": {"coordinates":[-121.873318,36.955481],"type":"Point"}
}