{
  "type": "Feature",
  "properties": {
    "addr:full":"11875 Dublin Blvd B135 Dublin CA 94568",
    "addr:housenumber":"11875",
    "addr:postcode":"94568",
    "addr:street":"Dublin Blvd B135",
    "iso:country":"US",
    "sg:address":"11875 Dublin Blvd B135",
    "sg:city":"Dublin",
    "sg:classifiers":[
        {
            "category":"Real Estate",
            "subcategory":"Real Estate Services",
            "type":"Services"
        },
        {
            "category":"Structure",
            "subcategory":"Office Building",
            "type":"Public Place"
        }
    ],
    "sg:phone":"+1 925 828 4512",
    "sg:postcode":"94568",
    "sg:province":"CA",
    "sg:tags":[
        "vacancy",
        "park",
        "rental",
        "commercial",
        "listing"
    ],
    "sg:website":"http://www.mjrivas.com",
    "wof:name":"Heritage Park Office Center",
    "wof:placetype":"venue"
},
  "geometry": {"coordinates":[-121.93841500000001,37.70134],"type":"Point"}
}