{
  "type": "Feature",
  "properties": {
    "iso:country":"US",
    "sg:address":"1090 Leisure Town Rd",
    "sg:city":"Vacaville",
    "sg:classifiers":[
        {
            "category":"Freight",
            "type":"Transportation"
        }
    ],
    "sg:phone":"+1 707 446 8276",
    "sg:postcode":"95687",
    "sg:province":"CA",
    "sg:tags":[
        "special"
    ],
    "sg:website":"http://securitypublicstorage.com/SPSVacaville.html",
    "wof:name":"Security Public Storage",
    "wof:placetype":"venue"
},
  "geometry": {"coordinates":[-121.93376000000001,38.384293],"type":"Point"}
}