{
  "type": "Feature",
  "properties": {
    "iso:country":"US",
    "sg:address":"1450 Fashion Island Boulevard",
    "sg:city":"San Mateo",
    "sg:classifiers":[
        {
            "category":"Banks & Credit Unions",
            "subcategory":"Financial Services",
            "type":"Services"
        }
    ],
    "sg:phone":"+1 650 287 4262",
    "sg:postcode":"94404",
    "sg:province":"CA",
    "sg:tags":[
        "broker",
        "mortgage"
    ],
    "wof:name":"Hilltop Financial Mortgage",
    "wof:placetype":"venue"
},
  "geometry": {"coordinates":[-122.288495,37.556806],"type":"Point"}
}