{
  "type": "Feature",
  "properties": {
    "iso:country":"US",
    "sg:address":"7066 Las Positas Rd",
    "sg:city":"Livermore",
    "sg:classifiers":[
        {
            "category":"Food & Beverages",
            "subcategory":"Bakery",
            "type":"Retail Goods"
        }
    ],
    "sg:phone":"+1 925 373 7700",
    "sg:postcode":"94551",
    "sg:province":"CA",
    "sg:tags":[
        "pie"
    ],
    "wof:name":"California Pie Co",
    "wof:placetype":"venue"
},
  "geometry": {"coordinates":[-121.708319,37.707724],"type":"Point"}
}