{
  "type": "Feature",
  "properties": {
    "addr:full":"170 E El Camino Real Sunnyvale CA 94087",
    "addr:housenumber":"170",
    "addr:postcode":"94087",
    "addr:street":"E El Camino Real",
    "iso:country":"US",
    "sg:address":"170 E El Camino Real",
    "sg:city":"Sunnyvale",
    "sg:classifiers":[
        {
            "category":"Retail",
            "subcategory":"Auto Repair",
            "type":"Services"
        }
    ],
    "sg:phone":"+1 408 774 0159",
    "sg:postcode":"94087",
    "sg:province":"CA",
    "sg:website":"www.pepboys.com",
    "wof:name":"Pep Boys Supercenter",
    "wof:placetype":"venue"
},
  "geometry": {"coordinates":[-122.029708,37.365555],"type":"Point"}
}