{
  "type": "Feature",
  "properties": {
    "addr:full":"1819 Pontius Ave Los Angeles CA 90025",
    "addr:housenumber":"1819",
    "addr:postcode":"90025",
    "addr:street":"Pontius Ave",
    "iso:country":"US",
    "sg:address":"1819 Pontius Ave",
    "sg:city":"Los Angeles",
    "sg:classifiers":[
        {
            "category":"Retail",
            "subcategory":"Pet Boarding",
            "type":"Services"
        },
        {
            "category":"Retail",
            "subcategory":"Animal Services",
            "type":"Services"
        }
    ],
    "sg:phone":"+1 310 473 8585",
    "sg:postcode":"90025",
    "sg:province":"CA",
    "sg:tags":[
        "boarding/pet",
        "sitting"
    ],
    "sg:website":"www.campbestfriendscom.verizonsu...",
    "wof:name":"Camp Best Friends Inc",
    "wof:placetype":"venue"
},
  "geometry": {"coordinates":[-118.443001,34.045101],"type":"Point"}
}