{
  "type": "Feature",
  "properties": {
    "addr:full":"2104 Glendale Galleria Glendale CA 91210",
    "addr:housenumber":"2104",
    "addr:postcode":"91210",
    "addr:street":"Glendale Galleria",
    "iso:country":"US",
    "sg:address":"2104 Glendale Galleria",
    "sg:city":"Glendale",
    "sg:classifiers":[
        {
            "category":"Shopping",
            "subcategory":"Clothing, Apparel, & Fashions",
            "type":"Retail Goods"
        }
    ],
    "sg:phone":"+1 818 551 0887",
    "sg:postcode":"91210",
    "sg:province":"CA",
    "sg:tags":[
        "accessory",
        "clothing",
        "women's"
    ],
    "wof:name":"Bebe",
    "wof:placetype":"venue"
},
  "geometry": {"coordinates":[-118.254997,34.146301],"type":"Point"}
}