{
  "type": "Feature",
  "properties": {
    "addr:full":"27560 Jefferson Ave Temecula CA 92590",
    "addr:housenumber":"27560",
    "addr:postcode":"92590",
    "addr:street":"Jefferson Ave",
    "iso:country":"US",
    "sg:address":"27560 Jefferson Ave",
    "sg:city":"Temecula",
    "sg:classifiers":[
        {
            "category":"Freight",
            "type":"Transportation"
        }
    ],
    "sg:phone":"+1 951 676 1623",
    "sg:postcode":"92590",
    "sg:province":"CA",
    "sg:tags":[
        "commercial",
        "storage"
    ],
    "wof:name":"Secure It Self Storage",
    "wof:placetype":"venue"
},
  "geometry": {"coordinates":[-117.162378,33.517788],"type":"Point"}
}