{
  "type": "Feature",
  "properties": {
    "iso:country":"US",
    "sg:address":"17 S 5th St",
    "sg:city":"Redlands",
    "sg:classifiers":[
        {
            "category":"Personal",
            "type":"Services"
        }
    ],
    "sg:phone":"+1 909 792 8586",
    "sg:postcode":"92373",
    "sg:province":"CA",
    "sg:tags":[
        "therapist",
        "massage"
    ],
    "wof:name":"Rebecca Schutt",
    "wof:placetype":"venue"
},
  "geometry": {"coordinates":[-117.181387,34.054787],"type":"Point"}
}