{
  "type": "Feature",
  "properties": {
    "addr:full":"650 Shady Tree Ct Danville CA 94526",
    "addr:housenumber":"650",
    "addr:postcode":"94526",
    "addr:street":"Shady Tree Ct",
    "iso:country":"US",
    "sg:address":"650 Shady Tree Ct",
    "sg:city":"Danville",
    "sg:classifiers":[
        {
            "category":"Building & Trades",
            "subcategory":"Plumbing",
            "type":"Services"
        }
    ],
    "sg:phone":"+1 925 837 6766",
    "sg:postcode":"94526",
    "sg:province":"CA",
    "sg:tags":[
        "plumbing",
        "contractor"
    ],
    "wof:name":"Mike Williams Plumbing",
    "wof:placetype":"venue"
},
  "geometry": {"coordinates":[-121.95834600000001,37.811098],"type":"Point"}
}