{
  "type": "Feature",
  "properties": {
    "addr:full":"310 N Soto St Los Angeles CA 90033",
    "addr:housenumber":"310",
    "addr:postcode":"90033",
    "addr:street":"N Soto St",
    "iso:country":"US",
    "sg:address":"310 N Soto St",
    "sg:city":"Los Angeles",
    "sg:classifiers":[
        {
            "category":"Professional",
            "subcategory":"Lawyer & Legal Services",
            "type":"Services"
        }
    ],
    "sg:phone":"+1 323 260 8012",
    "sg:postcode":"90033",
    "sg:province":"CA",
    "sg:tags":[
        "naturalization",
        "immigration"
    ],
    "wof:name":"Hermandad Mexicanca Nacional",
    "wof:placetype":"venue"
},
  "geometry": {"coordinates":[-118.20719200000001,34.047575],"type":"Point"}
}