{
  "type": "Feature",
  "properties": {
    "addr:full":"1813 S Bayless St Anaheim CA 92802",
    "addr:housenumber":"1813",
    "addr:postcode":"92802",
    "addr:street":"S Bayless St",
    "iso:country":"US",
    "sg:address":"1813 S Bayless St",
    "sg:city":"Anaheim",
    "sg:classifiers":[
        {
            "category":"Shopping",
            "subcategory":"Gifts & Souvenirs",
            "type":"Retail Goods"
        }
    ],
    "sg:phone":"+1 714 772 2615",
    "sg:postcode":"92802",
    "sg:province":"CA",
    "wof:name":"Ch Hutchinson Co",
    "wof:placetype":"venue"
},
  "geometry": {"coordinates":[-117.93629300000001,33.801171],"type":"Point"}
}