{
  "type": "Feature",
  "properties": {
    "iso:country":"US",
    "sg:address":"23181 Verdugo Dr",
    "sg:city":"Laguna Hills",
    "sg:classifiers":[
        {
            "category":"Communications",
            "type":"Services"
        }
    ],
    "sg:phone":"+1 949 916 4335",
    "sg:postcode":"92653",
    "sg:province":"CA",
    "sg:tags":[
        "video"
    ],
    "wof:name":"Renscape Tech Group Inc",
    "wof:placetype":"venue"
},
  "geometry": {"coordinates":[-117.72926099999999,33.626449],"type":"Point"}
}