{
  "type": "Feature",
  "properties": {
    "iso:country":"US",
    "sg:address":"4527 Spencer St",
    "sg:city":"Torrance",
    "sg:classifiers":[
        {
            "category":"Organizations",
            "subcategory":"Religious Organization",
            "type":"Services"
        }
    ],
    "sg:phone":"+1 310 371 3813",
    "sg:postcode":"90503",
    "sg:province":"CA",
    "sg:tags":[
        "church"
    ],
    "wof:name":"Anza Baptist Church",
    "wof:placetype":"venue"
},
  "geometry": {"coordinates":[-118.36199999999999,33.844898],"type":"Point"}
}