{
  "type": "Feature",
  "properties": {
    "addr:full":"454 S 16th St Grover Beach CA 93433",
    "addr:housenumber":"454",
    "addr:postcode":"93433",
    "addr:street":"S 16Th St",
    "iso:country":"US",
    "sg:address":"454 S 16th St",
    "sg:city":"Grover Beach",
    "sg:classifiers":[
        {
            "category":"Building & Trades",
            "subcategory":"Construction",
            "type":"Services"
        }
    ],
    "sg:phone":"+1 805 489 7766",
    "sg:postcode":"93433",
    "sg:province":"CA",
    "sg:tags":[
        "maker",
        "cabinet"
    ],
    "wof:name":"Benchmark",
    "wof:placetype":"venue"
},
  "geometry": {"coordinates":[-120.61194500000001,35.117412],"type":"Point"}
}