{
  "type": "Feature",
  "properties": {
    "iso:country":"US",
    "sg:address":"1754 E Rose Ave",
    "sg:city":"Orange",
    "sg:classifiers":[
        {
            "category":"Place Of Worship",
            "type":"Public Place"
        }
    ],
    "sg:phone":"+1 714 538 1859",
    "sg:postcode":"92867",
    "sg:province":"CA",
    "sg:tags":[
        "church"
    ],
    "wof:name":"Perez Maria De Los Angeles",
    "wof:placetype":"venue"
},
  "geometry": {"coordinates":[-117.835172,33.797268],"type":"Point"}
}