{
  "type": "Feature",
  "properties": {
    "addr:full":"4740 Livingstone Pl Santa Rosa CA 95405",
    "addr:housenumber":"4740",
    "addr:postcode":"95405",
    "addr:street":"Livingstone Pl",
    "iso:country":"US",
    "sg:address":"4740 Livingstone Pl",
    "sg:city":"Santa Rosa",
    "sg:classifiers":[
        {
            "category":"Building & Trades",
            "subcategory":"Construction",
            "type":"Services"
        }
    ],
    "sg:phone":"+1 707 568 1684",
    "sg:postcode":"95405",
    "sg:province":"CA",
    "sg:tags":[
        "fire",
        "restoration",
        "damage"
    ],
    "wof:name":"K 2 Environmental Inc",
    "wof:placetype":"venue"
},
  "geometry": {"coordinates":[-122.657504,38.429991],"type":"Point"}
}