{
  "type": "Feature",
  "properties": {
    "iso:country":"US",
    "sg:address":"550 Hartnell St",
    "sg:city":"Monterey",
    "sg:classifiers":[
        {
            "category":"Winery",
            "type":"Food & Drink"
        }
    ],
    "sg:phone":"+1 831 648 1234",
    "sg:postcode":"93940",
    "sg:province":"CA",
    "wof:name":"Zabala Paseo",
    "wof:placetype":"venue"
},
  "geometry": {"coordinates":[-121.895899,36.596502],"type":"Point"}
}