{
  "type": "Feature",
  "properties": {
    "addr:full":"8417 Limestone Dr Riverside CA 92504",
    "addr:housenumber":"8417",
    "addr:postcode":"92504",
    "addr:street":"Limestone Dr",
    "iso:country":"US",
    "sg:address":"8417 Limestone Dr",
    "sg:city":"Riverside",
    "sg:classifiers":[
        {
            "category":"Building & Trades",
            "subcategory":"Construction",
            "type":"Services"
        }
    ],
    "sg:phone":"+1 951 687 0306",
    "sg:postcode":"92504",
    "sg:province":"CA",
    "sg:tags":[
        "roofing",
        "contractor"
    ],
    "wof:name":"Champion Roofing",
    "wof:placetype":"venue"
},
  "geometry": {"coordinates":[-117.41874199999999,33.921154],"type":"Point"}
}