{
  "type": "Feature",
  "properties": {
    "iso:country":"US",
    "sg:address":"776 E Washington Blvd",
    "sg:city":"Pasadena",
    "sg:classifiers":[
        {
            "category":"Personal",
            "subcategory":"Barber",
            "type":"Services"
        }
    ],
    "sg:phone":"+1 626 794 9801",
    "sg:postcode":"91104",
    "sg:province":"CA",
    "wof:name":"Professional Barber Shop",
    "wof:placetype":"venue"
},
  "geometry": {"coordinates":[-118.134467,34.168887],"type":"Point"}
}