{
  "type": "Feature",
  "properties": {
    "addr:full":"5909 Hillview Avenue San Jose CA 95123",
    "addr:housenumber":"5909",
    "addr:postcode":"95123",
    "addr:street":"Hillview Avenue",
    "iso:country":"US",
    "sg:address":"5909 Hillview Avenue",
    "sg:city":"San Jose",
    "sg:classifiers":[
        {
            "category":"Building & Trades",
            "subcategory":"Cleaning & Sanitation",
            "type":"Services"
        }
    ],
    "sg:phone":"+1 408 227 4135",
    "sg:postcode":"95123",
    "sg:province":"CA",
    "sg:tags":[
        "window",
        "washing"
    ],
    "wof:name":"A1 Enterprise Glass and Window Company",
    "wof:placetype":"venue"
},
  "geometry": {"coordinates":[-121.863015,37.244867],"type":"Point"}
}