{
  "type": "Feature",
  "properties": {
    "iso:country":"US",
    "sg:address":"2430 Torrance Blvd",
    "sg:city":"Torrance",
    "sg:classifiers":[
        {
            "category":"Real Estate",
            "subcategory":"Real Estate Agent",
            "type":"Services"
        }
    ],
    "sg:phone":"+1 310 533 8484",
    "sg:postcode":"90501",
    "sg:province":"CA",
    "wof:name":"Suburban Realty",
    "wof:placetype":"venue"
},
  "geometry": {"coordinates":[-118.327073,33.836353],"type":"Point"}
}