{
  "type": "Feature",
  "properties": {
    "addr:full":"12312 Ranchero Way Grass Valley CA 95949",
    "addr:housenumber":"12312",
    "addr:postcode":"95949",
    "addr:street":"Ranchero Way",
    "iso:country":"US",
    "sg:address":"12312 Ranchero Way",
    "sg:city":"Grass Valley",
    "sg:classifiers":[
        {
            "category":"Shopping",
            "subcategory":"Catalog Store",
            "type":"Retail Goods"
        }
    ],
    "sg:phone":"+1 530 268 0250",
    "sg:postcode":"95949",
    "sg:province":"CA",
    "sg:tags":[
        "mail",
        "order"
    ],
    "wof:name":"Allure Of Radiance",
    "wof:placetype":"venue"
},
  "geometry": {"coordinates":[-121.053364,39.050264],"type":"Point"}
}