{
  "type": "Feature",
  "properties": {
    "iso:country":"US",
    "sg:address":"153 Innsbrook Way",
    "sg:city":"Chico",
    "sg:classifiers":[
        {
            "category":"Building & Trades",
            "subcategory":"Landscaping Services",
            "type":"Services"
        }
    ],
    "sg:phone":"+1 530 343 6608",
    "sg:postcode":"95973",
    "sg:province":"CA",
    "sg:tags":[
        "tree"
    ],
    "wof:name":"Ledford's Tree Svc",
    "wof:placetype":"venue"
},
  "geometry": {"coordinates":[-121.883247,39.774135],"type":"Point"}
}