{
  "type": "Feature",
  "properties": {
    "iso:country":"US",
    "sg:address":"400 S Baldwin Ave # D3",
    "sg:city":"Arcadia",
    "sg:classifiers":[
        {
            "category":"Ice Cream",
            "type":"Food & Drink"
        }
    ],
    "sg:phone":"+1 626 447 1382",
    "sg:postcode":"91007",
    "sg:province":"CA",
    "sg:tags":[
        "frozen",
        "yogurt"
    ],
    "sg:website":"www.cefiore.com",
    "wof:name":"C?fiore",
    "wof:placetype":"venue"
},
  "geometry": {"coordinates":[-118.052645,34.132623],"type":"Point"}
}