{
  "type": "Feature",
  "properties": {
    "iso:country":"US",
    "sg:address":"2246 S Mountain Ave",
    "sg:city":"Ontario",
    "sg:classifiers":[
        {
            "category":"Recreation",
            "type":"Entertainment"
        }
    ],
    "sg:phone":"+1 909 933 9116",
    "sg:postcode":"91762",
    "sg:province":"CA",
    "sg:tags":[
        "martial",
        "arts",
        "instruction"
    ],
    "wof:name":"Dan Castro's Kung Fu San Soo",
    "wof:placetype":"venue"
},
  "geometry": {"coordinates":[-117.66976,34.034691],"type":"Point"}
}