{
  "type": "Feature",
  "properties": {
    "iso:country":"US",
    "sg:address":"120 Newport Center Dr #160",
    "sg:city":"Newport Beach",
    "sg:classifiers":[
        {
            "category":"Real Estate",
            "subcategory":"Real Estate Services",
            "type":"Services"
        }
    ],
    "sg:phone":"+1 949 433 3225",
    "sg:postcode":"92660",
    "sg:province":"CA",
    "sg:website":"www.yourocdreamhomes.com",
    "wof:name":"Metro Estates",
    "wof:placetype":"venue"
},
  "geometry": {"coordinates":[-117.876735,33.612037],"type":"Point"}
}