{
  "type": "Feature",
  "properties": {
    "iso:country":"US",
    "sg:address":"1623 Mission Dr",
    "sg:city":"Solvang",
    "sg:classifiers":[
        {
            "category":"Health Services",
            "subcategory":"Clinic",
            "type":"Services"
        }
    ],
    "sg:phone":"+1 805 693 0218",
    "sg:postcode":"93463",
    "sg:province":"CA",
    "sg:tags":[
        "specialty",
        "outpatient"
    ],
    "wof:name":"Family Life Counseling",
    "wof:placetype":"venue"
},
  "geometry": {"coordinates":[-120.14108899999999,34.596028],"type":"Point"}
}