{
  "type": "Feature",
  "properties": {
    "addr:full":"501 Oak Ave Davis CA 95616",
    "addr:housenumber":"501",
    "addr:postcode":"95616",
    "addr:street":"Oak Ave",
    "iso:country":"US",
    "sg:address":"501 Oak Ave",
    "sg:city":"Davis",
    "sg:classifiers":[
        {
            "category":"Education",
            "subcategory":"University",
            "type":"Public Place"
        }
    ],
    "sg:phone":"+1 530 752 2330",
    "sg:postcode":"95616",
    "sg:province":"CA",
    "sg:tags":[
        "college"
    ],
    "sg:website":"http://www.kinghall.ucdavis.edu",
    "wof:name":"Employee Health Services",
    "wof:placetype":"venue"
},
  "geometry": {"coordinates":[-121.75279999999999,38.546299],"type":"Point"}
}