{
  "type": "Feature",
  "properties": {
    "iso:country":"US",
    "sg:address":"210 E Castle St",
    "sg:city":"Mount Shasta",
    "sg:classifiers":[
        {
            "category":"Travel",
            "subcategory":"Travel Agent",
            "type":"Entertainment"
        }
    ],
    "sg:phone":"+1 530 926 6003",
    "sg:postcode":"96067",
    "sg:province":"CA",
    "sg:tags":[
        "operator",
        "tour"
    ],
    "wof:name":"Sierra Wilderness Seminars",
    "wof:placetype":"venue"
},
  "geometry": {"coordinates":[-122.312401,41.315098],"type":"Point"}
}