{
  "type": "Feature",
  "properties": {
    "iso:country":"US",
    "sg:address":"11301 Wilshire Blvd Bldg 212",
    "sg:city":"Los Angeles",
    "sg:classifiers":[
        {
            "category":"Personal",
            "subcategory":"Barber",
            "type":"Services"
        }
    ],
    "sg:phone":"+1 310 312 6783",
    "sg:postcode":"90073",
    "sg:province":"CA",
    "sg:website":"sites.google.com/site/thebarbero...",
    "wof:name":"Barber of Dreamers",
    "wof:placetype":"venue"
},
  "geometry": {"coordinates":[-118.243539,34.049948],"type":"Point"}
}