{
  "type": "Feature",
  "properties": {
    "addr:full":"123 University Ave Ventura CA 93003",
    "addr:housenumber":"123",
    "addr:postcode":"93003",
    "addr:street":"University Ave",
    "iso:country":"US",
    "sg:address":"123 University Ave",
    "sg:city":"Ventura",
    "sg:classifiers":[
        {
            "category":"Health Services",
            "subcategory":"Clinic",
            "type":"Services"
        }
    ],
    "sg:phone":"+1 805 639 0111",
    "sg:postcode":"93003",
    "sg:province":"CA",
    "wof:name":"Inside Healthcare Computing",
    "wof:placetype":"venue"
},
  "geometry": {"coordinates":[-119.232806,34.273253],"type":"Point"}
}