{
  "type": "Feature",
  "properties": {
    "iso:country":"US",
    "sg:address":"15700 Rosecrans Ave",
    "sg:city":"La Mirada",
    "sg:classifiers":[
        {
            "category":"Education",
            "subcategory":"Preschool",
            "type":"Public Place"
        },
        {
            "category":"Education",
            "subcategory":"School",
            "type":"Public Place"
        }
    ],
    "sg:phone":"+1 714 739 1198",
    "sg:postcode":"90638",
    "sg:province":"CA",
    "sg:tags":[
        "elementary"
    ],
    "wof:name":"Gim Place Preschool",
    "wof:placetype":"venue"
},
  "geometry": {"coordinates":[-117.996621,33.898643],"type":"Point"}
}