{
  "type": "Feature",
  "properties": {
    "iso:country":"US",
    "sg:address":"14 Orinda Way",
    "sg:city":"Orinda",
    "sg:classifiers":[
        {
            "category":"Banks & Credit Unions",
            "subcategory":"Investment Brokerage",
            "type":"Services"
        }
    ],
    "sg:phone":"+1 925 254 1074",
    "sg:postcode":"94563",
    "sg:province":"CA",
    "sg:tags":[
        "security"
    ],
    "wof:name":"Paulson Investment Co",
    "wof:placetype":"venue"
},
  "geometry": {"coordinates":[-122.189245,37.883568],"type":"Point"}
}