{
  "type": "Feature",
  "properties": {
    "iso:country":"US",
    "sg:address":"5375 Kearny Villa Rd Ste 102",
    "sg:city":"San Diego",
    "sg:classifiers":[
        {
            "category":"Communications",
            "subcategory":"Newspaper",
            "type":"Services"
        }
    ],
    "sg:phone":"+1 858 571 3151",
    "sg:postcode":"92123",
    "sg:province":"CA",
    "sg:tags":[
        "advertising"
    ],
    "wof:name":"Express Signs",
    "wof:placetype":"venue"
},
  "geometry": {"coordinates":[-117.138828,32.830669],"type":"Point"}
}