{
  "type": "Feature",
  "properties": {
    "iso:country":"US",
    "sg:address":"500 S Glenoaks Blvd",
    "sg:city":"Burbank",
    "sg:classifiers":[
        {
            "category":"Food & Beverages",
            "subcategory":"Liquor & Beverages",
            "type":"Retail Goods"
        }
    ],
    "sg:phone":"+1 818 848 5634",
    "sg:postcode":"91502",
    "sg:province":"CA",
    "wof:name":"Burbank Liquor & Market",
    "wof:placetype":"venue"
},
  "geometry": {"coordinates":[-118.301844,34.179975],"type":"Point"}
}