{
  "type": "Feature",
  "properties": {
    "iso:country":"US",
    "sg:address":"14320 Hawthorne Blvd",
    "sg:city":"Lawndale",
    "sg:classifiers":[
        {
            "category":"Personal",
            "subcategory":"Nail Salon",
            "type":"Services"
        }
    ],
    "sg:phone":"+1 310 263 1510",
    "sg:postcode":"90260",
    "sg:province":"CA",
    "wof:name":"A & B Nails",
    "wof:placetype":"venue"
},
  "geometry": {"coordinates":[-118.351997,33.901001],"type":"Point"}
}