{
  "type": "Feature",
  "properties": {
    "iso:country":"US",
    "sg:address":"6261 Eisenhower Ct",
    "sg:city":"Chino",
    "sg:classifiers":[
        {
            "category":"Personal",
            "subcategory":"Beauty Salon",
            "type":"Services"
        }
    ],
    "sg:phone":"+1 909 391 0091",
    "sg:postcode":"91710",
    "sg:province":"CA",
    "wof:name":"Infinite Styles",
    "wof:placetype":"venue"
},
  "geometry": {"coordinates":[-117.668616,34.025699],"type":"Point"}
}