{
  "type": "Feature",
  "properties": {
    "iso:country":"US",
    "sg:address":"4735 Clairemont Dr",
    "sg:city":"San Diego",
    "sg:classifiers":[
        {
            "category":"Wholesale",
            "subcategory":"Hardware",
            "type":"Manufacturing & Wholesale Goods"
        }
    ],
    "sg:phone":"+1 858 270 7655",
    "sg:postcode":"92117",
    "sg:province":"CA",
    "sg:tags":[
        "water",
        "treatment"
    ],
    "wof:name":"Aqua-Clear LLC",
    "wof:placetype":"venue"
},
  "geometry": {"coordinates":[-117.203041,32.83296],"type":"Point"}
}