{
  "type": "Feature",
  "properties": {
    "addr:full":"1897 Concourse Dr Suite 201 San Jose CA 95131",
    "addr:housenumber":"1897",
    "addr:postcode":"95131",
    "addr:street":"Concourse Dr Suite 201",
    "iso:country":"US",
    "sg:address":"1897 Concourse Dr Suite 201",
    "sg:city":"San Jose",
    "sg:classifiers":[
        {
            "category":"Professional",
            "subcategory":"Employment Agencies",
            "type":"Services"
        }
    ],
    "sg:phone":"+1 408 954 1688",
    "sg:postcode":"95131",
    "sg:province":"CA",
    "wof:name":"Silicon Valley Professional Staffing",
    "wof:placetype":"venue"
},
  "geometry": {"coordinates":[-121.89635199999999,37.3979],"type":"Point"}
}