{
  "type": "Feature",
  "properties": {
    "iso:country":"US",
    "sg:address":"416 N Bedford Dr",
    "sg:city":"Beverly Hills",
    "sg:classifiers":[
        {
            "category":"Health Services",
            "subcategory":"Doctor",
            "type":"Services"
        }
    ],
    "sg:phone":"+1 310 278 8823",
    "sg:postcode":"90210",
    "sg:province":"CA",
    "sg:tags":[
        "surgeon",
        "cosmetic"
    ],
    "wof:name":"Beverly Hls Institute of Asthtc & Rcnstrctve Srgry",
    "wof:placetype":"venue"
},
  "geometry": {"coordinates":[-118.404999,34.068199],"type":"Point"}
}