{
  "type": "Feature",
  "properties": {
    "addr:full":"1155 Alpine Rd Walnut Creek CA 94596",
    "addr:housenumber":"1155",
    "addr:postcode":"94596",
    "addr:street":"Alpine Rd",
    "iso:country":"US",
    "sg:address":"1155 Alpine Rd",
    "sg:city":"Walnut Creek",
    "sg:classifiers":[
        {
            "category":"Building & Trades",
            "subcategory":"Landscaping Services",
            "type":"Services"
        }
    ],
    "sg:phone":"+1 925 945 8493",
    "sg:postcode":"94596",
    "sg:province":"CA",
    "wof:name":"Compuscape",
    "wof:placetype":"venue"
},
  "geometry": {"coordinates":[-122.066158,37.895622],"type":"Point"}
}