{
  "type": "Feature",
  "properties": {
    "addr:full":"110 Commerce Cir Sacramento CA 95815",
    "addr:housenumber":"110",
    "addr:postcode":"95815",
    "addr:street":"Commerce Cir",
    "iso:country":"US",
    "sg:address":"110 Commerce Cir",
    "sg:city":"Sacramento",
    "sg:classifiers":[
        {
            "category":"Manufacturing",
            "subcategory":"Metals",
            "type":"Manufacturing & Wholesale Goods"
        }
    ],
    "sg:phone":"+1 916 925 6100",
    "sg:postcode":"95815",
    "sg:province":"CA",
    "sg:tags":[
        "treating",
        "heat"
    ],
    "sg:website":"www.vpei.com",
    "wof:name":"Vacuum Process Engineering",
    "wof:placetype":"venue"
},
  "geometry": {"coordinates":[-121.459228,38.598079],"type":"Point"}
}