{
  "type": "Feature",
  "properties": {
    "addr:full":"8715 Lake Murray Blvd San Diego CA 92119",
    "addr:housenumber":"8715",
    "addr:postcode":"92119",
    "addr:street":"Lake Murray Blvd",
    "iso:country":"US",
    "sg:address":"8715 Lake Murray Blvd",
    "sg:city":"San Diego",
    "sg:classifiers":[
        {
            "category":"Wholesale",
            "subcategory":"Non-durable Goods",
            "type":"Manufacturing & Wholesale Goods"
        }
    ],
    "sg:phone":"+1 619 668 0445",
    "sg:postcode":"92119",
    "sg:province":"CA",
    "sg:tags":[
        "gen",
        "merchandise"
    ],
    "wof:name":"Raf International Inc",
    "wof:placetype":"venue"
},
  "geometry": {"coordinates":[-117.01034799999999,32.802684],"type":"Point"}
}