{
  "type": "Feature",
  "properties": {
    "addr:full":"2915 Chanticleer Avenue Santa Cruz CA 95065",
    "addr:housenumber":"2915",
    "addr:postcode":"95065",
    "addr:street":"Chanticleer Avenue",
    "iso:country":"US",
    "sg:address":"2915 Chanticleer Avenue",
    "sg:city":"Santa Cruz",
    "sg:classifiers":[
        {
            "category":"Health Services",
            "subcategory":"Doctor",
            "type":"Services"
        },
        {
            "category":"Personal",
            "subcategory":"Adult",
            "type":"Services"
        }
    ],
    "sg:phone":"+1 831 477 2375",
    "sg:postcode":"95065",
    "sg:province":"CA",
    "sg:tags":[
        "midwife"
    ],
    "wof:name":"Christy Adwoa A MD",
    "wof:placetype":"venue"
},
  "geometry": {"coordinates":[-121.97814099999999,36.98831],"type":"Point"}
}