{
  "type": "Feature",
  "properties": {
    "addr:full":"916 Claire Ave Corcoran CA 93212",
    "addr:housenumber":"916",
    "addr:postcode":"93212",
    "addr:street":"Claire Ave",
    "iso:country":"US",
    "sg:address":"916 Claire Ave",
    "sg:city":"Corcoran",
    "sg:classifiers":[
        {
            "category":"Food & Beverages",
            "subcategory":"Groceries & Convenience Stores",
            "type":"Retail Goods"
        }
    ],
    "sg:phone":"+1 559 992 5793",
    "sg:postcode":"93212",
    "sg:province":"CA",
    "sg:tags":[
        "market"
    ],
    "wof:name":"LA Morenita Market",
    "wof:placetype":"venue"
},
  "geometry": {"coordinates":[-119.57102399999999,36.10075],"type":"Point"}
}