{
  "type": "Feature",
  "properties": {
    "addr:full":"150 Muir Rd Martinez CA 94553",
    "addr:housenumber":"150",
    "addr:postcode":"94553",
    "addr:street":"Muir Rd",
    "iso:country":"US",
    "sg:address":"150 Muir Rd",
    "sg:city":"Martinez",
    "sg:classifiers":[
        {
            "category":"Community Center",
            "type":"Public Place"
        },
        {
            "category":"Government",
            "subcategory":"Office",
            "type":"Public Place"
        }
    ],
    "sg:phone":"+1 925 372 2000",
    "sg:postcode":"94553",
    "sg:province":"CA",
    "sg:tags":[
        "medical"
    ],
    "wof:name":"Mil Veteran Canteen 612",
    "wof:placetype":"venue"
},
  "geometry": {"coordinates":[-122.112228,37.994831],"type":"Point"}
}