{
  "type": "Feature",
  "properties": {
    "iso:country":"US",
    "sg:address":"947 Los Coches Rd",
    "sg:city":"Soledad",
    "sg:classifiers":[
        {
            "category":"Freight",
            "type":"Transportation"
        }
    ],
    "sg:phone":"+1 831 678 8677",
    "sg:postcode":"93960",
    "sg:province":"CA",
    "sg:tags":[
        "commercial",
        "storage"
    ],
    "wof:name":"Los Coches Self Storage",
    "wof:placetype":"venue"
},
  "geometry": {"coordinates":[-121.318241,36.412243],"type":"Point"}
}