{
  "type": "Feature",
  "properties": {
    "addr:full":"9850 Siempre Viva Rd San Diego CA 92154",
    "addr:housenumber":"9850",
    "addr:postcode":"92154",
    "addr:street":"Siempre Viva Rd",
    "iso:country":"US",
    "sg:address":"9850 Siempre Viva Rd",
    "sg:city":"San Diego",
    "sg:classifiers":[
        {
            "category":"Professional",
            "type":"Services"
        }
    ],
    "sg:phone":"+1 619 661 6497",
    "sg:postcode":"92154",
    "sg:province":"CA",
    "wof:name":"Diapers & Pads",
    "wof:placetype":"venue"
},
  "geometry": {"coordinates":[-116.934133,32.556891],"type":"Point"}
}