{
  "type": "Feature",
  "properties": {
    "addr:full":"113 Park Pl Richmond CA 94801",
    "addr:housenumber":"113",
    "addr:postcode":"94801",
    "addr:street":"Park Pl",
    "iso:country":"US",
    "sg:address":"113 Park Pl",
    "sg:city":"Richmond",
    "sg:classifiers":[
        {
            "category":"Personal",
            "subcategory":"Barber",
            "type":"Services"
        }
    ],
    "sg:phone":"+1 510 236 0250",
    "sg:postcode":"94801",
    "sg:province":"CA",
    "wof:name":"Park Place Barbers",
    "wof:placetype":"venue"
},
  "geometry": {"coordinates":[-122.38516300000001,37.925906],"type":"Point"}
}