{
  "type": "Feature",
  "properties": {
    "iso:country":"US",
    "sg:address":"781 Garden View Ct",
    "sg:city":"Encinitas",
    "sg:classifiers":[
        {
            "category":"Banks & Credit Unions",
            "subcategory":"Bank",
            "type":"Services"
        }
    ],
    "sg:phone":"+1 760 633 1460",
    "sg:postcode":"92024",
    "sg:province":"CA",
    "sg:website":"www.sandiegotrustbank.com",
    "wof:name":"San Diego Trust Bank",
    "wof:placetype":"venue"
},
  "geometry": {"coordinates":[-117.26045499999999,33.01582],"type":"Point"}
}