{
  "type": "Feature",
  "properties": {
    "addr:full":"2501 Spring St Redwood City CA 94063",
    "addr:housenumber":"2501",
    "addr:postcode":"94063",
    "addr:street":"Spring St",
    "iso:country":"US",
    "sg:address":"2501 Spring St",
    "sg:city":"Redwood City",
    "sg:classifiers":[
        {
            "category":"Building & Trades",
            "subcategory":"Construction",
            "type":"Services"
        }
    ],
    "sg:phone":"+1 650 299 1676",
    "sg:postcode":"94063",
    "sg:province":"CA",
    "sg:tags":[
        "resurfacing",
        "laying",
        "refinishing",
        "floor"
    ],
    "wof:name":"D G Floor Coverings",
    "wof:placetype":"venue"
},
  "geometry": {"coordinates":[-122.21042300000001,37.482893],"type":"Point"}
}