{
  "type": "Feature",
  "properties": {
    "addr:full":"1498 Long Beach Blvd Long Beach CA 90813",
    "addr:housenumber":"1498",
    "addr:postcode":"90813",
    "addr:street":"Long Beach Blvd",
    "iso:country":"US",
    "sg:address":"1498 Long Beach Blvd",
    "sg:city":"Long Beach",
    "sg:classifiers":[
        {
            "category":"Professional",
            "subcategory":"Business Services",
            "type":"Services"
        }
    ],
    "sg:phone":"+1 562 218 6244",
    "sg:postcode":"90813",
    "sg:province":"CA",
    "sg:tags":[
        "delivery",
        "courier"
    ],
    "wof:name":"Greyhound Package Express",
    "wof:placetype":"venue"
},
  "geometry": {"coordinates":[-118.189003,33.785599],"type":"Point"}
}