{
  "type": "Feature",
  "properties": {
    "addr:full":"8721 N Magnolia Ave Santee CA 92071",
    "addr:housenumber":"8721",
    "addr:postcode":"92071",
    "addr:street":"N Magnolia Ave",
    "iso:country":"US",
    "sg:address":"8721 N Magnolia Ave",
    "sg:city":"Santee",
    "sg:phone":"+1 619 258 7015",
    "sg:postcode":"92071",
    "sg:province":"CA",
    "sg:website":"http://www.sunsetroofingcompany.com",
    "wof:name":"Sunset Roofing Company Inc.",
    "wof:placetype":"venue"
},
  "geometry": {"coordinates":[-116.96456999999999,32.833585],"type":"Point"}
}