{
  "type": "Feature",
  "properties": {
    "iso:country":"US",
    "sg:address":"8030 Greenback Ln",
    "sg:city":"Citrus Heights",
    "sg:classifiers":[
        {
            "category":"Restaurant",
            "type":"Food & Drink"
        }
    ],
    "sg:menulink":"http://www.allmenus.com/ca/sacramento/172138-burger-king/menu/",
    "sg:phone":"+1 916 726 5660",
    "sg:postcode":"95610",
    "sg:province":"CA",
    "sg:tags":[
        "burger",
        "american"
    ],
    "wof:name":"Burger King",
    "wof:placetype":"venue"
},
  "geometry": {"coordinates":[-121.26519999999999,38.677958],"type":"Point"}
}