{
  "type": "Feature",
  "properties": {
    "addr:full":"1313 E Herndon Ave # 105 Fresno CA 93720",
    "addr:housenumber":"1313;105",
    "addr:postcode":"93720",
    "addr:street":"E Herndon Ave #",
    "iso:country":"US",
    "sg:address":"1313 E Herndon Ave # 105",
    "sg:city":"Fresno",
    "sg:classifiers":[
        {
            "category":"Health Services",
            "subcategory":"Doctor",
            "type":"Services"
        },
        {
            "category":"Health Services",
            "subcategory":"Clinic",
            "type":"Services"
        },
        {
            "category":"Community Center",
            "type":"Public Place"
        }
    ],
    "sg:phone":"+1 559 448 8481",
    "sg:postcode":"93720",
    "sg:province":"CA",
    "sg:tags":[
        "physician",
        "medical",
        "surgeons",
        "nephrology",
        "surgeon",
        "kidneys"
    ],
    "sg:website":"http://www.valleynephrology.com",
    "wof:name":"Valley Nephrology Medical Group",
    "wof:placetype":"venue"
},
  "geometry": {"coordinates":[-119.765862,36.837078],"type":"Point"}
}