{
  "type": "Feature",
  "properties": {
    "addr:full":"517 Castro St San Francisco CA 94114",
    "addr:housenumber":"517",
    "addr:postcode":"94114",
    "addr:street":"Castro St",
    "iso:country":"US",
    "sg:address":"517 Castro St",
    "sg:city":"San Francisco",
    "sg:classifiers":[
        {
            "category":"Restaurant",
            "type":"Food & Drink"
        }
    ],
    "sg:phone":"+1 415 626 1250",
    "sg:postcode":"94114",
    "sg:province":"CA",
    "wof:name":"Sausage Factory Inc",
    "wof:placetype":"venue"
},
  "geometry": {"coordinates":[-122.434798,37.759555],"type":"Point"}
}