{
  "type": "Feature",
  "properties": {
    "addr:full":"1887 Galt St Simi Valley CA 93065",
    "addr:housenumber":"1887",
    "addr:postcode":"93065",
    "addr:street":"Galt St",
    "iso:country":"US",
    "sg:address":"1887 Galt St",
    "sg:city":"Simi Valley",
    "sg:classifiers":[
        {
            "category":"Social Services",
            "subcategory":"Child Care",
            "type":"Services"
        }
    ],
    "sg:phone":"+1 805 577 8782",
    "sg:postcode":"93065",
    "sg:province":"CA",
    "wof:name":"Guiding Our Youth",
    "wof:placetype":"venue"
},
  "geometry": {"coordinates":[-118.765962,34.270966],"type":"Point"}
}