{
  "type": "Feature",
  "properties": {
    "addr:full":"Hamilton Plaza Shopping Center 1650 S Bascom Ave Campbell CA 95008",
    "addr:housenumber":"1650",
    "addr:postcode":"95008",
    "addr:street":"S Bascom Ave",
    "iso:country":"US",
    "sg:address":"Hamilton Plaza Shopping Center 1650 S Bascom Ave",
    "sg:city":"Campbell",
    "sg:classifiers":[
        {
            "category":"Shopping",
            "subcategory":"Clothing, Apparel, & Fashions",
            "type":"Retail Goods"
        }
    ],
    "sg:phone":"+1 408 377 7544",
    "sg:postcode":"95008",
    "sg:province":"CA",
    "sg:tags":[
        "accessory",
        "clothing",
        "women's"
    ],
    "sg:website":"www.dressbarn.com",
    "wof:name":"Dress Barn-Dress Barn Woman",
    "wof:placetype":"venue"
},
  "geometry": {"coordinates":[-121.931595,37.293254],"type":"Point"}
}