{
  "type": "Feature",
  "properties": {
    "iso:country":"US",
    "sg:address":"7081 N Marks Ave",
    "sg:city":"Fresno",
    "sg:classifiers":[
        {
            "category":"Professional",
            "subcategory":"Business Services",
            "type":"Services"
        }
    ],
    "sg:phone":"+1 559 431 8096",
    "sg:postcode":"93711",
    "sg:province":"CA",
    "sg:tags":[
        "fax",
        "copy",
        "rental",
        "related",
        "mailbox"
    ],
    "wof:name":"UPS Stores 1531 The",
    "wof:placetype":"venue"
},
  "geometry": {"coordinates":[-119.84753000000001,36.838049],"type":"Point"}
}