{
  "type": "Feature",
  "properties": {
    "iso:country":"US",
    "sg:address":"9844 Kitty Lane",
    "sg:city":"Oakland",
    "sg:classifiers":[
        {
            "category":"Shopping",
            "subcategory":"Stationery & Office Supplies",
            "type":"Retail Goods"
        },
        {
            "category":"Coffee & Tea",
            "type":"Food & Drink"
        }
    ],
    "sg:phone":"+1 510 569 8000",
    "sg:postcode":"94603",
    "sg:province":"CA",
    "sg:tags":[
        "devices-wholesale",
        "brewing",
        "break",
        "equipment",
        "device",
        "manufacturer"
    ],
    "sg:website":"customcoffeeplan.com",
    "wof:name":"Custom Coffee Plan",
    "wof:placetype":"venue"
},
  "geometry": {"coordinates":[-122.19541099999999,37.727958],"type":"Point"}
}