{
  "type": "Feature",
  "properties": {
    "iso:country":"US",
    "sg:address":"2180 Meyers Ave",
    "sg:city":"Escondido",
    "sg:classifiers":[
        {
            "category":"Building & Trades",
            "subcategory":"Electrical",
            "type":"Services"
        }
    ],
    "sg:phone":"+1 760 745 2001",
    "sg:postcode":"92029",
    "sg:province":"CA",
    "sg:tags":[
        "electric",
        "contractor"
    ],
    "wof:name":"Baker Electric Inc",
    "wof:placetype":"venue"
},
  "geometry": {"coordinates":[-117.12457499999999,33.129287],"type":"Point"}
}