{
  "type": "Feature",
  "properties": {
    "iso:country":"US",
    "sg:address":"625 S Hill St",
    "sg:city":"Los Angeles",
    "sg:classifiers":[
        {
            "category":"Retail",
            "subcategory":"Repair Shop",
            "type":"Services"
        },
        {
            "category":"Shopping",
            "subcategory":"Jewelry",
            "type":"Retail Goods"
        }
    ],
    "sg:phone":"+1 213 683 1889",
    "sg:postcode":"90014",
    "sg:province":"CA",
    "wof:name":"First Class Jewelry Inc",
    "wof:placetype":"venue"
},
  "geometry": {"coordinates":[-118.25423600000001,34.046307],"type":"Point"}
}