{
  "type": "Feature",
  "properties": {
    "iso:country":"US",
    "sg:address":"1406 W 178th St",
    "sg:city":"Gardena",
    "sg:classifiers":[
        {
            "category":"Shopping",
            "subcategory":"Clothing, Apparel, & Fashions",
            "type":"Retail Goods"
        },
        {
            "category":"Shopping",
            "subcategory":"Baby Store",
            "type":"Retail Goods"
        }
    ],
    "sg:phone":"+1 310 225 2522",
    "sg:postcode":"90248",
    "sg:province":"CA",
    "sg:tags":[
        "infant",
        "women's",
        "children's",
        "wear",
        "apparel",
        "girls'",
        "clothing"
    ],
    "wof:name":"Lily Bleu",
    "wof:placetype":"venue"
},
  "geometry": {"coordinates":[-118.299859,33.868896],"type":"Point"}
}