{
  "type": "Feature",
  "properties": {
    "addr:full":"18014 Sherman Way Reseda CA 91335",
    "addr:housenumber":"18014",
    "addr:postcode":"91335",
    "addr:street":"Sherman Way",
    "iso:country":"US",
    "sg:address":"18014 Sherman Way",
    "sg:city":"Reseda",
    "sg:classifiers":[
        {
            "category":"Real Estate",
            "subcategory":"Real Estate Operator",
            "type":"Services"
        }
    ],
    "sg:phone":"+1 818 342 1218",
    "sg:postcode":"91335",
    "sg:province":"CA",
    "sg:tags":[
        "apartment"
    ],
    "wof:name":"Concord Square Apartments",
    "wof:placetype":"venue"
},
  "geometry": {"coordinates":[-118.525775,34.200936],"type":"Point"}
}