{
  "type": "Feature",
  "properties": {
    "addr:full":"450 N East St Woodland CA 95776",
    "addr:housenumber":"450",
    "addr:postcode":"95776",
    "addr:street":"N East St",
    "iso:country":"US",
    "sg:address":"450 N East St",
    "sg:city":"Woodland",
    "sg:classifiers":[
        {
            "category":"Building & Trades",
            "subcategory":"Electrical",
            "type":"Services"
        }
    ],
    "sg:phone":"+1 530 662 5560",
    "sg:postcode":"95776",
    "sg:province":"CA",
    "sg:tags":[
        "electric",
        "contractor"
    ],
    "wof:name":"Rowland Electric Svc",
    "wof:placetype":"venue"
},
  "geometry": {"coordinates":[-121.765192,38.69038],"type":"Point"}
}