{
  "type": "Feature",
  "properties": {
    "iso:country":"US",
    "sg:address":"2116 Northgate Blvd",
    "sg:city":"Sacramento",
    "sg:classifiers":[
        {
            "category":"Home & Garden",
            "subcategory":"Household Appliances",
            "type":"Retail Goods"
        }
    ],
    "sg:phone":"+1 916 993 4858",
    "sg:postcode":"95833",
    "sg:province":"CA",
    "sg:tags":[
        "major",
        "appliances-small"
    ],
    "wof:name":"Julios Sewing & Appliance",
    "wof:placetype":"venue"
},
  "geometry": {"coordinates":[-121.47572099999999,38.605859],"type":"Point"}
}