{
  "type": "Feature",
  "properties": {
    "addr:full":"11 Allendale Ct Walnut Creek CA 94595",
    "addr:housenumber":"11",
    "addr:postcode":"94595",
    "addr:street":"Allendale Ct",
    "iso:country":"US",
    "sg:address":"11 Allendale Ct",
    "sg:city":"Walnut Creek",
    "sg:classifiers":[
        {
            "category":"Building & Trades",
            "subcategory":"Construction",
            "type":"Services"
        }
    ],
    "sg:phone":"+1 925 944 5300",
    "sg:postcode":"94595",
    "sg:province":"CA",
    "sg:tags":[
        "repairing",
        "remodeling",
        "contractor"
    ],
    "wof:name":"Simply Kitchen & Bath",
    "wof:placetype":"venue"
},
  "geometry": {"coordinates":[-122.072222,37.890784],"type":"Point"}
}