{
  "type": "Feature",
  "properties": {
    "addr:full":"243 Pacific Coast Hwy Hermosa Beach CA 90254",
    "addr:housenumber":"243",
    "addr:postcode":"90254",
    "addr:street":"Pacific Coast Hwy",
    "iso:country":"US",
    "sg:address":"243 Pacific Coast Hwy",
    "sg:city":"Hermosa Beach",
    "sg:classifiers":[
        {
            "category":"Retail",
            "subcategory":"Self-service Laundry",
            "type":"Services"
        }
    ],
    "sg:phone":"+1 310 372 2877",
    "sg:postcode":"90254",
    "sg:province":"CA",
    "wof:name":"Brothers II Laundry & Cleaners",
    "wof:placetype":"venue"
},
  "geometry": {"coordinates":[-118.390782,33.85656],"type":"Point"}
}