{
  "type": "Feature",
  "properties": {
    "addr:full":"6325 Topanga Canyon Blvd Ste 320 Woodland Hills CA 91367",
    "addr:housenumber":"6325",
    "addr:postcode":"91367",
    "addr:street":"Topanga Canyon Blvd Ste 320",
    "iso:country":"US",
    "sg:address":"6325 Topanga Canyon Blvd Ste 320",
    "sg:city":"Woodland Hills",
    "sg:classifiers":[
        {
            "category":"Health Services",
            "subcategory":"Dentist",
            "type":"Services"
        }
    ],
    "sg:phone":"+1 818 716 7966",
    "sg:postcode":"91367",
    "sg:province":"CA",
    "wof:name":"Butterworth Jere DDS",
    "wof:placetype":"venue"
},
  "geometry": {"coordinates":[-118.60612500000001,34.18536],"type":"Point"}
}