{
  "type": "Feature",
  "properties": {
    "addr:full":"2141 S Hathaway St Santa Ana CA 92705",
    "addr:housenumber":"2141",
    "addr:postcode":"92705",
    "addr:street":"S Hathaway St",
    "iso:country":"US",
    "sg:address":"2141 S Hathaway St",
    "sg:city":"Santa Ana",
    "sg:classifiers":[
        {
            "category":"Wholesale",
            "subcategory":"Apparel",
            "type":"Manufacturing & Wholesale Goods"
        }
    ],
    "sg:phone":"+1 714 549 5245",
    "sg:postcode":"92705",
    "sg:province":"CA",
    "sg:tags":[
        "clothing",
        "business"
    ],
    "wof:name":"Frontline USA Inc",
    "wof:placetype":"venue"
},
  "geometry": {"coordinates":[-117.852585,33.71956],"type":"Point"}
}