{
  "type": "Feature",
  "properties": {
    "iso:country":"US",
    "sg:address":"160 Sansome St",
    "sg:city":"San Francisco",
    "sg:classifiers":[
        {
            "category":"Professional",
            "subcategory":"Management & Consulting",
            "type":"Services"
        }
    ],
    "sg:phone":"+1 415 788 7983",
    "sg:postcode":"94104",
    "sg:province":"CA",
    "sg:tags":[
        "consultant",
        "business"
    ],
    "sg:website":"www.devinegong.com",
    "wof:name":"Devine & Gong Inc",
    "wof:placetype":"venue"
},
  "geometry": {"coordinates":[-122.400768,37.79155],"type":"Point"}
}