{
  "type": "Feature",
  "properties": {
    "addr:full":"1604 Mission Street Santa Cruz CA 95060",
    "addr:housenumber":"1604",
    "addr:postcode":"95060",
    "addr:street":"Mission Street",
    "iso:country":"US",
    "sg:address":"1604 Mission Street",
    "sg:city":"Santa Cruz",
    "sg:classifiers":[
        {
            "category":"Shopping",
            "subcategory":"Clothing, Apparel, & Fashions",
            "type":"Retail Goods"
        },
        {
            "category":"Sports & Exercise",
            "subcategory":"Bicycle Rental",
            "type":"Entertainment"
        }
    ],
    "sg:phone":"+1 831 454 0360",
    "sg:postcode":"95060",
    "sg:province":"CA",
    "sg:tags":[
        "men's",
        "clothing",
        "wear",
        "women's"
    ],
    "sg:website":"www.ripcurl.com",
    "wof:name":"Rip Curl Surf Shop",
    "wof:placetype":"venue"
},
  "geometry": {"coordinates":[-122.041162,36.966765],"type":"Point"}
}