{
  "type": "Feature",
  "properties": {
    "addr:full":"903 10Th Avenue Redwood City, Ca 94063",
    "wof:categories":[
        "education_and_religion:education=school"
    ],
    "wof:name":"Taft Elementary School",
    "wof:placetype":"venue"
},
  "geometry": {"coordinates":[-122.19399900113385,37.47999756883689],"type":"Point"}
}