{
  "type": "Feature",
  "properties": {
    "addr:full":"4595 Tilbury Ct Santa Maria CA 93455",
    "addr:housenumber":"4595",
    "addr:postcode":"93455",
    "addr:street":"Tilbury Ct",
    "iso:country":"US",
    "sg:address":"4595 Tilbury Ct",
    "sg:city":"Santa Maria",
    "sg:classifiers":[
        {
            "category":"Building & Trades",
            "subcategory":"Electrical",
            "type":"Services"
        }
    ],
    "sg:phone":"+1 805 937 2569",
    "sg:postcode":"93455",
    "sg:province":"CA",
    "sg:tags":[
        "electrical",
        "contractor"
    ],
    "wof:name":"T & G Electric Inc",
    "wof:placetype":"venue"
},
  "geometry": {"coordinates":[-120.412915,34.871368],"type":"Point"}
}