{
  "type": "Feature",
  "properties": {
    "addr:full":"732 S Maple Ave Montebello CA 90640",
    "addr:housenumber":"732",
    "addr:postcode":"90640",
    "addr:street":"S Maple Ave",
    "iso:country":"US",
    "sg:address":"732 S Maple Ave",
    "sg:city":"Montebello",
    "sg:classifiers":[
        {
            "category":"Retail",
            "subcategory":"Repair Shop",
            "type":"Services"
        }
    ],
    "sg:phone":"+1 323 721 2765",
    "sg:postcode":"90640",
    "sg:province":"CA",
    "sg:tags":[
        "equipment",
        "hydraulic"
    ],
    "wof:name":"Evergreen Hydraulics",
    "wof:placetype":"venue"
},
  "geometry": {"coordinates":[-118.120667,34.002013],"type":"Point"}
}