{
  "type": "Feature",
  "properties": {
    "addr:full":"23737 Chrisman Rd Tracy CA 95304",
    "addr:postcode":"23737;95304",
    "addr:street":"Chrisman Rd",
    "iso:country":"US",
    "sg:address":"23737 Chrisman Rd",
    "sg:city":"Tracy",
    "sg:classifiers":[
        {
            "category":"Autos & Motor Vehicles",
            "subcategory":"Automobile Sales",
            "type":"Retail Goods"
        }
    ],
    "sg:phone":"+1 209 835 1639",
    "sg:postcode":"95304",
    "sg:province":"CA",
    "sg:tags":[
        "classic"
    ],
    "wof:name":"Borges Wire Works",
    "wof:placetype":"venue"
},
  "geometry": {"coordinates":[-121.39825500000001,37.743415],"type":"Point"}
}