{
  "type": "Feature",
  "properties": {
    "addr:full":"8145 Ronson Rd San Diego CA 92111",
    "addr:housenumber":"8145",
    "addr:postcode":"92111",
    "addr:street":"Ronson Rd",
    "iso:country":"US",
    "sg:address":"8145 Ronson Rd",
    "sg:city":"San Diego",
    "sg:classifiers":[
        {
            "category":"Professional",
            "type":"Services"
        }
    ],
    "sg:phone":"+1 858 467 6900",
    "sg:postcode":"92111",
    "sg:province":"CA",
    "sg:tags":[
        "establishment"
    ],
    "wof:name":"New Alternatives Inc",
    "wof:placetype":"venue"
},
  "geometry": {"coordinates":[-117.14688,32.829021],"type":"Point"}
}