{
  "type": "Feature",
  "properties": {
    "addr:full":"20348 Sun Valley Dr Laguna Beach CA 92651",
    "addr:housenumber":"20348",
    "addr:postcode":"92651",
    "addr:street":"Sun Valley Dr",
    "iso:country":"US",
    "sg:address":"20348 Sun Valley Dr",
    "sg:city":"Laguna Beach",
    "sg:classifiers":[
        {
            "category":"Wholesale",
            "subcategory":"Computers",
            "type":"Manufacturing & Wholesale Goods"
        }
    ],
    "sg:phone":"+1 619 602 3344",
    "sg:postcode":"92651",
    "sg:province":"CA",
    "wof:name":"Peternavarro Co",
    "wof:placetype":"venue"
},
  "geometry": {"coordinates":[-117.75924999999999,33.57947],"type":"Point"}
}