{
  "type": "Feature",
  "properties": {
    "addr:full":"10613 Odell Rd San Diego CA 92126",
    "addr:housenumber":"10613",
    "addr:postcode":"92126",
    "addr:street":"Odell Rd",
    "iso:country":"US",
    "sg:address":"10613 Odell Rd",
    "sg:city":"San Diego",
    "sg:classifiers":[
        {
            "category":"Wholesale",
            "subcategory":"Durable Goods & Equipment",
            "type":"Manufacturing & Wholesale Goods"
        }
    ],
    "sg:phone":"+1 858 549 6811",
    "sg:postcode":"92126",
    "sg:province":"CA",
    "wof:name":"Dasoph Trade Import Export",
    "wof:placetype":"venue"
},
  "geometry": {"coordinates":[-117.154329,32.910249],"type":"Point"}
}