{
  "type": "Feature",
  "properties": {
    "addr:full":"3320 Second Ave San Diego CA 92103",
    "addr:housenumber":"3320",
    "addr:postcode":"92103",
    "addr:street":"Second Ave",
    "iso:country":"US",
    "sg:address":"3320 Second Ave",
    "sg:city":"San Diego",
    "sg:classifiers":[
        {
            "category":"Personal",
            "subcategory":"Beauty Salon",
            "type":"Services"
        }
    ],
    "sg:phone":"+1 858 717 7710",
    "sg:postcode":"92103",
    "sg:province":"CA",
    "sg:tags":[
        "hair",
        "makeup",
        "artist"
    ],
    "sg:website":"www.bellefemmebeauty.com/",
    "wof:name":"Belle Femme Beauty",
    "wof:placetype":"venue"
},
  "geometry": {"coordinates":[-117.16338,32.740059],"type":"Point"}
}