{
  "type": "Feature",
  "properties": {
    "addr:full":"331 W 9th St Santa Rosa CA 95401",
    "addr:housenumber":"331",
    "addr:postcode":"ca 95401",
    "addr:street":"W 9Th St",
    "iso:country":"US",
    "sg:address":"331 W 9th St",
    "sg:city":"Santa Rosa",
    "sg:classifiers":[
        {
            "category":"Retail",
            "subcategory":"Auto Repair",
            "type":"Services"
        }
    ],
    "sg:phone":"+1 707 545 0232",
    "sg:postcode":"95401",
    "sg:province":"CA",
    "sg:tags":[
        "repairing",
        "automobile"
    ],
    "wof:name":"Callagy Automotive & Smog",
    "wof:placetype":"venue"
},
  "geometry": {"coordinates":[-122.72999,38.441698],"type":"Point"}
}