{
  "type": "Feature",
  "properties": {
    "addr:full":"1107 Fair Oaks Ave Ste 328 South Pasadena CA 91030",
    "addr:housenumber":"1107",
    "addr:postcode":"91030",
    "addr:street":"Fair Oaks Ave Ste 328",
    "iso:country":"US",
    "sg:address":"1107 Fair Oaks Ave Ste 328",
    "sg:city":"South Pasadena",
    "sg:classifiers":[
        {
            "category":"Shopping",
            "subcategory":"Beauty & Cosmetics",
            "type":"Retail Goods"
        },
        {
            "category":"Personal",
            "subcategory":"Beauty Salon",
            "type":"Services"
        }
    ],
    "sg:phone":"+1 626 818 6083",
    "sg:postcode":"91030",
    "sg:province":"CA",
    "sg:tags":[
        "makeup",
        "artist",
        "supply"
    ],
    "wof:name":"Vox Cosmetics",
    "wof:placetype":"venue"
},
  "geometry": {"coordinates":[-118.15037100000001,34.112461],"type":"Point"}
}