{
  "type": "Feature",
  "properties": {
    "addr:full":"413 Moorpark Ave Moorpark CA 93021",
    "addr:housenumber":"413",
    "addr:postcode":"ca 93021",
    "addr:street":"Moorpark Ave",
    "iso:country":"US",
    "sg:address":"413 Moorpark Ave",
    "sg:city":"Moorpark",
    "sg:classifiers":[
        {
            "category":"Personal",
            "subcategory":"Beauty Salon",
            "type":"Services"
        }
    ],
    "sg:phone":"+1 805 523 8802",
    "sg:postcode":"93021",
    "sg:province":"CA",
    "wof:name":"Lucy's Beauty Salon",
    "wof:placetype":"venue"
},
  "geometry": {"coordinates":[-118.88211699999999,34.283068],"type":"Point"}
}