{
  "type": "Feature",
  "properties": {
    "iso:country":"US",
    "sg:address":"3807 E Tulare Ave",
    "sg:city":"Fresno",
    "sg:classifiers":[
        {
            "category":"Retail",
            "subcategory":"Repair Shop",
            "type":"Services"
        }
    ],
    "sg:phone":"+1 559 445 0019",
    "sg:postcode":"93702",
    "sg:province":"CA",
    "sg:tags":[
        "upholsterer"
    ],
    "wof:name":"Colin Upholstery",
    "wof:placetype":"venue"
},
  "geometry": {"coordinates":[-119.760899,36.743252],"type":"Point"}
}