{
  "type": "Feature",
  "properties": {
    "iso:country":"US",
    "sg:address":"28924 S Western Ave",
    "sg:city":"Rancho Pls Vrds",
    "sg:classifiers":[
        {
            "category":"Retail",
            "subcategory":"Funeral Services",
            "type":"Services"
        }
    ],
    "sg:phone":"+1 310 521 1353",
    "sg:postcode":"90275",
    "sg:province":"CA",
    "sg:tags":[
        "information"
    ],
    "wof:name":"Advanced Funeral Planning",
    "wof:placetype":"venue"
},
  "geometry": {"coordinates":[-118.310002,33.756349],"type":"Point"}
}