{
  "type": "Feature",
  "properties": {
    "iso:country":"US",
    "sg:address":"59 11th St",
    "sg:city":"Hermosa Beach",
    "sg:classifiers":[
        {
            "category":"Parking",
            "type":"Transportation"
        }
    ],
    "sg:phone":"+1 310 376 2196",
    "sg:postcode":"90254",
    "sg:province":"CA",
    "sg:tags":[
        "garage"
    ],
    "wof:name":"Parking Concepts",
    "wof:placetype":"venue"
},
  "geometry": {"coordinates":[-118.400323,33.861433],"type":"Point"}
}