{
  "type": "Feature",
  "properties": {
    "addr:full":"15136 Ventura Blvd Sherman Oaks CA 91403",
    "addr:housenumber":"15136",
    "addr:postcode":"91403",
    "addr:street":"Ventura Blvd",
    "iso:country":"US",
    "sg:address":"15136 Ventura Blvd",
    "sg:city":"Sherman Oaks",
    "sg:classifiers":[
        {
            "category":"Restaurant",
            "type":"Food & Drink"
        }
    ],
    "sg:menulink":"http://www.allmenus.com/ca/san-fernando-valley/283692-big-slice-pizza/menu/",
    "sg:phone":"+1 818 784 2602",
    "sg:postcode":"91403",
    "sg:province":"CA",
    "sg:tags":[
        "american",
        "pizza"
    ],
    "wof:name":"Big Slice Pizza",
    "wof:placetype":"venue"
},
  "geometry": {"coordinates":[-118.463081,34.152913],"type":"Point"}
}