{
  "type": "Feature",
  "properties": {
    "addr:full":"150 S Market St Inglewood CA 90301",
    "addr:housenumber":"150",
    "addr:postcode":"90301",
    "addr:street":"S Market St",
    "iso:country":"US",
    "sg:address":"150 S Market St",
    "sg:city":"Inglewood",
    "sg:classifiers":[
        {
            "category":"Shopping",
            "subcategory":"Clothing, Apparel, & Fashions",
            "type":"Retail Goods"
        }
    ],
    "sg:phone":"+1 310 677 5557",
    "sg:postcode":"90301",
    "sg:province":"CA",
    "sg:tags":[
        "hat"
    ],
    "wof:name":"World Hats & Boots Mart",
    "wof:placetype":"venue"
},
  "geometry": {"coordinates":[-118.351805,33.962731],"type":"Point"}
}