{
  "type": "Feature",
  "properties": {
    "iso:country":"US",
    "sg:address":"1504 N Pearl Ave",
    "sg:city":"Compton",
    "sg:classifiers":[
        {
            "category":"Place Of Worship",
            "type":"Public Place"
        }
    ],
    "sg:phone":"+1 310 635 8659",
    "sg:postcode":"90221",
    "sg:province":"CA",
    "sg:tags":[
        "church"
    ],
    "wof:name":"Compton Ave. Church Of Christ",
    "wof:placetype":"venue"
},
  "geometry": {"coordinates":[-118.214685,33.905794],"type":"Point"}
}