{
  "type": "Feature",
  "properties": {
    "addr:full":"1611 Median Ave Central Valley CA 96019",
    "addr:housenumber":"1611",
    "addr:postcode":"96019",
    "addr:street":"Median Ave",
    "iso:country":"US",
    "sg:address":"1611 Median Ave",
    "sg:city":"Central Valley",
    "sg:classifiers":[
        {
            "category":"Personal",
            "subcategory":"Beauty Salon",
            "type":"Services"
        }
    ],
    "sg:phone":"+1 530 275 3910",
    "sg:postcode":"96019",
    "sg:province":"CA",
    "wof:name":"Vel's Beauty Salon",
    "wof:placetype":"venue"
},
  "geometry": {"coordinates":[-122.363522,40.680971],"type":"Point"}
}