{
  "type": "Feature",
  "properties": {
    "iso:country":"US",
    "sg:address":"925 L St",
    "sg:city":"Sacramento",
    "sg:classifiers":[
        {
            "category":"Professional",
            "subcategory":"Management & Consulting",
            "type":"Services"
        }
    ],
    "sg:phone":"+1 916 441 4166",
    "sg:postcode":"95814",
    "sg:province":"CA",
    "sg:tags":[
        "lobbyist"
    ],
    "wof:name":"Desmond & Desmond",
    "wof:placetype":"venue"
},
  "geometry": {"coordinates":[-121.494652,38.578265],"type":"Point"}
}