{
  "type": "Feature",
  "properties": {
    "iso:country":"US",
    "sg:address":"30270 Mayacamas Dr",
    "sg:city":"Murrieta",
    "sg:classifiers":[
        {
            "category":"Professional",
            "subcategory":"Business Services",
            "type":"Services"
        }
    ],
    "sg:phone":"+1 951 461 7621",
    "sg:postcode":"92563",
    "sg:province":"CA",
    "sg:tags":[
        "drafting"
    ],
    "wof:name":"Schematics Unlimited",
    "wof:placetype":"venue"
},
  "geometry": {"coordinates":[-117.134462,33.543461],"type":"Point"}
}