{
  "type": "Feature",
  "properties": {
    "addr:full":"21d Peninsula Ctr Palos Verdes Peninsula CA 90274",
    "addr:housenumber":"21d",
    "addr:postcode":"90274",
    "addr:street":"Peninsula Ctr",
    "iso:country":"US",
    "sg:address":"21d Peninsula Ctr",
    "sg:city":"Palos Verdes Peninsula",
    "sg:classifiers":[
        {
            "category":"Ice Cream",
            "type":"Food & Drink"
        }
    ],
    "sg:menulink":"http://www.allmenus.com/ca/palos-verdes/242397-baskin-robbins/menu/",
    "sg:phone":"+1 310 544 5044",
    "sg:postcode":"90274",
    "sg:province":"CA",
    "sg:tags":[
        "american"
    ],
    "wof:name":"Baskin-Robbins",
    "wof:placetype":"venue"
},
  "geometry": {"coordinates":[-118.376897,33.775272],"type":"Point"}
}