{
  "type": "Feature",
  "properties": {
    "iso:country":"US",
    "sg:address":"3758 Lake Rd",
    "sg:city":"Merced",
    "sg:phone":"+1 209 723 0686",
    "sg:postcode":"95340",
    "sg:province":"CA",
    "sg:tags":[
        "be",
        "farm",
        "nut",
        "tree",
        "cash",
        "grove",
        "grain"
    ],
    "wof:name":"Hunt Farms",
    "wof:placetype":"venue"
},
  "geometry": {"coordinates":[-120.432744,37.337066],"type":"Point"}
}