{
  "type": "Feature",
  "properties": {
    "iso:country":"US",
    "sg:address":"2822 S Vermont Ave",
    "sg:city":"Los Angeles",
    "sg:classifiers":[
        {
            "category":"Social Services",
            "type":"Services"
        }
    ],
    "sg:phone":"+1 323 735 4301",
    "sg:postcode":"90007",
    "sg:province":"CA",
    "sg:tags":[
        "pregnancy",
        "counseling",
        "information"
    ],
    "wof:name":"El Sol Products",
    "wof:placetype":"venue"
},
  "geometry": {"coordinates":[-118.291464,34.029554],"type":"Point"}
}