{
  "type": "Feature",
  "properties": {
    "iso:country":"US",
    "sg:address":"1 Airport Dr Ste 15",
    "sg:city":"Oakland",
    "sg:classifiers":[
        {
            "category":"Parking",
            "type":"Transportation"
        },
        {
            "category":"Airline",
            "type":"Transportation"
        }
    ],
    "sg:phone":"+1 510 633 2571",
    "sg:postcode":"94621",
    "sg:province":"CA",
    "sg:tags":[
        "airport"
    ],
    "wof:name":"Five Star Parking",
    "wof:placetype":"venue"
},
  "geometry": {"coordinates":[-122.195999,37.7425],"type":"Point"}
}