{
  "type": "Feature",
  "properties": {
    "iso:country":"US",
    "sg:address":"1590 Stockbridge Ave",
    "sg:city":"Redwood City",
    "sg:classifiers":[
        {
            "category":"Wholesale",
            "subcategory":"Computers",
            "type":"Manufacturing & Wholesale Goods"
        }
    ],
    "sg:phone":"+1 650 363 9111",
    "sg:postcode":"94061",
    "sg:province":"CA",
    "wof:name":"Hyperdigital Research Inc",
    "wof:placetype":"venue"
},
  "geometry": {"coordinates":[-122.219012,37.45162],"type":"Point"}
}