{
  "type": "Feature",
  "properties": {
    "addr:full":"3870 Murphy Canyon Rd San Diego CA 92123",
    "addr:housenumber":"3870",
    "addr:postcode":"92123",
    "addr:street":"Murphy Canyon Rd",
    "iso:country":"US",
    "sg:address":"3870 Murphy Canyon Rd",
    "sg:city":"San Diego",
    "sg:classifiers":[
        {
            "category":"Real Estate",
            "subcategory":"Real Estate Agent",
            "type":"Services"
        }
    ],
    "sg:phone":"+1 858 503 7400",
    "sg:postcode":"92123",
    "sg:province":"CA",
    "wof:name":"Jannie Enterprises",
    "wof:placetype":"venue"
},
  "geometry": {"coordinates":[-117.11612,32.81266],"type":"Point"}
}