{
  "type": "Feature",
  "properties": {
    "iso:country":"US",
    "sg:address":"4323 Clayton Rd",
    "sg:city":"Concord",
    "sg:classifiers":[
        {
            "category":"Food & Beverages",
            "subcategory":"Groceries & Convenience Stores",
            "type":"Retail Goods"
        }
    ],
    "sg:phone":"+1 925 827 3333",
    "sg:postcode":"94521",
    "sg:province":"CA",
    "wof:name":"American",
    "wof:placetype":"venue"
},
  "geometry": {"coordinates":[-121.991157,37.964262],"type":"Point"}
}