{
  "type": "Feature",
  "properties": {
    "iso:country":"US",
    "sg:address":"3330 Vincent Rd",
    "sg:city":"Pleasant Hill",
    "sg:classifiers":[
        {
            "category":"Building & Trades",
            "subcategory":"Construction",
            "type":"Services"
        }
    ],
    "sg:phone":"+1 925 979 9287",
    "sg:postcode":"94523",
    "sg:province":"CA",
    "sg:tags":[
        "contractor"
    ],
    "wof:name":"Chaffey Construction",
    "wof:placetype":"venue"
},
  "geometry": {"coordinates":[-122.05401999999999,37.94048],"type":"Point"}
}