{
  "type": "Feature",
  "properties": {
    "addr:full":"29255 Las Terreno Ln Valencia CA 91354",
    "addr:housenumber":"29255",
    "addr:postcode":"91354",
    "addr:street":"Las Terreno Ln",
    "iso:country":"US",
    "sg:address":"29255 Las Terreno Ln",
    "sg:city":"Valencia",
    "sg:classifiers":[
        {
            "category":"Building & Trades",
            "subcategory":"Construction",
            "type":"Services"
        }
    ],
    "sg:phone":"+1 661 257 8416",
    "sg:postcode":"91354",
    "sg:province":"CA",
    "sg:tags":[
        "contractor"
    ],
    "wof:name":"Automation By Design",
    "wof:placetype":"venue"
},
  "geometry": {"coordinates":[-118.5642,34.469974],"type":"Point"}
}