{
  "type": "Feature",
  "properties": {
    "addr:full":"234 N Brand Blvd Glendale CA 91203",
    "addr:housenumber":"234",
    "addr:postcode":"91203",
    "addr:street":"N Brand Blvd",
    "iso:country":"US",
    "sg:address":"234 N Brand Blvd",
    "sg:city":"Glendale",
    "sg:classifiers":[
        {
            "category":"Communications",
            "subcategory":"Newspaper",
            "type":"Services"
        }
    ],
    "sg:phone":"+1 818 551 0625",
    "sg:postcode":"91203",
    "sg:province":"CA",
    "sg:tags":[
        "print",
        "magazine",
        "medium"
    ],
    "wof:name":"Brand Newstand",
    "wof:placetype":"venue"
},
  "geometry": {"coordinates":[-118.254997,34.149502],"type":"Point"}
}