{
  "type": "Feature",
  "properties": {
    "iso:country":"US",
    "sg:address":"1430 Holly Dr",
    "sg:city":"Lodi",
    "sg:classifiers":[
        {
            "category":"Professional",
            "subcategory":"Business Services",
            "type":"Services"
        }
    ],
    "sg:phone":"+1 209 369 6670",
    "sg:postcode":"95242",
    "sg:province":"CA",
    "sg:tags":[
        "good"
    ],
    "wof:name":"Taylor Bing Packaging",
    "wof:placetype":"venue"
},
  "geometry": {"coordinates":[-121.29128300000001,38.142298],"type":"Point"}
}