{
  "type": "Feature",
  "properties": {
    "iso:country":"US",
    "sg:address":"8611 Lindley Ave",
    "sg:city":"Northridge",
    "sg:classifiers":[
        {
            "category":"Food & Beverages",
            "subcategory":"Dairy",
            "type":"Retail Goods"
        }
    ],
    "sg:phone":"+1 818 893 5782",
    "sg:postcode":"91325",
    "sg:province":"CA",
    "sg:tags":[
        "product"
    ],
    "wof:name":"M Sr Drive In Dairy",
    "wof:placetype":"venue"
},
  "geometry": {"coordinates":[-118.527421,34.226975],"type":"Point"}
}