{
  "type": "Feature",
  "properties": {
    "addr:full":"2335 Roll Dr San Diego CA 92154",
    "addr:housenumber":"2335",
    "addr:postcode":"92154",
    "addr:street":"Roll Dr",
    "iso:country":"US",
    "sg:address":"2335 Roll Dr",
    "sg:city":"San Diego",
    "sg:classifiers":[
        {
            "category":"Restaurant",
            "type":"Food & Drink"
        }
    ],
    "sg:phone":"+1 619 661 1826",
    "sg:postcode":"92154",
    "sg:province":"CA",
    "sg:tags":[
        "cafe"
    ],
    "wof:name":"Cafe Vallarta",
    "wof:placetype":"venue"
},
  "geometry": {"coordinates":[-116.937354,32.553535],"type":"Point"}
}