{
  "type": "Feature",
  "properties": {
    "addr:full":"2216 Dunlop St San Diego CA 92111",
    "addr:housenumber":"2216",
    "addr:postcode":"92111",
    "addr:street":"Dunlop St",
    "iso:country":"US",
    "sg:address":"2216 Dunlop St",
    "sg:city":"San Diego",
    "sg:classifiers":[
        {
            "category":"Retail",
            "subcategory":"Car Wash",
            "type":"Services"
        }
    ],
    "sg:phone":"+1 619 283 5771",
    "sg:postcode":"92111",
    "sg:province":"CA",
    "sg:tags":[
        "automobile",
        "detail",
        "clean"
    ],
    "wof:name":"Esgar Auto Detail",
    "wof:placetype":"venue"
},
  "geometry": {"coordinates":[-117.167267,32.785688],"type":"Point"}
}