{
  "type": "Feature",
  "properties": {
    "addr:full":"10864 State Rte 59 El Nido CA 95317",
    "addr:housenumber":"10864",
    "addr:postcode":"95317",
    "addr:street":"State Rte 59",
    "iso:country":"US",
    "sg:address":"10864 State Rte 59",
    "sg:city":"El Nido",
    "sg:classifiers":[
        {
            "category":"Farming",
            "subcategory":"Dairy Farm",
            "type":"Manufacturing & Wholesale Goods"
        }
    ],
    "sg:phone":"+1 209 383 0299",
    "sg:postcode":"95317",
    "sg:province":"CA",
    "wof:name":"Cipriano and Son Dairy",
    "wof:placetype":"venue"
},
  "geometry": {"coordinates":[-120.49208900000001,37.129532],"type":"Point"}
}