{
  "type": "Feature",
  "properties": {
    "addr:full":"24 Hour Fitness 1850 Ocean Ave San Francisco CA 94112",
    "addr:housenumber":"1850",
    "addr:postcode":"94112",
    "addr:street":"Ocean Ave",
    "iso:country":"US",
    "sg:address":"24 Hour Fitness 1850 Ocean Ave",
    "sg:city":"San Francisco",
    "sg:classifiers":[
        {
            "category":"Sports & Exercise",
            "subcategory":"Gym",
            "type":"Entertainment"
        }
    ],
    "sg:phone":"+1 415 333 1400",
    "sg:postcode":"94112",
    "sg:province":"CA",
    "sg:tags":[
        "trainer"
    ],
    "sg:website":"www.24hourfitness.com",
    "wof:name":"Jiries Naser, Personal Trainer",
    "wof:placetype":"venue"
},
  "geometry": {"coordinates":[-122.461747,37.72515],"type":"Point"}
}