{
  "type": "Feature",
  "properties": {
    "addr:full":"20021 Roscoe Blvd Canoga Park CA 91306",
    "addr:housenumber":"20021",
    "addr:postcode":"91306",
    "addr:street":"Roscoe Blvd",
    "iso:country":"US",
    "sg:address":"20021 Roscoe Blvd",
    "sg:city":"Canoga Park",
    "sg:classifiers":[
        {
            "category":"Retail",
            "subcategory":"Self-service Laundry",
            "type":"Services"
        }
    ],
    "sg:phone":"+1 818 718 6206",
    "sg:postcode":"91306",
    "sg:province":"CA",
    "wof:name":"Phancomat Inc",
    "wof:placetype":"venue"
},
  "geometry": {"coordinates":[-118.570667,34.220282],"type":"Point"}
}