{
  "type": "Feature",
  "properties": {
    "iso:country":"US",
    "sg:address":"146 Main St",
    "sg:city":"Los Altos",
    "sg:classifiers":[
        {
            "category":"Shopping",
            "subcategory":"Computers & Home Electronics",
            "type":"Retail Goods"
        }
    ],
    "sg:phone":"+1 650 941 4121",
    "sg:postcode":"94022",
    "sg:province":"CA",
    "sg:tags":[
        "software"
    ],
    "wof:name":"Waterwheel Software Inc",
    "wof:placetype":"venue"
},
  "geometry": {"coordinates":[-122.115027,37.379472],"type":"Point"}
}