{
  "type": "Feature",
  "properties": {
    "addr:full":"5121 Brynhurst Ave Los Angeles CA 90043",
    "addr:postcode":"5121;90043",
    "addr:street":"Brynhurst Ave",
    "iso:country":"US",
    "sg:address":"5121 Brynhurst Ave",
    "sg:city":"Los Angeles",
    "sg:classifiers":[
        {
            "category":"Banks & Credit Unions",
            "subcategory":"Investment Brokerage",
            "type":"Services"
        }
    ],
    "sg:phone":"+1 323 294 8904",
    "sg:postcode":"90043",
    "sg:province":"CA",
    "sg:tags":[
        "advisory"
    ],
    "wof:name":"D U B Financial Corporation",
    "wof:placetype":"venue"
},
  "geometry": {"coordinates":[-118.333297,33.994946],"type":"Point"}
}