{
  "type": "Feature",
  "properties": {
    "addr:full":"599 S State Hwy 49 Jackson CA 95642",
    "addr:housenumber":"599",
    "addr:postcode":"95642",
    "addr:street":"S State Hwy 49",
    "iso:country":"US",
    "sg:address":"599 S State Hwy 49",
    "sg:city":"Jackson",
    "sg:classifiers":[
        {
            "category":"Retail",
            "subcategory":"Laundry & Dry Cleaning",
            "type":"Services"
        }
    ],
    "sg:phone":"+1 209 223 3089",
    "sg:postcode":"95642",
    "sg:province":"CA",
    "wof:name":"Mother Lode Laundry",
    "wof:placetype":"venue"
},
  "geometry": {"coordinates":[-120.770143,38.34471],"type":"Point"}
}