{
  "type": "Feature",
  "properties": {
    "iso:country":"US",
    "sg:address":"170 High Street",
    "sg:city":"Santa Cruz",
    "sg:classifiers":[
        {
            "category":"Retail",
            "subcategory":"Event Space",
            "type":"Services"
        }
    ],
    "sg:phone":"+1 831 469 3560",
    "sg:postcode":"95060",
    "sg:province":"CA",
    "sg:tags":[
        "venue"
    ],
    "sg:website":"www.holycrosssantacruz.com",
    "wof:name":"Holy Cross Parish Hall",
    "wof:placetype":"venue"
},
  "geometry": {"coordinates":[-122.03080799999999,36.978486],"type":"Point"}
}