{
  "type": "Feature",
  "properties": {
    "addr:full":"16700 Madrone Ave Los Gatos CA 95030",
    "addr:housenumber":"16700",
    "addr:postcode":"95030",
    "addr:street":"Madrone Ave",
    "iso:country":"US",
    "sg:address":"16700 Madrone Ave",
    "sg:city":"Los Gatos",
    "sg:classifiers":[
        {
            "category":"Banks & Credit Unions",
            "subcategory":"Financial Services",
            "type":"Services"
        }
    ],
    "sg:phone":"+1 408 395 2928",
    "sg:postcode":"95030",
    "sg:province":"CA",
    "sg:tags":[
        "trust",
        "investment",
        "real estate"
    ],
    "wof:name":"Staffield Interest",
    "wof:placetype":"venue"
},
  "geometry": {"coordinates":[-121.99606300000001,37.224937],"type":"Point"}
}