{
  "type": "Feature",
  "properties": {
    "iso:country":"US",
    "sg:address":"1670 W Barstow Ave",
    "sg:city":"Fresno",
    "sg:classifiers":[
        {
            "category":"Real Estate",
            "subcategory":"Real Estate Agent",
            "type":"Services"
        }
    ],
    "sg:phone":"+1 559 438 6740",
    "sg:postcode":"93711",
    "sg:province":"CA",
    "wof:name":"Secco Realty Realtor",
    "wof:placetype":"venue"
},
  "geometry": {"coordinates":[-119.82361299999999,36.815604],"type":"Point"}
}