{
  "type": "Feature",
  "properties": {
    "iso:country":"US",
    "sg:address":"941 Broadway",
    "sg:city":"El Cajon",
    "sg:classifiers":[
        {
            "category":"Shopping",
            "type":"Retail Goods"
        }
    ],
    "sg:phone":"+1 619 631 6333",
    "sg:postcode":"92021",
    "sg:province":"CA",
    "sg:tags":[
        "telephone",
        "cellular"
    ],
    "wof:name":"Automated Telecom",
    "wof:placetype":"venue"
},
  "geometry": {"coordinates":[-116.949152,32.807622],"type":"Point"}
}