{
  "type": "Feature",
  "properties": {
    "iso:country":"US",
    "sg:address":"717 W El Segundo Boulevard",
    "sg:city":"Gardena",
    "sg:classifiers":[
        {
            "category":"Real Estate",
            "subcategory":"Real Estate Services",
            "type":"Services"
        },
        {
            "category":"Real Estate",
            "subcategory":"Real Estate Operator",
            "type":"Services"
        }
    ],
    "sg:phone":"+1 323 755 7191",
    "sg:postcode":"90247",
    "sg:province":"CA",
    "sg:tags":[
        "vacancy",
        "apartment",
        "rental",
        "finder",
        "listing"
    ],
    "wof:name":"Royal Apartments",
    "wof:placetype":"venue"
},
  "geometry": {"coordinates":[-118.2876,33.91644],"type":"Point"}
}