{
  "type": "Feature",
  "properties": {
    "iso:country":"US",
    "sg:address":"1741 Ivar Ave",
    "sg:city":"Los Angeles",
    "sg:classifiers":[
        {
            "category":"Manufacturing",
            "subcategory":"Retail Goods",
            "type":"Manufacturing & Wholesale Goods"
        }
    ],
    "sg:phone":"+1 323 461 1548",
    "sg:postcode":"90028",
    "sg:province":"CA",
    "sg:tags":[
        "manufacturer"
    ],
    "wof:name":"Factory Direct Fastening",
    "wof:placetype":"venue"
},
  "geometry": {"coordinates":[-118.328247,34.102969],"type":"Point"}
}