{
  "type": "Feature",
  "properties": {
    "iso:country":"US",
    "sg:address":"16060 Horace St",
    "sg:city":"Granada Hills",
    "sg:classifiers":[
        {
            "category":"Recreation",
            "type":"Entertainment"
        }
    ],
    "sg:phone":"+1 818 407 1799",
    "sg:postcode":"91344",
    "sg:province":"CA",
    "sg:tags":[
        "martial",
        "arts",
        "instruction"
    ],
    "sg:website":"www.kfasansoo.com",
    "wof:name":"Academy Of Kung Fu",
    "wof:placetype":"venue"
},
  "geometry": {"coordinates":[-118.482324,34.269858],"type":"Point"}
}