{
  "type": "Feature",
  "properties": {
    "iso:country":"US",
    "sg:address":"473 Tejon Hwy",
    "sg:city":"Arvin",
    "sg:classifiers":[
        {
            "category":"Freight",
            "type":"Transportation"
        }
    ],
    "sg:phone":"+1 661 854 5386",
    "sg:postcode":"93203",
    "sg:province":"CA",
    "sg:tags":[
        "trucking"
    ],
    "wof:name":"M & J Ojeda Trucking Contr",
    "wof:placetype":"venue"
},
  "geometry": {"coordinates":[-118.82426100000001,35.205714],"type":"Point"}
}