{
  "type": "Feature",
  "properties": {
    "iso:country":"US",
    "sg:address":"3825 Ramsdell Ave",
    "sg:city":"La Crescenta",
    "sg:classifiers":[
        {
            "category":"Professional",
            "subcategory":"Business Services",
            "type":"Services"
        }
    ],
    "sg:phone":"+1 818 248 3939",
    "sg:postcode":"91214",
    "sg:province":"CA",
    "sg:tags":[
        "interior",
        "consultant",
        "design",
        "decorator"
    ],
    "wof:name":"Studio Exodus Inc",
    "wof:placetype":"venue"
},
  "geometry": {"coordinates":[-118.244427,34.214501],"type":"Point"}
}