{
  "type": "Feature",
  "properties": {
    "iso:country":"US",
    "sg:address":"3330 S Figeuroa St",
    "sg:city":"Los Angeles",
    "sg:classifiers":[
        {
            "category":"Arts & Performance",
            "subcategory":"Arts Center",
            "type":"Entertainment"
        }
    ],
    "sg:phone":"+1 888 231 8828",
    "sg:postcode":"90007",
    "sg:province":"CA",
    "sg:website":"www.carcallsradio.com",
    "wof:name":"Car Calls Radio show on 97.1 FREE FM",
    "wof:placetype":"venue"
},
  "geometry": {"coordinates":[-118.279503,34.022705],"type":"Point"}
}