{
  "type": "Feature",
  "properties": {
    "addr:full":"9 Paine Cir Irvine CA 92614",
    "addr:housenumber":"9",
    "addr:postcode":"92614",
    "addr:street":"Paine Cir",
    "iso:country":"US",
    "sg:address":"9 Paine Cir",
    "sg:city":"Irvine",
    "sg:classifiers":[
        {
            "category":"Professional",
            "subcategory":"Computer Services",
            "type":"Services"
        }
    ],
    "sg:phone":"+1 949 786 3020",
    "sg:postcode":"92614",
    "sg:province":"CA",
    "sg:tags":[
        "hardware",
        "provider",
        "internet",
        "software"
    ],
    "wof:name":"Logic Domain",
    "wof:placetype":"venue"
},
  "geometry": {"coordinates":[-117.821348,33.673112],"type":"Point"}
}