{
  "type": "Feature",
  "properties": {
    "addr:full":"333 S Auburn St Colfax CA 95713",
    "addr:housenumber":"333",
    "addr:postcode":"95713",
    "addr:street":"S Auburn St",
    "iso:country":"US",
    "sg:address":"333 S Auburn St",
    "sg:city":"Colfax",
    "sg:classifiers":[
        {
            "category":"Professional",
            "subcategory":"Accounting & Tax Preparation",
            "type":"Services"
        }
    ],
    "sg:phone":"+1 530 346 2259",
    "sg:postcode":"95713",
    "sg:province":"CA",
    "sg:tags":[
        "accountant"
    ],
    "wof:name":"Thomas E Nunley CPA",
    "wof:placetype":"venue"
},
  "geometry": {"coordinates":[-120.951086,39.097531],"type":"Point"}
}