{
  "type": "Feature",
  "properties": {
    "addr:full":"2750 41st Ave Suite F Soquel CA 95073",
    "addr:housenumber":"2750",
    "addr:postcode":"95073",
    "addr:street":"41St Ave Suite F",
    "iso:country":"US",
    "sg:address":"2750 41st Ave Suite F",
    "sg:city":"Soquel",
    "sg:classifiers":[
        {
            "category":"Banks & Credit Unions",
            "subcategory":"Bank",
            "type":"Services"
        }
    ],
    "sg:phone":"+1 831 647 1000",
    "sg:postcode":"95073",
    "sg:province":"CA",
    "sg:website":"www.montereycu.com",
    "wof:name":"Monterey Credit Union",
    "wof:placetype":"venue"
},
  "geometry": {"coordinates":[-121.96486899999999,36.986217],"type":"Point"}
}