{
  "type": "Feature",
  "properties": {
    "iso:country":"US",
    "sg:address":"16921 Saticoy St",
    "sg:city":"Van Nuys",
    "sg:classifiers":[
        {
            "category":"Shopping",
            "subcategory":"Gifts & Souvenirs",
            "type":"Retail Goods"
        }
    ],
    "sg:phone":"+1 818 342 6494",
    "sg:postcode":"91406",
    "sg:province":"CA",
    "sg:tags":[
        "party",
        "supply"
    ],
    "wof:name":"Modern Party Rental",
    "wof:placetype":"venue"
},
  "geometry": {"coordinates":[-118.502873,34.208344],"type":"Point"}
}