{
  "type": "Feature",
  "properties": {
    "addr:full":"150 Shoreline Hwy Mill Valley CA 94965",
    "addr:housenumber":"150",
    "addr:postcode":"94965",
    "addr:street":"Shoreline Hwy",
    "iso:country":"US",
    "sg:address":"150 Shoreline Hwy",
    "sg:city":"Mill Valley",
    "sg:classifiers":[
        {
            "category":"Professional",
            "subcategory":"Art Services",
            "type":"Services"
        }
    ],
    "sg:phone":"+1 415 332 9318",
    "sg:postcode":"94965",
    "sg:province":"CA",
    "sg:tags":[
        "graphic",
        "designer"
    ],
    "wof:name":"Burg Design",
    "wof:placetype":"venue"
},
  "geometry": {"coordinates":[-122.522606,37.879536],"type":"Point"}
}