{
  "type": "Feature",
  "properties": {
    "iso:country":"US",
    "sg:address":"9834 Niagara Ave",
    "sg:city":"Fontana",
    "sg:classifiers":[
        {
            "category":"Freight",
            "type":"Transportation"
        }
    ],
    "sg:phone":"+1 909 349 1951",
    "sg:postcode":"92335",
    "sg:province":"CA",
    "wof:name":"Capuchino Transport",
    "wof:placetype":"venue"
},
  "geometry": {"coordinates":[-117.459045,34.074518],"type":"Point"}
}