{
  "type": "Feature",
  "properties": {
    "iso:country":"US",
    "sg:address":"16640 Pine Dr",
    "sg:city":"Fort Bragg",
    "sg:classifiers":[
        {
            "category":"Building & Trades",
            "subcategory":"Construction",
            "type":"Services"
        }
    ],
    "sg:phone":"+1 707 962 0194",
    "sg:postcode":"95437",
    "sg:province":"CA",
    "sg:tags":[
        "general",
        "contractor"
    ],
    "wof:name":"Heyden Loudon Construction Inc",
    "wof:placetype":"venue"
},
  "geometry": {"coordinates":[-123.81128200000001,39.385197],"type":"Point"}
}