{
  "type": "Feature",
  "properties": {
    "iso:country":"US",
    "sg:address":"1491 Yosemite Ave",
    "sg:city":"Manteca",
    "sg:classifiers":[
        {
            "category":"Banks & Credit Unions",
            "subcategory":"Bank",
            "type":"Services"
        }
    ],
    "sg:phone":"+1 209 239 1285",
    "sg:postcode":"95337",
    "sg:province":"CA",
    "sg:tags":[
        "financing"
    ],
    "wof:name":"American General Finance Inc",
    "wof:placetype":"venue"
},
  "geometry": {"coordinates":[-121.240135,37.79744],"type":"Point"}
}