{
  "type": "Feature",
  "properties": {
    "iso:country":"US",
    "sg:address":"1749 State Hwy 45",
    "sg:city":"Grimes",
    "sg:classifiers":[
        {
            "category":"Farming",
            "subcategory":"Farm & Veterinary Services",
            "type":"Manufacturing & Wholesale Goods"
        }
    ],
    "sg:phone":"+1 530 437 2225",
    "sg:postcode":"95950",
    "sg:province":"CA",
    "sg:tags":[
        "aerial",
        "applicator"
    ],
    "wof:name":"Thayer Agriculture Aviation",
    "wof:placetype":"venue"
},
  "geometry": {"coordinates":[-121.920592,39.087807],"type":"Point"}
}