{
  "type": "Feature",
  "properties": {
    "iso:country":"US",
    "sg:address":"1601 N Long Beach Blvd",
    "sg:city":"Long Beach Twp",
    "sg:classifiers":[
        {
            "category":"Real Estate",
            "subcategory":"Real Estate Agent",
            "type":"Services"
        }
    ],
    "sg:phone":"+1 609 492 0990",
    "sg:postcode":"90813",
    "sg:province":"CA",
    "sg:website":"www.lbirealestatenews.com",
    "wof:name":"Coldwell Banker",
    "wof:placetype":"venue"
},
  "geometry": {"coordinates":[-118.189374,33.78805],"type":"Point"}
}