{
  "type": "Feature",
  "properties": {
    "addr:full":"8215 Auburn Blvd Citrus Heights CA 95610",
    "addr:housenumber":"8215",
    "addr:postcode":"95610",
    "addr:street":"Auburn Blvd",
    "iso:country":"US",
    "sg:address":"8215 Auburn Blvd",
    "sg:city":"Citrus Heights",
    "sg:classifiers":[
        {
            "category":"Retail",
            "subcategory":"Auto Repair",
            "type":"Services"
        }
    ],
    "sg:phone":"+1 916 725 2272",
    "sg:postcode":"95610",
    "sg:province":"CA",
    "sg:tags":[
        "repairing",
        "automobile"
    ],
    "wof:name":"Pat Henry's Auto Repair",
    "wof:placetype":"venue"
},
  "geometry": {"coordinates":[-121.290498,38.714516],"type":"Point"}
}