{
  "type": "Feature",
  "properties": {
    "iso:country":"US",
    "sg:address":"16626 S Main Street",
    "sg:city":"Gardena",
    "sg:classifiers":[
        {
            "category":"Retail",
            "subcategory":"Auto Repair",
            "type":"Services"
        }
    ],
    "sg:phone":"+1 310 323 9181",
    "sg:postcode":"90248",
    "sg:province":"CA",
    "wof:name":"Mels Auto Repair",
    "wof:placetype":"venue"
},
  "geometry": {"coordinates":[-118.275848,33.879765],"type":"Point"}
}