{
  "type": "Feature",
  "properties": {
    "iso:country":"US",
    "sg:address":"142 Ranch Dr",
    "sg:city":"Milpitas",
    "sg:classifiers":[
        {
            "category":"Health Services",
            "subcategory":"Dentist",
            "type":"Services"
        }
    ],
    "sg:phone":"+1 408 262 4434",
    "sg:postcode":"95035",
    "sg:province":"CA",
    "wof:name":"Rose Steven",
    "wof:placetype":"venue"
},
  "geometry": {"coordinates":[-121.920649,37.427636],"type":"Point"}
}