{
  "type": "Feature",
  "properties": {
    "iso:country":"US",
    "sg:address":"23 E Laurel Dr",
    "sg:city":"Salinas",
    "sg:classifiers":[
        {
            "category":"Retail",
            "subcategory":"Self-service Laundry",
            "type":"Services"
        }
    ],
    "sg:phone":"+1 831 449 1020",
    "sg:postcode":"93906",
    "sg:province":"CA",
    "sg:tags":[
        "laundries-self"
    ],
    "wof:name":"La Fiesta Laundry",
    "wof:placetype":"venue"
},
  "geometry": {"coordinates":[-121.65166000000001,36.699312],"type":"Point"}
}