{
  "type": "Feature",
  "properties": {
    "iso:country":"US",
    "sg:address":"42240 Green Way",
    "sg:city":"Palm Desert",
    "sg:classifiers":[
        {
            "category":"Home & Garden",
            "subcategory":"Home Furnishings",
            "type":"Retail Goods"
        }
    ],
    "sg:phone":"+1 760 341 7725",
    "sg:postcode":"92211",
    "sg:province":"CA",
    "sg:tags":[
        "mirror"
    ],
    "wof:name":"Midwest Glass & Aluminum",
    "wof:placetype":"venue"
},
  "geometry": {"coordinates":[-116.355379,33.741802],"type":"Point"}
}