{
  "type": "Feature",
  "properties": {
    "iso:country":"US",
    "sg:address":"210 S E St",
    "sg:city":"Madera",
    "sg:classifiers":[
        {
            "category":"Personal",
            "subcategory":"Beauty Salon",
            "type":"Services"
        }
    ],
    "sg:phone":"+1 559 675 0539",
    "sg:postcode":"93638",
    "sg:province":"CA",
    "wof:name":"Nancy's Beauty Salon",
    "wof:placetype":"venue"
},
  "geometry": {"coordinates":[-120.05831999999999,36.960824],"type":"Point"}
}