{
  "type": "Feature",
  "properties": {
    "addr:full":"1251 W Century Blvd Los Angeles CA 90044",
    "addr:housenumber":"1251",
    "addr:postcode":"90044",
    "addr:street":"W Century Blvd",
    "iso:country":"US",
    "sg:address":"1251 W Century Blvd",
    "sg:city":"Los Angeles",
    "sg:classifiers":[
        {
            "category":"Home & Garden",
            "subcategory":"Furniture",
            "type":"Retail Goods"
        }
    ],
    "sg:phone":"+1 323 756 7965",
    "sg:postcode":"90044",
    "sg:province":"CA",
    "wof:name":"Amelia Furniture",
    "wof:placetype":"venue"
},
  "geometry": {"coordinates":[-118.296065,33.945569],"type":"Point"}
}