{
  "type": "Feature",
  "properties": {
    "addr:full":"2717 Fletcher Dr Los Angeles CA 90039",
    "addr:housenumber":"2717",
    "addr:postcode":"90039",
    "addr:street":"Fletcher Dr",
    "iso:country":"US",
    "sg:address":"2717 Fletcher Dr",
    "sg:city":"Los Angeles",
    "sg:classifiers":[
        {
            "category":"Building & Trades",
            "subcategory":"Construction",
            "type":"Services"
        }
    ],
    "sg:phone":"+1 323 663 3291",
    "sg:postcode":"90039",
    "sg:province":"CA",
    "sg:tags":[
        "tile",
        "dealer"
    ],
    "wof:name":"Mortarless Building Supply Co",
    "wof:placetype":"venue"
},
  "geometry": {"coordinates":[-118.250857,34.110848],"type":"Point"}
}