{
  "type": "Feature",
  "properties": {
    "iso:country":"US",
    "sg:address":"605 Hackberry Ave",
    "sg:city":"Modesto",
    "sg:classifiers":[
        {
            "category":"Communications",
            "subcategory":"Film & Video Production",
            "type":"Services"
        }
    ],
    "sg:phone":"+1 209 544 8755",
    "sg:postcode":"95354",
    "sg:province":"CA",
    "sg:tags":[
        "taping"
    ],
    "wof:name":"Bellissimo Wedding Videos",
    "wof:placetype":"venue"
},
  "geometry": {"coordinates":[-121.00187,37.653801],"type":"Point"}
}