{
  "type": "Feature",
  "properties": {
    "iso:country":"US",
    "sg:address":"11868 Rosecrans Ave",
    "sg:city":"Norwalk",
    "sg:classifiers":[
        {
            "category":"Health Services",
            "subcategory":"Doctor",
            "type":"Services"
        }
    ],
    "sg:phone":"+1 562 864 1727",
    "sg:postcode":"90650",
    "sg:province":"CA",
    "wof:name":"Chavis Tony Johnston MD",
    "wof:placetype":"venue"
},
  "geometry": {"coordinates":[-118.020999,33.902002],"type":"Point"}
}