{
  "type": "Feature",
  "properties": {
    "addr:full":"11024 Lower Azusa Rd El Monte CA 91731",
    "addr:housenumber":"11024",
    "addr:postcode":"91731",
    "addr:street":"Lower Azusa Rd",
    "iso:country":"US",
    "sg:address":"11024 Lower Azusa Rd",
    "sg:city":"El Monte",
    "sg:classifiers":[
        {
            "category":"Home & Garden",
            "subcategory":"Furniture",
            "type":"Retail Goods"
        }
    ],
    "sg:phone":"+1 626 443 5589",
    "sg:postcode":"91731",
    "sg:province":"CA",
    "sg:tags":[
        "household"
    ],
    "wof:name":"Hetty Enterprise",
    "wof:placetype":"venue"
},
  "geometry": {"coordinates":[-118.024725,34.091843],"type":"Point"}
}