{
  "type": "Feature",
  "properties": {
    "addr:full":"27972 Forbes Road Laguna Niguel CA 92677",
    "addr:housenumber":"27972",
    "addr:postcode":"92677",
    "addr:street":"Forbes Road",
    "iso:country":"US",
    "sg:address":"27972 Forbes Road",
    "sg:city":"Laguna Niguel",
    "sg:classifiers":[
        {
            "category":"Retail",
            "subcategory":"Auto Repair",
            "type":"Services"
        }
    ],
    "sg:phone":"+1 949 495 4900",
    "sg:postcode":"92677",
    "sg:province":"CA",
    "sg:website":"www.crownvalleytrans.com",
    "wof:name":"Crown Valley Transmission",
    "wof:placetype":"venue"
},
  "geometry": {"coordinates":[-117.675495,33.555546],"type":"Point"}
}