{
  "type": "Feature",
  "properties": {
    "iso:country":"US",
    "sg:address":"8 Brisa Dr",
    "sg:city":"Mission Viejo",
    "sg:classifiers":[
        {
            "category":"Professional",
            "type":"Services"
        }
    ],
    "sg:phone":"+1 949 581 6565",
    "sg:postcode":"92692",
    "sg:province":"CA",
    "wof:name":"Inforam Inc",
    "wof:placetype":"venue"
},
  "geometry": {"coordinates":[-117.62983199999999,33.665953],"type":"Point"}
}