{
  "type": "Feature",
  "properties": {
    "iso:country":"US",
    "sg:address":"16232 Chadwick Ct",
    "sg:city":"Chino Hills",
    "sg:classifiers":[
        {
            "category":"Building & Trades",
            "subcategory":"Construction",
            "type":"Services"
        }
    ],
    "sg:phone":"+1 909 393 9131",
    "sg:postcode":"91709",
    "sg:province":"CA",
    "sg:tags":[
        "contractor"
    ],
    "wof:name":"T & K Pools",
    "wof:placetype":"venue"
},
  "geometry": {"coordinates":[-117.68225099999999,33.959669],"type":"Point"}
}