{
  "type": "Feature",
  "properties": {
    "addr:full":"597 Creek Dr Watsonville CA 95076",
    "addr:housenumber":"597",
    "addr:postcode":"95076",
    "addr:street":"Creek Dr",
    "iso:country":"US",
    "sg:address":"597 Creek Dr",
    "sg:city":"Watsonville",
    "sg:classifiers":[
        {
            "category":"Farming",
            "subcategory":"Berry Farm",
            "type":"Manufacturing & Wholesale Goods"
        }
    ],
    "sg:phone":"+1 831 722 2166",
    "sg:postcode":"95076",
    "sg:province":"CA",
    "sg:tags":[
        "crop"
    ],
    "wof:name":"Murakami Farms",
    "wof:placetype":"venue"
},
  "geometry": {"coordinates":[-121.742772,36.920874],"type":"Point"}
}