{
  "type": "Feature",
  "properties": {
    "addr:full":"16119 Prairie Ave Lawndale CA 90260",
    "addr:housenumber":"16119",
    "addr:postcode":"ca 90260",
    "addr:street":"Prairie Ave",
    "iso:country":"US",
    "sg:address":"16119 Prairie Ave",
    "sg:city":"Lawndale",
    "sg:classifiers":[
        {
            "category":"Social Services",
            "type":"Services"
        },
        {
            "category":"Social Services",
            "subcategory":"Adult Care",
            "type":"Services"
        }
    ],
    "sg:phone":"+1 310 542 4825",
    "sg:postcode":"90260",
    "sg:province":"CA",
    "sg:tags":[
        "residential",
        "rehabilitation",
        "welfare"
    ],
    "wof:name":"Transitional Living Centers",
    "wof:placetype":"venue"
},
  "geometry": {"coordinates":[-118.34382600000001,33.884353],"type":"Point"}
}