{
  "type": "Feature",
  "properties": {
    "addr:full":"1833 Evans Rd Ceres CA 95307",
    "addr:housenumber":"1833",
    "addr:postcode":"95307",
    "addr:street":"Evans Rd",
    "iso:country":"US",
    "sg:address":"1833 Evans Rd",
    "sg:city":"Ceres",
    "sg:classifiers":[
        {
            "category":"Farming",
            "subcategory":"Farm & Veterinary Services",
            "type":"Manufacturing & Wholesale Goods"
        }
    ],
    "sg:phone":"+1 530 473 3377",
    "sg:postcode":"95307",
    "sg:province":"CA",
    "sg:tags":[
        "gin",
        "cotton"
    ],
    "wof:name":"Sacramento Valley Ginning Co",
    "wof:placetype":"venue"
},
  "geometry": {"coordinates":[-120.962422,37.602702],"type":"Point"}
}