{
  "type": "Feature",
  "properties": {
    "addr:full":"3819 W Slauson Ave Ste E Los Angeles CA 90043",
    "addr:housenumber":"3819",
    "addr:postcode":"90043",
    "addr:street":"W Slauson Ave Ste E",
    "iso:country":"US",
    "sg:address":"3819 W Slauson Ave Ste E",
    "sg:city":"Los Angeles",
    "sg:classifiers":[
        {
            "category":"Personal",
            "subcategory":"Nail Salon",
            "type":"Services"
        }
    ],
    "sg:phone":"+1 323 295 4740",
    "sg:postcode":"90043",
    "sg:province":"CA",
    "wof:name":"Katie's Nails",
    "wof:placetype":"venue"
},
  "geometry": {"coordinates":[-118.341003,33.988998],"type":"Point"}
}