{
  "type": "Feature",
  "properties": {
    "iso:country":"US",
    "sg:address":"2023 Baker St",
    "sg:city":"Bakersfield",
    "sg:classifiers":[
        {
            "category":"Food & Beverages",
            "subcategory":"Liquor & Beverages",
            "type":"Retail Goods"
        }
    ],
    "sg:phone":"+1 661 323 4684",
    "sg:postcode":"93305",
    "sg:province":"CA",
    "wof:name":"Fiesta Liquors",
    "wof:placetype":"venue"
},
  "geometry": {"coordinates":[-118.988095,35.390039],"type":"Point"}
}