{
  "type": "Feature",
  "properties": {
    "iso:country":"US",
    "sg:address":"708 Litchfield Ln",
    "sg:city":"Santa Barbara",
    "sg:classifiers":[
        {
            "category":"Professional",
            "subcategory":"Computer Services",
            "type":"Services"
        }
    ],
    "sg:phone":"+1 805 886 4383",
    "sg:postcode":"93109",
    "sg:province":"CA",
    "sg:tags":[
        "consultant"
    ],
    "wof:name":"Greener Grass Group",
    "wof:placetype":"venue"
},
  "geometry": {"coordinates":[-119.726482,34.406473],"type":"Point"}
}