{
  "type": "Feature",
  "properties": {
    "iso:country":"US",
    "sg:address":"7327 Silverado Trl",
    "sg:city":"Napa",
    "sg:classifiers":[
        {
            "category":"Farming",
            "subcategory":"Vineyard",
            "type":"Manufacturing & Wholesale Goods"
        }
    ],
    "sg:phone":"+1 707 944 9135",
    "sg:postcode":"94558",
    "sg:province":"CA",
    "wof:name":"Vyborny Vineyard Management Co",
    "wof:placetype":"venue"
},
  "geometry": {"coordinates":[-122.35207800000001,38.440934],"type":"Point"}
}