{
  "type": "Feature",
  "properties": {
    "iso:country":"US",
    "sg:address":"1800 N. New Hampshire Ave Suite 214",
    "sg:city":"Los Angeles",
    "sg:classifiers":[
        {
            "category":"Professional",
            "subcategory":"Computer Services",
            "type":"Services"
        }
    ],
    "sg:phone":"+1 323 286 3777",
    "sg:postcode":"90027",
    "sg:province":"CA",
    "sg:website":"http://www.silvatarmedia.com",
    "wof:name":"Silvatar Media",
    "wof:placetype":"venue"
},
  "geometry": {"coordinates":[-118.293239,34.103572],"type":"Point"}
}