{
  "type": "Feature",
  "properties": {
    "addr:full":"2515 Noriega St San Francisco CA 94122",
    "addr:housenumber":"2515",
    "addr:postcode":"94122",
    "addr:street":"Noriega St",
    "iso:country":"US",
    "sg:address":"2515 Noriega St",
    "sg:city":"San Francisco",
    "sg:classifiers":[
        {
            "category":"Restaurant",
            "type":"Food & Drink"
        }
    ],
    "sg:menulink":"http://www.allmenus.com/ca/san-francisco/44554-three-star-restaurant/menu/",
    "sg:phone":"+1 415 566 7177",
    "sg:postcode":"94122",
    "sg:province":"CA",
    "sg:tags":[
        "asian",
        "chinese"
    ],
    "wof:name":"Three Star Restaurant",
    "wof:placetype":"venue"
},
  "geometry": {"coordinates":[-122.49069799999999,37.753689],"type":"Point"}
}