{
  "type": "Feature",
  "properties": {
    "addr:full":"5782 Tenneyson Dr Agoura Hills CA 91301",
    "addr:housenumber":"5782",
    "addr:postcode":"91301",
    "addr:street":"Tenneyson Dr",
    "iso:country":"US",
    "sg:address":"5782 Tenneyson Dr",
    "sg:city":"Agoura Hills",
    "sg:classifiers":[
        {
            "category":"Wholesale",
            "subcategory":"Non-durable Goods",
            "type":"Manufacturing & Wholesale Goods"
        }
    ],
    "sg:phone":"+1 818 706 9995",
    "sg:postcode":"91301",
    "sg:province":"CA",
    "wof:name":"B Ki International Trading Co",
    "wof:placetype":"venue"
},
  "geometry": {"coordinates":[-118.767724,34.156932],"type":"Point"}
}