{
  "type": "Feature",
  "properties": {
    "iso:country":"US",
    "sg:address":"13903 Amar Rd",
    "sg:city":"La Puente",
    "sg:classifiers":[
        {
            "category":"Professional",
            "type":"Services"
        }
    ],
    "sg:phone":"+1 626 480 7939",
    "sg:postcode":"91746",
    "sg:province":"CA",
    "sg:tags":[
        "establishment"
    ],
    "wof:name":"Kids Land",
    "wof:placetype":"venue"
},
  "geometry": {"coordinates":[-117.972593,34.052398],"type":"Point"}
}