{
  "type": "Feature",
  "properties": {
    "iso:country":"US",
    "sg:address":"3283 de la Cruz Blvd",
    "sg:city":"Santa Clara",
    "sg:classifiers":[
        {
            "category":"Shopping",
            "subcategory":"Florist",
            "type":"Retail Goods"
        }
    ],
    "sg:phone":"+1 408 727 4416",
    "sg:postcode":"95054",
    "sg:province":"CA",
    "sg:website":"www.flowerdivas.com",
    "wof:name":"Futagaki Floral Designs",
    "wof:placetype":"venue"
},
  "geometry": {"coordinates":[-121.942368,37.383719],"type":"Point"}
}