{
  "type": "Feature",
  "properties": {
    "addr:full":"5397 E Olive Ave Fresno CA 93727",
    "addr:housenumber":"5397",
    "addr:postcode":"93727",
    "addr:street":"E Olive Ave",
    "iso:country":"US",
    "sg:address":"5397 E Olive Ave",
    "sg:city":"Fresno",
    "sg:classifiers":[
        {
            "category":"Education",
            "subcategory":"School",
            "type":"Public Place"
        }
    ],
    "sg:phone":"+1 559 252 6493",
    "sg:postcode":"93727",
    "sg:province":"CA",
    "sg:website":"www.faa.org",
    "wof:name":"Fresno Adventist Academy",
    "wof:placetype":"venue"
},
  "geometry": {"coordinates":[-119.70605500000001,36.75751],"type":"Point"}
}