{
  "type": "Feature",
  "properties": {
    "addr:full":"281 Main St Murphys CA 95247",
    "addr:housenumber":"281",
    "addr:postcode":"95247",
    "addr:street":"Main St",
    "iso:country":"US",
    "sg:address":"281 Main St",
    "sg:city":"Murphys",
    "sg:classifiers":[
        {
            "category":"Shopping",
            "subcategory":"Clothing, Apparel, & Fashions",
            "type":"Retail Goods"
        }
    ],
    "sg:phone":"+1 209 728 8089",
    "sg:postcode":"95247",
    "sg:province":"CA",
    "wof:name":"Sierra Sunwear",
    "wof:placetype":"venue"
},
  "geometry": {"coordinates":[-120.461985,38.137409],"type":"Point"}
}