{
  "type": "Feature",
  "properties": {
    "addr:full":"907 1st St Benicia CA 94510",
    "addr:housenumber":"907",
    "addr:postcode":"94510",
    "addr:street":"1St St",
    "iso:country":"US",
    "sg:address":"907 1st St",
    "sg:city":"Benicia",
    "sg:classifiers":[
        {
            "category":"Restaurant",
            "type":"Food & Drink"
        }
    ],
    "sg:phone":"+1 707 745 4761",
    "sg:postcode":"94510",
    "sg:province":"CA",
    "sg:tags":[
        "sandwich"
    ],
    "wof:name":"Jax 2 Catering",
    "wof:placetype":"venue"
},
  "geometry": {"coordinates":[-122.156916,38.05222],"type":"Point"}
}