{
  "type": "Feature",
  "properties": {
    "addr:full":"4602 Cowell Blvd Davis CA 95618",
    "addr:housenumber":"4602",
    "addr:postcode":"95618",
    "addr:street":"Cowell Blvd",
    "iso:country":"US",
    "sg:address":"4602 Cowell Blvd",
    "sg:city":"Davis",
    "sg:classifiers":[
        {
            "category":"Professional",
            "type":"Services"
        }
    ],
    "sg:phone":"+1 530 753 5563",
    "sg:postcode":"95618",
    "sg:province":"CA",
    "wof:name":"Jacobson Betts & Co",
    "wof:placetype":"venue"
},
  "geometry": {"coordinates":[-121.695161,38.54874],"type":"Point"}
}