{
  "type": "Feature",
  "properties": {
    "addr:full":"100 The Alameda San Jn Bautista CA 95045",
    "addr:housenumber":"100",
    "addr:postcode":"95045",
    "addr:street":"The Alameda San Jn Bautista",
    "iso:country":"US",
    "sg:address":"100 The Alameda",
    "sg:city":"San Jn Bautista",
    "sg:classifiers":[
        {
            "category":"Restaurant",
            "type":"Food & Drink"
        }
    ],
    "sg:phone":"+1 831 623 1748",
    "sg:postcode":"95045",
    "sg:province":"CA",
    "wof:name":"J J's Homemade Burgers",
    "wof:placetype":"venue"
},
  "geometry": {"coordinates":[-121.535357,36.843585],"type":"Point"}
}