{
  "type": "Feature",
  "properties": {
    "iso:country":"US",
    "sg:address":"720 S Lyon St",
    "sg:city":"Santa Ana",
    "sg:classifiers":[
        {
            "category":"Real Estate",
            "subcategory":"Real Estate Operator",
            "type":"Services"
        }
    ],
    "sg:phone":"+1 714 667 5148",
    "sg:postcode":"92705",
    "sg:province":"CA",
    "sg:tags":[
        "apartment"
    ],
    "wof:name":"Warwick Square Social Services",
    "wof:placetype":"venue"
},
  "geometry": {"coordinates":[-117.845001,33.740898],"type":"Point"}
}