{
  "type": "Feature",
  "properties": {
    "iso:country":"US",
    "sg:address":"16265 Laguna Canyon Rd",
    "sg:city":"Irvine",
    "sg:classifiers":[
        {
            "category":"Organizations",
            "subcategory":"Non-profit Organization",
            "type":"Services"
        }
    ],
    "sg:phone":"+1 949 788 9236",
    "sg:postcode":"92618",
    "sg:province":"CA",
    "sg:tags":[
        "service/non-profit",
        "community"
    ],
    "wof:name":"I C E C",
    "wof:placetype":"venue"
},
  "geometry": {"coordinates":[-117.76846999999999,33.65891],"type":"Point"}
}