{
  "type": "Feature",
  "properties": {
    "addr:full":"18149 Ventura Blvd Tarzana CA 91356",
    "addr:housenumber":"18149",
    "addr:postcode":"91356",
    "addr:street":"Ventura Blvd",
    "iso:country":"US",
    "sg:address":"18149 Ventura Blvd",
    "sg:city":"Tarzana",
    "sg:classifiers":[
        {
            "category":"Recreation",
            "type":"Entertainment"
        }
    ],
    "sg:phone":"+1 818 342 4336",
    "sg:postcode":"91356",
    "sg:province":"CA",
    "sg:tags":[
        "martial",
        "arts",
        "instruction"
    ],
    "wof:name":"Moon-Moo Tae Kwondo",
    "wof:placetype":"venue"
},
  "geometry": {"coordinates":[-118.528639,34.165928],"type":"Point"}
}