{
  "type": "Feature",
  "properties": {
    "addr:full":"100 Century Center Court Ste 705 San Jose CA 95112",
    "addr:housenumber":"100",
    "addr:postcode":"95112",
    "addr:street":"Century Center Court Ste 705",
    "iso:country":"US",
    "sg:address":"100 Century Center Court Ste 705",
    "sg:city":"San Jose",
    "sg:classifiers":[
        {
            "category":"Professional",
            "subcategory":"Computer Services",
            "type":"Services"
        }
    ],
    "sg:phone":"+1 404 302 9700",
    "sg:postcode":"95112",
    "sg:province":"CA",
    "sg:tags":[
        "software",
        "colocation",
        "data-center",
        "datacenter",
        "ip",
        "bandwidth",
        "storage",
        "saas",
        "atlanta",
        "managed-hosting",
        "ecommerce",
        "games",
        "video-and-entertainment",
        "enterprise",
        "cdn",
        "content-delivery-network",
        "contentdeliverynetwork",
        "livestreaming",
        "video-streaming",
        "live-strea"
    ],
    "sg:website":"http://www.internap.com",
    "wof:name":"Internap",
    "wof:placetype":"venue"
},
  "geometry": {"coordinates":[-121.91470200000001,37.368515],"type":"Point"}
}