{
  "type": "Feature",
  "properties": {
    "addr:full":"1520 S Santa Fe Ave Compton CA 90221",
    "addr:housenumber":"1520",
    "addr:postcode":"90221",
    "addr:street":"S Santa Fe Ave",
    "iso:country":"US",
    "sg:address":"1520 S Santa Fe Ave",
    "sg:city":"Compton",
    "sg:classifiers":[
        {
            "category":"Home & Garden",
            "subcategory":"Carpets & Floor Coverings",
            "type":"Retail Goods"
        }
    ],
    "sg:phone":"+1 310 856 7770",
    "sg:postcode":"90221",
    "sg:province":"CA",
    "sg:tags":[
        "dealer",
        "rug"
    ],
    "wof:name":"Double Discount Carpet Wrhs",
    "wof:placetype":"venue"
},
  "geometry": {"coordinates":[-118.215441,33.881487],"type":"Point"}
}