{
  "type": "Feature",
  "properties": {
    "addr:full":"5301 W Centinela Ave Los Angeles CA 90045",
    "addr:housenumber":"5301",
    "addr:postcode":"90045",
    "addr:street":"W Centinela Ave",
    "iso:country":"US",
    "sg:address":"5301 W Centinela Ave",
    "sg:city":"Los Angeles",
    "sg:classifiers":[
        {
            "category":"Restaurant",
            "type":"Food & Drink"
        }
    ],
    "sg:phone":"+1 310 338 1297",
    "sg:postcode":"90045",
    "sg:province":"CA",
    "sg:tags":[
        "shop",
        "coffee"
    ],
    "sg:website":"www.starbucks.com",
    "wof:name":"Starbucks",
    "wof:placetype":"venue"
},
  "geometry": {"coordinates":[-118.372865,33.97726],"type":"Point"}
}