{
  "type": "Feature",
  "properties": {
    "addr:full":"225 Park St Lakeport CA 95453",
    "addr:housenumber":"225",
    "addr:postcode":"95453",
    "addr:street":"Park St",
    "iso:country":"US",
    "sg:address":"225 Park St",
    "sg:city":"Lakeport",
    "sg:classifiers":[
        {
            "category":"Government",
            "subcategory":"Office",
            "type":"Public Place"
        }
    ],
    "sg:phone":"+1 707 263 5615",
    "sg:postcode":"95453",
    "sg:province":"CA",
    "sg:tags":[
        "township",
        "government-city",
        "village"
    ],
    "wof:name":"City of Lakeport",
    "wof:placetype":"venue"
},
  "geometry": {"coordinates":[-122.914064,39.043336],"type":"Point"}
}