{
  "type": "Feature",
  "properties": {
    "addr:full":"11418 Hallwood Dr El Monte CA 91732",
    "addr:housenumber":"11418",
    "addr:postcode":"91732",
    "addr:street":"Hallwood Dr",
    "iso:country":"US",
    "sg:address":"11418 Hallwood Dr",
    "sg:city":"El Monte",
    "sg:classifiers":[
        {
            "category":"Building & Trades",
            "subcategory":"Construction",
            "type":"Services"
        }
    ],
    "sg:phone":"+1 626 443 8047",
    "sg:postcode":"91732",
    "sg:province":"CA",
    "sg:tags":[
        "coping",
        "plastering",
        "tiling",
        "pool",
        "swimming"
    ],
    "wof:name":"Art's Pool Svc",
    "wof:placetype":"venue"
},
  "geometry": {"coordinates":[-118.018379,34.094069],"type":"Point"}
}