{
  "type": "Feature",
  "properties": {
    "addr:full":"1414 S Miller St Santa Maria CA 93454",
    "addr:housenumber":"1414",
    "addr:postcode":"93454",
    "addr:street":"S Miller St",
    "iso:country":"US",
    "sg:address":"1414 S Miller St",
    "sg:city":"Santa Maria",
    "sg:classifiers":[
        {
            "category":"Professional",
            "subcategory":"Management & Consulting",
            "type":"Services"
        }
    ],
    "sg:phone":"+1 805 925 5313",
    "sg:postcode":"93454",
    "sg:province":"CA",
    "sg:tags":[
        "consultant",
        "educational"
    ],
    "wof:name":"Visual Learning Ctr",
    "wof:placetype":"venue"
},
  "geometry": {"coordinates":[-120.431455,34.937261],"type":"Point"}
}