{
  "type": "Feature",
  "properties": {
    "iso:country":"US",
    "sg:address":"5896 Smiley Drive",
    "sg:city":"Culver City",
    "sg:classifiers":[
        {
            "category":"Professional",
            "type":"Services"
        },
        {
            "category":"Arts & Performance",
            "subcategory":"Arts Center",
            "type":"Entertainment"
        }
    ],
    "sg:phone":"+1 310 838 3800",
    "sg:postcode":"90232",
    "sg:province":"CA",
    "sg:tags":[
        "planning",
        "event"
    ],
    "sg:website":"www.highprofileproductions.com",
    "wof:name":"High Profile Productions",
    "wof:placetype":"venue"
},
  "geometry": {"coordinates":[-118.37403500000001,34.031374],"type":"Point"}
}