{
  "type": "Feature",
  "properties": {
    "iso:country":"US",
    "sg:address":"1037 Cole Ave",
    "sg:city":"Los Angeles",
    "sg:classifiers":[
        {
            "category":"Communications",
            "subcategory":"Film & Video Production",
            "type":"Services"
        }
    ],
    "sg:phone":"+1 323 962 2233",
    "sg:postcode":"90038",
    "sg:province":"CA",
    "sg:tags":[
        "editing",
        "tape"
    ],
    "sg:website":"www.visualimagehollywood.com",
    "wof:name":"Visual Image",
    "wof:placetype":"venue"
},
  "geometry": {"coordinates":[-118.329959,34.090067],"type":"Point"}
}