{
  "type": "Feature",
  "properties": {
    "addr:full":"1600 Saratoga Ave San Jose CA 95129",
    "addr:housenumber":"1600",
    "addr:postcode":"95129",
    "addr:street":"Saratoga Ave",
    "iso:country":"US",
    "sg:address":"1600 Saratoga Ave",
    "sg:city":"San Jose",
    "sg:classifiers":[
        {
            "category":"Shopping",
            "subcategory":"Clothing, Apparel, & Fashions",
            "type":"Retail Goods"
        }
    ],
    "sg:postcode":"95129",
    "sg:province":"CA",
    "sg:tags":[
        "children's",
        "clothing"
    ],
    "sg:website":"www.shopjustice.com/",
    "wof:name":"Justice, Just for Girls",
    "wof:placetype":"venue"
},
  "geometry": {"coordinates":[-121.989541,37.291254],"type":"Point"}
}