{
  "type": "Feature",
  "properties": {
    "iso:country":"US",
    "sg:address":"2248 S Baker Ave",
    "sg:city":"Ontario",
    "sg:classifiers":[
        {
            "category":"Manufacturing",
            "subcategory":"Retail Goods",
            "type":"Manufacturing & Wholesale Goods"
        }
    ],
    "sg:phone":"+1 909 930 1444",
    "sg:postcode":"91761",
    "sg:province":"CA",
    "sg:tags":[
        "badge",
        "mfg"
    ],
    "sg:website":"www.sunbadgeco.com",
    "wof:name":"Sun Badge Co",
    "wof:placetype":"venue"
},
  "geometry": {"coordinates":[-117.615387,34.03405],"type":"Point"}
}