{
  "type": "Feature",
  "properties": {
    "addr:full":"255 Kingsbury Grade Rd Stateline CA 89449",
    "addr:housenumber":"255",
    "addr:postcode":"89449",
    "addr:street":"Kingsbury Grade Rd",
    "iso:country":"US",
    "sg:address":"255 Kingsbury Grade Rd",
    "sg:city":"Stateline",
    "sg:classifiers":[
        {
            "category":"Banks & Credit Unions",
            "subcategory":"Bank",
            "type":"Services"
        }
    ],
    "sg:phone":"+1 775 586 1360",
    "sg:postcode":"89449",
    "sg:province":"CA",
    "wof:name":"Phoenix Savings Bank",
    "wof:placetype":"venue"
},
  "geometry": {"coordinates":[-119.929551,38.968288],"type":"Point"}
}