{
  "type": "Feature",
  "properties": {
    "iso:country":"US",
    "sg:address":"19375 Prospect St",
    "sg:city":"Desert Hot Spgs",
    "sg:classifiers":[
        {
            "category":"Building & Trades",
            "subcategory":"Electrical",
            "type":"Services"
        }
    ],
    "sg:phone":"+1 760 327 2571",
    "sg:postcode":"92241",
    "sg:province":"CA",
    "sg:tags":[
        "electric",
        "contractor"
    ],
    "wof:name":"Arwin Electric",
    "wof:placetype":"venue"
},
  "geometry": {"coordinates":[-116.384118,33.910442],"type":"Point"}
}