{
  "type": "Feature",
  "properties": {
    "addr:full":"406 Chinn St Santa Rosa CA 95404",
    "addr:housenumber":"406",
    "addr:postcode":"ca 95404",
    "addr:street":"Chinn St",
    "iso:country":"US",
    "sg:address":"406 Chinn St",
    "sg:city":"Santa Rosa",
    "sg:classifiers":[
        {
            "category":"Banks & Credit Unions",
            "subcategory":"Investment Brokerage",
            "type":"Services"
        }
    ],
    "sg:phone":"+1 707 591 9115",
    "sg:postcode":"95404",
    "sg:province":"CA",
    "sg:tags":[
        "consultant",
        "planning",
        "financial"
    ],
    "wof:name":"Douglas Gunter",
    "wof:placetype":"venue"
},
  "geometry": {"coordinates":[-122.707207,38.444673],"type":"Point"}
}