{
  "type": "Feature",
  "properties": {
    "iso:country":"US",
    "sg:address":"838 Placer Ave",
    "sg:city":"South Lake Tahoe",
    "sg:classifiers":[
        {
            "category":"Real Estate",
            "subcategory":"Real Estate Agent",
            "type":"Services"
        }
    ],
    "sg:phone":"+1 530 544 6316",
    "sg:postcode":"96150",
    "sg:province":"CA",
    "wof:name":"Andrew Lyell",
    "wof:placetype":"venue"
},
  "geometry": {"coordinates":[-119.98307800000001,38.934801],"type":"Point"}
}