{
  "type": "Feature",
  "properties": {
    "addr:full":"164 Los Gatos-Saratoga Rd Los Gatos CA 95030",
    "addr:housenumber":"164",
    "addr:postcode":"95030",
    "addr:street":"Los Gatos-Saratoga Rd",
    "iso:country":"US",
    "sg:address":"164 Los Gatos-Saratoga Rd",
    "sg:city":"Los Gatos",
    "sg:classifiers":[
        {
            "category":"Insurance",
            "subcategory":"Hazard Insurance",
            "type":"Services"
        }
    ],
    "sg:phone":"+1 408 399 6669",
    "sg:postcode":"95030",
    "sg:province":"CA",
    "sg:website":"www.patriciamoney.com/",
    "wof:name":"Patricia Money - State Farm Insurance",
    "wof:placetype":"venue"
},
  "geometry": {"coordinates":[-121.979854,37.228425],"type":"Point"}
}