{
  "type": "Feature",
  "properties": {
    "addr:full":"2237 E Colorado Blvd Pasadena CA 91199",
    "addr:housenumber":"2237",
    "addr:postcode":"91199",
    "addr:street":"E Colorado Blvd",
    "iso:country":"US",
    "sg:address":"2237 E Colorado Blvd",
    "sg:city":"Pasadena",
    "sg:classifiers":[
        {
            "category":"Restaurant",
            "type":"Food & Drink"
        }
    ],
    "sg:phone":"+1 626 796 7808",
    "sg:postcode":"91199",
    "sg:province":"CA",
    "sg:tags":[
        "mexican"
    ],
    "wof:name":"Casita Taco",
    "wof:placetype":"venue"
},
  "geometry": {"coordinates":[-118.10440199999999,34.146443],"type":"Point"}
}