{
  "type": "Feature",
  "properties": {
    "addr:full":"4227 Arden Way Sacramento CA 95864",
    "addr:housenumber":"4227",
    "addr:postcode":"95864",
    "addr:street":"Arden Way",
    "iso:country":"US",
    "sg:address":"4227 Arden Way",
    "sg:city":"Sacramento",
    "sg:classifiers":[
        {
            "category":"Personal",
            "subcategory":"Barber",
            "type":"Services"
        }
    ],
    "sg:phone":"+1 916 483 7255",
    "sg:postcode":"95864",
    "sg:province":"CA",
    "wof:name":"Barber Joe's",
    "wof:placetype":"venue"
},
  "geometry": {"coordinates":[-121.366417,38.595625],"type":"Point"}
}