{
  "type": "Feature",
  "properties": {
    "addr:full":"250 Bonifacio Pl Monterey CA 93940",
    "addr:housenumber":"250",
    "addr:postcode":"93940",
    "addr:street":"Bonifacio Pl",
    "iso:country":"US",
    "sg:address":"250 Bonifacio Pl",
    "sg:city":"Monterey",
    "sg:classifiers":[
        {
            "category":"Real Estate",
            "subcategory":"Real Estate Services",
            "type":"Services"
        }
    ],
    "sg:phone":"+1 831 375 2262",
    "sg:postcode":"93940",
    "sg:province":"CA",
    "sg:tags":[
        "company",
        "title"
    ],
    "wof:name":"Chicago Title Co",
    "wof:placetype":"venue"
},
  "geometry": {"coordinates":[-121.893186,36.598702],"type":"Point"}
}