{
  "type": "Feature",
  "properties": {
    "iso:country":"US",
    "sg:address":"1625 Alamo Dr",
    "sg:city":"Vacaville",
    "sg:classifiers":[
        {
            "category":"Social Services",
            "type":"Services"
        }
    ],
    "sg:phone":"+1 707 451 0755",
    "sg:postcode":"95687",
    "sg:province":"CA",
    "sg:tags":[
        "youth",
        "organization",
        "center"
    ],
    "wof:name":"Vacaville Neighborhood Boys",
    "wof:placetype":"venue"
},
  "geometry": {"coordinates":[-121.97913800000001,38.335549],"type":"Point"}
}