{
  "type": "Feature",
  "properties": {
    "iso:country":"US",
    "sg:address":"1522 W Mission Blvd",
    "sg:city":"Ontario",
    "sg:classifiers":[
        {
            "category":"Travel",
            "subcategory":"Hotels & Motels",
            "type":"Entertainment"
        }
    ],
    "sg:phone":"+1 909 984 6789",
    "sg:postcode":"91762",
    "sg:province":"CA",
    "sg:tags":[
        "operation"
    ],
    "wof:name":"Ontario Motor Inn",
    "wof:placetype":"venue"
},
  "geometry": {"coordinates":[-117.677825,34.056044],"type":"Point"}
}