{
  "type": "Feature",
  "properties": {
    "addr:full":"345 Blythe Rd La Canada Fltrdg CA 91011",
    "addr:housenumber":"345",
    "addr:postcode":"91011",
    "addr:street":"Blythe Rd La",
    "iso:country":"US",
    "sg:address":"345 Blythe Rd",
    "sg:city":"La Canada Fltrdg",
    "sg:classifiers":[
        {
            "category":"Professional",
            "subcategory":"Management & Consulting",
            "type":"Services"
        }
    ],
    "sg:phone":"+1 818 790 6278",
    "sg:postcode":"91011",
    "sg:province":"CA",
    "sg:tags":[
        "consultant",
        "energy",
        "conservation"
    ],
    "wof:name":"Douglas B Nickerson",
    "wof:placetype":"venue"
},
  "geometry": {"coordinates":[-118.184679,34.193939],"type":"Point"}
}