{
  "type": "Feature",
  "properties": {
    "addr:full":"1817 Harriman Ln Redondo Beach CA 90278",
    "addr:housenumber":"1817",
    "addr:postcode":"90278",
    "addr:street":"Harriman Ln",
    "iso:country":"US",
    "sg:address":"1817 Harriman Ln",
    "sg:city":"Redondo Beach",
    "sg:classifiers":[
        {
            "category":"Wholesale",
            "subcategory":"Durable Goods & Equipment",
            "type":"Manufacturing & Wholesale Goods"
        }
    ],
    "sg:phone":"+1 310 937 9053",
    "sg:postcode":"90278",
    "sg:province":"CA",
    "sg:tags":[
        "environmental",
        "ecological",
        "prod"
    ],
    "wof:name":"I Lanco Environmental",
    "wof:placetype":"venue"
},
  "geometry": {"coordinates":[-118.37932000000001,33.867158],"type":"Point"}
}