{
  "type": "Feature",
  "properties": {
    "iso:country":"US",
    "sg:address":"5614 Nectar Ave",
    "sg:city":"Hemet",
    "sg:classifiers":[
        {
            "category":"Social Services",
            "subcategory":"Child Care",
            "type":"Services"
        }
    ],
    "sg:phone":"+1 951 765 7365",
    "sg:postcode":"92544",
    "sg:province":"CA",
    "wof:name":"Spraggs Family Daycare",
    "wof:placetype":"venue"
},
  "geometry": {"coordinates":[-116.911952,33.750599],"type":"Point"}
}