{
  "type": "Feature",
  "properties": {
    "addr:full":"177 Brannan St San Francisco CA 94107",
    "addr:housenumber":"177",
    "addr:postcode":"94107",
    "addr:street":"Brannan St",
    "iso:country":"US",
    "sg:address":"177 Brannan St",
    "sg:city":"San Francisco",
    "sg:classifiers":[
        {
            "category":"Home & Garden",
            "subcategory":"Furniture",
            "type":"Retail Goods"
        }
    ],
    "sg:phone":"+1 415 882 7147",
    "sg:postcode":"94107",
    "sg:province":"CA",
    "wof:name":"Embellish",
    "wof:placetype":"venue"
},
  "geometry": {"coordinates":[-122.38918700000001,37.78416],"type":"Point"}
}