{
  "type": "Feature",
  "properties": {
    "addr:full":"25155 Sunnymead Blvd Moreno Valley CA 92553",
    "addr:postcode":"25155;92553",
    "addr:street":"Sunnymead Blvd",
    "iso:country":"US",
    "sg:address":"25155 Sunnymead Blvd",
    "sg:city":"Moreno Valley",
    "sg:classifiers":[
        {
            "category":"Shopping",
            "subcategory":"Bicycles & Sporting Goods",
            "type":"Retail Goods"
        }
    ],
    "sg:phone":"+1 951 243 5393",
    "sg:postcode":"92553",
    "sg:province":"CA",
    "sg:tags":[
        "commercial",
        "printing",
        "sport",
        "book"
    ],
    "wof:name":"Empire Sports",
    "wof:placetype":"venue"
},
  "geometry": {"coordinates":[-117.22589499999999,33.939007],"type":"Point"}
}