{
  "type": "Feature",
  "properties": {
    "iso:country":"US",
    "sg:address":"3675 Huntington Dr Ste 260",
    "sg:city":"Pasadena",
    "sg:classifiers":[
        {
            "category":"Banks & Credit Unions",
            "subcategory":"Financial Services",
            "type":"Services"
        }
    ],
    "sg:phone":"+1 626 795 9928",
    "sg:postcode":"91107",
    "sg:province":"CA",
    "sg:tags":[
        "broker",
        "mortgage"
    ],
    "wof:name":"Nationwide Mortgage Consultants Inc",
    "wof:placetype":"venue"
},
  "geometry": {"coordinates":[-118.07199900000001,34.1306],"type":"Point"}
}