{
  "type": "Feature",
  "properties": {
    "addr:full":"3951 Hamilton Ave San Jose CA 95130",
    "addr:housenumber":"3951",
    "addr:postcode":"95130",
    "addr:street":"Hamilton Ave",
    "iso:country":"US",
    "sg:address":"3951 Hamilton Ave",
    "sg:city":"San Jose",
    "sg:classifiers":[
        {
            "category":"Professional",
            "type":"Services"
        }
    ],
    "sg:phone":"+1 408 379 5185",
    "sg:postcode":"95130",
    "sg:province":"CA",
    "wof:name":"Ravia Razak",
    "wof:placetype":"venue"
},
  "geometry": {"coordinates":[-121.970963,37.294148],"type":"Point"}
}