{
  "type": "Feature",
  "properties": {
    "addr:full":"780 Crocker St Los Angeles CA 90021",
    "addr:housenumber":"780",
    "addr:postcode":"90021",
    "addr:street":"Crocker St",
    "iso:country":"US",
    "sg:address":"780 Crocker St",
    "sg:city":"Los Angeles",
    "sg:classifiers":[
        {
            "category":"Wholesale",
            "subcategory":"Apparel",
            "type":"Manufacturing & Wholesale Goods"
        }
    ],
    "sg:phone":"+1 213 623 2626",
    "sg:postcode":"90021",
    "sg:province":"CA",
    "sg:tags":[
        "piece",
        "fabric"
    ],
    "wof:name":"Capital Textiles",
    "wof:placetype":"venue"
},
  "geometry": {"coordinates":[-118.247668,34.03846],"type":"Point"}
}