{
  "type": "Feature",
  "properties": {
    "addr:full":"345 Pearl Ave Redlands CA 92374",
    "addr:housenumber":"345",
    "addr:postcode":"92374",
    "addr:street":"Pearl Ave",
    "iso:country":"US",
    "sg:address":"345 Pearl Ave",
    "sg:city":"Redlands",
    "sg:phone":"+1 909 335 5700",
    "sg:postcode":"92374",
    "sg:province":"CA",
    "wof:name":"Eureka Burger I",
    "wof:placetype":"venue"
},
  "geometry": {"coordinates":[-117.185925,34.061329],"type":"Point"}
}