{
  "type": "Feature",
  "properties": {
    "iso:country":"US",
    "sg:address":"965 S E St",
    "sg:city":"San Bernardino",
    "sg:classifiers":[
        {
            "category":"Professional",
            "subcategory":"Detective & Security Services",
            "type":"Services"
        }
    ],
    "sg:phone":"+1 909 888 3166",
    "sg:postcode":"92408",
    "sg:province":"CA",
    "sg:tags":[
        "guard",
        "patrol"
    ],
    "wof:name":"Enders Security & Invstgtns",
    "wof:placetype":"venue"
},
  "geometry": {"coordinates":[-117.293975,34.082794],"type":"Point"}
}