{
  "type": "Feature",
  "properties": {
    "addr:full":"17595 Almahurst St City Of Industry CA 91748",
    "addr:housenumber":"17595",
    "addr:postcode":"91748",
    "addr:street":"Almahurst St",
    "iso:country":"US",
    "sg:address":"17595 Almahurst St",
    "sg:city":"City Of Industry",
    "sg:classifiers":[
        {
            "category":"Banks & Credit Unions",
            "subcategory":"Bank",
            "type":"Services"
        }
    ],
    "sg:phone":"+1 626 964 5300",
    "sg:postcode":"91748",
    "sg:province":"CA",
    "sg:tags":[
        "machine",
        "teller",
        "automated"
    ],
    "wof:name":"Money Access Corp",
    "wof:placetype":"venue"
},
  "geometry": {"coordinates":[-117.92317,33.991997],"type":"Point"}
}