{
  "type": "Feature",
  "properties": {
    "addr:full":"1519 Venice Blvd Los Angeles CA 90006",
    "addr:housenumber":"1519",
    "addr:postcode":"90006",
    "addr:street":"Venice Blvd",
    "iso:country":"US",
    "sg:address":"1519 Venice Blvd",
    "sg:city":"Los Angeles",
    "sg:classifiers":[
        {
            "category":"Food & Beverages",
            "subcategory":"Specialty",
            "type":"Retail Goods"
        }
    ],
    "sg:phone":"+1 213 383 7799",
    "sg:postcode":"90006",
    "sg:province":"CA",
    "sg:tags":[
        "product",
        "chinese"
    ],
    "wof:name":"Howondang Inc",
    "wof:placetype":"venue"
},
  "geometry": {"coordinates":[-118.28820399999999,34.044321],"type":"Point"}
}