{
  "type": "Feature",
  "properties": {
    "iso:country":"US",
    "sg:address":"10915 Deliban St",
    "sg:city":"Tujunga",
    "sg:classifiers":[
        {
            "category":"Professional",
            "subcategory":"Management & Consulting",
            "type":"Services"
        }
    ],
    "sg:phone":"+1 818 353 0120",
    "sg:postcode":"91042",
    "sg:province":"CA",
    "sg:tags":[
        "consultant"
    ],
    "wof:name":"Magic Carpet",
    "wof:placetype":"venue"
},
  "geometry": {"coordinates":[-118.288575,34.267065],"type":"Point"}
}