{
  "type": "Feature",
  "properties": {
    "addr:full":"711 W Grangeville Blvd Hanford CA 93230",
    "addr:housenumber":"711",
    "addr:postcode":"ca 93230",
    "addr:street":"W Grangeville Blvd",
    "iso:country":"US",
    "sg:address":"711 W Grangeville Blvd",
    "sg:city":"Hanford",
    "sg:classifiers":[
        {
            "category":"Restaurant",
            "type":"Food & Drink"
        }
    ],
    "sg:phone":"+1 559 584 9249",
    "sg:postcode":"93230",
    "sg:province":"CA",
    "sg:tags":[
        "pizza"
    ],
    "wof:name":"Me-N-Ed's Pizzeria",
    "wof:placetype":"venue"
},
  "geometry": {"coordinates":[-119.656705,36.342533],"type":"Point"}
}