{
  "type": "Feature",
  "properties": {
    "addr:full":"1034 B St Hayward CA 94541",
    "addr:housenumber":"1034",
    "addr:postcode":"94541",
    "addr:street":"B St",
    "iso:country":"US",
    "sg:address":"1034 B St",
    "sg:city":"Hayward",
    "sg:classifiers":[
        {
            "category":"Restaurant",
            "type":"Food & Drink"
        }
    ],
    "sg:menulink":"http://www.allmenus.com/ca/hayward/111075-b-st-restaurant/menu/",
    "sg:phone":"+1 510 888 8938",
    "sg:postcode":"94541",
    "sg:province":"CA",
    "sg:tags":[
        "asian",
        "chinese"
    ],
    "wof:name":"B St. Restaurant",
    "wof:placetype":"venue"
},
  "geometry": {"coordinates":[-122.082116,37.673227],"type":"Point"}
}