{
  "type": "Feature",
  "properties": {
    "iso:country":"US",
    "sg:address":"3436 Mount Pinos Way",
    "sg:city":"Frazier Park",
    "sg:classifiers":[
        {
            "category":"Food & Beverages",
            "subcategory":"Candy",
            "type":"Retail Goods"
        }
    ],
    "sg:phone":"+1 661 245 3217",
    "sg:postcode":"93225",
    "sg:province":"CA",
    "sg:tags":[
        "confectionery"
    ],
    "wof:name":"Sweet Things",
    "wof:placetype":"venue"
},
  "geometry": {"coordinates":[-118.943456,34.8222],"type":"Point"}
}