{
  "type": "Feature",
  "properties": {
    "iso:country":"US",
    "sg:address":"8459 Hollywood Blvd",
    "sg:city":"Los Angeles",
    "sg:classifiers":[
        {
            "category":"Manufacturing",
            "subcategory":"Apparel",
            "type":"Manufacturing & Wholesale Goods"
        }
    ],
    "sg:phone":"+1 323 656 3978",
    "sg:postcode":"90069",
    "sg:province":"CA",
    "wof:name":"Cam & Co",
    "wof:placetype":"venue"
},
  "geometry": {"coordinates":[-118.372424,34.098198],"type":"Point"}
}