{
  "type": "Feature",
  "properties": {
    "iso:country":"US",
    "sg:address":"216 N Floral St",
    "sg:city":"Visalia",
    "sg:classifiers":[
        {
            "category":"Shopping",
            "subcategory":"Clothing, Apparel, & Fashions",
            "type":"Retail Goods"
        }
    ],
    "sg:phone":"+1 559 627 2593",
    "sg:postcode":"93291",
    "sg:province":"CA",
    "sg:tags":[
        "tailor"
    ],
    "wof:name":"Alterations By Nancy",
    "wof:placetype":"venue"
},
  "geometry": {"coordinates":[-119.295621,36.331347],"type":"Point"}
}