{
  "type": "Feature",
  "properties": {
    "iso:country":"US",
    "sg:address":"51 Manchester St",
    "sg:city":"San Francisco",
    "sg:classifiers":[
        {
            "category":"Professional",
            "subcategory":"Accounting & Tax Preparation",
            "type":"Services"
        }
    ],
    "sg:phone":"+1 415 824 8080",
    "sg:postcode":"94110",
    "sg:province":"CA",
    "sg:tags":[
        "payroll"
    ],
    "wof:name":"East West Payroll Svc",
    "wof:placetype":"venue"
},
  "geometry": {"coordinates":[-122.41412,37.745389],"type":"Point"}
}