{
  "type": "Feature",
  "properties": {
    "addr:full":"10 Fullerton Court Sacramento CA 95825",
    "addr:housenumber":"10",
    "addr:postcode":"95825",
    "addr:street":"Fullerton Court",
    "iso:country":"US",
    "sg:address":"10 Fullerton Court",
    "sg:city":"Sacramento",
    "sg:classifiers":[
        {
            "category":"Professional",
            "subcategory":"Lawyer & Legal Services",
            "type":"Services"
        }
    ],
    "sg:phone":"+1 916 649 3600",
    "sg:postcode":"95825",
    "sg:province":"CA",
    "wof:name":"Sargetis John S Attorney At Law",
    "wof:placetype":"venue"
},
  "geometry": {"coordinates":[-121.41165700000001,38.572847],"type":"Point"}
}