{
  "type": "Feature",
  "properties": {
    "acgov:api":"0.0",
    "acgov:type":"K-12",
    "addr:full":"500 Pacific Ave. Alameda CA",
    "wof:categories":[
        "education_and_religion:education=school"
    ],
    "wof:name":"Nea Community Learning Center",
    "wof:placetype":"venue"
},
  "geometry": {"coordinates":[-122.28216277592567,37.77623121585263],"type":"Point"}
}