{
  "type": "Feature",
  "properties": {
    "addr:full":"800 Pine St Paso Robles CA 93446",
    "addr:housenumber":"800",
    "addr:postcode":"93446",
    "addr:street":"Pine St",
    "iso:country":"US",
    "sg:address":"800 Pine St",
    "sg:city":"Paso Robles",
    "sg:classifiers":[
        {
            "category":"Travel",
            "subcategory":"Travel Agent",
            "type":"Entertainment"
        }
    ],
    "sg:phone":"+1 805 239 8836",
    "sg:postcode":"93446",
    "sg:province":"CA",
    "sg:tags":[
        "passenger",
        "transportation",
        "arrangement"
    ],
    "wof:name":"Medi Rides Laidlaw Company",
    "wof:placetype":"venue"
},
  "geometry": {"coordinates":[-120.68857199999999,35.623663],"type":"Point"}
}