{
  "type": "Feature",
  "properties": {
    "addr:full":"10301 County Road 96 Woodland CA 95695",
    "addr:housenumber":"10301",
    "addr:postcode":"95695",
    "addr:street":"County Road 96",
    "iso:country":"US",
    "sg:address":"10301 County Road 96",
    "sg:city":"Woodland",
    "sg:classifiers":[
        {
            "category":"Food & Beverages",
            "subcategory":"Farmers Market",
            "type":"Retail Goods"
        }
    ],
    "sg:phone":"+1 530 662 4965",
    "sg:postcode":"95695",
    "sg:province":"CA",
    "sg:tags":[
        "vegetable",
        "fruit",
        "shipper",
        "grower"
    ],
    "wof:name":"Ray Diffenderffe",
    "wof:placetype":"venue"
},
  "geometry": {"coordinates":[-121.840025,38.790942],"type":"Point"}
}