{
  "type": "Feature",
  "properties": {
    "iso:country":"US",
    "sg:address":"2045 Glen Way",
    "sg:city":"Palo Alto",
    "sg:classifiers":[
        {
            "category":"Wholesale",
            "subcategory":"Durable Goods & Equipment",
            "type":"Manufacturing & Wholesale Goods"
        }
    ],
    "sg:phone":"+1 650 289 9046",
    "sg:postcode":"94303",
    "sg:province":"CA",
    "sg:tags":[
        "exporter"
    ],
    "wof:name":"Bi-Fus",
    "wof:placetype":"venue"
},
  "geometry": {"coordinates":[-122.145072,37.464048],"type":"Point"}
}