{
  "type": "Feature",
  "properties": {
    "iso:country":"US",
    "sg:address":"950 Enchanted Way",
    "sg:city":"Simi Valley",
    "sg:classifiers":[
        {
            "category":"Restaurant",
            "type":"Food & Drink"
        }
    ],
    "sg:phone":"+1 805 583 5500",
    "sg:postcode":"93065",
    "sg:province":"CA",
    "sg:tags":[
        "management"
    ],
    "wof:name":"3 H Network Inc",
    "wof:placetype":"venue"
},
  "geometry": {"coordinates":[-118.782468,34.285259],"type":"Point"}
}