{
  "type": "Feature",
  "properties": {
    "addr:full":"950 Enchanted Way Simi Valley CA 93065",
    "addr:housenumber":"950",
    "addr:postcode":"93065",
    "addr:street":"Enchanted Way",
    "iso:country":"US",
    "sg:address":"950 Enchanted Way",
    "sg:city":"Simi Valley",
    "sg:classifiers":[
        {
            "category":"Restaurant",
            "type":"Food & Drink"
        }
    ],
    "sg:phone":"+1 805 583 5500",
    "sg:postcode":"93065",
    "sg:province":"CA",
    "sg:tags":[
        "management"
    ],
    "wof:name":"3 H Network Inc",
    "wof:placetype":"venue"
},
  "geometry": {"coordinates":[-118.78246799999999,34.285259],"type":"Point"}
}