{
  "type": "Feature",
  "properties": {
    "addr:full":"7734 Girard Ave Ste A La Jolla CA 92037",
    "addr:housenumber":"7734",
    "addr:postcode":"92037",
    "addr:street":"Girard Ave Ste A",
    "iso:country":"US",
    "sg:address":"7734 Girard Ave Ste A",
    "sg:city":"La Jolla",
    "sg:classifiers":[
        {
            "category":"Restaurant",
            "type":"Food & Drink"
        }
    ],
    "sg:phone":"+1 858 456 2020",
    "sg:postcode":"92037",
    "sg:province":"CA",
    "sg:tags":[
        "sushi",
        "bar"
    ],
    "sg:website":"tabusushibar.com",
    "wof:name":"Tabu Sushi Bar & Grill",
    "wof:placetype":"venue"
},
  "geometry": {"coordinates":[-117.274111,32.844236],"type":"Point"}
}