{
  "type": "Feature",
  "properties": {
    "iso:country":"US",
    "sg:address":"285 E Mill St",
    "sg:city":"San Bernardino",
    "sg:classifiers":[
        {
            "category":"Building & Trades",
            "subcategory":"Construction",
            "type":"Services"
        }
    ],
    "sg:phone":"+1 909 890 1721",
    "sg:postcode":"92408",
    "sg:province":"CA",
    "sg:tags":[
        "contractor"
    ],
    "wof:name":"Gibbs Construction Inc",
    "wof:placetype":"venue"
},
  "geometry": {"coordinates":[-117.280145,34.19929],"type":"Point"}
}