{
  "type": "Feature",
  "properties": {
    "iso:country":"US",
    "sg:address":"8747 Baird Ave",
    "sg:city":"Northridge",
    "sg:classifiers":[
        {
            "category":"Retail",
            "subcategory":"Auto Repair",
            "type":"Services"
        }
    ],
    "sg:phone":"+1 818 775 1777",
    "sg:postcode":"91324",
    "sg:province":"CA",
    "sg:tags":[
        "body",
        "repairing",
        "painting",
        "automobile"
    ],
    "wof:name":"Jo-Jo Auto Body Inc.",
    "wof:placetype":"venue"
},
  "geometry": {"coordinates":[-118.53736499999999,34.230187],"type":"Point"}
}