{
  "type": "Feature",
  "properties": {
    "addr:full":"888 5th St Imperial Beach CA 91932",
    "addr:housenumber":"888",
    "addr:postcode":"91932",
    "addr:street":"5Th St",
    "iso:country":"US",
    "sg:address":"888 5th St",
    "sg:city":"Imperial Beach",
    "sg:classifiers":[
        {
            "category":"Organizations",
            "subcategory":"Religious Organization",
            "type":"Services"
        }
    ],
    "sg:phone":"+1 619 424 7877",
    "sg:postcode":"91932",
    "sg:province":"CA",
    "sg:tags":[
        "church"
    ],
    "wof:name":"Mar Vista Baptist Church",
    "wof:placetype":"venue"
},
  "geometry": {"coordinates":[-117.122438,32.580863],"type":"Point"}
}