{
  "type": "Feature",
  "properties": {
    "addr:full":"400 W Ball Rd Anaheim CA 92805",
    "addr:housenumber":"400",
    "addr:postcode":"92805",
    "addr:street":"W Ball Rd",
    "iso:country":"US",
    "sg:address":"400 W Ball Rd",
    "sg:city":"Anaheim",
    "sg:classifiers":[
        {
            "category":"Home & Garden",
            "subcategory":"Building Materials",
            "type":"Retail Goods"
        },
        {
            "category":"Building & Trades",
            "subcategory":"Construction",
            "type":"Services"
        }
    ],
    "sg:phone":"+1 714 535 5550",
    "sg:postcode":"92805",
    "sg:province":"CA",
    "sg:tags":[
        "tile",
        "dealer"
    ],
    "sg:website":"www.cepactile.com",
    "wof:name":"Cepac Tiles",
    "wof:placetype":"venue"
},
  "geometry": {"coordinates":[-117.91171199999999,33.817999],"type":"Point"}
}