{
  "type": "Feature",
  "properties": {
    "addr:full":"553 Laidley St San Francisco CA 94131",
    "addr:housenumber":"553",
    "addr:postcode":"94131",
    "addr:street":"Laidley St",
    "iso:country":"US",
    "sg:address":"553 Laidley St",
    "sg:city":"San Francisco",
    "sg:classifiers":[
        {
            "category":"Professional",
            "subcategory":"Secretarial Services",
            "type":"Services"
        }
    ],
    "sg:phone":"+1 415 585 4009",
    "sg:postcode":"94131",
    "sg:province":"CA",
    "sg:tags":[
        "convention",
        "court",
        "reporter"
    ],
    "wof:name":"Bema Reporting-L Viat",
    "wof:placetype":"venue"
},
  "geometry": {"coordinates":[-122.43171100000001,37.735523],"type":"Point"}
}