{
  "type": "Feature",
  "properties": {
    "addr:full":"650 S. Hill St Los Angeles CA 90014",
    "addr:housenumber":"650",
    "addr:postcode":"90014",
    "addr:street":"S. Hill St",
    "iso:country":"US",
    "sg:address":"650 S. Hill St",
    "sg:city":"Los Angeles",
    "sg:classifiers":[
        {
            "category":"Shopping",
            "subcategory":"Jewelry",
            "type":"Retail Goods"
        },
        {
            "category":"Shopping",
            "subcategory":"Bridal",
            "type":"Retail Goods"
        }
    ],
    "sg:phone":"+1 213 612 4505",
    "sg:postcode":"90014",
    "sg:province":"CA",
    "wof:name":"Easigo",
    "wof:placetype":"venue"
},
  "geometry": {"coordinates":[-118.254306,34.046133],"type":"Point"}
}