{
  "type": "Feature",
  "properties": {
    "addr:full":"5545 Walnut Ave Chino CA 91710",
    "addr:housenumber":"5545",
    "addr:postcode":"91710",
    "addr:street":"Walnut Ave",
    "iso:country":"US",
    "sg:address":"5545 Walnut Ave",
    "sg:city":"Chino",
    "sg:classifiers":[
        {
            "category":"Health Services",
            "subcategory":"Medical Lab",
            "type":"Services"
        }
    ],
    "sg:phone":"+1 909 628 4566",
    "sg:postcode":"91710",
    "sg:province":"CA",
    "sg:tags":[
        "laboratory"
    ],
    "wof:name":"Shakespeare Dental Lab",
    "wof:placetype":"venue"
},
  "geometry": {"coordinates":[-117.68207,34.026289],"type":"Point"}
}