{
  "type": "Feature",
  "properties": {
    "iso:country":"US",
    "sg:address":"516 18th St",
    "sg:city":"Manhattan Beach",
    "sg:classifiers":[
        {
            "category":"Sports & Exercise",
            "subcategory":"Gym",
            "type":"Entertainment"
        }
    ],
    "sg:phone":"+1 310 545 9052",
    "sg:postcode":"90266",
    "sg:province":"CA",
    "sg:tags":[
        "athletic",
        "amateur",
        "center",
        "team"
    ],
    "wof:name":"Manhattan Beach Badminton Club",
    "wof:placetype":"venue"
},
  "geometry": {"coordinates":[-118.408997,33.890202],"type":"Point"}
}