{
  "type": "Feature",
  "properties": {
    "iso:country":"US",
    "sg:address":"27 7th St",
    "sg:city":"Eureka",
    "sg:classifiers":[
        {
            "category":"Autos & Motor Vehicles",
            "subcategory":"Automobile Sales",
            "type":"Retail Goods"
        }
    ],
    "sg:phone":"+1 707 445 2837",
    "sg:postcode":"95501",
    "sg:province":"CA",
    "sg:tags":[
        "car",
        "dealer"
    ],
    "wof:name":"Sole Savers",
    "wof:placetype":"venue"
},
  "geometry": {"coordinates":[-124.170558,40.799654],"type":"Point"}
}