{
  "type": "Feature",
  "properties": {
    "addr:full":"300 7th St Manhattan Beach CA 90266",
    "addr:housenumber":"300",
    "addr:postcode":"90266",
    "addr:street":"7Th St",
    "iso:country":"US",
    "sg:address":"300 7th St",
    "sg:city":"Manhattan Beach",
    "sg:classifiers":[
        {
            "category":"Professional",
            "type":"Services"
        }
    ],
    "sg:phone":"+1 310 376 7284",
    "sg:postcode":"90266",
    "sg:province":"CA",
    "wof:name":"RE De Sign",
    "wof:placetype":"venue"
},
  "geometry": {"coordinates":[-118.40755299999999,33.882083],"type":"Point"}
}