{
  "type": "Feature",
  "properties": {
    "iso:country":"US",
    "sg:address":"615 Mission Ave",
    "sg:city":"Oceanside",
    "sg:classifiers":[
        {
            "category":"Professional",
            "subcategory":"Lawyer & Legal Services",
            "type":"Services"
        },
        {
            "category":"Banks & Credit Unions",
            "subcategory":"Financial Services",
            "type":"Services"
        }
    ],
    "sg:phone":"+1 888 744 9519",
    "sg:postcode":"92054",
    "sg:province":"CA",
    "sg:tags":[
        "advising"
    ],
    "sg:website":"www.1stamericanlawcenter.com",
    "wof:name":"1st American Law Center",
    "wof:placetype":"venue"
},
  "geometry": {"coordinates":[-117.37797999999999,33.196516],"type":"Point"}
}