{
  "type": "Feature",
  "properties": {
    "addr:full":"1705 Westcliff Dr Newport Beach CA 92660",
    "addr:housenumber":"1705",
    "addr:postcode":"92660",
    "addr:street":"Westcliff Dr",
    "iso:country":"US",
    "sg:address":"1705 Westcliff Dr",
    "sg:city":"Newport Beach",
    "sg:classifiers":[
        {
            "category":"Personal",
            "subcategory":"Skin Care",
            "type":"Services"
        }
    ],
    "sg:phone":"+1 949 650 8817",
    "sg:postcode":"92660",
    "sg:province":"CA",
    "wof:name":"Anna Crose Essential Skin Care",
    "wof:placetype":"venue"
},
  "geometry": {"coordinates":[-117.905998,33.626301],"type":"Point"}
}