{
  "type": "Feature",
  "properties": {
    "iso:country":"US",
    "sg:address":"526 E 12th St",
    "sg:city":"Los Angeles",
    "sg:classifiers":[
        {
            "category":"Manufacturing",
            "subcategory":"Apparel",
            "type":"Manufacturing & Wholesale Goods"
        }
    ],
    "sg:phone":"+1 213 746 4346",
    "sg:postcode":"90015",
    "sg:province":"CA",
    "sg:tags":[
        "clothes",
        "accessory"
    ],
    "wof:name":"Kids USA",
    "wof:placetype":"venue"
},
  "geometry": {"coordinates":[-118.25461199999999,34.034473],"type":"Point"}
}