{
  "type": "Feature",
  "properties": {
    "addr:full":"2531 Adams Ave San Diego CA 92116",
    "addr:housenumber":"2531",
    "addr:postcode":"92116",
    "addr:street":"Adams Ave",
    "iso:country":"US",
    "sg:address":"2531 Adams Ave",
    "sg:city":"San Diego",
    "sg:classifiers":[
        {
            "category":"Personal",
            "subcategory":"Massage",
            "type":"Services"
        }
    ],
    "sg:phone":"+1 619 228 3218",
    "sg:postcode":"92116",
    "sg:province":"CA",
    "wof:name":"SD Massage Tech",
    "wof:placetype":"venue"
},
  "geometry": {"coordinates":[-117.136836,32.762867],"type":"Point"}
}