{
  "type": "Feature",
  "properties": {
    "addr:full":"15555 Main St Hesperia CA 92345",
    "addr:housenumber":"15555",
    "addr:postcode":"92345",
    "addr:street":"Main St",
    "iso:country":"US",
    "sg:address":"15555 Main St",
    "sg:city":"Hesperia",
    "sg:classifiers":[
        {
            "category":"Restaurant",
            "type":"Food & Drink"
        }
    ],
    "sg:menulink":"http://www.allmenus.com/ca/barstow-victorville/164323-wienerschnitzel/menu/",
    "sg:phone":"+1 760 949 9966",
    "sg:postcode":"92345",
    "sg:province":"CA",
    "sg:tags":[
        "sandwich",
        "dog",
        "burger",
        "hot",
        "wrap",
        "american"
    ],
    "wof:name":"Wienerschnitzel",
    "wof:placetype":"venue"
},
  "geometry": {"coordinates":[-117.32341,34.424398],"type":"Point"}
}