{
  "type": "Feature",
  "properties": {
    "iso:country":"US",
    "sg:address":"390 El Camino Real Ste N",
    "sg:city":"Belmont",
    "sg:classifiers":[
        {
            "category":"Education",
            "subcategory":"Special Training",
            "type":"Public Place"
        }
    ],
    "sg:phone":"+1 650 592 6284",
    "sg:postcode":"94002",
    "sg:province":"CA",
    "sg:tags":[
        "tutoring"
    ],
    "wof:name":"Supermath",
    "wof:placetype":"venue"
},
  "geometry": {"coordinates":[-122.283997,37.526798],"type":"Point"}
}