{
  "type": "Feature",
  "properties": {
    "addr:full":"1057 N State St Ukiah CA 95482",
    "addr:housenumber":"1057",
    "addr:postcode":"ca 95482",
    "addr:street":"N State St",
    "iso:country":"US",
    "sg:address":"1057 N State St",
    "sg:city":"Ukiah",
    "sg:classifiers":[
        {
            "category":"Utilities",
            "subcategory":"Telephone",
            "type":"Services"
        }
    ],
    "sg:phone":"+1 707 467 3959",
    "sg:postcode":"95482",
    "sg:province":"CA",
    "sg:tags":[
        "communications"
    ],
    "wof:name":"Ryan Assoc",
    "wof:placetype":"venue"
},
  "geometry": {"coordinates":[-123.20953,39.161409],"type":"Point"}
}