{
  "type": "Feature",
  "properties": {
    "addr:full":"17730 Rinaldi St Granada Hills CA 91344",
    "addr:housenumber":"17730",
    "addr:postcode":"91344",
    "addr:street":"Rinaldi St",
    "iso:country":"US",
    "sg:address":"17730 Rinaldi St",
    "sg:city":"Granada Hills",
    "sg:classifiers":[
        {
            "category":"Social Services",
            "subcategory":"Child Care",
            "type":"Services"
        }
    ],
    "sg:phone":"+1 818 363 8442",
    "sg:postcode":"91344",
    "sg:province":"CA",
    "sg:website":"www.kindercare.com",
    "wof:name":"Kinder Care Learning Ctr",
    "wof:placetype":"venue"
},
  "geometry": {"coordinates":[-118.519773,34.279314],"type":"Point"}
}