{
  "type": "Feature",
  "properties": {
    "iso:country":"US",
    "sg:address":"149 E Arrow Hwy",
    "sg:city":"San Dimas",
    "sg:classifiers":[
        {
            "category":"Professional",
            "subcategory":"Management & Consulting",
            "type":"Services"
        }
    ],
    "sg:phone":"+1 909 542 0445",
    "sg:postcode":"91773",
    "sg:province":"CA",
    "sg:tags":[
        "food"
    ],
    "wof:name":"Daniel Paul Catering",
    "wof:placetype":"venue"
},
  "geometry": {"coordinates":[-117.80377799999999,34.103035],"type":"Point"}
}