{
  "type": "Feature",
  "properties": {
    "addr:full":"1762 Mesa Dr Lancaster CA 93535",
    "addr:housenumber":"1762",
    "addr:postcode":"93535",
    "addr:street":"Mesa Dr",
    "iso:country":"US",
    "sg:address":"1762 Mesa Dr",
    "sg:city":"Lancaster",
    "sg:classifiers":[
        {
            "category":"Organizations",
            "subcategory":"Membership Organization",
            "type":"Services"
        }
    ],
    "sg:phone":"+1 661 723 5149",
    "sg:postcode":"93535",
    "sg:province":"CA",
    "sg:tags":[
        "fraternal"
    ],
    "wof:name":"Eagles Helen",
    "wof:placetype":"venue"
},
  "geometry": {"coordinates":[-118.097606,34.682808],"type":"Point"}
}