{
  "type": "Feature",
  "properties": {
    "addr:full":"724 Kiernan Ave Modesto CA 95356",
    "addr:housenumber":"724",
    "addr:postcode":"ca 95356",
    "addr:street":"Kiernan Ave",
    "iso:country":"US",
    "sg:address":"724 Kiernan Ave",
    "sg:city":"Modesto",
    "sg:classifiers":[
        {
            "category":"Wholesale",
            "subcategory":"Construction Materials",
            "type":"Manufacturing & Wholesale Goods"
        }
    ],
    "sg:phone":"+1 209 575 3067",
    "sg:postcode":"95356",
    "sg:province":"CA",
    "sg:tags":[
        "pallet",
        "skid"
    ],
    "wof:name":"Fritz & Rodriguez Inc",
    "wof:placetype":"venue"
},
  "geometry": {"coordinates":[-121.003721,37.711061],"type":"Point"}
}