{
  "type": "Feature",
  "properties": {
    "addr:full":"116 Main St Downieville CA 95936",
    "addr:housenumber":"116",
    "addr:postcode":"95936",
    "addr:street":"Main St",
    "iso:country":"US",
    "sg:address":"116 Main St",
    "sg:city":"Downieville",
    "sg:classifiers":[
        {
            "category":"Restaurant",
            "type":"Food & Drink"
        }
    ],
    "sg:phone":"+1 530 289 3540",
    "sg:postcode":"95936",
    "sg:province":"CA",
    "sg:tags":[
        "pizza"
    ],
    "wof:name":"The Gallows Cafe",
    "wof:placetype":"venue"
},
  "geometry": {"coordinates":[-120.82552200000001,39.566555],"type":"Point"}
}