{
  "type": "Feature",
  "properties": {
    "addr:full":"890 Jackson St San Francisco CA 94133",
    "addr:housenumber":"890",
    "addr:postcode":"94133",
    "addr:street":"Jackson St",
    "iso:country":"US",
    "sg:address":"890 Jackson St",
    "sg:city":"San Francisco",
    "sg:classifiers":[
        {
            "category":"Health Services",
            "subcategory":"Doctor",
            "type":"Services"
        }
    ],
    "sg:phone":"+1 415 788 8881",
    "sg:postcode":"94133",
    "sg:province":"CA",
    "sg:tags":[
        "dentist"
    ],
    "wof:name":"Golden Gate Dental",
    "wof:placetype":"venue"
},
  "geometry": {"coordinates":[-122.409688,37.795725],"type":"Point"}
}