{
  "type": "Feature",
  "properties": {
    "iso:country":"US",
    "sg:address":"41915 Motor Car Pkwy",
    "sg:city":"Temecula",
    "sg:classifiers":[
        {
            "category":"Professional",
            "subcategory":"Employment Agencies",
            "type":"Services"
        }
    ],
    "sg:phone":"+1 951 308 2686",
    "sg:postcode":"92591",
    "sg:province":"CA",
    "sg:tags":[
        "opportunity"
    ],
    "sg:website":"www.us.manpower.com",
    "wof:name":"Manpower Temporary Svc",
    "wof:placetype":"venue"
},
  "geometry": {"coordinates":[-117.15441800000001,33.516919],"type":"Point"}
}