{
  "type": "Feature",
  "properties": {
    "addr:full":"5962 S Normandie Ave Los Angeles CA 90044",
    "addr:housenumber":"5962",
    "addr:postcode":"90044",
    "addr:street":"S Normandie Ave",
    "iso:country":"US",
    "sg:address":"5962 S Normandie Ave",
    "sg:city":"Los Angeles",
    "sg:classifiers":[
        {
            "category":"Personal",
            "subcategory":"Beauty Salon",
            "type":"Services"
        }
    ],
    "sg:phone":"+1 323 971 9413",
    "sg:postcode":"90044",
    "sg:province":"CA",
    "wof:name":"International Beauty Salon",
    "wof:placetype":"venue"
},
  "geometry": {"coordinates":[-118.30013700000001,33.986079],"type":"Point"}
}