{
  "type": "Feature",
  "properties": {
    "addr:full":"125 S Main St Bishop CA 93514",
    "addr:housenumber":"125",
    "addr:postcode":"93514",
    "addr:street":"S Main St",
    "iso:country":"US",
    "sg:address":"125 S Main St",
    "sg:city":"Bishop",
    "sg:classifiers":[
        {
            "category":"Place Of Worship",
            "subcategory":"Church",
            "type":"Public Place"
        },
        {
            "category":"Place Of Worship",
            "type":"Public Place"
        },
        {
            "category":"Organizations",
            "subcategory":"Religious Organization",
            "type":"Services"
        }
    ],
    "sg:phone":"+1 760 872 4225",
    "sg:postcode":"93514",
    "sg:province":"CA",
    "sg:tags":[
        "churches-interdenominational",
        "churches-various",
        "denomination"
    ],
    "sg:website":"http://www.calvarychapel.com",
    "wof:name":"Calvary Chapel Bishop",
    "wof:placetype":"venue"
},
  "geometry": {"coordinates":[-118.395276,37.361228],"type":"Point"}
}