{
  "type": "Feature",
  "properties": {
    "iso:country":"US",
    "sfac:artist":"Walburg, Gerald",
    "sfac:created_at":"01/01/1970 12:32:54 AM +0000",
    "sfac:credit_line":"Purchased by the San Francisco Art Commission for the San Francisco General Hospital",
    "sfac:display_dimensions":"120\" H X 300\" W X 96\"D",
    "sfac:location_description":"City Department : SFGH : Main Quad",
    "sfac:medium":"Corten steel",
    "sfac:revision":"2-6d37a1bb562bf9bdf7a1aff1207b1085",
    "sfac:title":"Stiff Loops (Loop IV)",
    "wof:name":"Stiff Loops (Loop IV)",
    "wof:placetype":"venue"
},
  "geometry": {"coordinates":[-122.40444309999999,37.7557795],"type":"Point"}
}