{
  "type": "Feature",
  "properties": {
    "addr:full":"345 S California Ave Palo Alto CA 94306",
    "addr:housenumber":"345",
    "addr:postcode":"94306",
    "addr:street":"S California Ave",
    "iso:country":"US",
    "sg:address":"345 S California Ave",
    "sg:city":"Palo Alto",
    "sg:classifiers":[
        {
            "category":"Manufacturing",
            "subcategory":"Musical Instruments",
            "type":"Manufacturing & Wholesale Goods"
        }
    ],
    "sg:phone":"+1 650 327 8465",
    "sg:postcode":"94306",
    "sg:province":"CA",
    "sg:tags":[
        "repair",
        "mfg"
    ],
    "wof:name":"Palo Alto Violins",
    "wof:placetype":"venue"
},
  "geometry": {"coordinates":[-122.144308,37.426879],"type":"Point"}
}