{
  "type": "Feature",
  "properties": {
    "addr:full":"3005 W Ave L Lancaster CA 93536",
    "addr:housenumber":"3005",
    "addr:postcode":"93536",
    "addr:street":"W Ave L",
    "iso:country":"US",
    "sg:address":"3005 W Ave L",
    "sg:city":"Lancaster",
    "sg:classifiers":[
        {
            "category":"Retail",
            "subcategory":"Repair Shop",
            "type":"Services"
        }
    ],
    "sg:phone":"+1 661 943 9594",
    "sg:postcode":"93536",
    "sg:province":"CA",
    "sg:tags":[
        "instrument",
        "musical"
    ],
    "wof:name":"Joe Giesler",
    "wof:placetype":"venue"
},
  "geometry": {"coordinates":[-118.18355099999999,34.660219],"type":"Point"}
}