{
  "type": "Feature",
  "properties": {
    "addr:full":"2280 S K St Tulare CA 93274",
    "addr:housenumber":"2280",
    "addr:postcode":"93274",
    "addr:street":"S K St",
    "iso:country":"US",
    "sg:address":"2280 S K St",
    "sg:city":"Tulare",
    "sg:classifiers":[
        {
            "category":"Wholesale",
            "subcategory":"Hardware",
            "type":"Manufacturing & Wholesale Goods"
        },
        {
            "category":"Building & Trades",
            "subcategory":"Equipment Rental",
            "type":"Services"
        },
        {
            "category":"Home & Garden",
            "subcategory":"Hardware",
            "type":"Retail Goods"
        }
    ],
    "sg:phone":"+1 559 687 2599",
    "sg:postcode":"93274",
    "sg:province":"CA",
    "sg:tags":[
        "contractor",
        "hardware-builders",
        "store",
        "supply"
    ],
    "wof:name":"Direct Distributing",
    "wof:placetype":"venue"
},
  "geometry": {"coordinates":[-119.34103899999999,36.185365],"type":"Point"}
}