{
  "type": "Feature",
  "properties": {
    "addr:full":"29021 Ave Sherman Ste 112 Valencia CA 91355",
    "addr:housenumber":"29021",
    "addr:postcode":"91355",
    "addr:street":"Ave;112",
    "iso:country":"US",
    "sg:address":"29021 Ave Sherman Ste 112",
    "sg:city":"Valencia",
    "sg:classifiers":[
        {
            "category":"Food & Beverages",
            "subcategory":"Ethnic Foods",
            "type":"Retail Goods"
        }
    ],
    "sg:phone":"+1 661 295 9833",
    "sg:postcode":"91355",
    "sg:province":"CA",
    "sg:website":"www.mariaelenas.com",
    "wof:name":"Maria Elena's Authentic Latino Inc.",
    "wof:placetype":"venue"
},
  "geometry": {"coordinates":[-118.633335,34.445506],"type":"Point"}
}