{
  "type": "Feature",
  "properties": {
    "iso:country":"US",
    "sg:address":"3841 Larkspur Dr",
    "sg:city":"Concord",
    "sg:classifiers":[
        {
            "category":"Social Services",
            "subcategory":"Child Care",
            "type":"Services"
        }
    ],
    "sg:phone":"+1 925 356 2343",
    "sg:postcode":"94519",
    "sg:province":"CA",
    "wof:name":"Monte Gardens Day Care Ctr",
    "wof:placetype":"venue"
},
  "geometry": {"coordinates":[-122.00472600000001,37.988826],"type":"Point"}
}