{
  "type": "Feature",
  "properties": {
    "iso:country":"US",
    "sg:address":"9121 Oakdale Ave Ste 100",
    "sg:city":"Chatsworth",
    "sg:classifiers":[
        {
            "category":"Shopping",
            "subcategory":"Party Supplies",
            "type":"Retail Goods"
        }
    ],
    "sg:phone":"+1 818 734 4700",
    "sg:postcode":"91311",
    "sg:province":"CA",
    "sg:tags":[
        "decoration",
        "favors"
    ],
    "wof:name":"Ehp Administrators",
    "wof:placetype":"venue"
},
  "geometry": {"coordinates":[-118.566821,34.236197],"type":"Point"}
}