{
  "type": "Feature",
  "properties": {
    "iso:country":"US",
    "sg:address":"666 N Palm Canyon Dr",
    "sg:city":"Palm Springs",
    "sg:classifiers":[
        {
            "category":"Professional",
            "type":"Services"
        }
    ],
    "sg:phone":"+1 760 327 0018",
    "sg:postcode":"92262",
    "sg:province":"CA",
    "sg:tags":[
        "establishment"
    ],
    "wof:name":"Kennedy Christopher Design",
    "wof:placetype":"venue"
},
  "geometry": {"coordinates":[-116.546705,33.832703],"type":"Point"}
}