{
  "type": "Feature",
  "properties": {
    "addr:full":"415 W Compton Blvd Compton CA 90220",
    "addr:housenumber":"415",
    "addr:postcode":"90220",
    "addr:street":"W Compton Blvd",
    "iso:country":"US",
    "sg:address":"415 W Compton Blvd",
    "sg:city":"Compton",
    "sg:classifiers":[
        {
            "category":"Recreation",
            "type":"Entertainment"
        }
    ],
    "sg:phone":"+1 310 761 1055",
    "sg:postcode":"90220",
    "sg:province":"CA",
    "sg:tags":[
        "club",
        "membership"
    ],
    "wof:name":"Compton Athletic Club",
    "wof:placetype":"venue"
},
  "geometry": {"coordinates":[-118.230597,33.896002],"type":"Point"}
}