{
  "type": "Feature",
  "properties": {
    "addr:full":"3236 San Gabriel Blvd Rosemead CA 91770",
    "addr:housenumber":"3236",
    "addr:postcode":"91770",
    "addr:street":"San Gabriel Blvd",
    "iso:country":"US",
    "sg:address":"3236 San Gabriel Blvd",
    "sg:city":"Rosemead",
    "sg:classifiers":[
        {
            "category":"Autos & Motor Vehicles",
            "subcategory":"Automobile Sales",
            "type":"Retail Goods"
        }
    ],
    "sg:phone":"+1 626 569 2836",
    "sg:postcode":"91770",
    "sg:province":"CA",
    "sg:tags":[
        "car",
        "dealer"
    ],
    "wof:name":"Auto Used-Car Inc",
    "wof:placetype":"venue"
},
  "geometry": {"coordinates":[-118.090484,34.067224],"type":"Point"}
}