{
  "type": "Feature",
  "properties": {
    "addr:full":"5870 Melrose Ave Ste 2 Los Angeles CA 90038",
    "addr:housenumber":"5870",
    "addr:postcode":"90038",
    "addr:street":"Melrose Ave Ste 2",
    "iso:country":"US",
    "sg:address":"5870 Melrose Ave Ste 2",
    "sg:city":"Los Angeles",
    "sg:classifiers":[
        {
            "category":"Retail",
            "subcategory":"Laundry & Dry Cleaning",
            "type":"Services"
        }
    ],
    "sg:phone":"+1 323 962 4497",
    "sg:postcode":"90038",
    "sg:province":"CA",
    "wof:name":"Star Cleaners",
    "wof:placetype":"venue"
},
  "geometry": {"coordinates":[-118.328003,34.083401],"type":"Point"}
}