{
  "type": "Feature",
  "properties": {
    "iso:country":"US",
    "sg:address":"751 W Daily Dr",
    "sg:city":"Camarillo",
    "sg:classifiers":[
        {
            "category":"Government",
            "subcategory":"Office",
            "type":"Public Place"
        }
    ],
    "sg:phone":"+1 805 388 0383",
    "sg:postcode":"93010",
    "sg:province":"CA",
    "sg:tags":[
        "defense",
        "investigation"
    ],
    "wof:name":"Personnel Security Investi",
    "wof:placetype":"venue"
},
  "geometry": {"coordinates":[-119.09187,34.221206],"type":"Point"}
}