{
  "type": "Feature",
  "properties": {
    "iso:country":"US",
    "sg:address":"2300 Pullman Ln",
    "sg:city":"Redondo Beach",
    "sg:classifiers":[
        {
            "category":"Wholesale",
            "subcategory":"Jewelry",
            "type":"Manufacturing & Wholesale Goods"
        }
    ],
    "sg:phone":"+1 310 798 1020",
    "sg:postcode":"90278",
    "sg:province":"CA",
    "sg:tags":[
        "jeweler",
        "supply"
    ],
    "wof:name":"Janet Christy & Assoc",
    "wof:placetype":"venue"
},
  "geometry": {"coordinates":[-118.368489,33.8643],"type":"Point"}
}