{
  "type": "Feature",
  "properties": {
    "addr:full":"1777 S Yosemite Ave Oakdale CA 95361",
    "addr:housenumber":"1777",
    "addr:postcode":"95361",
    "addr:street":"S Yosemite Ave",
    "iso:country":"US",
    "sg:address":"1777 S Yosemite Ave",
    "sg:city":"Oakdale",
    "sg:classifiers":[
        {
            "category":"Sports & Exercise",
            "subcategory":"Gym",
            "type":"Entertainment"
        }
    ],
    "sg:phone":"+1 209 847 7504",
    "sg:postcode":"95361",
    "sg:province":"CA",
    "sg:tags":[
        "club",
        "health",
        "studio",
        "gymnasium"
    ],
    "wof:name":"Fitness Plus",
    "wof:placetype":"venue"
},
  "geometry": {"coordinates":[-120.83993100000001,37.748781],"type":"Point"}
}