{
  "type": "Feature",
  "properties": {
    "iso:country":"US",
    "sg:address":"2444 247th St",
    "sg:city":"Lomita",
    "sg:classifiers":[
        {
            "category":"Building & Trades",
            "subcategory":"Construction",
            "type":"Services"
        }
    ],
    "sg:phone":"+1 310 530 5021",
    "sg:postcode":"90717",
    "sg:province":"CA",
    "sg:tags":[
        "general",
        "contractor"
    ],
    "wof:name":"Just In Time",
    "wof:placetype":"venue"
},
  "geometry": {"coordinates":[-118.32671999999999,33.800491],"type":"Point"}
}