{
  "type": "Feature",
  "properties": {
    "addr:full":"478 South Norfolk St San Mateo CA 94401",
    "addr:housenumber":"478",
    "addr:postcode":"94401",
    "addr:street":"South;St",
    "iso:country":"US",
    "sg:address":"478 South Norfolk St",
    "sg:city":"San Mateo",
    "sg:classifiers":[
        {
            "category":"Restaurant",
            "type":"Food & Drink"
        }
    ],
    "sg:phone":"+1 650 340 8131",
    "sg:postcode":"94401",
    "sg:province":"CA",
    "sg:tags":[
        "mexican"
    ],
    "wof:name":"Taqueria Ay Caray!",
    "wof:placetype":"venue"
},
  "geometry": {"coordinates":[-122.30998599999999,37.571823],"type":"Point"}
}