{
  "type": "Feature",
  "properties": {
    "addr:full":"1045 Montgomery Ave San Bruno CA 94066",
    "addr:housenumber":"1045",
    "addr:postcode":"94066",
    "addr:street":"Montgomery Ave",
    "iso:country":"US",
    "sg:address":"1045 Montgomery Ave",
    "sg:city":"San Bruno",
    "sg:classifiers":[
        {
            "category":"Retail",
            "subcategory":"Auto Repair",
            "type":"Services"
        }
    ],
    "sg:phone":"+1 650 615 0393",
    "sg:postcode":"94066",
    "sg:province":"CA",
    "sg:tags":[
        "body",
        "automobile",
        "painting"
    ],
    "wof:name":"A & W Auto Body & Repair",
    "wof:placetype":"venue"
},
  "geometry": {"coordinates":[-122.41244,37.636153],"type":"Point"}
}