{
  "type": "Feature",
  "properties": {
    "iso:country":"US",
    "sg:address":"132 Mill St",
    "sg:city":"Healdsburg",
    "sg:classifiers":[
        {
            "category":"Professional",
            "subcategory":"Art Services",
            "type":"Services"
        }
    ],
    "sg:phone":"+1 707 433 7585",
    "sg:postcode":"95448",
    "sg:province":"CA",
    "sg:tags":[
        "graphic",
        "designer"
    ],
    "wof:name":"Graphite Studio",
    "wof:placetype":"venue"
},
  "geometry": {"coordinates":[-122.86783,38.60877],"type":"Point"}
}