{
  "type": "Feature",
  "properties": {
    "iso:country":"US",
    "sg:address":"12231 Horley Ave",
    "sg:city":"Downey",
    "sg:classifiers":[
        {
            "category":"Freight",
            "type":"Transportation"
        }
    ],
    "sg:phone":"+1 562 577 8753",
    "sg:postcode":"90242",
    "sg:province":"CA",
    "wof:name":"X Transportation Storage",
    "wof:placetype":"venue"
},
  "geometry": {"coordinates":[-118.15431599999999,33.930655],"type":"Point"}
}