{
  "type": "Feature",
  "properties": {
    "iso:country":"US",
    "sg:address":"1126 E Idahome St",
    "sg:city":"West Covina",
    "sg:classifiers":[
        {
            "category":"Professional",
            "type":"Services"
        }
    ],
    "sg:phone":"+1 626 967 0838",
    "sg:postcode":"91790",
    "sg:province":"CA",
    "wof:name":"MEI Hsiang Inc",
    "wof:placetype":"venue"
},
  "geometry": {"coordinates":[-117.923941,34.074565],"type":"Point"}
}