{
  "type": "Feature",
  "properties": {
    "addr:full":"417 Santa Barbara St Santa Barbara CA 93101",
    "addr:housenumber":"417",
    "addr:postcode":"93101",
    "addr:street":"Santa Barbara St",
    "iso:country":"US",
    "sg:address":"417 Santa Barbara St",
    "sg:city":"Santa Barbara",
    "sg:classifiers":[
        {
            "category":"Building & Trades",
            "subcategory":"Plumbing",
            "type":"Services"
        }
    ],
    "sg:phone":"+1 805 965 7302",
    "sg:postcode":"93101",
    "sg:province":"CA",
    "sg:tags":[
        "plumbing",
        "contractor"
    ],
    "wof:name":"Puchli Plumbing",
    "wof:placetype":"venue"
},
  "geometry": {"coordinates":[-119.69309800000001,34.418725],"type":"Point"}
}