{
  "type": "Feature",
  "properties": {
    "addr:full":"323 9th St Oakland CA 94607",
    "addr:housenumber":"323",
    "addr:postcode":"94607",
    "addr:street":"9Th St",
    "iso:country":"US",
    "sg:address":"323 9th St",
    "sg:city":"Oakland",
    "sg:classifiers":[
        {
            "category":"Food & Beverages",
            "subcategory":"Specialty",
            "type":"Retail Goods"
        }
    ],
    "sg:phone":"+1 510 268 1155",
    "sg:postcode":"94607",
    "sg:province":"CA",
    "sg:tags":[
        "poultry"
    ],
    "wof:name":"T & S Market",
    "wof:placetype":"venue"
},
  "geometry": {"coordinates":[-122.270382,37.799462],"type":"Point"}
}