{
  "type": "Feature",
  "properties": {
    "iso:country":"US",
    "sg:address":"9821 Fair Oaks Blvd",
    "sg:city":"Fair Oaks",
    "sg:classifiers":[
        {
            "category":"Professional",
            "subcategory":"Accounting & Tax Preparation",
            "type":"Services"
        }
    ],
    "sg:phone":"+1 916 966 9966",
    "sg:postcode":"95628",
    "sg:province":"CA",
    "sg:tags":[
        "accountant"
    ],
    "wof:name":"Kenneth A Bersinger CPA",
    "wof:placetype":"venue"
},
  "geometry": {"coordinates":[-121.27591200000001,38.639377],"type":"Point"}
}