{
  "type": "Feature",
  "properties": {
    "addr:full":"3970 Goldfinch St San Diego CA 92103",
    "addr:housenumber":"3970",
    "addr:postcode":"92103",
    "addr:street":"Goldfinch St",
    "iso:country":"US",
    "sg:address":"3970 Goldfinch St",
    "sg:city":"San Diego",
    "sg:classifiers":[
        {
            "category":"Banks & Credit Unions",
            "subcategory":"Bank",
            "type":"Services"
        }
    ],
    "sg:phone":"+1 619 298 6802",
    "sg:postcode":"92103",
    "sg:province":"CA",
    "sg:tags":[
        "federal",
        "agency"
    ],
    "wof:name":"Mks International Distributor",
    "wof:placetype":"venue"
},
  "geometry": {"coordinates":[-117.171452,32.749467],"type":"Point"}
}