{
  "type": "Feature",
  "properties": {
    "addr:full":"18720 Sherman Way Reseda CA 91335",
    "addr:housenumber":"18720",
    "addr:postcode":"91335",
    "addr:street":"Sherman Way",
    "iso:country":"US",
    "sg:address":"18720 Sherman Way",
    "sg:city":"Reseda",
    "sg:classifiers":[
        {
            "category":"Autos & Motor Vehicles",
            "subcategory":"Auto Supplies",
            "type":"Retail Goods"
        }
    ],
    "sg:phone":"+1 818 343 8473",
    "sg:postcode":"91335",
    "sg:province":"CA",
    "sg:tags":[
        "tire"
    ],
    "wof:name":"A & A Tires Wheels & Service",
    "wof:placetype":"venue"
},
  "geometry": {"coordinates":[-118.54118,34.20105],"type":"Point"}
}