{
  "type": "Feature",
  "properties": {
    "addr:full":"761 Maria Way Gilroy CA 95020",
    "addr:housenumber":"761",
    "addr:postcode":"95020",
    "addr:street":"Maria Way",
    "iso:country":"US",
    "sg:address":"761 Maria Way",
    "sg:city":"Gilroy",
    "sg:classifiers":[
        {
            "category":"Building & Trades",
            "subcategory":"Cleaning & Sanitation",
            "type":"Services"
        }
    ],
    "sg:phone":"+1 408 842 7430",
    "sg:postcode":"95020",
    "sg:province":"CA",
    "sg:tags":[
        "janitor"
    ],
    "wof:name":"M & R Janitorial",
    "wof:placetype":"venue"
},
  "geometry": {"coordinates":[-121.587931,37.022024],"type":"Point"}
}