{
  "type": "Feature",
  "properties": {
    "addr:full":"1207 N St Firebaugh CA 93622",
    "addr:housenumber":"1207",
    "addr:postcode":"93622",
    "addr:street":"N St",
    "iso:country":"US",
    "sg:address":"1207 N St",
    "sg:city":"Firebaugh",
    "sg:classifiers":[
        {
            "category":"Food & Beverages",
            "subcategory":"Groceries & Convenience Stores",
            "type":"Retail Goods"
        }
    ],
    "sg:phone":"+1 559 659 4013",
    "sg:postcode":"93622",
    "sg:province":"CA",
    "wof:name":"Reno's Mega Mart",
    "wof:placetype":"venue"
},
  "geometry": {"coordinates":[-120.456317,36.857184],"type":"Point"}
}