{
  "type": "Feature",
  "properties": {
    "iso:country":"US",
    "sg:address":"52 Via Pamplona",
    "sg:city":"Rancho Santa Margarita",
    "sg:classifiers":[
        {
            "category":"Shopping",
            "subcategory":"Catalog Store",
            "type":"Retail Goods"
        }
    ],
    "sg:phone":"+1 949 888 9370",
    "sg:postcode":"92688",
    "sg:province":"CA",
    "sg:tags":[
        "mail",
        "house"
    ],
    "wof:name":"Home Works",
    "wof:placetype":"venue"
},
  "geometry": {"coordinates":[-117.589468,33.640232],"type":"Point"}
}