{
  "type": "Feature",
  "properties": {
    "iso:country":"US",
    "sg:address":"28188 Moulton Pkwy",
    "sg:city":"Laguna Niguel",
    "sg:classifiers":[
        {
            "category":"Professional",
            "type":"Services"
        }
    ],
    "sg:phone":"+1 949 215 7505",
    "sg:postcode":"92677",
    "sg:province":"CA",
    "wof:name":"Queen of Neat",
    "wof:placetype":"venue"
},
  "geometry": {"coordinates":[-117.69747700000001,33.55409],"type":"Point"}
}