{
  "type": "Feature",
  "properties": {
    "addr:full":"8484 Wilshire Blvd Beverly Hills CA 90211",
    "addr:housenumber":"8484",
    "addr:postcode":"90211",
    "addr:street":"Wilshire Blvd",
    "iso:country":"US",
    "sg:address":"8484 Wilshire Blvd",
    "sg:city":"Beverly Hills",
    "sg:classifiers":[
        {
            "category":"Building & Trades",
            "subcategory":"Equipment Rental",
            "type":"Services"
        }
    ],
    "sg:phone":"+1 310 652 2678",
    "sg:postcode":"90211",
    "sg:province":"CA",
    "sg:tags":[
        "leasing",
        "furniture"
    ],
    "wof:name":"Cort Furniture Rental",
    "wof:placetype":"venue"
},
  "geometry": {"coordinates":[-118.37599899999999,34.065201],"type":"Point"}
}