{
  "type": "Feature",
  "properties": {
    "iso:country":"US",
    "sg:address":"1086 Hygeia Ave",
    "sg:city":"Encinitas",
    "sg:classifiers":[
        {
            "category":"Manufacturing",
            "subcategory":"Glass & Minerals",
            "type":"Manufacturing & Wholesale Goods"
        }
    ],
    "sg:phone":"+1 760 942 2002",
    "sg:postcode":"92024",
    "sg:province":"CA",
    "sg:website":"www.blodgettglass.com",
    "wof:name":"Blodgett Glass Inc",
    "wof:placetype":"venue"
},
  "geometry": {"coordinates":[-117.299783,33.068642],"type":"Point"}
}