{
  "type": "Feature",
  "properties": {
    "addr:full":"431 Aurora Dr El Centro CA 92243",
    "addr:housenumber":"431",
    "addr:postcode":"92243",
    "addr:street":"Aurora Dr",
    "iso:country":"US",
    "sg:address":"431 Aurora Dr",
    "sg:city":"El Centro",
    "sg:classifiers":[
        {
            "category":"Health Services",
            "subcategory":"Health Practitioner",
            "type":"Services"
        }
    ],
    "sg:phone":"+1 760 353 9287",
    "sg:postcode":"92243",
    "sg:province":"CA",
    "sg:tags":[
        "therapist",
        "physical"
    ],
    "wof:name":"Central Physical Therapy",
    "wof:placetype":"venue"
},
  "geometry": {"coordinates":[-115.553972,32.778358],"type":"Point"}
}