{
  "type": "Feature",
  "properties": {
    "addr:full":"20700 Avalon Blvd Carson CA 90746",
    "addr:housenumber":"20700",
    "addr:postcode":"90746",
    "addr:street":"Avalon Blvd",
    "iso:country":"US",
    "sg:address":"20700 Avalon Blvd",
    "sg:city":"Carson",
    "sg:classifiers":[
        {
            "category":"Restaurant",
            "type":"Food & Drink"
        }
    ],
    "sg:menulink":"http://www.allmenus.com/ca/compton/239804-panda-express/menu/",
    "sg:phone":"+1 310 327 0357",
    "sg:postcode":"90746",
    "sg:province":"CA",
    "sg:tags":[
        "asian",
        "chinese"
    ],
    "wof:name":"Panda Express",
    "wof:placetype":"venue"
},
  "geometry": {"coordinates":[-118.260518,33.844145],"type":"Point"}
}