{
  "type": "Feature",
  "properties": {
    "iso:country":"US",
    "sg:address":"1298 W 25th St",
    "sg:city":"Upland",
    "sg:classifiers":[
        {
            "category":"Home & Garden",
            "subcategory":"Furniture",
            "type":"Retail Goods"
        }
    ],
    "sg:phone":"+1 909 981 6962",
    "sg:postcode":"91784",
    "sg:province":"CA",
    "wof:name":"Inland Valley Office Furniture",
    "wof:placetype":"venue"
},
  "geometry": {"coordinates":[-117.672183,34.154134],"type":"Point"}
}