{
  "type": "Feature",
  "properties": {
    "iso:country":"US",
    "sg:address":"114 N Oak St",
    "sg:city":"Santa Paula",
    "sg:classifiers":[
        {
            "category":"Food & Beverages",
            "subcategory":"Fruits & Vegetables",
            "type":"Retail Goods"
        }
    ],
    "sg:phone":"+1 805 525 5463",
    "sg:postcode":"93060",
    "sg:province":"CA",
    "sg:tags":[
        "produce"
    ],
    "wof:name":"Rancho Sunset Produce",
    "wof:placetype":"venue"
},
  "geometry": {"coordinates":[-119.057708,34.356363],"type":"Point"}
}