{
  "type": "Feature",
  "properties": {
    "iso:country":"US",
    "sg:address":"219 N Western Ave",
    "sg:city":"Hemet",
    "sg:classifiers":[
        {
            "category":"Building & Trades",
            "subcategory":"Construction",
            "type":"Services"
        }
    ],
    "sg:phone":"+1 951 929 1518",
    "sg:postcode":"92543",
    "sg:province":"CA",
    "sg:tags":[
        "roofing",
        "contractor"
    ],
    "wof:name":"Willie The Roofer Co",
    "wof:placetype":"venue"
},
  "geometry": {"coordinates":[-116.981561,33.749629],"type":"Point"}
}