{
  "type": "Feature",
  "properties": {
    "addr:full":"7415 S Main St Los Angeles CA 90003",
    "addr:housenumber":"7415",
    "addr:postcode":"90003",
    "addr:street":"S Main St",
    "iso:country":"US",
    "sg:address":"7415 S Main St",
    "sg:city":"Los Angeles",
    "sg:classifiers":[
        {
            "category":"Food & Beverages",
            "subcategory":"Groceries & Convenience Stores",
            "type":"Retail Goods"
        }
    ],
    "sg:phone":"+1 323 750 7609",
    "sg:postcode":"90003",
    "sg:province":"CA",
    "sg:tags":[
        "grocer"
    ],
    "wof:name":"Castillo Market",
    "wof:placetype":"venue"
},
  "geometry": {"coordinates":[-118.273994,33.972618],"type":"Point"}
}