{
  "type": "Feature",
  "properties": {
    "addr:full":"3100 E Miraloma Ave Anaheim CA 92806",
    "addr:housenumber":"3100",
    "addr:postcode":"92806",
    "addr:street":"E Miraloma Ave",
    "iso:country":"US",
    "sg:address":"3100 E Miraloma Ave",
    "sg:city":"Anaheim",
    "sg:classifiers":[
        {
            "category":"Banks & Credit Unions",
            "subcategory":"Financial Services",
            "type":"Services"
        }
    ],
    "sg:phone":"+1 714 630 7900",
    "sg:postcode":"92806",
    "sg:province":"CA",
    "sg:tags":[
        "broker",
        "mortgage"
    ],
    "wof:name":"Good News Mortgage Inc",
    "wof:placetype":"venue"
},
  "geometry": {"coordinates":[-117.859769,33.857946],"type":"Point"}
}