{
  "type": "Feature",
  "properties": {
    "iso:country":"US",
    "sg:address":"12220 Perris Blvd",
    "sg:city":"Moreno Valley",
    "sg:classifiers":[
        {
            "category":"Shopping",
            "subcategory":"Musical Instruments",
            "type":"Retail Goods"
        }
    ],
    "sg:phone":"+1 951 924 2455",
    "sg:postcode":"92557",
    "sg:province":"CA",
    "sg:tags":[
        "music",
        "dealer"
    ],
    "wof:name":"High Fidelity",
    "wof:placetype":"venue"
},
  "geometry": {"coordinates":[-117.226318,33.946222],"type":"Point"}
}