{
  "type": "Feature",
  "properties": {
    "iso:country":"US",
    "sg:address":"3940 Rosedale Hwy",
    "sg:city":"Bakersfield",
    "sg:classifiers":[
        {
            "category":"Wholesale",
            "subcategory":"Petroleum",
            "type":"Manufacturing & Wholesale Goods"
        }
    ],
    "sg:phone":"+1 661 327 7212",
    "sg:postcode":"93308",
    "sg:province":"CA",
    "sg:tags":[
        "bulk",
        "oil",
        "gasoline"
    ],
    "sg:website":"www.sunvalleyoil.com",
    "wof:name":"C L Bryant Inc",
    "wof:placetype":"venue"
},
  "geometry": {"coordinates":[-119.049018,35.3833],"type":"Point"}
}