{
  "type": "Feature",
  "properties": {
    "iso:country":"US",
    "sg:address":"7300 Bancroft Ave",
    "sg:city":"Oakland",
    "sg:classifiers":[
        {
            "category":"Restaurant",
            "type":"Food & Drink"
        }
    ],
    "sg:phone":"+1 510 430 9688",
    "sg:postcode":"94605",
    "sg:province":"CA",
    "wof:name":"Eastmont Hero",
    "wof:placetype":"venue"
},
  "geometry": {"coordinates":[-122.175698,37.764939],"type":"Point"}
}