{
  "type": "Feature",
  "properties": {
    "addr:full":"5814 Van Allen Way # 175 Carlsbad CA 92008",
    "addr:housenumber":"5814",
    "addr:postcode":"92008",
    "addr:street":"Van Allen Way # 175",
    "iso:country":"US",
    "sg:address":"5814 Van Allen Way # 175",
    "sg:city":"Carlsbad",
    "sg:classifiers":[
        {
            "category":"Communications",
            "subcategory":"Newspaper",
            "type":"Services"
        }
    ],
    "sg:phone":"+1 760 931 0226",
    "sg:postcode":"92008",
    "sg:province":"CA",
    "wof:name":"Postal Annex Plus",
    "wof:placetype":"venue"
},
  "geometry": {"coordinates":[-117.287582,33.136204],"type":"Point"}
}