{
  "type": "Feature",
  "properties": {
    "addr:full":"1500 41st Avenue, Suite 260 Capitola CA 95010",
    "addr:housenumber":"1500",
    "addr:postcode":"95010",
    "addr:street":"41St Avenue Suite 260",
    "iso:country":"US",
    "sg:address":"1500 41st Avenue, Suite 260",
    "sg:city":"Capitola",
    "sg:phone":"+1 831 435 6118",
    "sg:postcode":"95010",
    "sg:province":"CA",
    "sg:website":"http://FIELDFRESHFLOWERS.COM",
    "wof:name":"Capitola Blooming Flowers",
    "wof:placetype":"venue"
},
  "geometry": {"coordinates":[-121.964859,36.971787],"type":"Point"}
}