{
  "type": "Feature",
  "properties": {
    "iso:country":"US",
    "sg:address":"3318 San Leandro St",
    "sg:city":"Oakland",
    "sg:classifiers":[
        {
            "category":"Retail",
            "subcategory":"Auto Repair",
            "type":"Services"
        }
    ],
    "sg:phone":"+1 510 536 2970",
    "sg:postcode":"94601",
    "sg:province":"CA",
    "wof:name":"Ben's Auto",
    "wof:placetype":"venue"
},
  "geometry": {"coordinates":[-122.225998,37.774601],"type":"Point"}
}