{
  "type": "Feature",
  "properties": {
    "addr:full":"2435 California St San Francisco CA 94115",
    "addr:housenumber":"2435",
    "addr:postcode":"94115",
    "addr:street":"California St",
    "iso:country":"US",
    "sg:address":"2435 California St",
    "sg:city":"San Francisco",
    "sg:classifiers":[
        {
            "category":"Coffee & Tea",
            "type":"Food & Drink"
        }
    ],
    "sg:menulink":"http://www.allmenus.com/ca/san-francisco/117202-starbucks-coffee/menu/",
    "sg:phone":"+1 415 567 3978",
    "sg:postcode":"94115",
    "sg:province":"CA",
    "sg:tags":[
        "american"
    ],
    "wof:name":"Starbucks Coffee",
    "wof:placetype":"venue"
},
  "geometry": {"coordinates":[-122.43481199999999,37.788469],"type":"Point"}
}