{
  "type": "Feature",
  "properties": {
    "iso:country":"US",
    "sg:address":"6234 San Fernando Rd",
    "sg:city":"Glendale",
    "sg:classifiers":[
        {
            "category":"Retail",
            "subcategory":"Auto Repair",
            "type":"Services"
        }
    ],
    "sg:phone":"+1 818 246 2900",
    "sg:postcode":"91201",
    "sg:province":"CA",
    "wof:name":"Glendale British & European Motor Works",
    "wof:placetype":"venue"
},
  "geometry": {"coordinates":[-118.285004,34.164001],"type":"Point"}
}