{
  "type": "Feature",
  "properties": {
    "addr:full":"4095 Foothill Blvd Oakland CA 94601",
    "addr:housenumber":"4095",
    "addr:postcode":"94601",
    "addr:street":"Foothill Blvd",
    "iso:country":"US",
    "sg:address":"4095 Foothill Blvd",
    "sg:city":"Oakland",
    "sg:classifiers":[
        {
            "category":"Food & Beverages",
            "subcategory":"Meat & Fish",
            "type":"Retail Goods"
        }
    ],
    "sg:phone":"+1 510 536 5097",
    "sg:postcode":"94601",
    "sg:province":"CA",
    "sg:tags":[
        "shop"
    ],
    "wof:name":"El Paracho Carniceria",
    "wof:placetype":"venue"
},
  "geometry": {"coordinates":[-122.21399700000001,37.776798],"type":"Point"}
}