{
  "type": "Feature",
  "properties": {
    "iso:country":"US",
    "sg:address":"1057 MacArthur Boulevard",
    "sg:city":"San Leandro",
    "sg:classifiers":[
        {
            "category":"Coffee & Tea",
            "type":"Food & Drink"
        }
    ],
    "sg:phone":"+1 510 633 3045",
    "sg:postcode":"94577",
    "sg:province":"CA",
    "wof:name":"Starbucks",
    "wof:placetype":"venue"
},
  "geometry": {"coordinates":[-122.139999,37.7332],"type":"Point"}
}