{
  "type": "Feature",
  "properties": {
    "addr:full":"1801 Wilshire Blvd Los Angeles CA 90057",
    "addr:housenumber":"1801",
    "addr:postcode":"90057",
    "addr:street":"Wilshire Blvd",
    "iso:country":"US",
    "sg:address":"1801 Wilshire Blvd",
    "sg:city":"Los Angeles",
    "sg:classifiers":[
        {
            "category":"Professional",
            "subcategory":"Business Services",
            "type":"Services"
        }
    ],
    "sg:phone":"+1 213 353 0999",
    "sg:postcode":"90057",
    "sg:province":"CA",
    "sg:tags":[
        "arbitration"
    ],
    "sg:website":"www.christiantv.com",
    "wof:name":"CHRISTIANTV.COM",
    "wof:placetype":"venue"
},
  "geometry": {"coordinates":[-118.273591,34.056896],"type":"Point"}
}