{
  "type": "Feature",
  "properties": {
    "addr:full":"626 Irving Dr Burbank CA 91504",
    "addr:housenumber":"626",
    "addr:postcode":"91504",
    "addr:street":"Irving Dr",
    "iso:country":"US",
    "sg:address":"626 Irving Dr",
    "sg:city":"Burbank",
    "sg:classifiers":[
        {
            "category":"Building & Trades",
            "subcategory":"Construction",
            "type":"Services"
        }
    ],
    "sg:phone":"+1 818 972 2807",
    "sg:postcode":"91504",
    "sg:province":"CA",
    "sg:tags":[
        "painter"
    ],
    "wof:name":"David Painting & Maintenance",
    "wof:placetype":"venue"
},
  "geometry": {"coordinates":[-118.32384500000001,34.204056],"type":"Point"}
}