{
  "type": "Feature",
  "properties": {
    "addr:full":"5570 Marquet Ct Yorba Linda CA 92887",
    "addr:postcode":"5570;92887",
    "addr:street":"Marquet Ct",
    "iso:country":"US",
    "sg:address":"5570 Marquet Ct",
    "sg:city":"Yorba Linda",
    "sg:classifiers":[
        {
            "category":"Wholesale",
            "subcategory":"Sporting Goods",
            "type":"Manufacturing & Wholesale Goods"
        }
    ],
    "sg:phone":"+1 714 692 0440",
    "sg:postcode":"92887",
    "sg:province":"CA",
    "wof:name":"Fore Sport",
    "wof:placetype":"venue"
},
  "geometry": {"coordinates":[-117.709507,33.87879],"type":"Point"}
}