{
  "type": "Feature",
  "properties": {
    "addr:full":"1000 N Bristol St Newport Beach CA 92660",
    "addr:housenumber":"1000",
    "addr:postcode":"92660",
    "addr:street":"N Bristol St",
    "iso:country":"US",
    "sg:address":"1000 N Bristol St",
    "sg:city":"Newport Beach",
    "sg:classifiers":[
        {
            "category":"Shopping",
            "subcategory":"Florist",
            "type":"Retail Goods"
        }
    ],
    "sg:phone":"+1 949 252 8499",
    "sg:postcode":"92660",
    "sg:province":"CA",
    "wof:name":"Chris Lindsey Designs",
    "wof:placetype":"venue"
},
  "geometry": {"coordinates":[-117.86592,33.656816],"type":"Point"}
}