{
  "type": "Feature",
  "properties": {
    "iso:country":"US",
    "sg:address":"471 W George St",
    "sg:city":"Banning",
    "sg:classifiers":[
        {
            "category":"Animal Shelter",
            "type":"Public Place"
        },
        {
            "category":"Shopping",
            "subcategory":"Pets & Pet Supplies",
            "type":"Retail Goods"
        }
    ],
    "sg:phone":"+1 951 769 8773",
    "sg:postcode":"92220",
    "sg:province":"CA",
    "sg:tags":[
        "store"
    ],
    "wof:name":"Tender Loving Critters Animal Rescue",
    "wof:placetype":"venue"
},
  "geometry": {"coordinates":[-116.881958,33.930937],"type":"Point"}
}