{
  "type": "Feature",
  "properties": {
    "addr:full":"416 The Terrace Redlands CA 92374",
    "addr:housenumber":"416",
    "addr:postcode":"92374",
    "addr:street":"The Terrace",
    "iso:country":"US",
    "sg:address":"416 The Terrace",
    "sg:city":"Redlands",
    "sg:classifiers":[
        {
            "category":"Real Estate",
            "subcategory":"Real Estate Operator",
            "type":"Services"
        }
    ],
    "sg:phone":"+1 909 792 0105",
    "sg:postcode":"92374",
    "sg:province":"CA",
    "sg:tags":[
        "apartment"
    ],
    "wof:name":"Park Magnolia",
    "wof:placetype":"venue"
},
  "geometry": {"coordinates":[-117.177958,34.246935],"type":"Point"}
}