{
  "type": "Feature",
  "properties": {
    "addr:full":"2017 E 4th St Long Beach CA 90814",
    "addr:housenumber":"2017",
    "addr:postcode":"90814",
    "addr:street":"E 4Th St",
    "iso:country":"US",
    "sg:address":"2017 E 4th St",
    "sg:city":"Long Beach",
    "sg:classifiers":[
        {
            "category":"Social Services",
            "type":"Services"
        }
    ],
    "sg:phone":"+1 562 434 4455",
    "sg:postcode":"90814",
    "sg:province":"CA",
    "sg:tags":[
        "organization",
        "welfare"
    ],
    "wof:name":"Gay & Lesbian Community Svc",
    "wof:placetype":"venue"
},
  "geometry": {"coordinates":[-118.16677,33.771768],"type":"Point"}
}