{
  "type": "Feature",
  "properties": {
    "iso:country":"US",
    "sg:address":"9219 Trailhead Pt",
    "sg:city":"Riverside",
    "sg:classifiers":[
        {
            "category":"Real Estate",
            "subcategory":"Real Estate Agent",
            "type":"Services"
        }
    ],
    "sg:phone":"+1 951 360 9421",
    "sg:postcode":"92509",
    "sg:province":"CA",
    "sg:website":"www.jacksonrivero.com",
    "wof:name":"Jackson Rivero Realty",
    "wof:placetype":"venue"
},
  "geometry": {"coordinates":[-117.48527799999999,33.982172],"type":"Point"}
}