{
  "type": "Feature",
  "properties": {
    "addr:full":"100 Lake Ave Piedmont CA 94611",
    "addr:housenumber":"100",
    "addr:postcode":"94611",
    "addr:street":"Lake Ave",
    "iso:country":"US",
    "sg:address":"100 Lake Ave",
    "sg:city":"Piedmont",
    "sg:classifiers":[
        {
            "category":"Education",
            "subcategory":"School",
            "type":"Public Place"
        }
    ],
    "sg:phone":"+1 510 594 2686",
    "sg:postcode":"94611",
    "sg:province":"CA",
    "sg:tags":[
        "high",
        "middle",
        "elementary"
    ],
    "wof:name":"Piedmont Unified School District",
    "wof:placetype":"venue"
},
  "geometry": {"coordinates":[-122.247058,37.824103],"type":"Point"}
}