{
  "type": "Feature",
  "properties": {
    "iso:country":"US",
    "sg:address":"647 Cam de Los Mares",
    "sg:city":"San Clemente",
    "sg:classifiers":[
        {
            "category":"Banks & Credit Unions",
            "subcategory":"Investment Brokerage",
            "type":"Services"
        }
    ],
    "sg:phone":"+1 949 489 1112",
    "sg:postcode":"92673",
    "sg:province":"CA",
    "sg:tags":[
        "advisory",
        "financial"
    ],
    "wof:name":"RGH Financial",
    "wof:placetype":"venue"
},
  "geometry": {"coordinates":[-117.647156,33.457026],"type":"Point"}
}