{
  "type": "Feature",
  "properties": {
    "iso:country":"US",
    "sg:address":"126 S 10th Ave",
    "sg:city":"Hanford",
    "sg:classifiers":[
        {
            "category":"Organizations",
            "subcategory":"Professional Association",
            "type":"Services"
        }
    ],
    "sg:phone":"+1 559 582 6780",
    "sg:postcode":"93230",
    "sg:province":"CA",
    "wof:name":"King's County Dairy Herd",
    "wof:placetype":"venue"
},
  "geometry": {"coordinates":[-119.637084,36.327585],"type":"Point"}
}