{
  "type": "Feature",
  "properties": {
    "addr:full":"30825 Wiegman Rd Hayward CA 94544",
    "addr:postcode":"30825;94544",
    "addr:street":"Wiegman Rd",
    "iso:country":"US",
    "sg:address":"30825 Wiegman Rd",
    "sg:city":"Hayward",
    "sg:classifiers":[
        {
            "category":"Professional",
            "type":"Services"
        }
    ],
    "sg:phone":"+1 510 476 5201",
    "sg:postcode":"94544",
    "sg:province":"CA",
    "sg:tags":[
        "establishment"
    ],
    "wof:name":"Mcwilliams Hanwood Estate",
    "wof:placetype":"venue"
},
  "geometry": {"coordinates":[-122.061359,37.613504],"type":"Point"}
}