{
  "type": "Feature",
  "properties": {
    "iso:country":"US",
    "sg:address":"4800 Patrick Henry Dr",
    "sg:city":"Santa Clara",
    "sg:classifiers":[
        {
            "category":"Professional",
            "type":"Services"
        },
        {
            "category":"Personal",
            "type":"Services"
        }
    ],
    "sg:phone":"+1 888 839 7233",
    "sg:postcode":"95054",
    "sg:province":"CA",
    "sg:tags":[
        "local"
    ],
    "sg:website":"www.allsafemove.com",
    "wof:name":"All Safe Move",
    "wof:placetype":"venue"
},
  "geometry": {"coordinates":[-121.985754,37.400287],"type":"Point"}
}