{
  "type": "Feature",
  "properties": {
    "addr:full":"10152 Barbara Ln Cupertino CA 95014",
    "addr:housenumber":"10152",
    "addr:postcode":"95014",
    "addr:street":"Barbara Ln",
    "iso:country":"US",
    "sg:address":"10152 Barbara Ln",
    "sg:city":"Cupertino",
    "sg:classifiers":[
        {
            "category":"Real Estate",
            "subcategory":"Real Estate Services",
            "type":"Services"
        },
        {
            "category":"Real Estate",
            "subcategory":"Real Estate Agent",
            "type":"Services"
        }
    ],
    "sg:phone":"+1 408 257 0495",
    "sg:postcode":"95014",
    "sg:province":"CA",
    "sg:tags":[
        "buyer",
        "broker"
    ],
    "wof:name":"James Chung Realtor",
    "wof:placetype":"venue"
},
  "geometry": {"coordinates":[-122.038769,37.320775],"type":"Point"}
}