{
  "type": "Feature",
  "properties": {
    "iso:country":"US",
    "sg:address":"622 S Harbor Blvd",
    "sg:city":"Santa Ana",
    "sg:classifiers":[
        {
            "category":"Wholesale",
            "subcategory":"Groceries",
            "type":"Manufacturing & Wholesale Goods"
        }
    ],
    "sg:phone":"+1 714 531 5524",
    "sg:postcode":"92704",
    "sg:province":"CA",
    "wof:name":"Jugos La Tropicana",
    "wof:placetype":"venue"
},
  "geometry": {"coordinates":[-117.920187,33.739091],"type":"Point"}
}