{
  "type": "Feature",
  "properties": {
    "addr:full":"12 Rancho Cir Lake Forest CA 92630",
    "addr:housenumber":"12",
    "addr:postcode":"92630",
    "addr:street":"Rancho Cir",
    "iso:country":"US",
    "sg:address":"12 Rancho Cir",
    "sg:city":"Lake Forest",
    "sg:classifiers":[
        {
            "category":"Building & Trades",
            "subcategory":"Construction",
            "type":"Services"
        }
    ],
    "sg:phone":"+1 949 716 2665",
    "sg:postcode":"92630",
    "sg:province":"CA",
    "sg:tags":[
        "contractor"
    ],
    "wof:name":"Enhanced Living Design",
    "wof:placetype":"venue"
},
  "geometry": {"coordinates":[-117.668319,33.673988],"type":"Point"}
}