{
  "type": "Feature",
  "properties": {
    "iso:country":"US",
    "sg:address":"2991 Shattuck Ave Ste 200",
    "sg:city":"Berkeley",
    "sg:classifiers":[
        {
            "category":"Professional",
            "subcategory":"Lawyer & Legal Services",
            "type":"Services"
        },
        {
            "category":"Professional",
            "subcategory":"Art Services",
            "type":"Services"
        }
    ],
    "sg:phone":"+1 510 644 3490",
    "sg:postcode":"94705",
    "sg:province":"CA",
    "sg:tags":[
        "notary",
        "graphic",
        "design"
    ],
    "sg:website":"www.avantext-usa.com",
    "wof:name":"Avantext Translations",
    "wof:placetype":"venue"
},
  "geometry": {"coordinates":[-122.266482,37.855359],"type":"Point"}
}