{
  "type": "Feature",
  "properties": {
    "iso:country":"US",
    "sg:address":"226 Market St",
    "sg:city":"Galt",
    "sg:classifiers":[
        {
            "category":"Personal",
            "type":"Services"
        }
    ],
    "sg:phone":"+1 209 744 0705",
    "sg:postcode":"95632",
    "sg:province":"CA",
    "sg:tags":[
        "electrolysis"
    ],
    "wof:name":"Teresa L Pearson",
    "wof:placetype":"venue"
},
  "geometry": {"coordinates":[-121.299656,38.253105],"type":"Point"}
}