{
  "type": "Feature",
  "properties": {
    "iso:country":"US",
    "sg:address":"1 Pirates Cove",
    "sg:city":"Oceanside",
    "sg:classifiers":[
        {
            "category":"Place Of Worship",
            "subcategory":"Church",
            "type":"Public Place"
        }
    ],
    "sg:phone":"+1 253 686 2129",
    "sg:postcode":"92054",
    "sg:province":"CA",
    "sg:website":"www.missiong12.com",
    "wof:name":"Mission Church",
    "wof:placetype":"venue"
},
  "geometry": {"coordinates":[-117.37365699999999,33.199276],"type":"Point"}
}