{
  "type": "Feature",
  "properties": {
    "iso:country":"US",
    "sg:address":"7548 Garvey Ave",
    "sg:city":"Rosemead",
    "sg:classifiers":[
        {
            "category":"Health Services",
            "subcategory":"Health Practitioner",
            "type":"Services"
        }
    ],
    "sg:phone":"+1 626 572 4103",
    "sg:postcode":"91770",
    "sg:province":"CA",
    "sg:tags":[
        "acupuncture"
    ],
    "wof:name":"F K Medical Group",
    "wof:placetype":"venue"
},
  "geometry": {"coordinates":[-118.103996,34.0625],"type":"Point"}
}