{
  "type": "Feature",
  "properties": {
    "iso:country":"US",
    "sg:address":"710 Main St",
    "sg:city":"Huntington Beach",
    "sg:classifiers":[
        {
            "category":"Banks & Credit Unions",
            "subcategory":"Bank",
            "type":"Services"
        }
    ],
    "sg:phone":"+1 714 374 0491",
    "sg:postcode":"92648",
    "sg:province":"CA",
    "sg:tags":[
        "loan"
    ],
    "wof:name":"American Home Loans",
    "wof:placetype":"venue"
},
  "geometry": {"coordinates":[-117.99969299999999,33.666031],"type":"Point"}
}