{
  "type": "Feature",
  "properties": {
    "addr:full":"74180 Hwy 111 Palm Desert CA 92260",
    "addr:housenumber":"74180",
    "addr:postcode":"ca 92260",
    "addr:street":"Hwy 111",
    "iso:country":"US",
    "sg:address":"74180 Hwy 111",
    "sg:city":"Palm Desert",
    "sg:classifiers":[
        {
            "category":"Retail",
            "subcategory":"Auto Repair",
            "type":"Services"
        }
    ],
    "sg:phone":"+1 760 776 7570",
    "sg:postcode":"92260",
    "sg:province":"CA",
    "wof:name":"Fastlane Auto Care",
    "wof:placetype":"venue"
},
  "geometry": {"coordinates":[-116.37051700000001,33.721775],"type":"Point"}
}