{
  "type": "Feature",
  "properties": {
    "iso:country":"US",
    "sg:address":"660 E Palm St",
    "sg:city":"Altadena",
    "sg:classifiers":[
        {
            "category":"Professional",
            "subcategory":"Computer Services",
            "type":"Services"
        }
    ],
    "sg:phone":"+1 626 791 5537",
    "sg:postcode":"91001",
    "sg:province":"CA",
    "sg:tags":[
        "isp",
        "provider",
        "internet"
    ],
    "wof:name":"Pete Carah dba Altadena Internet",
    "wof:placetype":"venue"
},
  "geometry": {"coordinates":[-118.133421,34.192874],"type":"Point"}
}