{
  "type": "Feature",
  "properties": {
    "iso:country":"US",
    "sg:address":"17745 Sherman Way",
    "sg:city":"Reseda",
    "sg:classifiers":[
        {
            "category":"Shopping",
            "subcategory":"Books",
            "type":"Retail Goods"
        }
    ],
    "sg:phone":"+1 818 758 9005",
    "sg:postcode":"91335",
    "sg:province":"CA",
    "wof:name":"Alpha Y Omega",
    "wof:placetype":"venue"
},
  "geometry": {"coordinates":[-118.520582,34.201089],"type":"Point"}
}