{
  "type": "Feature",
  "properties": {
    "iso:country":"US",
    "sg:address":"2100 Riverside Drive",
    "sg:city":"Burbank",
    "sg:classifiers":[
        {
            "category":"Coffee & Tea",
            "type":"Food & Drink"
        }
    ],
    "sg:postcode":"91521",
    "sg:province":"CA",
    "wof:name":"The Caffeine Patch",
    "wof:placetype":"venue"
},
  "geometry": {"coordinates":[-118.323784,34.155657],"type":"Point"}
}