{
  "type": "Feature",
  "properties": {
    "iso:country":"US",
    "sg:address":"231 Pomeroy Ave",
    "sg:city":"Pismo Beach",
    "sg:classifiers":[
        {
            "category":"Shopping",
            "type":"Retail Goods"
        }
    ],
    "sg:phone":"+1 805 773 1144",
    "sg:postcode":"93449",
    "sg:province":"CA",
    "sg:tags":[
        "art",
        "gallery",
        "dealer"
    ],
    "wof:name":"Seaside Gallery II",
    "wof:placetype":"venue"
},
  "geometry": {"coordinates":[-120.641612,35.140492],"type":"Point"}
}