{
  "type": "Feature",
  "properties": {
    "iso:country":"US",
    "sg:address":"15801 Quartz Valley Rd",
    "sg:city":"Fort Jones",
    "sg:classifiers":[
        {
            "category":"Farming",
            "subcategory":"Livestock Farm",
            "type":"Manufacturing & Wholesale Goods"
        }
    ],
    "sg:phone":"+1 530 468 2929",
    "sg:postcode":"96032",
    "sg:province":"CA",
    "sg:tags":[
        "feedlot",
        "field",
        "crop",
        "beef",
        "cattle"
    ],
    "wof:name":"B M Burton Son",
    "wof:placetype":"venue"
},
  "geometry": {"coordinates":[-122.972798,41.624079],"type":"Point"}
}