{
  "type": "Feature",
  "properties": {
    "iso:country":"US",
    "sg:address":"903 Pine St",
    "sg:city":"San Francisco",
    "sg:classifiers":[
        {
            "category":"Real Estate",
            "subcategory":"Real Estate Operator",
            "type":"Services"
        }
    ],
    "sg:phone":"+1 415 474 3449",
    "sg:postcode":"94108",
    "sg:province":"CA",
    "sg:tags":[
        "apartment"
    ],
    "wof:name":"Pine Street Apartments",
    "wof:placetype":"venue"
},
  "geometry": {"coordinates":[-122.410956,37.790764],"type":"Point"}
}