{
  "type": "Feature",
  "properties": {
    "iso:country":"US",
    "sg:address":"157 N Garfield Ave",
    "sg:city":"Alhambra",
    "sg:classifiers":[
        {
            "category":"Health Services",
            "subcategory":"Doctor",
            "type":"Services"
        }
    ],
    "sg:phone":"+1 626 284 5113",
    "sg:postcode":"91801",
    "sg:province":"CA",
    "sg:tags":[
        "surgeon",
        "oral"
    ],
    "wof:name":"Lee Hart H DDS",
    "wof:placetype":"venue"
},
  "geometry": {"coordinates":[-118.12799800000001,34.0965],"type":"Point"}
}