{
  "type": "Feature",
  "properties": {
    "iso:country":"US",
    "sg:address":"1660 N Hobart Blvd",
    "sg:city":"Los Angeles",
    "sg:classifiers":[
        {
            "category":"Health Services",
            "subcategory":"Medical Lab",
            "type":"Services"
        }
    ],
    "sg:phone":"+1 323 469 2728",
    "sg:postcode":"90027",
    "sg:province":"CA",
    "sg:tags":[
        "laboratory"
    ],
    "sg:website":"www.hollywood-dental.com",
    "wof:name":"Hollywood Dental Lab",
    "wof:placetype":"venue"
},
  "geometry": {"coordinates":[-118.305553,34.098808],"type":"Point"}
}