{
  "type": "Feature",
  "properties": {
    "addr:full":"6541 Hollywood Blvd Los Angeles CA 90028",
    "addr:housenumber":"6541",
    "addr:postcode":"90028",
    "addr:street":"Hollywood Blvd",
    "iso:country":"US",
    "sg:address":"6541 Hollywood Blvd",
    "sg:city":"Los Angeles",
    "sg:classifiers":[
        {
            "category":"Shopping",
            "type":"Retail Goods"
        }
    ],
    "sg:phone":"+1 323 461 1012",
    "sg:postcode":"90028",
    "sg:province":"CA",
    "sg:tags":[
        "merchandise"
    ],
    "wof:name":"Frame Art Frame",
    "wof:placetype":"venue"
},
  "geometry": {"coordinates":[-118.333208,34.101655],"type":"Point"}
}