{
  "type": "Feature",
  "properties": {
    "addr:full":"8891 Mission Blvd Riverside CA 92509",
    "addr:housenumber":"8891",
    "addr:postcode":"92509",
    "addr:street":"Mission Blvd",
    "iso:country":"US",
    "sg:address":"8891 Mission Blvd",
    "sg:city":"Riverside",
    "sg:classifiers":[
        {
            "category":"Real Estate",
            "subcategory":"Architect",
            "type":"Services"
        },
        {
            "category":"Building & Trades",
            "subcategory":"Construction",
            "type":"Services"
        }
    ],
    "sg:phone":"+1 951 360 2120",
    "sg:postcode":"92509",
    "sg:province":"CA",
    "sg:tags":[
        "roofing",
        "estimate",
        "contractor"
    ],
    "wof:name":"California Construction & Rfng",
    "wof:placetype":"venue"
},
  "geometry": {"coordinates":[-117.47773599999999,34.011882],"type":"Point"}
}