{
  "type": "Feature",
  "properties": {
    "addr:full":"1755 Market Street San Francisco CA 94103",
    "addr:housenumber":"1755",
    "addr:postcode":"94103",
    "addr:street":"Market Street",
    "iso:country":"US",
    "sg:address":"1755 Market Street",
    "sg:city":"San Francisco",
    "sg:classifiers":[
        {
            "category":"Personal",
            "subcategory":"Piercing",
            "type":"Services"
        }
    ],
    "sg:phone":"+1 415 553 7771",
    "sg:postcode":"94103",
    "sg:province":"CA",
    "sg:website":"www.nomadsf.com",
    "wof:name":"Nomad Body Piercing",
    "wof:placetype":"venue"
},
  "geometry": {"coordinates":[-122.42290300000001,37.771862],"type":"Point"}
}