{
  "type": "Feature",
  "properties": {
    "addr:full":"980 I St Arcata CA 95521",
    "addr:housenumber":"980",
    "addr:postcode":"95521",
    "addr:street":"I St",
    "iso:country":"US",
    "sg:address":"980 I St",
    "sg:city":"Arcata",
    "sg:classifiers":[
        {
            "category":"Health Services",
            "subcategory":"Health Practitioner",
            "type":"Services"
        }
    ],
    "sg:phone":"+1 707 822 7525",
    "sg:postcode":"95521",
    "sg:province":"CA",
    "sg:tags":[
        "occupational",
        "therapist"
    ],
    "wof:name":"Hand Therapy Ctr",
    "wof:placetype":"venue"
},
  "geometry": {"coordinates":[-124.087658,40.869371],"type":"Point"}
}