{
  "type": "Feature",
  "properties": {
    "addr:full":"13421 Benson Ave Chino CA 91710",
    "addr:housenumber":"13421",
    "addr:postcode":"91710",
    "addr:street":"Benson Ave",
    "iso:country":"US",
    "sg:address":"13421 Benson Ave",
    "sg:city":"Chino",
    "sg:classifiers":[
        {
            "category":"Building & Trades",
            "subcategory":"Construction",
            "type":"Services"
        }
    ],
    "sg:phone":"+1 909 548 7924",
    "sg:postcode":"91710",
    "sg:province":"CA",
    "sg:tags":[
        "woodworker"
    ],
    "wof:name":"ACTION Saw & Abrasive Products",
    "wof:placetype":"venue"
},
  "geometry": {"coordinates":[-117.680431,34.011257],"type":"Point"}
}