{
  "type": "Feature",
  "properties": {
    "addr:full":"13447 Telegraph Rd Whittier CA 90605",
    "addr:housenumber":"13447",
    "addr:postcode":"90605",
    "addr:street":"Telegraph Rd",
    "iso:country":"US",
    "sg:address":"13447 Telegraph Rd",
    "sg:city":"Whittier",
    "sg:classifiers":[
        {
            "category":"Shopping",
            "subcategory":"Tobacco",
            "type":"Retail Goods"
        }
    ],
    "sg:phone":"+1 562 941 9730",
    "sg:postcode":"90605",
    "sg:province":"CA",
    "sg:tags":[
        "shop",
        "cigarette",
        "cigar"
    ],
    "wof:name":"Whittier Smoke Shop",
    "wof:placetype":"venue"
},
  "geometry": {"coordinates":[-118.04482400000001,33.939225],"type":"Point"}
}