{
  "type": "Feature",
  "properties": {
    "iso:country":"US",
    "sg:address":"303 Primrose Rd.",
    "sg:city":"Burlingame",
    "sg:classifiers":[
        {
            "category":"Shopping",
            "subcategory":"Clothing, Apparel, & Fashions",
            "type":"Retail Goods"
        },
        {
            "category":"Sports & Exercise",
            "subcategory":"Bicycle Rental",
            "type":"Entertainment"
        }
    ],
    "sg:phone":"+1 650 685 6677",
    "sg:postcode":"94010",
    "sg:province":"CA",
    "sg:tags":[
        "wear",
        "accessory"
    ],
    "wof:name":"Domez",
    "wof:placetype":"venue"
},
  "geometry": {"coordinates":[-122.34819400000001,37.577918],"type":"Point"}
}