{
  "type": "Feature",
  "properties": {
    "addr:full":"6200 E Spring St Ste D Long Beach CA 90815",
    "addr:housenumber":"6200",
    "addr:postcode":"90815",
    "addr:street":"E Spring St Ste D",
    "iso:country":"US",
    "sg:address":"6200 E Spring St Ste D",
    "sg:city":"Long Beach",
    "sg:classifiers":[
        {
            "category":"Real Estate",
            "subcategory":"Real Estate Services",
            "type":"Services"
        }
    ],
    "sg:phone":"+1 562 425 1979",
    "sg:postcode":"90815",
    "sg:province":"CA",
    "sg:tags":[
        "management",
        "property"
    ],
    "wof:name":"Contemporary Property Management Inc",
    "wof:placetype":"venue"
},
  "geometry": {"coordinates":[-118.111,33.810398],"type":"Point"}
}