{
  "type": "Feature",
  "properties": {
    "iso:country":"US",
    "sg:address":"1124 Maple Ave",
    "sg:city":"Los Angeles",
    "sg:classifiers":[
        {
            "category":"Shopping",
            "subcategory":"Clothing, Apparel, & Fashions",
            "type":"Retail Goods"
        }
    ],
    "sg:phone":"+1 213 747 3754",
    "sg:postcode":"90015",
    "sg:province":"CA",
    "sg:tags":[
        "clothing",
        "women's"
    ],
    "wof:name":"Song's Fashion",
    "wof:placetype":"venue"
},
  "geometry": {"coordinates":[-118.254997,34.0369],"type":"Point"}
}