{
  "type": "Feature",
  "properties": {
    "iso:country":"US",
    "sg:address":"600 Central Ave",
    "sg:city":"Riverside",
    "sg:classifiers":[
        {
            "category":"Professional",
            "type":"Services"
        }
    ],
    "sg:phone":"+1 951 684 5896",
    "sg:postcode":"92507",
    "sg:province":"CA",
    "sg:tags":[
        "establishment"
    ],
    "wof:name":"Austin William Co",
    "wof:placetype":"venue"
},
  "geometry": {"coordinates":[-117.32684500000001,33.955066],"type":"Point"}
}