{
  "type": "Feature",
  "properties": {
    "iso:country":"US",
    "sg:address":"2999 San Ysidro Way",
    "sg:city":"Santa Clara",
    "sg:classifiers":[
        {
            "category":"Banks & Credit Unions",
            "subcategory":"Bank",
            "type":"Services"
        }
    ],
    "sg:phone":"+1 888 672 6073",
    "sg:postcode":"95051",
    "sg:province":"CA",
    "sg:website":"www.national1st.org",
    "wof:name":"National 1st Credit Union",
    "wof:placetype":"venue"
},
  "geometry": {"coordinates":[-121.99769999999999,37.376072],"type":"Point"}
}