{
  "type": "Feature",
  "properties": {
    "iso:country":"US",
    "sg:address":"1121 Harbor Blvd.",
    "sg:city":"Fullerton",
    "sg:classifiers":[
        {
            "category":"Food & Beverages",
            "subcategory":"Groceries & Convenience Stores",
            "type":"Retail Goods"
        }
    ],
    "sg:phone":"+1 714 992 2590",
    "sg:postcode":"92832",
    "sg:province":"CA",
    "sg:website":"ralphs.com",
    "wof:name":"Ralphs",
    "wof:placetype":"venue"
},
  "geometry": {"coordinates":[-117.924629,33.88092],"type":"Point"}
}