{
  "type": "Feature",
  "properties": {
    "addr:full":"350 30th St Oakland CA 94609",
    "addr:housenumber":"350",
    "addr:postcode":"94609",
    "addr:street":"30Th St",
    "iso:country":"US",
    "sg:address":"350 30th St",
    "sg:city":"Oakland",
    "sg:classifiers":[
        {
            "category":"Health Services",
            "subcategory":"Doctor",
            "type":"Services"
        }
    ],
    "sg:phone":"+1 510 204 8290",
    "sg:postcode":"94609",
    "sg:province":"CA",
    "wof:name":"Tucker Harris Shirley MD",
    "wof:placetype":"venue"
},
  "geometry": {"coordinates":[-122.263053,37.81888],"type":"Point"}
}