{
  "type": "Feature",
  "properties": {
    "iso:country":"US",
    "sg:address":"5637 Glen Oaks Dr",
    "sg:city":"Rocklin",
    "sg:classifiers":[
        {
            "category":"Manufacturing",
            "subcategory":"Printing",
            "type":"Manufacturing & Wholesale Goods"
        }
    ],
    "sg:phone":"+1 916 315 8451",
    "sg:postcode":"95765",
    "sg:province":"CA",
    "sg:tags":[
        "publishing"
    ],
    "wof:name":"Tahoemap Publications",
    "wof:placetype":"venue"
},
  "geometry": {"coordinates":[-121.264594,38.805171],"type":"Point"}
}