{
  "type": "Feature",
  "properties": {
    "iso:country":"US",
    "sg:address":"5200 Irvine Blvd",
    "sg:city":"Irvine",
    "sg:classifiers":[
        {
            "category":"Shopping",
            "subcategory":"Jewelry",
            "type":"Retail Goods"
        }
    ],
    "sg:phone":"+1 714 838 6135",
    "sg:postcode":"92620",
    "sg:province":"CA",
    "wof:name":"Crafty Clan",
    "wof:placetype":"venue"
},
  "geometry": {"coordinates":[-117.756973,33.711643],"type":"Point"}
}