{
  "type": "Feature",
  "properties": {
    "iso:country":"US",
    "sg:address":"494 Century Dr",
    "sg:city":"Campbell",
    "sg:classifiers":[
        {
            "category":"Manufacturing",
            "subcategory":"Building Materials",
            "type":"Manufacturing & Wholesale Goods"
        }
    ],
    "sg:phone":"+1 408 378 9280",
    "sg:postcode":"95008",
    "sg:province":"CA",
    "sg:tags":[
        "contractor",
        "wood",
        "kitchen",
        "cabinet"
    ],
    "wof:name":"Full Spectrum Construction",
    "wof:placetype":"venue"
},
  "geometry": {"coordinates":[-121.96399700000001,37.280998],"type":"Point"}
}