{
  "type": "Feature",
  "properties": {
    "addr:full":"210 W Union Ave Fullerton CA 92832",
    "addr:housenumber":"210",
    "addr:postcode":"92832",
    "addr:street":"W Union Ave",
    "iso:country":"US",
    "sg:address":"210 W Union Ave",
    "sg:city":"Fullerton",
    "sg:classifiers":[
        {
            "category":"Real Estate",
            "subcategory":"Real Estate Operator",
            "type":"Services"
        }
    ],
    "sg:phone":"+1 714 738 0262",
    "sg:postcode":"92832",
    "sg:province":"CA",
    "sg:tags":[
        "apartment"
    ],
    "wof:name":"Kashmir Apartments",
    "wof:placetype":"venue"
},
  "geometry": {"coordinates":[-117.92800099999999,33.877701],"type":"Point"}
}