{
  "type": "Feature",
  "properties": {
    "addr:full":"1324 W 7th Street Los Angeles CA 90017",
    "addr:housenumber":"1324",
    "addr:postcode":"90017",
    "addr:street":"W 7Th Street",
    "iso:country":"US",
    "sg:address":"1324 W 7th Street",
    "sg:city":"Los Angeles",
    "sg:classifiers":[
        {
            "category":"Food & Beverages",
            "subcategory":"Groceries & Convenience Stores",
            "type":"Retail Goods"
        }
    ],
    "sg:phone":"+1 213 484 4030",
    "sg:postcode":"90017",
    "sg:province":"CA",
    "wof:name":"Elf Market",
    "wof:placetype":"venue"
},
  "geometry": {"coordinates":[-118.26776700000001,34.052377],"type":"Point"}
}