{
  "type": "Feature",
  "properties": {
    "addr:full":"1633 State Rte 46 Wasco CA 93280",
    "addr:housenumber":"1633",
    "addr:postcode":"ca 93280",
    "addr:street":"State Rte 46",
    "iso:country":"US",
    "sg:address":"1633 State Rte 46",
    "sg:city":"Wasco",
    "sg:classifiers":[
        {
            "category":"Autos & Motor Vehicles",
            "subcategory":"Automobile Sales",
            "type":"Retail Goods"
        }
    ],
    "sg:phone":"+1 661 758 4106",
    "sg:postcode":"93280",
    "sg:province":"CA",
    "sg:tags":[
        "car",
        "dealer"
    ],
    "wof:name":"Garces Auto Sales",
    "wof:placetype":"venue"
},
  "geometry": {"coordinates":[-119.343564,35.601465],"type":"Point"}
}