{
  "type": "Feature",
  "properties": {
    "iso:country":"US",
    "sg:address":"11257 Coloma Rd",
    "sg:city":"Gold River",
    "sg:classifiers":[
        {
            "category":"Retail",
            "subcategory":"Storage",
            "type":"Services"
        }
    ],
    "sg:phone":"+1 916 635 4501",
    "sg:postcode":"95670",
    "sg:province":"CA",
    "sg:tags":[
        "self"
    ],
    "wof:name":"Storage",
    "wof:placetype":"venue"
},
  "geometry": {"coordinates":[-121.26300000000001,38.619301],"type":"Point"}
}