{
  "type": "Feature",
  "properties": {
    "iso:country":"US",
    "sg:address":"830 Jury Ct",
    "sg:city":"San Jose",
    "sg:classifiers":[
        {
            "category":"Winery",
            "type":"Food & Drink"
        }
    ],
    "sg:phone":"+1 408 835 4054",
    "sg:postcode":"95112",
    "sg:province":"CA",
    "wof:name":"Team Zin Winery",
    "wof:placetype":"venue"
},
  "geometry": {"coordinates":[-121.894702,37.369821],"type":"Point"}
}