{
  "type": "Feature",
  "properties": {
    "addr:full":"327 E Pico Blvd Los Angeles CA 90015",
    "addr:housenumber":"327",
    "addr:postcode":"90015",
    "addr:street":"E Pico Blvd",
    "iso:country":"US",
    "sg:address":"327 E Pico Blvd",
    "sg:city":"Los Angeles",
    "sg:classifiers":[
        {
            "category":"Manufacturing",
            "subcategory":"Apparel",
            "type":"Manufacturing & Wholesale Goods"
        }
    ],
    "sg:phone":"+1 213 748 9727",
    "sg:postcode":"90015",
    "sg:province":"CA",
    "sg:tags":[
        "underwear",
        "woman",
        "business",
        "mfg"
    ],
    "wof:name":"Venus Fashion",
    "wof:placetype":"venue"
},
  "geometry": {"coordinates":[-118.257409,34.034778],"type":"Point"}
}