{
  "type": "Feature",
  "properties": {
    "iso:country":"US",
    "sg:address":"2377 Gold Meadow Way",
    "sg:city":"Gold River",
    "sg:classifiers":[
        {
            "category":"Professional",
            "subcategory":"Lawyer & Legal Services",
            "type":"Services"
        }
    ],
    "sg:phone":"+1 916 526 2655",
    "sg:postcode":"95670",
    "sg:province":"CA",
    "wof:name":"Debartolo James Law Offices of",
    "wof:placetype":"venue"
},
  "geometry": {"coordinates":[-121.260632,38.621291],"type":"Point"}
}