{
  "type": "Feature",
  "properties": {
    "iso:country":"US",
    "sg:address":"2324 Ventura Blvd",
    "sg:city":"Camarillo",
    "sg:classifiers":[
        {
            "category":"Bars & Pubs",
            "subcategory":"Wine Bar",
            "type":"Food & Drink"
        }
    ],
    "sg:phone":"+1 805 383 9812",
    "sg:postcode":"93010",
    "sg:province":"CA",
    "sg:website":"www.wineclosetinc.com",
    "wof:name":"The Wine Closet",
    "wof:placetype":"venue"
},
  "geometry": {"coordinates":[-119.038569,34.21636],"type":"Point"}
}