{
  "type": "Feature",
  "properties": {
    "addr:full":"1905 Calle Barcelona Carlsbad CA 92009",
    "addr:housenumber":"1905",
    "addr:postcode":"92009",
    "addr:street":"Calle Barcelona",
    "iso:country":"US",
    "sg:address":"1905 Calle Barcelona",
    "sg:city":"Carlsbad",
    "sg:classifiers":[
        {
            "category":"Shopping",
            "subcategory":"Beauty & Cosmetics",
            "type":"Retail Goods"
        }
    ],
    "sg:phone":"+1 760 635 1625",
    "sg:postcode":"92009",
    "sg:province":"CA",
    "sg:tags":[
        "supply"
    ],
    "wof:name":"Ulta Cosmetics",
    "wof:placetype":"venue"
},
  "geometry": {"coordinates":[-117.26751,33.072203],"type":"Point"}
}