{
  "type": "Feature",
  "properties": {
    "addr:full":"28415 Industry Dr Ste 505 Valencia CA 91355",
    "addr:housenumber":"28415",
    "addr:postcode":"91355",
    "addr:street":"Industry Dr Ste 505",
    "iso:country":"US",
    "sg:address":"28415 Industry Dr Ste 505",
    "sg:city":"Valencia",
    "sg:classifiers":[
        {
            "category":"Retail",
            "subcategory":"Storage",
            "type":"Services"
        }
    ],
    "sg:phone":"+1 661 775 2620",
    "sg:postcode":"91355",
    "sg:province":"CA",
    "sg:tags":[
        "self"
    ],
    "wof:name":"Profilers",
    "wof:placetype":"venue"
},
  "geometry": {"coordinates":[-118.63200399999999,34.452],"type":"Point"}
}