{
  "type": "Feature",
  "properties": {
    "addr:full":"1626 Ohms Way Costa Mesa CA 92627",
    "addr:housenumber":"1626",
    "addr:postcode":"92627",
    "addr:street":"Ohms Way",
    "iso:country":"US",
    "sg:address":"1626 Ohms Way",
    "sg:city":"Costa Mesa",
    "sg:classifiers":[
        {
            "category":"Building & Trades",
            "subcategory":"Construction",
            "type":"Services"
        }
    ],
    "sg:phone":"+1 949 631 4272",
    "sg:postcode":"92627",
    "sg:province":"CA",
    "sg:tags":[
        "fabricator",
        "metal"
    ],
    "wof:name":"S S Metal Fabricators",
    "wof:placetype":"venue"
},
  "geometry": {"coordinates":[-117.92828799999999,33.634329],"type":"Point"}
}