{
  "type": "Feature",
  "properties": {
    "iso:country":"US",
    "sg:address":"1505 W Jefferson Blvd",
    "sg:city":"Los Angeles",
    "sg:classifiers":[
        {
            "category":"Food & Beverages",
            "subcategory":"Groceries & Convenience Stores",
            "type":"Retail Goods"
        }
    ],
    "sg:phone":"+1 323 734 3459",
    "sg:postcode":"90018",
    "sg:province":"CA",
    "sg:tags":[
        "grocer"
    ],
    "wof:name":"La Paloma Market",
    "wof:placetype":"venue"
},
  "geometry": {"coordinates":[-118.30100299999999,34.025398],"type":"Point"}
}