{
  "type": "Feature",
  "properties": {
    "iso:country":"US",
    "sg:address":"255 King St Ste A",
    "sg:city":"San Francisco",
    "sg:classifiers":[
        {
            "category":"Health Services",
            "subcategory":"Dentist",
            "type":"Services"
        }
    ],
    "sg:phone":"+1 415 644 0644",
    "sg:postcode":"94107",
    "sg:province":"CA",
    "wof:name":"Alexander Kogan, DDS",
    "wof:placetype":"venue"
},
  "geometry": {"coordinates":[-122.396006,37.774683],"type":"Point"}
}