{
  "type": "Feature",
  "properties": {
    "iso:country":"US",
    "sg:address":"1036 Darms Ln",
    "sg:city":"Napa",
    "sg:classifiers":[
        {
            "category":"Organizations",
            "subcategory":"Religious Organization",
            "type":"Services"
        }
    ],
    "sg:phone":"+1 707 944 1376",
    "sg:postcode":"94558",
    "sg:province":"CA",
    "wof:name":"Jehovahs Witnesses",
    "wof:placetype":"venue"
},
  "geometry": {"coordinates":[-122.34325,38.363673],"type":"Point"}
}