{
  "type": "Feature",
  "properties": {
    "addr:full":"8489 Auburn Blvd Citrus Heights CA 95610",
    "addr:housenumber":"8489",
    "addr:postcode":"95610",
    "addr:street":"Auburn Blvd",
    "iso:country":"US",
    "sg:address":"8489 Auburn Blvd",
    "sg:city":"Citrus Heights",
    "sg:classifiers":[
        {
            "category":"Shopping",
            "subcategory":"Shoes",
            "type":"Retail Goods"
        }
    ],
    "sg:phone":"+1 916 722 7294",
    "sg:postcode":"95610",
    "sg:province":"CA",
    "wof:name":"Payless Shoe Source",
    "wof:placetype":"venue"
},
  "geometry": {"coordinates":[-121.290482,38.719874],"type":"Point"}
}