{
  "type": "Feature",
  "properties": {
    "iso:country":"US",
    "sg:address":"3548 Flintwood Dr",
    "sg:city":"Santa Rosa",
    "sg:classifiers":[
        {
            "category":"Shopping",
            "subcategory":"Gifts & Souvenirs",
            "type":"Retail Goods"
        }
    ],
    "sg:phone":"+1 707 570 2654",
    "sg:postcode":"95404",
    "sg:province":"CA",
    "wof:name":"Living Gifts",
    "wof:placetype":"venue"
},
  "geometry": {"coordinates":[-122.70278500000001,38.479902],"type":"Point"}
}