{
  "type": "Feature",
  "properties": {
    "addr:full":"1368 34th Ave San Francisco CA 94122",
    "addr:housenumber":"1368",
    "addr:postcode":"94122",
    "addr:street":"34Th Ave",
    "iso:country":"US",
    "sg:address":"1368 34th Ave",
    "sg:city":"San Francisco",
    "sg:classifiers":[
        {
            "category":"Building & Trades",
            "subcategory":"Construction",
            "type":"Services"
        }
    ],
    "sg:phone":"+1 415 566 0236",
    "sg:postcode":"94122",
    "sg:province":"CA",
    "sg:tags":[
        "contractor"
    ],
    "wof:name":"Superior Construction Co",
    "wof:placetype":"venue"
},
  "geometry": {"coordinates":[-122.493065,37.762287],"type":"Point"}
}