{
  "type": "Feature",
  "properties": {
    "addr:full":"800 Grand Ave Carlsbad CA 92008",
    "addr:housenumber":"800",
    "addr:postcode":"92008",
    "addr:street":"Grand Ave",
    "iso:country":"US",
    "sg:address":"800 Grand Ave",
    "sg:city":"Carlsbad",
    "sg:classifiers":[
        {
            "category":"Real Estate",
            "subcategory":"Real Estate Agent",
            "type":"Services"
        }
    ],
    "sg:phone":"+1 760 434 9950",
    "sg:postcode":"92008",
    "sg:province":"CA",
    "sg:tags":[
        "appraiser"
    ],
    "wof:name":"George Hatch",
    "wof:placetype":"venue"
},
  "geometry": {"coordinates":[-117.346018,33.162765],"type":"Point"}
}