{
  "type": "Feature",
  "properties": {
    "iso:country":"US",
    "sg:address":"3588 Palo Verde Ave",
    "sg:city":"Long Beach",
    "sg:classifiers":[
        {
            "category":"Shopping",
            "subcategory":"Crafts & Fabrics",
            "type":"Retail Goods"
        }
    ],
    "sg:phone":"+1 562 421 9497",
    "sg:postcode":"90808",
    "sg:province":"CA",
    "sg:tags":[
        "art",
        "store",
        "supply"
    ],
    "wof:name":"Jo-Ann Fabrics and Crafts",
    "wof:placetype":"venue"
},
  "geometry": {"coordinates":[-118.108002,33.821602],"type":"Point"}
}