{
  "type": "Feature",
  "properties": {
    "iso:country":"US",
    "sg:address":"3612 Jasmine St",
    "sg:city":"Sacramento",
    "sg:classifiers":[
        {
            "category":"Building & Trades",
            "subcategory":"Electrical",
            "type":"Services"
        }
    ],
    "sg:phone":"+1 916 924 9900",
    "sg:postcode":"95838",
    "sg:province":"CA",
    "sg:tags":[
        "electric",
        "contractor"
    ],
    "wof:name":"Cap City Electric Inc",
    "wof:placetype":"venue"
},
  "geometry": {"coordinates":[-121.42657,38.63441],"type":"Point"}
}