{
  "type": "Feature",
  "properties": {
    "iso:country":"US",
    "sg:address":"17081 Donmetz St",
    "sg:city":"Granada Hills",
    "sg:classifiers":[
        {
            "category":"Building & Trades",
            "subcategory":"Pest Control",
            "type":"Services"
        }
    ],
    "sg:phone":"+1 818 831 3396",
    "sg:postcode":"91344",
    "sg:province":"CA",
    "wof:name":"KNC Termite Control Inc",
    "wof:placetype":"venue"
},
  "geometry": {"coordinates":[-118.50501800000001,34.273017],"type":"Point"}
}