{
  "type": "Feature",
  "properties": {
    "addr:full":"7769 Melrose Ave Los Angeles CA 90046",
    "addr:housenumber":"7769",
    "addr:postcode":"90046",
    "addr:street":"Melrose Ave",
    "iso:country":"US",
    "sg:address":"7769 Melrose Ave",
    "sg:city":"Los Angeles",
    "sg:classifiers":[
        {
            "category":"Shopping",
            "subcategory":"Clothing, Apparel, & Fashions",
            "type":"Retail Goods"
        },
        {
            "category":"Shopping",
            "subcategory":"Shoes",
            "type":"Retail Goods"
        }
    ],
    "sg:phone":"+1 323 852 7179",
    "sg:postcode":"90046",
    "sg:province":"CA",
    "sg:tags":[
        "men's",
        "clothing",
        "store",
        "women's"
    ],
    "sg:website":"www.barracudashop.com",
    "wof:name":"Barracuda",
    "wof:placetype":"venue"
},
  "geometry": {"coordinates":[-118.359163,34.084037],"type":"Point"}
}