{
  "type": "Feature",
  "properties": {
    "addr:full":"2850 Telegraph Ave Berkeley CA 94705",
    "addr:housenumber":"2850",
    "addr:postcode":"94705",
    "addr:street":"Telegraph Ave",
    "iso:country":"US",
    "sg:address":"2850 Telegraph Ave",
    "sg:city":"Berkeley",
    "sg:classifiers":[
        {
            "category":"Health Services",
            "subcategory":"Medical Lab",
            "type":"Services"
        }
    ],
    "sg:phone":"+1 510 548 2994",
    "sg:postcode":"94705",
    "sg:province":"CA",
    "sg:tags":[
        "laboratory"
    ],
    "wof:name":"Laboratory Corp Of America",
    "wof:placetype":"venue"
},
  "geometry": {"coordinates":[-122.259417,37.858011],"type":"Point"}
}