{
  "type": "Feature",
  "properties": {
    "iso:country":"US",
    "sg:address":"501 E Anaheim St",
    "sg:city":"Long Beach",
    "sg:classifiers":[
        {
            "category":"Manufacturing",
            "subcategory":"Motor Vehicles & Parts",
            "type":"Manufacturing & Wholesale Goods"
        }
    ],
    "sg:phone":"+1 562 599 3531",
    "sg:postcode":"90813",
    "sg:province":"CA",
    "sg:tags":[
        "auto",
        "supply",
        "automobile"
    ],
    "wof:name":"C & C Auto Parts",
    "wof:placetype":"venue"
},
  "geometry": {"coordinates":[-118.18634400000001,33.782915],"type":"Point"}
}