{
  "type": "Feature",
  "properties": {
    "iso:country":"US",
    "sg:address":"510 Couch St",
    "sg:city":"Vallejo",
    "sg:classifiers":[
        {
            "category":"Autos & Motor Vehicles",
            "subcategory":"Motorcycle Sales",
            "type":"Retail Goods"
        }
    ],
    "sg:phone":"+1 707 643 2548",
    "sg:postcode":"94590",
    "sg:province":"CA",
    "sg:tags":[
        "scooter"
    ],
    "sg:website":"www.mach1motorsports.com",
    "wof:name":"Mach 1 Motorsports",
    "wof:placetype":"venue"
},
  "geometry": {"coordinates":[-122.251374,38.126629],"type":"Point"}
}