{
  "type": "Feature",
  "properties": {
    "iso:country":"US",
    "sg:address":"19061 Wells Dr",
    "sg:city":"Tarzana",
    "sg:classifiers":[
        {
            "category":"Professional",
            "type":"Services"
        }
    ],
    "sg:phone":"+1 818 996 5902",
    "sg:postcode":"91356",
    "sg:province":"CA",
    "sg:tags":[
        "establishment"
    ],
    "wof:name":"MCL Productions",
    "wof:placetype":"venue"
},
  "geometry": {"coordinates":[-118.548549,34.16349],"type":"Point"}
}