{
  "type": "Feature",
  "properties": {
    "iso:country":"US",
    "sg:address":"639 E El Segundo Boulevard",
    "sg:city":"Los Angeles",
    "sg:classifiers":[
        {
            "category":"Restaurant",
            "type":"Food & Drink"
        }
    ],
    "sg:phone":"+1 323 756 9539",
    "sg:postcode":"90059",
    "sg:province":"CA",
    "sg:tags":[
        "chinese"
    ],
    "wof:name":"Chinese Deli",
    "wof:placetype":"venue"
},
  "geometry": {"coordinates":[-118.263946,33.916515],"type":"Point"}
}