{
  "type": "Feature",
  "properties": {
    "iso:country":"US",
    "sg:address":"13535 Alondra Blvd",
    "sg:city":"Santa Fe Springs",
    "sg:classifiers":[
        {
            "category":"Home & Garden",
            "subcategory":"Home Furnishings",
            "type":"Retail Goods"
        }
    ],
    "sg:phone":"+1 562 229 9468",
    "sg:postcode":"90670",
    "sg:province":"CA",
    "sg:tags":[
        "drape"
    ],
    "wof:name":"Nbb Draperies and Blinds",
    "wof:placetype":"venue"
},
  "geometry": {"coordinates":[-118.044389,33.887944],"type":"Point"}
}