{
  "type": "Feature",
  "properties": {
    "iso:country":"US",
    "sg:address":"1306 N Benson Ave",
    "sg:city":"Upland",
    "sg:classifiers":[
        {
            "category":"Manufacturing",
            "subcategory":"Tools & Machinery",
            "type":"Manufacturing & Wholesale Goods"
        }
    ],
    "sg:phone":"+1 909 981 2122",
    "sg:postcode":"91786",
    "sg:province":"CA",
    "sg:tags":[
        "mold"
    ],
    "wof:name":"Brunton Molds Inc",
    "wof:placetype":"venue"
},
  "geometry": {"coordinates":[-117.68087300000001,34.114948],"type":"Point"}
}