{
  "type": "Feature",
  "properties": {
    "addr:full":"604 Main St Cambria CA 93428",
    "addr:housenumber":"604",
    "addr:postcode":"93428",
    "addr:street":"Main St",
    "iso:country":"US",
    "sg:address":"604 Main St",
    "sg:city":"Cambria",
    "sg:classifiers":[
        {
            "category":"Restaurant",
            "type":"Food & Drink"
        }
    ],
    "sg:phone":"+1 805 927 3833",
    "sg:postcode":"93428",
    "sg:province":"CA",
    "sg:tags":[
        "delicatessen"
    ],
    "wof:name":"Courtyard Deli",
    "wof:placetype":"venue"
},
  "geometry": {"coordinates":[-121.09944400000001,35.566755],"type":"Point"}
}