{
  "type": "Feature",
  "properties": {
    "addr:full":"110 W Holt Blvd Ontario CA 91762",
    "addr:housenumber":"110",
    "addr:postcode":"91762",
    "addr:street":"W Holt Blvd",
    "iso:country":"US",
    "sg:address":"110 W Holt Blvd",
    "sg:city":"Ontario",
    "sg:classifiers":[
        {
            "category":"Personal",
            "subcategory":"Beauty Salon",
            "type":"Services"
        }
    ],
    "sg:phone":"+1 909 988 7795",
    "sg:postcode":"91762",
    "sg:province":"CA",
    "wof:name":"Perfect Nail",
    "wof:placetype":"venue"
},
  "geometry": {"coordinates":[-117.65227299999999,34.063437],"type":"Point"}
}