{
  "type": "Feature",
  "properties": {
    "iso:country":"US",
    "sg:address":"19640 Natalie Way",
    "sg:city":"Redding",
    "sg:classifiers":[
        {
            "category":"Banks & Credit Unions",
            "subcategory":"Investment Brokerage",
            "type":"Services"
        }
    ],
    "sg:phone":"+1 530 241 5702",
    "sg:postcode":"96003",
    "sg:province":"CA",
    "sg:tags":[
        "security"
    ],
    "wof:name":"US Allianz Securities",
    "wof:placetype":"venue"
},
  "geometry": {"coordinates":[-122.330563,40.677018],"type":"Point"}
}