{
  "type": "Feature",
  "properties": {
    "iso:country":"US",
    "sg:address":"7927 Imperial Hwy",
    "sg:city":"Downey",
    "sg:classifiers":[
        {
            "category":"Personal",
            "subcategory":"Barber",
            "type":"Services"
        }
    ],
    "sg:phone":"+1 562 861 3710",
    "sg:postcode":"90242",
    "sg:province":"CA",
    "wof:name":"Big Boys Cuts",
    "wof:placetype":"venue"
},
  "geometry": {"coordinates":[-118.153796,33.925146],"type":"Point"}
}