{
  "type": "Feature",
  "properties": {
    "iso:country":"US",
    "sg:address":"10325 Mills Ave",
    "sg:city":"Montclair",
    "sg:classifiers":[
        {
            "category":"Restaurant",
            "type":"Food & Drink"
        }
    ],
    "sg:phone":"+1 909 626 9816",
    "sg:postcode":"91763",
    "sg:province":"CA",
    "wof:name":"Chavela's Bar",
    "wof:placetype":"venue"
},
  "geometry": {"coordinates":[-117.71669199999999,34.066345],"type":"Point"}
}