{
  "type": "Feature",
  "properties": {
    "iso:country":"US",
    "sg:address":"18430 Sutter Blvd",
    "sg:city":"Morgan Hill",
    "sg:classifiers":[
        {
            "category":"Wholesale",
            "subcategory":"Electrical",
            "type":"Manufacturing & Wholesale Goods"
        }
    ],
    "sg:phone":"+1 408 782 0800",
    "sg:postcode":"95037",
    "sg:province":"CA",
    "sg:tags":[
        "semiconductor"
    ],
    "wof:name":"Busch Semiconductor Vaccuum",
    "wof:placetype":"venue"
},
  "geometry": {"coordinates":[-121.65487899999999,37.143797],"type":"Point"}
}