{
  "type": "Feature",
  "properties": {
    "addr:full":"1693 Kimtu Rd Garberville CA 95542",
    "addr:housenumber":"1693",
    "addr:postcode":"95542",
    "addr:street":"Kimtu Rd",
    "iso:country":"US",
    "sg:address":"1693 Kimtu Rd",
    "sg:city":"Garberville",
    "sg:classifiers":[
        {
            "category":"Manufacturing",
            "subcategory":"Signs",
            "type":"Manufacturing & Wholesale Goods"
        }
    ],
    "sg:phone":"+1 707 923 3184",
    "sg:postcode":"95542",
    "sg:province":"CA",
    "wof:name":"Roger Clark Signs",
    "wof:placetype":"venue"
},
  "geometry": {"coordinates":[-123.820487,40.075856],"type":"Point"}
}