{
  "type": "Feature",
  "properties": {
    "iso:country":"US",
    "sg:address":"3636 Veneman Ave N",
    "sg:city":"Modesto",
    "sg:classifiers":[
        {
            "category":"Health Services",
            "subcategory":"Nursing And Care Facility",
            "type":"Services"
        }
    ],
    "sg:phone":"+1 209 529 1533",
    "sg:postcode":"95356",
    "sg:province":"CA",
    "wof:name":"Heaven Living Facility",
    "wof:placetype":"venue"
},
  "geometry": {"coordinates":[-121.036095,37.689544],"type":"Point"}
}