{
  "type": "Feature",
  "properties": {
    "addr:full":"23929 McBean Pkwy Valencia CA 91355",
    "addr:housenumber":"23929",
    "addr:postcode":"91355",
    "addr:street":"Mcbean Pkwy",
    "iso:country":"US",
    "sg:address":"23929 McBean Pkwy",
    "sg:city":"Valencia",
    "sg:classifiers":[
        {
            "category":"Shopping",
            "subcategory":"Pharmacy",
            "type":"Retail Goods"
        }
    ],
    "sg:phone":"+1 661 254 3600",
    "sg:postcode":"91355",
    "sg:province":"CA",
    "sg:tags":[
        "drugstore"
    ],
    "wof:name":"Santa Clarita Medical Center Pharmacy",
    "wof:placetype":"venue"
},
  "geometry": {"coordinates":[-118.55300099999999,34.396599],"type":"Point"}
}