{
  "type": "Feature",
  "properties": {
    "iso:country":"US",
    "sg:address":"2921 E Miraloma Ave Ste 10",
    "sg:city":"Anaheim",
    "sg:classifiers":[
        {
            "category":"Building & Trades",
            "subcategory":"Construction",
            "type":"Services"
        }
    ],
    "sg:phone":"+1 714 348 0320",
    "sg:postcode":"92806",
    "sg:province":"CA",
    "sg:tags":[
        "contractor"
    ],
    "sg:website":"www.pikestaircompany.com/",
    "wof:name":"Pike Stair Company",
    "wof:placetype":"venue"
},
  "geometry": {"coordinates":[-117.86673500000001,33.856347],"type":"Point"}
}