{
  "type": "Feature",
  "properties": {
    "iso:country":"US",
    "sg:address":"26871 Hobie Cir",
    "sg:city":"Murrieta",
    "sg:classifiers":[
        {
            "category":"Retail",
            "subcategory":"Repair Shop",
            "type":"Services"
        }
    ],
    "sg:phone":"+1 951 698 4044",
    "sg:postcode":"92562",
    "sg:province":"CA",
    "sg:tags":[
        "equipment",
        "conditioning",
        "air"
    ],
    "wof:name":"Mgi Heating & Air Cond",
    "wof:placetype":"venue"
},
  "geometry": {"coordinates":[-117.172602,33.530234],"type":"Point"}
}