{
  "type": "Feature",
  "properties": {
    "addr:full":"2415 Clement St San Francisco CA 94121",
    "addr:housenumber":"2415",
    "addr:postcode":"94121",
    "addr:street":"Clement St",
    "iso:country":"US",
    "sg:address":"2415 Clement St",
    "sg:city":"San Francisco",
    "sg:classifiers":[
        {
            "category":"Restaurant",
            "type":"Food & Drink"
        }
    ],
    "sg:menulink":"http://www.allmenus.com/ca/san-francisco/62012-patpong/menu/",
    "sg:phone":"+1 415 379 9726",
    "sg:postcode":"94121",
    "sg:province":"CA",
    "sg:tags":[
        "thai",
        "asian"
    ],
    "wof:name":"Patpong",
    "wof:placetype":"venue"
},
  "geometry": {"coordinates":[-122.48513699999999,37.782055],"type":"Point"}
}