{
  "type": "Feature",
  "properties": {
    "addr:full":"5304 Laurel Canyon Blvd Valley Village CA 91607",
    "addr:housenumber":"5304",
    "addr:postcode":"91607",
    "addr:street":"Laurel Canyon Blvd",
    "iso:country":"US",
    "sg:address":"5304 Laurel Canyon Blvd",
    "sg:city":"Valley Village",
    "sg:classifiers":[
        {
            "category":"Wholesale",
            "subcategory":"Stationery",
            "type":"Manufacturing & Wholesale Goods"
        }
    ],
    "sg:phone":"+1 818 508 4827",
    "sg:postcode":"91607",
    "sg:province":"CA",
    "sg:tags":[
        "card"
    ],
    "wof:name":"Village Arts Press",
    "wof:placetype":"venue"
},
  "geometry": {"coordinates":[-118.396004,34.166901],"type":"Point"}
}