{
  "type": "Feature",
  "properties": {
    "iso:country":"US",
    "sg:address":"676 N Loma Ave",
    "sg:city":"Long Beach",
    "sg:classifiers":[
        {
            "category":"Wholesale",
            "subcategory":"Machinery & Supplies",
            "type":"Manufacturing & Wholesale Goods"
        }
    ],
    "sg:phone":"+1 562 597 5870",
    "sg:postcode":"90814",
    "sg:province":"CA",
    "sg:tags":[
        "equipment",
        "industrial"
    ],
    "wof:name":"AC Ostberg Co",
    "wof:placetype":"venue"
},
  "geometry": {"coordinates":[-118.150158,33.773921],"type":"Point"}
}