{
  "type": "Feature",
  "properties": {
    "addr:full":"6580 N Blackstone Ave Fresno CA 93710",
    "addr:housenumber":"6580",
    "addr:postcode":"93710",
    "addr:street":"N Blackstone Ave",
    "iso:country":"US",
    "sg:address":"6580 N Blackstone Ave",
    "sg:city":"Fresno",
    "sg:phone":"+1 559 438 5700",
    "sg:postcode":"93710",
    "sg:province":"CA",
    "sg:website":"http://www.autoenhancements.net",
    "wof:name":"Auto Enhancement",
    "wof:placetype":"venue"
},
  "geometry": {"coordinates":[-119.790177,36.833636],"type":"Point"}
}