{
  "type": "Feature",
  "properties": {
    "iso:country":"US",
    "sg:address":"26245 Monroe Ave",
    "sg:city":"Murrieta",
    "sg:classifiers":[
        {
            "category":"Professional",
            "subcategory":"Engineering",
            "type":"Services"
        }
    ],
    "sg:phone":"+1 951 696 9317",
    "sg:postcode":"92562",
    "sg:province":"CA",
    "sg:tags":[
        "general",
        "contractor"
    ],
    "wof:name":"Kiene Construction Co",
    "wof:placetype":"venue"
},
  "geometry": {"coordinates":[-117.186091,33.549664],"type":"Point"}
}