{
  "type": "Feature",
  "properties": {
    "iso:country":"US",
    "sg:address":"816 Redwood Dr",
    "sg:city":"Garberville",
    "sg:classifiers":[
        {
            "category":"Shopping",
            "subcategory":"Jewelry",
            "type":"Retail Goods"
        }
    ],
    "sg:phone":"+1 707 923 9559",
    "sg:postcode":"95542",
    "sg:province":"CA",
    "sg:tags":[
        "jeweler"
    ],
    "wof:name":"Sunshine Jewelers",
    "wof:placetype":"venue"
},
  "geometry": {"coordinates":[-123.79508199999999,40.099828],"type":"Point"}
}