{
  "type": "Feature",
  "properties": {
    "iso:country":"US",
    "sg:address":"1225 Willow Pass Rd",
    "sg:city":"Concord",
    "sg:classifiers":[
        {
            "category":"Bars & Pubs",
            "type":"Food & Drink"
        }
    ],
    "sg:menulink":"http://www.allmenus.com/ca/central-contra-costa/52244-elephant-bar-restaurant/menu/",
    "sg:phone":"+1 925 671 7757",
    "sg:postcode":"94520",
    "sg:province":"CA",
    "sg:tags":[
        "new",
        "american"
    ],
    "wof:name":"Elephant Bar Restaurant",
    "wof:placetype":"venue"
},
  "geometry": {"coordinates":[-122.05520199999999,37.966806],"type":"Point"}
}