{
  "type": "Feature",
  "properties": {
    "addr:full":"825 B St Hayward CA 94541",
    "addr:housenumber":"825",
    "addr:postcode":"94541",
    "addr:street":"B St",
    "iso:country":"US",
    "sg:address":"825 B St",
    "sg:city":"Hayward",
    "sg:classifiers":[
        {
            "category":"Personal",
            "subcategory":"Beauty Salon",
            "type":"Services"
        },
        {
            "category":"Personal",
            "subcategory":"Nail Salon",
            "type":"Services"
        }
    ],
    "sg:phone":"+1 510 247 9800",
    "sg:postcode":"94541",
    "sg:province":"CA",
    "sg:tags":[
        "hair"
    ],
    "wof:name":"Li's Hair & Nails",
    "wof:placetype":"venue"
},
  "geometry": {"coordinates":[-122.08476,37.671639],"type":"Point"}
}