{
  "type": "Feature",
  "properties": {
    "iso:country":"US",
    "sg:address":"15051 Leffingwell Rd",
    "sg:city":"Whittier",
    "sg:classifiers":[
        {
            "category":"Freight",
            "type":"Transportation"
        }
    ],
    "sg:phone":"+1 562 946 8311",
    "sg:postcode":"90604",
    "sg:province":"CA",
    "sg:tags":[
        "operator",
        "local",
        "trucking"
    ],
    "wof:name":"Lincoln Trucking School",
    "wof:placetype":"venue"
},
  "geometry": {"coordinates":[-118.01181099999999,33.926766],"type":"Point"}
}