{
  "type": "Feature",
  "properties": {
    "iso:country":"US",
    "sg:address":"6941 Douglas Blvd",
    "sg:city":"Roseville",
    "sg:classifiers":[
        {
            "category":"Retail",
            "subcategory":"Laundry & Dry Cleaning",
            "type":"Services"
        }
    ],
    "sg:phone":"+1 916 791 8155",
    "sg:postcode":"95746",
    "sg:province":"CA",
    "sg:tags":[
        "cleaners"
    ],
    "wof:name":"Swanson's Cleaners",
    "wof:placetype":"venue"
},
  "geometry": {"coordinates":[-121.171299,38.743501],"type":"Point"}
}