{
  "type": "Feature",
  "properties": {
    "addr:full":"448 Redcliff Dr Redding CA 96002",
    "addr:housenumber":"448",
    "addr:postcode":"96002",
    "addr:street":"Redcliff Dr",
    "iso:country":"US",
    "sg:address":"448 Redcliff Dr",
    "sg:city":"Redding",
    "sg:classifiers":[
        {
            "category":"Insurance",
            "subcategory":"Life Insurance",
            "type":"Services"
        }
    ],
    "sg:phone":"+1 530 226 8210",
    "sg:postcode":"96002",
    "sg:province":"CA",
    "sg:tags":[
        "carrier"
    ],
    "wof:name":"Robert L Salyer",
    "wof:placetype":"venue"
},
  "geometry": {"coordinates":[-122.363029,40.575249],"type":"Point"}
}