{
  "type": "Feature",
  "properties": {
    "iso:country":"US",
    "sg:address":"4509 Mount Lindsey Pl",
    "sg:city":"San Diego",
    "sg:classifiers":[
        {
            "category":"Manufacturing",
            "subcategory":"Retail Goods",
            "type":"Manufacturing & Wholesale Goods"
        }
    ],
    "sg:phone":"+1 858 565 6269",
    "sg:postcode":"92117",
    "sg:province":"CA",
    "sg:tags":[
        "product",
        "mfg"
    ],
    "wof:name":"Moore Puppets",
    "wof:placetype":"venue"
},
  "geometry": {"coordinates":[-117.19497699999999,32.825308],"type":"Point"}
}