{
  "type": "Feature",
  "properties": {
    "addr:full":"1432 E Katella Ave Orange CA 92867",
    "addr:housenumber":"1432",
    "addr:postcode":"92867",
    "addr:street":"E Katella Ave",
    "iso:country":"US",
    "sg:address":"1432 E Katella Ave",
    "sg:city":"Orange",
    "sg:classifiers":[
        {
            "category":"Manufacturing",
            "subcategory":"Signs",
            "type":"Manufacturing & Wholesale Goods"
        }
    ],
    "sg:phone":"+1 714 997 9823",
    "sg:postcode":"92867",
    "sg:province":"CA",
    "wof:name":"Sign Express",
    "wof:placetype":"venue"
},
  "geometry": {"coordinates":[-117.837728,33.809096],"type":"Point"}
}