{
  "type": "Feature",
  "properties": {
    "iso:country":"US",
    "sg:address":"7772 Glenn Ave",
    "sg:city":"Citrus Heights",
    "sg:classifiers":[
        {
            "category":"Personal",
            "subcategory":"Beauty Salon",
            "type":"Services"
        }
    ],
    "sg:phone":"+1 916 725 4291",
    "sg:postcode":"95610",
    "sg:province":"CA",
    "wof:name":"Charlotte Parr Hair Gallerys",
    "wof:placetype":"venue"
},
  "geometry": {"coordinates":[-121.279887,38.713782],"type":"Point"}
}