{
  "type": "Feature",
  "properties": {
    "addr:full":"12587 Eagle Ranch Pkwy Victorville CA 92392",
    "addr:housenumber":"12587",
    "addr:postcode":"92392",
    "addr:street":"Eagle Ranch Pkwy",
    "iso:country":"US",
    "sg:address":"12587 Eagle Ranch Pkwy",
    "sg:city":"Victorville",
    "sg:classifiers":[
        {
            "category":"Recreation",
            "type":"Entertainment"
        }
    ],
    "sg:phone":"+1 760 245 5551",
    "sg:postcode":"92392",
    "sg:province":"CA",
    "sg:tags":[
        "parks"
    ],
    "wof:name":"Eagle Ranch Park",
    "wof:placetype":"venue"
},
  "geometry": {"coordinates":[-117.389802,34.479311],"type":"Point"}
}