{
  "type": "Feature",
  "properties": {
    "addr:full":"560 34th Ave Santa Cruz CA 95062",
    "addr:housenumber":"560",
    "addr:postcode":"95062",
    "addr:street":"34Th Ave",
    "iso:country":"US",
    "sg:address":"560 34th Ave",
    "sg:city":"Santa Cruz",
    "sg:classifiers":[
        {
            "category":"Professional",
            "subcategory":"Art Services",
            "type":"Services"
        }
    ],
    "sg:phone":"+1 831 476 9528",
    "sg:postcode":"95062",
    "sg:province":"CA",
    "sg:tags":[
        "graphic",
        "designer"
    ],
    "wof:name":"Stark Designs",
    "wof:placetype":"venue"
},
  "geometry": {"coordinates":[-121.971226,36.958994],"type":"Point"}
}