{
  "type": "Feature",
  "properties": {
    "addr:full":"12125 Venice Blvd Los Angeles CA 90066",
    "addr:housenumber":"12125",
    "addr:postcode":"90066",
    "addr:street":"Venice Blvd",
    "iso:country":"US",
    "sg:address":"12125 Venice Blvd",
    "sg:city":"Los Angeles",
    "sg:classifiers":[
        {
            "category":"Restaurant",
            "type":"Food & Drink"
        }
    ],
    "sg:phone":"+1 310 390 0577",
    "sg:postcode":"90066",
    "sg:province":"CA",
    "sg:tags":[
        "mexican",
        "diner"
    ],
    "sg:website":"pepysgalley.com",
    "wof:name":"Pepy's Galley",
    "wof:placetype":"venue"
},
  "geometry": {"coordinates":[-118.430725,34.005305],"type":"Point"}
}