{
  "type": "Feature",
  "properties": {
    "iso:country":"US",
    "sg:address":"2445 E Whitmore Ave",
    "sg:city":"Ceres",
    "sg:classifiers":[
        {
            "category":"Education",
            "subcategory":"Dance Studio",
            "type":"Public Place"
        }
    ],
    "sg:phone":"+1 209 538 8544",
    "sg:postcode":"95307",
    "sg:province":"CA",
    "sg:tags":[
        "instruction",
        "dancing"
    ],
    "wof:name":"Footnotes Dance Studio",
    "wof:placetype":"venue"
},
  "geometry": {"coordinates":[-120.95079,37.594744],"type":"Point"}
}