{
  "type": "Feature",
  "properties": {
    "addr:full":"7816 Skyway Rd Paradise CA 95969",
    "addr:housenumber":"7816",
    "addr:postcode":"95969",
    "addr:street":"Skyway Rd",
    "iso:country":"US",
    "sg:address":"7816 Skyway Rd",
    "sg:city":"Paradise",
    "sg:classifiers":[
        {
            "category":"Personal",
            "subcategory":"Beauty Salon",
            "type":"Services"
        }
    ],
    "sg:phone":"+1 530 872 4503",
    "sg:postcode":"95969",
    "sg:province":"CA",
    "wof:name":"Paradise Skin Care",
    "wof:placetype":"venue"
},
  "geometry": {"coordinates":[-121.611301,39.772262],"type":"Point"}
}