{
  "type": "Feature",
  "properties": {
    "iso:country":"US",
    "sg:address":"5969 Serena St",
    "sg:city":"Simi Valley",
    "sg:classifiers":[
        {
            "category":"Building & Trades",
            "subcategory":"Construction",
            "type":"Services"
        }
    ],
    "sg:phone":"+1 805 527 4127",
    "sg:postcode":"93063",
    "sg:province":"CA",
    "sg:tags":[
        "business",
        "contractor"
    ],
    "wof:name":"Hansens Interior Restoration",
    "wof:placetype":"venue"
},
  "geometry": {"coordinates":[-118.675273,34.280812],"type":"Point"}
}