{
  "type": "Feature",
  "properties": {
    "addr:full":"17495 Hurley St City Of Industry CA 91744",
    "addr:housenumber":"17495",
    "addr:postcode":"91744",
    "addr:street":"Hurley St",
    "iso:country":"US",
    "sg:address":"17495 Hurley St",
    "sg:city":"City Of Industry",
    "sg:classifiers":[
        {
            "category":"Organizations",
            "subcategory":"Labor Organization",
            "type":"Services"
        }
    ],
    "sg:phone":"+1 323 263 4183",
    "sg:postcode":"91744",
    "sg:province":"CA",
    "wof:name":"Iron Workers Union Structural",
    "wof:placetype":"venue"
},
  "geometry": {"coordinates":[-117.923715,34.011354],"type":"Point"}
}