{
  "type": "Feature",
  "properties": {
    "addr:full":"2935 Clay St San Francisco CA 94115",
    "addr:housenumber":"2935",
    "addr:postcode":"94115",
    "addr:street":"Clay St",
    "iso:country":"US",
    "sg:address":"2935 Clay St",
    "sg:city":"San Francisco",
    "sg:classifiers":[
        {
            "category":"Professional",
            "subcategory":"Computer Services",
            "type":"Services"
        }
    ],
    "sg:phone":"+1 415 431 6766",
    "sg:postcode":"94115",
    "sg:province":"CA",
    "sg:tags":[
        "repair"
    ],
    "sg:website":"www.c-help.com",
    "wof:name":"Computer Help",
    "wof:placetype":"venue"
},
  "geometry": {"coordinates":[-122.44200600000001,37.789661],"type":"Point"}
}