{
  "type": "Feature",
  "properties": {
    "iso:country":"US",
    "sg:address":"10341 Long Beach Blvd",
    "sg:city":"Lynwood",
    "sg:classifiers":[
        {
            "category":"Food & Beverages",
            "subcategory":"Groceries & Convenience Stores",
            "type":"Retail Goods"
        }
    ],
    "sg:phone":"+1 323 569 1431",
    "sg:postcode":"90262",
    "sg:province":"CA",
    "wof:name":"La Mexicana Market",
    "wof:placetype":"venue"
},
  "geometry": {"coordinates":[-118.214996,33.941601],"type":"Point"}
}