{
  "type": "Feature",
  "properties": {
    "addr:full":"8849 Alcott St Los Angeles CA 90035",
    "addr:housenumber":"8849",
    "addr:postcode":"90035",
    "addr:street":"Alcott St",
    "iso:country":"US",
    "sg:address":"8849 Alcott St",
    "sg:city":"Los Angeles",
    "sg:classifiers":[
        {
            "category":"Retail",
            "subcategory":"Repair Shop",
            "type":"Services"
        }
    ],
    "sg:phone":"+1 323 954 9777",
    "sg:postcode":"90035",
    "sg:province":"CA",
    "sg:tags":[
        "lock",
        "locksmith"
    ],
    "wof:name":"Lucky Lock & Key",
    "wof:placetype":"venue"
},
  "geometry": {"coordinates":[-118.385341,34.054057],"type":"Point"}
}