{
  "type": "Feature",
  "properties": {
    "iso:country":"US",
    "sg:address":"3507 Deer Trail Rd",
    "sg:city":"Santa Rosa",
    "sg:classifiers":[
        {
            "category":"Professional",
            "subcategory":"Accounting & Tax Preparation",
            "type":"Services"
        }
    ],
    "sg:phone":"+1 707 539 5697",
    "sg:postcode":"95404",
    "sg:province":"CA",
    "sg:tags":[
        "accountant"
    ],
    "wof:name":"Anita J Graziano CPA",
    "wof:placetype":"venue"
},
  "geometry": {"coordinates":[-122.681493,38.483935],"type":"Point"}
}