{
  "type": "Feature",
  "properties": {
    "addr:full":"3118 Pacific Coast Hwy Torrance CA 90505",
    "addr:housenumber":"3118",
    "addr:postcode":"90505",
    "addr:street":"Pacific Coast Hwy",
    "iso:country":"US",
    "sg:address":"3118 Pacific Coast Hwy",
    "sg:city":"Torrance",
    "sg:classifiers":[
        {
            "category":"Shopping",
            "subcategory":"Bicycles & Sporting Goods",
            "type":"Retail Goods"
        }
    ],
    "sg:phone":"+1 310 539 4343",
    "sg:postcode":"90505",
    "sg:province":"CA",
    "sg:tags":[
        "equipment",
        "tennis",
        "supply"
    ],
    "wof:name":"Pete Martin's Tennis & Sports Shop Inc",
    "wof:placetype":"venue"
},
  "geometry": {"coordinates":[-118.341003,33.797901],"type":"Point"}
}