{
  "type": "Feature",
  "properties": {
    "iso:country":"US",
    "sg:address":"1037 S Coast Hwy",
    "sg:city":"Oceanside",
    "sg:classifiers":[
        {
            "category":"Autos & Motor Vehicles",
            "subcategory":"Auto Supplies",
            "type":"Retail Goods"
        }
    ],
    "sg:phone":"+1 760 439 8539",
    "sg:postcode":"92054",
    "sg:province":"CA",
    "sg:tags":[
        "tire"
    ],
    "sg:website":"www.discounttire.com/makeappt",
    "wof:name":"Discount Tire",
    "wof:placetype":"venue"
},
  "geometry": {"coordinates":[-117.371269,33.185977],"type":"Point"}
}