{
  "type": "Feature",
  "properties": {
    "addr:full":"41690 Enterprise Cir N Temecula CA 92590",
    "addr:housenumber":"41690",
    "addr:postcode":"92590",
    "addr:street":"Enterprise Cir N",
    "iso:country":"US",
    "sg:address":"41690 Enterprise Cir N",
    "sg:city":"Temecula",
    "sg:classifiers":[
        {
            "category":"Recreation",
            "type":"Entertainment"
        }
    ],
    "sg:phone":"+1 951 296 3989",
    "sg:postcode":"92590",
    "sg:province":"CA",
    "sg:tags":[
        "ticket"
    ],
    "wof:name":"Cloud Nine Tickets",
    "wof:placetype":"venue"
},
  "geometry": {"coordinates":[-117.16933400000001,33.519505],"type":"Point"}
}