{
  "type": "Feature",
  "properties": {
    "addr:full":"11871 Carson St in Hawaiian Gardens Casino Hawaiian Gardens CA 90716",
    "addr:housenumber":"11871",
    "addr:postcode":"90716",
    "addr:street":"Carson St",
    "iso:country":"US",
    "sg:address":"11871 Carson St in Hawaiian Gardens Casino",
    "sg:city":"Hawaiian Gardens",
    "sg:classifiers":[
        {
            "category":"Restaurant",
            "type":"Food & Drink"
        }
    ],
    "sg:phone":"+1 562 860 5887",
    "sg:postcode":"90716",
    "sg:province":"CA",
    "sg:tags":[
        "traditional",
        "american"
    ],
    "sg:website":"www.hgcasino.com",
    "wof:name":"Lahaina Restaurant",
    "wof:placetype":"venue"
},
  "geometry": {"coordinates":[-118.079897,33.83151],"type":"Point"}
}