{
  "type": "Feature",
  "properties": {
    "iso:country":"US",
    "sg:address":"216 Marine Ave",
    "sg:city":"Newport Beach",
    "sg:classifiers":[
        {
            "category":"Restaurant",
            "type":"Food & Drink"
        }
    ],
    "sg:phone":"+1 949 566 9525",
    "sg:postcode":"92662",
    "sg:province":"CA",
    "sg:tags":[
        "mediterranean",
        "french"
    ],
    "sg:website":"www.pasturestaurant.com/",
    "wof:name":"Pas Tu",
    "wof:placetype":"venue"
},
  "geometry": {"coordinates":[-117.88978400000001,33.606477],"type":"Point"}
}