{
  "type": "Feature",
  "properties": {
    "addr:full":"1312 Peacock Hill Dr Santa Ana CA 92705",
    "addr:housenumber":"1312",
    "addr:postcode":"92705",
    "addr:street":"Peacock Hill Dr",
    "iso:country":"US",
    "sg:address":"1312 Peacock Hill Dr",
    "sg:city":"Santa Ana",
    "sg:classifiers":[
        {
            "category":"Building & Trades",
            "subcategory":"Construction",
            "type":"Services"
        }
    ],
    "sg:phone":"+1 714 731 5199",
    "sg:postcode":"92705",
    "sg:province":"CA",
    "sg:tags":[
        "house",
        "contractor",
        "transportation",
        "mfg"
    ],
    "wof:name":"Coronado Construction Company",
    "wof:placetype":"venue"
},
  "geometry": {"coordinates":[-117.78299699999999,33.771099],"type":"Point"}
}