{
  "type": "Feature",
  "properties": {
    "iso:country":"US",
    "sg:address":"2627 Faivre St",
    "sg:city":"Chula Vista",
    "sg:classifiers":[
        {
            "category":"Retail",
            "subcategory":"Auto Repair",
            "type":"Services"
        }
    ],
    "sg:phone":"+1 619 429 6994",
    "sg:postcode":"91911",
    "sg:province":"CA",
    "sg:tags":[
        "repairing",
        "automobile"
    ],
    "wof:name":"Chula Vista Auto Repair",
    "wof:placetype":"venue"
},
  "geometry": {"coordinates":[-117.078086,32.592891],"type":"Point"}
}