{
  "type": "Feature",
  "properties": {
    "addr:full":"5045 Robert J Mathews Pkwy El Dorado Hills CA 95762",
    "addr:housenumber":"5045",
    "addr:postcode":"95762",
    "addr:street":"Robert J Mathews Pkwy",
    "iso:country":"US",
    "sg:address":"5045 Robert J Mathews Pkwy",
    "sg:city":"El Dorado Hills",
    "sg:classifiers":[
        {
            "category":"Professional",
            "type":"Services"
        }
    ],
    "sg:phone":"+1 916 939 1552",
    "sg:postcode":"95762",
    "sg:province":"CA",
    "wof:name":"Kissela Lnda Lmft Psychthrpist",
    "wof:placetype":"venue"
},
  "geometry": {"coordinates":[-121.059769,38.624865],"type":"Point"}
}