{
  "type": "Feature",
  "properties": {
    "addr:full":"451 Broadway Millbrae CA 94030",
    "addr:housenumber":"451",
    "addr:postcode":"94030",
    "addr:street":"Broadway",
    "iso:country":"US",
    "sg:address":"451 Broadway",
    "sg:city":"Millbrae",
    "sg:classifiers":[
        {
            "category":"Food & Beverages",
            "subcategory":"Fruits & Vegetables",
            "type":"Retail Goods"
        }
    ],
    "sg:phone":"+1 650 692 1042",
    "sg:postcode":"94030",
    "sg:province":"CA",
    "sg:tags":[
        "produce",
        "veggie"
    ],
    "wof:name":"Dean's Produce",
    "wof:placetype":"venue"
},
  "geometry": {"coordinates":[-122.393241,37.602077],"type":"Point"}
}