{
  "type": "Feature",
  "properties": {
    "iso:country":"US",
    "sg:address":"2997 Roblar Ave",
    "sg:city":"Santa Ynez",
    "sg:classifiers":[
        {
            "category":"Farming",
            "subcategory":"Livestock Farm",
            "type":"Manufacturing & Wholesale Goods"
        }
    ],
    "sg:phone":"+1 805 688 3473",
    "sg:postcode":"93460",
    "sg:province":"CA",
    "sg:tags":[
        "equine"
    ],
    "wof:name":"Paul Hemming Ranch",
    "wof:placetype":"venue"
},
  "geometry": {"coordinates":[-120.097941,34.650302],"type":"Point"}
}