{
  "type": "Feature",
  "properties": {
    "iso:country":"US",
    "sg:address":"477 N El Camino Real Ste B201",
    "sg:city":"Encinitas",
    "sg:classifiers":[
        {
            "category":"Professional",
            "subcategory":"Testing Lab",
            "type":"Services"
        },
        {
            "category":"Health Services",
            "subcategory":"Medical Lab",
            "type":"Services"
        }
    ],
    "sg:phone":"+1 760 753 0281",
    "sg:postcode":"92024",
    "sg:province":"CA",
    "sg:tags":[
        "laboratories-pathological",
        "laboratory",
        "analytical"
    ],
    "sg:website":"http://www.nicholsinstitute.com",
    "wof:name":"Quest Diagnostics",
    "wof:placetype":"venue"
},
  "geometry": {"coordinates":[-117.262535,33.057291],"type":"Point"}
}