{
  "type": "Feature",
  "properties": {
    "addr:full":"19849 Riverside Ave Anderson CA 96007",
    "addr:housenumber":"19849",
    "addr:postcode":"96007",
    "addr:street":"Riverside Ave",
    "iso:country":"US",
    "sg:address":"19849 Riverside Ave",
    "sg:city":"Anderson",
    "sg:classifiers":[
        {
            "category":"Manufacturing",
            "subcategory":"Tools & Machinery",
            "type":"Manufacturing & Wholesale Goods"
        }
    ],
    "sg:phone":"+1 530 365 9191",
    "sg:postcode":"96007",
    "sg:province":"CA",
    "sg:tags":[
        "equipment",
        "hydraulic"
    ],
    "sg:website":"www.ramsayco.com",
    "wof:name":"Ramsay Co",
    "wof:placetype":"venue"
},
  "geometry": {"coordinates":[-122.311841,40.467842],"type":"Point"}
}