{
  "type": "Feature",
  "properties": {
    "addr:full":"938 Palm Ave Imperial Beach CA 91932",
    "addr:housenumber":"938",
    "addr:postcode":"91932",
    "addr:street":"Palm Ave",
    "iso:country":"US",
    "sg:address":"938 Palm Ave",
    "sg:city":"Imperial Beach",
    "sg:classifiers":[
        {
            "category":"Personal",
            "subcategory":"Beauty Salon",
            "type":"Services"
        }
    ],
    "sg:phone":"+1 619 429 0910",
    "sg:postcode":"91932",
    "sg:province":"CA",
    "sg:tags":[
        "nail",
        "manicuring"
    ],
    "wof:name":"Nail Tech",
    "wof:placetype":"venue"
},
  "geometry": {"coordinates":[-117.113998,32.5839],"type":"Point"}
}