{
  "type": "Feature",
  "properties": {
    "addr:full":"3200 Fulton St San Francisco CA 94118",
    "addr:housenumber":"3200",
    "addr:postcode":"94118",
    "addr:street":"Fulton St",
    "iso:country":"US",
    "sg:address":"3200 Fulton St",
    "sg:city":"San Francisco",
    "sg:classifiers":[
        {
            "category":"Real Estate",
            "subcategory":"Real Estate Services",
            "type":"Services"
        }
    ],
    "sg:phone":"+1 415 668 1200",
    "sg:postcode":"94118",
    "sg:province":"CA",
    "sg:tags":[
        "company",
        "title"
    ],
    "wof:name":"Fidelity National Title",
    "wof:placetype":"venue"
},
  "geometry": {"coordinates":[-122.46695099999999,37.773351],"type":"Point"}
}