{
  "type": "Feature",
  "properties": {
    "iso:country":"US",
    "sg:address":"10626 Flora Vista Ave",
    "sg:city":"Cupertino",
    "sg:classifiers":[
        {
            "category":"Professional",
            "subcategory":"Engineering",
            "type":"Services"
        }
    ],
    "sg:phone":"+1 408 861 8000",
    "sg:postcode":"95014",
    "sg:province":"CA",
    "sg:tags":[
        "engineer"
    ],
    "sg:website":"www.siliconwebinc.com",
    "wof:name":"Siliconweb Inc",
    "wof:placetype":"venue"
},
  "geometry": {"coordinates":[-122.042404,37.332241],"type":"Point"}
}