{
  "type": "Feature",
  "properties": {
    "addr:full":"281 Pine St Brentwood CA 94513",
    "addr:housenumber":"281",
    "addr:postcode":"ca 94513",
    "addr:street":"Pine St",
    "iso:country":"US",
    "sg:address":"281 Pine St",
    "sg:city":"Brentwood",
    "sg:classifiers":[
        {
            "category":"Professional",
            "subcategory":"Employment Agencies",
            "type":"Services"
        }
    ],
    "sg:phone":"+1 925 634 2195",
    "sg:postcode":"94513",
    "sg:province":"CA",
    "wof:name":"Eastbay Works-One Stop Career Centers",
    "wof:placetype":"venue"
},
  "geometry": {"coordinates":[-121.69676200000001,37.934786],"type":"Point"}
}