{
  "type": "Feature",
  "properties": {
    "addr:full":"21628 Figueroa St Carson CA 90745",
    "addr:housenumber":"21628",
    "addr:postcode":"90745",
    "addr:street":"Figueroa St",
    "iso:country":"US",
    "sg:address":"21628 Figueroa St",
    "sg:city":"Carson",
    "sg:classifiers":[
        {
            "category":"Banks & Credit Unions",
            "subcategory":"Financial Services",
            "type":"Services"
        }
    ],
    "sg:phone":"+1 310 787 8714",
    "sg:postcode":"90745",
    "sg:province":"CA",
    "sg:tags":[
        "broker",
        "mortgage"
    ],
    "wof:name":"Rainbow Capital",
    "wof:placetype":"venue"
},
  "geometry": {"coordinates":[-118.285954,33.824309],"type":"Point"}
}