{
  "type": "Feature",
  "properties": {
    "iso:country":"US",
    "sg:address":"5949 Florin Rd",
    "sg:city":"Sacramento",
    "sg:classifiers":[
        {
            "category":"Shopping",
            "subcategory":"Computers & Home Electronics",
            "type":"Retail Goods"
        }
    ],
    "sg:phone":"+1 916 422 2527",
    "sg:postcode":"95823",
    "sg:province":"CA",
    "sg:tags":[
        "game",
        "video"
    ],
    "wof:name":"A Video Games Emporium",
    "wof:placetype":"venue"
},
  "geometry": {"coordinates":[-121.434774,38.496152],"type":"Point"}
}