{
  "type": "Feature",
  "properties": {
    "iso:country":"US",
    "sg:address":"2013 Kerwood Ave",
    "sg:city":"Los Angeles",
    "sg:classifiers":[
        {
            "category":"Professional",
            "type":"Services"
        }
    ],
    "sg:phone":"+1 310 552 8290",
    "sg:postcode":"90025",
    "sg:province":"CA",
    "wof:name":"Probiohealth",
    "wof:placetype":"venue"
},
  "geometry": {"coordinates":[-118.41988,34.052977],"type":"Point"}
}