{
  "type": "Feature",
  "properties": {
    "iso:country":"US",
    "sg:address":"1043 W Gardena Blvd",
    "sg:city":"Gardena",
    "sg:classifiers":[
        {
            "category":"Restaurant",
            "type":"Food & Drink"
        }
    ],
    "sg:phone":"+1 310 324 4820",
    "sg:postcode":"90247",
    "sg:province":"CA",
    "sg:tags":[
        "caterer"
    ],
    "wof:name":"Santos Creations",
    "wof:placetype":"venue"
},
  "geometry": {"coordinates":[-118.293249,33.881618],"type":"Point"}
}