{
  "type": "Feature",
  "properties": {
    "addr:full":"1125 Rhinecastle Wy San Jose CA 95120",
    "addr:housenumber":"1125",
    "addr:postcode":"95120",
    "addr:street":"Rhinecastle Wy",
    "iso:country":"US",
    "sg:address":"1125 Rhinecastle Wy",
    "sg:city":"San Jose",
    "sg:classifiers":[
        {
            "category":"Professional",
            "subcategory":"Art Services",
            "type":"Services"
        }
    ],
    "sg:phone":"+1 408 316 2360",
    "sg:postcode":"95120",
    "sg:province":"CA",
    "sg:tags":[
        "photographer"
    ],
    "sg:website":"www.jslstudio.com",
    "wof:name":"JSL Studio",
    "wof:placetype":"venue"
},
  "geometry": {"coordinates":[-121.873366,37.233511],"type":"Point"}
}