{
  "type": "Feature",
  "properties": {
    "iso:country":"US",
    "sg:address":"2800 Nicolaus Rd",
    "sg:city":"Lincoln",
    "sg:classifiers":[
        {
            "category":"Education",
            "subcategory":"School",
            "type":"Public Place"
        }
    ],
    "sg:phone":"+1 916 408 5200",
    "sg:postcode":"95648",
    "sg:province":"CA",
    "sg:website":"http://www.horizoncharterschool.org",
    "wof:name":"Horizon Charter Schools",
    "wof:placetype":"venue"
},
  "geometry": {"coordinates":[-121.328339,38.897369],"type":"Point"}
}