{
  "type": "Feature",
  "properties": {
    "addr:full":"8007 S Main St Los Angeles CA 90003",
    "addr:housenumber":"8007",
    "addr:postcode":"90003",
    "addr:street":"S Main St",
    "iso:country":"US",
    "sg:address":"8007 S Main St",
    "sg:city":"Los Angeles",
    "sg:classifiers":[
        {
            "category":"Shopping",
            "subcategory":"Clothing, Apparel, & Fashions",
            "type":"Retail Goods"
        }
    ],
    "sg:phone":"+1 323 758 8482",
    "sg:postcode":"90003",
    "sg:province":"CA",
    "sg:tags":[
        "infant",
        "wear"
    ],
    "wof:name":"Fashion Store",
    "wof:placetype":"venue"
},
  "geometry": {"coordinates":[-118.273972,33.967823],"type":"Point"}
}