{
  "type": "Feature",
  "properties": {
    "addr:full":"1514 Roosevelt Ave National City CA 91950",
    "addr:housenumber":"1514",
    "addr:postcode":"91950",
    "addr:street":"Roosevelt Ave",
    "iso:country":"US",
    "sg:address":"1514 Roosevelt Ave",
    "sg:city":"National City",
    "sg:classifiers":[
        {
            "category":"Building & Trades",
            "subcategory":"Construction",
            "type":"Services"
        }
    ],
    "sg:phone":"+1 619 336 9793",
    "sg:postcode":"91950",
    "sg:province":"CA",
    "sg:tags":[
        "engineering",
        "contractor"
    ],
    "wof:name":"Western Pacific Design & Dev",
    "wof:placetype":"venue"
},
  "geometry": {"coordinates":[-117.10539900000001,32.66873],"type":"Point"}
}