{
  "type": "Feature",
  "properties": {
    "addr:full":"211 Las Gallinas Ave San Rafael CA 94903",
    "addr:housenumber":"211",
    "addr:postcode":"94903",
    "addr:street":"Las Gallinas Ave",
    "iso:country":"US",
    "sg:address":"211 Las Gallinas Ave",
    "sg:city":"San Rafael",
    "sg:classifiers":[
        {
            "category":"Government",
            "subcategory":"Office",
            "type":"Public Place"
        }
    ],
    "sg:phone":"+1 415 479 3892",
    "sg:postcode":"94903",
    "sg:province":"CA",
    "sg:tags":[
        "program",
        "administrative"
    ],
    "wof:name":"Kathleen Graham Leema",
    "wof:placetype":"venue"
},
  "geometry": {"coordinates":[-122.53851,37.997612],"type":"Point"}
}