{
  "type": "Feature",
  "properties": {
    "addr:full":"8207 Atwater Jordan Rd Atwater CA 95301",
    "addr:housenumber":"8207",
    "addr:postcode":"95301",
    "addr:street":"Atwater Jordan Rd",
    "iso:country":"US",
    "sg:address":"8207 Atwater Jordan Rd",
    "sg:city":"Atwater",
    "sg:classifiers":[
        {
            "category":"Farming",
            "subcategory":"Crops",
            "type":"Manufacturing & Wholesale Goods"
        }
    ],
    "sg:phone":"+1 209 358 6265",
    "sg:postcode":"95301",
    "sg:province":"CA",
    "sg:tags":[
        "grove",
        "nut",
        "tree"
    ],
    "wof:name":"Joe Corvelo",
    "wof:placetype":"venue"
},
  "geometry": {"coordinates":[-120.63912000000001,37.331135],"type":"Point"}
}