{
  "type": "Feature",
  "properties": {
    "addr:full":"270 W Grand Ave Porterville CA 93257",
    "addr:housenumber":"270",
    "addr:postcode":"93257",
    "addr:street":"W Grand Ave",
    "iso:country":"US",
    "sg:address":"270 W Grand Ave",
    "sg:city":"Porterville",
    "sg:classifiers":[
        {
            "category":"Home & Garden",
            "subcategory":"Household Appliances",
            "type":"Retail Goods"
        }
    ],
    "sg:phone":"+1 559 784 4242",
    "sg:postcode":"93257",
    "sg:province":"CA",
    "wof:name":"Mel's Appliance Svc",
    "wof:placetype":"venue"
},
  "geometry": {"coordinates":[-119.022583,36.076793],"type":"Point"}
}