{
  "type": "Feature",
  "properties": {
    "iso:country":"US",
    "sg:address":"500 Sutter St Ste 310",
    "sg:city":"San Francisco",
    "sg:classifiers":[
        {
            "category":"Education",
            "subcategory":"School",
            "type":"Public Place"
        }
    ],
    "sg:phone":"+1 415 902 8873",
    "sg:postcode":"94101",
    "sg:province":"CA",
    "sg:website":"www.portuguesebrazil.com/",
    "wof:name":"Portuguese Brazil School",
    "wof:placetype":"venue"
},
  "geometry": {"coordinates":[-122.408851,37.789268],"type":"Point"}
}