{
  "type": "Feature",
  "properties": {
    "addr:full":"216 Auto Center Ct Modesto CA 95356",
    "addr:housenumber":"216",
    "addr:postcode":"ca 95356",
    "addr:street":"Auto Center Ct",
    "iso:country":"US",
    "sg:address":"216 Auto Center Ct",
    "sg:city":"Modesto",
    "sg:classifiers":[
        {
            "category":"Autos & Motor Vehicles",
            "subcategory":"Automobile Sales",
            "type":"Retail Goods"
        },
        {
            "category":"Wholesale",
            "subcategory":"Motor Vehicles",
            "type":"Manufacturing & Wholesale Goods"
        }
    ],
    "sg:phone":"+1 209 575 3825",
    "sg:postcode":"95356",
    "sg:province":"CA",
    "sg:tags":[
        "car",
        "dealer"
    ],
    "wof:name":"Show Time Wholesale",
    "wof:placetype":"venue"
},
  "geometry": {"coordinates":[-120.99334899999999,37.701731],"type":"Point"}
}