{
  "type": "Feature",
  "properties": {
    "addr:full":"24850 Ave Rockefeller Valencia CA 91355",
    "addr:housenumber":"24850",
    "addr:postcode":"91355",
    "addr:street":"Ave Rockefeller",
    "iso:country":"US",
    "sg:address":"24850 Ave Rockefeller",
    "sg:city":"Valencia",
    "sg:classifiers":[
        {
            "category":"Wholesale",
            "subcategory":"Motor Vehicles",
            "type":"Manufacturing & Wholesale Goods"
        }
    ],
    "sg:phone":"+1 661 295 1900",
    "sg:postcode":"91355",
    "sg:province":"CA",
    "sg:tags":[
        "automobile",
        "truck",
        "broker"
    ],
    "sg:website":"www.childs-albert.com",
    "wof:name":"Childs & Albert Inc",
    "wof:placetype":"venue"
},
  "geometry": {"coordinates":[-118.568348,34.429889],"type":"Point"}
}