{
  "type": "Feature",
  "properties": {
    "addr:full":"12338 Lakeshore Dr Lakeside CA 92040",
    "addr:housenumber":"12338",
    "addr:postcode":"92040",
    "addr:street":"Lakeshore Dr",
    "iso:country":"US",
    "sg:address":"12338 Lakeshore Dr",
    "sg:city":"Lakeside",
    "sg:classifiers":[
        {
            "category":"Wholesale",
            "subcategory":"Machinery & Supplies",
            "type":"Manufacturing & Wholesale Goods"
        }
    ],
    "sg:phone":"+1 619 561 3540",
    "sg:postcode":"92040",
    "sg:province":"CA",
    "sg:tags":[
        "equipment",
        "establishment"
    ],
    "wof:name":"Lakeside Upholstery",
    "wof:placetype":"venue"
},
  "geometry": {"coordinates":[-116.924119,32.859651],"type":"Point"}
}