{
  "type": "Feature",
  "properties": {
    "iso:country":"US",
    "sg:address":"596 Lighthouse Ave",
    "sg:city":"Monterey",
    "sg:classifiers":[
        {
            "category":"Personal",
            "subcategory":"Nail Salon",
            "type":"Services"
        }
    ],
    "sg:phone":"+1 831 643 0697",
    "sg:postcode":"93940",
    "sg:province":"CA",
    "wof:name":"Francis Nails",
    "wof:placetype":"venue"
},
  "geometry": {"coordinates":[-121.901692,36.613538],"type":"Point"}
}