{
  "type": "Feature",
  "properties": {
    "addr:full":"2661 S Lilac Ave Bloomington CA 92316",
    "addr:housenumber":"2661",
    "addr:postcode":"92316",
    "addr:street":"S Lilac Ave",
    "iso:country":"US",
    "sg:address":"2661 S Lilac Ave",
    "sg:city":"Bloomington",
    "sg:classifiers":[
        {
            "category":"Manufacturing",
            "subcategory":"Motor Vehicles & Parts",
            "type":"Manufacturing & Wholesale Goods"
        }
    ],
    "sg:phone":"+1 909 877 5940",
    "sg:postcode":"92316",
    "sg:province":"CA",
    "sg:tags":[
        "chassis",
        "mfg"
    ],
    "wof:name":"Steelco Inc",
    "wof:placetype":"venue"
},
  "geometry": {"coordinates":[-117.378989,34.06323],"type":"Point"}
}