{
  "type": "Feature",
  "properties": {
    "iso:country":"US",
    "sg:address":"3501 Gage Ave",
    "sg:city":"Bell",
    "sg:classifiers":[
        {
            "category":"Retail",
            "subcategory":"Auto Repair",
            "type":"Services"
        }
    ],
    "sg:phone":"+1 323 582 1579",
    "sg:postcode":"90201",
    "sg:province":"CA",
    "sg:tags":[
        "repairing",
        "automobile"
    ],
    "wof:name":"California Auto Care",
    "wof:placetype":"venue"
},
  "geometry": {"coordinates":[-118.202003,33.979801],"type":"Point"}
}