{
  "type": "Feature",
  "properties": {
    "addr:full":"2833 S Castle Harbour Pl Ontario CA 91761",
    "addr:housenumber":"2833",
    "addr:postcode":"91761",
    "addr:street":"S Castle Harbour Pl",
    "iso:country":"US",
    "sg:address":"2833 S Castle Harbour Pl",
    "sg:city":"Ontario",
    "sg:classifiers":[
        {
            "category":"Health Services",
            "subcategory":"Chiropractor",
            "type":"Services"
        }
    ],
    "sg:phone":"+1 909 226 9871",
    "sg:postcode":"91761",
    "sg:province":"CA",
    "sg:tags":[
        "chiropractic"
    ],
    "wof:name":"Olsen Family Realitor",
    "wof:placetype":"venue"
},
  "geometry": {"coordinates":[-117.616179,34.022651],"type":"Point"}
}