{
  "type": "Feature",
  "properties": {
    "addr:full":"3622 Rosemead Blvd Rosemead CA 91770",
    "addr:housenumber":"3622",
    "addr:postcode":"91770",
    "addr:street":"Rosemead Blvd",
    "iso:country":"US",
    "sg:address":"3622 Rosemead Blvd",
    "sg:city":"Rosemead",
    "sg:classifiers":[
        {
            "category":"Personal",
            "subcategory":"Beauty Salon",
            "type":"Services"
        },
        {
            "category":"Personal",
            "subcategory":"Barber",
            "type":"Services"
        }
    ],
    "sg:phone":"+1 626 572 2900",
    "sg:postcode":"91770",
    "sg:province":"CA",
    "sg:tags":[
        "hair"
    ],
    "sg:website":"www.supercuts.com",
    "wof:name":"Supercuts",
    "wof:placetype":"venue"
},
  "geometry": {"coordinates":[-118.072998,34.074402],"type":"Point"}
}