{
  "type": "Feature",
  "properties": {
    "iso:country":"US",
    "sg:address":"3800 Watt Ave",
    "sg:city":"Sacramento",
    "sg:classifiers":[
        {
            "category":"Professional",
            "subcategory":"Management & Consulting",
            "type":"Services"
        }
    ],
    "sg:phone":"+1 916 972 1969",
    "sg:postcode":"95821",
    "sg:province":"CA",
    "sg:tags":[
        "consultant",
        "business"
    ],
    "wof:name":"Performance Consulting Group",
    "wof:placetype":"venue"
},
  "geometry": {"coordinates":[-121.382931,38.635101],"type":"Point"}
}