{
  "type": "Feature",
  "properties": {
    "iso:country":"US",
    "sg:address":"3541 N Canyon Rd",
    "sg:city":"Camino",
    "sg:classifiers":[
        {
            "category":"Winery",
            "type":"Food & Drink"
        }
    ],
    "sg:phone":"+1 530 622 5100",
    "sg:postcode":"95709",
    "sg:province":"CA",
    "sg:website":"www.stonesthrowwines.com/",
    "wof:name":"Stones Throw Winery",
    "wof:placetype":"venue"
},
  "geometry": {"coordinates":[-120.71329799999999,38.760512],"type":"Point"}
}