{
  "type": "Feature",
  "properties": {
    "addr:full":"5953 Jamar Dr San Diego CA 92117",
    "addr:housenumber":"5953",
    "addr:postcode":"92117",
    "addr:street":"Jamar Dr",
    "iso:country":"US",
    "sg:address":"5953 Jamar Dr",
    "sg:city":"San Diego",
    "sg:classifiers":[
        {
            "category":"Wholesale",
            "subcategory":"Seafood",
            "type":"Manufacturing & Wholesale Goods"
        }
    ],
    "sg:phone":"+1 858 565 7482",
    "sg:postcode":"92117",
    "sg:province":"CA",
    "wof:name":"J B C Chartered",
    "wof:placetype":"venue"
},
  "geometry": {"coordinates":[-117.169768,32.830956],"type":"Point"}
}