{
  "type": "Feature",
  "properties": {
    "addr:full":"1820 S Grant St San Mateo CA 94402",
    "addr:housenumber":"1820",
    "addr:postcode":"94402",
    "addr:street":"S Grant St",
    "iso:country":"US",
    "sg:address":"1820 S Grant St",
    "sg:city":"San Mateo",
    "sg:classifiers":[
        {
            "category":"Food & Beverages",
            "subcategory":"Groceries & Convenience Stores",
            "type":"Retail Goods"
        }
    ],
    "sg:phone":"+1 650 570 6140",
    "sg:postcode":"94402",
    "sg:province":"CA",
    "wof:name":"Trader Joe's",
    "wof:placetype":"venue"
},
  "geometry": {"coordinates":[-122.302002,37.554901],"type":"Point"}
}