{
  "type": "Feature",
  "properties": {
    "iso:country":"US",
    "sg:address":"69930 Highway 111",
    "sg:city":"Rancho Mirage",
    "sg:classifiers":[
        {
            "category":"Restaurant",
            "type":"Food & Drink"
        }
    ],
    "sg:postcode":"92270",
    "sg:province":"CA",
    "wof:name":"Palms Cafe",
    "wof:placetype":"venue"
},
  "geometry": {"coordinates":[-116.444671,33.767959],"type":"Point"}
}