{
  "type": "Feature",
  "properties": {
    "iso:country":"US",
    "sg:address":"22750 Hawthorne Blvd",
    "sg:city":"Torrance",
    "sg:classifiers":[
        {
            "category":"Communications",
            "type":"Services"
        }
    ],
    "sg:phone":"+1 310 373 7502",
    "sg:postcode":"90505",
    "sg:province":"CA",
    "sg:tags":[
        "web",
        "design"
    ],
    "sg:website":"www.accelerateonline.net",
    "wof:name":"Acceletate Online Inc.",
    "wof:placetype":"venue"
},
  "geometry": {"coordinates":[-118.35081099999999,33.821655],"type":"Point"}
}