{
  "type": "Feature",
  "properties": {
    "iso:country":"US",
    "sg:address":"44139 Monterey Ave Ste A",
    "sg:city":"Palm Desert",
    "sg:classifiers":[
        {
            "category":"Health Services",
            "subcategory":"Optometrist",
            "type":"Services"
        }
    ],
    "sg:phone":"+1 760 773 3099",
    "sg:postcode":"92260",
    "sg:province":"CA",
    "wof:name":"Inland Eye Institute Medical Group Inc",
    "wof:placetype":"venue"
},
  "geometry": {"coordinates":[-116.39099899999999,33.727798],"type":"Point"}
}