{
  "type": "Feature",
  "properties": {
    "iso:country":"US",
    "sg:address":"740 S Olive St",
    "sg:city":"Los Angeles",
    "sg:classifiers":[
        {
            "category":"Professional",
            "subcategory":"Art Services",
            "type":"Services"
        }
    ],
    "sg:phone":"+1 213 327 0580",
    "sg:postcode":"90014",
    "sg:province":"CA",
    "sg:tags":[
        "photographer"
    ],
    "wof:name":"Gary Leonard Photography",
    "wof:placetype":"venue"
},
  "geometry": {"coordinates":[-118.256351,34.045703],"type":"Point"}
}