{
  "type": "Feature",
  "properties": {
    "addr:full":"447 Hudson St Healdsburg CA 95448",
    "addr:housenumber":"447",
    "addr:postcode":"95448",
    "addr:street":"Hudson St",
    "iso:country":"US",
    "sg:address":"447 Hudson St",
    "sg:city":"Healdsburg",
    "sg:classifiers":[
        {
            "category":"Shopping",
            "type":"Retail Goods"
        }
    ],
    "sg:phone":"+1 707 433 4398",
    "sg:postcode":"95448",
    "sg:province":"CA",
    "sg:tags":[
        "equipment",
        "wine",
        "supply"
    ],
    "wof:name":"Canals Capsules USA",
    "wof:placetype":"venue"
},
  "geometry": {"coordinates":[-122.863052,38.606465],"type":"Point"}
}