{
  "type": "Feature",
  "properties": {
    "addr:full":"2272 Cabrera Ave San Bernardino CA 92411",
    "addr:housenumber":"2272",
    "addr:postcode":"92411",
    "addr:street":"Cabrera Ave",
    "iso:country":"US",
    "sg:address":"2272 Cabrera Ave",
    "sg:city":"San Bernardino",
    "sg:classifiers":[
        {
            "category":"Manufacturing",
            "subcategory":"Tools & Machinery",
            "type":"Manufacturing & Wholesale Goods"
        }
    ],
    "sg:phone":"+1 909 880 6464",
    "sg:postcode":"92411",
    "sg:province":"CA",
    "sg:tags":[
        "automotive",
        "mfg",
        "repair"
    ],
    "wof:name":"Cucos Carburetors",
    "wof:placetype":"venue"
},
  "geometry": {"coordinates":[-117.320571,34.137592],"type":"Point"}
}