{
  "type": "Feature",
  "properties": {
    "addr:full":"257 Arlen Dr Rohnert Park CA 94928",
    "addr:housenumber":"257",
    "addr:postcode":"94928",
    "addr:street":"Arlen Dr",
    "iso:country":"US",
    "sg:address":"257 Arlen Dr",
    "sg:city":"Rohnert Park",
    "sg:classifiers":[
        {
            "category":"Building & Trades",
            "subcategory":"Construction",
            "type":"Services"
        }
    ],
    "sg:phone":"+1 707 792 0448",
    "sg:postcode":"94928",
    "sg:province":"CA",
    "sg:tags":[
        "painter"
    ],
    "wof:name":"Advantage Painting",
    "wof:placetype":"venue"
},
  "geometry": {"coordinates":[-122.70678700000001,38.339863],"type":"Point"}
}