{
  "type": "Feature",
  "properties": {
    "iso:country":"US",
    "sg:address":"1000 Universal Studios Blvd",
    "sg:city":"North Hollywood",
    "sg:classifiers":[
        {
            "category":"Deli",
            "type":"Food & Drink"
        },
        {
            "category":"Food & Beverages",
            "subcategory":"Bakery",
            "type":"Retail Goods"
        }
    ],
    "sg:phone":"+1 818 760 4484",
    "sg:postcode":"91608",
    "sg:province":"CA",
    "sg:tags":[
        "sandwich"
    ],
    "sg:website":"www.jodymaroni.com",
    "wof:name":"Jody Maroni Sausage Kingdom",
    "wof:placetype":"venue"
},
  "geometry": {"coordinates":[-118.351488,34.134247],"type":"Point"}
}