{
  "type": "Feature",
  "properties": {
    "iso:country":"US",
    "sg:address":"1250 N Parker St",
    "sg:city":"Orange",
    "sg:classifiers":[
        {
            "category":"Building & Trades",
            "subcategory":"Electrical",
            "type":"Services"
        }
    ],
    "sg:phone":"+1 714 639 0876",
    "sg:postcode":"92867",
    "sg:province":"CA",
    "sg:tags":[
        "electrician"
    ],
    "wof:name":"American Electric",
    "wof:placetype":"venue"
},
  "geometry": {"coordinates":[-117.85979500000001,33.808255],"type":"Point"}
}