{
  "type": "Feature",
  "properties": {
    "addr:full":"1296 E Baseline St San Bernardino CA 92410",
    "addr:housenumber":"1296",
    "addr:postcode":"92410",
    "addr:street":"E Baseline St",
    "iso:country":"US",
    "sg:address":"1296 E Baseline St",
    "sg:city":"San Bernardino",
    "sg:classifiers":[
        {
            "category":"Autos & Motor Vehicles",
            "subcategory":"Automobile Sales",
            "type":"Retail Goods"
        }
    ],
    "sg:phone":"+1 909 381 1976",
    "sg:postcode":"92410",
    "sg:province":"CA",
    "sg:tags":[
        "car",
        "dealer"
    ],
    "wof:name":"Inland Auto Boat & Rv SALES",
    "wof:placetype":"venue"
},
  "geometry": {"coordinates":[-117.260301,34.121392],"type":"Point"}
}