{
  "type": "Feature",
  "properties": {
    "iso:country":"US",
    "sg:address":"660 E 3rd Ave",
    "sg:city":"San Mateo",
    "sg:classifiers":[
        {
            "category":"Restaurant",
            "type":"Food & Drink"
        }
    ],
    "sg:phone":"+1 650 347 5414",
    "sg:postcode":"94401",
    "sg:province":"CA",
    "wof:name":"Taqueria El Nayarita",
    "wof:placetype":"venue"
},
  "geometry": {"coordinates":[-122.31999999999999,37.567402],"type":"Point"}
}