{
  "type": "Feature",
  "properties": {
    "iso:country":"US",
    "sg:address":"2700 Cahuenga Blvd E",
    "sg:city":"Los Angeles",
    "sg:classifiers":[
        {
            "category":"Manufacturing",
            "subcategory":"Tools & Machinery",
            "type":"Manufacturing & Wholesale Goods"
        }
    ],
    "sg:phone":"+1 323 851 9100",
    "sg:postcode":"90068",
    "sg:province":"CA",
    "sg:tags":[
        "photographic",
        "mfg"
    ],
    "wof:name":"Filmmakers United",
    "wof:placetype":"venue"
},
  "geometry": {"coordinates":[-118.33768499999999,34.11939],"type":"Point"}
}