{
  "type": "Feature",
  "properties": {
    "iso:country":"US",
    "sg:address":"3775 Via Nona Marie",
    "sg:city":"Carmel",
    "sg:classifiers":[
        {
            "category":"Real Estate",
            "subcategory":"Real Estate Services",
            "type":"Services"
        },
        {
            "category":"Real Estate",
            "subcategory":"Real Estate Agent",
            "type":"Services"
        }
    ],
    "sg:phone":"+1 831 622 4630",
    "sg:postcode":"93923",
    "sg:province":"CA",
    "sg:tags":[
        "buyer",
        "broker"
    ],
    "wof:name":"Elizabeth Smith",
    "wof:placetype":"venue"
},
  "geometry": {"coordinates":[-121.906007,36.538747],"type":"Point"}
}