{
  "type": "Feature",
  "properties": {
    "iso:country":"US",
    "sg:address":"57 Corte Gracitas",
    "sg:city":"Greenbrae",
    "sg:classifiers":[
        {
            "category":"Farming",
            "subcategory":"Vineyard",
            "type":"Manufacturing & Wholesale Goods"
        }
    ],
    "sg:phone":"+1 415 461 1071",
    "sg:postcode":"94904",
    "sg:province":"CA",
    "sg:tags":[
        "grape"
    ],
    "wof:name":"Peter Molinari",
    "wof:placetype":"venue"
},
  "geometry": {"coordinates":[-122.51919700000001,37.949436],"type":"Point"}
}