{
  "type": "Feature",
  "properties": {
    "addr:full":"10 United Nations Plz San Francisco CA 94102",
    "addr:housenumber":"10",
    "addr:postcode":"94102",
    "addr:street":"United Nations Plz",
    "iso:country":"US",
    "sg:address":"10 United Nations Plz",
    "sg:city":"San Francisco",
    "sg:classifiers":[
        {
            "category":"Restaurant",
            "type":"Food & Drink"
        }
    ],
    "sg:menulink":"http://www.allmenus.com/ca/san-francisco/170846-carls-jr/menu/",
    "sg:phone":"+1 415 431 3905",
    "sg:postcode":"94102",
    "sg:province":"CA",
    "sg:tags":[
        "burger",
        "american"
    ],
    "wof:name":"Carl's Jr.",
    "wof:placetype":"venue"
},
  "geometry": {"coordinates":[-122.41463299999999,37.779702],"type":"Point"}
}