{
  "type": "Feature",
  "properties": {
    "addr:full":"2141 Industrial Ct Suite B Vista CA 92081",
    "addr:housenumber":"2141",
    "addr:postcode":"92081",
    "addr:street":"Industrial Ct Suite B",
    "iso:country":"US",
    "sg:address":"2141 Industrial Ct Suite B",
    "sg:city":"Vista",
    "sg:classifiers":[
        {
            "category":"Building & Trades",
            "subcategory":"Construction",
            "type":"Services"
        },
        {
            "category":"Government",
            "subcategory":"Fire Station",
            "type":"Public Place"
        },
        {
            "category":"Building & Trades",
            "subcategory":"Plumbing",
            "type":"Services"
        },
        {
            "category":"Home & Garden",
            "subcategory":"Building Materials",
            "type":"Retail Goods"
        },
        {
            "category":"Home & Garden",
            "subcategory":"Hardware",
            "type":"Retail Goods"
        },
        {
            "category":"Utilities",
            "subcategory":"Water",
            "type":"Services"
        },
        {
            "category":"Building & Trades",
            "subcategory":"Cleaning & Sanitation",
            "type":"Services"
        },
        {
            "category":"Utilities",
            "subcategory":"Sewage",
            "type":"Services"
        }
    ],
    "sg:phone":"+1 760 726 6260",
    "sg:postcode":"92081",
    "sg:province":"CA",
    "sg:tags":[
        "cleaner",
        "systems-cleaning",
        "tank",
        "septic",
        "heater",
        "excavation",
        "repairer",
        "well",
        "system",
        "contractor",
        "tanks-removal",
        "pump",
        "piping",
        "plumber",
        "drilling",
        "maintenance",
        "installation",
        "plumbing-drain",
        "repair",
        "sewer"
    ],
    "sg:website":"http://sandiego.citysearch.com/profile/external/443259/vista_ca/roto_rooter_plumbing_drain_service.html?publisher=yellowpages&reference_id=1&placement=ypwebsitemip",
    "wof:name":"Roto-Rooter Plumbing & Drain Service",
    "wof:placetype":"venue"
},
  "geometry": {"coordinates":[-117.219356,33.168881],"type":"Point"}
}