{
  "type": "Feature",
  "properties": {
    "addr:full":"4 Lexington Way Trabuco Canyon CA 92679",
    "addr:housenumber":"4",
    "addr:postcode":"92679",
    "addr:street":"Lexington Way",
    "iso:country":"US",
    "sg:address":"4 Lexington Way",
    "sg:city":"Trabuco Canyon",
    "sg:classifiers":[
        {
            "category":"Real Estate",
            "subcategory":"Real Estate Agent",
            "type":"Services"
        }
    ],
    "sg:phone":"+1 949 858 1707",
    "sg:postcode":"92679",
    "sg:province":"CA",
    "wof:name":"Phillip Jackson Appraisal",
    "wof:placetype":"venue"
},
  "geometry": {"coordinates":[-117.580878,33.606608],"type":"Point"}
}