{
  "type": "Feature",
  "properties": {
    "iso:country":"US",
    "sg:address":"48688 Victoria Ln",
    "sg:city":"Oakhurst",
    "sg:classifiers":[
        {
            "category":"Travel",
            "subcategory":"Hotels & Motels",
            "type":"Entertainment"
        }
    ],
    "sg:phone":"+1 559 683 6860",
    "sg:postcode":"93644",
    "sg:province":"CA",
    "wof:name":"Chateau Du Sureau",
    "wof:placetype":"venue"
},
  "geometry": {"coordinates":[-119.660329,37.326631],"type":"Point"}
}