{
  "type": "Feature",
  "properties": {
    "addr:full":"204 Ave Sierra San Clemente CA 92672",
    "addr:housenumber":"204",
    "addr:postcode":"92672",
    "addr:street":"Ave Sierra",
    "iso:country":"US",
    "sg:address":"204 Ave Sierra",
    "sg:city":"San Clemente",
    "sg:classifiers":[
        {
            "category":"Manufacturing",
            "subcategory":"Glass & Minerals",
            "type":"Manufacturing & Wholesale Goods"
        }
    ],
    "sg:phone":"+1 949 498 6489",
    "sg:postcode":"92672",
    "sg:province":"CA",
    "sg:tags":[
        "product",
        "mfg"
    ],
    "wof:name":"Glassics",
    "wof:placetype":"venue"
},
  "geometry": {"coordinates":[-117.618488,33.433472],"type":"Point"}
}