{
  "type": "Feature",
  "properties": {
    "iso:country":"US",
    "sg:address":"1216 S Magnolia Ave",
    "sg:city":"Anaheim",
    "sg:classifiers":[
        {
            "category":"Food & Beverages",
            "subcategory":"Groceries & Convenience Stores",
            "type":"Retail Goods"
        }
    ],
    "sg:phone":"+1 714 995 4561",
    "sg:postcode":"92804",
    "sg:province":"CA",
    "sg:tags":[
        "grocer"
    ],
    "wof:name":"Chia Supermarket",
    "wof:placetype":"venue"
},
  "geometry": {"coordinates":[-117.975748,33.816716],"type":"Point"}
}