{
  "type": "Feature",
  "properties": {
    "iso:country":"US",
    "sg:address":"5104 N Harbor Dr",
    "sg:city":"San Diego",
    "sg:classifiers":[
        {
            "category":"Recreation",
            "subcategory":"Marina",
            "type":"Entertainment"
        }
    ],
    "sg:phone":"+1 619 222 1167",
    "sg:postcode":"92106",
    "sg:province":"CA",
    "sg:tags":[
        "building",
        "mini",
        "storage",
        "lease"
    ],
    "wof:name":"Sun Harbor Marina",
    "wof:placetype":"venue"
},
  "geometry": {"coordinates":[-117.22787,32.726075],"type":"Point"}
}