{
  "type": "Feature",
  "properties": {
    "iso:country":"US",
    "sg:address":"1627 20th St",
    "sg:city":"San Francisco",
    "sg:classifiers":[
        {
            "category":"Real Estate",
            "subcategory":"Real Estate Agent",
            "type":"Services"
        }
    ],
    "sg:phone":"+1 415 401 0455",
    "sg:postcode":"94107",
    "sg:province":"CA",
    "wof:name":"American First Funding",
    "wof:placetype":"venue"
},
  "geometry": {"coordinates":[-122.398007,37.759849],"type":"Point"}
}