{
  "type": "Feature",
  "properties": {
    "addr:full":"850 Santee St Los Angeles CA 90014",
    "addr:housenumber":"850",
    "addr:postcode":"90014",
    "addr:street":"Santee St",
    "iso:country":"US",
    "sg:address":"850 Santee St",
    "sg:city":"Los Angeles",
    "sg:classifiers":[
        {
            "category":"Shopping",
            "subcategory":"Crafts & Fabrics",
            "type":"Retail Goods"
        }
    ],
    "sg:phone":"+1 213 622 2201",
    "sg:postcode":"90014",
    "sg:province":"CA",
    "sg:tags":[
        "sewing"
    ],
    "wof:name":"Goal Fabric",
    "wof:placetype":"venue"
},
  "geometry": {"coordinates":[-118.25258700000001,34.040647],"type":"Point"}
}