{
  "type": "Feature",
  "properties": {
    "addr:full":"2625 N Tustin Ave Santa Ana CA 92705",
    "addr:housenumber":"2625",
    "addr:postcode":"92705",
    "addr:street":"N Tustin Ave",
    "iso:country":"US",
    "sg:address":"2625 N Tustin Ave",
    "sg:city":"Santa Ana",
    "sg:classifiers":[
        {
            "category":"Place Of Worship",
            "subcategory":"Synagogue",
            "type":"Public Place"
        },
        {
            "category":"Social Services",
            "subcategory":"Child Care",
            "type":"Services"
        }
    ],
    "sg:phone":"+1 714 628 4600",
    "sg:postcode":"92705",
    "sg:province":"CA",
    "sg:tags":[
        "day"
    ],
    "wof:name":"Temple Beth Sholom",
    "wof:placetype":"venue"
},
  "geometry": {"coordinates":[-117.835999,33.7714],"type":"Point"}
}