{
  "type": "Feature",
  "properties": {
    "addr:full":"9242 Bolsa Avenue Westminster CA 92683",
    "addr:housenumber":"9242",
    "addr:postcode":"92683",
    "addr:street":"Bolsa Avenue",
    "iso:country":"US",
    "sg:address":"9242 Bolsa Avenue",
    "sg:city":"Westminster",
    "sg:classifiers":[
        {
            "category":"Shopping",
            "subcategory":"Crafts & Fabrics",
            "type":"Retail Goods"
        }
    ],
    "sg:phone":"+1 714 895 1975",
    "sg:postcode":"92683",
    "sg:province":"CA",
    "sg:tags":[
        "store"
    ],
    "wof:name":"Hoa Binh Fabric",
    "wof:placetype":"venue"
},
  "geometry": {"coordinates":[-117.96831899999999,33.744831],"type":"Point"}
}