{
  "type": "Feature",
  "properties": {
    "addr:full":"3542 Balboa Street San Francisco CA 94121",
    "addr:housenumber":"3542",
    "addr:postcode":"94121",
    "addr:street":"Balboa Street",
    "iso:country":"US",
    "sg:address":"3542 Balboa Street",
    "sg:city":"San Francisco",
    "sg:classifiers":[
        {
            "category":"Building & Trades",
            "subcategory":"Construction",
            "type":"Services"
        }
    ],
    "sg:phone":"+1 415 387 4555",
    "sg:postcode":"94121",
    "sg:province":"CA",
    "sg:tags":[
        "contractor"
    ],
    "wof:name":"Eng T W Construction Company",
    "wof:placetype":"venue"
},
  "geometry": {"coordinates":[-122.497193,37.775863],"type":"Point"}
}