{
  "type": "Feature",
  "properties": {
    "addr:full":"26435 Club Dr Madera CA 93638",
    "addr:housenumber":"26435",
    "addr:postcode":"93638",
    "addr:street":"Club Dr",
    "iso:country":"US",
    "sg:address":"26435 Club Dr",
    "sg:city":"Madera",
    "sg:classifiers":[
        {
            "category":"Farming",
            "subcategory":"Crops",
            "type":"Manufacturing & Wholesale Goods"
        }
    ],
    "sg:phone":"+1 559 674 7706",
    "sg:postcode":"93638",
    "sg:province":"CA",
    "sg:tags":[
        "grove",
        "nut",
        "tree"
    ],
    "wof:name":"Don Schnoor Farms",
    "wof:placetype":"venue"
},
  "geometry": {"coordinates":[-120.06696700000001,37.024776],"type":"Point"}
}