{
  "type": "Feature",
  "properties": {
    "addr:full":"3406 American River Dr Sacramento CA 95864",
    "addr:housenumber":"3406",
    "addr:postcode":"95864",
    "addr:street":"American River Dr",
    "iso:country":"US",
    "sg:address":"3406 American River Dr",
    "sg:city":"Sacramento",
    "sg:classifiers":[
        {
            "category":"Utilities",
            "subcategory":"Refuse",
            "type":"Services"
        }
    ],
    "sg:phone":"+1 916 480 0742",
    "sg:postcode":"95864",
    "sg:province":"CA",
    "sg:tags":[
        "disposal",
        "waste"
    ],
    "wof:name":"Ecotechnology",
    "wof:placetype":"venue"
},
  "geometry": {"coordinates":[-121.38303999999999,38.570087],"type":"Point"}
}