{
  "type": "Feature",
  "properties": {
    "addr:full":"2525 Lincoln Blvd Venice CA 90291",
    "addr:housenumber":"2525",
    "addr:postcode":"90291",
    "addr:street":"Lincoln Blvd",
    "iso:country":"US",
    "sg:address":"2525 Lincoln Blvd",
    "sg:city":"Venice",
    "sg:classifiers":[
        {
            "category":"Shopping",
            "subcategory":"Catalog Store",
            "type":"Retail Goods"
        }
    ],
    "sg:phone":"+1 310 821 8488",
    "sg:postcode":"90291",
    "sg:province":"CA",
    "sg:tags":[
        "mail",
        "house"
    ],
    "wof:name":"Sherry Mindel",
    "wof:placetype":"venue"
},
  "geometry": {"coordinates":[-118.449344,33.992141],"type":"Point"}
}