{
  "type": "Feature",
  "properties": {
    "iso:country":"US",
    "sg:address":"1024 Anza St",
    "sg:city":"San Francisco",
    "sg:classifiers":[
        {
            "category":"Professional",
            "subcategory":"Management & Consulting",
            "type":"Services"
        }
    ],
    "sg:phone":"+1 415 876 8400",
    "sg:postcode":"94118",
    "sg:province":"CA",
    "sg:tags":[
        "consultant",
        "training"
    ],
    "wof:name":"Elkind Group",
    "wof:placetype":"venue"
},
  "geometry": {"coordinates":[-122.45964499999999,37.77937],"type":"Point"}
}