{
  "type": "Feature",
  "properties": {
    "addr:full":"599 S Bascom Avenue San Jose CA 95128",
    "addr:housenumber":"599",
    "addr:postcode":"95128",
    "addr:street":"S Bascom Avenue",
    "iso:country":"US",
    "sg:address":"599 S Bascom Avenue",
    "sg:city":"San Jose",
    "sg:classifiers":[
        {
            "category":"Shopping",
            "subcategory":"Florist",
            "type":"Retail Goods"
        }
    ],
    "sg:phone":"+1 408 293 4596",
    "sg:postcode":"95128",
    "sg:province":"CA",
    "wof:name":"Cute Flowers",
    "wof:placetype":"venue"
},
  "geometry": {"coordinates":[-121.931815,37.316446],"type":"Point"}
}