{
  "type": "Feature",
  "properties": {
    "iso:country":"US",
    "sg:address":"18523 Roscoe Blvd",
    "sg:city":"Northridge",
    "sg:classifiers":[
        {
            "category":"Personal",
            "subcategory":"Beauty Salon",
            "type":"Services"
        }
    ],
    "sg:phone":"+1 818 886 6011",
    "sg:postcode":"91324",
    "sg:province":"CA",
    "wof:name":"Black Hair & Beyond",
    "wof:placetype":"venue"
},
  "geometry": {"coordinates":[-118.538223,34.220771],"type":"Point"}
}