{
  "type": "Feature",
  "properties": {
    "iso:country":"US",
    "sg:address":"16814 Packers Bay Rd",
    "sg:city":"Lakehead",
    "sg:classifiers":[
        {
            "category":"Manufacturing",
            "subcategory":"Watercraft",
            "type":"Manufacturing & Wholesale Goods"
        }
    ],
    "sg:phone":"+1 530 275 9760",
    "sg:postcode":"96051",
    "sg:province":"CA",
    "sg:tags":[
        "houseboat"
    ],
    "sg:website":"www.packersbay.com",
    "wof:name":"Holiday Flotels Inc",
    "wof:placetype":"venue"
},
  "geometry": {"coordinates":[-122.32649600000001,40.789522],"type":"Point"}
}