{
  "type": "Feature",
  "properties": {
    "addr:full":"143 N Glassell Orange CA 92866",
    "addr:housenumber":"143",
    "addr:postcode":"92866",
    "addr:street":"N Glassell",
    "iso:country":"US",
    "sg:address":"143 N Glassell",
    "sg:city":"Orange",
    "sg:classifiers":[
        {
            "category":"Food & Beverages",
            "subcategory":"Liquor & Beverages",
            "type":"Retail Goods"
        }
    ],
    "sg:phone":"+1 714 997 2337",
    "sg:postcode":"92866",
    "sg:province":"CA",
    "sg:tags":[
        "beer",
        "spirit",
        "wine"
    ],
    "sg:website":"www.brueryprovisions.com",
    "wof:name":"The Bruery Provisions",
    "wof:placetype":"venue"
},
  "geometry": {"coordinates":[-117.85306799999999,33.789081],"type":"Point"}
}