{
  "type": "Feature",
  "properties": {
    "iso:country":"US",
    "sg:address":"1910 Lanai Dr",
    "sg:city":"Costa Mesa",
    "sg:classifiers":[
        {
            "category":"Shopping",
            "subcategory":"Florist",
            "type":"Retail Goods"
        }
    ],
    "sg:phone":"+1 949 293 9830",
    "sg:postcode":"92626",
    "sg:province":"CA",
    "wof:name":"Picket Fence Bloom N Flower De",
    "wof:placetype":"venue"
},
  "geometry": {"coordinates":[-117.937729,33.678019],"type":"Point"}
}