{
  "type": "Feature",
  "properties": {
    "iso:country":"US",
    "sg:address":"82310 Ocotillo Ave",
    "sg:city":"Indio",
    "sg:classifiers":[
        {
            "category":"Building & Trades",
            "subcategory":"Pest Control",
            "type":"Services"
        }
    ],
    "sg:phone":"+1 760 347 5561",
    "sg:postcode":"92201",
    "sg:province":"CA",
    "wof:name":"Manuel's Pest Control",
    "wof:placetype":"venue"
},
  "geometry": {"coordinates":[-116.225752,33.730014],"type":"Point"}
}