{
  "type": "Feature",
  "properties": {
    "addr:full":"3882 Chestnut Ave Concord CA 94519",
    "addr:housenumber":"3882",
    "addr:postcode":"94519",
    "addr:street":"Chestnut Ave",
    "iso:country":"US",
    "sg:address":"3882 Chestnut Ave",
    "sg:city":"Concord",
    "sg:classifiers":[
        {
            "category":"Building & Trades",
            "subcategory":"Construction",
            "type":"Services"
        }
    ],
    "sg:phone":"+1 925 827 1762",
    "sg:postcode":"94519",
    "sg:province":"CA",
    "sg:tags":[
        "house"
    ],
    "wof:name":"Consolidated Home Services",
    "wof:placetype":"venue"
},
  "geometry": {"coordinates":[-122.005331,37.971795],"type":"Point"}
}