{
  "type": "Feature",
  "properties": {
    "addr:full":"914 Beaumont Ave Beaumont CA 92223",
    "addr:housenumber":"914",
    "addr:postcode":"92223",
    "addr:street":"Beaumont Ave",
    "iso:country":"US",
    "sg:address":"914 Beaumont Ave",
    "sg:city":"Beaumont",
    "sg:classifiers":[
        {
            "category":"Health Services",
            "subcategory":"Health Practitioner",
            "type":"Services"
        }
    ],
    "sg:phone":"+1 951 769 1668",
    "sg:postcode":"92223",
    "sg:province":"CA",
    "sg:tags":[
        "medicine",
        "alternative"
    ],
    "wof:name":"Holistic Renewal Ctr",
    "wof:placetype":"venue"
},
  "geometry": {"coordinates":[-116.977096,33.935329],"type":"Point"}
}