{
  "type": "Feature",
  "properties": {
    "addr:full":"6676 Rosemead Blvd Pico Rivera CA 90660",
    "addr:housenumber":"6676",
    "addr:postcode":"90660",
    "addr:street":"Rosemead Blvd",
    "iso:country":"US",
    "sg:address":"6676 Rosemead Blvd",
    "sg:city":"Pico Rivera",
    "sg:classifiers":[
        {
            "category":"Bakery",
            "type":"Food & Drink"
        }
    ],
    "sg:phone":"+1 562 222 1054",
    "sg:postcode":"90660",
    "sg:province":"CA",
    "wof:name":"La Bonita Bakery",
    "wof:placetype":"venue"
},
  "geometry": {"coordinates":[-118.096001,33.984798],"type":"Point"}
}