{
  "type": "Feature",
  "properties": {
    "addr:full":"2266 N Sierra Way San Bernardino CA 92405",
    "addr:housenumber":"2266",
    "addr:postcode":"92405",
    "addr:street":"N Sierra Way",
    "iso:country":"US",
    "sg:address":"2266 N Sierra Way",
    "sg:city":"San Bernardino",
    "sg:classifiers":[
        {
            "category":"Retail",
            "subcategory":"Car Wash",
            "type":"Services"
        }
    ],
    "sg:phone":"+1 909 886 6216",
    "sg:postcode":"92405",
    "sg:province":"CA",
    "sg:tags":[
        "polishing",
        "washing"
    ],
    "wof:name":"San Bernardino Car Wash",
    "wof:placetype":"venue"
},
  "geometry": {"coordinates":[-117.28514199999999,34.140671],"type":"Point"}
}