{
  "type": "Feature",
  "properties": {
    "iso:country":"US",
    "sg:address":"4075 W Rosecrans Ave",
    "sg:city":"Hawthorne",
    "sg:classifiers":[
        {
            "category":"Professional",
            "type":"Services"
        }
    ],
    "sg:phone":"+1 310 372 2300",
    "sg:postcode":"90250",
    "sg:province":"CA",
    "wof:name":"Babalu Jeans",
    "wof:placetype":"venue"
},
  "geometry": {"coordinates":[-118.346557,33.901985],"type":"Point"}
}