{
  "type": "Feature",
  "properties": {
    "iso:country":"US",
    "sg:address":"2787 del Monte St",
    "sg:city":"West Sacramento",
    "sg:classifiers":[
        {
            "category":"Organizations",
            "subcategory":"Non-profit Organization",
            "type":"Services"
        }
    ],
    "sg:phone":"+1 916 372 5277",
    "sg:postcode":"95691",
    "sg:province":"CA",
    "wof:name":"Sacramento Traditional Jazz",
    "wof:placetype":"venue"
},
  "geometry": {"coordinates":[-121.547164,38.569757],"type":"Point"}
}