{
  "type": "Feature",
  "properties": {
    "addr:full":"1647 Willow Pass Rd Ste 400 Concord CA 94520",
    "addr:housenumber":"1647",
    "addr:postcode":"94520",
    "addr:street":"Willow Pass Rd Ste 400",
    "iso:country":"US",
    "sg:address":"1647 Willow Pass Rd Ste 400",
    "sg:city":"Concord",
    "sg:classifiers":[
        {
            "category":"Professional",
            "subcategory":"Employment Agencies",
            "type":"Services"
        },
        {
            "category":"Health Services",
            "subcategory":"Health Practitioner",
            "type":"Services"
        },
        {
            "category":"Social Services",
            "subcategory":"Adult Care",
            "type":"Services"
        }
    ],
    "sg:phone":"+1 925 435 8085",
    "sg:postcode":"94520",
    "sg:province":"CA",
    "sg:tags":[
        "nurses-home",
        "home"
    ],
    "sg:website":"http://www.premiereldercarellc.com",
    "wof:name":"Premier Elder Care LLC",
    "wof:placetype":"venue"
},
  "geometry": {"coordinates":[-122.043879,37.971925],"type":"Point"}
}