{
  "type": "Feature",
  "properties": {
    "addr:full":"9747 Wheatland Ave Sunland CA 91040",
    "addr:housenumber":"9747",
    "addr:postcode":"91040",
    "addr:street":"Wheatland Ave",
    "iso:country":"US",
    "sg:address":"9747 Wheatland Ave",
    "sg:city":"Sunland",
    "sg:classifiers":[
        {
            "category":"Real Estate",
            "subcategory":"Real Estate Agent",
            "type":"Services"
        }
    ],
    "sg:phone":"+1 818 951 7737",
    "sg:postcode":"91040",
    "sg:province":"CA",
    "wof:name":"Snow Realty",
    "wof:placetype":"venue"
},
  "geometry": {"coordinates":[-118.357544,34.246273],"type":"Point"}
}