{
  "type": "Feature",
  "properties": {
    "addr:full":"2620 Worden St San Diego CA 92110",
    "addr:housenumber":"2620",
    "addr:postcode":"92110",
    "addr:street":"Worden St",
    "iso:country":"US",
    "sg:address":"2620 Worden St",
    "sg:city":"San Diego",
    "sg:classifiers":[
        {
            "category":"Real Estate",
            "subcategory":"Developer",
            "type":"Services"
        }
    ],
    "sg:phone":"+1 619 223 1860",
    "sg:postcode":"92110",
    "sg:province":"CA",
    "wof:name":"Matrix Services",
    "wof:placetype":"venue"
},
  "geometry": {"coordinates":[-117.226733,32.747485],"type":"Point"}
}