{
  "type": "Feature",
  "properties": {
    "iso:country":"US",
    "sg:address":"5755 Willowtree Dr",
    "sg:city":"Agoura Hills",
    "sg:classifiers":[
        {
            "category":"Wholesale",
            "subcategory":"Chemicals & Plastics",
            "type":"Manufacturing & Wholesale Goods"
        }
    ],
    "sg:phone":"+1 818 707 0939",
    "sg:postcode":"91301",
    "sg:province":"CA",
    "wof:name":"Amway Distributors",
    "wof:placetype":"venue"
},
  "geometry": {"coordinates":[-118.775931,34.156708],"type":"Point"}
}