{
  "type": "Feature",
  "properties": {
    "iso:country":"US",
    "sg:address":"2770 Winrock Ave",
    "sg:city":"Altadena",
    "sg:classifiers":[
        {
            "category":"Shopping",
            "subcategory":"Stationery & Office Supplies",
            "type":"Retail Goods"
        }
    ],
    "sg:phone":"+1 626 794 9700",
    "sg:postcode":"91001",
    "sg:province":"CA",
    "sg:tags":[
        "equipment"
    ],
    "sg:website":"www.systematedproducts.com",
    "wof:name":"Systemated Business Products",
    "wof:placetype":"venue"
},
  "geometry": {"coordinates":[-118.11806,34.194154],"type":"Point"}
}