{
  "type": "Feature",
  "properties": {
    "addr:full":"14689 W Whitesbridge Ave Kerman CA 93630",
    "addr:housenumber":"14689",
    "addr:postcode":"93630",
    "addr:street":"W Whitesbridge Ave",
    "iso:country":"US",
    "sg:address":"14689 W Whitesbridge Ave",
    "sg:city":"Kerman",
    "sg:classifiers":[
        {
            "category":"Manufacturing",
            "subcategory":"Printing",
            "type":"Manufacturing & Wholesale Goods"
        }
    ],
    "sg:phone":"+1 559 655 3939",
    "sg:postcode":"93630",
    "sg:province":"CA",
    "sg:tags":[
        "newspaper"
    ],
    "wof:name":"Westside Advance",
    "wof:placetype":"venue"
},
  "geometry": {"coordinates":[-120.05564200000001,36.734868],"type":"Point"}
}