{
  "type": "Feature",
  "properties": {
    "iso:country":"US",
    "sg:address":"825 Rutherford Cir",
    "sg:city":"Brentwood",
    "sg:classifiers":[
        {
            "category":"Real Estate",
            "subcategory":"Real Estate Agent",
            "type":"Services"
        }
    ],
    "sg:phone":"+1 925 207 5963",
    "sg:postcode":"94513",
    "sg:province":"CA",
    "wof:name":"APPLEHILLHOMES.NET",
    "wof:placetype":"venue"
},
  "geometry": {"coordinates":[-121.730082,37.933113],"type":"Point"}
}