{
  "type": "Feature",
  "properties": {
    "iso:country":"US",
    "sg:address":"735 Santa Cruz Ave",
    "sg:city":"Menlo Park",
    "sg:classifiers":[
        {
            "category":"Banks & Credit Unions",
            "subcategory":"Bank",
            "type":"Services"
        }
    ],
    "sg:phone":"+1 650 855 7548",
    "sg:postcode":"94025",
    "sg:province":"CA",
    "sg:tags":[
        "national",
        "commercial"
    ],
    "wof:name":"Wells Fargo",
    "wof:placetype":"venue"
},
  "geometry": {"coordinates":[-122.184898,37.451063],"type":"Point"}
}