{
  "type": "Feature",
  "properties": {
    "addr:full":"12739 Lakewood Blvd Downey CA 90242",
    "addr:housenumber":"12739",
    "addr:postcode":"90242",
    "addr:street":"Lakewood Blvd",
    "iso:country":"US",
    "sg:address":"12739 Lakewood Blvd",
    "sg:city":"Downey",
    "sg:classifiers":[
        {
            "category":"Real Estate",
            "subcategory":"Real Estate Agent",
            "type":"Services"
        }
    ],
    "sg:phone":"+1 562 904 7222",
    "sg:postcode":"90242",
    "sg:province":"CA",
    "wof:name":"Casa Propia Realty & Finance",
    "wof:placetype":"venue"
},
  "geometry": {"coordinates":[-118.139537,33.914729],"type":"Point"}
}