{
  "type": "Feature",
  "properties": {
    "addr:full":"96 San Domingo Way Novato CA 94945",
    "addr:housenumber":"96",
    "addr:postcode":"94945",
    "addr:street":"San Domingo Way",
    "iso:country":"US",
    "sg:address":"96 San Domingo Way",
    "sg:city":"Novato",
    "sg:classifiers":[
        {
            "category":"Shopping",
            "subcategory":"Florist",
            "type":"Retail Goods"
        }
    ],
    "sg:phone":"+1 415 250 3344",
    "sg:postcode":"94945",
    "sg:province":"CA",
    "wof:name":"Fleurish",
    "wof:placetype":"venue"
},
  "geometry": {"coordinates":[-122.602069,38.125164],"type":"Point"}
}