{
  "type": "Feature",
  "properties": {
    "iso:country":"US",
    "sg:address":"701 Ellis Rd",
    "sg:city":"Marysville",
    "sg:classifiers":[
        {
            "category":"Manufacturing",
            "subcategory":"Tools & Machinery",
            "type":"Manufacturing & Wholesale Goods"
        }
    ],
    "sg:phone":"+1 530 742 4686",
    "sg:postcode":"95901",
    "sg:province":"CA",
    "sg:tags":[
        "scale"
    ],
    "wof:name":"Schrader Scales Shop",
    "wof:placetype":"venue"
},
  "geometry": {"coordinates":[-121.587942,39.197959],"type":"Point"}
}