{
  "type": "Feature",
  "properties": {
    "addr:full":"11791 Monarch St Garden Grove CA 92841",
    "addr:housenumber":"11791",
    "addr:postcode":"92841",
    "addr:street":"Monarch St",
    "iso:country":"US",
    "sg:address":"11791 Monarch St",
    "sg:city":"Garden Grove",
    "sg:classifiers":[
        {
            "category":"Manufacturing",
            "subcategory":"Printing",
            "type":"Manufacturing & Wholesale Goods"
        }
    ],
    "sg:phone":"+1 714 698 2883",
    "sg:postcode":"92841",
    "sg:province":"CA",
    "sg:tags":[
        "multimedia"
    ],
    "wof:name":"Ikanoi Media Inc",
    "wof:placetype":"venue"
},
  "geometry": {"coordinates":[-118.005942,33.788465],"type":"Point"}
}