{
  "type": "Feature",
  "properties": {
    "iso:country":"US",
    "sg:address":"541 Mountain View Ave",
    "sg:city":"Oxnard",
    "sg:classifiers":[
        {
            "category":"Manufacturing",
            "subcategory":"Food",
            "type":"Manufacturing & Wholesale Goods"
        }
    ],
    "sg:phone":"+1 805 487 0061",
    "sg:postcode":"93030",
    "sg:province":"CA",
    "sg:tags":[
        "ice",
        "mfg"
    ],
    "wof:name":"Superior Ice",
    "wof:placetype":"venue"
},
  "geometry": {"coordinates":[-119.170098,34.193755],"type":"Point"}
}