{
  "type": "Feature",
  "properties": {
    "iso:country":"US",
    "sg:address":"13762 Newport Ave Ste C",
    "sg:city":"Tustin",
    "sg:classifiers":[
        {
            "category":"Health Services",
            "subcategory":"Health Practitioner",
            "type":"Services"
        },
        {
            "category":"Health Services",
            "subcategory":"Chiropractor",
            "type":"Services"
        }
    ],
    "sg:phone":"+1 714 838 2225",
    "sg:postcode":"92780",
    "sg:province":"CA",
    "sg:tags":[
        "medicine",
        "alternative",
        "chiropractic"
    ],
    "sg:website":"www.tustincitychiropractic.com",
    "wof:name":"City Chiropractic",
    "wof:placetype":"venue"
},
  "geometry": {"coordinates":[-117.819209,33.740523],"type":"Point"}
}