{
  "type": "Feature",
  "properties": {
    "addr:full":"2007 E Compton Blvd Compton CA 90221",
    "addr:housenumber":"2007",
    "addr:postcode":"90221",
    "addr:street":"E Compton Blvd",
    "iso:country":"US",
    "sg:address":"2007 E Compton Blvd",
    "sg:city":"Compton",
    "sg:classifiers":[
        {
            "category":"Education",
            "subcategory":"College",
            "type":"Public Place"
        }
    ],
    "sg:phone":"+1 310 609 2704",
    "sg:postcode":"90221",
    "sg:province":"CA",
    "sg:tags":[
        "academic",
        "university",
        "school"
    ],
    "sg:website":"www.yuin.edu",
    "wof:name":"Yuin University",
    "wof:placetype":"venue"
},
  "geometry": {"coordinates":[-118.200996,33.896198],"type":"Point"}
}