{
  "type": "Feature",
  "properties": {
    "addr:full":"16011 Whittier Blvd Whittier CA 90603",
    "addr:housenumber":"16011",
    "addr:postcode":"90603",
    "addr:street":"Whittier Blvd",
    "iso:country":"US",
    "sg:address":"16011 Whittier Blvd",
    "sg:city":"Whittier",
    "sg:classifiers":[
        {
            "category":"Education",
            "subcategory":"School",
            "type":"Public Place"
        }
    ],
    "sg:phone":"+1 562 902 7561",
    "sg:postcode":"90603",
    "sg:province":"CA",
    "sg:tags":[
        "academic",
        "special"
    ],
    "wof:name":"Whittier Area Parents Assn",
    "wof:placetype":"venue"
},
  "geometry": {"coordinates":[-117.988387,33.942503],"type":"Point"}
}