{
  "type": "Feature",
  "properties": {
    "addr:full":"10331 Monterey Pine Ln Yucaipa CA 92399",
    "addr:housenumber":"10331",
    "addr:postcode":"92399",
    "addr:street":"Monterey Pine Ln",
    "iso:country":"US",
    "sg:address":"10331 Monterey Pine Ln",
    "sg:city":"Yucaipa",
    "sg:classifiers":[
        {
            "category":"Building & Trades",
            "subcategory":"Landscaping Services",
            "type":"Services"
        }
    ],
    "sg:phone":"+1 909 797 7792",
    "sg:postcode":"92399",
    "sg:province":"CA",
    "sg:tags":[
        "gardening"
    ],
    "wof:name":"Urban Environmental Services",
    "wof:placetype":"venue"
},
  "geometry": {"coordinates":[-117.038799,34.065547],"type":"Point"}
}