{
  "type": "Feature",
  "properties": {
    "iso:country":"US",
    "sg:address":"418 Petaluma Ave",
    "sg:city":"Sebastopol",
    "sg:classifiers":[
        {
            "category":"Real Estate",
            "subcategory":"Architect",
            "type":"Services"
        }
    ],
    "sg:phone":"+1 707 829 3226",
    "sg:postcode":"95472",
    "sg:province":"CA",
    "wof:name":"Marilyn Standley Drafting",
    "wof:placetype":"venue"
},
  "geometry": {"coordinates":[-122.82136199999999,38.398526],"type":"Point"}
}