{
  "type": "Feature",
  "properties": {
    "iso:country":"US",
    "sg:address":"460 S. California Avenue Suite B1",
    "sg:city":"Palo Alto",
    "sg:classifiers":[
        {
            "category":"Professional",
            "subcategory":"Computer Services",
            "type":"Services"
        }
    ],
    "sg:phone":"+1 650 485 2956",
    "sg:postcode":"94306",
    "sg:province":"CA",
    "sg:website":"http://www.guidebookapp.com",
    "wof:name":"Guidebook",
    "wof:placetype":"venue"
},
  "geometry": {"coordinates":[-122.145112,37.426104],"type":"Point"}
}