{
  "type": "Feature",
  "properties": {
    "iso:country":"US",
    "sg:address":"2699 E 28th St",
    "sg:city":"Long Beach",
    "sg:classifiers":[
        {
            "category":"Professional",
            "type":"Services"
        }
    ],
    "sg:phone":"+1 562 426 6654",
    "sg:postcode":"90755",
    "sg:province":"CA",
    "wof:name":"Parani Matthiesen Co",
    "wof:placetype":"venue"
},
  "geometry": {"coordinates":[-118.160698,33.808029],"type":"Point"}
}