{
  "type": "Feature",
  "properties": {
    "addr:full":"2736 N Bristol St Santa Ana CA 92706",
    "addr:housenumber":"2736",
    "addr:postcode":"92706",
    "addr:street":"N Bristol St",
    "iso:country":"US",
    "sg:address":"2736 N Bristol St",
    "sg:city":"Santa Ana",
    "sg:classifiers":[
        {
            "category":"Professional",
            "subcategory":"Art Services",
            "type":"Services"
        }
    ],
    "sg:phone":"+1 714 836 9425",
    "sg:postcode":"92706",
    "sg:province":"CA",
    "sg:tags":[
        "graphic",
        "designer"
    ],
    "wof:name":"Compu-Signs",
    "wof:placetype":"venue"
},
  "geometry": {"coordinates":[-117.884761,33.774848],"type":"Point"}
}