{
  "type": "Feature",
  "properties": {
    "iso:country":"US",
    "sg:address":"818 Gateview Dr",
    "sg:city":"San Jose",
    "sg:classifiers":[
        {
            "category":"Real Estate",
            "subcategory":"Real Estate Agent",
            "type":"Services"
        }
    ],
    "sg:phone":"+1 408 926 0692",
    "sg:postcode":"95133",
    "sg:province":"CA",
    "sg:tags":[
        "preparation",
        "tax",
        "return"
    ],
    "wof:name":"Asian Tax Service",
    "wof:placetype":"venue"
},
  "geometry": {"coordinates":[-121.85903500000001,37.379164],"type":"Point"}
}