{
  "type": "Feature",
  "properties": {
    "iso:country":"US",
    "sg:address":"26336 Western Ave",
    "sg:city":"Lomita",
    "sg:classifiers":[
        {
            "category":"Personal",
            "subcategory":"Beauty Salon",
            "type":"Services"
        }
    ],
    "sg:phone":"+1 310 325 9566",
    "sg:postcode":"90717",
    "sg:province":"CA",
    "wof:name":"Salon De Sola",
    "wof:placetype":"venue"
},
  "geometry": {"coordinates":[-118.309883,33.782531],"type":"Point"}
}