{
  "type": "Feature",
  "properties": {
    "iso:country":"US",
    "sg:address":"4625 Van Nuys Blvd",
    "sg:city":"Sherman Oaks",
    "sg:classifiers":[
        {
            "category":"Arena",
            "subcategory":"Sports Club",
            "type":"Entertainment"
        }
    ],
    "sg:phone":"+1 818 380 0822",
    "sg:postcode":"91403",
    "sg:province":"CA",
    "sg:tags":[
        "martial art"
    ],
    "wof:name":"La Wing Chun Kung Fu",
    "wof:placetype":"venue"
},
  "geometry": {"coordinates":[-118.448702,34.155574],"type":"Point"}
}