{
  "type": "Feature",
  "properties": {
    "iso:country":"US",
    "sg:address":"1412 Freeman St",
    "sg:city":"Marysville",
    "sg:classifiers":[
        {
            "category":"Building & Trades",
            "subcategory":"Construction",
            "type":"Services"
        }
    ],
    "sg:phone":"+1 530 741 2382",
    "sg:postcode":"95901",
    "sg:province":"CA",
    "sg:tags":[
        "layer",
        "carpet"
    ],
    "wof:name":"PCM Carpet Svc",
    "wof:placetype":"venue"
},
  "geometry": {"coordinates":[-121.579379,39.152295],"type":"Point"}
}