{
  "type": "Feature",
  "properties": {
    "iso:country":"US",
    "sg:address":"830 Bear Valley Pkwy",
    "sg:city":"Escondido",
    "sg:classifiers":[
        {
            "category":"Building & Trades",
            "subcategory":"Electrical",
            "type":"Services"
        }
    ],
    "sg:phone":"+1 760 743 3409",
    "sg:postcode":"92025",
    "sg:province":"CA",
    "sg:tags":[
        "electric",
        "contractor"
    ],
    "wof:name":"Mc Cullough Electric",
    "wof:placetype":"venue"
},
  "geometry": {"coordinates":[-117.05118899999999,33.106453],"type":"Point"}
}