{
  "type": "Feature",
  "properties": {
    "iso:country":"US",
    "sg:address":"1131 Melba Rd",
    "sg:city":"Encinitas",
    "sg:classifiers":[
        {
            "category":"Professional",
            "type":"Services"
        }
    ],
    "sg:phone":"+1 760 633 1912",
    "sg:postcode":"92024",
    "sg:province":"CA",
    "wof:name":"Kellys Simply Fresh",
    "wof:placetype":"venue"
},
  "geometry": {"coordinates":[-117.266969,33.039746],"type":"Point"}
}