{
  "type": "Feature",
  "properties": {
    "iso:country":"US",
    "sg:address":"6263 Leland Way",
    "sg:city":"Los Angeles",
    "sg:classifiers":[
        {
            "category":"Restaurant",
            "type":"Food & Drink"
        }
    ],
    "sg:phone":"+1 323 962 1900",
    "sg:postcode":"90028",
    "sg:province":"CA",
    "sg:tags":[
        "new",
        "american"
    ],
    "sg:website":"www.offvine.com",
    "wof:name":"Off Vine Restaurant",
    "wof:placetype":"venue"
},
  "geometry": {"coordinates":[-118.325996,34.096901],"type":"Point"}
}