{
  "type": "Feature",
  "properties": {
    "addr:full":"39395 Paseo Padre Pkwy 2nd Fl Fremont CA 94538",
    "addr:housenumber":"39395",
    "addr:postcode":"94538",
    "addr:street":"Paseo Padre Pkwy 2Nd",
    "iso:country":"US",
    "sg:address":"39395 Paseo Padre Pkwy 2nd Fl",
    "sg:city":"Fremont",
    "sg:classifiers":[
        {
            "category":"Banks & Credit Unions",
            "subcategory":"Bank",
            "type":"Services"
        },
        {
            "category":"Banks & Credit Unions",
            "subcategory":"Financial Services",
            "type":"Services"
        }
    ],
    "sg:phone":"+1 510 796 0517",
    "sg:postcode":"94538",
    "sg:province":"CA",
    "sg:tags":[
        "saving",
        "loan",
        "commercial"
    ],
    "sg:website":"https://www.chase.com/",
    "wof:name":"Chase Bank",
    "wof:placetype":"venue"
},
  "geometry": {"coordinates":[-121.97791100000001,37.551891],"type":"Point"}
}