{
  "type": "Feature",
  "properties": {
    "iso:country":"US",
    "sg:address":"46 Market St",
    "sg:city":"Venice",
    "sg:classifiers":[
        {
            "category":"Communications",
            "subcategory":"Film & Video Production",
            "type":"Services"
        }
    ],
    "sg:phone":"+1 310 396 1200",
    "sg:postcode":"90291",
    "sg:province":"CA",
    "sg:tags":[
        "motion",
        "picture",
        "studio",
        "producer"
    ],
    "wof:name":"Yerkovich Productions",
    "wof:placetype":"venue"
},
  "geometry": {"coordinates":[-118.473004,33.988041],"type":"Point"}
}