{
  "type": "Feature",
  "properties": {
    "addr:full":"2021 W March Ln Stockton CA 95207",
    "addr:housenumber":"2021",
    "addr:postcode":"95207",
    "addr:street":"W March Ln",
    "iso:country":"US",
    "sg:address":"2021 W March Ln",
    "sg:city":"Stockton",
    "sg:classifiers":[
        {
            "category":"Banks & Credit Unions",
            "subcategory":"Investment Brokerage",
            "type":"Services"
        }
    ],
    "sg:phone":"+1 209 747 5660",
    "sg:postcode":"95207",
    "sg:province":"CA",
    "sg:tags":[
        "consultant",
        "planning",
        "financial"
    ],
    "wof:name":"Financial Network Investment",
    "wof:placetype":"venue"
},
  "geometry": {"coordinates":[-121.333821,37.986186],"type":"Point"}
}