{
  "type": "Feature",
  "properties": {
    "iso:country":"US",
    "sg:address":"10838 Cara Mia Pkwy",
    "sg:city":"Castroville",
    "sg:classifiers":[
        {
            "category":"Freight",
            "type":"Transportation"
        }
    ],
    "sg:phone":"+1 831 632 3876",
    "sg:postcode":"95012",
    "sg:province":"CA",
    "sg:tags":[
        "commercial",
        "storage"
    ],
    "wof:name":"Storage Mobility",
    "wof:placetype":"venue"
},
  "geometry": {"coordinates":[-121.743611,36.759563],"type":"Point"}
}