{
  "type": "Feature",
  "properties": {
    "iso:country":"US",
    "sg:address":"1495 N Maple Ave",
    "sg:city":"Fresno",
    "sg:classifiers":[
        {
            "category":"Retail",
            "subcategory":"Repair Shop",
            "type":"Services"
        }
    ],
    "sg:phone":"+1 559 251 3687",
    "sg:postcode":"93703",
    "sg:province":"CA",
    "sg:tags":[
        "lock",
        "locksmith"
    ],
    "wof:name":"Ace Mobile Key Svc",
    "wof:placetype":"venue"
},
  "geometry": {"coordinates":[-119.74549399999999,36.762367],"type":"Point"}
}