{
  "type": "Feature",
  "properties": {
    "addr:full":"374 Catherine Dr South San Francisco CA 94080",
    "addr:housenumber":"374",
    "addr:postcode":"94080",
    "addr:street":"Catherine Dr",
    "iso:country":"US",
    "sg:address":"374 Catherine Dr",
    "sg:city":"South San Francisco",
    "sg:classifiers":[
        {
            "category":"Building & Trades",
            "subcategory":"Cleaning & Sanitation",
            "type":"Services"
        }
    ],
    "sg:phone":"+1 650 588 8130",
    "sg:postcode":"94080",
    "sg:province":"CA",
    "sg:tags":[
        "home"
    ],
    "sg:website":"www.merrymaids.com/locations/loc...",
    "wof:name":"Merry Maids",
    "wof:placetype":"venue"
},
  "geometry": {"coordinates":[-122.449997,37.6562],"type":"Point"}
}