{
  "type": "Feature",
  "properties": {
    "iso:country":"US",
    "sg:address":"25842 Domingo Ave",
    "sg:city":"Capistrano Beach",
    "sg:classifiers":[
        {
            "category":"Manufacturing",
            "subcategory":"Building Materials",
            "type":"Manufacturing & Wholesale Goods"
        },
        {
            "category":"Building & Trades",
            "subcategory":"Construction",
            "type":"Services"
        }
    ],
    "sg:phone":"+1 949 493 3372",
    "sg:postcode":"92624",
    "sg:province":"CA",
    "sg:tags":[
        "cabinet",
        "wood",
        "maker",
        "kitchen",
        "mfg"
    ],
    "wof:name":"Brock Woodworks Inc",
    "wof:placetype":"venue"
},
  "geometry": {"coordinates":[-117.679214,33.46622],"type":"Point"}
}