{
  "type": "Feature",
  "properties": {
    "addr:full":"69 Mirabel Ave San Francisco CA 94110",
    "addr:housenumber":"69",
    "addr:postcode":"94110",
    "addr:street":"Mirabel Ave",
    "iso:country":"US",
    "sg:address":"69 Mirabel Ave",
    "sg:city":"San Francisco",
    "sg:classifiers":[
        {
            "category":"Building & Trades",
            "subcategory":"Construction",
            "type":"Services"
        }
    ],
    "sg:phone":"+1 415 642 8582",
    "sg:postcode":"94110",
    "sg:province":"CA",
    "sg:tags":[
        "designer"
    ],
    "wof:name":"Black Top Design",
    "wof:placetype":"venue"
},
  "geometry": {"coordinates":[-122.417823,37.745957],"type":"Point"}
}