{
  "type": "Feature",
  "properties": {
    "iso:country":"US",
    "sg:address":"10231 Ridge Rd",
    "sg:city":"Nevada City",
    "sg:classifiers":[
        {
            "category":"Building & Trades",
            "subcategory":"Construction",
            "type":"Services"
        }
    ],
    "sg:phone":"+1 530 265 6802",
    "sg:postcode":"95959",
    "sg:province":"CA",
    "sg:tags":[
        "home",
        "builder"
    ],
    "wof:name":"High Sierra Log & Timberframe",
    "wof:placetype":"venue"
},
  "geometry": {"coordinates":[-121.02538,39.248508],"type":"Point"}
}