{
  "type": "Feature",
  "properties": {
    "addr:full":"1020 Merrill St Salinas CA 93901",
    "addr:housenumber":"1020",
    "addr:postcode":"93901",
    "addr:street":"Merrill St",
    "iso:country":"US",
    "sg:address":"1020 Merrill St",
    "sg:city":"Salinas",
    "sg:classifiers":[
        {
            "category":"Wholesale",
            "subcategory":"Machinery & Supplies",
            "type":"Manufacturing & Wholesale Goods"
        }
    ],
    "sg:phone":"+1 831 751 1995",
    "sg:postcode":"93901",
    "sg:province":"CA",
    "sg:tags":[
        "equipment",
        "material",
        "handling"
    ],
    "wof:name":"Twin Pick Rack Systems",
    "wof:placetype":"venue"
},
  "geometry": {"coordinates":[-121.631765,36.655124],"type":"Point"}
}