{
  "type": "Feature",
  "properties": {
    "iso:country":"US",
    "sg:address":"1809 S Street",
    "sg:city":"Sacramento",
    "sg:classifiers":[
        {
            "category":"Personal",
            "subcategory":"Hair Removal",
            "type":"Services"
        },
        {
            "category":"Personal",
            "subcategory":"Nail Salon",
            "type":"Services"
        }
    ],
    "sg:phone":"+1 916 444 5220",
    "sg:postcode":"95814",
    "sg:province":"CA",
    "sg:website":"melodysalon.googlepages.com",
    "wof:name":"Melody Salon",
    "wof:placetype":"venue"
},
  "geometry": {"coordinates":[-121.48699999999999,38.5676],"type":"Point"}
}