{
  "type": "Feature",
  "properties": {
    "iso:country":"US",
    "sg:address":"502 S Bay Front",
    "sg:city":"Newport Beach",
    "sg:classifiers":[
        {
            "category":"Professional",
            "type":"Services"
        }
    ],
    "sg:phone":"+1 949 673 0186",
    "sg:postcode":"92662",
    "sg:province":"CA",
    "wof:name":"Marina Village LLC",
    "wof:placetype":"venue"
},
  "geometry": {"coordinates":[-117.89733699999999,33.605174],"type":"Point"}
}