{
  "type": "Feature",
  "properties": {
    "iso:country":"US",
    "sg:address":"16 Edgar Ct",
    "sg:city":"Newbury Park",
    "sg:classifiers":[
        {
            "category":"Building & Trades",
            "subcategory":"Construction",
            "type":"Services"
        }
    ],
    "sg:phone":"+1 805 499 1725",
    "sg:postcode":"91320",
    "sg:province":"CA",
    "sg:tags":[
        "house",
        "nonresidential"
    ],
    "wof:name":"C M Construction Co",
    "wof:placetype":"venue"
},
  "geometry": {"coordinates":[-118.950677,34.176545],"type":"Point"}
}