{
  "type": "Feature",
  "properties": {
    "iso:country":"US",
    "sg:address":"2080 S Harbor Blvd",
    "sg:city":"Anaheim",
    "sg:classifiers":[
        {
            "category":"Restaurant",
            "type":"Food & Drink"
        }
    ],
    "sg:phone":"+1 714 750 5120",
    "sg:postcode":"92802",
    "sg:province":"CA",
    "sg:tags":[
        "breakfast",
        "brunch",
        "diner"
    ],
    "sg:website":"www.dennys.com",
    "wof:name":"Denny's",
    "wof:placetype":"venue"
},
  "geometry": {"coordinates":[-117.915001,33.7962],"type":"Point"}
}