{
  "type": "Feature",
  "properties": {
    "addr:full":"532 Pepper Dr Bakersfield CA 93220",
    "addr:housenumber":"532",
    "addr:postcode":"93220",
    "addr:street":"Pepper Dr",
    "iso:country":"US",
    "sg:address":"532 Pepper Dr",
    "sg:city":"Bakersfield",
    "sg:classifiers":[
        {
            "category":"Shopping",
            "subcategory":"Bicycles & Sporting Goods",
            "type":"Retail Goods"
        }
    ],
    "sg:phone":"+1 661 363 5000",
    "sg:postcode":"93220",
    "sg:province":"CA",
    "sg:tags":[
        "saddlery",
        "harness"
    ],
    "wof:name":"Fleming Silver",
    "wof:placetype":"venue"
},
  "geometry": {"coordinates":[-118.87320800000001,35.3514],"type":"Point"}
}