{
  "type": "Feature",
  "properties": {
    "addr:full":"310 Peralta St Oakland CA 94607",
    "addr:housenumber":"310",
    "addr:postcode":"94607",
    "addr:street":"Peralta St",
    "iso:country":"US",
    "sg:address":"310 Peralta St",
    "sg:city":"Oakland",
    "sg:classifiers":[
        {
            "category":"Organizations",
            "subcategory":"Religious Organization",
            "type":"Services"
        }
    ],
    "sg:phone":"+1 510 832 4130",
    "sg:postcode":"94607",
    "sg:province":"CA",
    "wof:name":"Church of the Living God Faith Tabernacle",
    "wof:placetype":"venue"
},
  "geometry": {"coordinates":[-122.300003,37.8036],"type":"Point"}
}