{
  "type": "Feature",
  "properties": {
    "iso:country":"US",
    "sg:address":"3787 Cork Pl",
    "sg:city":"South San Francisco",
    "sg:classifiers":[
        {
            "category":"Shopping",
            "subcategory":"Catalog Store",
            "type":"Retail Goods"
        }
    ],
    "sg:phone":"+1 650 872 3383",
    "sg:postcode":"94080",
    "sg:province":"CA",
    "sg:tags":[
        "mail",
        "house"
    ],
    "wof:name":"Goel Mansi",
    "wof:placetype":"venue"
},
  "geometry": {"coordinates":[-122.467124,37.647011],"type":"Point"}
}