{
  "type": "Feature",
  "properties": {
    "iso:country":"US",
    "sg:address":"2348 Sterling Ave",
    "sg:city":"San Bernardino",
    "sg:classifiers":[
        {
            "category":"Home & Garden",
            "subcategory":"Building Materials",
            "type":"Retail Goods"
        }
    ],
    "sg:phone":"+1 951 360 9060",
    "sg:postcode":"92404",
    "sg:province":"CA",
    "sg:tags":[
        "door"
    ],
    "wof:name":"Cabinet Doors USA",
    "wof:placetype":"venue"
},
  "geometry": {"coordinates":[-117.24360299999999,34.137154],"type":"Point"}
}