{
  "type": "Feature",
  "properties": {
    "iso:country":"US",
    "sg:address":"6 Cromwell Suite 102",
    "sg:city":"Irvine",
    "sg:classifiers":[
        {
            "category":"Professional",
            "subcategory":"Computer Services",
            "type":"Services"
        }
    ],
    "sg:phone":"+1 949 715 2424",
    "sg:postcode":"92651",
    "sg:province":"CA",
    "sg:website":"http://www.orth-align.com/",
    "wof:name":"OrthAlign",
    "wof:placetype":"venue"
},
  "geometry": {"coordinates":[-117.96033,33.733769],"type":"Point"}
}