{
  "type": "Feature",
  "properties": {
    "iso:country":"US",
    "sg:address":"22180 Knox Dr",
    "sg:city":"Twain Harte",
    "sg:classifiers":[
        {
            "category":"Building & Trades",
            "subcategory":"Electrical",
            "type":"Services"
        }
    ],
    "sg:phone":"+1 209 664 1160",
    "sg:postcode":"95383",
    "sg:province":"CA",
    "sg:tags":[
        "electrical",
        "contractor"
    ],
    "wof:name":"Alan Wallace Electrical Contr",
    "wof:placetype":"venue"
},
  "geometry": {"coordinates":[-120.231883,38.020643],"type":"Point"}
}