{
  "type": "Feature",
  "properties": {
    "iso:country":"US",
    "sg:address":"131 Anacapa St",
    "sg:city":"Santa Barbara",
    "sg:classifiers":[
        {
            "category":"Wholesale",
            "subcategory":"Sporting Goods",
            "type":"Manufacturing & Wholesale Goods"
        }
    ],
    "sg:phone":"+1 805 965 6922",
    "sg:postcode":"93101",
    "sg:province":"CA",
    "sg:tags":[
        "bicycle"
    ],
    "sg:website":"www.inertiadesigns.com",
    "wof:name":"Inertia Design USA",
    "wof:placetype":"venue"
},
  "geometry": {"coordinates":[-119.690085,34.414585],"type":"Point"}
}