{
  "type": "Feature",
  "properties": {
    "iso:country":"US",
    "sg:address":"156 Great Mall Dr",
    "sg:city":"Milpitas",
    "sg:classifiers":[
        {
            "category":"Professional",
            "type":"Services"
        }
    ],
    "sg:phone":"+1 408 263 9901",
    "sg:postcode":"95035",
    "sg:province":"CA",
    "sg:tags":[
        "arts",
        "artist"
    ],
    "wof:name":"Art Portraits By Yvette",
    "wof:placetype":"venue"
},
  "geometry": {"coordinates":[-121.901431,37.419067],"type":"Point"}
}