{
  "type": "Feature",
  "properties": {
    "iso:country":"US",
    "sg:address":"402 Ingalls St",
    "sg:city":"Santa Cruz",
    "sg:classifiers":[
        {
            "category":"Professional",
            "type":"Services"
        }
    ],
    "sg:phone":"+1 831 425 3984",
    "sg:postcode":"95060",
    "sg:province":"CA",
    "wof:name":"Janet Allenger",
    "wof:placetype":"venue"
},
  "geometry": {"coordinates":[-122.047566,36.958741],"type":"Point"}
}