{
  "type": "Feature",
  "properties": {
    "iso:country":"US",
    "sg:address":"6330 Nancy Ridge Dr",
    "sg:city":"San Diego",
    "sg:classifiers":[
        {
            "category":"Professional",
            "subcategory":"Computer Services",
            "type":"Services"
        }
    ],
    "sg:phone":"+1 858 526 0786",
    "sg:postcode":"92121",
    "sg:province":"CA",
    "sg:tags":[
        "information",
        "technology"
    ],
    "wof:name":"HTE North America",
    "wof:placetype":"venue"
},
  "geometry": {"coordinates":[-117.187253,32.888852],"type":"Point"}
}