{
  "type": "Feature",
  "properties": {
    "addr:full":"37096 Blacow Rd Fremont CA 94536",
    "addr:postcode":"37096;94536",
    "addr:street":"Blacow Rd",
    "iso:country":"US",
    "sg:address":"37096 Blacow Rd",
    "sg:city":"Fremont",
    "sg:classifiers":[
        {
            "category":"Retail",
            "subcategory":"Laundry & Dry Cleaning",
            "type":"Services"
        }
    ],
    "sg:phone":"+1 510 505 9013",
    "sg:postcode":"94536",
    "sg:province":"CA",
    "sg:tags":[
        "cleaners",
        "rug",
        "carpet"
    ],
    "wof:name":"Ace Carpet & Upholstery Clnrs",
    "wof:placetype":"venue"
},
  "geometry": {"coordinates":[-122.017959,37.546424],"type":"Point"}
}