{
  "type": "Feature",
  "properties": {
    "addr:full":"10935 Derrydown Way San Diego CA 92130",
    "addr:housenumber":"10935",
    "addr:postcode":"92130",
    "addr:street":"Derrydown Way",
    "iso:country":"US",
    "sg:address":"10935 Derrydown Way",
    "sg:city":"San Diego",
    "sg:classifiers":[
        {
            "category":"Shopping",
            "subcategory":"Clothing, Apparel, & Fashions",
            "type":"Retail Goods"
        }
    ],
    "sg:phone":"+1 858 259 1854",
    "sg:postcode":"92130",
    "sg:province":"CA",
    "sg:tags":[
        "wear"
    ],
    "wof:name":"Cherries Designs",
    "wof:placetype":"venue"
},
  "geometry": {"coordinates":[-117.203087,32.932774],"type":"Point"}
}