{
  "type": "Feature",
  "properties": {
    "iso:country":"US",
    "sg:address":"545 E Bixby Rd",
    "sg:city":"Long Beach",
    "sg:classifiers":[
        {
            "category":"Real Estate",
            "subcategory":"Real Estate Agent",
            "type":"Services"
        }
    ],
    "sg:phone":"+1 562 427 8949",
    "sg:postcode":"90807",
    "sg:province":"CA",
    "wof:name":"Bixby Knolls Realty",
    "wof:placetype":"venue"
},
  "geometry": {"coordinates":[-118.18555,33.826781],"type":"Point"}
}