{
  "type": "Feature",
  "properties": {
    "iso:country":"US",
    "sg:address":"626 Blossom Hill Rd",
    "sg:city":"San Jose",
    "sg:classifiers":[
        {
            "category":"Fast Food",
            "type":"Food & Drink"
        }
    ],
    "sg:phone":"+1 408 227 7151",
    "sg:postcode":"95123",
    "sg:province":"CA",
    "wof:name":"Kfc",
    "wof:placetype":"venue"
},
  "geometry": {"coordinates":[-121.84277299999999,37.250524],"type":"Point"}
}