{
  "type": "Feature",
  "properties": {
    "iso:country":"US",
    "sg:address":"9237 Las Tunas Dr",
    "sg:city":"Temple City",
    "sg:classifiers":[
        {
            "category":"Personal",
            "subcategory":"Beauty Salon",
            "type":"Services"
        }
    ],
    "sg:phone":"+1 626 664 0382",
    "sg:postcode":"91780",
    "sg:province":"CA",
    "wof:name":"Danny Facial Salon",
    "wof:placetype":"venue"
},
  "geometry": {"coordinates":[-118.066767,34.10593],"type":"Point"}
}