{
  "type": "Feature",
  "properties": {
    "iso:country":"US",
    "sg:address":"3580 Mt Diablo Blvd",
    "sg:city":"Lafayette",
    "sg:classifiers":[
        {
            "category":"Retail",
            "subcategory":"Laundry & Dry Cleaning",
            "type":"Services"
        }
    ],
    "sg:phone":"+1 925 283 2969",
    "sg:postcode":"94549",
    "sg:province":"CA",
    "sg:tags":[
        "cleaners"
    ],
    "wof:name":"One Hour Cleaners",
    "wof:placetype":"venue"
},
  "geometry": {"coordinates":[-122.120621,37.891842],"type":"Point"}
}