{
  "type": "Feature",
  "properties": {
    "addr:full":"1833 Springs Rd Vallejo CA 94591",
    "addr:housenumber":"1833",
    "addr:postcode":"94591",
    "addr:street":"Springs Rd",
    "iso:country":"US",
    "sg:address":"1833 Springs Rd",
    "sg:city":"Vallejo",
    "sg:classifiers":[
        {
            "category":"Shopping",
            "type":"Retail Goods"
        }
    ],
    "sg:phone":"+1 707 643 0105",
    "sg:postcode":"94591",
    "sg:province":"CA",
    "sg:tags":[
        "telephone",
        "cellular"
    ],
    "wof:name":"Coast To Coast Communications",
    "wof:placetype":"venue"
},
  "geometry": {"coordinates":[-122.220877,38.105969],"type":"Point"}
}