{
  "type": "Feature",
  "properties": {
    "addr:full":"2089 E Colorado Blvd Pasadena CA 91107",
    "addr:housenumber":"2089",
    "addr:postcode":"91107",
    "addr:street":"E Colorado Blvd",
    "iso:country":"US",
    "sg:address":"2089 E Colorado Blvd",
    "sg:city":"Pasadena",
    "sg:classifiers":[
        {
            "category":"Sports & Exercise",
            "subcategory":"Gym",
            "type":"Entertainment"
        }
    ],
    "sg:phone":"+1 626 304 9642",
    "sg:postcode":"91107",
    "sg:province":"CA",
    "sg:tags":[
        "yoga"
    ],
    "sg:website":"www.bikrampasadena.com",
    "wof:name":"Bikram Yoga Pasadena",
    "wof:placetype":"venue"
},
  "geometry": {"coordinates":[-118.10700199999999,34.146198],"type":"Point"}
}