{
  "type": "Feature",
  "properties": {
    "addr:full":"1323 E Pacific Coast Hwy Wilmington CA 90744",
    "addr:housenumber":"1323",
    "addr:postcode":"90744",
    "addr:street":"E Pacific Coast Hwy",
    "iso:country":"US",
    "sg:address":"1323 E Pacific Coast Hwy",
    "sg:city":"Wilmington",
    "sg:classifiers":[
        {
            "category":"Retail",
            "subcategory":"Repair Shop",
            "type":"Services"
        }
    ],
    "sg:phone":"+1 310 513 1195",
    "sg:postcode":"90744",
    "sg:province":"CA",
    "sg:tags":[
        "reupholstery",
        "furniture"
    ],
    "wof:name":"Dennis Upholstery Supplies",
    "wof:placetype":"venue"
},
  "geometry": {"coordinates":[-118.24700199999999,33.7911],"type":"Point"}
}