{
  "type": "Feature",
  "properties": {
    "iso:country":"US",
    "sg:address":"2290 S State St",
    "sg:city":"Ukiah",
    "sg:classifiers":[
        {
            "category":"Retail",
            "subcategory":"Repair Shop",
            "type":"Services"
        }
    ],
    "sg:phone":"+1 707 472 0361",
    "sg:postcode":"95482",
    "sg:province":"CA",
    "sg:tags":[
        "equipment",
        "conditioning",
        "air"
    ],
    "wof:name":"Wake Mechanical Svc",
    "wof:placetype":"venue"
},
  "geometry": {"coordinates":[-123.202082,39.119781],"type":"Point"}
}