{
  "type": "Feature",
  "properties": {
    "iso:country":"US",
    "sg:address":"21000 Osborne St",
    "sg:city":"Canoga Park",
    "sg:classifiers":[
        {
            "category":"Professional",
            "type":"Services"
        }
    ],
    "sg:phone":"+1 818 701 2919",
    "sg:postcode":"91304",
    "sg:province":"CA",
    "wof:name":"Apilan",
    "wof:placetype":"venue"
},
  "geometry": {"coordinates":[-118.592302,34.233038],"type":"Point"}
}