{
  "type": "Feature",
  "properties": {
    "iso:country":"US",
    "sg:address":"170 Great Mall Dr",
    "sg:city":"Milpitas",
    "sg:classifiers":[
        {
            "category":"Food & Beverages",
            "subcategory":"Candy",
            "type":"Retail Goods"
        }
    ],
    "sg:phone":"+1 408 942 7211",
    "sg:postcode":"95035",
    "sg:province":"CA",
    "sg:tags":[
        "dessert"
    ],
    "wof:name":"Rocky Mountain Chocolate Factory",
    "wof:placetype":"venue"
},
  "geometry": {"coordinates":[-121.89927,37.418934],"type":"Point"}
}