{
  "type": "Feature",
  "properties": {
    "addr:full":"100 Wilshire Blvd Santa Monica CA 90401",
    "addr:housenumber":"100",
    "addr:postcode":"90401",
    "addr:street":"Wilshire Blvd",
    "iso:country":"US",
    "sg:address":"100 Wilshire Blvd",
    "sg:city":"Santa Monica",
    "sg:classifiers":[
        {
            "category":"Banks & Credit Unions",
            "subcategory":"Financial Services",
            "type":"Services"
        }
    ],
    "sg:phone":"+1 310 917 3326",
    "sg:postcode":"90401",
    "sg:province":"CA",
    "sg:tags":[
        "company",
        "holding"
    ],
    "wof:name":"Vliet Co Enterprises",
    "wof:placetype":"venue"
},
  "geometry": {"coordinates":[-118.500187,34.017575],"type":"Point"}
}