{
  "type": "Feature",
  "properties": {
    "addr:full":"3429 Millbury Ave Baldwin Park CA 91706",
    "addr:housenumber":"3429",
    "addr:postcode":"91706",
    "addr:street":"Millbury Ave",
    "iso:country":"US",
    "sg:address":"3429 Millbury Ave",
    "sg:city":"Baldwin Park",
    "sg:classifiers":[
        {
            "category":"Professional",
            "type":"Services"
        }
    ],
    "sg:phone":"+1 626 962 4158",
    "sg:postcode":"91706",
    "sg:province":"CA",
    "wof:name":"Teotimo C San Antonio/Et",
    "wof:placetype":"venue"
},
  "geometry": {"coordinates":[-117.95758499999999,34.0771],"type":"Point"}
}