{
  "type": "Feature",
  "properties": {
    "iso:country":"US",
    "sg:address":"21807 Rodax St",
    "sg:city":"Canoga Park",
    "sg:classifiers":[
        {
            "category":"Professional",
            "type":"Services"
        }
    ],
    "sg:phone":"+1 818 346 7642",
    "sg:postcode":"91304",
    "sg:province":"CA",
    "wof:name":"Paulo R Duarte",
    "wof:placetype":"venue"
},
  "geometry": {"coordinates":[-118.60357500000001,34.223583],"type":"Point"}
}