{
  "type": "Feature",
  "properties": {
    "iso:country":"US",
    "sg:address":"215 Cowper St",
    "sg:city":"Palo Alto",
    "sg:classifiers":[
        {
            "category":"Real Estate",
            "subcategory":"Real Estate Agent",
            "type":"Services"
        }
    ],
    "sg:phone":"+1 650 323 5305",
    "sg:postcode":"94301",
    "sg:province":"CA",
    "wof:name":"Zane Mac Gregor & Co",
    "wof:placetype":"venue"
},
  "geometry": {"coordinates":[-122.161781,37.450044],"type":"Point"}
}