{
  "type": "Feature",
  "properties": {
    "addr:full":"3211 S Golden State Blvd Fresno CA 93725",
    "addr:housenumber":"3211",
    "addr:postcode":"93725",
    "addr:street":"S Golden State Blvd",
    "iso:country":"US",
    "sg:address":"3211 S Golden State Blvd",
    "sg:city":"Fresno",
    "sg:classifiers":[
        {
            "category":"Wholesale",
            "subcategory":"Scrap",
            "type":"Manufacturing & Wholesale Goods"
        }
    ],
    "sg:phone":"+1 559 233 6543",
    "sg:postcode":"93725",
    "sg:province":"CA",
    "sg:tags":[
        "recycling",
        "center"
    ],
    "sg:website":"www.brunosiron.com",
    "wof:name":"Bruno's Recycling",
    "wof:placetype":"venue"
},
  "geometry": {"coordinates":[-119.74562,36.688481],"type":"Point"}
}