{
  "type": "Feature",
  "properties": {
    "iso:country":"US",
    "sg:address":"4070 Chino Hills Pkwy",
    "sg:city":"Chino Hills",
    "sg:classifiers":[
        {
            "category":"Food & Beverages",
            "subcategory":"Specialty",
            "type":"Retail Goods"
        }
    ],
    "sg:phone":"+1 909 597 0844",
    "sg:postcode":"91709",
    "sg:province":"CA",
    "sg:tags":[
        "health",
        "diet"
    ],
    "wof:name":"Max Muscle Chino Hills",
    "wof:placetype":"venue"
},
  "geometry": {"coordinates":[-117.71687,33.98273],"type":"Point"}
}