{
  "type": "Feature",
  "properties": {
    "addr:full":"400 San Antonio Rd Mountain View CA 94040",
    "addr:housenumber":"400",
    "addr:postcode":"94040",
    "addr:street":"San Antonio Rd",
    "iso:country":"US",
    "sg:address":"400 San Antonio Rd",
    "sg:city":"Mountain View",
    "sg:classifiers":[
        {
            "category":"Restaurant",
            "type":"Food & Drink"
        }
    ],
    "sg:menulink":"http://www.allmenus.com/ca/san-jose/19688-masas-sushi/menu/",
    "sg:phone":"+1 650 941 2117",
    "sg:postcode":"94040",
    "sg:province":"CA",
    "sg:tags":[
        "japanese",
        "asian"
    ],
    "wof:name":"Masa's Sushi",
    "wof:placetype":"venue"
},
  "geometry": {"coordinates":[-122.111481,37.404911],"type":"Point"}
}