{
  "type": "Feature",
  "properties": {
    "addr:full":"4 Thomas Irvine CA 92618",
    "addr:housenumber":"4",
    "addr:postcode":"92618",
    "addr:street":"Thomas",
    "iso:country":"US",
    "sg:address":"4 Thomas",
    "sg:city":"Irvine",
    "sg:classifiers":[
        {
            "category":"Manufacturing",
            "subcategory":"Electronics",
            "type":"Manufacturing & Wholesale Goods"
        }
    ],
    "sg:phone":"+1 949 951 8808",
    "sg:postcode":"92618",
    "sg:province":"CA",
    "sg:tags":[
        "equipment",
        "electronic",
        "supply"
    ],
    "sg:website":"www.bivar.com",
    "wof:name":"Bivar Inc",
    "wof:placetype":"venue"
},
  "geometry": {"coordinates":[-117.720178,33.64468],"type":"Point"}
}