{
  "type": "Feature",
  "properties": {
    "addr:full":"10 Cottonwood Rd Oroville CA 95965",
    "addr:housenumber":"10",
    "addr:postcode":"95965",
    "addr:street":"Cottonwood Rd",
    "iso:country":"US",
    "sg:address":"10 Cottonwood Rd",
    "sg:city":"Oroville",
    "sg:phone":"+1 530 342 9151",
    "sg:postcode":"95965",
    "sg:province":"CA",
    "sg:tags":[
        "farm",
        "rice"
    ],
    "wof:name":"Starkey Ranch",
    "wof:placetype":"venue"
},
  "geometry": {"coordinates":[-121.67391000000001,39.552348],"type":"Point"}
}