{
  "type": "Feature",
  "properties": {
    "addr:full":"6716 Van Nuys Blvd Van Nuys CA 91405",
    "addr:housenumber":"6716",
    "addr:postcode":"91405",
    "addr:street":"Van Nuys Blvd",
    "iso:country":"US",
    "sg:address":"6716 Van Nuys Blvd",
    "sg:city":"Van Nuys",
    "sg:classifiers":[
        {
            "category":"Home & Garden",
            "subcategory":"Household Appliances",
            "type":"Retail Goods"
        }
    ],
    "sg:phone":"+1 800 667 9692",
    "sg:postcode":"91405",
    "sg:province":"CA",
    "sg:tags":[
        "repair"
    ],
    "sg:website":"www.marcone.com",
    "wof:name":"Marcone Appliance Parts Center",
    "wof:placetype":"venue"
},
  "geometry": {"coordinates":[-118.448206,34.192748],"type":"Point"}
}