{
  "type": "Feature",
  "properties": {
    "iso:country":"US",
    "sg:address":"14005 Purche Ave",
    "sg:city":"Gardena",
    "sg:classifiers":[
        {
            "category":"Professional",
            "subcategory":"Business Services",
            "type":"Services"
        }
    ],
    "sg:phone":"+1 310 464 8406",
    "sg:postcode":"90249",
    "sg:province":"CA",
    "sg:tags":[
        "paralegal"
    ],
    "wof:name":"Action Care Svc",
    "wof:placetype":"venue"
},
  "geometry": {"coordinates":[-118.320668,33.905019],"type":"Point"}
}