{
  "type": "Feature",
  "properties": {
    "addr:full":"105 N Market Street Inglewood CA 90301",
    "addr:housenumber":"105",
    "addr:postcode":"90301",
    "addr:street":"N Market Street",
    "iso:country":"US",
    "sg:address":"105 N Market Street",
    "sg:city":"Inglewood",
    "sg:classifiers":[
        {
            "category":"Health Services",
            "subcategory":"Optometrist",
            "type":"Services"
        }
    ],
    "sg:phone":"+1 310 674 5123",
    "sg:postcode":"90301",
    "sg:province":"CA",
    "wof:name":"Simmons Marc S Dr Optmtrst",
    "wof:placetype":"venue"
},
  "geometry": {"coordinates":[-118.352154,33.963164],"type":"Point"}
}