{
  "type": "Feature",
  "properties": {
    "iso:country":"US",
    "sg:address":"215 E Beach St",
    "sg:city":"Watsonville",
    "sg:classifiers":[
        {
            "category":"Government",
            "subcategory":"Office",
            "type":"Public Place"
        }
    ],
    "sg:phone":"+1 831 763 4126",
    "sg:postcode":"95076",
    "sg:province":"CA",
    "sg:tags":[
        "village"
    ],
    "wof:name":"Watsonville Veterans Memorial",
    "wof:placetype":"venue"
},
  "geometry": {"coordinates":[-121.754248,36.912213],"type":"Point"}
}