{
  "type": "Feature",
  "properties": {
    "addr:full":"14323 Haynes St Van Nuys CA 91401",
    "addr:housenumber":"14323",
    "addr:postcode":"91401",
    "addr:street":"Haynes St",
    "iso:country":"US",
    "sg:address":"14323 Haynes St",
    "sg:city":"Van Nuys",
    "sg:classifiers":[
        {
            "category":"Professional",
            "subcategory":"Accounting & Tax Preparation",
            "type":"Services"
        }
    ],
    "sg:phone":"+1 818 997 3314",
    "sg:postcode":"91401",
    "sg:province":"CA",
    "sg:tags":[
        "return",
        "filing"
    ],
    "wof:name":"Ledi's Income Tax",
    "wof:placetype":"venue"
},
  "geometry": {"coordinates":[-118.446128,34.18976],"type":"Point"}
}