{
  "type": "Feature",
  "properties": {
    "iso:country":"US",
    "sg:address":"521 E Alisal St",
    "sg:city":"Salinas",
    "sg:classifiers":[
        {
            "category":"Shopping",
            "subcategory":"Used Merchandise",
            "type":"Retail Goods"
        }
    ],
    "sg:phone":"+1 831 758 5377",
    "sg:postcode":"93905",
    "sg:province":"CA",
    "sg:tags":[
        "appliance"
    ],
    "wof:name":"Bill's Bargain Appliance",
    "wof:placetype":"venue"
},
  "geometry": {"coordinates":[-121.637488,36.674016],"type":"Point"}
}