{
  "type": "Feature",
  "properties": {
    "iso:country":"US",
    "sg:address":"615 E Gutierrez St",
    "sg:city":"Santa Barbara",
    "sg:classifiers":[
        {
            "category":"Taxi",
            "type":"Transportation"
        }
    ],
    "sg:phone":"+1 805 568 5105",
    "sg:postcode":"93103",
    "sg:province":"CA",
    "sg:tags":[
        "taxicab"
    ],
    "wof:name":"California Cab",
    "wof:placetype":"venue"
},
  "geometry": {"coordinates":[-119.68702399999999,34.422608],"type":"Point"}
}