{
  "type": "Feature",
  "properties": {
    "addr:full":"412 Bamboo Lane Los Angeles CA 90012",
    "addr:housenumber":"412",
    "addr:postcode":"90012",
    "addr:street":"Bamboo Lane",
    "iso:country":"US",
    "sg:address":"412 Bamboo Lane",
    "sg:city":"Los Angeles",
    "sg:classifiers":[
        {
            "category":"Shopping",
            "subcategory":"Jewelry",
            "type":"Retail Goods"
        },
        {
            "category":"Shopping",
            "subcategory":"Antiques",
            "type":"Retail Goods"
        }
    ],
    "sg:phone":"+1 213 628 8439",
    "sg:postcode":"90012",
    "sg:province":"CA",
    "sg:website":"www.jinhingjewelry.com",
    "wof:name":"Jin Hing Company",
    "wof:placetype":"venue"
},
  "geometry": {"coordinates":[-118.23677499999999,34.065949],"type":"Point"}
}