{
  "type": "Feature",
  "properties": {
    "iso:country":"US",
    "sg:address":"637 Gibraltar Ct",
    "sg:city":"Milpitas",
    "sg:classifiers":[
        {
            "category":"Manufacturing",
            "subcategory":"Electronics",
            "type":"Manufacturing & Wholesale Goods"
        }
    ],
    "sg:phone":"+1 408 957 8500",
    "sg:postcode":"95035",
    "sg:province":"CA",
    "sg:tags":[
        "mfg",
        "boards",
        "circuit",
        "printed"
    ],
    "wof:name":"Selectron/F C D",
    "wof:placetype":"venue"
},
  "geometry": {"coordinates":[-121.895219,37.423278],"type":"Point"}
}