{
  "type": "Feature",
  "properties": {
    "iso:country":"US",
    "sg:address":"49969 Rd 427",
    "sg:city":"Oakhurst",
    "sg:classifiers":[
        {
            "category":"Organizations",
            "subcategory":"Religious Organization",
            "type":"Services"
        }
    ],
    "sg:phone":"+1 559 683 2930",
    "sg:postcode":"93644",
    "sg:province":"CA",
    "wof:name":"Corporation of President of Th",
    "wof:placetype":"venue"
},
  "geometry": {"coordinates":[-119.634728,37.329817],"type":"Point"}
}