{
  "type": "Feature",
  "properties": {
    "iso:country":"US",
    "sg:address":"701 E Meadow Dr",
    "sg:city":"Palo Alto",
    "sg:classifiers":[
        {
            "category":"Organizations",
            "subcategory":"Religious Organization",
            "type":"Services"
        }
    ],
    "sg:phone":"+1 650 493 4294",
    "sg:postcode":"94303",
    "sg:province":"CA",
    "sg:tags":[
        "church"
    ],
    "wof:name":"Palo Alto Baptist Church",
    "wof:placetype":"venue"
},
  "geometry": {"coordinates":[-122.113,37.4251],"type":"Point"}
}