{
  "type": "Feature",
  "properties": {
    "iso:country":"US",
    "sg:address":"16320 Foothill Blvd",
    "sg:city":"San Leandro",
    "sg:classifiers":[
        {
            "category":"Travel",
            "subcategory":"Hotels & Motels",
            "type":"Entertainment"
        }
    ],
    "sg:phone":"+1 510 276 4484",
    "sg:postcode":"94578",
    "sg:province":"CA",
    "wof:name":"Fairmont Inn",
    "wof:placetype":"venue"
},
  "geometry": {"coordinates":[-122.108265,37.700966],"type":"Point"}
}