{
  "type": "Feature",
  "properties": {
    "addr:full":"742 Lake Tahoe Blvd South Lake Tahoe CA 96150",
    "addr:housenumber":"742",
    "addr:postcode":"96150",
    "addr:street":"Lake Tahoe Blvd",
    "iso:country":"US",
    "sg:address":"742 Lake Tahoe Blvd",
    "sg:city":"South Lake Tahoe",
    "sg:classifiers":[
        {
            "category":"Building & Trades",
            "subcategory":"Construction",
            "type":"Services"
        }
    ],
    "sg:phone":"+1 530 573 1745",
    "sg:postcode":"96150",
    "sg:province":"CA",
    "sg:tags":[
        "roofing",
        "contractor"
    ],
    "wof:name":"Roof Masters",
    "wof:placetype":"venue"
},
  "geometry": {"coordinates":[-120.03947100000001,38.883485],"type":"Point"}
}