{
  "type": "Feature",
  "properties": {
    "addr:full":"132 N Glendale Ave Glendale CA 91206",
    "addr:housenumber":"132",
    "addr:postcode":"91206",
    "addr:street":"N Glendale Ave",
    "iso:country":"US",
    "sg:address":"132 N Glendale Ave",
    "sg:city":"Glendale",
    "sg:classifiers":[
        {
            "category":"Restaurant",
            "type":"Food & Drink"
        }
    ],
    "sg:phone":"+1 818 247 2750",
    "sg:postcode":"91206",
    "sg:province":"CA",
    "wof:name":"China Inn",
    "wof:placetype":"venue"
},
  "geometry": {"coordinates":[-118.24656,34.147532],"type":"Point"}
}