{
  "type": "Feature",
  "properties": {
    "addr:full":"2045 Lundy Ave San Jose CA 95131",
    "addr:housenumber":"2045",
    "addr:postcode":"95131",
    "addr:street":"Lundy Ave",
    "iso:country":"US",
    "sg:address":"2045 Lundy Ave",
    "sg:city":"San Jose",
    "sg:classifiers":[
        {
            "category":"Organizations",
            "subcategory":"Labor Organization",
            "type":"Services"
        }
    ],
    "sg:phone":"+1 408 473 1000",
    "sg:postcode":"95131",
    "sg:province":"CA",
    "sg:website":"www.csea.com",
    "wof:name":"California School Employees",
    "wof:placetype":"venue"
},
  "geometry": {"coordinates":[-121.890905,37.395561],"type":"Point"}
}