{
  "type": "Feature",
  "properties": {
    "iso:country":"US",
    "sg:address":"2740 Fulton Ave",
    "sg:city":"Sacramento",
    "sg:classifiers":[
        {
            "category":"Social Services",
            "type":"Services"
        }
    ],
    "sg:phone":"+1 916 972 9316",
    "sg:postcode":"95821",
    "sg:province":"CA",
    "sg:tags":[
        "counselor",
        "marriage",
        "family"
    ],
    "wof:name":"Carol A Livingston",
    "wof:placetype":"venue"
},
  "geometry": {"coordinates":[-121.401338,38.61776],"type":"Point"}
}