{
  "type": "Feature",
  "properties": {
    "addr:full":"9520 Redfern Ave Inglewood CA 90301",
    "addr:housenumber":"9520",
    "addr:postcode":"90301",
    "addr:street":"Redfern Ave",
    "iso:country":"US",
    "sg:address":"9520 Redfern Ave",
    "sg:city":"Inglewood",
    "sg:classifiers":[
        {
            "category":"Place Of Worship",
            "subcategory":"Church",
            "type":"Public Place"
        },
        {
            "category":"Place Of Worship",
            "type":"Public Place"
        }
    ],
    "sg:phone":"+1 310 671 4772",
    "sg:postcode":"90301",
    "sg:province":"CA",
    "sg:tags":[
        "churches-baptist-general",
        "churches-baptist"
    ],
    "sg:website":"http://www.cbwla.com",
    "wof:name":"Lax Urban Center",
    "wof:placetype":"venue"
},
  "geometry": {"coordinates":[-118.366722,33.95014],"type":"Point"}
}