{
  "type": "Feature",
  "properties": {
    "iso:country":"US",
    "sg:address":"1425 94th Ave",
    "sg:city":"Oakland",
    "sg:classifiers":[
        {
            "category":"Parking",
            "subcategory":"Garage",
            "type":"Transportation"
        }
    ],
    "sg:phone":"+1 510 635 0225",
    "sg:postcode":"94603",
    "sg:province":"CA",
    "sg:tags":[
        "lot"
    ],
    "wof:name":"Pharaoh Tutuly",
    "wof:placetype":"venue"
},
  "geometry": {"coordinates":[-122.17225999999999,37.747334],"type":"Point"}
}