{
  "type": "Feature",
  "properties": {
    "iso:country":"US",
    "sg:address":"14827 Crenshaw Blvd",
    "sg:city":"Gardena",
    "sg:classifiers":[
        {
            "category":"Travel",
            "subcategory":"Hotels & Motels",
            "type":"Entertainment"
        }
    ],
    "sg:phone":"+1 310 675 2100",
    "sg:postcode":"90249",
    "sg:province":"CA",
    "wof:name":"Merle Motel",
    "wof:placetype":"venue"
},
  "geometry": {"coordinates":[-118.325996,33.897202],"type":"Point"}
}