{
  "type": "Feature",
  "properties": {
    "addr:full":"599 Delia Ct Grass Valley CA 95945",
    "addr:housenumber":"599",
    "addr:postcode":"95945",
    "addr:street":"Delia Ct",
    "iso:country":"US",
    "sg:address":"599 Delia Ct",
    "sg:city":"Grass Valley",
    "sg:classifiers":[
        {
            "category":"Sports & Exercise",
            "subcategory":"Race Track",
            "type":"Entertainment"
        }
    ],
    "sg:phone":"+1 530 273 3294",
    "sg:postcode":"95945",
    "sg:province":"CA",
    "sg:tags":[
        "equipment",
        "supply"
    ],
    "wof:name":"W W Racing",
    "wof:placetype":"venue"
},
  "geometry": {"coordinates":[-121.07812800000001,39.212671],"type":"Point"}
}