{
  "type": "Feature",
  "properties": {
    "iso:country":"US",
    "sg:address":"650 S Hill St",
    "sg:city":"Los Angeles",
    "sg:classifiers":[
        {
            "category":"Shopping",
            "subcategory":"Jewelry",
            "type":"Retail Goods"
        }
    ],
    "sg:phone":"+1 213 689 7968",
    "sg:postcode":"90014",
    "sg:province":"CA",
    "wof:name":"B J Jewelry",
    "wof:placetype":"venue"
},
  "geometry": {"coordinates":[-118.253998,34.0466],"type":"Point"}
}