{
  "type": "Feature",
  "properties": {
    "addr:full":"10644 Leeds St Norwalk CA 90650",
    "addr:housenumber":"10644",
    "addr:postcode":"90650",
    "addr:street":"Leeds St",
    "iso:country":"US",
    "sg:address":"10644 Leeds St",
    "sg:city":"Norwalk",
    "sg:classifiers":[
        {
            "category":"Wholesale",
            "subcategory":"Motor Vehicles",
            "type":"Manufacturing & Wholesale Goods"
        }
    ],
    "sg:phone":"+1 562 699 7876",
    "sg:postcode":"90650",
    "sg:province":"CA",
    "wof:name":"J & C Auto Sales",
    "wof:placetype":"venue"
},
  "geometry": {"coordinates":[-118.106893,33.918007],"type":"Point"}
}