{
  "type": "Feature",
  "properties": {
    "iso:country":"US",
    "sg:address":"9346 Corbin Ave",
    "sg:city":"Northridge",
    "sg:classifiers":[
        {
            "category":"Health Services",
            "subcategory":"Doctor",
            "type":"Services"
        }
    ],
    "sg:phone":"+1 818 349 8934",
    "sg:postcode":"91324",
    "sg:province":"CA",
    "sg:tags":[
        "clinic"
    ],
    "wof:name":"Valley Urgent Medical Dental",
    "wof:placetype":"venue"
},
  "geometry": {"coordinates":[-118.562236,34.241893],"type":"Point"}
}