{
  "type": "Feature",
  "properties": {
    "iso:country":"US",
    "sg:address":"633 W 5th St",
    "sg:city":"Los Angeles",
    "sg:classifiers":[
        {
            "category":"Arts & Performance",
            "subcategory":"Theater",
            "type":"Entertainment"
        }
    ],
    "sg:phone":"+1 213 430 9177",
    "sg:postcode":"90071",
    "sg:province":"CA",
    "sg:tags":[
        "bureau"
    ],
    "wof:name":"Rosa's Entertainment",
    "wof:placetype":"venue"
},
  "geometry": {"coordinates":[-118.254613,34.050669],"type":"Point"}
}