{
  "type": "Feature",
  "properties": {
    "iso:country":"US",
    "sg:address":"460 Drake Cir",
    "sg:city":"Sacramento",
    "sg:classifiers":[
        {
            "category":"Real Estate",
            "subcategory":"Real Estate Services",
            "type":"Services"
        }
    ],
    "sg:phone":"+1 916 971 8550",
    "sg:postcode":"95864",
    "sg:province":"CA",
    "sg:tags":[
        "company",
        "title"
    ],
    "wof:name":"Alliance Title Co",
    "wof:placetype":"venue"
},
  "geometry": {"coordinates":[-121.392948,38.5741],"type":"Point"}
}