{
  "type": "Feature",
  "properties": {
    "addr:full":"29530 Rancho California Rd Temecula CA 92591",
    "addr:housenumber":"29530",
    "addr:postcode":"92591",
    "addr:street":"Rancho California Rd",
    "iso:country":"US",
    "sg:address":"29530 Rancho California Rd",
    "sg:city":"Temecula",
    "sg:classifiers":[
        {
            "category":"Food & Beverages",
            "subcategory":"Groceries & Convenience Stores",
            "type":"Retail Goods"
        }
    ],
    "sg:phone":"+1 951 699 7100",
    "sg:postcode":"92591",
    "sg:province":"CA",
    "wof:name":"Kroger",
    "wof:placetype":"venue"
},
  "geometry": {"coordinates":[-117.14451699999999,33.505664],"type":"Point"}
}