{
  "type": "Feature",
  "properties": {
    "iso:country":"US",
    "sg:address":"1093 W Celeste Ave",
    "sg:city":"Fresno",
    "sg:classifiers":[
        {
            "category":"Real Estate",
            "subcategory":"Real Estate Services",
            "type":"Services"
        },
        {
            "category":"Building & Trades",
            "subcategory":"Cleaning & Sanitation",
            "type":"Services"
        }
    ],
    "sg:phone":"+1 559 284 4412",
    "sg:postcode":"93711",
    "sg:province":"CA",
    "sg:tags":[
        "maintenance",
        "cleaners-interior"
    ],
    "wof:name":"A & M Property Maintenance",
    "wof:placetype":"venue"
},
  "geometry": {"coordinates":[-119.810338,36.821035],"type":"Point"}
}