{
  "type": "Feature",
  "properties": {
    "iso:country":"US",
    "sg:address":"1909 Daphne Ln",
    "sg:city":"Yuba City",
    "sg:classifiers":[
        {
            "category":"Building & Trades",
            "subcategory":"Construction",
            "type":"Services"
        }
    ],
    "sg:phone":"+1 530 673 5445",
    "sg:postcode":"95993",
    "sg:province":"CA",
    "sg:tags":[
        "excavation",
        "material",
        "contractor"
    ],
    "wof:name":"Bi Counties SPTC Tnk & Bckh Sv",
    "wof:placetype":"venue"
},
  "geometry": {"coordinates":[-121.69262500000001,39.099189],"type":"Point"}
}