{
  "type": "Feature",
  "properties": {
    "iso:country":"US",
    "sg:address":"6087 Jurupa Ave",
    "sg:city":"Riverside",
    "sg:classifiers":[
        {
            "category":"Retail",
            "subcategory":"Auto Repair",
            "type":"Services"
        }
    ],
    "sg:phone":"+1 951 977 9202",
    "sg:postcode":"92504",
    "sg:province":"CA",
    "sg:tags":[
        "body",
        "automobile",
        "removal",
        "dent",
        "painting",
        "repairing"
    ],
    "wof:name":"Cornerstone Auto Body",
    "wof:placetype":"venue"
},
  "geometry": {"coordinates":[-117.43567,33.962795],"type":"Point"}
}