{
  "type": "Feature",
  "properties": {
    "addr:full":"2509 Cortez St Oxnard CA 93036",
    "addr:housenumber":"2509",
    "addr:postcode":"93036",
    "addr:street":"Cortez St",
    "iso:country":"US",
    "sg:address":"2509 Cortez St",
    "sg:city":"Oxnard",
    "sg:classifiers":[
        {
            "category":"Retail",
            "subcategory":"Repair Shop",
            "type":"Services"
        }
    ],
    "sg:phone":"+1 805 981 9779",
    "sg:postcode":"93036",
    "sg:province":"CA",
    "sg:tags":[
        "upholsterer"
    ],
    "wof:name":"Lujan Upholstery",
    "wof:placetype":"venue"
},
  "geometry": {"coordinates":[-119.167024,34.232524],"type":"Point"}
}