{
  "type": "Feature",
  "properties": {
    "addr:full":"4651 Holt Blvd Montclair CA 91763",
    "addr:housenumber":"4651",
    "addr:postcode":"91763",
    "addr:street":"Holt Blvd",
    "iso:country":"US",
    "sg:address":"4651 Holt Blvd",
    "sg:city":"Montclair",
    "sg:classifiers":[
        {
            "category":"Shopping",
            "subcategory":"Crafts & Fabrics",
            "type":"Retail Goods"
        }
    ],
    "sg:phone":"+1 909 398 1475",
    "sg:postcode":"91763",
    "sg:province":"CA",
    "sg:tags":[
        "sewing"
    ],
    "wof:name":"World of Fabrics",
    "wof:placetype":"venue"
},
  "geometry": {"coordinates":[-117.705433,34.063101],"type":"Point"}
}