{
  "type": "Feature",
  "properties": {
    "addr:full":"1032 N Lilac Ave Rialto CA 92376",
    "addr:housenumber":"1032",
    "addr:postcode":"92376",
    "addr:street":"N Lilac Ave",
    "iso:country":"US",
    "sg:address":"1032 N Lilac Ave",
    "sg:city":"Rialto",
    "sg:classifiers":[
        {
            "category":"Professional",
            "subcategory":"Detective & Security Services",
            "type":"Services"
        }
    ],
    "sg:phone":"+1 909 717 3700",
    "sg:postcode":"92376",
    "sg:province":"CA",
    "sg:tags":[
        "guard",
        "patrol"
    ],
    "wof:name":"Progressive Protective Svc",
    "wof:placetype":"venue"
},
  "geometry": {"coordinates":[-117.379244,34.117032],"type":"Point"}
}