{
  "type": "Feature",
  "properties": {
    "addr:full":"505 Laurel St San Diego CA 92101",
    "addr:housenumber":"505",
    "addr:postcode":"92101",
    "addr:street":"Laurel St",
    "iso:country":"US",
    "sg:address":"505 Laurel St",
    "sg:city":"San Diego",
    "sg:classifiers":[
        {
            "category":"Bars & Pubs",
            "type":"Food & Drink"
        },
        {
            "category":"Restaurant",
            "type":"Food & Drink"
        }
    ],
    "sg:menulink":"http://www.allmenus.com/ca/san-diego/5683-laurel-restaurant--bar/menu/",
    "sg:phone":"+1 619 239 2222",
    "sg:postcode":"92101",
    "sg:province":"CA",
    "sg:tags":[
        "mediterranean"
    ],
    "wof:name":"Laurel Restaurant & Bar",
    "wof:placetype":"venue"
},
  "geometry": {"coordinates":[-117.160172,32.731437],"type":"Point"}
}