{
  "type": "Feature",
  "properties": {
    "addr:full":"1456 Alturas Rd Fallbrook CA 92028",
    "addr:housenumber":"1456",
    "addr:postcode":"92028",
    "addr:street":"Alturas Rd",
    "iso:country":"US",
    "sg:address":"1456 Alturas Rd",
    "sg:city":"Fallbrook",
    "sg:classifiers":[
        {
            "category":"Manufacturing",
            "subcategory":"Tools & Machinery",
            "type":"Manufacturing & Wholesale Goods"
        }
    ],
    "sg:phone":"+1 760 728 5795",
    "sg:postcode":"92028",
    "sg:province":"CA",
    "sg:tags":[
        "technician"
    ],
    "wof:name":"Leander Shabazz Inc",
    "wof:placetype":"venue"
},
  "geometry": {"coordinates":[-117.25789899999999,33.368729],"type":"Point"}
}