{
  "type": "Feature",
  "properties": {
    "iso:country":"US",
    "sg:address":"7602 Katella Ave",
    "sg:city":"Stanton",
    "sg:classifiers":[
        {
            "category":"Shopping",
            "type":"Retail Goods"
        }
    ],
    "sg:phone":"+1 714 527 0217",
    "sg:postcode":"90680",
    "sg:province":"CA",
    "sg:tags":[
        "telephone",
        "cellular"
    ],
    "wof:name":"Speed Wireless",
    "wof:placetype":"venue"
},
  "geometry": {"coordinates":[-117.999332,33.802835],"type":"Point"}
}