{
  "type": "Feature",
  "properties": {
    "iso:country":"US",
    "sg:address":"27732 McBean Pkwy",
    "sg:city":"Valencia",
    "sg:classifiers":[
        {
            "category":"Restaurant",
            "type":"Food & Drink"
        },
        {
            "category":"Professional",
            "subcategory":"Business Services",
            "type":"Services"
        }
    ],
    "sg:phone":"+1 661 263 8646",
    "sg:postcode":"91354",
    "sg:province":"CA",
    "sg:tags":[
        "delivery",
        "pizza"
    ],
    "sg:website":"www.tomatojoespizza.com",
    "wof:name":"Tomato Joe's Pizza Bakery",
    "wof:placetype":"venue"
},
  "geometry": {"coordinates":[-118.552952,34.44461],"type":"Point"}
}