{
  "type": "Feature",
  "properties": {
    "addr:full":"1685 Clovis Ave San Jose CA 95124",
    "addr:housenumber":"1685",
    "addr:postcode":"95124",
    "addr:street":"Clovis Ave",
    "iso:country":"US",
    "sg:address":"1685 Clovis Ave",
    "sg:city":"San Jose",
    "sg:classifiers":[
        {
            "category":"Building & Trades",
            "subcategory":"Construction",
            "type":"Services"
        }
    ],
    "sg:phone":"+1 408 269 7999",
    "sg:postcode":"95124",
    "sg:province":"CA",
    "sg:tags":[
        "general",
        "contractor"
    ],
    "wof:name":"D C Bean Construction Co",
    "wof:placetype":"venue"
},
  "geometry": {"coordinates":[-121.90775499999999,37.239036],"type":"Point"}
}