{
  "type": "Feature",
  "properties": {
    "addr:full":"1145 Broadway Burlingame CA 94010",
    "addr:housenumber":"1145",
    "addr:postcode":"94010",
    "addr:street":"Broadway",
    "iso:country":"US",
    "sg:address":"1145 Broadway",
    "sg:city":"Burlingame",
    "sg:classifiers":[
        {
            "category":"Banks & Credit Unions",
            "subcategory":"Bank",
            "type":"Services"
        }
    ],
    "sg:phone":"+1 650 348 4662",
    "sg:postcode":"94010",
    "sg:province":"CA",
    "wof:name":"Wells Fargo",
    "wof:placetype":"venue"
},
  "geometry": {"coordinates":[-122.363648,37.586934],"type":"Point"}
}