{
  "type": "Feature",
  "properties": {
    "addr:full":"825 Riverside Ave Paso Robles CA 93446",
    "addr:housenumber":"825",
    "addr:postcode":"93446",
    "addr:street":"Riverside Ave",
    "iso:country":"US",
    "sg:address":"825 Riverside Ave",
    "sg:city":"Paso Robles",
    "sg:classifiers":[
        {
            "category":"Professional",
            "subcategory":"Business Services",
            "type":"Services"
        }
    ],
    "sg:phone":"+1 805 239 4138",
    "sg:postcode":"93446",
    "sg:province":"CA",
    "sg:tags":[
        "water",
        "treatment"
    ],
    "wof:name":"Davis Water Conditioning",
    "wof:placetype":"venue"
},
  "geometry": {"coordinates":[-120.686607,35.623368],"type":"Point"}
}