{
  "type": "Feature",
  "properties": {
    "addr:full":"736 Echo Park Ter Los Angeles CA 90026",
    "addr:housenumber":"736",
    "addr:postcode":"90026",
    "addr:street":"Echo Park Ter",
    "iso:country":"US",
    "sg:address":"736 Echo Park Ter",
    "sg:city":"Los Angeles",
    "sg:classifiers":[
        {
            "category":"Professional",
            "subcategory":"Management & Consulting",
            "type":"Services"
        }
    ],
    "sg:phone":"+1 213 250 5253",
    "sg:postcode":"90026",
    "sg:province":"CA",
    "sg:tags":[
        "promotion",
        "sales"
    ],
    "wof:name":"Echo Sales",
    "wof:placetype":"venue"
},
  "geometry": {"coordinates":[-118.259254,34.071582],"type":"Point"}
}