{
  "type": "Feature",
  "properties": {
    "addr:full":"11746 Broadway Whittier CA 90601",
    "addr:housenumber":"11746",
    "addr:postcode":"90601",
    "addr:street":"Broadway",
    "iso:country":"US",
    "sg:address":"11746 Broadway",
    "sg:city":"Whittier",
    "sg:classifiers":[
        {
            "category":"Manufacturing",
            "subcategory":"Printing",
            "type":"Manufacturing & Wholesale Goods"
        }
    ],
    "sg:phone":"+1 562 699 0224",
    "sg:postcode":"90601",
    "sg:province":"CA",
    "sg:tags":[
        "publisher",
        "music"
    ],
    "wof:name":"Rubyana Music",
    "wof:placetype":"venue"
},
  "geometry": {"coordinates":[-118.050724,33.986274],"type":"Point"}
}