{
  "type": "Feature",
  "properties": {
    "iso:country":"US",
    "sg:address":"8432 Lemon Ave",
    "sg:city":"La Mesa",
    "sg:classifiers":[
        {
            "category":"Real Estate",
            "subcategory":"Real Estate Agent",
            "type":"Services"
        }
    ],
    "sg:phone":"+1 619 697 0096",
    "sg:postcode":"91941",
    "sg:province":"CA",
    "sg:tags":[
        "inspection"
    ],
    "wof:name":"Monte Verde Consulting",
    "wof:placetype":"venue"
},
  "geometry": {"coordinates":[-117.01561700000001,32.765349],"type":"Point"}
}