{
  "type": "Feature",
  "properties": {
    "addr:full":"849 29th St Oakland CA 94608",
    "addr:housenumber":"849",
    "addr:postcode":"94608",
    "addr:street":"29Th St",
    "iso:country":"US",
    "sg:address":"849 29th St",
    "sg:city":"Oakland",
    "sg:classifiers":[
        {
            "category":"Building & Trades",
            "subcategory":"Construction",
            "type":"Services"
        }
    ],
    "sg:phone":"+1 510 893 1157",
    "sg:postcode":"94608",
    "sg:province":"CA",
    "sg:tags":[
        "window",
        "installation"
    ],
    "sg:website":"www.woodenwindow.com",
    "wof:name":"Wooden Window, Inc.",
    "wof:placetype":"venue"
},
  "geometry": {"coordinates":[-122.275007,37.819053],"type":"Point"}
}