{
  "type": "Feature",
  "properties": {
    "iso:country":"US",
    "sg:address":"180 Montgomery Street Suite 2340",
    "sg:city":"San Francisco",
    "sg:classifiers":[
        {
            "category":"Professional",
            "subcategory":"Accounting & Tax Preparation",
            "type":"Services"
        }
    ],
    "sg:phone":"+1 415 398 3534",
    "sg:postcode":"94104",
    "sg:province":"CA",
    "sg:tags":[
        "accountant"
    ],
    "wof:name":"Bachecki Crom & Company Llp",
    "wof:placetype":"venue"
},
  "geometry": {"coordinates":[-122.402282,37.790743],"type":"Point"}
}