{
  "type": "Feature",
  "properties": {
    "iso:country":"US",
    "sg:address":"2530 N Los Lomitas Way",
    "sg:city":"Covina",
    "sg:classifiers":[
        {
            "category":"Banks & Credit Unions",
            "subcategory":"Investment Brokerage",
            "type":"Services"
        }
    ],
    "sg:phone":"+1 626 339 2042",
    "sg:postcode":"91724",
    "sg:province":"CA",
    "sg:tags":[
        "trust"
    ],
    "wof:name":"Pierce Family Trust",
    "wof:placetype":"venue"
},
  "geometry": {"coordinates":[-117.864508,34.060896],"type":"Point"}
}