{
  "type": "Feature",
  "properties": {
    "iso:country":"US",
    "sg:address":"555 Skyway Rd",
    "sg:city":"San Carlos",
    "sg:classifiers":[
        {
            "category":"Travel",
            "subcategory":"Hotels & Motels",
            "type":"Entertainment"
        }
    ],
    "sg:phone":"+1 650 631 0777",
    "sg:postcode":"94070",
    "sg:province":"CA",
    "wof:name":"Fairfield Inn",
    "wof:placetype":"venue"
},
  "geometry": {"coordinates":[-122.254644,37.51392],"type":"Point"}
}