{
  "type": "Feature",
  "properties": {
    "iso:country":"US",
    "sg:address":"4565 Ruffner St",
    "sg:city":"San Diego",
    "sg:classifiers":[
        {
            "category":"Travel",
            "subcategory":"Travel Agent",
            "type":"Entertainment"
        }
    ],
    "sg:phone":"+1 858 836 1127",
    "sg:postcode":"92111",
    "sg:province":"CA",
    "sg:tags":[
        "agency",
        "bureau"
    ],
    "wof:name":"Cosmopolitan Travel and Tours",
    "wof:placetype":"venue"
},
  "geometry": {"coordinates":[-117.156953,32.822402],"type":"Point"}
}