{
  "type": "Feature",
  "properties": {
    "addr:full":"2383 California Street San Francisco CA 94115",
    "addr:housenumber":"2383",
    "addr:postcode":"94115",
    "addr:street":"California Street",
    "iso:country":"US",
    "sg:address":"2383 California Street",
    "sg:city":"San Francisco",
    "sg:classifiers":[
        {
            "category":"Health Services",
            "subcategory":"Dentist",
            "type":"Services"
        }
    ],
    "sg:phone":"+1 415 921 2448",
    "sg:postcode":"94115",
    "sg:province":"CA",
    "wof:name":"Jacobsen Peter L DDS",
    "wof:placetype":"venue"
},
  "geometry": {"coordinates":[-122.433424,37.788956],"type":"Point"}
}