{
  "type": "Feature",
  "properties": {
    "addr:full":"5478 Feather River Pl Paradise CA 95969",
    "addr:housenumber":"5478",
    "addr:postcode":"95969",
    "addr:street":"Feather River Pl",
    "iso:country":"US",
    "sg:address":"5478 Feather River Pl",
    "sg:city":"Paradise",
    "sg:classifiers":[
        {
            "category":"Restaurant",
            "type":"Food & Drink"
        }
    ],
    "sg:phone":"+1 530 872 9536",
    "sg:postcode":"95969",
    "sg:province":"CA",
    "wof:name":"Country Waffles",
    "wof:placetype":"venue"
},
  "geometry": {"coordinates":[-121.57058499999999,39.748648],"type":"Point"}
}