{
  "type": "Feature",
  "properties": {
    "iso:country":"US",
    "sg:address":"12361 Baja Panorama",
    "sg:city":"Santa Ana",
    "sg:classifiers":[
        {
            "category":"Real Estate",
            "subcategory":"Architect",
            "type":"Services"
        }
    ],
    "sg:phone":"+1 714 997 4956",
    "sg:postcode":"92705",
    "sg:province":"CA",
    "wof:name":"Bennett Phillip Architect",
    "wof:placetype":"venue"
},
  "geometry": {"coordinates":[-117.799004,33.783699],"type":"Point"}
}