{
  "type": "Feature",
  "properties": {
    "addr:full":"100 Oceangate Long Beach CA 90802",
    "addr:housenumber":"100",
    "addr:postcode":"90802",
    "addr:street":"Oceangate",
    "iso:country":"US",
    "sg:address":"100 Oceangate",
    "sg:city":"Long Beach",
    "sg:classifiers":[
        {
            "category":"Real Estate",
            "subcategory":"Real Estate Agent",
            "type":"Services"
        }
    ],
    "sg:phone":"+1 562 951 8220",
    "sg:postcode":"90802",
    "sg:province":"CA",
    "sg:website":"www.oceangaterealtors.com",
    "wof:name":"Oceangate Realtors Inc",
    "wof:placetype":"venue"
},
  "geometry": {"coordinates":[-118.19936,33.76651],"type":"Point"}
}