{
  "type": "Feature",
  "properties": {
    "iso:country":"US",
    "sg:address":"647 Matthew Ln",
    "sg:city":"San Marcos",
    "sg:classifiers":[
        {
            "category":"Wholesale",
            "subcategory":"Machinery & Supplies",
            "type":"Manufacturing & Wholesale Goods"
        }
    ],
    "sg:phone":"+1 760 737 8449",
    "sg:postcode":"92069",
    "sg:province":"CA",
    "sg:tags":[
        "salon",
        "beauty"
    ],
    "wof:name":"Escondido Beauty Supply",
    "wof:placetype":"venue"
},
  "geometry": {"coordinates":[-117.124568,33.146508],"type":"Point"}
}