{
  "type": "Feature",
  "properties": {
    "iso:country":"US",
    "sg:address":"7122 Ave 424",
    "sg:city":"Dinuba",
    "sg:classifiers":[
        {
            "category":"Building & Trades",
            "subcategory":"Construction",
            "type":"Services"
        }
    ],
    "sg:phone":"+1 559 591 6009",
    "sg:postcode":"93618",
    "sg:province":"CA",
    "sg:tags":[
        "paving",
        "contractor"
    ],
    "wof:name":"Cal Slurry",
    "wof:placetype":"venue"
},
  "geometry": {"coordinates":[-119.415252,36.560701],"type":"Point"}
}