{
  "type": "Feature",
  "properties": {
    "iso:country":"US",
    "sg:address":"515 Alondra Dr",
    "sg:city":"Huntington Beach",
    "sg:classifiers":[
        {
            "category":"Health Services",
            "subcategory":"Doctor",
            "type":"Services"
        }
    ],
    "sg:phone":"+1 310 517 0085",
    "sg:postcode":"92648",
    "sg:province":"CA",
    "wof:name":"Torrance Doctors Group",
    "wof:placetype":"venue"
},
  "geometry": {"coordinates":[-117.992375,33.670229],"type":"Point"}
}