{
  "type": "Feature",
  "properties": {
    "addr:full":"2801 Erin Dr Sacramento CA 95833",
    "addr:housenumber":"2801",
    "addr:postcode":"95833",
    "addr:street":"Erin Dr",
    "iso:country":"US",
    "sg:address":"2801 Erin Dr",
    "sg:city":"Sacramento",
    "sg:classifiers":[
        {
            "category":"Shopping",
            "subcategory":"Catalog Store",
            "type":"Retail Goods"
        }
    ],
    "sg:phone":"+1 916 929 6909",
    "sg:postcode":"95833",
    "sg:province":"CA",
    "sg:tags":[
        "mail",
        "order"
    ],
    "wof:name":"Copeland Enterprises",
    "wof:placetype":"venue"
},
  "geometry": {"coordinates":[-121.487968,38.615907],"type":"Point"}
}