{
  "type": "Feature",
  "properties": {
    "iso:country":"US",
    "sg:address":"24509 Walnut St Ste 101",
    "sg:city":"Newhall",
    "sg:classifiers":[
        {
            "category":"Health Services",
            "subcategory":"Chiropractor",
            "type":"Services"
        }
    ],
    "sg:phone":"+1 661 253 9600",
    "sg:postcode":"91321",
    "sg:province":"CA",
    "wof:name":"Phillip Pinto DC, Chiropractic Offices",
    "wof:placetype":"venue"
},
  "geometry": {"coordinates":[-118.531342,34.380983],"type":"Point"}
}