{
  "type": "Feature",
  "properties": {
    "addr:full":"6221 Pleasant Valley Rd El Dorado CA 95623",
    "addr:housenumber":"6221",
    "addr:postcode":"95623",
    "addr:street":"Pleasant Valley Rd",
    "iso:country":"US",
    "sg:address":"6221 Pleasant Valley Rd",
    "sg:city":"El Dorado",
    "sg:classifiers":[
        {
            "category":"Personal",
            "subcategory":"Beauty Salon",
            "type":"Services"
        }
    ],
    "sg:phone":"+1 530 626 7667",
    "sg:postcode":"95623",
    "sg:province":"CA",
    "wof:name":"Salon Rouge",
    "wof:placetype":"venue"
},
  "geometry": {"coordinates":[-120.847301,38.682358],"type":"Point"}
}