{
  "type": "Feature",
  "properties": {
    "addr:full":"1244 E 8th Street Los Angeles CA 90021",
    "addr:housenumber":"1244",
    "addr:postcode":"90021",
    "addr:street":"E 8Th Street",
    "iso:country":"US",
    "sg:address":"1244 E 8th Street",
    "sg:city":"Los Angeles",
    "sg:classifiers":[
        {
            "category":"Banks & Credit Unions",
            "subcategory":"Bank",
            "type":"Services"
        }
    ],
    "sg:phone":"+1 213 673 2000",
    "sg:postcode":"90021",
    "sg:province":"CA",
    "wof:name":"Wells Fargo Bank Na",
    "wof:placetype":"venue"
},
  "geometry": {"coordinates":[-118.24377,34.033846],"type":"Point"}
}