{
  "type": "Feature",
  "properties": {
    "addr:full":"1410 Monument Blvd Concord CA 94520",
    "addr:housenumber":"1410",
    "addr:postcode":"94520",
    "addr:street":"Monument Blvd",
    "iso:country":"US",
    "sg:address":"1410 Monument Blvd",
    "sg:city":"Concord",
    "sg:classifiers":[
        {
            "category":"Health Services",
            "subcategory":"Doctor",
            "type":"Services"
        }
    ],
    "sg:phone":"+1 925 602 0696",
    "sg:postcode":"94520",
    "sg:province":"CA",
    "sg:tags":[
        "dentist"
    ],
    "wof:name":"Gerardo Castro DDS",
    "wof:placetype":"venue"
},
  "geometry": {"coordinates":[-122.046964,37.950686],"type":"Point"}
}