{
  "type": "Feature",
  "properties": {
    "iso:country":"US",
    "sg:address":"1670 Malcolm Ave",
    "sg:city":"Los Angeles",
    "sg:classifiers":[
        {
            "category":"Professional",
            "type":"Services"
        }
    ],
    "sg:phone":"+1 310 474 1456",
    "sg:postcode":"90024",
    "sg:province":"CA",
    "wof:name":"West Breeze Homeowners As",
    "wof:placetype":"venue"
},
  "geometry": {"coordinates":[-118.43724400000001,34.053693],"type":"Point"}
}