{
  "type": "Feature",
  "properties": {
    "iso:country":"US",
    "sg:address":"1598 Fitzgerald Dr",
    "sg:city":"Pinole",
    "sg:classifiers":[
        {
            "category":"Home & Garden",
            "subcategory":"Furniture",
            "type":"Retail Goods"
        }
    ],
    "sg:phone":"+1 510 758 8588",
    "sg:postcode":"94564",
    "sg:province":"CA",
    "wof:name":"Bedroom Depot",
    "wof:placetype":"venue"
},
  "geometry": {"coordinates":[-122.30088,37.992222],"type":"Point"}
}