{
  "type": "Feature",
  "properties": {
    "iso:country":"US",
    "sg:address":"4201 Wilshire Boulevard",
    "sg:city":"Los Angeles",
    "sg:classifiers":[
        {
            "category":"Education",
            "subcategory":"School",
            "type":"Public Place"
        }
    ],
    "sg:phone":"+1 323 932 2266",
    "sg:postcode":"90010",
    "sg:province":"CA",
    "sg:tags":[
        "high",
        "middle",
        "elementary"
    ],
    "wof:name":"Los Angeles Unified School District",
    "wof:placetype":"venue"
},
  "geometry": {"coordinates":[-118.319224,34.061764],"type":"Point"}
}