{
  "type": "Feature",
  "properties": {
    "iso:country":"US",
    "sg:address":"6108 Sheila St",
    "sg:city":"City Of Commerce",
    "sg:classifiers":[
        {
            "category":"Wholesale",
            "subcategory":"Seafood",
            "type":"Manufacturing & Wholesale Goods"
        }
    ],
    "sg:phone":"+1 323 724 5029",
    "sg:postcode":"90040",
    "sg:province":"CA",
    "wof:name":"Southern Cal Seafood",
    "wof:placetype":"venue"
},
  "geometry": {"coordinates":[-118.145882,33.994525],"type":"Point"}
}