{
  "type": "Feature",
  "properties": {
    "iso:country":"US",
    "sg:address":"695 S Imperial Ave",
    "sg:city":"Brawley",
    "sg:classifiers":[
        {
            "category":"Education",
            "subcategory":"Special Training",
            "type":"Public Place"
        }
    ],
    "sg:phone":"+1 760 344 7745",
    "sg:postcode":"92227",
    "sg:province":"CA",
    "sg:tags":[
        "center"
    ],
    "wof:name":"Iv Learning Ctr",
    "wof:placetype":"venue"
},
  "geometry": {"coordinates":[-115.535101,32.97082],"type":"Point"}
}