{
  "type": "Feature",
  "properties": {
    "addr:full":"826 Orange Blossom Way Danville CA 94526",
    "addr:housenumber":"826",
    "addr:postcode":"94526",
    "addr:street":"Orange Blossom Way",
    "iso:country":"US",
    "sg:address":"826 Orange Blossom Way",
    "sg:city":"Danville",
    "sg:classifiers":[
        {
            "category":"Shopping",
            "subcategory":"Florist",
            "type":"Retail Goods"
        }
    ],
    "sg:phone":"+1 925 831 3606",
    "sg:postcode":"94526",
    "sg:province":"CA",
    "wof:name":"Two Flower Girls",
    "wof:placetype":"venue"
},
  "geometry": {"coordinates":[-121.98231,37.803238],"type":"Point"}
}