{
  "type": "Feature",
  "properties": {
    "iso:country":"US",
    "sg:address":"1100 Marin St",
    "sg:city":"Vallejo",
    "sg:classifiers":[
        {
            "category":"Health Services",
            "subcategory":"Medical Lab",
            "type":"Services"
        }
    ],
    "sg:phone":"+1 707 553 9052",
    "sg:postcode":"94590",
    "sg:province":"CA",
    "sg:tags":[
        "laboratory"
    ],
    "wof:name":"C & M Dental Laboratory",
    "wof:placetype":"venue"
},
  "geometry": {"coordinates":[-122.256497,38.106553],"type":"Point"}
}