{
  "type": "Feature",
  "properties": {
    "addr:full":"8437 Westminster Blvd Westminster CA 92683",
    "addr:housenumber":"8437",
    "addr:postcode":"92683",
    "addr:street":"Westminster Blvd",
    "iso:country":"US",
    "sg:address":"8437 Westminster Blvd",
    "sg:city":"Westminster",
    "sg:classifiers":[
        {
            "category":"Wholesale",
            "subcategory":"Machinery & Supplies",
            "type":"Manufacturing & Wholesale Goods"
        }
    ],
    "sg:phone":"+1 714 891 9980",
    "sg:postcode":"92683",
    "sg:province":"CA",
    "sg:tags":[
        "industrial",
        "general"
    ],
    "wof:name":"VI Man Sewing Sply Center",
    "wof:placetype":"venue"
},
  "geometry": {"coordinates":[-117.981128,33.759335],"type":"Point"}
}