{
  "type": "Feature",
  "properties": {
    "addr:full":"3395 Sacramento St San Francisco CA 94118",
    "addr:housenumber":"3395",
    "addr:postcode":"94118",
    "addr:street":"Sacramento St",
    "iso:country":"US",
    "sg:address":"3395 Sacramento St",
    "sg:city":"San Francisco",
    "sg:classifiers":[
        {
            "category":"Manufacturing",
            "subcategory":"Furniture",
            "type":"Manufacturing & Wholesale Goods"
        }
    ],
    "sg:phone":"+1 415 931 8131",
    "sg:postcode":"94118",
    "sg:province":"CA",
    "sg:tags":[
        "household",
        "wood",
        "mfg"
    ],
    "wof:name":"Thomas Moser Cabinetmakers",
    "wof:placetype":"venue"
},
  "geometry": {"coordinates":[-122.44736899999999,37.788102],"type":"Point"}
}