{
  "type": "Feature",
  "properties": {
    "addr:full":"712 Capitola Avenue Capitola CA 95010",
    "addr:housenumber":"712",
    "addr:postcode":"95010",
    "addr:street":"Capitola Avenue",
    "iso:country":"US",
    "sg:address":"712 Capitola Avenue",
    "sg:city":"Capitola",
    "sg:classifiers":[
        {
            "category":"Taxi",
            "type":"Transportation"
        }
    ],
    "sg:phone":"+1 831 476 2616",
    "sg:postcode":"95010",
    "sg:province":"CA",
    "sg:website":"www.dennisnortondesign.com",
    "wof:name":"Norton Dennis Home Design",
    "wof:placetype":"venue"
},
  "geometry": {"coordinates":[-121.95560399999999,36.976642],"type":"Point"}
}