{
  "type": "Feature",
  "properties": {
    "iso:country":"US",
    "sg:address":"1421 N Acacia Ave",
    "sg:city":"Reedley",
    "sg:classifiers":[
        {
            "category":"Health Services",
            "subcategory":"Doctor",
            "type":"Services"
        }
    ],
    "sg:phone":"+1 559 637 1676",
    "sg:postcode":"93654",
    "sg:province":"CA",
    "sg:tags":[
        "clinic"
    ],
    "wof:name":"Central Valley Rural Dialysis",
    "wof:placetype":"venue"
},
  "geometry": {"coordinates":[-119.45102199999999,36.60852],"type":"Point"}
}