{
  "type": "Feature",
  "properties": {
    "iso:country":"US",
    "sg:address":"4829 Clairemont Dr",
    "sg:city":"San Diego",
    "sg:classifiers":[
        {
            "category":"Shopping",
            "subcategory":"Pharmacy",
            "type":"Retail Goods"
        }
    ],
    "sg:phone":"+1 858 273 8010",
    "sg:postcode":"92117",
    "sg:province":"CA",
    "wof:name":"Sav-On Drugs",
    "wof:placetype":"venue"
},
  "geometry": {"coordinates":[-117.204114,32.832323],"type":"Point"}
}