{
  "type": "Feature",
  "properties": {
    "addr:full":"400 N Nash St El Segundo CA 90245",
    "addr:housenumber":"400",
    "addr:postcode":"90245",
    "addr:street":"N Nash St",
    "iso:country":"US",
    "sg:address":"400 N Nash St",
    "sg:city":"El Segundo",
    "sg:classifiers":[
        {
            "category":"Wholesale",
            "subcategory":"Drugs",
            "type":"Manufacturing & Wholesale Goods"
        }
    ],
    "sg:phone":"+1 323 772 0083",
    "sg:postcode":"90245",
    "sg:province":"CA",
    "wof:name":"Gordon Laboratories Inc",
    "wof:placetype":"venue"
},
  "geometry": {"coordinates":[-118.38736400000001,33.922333],"type":"Point"}
}