{
  "type": "Feature",
  "properties": {
    "iso:country":"US",
    "sg:address":"18300 Gridley Rd Ste 304",
    "sg:city":"Artesia",
    "sg:classifiers":[
        {
            "category":"Health Services",
            "subcategory":"Doctor",
            "type":"Services"
        }
    ],
    "sg:phone":"+1 562 924 3851",
    "sg:postcode":"90701",
    "sg:province":"CA",
    "wof:name":"Family Wellness Center",
    "wof:placetype":"venue"
},
  "geometry": {"coordinates":[-118.07651,33.865622],"type":"Point"}
}