{
  "type": "Feature",
  "properties": {
    "addr:full":"822 Hermosa Ave Hermosa Beach CA 90254",
    "addr:housenumber":"822",
    "addr:postcode":"90254",
    "addr:street":"Hermosa Ave",
    "iso:country":"US",
    "sg:address":"822 Hermosa Ave",
    "sg:city":"Hermosa Beach",
    "sg:classifiers":[
        {
            "category":"Personal",
            "subcategory":"Beauty Salon",
            "type":"Services"
        }
    ],
    "sg:phone":"+1 310 406 1633",
    "sg:postcode":"90254",
    "sg:province":"CA",
    "sg:tags":[
        "treatment",
        "skin"
    ],
    "wof:name":"Aesthetics By Amaal & Niko",
    "wof:placetype":"venue"
},
  "geometry": {"coordinates":[-118.39934,33.859954],"type":"Point"}
}