{
  "type": "Feature",
  "properties": {
    "addr:full":"11490 Burbank Blvd North Hollywood CA 91601",
    "addr:housenumber":"11490",
    "addr:postcode":"91601",
    "addr:street":"Burbank Blvd",
    "iso:country":"US",
    "sg:address":"11490 Burbank Blvd",
    "sg:city":"North Hollywood",
    "sg:classifiers":[
        {
            "category":"Autos & Motor Vehicles",
            "subcategory":"Automobile Sales",
            "type":"Retail Goods"
        }
    ],
    "sg:phone":"+1 818 761 6940",
    "sg:postcode":"91601",
    "sg:province":"CA",
    "sg:tags":[
        "car"
    ],
    "sg:website":"www.FCautogroup.com",
    "wof:name":"First Class Auto Group",
    "wof:placetype":"venue"
},
  "geometry": {"coordinates":[-118.381985,34.171879],"type":"Point"}
}