{
  "type": "Feature",
  "properties": {
    "addr:full":"4150 Capitola Rd Capitola CA 95010",
    "addr:housenumber":"4150",
    "addr:postcode":"95010",
    "addr:street":"Capitola Rd",
    "iso:country":"US",
    "sg:address":"4150 Capitola Rd",
    "sg:city":"Capitola",
    "sg:classifiers":[
        {
            "category":"Shopping",
            "subcategory":"Gifts & Souvenirs",
            "type":"Retail Goods"
        }
    ],
    "sg:phone":"+1 831 475 8575",
    "sg:postcode":"95010",
    "sg:province":"CA",
    "sg:tags":[
        "shop"
    ],
    "wof:name":"Graceland Christian Books",
    "wof:placetype":"venue"
},
  "geometry": {"coordinates":[-121.96375399999999,36.973646],"type":"Point"}
}