{
  "type": "Feature",
  "properties": {
    "iso:country":"US",
    "sg:address":"70 W Hedding St",
    "sg:city":"San Jose",
    "sg:classifiers":[
        {
            "category":"Government",
            "subcategory":"Office",
            "type":"Public Place"
        },
        {
            "category":"Professional",
            "subcategory":"Management & Consulting",
            "type":"Services"
        }
    ],
    "sg:phone":"+1 408 792 2315",
    "sg:postcode":"95110",
    "sg:province":"CA",
    "sg:tags":[
        "social",
        "program",
        "administration",
        "relations",
        "manpower"
    ],
    "wof:name":"Human Relations Office of",
    "wof:placetype":"venue"
},
  "geometry": {"coordinates":[-121.904236,37.353007],"type":"Point"}
}