{
  "type": "Feature",
  "properties": {
    "addr:full":"165 N 3rd St Porterville CA 93257",
    "addr:housenumber":"165",
    "addr:postcode":"93257",
    "addr:street":"N 3Rd St",
    "iso:country":"US",
    "sg:address":"165 N 3rd St",
    "sg:city":"Porterville",
    "sg:classifiers":[
        {
            "category":"Wholesale",
            "subcategory":"Computers",
            "type":"Manufacturing & Wholesale Goods"
        },
        {
            "category":"Shopping",
            "subcategory":"Computers & Home Electronics",
            "type":"Retail Goods"
        }
    ],
    "sg:phone":"+1 559 781 0173",
    "sg:postcode":"93257",
    "sg:province":"CA",
    "sg:tags":[
        "equipment",
        "dealer"
    ],
    "wof:name":"Tree's Computer Solutions",
    "wof:placetype":"venue"
},
  "geometry": {"coordinates":[-119.014241,36.068344],"type":"Point"}
}