{
  "type": "Feature",
  "properties": {
    "addr:full":"13502 Whittier Blvd Whittier CA 90605",
    "addr:housenumber":"13502",
    "addr:postcode":"90605",
    "addr:street":"Whittier Blvd",
    "iso:country":"US",
    "sg:address":"13502 Whittier Blvd",
    "sg:city":"Whittier",
    "sg:classifiers":[
        {
            "category":"Wholesale",
            "subcategory":"Machinery & Supplies",
            "type":"Manufacturing & Wholesale Goods"
        }
    ],
    "sg:phone":"+1 562 945 6912",
    "sg:postcode":"90605",
    "sg:province":"CA",
    "sg:tags":[
        "abrasive"
    ],
    "wof:name":"Rdl Industrial Supplies",
    "wof:placetype":"venue"
},
  "geometry": {"coordinates":[-118.032149,33.962803],"type":"Point"}
}