{
  "type": "Feature",
  "properties": {
    "addr:full":"173 Mc Kinley Pl Monrovia CA 91016",
    "addr:housenumber":"173",
    "addr:postcode":"91016",
    "addr:street":"Mc Kinley Pl",
    "iso:country":"US",
    "sg:address":"173 Mc Kinley Pl",
    "sg:city":"Monrovia",
    "sg:classifiers":[
        {
            "category":"Building & Trades",
            "subcategory":"Equipment Rental",
            "type":"Services"
        }
    ],
    "sg:phone":"+1 626 358 6107",
    "sg:postcode":"91016",
    "sg:province":"CA",
    "wof:name":"Banana Grip Equipment",
    "wof:placetype":"venue"
},
  "geometry": {"coordinates":[-118.016496,34.152739],"type":"Point"}
}