{
  "type": "Feature",
  "properties": {
    "addr:full":"3rd Avenue b/t Naples and Palm Orange Avenue b/t 3rd Ave and 805 Chula Vista CA 91912",
    "addr:postcode":"91912",
    "addr:street":"3Rd Avenue B / T Naples And Palm Orange Avenue B / T 3Rd Ave And 805",
    "iso:country":"US",
    "sg:address":"3rd Avenue b/t Naples and Palm Orange Avenue b/t 3rd Ave and 805",
    "sg:city":"Chula Vista",
    "sg:classifiers":[
        {
            "category":"Food Court",
            "type":"Food & Drink"
        }
    ],
    "sg:postcode":"91912",
    "sg:province":"CA",
    "sg:tags":[
        "stand"
    ],
    "wof:name":"Tacquiza Cart",
    "wof:placetype":"venue"
},
  "geometry": {"coordinates":[-117.069115,32.613686],"type":"Point"}
}