{
  "type": "Feature",
  "properties": {
    "iso:country":"US",
    "sg:address":"3106 E Plaza Blvd",
    "sg:city":"National City",
    "sg:classifiers":[
        {
            "category":"Shopping",
            "subcategory":"Clothing, Apparel, & Fashions",
            "type":"Retail Goods"
        }
    ],
    "sg:phone":"+1 619 292 3634",
    "sg:postcode":"91950",
    "sg:province":"CA",
    "sg:tags":[
        "men's",
        "clothing",
        "women's"
    ],
    "wof:name":"Street Level Clothing & Accessories",
    "wof:placetype":"venue"
},
  "geometry": {"coordinates":[-117.07340000000001,32.681959],"type":"Point"}
}