{
  "type": "Feature",
  "properties": {
    "iso:country":"US",
    "sg:address":"2115 S Hellman Ave",
    "sg:city":"Ontario",
    "sg:classifiers":[
        {
            "category":"Manufacturing",
            "subcategory":"Tools & Machinery",
            "type":"Manufacturing & Wholesale Goods"
        }
    ],
    "sg:phone":"+1 909 673 1633",
    "sg:postcode":"91761",
    "sg:province":"CA",
    "sg:tags":[
        "machine",
        "shop",
        "industrial",
        "mfg"
    ],
    "wof:name":"AM Tek Engineering",
    "wof:placetype":"venue"
},
  "geometry": {"coordinates":[-117.601945,34.034169],"type":"Point"}
}