{
  "type": "Feature",
  "properties": {
    "iso:country":"US",
    "sg:address":"1928 Rustin Ave",
    "sg:city":"Riverside",
    "sg:classifiers":[
        {
            "category":"Home & Garden",
            "subcategory":"Building Materials",
            "type":"Retail Goods"
        }
    ],
    "sg:phone":"+1 951 778 1089",
    "sg:postcode":"92507",
    "sg:province":"CA",
    "sg:tags":[
        "door"
    ],
    "wof:name":"Clopay Holmes Garage Doors",
    "wof:placetype":"venue"
},
  "geometry": {"coordinates":[-117.335392,33.991207],"type":"Point"}
}