{
  "type": "Feature",
  "properties": {
    "iso:country":"US",
    "sg:address":"1306 Solano St",
    "sg:city":"Corning",
    "sg:classifiers":[
        {
            "category":"Home & Garden",
            "subcategory":"Household Appliances",
            "type":"Retail Goods"
        }
    ],
    "sg:phone":"+1 530 824 3645",
    "sg:postcode":"96021",
    "sg:province":"CA",
    "wof:name":"Jim's Appliances",
    "wof:placetype":"venue"
},
  "geometry": {"coordinates":[-122.183396,39.927996],"type":"Point"}
}