{
  "type": "Feature",
  "properties": {
    "iso:country":"US",
    "sg:address":"13730 Navajo Rd",
    "sg:city":"Apple Valley",
    "sg:classifiers":[
        {
            "category":"Restaurant",
            "type":"Food & Drink"
        }
    ],
    "sg:menulink":"http://www.allmenus.com/ca/barstow-victorville/165501-del-taco/menu/",
    "sg:phone":"+1 760 247 3364",
    "sg:postcode":"92307",
    "sg:province":"CA",
    "sg:tags":[
        "american",
        "mexican",
        "tex-mex"
    ],
    "wof:name":"Del Taco",
    "wof:placetype":"venue"
},
  "geometry": {"coordinates":[-117.190631,34.501145],"type":"Point"}
}