{
  "type": "Feature",
  "properties": {
    "iso:country":"US",
    "sg:address":"810 Wright St",
    "sg:city":"Santa Rosa",
    "sg:classifiers":[
        {
            "category":"Shopping",
            "subcategory":"Stationery & Office Supplies",
            "type":"Retail Goods"
        }
    ],
    "sg:phone":"+1 707 528 0607",
    "sg:postcode":"95404",
    "sg:province":"CA",
    "wof:name":"Johnson Business Services",
    "wof:placetype":"venue"
},
  "geometry": {"coordinates":[-122.709419,38.449406],"type":"Point"}
}