{
  "type": "Feature",
  "properties": {
    "addr:full":"6504 1/2 Arizona Ave Los Angeles CA 90045",
    "addr:housenumber":"6504 1 / 2",
    "addr:postcode":"90045",
    "addr:street":"Arizona Ave",
    "iso:country":"US",
    "sg:address":"6504 1/2 Arizona Ave",
    "sg:city":"Los Angeles",
    "sg:classifiers":[
        {
            "category":"Wholesale",
            "subcategory":"Computers",
            "type":"Manufacturing & Wholesale Goods"
        }
    ],
    "sg:phone":"+1 310 348 9626",
    "sg:postcode":"90045",
    "sg:province":"CA",
    "sg:website":"www.ourcomputertech.com",
    "wof:name":"Our Computer Tech",
    "wof:placetype":"venue"
},
  "geometry": {"coordinates":[-118.395886,33.981181],"type":"Point"}
}