{
  "type": "Feature",
  "properties": {
    "iso:country":"US",
    "sg:address":"1311 Hampshire Ct",
    "sg:city":"Concord",
    "sg:classifiers":[
        {
            "category":"Wholesale",
            "subcategory":"Electrical",
            "type":"Manufacturing & Wholesale Goods"
        }
    ],
    "sg:phone":"+1 925 689 9090",
    "sg:postcode":"94518",
    "sg:province":"CA",
    "sg:tags":[
        "equipment"
    ],
    "wof:name":"Crowbar Electrical Parts",
    "wof:placetype":"venue"
},
  "geometry": {"coordinates":[-122.047831,37.942888],"type":"Point"}
}