{
  "type": "Feature",
  "properties": {
    "iso:country":"US",
    "sg:address":"4885 Newport Ave",
    "sg:city":"San Diego",
    "sg:classifiers":[
        {
            "category":"Shopping",
            "subcategory":"Gifts & Souvenirs",
            "type":"Retail Goods"
        },
        {
            "category":"Personal",
            "subcategory":"Skin Care",
            "type":"Services"
        }
    ],
    "sg:phone":"+1 619 501 1627",
    "sg:postcode":"92107",
    "sg:province":"CA",
    "sg:tags":[
        "flower"
    ],
    "sg:website":"www.pinetreeroadshop.com",
    "wof:name":"Pine Tree Road Soap Shop",
    "wof:placetype":"venue"
},
  "geometry": {"coordinates":[-117.24906799999999,32.745617],"type":"Point"}
}