{
  "type": "Feature",
  "properties": {
    "iso:country":"US",
    "sg:address":"3209 E Vermillion St",
    "sg:city":"West Covina",
    "sg:classifiers":[
        {
            "category":"Shopping",
            "subcategory":"Musical Instruments",
            "type":"Retail Goods"
        }
    ],
    "sg:phone":"+1 626 964 9860",
    "sg:postcode":"91792",
    "sg:province":"CA",
    "wof:name":"Organisacion Musical Alpha",
    "wof:placetype":"venue"
},
  "geometry": {"coordinates":[-117.875259,34.005767],"type":"Point"}
}