{
  "type": "Feature",
  "properties": {
    "iso:country":"US",
    "sg:address":"969 Valley Dr",
    "sg:city":"Vista",
    "sg:classifiers":[
        {
            "category":"Professional",
            "subcategory":"Detective & Security Services",
            "type":"Services"
        }
    ],
    "sg:phone":"+1 760 941 3592",
    "sg:postcode":"92084",
    "sg:province":"CA",
    "sg:tags":[
        "investigator"
    ],
    "wof:name":"Laurence G Hagen Investigation",
    "wof:placetype":"venue"
},
  "geometry": {"coordinates":[-117.213539,33.192472],"type":"Point"}
}