{
  "type": "Feature",
  "properties": {
    "addr:full":"5404 Napa St San Diego CA 92110",
    "addr:housenumber":"5404",
    "addr:postcode":"92110",
    "addr:street":"Napa St",
    "iso:country":"US",
    "sg:address":"5404 Napa St",
    "sg:city":"San Diego",
    "sg:classifiers":[
        {
            "category":"Organizations",
            "subcategory":"Non-profit Organization",
            "type":"Services"
        }
    ],
    "sg:phone":"+1 619 276 5296",
    "sg:postcode":"92110",
    "sg:province":"CA",
    "sg:website":"www.nayre.org",
    "wof:name":"National Assn For Year Round",
    "wof:placetype":"venue"
},
  "geometry": {"coordinates":[-117.195425,32.764214],"type":"Point"}
}