{
  "type": "Feature",
  "properties": {
    "iso:country":"US",
    "sg:address":"1825 Chaucer Dr",
    "sg:city":"San Jose",
    "sg:classifiers":[
        {
            "category":"Professional",
            "subcategory":"Management & Consulting",
            "type":"Services"
        }
    ],
    "sg:phone":"+1 408 505 4838",
    "sg:postcode":"95116",
    "sg:province":"CA",
    "sg:tags":[
        "control",
        "builder",
        "painter"
    ],
    "wof:name":"Contractors Painting Group",
    "wof:placetype":"venue"
},
  "geometry": {"coordinates":[-121.84340400000001,37.344209],"type":"Point"}
}