{
  "type": "Feature",
  "properties": {
    "addr:full":"3100 Howsley Rd Pleasant Grove CA 95668",
    "addr:postcode":"3100;95668",
    "addr:street":"Howsley Rd",
    "iso:country":"US",
    "sg:address":"3100 Howsley Rd",
    "sg:city":"Pleasant Grove",
    "sg:classifiers":[
        {
            "category":"Government",
            "subcategory":"Fire Station",
            "type":"Public Place"
        }
    ],
    "sg:phone":"+1 916 655 3937",
    "sg:postcode":"95668",
    "sg:province":"CA",
    "sg:tags":[
        "department"
    ],
    "wof:name":"Pleasant Grove Fire Dept",
    "wof:placetype":"venue"
},
  "geometry": {"coordinates":[-121.504459,38.823849],"type":"Point"}
}