{
  "type": "Feature",
  "properties": {
    "iso:country":"US",
    "sg:address":"3460 Laurie Pl",
    "sg:city":"Studio City",
    "sg:classifiers":[
        {
            "category":"Wholesale",
            "subcategory":"Computers",
            "type":"Manufacturing & Wholesale Goods"
        }
    ],
    "sg:phone":"+1 310 230 6013",
    "sg:postcode":"91604",
    "sg:province":"CA",
    "wof:name":"Xamountcom LLC",
    "wof:placetype":"venue"
},
  "geometry": {"coordinates":[-118.375656,34.135855],"type":"Point"}
}