{
  "type": "Feature",
  "properties": {
    "addr:full":"3460 Laurie Pl Studio City CA 91604",
    "addr:housenumber":"3460",
    "addr:postcode":"91604",
    "addr:street":"Laurie Pl",
    "iso:country":"US",
    "sg:address":"3460 Laurie Pl",
    "sg:city":"Studio City",
    "sg:classifiers":[
        {
            "category":"Wholesale",
            "subcategory":"Computers",
            "type":"Manufacturing & Wholesale Goods"
        }
    ],
    "sg:phone":"+1 310 230 6013",
    "sg:postcode":"91604",
    "sg:province":"CA",
    "wof:name":"Xamountcom LLC",
    "wof:placetype":"venue"
},
  "geometry": {"coordinates":[-118.37565600000001,34.135855],"type":"Point"}
}