{
  "type": "Feature",
  "properties": {
    "addr:full":"194 Arcadia Dr Grass Valley CA 95945",
    "addr:housenumber":"194",
    "addr:postcode":"95945",
    "addr:street":"Arcadia Dr",
    "iso:country":"US",
    "sg:address":"194 Arcadia Dr",
    "sg:city":"Grass Valley",
    "sg:classifiers":[
        {
            "category":"Retail",
            "subcategory":"Laundry & Dry Cleaning",
            "type":"Services"
        }
    ],
    "sg:phone":"+1 530 273 1511",
    "sg:postcode":"95945",
    "sg:province":"CA",
    "sg:tags":[
        "cleaners",
        "rug",
        "carpet"
    ],
    "wof:name":"Nice N'Tidy",
    "wof:placetype":"venue"
},
  "geometry": {"coordinates":[-121.058695,39.229095],"type":"Point"}
}