{
  "type": "Feature",
  "properties": {
    "addr:full":"1130 Monaco Ct Stockton CA 95207",
    "addr:housenumber":"1130",
    "addr:postcode":"95207",
    "addr:street":"Monaco Ct",
    "iso:country":"US",
    "sg:address":"1130 Monaco Ct",
    "sg:city":"Stockton",
    "sg:classifiers":[
        {
            "category":"Health Services",
            "subcategory":"Nursing And Care Facility",
            "type":"Services"
        }
    ],
    "sg:phone":"+1 209 478 2060",
    "sg:postcode":"95207",
    "sg:province":"CA",
    "sg:tags":[
        "home",
        "convalescent"
    ],
    "wof:name":"Crestwood Manor",
    "wof:placetype":"venue"
},
  "geometry": {"coordinates":[-121.3212,37.988025],"type":"Point"}
}