{
  "type": "Feature",
  "properties": {
    "iso:country":"US",
    "sg:address":"26952 La Paz Rd",
    "sg:city":"Aliso Viejo",
    "sg:classifiers":[
        {
            "category":"Restaurant",
            "type":"Food & Drink"
        }
    ],
    "sg:phone":"+1 949 643 1232",
    "sg:postcode":"92656",
    "sg:province":"CA",
    "sg:tags":[
        "sushi",
        "bar"
    ],
    "wof:name":"Zen Sushi & Sushi Bar",
    "wof:placetype":"venue"
},
  "geometry": {"coordinates":[-117.70706300000001,33.571562],"type":"Point"}
}