{
  "type": "Feature",
  "properties": {
    "addr:full":"9333 Narnia Dr Riverside CA 92503",
    "addr:housenumber":"9333",
    "addr:postcode":"92503",
    "addr:street":"Narnia Dr",
    "iso:country":"US",
    "sg:address":"9333 Narnia Dr",
    "sg:city":"Riverside",
    "sg:classifiers":[
        {
            "category":"Food & Beverages",
            "subcategory":"Specialty",
            "type":"Retail Goods"
        }
    ],
    "sg:phone":"+1 951 358 0039",
    "sg:postcode":"92503",
    "sg:province":"CA",
    "sg:tags":[
        "gourmet",
        "shop"
    ],
    "wof:name":"Ciao Italia Foods Inc",
    "wof:placetype":"venue"
},
  "geometry": {"coordinates":[-117.43809,33.914912],"type":"Point"}
}