{
  "type": "Feature",
  "properties": {
    "addr:full":"101 Bridewell St #102 Los Angeles CA 90042",
    "addr:housenumber":"101",
    "addr:postcode":"90042",
    "addr:street":"Bridewell St # 102",
    "iso:country":"US",
    "sg:address":"101 Bridewell St #102",
    "sg:city":"Los Angeles",
    "sg:classifiers":[
        {
            "category":"Real Estate",
            "subcategory":"Real Estate Services",
            "type":"Services"
        },
        {
            "category":"Real Estate",
            "subcategory":"Real Estate Operator",
            "type":"Services"
        }
    ],
    "sg:phone":"+1 323 254 3519",
    "sg:postcode":"90042",
    "sg:province":"CA",
    "sg:tags":[
        "apartment",
        "property",
        "management"
    ],
    "sg:website":"www.pasadenaparkplace.com",
    "wof:name":"Pasadena Park Place Apartments",
    "wof:placetype":"venue"
},
  "geometry": {"coordinates":[-118.178229,34.112671],"type":"Point"}
}