{
  "type": "Feature",
  "properties": {
    "iso:country":"US",
    "sg:address":"149 N Main St",
    "sg:city":"Lakeport",
    "sg:classifiers":[
        {
            "category":"Government",
            "subcategory":"Office",
            "type":"Public Place"
        }
    ],
    "sg:phone":"+1 707 263 4771",
    "sg:postcode":"95453",
    "sg:province":"CA",
    "wof:name":"Scotts Valley Bnd-Pomo Indians",
    "wof:placetype":"venue"
},
  "geometry": {"coordinates":[-122.915233,39.04272],"type":"Point"}
}