{
  "type": "Feature",
  "properties": {
    "iso:country":"US",
    "sg:address":"853 Veterans Blvd",
    "sg:city":"Redwood City",
    "sg:classifiers":[
        {
            "category":"Personal",
            "subcategory":"Beauty Salon",
            "type":"Services"
        }
    ],
    "sg:phone":"+1 650 364 1268",
    "sg:postcode":"94063",
    "sg:province":"CA",
    "wof:name":"Supercuts",
    "wof:placetype":"venue"
},
  "geometry": {"coordinates":[-122.22890599999999,37.490653],"type":"Point"}
}