{
  "type": "Feature",
  "properties": {
    "iso:country":"US",
    "sg:address":"10609 Bloomfield St",
    "sg:city":"North Hollywood",
    "sg:classifiers":[
        {
            "category":"Home & Garden",
            "subcategory":"Furniture",
            "type":"Retail Goods"
        }
    ],
    "sg:phone":"+1 818 761 9148",
    "sg:postcode":"91602",
    "sg:province":"CA",
    "wof:name":"Bojob Patio Art",
    "wof:placetype":"venue"
},
  "geometry": {"coordinates":[-118.363483,34.149681],"type":"Point"}
}