{
  "type": "Feature",
  "properties": {
    "addr:full":"24775 Kauffman Ave Red Bluff CA 96080",
    "addr:housenumber":"24775",
    "addr:postcode":"96080",
    "addr:street":"Kauffman Ave",
    "iso:country":"US",
    "sg:address":"24775 Kauffman Ave",
    "sg:city":"Red Bluff",
    "sg:classifiers":[
        {
            "category":"Farming",
            "subcategory":"Orchard",
            "type":"Manufacturing & Wholesale Goods"
        }
    ],
    "sg:phone":"+1 530 527 0196",
    "sg:postcode":"96080",
    "sg:province":"CA",
    "sg:tags":[
        "ranch",
        "prune",
        "walnut"
    ],
    "wof:name":"Smith Ranch",
    "wof:placetype":"venue"
},
  "geometry": {"coordinates":[-122.108333,40.127656],"type":"Point"}
}