{
  "type": "Feature",
  "properties": {
    "iso:country":"US",
    "sg:address":"806 N Winuba Ln",
    "sg:city":"Bishop",
    "sg:classifiers":[
        {
            "category":"Building & Trades",
            "subcategory":"Construction",
            "type":"Services"
        }
    ],
    "sg:phone":"+1 760 873 6929",
    "sg:postcode":"93514",
    "sg:province":"CA",
    "sg:tags":[
        "painter"
    ],
    "wof:name":"Piper Painting",
    "wof:placetype":"venue"
},
  "geometry": {"coordinates":[-118.429787,37.370827],"type":"Point"}
}