{
  "type": "Feature",
  "properties": {
    "addr:full":"12807 Halldale Ave Gardena CA 90249",
    "addr:housenumber":"12807",
    "addr:postcode":"90249",
    "addr:street":"Halldale Ave",
    "iso:country":"US",
    "sg:address":"12807 Halldale Ave",
    "sg:city":"Gardena",
    "sg:classifiers":[
        {
            "category":"Professional",
            "type":"Services"
        }
    ],
    "sg:phone":"+1 310 516 8325",
    "sg:postcode":"90249",
    "sg:province":"CA",
    "wof:name":"Motiva Kaxan",
    "wof:placetype":"venue"
},
  "geometry": {"coordinates":[-118.30235999999999,33.914602],"type":"Point"}
}