{
  "type": "Feature",
  "properties": {
    "iso:country":"US",
    "sg:address":"3720 Industry Ave Ste 125",
    "sg:city":"Lakewood",
    "sg:classifiers":[
        {
            "category":"Shopping",
            "subcategory":"Shoes",
            "type":"Retail Goods"
        }
    ],
    "sg:phone":"+1 562 988 8528",
    "sg:postcode":"90712",
    "sg:province":"CA",
    "sg:tags":[
        "store"
    ],
    "wof:name":"Footprints Usa",
    "wof:placetype":"venue"
},
  "geometry": {"coordinates":[-118.1653,33.824866],"type":"Point"}
}