{
  "type": "Feature",
  "properties": {
    "addr:full":"925 Hooper Ave Los Angeles CA 90021",
    "addr:housenumber":"925",
    "addr:postcode":"90021",
    "addr:street":"Hooper Ave",
    "iso:country":"US",
    "sg:address":"925 Hooper Ave",
    "sg:city":"Los Angeles",
    "sg:classifiers":[
        {
            "category":"Wholesale",
            "subcategory":"Fruits & Vegetables",
            "type":"Manufacturing & Wholesale Goods"
        }
    ],
    "sg:phone":"+1 213 489 9982",
    "sg:postcode":"90021",
    "sg:province":"CA",
    "sg:tags":[
        "veggie"
    ],
    "wof:name":"Andrew's Produce",
    "wof:placetype":"venue"
},
  "geometry": {"coordinates":[-118.24099699999999,34.028702],"type":"Point"}
}