{
  "type": "Feature",
  "properties": {
    "addr:full":"3319 Madera Ave Oakland CA 94619",
    "addr:housenumber":"3319",
    "addr:postcode":"94619",
    "addr:street":"Madera Ave",
    "iso:country":"US",
    "sg:address":"3319 Madera Ave",
    "sg:city":"Oakland",
    "sg:classifiers":[
        {
            "category":"Building & Trades",
            "subcategory":"Construction",
            "type":"Services"
        }
    ],
    "sg:phone":"+1 510 261 0922",
    "sg:postcode":"94619",
    "sg:province":"CA",
    "sg:tags":[
        "system",
        "contractor",
        "air conditioning"
    ],
    "wof:name":"Sealed Air",
    "wof:placetype":"venue"
},
  "geometry": {"coordinates":[-122.190331,37.780772],"type":"Point"}
}