{
  "type": "Feature",
  "properties": {
    "addr:full":"825 15th St Sacramento CA 95814",
    "addr:housenumber":"825",
    "addr:postcode":"95814",
    "addr:street":"15Th St",
    "iso:country":"US",
    "sg:address":"825 15th St",
    "sg:city":"Sacramento",
    "sg:classifiers":[
        {
            "category":"Place Of Worship",
            "subcategory":"Church",
            "type":"Public Place"
        },
        {
            "category":"Place Of Worship",
            "type":"Public Place"
        }
    ],
    "sg:phone":"+1 916 448 5891",
    "sg:postcode":"95814",
    "sg:province":"CA",
    "sg:tags":[
        "churches-interdenominational",
        "denomination",
        "churches-various",
        "churches-non-denominational"
    ],
    "wof:name":"Hubbard Dianetics Foundation",
    "wof:placetype":"venue"
},
  "geometry": {"coordinates":[-121.485719,38.580395],"type":"Point"}
}