{
  "type": "Feature",
  "properties": {
    "iso:country":"US",
    "sg:address":"8440 Warner Dr",
    "sg:city":"Culver City",
    "sg:classifiers":[
        {
            "category":"Wholesale",
            "subcategory":"Stationery",
            "type":"Manufacturing & Wholesale Goods"
        }
    ],
    "sg:phone":"+1 310 842 4967",
    "sg:postcode":"90232",
    "sg:province":"CA",
    "sg:tags":[
        "supply"
    ],
    "wof:name":"All Star Paper Co",
    "wof:placetype":"venue"
},
  "geometry": {"coordinates":[-118.381152,34.023396],"type":"Point"}
}