{
  "type": "Feature",
  "properties": {
    "iso:country":"US",
    "sg:address":"1491 S Wolfe Rd",
    "sg:city":"Sunnyvale",
    "sg:classifiers":[
        {
            "category":"Professional",
            "subcategory":"Accounting & Tax Preparation",
            "type":"Services"
        }
    ],
    "sg:phone":"+1 408 736 2451",
    "sg:postcode":"94087",
    "sg:province":"CA",
    "sg:tags":[
        "accountant"
    ],
    "sg:website":"www.jessietax.com",
    "wof:name":"Jessie Tax Services",
    "wof:placetype":"venue"
},
  "geometry": {"coordinates":[-122.01454699999999,37.345244],"type":"Point"}
}