{
  "type": "Feature",
  "properties": {
    "iso:country":"US",
    "sg:address":"1580 E Edinger Ave",
    "sg:city":"Santa Ana",
    "sg:classifiers":[
        {
            "category":"Manufacturing",
            "subcategory":"Metals",
            "type":"Manufacturing & Wholesale Goods"
        }
    ],
    "sg:phone":"+1 714 953 4265",
    "sg:postcode":"92707",
    "sg:province":"CA",
    "sg:tags":[
        "product",
        "industrial",
        "fabricated",
        "mfg"
    ],
    "wof:name":"Nick Succa",
    "wof:placetype":"venue"
},
  "geometry": {"coordinates":[-117.841413,33.726753],"type":"Point"}
}