{
  "type": "Feature",
  "properties": {
    "addr:full":"14423 Sespe Pl Poway CA 92064",
    "addr:housenumber":"14423",
    "addr:postcode":"ca 92064",
    "addr:street":"Sespe Pl",
    "iso:country":"US",
    "sg:address":"14423 Sespe Pl",
    "sg:city":"Poway",
    "sg:classifiers":[
        {
            "category":"Real Estate",
            "subcategory":"Real Estate Services",
            "type":"Services"
        },
        {
            "category":"Real Estate",
            "subcategory":"Real Estate Agent",
            "type":"Services"
        }
    ],
    "sg:phone":"+1 858 486 8849",
    "sg:postcode":"92064",
    "sg:province":"CA",
    "sg:tags":[
        "buyer",
        "broker"
    ],
    "sg:website":"http://www.ranchandcoasthomes.com",
    "wof:name":"Amy Bramy",
    "wof:placetype":"venue"
},
  "geometry": {"coordinates":[-117.017448,32.975294],"type":"Point"}
}