{
  "type": "Feature",
  "properties": {
    "iso:country":"US",
    "sg:address":"11054 W Pico Blvd Ste 101",
    "sg:city":"Los Angeles",
    "sg:classifiers":[
        {
            "category":"Home & Garden",
            "subcategory":"Home Furnishings",
            "type":"Retail Goods"
        },
        {
            "category":"Building & Trades",
            "subcategory":"Construction",
            "type":"Services"
        }
    ],
    "sg:phone":"+1 310 479 1499",
    "sg:postcode":"90064",
    "sg:province":"CA",
    "sg:tags":[
        "interior",
        "bath",
        "design",
        "kitchen"
    ],
    "sg:website":"www.eurokitchenandbath.com",
    "wof:name":"Euro Design Kitchen & Bath",
    "wof:placetype":"venue"
},
  "geometry": {"coordinates":[-118.433711,34.037072],"type":"Point"}
}