{
  "type": "Feature",
  "properties": {
    "addr:full":"12326 Denholm Dr El Monte CA 91732",
    "addr:housenumber":"12326",
    "addr:postcode":"91732",
    "addr:street":"Denholm Dr",
    "iso:country":"US",
    "sg:address":"12326 Denholm Dr",
    "sg:city":"El Monte",
    "sg:classifiers":[
        {
            "category":"Manufacturing",
            "subcategory":"Tools & Machinery",
            "type":"Manufacturing & Wholesale Goods"
        }
    ],
    "sg:phone":"+1 626 443 8861",
    "sg:postcode":"91732",
    "sg:province":"CA",
    "sg:tags":[
        "machine",
        "shop"
    ],
    "wof:name":"Anzon Co",
    "wof:placetype":"venue"
},
  "geometry": {"coordinates":[-118.013713,34.057567],"type":"Point"}
}