{
  "type": "Feature",
  "properties": {
    "iso:country":"US",
    "sg:address":"16311 Ventura Blvd",
    "sg:city":"Encino",
    "sg:classifiers":[
        {
            "category":"Retail",
            "subcategory":"Portrait Studio",
            "type":"Services"
        }
    ],
    "sg:phone":"+1 818 995 0077",
    "sg:postcode":"91436",
    "sg:province":"CA",
    "sg:tags":[
        "photographer"
    ],
    "wof:name":"Gary West Productions Inc",
    "wof:placetype":"venue"
},
  "geometry": {"coordinates":[-118.489954,34.157308],"type":"Point"}
}