{
  "type": "Feature",
  "properties": {
    "addr:full":"2205 W 231st St Torrance CA 90501",
    "addr:housenumber":"2205",
    "addr:postcode":"90501",
    "addr:street":"W 231St St",
    "iso:country":"US",
    "sg:address":"2205 W 231st St",
    "sg:city":"Torrance",
    "sg:classifiers":[
        {
            "category":"Building & Trades",
            "subcategory":"Construction",
            "type":"Services"
        }
    ],
    "sg:phone":"+1 310 325 8340",
    "sg:postcode":"90501",
    "sg:province":"CA",
    "sg:tags":[
        "wallcoverings-installation",
        "wallpaper",
        "painting",
        "painter",
        "contractor"
    ],
    "wof:name":"Kim's Painting Maintenance",
    "wof:placetype":"venue"
},
  "geometry": {"coordinates":[-118.31999999999999,33.815498],"type":"Point"}
}