{
  "type": "Feature",
  "properties": {
    "iso:country":"US",
    "sg:address":"2205 W 231st St",
    "sg:city":"Torrance",
    "sg:classifiers":[
        {
            "category":"Building & Trades",
            "subcategory":"Construction",
            "type":"Services"
        }
    ],
    "sg:phone":"+1 310 325 8340",
    "sg:postcode":"90501",
    "sg:province":"CA",
    "sg:tags":[
        "wallcoverings-installation",
        "wallpaper",
        "painting",
        "painter",
        "contractor"
    ],
    "wof:name":"Kim's Painting Maintenance",
    "wof:placetype":"venue"
},
  "geometry": {"coordinates":[-118.32,33.815498],"type":"Point"}
}