{
  "type": "Feature",
  "properties": {
    "addr:full":"12940 Central Ave Chino CA 91710",
    "addr:housenumber":"12940",
    "addr:postcode":"91710",
    "addr:street":"Central Ave",
    "iso:country":"US",
    "sg:address":"12940 Central Ave",
    "sg:city":"Chino",
    "sg:classifiers":[
        {
            "category":"Restaurant",
            "type":"Food & Drink"
        }
    ],
    "sg:phone":"+1 909 628 2921",
    "sg:postcode":"91710",
    "sg:province":"CA",
    "wof:name":"Cock-A-Doodle Restaurant",
    "wof:placetype":"venue"
},
  "geometry": {"coordinates":[-117.689378,34.018329],"type":"Point"}
}