{
  "type": "Feature",
  "properties": {
    "addr:full":"Hilltop Mall Richmond CA 94801",
    "addr:postcode":"94801",
    "iso:country":"US",
    "sg:address":"Hilltop Mall",
    "sg:city":"Richmond",
    "sg:classifiers":[
        {
            "category":"Health Services",
            "subcategory":"Optometrist",
            "type":"Services"
        }
    ],
    "sg:phone":"+1 510 223 4441",
    "sg:postcode":"94801",
    "sg:province":"CA",
    "wof:name":"Eyexam of California",
    "wof:placetype":"venue"
},
  "geometry": {"coordinates":[-122.36599699999999,37.939899],"type":"Point"}
}