{
  "type": "Feature",
  "properties": {
    "addr:full":"409 E Cedar St Ontario CA 91761",
    "addr:housenumber":"409",
    "addr:postcode":"91761",
    "addr:street":"E Cedar St",
    "iso:country":"US",
    "sg:address":"409 E Cedar St",
    "sg:city":"Ontario",
    "sg:classifiers":[
        {
            "category":"Building & Trades",
            "subcategory":"Construction",
            "type":"Services"
        }
    ],
    "sg:phone":"+1 909 984 8607",
    "sg:postcode":"91761",
    "sg:province":"CA",
    "sg:tags":[
        "contractor"
    ],
    "wof:name":"Vasquez Design Group",
    "wof:placetype":"venue"
},
  "geometry": {"coordinates":[-117.647199,34.037559],"type":"Point"}
}