{
  "type": "Feature",
  "properties": {
    "iso:country":"US",
    "sg:address":"671 Colusa Ave",
    "sg:city":"Yuba City",
    "sg:classifiers":[
        {
            "category":"Home & Garden",
            "subcategory":"Carpets & Floor Coverings",
            "type":"Retail Goods"
        }
    ],
    "sg:phone":"+1 530 673 1450",
    "sg:postcode":"95991",
    "sg:province":"CA",
    "sg:tags":[
        "dealer",
        "rug"
    ],
    "wof:name":"Carpet One",
    "wof:placetype":"venue"
},
  "geometry": {"coordinates":[-121.625631,39.141562],"type":"Point"}
}