{
  "type": "Feature",
  "properties": {
    "iso:country":"US",
    "sg:address":"1133 Westwood Blvd",
    "sg:city":"Los Angeles",
    "sg:classifiers":[
        {
            "category":"Professional",
            "subcategory":"Printing & Photocopies",
            "type":"Services"
        }
    ],
    "sg:phone":"+1 310 443 3300",
    "sg:postcode":"90024",
    "sg:province":"CA",
    "wof:name":"Course Reader Materials",
    "wof:placetype":"venue"
},
  "geometry": {"coordinates":[-118.44499999999999,34.059502],"type":"Point"}
}