{
  "type": "Feature",
  "properties": {
    "addr:full":"1661 Airport Blvd Terminal C San Jose CA 95110",
    "addr:housenumber":"1661",
    "addr:postcode":"95110",
    "addr:street":"Airport Blvd Terminal C",
    "iso:country":"US",
    "sg:address":"1661 Airport Blvd Terminal C",
    "sg:city":"San Jose",
    "sg:classifiers":[
        {
            "category":"Donuts",
            "subcategory":"None",
            "type":"Food & Drink"
        }
    ],
    "sg:postcode":"95110",
    "sg:province":"CA",
    "wof:name":"Grab n Go Food",
    "wof:placetype":"venue"
},
  "geometry": {"coordinates":[-121.922606,37.363803],"type":"Point"}
}