{
  "type": "Feature",
  "properties": {
    "addr:full":"2831 Meridian Ave San Jose CA 95124",
    "addr:housenumber":"2831",
    "addr:postcode":"95124",
    "addr:street":"Meridian Ave",
    "iso:country":"US",
    "sg:address":"2831 Meridian Ave",
    "sg:city":"San Jose",
    "sg:classifiers":[
        {
            "category":"Restaurant",
            "type":"Food & Drink"
        }
    ],
    "sg:phone":"+1 408 265 7130",
    "sg:postcode":"95124",
    "sg:province":"CA",
    "wof:name":"Marie Callender's",
    "wof:placetype":"venue"
},
  "geometry": {"coordinates":[-121.906076,37.271112],"type":"Point"}
}