{
  "type": "Feature",
  "properties": {
    "addr:full":"10124 Carreta Dr Santee CA 92071",
    "addr:housenumber":"10124",
    "addr:postcode":"92071",
    "addr:street":"Carreta Dr",
    "iso:country":"US",
    "sg:address":"10124 Carreta Dr",
    "sg:city":"Santee",
    "sg:classifiers":[
        {
            "category":"Professional",
            "type":"Services"
        }
    ],
    "sg:phone":"+1 619 562 7352",
    "sg:postcode":"92071",
    "sg:province":"CA",
    "wof:name":"J&L Transaction Inc",
    "wof:placetype":"venue"
},
  "geometry": {"coordinates":[-116.968559,32.861828],"type":"Point"}
}