{
  "type": "Feature",
  "properties": {
    "addr:full":"3939 Ews Woods Blvd Stockton CA 95206",
    "addr:housenumber":"3939",
    "addr:postcode":"95206",
    "addr:street":"Ews Woods Blvd",
    "iso:country":"US",
    "sg:address":"3939 Ews Woods Blvd",
    "sg:city":"Stockton",
    "sg:classifiers":[
        {
            "category":"Education",
            "subcategory":"School",
            "type":"Public Place"
        }
    ],
    "sg:phone":"+1 209 858 3020",
    "sg:postcode":"95206",
    "sg:province":"CA",
    "wof:name":"August Knodt Elementary School",
    "wof:placetype":"venue"
},
  "geometry": {"coordinates":[-121.304103,37.907015],"type":"Point"}
}