{
  "type": "Feature",
  "properties": {
    "addr:full":"120 Seminary Dr Mill Valley CA 94941",
    "addr:housenumber":"120",
    "addr:postcode":"94941",
    "addr:street":"Seminary Dr",
    "iso:country":"US",
    "sg:address":"120 Seminary Dr",
    "sg:city":"Mill Valley",
    "sg:classifiers":[
        {
            "category":"Real Estate",
            "subcategory":"Real Estate Agent",
            "type":"Services"
        }
    ],
    "sg:phone":"+1 415 391 1777",
    "sg:postcode":"94941",
    "sg:province":"CA",
    "wof:name":"J Carcioner Commercial Rl Est",
    "wof:placetype":"venue"
},
  "geometry": {"coordinates":[-122.510047,37.883151],"type":"Point"}
}