{
  "type": "Feature",
  "properties": {
    "addr:full":"3774 Pacific Coast Hwy Torrance CA 90505",
    "addr:housenumber":"3774",
    "addr:postcode":"90505",
    "addr:street":"Pacific Coast Hwy",
    "iso:country":"US",
    "sg:address":"3774 Pacific Coast Hwy",
    "sg:city":"Torrance",
    "sg:classifiers":[
        {
            "category":"Sports & Exercise",
            "subcategory":"Gym",
            "type":"Entertainment"
        },
        {
            "category":"Organizations",
            "subcategory":"Religious Organization",
            "type":"Services"
        }
    ],
    "sg:phone":"+1 310 779 9131",
    "sg:postcode":"90505",
    "sg:province":"CA",
    "sg:tags":[
        "yoga"
    ],
    "sg:website":"www.anandasouthbay.org",
    "wof:name":"Ananda Meditation Center of the South Bay",
    "wof:placetype":"venue"
},
  "geometry": {"coordinates":[-118.352046,33.805358],"type":"Point"}
}