{
  "type": "Feature",
  "properties": {
    "iso:country":"US",
    "sg:address":"5368 Atlantic Ave",
    "sg:city":"Long Beach",
    "sg:classifiers":[
        {
            "category":"Sports & Exercise",
            "subcategory":"Bicycle Rental",
            "type":"Entertainment"
        }
    ],
    "sg:phone":"+1 562 422 3500",
    "sg:postcode":"90805",
    "sg:province":"CA",
    "sg:tags":[
        "wear"
    ],
    "wof:name":"Sky Wear",
    "wof:placetype":"venue"
},
  "geometry": {"coordinates":[-118.18469899999999,33.853744],"type":"Point"}
}