{
  "type": "Feature",
  "properties": {
    "iso:country":"US",
    "sg:address":"656 Santa Rosa St",
    "sg:city":"San Luis Obispo",
    "sg:classifiers":[
        {
            "category":"Banks & Credit Unions",
            "subcategory":"Investment Brokerage",
            "type":"Services"
        }
    ],
    "sg:phone":"+1 805 783 7150",
    "sg:postcode":"93401",
    "sg:province":"CA",
    "sg:tags":[
        "security"
    ],
    "wof:name":"RBC Dain Rauscher",
    "wof:placetype":"venue"
},
  "geometry": {"coordinates":[-120.66246,35.285476],"type":"Point"}
}