{
  "type": "Feature",
  "properties": {
    "iso:country":"US",
    "sg:address":"2551 State St",
    "sg:city":"Carlsbad",
    "sg:classifiers":[
        {
            "category":"Banks & Credit Unions",
            "subcategory":"Bank",
            "type":"Services"
        }
    ],
    "sg:phone":"+1 760 720 4657",
    "sg:postcode":"92008",
    "sg:province":"CA",
    "sg:tags":[
        "loan",
        "real estate"
    ],
    "wof:name":"Mortgage Loan Specialists",
    "wof:placetype":"venue"
},
  "geometry": {"coordinates":[-117.35431,33.165809],"type":"Point"}
}