{
  "type": "Feature",
  "properties": {
    "iso:country":"US",
    "sg:address":"409 Center St",
    "sg:city":"Yuba City",
    "sg:classifiers":[
        {
            "category":"Real Estate",
            "subcategory":"Real Estate Agent",
            "type":"Services"
        }
    ],
    "sg:phone":"+1 530 673 9040",
    "sg:postcode":"95991",
    "sg:province":"CA",
    "sg:tags":[
        "broker"
    ],
    "wof:name":"321 Real Estate Inc",
    "wof:placetype":"venue"
},
  "geometry": {"coordinates":[-121.614941,39.137219],"type":"Point"}
}