{
  "type": "Feature",
  "properties": {
    "addr:full":"1016 Englander St San Pedro CA 90731",
    "addr:housenumber":"1016",
    "addr:postcode":"90731",
    "addr:street":"Englander St",
    "iso:country":"US",
    "sg:address":"1016 Englander St",
    "sg:city":"San Pedro",
    "sg:classifiers":[
        {
            "category":"Manufacturing",
            "subcategory":"Printing",
            "type":"Manufacturing & Wholesale Goods"
        }
    ],
    "sg:phone":"+1 310 832 4896",
    "sg:postcode":"90731",
    "sg:province":"CA",
    "sg:tags":[
        "sport",
        "greeting",
        "card"
    ],
    "wof:name":"Bryan Gaddis Sports Artists",
    "wof:placetype":"venue"
},
  "geometry": {"coordinates":[-118.30254600000001,33.764901],"type":"Point"}
}