{
  "type": "Feature",
  "properties": {
    "iso:country":"US",
    "sg:address":"3691 Township Ave",
    "sg:city":"Simi Valley",
    "sg:classifiers":[
        {
            "category":"Building & Trades",
            "subcategory":"Plumbing",
            "type":"Services"
        }
    ],
    "sg:phone":"+1 805 583 8030",
    "sg:postcode":"93063",
    "sg:province":"CA",
    "sg:tags":[
        "plumbing",
        "contractor"
    ],
    "wof:name":"Barcena Plumbing",
    "wof:placetype":"venue"
},
  "geometry": {"coordinates":[-118.724437,34.293571],"type":"Point"}
}