{
  "type": "Feature",
  "properties": {
    "addr:full":"3691 Township Ave Simi Valley CA 93063",
    "addr:housenumber":"3691",
    "addr:postcode":"93063",
    "addr:street":"Township Ave",
    "iso:country":"US",
    "sg:address":"3691 Township Ave",
    "sg:city":"Simi Valley",
    "sg:classifiers":[
        {
            "category":"Building & Trades",
            "subcategory":"Plumbing",
            "type":"Services"
        }
    ],
    "sg:phone":"+1 805 583 8030",
    "sg:postcode":"93063",
    "sg:province":"CA",
    "sg:tags":[
        "plumbing",
        "contractor"
    ],
    "wof:name":"Barcena Plumbing",
    "wof:placetype":"venue"
},
  "geometry": {"coordinates":[-118.72443699999999,34.293571],"type":"Point"}
}