{
  "type": "Feature",
  "properties": {
    "addr:full":"17643 Sherman Way Van Nuys CA 91406",
    "addr:housenumber":"17643",
    "addr:postcode":"91406",
    "addr:street":"Sherman Way",
    "iso:country":"US",
    "sg:address":"17643 Sherman Way",
    "sg:city":"Van Nuys",
    "sg:classifiers":[
        {
            "category":"Wholesale",
            "subcategory":"Machinery & Supplies",
            "type":"Manufacturing & Wholesale Goods"
        }
    ],
    "sg:phone":"+1 818 881 7137",
    "sg:postcode":"91406",
    "sg:province":"CA",
    "sg:tags":[
        "salon",
        "beauty"
    ],
    "wof:name":"Venus",
    "wof:placetype":"venue"
},
  "geometry": {"coordinates":[-118.51712499999999,34.201093],"type":"Point"}
}