{
  "type": "Feature",
  "properties": {
    "addr:full":"1134 W Donington St Glendora CA 91741",
    "addr:housenumber":"1134",
    "addr:postcode":"91741",
    "addr:street":"W Donington St",
    "iso:country":"US",
    "sg:address":"1134 W Donington St",
    "sg:city":"Glendora",
    "sg:classifiers":[
        {
            "category":"Freight",
            "type":"Transportation"
        }
    ],
    "sg:phone":"+1 626 914 7147",
    "sg:postcode":"91741",
    "sg:province":"CA",
    "sg:tags":[
        "operator",
        "local",
        "trucking"
    ],
    "wof:name":"RE Trucking Inc",
    "wof:placetype":"venue"
},
  "geometry": {"coordinates":[-117.88382799999999,34.144483],"type":"Point"}
}