{
  "type": "Feature",
  "properties": {
    "iso:country":"US",
    "sg:address":"558 Lori Dr",
    "sg:city":"Benicia",
    "sg:classifiers":[
        {
            "category":"Professional",
            "subcategory":"Business Services",
            "type":"Services"
        }
    ],
    "sg:phone":"+1 707 747 5963",
    "sg:postcode":"94510",
    "sg:province":"CA",
    "sg:tags":[
        "consultant",
        "coach"
    ],
    "wof:name":"State Wide Construction Consulting",
    "wof:placetype":"venue"
},
  "geometry": {"coordinates":[-122.162384,38.063322],"type":"Point"}
}