{
  "type": "Feature",
  "properties": {
    "addr:full":"12510 Slauson Ave Santa Fe Springs CA 90670",
    "addr:postcode":"12510;90670",
    "addr:street":"Slauson Ave",
    "iso:country":"US",
    "sg:address":"12510 Slauson Ave",
    "sg:city":"Santa Fe Springs",
    "sg:classifiers":[
        {
            "category":"Manufacturing",
            "subcategory":"Tools & Machinery",
            "type":"Manufacturing & Wholesale Goods"
        }
    ],
    "sg:phone":"+1 562 696 8177",
    "sg:postcode":"90670",
    "sg:province":"CA",
    "sg:tags":[
        "die",
        "maker"
    ],
    "wof:name":"Dieco Inc",
    "wof:placetype":"venue"
},
  "geometry": {"coordinates":[-118.052841,33.960031],"type":"Point"}
}