{
  "type": "Feature",
  "properties": {
    "addr:full":"123 N Lincoln Ave Monterey Park CA 91755",
    "addr:housenumber":"123",
    "addr:postcode":"91755",
    "addr:street":"N Lincoln Ave",
    "iso:country":"US",
    "sg:address":"123 N Lincoln Ave",
    "sg:city":"Monterey Park",
    "sg:classifiers":[
        {
            "category":"Restaurant",
            "type":"Food & Drink"
        }
    ],
    "sg:phone":"+1 626 573 2209",
    "sg:postcode":"91755",
    "sg:province":"CA",
    "wof:name":"Lin's Bakery",
    "wof:placetype":"venue"
},
  "geometry": {"coordinates":[-118.121002,34.0634],"type":"Point"}
}