{
  "type": "Feature",
  "properties": {
    "addr:full":"5646 Mission Blvd Riverside CA 92509",
    "addr:housenumber":"5646",
    "addr:postcode":"92509",
    "addr:street":"Mission Blvd",
    "iso:country":"US",
    "sg:address":"5646 Mission Blvd",
    "sg:city":"Riverside",
    "sg:classifiers":[
        {
            "category":"Shopping",
            "subcategory":"Clothing, Apparel, & Fashions",
            "type":"Retail Goods"
        }
    ],
    "sg:phone":"+1 951 784 6808",
    "sg:postcode":"92509",
    "sg:province":"CA",
    "wof:name":"Lilia",
    "wof:placetype":"venue"
},
  "geometry": {"coordinates":[-117.40835199999999,33.997745],"type":"Point"}
}