{
  "type": "Feature",
  "properties": {
    "iso:country":"US",
    "sg:address":"13091 Harbor Blvd",
    "sg:city":"Garden Grove",
    "sg:classifiers":[
        {
            "category":"Restaurant",
            "type":"Food & Drink"
        }
    ],
    "sg:phone":"+1 714 534 4730",
    "sg:postcode":"92843",
    "sg:province":"CA",
    "wof:name":"Togo's Eatery",
    "wof:placetype":"venue"
},
  "geometry": {"coordinates":[-117.920998,33.7728],"type":"Point"}
}