{
  "type": "Feature",
  "properties": {
    "addr:full":"5451 W 104th St Los Angeles CA 90045",
    "addr:housenumber":"5451",
    "addr:postcode":"90045",
    "addr:street":"W 104Th St",
    "iso:country":"US",
    "sg:address":"5451 W 104th St",
    "sg:city":"Los Angeles",
    "sg:classifiers":[
        {
            "category":"Freight",
            "type":"Transportation"
        }
    ],
    "sg:phone":"+1 310 417 3050",
    "sg:postcode":"90045",
    "sg:province":"CA",
    "sg:tags":[
        "trucking"
    ],
    "wof:name":"Ventura Highway",
    "wof:placetype":"venue"
},
  "geometry": {"coordinates":[-118.373645,33.942043],"type":"Point"}
}