{
  "type": "Feature",
  "properties": {
    "addr:full":"499 14th St Ste 17 Oakland CA 94612",
    "addr:housenumber":"499",
    "addr:postcode":"94612",
    "addr:street":"14Th St Ste 17",
    "iso:country":"US",
    "sg:address":"499 14th St Ste 17",
    "sg:city":"Oakland",
    "sg:classifiers":[
        {
            "category":"Fast Food",
            "type":"Food & Drink"
        },
        {
            "category":"Food & Beverages",
            "subcategory":"Meat & Fish",
            "type":"Retail Goods"
        }
    ],
    "sg:phone":"+1 510 625 1060",
    "sg:postcode":"94612",
    "sg:province":"CA",
    "sg:tags":[
        "hot",
        "dog"
    ],
    "sg:website":"www.topdoghotdogs.com",
    "wof:name":"Top Dog",
    "wof:placetype":"venue"
},
  "geometry": {"coordinates":[-122.272926,37.804292],"type":"Point"}
}