{
  "type": "Feature",
  "properties": {
    "iso:country":"US",
    "sg:address":"3287 F St",
    "sg:city":"San Diego",
    "sg:classifiers":[
        {
            "category":"Autos & Motor Vehicles",
            "subcategory":"Automobile Sales",
            "type":"Retail Goods"
        }
    ],
    "sg:phone":"+1 619 238 1977",
    "sg:postcode":"92102",
    "sg:province":"CA",
    "sg:tags":[
        "classic"
    ],
    "wof:name":"Motoring Investments",
    "wof:placetype":"venue"
},
  "geometry": {"coordinates":[-117.123998,32.713718],"type":"Point"}
}