{
  "type": "Feature",
  "properties": {
    "addr:full":"3625 Placentia Ct Chino CA 91710",
    "addr:housenumber":"3625",
    "addr:postcode":"91710",
    "addr:street":"Placentia Ct",
    "iso:country":"US",
    "sg:address":"3625 Placentia Ct",
    "sg:city":"Chino",
    "sg:classifiers":[
        {
            "category":"Wholesale",
            "subcategory":"Groceries",
            "type":"Manufacturing & Wholesale Goods"
        }
    ],
    "sg:phone":"+1 909 902 1997",
    "sg:postcode":"91710",
    "sg:province":"CA",
    "sg:tags":[
        "food",
        "product"
    ],
    "wof:name":"A A Foods Inc",
    "wof:placetype":"venue"
},
  "geometry": {"coordinates":[-117.72627900000001,34.023148],"type":"Point"}
}