{
  "type": "Feature",
  "properties": {
    "addr:full":"27922 Via Crespi Laguna Niguel CA 92677",
    "addr:housenumber":"27922",
    "addr:postcode":"92677",
    "addr:street":"Via Crespi",
    "iso:country":"US",
    "sg:address":"27922 Via Crespi",
    "sg:city":"Laguna Niguel",
    "sg:classifiers":[
        {
            "category":"Building & Trades",
            "subcategory":"Cleaning & Sanitation",
            "type":"Services"
        }
    ],
    "sg:phone":"+1 949 362 5388",
    "sg:postcode":"92677",
    "sg:province":"CA",
    "sg:tags":[
        "carpet"
    ],
    "wof:name":"Jarvis Bros Emergency Water Damage",
    "wof:placetype":"venue"
},
  "geometry": {"coordinates":[-117.690506,33.557621],"type":"Point"}
}