{
  "type": "Feature",
  "properties": {
    "addr:full":"2 Highgate Rd Kensington CA 94707",
    "addr:housenumber":"2",
    "addr:postcode":"94707",
    "addr:street":"Highgate Rd",
    "iso:country":"US",
    "sg:address":"2 Highgate Rd",
    "sg:city":"Kensington",
    "sg:classifiers":[
        {
            "category":"Real Estate",
            "subcategory":"Real Estate Agent",
            "type":"Services"
        }
    ],
    "sg:phone":"+1 510 525 7153",
    "sg:postcode":"94707",
    "sg:province":"CA",
    "wof:name":"Ruby By Properties",
    "wof:placetype":"venue"
},
  "geometry": {"coordinates":[-122.288353,37.915272],"type":"Point"}
}