{
  "type": "Feature",
  "properties": {
    "iso:country":"US",
    "sg:address":"2189 Jackson Ave",
    "sg:city":"Escalon",
    "sg:classifiers":[
        {
            "category":"Shopping",
            "subcategory":"Antiques",
            "type":"Retail Goods"
        }
    ],
    "sg:phone":"+1 209 838 1933",
    "sg:postcode":"95320",
    "sg:province":"CA",
    "wof:name":"Country Cottage",
    "wof:placetype":"venue"
},
  "geometry": {"coordinates":[-120.986062,37.79424],"type":"Point"}
}