{
  "type": "Feature",
  "properties": {
    "addr:full":"15510 Hawley Pl El Cajon CA 92021",
    "addr:housenumber":"15510",
    "addr:postcode":"92021",
    "addr:street":"Hawley Pl",
    "iso:country":"US",
    "sg:address":"15510 Hawley Pl",
    "sg:city":"El Cajon",
    "sg:classifiers":[
        {
            "category":"Arts & Performance",
            "subcategory":"Theater",
            "type":"Entertainment"
        }
    ],
    "sg:phone":"+1 619 561 5748",
    "sg:postcode":"92021",
    "sg:province":"CA",
    "sg:tags":[
        "live",
        "music"
    ],
    "wof:name":"Bob Tooley's Music Machine",
    "wof:placetype":"venue"
},
  "geometry": {"coordinates":[-116.834722,32.862475],"type":"Point"}
}