{
  "type": "Feature",
  "properties": {
    "addr:full":"19800 MacArthur Blvd Ste 800 Irvine CA 92612",
    "addr:housenumber":"19800",
    "addr:postcode":"92612",
    "addr:street":"Macarthur Blvd Ste 800",
    "iso:country":"US",
    "sg:address":"19800 MacArthur Blvd Ste 800",
    "sg:city":"Irvine",
    "sg:classifiers":[
        {
            "category":"Professional",
            "subcategory":"Lawyer & Legal Services",
            "type":"Services"
        }
    ],
    "sg:phone":"+1 949 757 2800",
    "sg:postcode":"92612",
    "sg:province":"CA",
    "wof:name":"Barger & Wolen",
    "wof:placetype":"venue"
},
  "geometry": {"coordinates":[-117.860001,33.652199],"type":"Point"}
}