{
  "type": "Feature",
  "properties": {
    "addr:full":"3434 Chatwin Ave Long Beach CA 90808",
    "addr:housenumber":"3434",
    "addr:postcode":"90808",
    "addr:street":"Chatwin Ave",
    "iso:country":"US",
    "sg:address":"3434 Chatwin Ave",
    "sg:city":"Long Beach",
    "sg:classifiers":[
        {
            "category":"Shopping",
            "subcategory":"Pets & Pet Supplies",
            "type":"Retail Goods"
        },
        {
            "category":"Education",
            "subcategory":"School",
            "type":"Public Place"
        }
    ],
    "sg:postcode":"90808",
    "sg:province":"CA",
    "sg:website":"tortoise.org/ttcs",
    "wof:name":"California Turtle and Tortoise Club",
    "wof:placetype":"venue"
},
  "geometry": {"coordinates":[-118.12268400000001,33.819945],"type":"Point"}
}