{
  "type": "Feature",
  "properties": {
    "addr:full":"2214 U St Sacramento CA 95818",
    "addr:housenumber":"2214",
    "addr:postcode":"95818",
    "addr:street":"U St",
    "iso:country":"US",
    "sg:address":"2214 U St",
    "sg:city":"Sacramento",
    "sg:classifiers":[
        {
            "category":"Banks & Credit Unions",
            "subcategory":"Atm",
            "type":"Services"
        }
    ],
    "sg:phone":"+1 916 442 6200",
    "sg:postcode":"95818",
    "sg:province":"CA",
    "sg:tags":[
        "bankruptcy"
    ],
    "wof:name":"Rossi Bret R",
    "wof:placetype":"venue"
},
  "geometry": {"coordinates":[-121.48200199999999,38.563702],"type":"Point"}
}