{
  "type": "Feature",
  "properties": {
    "addr:full":"2001 Market St Redding CA 96001",
    "addr:housenumber":"2001",
    "addr:postcode":"96001",
    "addr:street":"Market St",
    "iso:country":"US",
    "sg:address":"2001 Market St",
    "sg:city":"Redding",
    "sg:classifiers":[
        {
            "category":"Utilities",
            "subcategory":"Telephone",
            "type":"Services"
        },
        {
            "category":"Professional",
            "subcategory":"Computer Services",
            "type":"Services"
        }
    ],
    "sg:phone":"+1 530 241 3131",
    "sg:postcode":"96001",
    "sg:province":"CA",
    "sg:tags":[
        "wholesale",
        "software",
        "network",
        "internet"
    ],
    "sg:website":"www.compulog.com",
    "wof:name":"Computer Logistics Corp",
    "wof:placetype":"venue"
},
  "geometry": {"coordinates":[-122.38843199999999,40.578817],"type":"Point"}
}