{
  "type": "Feature",
  "properties": {
    "iso:country":"US",
    "sg:address":"237 E Port Hueneme Rd",
    "sg:city":"Port Hueneme",
    "sg:classifiers":[
        {
            "category":"Professional",
            "type":"Services"
        }
    ],
    "sg:phone":"+1 805 488 6658",
    "sg:postcode":"93041",
    "sg:province":"CA",
    "sg:tags":[
        "establishment"
    ],
    "wof:name":"Umina Brothers Inc",
    "wof:placetype":"venue"
},
  "geometry": {"coordinates":[-119.198972,34.147806],"type":"Point"}
}