{
  "type": "Feature",
  "properties": {
    "iso:country":"US",
    "sg:address":"2811 College Avenue",
    "sg:city":"Berkeley",
    "sg:classifiers":[
        {
            "category":"Health Services",
            "subcategory":"Clinic",
            "type":"Services"
        }
    ],
    "sg:phone":"+1 510 549 9297",
    "sg:postcode":"94705",
    "sg:province":"CA",
    "sg:tags":[
        "counseling",
        "mental"
    ],
    "wof:name":"Sheets Sheryl Mfcc",
    "wof:placetype":"venue"
},
  "geometry": {"coordinates":[-122.25299800000001,37.859699],"type":"Point"}
}