{
  "type": "Feature",
  "properties": {
    "addr:full":"314 S Soto St Los Angeles CA 90033",
    "addr:housenumber":"314",
    "addr:postcode":"90033",
    "addr:street":"S Soto St",
    "iso:country":"US",
    "sg:address":"314 S Soto St",
    "sg:city":"Los Angeles",
    "sg:classifiers":[
        {
            "category":"Building & Trades",
            "subcategory":"Electrical",
            "type":"Services"
        }
    ],
    "sg:phone":"+1 323 262 5670",
    "sg:postcode":"90033",
    "sg:province":"CA",
    "sg:tags":[
        "repair",
        "stereo",
        "installation",
        "radio",
        "contractor"
    ],
    "sg:website":"www.californiainstalls.com",
    "wof:name":"Calif Installs",
    "wof:placetype":"venue"
},
  "geometry": {"coordinates":[-118.21199799999999,34.040901],"type":"Point"}
}