{
  "type": "Feature",
  "properties": {
    "addr:full":"7219 Canby Ave Reseda CA 91335",
    "addr:housenumber":"7219",
    "addr:postcode":"91335",
    "addr:street":"Canby Ave",
    "iso:country":"US",
    "sg:address":"7219 Canby Ave",
    "sg:city":"Reseda",
    "sg:classifiers":[
        {
            "category":"Wholesale",
            "subcategory":"Durable Goods & Equipment",
            "type":"Manufacturing & Wholesale Goods"
        }
    ],
    "sg:phone":"+1 818 343 1508",
    "sg:postcode":"91335",
    "sg:province":"CA",
    "sg:tags":[
        "importer"
    ],
    "wof:name":"CBS",
    "wof:placetype":"venue"
},
  "geometry": {"coordinates":[-118.534835,34.202714],"type":"Point"}
}