{
  "type": "Feature",
  "properties": {
    "addr:full":"24415 Hawthorne Blvd Torrance CA 90505",
    "addr:housenumber":"24415",
    "addr:postcode":"90505",
    "addr:street":"Hawthorne Blvd",
    "iso:country":"US",
    "sg:address":"24415 Hawthorne Blvd",
    "sg:city":"Torrance",
    "sg:classifiers":[
        {
            "category":"Building & Trades",
            "subcategory":"Cleaning & Sanitation",
            "type":"Services"
        },
        {
            "category":"Home & Garden",
            "subcategory":"Carpets & Floor Coverings",
            "type":"Retail Goods"
        }
    ],
    "sg:phone":"+1 310 373 7373",
    "sg:postcode":"90505",
    "sg:province":"CA",
    "sg:tags":[
        "carpeting"
    ],
    "wof:name":"Southbays Art Oriental Rug Co",
    "wof:placetype":"venue"
},
  "geometry": {"coordinates":[-118.350998,33.800598],"type":"Point"}
}