{
  "type": "Feature",
  "properties": {
    "iso:country":"US",
    "sg:address":"28545 Old Town Front St",
    "sg:city":"Temecula",
    "sg:classifiers":[
        {
            "category":"Building & Trades",
            "subcategory":"Construction",
            "type":"Services"
        }
    ],
    "sg:phone":"+1 951 695 2800",
    "sg:postcode":"92590",
    "sg:province":"CA",
    "sg:tags":[
        "industrial",
        "contractors-commercial"
    ],
    "wof:name":"Varela, Cristy",
    "wof:placetype":"venue"
},
  "geometry": {"coordinates":[-117.15012400000001,33.494474],"type":"Point"}
}