{
  "type": "Feature",
  "properties": {
    "addr:full":"1464 Spear Ave Arcata CA 95521",
    "addr:housenumber":"1464",
    "addr:postcode":"95521",
    "addr:street":"Spear Ave",
    "iso:country":"US",
    "sg:address":"1464 Spear Ave",
    "sg:city":"Arcata",
    "sg:classifiers":[
        {
            "category":"Education",
            "subcategory":"School",
            "type":"Public Place"
        }
    ],
    "sg:phone":"+1 707 822 0351",
    "sg:postcode":"95521",
    "sg:province":"CA",
    "sg:tags":[
        "elementary",
        "private"
    ],
    "wof:name":"Trillium Elementary School",
    "wof:placetype":"venue"
},
  "geometry": {"coordinates":[-124.08280000000001,40.889172],"type":"Point"}
}