{
  "type": "Feature",
  "properties": {
    "addr:full":"6135 Graham Hill Rd Felton CA 95018",
    "addr:housenumber":"6135",
    "addr:postcode":"95018",
    "addr:street":"Graham Hill Rd",
    "iso:country":"US",
    "sg:address":"6135 Graham Hill Rd",
    "sg:city":"Felton",
    "sg:classifiers":[
        {
            "category":"Retail",
            "subcategory":"Self-service Laundry",
            "type":"Services"
        }
    ],
    "sg:phone":"+1 831 335 9951",
    "sg:postcode":"95018",
    "sg:province":"CA",
    "wof:name":"Felton Grove Laundry",
    "wof:placetype":"venue"
},
  "geometry": {"coordinates":[-122.068241,37.051159],"type":"Point"}
}