{
  "type": "Feature",
  "properties": {
    "iso:country":"US",
    "sg:address":"2017 Dickens Dr",
    "sg:city":"Modesto",
    "sg:classifiers":[
        {
            "category":"Food & Beverages",
            "subcategory":"Candy",
            "type":"Retail Goods"
        }
    ],
    "sg:phone":"+1 209 523 1818",
    "sg:postcode":"95350",
    "sg:province":"CA",
    "sg:tags":[
        "confectionery"
    ],
    "wof:name":"Beckles Candies & Gifts",
    "wof:placetype":"venue"
},
  "geometry": {"coordinates":[-121.02967599999999,37.674572],"type":"Point"}
}