{
  "type": "Feature",
  "properties": {
    "addr:full":"4461 el Dorado Rd El Dorado CA 95623",
    "addr:housenumber":"4461",
    "addr:postcode":"95623",
    "addr:street":"El Dorado Rd",
    "iso:country":"US",
    "sg:address":"4461 el Dorado Rd",
    "sg:city":"El Dorado",
    "sg:classifiers":[
        {
            "category":"Retail",
            "subcategory":"Car Wash",
            "type":"Services"
        }
    ],
    "sg:phone":"+1 530 622 9599",
    "sg:postcode":"95623",
    "sg:province":"CA",
    "sg:tags":[
        "automobile",
        "detail",
        "clean"
    ],
    "wof:name":"A 1 Auto Detailing Specialists",
    "wof:placetype":"venue"
},
  "geometry": {"coordinates":[-120.860007,38.691621],"type":"Point"}
}