{
  "type": "Feature",
  "properties": {
    "addr:full":"1070 Happy Valley Rd Santa Cruz CA 95065",
    "addr:housenumber":"1070",
    "addr:postcode":"95065",
    "addr:street":"Happy Valley Rd",
    "iso:country":"US",
    "sg:address":"1070 Happy Valley Rd",
    "sg:city":"Santa Cruz",
    "sg:classifiers":[
        {
            "category":"Farming",
            "subcategory":"Orchard",
            "type":"Manufacturing & Wholesale Goods"
        }
    ],
    "sg:phone":"+1 831 427 3662",
    "sg:postcode":"95065",
    "sg:province":"CA",
    "sg:tags":[
        "apple"
    ],
    "wof:name":"Denevan Apples",
    "wof:placetype":"venue"
},
  "geometry": {"coordinates":[-121.980188,37.036138],"type":"Point"}
}