{
  "type": "Feature",
  "properties": {
    "addr:full":"44435 Sierra Hwy Lancaster CA 93534",
    "addr:housenumber":"44435",
    "addr:postcode":"93534",
    "addr:street":"Sierra Hwy",
    "iso:country":"US",
    "sg:address":"44435 Sierra Hwy",
    "sg:city":"Lancaster",
    "sg:classifiers":[
        {
            "category":"Home & Garden",
            "subcategory":"Garden Supply",
            "type":"Retail Goods"
        }
    ],
    "sg:phone":"+1 661 942 1826",
    "sg:postcode":"93534",
    "sg:province":"CA",
    "sg:tags":[
        "lawn",
        "mower"
    ],
    "wof:name":"Sierra Mower & Chain Saw Ctr",
    "wof:placetype":"venue"
},
  "geometry": {"coordinates":[-118.135673,34.689921],"type":"Point"}
}