{
  "type": "Feature",
  "properties": {
    "iso:country":"US",
    "sg:address":"1126 Vallecito Rd",
    "sg:city":"Carpinteria",
    "sg:classifiers":[
        {
            "category":"Building & Trades",
            "subcategory":"Plumbing",
            "type":"Services"
        }
    ],
    "sg:phone":"+1 805 684 2474",
    "sg:postcode":"93013",
    "sg:province":"CA",
    "sg:tags":[
        "plumber",
        "industrial",
        "contractors-commercial"
    ],
    "wof:name":"Coastline Plumbing",
    "wof:placetype":"venue"
},
  "geometry": {"coordinates":[-119.514465,34.398268],"type":"Point"}
}