{
  "type": "Feature",
  "properties": {
    "addr:full":"3417 El Camino Avenue Sacramento CA 95821",
    "addr:housenumber":"3417",
    "addr:postcode":"95821",
    "addr:street":"El Camino Avenue",
    "iso:country":"US",
    "sg:address":"3417 El Camino Avenue",
    "sg:city":"Sacramento",
    "sg:classifiers":[
        {
            "category":"Restaurant",
            "type":"Food & Drink"
        }
    ],
    "sg:phone":"+1 916 971 3033",
    "sg:postcode":"95821",
    "sg:province":"CA",
    "sg:tags":[
        "pizza"
    ],
    "wof:name":"Dominos Pizza",
    "wof:placetype":"venue"
},
  "geometry": {"coordinates":[-121.384325,38.610599],"type":"Point"}
}