{
  "type": "Feature",
  "properties": {
    "addr:full":"7967 Beverly Boulevard Los Angeles CA 90048",
    "addr:housenumber":"7967",
    "addr:postcode":"90048",
    "addr:street":"Beverly Boulevard",
    "iso:country":"US",
    "sg:address":"7967 Beverly Boulevard",
    "sg:city":"Los Angeles",
    "sg:classifiers":[
        {
            "category":"Place Of Worship",
            "subcategory":"Synagogue",
            "type":"Public Place"
        }
    ],
    "sg:phone":"+1 323 651 3594",
    "sg:postcode":"90048",
    "sg:province":"CA",
    "wof:name":"Congregation Ohel David",
    "wof:placetype":"venue"
},
  "geometry": {"coordinates":[-118.36349800000001,34.075991],"type":"Point"}
}