{
  "type": "Feature",
  "properties": {
    "addr:full":"1520 Tennessee St Vallejo CA 94590",
    "addr:housenumber":"1520",
    "addr:postcode":"94590",
    "addr:street":"Tennessee St",
    "iso:country":"US",
    "sg:address":"1520 Tennessee St",
    "sg:city":"Vallejo",
    "sg:classifiers":[
        {
            "category":"Professional",
            "subcategory":"Lawyer & Legal Services",
            "type":"Services"
        }
    ],
    "sg:phone":"+1 707 644 4191",
    "sg:postcode":"94590",
    "sg:province":"CA",
    "sg:tags":[
        "attorney",
        "practice"
    ],
    "wof:name":"Gianola, Chas M",
    "wof:placetype":"venue"
},
  "geometry": {"coordinates":[-122.239484,38.109776],"type":"Point"}
}