{
  "type": "Feature",
  "properties": {
    "iso:country":"US",
    "sg:address":"1260 E Main St",
    "sg:city":"Barstow",
    "sg:classifiers":[
        {
            "category":"Shopping",
            "subcategory":"Department Store",
            "type":"Retail Goods"
        },
        {
            "category":"Shopping",
            "type":"Retail Goods"
        },
        {
            "category":"Shopping",
            "subcategory":"Discount & Variety Stores",
            "type":"Retail Goods"
        }
    ],
    "sg:phone":"+1 760 256 2870",
    "sg:postcode":"92311",
    "sg:province":"CA",
    "sg:tags":[
        "merchandise"
    ],
    "sg:website":"http://www.dollartree.com/",
    "wof:name":"Dollar Tree",
    "wof:placetype":"venue"
},
  "geometry": {"coordinates":[-117.00845200000001,34.896964],"type":"Point"}
}