{
  "type": "Feature",
  "properties": {
    "iso:country":"US",
    "sg:address":"3475 E Oleander Dr",
    "sg:city":"Highland",
    "sg:classifiers":[
        {
            "category":"Professional",
            "subcategory":"Engineering",
            "type":"Services"
        }
    ],
    "sg:phone":"+1 909 862 0216",
    "sg:postcode":"92346",
    "sg:province":"CA",
    "sg:tags":[
        "engineer"
    ],
    "wof:name":"L Curtis Vann Consulting",
    "wof:placetype":"venue"
},
  "geometry": {"coordinates":[-117.211423,34.141126],"type":"Point"}
}