{
  "type": "Feature",
  "properties": {
    "addr:full":"1620 W El Camino Ave Sacramento CA 95833",
    "addr:housenumber":"1620",
    "addr:postcode":"95833",
    "addr:street":"W El Camino Ave",
    "iso:country":"US",
    "sg:address":"1620 W El Camino Ave",
    "sg:city":"Sacramento",
    "sg:classifiers":[
        {
            "category":"Retail",
            "subcategory":"Laundry & Dry Cleaning",
            "type":"Services"
        }
    ],
    "sg:phone":"+1 916 920 5200",
    "sg:postcode":"95833",
    "sg:province":"CA",
    "sg:website":"www.swansonscleaners.com",
    "wof:name":"Swansons Cleaners",
    "wof:placetype":"venue"
},
  "geometry": {"coordinates":[-121.498001,38.612701],"type":"Point"}
}