{
  "type": "Feature",
  "properties": {
    "iso:country":"US",
    "sg:address":"265 Tom Bell Dr",
    "sg:city":"Murphys",
    "sg:classifiers":[
        {
            "category":"Shopping",
            "type":"Retail Goods"
        }
    ],
    "sg:phone":"+1 209 728 2955",
    "sg:postcode":"95247",
    "sg:province":"CA",
    "sg:tags":[
        "picture",
        "frame"
    ],
    "wof:name":"Diane's Frameplace",
    "wof:placetype":"venue"
},
  "geometry": {"coordinates":[-120.454947,38.138624],"type":"Point"}
}