{
  "type": "Feature",
  "properties": {
    "iso:country":"US",
    "sg:address":"9805 Campo Rd 180",
    "sg:city":"Spring Valley",
    "sg:classifiers":[
        {
            "category":"Education",
            "subcategory":"Library",
            "type":"Public Place"
        }
    ],
    "sg:phone":"+1 619 463 3236",
    "sg:postcode":"91977",
    "sg:province":"CA",
    "sg:website":"sdcl.org/locations_CS.html",
    "wof:name":"San Diego County Library - Casa de Oro branch",
    "wof:placetype":"venue"
},
  "geometry": {"coordinates":[-116.986295,32.747158],"type":"Point"}
}