{
  "type": "Feature",
  "properties": {
    "iso:country":"US",
    "sg:address":"301 E Ocean Blvd Ste 2010",
    "sg:city":"Long Beach",
    "sg:classifiers":[
        {
            "category":"Shopping",
            "subcategory":"Mobile Phones",
            "type":"Retail Goods"
        }
    ],
    "sg:phone":"+1 562 624 5101",
    "sg:postcode":"90802",
    "sg:province":"CA",
    "sg:website":"sprint.com",
    "wof:name":"Sprint",
    "wof:placetype":"venue"
},
  "geometry": {"coordinates":[-118.189302,33.767076],"type":"Point"}
}