{
  "type": "Feature",
  "properties": {
    "addr:full":"3027 Polk Ave San Diego CA 92104",
    "addr:housenumber":"3027",
    "addr:postcode":"92104",
    "addr:street":"Polk Ave",
    "iso:country":"US",
    "sg:address":"3027 Polk Ave",
    "sg:city":"San Diego",
    "sg:classifiers":[
        {
            "category":"Wholesale",
            "subcategory":"Medical Equipment & Supplies",
            "type":"Manufacturing & Wholesale Goods"
        }
    ],
    "sg:phone":"+1 619 521 1045",
    "sg:postcode":"92104",
    "sg:province":"CA",
    "wof:name":"Sure Quality Products",
    "wof:placetype":"venue"
},
  "geometry": {"coordinates":[-117.12896600000001,32.752137],"type":"Point"}
}