{
  "type": "Feature",
  "properties": {
    "iso:country":"US",
    "sg:address":"3027 Polk Ave",
    "sg:city":"San Diego",
    "sg:classifiers":[
        {
            "category":"Wholesale",
            "subcategory":"Medical Equipment & Supplies",
            "type":"Manufacturing & Wholesale Goods"
        }
    ],
    "sg:phone":"+1 619 521 1045",
    "sg:postcode":"92104",
    "sg:province":"CA",
    "wof:name":"Sure Quality Products",
    "wof:placetype":"venue"
},
  "geometry": {"coordinates":[-117.128966,32.752137],"type":"Point"}
}