{
  "type": "Feature",
  "properties": {
    "addr:full":"1055 Mission Ct Fremont CA 94539",
    "addr:housenumber":"1055",
    "addr:postcode":"94539",
    "addr:street":"Mission Ct",
    "iso:country":"US",
    "sg:address":"1055 Mission Ct",
    "sg:city":"Fremont",
    "sg:classifiers":[
        {
            "category":"Manufacturing",
            "subcategory":"Tools & Machinery",
            "type":"Manufacturing & Wholesale Goods"
        }
    ],
    "sg:phone":"+1 510 661 6000",
    "sg:postcode":"94539",
    "sg:province":"CA",
    "sg:tags":[
        "devices",
        "mfg"
    ],
    "wof:name":"G E Novasensor Inc",
    "wof:placetype":"venue"
},
  "geometry": {"coordinates":[-121.930223,37.490791],"type":"Point"}
}