{
  "type": "Feature",
  "properties": {
    "addr:full":"5942 Edinger Ave Huntington Beach CA 92649",
    "addr:housenumber":"5942",
    "addr:postcode":"92649",
    "addr:street":"Edinger Ave",
    "iso:country":"US",
    "sg:address":"5942 Edinger Ave",
    "sg:city":"Huntington Beach",
    "sg:classifiers":[
        {
            "category":"Shopping",
            "subcategory":"Jewelry",
            "type":"Retail Goods"
        }
    ],
    "sg:phone":"+1 714 840 5558",
    "sg:postcode":"92649",
    "sg:province":"CA",
    "wof:name":"Noal Jewelry Designs",
    "wof:placetype":"venue"
},
  "geometry": {"coordinates":[-118.024857,33.72991],"type":"Point"}
}