{
  "type": "Feature",
  "properties": {
    "iso:country":"US",
    "sg:address":"4376 Rustica Cir",
    "sg:city":"Fremont",
    "sg:classifiers":[
        {
            "category":"Freight",
            "type":"Transportation"
        }
    ],
    "sg:phone":"+1 510 693 8696",
    "sg:postcode":"94536",
    "sg:province":"CA",
    "wof:name":"Hwa-Chun Line Inc",
    "wof:placetype":"venue"
},
  "geometry": {"coordinates":[-122.010019,37.553527],"type":"Point"}
}