{
  "type": "Feature",
  "properties": {
    "addr:full":"140 S Willow St Blythe CA 92225",
    "addr:housenumber":"140",
    "addr:postcode":"92225",
    "addr:street":"S Willow St",
    "iso:country":"US",
    "sg:address":"140 S Willow St",
    "sg:city":"Blythe",
    "sg:classifiers":[
        {
            "category":"Place Of Worship",
            "subcategory":"Church",
            "type":"Public Place"
        },
        {
            "category":"Place Of Worship",
            "type":"Public Place"
        },
        {
            "category":"Organizations",
            "subcategory":"Religious Organization",
            "type":"Services"
        }
    ],
    "sg:phone":"+1 760 922 2301",
    "sg:postcode":"92225",
    "sg:province":"CA",
    "sg:tags":[
        "god",
        "god-independent",
        "churches-assemblies"
    ],
    "wof:name":"Blythe First Assembly Of God",
    "wof:placetype":"venue"
},
  "geometry": {"coordinates":[-114.604373,33.609424],"type":"Point"}
}