{
  "type": "Feature",
  "properties": {
    "addr:full":"1872 Shore Rd Hollister CA 95023",
    "addr:housenumber":"1872",
    "addr:postcode":"hollister ca 95023",
    "addr:street":"Shore Rd",
    "iso:country":"US",
    "sg:address":"1872 Shore Rd",
    "sg:city":"Hollister",
    "sg:classifiers":[
        {
            "category":"Building & Trades",
            "subcategory":"Construction",
            "type":"Services"
        }
    ],
    "sg:phone":"+1 831 637 0109",
    "sg:postcode":"95023",
    "sg:province":"CA",
    "sg:tags":[
        "contractor"
    ],
    "wof:name":"Chet Hastings",
    "wof:placetype":"venue"
},
  "geometry": {"coordinates":[-121.440243,36.942278],"type":"Point"}
}