{
  "type": "Feature",
  "properties": {
    "iso:country":"US",
    "sg:address":"318 Lincoln Blvd",
    "sg:city":"Venice",
    "sg:classifiers":[
        {
            "category":"Arts & Performance",
            "subcategory":"Theater",
            "type":"Entertainment"
        }
    ],
    "sg:phone":"+1 310 452 7870",
    "sg:postcode":"90291",
    "sg:province":"CA",
    "sg:tags":[
        "building",
        "group",
        "nonresidential"
    ],
    "wof:name":"Rose Alley Theater",
    "wof:placetype":"venue"
},
  "geometry": {"coordinates":[-118.466665,34.000851],"type":"Point"}
}