{
  "type": "Feature",
  "properties": {
    "addr:full":"1161 High St Auburn CA 95603",
    "addr:housenumber":"1161",
    "addr:postcode":"ca 95603",
    "addr:street":"High St",
    "iso:country":"US",
    "sg:address":"1161 High St",
    "sg:city":"Auburn",
    "sg:classifiers":[
        {
            "category":"Professional",
            "subcategory":"Engineering",
            "type":"Services"
        }
    ],
    "sg:phone":"+1 530 823 8420",
    "sg:postcode":"95603",
    "sg:province":"CA",
    "sg:tags":[
        "engineer"
    ],
    "sg:website":"www.randbengineering.com",
    "wof:name":"R & B Engineering Inc",
    "wof:placetype":"venue"
},
  "geometry": {"coordinates":[-121.07195,38.896654],"type":"Point"}
}