{
  "type": "Feature",
  "properties": {
    "addr:full":"6101 Centinela Ave Ste 350 Culver City CA 90230",
    "addr:housenumber":"6101",
    "addr:postcode":"90230",
    "addr:street":"Centinela Ave Ste 350",
    "iso:country":"US",
    "sg:address":"6101 Centinela Ave Ste 350",
    "sg:city":"Culver City",
    "sg:classifiers":[
        {
            "category":"Community Center",
            "type":"Public Place"
        }
    ],
    "sg:phone":"+1 310 568 1500",
    "sg:postcode":"90230",
    "sg:province":"CA",
    "sg:tags":[
        "medical"
    ],
    "sg:website":"performancemedicalcenters.com",
    "wof:name":"Ultimate Performance Medical Center",
    "wof:placetype":"venue"
},
  "geometry": {"coordinates":[-118.395554,33.981887],"type":"Point"}
}