{
  "type": "Feature",
  "properties": {
    "iso:country":"US",
    "sg:address":"4504 Yankee Hill Ct",
    "sg:city":"Rocklin",
    "sg:classifiers":[
        {
            "category":"Retail",
            "subcategory":"Repair Shop",
            "type":"Services"
        }
    ],
    "sg:phone":"+1 530 885 8872",
    "sg:postcode":"95677",
    "sg:province":"CA",
    "sg:tags":[
        "grease",
        "trap"
    ],
    "wof:name":"Chuck's & Auburn Septic Svc",
    "wof:placetype":"venue"
},
  "geometry": {"coordinates":[-121.228956,38.799786],"type":"Point"}
}