{
  "type": "Feature",
  "properties": {
    "addr:full":"9691 Murphy Rd Stockton CA 95215",
    "addr:housenumber":"9691",
    "addr:postcode":"95215",
    "addr:street":"Murphy Rd",
    "iso:country":"US",
    "sg:address":"9691 Murphy Rd",
    "sg:city":"Stockton",
    "sg:classifiers":[
        {
            "category":"Farming",
            "subcategory":"Vineyard",
            "type":"Manufacturing & Wholesale Goods"
        }
    ],
    "sg:phone":"+1 209 599 3990",
    "sg:postcode":"95215",
    "sg:province":"CA",
    "wof:name":"Vineyard Properties",
    "wof:placetype":"venue"
},
  "geometry": {"coordinates":[-121.110333,37.886907],"type":"Point"}
}