{
  "type": "Feature",
  "properties": {
    "addr:full":"2832 San Bruno Avenue San Francisco CA 94134",
    "addr:housenumber":"2832",
    "addr:postcode":"94134",
    "addr:street":"San Bruno Avenue",
    "iso:country":"US",
    "sg:address":"2832 San Bruno Avenue",
    "sg:city":"San Francisco",
    "sg:classifiers":[
        {
            "category":"Personal",
            "subcategory":"Nail Salon",
            "type":"Services"
        }
    ],
    "sg:phone":"+1 415 656 1146",
    "sg:postcode":"94134",
    "sg:province":"CA",
    "wof:name":"San Bruno Nails",
    "wof:placetype":"venue"
},
  "geometry": {"coordinates":[-122.40300000000001,37.725899],"type":"Point"}
}