{
  "type": "Feature",
  "properties": {
    "addr:full":"1202 W Broadway St Needles CA 92363",
    "addr:housenumber":"1202",
    "addr:postcode":"92363",
    "addr:street":"W Broadway St",
    "iso:country":"US",
    "sg:address":"1202 W Broadway St",
    "sg:city":"Needles",
    "sg:classifiers":[
        {
            "category":"Shopping",
            "subcategory":"Gifts & Souvenirs",
            "type":"Retail Goods"
        }
    ],
    "sg:phone":"+1 760 326 1244",
    "sg:postcode":"92363",
    "sg:province":"CA",
    "sg:tags":[
        "shop"
    ],
    "wof:name":"Arch Mart",
    "wof:placetype":"venue"
},
  "geometry": {"coordinates":[-114.60989499999999,34.841345],"type":"Point"}
}