{
  "type": "Feature",
  "properties": {
    "iso:country":"US",
    "sg:address":"27742 Vis del Lago",
    "sg:city":"Mission Viejo",
    "sg:classifiers":[
        {
            "category":"Real Estate",
            "subcategory":"Real Estate Agent",
            "type":"Services"
        }
    ],
    "sg:phone":"+1 949 837 5700",
    "sg:postcode":"92692",
    "sg:province":"CA",
    "sg:website":"www.coldwellbanker.com",
    "wof:name":"Coldwell Banker",
    "wof:placetype":"venue"
},
  "geometry": {"coordinates":[-117.649367,33.634847],"type":"Point"}
}