{
  "type": "Feature",
  "properties": {
    "iso:country":"US",
    "sg:address":"5870 Monterey Rd",
    "sg:city":"Gilroy",
    "sg:classifiers":[
        {
            "category":"Retail",
            "subcategory":"Car Wash",
            "type":"Services"
        }
    ],
    "sg:phone":"+1 408 846 0660",
    "sg:postcode":"95020",
    "sg:province":"CA",
    "sg:tags":[
        "truck",
        "cleaning"
    ],
    "wof:name":"Precision Wash Inc",
    "wof:placetype":"venue"
},
  "geometry": {"coordinates":[-121.562225,36.992582],"type":"Point"}
}