{
  "type": "Feature",
  "properties": {
    "addr:full":"3896 Bayside Walk San Diego CA 92109",
    "addr:housenumber":"3896",
    "addr:postcode":"92109",
    "addr:street":"Bayside Walk",
    "iso:country":"US",
    "sg:address":"3896 Bayside Walk",
    "sg:city":"San Diego",
    "sg:classifiers":[
        {
            "category":"Building & Trades",
            "subcategory":"Construction",
            "type":"Services"
        }
    ],
    "sg:phone":"+1 858 488 3887",
    "sg:postcode":"92109",
    "sg:province":"CA",
    "sg:tags":[
        "residential"
    ],
    "wof:name":"Picket Fences Home Cnstr",
    "wof:placetype":"venue"
},
  "geometry": {"coordinates":[-117.25269900000001,32.786914],"type":"Point"}
}