{
  "type": "Feature",
  "properties": {
    "addr:full":"799 G St Sacramento CA 95814",
    "addr:housenumber":"799",
    "addr:postcode":"95814",
    "addr:street":"G St",
    "iso:country":"US",
    "sg:address":"799 G St",
    "sg:city":"Sacramento",
    "sg:classifiers":[
        {
            "category":"Government",
            "subcategory":"Office",
            "type":"Public Place"
        }
    ],
    "sg:phone":"+1 916 874 6144",
    "sg:postcode":"95814",
    "sg:province":"CA",
    "wof:name":"Sacramento Cnty Computer Oper",
    "wof:placetype":"venue"
},
  "geometry": {"coordinates":[-121.496038,38.584651],"type":"Point"}
}