{
  "type": "Feature",
  "properties": {
    "addr:full":"7424 E Woodsboro Ave Anaheim CA 92807",
    "addr:housenumber":"7424",
    "addr:postcode":"92807",
    "addr:street":"E Woodsboro Ave",
    "iso:country":"US",
    "sg:address":"7424 E Woodsboro Ave",
    "sg:city":"Anaheim",
    "sg:classifiers":[
        {
            "category":"Building & Trades",
            "subcategory":"Landscaping Services",
            "type":"Services"
        }
    ],
    "sg:phone":"+1 714 779 0865",
    "sg:postcode":"92807",
    "sg:province":"CA",
    "sg:tags":[
        "landscape"
    ],
    "wof:name":"Sacred Spaces Garden Designs",
    "wof:placetype":"venue"
},
  "geometry": {"coordinates":[-117.774843,33.865646],"type":"Point"}
}