{
  "type": "Feature",
  "properties": {
    "iso:country":"US",
    "sg:address":"2204 W Burbank Blvd",
    "sg:city":"Burbank",
    "sg:classifiers":[
        {
            "category":"Retail",
            "subcategory":"Auto Repair",
            "type":"Services"
        }
    ],
    "sg:phone":"+1 818 955 9577",
    "sg:postcode":"91506",
    "sg:province":"CA",
    "wof:name":"Imports Unlimited",
    "wof:placetype":"venue"
},
  "geometry": {"coordinates":[-118.334999,34.179901],"type":"Point"}
}