{
  "type": "Feature",
  "properties": {
    "iso:country":"US",
    "sg:address":"920 Country Club Dr",
    "sg:city":"Moraga",
    "sg:classifiers":[
        {
            "category":"Professional",
            "subcategory":"Lawyer & Legal Services",
            "type":"Services"
        }
    ],
    "sg:phone":"+1 925 376 2325",
    "sg:postcode":"94556",
    "sg:province":"CA",
    "sg:tags":[
        "attorney"
    ],
    "wof:name":"Radcliffe & Radcliffe",
    "wof:placetype":"venue"
},
  "geometry": {"coordinates":[-122.131276,37.834175],"type":"Point"}
}