{
  "type": "Feature",
  "properties": {
    "addr:full":"26449 Fairview Ave Hayward CA 94542",
    "addr:housenumber":"26449",
    "addr:postcode":"94542",
    "addr:street":"Fairview Ave",
    "iso:country":"US",
    "sg:address":"26449 Fairview Ave",
    "sg:city":"Hayward",
    "sg:classifiers":[
        {
            "category":"Professional",
            "type":"Services"
        }
    ],
    "sg:phone":"+1 510 537 4511",
    "sg:postcode":"94542",
    "sg:province":"CA",
    "wof:name":"Lee Baker",
    "wof:placetype":"venue"
},
  "geometry": {"coordinates":[-122.029072,37.670219],"type":"Point"}
}