{
  "type": "Feature",
  "properties": {
    "iso:country":"US",
    "sg:address":"Cote d'Azur Spa 74 N Fair Oaks Ave",
    "sg:city":"Pasadena",
    "sg:classifiers":[
        {
            "category":"Personal",
            "subcategory":"Skin Care",
            "type":"Services"
        }
    ],
    "sg:phone":"+1 626 290 9666",
    "sg:postcode":"91103",
    "sg:province":"CA",
    "wof:name":"Petal Holistic Skin Care",
    "wof:placetype":"venue"
},
  "geometry": {"coordinates":[-118.150498,34.147011],"type":"Point"}
}