{
  "type": "Feature",
  "properties": {
    "addr:full":"1290 W Redondo Beach Boulevard Gardena CA 90247",
    "addr:housenumber":"1290",
    "addr:postcode":"90247",
    "addr:street":"W Redondo Beach Boulevard",
    "iso:country":"US",
    "sg:address":"1290 W Redondo Beach Boulevard",
    "sg:city":"Gardena",
    "sg:classifiers":[
        {
            "category":"Cinema",
            "subcategory":"Movie Rental",
            "type":"Entertainment"
        }
    ],
    "sg:phone":"+1 310 323 4999",
    "sg:postcode":"90247",
    "sg:province":"CA",
    "sg:tags":[
        "game",
        "video"
    ],
    "wof:name":"Hollywood Video",
    "wof:placetype":"venue"
},
  "geometry": {"coordinates":[-118.298734,33.891994],"type":"Point"}
}