{
  "type": "Feature",
  "properties": {
    "addr:full":"3241 E Gage Ave Huntington Park CA 90255",
    "addr:housenumber":"3241",
    "addr:postcode":"90255",
    "addr:street":"E Gage Ave;Park",
    "iso:country":"US",
    "sg:address":"3241 E Gage Ave",
    "sg:city":"Huntington Park",
    "sg:classifiers":[
        {
            "category":"Building & Trades",
            "subcategory":"Electrical",
            "type":"Services"
        }
    ],
    "sg:phone":"+1 323 583 4224",
    "sg:postcode":"90255",
    "sg:province":"CA",
    "sg:tags":[
        "consulting",
        "electrical",
        "business",
        "contractor"
    ],
    "wof:name":"BBB Electric",
    "wof:placetype":"venue"
},
  "geometry": {"coordinates":[-118.208832,33.980424],"type":"Point"}
}