{
  "type": "Feature",
  "properties": {
    "addr:full":"2150 Capitol Ave Ste 200 Sacramento CA 95816",
    "addr:housenumber":"2150",
    "addr:postcode":"95816",
    "addr:street":"Capitol Ave Ste 200",
    "iso:country":"US",
    "sg:address":"2150 Capitol Ave Ste 200",
    "sg:city":"Sacramento",
    "sg:classifiers":[
        {
            "category":"Professional",
            "subcategory":"Management & Consulting",
            "type":"Services"
        },
        {
            "category":"Professional",
            "subcategory":"Business Services",
            "type":"Services"
        }
    ],
    "sg:phone":"+1 916 553 4400",
    "sg:postcode":"95816",
    "sg:province":"CA",
    "sg:tags":[
        "consultant",
        "organizing",
        "services-household"
    ],
    "sg:website":"http://www.capitalpm.com",
    "wof:name":"Capital Program Mgt Group",
    "wof:placetype":"venue"
},
  "geometry": {"coordinates":[-121.47933,38.572846],"type":"Point"}
}