{
  "type": "Feature",
  "properties": {
    "iso:country":"US",
    "sg:address":"15253 Palmdale Rd",
    "sg:city":"Victorville",
    "sg:classifiers":[
        {
            "category":"Retail",
            "subcategory":"Auto Repair",
            "type":"Services"
        }
    ],
    "sg:phone":"+1 760 843 5806",
    "sg:postcode":"92392",
    "sg:province":"CA",
    "sg:tags":[
        "repairing",
        "automobile"
    ],
    "wof:name":"Reliable Auto Repair",
    "wof:placetype":"venue"
},
  "geometry": {"coordinates":[-117.331171,34.507002],"type":"Point"}
}