{
  "type": "Feature",
  "properties": {
    "addr:full":"6500 Wilshire Blvd Ste 1860 Los Angeles CA 90048",
    "addr:housenumber":"6500",
    "addr:postcode":"90048",
    "addr:street":"Wilshire Blvd Ste 1860",
    "iso:country":"US",
    "sg:address":"6500 Wilshire Blvd Ste 1860",
    "sg:city":"Los Angeles",
    "sg:classifiers":[
        {
            "category":"Professional",
            "subcategory":"Lawyer & Legal Services",
            "type":"Services"
        }
    ],
    "sg:phone":"+1 323 651 3792",
    "sg:postcode":"90048",
    "sg:province":"CA",
    "wof:name":"Berkowitz And Cohen Law Offices Of",
    "wof:placetype":"venue"
},
  "geometry": {"coordinates":[-118.370587,34.380701],"type":"Point"}
}