{
  "type": "Feature",
  "properties": {
    "addr:full":"8664 Venice Blvd Los Angeles CA 90034",
    "addr:housenumber":"8664",
    "addr:postcode":"90034",
    "addr:street":"Venice Blvd",
    "iso:country":"US",
    "sg:address":"8664 Venice Blvd",
    "sg:city":"Los Angeles",
    "sg:classifiers":[
        {
            "category":"Autos & Motor Vehicles",
            "subcategory":"Auto Supplies",
            "type":"Retail Goods"
        }
    ],
    "sg:phone":"+1 310 733 4334",
    "sg:postcode":"90034",
    "sg:province":"CA",
    "sg:tags":[
        "part"
    ],
    "sg:website":"www.voltecbattery.com",
    "wof:name":"Voltec Battery",
    "wof:placetype":"venue"
},
  "geometry": {"coordinates":[-118.38145799999999,34.032725],"type":"Point"}
}