{
  "type": "Feature",
  "properties": {
    "iso:country":"US",
    "sg:address":"819 Eddy",
    "sg:city":"South San Francisco",
    "sg:classifiers":[
        {
            "category":"Professional",
            "subcategory":"Lawyer & Legal Services",
            "type":"Services"
        }
    ],
    "sg:phone":"+1 415 771 6174",
    "sg:postcode":"94080",
    "sg:province":"CA",
    "wof:name":"Berko Dan Atty",
    "wof:placetype":"venue"
},
  "geometry": {"coordinates":[-122.435997,37.6563],"type":"Point"}
}