{
  "type": "Feature",
  "properties": {
    "addr:full":"713 S Pacific Coast Hwy Redondo Beach CA 90277",
    "addr:housenumber":"713",
    "addr:postcode":"90277",
    "addr:street":"S Pacific Coast Hwy",
    "iso:country":"US",
    "sg:address":"713 S Pacific Coast Hwy",
    "sg:city":"Redondo Beach",
    "sg:classifiers":[
        {
            "category":"Professional",
            "subcategory":"Accounting & Tax Preparation",
            "type":"Services"
        }
    ],
    "sg:phone":"+1 310 540 3434",
    "sg:postcode":"90277",
    "sg:province":"CA",
    "sg:tags":[
        "return",
        "filing"
    ],
    "wof:name":"Grennan-Kanuit Tax Svc Inc",
    "wof:placetype":"venue"
},
  "geometry": {"coordinates":[-118.385542,33.829067],"type":"Point"}
}