{
  "type": "Feature",
  "properties": {
    "addr:full":"1212 17th Ave Santa Cruz CA 95062",
    "addr:housenumber":"1212",
    "addr:postcode":"95062",
    "addr:street":"17Th Ave",
    "iso:country":"US",
    "sg:address":"1212 17th Ave",
    "sg:city":"Santa Cruz",
    "sg:classifiers":[
        {
            "category":"Coffee & Tea",
            "type":"Food & Drink"
        }
    ],
    "sg:phone":"+1 831 464 2739",
    "sg:postcode":"95062",
    "sg:province":"CA",
    "wof:name":"People's Coffee",
    "wof:placetype":"venue"
},
  "geometry": {"coordinates":[-121.984405,36.971226],"type":"Point"}
}