{
  "type": "Feature",
  "properties": {
    "addr:full":"640 Cesar Chavez San Francisco CA 94124",
    "addr:housenumber":"640",
    "addr:postcode":"94124",
    "addr:street":"Cesar Chavez",
    "iso:country":"US",
    "sg:address":"640 Cesar Chavez",
    "sg:city":"San Francisco",
    "sg:classifiers":[
        {
            "category":"Freight",
            "type":"Transportation"
        }
    ],
    "sg:phone":"+1 415 821 0800",
    "sg:postcode":"94124",
    "sg:province":"CA",
    "sg:tags":[
        "arrangement",
        "courier",
        "air"
    ],
    "sg:website":"www.accordx.com",
    "wof:name":"Accord Export Lines Inc",
    "wof:placetype":"venue"
},
  "geometry": {"coordinates":[-122.384229,37.750565],"type":"Point"}
}