{
  "type": "Feature",
  "properties": {
    "addr:full":"955 Leneve Pl El Cerrito CA 94530",
    "addr:housenumber":"955",
    "addr:postcode":"94530",
    "addr:street":"Leneve Pl",
    "iso:country":"US",
    "sg:address":"955 Leneve Pl",
    "sg:city":"El Cerrito",
    "sg:classifiers":[
        {
            "category":"Professional",
            "subcategory":"Management & Consulting",
            "type":"Services"
        }
    ],
    "sg:phone":"+1 510 527 1795",
    "sg:postcode":"94530",
    "sg:province":"CA",
    "sg:tags":[
        "consultant",
        "educational"
    ],
    "wof:name":"Michele Radcliffe",
    "wof:placetype":"venue"
},
  "geometry": {"coordinates":[-122.284581,37.92144],"type":"Point"}
}