{
  "type": "Feature",
  "properties": {
    "iso:country":"US",
    "sg:address":"5785 Adobe Rd",
    "sg:city":"Twentynine Palms",
    "sg:classifiers":[
        {
            "category":"Real Estate",
            "subcategory":"Real Estate Agent",
            "type":"Services"
        }
    ],
    "sg:phone":"+1 760 361 2237",
    "sg:postcode":"92277",
    "sg:province":"CA",
    "wof:name":"Sandy's Realty",
    "wof:placetype":"venue"
},
  "geometry": {"coordinates":[-116.05412800000001,34.147351],"type":"Point"}
}