{
  "type": "Feature",
  "properties": {
    "iso:country":"US",
    "sg:address":"5831 Rosebud Ln",
    "sg:city":"Sacramento",
    "sg:classifiers":[
        {
            "category":"Retail",
            "subcategory":"Auto Repair",
            "type":"Services"
        }
    ],
    "sg:phone":"+1 916 223 3613",
    "sg:postcode":"95841",
    "sg:province":"CA",
    "sg:tags":[
        "transmission"
    ],
    "wof:name":"ARW Transmission",
    "wof:placetype":"venue"
},
  "geometry": {"coordinates":[-121.329119,38.674879],"type":"Point"}
}