{
  "type": "Feature",
  "properties": {
    "addr:full":"717 W 152nd St Gardena CA 90247",
    "addr:housenumber":"717",
    "addr:postcode":"90247",
    "addr:street":"W 152Nd St",
    "iso:country":"US",
    "sg:address":"717 W 152nd St",
    "sg:city":"Gardena",
    "sg:classifiers":[
        {
            "category":"Wholesale",
            "subcategory":"Construction Materials",
            "type":"Manufacturing & Wholesale Goods"
        }
    ],
    "sg:phone":"+1 310 327 3651",
    "sg:postcode":"90247",
    "sg:province":"CA",
    "sg:tags":[
        "pallet",
        "skid"
    ],
    "wof:name":"R & M Pallets",
    "wof:placetype":"venue"
},
  "geometry": {"coordinates":[-118.287181,33.894503],"type":"Point"}
}