{
  "type": "Feature",
  "properties": {
    "addr:full":"655 Eunice Ave Mountain View CA 94040",
    "addr:housenumber":"655",
    "addr:postcode":"94040",
    "addr:street":"Eunice Ave",
    "iso:country":"US",
    "sg:address":"655 Eunice Ave",
    "sg:city":"Mountain View",
    "sg:classifiers":[
        {
            "category":"Manufacturing",
            "subcategory":"Electronics",
            "type":"Manufacturing & Wholesale Goods"
        }
    ],
    "sg:phone":"+1 650 968 9669",
    "sg:postcode":"94040",
    "sg:province":"CA",
    "sg:tags":[
        "electronic",
        "component",
        "mfg"
    ],
    "wof:name":"Fmedoptics",
    "wof:placetype":"venue"
},
  "geometry": {"coordinates":[-122.071877,37.369735],"type":"Point"}
}