{
  "type": "Feature",
  "properties": {
    "addr:full":"1019 S H St Bakersfield CA 93304",
    "addr:housenumber":"1019",
    "addr:postcode":"93304",
    "addr:street":"S H St",
    "iso:country":"US",
    "sg:address":"1019 S H St",
    "sg:city":"Bakersfield",
    "sg:classifiers":[
        {
            "category":"Retail",
            "subcategory":"Auto Repair",
            "type":"Services"
        }
    ],
    "sg:phone":"+1 661 398 0562",
    "sg:postcode":"93304",
    "sg:province":"CA",
    "sg:tags":[
        "machine",
        "automobile",
        "shop"
    ],
    "wof:name":"D & M Automotive Machine & Rpr",
    "wof:placetype":"venue"
},
  "geometry": {"coordinates":[-119.02126699999999,35.344148],"type":"Point"}
}