{
  "type": "Feature",
  "properties": {
    "addr:full":"26328 Bouquet Canyon Rd Santa Clarita CA 91350",
    "addr:housenumber":"26328",
    "addr:postcode":"91350",
    "addr:street":"Bouquet Canyon Rd",
    "iso:country":"US",
    "sg:address":"26328 Bouquet Canyon Rd",
    "sg:city":"Santa Clarita",
    "sg:classifiers":[
        {
            "category":"Bars & Pubs",
            "subcategory":"Nightclub",
            "type":"Food & Drink"
        }
    ],
    "sg:phone":"+1 661 259 8822",
    "sg:postcode":"91350",
    "sg:province":"CA",
    "sg:tags":[
        "nightlife"
    ],
    "wof:name":"Mabel's Roadhouse",
    "wof:placetype":"venue"
},
  "geometry": {"coordinates":[-118.542,34.419701],"type":"Point"}
}