{
  "type": "Feature",
  "properties": {
    "iso:country":"US",
    "sg:address":"2601 Oakdale Rd",
    "sg:city":"Modesto",
    "sg:classifiers":[
        {
            "category":"Banks & Credit Unions",
            "subcategory":"Bank",
            "type":"Services"
        }
    ],
    "sg:phone":"+1 209 524 8656",
    "sg:postcode":"95355",
    "sg:province":"CA",
    "sg:tags":[
        "cashing",
        "personal",
        "check",
        "institution"
    ],
    "wof:name":"Advance America",
    "wof:placetype":"venue"
},
  "geometry": {"coordinates":[-120.957823,37.680165],"type":"Point"}
}