{
  "type": "Feature",
  "properties": {
    "addr:full":"32 Flintstone Aliso Viejo CA 92656",
    "addr:housenumber":"32",
    "addr:postcode":"92656",
    "addr:street":"Flintstone",
    "iso:country":"US",
    "sg:address":"32 Flintstone",
    "sg:city":"Aliso Viejo",
    "sg:classifiers":[
        {
            "category":"Wholesale",
            "subcategory":"Metals & Minerals",
            "type":"Manufacturing & Wholesale Goods"
        }
    ],
    "sg:phone":"+1 949 362 7993",
    "sg:postcode":"92656",
    "sg:province":"CA",
    "sg:tags":[
        "center"
    ],
    "wof:name":"Tom Gillan Co",
    "wof:placetype":"venue"
},
  "geometry": {"coordinates":[-117.735338,33.589477],"type":"Point"}
}