{
  "type": "Feature",
  "properties": {
    "addr:full":"701 E 28th St Long Beach CA 90806",
    "addr:housenumber":"701",
    "addr:postcode":"90806",
    "addr:street":"E 28Th St",
    "iso:country":"US",
    "sg:address":"701 E 28th St",
    "sg:city":"Long Beach",
    "sg:classifiers":[
        {
            "category":"Health Services",
            "subcategory":"Doctor",
            "type":"Services"
        }
    ],
    "sg:phone":"+1 562 989 7997",
    "sg:postcode":"90806",
    "sg:province":"CA",
    "sg:tags":[
        "physician",
        "surgeon"
    ],
    "wof:name":"Daniel D Truong Inc",
    "wof:placetype":"venue"
},
  "geometry": {"coordinates":[-118.183852,33.808079],"type":"Point"}
}