{
  "type": "Feature",
  "properties": {
    "iso:country":"US",
    "sg:address":"810 Indian Hill Blvd",
    "sg:city":"Pomona",
    "sg:classifiers":[
        {
            "category":"Government",
            "subcategory":"Office",
            "type":"Public Place"
        }
    ],
    "sg:phone":"+1 909 621 4219",
    "sg:postcode":"91767",
    "sg:province":"CA",
    "sg:tags":[
        "armed",
        "force",
        "recruiting"
    ],
    "wof:name":"US Army Recruiting",
    "wof:placetype":"venue"
},
  "geometry": {"coordinates":[-117.719147,34.068028],"type":"Point"}
}