{
  "type": "Feature",
  "properties": {
    "iso:country":"US",
    "sg:address":"3303 Harbor Boulevard",
    "sg:city":"Costa Mesa",
    "sg:classifiers":[
        {
            "category":"Shopping",
            "subcategory":"Pharmacy",
            "type":"Retail Goods"
        }
    ],
    "sg:phone":"+1 714 662 5589",
    "sg:postcode":"92626",
    "sg:province":"CA",
    "sg:tags":[
        "drugstore"
    ],
    "wof:name":"Extended Homecare Pharmacy United Drugs",
    "wof:placetype":"venue"
},
  "geometry": {"coordinates":[-117.919594,33.691696],"type":"Point"}
}