{
  "type": "Feature",
  "properties": {
    "addr:full":"37827 97th St E Littlerock CA 93543",
    "addr:housenumber":"37827",
    "addr:postcode":"littlerock ca 93543",
    "addr:street":"97Th St E",
    "iso:country":"US",
    "sg:address":"37827 97th St E",
    "sg:city":"Littlerock",
    "sg:classifiers":[
        {
            "category":"Education",
            "subcategory":"School",
            "type":"Public Place"
        }
    ],
    "sg:phone":"+1 661 944 5195",
    "sg:postcode":"93543",
    "sg:province":"CA",
    "wof:name":"Desert Blossom Christian Dev",
    "wof:placetype":"venue"
},
  "geometry": {"coordinates":[-117.956699,34.569244],"type":"Point"}
}