{
  "type": "Feature",
  "properties": {
    "addr:full":"815 W 92nd St Los Angeles CA 90044",
    "addr:housenumber":"815",
    "addr:postcode":"90044",
    "addr:street":"W 92Nd St",
    "iso:country":"US",
    "sg:address":"815 W 92nd St",
    "sg:city":"Los Angeles",
    "sg:classifiers":[
        {
            "category":"Shopping",
            "type":"Retail Goods"
        }
    ],
    "sg:phone":"+1 323 242 0511",
    "sg:postcode":"90044",
    "sg:province":"CA",
    "sg:tags":[
        "cosmetic",
        "perfume"
    ],
    "wof:name":"Giselle Perfumes",
    "wof:placetype":"venue"
},
  "geometry": {"coordinates":[-118.29015699999999,33.952872],"type":"Point"}
}