{
  "type": "Feature",
  "properties": {
    "iso:country":"US",
    "sg:address":"1126 Queens Hwy Ste 108",
    "sg:city":"Long Beach",
    "sg:classifiers":[
        {
            "category":"Shopping",
            "subcategory":"Hobbies, Toys, & Games",
            "type":"Retail Goods"
        }
    ],
    "sg:phone":"+1 562 499 1760",
    "sg:postcode":"90802",
    "sg:province":"CA",
    "sg:tags":[
        "shop",
        "hobby"
    ],
    "sg:website":"www.scottishheritagecenter.com/t...",
    "wof:name":"Scottish Heritage Center",
    "wof:placetype":"venue"
},
  "geometry": {"coordinates":[-118.191107,33.752206],"type":"Point"}
}