{
  "type": "Feature",
  "properties": {
    "iso:country":"US",
    "sg:address":"5587 Greeley Hill Rd",
    "sg:city":"Coulterville",
    "sg:classifiers":[
        {
            "category":"Personal",
            "subcategory":"Beauty Salon",
            "type":"Services"
        }
    ],
    "sg:phone":"+1 209 878 3429",
    "sg:postcode":"95311",
    "sg:province":"CA",
    "wof:name":"Nadin' S Beauty Shop",
    "wof:placetype":"venue"
},
  "geometry": {"coordinates":[-120.177757,37.733269],"type":"Point"}
}