{
  "type": "Feature",
  "properties": {
    "addr:full":"444 Oakland Ave Oakland CA 94611",
    "addr:housenumber":"444",
    "addr:postcode":"94611",
    "addr:street":"Oakland Ave",
    "iso:country":"US",
    "sg:address":"444 Oakland Ave",
    "sg:city":"Oakland",
    "sg:classifiers":[
        {
            "category":"Building & Trades",
            "subcategory":"Electrical",
            "type":"Services"
        }
    ],
    "sg:phone":"+1 415 450 9072",
    "sg:postcode":"94611",
    "sg:province":"CA",
    "sg:tags":[
        "industrial",
        "electrician",
        "electric",
        "contractors-commercial"
    ],
    "wof:name":"Domb Electric Co.",
    "wof:placetype":"venue"
},
  "geometry": {"coordinates":[-122.25467399999999,37.818277],"type":"Point"}
}