{
  "type": "Feature",
  "properties": {
    "iso:country":"US",
    "sg:address":"5427 E Washington Blvd",
    "sg:city":"Los Angeles",
    "sg:classifiers":[
        {
            "category":"Wholesale",
            "subcategory":"Groceries",
            "type":"Manufacturing & Wholesale Goods"
        }
    ],
    "sg:phone":"+1 323 724 9496",
    "sg:postcode":"90040",
    "sg:province":"CA",
    "sg:tags":[
        "product"
    ],
    "wof:name":"Cortes Guarex USA",
    "wof:placetype":"venue"
},
  "geometry": {"coordinates":[-118.161616,34.001037],"type":"Point"}
}