{
  "type": "Feature",
  "properties": {
    "addr:full":"736 S San Pedro St Los Angeles CA 90014",
    "addr:housenumber":"736",
    "addr:postcode":"90014",
    "addr:street":"S San Pedro St",
    "iso:country":"US",
    "sg:address":"736 S San Pedro St",
    "sg:city":"Los Angeles",
    "sg:classifiers":[
        {
            "category":"Shopping",
            "subcategory":"Crafts & Fabrics",
            "type":"Retail Goods"
        }
    ],
    "sg:phone":"+1 213 488 1299",
    "sg:postcode":"90014",
    "sg:province":"CA",
    "sg:tags":[
        "sewing"
    ],
    "wof:name":"ABG Fabrics",
    "wof:placetype":"venue"
},
  "geometry": {"coordinates":[-118.247236,34.040291],"type":"Point"}
}