{
  "type": "Feature",
  "properties": {
    "addr:full":"145 Ramona Expy Perris CA 92571",
    "addr:housenumber":"145",
    "addr:postcode":"92571",
    "addr:street":"Ramona Expy",
    "iso:country":"US",
    "sg:address":"145 Ramona Expy",
    "sg:city":"Perris",
    "sg:classifiers":[
        {
            "category":"Personal",
            "subcategory":"Beauty Salon",
            "type":"Services"
        }
    ],
    "sg:phone":"+1 951 657 3828",
    "sg:postcode":"92571",
    "sg:province":"CA",
    "sg:tags":[
        "manicuring"
    ],
    "wof:name":"NAIL&Spa.Com",
    "wof:placetype":"venue"
},
  "geometry": {"coordinates":[-117.22275999999999,33.844629],"type":"Point"}
}