{
  "type": "Feature",
  "properties": {
    "iso:country":"US",
    "sg:address":"545 Ashbury Avenue",
    "sg:city":"El Cerrito",
    "sg:classifiers":[
        {
            "category":"Health Services",
            "subcategory":"Clinic",
            "type":"Services"
        }
    ],
    "sg:phone":"+1 510 527 7249",
    "sg:postcode":"94530",
    "sg:province":"CA",
    "sg:tags":[
        "counseling",
        "mental"
    ],
    "wof:name":"West Coast Children's Clinic",
    "wof:placetype":"venue"
},
  "geometry": {"coordinates":[-122.29499800000001,37.906799],"type":"Point"}
}