{
  "type": "Feature",
  "properties": {
    "iso:country":"US",
    "sg:address":"1717 Coffee Rd",
    "sg:city":"Modesto",
    "sg:classifiers":[
        {
            "category":"Health Services",
            "subcategory":"Doctor",
            "type":"Services"
        }
    ],
    "sg:phone":"+1 209 529 0531",
    "sg:postcode":"95355",
    "sg:province":"CA",
    "sg:tags":[
        "practice",
        "family"
    ],
    "wof:name":"Fitzpatrick Dale W MD",
    "wof:placetype":"venue"
},
  "geometry": {"coordinates":[-120.975998,37.668098],"type":"Point"}
}