{
  "type": "Feature",
  "properties": {
    "iso:country":"US",
    "sg:address":"133 S Crescent Dr",
    "sg:city":"Beverly Hills",
    "sg:classifiers":[
        {
            "category":"Professional",
            "type":"Services"
        }
    ],
    "sg:phone":"+1 310 888 0026",
    "sg:postcode":"90212",
    "sg:province":"CA",
    "wof:name":"1575 & Company",
    "wof:placetype":"venue"
},
  "geometry": {"coordinates":[-118.395971,34.065024],"type":"Point"}
}