{
  "type": "Feature",
  "properties": {
    "iso:country":"US",
    "sg:address":"2849 Rockville Rd",
    "sg:city":"Fairfield",
    "sg:classifiers":[
        {
            "category":"Building & Trades",
            "subcategory":"Equipment Rental",
            "type":"Services"
        },
        {
            "category":"Shopping",
            "subcategory":"Computers & Home Electronics",
            "type":"Retail Goods"
        }
    ],
    "sg:phone":"+1 707 426 3599",
    "sg:postcode":"94534",
    "sg:province":"CA",
    "sg:tags":[
        "stereo",
        "leasing",
        "video",
        "audio",
        "equipment-renting",
        "audio-visual"
    ],
    "wof:name":"The Grapevine Collection",
    "wof:placetype":"venue"
},
  "geometry": {"coordinates":[-122.084457,38.246891],"type":"Point"}
}