{
  "type": "Feature",
  "properties": {
    "addr:full":"10885 Los Alamitos Blvd Los Alamitos CA 90720",
    "addr:housenumber":"10885",
    "addr:postcode":"90720",
    "addr:street":"Los Alamitos Blvd",
    "iso:country":"US",
    "sg:address":"10885 Los Alamitos Blvd",
    "sg:city":"Los Alamitos",
    "sg:classifiers":[
        {
            "category":"Arena",
            "subcategory":"Sports Club",
            "type":"Entertainment"
        }
    ],
    "sg:phone":"+1 562 430 5263",
    "sg:postcode":"90720",
    "sg:province":"CA",
    "sg:tags":[
        "martial art"
    ],
    "sg:website":"www.NHCfitness.com",
    "wof:name":"NHC Martial Arts & Fitness",
    "wof:placetype":"venue"
},
  "geometry": {"coordinates":[-118.071873,33.804306],"type":"Point"}
}