{
  "type": "Feature",
  "properties": {
    "addr:full":"734 University Ave Ste A San Diego CA 92103",
    "addr:housenumber":"734",
    "addr:postcode":"92103",
    "addr:street":"University Ave Ste A",
    "iso:country":"US",
    "sg:address":"734 University Ave Ste A",
    "sg:city":"San Diego",
    "sg:classifiers":[
        {
            "category":"Professional",
            "subcategory":"Lawyer & Legal Services",
            "type":"Services"
        }
    ],
    "sg:phone":"+1 619 681 0575",
    "sg:postcode":"92103",
    "sg:province":"CA",
    "sg:tags":[
        "notary"
    ],
    "sg:website":"www.kinkos.com",
    "wof:name":"FedEx Office",
    "wof:placetype":"venue"
},
  "geometry": {"coordinates":[-117.157719,32.748508],"type":"Point"}
}