{
  "type": "Feature",
  "properties": {
    "addr:full":"1010 W Chapman Ave Orange CA 92868",
    "addr:housenumber":"1010",
    "addr:postcode":"92868",
    "addr:street":"W Chapman Ave",
    "iso:country":"US",
    "sg:address":"1010 W Chapman Ave",
    "sg:city":"Orange",
    "sg:classifiers":[
        {
            "category":"Banks & Credit Unions",
            "subcategory":"Bank",
            "type":"Services"
        }
    ],
    "sg:phone":"+1 714 744 1474",
    "sg:postcode":"92868",
    "sg:province":"CA",
    "wof:name":"American First Credit Union",
    "wof:placetype":"venue"
},
  "geometry": {"coordinates":[-117.862999,33.787899],"type":"Point"}
}