{
  "type": "Feature",
  "properties": {
    "addr:full":"26 Orinda Way Orinda CA 94563",
    "addr:housenumber":"26",
    "addr:postcode":"94563",
    "addr:street":"Orinda Way",
    "iso:country":"US",
    "sg:address":"26 Orinda Way",
    "sg:city":"Orinda",
    "sg:classifiers":[
        {
            "category":"Park",
            "type":"Public Place"
        }
    ],
    "sg:postcode":"94563",
    "sg:province":"CA",
    "sg:website":"old.ci.orinda.ca.us/parksandrec/...",
    "wof:name":"Orinda Community Center Park",
    "wof:placetype":"venue"
},
  "geometry": {"coordinates":[-122.187635,37.882534],"type":"Point"}
}