{
  "type": "Feature",
  "properties": {
    "iso:country":"US",
    "sg:address":"3612 Coffee Rd",
    "sg:city":"Bakersfield",
    "sg:classifiers":[
        {
            "category":"Professional",
            "subcategory":"Employment Agencies",
            "type":"Services"
        }
    ],
    "sg:phone":"+1 661 410 7770",
    "sg:postcode":"93308",
    "sg:province":"CA",
    "sg:tags":[
        "opportunity"
    ],
    "wof:name":"Rand Employment Solutions",
    "wof:placetype":"venue"
},
  "geometry": {"coordinates":[-119.092269,35.391491],"type":"Point"}
}