{
  "type": "Feature",
  "properties": {
    "iso:country":"US",
    "sg:address":"773 Andersen Dr",
    "sg:city":"San Rafael",
    "sg:classifiers":[
        {
            "category":"Building & Trades",
            "subcategory":"Plumbing",
            "type":"Services"
        }
    ],
    "sg:phone":"+1 415 591 6615",
    "sg:postcode":"94901",
    "sg:province":"CA",
    "sg:tags":[
        "contractor"
    ],
    "wof:name":"Skips Hvac Consulting",
    "wof:placetype":"venue"
},
  "geometry": {"coordinates":[-122.51133799999999,37.960256],"type":"Point"}
}