{
  "type": "Feature",
  "properties": {
    "addr:full":"16811 San Jose St Granada Hills CA 91344",
    "addr:housenumber":"16811",
    "addr:postcode":"91344",
    "addr:street":"San Jose St",
    "iso:country":"US",
    "sg:address":"16811 San Jose St",
    "sg:city":"Granada Hills",
    "sg:classifiers":[
        {
            "category":"Professional",
            "subcategory":"Business Services",
            "type":"Services"
        }
    ],
    "sg:phone":"+1 818 831 1931",
    "sg:postcode":"91344",
    "sg:province":"CA",
    "sg:tags":[
        "messenger"
    ],
    "wof:name":"RAZ Com-Messaging Svc",
    "wof:placetype":"venue"
},
  "geometry": {"coordinates":[-118.500334,34.261211],"type":"Point"}
}