{
  "type": "Feature",
  "properties": {
    "iso:country":"US",
    "sg:address":"26135 Carmel Rancho Blvd Ste B1",
    "sg:city":"Carmel",
    "sg:classifiers":[
        {
            "category":"Cinema",
            "subcategory":"Movie Rental",
            "type":"Entertainment"
        },
        {
            "category":"Shopping",
            "subcategory":"Music",
            "type":"Retail Goods"
        }
    ],
    "sg:phone":"+1 831 625 1229",
    "sg:postcode":"93923",
    "sg:province":"CA",
    "sg:tags":[
        "game",
        "video",
        "dvd's"
    ],
    "wof:name":"DO Re Mi Music & Video",
    "wof:placetype":"venue"
},
  "geometry": {"coordinates":[-121.904999,36.541401],"type":"Point"}
}