{
  "type": "Feature",
  "properties": {
    "iso:country":"US",
    "sg:address":"15037 Alondra Blvd",
    "sg:city":"La Mirada",
    "sg:classifiers":[
        {
            "category":"Personal",
            "subcategory":"Nail Salon",
            "type":"Services"
        }
    ],
    "sg:phone":"+1 714 228 9171",
    "sg:postcode":"90638",
    "sg:province":"CA",
    "wof:name":"Fancy Nails",
    "wof:placetype":"venue"
},
  "geometry": {"coordinates":[-118.010002,33.888199],"type":"Point"}
}