{
  "type": "Feature",
  "properties": {
    "addr:full":"970 Kristin Ridge Way Milpitas CA 95035",
    "addr:housenumber":"970",
    "addr:postcode":"95035",
    "addr:street":"Kristin Ridge Way",
    "iso:country":"US",
    "sg:address":"970 Kristin Ridge Way",
    "sg:city":"Milpitas",
    "sg:classifiers":[
        {
            "category":"Professional",
            "subcategory":"Computer Services",
            "type":"Services"
        }
    ],
    "sg:phone":"+1 408 666 6133",
    "sg:postcode":"95035",
    "sg:province":"CA",
    "sg:tags":[
        "consultant",
        "designer"
    ],
    "wof:name":"Caspian Solutions",
    "wof:placetype":"venue"
},
  "geometry": {"coordinates":[-121.86319399999999,37.426753],"type":"Point"}
}