{
  "type": "Feature",
  "properties": {
    "addr:full":"145 Commerce Way Unit A Walnut CA 91789",
    "addr:housenumber":"145",
    "addr:postcode":"91789",
    "addr:street":"Commerce Way Unit A",
    "iso:country":"US",
    "sg:address":"145 Commerce Way Unit A",
    "sg:city":"Walnut",
    "sg:classifiers":[
        {
            "category":"Building & Trades",
            "subcategory":"Cleaning & Sanitation",
            "type":"Services"
        },
        {
            "category":"Home & Garden",
            "subcategory":"Building Materials",
            "type":"Retail Goods"
        },
        {
            "category":"Building & Trades",
            "subcategory":"Construction",
            "type":"Services"
        }
    ],
    "sg:phone":"+1 909 396 9602",
    "sg:postcode":"91789",
    "sg:province":"CA",
    "sg:tags":[
        "system",
        "specialty",
        "duct",
        "heating",
        "equipment",
        "contractor",
        "air conditioning"
    ],
    "sg:website":"http://www.stevesheatingandac.com",
    "wof:name":"Steve's Heating & Air Conditioning",
    "wof:placetype":"venue"
},
  "geometry": {"coordinates":[-117.854861,34.015312],"type":"Point"}
}