{
  "type": "Feature",
  "properties": {
    "addr:full":"1732 E 14th St San Leandro CA 94577",
    "addr:housenumber":"1732",
    "addr:postcode":"94577",
    "addr:street":"E 14Th St",
    "iso:country":"US",
    "sg:address":"1732 E 14th St",
    "sg:city":"San Leandro",
    "sg:classifiers":[
        {
            "category":"Banks & Credit Unions",
            "subcategory":"Financial Services",
            "type":"Services"
        }
    ],
    "sg:phone":"+1 510 895 2356",
    "sg:postcode":"94577",
    "sg:province":"CA",
    "sg:tags":[
        "broker",
        "mortgage"
    ],
    "wof:name":"Geritz Financial Services",
    "wof:placetype":"venue"
},
  "geometry": {"coordinates":[-122.152,37.721699],"type":"Point"}
}