{
  "type": "Feature",
  "properties": {
    "iso:country":"US",
    "sg:address":"8600 Melrose Ave",
    "sg:city":"Los Angeles",
    "sg:classifiers":[
        {
            "category":"Home & Garden",
            "subcategory":"Carpets & Floor Coverings",
            "type":"Retail Goods"
        }
    ],
    "sg:phone":"+1 310 652 9999",
    "sg:postcode":"90069",
    "sg:province":"CA",
    "sg:tags":[
        "dealer",
        "rug"
    ],
    "sg:website":"www.mansourrug.com",
    "wof:name":"Mansour Fine Rug & Floor Cvrng",
    "wof:placetype":"venue"
},
  "geometry": {"coordinates":[-118.380694,34.081973],"type":"Point"}
}