{
  "type": "Feature",
  "properties": {
    "iso:country":"US",
    "sg:address":"115 W 7th St",
    "sg:city":"Los Angeles",
    "sg:classifiers":[
        {
            "category":"Wholesale",
            "subcategory":"Apparel",
            "type":"Manufacturing & Wholesale Goods"
        }
    ],
    "sg:phone":"+1 213 623 4561",
    "sg:postcode":"90014",
    "sg:province":"CA",
    "sg:tags":[
        "clothing"
    ],
    "wof:name":"Micropattern",
    "wof:placetype":"venue"
},
  "geometry": {"coordinates":[-118.251589,34.044125],"type":"Point"}
}