{
  "type": "Feature",
  "properties": {
    "iso:country":"US",
    "sg:address":"2842 N Business Park Ave",
    "sg:city":"Fresno",
    "sg:classifiers":[
        {
            "category":"Manufacturing",
            "subcategory":"Tools & Machinery",
            "type":"Manufacturing & Wholesale Goods"
        }
    ],
    "sg:phone":"+1 559 292 2171",
    "sg:postcode":"93727",
    "sg:province":"CA",
    "sg:tags":[
        "product",
        "mfg",
        "patient",
        "care"
    ],
    "wof:name":"Sunrise Medical Inc",
    "wof:placetype":"venue"
},
  "geometry": {"coordinates":[-119.685125,36.776143],"type":"Point"}
}