{
  "type": "Feature",
  "properties": {
    "iso:country":"US",
    "sg:address":"1839 Kellerton Dr",
    "sg:city":"Hacienda Heights",
    "sg:classifiers":[
        {
            "category":"Professional",
            "type":"Services"
        }
    ],
    "sg:phone":"+1 626 968 2281",
    "sg:postcode":"91745",
    "sg:province":"CA",
    "wof:name":"Take Out Records",
    "wof:placetype":"venue"
},
  "geometry": {"coordinates":[-117.96209,33.996782],"type":"Point"}
}