{
  "type": "Feature",
  "properties": {
    "iso:country":"US",
    "sg:address":"32169 Corte Daroca",
    "sg:city":"Temecula",
    "sg:classifiers":[
        {
            "category":"Farming",
            "subcategory":"Livestock Farm",
            "type":"Manufacturing & Wholesale Goods"
        }
    ],
    "sg:phone":"+1 951 302 9199",
    "sg:postcode":"92592",
    "sg:province":"CA",
    "sg:tags":[
        "animal",
        "general"
    ],
    "wof:name":"Cimarron At 3 Rings Ranch LLC",
    "wof:placetype":"venue"
},
  "geometry": {"coordinates":[-117.095823,33.463249],"type":"Point"}
}