{
  "type": "Feature",
  "properties": {
    "addr:full":"1468 Whitewood Ct San Jose CA 95131",
    "addr:housenumber":"1468",
    "addr:postcode":"95131",
    "addr:street":"Whitewood Ct",
    "iso:country":"US",
    "sg:address":"1468 Whitewood Ct",
    "sg:city":"San Jose",
    "sg:classifiers":[
        {
            "category":"Real Estate",
            "subcategory":"Real Estate Agent",
            "type":"Services"
        }
    ],
    "sg:phone":"+1 408 441 6867",
    "sg:postcode":"95131",
    "sg:province":"CA",
    "sg:tags":[
        "agency",
        "rental"
    ],
    "wof:name":"Woodland Meadow Rental Cndmnms",
    "wof:placetype":"venue"
},
  "geometry": {"coordinates":[-121.890019,37.385723],"type":"Point"}
}