{
  "type": "Feature",
  "properties": {
    "iso:country":"US",
    "sg:address":"27 W Main St",
    "sg:city":"Alhambra",
    "sg:classifiers":[
        {
            "category":"Utilities",
            "subcategory":"Telephone",
            "type":"Services"
        }
    ],
    "sg:phone":"+1 626 300 8630",
    "sg:postcode":"91801",
    "sg:province":"CA",
    "sg:tags":[
        "telecommunication"
    ],
    "wof:name":"Uphone Corp",
    "wof:placetype":"venue"
},
  "geometry": {"coordinates":[-118.12771499999999,34.094864],"type":"Point"}
}