{
  "type": "Feature",
  "properties": {
    "iso:country":"US",
    "sg:address":"4190 Green River Rd",
    "sg:city":"Corona",
    "sg:classifiers":[
        {
            "category":"Banks & Credit Unions",
            "subcategory":"Financial Services",
            "type":"Services"
        }
    ],
    "sg:phone":"+1 951 284 2300",
    "sg:postcode":"92880",
    "sg:province":"CA",
    "sg:tags":[
        "broker",
        "mortgage"
    ],
    "wof:name":"Dove Capital Corporation",
    "wof:placetype":"venue"
},
  "geometry": {"coordinates":[-117.646365,33.879474],"type":"Point"}
}