{
  "type": "Feature",
  "properties": {
    "addr:full":"1221 Ralston Ave Belmont CA 94002",
    "addr:housenumber":"1221",
    "addr:postcode":"94002",
    "addr:street":"Ralston Ave",
    "iso:country":"US",
    "sg:address":"1221 Ralston Ave",
    "sg:city":"Belmont",
    "sg:classifiers":[
        {
            "category":"Professional",
            "subcategory":"Business Services",
            "type":"Services"
        }
    ],
    "sg:phone":"+1 650 592 4441",
    "sg:postcode":"94002",
    "sg:province":"CA",
    "sg:tags":[
        "recording",
        "studio"
    ],
    "wof:name":"Sharon Bearce Studio",
    "wof:placetype":"venue"
},
  "geometry": {"coordinates":[-122.280052,37.516737],"type":"Point"}
}