{
  "type": "Feature",
  "properties": {
    "addr:full":"42202 50th St W Lancaster CA 93536",
    "addr:housenumber":"42202",
    "addr:postcode":"93536",
    "addr:street":"50Th St W",
    "iso:country":"US",
    "sg:address":"42202 50th St W",
    "sg:city":"Lancaster",
    "sg:classifiers":[
        {
            "category":"Manufacturing",
            "subcategory":"Food",
            "type":"Manufacturing & Wholesale Goods"
        },
        {
            "category":"Food & Beverages",
            "subcategory":"Bakery",
            "type":"Retail Goods"
        }
    ],
    "sg:phone":"+1 661 722 8156",
    "sg:postcode":"93536",
    "sg:province":"CA",
    "sg:tags":[
        "product",
        "doughnut",
        "mfg"
    ],
    "wof:name":"Sugary Donuts",
    "wof:placetype":"venue"
},
  "geometry": {"coordinates":[-118.218433,34.649306],"type":"Point"}
}