{
  "type": "Feature",
  "properties": {
    "iso:country":"US",
    "sg:address":"685 Royce Ln",
    "sg:city":"Chico",
    "sg:classifiers":[
        {
            "category":"Building & Trades",
            "subcategory":"Construction",
            "type":"Services"
        }
    ],
    "sg:phone":"+1 530 891 8116",
    "sg:postcode":"95973",
    "sg:province":"CA",
    "sg:tags":[
        "repairing",
        "remodeling",
        "contractor"
    ],
    "wof:name":"St Charles Co",
    "wof:placetype":"venue"
},
  "geometry": {"coordinates":[-121.872276,39.751902],"type":"Point"}
}