{
  "type": "Feature",
  "properties": {
    "addr:full":"2518 E 53rd St Huntington Park CA 90255",
    "addr:housenumber":"2518",
    "addr:postcode":"90255",
    "addr:street":"E 53Rd St;Park",
    "iso:country":"US",
    "sg:address":"2518 E 53rd St",
    "sg:city":"Huntington Park",
    "sg:classifiers":[
        {
            "category":"Manufacturing",
            "subcategory":"Metals",
            "type":"Manufacturing & Wholesale Goods"
        }
    ],
    "sg:phone":"+1 323 589 9933",
    "sg:postcode":"90255",
    "sg:province":"CA",
    "sg:tags":[
        "steel"
    ],
    "wof:name":"Progressive Frame",
    "wof:placetype":"venue"
},
  "geometry": {"coordinates":[-118.226305,33.994707],"type":"Point"}
}