{
  "type": "Feature",
  "properties": {
    "iso:country":"US",
    "sg:address":"26780 Chiplay Rd",
    "sg:city":"Hayward",
    "sg:classifiers":[
        {
            "category":"Sports & Exercise",
            "subcategory":"Tennis Court",
            "type":"Entertainment"
        }
    ],
    "sg:phone":"+1 510 881 6700",
    "sg:postcode":"94545",
    "sg:province":"CA",
    "sg:website":"www.haywardrec.org",
    "wof:name":"Southgate Park Tennis Courts",
    "wof:placetype":"venue"
},
  "geometry": {"coordinates":[-122.095592,37.635776],"type":"Point"}
}