{
  "type": "Feature",
  "properties": {
    "addr:full":"621 S Virgil Ave Los Angeles CA 90005",
    "addr:housenumber":"621",
    "addr:postcode":"90005",
    "addr:street":"S Virgil Ave",
    "iso:country":"US",
    "sg:address":"621 S Virgil Ave",
    "sg:city":"Los Angeles",
    "sg:classifiers":[
        {
            "category":"Professional",
            "subcategory":"Advertising",
            "type":"Services"
        }
    ],
    "sg:phone":"+1 213 387 6827",
    "sg:postcode":"90005",
    "sg:province":"CA",
    "sg:tags":[
        "counselor"
    ],
    "wof:name":"Design Concept GS",
    "wof:placetype":"venue"
},
  "geometry": {"coordinates":[-118.28710700000001,34.062762],"type":"Point"}
}