{
  "type": "Feature",
  "properties": {
    "addr:full":"16059 Kaplan Ave City Of Industry CA 91744",
    "addr:housenumber":"16059",
    "addr:postcode":"91744",
    "addr:street":"Kaplan Ave",
    "iso:country":"US",
    "sg:address":"16059 Kaplan Ave",
    "sg:city":"City Of Industry",
    "sg:classifiers":[
        {
            "category":"Autos & Motor Vehicles",
            "subcategory":"Auto Supplies",
            "type":"Retail Goods"
        }
    ],
    "sg:phone":"+1 626 968 5608",
    "sg:postcode":"91744",
    "sg:province":"CA",
    "sg:tags":[
        "automobile",
        "parts"
    ],
    "wof:name":"Wholesale Hyperformance",
    "wof:placetype":"venue"
},
  "geometry": {"coordinates":[-117.93515600000001,34.034877],"type":"Point"}
}