{
  "type": "Feature",
  "properties": {
    "addr:full":"375 Enterprise Way Tehachapi CA 93561",
    "addr:housenumber":"375",
    "addr:postcode":"93561",
    "addr:street":"Enterprise Way",
    "iso:country":"US",
    "sg:address":"375 Enterprise Way",
    "sg:city":"Tehachapi",
    "sg:classifiers":[
        {
            "category":"Retail",
            "subcategory":"Auto Repair",
            "type":"Services"
        }
    ],
    "sg:phone":"+1 661 822 5942",
    "sg:postcode":"93561",
    "sg:province":"CA",
    "sg:tags":[
        "wrecker"
    ],
    "wof:name":"Tehachapi Towing Svc",
    "wof:placetype":"venue"
},
  "geometry": {"coordinates":[-118.45435500000001,35.136047],"type":"Point"}
}