{
  "type": "Feature",
  "properties": {
    "iso:country":"US",
    "sg:address":"522 S Lorena St",
    "sg:city":"Los Angeles",
    "sg:classifiers":[
        {
            "category":"Restaurant",
            "type":"Food & Drink"
        }
    ],
    "sg:phone":"+1 323 881 9707",
    "sg:postcode":"90063",
    "sg:province":"CA",
    "wof:name":"El Jacalito",
    "wof:placetype":"venue"
},
  "geometry": {"coordinates":[-118.198077,34.032289],"type":"Point"}
}