{
  "type": "Feature",
  "properties": {
    "addr:full":"584 Castro St Ste 110 San Francisco CA 94114",
    "addr:housenumber":"584",
    "addr:postcode":"94114",
    "addr:street":"Castro St Ste 110",
    "iso:country":"US",
    "sg:address":"584 Castro St Ste 110",
    "sg:city":"San Francisco",
    "sg:classifiers":[
        {
            "category":"Shopping",
            "subcategory":"Party Supplies",
            "type":"Retail Goods"
        }
    ],
    "sg:phone":"+1 415 572 1472",
    "sg:postcode":"94114",
    "sg:province":"CA",
    "sg:website":"www.sparkysballoons.com",
    "wof:name":"Sparky's Balloons",
    "wof:placetype":"venue"
},
  "geometry": {"coordinates":[-122.435002,37.759577],"type":"Point"}
}