{
  "type": "Feature",
  "properties": {
    "addr:full":"2589 Nance Rd Imperial CA 92251",
    "addr:postcode":"2589;92251",
    "addr:street":"Nance Rd",
    "iso:country":"US",
    "sg:address":"2589 Nance Rd",
    "sg:city":"Imperial",
    "sg:classifiers":[
        {
            "category":"Building & Trades",
            "subcategory":"Plumbing",
            "type":"Services"
        }
    ],
    "sg:phone":"+1 760 355 2507",
    "sg:postcode":"92251",
    "sg:province":"CA",
    "sg:tags":[
        "tank",
        "septic"
    ],
    "wof:name":"DES Construction & Rental",
    "wof:placetype":"venue"
},
  "geometry": {"coordinates":[-115.586264,32.839938],"type":"Point"}
}