{
  "type": "Feature",
  "properties": {
    "iso:country":"US",
    "sg:address":"1017 K St",
    "sg:city":"Sacramento",
    "sg:classifiers":[
        {
            "category":"Restaurant",
            "type":"Food & Drink"
        }
    ],
    "sg:phone":"+1 916 444 2722",
    "sg:postcode":"95814",
    "sg:province":"CA",
    "wof:name":"Crest Cafe",
    "wof:placetype":"venue"
},
  "geometry": {"coordinates":[-121.49400300000001,38.5793],"type":"Point"}
}