{
  "type": "Feature",
  "properties": {
    "iso:country":"US",
    "sg:address":"1710 N Fuller Ave",
    "sg:city":"Los Angeles",
    "sg:classifiers":[
        {
            "category":"Professional",
            "type":"Services"
        }
    ],
    "sg:phone":"+1 323 874 7200",
    "sg:postcode":"90046",
    "sg:province":"CA",
    "sg:tags":[
        "establishment"
    ],
    "wof:name":"Iamg Apartmentime",
    "wof:placetype":"venue"
},
  "geometry": {"coordinates":[-118.34887,34.10325],"type":"Point"}
}