{
  "type": "Feature",
  "properties": {
    "addr:full":"2730 21st St San Francisco CA 94110",
    "addr:housenumber":"2730",
    "addr:postcode":"94110",
    "addr:street":"21St St",
    "iso:country":"US",
    "sg:address":"2730 21st St",
    "sg:city":"San Francisco",
    "sg:classifiers":[
        {
            "category":"Bars & Pubs",
            "subcategory":"Lounge",
            "type":"Food & Drink"
        },
        {
            "category":"Restaurant",
            "type":"Food & Drink"
        }
    ],
    "sg:phone":"+1 415 829 3375",
    "sg:postcode":"94110",
    "sg:province":"CA",
    "sg:website":"www.asientosf.com",
    "wof:name":"Asiento",
    "wof:placetype":"venue"
},
  "geometry": {"coordinates":[-122.409418,37.757622],"type":"Point"}
}