{
  "type": "Feature",
  "properties": {
    "iso:country":"US",
    "sg:address":"9706 Fair Oaks Blvd",
    "sg:city":"Fair Oaks",
    "sg:classifiers":[
        {
            "category":"Wholesale",
            "subcategory":"Sporting Goods",
            "type":"Manufacturing & Wholesale Goods"
        }
    ],
    "sg:phone":"+1 916 965 1790",
    "sg:postcode":"95628",
    "sg:province":"CA",
    "sg:tags":[
        "tackle",
        "fishing"
    ],
    "wof:name":"Western Hoegee Co",
    "wof:placetype":"venue"
},
  "geometry": {"coordinates":[-121.273505,38.639157],"type":"Point"}
}