{
  "type": "Feature",
  "properties": {
    "addr:full":"136 Willow St Redwood City CA 94063",
    "addr:housenumber":"136",
    "addr:postcode":"94063",
    "addr:street":"Willow St",
    "iso:country":"US",
    "sg:address":"136 Willow St",
    "sg:city":"Redwood City",
    "sg:classifiers":[
        {
            "category":"Freight",
            "type":"Transportation"
        }
    ],
    "sg:phone":"+1 650 365 0900",
    "sg:postcode":"94063",
    "sg:province":"CA",
    "sg:tags":[
        "general"
    ],
    "wof:name":"Stor-LL Storage",
    "wof:placetype":"venue"
},
  "geometry": {"coordinates":[-122.217889,37.477155],"type":"Point"}
}