{
  "type": "Feature",
  "properties": {
    "addr:full":"3111 Via Real Carpinteria CA 93013",
    "addr:housenumber":"3111",
    "addr:postcode":"93013",
    "addr:street":"Via Real",
    "iso:country":"US",
    "sg:address":"3111 Via Real",
    "sg:city":"Carpinteria",
    "sg:classifiers":[
        {
            "category":"Manufacturing",
            "subcategory":"Tools & Machinery",
            "type":"Manufacturing & Wholesale Goods"
        }
    ],
    "sg:phone":"+1 805 684 7146",
    "sg:postcode":"93013",
    "sg:province":"CA",
    "sg:tags":[
        "process",
        "control",
        "mfg",
        "instrument"
    ],
    "wof:name":"Timothy M Ranger",
    "wof:placetype":"venue"
},
  "geometry": {"coordinates":[-119.569355,34.416674],"type":"Point"}
}