{
  "type": "Feature",
  "properties": {
    "addr:full":"12525 Magnolia Blvd Valley Village CA 91607",
    "addr:housenumber":"12525",
    "addr:postcode":"91607",
    "addr:street":"Magnolia Blvd",
    "iso:country":"US",
    "sg:address":"12525 Magnolia Blvd",
    "sg:city":"Valley Village",
    "sg:classifiers":[
        {
            "category":"Health Services",
            "subcategory":"Chiropractor",
            "type":"Services"
        }
    ],
    "sg:phone":"+1 818 760 2786",
    "sg:postcode":"91607",
    "sg:province":"CA",
    "wof:name":"Metropolitan Back and Neck",
    "wof:placetype":"venue"
},
  "geometry": {"coordinates":[-118.405998,34.164799],"type":"Point"}
}