{
  "type": "Feature",
  "properties": {
    "addr:full":"6666 Meadowlark Ave Winton CA 95388",
    "addr:housenumber":"6666",
    "addr:postcode":"95388",
    "addr:street":"Meadowlark Ave",
    "iso:country":"US",
    "sg:address":"6666 Meadowlark Ave",
    "sg:city":"Winton",
    "sg:classifiers":[
        {
            "category":"Place Of Worship",
            "type":"Public Place"
        }
    ],
    "sg:phone":"+1 209 676 2295",
    "sg:postcode":"95388",
    "sg:province":"CA",
    "sg:tags":[
        "church"
    ],
    "wof:name":"Creek Pointe Church",
    "wof:placetype":"venue"
},
  "geometry": {"coordinates":[-120.61973500000001,37.384752],"type":"Point"}
}