{
  "type": "Feature",
  "properties": {
    "addr:full":"4730 H St Sheridan CA 95681",
    "addr:housenumber":"4730",
    "addr:postcode":"95681",
    "addr:street":"H St",
    "iso:country":"US",
    "sg:address":"4730 H St",
    "sg:city":"Sheridan",
    "sg:classifiers":[
        {
            "category":"Social Services",
            "subcategory":"Child Care",
            "type":"Services"
        }
    ],
    "sg:phone":"+1 530 633 9640",
    "sg:postcode":"95681",
    "sg:province":"CA",
    "sg:tags":[
        "nursery",
        "day"
    ],
    "wof:name":"Kids Count",
    "wof:placetype":"venue"
},
  "geometry": {"coordinates":[-121.372996,38.982719],"type":"Point"}
}