{
  "type": "Feature",
  "properties": {
    "iso:country":"US",
    "sg:address":"948 Santa Rosa St",
    "sg:city":"San Luis Obispo",
    "sg:classifiers":[
        {
            "category":"Professional",
            "subcategory":"Lawyer & Legal Services",
            "type":"Services"
        }
    ],
    "sg:phone":"+1 805 544 6565",
    "sg:postcode":"93401",
    "sg:province":"CA",
    "sg:tags":[
        "attorney"
    ],
    "wof:name":"Central Coast Divorce Mdtn",
    "wof:placetype":"venue"
},
  "geometry": {"coordinates":[-120.660347,35.283041],"type":"Point"}
}