{
  "type": "Feature",
  "properties": {
    "addr:full":"9767 Bus Park Dr Sacramento CA 95827",
    "addr:housenumber":"9767",
    "addr:postcode":"95827",
    "addr:street":"Bus Park Dr",
    "iso:country":"US",
    "sg:address":"9767 Bus Park Dr",
    "sg:city":"Sacramento",
    "sg:classifiers":[
        {
            "category":"Home & Garden",
            "subcategory":"Home Furnishings",
            "type":"Retail Goods"
        }
    ],
    "sg:phone":"+1 916 362 1800",
    "sg:postcode":"95827",
    "sg:province":"CA",
    "sg:tags":[
        "venetian",
        "blind",
        "drape"
    ],
    "wof:name":"Discount Best Blinds Inc",
    "wof:placetype":"venue"
},
  "geometry": {"coordinates":[-121.329427,38.570852],"type":"Point"}
}