{
  "type": "Feature",
  "properties": {
    "iso:country":"US",
    "sg:address":"811 el Capitan Way",
    "sg:city":"San Luis Obispo",
    "sg:classifiers":[
        {
            "category":"Organizations",
            "subcategory":"Professional Association",
            "type":"Services"
        }
    ],
    "sg:phone":"+1 805 546 0418",
    "sg:postcode":"93401",
    "sg:province":"CA",
    "sg:website":"www.hbacc.org",
    "wof:name":"Home Builders Assn-Central Cst",
    "wof:placetype":"venue"
},
  "geometry": {"coordinates":[-120.642,35.246653],"type":"Point"}
}