{
  "type": "Feature",
  "properties": {
    "iso:country":"US",
    "sg:address":"3360 Magnolia Ave",
    "sg:city":"Long Beach",
    "sg:classifiers":[
        {
            "category":"Health Services",
            "subcategory":"Nursing And Care Facility",
            "type":"Services"
        }
    ],
    "sg:phone":"+1 562 595 1559",
    "sg:postcode":"90806",
    "sg:province":"CA",
    "sg:tags":[
        "home",
        "retirement",
        "community"
    ],
    "wof:name":"Magnolia Royale Retirement Center",
    "wof:placetype":"venue"
},
  "geometry": {"coordinates":[-118.197998,33.8181],"type":"Point"}
}