{
  "type": "Feature",
  "properties": {
    "addr:full":"720 Capitola Ave Capitola CA 95010",
    "addr:housenumber":"720",
    "addr:postcode":"95010",
    "addr:street":"Capitola Ave",
    "iso:country":"US",
    "sg:address":"720 Capitola Ave",
    "sg:city":"Capitola",
    "sg:classifiers":[
        {
            "category":"Real Estate",
            "subcategory":"Real Estate Agent",
            "type":"Services"
        }
    ],
    "sg:phone":"+1 831 476 6195",
    "sg:postcode":"95010",
    "sg:province":"CA",
    "wof:name":"Bay Estates",
    "wof:placetype":"venue"
},
  "geometry": {"coordinates":[-121.95280700000001,36.979797],"type":"Point"}
}