{
  "type": "Feature",
  "properties": {
    "iso:country":"US",
    "sg:address":"401 W Radio Rd",
    "sg:city":"Palm Springs",
    "sg:classifiers":[
        {
            "category":"Building & Trades",
            "subcategory":"Electrical",
            "type":"Services"
        }
    ],
    "sg:phone":"+1 760 320 7778",
    "sg:postcode":"92262",
    "sg:province":"CA",
    "sg:tags":[
        "electrical",
        "contractor"
    ],
    "wof:name":"Klockenteger Electric",
    "wof:placetype":"venue"
},
  "geometry": {"coordinates":[-116.549752,33.862206],"type":"Point"}
}