{
  "type": "Feature",
  "properties": {
    "iso:country":"US",
    "sg:address":"11100 Sepulveda Blvd",
    "sg:city":"Mission Hills",
    "sg:classifiers":[
        {
            "category":"Shopping",
            "subcategory":"Computers & Home Electronics",
            "type":"Retail Goods"
        }
    ],
    "sg:phone":"+1 818 227 8020",
    "sg:postcode":"91345",
    "sg:province":"CA",
    "sg:tags":[
        "on",
        "store"
    ],
    "wof:name":"Ebargain Software",
    "wof:placetype":"venue"
},
  "geometry": {"coordinates":[-118.467582,34.272687],"type":"Point"}
}