{
  "type": "Feature",
  "properties": {
    "iso:country":"US",
    "sg:address":"9100 Wilshire Boulevard Suite 265 E",
    "sg:city":"Beverly Hills",
    "sg:classifiers":[
        {
            "category":"Health Services",
            "subcategory":"Optometrist",
            "type":"Services"
        }
    ],
    "sg:phone":"+1 310 274 1221",
    "sg:postcode":"90212",
    "sg:province":"CA",
    "sg:tags":[
        "ophthalmologist"
    ],
    "sg:website":"www.CasterVision.com",
    "wof:name":"Caster Eye Center Medical Group",
    "wof:placetype":"venue"
},
  "geometry": {"coordinates":[-118.389748,34.067114],"type":"Point"}
}