{
  "type": "Feature",
  "properties": {
    "iso:country":"US",
    "sg:address":"147 Beverly St",
    "sg:city":"San Francisco",
    "sg:classifiers":[
        {
            "category":"Wholesale",
            "subcategory":"Non-durable Goods",
            "type":"Manufacturing & Wholesale Goods"
        }
    ],
    "sg:phone":"+1 415 337 7700",
    "sg:postcode":"94132",
    "sg:province":"CA",
    "wof:name":"Vk Trading Co",
    "wof:placetype":"venue"
},
  "geometry": {"coordinates":[-122.47172,37.718811],"type":"Point"}
}