{
  "type": "Feature",
  "properties": {
    "addr:full":"9810 Owensmouth Ave Chatsworth CA 91311",
    "addr:housenumber":"9810",
    "addr:postcode":"91311",
    "addr:street":"Owensmouth Ave",
    "iso:country":"US",
    "sg:address":"9810 Owensmouth Ave",
    "sg:city":"Chatsworth",
    "sg:classifiers":[
        {
            "category":"Wholesale",
            "subcategory":"Non-durable Goods",
            "type":"Manufacturing & Wholesale Goods"
        }
    ],
    "sg:phone":"+1 818 993 0836",
    "sg:postcode":"91311",
    "sg:province":"CA",
    "wof:name":"Sunrise Distribution Corp",
    "wof:placetype":"venue"
},
  "geometry": {"coordinates":[-118.60159400000001,34.249782],"type":"Point"}
}