{
  "type": "Feature",
  "properties": {
    "addr:full":"5400 Ygnacio Valley Rd Concord CA 94521",
    "addr:housenumber":"5400",
    "addr:postcode":"94521",
    "addr:street":"Ygnacio Valley Rd",
    "iso:country":"US",
    "sg:address":"5400 Ygnacio Valley Rd",
    "sg:city":"Concord",
    "sg:classifiers":[
        {
            "category":"Restaurant",
            "type":"Food & Drink"
        }
    ],
    "sg:menulink":"http://www.allmenus.com/ca/central-contra-costa/172149-burger-king/menu/",
    "sg:phone":"+1 925 672 6090",
    "sg:postcode":"94521",
    "sg:province":"CA",
    "sg:tags":[
        "burger",
        "american"
    ],
    "wof:name":"Burger King",
    "wof:placetype":"venue"
},
  "geometry": {"coordinates":[-121.95723099999999,37.951653],"type":"Point"}
}