{
  "type": "Feature",
  "properties": {
    "addr:full":"1020 15th St Modesto CA 95354",
    "addr:housenumber":"1020",
    "addr:postcode":"ca 95354",
    "addr:street":"15Th St",
    "iso:country":"US",
    "sg:address":"1020 15th St",
    "sg:city":"Modesto",
    "sg:classifiers":[
        {
            "category":"Professional",
            "subcategory":"Accounting & Tax Preparation",
            "type":"Services"
        }
    ],
    "sg:phone":"+1 209 529 4060",
    "sg:postcode":"95354",
    "sg:province":"CA",
    "sg:tags":[
        "accountant"
    ],
    "sg:website":"www.shollingsworth.com",
    "wof:name":"Hollingsworth Sue CPA",
    "wof:placetype":"venue"
},
  "geometry": {"coordinates":[-120.99610800000001,37.64476],"type":"Point"}
}