{
  "type": "Feature",
  "properties": {
    "iso:country":"US",
    "sg:address":"119 N China Lake Blvd",
    "sg:city":"Ridgecrest",
    "sg:classifiers":[
        {
            "category":"Restaurant",
            "type":"Food & Drink"
        }
    ],
    "sg:phone":"+1 760 375 5901",
    "sg:postcode":"93555",
    "sg:province":"CA",
    "wof:name":"LA Fiesta Sandwiches & Things",
    "wof:placetype":"venue"
},
  "geometry": {"coordinates":[-117.670086,35.622727],"type":"Point"}
}