{
  "type": "Feature",
  "properties": {
    "addr:full":"706 Oak St Bakersfield CA 93304",
    "addr:housenumber":"706",
    "addr:postcode":"93304",
    "addr:street":"Oak St",
    "iso:country":"US",
    "sg:address":"706 Oak St",
    "sg:city":"Bakersfield",
    "sg:classifiers":[
        {
            "category":"Arts & Performance",
            "subcategory":"Theater",
            "type":"Entertainment"
        }
    ],
    "sg:phone":"+1 661 327 7529",
    "sg:postcode":"93304",
    "sg:province":"CA",
    "wof:name":"Empty Space",
    "wof:placetype":"venue"
},
  "geometry": {"coordinates":[-119.03871700000001,35.364085],"type":"Point"}
}