{
  "type": "Feature",
  "properties": {
    "addr:full":"3452 Argyle Rd Redding CA 96002",
    "addr:housenumber":"3452",
    "addr:postcode":"96002",
    "addr:street":"Argyle Rd",
    "iso:country":"US",
    "sg:address":"3452 Argyle Rd",
    "sg:city":"Redding",
    "sg:classifiers":[
        {
            "category":"Recreation",
            "type":"Entertainment"
        }
    ],
    "sg:phone":"+1 530 221 4405",
    "sg:postcode":"96002",
    "sg:province":"CA",
    "sg:tags":[
        "tennis",
        "court"
    ],
    "wof:name":"Sun Oaks Tennis & Fitness",
    "wof:placetype":"venue"
},
  "geometry": {"coordinates":[-122.30473600000001,40.556091],"type":"Point"}
}