{
  "type": "Feature",
  "properties": {
    "addr:full":"4141 Camino De La Plz San Diego CA 92173",
    "addr:housenumber":"4141",
    "addr:postcode":"92173",
    "addr:street":"Camino De La Plz",
    "iso:country":"US",
    "sg:address":"4141 Camino De La Plz",
    "sg:city":"San Diego",
    "sg:classifiers":[
        {
            "category":"Shopping",
            "subcategory":"Department Store",
            "type":"Retail Goods"
        }
    ],
    "sg:phone":"+1 619 428 6800",
    "sg:postcode":"92173",
    "sg:province":"CA",
    "wof:name":"Hugo Boss Inc.",
    "wof:placetype":"venue"
},
  "geometry": {"coordinates":[-117.043432,32.545448],"type":"Point"}
}