{
  "type": "Feature",
  "properties": {
    "iso:country":"US",
    "sg:address":"6608 Pacheco Way",
    "sg:city":"Citrus Heights",
    "sg:classifiers":[
        {
            "category":"Shopping",
            "subcategory":"Books",
            "type":"Retail Goods"
        }
    ],
    "sg:phone":"+1 916 722 8942",
    "sg:postcode":"95610",
    "sg:province":"CA",
    "sg:tags":[
        "dealer"
    ],
    "wof:name":"Mr Dickens Books & Video",
    "wof:placetype":"venue"
},
  "geometry": {"coordinates":[-121.275122,38.687886],"type":"Point"}
}