{
  "type": "Feature",
  "properties": {
    "addr:full":"8 E Figueroa St Santa Barbara CA 93101",
    "addr:housenumber":"8",
    "addr:postcode":"93101",
    "addr:street":"E Figueroa St",
    "iso:country":"US",
    "sg:address":"8 E Figueroa St",
    "sg:city":"Santa Barbara",
    "sg:classifiers":[
        {
            "category":"Banks & Credit Unions",
            "subcategory":"Bank",
            "type":"Services"
        }
    ],
    "sg:phone":"+1 805 963 1410",
    "sg:postcode":"93101",
    "sg:province":"CA",
    "wof:name":"Bank Of The West",
    "wof:placetype":"venue"
},
  "geometry": {"coordinates":[-119.70202999999999,34.423374],"type":"Point"}
}