{
  "type": "Feature",
  "properties": {
    "addr:full":"4656 S Pedersen Ave Reedley CA 93654",
    "addr:housenumber":"4656",
    "addr:postcode":"93654",
    "addr:street":"S Pedersen Ave",
    "iso:country":"US",
    "sg:address":"4656 S Pedersen Ave",
    "sg:city":"Reedley",
    "sg:classifiers":[
        {
            "category":"Professional",
            "type":"Services"
        }
    ],
    "sg:phone":"+1 559 638 1507",
    "sg:postcode":"93654",
    "sg:province":"CA",
    "wof:name":"Steve Boos",
    "wof:placetype":"venue"
},
  "geometry": {"coordinates":[-119.40351699999999,36.661978],"type":"Point"}
}