{
  "type": "Feature",
  "properties": {
    "iso:country":"US",
    "sg:address":"33921 Lake Breeze Dr",
    "sg:city":"Yucaipa",
    "sg:classifiers":[
        {
            "category":"Professional",
            "type":"Services"
        }
    ],
    "sg:phone":"+1 909 790 5960",
    "sg:postcode":"92399",
    "sg:province":"CA",
    "sg:tags":[
        "transportation"
    ],
    "wof:name":"Mario Perez",
    "wof:placetype":"venue"
},
  "geometry": {"coordinates":[-117.06427499999999,34.036862],"type":"Point"}
}