{
  "type": "Feature",
  "properties": {
    "addr:full":"375 Macarthur Blvd San Leandro CA 94577",
    "addr:housenumber":"375",
    "addr:postcode":"94577",
    "addr:street":"Macarthur Blvd",
    "iso:country":"US",
    "sg:address":"375 Macarthur Blvd",
    "sg:city":"San Leandro",
    "sg:classifiers":[
        {
            "category":"Professional",
            "type":"Services"
        }
    ],
    "sg:phone":"+1 510 639 9225",
    "sg:postcode":"94577",
    "sg:province":"CA",
    "wof:name":"Glory Hallelujah Only 99 Cents",
    "wof:placetype":"venue"
},
  "geometry": {"coordinates":[-122.145731,37.739392],"type":"Point"}
}