{
  "type": "Feature",
  "properties": {
    "addr:full":"6428 Terraza Portico Carlsbad CA 92009",
    "addr:housenumber":"6428",
    "addr:postcode":"92009",
    "addr:street":"Terraza Portico",
    "iso:country":"US",
    "sg:address":"6428 Terraza Portico",
    "sg:city":"Carlsbad",
    "sg:classifiers":[
        {
            "category":"Real Estate",
            "subcategory":"Real Estate Services",
            "type":"Services"
        },
        {
            "category":"Real Estate",
            "subcategory":"Real Estate Agent",
            "type":"Services"
        }
    ],
    "sg:phone":"+1 760 431 7788",
    "sg:postcode":"92009",
    "sg:province":"CA",
    "sg:tags":[
        "management"
    ],
    "wof:name":"Inc United Investm",
    "wof:placetype":"venue"
},
  "geometry": {"coordinates":[-117.232846,33.114646],"type":"Point"}
}