{
  "type": "Feature",
  "properties": {
    "addr:full":"13001 Garden Grove Blvd Garden Grove CA 92843",
    "addr:housenumber":"13001",
    "addr:postcode":"92843",
    "addr:street":"Garden Grove Blvd",
    "iso:country":"US",
    "sg:address":"13001 Garden Grove Blvd",
    "sg:city":"Garden Grove",
    "sg:classifiers":[
        {
            "category":"Government",
            "subcategory":"Office",
            "type":"Public Place"
        }
    ],
    "sg:phone":"+1 714 971 2421",
    "sg:postcode":"92843",
    "sg:province":"CA",
    "sg:tags":[
        "general"
    ],
    "wof:name":"Vestor Control",
    "wof:placetype":"venue"
},
  "geometry": {"coordinates":[-117.90477,33.774438],"type":"Point"}
}