{
  "type": "Feature",
  "properties": {
    "iso:country":"US",
    "sg:address":"937 N Harbor Dr",
    "sg:city":"San Diego",
    "sg:classifiers":[
        {
            "category":"Government",
            "subcategory":"Office",
            "type":"Public Place"
        }
    ],
    "sg:phone":"+1 619 532 1430",
    "sg:postcode":"92106",
    "sg:province":"CA",
    "sg:tags":[
        "national",
        "security"
    ],
    "wof:name":"Public Affairs",
    "wof:placetype":"venue"
},
  "geometry": {"coordinates":[-117.17304900000001,32.714128],"type":"Point"}
}