{
  "type": "Feature",
  "properties": {
    "addr:full":"841 Marina Village Pkwy Alameda CA 94501",
    "addr:housenumber":"841",
    "addr:postcode":"94501",
    "addr:street":"Marina Village Pkwy",
    "iso:country":"US",
    "sg:address":"841 Marina Village Pkwy",
    "sg:city":"Alameda",
    "sg:classifiers":[
        {
            "category":"Shopping",
            "type":"Retail Goods"
        }
    ],
    "sg:phone":"+1 510 523 8028",
    "sg:postcode":"94501",
    "sg:province":"CA",
    "sg:tags":[
        "telephone",
        "cellular"
    ],
    "wof:name":"Wireless World",
    "wof:placetype":"venue"
},
  "geometry": {"coordinates":[-122.274466,37.783084],"type":"Point"}
}