{
  "type": "Feature",
  "properties": {
    "iso:country":"US",
    "sg:address":"6410 Van Nuys Blvd",
    "sg:city":"Van Nuys",
    "sg:classifiers":[
        {
            "category":"Professional",
            "subcategory":"Lawyer & Legal Services",
            "type":"Services"
        }
    ],
    "sg:phone":"+1 818 340 4640",
    "sg:postcode":"91401",
    "sg:province":"CA",
    "sg:tags":[
        "divorce",
        "assistance"
    ],
    "wof:name":"Public Paralegal Svc",
    "wof:placetype":"venue"
},
  "geometry": {"coordinates":[-118.44864,34.187444],"type":"Point"}
}