{
  "type": "Feature",
  "properties": {
    "addr:full":"1039 el Monte Ave Mountain View CA 94040",
    "addr:housenumber":"1039",
    "addr:postcode":"94040",
    "addr:street":"El Monte Ave",
    "iso:country":"US",
    "sg:address":"1039 el Monte Ave",
    "sg:city":"Mountain View",
    "sg:classifiers":[
        {
            "category":"Manufacturing",
            "subcategory":"Printing",
            "type":"Manufacturing & Wholesale Goods"
        }
    ],
    "sg:phone":"+1 650 965 3600",
    "sg:postcode":"94040",
    "sg:province":"CA",
    "sg:tags":[
        "lithographic",
        "printer",
        "commercial"
    ],
    "wof:name":"Minuteman Press",
    "wof:placetype":"venue"
},
  "geometry": {"coordinates":[-122.09580800000001,37.390138],"type":"Point"}
}