{
  "type": "Feature",
  "properties": {
    "iso:country":"US",
    "sg:address":"1209 2nd St",
    "sg:city":"San Rafael",
    "sg:classifiers":[
        {
            "category":"Manufacturing",
            "subcategory":"Printing",
            "type":"Manufacturing & Wholesale Goods"
        }
    ],
    "sg:phone":"+1 415 453 8383",
    "sg:postcode":"94901",
    "sg:province":"CA",
    "sg:tags":[
        "publishing"
    ],
    "wof:name":"Calico Graphics",
    "wof:placetype":"venue"
},
  "geometry": {"coordinates":[-122.530974,37.971345],"type":"Point"}
}