{
  "type": "Feature",
  "properties": {
    "addr:full":"340 Knight Dr San Rafael CA 94901",
    "addr:housenumber":"340",
    "addr:postcode":"94901",
    "addr:street":"Knight Dr",
    "iso:country":"US",
    "sg:address":"340 Knight Dr",
    "sg:city":"San Rafael",
    "sg:classifiers":[
        {
            "category":"Retail",
            "subcategory":"Portrait Studio",
            "type":"Services"
        }
    ],
    "sg:phone":"+1 415 454 0839",
    "sg:postcode":"94901",
    "sg:province":"CA",
    "sg:tags":[
        "photographer"
    ],
    "wof:name":"Bruce Burtch Photography",
    "wof:placetype":"venue"
},
  "geometry": {"coordinates":[-122.480248,37.992099],"type":"Point"}
}