{
  "type": "Feature",
  "properties": {
    "iso:country":"US",
    "sg:address":"3294 Bechelli Ln",
    "sg:city":"Redding",
    "sg:classifiers":[
        {
            "category":"Real Estate",
            "subcategory":"Real Estate Agent",
            "type":"Services"
        }
    ],
    "sg:phone":"+1 530 222 6600",
    "sg:postcode":"96002",
    "sg:province":"CA",
    "wof:name":"Sal Curato Realty & Prop Mgmt",
    "wof:placetype":"venue"
},
  "geometry": {"coordinates":[-122.362712,40.560944],"type":"Point"}
}