{
  "type": "Feature",
  "properties": {
    "addr:full":"The District at Tustin Legacy 2427 Park Ave Tustin CA 92782",
    "addr:housenumber":"2427",
    "addr:postcode":"92782",
    "addr:street":"Park Ave",
    "iso:country":"US",
    "sg:address":"The District at Tustin Legacy 2427 Park Ave",
    "sg:city":"Tustin",
    "sg:classifiers":[
        {
            "category":"Fast Food",
            "type":"Food & Drink"
        }
    ],
    "sg:phone":"+1 714 259 1162",
    "sg:postcode":"92782",
    "sg:province":"CA",
    "sg:tags":[
        "burger"
    ],
    "sg:website":"www.johnnyrockets.com",
    "wof:name":"Johnny Rockets",
    "wof:placetype":"venue"
},
  "geometry": {"coordinates":[-117.82864600000001,33.700198],"type":"Point"}
}