{
  "type": "Feature",
  "properties": {
    "iso:country":"US",
    "sg:address":"356 S Indian Canyon Dr",
    "sg:city":"Palm Springs",
    "sg:classifiers":[
        {
            "category":"Restaurant",
            "type":"Food & Drink"
        }
    ],
    "sg:phone":"+1 760 327 2036",
    "sg:postcode":"92262",
    "sg:province":"CA",
    "sg:tags":[
        "scandinavian"
    ],
    "wof:name":"Cafe Scandia",
    "wof:placetype":"venue"
},
  "geometry": {"coordinates":[-116.545568,33.818783],"type":"Point"}
}