{
  "type": "Feature",
  "properties": {
    "addr:full":"13500 Whittier Blvd Whittier CA 90605",
    "addr:housenumber":"13500",
    "addr:postcode":"90605",
    "addr:street":"Whittier Blvd",
    "iso:country":"US",
    "sg:address":"13500 Whittier Blvd",
    "sg:city":"Whittier",
    "sg:classifiers":[
        {
            "category":"Restaurant",
            "type":"Food & Drink"
        }
    ],
    "sg:menulink":"http://www.allmenus.com/ca/whittier/14164-olive-garden-italian-restaurant/menu/",
    "sg:phone":"+1 562 693 5999",
    "sg:postcode":"90605",
    "sg:province":"CA",
    "sg:tags":[
        "italian"
    ],
    "wof:name":"Olive Garden Italian Restaurant",
    "wof:placetype":"venue"
},
  "geometry": {"coordinates":[-118.030905,33.961599],"type":"Point"}
}