{
  "type": "Feature",
  "properties": {
    "addr:full":"26 Tamalpais Dr Corte Madera CA 94925",
    "addr:housenumber":"26",
    "addr:postcode":"94925",
    "addr:street":"Tamalpais Dr",
    "iso:country":"US",
    "sg:address":"26 Tamalpais Dr",
    "sg:city":"Corte Madera",
    "sg:classifiers":[
        {
            "category":"Personal",
            "subcategory":"Beauty Salon",
            "type":"Services"
        }
    ],
    "sg:phone":"+1 415 924 7300",
    "sg:postcode":"94925",
    "sg:province":"CA",
    "sg:tags":[
        "spa",
        "day"
    ],
    "wof:name":"Stellar Spa",
    "wof:placetype":"venue"
},
  "geometry": {"coordinates":[-122.529246,37.926376],"type":"Point"}
}