{
  "type": "Feature",
  "properties": {
    "addr:full":"23021 Normandie Ave Torrance CA 90501",
    "addr:housenumber":"23021",
    "addr:postcode":"90501",
    "addr:street":"Normandie Ave",
    "iso:country":"US",
    "sg:address":"23021 Normandie Ave",
    "sg:city":"Torrance",
    "sg:classifiers":[
        {
            "category":"Wholesale",
            "subcategory":"Machinery & Supplies",
            "type":"Manufacturing & Wholesale Goods"
        }
    ],
    "sg:phone":"+1 310 891 0862",
    "sg:postcode":"90501",
    "sg:province":"CA",
    "sg:tags":[
        "equipment",
        "industrial"
    ],
    "wof:name":"Grainger Inc",
    "wof:placetype":"venue"
},
  "geometry": {"coordinates":[-118.29824600000001,33.817361],"type":"Point"}
}