{
  "type": "Feature",
  "properties": {
    "addr:full":"100 el Dorado Vallejo CA 94590",
    "addr:housenumber":"100",
    "addr:postcode":"94590",
    "addr:street":"El Dorado",
    "iso:country":"US",
    "sg:address":"100 el Dorado",
    "sg:city":"Vallejo",
    "sg:classifiers":[
        {
            "category":"Building & Trades",
            "subcategory":"Construction",
            "type":"Services"
        }
    ],
    "sg:phone":"+1 510 223 1279",
    "sg:postcode":"94590",
    "sg:province":"CA",
    "sg:tags":[
        "fire",
        "restoration",
        "damage"
    ],
    "wof:name":"Advanced Recovery Corp",
    "wof:placetype":"venue"
},
  "geometry": {"coordinates":[-122.250016,38.097052],"type":"Point"}
}