{
  "type": "Feature",
  "properties": {
    "iso:country":"US",
    "sg:address":"636 San Mateo Ave",
    "sg:city":"San Bruno",
    "sg:classifiers":[
        {
            "category":"Organizations",
            "subcategory":"Non-profit Organization",
            "type":"Services"
        }
    ],
    "sg:phone":"+1 650 952 9513",
    "sg:postcode":"94066",
    "sg:province":"CA",
    "sg:tags":[
        "religious"
    ],
    "wof:name":"Purple Lotus Society of USA",
    "wof:placetype":"venue"
},
  "geometry": {"coordinates":[-122.41100299999999,37.627201],"type":"Point"}
}