{
  "type": "Feature",
  "properties": {
    "addr:full":"1470 Via Codorniz San Jose CA 95128",
    "addr:housenumber":"1470",
    "addr:postcode":"95128",
    "addr:street":"Via Codorniz",
    "iso:country":"US",
    "sg:address":"1470 Via Codorniz",
    "sg:city":"San Jose",
    "sg:classifiers":[
        {
            "category":"Organizations",
            "subcategory":"Membership Organization",
            "type":"Services"
        }
    ],
    "sg:phone":"+1 408 345 9657",
    "sg:postcode":"95128",
    "sg:province":"CA",
    "sg:tags":[
        "athletic"
    ],
    "wof:name":"USA All Stars",
    "wof:placetype":"venue"
},
  "geometry": {"coordinates":[-121.938258,37.296429],"type":"Point"}
}