{
  "type": "Feature",
  "properties": {
    "addr:full":"2412 Cohasset Rd Chico CA 95926",
    "addr:postcode":"2412;95926",
    "addr:street":"Cohasset Rd",
    "iso:country":"US",
    "sg:address":"2412 Cohasset Rd",
    "sg:city":"Chico",
    "sg:classifiers":[
        {
            "category":"Education",
            "subcategory":"School",
            "type":"Public Place"
        }
    ],
    "sg:phone":"+1 530 895 4185",
    "sg:postcode":"95926",
    "sg:province":"CA",
    "wof:name":"Chico Unified School District Alternative Schools",
    "wof:placetype":"venue"
},
  "geometry": {"coordinates":[-121.843559,39.758781],"type":"Point"}
}