{
  "type": "Feature",
  "properties": {
    "addr:full":"1515 Hotel Cir S San Diego CA 92108",
    "addr:housenumber":"1515",
    "addr:postcode":"92108",
    "addr:street":"Hotel Cir S",
    "iso:country":"US",
    "sg:address":"1515 Hotel Cir S",
    "sg:city":"San Diego",
    "sg:classifiers":[
        {
            "category":"Travel",
            "subcategory":"Hotels & Motels",
            "type":"Entertainment"
        }
    ],
    "sg:phone":"+1 619 298 0732",
    "sg:postcode":"92108",
    "sg:province":"CA",
    "wof:name":"Tarsadia Hotels",
    "wof:placetype":"venue"
},
  "geometry": {"coordinates":[-117.183702,32.759103],"type":"Point"}
}