{
  "type": "Feature",
  "properties": {
    "addr:full":"1801 Logan Ave San Diego CA 92113",
    "addr:housenumber":"1801",
    "addr:postcode":"92113",
    "addr:street":"Logan Ave",
    "iso:country":"US",
    "sg:address":"1801 Logan Ave",
    "sg:city":"San Diego",
    "sg:classifiers":[
        {
            "category":"Travel",
            "subcategory":"Hotels & Motels",
            "type":"Entertainment"
        }
    ],
    "sg:phone":"+1 619 232 1616",
    "sg:postcode":"92113",
    "sg:province":"CA",
    "sg:website":"www.valueinnsandiego.com",
    "wof:name":"America's Best Value Inn",
    "wof:placetype":"venue"
},
  "geometry": {"coordinates":[-117.145923,32.702253],"type":"Point"}
}