{
  "type": "Feature",
  "properties": {
    "iso:country":"US",
    "sg:address":"3651 Via Bernardo",
    "sg:city":"Oceanside",
    "sg:classifiers":[
        {
            "category":"Science Facility",
            "type":"Public Place"
        }
    ],
    "sg:phone":"+1 760 941 7424",
    "sg:postcode":"92056",
    "sg:province":"CA",
    "sg:tags":[
        "development",
        "laboratories-research"
    ],
    "wof:name":"Pacific Blue Innovations",
    "wof:placetype":"venue"
},
  "geometry": {"coordinates":[-117.253032,33.167534],"type":"Point"}
}