{
  "type": "Feature",
  "properties": {
    "addr:full":"890 Berry Ave Los Altos CA 94024",
    "addr:housenumber":"890",
    "addr:postcode":"94024",
    "addr:street":"Berry Ave",
    "iso:country":"US",
    "sg:address":"890 Berry Ave",
    "sg:city":"Los Altos",
    "sg:classifiers":[
        {
            "category":"Social Services",
            "subcategory":"Adult Care",
            "type":"Services"
        }
    ],
    "sg:phone":"+1 650 254 0721",
    "sg:postcode":"94024",
    "sg:province":"CA",
    "sg:tags":[
        "home",
        "residential"
    ],
    "wof:name":"Hidden Lane Villa",
    "wof:placetype":"venue"
},
  "geometry": {"coordinates":[-122.090733,37.361395],"type":"Point"}
}