{
  "type": "Feature",
  "properties": {
    "addr:full":"71446 Highway 111 Rancho Mirage CA 92270",
    "addr:housenumber":"71446",
    "addr:postcode":"92270",
    "addr:street":"Highway 111",
    "iso:country":"US",
    "sg:address":"71446 Highway 111",
    "sg:city":"Rancho Mirage",
    "sg:classifiers":[
        {
            "category":"Retail",
            "subcategory":"Auto Repair",
            "type":"Services"
        }
    ],
    "sg:phone":"+1 760 346 1904",
    "sg:postcode":"92270",
    "sg:province":"CA",
    "sg:tags":[
        "body",
        "shop"
    ],
    "wof:name":"Emmons Duncan",
    "wof:placetype":"venue"
},
  "geometry": {"coordinates":[-116.416,33.745399],"type":"Point"}
}