{
  "type": "Feature",
  "properties": {
    "iso:country":"US",
    "sg:address":"721 S Parker St",
    "sg:city":"Orange",
    "sg:classifiers":[
        {
            "category":"Insurance",
            "subcategory":"Insurance Agent",
            "type":"Services"
        }
    ],
    "sg:phone":"+1 714 542 4200",
    "sg:postcode":"92868",
    "sg:province":"CA",
    "wof:name":"Californiachoice",
    "wof:placetype":"venue"
},
  "geometry": {"coordinates":[-117.859515,33.776756],"type":"Point"}
}