{
  "type": "Feature",
  "properties": {
    "addr:full":"5566 Gage Avenue Bell Gardens CA 90201",
    "addr:housenumber":"5566",
    "addr:postcode":"90201",
    "addr:street":"Gage Avenue",
    "iso:country":"US",
    "sg:address":"5566 Gage Avenue",
    "sg:city":"Bell Gardens",
    "sg:classifiers":[
        {
            "category":"Home & Garden",
            "subcategory":"Furniture",
            "type":"Retail Goods"
        }
    ],
    "sg:phone":"+1 562 740 3787",
    "sg:postcode":"90201",
    "sg:province":"CA",
    "sg:tags":[
        "store"
    ],
    "wof:name":"Forest Furniture",
    "wof:placetype":"venue"
},
  "geometry": {"coordinates":[-118.16548899999999,33.975533],"type":"Point"}
}