{
  "type": "Feature",
  "properties": {
    "iso:country":"US",
    "sg:address":"8573 Garden Grove Blvd",
    "sg:city":"Garden Grove",
    "sg:classifiers":[
        {
            "category":"Building & Trades",
            "subcategory":"Cleaning & Sanitation",
            "type":"Services"
        }
    ],
    "sg:phone":"+1 714 534 6721",
    "sg:postcode":"92844",
    "sg:province":"CA",
    "sg:tags":[
        "carpet"
    ],
    "wof:name":"Orange Coast Carpet & Upholstery Cleaning",
    "wof:placetype":"venue"
},
  "geometry": {"coordinates":[-117.983002,33.773998],"type":"Point"}
}