{
  "type": "Feature",
  "properties": {
    "iso:country":"US",
    "sg:address":"2660 River Ave",
    "sg:city":"Rosemead",
    "sg:classifiers":[
        {
            "category":"Building & Trades",
            "subcategory":"Construction",
            "type":"Services"
        }
    ],
    "sg:phone":"+1 626 571 1999",
    "sg:postcode":"91770",
    "sg:province":"CA",
    "sg:tags":[
        "resurfacing",
        "laying",
        "refinishing",
        "floor"
    ],
    "wof:name":"Professional Flooring",
    "wof:placetype":"venue"
},
  "geometry": {"coordinates":[-118.073036,34.060755],"type":"Point"}
}