{
  "type": "Feature",
  "properties": {
    "addr:full":"11103 Paramount Blvd Downey CA 90241",
    "addr:housenumber":"11103",
    "addr:postcode":"90241",
    "addr:street":"Paramount Blvd",
    "iso:country":"US",
    "sg:address":"11103 Paramount Blvd",
    "sg:city":"Downey",
    "sg:classifiers":[
        {
            "category":"Retail",
            "subcategory":"Auto Repair",
            "type":"Services"
        }
    ],
    "sg:phone":"+1 562 869 7778",
    "sg:postcode":"90241",
    "sg:province":"CA",
    "wof:name":"Pardella's Automotive Repair Service",
    "wof:placetype":"venue"
},
  "geometry": {"coordinates":[-118.137001,33.943401],"type":"Point"}
}