{
  "type": "Feature",
  "properties": {
    "addr:full":"27051 Robert C Lee Pkwy Santa Clarita CA 91350",
    "addr:housenumber":"27051",
    "addr:postcode":"91350",
    "addr:street":"Robert C Lee Pkwy",
    "iso:country":"US",
    "sg:address":"27051 Robert C Lee Pkwy",
    "sg:city":"Santa Clarita",
    "sg:classifiers":[
        {
            "category":"Education",
            "subcategory":"Preschool",
            "type":"Public Place"
        },
        {
            "category":"Education",
            "subcategory":"School",
            "type":"Public Place"
        }
    ],
    "sg:phone":"+1 661 298 8140",
    "sg:postcode":"91350",
    "sg:province":"CA",
    "sg:tags":[
        "elementary"
    ],
    "sg:website":"www.hart.k12.ca.us",
    "wof:name":"Golden Valley High School",
    "wof:placetype":"venue"
},
  "geometry": {"coordinates":[-118.491642,34.399562],"type":"Point"}
}