{
  "type": "Feature",
  "properties": {
    "iso:country":"US",
    "sg:address":"520 N Prospect Ave",
    "sg:city":"Redondo Beach",
    "sg:classifiers":[
        {
            "category":"Health Services",
            "subcategory":"Medical Lab",
            "type":"Services"
        }
    ],
    "sg:phone":"+1 310 376 4830",
    "sg:postcode":"90277",
    "sg:province":"CA",
    "sg:tags":[
        "laboratory"
    ],
    "wof:name":"Quest Diagnostics Inc",
    "wof:placetype":"venue"
},
  "geometry": {"coordinates":[-118.38166,33.853961],"type":"Point"}
}