{
  "type": "Feature",
  "properties": {
    "iso:country":"US",
    "sg:address":"452 Veile Ave",
    "sg:city":"Beaumont",
    "sg:classifiers":[
        {
            "category":"Wholesale",
            "subcategory":"Motor Vehicles",
            "type":"Manufacturing & Wholesale Goods"
        }
    ],
    "sg:phone":"+1 951 769 0092",
    "sg:postcode":"92223",
    "sg:province":"CA",
    "sg:tags":[
        "automobile",
        "truck",
        "broker"
    ],
    "wof:name":"D & R Auto Brokers",
    "wof:placetype":"venue"
},
  "geometry": {"coordinates":[-116.98820499999999,33.92731],"type":"Point"}
}