{
  "type": "Feature",
  "properties": {
    "iso:country":"US",
    "sg:address":"10170 Main St",
    "sg:city":"Potter Valley",
    "sg:classifiers":[
        {
            "category":"Utilities",
            "subcategory":"Water",
            "type":"Services"
        }
    ],
    "sg:phone":"+1 707 743 1109",
    "sg:postcode":"95469",
    "sg:province":"CA",
    "sg:tags":[
        "company",
        "sewage",
        "supply"
    ],
    "wof:name":"Potter Valley Irrigation Dist",
    "wof:placetype":"venue"
},
  "geometry": {"coordinates":[-123.109686,39.321917],"type":"Point"}
}