{
  "type": "Feature",
  "properties": {
    "addr:full":"5151 N Palm Ave Fresno CA 93704",
    "addr:housenumber":"5151",
    "addr:postcode":"93704",
    "addr:street":"N Palm Ave",
    "iso:country":"US",
    "sg:address":"5151 N Palm Ave",
    "sg:city":"Fresno",
    "sg:classifiers":[
        {
            "category":"Health Services",
            "subcategory":"Doctor",
            "type":"Services"
        }
    ],
    "sg:phone":"+1 559 221 8814",
    "sg:postcode":"93704",
    "sg:province":"CA",
    "sg:tags":[
        "physician",
        "surgeon"
    ],
    "wof:name":"Thomas R Callahan MD",
    "wof:placetype":"venue"
},
  "geometry": {"coordinates":[-119.80849000000001,36.809208],"type":"Point"}
}