{
  "type": "Feature",
  "properties": {
    "addr:full":"2836 Foothill Blvd Oakland CA 94601",
    "addr:housenumber":"2836",
    "addr:postcode":"94601",
    "addr:street":"Foothill Blvd",
    "iso:country":"US",
    "sg:address":"2836 Foothill Blvd",
    "sg:city":"Oakland",
    "sg:classifiers":[
        {
            "category":"Real Estate",
            "subcategory":"Real Estate Services",
            "type":"Services"
        },
        {
            "category":"Real Estate",
            "subcategory":"Real Estate Agent",
            "type":"Services"
        }
    ],
    "sg:phone":"+1 510 261 0530",
    "sg:postcode":"94601",
    "sg:province":"CA",
    "sg:tags":[
        "management"
    ],
    "wof:name":"Us Realty",
    "wof:placetype":"venue"
},
  "geometry": {"coordinates":[-122.225145,37.784345],"type":"Point"}
}