{
  "type": "Feature",
  "properties": {
    "addr:full":"2490 Arnold Industrial Way Concord CA 94520",
    "addr:housenumber":"2490",
    "addr:postcode":"94520",
    "addr:street":"Arnold Industrial Way",
    "iso:country":"US",
    "sg:address":"2490 Arnold Industrial Way",
    "sg:city":"Concord",
    "sg:classifiers":[
        {
            "category":"Wholesale",
            "subcategory":"Medical Equipment & Supplies",
            "type":"Manufacturing & Wholesale Goods"
        },
        {
            "category":"Real Estate",
            "subcategory":"Real Estate Services",
            "type":"Services"
        },
        {
            "category":"Banks & Credit Unions",
            "subcategory":"Financial Services",
            "type":"Services"
        },
        {
            "category":"Health Services",
            "subcategory":"Dentist",
            "type":"Services"
        }
    ],
    "sg:phone":"+1 925 356 0661",
    "sg:postcode":"94520",
    "sg:province":"CA",
    "sg:tags":[
        "loan",
        "processing",
        "appliance",
        "appliances-manufacturing",
        "orthopedic"
    ],
    "wof:name":"Bmc",
    "wof:placetype":"venue"
},
  "geometry": {"coordinates":[-122.024074,38.011499],"type":"Point"}
}