{
  "type": "Feature",
  "properties": {
    "iso:country":"US",
    "sg:address":"1319 Lincoln Ave",
    "sg:city":"San Jose",
    "sg:classifiers":[
        {
            "category":"Deli",
            "type":"Food & Drink"
        },
        {
            "category":"Food & Beverages",
            "subcategory":"Bakery",
            "type":"Retail Goods"
        },
        {
            "category":"Food & Beverages",
            "subcategory":"Meat & Fish",
            "type":"Retail Goods"
        }
    ],
    "sg:phone":"+1 408 295 7851",
    "sg:postcode":"95125",
    "sg:province":"CA",
    "sg:tags":[
        "shop",
        "sandwich"
    ],
    "sg:website":"www.wglavilla.com",
    "wof:name":"La Villa Delicatessen & Gourmet Shop",
    "wof:placetype":"venue"
},
  "geometry": {"coordinates":[-121.898527,37.304584],"type":"Point"}
}