{
  "type": "Feature",
  "properties": {
    "addr:full":"1020 Grouse Dr Redding CA 96003",
    "addr:housenumber":"1020",
    "addr:postcode":"96003",
    "addr:street":"Grouse Dr",
    "iso:country":"US",
    "sg:address":"1020 Grouse Dr",
    "sg:city":"Redding",
    "sg:classifiers":[
        {
            "category":"Health Services",
            "subcategory":"Medical Lab",
            "type":"Services"
        }
    ],
    "sg:phone":"+1 530 222 6728",
    "sg:postcode":"96003",
    "sg:province":"CA",
    "sg:tags":[
        "laboratory"
    ],
    "wof:name":"Tech Dental Studio",
    "wof:placetype":"venue"
},
  "geometry": {"coordinates":[-122.34723,40.592597],"type":"Point"}
}