{
  "type": "Feature",
  "properties": {
    "iso:country":"US",
    "sg:address":"1630 E 4th St",
    "sg:city":"Ontario",
    "sg:classifiers":[
        {
            "category":"Shopping",
            "subcategory":"Tobacco",
            "type":"Retail Goods"
        }
    ],
    "sg:phone":"+1 909 986 2677",
    "sg:postcode":"91764",
    "sg:province":"CA",
    "sg:tags":[
        "product"
    ],
    "wof:name":"Tobacco 4 Less",
    "wof:placetype":"venue"
},
  "geometry": {"coordinates":[-117.617908,34.07755],"type":"Point"}
}