{
  "type": "Feature",
  "properties": {
    "iso:country":"US",
    "sg:address":"4957 Lake Shore Ct",
    "sg:city":"Fallbrook",
    "sg:classifiers":[
        {
            "category":"Professional",
            "subcategory":"Business Services",
            "type":"Services"
        }
    ],
    "sg:phone":"+1 760 451 1699",
    "sg:postcode":"92028",
    "sg:province":"CA",
    "sg:tags":[
        "inspection"
    ],
    "wof:name":"US Inspection Group",
    "wof:placetype":"venue"
},
  "geometry": {"coordinates":[-117.151378,33.326109],"type":"Point"}
}