{
  "type": "Feature",
  "properties": {
    "addr:full":"5859 Mandarin Dr Goleta CA 93117",
    "addr:housenumber":"5859",
    "addr:postcode":"93117",
    "addr:street":"Mandarin Dr",
    "iso:country":"US",
    "sg:address":"5859 Mandarin Dr",
    "sg:city":"Goleta",
    "sg:classifiers":[
        {
            "category":"Building & Trades",
            "subcategory":"Plumbing",
            "type":"Services"
        }
    ],
    "sg:phone":"+1 805 683 8914",
    "sg:postcode":"93117",
    "sg:province":"CA",
    "sg:tags":[
        "contractor"
    ],
    "wof:name":"Estrada Plumbing",
    "wof:placetype":"venue"
},
  "geometry": {"coordinates":[-119.828799,34.437321],"type":"Point"}
}