{
  "type": "Feature",
  "properties": {
    "iso:country":"US",
    "sg:address":"2525 N Grand Ave",
    "sg:city":"Santa Ana",
    "sg:classifiers":[
        {
            "category":"Retail",
            "subcategory":"Veterinary Services",
            "type":"Services"
        }
    ],
    "sg:phone":"+1 714 633 2910",
    "sg:postcode":"92705",
    "sg:province":"CA",
    "wof:name":"Bird Clinic The",
    "wof:placetype":"venue"
},
  "geometry": {"coordinates":[-117.851442,33.767567],"type":"Point"}
}