{
  "type": "Feature",
  "properties": {
    "iso:country":"US",
    "sg:address":"102 2nd St",
    "sg:city":"Colusa",
    "sg:classifiers":[
        {
            "category":"Wholesale",
            "subcategory":"Fruits & Vegetables",
            "type":"Manufacturing & Wholesale Goods"
        }
    ],
    "sg:phone":"+1 530 458 8034",
    "sg:postcode":"95932",
    "sg:province":"CA",
    "wof:name":"West Side Produce",
    "wof:placetype":"venue"
},
  "geometry": {"coordinates":[-122.003805,39.213615],"type":"Point"}
}