{
  "type": "Feature",
  "properties": {
    "addr:full":"407 N Main St Manteca CA 95336",
    "addr:housenumber":"407",
    "addr:postcode":"95336",
    "addr:street":"N Main St",
    "iso:country":"US",
    "sg:address":"407 N Main St",
    "sg:city":"Manteca",
    "sg:classifiers":[
        {
            "category":"Shopping",
            "type":"Retail Goods"
        }
    ],
    "sg:phone":"+1 209 239 3700",
    "sg:postcode":"95336",
    "sg:province":"CA",
    "sg:tags":[
        "telephone",
        "cellular"
    ],
    "wof:name":"Cell Maxx Wireless",
    "wof:placetype":"venue"
},
  "geometry": {"coordinates":[-121.216864,37.804004],"type":"Point"}
}