{
  "type": "Feature",
  "properties": {
    "iso:country":"US",
    "sg:address":"17537 Blanchard Dr",
    "sg:city":"Monte Sereno",
    "sg:classifiers":[
        {
            "category":"Manufacturing",
            "subcategory":"Printing",
            "type":"Manufacturing & Wholesale Goods"
        }
    ],
    "sg:phone":"+1 408 866 8016",
    "sg:postcode":"95030",
    "sg:province":"CA",
    "sg:tags":[
        "publisher",
        "software"
    ],
    "wof:name":"Inductel Inc",
    "wof:placetype":"venue"
},
  "geometry": {"coordinates":[-121.979992,37.24356],"type":"Point"}
}