{
  "type": "Feature",
  "properties": {
    "addr:full":"16137 Augusta Dr Chino Hills CA 91709",
    "addr:housenumber":"16137",
    "addr:postcode":"91709",
    "addr:street":"Augusta Dr",
    "iso:country":"US",
    "sg:address":"16137 Augusta Dr",
    "sg:city":"Chino Hills",
    "sg:classifiers":[
        {
            "category":"Wholesale",
            "subcategory":"Durable Goods & Equipment",
            "type":"Manufacturing & Wholesale Goods"
        }
    ],
    "sg:phone":"+1 909 393 0638",
    "sg:postcode":"91709",
    "sg:province":"CA",
    "sg:tags":[
        "importer"
    ],
    "wof:name":"Hancco Industries",
    "wof:placetype":"venue"
},
  "geometry": {"coordinates":[-117.7152,33.960079],"type":"Point"}
}