{
  "type": "Feature",
  "properties": {
    "addr:full":"10987 Magnolia Ave Riverside CA 92505",
    "addr:housenumber":"10987",
    "addr:postcode":"92505",
    "addr:street":"Magnolia Ave",
    "iso:country":"US",
    "sg:address":"10987 Magnolia Ave",
    "sg:city":"Riverside",
    "sg:classifiers":[
        {
            "category":"Personal",
            "subcategory":"Beauty Salon",
            "type":"Services"
        }
    ],
    "sg:phone":"+1 951 689 3839",
    "sg:postcode":"92505",
    "sg:province":"CA",
    "wof:name":"Hair By Jennifer Leath",
    "wof:placetype":"venue"
},
  "geometry": {"coordinates":[-117.475889,33.903767],"type":"Point"}
}