{
  "type": "Feature",
  "properties": {
    "addr:full":"7376 Via Montecitos San Jose CA 95135",
    "addr:housenumber":"7376",
    "addr:postcode":"95135",
    "addr:street":"Via Montecitos",
    "iso:country":"US",
    "sg:address":"7376 Via Montecitos",
    "sg:city":"San Jose",
    "sg:classifiers":[
        {
            "category":"Professional",
            "type":"Services"
        }
    ],
    "sg:phone":"+1 408 223 2702",
    "sg:postcode":"95135",
    "sg:province":"CA",
    "wof:name":"Northwest Coating Systems",
    "wof:placetype":"venue"
},
  "geometry": {"coordinates":[-121.74427900000001,37.292984],"type":"Point"}
}