{
  "type": "Feature",
  "properties": {
    "iso:country":"US",
    "sg:address":"3760 Mission Ave Ste B",
    "sg:city":"Oceanside",
    "sg:classifiers":[
        {
            "category":"Shopping",
            "subcategory":"Mobile Phones",
            "type":"Retail Goods"
        }
    ],
    "sg:phone":"+1 760 757 7075",
    "sg:postcode":"92058",
    "sg:province":"CA",
    "sg:website":"www.verizonwireless.com",
    "wof:name":"Verizon Wireless",
    "wof:placetype":"venue"
},
  "geometry": {"coordinates":[-117.33134,33.226536],"type":"Point"}
}