{
  "type": "Feature",
  "properties": {
    "iso:country":"US",
    "sg:address":"10013 8th St",
    "sg:city":"Rancho Cucamonga",
    "sg:classifiers":[
        {
            "category":"Retail",
            "subcategory":"Auto Repair",
            "type":"Services"
        }
    ],
    "sg:phone":"+1 909 987 2193",
    "sg:postcode":"91730",
    "sg:province":"CA",
    "sg:tags":[
        "repairing",
        "automobile"
    ],
    "wof:name":"Scott's",
    "wof:placetype":"venue"
},
  "geometry": {"coordinates":[-117.587053,34.091731],"type":"Point"}
}