{
  "type": "Feature",
  "properties": {
    "iso:country":"US",
    "sg:address":"6213 Spring Valley Dr",
    "sg:city":"Bakersfield",
    "sg:classifiers":[
        {
            "category":"Building & Trades",
            "subcategory":"Landscaping Services",
            "type":"Services"
        }
    ],
    "sg:phone":"+1 661 392 9574",
    "sg:postcode":"93308",
    "sg:province":"CA",
    "sg:tags":[
        "lawn",
        "maintenance",
        "grounds"
    ],
    "wof:name":"Dan N Sons Lawn Svc",
    "wof:placetype":"venue"
},
  "geometry": {"coordinates":[-119.071691,35.407303],"type":"Point"}
}