{
  "type": "Feature",
  "properties": {
    "addr:full":"5527 Fremont St Oakland CA 94608",
    "addr:housenumber":"5527",
    "addr:postcode":"94608",
    "addr:street":"Fremont St",
    "iso:country":"US",
    "sg:address":"5527 Fremont St",
    "sg:city":"Oakland",
    "sg:classifiers":[
        {
            "category":"Sports & Exercise",
            "subcategory":"Gym",
            "type":"Entertainment"
        }
    ],
    "sg:phone":"+1 510 658 3169",
    "sg:postcode":"94608",
    "sg:province":"CA",
    "sg:tags":[
        "instruction",
        "yoga"
    ],
    "wof:name":"Yogeshwari Arts",
    "wof:placetype":"venue"
},
  "geometry": {"coordinates":[-122.284265,37.838698],"type":"Point"}
}