{
  "type": "Feature",
  "properties": {
    "iso:country":"US",
    "sg:address":"1218 Long Beach Ave",
    "sg:city":"Los Angeles",
    "sg:classifiers":[
        {
            "category":"Arts & Performance",
            "subcategory":"Music",
            "type":"Entertainment"
        },
        {
            "category":"Communications",
            "subcategory":"Radio Station",
            "type":"Services"
        }
    ],
    "sg:postcode":"90021",
    "sg:province":"CA",
    "sg:tags":[
        "venue"
    ],
    "sg:website":"www.littleradio.com",
    "wof:name":"Little Radio Warehouse",
    "wof:placetype":"venue"
},
  "geometry": {"coordinates":[-118.240997,34.025799],"type":"Point"}
}