{
  "type": "Feature",
  "properties": {
    "iso:country":"US",
    "sg:address":"830 S Broadway",
    "sg:city":"Santa Maria",
    "sg:classifiers":[
        {
            "category":"Restaurant",
            "type":"Food & Drink"
        }
    ],
    "sg:menulink":"http://www.allmenus.com/ca/santa-maria-valley/178348-jack-in-the-box/menu/",
    "sg:phone":"+1 805 922 5693",
    "sg:postcode":"93454",
    "sg:province":"CA",
    "sg:tags":[
        "burger",
        "american"
    ],
    "wof:name":"Jack in the Box",
    "wof:placetype":"venue"
},
  "geometry": {"coordinates":[-120.435526,34.943315],"type":"Point"}
}