{
  "type": "Feature",
  "properties": {
    "addr:full":"1323 2nd St San Rafael CA 94901",
    "addr:housenumber":"1323",
    "addr:postcode":"94901",
    "addr:street":"2Nd St",
    "iso:country":"US",
    "sg:address":"1323 2nd St",
    "sg:city":"San Rafael",
    "sg:classifiers":[
        {
            "category":"Autos & Motor Vehicles",
            "subcategory":"Auto Supplies",
            "type":"Retail Goods"
        }
    ],
    "sg:phone":"+1 415 454 2963",
    "sg:postcode":"94901",
    "sg:province":"CA",
    "sg:tags":[
        "automobile",
        "parts"
    ],
    "sg:website":"www.kragen.com",
    "wof:name":"Kragen Auto Parts",
    "wof:placetype":"venue"
},
  "geometry": {"coordinates":[-122.53203600000001,37.971446],"type":"Point"}
}