{
  "type": "Feature",
  "properties": {
    "addr:full":"3111 Professional Dr Auburn CA 95603",
    "addr:housenumber":"3111",
    "addr:postcode":"ca 95603",
    "addr:street":"Professional Dr",
    "iso:country":"US",
    "sg:address":"3111 Professional Dr",
    "sg:city":"Auburn",
    "sg:classifiers":[
        {
            "category":"Health Services",
            "subcategory":"Doctor",
            "type":"Services"
        }
    ],
    "sg:phone":"+1 530 885 5618",
    "sg:postcode":"95603",
    "sg:province":"CA",
    "sg:tags":[
        "physician",
        "surgeon"
    ],
    "wof:name":"U C Davis Medical Group",
    "wof:placetype":"venue"
},
  "geometry": {"coordinates":[-121.10074299999999,38.939952],"type":"Point"}
}