{
  "type": "Feature",
  "properties": {
    "iso:country":"US",
    "sg:address":"1762 Production Cir",
    "sg:city":"Riverside",
    "sg:classifiers":[
        {
            "category":"Building & Trades",
            "subcategory":"Construction",
            "type":"Services"
        }
    ],
    "sg:phone":"+1 951 779 1934",
    "sg:postcode":"92509",
    "sg:province":"CA",
    "sg:tags":[
        "contractor"
    ],
    "wof:name":"CMB Construction",
    "wof:placetype":"venue"
},
  "geometry": {"coordinates":[-117.391259,34.023688],"type":"Point"}
}