{
  "type": "Feature",
  "properties": {
    "addr:full":"1821 Steiner St San Francisco CA 94115",
    "addr:housenumber":"1821",
    "addr:postcode":"94115",
    "addr:street":"Steiner St",
    "iso:country":"US",
    "sg:address":"1821 Steiner St",
    "sg:city":"San Francisco",
    "sg:classifiers":[
        {
            "category":"Shopping",
            "subcategory":"Clothing, Apparel, & Fashions",
            "type":"Retail Goods"
        }
    ],
    "sg:phone":"+1 415 351 0279",
    "sg:postcode":"94115",
    "sg:province":"CA",
    "sg:tags":[
        "shop",
        "bridal"
    ],
    "wof:name":"Metrofashion",
    "wof:placetype":"venue"
},
  "geometry": {"coordinates":[-122.435149,37.786608],"type":"Point"}
}