{
  "type": "Feature",
  "properties": {
    "iso:country":"US",
    "sg:address":"1660 Hamner Ave",
    "sg:city":"Norco",
    "sg:classifiers":[
        {
            "category":"Shopping",
            "subcategory":"Clothing, Apparel, & Fashions",
            "type":"Retail Goods"
        }
    ],
    "sg:phone":"+1 951 738 1544",
    "sg:postcode":"92860",
    "sg:province":"CA",
    "sg:tags":[
        "maternity"
    ],
    "wof:name":"Pickles & Ice Cream Resale",
    "wof:placetype":"venue"
},
  "geometry": {"coordinates":[-117.562005,33.903791],"type":"Point"}
}