{
  "type": "Feature",
  "properties": {
    "addr:full":"1440 Main St Delano CA 93215",
    "addr:housenumber":"1440",
    "addr:postcode":"93215",
    "addr:street":"Main St",
    "iso:country":"US",
    "sg:address":"1440 Main St",
    "sg:city":"Delano",
    "sg:classifiers":[
        {
            "category":"Restaurant",
            "type":"Food & Drink"
        }
    ],
    "sg:phone":"+1 661 725 4900",
    "sg:postcode":"93215",
    "sg:province":"CA",
    "sg:tags":[
        "out"
    ],
    "wof:name":"Taco Factory",
    "wof:placetype":"venue"
},
  "geometry": {"coordinates":[-119.24702000000001,35.775235],"type":"Point"}
}