{
  "type": "Feature",
  "properties": {
    "addr:full":"6290 Pony Express Trail Pollock Pines CA 95726",
    "addr:housenumber":"6290",
    "addr:postcode":"95726",
    "addr:street":"Pony Express Trail",
    "iso:country":"US",
    "sg:address":"6290 Pony Express Trail",
    "sg:city":"Pollock Pines",
    "sg:classifiers":[
        {
            "category":"Real Estate",
            "subcategory":"Real Estate Services",
            "type":"Services"
        }
    ],
    "sg:phone":"+1 530 644 1644",
    "sg:postcode":"95726",
    "sg:province":"CA",
    "sg:website":"www.CallZGroup.com",
    "wof:name":"Z Group REMAX Gold",
    "wof:placetype":"venue"
},
  "geometry": {"coordinates":[-120.58560900000001,38.761327],"type":"Point"}
}