{
  "type": "Feature",
  "properties": {
    "addr:full":"1780 Avenida Del Mundo Coronado CA 92118",
    "addr:housenumber":"1780",
    "addr:postcode":"92118",
    "addr:street":"Avenida Del Mundo",
    "iso:country":"US",
    "sg:address":"1780 Avenida Del Mundo",
    "sg:city":"Coronado",
    "sg:classifiers":[
        {
            "category":"Real Estate",
            "subcategory":"Real Estate Operator",
            "type":"Services"
        }
    ],
    "sg:phone":"+1 619 435 2533",
    "sg:postcode":"92118",
    "sg:province":"CA",
    "sg:tags":[
        "apartment"
    ],
    "wof:name":"Coronado Shores Health Club",
    "wof:placetype":"venue"
},
  "geometry": {"coordinates":[-117.17419599999999,32.676667],"type":"Point"}
}