{
  "type": "Feature",
  "properties": {
    "addr:full":"1512 Santee St Los Angeles CA 90015",
    "addr:housenumber":"1512",
    "addr:postcode":"90015",
    "addr:street":"Santee St",
    "iso:country":"US",
    "sg:address":"1512 Santee St",
    "sg:city":"Los Angeles",
    "sg:classifiers":[
        {
            "category":"Shopping",
            "subcategory":"Clothing, Apparel, & Fashions",
            "type":"Retail Goods"
        }
    ],
    "sg:phone":"+1 213 746 2155",
    "sg:postcode":"90015",
    "sg:province":"CA",
    "sg:tags":[
        "clothing",
        "women's"
    ],
    "wof:name":"Club 408",
    "wof:placetype":"venue"
},
  "geometry": {"coordinates":[-118.260282,34.032628],"type":"Point"}
}