{
  "type": "Feature",
  "properties": {
    "iso:country":"US",
    "sg:address":"The Law Offices of Beck, Ross 50 West San Fernando Street Suite 1300",
    "sg:city":"San Jose",
    "sg:classifiers":[
        {
            "category":"Professional",
            "subcategory":"Lawyer & Legal Services",
            "type":"Services"
        }
    ],
    "sg:phone":"+1 408 938 7900",
    "sg:postcode":"95113",
    "sg:province":"CA",
    "sg:website":"www.beckross.com/index.cfm?page=...",
    "wof:name":"Andrea Starrett, Esq.",
    "wof:placetype":"venue"
},
  "geometry": {"coordinates":[-121.88923699999999,37.333868],"type":"Point"}
}