{
  "type": "Feature",
  "properties": {
    "iso:country":"US",
    "sg:address":"2668 S Cherokee Way",
    "sg:city":"Palm Springs",
    "sg:classifiers":[
        {
            "category":"Building & Trades",
            "subcategory":"Construction",
            "type":"Services"
        },
        {
            "category":"Home & Garden",
            "subcategory":"Carpets & Floor Coverings",
            "type":"Retail Goods"
        }
    ],
    "sg:phone":"+1 760 328 9390",
    "sg:postcode":"92264",
    "sg:province":"CA",
    "sg:tags":[
        "interior",
        "design",
        "carpeting"
    ],
    "wof:name":"Phillip's Floor Covering",
    "wof:placetype":"venue"
},
  "geometry": {"coordinates":[-116.501999,33.791599],"type":"Point"}
}