{
  "type": "Feature",
  "properties": {
    "iso:country":"US",
    "sg:address":"22812 Victory Blvd",
    "sg:city":"Woodland Hills",
    "sg:classifiers":[
        {
            "category":"Retail",
            "subcategory":"Laundry & Dry Cleaning",
            "type":"Services"
        }
    ],
    "sg:phone":"+1 818 999 3624",
    "sg:postcode":"91367",
    "sg:province":"CA",
    "wof:name":"Fallbrook Celebrity Cleaners",
    "wof:placetype":"venue"
},
  "geometry": {"coordinates":[-118.624466,34.186451],"type":"Point"}
}