{
  "type": "Feature",
  "properties": {
    "addr:full":"148 E Brokaw Rd San Jose CA 95112",
    "addr:housenumber":"148",
    "addr:postcode":"95112",
    "addr:street":"E Brokaw Rd",
    "iso:country":"US",
    "sg:address":"148 E Brokaw Rd",
    "sg:city":"San Jose",
    "sg:classifiers":[
        {
            "category":"Manufacturing",
            "subcategory":"Electronics",
            "type":"Manufacturing & Wholesale Goods"
        }
    ],
    "sg:phone":"+1 408 467 0410",
    "sg:postcode":"95112",
    "sg:province":"CA",
    "sg:tags":[
        "semiconductor",
        "chip",
        "set",
        "mfg"
    ],
    "sg:website":"www.sirf.org",
    "wof:name":"Sirf Technology Holdings Inc",
    "wof:placetype":"venue"
},
  "geometry": {"coordinates":[-121.91654800000001,37.374515],"type":"Point"}
}