{
  "type": "Feature",
  "properties": {
    "iso:country":"US",
    "sg:address":"1228 E Fairmont Ave",
    "sg:city":"Modesto",
    "sg:classifiers":[
        {
            "category":"Building & Trades",
            "subcategory":"Cleaning & Sanitation",
            "type":"Services"
        }
    ],
    "sg:phone":"+1 209 521 7022",
    "sg:postcode":"95350",
    "sg:province":"CA",
    "sg:tags":[
        "house"
    ],
    "wof:name":"Kleentech",
    "wof:placetype":"venue"
},
  "geometry": {"coordinates":[-120.975827,37.65712],"type":"Point"}
}