{
  "type": "Feature",
  "properties": {
    "addr:full":"261 Bloomington Ave Rialto CA 92376",
    "addr:housenumber":"261",
    "addr:postcode":"92376",
    "addr:street":"Bloomington Ave",
    "iso:country":"US",
    "sg:address":"261 Bloomington Ave",
    "sg:city":"Rialto",
    "sg:classifiers":[
        {
            "category":"Manufacturing",
            "subcategory":"Electronics",
            "type":"Manufacturing & Wholesale Goods"
        }
    ],
    "sg:phone":"+1 909 875 2190",
    "sg:postcode":"92376",
    "sg:province":"CA",
    "sg:tags":[
        "equipment",
        "mfg",
        "communication"
    ],
    "wof:name":"ACS Assoc Communications",
    "wof:placetype":"venue"
},
  "geometry": {"coordinates":[-117.37433799999999,34.088898],"type":"Point"}
}