{
  "type": "Feature",
  "properties": {
    "iso:country":"US",
    "sg:address":"761 E Teague Ave",
    "sg:city":"Fresno",
    "sg:classifiers":[
        {
            "category":"Organizations",
            "subcategory":"Professional Association",
            "type":"Services"
        }
    ],
    "sg:phone":"+1 559 434 3486",
    "sg:postcode":"93720",
    "sg:province":"CA",
    "wof:name":"Weather Modification Assn",
    "wof:placetype":"venue"
},
  "geometry": {"coordinates":[-119.771512,36.859096],"type":"Point"}
}