{
  "type": "Feature",
  "properties": {
    "addr:full":"1238 2nd Ave Napa CA 94558",
    "addr:housenumber":"1238",
    "addr:postcode":"94558",
    "addr:street":"2Nd Ave",
    "iso:country":"US",
    "sg:address":"1238 2nd Ave",
    "sg:city":"Napa",
    "sg:classifiers":[
        {
            "category":"Professional",
            "subcategory":"Management & Consulting",
            "type":"Services"
        },
        {
            "category":"Professional",
            "subcategory":"Advertising",
            "type":"Services"
        }
    ],
    "sg:phone":"+1 707 255 6914",
    "sg:postcode":"94558",
    "sg:province":"CA",
    "sg:tags":[
        "marketing",
        "program",
        "consultant"
    ],
    "wof:name":"Edward J Shenk",
    "wof:placetype":"venue"
},
  "geometry": {"coordinates":[-122.24436300000001,38.303985],"type":"Point"}
}