{
  "type": "Feature",
  "properties": {
    "iso:country":"US",
    "sg:address":"1302 E Adams Blvd",
    "sg:city":"Los Angeles",
    "sg:classifiers":[
        {
            "category":"Organizations",
            "subcategory":"Religious Organization",
            "type":"Services"
        }
    ],
    "sg:phone":"+1 323 232 5463",
    "sg:postcode":"90011",
    "sg:province":"CA",
    "sg:tags":[
        "church"
    ],
    "wof:name":"Bethel Church Of Christ",
    "wof:placetype":"venue"
},
  "geometry": {"coordinates":[-118.248614,34.015728],"type":"Point"}
}