{
  "type": "Feature",
  "properties": {
    "iso:country":"US",
    "sg:address":"220 Montgomery St, #15",
    "sg:city":"San Francisco",
    "sg:classifiers":[
        {
            "category":"Professional",
            "subcategory":"Lawyer & Legal Services",
            "type":"Services"
        }
    ],
    "sg:phone":"+1 415 403 1660",
    "sg:postcode":"94104",
    "sg:province":"CA",
    "wof:name":"Law Offices of Steven Sherman",
    "wof:placetype":"venue"
},
  "geometry": {"coordinates":[-122.40198599999999,37.791306],"type":"Point"}
}