{
  "type": "Feature",
  "properties": {
    "addr:full":"1865 E 4th St Ontario CA 91764",
    "addr:housenumber":"1865",
    "addr:postcode":"91764",
    "addr:street":"E 4Th St",
    "iso:country":"US",
    "sg:address":"1865 E 4th St",
    "sg:city":"Ontario",
    "sg:classifiers":[
        {
            "category":"Restaurant",
            "type":"Food & Drink"
        }
    ],
    "sg:phone":"+1 909 984 0544",
    "sg:postcode":"91764",
    "sg:province":"CA",
    "wof:name":"Sizzler",
    "wof:placetype":"venue"
},
  "geometry": {"coordinates":[-117.61169700000001,34.077512],"type":"Point"}
}