{
  "type": "Feature",
  "properties": {
    "iso:country":"US",
    "sg:address":"1865 E 4th St",
    "sg:city":"Ontario",
    "sg:classifiers":[
        {
            "category":"Restaurant",
            "type":"Food & Drink"
        }
    ],
    "sg:phone":"+1 909 984 0544",
    "sg:postcode":"91764",
    "sg:province":"CA",
    "wof:name":"Sizzler",
    "wof:placetype":"venue"
},
  "geometry": {"coordinates":[-117.611697,34.077512],"type":"Point"}
}