{
  "type": "Feature",
  "properties": {
    "addr:full":"26724 Oak Ave Canyon Country CA 91351",
    "addr:housenumber":"26724",
    "addr:postcode":"91351",
    "addr:street":"Oak Ave",
    "iso:country":"US",
    "sg:address":"26724 Oak Ave",
    "sg:city":"Canyon Country",
    "sg:classifiers":[
        {
            "category":"Wholesale",
            "subcategory":"Durable Goods & Equipment",
            "type":"Manufacturing & Wholesale Goods"
        },
        {
            "category":"Wholesale",
            "subcategory":"Auto Parts",
            "type":"Manufacturing & Wholesale Goods"
        }
    ],
    "sg:phone":"+1 661 250 1494",
    "sg:postcode":"91351",
    "sg:province":"CA",
    "sg:tags":[
        "automobile",
        "supply"
    ],
    "wof:name":"Service Center Supply",
    "wof:placetype":"venue"
},
  "geometry": {"coordinates":[-118.500406,34.422876],"type":"Point"}
}