{
  "type": "Feature",
  "properties": {
    "addr:full":"3581 Mather Field Rd Rancho Cordova CA 95670",
    "addr:housenumber":"3581",
    "addr:postcode":"95670",
    "addr:street":"Mather Field Rd",
    "iso:country":"US",
    "sg:address":"3581 Mather Field Rd",
    "sg:city":"Rancho Cordova",
    "sg:classifiers":[
        {
            "category":"Education",
            "subcategory":"Special Training",
            "type":"Public Place"
        }
    ],
    "sg:phone":"+1 916 869 7212",
    "sg:postcode":"95670",
    "sg:province":"CA",
    "sg:tags":[
        "instruction",
        "driving"
    ],
    "wof:name":"Safe Car Driving School",
    "wof:placetype":"venue"
},
  "geometry": {"coordinates":[-121.299229,38.572125],"type":"Point"}
}