{
  "type": "Feature",
  "properties": {
    "addr:full":"11130 Rose Ave Los Angeles CA 90034",
    "addr:housenumber":"11130",
    "addr:postcode":"90034",
    "addr:street":"Rose Ave",
    "iso:country":"US",
    "sg:address":"11130 Rose Ave",
    "sg:city":"Los Angeles",
    "sg:classifiers":[
        {
            "category":"Professional",
            "type":"Services"
        }
    ],
    "sg:phone":"+1 310 915 0906",
    "sg:postcode":"90034",
    "sg:province":"CA",
    "wof:name":"US China Biotech Communication",
    "wof:placetype":"venue"
},
  "geometry": {"coordinates":[-118.42335199999999,34.021381],"type":"Point"}
}