{
  "type": "Feature",
  "properties": {
    "addr:full":"645 Russell St Vallejo CA 94591",
    "addr:housenumber":"645",
    "addr:postcode":"94591",
    "addr:street":"Russell St",
    "iso:country":"US",
    "sg:address":"645 Russell St",
    "sg:city":"Vallejo",
    "sg:classifiers":[
        {
            "category":"Utilities",
            "subcategory":"Refuse",
            "type":"Services"
        }
    ],
    "sg:phone":"+1 707 642 6701",
    "sg:postcode":"94591",
    "sg:province":"CA",
    "sg:tags":[
        "detoxification",
        "center"
    ],
    "wof:name":"Path To Recovery Inc",
    "wof:placetype":"venue"
},
  "geometry": {"coordinates":[-122.225115,38.098624],"type":"Point"}
}