{
  "type": "Feature",
  "properties": {
    "addr:full":"345 Railroad Ave Grass Valley CA 95945",
    "addr:housenumber":"345",
    "addr:postcode":"95945",
    "addr:street":"Railroad Ave",
    "iso:country":"US",
    "sg:address":"345 Railroad Ave",
    "sg:city":"Grass Valley",
    "sg:classifiers":[
        {
            "category":"Building & Trades",
            "subcategory":"Landscaping Services",
            "type":"Services"
        }
    ],
    "sg:phone":"+1 530 477 8855",
    "sg:postcode":"95945",
    "sg:province":"CA",
    "sg:tags":[
        "tree"
    ],
    "wof:name":"Toney's Tree Svc",
    "wof:placetype":"venue"
},
  "geometry": {"coordinates":[-121.050968,39.221022],"type":"Point"}
}