{
  "type": "Feature",
  "properties": {
    "iso:country":"US",
    "sg:address":"1625 Shattuck Ave",
    "sg:city":"Berkeley",
    "sg:classifiers":[
        {
            "category":"Government",
            "subcategory":"Office",
            "type":"Public Place"
        }
    ],
    "sg:phone":"+1 510 540 2800",
    "sg:postcode":"94709",
    "sg:province":"CA",
    "sg:tags":[
        "administrative",
        "program",
        "health"
    ],
    "wof:name":"Envirnmntal Lab Accrdttion Pro",
    "wof:placetype":"venue"
},
  "geometry": {"coordinates":[-122.268918,37.876572],"type":"Point"}
}