{
  "type": "Feature",
  "properties": {
    "addr:full":"770 el Camino del Mar San Francisco CA 94121",
    "addr:housenumber":"770",
    "addr:postcode":"94121",
    "addr:street":"El Camino Del Mar",
    "iso:country":"US",
    "sg:address":"770 el Camino del Mar",
    "sg:city":"San Francisco",
    "sg:classifiers":[
        {
            "category":"Shopping",
            "subcategory":"Catalog Store",
            "type":"Retail Goods"
        }
    ],
    "sg:phone":"+1 415 221 7707",
    "sg:postcode":"94121",
    "sg:province":"CA",
    "sg:tags":[
        "house",
        "mail"
    ],
    "wof:name":"Barbara Land",
    "wof:placetype":"venue"
},
  "geometry": {"coordinates":[-122.490561,37.786283],"type":"Point"}
}