{
  "type": "Feature",
  "properties": {
    "iso:country":"US",
    "sg:address":"104 Calumet Ave",
    "sg:city":"San Anselmo",
    "sg:classifiers":[
        {
            "category":"Manufacturing",
            "subcategory":"Printing",
            "type":"Manufacturing & Wholesale Goods"
        }
    ],
    "sg:phone":"+1 415 454 8170",
    "sg:postcode":"94960",
    "sg:province":"CA",
    "sg:tags":[
        "lithographic",
        "book",
        "commercial"
    ],
    "wof:name":"Madden & Son",
    "wof:placetype":"venue"
},
  "geometry": {"coordinates":[-122.568882,37.980136],"type":"Point"}
}