{
  "type": "Feature",
  "properties": {
    "iso:country":"US",
    "sg:address":"PO Box 2375",
    "sg:city":"Santa Maria",
    "sg:classifiers":[
        {
            "category":"Building & Trades",
            "subcategory":"Construction",
            "type":"Services"
        }
    ],
    "sg:phone":"+1 805 925 3964",
    "sg:postcode":"93457",
    "sg:province":"CA",
    "sg:tags":[
        "painter"
    ],
    "wof:name":"Reiner Painting",
    "wof:placetype":"venue"
},
  "geometry": {"coordinates":[-120.445999,34.864799],"type":"Point"}
}