{
  "type": "Feature",
  "properties": {
    "addr:full":"790 N San Mateo Drive San Mateo CA 94401",
    "addr:housenumber":"790",
    "addr:postcode":"94401",
    "addr:street":"N San Mateo Drive",
    "iso:country":"US",
    "sg:address":"790 N San Mateo Drive",
    "sg:city":"San Mateo",
    "sg:classifiers":[
        {
            "category":"Autos & Motor Vehicles",
            "subcategory":"Automobile Sales",
            "type":"Retail Goods"
        }
    ],
    "sg:phone":"+1 650 340 7199",
    "sg:postcode":"94401",
    "sg:province":"CA",
    "sg:tags":[
        "car"
    ],
    "sg:website":"www.veracom.com",
    "wof:name":"Veracom",
    "wof:placetype":"venue"
},
  "geometry": {"coordinates":[-122.336325,37.576101],"type":"Point"}
}