{
  "type": "Feature",
  "properties": {
    "iso:country":"US",
    "sg:address":"2654 Alpine Blvd",
    "sg:city":"Alpine",
    "sg:classifiers":[
        {
            "category":"Restaurant",
            "type":"Food & Drink"
        }
    ],
    "sg:phone":"+1 619 445 4006",
    "sg:postcode":"91901",
    "sg:province":"CA",
    "wof:name":"Donato's Italian Restaurant",
    "wof:placetype":"venue"
},
  "geometry": {"coordinates":[-116.757254,32.834837],"type":"Point"}
}