{
  "type": "Feature",
  "properties": {
    "addr:full":"805 Douglas Blvd Roseville CA 95678",
    "addr:housenumber":"805",
    "addr:postcode":"95678",
    "addr:street":"Douglas Blvd",
    "iso:country":"US",
    "sg:address":"805 Douglas Blvd",
    "sg:city":"Roseville",
    "sg:classifiers":[
        {
            "category":"Professional",
            "subcategory":"Management & Consulting",
            "type":"Services"
        }
    ],
    "sg:phone":"+1 916 780 2601",
    "sg:postcode":"95678",
    "sg:province":"CA",
    "sg:tags":[
        "consultant",
        "medical"
    ],
    "wof:name":"BMS",
    "wof:placetype":"venue"
},
  "geometry": {"coordinates":[-121.282478,38.743925],"type":"Point"}
}