{
  "type": "Feature",
  "properties": {
    "iso:country":"US",
    "sg:address":"4067 Transport St",
    "sg:city":"Palo Alto",
    "sg:classifiers":[
        {
            "category":"Building & Trades",
            "subcategory":"Electrical",
            "type":"Services"
        }
    ],
    "sg:phone":"+1 650 813 9999",
    "sg:postcode":"94303",
    "sg:province":"CA",
    "sg:tags":[
        "electric",
        "contractor"
    ],
    "wof:name":"Wong Electric Inc",
    "wof:placetype":"venue"
},
  "geometry": {"coordinates":[-122.101259,37.423775],"type":"Point"}
}