{
  "type": "Feature",
  "properties": {
    "iso:country":"US",
    "sg:address":"10732 Myrtle St",
    "sg:city":"Loma Linda",
    "sg:classifiers":[
        {
            "category":"Shopping",
            "subcategory":"Clothing, Apparel, & Fashions",
            "type":"Retail Goods"
        }
    ],
    "sg:phone":"+1 909 796 7085",
    "sg:postcode":"92354",
    "sg:province":"CA",
    "sg:tags":[
        "baby",
        "accessory"
    ],
    "wof:name":"Oops-A-Daisy",
    "wof:placetype":"venue"
},
  "geometry": {"coordinates":[-117.23985999999999,34.058556],"type":"Point"}
}