{
  "type": "Feature",
  "properties": {
    "addr:full":"111 E 1st St Cloverdale CA 95425",
    "addr:housenumber":"111",
    "addr:postcode":"95425",
    "addr:street":"E 1St St",
    "iso:country":"US",
    "sg:address":"111 E 1st St",
    "sg:city":"Cloverdale",
    "sg:classifiers":[
        {
            "category":"Shopping",
            "subcategory":"Jewelry",
            "type":"Retail Goods"
        }
    ],
    "sg:phone":"+1 707 894 5015",
    "sg:postcode":"95425",
    "sg:province":"CA",
    "sg:tags":[
        "jeweler"
    ],
    "wof:name":"Joyeria Ruby",
    "wof:placetype":"venue"
},
  "geometry": {"coordinates":[-123.01584099999999,38.805625],"type":"Point"}
}