{
  "type": "Feature",
  "properties": {
    "addr:full":"9171 Towne Centre Dr San Diego CA 92122",
    "addr:housenumber":"9171",
    "addr:postcode":"92122",
    "addr:street":"Towne Centre Dr",
    "iso:country":"US",
    "sg:address":"9171 Towne Centre Dr",
    "sg:city":"San Diego",
    "sg:classifiers":[
        {
            "category":"Building & Trades",
            "subcategory":"Pest Control",
            "type":"Services"
        }
    ],
    "sg:phone":"+1 858 535 2043",
    "sg:postcode":"92122",
    "sg:province":"CA",
    "sg:website":"www.steritech.com",
    "wof:name":"Steritech Group Inc",
    "wof:placetype":"venue"
},
  "geometry": {"coordinates":[-117.207157,32.87339],"type":"Point"}
}