{
  "type": "Feature",
  "properties": {
    "iso:country":"US",
    "sg:address":"1250 Addison St Suite 210",
    "sg:city":"Berkeley",
    "sg:classifiers":[
        {
            "category":"Building & Trades",
            "subcategory":"Construction",
            "type":"Services"
        }
    ],
    "sg:phone":"+1 510 381 2554",
    "sg:postcode":"94702",
    "sg:province":"CA",
    "sg:tags":[
        "contractor"
    ],
    "wof:name":"David B. Collins Builder",
    "wof:placetype":"venue"
},
  "geometry": {"coordinates":[-122.287436,37.868735],"type":"Point"}
}