{
  "type": "Feature",
  "properties": {
    "addr:full":"734 Pacific St San Luis Obispo CA 93401",
    "addr:housenumber":"734",
    "addr:postcode":"93401",
    "addr:street":"Pacific St",
    "iso:country":"US",
    "sg:address":"734 Pacific St",
    "sg:city":"San Luis Obispo",
    "sg:classifiers":[
        {
            "category":"Banks & Credit Unions",
            "subcategory":"Investment Brokerage",
            "type":"Services"
        }
    ],
    "sg:phone":"+1 805 541 6674",
    "sg:postcode":"93401",
    "sg:province":"CA",
    "sg:tags":[
        "security",
        "stock",
        "bond"
    ],
    "wof:name":"Securities America Inc",
    "wof:placetype":"venue"
},
  "geometry": {"coordinates":[-120.662723,35.277664],"type":"Point"}
}