{
  "type": "Feature",
  "properties": {
    "addr:full":"2321 E 4th St Ste C-613 Santa Ana CA 92705",
    "addr:housenumber":"2321",
    "addr:postcode":"92705",
    "addr:street":"E 4Th St Ste C-613",
    "iso:country":"US",
    "sg:address":"2321 E 4th St Ste C-613",
    "sg:city":"Santa Ana",
    "sg:classifiers":[
        {
            "category":"Communications",
            "type":"Services"
        },
        {
            "category":"Utilities",
            "type":"Services"
        }
    ],
    "sg:phone":"+1 949 369 2554",
    "sg:postcode":"92705",
    "sg:province":"CA",
    "sg:tags":[
        "web",
        "provider",
        "design",
        "internet"
    ],
    "sg:website":"www.seostylist.com",
    "wof:name":"Seostylist",
    "wof:placetype":"venue"
},
  "geometry": {"coordinates":[-117.83345199999999,33.748915],"type":"Point"}
}