{
  "type": "Feature",
  "properties": {
    "iso:country":"US",
    "sg:address":"2051 Pelham Ave",
    "sg:city":"Los Angeles",
    "sg:classifiers":[
        {
            "category":"Wholesale",
            "subcategory":"Durable Goods & Equipment",
            "type":"Manufacturing & Wholesale Goods"
        }
    ],
    "sg:phone":"+1 310 470 7811",
    "sg:postcode":"90025",
    "sg:province":"CA",
    "wof:name":"Mdf Products",
    "wof:placetype":"venue"
},
  "geometry": {"coordinates":[-118.429046,34.048599],"type":"Point"}
}