{
  "type": "Feature",
  "properties": {
    "iso:country":"US",
    "sg:address":"1122 Elliott Rd",
    "sg:city":"Paradise",
    "sg:classifiers":[
        {
            "category":"Retail",
            "subcategory":"Auto Repair",
            "type":"Services"
        }
    ],
    "sg:phone":"+1 530 872 8060",
    "sg:postcode":"95969",
    "sg:province":"CA",
    "sg:tags":[
        "body",
        "automobile",
        "painting"
    ],
    "wof:name":"Paradise Auto Body",
    "wof:placetype":"venue"
},
  "geometry": {"coordinates":[-121.605938,39.759434],"type":"Point"}
}