{
  "type": "Feature",
  "properties": {
    "iso:country":"US",
    "sg:address":"3842 International Blvd",
    "sg:city":"Oakland",
    "sg:classifiers":[
        {
            "category":"Restaurant",
            "type":"Food & Drink"
        }
    ],
    "sg:phone":"+1 510 533 2395",
    "sg:postcode":"94601",
    "sg:province":"CA",
    "sg:tags":[
        "american",
        "latin"
    ],
    "sg:website":"www.elhuaracheaztec.com",
    "wof:name":"El Huarache Azteca",
    "wof:placetype":"venue"
},
  "geometry": {"coordinates":[-122.219002,37.774399],"type":"Point"}
}