{
  "type": "Feature",
  "properties": {
    "addr:full":"41622 Big Sage Ct Temecula CA 92591",
    "addr:housenumber":"41622",
    "addr:postcode":"92591",
    "addr:street":"Big Sage Ct",
    "iso:country":"US",
    "sg:address":"41622 Big Sage Ct",
    "sg:city":"Temecula",
    "sg:classifiers":[
        {
            "category":"Building & Trades",
            "subcategory":"Construction",
            "type":"Services"
        }
    ],
    "sg:phone":"+1 951 694 5523",
    "sg:postcode":"92591",
    "sg:province":"CA",
    "sg:tags":[
        "tile",
        "marble",
        "contractor"
    ],
    "wof:name":"David G Jones Marble & Tile Co",
    "wof:placetype":"venue"
},
  "geometry": {"coordinates":[-117.122891,33.515912],"type":"Point"}
}