{
  "type": "Feature",
  "properties": {
    "iso:country":"US",
    "sg:address":"1700 Bay St",
    "sg:city":"Los Angeles",
    "sg:classifiers":[
        {
            "category":"Wholesale",
            "subcategory":"Fruits & Vegetables",
            "type":"Manufacturing & Wholesale Goods"
        }
    ],
    "sg:phone":"+1 213 896 4300",
    "sg:postcode":"90021",
    "sg:province":"CA",
    "sg:website":"www.tdiproduce.com",
    "wof:name":"Tanimura Distributing Inc",
    "wof:placetype":"venue"
},
  "geometry": {"coordinates":[-118.234127,34.031259],"type":"Point"}
}