{
  "type": "Feature",
  "properties": {
    "iso:country":"US",
    "sg:address":"1744 G St",
    "sg:city":"Merced",
    "sg:classifiers":[
        {
            "category":"Professional",
            "subcategory":"Accounting & Tax Preparation",
            "type":"Services"
        }
    ],
    "sg:phone":"+1 209 383 1673",
    "sg:postcode":"95340",
    "sg:province":"CA",
    "sg:tags":[
        "return",
        "filing"
    ],
    "wof:name":"Bayne Bookkeeping & Tax Svc",
    "wof:placetype":"venue"
},
  "geometry": {"coordinates":[-120.475397,37.299186],"type":"Point"}
}