{
  "type": "Feature",
  "properties": {
    "addr:full":"4242 W Sunset Boulevard Suite 11 Los Angeles CA 90029",
    "addr:housenumber":"4242;11",
    "addr:postcode":"90029",
    "addr:street":"W Sunset Boulevard Suite",
    "iso:country":"US",
    "sg:address":"4242 W Sunset Boulevard Suite 11",
    "sg:city":"Los Angeles",
    "sg:classifiers":[
        {
            "category":"Utilities",
            "type":"Services"
        }
    ],
    "sg:phone":"+1 323 669 8660",
    "sg:postcode":"90029",
    "sg:province":"CA",
    "sg:tags":[
        "provider",
        "internet"
    ],
    "wof:name":"Latinoplaza",
    "wof:placetype":"venue"
},
  "geometry": {"coordinates":[-118.282274,34.09413],"type":"Point"}
}