{
  "type": "Feature",
  "properties": {
    "iso:country":"US",
    "sg:address":"4001 El Cajon Boulevard",
    "sg:city":"San Diego",
    "sg:classifiers":[
        {
            "category":"Restaurant",
            "type":"Food & Drink"
        }
    ],
    "sg:phone":"+1 619 280 8474",
    "sg:postcode":"92105",
    "sg:province":"CA",
    "wof:name":"Taste of Italy Restaurant",
    "wof:placetype":"venue"
},
  "geometry": {"coordinates":[-117.108138,32.7552],"type":"Point"}
}