{
  "type": "Feature",
  "properties": {
    "iso:country":"US",
    "sg:address":"PO Box 210482",
    "sg:city":"San Francisco",
    "sg:classifiers":[
        {
            "category":"Recreation",
            "type":"Entertainment"
        }
    ],
    "sg:phone":"+1 415 978 0837",
    "sg:postcode":"94121",
    "sg:province":"CA",
    "sg:tags":[
        "active",
        "life"
    ],
    "sg:website":"dserunners.com",
    "wof:name":"Dolphin South End Running Club",
    "wof:placetype":"venue"
},
  "geometry": {"coordinates":[-122.49498199999999,37.777243],"type":"Point"}
}