{
  "type": "Feature",
  "properties": {
    "addr:full":"3015 O St Sacramento CA 95816",
    "addr:housenumber":"3015",
    "addr:postcode":"95816",
    "addr:street":"O St",
    "iso:country":"US",
    "sg:address":"3015 O St",
    "sg:city":"Sacramento",
    "sg:classifiers":[
        {
            "category":"Health Services",
            "subcategory":"Health Practitioner",
            "type":"Services"
        }
    ],
    "sg:phone":"+1 916 454 6018",
    "sg:postcode":"95816",
    "sg:province":"CA",
    "sg:tags":[
        "psychologist"
    ],
    "wof:name":"Sylvia A Boyle PHD",
    "wof:placetype":"venue"
},
  "geometry": {"coordinates":[-121.467726,38.567382],"type":"Point"}
}