{
  "type": "Feature",
  "properties": {
    "addr:full":"1600 N H St Lompoc CA 93436",
    "addr:housenumber":"1600",
    "addr:postcode":"93436",
    "addr:street":"N H St",
    "iso:country":"US",
    "sg:address":"1600 N H St",
    "sg:city":"Lompoc",
    "sg:classifiers":[
        {
            "category":"Shopping",
            "subcategory":"Department Store",
            "type":"Retail Goods"
        }
    ],
    "sg:phone":"+1 805 736 8822",
    "sg:postcode":"93436",
    "sg:province":"CA",
    "wof:name":"Mervyns California",
    "wof:placetype":"venue"
},
  "geometry": {"coordinates":[-120.45753999999999,34.667761],"type":"Point"}
}