{
  "type": "Feature",
  "properties": {
    "addr:full":"136 Stanford Shopping Ctr Palo Alto CA 94304",
    "addr:housenumber":"136",
    "addr:postcode":"94304",
    "addr:street":"Stanford Shopping Ctr",
    "iso:country":"US",
    "sg:address":"136 Stanford Shopping Ctr",
    "sg:city":"Palo Alto",
    "sg:classifiers":[
        {
            "category":"Restaurant",
            "type":"Food & Drink"
        }
    ],
    "sg:menulink":"http://www.allmenus.com/ca/san-jose/53927-california-pizza-kitchen/menu/",
    "sg:phone":"+1 650 325 2753",
    "sg:postcode":"94304",
    "sg:province":"CA",
    "sg:tags":[
        "sandwich",
        "salad",
        "soup",
        "american",
        "pasta",
        "californian",
        "pizza"
    ],
    "wof:name":"California Pizza Kitchen",
    "wof:placetype":"venue"
},
  "geometry": {"coordinates":[-122.17094299999999,37.444625],"type":"Point"}
}