{
  "type": "Feature",
  "properties": {
    "addr:full":"9501 Keokuk Ave Chatsworth CA 91311",
    "addr:housenumber":"9501",
    "addr:postcode":"91311",
    "addr:street":"Keokuk Ave",
    "iso:country":"US",
    "sg:address":"9501 Keokuk Ave",
    "sg:city":"Chatsworth",
    "sg:classifiers":[
        {
            "category":"Building & Trades",
            "subcategory":"Plumbing",
            "type":"Services"
        }
    ],
    "sg:phone":"+1 818 772 1449",
    "sg:postcode":"91311",
    "sg:province":"CA",
    "sg:tags":[
        "conditioning",
        "air",
        "system",
        "contractor"
    ],
    "wof:name":"Quality Air Heating & Air Cond",
    "wof:placetype":"venue"
},
  "geometry": {"coordinates":[-118.574479,34.243898],"type":"Point"}
}