{
  "type": "Feature",
  "properties": {
    "addr:full":"426 Folsom Rd Roseville CA 95678",
    "addr:housenumber":"426",
    "addr:postcode":"95678",
    "addr:street":"Folsom Rd",
    "iso:country":"US",
    "sg:address":"426 Folsom Rd",
    "sg:city":"Roseville",
    "sg:classifiers":[
        {
            "category":"Organizations",
            "subcategory":"Non-profit Organization",
            "type":"Services"
        }
    ],
    "sg:phone":"+1 916 788 0747",
    "sg:postcode":"95678",
    "sg:province":"CA",
    "wof:name":"International Students Inc",
    "wof:placetype":"venue"
},
  "geometry": {"coordinates":[-121.276741,38.744376],"type":"Point"}
}