{
  "type": "Feature",
  "properties": {
    "addr:full":"1412 N H St Lompoc CA 93436",
    "addr:housenumber":"1412",
    "addr:postcode":"93436",
    "addr:street":"N H St",
    "iso:country":"US",
    "sg:address":"1412 N H St",
    "sg:city":"Lompoc",
    "sg:classifiers":[
        {
            "category":"Restaurant",
            "type":"Food & Drink"
        }
    ],
    "sg:phone":"+1 805 735 9567",
    "sg:postcode":"93436",
    "sg:province":"CA",
    "wof:name":"Burrito Loco Restaurant",
    "wof:placetype":"venue"
},
  "geometry": {"coordinates":[-120.45757399999999,34.664023],"type":"Point"}
}