{
  "type": "Feature",
  "properties": {
    "addr:full":"4681 Convoy St Ste I San Diego CA 92111",
    "addr:housenumber":"4681",
    "addr:postcode":"92111",
    "addr:street":"Convoy St Ste I",
    "iso:country":"US",
    "sg:address":"4681 Convoy St Ste I",
    "sg:city":"San Diego",
    "sg:classifiers":[
        {
            "category":"Restaurant",
            "type":"Food & Drink"
        }
    ],
    "sg:phone":"+1 858 576 7244",
    "sg:postcode":"92111",
    "sg:province":"CA",
    "sg:tags":[
        "japanese"
    ],
    "sg:website":"www.tajimasandiego.com/index.html",
    "wof:name":"Tajima Japanese Restaurant",
    "wof:placetype":"venue"
},
  "geometry": {"coordinates":[-117.154326,32.825694],"type":"Point"}
}