{
  "type": "Feature",
  "properties": {
    "addr:full":"2514 San Marcos Ave San Diego CA 92104",
    "addr:housenumber":"2514",
    "addr:postcode":"92104",
    "addr:street":"San Marcos Ave",
    "iso:country":"US",
    "sg:address":"2514 San Marcos Ave",
    "sg:city":"San Diego",
    "sg:classifiers":[
        {
            "category":"Manufacturing",
            "subcategory":"Toys & Sporting Goods",
            "type":"Manufacturing & Wholesale Goods"
        }
    ],
    "sg:phone":"+1 619 239 9242",
    "sg:postcode":"92104",
    "sg:province":"CA",
    "sg:tags":[
        "equipment",
        "golf",
        "supply"
    ],
    "sg:website":"www.golflaboratories.com",
    "wof:name":"Golf Laboratories",
    "wof:placetype":"venue"
},
  "geometry": {"coordinates":[-117.127298,32.733455],"type":"Point"}
}