{
  "type": "Feature",
  "properties": {
    "addr:full":"233 Winston Dr San Francisco CA 94132",
    "addr:housenumber":"233",
    "addr:postcode":"94132",
    "addr:street":"Winston Dr",
    "iso:country":"US",
    "sg:address":"233 Winston Dr",
    "sg:city":"San Francisco",
    "sg:classifiers":[
        {
            "category":"Shopping",
            "subcategory":"Books",
            "type":"Retail Goods"
        }
    ],
    "sg:phone":"+1 415 731 0665",
    "sg:postcode":"94132",
    "sg:province":"CA",
    "sg:tags":[
        "dealer"
    ],
    "wof:name":"Borders Books Music & Cafe",
    "wof:placetype":"venue"
},
  "geometry": {"coordinates":[-122.475697,37.726814],"type":"Point"}
}