{
  "type": "Feature",
  "properties": {
    "addr:full":"333 E Ramon Rd Palm Springs CA 92264",
    "addr:housenumber":"333",
    "addr:postcode":"92264",
    "addr:street":"E Ramon Rd",
    "iso:country":"US",
    "sg:address":"333 E Ramon Rd",
    "sg:city":"Palm Springs",
    "sg:classifiers":[
        {
            "category":"Travel",
            "subcategory":"Hotels & Motels",
            "type":"Entertainment"
        }
    ],
    "sg:phone":"+1 760 320 7744",
    "sg:postcode":"92264",
    "sg:province":"CA",
    "sg:tags":[
        "breakfast",
        "accommodation",
        "bed"
    ],
    "wof:name":"Three Thirty Three B & B",
    "wof:placetype":"venue"
},
  "geometry": {"coordinates":[-116.54319099999999,33.815805],"type":"Point"}
}