{
  "type": "Feature",
  "properties": {
    "addr:full":"1119 E Santa Clara St San Jose CA 95116",
    "addr:housenumber":"1119",
    "addr:postcode":"95116",
    "addr:street":"E Santa Clara St",
    "iso:country":"US",
    "sg:address":"1119 E Santa Clara St",
    "sg:city":"San Jose",
    "sg:classifiers":[
        {
            "category":"Retail",
            "subcategory":"Auto Repair",
            "type":"Services"
        }
    ],
    "sg:phone":"+1 408 971 6577",
    "sg:postcode":"95116",
    "sg:province":"CA",
    "sg:tags":[
        "body",
        "shop",
        "painting",
        "automobile"
    ],
    "wof:name":"Tac Auto Repair",
    "wof:placetype":"venue"
},
  "geometry": {"coordinates":[-121.86900300000001,37.346699],"type":"Point"}
}