{
  "type": "Feature",
  "properties": {
    "addr:full":"815 Roth Rd French Camp CA 95231",
    "addr:housenumber":"815",
    "addr:postcode":"95231",
    "addr:street":"Roth Rd",
    "iso:country":"US",
    "sg:address":"815 Roth Rd",
    "sg:city":"French Camp",
    "sg:classifiers":[
        {
            "category":"Freight",
            "type":"Transportation"
        }
    ],
    "sg:phone":"+1 209 234 2650",
    "sg:postcode":"95231",
    "sg:province":"CA",
    "sg:tags":[
        "trucking"
    ],
    "wof:name":"Covenant Transport",
    "wof:placetype":"venue"
},
  "geometry": {"coordinates":[-121.268545,37.85568],"type":"Point"}
}