{
  "type": "Feature",
  "properties": {
    "addr:full":"6222 Ferris Sq San Diego CA 92121",
    "addr:housenumber":"6222",
    "addr:postcode":"92121",
    "addr:street":"Ferris Sq",
    "iso:country":"US",
    "sg:address":"6222 Ferris Sq",
    "sg:city":"San Diego",
    "sg:classifiers":[
        {
            "category":"Professional",
            "subcategory":"Computer Services",
            "type":"Services"
        }
    ],
    "sg:phone":"+1 858 410 0700",
    "sg:postcode":"92121",
    "sg:province":"CA",
    "sg:tags":[
        "consultant",
        "designer"
    ],
    "wof:name":"Commentum Corp",
    "wof:placetype":"venue"
},
  "geometry": {"coordinates":[-117.180052,32.889574],"type":"Point"}
}