{
  "type": "Feature",
  "properties": {
    "iso:country":"US",
    "sg:address":"1743 Orange Tree Ln",
    "sg:city":"Redlands",
    "sg:classifiers":[
        {
            "category":"Social Services",
            "subcategory":"Adult Care",
            "type":"Services"
        }
    ],
    "sg:phone":"+1 909 335 1164",
    "sg:postcode":"92374",
    "sg:province":"CA",
    "sg:tags":[
        "foster"
    ],
    "wof:name":"Childhelp Foster Family Agency",
    "wof:placetype":"venue"
},
  "geometry": {"coordinates":[-117.212914,34.067758],"type":"Point"}
}