{
  "type": "Feature",
  "properties": {
    "iso:country":"US",
    "sg:address":"6050 Mission Blvd",
    "sg:city":"Riverside",
    "sg:classifiers":[
        {
            "category":"Professional",
            "subcategory":"Detective & Security Services",
            "type":"Services"
        }
    ],
    "sg:phone":"+1 951 779 2920",
    "sg:postcode":"92509",
    "sg:province":"CA",
    "sg:tags":[
        "guard",
        "patrol"
    ],
    "wof:name":"South West Private Patrol",
    "wof:placetype":"venue"
},
  "geometry": {"coordinates":[-117.417573,34.002054],"type":"Point"}
}