{
  "type": "Feature",
  "properties": {
    "addr:full":"23415 Via San Gabriel Aliso Viejo CA 92656",
    "addr:housenumber":"23415",
    "addr:postcode":"92656",
    "addr:street":"Via San Gabriel Aliso",
    "iso:country":"US",
    "sg:address":"23415 Via San Gabriel",
    "sg:city":"Aliso Viejo",
    "sg:classifiers":[
        {
            "category":"Professional",
            "subcategory":"Computer Services",
            "type":"Services"
        }
    ],
    "sg:phone":"+1 310 619 8482",
    "sg:postcode":"92656",
    "sg:province":"CA",
    "sg:tags":[
        "repair"
    ],
    "sg:website":"www.agilenetsolutions.com",
    "wof:name":"Agile Network Solutions",
    "wof:placetype":"venue"
},
  "geometry": {"coordinates":[-117.72109399999999,33.605155],"type":"Point"}
}