{
  "type": "Feature",
  "properties": {
    "iso:country":"US",
    "sg:address":"811 McHenry Ave",
    "sg:city":"Modesto",
    "sg:classifiers":[
        {
            "category":"Professional",
            "subcategory":"Secretarial Services",
            "type":"Services"
        }
    ],
    "sg:phone":"+1 209 549 8955",
    "sg:postcode":"95350",
    "sg:province":"CA",
    "sg:tags":[
        "information",
        "document",
        "financial"
    ],
    "wof:name":"RFC Finance",
    "wof:placetype":"venue"
},
  "geometry": {"coordinates":[-120.993896,37.655676],"type":"Point"}
}