{
  "type": "Feature",
  "properties": {
    "addr:full":"22827 Hawthorne Blvd Torrance CA 90505",
    "addr:housenumber":"22827",
    "addr:postcode":"90505",
    "addr:street":"Hawthorne Blvd",
    "iso:country":"US",
    "sg:address":"22827 Hawthorne Blvd",
    "sg:city":"Torrance",
    "sg:classifiers":[
        {
            "category":"Personal",
            "subcategory":"Beauty Salon",
            "type":"Services"
        }
    ],
    "sg:phone":"+1 310 373 0759",
    "sg:postcode":"90505",
    "sg:province":"CA",
    "wof:name":"Hair Magic",
    "wof:placetype":"venue"
},
  "geometry": {"coordinates":[-118.35104200000001,33.820073],"type":"Point"}
}