{
  "type": "Feature",
  "properties": {
    "iso:country":"US",
    "sg:address":"7619 Pipit Pl",
    "sg:city":"San Diego",
    "sg:classifiers":[
        {
            "category":"Professional",
            "subcategory":"Management & Consulting",
            "type":"Services"
        }
    ],
    "sg:phone":"+1 858 484 3690",
    "sg:postcode":"92129",
    "sg:province":"CA",
    "sg:tags":[
        "consultant",
        "business"
    ],
    "wof:name":"China Trade Consulting",
    "wof:placetype":"venue"
},
  "geometry": {"coordinates":[-117.158299,32.940541],"type":"Point"}
}