{
  "type": "Feature",
  "properties": {
    "iso:country":"US",
    "sg:address":"3786 N 1st St",
    "sg:city":"Fresno",
    "sg:classifiers":[
        {
            "category":"Social Services",
            "type":"Services"
        }
    ],
    "sg:phone":"+1 559 291 0610",
    "sg:postcode":"93726",
    "sg:province":"CA",
    "wof:name":"ARC Fresno",
    "wof:placetype":"venue"
},
  "geometry": {"coordinates":[-119.772379,36.785131],"type":"Point"}
}