{
  "type": "Feature",
  "properties": {
    "addr:full":"7506 Camellia Ln Stockton CA 95207",
    "addr:housenumber":"7506",
    "addr:postcode":"95207",
    "addr:street":"Camellia Ln",
    "iso:country":"US",
    "sg:address":"7506 Camellia Ln",
    "sg:city":"Stockton",
    "sg:classifiers":[
        {
            "category":"Recreation",
            "type":"Entertainment"
        }
    ],
    "sg:phone":"+1 209 478 4365",
    "sg:postcode":"95207",
    "sg:province":"CA",
    "sg:tags":[
        "club",
        "membership"
    ],
    "wof:name":"Doberman Pinscher Club",
    "wof:placetype":"venue"
},
  "geometry": {"coordinates":[-121.336612,38.016776],"type":"Point"}
}