{
  "type": "Feature",
  "properties": {
    "addr:full":"691 Donna Dr Martinez CA 94553",
    "addr:housenumber":"691",
    "addr:postcode":"94553",
    "addr:street":"Donna Dr",
    "iso:country":"US",
    "sg:address":"691 Donna Dr",
    "sg:city":"Martinez",
    "sg:classifiers":[
        {
            "category":"Building & Trades",
            "subcategory":"Plumbing",
            "type":"Services"
        }
    ],
    "sg:phone":"+1 925 335 0395",
    "sg:postcode":"94553",
    "sg:province":"CA",
    "sg:tags":[
        "contractor"
    ],
    "wof:name":"Guerra Bros Plumbing",
    "wof:placetype":"venue"
},
  "geometry": {"coordinates":[-122.087761,38.017656],"type":"Point"}
}