{
  "type": "Feature",
  "properties": {
    "iso:country":"US",
    "sg:address":"140 Pinal Ave",
    "sg:city":"Orcutt",
    "sg:classifiers":[
        {
            "category":"Professional",
            "subcategory":"Business Services",
            "type":"Services"
        }
    ],
    "sg:phone":"+1 805 714 3257",
    "sg:postcode":"93455",
    "sg:province":"CA",
    "sg:tags":[
        "sales",
        "estate"
    ],
    "wof:name":"C & L Estate Sales",
    "wof:placetype":"venue"
},
  "geometry": {"coordinates":[-120.447008,34.863054],"type":"Point"}
}