{
  "type": "Feature",
  "properties": {
    "iso:country":"US",
    "sg:address":"10240 Westminster Ave Ste 101",
    "sg:city":"Garden Grove",
    "sg:classifiers":[
        {
            "category":"Restaurant",
            "type":"Food & Drink"
        }
    ],
    "sg:phone":"+1 714 534 3210",
    "sg:postcode":"92843",
    "sg:province":"CA",
    "wof:name":"Pho 54 Restaurant",
    "wof:placetype":"venue"
},
  "geometry": {"coordinates":[-117.949997,33.759499],"type":"Point"}
}