{
  "type": "Feature",
  "properties": {
    "addr:full":"1265 W McCoy Ln Ste A Santa Maria CA 93455",
    "addr:housenumber":"1265",
    "addr:postcode":"93455",
    "addr:street":"W Mccoy Ln Ste A",
    "iso:country":"US",
    "sg:address":"1265 W McCoy Ln Ste A",
    "sg:city":"Santa Maria",
    "sg:classifiers":[
        {
            "category":"Organizations",
            "subcategory":"Religious Organization",
            "type":"Services"
        }
    ],
    "sg:phone":"+1 805 347 7682",
    "sg:postcode":"93455",
    "sg:province":"CA",
    "wof:name":"Iglesia Internacional",
    "wof:placetype":"venue"
},
  "geometry": {"coordinates":[-120.457151,34.916904],"type":"Point"}
}