{
  "type": "Feature",
  "properties": {
    "addr:full":"8533 E Ave T Littlerock CA 93543",
    "addr:housenumber":"8533",
    "addr:postcode":"93543",
    "addr:street":"E Ave",
    "iso:country":"US",
    "sg:address":"8533 E Ave T",
    "sg:city":"Littlerock",
    "sg:classifiers":[
        {
            "category":"Organizations",
            "subcategory":"Religious Organization",
            "type":"Services"
        }
    ],
    "sg:phone":"+1 661 944 1880",
    "sg:postcode":"93543",
    "sg:province":"CA",
    "sg:tags":[
        "church"
    ],
    "sg:website":"www.cornerstonelittlerock.org",
    "wof:name":"Cornerstone Church-Littlerock",
    "wof:placetype":"venue"
},
  "geometry": {"coordinates":[-117.977672,34.542987],"type":"Point"}
}