{
  "type": "Feature",
  "properties": {
    "addr:full":"2625 E Anaheim St Long Beach CA 90804",
    "addr:housenumber":"2625",
    "addr:postcode":"90804",
    "addr:street":"E Anaheim St",
    "iso:country":"US",
    "sg:address":"2625 E Anaheim St",
    "sg:city":"Long Beach",
    "sg:classifiers":[
        {
            "category":"Retail",
            "subcategory":"Auto Repair",
            "type":"Services"
        }
    ],
    "sg:phone":"+1 562 443 9958",
    "sg:postcode":"90804",
    "sg:province":"CA",
    "sg:tags":[
        "body",
        "shop"
    ],
    "wof:name":"Laszlo's Auto Body and Painting",
    "wof:placetype":"venue"
},
  "geometry": {"coordinates":[-118.16100299999999,33.7827],"type":"Point"}
}