{
  "type": "Feature",
  "properties": {
    "iso:country":"US",
    "sg:address":"10429 Sultana Ave",
    "sg:city":"Fontana",
    "sg:classifiers":[
        {
            "category":"Retail",
            "subcategory":"Auto Repair",
            "type":"Services"
        }
    ],
    "sg:phone":"+1 909 428 3410",
    "sg:postcode":"92337",
    "sg:province":"CA",
    "sg:tags":[
        "lettering",
        "truck"
    ],
    "wof:name":"All America Truck & Auto Body",
    "wof:placetype":"venue"
},
  "geometry": {"coordinates":[-117.468817,34.063375],"type":"Point"}
}