{
  "type": "Feature",
  "properties": {
    "addr:full":"22160 State Hwy 33 Crows Landing CA 95313",
    "addr:housenumber":"22160",
    "addr:postcode":"95313",
    "addr:street":"State Hwy 33",
    "iso:country":"US",
    "sg:address":"22160 State Hwy 33",
    "sg:city":"Crows Landing",
    "sg:classifiers":[
        {
            "category":"Wholesale",
            "subcategory":"Auto Parts",
            "type":"Manufacturing & Wholesale Goods"
        }
    ],
    "sg:phone":"+1 209 837 9999",
    "sg:postcode":"95313",
    "sg:province":"CA",
    "wof:name":"Powers Transmissions",
    "wof:placetype":"venue"
},
  "geometry": {"coordinates":[-121.070666,37.392113],"type":"Point"}
}