{
  "type": "Feature",
  "properties": {
    "iso:country":"US",
    "sg:address":"3 Quail Run Cir",
    "sg:city":"Salinas",
    "sg:classifiers":[
        {
            "category":"Real Estate",
            "subcategory":"Developer",
            "type":"Services"
        }
    ],
    "sg:phone":"+1 831 772 8100",
    "sg:postcode":"93907",
    "sg:province":"CA",
    "wof:name":"Shaw Development",
    "wof:placetype":"venue"
},
  "geometry": {"coordinates":[-121.670458,36.68575],"type":"Point"}
}