{
  "type": "Feature",
  "properties": {
    "iso:country":"US",
    "sg:address":"2207 Garnet Avenue",
    "sg:city":"San Diego",
    "sg:classifiers":[
        {
            "category":"Real Estate",
            "subcategory":"Real Estate Services",
            "type":"Services"
        }
    ],
    "sg:phone":"+1 858 272 1348",
    "sg:postcode":"92109",
    "sg:province":"CA",
    "sg:tags":[
        "management",
        "property"
    ],
    "wof:name":"Reis John A & Company",
    "wof:placetype":"venue"
},
  "geometry": {"coordinates":[-117.22975,32.80222],"type":"Point"}
}