{
  "type": "Feature",
  "properties": {
    "addr:full":"370 Brannan St Fl 2 San Francisco CA 94107",
    "addr:housenumber":"370",
    "addr:postcode":"2;94107",
    "addr:street":"Brannan St",
    "iso:country":"US",
    "sg:address":"370 Brannan St Fl 2",
    "sg:city":"San Francisco",
    "sg:classifiers":[
        {
            "category":"Real Estate",
            "subcategory":"Architect",
            "type":"Services"
        }
    ],
    "sg:phone":"+1 415 575 0888",
    "sg:postcode":"94107",
    "sg:province":"CA",
    "wof:name":"Rupel Geiszler McLeod Architecture",
    "wof:placetype":"venue"
},
  "geometry": {"coordinates":[-122.393783,37.780686],"type":"Point"}
}