{
  "type": "Feature",
  "properties": {
    "addr:full":"5341 W 104th St Los Angeles CA 90045",
    "addr:housenumber":"5341",
    "addr:postcode":"90045",
    "addr:street":"W 104Th St",
    "iso:country":"US",
    "sg:address":"5341 W 104th St",
    "sg:city":"Los Angeles",
    "sg:classifiers":[
        {
            "category":"Freight",
            "type":"Transportation"
        }
    ],
    "sg:phone":"+1 310 641 0029",
    "sg:postcode":"90045",
    "sg:province":"CA",
    "sg:tags":[
        "delivery"
    ],
    "wof:name":"Five Star Svc",
    "wof:placetype":"venue"
},
  "geometry": {"coordinates":[-118.375524,33.942041],"type":"Point"}
}