{
  "type": "Feature",
  "properties": {
    "iso:country":"US",
    "sg:address":"4664 Mercury St",
    "sg:city":"San Diego",
    "sg:classifiers":[
        {
            "category":"Wholesale",
            "subcategory":"Machinery & Supplies",
            "type":"Manufacturing & Wholesale Goods"
        }
    ],
    "sg:phone":"+1 858 268 3830",
    "sg:postcode":"92111",
    "sg:province":"CA",
    "sg:tags":[
        "bookbinder",
        "equipment"
    ],
    "sg:website":"www.custombinding.com",
    "wof:name":"Custom Binding Products",
    "wof:placetype":"venue"
},
  "geometry": {"coordinates":[-117.148918,32.826715],"type":"Point"}
}