{
  "type": "Feature",
  "properties": {
    "iso:country":"US",
    "sg:address":"1800 W 6th St",
    "sg:city":"Los Angeles",
    "sg:classifiers":[
        {
            "category":"Banks & Credit Unions",
            "subcategory":"Bank",
            "type":"Services"
        }
    ],
    "sg:phone":"+1 213 413 6257",
    "sg:postcode":"90057",
    "sg:province":"CA",
    "sg:tags":[
        "money",
        "transfer"
    ],
    "wof:name":"Nix Check Cashing",
    "wof:placetype":"venue"
},
  "geometry": {"coordinates":[-118.27242200000001,34.058451],"type":"Point"}
}