{
  "type": "Feature",
  "properties": {
    "addr:full":"1197 San Pablo Avenue Albany CA 94706",
    "addr:housenumber":"1197",
    "addr:postcode":"94706",
    "addr:street":"San Pablo Avenue",
    "iso:country":"US",
    "sg:address":"1197 San Pablo Avenue",
    "sg:city":"Albany",
    "sg:classifiers":[
        {
            "category":"Retail",
            "subcategory":"Auto Repair",
            "type":"Services"
        }
    ],
    "sg:phone":"+1 510 527 5226",
    "sg:postcode":"94706",
    "sg:province":"CA",
    "wof:name":"Gilman Auto",
    "wof:placetype":"venue"
},
  "geometry": {"coordinates":[-122.295998,37.8825],"type":"Point"}
}