{
  "type": "Feature",
  "properties": {
    "addr:full":"379 Diablo Rd Danville CA 94526",
    "addr:housenumber":"379",
    "addr:postcode":"94526",
    "addr:street":"Diablo Rd",
    "iso:country":"US",
    "sg:address":"379 Diablo Rd",
    "sg:city":"Danville",
    "sg:classifiers":[
        {
            "category":"Wholesale",
            "subcategory":"Auto Parts",
            "type":"Manufacturing & Wholesale Goods"
        }
    ],
    "sg:phone":"+1 412 434 4044",
    "sg:postcode":"94526",
    "sg:province":"CA",
    "sg:tags":[
        "glass",
        "replacement"
    ],
    "wof:name":"P P G Auto Glass",
    "wof:placetype":"venue"
},
  "geometry": {"coordinates":[-121.997607,37.822883],"type":"Point"}
}