{
  "type": "Feature",
  "properties": {
    "addr:full":"1065 Viewpoint Blvd Rodeo CA 94572",
    "addr:housenumber":"1065",
    "addr:postcode":"94572",
    "addr:street":"Viewpoint Blvd",
    "iso:country":"US",
    "sg:address":"1065 Viewpoint Blvd",
    "sg:city":"Rodeo",
    "sg:classifiers":[
        {
            "category":"Shopping",
            "subcategory":"Catalog Store",
            "type":"Retail Goods"
        }
    ],
    "sg:phone":"+1 510 799 1329",
    "sg:postcode":"94572",
    "sg:province":"CA",
    "sg:tags":[
        "mail",
        "house"
    ],
    "wof:name":"Monica Leclerq",
    "wof:placetype":"venue"
},
  "geometry": {"coordinates":[-122.25147200000001,38.027168],"type":"Point"}
}