{
  "type": "Feature",
  "properties": {
    "iso:country":"US",
    "sg:address":"17965 Monterey St",
    "sg:city":"Morgan Hill",
    "sg:classifiers":[
        {
            "category":"Food & Beverages",
            "subcategory":"Specialty",
            "type":"Retail Goods"
        }
    ],
    "sg:phone":"+1 408 778 4178",
    "sg:postcode":"95037",
    "sg:province":"CA",
    "sg:tags":[
        "american",
        "latin",
        "mexican",
        "product"
    ],
    "wof:name":"Artesanias Jalisco",
    "wof:placetype":"venue"
},
  "geometry": {"coordinates":[-121.660425,37.137129],"type":"Point"}
}