{
  "type": "Feature",
  "properties": {
    "iso:country":"US",
    "sg:address":"142 N Sunningdale Cir",
    "sg:city":"Orange",
    "sg:classifiers":[
        {
            "category":"Building & Trades",
            "subcategory":"Landscaping Services",
            "type":"Services"
        }
    ],
    "sg:phone":"+1 714 385 0171",
    "sg:postcode":"92868",
    "sg:province":"CA",
    "wof:name":"La Landscape Gardening",
    "wof:placetype":"venue"
},
  "geometry": {"coordinates":[-117.896592,33.789797],"type":"Point"}
}