{
  "type": "Feature",
  "properties": {
    "addr:full":"2700 Esplanade Chico CA 95973",
    "addr:housenumber":"2700",
    "addr:postcode":"95973",
    "addr:street":"Esplanade Chico",
    "iso:country":"US",
    "sg:address":"2700 Esplanade",
    "sg:city":"Chico",
    "sg:classifiers":[
        {
            "category":"Building & Trades",
            "subcategory":"Landscaping Services",
            "type":"Services"
        }
    ],
    "sg:phone":"+1 530 895 8073",
    "sg:postcode":"95973",
    "sg:province":"CA",
    "sg:tags":[
        "designer",
        "landscape"
    ],
    "wof:name":"Carl Rottschalk Landscape Artc",
    "wof:placetype":"venue"
},
  "geometry": {"coordinates":[-121.864672,39.760047],"type":"Point"}
}