{
  "type": "Feature",
  "properties": {
    "iso:country":"US",
    "sg:address":"1031 National City Blvd",
    "sg:city":"National City",
    "sg:classifiers":[
        {
            "category":"Retail",
            "subcategory":"Auto Repair",
            "type":"Services"
        }
    ],
    "sg:phone":"+1 619 477 9206",
    "sg:postcode":"91950",
    "sg:province":"CA",
    "sg:tags":[
        "transmission"
    ],
    "wof:name":"LA Mesa Transmission & Engine",
    "wof:placetype":"venue"
},
  "geometry": {"coordinates":[-117.105936,32.673522],"type":"Point"}
}