{
  "type": "Feature",
  "properties": {
    "iso:country":"US",
    "sg:address":"702 Earl Street",
    "sg:city":"San Francisco",
    "sg:classifiers":[
        {
            "category":"Building & Trades",
            "subcategory":"Construction",
            "type":"Services"
        }
    ],
    "sg:phone":"+1 415 643 1376",
    "sg:postcode":"94124",
    "sg:province":"CA",
    "sg:tags":[
        "contractor"
    ],
    "wof:name":"Michael Hamman, General Contractor",
    "wof:placetype":"venue"
},
  "geometry": {"coordinates":[-122.37038099999999,37.731837],"type":"Point"}
}