{
  "type": "Feature",
  "properties": {
    "iso:country":"US",
    "sg:address":"226 Laurel Ave",
    "sg:city":"Pacific Grove",
    "sg:classifiers":[
        {
            "category":"Shopping",
            "subcategory":"Hobbies, Toys, & Games",
            "type":"Retail Goods"
        }
    ],
    "sg:phone":"+1 831 646 5279",
    "sg:postcode":"93950",
    "sg:province":"CA",
    "wof:name":"Hobbie Richard A Jean A H",
    "wof:placetype":"venue"
},
  "geometry": {"coordinates":[-121.90933800000001,36.617314],"type":"Point"}
}