{
  "type": "Feature",
  "properties": {
    "addr:full":"12190 Perris Blvd Moreno Valley CA 92557",
    "addr:housenumber":"12190",
    "addr:postcode":"92557",
    "addr:street":"Perris Blvd",
    "iso:country":"US",
    "sg:address":"12190 Perris Blvd",
    "sg:city":"Moreno Valley",
    "sg:classifiers":[
        {
            "category":"Restaurant",
            "type":"Food & Drink"
        }
    ],
    "sg:menulink":"http://www.allmenus.com/ca/riverside/87865-little-caesars-pizza/menu/",
    "sg:phone":"+1 951 571 0045",
    "sg:postcode":"92557",
    "sg:province":"CA",
    "sg:tags":[
        "american",
        "pizza"
    ],
    "wof:name":"Little Caesar's Pizza",
    "wof:placetype":"venue"
},
  "geometry": {"coordinates":[-117.22624,33.944321],"type":"Point"}
}