{
  "type": "Feature",
  "properties": {
    "iso:country":"US",
    "sg:address":"5787 Rosemead Blvd",
    "sg:city":"Temple City",
    "sg:classifiers":[
        {
            "category":"Shopping",
            "subcategory":"Mobile Phones",
            "type":"Retail Goods"
        }
    ],
    "sg:phone":"+1 626 237 0505",
    "sg:postcode":"91780",
    "sg:province":"CA",
    "wof:name":"AT&T California",
    "wof:placetype":"venue"
},
  "geometry": {"coordinates":[-118.37942700000001,34.104779],"type":"Point"}
}