{
  "type": "Feature",
  "properties": {
    "iso:country":"US",
    "sg:address":"938 Zook Dr",
    "sg:city":"Glendale",
    "sg:classifiers":[
        {
            "category":"Mining & Drilling",
            "type":"Manufacturing & Wholesale Goods"
        }
    ],
    "sg:phone":"+1 818 241 9500",
    "sg:postcode":"91202",
    "sg:province":"CA",
    "sg:tags":[
        "ore",
        "gold"
    ],
    "wof:name":"Yellow Dog Mining Co Inc",
    "wof:placetype":"venue"
},
  "geometry": {"coordinates":[-118.280145,34.160665],"type":"Point"}
}