{
  "type": "Feature",
  "properties": {
    "iso:country":"US",
    "sg:address":"5723 E Bryce Ave",
    "sg:city":"Orange",
    "sg:classifiers":[
        {
            "category":"Farming",
            "subcategory":"Fish & Marine Products",
            "type":"Manufacturing & Wholesale Goods"
        }
    ],
    "sg:phone":"+1 714 749 8811",
    "sg:postcode":"92867",
    "sg:province":"CA",
    "sg:tags":[
        "fishing"
    ],
    "wof:name":"Amber Marie",
    "wof:placetype":"venue"
},
  "geometry": {"coordinates":[-117.792084,33.820178],"type":"Point"}
}