{
  "type": "Feature",
  "properties": {
    "iso:country":"US",
    "sg:address":"13001 Venice Blvd. Suite 3",
    "sg:city":"Los Angeles",
    "sg:classifiers":[
        {
            "category":"Professional",
            "subcategory":"Art Services",
            "type":"Services"
        },
        {
            "category":"Communications",
            "type":"Services"
        }
    ],
    "sg:phone":"+1 310 751 6168",
    "sg:postcode":"90066",
    "sg:province":"CA",
    "sg:tags":[
        "web",
        "graphic",
        "design"
    ],
    "sg:website":"www.brandedlegion.com",
    "wof:name":"Branded Legion",
    "wof:placetype":"venue"
},
  "geometry": {"coordinates":[-118.44298000000001,33.999361],"type":"Point"}
}