{
  "type": "Feature",
  "properties": {
    "addr:full":"1201 Sanborn Ave Los Angeles CA 90029",
    "addr:housenumber":"1201",
    "addr:postcode":"90029",
    "addr:street":"Sanborn Ave",
    "iso:country":"US",
    "sg:address":"1201 Sanborn Ave",
    "sg:city":"Los Angeles",
    "sg:classifiers":[
        {
            "category":"Autos & Motor Vehicles",
            "subcategory":"Automobile Sales",
            "type":"Retail Goods"
        }
    ],
    "sg:phone":"+1 323 668 2070",
    "sg:postcode":"90029",
    "sg:province":"CA",
    "sg:tags":[
        "limo"
    ],
    "wof:name":"Alumni Limousine Service",
    "wof:placetype":"venue"
},
  "geometry": {"coordinates":[-118.278999,34.094299],"type":"Point"}
}