{
  "type": "Feature",
  "properties": {
    "addr:full":"18457 Colima Rd Rowland Heights CA 91748",
    "addr:postcode":"18457;91748",
    "addr:street":"Colima Rd",
    "iso:country":"US",
    "sg:address":"18457 Colima Rd",
    "sg:city":"Rowland Heights",
    "sg:classifiers":[
        {
            "category":"Restaurant",
            "type":"Food & Drink"
        }
    ],
    "sg:phone":"+1 626 839 7550",
    "sg:postcode":"91748",
    "sg:province":"CA",
    "wof:name":"Pacific Plaza",
    "wof:placetype":"venue"
},
  "geometry": {"coordinates":[-117.90119,33.98817],"type":"Point"}
}