{
  "type": "Feature",
  "properties": {
    "addr:full":"12474 Cottonwood St Ste B Victorville CA 92395",
    "addr:housenumber":"12474",
    "addr:postcode":"92395",
    "addr:street":"Cottonwood St Ste B",
    "iso:country":"US",
    "sg:address":"12474 Cottonwood St Ste B",
    "sg:city":"Victorville",
    "sg:classifiers":[
        {
            "category":"Arts & Performance",
            "subcategory":"Dance",
            "type":"Entertainment"
        }
    ],
    "sg:phone":"+1 760 241 8277",
    "sg:postcode":"92395",
    "sg:province":"CA",
    "sg:tags":[
        "instruction",
        "dancing"
    ],
    "wof:name":"Dance Time Studio",
    "wof:placetype":"venue"
},
  "geometry": {"coordinates":[-117.33873800000001,34.473424],"type":"Point"}
}