{
  "type": "Feature",
  "properties": {
    "iso:country":"US",
    "sg:address":"The Travelodge 1201 Hotel Cir S",
    "sg:city":"San Diego",
    "sg:classifiers":[
        {
            "category":"Bars & Pubs",
            "subcategory":"Lounge",
            "type":"Food & Drink"
        },
        {
            "category":"Restaurant",
            "type":"Food & Drink"
        }
    ],
    "sg:phone":"+1 619 291 1103",
    "sg:postcode":"92108",
    "sg:province":"CA",
    "sg:tags":[
        "traditional",
        "american",
        "steakhouse"
    ],
    "sg:website":"www.albiesbeefinn.com",
    "wof:name":"Albie's Beef Inn",
    "wof:placetype":"venue"
},
  "geometry": {"coordinates":[-117.173394,32.759432],"type":"Point"}
}