{
  "type": "Feature",
  "properties": {
    "iso:country":"US",
    "sg:address":"2604 S Vermont Avenue Suite D",
    "sg:city":"Los Angeles",
    "sg:classifiers":[
        {
            "category":"Restaurant",
            "type":"Food & Drink"
        }
    ],
    "sg:phone":"+1 323 732 1318",
    "sg:postcode":"90007",
    "sg:province":"CA",
    "wof:name":"Hong Kong Express",
    "wof:placetype":"venue"
},
  "geometry": {"coordinates":[-118.29151299999999,34.032591],"type":"Point"}
}