{
  "type": "Feature",
  "properties": {
    "addr:full":"4917 Central Ave Fremont CA 94536",
    "addr:housenumber":"4917",
    "addr:postcode":"94536",
    "addr:street":"Central Ave",
    "iso:country":"US",
    "sg:address":"4917 Central Ave",
    "sg:city":"Fremont",
    "sg:classifiers":[
        {
            "category":"Building & Trades",
            "subcategory":"Electrical",
            "type":"Services"
        }
    ],
    "sg:phone":"+1 510 607 0333",
    "sg:postcode":"94536",
    "sg:province":"CA",
    "sg:tags":[
        "electrical",
        "contractor"
    ],
    "wof:name":"Lesher Electric",
    "wof:placetype":"venue"
},
  "geometry": {"coordinates":[-122.013131,37.545081],"type":"Point"}
}