{
  "type": "Feature",
  "properties": {
    "iso:country":"US",
    "sg:address":"5150 N 6th St #167",
    "sg:city":"Fresno",
    "sg:classifiers":[
        {
            "category":"Insurance",
            "subcategory":"Hazard Insurance",
            "type":"Services"
        },
        {
            "category":"Insurance",
            "subcategory":"Insurance Agent",
            "type":"Services"
        },
        {
            "category":"Insurance",
            "subcategory":"Life Insurance",
            "type":"Services"
        },
        {
            "category":"Insurance",
            "subcategory":"Title Insurance",
            "type":"Services"
        }
    ],
    "sg:phone":"+1 559 244 6444",
    "sg:postcode":"93710",
    "sg:province":"CA",
    "sg:tags":[
        "auto",
        "commercial",
        "business",
        "homeowner"
    ],
    "sg:website":"http://www.farmersagent.com/jcunningham3/",
    "wof:name":"Jim Cunningham - Farmers Insurance",
    "wof:placetype":"venue"
},
  "geometry": {"coordinates":[-119.763102,36.811997],"type":"Point"}
}