{
  "type": "Feature",
  "properties": {
    "iso:country":"US",
    "sg:address":"1450 Lincoln Ave",
    "sg:city":"Calistoga",
    "sg:classifiers":[
        {
            "category":"Home & Garden",
            "subcategory":"Hardware",
            "type":"Retail Goods"
        }
    ],
    "sg:phone":"+1 707 942 4396",
    "sg:postcode":"94515",
    "sg:province":"CA",
    "sg:tags":[
        "store"
    ],
    "sg:website":"www.silveradoace.com",
    "wof:name":"Silverado Ace Hardware",
    "wof:placetype":"venue"
},
  "geometry": {"coordinates":[-122.578003,38.5797],"type":"Point"}
}