{
  "type": "Feature",
  "properties": {
    "addr:full":"103 Scripps Dr Sacramento CA 95825",
    "addr:housenumber":"103",
    "addr:postcode":"95825",
    "addr:street":"Scripps Dr",
    "iso:country":"US",
    "sg:address":"103 Scripps Dr",
    "sg:city":"Sacramento",
    "sg:classifiers":[
        {
            "category":"Health Services",
            "subcategory":"Doctor",
            "type":"Services"
        }
    ],
    "sg:phone":"+1 916 929 4546",
    "sg:postcode":"95825",
    "sg:province":"CA",
    "sg:tags":[
        "dentist"
    ],
    "wof:name":"Harry M Viani Inc",
    "wof:placetype":"venue"
},
  "geometry": {"coordinates":[-121.409149,38.571369],"type":"Point"}
}