{
  "type": "Feature",
  "properties": {
    "iso:country":"US",
    "sg:address":"199 S Grove Ave",
    "sg:city":"Ontario",
    "sg:classifiers":[
        {
            "category":"Wholesale",
            "subcategory":"Drugs",
            "type":"Manufacturing & Wholesale Goods"
        }
    ],
    "sg:phone":"+1 909 923 1166",
    "sg:postcode":"91761",
    "sg:province":"CA",
    "wof:name":"SF & B LLC",
    "wof:placetype":"venue"
},
  "geometry": {"coordinates":[-117.628423,34.063264],"type":"Point"}
}