{
  "type": "Feature",
  "properties": {
    "addr:full":"7035 N Lake Blvd Tahoe Vista CA 96148",
    "addr:housenumber":"7035",
    "addr:postcode":"96148",
    "addr:street":"N Lake Blvd",
    "iso:country":"US",
    "sg:address":"7035 N Lake Blvd",
    "sg:city":"Tahoe Vista",
    "sg:classifiers":[
        {
            "category":"Freight",
            "type":"Transportation"
        }
    ],
    "sg:phone":"+1 530 546 0909",
    "sg:postcode":"96148",
    "sg:province":"CA",
    "sg:tags":[
        "trucking"
    ],
    "wof:name":"American Ranch Inc",
    "wof:placetype":"venue"
},
  "geometry": {"coordinates":[-120.04144700000001,39.238694],"type":"Point"}
}