{
  "type": "Feature",
  "properties": {
    "iso:country":"US",
    "sg:address":"25991 Summer Hill Ct",
    "sg:city":"Murrieta",
    "sg:classifiers":[
        {
            "category":"Freight",
            "type":"Transportation"
        }
    ],
    "sg:phone":"+1 951 677 5524",
    "sg:postcode":"92563",
    "sg:province":"CA",
    "sg:tags":[
        "local",
        "without",
        "storage",
        "trucking"
    ],
    "wof:name":"Richard G Aguirre",
    "wof:placetype":"venue"
},
  "geometry": {"coordinates":[-117.16663,33.557094],"type":"Point"}
}