{
  "type": "Feature",
  "properties": {
    "iso:country":"US",
    "sg:address":"6265 Greenwich Dr",
    "sg:city":"San Diego",
    "sg:classifiers":[
        {
            "category":"Professional",
            "type":"Services"
        }
    ],
    "sg:phone":"+1 858 677 0156",
    "sg:postcode":"92122",
    "sg:province":"CA",
    "sg:website":"californiadiatomite.com/",
    "wof:name":"California Diatomite",
    "wof:placetype":"venue"
},
  "geometry": {"coordinates":[-117.18454300000001,32.854617],"type":"Point"}
}