{
  "type": "Feature",
  "properties": {
    "iso:country":"US",
    "sg:address":"1405 W 228th St",
    "sg:city":"Torrance",
    "sg:classifiers":[
        {
            "category":"Retail",
            "subcategory":"Animal Services",
            "type":"Services"
        }
    ],
    "sg:phone":"+1 310 328 7534",
    "sg:postcode":"90501",
    "sg:province":"CA",
    "wof:name":"Cal Kerry Kennels",
    "wof:placetype":"venue"
},
  "geometry": {"coordinates":[-118.303596,33.819088],"type":"Point"}
}