{
  "type": "Feature",
  "properties": {
    "iso:country":"US",
    "sg:address":"3421 E 14th Street",
    "sg:city":"Los Angeles",
    "sg:classifiers":[
        {
            "category":"Restaurant",
            "type":"Food & Drink"
        }
    ],
    "sg:phone":"+1 323 268 2267",
    "sg:postcode":"90023",
    "sg:province":"CA",
    "wof:name":"King Taco Restaurant",
    "wof:placetype":"venue"
},
  "geometry": {"coordinates":[-118.206164,34.017237],"type":"Point"}
}