{
  "type": "Feature",
  "properties": {
    "iso:country":"US",
    "sg:address":"16870 W Bernardo Dr",
    "sg:city":"San Diego",
    "sg:classifiers":[
        {
            "category":"Wholesale",
            "subcategory":"Computers",
            "type":"Manufacturing & Wholesale Goods"
        },
        {
            "category":"Professional",
            "subcategory":"Computer Services",
            "type":"Services"
        }
    ],
    "sg:phone":"+1 858 521 1382",
    "sg:postcode":"92127",
    "sg:province":"CA",
    "sg:tags":[
        "repair"
    ],
    "wof:name":"Pacific Mind Works",
    "wof:placetype":"venue"
},
  "geometry": {"coordinates":[-117.09985,33.985942],"type":"Point"}
}