{
  "type": "Feature",
  "properties": {
    "iso:country":"US",
    "sg:address":"5680 Lake Murray Blvd",
    "sg:city":"La Mesa",
    "sg:classifiers":[
        {
            "category":"Personal",
            "type":"Services"
        }
    ],
    "sg:phone":"+1 619 469 9962",
    "sg:postcode":"91942",
    "sg:province":"CA",
    "sg:tags":[
        "electrolysis"
    ],
    "wof:name":"Bette's Electrolysis",
    "wof:placetype":"venue"
},
  "geometry": {"coordinates":[-117.028886,32.783207],"type":"Point"}
}