{
  "type": "Feature",
  "properties": {
    "addr:full":"600 A St Davis CA 95616",
    "addr:housenumber":"600",
    "addr:postcode":"95616",
    "addr:street":"A St",
    "iso:country":"US",
    "sg:address":"600 A St",
    "sg:city":"Davis",
    "sg:classifiers":[
        {
            "category":"Government",
            "subcategory":"Office",
            "type":"Public Place"
        }
    ],
    "sg:phone":"+1 530 757 5695",
    "sg:postcode":"95616",
    "sg:province":"CA",
    "sg:tags":[
        "city",
        "resource",
        "human"
    ],
    "wof:name":"Davis City Child Care Subsidy",
    "wof:placetype":"venue"
},
  "geometry": {"coordinates":[-121.747688,38.547744],"type":"Point"}
}