{
  "type": "Feature",
  "properties": {
    "addr:full":"5101 E Clinton Way Fresno CA 93727",
    "addr:housenumber":"5101",
    "addr:postcode":"93727",
    "addr:street":"E Clinton Way",
    "iso:country":"US",
    "sg:address":"5101 E Clinton Way",
    "sg:city":"Fresno",
    "sg:classifiers":[
        {
            "category":"Retail",
            "subcategory":"Auto Rental",
            "type":"Services"
        }
    ],
    "sg:phone":"+1 559 454 5029",
    "sg:postcode":"93727",
    "sg:province":"CA",
    "sg:tags":[
        "renting",
        "automobile"
    ],
    "wof:name":"Avis Rent A Car",
    "wof:placetype":"venue"
},
  "geometry": {"coordinates":[-119.718288,36.76517],"type":"Point"}
}