{
  "type": "Feature",
  "properties": {
    "addr:full":"360 W Court St San Bernardino CA 92401",
    "addr:housenumber":"360",
    "addr:postcode":"92401",
    "addr:street":"W Court St",
    "iso:country":"US",
    "sg:address":"360 W Court St",
    "sg:city":"San Bernardino",
    "sg:classifiers":[
        {
            "category":"Restaurant",
            "type":"Food & Drink"
        }
    ],
    "sg:phone":"+1 909 889 1183",
    "sg:postcode":"92401",
    "sg:province":"CA",
    "sg:tags":[
        "shop",
        "coffee"
    ],
    "wof:name":"Coffee Rocket",
    "wof:placetype":"venue"
},
  "geometry": {"coordinates":[-117.290699,34.105591],"type":"Point"}
}