{
  "type": "Feature",
  "properties": {
    "addr:full":"231 S Center St Turlock CA 95380",
    "addr:housenumber":"231",
    "addr:postcode":"95380",
    "addr:street":"S Center St",
    "iso:country":"US",
    "sg:address":"231 S Center St",
    "sg:city":"Turlock",
    "sg:classifiers":[
        {
            "category":"Autos & Motor Vehicles",
            "subcategory":"Automobile Sales",
            "type":"Retail Goods"
        }
    ],
    "sg:phone":"+1 209 632 8871",
    "sg:postcode":"95380",
    "sg:province":"CA",
    "sg:tags":[
        "repair",
        "parts",
        "truck",
        "lease"
    ],
    "sg:website":"www.bonanderauto.com",
    "wof:name":"Bonander Pontiac-BUICK-GMC",
    "wof:placetype":"venue"
},
  "geometry": {"coordinates":[-120.84348799999999,37.49401],"type":"Point"}
}