{
  "type": "Feature",
  "properties": {
    "addr:full":"12777 Valley View St Garden Grove CA 92845",
    "addr:housenumber":"12777",
    "addr:postcode":"92845",
    "addr:street":"Valley View St",
    "iso:country":"US",
    "sg:address":"12777 Valley View St",
    "sg:city":"Garden Grove",
    "sg:classifiers":[
        {
            "category":"Wholesale",
            "subcategory":"Groceries",
            "type":"Manufacturing & Wholesale Goods"
        }
    ],
    "sg:phone":"+1 714 791 3715",
    "sg:postcode":"92845",
    "sg:province":"CA",
    "wof:name":"CNA Sales",
    "wof:placetype":"venue"
},
  "geometry": {"coordinates":[-118.035139,33.776941],"type":"Point"}
}