{
  "type": "Feature",
  "properties": {
    "iso:country":"US",
    "sg:address":"3600 Fletcher Dr",
    "sg:city":"Los Angeles",
    "sg:classifiers":[
        {
            "category":"Manufacturing",
            "subcategory":"Tools & Machinery",
            "type":"Manufacturing & Wholesale Goods"
        }
    ],
    "sg:phone":"+1 323 258 9434",
    "sg:postcode":"90065",
    "sg:province":"CA",
    "sg:tags":[
        "lamp",
        "mfg",
        "metal",
        "floor"
    ],
    "wof:name":"Saturn Lighting",
    "wof:placetype":"venue"
},
  "geometry": {"coordinates":[-118.234494,34.118984],"type":"Point"}
}