{
  "type": "Feature",
  "properties": {
    "addr:full":"529 N Mount Holyoke Ave Pacific Plsds CA 90272",
    "addr:housenumber":"529",
    "addr:postcode":"90272",
    "addr:street":"N Mount Holyoke Ave",
    "iso:country":"US",
    "sg:address":"529 N Mount Holyoke Ave",
    "sg:city":"Pacific Plsds",
    "sg:classifiers":[
        {
            "category":"Insurance",
            "subcategory":"Insurance Agent",
            "type":"Services"
        }
    ],
    "sg:phone":"+1 310 459 9681",
    "sg:postcode":"90272",
    "sg:province":"CA",
    "wof:name":"Robert Silberman Insurance Svc",
    "wof:placetype":"venue"
},
  "geometry": {"coordinates":[-118.53103299999999,34.038919],"type":"Point"}
}