{
  "type": "Feature",
  "properties": {
    "addr:full":"17993 State Hwy 18 Apple Valley CA 92307",
    "addr:housenumber":"17993",
    "addr:postcode":"92307",
    "addr:street":"State Hwy 18",
    "iso:country":"US",
    "sg:address":"17993 State Hwy 18",
    "sg:city":"Apple Valley",
    "sg:classifiers":[
        {
            "category":"Food & Beverages",
            "subcategory":"Candy",
            "type":"Retail Goods"
        },
        {
            "category":"Food & Beverages",
            "subcategory":"Liquor & Beverages",
            "type":"Retail Goods"
        }
    ],
    "sg:phone":"+1 760 242 2075",
    "sg:postcode":"92307",
    "sg:province":"CA",
    "sg:tags":[
        "snack",
        "store"
    ],
    "wof:name":"Apple Valley Liquor",
    "wof:placetype":"venue"
},
  "geometry": {"coordinates":[-117.268489,34.540522],"type":"Point"}
}