{
  "type": "Feature",
  "properties": {
    "addr:full":"100 W Walnut St Pasadena CA 91124",
    "addr:housenumber":"100",
    "addr:postcode":"91124",
    "addr:street":"W Walnut St",
    "iso:country":"US",
    "sg:address":"100 W Walnut St",
    "sg:city":"Pasadena",
    "sg:classifiers":[
        {
            "category":"Banks & Credit Unions",
            "subcategory":"Bank",
            "type":"Services"
        }
    ],
    "sg:phone":"+1 626 440 7000",
    "sg:postcode":"91124",
    "sg:province":"CA",
    "sg:website":"www.parsonsfcu.net",
    "wof:name":"Parsons Federal Credit Union",
    "wof:placetype":"venue"
},
  "geometry": {"coordinates":[-118.152,34.149799],"type":"Point"}
}