{
  "type": "Feature",
  "properties": {
    "iso:country":"US",
    "sg:address":"13524 Hilleary Pl",
    "sg:city":"Poway",
    "sg:classifiers":[
        {
            "category":"Real Estate",
            "subcategory":"Real Estate Operator",
            "type":"Services"
        }
    ],
    "sg:phone":"+1 858 748 3160",
    "sg:postcode":"92064",
    "sg:province":"CA",
    "sg:tags":[
        "apartment"
    ],
    "wof:name":"Canary Palm Apartments",
    "wof:placetype":"venue"
},
  "geometry": {"coordinates":[-117.039548,32.960138],"type":"Point"}
}