{
  "type": "Feature",
  "properties": {
    "addr:full":"1400 Main St Ferndale CA 95536",
    "addr:housenumber":"1400",
    "addr:postcode":"95536",
    "addr:street":"Main St",
    "iso:country":"US",
    "sg:address":"1400 Main St",
    "sg:city":"Ferndale",
    "sg:classifiers":[
        {
            "category":"Communications",
            "subcategory":"Radio Station",
            "type":"Services"
        }
    ],
    "sg:phone":"+1 707 786 5104",
    "sg:postcode":"95536",
    "sg:province":"CA",
    "sg:tags":[
        "company",
        "broadcasting"
    ],
    "sg:website":"www.khum.com",
    "wof:name":"KHUM",
    "wof:placetype":"venue"
},
  "geometry": {"coordinates":[-124.25650899999999,40.588035],"type":"Point"}
}