{
  "type": "Feature",
  "properties": {
    "addr:full":"31821 Potsdam St Hayward CA 94544",
    "addr:postcode":"31821;94544",
    "addr:street":"Potsdam St",
    "iso:country":"US",
    "sg:address":"31821 Potsdam St",
    "sg:city":"Hayward",
    "sg:classifiers":[
        {
            "category":"Building & Trades",
            "subcategory":"Cleaning & Sanitation",
            "type":"Services"
        }
    ],
    "sg:phone":"+1 510 441 9913",
    "sg:postcode":"94544",
    "sg:province":"CA",
    "sg:tags":[
        "carpet"
    ],
    "wof:name":"S & J Steam Cleaning & Janitorial",
    "wof:placetype":"venue"
},
  "geometry": {"coordinates":[-122.033997,37.612801],"type":"Point"}
}