{
  "type": "Feature",
  "properties": {
    "addr:full":"1425 Annajeane Dr Placentia CA 92870",
    "addr:housenumber":"1425",
    "addr:postcode":"ca 92870",
    "addr:street":"Annajeane Dr",
    "iso:country":"US",
    "sg:address":"1425 Annajeane Dr",
    "sg:city":"Placentia",
    "sg:classifiers":[
        {
            "category":"Education",
            "subcategory":"School",
            "type":"Public Place"
        }
    ],
    "sg:phone":"+1 714 577 0148",
    "sg:postcode":"92870",
    "sg:province":"CA",
    "wof:name":"John Bunyan Academy",
    "wof:placetype":"venue"
},
  "geometry": {"coordinates":[-117.86077299999999,33.886967],"type":"Point"}
}