{
  "type": "Feature",
  "properties": {
    "iso:country":"US",
    "sg:address":"1652 Mateo St",
    "sg:city":"Los Angeles",
    "sg:classifiers":[
        {
            "category":"Professional",
            "type":"Services"
        }
    ],
    "sg:phone":"+1 310 659 6713",
    "sg:postcode":"90021",
    "sg:province":"CA",
    "wof:name":"Marc Pizzuto",
    "wof:placetype":"venue"
},
  "geometry": {"coordinates":[-118.232219,34.024308],"type":"Point"}
}