{
  "type": "Feature",
  "properties": {
    "iso:country":"US",
    "sg:address":"3300 Industrial Blvd",
    "sg:city":"West Sacramento",
    "sg:classifiers":[
        {
            "category":"Professional",
            "subcategory":"Research",
            "type":"Services"
        }
    ],
    "sg:phone":"+1 916 375 0377",
    "sg:postcode":"95691",
    "sg:province":"CA",
    "sg:tags":[
        "development",
        "laboratory"
    ],
    "wof:name":"Daimler Chrysler Research-Tech",
    "wof:placetype":"venue"
},
  "geometry": {"coordinates":[-121.558589,38.573515],"type":"Point"}
}