{
  "type": "Feature",
  "properties": {
    "addr:full":"5138 W Mission Blvd Ontario CA 91762",
    "addr:housenumber":"5138",
    "addr:postcode":"91762",
    "addr:street":"W Mission Blvd",
    "iso:country":"US",
    "sg:address":"5138 W Mission Blvd",
    "sg:city":"Ontario",
    "sg:classifiers":[
        {
            "category":"Place Of Worship",
            "subcategory":"Church",
            "type":"Public Place"
        },
        {
            "category":"Place Of Worship",
            "type":"Public Place"
        }
    ],
    "sg:phone":"+1 909 902 0805",
    "sg:postcode":"91762",
    "sg:province":"CA",
    "sg:tags":[
        "churches-pentecostal-independent",
        "churches-pentecostal"
    ],
    "wof:name":"Iglesia Cristiana Ebenezer",
    "wof:placetype":"venue"
},
  "geometry": {"coordinates":[-117.655457,34.054871],"type":"Point"}
}