{
  "type": "Feature",
  "properties": {
    "iso:country":"US",
    "sg:address":"190 Mathilda Pl",
    "sg:city":"Sunnyvale",
    "sg:classifiers":[
        {
            "category":"Wholesale",
            "subcategory":"Electrical",
            "type":"Manufacturing & Wholesale Goods"
        }
    ],
    "sg:phone":"+1 408 543 3300",
    "sg:postcode":"94086",
    "sg:province":"CA",
    "sg:tags":[
        "semiconductor",
        "device"
    ],
    "sg:website":"http://www.broadcom.com",
    "wof:name":"Broadcom Corporation",
    "wof:placetype":"venue"
},
  "geometry": {"coordinates":[-122.03326,37.378991],"type":"Point"}
}