{
  "type": "Feature",
  "properties": {
    "addr:full":"15909 Norton Rd Healdsburg CA 95448",
    "addr:housenumber":"15909",
    "addr:postcode":"95448",
    "addr:street":"Norton Rd",
    "iso:country":"US",
    "sg:address":"15909 Norton Rd",
    "sg:city":"Healdsburg",
    "sg:classifiers":[
        {
            "category":"Farming",
            "subcategory":"Vineyard",
            "type":"Manufacturing & Wholesale Goods"
        }
    ],
    "sg:phone":"+1 707 433 0253",
    "sg:postcode":"95448",
    "sg:province":"CA",
    "sg:tags":[
        "grape"
    ],
    "wof:name":"Somers Vineyard",
    "wof:placetype":"venue"
},
  "geometry": {"coordinates":[-122.889421,38.638292],"type":"Point"}
}