{
  "type": "Feature",
  "properties": {
    "addr:full":"417 F St Lincoln CA 95648",
    "addr:housenumber":"417",
    "addr:postcode":"95648",
    "addr:street":"F St",
    "iso:country":"US",
    "sg:address":"417 F St",
    "sg:city":"Lincoln",
    "sg:classifiers":[
        {
            "category":"Professional",
            "subcategory":"Lawyer & Legal Services",
            "type":"Services"
        }
    ],
    "sg:phone":"+1 916 645 9529",
    "sg:postcode":"95648",
    "sg:province":"CA",
    "sg:tags":[
        "attorney",
        "practice"
    ],
    "wof:name":"Beyer Pongratz and Rosen A Professional Law Corp",
    "wof:placetype":"venue"
},
  "geometry": {"coordinates":[-121.29154200000001,38.890723],"type":"Point"}
}