{
  "type": "Feature",
  "properties": {
    "iso:country":"US",
    "sg:address":"6333 W 3rd Street",
    "sg:city":"Los Angeles",
    "sg:classifiers":[
        {
            "category":"Restaurant",
            "type":"Food & Drink"
        }
    ],
    "sg:phone":"+1 323 939 2078",
    "sg:postcode":"90036",
    "sg:province":"CA",
    "wof:name":"Tesquella's Fish & Oyster Bar",
    "wof:placetype":"venue"
},
  "geometry": {"coordinates":[-118.360095,34.071348],"type":"Point"}
}