{
  "type": "Feature",
  "properties": {
    "iso:country":"US",
    "sg:address":"14820 Carmenita Rd",
    "sg:city":"Norwalk",
    "sg:classifiers":[
        {
            "category":"Freight",
            "type":"Transportation"
        }
    ],
    "sg:phone":"+1 562 407 5800",
    "sg:postcode":"90650",
    "sg:province":"CA",
    "sg:tags":[
        "general"
    ],
    "wof:name":"Fuji Hunt",
    "wof:placetype":"venue"
},
  "geometry": {"coordinates":[-118.046497,33.896605],"type":"Point"}
}