{
  "type": "Feature",
  "properties": {
    "addr:full":"8977 8th Ave Hesperia CA 92345",
    "addr:housenumber":"8977",
    "addr:postcode":"92345",
    "addr:street":"8Th Ave",
    "iso:country":"US",
    "sg:address":"8977 8th Ave",
    "sg:city":"Hesperia",
    "sg:classifiers":[
        {
            "category":"Banks & Credit Unions",
            "subcategory":"Investment Brokerage",
            "type":"Services"
        },
        {
            "category":"Professional",
            "subcategory":"Management & Consulting",
            "type":"Services"
        }
    ],
    "sg:phone":"+1 760 948 4310",
    "sg:postcode":"92345",
    "sg:province":"CA",
    "sg:tags":[
        "consultant",
        "planning",
        "financial",
        "insurance"
    ],
    "wof:name":"Chuck Wolf Financial Services",
    "wof:placetype":"venue"
},
  "geometry": {"coordinates":[-117.320078,34.413677],"type":"Point"}
}