{
  "type": "Feature",
  "properties": {
    "iso:country":"US",
    "sg:address":"15139 Woodlawn Ave",
    "sg:city":"Tustin",
    "sg:classifiers":[
        {
            "category":"Professional",
            "subcategory":"Lawyer & Legal Services",
            "type":"Services"
        }
    ],
    "sg:phone":"+1 714 258 1550",
    "sg:postcode":"92780",
    "sg:province":"CA",
    "wof:name":"Spray Gould & Bowers LLP",
    "wof:placetype":"venue"
},
  "geometry": {"coordinates":[-117.832003,33.721385],"type":"Point"}
}