{
  "type": "Feature",
  "properties": {
    "addr:full":"69842 Willow Ln Cathedral City CA 92234",
    "addr:housenumber":"69842",
    "addr:postcode":"92234",
    "addr:street":"Willow Ln",
    "iso:country":"US",
    "sg:address":"69842 Willow Ln",
    "sg:city":"Cathedral City",
    "sg:classifiers":[
        {
            "category":"Shopping",
            "type":"Retail Goods"
        }
    ],
    "sg:phone":"+1 760 578 8691",
    "sg:postcode":"92234",
    "sg:province":"CA",
    "sg:tags":[
        "merchandise"
    ],
    "wof:name":"Classic Arts",
    "wof:placetype":"venue"
},
  "geometry": {"coordinates":[-116.443575,33.824076],"type":"Point"}
}