{
  "type": "Feature",
  "properties": {
    "addr:full":"1408 Dayton Rd Chico CA 95928",
    "addr:housenumber":"1408",
    "addr:postcode":"95928",
    "addr:street":"Dayton Rd",
    "iso:country":"US",
    "sg:address":"1408 Dayton Rd",
    "sg:city":"Chico",
    "sg:classifiers":[
        {
            "category":"Retail",
            "subcategory":"Auto Repair",
            "type":"Services"
        }
    ],
    "sg:phone":"+1 530 894 8163",
    "sg:postcode":"95928",
    "sg:province":"CA",
    "sg:tags":[
        "repairing",
        "automobile"
    ],
    "wof:name":"Irmer's Auto Repair",
    "wof:placetype":"venue"
},
  "geometry": {"coordinates":[-121.84372399999999,39.714928],"type":"Point"}
}