{
  "type": "Feature",
  "properties": {
    "iso:country":"US",
    "sg:address":"1408 Dayton Rd",
    "sg:city":"Chico",
    "sg:classifiers":[
        {
            "category":"Retail",
            "subcategory":"Auto Repair",
            "type":"Services"
        }
    ],
    "sg:phone":"+1 530 894 8163",
    "sg:postcode":"95928",
    "sg:province":"CA",
    "sg:tags":[
        "repairing",
        "automobile"
    ],
    "wof:name":"Irmer's Auto Repair",
    "wof:placetype":"venue"
},
  "geometry": {"coordinates":[-121.843724,39.714928],"type":"Point"}
}