{
  "type": "Feature",
  "properties": {
    "iso:country":"US",
    "sg:address":"7106 E Kettleman Ln",
    "sg:city":"Lodi",
    "sg:classifiers":[
        {
            "category":"Manufacturing",
            "subcategory":"Metals",
            "type":"Manufacturing & Wholesale Goods"
        }
    ],
    "sg:phone":"+1 209 369 7818",
    "sg:postcode":"95240",
    "sg:province":"CA",
    "sg:tags":[
        "cutlery",
        "mfg"
    ],
    "wof:name":"Howell Wooden Weapons",
    "wof:placetype":"venue"
},
  "geometry": {"coordinates":[-121.230456,38.115811],"type":"Point"}
}