{
  "type": "Feature",
  "properties": {
    "iso:country":"US",
    "sg:address":"1976 S Bascom Ave",
    "sg:city":"Campbell",
    "sg:classifiers":[
        {
            "category":"Restaurant",
            "type":"Food & Drink"
        }
    ],
    "sg:menulink":"http://www.allmenus.com/ca/san-jose/45725-baja-fresh-mexican-grill/menu/",
    "sg:phone":"+1 408 377 2600",
    "sg:postcode":"95008",
    "sg:province":"CA",
    "sg:tags":[
        "mexican"
    ],
    "wof:name":"Baja Fresh Mexican Grill",
    "wof:placetype":"venue"
},
  "geometry": {"coordinates":[-121.931572,37.287646],"type":"Point"}
}