{
  "type": "Feature",
  "properties": {
    "addr:full":"660 W Ave L Lancaster CA 93534",
    "addr:housenumber":"660",
    "addr:postcode":"93534",
    "addr:street":"W Ave L",
    "iso:country":"US",
    "sg:address":"660 W Ave L",
    "sg:city":"Lancaster",
    "sg:classifiers":[
        {
            "category":"Home & Garden",
            "subcategory":"Building Materials",
            "type":"Retail Goods"
        }
    ],
    "sg:phone":"+1 661 723 7201",
    "sg:postcode":"93534",
    "sg:province":"CA",
    "sg:tags":[
        "lumber"
    ],
    "wof:name":"Antelope Pallets & Lumber",
    "wof:placetype":"venue"
},
  "geometry": {"coordinates":[-118.142667,34.660249],"type":"Point"}
}