{
  "type": "Feature",
  "properties": {
    "addr:full":"1630 Contra Costa Blvd Pleasant Hill CA 94523",
    "addr:housenumber":"1630",
    "addr:postcode":"94523",
    "addr:street":"Contra Costa Blvd",
    "iso:country":"US",
    "sg:address":"1630 Contra Costa Blvd",
    "sg:city":"Pleasant Hill",
    "sg:classifiers":[
        {
            "category":"Insurance",
            "subcategory":"Insurance Agent",
            "type":"Services"
        }
    ],
    "sg:phone":"+1 925 680 7405",
    "sg:postcode":"94523",
    "sg:province":"CA",
    "wof:name":"Jay-Marie Garcia Insurance",
    "wof:placetype":"venue"
},
  "geometry": {"coordinates":[-122.060087,37.954129],"type":"Point"}
}