{
  "type": "Feature",
  "properties": {
    "iso:country":"US",
    "sg:address":"9570 Murray Dr",
    "sg:city":"La Mesa",
    "sg:classifiers":[
        {
            "category":"Restaurant",
            "type":"Food & Drink"
        }
    ],
    "sg:phone":"+1 619 466 2912",
    "sg:postcode":"91942",
    "sg:province":"CA",
    "wof:name":"Don Primo's Bolivian Restaurant & Cafe",
    "wof:placetype":"venue"
},
  "geometry": {"coordinates":[-116.99099699999999,32.7794],"type":"Point"}
}