{
  "type": "Feature",
  "properties": {
    "iso:country":"US",
    "sg:address":"5772 Ave 378",
    "sg:city":"Dinuba",
    "sg:classifiers":[
        {
            "category":"Social Services",
            "subcategory":"Child Care",
            "type":"Services"
        }
    ],
    "sg:phone":"+1 559 595 0317",
    "sg:postcode":"93618",
    "sg:province":"CA",
    "wof:name":"Tulare County Child Care",
    "wof:placetype":"venue"
},
  "geometry": {"coordinates":[-119.443567,36.477179],"type":"Point"}
}