{
  "type": "Feature",
  "properties": {
    "addr:full":"512 N Irwin St Hanford CA 93230",
    "addr:housenumber":"512",
    "addr:postcode":"ca 93230",
    "addr:street":"N Irwin St",
    "iso:country":"US",
    "sg:address":"512 N Irwin St",
    "sg:city":"Hanford",
    "sg:classifiers":[
        {
            "category":"Professional",
            "subcategory":"Management & Consulting",
            "type":"Services"
        }
    ],
    "sg:phone":"+1 559 582 3463",
    "sg:postcode":"93230",
    "sg:province":"CA",
    "sg:tags":[
        "consultant",
        "business"
    ],
    "wof:name":"Shawhan Consulting",
    "wof:placetype":"venue"
},
  "geometry": {"coordinates":[-119.64776000000001,36.330134],"type":"Point"}
}