{
  "type": "Feature",
  "properties": {
    "addr:full":"1279 Park Blvd Orange Cove CA 93646",
    "addr:housenumber":"1279",
    "addr:postcode":"93646",
    "addr:street":"Park Blvd",
    "iso:country":"US",
    "sg:address":"1279 Park Blvd",
    "sg:city":"Orange Cove",
    "sg:classifiers":[
        {
            "category":"Shopping",
            "subcategory":"Clothing, Apparel, & Fashions",
            "type":"Retail Goods"
        }
    ],
    "sg:phone":"+1 559 626 4050",
    "sg:postcode":"93646",
    "sg:province":"CA",
    "wof:name":"Tj Fashion",
    "wof:placetype":"venue"
},
  "geometry": {"coordinates":[-119.321034,36.62455],"type":"Point"}
}