{
  "type": "Feature",
  "properties": {
    "iso:country":"US",
    "sg:address":"982 W 9th St",
    "sg:city":"Upland",
    "sg:classifiers":[
        {
            "category":"Building & Trades",
            "subcategory":"Construction",
            "type":"Services"
        }
    ],
    "sg:phone":"+1 909 982 4757",
    "sg:postcode":"91786",
    "sg:province":"CA",
    "sg:tags":[
        "garage",
        "opener",
        "door",
        "installing",
        "contractor"
    ],
    "wof:name":"Jmk Garage Door Service",
    "wof:placetype":"venue"
},
  "geometry": {"coordinates":[-117.663918,34.095982],"type":"Point"}
}