{
  "type": "Feature",
  "properties": {
    "addr:full":"11420 Swan Lake Dr San Diego CA 92131",
    "addr:housenumber":"11420",
    "addr:postcode":"92131",
    "addr:street":"Swan Lake Dr",
    "iso:country":"US",
    "sg:address":"11420 Swan Lake Dr",
    "sg:city":"San Diego",
    "sg:classifiers":[
        {
            "category":"Manufacturing",
            "subcategory":"Electronics",
            "type":"Manufacturing & Wholesale Goods"
        }
    ],
    "sg:phone":"+1 858 689 8455",
    "sg:postcode":"92131",
    "sg:province":"CA",
    "sg:tags":[
        "electronic",
        "component",
        "mfg"
    ],
    "wof:name":"Omron Electronics",
    "wof:placetype":"venue"
},
  "geometry": {"coordinates":[-117.10138600000001,32.925867],"type":"Point"}
}