{
  "type": "Feature",
  "properties": {
    "addr:full":"319 F St Chula Vista CA 91910",
    "addr:housenumber":"319",
    "addr:postcode":"91910",
    "addr:street":"F St",
    "iso:country":"US",
    "sg:address":"319 F St",
    "sg:city":"Chula Vista",
    "sg:classifiers":[
        {
            "category":"Health Services",
            "subcategory":"Doctor",
            "type":"Services"
        }
    ],
    "sg:phone":"+1 619 476 1200",
    "sg:postcode":"91910",
    "sg:province":"CA",
    "sg:tags":[
        "physician",
        "surgeon"
    ],
    "sg:website":"www.dermlasercenter.com",
    "wof:name":"Dermatology & Laser-San Diego",
    "wof:placetype":"venue"
},
  "geometry": {"coordinates":[-117.080454,32.641123],"type":"Point"}
}