{
  "type": "Feature",
  "properties": {
    "addr:full":"2031 S Garey Ave Pomona CA 91766",
    "addr:housenumber":"2031",
    "addr:postcode":"91766",
    "addr:street":"S Garey Ave",
    "iso:country":"US",
    "sg:address":"2031 S Garey Ave",
    "sg:city":"Pomona",
    "sg:classifiers":[
        {
            "category":"Shopping",
            "subcategory":"Gifts & Souvenirs",
            "type":"Retail Goods"
        }
    ],
    "sg:phone":"+1 909 628 9863",
    "sg:postcode":"91766",
    "sg:province":"CA",
    "wof:name":"Wireless Touch Gift",
    "wof:placetype":"venue"
},
  "geometry": {"coordinates":[-117.749399,34.035801],"type":"Point"}
}