{
  "type": "Feature",
  "properties": {
    "iso:country":"US",
    "sg:address":"33 Miller Aly",
    "sg:city":"Pasadena",
    "sg:classifiers":[
        {
            "category":"Building & Trades",
            "subcategory":"Locksmith",
            "type":"Services"
        }
    ],
    "sg:phone":"+1 626 381 9647",
    "sg:postcode":"91103",
    "sg:province":"CA",
    "sg:tags":[
        "key"
    ],
    "wof:name":"lock 1 Services",
    "wof:placetype":"venue"
},
  "geometry": {"coordinates":[-118.151145,34.146379],"type":"Point"}
}