{
  "type": "Feature",
  "properties": {
    "iso:country":"US",
    "sg:address":"570 E Dayman St",
    "sg:city":"Long Beach",
    "sg:classifiers":[
        {
            "category":"Social Services",
            "subcategory":"Retirement Home",
            "type":"Services"
        }
    ],
    "sg:phone":"+1 562 218 8665",
    "sg:postcode":"90806",
    "sg:province":"CA",
    "wof:name":"Shelters Inn Jr",
    "wof:placetype":"venue"
},
  "geometry": {"coordinates":[-118.185997,33.790699],"type":"Point"}
}