{
  "type": "Feature",
  "properties": {
    "iso:country":"US",
    "sg:address":"15180 Raymer St",
    "sg:city":"Van Nuys",
    "sg:classifiers":[
        {
            "category":"Home & Garden",
            "subcategory":"Building Materials",
            "type":"Retail Goods"
        }
    ],
    "sg:phone":"+1 818 904 0055",
    "sg:postcode":"91405",
    "sg:province":"CA",
    "sg:tags":[
        "glass",
        "window",
        "plate"
    ],
    "wof:name":"Glass Co",
    "wof:placetype":"venue"
},
  "geometry": {"coordinates":[-118.465374,34.21422],"type":"Point"}
}