{
  "type": "Feature",
  "properties": {
    "addr:full":"9247 Reseda Blvd Northridge CA 91324",
    "addr:housenumber":"9247",
    "addr:postcode":"91324",
    "addr:street":"Reseda Blvd",
    "iso:country":"US",
    "sg:address":"9247 Reseda Blvd",
    "sg:city":"Northridge",
    "sg:classifiers":[
        {
            "category":"Utilities",
            "subcategory":"Mobile Phone",
            "type":"Services"
        }
    ],
    "sg:phone":"+1 818 885 1115",
    "sg:postcode":"91324",
    "sg:province":"CA",
    "sg:tags":[
        "communication",
        "radiotelephone"
    ],
    "wof:name":"Planet Wireless",
    "wof:placetype":"venue"
},
  "geometry": {"coordinates":[-118.536162,34.238269],"type":"Point"}
}