{
  "type": "Feature",
  "properties": {
    "addr:full":"1147 California Dr Burlingame CA 94010",
    "addr:housenumber":"1147",
    "addr:postcode":"94010",
    "addr:street":"California Dr",
    "iso:country":"US",
    "sg:address":"1147 California Dr",
    "sg:city":"Burlingame",
    "sg:classifiers":[
        {
            "category":"Retail",
            "subcategory":"Portrait Studio",
            "type":"Services"
        }
    ],
    "sg:phone":"+1 650 348 3655",
    "sg:postcode":"94010",
    "sg:province":"CA",
    "sg:tags":[
        "photographer"
    ],
    "sg:website":"www.dawnphotography.com",
    "wof:name":"Dawn Photography",
    "wof:placetype":"venue"
},
  "geometry": {"coordinates":[-122.362711,37.5871],"type":"Point"}
}