{
  "type": "Feature",
  "properties": {
    "iso:country":"US",
    "sg:address":"1177 N Ventura Ave",
    "sg:city":"Ventura",
    "sg:classifiers":[
        {
            "category":"Autos & Motor Vehicles",
            "subcategory":"Auto Supplies",
            "type":"Retail Goods"
        },
        {
            "category":"Retail",
            "subcategory":"Auto Repair",
            "type":"Services"
        }
    ],
    "sg:phone":"+1 805 653 0086",
    "sg:postcode":"93001",
    "sg:province":"CA",
    "sg:tags":[
        "recap",
        "retread",
        "tire"
    ],
    "wof:name":"Ocean Tires Service",
    "wof:placetype":"venue"
},
  "geometry": {"coordinates":[-119.29701,34.293979],"type":"Point"}
}