{
  "type": "Feature",
  "properties": {
    "addr:full":"5084 Mission St San Francisco CA 94112",
    "addr:housenumber":"5084",
    "addr:postcode":"94112",
    "addr:street":"Mission St",
    "iso:country":"US",
    "sg:address":"5084 Mission St",
    "sg:city":"San Francisco",
    "sg:classifiers":[
        {
            "category":"Food & Beverages",
            "subcategory":"Liquor & Beverages",
            "type":"Retail Goods"
        }
    ],
    "sg:phone":"+1 415 587 5000",
    "sg:postcode":"94112",
    "sg:province":"CA",
    "sg:tags":[
        "beer",
        "spirit",
        "wine"
    ],
    "sg:website":"www.mikesliquors.com/",
    "wof:name":"Mike's Liquors",
    "wof:placetype":"venue"
},
  "geometry": {"coordinates":[-122.440839,37.717187],"type":"Point"}
}