{
  "type": "Feature",
  "properties": {
    "iso:country":"US",
    "sg:address":"1030 15th Street",
    "sg:city":"Sacramento",
    "sg:classifiers":[
        {
            "category":"Professional",
            "subcategory":"Lawyer & Legal Services",
            "type":"Services"
        }
    ],
    "sg:phone":"+1 916 443 1030",
    "sg:postcode":"95814",
    "sg:province":"CA",
    "wof:name":"Lenahan Gerald M",
    "wof:placetype":"venue"
},
  "geometry": {"coordinates":[-121.48672000000001,38.578127],"type":"Point"}
}