{
  "type": "Feature",
  "properties": {
    "iso:country":"US",
    "sg:address":"2963 Michelson Dr",
    "sg:city":"Irvine",
    "sg:classifiers":[
        {
            "category":"Restaurant",
            "type":"Food & Drink"
        }
    ],
    "sg:menulink":"http://www.allmenus.com/ca/central-coast/39154-mothers-market--kitchen/menu/",
    "sg:phone":"+1 949 752 6667",
    "sg:postcode":"92612",
    "sg:province":"CA",
    "sg:tags":[
        "american"
    ],
    "wof:name":"Mother's Market & Kitchen",
    "wof:placetype":"venue"
},
  "geometry": {"coordinates":[-117.84476600000001,33.671014],"type":"Point"}
}