{
  "type": "Feature",
  "properties": {
    "iso:country":"US",
    "sg:address":"6221 Wilshire Blvd Suite 220",
    "sg:city":"Los Angeles",
    "sg:classifiers":[
        {
            "category":"Health Services",
            "subcategory":"Doctor",
            "type":"Services"
        }
    ],
    "sg:phone":"+1 323 937 4546",
    "sg:postcode":"90048",
    "sg:province":"CA",
    "sg:tags":[
        "dermatologist"
    ],
    "wof:name":"Erma L Benitez MD",
    "wof:placetype":"venue"
},
  "geometry": {"coordinates":[-118.363997,34.063577],"type":"Point"}
}