{
  "type": "Feature",
  "properties": {
    "addr:full":"30 N Raymond Ave Pasadena CA 91103",
    "addr:housenumber":"30",
    "addr:postcode":"91103",
    "addr:street":"N Raymond Ave",
    "iso:country":"US",
    "sg:address":"30 N Raymond Ave",
    "sg:city":"Pasadena",
    "sg:classifiers":[
        {
            "category":"Professional",
            "subcategory":"Lawyer & Legal Services",
            "type":"Services"
        }
    ],
    "sg:phone":"+1 626 796 7470",
    "sg:postcode":"91103",
    "sg:province":"CA",
    "wof:name":"Vogel Brian",
    "wof:placetype":"venue"
},
  "geometry": {"coordinates":[-118.148714,34.146304],"type":"Point"}
}