{
  "type": "Feature",
  "properties": {
    "addr:full":"29 Prado Rd San Luis Obispo CA 93401",
    "addr:housenumber":"29",
    "addr:postcode":"93401",
    "addr:street":"Prado Rd",
    "iso:country":"US",
    "sg:address":"29 Prado Rd",
    "sg:city":"San Luis Obispo",
    "sg:classifiers":[
        {
            "category":"Government",
            "subcategory":"Office",
            "type":"Public Place"
        }
    ],
    "sg:phone":"+1 805 541 2877",
    "sg:postcode":"93401",
    "sg:province":"CA",
    "sg:tags":[
        "city",
        "program"
    ],
    "sg:website":"www.slocity.org",
    "wof:name":"San Luis Obispo Transit",
    "wof:placetype":"venue"
},
  "geometry": {"coordinates":[-120.67335300000001,35.256196],"type":"Point"}
}