{
  "type": "Feature",
  "properties": {
    "addr:full":"16045 Victory Blvd Van Nuys CA 91406",
    "addr:housenumber":"16045",
    "addr:postcode":"91406",
    "addr:street":"Victory Blvd",
    "iso:country":"US",
    "sg:address":"16045 Victory Blvd",
    "sg:city":"Van Nuys",
    "sg:classifiers":[
        {
            "category":"Restaurant",
            "type":"Food & Drink"
        }
    ],
    "sg:phone":"+1 818 780 4041",
    "sg:postcode":"91406",
    "sg:province":"CA",
    "wof:name":"Panos Char Broiler",
    "wof:placetype":"venue"
},
  "geometry": {"coordinates":[-118.483448,34.186714],"type":"Point"}
}