{
  "type": "Feature",
  "properties": {
    "addr:full":"2999 W Florida Ave Hemet CA 92545",
    "addr:housenumber":"2999",
    "addr:postcode":"92545",
    "addr:street":"W Florida Ave",
    "iso:country":"US",
    "sg:address":"2999 W Florida Ave",
    "sg:city":"Hemet",
    "sg:classifiers":[
        {
            "category":"Shopping",
            "subcategory":"Department Store",
            "type":"Retail Goods"
        }
    ],
    "sg:phone":"+1 951 658 0332",
    "sg:postcode":"92545",
    "sg:province":"CA",
    "sg:tags":[
        "shop"
    ],
    "wof:name":"Pier 1 Imports",
    "wof:placetype":"venue"
},
  "geometry": {"coordinates":[-117.002639,33.747318],"type":"Point"}
}