{
  "type": "Feature",
  "properties": {
    "addr:full":"5775 Jurupa St Ontario CA 91761",
    "addr:housenumber":"5775",
    "addr:postcode":"91761",
    "addr:street":"Jurupa St",
    "iso:country":"US",
    "sg:address":"5775 Jurupa St",
    "sg:city":"Ontario",
    "sg:classifiers":[
        {
            "category":"Shopping",
            "subcategory":"Clothing, Apparel, & Fashions",
            "type":"Retail Goods"
        },
        {
            "category":"Shopping",
            "subcategory":"Baby Store",
            "type":"Retail Goods"
        },
        {
            "category":"Wholesale",
            "subcategory":"Apparel",
            "type":"Manufacturing & Wholesale Goods"
        }
    ],
    "sg:phone":"+1 909 390 4237",
    "sg:postcode":"91761",
    "sg:province":"CA",
    "sg:tags":[
        "wear-wholesale",
        "infant",
        "children's",
        "wear",
        "clothing",
        "manufacturer"
    ],
    "wof:name":"Stani Corp",
    "wof:placetype":"venue"
},
  "geometry": {"coordinates":[-117.524879,34.046808],"type":"Point"}
}