{
  "type": "Feature",
  "properties": {
    "iso:country":"US",
    "sg:address":"5001 Great America Pkwy",
    "sg:city":"Santa Clara",
    "sg:classifiers":[
        {
            "category":"Restaurant",
            "type":"Food & Drink"
        }
    ],
    "sg:postcode":"95053",
    "sg:province":"CA",
    "sg:tags":[
        "flavor",
        "local"
    ],
    "sg:website":"www.knittinguniverse.com/xrx/eve...",
    "wof:name":"Stitches West",
    "wof:placetype":"venue"
},
  "geometry": {"coordinates":[-121.977661,37.403584],"type":"Point"}
}