{
  "type": "Feature",
  "properties": {
    "iso:country":"US",
    "sg:address":"9390 7th St",
    "sg:city":"Rancho Cucamonga",
    "sg:classifiers":[
        {
            "category":"Manufacturing",
            "subcategory":"Printing",
            "type":"Manufacturing & Wholesale Goods"
        }
    ],
    "sg:phone":"+1 909 483 0688",
    "sg:postcode":"91730",
    "sg:province":"CA",
    "sg:tags":[
        "printer"
    ],
    "wof:name":"Minuteman Press",
    "wof:placetype":"venue"
},
  "geometry": {"coordinates":[-117.599489,34.088509],"type":"Point"}
}