{
  "type": "Feature",
  "properties": {
    "addr:full":"9390 7th St Rancho Cucamonga CA 91730",
    "addr:housenumber":"9390",
    "addr:postcode":"91730",
    "addr:street":"7Th St",
    "iso:country":"US",
    "sg:address":"9390 7th St",
    "sg:city":"Rancho Cucamonga",
    "sg:classifiers":[
        {
            "category":"Manufacturing",
            "subcategory":"Printing",
            "type":"Manufacturing & Wholesale Goods"
        }
    ],
    "sg:phone":"+1 909 483 0688",
    "sg:postcode":"91730",
    "sg:province":"CA",
    "sg:tags":[
        "printer"
    ],
    "wof:name":"Minuteman Press",
    "wof:placetype":"venue"
},
  "geometry": {"coordinates":[-117.59948900000001,34.088509],"type":"Point"}
}