{
  "type": "Feature",
  "properties": {
    "iso:country":"US",
    "sg:address":"26805 Rd 15",
    "sg:city":"Chowchilla",
    "sg:classifiers":[
        {
            "category":"Bars & Pubs",
            "type":"Food & Drink"
        }
    ],
    "sg:phone":"+1 559 665 5940",
    "sg:postcode":"93610",
    "sg:province":"CA",
    "wof:name":"Minturn Roadhouse Bar",
    "wof:placetype":"venue"
},
  "geometry": {"coordinates":[-120.274385,37.129437],"type":"Point"}
}