{
  "type": "Feature",
  "properties": {
    "addr:full":"26805 Rd 15 Chowchilla CA 93610",
    "addr:housenumber":"26805",
    "addr:postcode":"93610",
    "addr:street":"Rd 15",
    "iso:country":"US",
    "sg:address":"26805 Rd 15",
    "sg:city":"Chowchilla",
    "sg:classifiers":[
        {
            "category":"Bars & Pubs",
            "type":"Food & Drink"
        }
    ],
    "sg:phone":"+1 559 665 5940",
    "sg:postcode":"93610",
    "sg:province":"CA",
    "wof:name":"Minturn Roadhouse Bar",
    "wof:placetype":"venue"
},
  "geometry": {"coordinates":[-120.274385,37.129437],"type":"Point"}
}