{
  "type": "Feature",
  "properties": {
    "addr:full":"10401 Venice Blvd Ste 295 Los Angeles CA 90034",
    "addr:housenumber":"10401",
    "addr:postcode":"90034",
    "addr:street":"Venice Blvd Ste 295",
    "iso:country":"US",
    "sg:address":"10401 Venice Blvd Ste 295",
    "sg:city":"Los Angeles",
    "sg:classifiers":[
        {
            "category":"Shopping",
            "subcategory":"Beauty & Cosmetics",
            "type":"Retail Goods"
        }
    ],
    "sg:phone":"+1 424 298 8601",
    "sg:postcode":"90034",
    "sg:province":"CA",
    "sg:tags":[
        "supply"
    ],
    "wof:name":"Marie Dean Hair & Body Care",
    "wof:placetype":"venue"
},
  "geometry": {"coordinates":[-118.404532,34.020399],"type":"Point"}
}