{
  "type": "Feature",
  "properties": {
    "iso:country":"US",
    "sg:address":"6721 Quail Hill Pkwy",
    "sg:city":"Irvine",
    "sg:classifiers":[
        {
            "category":"Coffee & Tea",
            "type":"Food & Drink"
        },
        {
            "category":"Restaurant",
            "type":"Food & Drink"
        }
    ],
    "sg:phone":"+1 949 725 0018",
    "sg:postcode":"92603",
    "sg:province":"CA",
    "sg:tags":[
        "espresso",
        "pizza"
    ],
    "sg:website":"http://www.redbrickpizza.com",
    "wof:name":"Red Brick Pizza Cafe",
    "wof:placetype":"venue"
},
  "geometry": {"coordinates":[-117.777395,33.65289],"type":"Point"}
}