{
  "type": "Feature",
  "properties": {
    "iso:country":"US",
    "sg:address":"2931 E 4th Street",
    "sg:city":"Los Angeles",
    "sg:classifiers":[
        {
            "category":"Restaurant",
            "type":"Food & Drink"
        }
    ],
    "sg:phone":"+1 323 261 0703",
    "sg:postcode":"90033",
    "sg:province":"CA",
    "wof:name":"La Cabana Restaurant",
    "wof:placetype":"venue"
},
  "geometry": {"coordinates":[-118.204137,34.037298],"type":"Point"}
}