{
  "type": "Feature",
  "properties": {
    "iso:country":"US",
    "sg:address":"625 Center St",
    "sg:city":"Santa Cruz",
    "sg:classifiers":[
        {
            "category":"Personal",
            "subcategory":"Beauty Salon",
            "type":"Services"
        }
    ],
    "sg:phone":"+1 831 458 0548",
    "sg:postcode":"95060",
    "sg:province":"CA",
    "wof:name":"Jillz Hair Design Studio",
    "wof:placetype":"venue"
},
  "geometry": {"coordinates":[-122.028363,36.972851],"type":"Point"}
}