{
  "type": "Feature",
  "properties": {
    "iso:country":"US",
    "sg:address":"1430 Parkinson Ave",
    "sg:city":"Palo Alto",
    "sg:classifiers":[
        {
            "category":"Travel",
            "subcategory":"Travel Agent",
            "type":"Entertainment"
        }
    ],
    "sg:phone":"+1 650 327 2330",
    "sg:postcode":"94301",
    "sg:province":"CA",
    "sg:tags":[
        "agency"
    ],
    "wof:name":"Geek Cruises Inc",
    "wof:placetype":"venue"
},
  "geometry": {"coordinates":[-122.140078,37.445534],"type":"Point"}
}