{
  "type": "Feature",
  "properties": {
    "addr:full":"1155 N Capitol Avenue San Jose CA 95132",
    "addr:housenumber":"1155",
    "addr:postcode":"95132",
    "addr:street":"N Capitol Avenue",
    "iso:country":"US",
    "sg:address":"1155 N Capitol Avenue",
    "sg:city":"San Jose",
    "sg:classifiers":[
        {
            "category":"Health Services",
            "subcategory":"Optometrist",
            "type":"Services"
        }
    ],
    "sg:phone":"+1 408 272 4445",
    "sg:postcode":"95132",
    "sg:province":"CA",
    "wof:name":"Ngo Tarryn Uyen OD",
    "wof:placetype":"venue"
},
  "geometry": {"coordinates":[-121.86148,37.38731],"type":"Point"}
}