{
  "type": "Feature",
  "properties": {
    "addr:full":"1443 Franklin Rd Yuba City CA 95993",
    "addr:housenumber":"1443",
    "addr:postcode":"95993",
    "addr:street":"Franklin Rd",
    "iso:country":"US",
    "sg:address":"1443 Franklin Rd",
    "sg:city":"Yuba City",
    "sg:classifiers":[
        {
            "category":"Food & Beverages",
            "subcategory":"Groceries & Convenience Stores",
            "type":"Retail Goods"
        }
    ],
    "sg:phone":"+1 530 674 7371",
    "sg:postcode":"95993",
    "sg:province":"CA",
    "sg:tags":[
        "grocer"
    ],
    "wof:name":"Bill's Market & Deli",
    "wof:placetype":"venue"
},
  "geometry": {"coordinates":[-121.641957,39.127384],"type":"Point"}
}