{
  "type": "Feature",
  "properties": {
    "addr:full":"921 S Park Cir Anaheim CA 92804",
    "addr:housenumber":"921",
    "addr:postcode":"92804",
    "addr:street":"S Park Cir",
    "iso:country":"US",
    "sg:address":"921 S Park Cir",
    "sg:city":"Anaheim",
    "sg:classifiers":[
        {
            "category":"Real Estate",
            "subcategory":"Real Estate Operator",
            "type":"Services"
        }
    ],
    "sg:phone":"+1 714 776 8102",
    "sg:postcode":"92804",
    "sg:province":"CA",
    "sg:tags":[
        "apartment"
    ],
    "wof:name":"21 Apartments",
    "wof:placetype":"venue"
},
  "geometry": {"coordinates":[-117.94761,33.819453],"type":"Point"}
}