{
  "type": "Feature",
  "properties": {
    "iso:country":"US",
    "sg:address":"34241 Fremont Blvd",
    "sg:city":"Fremont",
    "sg:classifiers":[
        {
            "category":"Shopping",
            "subcategory":"Music",
            "type":"Retail Goods"
        }
    ],
    "sg:phone":"+1 510 739 1235",
    "sg:postcode":"94555",
    "sg:province":"CA",
    "sg:tags":[
        "video",
        "disc",
        "tape",
        "cassette"
    ],
    "wof:name":"Fremont Video",
    "wof:placetype":"venue"
},
  "geometry": {"coordinates":[-122.043417,37.576101],"type":"Point"}
}