{
  "type": "Feature",
  "properties": {
    "addr:full":"614 Sandydale Dr Nipomo CA 93444",
    "addr:housenumber":"614",
    "addr:postcode":"93444",
    "addr:street":"Sandydale Dr",
    "iso:country":"US",
    "sg:address":"614 Sandydale Dr",
    "sg:city":"Nipomo",
    "sg:classifiers":[
        {
            "category":"Home & Garden",
            "subcategory":"Household Appliances",
            "type":"Retail Goods"
        },
        {
            "category":"Manufacturing",
            "subcategory":"Chemicals & Compounds",
            "type":"Manufacturing & Wholesale Goods"
        }
    ],
    "sg:phone":"+1 805 929 5370",
    "sg:postcode":"93444",
    "sg:province":"CA",
    "sg:tags":[
        "cosmetic"
    ],
    "wof:name":"M R L Mechanical Systems",
    "wof:placetype":"venue"
},
  "geometry": {"coordinates":[-120.495842,35.043404],"type":"Point"}
}