{
  "type": "Feature",
  "properties": {
    "iso:country":"US",
    "sg:address":"49 Rockinghorse Rd",
    "sg:city":"Rancho Palos Verdes",
    "sg:classifiers":[
        {
            "category":"Manufacturing",
            "subcategory":"Printing",
            "type":"Manufacturing & Wholesale Goods"
        }
    ],
    "sg:phone":"+1 310 831 2219",
    "sg:postcode":"90275",
    "sg:province":"CA",
    "sg:tags":[
        "publishing"
    ],
    "wof:name":"Independent Systems & Technica",
    "wof:placetype":"venue"
},
  "geometry": {"coordinates":[-118.32521199999999,33.759319],"type":"Point"}
}