{
  "type": "Feature",
  "properties": {
    "iso:country":"US",
    "sg:address":"1455 Crenshaw Blvd",
    "sg:city":"Torrance",
    "sg:classifiers":[
        {
            "category":"Professional",
            "subcategory":"Art Services",
            "type":"Services"
        }
    ],
    "sg:phone":"+1 310 787 6555",
    "sg:postcode":"90501",
    "sg:province":"CA",
    "sg:tags":[
        "graphic",
        "designer"
    ],
    "sg:website":"www.studiotanimoto.com",
    "wof:name":"Studio Tanimoto Inc",
    "wof:placetype":"venue"
},
  "geometry": {"coordinates":[-118.32869700000001,33.834127],"type":"Point"}
}