{
  "type": "Feature",
  "properties": {
    "iso:country":"US",
    "sg:address":"746 N Midway Dr",
    "sg:city":"Escondido",
    "sg:classifiers":[
        {
            "category":"Personal",
            "subcategory":"Beauty Salon",
            "type":"Services"
        }
    ],
    "sg:phone":"+1 760 745 0024",
    "sg:postcode":"92027",
    "sg:province":"CA",
    "wof:name":"Cosmet'Tee Salon Of Beauty",
    "wof:placetype":"venue"
},
  "geometry": {"coordinates":[-117.055909,33.144012],"type":"Point"}
}