{
  "type": "Feature",
  "properties": {
    "addr:full":"2365 Durham Ferry Rd Tracy CA 95304",
    "addr:housenumber":"2365",
    "addr:postcode":"95304",
    "addr:street":"Durham Ferry Rd",
    "iso:country":"US",
    "sg:address":"2365 Durham Ferry Rd",
    "sg:city":"Tracy",
    "sg:classifiers":[
        {
            "category":"Farming",
            "subcategory":"Farm",
            "type":"Manufacturing & Wholesale Goods"
        }
    ],
    "sg:phone":"+1 209 835 5442",
    "sg:postcode":"95304",
    "sg:province":"CA",
    "sg:tags":[
        "alfalfa"
    ],
    "wof:name":"Thomsen Farms Inc",
    "wof:placetype":"venue"
},
  "geometry": {"coordinates":[-121.278969,37.667496],"type":"Point"}
}