{
  "type": "Feature",
  "properties": {
    "addr:full":"2781 Obanion Rd Yuba City CA 95993",
    "addr:housenumber":"2781",
    "addr:postcode":"95993",
    "addr:street":"Obanion Rd",
    "iso:country":"US",
    "sg:address":"2781 Obanion Rd",
    "sg:city":"Yuba City",
    "sg:classifiers":[
        {
            "category":"Professional",
            "type":"Services"
        }
    ],
    "sg:phone":"+1 530 671 7272",
    "sg:postcode":"95993",
    "sg:province":"CA",
    "wof:name":"Hoppin Fmly Frms A Gen Prtnrsh",
    "wof:placetype":"venue"
},
  "geometry": {"coordinates":[-121.667827,39.025465],"type":"Point"}
}