{
  "type": "Feature",
  "properties": {
    "iso:country":"US",
    "sg:address":"555 E Olive Ave",
    "sg:city":"Fresno",
    "sg:classifiers":[
        {
            "category":"Restaurant",
            "type":"Food & Drink"
        }
    ],
    "sg:phone":"+1 559 268 2400",
    "sg:postcode":"93728",
    "sg:province":"CA",
    "wof:name":"Peach Pit",
    "wof:placetype":"venue"
},
  "geometry": {"coordinates":[-119.804826,36.757719],"type":"Point"}
}