{
  "type": "Feature",
  "properties": {
    "addr:full":"802 W 12th St Alturas CA 96101",
    "addr:housenumber":"802",
    "addr:postcode":"96101",
    "addr:street":"W 12Th St",
    "iso:country":"US",
    "sg:address":"802 W 12th St",
    "sg:city":"Alturas",
    "sg:classifiers":[
        {
            "category":"Government",
            "subcategory":"Office",
            "type":"Public Place"
        }
    ],
    "sg:phone":"+1 530 233 4391",
    "sg:postcode":"96101",
    "sg:province":"CA",
    "sg:tags":[
        "federal"
    ],
    "wof:name":"US Consolidated Farm Svc Agcy",
    "wof:placetype":"venue"
},
  "geometry": {"coordinates":[-120.555156,41.494636],"type":"Point"}
}