{
  "type": "Feature",
  "properties": {
    "iso:country":"US",
    "sg:address":"165 N Raymond Ave",
    "sg:city":"Fullerton",
    "sg:classifiers":[
        {
            "category":"Manufacturing",
            "subcategory":"Printing",
            "type":"Manufacturing & Wholesale Goods"
        }
    ],
    "sg:phone":"+1 714 446 0431",
    "sg:postcode":"92831",
    "sg:province":"CA",
    "sg:tags":[
        "printer"
    ],
    "wof:name":"Ad-U Colorcard",
    "wof:placetype":"venue"
},
  "geometry": {"coordinates":[-117.907072,33.871241],"type":"Point"}
}