{
  "type": "Feature",
  "properties": {
    "iso:country":"US",
    "sg:address":"1126 W Foothill Blvd",
    "sg:city":"Upland",
    "sg:classifiers":[
        {
            "category":"Real Estate",
            "subcategory":"Real Estate Agent",
            "type":"Services"
        }
    ],
    "sg:phone":"+1 909 985 0550",
    "sg:postcode":"91786",
    "sg:province":"CA",
    "wof:name":"Pacific Empire Real Estate",
    "wof:placetype":"venue"
},
  "geometry": {"coordinates":[-117.672261,34.10688],"type":"Point"}
}