{
  "type": "Feature",
  "properties": {
    "iso:country":"US",
    "sg:address":"2300 Fair St",
    "sg:city":"Chico",
    "sg:classifiers":[
        {
            "category":"Utilities",
            "subcategory":"Refuse",
            "type":"Services"
        }
    ],
    "sg:phone":"+1 530 343 8641",
    "sg:postcode":"95928",
    "sg:province":"CA",
    "sg:tags":[
        "system"
    ],
    "sg:website":"www.wtc.org",
    "wof:name":"Fair Street Recycling",
    "wof:placetype":"venue"
},
  "geometry": {"coordinates":[-121.815342,39.716597],"type":"Point"}
}