{
  "type": "Feature",
  "properties": {
    "iso:country":"US",
    "sg:address":"1541 Amapola St",
    "sg:city":"Vacaville",
    "sg:classifiers":[
        {
            "category":"Freight",
            "type":"Transportation"
        }
    ],
    "sg:phone":"+1 707 446 3767",
    "sg:postcode":"95687",
    "sg:province":"CA",
    "sg:tags":[
        "operator",
        "trucking"
    ],
    "wof:name":"W D Trucking",
    "wof:placetype":"venue"
},
  "geometry": {"coordinates":[-121.981021,38.334252],"type":"Point"}
}