{
  "type": "Feature",
  "properties": {
    "iso:country":"US",
    "sg:address":"2755 Moore Rd",
    "sg:city":"Lincoln",
    "sg:classifiers":[
        {
            "category":"Shopping",
            "subcategory":"Baby Store",
            "type":"Retail Goods"
        }
    ],
    "sg:phone":"+1 916 434 6769",
    "sg:postcode":"95648",
    "sg:province":"CA",
    "sg:tags":[
        "accessories",
        "furnishing"
    ],
    "wof:name":"Bumble Baby",
    "wof:placetype":"venue"
},
  "geometry": {"coordinates":[-121.330703,38.868913],"type":"Point"}
}