{
  "type": "Feature",
  "properties": {
    "iso:country":"US",
    "sg:address":"1035 Carol Ln",
    "sg:city":"Lafayette",
    "sg:classifiers":[
        {
            "category":"Social Services",
            "subcategory":"Adult Care",
            "type":"Services"
        }
    ],
    "sg:phone":"+1 925 284 8328",
    "sg:postcode":"94549",
    "sg:province":"CA",
    "sg:tags":[
        "organization",
        "senior",
        "citizen"
    ],
    "wof:name":"Contact Care Ctr",
    "wof:placetype":"venue"
},
  "geometry": {"coordinates":[-122.102646,37.891427],"type":"Point"}
}