{
  "type": "Feature",
  "properties": {
    "iso:country":"US",
    "sg:address":"24571 Sunnymead Blvd",
    "sg:city":"Moreno Valley",
    "sg:classifiers":[
        {
            "category":"Autos & Motor Vehicles",
            "subcategory":"Auto Supplies",
            "type":"Retail Goods"
        }
    ],
    "sg:phone":"+1 951 601 1733",
    "sg:postcode":"92553",
    "sg:province":"CA",
    "sg:tags":[
        "automobile",
        "stereo",
        "radio"
    ],
    "wof:name":"Modern Image Car Audio",
    "wof:placetype":"venue"
},
  "geometry": {"coordinates":[-117.227942,33.939027],"type":"Point"}
}