{
  "type": "Feature",
  "properties": {
    "iso:country":"US",
    "sg:address":"19402 Elmira Ct",
    "sg:city":"Cerritos",
    "sg:classifiers":[
        {
            "category":"Insurance",
            "subcategory":"Insurance Agent",
            "type":"Services"
        }
    ],
    "sg:phone":"+1 562 924 1753",
    "sg:postcode":"90703",
    "sg:province":"CA",
    "wof:name":"Eugenio Rene P Insurance",
    "wof:placetype":"venue"
},
  "geometry": {"coordinates":[-118.094165,33.854441],"type":"Point"}
}