{
  "type": "Feature",
  "properties": {
    "addr:full":"609 Ord St Aptos CA 95003",
    "addr:housenumber":"609",
    "addr:postcode":"ca 95003",
    "addr:street":"Ord St",
    "iso:country":"US",
    "sg:address":"609 Ord St",
    "sg:city":"Aptos",
    "sg:classifiers":[
        {
            "category":"Arts & Performance",
            "subcategory":"Theater",
            "type":"Entertainment"
        },
        {
            "category":"Shopping",
            "subcategory":"Gifts & Souvenirs",
            "type":"Retail Goods"
        }
    ],
    "sg:phone":"+1 831 477 7633",
    "sg:postcode":"95003",
    "sg:province":"CA",
    "sg:tags":[
        "entertainer",
        "business"
    ],
    "wof:name":"Adventure Balloons",
    "wof:placetype":"venue"
},
  "geometry": {"coordinates":[-121.919742,36.980374],"type":"Point"}
}