{
  "type": "Feature",
  "properties": {
    "addr:full":"5960 S Land Park Dr Sacramento CA 95822",
    "addr:housenumber":"5960",
    "addr:postcode":"95822",
    "addr:street":"S Land Park Dr",
    "iso:country":"US",
    "sg:address":"5960 S Land Park Dr",
    "sg:city":"Sacramento",
    "sg:classifiers":[
        {
            "category":"Government",
            "subcategory":"Embassy",
            "type":"Public Place"
        },
        {
            "category":"Professional",
            "subcategory":"Lawyer & Legal Services",
            "type":"Services"
        },
        {
            "category":"Professional",
            "subcategory":"Business Services",
            "type":"Services"
        },
        {
            "category":"Professional",
            "subcategory":"Printing & Photocopies",
            "type":"Services"
        },
        {
            "category":"Government",
            "subcategory":"Post Office",
            "type":"Public Place"
        }
    ],
    "sg:phone":"+1 916 399 8171",
    "sg:postcode":"95822",
    "sg:province":"CA",
    "sg:tags":[
        "information",
        "copying",
        "photo",
        "duplicating",
        "mailbox-rental",
        "visa",
        "passport",
        "notary",
        "receiving"
    ],
    "sg:website":"http://www.landparkbusinessservices.com",
    "wof:name":"Land Park Business Services",
    "wof:placetype":"venue"
},
  "geometry": {"coordinates":[-121.51300000000001,38.5191],"type":"Point"}
}