{
  "type": "Feature",
  "properties": {
    "addr:full":"900 N Milpas St Santa Barbara CA 93103",
    "addr:housenumber":"900",
    "addr:postcode":"93103",
    "addr:street":"N Milpas St",
    "iso:country":"US",
    "sg:address":"900 N Milpas St",
    "sg:city":"Santa Barbara",
    "sg:classifiers":[
        {
            "category":"Shopping",
            "subcategory":"Clothing, Apparel, & Fashions",
            "type":"Retail Goods"
        }
    ],
    "sg:phone":"+1 805 963 0607",
    "sg:postcode":"93103",
    "sg:province":"CA",
    "sg:tags":[
        "shop",
        "bridal"
    ],
    "wof:name":"Angels's Bridal Boutique",
    "wof:placetype":"venue"
},
  "geometry": {"coordinates":[-119.691614,34.43091],"type":"Point"}
}