{
  "type": "Feature",
  "properties": {
    "iso:country":"US",
    "sg:address":"23456 Hawthorne Blvd Ste 200",
    "sg:city":"Torrance",
    "sg:classifiers":[
        {
            "category":"Health Services",
            "subcategory":"Doctor",
            "type":"Services"
        }
    ],
    "sg:phone":"+1 310 375 8700",
    "sg:postcode":"90505",
    "sg:province":"CA",
    "sg:tags":[
        "orthopedist"
    ],
    "wof:name":"Borden Peter S MD",
    "wof:placetype":"venue"
},
  "geometry": {"coordinates":[-118.350844,33.812909],"type":"Point"}
}