{
  "type": "Feature",
  "properties": {
    "iso:country":"US",
    "sg:address":"Mendoza Elementary School 2050 Coronado Avenue",
    "sg:city":"San Diego",
    "sg:classifiers":[
        {
            "category":"Place Of Worship",
            "subcategory":"Church",
            "type":"Public Place"
        }
    ],
    "sg:phone":"+1 619 421 4100",
    "sg:postcode":"92154",
    "sg:province":"CA",
    "sg:website":"blog.eastlakechurch.com/",
    "wof:name":"Eastlake Church Southcoast",
    "wof:placetype":"venue"
},
  "geometry": {"coordinates":[-117.08954199999999,32.577396],"type":"Point"}
}