{
  "type": "Feature",
  "properties": {
    "addr:full":"1348 Beach St Vallejo CA 94590",
    "addr:housenumber":"1348",
    "addr:postcode":"94590",
    "addr:street":"Beach St",
    "iso:country":"US",
    "sg:address":"1348 Beach St",
    "sg:city":"Vallejo",
    "sg:classifiers":[
        {
            "category":"Health Services",
            "subcategory":"Nursing And Care Facility",
            "type":"Services"
        }
    ],
    "sg:phone":"+1 707 557 9275",
    "sg:postcode":"94590",
    "sg:province":"CA",
    "wof:name":"Columbus Nursing Home",
    "wof:placetype":"venue"
},
  "geometry": {"coordinates":[-122.237658,38.097272],"type":"Point"}
}