{
  "type": "Feature",
  "properties": {
    "addr:full":"3413 Watt Ave Sacramento CA 95821",
    "addr:housenumber":"3413",
    "addr:postcode":"95821",
    "addr:street":"Watt Ave",
    "iso:country":"US",
    "sg:address":"3413 Watt Ave",
    "sg:city":"Sacramento",
    "sg:classifiers":[
        {
            "category":"Retail",
            "subcategory":"Laundry & Dry Cleaning",
            "type":"Services"
        }
    ],
    "sg:phone":"+1 916 487 5591",
    "sg:postcode":"95821",
    "sg:province":"CA",
    "sg:tags":[
        "cleaner"
    ],
    "wof:name":"Dry Clean Today",
    "wof:placetype":"venue"
},
  "geometry": {"coordinates":[-121.38298,38.626406],"type":"Point"}
}