{
  "type": "Feature",
  "properties": {
    "iso:country":"US",
    "sg:address":"25961 Wright",
    "sg:city":"El Toro",
    "sg:classifiers":[
        {
            "category":"Wholesale",
            "subcategory":"Machinery & Supplies",
            "type":"Manufacturing & Wholesale Goods"
        }
    ],
    "sg:phone":"+1 949 768 1777",
    "sg:postcode":"92610",
    "sg:province":"CA",
    "sg:tags":[
        "equipment",
        "industrial"
    ],
    "wof:name":"Quinn Shepherd Machinery",
    "wof:placetype":"venue"
},
  "geometry": {"coordinates":[-117.67728,33.683479],"type":"Point"}
}