{
  "type": "Feature",
  "properties": {
    "addr:full":"206 Edwards St Winters CA 95694",
    "addr:housenumber":"206",
    "addr:postcode":"95694",
    "addr:street":"Edwards St",
    "iso:country":"US",
    "sg:address":"206 Edwards St",
    "sg:city":"Winters",
    "sg:classifiers":[
        {
            "category":"Utilities",
            "subcategory":"Telephone",
            "type":"Services"
        }
    ],
    "sg:phone":"+1 530 795 1552",
    "sg:postcode":"95694",
    "sg:province":"CA",
    "sg:tags":[
        "internet"
    ],
    "wof:name":"Innetvations",
    "wof:placetype":"venue"
},
  "geometry": {"coordinates":[-121.97273,38.522262],"type":"Point"}
}