{
  "type": "Feature",
  "properties": {
    "iso:country":"US",
    "sg:address":"1142 W Evelyn Ave",
    "sg:city":"Sunnyvale",
    "sg:classifiers":[
        {
            "category":"Home & Garden",
            "subcategory":"Household Appliances",
            "type":"Retail Goods"
        }
    ],
    "sg:phone":"+1 408 245 5602",
    "sg:postcode":"94086",
    "sg:province":"CA",
    "sg:tags":[
        "repair"
    ],
    "sg:website":"www.mmipowerequipment.com",
    "wof:name":"MMI Power Equipment",
    "wof:placetype":"venue"
},
  "geometry": {"coordinates":[-122.050701,37.384481],"type":"Point"}
}