{
  "type": "Feature",
  "properties": {
    "iso:country":"US",
    "sg:address":"1646 Front St",
    "sg:city":"San Diego",
    "sg:classifiers":[
        {
            "category":"Shopping",
            "subcategory":"Gifts & Souvenirs",
            "type":"Retail Goods"
        }
    ],
    "sg:phone":"+1 619 233 8846",
    "sg:postcode":"92101",
    "sg:province":"CA",
    "sg:tags":[
        "shop"
    ],
    "wof:name":"S D Giftshop II",
    "wof:placetype":"venue"
},
  "geometry": {"coordinates":[-117.164852,32.722507],"type":"Point"}
}