{
  "type": "Feature",
  "properties": {
    "iso:country":"US",
    "sg:address":"3467 Whittier",
    "sg:city":"Los Angeles",
    "sg:classifiers":[
        {
            "category":"Health Services",
            "subcategory":"Clinic",
            "type":"Services"
        }
    ],
    "sg:phone":"+1 323 265 9228",
    "sg:postcode":"90023",
    "sg:province":"CA",
    "sg:tags":[
        "counseling",
        "mental"
    ],
    "sg:website":"Elcentrodeayuda.org",
    "wof:name":"El Centro de Ayuda",
    "wof:placetype":"venue"
},
  "geometry": {"coordinates":[-118.198776,34.027205],"type":"Point"}
}