{
  "type": "Feature",
  "properties": {
    "addr:full":"138 Santa Monica Blvd Santa Monica CA 90401",
    "addr:housenumber":"138",
    "addr:postcode":"90401",
    "addr:street":"Santa Monica Blvd",
    "iso:country":"US",
    "sg:address":"138 Santa Monica Blvd",
    "sg:city":"Santa Monica",
    "sg:classifiers":[
        {
            "category":"Shopping",
            "subcategory":"Shoes",
            "type":"Retail Goods"
        }
    ],
    "sg:phone":"+1 310 587 3365",
    "sg:postcode":"90401",
    "sg:province":"CA",
    "wof:name":"Nine West",
    "wof:placetype":"venue"
},
  "geometry": {"coordinates":[-118.497139,34.014715],"type":"Point"}
}