{
  "type": "Feature",
  "properties": {
    "iso:country":"US",
    "sg:address":"4361 Latham St",
    "sg:city":"Riverside",
    "sg:classifiers":[
        {
            "category":"Insurance",
            "subcategory":"Insurance Agent",
            "type":"Services"
        }
    ],
    "sg:phone":"+1 909 466 9663",
    "sg:postcode":"92501",
    "sg:province":"CA",
    "wof:name":"Matrix Absence Management Inc",
    "wof:placetype":"venue"
},
  "geometry": {"coordinates":[-117.374822,34.002466],"type":"Point"}
}