{
  "type": "Feature",
  "properties": {
    "addr:full":"1600 E Citrus Ave Redlands CA 92374",
    "addr:housenumber":"1600",
    "addr:postcode":"92374",
    "addr:street":"E Citrus Ave",
    "iso:country":"US",
    "sg:address":"1600 E Citrus Ave",
    "sg:city":"Redlands",
    "sg:classifiers":[
        {
            "category":"Restaurant",
            "type":"Food & Drink"
        }
    ],
    "sg:phone":"+1 909 794 6499",
    "sg:postcode":"92374",
    "sg:province":"CA",
    "wof:name":"B K Subs",
    "wof:placetype":"venue"
},
  "geometry": {"coordinates":[-117.146798,34.054811],"type":"Point"}
}