{
  "type": "Feature",
  "properties": {
    "addr:full":"925 Blossom Hill Road Ofc Oakridge Mall San Jose CA 95123",
    "addr:housenumber":"925",
    "addr:postcode":"95123",
    "addr:street":"Blossom Hill Road;Oakridge Mall",
    "iso:country":"US",
    "sg:address":"925 Blossom Hill Road Ofc Oakridge Mall",
    "sg:city":"San Jose",
    "sg:classifiers":[
        {
            "category":"Shopping",
            "subcategory":"Clothing, Apparel, & Fashions",
            "type":"Retail Goods"
        }
    ],
    "sg:phone":"+1 408 578 9700",
    "sg:postcode":"95123",
    "sg:province":"CA",
    "wof:name":"Aeropostale Inc",
    "wof:placetype":"venue"
},
  "geometry": {"coordinates":[-121.86199999999999,37.250599],"type":"Point"}
}