{
  "type": "Feature",
  "properties": {
    "iso:country":"US",
    "sg:address":"925 Elm St",
    "sg:city":"San Carlos",
    "sg:classifiers":[
        {
            "category":"Communications",
            "type":"Services"
        }
    ],
    "sg:phone":"+1 650 631 9345",
    "sg:postcode":"94070",
    "sg:province":"CA",
    "sg:tags":[
        "communication"
    ],
    "wof:name":"Scott Communications",
    "wof:placetype":"venue"
},
  "geometry": {"coordinates":[-122.256705,37.500608],"type":"Point"}
}