{
  "type": "Feature",
  "properties": {
    "iso:country":"US",
    "sg:address":"312 Monterey Pass Rd",
    "sg:city":"Monterey Park",
    "sg:classifiers":[
        {
            "category":"Manufacturing",
            "subcategory":"Apparel",
            "type":"Manufacturing & Wholesale Goods"
        }
    ],
    "sg:phone":"+1 626 282 6452",
    "sg:postcode":"91754",
    "sg:province":"CA",
    "sg:tags":[
        "sewing",
        "contractor"
    ],
    "wof:name":"Elenas Fashion",
    "wof:placetype":"venue"
},
  "geometry": {"coordinates":[-118.14322199999999,34.060057],"type":"Point"}
}