{
  "type": "Feature",
  "properties": {
    "addr:full":"1125 5th St Los Banos CA 93635",
    "addr:housenumber":"1125",
    "addr:postcode":"93635",
    "addr:street":"5Th St",
    "iso:country":"US",
    "sg:address":"1125 5th St",
    "sg:city":"Los Banos",
    "sg:classifiers":[
        {
            "category":"Social Services",
            "type":"Services"
        }
    ],
    "sg:phone":"+1 209 829 0744",
    "sg:postcode":"93635",
    "sg:province":"CA",
    "sg:tags":[
        "counselor",
        "marriage",
        "family"
    ],
    "wof:name":"Diana C Sehnal",
    "wof:placetype":"venue"
},
  "geometry": {"coordinates":[-120.850893,37.059419],"type":"Point"}
}