{
  "type": "Feature",
  "properties": {
    "addr:full":"5309 Comercio Way Woodland Hills CA 91364",
    "addr:housenumber":"5309",
    "addr:postcode":"91364",
    "addr:street":"Comercio Way",
    "iso:country":"US",
    "sg:address":"5309 Comercio Way",
    "sg:city":"Woodland Hills",
    "sg:classifiers":[
        {
            "category":"Banks & Credit Unions",
            "subcategory":"Atm",
            "type":"Services"
        }
    ],
    "sg:phone":"+1 818 888 7528",
    "sg:postcode":"91364",
    "sg:province":"CA",
    "sg:tags":[
        "bankruptcy"
    ],
    "wof:name":"Affordable Legal Solutions",
    "wof:placetype":"venue"
},
  "geometry": {"coordinates":[-118.596001,34.165798],"type":"Point"}
}