{
  "type": "Feature",
  "properties": {
    "addr:full":"1551 MacArthur Blvd Oakland CA 94602",
    "addr:housenumber":"1551",
    "addr:postcode":"94602",
    "addr:street":"Macarthur Blvd",
    "iso:country":"US",
    "sg:address":"1551 MacArthur Blvd",
    "sg:city":"Oakland",
    "sg:classifiers":[
        {
            "category":"Personal",
            "type":"Services"
        },
        {
            "category":"Retail",
            "subcategory":"Storage",
            "type":"Services"
        }
    ],
    "sg:phone":"+1 510 482 3010",
    "sg:postcode":"94602",
    "sg:province":"CA",
    "sg:tags":[
        "full",
        "self",
        "commercial",
        "mover",
        "household"
    ],
    "sg:website":"www.publicstorage.com",
    "wof:name":"Public Storage",
    "wof:placetype":"venue"
},
  "geometry": {"coordinates":[-122.22399900000001,37.8008],"type":"Point"}
}