{
  "type": "Feature",
  "properties": {
    "addr:full":"1040 W Las Palmas Ave Patterson CA 95363",
    "addr:housenumber":"1040",
    "addr:postcode":"95363",
    "addr:street":"W Las Palmas Ave",
    "iso:country":"US",
    "sg:address":"1040 W Las Palmas Ave",
    "sg:city":"Patterson",
    "sg:classifiers":[
        {
            "category":"Professional",
            "subcategory":"Detective & Security Services",
            "type":"Services"
        }
    ],
    "sg:phone":"+1 209 834 4372",
    "sg:postcode":"95363",
    "sg:province":"CA",
    "sg:tags":[
        "equipment",
        "system",
        "consultant"
    ],
    "wof:name":"Bay Valley Security",
    "wof:placetype":"venue"
},
  "geometry": {"coordinates":[-121.143044,37.466579],"type":"Point"}
}