{
  "type": "Feature",
  "properties": {
    "iso:country":"US",
    "sg:address":"2554 Lincoln Blvd",
    "sg:city":"Venice",
    "sg:classifiers":[
        {
            "category":"Shopping",
            "subcategory":"Gifts & Souvenirs",
            "type":"Retail Goods"
        }
    ],
    "sg:phone":"+1 310 578 1792",
    "sg:postcode":"90291",
    "sg:province":"CA",
    "sg:tags":[
        "basket",
        "parcel"
    ],
    "wof:name":"Adult Gift Baskets",
    "wof:placetype":"venue"
},
  "geometry": {"coordinates":[-118.448256,33.991129],"type":"Point"}
}