{
  "type": "Feature",
  "properties": {
    "addr:full":"181 Cecil Pl Costa Mesa CA 92627",
    "addr:housenumber":"181",
    "addr:postcode":"92627",
    "addr:street":"Cecil Pl",
    "iso:country":"US",
    "sg:address":"181 Cecil Pl",
    "sg:city":"Costa Mesa",
    "sg:classifiers":[
        {
            "category":"Home & Garden",
            "subcategory":"Home Furnishings",
            "type":"Retail Goods"
        }
    ],
    "sg:phone":"+1 949 836 1808",
    "sg:postcode":"92627",
    "sg:province":"CA",
    "sg:tags":[
        "window",
        "covering"
    ],
    "wof:name":"Almighty Window Washing/Blind",
    "wof:placetype":"venue"
},
  "geometry": {"coordinates":[-117.904375,33.651376],"type":"Point"}
}