{
  "type": "Feature",
  "properties": {
    "iso:country":"US",
    "sg:address":"9180 Kelvin Ave",
    "sg:city":"Chatsworth",
    "sg:classifiers":[
        {
            "category":"Retail",
            "subcategory":"Auto Rental",
            "type":"Services"
        }
    ],
    "sg:phone":"+1 818 775 9811",
    "sg:postcode":"91311",
    "sg:province":"CA",
    "sg:tags":[
        "renting",
        "truck",
        "leasing"
    ],
    "wof:name":"Alternative Transit Solutions",
    "wof:placetype":"venue"
},
  "geometry": {"coordinates":[-118.585384,34.23767],"type":"Point"}
}