{
  "type": "Feature",
  "properties": {
    "addr:full":"15901 Imperial Hwy La Mirada CA 90638",
    "addr:housenumber":"15901",
    "addr:postcode":"90638",
    "addr:street":"Imperial Hwy",
    "iso:country":"US",
    "sg:address":"15901 Imperial Hwy",
    "sg:city":"La Mirada",
    "sg:classifiers":[
        {
            "category":"Professional",
            "subcategory":"Lawyer & Legal Services",
            "type":"Services"
        }
    ],
    "sg:phone":"+1 562 943 7281",
    "sg:postcode":"90638",
    "sg:province":"CA",
    "sg:tags":[
        "divorce",
        "law",
        "family"
    ],
    "wof:name":"Tomeo Kathleen Atty",
    "wof:placetype":"venue"
},
  "geometry": {"coordinates":[-117.99700199999999,33.917198],"type":"Point"}
}