{
  "type": "Feature",
  "properties": {
    "iso:country":"US",
    "sg:address":"1330 San Bernardino Rd",
    "sg:city":"Upland",
    "sg:classifiers":[
        {
            "category":"Shopping",
            "type":"Retail Goods"
        }
    ],
    "sg:phone":"+1 909 946 6476",
    "sg:postcode":"91786",
    "sg:province":"CA",
    "sg:tags":[
        "consulting",
        "merchandise",
        "business"
    ],
    "wof:name":"Inland Hearing Center",
    "wof:placetype":"venue"
},
  "geometry": {"coordinates":[-117.631241,34.103486],"type":"Point"}
}