{
  "type": "Feature",
  "properties": {
    "iso:country":"US",
    "sg:address":"13736 Goldenwest St Ste A",
    "sg:city":"Westminster",
    "sg:classifiers":[
        {
            "category":"Personal",
            "type":"Services"
        }
    ],
    "sg:phone":"+1 714 894 5135",
    "sg:postcode":"92683",
    "sg:province":"CA",
    "sg:tags":[
        "sewing",
        "alteration"
    ],
    "wof:name":"Tam Truong Tailor",
    "wof:placetype":"venue"
},
  "geometry": {"coordinates":[-118.007125,33.762738],"type":"Point"}
}