{
  "type": "Feature",
  "properties": {
    "iso:country":"US",
    "sg:address":"242 N Santa Cruz Ave",
    "sg:city":"Los Gatos",
    "sg:classifiers":[
        {
            "category":"Shopping",
            "type":"Retail Goods"
        }
    ],
    "sg:phone":"+1 408 354 1606",
    "sg:postcode":"95030",
    "sg:province":"CA",
    "sg:tags":[
        "picture",
        "frame",
        "framing"
    ],
    "wof:name":"Finn's",
    "wof:placetype":"venue"
},
  "geometry": {"coordinates":[-121.98200199999999,37.226601],"type":"Point"}
}