{
  "type": "Feature",
  "properties": {
    "addr:full":"14855 Rosemary Dr Victorville CA 92394",
    "addr:housenumber":"14855",
    "addr:postcode":"92394",
    "addr:street":"Rosemary Dr",
    "iso:country":"US",
    "sg:address":"14855 Rosemary Dr",
    "sg:city":"Victorville",
    "sg:classifiers":[
        {
            "category":"Professional",
            "type":"Services"
        }
    ],
    "sg:phone":"+1 760 963 0066",
    "sg:postcode":"92394",
    "sg:province":"CA",
    "wof:name":"Fidelis Services",
    "wof:placetype":"venue"
},
  "geometry": {"coordinates":[-117.342129,34.519981],"type":"Point"}
}