{
  "type": "Feature",
  "properties": {
    "addr:full":"10067 Freesia Ave Stockton CA 95212",
    "addr:postcode":"10067;95212",
    "addr:street":"Freesia Ave",
    "iso:country":"US",
    "sg:address":"10067 Freesia Ave",
    "sg:city":"Stockton",
    "sg:classifiers":[
        {
            "category":"Professional",
            "subcategory":"Engineering",
            "type":"Services"
        }
    ],
    "sg:phone":"+1 209 931 0258",
    "sg:postcode":"95212",
    "sg:province":"CA",
    "sg:tags":[
        "consultant",
        "sales"
    ],
    "wof:name":"Araco",
    "wof:placetype":"venue"
},
  "geometry": {"coordinates":[-121.25200100000001,38.046195],"type":"Point"}
}