{
  "type": "Feature",
  "properties": {
    "iso:country":"US",
    "sg:address":"4453 Via Majorca",
    "sg:city":"Cypress",
    "sg:classifiers":[
        {
            "category":"Local Transit",
            "type":"Transportation"
        }
    ],
    "sg:phone":"+1 714 229 9706",
    "sg:postcode":"90630",
    "sg:province":"CA",
    "sg:tags":[
        "passenger"
    ],
    "wof:name":"Mr Barrs Wheelchair Cleaning",
    "wof:placetype":"venue"
},
  "geometry": {"coordinates":[-118.054678,33.820205],"type":"Point"}
}