{
  "type": "Feature",
  "properties": {
    "addr:full":"5464 N Palm Ave Fresno CA 93704",
    "addr:housenumber":"5464",
    "addr:postcode":"93704",
    "addr:street":"N Palm Ave",
    "iso:country":"US",
    "sg:address":"5464 N Palm Ave",
    "sg:city":"Fresno",
    "sg:classifiers":[
        {
            "category":"Professional",
            "subcategory":"Accounting & Tax Preparation",
            "type":"Services"
        }
    ],
    "sg:phone":"+1 559 438 4357",
    "sg:postcode":"93704",
    "sg:province":"CA",
    "sg:tags":[
        "return",
        "filing"
    ],
    "wof:name":"Exact Financial Svc",
    "wof:placetype":"venue"
},
  "geometry": {"coordinates":[-119.80826500000001,36.81807],"type":"Point"}
}