{
  "type": "Feature",
  "properties": {
    "iso:country":"US",
    "sg:address":"5064 Lankershim Blvd",
    "sg:city":"North Hollywood",
    "sg:classifiers":[
        {
            "category":"Arts & Performance",
            "subcategory":"Music",
            "type":"Entertainment"
        },
        {
            "category":"Communications",
            "type":"Services"
        }
    ],
    "sg:phone":"+1 818 980 9122",
    "sg:postcode":"91601",
    "sg:province":"CA",
    "sg:tags":[
        "recording",
        "rehearsal",
        "venue",
        "studio"
    ],
    "wof:name":"The Alley",
    "wof:placetype":"venue"
},
  "geometry": {"coordinates":[-118.373215,34.162554],"type":"Point"}
}