{
  "type": "Feature",
  "properties": {
    "addr:full":"20382 Barents Sea Cir Lake Forest CA 92630",
    "addr:housenumber":"20382",
    "addr:postcode":"92630",
    "addr:street":"Barents Sea Cir",
    "iso:country":"US",
    "sg:address":"20382 Barents Sea Cir",
    "sg:city":"Lake Forest",
    "sg:classifiers":[
        {
            "category":"Banks & Credit Unions",
            "subcategory":"Investment Brokerage",
            "type":"Services"
        }
    ],
    "sg:phone":"+1 949 768 3310",
    "sg:postcode":"92630",
    "sg:province":"CA",
    "sg:tags":[
        "advisory",
        "financial"
    ],
    "wof:name":"Plexus Financial Group Inc",
    "wof:placetype":"venue"
},
  "geometry": {"coordinates":[-117.679193,33.666221],"type":"Point"}
}