{
  "type": "Feature",
  "properties": {
    "addr:full":"4561 Alla Rd Marina Del Rey CA 90292",
    "addr:housenumber":"4561",
    "addr:postcode":"90292",
    "addr:street":"Alla Rd",
    "iso:country":"US",
    "sg:address":"4561 Alla Rd",
    "sg:city":"Marina Del Rey",
    "sg:classifiers":[
        {
            "category":"Travel",
            "subcategory":"Hotels & Motels",
            "type":"Entertainment"
        }
    ],
    "sg:phone":"+1 661 678 4048",
    "sg:postcode":"90292",
    "sg:province":"CA",
    "sg:tags":[
        "operation"
    ],
    "wof:name":"Hyatt",
    "wof:placetype":"venue"
},
  "geometry": {"coordinates":[-118.43217799999999,33.986362],"type":"Point"}
}