{
  "type": "Feature",
  "properties": {
    "iso:country":"US",
    "sg:address":"78415 Varner Rd",
    "sg:city":"Palm Desert",
    "sg:classifiers":[
        {
            "category":"Autos & Motor Vehicles",
            "subcategory":"Fuel & Gas Station",
            "type":"Retail Goods"
        }
    ],
    "sg:phone":"+1 760 772 2421",
    "sg:postcode":"92211",
    "sg:province":"CA",
    "sg:tags":[
        "oil"
    ],
    "wof:name":"Desert Cities Chevron",
    "wof:placetype":"venue"
},
  "geometry": {"coordinates":[-116.293511,33.757875],"type":"Point"}
}