{
  "type": "Feature",
  "properties": {
    "iso:country":"US",
    "sg:address":"1933 Hornblend St",
    "sg:city":"San Diego",
    "sg:classifiers":[
        {
            "category":"Real Estate",
            "subcategory":"Real Estate Operator",
            "type":"Services"
        }
    ],
    "sg:phone":"+1 858 483 1933",
    "sg:postcode":"92109",
    "sg:province":"CA",
    "sg:tags":[
        "apartment"
    ],
    "wof:name":"Hornblend House Apartments",
    "wof:placetype":"venue"
},
  "geometry": {"coordinates":[-117.233772,32.800267],"type":"Point"}
}