{
  "type": "Feature",
  "properties": {
    "addr:full":"3366 Leonis Boulevard Los Angeles CA 90058",
    "addr:housenumber":"3366",
    "addr:postcode":"90058",
    "addr:street":"Leonis Boulevard",
    "iso:country":"US",
    "sg:address":"3366 Leonis Boulevard",
    "sg:city":"Los Angeles",
    "sg:classifiers":[
        {
            "category":"Autos & Motor Vehicles",
            "subcategory":"Auto Supplies",
            "type":"Retail Goods"
        }
    ],
    "sg:phone":"+1 323 583 1561",
    "sg:postcode":"90058",
    "sg:province":"CA",
    "sg:tags":[
        "tire"
    ],
    "wof:name":"Commercial Tire Company",
    "wof:placetype":"venue"
},
  "geometry": {"coordinates":[-118.205898,34.000182],"type":"Point"}
}