{
  "type": "Feature",
  "properties": {
    "addr:full":"3443 San Pablo Ave Oakland CA 94608",
    "addr:housenumber":"3443",
    "addr:postcode":"94608",
    "addr:street":"San Pablo Ave",
    "iso:country":"US",
    "sg:address":"3443 San Pablo Ave",
    "sg:city":"Oakland",
    "sg:classifiers":[
        {
            "category":"Health Services",
            "subcategory":"Clinic",
            "type":"Services"
        }
    ],
    "sg:phone":"+1 510 596 8200",
    "sg:postcode":"94608",
    "sg:province":"CA",
    "sg:tags":[
        "aids",
        "testing",
        "information"
    ],
    "sg:website":"www.openhand.org",
    "wof:name":"Project Open Hand",
    "wof:placetype":"venue"
},
  "geometry": {"coordinates":[-122.278436,37.826058],"type":"Point"}
}