{
  "type": "Feature",
  "properties": {
    "iso:country":"US",
    "sg:address":"437 Briggs Rd",
    "sg:city":"Hollister",
    "sg:classifiers":[
        {
            "category":"Wholesale",
            "subcategory":"Fruits & Vegetables",
            "type":"Manufacturing & Wholesale Goods"
        }
    ],
    "sg:phone":"+1 831 637 1499",
    "sg:postcode":"95023",
    "sg:province":"CA",
    "wof:name":"David E Grimes Co",
    "wof:placetype":"venue"
},
  "geometry": {"coordinates":[-121.408941,36.877658],"type":"Point"}
}