{
  "type": "Feature",
  "properties": {
    "iso:country":"US",
    "sg:address":"1055 Sylvan Glen Pl",
    "sg:city":"Auburn",
    "sg:classifiers":[
        {
            "category":"Real Estate",
            "subcategory":"Real Estate Agent",
            "type":"Services"
        }
    ],
    "sg:phone":"+1 530 888 7250",
    "sg:postcode":"95603",
    "sg:province":"CA",
    "wof:name":"Howard and Associates Realty",
    "wof:placetype":"venue"
},
  "geometry": {"coordinates":[-121.051518,38.927926],"type":"Point"}
}