{
  "type": "Feature",
  "properties": {
    "addr:full":"886 W 9th St Upland CA 91786",
    "addr:housenumber":"886",
    "addr:postcode":"91786",
    "addr:street":"W 9Th St",
    "iso:country":"US",
    "sg:address":"886 W 9th St",
    "sg:city":"Upland",
    "sg:classifiers":[
        {
            "category":"Manufacturing",
            "subcategory":"Electronics",
            "type":"Manufacturing & Wholesale Goods"
        }
    ],
    "sg:phone":"+1 909 920 0314",
    "sg:postcode":"91786",
    "sg:province":"CA",
    "sg:tags":[
        "printers-equipment",
        "supply"
    ],
    "wof:name":"Quint Printing Equipment Mvrs",
    "wof:placetype":"venue"
},
  "geometry": {"coordinates":[-117.663211,34.096043],"type":"Point"}
}