{
  "type": "Feature",
  "properties": {
    "addr:full":"312 Sierra Ridge Dr Encinitas CA 92024",
    "addr:housenumber":"312",
    "addr:postcode":"92024",
    "addr:street":"Sierra Ridge Dr",
    "iso:country":"US",
    "sg:address":"312 Sierra Ridge Dr",
    "sg:city":"Encinitas",
    "sg:classifiers":[
        {
            "category":"Health Services",
            "subcategory":"Medical Lab",
            "type":"Services"
        }
    ],
    "sg:phone":"+1 760 942 8501",
    "sg:postcode":"92024",
    "sg:province":"CA",
    "sg:tags":[
        "laboratory"
    ],
    "wof:name":"Pacific Dental Restorations",
    "wof:placetype":"venue"
},
  "geometry": {"coordinates":[-117.23960599999999,33.046937],"type":"Point"}
}