{
  "type": "Feature",
  "properties": {
    "addr:full":"8210 Katella Ave Stanton CA 90680",
    "addr:housenumber":"8210",
    "addr:postcode":"ca 90680",
    "addr:street":"Katella Ave",
    "iso:country":"US",
    "sg:address":"8210 Katella Ave",
    "sg:city":"Stanton",
    "sg:classifiers":[
        {
            "category":"Shopping",
            "subcategory":"Clothing, Apparel, & Fashions",
            "type":"Retail Goods"
        }
    ],
    "sg:phone":"+1 714 897 3638",
    "sg:postcode":"90680",
    "sg:province":"CA",
    "wof:name":"Anton Fashions",
    "wof:placetype":"venue"
},
  "geometry": {"coordinates":[-117.989141,33.802874],"type":"Point"}
}