{
  "type": "Feature",
  "properties": {
    "iso:country":"US",
    "sg:address":"21804 S Vermont Ave",
    "sg:city":"Torrance",
    "sg:classifiers":[
        {
            "category":"Retail",
            "subcategory":"Repair Shop",
            "type":"Services"
        }
    ],
    "sg:phone":"+1 310 328 6472",
    "sg:postcode":"90502",
    "sg:province":"CA",
    "sg:tags":[
        "tool",
        "parts"
    ],
    "wof:name":"Universal Tool Svc",
    "wof:placetype":"venue"
},
  "geometry": {"coordinates":[-118.290226,33.831292],"type":"Point"}
}