{
  "type": "Feature",
  "properties": {
    "addr:full":"2716 Carina Ct Walnut Creek CA 94598",
    "addr:housenumber":"2716",
    "addr:postcode":"94598",
    "addr:street":"Carina Ct",
    "iso:country":"US",
    "sg:address":"2716 Carina Ct",
    "sg:city":"Walnut Creek",
    "sg:classifiers":[
        {
            "category":"Professional",
            "subcategory":"Accounting & Tax Preparation",
            "type":"Services"
        }
    ],
    "sg:phone":"+1 925 947 4358",
    "sg:postcode":"94598",
    "sg:province":"CA",
    "sg:tags":[
        "billing"
    ],
    "wof:name":"Medi-Bill",
    "wof:placetype":"venue"
},
  "geometry": {"coordinates":[-122.01424400000001,37.912882],"type":"Point"}
}