{
  "type": "Feature",
  "properties": {
    "iso:country":"US",
    "sg:address":"4743 Trafalgar Pl",
    "sg:city":"Santa Rosa",
    "sg:classifiers":[
        {
            "category":"Building & Trades",
            "subcategory":"Construction",
            "type":"Services"
        }
    ],
    "sg:phone":"+1 707 539 5069",
    "sg:postcode":"95405",
    "sg:province":"CA",
    "sg:tags":[
        "development"
    ],
    "wof:name":"Rcx Inc",
    "wof:placetype":"venue"
},
  "geometry": {"coordinates":[-122.653678,38.438885],"type":"Point"}
}