{
  "type": "Feature",
  "properties": {
    "iso:country":"US",
    "sg:address":"2874 Alum Rock Ave # A",
    "sg:city":"San Jose",
    "sg:classifiers":[
        {
            "category":"Shopping",
            "subcategory":"Pharmacy",
            "type":"Retail Goods"
        }
    ],
    "sg:phone":"+1 408 937 4618",
    "sg:postcode":"95127",
    "sg:province":"CA",
    "sg:tags":[
        "drugstore"
    ],
    "wof:name":"Pacific Pharmacy",
    "wof:placetype":"venue"
},
  "geometry": {"coordinates":[-121.83200100000001,37.363701],"type":"Point"}
}