{
  "type": "Feature",
  "properties": {
    "addr:full":"42150 Cook St Palm Desert CA 92211",
    "addr:housenumber":"42150",
    "addr:postcode":"92211",
    "addr:street":"Cook St",
    "iso:country":"US",
    "sg:address":"42150 Cook St",
    "sg:city":"Palm Desert",
    "sg:classifiers":[
        {
            "category":"Food & Beverages",
            "subcategory":"Groceries & Convenience Stores",
            "type":"Retail Goods"
        }
    ],
    "sg:phone":"+1 760 837 1877",
    "sg:postcode":"92211",
    "sg:province":"CA",
    "sg:tags":[
        "grocer"
    ],
    "wof:name":"Jensen's Finest Foods",
    "wof:placetype":"venue"
},
  "geometry": {"coordinates":[-116.356233,33.741248],"type":"Point"}
}