{
  "type": "Feature",
  "properties": {
    "iso:country":"US",
    "sg:address":"316 Temple Ave",
    "sg:city":"Long Beach",
    "sg:classifiers":[
        {
            "category":"Professional",
            "subcategory":"Business Services",
            "type":"Services"
        }
    ],
    "sg:phone":"+1 562 438 6857",
    "sg:postcode":"90814",
    "sg:province":"CA",
    "wof:name":"Vanessa",
    "wof:placetype":"venue"
},
  "geometry": {"coordinates":[-118.15885400000001,33.769288],"type":"Point"}
}