{
  "type": "Feature",
  "properties": {
    "addr:full":"16285 Pine Ave Fontana CA 92335",
    "addr:housenumber":"16285",
    "addr:postcode":"92335",
    "addr:street":"Pine Ave",
    "iso:country":"US",
    "sg:address":"16285 Pine Ave",
    "sg:city":"Fontana",
    "sg:classifiers":[
        {
            "category":"Manufacturing",
            "subcategory":"Metals",
            "type":"Manufacturing & Wholesale Goods"
        }
    ],
    "sg:phone":"+1 909 854 0807",
    "sg:postcode":"92335",
    "sg:province":"CA",
    "wof:name":"Corona Metal Polishing",
    "wof:placetype":"venue"
},
  "geometry": {"coordinates":[-117.449944,34.086961],"type":"Point"}
}