{
  "type": "Feature",
  "properties": {
    "addr:full":"330 Townsend Street Suite 213 San Francisco CA 94107",
    "addr:housenumber":"330",
    "addr:postcode":"94107",
    "addr:street":"Townsend Street Suite 213",
    "iso:country":"US",
    "sg:address":"330 Townsend Street Suite 213",
    "sg:city":"San Francisco",
    "sg:classifiers":[
        {
            "category":"Professional",
            "subcategory":"Computer Services",
            "type":"Services"
        }
    ],
    "sg:phone":"+1 415 637 3307",
    "sg:postcode":"94107",
    "sg:province":"CA",
    "sg:tags":[
        "flixya",
        "youtube",
        "google",
        "adsense",
        "revenue-share"
    ],
    "sg:website":"http://flixya.com",
    "wof:name":"Flixya",
    "wof:placetype":"venue"
},
  "geometry": {"coordinates":[-122.396721,37.775923],"type":"Point"}
}