{
  "type": "Feature",
  "properties": {
    "iso:country":"US",
    "sg:address":"7400 Imperial Hwy",
    "sg:city":"Downey",
    "sg:classifiers":[
        {
            "category":"Education",
            "subcategory":"Library",
            "type":"Public Place"
        }
    ],
    "sg:phone":"+1 562 940 8462",
    "sg:postcode":"90242",
    "sg:province":"CA",
    "wof:name":"Los Angeles County Library",
    "wof:placetype":"venue"
},
  "geometry": {"coordinates":[-118.160968,33.928497],"type":"Point"}
}