{
  "type": "Feature",
  "properties": {
    "addr:full":"725 35th St Manhattan Beach CA 90266",
    "addr:housenumber":"725",
    "addr:postcode":"90266",
    "addr:street":"35Th St",
    "iso:country":"US",
    "sg:address":"725 35th St",
    "sg:city":"Manhattan Beach",
    "sg:classifiers":[
        {
            "category":"Professional",
            "type":"Services"
        }
    ],
    "sg:phone":"+1 310 802 1144",
    "sg:postcode":"90266",
    "sg:province":"CA",
    "wof:name":"Charles Dapoz Inc",
    "wof:placetype":"venue"
},
  "geometry": {"coordinates":[-118.406645,33.900077],"type":"Point"}
}