{
  "type": "Feature",
  "properties": {
    "iso:country":"US",
    "sg:address":"15651 Hawthorne Blvd",
    "sg:city":"Hawthorne",
    "sg:classifiers":[
        {
            "category":"Restaurant",
            "type":"Food & Drink"
        }
    ],
    "sg:phone":"+1 310 973 6476",
    "sg:postcode":"90260",
    "sg:province":"CA",
    "sg:tags":[
        "american",
        "latin",
        "buffet"
    ],
    "sg:website":"www.incagourmetrestaurant.com",
    "wof:name":"Inca Gourmet Restaurant",
    "wof:placetype":"venue"
},
  "geometry": {"coordinates":[-118.352711,33.889103],"type":"Point"}
}