{
  "type": "Feature",
  "properties": {
    "iso:country":"US",
    "sg:address":"3375 S Hoover St",
    "sg:city":"Los Angeles",
    "sg:classifiers":[
        {
            "category":"Shopping Center",
            "type":"Public Place"
        }
    ],
    "sg:phone":"+1 310 312 4570",
    "sg:postcode":"90007",
    "sg:province":"CA",
    "wof:name":"University Village Shopping Center",
    "wof:placetype":"venue"
},
  "geometry": {"coordinates":[-118.283997,34.0243],"type":"Point"}
}