{
  "type": "Feature",
  "properties": {
    "addr:full":"2330 Big Pine Rd Escondido CA 92027",
    "addr:housenumber":"2330",
    "addr:postcode":"92027",
    "addr:street":"Big Pine Rd",
    "iso:country":"US",
    "sg:address":"2330 Big Pine Rd",
    "sg:city":"Escondido",
    "sg:classifiers":[
        {
            "category":"Real Estate",
            "subcategory":"Real Estate Services",
            "type":"Services"
        },
        {
            "category":"Real Estate",
            "subcategory":"Real Estate Agent",
            "type":"Services"
        }
    ],
    "sg:phone":"+1 760 839 3900",
    "sg:postcode":"92027",
    "sg:province":"CA",
    "sg:tags":[
        "buyer",
        "broker"
    ],
    "wof:name":"Cox Realty Inc",
    "wof:placetype":"venue"
},
  "geometry": {"coordinates":[-117.03833,33.123385],"type":"Point"}
}