{
  "type": "Feature",
  "properties": {
    "addr:full":"3306 Harrison St Oakland CA 94611",
    "addr:housenumber":"3306",
    "addr:postcode":"94611",
    "addr:street":"Harrison St",
    "iso:country":"US",
    "sg:address":"3306 Harrison St",
    "sg:city":"Oakland",
    "sg:classifiers":[
        {
            "category":"Professional",
            "subcategory":"Lawyer & Legal Services",
            "type":"Services"
        }
    ],
    "sg:phone":"+1 510 834 4511",
    "sg:postcode":"94611",
    "sg:province":"CA",
    "sg:tags":[
        "attorney"
    ],
    "wof:name":"Michael R Berger",
    "wof:placetype":"venue"
},
  "geometry": {"coordinates":[-122.25528,37.818675],"type":"Point"}
}