{
  "type": "Feature",
  "properties": {
    "iso:country":"US",
    "sg:address":"1320 W Gardena Boulevard Sutie 102",
    "sg:city":"Gardena",
    "sg:classifiers":[
        {
            "category":"Banks & Credit Unions",
            "subcategory":"Financial Services",
            "type":"Services"
        }
    ],
    "sg:phone":"+1 310 323 0069",
    "sg:postcode":"90247",
    "sg:province":"CA",
    "wof:name":"Naso Tax Service",
    "wof:placetype":"venue"
},
  "geometry": {"coordinates":[-118.298173,33.881386],"type":"Point"}
}