{
  "type": "Feature",
  "properties": {
    "iso:country":"US",
    "sg:address":"11635 Cebada Ct",
    "sg:city":"San Diego",
    "sg:classifiers":[
        {
            "category":"Shopping",
            "subcategory":"Hobbies, Toys, & Games",
            "type":"Retail Goods"
        }
    ],
    "sg:phone":"+1 858 279 9474",
    "sg:postcode":"92124",
    "sg:province":"CA",
    "wof:name":"Kueys Creations",
    "wof:placetype":"venue"
},
  "geometry": {"coordinates":[-117.078132,32.819209],"type":"Point"}
}