{
  "type": "Feature",
  "properties": {
    "iso:country":"US",
    "sg:address":"1101 W McKinley Ave",
    "sg:city":"Pomona",
    "sg:classifiers":[
        {
            "category":"Shopping",
            "type":"Retail Goods"
        }
    ],
    "sg:phone":"+1 909 865 4560",
    "sg:postcode":"91768",
    "sg:province":"CA",
    "sg:tags":[
        "art",
        "gallery",
        "dealer"
    ],
    "wof:name":"Millard Sheets Gallery",
    "wof:placetype":"venue"
},
  "geometry": {"coordinates":[-117.767893,34.081216],"type":"Point"}
}