{
  "type": "Feature",
  "properties": {
    "addr:full":"27981 Greenfield Dr Ste F Laguna Niguel CA 92677",
    "addr:housenumber":"27981",
    "addr:postcode":"92677",
    "addr:street":"Greenfield Dr Ste F",
    "iso:country":"US",
    "sg:address":"27981 Greenfield Dr Ste F",
    "sg:city":"Laguna Niguel",
    "sg:classifiers":[
        {
            "category":"Health Services",
            "subcategory":"Dentist",
            "type":"Services"
        }
    ],
    "sg:phone":"+1 949 362 7474",
    "sg:postcode":"92677",
    "sg:province":"CA",
    "sg:tags":[
        "orthodontist"
    ],
    "sg:website":"www.drhumphriesortho.com/",
    "wof:name":"Gene R Humphries, DDS, MS",
    "wof:placetype":"venue"
},
  "geometry": {"coordinates":[-117.685378,33.558475],"type":"Point"}
}