{
  "type": "Feature",
  "properties": {
    "iso:country":"US",
    "sg:address":"900 E Main St",
    "sg:city":"Grass Valley",
    "sg:classifiers":[
        {
            "category":"Manufacturing",
            "subcategory":"Electronics",
            "type":"Manufacturing & Wholesale Goods"
        }
    ],
    "sg:phone":"+1 530 272 9800",
    "sg:postcode":"95945",
    "sg:province":"CA",
    "sg:website":"www.accom.com",
    "wof:name":"Accom Inc",
    "wof:placetype":"venue"
},
  "geometry": {"coordinates":[-121.051661,39.228298],"type":"Point"}
}