{
  "type": "Feature",
  "properties": {
    "iso:country":"US",
    "sg:address":"2627 W 116th Street",
    "sg:city":"Hawthorne",
    "sg:classifiers":[
        {
            "category":"Education",
            "subcategory":"Preschool",
            "type":"Public Place"
        },
        {
            "category":"Education",
            "subcategory":"School",
            "type":"Public Place"
        }
    ],
    "sg:phone":"+1 323 757 0228",
    "sg:postcode":"90250",
    "sg:province":"CA",
    "sg:tags":[
        "high",
        "middle",
        "elementary"
    ],
    "wof:name":"Atherton Christian School",
    "wof:placetype":"venue"
},
  "geometry": {"coordinates":[-118.32191400000001,33.928649],"type":"Point"}
}