{
  "type": "Feature",
  "properties": {
    "addr:full":"201 Sand Creek Rd Brentwood CA 94513",
    "addr:housenumber":"201",
    "addr:postcode":"ca 94513",
    "addr:street":"Sand Creek Rd",
    "iso:country":"US",
    "sg:address":"201 Sand Creek Rd",
    "sg:city":"Brentwood",
    "sg:classifiers":[
        {
            "category":"Wholesale",
            "subcategory":"Books, Periodicals, & Newspapers",
            "type":"Manufacturing & Wholesale Goods"
        }
    ],
    "sg:phone":"+1 925 634 4870",
    "sg:postcode":"94513",
    "sg:province":"CA",
    "sg:tags":[
        "publisher",
        "book"
    ],
    "wof:name":"B A E B Publishing",
    "wof:placetype":"venue"
},
  "geometry": {"coordinates":[-121.700333,37.94659],"type":"Point"}
}