{
  "type": "Feature",
  "properties": {
    "iso:country":"US",
    "sg:address":"5412 Cleon Ave",
    "sg:city":"North Hollywood",
    "sg:classifiers":[
        {
            "category":"Education",
            "subcategory":"Music School",
            "type":"Public Place"
        }
    ],
    "sg:phone":"+1 818 985 7300",
    "sg:postcode":"91601",
    "sg:province":"CA",
    "sg:tags":[
        "instrument",
        "teacher",
        "musical"
    ],
    "wof:name":"Korg Studio West",
    "wof:placetype":"venue"
},
  "geometry": {"coordinates":[-118.368444,34.168901],"type":"Point"}
}