{
  "type": "Feature",
  "properties": {
    "addr:full":"18374 Phantom E Victorville CA 92394",
    "addr:housenumber":"18374",
    "addr:postcode":"92394",
    "addr:street":"Phantom E",
    "iso:country":"US",
    "sg:address":"18374 Phantom E",
    "sg:city":"Victorville",
    "sg:classifiers":[
        {
            "category":"Airport",
            "type":"Transportation"
        }
    ],
    "sg:phone":"+1 760 243 1900",
    "sg:postcode":"92394",
    "sg:province":"CA",
    "wof:name":"Victorville City Airport",
    "wof:placetype":"venue"
},
  "geometry": {"coordinates":[-117.348223,34.57878],"type":"Point"}
}