{
  "type": "Feature",
  "properties": {
    "iso:country":"US",
    "sg:address":"8266 Miramar Cir",
    "sg:city":"Riverside",
    "sg:classifiers":[
        {
            "category":"Health Services",
            "subcategory":"Nursing And Care Facility",
            "type":"Services"
        }
    ],
    "sg:phone":"+1 951 685 6164",
    "sg:postcode":"92509",
    "sg:province":"CA",
    "wof:name":"Miramar House",
    "wof:placetype":"venue"
},
  "geometry": {"coordinates":[-117.46387,33.999155],"type":"Point"}
}