{
  "type": "Feature",
  "properties": {
    "addr:full":"25821 Industrial Blvd Hayward CA 94545",
    "addr:housenumber":"25821",
    "addr:postcode":"94545",
    "addr:street":"Industrial Blvd",
    "iso:country":"US",
    "sg:address":"25821 Industrial Blvd",
    "sg:city":"Hayward",
    "sg:classifiers":[
        {
            "category":"Professional",
            "subcategory":"Advertising",
            "type":"Services"
        }
    ],
    "sg:phone":"+1 510 732 7700",
    "sg:postcode":"94545",
    "sg:province":"CA",
    "sg:tags":[
        "designer",
        "display",
        "producer"
    ],
    "wof:name":"Showtime Enterprises West Inc",
    "wof:placetype":"venue"
},
  "geometry": {"coordinates":[-122.11516,37.636703],"type":"Point"}
}