{
  "type": "Feature",
  "properties": {
    "addr:full":"8561 Roland St Buena Park CA 90621",
    "addr:housenumber":"8561",
    "addr:postcode":"90621",
    "addr:street":"Roland St",
    "iso:country":"US",
    "sg:address":"8561 Roland St",
    "sg:city":"Buena Park",
    "sg:classifiers":[
        {
            "category":"Food & Beverages",
            "subcategory":"Candy",
            "type":"Retail Goods"
        }
    ],
    "sg:phone":"+1 714 521 2121",
    "sg:postcode":"90621",
    "sg:province":"CA",
    "sg:tags":[
        "store"
    ],
    "wof:name":"Candyman Can",
    "wof:placetype":"venue"
},
  "geometry": {"coordinates":[-117.98455300000001,33.86854],"type":"Point"}
}