{
  "type": "Feature",
  "properties": {
    "iso:country":"US",
    "sg:address":"1371 Nancy Ct",
    "sg:city":"Yuba City",
    "sg:classifiers":[
        {
            "category":"Retail",
            "subcategory":"Repair Shop",
            "type":"Services"
        }
    ],
    "sg:phone":"+1 530 671 2726",
    "sg:postcode":"95993",
    "sg:province":"CA",
    "sg:tags":[
        "related"
    ],
    "wof:name":"A 1 House Repair",
    "wof:placetype":"venue"
},
  "geometry": {"coordinates":[-121.63682,39.155261],"type":"Point"}
}