{
  "type": "Feature",
  "properties": {
    "iso:country":"US",
    "sg:address":"200 Ridgetop Dr #",
    "sg:city":"Redding",
    "sg:classifiers":[
        {
            "category":"Shopping",
            "subcategory":"Beauty & Cosmetics",
            "type":"Retail Goods"
        }
    ],
    "sg:phone":"+1 530 222 0651",
    "sg:postcode":"96003",
    "sg:province":"CA",
    "sg:tags":[
        "salons-equipment",
        "supply"
    ],
    "wof:name":"Cleo's Beauty Supply",
    "wof:placetype":"venue"
},
  "geometry": {"coordinates":[-122.374962,40.603298],"type":"Point"}
}