{
  "type": "Feature",
  "properties": {
    "addr:full":"44330 Rodin Ave Lancaster CA 93535",
    "addr:postcode":"44330;93535",
    "addr:street":"Rodin Ave",
    "iso:country":"US",
    "sg:address":"44330 Rodin Ave",
    "sg:city":"Lancaster",
    "sg:classifiers":[
        {
            "category":"Personal",
            "subcategory":"Beauty Salon",
            "type":"Services"
        }
    ],
    "sg:phone":"+1 661 948 2331",
    "sg:postcode":"93535",
    "sg:province":"CA",
    "wof:name":"Ginnie's Custom Hair",
    "wof:placetype":"venue"
},
  "geometry": {"coordinates":[-118.11873300000001,34.688278],"type":"Point"}
}