{
  "type": "Feature",
  "properties": {
    "iso:country":"US",
    "sg:address":"3443 Castro Valley Blvd",
    "sg:city":"Castro Valley",
    "sg:classifiers":[
        {
            "category":"Food & Beverages",
            "subcategory":"Groceries & Convenience Stores",
            "type":"Retail Goods"
        }
    ],
    "sg:phone":"+1 510 581 8636",
    "sg:postcode":"94546",
    "sg:province":"CA",
    "wof:name":"Albertsons Supermarkets",
    "wof:placetype":"venue"
},
  "geometry": {"coordinates":[-122.075996,37.695599],"type":"Point"}
}