{
  "type": "Feature",
  "properties": {
    "iso:country":"US",
    "sg:address":"3429 Freedom Park Dr",
    "sg:city":"North Highlands",
    "sg:classifiers":[
        {
            "category":"Shopping",
            "subcategory":"Computers & Home Electronics",
            "type":"Retail Goods"
        }
    ],
    "sg:phone":"+1 916 334 1888",
    "sg:postcode":"95660",
    "sg:province":"CA",
    "wof:name":"Sound & Light Source",
    "wof:placetype":"venue"
},
  "geometry": {"coordinates":[-121.386132,38.67679],"type":"Point"}
}