{
  "type": "Feature",
  "properties": {
    "iso:country":"US",
    "sg:address":"9647 Bolsa Ave",
    "sg:city":"Westminster",
    "sg:classifiers":[
        {
            "category":"Shopping",
            "subcategory":"Beauty & Cosmetics",
            "type":"Retail Goods"
        }
    ],
    "sg:phone":"+1 714 531 0775",
    "sg:postcode":"92683",
    "sg:province":"CA",
    "sg:tags":[
        "supply"
    ],
    "wof:name":"Bolsa Nails & Beauty Supply",
    "wof:placetype":"venue"
},
  "geometry": {"coordinates":[-117.96052,33.745127],"type":"Point"}
}