{
  "type": "Feature",
  "properties": {
    "addr:full":"609 Anderson Rd Davis CA 95616",
    "addr:housenumber":"609",
    "addr:postcode":"95616",
    "addr:street":"Anderson Rd",
    "iso:country":"US",
    "sg:address":"609 Anderson Rd",
    "sg:city":"Davis",
    "sg:classifiers":[
        {
            "category":"Real Estate",
            "subcategory":"Real Estate Operator",
            "type":"Services"
        }
    ],
    "sg:phone":"+1 530 756 4186",
    "sg:postcode":"95616",
    "sg:province":"CA",
    "sg:tags":[
        "apartment"
    ],
    "wof:name":"Sycamore Lane Garden Apts",
    "wof:placetype":"venue"
},
  "geometry": {"coordinates":[-121.758824,38.547469],"type":"Point"}
}