{
  "type": "Feature",
  "properties": {
    "addr:full":"1300 Stratford Ave Dixon CA 95620",
    "addr:housenumber":"1300",
    "addr:postcode":"95620",
    "addr:street":"Stratford Ave",
    "iso:country":"US",
    "sg:address":"1300 Stratford Ave",
    "sg:city":"Dixon",
    "sg:classifiers":[
        {
            "category":"Autos & Motor Vehicles",
            "subcategory":"Fuel & Gas Station",
            "type":"Retail Goods"
        },
        {
            "category":"Food & Beverages",
            "subcategory":"Groceries & Convenience Stores",
            "type":"Retail Goods"
        }
    ],
    "sg:phone":"+1 707 678 0528",
    "sg:postcode":"95620",
    "sg:province":"CA",
    "sg:website":"http://www.chevron.com/products/",
    "wof:name":"Chevron",
    "wof:placetype":"venue"
},
  "geometry": {"coordinates":[-121.839688,38.45804],"type":"Point"}
}