{
  "type": "Feature",
  "properties": {
    "addr:full":"714 N Coast Hwy Oceanside CA 92054",
    "addr:housenumber":"714",
    "addr:postcode":"92054",
    "addr:street":"N Coast Hwy",
    "iso:country":"US",
    "sg:address":"714 N Coast Hwy",
    "sg:city":"Oceanside",
    "sg:classifiers":[
        {
            "category":"Restaurant",
            "type":"Food & Drink"
        }
    ],
    "sg:phone":"+1 760 722 2254",
    "sg:postcode":"92054",
    "sg:province":"CA",
    "sg:tags":[
        "new",
        "american"
    ],
    "wof:name":"Harbor House Cafe",
    "wof:placetype":"venue"
},
  "geometry": {"coordinates":[-117.383003,33.200699],"type":"Point"}
}