{
  "type": "Feature",
  "properties": {
    "iso:country":"US",
    "sg:address":"21515 Hawthorne Blvd",
    "sg:city":"Torrance",
    "sg:classifiers":[
        {
            "category":"Professional",
            "subcategory":"Lawyer & Legal Services",
            "type":"Services"
        }
    ],
    "sg:phone":"+1 310 944 9800",
    "sg:postcode":"90503",
    "sg:province":"CA",
    "sg:tags":[
        "attorney"
    ],
    "wof:name":"Hansen Seto",
    "wof:placetype":"venue"
},
  "geometry": {"coordinates":[-118.35257900000001,33.831713],"type":"Point"}
}