{
  "type": "Feature",
  "properties": {
    "iso:country":"US",
    "sg:address":"28211 Newhall Ranch Rd",
    "sg:city":"Valencia",
    "sg:classifiers":[
        {
            "category":"Sports & Exercise",
            "subcategory":"Playing Field",
            "type":"Entertainment"
        }
    ],
    "sg:postcode":"91355",
    "sg:province":"CA",
    "sg:tags":[
        "instruction",
        "fitness"
    ],
    "wof:name":"LA Fitness",
    "wof:placetype":"venue"
},
  "geometry": {"coordinates":[-118.600584,34.443996],"type":"Point"}
}