{
  "type": "Feature",
  "properties": {
    "iso:country":"US",
    "sg:address":"240 Tamal Vista Blvd",
    "sg:city":"Corte Madera",
    "sg:classifiers":[
        {
            "category":"Health Services",
            "subcategory":"Doctor",
            "type":"Services"
        }
    ],
    "sg:phone":"+1 415 924 2861",
    "sg:postcode":"94925",
    "sg:province":"CA",
    "sg:tags":[
        "dentist"
    ],
    "wof:name":"Robert K Fowler DDS",
    "wof:placetype":"venue"
},
  "geometry": {"coordinates":[-122.518794,37.937942],"type":"Point"}
}