{
  "type": "Feature",
  "properties": {
    "addr:full":"110 E Carson St Carson CA 90745",
    "addr:housenumber":"110",
    "addr:postcode":"90745",
    "addr:street":"E Carson St",
    "iso:country":"US",
    "sg:address":"110 E Carson St",
    "sg:city":"Carson",
    "sg:classifiers":[
        {
            "category":"Shopping",
            "subcategory":"Pharmacy",
            "type":"Retail Goods"
        }
    ],
    "sg:phone":"+1 310 834 2561",
    "sg:postcode":"90745",
    "sg:province":"CA",
    "sg:tags":[
        "drugstore"
    ],
    "sg:website":"www.savon.com",
    "wof:name":"Sav-on Drugs",
    "wof:placetype":"venue"
},
  "geometry": {"coordinates":[-118.276349,33.831432],"type":"Point"}
}