{
  "type": "Feature",
  "properties": {
    "iso:country":"US",
    "sg:address":"19 S Garfield Ave",
    "sg:city":"Alhambra",
    "sg:classifiers":[
        {
            "category":"Professional",
            "subcategory":"Employment Agencies",
            "type":"Services"
        }
    ],
    "sg:phone":"+1 626 284 5627",
    "sg:postcode":"91801",
    "sg:province":"CA",
    "sg:tags":[
        "contractor"
    ],
    "wof:name":"SMART Staffing Services",
    "wof:placetype":"venue"
},
  "geometry": {"coordinates":[-118.12658399999999,34.094799],"type":"Point"}
}