{
  "type": "Feature",
  "properties": {
    "addr:full":"925 S 2nd St El Cajon CA 92019",
    "addr:housenumber":"925",
    "addr:postcode":"92019",
    "addr:street":"S 2Nd St",
    "iso:country":"US",
    "sg:address":"925 S 2nd St",
    "sg:city":"El Cajon",
    "sg:classifiers":[
        {
            "category":"Building & Trades",
            "subcategory":"Electrical",
            "type":"Services"
        }
    ],
    "sg:phone":"+1 619 441 9684",
    "sg:postcode":"92019",
    "sg:province":"CA",
    "sg:tags":[
        "electrical",
        "contractor"
    ],
    "wof:name":"Juneau Electric",
    "wof:placetype":"venue"
},
  "geometry": {"coordinates":[-116.937273,32.78419],"type":"Point"}
}