{
  "type": "Feature",
  "properties": {
    "iso:country":"US",
    "sg:address":"19000 MacArthur Boulevard Suite 610",
    "sg:city":"Irvine",
    "sg:classifiers":[
        {
            "category":"Professional",
            "subcategory":"Lawyer & Legal Services",
            "type":"Services"
        }
    ],
    "sg:phone":"+1 949 851 1229",
    "sg:postcode":"92612",
    "sg:province":"CA",
    "wof:name":"Hargan Mark C Attorney At Law",
    "wof:placetype":"venue"
},
  "geometry": {"coordinates":[-117.86312599999999,33.673306],"type":"Point"}
}