{
  "type": "Feature",
  "properties": {
    "iso:country":"US",
    "sg:address":"5500 Grossmont Center Dr",
    "sg:city":"La Mesa",
    "sg:classifiers":[
        {
            "category":"Restaurant",
            "type":"Food & Drink"
        }
    ],
    "sg:menulink":"http://www.allmenus.com/ca/san-diego/135518-jamba-juice/menu/",
    "sg:phone":"+1 619 460 7177",
    "sg:postcode":"91942",
    "sg:province":"CA",
    "sg:tags":[
        "smoothy",
        "juice",
        "american"
    ],
    "wof:name":"Jamba Juice",
    "wof:placetype":"venue"
},
  "geometry": {"coordinates":[-117.011584,32.777535],"type":"Point"}
}