{
  "type": "Feature",
  "properties": {
    "addr:full":"54326 Wildwood Springs Trl North Fork CA 93643",
    "addr:housenumber":"54326",
    "addr:postcode":"93643",
    "addr:street":"Wildwood Springs Trl",
    "iso:country":"US",
    "sg:address":"54326 Wildwood Springs Trl",
    "sg:city":"North Fork",
    "sg:classifiers":[
        {
            "category":"Professional",
            "subcategory":"Accounting & Tax Preparation",
            "type":"Services"
        }
    ],
    "sg:phone":"+1 559 877 3800",
    "sg:postcode":"93643",
    "sg:province":"CA",
    "sg:tags":[
        "accountant"
    ],
    "wof:name":"Julie M Chorjel CPA",
    "wof:placetype":"venue"
},
  "geometry": {"coordinates":[-119.558194,37.235085],"type":"Point"}
}