{
  "type": "Feature",
  "properties": {
    "iso:country":"US",
    "sg:address":"3550 E Cesar E Chavez Ave",
    "sg:city":"Los Angeles",
    "sg:classifiers":[
        {
            "category":"Food & Beverages",
            "subcategory":"Groceries & Convenience Stores",
            "type":"Retail Goods"
        }
    ],
    "sg:phone":"+1 323 261 9439",
    "sg:postcode":"90063",
    "sg:province":"CA",
    "wof:name":"Aguirre Paul & Sons Mkt",
    "wof:placetype":"venue"
},
  "geometry": {"coordinates":[-118.186996,34.040401],"type":"Point"}
}