{
  "type": "Feature",
  "properties": {
    "addr:full":"2800 S El Camino Real San Mateo CA 94403",
    "addr:housenumber":"2800",
    "addr:postcode":"94403",
    "addr:street":"S El Camino Real",
    "iso:country":"US",
    "sg:address":"2800 S El Camino Real",
    "sg:city":"San Mateo",
    "sg:classifiers":[
        {
            "category":"Autos & Motor Vehicles",
            "subcategory":"Fuel & Gas Station",
            "type":"Retail Goods"
        }
    ],
    "sg:phone":"+1 650 312 9519",
    "sg:postcode":"94403",
    "sg:province":"CA",
    "wof:name":"Pacific Conveinence & Fuels LLC",
    "wof:placetype":"venue"
},
  "geometry": {"coordinates":[-122.30295599999999,37.541538],"type":"Point"}
}