{
  "type": "Feature",
  "properties": {
    "iso:country":"US",
    "sg:address":"6895 Lariat Ln",
    "sg:city":"Castro Valley",
    "sg:classifiers":[
        {
            "category":"Professional",
            "subcategory":"Business Services",
            "type":"Services"
        }
    ],
    "sg:phone":"+1 510 886 0871",
    "sg:postcode":"94552",
    "sg:province":"CA",
    "sg:tags":[
        "packaging"
    ],
    "wof:name":"Fazzios Packaging Solutions",
    "wof:placetype":"venue"
},
  "geometry": {"coordinates":[-122.027168,37.715797],"type":"Point"}
}