{
  "type": "Feature",
  "properties": {
    "addr:full":"870 N Diamond Bar Blvd Diamond Bar CA 91765",
    "addr:housenumber":"870",
    "addr:postcode":"91765",
    "addr:street":"N Diamond Bar Blvd",
    "iso:country":"US",
    "sg:address":"870 N Diamond Bar Blvd",
    "sg:city":"Diamond Bar",
    "sg:classifiers":[
        {
            "category":"Banks & Credit Unions",
            "subcategory":"Investment Brokerage",
            "type":"Services"
        }
    ],
    "sg:phone":"+1 909 861 2500",
    "sg:postcode":"91765",
    "sg:province":"CA",
    "sg:tags":[
        "consultant",
        "financing"
    ],
    "wof:name":"L & J Funding Group",
    "wof:placetype":"venue"
},
  "geometry": {"coordinates":[-117.806994,34.034577],"type":"Point"}
}