{
  "type": "Feature",
  "properties": {
    "iso:country":"US",
    "sg:address":"15 W 5th St",
    "sg:city":"Morgan Hill",
    "sg:classifiers":[
        {
            "category":"Insurance",
            "subcategory":"Insurance Agent",
            "type":"Services"
        }
    ],
    "sg:phone":"+1 408 778 1443",
    "sg:postcode":"95037",
    "sg:province":"CA",
    "wof:name":"Gary Carroll Insurance",
    "wof:placetype":"venue"
},
  "geometry": {"coordinates":[-121.652739,37.125668],"type":"Point"}
}