{
  "type": "Feature",
  "properties": {
    "addr:full":"45 Poncetta Dr Daly City CA 94015",
    "addr:housenumber":"45",
    "addr:postcode":"94015",
    "addr:street":"Poncetta Dr",
    "iso:country":"US",
    "sg:address":"45 Poncetta Dr",
    "sg:city":"Daly City",
    "sg:classifiers":[
        {
            "category":"Wholesale",
            "subcategory":"Machinery & Supplies",
            "type":"Manufacturing & Wholesale Goods"
        },
        {
            "category":"Shopping",
            "subcategory":"Clothing, Apparel, & Fashions",
            "type":"Retail Goods"
        }
    ],
    "sg:phone":"+1 650 757 1166",
    "sg:postcode":"94015",
    "sg:province":"CA",
    "sg:tags":[
        "equipment",
        "establishment"
    ],
    "wof:name":"Beauty Hunt",
    "wof:placetype":"venue"
},
  "geometry": {"coordinates":[-122.473072,37.702964],"type":"Point"}
}