{
  "type": "Feature",
  "properties": {
    "addr:full":"1225 E Vista Way Vista CA 92084",
    "addr:housenumber":"1225",
    "addr:postcode":"92084",
    "addr:street":"E Vista Way",
    "iso:country":"US",
    "sg:address":"1225 E Vista Way",
    "sg:city":"Vista",
    "sg:classifiers":[
        {
            "category":"Banks & Credit Unions",
            "subcategory":"Investment Brokerage",
            "type":"Services"
        }
    ],
    "sg:phone":"+1 760 758 1711",
    "sg:postcode":"92084",
    "sg:province":"CA",
    "wof:name":"CBC Investment Inc",
    "wof:placetype":"venue"
},
  "geometry": {"coordinates":[-117.227289,33.215512],"type":"Point"}
}