{
  "type": "Feature",
  "properties": {
    "iso:country":"US",
    "sg:address":"1177 S Beverly Drive",
    "sg:city":"Beverly Hills",
    "sg:classifiers":[
        {
            "category":"Retail",
            "subcategory":"Auto Rental",
            "type":"Services"
        }
    ],
    "sg:phone":"+1 310 553 5128",
    "sg:postcode":"90210",
    "sg:province":"CA",
    "sg:tags":[
        "car"
    ],
    "wof:name":"Hertz",
    "wof:placetype":"venue"
},
  "geometry": {"coordinates":[-118.413907,34.09424],"type":"Point"}
}