{
  "type": "Feature",
  "properties": {
    "addr:full":"3540 Wilshire Blvd Suite 1201 Los Angeles CA 90005",
    "addr:housenumber":"3540",
    "addr:postcode":"90005",
    "addr:street":"Wilshire Blvd Suite 1201",
    "iso:country":"US",
    "sg:address":"3540 Wilshire Blvd Suite 1201",
    "sg:city":"Los Angeles",
    "sg:classifiers":[
        {
            "category":"Professional",
            "type":"Services"
        }
    ],
    "sg:phone":"+1 213 255 5686",
    "sg:postcode":"90005",
    "sg:province":"CA",
    "sg:website":"www.mountain25.com/",
    "wof:name":"Mountain 25",
    "wof:placetype":"venue"
},
  "geometry": {"coordinates":[-118.30167,34.060987],"type":"Point"}
}