{
  "type": "Feature",
  "properties": {
    "iso:country":"US",
    "sg:address":"8337 Corbin Ave",
    "sg:city":"Winnetka",
    "sg:classifiers":[
        {
            "category":"Manufacturing",
            "subcategory":"Printing",
            "type":"Manufacturing & Wholesale Goods"
        }
    ],
    "sg:phone":"+1 818 725 2893",
    "sg:postcode":"91306",
    "sg:province":"CA",
    "sg:tags":[
        "commercial"
    ],
    "wof:name":"Your Posters Company",
    "wof:placetype":"venue"
},
  "geometry": {"coordinates":[-118.56237,34.220814],"type":"Point"}
}