{
  "type": "Feature",
  "properties": {
    "addr:full":"2465 Santa Ana St Huntington Park CA 90255",
    "addr:housenumber":"2465",
    "addr:postcode":"90255",
    "addr:street":"Santa Ana St;Park",
    "iso:country":"US",
    "sg:address":"2465 Santa Ana St",
    "sg:city":"Huntington Park",
    "sg:classifiers":[
        {
            "category":"Wholesale",
            "subcategory":"Toys & Hobbies",
            "type":"Manufacturing & Wholesale Goods"
        }
    ],
    "sg:phone":"+1 323 581 9687",
    "sg:postcode":"90255",
    "sg:province":"CA",
    "wof:name":"J & MS Fun Factory",
    "wof:placetype":"venue"
},
  "geometry": {"coordinates":[-118.227084,33.96531],"type":"Point"}
}