{
  "type": "Feature",
  "properties": {
    "addr:full":"5767 Bloomfield Rd Petaluma CA 94952",
    "addr:housenumber":"5767",
    "addr:postcode":"94952",
    "addr:street":"Bloomfield Rd",
    "iso:country":"US",
    "sg:address":"5767 Bloomfield Rd",
    "sg:city":"Petaluma",
    "sg:classifiers":[
        {
            "category":"Building & Trades",
            "subcategory":"Construction",
            "type":"Services"
        }
    ],
    "sg:phone":"+1 707 792 1853",
    "sg:postcode":"94952",
    "sg:province":"CA",
    "sg:tags":[
        "general",
        "contractor"
    ],
    "wof:name":"Rafter B Construction",
    "wof:placetype":"venue"
},
  "geometry": {"coordinates":[-122.84152899999999,38.338268],"type":"Point"}
}