{
  "type": "Feature",
  "properties": {
    "iso:country":"US",
    "sg:address":"Farmer's Market 6333 W 3rd St",
    "sg:city":"Los Angeles",
    "sg:classifiers":[
        {
            "category":"Tea Room",
            "subcategory":"None",
            "type":"Food & Drink"
        },
        {
            "category":"Coffee & Tea",
            "type":"Food & Drink"
        }
    ],
    "sg:phone":"+1 323 930 0076",
    "sg:postcode":"90036",
    "sg:province":"CA",
    "sg:website":"www.teashopla.com",
    "wof:name":"T - Tea Shoppe",
    "wof:placetype":"venue"
},
  "geometry": {"coordinates":[-118.360105,34.071329],"type":"Point"}
}