{
  "type": "Feature",
  "properties": {
    "addr:full":"13580 Whittier Blvd Whittier CA 90605",
    "addr:housenumber":"13580",
    "addr:postcode":"90605",
    "addr:street":"Whittier Blvd",
    "iso:country":"US",
    "sg:address":"13580 Whittier Blvd",
    "sg:city":"Whittier",
    "sg:classifiers":[
        {
            "category":"Restaurant",
            "type":"Food & Drink"
        }
    ],
    "sg:menulink":"http://www.allmenus.com/ca/whittier/109878-chilis/menu/",
    "sg:phone":"+1 562 693 7300",
    "sg:postcode":"90605",
    "sg:province":"CA",
    "sg:tags":[
        "burger",
        "american",
        "sandwich",
        "tex-mex",
        "soup"
    ],
    "wof:name":"Chili's",
    "wof:placetype":"venue"
},
  "geometry": {"coordinates":[-118.029838,33.960977],"type":"Point"}
}