{
  "type": "Feature",
  "properties": {
    "iso:country":"US",
    "sg:address":"8328 Tunney Ave",
    "sg:city":"Northridge",
    "sg:classifiers":[
        {
            "category":"Professional",
            "subcategory":"Management & Consulting",
            "type":"Services"
        }
    ],
    "sg:phone":"+1 310 337 7750",
    "sg:postcode":"91324",
    "sg:province":"CA",
    "sg:tags":[
        "consultant",
        "hospital"
    ],
    "wof:name":"Healthcare Systems Consultants",
    "wof:placetype":"venue"
},
  "geometry": {"coordinates":[-118.55676,34.224005],"type":"Point"}
}