{
  "type": "Feature",
  "properties": {
    "addr:full":"4061 Ball Rd Cypress CA 90630",
    "addr:housenumber":"4061",
    "addr:postcode":"90630",
    "addr:street":"Ball Rd",
    "iso:country":"US",
    "sg:address":"4061 Ball Rd",
    "sg:city":"Cypress",
    "sg:classifiers":[
        {
            "category":"Shopping",
            "subcategory":"Florist",
            "type":"Retail Goods"
        }
    ],
    "sg:phone":"+1 714 229 1646",
    "sg:postcode":"90630",
    "sg:province":"CA",
    "wof:name":"Willows A Floral Impression",
    "wof:placetype":"venue"
},
  "geometry": {"coordinates":[-118.06199599999999,33.817799],"type":"Point"}
}