{
  "type": "Feature",
  "properties": {
    "addr:full":"Lake Merced Boulevard Southeast San Francisco CA 94199",
    "addr:postcode":"94199",
    "addr:street":"Lake Merced Boulevard Southeast",
    "iso:country":"US",
    "sg:address":"Lake Merced Boulevard Southeast",
    "sg:city":"San Francisco",
    "sg:classifiers":[
        {
            "category":"Landmark",
            "subcategory":"Historic",
            "type":"Public Place"
        }
    ],
    "sg:postcode":"94199",
    "sg:province":"CA",
    "sg:tags":[
        "building",
        "historical"
    ],
    "wof:name":"Broderick-Terry Duel Site",
    "wof:placetype":"venue"
},
  "geometry": {"coordinates":[-122.485147,37.720253],"type":"Point"}
}