{
  "type": "Feature",
  "properties": {
    "addr:full":"2025 Airpark Ct Auburn CA 95602",
    "addr:housenumber":"2025",
    "addr:postcode":"ca 95602",
    "addr:street":"Airpark Ct",
    "iso:country":"US",
    "sg:address":"2025 Airpark Ct",
    "sg:city":"Auburn",
    "sg:classifiers":[
        {
            "category":"Manufacturing",
            "subcategory":"Tools & Machinery",
            "type":"Manufacturing & Wholesale Goods"
        }
    ],
    "sg:phone":"+1 530 885 0700",
    "sg:postcode":"95602",
    "sg:province":"CA",
    "sg:tags":[
        "machine",
        "shop"
    ],
    "sg:website":"www.surfacemfg.com",
    "wof:name":"Surface Manufacturing",
    "wof:placetype":"venue"
},
  "geometry": {"coordinates":[-121.078,38.951563],"type":"Point"}
}