{
  "type": "Feature",
  "properties": {
    "iso:country":"US",
    "sg:address":"462 S Palm Canyon Dr",
    "sg:city":"Palm Springs",
    "sg:classifiers":[
        {
            "category":"Professional",
            "type":"Services"
        }
    ],
    "sg:phone":"+1 760 327 8858",
    "sg:postcode":"92262",
    "sg:province":"CA",
    "sg:tags":[
        "establishment"
    ],
    "wof:name":"J Robert Scott Inc",
    "wof:placetype":"venue"
},
  "geometry": {"coordinates":[-116.546707,33.818819],"type":"Point"}
}