{
  "type": "Feature",
  "properties": {
    "iso:country":"US",
    "sg:address":"69 W Willow Ave",
    "sg:city":"Porterville",
    "sg:classifiers":[
        {
            "category":"Shopping",
            "subcategory":"Gifts & Souvenirs",
            "type":"Retail Goods"
        }
    ],
    "sg:phone":"+1 559 781 1250",
    "sg:postcode":"93257",
    "sg:province":"CA",
    "sg:tags":[
        "shop"
    ],
    "sg:website":"www.longs.com",
    "wof:name":"Longs Drug",
    "wof:placetype":"venue"
},
  "geometry": {"coordinates":[-119.017596,36.066421],"type":"Point"}
}