{
  "type": "Feature",
  "properties": {
    "iso:country":"US",
    "sg:address":"3151 S. White Road Suite 104",
    "sg:city":"San Jose",
    "sg:classifiers":[
        {
            "category":"Health Services",
            "subcategory":"Dentist",
            "type":"Services"
        }
    ],
    "sg:phone":"+1 408 270 2273",
    "sg:postcode":"95148",
    "sg:province":"CA",
    "sg:website":"www.arbordentalsanjose.com",
    "wof:name":"Arbor Dental Group",
    "wof:placetype":"venue"
},
  "geometry": {"coordinates":[-121.793898,37.316527],"type":"Point"}
}