{
  "type": "Feature",
  "properties": {
    "iso:country":"US",
    "sg:address":"106 Placerville Dr",
    "sg:city":"Placerville",
    "sg:classifiers":[
        {
            "category":"Social Services",
            "type":"Services"
        }
    ],
    "sg:phone":"+1 530 626 3742",
    "sg:postcode":"95667",
    "sg:province":"CA",
    "sg:tags":[
        "youth",
        "organization",
        "center"
    ],
    "wof:name":"Timber Senior Little League",
    "wof:placetype":"venue"
},
  "geometry": {"coordinates":[-120.83555200000001,38.725431],"type":"Point"}
}