{
  "type": "Feature",
  "properties": {
    "iso:country":"US",
    "sg:address":"323 E Holly St",
    "sg:city":"Rialto",
    "sg:classifiers":[
        {
            "category":"Home & Garden",
            "subcategory":"Building Materials",
            "type":"Retail Goods"
        }
    ],
    "sg:phone":"+1 909 875 4267",
    "sg:postcode":"92376",
    "sg:province":"CA",
    "sg:tags":[
        "door"
    ],
    "wof:name":"Keegan's Garage Doors",
    "wof:placetype":"venue"
},
  "geometry": {"coordinates":[-117.364834,34.116191],"type":"Point"}
}