{
  "type": "Feature",
  "properties": {
    "addr:full":"209 N. Louise St. Glendale CA 91206",
    "addr:housenumber":"209",
    "addr:postcode":"91206",
    "addr:street":"N. Louise St.",
    "iso:country":"US",
    "sg:address":"209 N. Louise St.",
    "sg:city":"Glendale",
    "sg:classifiers":[
        {
            "category":"Arts & Performance",
            "subcategory":"Arts Center",
            "type":"Entertainment"
        }
    ],
    "sg:phone":"+1 818 640 5974",
    "sg:postcode":"91206",
    "sg:province":"CA",
    "sg:website":"www.achessacademy.org/",
    "wof:name":"American Chess Academy",
    "wof:placetype":"venue"
},
  "geometry": {"coordinates":[-118.252655,34.148498],"type":"Point"}
}