{
  "type": "Feature",
  "properties": {
    "iso:country":"US",
    "sg:address":"617 Alexander St",
    "sg:city":"Glendale",
    "sg:classifiers":[
        {
            "category":"Manufacturing",
            "subcategory":"Apparel",
            "type":"Manufacturing & Wholesale Goods"
        }
    ],
    "sg:phone":"+1 818 246 1980",
    "sg:postcode":"91203",
    "sg:province":"CA",
    "sg:tags":[
        "work",
        "clothing",
        "mfg"
    ],
    "wof:name":"Ect",
    "wof:placetype":"venue"
},
  "geometry": {"coordinates":[-118.269467,34.153279],"type":"Point"}
}