{
  "type": "Feature",
  "properties": {
    "addr:full":"914 Bayview Ave Oakland CA 94610",
    "addr:housenumber":"914",
    "addr:postcode":"94610",
    "addr:street":"Bayview Ave",
    "iso:country":"US",
    "sg:address":"914 Bayview Ave",
    "sg:city":"Oakland",
    "sg:classifiers":[
        {
            "category":"Professional",
            "subcategory":"Art Services",
            "type":"Services"
        }
    ],
    "sg:phone":"+1 510 919 5512",
    "sg:postcode":"94610",
    "sg:province":"CA",
    "sg:tags":[
        "designer",
        "display",
        "producer"
    ],
    "wof:name":"Interior Space Research",
    "wof:placetype":"venue"
},
  "geometry": {"coordinates":[-122.238266,37.801552],"type":"Point"}
}