{
  "type": "Feature",
  "properties": {
    "iso:country":"US",
    "sg:address":"15535 E Tetley St",
    "sg:city":"Hacienda Heights",
    "sg:classifiers":[
        {
            "category":"Manufacturing",
            "subcategory":"Metals",
            "type":"Manufacturing & Wholesale Goods"
        }
    ],
    "sg:phone":"+1 626 336 6486",
    "sg:postcode":"91745",
    "sg:province":"CA",
    "sg:tags":[
        "finisher"
    ],
    "wof:name":"Eqmpt Source",
    "wof:placetype":"venue"
},
  "geometry": {"coordinates":[-117.97715,33.995635],"type":"Point"}
}