{
  "type": "Feature",
  "properties": {
    "iso:country":"US",
    "sg:address":"1100 El Camino Real",
    "sg:city":"Belmont",
    "sg:classifiers":[
        {
            "category":"Autos & Motor Vehicles",
            "subcategory":"Automobile Sales",
            "type":"Retail Goods"
        },
        {
            "category":"Taxi",
            "type":"Transportation"
        }
    ],
    "sg:phone":"+1 650 669 0101",
    "sg:postcode":"94002",
    "sg:province":"CA",
    "sg:tags":[
        "limo"
    ],
    "sg:website":"www.order1taxi.com",
    "wof:name":"Belmont Taxi Cab & Limo",
    "wof:placetype":"venue"
},
  "geometry": {"coordinates":[-122.27555599999999,37.518887],"type":"Point"}
}