{
  "type": "Feature",
  "properties": {
    "addr:full":"222 N Sepulveda Boulevard El Segundo CA 90245",
    "addr:housenumber":"222",
    "addr:postcode":"90245",
    "addr:street":"N Sepulveda Boulevard",
    "iso:country":"US",
    "sg:address":"222 N Sepulveda Boulevard",
    "sg:city":"El Segundo",
    "sg:classifiers":[
        {
            "category":"Airline",
            "type":"Transportation"
        }
    ],
    "sg:phone":"+1 310 414 3250",
    "sg:postcode":"90245",
    "sg:province":"CA",
    "wof:name":"Emirates Airlines",
    "wof:placetype":"venue"
},
  "geometry": {"coordinates":[-118.395826,33.918526],"type":"Point"}
}