{
  "type": "Feature",
  "properties": {
    "iso:country":"US",
    "sg:address":"8521 Villa La Jolla Dr",
    "sg:city":"La Jolla",
    "sg:classifiers":[
        {
            "category":"Professional",
            "subcategory":"Art Services",
            "type":"Services"
        }
    ],
    "sg:phone":"+1 858 356 5358",
    "sg:postcode":"92037",
    "sg:province":"CA",
    "sg:tags":[
        "photographer"
    ],
    "sg:website":"www.davidmaxphotography.com",
    "wof:name":"David Max Photographer / Studio Light House",
    "wof:placetype":"venue"
},
  "geometry": {"coordinates":[-117.235669,32.86295],"type":"Point"}
}