{
  "type": "Feature",
  "properties": {
    "iso:country":"US",
    "sg:address":"1225 Saint Elizabeth Ct",
    "sg:city":"Concord",
    "sg:classifiers":[
        {
            "category":"Wholesale",
            "subcategory":"Sporting Goods",
            "type":"Manufacturing & Wholesale Goods"
        }
    ],
    "sg:phone":"+1 925 932 3017",
    "sg:postcode":"94518",
    "sg:province":"CA",
    "sg:tags":[
        "equipment",
        "billiard",
        "supply"
    ],
    "wof:name":"Ace Billard Svc",
    "wof:placetype":"venue"
},
  "geometry": {"coordinates":[-122.010686,37.963309],"type":"Point"}
}