{
  "type": "Feature",
  "properties": {
    "iso:country":"US",
    "sg:address":"7222 Owensmouth Ave",
    "sg:city":"Canoga Park",
    "sg:classifiers":[
        {
            "category":"Home & Garden",
            "subcategory":"Carpets & Floor Coverings",
            "type":"Retail Goods"
        }
    ],
    "sg:phone":"+1 818 884 4343",
    "sg:postcode":"91303",
    "sg:province":"CA",
    "sg:tags":[
        "dealer",
        "rug"
    ],
    "wof:name":"MD Carpet & Upholstery Clnng",
    "wof:placetype":"venue"
},
  "geometry": {"coordinates":[-118.601495,34.202435],"type":"Point"}
}