{
  "type": "Feature",
  "properties": {
    "addr:full":"3402 Cam Tassajara Danville CA 94506",
    "addr:housenumber":"3402",
    "addr:postcode":"94506",
    "addr:street":"Cam Tassajara",
    "iso:country":"US",
    "sg:address":"3402 Cam Tassajara",
    "sg:city":"Danville",
    "sg:classifiers":[
        {
            "category":"Banks & Credit Unions",
            "subcategory":"Bank",
            "type":"Services"
        }
    ],
    "sg:phone":"+1 925 736 3454",
    "sg:postcode":"94506",
    "sg:province":"CA",
    "wof:name":"Wells Fargo Bank",
    "wof:placetype":"venue"
},
  "geometry": {"coordinates":[-121.921826,37.799116],"type":"Point"}
}