{
  "type": "Feature",
  "properties": {
    "iso:country":"US",
    "sg:address":"417 Nevada St",
    "sg:city":"Vallejo",
    "sg:classifiers":[
        {
            "category":"Wholesale",
            "subcategory":"Sporting Goods",
            "type":"Manufacturing & Wholesale Goods"
        }
    ],
    "sg:phone":"+1 707 643 7509",
    "sg:postcode":"94590",
    "sg:province":"CA",
    "sg:tags":[
        "equipment",
        "billiard",
        "supply"
    ],
    "wof:name":"Right On Cue",
    "wof:placetype":"venue"
},
  "geometry": {"coordinates":[-122.24498699999999,38.117734],"type":"Point"}
}