{
  "type": "Feature",
  "properties": {
    "addr:full":"451 March Ave Healdsburg CA 95448",
    "addr:housenumber":"451",
    "addr:postcode":"95448",
    "addr:street":"March Ave",
    "iso:country":"US",
    "sg:address":"451 March Ave",
    "sg:city":"Healdsburg",
    "sg:classifiers":[
        {
            "category":"Health Services",
            "subcategory":"Doctor",
            "type":"Services"
        }
    ],
    "sg:phone":"+1 707 433 2120",
    "sg:postcode":"95448",
    "sg:province":"CA",
    "sg:tags":[
        "physician",
        "surgeon"
    ],
    "wof:name":"Mitchell E Bailey MD",
    "wof:placetype":"venue"
},
  "geometry": {"coordinates":[-122.86502900000001,38.625991],"type":"Point"}
}