{
  "type": "Feature",
  "properties": {
    "iso:country":"US",
    "sg:address":"12720 Rancho Penasquitos Blvd",
    "sg:city":"San Diego",
    "sg:classifiers":[
        {
            "category":"Building & Trades",
            "subcategory":"Cleaning & Sanitation",
            "type":"Services"
        }
    ],
    "sg:phone":"+1 858 693 7314",
    "sg:postcode":"92129",
    "sg:province":"CA",
    "sg:tags":[
        "window"
    ],
    "wof:name":"North County Window Cleaning",
    "wof:placetype":"venue"
},
  "geometry": {"coordinates":[-117.106086,32.948164],"type":"Point"}
}