{
  "type": "Feature",
  "properties": {
    "addr:full":"8217 Somerset Blvd Paramount CA 90723",
    "addr:housenumber":"8217",
    "addr:postcode":"90723",
    "addr:street":"Somerset Blvd",
    "iso:country":"US",
    "sg:address":"8217 Somerset Blvd",
    "sg:city":"Paramount",
    "sg:classifiers":[
        {
            "category":"Retail",
            "subcategory":"Auto Repair",
            "type":"Services"
        }
    ],
    "sg:phone":"+1 562 408 6638",
    "sg:postcode":"90723",
    "sg:province":"CA",
    "wof:name":"C & A Auto Repair",
    "wof:placetype":"venue"
},
  "geometry": {"coordinates":[-118.154999,33.896599],"type":"Point"}
}