{
  "type": "Feature",
  "properties": {
    "addr:full":"15852 Cherry Blossom Ln Los Gatos CA 95032",
    "addr:housenumber":"15852",
    "addr:postcode":"95032",
    "addr:street":"Cherry Blossom Ln",
    "iso:country":"US",
    "sg:address":"15852 Cherry Blossom Ln",
    "sg:city":"Los Gatos",
    "sg:classifiers":[
        {
            "category":"Manufacturing",
            "subcategory":"Tools & Machinery",
            "type":"Manufacturing & Wholesale Goods"
        }
    ],
    "sg:phone":"+1 408 356 3988",
    "sg:postcode":"95032",
    "sg:province":"CA",
    "sg:tags":[
        "industry",
        "merchandise",
        "mfg"
    ],
    "wof:name":"Wc Service Company Inc",
    "wof:placetype":"venue"
},
  "geometry": {"coordinates":[-121.957218,37.237955],"type":"Point"}
}