{
  "type": "Feature",
  "properties": {
    "addr:full":"24402 Hawthorne Blvd Torrance CA 90505",
    "addr:housenumber":"24402",
    "addr:postcode":"90505",
    "addr:street":"Hawthorne Blvd",
    "iso:country":"US",
    "sg:address":"24402 Hawthorne Blvd",
    "sg:city":"Torrance",
    "sg:classifiers":[
        {
            "category":"Health Services",
            "subcategory":"Clinic",
            "type":"Services"
        }
    ],
    "sg:phone":"+1 310 378 4866",
    "sg:postcode":"90505",
    "sg:province":"CA",
    "sg:tags":[
        "medical"
    ],
    "wof:name":"End Results Health & Wellness Center",
    "wof:placetype":"venue"
},
  "geometry": {"coordinates":[-118.35101299999999,33.801367],"type":"Point"}
}