{
  "type": "Feature",
  "properties": {
    "iso:country":"US",
    "sg:address":"1528 N Sierra Vista Ave",
    "sg:city":"Fresno",
    "sg:classifiers":[
        {
            "category":"Professional",
            "subcategory":"Advertising",
            "type":"Services"
        }
    ],
    "sg:phone":"+1 559 255 8273",
    "sg:postcode":"93703",
    "sg:province":"CA",
    "sg:tags":[
        "counselor"
    ],
    "sg:website":"www.ashfordworld.com",
    "wof:name":"Ashford Advertising Agency",
    "wof:placetype":"venue"
},
  "geometry": {"coordinates":[-119.740773,36.763909],"type":"Point"}
}