{
  "type": "Feature",
  "properties": {
    "iso:country":"US",
    "sg:address":"103 W Honolulu St",
    "sg:city":"Lindsay",
    "sg:classifiers":[
        {
            "category":"Travel",
            "subcategory":"Travel Agent",
            "type":"Entertainment"
        }
    ],
    "sg:phone":"+1 559 562 4200",
    "sg:postcode":"93247",
    "sg:province":"CA",
    "sg:tags":[
        "agency"
    ],
    "wof:name":"Turamerica",
    "wof:placetype":"venue"
},
  "geometry": {"coordinates":[-119.09010600000001,36.202634],"type":"Point"}
}