{
  "type": "Feature",
  "properties": {
    "iso:country":"US",
    "sg:address":"12843 S Highland Ave",
    "sg:city":"Selma",
    "sg:classifiers":[
        {
            "category":"Farming",
            "subcategory":"Vineyard",
            "type":"Manufacturing & Wholesale Goods"
        }
    ],
    "sg:phone":"+1 559 896 1092",
    "sg:postcode":"93662",
    "sg:province":"CA",
    "sg:tags":[
        "grape"
    ],
    "wof:name":"James H Zack",
    "wof:placetype":"venue"
},
  "geometry": {"coordinates":[-119.628793,36.553783],"type":"Point"}
}