{
  "type": "Feature",
  "properties": {
    "iso:country":"US",
    "sg:address":"1754 Technology Dr",
    "sg:city":"San Jose",
    "sg:classifiers":[
        {
            "category":"Professional",
            "subcategory":"Employment Agencies",
            "type":"Services"
        }
    ],
    "sg:phone":"+1 408 998 3322",
    "sg:postcode":"95110",
    "sg:province":"CA",
    "sg:tags":[
        "opportunity"
    ],
    "wof:name":"Delyse Nash & Assoc",
    "wof:placetype":"venue"
},
  "geometry": {"coordinates":[-121.919597,37.368846],"type":"Point"}
}