{
  "type": "Feature",
  "properties": {
    "addr:full":"23120 Alicia Pkwy Ste 200 Mission Viejo CA 92692",
    "addr:housenumber":"23120",
    "addr:postcode":"92692",
    "addr:street":"Alicia Pkwy Ste 200",
    "iso:country":"US",
    "sg:address":"23120 Alicia Pkwy Ste 200",
    "sg:city":"Mission Viejo",
    "sg:classifiers":[
        {
            "category":"Professional",
            "subcategory":"Lawyer & Legal Services",
            "type":"Services"
        }
    ],
    "sg:phone":"+1 949 837 9447",
    "sg:postcode":"92692",
    "sg:province":"CA",
    "wof:name":"Fagel Bruce MD Law Corp",
    "wof:placetype":"venue"
},
  "geometry": {"coordinates":[-117.635002,33.628601],"type":"Point"}
}