{
  "type": "Feature",
  "properties": {
    "iso:country":"US",
    "sg:address":"3491 Orange Grove Ave",
    "sg:city":"North Highlands",
    "sg:classifiers":[
        {
            "category":"Building & Trades",
            "subcategory":"Construction",
            "type":"Services"
        }
    ],
    "sg:phone":"+1 916 481 6293",
    "sg:postcode":"95660",
    "sg:province":"CA",
    "sg:tags":[
        "roofing",
        "contractor"
    ],
    "sg:website":"www.watsonroofing.com",
    "wof:name":"Watson Roofing Inc",
    "wof:placetype":"venue"
},
  "geometry": {"coordinates":[-121.387102,38.64666],"type":"Point"}
}