{
  "type": "Feature",
  "properties": {
    "addr:full":"6108 San Fernando Rd Glendale CA 91201",
    "addr:housenumber":"6108",
    "addr:postcode":"91201",
    "addr:street":"San Fernando Rd",
    "iso:country":"US",
    "sg:address":"6108 San Fernando Rd",
    "sg:city":"Glendale",
    "sg:classifiers":[
        {
            "category":"Professional",
            "subcategory":"Computer Services",
            "type":"Services"
        }
    ],
    "sg:phone":"+1 818 548 8600",
    "sg:postcode":"91201",
    "sg:province":"CA",
    "sg:tags":[
        "repair"
    ],
    "wof:name":"Vantage PC Inc",
    "wof:placetype":"venue"
},
  "geometry": {"coordinates":[-118.283923,34.162887],"type":"Point"}
}