{
  "type": "Feature",
  "properties": {
    "iso:country":"US",
    "sg:address":"1029 Heinz Avenue",
    "sg:city":"Berkeley",
    "sg:classifiers":[
        {
            "category":"Real Estate",
            "subcategory":"Architect",
            "type":"Services"
        }
    ],
    "sg:phone":"+1 510 845 6941",
    "sg:postcode":"94710",
    "sg:province":"CA",
    "sg:website":"www.levitch.com",
    "wof:name":"Levitch",
    "wof:placetype":"venue"
},
  "geometry": {"coordinates":[-122.288799,37.854368],"type":"Point"}
}