{
  "type": "Feature",
  "properties": {
    "iso:country":"US",
    "sg:address":"3248 Mary St",
    "sg:city":"Riverside",
    "sg:classifiers":[
        {
            "category":"Personal",
            "type":"Services"
        },
        {
            "category":"Retail",
            "subcategory":"Storage",
            "type":"Services"
        }
    ],
    "sg:phone":"+1 951 682 1999",
    "sg:postcode":"92506",
    "sg:province":"CA",
    "sg:tags":[
        "self",
        "full",
        "commercial",
        "mover",
        "household"
    ],
    "sg:website":"http://www.executiveselfstorage.com",
    "wof:name":"Mary Street Self Storage",
    "wof:placetype":"venue"
},
  "geometry": {"coordinates":[-117.392308,33.940388],"type":"Point"}
}