{
  "type": "Feature",
  "properties": {
    "sfgov:dept":"7",
    "sfgov:deptname":"SF Unified School District (SFUSD)",
    "sfgov:facility_i":"0000003131",
    "sfgov:school_typ":"Elementary",
    "wof:categories":[
        "education_and_religion:education=school"
    ],
    "wof:name":"Muir, John Elementary School",
    "wof:placetype":"venue"
},
  "geometry": {"coordinates":[-122.42878722381754,37.77372369630451],"type":"Point"}
}