{
  "type": "Feature",
  "properties": {
    "iso:country":"US",
    "sg:address":"8687 Melrose Ave",
    "sg:city":"Los Angeles",
    "sg:classifiers":[
        {
            "category":"Shopping",
            "type":"Retail Goods"
        }
    ],
    "sg:phone":"+1 310 652 0203",
    "sg:postcode":"90069",
    "sg:province":"CA",
    "sg:tags":[
        "art",
        "gallery",
        "dealer"
    ],
    "wof:name":"Dassin Gallery",
    "wof:placetype":"venue"
},
  "geometry": {"coordinates":[-118.383058,34.081384],"type":"Point"}
}