{
  "type": "Feature",
  "properties": {
    "addr:full":"2900 Rainbow Mountain Ranch Glencoe CA 95245",
    "addr:housenumber":"2900",
    "addr:postcode":"95245",
    "addr:street":"Rainbow Mountain",
    "iso:country":"US",
    "sg:address":"2900 Rainbow Mountain Ranch",
    "sg:city":"Glencoe",
    "sg:classifiers":[
        {
            "category":"Building & Trades",
            "subcategory":"Electrical",
            "type":"Services"
        }
    ],
    "sg:phone":"+1 209 293 7301",
    "sg:postcode":"95245",
    "sg:province":"CA",
    "sg:tags":[
        "electrical",
        "contractor"
    ],
    "wof:name":"Taylor Electric",
    "wof:placetype":"venue"
},
  "geometry": {"coordinates":[-120.574366,38.340395],"type":"Point"}
}