{
  "type": "Feature",
  "properties": {
    "addr:full":"375 3rd St Hollister CA 95023",
    "addr:housenumber":"375",
    "addr:postcode":"hollister ca 95023",
    "addr:street":"3Rd St",
    "iso:country":"US",
    "sg:address":"375 3rd St",
    "sg:city":"Hollister",
    "sg:classifiers":[
        {
            "category":"Personal",
            "subcategory":"Beauty Salon",
            "type":"Services"
        }
    ],
    "sg:phone":"+1 831 637 2010",
    "sg:postcode":"95023",
    "sg:province":"CA",
    "wof:name":"Dimensions Of Style",
    "wof:placetype":"venue"
},
  "geometry": {"coordinates":[-121.403373,36.853541],"type":"Point"}
}