{
  "type": "Feature",
  "properties": {
    "iso:country":"US",
    "sg:address":"200 Main St",
    "sg:city":"Huntington Beach",
    "sg:classifiers":[
        {
            "category":"Parking",
            "type":"Transportation"
        }
    ],
    "sg:postcode":"92648",
    "sg:province":"CA",
    "sg:website":"www.stockteam.com/garage.html",
    "wof:name":"Main Street Promenade Parking Garage",
    "wof:placetype":"venue"
},
  "geometry": {"coordinates":[-118.001077,33.658054],"type":"Point"}
}