{
  "type": "Feature",
  "properties": {
    "addr:full":"5067 Sutherland Dr Concord CA 94521",
    "addr:housenumber":"5067",
    "addr:postcode":"94521",
    "addr:street":"Sutherland Dr",
    "iso:country":"US",
    "sg:address":"5067 Sutherland Dr",
    "sg:city":"Concord",
    "sg:classifiers":[
        {
            "category":"Building & Trades",
            "subcategory":"Construction",
            "type":"Services"
        }
    ],
    "sg:phone":"+1 925 825 4111",
    "sg:postcode":"94521",
    "sg:province":"CA",
    "sg:tags":[
        "contractor"
    ],
    "wof:name":"Jackett Construction",
    "wof:placetype":"venue"
},
  "geometry": {"coordinates":[-121.968817,37.95867],"type":"Point"}
}