{
  "type": "Feature",
  "properties": {
    "addr:full":"12560 Laurel St Lakeside CA 92040",
    "addr:housenumber":"12560",
    "addr:postcode":"92040",
    "addr:street":"Laurel St",
    "iso:country":"US",
    "sg:address":"12560 Laurel St",
    "sg:city":"Lakeside",
    "sg:classifiers":[
        {
            "category":"Freight",
            "type":"Transportation"
        }
    ],
    "sg:phone":"+1 619 443 6403",
    "sg:postcode":"92040",
    "sg:province":"CA",
    "sg:tags":[
        "operator",
        "local",
        "trucking"
    ],
    "wof:name":"Three Sons Trucking",
    "wof:placetype":"venue"
},
  "geometry": {"coordinates":[-116.92114100000001,32.861608],"type":"Point"}
}