{
  "type": "Feature",
  "properties": {
    "iso:country":"US",
    "sg:address":"909 S Arrowhead Ave",
    "sg:city":"San Bernardino",
    "sg:classifiers":[
        {
            "category":"Home & Garden",
            "subcategory":"Carpets & Floor Coverings",
            "type":"Retail Goods"
        }
    ],
    "sg:phone":"+1 909 888 9732",
    "sg:postcode":"92408",
    "sg:province":"CA",
    "sg:tags":[
        "dealer",
        "rug"
    ],
    "wof:name":"Stafford's Discount Carpets",
    "wof:placetype":"venue"
},
  "geometry": {"coordinates":[-117.289592,34.082767],"type":"Point"}
}