{
  "type": "Feature",
  "properties": {
    "addr:full":"2935 Coronado Ave San Diego CA 92154",
    "addr:housenumber":"2935",
    "addr:postcode":"92154",
    "addr:street":"Coronado Ave",
    "iso:country":"US",
    "sg:address":"2935 Coronado Ave",
    "sg:city":"San Diego",
    "sg:classifiers":[
        {
            "category":"Insurance",
            "subcategory":"Insurance Agent",
            "type":"Services"
        }
    ],
    "sg:phone":"+1 619 429 1333",
    "sg:postcode":"92154",
    "sg:province":"CA",
    "wof:name":"Oasis Insurance Svc",
    "wof:placetype":"venue"
},
  "geometry": {"coordinates":[-117.070155,32.576367],"type":"Point"}
}