{
  "type": "Feature",
  "properties": {
    "iso:country":"US",
    "sg:address":"844 N Diamond Bar Blvd",
    "sg:city":"Diamond Bar",
    "sg:classifiers":[
        {
            "category":"Health Services",
            "subcategory":"Health Practitioner",
            "type":"Services"
        }
    ],
    "sg:phone":"+1 909 396 1009",
    "sg:postcode":"91765",
    "sg:province":"CA",
    "sg:tags":[
        "therapist",
        "physical"
    ],
    "wof:name":"Athletic Rehabilitation Ctr",
    "wof:placetype":"venue"
},
  "geometry": {"coordinates":[-117.80807799999999,34.033166],"type":"Point"}
}