{
  "type": "Feature",
  "properties": {
    "iso:country":"US",
    "sg:address":"12902 Foothill Blvd",
    "sg:city":"Sylmar",
    "sg:classifiers":[
        {
            "category":"Restaurant",
            "type":"Food & Drink"
        }
    ],
    "sg:phone":"+1 818 365 7444",
    "sg:postcode":"91342",
    "sg:province":"CA",
    "sg:tags":[
        "japanese",
        "lunch",
        "asian",
        "brunch",
        "breakfast",
        "pan"
    ],
    "sg:website":"http://yoshinoyaamerica.com/",
    "wof:name":"Yoshinoya",
    "wof:placetype":"venue"
},
  "geometry": {"coordinates":[-118.416234,34.294476],"type":"Point"}
}