{
  "type": "Feature",
  "properties": {
    "iso:country":"US",
    "sg:address":"ArtWorks Studio 660 N Larchmont Blvd",
    "sg:city":"Los Angeles",
    "sg:classifiers":[
        {
            "category":"Arts & Performance",
            "subcategory":"Art Gallery",
            "type":"Entertainment"
        }
    ],
    "sg:phone":"+1 323 463 2562",
    "sg:postcode":"90004",
    "sg:province":"CA",
    "sg:website":"www.drawingparty.com",
    "wof:name":"Drawing Party",
    "wof:placetype":"venue"
},
  "geometry": {"coordinates":[-118.323652,34.083173],"type":"Point"}
}