{
  "type": "Feature",
  "properties": {
    "addr:full":"75 S Gay St Susanville CA 96130",
    "addr:housenumber":"75",
    "addr:postcode":"96130",
    "addr:street":"S Gay St",
    "iso:country":"US",
    "sg:address":"75 S Gay St",
    "sg:city":"Susanville",
    "sg:classifiers":[
        {
            "category":"Professional",
            "subcategory":"Lawyer & Legal Services",
            "type":"Services"
        }
    ],
    "sg:phone":"+1 530 257 6013",
    "sg:postcode":"96130",
    "sg:province":"CA",
    "sg:tags":[
        "attorney"
    ],
    "wof:name":"Oretsky & Gay",
    "wof:placetype":"venue"
},
  "geometry": {"coordinates":[-120.66076200000001,40.417529],"type":"Point"}
}