{
  "type": "Feature",
  "properties": {
    "iso:country":"US",
    "sg:address":"18123 Pine St",
    "sg:city":"Hesperia",
    "sg:classifiers":[
        {
            "category":"Freight",
            "type":"Transportation"
        }
    ],
    "sg:phone":"+1 760 956 7587",
    "sg:postcode":"92345",
    "sg:province":"CA",
    "sg:tags":[
        "operator",
        "trucking"
    ],
    "wof:name":"All Greene Express",
    "wof:placetype":"venue"
},
  "geometry": {"coordinates":[-117.268128,34.42232],"type":"Point"}
}