{
  "type": "Feature",
  "properties": {
    "addr:full":"1200 S Harbor Blvd Ste 204 Anaheim CA 92805",
    "addr:housenumber":"1200",
    "addr:postcode":"92805",
    "addr:street":"S Harbor Blvd Ste 204",
    "iso:country":"US",
    "sg:address":"1200 S Harbor Blvd Ste 204",
    "sg:city":"Anaheim",
    "sg:classifiers":[
        {
            "category":"Travel",
            "subcategory":"Travel Agent",
            "type":"Entertainment"
        }
    ],
    "sg:phone":"+1 888 451 2974",
    "sg:postcode":"92805",
    "sg:province":"CA",
    "sg:website":"cheapvacationforyou.com/",
    "wof:name":"Cheap Vacation For You",
    "wof:placetype":"venue"
},
  "geometry": {"coordinates":[-117.91482499999999,33.817582],"type":"Point"}
}