{
  "type": "Feature",
  "properties": {
    "addr:full":"103 Stockton Ave Capitola CA 95010",
    "addr:housenumber":"103",
    "addr:postcode":"95010",
    "addr:street":"Stockton Ave",
    "iso:country":"US",
    "sg:address":"103 Stockton Ave",
    "sg:city":"Capitola",
    "sg:classifiers":[
        {
            "category":"Manufacturing",
            "subcategory":"Food",
            "type":"Manufacturing & Wholesale Goods"
        }
    ],
    "sg:phone":"+1 831 462 1065",
    "sg:postcode":"95010",
    "sg:province":"CA",
    "sg:tags":[
        "winery",
        "mfg"
    ],
    "wof:name":"Armida Winery",
    "wof:placetype":"venue"
},
  "geometry": {"coordinates":[-121.953003,36.972599],"type":"Point"}
}