{
  "type": "Feature",
  "properties": {
    "addr:full":"4950 Barranca Pkwy Ste 105 Irvine CA 92604",
    "addr:housenumber":"4950",
    "addr:postcode":"92604",
    "addr:street":"Barranca Pkwy Ste 105",
    "iso:country":"US",
    "sg:address":"4950 Barranca Pkwy Ste 105",
    "sg:city":"Irvine",
    "sg:classifiers":[
        {
            "category":"Health Services",
            "subcategory":"Dentist",
            "type":"Services"
        }
    ],
    "sg:phone":"+1 949 551 4242",
    "sg:postcode":"92604",
    "sg:province":"CA",
    "wof:name":"Gentle Dental",
    "wof:placetype":"venue"
},
  "geometry": {"coordinates":[-117.794228,33.676208],"type":"Point"}
}