{
  "type": "Feature",
  "properties": {
    "addr:full":"219 Ofarrell St San Francisco CA 94102",
    "addr:housenumber":"219",
    "addr:postcode":"94102",
    "addr:street":"Ofarrell St",
    "iso:country":"US",
    "sg:address":"219 Ofarrell St",
    "sg:city":"San Francisco",
    "sg:classifiers":[
        {
            "category":"Restaurant",
            "type":"Food & Drink"
        }
    ],
    "sg:menulink":"http://www.allmenus.com/ca/san-francisco/46137-dojima-ann/menu/",
    "sg:phone":"+1 415 986 2129",
    "sg:postcode":"94102",
    "sg:province":"CA",
    "sg:tags":[
        "sushi",
        "asian"
    ],
    "wof:name":"Dojima Ann",
    "wof:placetype":"venue"
},
  "geometry": {"coordinates":[-122.408429,37.786406],"type":"Point"}
}