{
  "type": "Feature",
  "properties": {
    "iso:country":"US",
    "sg:address":"3720 Stephen M White Dr",
    "sg:city":"San Pedro",
    "sg:classifiers":[
        {
            "category":"Museum",
            "subcategory":"Botanical Garden",
            "type":"Entertainment"
        }
    ],
    "sg:phone":"+1 310 548 7563",
    "sg:postcode":"90731",
    "sg:province":"CA",
    "wof:name":"Parks & Recreation Dept",
    "wof:placetype":"venue"
},
  "geometry": {"coordinates":[-118.285442,33.70875],"type":"Point"}
}