{
  "type": "Feature",
  "properties": {
    "addr:full":"3271 Lakeshore Ave Oakland CA 94610",
    "addr:housenumber":"3271",
    "addr:postcode":"94610",
    "addr:street":"Lakeshore Ave",
    "iso:country":"US",
    "sg:address":"3271 Lakeshore Ave",
    "sg:city":"Oakland",
    "sg:classifiers":[
        {
            "category":"Restaurant",
            "type":"Food & Drink"
        }
    ],
    "sg:phone":"+1 510 452 3610",
    "sg:postcode":"94610",
    "sg:province":"CA",
    "wof:name":"ABC Food Express",
    "wof:placetype":"venue"
},
  "geometry": {"coordinates":[-122.24400300000001,37.810799],"type":"Point"}
}