{
  "type": "Feature",
  "properties": {
    "iso:country":"US",
    "sg:address":"2636 Shelter Island Dr",
    "sg:city":"San Diego",
    "sg:classifiers":[
        {
            "category":"Autos & Motor Vehicles",
            "subcategory":"Boat Sales",
            "type":"Retail Goods"
        }
    ],
    "sg:phone":"+1 619 223 7159",
    "sg:postcode":"92106",
    "sg:province":"CA",
    "sg:tags":[
        "equipment",
        "marine",
        "supply"
    ],
    "sg:website":"www.sandiegomarine.com",
    "wof:name":"San Diego Marine Exchange",
    "wof:placetype":"venue"
},
  "geometry": {"coordinates":[-117.22895200000001,32.721353],"type":"Point"}
}