{
  "type": "Feature",
  "properties": {
    "iso:country":"US",
    "sg:address":"706 W California Ave",
    "sg:city":"Fresno",
    "sg:classifiers":[
        {
            "category":"Manufacturing",
            "subcategory":"Metals",
            "type":"Manufacturing & Wholesale Goods"
        }
    ],
    "sg:phone":"+1 559 268 6281",
    "sg:postcode":"93706",
    "sg:province":"CA",
    "sg:tags":[
        "steel"
    ],
    "wof:name":"Suburban Steel Inc",
    "wof:placetype":"venue"
},
  "geometry": {"coordinates":[-119.820712,36.721393],"type":"Point"}
}