{
  "type": "Feature",
  "properties": {
    "iso:country":"US",
    "sg:address":"1241 N el Dorado St",
    "sg:city":"Stockton",
    "sg:classifiers":[
        {
            "category":"Autos & Motor Vehicles",
            "subcategory":"Automobile Sales",
            "type":"Retail Goods"
        }
    ],
    "sg:phone":"+1 209 465 7376",
    "sg:postcode":"95202",
    "sg:province":"CA",
    "sg:tags":[
        "car",
        "dealer"
    ],
    "wof:name":"Buckenham Buckenhams Auto Sls",
    "wof:placetype":"venue"
},
  "geometry": {"coordinates":[-121.29326399999999,37.965113],"type":"Point"}
}