{
  "type": "Feature",
  "properties": {
    "iso:country":"US",
    "sg:address":"2160 Meyers Ave",
    "sg:city":"Escondido",
    "sg:classifiers":[
        {
            "category":"Wholesale",
            "subcategory":"Electrical",
            "type":"Manufacturing & Wholesale Goods"
        }
    ],
    "sg:phone":"+1 760 747 2900",
    "sg:postcode":"92029",
    "sg:province":"CA",
    "sg:tags":[
        "supply"
    ],
    "wof:name":"C E D Escondido",
    "wof:placetype":"venue"
},
  "geometry": {"coordinates":[-117.125089,33.129286],"type":"Point"}
}