{
  "type": "Feature",
  "properties": {
    "iso:country":"US",
    "sg:address":"13351 Cumpston St",
    "sg:city":"Van Nuys",
    "sg:classifiers":[
        {
            "category":"Professional",
            "type":"Services"
        }
    ],
    "sg:phone":"+1 818 787 9799",
    "sg:postcode":"91401",
    "sg:province":"CA",
    "wof:name":"Julie A Goren",
    "wof:placetype":"venue"
},
  "geometry": {"coordinates":[-118.42509200000001,34.169569],"type":"Point"}
}