{
  "type": "Feature",
  "properties": {
    "iso:country":"US",
    "sg:address":"91 Colma Blvd",
    "sg:city":"Daly City",
    "sg:classifiers":[
        {
            "category":"Wholesale",
            "subcategory":"Machinery & Supplies",
            "type":"Manufacturing & Wholesale Goods"
        }
    ],
    "sg:phone":"+1 800 879 8000",
    "sg:postcode":"94014",
    "sg:province":"CA",
    "sg:tags":[
        "fastening",
        "fastener",
        "system",
        "tool",
        "sales"
    ],
    "wof:name":"Colma Home Depot Pro Shop",
    "wof:placetype":"venue"
},
  "geometry": {"coordinates":[-122.466416,37.676934],"type":"Point"}
}