{
  "type": "Feature",
  "properties": {
    "addr:full":"3889 Crenshaw Blvd Los Angeles CA 90008",
    "addr:housenumber":"3889",
    "addr:postcode":"90008",
    "addr:street":"Crenshaw Blvd",
    "iso:country":"US",
    "sg:address":"3889 Crenshaw Blvd",
    "sg:city":"Los Angeles",
    "sg:classifiers":[
        {
            "category":"Shopping",
            "subcategory":"Florist",
            "type":"Retail Goods"
        }
    ],
    "sg:phone":"+1 323 293 4542",
    "sg:postcode":"90008",
    "sg:province":"CA",
    "wof:name":"Angelus Florist",
    "wof:placetype":"venue"
},
  "geometry": {"coordinates":[-118.334957,34.016161],"type":"Point"}
}