{
  "type": "Feature",
  "properties": {
    "iso:country":"US",
    "sg:address":"13710 Carmenita Rd",
    "sg:city":"Santa Fe Springs",
    "sg:classifiers":[
        {
            "category":"Autos & Motor Vehicles",
            "subcategory":"Auto Supplies",
            "type":"Retail Goods"
        }
    ],
    "sg:phone":"+1 562 802 3400",
    "sg:postcode":"90670",
    "sg:province":"CA",
    "sg:tags":[
        "filter",
        "gas"
    ],
    "wof:name":"Calgon Carbon",
    "wof:placetype":"venue"
},
  "geometry": {"coordinates":[-118.046575,33.90613],"type":"Point"}
}