{
  "type": "Feature",
  "properties": {
    "iso:country":"US",
    "sg:address":"1428 Paulette Ave",
    "sg:city":"Modesto",
    "sg:classifiers":[
        {
            "category":"Shopping",
            "subcategory":"Bicycles & Sporting Goods",
            "type":"Retail Goods"
        }
    ],
    "sg:phone":"+1 209 526 3884",
    "sg:postcode":"95355",
    "sg:province":"CA",
    "wof:name":"Gebco Firearms",
    "wof:placetype":"venue"
},
  "geometry": {"coordinates":[-120.968567,37.66505],"type":"Point"}
}