{
  "type": "Feature",
  "properties": {
    "addr:full":"1428 Paulette Ave Modesto CA 95355",
    "addr:housenumber":"1428",
    "addr:postcode":"ca 95355",
    "addr:street":"Paulette Ave",
    "iso:country":"US",
    "sg:address":"1428 Paulette Ave",
    "sg:city":"Modesto",
    "sg:classifiers":[
        {
            "category":"Shopping",
            "subcategory":"Bicycles & Sporting Goods",
            "type":"Retail Goods"
        }
    ],
    "sg:phone":"+1 209 526 3884",
    "sg:postcode":"95355",
    "sg:province":"CA",
    "wof:name":"Gebco Firearms",
    "wof:placetype":"venue"
},
  "geometry": {"coordinates":[-120.96856699999999,37.66505],"type":"Point"}
}