{
  "type": "Feature",
  "properties": {
    "iso:country":"US",
    "sg:address":"3314 K St",
    "sg:city":"Eureka",
    "sg:classifiers":[
        {
            "category":"Building & Trades",
            "subcategory":"Cleaning & Sanitation",
            "type":"Services"
        }
    ],
    "sg:phone":"+1 707 443 1373",
    "sg:postcode":"95503",
    "sg:province":"CA",
    "sg:tags":[
        "janitor"
    ],
    "wof:name":"Ken Voss Maintenance",
    "wof:placetype":"venue"
},
  "geometry": {"coordinates":[-124.157941,40.778511],"type":"Point"}
}