{
  "type": "Feature",
  "properties": {
    "addr:full":"18207 Santa Cecilia Fountain Valley CA 92708",
    "addr:housenumber":"18207",
    "addr:postcode":"92708",
    "addr:street":"Santa Cecilia",
    "iso:country":"US",
    "sg:address":"18207 Santa Cecilia",
    "sg:city":"Fountain Valley",
    "sg:classifiers":[
        {
            "category":"Wholesale",
            "subcategory":"Apparel",
            "type":"Manufacturing & Wholesale Goods"
        }
    ],
    "sg:phone":"+1 714 856 5383",
    "sg:postcode":"92708",
    "sg:province":"CA",
    "sg:tags":[
        "clothing"
    ],
    "wof:name":"Lennox Worldwide",
    "wof:placetype":"venue"
},
  "geometry": {"coordinates":[-117.974805,33.698325],"type":"Point"}
}