{
  "type": "Feature",
  "properties": {
    "iso:country":"US",
    "sg:address":"7351 Variel St Ste 3",
    "sg:city":"San Fernando Valley",
    "sg:classifiers":[
        {
            "category":"Home & Garden",
            "subcategory":"Household Appliances",
            "type":"Retail Goods"
        },
        {
            "category":"Building & Trades",
            "subcategory":"Construction",
            "type":"Services"
        }
    ],
    "sg:phone":"+1 818 934 9669",
    "sg:postcode":"91303",
    "sg:province":"CA",
    "sg:tags":[
        "repair",
        "conditioning/hvac",
        "heating",
        "air"
    ],
    "sg:website":"www.TheButterflyServices.com",
    "wof:name":"Butterfly Services",
    "wof:placetype":"venue"
},
  "geometry": {"coordinates":[-118.59325800000001,34.204314],"type":"Point"}
}