{
  "type": "Feature",
  "properties": {
    "addr:full":"82 N Main St Angels Camp CA 95222",
    "addr:housenumber":"82",
    "addr:postcode":"95222",
    "addr:street":"N Main St",
    "iso:country":"US",
    "sg:address":"82 N Main St",
    "sg:city":"Angels Camp",
    "sg:classifiers":[
        {
            "category":"Shopping",
            "subcategory":"Florist",
            "type":"Retail Goods"
        }
    ],
    "sg:phone":"+1 209 736 6771",
    "sg:postcode":"95222",
    "sg:province":"CA",
    "wof:name":"Blooms & Things Florist",
    "wof:placetype":"venue"
},
  "geometry": {"coordinates":[-120.561345,38.084278],"type":"Point"}
}