{
  "type": "Feature",
  "properties": {
    "iso:country":"US",
    "sg:address":"664 S Santa Fe Ave",
    "sg:city":"Los Angeles",
    "sg:classifiers":[
        {
            "category":"Wholesale",
            "subcategory":"Groceries",
            "type":"Manufacturing & Wholesale Goods"
        }
    ],
    "sg:phone":"+1 213 622 7348",
    "sg:postcode":"90021",
    "sg:province":"CA",
    "wof:name":"Hs Traders",
    "wof:placetype":"venue"
},
  "geometry": {"coordinates":[-118.23005999999999,34.035103],"type":"Point"}
}