{
  "type": "Feature",
  "properties": {
    "iso:country":"US",
    "sg:address":"3144 W Olympic Boulevard",
    "sg:city":"Los Angeles",
    "sg:classifiers":[
        {
            "category":"Shopping",
            "subcategory":"Jewelry",
            "type":"Retail Goods"
        }
    ],
    "sg:phone":"+1 323 735 9147",
    "sg:postcode":"90006",
    "sg:province":"CA",
    "wof:name":"Bogosa Company",
    "wof:placetype":"venue"
},
  "geometry": {"coordinates":[-118.304802,34.052708],"type":"Point"}
}