{
  "type": "Feature",
  "properties": {
    "iso:country":"US",
    "sg:address":"2026 Agnew Rd",
    "sg:city":"Santa Clara",
    "sg:classifiers":[
        {
            "category":"Fast Food",
            "type":"Food & Drink"
        },
        {
            "category":"Restaurant",
            "type":"Food & Drink"
        }
    ],
    "sg:phone":"+1 408 748 9110",
    "sg:postcode":"95054",
    "sg:province":"CA",
    "sg:tags":[
        "filipino"
    ],
    "wof:name":"Aling Elenas",
    "wof:placetype":"venue"
},
  "geometry": {"coordinates":[-121.959,37.394798],"type":"Point"}
}