{
  "type": "Feature",
  "properties": {
    "iso:country":"US",
    "sg:address":"23595 Moulton Pkwy Ste J",
    "sg:city":"Laguna Hills",
    "sg:classifiers":[
        {
            "category":"Shopping",
            "subcategory":"Clothing, Apparel, & Fashions",
            "type":"Retail Goods"
        }
    ],
    "sg:phone":"+1 949 206 1310",
    "sg:postcode":"92653",
    "sg:province":"CA",
    "sg:tags":[
        "accessory",
        "clothing",
        "women's"
    ],
    "wof:name":"Draper's & Damon's Outlet",
    "wof:placetype":"venue"
},
  "geometry": {"coordinates":[-117.73200199999999,33.619999],"type":"Point"}
}