{
  "type": "Feature",
  "properties": {
    "addr:full":"22500 Barone Rd Volcano CA 95689",
    "addr:postcode":"22500;95689",
    "addr:street":"Barone Rd",
    "iso:country":"US",
    "sg:address":"22500 Barone Rd",
    "sg:city":"Volcano",
    "sg:classifiers":[
        {
            "category":"Travel",
            "subcategory":"Campground",
            "type":"Entertainment"
        }
    ],
    "sg:phone":"+1 209 296 4632",
    "sg:postcode":"95689",
    "sg:province":"CA",
    "sg:tags":[
        "camp"
    ],
    "wof:name":"Golden Valley Camp",
    "wof:placetype":"venue"
},
  "geometry": {"coordinates":[-120.61194399999999,38.464381],"type":"Point"}
}