{
  "type": "Feature",
  "properties": {
    "addr:full":"14240 Hawthorne Boulevard Hawthorne CA 90250",
    "addr:housenumber":"14240",
    "addr:postcode":"90250",
    "addr:street":"Hawthorne Boulevard",
    "iso:country":"US",
    "sg:address":"14240 Hawthorne Boulevard",
    "sg:city":"Hawthorne",
    "sg:classifiers":[
        {
            "category":"Food & Beverages",
            "subcategory":"Groceries & Convenience Stores",
            "type":"Retail Goods"
        }
    ],
    "sg:phone":"+1 310 675 8610",
    "sg:postcode":"90250",
    "sg:province":"CA",
    "wof:name":"7-Eleven Food Stores",
    "wof:placetype":"venue"
},
  "geometry": {"coordinates":[-118.352475,33.9027],"type":"Point"}
}