{
  "type": "Feature",
  "properties": {
    "iso:country":"US",
    "sg:address":"1329 E 28th St",
    "sg:city":"Signal Hill",
    "sg:classifiers":[
        {
            "category":"Manufacturing",
            "subcategory":"Tools & Machinery",
            "type":"Manufacturing & Wholesale Goods"
        }
    ],
    "sg:phone":"+1 562 427 9633",
    "sg:postcode":"90755",
    "sg:province":"CA",
    "sg:tags":[
        "machine"
    ],
    "wof:name":"Unisource Automation",
    "wof:placetype":"venue"
},
  "geometry": {"coordinates":[-118.175788,33.808099],"type":"Point"}
}