{
  "type": "Feature",
  "properties": {
    "addr:full":"105 Cajon St Redlands CA 92373",
    "addr:housenumber":"105",
    "addr:postcode":"92373",
    "addr:street":"Cajon St",
    "iso:country":"US",
    "sg:address":"105 Cajon St",
    "sg:city":"Redlands",
    "sg:classifiers":[
        {
            "category":"Professional",
            "subcategory":"Business Services",
            "type":"Services"
        }
    ],
    "sg:phone":"+1 909 266 9694",
    "sg:postcode":"92373",
    "sg:province":"CA",
    "sg:tags":[
        "auctioneer"
    ],
    "wof:name":"Quicklist",
    "wof:placetype":"venue"
},
  "geometry": {"coordinates":[-117.181969,34.054434],"type":"Point"}
}