{
  "type": "Feature",
  "properties": {
    "addr:full":"1880 W Carson St Torrance CA 90501",
    "addr:housenumber":"1880",
    "addr:postcode":"90501",
    "addr:street":"W Carson St",
    "iso:country":"US",
    "sg:address":"1880 W Carson St",
    "sg:city":"Torrance",
    "sg:classifiers":[
        {
            "category":"Personal",
            "subcategory":"Beauty Salon",
            "type":"Services"
        }
    ],
    "sg:phone":"+1 310 320 1309",
    "sg:postcode":"90501",
    "sg:province":"CA",
    "wof:name":"Hair Fitness",
    "wof:placetype":"venue"
},
  "geometry": {"coordinates":[-118.31399399999999,33.831429],"type":"Point"}
}