{
  "type": "Feature",
  "properties": {
    "addr:full":"2475 Pine Valley Gln Escondido CA 92026",
    "addr:housenumber":"2475",
    "addr:postcode":"92026",
    "addr:street":"Pine Valley Gln",
    "iso:country":"US",
    "sg:address":"2475 Pine Valley Gln",
    "sg:city":"Escondido",
    "sg:classifiers":[
        {
            "category":"Building & Trades",
            "subcategory":"Construction",
            "type":"Services"
        }
    ],
    "sg:phone":"+1 760 432 9223",
    "sg:postcode":"92026",
    "sg:province":"CA",
    "sg:tags":[
        "house"
    ],
    "wof:name":"Brookside Design Center",
    "wof:placetype":"venue"
},
  "geometry": {"coordinates":[-117.08786600000001,33.16251],"type":"Point"}
}