{
  "type": "Feature",
  "properties": {
    "addr:full":"631 Buena Vista Ave Alameda CA 94501",
    "addr:housenumber":"631",
    "addr:postcode":"94501",
    "addr:street":"Buena Vista Ave",
    "iso:country":"US",
    "sg:address":"631 Buena Vista Ave",
    "sg:city":"Alameda",
    "sg:classifiers":[
        {
            "category":"Professional",
            "type":"Services"
        },
        {
            "category":"Retail",
            "subcategory":"Auto Rental",
            "type":"Services"
        },
        {
            "category":"Building & Trades",
            "subcategory":"Equipment Rental",
            "type":"Services"
        },
        {
            "category":"Retail",
            "subcategory":"Storage",
            "type":"Services"
        }
    ],
    "sg:phone":"+1 866 205 7339",
    "sg:postcode":"94501",
    "sg:province":"CA",
    "sg:tags":[
        "renting",
        "moving-self",
        "leasing",
        "material",
        "moving",
        "services-labor",
        "truck",
        "trailer"
    ],
    "sg:website":"http://www.pensketruckrental.com/personal_rental/?cid=Yptmlist",
    "wof:name":"Penske Truck Rental",
    "wof:placetype":"venue"
},
  "geometry": {"coordinates":[-122.278282,37.777287],"type":"Point"}
}