{
  "type": "Feature",
  "properties": {
    "iso:country":"US",
    "sg:address":"3411 Tweedy Boulevard",
    "sg:city":"South Gate",
    "sg:classifiers":[
        {
            "category":"Shopping",
            "subcategory":"Mobile Phones",
            "type":"Retail Goods"
        }
    ],
    "sg:phone":"+1 323 563 8824",
    "sg:postcode":"90280",
    "sg:province":"CA",
    "wof:name":"Digital Communications",
    "wof:placetype":"venue"
},
  "geometry": {"coordinates":[-118.209514,33.944644],"type":"Point"}
}