{
  "type": "Feature",
  "properties": {
    "addr:full":"5264 E Beverly Blvd Los Angeles CA 90022",
    "addr:housenumber":"5264",
    "addr:postcode":"90022",
    "addr:street":"E Beverly Blvd",
    "iso:country":"US",
    "sg:address":"5264 E Beverly Blvd",
    "sg:city":"Los Angeles",
    "sg:classifiers":[
        {
            "category":"Government",
            "subcategory":"Office",
            "type":"Public Place"
        }
    ],
    "sg:phone":"+1 323 881 4601",
    "sg:postcode":"90022",
    "sg:province":"CA",
    "sg:website":"www.lacounty.info",
    "wof:name":"Los Angeles Cnty Supervisors",
    "wof:placetype":"venue"
},
  "geometry": {"coordinates":[-118.153082,34.031721],"type":"Point"}
}