{
  "type": "Feature",
  "properties": {
    "addr:full":"17210 Slover Ave Fontana CA 92337",
    "addr:housenumber":"17210",
    "addr:postcode":"92337",
    "addr:street":"Slover Ave",
    "iso:country":"US",
    "sg:address":"17210 Slover Ave",
    "sg:city":"Fontana",
    "sg:classifiers":[
        {
            "category":"Social Services",
            "subcategory":"Child Care",
            "type":"Services"
        }
    ],
    "sg:phone":"+1 909 428 0335",
    "sg:postcode":"92337",
    "sg:province":"CA",
    "sg:tags":[
        "kindergarten",
        "academic",
        "school"
    ],
    "wof:name":"Sierra Academy Child Care Ctr",
    "wof:placetype":"venue"
},
  "geometry": {"coordinates":[-117.43108700000001,34.063114],"type":"Point"}
}