{
  "type": "Feature",
  "properties": {
    "addr:full":"9340 Hazard Way San Diego CA 92123",
    "addr:housenumber":"9340",
    "addr:postcode":"92123",
    "addr:street":"Hazard Way",
    "iso:country":"US",
    "sg:address":"9340 Hazard Way",
    "sg:city":"San Diego",
    "sg:classifiers":[
        {
            "category":"Professional",
            "subcategory":"Engineering",
            "type":"Services"
        }
    ],
    "sg:phone":"+1 858 751 0450",
    "sg:postcode":"92123",
    "sg:province":"CA",
    "sg:tags":[
        "engineer"
    ],
    "wof:name":"San Diego Composites",
    "wof:placetype":"venue"
},
  "geometry": {"coordinates":[-117.127275,32.83575],"type":"Point"}
}