{
  "type": "Feature",
  "properties": {
    "iso:country":"US",
    "sg:address":"9375 Ruffin Ct",
    "sg:city":"San Diego",
    "sg:classifiers":[
        {
            "category":"Manufacturing",
            "subcategory":"Tools & Machinery",
            "type":"Manufacturing & Wholesale Goods"
        }
    ],
    "sg:phone":"+1 858 499 0379",
    "sg:postcode":"92123",
    "sg:province":"CA",
    "sg:tags":[
        "industrial",
        "sheet",
        "metalwork",
        "mfg"
    ],
    "sg:website":"www.sdpm.com",
    "wof:name":"San Diego Precision Machining",
    "wof:placetype":"venue"
},
  "geometry": {"coordinates":[-117.123594,32.828644],"type":"Point"}
}