{
  "type": "Feature",
  "properties": {
    "addr:full":"5321 Saint Andrews Dr Stockton CA 95219",
    "addr:housenumber":"5321",
    "addr:postcode":"95219",
    "addr:street":"Saint Andrews Dr",
    "iso:country":"US",
    "sg:address":"5321 Saint Andrews Dr",
    "sg:city":"Stockton",
    "sg:classifiers":[
        {
            "category":"Wholesale",
            "subcategory":"Office Equipment",
            "type":"Manufacturing & Wholesale Goods"
        }
    ],
    "sg:phone":"+1 209 474 9987",
    "sg:postcode":"95219",
    "sg:province":"CA",
    "sg:tags":[
        "credit",
        "system",
        "card"
    ],
    "wof:name":"Chextronic",
    "wof:placetype":"venue"
},
  "geometry": {"coordinates":[-121.367446,37.968193],"type":"Point"}
}