{
  "type": "Feature",
  "properties": {
    "iso:country":"US",
    "sg:address":"1260 N Harvard Ave",
    "sg:city":"Claremont",
    "sg:classifiers":[
        {
            "category":"Personal",
            "subcategory":"Beauty Salon",
            "type":"Services"
        }
    ],
    "sg:phone":"+1 909 626 1868",
    "sg:postcode":"91711",
    "sg:province":"CA",
    "sg:tags":[
        "treatment",
        "skin"
    ],
    "wof:name":"Esthetic Facial Skin Care",
    "wof:placetype":"venue"
},
  "geometry": {"coordinates":[-117.716615,34.106009],"type":"Point"}
}