{
  "type": "Feature",
  "properties": {
    "iso:country":"US",
    "sg:address":"27576 Commerce Center Dr",
    "sg:city":"Temecula",
    "sg:classifiers":[
        {
            "category":"Manufacturing",
            "subcategory":"Tools & Machinery",
            "type":"Manufacturing & Wholesale Goods"
        }
    ],
    "sg:phone":"+1 951 587 6690",
    "sg:postcode":"92590",
    "sg:province":"CA",
    "sg:tags":[
        "die",
        "cutting"
    ],
    "wof:name":"Express Die Cutting",
    "wof:placetype":"venue"
},
  "geometry": {"coordinates":[-117.160511,33.511642],"type":"Point"}
}