{
  "type": "Feature",
  "properties": {
    "iso:country":"US",
    "sg:address":"5 Madrone Ave",
    "sg:city":"Oroville",
    "sg:classifiers":[
        {
            "category":"Real Estate",
            "subcategory":"Developer",
            "type":"Services"
        }
    ],
    "sg:phone":"+1 530 321 6118",
    "sg:postcode":"95966",
    "sg:province":"CA",
    "wof:name":"Development Services LTD",
    "wof:placetype":"venue"
},
  "geometry": {"coordinates":[-121.541411,39.510022],"type":"Point"}
}