{
  "type": "Feature",
  "properties": {
    "addr:full":"3540 Wilshire Blvd Los Angeles CA 90010",
    "addr:housenumber":"3540",
    "addr:postcode":"90010",
    "addr:street":"Wilshire Blvd",
    "iso:country":"US",
    "sg:address":"3540 Wilshire Blvd",
    "sg:city":"Los Angeles",
    "sg:classifiers":[
        {
            "category":"Professional",
            "subcategory":"Accounting & Tax Preparation",
            "type":"Services"
        }
    ],
    "sg:phone":"+1 213 387 7291",
    "sg:postcode":"90010",
    "sg:province":"CA",
    "sg:tags":[
        "accountant"
    ],
    "sg:website":"www.balbinco.com",
    "wof:name":"Balbin & Co",
    "wof:placetype":"venue"
},
  "geometry": {"coordinates":[-118.301928,34.061659],"type":"Point"}
}