{
  "type": "Feature",
  "properties": {
    "addr:full":"546 W Las Tunas Dr San Gabriel CA 91776",
    "addr:housenumber":"546",
    "addr:postcode":"91776",
    "addr:street":"W Las Tunas Dr",
    "iso:country":"US",
    "sg:address":"546 W Las Tunas Dr",
    "sg:city":"San Gabriel",
    "sg:classifiers":[
        {
            "category":"Shopping",
            "subcategory":"Florist",
            "type":"Retail Goods"
        }
    ],
    "sg:phone":"+1 626 308 3700",
    "sg:postcode":"91776",
    "sg:province":"CA",
    "wof:name":"Corianne's Flowers & Gifts",
    "wof:placetype":"venue"
},
  "geometry": {"coordinates":[-118.108002,34.1026],"type":"Point"}
}