{
  "type": "Feature",
  "properties": {
    "addr:full":"14450 Culver Dr Ste C Irvine CA 92604",
    "addr:housenumber":"14450",
    "addr:postcode":"92604",
    "addr:street":"Culver Dr Ste C",
    "iso:country":"US",
    "sg:address":"14450 Culver Dr Ste C",
    "sg:city":"Irvine",
    "sg:classifiers":[
        {
            "category":"Restaurant",
            "type":"Food & Drink"
        }
    ],
    "sg:phone":"+1 949 552 3456",
    "sg:postcode":"92604",
    "sg:province":"CA",
    "wof:name":"Quizno's Restaurant",
    "wof:placetype":"venue"
},
  "geometry": {"coordinates":[-117.787003,33.705101],"type":"Point"}
}