{
  "type": "Feature",
  "properties": {
    "addr:full":"8320 Sepulveda Blvd Sepulveda CA 91343",
    "addr:housenumber":"8320",
    "addr:postcode":"91343",
    "addr:street":"Sepulveda Blvd",
    "iso:country":"US",
    "sg:address":"8320 Sepulveda Blvd",
    "sg:city":"Sepulveda",
    "sg:classifiers":[
        {
            "category":"Restaurant",
            "type":"Food & Drink"
        }
    ],
    "sg:phone":"+1 818 891 4306",
    "sg:postcode":"91343",
    "sg:province":"CA",
    "wof:name":"Mc Donald's",
    "wof:placetype":"venue"
},
  "geometry": {"coordinates":[-118.46762200000001,34.224319],"type":"Point"}
}