{
  "type": "Feature",
  "properties": {
    "iso:country":"US",
    "sg:address":"8320 Sepulveda Blvd",
    "sg:city":"Sepulveda",
    "sg:classifiers":[
        {
            "category":"Restaurant",
            "type":"Food & Drink"
        }
    ],
    "sg:phone":"+1 818 891 4306",
    "sg:postcode":"91343",
    "sg:province":"CA",
    "wof:name":"Mc Donald's",
    "wof:placetype":"venue"
},
  "geometry": {"coordinates":[-118.467622,34.224319],"type":"Point"}
}