{
  "type": "Feature",
  "properties": {
    "iso:country":"US",
    "sg:address":"3181 Fitzgerald Rd",
    "sg:city":"Rancho Cordova",
    "sg:classifiers":[
        {
            "category":"Building & Trades",
            "subcategory":"Construction",
            "type":"Services"
        }
    ],
    "sg:phone":"+1 916 988 7112",
    "sg:postcode":"95742",
    "sg:province":"CA",
    "sg:tags":[
        "contractor"
    ],
    "wof:name":"Eaton Environmental Asbestos Contr",
    "wof:placetype":"venue"
},
  "geometry": {"coordinates":[-121.25900300000001,38.588501],"type":"Point"}
}