{
  "type": "Feature",
  "properties": {
    "iso:country":"US",
    "sg:address":"22616 Vermont St",
    "sg:city":"Hayward",
    "sg:classifiers":[
        {
            "category":"Restaurant",
            "type":"Food & Drink"
        }
    ],
    "sg:phone":"+1 510 537 6800",
    "sg:postcode":"94541",
    "sg:province":"CA",
    "sg:tags":[
        "shop",
        "coffee"
    ],
    "wof:name":"Shakey Grounds",
    "wof:placetype":"venue"
},
  "geometry": {"coordinates":[-122.063568,37.681122],"type":"Point"}
}