{
  "type": "Feature",
  "properties": {
    "addr:full":"4796 Clark Rd Live Oak CA 95953",
    "addr:housenumber":"4796",
    "addr:postcode":"95953",
    "addr:street":"Clark Rd",
    "iso:country":"US",
    "sg:address":"4796 Clark Rd",
    "sg:city":"Live Oak",
    "sg:phone":"+1 530 695 1048",
    "sg:postcode":"95953",
    "sg:province":"CA",
    "sg:tags":[
        "farm",
        "rice"
    ],
    "wof:name":"Nock Farm Inc",
    "wof:placetype":"venue"
},
  "geometry": {"coordinates":[-121.697389,39.231892],"type":"Point"}
}