{
  "type": "Feature",
  "properties": {
    "addr:full":"707 Sacramento St, Floor 01 San Francisco CA 94108",
    "addr:housenumber":"707;01",
    "addr:postcode":"94108",
    "addr:street":"Sacramento St Floor",
    "iso:country":"US",
    "sg:address":"707 Sacramento St, Floor 01",
    "sg:city":"San Francisco",
    "sg:classifiers":[
        {
            "category":"Banks & Credit Unions",
            "subcategory":"Investment Brokerage",
            "type":"Services"
        },
        {
            "category":"Banks & Credit Unions",
            "subcategory":"Bank",
            "type":"Services"
        }
    ],
    "sg:phone":"+1 415 782 7721",
    "sg:postcode":"94108",
    "sg:province":"CA",
    "sg:tags":[
        "investing"
    ],
    "sg:website":"www.schwab.com/",
    "wof:name":"Charles Schwab",
    "wof:placetype":"venue"
},
  "geometry": {"coordinates":[-122.40471599999999,37.793539],"type":"Point"}
}