{
  "type": "Feature",
  "properties": {
    "addr:full":"501 7th Ave San Diego CA 92101",
    "addr:housenumber":"501",
    "addr:postcode":"92101",
    "addr:street":"7Th Ave",
    "iso:country":"US",
    "sg:address":"501 7th Ave",
    "sg:city":"San Diego",
    "sg:classifiers":[
        {
            "category":"Travel",
            "subcategory":"Hotels & Motels",
            "type":"Entertainment"
        }
    ],
    "sg:phone":"+1 619 239 4604",
    "sg:postcode":"92101",
    "sg:province":"CA",
    "wof:name":"Coast Hotel",
    "wof:placetype":"venue"
},
  "geometry": {"coordinates":[-117.158297,32.710975],"type":"Point"}
}