{
  "type": "Feature",
  "properties": {
    "addr:full":"623 34th St Paso Robles CA 93446",
    "addr:housenumber":"623",
    "addr:postcode":"93446",
    "addr:street":"34Th St",
    "iso:country":"US",
    "sg:address":"623 34th St",
    "sg:city":"Paso Robles",
    "sg:classifiers":[
        {
            "category":"Building & Trades",
            "subcategory":"Construction",
            "type":"Services"
        }
    ],
    "sg:phone":"+1 805 239 5825",
    "sg:postcode":"93446",
    "sg:province":"CA",
    "sg:tags":[
        "painter"
    ],
    "wof:name":"Rendon's Painting",
    "wof:placetype":"venue"
},
  "geometry": {"coordinates":[-120.694304,35.64959],"type":"Point"}
}