{
  "type": "Feature",
  "properties": {
    "addr:full":"Paseo Colorado 330 E Colorado Blvd Pasadena CA 91101",
    "addr:housenumber":"330 e",
    "addr:postcode":"91101",
    "addr:street":"Paseo Colorado;Colorado Blvd",
    "iso:country":"US",
    "sg:address":"Paseo Colorado 330 E Colorado Blvd",
    "sg:city":"Pasadena",
    "sg:classifiers":[
        {
            "category":"Restaurant",
            "type":"Food & Drink"
        },
        {
            "category":"Ice Cream",
            "type":"Food & Drink"
        }
    ],
    "sg:phone":"+1 626 440 0140",
    "sg:postcode":"91101",
    "sg:province":"CA",
    "sg:tags":[
        "frozen",
        "dessert",
        "yogurt"
    ],
    "sg:website":"www.coldstonecreamery.com",
    "wof:name":"Cold Stone Creamery",
    "wof:placetype":"venue"
},
  "geometry": {"coordinates":[-118.142858,34.145819],"type":"Point"}
}