{
  "type": "Feature",
  "properties": {
    "iso:country":"US",
    "sg:address":"7887 N 9th St",
    "sg:city":"Fresno",
    "sg:classifiers":[
        {
            "category":"Building & Trades",
            "subcategory":"Construction",
            "type":"Services"
        }
    ],
    "sg:phone":"+1 559 438 4653",
    "sg:postcode":"93720",
    "sg:province":"CA",
    "sg:tags":[
        "house"
    ],
    "wof:name":"Rogers & Fields Construction",
    "wof:placetype":"venue"
},
  "geometry": {"coordinates":[-119.76067999999999,36.850057],"type":"Point"}
}