{
  "type": "Feature",
  "properties": {
    "addr:full":"400 Citadel Dr Commerce CA 90040",
    "addr:housenumber":"400",
    "addr:postcode":"90040",
    "addr:street":"Citadel Dr",
    "iso:country":"US",
    "sg:address":"400 Citadel Dr",
    "sg:city":"Commerce",
    "sg:classifiers":[
        {
            "category":"Real Estate",
            "subcategory":"Real Estate Agent",
            "type":"Services"
        }
    ],
    "sg:phone":"+1 323 622 1740",
    "sg:postcode":"90040",
    "sg:province":"CA",
    "wof:name":"2828 Corp",
    "wof:placetype":"venue"
},
  "geometry": {"coordinates":[-118.152382,34.005412],"type":"Point"}
}