{
  "type": "Feature",
  "properties": {
    "addr:full":"1218 H St Modesto CA 95354",
    "addr:housenumber":"1218",
    "addr:postcode":"ca 95354",
    "addr:street":"H St",
    "iso:country":"US",
    "sg:address":"1218 H St",
    "sg:city":"Modesto",
    "sg:classifiers":[
        {
            "category":"Insurance",
            "subcategory":"Hazard Insurance",
            "type":"Services"
        }
    ],
    "sg:phone":"+1 209 524 5291",
    "sg:postcode":"95354",
    "sg:province":"CA",
    "sg:tags":[
        "bond"
    ],
    "wof:name":"Woody's Bail Bonds",
    "wof:placetype":"venue"
},
  "geometry": {"coordinates":[-120.995188,37.640533],"type":"Point"}
}