{
  "type": "Feature",
  "properties": {
    "iso:country":"US",
    "sg:address":"11363 Northview Dr",
    "sg:city":"Nevada City",
    "sg:classifiers":[
        {
            "category":"Retail",
            "subcategory":"Auto Repair",
            "type":"Services"
        }
    ],
    "sg:phone":"+1 530 272 3075",
    "sg:postcode":"95959",
    "sg:province":"CA",
    "sg:tags":[
        "automobile",
        "customizing"
    ],
    "wof:name":"Hoppers Hot Rod Garage",
    "wof:placetype":"venue"
},
  "geometry": {"coordinates":[-121.009044,39.239704],"type":"Point"}
}