{
  "type": "Feature",
  "properties": {
    "addr:full":"305 Railroad Ave Nevada City CA 95959",
    "addr:housenumber":"305",
    "addr:postcode":"95959",
    "addr:street":"Railroad Ave",
    "iso:country":"US",
    "sg:address":"305 Railroad Ave",
    "sg:city":"Nevada City",
    "sg:classifiers":[
        {
            "category":"Personal",
            "subcategory":"Beauty Salon",
            "type":"Services"
        }
    ],
    "sg:phone":"+1 530 470 8450",
    "sg:postcode":"95959",
    "sg:province":"CA",
    "wof:name":"Aesthetics By Victoria Cook",
    "wof:placetype":"venue"
},
  "geometry": {"coordinates":[-121.017495,39.258837],"type":"Point"}
}