{
  "type": "Feature",
  "properties": {
    "addr:full":"4301 Oxwood Dr Sacramento CA 95826",
    "addr:housenumber":"4301",
    "addr:postcode":"95826",
    "addr:street":"Oxwood Dr",
    "iso:country":"US",
    "sg:address":"4301 Oxwood Dr",
    "sg:city":"Sacramento",
    "sg:classifiers":[
        {
            "category":"Building & Trades",
            "subcategory":"Construction",
            "type":"Services"
        }
    ],
    "sg:phone":"+1 916 410 1408",
    "sg:postcode":"95826",
    "sg:province":"CA",
    "sg:tags":[
        "general",
        "contractor"
    ],
    "wof:name":"Little Rhino Construction Co",
    "wof:placetype":"venue"
},
  "geometry": {"coordinates":[-121.349422,38.541913],"type":"Point"}
}