{
  "type": "Feature",
  "properties": {
    "addr:full":"2828 University Avenue Suite 102 San Diego CA 92104",
    "addr:housenumber":"2828",
    "addr:postcode":"92104",
    "addr:street":"University Avenue Suite 102",
    "iso:country":"US",
    "sg:address":"2828 University Avenue Suite 102",
    "sg:city":"San Diego",
    "sg:classifiers":[
        {
            "category":"Professional",
            "subcategory":"Lawyer & Legal Services",
            "type":"Services"
        }
    ],
    "sg:phone":"+1 619 794 0243",
    "sg:postcode":"92104",
    "sg:province":"CA",
    "sg:website":"www.sandiegolawfirm.com",
    "wof:name":"San Diego Law Firm",
    "wof:placetype":"venue"
},
  "geometry": {"coordinates":[-117.13298,32.748778],"type":"Point"}
}