{
  "type": "Feature",
  "properties": {
    "iso:country":"US",
    "sg:address":"8600 Jaytee Way",
    "sg:city":"Fair Oaks",
    "sg:classifiers":[
        {
            "category":"Building & Trades",
            "subcategory":"Cleaning & Sanitation",
            "type":"Services"
        }
    ],
    "sg:phone":"+1 916 863 1461",
    "sg:postcode":"95628",
    "sg:province":"CA",
    "sg:tags":[
        "janitor"
    ],
    "wof:name":"H & M Complete Janitorial Svc",
    "wof:placetype":"venue"
},
  "geometry": {"coordinates":[-121.24149199999999,38.668287],"type":"Point"}
}