{
  "type": "Feature",
  "properties": {
    "iso:country":"US",
    "sg:address":"1500A South River Road",
    "sg:city":"West Sacramento",
    "sg:classifiers":[
        {
            "category":"Professional",
            "type":"Services"
        },
        {
            "category":"Building & Trades",
            "subcategory":"Pest Control",
            "type":"Services"
        }
    ],
    "sg:phone":"+1 916 371 0864",
    "sg:postcode":"95691",
    "sg:province":"CA",
    "sg:website":"www.pegasuspest.com",
    "wof:name":"Pegasus Pest Control",
    "wof:placetype":"venue"
},
  "geometry": {"coordinates":[-121.52074399999999,38.571161],"type":"Point"}
}