{
  "type": "Feature",
  "properties": {
    "iso:country":"US",
    "sg:address":"456 Montgomery Street",
    "sg:city":"San Francisco",
    "sg:classifiers":[
        {
            "category":"Professional",
            "subcategory":"Lawyer & Legal Services",
            "type":"Services"
        }
    ],
    "sg:phone":"+1 415 398 0200",
    "sg:postcode":"94104",
    "sg:province":"CA",
    "wof:name":"Firestone David A Atty",
    "wof:placetype":"venue"
},
  "geometry": {"coordinates":[-122.402,37.791599],"type":"Point"}
}