{
  "type": "Feature",
  "properties": {
    "iso:country":"US",
    "sg:address":"24136 Humphries Rd",
    "sg:city":"Tecate",
    "sg:classifiers":[
        {
            "category":"Farming",
            "subcategory":"Fish & Marine Products",
            "type":"Manufacturing & Wholesale Goods"
        }
    ],
    "sg:phone":"+1 619 478 9736",
    "sg:postcode":"91980",
    "sg:province":"CA",
    "sg:tags":[
        "catching"
    ],
    "wof:name":"Wrens Marine Products",
    "wof:placetype":"venue"
},
  "geometry": {"coordinates":[-116.63210100000001,32.582486],"type":"Point"}
}