{
  "type": "Feature",
  "properties": {
    "addr:full":"446 S Anaheim Hills Rd # 143 Anaheim CA 92807",
    "addr:housenumber":"446",
    "addr:postcode":"92807",
    "addr:street":"S Anaheim Hills Rd # 143",
    "iso:country":"US",
    "sg:address":"446 S Anaheim Hills Rd # 143",
    "sg:city":"Anaheim",
    "sg:classifiers":[
        {
            "category":"Building & Trades",
            "subcategory":"Construction",
            "type":"Services"
        }
    ],
    "sg:phone":"+1 714 666 2222",
    "sg:postcode":"92807",
    "sg:province":"CA",
    "sg:tags":[
        "system",
        "specialty",
        "heating",
        "contractor",
        "air conditioning"
    ],
    "wof:name":"Industrial Piping Systems Eqp",
    "wof:placetype":"venue"
},
  "geometry": {"coordinates":[-117.77735699999999,33.846128],"type":"Point"}
}