{
  "type": "Feature",
  "properties": {
    "iso:country":"US",
    "sg:address":"440 Main St",
    "sg:city":"Pleasanton",
    "sg:classifiers":[
        {
            "category":"Retail",
            "subcategory":"Photofinishing",
            "type":"Services"
        }
    ],
    "sg:phone":"+1 925 484 5098",
    "sg:postcode":"94566",
    "sg:province":"CA",
    "sg:tags":[
        "film",
        "developing"
    ],
    "wof:name":"Pleasanton One Hour Photo",
    "wof:placetype":"venue"
},
  "geometry": {"coordinates":[-121.876004,37.660065],"type":"Point"}
}