{
  "type": "Feature",
  "properties": {
    "addr:full":"17186 Marilla St Northridge CA 91325",
    "addr:housenumber":"17186",
    "addr:postcode":"91325",
    "addr:street":"Marilla St",
    "iso:country":"US",
    "sg:address":"17186 Marilla St",
    "sg:city":"Northridge",
    "sg:classifiers":[
        {
            "category":"Professional",
            "subcategory":"Business Services",
            "type":"Services"
        }
    ],
    "sg:phone":"+1 818 886 5963",
    "sg:postcode":"91325",
    "sg:province":"CA",
    "sg:tags":[
        "notary"
    ],
    "wof:name":"Doc Docs",
    "wof:placetype":"venue"
},
  "geometry": {"coordinates":[-118.508638,34.247548],"type":"Point"}
}