{
  "type": "Feature",
  "properties": {
    "addr:full":"211 Center St Manteca CA 95336",
    "addr:housenumber":"211",
    "addr:postcode":"95336",
    "addr:street":"Center St",
    "iso:country":"US",
    "sg:address":"211 Center St",
    "sg:city":"Manteca",
    "sg:classifiers":[
        {
            "category":"Health Services",
            "subcategory":"Chiropractor",
            "type":"Services"
        }
    ],
    "sg:phone":"+1 209 239 1258",
    "sg:postcode":"95336",
    "sg:province":"CA",
    "wof:name":"Norlinger Chiropractic Office",
    "wof:placetype":"venue"
},
  "geometry": {"coordinates":[-121.21471699999999,37.799181],"type":"Point"}
}