{
  "type": "Feature",
  "properties": {
    "addr:full":"2020 High St Ste D Selma CA 93662",
    "addr:housenumber":"2020",
    "addr:postcode":"93662",
    "addr:street":"High St Ste D",
    "iso:country":"US",
    "sg:address":"2020 High St Ste D",
    "sg:city":"Selma",
    "sg:classifiers":[
        {
            "category":"Food & Beverages",
            "subcategory":"Farmers Market",
            "type":"Retail Goods"
        },
        {
            "category":"Wholesale",
            "subcategory":"Fruits & Vegetables",
            "type":"Manufacturing & Wholesale Goods"
        }
    ],
    "sg:phone":"+1 559 896 0525",
    "sg:postcode":"93662",
    "sg:province":"CA",
    "sg:tags":[
        "shipper",
        "grower",
        "vegetables-wholesale"
    ],
    "wof:name":"Steve Wilson Produce Distributing",
    "wof:placetype":"venue"
},
  "geometry": {"coordinates":[-119.612213,36.568934],"type":"Point"}
}