{
  "type": "Feature",
  "properties": {
    "iso:country":"US",
    "sg:address":"12818 Wardman St",
    "sg:city":"Whittier",
    "sg:classifiers":[
        {
            "category":"Organizations",
            "subcategory":"Community Association",
            "type":"Services"
        }
    ],
    "sg:phone":"+1 562 698 9053",
    "sg:postcode":"90602",
    "sg:province":"CA",
    "sg:tags":[
        "fraternal"
    ],
    "wof:name":"Independent Order-Odd Fellows",
    "wof:placetype":"venue"
},
  "geometry": {"coordinates":[-118.039317,33.977198],"type":"Point"}
}