{
  "type": "Feature",
  "properties": {
    "addr:full":"9612 Kalmia St Los Angeles CA 90002",
    "addr:housenumber":"9612",
    "addr:postcode":"90002",
    "addr:street":"Kalmia St",
    "iso:country":"US",
    "sg:address":"9612 Kalmia St",
    "sg:city":"Los Angeles",
    "sg:classifiers":[
        {
            "category":"Building & Trades",
            "subcategory":"Construction",
            "type":"Services"
        }
    ],
    "sg:phone":"+1 323 564 3855",
    "sg:postcode":"90002",
    "sg:province":"CA",
    "sg:tags":[
        "residential"
    ],
    "wof:name":"Solis Construction",
    "wof:placetype":"venue"
},
  "geometry": {"coordinates":[-118.231644,33.94955],"type":"Point"}
}