{
  "type": "Feature",
  "properties": {
    "addr:full":"222 Rheem Blvd Moraga CA 94556",
    "addr:housenumber":"222",
    "addr:postcode":"94556",
    "addr:street":"Rheem Blvd",
    "iso:country":"US",
    "sg:address":"222 Rheem Blvd",
    "sg:city":"Moraga",
    "sg:classifiers":[
        {
            "category":"Professional",
            "type":"Services"
        }
    ],
    "sg:phone":"+1 925 631 7826",
    "sg:postcode":"94556",
    "sg:province":"CA",
    "wof:name":"David Call Products",
    "wof:placetype":"venue"
},
  "geometry": {"coordinates":[-122.14246,37.866213],"type":"Point"}
}