{
  "type": "Feature",
  "properties": {
    "addr:full":"3338 N Texas St Fairfield CA 94533",
    "addr:housenumber":"3338",
    "addr:postcode":"94533",
    "addr:street":"N Texas St",
    "iso:country":"US",
    "sg:address":"3338 N Texas St",
    "sg:city":"Fairfield",
    "sg:classifiers":[
        {
            "category":"Utilities",
            "subcategory":"Mobile Phone",
            "type":"Services"
        }
    ],
    "sg:phone":"+1 707 421 8080",
    "sg:postcode":"94533",
    "sg:province":"CA",
    "sg:tags":[
        "telephone",
        "cellular"
    ],
    "wof:name":"Nextel-Northstar Wireless",
    "wof:placetype":"venue"
},
  "geometry": {"coordinates":[-122.033873,38.288205],"type":"Point"}
}