{
  "type": "Feature",
  "properties": {
    "iso:country":"US",
    "sg:address":"23297 Ave 88",
    "sg:city":"Terra Bella",
    "sg:classifiers":[
        {
            "category":"Manufacturing",
            "subcategory":"Motor Vehicles & Parts",
            "type":"Manufacturing & Wholesale Goods"
        }
    ],
    "sg:phone":"+1 559 535 2706",
    "sg:postcode":"93270",
    "sg:province":"CA",
    "sg:tags":[
        "trailer"
    ],
    "wof:name":"Gallaty Trailer Sales",
    "wof:placetype":"venue"
},
  "geometry": {"coordinates":[-119.050375,35.949775],"type":"Point"}
}