{
  "type": "Feature",
  "properties": {
    "addr:full":"3450 W Warren Ave Fremont CA 94538",
    "addr:housenumber":"3450",
    "addr:postcode":"94538",
    "addr:street":"W Warren Ave",
    "iso:country":"US",
    "sg:address":"3450 W Warren Ave",
    "sg:city":"Fremont",
    "sg:classifiers":[
        {
            "category":"Utilities",
            "subcategory":"Telephone",
            "type":"Services"
        }
    ],
    "sg:phone":"+1 510 979 2200",
    "sg:postcode":"94538",
    "sg:province":"CA",
    "sg:tags":[
        "telecommunication"
    ],
    "wof:name":"Go Digital Telecommunications",
    "wof:placetype":"venue"
},
  "geometry": {"coordinates":[-121.944292,37.481189],"type":"Point"}
}