{
  "type": "Feature",
  "properties": {
    "addr:full":"24604 Falena Ave Lomita CA 90717",
    "addr:postcode":"24604;90717",
    "addr:street":"Falena Ave",
    "iso:country":"US",
    "sg:address":"24604 Falena Ave",
    "sg:city":"Lomita",
    "sg:classifiers":[
        {
            "category":"Building & Trades",
            "subcategory":"Construction",
            "type":"Services"
        }
    ],
    "sg:phone":"+1 310 784 1995",
    "sg:postcode":"90717",
    "sg:province":"CA",
    "sg:tags":[
        "concrete",
        "contractor"
    ],
    "wof:name":"Competitive Concrete Sawing",
    "wof:placetype":"venue"
},
  "geometry": {"coordinates":[-118.310889,33.800998],"type":"Point"}
}