{
  "type": "Feature",
  "properties": {
    "iso:country":"US",
    "sg:address":"505 Magnolia Ave",
    "sg:city":"Larkspur",
    "sg:classifiers":[
        {
            "category":"Real Estate",
            "subcategory":"Real Estate Operator",
            "type":"Services"
        }
    ],
    "sg:phone":"+1 415 924 1415",
    "sg:postcode":"94939",
    "sg:province":"CA",
    "sg:tags":[
        "building",
        "apartment"
    ],
    "wof:name":"Blue Rock & Larkwood Apts",
    "wof:placetype":"venue"
},
  "geometry": {"coordinates":[-122.5351,37.936364],"type":"Point"}
}