{
  "type": "Feature",
  "properties": {
    "addr:full":"4750 Norris Canyon Rd San Ramon CA 94583",
    "addr:housenumber":"4750",
    "addr:postcode":"ca 94583",
    "addr:street":"Norris Canyon Rd",
    "iso:country":"US",
    "sg:address":"4750 Norris Canyon Rd",
    "sg:city":"San Ramon",
    "sg:classifiers":[
        {
            "category":"Building & Trades",
            "subcategory":"Construction",
            "type":"Services"
        }
    ],
    "sg:phone":"+1 925 867 3811",
    "sg:postcode":"94583",
    "sg:province":"CA",
    "sg:tags":[
        "contractor"
    ],
    "sg:website":"www.brandonconst.com",
    "wof:name":"Brandon Construction",
    "wof:placetype":"venue"
},
  "geometry": {"coordinates":[-121.96202,37.776436],"type":"Point"}
}