{
  "type": "Feature",
  "properties": {
    "iso:country":"US",
    "sg:address":"14 Duquesa",
    "sg:city":"Dana Point",
    "sg:classifiers":[
        {
            "category":"Wholesale",
            "subcategory":"Sporting Goods",
            "type":"Manufacturing & Wholesale Goods"
        }
    ],
    "sg:phone":"+1 949 443 0418",
    "sg:postcode":"92629",
    "sg:province":"CA",
    "wof:name":"Pacific Coast Athletic Sales",
    "wof:placetype":"venue"
},
  "geometry": {"coordinates":[-117.707893,33.485835],"type":"Point"}
}