{
  "type": "Feature",
  "properties": {
    "iso:country":"US",
    "sg:address":"1566 W Holt Ave",
    "sg:city":"El Centro",
    "sg:classifiers":[
        {
            "category":"Building & Trades",
            "subcategory":"Electrical",
            "type":"Services"
        }
    ],
    "sg:phone":"+1 760 353 4913",
    "sg:postcode":"92243",
    "sg:province":"CA",
    "sg:tags":[
        "electric",
        "contractor"
    ],
    "wof:name":"T-O Electric",
    "wof:placetype":"venue"
},
  "geometry": {"coordinates":[-115.572384,32.788075],"type":"Point"}
}