{
  "type": "Feature",
  "properties": {
    "iso:country":"US",
    "sg:address":"30912 S Coast Hwy",
    "sg:city":"Laguna Beach",
    "sg:classifiers":[
        {
            "category":"Shopping",
            "type":"Retail Goods"
        }
    ],
    "sg:phone":"+1 949 499 5366",
    "sg:postcode":"92651",
    "sg:province":"CA",
    "sg:tags":[
        "awning",
        "canopy"
    ],
    "wof:name":"Walsh Flooring & Window Cvrng",
    "wof:placetype":"venue"
},
  "geometry": {"coordinates":[-117.755432,33.514166],"type":"Point"}
}