{
  "type": "Feature",
  "properties": {
    "addr:full":"4588 W Shaw Ave Fresno CA 93722",
    "addr:housenumber":"4588",
    "addr:postcode":"93722",
    "addr:street":"W Shaw Ave",
    "iso:country":"US",
    "sg:address":"4588 W Shaw Ave",
    "sg:city":"Fresno",
    "sg:classifiers":[
        {
            "category":"Bus Charters",
            "type":"Transportation"
        }
    ],
    "sg:phone":"+1 559 275 2121",
    "sg:postcode":"93722",
    "sg:province":"CA",
    "wof:name":"Abbey Road Tours",
    "wof:placetype":"venue"
},
  "geometry": {"coordinates":[-119.876096,36.808301],"type":"Point"}
}