{
  "type": "Feature",
  "properties": {
    "addr:full":"4140 Mother Lode Dr Shingle Springs CA 95682",
    "addr:housenumber":"4140",
    "addr:postcode":"95682",
    "addr:street":"Mother Lode Dr",
    "iso:country":"US",
    "sg:address":"4140 Mother Lode Dr",
    "sg:city":"Shingle Springs",
    "sg:classifiers":[
        {
            "category":"Health Services",
            "subcategory":"Clinic",
            "type":"Services"
        }
    ],
    "sg:phone":"+1 530 672 8059",
    "sg:postcode":"95682",
    "sg:province":"CA",
    "wof:name":"Shingle Springs Tribal Health",
    "wof:placetype":"venue"
},
  "geometry": {"coordinates":[-120.93147999999999,38.663778],"type":"Point"}
}