{
  "type": "Feature",
  "properties": {
    "iso:country":"US",
    "sg:address":"226 Glendale Blvd",
    "sg:city":"Los Angeles",
    "sg:classifiers":[
        {
            "category":"Professional",
            "type":"Services"
        }
    ],
    "sg:phone":"+1 323 930 0460",
    "sg:postcode":"90026",
    "sg:province":"CA",
    "wof:name":"Angeles Garcia Dr",
    "wof:placetype":"venue"
},
  "geometry": {"coordinates":[-118.26009999999999,34.065302],"type":"Point"}
}