{
  "type": "Feature",
  "properties": {
    "iso:country":"US",
    "sg:address":"2400 E Katella Ave Ste 175",
    "sg:city":"Anaheim",
    "sg:classifiers":[
        {
            "category":"Restaurant",
            "type":"Food & Drink"
        }
    ],
    "sg:phone":"+1 714 634 8201",
    "sg:postcode":"92806",
    "sg:province":"CA",
    "wof:name":"Presto Cafe",
    "wof:placetype":"venue"
},
  "geometry": {"coordinates":[-117.88400300000001,33.805199],"type":"Point"}
}