{
  "type": "Feature",
  "properties": {
    "iso:country":"US",
    "sg:address":"1607 Meridian Ave",
    "sg:city":"San Jose",
    "sg:classifiers":[
        {
            "category":"Shopping",
            "subcategory":"Computers & Home Electronics",
            "type":"Retail Goods"
        }
    ],
    "sg:phone":"+1 408 979 9077",
    "sg:postcode":"95125",
    "sg:province":"CA",
    "sg:tags":[
        "equipment",
        "satellite",
        "system"
    ],
    "wof:name":"Satellite Solutions",
    "wof:placetype":"venue"
},
  "geometry": {"coordinates":[-121.91359799999999,37.293857],"type":"Point"}
}