{
  "type": "Feature",
  "properties": {
    "iso:country":"US",
    "sg:address":"25601 Mission Blvd",
    "sg:city":"Hayward",
    "sg:classifiers":[
        {
            "category":"Autos & Motor Vehicles",
            "subcategory":"Automobile Sales",
            "type":"Retail Goods"
        }
    ],
    "sg:phone":"+1 510 538 4433",
    "sg:postcode":"94544",
    "sg:province":"CA",
    "sg:tags":[
        "car",
        "dealer"
    ],
    "wof:name":"Hayward Dodge Inc",
    "wof:placetype":"venue"
},
  "geometry": {"coordinates":[-122.068801,37.653662],"type":"Point"}
}