{
  "type": "Feature",
  "properties": {
    "addr:full":"2106 Sorrento Dr Oceanside CA 92056",
    "addr:housenumber":"2106",
    "addr:postcode":"92056",
    "addr:street":"Sorrento Dr",
    "iso:country":"US",
    "sg:address":"2106 Sorrento Dr",
    "sg:city":"Oceanside",
    "sg:classifiers":[
        {
            "category":"Health Services",
            "subcategory":"Clinic",
            "type":"Services"
        }
    ],
    "sg:phone":"+1 760 757 7689",
    "sg:postcode":"92056",
    "sg:province":"CA",
    "wof:name":"Health & Wellness Enterprises",
    "wof:placetype":"venue"
},
  "geometry": {"coordinates":[-117.309043,33.19527],"type":"Point"}
}