{
  "type": "Feature",
  "properties": {
    "addr:full":"19191 S Vermont Ave Torrance CA 90502",
    "addr:housenumber":"19191",
    "addr:postcode":"90502",
    "addr:street":"S Vermont Ave",
    "iso:country":"US",
    "sg:address":"19191 S Vermont Ave",
    "sg:city":"Torrance",
    "sg:classifiers":[
        {
            "category":"Professional",
            "subcategory":"Accounting & Tax Preparation",
            "type":"Services"
        }
    ],
    "sg:phone":"+1 310 323 0333",
    "sg:postcode":"90502",
    "sg:province":"CA",
    "sg:tags":[
        "accountant"
    ],
    "wof:name":"Tax Advice Inc",
    "wof:placetype":"venue"
},
  "geometry": {"coordinates":[-118.29059700000001,33.857346],"type":"Point"}
}