{
  "type": "Feature",
  "properties": {
    "addr:full":"1315 Military W Benicia CA 94510",
    "addr:housenumber":"1315",
    "addr:postcode":"94510",
    "addr:street":"Military W",
    "iso:country":"US",
    "sg:address":"1315 Military W",
    "sg:city":"Benicia",
    "sg:classifiers":[
        {
            "category":"Organizations",
            "subcategory":"Religious Organization",
            "type":"Services"
        }
    ],
    "sg:phone":"+1 707 745 5683",
    "sg:postcode":"94510",
    "sg:province":"CA",
    "sg:tags":[
        "church"
    ],
    "wof:name":"Calvary Community Church",
    "wof:placetype":"venue"
},
  "geometry": {"coordinates":[-122.180409,38.066917],"type":"Point"}
}