{
  "type": "Feature",
  "properties": {
    "addr:full":"9059 Cerritos Ave Anaheim CA 92804",
    "addr:housenumber":"9059",
    "addr:postcode":"92804",
    "addr:street":"Cerritos Ave",
    "iso:country":"US",
    "sg:address":"9059 Cerritos Ave",
    "sg:city":"Anaheim",
    "sg:classifiers":[
        {
            "category":"Shopping",
            "subcategory":"Bridal",
            "type":"Retail Goods"
        }
    ],
    "sg:phone":"+1 714 827 1939",
    "sg:postcode":"92804",
    "sg:province":"CA",
    "wof:name":"Elia's Bridal Shop",
    "wof:placetype":"venue"
},
  "geometry": {"coordinates":[-117.97399900000001,33.810398],"type":"Point"}
}