{
  "type": "Feature",
  "properties": {
    "addr:full":"4445 Eastgate Mall Ste. 405 San Diego CA 92121",
    "addr:housenumber":"4445",
    "addr:postcode":"92121",
    "addr:street":"Eastgate Mall Ste. 405",
    "iso:country":"US",
    "sg:address":"4445 Eastgate Mall Ste. 405",
    "sg:city":"San Diego",
    "sg:classifiers":[
        {
            "category":"Professional",
            "subcategory":"Computer Services",
            "type":"Services"
        }
    ],
    "sg:phone":"+1 619 764 5650",
    "sg:postcode":"92121",
    "sg:province":"CA",
    "sg:tags":[
        "nirvanix",
        "storage",
        "online",
        "s3",
        "transcoding",
        "service",
        "cloud",
        "isilon"
    ],
    "sg:website":"http://www.nirvanix.com",
    "wof:name":"Nirvanix",
    "wof:placetype":"venue"
},
  "geometry": {"coordinates":[-117.214032,32.877576],"type":"Point"}
}