{
  "type": "Feature",
  "properties": {
    "iso:country":"US",
    "sg:address":"2127 Ashby Ave",
    "sg:city":"Berkeley",
    "sg:classifiers":[
        {
            "category":"Health Services",
            "subcategory":"Clinic",
            "type":"Services"
        }
    ],
    "sg:phone":"+1 510 548 7960",
    "sg:postcode":"94705",
    "sg:province":"CA",
    "sg:tags":[
        "counseling",
        "mental"
    ],
    "wof:name":"Leslie C. Bell, Ph.D., LCSW",
    "wof:placetype":"venue"
},
  "geometry": {"coordinates":[-122.265191,37.855466],"type":"Point"}
}