{
  "type": "Feature",
  "properties": {
    "addr:full":"1641 Bixler Rd Brentwood CA 94513",
    "addr:housenumber":"1641",
    "addr:postcode":"ca 94513",
    "addr:street":"Bixler Rd",
    "iso:country":"US",
    "sg:address":"1641 Bixler Rd",
    "sg:city":"Brentwood",
    "sg:classifiers":[
        {
            "category":"Building & Trades",
            "subcategory":"Construction",
            "type":"Services"
        }
    ],
    "sg:phone":"+1 925 634 0382",
    "sg:postcode":"94513",
    "sg:province":"CA",
    "sg:tags":[
        "dry wall",
        "contractor"
    ],
    "wof:name":"Brent Evans Paper Hanger",
    "wof:placetype":"venue"
},
  "geometry": {"coordinates":[-121.622827,37.917264],"type":"Point"}
}