{
  "type": "Feature",
  "properties": {
    "iso:country":"US",
    "sg:address":"11840 Paramount Blvd",
    "sg:city":"Downey",
    "sg:classifiers":[
        {
            "category":"Organizations",
            "subcategory":"Religious Organization",
            "type":"Services"
        }
    ],
    "sg:phone":"+1 562 862 2644",
    "sg:postcode":"90241",
    "sg:province":"CA",
    "sg:tags":[
        "church"
    ],
    "wof:name":"Siloam Church",
    "wof:placetype":"venue"
},
  "geometry": {"coordinates":[-118.143364,33.935205],"type":"Point"}
}