{
  "type": "Feature",
  "properties": {
    "addr:full":"3105 S Hacienda Blvd Hacienda Heights CA 91745",
    "addr:housenumber":"3105",
    "addr:postcode":"91745",
    "addr:street":"S Hacienda Blvd",
    "iso:country":"US",
    "sg:address":"3105 S Hacienda Blvd",
    "sg:city":"Hacienda Heights",
    "sg:classifiers":[
        {
            "category":"Wholesale",
            "subcategory":"Durable Goods & Equipment",
            "type":"Manufacturing & Wholesale Goods"
        }
    ],
    "sg:phone":"+1 626 333 5221",
    "sg:postcode":"91745",
    "sg:province":"CA",
    "sg:tags":[
        "importer"
    ],
    "wof:name":"Kingmax Industrial Inc",
    "wof:placetype":"venue"
},
  "geometry": {"coordinates":[-117.972037,33.979399],"type":"Point"}
}