{
  "type": "Feature",
  "properties": {
    "iso:country":"US",
    "sg:address":"827 Jackson Dr",
    "sg:city":"Paso Robles",
    "sg:classifiers":[
        {
            "category":"Building & Trades",
            "subcategory":"Construction",
            "type":"Services"
        }
    ],
    "sg:phone":"+1 805 237 9767",
    "sg:postcode":"93446",
    "sg:province":"CA",
    "sg:tags":[
        "concrete",
        "restoration",
        "cleaning",
        "repair"
    ],
    "wof:name":"Concrete Restoration Svc",
    "wof:placetype":"venue"
},
  "geometry": {"coordinates":[-120.6748,35.632535],"type":"Point"}
}