{
  "type": "Feature",
  "properties": {
    "iso:country":"US",
    "sg:address":"12188 Central Ave",
    "sg:city":"Chino",
    "sg:classifiers":[
        {
            "category":"Freight",
            "type":"Transportation"
        }
    ],
    "sg:phone":"+1 909 460 9046",
    "sg:postcode":"91710",
    "sg:province":"CA",
    "sg:tags":[
        "operator",
        "local",
        "trucking"
    ],
    "wof:name":"T & T Trucking",
    "wof:placetype":"venue"
},
  "geometry": {"coordinates":[-117.689372,34.03277],"type":"Point"}
}