{
  "type": "Feature",
  "properties": {
    "addr:full":"25 Hanson Ln Walnut Creek CA 94596",
    "addr:housenumber":"25",
    "addr:postcode":"94596",
    "addr:street":"Hanson Ln",
    "iso:country":"US",
    "sg:address":"25 Hanson Ln",
    "sg:city":"Walnut Creek",
    "sg:classifiers":[
        {
            "category":"Wholesale",
            "subcategory":"Medical Equipment & Supplies",
            "type":"Manufacturing & Wholesale Goods"
        }
    ],
    "sg:phone":"+1 925 938 6128",
    "sg:postcode":"94596",
    "sg:province":"CA",
    "wof:name":"Walco",
    "wof:placetype":"venue"
},
  "geometry": {"coordinates":[-122.038432,37.896682],"type":"Point"}
}