{
  "type": "Feature",
  "properties": {
    "addr:full":"1440 S State College Blvd Anaheim CA 92806",
    "addr:housenumber":"1440",
    "addr:postcode":"92806",
    "addr:street":"S;Blvd",
    "iso:country":"US",
    "sg:address":"1440 S State College Blvd",
    "sg:city":"Anaheim",
    "sg:classifiers":[
        {
            "category":"Health Services",
            "subcategory":"Medical Lab",
            "type":"Services"
        }
    ],
    "sg:phone":"+1 714 991 1935",
    "sg:postcode":"92806",
    "sg:province":"CA",
    "wof:name":"Ctd",
    "wof:placetype":"venue"
},
  "geometry": {"coordinates":[-117.889258,33.812139],"type":"Point"}
}