{
  "type": "Feature",
  "properties": {
    "addr:full":"2333 Cam del Rio S San Diego CA 92108",
    "addr:housenumber":"2333",
    "addr:postcode":"92108",
    "addr:street":"Cam Del Rio S",
    "iso:country":"US",
    "sg:address":"2333 Cam del Rio S",
    "sg:city":"San Diego",
    "sg:classifiers":[
        {
            "category":"Professional",
            "type":"Services"
        }
    ],
    "sg:phone":"+1 619 683 2311",
    "sg:postcode":"92108",
    "sg:province":"CA",
    "wof:name":"A Greater Hope",
    "wof:placetype":"venue"
},
  "geometry": {"coordinates":[-117.151031,32.765586],"type":"Point"}
}