{
  "type": "Feature",
  "properties": {
    "iso:country":"US",
    "sg:address":"28046 del Rio Rd Ste C",
    "sg:city":"Temecula",
    "sg:classifiers":[
        {
            "category":"Real Estate",
            "subcategory":"Real Estate Services",
            "type":"Services"
        },
        {
            "category":"Real Estate",
            "subcategory":"Real Estate Agent",
            "type":"Services"
        }
    ],
    "sg:phone":"+1 951 676 4148",
    "sg:postcode":"92590",
    "sg:province":"CA",
    "sg:tags":[
        "buyer",
        "broker"
    ],
    "wof:name":"Rancho Land Associates",
    "wof:placetype":"venue"
},
  "geometry": {"coordinates":[-117.154886,33.503428],"type":"Point"}
}