{
  "type": "Feature",
  "properties": {
    "iso:country":"US",
    "sg:address":"4184 Beyer Blvd",
    "sg:city":"San Diego",
    "sg:classifiers":[
        {
            "category":"Shopping",
            "type":"Retail Goods"
        }
    ],
    "sg:phone":"+1 619 428 3732",
    "sg:postcode":"92173",
    "sg:province":"CA",
    "sg:tags":[
        "perfume"
    ],
    "wof:name":"Perfumes R-Us",
    "wof:placetype":"venue"
},
  "geometry": {"coordinates":[-117.045489,32.558338],"type":"Point"}
}