{
  "type": "Feature",
  "properties": {
    "addr:full":"4005 E Church Ave Fresno CA 93721",
    "addr:housenumber":"4005",
    "addr:postcode":"93721",
    "addr:street":"E Church Ave",
    "iso:country":"US",
    "sg:address":"4005 E Church Ave",
    "sg:city":"Fresno",
    "sg:classifiers":[
        {
            "category":"Wholesale",
            "subcategory":"Metals & Minerals",
            "type":"Manufacturing & Wholesale Goods"
        }
    ],
    "sg:phone":"+1 559 442 1410",
    "sg:postcode":"93721",
    "sg:province":"CA",
    "sg:tags":[
        "steel",
        "warehouse"
    ],
    "sg:website":"www.pdmsteel.com",
    "wof:name":"PDM Steel Svc Ctr",
    "wof:placetype":"venue"
},
  "geometry": {"coordinates":[-119.762962,36.714224],"type":"Point"}
}