{
  "type": "Feature",
  "properties": {
    "addr:full":"2261 Market St San Francisco CA 94114",
    "addr:housenumber":"2261",
    "addr:postcode":"94114",
    "addr:street":"Market St",
    "iso:country":"US",
    "sg:address":"2261 Market St",
    "sg:city":"San Francisco",
    "sg:classifiers":[
        {
            "category":"Government",
            "subcategory":"Police Station",
            "type":"Public Place"
        }
    ],
    "sg:phone":"+1 415 553 3831",
    "sg:postcode":"94114",
    "sg:province":"CA",
    "sg:tags":[
        "protection"
    ],
    "wof:name":"Metro Pacific Patrol",
    "wof:placetype":"venue"
},
  "geometry": {"coordinates":[-122.43191,37.765125],"type":"Point"}
}