{
  "type": "Feature",
  "properties": {
    "iso:country":"US",
    "sg:address":"845 Charleston Way",
    "sg:city":"Brea",
    "sg:classifiers":[
        {
            "category":"Professional",
            "subcategory":"Business Services",
            "type":"Services"
        }
    ],
    "sg:phone":"+1 714 255 9525",
    "sg:postcode":"92821",
    "sg:province":"CA",
    "sg:tags":[
        "appraiser"
    ],
    "wof:name":"Apparel Arena",
    "wof:placetype":"venue"
},
  "geometry": {"coordinates":[-117.909532,33.934215],"type":"Point"}
}