{
  "type": "Feature",
  "properties": {
    "iso:country":"US",
    "sg:address":"424 W Le Roy Ave",
    "sg:city":"Arcadia",
    "sg:classifiers":[
        {
            "category":"Wholesale",
            "subcategory":"Non-durable Goods",
            "type":"Manufacturing & Wholesale Goods"
        }
    ],
    "sg:phone":"+1 626 447 8802",
    "sg:postcode":"91007",
    "sg:province":"CA",
    "wof:name":"Best Deal Import Corp",
    "wof:placetype":"venue"
},
  "geometry": {"coordinates":[-118.05072,34.124958],"type":"Point"}
}