{
  "type": "Feature",
  "properties": {
    "iso:country":"US",
    "sg:address":"1452 Scenicview Dr",
    "sg:city":"San Leandro",
    "sg:classifiers":[
        {
            "category":"Banks & Credit Unions",
            "subcategory":"Bank",
            "type":"Services"
        }
    ],
    "sg:phone":"+1 510 710 4931",
    "sg:postcode":"94577",
    "sg:province":"CA",
    "sg:tags":[
        "financing"
    ],
    "wof:name":"Diversified Funding Solutions",
    "wof:placetype":"venue"
},
  "geometry": {"coordinates":[-122.132223,37.725815],"type":"Point"}
}