{
  "type": "Feature",
  "properties": {
    "addr:full":"1924 Franklin St Oakland CA 94612",
    "addr:housenumber":"1924",
    "addr:postcode":"94612",
    "addr:street":"Franklin St",
    "iso:country":"US",
    "sg:address":"1924 Franklin St",
    "sg:city":"Oakland",
    "sg:classifiers":[
        {
            "category":"Coffee & Tea",
            "type":"Food & Drink"
        },
        {
            "category":"Deli",
            "type":"Food & Drink"
        }
    ],
    "sg:phone":"+1 510 268 9021",
    "sg:postcode":"94612",
    "sg:province":"CA",
    "wof:name":"Coco Cafe",
    "wof:placetype":"venue"
},
  "geometry": {"coordinates":[-122.267189,37.807583],"type":"Point"}
}