{
  "type": "Feature",
  "properties": {
    "iso:country":"US",
    "sg:address":"664 Palm Ave",
    "sg:city":"Los Altos",
    "sg:classifiers":[
        {
            "category":"Professional",
            "type":"Services"
        }
    ],
    "sg:phone":"+1 650 941 1083",
    "sg:postcode":"94022",
    "sg:province":"CA",
    "wof:name":"Jerry H Shlker Drthy Shlker As",
    "wof:placetype":"venue"
},
  "geometry": {"coordinates":[-122.112798,37.37108],"type":"Point"}
}