{
  "type": "Feature",
  "properties": {
    "addr:full":"851 Danville Ave Tulare CA 93274",
    "addr:housenumber":"851",
    "addr:postcode":"93274",
    "addr:street":"Danville Ave",
    "iso:country":"US",
    "sg:address":"851 Danville Ave",
    "sg:city":"Tulare",
    "sg:classifiers":[
        {
            "category":"Social Services",
            "subcategory":"Child Care",
            "type":"Services"
        }
    ],
    "sg:phone":"+1 559 687 1804",
    "sg:postcode":"93274",
    "sg:province":"CA",
    "wof:name":"Dream A Little Dream Daycare",
    "wof:placetype":"venue"
},
  "geometry": {"coordinates":[-119.361507,36.223498],"type":"Point"}
}