{
  "type": "Feature",
  "properties": {
    "addr:full":"25290 Jeronimo Rd Lake Forest CA 92630",
    "addr:housenumber":"25290",
    "addr:postcode":"92630",
    "addr:street":"Jeronimo Rd",
    "iso:country":"US",
    "sg:address":"25290 Jeronimo Rd",
    "sg:city":"Lake Forest",
    "sg:classifiers":[
        {
            "category":"Home & Garden",
            "subcategory":"Garden Supply",
            "type":"Retail Goods"
        },
        {
            "category":"Education",
            "subcategory":"Preschool",
            "type":"Public Place"
        },
        {
            "category":"Education",
            "subcategory":"School",
            "type":"Public Place"
        }
    ],
    "sg:phone":"+1 949 830 5653",
    "sg:postcode":"92630",
    "sg:province":"CA",
    "sg:tags":[
        "elementary",
        "nursery",
        "gardening"
    ],
    "wof:name":"Matsuoka Gary",
    "wof:placetype":"venue"
},
  "geometry": {"coordinates":[-117.68699599999999,33.624901],"type":"Point"}
}