{
  "type": "Feature",
  "properties": {
    "iso:country":"US",
    "sg:address":"44252 Hunter Pl",
    "sg:city":"Fremont",
    "sg:classifiers":[
        {
            "category":"Professional",
            "subcategory":"Lawyer & Legal Services",
            "type":"Services"
        }
    ],
    "sg:phone":"+1 510 593 9240",
    "sg:postcode":"94539",
    "sg:province":"CA",
    "sg:tags":[
        "plan"
    ],
    "wof:name":"Jairam Enterprises",
    "wof:placetype":"venue"
},
  "geometry": {"coordinates":[-121.91447599999999,37.51993],"type":"Point"}
}