{
  "type": "Feature",
  "properties": {
    "iso:country":"US",
    "sg:address":"455 Capitol Mall",
    "sg:city":"Sacramento",
    "sg:classifiers":[
        {
            "category":"Banks & Credit Unions",
            "subcategory":"Financial Services",
            "type":"Services"
        }
    ],
    "sg:phone":"+1 800 548 1981",
    "sg:postcode":"95814",
    "sg:province":"CA",
    "sg:tags":[
        "annuity",
        "retirement",
        "plan",
        "insurance"
    ],
    "wof:name":"U S Bancorp Securities",
    "wof:placetype":"venue"
},
  "geometry": {"coordinates":[-121.50210199999999,38.579032],"type":"Point"}
}