{
  "type": "Feature",
  "properties": {
    "addr:full":"1107 W Shaw Ave Fresno CA 93711",
    "addr:housenumber":"1107",
    "addr:postcode":"93711",
    "addr:street":"W Shaw Ave",
    "iso:country":"US",
    "sg:address":"1107 W Shaw Ave",
    "sg:city":"Fresno",
    "sg:classifiers":[
        {
            "category":"Social Services",
            "subcategory":"Adult Care",
            "type":"Services"
        }
    ],
    "sg:phone":"+1 559 226 6110",
    "sg:postcode":"93711",
    "sg:province":"CA",
    "sg:tags":[
        "home",
        "residential"
    ],
    "wof:name":"Gablecrest",
    "wof:placetype":"venue"
},
  "geometry": {"coordinates":[-119.81160199999999,36.808284],"type":"Point"}
}