{
  "type": "Feature",
  "properties": {
    "addr:full":"150 E Brokaw Rd San Jose CA 95112",
    "addr:housenumber":"150",
    "addr:postcode":"95112",
    "addr:street":"E Brokaw Rd",
    "iso:country":"US",
    "sg:address":"150 E Brokaw Rd",
    "sg:city":"San Jose",
    "sg:classifiers":[
        {
            "category":"Wholesale",
            "subcategory":"Computers",
            "type":"Manufacturing & Wholesale Goods"
        }
    ],
    "sg:phone":"+1 408 350 7800",
    "sg:postcode":"95112",
    "sg:province":"CA",
    "wof:name":"Lg International",
    "wof:placetype":"venue"
},
  "geometry": {"coordinates":[-121.916,37.374699],"type":"Point"}
}