{
  "type": "Feature",
  "properties": {
    "addr:full":"2647 International Blvd Oakland CA 94601",
    "addr:housenumber":"2647",
    "addr:postcode":"94601",
    "addr:street":"International Blvd",
    "iso:country":"US",
    "sg:address":"2647 International Blvd",
    "sg:city":"Oakland",
    "sg:classifiers":[
        {
            "category":"Health Services",
            "subcategory":"Doctor",
            "type":"Services"
        }
    ],
    "sg:phone":"+1 510 261 3368",
    "sg:postcode":"94601",
    "sg:province":"CA",
    "sg:tags":[
        "dentist"
    ],
    "wof:name":"Bay Dental Ctr",
    "wof:placetype":"venue"
},
  "geometry": {"coordinates":[-122.231984,37.781016],"type":"Point"}
}