{
  "type": "Feature",
  "properties": {
    "iso:country":"US",
    "sg:address":"8210 Sepulveda Blvd",
    "sg:city":"Panorama City",
    "sg:classifiers":[
        {
            "category":"Restaurant",
            "type":"Food & Drink"
        }
    ],
    "sg:menulink":"http://www.allmenus.com/ca/san-fernando-valley/74552-shakeys-pizza/menu/",
    "sg:phone":"+1 818 988 4231",
    "sg:postcode":"91402",
    "sg:province":"CA",
    "sg:tags":[
        "american",
        "italian",
        "pizza"
    ],
    "wof:name":"Shakey's Pizza",
    "wof:placetype":"venue"
},
  "geometry": {"coordinates":[-118.466837,34.220038],"type":"Point"}
}