{
  "type": "Feature",
  "properties": {
    "iso:country":"US",
    "sg:address":"2809 Patterson Rd",
    "sg:city":"Riverbank",
    "sg:classifiers":[
        {
            "category":"Autos & Motor Vehicles",
            "subcategory":"Auto Supplies",
            "type":"Retail Goods"
        }
    ],
    "sg:phone":"+1 209 863 0909",
    "sg:postcode":"95367",
    "sg:province":"CA",
    "sg:tags":[
        "automobile",
        "parts"
    ],
    "wof:name":"Gear Works",
    "wof:placetype":"venue"
},
  "geometry": {"coordinates":[-120.942864,37.732787],"type":"Point"}
}