{
  "type": "Feature",
  "properties": {
    "addr:full":"1716 L St Inside Old Soul Coffee Co Sacramento CA 95814",
    "addr:housenumber":"1716",
    "addr:postcode":"95814",
    "addr:street":"L St Inside",
    "iso:country":"US",
    "sg:address":"1716 L St Inside Old Soul Coffee Co",
    "sg:city":"Sacramento",
    "sg:classifiers":[
        {
            "category":"Shopping",
            "subcategory":"Pets & Pet Supplies",
            "type":"Retail Goods"
        }
    ],
    "sg:phone":"+1 916 599 0438",
    "sg:postcode":"95814",
    "sg:province":"CA",
    "sg:tags":[
        "store"
    ],
    "sg:website":"www.givethedogabone.net",
    "wof:name":"Give the Dog a Bone",
    "wof:placetype":"venue"
},
  "geometry": {"coordinates":[-121.484606,38.575496],"type":"Point"}
}