{
  "type": "Feature",
  "properties": {
    "iso:country":"US",
    "sg:address":"1368 N. Lake Street",
    "sg:city":"Pasadena",
    "sg:classifiers":[
        {
            "category":"Arts & Performance",
            "subcategory":"Jazz & Blues",
            "type":"Entertainment"
        }
    ],
    "sg:postcode":"91104",
    "sg:province":"CA",
    "sg:website":"www.dosomethingblue.com",
    "wof:name":"Do Something Blue",
    "wof:placetype":"venue"
},
  "geometry": {"coordinates":[-118.131822,34.169477],"type":"Point"}
}