{
  "type": "Feature",
  "properties": {
    "addr:full":"12583 Highland Ave Desert Hot Spgs CA 92240",
    "addr:housenumber":"12583",
    "addr:postcode":"92240",
    "addr:street":"Highland Ave;Hot Spgs",
    "iso:country":"US",
    "sg:address":"12583 Highland Ave",
    "sg:city":"Desert Hot Spgs",
    "sg:classifiers":[
        {
            "category":"Restaurant",
            "type":"Food & Drink"
        }
    ],
    "sg:phone":"+1 760 899 1016",
    "sg:postcode":"92240",
    "sg:province":"CA",
    "wof:name":"Etiwanda Roadhouse",
    "wof:placetype":"venue"
},
  "geometry": {"coordinates":[-116.473935,33.957579],"type":"Point"}
}