{
  "type": "Feature",
  "properties": {
    "addr:full":"30 Hacienda Ln El Sobrante CA 94803",
    "addr:housenumber":"30",
    "addr:postcode":"94803",
    "addr:street":"Hacienda Ln",
    "iso:country":"US",
    "sg:address":"30 Hacienda Ln",
    "sg:city":"El Sobrante",
    "sg:classifiers":[
        {
            "category":"Building & Trades",
            "subcategory":"Landscaping Services",
            "type":"Services"
        }
    ],
    "sg:phone":"+1 510 243 1715",
    "sg:postcode":"94803",
    "sg:province":"CA",
    "sg:tags":[
        "landscape",
        "contractor"
    ],
    "wof:name":"Global Sweeping Svc",
    "wof:placetype":"venue"
},
  "geometry": {"coordinates":[-122.289309,37.986285],"type":"Point"}
}