{
  "type": "Feature",
  "properties": {
    "iso:country":"US",
    "sg:address":"1041 N Pass Ave",
    "sg:city":"Burbank",
    "sg:classifiers":[
        {
            "category":"Wholesale",
            "subcategory":"Stationery",
            "type":"Manufacturing & Wholesale Goods"
        }
    ],
    "sg:phone":"+1 818 238 0205",
    "sg:postcode":"91505",
    "sg:province":"CA",
    "sg:tags":[
        "merchandise",
        "supply"
    ],
    "wof:name":"Icon Business Products",
    "wof:placetype":"venue"
},
  "geometry": {"coordinates":[-118.352638,34.16959],"type":"Point"}
}