{
  "type": "Feature",
  "properties": {
    "iso:country":"US",
    "sg:address":"3233A De La Cruz Blvd",
    "sg:city":"Santa Clara",
    "sg:classifiers":[
        {
            "category":"Home & Garden",
            "subcategory":"Home Furnishings",
            "type":"Retail Goods"
        },
        {
            "category":"Home & Garden",
            "subcategory":"Building Materials",
            "type":"Retail Goods"
        }
    ],
    "sg:phone":"+1 408 727 2888",
    "sg:postcode":"95054",
    "sg:province":"CA",
    "sg:tags":[
        "bath",
        "kitchen",
        "supply"
    ],
    "sg:website":"www.makicabinet.com/",
    "wof:name":"Maki Kitchen Cabinet Inc.",
    "wof:placetype":"venue"
},
  "geometry": {"coordinates":[-121.941661,37.382702],"type":"Point"}
}