{
  "type": "Feature",
  "properties": {
    "iso:country":"US",
    "sg:address":"3372 Via Lido",
    "sg:city":"Newport Beach",
    "sg:classifiers":[
        {
            "category":"Banks & Credit Unions",
            "subcategory":"Atm",
            "type":"Services"
        }
    ],
    "sg:phone":"+1 949 478 2101",
    "sg:postcode":"92663",
    "sg:province":"CA",
    "sg:tags":[
        "bankruptcy"
    ],
    "sg:website":"reachlegal.net/",
    "wof:name":"Reach Legal",
    "wof:placetype":"venue"
},
  "geometry": {"coordinates":[-117.927892,33.61763],"type":"Point"}
}