{
  "type": "Feature",
  "properties": {
    "addr:full":"433 N Mathilda Ave Sunnyvale CA 94085",
    "addr:housenumber":"433",
    "addr:postcode":"94085",
    "addr:street":"N Mathilda Ave",
    "iso:country":"US",
    "sg:address":"433 N Mathilda Ave",
    "sg:city":"Sunnyvale",
    "sg:classifiers":[
        {
            "category":"Wholesale",
            "subcategory":"Electrical",
            "type":"Manufacturing & Wholesale Goods"
        }
    ],
    "sg:phone":"+1 408 737 7600",
    "sg:postcode":"94085",
    "sg:province":"CA",
    "sg:tags":[
        "parts",
        "electronic"
    ],
    "wof:name":"Maxim Integrated Products",
    "wof:placetype":"venue"
},
  "geometry": {"coordinates":[-122.03146,37.38619],"type":"Point"}
}