{
  "type": "Feature",
  "properties": {
    "addr:full":"1136 Richfield Rd Placentia CA 92870",
    "addr:housenumber":"1136",
    "addr:postcode":"ca 92870",
    "addr:street":"Richfield Rd",
    "iso:country":"US",
    "sg:address":"1136 Richfield Rd",
    "sg:city":"Placentia",
    "sg:classifiers":[
        {
            "category":"Shopping",
            "subcategory":"Crafts & Fabrics",
            "type":"Retail Goods"
        }
    ],
    "sg:phone":"+1 714 524 7395",
    "sg:postcode":"92870",
    "sg:province":"CA",
    "sg:tags":[
        "store"
    ],
    "wof:name":"Robinson Manufacturing",
    "wof:placetype":"venue"
},
  "geometry": {"coordinates":[-117.82501000000001,33.861112],"type":"Point"}
}