{
  "type": "Feature",
  "properties": {
    "addr:full":"421 Foss St Healdsburg CA 95448",
    "addr:housenumber":"421",
    "addr:postcode":"95448",
    "addr:street":"Foss St",
    "iso:country":"US",
    "sg:address":"421 Foss St",
    "sg:city":"Healdsburg",
    "sg:classifiers":[
        {
            "category":"Travel",
            "subcategory":"Hotels & Motels",
            "type":"Entertainment"
        }
    ],
    "sg:phone":"+1 707 431 1300",
    "sg:postcode":"95448",
    "sg:province":"CA",
    "sg:website":"www.duchamphotel.com",
    "wof:name":"Duchamp Hotel",
    "wof:placetype":"venue"
},
  "geometry": {"coordinates":[-122.87205400000001,38.612966],"type":"Point"}
}