{
  "type": "Feature",
  "properties": {
    "iso:country":"US",
    "sg:address":"3218 Wabash Ave",
    "sg:city":"Los Angeles",
    "sg:classifiers":[
        {
            "category":"Social Services",
            "type":"Services"
        }
    ],
    "sg:phone":"+1 323 263 7519",
    "sg:postcode":"90063",
    "sg:province":"CA",
    "sg:tags":[
        "youth",
        "organization",
        "center"
    ],
    "wof:name":"Salesian Family Youth Ctr",
    "wof:placetype":"venue"
},
  "geometry": {"coordinates":[-118.192029,34.047875],"type":"Point"}
}