{
  "type": "Feature",
  "properties": {
    "iso:country":"US",
    "sg:address":"2541 State St",
    "sg:city":"Carlsbad",
    "sg:classifiers":[
        {
            "category":"Wholesale",
            "subcategory":"Scrap",
            "type":"Manufacturing & Wholesale Goods"
        }
    ],
    "sg:phone":"+1 760 434 0003",
    "sg:postcode":"92008",
    "sg:province":"CA",
    "sg:tags":[
        "waste"
    ],
    "wof:name":"Solid Solutions",
    "wof:placetype":"venue"
},
  "geometry": {"coordinates":[-117.354248,33.165757],"type":"Point"}
}