{
  "type": "Feature",
  "properties": {
    "addr:full":"4255 Winding Way Sacramento CA 95841",
    "addr:housenumber":"4255",
    "addr:postcode":"95841",
    "addr:street":"Winding Way",
    "iso:country":"US",
    "sg:address":"4255 Winding Way",
    "sg:city":"Sacramento",
    "sg:classifiers":[
        {
            "category":"Shopping",
            "subcategory":"Florist",
            "type":"Retail Goods"
        }
    ],
    "sg:phone":"+1 916 716 2573",
    "sg:postcode":"95841",
    "sg:province":"CA",
    "wof:name":"Leecee",
    "wof:placetype":"venue"
},
  "geometry": {"coordinates":[-121.36109399999999,38.642012],"type":"Point"}
}