{
  "type": "Feature",
  "properties": {
    "iso:country":"US",
    "sg:address":"400 S 2nd Ave",
    "sg:city":"Barstow",
    "sg:classifiers":[
        {
            "category":"Professional",
            "subcategory":"Detective & Security Services",
            "type":"Services"
        }
    ],
    "sg:phone":"+1 760 256 9014",
    "sg:postcode":"92311",
    "sg:province":"CA",
    "sg:tags":[
        "investigator"
    ],
    "wof:name":"E J Simko Private Invstgtns",
    "wof:placetype":"venue"
},
  "geometry": {"coordinates":[-117.0262,34.89562],"type":"Point"}
}