{
  "type": "Feature",
  "properties": {
    "iso:country":"US",
    "sg:address":"12523 Califa St",
    "sg:city":"Valley Village",
    "sg:classifiers":[
        {
            "category":"Health Services",
            "subcategory":"Clinic",
            "type":"Services"
        }
    ],
    "sg:phone":"+1 818 761 3829",
    "sg:postcode":"91607",
    "sg:province":"CA",
    "sg:tags":[
        "home",
        "care"
    ],
    "wof:name":"Marys Home Care Inc",
    "wof:placetype":"venue"
},
  "geometry": {"coordinates":[-118.406953,34.177625],"type":"Point"}
}