{
  "type": "Feature",
  "properties": {
    "iso:country":"US",
    "sg:address":"930 Sunnyslope Rd",
    "sg:city":"Hollister",
    "sg:classifiers":[
        {
            "category":"Health Services",
            "subcategory":"Doctor",
            "type":"Services"
        }
    ],
    "sg:phone":"+1 831 637 9862",
    "sg:postcode":"95023",
    "sg:province":"CA",
    "sg:tags":[
        "physician",
        "surgeon"
    ],
    "wof:name":"John Bowman MD",
    "wof:placetype":"venue"
},
  "geometry": {"coordinates":[-121.38409,36.839143],"type":"Point"}
}