{
  "type": "Feature",
  "properties": {
    "addr:full":"5 Angwin Ave Angwin CA 94508",
    "addr:housenumber":"5",
    "addr:postcode":"94508",
    "addr:street":"Angwin Ave",
    "iso:country":"US",
    "sg:address":"5 Angwin Ave",
    "sg:city":"Angwin",
    "sg:classifiers":[
        {
            "category":"Government",
            "subcategory":"Post Office",
            "type":"Public Place"
        }
    ],
    "sg:phone":"+1 707 965 2272",
    "sg:postcode":"94508",
    "sg:province":"CA",
    "wof:name":"US Post Office",
    "wof:placetype":"venue"
},
  "geometry": {"coordinates":[-122.441491,38.57071],"type":"Point"}
}