{
  "type": "Feature",
  "properties": {
    "addr:full":"641 Broadway San Francisco CA 94133",
    "addr:housenumber":"641",
    "addr:postcode":"94133",
    "addr:street":"Broadway",
    "iso:country":"US",
    "sg:address":"641 Broadway",
    "sg:city":"San Francisco",
    "sg:classifiers":[
        {
            "category":"Food & Beverages",
            "subcategory":"Groceries & Convenience Stores",
            "type":"Retail Goods"
        }
    ],
    "sg:phone":"+1 415 398 3966",
    "sg:postcode":"94133",
    "sg:province":"CA",
    "wof:name":"ABC Supermarket",
    "wof:placetype":"venue"
},
  "geometry": {"coordinates":[-122.40780599999999,37.797622],"type":"Point"}
}