{
  "type": "Feature",
  "properties": {
    "addr:full":"1359 Dayton St Salinas CA 93901",
    "addr:housenumber":"1359",
    "addr:postcode":"93901",
    "addr:street":"Dayton St",
    "iso:country":"US",
    "sg:address":"1359 Dayton St",
    "sg:city":"Salinas",
    "sg:classifiers":[
        {
            "category":"Freight",
            "type":"Transportation"
        }
    ],
    "sg:phone":"+1 831 372 6222",
    "sg:postcode":"93901",
    "sg:province":"CA",
    "sg:tags":[
        "mover"
    ],
    "wof:name":"Paul Arpin",
    "wof:placetype":"venue"
},
  "geometry": {"coordinates":[-121.629615,36.648304],"type":"Point"}
}