{
  "type": "Feature",
  "properties": {
    "addr:full":"118 Florin St Pismo Beach CA 93449",
    "addr:housenumber":"118",
    "addr:postcode":"93449",
    "addr:street":"Florin St",
    "iso:country":"US",
    "sg:address":"118 Florin St",
    "sg:city":"Pismo Beach",
    "sg:classifiers":[
        {
            "category":"Home & Garden",
            "subcategory":"Building Materials",
            "type":"Retail Goods"
        }
    ],
    "sg:phone":"+1 805 773 3187",
    "sg:postcode":"93449",
    "sg:province":"CA",
    "wof:name":"Pacific Art Tile",
    "wof:placetype":"venue"
},
  "geometry": {"coordinates":[-120.69594600000001,35.171489],"type":"Point"}
}