{
  "type": "Feature",
  "properties": {
    "addr:full":"1528 El Camino Real Ste 309 San Mateo CA 94402",
    "addr:housenumber":"1528",
    "addr:postcode":"94402",
    "addr:street":"El Camino Real Ste 309",
    "iso:country":"US",
    "sg:address":"1528 El Camino Real Ste 309",
    "sg:city":"San Mateo",
    "sg:classifiers":[
        {
            "category":"Banks & Credit Unions",
            "subcategory":"Financial Services",
            "type":"Services"
        }
    ],
    "sg:phone":"+1 650 513 1511",
    "sg:postcode":"94402",
    "sg:province":"CA",
    "sg:website":"www.century21financialservices.com/",
    "wof:name":"Century 21 Financial Services",
    "wof:placetype":"venue"
},
  "geometry": {"coordinates":[-122.315792,37.553727],"type":"Point"}
}