{
  "type": "Feature",
  "properties": {
    "iso:country":"US",
    "sg:address":"720 E Latham Ave",
    "sg:city":"Hemet",
    "sg:classifiers":[
        {
            "category":"Health Services",
            "subcategory":"Nursing And Care Facility",
            "type":"Services"
        }
    ],
    "sg:phone":"+1 951 765 5005",
    "sg:postcode":"92543",
    "sg:province":"CA",
    "wof:name":"New Life Women's Health Ctr",
    "wof:placetype":"venue"
},
  "geometry": {"coordinates":[-116.964937,33.749479],"type":"Point"}
}