{
  "type": "Feature",
  "properties": {
    "iso:country":"US",
    "sg:address":"22473 Ferdinand Dr",
    "sg:city":"Salinas",
    "sg:classifiers":[
        {
            "category":"Travel",
            "subcategory":"Travel Agent",
            "type":"Entertainment"
        }
    ],
    "sg:phone":"+1 831 484 9866",
    "sg:postcode":"93908",
    "sg:province":"CA",
    "sg:tags":[
        "planning",
        "tournament",
        "golf",
        "booking"
    ],
    "sg:website":"http://www.corporategolfpros.com",
    "wof:name":"Corporate Golf Professionals",
    "wof:placetype":"venue"
},
  "geometry": {"coordinates":[-121.70053900000001,36.599911],"type":"Point"}
}