{
  "type": "Feature",
  "properties": {
    "addr:full":"5045 Calmview Ave Baldwin Park CA 91706",
    "addr:housenumber":"5045",
    "addr:postcode":"91706",
    "addr:street":"Calmview Ave",
    "iso:country":"US",
    "sg:address":"5045 Calmview Ave",
    "sg:city":"Baldwin Park",
    "sg:classifiers":[
        {
            "category":"Manufacturing",
            "subcategory":"Electronics",
            "type":"Manufacturing & Wholesale Goods"
        },
        {
            "category":"Manufacturing",
            "subcategory":"Tools & Machinery",
            "type":"Manufacturing & Wholesale Goods"
        }
    ],
    "sg:phone":"+1 626 338 7149",
    "sg:postcode":"91706",
    "sg:province":"CA",
    "sg:tags":[
        "shop",
        "industrial",
        "mfg",
        "m",
        "component",
        "machine",
        "aircraft",
        "electronic"
    ],
    "wof:name":"S and C Precision",
    "wof:placetype":"venue"
},
  "geometry": {"coordinates":[-117.947991,34.105888],"type":"Point"}
}