{
  "type": "Feature",
  "properties": {
    "addr:full":"7305 Pacific Blvd Huntington Park CA 90255",
    "addr:housenumber":"7305",
    "addr:postcode":"90255",
    "addr:street":"Pacific Blvd;Park",
    "iso:country":"US",
    "sg:address":"7305 Pacific Blvd",
    "sg:city":"Huntington Park",
    "sg:classifiers":[
        {
            "category":"Health Services",
            "subcategory":"Health Practitioner",
            "type":"Services"
        }
    ],
    "sg:phone":"+1 310 973 8681",
    "sg:postcode":"90255",
    "sg:province":"CA",
    "sg:tags":[
        "psychologist"
    ],
    "wof:name":"Mater Dei Sleep Diagnostic Ctr",
    "wof:placetype":"venue"
},
  "geometry": {"coordinates":[-118.225286,33.972537],"type":"Point"}
}