{
  "type": "Feature",
  "properties": {
    "addr:full":"200 S Lena Rd San Bernardino CA 92408",
    "addr:housenumber":"200",
    "addr:postcode":"92408",
    "addr:street":"S Lena Rd",
    "iso:country":"US",
    "sg:address":"200 S Lena Rd",
    "sg:city":"San Bernardino",
    "sg:classifiers":[
        {
            "category":"Government",
            "subcategory":"Office",
            "type":"Public Place"
        }
    ],
    "sg:phone":"+1 909 387 2200",
    "sg:postcode":"92408",
    "sg:province":"CA",
    "wof:name":"San Bernardino Scientific",
    "wof:placetype":"venue"
},
  "geometry": {"coordinates":[-117.269429,34.099329],"type":"Point"}
}