{
  "type": "Feature",
  "properties": {
    "addr:full":"1510 4th St Berkeley CA 94710",
    "addr:housenumber":"1510",
    "addr:postcode":"94710",
    "addr:street":"4Th St",
    "iso:country":"US",
    "sg:address":"1510 4th St",
    "sg:city":"Berkeley",
    "sg:classifiers":[
        {
            "category":"Professional",
            "subcategory":"Management & Consulting",
            "type":"Services"
        }
    ],
    "sg:phone":"+1 510 528 8008",
    "sg:postcode":"94710",
    "sg:province":"CA",
    "sg:tags":[
        "consultant",
        "educational"
    ],
    "wof:name":"FMK & Assoc",
    "wof:placetype":"venue"
},
  "geometry": {"coordinates":[-122.30196100000001,37.873812],"type":"Point"}
}