{
  "type": "Feature",
  "properties": {
    "iso:country":"US",
    "sg:address":"162 Evergreen Way",
    "sg:city":"Milpitas",
    "sg:classifiers":[
        {
            "category":"Professional",
            "subcategory":"Management & Consulting",
            "type":"Services"
        }
    ],
    "sg:phone":"+1 408 263 6986",
    "sg:postcode":"95035",
    "sg:province":"CA",
    "sg:tags":[
        "home",
        "demonstration"
    ],
    "wof:name":"Amway Distributors",
    "wof:placetype":"venue"
},
  "geometry": {"coordinates":[-121.906989,37.409975],"type":"Point"}
}