{
  "type": "Feature",
  "properties": {
    "iso:country":"US",
    "sg:address":"8720 Firestone Blvd",
    "sg:city":"Downey",
    "sg:classifiers":[
        {
            "category":"Autos & Motor Vehicles",
            "subcategory":"Automobile Sales",
            "type":"Retail Goods"
        }
    ],
    "sg:phone":"+1 562 861 7689",
    "sg:postcode":"90241",
    "sg:province":"CA",
    "sg:tags":[
        "automotive"
    ],
    "wof:name":"Premium Truck & Auto Sales",
    "wof:placetype":"venue"
},
  "geometry": {"coordinates":[-118.125999,33.936501],"type":"Point"}
}