{
  "type": "Feature",
  "properties": {
    "iso:country":"US",
    "sg:address":"16321 S Broadway St",
    "sg:city":"Gardena",
    "sg:classifiers":[
        {
            "category":"Professional",
            "subcategory":"Business Services",
            "type":"Services"
        }
    ],
    "sg:phone":"+1 310 324 4658",
    "sg:postcode":"90248",
    "sg:province":"CA",
    "sg:tags":[
        "glass"
    ],
    "wof:name":"Advanced Glass",
    "wof:placetype":"venue"
},
  "geometry": {"coordinates":[-118.27843799999999,33.885304],"type":"Point"}
}