{
  "type": "Feature",
  "properties": {
    "iso:country":"US",
    "sg:address":"5435 Scotts Valley Dr",
    "sg:city":"Scotts Valley",
    "sg:classifiers":[
        {
            "category":"Travel",
            "subcategory":"Travel Agent",
            "type":"Entertainment"
        }
    ],
    "sg:phone":"+1 831 438 6663",
    "sg:postcode":"95066",
    "sg:province":"CA",
    "sg:tags":[
        "agency",
        "bureau"
    ],
    "wof:name":"Cruise & Travel Store",
    "wof:placetype":"venue"
},
  "geometry": {"coordinates":[-122.009692,37.059559],"type":"Point"}
}