{
  "type": "Feature",
  "properties": {
    "iso:country":"US",
    "sg:address":"3211 Santa Fe Ave",
    "sg:city":"Long Beach",
    "sg:classifiers":[
        {
            "category":"Organizations",
            "subcategory":"Religious Organization",
            "type":"Services"
        }
    ],
    "sg:phone":"+1 562 427 5290",
    "sg:postcode":"90810",
    "sg:province":"CA",
    "wof:name":"Fountain Of Life",
    "wof:placetype":"venue"
},
  "geometry": {"coordinates":[-118.215681,33.815842],"type":"Point"}
}