{
  "type": "Feature",
  "properties": {
    "addr:full":"19142 Beach Blvd Ste Z Huntington Beach CA 92648",
    "addr:housenumber":"19142",
    "addr:postcode":"92648",
    "addr:street":"Beach Blvd Ste Z",
    "iso:country":"US",
    "sg:address":"19142 Beach Blvd Ste Z",
    "sg:city":"Huntington Beach",
    "sg:classifiers":[
        {
            "category":"Personal",
            "subcategory":"Massage",
            "type":"Services"
        }
    ],
    "sg:phone":"+1 714 968 9680",
    "sg:postcode":"92648",
    "sg:province":"CA",
    "sg:website":"www.mypuresole.com",
    "wof:name":"Pure Sole",
    "wof:placetype":"venue"
},
  "geometry": {"coordinates":[-117.988603,33.684534],"type":"Point"}
}