{
  "type": "Feature",
  "properties": {
    "iso:country":"US",
    "sg:address":"433 E Alondra Blvd",
    "sg:city":"Gardena",
    "sg:classifiers":[
        {
            "category":"Restaurant",
            "type":"Food & Drink"
        }
    ],
    "sg:phone":"+1 310 538 3887",
    "sg:postcode":"90248",
    "sg:province":"CA",
    "sg:tags":[
        "mexican"
    ],
    "sg:website":"www.tacosymariscoseltaurino.com",
    "wof:name":"Tacos Y Mariscos El Taurino",
    "wof:placetype":"venue"
},
  "geometry": {"coordinates":[-118.268411,33.886749],"type":"Point"}
}