{
  "type": "Feature",
  "properties": {
    "iso:country":"US",
    "sg:address":"5091 G St",
    "sg:city":"Chino",
    "sg:classifiers":[
        {
            "category":"Manufacturing",
            "subcategory":"Metals",
            "type":"Manufacturing & Wholesale Goods"
        }
    ],
    "sg:phone":"+1 909 902 5200",
    "sg:postcode":"91710",
    "sg:province":"CA",
    "sg:tags":[
        "stamping"
    ],
    "sg:website":"www.hpwetmore.com",
    "wof:name":"California Associated Products",
    "wof:placetype":"venue"
},
  "geometry": {"coordinates":[-117.69595099999999,34.009828],"type":"Point"}
}