{
  "type": "Feature",
  "properties": {
    "addr:full":"4510 Peralta Blvd Fremont CA 94536",
    "addr:housenumber":"4510",
    "addr:postcode":"94536",
    "addr:street":"Peralta Blvd",
    "iso:country":"US",
    "sg:address":"4510 Peralta Blvd",
    "sg:city":"Fremont",
    "sg:classifiers":[
        {
            "category":"Banks & Credit Unions",
            "subcategory":"Bank",
            "type":"Services"
        }
    ],
    "sg:phone":"+1 510 818 0903",
    "sg:postcode":"94536",
    "sg:province":"CA",
    "sg:tags":[
        "broker",
        "mortgage"
    ],
    "wof:name":"Atlas Financial Services",
    "wof:placetype":"venue"
},
  "geometry": {"coordinates":[-122.010251,37.552466],"type":"Point"}
}