{
  "type": "Feature",
  "properties": {
    "iso:country":"US",
    "sg:address":"1628 Crow Ct",
    "sg:city":"Sunnyvale",
    "sg:classifiers":[
        {
            "category":"Professional",
            "type":"Services"
        }
    ],
    "sg:phone":"+1 408 736 7170",
    "sg:postcode":"94087",
    "sg:province":"CA",
    "sg:tags":[
        "establishment"
    ],
    "wof:name":"Heathers World",
    "wof:placetype":"venue"
},
  "geometry": {"coordinates":[-122.026771,37.340354],"type":"Point"}
}