{
  "type": "Feature",
  "properties": {
    "iso:country":"US",
    "sg:address":"2459 E Florida Ave",
    "sg:city":"Hemet",
    "sg:classifiers":[
        {
            "category":"Real Estate",
            "subcategory":"Real Estate Agent",
            "type":"Services"
        }
    ],
    "sg:phone":"+1 951 929 3121",
    "sg:postcode":"92544",
    "sg:province":"CA",
    "wof:name":"Century 21",
    "wof:placetype":"venue"
},
  "geometry": {"coordinates":[-116.94563,33.747675],"type":"Point"}
}