{
  "type": "Feature",
  "properties": {
    "iso:country":"US",
    "sg:address":"10324 Northvale Rd",
    "sg:city":"Los Angeles",
    "sg:classifiers":[
        {
            "category":"Wholesale",
            "subcategory":"Medical Equipment & Supplies",
            "type":"Manufacturing & Wholesale Goods"
        }
    ],
    "sg:phone":"+1 310 287 0319",
    "sg:postcode":"90064",
    "sg:province":"CA",
    "sg:tags":[
        "wholesaler"
    ],
    "wof:name":"Max Medical Inc",
    "wof:placetype":"venue"
},
  "geometry": {"coordinates":[-118.41203,34.033114],"type":"Point"}
}