{
  "type": "Feature",
  "properties": {
    "addr:full":"27440 Hawthorne Blvd Fl 1 Rolling Hills Estates CA 90274",
    "addr:housenumber":"27440;1",
    "addr:postcode":"90274",
    "addr:street":"Hawthorne Blvd Fl",
    "iso:country":"US",
    "sg:address":"27440 Hawthorne Blvd Fl 1",
    "sg:city":"Rolling Hills Estates",
    "sg:classifiers":[
        {
            "category":"Health Services",
            "subcategory":"Health Practitioner",
            "type":"Services"
        }
    ],
    "sg:phone":"+1 626 330 6028",
    "sg:postcode":"90274",
    "sg:province":"CA",
    "sg:tags":[
        "acupuncture"
    ],
    "wof:name":"T C M Acupuncture Healing Center",
    "wof:placetype":"venue"
},
  "geometry": {"coordinates":[-118.37695100000001,33.776152],"type":"Point"}
}