{
  "type": "Feature",
  "properties": {
    "iso:country":"US",
    "sg:address":"38733 9th St E",
    "sg:city":"Palmdale",
    "sg:classifiers":[
        {
            "category":"Real Estate",
            "subcategory":"Real Estate Agent",
            "type":"Services"
        }
    ],
    "sg:phone":"+1 661 266 2706",
    "sg:postcode":"93550",
    "sg:province":"CA",
    "wof:name":"T & T Real Estate & Loans",
    "wof:placetype":"venue"
},
  "geometry": {"coordinates":[-118.114395,34.584647],"type":"Point"}
}