{
  "type": "Feature",
  "properties": {
    "addr:full":"10116 Topanga Canyon Blvd Chatsworth CA 91311",
    "addr:housenumber":"10116",
    "addr:postcode":"91311",
    "addr:street":"Topanga Canyon Blvd",
    "iso:country":"US",
    "sg:address":"10116 Topanga Canyon Blvd",
    "sg:city":"Chatsworth",
    "sg:classifiers":[
        {
            "category":"Health Services",
            "subcategory":"Health Practitioner",
            "type":"Services"
        }
    ],
    "sg:phone":"+1 818 576 9944",
    "sg:postcode":"91311",
    "sg:province":"CA",
    "sg:tags":[
        "acupuncture"
    ],
    "wof:name":"Gung Ho Cho",
    "wof:placetype":"venue"
},
  "geometry": {"coordinates":[-118.605892,34.254791],"type":"Point"}
}