{
  "type": "Feature",
  "properties": {
    "iso:country":"US",
    "sg:address":"2268 Minaret Dr",
    "sg:city":"Martinez",
    "sg:classifiers":[
        {
            "category":"Wholesale",
            "subcategory":"Machinery & Supplies",
            "type":"Manufacturing & Wholesale Goods"
        }
    ],
    "sg:phone":"+1 925 229 4030",
    "sg:postcode":"94553",
    "sg:province":"CA",
    "sg:tags":[
        "spraying",
        "equipment"
    ],
    "wof:name":"Air Plus Purification",
    "wof:placetype":"venue"
},
  "geometry": {"coordinates":[-122.080815,37.986494],"type":"Point"}
}