{
  "type": "Feature",
  "properties": {
    "addr:full":"25490 Flanders Dr Carmel CA 93923",
    "addr:housenumber":"25490",
    "addr:postcode":"93923",
    "addr:street":"Flanders Dr",
    "iso:country":"US",
    "sg:address":"25490 Flanders Dr",
    "sg:city":"Carmel",
    "sg:classifiers":[
        {
            "category":"Personal",
            "subcategory":"Massage",
            "type":"Services"
        }
    ],
    "sg:phone":"+1 831 917 9373",
    "sg:postcode":"93923",
    "sg:province":"CA",
    "sg:website":"massagecarmel.com#cid=yelp",
    "wof:name":"Carmel Massage",
    "wof:placetype":"venue"
},
  "geometry": {"coordinates":[-121.907466,36.553985],"type":"Point"}
}