{
  "type": "Feature",
  "properties": {
    "addr:full":"1010 Crenshaw Blvd Torrance CA 90501",
    "addr:housenumber":"1010",
    "addr:postcode":"90501",
    "addr:street":"Crenshaw Blvd",
    "iso:country":"US",
    "sg:address":"1010 Crenshaw Blvd",
    "sg:city":"Torrance",
    "sg:classifiers":[
        {
            "category":"Professional",
            "subcategory":"Business Services",
            "type":"Services"
        }
    ],
    "sg:phone":"+1 310 782 8628",
    "sg:postcode":"90501",
    "sg:province":"CA",
    "sg:tags":[
        "broker",
        "merchandise"
    ],
    "wof:name":"THG Homeloan Brokerage",
    "wof:placetype":"venue"
},
  "geometry": {"coordinates":[-118.328587,33.836427],"type":"Point"}
}