{
  "type": "Feature",
  "properties": {
    "addr:full":"376 D St Davis CA 95616",
    "addr:housenumber":"376",
    "addr:postcode":"95616",
    "addr:street":"D St",
    "iso:country":"US",
    "sg:address":"376 D St",
    "sg:city":"Davis",
    "sg:classifiers":[
        {
            "category":"Shopping",
            "subcategory":"Gifts & Souvenirs",
            "type":"Retail Goods"
        }
    ],
    "sg:phone":"+1 530 758 5856",
    "sg:postcode":"95616",
    "sg:province":"CA",
    "wof:name":"Babys First Cry",
    "wof:placetype":"venue"
},
  "geometry": {"coordinates":[-121.742566,38.544642],"type":"Point"}
}