{
  "type": "Feature",
  "properties": {
    "iso:country":"US",
    "sg:address":"97 S 2nd St",
    "sg:city":"San Jose",
    "sg:classifiers":[
        {
            "category":"Restaurant",
            "type":"Food & Drink"
        }
    ],
    "sg:phone":"+1 408 297 0230",
    "sg:postcode":"95113",
    "sg:province":"CA",
    "wof:name":"Panda Computer Svc",
    "wof:placetype":"venue"
},
  "geometry": {"coordinates":[-121.889181,37.336146],"type":"Point"}
}