{
  "type": "Feature",
  "properties": {
    "iso:country":"US",
    "sg:address":"5044 Royal Palm Dr",
    "sg:city":"Fremont",
    "sg:classifiers":[
        {
            "category":"Professional",
            "type":"Services"
        }
    ],
    "sg:phone":"+1 510 468 1381",
    "sg:postcode":"94538",
    "sg:province":"CA",
    "wof:name":"Eric Lu",
    "wof:placetype":"venue"
},
  "geometry": {"coordinates":[-121.99556200000001,37.533952],"type":"Point"}
}