{
  "type": "Feature",
  "properties": {
    "iso:country":"US",
    "sg:address":"21755 Ventura Blvd",
    "sg:city":"Woodland Hills",
    "sg:classifiers":[
        {
            "category":"Retail",
            "subcategory":"Veterinary Services",
            "type":"Services"
        }
    ],
    "sg:phone":"+1 818 710 9898",
    "sg:postcode":"91364",
    "sg:province":"CA",
    "wof:name":"New Leash On Life Anmal Rescue",
    "wof:placetype":"venue"
},
  "geometry": {"coordinates":[-118.601455,34.168408],"type":"Point"}
}