{
  "type": "Feature",
  "properties": {
    "iso:country":"US",
    "sg:address":"334 Monterey St",
    "sg:city":"Salinas",
    "sg:classifiers":[
        {
            "category":"Organizations",
            "subcategory":"Labor Organization",
            "type":"Services"
        }
    ],
    "sg:phone":"+1 831 757 2061",
    "sg:postcode":"93901",
    "sg:province":"CA",
    "wof:name":"Service Employee's Local 817",
    "wof:placetype":"venue"
},
  "geometry": {"coordinates":[-121.653722,36.673801],"type":"Point"}
}