{
  "type": "Feature",
  "properties": {
    "iso:country":"US",
    "sg:address":"8383 Wilshire Blvd",
    "sg:city":"Beverly Hills",
    "sg:classifiers":[
        {
            "category":"Building & Trades",
            "subcategory":"Construction",
            "type":"Services"
        }
    ],
    "sg:phone":"+1 323 655 7330",
    "sg:postcode":"90211",
    "sg:province":"CA",
    "sg:tags":[
        "operative",
        "builder",
        "financing",
        "mortgage",
        "escrow"
    ],
    "sg:website":"www.shapell.com",
    "wof:name":"S & S Construction Co",
    "wof:placetype":"venue"
},
  "geometry": {"coordinates":[-118.373314,34.064543],"type":"Point"}
}