{
  "type": "Feature",
  "properties": {
    "iso:country":"US",
    "sg:address":"305 N Harbor Blvd",
    "sg:city":"Fullerton",
    "sg:classifiers":[
        {
            "category":"Real Estate",
            "subcategory":"Real Estate Operator",
            "type":"Services"
        }
    ],
    "sg:phone":"+1 714 639 5353",
    "sg:postcode":"92832",
    "sg:province":"CA",
    "sg:tags":[
        "apartment"
    ],
    "wof:name":"Orange Meadows Apartments",
    "wof:placetype":"venue"
},
  "geometry": {"coordinates":[-117.924004,33.872501],"type":"Point"}
}