{
  "type": "Feature",
  "properties": {
    "addr:full":"3269 N San Fernando Rd Los Angeles CA 90065",
    "addr:housenumber":"3269",
    "addr:postcode":"90065",
    "addr:street":"N San Fernando Rd",
    "iso:country":"US",
    "sg:address":"3269 N San Fernando Rd",
    "sg:city":"Los Angeles",
    "sg:classifiers":[
        {
            "category":"Shopping",
            "subcategory":"Gifts & Souvenirs",
            "type":"Retail Goods"
        }
    ],
    "sg:phone":"+1 323 254 4300",
    "sg:postcode":"90065",
    "sg:province":"CA",
    "sg:tags":[
        "party",
        "supply"
    ],
    "wof:name":"Five Star Party Rental",
    "wof:placetype":"venue"
},
  "geometry": {"coordinates":[-118.24879799999999,34.117637],"type":"Point"}
}