{
  "type": "Feature",
  "properties": {
    "iso:country":"US",
    "sg:address":"3269 N San Fernando Rd",
    "sg:city":"Los Angeles",
    "sg:classifiers":[
        {
            "category":"Shopping",
            "subcategory":"Gifts & Souvenirs",
            "type":"Retail Goods"
        }
    ],
    "sg:phone":"+1 323 254 4300",
    "sg:postcode":"90065",
    "sg:province":"CA",
    "sg:tags":[
        "party",
        "supply"
    ],
    "wof:name":"Five Star Party Rental",
    "wof:placetype":"venue"
},
  "geometry": {"coordinates":[-118.248798,34.117637],"type":"Point"}
}