{
  "type": "Feature",
  "properties": {
    "iso:country":"US",
    "sg:address":"8801 Folsom Blvd",
    "sg:city":"Sacramento",
    "sg:classifiers":[
        {
            "category":"Professional",
            "type":"Services"
        },
        {
            "category":"Professional",
            "subcategory":"Accounting & Tax Preparation",
            "type":"Services"
        }
    ],
    "sg:phone":"+1 916 383 8100",
    "sg:postcode":"95826",
    "sg:province":"CA",
    "sg:tags":[
        "accountant"
    ],
    "wof:name":"McGovern Planesi & Walters LLP",
    "wof:placetype":"venue"
},
  "geometry": {"coordinates":[-121.375386,38.553019],"type":"Point"}
}