{
  "type": "Feature",
  "properties": {
    "addr:full":"34475 Madera de Playa Temecula CA 92592",
    "addr:housenumber":"34475",
    "addr:postcode":"92592",
    "addr:street":"Madera De Playa",
    "iso:country":"US",
    "sg:address":"34475 Madera de Playa",
    "sg:city":"Temecula",
    "sg:classifiers":[
        {
            "category":"Manufacturing",
            "subcategory":"Motor Vehicles & Parts",
            "type":"Manufacturing & Wholesale Goods"
        }
    ],
    "sg:phone":"+1 951 852 0469",
    "sg:postcode":"92592",
    "sg:province":"CA",
    "sg:tags":[
        "mfg"
    ],
    "wof:name":"Rampage Products LLC",
    "wof:placetype":"venue"
},
  "geometry": {"coordinates":[-117.06006499999999,33.521757],"type":"Point"}
}