{
  "type": "Feature",
  "properties": {
    "iso:country":"US",
    "sg:address":"945 Margaret St",
    "sg:city":"Monterey",
    "sg:classifiers":[
        {
            "category":"Building & Trades",
            "subcategory":"Construction",
            "type":"Services"
        }
    ],
    "sg:phone":"+1 831 373 2146",
    "sg:postcode":"93940",
    "sg:province":"CA",
    "sg:tags":[
        "tile",
        "dealer"
    ],
    "wof:name":"Giovanni Tile & Marble",
    "wof:placetype":"venue"
},
  "geometry": {"coordinates":[-121.902562,36.604219],"type":"Point"}
}