{
  "type": "Feature",
  "properties": {
    "iso:country":"US",
    "sg:address":"8805 Duncanson Dr",
    "sg:city":"Bakersfield",
    "sg:classifiers":[
        {
            "category":"Wholesale",
            "subcategory":"Hardware",
            "type":"Manufacturing & Wholesale Goods"
        }
    ],
    "sg:phone":"+1 661 664 3960",
    "sg:postcode":"93311",
    "sg:province":"CA",
    "sg:tags":[
        "equipment",
        "energy",
        "solar"
    ],
    "wof:name":"A E Resources",
    "wof:placetype":"venue"
},
  "geometry": {"coordinates":[-119.09943699999999,35.318222],"type":"Point"}
}