{
  "type": "Feature",
  "properties": {
    "iso:country":"US",
    "sg:address":"1499 Bayshore Hwy Ste 133",
    "sg:city":"Burlingame",
    "sg:classifiers":[
        {
            "category":"Communications",
            "subcategory":"Newspaper",
            "type":"Services"
        },
        {
            "category":"Professional",
            "subcategory":"Art Services",
            "type":"Services"
        },
        {
            "category":"Communications",
            "type":"Services"
        }
    ],
    "sg:phone":"+1 650 425 7486",
    "sg:postcode":"94010",
    "sg:province":"CA",
    "sg:tags":[
        "web",
        "graphic",
        "design",
        "advertising"
    ],
    "sg:website":"www.saetta.com",
    "wof:name":"Saetta Media Group",
    "wof:placetype":"venue"
},
  "geometry": {"coordinates":[-122.36660000000001,37.597092],"type":"Point"}
}