{
  "type": "Feature",
  "properties": {
    "addr:full":"7605 Old Dominion Court Aptos CA 95003",
    "addr:housenumber":"7605",
    "addr:postcode":"ca 95003",
    "addr:street":"Old Dominion Court",
    "iso:country":"US",
    "sg:address":"7605 Old Dominion Court",
    "sg:city":"Aptos",
    "sg:classifiers":[
        {
            "category":"Real Estate",
            "subcategory":"Real Estate Services",
            "type":"Services"
        },
        {
            "category":"Banks & Credit Unions",
            "subcategory":"Financial Services",
            "type":"Services"
        }
    ],
    "sg:phone":"+1 831 688 3088",
    "sg:postcode":"95003",
    "sg:province":"CA",
    "sg:tags":[
        "broker",
        "mortgage"
    ],
    "sg:website":"www.cypressmortgageca.com",
    "wof:name":"Cypress Mortgage",
    "wof:placetype":"venue"
},
  "geometry": {"coordinates":[-121.909836,36.978987],"type":"Point"}
}