{
  "type": "Feature",
  "properties": {
    "addr:full":"4000 Lake Tahoe Blvd South Lake Tahoe CA 96150",
    "addr:housenumber":"4000",
    "addr:postcode":"96150",
    "addr:street":"Lake Tahoe Blvd",
    "iso:country":"US",
    "sg:address":"4000 Lake Tahoe Blvd",
    "sg:city":"South Lake Tahoe",
    "sg:classifiers":[
        {
            "category":"Restaurant",
            "type":"Food & Drink"
        },
        {
            "category":"Food & Beverages",
            "subcategory":"Fruits & Vegetables",
            "type":"Retail Goods"
        }
    ],
    "sg:menulink":"http://www.allmenus.com/ca/south-lake-tahoe/135712-jamba-juice/menu/",
    "sg:phone":"+1 530 544 8890",
    "sg:postcode":"96150",
    "sg:province":"CA",
    "sg:tags":[
        "smoothy",
        "juice",
        "american"
    ],
    "wof:name":"Jamba Juice",
    "wof:placetype":"venue"
},
  "geometry": {"coordinates":[-119.944621,38.955352],"type":"Point"}
}