{
  "type": "Feature",
  "properties": {
    "iso:country":"US",
    "sg:address":"5692 Fontaine St",
    "sg:city":"San Diego",
    "sg:classifiers":[
        {
            "category":"Building & Trades",
            "subcategory":"Electrical",
            "type":"Services"
        }
    ],
    "sg:phone":"+1 619 582 3812",
    "sg:postcode":"92120",
    "sg:province":"CA",
    "sg:tags":[
        "electrical",
        "contractor"
    ],
    "wof:name":"Mjc Electric Inc",
    "wof:placetype":"venue"
},
  "geometry": {"coordinates":[-117.070316,32.802358],"type":"Point"}
}