{
  "type": "Feature",
  "properties": {
    "iso:country":"US",
    "sg:address":"1615 Hill Rd",
    "sg:city":"Novato",
    "sg:classifiers":[
        {
            "category":"Health Services",
            "subcategory":"Doctor",
            "type":"Services"
        }
    ],
    "sg:phone":"+1 415 479 8642",
    "sg:postcode":"94947",
    "sg:province":"CA",
    "sg:tags":[
        "physician",
        "surgeon"
    ],
    "wof:name":"Angelle Ferrell MD",
    "wof:placetype":"venue"
},
  "geometry": {"coordinates":[-122.57814,38.097285],"type":"Point"}
}