{
  "type": "Feature",
  "properties": {
    "addr:full":"140 Vintage Way Novato CA 94945",
    "addr:housenumber":"140",
    "addr:postcode":"94945",
    "addr:street":"Vintage Way",
    "iso:country":"US",
    "sg:address":"140 Vintage Way",
    "sg:city":"Novato",
    "sg:classifiers":[
        {
            "category":"Restaurant",
            "type":"Food & Drink"
        }
    ],
    "sg:menulink":"http://www.allmenus.com/ca/northeast-marin/51739-pasta-pomodoro/menu/",
    "sg:phone":"+1 415 899 1861",
    "sg:postcode":"94945",
    "sg:province":"CA",
    "sg:tags":[
        "italian"
    ],
    "wof:name":"Pasta Pomodoro",
    "wof:placetype":"venue"
},
  "geometry": {"coordinates":[-122.55636699999999,38.092162],"type":"Point"}
}