{
  "type": "Feature",
  "properties": {
    "iso:country":"US",
    "sg:address":"2246 Cam Ramon",
    "sg:city":"San Ramon",
    "sg:classifiers":[
        {
            "category":"Manufacturing",
            "subcategory":"Tools & Machinery",
            "type":"Manufacturing & Wholesale Goods"
        }
    ],
    "sg:phone":"+1 925 355 0750",
    "sg:postcode":"94583",
    "sg:province":"CA",
    "sg:tags":[
        "physician",
        "surgeon"
    ],
    "sg:website":"www.ttimedical.com",
    "wof:name":"Tti Medical",
    "wof:placetype":"venue"
},
  "geometry": {"coordinates":[-121.966088,37.77552],"type":"Point"}
}