{
  "type": "Feature",
  "properties": {
    "iso:country":"US",
    "sg:address":"805 Talbot Ave",
    "sg:city":"Albany",
    "sg:classifiers":[
        {
            "category":"Building & Trades",
            "subcategory":"Construction",
            "type":"Services"
        }
    ],
    "sg:phone":"+1 510 527 0171",
    "sg:postcode":"94706",
    "sg:province":"CA",
    "sg:tags":[
        "contractor"
    ],
    "wof:name":"J Ronald Thompson Masonry",
    "wof:placetype":"venue"
},
  "geometry": {"coordinates":[-122.295339,37.89057],"type":"Point"}
}