{
  "type": "Feature",
  "properties": {
    "addr:full":"2424 Dwight Way Berkeley CA 94704",
    "addr:housenumber":"2424",
    "addr:postcode":"94704",
    "addr:street":"Dwight Way",
    "iso:country":"US",
    "sg:address":"2424 Dwight Way",
    "sg:city":"Berkeley",
    "sg:classifiers":[
        {
            "category":"Social Services",
            "type":"Services"
        }
    ],
    "sg:phone":"+1 510 843 2424",
    "sg:postcode":"94704",
    "sg:province":"CA",
    "sg:tags":[
        "counselor",
        "marriage",
        "family"
    ],
    "wof:name":"Jim Moyers",
    "wof:placetype":"venue"
},
  "geometry": {"coordinates":[-122.259044,37.864985],"type":"Point"}
}