{
  "type": "Feature",
  "properties": {
    "iso:country":"US",
    "sg:address":"1944 Gardena Ave",
    "sg:city":"Glendale",
    "sg:classifiers":[
        {
            "category":"Building & Trades",
            "subcategory":"Plumbing",
            "type":"Services"
        }
    ],
    "sg:phone":"+1 818 246 7191",
    "sg:postcode":"91204",
    "sg:province":"CA",
    "sg:tags":[
        "conditioning",
        "air",
        "system",
        "contractor"
    ],
    "wof:name":"Renkow Mechanical Inc",
    "wof:placetype":"venue"
},
  "geometry": {"coordinates":[-118.254098,34.119978],"type":"Point"}
}