{
  "type": "Feature",
  "properties": {
    "iso:country":"US",
    "sg:address":"870 S Larch Ave",
    "sg:city":"Rialto",
    "sg:classifiers":[
        {
            "category":"Freight",
            "type":"Transportation"
        }
    ],
    "sg:phone":"+1 909 875 4710",
    "sg:postcode":"92376",
    "sg:province":"CA",
    "sg:tags":[
        "operator",
        "local",
        "trucking"
    ],
    "wof:name":"Leo S Trucking",
    "wof:placetype":"venue"
},
  "geometry": {"coordinates":[-117.392208,34.08604],"type":"Point"}
}