{
  "type": "Feature",
  "properties": {
    "addr:full":"13318 Valleyheart Dr Sherman Oaks CA 91423",
    "addr:housenumber":"13318",
    "addr:postcode":"91423",
    "addr:street":"Valleyheart Dr",
    "iso:country":"US",
    "sg:address":"13318 Valleyheart Dr",
    "sg:city":"Sherman Oaks",
    "sg:classifiers":[
        {
            "category":"Professional",
            "type":"Services"
        }
    ],
    "sg:phone":"+1 818 784 7312",
    "sg:postcode":"91423",
    "sg:province":"CA",
    "sg:tags":[
        "establishment"
    ],
    "wof:name":"Encino Descanso Valleyheart",
    "wof:placetype":"venue"
},
  "geometry": {"coordinates":[-118.423134,34.151602],"type":"Point"}
}