{
  "type": "Feature",
  "properties": {
    "addr:full":"1345 N Grand Ave Walnut CA 91789",
    "addr:housenumber":"1345",
    "addr:postcode":"91789",
    "addr:street":"N Grand Ave",
    "iso:country":"US",
    "sg:address":"1345 N Grand Ave",
    "sg:city":"Walnut",
    "sg:classifiers":[
        {
            "category":"Personal",
            "subcategory":"Beauty Salon",
            "type":"Services"
        }
    ],
    "sg:phone":"+1 909 595 8459",
    "sg:postcode":"91789",
    "sg:province":"CA",
    "wof:name":"Angel",
    "wof:placetype":"venue"
},
  "geometry": {"coordinates":[-117.84923999999999,34.045935],"type":"Point"}
}