{
  "type": "Feature",
  "properties": {
    "addr:full":"12219 Meadow View Way Rough And Ready CA 95975",
    "addr:housenumber":"12219",
    "addr:postcode":"95975",
    "addr:street":"Meadow View Way",
    "iso:country":"US",
    "sg:address":"12219 Meadow View Way",
    "sg:city":"Rough And Ready",
    "sg:classifiers":[
        {
            "category":"Building & Trades",
            "subcategory":"Construction",
            "type":"Services"
        }
    ],
    "sg:phone":"+1 530 432 2269",
    "sg:postcode":"95975",
    "sg:province":"CA",
    "sg:tags":[
        "home",
        "builder"
    ],
    "wof:name":"Franzen Construction Co",
    "wof:placetype":"venue"
},
  "geometry": {"coordinates":[-121.159109,39.24504],"type":"Point"}
}