{
  "type": "Feature",
  "properties": {
    "addr:full":"3231 D St Hayward CA 94541",
    "addr:housenumber":"3231",
    "addr:postcode":"94541",
    "addr:street":"D St",
    "iso:country":"US",
    "sg:address":"3231 D St",
    "sg:city":"Hayward",
    "sg:classifiers":[
        {
            "category":"Health Services",
            "subcategory":"Clinic",
            "type":"Services"
        }
    ],
    "sg:phone":"+1 510 881 9129",
    "sg:postcode":"94541",
    "sg:province":"CA",
    "sg:tags":[
        "home"
    ],
    "wof:name":"Bassard's Young Adult Board",
    "wof:placetype":"venue"
},
  "geometry": {"coordinates":[-122.047883,37.680006],"type":"Point"}
}