{
  "type": "Feature",
  "properties": {
    "addr:full":"750 Lakeway Dr Sunnyvale CA 94085",
    "addr:housenumber":"750",
    "addr:postcode":"94085",
    "addr:street":"Lakeway Dr",
    "iso:country":"US",
    "sg:address":"750 Lakeway Dr",
    "sg:city":"Sunnyvale",
    "sg:classifiers":[
        {
            "category":"Travel",
            "subcategory":"Hotels & Motels",
            "type":"Entertainment"
        }
    ],
    "sg:phone":"+1 408 720 1000",
    "sg:postcode":"94085",
    "sg:province":"CA",
    "wof:name":"Residence Inn Silicon Valley I",
    "wof:placetype":"venue"
},
  "geometry": {"coordinates":[-121.988197,37.387398],"type":"Point"}
}