{
  "type": "Feature",
  "properties": {
    "addr:full":"110 2nd St Eureka CA 95501",
    "addr:housenumber":"110",
    "addr:postcode":"95501",
    "addr:street":"2Nd St",
    "iso:country":"US",
    "sg:address":"110 2nd St",
    "sg:city":"Eureka",
    "sg:classifiers":[
        {
            "category":"Social Services",
            "type":"Services"
        }
    ],
    "sg:phone":"+1 707 443 4551",
    "sg:postcode":"95501",
    "sg:province":"CA",
    "sg:tags":[
        "organization",
        "welfare"
    ],
    "wof:name":"Eureka Rescue Mission",
    "wof:placetype":"venue"
},
  "geometry": {"coordinates":[-124.170619,40.80372],"type":"Point"}
}