{
  "type": "Feature",
  "properties": {
    "iso:country":"US",
    "sg:address":"3137 Telegraph Ave",
    "sg:city":"Oakland",
    "sg:classifiers":[
        {
            "category":"Professional",
            "type":"Services"
        }
    ],
    "sg:phone":"+1 510 653 2324",
    "sg:postcode":"94609",
    "sg:province":"CA",
    "wof:name":"Work Life Support Svc",
    "wof:placetype":"venue"
},
  "geometry": {"coordinates":[-122.266846,37.820865],"type":"Point"}
}