{
  "type": "Feature",
  "properties": {
    "addr:full":"4756 Brighton Ave San Diego CA 92107",
    "addr:housenumber":"4756",
    "addr:postcode":"92107",
    "addr:street":"Brighton Ave",
    "iso:country":"US",
    "sg:address":"4756 Brighton Ave",
    "sg:city":"San Diego",
    "sg:classifiers":[
        {
            "category":"Manufacturing",
            "subcategory":"Glass & Minerals",
            "type":"Manufacturing & Wholesale Goods"
        }
    ],
    "sg:phone":"+1 619 224 7490",
    "sg:postcode":"92107",
    "sg:province":"CA",
    "sg:tags":[
        "product",
        "mfg"
    ],
    "wof:name":"Nevingers Terry Glass Art",
    "wof:placetype":"venue"
},
  "geometry": {"coordinates":[-117.24379,32.747525],"type":"Point"}
}