{
  "type": "Feature",
  "properties": {
    "addr:full":"6505 Crenshaw Ct San Jose CA 95120",
    "addr:housenumber":"6505",
    "addr:postcode":"95120",
    "addr:street":"Crenshaw Ct",
    "iso:country":"US",
    "sg:address":"6505 Crenshaw Ct",
    "sg:city":"San Jose",
    "sg:classifiers":[
        {
            "category":"Professional",
            "subcategory":"Management & Consulting",
            "type":"Services"
        }
    ],
    "sg:phone":"+1 408 323 1900",
    "sg:postcode":"95120",
    "sg:province":"CA",
    "sg:tags":[
        "counselor",
        "public",
        "relations"
    ],
    "wof:name":"Red Haute Coutire",
    "wof:placetype":"venue"
},
  "geometry": {"coordinates":[-121.864125,37.21899],"type":"Point"}
}