{
  "type": "Feature",
  "properties": {
    "addr:full":"2055 Gateway Pl San Jose CA 95110",
    "addr:housenumber":"2055",
    "addr:postcode":"95110",
    "addr:street":"Gateway Pl",
    "iso:country":"US",
    "sg:address":"2055 Gateway Pl",
    "sg:city":"San Jose",
    "sg:classifiers":[
        {
            "category":"Real Estate",
            "subcategory":"Real Estate Agent",
            "type":"Services"
        }
    ],
    "sg:phone":"+1 408 437 7400",
    "sg:postcode":"95110",
    "sg:province":"CA",
    "sg:website":"www.comedycruise.com",
    "wof:name":"Group West Media Corp",
    "wof:placetype":"venue"
},
  "geometry": {"coordinates":[-121.92355000000001,37.371024],"type":"Point"}
}