{
  "type": "Feature",
  "properties": {
    "addr:full":"404 W Pine St Lodi CA 95240",
    "addr:housenumber":"404",
    "addr:postcode":"95240",
    "addr:street":"W Pine St",
    "iso:country":"US",
    "sg:address":"404 W Pine St",
    "sg:city":"Lodi",
    "sg:classifiers":[
        {
            "category":"Personal",
            "subcategory":"Beauty Salon",
            "type":"Services"
        }
    ],
    "sg:phone":"+1 209 367 5800",
    "sg:postcode":"95240",
    "sg:province":"CA",
    "wof:name":"Body Spa",
    "wof:placetype":"venue"
},
  "geometry": {"coordinates":[-121.27905,38.134355],"type":"Point"}
}