{
  "type": "Feature",
  "properties": {
    "addr:full":"4612 Kiernan Ave Salida CA 95368",
    "addr:postcode":"4612;95368",
    "addr:street":"Kiernan Ave",
    "iso:country":"US",
    "sg:address":"4612 Kiernan Ave",
    "sg:city":"Salida",
    "sg:phone":"+1 209 545 0791",
    "sg:postcode":"95368",
    "sg:province":"CA",
    "sg:tags":[
        "oil"
    ],
    "wof:name":"George Lowry Petroleum Product",
    "wof:placetype":"venue"
},
  "geometry": {"coordinates":[-121.088003,37.710785],"type":"Point"}
}