{
  "type": "Feature",
  "properties": {
    "iso:country":"US",
    "sg:address":"2334 Highgate Dr",
    "sg:city":"Richmond",
    "sg:classifiers":[
        {
            "category":"Social Services",
            "subcategory":"Child Care",
            "type":"Services"
        }
    ],
    "sg:phone":"+1 510 669 0610",
    "sg:postcode":"94806",
    "sg:province":"CA",
    "wof:name":"Alice's Wonderland",
    "wof:placetype":"venue"
},
  "geometry": {"coordinates":[-122.338154,37.977928],"type":"Point"}
}