{
  "type": "Feature",
  "properties": {
    "iso:country":"US",
    "sg:address":"1236 Quarry Ln",
    "sg:city":"Pleasanton",
    "sg:classifiers":[
        {
            "category":"Manufacturing",
            "subcategory":"Tools & Machinery",
            "type":"Manufacturing & Wholesale Goods"
        }
    ],
    "sg:phone":"+1 925 426 0400",
    "sg:postcode":"94566",
    "sg:province":"CA",
    "sg:tags":[
        "machine",
        "shop"
    ],
    "sg:website":"www.proconmach.com",
    "wof:name":"Progressive Concepts Machining",
    "wof:placetype":"venue"
},
  "geometry": {"coordinates":[-121.865734,37.673891],"type":"Point"}
}