{
  "type": "Feature",
  "properties": {
    "iso:country":"US",
    "sg:address":"1236 E Santa Clara St",
    "sg:city":"San Jose",
    "sg:classifiers":[
        {
            "category":"Professional",
            "subcategory":"Advertising",
            "type":"Services"
        }
    ],
    "sg:phone":"+1 408 294 5747",
    "sg:postcode":"95116",
    "sg:province":"CA",
    "sg:tags":[
        "station",
        "radio",
        "representative"
    ],
    "wof:name":"Portugal De Hoje",
    "wof:placetype":"venue"
},
  "geometry": {"coordinates":[-121.866376,37.347523],"type":"Point"}
}