{
  "type": "Feature",
  "properties": {
    "addr:full":"Grant & Clay San Francisco CA 94199",
    "addr:postcode":"94199",
    "iso:country":"US",
    "sg:address":"Grant & Clay",
    "sg:city":"San Francisco",
    "sg:classifiers":[
        {
            "category":"Wholesale",
            "subcategory":"Stationery",
            "type":"Manufacturing & Wholesale Goods"
        }
    ],
    "sg:postcode":"94199",
    "sg:province":"CA",
    "sg:tags":[
        "card"
    ],
    "wof:name":"Gifts Unlimited",
    "wof:placetype":"venue"
},
  "geometry": {"coordinates":[-122.40631399999999,37.794316],"type":"Point"}
}