{
  "type": "Feature",
  "properties": {
    "addr:full":"Physique Magnifique 387 Grand Ave South San Francisco CA 94080",
    "addr:housenumber":"387",
    "addr:postcode":"94080",
    "addr:street":"Grand Ave",
    "iso:country":"US",
    "sg:address":"Physique Magnifique 387 Grand Ave",
    "sg:city":"South San Francisco",
    "sg:classifiers":[
        {
            "category":"Sports & Exercise",
            "subcategory":"Gym",
            "type":"Entertainment"
        }
    ],
    "sg:phone":"+1 415 648 7231",
    "sg:postcode":"94080",
    "sg:province":"CA",
    "sg:tags":[
        "trainer"
    ],
    "sg:website":"www.sportspalace.org",
    "wof:name":"Jim Schmitz",
    "wof:placetype":"venue"
},
  "geometry": {"coordinates":[-122.412368,37.655339],"type":"Point"}
}