{
  "type": "Feature",
  "properties": {
    "addr:full":"40 S Market St San Jose CA 95113",
    "addr:housenumber":"40",
    "addr:postcode":"95113",
    "addr:street":"S Market St",
    "iso:country":"US",
    "sg:address":"40 S Market St",
    "sg:city":"San Jose",
    "sg:classifiers":[
        {
            "category":"Real Estate",
            "subcategory":"Developer",
            "type":"Services"
        }
    ],
    "sg:phone":"+1 408 283 5200",
    "sg:postcode":"95113",
    "sg:province":"CA",
    "wof:name":"Imwalle Stegner Development",
    "wof:placetype":"venue"
},
  "geometry": {"coordinates":[-121.891873,37.335352],"type":"Point"}
}