{
  "type": "Feature",
  "properties": {
    "addr:full":"44831 Oro Grande Cir Indian Wells CA 92210",
    "addr:housenumber":"44831",
    "addr:postcode":"92210",
    "addr:street":"Oro Grande Cir",
    "iso:country":"US",
    "sg:address":"44831 Oro Grande Cir",
    "sg:city":"Indian Wells",
    "sg:classifiers":[
        {
            "category":"Museum",
            "type":"Entertainment"
        }
    ],
    "sg:phone":"+1 760 863 5612",
    "sg:postcode":"92210",
    "sg:province":"CA",
    "sg:tags":[
        "art",
        "center"
    ],
    "wof:name":"Decorative Accents Collection",
    "wof:placetype":"venue"
},
  "geometry": {"coordinates":[-116.340943,33.726001],"type":"Point"}
}