{
  "type": "Feature",
  "properties": {
    "iso:country":"US",
    "sg:address":"15 Spectrum Pointe Dr",
    "sg:city":"Lake Forest",
    "sg:classifiers":[
        {
            "category":"Organizations",
            "subcategory":"Religious Organization",
            "type":"Services"
        }
    ],
    "sg:phone":"+1 949 597 1591",
    "sg:postcode":"92630",
    "sg:province":"CA",
    "sg:tags":[
        "church"
    ],
    "sg:website":"www.cclf.com",
    "wof:name":"Calvary Chapel Of Lake Forest",
    "wof:placetype":"venue"
},
  "geometry": {"coordinates":[-117.69139300000001,33.661087],"type":"Point"}
}