{
  "type": "Feature",
  "properties": {
    "addr:full":"1 City Blvd W Orange CA 92868",
    "addr:housenumber":"1",
    "addr:postcode":"92868",
    "addr:street":"City Blvd W",
    "iso:country":"US",
    "sg:address":"1 City Blvd W",
    "sg:city":"Orange",
    "sg:classifiers":[
        {
            "category":"Professional",
            "subcategory":"Lawyer & Legal Services",
            "type":"Services"
        }
    ],
    "sg:phone":"+1 714 937 1020",
    "sg:postcode":"92868",
    "sg:province":"CA",
    "sg:tags":[
        "divorce",
        "law",
        "family"
    ],
    "wof:name":"Denny John R Atty",
    "wof:placetype":"venue"
},
  "geometry": {"coordinates":[-117.89299800000001,33.787601],"type":"Point"}
}