{
  "type": "Feature",
  "properties": {
    "addr:full":"10075 Levone Ave Truckee CA 96161",
    "addr:housenumber":"10075",
    "addr:postcode":"96161",
    "addr:street":"Levone Ave",
    "iso:country":"US",
    "sg:address":"10075 Levone Ave",
    "sg:city":"Truckee",
    "sg:classifiers":[
        {
            "category":"Government",
            "subcategory":"Court House",
            "type":"Public Place"
        }
    ],
    "sg:phone":"+1 530 582 7835",
    "sg:postcode":"96161",
    "sg:province":"CA",
    "sg:tags":[
        "county"
    ],
    "sg:website":"www.court.co.nevada.ca.us",
    "wof:name":"Nevada County Municipal Court",
    "wof:placetype":"venue"
},
  "geometry": {"coordinates":[-120.200076,39.325639],"type":"Point"}
}