{
  "type": "Feature",
  "properties": {
    "iso:country":"US",
    "sg:address":"592 E Scott Ave",
    "sg:city":"Fresno",
    "sg:classifiers":[
        {
            "category":"Wholesale",
            "subcategory":"Electrical",
            "type":"Manufacturing & Wholesale Goods"
        }
    ],
    "sg:phone":"+1 559 229 5230",
    "sg:postcode":"93710",
    "sg:province":"CA",
    "sg:tags":[
        "alarm",
        "burglar",
        "system"
    ],
    "wof:name":"Burglar Alarm Svc",
    "wof:placetype":"venue"
},
  "geometry": {"coordinates":[-119.778891,36.811315],"type":"Point"}
}