{
  "type": "Feature",
  "properties": {
    "iso:country":"US",
    "sg:address":"10612 6th Ave",
    "sg:city":"Hanford",
    "sg:classifiers":[
        {
            "category":"Organizations",
            "subcategory":"Community Association",
            "type":"Services"
        }
    ],
    "sg:phone":"+1 559 582 4647",
    "sg:postcode":"93230",
    "sg:province":"CA",
    "wof:name":"American Lgion Axillary Unit 3",
    "wof:placetype":"venue"
},
  "geometry": {"coordinates":[-119.565197,36.319214],"type":"Point"}
}