{
  "type": "Feature",
  "properties": {
    "addr:full":"2940 Plaza Carlos Bonita CA 91902",
    "addr:housenumber":"2940",
    "addr:postcode":"91902",
    "addr:street":"Plaza Carlos Bonita",
    "iso:country":"US",
    "sg:address":"2940 Plaza Carlos",
    "sg:city":"Bonita",
    "sg:classifiers":[
        {
            "category":"Professional",
            "subcategory":"Computer Services",
            "type":"Services"
        }
    ],
    "sg:phone":"+1 619 948 4062",
    "sg:postcode":"91902",
    "sg:province":"CA",
    "sg:tags":[
        "technical",
        "assistance",
        "support"
    ],
    "sg:website":"http://www.mymarchi.com",
    "wof:name":"Ddc Solutions",
    "wof:placetype":"venue"
},
  "geometry": {"coordinates":[-117.028077,32.679218],"type":"Point"}
}