{
  "type": "Feature",
  "properties": {
    "iso:country":"US",
    "sg:address":"11823 Slauson Ave",
    "sg:city":"Santa Fe Springs",
    "sg:classifiers":[
        {
            "category":"Building & Trades",
            "subcategory":"Pest Control",
            "type":"Services"
        }
    ],
    "sg:phone":"+1 562 696 5900",
    "sg:postcode":"90670",
    "sg:province":"CA",
    "wof:name":"Wesley Thompson Termite",
    "wof:placetype":"venue"
},
  "geometry": {"coordinates":[-118.343484,33.964748],"type":"Point"}
}