{
  "type": "Feature",
  "properties": {
    "addr:full":"100 E Cedar Ave Coalinga CA 93210",
    "addr:housenumber":"100",
    "addr:postcode":"93210",
    "addr:street":"E Cedar Ave",
    "iso:country":"US",
    "sg:address":"100 E Cedar Ave",
    "sg:city":"Coalinga",
    "sg:classifiers":[
        {
            "category":"Home & Garden",
            "subcategory":"Carpets & Floor Coverings",
            "type":"Retail Goods"
        }
    ],
    "sg:phone":"+1 559 935 8995",
    "sg:postcode":"93210",
    "sg:province":"CA",
    "wof:name":"Coalinga Floors & More",
    "wof:placetype":"venue"
},
  "geometry": {"coordinates":[-120.36145,36.14214],"type":"Point"}
}