{
  "type": "Feature",
  "properties": {
    "addr:full":"1041 Irving St San Francisco CA 94122",
    "addr:housenumber":"1041",
    "addr:postcode":"94122",
    "addr:street":"Irving St",
    "iso:country":"US",
    "sg:address":"1041 Irving St",
    "sg:city":"San Francisco",
    "sg:classifiers":[
        {
            "category":"Freight",
            "type":"Transportation"
        }
    ],
    "sg:phone":"+1 415 566 4536",
    "sg:postcode":"94122",
    "sg:province":"CA",
    "sg:tags":[
        "operator",
        "local",
        "trucking"
    ],
    "wof:name":"Advance Delivery",
    "wof:placetype":"venue"
},
  "geometry": {"coordinates":[-122.469172,37.76384],"type":"Point"}
}