{
  "type": "Feature",
  "properties": {
    "iso:country":"US",
    "sg:address":"77 Woodland Ave",
    "sg:city":"San Rafael",
    "sg:classifiers":[
        {
            "category":"Real Estate",
            "subcategory":"Surveying",
            "type":"Services"
        }
    ],
    "sg:phone":"+1 415 883 0775",
    "sg:postcode":"94901",
    "sg:province":"CA",
    "sg:tags":[
        "surveyor"
    ],
    "wof:name":"Renner Surveying & Engineering",
    "wof:placetype":"venue"
},
  "geometry": {"coordinates":[-122.517809,37.962868],"type":"Point"}
}