{
  "type": "Feature",
  "properties": {
    "iso:country":"US",
    "sg:address":"14713 Weedpatch Hwy",
    "sg:city":"Bakersfield",
    "sg:classifiers":[
        {
            "category":"Education",
            "subcategory":"School",
            "type":"Public Place"
        }
    ],
    "sg:phone":"+1 661 845 3713",
    "sg:postcode":"93307",
    "sg:province":"CA",
    "sg:tags":[
        "district"
    ],
    "sg:website":"http://www.vinelandschooldistrict.com",
    "wof:name":"Vineland School District",
    "wof:placetype":"venue"
},
  "geometry": {"coordinates":[-118.914276,35.3514],"type":"Point"}
}