{
  "type": "Feature",
  "properties": {
    "iso:country":"US",
    "sg:address":"1225 Fitzgerald Rd",
    "sg:city":"Simi Valley",
    "sg:classifiers":[
        {
            "category":"Professional",
            "subcategory":"Research",
            "type":"Services"
        }
    ],
    "sg:phone":"+1 805 520 0383",
    "sg:postcode":"93065",
    "sg:province":"CA",
    "sg:tags":[
        "environmental",
        "ecological"
    ],
    "wof:name":"Ecological",
    "wof:placetype":"venue"
},
  "geometry": {"coordinates":[-118.77597,34.257244],"type":"Point"}
}