{
  "type": "Feature",
  "properties": {
    "iso:country":"US",
    "sg:address":"5145 Industrial Way",
    "sg:city":"Benicia",
    "sg:classifiers":[
        {
            "category":"Professional",
            "subcategory":"Engineering",
            "type":"Services"
        }
    ],
    "sg:phone":"+1 707 746 8800",
    "sg:postcode":"94510",
    "sg:province":"CA",
    "sg:tags":[
        "general",
        "contractor"
    ],
    "sg:website":"www.undergroundconstruction.net",
    "wof:name":"Underground Construction Co",
    "wof:placetype":"venue"
},
  "geometry": {"coordinates":[-122.11257999999999,38.080955],"type":"Point"}
}