{
  "type": "Feature",
  "properties": {
    "addr:full":"320 5th St Gustine CA 95322",
    "addr:housenumber":"320",
    "addr:postcode":"95322",
    "addr:street":"5Th St",
    "iso:country":"US",
    "sg:address":"320 5th St",
    "sg:city":"Gustine",
    "sg:classifiers":[
        {
            "category":"Real Estate",
            "subcategory":"Real Estate Agent",
            "type":"Services"
        }
    ],
    "sg:phone":"+1 209 854 2487",
    "sg:postcode":"95322",
    "sg:province":"CA",
    "wof:name":"Davenport Real Estate Inc",
    "wof:placetype":"venue"
},
  "geometry": {"coordinates":[-120.999619,37.256288],"type":"Point"}
}