{
  "type": "Feature",
  "properties": {
    "iso:country":"US",
    "sg:address":"1211 Pine St",
    "sg:city":"Redding",
    "sg:classifiers":[
        {
            "category":"Autos & Motor Vehicles",
            "subcategory":"Automobile Sales",
            "type":"Retail Goods"
        }
    ],
    "sg:phone":"+1 530 243 3151",
    "sg:postcode":"96001",
    "sg:province":"CA",
    "sg:tags":[
        "car",
        "dealer"
    ],
    "wof:name":"Budget Auto Ctr",
    "wof:placetype":"venue"
},
  "geometry": {"coordinates":[-122.390305,40.586858],"type":"Point"}
}