{
  "type": "Feature",
  "properties": {
    "addr:full":"4310 Artesia Blvd Torrance CA 90510",
    "addr:housenumber":"4310",
    "addr:postcode":"90510",
    "addr:street":"Artesia Blvd",
    "iso:country":"US",
    "sg:address":"4310 Artesia Blvd",
    "sg:city":"Torrance",
    "sg:classifiers":[
        {
            "category":"Home & Garden",
            "subcategory":"Furniture",
            "type":"Retail Goods"
        }
    ],
    "sg:phone":"+1 310 542 9399",
    "sg:postcode":"90510",
    "sg:province":"CA",
    "sg:tags":[
        "store"
    ],
    "sg:website":"www.easylifefurniture.com",
    "wof:name":"Easy Life Furniture",
    "wof:placetype":"venue"
},
  "geometry": {"coordinates":[-118.350722,33.872435],"type":"Point"}
}