{
  "type": "Feature",
  "properties": {
    "addr:full":"8759 Elk Grove Blvd Elk Grove CA 95624",
    "addr:housenumber":"8759",
    "addr:postcode":"95624",
    "addr:street":"Elk Grove Blvd",
    "iso:country":"US",
    "sg:address":"8759 Elk Grove Blvd",
    "sg:city":"Elk Grove",
    "sg:classifiers":[
        {
            "category":"Manufacturing",
            "subcategory":"Printing",
            "type":"Manufacturing & Wholesale Goods"
        }
    ],
    "sg:phone":"+1 916 686 4670",
    "sg:postcode":"95624",
    "sg:province":"CA",
    "sg:tags":[
        "printer"
    ],
    "wof:name":"PIP Printing",
    "wof:placetype":"venue"
},
  "geometry": {"coordinates":[-121.37855399999999,38.409064],"type":"Point"}
}