{
  "type": "Feature",
  "properties": {
    "addr:full":"22844 Hawthorne Blvd Torrance CA 90505",
    "addr:housenumber":"22844",
    "addr:postcode":"90505",
    "addr:street":"Hawthorne Blvd",
    "iso:country":"US",
    "sg:address":"22844 Hawthorne Blvd",
    "sg:city":"Torrance",
    "sg:classifiers":[
        {
            "category":"Shopping",
            "subcategory":"Party Supplies",
            "type":"Retail Goods"
        },
        {
            "category":"Personal",
            "type":"Services"
        }
    ],
    "sg:phone":"+1 310 465 0075",
    "sg:postcode":"90505",
    "sg:province":"CA",
    "sg:tags":[
        "planning",
        "event"
    ],
    "wof:name":"Playful Minds Llc",
    "wof:placetype":"venue"
},
  "geometry": {"coordinates":[-118.350998,33.820099],"type":"Point"}
}