{
  "type": "Feature",
  "properties": {
    "iso:country":"US",
    "sg:address":"10833 Le Conte Ave",
    "sg:city":"Los Angeles",
    "sg:classifiers":[
        {
            "category":"Health Services",
            "subcategory":"Hospital",
            "type":"Services"
        },
        {
            "category":"Community Center",
            "type":"Public Place"
        }
    ],
    "sg:phone":"+1 310 825 8611",
    "sg:postcode":"90095",
    "sg:province":"CA",
    "sg:tags":[
        "medical"
    ],
    "sg:website":"www.uclahealth.org",
    "wof:name":"Ronald Reagan UCLA Medical Center",
    "wof:placetype":"venue"
},
  "geometry": {"coordinates":[-118.44296,34.064908],"type":"Point"}
}