{
  "type": "Feature",
  "properties": {
    "iso:country":"US",
    "sg:address":"1470 Fruitvale Ave",
    "sg:city":"Oakland",
    "sg:classifiers":[
        {
            "category":"Professional",
            "type":"Services"
        },
        {
            "category":"Education",
            "subcategory":"School",
            "type":"Public Place"
        }
    ],
    "sg:phone":"+1 510 532 2365",
    "sg:postcode":"94601",
    "sg:province":"CA",
    "wof:name":"Oasis High School",
    "wof:placetype":"venue"
},
  "geometry": {"coordinates":[-122.225257,37.778558],"type":"Point"}
}