{
  "type": "Feature",
  "properties": {
    "addr:full":"3585 Telegraph Rd Ventura CA 93003",
    "addr:housenumber":"3585",
    "addr:postcode":"93003",
    "addr:street":"Telegraph Rd",
    "iso:country":"US",
    "sg:address":"3585 Telegraph Rd",
    "sg:city":"Ventura",
    "sg:classifiers":[
        {
            "category":"Shopping",
            "type":"Retail Goods"
        }
    ],
    "sg:phone":"+1 805 658 6013",
    "sg:postcode":"93003",
    "sg:province":"CA",
    "sg:tags":[
        "hearing",
        "equipment",
        "supply",
        "impaired"
    ],
    "wof:name":"Community Hearing Aid Ctr",
    "wof:placetype":"venue"
},
  "geometry": {"coordinates":[-119.247484,34.273205],"type":"Point"}
}