{
  "type": "Feature",
  "properties": {
    "addr:full":"7426 Maureen Ln Rohnert Park CA 94928",
    "addr:housenumber":"7426",
    "addr:postcode":"94928",
    "addr:street":"Maureen Ln",
    "iso:country":"US",
    "sg:address":"7426 Maureen Ln",
    "sg:city":"Rohnert Park",
    "sg:classifiers":[
        {
            "category":"Professional",
            "subcategory":"Management & Consulting",
            "type":"Services"
        }
    ],
    "sg:phone":"+1 707 795 1625",
    "sg:postcode":"94928",
    "sg:province":"CA",
    "sg:tags":[
        "retail",
        "direct",
        "sales"
    ],
    "wof:name":"K & K Marketing",
    "wof:placetype":"venue"
},
  "geometry": {"coordinates":[-122.67854,38.333318],"type":"Point"}
}