{
  "type": "Feature",
  "properties": {
    "iso:country":"US",
    "sg:address":"4303 Mohawk St",
    "sg:city":"Bakersfield",
    "sg:classifiers":[
        {
            "category":"Insurance",
            "subcategory":"Insurance Agent",
            "type":"Services"
        }
    ],
    "sg:phone":"+1 909 399 9338",
    "sg:postcode":"93308",
    "sg:province":"CA",
    "wof:name":"Jack Lin Insurance Svc",
    "wof:placetype":"venue"
},
  "geometry": {"coordinates":[-119.06545,35.38332],"type":"Point"}
}