{
  "type": "Feature",
  "properties": {
    "addr:full":"4517 Market St Ventura CA 93003",
    "addr:housenumber":"4517",
    "addr:postcode":"93003",
    "addr:street":"Market St",
    "iso:country":"US",
    "sg:address":"4517 Market St",
    "sg:city":"Ventura",
    "sg:classifiers":[
        {
            "category":"Home & Garden",
            "subcategory":"Building Materials",
            "type":"Retail Goods"
        },
        {
            "category":"Wholesale",
            "subcategory":"Auto Parts",
            "type":"Manufacturing & Wholesale Goods"
        }
    ],
    "sg:phone":"+1 805 644 7930",
    "sg:postcode":"93003",
    "sg:province":"CA",
    "sg:tags":[
        "glass",
        "window",
        "plate"
    ],
    "wof:name":"Advantage Glass and Windows",
    "wof:placetype":"venue"
},
  "geometry": {"coordinates":[-119.23246,34.257162],"type":"Point"}
}