{
  "type": "Feature",
  "properties": {
    "addr:full":"1646 W Katella Ave Anaheim CA 92802",
    "addr:housenumber":"1646",
    "addr:postcode":"92802",
    "addr:street":"W Katella Ave",
    "iso:country":"US",
    "sg:address":"1646 W Katella Ave",
    "sg:city":"Anaheim",
    "sg:classifiers":[
        {
            "category":"Bakery",
            "type":"Food & Drink"
        },
        {
            "category":"Ice Cream",
            "type":"Food & Drink"
        }
    ],
    "sg:phone":"+1 714 772 8441",
    "sg:postcode":"92802",
    "sg:province":"CA",
    "sg:tags":[
        "frozen",
        "yogurt"
    ],
    "wof:name":"Baskin-Robbins 31 Ice Cream Stores",
    "wof:placetype":"venue"
},
  "geometry": {"coordinates":[-117.939003,33.8032],"type":"Point"}
}