{
  "type": "Feature",
  "properties": {
    "iso:country":"US",
    "sg:address":"407 E 19th St",
    "sg:city":"Bakersfield",
    "sg:classifiers":[
        {
            "category":"Building & Trades",
            "subcategory":"Electrical",
            "type":"Services"
        }
    ],
    "sg:phone":"+1 661 395 0759",
    "sg:postcode":"93305",
    "sg:province":"CA",
    "sg:tags":[
        "electrical",
        "contractor",
        "com",
        "specialty",
        "mfg"
    ],
    "wof:name":"Signs Unlimited",
    "wof:placetype":"venue"
},
  "geometry": {"coordinates":[-118.996821,35.375486],"type":"Point"}
}