{
  "type": "Feature",
  "properties": {
    "addr:full":"19323 Ventura Blvd Tarzana CA 91356",
    "addr:housenumber":"19323",
    "addr:postcode":"91356",
    "addr:street":"Ventura Blvd",
    "iso:country":"US",
    "sg:address":"19323 Ventura Blvd",
    "sg:city":"Tarzana",
    "sg:classifiers":[
        {
            "category":"Shopping",
            "subcategory":"Gifts & Souvenirs",
            "type":"Retail Goods"
        }
    ],
    "sg:phone":"+1 818 609 1332",
    "sg:postcode":"91356",
    "sg:province":"CA",
    "sg:tags":[
        "shop"
    ],
    "wof:name":"Ruthys Gifts & Plus",
    "wof:placetype":"venue"
},
  "geometry": {"coordinates":[-118.554006,34.172738],"type":"Point"}
}