{
  "type": "Feature",
  "properties": {
    "iso:country":"US",
    "sg:address":"2116 E I St",
    "sg:city":"Wilmington",
    "sg:classifiers":[
        {
            "category":"Freight",
            "type":"Transportation"
        }
    ],
    "sg:phone":"+1 562 437 3755",
    "sg:postcode":"90744",
    "sg:province":"CA",
    "sg:tags":[
        "hauling",
        "trucking"
    ],
    "wof:name":"Big West Transport",
    "wof:placetype":"venue"
},
  "geometry": {"coordinates":[-118.234821,33.78277],"type":"Point"}
}