{
  "type": "Feature",
  "properties": {
    "addr:full":"776 E Green St Ste 205 Pasadena CA 91101",
    "addr:housenumber":"776",
    "addr:postcode":"91101",
    "addr:street":"E Green St Ste 205",
    "iso:country":"US",
    "sg:address":"776 E Green St Ste 205",
    "sg:city":"Pasadena",
    "sg:classifiers":[
        {
            "category":"Health Services",
            "subcategory":"Hospital",
            "type":"Services"
        },
        {
            "category":"Banks & Credit Unions",
            "subcategory":"Investment Brokerage",
            "type":"Services"
        }
    ],
    "sg:phone":"+1 626 440 1314",
    "sg:postcode":"91101",
    "sg:province":"CA",
    "sg:tags":[
        "trust"
    ],
    "sg:website":"http://www.stubbsassociates.com",
    "wof:name":"Stubbs& Associates",
    "wof:placetype":"venue"
},
  "geometry": {"coordinates":[-118.134336,34.144393],"type":"Point"}
}