{
  "type": "Feature",
  "properties": {
    "addr:full":"2981 K Street San Diego CA 92102",
    "addr:housenumber":"2981",
    "addr:postcode":"92102",
    "addr:street":"K Street",
    "iso:country":"US",
    "sg:address":"2981 K Street",
    "sg:city":"San Diego",
    "sg:classifiers":[
        {
            "category":"Professional",
            "subcategory":"Printing & Photocopies",
            "type":"Services"
        }
    ],
    "sg:phone":"+1 619 233 8432",
    "sg:postcode":"92102",
    "sg:province":"CA",
    "sg:website":"www.supersignssd.com",
    "wof:name":"Super Signs",
    "wof:placetype":"venue"
},
  "geometry": {"coordinates":[-117.129876,32.708605],"type":"Point"}
}