{
  "type": "Feature",
  "properties": {
    "addr:full":"19345 E American Ave Reedley CA 93654",
    "addr:housenumber":"19345",
    "addr:postcode":"93654",
    "addr:street":"E American Ave",
    "iso:country":"US",
    "sg:address":"19345 E American Ave",
    "sg:city":"Reedley",
    "sg:classifiers":[
        {
            "category":"Wholesale",
            "subcategory":"Non-durable Goods",
            "type":"Manufacturing & Wholesale Goods"
        }
    ],
    "sg:phone":"+1 510 386 5496",
    "sg:postcode":"93654",
    "sg:province":"CA",
    "sg:tags":[
        "interior"
    ],
    "wof:name":"Design Gallery",
    "wof:placetype":"venue"
},
  "geometry": {"coordinates":[-119.444913,36.662244],"type":"Point"}
}