{
  "type": "Feature",
  "properties": {
    "iso:country":"US",
    "sg:address":"3244 E Gage Ave",
    "sg:city":"Huntington Park",
    "sg:classifiers":[
        {
            "category":"Personal",
            "subcategory":"Beauty Salon",
            "type":"Services"
        }
    ],
    "sg:phone":"+1 323 582 7768",
    "sg:postcode":"90255",
    "sg:province":"CA",
    "wof:name":"Pierina's Beauty Salon",
    "wof:placetype":"venue"
},
  "geometry": {"coordinates":[-118.209049,33.9803],"type":"Point"}
}