{
  "type": "Feature",
  "properties": {
    "addr:full":"3244 E Gage Ave Huntington Park CA 90255",
    "addr:housenumber":"3244",
    "addr:postcode":"90255",
    "addr:street":"E Gage Ave;Park",
    "iso:country":"US",
    "sg:address":"3244 E Gage Ave",
    "sg:city":"Huntington Park",
    "sg:classifiers":[
        {
            "category":"Personal",
            "subcategory":"Beauty Salon",
            "type":"Services"
        }
    ],
    "sg:phone":"+1 323 582 7768",
    "sg:postcode":"90255",
    "sg:province":"CA",
    "wof:name":"Pierina's Beauty Salon",
    "wof:placetype":"venue"
},
  "geometry": {"coordinates":[-118.20904899999999,33.9803],"type":"Point"}
}