{
  "type": "Feature",
  "properties": {
    "addr:full":"2244 Westwood Blvd Los Angeles CA 90064",
    "addr:housenumber":"2244",
    "addr:postcode":"90064",
    "addr:street":"Westwood Blvd",
    "iso:country":"US",
    "sg:address":"2244 Westwood Blvd",
    "sg:city":"Los Angeles",
    "sg:classifiers":[
        {
            "category":"Real Estate",
            "subcategory":"Real Estate Agent",
            "type":"Services"
        }
    ],
    "sg:phone":"+1 310 474 6560",
    "sg:postcode":"90064",
    "sg:province":"CA",
    "wof:name":"Retail Enterprise Group",
    "wof:placetype":"venue"
},
  "geometry": {"coordinates":[-118.430869,34.043106],"type":"Point"}
}