{
  "type": "Feature",
  "properties": {
    "addr:full":"4449 W Adams Blvd Los Angeles CA 90016",
    "addr:housenumber":"4449",
    "addr:postcode":"90016",
    "addr:street":"W Adams Blvd",
    "iso:country":"US",
    "sg:address":"4449 W Adams Blvd",
    "sg:city":"Los Angeles",
    "sg:classifiers":[
        {
            "category":"Social Services",
            "subcategory":"Child Care",
            "type":"Services"
        },
        {
            "category":"Education",
            "subcategory":"Preschool",
            "type":"Public Place"
        },
        {
            "category":"Education",
            "subcategory":"School",
            "type":"Public Place"
        }
    ],
    "sg:phone":"+1 323 737 6803",
    "sg:postcode":"90016",
    "sg:province":"CA",
    "sg:tags":[
        "elementary",
        "day"
    ],
    "wof:name":"Cleophas Oliver Learning Academy",
    "wof:placetype":"venue"
},
  "geometry": {"coordinates":[-118.337997,34.032501],"type":"Point"}
}