{
  "type": "Feature",
  "properties": {
    "addr:full":"324 Suey Rd Santa Maria CA 93454",
    "addr:housenumber":"324",
    "addr:postcode":"93454",
    "addr:street":"Suey Rd",
    "iso:country":"US",
    "sg:address":"324 Suey Rd",
    "sg:city":"Santa Maria",
    "sg:classifiers":[
        {
            "category":"Organizations",
            "subcategory":"Religious Organization",
            "type":"Services"
        }
    ],
    "sg:phone":"+1 805 925 2116",
    "sg:postcode":"93454",
    "sg:province":"CA",
    "sg:tags":[
        "church"
    ],
    "wof:name":"Calvary Temple Church Of God",
    "wof:placetype":"venue"
},
  "geometry": {"coordinates":[-120.40895500000001,34.955574],"type":"Point"}
}