{
  "type": "Feature",
  "properties": {
    "iso:country":"US",
    "sg:address":"25709 Rye Canyon Rd",
    "sg:city":"Valencia",
    "sg:classifiers":[
        {
            "category":"Manufacturing",
            "subcategory":"Signs",
            "type":"Manufacturing & Wholesale Goods"
        }
    ],
    "sg:phone":"+1 661 775 4890",
    "sg:postcode":"91355",
    "sg:province":"CA",
    "wof:name":"Signs Unlimited",
    "wof:placetype":"venue"
},
  "geometry": {"coordinates":[-118.586997,34.432131],"type":"Point"}
}