{
  "type": "Feature",
  "properties": {
    "addr:full":"401 N E St Madera CA 93638",
    "addr:housenumber":"401",
    "addr:postcode":"93638",
    "addr:street":"N E St",
    "iso:country":"US",
    "sg:address":"401 N E St",
    "sg:city":"Madera",
    "sg:classifiers":[
        {
            "category":"Professional",
            "type":"Services"
        }
    ],
    "sg:phone":"+1 559 674 4060",
    "sg:postcode":"93638",
    "sg:province":"CA",
    "wof:name":"Twilight Hammers",
    "wof:placetype":"venue"
},
  "geometry": {"coordinates":[-120.063367,36.965576],"type":"Point"}
}