{
  "type": "Feature",
  "properties": {
    "iso:country":"US",
    "sg:address":"953 San Pablo Ave",
    "sg:city":"Albany",
    "sg:classifiers":[
        {
            "category":"Bars & Pubs",
            "type":"Food & Drink"
        }
    ],
    "sg:phone":"+1 510 528 1734",
    "sg:postcode":"94706",
    "sg:province":"CA",
    "wof:name":"Kellee's",
    "wof:placetype":"venue"
},
  "geometry": {"coordinates":[-122.29833600000001,37.888386],"type":"Point"}
}