{
  "type": "Feature",
  "properties": {
    "iso:country":"US",
    "sg:address":"1416 9th St",
    "sg:city":"Sacramento",
    "sg:classifiers":[
        {
            "category":"Manufacturing",
            "subcategory":"Lumber",
            "type":"Manufacturing & Wholesale Goods"
        }
    ],
    "sg:phone":"+1 916 653 5121",
    "sg:postcode":"95814",
    "sg:province":"CA",
    "sg:tags":[
        "government"
    ],
    "sg:website":"www.fire.ca.gov",
    "wof:name":"Forestry & Fire Protection",
    "wof:placetype":"venue"
},
  "geometry": {"coordinates":[-121.496968,38.575899],"type":"Point"}
}