{
  "type": "Feature",
  "properties": {
    "iso:country":"US",
    "sg:address":"925 E Villa St",
    "sg:city":"Pasadena",
    "sg:classifiers":[
        {
            "category":"Travel",
            "subcategory":"Hotels & Motels",
            "type":"Entertainment"
        }
    ],
    "sg:phone":"+1 626 796 4303",
    "sg:postcode":"91106",
    "sg:province":"CA",
    "sg:website":"www.pasadena-village.com",
    "wof:name":"The Villas By Regency Park",
    "wof:placetype":"venue"
},
  "geometry": {"coordinates":[-118.131237,34.154427],"type":"Point"}
}