{
  "type": "Feature",
  "properties": {
    "addr:full":"675 B St San Diego CA 92101",
    "addr:housenumber":"675",
    "addr:postcode":"92101",
    "addr:street":"B St",
    "iso:country":"US",
    "sg:address":"675 B St",
    "sg:city":"San Diego",
    "sg:classifiers":[
        {
            "category":"Restaurant",
            "type":"Food & Drink"
        }
    ],
    "sg:phone":"+1 619 531 0955",
    "sg:postcode":"92101",
    "sg:province":"CA",
    "sg:tags":[
        "pizza"
    ],
    "sg:website":"www.citypizzeriasd.com",
    "wof:name":"City Pizzeria",
    "wof:placetype":"venue"
},
  "geometry": {"coordinates":[-117.158458,32.71778],"type":"Point"}
}