{
  "type": "Feature",
  "properties": {
    "addr:full":"873 Country Club Dr Simi Valley CA 93065",
    "addr:housenumber":"873",
    "addr:postcode":"93065",
    "addr:street":"Country Club Dr",
    "iso:country":"US",
    "sg:address":"873 Country Club Dr",
    "sg:city":"Simi Valley",
    "sg:classifiers":[
        {
            "category":"Food & Beverages",
            "subcategory":"Specialty",
            "type":"Retail Goods"
        }
    ],
    "sg:phone":"+1 805 527 8279",
    "sg:postcode":"93065",
    "sg:province":"CA",
    "wof:name":"Travelers Tea Coffee",
    "wof:placetype":"venue"
},
  "geometry": {"coordinates":[-118.817159,34.2511],"type":"Point"}
}