{
  "type": "Feature",
  "properties": {
    "addr:full":"3832 Holloway Rd Colusa CA 95932",
    "addr:housenumber":"3832",
    "addr:postcode":"95932",
    "addr:street":"Holloway Rd",
    "iso:country":"US",
    "sg:address":"3832 Holloway Rd",
    "sg:city":"Colusa",
    "sg:classifiers":[
        {
            "category":"Farming",
            "subcategory":"Farm & Veterinary Services",
            "type":"Manufacturing & Wholesale Goods"
        }
    ],
    "sg:phone":"+1 530 458 2248",
    "sg:postcode":"95932",
    "sg:province":"CA",
    "sg:tags":[
        "aerial",
        "applicator"
    ],
    "wof:name":"Moore Aviation Inc",
    "wof:placetype":"venue"
},
  "geometry": {"coordinates":[-122.069985,39.274012],"type":"Point"}
}