{
  "type": "Feature",
  "properties": {
    "addr:full":"9353 Greenback Ln Orangevale CA 95662",
    "addr:housenumber":"9353",
    "addr:postcode":"95662",
    "addr:street":"Greenback Ln",
    "iso:country":"US",
    "sg:address":"9353 Greenback Ln",
    "sg:city":"Orangevale",
    "sg:classifiers":[
        {
            "category":"Restaurant",
            "type":"Food & Drink"
        }
    ],
    "sg:phone":"+1 916 988 8014",
    "sg:postcode":"95662",
    "sg:province":"CA",
    "sg:website":"http://www.lupitasflavor.com",
    "wof:name":"Lupita's Mexican Restaurant",
    "wof:placetype":"venue"
},
  "geometry": {"coordinates":[-121.204474,38.678158],"type":"Point"}
}