{
  "type": "Feature",
  "properties": {
    "iso:country":"US",
    "sg:address":"660 S 2nd St",
    "sg:city":"Brawley",
    "sg:classifiers":[
        {
            "category":"Freight",
            "type":"Transportation"
        }
    ],
    "sg:phone":"+1 760 344 5020",
    "sg:postcode":"92227",
    "sg:province":"CA",
    "sg:tags":[
        "operator",
        "local",
        "trucking"
    ],
    "wof:name":"Dominguez Trucking",
    "wof:placetype":"venue"
},
  "geometry": {"coordinates":[-115.539361,32.97161],"type":"Point"}
}