{
  "type": "Feature",
  "properties": {
    "iso:country":"US",
    "sg:address":"4380 La Jolla Village Dr Ste 200",
    "sg:city":"San Diego",
    "sg:classifiers":[
        {
            "category":"Banks & Credit Unions",
            "subcategory":"Financial Services",
            "type":"Services"
        }
    ],
    "sg:phone":"+1 858 410 3900",
    "sg:postcode":"92122",
    "sg:province":"CA",
    "sg:tags":[
        "broker",
        "mortgage"
    ],
    "sg:website":"www.firstamtrust.com",
    "wof:name":"First American Trust",
    "wof:placetype":"venue"
},
  "geometry": {"coordinates":[-117.210289,32.874131],"type":"Point"}
}