{
  "type": "Feature",
  "properties": {
    "addr:full":"38350 Alta Dr Fremont CA 94536",
    "addr:housenumber":"38350",
    "addr:postcode":"94536",
    "addr:street":"Alta Dr",
    "iso:country":"US",
    "sg:address":"38350 Alta Dr",
    "sg:city":"Fremont",
    "sg:classifiers":[
        {
            "category":"Recreation",
            "type":"Entertainment"
        }
    ],
    "sg:phone":"+1 510 797 7600",
    "sg:postcode":"94536",
    "sg:province":"CA",
    "sg:tags":[
        "club",
        "membership",
        "real estate"
    ],
    "wof:name":"Glenmoor Gardens Alta Swmmg",
    "wof:placetype":"venue"
},
  "geometry": {"coordinates":[-122.007295,37.539258],"type":"Point"}
}