{
  "type": "Feature",
  "properties": {
    "addr:full":"1270 Memorex Dr Santa Clara CA 95050",
    "addr:housenumber":"1270",
    "addr:postcode":"95050",
    "addr:street":"Memorex Dr",
    "iso:country":"US",
    "sg:address":"1270 Memorex Dr",
    "sg:city":"Santa Clara",
    "sg:classifiers":[
        {
            "category":"Retail",
            "subcategory":"Auto Repair",
            "type":"Services"
        }
    ],
    "sg:phone":"+1 408 986 8267",
    "sg:postcode":"95050",
    "sg:province":"CA",
    "sg:tags":[
        "wrecker"
    ],
    "wof:name":"Lima Towing",
    "wof:placetype":"venue"
},
  "geometry": {"coordinates":[-121.95077499999999,37.362535],"type":"Point"}
}