{
  "type": "Feature",
  "properties": {
    "iso:country":"US",
    "sg:address":"9837 S Leonard Ave",
    "sg:city":"Selma",
    "sg:classifiers":[
        {
            "category":"Farming",
            "subcategory":"Vineyard",
            "type":"Manufacturing & Wholesale Goods"
        }
    ],
    "sg:phone":"+1 559 896 0926",
    "sg:postcode":"93662",
    "sg:province":"CA",
    "sg:tags":[
        "dehydrated",
        "grape",
        "mfg"
    ],
    "wof:name":"Nick Martinez Jr",
    "wof:placetype":"venue"
},
  "geometry": {"coordinates":[-119.637598,36.592928],"type":"Point"}
}