{
  "type": "Feature",
  "properties": {
    "iso:country":"US",
    "sg:address":"39700 Bob Hope Dr Ste 110",
    "sg:city":"Rancho Mirage",
    "sg:classifiers":[
        {
            "category":"Health Services",
            "subcategory":"Doctor",
            "type":"Services"
        }
    ],
    "sg:phone":"+1 760 568 4461",
    "sg:postcode":"92270",
    "sg:province":"CA",
    "wof:name":"Cancer & Blood Institute of the Desert",
    "wof:placetype":"venue"
},
  "geometry": {"coordinates":[-116.40799699999999,33.761501],"type":"Point"}
}