{
  "type": "Feature",
  "properties": {
    "addr:full":"1464 4th St Santa Monica CA 90401",
    "addr:housenumber":"1464",
    "addr:postcode":"90401",
    "addr:street":"4Th St",
    "iso:country":"US",
    "sg:address":"1464 4th St",
    "sg:city":"Santa Monica",
    "sg:classifiers":[
        {
            "category":"Professional",
            "type":"Services"
        }
    ],
    "sg:phone":"+1 310 576 1808",
    "sg:postcode":"90401",
    "sg:province":"CA",
    "wof:name":"Aline Media",
    "wof:placetype":"venue"
},
  "geometry": {"coordinates":[-118.494495,34.015885],"type":"Point"}
}