{
  "type": "Feature",
  "properties": {
    "addr:full":"11281 State Rte 49 Sonora CA 95370",
    "addr:housenumber":"11281",
    "addr:postcode":"95370",
    "addr:street":"State Rte 49",
    "iso:country":"US",
    "sg:address":"11281 State Rte 49",
    "sg:city":"Sonora",
    "sg:classifiers":[
        {
            "category":"Personal",
            "subcategory":"Beauty Salon",
            "type":"Services"
        }
    ],
    "sg:phone":"+1 209 532 7505",
    "sg:postcode":"95370",
    "sg:province":"CA",
    "wof:name":"Shear Results",
    "wof:placetype":"venue"
},
  "geometry": {"coordinates":[-120.39566000000001,38.013823],"type":"Point"}
}