{
  "type": "Feature",
  "properties": {
    "iso:country":"US",
    "sg:address":"1823 S Hope Street",
    "sg:city":"Los Angeles",
    "sg:classifiers":[
        {
            "category":"Shopping",
            "subcategory":"Bicycles & Sporting Goods",
            "type":"Retail Goods"
        }
    ],
    "sg:phone":"+1 213 765 5400",
    "sg:postcode":"90015",
    "sg:province":"CA",
    "sg:website":"www.taskermetalproducts.com",
    "wof:name":"Tasker Metal Products",
    "wof:placetype":"venue"
},
  "geometry": {"coordinates":[-118.26929800000001,34.03379],"type":"Point"}
}