{
  "type": "Feature",
  "properties": {
    "iso:country":"US",
    "sg:address":"1260 Dell Avenue",
    "sg:city":"Campbell",
    "sg:classifiers":[
        {
            "category":"Building & Trades",
            "subcategory":"Plumbing",
            "type":"Services"
        }
    ],
    "sg:phone":"+1 408 374 7440",
    "sg:postcode":"95008",
    "sg:province":"CA",
    "wof:name":"West Valley Plumbing & Heating.",
    "wof:placetype":"venue"
},
  "geometry": {"coordinates":[-121.95314,37.268358],"type":"Point"}
}