{
  "type": "Feature",
  "properties": {
    "addr:full":"29 Cll Viveza San Clemente CA 92673",
    "addr:housenumber":"29",
    "addr:postcode":"92673",
    "addr:street":"Cll Viveza",
    "iso:country":"US",
    "sg:address":"29 Cll Viveza",
    "sg:city":"San Clemente",
    "sg:classifiers":[
        {
            "category":"Insurance",
            "subcategory":"Insurance Agent",
            "type":"Services"
        }
    ],
    "sg:phone":"+1 949 492 9445",
    "sg:postcode":"92673",
    "sg:province":"CA",
    "wof:name":"Ted Smith Insurance",
    "wof:placetype":"venue"
},
  "geometry": {"coordinates":[-117.576915,33.457337],"type":"Point"}
}