{
  "type": "Feature",
  "properties": {
    "iso:country":"US",
    "sg:address":"1747 King St",
    "sg:city":"Santa Cruz",
    "sg:classifiers":[
        {
            "category":"Manufacturing",
            "subcategory":"Printing",
            "type":"Manufacturing & Wholesale Goods"
        }
    ],
    "sg:phone":"+1 831 427 2202",
    "sg:postcode":"95060",
    "sg:province":"CA",
    "sg:tags":[
        "publishing"
    ],
    "wof:name":"Bloclheadia Ringnosii",
    "wof:placetype":"venue"
},
  "geometry": {"coordinates":[-122.048723,36.962451],"type":"Point"}
}