{
  "type": "Feature",
  "properties": {
    "iso:country":"US",
    "sg:address":"4538 Brookview Ct",
    "sg:city":"Chino Hills",
    "sg:classifiers":[
        {
            "category":"Professional",
            "subcategory":"Accounting & Tax Preparation",
            "type":"Services"
        }
    ],
    "sg:phone":"+1 909 374 6433",
    "sg:postcode":"91709",
    "sg:province":"CA",
    "sg:tags":[
        "billing"
    ],
    "wof:name":"Accubilling Services",
    "wof:placetype":"venue"
},
  "geometry": {"coordinates":[-117.704524,33.978044],"type":"Point"}
}