{
  "type": "Feature",
  "properties": {
    "addr:full":"44 Verona Ct Danville CA 94526",
    "addr:housenumber":"44",
    "addr:postcode":"94526",
    "addr:street":"Verona Ct",
    "iso:country":"US",
    "sg:address":"44 Verona Ct",
    "sg:city":"Danville",
    "sg:classifiers":[
        {
            "category":"Building & Trades",
            "subcategory":"Equipment Rental",
            "type":"Services"
        }
    ],
    "sg:phone":"+1 925 838 4950",
    "sg:postcode":"94526",
    "sg:province":"CA",
    "sg:tags":[
        "aircraft",
        "leasing",
        "charter"
    ],
    "sg:website":"www.wcci.com",
    "wof:name":"World Class Charters Svc",
    "wof:placetype":"venue"
},
  "geometry": {"coordinates":[-122.004841,37.822601],"type":"Point"}
}