{
  "type": "Feature",
  "properties": {
    "addr:full":"921 E Main St Ventura CA 93001",
    "addr:housenumber":"921",
    "addr:postcode":"93001",
    "addr:street":"E Main St",
    "iso:country":"US",
    "sg:address":"921 E Main St",
    "sg:city":"Ventura",
    "sg:classifiers":[
        {
            "category":"Health Services",
            "subcategory":"Clinic",
            "type":"Services"
        }
    ],
    "sg:phone":"+1 805 653 7342",
    "sg:postcode":"93001",
    "sg:province":"CA",
    "sg:tags":[
        "specialty",
        "outpatient"
    ],
    "wof:name":"T Bennett Pathologist",
    "wof:placetype":"venue"
},
  "geometry": {"coordinates":[-119.285713,34.280914],"type":"Point"}
}