{
  "type": "Feature",
  "properties": {
    "iso:country":"US",
    "sg:address":"7853 Houghton Rd",
    "sg:city":"Bakersfield",
    "sg:classifiers":[
        {
            "category":"Professional",
            "type":"Services"
        }
    ],
    "sg:phone":"+1 661 835 8597",
    "sg:postcode":"93313",
    "sg:province":"CA",
    "wof:name":"Zl Rodeo Co",
    "wof:placetype":"venue"
},
  "geometry": {"coordinates":[-119.087653,35.238003],"type":"Point"}
}