{
  "type": "Feature",
  "properties": {
    "iso:country":"US",
    "sg:address":"745 N Perris Blvd",
    "sg:city":"Perris",
    "sg:classifiers":[
        {
            "category":"Organizations",
            "subcategory":"Religious Organization",
            "type":"Services"
        }
    ],
    "sg:phone":"+1 951 657 9566",
    "sg:postcode":"92571",
    "sg:province":"CA",
    "sg:tags":[
        "church"
    ],
    "wof:name":"Templo Bautista Hispano",
    "wof:placetype":"venue"
},
  "geometry": {"coordinates":[-117.226085,33.7953],"type":"Point"}
}