{
  "type": "Feature",
  "properties": {
    "addr:full":"1333 Cam del Rio S San Diego CA 92108",
    "addr:housenumber":"1333",
    "addr:postcode":"92108",
    "addr:street":"Cam Del Rio S",
    "iso:country":"US",
    "sg:address":"1333 Cam del Rio S",
    "sg:city":"San Diego",
    "sg:classifiers":[
        {
            "category":"Health Services",
            "subcategory":"Doctor",
            "type":"Services"
        }
    ],
    "sg:phone":"+1 619 260 4990",
    "sg:postcode":"92108",
    "sg:province":"CA",
    "sg:tags":[
        "dentist"
    ],
    "sg:website":"www.smilecare.com",
    "wof:name":"Smile Care Family Dentistry",
    "wof:placetype":"venue"
},
  "geometry": {"coordinates":[-117.14165300000001,32.768518],"type":"Point"}
}