{
  "type": "Feature",
  "properties": {
    "addr:full":"600 W Grand Ave Porterville CA 93257",
    "addr:housenumber":"600",
    "addr:postcode":"93257",
    "addr:street":"W Grand Ave",
    "iso:country":"US",
    "sg:address":"600 W Grand Ave",
    "sg:city":"Porterville",
    "sg:classifiers":[
        {
            "category":"Education",
            "subcategory":"Special Training",
            "type":"Public Place"
        }
    ],
    "sg:phone":"+1 559 782 7095",
    "sg:postcode":"93257",
    "sg:province":"CA",
    "sg:tags":[
        "educational"
    ],
    "wof:name":"Prospect Education Center",
    "wof:placetype":"venue"
},
  "geometry": {"coordinates":[-119.03053300000001,36.076832],"type":"Point"}
}