{
  "type": "Feature",
  "properties": {
    "iso:country":"US",
    "sg:address":"4910 E Clinton Way",
    "sg:city":"Fresno",
    "sg:classifiers":[
        {
            "category":"Health Services",
            "subcategory":"Clinic",
            "type":"Services"
        },
        {
            "category":"Community Center",
            "type":"Public Place"
        }
    ],
    "sg:phone":"+1 559 453 5200",
    "sg:postcode":"93727",
    "sg:province":"CA",
    "sg:tags":[
        "medical"
    ],
    "sg:website":"http://www.ccfmg.org",
    "wof:name":"Medical Group",
    "wof:placetype":"venue"
},
  "geometry": {"coordinates":[-119.73155300000001,36.772177],"type":"Point"}
}