{
  "type": "Feature",
  "properties": {
    "iso:country":"US",
    "sg:address":"480 Redwood St",
    "sg:city":"Vallejo",
    "sg:classifiers":[
        {
            "category":"Retail",
            "subcategory":"Portrait Studio",
            "type":"Services"
        }
    ],
    "sg:phone":"+1 707 557 4090",
    "sg:postcode":"94590",
    "sg:province":"CA",
    "sg:tags":[
        "photo"
    ],
    "wof:name":"Focus Studio",
    "wof:placetype":"venue"
},
  "geometry": {"coordinates":[-122.256792,38.123305],"type":"Point"}
}