{
  "type": "Feature",
  "properties": {
    "addr:full":"9003 Reseda Blvd Northridge CA 91324",
    "addr:housenumber":"9003",
    "addr:postcode":"91324",
    "addr:street":"Reseda Blvd",
    "iso:country":"US",
    "sg:address":"9003 Reseda Blvd",
    "sg:city":"Northridge",
    "sg:classifiers":[
        {
            "category":"Real Estate",
            "subcategory":"Real Estate Agent",
            "type":"Services"
        }
    ],
    "sg:phone":"+1 818 993 8900",
    "sg:postcode":"91324",
    "sg:province":"CA",
    "sg:tags":[
        "broker"
    ],
    "wof:name":"Prudential",
    "wof:placetype":"venue"
},
  "geometry": {"coordinates":[-118.53616,34.233622],"type":"Point"}
}