{
  "type": "Feature",
  "properties": {
    "addr:full":"555 Ramirez St Los Angeles CA 90012",
    "addr:housenumber":"555",
    "addr:postcode":"90012",
    "addr:street":"Ramirez St",
    "iso:country":"US",
    "sg:address":"555 Ramirez St",
    "sg:city":"Los Angeles",
    "sg:classifiers":[
        {
            "category":"Freight",
            "type":"Transportation"
        },
        {
            "category":"Government",
            "subcategory":"Office",
            "type":"Public Place"
        }
    ],
    "sg:phone":"+1 213 847 0519",
    "sg:postcode":"90012",
    "sg:province":"CA",
    "sg:tags":[
        "terminal",
        "joint",
        "maintenance",
        "facility"
    ],
    "wof:name":"Transportation Dept",
    "wof:placetype":"venue"
},
  "geometry": {"coordinates":[-118.230182,34.053689],"type":"Point"}
}