{
  "type": "Feature",
  "properties": {
    "addr:full":"12700 Everett Ave Hanford CA 93230",
    "addr:housenumber":"12700",
    "addr:postcode":"ca 93230",
    "addr:street":"Everett Ave",
    "iso:country":"US",
    "sg:address":"12700 Everett Ave",
    "sg:city":"Hanford",
    "sg:classifiers":[
        {
            "category":"Farming",
            "subcategory":"Dairy Farm",
            "type":"Manufacturing & Wholesale Goods"
        }
    ],
    "sg:phone":"+1 559 585 0806",
    "sg:postcode":"93230",
    "sg:province":"CA",
    "wof:name":"Double N Dairy",
    "wof:placetype":"venue"
},
  "geometry": {"coordinates":[-119.68026999999999,36.393574],"type":"Point"}
}