{
  "type": "Feature",
  "properties": {
    "iso:country":"US",
    "sg:address":"2215 North Towner",
    "sg:city":"Santa Ana",
    "sg:classifiers":[
        {
            "category":"Building & Trades",
            "subcategory":"Construction",
            "type":"Services"
        }
    ],
    "sg:phone":"+1 714 227 0285",
    "sg:postcode":"92706",
    "sg:province":"CA",
    "sg:tags":[
        "contractor"
    ],
    "wof:name":"Novella Construction",
    "wof:placetype":"venue"
},
  "geometry": {"coordinates":[-117.87919100000001,33.765678],"type":"Point"}
}