{
  "type": "Feature",
  "properties": {
    "addr:full":"1371-A Vallejo St San Francisco CA 94109",
    "addr:housenumber":"1371-a",
    "addr:postcode":"94109",
    "addr:street":"Vallejo St",
    "iso:country":"US",
    "sg:address":"1371-A Vallejo St",
    "sg:city":"San Francisco",
    "sg:classifiers":[
        {
            "category":"Education",
            "subcategory":"Special Training",
            "type":"Public Place"
        },
        {
            "category":"Social Services",
            "subcategory":"Child Care",
            "type":"Services"
        }
    ],
    "sg:phone":"+1 415 205 2682",
    "sg:postcode":"94109",
    "sg:province":"CA",
    "sg:tags":[
        "educational",
        "day"
    ],
    "wof:name":"Little Bee Daycare",
    "wof:placetype":"venue"
},
  "geometry": {"coordinates":[-122.419738,37.79699],"type":"Point"}
}