{
  "type": "Feature",
  "properties": {
    "addr:full":"1750 Ocean Park Blvd Santa Monica CA 90405",
    "addr:housenumber":"1750",
    "addr:postcode":"90405",
    "addr:street":"Ocean Park Blvd",
    "iso:country":"US",
    "sg:address":"1750 Ocean Park Blvd",
    "sg:city":"Santa Monica",
    "sg:classifiers":[
        {
            "category":"Professional",
            "subcategory":"Accounting & Tax Preparation",
            "type":"Services"
        }
    ],
    "sg:phone":"+1 310 399 1556",
    "sg:postcode":"90405",
    "sg:province":"CA",
    "sg:tags":[
        "return",
        "filing"
    ],
    "wof:name":"Jeannine Young & Assoc",
    "wof:placetype":"venue"
},
  "geometry": {"coordinates":[-118.466247,34.01265],"type":"Point"}
}