{
  "type": "Feature",
  "properties": {
    "iso:country":"US",
    "sg:address":"1313 5th St",
    "sg:city":"Santa Monica",
    "sg:classifiers":[
        {
            "category":"Communications",
            "subcategory":"Film & Video Production",
            "type":"Services"
        }
    ],
    "sg:phone":"+1 310 396 7333",
    "sg:postcode":"90401",
    "sg:province":"CA",
    "sg:tags":[
        "motion",
        "picture",
        "studio",
        "producer"
    ],
    "sg:website":"www.bobcentral.com",
    "wof:name":"Bob Industries",
    "wof:placetype":"venue"
},
  "geometry": {"coordinates":[-118.494315,34.017395],"type":"Point"}
}