{
  "type": "Feature",
  "properties": {
    "iso:country":"US",
    "sg:address":"75 Half Moon Rd",
    "sg:city":"Novato",
    "sg:classifiers":[
        {
            "category":"Professional",
            "subcategory":"Computer Services",
            "type":"Services"
        }
    ],
    "sg:phone":"+1 415 893 0150",
    "sg:postcode":"94947",
    "sg:province":"CA",
    "sg:tags":[
        "consultant",
        "designer"
    ],
    "wof:name":"Windigo Systems",
    "wof:placetype":"venue"
},
  "geometry": {"coordinates":[-122.586275,38.092268],"type":"Point"}
}