{
  "type": "Feature",
  "properties": {
    "addr:full":"1671 The Alameda San Jose CA 95126",
    "addr:housenumber":"1671",
    "addr:postcode":"95126",
    "addr:street":"The Alameda",
    "iso:country":"US",
    "sg:address":"1671 The Alameda",
    "sg:city":"San Jose",
    "sg:classifiers":[
        {
            "category":"Professional",
            "subcategory":"Lawyer & Legal Services",
            "type":"Services"
        }
    ],
    "sg:phone":"+1 408 293 8400",
    "sg:postcode":"95126",
    "sg:province":"CA",
    "wof:name":"Wilson Stuart M --Atty--",
    "wof:placetype":"venue"
},
  "geometry": {"coordinates":[-121.918148,37.336532],"type":"Point"}
}