{
  "type": "Feature",
  "properties": {
    "addr:full":"617 Main St Susanville CA 96130",
    "addr:housenumber":"617",
    "addr:postcode":"96130",
    "addr:street":"Main St",
    "iso:country":"US",
    "sg:address":"617 Main St",
    "sg:city":"Susanville",
    "sg:classifiers":[
        {
            "category":"Retail",
            "subcategory":"Portrait Studio",
            "type":"Services"
        }
    ],
    "sg:phone":"+1 530 251 5588",
    "sg:postcode":"96130",
    "sg:province":"CA",
    "sg:tags":[
        "photographer"
    ],
    "wof:name":"Creative Images Photography",
    "wof:placetype":"venue"
},
  "geometry": {"coordinates":[-120.662981,40.418953],"type":"Point"}
}