{
  "type": "Feature",
  "properties": {
    "iso:country":"US",
    "sg:address":"3470 Wilshire Blvd Ste 1022",
    "sg:city":"Los Angeles",
    "sg:classifiers":[
        {
            "category":"Cinema",
            "subcategory":"Movie Theater",
            "type":"Entertainment"
        }
    ],
    "sg:phone":"+1 213 480 7088",
    "sg:postcode":"90010",
    "sg:province":"CA",
    "sg:website":"www.outfest.org",
    "wof:name":"Outfest",
    "wof:placetype":"venue"
},
  "geometry": {"coordinates":[-118.299004,34.061699],"type":"Point"}
}