{
  "type": "Feature",
  "properties": {
    "iso:country":"US",
    "sg:address":"5345 Geary Blvd",
    "sg:city":"San Francisco",
    "sg:classifiers":[
        {
            "category":"Shopping",
            "subcategory":"Pharmacy",
            "type":"Retail Goods"
        }
    ],
    "sg:phone":"+1 415 831 8600",
    "sg:postcode":"94121",
    "sg:province":"CA",
    "wof:name":"Canadian Disc Pharmaceutical",
    "wof:placetype":"venue"
},
  "geometry": {"coordinates":[-122.476829,37.78031],"type":"Point"}
}