{
  "type": "Feature",
  "properties": {
    "addr:full":"917 6th St Woodland CA 95695",
    "addr:housenumber":"917",
    "addr:postcode":"95695",
    "addr:street":"6Th St",
    "iso:country":"US",
    "sg:address":"917 6th St",
    "sg:city":"Woodland",
    "sg:classifiers":[
        {
            "category":"Freight",
            "type":"Transportation"
        }
    ],
    "sg:phone":"+1 530 668 0435",
    "sg:postcode":"95695",
    "sg:province":"CA",
    "sg:tags":[
        "operator",
        "local",
        "trucking"
    ],
    "wof:name":"JB Gracian Trucking",
    "wof:placetype":"venue"
},
  "geometry": {"coordinates":[-121.76735100000001,38.666342],"type":"Point"}
}