{
  "type": "Feature",
  "properties": {
    "addr:full":"556 Mississippi Street San Francisco CA 94107",
    "addr:housenumber":"556",
    "addr:postcode":"94107",
    "addr:street":"Mississippi Street",
    "iso:country":"US",
    "sg:address":"556 Mississippi Street",
    "sg:city":"San Francisco",
    "sg:classifiers":[
        {
            "category":"Building & Trades",
            "subcategory":"Construction",
            "type":"Services"
        }
    ],
    "sg:phone":"+1 415 821 3481",
    "sg:postcode":"94107",
    "sg:province":"CA",
    "sg:tags":[
        "contractor"
    ],
    "wof:name":"Capron Construction",
    "wof:placetype":"venue"
},
  "geometry": {"coordinates":[-122.39443799999999,37.75957],"type":"Point"}
}