{
  "type": "Feature",
  "properties": {
    "addr:full":"1900 Thau Way Alameda CA 94501",
    "addr:postcode":"1900;94501",
    "addr:street":"Thau Way",
    "iso:country":"US",
    "sg:address":"1900 Thau Way",
    "sg:city":"Alameda",
    "sg:classifiers":[
        {
            "category":"Government",
            "subcategory":"City Hall",
            "type":"Public Place"
        },
        {
            "category":"Restaurant",
            "type":"Food & Drink"
        },
        {
            "category":"Organizations",
            "subcategory":"Non-profit Organization",
            "type":"Services"
        }
    ],
    "sg:phone":"+1 510 523 5850",
    "sg:postcode":"94501",
    "sg:province":"CA",
    "sg:tags":[
        "community",
        "service/non-profit"
    ],
    "sg:website":"alamedafoodbank.org",
    "wof:name":"Alameda Food Bank",
    "wof:placetype":"venue"
},
  "geometry": {"coordinates":[-122.261002,37.768101],"type":"Point"}
}