{
  "type": "Feature",
  "properties": {
    "iso:country":"US",
    "sg:address":"1955 Zinfandel Dr",
    "sg:city":"Rancho Cordova",
    "sg:classifiers":[
        {
            "category":"Sports & Exercise",
            "subcategory":"Bicycle Rental",
            "type":"Entertainment"
        },
        {
            "category":"Sports & Exercise",
            "subcategory":"Tennis Court",
            "type":"Entertainment"
        }
    ],
    "sg:phone":"+1 916 858 8343",
    "sg:postcode":"95670",
    "sg:province":"CA",
    "sg:tags":[
        "wear"
    ],
    "sg:website":"www.courtsidetennis.com",
    "wof:name":"Courtside TENNIS & Apparel",
    "wof:placetype":"venue"
},
  "geometry": {"coordinates":[-121.271387,38.613784],"type":"Point"}
}