{
  "type": "Feature",
  "properties": {
    "iso:country":"US",
    "sg:address":"32215 Via Almazan",
    "sg:city":"Temecula",
    "sg:classifiers":[
        {
            "category":"Wholesale",
            "subcategory":"Groceries",
            "type":"Manufacturing & Wholesale Goods"
        }
    ],
    "sg:phone":"+1 951 440 7172",
    "sg:postcode":"92592",
    "sg:province":"CA",
    "sg:tags":[
        "confectionery"
    ],
    "wof:name":"Desert Snax",
    "wof:placetype":"venue"
},
  "geometry": {"coordinates":[-117.09535,33.465256],"type":"Point"}
}