{
  "type": "Feature",
  "properties": {
    "iso:country":"US",
    "sg:address":"1111 Firestone Blvd",
    "sg:city":"Los Angeles",
    "sg:classifiers":[
        {
            "category":"Professional",
            "type":"Services"
        }
    ],
    "sg:phone":"+1 323 650 5270",
    "sg:postcode":"90001",
    "sg:province":"CA",
    "wof:name":"Gerald Willard",
    "wof:placetype":"venue"
},
  "geometry": {"coordinates":[-118.256124,33.960245],"type":"Point"}
}