{
  "type": "Feature",
  "properties": {
    "iso:country":"US",
    "sg:address":"561 E Oxford St",
    "sg:city":"Chula Vista",
    "sg:classifiers":[
        {
            "category":"Professional",
            "subcategory":"Management & Consulting",
            "type":"Services"
        }
    ],
    "sg:phone":"+1 619 422 8899",
    "sg:postcode":"91911",
    "sg:province":"CA",
    "sg:tags":[
        "retail",
        "direct",
        "sales"
    ],
    "wof:name":"Eutierrez Noemi",
    "wof:placetype":"venue"
},
  "geometry": {"coordinates":[-117.035719,32.619622],"type":"Point"}
}