{
  "type": "Feature",
  "properties": {
    "addr:full":"1117 Coast Village Rd Santa Barbara CA 93108",
    "addr:housenumber":"1117",
    "addr:postcode":"93108",
    "addr:street":"Coast Village Rd",
    "iso:country":"US",
    "sg:address":"1117 Coast Village Rd",
    "sg:city":"Santa Barbara",
    "sg:classifiers":[
        {
            "category":"Real Estate",
            "subcategory":"Architect",
            "type":"Services"
        }
    ],
    "sg:phone":"+1 805 565 3640",
    "sg:postcode":"93108",
    "sg:province":"CA",
    "wof:name":"Pacific Arc Inc Architects",
    "wof:placetype":"venue"
},
  "geometry": {"coordinates":[-119.645145,34.421021],"type":"Point"}
}