{
  "type": "Feature",
  "properties": {
    "iso:country":"US",
    "sg:address":"518 Main St",
    "sg:city":"Martinez",
    "sg:classifiers":[
        {
            "category":"Professional",
            "subcategory":"Lawyer & Legal Services",
            "type":"Services"
        }
    ],
    "sg:phone":"+1 925 228 3191",
    "sg:postcode":"94553",
    "sg:province":"CA",
    "sg:tags":[
        "attorney",
        "bureau"
    ],
    "wof:name":"One Legal Svc Inc",
    "wof:placetype":"venue"
},
  "geometry": {"coordinates":[-122.138212,38.016254],"type":"Point"}
}