{
  "type": "Feature",
  "properties": {
    "iso:country":"US",
    "sg:address":"356 Harvest Ln",
    "sg:city":"Santa Rosa",
    "sg:classifiers":[
        {
            "category":"Professional",
            "type":"Services"
        }
    ],
    "sg:phone":"+1 707 526 0802",
    "sg:postcode":"95401",
    "sg:province":"CA",
    "wof:name":"Joseph R Pinochi",
    "wof:placetype":"venue"
},
  "geometry": {"coordinates":[-122.747568,38.433144],"type":"Point"}
}