{
  "type": "Feature",
  "properties": {
    "iso:country":"US",
    "sg:address":"1596 E F St",
    "sg:city":"Oakdale",
    "sg:classifiers":[
        {
            "category":"Shopping",
            "subcategory":"Bicycles & Sporting Goods",
            "type":"Retail Goods"
        }
    ],
    "sg:phone":"+1 209 847 2537",
    "sg:postcode":"95361",
    "sg:province":"CA",
    "wof:name":"Big 5 Sporting Goods",
    "wof:placetype":"venue"
},
  "geometry": {"coordinates":[-120.830608,37.772725],"type":"Point"}
}