{
  "type": "Feature",
  "properties": {
    "addr:full":"1136 Walsh Ave Santa Clara CA 95050",
    "addr:housenumber":"1136",
    "addr:postcode":"95050",
    "addr:street":"Walsh Ave",
    "iso:country":"US",
    "sg:address":"1136 Walsh Ave",
    "sg:city":"Santa Clara",
    "sg:classifiers":[
        {
            "category":"Manufacturing",
            "subcategory":"Tools & Machinery",
            "type":"Manufacturing & Wholesale Goods"
        }
    ],
    "sg:phone":"+1 408 982 9703",
    "sg:postcode":"95050",
    "sg:province":"CA",
    "sg:tags":[
        "machine",
        "shop"
    ],
    "wof:name":"C J Machining",
    "wof:placetype":"venue"
},
  "geometry": {"coordinates":[-121.95251,37.369683],"type":"Point"}
}