{
  "type": "Feature",
  "properties": {
    "addr:full":"815 Tamlei Ave Thousand Oaks CA 91362",
    "addr:housenumber":"815",
    "addr:postcode":"91362",
    "addr:street":"Tamlei Ave",
    "iso:country":"US",
    "sg:address":"815 Tamlei Ave",
    "sg:city":"Thousand Oaks",
    "sg:classifiers":[
        {
            "category":"Banks & Credit Unions",
            "subcategory":"Bank",
            "type":"Services"
        }
    ],
    "sg:phone":"+1 805 495 9880",
    "sg:postcode":"91362",
    "sg:province":"CA",
    "sg:tags":[
        "loan",
        "real estate"
    ],
    "wof:name":"Discount Real Estate-Mortgage",
    "wof:placetype":"venue"
},
  "geometry": {"coordinates":[-118.849621,34.189733],"type":"Point"}
}