{
  "type": "Feature",
  "properties": {
    "addr:full":"6801 White Ln Bakersfield CA 93309",
    "addr:housenumber":"6801",
    "addr:postcode":"93309",
    "addr:street":"White Ln",
    "iso:country":"US",
    "sg:address":"6801 White Ln",
    "sg:city":"Bakersfield",
    "sg:classifiers":[
        {
            "category":"Home & Garden",
            "subcategory":"Furniture",
            "type":"Retail Goods"
        }
    ],
    "sg:phone":"+1 661 831 1179",
    "sg:postcode":"93309",
    "sg:province":"CA",
    "sg:tags":[
        "equipment",
        "patio",
        "supply"
    ],
    "wof:name":"Patio Shoppe",
    "wof:placetype":"venue"
},
  "geometry": {"coordinates":[-119.081622,35.318218],"type":"Point"}
}