{
  "type": "Feature",
  "properties": {
    "iso:country":"US",
    "sg:address":"403 East Gutierrez",
    "sg:city":"Santa Barbara",
    "sg:classifiers":[
        {
            "category":"Professional",
            "subcategory":"Advertising",
            "type":"Services"
        }
    ],
    "sg:phone":"+1 888 844 6256",
    "sg:postcode":"93030",
    "sg:province":"CA",
    "sg:tags":[
        "twitter-for-iphone",
        "ruby-on-rails",
        "signalfire",
        "electric-checkbook",
        "logpost",
        "branding",
        "sell-the-truth",
        "authenticity"
    ],
    "sg:website":"http://newleaders.com",
    "wof:name":"New Leaders",
    "wof:placetype":"venue"
},
  "geometry": {"coordinates":[-119.162103,34.215238],"type":"Point"}
}