{
  "type": "Feature",
  "properties": {
    "addr:full":"1991 Burroughs Ave San Leandro CA 94577",
    "addr:housenumber":"1991",
    "addr:postcode":"94577",
    "addr:street":"Burroughs Ave",
    "iso:country":"US",
    "sg:address":"1991 Burroughs Ave",
    "sg:city":"San Leandro",
    "sg:classifiers":[
        {
            "category":"Building & Trades",
            "subcategory":"Plumbing",
            "type":"Services"
        }
    ],
    "sg:phone":"+1 510 618 1360",
    "sg:postcode":"94577",
    "sg:province":"CA",
    "sg:website":"www.olssonplumbing.com",
    "wof:name":"Olsson Plumbing & Heating",
    "wof:placetype":"venue"
},
  "geometry": {"coordinates":[-122.166496,37.698382],"type":"Point"}
}