{
  "type": "Feature",
  "properties": {
    "addr:full":"5205 W Pico Blvd Los Angeles CA 90019",
    "addr:housenumber":"5205",
    "addr:postcode":"90019",
    "addr:street":"W Pico Blvd",
    "iso:country":"US",
    "sg:address":"5205 W Pico Blvd",
    "sg:city":"Los Angeles",
    "sg:classifiers":[
        {
            "category":"Home & Garden",
            "subcategory":"Furniture",
            "type":"Retail Goods"
        }
    ],
    "sg:phone":"+1 323 936 2444",
    "sg:postcode":"90019",
    "sg:province":"CA",
    "sg:tags":[
        "equipment",
        "kitchen",
        "cabinet"
    ],
    "wof:name":"S & S Floor Covering Supply",
    "wof:placetype":"venue"
},
  "geometry": {"coordinates":[-118.352594,34.0483],"type":"Point"}
}