{
  "type": "Feature",
  "properties": {
    "iso:country":"US",
    "sg:address":"2707 Zoe Ave",
    "sg:city":"Huntington Park",
    "sg:classifiers":[
        {
            "category":"Professional",
            "subcategory":"Accounting & Tax Preparation",
            "type":"Services"
        }
    ],
    "sg:phone":"+1 323 589 2645",
    "sg:postcode":"90255",
    "sg:province":"CA",
    "sg:tags":[
        "return",
        "filing"
    ],
    "wof:name":"Sus Amigos",
    "wof:placetype":"venue"
},
  "geometry": {"coordinates":[-118.222024,33.979348],"type":"Point"}
}