{
  "type": "Feature",
  "properties": {
    "iso:country":"US",
    "sg:address":"2121 Pine St",
    "sg:city":"San Francisco",
    "sg:classifiers":[
        {
            "category":"Health Services",
            "subcategory":"Nursing And Care Facility",
            "type":"Services"
        }
    ],
    "sg:phone":"+1 415 922 5085",
    "sg:postcode":"94115",
    "sg:province":"CA",
    "sg:tags":[
        "skilled"
    ],
    "wof:name":"Kindred Healthcare Inc",
    "wof:placetype":"venue"
},
  "geometry": {"coordinates":[-122.431725,37.788128],"type":"Point"}
}