{
  "type": "Feature",
  "properties": {
    "addr:full":"12323 Sherman Way North Hollywood CA 91605",
    "addr:housenumber":"12323",
    "addr:postcode":"91605",
    "addr:street":"Sherman Way",
    "iso:country":"US",
    "sg:address":"12323 Sherman Way",
    "sg:city":"North Hollywood",
    "sg:classifiers":[
        {
            "category":"Wholesale",
            "subcategory":"Machinery & Supplies",
            "type":"Manufacturing & Wholesale Goods"
        }
    ],
    "sg:phone":"+1 818 765 5015",
    "sg:postcode":"91605",
    "sg:province":"CA",
    "sg:tags":[
        "box",
        "industrial",
        "fiber",
        "mfg"
    ],
    "wof:name":"Marfred Industries",
    "wof:placetype":"venue"
},
  "geometry": {"coordinates":[-118.39651499999999,34.200609],"type":"Point"}
}