{
  "type": "Feature",
  "properties": {
    "iso:country":"US",
    "sg:address":"1002 T St",
    "sg:city":"Fresno",
    "sg:classifiers":[
        {
            "category":"Retail",
            "subcategory":"Funeral Services",
            "type":"Services"
        }
    ],
    "sg:phone":"+1 559 237 4147",
    "sg:postcode":"93721",
    "sg:province":"CA",
    "sg:tags":[
        "director"
    ],
    "sg:website":"www.yostandwebb.com",
    "wof:name":"Yost & WEBB Funeral Home",
    "wof:placetype":"venue"
},
  "geometry": {"coordinates":[-119.780897,36.742196],"type":"Point"}
}