{
  "type": "Feature",
  "properties": {
    "addr:full":"2215 E Florence Ave Huntington Park CA 90255",
    "addr:housenumber":"2215",
    "addr:postcode":"90255",
    "addr:street":"E Florence Ave;Park",
    "iso:country":"US",
    "sg:address":"2215 E Florence Ave",
    "sg:city":"Huntington Park",
    "sg:classifiers":[
        {
            "category":"Retail",
            "subcategory":"Auto Repair",
            "type":"Services"
        }
    ],
    "sg:phone":"+1 323 584 0406",
    "sg:postcode":"90255",
    "sg:province":"CA",
    "sg:tags":[
        "body",
        "shop"
    ],
    "wof:name":"Florence Auto Body",
    "wof:placetype":"venue"
},
  "geometry": {"coordinates":[-118.233002,33.974899],"type":"Point"}
}