{
  "type": "Feature",
  "properties": {
    "iso:country":"US",
    "sg:address":"1303 W El Segundo Blvd",
    "sg:city":"Gardena",
    "sg:classifiers":[
        {
            "category":"Shopping",
            "subcategory":"Clothing, Apparel, & Fashions",
            "type":"Retail Goods"
        },
        {
            "category":"Manufacturing",
            "subcategory":"Textiles",
            "type":"Manufacturing & Wholesale Goods"
        }
    ],
    "sg:phone":"+1 323 754 5723",
    "sg:postcode":"90247",
    "sg:province":"CA",
    "sg:tags":[
        "apparel",
        "contractor",
        "sewing",
        "alterations-clothing",
        "women's"
    ],
    "wof:name":"Mimi Fashions",
    "wof:placetype":"venue"
},
  "geometry": {"coordinates":[-118.298751,33.916431],"type":"Point"}
}