{
  "type": "Feature",
  "properties": {
    "addr:full":"726 Main St Woodland CA 95695",
    "addr:housenumber":"726",
    "addr:postcode":"95695",
    "addr:street":"Main St",
    "iso:country":"US",
    "sg:address":"726 Main St",
    "sg:city":"Woodland",
    "sg:classifiers":[
        {
            "category":"Banks & Credit Unions",
            "subcategory":"Bank",
            "type":"Services"
        }
    ],
    "sg:phone":"+1 530 666 4242",
    "sg:postcode":"95695",
    "sg:province":"CA",
    "sg:tags":[
        "loan",
        "real estate"
    ],
    "wof:name":"First Priority Financial",
    "wof:placetype":"venue"
},
  "geometry": {"coordinates":[-121.770951,38.677383],"type":"Point"}
}