{
  "type": "Feature",
  "properties": {
    "iso:country":"US",
    "sg:address":"36111 Adobe Dr",
    "sg:city":"Fremont",
    "sg:classifiers":[
        {
            "category":"Banks & Credit Unions",
            "subcategory":"Bank",
            "type":"Services"
        }
    ],
    "sg:phone":"+1 510 796 8027",
    "sg:postcode":"94536",
    "sg:province":"CA",
    "sg:tags":[
        "federal",
        "agency"
    ],
    "wof:name":"K Dynasty",
    "wof:placetype":"venue"
},
  "geometry": {"coordinates":[-122.02443700000001,37.559015],"type":"Point"}
}