{
  "type": "Feature",
  "properties": {
    "addr:full":"1319 S Prairie Flower Rd Turlock CA 95380",
    "addr:housenumber":"1319",
    "addr:postcode":"95380",
    "addr:street":"S Prairie Flower Rd",
    "iso:country":"US",
    "sg:address":"1319 S Prairie Flower Rd",
    "sg:city":"Turlock",
    "sg:classifiers":[
        {
            "category":"Farming",
            "subcategory":"Farm & Veterinary Services",
            "type":"Manufacturing & Wholesale Goods"
        }
    ],
    "sg:phone":"+1 209 667 1220",
    "sg:postcode":"95380",
    "sg:province":"CA",
    "sg:tags":[
        "embryo",
        "transfer",
        "cattle"
    ],
    "wof:name":"Web Embryo Transfer Service",
    "wof:placetype":"venue"
},
  "geometry": {"coordinates":[-120.930952,37.472865],"type":"Point"}
}