{
  "type": "Feature",
  "properties": {
    "addr:full":"7532 Edinger Ave Huntington Beach CA 92647",
    "addr:housenumber":"7532",
    "addr:postcode":"92647",
    "addr:street":"Edinger Ave",
    "iso:country":"US",
    "sg:address":"7532 Edinger Ave",
    "sg:city":"Huntington Beach",
    "sg:classifiers":[
        {
            "category":"Home & Garden",
            "subcategory":"Household Appliances",
            "type":"Retail Goods"
        },
        {
            "category":"Shopping",
            "subcategory":"Computers & Home Electronics",
            "type":"Retail Goods"
        }
    ],
    "sg:phone":"+1 714 841 5447",
    "sg:postcode":"92647",
    "sg:province":"CA",
    "sg:website":"www.howards.com",
    "wof:name":"Howard's Appliance & Big Screen",
    "wof:placetype":"venue"
},
  "geometry": {"coordinates":[-117.997164,33.730084],"type":"Point"}
}