{
  "type": "Feature",
  "properties": {
    "iso:country":"US",
    "sg:address":"1821 S Bascom Ave",
    "sg:city":"Campbell",
    "sg:classifiers":[
        {
            "category":"Building & Trades",
            "subcategory":"Construction",
            "type":"Services"
        }
    ],
    "sg:phone":"+1 888 839 2136",
    "sg:postcode":"95008",
    "sg:province":"CA",
    "sg:tags":[
        "roofing"
    ],
    "sg:website":"skylightsincampbell.info/",
    "wof:name":"Lentz Construction Inc - Roof Skylights in Campbell CA",
    "wof:placetype":"venue"
},
  "geometry": {"coordinates":[-121.932044,37.290705],"type":"Point"}
}