{
  "type": "Feature",
  "properties": {
    "addr:full":"3212 Meridian Ave San Jose CA 95124",
    "addr:housenumber":"3212",
    "addr:postcode":"95124",
    "addr:street":"Meridian Ave",
    "iso:country":"US",
    "sg:address":"3212 Meridian Ave",
    "sg:city":"San Jose",
    "sg:classifiers":[
        {
            "category":"Professional",
            "type":"Services"
        }
    ],
    "sg:phone":"+1 408 978 1383",
    "sg:postcode":"95124",
    "sg:province":"CA",
    "wof:name":"Joyous Creations",
    "wof:placetype":"venue"
},
  "geometry": {"coordinates":[-121.904984,37.269103],"type":"Point"}
}