{
  "type": "Feature",
  "properties": {
    "iso:country":"US",
    "sg:address":"527 Figueroa St",
    "sg:city":"Wilmington",
    "sg:classifiers":[
        {
            "category":"Building & Trades",
            "subcategory":"Construction",
            "type":"Services"
        }
    ],
    "sg:phone":"+1 310 835 7300",
    "sg:postcode":"90744",
    "sg:province":"CA",
    "sg:tags":[
        "contractor"
    ],
    "wof:name":"Retail Property Services",
    "wof:placetype":"venue"
},
  "geometry": {"coordinates":[-118.278999,33.7757],"type":"Point"}
}