{
  "type": "Feature",
  "properties": {
    "iso:country":"US",
    "sg:address":"152 Frank West Cir Ste 200",
    "sg:city":"Stockton",
    "sg:classifiers":[
        {
            "category":"Manufacturing",
            "subcategory":"Buildings",
            "type":"Manufacturing & Wholesale Goods"
        },
        {
            "category":"Professional",
            "subcategory":"Art Services",
            "type":"Services"
        },
        {
            "category":"Building & Trades",
            "subcategory":"Construction",
            "type":"Services"
        }
    ],
    "sg:phone":"+1 209 234 5900",
    "sg:postcode":"95206",
    "sg:province":"CA",
    "sg:tags":[
        "designer",
        "builder",
        "contractor",
        "interior",
        "home",
        "decorator"
    ],
    "wof:name":"Builders Showcase Interiors",
    "wof:placetype":"venue"
},
  "geometry": {"coordinates":[-121.27825300000001,37.897417],"type":"Point"}
}