{
  "type": "Feature",
  "properties": {
    "iso:country":"US",
    "sg:address":"1985 Cameo Ct",
    "sg:city":"Redding",
    "sg:classifiers":[
        {
            "category":"Building & Trades",
            "subcategory":"Construction",
            "type":"Services"
        }
    ],
    "sg:phone":"+1 530 515 0269",
    "sg:postcode":"96002",
    "sg:province":"CA",
    "sg:tags":[
        "altering",
        "consultant",
        "remodeling",
        "contractor"
    ],
    "wof:name":"David W. Hittenberger",
    "wof:placetype":"venue"
},
  "geometry": {"coordinates":[-122.34280200000001,40.57848],"type":"Point"}
}