{
  "type": "Feature",
  "properties": {
    "addr:full":"1760 S Bascom Ave Campbell CA 95008",
    "addr:housenumber":"1760",
    "addr:postcode":"95008",
    "addr:street":"S Bascom Ave",
    "iso:country":"US",
    "sg:address":"1760 S Bascom Ave",
    "sg:city":"Campbell",
    "sg:classifiers":[
        {
            "category":"Shopping",
            "subcategory":"Stationery & Office Supplies",
            "type":"Retail Goods"
        }
    ],
    "sg:phone":"+1 408 369 7350",
    "sg:postcode":"95008",
    "sg:province":"CA",
    "sg:tags":[
        "equipment"
    ],
    "wof:name":"Officemax",
    "wof:placetype":"venue"
},
  "geometry": {"coordinates":[-121.931999,37.2901],"type":"Point"}
}