{
  "type": "Feature",
  "properties": {
    "iso:country":"US",
    "sg:address":"23706 Crenshaw Blvd Ste 103",
    "sg:city":"Torrance",
    "sg:classifiers":[
        {
            "category":"Education",
            "subcategory":"Special Training",
            "type":"Public Place"
        }
    ],
    "sg:phone":"+1 310 534 0196",
    "sg:postcode":"90505",
    "sg:province":"CA",
    "sg:tags":[
        "school",
        "art"
    ],
    "wof:name":"Torrance Art Center",
    "wof:placetype":"venue"
},
  "geometry": {"coordinates":[-118.328003,33.809601],"type":"Point"}
}