{
  "type": "Feature",
  "properties": {
    "addr:full":"13639 E Manning Ave Parlier CA 93648",
    "addr:housenumber":"13639",
    "addr:postcode":"93648",
    "addr:street":"E Manning Ave",
    "iso:country":"US",
    "sg:address":"13639 E Manning Ave",
    "sg:city":"Parlier",
    "sg:classifiers":[
        {
            "category":"Banks & Credit Unions",
            "subcategory":"Bank",
            "type":"Services"
        }
    ],
    "sg:phone":"+1 559 646 2303",
    "sg:postcode":"93648",
    "sg:province":"CA",
    "sg:tags":[
        "money",
        "order"
    ],
    "wof:name":"Dolex Dollar Express",
    "wof:placetype":"venue"
},
  "geometry": {"coordinates":[-119.542806,36.604816],"type":"Point"}
}