{
  "type": "Feature",
  "properties": {
    "addr:full":"9813 Fair Oaks Blvd Fair Oaks CA 95628",
    "addr:housenumber":"9813",
    "addr:postcode":"95628",
    "addr:street":"Fair Oaks Blvd",
    "iso:country":"US",
    "sg:address":"9813 Fair Oaks Blvd",
    "sg:city":"Fair Oaks",
    "sg:classifiers":[
        {
            "category":"Social Services",
            "type":"Services"
        }
    ],
    "sg:phone":"+1 916 863 0461",
    "sg:postcode":"95628",
    "sg:province":"CA",
    "sg:tags":[
        "organization",
        "welfare"
    ],
    "wof:name":"Home At Last Inc",
    "wof:placetype":"venue"
},
  "geometry": {"coordinates":[-121.275767,38.63938],"type":"Point"}
}