{
  "type": "Feature",
  "properties": {
    "addr:full":"4062 Flying C Rd Cameron Park CA 95682",
    "addr:housenumber":"4062",
    "addr:postcode":"95682",
    "addr:street":"Flying C;Park",
    "iso:country":"US",
    "sg:address":"4062 Flying C Rd",
    "sg:city":"Cameron Park",
    "sg:classifiers":[
        {
            "category":"Banks & Credit Unions",
            "subcategory":"Bank",
            "type":"Services"
        }
    ],
    "sg:phone":"+1 530 672 1500",
    "sg:postcode":"95682",
    "sg:province":"CA",
    "sg:tags":[
        "loan",
        "real estate"
    ],
    "sg:website":"www.stanfordloans.com",
    "wof:name":"Stanford Mortgage",
    "wof:placetype":"venue"
},
  "geometry": {"coordinates":[-120.99809999999999,38.655603],"type":"Point"}
}