{
  "type": "Feature",
  "properties": {
    "addr:full":"6355 Compton Ave Los Angeles CA 90001",
    "addr:housenumber":"6355",
    "addr:postcode":"90001",
    "addr:street":"Compton Ave",
    "iso:country":"US",
    "sg:address":"6355 Compton Ave",
    "sg:city":"Los Angeles",
    "sg:classifiers":[
        {
            "category":"Wholesale",
            "subcategory":"Scrap",
            "type":"Manufacturing & Wholesale Goods"
        }
    ],
    "sg:phone":"+1 323 582 7060",
    "sg:postcode":"90001",
    "sg:province":"CA",
    "sg:tags":[
        "recycling",
        "center"
    ],
    "wof:name":"Bargain Center",
    "wof:placetype":"venue"
},
  "geometry": {"coordinates":[-118.24775,33.981787],"type":"Point"}
}