{
  "type": "Feature",
  "properties": {
    "iso:country":"US",
    "sg:address":"1414 Pacific Coast Hwy",
    "sg:city":"Hermosa Beach",
    "sg:classifiers":[
        {
            "category":"Retail",
            "subcategory":"Auto Repair",
            "type":"Services"
        }
    ],
    "sg:phone":"+1 310 798 7929",
    "sg:postcode":"90254",
    "sg:province":"CA",
    "sg:tags":[
        "repairing",
        "automobile"
    ],
    "wof:name":"Discount Tire Ctr",
    "wof:placetype":"venue"
},
  "geometry": {"coordinates":[-118.393129,33.865431],"type":"Point"}
}