{
  "type": "Feature",
  "properties": {
    "iso:country":"US",
    "sg:address":"340 S Farrell Dr",
    "sg:city":"Palm Springs",
    "sg:classifiers":[
        {
            "category":"Health Services",
            "subcategory":"Doctor",
            "type":"Services"
        }
    ],
    "sg:phone":"+1 760 325 2545",
    "sg:postcode":"92262",
    "sg:province":"CA",
    "wof:name":"Nazareth Ivor J MD",
    "wof:placetype":"venue"
},
  "geometry": {"coordinates":[-116.51799800000001,33.818802],"type":"Point"}
}