{
  "type": "Feature",
  "properties": {
    "addr:full":"23161 Mill Creek Dr. #100 Laguna Hills CA 92653",
    "addr:housenumber":"23161",
    "addr:postcode":"92653",
    "addr:street":"Mill Creek Dr. # 100",
    "iso:country":"US",
    "sg:address":"23161 Mill Creek Dr. #100",
    "sg:city":"Laguna Hills",
    "sg:classifiers":[
        {
            "category":"Insurance",
            "subcategory":"Hazard Insurance",
            "type":"Services"
        }
    ],
    "sg:phone":"+1 949 586 2313",
    "sg:postcode":"92653",
    "sg:province":"CA",
    "wof:name":"Canzone Insurance Agency / Farmers Insurance Group",
    "wof:placetype":"venue"
},
  "geometry": {"coordinates":[-117.73536300000001,33.627004],"type":"Point"}
}