{
  "type": "Feature",
  "properties": {
    "iso:country":"US",
    "sg:address":"2192 Martin Ste 250",
    "sg:city":"Irvine",
    "sg:classifiers":[
        {
            "category":"Health Services",
            "subcategory":"Dentist",
            "type":"Services"
        }
    ],
    "sg:phone":"+1 949 752 5050",
    "sg:postcode":"92612",
    "sg:province":"CA",
    "sg:website":"www.truesmile.com",
    "wof:name":"Monica Trieu, DDS",
    "wof:placetype":"venue"
},
  "geometry": {"coordinates":[-117.860657,33.672126],"type":"Point"}
}