{
  "type": "Feature",
  "properties": {
    "addr:full":"2540 Oak Park Ln Campbell CA 95008",
    "addr:housenumber":"2540",
    "addr:postcode":"95008",
    "addr:street":"Oak Park Ln",
    "iso:country":"US",
    "sg:address":"2540 Oak Park Ln",
    "sg:city":"Campbell",
    "sg:classifiers":[
        {
            "category":"Shopping",
            "subcategory":"Clothing, Apparel, & Fashions",
            "type":"Retail Goods"
        }
    ],
    "sg:phone":"+1 408 246 3311",
    "sg:postcode":"95008",
    "sg:province":"CA",
    "sg:tags":[
        "t"
    ],
    "wof:name":"Koala-T's Inc",
    "wof:placetype":"venue"
},
  "geometry": {"coordinates":[-121.940451,37.275636],"type":"Point"}
}