{
  "type": "Feature",
  "properties": {
    "addr:full":"1111 Morse Ave Sunnyvale CA 94089",
    "addr:housenumber":"1111",
    "addr:postcode":"94089",
    "addr:street":"Morse Ave",
    "iso:country":"US",
    "sg:address":"1111 Morse Ave",
    "sg:city":"Sunnyvale",
    "sg:classifiers":[
        {
            "category":"Retail",
            "subcategory":"Auto Rental",
            "type":"Services"
        }
    ],
    "sg:phone":"+1 408 734 8900",
    "sg:postcode":"94089",
    "sg:province":"CA",
    "sg:tags":[
        "mobile",
        "home",
        "leasing"
    ],
    "wof:name":"Willow Ranch",
    "wof:placetype":"venue"
},
  "geometry": {"coordinates":[-122.01591999999999,37.40182],"type":"Point"}
}