{
  "type": "Feature",
  "properties": {
    "iso:country":"US",
    "sg:address":"1531 Purdue Ave",
    "sg:city":"Los Angeles",
    "sg:classifiers":[
        {
            "category":"Health Services",
            "subcategory":"Health Practitioner",
            "type":"Services"
        }
    ],
    "sg:phone":"+1 310 473 1885",
    "sg:postcode":"90025",
    "sg:province":"CA",
    "sg:tags":[
        "psychotherapist"
    ],
    "wof:name":"Terry Gisele",
    "wof:placetype":"venue"
},
  "geometry": {"coordinates":[-118.451106,34.046219],"type":"Point"}
}