{
  "type": "Feature",
  "properties": {
    "addr:full":"2001 S Barrington Ave Los Angeles CA 90025",
    "addr:housenumber":"2001",
    "addr:postcode":"90025",
    "addr:street":"S Barrington Ave",
    "iso:country":"US",
    "sg:address":"2001 S Barrington Ave",
    "sg:city":"Los Angeles",
    "sg:classifiers":[
        {
            "category":"Professional",
            "subcategory":"Management & Consulting",
            "type":"Services"
        }
    ],
    "sg:phone":"+1 310 478 6699",
    "sg:postcode":"90025",
    "sg:province":"CA",
    "sg:tags":[
        "fuel"
    ],
    "wof:name":"Air Quality Management",
    "wof:placetype":"venue"
},
  "geometry": {"coordinates":[-118.44904099999999,34.035612],"type":"Point"}
}