{
  "type": "Feature",
  "properties": {
    "iso:country":"US",
    "sg:address":"3338 Redondo Beach Blvd",
    "sg:city":"Torrance",
    "sg:classifiers":[
        {
            "category":"Real Estate",
            "subcategory":"Real Estate Operator",
            "type":"Services"
        }
    ],
    "sg:phone":"+1 310 323 2652",
    "sg:postcode":"90504",
    "sg:province":"CA",
    "sg:tags":[
        "apartment"
    ],
    "wof:name":"Alondra Park Apartments",
    "wof:placetype":"venue"
},
  "geometry": {"coordinates":[-118.331001,33.881302],"type":"Point"}
}