{
  "type": "Feature",
  "properties": {
    "iso:country":"US",
    "sg:address":"921 S 4th St",
    "sg:city":"Grover Beach",
    "sg:classifiers":[
        {
            "category":"Social Services",
            "type":"Services"
        }
    ],
    "sg:phone":"+1 805 489 4223",
    "sg:postcode":"93433",
    "sg:province":"CA",
    "sg:tags":[
        "organization",
        "welfare"
    ],
    "wof:name":"Harvest Bag Inc",
    "wof:placetype":"venue"
},
  "geometry": {"coordinates":[-120.624636,35.112367],"type":"Point"}
}