{
  "type": "Feature",
  "properties": {
    "addr:full":"1601 Cloverfield Blvd Santa Monica CA 90404",
    "addr:housenumber":"1601",
    "addr:postcode":"90404",
    "addr:street":"Cloverfield Blvd",
    "iso:country":"US",
    "sg:address":"1601 Cloverfield Blvd",
    "sg:city":"Santa Monica",
    "sg:classifiers":[
        {
            "category":"Professional",
            "type":"Services"
        }
    ],
    "sg:phone":"+1 310 255 8656",
    "sg:postcode":"90404",
    "sg:province":"CA",
    "sg:tags":[
        "establishment"
    ],
    "wof:name":"Image Co",
    "wof:placetype":"venue"
},
  "geometry": {"coordinates":[-118.47235999999999,34.02719],"type":"Point"}
}