{
  "type": "Feature",
  "properties": {
    "addr:full":"2542 W 3rd St Los Angeles CA 90057",
    "addr:housenumber":"2542",
    "addr:postcode":"90057",
    "addr:street":"W 3Rd St",
    "iso:country":"US",
    "sg:address":"2542 W 3rd St",
    "sg:city":"Los Angeles",
    "sg:classifiers":[
        {
            "category":"Health Services",
            "subcategory":"Clinic",
            "type":"Services"
        }
    ],
    "sg:phone":"+1 213 383 6333",
    "sg:postcode":"90057",
    "sg:province":"CA",
    "sg:tags":[
        "home",
        "care"
    ],
    "wof:name":"Rodan Home Health Services",
    "wof:placetype":"venue"
},
  "geometry": {"coordinates":[-118.277874,34.065434],"type":"Point"}
}