{
  "type": "Feature",
  "properties": {
    "addr:full":"2049 Century Park E Ste 100 Los Angeles CA 90067",
    "addr:housenumber":"2049",
    "addr:postcode":"90067",
    "addr:street":"Century Park E Ste 100",
    "iso:country":"US",
    "sg:address":"2049 Century Park E Ste 100",
    "sg:city":"Los Angeles",
    "sg:classifiers":[
        {
            "category":"Banks & Credit Unions",
            "subcategory":"Bank",
            "type":"Services"
        },
        {
            "category":"Banks & Credit Unions",
            "subcategory":"Financial Services",
            "type":"Services"
        }
    ],
    "sg:phone":"+1 310 247 2080",
    "sg:postcode":"90067",
    "sg:province":"CA",
    "sg:tags":[
        "broker",
        "mortgage"
    ],
    "wof:name":"Bank of America",
    "wof:placetype":"venue"
},
  "geometry": {"coordinates":[-118.413155,34.058908],"type":"Point"}
}