{
  "type": "Feature",
  "properties": {
    "iso:country":"US",
    "sg:address":"7305 Apache Trl",
    "sg:city":"Yucca Valley",
    "sg:classifiers":[
        {
            "category":"Shopping",
            "type":"Retail Goods"
        }
    ],
    "sg:phone":"+1 760 365 7985",
    "sg:postcode":"92284",
    "sg:province":"CA",
    "wof:name":"Dirty Dog",
    "wof:placetype":"venue"
},
  "geometry": {"coordinates":[-116.441059,34.120549],"type":"Point"}
}