{
  "type": "Feature",
  "properties": {
    "iso:country":"US",
    "sg:address":"433 Pioneer Dr Apt 6",
    "sg:city":"Glendale",
    "sg:classifiers":[
        {
            "category":"Real Estate",
            "subcategory":"Real Estate Operator",
            "type":"Services"
        }
    ],
    "sg:phone":"+1 818 662 9369",
    "sg:postcode":"91203",
    "sg:province":"CA",
    "sg:tags":[
        "apartment"
    ],
    "wof:name":"Pioneer Apartments",
    "wof:placetype":"venue"
},
  "geometry": {"coordinates":[-118.262001,34.155201],"type":"Point"}
}