{
  "type": "Feature",
  "properties": {
    "iso:country":"US",
    "sg:address":"4901 Birch Street",
    "sg:city":"Newport Beach",
    "sg:classifiers":[
        {
            "category":"Real Estate",
            "subcategory":"Real Estate Services",
            "type":"Services"
        }
    ],
    "sg:phone":"+1 949 252 9101",
    "sg:postcode":"92660",
    "sg:province":"CA",
    "sg:tags":[
        "management",
        "property"
    ],
    "wof:name":"Lyon William Property Management Company",
    "wof:placetype":"venue"
},
  "geometry": {"coordinates":[-117.860922,33.667554],"type":"Point"}
}