{
  "type": "Feature",
  "properties": {
    "addr:full":"306 W Compton Blvd Compton CA 90220",
    "addr:housenumber":"306",
    "addr:postcode":"90220",
    "addr:street":"W Compton Blvd",
    "iso:country":"US",
    "sg:address":"306 W Compton Blvd",
    "sg:city":"Compton",
    "sg:classifiers":[
        {
            "category":"Shopping",
            "subcategory":"Mobile Phones",
            "type":"Retail Goods"
        }
    ],
    "sg:phone":"+1 310 884 9104",
    "sg:postcode":"90220",
    "sg:province":"CA",
    "wof:name":"Touchdown Wireless",
    "wof:placetype":"venue"
},
  "geometry": {"coordinates":[-118.226579,33.895852],"type":"Point"}
}