{
  "type": "Feature",
  "properties": {
    "addr:full":"760 Magnolia Ave Piedmont CA 94611",
    "addr:housenumber":"760",
    "addr:postcode":"94611",
    "addr:street":"Magnolia Ave",
    "iso:country":"US",
    "sg:address":"760 Magnolia Ave",
    "sg:city":"Piedmont",
    "sg:classifiers":[
        {
            "category":"Education",
            "subcategory":"School",
            "type":"Public Place"
        }
    ],
    "sg:phone":"+1 510 594 2703",
    "sg:postcode":"94611",
    "sg:province":"CA",
    "sg:tags":[
        "high",
        "middle"
    ],
    "wof:name":"Millennium High School",
    "wof:placetype":"venue"
},
  "geometry": {"coordinates":[-122.233002,37.823502],"type":"Point"}
}