{
  "type": "Feature",
  "properties": {
    "addr:full":"1146 Gregory Ct Merced CA 95340",
    "addr:housenumber":"1146",
    "addr:postcode":"95340",
    "addr:street":"Gregory Ct",
    "iso:country":"US",
    "sg:address":"1146 Gregory Ct",
    "sg:city":"Merced",
    "sg:classifiers":[
        {
            "category":"Building & Trades",
            "subcategory":"Pest Control",
            "type":"Services"
        }
    ],
    "sg:phone":"+1 209 388 1800",
    "sg:postcode":"95340",
    "sg:province":"CA",
    "wof:name":"Gecko Pest & Landscape Management",
    "wof:placetype":"venue"
},
  "geometry": {"coordinates":[-120.457778,37.32084],"type":"Point"}
}