{
  "type": "Feature",
  "properties": {
    "iso:country":"US",
    "sg:address":"105 Orinda Way",
    "sg:city":"Orinda",
    "sg:classifiers":[
        {
            "category":"Personal",
            "subcategory":"Beauty Salon",
            "type":"Services"
        }
    ],
    "sg:phone":"+1 925 253 8414",
    "sg:postcode":"94563",
    "sg:province":"CA",
    "wof:name":"Penny Lane",
    "wof:placetype":"venue"
},
  "geometry": {"coordinates":[-122.192589,37.885734],"type":"Point"}
}