{
  "type": "Feature",
  "properties": {
    "addr:full":"40000 Fremont Blvd Fremont CA 94538",
    "addr:housenumber":"40000",
    "addr:postcode":"94538",
    "addr:street":"Fremont Blvd",
    "iso:country":"US",
    "sg:address":"40000 Fremont Blvd",
    "sg:city":"Fremont",
    "sg:classifiers":[
        {
            "category":"Health Services",
            "subcategory":"Health Practitioner",
            "type":"Services"
        }
    ],
    "sg:phone":"+1 510 683 0633",
    "sg:postcode":"94538",
    "sg:province":"CA",
    "sg:tags":[
        "acupuncture"
    ],
    "wof:name":"Fremont Acupuncture Clinic",
    "wof:placetype":"venue"
},
  "geometry": {"coordinates":[-121.973018,37.540614],"type":"Point"}
}