{
  "type": "Feature",
  "properties": {
    "addr:full":"3052 5th St Ste E Ceres CA 95307",
    "addr:housenumber":"3052",
    "addr:postcode":"95307",
    "addr:street":"5Th St Ste E",
    "iso:country":"US",
    "sg:address":"3052 5th St Ste E",
    "sg:city":"Ceres",
    "sg:classifiers":[
        {
            "category":"Real Estate",
            "subcategory":"Real Estate Services",
            "type":"Services"
        }
    ],
    "sg:phone":"+1 209 538 1926",
    "sg:postcode":"95307",
    "sg:province":"CA",
    "wof:name":"Strickler Real Estate",
    "wof:placetype":"venue"
},
  "geometry": {"coordinates":[-120.952003,37.589199],"type":"Point"}
}