{
  "type": "Feature",
  "properties": {
    "iso:country":"US",
    "sg:address":"502 Pacheco Blvd",
    "sg:city":"Los Banos",
    "sg:classifiers":[
        {
            "category":"Ice Cream",
            "type":"Food & Drink"
        }
    ],
    "sg:menulink":"http://www.allmenus.com/ca/los-banos/164940-dairy-queen/menu/",
    "sg:phone":"+1 209 826 5555",
    "sg:postcode":"93635",
    "sg:province":"CA",
    "sg:tags":[
        "burger",
        "american"
    ],
    "wof:name":"Dairy Queen",
    "wof:placetype":"venue"
},
  "geometry": {"coordinates":[-120.853061,37.05688],"type":"Point"}
}