{
  "type": "Feature",
  "properties": {
    "addr:full":"755 Chestnut Street San Jose CA 95110",
    "addr:housenumber":"755",
    "addr:postcode":"95110",
    "addr:street":"Chestnut Street",
    "iso:country":"US",
    "sg:address":"755 Chestnut Street",
    "sg:city":"San Jose",
    "sg:classifiers":[
        {
            "category":"Building & Trades",
            "subcategory":"Construction",
            "type":"Services"
        }
    ],
    "sg:phone":"+1 408 279 0433",
    "sg:postcode":"95110",
    "sg:province":"CA",
    "sg:tags":[
        "contractor"
    ],
    "wof:name":"Mission City Contractors",
    "wof:placetype":"venue"
},
  "geometry": {"coordinates":[-121.913061,37.342361],"type":"Point"}
}