{
  "type": "Feature",
  "properties": {
    "addr:full":"4189 Krolop Rd Castro Valley CA 94546",
    "addr:housenumber":"4189",
    "addr:postcode":"94546",
    "addr:street":"Krolop Rd",
    "iso:country":"US",
    "sg:address":"4189 Krolop Rd",
    "sg:city":"Castro Valley",
    "sg:classifiers":[
        {
            "category":"Building & Trades",
            "subcategory":"Construction",
            "type":"Services"
        }
    ],
    "sg:phone":"+1 510 538 3590",
    "sg:postcode":"94546",
    "sg:province":"CA",
    "sg:tags":[
        "plastering",
        "contractor"
    ],
    "wof:name":"Davidson Plastering Inc",
    "wof:placetype":"venue"
},
  "geometry": {"coordinates":[-122.09072399999999,37.719289],"type":"Point"}
}