{
  "type": "Feature",
  "properties": {
    "addr:full":"3305 Old Creek Rd Gilroy CA 95020",
    "addr:housenumber":"3305",
    "addr:postcode":"95020",
    "addr:street":"Old Creek Rd",
    "iso:country":"US",
    "sg:address":"3305 Old Creek Rd",
    "sg:city":"Gilroy",
    "sg:classifiers":[
        {
            "category":"Wholesale",
            "subcategory":"Office Equipment",
            "type":"Manufacturing & Wholesale Goods"
        },
        {
            "category":"Professional",
            "subcategory":"Printing & Photocopies",
            "type":"Services"
        },
        {
            "category":"Shopping",
            "subcategory":"Computers & Home Electronics",
            "type":"Retail Goods"
        }
    ],
    "sg:phone":"+1 408 847 0785",
    "sg:postcode":"95020",
    "sg:province":"CA",
    "sg:tags":[
        "scanning",
        "printer",
        "services-commercial",
        "plotting",
        "supply"
    ],
    "wof:name":"Publico Press Printers",
    "wof:placetype":"venue"
},
  "geometry": {"coordinates":[-121.65718,37.050958],"type":"Point"}
}