{
  "type": "Feature",
  "properties": {
    "addr:full":"2714 San Bruno Avenue San Francisco CA 94134",
    "addr:housenumber":"2714",
    "addr:postcode":"94134",
    "addr:street":"San Bruno Avenue",
    "iso:country":"US",
    "sg:address":"2714 San Bruno Avenue",
    "sg:city":"San Francisco",
    "sg:classifiers":[
        {
            "category":"Shopping",
            "subcategory":"Beauty & Cosmetics",
            "type":"Retail Goods"
        }
    ],
    "sg:phone":"+1 415 468 8433",
    "sg:postcode":"94134",
    "sg:province":"CA",
    "sg:tags":[
        "supply"
    ],
    "wof:name":"Tgif Beauty Supply",
    "wof:placetype":"venue"
},
  "geometry": {"coordinates":[-122.403654,37.727265],"type":"Point"}
}