{
  "type": "Feature",
  "properties": {
    "iso:country":"US",
    "sg:address":"1101 W El Camino Real",
    "sg:city":"Mountain View",
    "sg:classifiers":[
        {
            "category":"Retail",
            "subcategory":"Car Wash",
            "type":"Services"
        },
        {
            "category":"Retail",
            "subcategory":"Auto Repair",
            "type":"Services"
        }
    ],
    "sg:phone":"+1 650 967 7788",
    "sg:postcode":"94041",
    "sg:province":"CA",
    "sg:tags":[
        "detailing"
    ],
    "sg:website":"www.harvscarwash.com",
    "wof:name":"Harv's Car Wash",
    "wof:placetype":"venue"
},
  "geometry": {"coordinates":[-122.087385,37.387162],"type":"Point"}
}