{
  "type": "Feature",
  "properties": {
    "addr:full":"3107 Fillmore St San Francisco CA 94123",
    "addr:housenumber":"3107",
    "addr:postcode":"94123",
    "addr:street":"Fillmore St",
    "iso:country":"US",
    "sg:address":"3107 Fillmore St",
    "sg:city":"San Francisco",
    "sg:classifiers":[
        {
            "category":"Health Services",
            "subcategory":"Health Practitioner",
            "type":"Services"
        }
    ],
    "sg:phone":"+1 415 752 7022",
    "sg:postcode":"94123",
    "sg:province":"CA",
    "sg:tags":[
        "psychologist"
    ],
    "wof:name":"Janet M Mahoney PHD",
    "wof:placetype":"venue"
},
  "geometry": {"coordinates":[-122.43583099999999,37.798382],"type":"Point"}
}