{
  "type": "Feature",
  "properties": {
    "iso:country":"US",
    "sg:address":"16945 del Monte Ave",
    "sg:city":"Morgan Hill",
    "sg:classifiers":[
        {
            "category":"Real Estate",
            "subcategory":"Real Estate Operator",
            "type":"Services"
        }
    ],
    "sg:phone":"+1 408 779 8986",
    "sg:postcode":"95037",
    "sg:province":"CA",
    "sg:tags":[
        "apartment"
    ],
    "wof:name":"Archstone Morgan Hill",
    "wof:placetype":"venue"
},
  "geometry": {"coordinates":[-121.65212,37.123839],"type":"Point"}
}