{
  "type": "Feature",
  "properties": {
    "iso:country":"US",
    "sg:address":"2660 W Ball Rd",
    "sg:city":"Anaheim",
    "sg:classifiers":[
        {
            "category":"Real Estate",
            "subcategory":"Real Estate Operator",
            "type":"Services"
        }
    ],
    "sg:phone":"+1 714 952 8635",
    "sg:postcode":"92804",
    "sg:province":"CA",
    "sg:tags":[
        "apartment"
    ],
    "wof:name":"Balboa Apartments",
    "wof:placetype":"venue"
},
  "geometry": {"coordinates":[-117.977997,33.817501],"type":"Point"}
}