{
  "type": "Feature",
  "properties": {
    "addr:full":"230 California St Ste 700 San Francisco CA 94111",
    "addr:housenumber":"230",
    "addr:postcode":"94111",
    "addr:street":"California St Ste 700",
    "iso:country":"US",
    "sg:address":"230 California St Ste 700",
    "sg:city":"San Francisco",
    "sg:classifiers":[
        {
            "category":"Insurance",
            "subcategory":"Hazard Insurance",
            "type":"Services"
        }
    ],
    "sg:phone":"+1 415 788 4700",
    "sg:postcode":"94111",
    "sg:province":"CA",
    "sg:website":"www.barbaryinsurance.com",
    "wof:name":"Barbary Insurance Brokerage",
    "wof:placetype":"venue"
},
  "geometry": {"coordinates":[-122.399106,37.793352],"type":"Point"}
}