{
  "type": "Feature",
  "properties": {
    "addr:full":"1625 W Campbell Ave Campbell CA 95008",
    "addr:housenumber":"1625",
    "addr:postcode":"95008",
    "addr:street":"W Campbell Ave",
    "iso:country":"US",
    "sg:address":"1625 W Campbell Ave",
    "sg:city":"Campbell",
    "sg:classifiers":[
        {
            "category":"Professional",
            "subcategory":"Management & Consulting",
            "type":"Services"
        }
    ],
    "sg:phone":"+1 408 364 2800",
    "sg:postcode":"95008",
    "sg:province":"CA",
    "sg:tags":[
        "consultant",
        "resource",
        "human"
    ],
    "wof:name":"Execustaff HR",
    "wof:placetype":"venue"
},
  "geometry": {"coordinates":[-121.97739900000001,37.286038],"type":"Point"}
}