{
  "type": "Feature",
  "properties": {
    "addr:full":"16735 Lark Ave Los Gatos CA 95032",
    "addr:housenumber":"16735",
    "addr:postcode":"95032",
    "addr:street":"Lark Ave",
    "iso:country":"US",
    "sg:address":"16735 Lark Ave",
    "sg:city":"Los Gatos",
    "sg:classifiers":[
        {
            "category":"Organizations",
            "subcategory":"Religious Organization",
            "type":"Services"
        }
    ],
    "sg:phone":"+1 408 356 1191",
    "sg:postcode":"95032",
    "sg:province":"CA",
    "sg:tags":[
        "church"
    ],
    "wof:name":"Fountain Of Life Worship Ctr",
    "wof:placetype":"venue"
},
  "geometry": {"coordinates":[-121.962721,37.251287],"type":"Point"}
}