{
  "type": "Feature",
  "properties": {
    "addr:full":"229 Broad Ave Wilmington CA 90744",
    "addr:housenumber":"229",
    "addr:postcode":"90744",
    "addr:street":"Broad Ave",
    "iso:country":"US",
    "sg:address":"229 Broad Ave",
    "sg:city":"Wilmington",
    "sg:classifiers":[
        {
            "category":"Building & Trades",
            "subcategory":"Cleaning & Sanitation",
            "type":"Services"
        }
    ],
    "sg:phone":"+1 310 519 0343",
    "sg:postcode":"90744",
    "sg:province":"CA",
    "sg:tags":[
        "chemical"
    ],
    "sg:website":"www.ondeo-nalco.com",
    "wof:name":"Nalfleet Inc",
    "wof:placetype":"venue"
},
  "geometry": {"coordinates":[-118.260609,33.772375],"type":"Point"}
}