{
  "type": "Feature",
  "properties": {
    "addr:full":"6036 Cerritos Ave Cypress CA 90630",
    "addr:housenumber":"6036",
    "addr:postcode":"90630",
    "addr:street":"Cerritos Ave",
    "iso:country":"US",
    "sg:address":"6036 Cerritos Ave",
    "sg:city":"Cypress",
    "sg:classifiers":[
        {
            "category":"Retail",
            "subcategory":"Auto Repair",
            "type":"Services"
        }
    ],
    "sg:phone":"+1 714 826 5555",
    "sg:postcode":"90630",
    "sg:province":"CA",
    "sg:tags":[
        "repairing",
        "automobile",
        "smog",
        "check"
    ],
    "wof:name":"Cypress Auto Repair & Smog",
    "wof:placetype":"venue"
},
  "geometry": {"coordinates":[-118.027,33.8097],"type":"Point"}
}