{
  "type": "Feature",
  "properties": {
    "addr:full":"10108 Malaga Way Rancho Cordova CA 95670",
    "addr:postcode":"10108;95670",
    "addr:street":"Malaga Way",
    "iso:country":"US",
    "sg:address":"10108 Malaga Way",
    "sg:city":"Rancho Cordova",
    "sg:classifiers":[
        {
            "category":"Real Estate",
            "subcategory":"Real Estate Operator",
            "type":"Services"
        }
    ],
    "sg:phone":"+1 888 492 0157",
    "sg:postcode":"95670",
    "sg:province":"CA",
    "sg:tags":[
        "apartment"
    ],
    "wof:name":"The Meadows Apartments",
    "wof:placetype":"venue"
},
  "geometry": {"coordinates":[-121.314909,38.586179],"type":"Point"}
}