{
  "type": "Feature",
  "properties": {
    "iso:country":"US",
    "sg:address":"17370 Colima Rd",
    "sg:city":"Rowland Heights",
    "sg:classifiers":[
        {
            "category":"Shopping",
            "subcategory":"Department Store",
            "type":"Retail Goods"
        }
    ],
    "sg:phone":"+1 626 810 0417",
    "sg:postcode":"91748",
    "sg:province":"CA",
    "wof:name":"Marshalls",
    "wof:placetype":"venue"
},
  "geometry": {"coordinates":[-117.924646,33.990398],"type":"Point"}
}