{
  "type": "Feature",
  "properties": {
    "addr:full":"5201, Great America Parkway,  St.320 Santa Clara CA 95054",
    "addr:housenumber":"5201",
    "addr:postcode":"st.320;95054",
    "addr:street":"Great America Parkway",
    "iso:country":"US",
    "sg:address":"5201, Great America Parkway,  St.320",
    "sg:city":"Santa Clara",
    "sg:classifiers":[
        {
            "category":"Professional",
            "subcategory":"Computer Services",
            "type":"Services"
        }
    ],
    "sg:phone":"+1 408 465 9966",
    "sg:postcode":"95054",
    "sg:province":"CA",
    "sg:tags":[
        "iphone-application-development",
        "ipad-application-development",
        "blackberry-development",
        "html5-development",
        "android-development",
        "mobile-enterprise-solutions"
    ],
    "sg:website":"http://www.letsgomo.com",
    "wof:name":"LetsGoMo",
    "wof:placetype":"venue"
},
  "geometry": {"coordinates":[-121.98531,37.38057],"type":"Point"}
}