{
  "type": "Feature",
  "properties": {
    "addr:full":"8705 Truxton Ave Los Angeles CA 90045",
    "addr:housenumber":"8705",
    "addr:postcode":"90045",
    "addr:street":"Truxton Ave",
    "iso:country":"US",
    "sg:address":"8705 Truxton Ave",
    "sg:city":"Los Angeles",
    "sg:classifiers":[
        {
            "category":"Professional",
            "type":"Services"
        }
    ],
    "sg:phone":"+1 310 337 1169",
    "sg:postcode":"90045",
    "sg:province":"CA",
    "wof:name":"West Moldings",
    "wof:placetype":"venue"
},
  "geometry": {"coordinates":[-118.393227,33.958256],"type":"Point"}
}