{
  "type": "Feature",
  "properties": {
    "iso:country":"US",
    "sg:address":"217 Devcon Dr",
    "sg:city":"San Jose",
    "sg:classifiers":[
        {
            "category":"Shopping",
            "subcategory":"Mobile Phones",
            "type":"Retail Goods"
        }
    ],
    "sg:phone":"+1 408 467 0410",
    "sg:postcode":"95112",
    "sg:province":"CA",
    "wof:name":"Sirf Technology Inc",
    "wof:placetype":"venue"
},
  "geometry": {"coordinates":[-121.91369299999999,37.375048],"type":"Point"}
}