{
  "type": "Feature",
  "properties": {
    "iso:country":"US",
    "sg:address":"20265 Valley Blvd",
    "sg:city":"Walnut",
    "sg:classifiers":[
        {
            "category":"Wholesale",
            "subcategory":"Electrical",
            "type":"Manufacturing & Wholesale Goods"
        }
    ],
    "sg:phone":"+1 909 444 7888",
    "sg:postcode":"91789",
    "sg:province":"CA",
    "sg:tags":[
        "control",
        "security",
        "system"
    ],
    "wof:name":"Precision Security",
    "wof:placetype":"venue"
},
  "geometry": {"coordinates":[-117.862302,34.007709],"type":"Point"}
}