{
  "type": "Feature",
  "properties": {
    "iso:country":"US",
    "sg:address":"1725 Santa Clara Dr",
    "sg:city":"Roseville",
    "sg:classifiers":[
        {
            "category":"Retail",
            "subcategory":"Photofinishing",
            "type":"Services"
        }
    ],
    "sg:phone":"+1 916 784 2080",
    "sg:postcode":"95661",
    "sg:province":"CA",
    "sg:tags":[
        "photo",
        "finishing"
    ],
    "wof:name":"Rainbow One Hour Photo",
    "wof:placetype":"venue"
},
  "geometry": {"coordinates":[-121.262208,38.746619],"type":"Point"}
}