{
  "type": "Feature",
  "properties": {
    "iso:country":"US",
    "sg:address":"1337 Crows Landing Rd",
    "sg:city":"Modesto",
    "sg:classifiers":[
        {
            "category":"Banks & Credit Unions",
            "subcategory":"Bank",
            "type":"Services"
        }
    ],
    "sg:phone":"+1 209 236 0655",
    "sg:postcode":"95351",
    "sg:province":"CA",
    "sg:tags":[
        "loan",
        "real estate"
    ],
    "wof:name":"Golden Key Mortgage",
    "wof:placetype":"venue"
},
  "geometry": {"coordinates":[-120.993684,37.610588],"type":"Point"}
}