{
  "type": "Feature",
  "properties": {
    "iso:country":"US",
    "sg:address":"771 Lawrence Expy",
    "sg:city":"Santa Clara",
    "sg:classifiers":[
        {
            "category":"Retail",
            "subcategory":"Veterinary Services",
            "type":"Services"
        }
    ],
    "sg:phone":"+1 408 296 3300",
    "sg:postcode":"95051",
    "sg:province":"CA",
    "sg:tags":[
        "veterinarian"
    ],
    "wof:name":"Lynn Vieyra DVM",
    "wof:placetype":"venue"
},
  "geometry": {"coordinates":[-121.995374,37.336708],"type":"Point"}
}