{
  "type": "Feature",
  "properties": {
    "addr:full":"1868 Fremont Blvd Seaside CA 93955",
    "addr:housenumber":"1868",
    "addr:postcode":"93955",
    "addr:street":"Fremont Blvd",
    "iso:country":"US",
    "sg:address":"1868 Fremont Blvd",
    "sg:city":"Seaside",
    "sg:classifiers":[
        {
            "category":"Restaurant",
            "type":"Food & Drink"
        }
    ],
    "sg:phone":"+1 831 899 7800",
    "sg:postcode":"93955",
    "sg:province":"CA",
    "wof:name":"Yen Ching Restaurant",
    "wof:placetype":"venue"
},
  "geometry": {"coordinates":[-121.842135,36.615467],"type":"Point"}
}