{
  "type": "Feature",
  "properties": {
    "addr:full":"689 Marsat Ct Chula Vista CA 91911",
    "addr:housenumber":"689",
    "addr:postcode":"91911",
    "addr:street":"Marsat Ct",
    "iso:country":"US",
    "sg:address":"689 Marsat Ct",
    "sg:city":"Chula Vista",
    "sg:classifiers":[
        {
            "category":"Wholesale",
            "subcategory":"Hardware",
            "type":"Manufacturing & Wholesale Goods"
        }
    ],
    "sg:phone":"+1 619 575 0214",
    "sg:postcode":"91911",
    "sg:province":"CA",
    "sg:tags":[
        "tool"
    ],
    "wof:name":"Imperial Tool Co San Diego",
    "wof:placetype":"venue"
},
  "geometry": {"coordinates":[-117.081682,32.600756],"type":"Point"}
}