{
  "type": "Feature",
  "properties": {
    "iso:country":"US",
    "sg:address":"1642 E Capitol Expy",
    "sg:city":"San Jose",
    "sg:classifiers":[
        {
            "category":"Health Services",
            "subcategory":"Doctor",
            "type":"Services"
        }
    ],
    "sg:phone":"+1 408 270 3374",
    "sg:postcode":"95121",
    "sg:province":"CA",
    "wof:name":"Ha Linda MD",
    "wof:placetype":"venue"
},
  "geometry": {"coordinates":[-121.808998,37.3097],"type":"Point"}
}