{
  "type": "Feature",
  "properties": {
    "addr:full":"15 Mason Ln Irvine CA 92694",
    "addr:housenumber":"15",
    "addr:postcode":"92694",
    "addr:street":"Mason Ln",
    "iso:country":"US",
    "sg:address":"15 Mason Ln",
    "sg:city":"Irvine",
    "sg:classifiers":[
        {
            "category":"Wholesale",
            "subcategory":"Sporting Goods",
            "type":"Manufacturing & Wholesale Goods"
        }
    ],
    "sg:phone":"+1 949 699 2499",
    "sg:postcode":"92694",
    "sg:province":"CA",
    "wof:name":"Warrior Golf",
    "wof:placetype":"venue"
},
  "geometry": {"coordinates":[-117.722036,33.642413],"type":"Point"}
}