{
  "type": "Feature",
  "properties": {
    "addr:full":"871 Industrial Rd San Carlos CA 94070",
    "addr:housenumber":"871",
    "addr:postcode":"94070",
    "addr:street":"Industrial Rd",
    "iso:country":"US",
    "sg:address":"871 Industrial Rd",
    "sg:city":"San Carlos",
    "sg:classifiers":[
        {
            "category":"Professional",
            "subcategory":"Computer Services",
            "type":"Services"
        }
    ],
    "sg:phone":"+1 650 637 8318",
    "sg:postcode":"94070",
    "sg:province":"CA",
    "sg:tags":[
        "hardware",
        "provider",
        "internet",
        "software"
    ],
    "sg:website":"www.stanford.net",
    "wof:name":"Stanford Internet Solutions",
    "wof:placetype":"venue"
},
  "geometry": {"coordinates":[-122.251031,37.506833],"type":"Point"}
}