{
  "type": "Feature",
  "properties": {
    "addr:full":"346 Village Ln Los Gatos CA 95030",
    "addr:housenumber":"346",
    "addr:postcode":"95030",
    "addr:street":"Village Ln",
    "iso:country":"US",
    "sg:address":"346 Village Ln",
    "sg:city":"Los Gatos",
    "sg:classifiers":[
        {
            "category":"Personal",
            "subcategory":"Day Spa",
            "type":"Services"
        }
    ],
    "sg:phone":"+1 408 399 5620",
    "sg:postcode":"95030",
    "sg:province":"CA",
    "sg:website":"www.villagespalosgatos.com",
    "wof:name":"Village Spa",
    "wof:placetype":"venue"
},
  "geometry": {"coordinates":[-121.980931,37.227812],"type":"Point"}
}