{
  "type": "Feature",
  "properties": {
    "addr:full":"20016 Hawthorne Blvd Ste A Torrance CA 90503",
    "addr:housenumber":"20016",
    "addr:postcode":"90503",
    "addr:street":"Hawthorne Blvd Ste A",
    "iso:country":"US",
    "sg:address":"20016 Hawthorne Blvd Ste A",
    "sg:city":"Torrance",
    "sg:classifiers":[
        {
            "category":"Banks & Credit Unions",
            "subcategory":"Bank",
            "type":"Services"
        }
    ],
    "sg:phone":"+1 310 214 2950",
    "sg:postcode":"90503",
    "sg:province":"CA",
    "wof:name":"First Bank & Trust",
    "wof:placetype":"venue"
},
  "geometry": {"coordinates":[-118.353461,33.850638],"type":"Point"}
}