{
  "type": "Feature",
  "properties": {
    "addr:full":"984 Monte Vista Dr Santa Paula CA 93060",
    "addr:housenumber":"984",
    "addr:postcode":"93060",
    "addr:street":"Monte Vista Dr",
    "iso:country":"US",
    "sg:address":"984 Monte Vista Dr",
    "sg:city":"Santa Paula",
    "sg:classifiers":[
        {
            "category":"Organizations",
            "subcategory":"Religious Organization",
            "type":"Services"
        }
    ],
    "sg:phone":"+1 805 933 5063",
    "sg:postcode":"93060",
    "sg:province":"CA",
    "sg:tags":[
        "church"
    ],
    "sg:website":"www.cricusa.com",
    "wof:name":"Canons Regular-The Immaculate",
    "wof:placetype":"venue"
},
  "geometry": {"coordinates":[-119.063896,34.364841],"type":"Point"}
}