{
  "type": "Feature",
  "properties": {
    "addr:full":"16828 S Broadway St Gardena CA 90248",
    "addr:housenumber":"16828",
    "addr:postcode":"90248",
    "addr:street":"S Broadway St",
    "iso:country":"US",
    "sg:address":"16828 S Broadway St",
    "sg:city":"Gardena",
    "sg:classifiers":[
        {
            "category":"Building & Trades",
            "subcategory":"Construction",
            "type":"Services"
        }
    ],
    "sg:phone":"+1 310 370 0090",
    "sg:postcode":"90248",
    "sg:province":"CA",
    "sg:tags":[
        "roofing",
        "contractor"
    ],
    "wof:name":"Avalon Roofing Inc",
    "wof:placetype":"venue"
},
  "geometry": {"coordinates":[-118.278014,33.878728],"type":"Point"}
}