{
  "type": "Feature",
  "properties": {
    "addr:full":"465 Healdsburg Ave Healdsburg CA 95448",
    "addr:housenumber":"465",
    "addr:postcode":"95448",
    "addr:street":"Healdsburg Ave",
    "iso:country":"US",
    "sg:address":"465 Healdsburg Ave",
    "sg:city":"Healdsburg",
    "sg:classifiers":[
        {
            "category":"Professional",
            "subcategory":"Lawyer & Legal Services",
            "type":"Services"
        }
    ],
    "sg:phone":"+1 707 433 5297",
    "sg:postcode":"95448",
    "sg:province":"CA",
    "sg:tags":[
        "attorney"
    ],
    "wof:name":"Timothy D Fitzpatrick",
    "wof:placetype":"venue"
},
  "geometry": {"coordinates":[-122.871459,38.612704],"type":"Point"}
}