{
  "type": "Feature",
  "properties": {
    "addr:full":"4937 Sierra Vista Ave Riverside CA 92505",
    "addr:housenumber":"4937",
    "addr:postcode":"92505",
    "addr:street":"Sierra Vista Ave",
    "iso:country":"US",
    "sg:address":"4937 Sierra Vista Ave",
    "sg:city":"Riverside",
    "sg:classifiers":[
        {
            "category":"Social Services",
            "type":"Services"
        }
    ],
    "sg:phone":"+1 951 354 7090",
    "sg:postcode":"92505",
    "sg:province":"CA",
    "sg:tags":[
        "counseling"
    ],
    "wof:name":"Christian Counseling Ctr",
    "wof:placetype":"venue"
},
  "geometry": {"coordinates":[-117.499745,33.91473],"type":"Point"}
}