{
  "type": "Feature",
  "properties": {
    "iso:country":"US",
    "sg:address":"556 S Broadway",
    "sg:city":"Los Angeles",
    "sg:classifiers":[
        {
            "category":"Retail",
            "subcategory":"Repair Shop",
            "type":"Services"
        }
    ],
    "sg:phone":"+1 213 489 1452",
    "sg:postcode":"90013",
    "sg:province":"CA",
    "sg:tags":[
        "jewelry"
    ],
    "wof:name":"Michelle Jewelry",
    "wof:placetype":"venue"
},
  "geometry": {"coordinates":[-118.25134199999999,34.04742],"type":"Point"}
}