{
  "type": "Feature",
  "properties": {
    "iso:country":"US",
    "sg:address":"13421 Snow Rd",
    "sg:city":"Bakersfield",
    "sg:classifiers":[
        {
            "category":"Organizations",
            "subcategory":"Religious Organization",
            "type":"Services"
        }
    ],
    "sg:phone":"+1 661 588 1220",
    "sg:postcode":"93314",
    "sg:province":"CA",
    "sg:tags":[
        "church"
    ],
    "wof:name":"Sure Foundation Baptist Church",
    "wof:placetype":"venue"
},
  "geometry": {"coordinates":[-119.157408,35.427364],"type":"Point"}
}