{
  "type": "Feature",
  "properties": {
    "addr:full":"21562 Brookhurst Street Huntington Beach CA 92646",
    "addr:housenumber":"21562",
    "addr:postcode":"92646",
    "addr:street":"Brookhurst Street",
    "iso:country":"US",
    "sg:address":"21562 Brookhurst Street",
    "sg:city":"Huntington Beach",
    "sg:classifiers":[
        {
            "category":"Shopping",
            "subcategory":"Florist",
            "type":"Retail Goods"
        }
    ],
    "sg:phone":"+1 714 962 6687",
    "sg:postcode":"92646",
    "sg:province":"CA",
    "wof:name":"Hamilton Flowers and Gifts",
    "wof:placetype":"venue"
},
  "geometry": {"coordinates":[-117.95363999999999,33.649085],"type":"Point"}
}