{
  "type": "Feature",
  "properties": {
    "iso:country":"US",
    "sg:address":"12520 Saratoga Creek Dr",
    "sg:city":"Saratoga",
    "sg:classifiers":[
        {
            "category":"Professional",
            "subcategory":"Computer Services",
            "type":"Services"
        }
    ],
    "sg:phone":"+1 408 446 4015",
    "sg:postcode":"95070",
    "sg:province":"CA",
    "sg:tags":[
        "electronics"
    ],
    "wof:name":"Saratoga Technology Assoc",
    "wof:placetype":"venue"
},
  "geometry": {"coordinates":[-122.004322,37.286062],"type":"Point"}
}