{
  "type": "Feature",
  "properties": {
    "addr:full":"5341 Della Ave Rancho Cucamonga CA 91701",
    "addr:housenumber":"5341",
    "addr:postcode":"91701",
    "addr:street":"Della Ave",
    "iso:country":"US",
    "sg:address":"5341 Della Ave",
    "sg:city":"Rancho Cucamonga",
    "sg:classifiers":[
        {
            "category":"Real Estate",
            "subcategory":"Real Estate Agent",
            "type":"Services"
        }
    ],
    "sg:phone":"+1 909 989 8178",
    "sg:postcode":"91701",
    "sg:province":"CA",
    "wof:name":"Gold Nuggets Realty",
    "wof:placetype":"venue"
},
  "geometry": {"coordinates":[-117.63069400000001,34.1581],"type":"Point"}
}