{
  "type": "Feature",
  "properties": {
    "iso:country":"US",
    "sg:address":"4910 Lakewood Blvd",
    "sg:city":"Lakewood",
    "sg:classifiers":[
        {
            "category":"Restaurant",
            "type":"Food & Drink"
        }
    ],
    "sg:phone":"+1 562 531 0478",
    "sg:postcode":"90712",
    "sg:province":"CA",
    "wof:name":"McDonald's",
    "wof:placetype":"venue"
},
  "geometry": {"coordinates":[-118.141998,33.847401],"type":"Point"}
}