{
  "type": "Feature",
  "properties": {
    "addr:full":"1115 Burlingame Avenue Burlingame CA 94010",
    "addr:housenumber":"1115",
    "addr:postcode":"94010",
    "addr:street":"Burlingame Avenue",
    "iso:country":"US",
    "sg:address":"1115 Burlingame Avenue",
    "sg:city":"Burlingame",
    "sg:classifiers":[
        {
            "category":"Shopping",
            "subcategory":"Clothing, Apparel, & Fashions",
            "type":"Retail Goods"
        }
    ],
    "sg:phone":"+1 650 579 4514",
    "sg:postcode":"94010",
    "sg:province":"CA",
    "sg:tags":[
        "accessory",
        "clothing",
        "women's"
    ],
    "wof:name":"Manije Boutique",
    "wof:placetype":"venue"
},
  "geometry": {"coordinates":[-122.345815,37.579314],"type":"Point"}
}