{
  "type": "Feature",
  "properties": {
    "addr:full":"560 14th St Oakland CA 94612",
    "addr:housenumber":"560",
    "addr:postcode":"94612",
    "addr:street":"14Th St",
    "iso:country":"US",
    "sg:address":"560 14th St",
    "sg:city":"Oakland",
    "sg:classifiers":[
        {
            "category":"Real Estate",
            "subcategory":"Architect",
            "type":"Services"
        }
    ],
    "sg:phone":"+1 510 763 1313",
    "sg:postcode":"94612",
    "sg:province":"CA",
    "sg:website":"www.vbnarch.com",
    "wof:name":"Vbn Architects",
    "wof:placetype":"venue"
},
  "geometry": {"coordinates":[-122.274002,37.805401],"type":"Point"}
}