{
  "type": "Feature",
  "properties": {
    "addr:full":"3750 McKee Road San Jose CA 95127",
    "addr:housenumber":"3750",
    "addr:postcode":"95127",
    "addr:street":"Mckee Road",
    "iso:country":"US",
    "sg:address":"3750 McKee Road",
    "sg:city":"San Jose",
    "sg:classifiers":[
        {
            "category":"Building & Trades",
            "subcategory":"Cleaning & Sanitation",
            "type":"Services"
        },
        {
            "category":"Building & Trades",
            "subcategory":"Construction",
            "type":"Services"
        }
    ],
    "sg:phone":"+1 408 254 9010",
    "sg:postcode":"95127",
    "sg:province":"CA",
    "sg:tags":[
        "home",
        "contractor"
    ],
    "wof:name":"J & J Maintenance",
    "wof:placetype":"venue"
},
  "geometry": {"coordinates":[-121.830541,37.378473],"type":"Point"}
}