{
  "type": "Feature",
  "properties": {
    "addr:full":"4275 S Hoover St Los Angeles CA 90037",
    "addr:housenumber":"4275",
    "addr:postcode":"90037",
    "addr:street":"S Hoover St",
    "iso:country":"US",
    "sg:address":"4275 S Hoover St",
    "sg:city":"Los Angeles",
    "sg:classifiers":[
        {
            "category":"Food & Beverages",
            "subcategory":"Groceries & Convenience Stores",
            "type":"Retail Goods"
        }
    ],
    "sg:phone":"+1 323 231 1615",
    "sg:postcode":"90037",
    "sg:province":"CA",
    "wof:name":"Best Market",
    "wof:placetype":"venue"
},
  "geometry": {"coordinates":[-118.287003,34.005699],"type":"Point"}
}