{
  "type": "Feature",
  "properties": {
    "addr:full":"10247 Imperial Ave Cupertino CA 95014",
    "addr:housenumber":"10247",
    "addr:postcode":"95014",
    "addr:street":"Imperial Ave",
    "iso:country":"US",
    "sg:address":"10247 Imperial Ave",
    "sg:city":"Cupertino",
    "sg:classifiers":[
        {
            "category":"Professional",
            "subcategory":"Advertising",
            "type":"Services"
        }
    ],
    "sg:phone":"+1 650 903 4881",
    "sg:postcode":"95014",
    "sg:province":"CA",
    "sg:tags":[
        "counselor"
    ],
    "wof:name":"TWD Group",
    "wof:placetype":"venue"
},
  "geometry": {"coordinates":[-122.053315,37.31959],"type":"Point"}
}