{
  "type": "Feature",
  "properties": {
    "addr:full":"5527 Cahuenga Blvd North Hollywood CA 91601",
    "addr:housenumber":"5527",
    "addr:postcode":"91601",
    "addr:street":"Cahuenga Blvd",
    "iso:country":"US",
    "sg:address":"5527 Cahuenga Blvd",
    "sg:city":"North Hollywood",
    "sg:classifiers":[
        {
            "category":"Arts & Performance",
            "subcategory":"Theater",
            "type":"Entertainment"
        }
    ],
    "sg:phone":"+1 818 508 7602",
    "sg:postcode":"91601",
    "sg:province":"CA",
    "sg:tags":[
        "theatrical"
    ],
    "sg:website":"www.hobby-trains.com",
    "wof:name":"Dizko Entertainment",
    "wof:placetype":"venue"
},
  "geometry": {"coordinates":[-118.36162899999999,34.171582],"type":"Point"}
}