{
  "type": "Feature",
  "properties": {
    "addr:full":"788 Rodriguez St Watsonville CA 95076",
    "addr:housenumber":"788",
    "addr:postcode":"95076",
    "addr:street":"Rodriguez St",
    "iso:country":"US",
    "sg:address":"788 Rodriguez St",
    "sg:city":"Watsonville",
    "sg:classifiers":[
        {
            "category":"Freight",
            "type":"Transportation"
        }
    ],
    "sg:phone":"+1 831 594 2542",
    "sg:postcode":"95076",
    "sg:province":"CA",
    "sg:tags":[
        "operator",
        "local",
        "trucking"
    ],
    "wof:name":"Kplf Trucking",
    "wof:placetype":"venue"
},
  "geometry": {"coordinates":[-121.76430499999999,36.914733],"type":"Point"}
}