{
  "type": "Feature",
  "properties": {
    "addr:full":"1606 W Washington Blvd Los Angeles CA 90007",
    "addr:housenumber":"1606",
    "addr:postcode":"90007",
    "addr:street":"W Washington Blvd",
    "iso:country":"US",
    "sg:address":"1606 W Washington Blvd",
    "sg:city":"Los Angeles",
    "sg:classifiers":[
        {
            "category":"Restaurant",
            "type":"Food & Drink"
        }
    ],
    "sg:phone":"+1 323 730 8180",
    "sg:postcode":"90007",
    "sg:province":"CA",
    "wof:name":"Tato's Pizza",
    "wof:placetype":"venue"
},
  "geometry": {"coordinates":[-118.292196,34.039927],"type":"Point"}
}