{
  "type": "Feature",
  "properties": {
    "iso:country":"US",
    "sg:address":"3575 Santa Rosa Cir",
    "sg:city":"Corona",
    "sg:classifiers":[
        {
            "category":"Retail",
            "subcategory":"Portrait Studio",
            "type":"Services"
        }
    ],
    "sg:phone":"+1 951 736 9696",
    "sg:postcode":"92882",
    "sg:province":"CA",
    "sg:tags":[
        "photographer"
    ],
    "sg:website":"www.conardphoto.com",
    "wof:name":"Conard Photography",
    "wof:placetype":"venue"
},
  "geometry": {"coordinates":[-117.639009,33.874116],"type":"Point"}
}