{
  "type": "Feature",
  "properties": {
    "addr:full":"2237 S Bentley Ave Los Angeles CA 90064",
    "addr:housenumber":"2237",
    "addr:postcode":"90064",
    "addr:street":"S Bentley Ave",
    "iso:country":"US",
    "sg:address":"2237 S Bentley Ave",
    "sg:city":"Los Angeles",
    "sg:classifiers":[
        {
            "category":"Real Estate",
            "subcategory":"Real Estate Operator",
            "type":"Services"
        }
    ],
    "sg:phone":"+1 310 473 9247",
    "sg:postcode":"90064",
    "sg:province":"CA",
    "sg:tags":[
        "condominium"
    ],
    "wof:name":"Bentley Condominium",
    "wof:placetype":"venue"
},
  "geometry": {"coordinates":[-118.436217,34.039723],"type":"Point"}
}