{
  "type": "Feature",
  "properties": {
    "iso:country":"US",
    "sg:address":"1142 Parkside St",
    "sg:city":"Salinas",
    "sg:classifiers":[
        {
            "category":"Freight",
            "type":"Transportation"
        }
    ],
    "sg:phone":"+1 831 449 3964",
    "sg:postcode":"93906",
    "sg:province":"CA",
    "sg:tags":[
        "trucking"
    ],
    "wof:name":"V G Gomez Trucking",
    "wof:placetype":"venue"
},
  "geometry": {"coordinates":[-121.655779,36.698308],"type":"Point"}
}