{
  "type": "Feature",
  "properties": {
    "addr:full":"715 Petaluma Blvd S Petaluma CA 94952",
    "addr:housenumber":"715",
    "addr:postcode":"94952",
    "addr:street":"Petaluma Blvd S Petaluma",
    "iso:country":"US",
    "sg:address":"715 Petaluma Blvd S",
    "sg:city":"Petaluma",
    "sg:classifiers":[
        {
            "category":"Retail",
            "subcategory":"Auto Repair",
            "type":"Services"
        }
    ],
    "sg:phone":"+1 707 765 2393",
    "sg:postcode":"94952",
    "sg:province":"CA",
    "sg:tags":[
        "wrecker"
    ],
    "wof:name":"Petaluma Towing",
    "wof:placetype":"venue"
},
  "geometry": {"coordinates":[-122.62822300000001,38.229271],"type":"Point"}
}