{
  "type": "Feature",
  "properties": {
    "iso:country":"US",
    "sg:address":"1121 Morning View Dr",
    "sg:city":"Escondido",
    "sg:classifiers":[
        {
            "category":"Home & Garden",
            "subcategory":"Household Appliances",
            "type":"Retail Goods"
        }
    ],
    "sg:phone":"+1 760 480 0440",
    "sg:postcode":"92026",
    "sg:province":"CA",
    "wof:name":"Perks Appliance Svc",
    "wof:placetype":"venue"
},
  "geometry": {"coordinates":[-117.094975,33.135518],"type":"Point"}
}