{
  "type": "Feature",
  "properties": {
    "iso:country":"US",
    "sg:address":"11426 Coriender Ave",
    "sg:city":"Fountain Valley",
    "sg:classifiers":[
        {
            "category":"Professional",
            "type":"Services"
        }
    ],
    "sg:phone":"+1 714 775 8376",
    "sg:postcode":"92708",
    "sg:province":"CA",
    "wof:name":"Clyde R + Shirley M Key",
    "wof:placetype":"venue"
},
  "geometry": {"coordinates":[-117.930013,33.720381],"type":"Point"}
}