{
  "type": "Feature",
  "properties": {
    "iso:country":"US",
    "sg:address":"340 Camarillo Ranch Rd",
    "sg:city":"Camarillo",
    "sg:classifiers":[
        {
            "category":"Professional",
            "subcategory":"Computer Services",
            "type":"Services"
        }
    ],
    "sg:phone":"+1 805 388 3455",
    "sg:postcode":"93012",
    "sg:province":"CA",
    "sg:tags":[
        "repair"
    ],
    "wof:name":"Techzam Computer Svc Inc",
    "wof:placetype":"venue"
},
  "geometry": {"coordinates":[-119.020399,34.219042],"type":"Point"}
}