{
  "type": "Feature",
  "properties": {
    "addr:full":"357 12th St Oakland CA 94607",
    "addr:housenumber":"357",
    "addr:postcode":"94607",
    "addr:street":"12Th St",
    "iso:country":"US",
    "sg:address":"357 12th St",
    "sg:city":"Oakland",
    "sg:classifiers":[
        {
            "category":"Taxi",
            "type":"Transportation"
        }
    ],
    "sg:phone":"+1 510 208 3337",
    "sg:postcode":"94607",
    "sg:province":"CA",
    "wof:name":"Yellow 1A 1 Cab of Oakland",
    "wof:placetype":"venue"
},
  "geometry": {"coordinates":[-122.269997,37.802101],"type":"Point"}
}