{
  "type": "Feature",
  "properties": {
    "iso:country":"US",
    "sg:address":"1440 Grand Ave",
    "sg:city":"Grover Beach",
    "sg:classifiers":[
        {
            "category":"Building & Trades",
            "subcategory":"Construction",
            "type":"Services"
        }
    ],
    "sg:phone":"+1 805 489 1296",
    "sg:postcode":"93433",
    "sg:province":"CA",
    "sg:tags":[
        "designer",
        "marine",
        "contractor"
    ],
    "wof:name":"Pacific Coast Respiratory",
    "wof:placetype":"venue"
},
  "geometry": {"coordinates":[-120.613681,35.12112],"type":"Point"}
}