{
  "type": "Feature",
  "properties": {
    "addr:full":"10 Golf Club Rd Pleasant Hill CA 94523",
    "addr:housenumber":"10",
    "addr:postcode":"94523",
    "addr:street":"Golf Club Rd",
    "iso:country":"US",
    "sg:address":"10 Golf Club Rd",
    "sg:city":"Pleasant Hill",
    "sg:classifiers":[
        {
            "category":"Restaurant",
            "type":"Food & Drink"
        }
    ],
    "sg:phone":"+1 925 689 6094",
    "sg:postcode":"94523",
    "sg:province":"CA",
    "wof:name":"Giant Chef Burger Inc",
    "wof:placetype":"venue"
},
  "geometry": {"coordinates":[-122.064937,37.971629],"type":"Point"}
}