{
  "type": "Feature",
  "properties": {
    "addr:full":"608 S Hill St Ste 611 Los Angeles CA 90014",
    "addr:housenumber":"608",
    "addr:postcode":"90014",
    "addr:street":"S Hill St Ste 611",
    "iso:country":"US",
    "sg:address":"608 S Hill St Ste 611",
    "sg:city":"Los Angeles",
    "sg:classifiers":[
        {
            "category":"Shopping",
            "subcategory":"Jewelry",
            "type":"Retail Goods"
        }
    ],
    "sg:phone":"+1 213 614 7941",
    "sg:postcode":"90014",
    "sg:province":"CA",
    "wof:name":"Sevan A Designs",
    "wof:placetype":"venue"
},
  "geometry": {"coordinates":[-118.251999,34.0448],"type":"Point"}
}