{
  "type": "Feature",
  "properties": {
    "addr:full":"6405 Whittier Blvd Los Angeles CA 90022",
    "addr:housenumber":"6405",
    "addr:postcode":"90022",
    "addr:street":"Whittier Blvd",
    "iso:country":"US",
    "sg:address":"6405 Whittier Blvd",
    "sg:city":"Los Angeles",
    "sg:classifiers":[
        {
            "category":"Manufacturing",
            "subcategory":"Furniture",
            "type":"Manufacturing & Wholesale Goods"
        }
    ],
    "sg:phone":"+1 323 265 0555",
    "sg:postcode":"90022",
    "sg:province":"CA",
    "sg:tags":[
        "upholstered",
        "household",
        "mfg"
    ],
    "wof:name":"Magic Custom Design",
    "wof:placetype":"venue"
},
  "geometry": {"coordinates":[-118.133635,34.015496],"type":"Point"}
}