{
  "type": "Feature",
  "properties": {
    "addr:full":"1925 Solano Ave Vallejo CA 94590",
    "addr:housenumber":"1925",
    "addr:postcode":"94590",
    "addr:street":"Solano Ave",
    "iso:country":"US",
    "sg:address":"1925 Solano Ave",
    "sg:city":"Vallejo",
    "sg:classifiers":[
        {
            "category":"Organizations",
            "subcategory":"Religious Organization",
            "type":"Services"
        }
    ],
    "sg:phone":"+1 707 642 1156",
    "sg:postcode":"94590",
    "sg:province":"CA",
    "sg:tags":[
        "church"
    ],
    "wof:name":"Eltekon Ministry Church Of God",
    "wof:placetype":"venue"
},
  "geometry": {"coordinates":[-122.233253,38.104642],"type":"Point"}
}