{
  "type": "Feature",
  "properties": {
    "addr:full":"9100 Wilshire Boulevard Beverly Hills CA 90212",
    "addr:housenumber":"9100",
    "addr:postcode":"90212",
    "addr:street":"Wilshire Boulevard",
    "iso:country":"US",
    "sg:address":"9100 Wilshire Boulevard",
    "sg:city":"Beverly Hills",
    "sg:classifiers":[
        {
            "category":"Professional",
            "subcategory":"Lawyer & Legal Services",
            "type":"Services"
        }
    ],
    "sg:phone":"+1 310 274 1830",
    "sg:postcode":"90212",
    "sg:province":"CA",
    "wof:name":"Enright & Oceletree Llp",
    "wof:placetype":"venue"
},
  "geometry": {"coordinates":[-118.390744,34.067221],"type":"Point"}
}