{
  "type": "Feature",
  "properties": {
    "iso:country":"US",
    "sg:address":"1250 6th Ave",
    "sg:city":"San Diego",
    "sg:classifiers":[
        {
            "category":"Education",
            "subcategory":"School",
            "type":"Public Place"
        }
    ],
    "sg:phone":"+1 619 702 6300",
    "sg:postcode":"92101",
    "sg:province":"CA",
    "sg:website":"www.intraxenglish.com",
    "wof:name":"Intrax English Institute",
    "wof:placetype":"venue"
},
  "geometry": {"coordinates":[-117.159362,32.718324],"type":"Point"}
}