{
  "type": "Feature",
  "properties": {
    "addr:full":"774 Delnero Dr Suite D Sonora CA 95370",
    "addr:housenumber":"774",
    "addr:postcode":"95370",
    "addr:street":"Delnero Dr Suite D",
    "iso:country":"US",
    "sg:address":"774 Delnero Dr Suite D",
    "sg:city":"Sonora",
    "sg:classifiers":[
        {
            "category":"Health Services",
            "subcategory":"Dentist",
            "type":"Services"
        }
    ],
    "sg:phone":"+1 209 532 4401",
    "sg:postcode":"95370",
    "sg:province":"CA",
    "sg:tags":[
        "product",
        "dentists-cosmetic",
        "denture",
        "dentists-prosthodontists",
        "teeth",
        "dentists-pediatric",
        "whitening",
        "dentistry"
    ],
    "sg:website":"http://sonorafamilydentist.com",
    "wof:name":"Silva Richard DDS",
    "wof:placetype":"venue"
},
  "geometry": {"coordinates":[-120.370377,37.978477],"type":"Point"}
}