{
  "type": "Feature",
  "properties": {
    "addr:full":"11711 Westminster Ave Ste 4B Garden Grove CA 92843",
    "addr:housenumber":"11711",
    "addr:postcode":"92843",
    "addr:street":"Westminster Ave Ste 4B",
    "iso:country":"US",
    "sg:address":"11711 Westminster Ave Ste 4B",
    "sg:city":"Garden Grove",
    "sg:classifiers":[
        {
            "category":"Retail",
            "subcategory":"Auto Repair",
            "type":"Services"
        }
    ],
    "sg:phone":"+1 714 530 3558",
    "sg:postcode":"92843",
    "sg:province":"CA",
    "sg:tags":[
        "body",
        "shop"
    ],
    "sg:website":"www.orangecountybodyworks.com",
    "wof:name":"Orange County Bodyworks",
    "wof:placetype":"venue"
},
  "geometry": {"coordinates":[-117.925003,33.7598],"type":"Point"}
}