{
  "type": "Feature",
  "properties": {
    "iso:country":"US",
    "sg:address":"11415 Folsom Blvd",
    "sg:city":"Sacramento",
    "sg:classifiers":[
        {
            "category":"Home & Garden",
            "subcategory":"Furniture",
            "type":"Retail Goods"
        }
    ],
    "sg:phone":"+1 916 853 9404",
    "sg:postcode":"95814",
    "sg:province":"CA",
    "sg:tags":[
        "store"
    ],
    "wof:name":"Drexel Heritage Home Inspirations",
    "wof:placetype":"venue"
},
  "geometry": {"coordinates":[-121.491997,38.577599],"type":"Point"}
}