{
  "type": "Feature",
  "properties": {
    "iso:country":"US",
    "sg:address":"6415 Marindustry Dr",
    "sg:city":"San Diego",
    "sg:classifiers":[
        {
            "category":"Building & Trades",
            "subcategory":"Construction",
            "type":"Services"
        }
    ],
    "sg:phone":"+1 858 452 5590",
    "sg:postcode":"92121",
    "sg:province":"CA",
    "sg:tags":[
        "fence",
        "contractor"
    ],
    "sg:website":"www.crownfence.com",
    "wof:name":"Crown Fence Co",
    "wof:placetype":"venue"
},
  "geometry": {"coordinates":[-117.177845,32.880041],"type":"Point"}
}