{
  "type": "Feature",
  "properties": {
    "addr:full":"4143 3rd Avenue # 2 Sacramento CA 95817",
    "addr:housenumber":"4143",
    "addr:postcode":"95817",
    "addr:street":"3Rd Avenue # 2",
    "iso:country":"US",
    "sg:address":"4143 3rd Avenue # 2",
    "sg:city":"Sacramento",
    "sg:classifiers":[
        {
            "category":"Food & Beverages",
            "subcategory":"Groceries & Convenience Stores",
            "type":"Retail Goods"
        }
    ],
    "sg:phone":"+1 916 456 1468",
    "sg:postcode":"95817",
    "sg:province":"CA",
    "wof:name":"Sam's Market No 2",
    "wof:placetype":"venue"
},
  "geometry": {"coordinates":[-121.458448,38.549263],"type":"Point"}
}