{
  "type": "Feature",
  "properties": {
    "iso:country":"US",
    "sg:address":"1767 Westwood Boulevard",
    "sg:city":"Los Angeles",
    "sg:classifiers":[
        {
            "category":"Restaurant",
            "type":"Food & Drink"
        }
    ],
    "sg:phone":"+1 310 478 3270",
    "sg:postcode":"90024",
    "sg:province":"CA",
    "sg:tags":[
        "chinese"
    ],
    "wof:name":"Cheng Du",
    "wof:placetype":"venue"
},
  "geometry": {"coordinates":[-118.438143,34.050484],"type":"Point"}
}