{
  "type": "Feature",
  "properties": {
    "iso:country":"US",
    "sg:address":"137 Lyndon St",
    "sg:city":"Hermosa Beach",
    "sg:classifiers":[
        {
            "category":"Manufacturing",
            "subcategory":"Printing",
            "type":"Manufacturing & Wholesale Goods"
        }
    ],
    "sg:phone":"+1 310 937 9028",
    "sg:postcode":"90254",
    "sg:province":"CA",
    "sg:tags":[
        "lithographic",
        "commercial"
    ],
    "wof:name":"Orange County Fast Print Inc",
    "wof:placetype":"venue"
},
  "geometry": {"coordinates":[-118.395872,33.853427],"type":"Point"}
}