{
  "type": "Feature",
  "properties": {
    "addr:full":"9216 Berwyn Way Windsor CA 95492",
    "addr:housenumber":"9216",
    "addr:postcode":"95492",
    "addr:street":"Berwyn Way",
    "iso:country":"US",
    "sg:address":"9216 Berwyn Way",
    "sg:city":"Windsor",
    "sg:classifiers":[
        {
            "category":"Wholesale",
            "subcategory":"Electrical",
            "type":"Manufacturing & Wholesale Goods"
        }
    ],
    "sg:phone":"+1 707 838 9708",
    "sg:postcode":"95492",
    "sg:province":"CA",
    "sg:tags":[
        "cards",
        "distributes",
        "prepaid",
        "calling"
    ],
    "wof:name":"Emarketing",
    "wof:placetype":"venue"
},
  "geometry": {"coordinates":[-122.81878,38.550413],"type":"Point"}
}