{
  "type": "Feature",
  "properties": {
    "iso:country":"US",
    "sg:address":"1417 Buena Vista St",
    "sg:city":"Ventura",
    "sg:classifiers":[
        {
            "category":"Building & Trades",
            "subcategory":"Plumbing",
            "type":"Services"
        }
    ],
    "sg:phone":"+1 805 278 9989",
    "sg:postcode":"93001",
    "sg:province":"CA",
    "sg:tags":[
        "plumbing",
        "contractor"
    ],
    "wof:name":"Mc Rooter Plumbing",
    "wof:placetype":"venue"
},
  "geometry": {"coordinates":[-119.27805499999999,34.282929],"type":"Point"}
}