{
  "type": "Feature",
  "properties": {
    "addr:full":"8944 Burton Way Beverly Hills CA 90211",
    "addr:housenumber":"8944",
    "addr:postcode":"90211",
    "addr:street":"Burton Way",
    "iso:country":"US",
    "sg:address":"8944 Burton Way",
    "sg:city":"Beverly Hills",
    "sg:classifiers":[
        {
            "category":"Personal",
            "subcategory":"Beauty Salon",
            "type":"Services"
        }
    ],
    "sg:phone":"+1 310 285 0088",
    "sg:postcode":"90211",
    "sg:province":"CA",
    "sg:tags":[
        "hair"
    ],
    "sg:website":"www.chrismcmillansalon.com/Home....",
    "wof:name":"Chris McMillan Salon",
    "wof:placetype":"venue"
},
  "geometry": {"coordinates":[-118.387248,34.071999],"type":"Point"}
}