{
  "type": "Feature",
  "properties": {
    "iso:country":"US",
    "sg:address":"2460 Garden Rd",
    "sg:city":"Monterey",
    "sg:classifiers":[
        {
            "category":"Professional",
            "subcategory":"Art Services",
            "type":"Services"
        }
    ],
    "sg:phone":"+1 831 899 8830",
    "sg:postcode":"93940",
    "sg:province":"CA",
    "sg:tags":[
        "photographer"
    ],
    "sg:website":"www.interfacevisual.com",
    "wof:name":"Interface Visual",
    "wof:placetype":"venue"
},
  "geometry": {"coordinates":[-121.854744,36.586147],"type":"Point"}
}