{
  "type": "Feature",
  "properties": {
    "addr:full":"1277 Boulevard Way Walnut Creek CA 94595",
    "addr:housenumber":"1277",
    "addr:postcode":"94595",
    "addr:street":"Boulevard Way",
    "iso:country":"US",
    "sg:address":"1277 Boulevard Way",
    "sg:city":"Walnut Creek",
    "sg:classifiers":[
        {
            "category":"Education",
            "subcategory":"Special Training",
            "type":"Public Place"
        }
    ],
    "sg:phone":"+1 925 944 0551",
    "sg:postcode":"94595",
    "sg:province":"CA",
    "sg:tags":[
        "dramatic",
        "instruction"
    ],
    "wof:name":"California Theatre Arts",
    "wof:placetype":"venue"
},
  "geometry": {"coordinates":[-122.07649000000001,37.89385],"type":"Point"}
}