{
  "type": "Feature",
  "properties": {
    "iso:country":"US",
    "sg:address":"388 Russell Rd",
    "sg:city":"Brawley",
    "sg:classifiers":[
        {
            "category":"Farming",
            "subcategory":"Livestock Farm",
            "type":"Manufacturing & Wholesale Goods"
        }
    ],
    "sg:phone":"+1 760 344 0687",
    "sg:postcode":"92227",
    "sg:province":"CA",
    "sg:tags":[
        "alfalfa",
        "wheat",
        "beef",
        "sugar",
        "beet",
        "cattle",
        "feedlot"
    ],
    "wof:name":"Bill Wiest Ranches Inc",
    "wof:placetype":"venue"
},
  "geometry": {"coordinates":[-115.551676,32.975445],"type":"Point"}
}