{
  "type": "Feature",
  "properties": {
    "iso:country":"US",
    "sg:address":"1111 Wakeham Ave",
    "sg:city":"Santa Ana",
    "sg:classifiers":[
        {
            "category":"Manufacturing",
            "subcategory":"Building Materials",
            "type":"Manufacturing & Wholesale Goods"
        }
    ],
    "sg:phone":"+1 714 639 0774",
    "sg:postcode":"92705",
    "sg:province":"CA",
    "sg:tags":[
        "mfg",
        "wood",
        "kitchen",
        "cabinet"
    ],
    "wof:name":"A To Z Custom Cabinets",
    "wof:placetype":"venue"
},
  "geometry": {"coordinates":[-117.850345,33.737323],"type":"Point"}
}