{
  "type": "Feature",
  "properties": {
    "iso:country":"US",
    "sg:address":"1434 Mesa View St",
    "sg:city":"Hemet",
    "sg:classifiers":[
        {
            "category":"Manufacturing",
            "subcategory":"Metals",
            "type":"Manufacturing & Wholesale Goods"
        }
    ],
    "sg:phone":"+1 951 654 2882",
    "sg:postcode":"92543",
    "sg:province":"CA",
    "sg:tags":[
        "steel",
        "mfg",
        "metalwork",
        "structural"
    ],
    "wof:name":"Christie Steel Fabrication Inc",
    "wof:placetype":"venue"
},
  "geometry": {"coordinates":[-116.973816,33.772197],"type":"Point"}
}