{
  "type": "Feature",
  "properties": {
    "addr:full":"1640 Yosemite Pkwy Merced CA 95341",
    "addr:housenumber":"1640",
    "addr:postcode":"95341",
    "addr:street":"Yosemite Pkwy",
    "iso:country":"US",
    "sg:address":"1640 Yosemite Pkwy",
    "sg:city":"Merced",
    "sg:classifiers":[
        {
            "category":"Food & Beverages",
            "subcategory":"Groceries & Convenience Stores",
            "type":"Retail Goods"
        }
    ],
    "sg:phone":"+1 209 723 2265",
    "sg:postcode":"95341",
    "sg:province":"CA",
    "sg:tags":[
        "grocer"
    ],
    "wof:name":"You Cheng Market",
    "wof:placetype":"venue"
},
  "geometry": {"coordinates":[-120.45654999999999,37.295113],"type":"Point"}
}