{
  "type": "Feature",
  "properties": {
    "addr:full":"4120 Pleasant Valley Road Placerville CA 95667",
    "addr:housenumber":"4120",
    "addr:postcode":"95667",
    "addr:street":"Pleasant Valley Road",
    "iso:country":"US",
    "sg:address":"4120 Pleasant Valley Road",
    "sg:city":"Placerville",
    "sg:classifiers":[
        {
            "category":"Education",
            "subcategory":"School",
            "type":"Public Place"
        }
    ],
    "sg:phone":"+1 530 644 9620",
    "sg:postcode":"95667",
    "sg:province":"CA",
    "wof:name":"Pleasant Valley School",
    "wof:placetype":"venue"
},
  "geometry": {"coordinates":[-120.678577,38.693822],"type":"Point"}
}