{
  "type": "Feature",
  "properties": {
    "iso:country":"US",
    "sg:address":"740 Canyon Ct",
    "sg:city":"Ukiah",
    "sg:classifiers":[
        {
            "category":"Shopping",
            "subcategory":"Bicycles & Sporting Goods",
            "type":"Retail Goods"
        }
    ],
    "sg:phone":"+1 707 467 9003",
    "sg:postcode":"95482",
    "sg:province":"CA",
    "wof:name":"Eddy Out Enterprises",
    "wof:placetype":"venue"
},
  "geometry": {"coordinates":[-123.212729,39.112707],"type":"Point"}
}