{
  "type": "Feature",
  "properties": {
    "addr:full":"556 S Broadway Ste 12 Los Angeles CA 90013",
    "addr:housenumber":"556",
    "addr:postcode":"90013",
    "addr:street":"S Broadway Ste 12",
    "iso:country":"US",
    "sg:address":"556 S Broadway Ste 12",
    "sg:city":"Los Angeles",
    "sg:classifiers":[
        {
            "category":"Shopping",
            "subcategory":"Jewelry",
            "type":"Retail Goods"
        }
    ],
    "sg:phone":"+1 213 228 0044",
    "sg:postcode":"90013",
    "sg:province":"CA",
    "wof:name":"Matt Jewelry",
    "wof:placetype":"venue"
},
  "geometry": {"coordinates":[-118.24400300000001,34.045101],"type":"Point"}
}