{
  "type": "Feature",
  "properties": {
    "iso:country":"US",
    "sg:address":"6363 Wilshire Blvd",
    "sg:city":"Los Angeles",
    "sg:classifiers":[
        {
            "category":"Professional",
            "type":"Services"
        }
    ],
    "sg:phone":"+1 323 650 5353",
    "sg:postcode":"90048",
    "sg:province":"CA",
    "sg:tags":[
        "establishment"
    ],
    "wof:name":"Ig Communications",
    "wof:placetype":"venue"
},
  "geometry": {"coordinates":[-118.366788,34.063619],"type":"Point"}
}