{
  "type": "Feature",
  "properties": {
    "iso:country":"US",
    "sg:address":"230 N Crescent Way Ste D",
    "sg:city":"Anaheim",
    "sg:classifiers":[
        {
            "category":"Coffee & Tea",
            "type":"Food & Drink"
        }
    ],
    "sg:phone":"+1 714 991 4528",
    "sg:postcode":"92801",
    "sg:province":"CA",
    "wof:name":"Pacific Cafe",
    "wof:placetype":"venue"
},
  "geometry": {"coordinates":[-117.94699900000001,33.834099],"type":"Point"}
}