{
  "type": "Feature",
  "properties": {
    "iso:country":"US",
    "sg:address":"1940 The Alameda",
    "sg:city":"San Jose",
    "sg:classifiers":[
        {
            "category":"Building & Trades",
            "subcategory":"Equipment Rental",
            "type":"Services"
        }
    ],
    "sg:phone":"+1 408 557 8314",
    "sg:postcode":"95126",
    "sg:province":"CA",
    "sg:tags":[
        "crane"
    ],
    "wof:name":"John Crane Belfab",
    "wof:placetype":"venue"
},
  "geometry": {"coordinates":[-121.92317799999999,37.340979],"type":"Point"}
}