{
  "type": "Feature",
  "properties": {
    "addr:full":"870 E 9th St Pomona CA 91766",
    "addr:housenumber":"870",
    "addr:postcode":"91766",
    "addr:street":"E 9Th St",
    "iso:country":"US",
    "sg:address":"870 E 9th St",
    "sg:city":"Pomona",
    "sg:classifiers":[
        {
            "category":"Recreation",
            "type":"Entertainment"
        }
    ],
    "sg:phone":"+1 909 620 3671",
    "sg:postcode":"91766",
    "sg:province":"CA",
    "sg:tags":[
        "parks"
    ],
    "sg:website":"www.ci.pomona.ca.us",
    "wof:name":"Pomona Park Maintenance",
    "wof:placetype":"venue"
},
  "geometry": {"coordinates":[-117.740285,34.051632],"type":"Point"}
}