{
  "type": "Feature",
  "properties": {
    "iso:country":"US",
    "sg:address":"140 Lakewood Center Mall",
    "sg:city":"Lakewood",
    "sg:classifiers":[
        {
            "category":"Food & Beverages",
            "subcategory":"Specialty",
            "type":"Retail Goods"
        }
    ],
    "sg:phone":"+1 562 633 5064",
    "sg:postcode":"90712",
    "sg:province":"CA",
    "sg:tags":[
        "health",
        "diet"
    ],
    "wof:name":"GNC",
    "wof:placetype":"venue"
},
  "geometry": {"coordinates":[-118.140423,33.850294],"type":"Point"}
}