{
  "type": "Feature",
  "properties": {
    "addr:full":"3820 W El Segundo Boulevard Hawthorne CA 90250",
    "addr:housenumber":"3820",
    "addr:postcode":"90250",
    "addr:street":"W El Segundo Boulevard",
    "iso:country":"US",
    "sg:address":"3820 W El Segundo Boulevard",
    "sg:city":"Hawthorne",
    "sg:classifiers":[
        {
            "category":"Retail",
            "subcategory":"Auto Repair",
            "type":"Services"
        }
    ],
    "sg:phone":"+1 310 644 4443",
    "sg:postcode":"90250",
    "sg:province":"CA",
    "wof:name":"Tilden Car Care Center",
    "wof:placetype":"venue"
},
  "geometry": {"coordinates":[-118.339905,33.916445],"type":"Point"}
}