{
  "type": "Feature",
  "properties": {
    "iso:country":"US",
    "sg:address":"1111 Lockheed Martin Way",
    "sg:city":"Sunnyvale",
    "sg:classifiers":[
        {
            "category":"Government",
            "subcategory":"Office",
            "type":"Public Place"
        }
    ],
    "sg:phone":"+1 408 742 1611",
    "sg:postcode":"94089",
    "sg:province":"CA",
    "sg:tags":[
        "federal",
        "security"
    ],
    "wof:name":"US Defense Dept",
    "wof:placetype":"venue"
},
  "geometry": {"coordinates":[-122.02669,37.407197],"type":"Point"}
}