{
  "type": "Feature",
  "properties": {
    "iso:country":"US",
    "sg:address":"12915 Ruthelen Ave",
    "sg:city":"Gardena",
    "sg:classifiers":[
        {
            "category":"Wholesale",
            "subcategory":"Stationery",
            "type":"Manufacturing & Wholesale Goods"
        }
    ],
    "sg:phone":"+1 310 532 8127",
    "sg:postcode":"90249",
    "sg:province":"CA",
    "sg:tags":[
        "supply"
    ],
    "wof:name":"Toi Box",
    "wof:placetype":"venue"
},
  "geometry": {"coordinates":[-118.312341,33.912784],"type":"Point"}
}