{
  "type": "Feature",
  "properties": {
    "addr:full":"46710 Crawford St Fremont CA 94539",
    "addr:housenumber":"46710",
    "addr:postcode":"94539",
    "addr:street":"Crawford St",
    "iso:country":"US",
    "sg:address":"46710 Crawford St",
    "sg:city":"Fremont",
    "sg:classifiers":[
        {
            "category":"Wholesale",
            "subcategory":"Non-durable Goods",
            "type":"Manufacturing & Wholesale Goods"
        }
    ],
    "sg:phone":"+1 510 651 5513",
    "sg:postcode":"94539",
    "sg:province":"CA",
    "wof:name":"Innovative Technology & Trdg",
    "wof:placetype":"venue"
},
  "geometry": {"coordinates":[-121.922713,37.492634],"type":"Point"}
}