{
  "type": "Feature",
  "properties": {
    "iso:country":"US",
    "sg:address":"17819 Clark Ave",
    "sg:city":"Bellflower",
    "sg:classifiers":[
        {
            "category":"Food & Beverages",
            "subcategory":"Meat & Fish",
            "type":"Retail Goods"
        }
    ],
    "sg:phone":"+1 877 345 5982",
    "sg:postcode":"90706",
    "sg:province":"CA",
    "sg:tags":[
        "shop"
    ],
    "wof:name":"La Granja Meat Market",
    "wof:placetype":"venue"
},
  "geometry": {"coordinates":[-118.13419500000001,33.870448],"type":"Point"}
}