{
  "type": "Feature",
  "properties": {
    "addr:full":"44831 Fremont Blvd Fremont CA 94538",
    "addr:housenumber":"44831",
    "addr:postcode":"94538",
    "addr:street":"Fremont Blvd",
    "iso:country":"US",
    "sg:address":"44831 Fremont Blvd",
    "sg:city":"Fremont",
    "sg:classifiers":[
        {
            "category":"Shopping",
            "subcategory":"Computers & Home Electronics",
            "type":"Retail Goods"
        }
    ],
    "sg:phone":"+1 510 226 7999",
    "sg:postcode":"94538",
    "sg:province":"CA",
    "sg:tags":[
        "equipment",
        "dealer"
    ],
    "wof:name":"Soden Co",
    "wof:placetype":"venue"
},
  "geometry": {"coordinates":[-121.94911399999999,37.502396],"type":"Point"}
}