{
  "type": "Feature",
  "properties": {
    "addr:full":"20120 Alexander Ave Anderson CA 96007",
    "addr:housenumber":"20120",
    "addr:postcode":"96007",
    "addr:street":"Alexander Ave",
    "iso:country":"US",
    "sg:address":"20120 Alexander Ave",
    "sg:city":"Anderson",
    "sg:classifiers":[
        {
            "category":"Professional",
            "type":"Services"
        }
    ],
    "sg:phone":"+1 530 365 5556",
    "sg:postcode":"96007",
    "sg:province":"CA",
    "wof:name":"Miette S Wells",
    "wof:placetype":"venue"
},
  "geometry": {"coordinates":[-122.31222099999999,40.462002],"type":"Point"}
}