{
  "type": "Feature",
  "properties": {
    "addr:full":"15670 Stoney Creek Dr Riverside CA 92504",
    "addr:housenumber":"15670",
    "addr:postcode":"92504",
    "addr:street":"Stoney Creek Dr",
    "iso:country":"US",
    "sg:address":"15670 Stoney Creek Dr",
    "sg:city":"Riverside",
    "sg:classifiers":[
        {
            "category":"Building & Trades",
            "subcategory":"Construction",
            "type":"Services"
        }
    ],
    "sg:phone":"+1 951 789 0153",
    "sg:postcode":"92504",
    "sg:province":"CA",
    "sg:tags":[
        "contractor"
    ],
    "wof:name":"Gutzmann Masonry Inc",
    "wof:placetype":"venue"
},
  "geometry": {"coordinates":[-117.388746,33.877513],"type":"Point"}
}