{
  "type": "Feature",
  "properties": {
    "addr:full":"1336 Santa Ana Ave Sacramento CA 95838",
    "addr:housenumber":"1336",
    "addr:postcode":"95838",
    "addr:street":"Santa Ana Ave",
    "iso:country":"US",
    "sg:address":"1336 Santa Ana Ave",
    "sg:city":"Sacramento",
    "sg:classifiers":[
        {
            "category":"Autos & Motor Vehicles",
            "subcategory":"Auto Supplies",
            "type":"Retail Goods"
        },
        {
            "category":"Building & Trades",
            "subcategory":"Electrical",
            "type":"Services"
        },
        {
            "category":"Retail",
            "subcategory":"Auto Repair",
            "type":"Services"
        }
    ],
    "sg:phone":"+1 916 927 3386",
    "sg:postcode":"95838",
    "sg:province":"CA",
    "sg:tags":[
        "alternator",
        "industrial",
        "electrician",
        "electric",
        "automobile",
        "generators-automotive",
        "accessory",
        "part",
        "contractors-commercial"
    ],
    "wof:name":"George's Electrical Service",
    "wof:placetype":"venue"
},
  "geometry": {"coordinates":[-121.43476200000001,38.658289],"type":"Point"}
}