{
  "type": "Feature",
  "properties": {
    "iso:country":"US",
    "sg:address":"4720 Chino Ave",
    "sg:city":"Chino",
    "sg:classifiers":[
        {
            "category":"Autos & Motor Vehicles",
            "subcategory":"Auto Supplies",
            "type":"Retail Goods"
        }
    ],
    "sg:phone":"+1 909 465 6320",
    "sg:postcode":"91710",
    "sg:province":"CA",
    "sg:tags":[
        "automobile",
        "part",
        "tire",
        "accessory"
    ],
    "wof:name":"Bj's Chrome and Custom",
    "wof:placetype":"venue"
},
  "geometry": {"coordinates":[-117.702091,34.01174],"type":"Point"}
}