{
  "type": "Feature",
  "properties": {
    "addr:full":"17593 Penn Valley Dr Penn Valley CA 95946",
    "addr:housenumber":"17593",
    "addr:postcode":"95946",
    "addr:street":"Penn Valley Dr",
    "iso:country":"US",
    "sg:address":"17593 Penn Valley Dr",
    "sg:city":"Penn Valley",
    "sg:classifiers":[
        {
            "category":"Home & Garden",
            "subcategory":"Home Furnishings",
            "type":"Retail Goods"
        }
    ],
    "sg:phone":"+1 530 432 2499",
    "sg:postcode":"95946",
    "sg:province":"CA",
    "sg:tags":[
        "stove",
        "wood",
        "burning"
    ],
    "wof:name":"Abercrombie & Co",
    "wof:placetype":"venue"
},
  "geometry": {"coordinates":[-121.17988800000001,39.198103],"type":"Point"}
}