{
  "type": "Feature",
  "properties": {
    "iso:country":"US",
    "sg:address":"355 W Olive Ave",
    "sg:city":"Sunnyvale",
    "sg:classifiers":[
        {
            "category":"Banks & Credit Unions",
            "subcategory":"Investment Brokerage",
            "type":"Services"
        }
    ],
    "sg:phone":"+1 408 554 9988",
    "sg:postcode":"94086",
    "sg:province":"CA",
    "sg:tags":[
        "consultant",
        "planning",
        "financial"
    ],
    "wof:name":"Carole Zhou Financial Planning",
    "wof:placetype":"venue"
},
  "geometry": {"coordinates":[-122.035152,37.371568],"type":"Point"}
}