{
  "type": "Feature",
  "properties": {
    "addr:full":"1413 W Brooks St Ontario CA 91762",
    "addr:housenumber":"1413",
    "addr:postcode":"91762",
    "addr:street":"W Brooks St",
    "iso:country":"US",
    "sg:address":"1413 W Brooks St",
    "sg:city":"Ontario",
    "sg:classifiers":[
        {
            "category":"Manufacturing",
            "subcategory":"Printing",
            "type":"Manufacturing & Wholesale Goods"
        }
    ],
    "sg:phone":"+1 909 986 2675",
    "sg:postcode":"91762",
    "sg:province":"CA",
    "sg:tags":[
        "screen",
        "commercial"
    ],
    "wof:name":"Techni-Grafix",
    "wof:placetype":"venue"
},
  "geometry": {"coordinates":[-117.679766,34.061739],"type":"Point"}
}