{
  "type": "Feature",
  "properties": {
    "addr:full":"6850 Mission Gorge Rd San Diego CA 92120",
    "addr:housenumber":"6850",
    "addr:postcode":"92120",
    "addr:street":"Mission Gorge Rd",
    "iso:country":"US",
    "sg:address":"6850 Mission Gorge Rd",
    "sg:city":"San Diego",
    "sg:classifiers":[
        {
            "category":"Real Estate",
            "subcategory":"Real Estate Operator",
            "type":"Services"
        }
    ],
    "sg:phone":"+1 619 583 3440",
    "sg:postcode":"92120",
    "sg:province":"CA",
    "sg:tags":[
        "mobile",
        "home",
        "community"
    ],
    "wof:name":"Mission Valley Village",
    "wof:placetype":"venue"
},
  "geometry": {"coordinates":[-117.093434,32.797495],"type":"Point"}
}