{
  "type": "Feature",
  "properties": {
    "addr:full":"37 Terrace Ct Belvedere Tibrn CA 94920",
    "addr:housenumber":"37",
    "addr:postcode":"94920",
    "addr:street":"Terrace Ct",
    "iso:country":"US",
    "sg:address":"37 Terrace Ct",
    "sg:city":"Belvedere Tibrn",
    "sg:classifiers":[
        {
            "category":"Shopping",
            "subcategory":"Gifts & Souvenirs",
            "type":"Retail Goods"
        }
    ],
    "sg:phone":"+1 415 435 5161",
    "sg:postcode":"94920",
    "sg:province":"CA",
    "sg:tags":[
        "collectible"
    ],
    "wof:name":"Cathy's Collections",
    "wof:placetype":"venue"
},
  "geometry": {"coordinates":[-122.492581,37.898489],"type":"Point"}
}