{
  "type": "Feature",
  "properties": {
    "iso:country":"US",
    "sg:address":"407 C St",
    "sg:city":"Marysville",
    "sg:classifiers":[
        {
            "category":"Government",
            "subcategory":"Post Office",
            "type":"Public Place"
        }
    ],
    "sg:phone":"+1 530 742 1807",
    "sg:postcode":"95901",
    "sg:province":"CA",
    "sg:tags":[
        "postal",
        "us"
    ],
    "wof:name":"US Post Office",
    "wof:placetype":"venue"
},
  "geometry": {"coordinates":[-121.587416,39.140407],"type":"Point"}
}