{
  "type": "Feature",
  "properties": {
    "addr:full":"14250 Mulberry Drive Los Gatos CA 95032",
    "addr:housenumber":"14250",
    "addr:postcode":"95032",
    "addr:street":"Mulberry Drive",
    "iso:country":"US",
    "sg:address":"14250 Mulberry Drive",
    "sg:city":"Los Gatos",
    "sg:classifiers":[
        {
            "category":"Personal",
            "type":"Services"
        },
        {
            "category":"Professional",
            "subcategory":"Business Services",
            "type":"Services"
        }
    ],
    "sg:phone":"+1 408 781 1559",
    "sg:postcode":"95032",
    "sg:province":"CA",
    "sg:tags":[
        "delivery",
        "mover",
        "courier"
    ],
    "wof:name":"Adagio Piano Moving",
    "wof:placetype":"venue"
},
  "geometry": {"coordinates":[-121.974086,37.261298],"type":"Point"}
}