{
  "type": "Feature",
  "properties": {
    "addr:full":"1419 Park Ave Alameda CA 94501",
    "addr:housenumber":"1419",
    "addr:postcode":"94501",
    "addr:street":"Park Ave",
    "iso:country":"US",
    "sg:address":"1419 Park Ave",
    "sg:city":"Alameda",
    "sg:classifiers":[
        {
            "category":"Shopping",
            "subcategory":"Tobacco",
            "type":"Retail Goods"
        }
    ],
    "sg:postcode":"94501",
    "sg:province":"CA",
    "sg:tags":[
        "shop"
    ],
    "wof:name":"Pillow Park Puff",
    "wof:placetype":"venue"
},
  "geometry": {"coordinates":[-122.241702,37.763998],"type":"Point"}
}