{
  "type": "Feature",
  "properties": {
    "addr:full":"360 Thor Pl Brea CA 92821",
    "addr:housenumber":"360",
    "addr:postcode":"92821",
    "addr:street":"Thor Pl",
    "iso:country":"US",
    "sg:address":"360 Thor Pl",
    "sg:city":"Brea",
    "sg:classifiers":[
        {
            "category":"Wholesale",
            "subcategory":"Non-durable Goods",
            "type":"Manufacturing & Wholesale Goods"
        }
    ],
    "sg:phone":"+1 714 671 9788",
    "sg:postcode":"92821",
    "sg:province":"CA",
    "sg:tags":[
        "supply",
        "f"
    ],
    "wof:name":"Lungsal USA",
    "wof:placetype":"venue"
},
  "geometry": {"coordinates":[-117.891476,33.923395],"type":"Point"}
}