{
  "type": "Feature",
  "properties": {
    "iso:country":"US",
    "sg:address":"204 Main St",
    "sg:city":"Newport Beach",
    "sg:classifiers":[
        {
            "category":"Government",
            "subcategory":"City Hall",
            "type":"Public Place"
        }
    ],
    "sg:phone":"+1 800 275 8777",
    "sg:postcode":"92661",
    "sg:province":"CA",
    "wof:name":"US Post Office - Balboa Station",
    "wof:placetype":"venue"
},
  "geometry": {"coordinates":[-117.899057,33.602094],"type":"Point"}
}