{
  "type": "Feature",
  "properties": {
    "addr:full":"27901 La Paz Road Laguna Niguel CA 92677",
    "addr:housenumber":"27901",
    "addr:postcode":"92677",
    "addr:street":"La Paz Road",
    "iso:country":"US",
    "sg:address":"27901 La Paz Road",
    "sg:city":"Laguna Niguel",
    "sg:classifiers":[
        {
            "category":"Sports & Exercise",
            "subcategory":"Gym",
            "type":"Entertainment"
        }
    ],
    "sg:phone":"+1 949 425 9265",
    "sg:postcode":"92677",
    "sg:province":"CA",
    "sg:tags":[
        "trainer"
    ],
    "wof:name":"Pro Fit Personal Training",
    "wof:placetype":"venue"
},
  "geometry": {"coordinates":[-117.710021,33.556369],"type":"Point"}
}