{
  "type": "Feature",
  "properties": {
    "iso:country":"US",
    "sg:address":"330 S Almont Dr",
    "sg:city":"Los Angeles",
    "sg:classifiers":[
        {
            "category":"Communications",
            "subcategory":"Film & Video Production",
            "type":"Services"
        }
    ],
    "sg:phone":"+1 310 274 3874",
    "sg:postcode":"90048",
    "sg:province":"CA",
    "sg:tags":[
        "motion",
        "picture",
        "studio",
        "producer"
    ],
    "wof:name":"Aria Entertainment",
    "wof:placetype":"venue"
},
  "geometry": {"coordinates":[-118.38767199999999,34.072721],"type":"Point"}
}