{
  "type": "Feature",
  "properties": {
    "iso:country":"US",
    "sg:address":"408 7th St",
    "sg:city":"Eureka",
    "sg:classifiers":[
        {
            "category":"Real Estate",
            "subcategory":"Real Estate Services",
            "type":"Services"
        }
    ],
    "sg:phone":"+1 707 442 7878",
    "sg:postcode":"95501",
    "sg:province":"CA",
    "sg:tags":[
        "loan"
    ],
    "wof:name":"Financial Capital Inc. Mortgage Bankers",
    "wof:placetype":"venue"
},
  "geometry": {"coordinates":[-124.166586,40.800133],"type":"Point"}
}