{
  "type": "Feature",
  "properties": {
    "iso:country":"US",
    "sg:address":"909 N D St",
    "sg:city":"San Bernardino",
    "sg:classifiers":[
        {
            "category":"Real Estate",
            "subcategory":"Real Estate Agent",
            "type":"Services"
        }
    ],
    "sg:phone":"+1 909 384 8222",
    "sg:postcode":"92410",
    "sg:province":"CA",
    "sg:tags":[
        "management"
    ],
    "wof:name":"Management Plus 1",
    "wof:placetype":"venue"
},
  "geometry": {"coordinates":[-117.291848,34.117525],"type":"Point"}
}