{
  "type": "Feature",
  "properties": {
    "iso:country":"US",
    "sg:address":"4205 W Iris Ave",
    "sg:city":"Visalia",
    "sg:classifiers":[
        {
            "category":"Social Services",
            "subcategory":"Child Care",
            "type":"Services"
        }
    ],
    "sg:phone":"+1 559 734 5462",
    "sg:postcode":"93277",
    "sg:province":"CA",
    "wof:name":"Ms Jaimie's Day Care",
    "wof:placetype":"venue"
},
  "geometry": {"coordinates":[-119.339546,36.319067],"type":"Point"}
}