{
  "type": "Feature",
  "properties": {
    "addr:full":"6380 Tupelo Dr Citrus Heights CA 95621",
    "addr:housenumber":"6380",
    "addr:postcode":"95621",
    "addr:street":"Tupelo Dr",
    "iso:country":"US",
    "sg:address":"6380 Tupelo Dr",
    "sg:city":"Citrus Heights",
    "sg:classifiers":[
        {
            "category":"Wholesale",
            "subcategory":"Medical Equipment & Supplies",
            "type":"Manufacturing & Wholesale Goods"
        }
    ],
    "sg:phone":"+1 916 721 7518",
    "sg:postcode":"95621",
    "sg:province":"CA",
    "sg:tags":[
        "physician",
        "surgeon"
    ],
    "wof:name":"Taylor Marketing Svc",
    "wof:placetype":"venue"
},
  "geometry": {"coordinates":[-121.31529399999999,38.7041],"type":"Point"}
}