{
  "type": "Feature",
  "properties": {
    "iso:country":"US",
    "sg:address":"883 Joyner Ave",
    "sg:city":"Exeter",
    "sg:classifiers":[
        {
            "category":"Farming",
            "subcategory":"Orchard",
            "type":"Manufacturing & Wholesale Goods"
        }
    ],
    "sg:phone":"+1 559 592 9208",
    "sg:postcode":"93221",
    "sg:province":"CA",
    "sg:tags":[
        "citrus",
        "grove",
        "fruit"
    ],
    "wof:name":"Montgomery Farms",
    "wof:placetype":"venue"
},
  "geometry": {"coordinates":[-119.149545,36.287286],"type":"Point"}
}