{
  "type": "Feature",
  "properties": {
    "iso:country":"US",
    "sg:address":"190 Ave la Pata",
    "sg:city":"San Clemente",
    "sg:classifiers":[
        {
            "category":"Organizations",
            "subcategory":"Religious Organization",
            "type":"Services"
        }
    ],
    "sg:phone":"+1 949 361 1022",
    "sg:postcode":"92673",
    "sg:province":"CA",
    "sg:tags":[
        "church"
    ],
    "sg:website":"www.hcfsc.org",
    "wof:name":"Heritage Christian Fellowship",
    "wof:placetype":"venue"
},
  "geometry": {"coordinates":[-117.592575,33.451518],"type":"Point"}
}