{
  "type": "Feature",
  "properties": {
    "addr:full":"9961 Currant Ave Fountain Valley CA 92708",
    "addr:housenumber":"9961",
    "addr:postcode":"92708",
    "addr:street":"Currant Ave",
    "iso:country":"US",
    "sg:address":"9961 Currant Ave",
    "sg:city":"Fountain Valley",
    "sg:classifiers":[
        {
            "category":"Insurance",
            "subcategory":"Insurance Agent",
            "type":"Services"
        }
    ],
    "sg:phone":"+1 714 593 0747",
    "sg:postcode":"92708",
    "sg:province":"CA",
    "wof:name":"Crawford Risk Management Svc",
    "wof:placetype":"venue"
},
  "geometry": {"coordinates":[-117.956276,33.719486],"type":"Point"}
}