{
  "type": "Feature",
  "properties": {
    "iso:country":"US",
    "sg:address":"5465 Merchant Cir",
    "sg:city":"Placerville",
    "sg:classifiers":[
        {
            "category":"Building & Trades",
            "subcategory":"Construction",
            "type":"Services"
        }
    ],
    "sg:phone":"+1 530 621 1785",
    "sg:postcode":"95667",
    "sg:province":"CA",
    "sg:tags":[
        "contractor"
    ],
    "wof:name":"American River Construction",
    "wof:placetype":"venue"
},
  "geometry": {"coordinates":[-120.87814,38.676491],"type":"Point"}
}