{
  "type": "Feature",
  "properties": {
    "addr:full":"19 Dorland San Francisco CA 94110",
    "addr:housenumber":"19",
    "addr:postcode":"94110",
    "addr:street":"Dorland",
    "iso:country":"US",
    "sg:address":"19 Dorland",
    "sg:city":"San Francisco",
    "sg:classifiers":[
        {
            "category":"Professional",
            "subcategory":"Computer Services",
            "type":"Services"
        }
    ],
    "sg:postcode":"94110",
    "sg:province":"CA",
    "sg:tags":[
        "quizzes",
        "ugc",
        "widget"
    ],
    "sg:website":"http://mightyquiz.com",
    "wof:name":"MightyQuiz",
    "wof:placetype":"venue"
},
  "geometry": {"coordinates":[-122.4258,37.762164],"type":"Point"}
}