{
  "type": "Feature",
  "properties": {
    "addr:full":"18850 Rugged Trl Sonora CA 95370",
    "addr:housenumber":"18850",
    "addr:postcode":"95370",
    "addr:street":"Rugged Trl",
    "iso:country":"US",
    "sg:address":"18850 Rugged Trl",
    "sg:city":"Sonora",
    "sg:classifiers":[
        {
            "category":"Building & Trades",
            "subcategory":"Landscaping Services",
            "type":"Services"
        }
    ],
    "sg:phone":"+1 209 532 4418",
    "sg:postcode":"95370",
    "sg:province":"CA",
    "wof:name":"Anderson Landscaping",
    "wof:placetype":"venue"
},
  "geometry": {"coordinates":[-120.336057,37.96558],"type":"Point"}
}