{
  "type": "Feature",
  "properties": {
    "addr:full":"950 S Flower St Los Angeles CA 90015",
    "addr:housenumber":"950",
    "addr:postcode":"90015",
    "addr:street":"S Flower St",
    "iso:country":"US",
    "sg:address":"950 S Flower St",
    "sg:city":"Los Angeles",
    "sg:classifiers":[
        {
            "category":"Wholesale",
            "subcategory":"Durable Goods & Equipment",
            "type":"Manufacturing & Wholesale Goods"
        }
    ],
    "sg:phone":"+1 213 624 6400",
    "sg:postcode":"90015",
    "sg:province":"CA",
    "sg:tags":[
        "importer"
    ],
    "wof:name":"Global Oil Co",
    "wof:placetype":"venue"
},
  "geometry": {"coordinates":[-118.262152,34.045069],"type":"Point"}
}