{
  "type": "Feature",
  "properties": {
    "addr:full":"8111 Van Nuys Blvd Ste 101 Panorama City CA 91402",
    "addr:housenumber":"8111",
    "addr:postcode":"91402",
    "addr:street":"Van Nuys Blvd Ste 101",
    "iso:country":"US",
    "sg:address":"8111 Van Nuys Blvd Ste 101",
    "sg:city":"Panorama City",
    "sg:classifiers":[
        {
            "category":"Donuts",
            "subcategory":"None",
            "type":"Food & Drink"
        }
    ],
    "sg:phone":"+1 818 782 7892",
    "sg:postcode":"91402",
    "sg:province":"CA",
    "wof:name":"Jelly Donut the",
    "wof:placetype":"venue"
},
  "geometry": {"coordinates":[-118.44899700000001,34.218102],"type":"Point"}
}