{
  "type": "Feature",
  "properties": {
    "addr:full":"4977 Allison Pkwy Vacaville CA 95688",
    "addr:housenumber":"4977",
    "addr:postcode":"95688",
    "addr:street":"Allison Pkwy",
    "iso:country":"US",
    "sg:address":"4977 Allison Pkwy",
    "sg:city":"Vacaville",
    "sg:classifiers":[
        {
            "category":"Manufacturing",
            "subcategory":"Printing",
            "type":"Manufacturing & Wholesale Goods"
        }
    ],
    "sg:phone":"+1 707 469 9712",
    "sg:postcode":"95688",
    "sg:province":"CA",
    "sg:tags":[
        "printer"
    ],
    "sg:website":"www.browntrout.com",
    "wof:name":"Chess Press",
    "wof:placetype":"venue"
},
  "geometry": {"coordinates":[-121.96650699999999,38.390761],"type":"Point"}
}