{
  "type": "Feature",
  "properties": {
    "addr:full":"941 Estabrook St San Leandro CA 94577",
    "addr:housenumber":"941",
    "addr:postcode":"94577",
    "addr:street":"Estabrook St",
    "iso:country":"US",
    "sg:address":"941 Estabrook St",
    "sg:city":"San Leandro",
    "sg:classifiers":[
        {
            "category":"Wholesale",
            "subcategory":"Machinery & Supplies",
            "type":"Manufacturing & Wholesale Goods"
        }
    ],
    "sg:phone":"+1 510 667 0401",
    "sg:postcode":"94577",
    "sg:province":"CA",
    "sg:tags":[
        "salon",
        "beauty"
    ],
    "wof:name":"Kit Co",
    "wof:placetype":"venue"
},
  "geometry": {"coordinates":[-122.15922500000001,37.714552],"type":"Point"}
}