{
  "type": "Feature",
  "properties": {
    "addr:full":"18101 S Hobart Blvd Gardena CA 90248",
    "addr:housenumber":"18101",
    "addr:postcode":"90248",
    "addr:street":"S Hobart Blvd",
    "iso:country":"US",
    "sg:address":"18101 S Hobart Blvd",
    "sg:city":"Gardena",
    "sg:classifiers":[
        {
            "category":"Manufacturing",
            "subcategory":"Tools & Machinery",
            "type":"Manufacturing & Wholesale Goods"
        }
    ],
    "sg:phone":"+1 310 532 7805",
    "sg:postcode":"90248",
    "sg:province":"CA",
    "sg:tags":[
        "machine",
        "shop"
    ],
    "wof:name":"Jeray Precision Machine Inc",
    "wof:placetype":"venue"
},
  "geometry": {"coordinates":[-118.308117,33.866603],"type":"Point"}
}