{
  "type": "Feature",
  "properties": {
    "addr:full":"6401 Shattuck Ave Oakland CA 94609",
    "addr:housenumber":"6401",
    "addr:postcode":"94609",
    "addr:street":"Shattuck Ave",
    "iso:country":"US",
    "sg:address":"6401 Shattuck Ave",
    "sg:city":"Oakland",
    "sg:classifiers":[
        {
            "category":"Retail",
            "subcategory":"Laundry & Dry Cleaning",
            "type":"Services"
        }
    ],
    "sg:phone":"+1 510 922 1106",
    "sg:postcode":"94609",
    "sg:province":"CA",
    "sg:tags":[
        "operated",
        "washer",
        "dryer",
        "coin"
    ],
    "wof:name":"Lnd Room",
    "wof:placetype":"venue"
},
  "geometry": {"coordinates":[-122.265739,37.849499],"type":"Point"}
}