{
  "type": "Feature",
  "properties": {
    "iso:country":"US",
    "sg:address":"4658 Wortser Ave",
    "sg:city":"Sherman Oaks",
    "sg:classifiers":[
        {
            "category":"Travel",
            "subcategory":"Travel Agent",
            "type":"Entertainment"
        }
    ],
    "sg:phone":"+1 818 380 0856",
    "sg:postcode":"91423",
    "sg:province":"CA",
    "sg:tags":[
        "operator",
        "tour"
    ],
    "wof:name":"Caldwell Tours Inc",
    "wof:placetype":"venue"
},
  "geometry": {"coordinates":[-118.41699800000001,34.154726],"type":"Point"}
}