{
  "type": "Feature",
  "properties": {
    "iso:country":"US",
    "sg:address":"5016 California Ave",
    "sg:city":"Bakersfield",
    "sg:classifiers":[
        {
            "category":"Government",
            "subcategory":"Jail",
            "type":"Public Place"
        }
    ],
    "sg:phone":"+1 661 335 7337",
    "sg:postcode":"93309",
    "sg:province":"CA",
    "sg:tags":[
        "correctional",
        "institution"
    ],
    "wof:name":"Office Intrnal Adts-Cntral Reg",
    "wof:placetype":"venue"
},
  "geometry": {"coordinates":[-119.058605,35.362916],"type":"Point"}
}