{
  "type": "Feature",
  "properties": {
    "iso:country":"US",
    "sg:address":"26220 Industrial Blvd",
    "sg:city":"Hayward",
    "sg:classifiers":[
        {
            "category":"Health Services",
            "subcategory":"Health Practitioner",
            "type":"Services"
        }
    ],
    "sg:phone":"+1 510 782 9141",
    "sg:postcode":"94545",
    "sg:province":"CA",
    "sg:tags":[
        "nurse",
        "registry"
    ],
    "wof:name":"FAST",
    "wof:placetype":"venue"
},
  "geometry": {"coordinates":[-122.110356,37.632981],"type":"Point"}
}