{
  "type": "Feature",
  "properties": {
    "addr:full":"5190 Atlantic Ave Long Beach CA 90805",
    "addr:housenumber":"5190",
    "addr:postcode":"90805",
    "addr:street":"Atlantic Ave",
    "iso:country":"US",
    "sg:address":"5190 Atlantic Ave",
    "sg:city":"Long Beach",
    "sg:classifiers":[
        {
            "category":"Organizations",
            "subcategory":"Non-profit Organization",
            "type":"Services"
        }
    ],
    "sg:phone":"+1 562 428 4111",
    "sg:postcode":"90805",
    "sg:province":"CA",
    "sg:tags":[
        "info",
        "addiction",
        "abuse",
        "treatment",
        "drug"
    ],
    "sg:website":"www.tarzanatc.org",
    "wof:name":"Tarzana Treatment Ctr",
    "wof:placetype":"venue"
},
  "geometry": {"coordinates":[-118.18484599999999,33.848737],"type":"Point"}
}