{
  "type": "Feature",
  "properties": {
    "addr:full":"2013 Newport Blvd Costa Mesa CA 92627",
    "addr:housenumber":"2013",
    "addr:postcode":"92627",
    "addr:street":"Newport Blvd Costa",
    "iso:country":"US",
    "sg:address":"2013 Newport Blvd",
    "sg:city":"Costa Mesa",
    "sg:classifiers":[
        {
            "category":"Health Services",
            "subcategory":"Health Practitioner",
            "type":"Services"
        }
    ],
    "sg:phone":"+1 949 722 7444",
    "sg:postcode":"92627",
    "sg:province":"CA",
    "sg:tags":[
        "medicine",
        "alternative"
    ],
    "wof:name":"Alexander Wellness Ctr",
    "wof:placetype":"venue"
},
  "geometry": {"coordinates":[-117.909848,33.651167],"type":"Point"}
}