{
  "type": "Feature",
  "properties": {
    "addr:full":"2860 Broadway Oakland CA 94611",
    "addr:housenumber":"2860",
    "addr:postcode":"94611",
    "addr:street":"Broadway",
    "iso:country":"US",
    "sg:address":"2860 Broadway",
    "sg:city":"Oakland",
    "sg:classifiers":[
        {
            "category":"Retail",
            "subcategory":"Auto Repair",
            "type":"Services"
        }
    ],
    "sg:phone":"+1 510 268 1150",
    "sg:postcode":"94611",
    "sg:province":"CA",
    "sg:tags":[
        "automobile",
        "top",
        "upholstery"
    ],
    "wof:name":"Pacific Auto Trim",
    "wof:placetype":"venue"
},
  "geometry": {"coordinates":[-122.263369,37.816761],"type":"Point"}
}