{
  "type": "Feature",
  "properties": {
    "addr:full":"2929 Fulton Ave Ste 9 Sacramento CA 95821",
    "addr:housenumber":"2929",
    "addr:postcode":"95821",
    "addr:street":"Fulton Ave Ste 9",
    "iso:country":"US",
    "sg:address":"2929 Fulton Ave Ste 9",
    "sg:city":"Sacramento",
    "sg:classifiers":[
        {
            "category":"Communications",
            "subcategory":"Film & Video Production",
            "type":"Services"
        }
    ],
    "sg:phone":"+1 916 487 5923",
    "sg:postcode":"95821",
    "sg:province":"CA",
    "sg:tags":[
        "recording",
        "service-sound"
    ],
    "wof:name":"Right Choice Studio's Inc.",
    "wof:placetype":"venue"
},
  "geometry": {"coordinates":[-121.401466,38.618855],"type":"Point"}
}