{
  "type": "Feature",
  "properties": {
    "addr:full":"124 W Truslow Ave Apt 5 Fullerton CA 92832",
    "addr:housenumber":"124;5",
    "addr:postcode":"92832",
    "addr:street":"W Truslow Ave Apt",
    "iso:country":"US",
    "sg:address":"124 W Truslow Ave Apt 5",
    "sg:city":"Fullerton",
    "sg:classifiers":[
        {
            "category":"Personal",
            "type":"Services"
        }
    ],
    "sg:phone":"+1 714 873 7339",
    "sg:postcode":"92832",
    "sg:province":"CA",
    "sg:tags":[
        "towing"
    ],
    "wof:name":"Chopper Tow",
    "wof:placetype":"venue"
},
  "geometry": {"coordinates":[-117.924798,33.867258],"type":"Point"}
}