{
  "type": "Feature",
  "properties": {
    "iso:country":"US",
    "sg:address":"5959 Greenback Ln",
    "sg:city":"Citrus Heights",
    "sg:classifiers":[
        {
            "category":"Health Services",
            "subcategory":"Dentist",
            "type":"Services"
        }
    ],
    "sg:phone":"+1 916 723 4777",
    "sg:postcode":"95621",
    "sg:province":"CA",
    "wof:name":"Bal Harsimrat K Dds",
    "wof:placetype":"venue"
},
  "geometry": {"coordinates":[-121.325687,38.681314],"type":"Point"}
}