{
  "type": "Feature",
  "properties": {
    "addr:full":"2808 Park Ave Merced CA 95348",
    "addr:housenumber":"2808",
    "addr:postcode":"95348",
    "addr:street":"Park Ave",
    "iso:country":"US",
    "sg:address":"2808 Park Ave",
    "sg:city":"Merced",
    "sg:classifiers":[
        {
            "category":"Professional",
            "subcategory":"Engineering",
            "type":"Services"
        }
    ],
    "sg:phone":"+1 209 725 0313",
    "sg:postcode":"95348",
    "sg:province":"CA",
    "sg:tags":[
        "engineer"
    ],
    "wof:name":"MWH America's Inc",
    "wof:placetype":"venue"
},
  "geometry": {"coordinates":[-120.472173,37.312934],"type":"Point"}
}