{
  "type": "Feature",
  "properties": {
    "addr:full":"12019 Shale Ridge Rd Auburn CA 95602",
    "addr:housenumber":"12019",
    "addr:postcode":"ca 95602",
    "addr:street":"Shale Ridge Rd",
    "iso:country":"US",
    "sg:address":"12019 Shale Ridge Rd",
    "sg:city":"Auburn",
    "sg:classifiers":[
        {
            "category":"Shopping",
            "subcategory":"Clothing, Apparel, & Fashions",
            "type":"Retail Goods"
        }
    ],
    "sg:phone":"+1 530 823 5594",
    "sg:postcode":"95602",
    "sg:province":"CA",
    "sg:tags":[
        "western"
    ],
    "wof:name":"Sierra Saddlery & Mercantile",
    "wof:placetype":"venue"
},
  "geometry": {"coordinates":[-121.097122,38.953116],"type":"Point"}
}