{
  "type": "Feature",
  "properties": {
    "iso:country":"US",
    "sg:address":"1035 W Robinhood Dr",
    "sg:city":"Stockton",
    "sg:classifiers":[
        {
            "category":"Wholesale",
            "subcategory":"Office Equipment",
            "type":"Manufacturing & Wholesale Goods"
        }
    ],
    "sg:phone":"+1 209 948 2991",
    "sg:postcode":"95207",
    "sg:province":"CA",
    "sg:tags":[
        "repair",
        "electrical"
    ],
    "wof:name":"Dictaphone Corporation",
    "wof:placetype":"venue"
},
  "geometry": {"coordinates":[-121.31842,38.000117],"type":"Point"}
}