{
  "type": "Feature",
  "properties": {
    "addr:full":"401 Mission Ave Oceanside CA 92054",
    "addr:housenumber":"401",
    "addr:postcode":"92054",
    "addr:street":"Mission Ave",
    "iso:country":"US",
    "sg:address":"401 Mission Ave",
    "sg:city":"Oceanside",
    "sg:classifiers":[
        {
            "category":"Restaurant",
            "type":"Food & Drink"
        }
    ],
    "sg:phone":"+1 760 439 3566",
    "sg:postcode":"92054",
    "sg:province":"CA",
    "sg:tags":[
        "grill",
        "bar",
        "sushi",
        "japanese",
        "asian",
        "pan"
    ],
    "sg:website":"www.umijapanesegrill.com",
    "wof:name":"Umi Japanese Grill & Cafe",
    "wof:placetype":"venue"
},
  "geometry": {"coordinates":[-117.37981600000001,33.195092],"type":"Point"}
}