{
  "type": "Feature",
  "properties": {
    "iso:country":"US",
    "sg:address":"285 Bel Marin Keys Blvd K",
    "sg:city":"Novato",
    "sg:classifiers":[
        {
            "category":"Food & Beverages",
            "subcategory":"Liquor & Beverages",
            "type":"Retail Goods"
        },
        {
            "category":"Wholesale",
            "subcategory":"Wine & Distilled Alcoholic Beverages",
            "type":"Manufacturing & Wholesale Goods"
        }
    ],
    "sg:phone":"+1 415 884 9000",
    "sg:postcode":"94949",
    "sg:province":"CA",
    "sg:tags":[
        "broker"
    ],
    "sg:website":"http://www.cabernetcorp.com",
    "wof:name":"La Playa",
    "wof:placetype":"venue"
},
  "geometry": {"coordinates":[-122.536007,38.07103],"type":"Point"}
}