{
  "type": "Feature",
  "properties": {
    "iso:country":"US",
    "sg:address":"468 Whisman Ct",
    "sg:city":"Mountain View",
    "sg:classifiers":[
        {
            "category":"Professional",
            "subcategory":"Computer Services",
            "type":"Services"
        }
    ],
    "sg:phone":"+1 650 960 0190",
    "sg:postcode":"94043",
    "sg:province":"CA",
    "sg:tags":[
        "consultant",
        "designer"
    ],
    "wof:name":"Source Quest Inc",
    "wof:placetype":"venue"
},
  "geometry": {"coordinates":[-122.059163,37.400249],"type":"Point"}
}