{
  "type": "Feature",
  "properties": {
    "addr:full":"13662 Dawson St Garden Grove CA 92843",
    "addr:housenumber":"13662",
    "addr:postcode":"92843",
    "addr:street":"Dawson St",
    "iso:country":"US",
    "sg:address":"13662 Dawson St",
    "sg:city":"Garden Grove",
    "sg:classifiers":[
        {
            "category":"Personal",
            "type":"Services"
        }
    ],
    "sg:phone":"+1 714 740 1232",
    "sg:postcode":"92843",
    "sg:province":"CA",
    "sg:tags":[
        "mover"
    ],
    "wof:name":"Chau Moving Inc",
    "wof:placetype":"venue"
},
  "geometry": {"coordinates":[-117.952268,33.764259],"type":"Point"}
}