{
  "type": "Feature",
  "properties": {
    "addr:full":"13180 Casa Linda Ln Garden Grove CA 92844",
    "addr:housenumber":"13180",
    "addr:postcode":"92844",
    "addr:street":"Casa Linda Ln",
    "iso:country":"US",
    "sg:address":"13180 Casa Linda Ln",
    "sg:city":"Garden Grove",
    "sg:classifiers":[
        {
            "category":"Building & Trades",
            "subcategory":"Electrical",
            "type":"Services"
        }
    ],
    "sg:phone":"+1 714 636 6658",
    "sg:postcode":"92844",
    "sg:province":"CA",
    "sg:tags":[
        "electrical",
        "contractor"
    ],
    "wof:name":"Rapid Electric Service",
    "wof:placetype":"venue"
},
  "geometry": {"coordinates":[-117.969126,33.772711],"type":"Point"}
}