{
  "type": "Feature",
  "properties": {
    "addr:full":"2800 S Main St Soquel CA 95073",
    "addr:housenumber":"2800",
    "addr:postcode":"95073",
    "addr:street":"S Main St",
    "iso:country":"US",
    "sg:address":"2800 S Main St",
    "sg:city":"Soquel",
    "sg:classifiers":[
        {
            "category":"Building & Trades",
            "subcategory":"Construction",
            "type":"Services"
        }
    ],
    "sg:phone":"+1 831 458 3424",
    "sg:postcode":"95073",
    "sg:province":"CA",
    "sg:tags":[
        "water",
        "well",
        "drilling"
    ],
    "wof:name":"Pickens Water Well Drilling",
    "wof:placetype":"venue"
},
  "geometry": {"coordinates":[-121.954716,36.987677],"type":"Point"}
}