{
  "type": "Feature",
  "properties": {
    "iso:country":"US",
    "sg:address":"405 El Alamein Rd",
    "sg:city":"Felton",
    "sg:classifiers":[
        {
            "category":"Food & Beverages",
            "subcategory":"Farmers Market",
            "type":"Retail Goods"
        }
    ],
    "sg:phone":"+1 831 335 9019",
    "sg:postcode":"95018",
    "sg:province":"CA",
    "sg:tags":[
        "vegetable",
        "fruit",
        "shipper",
        "grower"
    ],
    "wof:name":"Andersen Vineyards",
    "wof:placetype":"venue"
},
  "geometry": {"coordinates":[-122.059348,37.065835],"type":"Point"}
}