{
  "type": "Feature",
  "properties": {
    "iso:country":"US",
    "sg:address":"1333 Howe Ave Ste 101",
    "sg:city":"Sacramento",
    "sg:classifiers":[
        {
            "category":"Real Estate",
            "subcategory":"Real Estate Services",
            "type":"Services"
        }
    ],
    "sg:phone":"+1 916 923 6405",
    "sg:postcode":"95825",
    "sg:province":"CA",
    "sg:tags":[
        "management",
        "property"
    ],
    "wof:name":"Atlas Investment Group",
    "wof:placetype":"venue"
},
  "geometry": {"coordinates":[-121.415611,38.589746],"type":"Point"}
}