{
  "type": "Feature",
  "properties": {
    "iso:country":"US",
    "sg:address":"2406 W Avenue 30",
    "sg:city":"Los Angeles",
    "sg:classifiers":[
        {
            "category":"Restaurant",
            "type":"Food & Drink"
        }
    ],
    "sg:phone":"+1 562 809 0092",
    "sg:postcode":"90065",
    "sg:province":"CA",
    "sg:tags":[
        "chinese"
    ],
    "wof:name":"Modern China",
    "wof:placetype":"venue"
},
  "geometry": {"coordinates":[-118.238998,34.1068],"type":"Point"}
}