{
  "type": "Feature",
  "properties": {
    "iso:country":"US",
    "sg:address":"44085 Royal Troon Dr",
    "sg:city":"Indio",
    "sg:classifiers":[
        {
            "category":"Insurance",
            "subcategory":"Insurance Agent",
            "type":"Services"
        }
    ],
    "sg:phone":"+1 760 345 3755",
    "sg:postcode":"92201",
    "sg:province":"CA",
    "wof:name":"Engen Insurance Svc",
    "wof:placetype":"venue"
},
  "geometry": {"coordinates":[-116.268214,33.725667],"type":"Point"}
}