{
  "type": "Feature",
  "properties": {
    "addr:full":"1045 Harriman Pl San Bernardino CA 92408",
    "addr:housenumber":"1045",
    "addr:postcode":"92408",
    "addr:street":"Harriman Pl",
    "iso:country":"US",
    "sg:address":"1045 Harriman Pl",
    "sg:city":"San Bernardino",
    "sg:classifiers":[
        {
            "category":"Restaurant",
            "type":"Food & Drink"
        }
    ],
    "sg:menulink":"http://www.allmenus.com/ca/san-bernardino/38871-bjs-restaurant--brewhouse/menu/",
    "sg:phone":"+1 909 380 7100",
    "sg:postcode":"92408",
    "sg:province":"CA",
    "sg:tags":[
        "new",
        "american"
    ],
    "wof:name":"BJ's Restaurant & Brewhouse",
    "wof:placetype":"venue"
},
  "geometry": {"coordinates":[-117.26606,34.065726],"type":"Point"}
}