{
  "type": "Feature",
  "properties": {
    "addr:full":"925 Blossom Hill Road San Jose CA 95123",
    "addr:housenumber":"925",
    "addr:postcode":"95123",
    "addr:street":"Blossom Hill Road",
    "iso:country":"US",
    "sg:address":"925 Blossom Hill Road",
    "sg:city":"San Jose",
    "sg:classifiers":[
        {
            "category":"Shopping",
            "subcategory":"Clothing, Apparel, & Fashions",
            "type":"Retail Goods"
        }
    ],
    "sg:phone":"+1 408 225 9075",
    "sg:postcode":"95123",
    "sg:province":"CA",
    "sg:tags":[
        "accessory",
        "clothing",
        "women's"
    ],
    "sg:website":"lanebryant.charmingshoppes.com",
    "wof:name":"Lane Bryant",
    "wof:placetype":"venue"
},
  "geometry": {"coordinates":[-121.833088,37.245625],"type":"Point"}
}