{
  "type": "Feature",
  "properties": {
    "addr:full":"5000 Windplay Dr El Dorado Hills CA 95762",
    "addr:housenumber":"5000",
    "addr:postcode":"95762",
    "addr:street":"Windplay Dr",
    "iso:country":"US",
    "sg:address":"5000 Windplay Dr",
    "sg:city":"El Dorado Hills",
    "sg:classifiers":[
        {
            "category":"Professional",
            "type":"Services"
        }
    ],
    "sg:phone":"+1 916 933 7459",
    "sg:postcode":"95762",
    "sg:province":"CA",
    "sg:tags":[
        "establishment"
    ],
    "wof:name":"Autopro",
    "wof:placetype":"venue"
},
  "geometry": {"coordinates":[-121.071074,38.636985],"type":"Point"}
}