{
  "type": "Feature",
  "properties": {
    "addr:full":"801 N Bush St Santa Ana CA 92701",
    "addr:housenumber":"801",
    "addr:postcode":"92701",
    "addr:street":"N Bush St",
    "iso:country":"US",
    "sg:address":"801 N Bush St",
    "sg:city":"Santa Ana",
    "sg:classifiers":[
        {
            "category":"Real Estate",
            "subcategory":"Real Estate Agent",
            "type":"Services"
        }
    ],
    "sg:phone":"+1 714 542 3600",
    "sg:postcode":"92701",
    "sg:province":"CA",
    "wof:name":"Re/Max",
    "wof:placetype":"venue"
},
  "geometry": {"coordinates":[-117.86658,33.7523],"type":"Point"}
}