{
  "type": "Feature",
  "properties": {
    "iso:country":"US",
    "sg:address":"140 W Broadway",
    "sg:city":"San Diego",
    "sg:classifiers":[
        {
            "category":"Restaurant",
            "type":"Food & Drink"
        }
    ],
    "sg:phone":"+1 619 702 6309",
    "sg:postcode":"92101",
    "sg:province":"CA",
    "sg:tags":[
        "new",
        "american",
        "french"
    ],
    "sg:website":"www.currantrestaurant.com",
    "wof:name":"Currant",
    "wof:placetype":"venue"
},
  "geometry": {"coordinates":[-117.164281,32.715824],"type":"Point"}
}