{
  "type": "Feature",
  "properties": {
    "addr:full":"1335 S Main St Walnut Creek CA 94595",
    "addr:housenumber":"1335",
    "addr:postcode":"94595",
    "addr:street":"S Main St",
    "iso:country":"US",
    "sg:address":"1335 S Main St",
    "sg:city":"Walnut Creek",
    "sg:classifiers":[
        {
            "category":"Autos & Motor Vehicles",
            "subcategory":"Motorcycle Sales",
            "type":"Retail Goods"
        }
    ],
    "sg:phone":"+1 925 256 8840",
    "sg:postcode":"94595",
    "sg:province":"CA",
    "sg:tags":[
        "scooter"
    ],
    "wof:name":"Motopsycho",
    "wof:placetype":"venue"
},
  "geometry": {"coordinates":[-122.058772,37.894212],"type":"Point"}
}