{
  "type": "Feature",
  "properties": {
    "iso:country":"US",
    "sg:address":"659 Twin Peaks Ave",
    "sg:city":"Simi Valley",
    "sg:classifiers":[
        {
            "category":"Building & Trades",
            "subcategory":"Construction",
            "type":"Services"
        }
    ],
    "sg:phone":"+1 805 526 1123",
    "sg:postcode":"93065",
    "sg:province":"CA",
    "sg:tags":[
        "contractor"
    ],
    "wof:name":"M V Tile",
    "wof:placetype":"venue"
},
  "geometry": {"coordinates":[-118.812536,34.239505],"type":"Point"}
}