{
  "type": "Feature",
  "properties": {
    "iso:country":"US",
    "sg:address":"69 Dorman Ave",
    "sg:city":"San Francisco",
    "sg:classifiers":[
        {
            "category":"Manufacturing",
            "subcategory":"Printing",
            "type":"Manufacturing & Wholesale Goods"
        }
    ],
    "sg:phone":"+1 415 647 1122",
    "sg:postcode":"94124",
    "sg:province":"CA",
    "sg:tags":[
        "printer"
    ],
    "wof:name":"Fox Graphics",
    "wof:placetype":"venue"
},
  "geometry": {"coordinates":[-122.402681,37.739776],"type":"Point"}
}