{
  "type": "Feature",
  "properties": {
    "addr:full":"341 N Montgomery St San Jose CA 95110",
    "addr:housenumber":"341",
    "addr:postcode":"95110",
    "addr:street":"N Montgomery St",
    "iso:country":"US",
    "sg:address":"341 N Montgomery St",
    "sg:city":"San Jose",
    "sg:classifiers":[
        {
            "category":"Retail",
            "subcategory":"Auto Repair",
            "type":"Services"
        }
    ],
    "sg:phone":"+1 408 291 0676",
    "sg:postcode":"95110",
    "sg:province":"CA",
    "sg:tags":[
        "truck"
    ],
    "sg:website":"www.fleetbodyworx.com",
    "wof:name":"Fleet Bodyworx",
    "wof:placetype":"venue"
},
  "geometry": {"coordinates":[-121.904523,37.336251],"type":"Point"}
}