{
  "type": "Feature",
  "properties": {
    "iso:country":"US",
    "sg:address":"201 N Uruapan Way",
    "sg:city":"Dinuba",
    "sg:classifiers":[
        {
            "category":"Wholesale",
            "subcategory":"Durable Goods & Equipment",
            "type":"Manufacturing & Wholesale Goods"
        }
    ],
    "sg:phone":"+1 559 595 8100",
    "sg:postcode":"93618",
    "sg:province":"CA",
    "sg:tags":[
        "professional"
    ],
    "wof:name":"Barker Bob Co Inc",
    "wof:placetype":"venue"
},
  "geometry": {"coordinates":[-119.394569,36.541222],"type":"Point"}
}