{
  "type": "Feature",
  "properties": {
    "iso:country":"US",
    "sg:address":"1139 Main Ave",
    "sg:city":"Sacramento",
    "sg:classifiers":[
        {
            "category":"Shopping",
            "subcategory":"Clothing, Apparel, & Fashions",
            "type":"Retail Goods"
        }
    ],
    "sg:phone":"+1 916 929 4885",
    "sg:postcode":"95838",
    "sg:province":"CA",
    "sg:tags":[
        "apparel",
        "women's"
    ],
    "wof:name":"Kays Fashions",
    "wof:placetype":"venue"
},
  "geometry": {"coordinates":[-121.43920300000001,38.654707],"type":"Point"}
}