{
  "type": "Feature",
  "properties": {
    "addr:full":"212 E Matilija St Ojai CA 93023",
    "addr:housenumber":"212",
    "addr:postcode":"93023",
    "addr:street":"E Matilija St",
    "iso:country":"US",
    "sg:address":"212 E Matilija St",
    "sg:city":"Ojai",
    "sg:classifiers":[
        {
            "category":"Personal",
            "subcategory":"Beauty Salon",
            "type":"Services"
        },
        {
            "category":"Personal",
            "subcategory":"Day Spa",
            "type":"Services"
        }
    ],
    "sg:phone":"+1 805 640 6536",
    "sg:postcode":"93023",
    "sg:province":"CA",
    "wof:name":"The Angelic Touch Day Spa/Ojai Healing Arts Center",
    "wof:placetype":"venue"
},
  "geometry": {"coordinates":[-119.24589400000001,34.448756],"type":"Point"}
}