{
  "type": "Feature",
  "properties": {
    "addr:full":"2707 McCone Ave Hayward CA 94545",
    "addr:housenumber":"2707",
    "addr:postcode":"94545",
    "addr:street":"Mccone Ave",
    "iso:country":"US",
    "sg:address":"2707 McCone Ave",
    "sg:city":"Hayward",
    "sg:classifiers":[
        {
            "category":"Manufacturing",
            "subcategory":"Leather Goods",
            "type":"Manufacturing & Wholesale Goods"
        }
    ],
    "sg:phone":"+1 510 576 1100",
    "sg:postcode":"94545",
    "sg:province":"CA",
    "sg:tags":[
        "shoes"
    ],
    "sg:website":"www.nytami.com",
    "wof:name":"New York Transit",
    "wof:placetype":"venue"
},
  "geometry": {"coordinates":[-122.13093499999999,37.644585],"type":"Point"}
}