{
  "type": "Feature",
  "properties": {
    "addr:full":"2512 D St Hayward CA 94541",
    "addr:housenumber":"2512",
    "addr:postcode":"94541",
    "addr:street":"D St",
    "iso:country":"US",
    "sg:address":"2512 D St",
    "sg:city":"Hayward",
    "sg:classifiers":[
        {
            "category":"Professional",
            "subcategory":"Computer Services",
            "type":"Services"
        }
    ],
    "sg:phone":"+1 510 581 2666",
    "sg:postcode":"94541",
    "sg:province":"CA",
    "sg:tags":[
        "information",
        "technology"
    ],
    "wof:name":"Genesis Resources Inc",
    "wof:placetype":"venue"
},
  "geometry": {"coordinates":[-122.055854,37.679733],"type":"Point"}
}