{
  "type": "Feature",
  "properties": {
    "iso:country":"US",
    "sg:address":"6543 Regional St",
    "sg:city":"Dublin",
    "sg:classifiers":[
        {
            "category":"Professional",
            "type":"Services"
        },
        {
            "category":"Manufacturing",
            "subcategory":"Electronics",
            "type":"Manufacturing & Wholesale Goods"
        }
    ],
    "sg:phone":"+1 925 875 9406",
    "sg:postcode":"94568",
    "sg:province":"CA",
    "sg:tags":[
        "semiconductor",
        "related",
        "devices"
    ],
    "wof:name":"Verticle",
    "wof:placetype":"venue"
},
  "geometry": {"coordinates":[-121.933489,37.702618],"type":"Point"}
}