{
  "type": "Feature",
  "properties": {
    "addr:full":"807 Seacoast Dr Imperial Beach CA 91932",
    "addr:housenumber":"807",
    "addr:postcode":"91932",
    "addr:street":"Seacoast Dr",
    "iso:country":"US",
    "sg:address":"807 Seacoast Dr",
    "sg:city":"Imperial Beach",
    "sg:classifiers":[
        {
            "category":"Restaurant",
            "type":"Food & Drink"
        }
    ],
    "sg:phone":"+1 619 423 4444",
    "sg:postcode":"91932",
    "sg:province":"CA",
    "wof:name":"Seacoast Giant Pizza",
    "wof:placetype":"venue"
},
  "geometry": {"coordinates":[-117.13163299999999,32.581476],"type":"Point"}
}