{
  "type": "Feature",
  "properties": {
    "iso:country":"US",
    "sg:address":"5893 Arboretum Dr",
    "sg:city":"Los Altos",
    "sg:classifiers":[
        {
            "category":"Professional",
            "subcategory":"Engineering",
            "type":"Services"
        }
    ],
    "sg:phone":"+1 650 965 9392",
    "sg:postcode":"94024",
    "sg:province":"CA",
    "sg:tags":[
        "engineer"
    ],
    "wof:name":"Kenneth L Meleen Civil Enginee",
    "wof:placetype":"venue"
},
  "geometry": {"coordinates":[-122.076233,37.334063],"type":"Point"}
}