{
  "type": "Feature",
  "properties": {
    "iso:country":"US",
    "sg:address":"101 Walter Way",
    "sg:city":"Antioch",
    "sg:classifiers":[
        {
            "category":"Bars & Pubs",
            "type":"Food & Drink"
        }
    ],
    "sg:phone":"+1 925 757 5455",
    "sg:postcode":"94509",
    "sg:province":"CA",
    "sg:tags":[
        "lounge",
        "drinking",
        "cocktail"
    ],
    "wof:name":"A B C Rendezvous",
    "wof:placetype":"venue"
},
  "geometry": {"coordinates":[-121.80680700000001,38.002994],"type":"Point"}
}