{
  "type": "Feature",
  "properties": {
    "iso:country":"US",
    "sg:address":"19562 Yuma St",
    "sg:city":"Castro Valley",
    "sg:classifiers":[
        {
            "category":"Professional",
            "type":"Services"
        }
    ],
    "sg:phone":"+1 510 537 0884",
    "sg:postcode":"94546",
    "sg:province":"CA",
    "sg:tags":[
        "writer"
    ],
    "wof:name":"Carson Hibbard Enterprises",
    "wof:placetype":"venue"
},
  "geometry": {"coordinates":[-122.096502,37.700854],"type":"Point"}
}