{
  "type": "Feature",
  "properties": {
    "addr:full":"412 Laurkris Ct Ridgecrest CA 93555",
    "addr:housenumber":"412",
    "addr:postcode":"93555",
    "addr:street":"Laurkris Ct",
    "iso:country":"US",
    "sg:address":"412 Laurkris Ct",
    "sg:city":"Ridgecrest",
    "sg:classifiers":[
        {
            "category":"Banks & Credit Unions",
            "subcategory":"Investment Brokerage",
            "type":"Services"
        }
    ],
    "sg:phone":"+1 760 375 6271",
    "sg:postcode":"93555",
    "sg:province":"CA",
    "wof:name":"Silver Ridge Investments",
    "wof:placetype":"venue"
},
  "geometry": {"coordinates":[-117.677097,35.636214],"type":"Point"}
}