{
  "type": "Feature",
  "properties": {
    "iso:country":"US",
    "sg:address":"5900 Wilshire Blvd",
    "sg:city":"Los Angeles",
    "sg:classifiers":[
        {
            "category":"Professional",
            "subcategory":"Lawyer & Legal Services",
            "type":"Services"
        }
    ],
    "sg:phone":"+1 323 260 7220",
    "sg:postcode":"90036",
    "sg:province":"CA",
    "sg:tags":[
        "attorney"
    ],
    "wof:name":"Takakjian Sowers & Sitkoff",
    "wof:placetype":"venue"
},
  "geometry": {"coordinates":[-118.359355,34.062684],"type":"Point"}
}