{
  "type": "Feature",
  "properties": {
    "iso:country":"US",
    "sg:address":"520 E Fresno St",
    "sg:city":"Avenal",
    "sg:classifiers":[
        {
            "category":"Government",
            "subcategory":"Office",
            "type":"Public Place"
        }
    ],
    "sg:phone":"+1 559 386 1242",
    "sg:postcode":"93204",
    "sg:province":"CA",
    "sg:tags":[
        "county",
        "resource"
    ],
    "wof:name":"Kings County Human Svc",
    "wof:placetype":"venue"
},
  "geometry": {"coordinates":[-120.129679,36.003493],"type":"Point"}
}