{
  "type": "Feature",
  "properties": {
    "iso:country":"US",
    "sg:address":"4477 Hollywood Blvd",
    "sg:city":"Los Angeles",
    "sg:classifiers":[
        {
            "category":"Health Services",
            "subcategory":"Medical Lab",
            "type":"Services"
        }
    ],
    "sg:phone":"+1 323 669 8670",
    "sg:postcode":"90027",
    "sg:province":"CA",
    "sg:tags":[
        "laboratory"
    ],
    "wof:name":"Hollywood Diagnostic Ctr",
    "wof:placetype":"venue"
},
  "geometry": {"coordinates":[-118.288305,34.098963],"type":"Point"}
}