{
  "type": "Feature",
  "properties": {
    "iso:country":"US",
    "sg:address":"1806 Novato Blvd",
    "sg:city":"Novato",
    "sg:classifiers":[
        {
            "category":"Organizations",
            "subcategory":"Religious Organization",
            "type":"Services"
        }
    ],
    "sg:phone":"+1 415 897 2171",
    "sg:postcode":"94947",
    "sg:province":"CA",
    "sg:tags":[
        "church"
    ],
    "wof:name":"Our Lady Of Loretto Church",
    "wof:placetype":"venue"
},
  "geometry": {"coordinates":[-122.585227,38.109095],"type":"Point"}
}