{
  "type": "Feature",
  "properties": {
    "addr:full":"11725 del Paso Ct Auburn CA 95602",
    "addr:housenumber":"11725",
    "addr:postcode":"ca 95602",
    "addr:street":"Del Paso Ct",
    "iso:country":"US",
    "sg:address":"11725 del Paso Ct",
    "sg:city":"Auburn",
    "sg:classifiers":[
        {
            "category":"Manufacturing",
            "subcategory":"Tools & Machinery",
            "type":"Manufacturing & Wholesale Goods"
        }
    ],
    "sg:phone":"+1 530 888 0690",
    "sg:postcode":"95602",
    "sg:province":"CA",
    "sg:tags":[
        "equipment",
        "household",
        "cooking",
        "mfg"
    ],
    "wof:name":"Roper Corporation",
    "wof:placetype":"venue"
},
  "geometry": {"coordinates":[-121.106696,38.957155],"type":"Point"}
}