{
  "type": "Feature",
  "properties": {
    "iso:country":"US",
    "sg:address":"599 Valencia St",
    "sg:city":"San Francisco",
    "sg:classifiers":[
        {
            "category":"Freight",
            "type":"Transportation"
        }
    ],
    "sg:phone":"+1 415 861 7300",
    "sg:postcode":"94110",
    "sg:province":"CA",
    "sg:tags":[
        "used",
        "storage",
        "trucking",
        "anti",
        "local",
        "furniture"
    ],
    "wof:name":"Harrington Bros Moving & Stor",
    "wof:placetype":"venue"
},
  "geometry": {"coordinates":[-122.421886,37.764917],"type":"Point"}
}