{
  "type": "Feature",
  "properties": {
    "iso:country":"US",
    "sg:address":"2288 Fulton St",
    "sg:city":"Berkeley",
    "sg:classifiers":[
        {
            "category":"Professional",
            "subcategory":"Management & Consulting",
            "type":"Services"
        }
    ],
    "sg:phone":"+1 510 647 1150",
    "sg:postcode":"94704",
    "sg:province":"CA",
    "sg:tags":[
        "consultant",
        "business"
    ],
    "sg:website":"www.corporatescenes.com",
    "wof:name":"Corporate Scenes Inc",
    "wof:placetype":"venue"
},
  "geometry": {"coordinates":[-122.266305,37.868572],"type":"Point"}
}