{
  "type": "Feature",
  "properties": {
    "addr:full":"3435 Wilshire Blvd Ste 1103 Los Angeles CA 90010",
    "addr:housenumber":"3435",
    "addr:postcode":"90010",
    "addr:street":"Wilshire Blvd Ste 1103",
    "iso:country":"US",
    "sg:address":"3435 Wilshire Blvd Ste 1103",
    "sg:city":"Los Angeles",
    "sg:classifiers":[
        {
            "category":"Banks & Credit Unions",
            "subcategory":"Investment Brokerage",
            "type":"Services"
        }
    ],
    "sg:phone":"+1 213 487 2955",
    "sg:postcode":"90010",
    "sg:province":"CA",
    "sg:tags":[
        "investing"
    ],
    "sg:website":"www.jkfutures.us",
    "wof:name":"Muhan Forex",
    "wof:placetype":"venue"
},
  "geometry": {"coordinates":[-118.29857,34.062474],"type":"Point"}
}