{
  "type": "Feature",
  "properties": {
    "addr:full":"301 N Lake Ave Pasadena CA 91101",
    "addr:housenumber":"301",
    "addr:postcode":"91101",
    "addr:street":"N Lake Ave",
    "iso:country":"US",
    "sg:address":"301 N Lake Ave",
    "sg:city":"Pasadena",
    "sg:classifiers":[
        {
            "category":"Professional",
            "subcategory":"Lawyer & Legal Services",
            "type":"Services"
        }
    ],
    "sg:phone":"+1 626 795 4231",
    "sg:postcode":"91101",
    "sg:province":"CA",
    "sg:tags":[
        "attorney"
    ],
    "wof:name":"Gary Jeffries Law Office",
    "wof:placetype":"venue"
},
  "geometry": {"coordinates":[-118.132481,34.150925],"type":"Point"}
}