{
  "type": "Feature",
  "properties": {
    "addr:full":"22962 Cavanaugh Rd Lake Forest CA 92630",
    "addr:housenumber":"22962",
    "addr:postcode":"92630",
    "addr:street":"Cavanaugh Rd",
    "iso:country":"US",
    "sg:address":"22962 Cavanaugh Rd",
    "sg:city":"Lake Forest",
    "sg:classifiers":[
        {
            "category":"Wholesale",
            "subcategory":"Medical Equipment & Supplies",
            "type":"Manufacturing & Wholesale Goods"
        }
    ],
    "sg:phone":"+1 949 457 8280",
    "sg:postcode":"92630",
    "sg:province":"CA",
    "wof:name":"Best Medical Enterprise",
    "wof:placetype":"venue"
},
  "geometry": {"coordinates":[-117.698041,33.628362],"type":"Point"}
}