{
  "type": "Feature",
  "properties": {
    "addr:full":"4267 Crenshaw Blvd Los Angeles CA 90008",
    "addr:housenumber":"4267",
    "addr:postcode":"90008",
    "addr:street":"Crenshaw Blvd",
    "iso:country":"US",
    "sg:address":"4267 Crenshaw Blvd",
    "sg:city":"Los Angeles",
    "sg:classifiers":[
        {
            "category":"Personal",
            "subcategory":"Barber",
            "type":"Services"
        }
    ],
    "sg:phone":"+1 323 299 0223",
    "sg:postcode":"90008",
    "sg:province":"CA",
    "wof:name":"Magnificent Brother No 1 Barber Salon",
    "wof:placetype":"venue"
},
  "geometry": {"coordinates":[-118.334,34.006302],"type":"Point"}
}