{
  "type": "Feature",
  "properties": {
    "addr:full":"18119 Ave 296 Exeter CA 93221",
    "addr:housenumber":"18119;296",
    "addr:postcode":"93221",
    "addr:street":"Ave",
    "iso:country":"US",
    "sg:address":"18119 Ave 296",
    "sg:city":"Exeter",
    "sg:classifiers":[
        {
            "category":"Real Estate",
            "subcategory":"Real Estate Operator",
            "type":"Services"
        }
    ],
    "sg:phone":"+1 559 592 6751",
    "sg:postcode":"93221",
    "sg:province":"CA",
    "sg:tags":[
        "boarding",
        "house"
    ],
    "wof:name":"Charisma Room & Board",
    "wof:placetype":"venue"
},
  "geometry": {"coordinates":[-119.167874,36.326362],"type":"Point"}
}