{
  "type": "Feature",
  "properties": {
    "addr:full":"3937 Rivermark Plz Santa Clara CA 95054",
    "addr:housenumber":"3937",
    "addr:postcode":"95054",
    "addr:street":"Rivermark Plz",
    "iso:country":"US",
    "sg:address":"3937 Rivermark Plz",
    "sg:city":"Santa Clara",
    "sg:classifiers":[
        {
            "category":"Fast Food",
            "type":"Food & Drink"
        }
    ],
    "sg:phone":"+1 408 654 9128",
    "sg:postcode":"95054",
    "sg:province":"CA",
    "sg:website":"www.quiznos.com",
    "wof:name":"Quiznos",
    "wof:placetype":"venue"
},
  "geometry": {"coordinates":[-121.945943,37.3948],"type":"Point"}
}