{
  "type": "Feature",
  "properties": {
    "iso:country":"US",
    "sg:address":"509 Winmoore Way",
    "sg:city":"Modesto",
    "sg:classifiers":[
        {
            "category":"Autos & Motor Vehicles",
            "subcategory":"Auto Supplies",
            "type":"Retail Goods"
        }
    ],
    "sg:phone":"+1 209 522 4431",
    "sg:postcode":"95358",
    "sg:province":"CA",
    "sg:tags":[
        "glass"
    ],
    "wof:name":"Miguel's Glass",
    "wof:placetype":"venue"
},
  "geometry": {"coordinates":[-120.98757000000001,37.60571],"type":"Point"}
}