{
  "type": "Feature",
  "properties": {
    "iso:country":"US",
    "sg:address":"13225 Beach Blvd",
    "sg:city":"Westminster",
    "sg:classifiers":[
        {
            "category":"Home & Garden",
            "subcategory":"Hardware",
            "type":"Retail Goods"
        }
    ],
    "sg:phone":"+1 714 799 0230",
    "sg:postcode":"92683",
    "sg:province":"CA",
    "sg:tags":[
        "store"
    ],
    "sg:website":"www.lowes.com",
    "wof:name":"Lowes",
    "wof:placetype":"venue"
},
  "geometry": {"coordinates":[-117.992896,33.768765],"type":"Point"}
}