{
  "type": "Feature",
  "properties": {
    "addr:full":"20 Nevada St Ste 100 Redlands CA 92373",
    "addr:housenumber":"20",
    "addr:postcode":"92373",
    "addr:street":"Nevada St Ste 100",
    "iso:country":"US",
    "sg:address":"20 Nevada St Ste 100",
    "sg:city":"Redlands",
    "sg:classifiers":[
        {
            "category":"Insurance",
            "subcategory":"Hazard Insurance",
            "type":"Services"
        }
    ],
    "sg:phone":"+1 909 792 7755",
    "sg:postcode":"92373",
    "sg:province":"CA",
    "sg:tags":[
        "commercial",
        "business"
    ],
    "sg:website":"http://www.newyorklife.com",
    "wof:name":"New York Life",
    "wof:placetype":"venue"
},
  "geometry": {"coordinates":[-117.217461,34.062969],"type":"Point"}
}