{
  "type": "Feature",
  "properties": {
    "iso:country":"US",
    "sg:address":"1411 W Covell Blvd",
    "sg:city":"Davis",
    "sg:classifiers":[
        {
            "category":"Building & Trades",
            "subcategory":"Landscaping Services",
            "type":"Services"
        }
    ],
    "sg:phone":"+1 530 756 5101",
    "sg:postcode":"95616",
    "sg:province":"CA",
    "sg:tags":[
        "designer",
        "landscape"
    ],
    "wof:name":"Margot M Anderson Architect",
    "wof:placetype":"venue"
},
  "geometry": {"coordinates":[-121.765511,38.56095],"type":"Point"}
}