{
  "type": "Feature",
  "properties": {
    "iso:country":"US",
    "sg:address":"496 E 3rd St",
    "sg:city":"San Bernardino",
    "sg:classifiers":[
        {
            "category":"Government",
            "subcategory":"Office",
            "type":"Public Place"
        }
    ],
    "sg:phone":"+1 909 885 8805",
    "sg:postcode":"92410",
    "sg:province":"CA",
    "sg:tags":[
        "armed",
        "force",
        "recruiting"
    ],
    "wof:name":"US Army Recruiting",
    "wof:placetype":"venue"
},
  "geometry": {"coordinates":[-117.274362,34.104324],"type":"Point"}
}