{
  "type": "Feature",
  "properties": {
    "iso:country":"US",
    "sg:address":"16937 Walnut St",
    "sg:city":"Hesperia",
    "sg:classifiers":[
        {
            "category":"Real Estate",
            "subcategory":"Real Estate Agent",
            "type":"Services"
        }
    ],
    "sg:phone":"+1 760 948 9810",
    "sg:postcode":"92345",
    "sg:province":"CA",
    "wof:name":"Regency Real Estate",
    "wof:placetype":"venue"
},
  "geometry": {"coordinates":[-117.29318,34.419217],"type":"Point"}
}