{
  "type": "Feature",
  "properties": {
    "addr:full":"9601 Riverview Ave Lakeside CA 92040",
    "addr:housenumber":"9601",
    "addr:postcode":"92040",
    "addr:street":"Riverview Ave",
    "iso:country":"US",
    "sg:address":"9601 Riverview Ave",
    "sg:city":"Lakeside",
    "sg:classifiers":[
        {
            "category":"Building & Trades",
            "subcategory":"Landscaping Services",
            "type":"Services"
        }
    ],
    "sg:phone":"+1 619 443 6648",
    "sg:postcode":"92040",
    "sg:province":"CA",
    "wof:name":"J R Agozino & Sons",
    "wof:placetype":"venue"
},
  "geometry": {"coordinates":[-116.935232,32.850331],"type":"Point"}
}