{
  "type": "Feature",
  "properties": {
    "addr:full":"3085 Wild Dove Ln Mariposa CA 95338",
    "addr:housenumber":"3085",
    "addr:postcode":"95338",
    "addr:street":"Wild Dove Ln",
    "iso:country":"US",
    "sg:address":"3085 Wild Dove Ln",
    "sg:city":"Mariposa",
    "sg:classifiers":[
        {
            "category":"Real Estate",
            "subcategory":"Real Estate Agent",
            "type":"Services"
        }
    ],
    "sg:phone":"+1 209 966 2653",
    "sg:postcode":"95338",
    "sg:province":"CA",
    "sg:tags":[
        "rental",
        "vacation"
    ],
    "wof:name":"Shangri-LA Guest Cottages",
    "wof:placetype":"venue"
},
  "geometry": {"coordinates":[-119.835121,37.536322],"type":"Point"}
}