{
  "type": "Feature",
  "properties": {
    "iso:country":"US",
    "sg:address":"19 E Lake Ave",
    "sg:city":"Watsonville",
    "sg:classifiers":[
        {
            "category":"Shopping",
            "subcategory":"Jewelry",
            "type":"Retail Goods"
        }
    ],
    "sg:phone":"+1 831 722 3283",
    "sg:postcode":"95076",
    "sg:province":"CA",
    "sg:tags":[
        "jeweler"
    ],
    "wof:name":"Gisselle's Jewelry & Fashions",
    "wof:placetype":"venue"
},
  "geometry": {"coordinates":[-121.756962,36.912666],"type":"Point"}
}