{
  "type": "Feature",
  "properties": {
    "addr:full":"30950 Rancho Viejo Road  Suite 120 San Juan Capistrano CA 92675",
    "addr:housenumber":"30950",
    "addr:postcode":"92675",
    "addr:street":"Rancho Viejo Road Suite 120",
    "iso:country":"US",
    "sg:address":"30950 Rancho Viejo Road  Suite 120",
    "sg:city":"San Juan Capistrano",
    "sg:classifiers":[
        {
            "category":"Professional",
            "subcategory":"Business Services",
            "type":"Services"
        }
    ],
    "sg:phone":"+1 949 260 0150",
    "sg:postcode":"92675",
    "sg:province":"CA",
    "sg:website":"http://www.dlgi.com",
    "wof:name":"DataLogix International",
    "wof:placetype":"venue"
},
  "geometry": {"coordinates":[-117.661761,33.513211],"type":"Point"}
}