{
  "type": "Feature",
  "properties": {
    "addr:full":"1900 Douglas Blvd Roseville CA 95678",
    "addr:housenumber":"1900",
    "addr:postcode":"95678",
    "addr:street":"Douglas Blvd",
    "iso:country":"US",
    "sg:address":"1900 Douglas Blvd",
    "sg:city":"Roseville",
    "sg:classifiers":[
        {
            "category":"Restaurant",
            "type":"Food & Drink"
        }
    ],
    "sg:phone":"+1 916 784 2888",
    "sg:postcode":"95678",
    "sg:province":"CA",
    "wof:name":"Strings Italian Cafe",
    "wof:placetype":"venue"
},
  "geometry": {"coordinates":[-121.253049,38.744264],"type":"Point"}
}