{
  "type": "Feature",
  "properties": {
    "iso:country":"US",
    "sg:address":"8032 W 3rd St",
    "sg:city":"Los Angeles",
    "sg:classifiers":[
        {
            "category":"Shopping",
            "subcategory":"Used Merchandise",
            "type":"Retail Goods"
        }
    ],
    "sg:phone":"+1 323 651 4732",
    "sg:postcode":"90048",
    "sg:province":"CA",
    "sg:tags":[
        "vintage",
        "consignment"
    ],
    "wof:name":"V E Trading",
    "wof:placetype":"venue"
},
  "geometry": {"coordinates":[-118.364998,34.071999],"type":"Point"}
}