{
  "type": "Feature",
  "properties": {
    "addr:full":"6345 N 10th St Fresno CA 93710",
    "addr:housenumber":"6345",
    "addr:postcode":"93710",
    "addr:street":"N 10Th St",
    "iso:country":"US",
    "sg:address":"6345 N 10th St",
    "sg:city":"Fresno",
    "sg:classifiers":[
        {
            "category":"Communications",
            "type":"Services"
        }
    ],
    "sg:phone":"+1 559 447 9226",
    "sg:postcode":"93710",
    "sg:province":"CA",
    "sg:tags":[
        "communication"
    ],
    "wof:name":"D&M Communications",
    "wof:placetype":"venue"
},
  "geometry": {"coordinates":[-119.75725300000001,36.828499],"type":"Point"}
}