{
  "type": "Feature",
  "properties": {
    "iso:country":"US",
    "sg:address":"6518 Via Florencia",
    "sg:city":"Riverside",
    "sg:classifiers":[
        {
            "category":"Freight",
            "type":"Transportation"
        }
    ],
    "sg:phone":"+1 951 684 1185",
    "sg:postcode":"92509",
    "sg:province":"CA",
    "sg:tags":[
        "operator",
        "local",
        "trucking"
    ],
    "wof:name":"Egelhoff Trucking Co",
    "wof:placetype":"venue"
},
  "geometry": {"coordinates":[-117.430554,33.992843],"type":"Point"}
}