{
  "type": "Feature",
  "properties": {
    "addr:full":"6443 Tokelau St Cypress CA 90630",
    "addr:housenumber":"6443",
    "addr:postcode":"90630",
    "addr:street":"Tokelau St",
    "iso:country":"US",
    "sg:address":"6443 Tokelau St",
    "sg:city":"Cypress",
    "sg:classifiers":[
        {
            "category":"Building & Trades",
            "subcategory":"Construction",
            "type":"Services"
        }
    ],
    "sg:phone":"+1 714 832 7941",
    "sg:postcode":"90630",
    "sg:province":"CA",
    "sg:tags":[
        "contractor"
    ],
    "wof:name":"Sun Maintenance",
    "wof:placetype":"venue"
},
  "geometry": {"coordinates":[-118.04067000000001,33.793872],"type":"Point"}
}