{
  "type": "Feature",
  "properties": {
    "addr:full":"8049 Elnora Ct Sacramento CA 95829",
    "addr:housenumber":"8049",
    "addr:postcode":"95829",
    "addr:street":"Elnora Ct",
    "iso:country":"US",
    "sg:address":"8049 Elnora Ct",
    "sg:city":"Sacramento",
    "sg:classifiers":[
        {
            "category":"Building & Trades",
            "subcategory":"Construction",
            "type":"Services"
        }
    ],
    "sg:phone":"+1 916 682 7477",
    "sg:postcode":"95829",
    "sg:province":"CA",
    "sg:tags":[
        "floor",
        "laying",
        "landscape",
        "contractor"
    ],
    "wof:name":"Expert Landscaping & Flooring",
    "wof:placetype":"venue"
},
  "geometry": {"coordinates":[-121.363078,38.464105],"type":"Point"}
}