{
  "type": "Feature",
  "properties": {
    "iso:country":"US",
    "sg:address":"500 Tamal Plz",
    "sg:city":"Corte Madera",
    "sg:classifiers":[
        {
            "category":"Freight",
            "type":"Transportation"
        }
    ],
    "sg:phone":"+1 415 927 5760",
    "sg:postcode":"94925",
    "sg:province":"CA",
    "sg:tags":[
        "forwarding"
    ],
    "wof:name":"Asi",
    "wof:placetype":"venue"
},
  "geometry": {"coordinates":[-122.519786,37.936924],"type":"Point"}
}