{
  "type": "Feature",
  "properties": {
    "iso:country":"US",
    "sg:address":"3565 Recycle Rd",
    "sg:city":"Rancho Cordova",
    "sg:classifiers":[
        {
            "category":"Wholesale",
            "subcategory":"Auto Parts",
            "type":"Manufacturing & Wholesale Goods"
        }
    ],
    "sg:phone":"+1 916 635 1617",
    "sg:postcode":"95742",
    "sg:province":"CA",
    "sg:tags":[
        "automobile",
        "wrecking"
    ],
    "wof:name":"Asian Auto Recycling",
    "wof:placetype":"venue"
},
  "geometry": {"coordinates":[-121.258831,38.57341],"type":"Point"}
}