{
  "type": "Feature",
  "properties": {
    "addr:full":"PO Box 60848 Sunnyvale CA 94088",
    "addr:housenumber":"po box",
    "addr:postcode":"94088",
    "addr:street":"60848",
    "iso:country":"US",
    "sg:address":"PO Box 60848",
    "sg:city":"Sunnyvale",
    "sg:classifiers":[
        {
            "category":"Personal",
            "type":"Services"
        }
    ],
    "sg:phone":"+1 800 503 0128",
    "sg:postcode":"94088",
    "sg:province":"CA",
    "sg:tags":[
        "party",
        "planning",
        "event",
        "wedding"
    ],
    "sg:website":"inyourelementevents.com/",
    "wof:name":"In Your Element Events",
    "wof:placetype":"venue"
},
  "geometry": {"coordinates":[-122.03530000000001,37.3688],"type":"Point"}
}