{
  "type": "Feature",
  "properties": {
    "iso:country":"US",
    "sg:address":"2261 Morello Ave",
    "sg:city":"Pleasant Hill",
    "sg:classifiers":[
        {
            "category":"Wholesale",
            "subcategory":"Motor Vehicles",
            "type":"Manufacturing & Wholesale Goods"
        }
    ],
    "sg:phone":"+1 925 671 7176",
    "sg:postcode":"94523",
    "sg:province":"CA",
    "wof:name":"Auto Hound",
    "wof:placetype":"venue"
},
  "geometry": {"coordinates":[-122.079024,37.961852],"type":"Point"}
}