{
  "type": "Feature",
  "properties": {
    "addr:full":"8555 Aero Dr San Diego CA 92123",
    "addr:housenumber":"8555",
    "addr:postcode":"92123",
    "addr:street":"Aero Dr",
    "iso:country":"US",
    "sg:address":"8555 Aero Dr",
    "sg:city":"San Diego",
    "sg:classifiers":[
        {
            "category":"Professional",
            "subcategory":"Management & Consulting",
            "type":"Services"
        }
    ],
    "sg:phone":"+1 858 560 6064",
    "sg:postcode":"92123",
    "sg:province":"CA",
    "sg:tags":[
        "business"
    ],
    "wof:name":"S A Industries Inc",
    "wof:placetype":"venue"
},
  "geometry": {"coordinates":[-117.14112799999999,32.809616],"type":"Point"}
}