{
  "type": "Feature",
  "properties": {
    "addr:full":"1255 N Grand Ave Walnut CA 91789",
    "addr:housenumber":"1255",
    "addr:postcode":"91789",
    "addr:street":"N Grand Ave",
    "iso:country":"US",
    "sg:address":"1255 N Grand Ave",
    "sg:city":"Walnut",
    "sg:classifiers":[
        {
            "category":"Building & Trades",
            "subcategory":"Construction",
            "type":"Services"
        }
    ],
    "sg:phone":"+1 213 596 9754",
    "sg:postcode":"91789",
    "sg:province":"CA",
    "sg:tags":[
        "general",
        "contractor"
    ],
    "wof:name":"Intra-Construction Company",
    "wof:placetype":"venue"
},
  "geometry": {"coordinates":[-117.84823,34.043623],"type":"Point"}
}