{
  "type": "Feature",
  "properties": {
    "iso:country":"US",
    "sg:address":"1840 Ventura Blvd",
    "sg:city":"Camarillo",
    "sg:classifiers":[
        {
            "category":"Shopping",
            "subcategory":"Clothing, Apparel, & Fashions",
            "type":"Retail Goods"
        }
    ],
    "sg:phone":"+1 805 482 4848",
    "sg:postcode":"93010",
    "sg:province":"CA",
    "sg:tags":[
        "wig",
        "toupee",
        "hairpiece"
    ],
    "wof:name":"Artistic Hair Pieces & Wigs",
    "wof:placetype":"venue"
},
  "geometry": {"coordinates":[-119.044407,34.217024],"type":"Point"}
}