{
  "type": "Feature",
  "properties": {
    "addr:full":"447 Great Mall Dr Milpitas CA 95035",
    "addr:housenumber":"447",
    "addr:postcode":"95035",
    "addr:street":"Great Mall Dr",
    "iso:country":"US",
    "sg:address":"447 Great Mall Dr",
    "sg:city":"Milpitas",
    "sg:classifiers":[
        {
            "category":"Shopping",
            "subcategory":"Music",
            "type":"Retail Goods"
        }
    ],
    "sg:phone":"+1 408 945 8267",
    "sg:postcode":"95035",
    "sg:province":"CA",
    "sg:tags":[
        "compact",
        "record",
        "disc",
        "tape"
    ],
    "wof:name":"Express Vinyl",
    "wof:placetype":"venue"
},
  "geometry": {"coordinates":[-121.895914,37.415197],"type":"Point"}
}