{
  "type": "Feature",
  "properties": {
    "iso:country":"US",
    "sg:address":"16999 Monterey St",
    "sg:city":"Morgan Hill",
    "sg:classifiers":[
        {
            "category":"Retail",
            "subcategory":"Animal Services",
            "type":"Services"
        }
    ],
    "sg:phone":"+1 408 778 5003",
    "sg:postcode":"95037",
    "sg:province":"CA",
    "sg:tags":[
        "pet",
        "grooming",
        "washing"
    ],
    "wof:name":"Canine Concepts",
    "wof:placetype":"venue"
},
  "geometry": {"coordinates":[-121.64946999999999,37.124196],"type":"Point"}
}