{
  "type": "Feature",
  "properties": {
    "iso:country":"US",
    "sg:address":"4600 District Blvd",
    "sg:city":"Vernon",
    "sg:classifiers":[
        {
            "category":"Wholesale",
            "subcategory":"Durable Goods & Equipment",
            "type":"Manufacturing & Wholesale Goods"
        }
    ],
    "sg:phone":"+1 323 582 6852",
    "sg:postcode":"90058",
    "sg:province":"CA",
    "sg:tags":[
        "representative",
        "manufacturer"
    ],
    "sg:website":"www.pacificsouthwestsales.com",
    "wof:name":"Pacific Southwest Sales",
    "wof:placetype":"venue"
},
  "geometry": {"coordinates":[-118.19483,33.999351],"type":"Point"}
}