{
  "type": "Feature",
  "properties": {
    "iso:country":"US",
    "sg:address":"8629 Auburn Folsom Rd",
    "sg:city":"Granite Bay",
    "sg:classifiers":[
        {
            "category":"Freight",
            "type":"Transportation"
        }
    ],
    "sg:phone":"+1 916 797 2932",
    "sg:postcode":"95746",
    "sg:province":"CA",
    "sg:tags":[
        "operator",
        "trucking"
    ],
    "wof:name":"Landstar",
    "wof:placetype":"venue"
},
  "geometry": {"coordinates":[-121.17049900000001,38.742636],"type":"Point"}
}