{
  "type": "Feature",
  "properties": {
    "iso:country":"US",
    "sg:address":"130 Dawson Dr",
    "sg:city":"Camarillo",
    "sg:classifiers":[
        {
            "category":"Government",
            "subcategory":"Office",
            "type":"Public Place"
        }
    ],
    "sg:phone":"+1 805 388 6422",
    "sg:postcode":"93012",
    "sg:province":"CA",
    "sg:tags":[
        "smog",
        "check"
    ],
    "sg:website":"www.barrysautoservice.com",
    "wof:name":"Barry's Auto Service",
    "wof:placetype":"venue"
},
  "geometry": {"coordinates":[-119.03394900000001,34.214508],"type":"Point"}
}