{
  "type": "Feature",
  "properties": {
    "addr:full":"3138 del Rey Ave Carlsbad CA 92009",
    "addr:housenumber":"3138",
    "addr:postcode":"92009",
    "addr:street":"Del Rey Ave",
    "iso:country":"US",
    "sg:address":"3138 del Rey Ave",
    "sg:city":"Carlsbad",
    "sg:classifiers":[
        {
            "category":"Building & Trades",
            "subcategory":"Construction",
            "type":"Services"
        }
    ],
    "sg:phone":"+1 760 635 7757",
    "sg:postcode":"92009",
    "sg:province":"CA",
    "sg:tags":[
        "general",
        "contractor"
    ],
    "wof:name":"Calif Kitchen & Bath Remodel",
    "wof:placetype":"venue"
},
  "geometry": {"coordinates":[-117.23942700000001,33.087824],"type":"Point"}
}