{
  "type": "Feature",
  "properties": {
    "addr:full":"43500 Ridge Park Dr Temecula CA 92590",
    "addr:housenumber":"43500",
    "addr:postcode":"92590",
    "addr:street":"Ridge Park Dr",
    "iso:country":"US",
    "sg:address":"43500 Ridge Park Dr",
    "sg:city":"Temecula",
    "sg:classifiers":[
        {
            "category":"Professional",
            "subcategory":"Engineering",
            "type":"Services"
        }
    ],
    "sg:phone":"+1 951 699 6450",
    "sg:postcode":"92590",
    "sg:province":"CA",
    "sg:tags":[
        "engineer"
    ],
    "wof:name":"Engineering Ventures",
    "wof:placetype":"venue"
},
  "geometry": {"coordinates":[-117.156661,33.49509],"type":"Point"}
}