{
  "type": "Feature",
  "properties": {
    "iso:country":"US",
    "sg:address":"1301 Yosemite Pkwy",
    "sg:city":"Merced",
    "sg:classifiers":[
        {
            "category":"Organizations",
            "subcategory":"Non-profit Organization",
            "type":"Services"
        }
    ],
    "sg:phone":"+1 209 722 6335",
    "sg:postcode":"95340",
    "sg:province":"CA",
    "sg:tags":[
        "information",
        "alcoholism",
        "treatment"
    ],
    "wof:name":"Hobie House",
    "wof:placetype":"venue"
},
  "geometry": {"coordinates":[-120.459739,37.295199],"type":"Point"}
}