{
  "type": "Feature",
  "properties": {
    "iso:country":"US",
    "sg:address":"2777 N Maroa Ave",
    "sg:city":"Fresno",
    "sg:classifiers":[
        {
            "category":"Bars & Pubs",
            "type":"Food & Drink"
        }
    ],
    "sg:phone":"+1 559 229 4188",
    "sg:postcode":"93704",
    "sg:province":"CA",
    "sg:tags":[
        "club",
        "night"
    ],
    "wof:name":"North Tower Circle",
    "wof:placetype":"venue"
},
  "geometry": {"coordinates":[-119.79966899999999,36.775081],"type":"Point"}
}