{
  "type": "Feature",
  "properties": {
    "iso:country":"US",
    "sg:address":"2 Park Plz",
    "sg:city":"Irvine",
    "sg:classifiers":[
        {
            "category":"Real Estate",
            "subcategory":"Real Estate Operator",
            "type":"Services"
        },
        {
            "category":"Banks & Credit Unions",
            "subcategory":"Investment Brokerage",
            "type":"Services"
        }
    ],
    "sg:phone":"+1 949 756 0320",
    "sg:postcode":"92614",
    "sg:province":"CA",
    "sg:tags":[
        "investing",
        "apartment"
    ],
    "wof:name":"Transitional Investors Llc",
    "wof:placetype":"venue"
},
  "geometry": {"coordinates":[-117.83882199999999,33.679397],"type":"Point"}
}