{
  "type": "Feature",
  "properties": {
    "iso:country":"US",
    "sg:address":"5701 Crestridge Road Apt 305",
    "sg:city":"Rancho Palos Verdes",
    "sg:classifiers":[
        {
            "category":"Social Services",
            "subcategory":"Retirement Home",
            "type":"Services"
        }
    ],
    "sg:phone":"+1 310 377 9977",
    "sg:postcode":"90275",
    "sg:province":"CA",
    "wof:name":"Belmont Village of Rancho",
    "wof:placetype":"venue"
},
  "geometry": {"coordinates":[-118.377351,33.768113],"type":"Point"}
}