{
  "type": "Feature",
  "properties": {
    "iso:country":"US",
    "sg:address":"644 Brannan St",
    "sg:city":"San Francisco",
    "sg:classifiers":[
        {
            "category":"Wholesale",
            "subcategory":"Plants",
            "type":"Manufacturing & Wholesale Goods"
        },
        {
            "category":"Farming",
            "subcategory":"Nursery",
            "type":"Manufacturing & Wholesale Goods"
        }
    ],
    "sg:phone":"+1 415 974 6633",
    "sg:postcode":"94107",
    "sg:province":"CA",
    "sg:tags":[
        "flower",
        "greenhouse"
    ],
    "wof:name":"Ano Nuevo Flowers Growers Inc",
    "wof:placetype":"venue"
},
  "geometry": {"coordinates":[-122.400168,37.775714],"type":"Point"}
}