{
  "type": "Feature",
  "properties": {
    "addr:full":"2854 Park Marina Dr Redding CA 96001",
    "addr:housenumber":"2854",
    "addr:postcode":"96001",
    "addr:street":"Park Marina Dr",
    "iso:country":"US",
    "sg:address":"2854 Park Marina Dr",
    "sg:city":"Redding",
    "sg:classifiers":[
        {
            "category":"Insurance",
            "subcategory":"Insurance Agent",
            "type":"Services"
        }
    ],
    "sg:phone":"+1 530 241 1635",
    "sg:postcode":"96001",
    "sg:province":"CA",
    "wof:name":"Pacific Cascade Insurance",
    "wof:placetype":"venue"
},
  "geometry": {"coordinates":[-122.3742,40.572359],"type":"Point"}
}