{
  "type": "Feature",
  "properties": {
    "addr:full":"117 Solana Rd Portola Valley CA 94028",
    "addr:housenumber":"117",
    "addr:postcode":"94028",
    "addr:street":"Solana Rd",
    "iso:country":"US",
    "sg:address":"117 Solana Rd",
    "sg:city":"Portola Valley",
    "sg:classifiers":[
        {
            "category":"Wholesale",
            "subcategory":"Chemicals & Plastics",
            "type":"Manufacturing & Wholesale Goods"
        }
    ],
    "sg:phone":"+1 650 529 9099",
    "sg:postcode":"94028",
    "sg:province":"CA",
    "wof:name":"Magellan Systems International",
    "wof:placetype":"venue"
},
  "geometry": {"coordinates":[-122.220753,37.389669],"type":"Point"}
}