{
  "type": "Feature",
  "properties": {
    "iso:country":"US",
    "sg:address":"21238 Royal Ave",
    "sg:city":"Hayward",
    "sg:classifiers":[
        {
            "category":"Social Services",
            "subcategory":"Adult Care",
            "type":"Services"
        }
    ],
    "sg:phone":"+1 510 785 9416",
    "sg:postcode":"94541",
    "sg:province":"CA",
    "sg:tags":[
        "home",
        "residential"
    ],
    "wof:name":"Sunshine ICF-Ddh",
    "wof:placetype":"venue"
},
  "geometry": {"coordinates":[-122.113299,37.666301],"type":"Point"}
}