{
  "type": "Feature",
  "properties": {
    "addr:full":"1160 Aviation Blvd Hermosa Beach CA 90254",
    "addr:housenumber":"1160",
    "addr:postcode":"90254",
    "addr:street":"Aviation Blvd",
    "iso:country":"US",
    "sg:address":"1160 Aviation Blvd",
    "sg:city":"Hermosa Beach",
    "sg:classifiers":[
        {
            "category":"Restaurant",
            "type":"Food & Drink"
        }
    ],
    "sg:menulink":"http://www.allmenus.com/ca/south-bay-cities/178491-jack-in-the-box/menu/",
    "sg:phone":"+1 310 374 9240",
    "sg:postcode":"90254",
    "sg:province":"CA",
    "sg:tags":[
        "burger",
        "american"
    ],
    "wof:name":"Jack in the Box",
    "wof:placetype":"venue"
},
  "geometry": {"coordinates":[-118.386548,33.865119],"type":"Point"}
}