{
  "type": "Feature",
  "properties": {
    "addr:full":"1306 Canal Blvd Richmond CA 94804",
    "addr:housenumber":"1306",
    "addr:postcode":"94804",
    "addr:street":"Canal Blvd",
    "iso:country":"US",
    "sg:address":"1306 Canal Blvd",
    "sg:city":"Richmond",
    "sg:classifiers":[
        {
            "category":"Professional",
            "subcategory":"Business Services",
            "type":"Services"
        }
    ],
    "sg:phone":"+1 510 234 0564",
    "sg:postcode":"94804",
    "sg:province":"CA",
    "sg:tags":[
        "consultant",
        "petroleum"
    ],
    "wof:name":"QMSI Inc",
    "wof:placetype":"venue"
},
  "geometry": {"coordinates":[-122.365921,37.909518],"type":"Point"}
}