{
  "type": "Feature",
  "properties": {
    "addr:full":"2860 Fletcher Dr Los Angeles CA 90039",
    "addr:housenumber":"2860",
    "addr:postcode":"90039",
    "addr:street":"Fletcher Dr",
    "iso:country":"US",
    "sg:address":"2860 Fletcher Dr",
    "sg:city":"Los Angeles",
    "sg:classifiers":[
        {
            "category":"Local Transit",
            "type":"Transportation"
        }
    ],
    "sg:phone":"+1 818 566 6819",
    "sg:postcode":"90039",
    "sg:province":"CA",
    "sg:tags":[
        "passenger",
        "limo"
    ],
    "wof:name":"B L S Limousine Service",
    "wof:placetype":"venue"
},
  "geometry": {"coordinates":[-118.248001,34.1129],"type":"Point"}
}