{
  "type": "Feature",
  "properties": {
    "addr:full":"400 E 1st St Los Angeles CA 90012",
    "addr:housenumber":"400",
    "addr:postcode":"90012",
    "addr:street":"E 1St St",
    "iso:country":"US",
    "sg:address":"400 E 1st St",
    "sg:city":"Los Angeles",
    "sg:classifiers":[
        {
            "category":"Bars & Pubs",
            "type":"Food & Drink"
        },
        {
            "category":"Restaurant",
            "type":"Food & Drink"
        },
        {
            "category":"Brewery",
            "type":"Food & Drink"
        }
    ],
    "sg:phone":"+1 213 680 2881",
    "sg:postcode":"90012",
    "sg:province":"CA",
    "sg:tags":[
        "traditional",
        "american"
    ],
    "sg:website":"www.weilandbrewery.net/WBR/",
    "wof:name":"Weiland Brewery Restaurant",
    "wof:placetype":"venue"
},
  "geometry": {"coordinates":[-118.23909500000001,34.049196],"type":"Point"}
}