{
  "type": "Feature",
  "properties": {
    "iso:country":"US",
    "sg:address":"1150 Crane St",
    "sg:city":"Menlo Park",
    "sg:classifiers":[
        {
            "category":"Personal",
            "subcategory":"Beauty Salon",
            "type":"Services"
        }
    ],
    "sg:phone":"+1 650 321 0679",
    "sg:postcode":"94025",
    "sg:province":"CA",
    "sg:tags":[
        "manicuring"
    ],
    "wof:name":"A Touch Of Elegance",
    "wof:placetype":"venue"
},
  "geometry": {"coordinates":[-122.185721,37.451482],"type":"Point"}
}