{
  "type": "Feature",
  "properties": {
    "addr:full":"8508 Cherry Crest Ct Elk Grove CA 95624",
    "addr:housenumber":"8508",
    "addr:postcode":"95624",
    "addr:street":"Cherry Crest Ct",
    "iso:country":"US",
    "sg:address":"8508 Cherry Crest Ct",
    "sg:city":"Elk Grove",
    "sg:classifiers":[
        {
            "category":"Building & Trades",
            "subcategory":"Construction",
            "type":"Services"
        }
    ],
    "sg:phone":"+1 916 685 8497",
    "sg:postcode":"95624",
    "sg:province":"CA",
    "sg:tags":[
        "general",
        "contractor"
    ],
    "wof:name":"Dapelo Construction",
    "wof:placetype":"venue"
},
  "geometry": {"coordinates":[-121.38936099999999,38.421454],"type":"Point"}
}