{
  "type": "Feature",
  "properties": {
    "addr:full":"1300 Grant Ave San Francisco CA 94133",
    "addr:housenumber":"1300",
    "addr:postcode":"94133",
    "addr:street":"Grant Ave",
    "iso:country":"US",
    "sg:address":"1300 Grant Ave",
    "sg:city":"San Francisco",
    "sg:classifiers":[
        {
            "category":"Manufacturing",
            "subcategory":"Apparel",
            "type":"Manufacturing & Wholesale Goods"
        }
    ],
    "sg:phone":"+1 415 986 1171",
    "sg:postcode":"94133",
    "sg:province":"CA",
    "sg:tags":[
        "outwear",
        "mfg"
    ],
    "wof:name":"Babette",
    "wof:placetype":"venue"
},
  "geometry": {"coordinates":[-122.40739499999999,37.799704],"type":"Point"}
}