{
  "type": "Feature",
  "properties": {
    "addr:full":"2525 Barrington Ct Hayward CA 94545",
    "addr:housenumber":"2525",
    "addr:postcode":"94545",
    "addr:street":"Barrington Ct",
    "iso:country":"US",
    "sg:address":"2525 Barrington Ct",
    "sg:city":"Hayward",
    "sg:classifiers":[
        {
            "category":"Building & Trades",
            "subcategory":"Landscaping Services",
            "type":"Services"
        },
        {
            "category":"Home & Garden",
            "subcategory":"Garden Supply",
            "type":"Retail Goods"
        }
    ],
    "sg:phone":"+1 510 785 8483",
    "sg:postcode":"94545",
    "sg:province":"CA",
    "sg:tags":[
        "lawn",
        "installation",
        "sprinkler",
        "sprinklers-garden",
        "system",
        "supervisory"
    ],
    "sg:website":"http://www.sprinklerfitters483.org",
    "wof:name":"Sprinkler Fitters Local 483",
    "wof:placetype":"venue"
},
  "geometry": {"coordinates":[-122.140776,37.655456],"type":"Point"}
}