{
  "type": "Feature",
  "properties": {
    "addr:full":"1304 S 43rd St San Diego CA 92113",
    "addr:housenumber":"1304",
    "addr:postcode":"92113",
    "addr:street":"S 43Rd St",
    "iso:country":"US",
    "sg:address":"1304 S 43rd St",
    "sg:city":"San Diego",
    "sg:classifiers":[
        {
            "category":"Autos & Motor Vehicles",
            "subcategory":"Auto Supplies",
            "type":"Retail Goods"
        }
    ],
    "sg:phone":"+1 619 263 9338",
    "sg:postcode":"92113",
    "sg:province":"CA",
    "sg:tags":[
        "automobile",
        "parts"
    ],
    "sg:website":"www.autozone.com",
    "wof:name":"Autozone",
    "wof:placetype":"venue"
},
  "geometry": {"coordinates":[-117.102458,32.692669],"type":"Point"}
}