{
  "type": "Feature",
  "properties": {
    "iso:country":"US",
    "sg:address":"112 W 9th St",
    "sg:city":"Los Angeles",
    "sg:classifiers":[
        {
            "category":"Wholesale",
            "subcategory":"Apparel",
            "type":"Manufacturing & Wholesale Goods"
        },
        {
            "category":"Wholesale",
            "subcategory":"Durable Goods & Equipment",
            "type":"Manufacturing & Wholesale Goods"
        }
    ],
    "sg:phone":"+1 213 614 0804",
    "sg:postcode":"90015",
    "sg:province":"CA",
    "sg:tags":[
        "importer",
        "clothing"
    ],
    "wof:name":"Lucky Star Imports Inc",
    "wof:placetype":"venue"
},
  "geometry": {"coordinates":[-118.255346,34.041756],"type":"Point"}
}