{
  "type": "Feature",
  "properties": {
    "iso:country":"US",
    "sg:address":"10625 Leffingwell Rd",
    "sg:city":"Norwalk",
    "sg:classifiers":[
        {
            "category":"Health Services",
            "subcategory":"Nursing And Care Facility",
            "type":"Services"
        }
    ],
    "sg:phone":"+1 562 864 2541",
    "sg:postcode":"90650",
    "sg:province":"CA",
    "sg:tags":[
        "home",
        "skilled",
        "convalescent"
    ],
    "wof:name":"Norwalk Meadows Nursing Center",
    "wof:placetype":"venue"
},
  "geometry": {"coordinates":[-118.107675,33.904669],"type":"Point"}
}