{
  "type": "Feature",
  "properties": {
    "addr:full":"1784 N 1st Ave Upland CA 91784",
    "addr:housenumber":"1784",
    "addr:postcode":"91784",
    "addr:street":"N 1St Ave",
    "iso:country":"US",
    "sg:address":"1784 N 1st Ave",
    "sg:city":"Upland",
    "sg:classifiers":[
        {
            "category":"Manufacturing",
            "subcategory":"Electronics",
            "type":"Manufacturing & Wholesale Goods"
        }
    ],
    "sg:phone":"+1 909 982 2922",
    "sg:postcode":"91784",
    "sg:province":"CA",
    "sg:tags":[
        "control",
        "security",
        "system"
    ],
    "wof:name":"JTI",
    "wof:placetype":"venue"
},
  "geometry": {"coordinates":[-117.649697,34.125696],"type":"Point"}
}