{
  "type": "Feature",
  "properties": {
    "iso:country":"US",
    "sg:address":"555 Twin Dolphin Dr",
    "sg:city":"Redwood City",
    "sg:classifiers":[
        {
            "category":"Banks & Credit Unions",
            "subcategory":"Bank",
            "type":"Services"
        }
    ],
    "sg:phone":"+1 650 592 4050",
    "sg:postcode":"94065",
    "sg:province":"CA",
    "sg:tags":[
        "loan",
        "real estate"
    ],
    "wof:name":"First Security Loans",
    "wof:placetype":"venue"
},
  "geometry": {"coordinates":[-122.250941,37.518604],"type":"Point"}
}