{
  "type": "Feature",
  "properties": {
    "addr:full":"1073 Alameda de las Pulgas Belmont CA 94002",
    "addr:housenumber":"1073",
    "addr:postcode":"94002",
    "addr:street":"Alameda De Las Pulgas",
    "iso:country":"US",
    "sg:address":"1073 Alameda de las Pulgas",
    "sg:city":"Belmont",
    "sg:classifiers":[
        {
            "category":"Food & Beverages",
            "subcategory":"Bakery",
            "type":"Retail Goods"
        }
    ],
    "sg:phone":"+1 650 591 9105",
    "sg:postcode":"94002",
    "sg:province":"CA",
    "sg:tags":[
        "sandwich"
    ],
    "sg:website":"www.subway.com",
    "wof:name":"Subway",
    "wof:placetype":"venue"
},
  "geometry": {"coordinates":[-122.293605,37.510495],"type":"Point"}
}