{
  "type": "Feature",
  "properties": {
    "addr:full":"15424 W Sunset Blvd Pacific Plsds CA 90272",
    "addr:housenumber":"15424",
    "addr:postcode":"90272",
    "addr:street":"W Sunset Blvd",
    "iso:country":"US",
    "sg:address":"15424 W Sunset Blvd",
    "sg:city":"Pacific Plsds",
    "sg:classifiers":[
        {
            "category":"Food & Beverages",
            "subcategory":"Bakery",
            "type":"Retail Goods"
        }
    ],
    "sg:phone":"+1 310 459 6093",
    "sg:postcode":"90272",
    "sg:province":"CA",
    "sg:tags":[
        "baker"
    ],
    "wof:name":"Viktor Benes Continental Bkry",
    "wof:placetype":"venue"
},
  "geometry": {"coordinates":[-118.528975,34.049457],"type":"Point"}
}