{
  "type": "Feature",
  "properties": {
    "addr:full":"111 N Long Beach Blvd Long Beach CA 90802",
    "addr:housenumber":"111",
    "addr:postcode":"90802",
    "addr:street":"N Long Beach Blvd",
    "iso:country":"US",
    "sg:address":"111 N Long Beach Blvd",
    "sg:city":"Long Beach",
    "sg:classifiers":[
        {
            "category":"Professional",
            "subcategory":"Business Services",
            "type":"Services"
        }
    ],
    "sg:phone":"+1 562 366 0620",
    "sg:postcode":"90802",
    "sg:province":"CA",
    "sg:tags":[
        "motion",
        "equipment",
        "re"
    ],
    "wof:name":"Caribiner Group The",
    "wof:placetype":"venue"
},
  "geometry": {"coordinates":[-118.18944999999999,33.768489],"type":"Point"}
}