{
  "type": "Feature",
  "properties": {
    "addr:full":"314 Miller Ave Mill Valley CA 94941",
    "addr:housenumber":"314",
    "addr:postcode":"94941",
    "addr:street":"Miller Ave",
    "iso:country":"US",
    "sg:address":"314 Miller Ave",
    "sg:city":"Mill Valley",
    "sg:classifiers":[
        {
            "category":"Sports & Exercise",
            "subcategory":"Gym",
            "type":"Entertainment"
        }
    ],
    "sg:phone":"+1 415 380 1866",
    "sg:postcode":"94941",
    "sg:province":"CA",
    "sg:tags":[
        "spa",
        "health"
    ],
    "wof:name":"Loyalty Spa",
    "wof:placetype":"venue"
},
  "geometry": {"coordinates":[-122.53815,37.89839],"type":"Point"}
}