{
  "type": "Feature",
  "properties": {
    "iso:country":"US",
    "sg:address":"632 E Colorado St",
    "sg:city":"Glendale",
    "sg:classifiers":[
        {
            "category":"Personal",
            "subcategory":"Beauty Salon",
            "type":"Services"
        }
    ],
    "sg:phone":"+1 818 246 0259",
    "sg:postcode":"91205",
    "sg:province":"CA",
    "wof:name":"Lora Kang Beauty Salon",
    "wof:placetype":"venue"
},
  "geometry": {"coordinates":[-118.246981,34.142598],"type":"Point"}
}