{
  "type": "Feature",
  "properties": {
    "addr:full":"1907 Yolo Ave Berkeley CA 94707",
    "addr:housenumber":"1907",
    "addr:postcode":"94707",
    "addr:street":"Yolo Ave",
    "iso:country":"US",
    "sg:address":"1907 Yolo Ave",
    "sg:city":"Berkeley",
    "sg:classifiers":[
        {
            "category":"Building & Trades",
            "subcategory":"Construction",
            "type":"Services"
        }
    ],
    "sg:phone":"+1 510 524 1352",
    "sg:postcode":"94707",
    "sg:province":"CA",
    "sg:tags":[
        "house"
    ],
    "wof:name":"Trillia Construction",
    "wof:placetype":"venue"
},
  "geometry": {"coordinates":[-122.273674,37.88537],"type":"Point"}
}