{
  "type": "Feature",
  "properties": {
    "addr:full":"13626 Monte Vista Ave Chino CA 91710",
    "addr:housenumber":"13626",
    "addr:postcode":"91710",
    "addr:street":"Monte Vista Ave",
    "iso:country":"US",
    "sg:address":"13626 Monte Vista Ave",
    "sg:city":"Chino",
    "sg:classifiers":[
        {
            "category":"Wholesale",
            "subcategory":"Apparel",
            "type":"Manufacturing & Wholesale Goods"
        },
        {
            "category":"Manufacturing",
            "subcategory":"Rubber & Plastics",
            "type":"Manufacturing & Wholesale Goods"
        }
    ],
    "sg:phone":"+1 909 591 8900",
    "sg:postcode":"91710",
    "sg:province":"CA",
    "sg:tags":[
        "mfg",
        "protective",
        "shoes",
        "footwear"
    ],
    "wof:name":"Daedo America Corp",
    "wof:placetype":"venue"
},
  "geometry": {"coordinates":[-117.69797,34.005264],"type":"Point"}
}