{
  "type": "Feature",
  "properties": {
    "iso:country":"US",
    "sg:address":"568 E Main St",
    "sg:city":"Grass Valley",
    "sg:classifiers":[
        {
            "category":"Insurance",
            "subcategory":"Insurance Agent",
            "type":"Services"
        }
    ],
    "sg:phone":"+1 530 273 3335",
    "sg:postcode":"95945",
    "sg:province":"CA",
    "wof:name":"B U I Insurance",
    "wof:placetype":"venue"
},
  "geometry": {"coordinates":[-121.054007,39.223719],"type":"Point"}
}