{
  "type": "Feature",
  "properties": {
    "iso:country":"US",
    "sg:address":"5155 W Rosecrans Avenue Suite 238",
    "sg:city":"Hawthorne",
    "sg:classifiers":[
        {
            "category":"Shopping",
            "subcategory":"Computers & Home Electronics",
            "type":"Retail Goods"
        }
    ],
    "sg:phone":"+1 310 675 4500",
    "sg:postcode":"90250",
    "sg:province":"CA",
    "wof:name":"Planet Minidisc",
    "wof:placetype":"venue"
},
  "geometry": {"coordinates":[-118.368436,33.90193],"type":"Point"}
}