{
  "type": "Feature",
  "properties": {
    "addr:full":"938 Katie Hammond St Hanford CA 93230",
    "addr:housenumber":"938",
    "addr:postcode":"ca 93230",
    "addr:street":"Katie Hammond St",
    "iso:country":"US",
    "sg:address":"938 Katie Hammond St",
    "sg:city":"Hanford",
    "sg:classifiers":[
        {
            "category":"Education",
            "subcategory":"School",
            "type":"Public Place"
        }
    ],
    "sg:phone":"+1 559 585 3644",
    "sg:postcode":"93230",
    "sg:province":"CA",
    "sg:tags":[
        "elementary"
    ],
    "wof:name":"Hanford Elementary School District Transportation",
    "wof:placetype":"venue"
},
  "geometry": {"coordinates":[-119.63146999999999,36.337761],"type":"Point"}
}