{
  "type": "Feature",
  "properties": {
    "iso:country":"US",
    "sg:address":"27612 Escuna",
    "sg:city":"Mission Viejo",
    "sg:classifiers":[
        {
            "category":"Building & Trades",
            "subcategory":"Construction",
            "type":"Services"
        }
    ],
    "sg:phone":"+1 949 951 1900",
    "sg:postcode":"92692",
    "sg:province":"CA",
    "sg:tags":[
        "contractor"
    ],
    "wof:name":"All Glass",
    "wof:placetype":"venue"
},
  "geometry": {"coordinates":[-117.649314,33.630016],"type":"Point"}
}