{
  "type": "Feature",
  "properties": {
    "addr:full":"3172 Latham Ln El Dorado Hills CA 95762",
    "addr:housenumber":"3172",
    "addr:postcode":"95762",
    "addr:street":"Latham Ln",
    "iso:country":"US",
    "sg:address":"3172 Latham Ln",
    "sg:city":"El Dorado Hills",
    "sg:classifiers":[
        {
            "category":"Building & Trades",
            "subcategory":"Construction",
            "type":"Services"
        }
    ],
    "sg:phone":"+1 916 933 3199",
    "sg:postcode":"95762",
    "sg:province":"CA",
    "sg:tags":[
        "roofing",
        "contractor"
    ],
    "wof:name":"Lakehills Roofing Co",
    "wof:placetype":"venue"
},
  "geometry": {"coordinates":[-121.07901699999999,38.679367],"type":"Point"}
}