{
  "type": "Feature",
  "properties": {
    "iso:country":"US",
    "sg:address":"1875 S Bascom Ave",
    "sg:city":"Campbell",
    "sg:classifiers":[
        {
            "category":"Insurance",
            "subcategory":"Insurance Agent",
            "type":"Services"
        }
    ],
    "sg:phone":"+1 408 244 2501",
    "sg:postcode":"95008",
    "sg:province":"CA",
    "sg:tags":[
        "administrator"
    ],
    "wof:name":"CBS Administrators",
    "wof:placetype":"venue"
},
  "geometry": {"coordinates":[-121.931853,37.289367],"type":"Point"}
}