{
  "type": "Feature",
  "properties": {
    "addr:full":"201 N Robertson Blvd Beverly Hills CA 90211",
    "addr:housenumber":"201",
    "addr:postcode":"90211",
    "addr:street":"N Robertson Blvd",
    "iso:country":"US",
    "sg:address":"201 N Robertson Blvd",
    "sg:city":"Beverly Hills",
    "sg:classifiers":[
        {
            "category":"Professional",
            "subcategory":"Management & Consulting",
            "type":"Services"
        }
    ],
    "sg:phone":"+1 310 777 1100",
    "sg:postcode":"90211",
    "sg:province":"CA",
    "sg:tags":[
        "fuel"
    ],
    "wof:name":"Rozon Mercer Management",
    "wof:placetype":"venue"
},
  "geometry": {"coordinates":[-118.38372699999999,34.069683],"type":"Point"}
}