{
  "type": "Feature",
  "properties": {
    "iso:country":"US",
    "sg:address":"1540 S Coast Hwy",
    "sg:city":"Laguna Beach",
    "sg:classifiers":[
        {
            "category":"Organizations",
            "subcategory":"Professional Association",
            "type":"Services"
        }
    ],
    "sg:phone":"+1 949 464 9810",
    "sg:postcode":"92651",
    "sg:province":"CA",
    "wof:name":"International Society",
    "wof:placetype":"venue"
},
  "geometry": {"coordinates":[-117.773065,33.530413],"type":"Point"}
}