{
  "type": "Feature",
  "properties": {
    "addr:full":"340 Ritch St San Francisco CA 94107",
    "addr:housenumber":"340",
    "addr:postcode":"94107",
    "addr:street":"Ritch St",
    "iso:country":"US",
    "sg:address":"340 Ritch St",
    "sg:city":"San Francisco",
    "sg:classifiers":[
        {
            "category":"Utilities",
            "subcategory":"Telephone",
            "type":"Services"
        }
    ],
    "sg:phone":"+1 415 495 6535",
    "sg:postcode":"94107",
    "sg:province":"CA",
    "sg:tags":[
        "communications"
    ],
    "wof:name":"Beprivate",
    "wof:placetype":"venue"
},
  "geometry": {"coordinates":[-122.394369,37.779246],"type":"Point"}
}