{
  "type": "Feature",
  "properties": {
    "iso:country":"US",
    "sg:address":"2621 Pico Blvd",
    "sg:city":"Santa Monica",
    "sg:classifiers":[
        {
            "category":"Building & Trades",
            "subcategory":"Plumbing",
            "type":"Services"
        }
    ],
    "sg:phone":"+1 310 394 8514",
    "sg:postcode":"90405",
    "sg:province":"CA",
    "sg:tags":[
        "plumbing",
        "contractor"
    ],
    "wof:name":"Estep & Sons Plumbing",
    "wof:placetype":"venue"
},
  "geometry": {"coordinates":[-118.461654,34.023652],"type":"Point"}
}