{
  "type": "Feature",
  "properties": {
    "addr:full":"464 W 4th St San Bernardino CA 92401",
    "addr:housenumber":"464",
    "addr:postcode":"92401",
    "addr:street":"W 4Th St",
    "iso:country":"US",
    "sg:address":"464 W 4th St",
    "sg:city":"San Bernardino",
    "sg:classifiers":[
        {
            "category":"Government",
            "subcategory":"Office",
            "type":"Public Place"
        }
    ],
    "sg:phone":"+1 909 383 4176",
    "sg:postcode":"92401",
    "sg:province":"CA",
    "sg:tags":[
        "agency",
        "tax",
        "labor",
        "health",
        "licensing",
        "regulatory"
    ],
    "wof:name":"San Bernardino District Office",
    "wof:placetype":"venue"
},
  "geometry": {"coordinates":[-117.29362,34.106516],"type":"Point"}
}