{
  "type": "Feature",
  "properties": {
    "addr:full":"401 N Pass Ave Burbank CA 91505",
    "addr:housenumber":"401",
    "addr:postcode":"91505",
    "addr:street":"N Pass Ave",
    "iso:country":"US",
    "sg:address":"401 N Pass Ave",
    "sg:city":"Burbank",
    "sg:classifiers":[
        {
            "category":"Professional",
            "type":"Services"
        }
    ],
    "sg:phone":"+1 818 481 7272",
    "sg:postcode":"91505",
    "sg:province":"CA",
    "wof:name":"West Way",
    "wof:placetype":"venue"
},
  "geometry": {"coordinates":[-118.346096,34.156282],"type":"Point"}
}