{
  "type": "Feature",
  "properties": {
    "addr:full":"1955 Cable St San Diego CA 92107",
    "addr:housenumber":"1955",
    "addr:postcode":"92107",
    "addr:street":"Cable St",
    "iso:country":"US",
    "sg:address":"1955 Cable St",
    "sg:city":"San Diego",
    "sg:classifiers":[
        {
            "category":"Personal",
            "subcategory":"Day Spa",
            "type":"Services"
        }
    ],
    "sg:phone":"+1 619 861 8351",
    "sg:postcode":"92107",
    "sg:province":"CA",
    "sg:website":"www.thesanctuarytoday.com",
    "wof:name":"The Sanctuary",
    "wof:placetype":"venue"
},
  "geometry": {"coordinates":[-117.248313,32.746942],"type":"Point"}
}