{
  "type": "Feature",
  "properties": {
    "addr:full":"2449 Sonora Dr El Dorado Hills CA 95762",
    "addr:housenumber":"2449",
    "addr:postcode":"95762",
    "addr:street":"Sonora Dr",
    "iso:country":"US",
    "sg:address":"2449 Sonora Dr",
    "sg:city":"El Dorado Hills",
    "sg:classifiers":[
        {
            "category":"Manufacturing",
            "subcategory":"Aerospace",
            "type":"Manufacturing & Wholesale Goods"
        }
    ],
    "sg:phone":"+1 916 601 1501",
    "sg:postcode":"95762",
    "sg:province":"CA",
    "sg:tags":[
        "equipment",
        "aircraft",
        "parts",
        "mfg"
    ],
    "wof:name":"Optimet Corporation",
    "wof:placetype":"venue"
},
  "geometry": {"coordinates":[-121.07906800000001,38.706384],"type":"Point"}
}