{
  "type": "Feature",
  "properties": {
    "iso:country":"US",
    "sg:address":"1300 Woodland Ave",
    "sg:city":"Modesto",
    "sg:classifiers":[
        {
            "category":"Building & Trades",
            "subcategory":"Cleaning & Sanitation",
            "type":"Services"
        }
    ],
    "sg:phone":"+1 209 576 4060",
    "sg:postcode":"95351",
    "sg:province":"CA",
    "sg:tags":[
        "maintenance"
    ],
    "wof:name":"City of Modesto",
    "wof:placetype":"venue"
},
  "geometry": {"coordinates":[-121.02866299999999,37.653217],"type":"Point"}
}