{
  "type": "Feature",
  "properties": {
    "iso:country":"US",
    "sg:address":"3700 Inland Empire Blvd",
    "sg:city":"Ontario",
    "sg:classifiers":[
        {
            "category":"Education",
            "subcategory":"College",
            "type":"Public Place"
        }
    ],
    "sg:phone":"+1 909 941 9410",
    "sg:postcode":"91764",
    "sg:province":"CA",
    "sg:tags":[
        "academic",
        "school"
    ],
    "sg:website":"www.plattcollege.edu",
    "wof:name":"Platt College Ontario",
    "wof:placetype":"venue"
},
  "geometry": {"coordinates":[-117.563029,34.068995],"type":"Point"}
}