{
  "type": "Feature",
  "properties": {
    "iso:country":"US",
    "sg:address":"14328 Victory Blvd",
    "sg:city":"Van Nuys",
    "sg:classifiers":[
        {
            "category":"Professional",
            "subcategory":"Printing & Photocopies",
            "type":"Services"
        }
    ],
    "sg:phone":"+1 818 779 0779",
    "sg:postcode":"91401",
    "sg:province":"CA",
    "sg:tags":[
        "duplicating",
        "copying"
    ],
    "wof:name":"Platinum Copy",
    "wof:placetype":"venue"
},
  "geometry": {"coordinates":[-118.446015,34.186587],"type":"Point"}
}