{
  "type": "Feature",
  "properties": {
    "addr:full":"7252 N Lake Blvd Tahoe Vista CA 96148",
    "addr:housenumber":"7252",
    "addr:postcode":"96148",
    "addr:street":"N Lake Blvd",
    "iso:country":"US",
    "sg:address":"7252 N Lake Blvd",
    "sg:city":"Tahoe Vista",
    "sg:classifiers":[
        {
            "category":"Personal",
            "subcategory":"Beauty Salon",
            "type":"Services"
        }
    ],
    "sg:phone":"+1 530 546 2161",
    "sg:postcode":"96148",
    "sg:province":"CA",
    "wof:name":"Japanese Facial Message",
    "wof:placetype":"venue"
},
  "geometry": {"coordinates":[-120.042108,39.23853],"type":"Point"}
}