{
  "type": "Feature",
  "properties": {
    "addr:full":"132 Peabody Rd Vacaville CA 95687",
    "addr:housenumber":"132",
    "addr:postcode":"95687",
    "addr:street":"Peabody Rd",
    "iso:country":"US",
    "sg:address":"132 Peabody Rd",
    "sg:city":"Vacaville",
    "sg:classifiers":[
        {
            "category":"Social Services",
            "type":"Services"
        }
    ],
    "sg:phone":"+1 707 454 0268",
    "sg:postcode":"95687",
    "sg:province":"CA",
    "sg:tags":[
        "organization",
        "welfare"
    ],
    "wof:name":"Vacaville Store House",
    "wof:placetype":"venue"
},
  "geometry": {"coordinates":[-121.976232,38.352263],"type":"Point"}
}