{
  "type": "Feature",
  "properties": {
    "addr:full":"153 N 12th St Santa Paula CA 93060",
    "addr:housenumber":"153",
    "addr:postcode":"93060",
    "addr:street":"N 12Th St",
    "iso:country":"US",
    "sg:address":"153 N 12th St",
    "sg:city":"Santa Paula",
    "sg:classifiers":[
        {
            "category":"Building & Trades",
            "subcategory":"Construction",
            "type":"Services"
        }
    ],
    "sg:phone":"+1 805 933 1054",
    "sg:postcode":"93060",
    "sg:province":"CA",
    "sg:tags":[
        "contractor"
    ],
    "wof:name":"Wild Wood Structures",
    "wof:placetype":"venue"
},
  "geometry": {"coordinates":[-119.056282,34.356094],"type":"Point"}
}