{
  "type": "Feature",
  "properties": {
    "addr:full":"23440 Hawthorne Blvd Torrance CA 90505",
    "addr:housenumber":"23440",
    "addr:postcode":"90505",
    "addr:street":"Hawthorne Blvd",
    "iso:country":"US",
    "sg:address":"23440 Hawthorne Blvd",
    "sg:city":"Torrance",
    "sg:classifiers":[
        {
            "category":"Wholesale",
            "subcategory":"Durable Goods & Equipment",
            "type":"Manufacturing & Wholesale Goods"
        }
    ],
    "sg:phone":"+1 310 791 5700",
    "sg:postcode":"90505",
    "sg:province":"CA",
    "sg:tags":[
        "exporter"
    ],
    "sg:website":"www.pushpaamerica.com",
    "wof:name":"Pushpa America Corp",
    "wof:placetype":"venue"
},
  "geometry": {"coordinates":[-118.35092299999999,33.812969],"type":"Point"}
}