{
  "type": "Feature",
  "properties": {
    "addr:full":"2900 Lakeside Drive Suite 100 Santa Clara CA 95054",
    "addr:housenumber":"2900",
    "addr:postcode":"95054",
    "addr:street":"Lakeside Drive Suite 100",
    "iso:country":"US",
    "sg:address":"2900 Lakeside Drive Suite 100",
    "sg:city":"Santa Clara",
    "sg:classifiers":[
        {
            "category":"Manufacturing",
            "subcategory":"Electronics",
            "type":"Manufacturing & Wholesale Goods"
        }
    ],
    "sg:phone":"+1 408 869 4000",
    "sg:postcode":"95054",
    "sg:province":"CA",
    "wof:name":"Mobilygen",
    "wof:placetype":"venue"
},
  "geometry": {"coordinates":[-121.98392,37.38728],"type":"Point"}
}