{
  "type": "Feature",
  "properties": {
    "iso:country":"US",
    "sg:address":"404 N Grand Ave",
    "sg:city":"Santa Ana",
    "sg:classifiers":[
        {
            "category":"Restaurant",
            "type":"Food & Drink"
        }
    ],
    "sg:phone":"+1 714 836 4409",
    "sg:postcode":"92701",
    "sg:province":"CA",
    "sg:tags":[
        "american",
        "latin"
    ],
    "wof:name":"Birrieria & Pupuseria Jalisco",
    "wof:placetype":"venue"
},
  "geometry": {"coordinates":[-117.852002,33.748413],"type":"Point"}
}