{
  "type": "Feature",
  "properties": {
    "iso:country":"US",
    "sg:address":"851 N San Mateo Dr",
    "sg:city":"San Mateo",
    "sg:classifiers":[
        {
            "category":"Professional",
            "type":"Services"
        }
    ],
    "sg:phone":"+1 650 343 3948",
    "sg:postcode":"94401",
    "sg:province":"CA",
    "wof:name":"Tek Elements Inc",
    "wof:placetype":"venue"
},
  "geometry": {"coordinates":[-122.338249,37.576427],"type":"Point"}
}