{
  "type": "Feature",
  "properties": {
    "iso:country":"US",
    "sg:address":"578 14th St",
    "sg:city":"Oakland",
    "sg:classifiers":[
        {
            "category":"Restaurant",
            "type":"Food & Drink"
        }
    ],
    "sg:phone":"+1 510 834 0910",
    "sg:postcode":"94612",
    "sg:province":"CA",
    "sg:tags":[
        "chinese"
    ],
    "wof:name":"Savannah's Place",
    "wof:placetype":"venue"
},
  "geometry": {"coordinates":[-122.274002,37.805599],"type":"Point"}
}