{
  "type": "Feature",
  "properties": {
    "addr:full":"1559 E Amar Rd West Covina CA 91792",
    "addr:housenumber":"1559",
    "addr:postcode":"91792",
    "addr:street":"E Amar Rd",
    "iso:country":"US",
    "sg:address":"1559 E Amar Rd",
    "sg:city":"West Covina",
    "sg:classifiers":[
        {
            "category":"Professional",
            "type":"Services"
        }
    ],
    "sg:phone":"+1 626 839 9815",
    "sg:postcode":"91792",
    "sg:province":"CA",
    "wof:name":"Lola Kusina Ni",
    "wof:placetype":"venue"
},
  "geometry": {"coordinates":[-117.9145,34.031265],"type":"Point"}
}