{
  "type": "Feature",
  "properties": {
    "iso:country":"US",
    "sg:address":"423 Center St",
    "sg:city":"Redwood City",
    "sg:classifiers":[
        {
            "category":"Building & Trades",
            "subcategory":"Plumbing",
            "type":"Services"
        }
    ],
    "sg:phone":"+1 650 366 8582",
    "sg:postcode":"94061",
    "sg:province":"CA",
    "sg:tags":[
        "contractor"
    ],
    "wof:name":"Pride Systems Heating & Rfrgn",
    "wof:placetype":"venue"
},
  "geometry": {"coordinates":[-122.221447,37.469605],"type":"Point"}
}