{
  "type": "Feature",
  "properties": {
    "iso:country":"US",
    "sg:address":"655 S State College Blvd",
    "sg:city":"Fullerton",
    "sg:classifiers":[
        {
            "category":"Building & Trades",
            "subcategory":"Construction",
            "type":"Services"
        }
    ],
    "sg:phone":"+1 714 526 2703",
    "sg:postcode":"92831",
    "sg:province":"CA",
    "sg:tags":[
        "painter"
    ],
    "wof:name":"E & J Painting",
    "wof:placetype":"venue"
},
  "geometry": {"coordinates":[-117.889999,33.8657],"type":"Point"}
}