{
  "type": "Feature",
  "properties": {
    "iso:country":"US",
    "sg:address":"807 Inglewood Ave",
    "sg:city":"Redondo Beach",
    "sg:classifiers":[
        {
            "category":"Park",
            "type":"Public Place"
        }
    ],
    "sg:postcode":"90278",
    "sg:province":"CA",
    "wof:name":"Franklin Park",
    "wof:placetype":"venue"
},
  "geometry": {"coordinates":[-118.361178,33.861314],"type":"Point"}
}