{
  "type": "Feature",
  "properties": {
    "iso:country":"US",
    "sg:address":"4452 Mission St",
    "sg:city":"San Francisco",
    "sg:classifiers":[
        {
            "category":"Retail",
            "subcategory":"Repair Shop",
            "type":"Services"
        }
    ],
    "sg:phone":"+1 415 337 0708",
    "sg:postcode":"94112",
    "sg:province":"CA",
    "sg:tags":[
        "lock",
        "key",
        "locksmith"
    ],
    "wof:name":"Mario's Locksmith",
    "wof:placetype":"venue"
},
  "geometry": {"coordinates":[-122.43355,37.72637],"type":"Point"}
}