{
  "type": "Feature",
  "properties": {
    "addr:full":"4304 Z St San Diego CA 92113",
    "addr:housenumber":"4304",
    "addr:postcode":"92113",
    "addr:street":"Z St",
    "iso:country":"US",
    "sg:address":"4304 Z St",
    "sg:city":"San Diego",
    "sg:classifiers":[
        {
            "category":"Real Estate",
            "subcategory":"Real Estate Agent",
            "type":"Services"
        }
    ],
    "sg:phone":"+1 619 264 0149",
    "sg:postcode":"92113",
    "sg:province":"CA",
    "wof:name":"S & S Realty Assoc",
    "wof:placetype":"venue"
},
  "geometry": {"coordinates":[-117.100238,32.692699],"type":"Point"}
}