{
  "type": "Feature",
  "properties": {
    "addr:full":"5059 Rebel Ct San Jose CA 95118",
    "addr:housenumber":"5059",
    "addr:postcode":"95118",
    "addr:street":"Rebel Ct",
    "iso:country":"US",
    "sg:address":"5059 Rebel Ct",
    "sg:city":"San Jose",
    "sg:classifiers":[
        {
            "category":"Insurance",
            "subcategory":"Insurance Agent",
            "type":"Services"
        }
    ],
    "sg:phone":"+1 408 445 3095",
    "sg:postcode":"95118",
    "sg:province":"CA",
    "wof:name":"California Southwestern Ins",
    "wof:placetype":"venue"
},
  "geometry": {"coordinates":[-121.903381,37.249634],"type":"Point"}
}