{
  "type": "Feature",
  "properties": {
    "iso:country":"US",
    "sg:address":"888 S Bethel Ave",
    "sg:city":"Sanger",
    "sg:classifiers":[
        {
            "category":"Building & Trades",
            "subcategory":"Cleaning & Sanitation",
            "type":"Services"
        }
    ],
    "sg:phone":"+1 559 875 1551",
    "sg:postcode":"93657",
    "sg:province":"CA",
    "sg:tags":[
        "property",
        "maintenance"
    ],
    "wof:name":"GSS Property Inc",
    "wof:placetype":"venue"
},
  "geometry": {"coordinates":[-119.574096,36.722992],"type":"Point"}
}