{
  "type": "Feature",
  "properties": {
    "addr:full":"1177 Yocum St Pasadena CA 91103",
    "addr:housenumber":"1177",
    "addr:postcode":"91103",
    "addr:street":"Yocum St",
    "iso:country":"US",
    "sg:address":"1177 Yocum St",
    "sg:city":"Pasadena",
    "sg:classifiers":[
        {
            "category":"Wholesale",
            "subcategory":"Machinery & Supplies",
            "type":"Manufacturing & Wholesale Goods"
        }
    ],
    "sg:phone":"+1 626 396 3908",
    "sg:postcode":"91103",
    "sg:province":"CA",
    "sg:tags":[
        "equipment",
        "veterinarian"
    ],
    "wof:name":"Ogden Equine",
    "wof:placetype":"venue"
},
  "geometry": {"coordinates":[-118.175743,34.172691],"type":"Point"}
}