{
  "type": "Feature",
  "properties": {
    "iso:country":"US",
    "sg:address":"210 Estates Dr",
    "sg:city":"Roseville",
    "sg:classifiers":[
        {
            "category":"Professional",
            "subcategory":"Engineering",
            "type":"Services"
        }
    ],
    "sg:phone":"+1 916 789 9300",
    "sg:postcode":"95678",
    "sg:province":"CA",
    "sg:tags":[
        "engineer"
    ],
    "wof:name":"Watson Engineering Inc",
    "wof:placetype":"venue"
},
  "geometry": {"coordinates":[-121.272108,38.747058],"type":"Point"}
}