{
  "type": "Feature",
  "properties": {
    "addr:full":"490 Broadway San Francisco CA 94133",
    "addr:housenumber":"490",
    "addr:postcode":"94133",
    "addr:street":"Broadway",
    "iso:country":"US",
    "sg:address":"490 Broadway",
    "sg:city":"San Francisco",
    "sg:classifiers":[
        {
            "category":"Travel",
            "subcategory":"Hostel",
            "type":"Entertainment"
        }
    ],
    "sg:phone":"+1 415 834 9060",
    "sg:postcode":"94133",
    "sg:province":"CA",
    "wof:name":"Green Tortoise Guest House",
    "wof:placetype":"venue"
},
  "geometry": {"coordinates":[-122.405377,37.798163],"type":"Point"}
}