{
  "type": "Feature",
  "properties": {
    "addr:full":"542 McGraw Ave Livermore CA 94551",
    "addr:housenumber":"542",
    "addr:postcode":"94551",
    "addr:street":"Mcgraw Ave",
    "iso:country":"US",
    "sg:address":"542 McGraw Ave",
    "sg:city":"Livermore",
    "sg:classifiers":[
        {
            "category":"Wholesale",
            "subcategory":"Metals & Minerals",
            "type":"Manufacturing & Wholesale Goods"
        }
    ],
    "sg:phone":"+1 925 449 6999",
    "sg:postcode":"94551",
    "sg:province":"CA",
    "sg:tags":[
        "concrete",
        "reinforcement"
    ],
    "sg:website":"www.missioncityrebar.com",
    "wof:name":"Mission City Rebar Inc",
    "wof:placetype":"venue"
},
  "geometry": {"coordinates":[-121.735708,37.702658],"type":"Point"}
}