{
  "type": "Feature",
  "properties": {
    "addr:full":"490 Geary Street San Francisco CA 94102",
    "addr:housenumber":"490",
    "addr:postcode":"94102",
    "addr:street":"Geary Street",
    "iso:country":"US",
    "sg:address":"490 Geary Street",
    "sg:city":"San Francisco",
    "sg:classifiers":[
        {
            "category":"Travel",
            "subcategory":"Hotels & Motels",
            "type":"Entertainment"
        }
    ],
    "sg:phone":"+1 415 928 7900",
    "sg:postcode":"94102",
    "sg:province":"CA",
    "wof:name":"San Francisco Accommodations",
    "wof:placetype":"venue"
},
  "geometry": {"coordinates":[-122.41100299999999,37.787102],"type":"Point"}
}