{
  "type": "Feature",
  "properties": {
    "iso:country":"US",
    "sg:address":"22945 Savi Ranch Pkwy",
    "sg:city":"Yorba Linda",
    "sg:classifiers":[
        {
            "category":"Retail",
            "subcategory":"Auto Repair",
            "type":"Services"
        }
    ],
    "sg:phone":"+1 714 974 6647",
    "sg:postcode":"92887",
    "sg:province":"CA",
    "sg:website":"saviranchauto.com/",
    "wof:name":"Savi Ranch Automotive Full Service Automotive Shop",
    "wof:placetype":"venue"
},
  "geometry": {"coordinates":[-117.736097,33.874561],"type":"Point"}
}