{
  "type": "Feature",
  "properties": {
    "addr:full":"9055 Locust St Elk Grove CA 95624",
    "addr:housenumber":"9055",
    "addr:postcode":"95624",
    "addr:street":"Locust St",
    "iso:country":"US",
    "sg:address":"9055 Locust St",
    "sg:city":"Elk Grove",
    "sg:classifiers":[
        {
            "category":"Retail",
            "subcategory":"Auto Repair",
            "type":"Services"
        }
    ],
    "sg:phone":"+1 916 685 6763",
    "sg:postcode":"95624",
    "sg:province":"CA",
    "sg:tags":[
        "body",
        "automobile",
        "painting"
    ],
    "wof:name":"Aello Auto Paint & Customz",
    "wof:placetype":"venue"
},
  "geometry": {"coordinates":[-121.363252,38.410199],"type":"Point"}
}