{
  "type": "Feature",
  "properties": {
    "addr:full":"928 S Western Ave Los Angeles CA 90006",
    "addr:housenumber":"928",
    "addr:postcode":"90006",
    "addr:street":"S Western Ave",
    "iso:country":"US",
    "sg:address":"928 S Western Ave",
    "sg:city":"Los Angeles",
    "sg:classifiers":[
        {
            "category":"Shopping",
            "subcategory":"Optician",
            "type":"Retail Goods"
        },
        {
            "category":"Health Services",
            "subcategory":"Clinic",
            "type":"Services"
        }
    ],
    "sg:phone":"+1 213 385 9100",
    "sg:postcode":"90006",
    "sg:province":"CA",
    "sg:tags":[
        "medical",
        "eyewear"
    ],
    "sg:website":"www.italee.com/index.html",
    "wof:name":"Italee Optometry",
    "wof:placetype":"venue"
},
  "geometry": {"coordinates":[-118.308426,34.055136],"type":"Point"}
}