{
  "type": "Feature",
  "properties": {
    "iso:country":"US",
    "sg:address":"801 K St",
    "sg:city":"Sacramento",
    "sg:classifiers":[
        {
            "category":"Professional",
            "subcategory":"Lawyer & Legal Services",
            "type":"Services"
        }
    ],
    "sg:phone":"+1 916 442 2910",
    "sg:postcode":"95814",
    "sg:province":"CA",
    "sg:tags":[
        "attorney",
        "criminal",
        "law"
    ],
    "wof:name":"Julian G Macias",
    "wof:placetype":"venue"
},
  "geometry": {"coordinates":[-121.496613,38.579929],"type":"Point"}
}