{
  "type": "Feature",
  "properties": {
    "addr:full":"920 Los Robles Blvd Sacramento CA 95838",
    "addr:housenumber":"920",
    "addr:postcode":"95838",
    "addr:street":"Los Robles Blvd",
    "iso:country":"US",
    "sg:address":"920 Los Robles Blvd",
    "sg:city":"Sacramento",
    "sg:classifiers":[
        {
            "category":"Organizations",
            "subcategory":"Religious Organization",
            "type":"Services"
        }
    ],
    "sg:phone":"+1 916 925 8151",
    "sg:postcode":"95838",
    "sg:province":"CA",
    "sg:tags":[
        "church"
    ],
    "wof:name":"Pilgrim's Rest Church Of God",
    "wof:placetype":"venue"
},
  "geometry": {"coordinates":[-121.44474,38.629408],"type":"Point"}
}