{
  "type": "Feature",
  "properties": {
    "addr:full":"15 Crow Canyon Ct San Ramon CA 94583",
    "addr:housenumber":"15",
    "addr:postcode":"94583",
    "addr:street":"Crow Canyon Ct",
    "iso:country":"US",
    "sg:address":"15 Crow Canyon Ct",
    "sg:city":"San Ramon",
    "sg:classifiers":[
        {
            "category":"Travel",
            "subcategory":"Travel Agent",
            "type":"Entertainment"
        }
    ],
    "sg:phone":"+1 925 831 8103",
    "sg:postcode":"94583",
    "sg:province":"CA",
    "sg:tags":[
        "agency",
        "bureau"
    ],
    "sg:website":"www.vacationdiscounters.net",
    "wof:name":"Vacation Discounters Inc",
    "wof:placetype":"venue"
},
  "geometry": {"coordinates":[-121.981486,37.777362],"type":"Point"}
}