{
  "type": "Feature",
  "properties": {
    "iso:country":"US",
    "sg:address":"107 S Kenwood St",
    "sg:city":"Glendale",
    "sg:classifiers":[
        {
            "category":"Utilities",
            "subcategory":"Mobile Phone",
            "type":"Services"
        }
    ],
    "sg:phone":"+1 818 550 1954",
    "sg:postcode":"91205",
    "sg:province":"CA",
    "sg:tags":[
        "communication",
        "radiotelephone"
    ],
    "wof:name":"Armnet",
    "wof:placetype":"venue"
},
  "geometry": {"coordinates":[-118.25141000000001,34.144583],"type":"Point"}
}