{
  "type": "Feature",
  "properties": {
    "addr:full":"168 N Main St Porterville CA 93257",
    "addr:housenumber":"168",
    "addr:postcode":"93257",
    "addr:street":"N Main St",
    "iso:country":"US",
    "sg:address":"168 N Main St",
    "sg:city":"Porterville",
    "sg:classifiers":[
        {
            "category":"Shopping",
            "subcategory":"Clothing, Apparel, & Fashions",
            "type":"Retail Goods"
        }
    ],
    "sg:phone":"+1 559 791 0633",
    "sg:postcode":"93257",
    "sg:province":"CA",
    "wof:name":"Leticia's Boutique",
    "wof:placetype":"venue"
},
  "geometry": {"coordinates":[-119.016188,36.068285],"type":"Point"}
}