{
  "type": "Feature",
  "properties": {
    "iso:country":"US",
    "sg:address":"1011 I St",
    "sg:city":"Los Banos",
    "sg:classifiers":[
        {
            "category":"Organizations",
            "subcategory":"Religious Organization",
            "type":"Services"
        }
    ],
    "sg:phone":"+1 209 827 1079",
    "sg:postcode":"93635",
    "sg:province":"CA",
    "sg:tags":[
        "church"
    ],
    "wof:name":"Praise Fellowship",
    "wof:placetype":"venue"
},
  "geometry": {"coordinates":[-120.84209300000001,37.058211],"type":"Point"}
}