{
  "type": "Feature",
  "properties": {
    "iso:country":"US",
    "sg:address":"845 Marie Ave",
    "sg:city":"Martinez",
    "sg:classifiers":[
        {
            "category":"Real Estate",
            "subcategory":"Real Estate Services",
            "type":"Services"
        },
        {
            "category":"Real Estate",
            "subcategory":"Real Estate Agent",
            "type":"Services"
        }
    ],
    "sg:phone":"+1 925 228 0421",
    "sg:postcode":"94553",
    "sg:province":"CA",
    "sg:tags":[
        "buyer",
        "broker"
    ],
    "wof:name":"Tom Flynn Realty",
    "wof:placetype":"venue"
},
  "geometry": {"coordinates":[-122.106145,38.003527],"type":"Point"}
}