{
  "type": "Feature",
  "properties": {
    "addr:full":"2022 Cliff Dr Santa Barbara CA 93109",
    "addr:housenumber":"2022",
    "addr:postcode":"93109",
    "addr:street":"Cliff Dr",
    "iso:country":"US",
    "sg:address":"2022 Cliff Dr",
    "sg:city":"Santa Barbara",
    "sg:classifiers":[
        {
            "category":"Professional",
            "subcategory":"Management & Consulting",
            "type":"Services"
        }
    ],
    "sg:phone":"+1 805 341 9995",
    "sg:postcode":"93109",
    "sg:province":"CA",
    "wof:name":"Tc Technology",
    "wof:placetype":"venue"
},
  "geometry": {"coordinates":[-119.725838,34.402455],"type":"Point"}
}