{
  "type": "Feature",
  "properties": {
    "iso:country":"US",
    "sg:address":"561 East St",
    "sg:city":"Hollister",
    "sg:classifiers":[
        {
            "category":"Autos & Motor Vehicles",
            "subcategory":"Auto Supplies",
            "type":"Retail Goods"
        }
    ],
    "sg:phone":"+1 831 636 1072",
    "sg:postcode":"95023",
    "sg:province":"CA",
    "sg:tags":[
        "repair",
        "part",
        "mfg",
        "automobile"
    ],
    "wof:name":"Autoworks",
    "wof:placetype":"venue"
},
  "geometry": {"coordinates":[-121.401008,36.850653],"type":"Point"}
}