{
  "type": "Feature",
  "properties": {
    "iso:country":"US",
    "sg:address":"2786 Fruitridge Rd",
    "sg:city":"Sacramento",
    "sg:classifiers":[
        {
            "category":"Organizations",
            "subcategory":"Non-profit Organization",
            "type":"Services"
        }
    ],
    "sg:phone":"+1 916 424 0819",
    "sg:postcode":"95820",
    "sg:province":"CA",
    "sg:tags":[
        "information",
        "alcoholism",
        "treatment"
    ],
    "wof:name":"Group Fe Y Esperanza",
    "wof:placetype":"venue"
},
  "geometry": {"coordinates":[-121.478919,38.524761],"type":"Point"}
}