{
  "type": "Feature",
  "properties": {
    "addr:full":"1540 W 107th St Los Angeles CA 90047",
    "addr:housenumber":"1540",
    "addr:postcode":"90047",
    "addr:street":"W 107Th St",
    "iso:country":"US",
    "sg:address":"1540 W 107th St",
    "sg:city":"Los Angeles",
    "sg:classifiers":[
        {
            "category":"Professional",
            "type":"Services"
        }
    ],
    "sg:phone":"+1 323 242 1765",
    "sg:postcode":"90047",
    "sg:province":"CA",
    "sg:tags":[
        "establishment"
    ],
    "wof:name":"Fncf Community Developmentl",
    "wof:placetype":"venue"
},
  "geometry": {"coordinates":[-118.30208399999999,33.939048],"type":"Point"}
}