{
  "type": "Feature",
  "properties": {
    "iso:country":"US",
    "sg:address":"5122 Bolsa Ave",
    "sg:city":"Huntington Beach",
    "sg:classifiers":[
        {
            "category":"Manufacturing",
            "subcategory":"Metals",
            "type":"Manufacturing & Wholesale Goods"
        }
    ],
    "sg:phone":"+1 714 898 7585",
    "sg:postcode":"92649",
    "sg:province":"CA",
    "sg:tags":[
        "hardware",
        "mfg"
    ],
    "wof:name":"Global Slide",
    "wof:placetype":"venue"
},
  "geometry": {"coordinates":[-118.038956,33.744249],"type":"Point"}
}