{
  "type": "Feature",
  "properties": {
    "iso:country":"US",
    "sg:address":"13566 Glenoaks Blvd",
    "sg:city":"Sylmar",
    "sg:classifiers":[
        {
            "category":"Food & Beverages",
            "subcategory":"Meat & Fish",
            "type":"Retail Goods"
        }
    ],
    "sg:phone":"+1 818 367 5555",
    "sg:postcode":"91342",
    "sg:province":"CA",
    "wof:name":"Rodolfo Ruiz",
    "wof:placetype":"venue"
},
  "geometry": {"coordinates":[-118.465272,34.319682],"type":"Point"}
}