{
  "type": "Feature",
  "properties": {
    "iso:country":"US",
    "sg:address":"10028 Orcas Way",
    "sg:city":"Lakeside",
    "sg:classifiers":[
        {
            "category":"Wholesale",
            "subcategory":"Auto Parts",
            "type":"Manufacturing & Wholesale Goods"
        }
    ],
    "sg:phone":"+1 619 443 9886",
    "sg:postcode":"92040",
    "sg:province":"CA",
    "sg:tags":[
        "turbochargers"
    ],
    "wof:name":"Toby's Turbos",
    "wof:placetype":"venue"
},
  "geometry": {"coordinates":[-116.907231,32.862515],"type":"Point"}
}