{
  "type": "Feature",
  "properties": {
    "addr:full":"200 S Hill St Los Angeles CA 90012",
    "addr:housenumber":"200",
    "addr:postcode":"90012",
    "addr:street":"S Hill St",
    "iso:country":"US",
    "sg:address":"200 S Hill St",
    "sg:city":"Los Angeles",
    "sg:classifiers":[
        {
            "category":"Travel",
            "subcategory":"Hotels & Motels",
            "type":"Entertainment"
        }
    ],
    "sg:phone":"+1 213 621 4455",
    "sg:postcode":"90012",
    "sg:province":"CA",
    "sg:website":"www.kawadahotel.com",
    "wof:name":"Kawada Hotel",
    "wof:placetype":"venue"
},
  "geometry": {"coordinates":[-118.249089,34.051657],"type":"Point"}
}