{
  "type": "Feature",
  "properties": {
    "iso:country":"US",
    "sg:address":"1999 W Arrow Rte",
    "sg:city":"Upland",
    "sg:classifiers":[
        {
            "category":"Shopping",
            "subcategory":"Books",
            "type":"Retail Goods"
        }
    ],
    "sg:phone":"+1 909 920 1135",
    "sg:postcode":"91786",
    "sg:province":"CA",
    "sg:tags":[
        "dealer"
    ],
    "wof:name":"Toy Box",
    "wof:placetype":"venue"
},
  "geometry": {"coordinates":[-117.68839,34.099593],"type":"Point"}
}