{
  "type": "Feature",
  "properties": {
    "iso:country":"US",
    "sg:address":"6125 Fulton Ave",
    "sg:city":"Van Nuys",
    "sg:classifiers":[
        {
            "category":"Real Estate",
            "subcategory":"Real Estate Operator",
            "type":"Services"
        }
    ],
    "sg:phone":"+1 818 787 1865",
    "sg:postcode":"91401",
    "sg:province":"CA",
    "sg:tags":[
        "apartment"
    ],
    "wof:name":"Fulton Pointe Apartments",
    "wof:placetype":"venue"
},
  "geometry": {"coordinates":[-118.422997,34.181599],"type":"Point"}
}