{
  "type": "Feature",
  "properties": {
    "iso:country":"US",
    "sg:address":"5333 Topanga Canyon Blvd",
    "sg:city":"Woodland Hills",
    "sg:classifiers":[
        {
            "category":"Retail",
            "subcategory":"Auto Repair",
            "type":"Services"
        }
    ],
    "sg:phone":"+1 818 999 5550",
    "sg:postcode":"91364",
    "sg:province":"CA",
    "sg:tags":[
        "body",
        "automobile",
        "painting"
    ],
    "wof:name":"Topanga Auto Body Inc",
    "wof:placetype":"venue"
},
  "geometry": {"coordinates":[-118.606003,34.167099],"type":"Point"}
}