{
  "type": "Feature",
  "properties": {
    "addr:full":"895 Luxury Dr Concord CA 94518",
    "addr:housenumber":"895",
    "addr:postcode":"94518",
    "addr:street":"Luxury Dr",
    "iso:country":"US",
    "sg:address":"895 Luxury Dr",
    "sg:city":"Concord",
    "sg:classifiers":[
        {
            "category":"Banks & Credit Unions",
            "subcategory":"Financial Services",
            "type":"Services"
        }
    ],
    "sg:phone":"+1 925 687 1065",
    "sg:postcode":"94518",
    "sg:province":"CA",
    "sg:tags":[
        "trust",
        "management"
    ],
    "wof:name":"D J Canty Estate",
    "wof:placetype":"venue"
},
  "geometry": {"coordinates":[-122.023156,37.950957],"type":"Point"}
}