{
  "type": "Feature",
  "properties": {
    "iso:country":"US",
    "sg:address":"43172 Christy St",
    "sg:city":"Fremont",
    "sg:classifiers":[
        {
            "category":"Shopping",
            "subcategory":"Computers & Home Electronics",
            "type":"Retail Goods"
        }
    ],
    "sg:phone":"+1 510 623 2329",
    "sg:postcode":"94538",
    "sg:province":"CA",
    "sg:tags":[
        "equipment",
        "dealer"
    ],
    "sg:website":"www.starmicrotech.com",
    "wof:name":"Star Micro Technologies Inc",
    "wof:placetype":"venue"
},
  "geometry": {"coordinates":[-121.972813,37.50651],"type":"Point"}
}