{
  "type": "Feature",
  "properties": {
    "addr:full":"5757 W Century Blvd Los Angeles CA 90045",
    "addr:housenumber":"5757",
    "addr:postcode":"90045",
    "addr:street":"W Century Blvd",
    "iso:country":"US",
    "sg:address":"5757 W Century Blvd",
    "sg:city":"Los Angeles",
    "sg:classifiers":[
        {
            "category":"Professional",
            "subcategory":"Lawyer & Legal Services",
            "type":"Services"
        }
    ],
    "sg:phone":"+1 310 649 3141",
    "sg:postcode":"90045",
    "sg:province":"CA",
    "sg:tags":[
        "attorney"
    ],
    "sg:website":"www.akleinlaw.com",
    "wof:name":"Alan M Klein Law Offices",
    "wof:placetype":"venue"
},
  "geometry": {"coordinates":[-118.382605,33.945637],"type":"Point"}
}