{
  "type": "Feature",
  "properties": {
    "iso:country":"US",
    "sg:address":"117 Belmont Ave",
    "sg:city":"Long Beach",
    "sg:classifiers":[
        {
            "category":"Manufacturing",
            "subcategory":"Watercraft",
            "type":"Manufacturing & Wholesale Goods"
        }
    ],
    "sg:phone":"+1 562 438 4543",
    "sg:postcode":"90803",
    "sg:province":"CA",
    "wof:name":"Pro Yacht",
    "wof:placetype":"venue"
},
  "geometry": {"coordinates":[-118.144886,33.762123],"type":"Point"}
}