{
  "type": "Feature",
  "properties": {
    "iso:country":"US",
    "sg:address":"15542 La Mirada Blvd",
    "sg:city":"La Mirada",
    "sg:classifiers":[
        {
            "category":"Personal",
            "subcategory":"Beauty Salon",
            "type":"Services"
        }
    ],
    "sg:phone":"+1 714 522 4065",
    "sg:postcode":"90638",
    "sg:province":"CA",
    "sg:tags":[
        "hair"
    ],
    "wof:name":"Julian Hair Studio",
    "wof:placetype":"venue"
},
  "geometry": {"coordinates":[-118.00111800000001,33.8904],"type":"Point"}
}