{
  "type": "Feature",
  "properties": {
    "iso:country":"US",
    "sg:address":"2521 Miller Ave",
    "sg:city":"Modesto",
    "sg:classifiers":[
        {
            "category":"Building & Trades",
            "subcategory":"Cleaning & Sanitation",
            "type":"Services"
        }
    ],
    "sg:phone":"+1 209 323 2273",
    "sg:postcode":"95354",
    "sg:province":"CA",
    "sg:tags":[
        "cleaner",
        "pool"
    ],
    "wof:name":"Go Green Pool Cleaning Service",
    "wof:placetype":"venue"
},
  "geometry": {"coordinates":[-120.94901299999999,37.640883],"type":"Point"}
}