{
  "type": "Feature",
  "properties": {
    "addr:full":"386 S Tustin St Orange CA 92866",
    "addr:housenumber":"386",
    "addr:postcode":"92866",
    "addr:street":"S Tustin St",
    "iso:country":"US",
    "sg:address":"386 S Tustin St",
    "sg:city":"Orange",
    "sg:classifiers":[
        {
            "category":"Shopping",
            "subcategory":"Crafts & Fabrics",
            "type":"Retail Goods"
        }
    ],
    "sg:phone":"+1 714 997 8823",
    "sg:postcode":"92866",
    "sg:province":"CA",
    "sg:tags":[
        "department",
        "sewing",
        "store"
    ],
    "wof:name":"Willys Needleworks",
    "wof:placetype":"venue"
},
  "geometry": {"coordinates":[-117.835807,33.783007],"type":"Point"}
}