{
  "type": "Feature",
  "properties": {
    "addr:full":"400 Moffett Blvd Mountain View CA 94043",
    "addr:housenumber":"400",
    "addr:postcode":"94043",
    "addr:street":"Moffett Blvd",
    "iso:country":"US",
    "sg:address":"400 Moffett Blvd",
    "sg:city":"Mountain View",
    "sg:classifiers":[
        {
            "category":"Retail",
            "subcategory":"Laundry & Dry Cleaning",
            "type":"Services"
        }
    ],
    "sg:phone":"+1 650 961 4941",
    "sg:postcode":"94043",
    "sg:province":"CA",
    "sg:tags":[
        "cleaners"
    ],
    "wof:name":"Gold Star Cleaners",
    "wof:placetype":"venue"
},
  "geometry": {"coordinates":[-122.07492999999999,37.39901],"type":"Point"}
}