{
  "type": "Feature",
  "properties": {
    "addr:full":"28731 Los Alisos Boulevard Mission Viejo CA 92692",
    "addr:housenumber":"28731",
    "addr:postcode":"92692",
    "addr:street":"Los Alisos Boulevard",
    "iso:country":"US",
    "sg:address":"28731 Los Alisos Boulevard",
    "sg:city":"Mission Viejo",
    "sg:classifiers":[
        {
            "category":"Retail",
            "subcategory":"Laundry & Dry Cleaning",
            "type":"Services"
        }
    ],
    "sg:phone":"+1 949 458 3428",
    "sg:postcode":"92692",
    "sg:province":"CA",
    "wof:name":"Angel's Cleaners",
    "wof:placetype":"venue"
},
  "geometry": {"coordinates":[-117.632569,33.656066],"type":"Point"}
}