{
  "type": "Feature",
  "properties": {
    "addr:full":"18850 Brickell Way Castro Valley CA 94546",
    "addr:housenumber":"18850",
    "addr:postcode":"94546",
    "addr:street":"Brickell Way",
    "iso:country":"US",
    "sg:address":"18850 Brickell Way",
    "sg:city":"Castro Valley",
    "sg:classifiers":[
        {
            "category":"Building & Trades",
            "subcategory":"Construction",
            "type":"Services"
        }
    ],
    "sg:phone":"+1 510 247 1496",
    "sg:postcode":"94546",
    "sg:province":"CA",
    "sg:tags":[
        "contractor"
    ],
    "wof:name":"D H Hunt Construction",
    "wof:placetype":"venue"
},
  "geometry": {"coordinates":[-122.068586,37.708225],"type":"Point"}
}