{
  "type": "Feature",
  "properties": {
    "addr:full":"1366 N Carolan Avenue Burlingame CA 94010",
    "addr:housenumber":"1366",
    "addr:postcode":"94010",
    "addr:street":"N Carolan Avenue",
    "iso:country":"US",
    "sg:address":"1366 N Carolan Avenue",
    "sg:city":"Burlingame",
    "sg:classifiers":[
        {
            "category":"Retail",
            "subcategory":"Auto Repair",
            "type":"Services"
        }
    ],
    "sg:phone":"+1 650 343 8223",
    "sg:postcode":"94010",
    "sg:province":"CA",
    "wof:name":"Carolan Auto Perform",
    "wof:placetype":"venue"
},
  "geometry": {"coordinates":[-122.36747699999999,37.590694],"type":"Point"}
}