{
  "type": "Feature",
  "properties": {
    "addr:full":"4040 Campbell Rd. Suite 100 Menlo Park CA 94025",
    "addr:housenumber":"4040",
    "addr:postcode":"94025",
    "addr:street":"Campbell Rd. Suite 100",
    "iso:country":"US",
    "sg:address":"4040 Campbell Rd. Suite 100",
    "sg:city":"Menlo Park",
    "sg:classifiers":[
        {
            "category":"Professional",
            "subcategory":"Computer Services",
            "type":"Services"
        }
    ],
    "sg:phone":"+1 650 561 8200",
    "sg:postcode":"94025",
    "sg:province":"CA",
    "sg:tags":[
        "data-center",
        "data-center-infrastructure-management",
        "dcim",
        "green-computing",
        "green-it",
        "green-tech",
        "clean--tech",
        "data-center-cooling",
        "data-center-power",
        "data-center-management"
    ],
    "sg:website":"http://www.nlyte.com",
    "wof:name":"nlyte Software",
    "wof:placetype":"venue"
},
  "geometry": {"coordinates":[-122.180215,37.480026],"type":"Point"}
}