{
  "type": "Feature",
  "properties": {
    "iso:country":"US",
    "sg:address":"915 L St Ste C",
    "sg:city":"Sacramento",
    "sg:classifiers":[
        {
            "category":"Arts & Performance",
            "subcategory":"Arts Center",
            "type":"Entertainment"
        }
    ],
    "sg:phone":"+1 916 436 7942",
    "sg:postcode":"95814",
    "sg:province":"CA",
    "wof:name":"The Venidici Group",
    "wof:placetype":"venue"
},
  "geometry": {"coordinates":[-121.49502,38.578619],"type":"Point"}
}