{
  "type": "Feature",
  "properties": {
    "iso:country":"US",
    "sg:address":"21021 Ventura Blvd",
    "sg:city":"Woodland Hills",
    "sg:classifiers":[
        {
            "category":"Arts & Performance",
            "subcategory":"Theater",
            "type":"Entertainment"
        }
    ],
    "sg:phone":"+1 818 593 2130",
    "sg:postcode":"91364",
    "sg:province":"CA",
    "sg:tags":[
        "television",
        "program",
        "producer"
    ],
    "wof:name":"RWI Enterprises",
    "wof:placetype":"venue"
},
  "geometry": {"coordinates":[-118.592432,34.166914],"type":"Point"}
}