{
  "type": "Feature",
  "properties": {
    "iso:country":"US",
    "sg:address":"900 Mountain Ranch Rd",
    "sg:city":"San Andreas",
    "sg:classifiers":[
        {
            "category":"Education",
            "subcategory":"Vocational School",
            "type":"Public Place"
        }
    ],
    "sg:phone":"+1 209 754 4122",
    "sg:postcode":"95249",
    "sg:province":"CA",
    "sg:tags":[
        "nurse"
    ],
    "wof:name":"Avalon Training Ctr",
    "wof:placetype":"venue"
},
  "geometry": {"coordinates":[-120.669315,38.19121],"type":"Point"}
}