{
  "type": "Feature",
  "properties": {
    "iso:country":"US",
    "sg:address":"38703 Larkin Ave",
    "sg:city":"Palmdale",
    "sg:classifiers":[
        {
            "category":"Personal",
            "subcategory":"Beauty Salon",
            "type":"Services"
        }
    ],
    "sg:phone":"+1 661 267 2307",
    "sg:postcode":"93550",
    "sg:province":"CA",
    "wof:name":"T Braids",
    "wof:placetype":"venue"
},
  "geometry": {"coordinates":[-118.122012,34.585704],"type":"Point"}
}