{
  "type": "Feature",
  "properties": {
    "addr:full":"3450 Palmer Dr Cameron Park CA 95682",
    "addr:housenumber":"3450",
    "addr:postcode":"95682",
    "addr:street":"Palmer Dr",
    "iso:country":"US",
    "sg:address":"3450 Palmer Dr",
    "sg:city":"Cameron Park",
    "sg:classifiers":[
        {
            "category":"Retail",
            "subcategory":"Laundry & Dry Cleaning",
            "type":"Services"
        }
    ],
    "sg:phone":"+1 530 676 8222",
    "sg:postcode":"95682",
    "sg:province":"CA",
    "sg:tags":[
        "cleaners"
    ],
    "wof:name":"Pressing Edge",
    "wof:placetype":"venue"
},
  "geometry": {"coordinates":[-120.962315,38.660688],"type":"Point"}
}