{
  "type": "Feature",
  "properties": {
    "iso:country":"US",
    "sg:address":"3435 Camino Del Rio S Ste 115",
    "sg:city":"San Diego",
    "sg:classifiers":[
        {
            "category":"Shopping",
            "subcategory":"Florist",
            "type":"Retail Goods"
        }
    ],
    "sg:phone":"+1 619 283 4432",
    "sg:postcode":"92108",
    "sg:province":"CA",
    "wof:name":"Dos Gringos Inc",
    "wof:placetype":"venue"
},
  "geometry": {"coordinates":[-117.119755,32.776959],"type":"Point"}
}