{
  "type": "Feature",
  "properties": {
    "iso:country":"US",
    "sg:address":"23161 Ventura Blvd",
    "sg:city":"Woodland Hills",
    "sg:classifiers":[
        {
            "category":"Health Services",
            "subcategory":"Clinic",
            "type":"Services"
        }
    ],
    "sg:phone":"+1 818 876 0175",
    "sg:postcode":"91364",
    "sg:province":"CA",
    "wof:name":"Tarazana Treatment Ctr",
    "wof:placetype":"venue"
},
  "geometry": {"coordinates":[-118.629573,34.163585],"type":"Point"}
}