{
  "type": "Feature",
  "properties": {
    "iso:country":"US",
    "sg:address":"3118 Wilshire Blvd",
    "sg:city":"Santa Monica",
    "sg:classifiers":[
        {
            "category":"Wholesale",
            "subcategory":"Dairy",
            "type":"Manufacturing & Wholesale Goods"
        }
    ],
    "sg:phone":"+1 310 829 4948",
    "sg:postcode":"90403",
    "sg:province":"CA",
    "sg:tags":[
        "distributor",
        "product"
    ],
    "wof:name":"North Valley Distribution Co",
    "wof:placetype":"venue"
},
  "geometry": {"coordinates":[-118.472387,34.039982],"type":"Point"}
}