{
  "type": "Feature",
  "properties": {
    "iso:country":"US",
    "sg:address":"19357 Londelius St",
    "sg:city":"Northridge",
    "sg:classifiers":[
        {
            "category":"Travel",
            "subcategory":"Travel Agent",
            "type":"Entertainment"
        }
    ],
    "sg:phone":"+1 818 717 8591",
    "sg:postcode":"91324",
    "sg:province":"CA",
    "sg:tags":[
        "agency",
        "bureau"
    ],
    "sg:website":"www.cheapseatstravel.com",
    "wof:name":"Cheap Seats Travel",
    "wof:placetype":"venue"
},
  "geometry": {"coordinates":[-118.556912,34.229943],"type":"Point"}
}