{
  "type": "Feature",
  "properties": {
    "addr:full":"4011 Idaho St San Diego CA 92104",
    "addr:housenumber":"4011",
    "addr:postcode":"92104",
    "addr:street":"Idaho St",
    "iso:country":"US",
    "sg:address":"4011 Idaho St",
    "sg:city":"San Diego",
    "sg:classifiers":[
        {
            "category":"Manufacturing",
            "subcategory":"Printing",
            "type":"Manufacturing & Wholesale Goods"
        }
    ],
    "sg:phone":"+1 619 692 6943",
    "sg:postcode":"92104",
    "sg:province":"CA",
    "sg:tags":[
        "cards",
        "business"
    ],
    "wof:name":"Bizcard-Cd Electronic Bus Card",
    "wof:placetype":"venue"
},
  "geometry": {"coordinates":[-117.133769,32.752011],"type":"Point"}
}