{
  "type": "Feature",
  "properties": {
    "addr:full":"150 Deodar Ln Bradbury CA 91008",
    "addr:housenumber":"150",
    "addr:postcode":"91008",
    "addr:street":"Deodar Ln",
    "iso:country":"US",
    "sg:address":"150 Deodar Ln",
    "sg:city":"Bradbury",
    "sg:classifiers":[
        {
            "category":"Professional",
            "subcategory":"Business Services",
            "type":"Services"
        }
    ],
    "sg:phone":"+1 626 625 8649",
    "sg:postcode":"91008",
    "sg:province":"CA",
    "sg:tags":[
        "organizing",
        "services-household"
    ],
    "wof:name":"Mzr Management",
    "wof:placetype":"venue"
},
  "geometry": {"coordinates":[-117.98165899999999,34.151594],"type":"Point"}
}