{
  "type": "Feature",
  "properties": {
    "addr:full":"400 Newport Center Dr Newport Beach CA 92660",
    "addr:housenumber":"400",
    "addr:postcode":"92660",
    "addr:street":"Newport Center Dr",
    "iso:country":"US",
    "sg:address":"400 Newport Center Dr",
    "sg:city":"Newport Beach",
    "sg:classifiers":[
        {
            "category":"Health Services",
            "subcategory":"Doctor",
            "type":"Services"
        }
    ],
    "sg:phone":"+1 949 760 1051",
    "sg:postcode":"92660",
    "sg:province":"CA",
    "sg:tags":[
        "dentist"
    ],
    "wof:name":"Carolyn Light, DDS",
    "wof:placetype":"venue"
},
  "geometry": {"coordinates":[-117.872489,33.614213],"type":"Point"}
}