{
  "type": "Feature",
  "properties": {
    "iso:country":"US",
    "sg:address":"Katherine Delmar Burke School 7070 California St",
    "sg:city":"San Francisco",
    "sg:classifiers":[
        {
            "category":"Education",
            "subcategory":"School",
            "type":"Public Place"
        },
        {
            "category":"Recreation",
            "type":"Entertainment"
        }
    ],
    "sg:phone":"+1 800 854 3684",
    "sg:postcode":"94121",
    "sg:province":"CA",
    "sg:tags":[
        "summer",
        "camp"
    ],
    "sg:website":"www.galileo-learning.com/Camp-Ga...",
    "wof:name":"Camp Galileo",
    "wof:placetype":"venue"
},
  "geometry": {"coordinates":[-122.493273,37.783519],"type":"Point"}
}