{
  "type": "Feature",
  "properties": {
    "iso:country":"US",
    "sg:address":"18640 Collins St Apt 204",
    "sg:city":"Tarzana",
    "sg:classifiers":[
        {
            "category":"Professional",
            "subcategory":"Art Services",
            "type":"Services"
        }
    ],
    "sg:phone":"+1 818 345 5037",
    "sg:postcode":"91356",
    "sg:province":"CA",
    "sg:tags":[
        "designer",
        "display",
        "producer"
    ],
    "wof:name":"Solo Perception Designs",
    "wof:placetype":"venue"
},
  "geometry": {"coordinates":[-118.539355,34.1745],"type":"Point"}
}