{
  "type": "Feature",
  "properties": {
    "addr:full":"100 Bush St San Francisco CA 94104",
    "addr:housenumber":"100",
    "addr:postcode":"94104",
    "addr:street":"Bush St",
    "iso:country":"US",
    "sg:address":"100 Bush St",
    "sg:city":"San Francisco",
    "sg:classifiers":[
        {
            "category":"Insurance",
            "subcategory":"Insurance Agent",
            "type":"Services"
        }
    ],
    "sg:phone":"+1 415 391 9988",
    "sg:postcode":"94104",
    "sg:province":"CA",
    "wof:name":"Allstate Insurance",
    "wof:placetype":"venue"
},
  "geometry": {"coordinates":[-122.400744,37.791177],"type":"Point"}
}