{
  "type": "Feature",
  "properties": {
    "iso:country":"US",
    "sg:address":"2174 Main St",
    "sg:city":"Morro Bay",
    "sg:classifiers":[
        {
            "category":"Professional",
            "type":"Services"
        }
    ],
    "sg:phone":"+1 805 772 9054",
    "sg:postcode":"93442",
    "sg:province":"CA",
    "wof:name":"Land & Sea Graphic Apparel",
    "wof:placetype":"venue"
},
  "geometry": {"coordinates":[-120.856748,35.384666],"type":"Point"}
}