{
  "type": "Feature",
  "properties": {
    "iso:country":"US",
    "sg:address":"4221 Gertrude St",
    "sg:city":"Simi Valley",
    "sg:classifiers":[
        {
            "category":"Professional",
            "subcategory":"Management & Consulting",
            "type":"Services"
        }
    ],
    "sg:phone":"+1 805 527 7321",
    "sg:postcode":"93063",
    "sg:province":"CA",
    "sg:tags":[
        "consultant",
        "business"
    ],
    "wof:name":"Ray KIRK Consulting",
    "wof:placetype":"venue"
},
  "geometry": {"coordinates":[-118.713047,34.274055],"type":"Point"}
}