{
  "type": "Feature",
  "properties": {
    "addr:full":"6969 Brockton Ave Riverside CA 92506",
    "addr:housenumber":"6969",
    "addr:postcode":"92506",
    "addr:street":"Brockton Ave",
    "iso:country":"US",
    "sg:address":"6969 Brockton Ave",
    "sg:city":"Riverside",
    "sg:classifiers":[
        {
            "category":"Personal",
            "subcategory":"Tanning Parlor",
            "type":"Services"
        }
    ],
    "sg:phone":"+1 951 788 4880",
    "sg:postcode":"92506",
    "sg:province":"CA",
    "sg:tags":[
        "salon"
    ],
    "wof:name":"Hawaiin Paradise Salon",
    "wof:placetype":"venue"
},
  "geometry": {"coordinates":[-117.39683599999999,33.947253],"type":"Point"}
}