{
  "type": "Feature",
  "properties": {
    "addr:full":"15215 Hesperian Blvd San Leandro CA 94578",
    "addr:housenumber":"15215",
    "addr:postcode":"94578",
    "addr:street":"Hesperian Blvd",
    "iso:country":"US",
    "sg:address":"15215 Hesperian Blvd",
    "sg:city":"San Leandro",
    "sg:classifiers":[
        {
            "category":"Personal",
            "subcategory":"Beauty Salon",
            "type":"Services"
        }
    ],
    "sg:phone":"+1 510 276 4955",
    "sg:postcode":"94578",
    "sg:province":"CA",
    "sg:tags":[
        "nail",
        "manicuring"
    ],
    "sg:website":"www.seoulbeautysalon.com",
    "wof:name":"Seoul Beauty Salon",
    "wof:placetype":"venue"
},
  "geometry": {"coordinates":[-122.129997,37.698299],"type":"Point"}
}