{
  "type": "Feature",
  "properties": {
    "addr:full":"1430 34th St Emeryville CA 94608",
    "addr:housenumber":"1430",
    "addr:postcode":"94608",
    "addr:street":"34Th St",
    "iso:country":"US",
    "sg:address":"1430 34th St",
    "sg:city":"Emeryville",
    "sg:classifiers":[
        {
            "category":"Building & Trades",
            "subcategory":"Construction",
            "type":"Services"
        }
    ],
    "sg:phone":"+1 510 547 2722",
    "sg:postcode":"94608",
    "sg:province":"CA",
    "sg:tags":[
        "contractor"
    ],
    "wof:name":"J K & Assoc Construction Inc",
    "wof:placetype":"venue"
},
  "geometry": {"coordinates":[-122.28467499999999,37.825886],"type":"Point"}
}