{
  "type": "Feature",
  "properties": {
    "iso:country":"US",
    "sg:address":"11686 Sheldon St",
    "sg:city":"Sun Valley",
    "sg:classifiers":[
        {
            "category":"Building & Trades",
            "subcategory":"Construction",
            "type":"Services"
        }
    ],
    "sg:phone":"+1 818 504 9142",
    "sg:postcode":"91352",
    "sg:province":"CA",
    "sg:tags":[
        "material",
        "contractor"
    ],
    "wof:name":"Sebastian Marble Co",
    "wof:placetype":"venue"
},
  "geometry": {"coordinates":[-118.390767,34.241751],"type":"Point"}
}