{
  "type": "Feature",
  "properties": {
    "addr:full":"106 S Main St Bishop CA 93514",
    "addr:housenumber":"106",
    "addr:postcode":"93514",
    "addr:street":"S Main St",
    "iso:country":"US",
    "sg:address":"106 S Main St",
    "sg:city":"Bishop",
    "sg:classifiers":[
        {
            "category":"Shopping",
            "type":"Retail Goods"
        }
    ],
    "sg:phone":"+1 760 873 7700",
    "sg:postcode":"93514",
    "sg:province":"CA",
    "sg:tags":[
        "art",
        "gallery",
        "dealer"
    ],
    "sg:website":"www.mountainlight.com",
    "wof:name":"Mountain Light Photography",
    "wof:placetype":"venue"
},
  "geometry": {"coordinates":[-118.395207,37.361337],"type":"Point"}
}