{
  "type": "Feature",
  "properties": {
    "addr:full":"5037 E Montclair Plaza Ln Montclair CA 91763",
    "addr:housenumber":"5037",
    "addr:postcode":"91763",
    "addr:street":"E Montclair Plaza Ln",
    "iso:country":"US",
    "sg:address":"5037 E Montclair Plaza Ln",
    "sg:city":"Montclair",
    "sg:classifiers":[
        {
            "category":"Shopping",
            "subcategory":"Clothing, Apparel, & Fashions",
            "type":"Retail Goods"
        }
    ],
    "sg:phone":"+1 909 626 0614",
    "sg:postcode":"91763",
    "sg:province":"CA",
    "wof:name":"Lerner New York",
    "wof:placetype":"venue"
},
  "geometry": {"coordinates":[-117.69489799999999,34.087182],"type":"Point"}
}