{
  "type": "Feature",
  "properties": {
    "iso:country":"US",
    "sg:address":"90 Gate 5 Rd",
    "sg:city":"Sausalito",
    "sg:classifiers":[
        {
            "category":"Retail",
            "subcategory":"Auto Repair",
            "type":"Services"
        }
    ],
    "sg:phone":"+1 415 332 2778",
    "sg:postcode":"94965",
    "sg:province":"CA",
    "sg:tags":[
        "repairing",
        "automobile"
    ],
    "wof:name":"Sun Automotive",
    "wof:placetype":"venue"
},
  "geometry": {"coordinates":[-122.501867,37.870923],"type":"Point"}
}